{
  "type": "Feature",
  "properties": {
    "iso:country":"US",
    "sg:address":"366 Rte 68",
    "sg:city":"Columbus",
    "sg:classifiers":[
        {
            "category":"Building & Trades",
            "subcategory":"Construction",
            "type":"Services"
        }
    ],
    "sg:phone":"+1 609 298 9688",
    "sg:postcode":"08022",
    "sg:province":"NJ",
    "sg:tags":[
        "house"
    ],
    "wof:name":"I & J Builders Inc",
    "wof:placetype":"venue"
},
  "geometry": {"coordinates":[-74.65276799999999,40.063899],"type":"Point"}
}