{
  "type": "Feature",
  "properties": {
    "addr:full":"680 Broad St Shrewsbury NJ 07702",
    "addr:housenumber":"680",
    "addr:postcode":"07702",
    "addr:street":"Broad St",
    "iso:country":"US",
    "sg:address":"680 Broad St",
    "sg:city":"Shrewsbury",
    "sg:classifiers":[
        {
            "category":"Personal",
            "subcategory":"Barber",
            "type":"Services"
        }
    ],
    "sg:phone":"+1   ",
    "sg:postcode":"07702",
    "sg:province":"NJ",
    "sg:tags":[
        "shop",
        "beauty"
    ],
    "wof:name":"Salon Indigo",
    "wof:placetype":"venue"
},
  "geometry": {"coordinates":[-74.062337,40.329052],"type":"Point"}
}