{
  "type": "Feature",
  "properties": {
    "addr:full":"520 N West Blvd Vineland NJ 08360",
    "addr:housenumber":"520",
    "addr:postcode":"08360",
    "addr:street":"N West Blvd",
    "iso:country":"US",
    "sg:address":"520 N West Blvd",
    "sg:city":"Vineland",
    "sg:classifiers":[
        {
            "category":"Health Services",
            "subcategory":"Clinic",
            "type":"Services"
        }
    ],
    "sg:phone":"+1 856 692 2881",
    "sg:postcode":"08360",
    "sg:province":"NJ",
    "wof:name":"V A Health Screening Clinic",
    "wof:placetype":"venue"
},
  "geometry": {"coordinates":[-75.025767,39.493082],"type":"Point"}
}