{
  "type": "Feature",
  "properties": {
    "addr:full":"406 Main St Fort Lee NJ 07024",
    "addr:housenumber":"406",
    "addr:postcode":"07024",
    "addr:street":"Main St",
    "iso:country":"US",
    "sg:address":"406 Main St",
    "sg:city":"Fort Lee",
    "sg:classifiers":[
        {
            "category":"Real Estate",
            "subcategory":"Real Estate Agent",
            "type":"Services"
        }
    ],
    "sg:phone":"+1 201 592 1988",
    "sg:postcode":"07024",
    "sg:province":"NJ",
    "wof:name":"Winfar Real Estate LLC",
    "wof:placetype":"venue"
},
  "geometry": {"coordinates":[-73.97493299999999,40.853644],"type":"Point"}
}