{
  "type": "Feature",
  "properties": {
    "iso:country":"US",
    "sg:address":"404 E Denver Ave",
    "sg:city":"Wildwood Crest",
    "sg:classifiers":[
        {
            "category":"Travel",
            "subcategory":"Hotels & Motels",
            "type":"Entertainment"
        },
        {
            "category":"Organizations",
            "subcategory":"Community Association",
            "type":"Services"
        }
    ],
    "sg:phone":"+1 609 729 4535",
    "sg:postcode":"08260",
    "sg:province":"NJ",
    "sg:tags":[
        "condo"
    ],
    "sg:website":"www.fourwindsbeachmotel.com",
    "wof:name":"Four Winds Motel",
    "wof:placetype":"venue"
},
  "geometry": {"coordinates":[-74.84271099999999,38.963772],"type":"Point"}
}