{
  "type": "Feature",
  "properties": {
    "addr:full":"370 Atlantic City Blvd Bayville NJ 08721",
    "addr:housenumber":"370",
    "addr:postcode":"08721",
    "addr:street":"Atlantic City Blvd",
    "iso:country":"US",
    "sg:address":"370 Atlantic City Blvd",
    "sg:city":"Bayville",
    "sg:classifiers":[
        {
            "category":"Professional",
            "subcategory":"Art Services",
            "type":"Services"
        }
    ],
    "sg:phone":"+1 732 237 0855",
    "sg:postcode":"08721",
    "sg:province":"NJ",
    "sg:tags":[
        "photographer"
    ],
    "wof:name":"Ocean Photo Pros",
    "wof:placetype":"venue"
},
  "geometry": {"coordinates":[-74.157707,39.917995],"type":"Point"}
}