{
  "type": "Feature",
  "properties": {
    "iso:country":"US",
    "sg:address":"53 Lott Rd",
    "sg:city":"Sussex",
    "sg:classifiers":[
        {
            "category":"Retail",
            "subcategory":"Animal Services",
            "type":"Services"
        }
    ],
    "sg:phone":"+1 973 875 6880",
    "sg:postcode":"07461",
    "sg:province":"NJ",
    "wof:name":"Newton Kennel Club Inc",
    "wof:placetype":"venue"
},
  "geometry": {"coordinates":[-74.573553,41.274574],"type":"Point"}
}