{
  "type": "Feature",
  "properties": {
    "addr:full":"321 Valley Rd Wayne NJ 07470",
    "addr:housenumber":"321",
    "addr:postcode":"07470",
    "addr:street":"Valley Rd",
    "iso:country":"US",
    "sg:address":"321 Valley Rd",
    "sg:city":"Wayne",
    "sg:classifiers":[
        {
            "category":"Food & Beverages",
            "subcategory":"Fruits & Vegetables",
            "type":"Retail Goods"
        }
    ],
    "sg:phone":"+1   ",
    "sg:postcode":"07470",
    "sg:province":"NJ",
    "wof:name":"California Farm Wayne Inc",
    "wof:placetype":"venue"
},
  "geometry": {"coordinates":[-74.233774,40.924733],"type":"Point"}
}