{
  "type": "Feature",
  "properties": {
    "iso:country":"US",
    "sg:address":"510 Palisade Ave",
    "sg:city":"Garfield",
    "sg:classifiers":[
        {
            "category":"Local Transit",
            "type":"Transportation"
        }
    ],
    "sg:phone":"+1 973 772 6228",
    "sg:postcode":"07026",
    "sg:province":"NJ",
    "wof:name":"Ayan Travel Inc",
    "wof:placetype":"venue"
},
  "geometry": {"coordinates":[-74.112403,40.881592],"type":"Point"}
}