{
  "type": "Feature",
  "properties": {
    "iso:country":"US",
    "sg:address":"38 Oak St",
    "sg:city":"Clifton",
    "sg:classifiers":[
        {
            "category":"Home & Garden",
            "subcategory":"Building Materials",
            "type":"Retail Goods"
        }
    ],
    "sg:phone":"+1 973 473 2521",
    "sg:postcode":"07014",
    "sg:province":"NJ",
    "sg:tags":[
        "supply"
    ],
    "wof:name":"Birch Lumber Co",
    "wof:placetype":"venue"
},
  "geometry": {"coordinates":[-74.1315,40.828899],"type":"Point"}
}