{
  "type": "Feature",
  "properties": {
    "iso:country":"US",
    "sg:address":"833 Winton Gait Ln",
    "sg:city":"Franklin Lakes",
    "sg:classifiers":[
        {
            "category":"Government",
            "subcategory":"Office",
            "type":"Public Place"
        }
    ],
    "sg:phone":"+1   ",
    "sg:postcode":"07417",
    "sg:province":"NJ",
    "sg:tags":[
        "transportation",
        "legal"
    ],
    "wof:name":"Karen Diamond Assoc Inc",
    "wof:placetype":"venue"
},
  "geometry": {"coordinates":[-74.20234499999999,41.034572],"type":"Point"}
}