{
  "type": "Feature",
  "properties": {
    "addr:full":"205 Bordentown Tpke Monroe Township NJ 08831",
    "addr:housenumber":"205",
    "addr:postcode":"08831",
    "addr:street":"Bordentown Tpke",
    "iso:country":"US",
    "sg:address":"205 Bordentown Tpke",
    "sg:city":"Monroe Township",
    "sg:classifiers":[
        {
            "category":"Building & Trades",
            "subcategory":"Construction",
            "type":"Services"
        }
    ],
    "sg:phone":"+1 732 521 2664",
    "sg:postcode":"08831",
    "sg:province":"NJ",
    "sg:tags":[
        "excavation",
        "contractor"
    ],
    "wof:name":"Smith Excvtg & Septic Systems",
    "wof:placetype":"venue"
},
  "geometry": {"coordinates":[-74.441001,40.362119],"type":"Point"}
}