{
  "type": "Feature",
  "properties": {
    "addr:full":"248 14th St Jersey City NJ 07310",
    "addr:housenumber":"248",
    "addr:postcode":"07310",
    "addr:street":"14Th St",
    "iso:country":"US",
    "sg:address":"248 14th St",
    "sg:city":"Jersey City",
    "sg:classifiers":[
        {
            "category":"Autos & Motor Vehicles",
            "subcategory":"Fuel & Gas Station",
            "type":"Retail Goods"
        }
    ],
    "sg:phone":"+1 201 386 5888",
    "sg:postcode":"07310",
    "sg:province":"NJ",
    "wof:name":"Yooryou Inc",
    "wof:placetype":"venue"
},
  "geometry": {"coordinates":[-74.043297,40.7323],"type":"Point"}
}