{
  "type": "Feature",
  "properties": {
    "iso:country":"US",
    "sg:address":"107 Christopher Columbus Dr",
    "sg:city":"Jersey City",
    "sg:classifiers":[
        {
            "category":"Personal",
            "subcategory":"Beauty Salon",
            "type":"Services"
        }
    ],
    "sg:phone":"+1 201 395 0045",
    "sg:postcode":"07302",
    "sg:province":"NJ",
    "sg:tags":[
        "hair"
    ],
    "sg:website":"www.shampoojc.com",
    "wof:name":"Shampoo JC Hair Salon",
    "wof:placetype":"venue"
},
  "geometry": {"coordinates":[-74.043339,40.719481],"type":"Point"}
}