{
  "type": "Feature",
  "properties": {
    "iso:country":"US",
    "sg:address":"218 Ave B",
    "sg:city":"Bayonne",
    "sg:classifiers":[
        {
            "category":"Restaurant",
            "type":"Food & Drink"
        }
    ],
    "sg:phone":"+1 201 339 1100",
    "sg:postcode":"07002",
    "sg:province":"NJ",
    "sg:tags":[
        "delicatessen"
    ],
    "wof:name":"Deli Express",
    "wof:placetype":"venue"
},
  "geometry": {"coordinates":[-74.107,40.685068],"type":"Point"}
}