{
  "type": "Feature",
  "properties": {
    "iso:country":"US",
    "sg:address":"1315 E Elizabeth Ave",
    "sg:city":"Linden",
    "sg:classifiers":[
        {
            "category":"Wholesale",
            "subcategory":"Hardware",
            "type":"Manufacturing & Wholesale Goods"
        }
    ],
    "sg:phone":"+1 908 925 8888",
    "sg:postcode":"07036",
    "sg:province":"NJ",
    "sg:tags":[
        "plumbing",
        "fixture",
        "supply"
    ],
    "wof:name":"JAS Inc",
    "wof:placetype":"venue"
},
  "geometry": {"coordinates":[-74.239087,40.643296],"type":"Point"}
}