{
  "type": "Feature",
  "properties": {
    "iso:country":"US",
    "sg:address":"1020 Galloping Hill Rd",
    "sg:city":"Union",
    "sg:classifiers":[
        {
            "category":"Shopping",
            "subcategory":"Optical Goods",
            "type":"Retail Goods"
        }
    ],
    "sg:phone":"+1   ",
    "sg:postcode":"07083",
    "sg:province":"NJ",
    "wof:name":"Vision Association Inc",
    "wof:placetype":"venue"
},
  "geometry": {"coordinates":[-74.26759,40.677082],"type":"Point"}
}