{
  "type": "Feature",
  "properties": {
    "addr:full":"1545 Pennington Rd Trenton NJ 08618",
    "addr:housenumber":"1545",
    "addr:postcode":"08618",
    "addr:street":"Pennington Rd",
    "iso:country":"US",
    "sg:address":"1545 Pennington Rd",
    "sg:city":"Trenton",
    "sg:classifiers":[
        {
            "category":"Organizations",
            "subcategory":"Religious Organization",
            "type":"Services"
        }
    ],
    "sg:phone":"+1 609 882 2860",
    "sg:postcode":"08618",
    "sg:province":"NJ",
    "sg:tags":[
        "church"
    ],
    "sg:website":"www.incarnationchurchewingnj.org",
    "wof:name":"Incarnation Roman Catholic Chr",
    "wof:placetype":"venue"
},
  "geometry": {"coordinates":[-74.77575,40.249887],"type":"Point"}
}