{
  "type": "Feature",
  "properties": {
    "iso:country":"US",
    "sg:address":"39 Waldwick Ave",
    "sg:city":"Waldwick",
    "sg:classifiers":[
        {
            "category":"Government",
            "subcategory":"Fire Station",
            "type":"Public Place"
        }
    ],
    "sg:phone":"+1 201 891 5736",
    "sg:postcode":"07463",
    "sg:province":"NJ",
    "sg:tags":[
        "consultant",
        "protection"
    ],
    "wof:name":"Franklin Lakes, Borough Of Inc",
    "wof:placetype":"venue"
},
  "geometry": {"coordinates":[-74.117154,41.013229],"type":"Point"}
}