{
  "type": "Feature",
  "properties": {
    "iso:country":"US",
    "sg:address":"104 Maple St",
    "sg:city":"Haworth",
    "sg:classifiers":[
        {
            "category":"Building & Trades",
            "subcategory":"Construction",
            "type":"Services"
        }
    ],
    "sg:phone":"+1 201 768 1180",
    "sg:postcode":"07641",
    "sg:province":"NJ",
    "sg:tags":[
        "contractor"
    ],
    "wof:name":"Richard Reduce Bldg Contractor",
    "wof:placetype":"venue"
},
  "geometry": {"coordinates":[-73.993635,40.959744],"type":"Point"}
}