{
  "type": "Feature",
  "properties": {
    "addr:full":"4 Robbins Pkwy Toms River NJ 08753",
    "addr:housenumber":"4",
    "addr:postcode":"08753",
    "addr:street":"Robbins Pkwy",
    "iso:country":"US",
    "sg:address":"4 Robbins Pkwy",
    "sg:city":"Toms River",
    "sg:classifiers":[
        {
            "category":"Professional",
            "subcategory":"Secretarial Services",
            "type":"Services"
        }
    ],
    "sg:phone":"+1   ",
    "sg:postcode":"08753",
    "sg:province":"NJ",
    "sg:tags":[
        "reporting"
    ],
    "wof:name":"Cole Trnscrption Recording Svc",
    "wof:placetype":"venue"
},
  "geometry": {"coordinates":[-74.19660500000001,39.950979],"type":"Point"}
}