{
  "type": "Feature",
  "properties": {
    "iso:country":"US",
    "sg:address":"912 Shore Rd",
    "sg:city":"Beach Haven",
    "sg:classifiers":[
        {
            "category":"Real Estate",
            "subcategory":"Real Estate Agent",
            "type":"Services"
        }
    ],
    "sg:phone":"+1   ",
    "sg:postcode":"08008",
    "sg:province":"NJ",
    "wof:name":"Prestige South LLC",
    "wof:placetype":"venue"
},
  "geometry": {"coordinates":[-74.183854,39.652874],"type":"Point"}
}