{
  "type": "Feature",
  "properties": {
    "iso:country":"US",
    "sg:address":"175 Union Ave",
    "sg:city":"Middlesex",
    "sg:classifiers":[
        {
            "category":"Professional",
            "subcategory":"Business Services",
            "type":"Services"
        }
    ],
    "sg:phone":"+1   ",
    "sg:postcode":"08846",
    "sg:province":"NJ",
    "sg:tags":[
        "personal"
    ],
    "wof:name":"Tarot Card Readings By Sandra",
    "wof:placetype":"venue"
},
  "geometry": {"coordinates":[-74.52211800000001,40.567195],"type":"Point"}
}