{
  "type": "Feature",
  "properties": {
    "addr:full":"640 S Broad St Rm 404 Trenton NJ 08611",
    "addr:housenumber":"640;404",
    "addr:postcode":"08611",
    "addr:street":"S Broad St Rm",
    "iso:country":"US",
    "sg:address":"640 S Broad St Rm 404",
    "sg:city":"Trenton",
    "sg:classifiers":[
        {
            "category":"Organizations",
            "subcategory":"Community Association",
            "type":"Services"
        }
    ],
    "sg:phone":"+1 609 989 6671",
    "sg:postcode":"08611",
    "sg:province":"NJ",
    "sg:tags":[
        "consumers'",
        "cooperative"
    ],
    "sg:website":"http://www.howellfarm.org",
    "wof:name":"Consumer Affairs",
    "wof:placetype":"venue"
},
  "geometry": {"coordinates":[-74.753865,40.20865],"type":"Point"}
}