{
  "type": "Feature",
  "properties": {
    "addr:full":"18 Back Bone Hill Rd Englishtown NJ 07726",
    "addr:housenumber":"18",
    "addr:postcode":"07726",
    "addr:street":"Back Bone Hill Rd",
    "iso:country":"US",
    "sg:address":"18 Back Bone Hill Rd",
    "sg:city":"Englishtown",
    "sg:classifiers":[
        {
            "category":"Professional",
            "subcategory":"Management & Consulting",
            "type":"Services"
        },
        {
            "category":"Wholesale",
            "subcategory":"Groceries",
            "type":"Manufacturing & Wholesale Goods"
        }
    ],
    "sg:phone":"+1 732 577 1431",
    "sg:postcode":"07726",
    "sg:province":"NJ",
    "sg:tags":[
        "equipment",
        "pizza",
        "direct",
        "supply"
    ],
    "wof:name":"L & M Food Products",
    "wof:placetype":"venue"
},
  "geometry": {"coordinates":[-74.393174,40.21455],"type":"Point"}
}