{
  "type": "Feature",
  "properties": {
    "addr:full":"2151 State Rte 50 Woodbine NJ 08270",
    "addr:housenumber":"2151",
    "addr:postcode":"08270",
    "addr:street":"State Rte 50",
    "iso:country":"US",
    "sg:address":"2151 State Rte 50",
    "sg:city":"Woodbine",
    "sg:classifiers":[
        {
            "category":"Shopping",
            "subcategory":"Bicycles & Sporting Goods",
            "type":"Retail Goods"
        }
    ],
    "sg:phone":"+1 609 628 0101",
    "sg:postcode":"08270",
    "sg:province":"NJ",
    "wof:name":"Surf Buggy Ctr",
    "wof:placetype":"venue"
},
  "geometry": {"coordinates":[-74.75396499999999,39.290009],"type":"Point"}
}