{
  "type": "Feature",
  "properties": {
    "addr:full":"909 Liberty St Trenton NJ 08611",
    "addr:housenumber":"909",
    "addr:postcode":"08611",
    "addr:street":"Liberty St",
    "iso:country":"US",
    "sg:address":"909 Liberty St",
    "sg:city":"Trenton",
    "sg:classifiers":[
        {
            "category":"Shopping",
            "subcategory":"Jewelry",
            "type":"Retail Goods"
        }
    ],
    "sg:phone":"+1   ",
    "sg:postcode":"08611",
    "sg:province":"NJ",
    "sg:tags":[
        "used",
        "merchandise"
    ],
    "wof:name":"Liberty Jewelry Buyers",
    "wof:placetype":"venue"
},
  "geometry": {"coordinates":[-74.738722,40.208236],"type":"Point"}
}