{
  "type": "Feature",
  "properties": {
    "addr:full":"598 State St # 606 Perth Amboy NJ 08861",
    "addr:housenumber":"598",
    "addr:postcode":"08861",
    "addr:street":"State St # 606",
    "iso:country":"US",
    "sg:address":"598 State St # 606",
    "sg:city":"Perth Amboy",
    "sg:classifiers":[
        {
            "category":"Banks & Credit Unions",
            "subcategory":"Bank",
            "type":"Services"
        },
        {
            "category":"Banks & Credit Unions",
            "subcategory":"Financial Services",
            "type":"Services"
        }
    ],
    "sg:phone":"+1 732 324 0081",
    "sg:postcode":"08861",
    "sg:province":"NJ",
    "sg:tags":[
        "broker",
        "mortgage"
    ],
    "sg:website":"www.isbnj.com",
    "wof:name":"Investors Savings Bank",
    "wof:placetype":"venue"
},
  "geometry": {"coordinates":[-74.264076,40.519083],"type":"Point"}
}