{
  "type": "Feature",
  "properties": {
    "addr:full":"916 Broadway Bayonne NJ 07002",
    "addr:housenumber":"916",
    "addr:postcode":"07002",
    "addr:street":"Broadway",
    "iso:country":"US",
    "sg:address":"916 Broadway",
    "sg:city":"Bayonne",
    "sg:classifiers":[
        {
            "category":"Insurance",
            "subcategory":"Insurance Agent",
            "type":"Services"
        }
    ],
    "sg:phone":"+1 201 437 0900",
    "sg:postcode":"07002",
    "sg:province":"NJ",
    "wof:name":"Longo Agency Inc",
    "wof:placetype":"venue"
},
  "geometry": {"coordinates":[-74.10547,40.678877],"type":"Point"}
}