{
  "type": "Feature",
  "properties": {
    "iso:country":"US",
    "sg:address":"168 Co Rd 526",
    "sg:city":"Allentown",
    "sg:classifiers":[
        {
            "category":"Professional",
            "subcategory":"Business Services",
            "type":"Services"
        }
    ],
    "sg:phone":"+1 609 259 8635",
    "sg:postcode":"08501",
    "sg:province":"NJ",
    "wof:name":"Andor Technologies",
    "wof:placetype":"venue"
},
  "geometry": {"coordinates":[-74.544805,40.171878],"type":"Point"}
}