{
  "type": "Feature",
  "properties": {
    "addr:full":"905 Oak Tree Rd South Plainfield NJ 07080",
    "addr:housenumber":"905",
    "addr:postcode":"07080",
    "addr:street":"Oak Tree Rd",
    "iso:country":"US",
    "sg:address":"905 Oak Tree Rd",
    "sg:city":"South Plainfield",
    "sg:classifiers":[
        {
            "category":"Banks & Credit Unions",
            "subcategory":"Bank",
            "type":"Services"
        }
    ],
    "sg:phone":"+1 908 754 3600",
    "sg:postcode":"07080",
    "sg:province":"NJ",
    "wof:name":"Wachovia Bank",
    "wof:placetype":"venue"
},
  "geometry": {"coordinates":[-74.38731300000001,40.577281],"type":"Point"}
}