{
  "type": "Feature",
  "properties": {
    "addr:full":"38 1st Ave Denville NJ 07834",
    "addr:housenumber":"38",
    "addr:postcode":"07834",
    "addr:street":"1St Ave",
    "iso:country":"US",
    "sg:address":"38 1st Ave",
    "sg:city":"Denville",
    "sg:classifiers":[
        {
            "category":"Manufacturing",
            "subcategory":"Food",
            "type":"Manufacturing & Wholesale Goods"
        }
    ],
    "sg:phone":"+1 973 625 0595",
    "sg:postcode":"07834",
    "sg:province":"NJ",
    "sg:tags":[
        "corn",
        "chips",
        "potato"
    ],
    "wof:name":"Snack Bar",
    "wof:placetype":"venue"
},
  "geometry": {"coordinates":[-74.476446,40.892361],"type":"Point"}
}