{
  "type": "Feature",
  "properties": {
    "iso:country":"US",
    "sg:address":"1201 Springfield Rd",
    "sg:city":"Union",
    "sg:classifiers":[
        {
            "category":"Autos & Motor Vehicles",
            "subcategory":"Fuel & Gas Station",
            "type":"Retail Goods"
        }
    ],
    "sg:phone":"+1 908 964 3779",
    "sg:postcode":"07083",
    "sg:province":"NJ",
    "wof:name":"J K Singh Corporation",
    "wof:placetype":"venue"
},
  "geometry": {"coordinates":[-74.30284899999999,40.696248],"type":"Point"}
}