{
  "type": "Feature",
  "properties": {
    "iso:country":"US",
    "sg:address":"568 New Brunswick Ave",
    "sg:city":"Fords",
    "sg:classifiers":[
        {
            "category":"Shopping",
            "subcategory":"Florist",
            "type":"Retail Goods"
        }
    ],
    "sg:phone":"+1   ",
    "sg:postcode":"08863",
    "sg:province":"NJ",
    "wof:name":"Forever Flowers",
    "wof:placetype":"venue"
},
  "geometry": {"coordinates":[-74.31452299999999,40.52862],"type":"Point"}
}