{
  "type": "Feature",
  "properties": {
    "addr:full":"3705 Quakerbridge Rd Trenton NJ 08619",
    "addr:housenumber":"3705",
    "addr:postcode":"08619",
    "addr:street":"Quakerbridge Rd",
    "iso:country":"US",
    "sg:address":"3705 Quakerbridge Rd",
    "sg:city":"Trenton",
    "sg:classifiers":[
        {
            "category":"Manufacturing",
            "subcategory":"Tools & Machinery",
            "type":"Manufacturing & Wholesale Goods"
        }
    ],
    "sg:phone":"+1 609 586 2345",
    "sg:postcode":"08619",
    "sg:province":"NJ",
    "sg:tags":[
        "industry",
        "aerospace"
    ],
    "wof:name":"Global Aerospace Systems",
    "wof:placetype":"venue"
},
  "geometry": {"coordinates":[-74.677156,40.259608],"type":"Point"}
}