{
  "type": "Feature",
  "properties": {
    "iso:country":"US",
    "sg:address":"305 Huntington Ct",
    "sg:city":"Absecon",
    "sg:classifiers":[
        {
            "category":"Freight",
            "type":"Transportation"
        }
    ],
    "sg:phone":"+1 609 748 6738",
    "sg:postcode":"08205",
    "sg:province":"NJ",
    "sg:tags":[
        "delivery"
    ],
    "wof:name":"Hot Shot Delivery",
    "wof:placetype":"venue"
},
  "geometry": {"coordinates":[-74.506648,39.453812],"type":"Point"}
}