{
  "type": "Feature",
  "properties": {
    "iso:country":"US",
    "sg:address":"163 E 31st St",
    "sg:city":"Paterson",
    "sg:classifiers":[
        {
            "category":"Utilities",
            "subcategory":"Refuse",
            "type":"Services"
        }
    ],
    "sg:phone":"+1 973 523 6896",
    "sg:postcode":"07514",
    "sg:province":"NJ",
    "sg:tags":[
        "household",
        "waste",
        "collection",
        "removal"
    ],
    "wof:name":"S & M Disposal",
    "wof:placetype":"venue"
},
  "geometry": {"coordinates":[-74.143201,40.920742],"type":"Point"}
}