{
  "type": "Feature",
  "properties": {
    "iso:country":"US",
    "sg:address":"113 US Hwy 46",
    "sg:city":"Parsippany",
    "sg:classifiers":[
        {
            "category":"Utilities",
            "subcategory":"Mobile Phone",
            "type":"Services"
        }
    ],
    "sg:phone":"+1 973 439 5610",
    "sg:postcode":"07054",
    "sg:province":"NJ",
    "sg:tags":[
        "telephone",
        "cellular"
    ],
    "wof:name":"Cellular Plus",
    "wof:placetype":"venue"
},
  "geometry": {"coordinates":[-74.35127799999999,40.857924],"type":"Point"}
}