{
  "type": "Feature",
  "properties": {
    "addr:full":"125 Paterson Ave Little Falls NJ 07424",
    "addr:housenumber":"125",
    "addr:postcode":"07424",
    "addr:street":"Paterson Ave",
    "iso:country":"US",
    "sg:address":"125 Paterson Ave",
    "sg:city":"Little Falls",
    "sg:classifiers":[
        {
            "category":"Communications",
            "subcategory":"Newspaper",
            "type":"Services"
        }
    ],
    "sg:phone":"+1 973 256 1333",
    "sg:postcode":"07424",
    "sg:province":"NJ",
    "sg:tags":[
        "print",
        "medium"
    ],
    "wof:name":"Paperclip Communications",
    "wof:placetype":"venue"
},
  "geometry": {"coordinates":[-74.224098,40.883801],"type":"Point"}
}