{
  "type": "Feature",
  "properties": {
    "addr:full":"1161 Broad St Bloomfield NJ 07003",
    "addr:housenumber":"1161",
    "addr:postcode":"07003",
    "addr:street":"Broad St",
    "iso:country":"US",
    "sg:address":"1161 Broad St",
    "sg:city":"Bloomfield",
    "sg:classifiers":[
        {
            "category":"Professional",
            "subcategory":"Computer Services",
            "type":"Services"
        }
    ],
    "sg:phone":"+1   ",
    "sg:postcode":"07003",
    "sg:province":"NJ",
    "sg:tags":[
        "hardware",
        "security",
        "software"
    ],
    "wof:name":"Xtract-Data",
    "wof:placetype":"venue"
},
  "geometry": {"coordinates":[-74.183339,40.831094],"type":"Point"}
}