{
  "type": "Feature",
  "properties": {
    "addr:full":"32 Hoxey St Paterson NJ 07501",
    "addr:housenumber":"32",
    "addr:postcode":"07501",
    "addr:street":"Hoxey St",
    "iso:country":"US",
    "sg:address":"32 Hoxey St",
    "sg:city":"Paterson",
    "sg:classifiers":[
        {
            "category":"Professional",
            "subcategory":"Business Services",
            "type":"Services"
        }
    ],
    "sg:phone":"+1 973 742 7704",
    "sg:postcode":"07501",
    "sg:province":"NJ",
    "wof:name":"Bioya Recording Studios",
    "wof:placetype":"venue"
},
  "geometry": {"coordinates":[-74.183364,40.910921],"type":"Point"}
}