{
  "type": "Feature",
  "properties": {
    "addr:full":"370 Duncan Ave Jersey City NJ 07306",
    "addr:housenumber":"370",
    "addr:postcode":"07306",
    "addr:street":"Duncan Ave",
    "iso:country":"US",
    "sg:address":"370 Duncan Ave",
    "sg:city":"Jersey City",
    "sg:classifiers":[
        {
            "category":"Autos & Motor Vehicles",
            "subcategory":"Automobile Sales",
            "type":"Retail Goods"
        }
    ],
    "sg:phone":"+1   ",
    "sg:postcode":"07306",
    "sg:province":"NJ",
    "sg:tags":[
        "supply"
    ],
    "wof:name":"G & A Equipment",
    "wof:placetype":"venue"
},
  "geometry": {"coordinates":[-74.085584,40.730727],"type":"Point"}
}