{
  "type": "Feature",
  "properties": {
    "iso:country":"US",
    "sg:address":"121 Hillcrest Ave",
    "sg:city":"Lawrenceville",
    "sg:classifiers":[
        {
            "category":"Organizations",
            "subcategory":"Religious Organization",
            "type":"Services"
        }
    ],
    "sg:phone":"+1 609 882 5136",
    "sg:postcode":"08648",
    "sg:province":"NJ",
    "sg:tags":[
        "church"
    ],
    "wof:name":"First Baptist Eggerts-Crossing",
    "wof:placetype":"venue"
},
  "geometry": {"coordinates":[-74.752252,40.271543],"type":"Point"}
}