{
  "type": "Feature",
  "properties": {
    "iso:country":"US",
    "sg:address":"7 Roberts St",
    "sg:city":"Kendall Park",
    "sg:classifiers":[
        {
            "category":"Freight",
            "type":"Transportation"
        }
    ],
    "sg:phone":"+1 732 422 0644",
    "sg:postcode":"08824",
    "sg:province":"NJ",
    "sg:tags":[
        "operator",
        "local",
        "trucking"
    ],
    "wof:name":"Quality Produce",
    "wof:placetype":"venue"
},
  "geometry": {"coordinates":[-74.551511,40.429363],"type":"Point"}
}