{
  "type": "Feature",
  "properties": {
    "iso:country":"US",
    "sg:address":"325 Columbia Tpke",
    "sg:city":"Florham Park",
    "sg:classifiers":[
        {
            "category":"Professional",
            "subcategory":"Management & Consulting",
            "type":"Services"
        },
        {
            "category":"Professional",
            "subcategory":"Employment Agencies",
            "type":"Services"
        }
    ],
    "sg:phone":"+1 973 822 3611",
    "sg:postcode":"07932",
    "sg:province":"NJ",
    "sg:tags":[
        "consultant",
        "resource",
        "help",
        "human",
        "supply"
    ],
    "sg:website":"www.administaff.com",
    "wof:name":"Administaff Inc",
    "wof:placetype":"venue"
},
  "geometry": {"coordinates":[-74.41770099999999,40.790989],"type":"Point"}
}