{
  "type": "Feature",
  "properties": {
    "addr:full":"1608 Lemoine Ave Fort Lee NJ 07024",
    "addr:housenumber":"1608",
    "addr:postcode":"07024",
    "addr:street":"Lemoine Ave",
    "iso:country":"US",
    "sg:address":"1608 Lemoine Ave",
    "sg:city":"Fort Lee",
    "sg:classifiers":[
        {
            "category":"Health Services",
            "subcategory":"Medical Lab",
            "type":"Services"
        }
    ],
    "sg:phone":"+1 201 302 0707",
    "sg:postcode":"07024",
    "sg:province":"NJ",
    "sg:tags":[
        "laboratory",
        "dental"
    ],
    "wof:name":"Dr Yun Ortho Clinic",
    "wof:placetype":"venue"
},
  "geometry": {"coordinates":[-73.970314,40.849854],"type":"Point"}
}