{
  "type": "Feature",
  "properties": {
    "addr:full":"273 E Cedar Ln Teaneck NJ 07666",
    "addr:housenumber":"273",
    "addr:postcode":"07666",
    "addr:street":"E Cedar Ln",
    "iso:country":"US",
    "sg:address":"273 E Cedar Ln",
    "sg:city":"Teaneck",
    "sg:classifiers":[
        {
            "category":"Professional",
            "type":"Services"
        }
    ],
    "sg:phone":"+1 201 261 6585",
    "sg:postcode":"07666",
    "sg:province":"NJ",
    "sg:tags":[
        "caterer"
    ],
    "sg:website":"www.shortroundscatering.com",
    "wof:name":"Shortrounds Catering",
    "wof:placetype":"venue"
},
  "geometry": {"coordinates":[-73.997755,40.881391],"type":"Point"}
}