{
  "type": "Feature",
  "properties": {
    "addr:full":"1601 Osprey Ct Point Pleasant Beach NJ 08742",
    "addr:housenumber":"1601",
    "addr:postcode":"08742",
    "addr:street":"Osprey Ct",
    "iso:country":"US",
    "sg:address":"1601 Osprey Ct",
    "sg:city":"Point Pleasant Beach",
    "sg:classifiers":[
        {
            "category":"Home & Garden",
            "subcategory":"Carpets & Floor Coverings",
            "type":"Retail Goods"
        }
    ],
    "sg:phone":"+1   ",
    "sg:postcode":"08742",
    "sg:province":"NJ",
    "wof:name":"Builders Flooring Center",
    "wof:placetype":"venue"
},
  "geometry": {"coordinates":[-74.07625,40.063306],"type":"Point"}
}