{
  "type": "Feature",
  "properties": {
    "iso:country":"US",
    "sg:address":"1824 Shore Blvd",
    "sg:city":"Point Pleasant Beach",
    "sg:classifiers":[
        {
            "category":"Building & Trades",
            "subcategory":"Plumbing",
            "type":"Services"
        }
    ],
    "sg:phone":"+1 732 295 0294",
    "sg:postcode":"08742",
    "sg:province":"NJ",
    "sg:tags":[
        "cooling",
        "heating"
    ],
    "wof:name":"American Mechanical",
    "wof:placetype":"venue"
},
  "geometry": {"coordinates":[-74.05582800000001,40.067096],"type":"Point"}
}