{
  "type": "Feature",
  "properties": {
    "addr:full":"411 Oak Rd Bridgeton NJ 08302",
    "addr:housenumber":"411",
    "addr:postcode":"08302",
    "addr:street":"Oak Rd",
    "iso:country":"US",
    "sg:address":"411 Oak Rd",
    "sg:city":"Bridgeton",
    "sg:classifiers":[
        {
            "category":"Manufacturing",
            "subcategory":"Toys & Sporting Goods",
            "type":"Manufacturing & Wholesale Goods"
        }
    ],
    "sg:phone":"+1 856 455 0502",
    "sg:postcode":"08302",
    "sg:province":"NJ",
    "sg:tags":[
        "game",
        "vehicle"
    ],
    "wof:name":"Sparethyme Creations",
    "wof:placetype":"venue"
},
  "geometry": {"coordinates":[-75.31072,39.459369],"type":"Point"}
}