{
  "type": "Feature",
  "properties": {
    "addr:full":"64 Harley Blvd Bayville NJ 08721",
    "addr:housenumber":"64",
    "addr:postcode":"08721",
    "addr:street":"Harley Blvd",
    "iso:country":"US",
    "sg:address":"64 Harley Blvd",
    "sg:city":"Bayville",
    "sg:classifiers":[
        {
            "category":"Building & Trades",
            "subcategory":"Plumbing",
            "type":"Services"
        }
    ],
    "sg:phone":"+1 732 269 4845",
    "sg:postcode":"08721",
    "sg:province":"NJ",
    "sg:tags":[
        "contractor"
    ],
    "wof:name":"Ef Ruthzler & Sons Heating &",
    "wof:placetype":"venue"
},
  "geometry": {"coordinates":[-74.16110399999999,39.875707],"type":"Point"}
}