{
  "type": "Feature",
  "properties": {
    "iso:country":"US",
    "sg:address":"240 Martin Luther King Jr Blvd",
    "sg:city":"Newark",
    "sg:classifiers":[
        {
            "category":"Shopping",
            "subcategory":"Computers & Home Electronics",
            "type":"Retail Goods"
        }
    ],
    "sg:phone":"+1 973 639 0606",
    "sg:postcode":"07102",
    "sg:province":"NJ",
    "sg:tags":[
        "software"
    ],
    "wof:name":"Adeena",
    "wof:placetype":"venue"
},
  "geometry": {"coordinates":[-74.174606,40.746207],"type":"Point"}
}