{
  "type": "Feature",
  "properties": {
    "addr:full":"249 Somerset St New Brunswick NJ 08901",
    "addr:housenumber":"249",
    "addr:postcode":"08901",
    "addr:street":"Somerset St",
    "iso:country":"US",
    "sg:address":"249 Somerset St",
    "sg:city":"New Brunswick",
    "sg:classifiers":[
        {
            "category":"Food & Beverages",
            "subcategory":"Groceries & Convenience Stores",
            "type":"Retail Goods"
        }
    ],
    "sg:phone":"+1 732 249 4279",
    "sg:postcode":"08901",
    "sg:province":"NJ",
    "sg:tags":[
        "grocer"
    ],
    "wof:name":"M & M Grocery",
    "wof:placetype":"venue"
},
  "geometry": {"coordinates":[-74.453665,40.494203],"type":"Point"}
}