{
  "type": "Feature",
  "properties": {
    "iso:country":"US",
    "sg:address":"191 Woodbine Cir",
    "sg:city":"New Providence",
    "sg:classifiers":[
        {
            "category":"Home & Garden",
            "subcategory":"Furniture",
            "type":"Retail Goods"
        }
    ],
    "sg:phone":"+1 908 508 1500",
    "sg:postcode":"07974",
    "sg:province":"NJ",
    "sg:tags":[
        "store"
    ],
    "wof:name":"Boyer Furniture Service",
    "wof:placetype":"venue"
},
  "geometry": {"coordinates":[-74.400002,40.7164],"type":"Point"}
}