{
  "type": "Feature",
  "properties": {
    "addr:full":"97 Tracey Pl Englewood NJ 07631",
    "addr:housenumber":"97",
    "addr:postcode":"07631",
    "addr:street":"Tracey Pl",
    "iso:country":"US",
    "sg:address":"97 Tracey Pl",
    "sg:city":"Englewood",
    "sg:classifiers":[
        {
            "category":"Personal",
            "type":"Services"
        }
    ],
    "sg:phone":"+1 201 541 2425",
    "sg:postcode":"07631",
    "sg:province":"NJ",
    "sg:tags":[
        "electrolysis"
    ],
    "wof:name":"Electrolysis By Rosine",
    "wof:placetype":"venue"
},
  "geometry": {"coordinates":[-73.973471,40.890797],"type":"Point"}
}