{
  "type": "Feature",
  "properties": {
    "addr:full":"69 Crestview Dr Clinton NJ 08848",
    "addr:housenumber":"69",
    "addr:postcode":"08848",
    "addr:street":"Crestview Dr",
    "iso:country":"US",
    "sg:address":"69 Crestview Dr",
    "sg:city":"Clinton",
    "sg:classifiers":[
        {
            "category":"Building & Trades",
            "subcategory":"Cleaning & Sanitation",
            "type":"Services"
        }
    ],
    "sg:phone":"+1 908 638 4135",
    "sg:postcode":"08848",
    "sg:province":"NJ",
    "sg:tags":[
        "window"
    ],
    "wof:name":"Bound Brook Window Cleaning",
    "wof:placetype":"venue"
},
  "geometry": {"coordinates":[-75.073751,40.565378],"type":"Point"}
}