{
  "type": "Feature",
  "properties": {
    "addr:full":"791 US Hwy 22 North Plainfield NJ 07060",
    "addr:housenumber":"791",
    "addr:postcode":"07060",
    "addr:street":"Us Hwy 22",
    "iso:country":"US",
    "sg:address":"791 US Hwy 22",
    "sg:city":"North Plainfield",
    "sg:classifiers":[
        {
            "category":"Education",
            "subcategory":"Dance Studio",
            "type":"Public Place"
        }
    ],
    "sg:phone":"+1 908 791 9494",
    "sg:postcode":"07060",
    "sg:province":"NJ",
    "sg:tags":[
        "instruction",
        "dancing"
    ],
    "wof:name":"Broadway Dance Theatre",
    "wof:placetype":"venue"
},
  "geometry": {"coordinates":[-74.440757,40.625442],"type":"Point"}
}