{
  "type": "Feature",
  "properties": {
    "addr:full":"310 95th St Stone Harbor NJ 08247",
    "addr:housenumber":"310",
    "addr:postcode":"08247",
    "addr:street":"95Th St",
    "iso:country":"US",
    "sg:address":"310 95th St",
    "sg:city":"Stone Harbor",
    "sg:classifiers":[
        {
            "category":"Organizations",
            "subcategory":"Religious Organization",
            "type":"Services"
        }
    ],
    "sg:phone":"+1 609 368 2670",
    "sg:postcode":"08247",
    "sg:province":"NJ",
    "sg:tags":[
        "clergy"
    ],
    "wof:name":"St Mary's Episcopal Church",
    "wof:placetype":"venue"
},
  "geometry": {"coordinates":[-74.76293,39.056648],"type":"Point"}
}