{
  "type": "Feature",
  "properties": {
    "iso:country":"US",
    "sg:address":"52 Red Valley Rd",
    "sg:city":"Clarksburg",
    "sg:classifiers":[
        {
            "category":"Professional",
            "subcategory":"Employment Agencies",
            "type":"Services"
        }
    ],
    "sg:phone":"+1 609 259 2200",
    "sg:postcode":"08510",
    "sg:province":"NJ",
    "sg:tags":[
        "contractor"
    ],
    "wof:name":"Northeast Resources Inc",
    "wof:placetype":"venue"
},
  "geometry": {"coordinates":[-74.442516,40.187678],"type":"Point"}
}