{
  "type": "Feature",
  "properties": {
    "addr:full":"145 Mortimer Ave Rutherford NJ 07070",
    "addr:housenumber":"145",
    "addr:postcode":"07070",
    "addr:street":"Mortimer Ave",
    "iso:country":"US",
    "sg:address":"145 Mortimer Ave",
    "sg:city":"Rutherford",
    "sg:classifiers":[
        {
            "category":"Social Services",
            "subcategory":"Child Care",
            "type":"Services"
        },
        {
            "category":"Education",
            "subcategory":"Preschool",
            "type":"Public Place"
        },
        {
            "category":"Education",
            "subcategory":"School",
            "type":"Public Place"
        }
    ],
    "sg:phone":"+1 201 842 1515",
    "sg:postcode":"07070",
    "sg:province":"NJ",
    "sg:tags":[
        "elementary",
        "day"
    ],
    "sg:website":"www.rutherfordmontessori.org",
    "wof:name":"Rutherford Montessori School",
    "wof:placetype":"venue"
},
  "geometry": {"coordinates":[-74.106796,40.831001],"type":"Point"}
}