{
  "type": "Feature",
  "properties": {
    "iso:country":"US",
    "sg:address":"401 Greenbrook Rd",
    "sg:city":"North Plainfield",
    "sg:classifiers":[
        {
            "category":"Social Services",
            "subcategory":"Child Care",
            "type":"Services"
        }
    ],
    "sg:phone":"+1 908 561 5055",
    "sg:postcode":"07063",
    "sg:province":"NJ",
    "sg:tags":[
        "kindergarten",
        "academic",
        "school"
    ],
    "sg:website":"www.sundanceschool.net",
    "wof:name":"Sundance School",
    "wof:placetype":"venue"
},
  "geometry": {"coordinates":[-74.44752200000001,40.614133],"type":"Point"}
}