{
  "type": "Feature",
  "properties": {
    "addr:full":"1166 River Ave Lakewood NJ 08701",
    "addr:housenumber":"1166",
    "addr:postcode":"08701",
    "addr:street":"River Ave",
    "iso:country":"US",
    "sg:address":"1166 River Ave",
    "sg:city":"Lakewood",
    "sg:classifiers":[
        {
            "category":"Wholesale",
            "subcategory":"Stationery",
            "type":"Manufacturing & Wholesale Goods"
        }
    ],
    "sg:phone":"+1 732 905 0202",
    "sg:postcode":"08701",
    "sg:province":"NJ",
    "sg:tags":[
        "recycled",
        "paper",
        "broker",
        "exporter"
    ],
    "wof:name":"Gem Fibre",
    "wof:placetype":"venue"
},
  "geometry": {"coordinates":[-74.220439,40.056197],"type":"Point"}
}