{
  "type": "Feature",
  "properties": {
    "addr:full":"82 Brunswick Ave Lebanon NJ 08833",
    "addr:housenumber":"82",
    "addr:postcode":"08833",
    "addr:street":"Brunswick Ave",
    "iso:country":"US",
    "sg:address":"82 Brunswick Ave",
    "sg:city":"Lebanon",
    "sg:classifiers":[
        {
            "category":"Professional",
            "subcategory":"Business Services",
            "type":"Services"
        }
    ],
    "sg:phone":"+1   ",
    "sg:postcode":"08833",
    "sg:province":"NJ",
    "wof:name":"Cw Enterprises LLC",
    "wof:placetype":"venue"
},
  "geometry": {"coordinates":[-74.837509,40.639652],"type":"Point"}
}