{
  "type": "Feature",
  "properties": {
    "iso:country":"US",
    "sg:address":"6 Forest Ave",
    "sg:city":"Paramus",
    "sg:classifiers":[
        {
            "category":"Education",
            "subcategory":"Vocational School",
            "type":"Public Place"
        },
        {
            "category":"Shopping",
            "subcategory":"Computers & Home Electronics",
            "type":"Retail Goods"
        }
    ],
    "sg:phone":"+1 201 843 6444",
    "sg:postcode":"07652",
    "sg:province":"NJ",
    "sg:tags":[
        "application",
        "training",
        "software",
        "consulting",
        "strategic"
    ],
    "sg:website":"www.sterlingnet.com",
    "wof:name":"Sterling Resources Intl",
    "wof:placetype":"venue"
},
  "geometry": {"coordinates":[-74.053838,40.917299],"type":"Point"}
}