{
  "type": "Feature",
  "properties": {
    "addr:full":"3 Indianfield Ct Mahwah NJ 07430",
    "addr:housenumber":"3",
    "addr:postcode":"07430",
    "addr:street":"Indianfield Ct",
    "iso:country":"US",
    "sg:address":"3 Indianfield Ct",
    "sg:city":"Mahwah",
    "sg:classifiers":[
        {
            "category":"Professional",
            "type":"Services"
        }
    ],
    "sg:phone":"+1 201 251 2400",
    "sg:postcode":"07430",
    "sg:province":"NJ",
    "sg:tags":[
        "establishment"
    ],
    "sg:website":"www.cyberincentives.com",
    "wof:name":"Creative Incentives Inc",
    "wof:placetype":"venue"
},
  "geometry": {"coordinates":[-74.13381800000001,41.08027],"type":"Point"}
}