{
  "type": "Feature",
  "properties": {
    "iso:country":"US",
    "sg:address":"219 Patterson St",
    "sg:city":"Perth Amboy",
    "sg:classifiers":[
        {
            "category":"Social Services",
            "subcategory":"Child Care",
            "type":"Services"
        }
    ],
    "sg:phone":"+1 732 826 0719",
    "sg:postcode":"08861",
    "sg:province":"NJ",
    "sg:tags":[
        "day"
    ],
    "wof:name":"Middlesex County Economic Opportunitis Crp Hd Strt",
    "wof:placetype":"venue"
},
  "geometry": {"coordinates":[-74.274902,40.504799],"type":"Point"}
}