{
  "type": "Feature",
  "properties": {
    "addr:full":"50 Olcott St Somerset NJ 08873",
    "addr:housenumber":"50",
    "addr:postcode":"08873",
    "addr:street":"Olcott St",
    "iso:country":"US",
    "sg:address":"50 Olcott St",
    "sg:city":"Somerset",
    "sg:classifiers":[
        {
            "category":"Building & Trades",
            "subcategory":"Construction",
            "type":"Services"
        }
    ],
    "sg:phone":"+1 732 873 0058",
    "sg:postcode":"08873",
    "sg:province":"NJ",
    "sg:tags":[
        "house"
    ],
    "wof:name":"Island Housewrights Corp",
    "wof:placetype":"venue"
},
  "geometry": {"coordinates":[-74.530693,40.495494],"type":"Point"}
}