{
  "type": "Feature",
  "properties": {
    "addr:full":"9 W Greenwood Ave Oaklyn NJ 08107",
    "addr:housenumber":"9",
    "addr:postcode":"08107",
    "addr:street":"W Greenwood Ave",
    "iso:country":"US",
    "sg:address":"9 W Greenwood Ave",
    "sg:city":"Oaklyn",
    "sg:classifiers":[
        {
            "category":"Building & Trades",
            "subcategory":"Construction",
            "type":"Services"
        }
    ],
    "sg:phone":"+1 856 854 6330",
    "sg:postcode":"08107",
    "sg:province":"NJ",
    "sg:tags":[
        "contractor"
    ],
    "wof:name":"Commercial Exterior Systmes",
    "wof:placetype":"venue"
},
  "geometry": {"coordinates":[-75.07769999999999,39.901961],"type":"Point"}
}