{
  "type": "Feature",
  "properties": {
    "addr:full":"647 Linden Ave Teaneck NJ 07666",
    "addr:housenumber":"647",
    "addr:postcode":"07666",
    "addr:street":"Linden Ave",
    "iso:country":"US",
    "sg:address":"647 Linden Ave",
    "sg:city":"Teaneck",
    "sg:classifiers":[
        {
            "category":"Manufacturing",
            "subcategory":"Tools & Machinery",
            "type":"Manufacturing & Wholesale Goods"
        }
    ],
    "sg:phone":"+1 917 806 2741",
    "sg:postcode":"07666",
    "sg:province":"NJ",
    "sg:tags":[
        "household",
        "appliance",
        "mfg"
    ],
    "wof:name":"City Sewing Machine Co",
    "wof:placetype":"venue"
},
  "geometry": {"coordinates":[-74.024373,40.886516],"type":"Point"}
}