{
  "type": "Feature",
  "properties": {
    "addr:full":"310 Bellevue Ave Hammonton NJ 08037",
    "addr:housenumber":"310",
    "addr:postcode":"08037",
    "addr:street":"Bellevue Ave",
    "iso:country":"US",
    "sg:address":"310 Bellevue Ave",
    "sg:city":"Hammonton",
    "sg:classifiers":[
        {
            "category":"Food & Beverages",
            "subcategory":"Groceries & Convenience Stores",
            "type":"Retail Goods"
        }
    ],
    "sg:phone":"+1 609 561 7911",
    "sg:postcode":"08037",
    "sg:province":"NJ",
    "sg:tags":[
        "electronic",
        "psychiatrist"
    ],
    "wof:name":"Atlanticare Behavioral Health",
    "wof:placetype":"venue"
},
  "geometry": {"coordinates":[-74.801598,39.637501],"type":"Point"}
}