{
  "type": "Feature",
  "properties": {
    "addr:full":"370 Campus Dr Somerset NJ 08873",
    "addr:housenumber":"370",
    "addr:postcode":"08873",
    "addr:street":"Campus Dr",
    "iso:country":"US",
    "sg:address":"370 Campus Dr",
    "sg:city":"Somerset",
    "sg:classifiers":[
        {
            "category":"Wholesale",
            "subcategory":"Medical Equipment & Supplies",
            "type":"Manufacturing & Wholesale Goods"
        }
    ],
    "sg:phone":"+1 732 560 9300",
    "sg:postcode":"08873",
    "sg:province":"NJ",
    "sg:tags":[
        "physician",
        "surgeon"
    ],
    "wof:name":"Bextna",
    "wof:placetype":"venue"
},
  "geometry": {"coordinates":[-74.543936,40.54707],"type":"Point"}
}