{
  "type": "Feature",
  "properties": {
    "addr:full":"60 Somers Ave Egg Harbor Twp NJ 08234",
    "addr:housenumber":"60",
    "addr:postcode":"08234",
    "addr:street":"Somers Ave",
    "iso:country":"US",
    "sg:address":"60 Somers Ave",
    "sg:city":"Egg Harbor Twp",
    "sg:classifiers":[
        {
            "category":"Recreation",
            "type":"Entertainment"
        }
    ],
    "sg:phone":"+1 609 412 3635",
    "sg:postcode":"08234",
    "sg:province":"NJ",
    "sg:tags":[
        "party",
        "fishing"
    ],
    "wof:name":"Jessie O'Fishing Charters",
    "wof:placetype":"venue"
},
  "geometry": {"coordinates":[-74.640604,39.322186],"type":"Point"}
}