{
  "type": "Feature",
  "properties": {
    "iso:country":"US",
    "sg:address":"2 Vernon Ave",
    "sg:city":"Hamburg",
    "sg:classifiers":[
        {
            "category":"Food & Beverages",
            "subcategory":"Meat & Fish",
            "type":"Retail Goods"
        }
    ],
    "sg:phone":"+1   ",
    "sg:postcode":"07419",
    "sg:province":"NJ",
    "sg:tags":[
        "deli",
        "market",
        "catering"
    ],
    "wof:name":"B & C Meating Pl & Cntry Deli",
    "wof:placetype":"venue"
},
  "geometry": {"coordinates":[-74.57480700000001,41.154666],"type":"Point"}
}