{
  "type": "Feature",
  "properties": {
    "iso:country":"US",
    "sg:address":"1372 Springfield Ave",
    "sg:city":"Irvington",
    "sg:classifiers":[
        {
            "category":"Personal",
            "subcategory":"Beauty Salon",
            "type":"Services"
        }
    ],
    "sg:phone":"+1 973 399 7979",
    "sg:postcode":"07111",
    "sg:province":"NJ",
    "sg:tags":[
        "shop"
    ],
    "wof:name":"Flore's Hair Designs",
    "wof:placetype":"venue"
},
  "geometry": {"coordinates":[-74.246623,40.724029],"type":"Point"}
}