{
  "type": "Feature",
  "properties": {
    "addr:full":"21 Broad St Red Bank NJ 07701",
    "addr:housenumber":"21",
    "addr:postcode":"07701",
    "addr:street":"Broad St",
    "iso:country":"US",
    "sg:address":"21 Broad St",
    "sg:city":"Red Bank",
    "sg:classifiers":[
        {
            "category":"Home & Garden",
            "subcategory":"Furniture",
            "type":"Retail Goods"
        }
    ],
    "sg:phone":"+1 732 933 0203",
    "sg:postcode":"07701",
    "sg:province":"NJ",
    "wof:name":"Design Studio",
    "wof:placetype":"venue"
},
  "geometry": {"coordinates":[-74.06549099999999,40.352193],"type":"Point"}
}