{
  "type": "Feature",
  "properties": {
    "addr:full":"200 Wexford Dr Cherry Hill NJ 08003",
    "addr:housenumber":"200",
    "addr:postcode":"08003",
    "addr:street":"Wexford Dr",
    "iso:country":"US",
    "sg:address":"200 Wexford Dr",
    "sg:city":"Cherry Hill",
    "sg:classifiers":[
        {
            "category":"Education",
            "subcategory":"School",
            "type":"Public Place"
        }
    ],
    "sg:phone":"+1 856 424 1505",
    "sg:postcode":"08003",
    "sg:province":"NJ",
    "wof:name":"Richard Stockton Elementary",
    "wof:placetype":"venue"
},
  "geometry": {"coordinates":[-74.959757,39.896974],"type":"Point"}
}