{
  "type": "Feature",
  "properties": {
    "addr:full":"802 E Vine St Millville NJ 08332",
    "addr:housenumber":"802",
    "addr:postcode":"08332",
    "addr:street":"E Vine St",
    "iso:country":"US",
    "sg:address":"802 E Vine St",
    "sg:city":"Millville",
    "sg:classifiers":[
        {
            "category":"Professional",
            "subcategory":"Management & Consulting",
            "type":"Services"
        }
    ],
    "sg:phone":"+1 856 825 2560",
    "sg:postcode":"08332",
    "sg:province":"NJ",
    "sg:tags":[
        "consultant",
        "financial"
    ],
    "wof:name":"D & H Financial Services",
    "wof:placetype":"venue"
},
  "geometry": {"coordinates":[-75.02728999999999,39.399656],"type":"Point"}
}