{
  "type": "Feature",
  "properties": {
    "addr:full":"3 Evergreen Ter Succasunna NJ 07876",
    "addr:housenumber":"3",
    "addr:postcode":"07876",
    "addr:street":"Evergreen Ter",
    "iso:country":"US",
    "sg:address":"3 Evergreen Ter",
    "sg:city":"Succasunna",
    "sg:classifiers":[
        {
            "category":"Manufacturing",
            "subcategory":"Metals",
            "type":"Manufacturing & Wholesale Goods"
        }
    ],
    "sg:phone":"+1 973 584 2748",
    "sg:postcode":"07876",
    "sg:province":"NJ",
    "sg:tags":[
        "stampings",
        "mfg"
    ],
    "wof:name":"Evergreen Machinery",
    "wof:placetype":"venue"
},
  "geometry": {"coordinates":[-74.631557,40.865262],"type":"Point"}
}