{
  "type": "Feature",
  "properties": {
    "addr:full":"102 Washington Ave Dumont NJ 07628",
    "addr:housenumber":"102",
    "addr:postcode":"07628",
    "addr:street":"Washington Ave",
    "iso:country":"US",
    "sg:address":"102 Washington Ave",
    "sg:city":"Dumont",
    "sg:classifiers":[
        {
            "category":"Home & Garden",
            "subcategory":"Household Appliances",
            "type":"Retail Goods"
        }
    ],
    "sg:phone":"+1   ",
    "sg:postcode":"07628",
    "sg:province":"NJ",
    "wof:name":"All Factory Appl & Parts Ctr",
    "wof:placetype":"venue"
},
  "geometry": {"coordinates":[-73.993939,40.940226],"type":"Point"}
}