{
  "type": "Feature",
  "properties": {
    "addr:full":"11 W Hudson Ave Englewood NJ 07631",
    "addr:housenumber":"11",
    "addr:postcode":"07631",
    "addr:street":"W Hudson Ave",
    "iso:country":"US",
    "sg:address":"11 W Hudson Ave",
    "sg:city":"Englewood",
    "sg:classifiers":[
        {
            "category":"Retail",
            "subcategory":"Repair Shop",
            "type":"Services"
        }
    ],
    "sg:phone":"+1 201 569 1483",
    "sg:postcode":"07631",
    "sg:province":"NJ",
    "sg:tags":[
        "upholsterer"
    ],
    "wof:name":"Walter's Upholstery",
    "wof:placetype":"venue"
},
  "geometry": {"coordinates":[-73.969256,40.910383],"type":"Point"}
}