{
  "type": "Feature",
  "properties": {
    "addr:full":"4 by Pass Rd Salem NJ 08079",
    "addr:housenumber":"4",
    "addr:postcode":"08079",
    "addr:street":"By Pass Rd",
    "iso:country":"US",
    "sg:address":"4 by Pass Rd",
    "sg:city":"Salem",
    "sg:classifiers":[
        {
            "category":"Health Services",
            "subcategory":"Doctor",
            "type":"Services"
        }
    ],
    "sg:phone":"+1 609 935 8988",
    "sg:postcode":"08079",
    "sg:province":"NJ",
    "sg:tags":[
        "medical"
    ],
    "wof:name":"Stanley R Lane MD",
    "wof:placetype":"venue"
},
  "geometry": {"coordinates":[-75.435659,39.556021],"type":"Point"}
}