{
  "type": "Feature",
  "properties": {
    "addr:full":"80 Stults Rd Dayton NJ 08810",
    "addr:housenumber":"80",
    "addr:postcode":"08810",
    "addr:street":"Stults Rd",
    "iso:country":"US",
    "sg:address":"80 Stults Rd",
    "sg:city":"Dayton",
    "sg:classifiers":[
        {
            "category":"Manufacturing",
            "subcategory":"Furniture",
            "type":"Manufacturing & Wholesale Goods"
        }
    ],
    "sg:phone":"+1 609 860 0220",
    "sg:postcode":"08810",
    "sg:province":"NJ",
    "sg:tags":[
        "building",
        "public",
        "mfg"
    ],
    "wof:name":"Johnson Controls",
    "wof:placetype":"venue"
},
  "geometry": {"coordinates":[-74.481746,40.355075],"type":"Point"}
}