{
  "type": "Feature",
  "properties": {
    "iso:country":"US",
    "sg:address":"3477 John F Kennedy Blvd",
    "sg:city":"Jersey City",
    "sg:classifiers":[
        {
            "category":"Food & Beverages",
            "subcategory":"Groceries & Convenience Stores",
            "type":"Retail Goods"
        }
    ],
    "sg:phone":"+1 201 656 1789",
    "sg:postcode":"07307",
    "sg:province":"NJ",
    "wof:name":"Nesh Grocery",
    "wof:placetype":"venue"
},
  "geometry": {"coordinates":[-74.054497,40.7505],"type":"Point"}
}