{
  "type": "Feature",
  "properties": {
    "iso:country":"US",
    "sg:address":"72 E Main St",
    "sg:city":"Sussex",
    "sg:classifiers":[
        {
            "category":"Real Estate",
            "subcategory":"Real Estate Agent",
            "type":"Services"
        }
    ],
    "sg:phone":"+1 973 875 3157",
    "sg:postcode":"07461",
    "sg:province":"NJ",
    "sg:tags":[
        "cooperative"
    ],
    "wof:name":"Sussex Agway Farm Ctr Co Op",
    "wof:placetype":"venue"
},
  "geometry": {"coordinates":[-74.603436,41.210974],"type":"Point"}
}