{
  "type": "Feature",
  "properties": {
    "iso:country":"US",
    "sg:address":"113 Parker Ave",
    "sg:city":"Maplewood",
    "sg:classifiers":[
        {
            "category":"Organizations",
            "subcategory":"Religious Organization",
            "type":"Services"
        }
    ],
    "sg:phone":"+1 973 313 0171",
    "sg:postcode":"07040",
    "sg:province":"NJ",
    "sg:tags":[
        "church"
    ],
    "sg:website":"www.iglesiamisioncristiana.org",
    "wof:name":"Iglesia Mision Cristiana",
    "wof:placetype":"venue"
},
  "geometry": {"coordinates":[-74.256663,40.732483],"type":"Point"}
}