{
  "type": "Feature",
  "properties": {
    "addr:full":"986 Raymond Boulevard. Between Market and Commerce St Newark NJ 07105",
    "addr:housenumber":"986",
    "addr:postcode":"07105",
    "addr:street":"Raymond Boulevard. Between;St",
    "iso:country":"US",
    "sg:address":"986 Raymond Boulevard. Between Market and Commerce St",
    "sg:city":"Newark",
    "sg:classifiers":[
        {
            "category":"Parking",
            "type":"Transportation"
        }
    ],
    "sg:phone":"+1 973 465 2240",
    "sg:postcode":"07105",
    "sg:province":"NJ",
    "sg:website":"www.parkfast.com",
    "wof:name":"Edison ParkFast",
    "wof:placetype":"venue"
},
  "geometry": {"coordinates":[-74.16251,40.734422],"type":"Point"}
}