{
  "type": "Feature",
  "properties": {
    "iso:country":"US",
    "sg:address":"6417 Bergenline Pl",
    "sg:city":"West New York",
    "sg:classifiers":[
        {
            "category":"Personal",
            "subcategory":"Beauty Salon",
            "type":"Services"
        }
    ],
    "sg:phone":"+1 201 662 7277",
    "sg:postcode":"07093",
    "sg:province":"NJ",
    "sg:tags":[
        "shop"
    ],
    "wof:name":"Bergen Nail",
    "wof:placetype":"venue"
},
  "geometry": {"coordinates":[-74.013345,40.792936],"type":"Point"}
}