{
  "type": "Feature",
  "properties": {
    "addr:full":"3808 Ventnor Ave Atlantic City NJ 08401",
    "addr:housenumber":"3808",
    "addr:postcode":"08401",
    "addr:street":"Ventnor Ave",
    "iso:country":"US",
    "sg:address":"3808 Ventnor Ave",
    "sg:city":"Atlantic City",
    "sg:classifiers":[
        {
            "category":"Restaurant",
            "type":"Food & Drink"
        }
    ],
    "sg:phone":"+1   ",
    "sg:postcode":"08401",
    "sg:province":"NJ",
    "sg:tags":[
        "eating"
    ],
    "wof:name":"Pho Hoa Cali",
    "wof:placetype":"venue"
},
  "geometry": {"coordinates":[-74.456909,39.350369],"type":"Point"}
}