{
  "type": "Feature",
  "properties": {
    "addr:full":"5 E Clinton Ave Bergenfield NJ 07621",
    "addr:housenumber":"5",
    "addr:postcode":"07621",
    "addr:street":"E Clinton Ave",
    "iso:country":"US",
    "sg:address":"5 E Clinton Ave",
    "sg:city":"Bergenfield",
    "sg:classifiers":[
        {
            "category":"Organizations",
            "subcategory":"Religious Organization",
            "type":"Services"
        }
    ],
    "sg:phone":"+1   ",
    "sg:postcode":"07621",
    "sg:province":"NJ",
    "wof:name":"Living Faith Christian Church",
    "wof:placetype":"venue"
},
  "geometry": {"coordinates":[-73.995643,40.923884],"type":"Point"}
}