{
  "type": "Feature",
  "properties": {
    "addr:full":"7 Boonton Ave Butler NJ 07405",
    "addr:housenumber":"7",
    "addr:postcode":"07405",
    "addr:street":"Boonton Ave",
    "iso:country":"US",
    "sg:address":"7 Boonton Ave",
    "sg:city":"Butler",
    "sg:classifiers":[
        {
            "category":"Wholesale",
            "subcategory":"Electrical",
            "type":"Manufacturing & Wholesale Goods"
        }
    ],
    "sg:phone":"+1 973 838 6800",
    "sg:postcode":"07405",
    "sg:province":"NJ",
    "sg:tags":[
        "electronic"
    ],
    "wof:name":"Base Electronics LLC",
    "wof:placetype":"venue"
},
  "geometry": {"coordinates":[-74.347247,40.983475],"type":"Point"}
}