{
  "type": "Feature",
  "properties": {
    "addr:full":"280 US Hwy 46 Denville NJ 07834",
    "addr:housenumber":"280",
    "addr:postcode":"07834",
    "addr:street":"Us Hwy 46",
    "iso:country":"US",
    "sg:address":"280 US Hwy 46",
    "sg:city":"Denville",
    "sg:classifiers":[
        {
            "category":"Health Services",
            "subcategory":"Doctor",
            "type":"Services"
        }
    ],
    "sg:phone":"+1 973 625 8784",
    "sg:postcode":"07834",
    "sg:province":"NJ",
    "sg:tags":[
        "dentist"
    ],
    "wof:name":"Marco L Fernandez DMD",
    "wof:placetype":"venue"
},
  "geometry": {"coordinates":[-74.49661399999999,40.897448],"type":"Point"}
}