{
  "type": "Feature",
  "properties": {
    "addr:full":"502 43rd St Union City NJ 07087",
    "addr:housenumber":"502",
    "addr:postcode":"07087",
    "addr:street":"43Rd St",
    "iso:country":"US",
    "sg:address":"502 43rd St",
    "sg:city":"Union City",
    "sg:classifiers":[
        {
            "category":"Travel",
            "subcategory":"Travel Agent",
            "type":"Entertainment"
        }
    ],
    "sg:phone":"+1 201 863 2422",
    "sg:postcode":"07087",
    "sg:province":"NJ",
    "sg:tags":[
        "tours",
        "promoter"
    ],
    "wof:name":"Inti Tours",
    "wof:placetype":"venue"
},
  "geometry": {"coordinates":[-74.026748,40.779133],"type":"Point"}
}