{
  "type": "Feature",
  "properties": {
    "addr:full":"341 Springfield Ave Summit NJ 07901",
    "addr:housenumber":"341",
    "addr:postcode":"07901",
    "addr:street":"Springfield Ave",
    "iso:country":"US",
    "sg:address":"341 Springfield Ave",
    "sg:city":"Summit",
    "sg:classifiers":[
        {
            "category":"Banks & Credit Unions",
            "subcategory":"Bank",
            "type":"Services"
        }
    ],
    "sg:phone":"+1 908 273 0122",
    "sg:postcode":"07901",
    "sg:province":"NJ",
    "sg:website":"www.hcsbonline.com",
    "wof:name":"Hudson City Savings Bank",
    "wof:placetype":"venue"
},
  "geometry": {"coordinates":[-74.35639999999999,40.717999],"type":"Point"}
}