{
  "type": "Feature",
  "properties": {
    "addr:full":"400 Highland Ter Apt 4J Orange NJ 07050",
    "addr:housenumber":"400",
    "addr:postcode":"07050",
    "addr:street":"Highland Ter Apt 4J",
    "iso:country":"US",
    "sg:address":"400 Highland Ter Apt 4J",
    "sg:city":"Orange",
    "sg:classifiers":[
        {
            "category":"Professional",
            "subcategory":"Computer Services",
            "type":"Services"
        }
    ],
    "sg:phone":"+1 908 245 2111",
    "sg:postcode":"07050",
    "sg:province":"NJ",
    "sg:tags":[
        "repair"
    ],
    "wof:name":"Electronic City",
    "wof:placetype":"venue"
},
  "geometry": {"coordinates":[-74.243599,40.7654],"type":"Point"}
}