{
  "type": "Feature",
  "properties": {
    "iso:country":"US",
    "sg:address":"14 Waverly Pl",
    "sg:city":"Madison",
    "sg:classifiers":[
        {
            "category":"Restaurant",
            "type":"Food & Drink"
        }
    ],
    "sg:phone":"+1 973 377 6630",
    "sg:postcode":"07940",
    "sg:province":"NJ",
    "sg:tags":[
        "eating"
    ],
    "wof:name":"Waverly Restaurant the",
    "wof:placetype":"venue"
},
  "geometry": {"coordinates":[-74.41529800000001,40.758301],"type":"Point"}
}