{
  "type": "Feature",
  "properties": {
    "addr:full":"11 Hardwood Dr Jackson NJ 08527",
    "addr:housenumber":"11",
    "addr:postcode":"08527",
    "addr:street":"Hardwood Dr",
    "iso:country":"US",
    "sg:address":"11 Hardwood Dr",
    "sg:city":"Jackson",
    "sg:classifiers":[
        {
            "category":"Banks & Credit Unions",
            "subcategory":"Financial Services",
            "type":"Services"
        }
    ],
    "sg:phone":"+1   ",
    "sg:postcode":"08527",
    "sg:province":"NJ",
    "sg:tags":[
        "investor"
    ],
    "wof:name":"Brothers of South Somerville",
    "wof:placetype":"venue"
},
  "geometry": {"coordinates":[-74.40631500000001,40.169974],"type":"Point"}
}