{
  "type": "Feature",
  "properties": {
    "iso:country":"US",
    "sg:address":"525 Sinatra Dr",
    "sg:city":"Hoboken",
    "sg:classifiers":[
        {
            "category":"Restaurant",
            "type":"Food & Drink"
        }
    ],
    "sg:menulink":"http://www.allmenus.com/nj/hoboken/280008-crepe-grill/menu/",
    "sg:phone":"+1 201 792 7373",
    "sg:postcode":"07030",
    "sg:province":"NJ",
    "sg:tags":[
        "american",
        "crepe"
    ],
    "wof:name":"Crepe Grill",
    "wof:placetype":"venue"
},
  "geometry": {"coordinates":[-74.025702,40.742824],"type":"Point"}
}