{
  "type": "Feature",
  "properties": {
    "iso:country":"US",
    "sg:address":"171 Loomis Ct",
    "sg:city":"Princeton",
    "sg:classifiers":[
        {
            "category":"Professional",
            "subcategory":"Business Services",
            "type":"Services"
        }
    ],
    "sg:phone":"+1   ",
    "sg:postcode":"08540",
    "sg:province":"NJ",
    "wof:name":"Sean Dolan Associates",
    "wof:placetype":"venue"
},
  "geometry": {"coordinates":[-74.65794,40.363835],"type":"Point"}
}