{
  "type": "Feature",
  "properties": {
    "addr:full":"77 Liberty Village Flemington NJ 08822",
    "addr:housenumber":"77",
    "addr:postcode":"08822",
    "addr:street":"Liberty Village",
    "iso:country":"US",
    "sg:address":"77 Liberty Village",
    "sg:city":"Flemington",
    "sg:classifiers":[
        {
            "category":"Home & Garden",
            "subcategory":"Home Furnishings",
            "type":"Retail Goods"
        }
    ],
    "sg:phone":"+1   ",
    "sg:postcode":"08822",
    "sg:province":"NJ",
    "wof:name":"Ralph Lauren Home Outlet",
    "wof:placetype":"venue"
},
  "geometry": {"coordinates":[-74.861003,40.501961],"type":"Point"}
}