{
  "type": "Feature",
  "properties": {
    "iso:country":"US",
    "sg:address":"200 Park Place Ave",
    "sg:city":"Bradley Beach",
    "sg:classifiers":[
        {
            "category":"Real Estate",
            "subcategory":"Real Estate Operator",
            "type":"Services"
        }
    ],
    "sg:phone":"+1 732 988 3311",
    "sg:postcode":"07720",
    "sg:province":"NJ",
    "sg:tags":[
        "condominium"
    ],
    "wof:name":"200 Park Place Condo Assn",
    "wof:placetype":"venue"
},
  "geometry": {"coordinates":[-74.01000500000001,40.205442],"type":"Point"}
}