{
  "type": "Feature",
  "properties": {
    "iso:country":"US",
    "sg:address":"2 Austin Ave",
    "sg:city":"Woodbridge",
    "sg:classifiers":[
        {
            "category":"Building & Trades",
            "subcategory":"Construction",
            "type":"Services"
        }
    ],
    "sg:phone":"+1 732 326 9090",
    "sg:postcode":"07095",
    "sg:province":"NJ",
    "sg:tags":[
        "contractor"
    ],
    "sg:website":"www.braginskysurvey.com",
    "wof:name":"Braginsky Surveying",
    "wof:placetype":"venue"
},
  "geometry": {"coordinates":[-74.265012,40.553328],"type":"Point"}
}