{
  "type": "Feature",
  "properties": {
    "addr:full":"7 Hopkins Pl Jackson NJ 08527",
    "addr:housenumber":"7",
    "addr:postcode":"08527",
    "addr:street":"Hopkins Pl",
    "iso:country":"US",
    "sg:address":"7 Hopkins Pl",
    "sg:city":"Jackson",
    "sg:classifiers":[
        {
            "category":"Real Estate",
            "subcategory":"Real Estate Agent",
            "type":"Services"
        }
    ],
    "sg:phone":"+1   ",
    "sg:postcode":"08527",
    "sg:province":"NJ",
    "wof:name":"Home Properties Inc",
    "wof:placetype":"venue"
},
  "geometry": {"coordinates":[-74.40706,40.155051],"type":"Point"}
}