{
  "type": "Feature",
  "properties": {
    "iso:country":"US",
    "sg:address":"633 Nassau St",
    "sg:city":"North Brunswick",
    "sg:classifiers":[
        {
            "category":"Manufacturing",
            "subcategory":"Electronics",
            "type":"Manufacturing & Wholesale Goods"
        }
    ],
    "sg:phone":"+1 732 846 7500",
    "sg:postcode":"08902",
    "sg:province":"NJ",
    "sg:tags":[
        "antenna"
    ],
    "wof:name":"Ward Products Corp",
    "wof:placetype":"venue"
},
  "geometry": {"coordinates":[-74.44887,40.472586],"type":"Point"}
}