{
  "type": "Feature",
  "properties": {
    "iso:country":"US",
    "sg:address":"595 Broad Ave",
    "sg:city":"Ridgefield",
    "sg:classifiers":[
        {
            "category":"Professional",
            "subcategory":"Computer Services",
            "type":"Services"
        }
    ],
    "sg:phone":"+1 201 941 9200",
    "sg:postcode":"07657",
    "sg:province":"NJ",
    "sg:tags":[
        "consultant",
        "designer",
        "programing",
        "custom"
    ],
    "sg:website":"www.mondonando.com",
    "wof:name":"Tesseract Technology Inc",
    "wof:placetype":"venue"
},
  "geometry": {"coordinates":[-74.009429,40.834216],"type":"Point"}
}