{
  "type": "Feature",
  "properties": {
    "iso:country":"US",
    "sg:address":"75 Chestnut St",
    "sg:city":"Red Bank",
    "sg:classifiers":[
        {
            "category":"Government",
            "subcategory":"Office",
            "type":"Public Place"
        }
    ],
    "sg:phone":"+1   ",
    "sg:postcode":"07701",
    "sg:province":"NJ",
    "sg:tags":[
        "water",
        "city",
        "sewer",
        "department"
    ],
    "wof:name":"Public Works",
    "wof:placetype":"venue"
},
  "geometry": {"coordinates":[-74.07061299999999,40.347206],"type":"Point"}
}