{
  "type": "Feature",
  "properties": {
    "iso:country":"US",
    "sg:address":"134 State Rte 183",
    "sg:city":"Stanhope",
    "sg:classifiers":[
        {
            "category":"Restaurant",
            "type":"Food & Drink"
        }
    ],
    "sg:phone":"+1 973 448 4944",
    "sg:postcode":"07874",
    "sg:province":"NJ",
    "wof:name":"Shakey Jakes",
    "wof:placetype":"venue"
},
  "geometry": {"coordinates":[-74.712777,40.910397],"type":"Point"}
}