{
  "type": "Feature",
  "properties": {
    "iso:country":"US",
    "sg:address":"165 Prospect St",
    "sg:city":"Passaic",
    "sg:classifiers":[
        {
            "category":"Professional",
            "subcategory":"Lawyer & Legal Services",
            "type":"Services"
        }
    ],
    "sg:phone":"+1 973 471 2300",
    "sg:postcode":"07055",
    "sg:province":"NJ",
    "sg:tags":[
        "personal",
        "injury"
    ],
    "wof:name":"Weiner & Ryan PC",
    "wof:placetype":"venue"
},
  "geometry": {"coordinates":[-74.126999,40.861401],"type":"Point"}
}