{
  "type": "Feature",
  "properties": {
    "addr:full":"150 North Ave Fanwood NJ 07023",
    "addr:housenumber":"150",
    "addr:postcode":"07023",
    "addr:street":"North Ave",
    "iso:country":"US",
    "sg:address":"150 North Ave",
    "sg:city":"Fanwood",
    "sg:classifiers":[
        {
            "category":"Wholesale",
            "subcategory":"Jewelry",
            "type":"Manufacturing & Wholesale Goods"
        }
    ],
    "sg:phone":"+1 908 322 0675",
    "sg:postcode":"07023",
    "sg:province":"NJ",
    "sg:tags":[
        "stone"
    ],
    "wof:name":"Crystee Inc",
    "wof:placetype":"venue"
},
  "geometry": {"coordinates":[-74.388682,40.639921],"type":"Point"}
}