{
  "type": "Feature",
  "properties": {
    "addr:full":"536 Bloomfield Ave Montclair NJ 07042",
    "addr:housenumber":"536",
    "addr:postcode":"07042",
    "addr:street":"Bloomfield Ave",
    "iso:country":"US",
    "sg:address":"536 Bloomfield Ave",
    "sg:city":"Montclair",
    "sg:classifiers":[
        {
            "category":"Banks & Credit Unions",
            "subcategory":"Bank",
            "type":"Services"
        }
    ],
    "sg:phone":"+1 800 482 5465",
    "sg:postcode":"07042",
    "sg:province":"NJ",
    "sg:website":"www.tdbanknorth.com",
    "wof:name":"Td Banknorth Na",
    "wof:placetype":"venue"
},
  "geometry": {"coordinates":[-74.219284,40.815005],"type":"Point"}
}