{
  "type": "Feature",
  "properties": {
    "iso:country":"US",
    "sg:address":"1827 Old Mill Rd",
    "sg:city":"Wall",
    "sg:classifiers":[
        {
            "category":"Wholesale",
            "subcategory":"Machinery & Supplies",
            "type":"Manufacturing & Wholesale Goods"
        }
    ],
    "sg:phone":"+1 732 280 7737",
    "sg:postcode":"07719",
    "sg:province":"NJ",
    "sg:tags":[
        "fire",
        "department",
        "equipment"
    ],
    "wof:name":"Fire Hooks Unlimited",
    "wof:placetype":"venue"
},
  "geometry": {"coordinates":[-74.051806,40.167974],"type":"Point"}
}