{
  "type": "Feature",
  "properties": {
    "iso:country":"US",
    "sg:address":"19 Dorchester Dr",
    "sg:city":"Sussex",
    "sg:classifiers":[
        {
            "category":"Banks & Credit Unions",
            "subcategory":"Financial Services",
            "type":"Services"
        }
    ],
    "sg:phone":"+1   ",
    "sg:postcode":"07461",
    "sg:province":"NJ",
    "sg:tags":[
        "investment",
        "closed"
    ],
    "wof:name":"Austin James Limited",
    "wof:placetype":"venue"
},
  "geometry": {"coordinates":[-74.49613600000001,41.22606],"type":"Point"}
}