{
  "type": "Feature",
  "properties": {
    "iso:country":"US",
    "sg:address":"146 W Barber Ave",
    "sg:city":"Woodbury",
    "sg:classifiers":[
        {
            "category":"Shopping",
            "type":"Retail Goods"
        }
    ],
    "sg:phone":"+1   ",
    "sg:postcode":"08096",
    "sg:province":"NJ",
    "sg:tags":[
        "merchandise"
    ],
    "wof:name":"For Pets Sake",
    "wof:placetype":"venue"
},
  "geometry": {"coordinates":[-75.15971,39.837321],"type":"Point"}
}