{
  "type": "Feature",
  "properties": {
    "addr:full":"1 International Blvd Mahwah NJ 07430",
    "addr:housenumber":"1",
    "addr:postcode":"07430",
    "addr:street":"International Blvd",
    "iso:country":"US",
    "sg:address":"1 International Blvd",
    "sg:city":"Mahwah",
    "sg:classifiers":[
        {
            "category":"Professional",
            "subcategory":"Business Services",
            "type":"Services"
        }
    ],
    "sg:phone":"+1   ",
    "sg:postcode":"07430",
    "sg:province":"NJ",
    "sg:tags":[
        "ship",
        "management",
        "risk",
        "inspecting"
    ],
    "wof:name":"Dnv",
    "wof:placetype":"venue"
},
  "geometry": {"coordinates":[-74.16328799999999,41.104352],"type":"Point"}
}