{
  "type": "Feature",
  "properties": {
    "addr:full":"21 E Front St Red Bank NJ 07701",
    "addr:housenumber":"21",
    "addr:postcode":"07701",
    "addr:street":"E Front St",
    "iso:country":"US",
    "sg:address":"21 E Front St",
    "sg:city":"Red Bank",
    "sg:classifiers":[
        {
            "category":"Professional",
            "type":"Services"
        }
    ],
    "sg:phone":"+1   ",
    "sg:postcode":"07701",
    "sg:province":"NJ",
    "wof:name":"Metrovation",
    "wof:placetype":"venue"
},
  "geometry": {"coordinates":[-74.06504700000001,40.352304],"type":"Point"}
}