{
  "type": "Feature",
  "properties": {
    "addr:full":"37 Jackson Ave Carteret NJ 07008",
    "addr:housenumber":"37",
    "addr:postcode":"07008",
    "addr:street":"Jackson Ave",
    "iso:country":"US",
    "sg:address":"37 Jackson Ave",
    "sg:city":"Carteret",
    "sg:classifiers":[
        {
            "category":"Professional",
            "subcategory":"Business Services",
            "type":"Services"
        },
        {
            "category":"Manufacturing",
            "subcategory":"Apparel",
            "type":"Manufacturing & Wholesale Goods"
        }
    ],
    "sg:phone":"+1 732 969 0232",
    "sg:postcode":"07008",
    "sg:province":"NJ",
    "sg:tags":[
        "embroidery"
    ],
    "wof:name":"Life's A Stitch",
    "wof:placetype":"venue"
},
  "geometry": {"coordinates":[-74.239667,40.582369],"type":"Point"}
}