{
  "type": "Feature",
  "properties": {
    "addr:full":"615 Hamburg Tpke Pompton Lakes NJ 07442",
    "addr:housenumber":"615",
    "addr:postcode":"07442",
    "addr:street":"Hamburg Tpke",
    "iso:country":"US",
    "sg:address":"615 Hamburg Tpke",
    "sg:city":"Pompton Lakes",
    "sg:classifiers":[
        {
            "category":"Health Services",
            "subcategory":"Health Practitioner",
            "type":"Services"
        }
    ],
    "sg:phone":"+1 973 633 7710",
    "sg:postcode":"07442",
    "sg:province":"NJ",
    "sg:tags":[
        "psychologist"
    ],
    "wof:name":"Counseling Care Assoc",
    "wof:placetype":"venue"
},
  "geometry": {"coordinates":[-74.282455,40.994578],"type":"Point"}
}