{
  "type": "Feature",
  "properties": {
    "iso:country":"US",
    "sg:address":"160 Lawrenceville Pennington Rd",
    "sg:city":"Trenton",
    "sg:classifiers":[
        {
            "category":"Personal",
            "subcategory":"Beauty Salon",
            "type":"Services"
        }
    ],
    "sg:phone":"+1 609 620 1268",
    "sg:postcode":"08648",
    "sg:province":"NJ",
    "sg:tags":[
        "manicuring"
    ],
    "wof:name":"Us Nail",
    "wof:placetype":"venue"
},
  "geometry": {"coordinates":[-74.74875400000001,40.301548],"type":"Point"}
}