{
  "type": "Feature",
  "properties": {
    "iso:country":"US",
    "sg:address":"1878 State Route 31",
    "sg:city":"Clinton",
    "sg:classifiers":[
        {
            "category":"Deli",
            "type":"Food & Drink"
        }
    ],
    "sg:phone":"+1 908 638 3354",
    "sg:postcode":"08809",
    "sg:province":"NJ",
    "wof:name":"Lakeside Deli",
    "wof:placetype":"venue"
},
  "geometry": {"coordinates":[-74.91330000000001,40.662102],"type":"Point"}
}