{
  "type": "Feature",
  "properties": {
    "iso:country":"US",
    "sg:address":"6 Wolverton Ln",
    "sg:city":"Hillsborough",
    "sg:classifiers":[
        {
            "category":"Insurance",
            "subcategory":"Insurance Agent",
            "type":"Services"
        }
    ],
    "sg:phone":"+1 908 369 3300",
    "sg:postcode":"08844",
    "sg:province":"NJ",
    "wof:name":"Prudential Insurance Co",
    "wof:placetype":"venue"
},
  "geometry": {"coordinates":[-74.66674500000001,40.512198],"type":"Point"}
}