{
  "type": "Feature",
  "properties": {
    "addr:full":"1701 S East Blvd Vineland NJ 08360",
    "addr:housenumber":"1701",
    "addr:postcode":"08360",
    "addr:street":"S East Blvd",
    "iso:country":"US",
    "sg:address":"1701 S East Blvd",
    "sg:city":"Vineland",
    "sg:classifiers":[
        {
            "category":"Professional",
            "subcategory":"Business Services",
            "type":"Services"
        }
    ],
    "sg:phone":"+1 856 696 3491",
    "sg:postcode":"08360",
    "sg:province":"NJ",
    "sg:tags":[
        "inspection"
    ],
    "wof:name":"Inspection Acres",
    "wof:placetype":"venue"
},
  "geometry": {"coordinates":[-75.027816,39.461179],"type":"Point"}
}