{
  "type": "Feature",
  "properties": {
    "addr:full":"3201 US Hwy 1 Lawrenceville NJ 08648",
    "addr:housenumber":"3201",
    "addr:postcode":"08648",
    "addr:street":"Us Hwy 1",
    "iso:country":"US",
    "sg:address":"3201 US Hwy 1",
    "sg:city":"Lawrenceville",
    "sg:classifiers":[
        {
            "category":"Retail",
            "subcategory":"Auto Rental",
            "type":"Services"
        }
    ],
    "sg:phone":"+1 609 620 1399",
    "sg:postcode":"08648",
    "sg:province":"NJ",
    "sg:tags":[
        "renting",
        "automobile"
    ],
    "wof:name":"Enterprise Rent A Car",
    "wof:placetype":"venue"
},
  "geometry": {"coordinates":[-74.68599399999999,40.291903],"type":"Point"}
}