{
  "type": "Feature",
  "properties": {
    "addr:full":"12 Arden Pl Summit NJ 07901",
    "addr:housenumber":"12",
    "addr:postcode":"07901",
    "addr:street":"Arden Pl",
    "iso:country":"US",
    "sg:address":"12 Arden Pl",
    "sg:city":"Summit",
    "sg:classifiers":[
        {
            "category":"Professional",
            "subcategory":"Business Services",
            "type":"Services"
        }
    ],
    "sg:phone":"+1 908 598 1670",
    "sg:postcode":"07901",
    "sg:province":"NJ",
    "sg:tags":[
        "interior",
        "consultant",
        "design",
        "decorator"
    ],
    "wof:name":"Frank Delle Donne Interiors",
    "wof:placetype":"venue"
},
  "geometry": {"coordinates":[-74.350568,40.72903],"type":"Point"}
}