{
  "type": "Feature",
  "properties": {
    "addr:full":"600 Stelton Rd Piscataway NJ 08854",
    "addr:housenumber":"600",
    "addr:postcode":"08854",
    "addr:street":"Stelton Rd",
    "iso:country":"US",
    "sg:address":"600 Stelton Rd",
    "sg:city":"Piscataway",
    "sg:classifiers":[
        {
            "category":"Restaurant",
            "type":"Food & Drink"
        }
    ],
    "sg:phone":"+1 732 752 6221",
    "sg:postcode":"08854",
    "sg:province":"NJ",
    "sg:tags":[
        "eating",
        "caterer"
    ],
    "wof:name":"Bob's Park Ave Caterers",
    "wof:placetype":"venue"
},
  "geometry": {"coordinates":[-74.441395,40.55973],"type":"Point"}
}