{
  "type": "Feature",
  "properties": {
    "addr:full":"6 Valley Rd Jackson NJ 08527",
    "addr:housenumber":"6",
    "addr:postcode":"08527",
    "addr:street":"Valley Rd",
    "iso:country":"US",
    "sg:address":"6 Valley Rd",
    "sg:city":"Jackson",
    "sg:classifiers":[
        {
            "category":"Organizations",
            "subcategory":"Religious Organization",
            "type":"Services"
        }
    ],
    "sg:phone":"+1 732 364 4489",
    "sg:postcode":"08527",
    "sg:province":"NJ",
    "sg:tags":[
        "church"
    ],
    "wof:name":"Jehovah's Witnesses",
    "wof:placetype":"venue"
},
  "geometry": {"coordinates":[-74.25401100000001,40.124607],"type":"Point"}
}