{
  "type": "Feature",
  "properties": {
    "iso:country":"US",
    "sg:address":"862 Woodruff Ln",
    "sg:city":"Elizabeth",
    "sg:classifiers":[
        {
            "category":"Retail",
            "subcategory":"Auto Repair",
            "type":"Services"
        }
    ],
    "sg:phone":"+1 908 352 5558",
    "sg:postcode":"07201",
    "sg:province":"NJ",
    "sg:tags":[
        "automotive"
    ],
    "wof:name":"American Crankshaft Grinding",
    "wof:placetype":"venue"
},
  "geometry": {"coordinates":[-74.195896,40.673615],"type":"Point"}
}