{
  "type": "Feature",
  "properties": {
    "addr:full":"17 Charred Oak Ln Hightstown NJ 08520",
    "addr:housenumber":"17",
    "addr:postcode":"08520",
    "addr:street":"Charred Oak Ln",
    "iso:country":"US",
    "sg:address":"17 Charred Oak Ln",
    "sg:city":"Hightstown",
    "sg:classifiers":[
        {
            "category":"Professional",
            "subcategory":"Business Services",
            "type":"Services"
        }
    ],
    "sg:phone":"+1 609 448 3594",
    "sg:postcode":"08520",
    "sg:province":"NJ",
    "wof:name":"Interior Image Inc",
    "wof:placetype":"venue"
},
  "geometry": {"coordinates":[-74.55859700000001,40.269038],"type":"Point"}
}