{
  "type": "Feature",
  "properties": {
    "addr:full":"103 E Front St Red Bank NJ 07701",
    "addr:housenumber":"103",
    "addr:postcode":"07701",
    "addr:street":"E Front St",
    "iso:country":"US",
    "sg:address":"103 E Front St",
    "sg:city":"Red Bank",
    "sg:classifiers":[
        {
            "category":"Wholesale",
            "subcategory":"Medical Equipment & Supplies",
            "type":"Manufacturing & Wholesale Goods"
        }
    ],
    "sg:phone":"+1 732 530 2548",
    "sg:postcode":"07701",
    "sg:province":"NJ",
    "sg:tags":[
        "hospital"
    ],
    "wof:name":"Meridian Hospitals Corporation",
    "wof:placetype":"venue"
},
  "geometry": {"coordinates":[-74.05944100000001,40.353265],"type":"Point"}
}