{
  "type": "Feature",
  "properties": {
    "iso:country":"US",
    "sg:address":"105 Enterprise Ave S",
    "sg:city":"Secaucus",
    "sg:classifiers":[
        {
            "category":"Shopping",
            "type":"Retail Goods"
        }
    ],
    "sg:phone":"+1 201 864 4777",
    "sg:postcode":"07094",
    "sg:province":"NJ",
    "sg:tags":[
        "factory",
        "outlet"
    ],
    "wof:name":"London Fog Industries",
    "wof:placetype":"venue"
},
  "geometry": {"coordinates":[-74.072142,40.776564],"type":"Point"}
}