{
  "type": "Feature",
  "properties": {
    "addr:full":"9701 Ventnor Ave Margate City NJ 08402",
    "addr:housenumber":"9701",
    "addr:postcode":"08402",
    "addr:street":"Ventnor Ave Margate",
    "iso:country":"US",
    "sg:address":"9701 Ventnor Ave",
    "sg:city":"Margate City",
    "sg:classifiers":[
        {
            "category":"Communications",
            "subcategory":"Television Station",
            "type":"Services"
        }
    ],
    "sg:phone":"+1 609 344 6661",
    "sg:postcode":"08402",
    "sg:province":"NJ",
    "wof:name":"ABC",
    "wof:placetype":"venue"
},
  "geometry": {"coordinates":[-74.518163,39.319917],"type":"Point"}
}