{
  "type": "Feature",
  "properties": {
    "iso:country":"US",
    "sg:address":"505 Bancroft Rd",
    "sg:city":"Cherry Hill",
    "sg:classifiers":[
        {
            "category":"Building & Trades",
            "subcategory":"Plumbing",
            "type":"Services"
        }
    ],
    "sg:phone":"+1 856 779 2585",
    "sg:postcode":"08034",
    "sg:province":"NJ",
    "sg:tags":[
        "plumbing",
        "heating",
        "air"
    ],
    "wof:name":"Mario Fanelli Electric",
    "wof:placetype":"venue"
},
  "geometry": {"coordinates":[-74.988236,39.92571],"type":"Point"}
}