{
  "type": "Feature",
  "properties": {
    "addr:full":"14 Wyckoff Ave Ramsey NJ 07446",
    "addr:housenumber":"14",
    "addr:postcode":"07446",
    "addr:street":"Wyckoff Ave",
    "iso:country":"US",
    "sg:address":"14 Wyckoff Ave",
    "sg:city":"Ramsey",
    "sg:classifiers":[
        {
            "category":"Shopping",
            "subcategory":"Clothing, Apparel, & Fashions",
            "type":"Retail Goods"
        }
    ],
    "sg:phone":"+1   ",
    "sg:postcode":"07446",
    "sg:province":"NJ",
    "sg:tags":[
        "tailoring",
        "custom"
    ],
    "wof:name":"Custom Tailoring & Styling",
    "wof:placetype":"venue"
},
  "geometry": {"coordinates":[-74.14650899999999,41.056643],"type":"Point"}
}