{
  "type": "Feature",
  "properties": {
    "addr:full":"18 Debell Ct Passaic NJ 07055",
    "addr:housenumber":"18",
    "addr:postcode":"07055",
    "addr:street":"Debell Ct",
    "iso:country":"US",
    "sg:address":"18 Debell Ct",
    "sg:city":"Passaic",
    "sg:classifiers":[
        {
            "category":"Professional",
            "subcategory":"Computer Services",
            "type":"Services"
        }
    ],
    "sg:phone":"+1 973 778 0287",
    "sg:postcode":"07055",
    "sg:province":"NJ",
    "sg:tags":[
        "custom",
        "electrical",
        "programing",
        "contractor"
    ],
    "wof:name":"Ascent Computer Solutions",
    "wof:placetype":"venue"
},
  "geometry": {"coordinates":[-74.130453,40.846195],"type":"Point"}
}