{
  "type": "Feature",
  "properties": {
    "iso:country":"US",
    "sg:address":"700 Summerfield Ave",
    "sg:city":"Asbury Park",
    "sg:classifiers":[
        {
            "category":"Retail",
            "subcategory":"Laundry & Dry Cleaning",
            "type":"Services"
        }
    ],
    "sg:phone":"+1 732 774 6154",
    "sg:postcode":"07712",
    "sg:province":"NJ",
    "sg:tags":[
        "cleaners",
        "coin",
        "power"
    ],
    "wof:name":"Sam Wah Chinese Laundry",
    "wof:placetype":"venue"
},
  "geometry": {"coordinates":[-74.012608,40.218154],"type":"Point"}
}