{
  "type": "Feature",
  "properties": {
    "addr:full":"81 Cliffwood Ave Matawan NJ 07721",
    "addr:housenumber":"81",
    "addr:postcode":"07721",
    "addr:street":"Cliffwood Ave",
    "iso:country":"US",
    "sg:address":"81 Cliffwood Ave",
    "sg:city":"Matawan",
    "sg:classifiers":[
        {
            "category":"Restaurant",
            "type":"Food & Drink"
        }
    ],
    "sg:phone":"+1   ",
    "sg:postcode":"07721",
    "sg:province":"NJ",
    "sg:tags":[
        "eating"
    ],
    "wof:name":"Evans Restaurant",
    "wof:placetype":"venue"
},
  "geometry": {"coordinates":[-74.24449199999999,40.43091],"type":"Point"}
}