{
  "type": "Feature",
  "properties": {
    "addr:full":"86 N Main St Cranbury NJ 08512",
    "addr:housenumber":"86",
    "addr:postcode":"08512",
    "addr:street":"N Main St",
    "iso:country":"US",
    "sg:address":"86 N Main St",
    "sg:city":"Cranbury",
    "sg:classifiers":[
        {
            "category":"Professional",
            "subcategory":"Management & Consulting",
            "type":"Services"
        }
    ],
    "sg:phone":"+1   ",
    "sg:postcode":"08512",
    "sg:province":"NJ",
    "sg:tags":[
        "business"
    ],
    "wof:name":"Intendere Consulting Partners",
    "wof:placetype":"venue"
},
  "geometry": {"coordinates":[-74.514194,40.315986],"type":"Point"}
}