{
  "type": "Feature",
  "properties": {
    "addr:full":"1085 N Black Horse Pike Williamstown NJ 08094",
    "addr:housenumber":"1085",
    "addr:postcode":"08094",
    "addr:street":"N Black Horse Pike",
    "iso:country":"US",
    "sg:address":"1085 N Black Horse Pike",
    "sg:city":"Williamstown",
    "sg:classifiers":[
        {
            "category":"Professional",
            "subcategory":"Engineering",
            "type":"Services"
        }
    ],
    "sg:phone":"+1 856 629 5292",
    "sg:postcode":"08094",
    "sg:province":"NJ",
    "sg:tags":[
        "engineer"
    ],
    "wof:name":"Fiber Engineering & Design Crp",
    "wof:placetype":"venue"
},
  "geometry": {"coordinates":[-75.005606,39.701948],"type":"Point"}
}