{
  "type": "Feature",
  "properties": {
    "addr:full":"244 Kamena St Fairview NJ 07022",
    "addr:housenumber":"244",
    "addr:postcode":"07022",
    "addr:street":"Kamena St",
    "iso:country":"US",
    "sg:address":"244 Kamena St",
    "sg:city":"Fairview",
    "sg:classifiers":[
        {
            "category":"Manufacturing",
            "subcategory":"Printing",
            "type":"Manufacturing & Wholesale Goods"
        }
    ],
    "sg:phone":"+1 201 941 0375",
    "sg:postcode":"07022",
    "sg:province":"NJ",
    "sg:tags":[
        "lithographic",
        "commercial"
    ],
    "wof:name":"Robert Purcell Printing",
    "wof:placetype":"venue"
},
  "geometry": {"coordinates":[-73.994737,40.814498],"type":"Point"}
}