{
  "type": "Feature",
  "properties": {
    "iso:country":"US",
    "sg:address":"241 Forsgate Dr",
    "sg:city":"Jamesburg",
    "sg:classifiers":[
        {
            "category":"Manufacturing",
            "subcategory":"Printing",
            "type":"Manufacturing & Wholesale Goods"
        }
    ],
    "sg:phone":"+1 732 656 0200",
    "sg:postcode":"08831",
    "sg:province":"NJ",
    "sg:tags":[
        "publisher",
        "guide"
    ],
    "wof:name":"Romanaine Pierson Publishers",
    "wof:placetype":"venue"
},
  "geometry": {"coordinates":[-74.440234,40.346951],"type":"Point"}
}