{
  "type": "Feature",
  "properties": {
    "addr:full":"8 Thornton Rd Oakland NJ 07436",
    "addr:housenumber":"8",
    "addr:postcode":"07436",
    "addr:street":"Thornton Rd",
    "iso:country":"US",
    "sg:address":"8 Thornton Rd",
    "sg:city":"Oakland",
    "sg:classifiers":[
        {
            "category":"Wholesale",
            "subcategory":"Non-durable Goods",
            "type":"Manufacturing & Wholesale Goods"
        }
    ],
    "sg:phone":"+1 201 651 5158",
    "sg:postcode":"07436",
    "sg:province":"NJ",
    "sg:website":"www.zrike.com",
    "wof:name":"Zrike Co Inc",
    "wof:placetype":"venue"
},
  "geometry": {"coordinates":[-74.245422,41.006925],"type":"Point"}
}