{
  "type": "Feature",
  "properties": {
    "iso:country":"US",
    "sg:address":"191 Coolidge Ave",
    "sg:city":"Englewood",
    "sg:classifiers":[
        {
            "category":"Manufacturing",
            "subcategory":"Retail Goods",
            "type":"Manufacturing & Wholesale Goods"
        }
    ],
    "sg:phone":"+1 201 871 4150",
    "sg:postcode":"07631",
    "sg:province":"NJ",
    "sg:tags":[
        "manufacturer"
    ],
    "wof:name":"AVOTLLC",
    "wof:placetype":"venue"
},
  "geometry": {"coordinates":[-73.987515,40.886728],"type":"Point"}
}