{
  "type": "Feature",
  "properties": {
    "addr:full":"417 N Broadway Pennsville NJ 08070",
    "addr:housenumber":"417",
    "addr:postcode":"08070",
    "addr:street":"N Broadway",
    "iso:country":"US",
    "sg:address":"417 N Broadway",
    "sg:city":"Pennsville",
    "sg:classifiers":[
        {
            "category":"Restaurant",
            "type":"Food & Drink"
        }
    ],
    "sg:phone":"+1 856 299 9268",
    "sg:postcode":"08070",
    "sg:province":"NJ",
    "sg:website":"www.mcdonalds.com",
    "wof:name":"Mc Donald's",
    "wof:placetype":"venue"
},
  "geometry": {"coordinates":[-75.49648500000001,39.676224],"type":"Point"}
}