{
  "type": "Feature",
  "properties": {
    "addr:full":"360 Passaic Ave Caldwell NJ 07006",
    "addr:housenumber":"360",
    "addr:postcode":"07006",
    "addr:street":"Passaic Ave",
    "iso:country":"US",
    "sg:address":"360 Passaic Ave",
    "sg:city":"Caldwell",
    "sg:classifiers":[
        {
            "category":"Health Services",
            "subcategory":"Clinic",
            "type":"Services"
        }
    ],
    "sg:phone":"+1 973 808 7280",
    "sg:postcode":"07006",
    "sg:province":"NJ",
    "wof:name":"Blood Recovery Services",
    "wof:placetype":"venue"
},
  "geometry": {"coordinates":[-74.30373899999999,40.83918],"type":"Point"}
}