{
  "type": "Feature",
  "properties": {
    "addr:full":"67 Sand Park Rd Cedar Grove NJ 07009",
    "addr:housenumber":"67",
    "addr:postcode":"07009",
    "addr:street":"Sand Park Rd",
    "iso:country":"US",
    "sg:address":"67 Sand Park Rd",
    "sg:city":"Cedar Grove",
    "sg:classifiers":[
        {
            "category":"Manufacturing",
            "subcategory":"Printing",
            "type":"Manufacturing & Wholesale Goods"
        }
    ],
    "sg:phone":"+1 973 857 0901",
    "sg:postcode":"07009",
    "sg:province":"NJ",
    "sg:tags":[
        "printer"
    ],
    "wof:name":"Dennison-Control Print",
    "wof:placetype":"venue"
},
  "geometry": {"coordinates":[-74.227198,40.867111],"type":"Point"}
}