{
  "type": "Feature",
  "properties": {
    "addr:full":"1040 State Rte 12 Frenchtown NJ 08825",
    "addr:housenumber":"1040",
    "addr:postcode":"08825",
    "addr:street":"State Rte 12",
    "iso:country":"US",
    "sg:address":"1040 State Rte 12",
    "sg:city":"Frenchtown",
    "sg:classifiers":[
        {
            "category":"Retail",
            "subcategory":"Animal Services",
            "type":"Services"
        }
    ],
    "sg:phone":"+1 908 996 7200",
    "sg:postcode":"08825",
    "sg:province":"NJ",
    "sg:tags":[
        "pet",
        "grooming",
        "washing"
    ],
    "wof:name":"Pet Country Club Inc",
    "wof:placetype":"venue"
},
  "geometry": {"coordinates":[-74.998043,40.519884],"type":"Point"}
}