{
  "type": "Feature",
  "properties": {
    "iso:country":"US",
    "sg:address":"191 Godwin Ave",
    "sg:city":"Wyckoff",
    "sg:classifiers":[
        {
            "category":"Professional",
            "subcategory":"Business Services",
            "type":"Services"
        }
    ],
    "sg:phone":"+1   ",
    "sg:postcode":"07481",
    "sg:province":"NJ",
    "wof:name":"Gsn Technologies LLC",
    "wof:placetype":"venue"
},
  "geometry": {"coordinates":[-74.160382,41.007166],"type":"Point"}
}