{
  "type": "Feature",
  "properties": {
    "addr:full":"1961 Jacksonville Jobstown Rd Columbus NJ 08022",
    "addr:housenumber":"1961",
    "addr:postcode":"08022",
    "addr:street":"Jacksonville Jobstown Rd",
    "iso:country":"US",
    "sg:address":"1961 Jacksonville Jobstown Rd",
    "sg:city":"Columbus",
    "sg:classifiers":[
        {
            "category":"Utilities",
            "subcategory":"Refuse",
            "type":"Services"
        }
    ],
    "sg:phone":"+1 609 261 0556",
    "sg:postcode":"08022",
    "sg:province":"NJ",
    "sg:tags":[
        "garbage",
        "collection"
    ],
    "wof:name":"Garden State Removal Co",
    "wof:placetype":"venue"
},
  "geometry": {"coordinates":[-74.73247000000001,40.041516],"type":"Point"}
}