{
  "type": "Feature",
  "properties": {
    "iso:country":"US",
    "sg:address":"330 Passaic St",
    "sg:city":"Passaic",
    "sg:classifiers":[
        {
            "category":"Professional",
            "subcategory":"Lawyer & Legal Services",
            "type":"Services"
        }
    ],
    "sg:phone":"+1   ",
    "sg:postcode":"07055",
    "sg:province":"NJ",
    "sg:tags":[
        "department"
    ],
    "wof:name":"Passaic Legal Department",
    "wof:placetype":"venue"
},
  "geometry": {"coordinates":[-74.124082,40.860198],"type":"Point"}
}