{
  "type": "Feature",
  "properties": {
    "iso:country":"US",
    "sg:address":"281 Heath Village",
    "sg:city":"Hackettstown",
    "sg:classifiers":[
        {
            "category":"Professional",
            "subcategory":"Engineering",
            "type":"Services"
        }
    ],
    "sg:phone":"+1 908 850 3435",
    "sg:postcode":"07840",
    "sg:province":"NJ",
    "wof:name":"Engineers Associated",
    "wof:placetype":"venue"
},
  "geometry": {"coordinates":[-74.82175599999999,40.821796],"type":"Point"}
}