{
  "type": "Feature",
  "properties": {
    "addr:full":"107 Taunton Lake Rd Marlton NJ 08053",
    "addr:housenumber":"107",
    "addr:postcode":"08053",
    "addr:street":"Taunton Lake Rd",
    "iso:country":"US",
    "sg:address":"107 Taunton Lake Rd",
    "sg:city":"Marlton",
    "sg:classifiers":[
        {
            "category":"Professional",
            "type":"Services"
        }
    ],
    "sg:phone":"+1 856 810 7877",
    "sg:postcode":"08053",
    "sg:province":"NJ",
    "sg:tags":[
        "establishment"
    ],
    "wof:name":"Brick & Prime Enterprises LLC",
    "wof:placetype":"venue"
},
  "geometry": {"coordinates":[-74.8927,39.866639],"type":"Point"}
}