{
  "type": "Feature",
  "properties": {
    "iso:country":"US",
    "sg:address":"160 Overlook Ave",
    "sg:city":"Hackensack",
    "sg:classifiers":[
        {
            "category":"Real Estate",
            "subcategory":"Real Estate Agent",
            "type":"Services"
        }
    ],
    "sg:phone":"+1   ",
    "sg:postcode":"07601",
    "sg:province":"NJ",
    "wof:name":"Mark Birnholz",
    "wof:placetype":"venue"
},
  "geometry": {"coordinates":[-74.054543,40.887739],"type":"Point"}
}