{
  "type": "Feature",
  "properties": {
    "iso:country":"US",
    "sg:address":"400 Paterson Plank Rd",
    "sg:city":"Carlstadt",
    "sg:classifiers":[
        {
            "category":"Wholesale",
            "subcategory":"Chemicals & Plastics",
            "type":"Manufacturing & Wholesale Goods"
        }
    ],
    "sg:phone":"+1 201 933 0600",
    "sg:postcode":"07072",
    "sg:province":"NJ",
    "sg:tags":[
        "silicone",
        "fluorocarbon",
        "polyurethane"
    ],
    "wof:name":"Advanced Polymer Inc",
    "wof:placetype":"venue"
},
  "geometry": {"coordinates":[-74.065511,40.815821],"type":"Point"}
}