{
  "type": "Feature",
  "properties": {
    "iso:country":"US",
    "sg:address":"1214 Riverside Ave",
    "sg:city":"Trenton",
    "sg:classifiers":[
        {
            "category":"Building & Trades",
            "subcategory":"Cleaning & Sanitation",
            "type":"Services"
        }
    ],
    "sg:phone":"+1 609 393 0940",
    "sg:postcode":"08618",
    "sg:province":"NJ",
    "sg:tags":[
        "janitor",
        "maintenance"
    ],
    "wof:name":"Sweet Home Cleaning Service",
    "wof:placetype":"venue"
},
  "geometry": {"coordinates":[-74.79598,40.232955],"type":"Point"}
}