{
  "type": "Feature",
  "properties": {
    "iso:country":"US",
    "sg:address":"203 Main St",
    "sg:city":"Flemington",
    "sg:classifiers":[
        {
            "category":"Professional",
            "subcategory":"Computer Services",
            "type":"Services"
        }
    ],
    "sg:phone":"+1   ",
    "sg:postcode":"08822",
    "sg:province":"NJ",
    "sg:tags":[
        "agency",
        "employment",
        "programing",
        "custom"
    ],
    "wof:name":"Xeryis Inc",
    "wof:placetype":"venue"
},
  "geometry": {"coordinates":[-74.858125,40.50295],"type":"Point"}
}