{
  "type": "Feature",
  "properties": {
    "addr:full":"1 Well Dr Fair Lawn NJ 07410",
    "addr:housenumber":"1",
    "addr:postcode":"07410",
    "addr:street":"Well Dr",
    "iso:country":"US",
    "sg:address":"1 Well Dr",
    "sg:city":"Fair Lawn",
    "sg:classifiers":[
        {
            "category":"Building & Trades",
            "subcategory":"Construction",
            "type":"Services"
        }
    ],
    "sg:phone":"+1 201 703 1277",
    "sg:postcode":"07410",
    "sg:province":"NJ",
    "sg:tags":[
        "carpentry",
        "contractor"
    ],
    "wof:name":"John A Krenrich & Son Inc",
    "wof:placetype":"venue"
},
  "geometry": {"coordinates":[-74.111155,40.942803],"type":"Point"}
}