{
  "type": "Feature",
  "properties": {
    "iso:country":"US",
    "sg:address":"213 Washington St",
    "sg:city":"Newark",
    "sg:classifiers":[
        {
            "category":"Real Estate",
            "subcategory":"Real Estate Agent",
            "type":"Services"
        }
    ],
    "sg:phone":"+1   ",
    "sg:postcode":"07102",
    "sg:province":"NJ",
    "wof:name":"Capital Agricultural Property",
    "wof:placetype":"venue"
},
  "geometry": {"coordinates":[-74.174339,40.73763],"type":"Point"}
}