{
  "type": "Feature",
  "properties": {
    "addr:full":"228 Lafayette St Newark NJ 07105",
    "addr:housenumber":"228",
    "addr:postcode":"07105",
    "addr:street":"Lafayette St",
    "iso:country":"US",
    "sg:address":"228 Lafayette St",
    "sg:city":"Newark",
    "sg:classifiers":[
        {
            "category":"Shopping",
            "subcategory":"Clothing, Apparel, & Fashions",
            "type":"Retail Goods"
        }
    ],
    "sg:phone":"+1   ",
    "sg:postcode":"07105",
    "sg:province":"NJ",
    "wof:name":"Family Care Center At St James",
    "wof:placetype":"venue"
},
  "geometry": {"coordinates":[-74.162741,40.729065],"type":"Point"}
}