{
  "type": "Feature",
  "properties": {
    "addr:full":"198 State Rte 73 Berlin NJ 08009",
    "addr:housenumber":"198",
    "addr:postcode":"08009",
    "addr:street":"State Rte 73",
    "iso:country":"US",
    "sg:address":"198 State Rte 73",
    "sg:city":"Berlin",
    "sg:classifiers":[
        {
            "category":"Retail",
            "subcategory":"Auto Rental",
            "type":"Services"
        }
    ],
    "sg:phone":"+1 856 753 4413",
    "sg:postcode":"08009",
    "sg:province":"NJ",
    "sg:tags":[
        "renting",
        "automobile",
        "passenger",
        "car"
    ],
    "wof:name":"Enterprise Rent-A-Car",
    "wof:placetype":"venue"
},
  "geometry": {"coordinates":[-74.92524899999999,39.796856],"type":"Point"}
}