{
  "type": "Feature",
  "properties": {
    "iso:country":"US",
    "sg:address":"868 Broad St",
    "sg:city":"Teaneck",
    "sg:classifiers":[
        {
            "category":"Home & Garden",
            "subcategory":"Home Furnishings",
            "type":"Retail Goods"
        }
    ],
    "sg:phone":"+1 718 753 6148",
    "sg:postcode":"07666",
    "sg:province":"NJ",
    "sg:tags":[
        "decor"
    ],
    "wof:name":"Adam's Urns",
    "wof:placetype":"venue"
},
  "geometry": {"coordinates":[-74.007807,40.886596],"type":"Point"}
}