{
  "type": "Feature",
  "properties": {
    "addr:full":"303 Cindy St Old Bridge NJ 08857",
    "addr:housenumber":"303",
    "addr:postcode":"08857",
    "addr:street":"Cindy St",
    "iso:country":"US",
    "sg:address":"303 Cindy St",
    "sg:city":"Old Bridge",
    "sg:classifiers":[
        {
            "category":"Professional",
            "type":"Services"
        }
    ],
    "sg:phone":"+1   ",
    "sg:postcode":"08857",
    "sg:province":"NJ",
    "wof:name":"MTI Inc",
    "wof:placetype":"venue"
},
  "geometry": {"coordinates":[-74.33578799999999,40.400367],"type":"Point"}
}