{
  "type": "Feature",
  "properties": {
    "iso:country":"US",
    "sg:address":"41 Genesee Ave",
    "sg:city":"Teaneck",
    "sg:classifiers":[
        {
            "category":"Professional",
            "type":"Services"
        }
    ],
    "sg:phone":"+1 201 447 7469",
    "sg:postcode":"07666",
    "sg:province":"NJ",
    "sg:tags":[
        "environmental",
        "ecological",
        "product"
    ],
    "wof:name":"Ncgcc",
    "wof:placetype":"venue"
},
  "geometry": {"coordinates":[-73.99765600000001,40.895641],"type":"Point"}
}