{
  "type": "Feature",
  "properties": {
    "iso:country":"US",
    "sg:address":"86 Sterling Avenue",
    "sg:city":"Weehawken",
    "sg:classifiers":[
        {
            "category":"Health Services",
            "subcategory":"Clinic",
            "type":"Services"
        }
    ],
    "sg:phone":"+1 917 841 8121",
    "sg:postcode":"07086",
    "sg:province":"NJ",
    "sg:tags":[
        "medical"
    ],
    "sg:website":"www.pptswellness.com",
    "wof:name":"PPTS Wellness",
    "wof:placetype":"venue"
},
  "geometry": {"coordinates":[-74.02140900000001,40.769944],"type":"Point"}
}