{
  "type": "Feature",
  "properties": {
    "iso:country":"US",
    "sg:address":"999 Mount Kemble Ave",
    "sg:city":"Morristown",
    "sg:classifiers":[
        {
            "category":"Professional",
            "subcategory":"Computer Services",
            "type":"Services"
        }
    ],
    "sg:phone":"+1   ",
    "sg:postcode":"07960",
    "sg:province":"NJ",
    "sg:tags":[
        "related"
    ],
    "wof:name":"Wilfred Dy",
    "wof:placetype":"venue"
},
  "geometry": {"coordinates":[-74.532748,40.745342],"type":"Point"}
}