{
  "type": "Feature",
  "properties": {
    "addr:full":"247 Whippany Rd Whippany NJ 07981",
    "addr:housenumber":"247",
    "addr:postcode":"07981",
    "addr:street":"Whippany Rd",
    "iso:country":"US",
    "sg:address":"247 Whippany Rd",
    "sg:city":"Whippany",
    "sg:classifiers":[
        {
            "category":"Building & Trades",
            "subcategory":"Construction",
            "type":"Services"
        }
    ],
    "sg:phone":"+1 973 887 2150",
    "sg:postcode":"07981",
    "sg:province":"NJ",
    "sg:tags":[
        "excavating",
        "contractor"
    ],
    "wof:name":"Underhill Excavating Corp",
    "wof:placetype":"venue"
},
  "geometry": {"coordinates":[-74.431861,40.809964],"type":"Point"}
}