{
  "type": "Feature",
  "properties": {
    "addr:full":"24 Euchner Ln Trenton NJ 08638",
    "addr:housenumber":"24",
    "addr:postcode":"08638",
    "addr:street":"Euchner Ln",
    "iso:country":"US",
    "sg:address":"24 Euchner Ln",
    "sg:city":"Trenton",
    "sg:classifiers":[
        {
            "category":"Bus Charters",
            "type":"Transportation"
        }
    ],
    "sg:phone":"+1 609 771 0399",
    "sg:postcode":"08638",
    "sg:province":"NJ",
    "sg:tags":[
        "rental"
    ],
    "wof:name":"Earl D Stires Bus Co",
    "wof:placetype":"venue"
},
  "geometry": {"coordinates":[-74.754874,40.272112],"type":"Point"}
}