{
  "type": "Feature",
  "properties": {
    "addr:full":"83 Summit Ave Berkeley Heights NJ 07922",
    "addr:housenumber":"83",
    "addr:postcode":"07922",
    "addr:street":"Summit Ave",
    "iso:country":"US",
    "sg:address":"83 Summit Ave",
    "sg:city":"Berkeley Heights",
    "sg:classifiers":[
        {
            "category":"Utilities",
            "subcategory":"Telephone",
            "type":"Services"
        }
    ],
    "sg:phone":"+1 908 286 0101",
    "sg:postcode":"07922",
    "sg:province":"NJ",
    "sg:tags":[
        "communications"
    ],
    "wof:name":"011 Glbal Comm Intrgrated Tech",
    "wof:placetype":"venue"
},
  "geometry": {"coordinates":[-74.44165099999999,40.685071],"type":"Point"}
}