{
  "type": "Feature",
  "properties": {
    "addr:full":"142 W End Ct Long Branch NJ 07740",
    "addr:housenumber":"142",
    "addr:postcode":"07740",
    "addr:street":"W End Ct",
    "iso:country":"US",
    "sg:address":"142 W End Ct",
    "sg:city":"Long Branch",
    "sg:classifiers":[
        {
            "category":"Retail",
            "subcategory":"Laundry & Dry Cleaning",
            "type":"Services"
        }
    ],
    "sg:phone":"+1 732 870 0037",
    "sg:postcode":"07740",
    "sg:province":"NJ",
    "sg:tags":[
        "garment",
        "agent",
        "cleaners"
    ],
    "wof:name":"Sands Dry Cleaners Inc",
    "wof:placetype":"venue"
},
  "geometry": {"coordinates":[-73.988541,40.283751],"type":"Point"}
}