{
  "type": "Feature",
  "properties": {
    "addr:full":"2812 Morris Ave Union NJ 07083",
    "addr:housenumber":"2812",
    "addr:postcode":"07083",
    "addr:street":"Morris Ave",
    "iso:country":"US",
    "sg:address":"2812 Morris Ave",
    "sg:city":"Union",
    "sg:classifiers":[
        {
            "category":"Health Services",
            "subcategory":"Dentist",
            "type":"Services"
        }
    ],
    "sg:phone":"+1 908 810 8887",
    "sg:postcode":"07083",
    "sg:province":"NJ",
    "sg:website":"dentistunion-nj.com/",
    "wof:name":"Marianella Ramirez \u00a0PA, DDS",
    "wof:placetype":"venue"
},
  "geometry": {"coordinates":[-74.299645,40.706885],"type":"Point"}
}