{
  "type": "Feature",
  "properties": {
    "addr:full":"200 S Jefferson Ave Wenonah NJ 08090",
    "addr:housenumber":"200",
    "addr:postcode":"08090",
    "addr:street":"S Jefferson Ave",
    "iso:country":"US",
    "sg:address":"200 S Jefferson Ave",
    "sg:city":"Wenonah",
    "sg:classifiers":[
        {
            "category":"Home & Garden",
            "subcategory":"Home Furnishings",
            "type":"Retail Goods"
        }
    ],
    "sg:phone":"+1 856 464 2746",
    "sg:postcode":"08090",
    "sg:province":"NJ",
    "sg:tags":[
        "pottery"
    ],
    "wof:name":"Clayhill Pottery",
    "wof:placetype":"venue"
},
  "geometry": {"coordinates":[-75.153201,39.786826],"type":"Point"}
}