{
  "type": "Feature",
  "properties": {
    "addr:full":"18 Orange Pl West Orange NJ 07052",
    "addr:housenumber":"18",
    "addr:postcode":"07052",
    "addr:street":"Orange Pl",
    "iso:country":"US",
    "sg:address":"18 Orange Pl",
    "sg:city":"West Orange",
    "sg:classifiers":[
        {
            "category":"Professional",
            "type":"Services"
        }
    ],
    "sg:phone":"+1   ",
    "sg:postcode":"07052",
    "sg:province":"NJ",
    "wof:name":"Paul Paris",
    "wof:placetype":"venue"
},
  "geometry": {"coordinates":[-74.23177,40.79279],"type":"Point"}
}