{
  "type": "Feature",
  "properties": {
    "addr:full":"521 E Main St Maple Shade NJ 08052",
    "addr:housenumber":"521",
    "addr:postcode":"08052",
    "addr:street":"E Main St",
    "iso:country":"US",
    "sg:address":"521 E Main St",
    "sg:city":"Maple Shade",
    "sg:classifiers":[
        {
            "category":"Freight",
            "type":"Transportation"
        }
    ],
    "sg:phone":"+1 856 667 3193",
    "sg:postcode":"08052",
    "sg:province":"NJ",
    "sg:tags":[
        "operator",
        "local",
        "trucking"
    ],
    "wof:name":"Rush Delivery",
    "wof:placetype":"venue"
},
  "geometry": {"coordinates":[-74.99462699999999,39.956101],"type":"Point"}
}