{
  "type": "Feature",
  "properties": {
    "iso:country":"US",
    "sg:address":"25 Philips Pkwy",
    "sg:city":"Montvale",
    "sg:classifiers":[
        {
            "category":"Real Estate",
            "subcategory":"Real Estate Agent",
            "type":"Services"
        }
    ],
    "sg:phone":"+1 201 666 4333",
    "sg:postcode":"07645",
    "sg:province":"NJ",
    "wof:name":"Services National Realty Title",
    "wof:placetype":"venue"
},
  "geometry": {"coordinates":[-74.061947,41.04726],"type":"Point"}
}