{
  "type": "Feature",
  "properties": {
    "addr:full":"87 Clinton Rd Fairfield NJ 07004",
    "addr:housenumber":"87",
    "addr:postcode":"07004",
    "addr:street":"Clinton Rd",
    "iso:country":"US",
    "sg:address":"87 Clinton Rd",
    "sg:city":"Fairfield",
    "sg:classifiers":[
        {
            "category":"Manufacturing",
            "subcategory":"Tools & Machinery",
            "type":"Manufacturing & Wholesale Goods"
        }
    ],
    "sg:phone":"+1 973 808 4455",
    "sg:postcode":"07004",
    "sg:province":"NJ",
    "sg:tags":[
        "machine",
        "mfg",
        "accessory"
    ],
    "wof:name":"Bawa Machine & Tool Mfg",
    "wof:placetype":"venue"
},
  "geometry": {"coordinates":[-74.31032999999999,40.857777],"type":"Point"}
}