{
  "type": "Feature",
  "properties": {
    "addr:full":"10 State Rte 35 Red Bank NJ 07701",
    "addr:housenumber":"10",
    "addr:postcode":"07701",
    "addr:street":"State Rte 35",
    "iso:country":"US",
    "sg:address":"10 State Rte 35",
    "sg:city":"Red Bank",
    "sg:classifiers":[
        {
            "category":"Real Estate",
            "subcategory":"Real Estate Operator",
            "type":"Services"
        }
    ],
    "sg:phone":"+1 732 747 7812",
    "sg:postcode":"07701",
    "sg:province":"NJ",
    "sg:tags":[
        "building",
        "parks"
    ],
    "wof:name":"Riverway Office Building",
    "wof:placetype":"venue"
},
  "geometry": {"coordinates":[-74.075507,40.35162],"type":"Point"}
}