{
  "type": "Feature",
  "properties": {
    "addr:full":"201 State Rte 70 Lakehurst NJ 08733",
    "addr:housenumber":"201",
    "addr:postcode":"08733",
    "addr:street":"State Rte 70",
    "iso:country":"US",
    "sg:address":"201 State Rte 70",
    "sg:city":"Lakehurst",
    "sg:classifiers":[
        {
            "category":"Retail",
            "subcategory":"Auto Repair",
            "type":"Services"
        }
    ],
    "sg:phone":"+1 732 657 2223",
    "sg:postcode":"08733",
    "sg:province":"NJ",
    "sg:tags":[
        "automotive"
    ],
    "wof:name":"Unique Automotive & Lube Inc",
    "wof:placetype":"venue"
},
  "geometry": {"coordinates":[-74.316778,40.014741],"type":"Point"}
}