{
  "type": "Feature",
  "properties": {
    "iso:country":"US",
    "sg:address":"14 Washington Rd",
    "sg:city":"Princeton Junction",
    "sg:classifiers":[
        {
            "category":"Professional",
            "subcategory":"Engineering",
            "type":"Services"
        }
    ],
    "sg:phone":"+1   ",
    "sg:postcode":"08550",
    "sg:province":"NJ",
    "sg:tags":[
        "environmental"
    ],
    "wof:name":"Mactec Engrg & Consulting",
    "wof:placetype":"venue"
},
  "geometry": {"coordinates":[-74.627517,40.323262],"type":"Point"}
}