{
  "type": "Feature",
  "properties": {
    "addr:full":"322 US Highway 46 Ste 210 Parsippany NJ 07054",
    "addr:housenumber":"322",
    "addr:postcode":"07054",
    "addr:street":"Us Highway 46 Ste 210",
    "iso:country":"US",
    "sg:address":"322 US Highway 46 Ste 210",
    "sg:city":"Parsippany",
    "sg:classifiers":[
        {
            "category":"Professional",
            "subcategory":"Lawyer & Legal Services",
            "type":"Services"
        }
    ],
    "sg:phone":"+1 973 227 5553",
    "sg:postcode":"07054",
    "sg:province":"NJ",
    "wof:name":"Markus & Cohen ESQ",
    "wof:placetype":"venue"
},
  "geometry": {"coordinates":[-74.35900100000001,40.8592],"type":"Point"}
}