{
  "type": "Feature",
  "properties": {
    "iso:country":"US",
    "sg:address":"620 W Clements Bridge Rd",
    "sg:city":"Runnemede",
    "sg:classifiers":[
        {
            "category":"Home & Garden",
            "subcategory":"Home Furnishings",
            "type":"Retail Goods"
        },
        {
            "category":"Wholesale",
            "subcategory":"Home Furnishings",
            "type":"Manufacturing & Wholesale Goods"
        }
    ],
    "sg:phone":"+1 856 939 2212",
    "sg:postcode":"08078",
    "sg:province":"NJ",
    "sg:tags":[
        "blind",
        "draperies",
        "installation",
        "vertical",
        "curtains",
        "blinds-venetian",
        "window",
        "treatment",
        "shade",
        "shades-wholesale",
        "curtain",
        "manufacturer"
    ],
    "sg:website":"http://www.danielsdrapes.com/",
    "wof:name":"Daniel's Custom Drapery Manufacturing Inc",
    "wof:placetype":"venue"
},
  "geometry": {"coordinates":[-75.08184799999999,39.841869],"type":"Point"}
}