{
  "type": "Feature",
  "properties": {
    "addr:full":"442 State Rte 35 Eatontown NJ 07724",
    "addr:housenumber":"442",
    "addr:postcode":"07724",
    "addr:street":"State Rte 35",
    "iso:country":"US",
    "sg:address":"442 State Rte 35",
    "sg:city":"Eatontown",
    "sg:classifiers":[
        {
            "category":"Wholesale",
            "subcategory":"Home Furnishings",
            "type":"Manufacturing & Wholesale Goods"
        }
    ],
    "sg:phone":"+1 732 389 5507",
    "sg:postcode":"07724",
    "sg:province":"NJ",
    "sg:tags":[
        "flatware",
        "kitchen"
    ],
    "wof:name":"Hampton Forge Ltd",
    "wof:placetype":"venue"
},
  "geometry": {"coordinates":[-74.04355700000001,40.273615],"type":"Point"}
}