{
  "type": "Feature",
  "properties": {
    "addr:full":"401 Main St Bradley Beach NJ 07720",
    "addr:housenumber":"401",
    "addr:postcode":"07720",
    "addr:street":"Main St",
    "iso:country":"US",
    "sg:address":"401 Main St",
    "sg:city":"Bradley Beach",
    "sg:classifiers":[
        {
            "category":"Restaurant",
            "type":"Food & Drink"
        }
    ],
    "sg:phone":"+1   ",
    "sg:postcode":"07720",
    "sg:province":"NJ",
    "sg:tags":[
        "eating"
    ],
    "wof:name":"Francos Bistro",
    "wof:placetype":"venue"
},
  "geometry": {"coordinates":[-74.018327,40.202099],"type":"Point"}
}