{
  "type": "Feature",
  "properties": {
    "iso:country":"US",
    "sg:address":"800 Summit Ave",
    "sg:city":"River Edge",
    "sg:classifiers":[
        {
            "category":"Real Estate",
            "subcategory":"Real Estate Agent",
            "type":"Services"
        }
    ],
    "sg:phone":"+1   ",
    "sg:postcode":"07661",
    "sg:province":"NJ",
    "wof:name":"Bergen Boat Landing Inc",
    "wof:placetype":"venue"
},
  "geometry": {"coordinates":[-74.032212,40.937595],"type":"Point"}
}