{
  "type": "Feature",
  "properties": {
    "addr:full":"290 Changebridge Rd Pine Brook NJ 07058",
    "addr:housenumber":"290",
    "addr:postcode":"07058",
    "addr:street":"Changebridge Rd",
    "iso:country":"US",
    "sg:address":"290 Changebridge Rd",
    "sg:city":"Pine Brook",
    "sg:phone":"+1 973 227 0294",
    "sg:postcode":"07058",
    "sg:province":"NJ",
    "sg:tags":[
        "farm",
        "fruit",
        "tree",
        "orchard"
    ],
    "wof:name":"Bader Frms HM Grown Prod Plnts",
    "wof:placetype":"venue"
},
  "geometry": {"coordinates":[-74.357867,40.869726],"type":"Point"}
}