{
  "type": "Feature",
  "properties": {
    "addr:full":"11 Bergen Ave Waldwick NJ 07463",
    "addr:housenumber":"11",
    "addr:postcode":"07463",
    "addr:street":"Bergen Ave",
    "iso:country":"US",
    "sg:address":"11 Bergen Ave",
    "sg:city":"Waldwick",
    "sg:classifiers":[
        {
            "category":"Building & Trades",
            "subcategory":"Construction",
            "type":"Services"
        }
    ],
    "sg:phone":"+1 201 612 8390",
    "sg:postcode":"07463",
    "sg:province":"NJ",
    "sg:tags":[
        "house"
    ],
    "wof:name":"Biango Home Improvements",
    "wof:placetype":"venue"
},
  "geometry": {"coordinates":[-74.118622,41.015238],"type":"Point"}
}