{
  "type": "Feature",
  "properties": {
    "addr:full":"95 Christopher Mill Rd Medford NJ 08055",
    "addr:housenumber":"95",
    "addr:postcode":"08055",
    "addr:street":"Christopher Mill Rd",
    "iso:country":"US",
    "sg:address":"95 Christopher Mill Rd",
    "sg:city":"Medford",
    "sg:classifiers":[
        {
            "category":"Professional",
            "subcategory":"Business Services",
            "type":"Services"
        }
    ],
    "sg:phone":"+1 609 654 1855",
    "sg:postcode":"08055",
    "sg:province":"NJ",
    "wof:name":"Femiano Enterprises",
    "wof:placetype":"venue"
},
  "geometry": {"coordinates":[-74.854083,39.883532],"type":"Point"}
}