{
  "type": "Feature",
  "properties": {
    "iso:country":"US",
    "sg:address":"314 Chestnut St",
    "sg:city":"Roselle Park",
    "sg:classifiers":[
        {
            "category":"Government",
            "subcategory":"Office",
            "type":"Public Place"
        }
    ],
    "sg:phone":"+1 908 245 9150",
    "sg:postcode":"07204",
    "sg:province":"NJ",
    "sg:tags":[
        "village"
    ],
    "wof:name":"Roselle Park Adm Assistant",
    "wof:placetype":"venue"
},
  "geometry": {"coordinates":[-74.264876,40.665149],"type":"Point"}
}