{
  "type": "Feature",
  "properties": {
    "iso:country":"US",
    "sg:address":"203 Sunset Rd",
    "sg:city":"Burlington",
    "sg:classifiers":[
        {
            "category":"Organizations",
            "subcategory":"Religious Organization",
            "type":"Services"
        }
    ],
    "sg:phone":"+1   ",
    "sg:postcode":"08016",
    "sg:province":"NJ",
    "wof:name":"Haitian Baptist Church Inc",
    "wof:placetype":"venue"
},
  "geometry": {"coordinates":[-74.843824,40.050499],"type":"Point"}
}