{
  "type": "Feature",
  "properties": {
    "addr:full":"414 Main St Chatham NJ 07928",
    "addr:housenumber":"414",
    "addr:postcode":"07928",
    "addr:street":"Main St",
    "iso:country":"US",
    "sg:address":"414 Main St",
    "sg:city":"Chatham",
    "sg:classifiers":[
        {
            "category":"Organizations",
            "subcategory":"Professional Association",
            "type":"Services"
        }
    ],
    "sg:phone":"+1 973 635 2444",
    "sg:postcode":"07928",
    "sg:province":"NJ",
    "sg:tags":[
        "chambers",
        "commerce"
    ],
    "wof:name":"Chamber Of Commerce",
    "wof:placetype":"venue"
},
  "geometry": {"coordinates":[-74.389788,40.743434],"type":"Point"}
}