{
  "type": "Feature",
  "properties": {
    "addr:full":"305 N High St Millville NJ 08332",
    "addr:housenumber":"305",
    "addr:postcode":"08332",
    "addr:street":"N High St",
    "iso:country":"US",
    "sg:address":"305 N High St",
    "sg:city":"Millville",
    "sg:classifiers":[
        {
            "category":"Personal",
            "subcategory":"Beauty Salon",
            "type":"Services"
        },
        {
            "category":"Personal",
            "subcategory":"Nail Salon",
            "type":"Services"
        }
    ],
    "sg:phone":"+1 856 293 1290",
    "sg:postcode":"08332",
    "sg:province":"NJ",
    "wof:name":"La Nails Salon",
    "wof:placetype":"venue"
},
  "geometry": {"coordinates":[-75.038487,39.398437],"type":"Point"}
}