{
  "type": "Feature",
  "properties": {
    "iso:country":"US",
    "sg:address":"299 Smith Rd",
    "sg:city":"Parsippany",
    "sg:classifiers":[
        {
            "category":"Travel",
            "subcategory":"Hotels & Motels",
            "type":"Entertainment"
        }
    ],
    "sg:phone":"+1 973 428 8875",
    "sg:postcode":"07054",
    "sg:province":"NJ",
    "sg:website":"www.hotel-sierra.com",
    "wof:name":"Hotel Sierra Parsippany",
    "wof:placetype":"venue"
},
  "geometry": {"coordinates":[-74.41240999999999,40.859911],"type":"Point"}
}