{
  "type": "Feature",
  "properties": {
    "iso:country":"US",
    "sg:address":"128 Cynthia Dr",
    "sg:city":"Hackettstown",
    "sg:classifiers":[
        {
            "category":"Retail",
            "subcategory":"Repair Shop",
            "type":"Services"
        }
    ],
    "sg:phone":"+1   ",
    "sg:postcode":"07840",
    "sg:province":"NJ",
    "wof:name":"Franco Complete Drain Cleaning",
    "wof:placetype":"venue"
},
  "geometry": {"coordinates":[-74.841992,40.833112],"type":"Point"}
}