{
  "type": "Feature",
  "properties": {
    "iso:country":"US",
    "sg:address":"229 N Warren St",
    "sg:city":"Trenton",
    "sg:classifiers":[
        {
            "category":"Professional",
            "subcategory":"Management & Consulting",
            "type":"Services"
        }
    ],
    "sg:phone":"+1   ",
    "sg:postcode":"08618",
    "sg:province":"NJ",
    "wof:name":"El Jay International Trade",
    "wof:placetype":"venue"
},
  "geometry": {"coordinates":[-74.765485,40.223065],"type":"Point"}
}