{
  "type": "Feature",
  "properties": {
    "iso:country":"US",
    "sg:address":"425 Sanford Ave",
    "sg:city":"Newark",
    "sg:classifiers":[
        {
            "category":"Social Services",
            "type":"Services"
        }
    ],
    "sg:phone":"+1 973 371 5711",
    "sg:postcode":"07106",
    "sg:province":"NJ",
    "sg:tags":[
        "senior",
        "citizen"
    ],
    "wof:name":"St Mary's Villa",
    "wof:placetype":"venue"
},
  "geometry": {"coordinates":[-74.232117,40.748095],"type":"Point"}
}