{
  "type": "Feature",
  "properties": {
    "addr:full":"498 Fairview Ave Orange NJ 07050",
    "addr:housenumber":"498",
    "addr:postcode":"07050",
    "addr:street":"Fairview Ave",
    "iso:country":"US",
    "sg:address":"498 Fairview Ave",
    "sg:city":"Orange",
    "sg:classifiers":[
        {
            "category":"Building & Trades",
            "subcategory":"Electrical",
            "type":"Services"
        }
    ],
    "sg:phone":"+1 973 674 0760",
    "sg:postcode":"07050",
    "sg:province":"NJ",
    "sg:tags":[
        "electrical",
        "contractor"
    ],
    "wof:name":"B Electric Service Corp",
    "wof:placetype":"venue"
},
  "geometry": {"coordinates":[-74.244429,40.762801],"type":"Point"}
}