{
  "type": "Feature",
  "properties": {
    "iso:country":"US",
    "sg:address":"1070 Delsea Dr",
    "sg:city":"Westville",
    "sg:classifiers":[
        {
            "category":"Shopping",
            "subcategory":"Discount & Variety Stores",
            "type":"Retail Goods"
        }
    ],
    "sg:phone":"+1 856 384 0096",
    "sg:postcode":"08093",
    "sg:province":"NJ",
    "wof:name":"United Dollar Plus",
    "wof:placetype":"venue"
},
  "geometry": {"coordinates":[-75.125204,39.85348],"type":"Point"}
}