{
  "type": "Feature",
  "properties": {
    "iso:country":"US",
    "sg:address":"108 N Main St",
    "sg:city":"Cape May Ct Hse",
    "sg:classifiers":[
        {
            "category":"Health Services",
            "subcategory":"Doctor",
            "type":"Services"
        }
    ],
    "sg:phone":"+1 609 465 9359",
    "sg:postcode":"08210",
    "sg:province":"NJ",
    "sg:tags":[
        "physician",
        "surgeon"
    ],
    "wof:name":"Somers Manor Obstetrics & Gyn",
    "wof:placetype":"venue"
},
  "geometry": {"coordinates":[-74.820858,39.085407],"type":"Point"}
}