{
  "type": "Feature",
  "properties": {
    "addr:full":"1636 State Rte 27 Edison NJ 08817",
    "addr:housenumber":"1636",
    "addr:postcode":"08817",
    "addr:street":"State Rte 27",
    "iso:country":"US",
    "sg:address":"1636 State Rte 27",
    "sg:city":"Edison",
    "sg:classifiers":[
        {
            "category":"Building & Trades",
            "subcategory":"Construction",
            "type":"Services"
        },
        {
            "category":"Wholesale",
            "subcategory":"Home Furnishings",
            "type":"Manufacturing & Wholesale Goods"
        }
    ],
    "sg:phone":"+1 732 777 0442",
    "sg:postcode":"08817",
    "sg:province":"NJ",
    "sg:tags":[
        "general",
        "contractor"
    ],
    "wof:name":"Dyna Star Designs Inc",
    "wof:placetype":"venue"
},
  "geometry": {"coordinates":[-74.41036800000001,40.509451],"type":"Point"}
}