{
  "type": "Feature",
  "properties": {
    "addr:full":"15 Warren St Hackensack NJ 07601",
    "addr:housenumber":"15",
    "addr:postcode":"07601",
    "addr:street":"Warren St",
    "iso:country":"US",
    "sg:address":"15 Warren St",
    "sg:city":"Hackensack",
    "sg:classifiers":[
        {
            "category":"Real Estate",
            "subcategory":"Real Estate Agent",
            "type":"Services"
        }
    ],
    "sg:phone":"+1   ",
    "sg:postcode":"07601",
    "sg:province":"NJ",
    "wof:name":"Daniel Properties LLC",
    "wof:placetype":"venue"
},
  "geometry": {"coordinates":[-74.04544,40.881415],"type":"Point"}
}