{
  "type": "Feature",
  "properties": {
    "addr:full":"222 Grand St Hoboken NJ 07030",
    "addr:housenumber":"222",
    "addr:postcode":"07030",
    "addr:street":"Grand St",
    "iso:country":"US",
    "sg:address":"222 Grand St",
    "sg:city":"Hoboken",
    "sg:classifiers":[
        {
            "category":"Professional",
            "subcategory":"Management & Consulting",
            "type":"Services"
        }
    ],
    "sg:phone":"+1 201 418 9101",
    "sg:postcode":"07030",
    "sg:province":"NJ",
    "sg:tags":[
        "consultant"
    ],
    "wof:name":"Andrew Chaves Consulting",
    "wof:placetype":"venue"
},
  "geometry": {"coordinates":[-74.035752,40.74067],"type":"Point"}
}