{
  "type": "Feature",
  "properties": {
    "iso:country":"US",
    "sg:address":"2001 Delsea Dr",
    "sg:city":"Franklinville",
    "sg:classifiers":[
        {
            "category":"Restaurant",
            "type":"Food & Drink"
        }
    ],
    "sg:menulink":"http://www.allmenus.com/nj/franklin/82383-dominos-pizza/menu/",
    "sg:phone":"+1 856 694 5200",
    "sg:postcode":"08322",
    "sg:province":"NJ",
    "sg:tags":[
        "american",
        "wing",
        "pizza"
    ],
    "wof:name":"Domino's Pizza",
    "wof:placetype":"venue"
},
  "geometry": {"coordinates":[-75.070262,39.605561],"type":"Point"}
}