{
  "type": "Feature",
  "properties": {
    "addr:full":"99 N Dean St Englewood NJ 07631",
    "addr:housenumber":"99",
    "addr:postcode":"07631",
    "addr:street":"N Dean St",
    "iso:country":"US",
    "sg:address":"99 N Dean St",
    "sg:city":"Englewood",
    "sg:classifiers":[
        {
            "category":"Wholesale",
            "subcategory":"Electrical",
            "type":"Manufacturing & Wholesale Goods"
        }
    ],
    "sg:phone":"+1 201 569 5800",
    "sg:postcode":"07631",
    "sg:province":"NJ",
    "sg:tags":[
        "sell",
        "repair",
        "telephone"
    ],
    "wof:name":"International Business Phone",
    "wof:placetype":"venue"
},
  "geometry": {"coordinates":[-73.97252,40.896455],"type":"Point"}
}