{
  "type": "Feature",
  "properties": {
    "iso:country":"US",
    "sg:address":"234 State Rte 4",
    "sg:city":"Paramus",
    "sg:classifiers":[
        {
            "category":"Autos & Motor Vehicles",
            "subcategory":"Automobile Sales",
            "type":"Retail Goods"
        }
    ],
    "sg:phone":"+1   ",
    "sg:postcode":"07652",
    "sg:province":"NJ",
    "sg:tags":[
        "repair",
        "general"
    ],
    "wof:name":"Chrysler Plymouth Kia Paramus",
    "wof:placetype":"venue"
},
  "geometry": {"coordinates":[-74.053663,40.915836],"type":"Point"}
}