{
  "type": "Feature",
  "properties": {
    "iso:country":"US",
    "sg:address":"184 Monmouth St",
    "sg:city":"Red Bank",
    "sg:classifiers":[
        {
            "category":"Food & Beverages",
            "subcategory":"Liquor & Beverages",
            "type":"Retail Goods"
        }
    ],
    "sg:phone":"+1 732 842 9500",
    "sg:postcode":"07701",
    "sg:province":"NJ",
    "sg:tags":[
        "alcoholic"
    ],
    "wof:name":"Eiffel Liquors Inc",
    "wof:placetype":"venue"
},
  "geometry": {"coordinates":[-74.07507200000001,40.348742],"type":"Point"}
}