{
  "type": "Feature",
  "properties": {
    "addr:full":"372 Berdan Ave Wayne NJ 07470",
    "addr:housenumber":"372",
    "addr:postcode":"07470",
    "addr:street":"Berdan Ave",
    "iso:country":"US",
    "sg:address":"372 Berdan Ave",
    "sg:city":"Wayne",
    "sg:phone":"+1 973 694 3269",
    "sg:postcode":"07470",
    "sg:province":"NJ",
    "sg:tags":[
        "farm"
    ],
    "wof:name":"Corbett Bunton",
    "wof:placetype":"venue"
},
  "geometry": {"coordinates":[-74.239812,40.971698],"type":"Point"}
}