{
  "type": "Feature",
  "properties": {
    "iso:country":"US",
    "sg:address":"18 W Palisade Ave",
    "sg:city":"Englewood",
    "sg:classifiers":[
        {
            "category":"Building & Trades",
            "subcategory":"Construction",
            "type":"Services"
        }
    ],
    "sg:phone":"+1 201 816 0034",
    "sg:postcode":"07631",
    "sg:province":"NJ",
    "sg:tags":[
        "maintenance",
        "contractor"
    ],
    "wof:name":"National Maintenance Svc",
    "wof:placetype":"venue"
},
  "geometry": {"coordinates":[-73.97566,40.894261],"type":"Point"}
}