{
  "type": "Feature",
  "properties": {
    "addr:full":"1001 Durham Ave South Plainfield NJ 07080",
    "addr:housenumber":"1001",
    "addr:postcode":"07080",
    "addr:street":"Durham Ave",
    "iso:country":"US",
    "sg:address":"1001 Durham Ave",
    "sg:city":"South Plainfield",
    "sg:classifiers":[
        {
            "category":"Building & Trades",
            "subcategory":"Equipment Rental",
            "type":"Services"
        }
    ],
    "sg:phone":"+1   ",
    "sg:postcode":"07080",
    "sg:province":"NJ",
    "sg:tags":[
        "financing",
        "leasing"
    ],
    "sg:website":"www.fleetwoodonline.com",
    "wof:name":"Fleetwood Financial Corp",
    "wof:placetype":"venue"
},
  "geometry": {"coordinates":[-74.41074399999999,40.548469],"type":"Point"}
}