{
  "type": "Feature",
  "properties": {
    "addr:full":"24 Farmstead Dr Parsippany NJ 07054",
    "addr:housenumber":"24",
    "addr:postcode":"07054",
    "addr:street":"Farmstead Dr",
    "iso:country":"US",
    "sg:address":"24 Farmstead Dr",
    "sg:city":"Parsippany",
    "sg:classifiers":[
        {
            "category":"Professional",
            "subcategory":"Computer Services",
            "type":"Services"
        }
    ],
    "sg:phone":"+1 973 402 7452",
    "sg:postcode":"07054",
    "sg:province":"NJ",
    "wof:name":"On Call Computer Svc",
    "wof:placetype":"venue"
},
  "geometry": {"coordinates":[-74.388334,40.874342],"type":"Point"}
}