{
  "type": "Feature",
  "properties": {
    "iso:country":"US",
    "sg:address":"482 Notch Rd",
    "sg:city":"Clifton",
    "sg:classifiers":[
        {
            "category":"Building & Trades",
            "subcategory":"Locksmith",
            "type":"Services"
        }
    ],
    "sg:phone":"+1 973 854 5641",
    "sg:postcode":"07013",
    "sg:province":"NJ",
    "sg:tags":[
        "key"
    ],
    "wof:name":"1 24 Hour 7 Day A Lock A Locksmith",
    "wof:placetype":"venue"
},
  "geometry": {"coordinates":[-74.190529,40.872457],"type":"Point"}
}