{
  "type": "Feature",
  "properties": {
    "addr:full":"1079 US Highway 22 Mountainside NJ 07092",
    "addr:housenumber":"1079",
    "addr:postcode":"07092",
    "addr:street":"Us Highway 22",
    "iso:country":"US",
    "sg:address":"1079 US Highway 22",
    "sg:city":"Mountainside",
    "sg:classifiers":[
        {
            "category":"Restaurant",
            "type":"Food & Drink"
        }
    ],
    "sg:phone":"+1 908 233 1098",
    "sg:postcode":"07092",
    "sg:province":"NJ",
    "wof:name":"Echo Queen Restaurant Diner",
    "wof:placetype":"venue"
},
  "geometry": {"coordinates":[-74.339699,40.6819],"type":"Point"}
}