{
  "type": "Feature",
  "properties": {
    "addr:full":"300 Alexander Park Dr Princeton NJ 08540",
    "addr:housenumber":"300",
    "addr:postcode":"08540",
    "addr:street":"Alexander Park Dr",
    "iso:country":"US",
    "sg:address":"300 Alexander Park Dr",
    "sg:city":"Princeton",
    "sg:classifiers":[
        {
            "category":"Professional",
            "subcategory":"Computer Services",
            "type":"Services"
        }
    ],
    "sg:phone":"+1   ",
    "sg:postcode":"08540",
    "sg:province":"NJ",
    "sg:tags":[
        "programing",
        "custom"
    ],
    "wof:name":"Csg Systems International",
    "wof:placetype":"venue"
},
  "geometry": {"coordinates":[-74.635313,40.319997],"type":"Point"}
}