{
  "type": "Feature",
  "properties": {
    "iso:country":"US",
    "sg:address":"356 Yeoman Rd",
    "sg:city":"Manahawkin",
    "sg:classifiers":[
        {
            "category":"Wholesale",
            "subcategory":"Office Equipment",
            "type":"Manufacturing & Wholesale Goods"
        }
    ],
    "sg:phone":"+1 609 660 9211",
    "sg:postcode":"08050",
    "sg:province":"NJ",
    "sg:tags":[
        "audio",
        "video"
    ],
    "wof:name":"Coastal Audio Products",
    "wof:placetype":"venue"
},
  "geometry": {"coordinates":[-74.275322,39.743327],"type":"Point"}
}