{
  "type": "Feature",
  "properties": {
    "addr:full":"317 Burd St Pennington NJ 08534",
    "addr:housenumber":"317",
    "addr:postcode":"08534",
    "addr:street":"Burd St",
    "iso:country":"US",
    "sg:address":"317 Burd St",
    "sg:city":"Pennington",
    "sg:classifiers":[
        {
            "category":"Professional",
            "subcategory":"Art Services",
            "type":"Services"
        }
    ],
    "sg:phone":"+1 609 730 0520",
    "sg:postcode":"08534",
    "sg:province":"NJ",
    "sg:tags":[
        "photography",
        "commercial"
    ],
    "wof:name":"Cortet Benoit",
    "wof:placetype":"venue"
},
  "geometry": {"coordinates":[-74.791697,40.319822],"type":"Point"}
}