{
  "type": "Feature",
  "properties": {
    "addr:full":"175 Berkeley Ave Berkeley Heights NJ 07922",
    "addr:housenumber":"175",
    "addr:postcode":"07922",
    "addr:street":"Berkeley Ave",
    "iso:country":"US",
    "sg:address":"175 Berkeley Ave",
    "sg:city":"Berkeley Heights",
    "sg:classifiers":[
        {
            "category":"Professional",
            "subcategory":"Employment Agencies",
            "type":"Services"
        }
    ],
    "sg:phone":"+1   ",
    "sg:postcode":"07922",
    "sg:province":"NJ",
    "wof:name":"Youth Employment Svc Summit",
    "wof:placetype":"venue"
},
  "geometry": {"coordinates":[-74.443617,40.680354],"type":"Point"}
}