{
  "type": "Feature",
  "properties": {
    "iso:country":"US",
    "sg:address":"108 High St",
    "sg:city":"Hackettstown",
    "sg:classifiers":[
        {
            "category":"Social Services",
            "type":"Services"
        }
    ],
    "sg:phone":"+1 908 852 7762",
    "sg:postcode":"07840",
    "sg:province":"NJ",
    "sg:tags":[
        "organization",
        "welfare"
    ],
    "wof:name":"Gentle Passages",
    "wof:placetype":"venue"
},
  "geometry": {"coordinates":[-74.829144,40.853913],"type":"Point"}
}