{
  "type": "Feature",
  "properties": {
    "addr:full":"3 Tennent Ave Englishtown NJ 07726",
    "addr:housenumber":"3",
    "addr:postcode":"07726",
    "addr:street":"Tennent Ave",
    "iso:country":"US",
    "sg:address":"3 Tennent Ave",
    "sg:city":"Englishtown",
    "sg:classifiers":[
        {
            "category":"Restaurant",
            "type":"Food & Drink"
        }
    ],
    "sg:phone":"+1 732 446 6433",
    "sg:postcode":"07726",
    "sg:province":"NJ",
    "sg:tags":[
        "parlor",
        "ice",
        "cream"
    ],
    "wof:name":"Four Boys Ice Cream Shop",
    "wof:placetype":"venue"
},
  "geometry": {"coordinates":[-74.356657,40.29533],"type":"Point"}
}