{
  "type": "Feature",
  "properties": {
    "addr:full":"668 Darlington Ave Mahwah NJ 07430",
    "addr:housenumber":"668",
    "addr:postcode":"07430",
    "addr:street":"Darlington Ave",
    "iso:country":"US",
    "sg:address":"668 Darlington Ave",
    "sg:city":"Mahwah",
    "sg:classifiers":[
        {
            "category":"Health Services",
            "subcategory":"Clinic",
            "type":"Services"
        },
        {
            "category":"Sports & Exercise",
            "subcategory":"Gym",
            "type":"Entertainment"
        }
    ],
    "sg:phone":"+1 201 818 6706",
    "sg:postcode":"07430",
    "sg:province":"NJ",
    "sg:tags":[
        "stress",
        "management",
        "mental",
        "prevention"
    ],
    "sg:website":"http://www.drmarywallach.com",
    "wof:name":"Mary Wallach, PhD, RN, LCADC",
    "wof:placetype":"venue"
},
  "geometry": {"coordinates":[-74.175169,41.066536],"type":"Point"}
}