{
  "type": "Feature",
  "properties": {
    "addr:full":"115 Spring St Morristown NJ 07960",
    "addr:housenumber":"115",
    "addr:postcode":"07960",
    "addr:street":"Spring St",
    "iso:country":"US",
    "sg:address":"115 Spring St",
    "sg:city":"Morristown",
    "sg:classifiers":[
        {
            "category":"Autos & Motor Vehicles",
            "subcategory":"Automobile Sales",
            "type":"Retail Goods"
        }
    ],
    "sg:phone":"+1 973 984 5358",
    "sg:postcode":"07960",
    "sg:province":"NJ",
    "sg:tags":[
        "car",
        "dealer"
    ],
    "wof:name":"Morris County Bmw",
    "wof:placetype":"venue"
},
  "geometry": {"coordinates":[-74.481573,40.801504],"type":"Point"}
}