{
  "type": "Feature",
  "properties": {
    "addr:full":"1905 State Rte 33 Trenton NJ 08690",
    "addr:housenumber":"1905",
    "addr:postcode":"08690",
    "addr:street":"State Rte 33",
    "iso:country":"US",
    "sg:address":"1905 State Rte 33",
    "sg:city":"Trenton",
    "sg:classifiers":[
        {
            "category":"Shopping",
            "subcategory":"Hobbies, Toys, & Games",
            "type":"Retail Goods"
        }
    ],
    "sg:phone":"+1 609 586 1661",
    "sg:postcode":"08690",
    "sg:province":"NJ",
    "sg:tags":[
        "model",
        "supply"
    ],
    "wof:name":"Hobby Shop Toys For Boys",
    "wof:placetype":"venue"
},
  "geometry": {"coordinates":[-74.65319100000001,40.224739],"type":"Point"}
}