{
  "type": "Feature",
  "properties": {
    "addr:full":"171 Clementon Rd W Gibbsboro NJ 08026",
    "addr:housenumber":"171",
    "addr:postcode":"08026",
    "addr:street":"Clementon Rd W Gibbsboro",
    "iso:country":"US",
    "sg:address":"171 Clementon Rd W",
    "sg:city":"Gibbsboro",
    "sg:classifiers":[
        {
            "category":"Manufacturing",
            "subcategory":"Furniture",
            "type":"Manufacturing & Wholesale Goods"
        }
    ],
    "sg:phone":"+1 856 784 6097",
    "sg:postcode":"08026",
    "sg:province":"NJ",
    "sg:tags":[
        "manufacture",
        "fixture"
    ],
    "wof:name":"Nicks Workshop Inc",
    "wof:placetype":"venue"
},
  "geometry": {"coordinates":[-74.973387,39.827204],"type":"Point"}
}