{
  "type": "Feature",
  "properties": {
    "iso:country":"US",
    "sg:address":"67 Schoolhouse Rd",
    "sg:city":"Wrightstown",
    "sg:classifiers":[
        {
            "category":"Building & Trades",
            "subcategory":"Construction",
            "type":"Services"
        }
    ],
    "sg:phone":"+1 609 758 1361",
    "sg:postcode":"08562",
    "sg:province":"NJ",
    "sg:tags":[
        "nonresidential"
    ],
    "wof:name":"E J Gangel & Sons",
    "wof:placetype":"venue"
},
  "geometry": {"coordinates":[-74.590142,40.07496],"type":"Point"}
}