{
  "type": "Feature",
  "properties": {
    "addr:full":"708 W Saint Georges Ave Linden NJ 07036",
    "addr:housenumber":"708",
    "addr:postcode":"07036",
    "addr:street":"W Saint Georges Ave",
    "iso:country":"US",
    "sg:address":"708 W Saint Georges Ave",
    "sg:city":"Linden",
    "sg:classifiers":[
        {
            "category":"Education",
            "subcategory":"Dance Studio",
            "type":"Public Place"
        }
    ],
    "sg:phone":"+1 908 925 9599",
    "sg:postcode":"07036",
    "sg:province":"NJ",
    "wof:name":"Julissas Dance & Choreogr",
    "wof:placetype":"venue"
},
  "geometry": {"coordinates":[-74.27029,40.630561],"type":"Point"}
}