{
  "type": "Feature",
  "properties": {
    "addr:full":"296 Renner Ave Newark NJ 07112",
    "addr:housenumber":"296",
    "addr:postcode":"07112",
    "addr:street":"Renner Ave",
    "iso:country":"US",
    "sg:address":"296 Renner Ave",
    "sg:city":"Newark",
    "sg:classifiers":[
        {
            "category":"Retail",
            "subcategory":"Laundry & Dry Cleaning",
            "type":"Services"
        }
    ],
    "sg:phone":"+1 973 923 2400",
    "sg:postcode":"07112",
    "sg:province":"NJ",
    "sg:tags":[
        "power"
    ],
    "wof:name":"Bubble City Laundromat LLC",
    "wof:placetype":"venue"
},
  "geometry": {"coordinates":[-74.212103,40.713962],"type":"Point"}
}