{
  "type": "Feature",
  "properties": {
    "iso:country":"US",
    "sg:address":"1202 Margaret Ct",
    "sg:city":"South Plainfield",
    "sg:classifiers":[
        {
            "category":"Professional",
            "subcategory":"Management & Consulting",
            "type":"Services"
        }
    ],
    "sg:phone":"+1 917 349 2284",
    "sg:postcode":"07080",
    "sg:province":"NJ",
    "sg:tags":[
        "traveler",
        "educational",
        "institution"
    ],
    "wof:name":"Platform 3000",
    "wof:placetype":"venue"
},
  "geometry": {"coordinates":[-74.41596800000001,40.545933],"type":"Point"}
}