{
  "type": "Feature",
  "properties": {
    "addr:full":"17 Park St Jersey City NJ 07304",
    "addr:housenumber":"17",
    "addr:postcode":"07304",
    "addr:street":"Park St",
    "iso:country":"US",
    "sg:address":"17 Park St",
    "sg:city":"Jersey City",
    "sg:classifiers":[
        {
            "category":"Organizations",
            "subcategory":"Religious Organization",
            "type":"Services"
        }
    ],
    "sg:phone":"+1   ",
    "sg:postcode":"07304",
    "sg:province":"NJ",
    "wof:name":"Bakka Inc",
    "wof:placetype":"venue"
},
  "geometry": {"coordinates":[-74.069048,40.716946],"type":"Point"}
}