{
  "type": "Feature",
  "properties": {
    "addr:full":"384 Ewing St Princeton NJ 08540",
    "addr:housenumber":"384",
    "addr:postcode":"08540",
    "addr:street":"Ewing St",
    "iso:country":"US",
    "sg:address":"384 Ewing St",
    "sg:city":"Princeton",
    "sg:classifiers":[
        {
            "category":"Professional",
            "subcategory":"Business Services",
            "type":"Services"
        }
    ],
    "sg:phone":"+1 609 688 8300",
    "sg:postcode":"08540",
    "sg:province":"NJ",
    "wof:name":"Ziment Associates",
    "wof:placetype":"venue"
},
  "geometry": {"coordinates":[-74.654183,40.363295],"type":"Point"}
}