{
  "type": "Feature",
  "properties": {
    "addr:full":"1071 State Rte 34 Matawan NJ 07747",
    "addr:housenumber":"1071",
    "addr:postcode":"07747",
    "addr:street":"State Rte 34",
    "iso:country":"US",
    "sg:address":"1071 State Rte 34",
    "sg:city":"Matawan",
    "sg:classifiers":[
        {
            "category":"Cinema",
            "subcategory":"Movie Rental",
            "type":"Entertainment"
        }
    ],
    "sg:phone":"+1 732 290 2244",
    "sg:postcode":"07747",
    "sg:province":"NJ",
    "sg:tags":[
        "leasing",
        "video",
        "disc",
        "tape"
    ],
    "sg:website":"www.blockbuster.com",
    "wof:name":"Blockbuster Video",
    "wof:placetype":"venue"
},
  "geometry": {"coordinates":[-74.227627,40.399023],"type":"Point"}
}