{
  "type": "Feature",
  "properties": {
    "addr:full":"140 Cider Mill Rd Flemington NJ 08822",
    "addr:housenumber":"140",
    "addr:postcode":"08822",
    "addr:street":"Cider Mill Rd",
    "iso:country":"US",
    "sg:address":"140 Cider Mill Rd",
    "sg:city":"Flemington",
    "sg:classifiers":[
        {
            "category":"Professional",
            "subcategory":"Accounting & Tax Preparation",
            "type":"Services"
        }
    ],
    "sg:phone":"+1 908 788 9117",
    "sg:postcode":"08822",
    "sg:province":"NJ",
    "sg:tags":[
        "return",
        "filing"
    ],
    "wof:name":"Joyce M Curving",
    "wof:placetype":"venue"
},
  "geometry": {"coordinates":[-74.79307,40.46909],"type":"Point"}
}