{
  "type": "Feature",
  "properties": {
    "addr:full":"206 Renfrew Ave Trenton NJ 08618",
    "addr:housenumber":"206",
    "addr:postcode":"08618",
    "addr:street":"Renfrew Ave",
    "iso:country":"US",
    "sg:address":"206 Renfrew Ave",
    "sg:city":"Trenton",
    "sg:classifiers":[
        {
            "category":"Organizations",
            "subcategory":"Non-profit Organization",
            "type":"Services"
        }
    ],
    "sg:phone":"+1 609 777 5447",
    "sg:postcode":"08618",
    "sg:province":"NJ",
    "sg:tags":[
        "social"
    ],
    "wof:name":"Center For Urban Self Hel",
    "wof:placetype":"venue"
},
  "geometry": {"coordinates":[-74.796544,40.244233],"type":"Point"}
}