{
  "type": "Feature",
  "properties": {
    "addr:full":"15 Victorian Dr Old Bridge NJ 08857",
    "addr:housenumber":"15",
    "addr:postcode":"08857",
    "addr:street":"Victorian Dr",
    "iso:country":"US",
    "sg:address":"15 Victorian Dr",
    "sg:city":"Old Bridge",
    "sg:classifiers":[
        {
            "category":"Insurance",
            "subcategory":"Life Insurance",
            "type":"Services"
        }
    ],
    "sg:phone":"+1   ",
    "sg:postcode":"08857",
    "sg:province":"NJ",
    "sg:tags":[
        "carrier"
    ],
    "wof:name":"USAA",
    "wof:placetype":"venue"
},
  "geometry": {"coordinates":[-74.31356,40.385838],"type":"Point"}
}