{
  "type": "Feature",
  "properties": {
    "iso:country":"US",
    "sg:address":"669 High St",
    "sg:city":"Burlington",
    "sg:classifiers":[
        {
            "category":"Retail",
            "subcategory":"Self-service Laundry",
            "type":"Services"
        }
    ],
    "sg:phone":"+1 609 387 9821",
    "sg:postcode":"08016",
    "sg:province":"NJ",
    "sg:tags":[
        "operated",
        "washer",
        "coin",
        "dryer"
    ],
    "wof:name":"On The Go Laundromat",
    "wof:placetype":"venue"
},
  "geometry": {"coordinates":[-74.8545,40.069654],"type":"Point"}
}