{
  "type": "Feature",
  "properties": {
    "iso:country":"US",
    "sg:address":"1674 Delsea Dr",
    "sg:city":"Woodbury",
    "sg:classifiers":[
        {
            "category":"Social Services",
            "subcategory":"Job Training",
            "type":"Services"
        },
        {
            "category":"Health Services",
            "subcategory":"Nursing And Care Facility",
            "type":"Services"
        },
        {
            "category":"Social Services",
            "subcategory":"Adult Care",
            "type":"Services"
        },
        {
            "category":"Social Services",
            "subcategory":"Retirement Home",
            "type":"Services"
        }
    ],
    "sg:phone":"+1 856 384 7750",
    "sg:postcode":"08096",
    "sg:province":"NJ",
    "sg:tags":[
        "living",
        "nurses-home",
        "homes-skilled",
        "people",
        "assisted",
        "elder",
        "convalescent",
        "homes-elderly"
    ],
    "sg:website":"http://www.brookdaleliving.com",
    "wof:name":"Senior Brookdale Living Inc",
    "wof:placetype":"venue"
},
  "geometry": {"coordinates":[-75.124612,39.81561],"type":"Point"}
}