{
  "type": "Feature",
  "properties": {
    "iso:country":"US",
    "sg:address":"55 Clinton Ave",
    "sg:city":"Mantua",
    "sg:classifiers":[
        {
            "category":"Organizations",
            "subcategory":"Community Association",
            "type":"Services"
        }
    ],
    "sg:phone":"+1   ",
    "sg:postcode":"08051",
    "sg:province":"NJ",
    "wof:name":"American Legion Dept of PA",
    "wof:placetype":"venue"
},
  "geometry": {"coordinates":[-75.167964,39.791733],"type":"Point"}
}