{
  "type": "Feature",
  "properties": {
    "addr:full":"57 New Rd Parsippany NJ 07054",
    "addr:housenumber":"57",
    "addr:postcode":"07054",
    "addr:street":"New Rd",
    "iso:country":"US",
    "sg:address":"57 New Rd",
    "sg:city":"Parsippany",
    "sg:classifiers":[
        {
            "category":"Retail",
            "subcategory":"Laundry & Dry Cleaning",
            "type":"Services"
        }
    ],
    "sg:phone":"+1 973 882 3489",
    "sg:postcode":"07054",
    "sg:province":"NJ",
    "wof:name":"Kwik Wash Laundromat & Dry Cleaners",
    "wof:placetype":"venue"
},
  "geometry": {"coordinates":[-74.349098,40.859001],"type":"Point"}
}