{
  "type": "Feature",
  "properties": {
    "addr:full":"126 Tyler St Newark NJ 07114",
    "addr:housenumber":"126",
    "addr:postcode":"07114",
    "addr:street":"Tyler St",
    "iso:country":"US",
    "sg:address":"126 Tyler St",
    "sg:city":"Newark",
    "sg:classifiers":[
        {
            "category":"Professional",
            "subcategory":"Business Services",
            "type":"Services"
        }
    ],
    "sg:phone":"+1 973 274 9026",
    "sg:postcode":"07114",
    "sg:province":"NJ",
    "sg:tags":[
        "packaging"
    ],
    "wof:name":"New England Shipping Co Inc",
    "wof:placetype":"venue"
},
  "geometry": {"coordinates":[-74.150806,40.69231],"type":"Point"}
}