{
  "type": "Feature",
  "properties": {
    "iso:country":"US",
    "sg:address":"1334 US Hwy 9",
    "sg:city":"Toms River",
    "sg:classifiers":[
        {
            "category":"Banks & Credit Unions",
            "subcategory":"Bank",
            "type":"Services"
        }
    ],
    "sg:phone":"+1 732 244 0084",
    "sg:postcode":"08755",
    "sg:province":"NJ",
    "wof:name":"Sovereign Bank",
    "wof:placetype":"venue"
},
  "geometry": {"coordinates":[-74.211187,39.991151],"type":"Point"}
}