{
  "type": "Feature",
  "properties": {
    "addr:full":"1111 Springhill Rd Skillman NJ 08558",
    "addr:housenumber":"1111",
    "addr:postcode":"08558",
    "addr:street":"Springhill Rd",
    "iso:country":"US",
    "sg:address":"1111 Springhill Rd",
    "sg:city":"Skillman",
    "sg:classifiers":[
        {
            "category":"Social Services",
            "type":"Services"
        }
    ],
    "sg:phone":"+1 609 688 3444",
    "sg:postcode":"08558",
    "sg:province":"NJ",
    "sg:tags":[
        "employee",
        "assistance",
        "program"
    ],
    "wof:name":"Cosmopolitan Group",
    "wof:placetype":"venue"
},
  "geometry": {"coordinates":[-74.74086200000001,40.421563],"type":"Point"}
}