{
  "type": "Feature",
  "properties": {
    "addr:full":"174 Maplewood Ave Maplewood NJ 07040",
    "addr:housenumber":"174",
    "addr:postcode":"07040",
    "addr:street":"Maplewood Ave",
    "iso:country":"US",
    "sg:address":"174 Maplewood Ave",
    "sg:city":"Maplewood",
    "sg:classifiers":[
        {
            "category":"Personal",
            "subcategory":"Beauty Salon",
            "type":"Services"
        }
    ],
    "sg:phone":"+1 973 762 1212",
    "sg:postcode":"07040",
    "sg:province":"NJ",
    "wof:name":"Anthony Garubo Hair Design",
    "wof:placetype":"venue"
},
  "geometry": {"coordinates":[-74.278408,40.730225],"type":"Point"}
}