{
  "type": "Feature",
  "properties": {
    "addr:full":"417 Broad St Bloomfield NJ 07003",
    "addr:housenumber":"417",
    "addr:postcode":"07003",
    "addr:street":"Broad St",
    "iso:country":"US",
    "sg:address":"417 Broad St",
    "sg:city":"Bloomfield",
    "sg:classifiers":[
        {
            "category":"Personal",
            "subcategory":"Beauty Salon",
            "type":"Services"
        }
    ],
    "sg:phone":"+1 973 748 1278",
    "sg:postcode":"07003",
    "sg:province":"NJ",
    "sg:tags":[
        "shop"
    ],
    "wof:name":"Gloria Richard's Coiffure",
    "wof:placetype":"venue"
},
  "geometry": {"coordinates":[-74.19223100000001,40.808639],"type":"Point"}
}