{
  "type": "Feature",
  "properties": {
    "addr:full":"46 W Clinton Ave Tenafly NJ 07670",
    "addr:housenumber":"46",
    "addr:postcode":"07670",
    "addr:street":"W Clinton Ave",
    "iso:country":"US",
    "sg:address":"46 W Clinton Ave",
    "sg:city":"Tenafly",
    "sg:classifiers":[
        {
            "category":"Professional",
            "subcategory":"Lawyer & Legal Services",
            "type":"Services"
        }
    ],
    "sg:phone":"+1 201 569 4142",
    "sg:postcode":"07670",
    "sg:province":"NJ",
    "sg:tags":[
        "attorney",
        "practice"
    ],
    "wof:name":"Law Offices of Fred L Crabbe",
    "wof:placetype":"venue"
},
  "geometry": {"coordinates":[-73.96758,40.924428],"type":"Point"}
}