{
  "type": "Feature",
  "properties": {
    "iso:country":"US",
    "sg:address":"178 Main St",
    "sg:city":"Little Falls",
    "sg:classifiers":[
        {
            "category":"Professional",
            "subcategory":"Business Services",
            "type":"Services"
        }
    ],
    "sg:phone":"+1   ",
    "sg:postcode":"07424",
    "sg:province":"NJ",
    "wof:name":"Jmd Networks & Solutions LLC",
    "wof:placetype":"venue"
},
  "geometry": {"coordinates":[-74.233424,40.882775],"type":"Point"}
}