{
  "type": "Feature",
  "properties": {
    "iso:country":"US",
    "sg:address":"6 Shinney Ln",
    "sg:city":"Trenton",
    "sg:classifiers":[
        {
            "category":"Professional",
            "type":"Services"
        }
    ],
    "sg:phone":"+1   ",
    "sg:postcode":"08648",
    "sg:province":"NJ",
    "wof:name":"Burkes Works",
    "wof:placetype":"venue"
},
  "geometry": {"coordinates":[-74.695656,40.275073],"type":"Point"}
}