{
  "type": "Feature",
  "properties": {
    "iso:country":"US",
    "sg:address":"442 Main St",
    "sg:city":"Fort Lee",
    "sg:classifiers":[
        {
            "category":"Real Estate",
            "subcategory":"Real Estate Agent",
            "type":"Services"
        }
    ],
    "sg:phone":"+1 201 363 8899",
    "sg:postcode":"07024",
    "sg:province":"NJ",
    "wof:name":"My Home Town Realty Inc",
    "wof:placetype":"venue"
},
  "geometry": {"coordinates":[-73.976474,40.854618],"type":"Point"}
}