{
  "type": "Feature",
  "properties": {
    "iso:country":"US",
    "sg:address":"1432 Morris Ave",
    "sg:city":"Union",
    "sg:classifiers":[
        {
            "category":"Banks & Credit Unions",
            "subcategory":"Bank",
            "type":"Services"
        }
    ],
    "sg:phone":"+1   ",
    "sg:postcode":"07083",
    "sg:province":"NJ",
    "sg:tags":[
        "commercial"
    ],
    "wof:name":"Norcrown Bank",
    "wof:placetype":"venue"
},
  "geometry": {"coordinates":[-74.246149,40.688768],"type":"Point"}
}