{
  "type": "Feature",
  "properties": {
    "addr:full":"4 Pond St Clifton NJ 07013",
    "addr:housenumber":"4",
    "addr:postcode":"07013",
    "addr:street":"Pond St",
    "iso:country":"US",
    "sg:address":"4 Pond St",
    "sg:city":"Clifton",
    "sg:classifiers":[
        {
            "category":"Organizations",
            "subcategory":"Membership Organization",
            "type":"Services"
        }
    ],
    "sg:phone":"+1 973 470 8093",
    "sg:postcode":"07013",
    "sg:province":"NJ",
    "sg:tags":[
        "social"
    ],
    "wof:name":"Women Marines Assoc",
    "wof:placetype":"venue"
},
  "geometry": {"coordinates":[-74.16990300000001,40.870392],"type":"Point"}
}