{
  "type": "Feature",
  "properties": {
    "addr:full":"112 Town Center Dr Warren NJ 07059",
    "addr:housenumber":"112",
    "addr:postcode":"07059",
    "addr:street":"Town Center Dr",
    "iso:country":"US",
    "sg:address":"112 Town Center Dr",
    "sg:city":"Warren",
    "sg:classifiers":[
        {
            "category":"Insurance",
            "subcategory":"Insurance Agent",
            "type":"Services"
        }
    ],
    "sg:phone":"+1   ",
    "sg:postcode":"07059",
    "sg:province":"NJ",
    "wof:name":"Gallagher Hartstein",
    "wof:placetype":"venue"
},
  "geometry": {"coordinates":[-74.49851700000001,40.617552],"type":"Point"}
}