{
  "type": "Feature",
  "properties": {
    "iso:country":"US",
    "sg:address":"6008 Riverfront Dr",
    "sg:city":"Palmyra",
    "sg:classifiers":[
        {
            "category":"Banks & Credit Unions",
            "subcategory":"Investment Brokerage",
            "type":"Services"
        }
    ],
    "sg:phone":"+1   ",
    "sg:postcode":"08065",
    "sg:province":"NJ",
    "sg:tags":[
        "commodity",
        "contract"
    ],
    "wof:name":"Burger Square",
    "wof:placetype":"venue"
},
  "geometry": {"coordinates":[-75.035399,40.010905],"type":"Point"}
}