{
  "type": "Feature",
  "properties": {
    "addr:full":"195 Norwood Ave Long Branch NJ 07740",
    "addr:housenumber":"195",
    "addr:postcode":"07740",
    "addr:street":"Norwood Ave",
    "iso:country":"US",
    "sg:address":"195 Norwood Ave",
    "sg:city":"Long Branch",
    "sg:classifiers":[
        {
            "category":"Recreation",
            "type":"Entertainment"
        }
    ],
    "sg:phone":"+1 732 870 2400",
    "sg:postcode":"07740",
    "sg:province":"NJ",
    "wof:name":"All Star Champions Taekwondo",
    "wof:placetype":"venue"
},
  "geometry": {"coordinates":[-74.001598,40.293664],"type":"Point"}
}