{
  "type": "Feature",
  "properties": {
    "iso:country":"US",
    "sg:address":"6 Woodland Dr",
    "sg:city":"Boonton",
    "sg:classifiers":[
        {
            "category":"Professional",
            "subcategory":"Business Services",
            "type":"Services"
        }
    ],
    "sg:phone":"+1   ",
    "sg:postcode":"07005",
    "sg:province":"NJ",
    "wof:name":"Forrest Interior",
    "wof:placetype":"venue"
},
  "geometry": {"coordinates":[-74.421441,40.879208],"type":"Point"}
}