{
  "type": "Feature",
  "properties": {
    "iso:country":"US",
    "sg:address":"1399 River Ave",
    "sg:city":"Lakewood",
    "sg:classifiers":[
        {
            "category":"Autos & Motor Vehicles",
            "subcategory":"Automobile Sales",
            "type":"Retail Goods"
        }
    ],
    "sg:phone":"+1 877 216 7568",
    "sg:postcode":"08701",
    "sg:province":"NJ",
    "sg:tags":[
        "new",
        "used",
        "car"
    ],
    "sg:website":"http://local.ingenio.com/Listings/Details.aspx?NUM=a%3a10128882%3a13%3a4859924%3a14%3a0%3a7",
    "wof:name":"Jim Curley GMC",
    "wof:placetype":"venue"
},
  "geometry": {"coordinates":[-74.221672,40.047958],"type":"Point"}
}