{
  "type": "Feature",
  "properties": {
    "iso:country":"US",
    "sg:address":"2303 Woodbridge Ave",
    "sg:city":"Edison",
    "sg:classifiers":[
        {
            "category":"Cinema",
            "subcategory":"Movie Rental",
            "type":"Entertainment"
        }
    ],
    "sg:phone":"+1 732 339 1399",
    "sg:postcode":"08817",
    "sg:province":"NJ",
    "sg:tags":[
        "leasing",
        "video",
        "disc",
        "tape"
    ],
    "wof:name":"Filmi City Co",
    "wof:placetype":"venue"
},
  "geometry": {"coordinates":[-74.38892800000001,40.50237],"type":"Point"}
}