{
  "type": "Feature",
  "properties": {
    "addr:full":"37 E Washington Ave Washington NJ 07882",
    "addr:housenumber":"37",
    "addr:postcode":"07882",
    "addr:street":"E Washington Ave",
    "iso:country":"US",
    "sg:address":"37 E Washington Ave",
    "sg:city":"Washington",
    "sg:classifiers":[
        {
            "category":"Home & Garden",
            "subcategory":"Furniture",
            "type":"Retail Goods"
        },
        {
            "category":"Home & Garden",
            "subcategory":"Carpets & Floor Coverings",
            "type":"Retail Goods"
        }
    ],
    "sg:phone":"+1 908 689 2900",
    "sg:postcode":"07882",
    "sg:province":"NJ",
    "sg:tags":[
        "store",
        "mattress"
    ],
    "wof:name":"Villa Furniture",
    "wof:placetype":"venue"
},
  "geometry": {"coordinates":[-74.979698,40.758499],"type":"Point"}
}