{
  "type": "Feature",
  "properties": {
    "addr:full":"3 Merion Dr Englishtown NJ 07726",
    "addr:housenumber":"3",
    "addr:postcode":"07726",
    "addr:street":"Merion Dr",
    "iso:country":"US",
    "sg:address":"3 Merion Dr",
    "sg:city":"Englishtown",
    "sg:classifiers":[
        {
            "category":"Professional",
            "subcategory":"Computer Services",
            "type":"Services"
        }
    ],
    "sg:phone":"+1 732 536 9736",
    "sg:postcode":"07726",
    "sg:province":"NJ",
    "wof:name":"Financial Software",
    "wof:placetype":"venue"
},
  "geometry": {"coordinates":[-74.311955,40.313621],"type":"Point"}
}