{
  "type": "Feature",
  "properties": {
    "iso:country":"US",
    "sg:address":"133 N Pleasant Ave",
    "sg:city":"Ridgewood",
    "sg:classifiers":[
        {
            "category":"Professional",
            "subcategory":"Engineering",
            "type":"Services"
        }
    ],
    "sg:phone":"+1   ",
    "sg:postcode":"07450",
    "sg:province":"NJ",
    "wof:name":"Norton Engineering Consultants",
    "wof:placetype":"venue"
},
  "geometry": {"coordinates":[-74.09858199999999,40.979115],"type":"Point"}
}