{
  "type": "Feature",
  "properties": {
    "iso:country":"US",
    "sg:address":"707 Raritan Ave",
    "sg:city":"Highland Park",
    "sg:classifiers":[
        {
            "category":"Manufacturing",
            "subcategory":"Printing",
            "type":"Manufacturing & Wholesale Goods"
        }
    ],
    "sg:phone":"+1 732 819 0949",
    "sg:postcode":"08904",
    "sg:province":"NJ",
    "sg:tags":[
        "typesetting"
    ],
    "wof:name":"Network Typesetting Inc",
    "wof:placetype":"venue"
},
  "geometry": {"coordinates":[-74.42158000000001,40.50162],"type":"Point"}
}