{
  "type": "Feature",
  "properties": {
    "addr:full":"960 Boardwalk Ocean City NJ 08226",
    "addr:housenumber":"960",
    "addr:postcode":"08226",
    "addr:street":"Boardwalk",
    "iso:country":"US",
    "sg:address":"960 Boardwalk",
    "sg:city":"Ocean City",
    "sg:classifiers":[
        {
            "category":"Shopping",
            "subcategory":"Clothing, Apparel, & Fashions",
            "type":"Retail Goods"
        }
    ],
    "sg:phone":"+1 609 398 5229",
    "sg:postcode":"08226",
    "sg:province":"NJ",
    "sg:tags":[
        "t"
    ],
    "wof:name":"B & D's T's",
    "wof:placetype":"venue"
},
  "geometry": {"coordinates":[-74.57262299999999,39.274916],"type":"Point"}
}