{
  "type": "Feature",
  "properties": {
    "addr:full":"248 Columbia Tpke Florham Park NJ 07932",
    "addr:housenumber":"248",
    "addr:postcode":"07932",
    "addr:street":"Columbia Tpke",
    "iso:country":"US",
    "sg:address":"248 Columbia Tpke",
    "sg:city":"Florham Park",
    "sg:classifiers":[
        {
            "category":"Insurance",
            "subcategory":"Insurance Agent",
            "type":"Services"
        }
    ],
    "sg:phone":"+1   ",
    "sg:postcode":"07932",
    "sg:province":"NJ",
    "wof:name":"Spagnoletti Investments Insur",
    "wof:placetype":"venue"
},
  "geometry": {"coordinates":[-74.397898,40.789071],"type":"Point"}
}