{
  "type": "Feature",
  "properties": {
    "addr:full":"329 Belleville Ave Bloomfield NJ 07003",
    "addr:housenumber":"329",
    "addr:postcode":"07003",
    "addr:street":"Belleville Ave",
    "iso:country":"US",
    "sg:address":"329 Belleville Ave",
    "sg:city":"Bloomfield",
    "sg:classifiers":[
        {
            "category":"Banks & Credit Unions",
            "subcategory":"Bank",
            "type":"Services"
        }
    ],
    "sg:phone":"+1 973 743 8471",
    "sg:postcode":"07003",
    "sg:province":"NJ",
    "wof:name":"Glen Ridge Savings Bank Sla",
    "wof:placetype":"venue"
},
  "geometry": {"coordinates":[-74.19541599999999,40.799937],"type":"Point"}
}