{
  "type": "Feature",
  "properties": {
    "addr:full":"616 Hudson St Hoboken NJ 07030",
    "addr:housenumber":"616",
    "addr:postcode":"07030",
    "addr:street":"Hudson St",
    "iso:country":"US",
    "sg:address":"616 Hudson St",
    "sg:city":"Hoboken",
    "sg:classifiers":[
        {
            "category":"Real Estate",
            "subcategory":"Real Estate Agent",
            "type":"Services"
        }
    ],
    "sg:phone":"+1   ",
    "sg:postcode":"07030",
    "sg:province":"NJ",
    "wof:name":"All Grands",
    "wof:placetype":"venue"
},
  "geometry": {"coordinates":[-74.02768500000001,40.744351],"type":"Point"}
}