{
  "type": "Feature",
  "properties": {
    "addr:full":"125 Park Ave East Rutherford NJ 07073",
    "addr:housenumber":"125",
    "addr:postcode":"07073",
    "addr:street":"Park Ave",
    "iso:country":"US",
    "sg:address":"125 Park Ave",
    "sg:city":"East Rutherford",
    "sg:classifiers":[
        {
            "category":"Restaurant",
            "type":"Food & Drink"
        }
    ],
    "sg:phone":"+1 201 933 3308",
    "sg:postcode":"07073",
    "sg:province":"NJ",
    "sg:website":"www.parkcitybar.com",
    "wof:name":"Jersey Sports Cafe",
    "wof:placetype":"venue"
},
  "geometry": {"coordinates":[-74.097397,40.8321],"type":"Point"}
}