{
  "type": "Feature",
  "properties": {
    "iso:country":"US",
    "sg:address":"679 Montgomery St",
    "sg:city":"Jersey City",
    "sg:classifiers":[
        {
            "category":"Health Services",
            "subcategory":"Doctor",
            "type":"Services"
        }
    ],
    "sg:phone":"+1 201 209 9110",
    "sg:postcode":"07306",
    "sg:province":"NJ",
    "sg:tags":[
        "medical"
    ],
    "wof:name":"Vascular Surgeon",
    "wof:placetype":"venue"
},
  "geometry": {"coordinates":[-74.06515899999999,40.724094],"type":"Point"}
}