{
  "type": "Feature",
  "properties": {
    "addr:full":"715 Bennetts Mills Rd Jackson NJ 08527",
    "addr:housenumber":"715",
    "addr:postcode":"08527",
    "addr:street":"Bennetts Mills Rd",
    "iso:country":"US",
    "sg:address":"715 Bennetts Mills Rd",
    "sg:city":"Jackson",
    "sg:classifiers":[
        {
            "category":"Restaurant",
            "type":"Food & Drink"
        }
    ],
    "sg:phone":"+1 732 928 8888",
    "sg:postcode":"08527",
    "sg:province":"NJ",
    "wof:name":"Shing Loon",
    "wof:placetype":"venue"
},
  "geometry": {"coordinates":[-74.286486,40.123465],"type":"Point"}
}