{
  "type": "Feature",
  "properties": {
    "addr:full":"5 Flynn Ter West Orange NJ 07052",
    "addr:housenumber":"5",
    "addr:postcode":"07052",
    "addr:street":"Flynn Ter West",
    "iso:country":"US",
    "sg:address":"5 Flynn Ter",
    "sg:city":"West Orange",
    "sg:classifiers":[
        {
            "category":"Professional",
            "subcategory":"Computer Services",
            "type":"Services"
        }
    ],
    "sg:phone":"+1 973 736 4290",
    "sg:postcode":"07052",
    "sg:province":"NJ",
    "sg:tags":[
        "repair"
    ],
    "wof:name":"B A C I Enterprises Inc",
    "wof:placetype":"venue"
},
  "geometry": {"coordinates":[-74.262472,40.799123],"type":"Point"}
}