{
  "type": "Feature",
  "properties": {
    "iso:country":"US",
    "sg:address":"39 Cambridge Dr",
    "sg:city":"Matawan",
    "sg:classifiers":[
        {
            "category":"Health Services",
            "subcategory":"Doctor",
            "type":"Services"
        }
    ],
    "sg:phone":"+1   ",
    "sg:postcode":"07747",
    "sg:province":"NJ",
    "wof:name":"Jonathan Min DDS",
    "wof:placetype":"venue"
},
  "geometry": {"coordinates":[-74.223545,40.398987],"type":"Point"}
}