{
  "type": "Feature",
  "properties": {
    "iso:country":"US",
    "sg:address":"82 Stokes Ave",
    "sg:city":"Trenton",
    "sg:classifiers":[
        {
            "category":"Wholesale",
            "subcategory":"Metals & Minerals",
            "type":"Manufacturing & Wholesale Goods"
        }
    ],
    "sg:phone":"+1 609 882 6983",
    "sg:postcode":"08638",
    "sg:province":"NJ",
    "sg:tags":[
        "steel",
        "warehouse"
    ],
    "wof:name":"Capital Steel Svc",
    "wof:placetype":"venue"
},
  "geometry": {"coordinates":[-74.766897,40.236385],"type":"Point"}
}