{
  "type": "Feature",
  "properties": {
    "addr:full":"491 Manalapan Rd Spotswood NJ 08884",
    "addr:housenumber":"491",
    "addr:postcode":"08884",
    "addr:street":"Manalapan Rd",
    "iso:country":"US",
    "sg:address":"491 Manalapan Rd",
    "sg:city":"Spotswood",
    "sg:classifiers":[
        {
            "category":"Retail",
            "subcategory":"Repair Shop",
            "type":"Services"
        }
    ],
    "sg:phone":"+1   ",
    "sg:postcode":"08884",
    "sg:province":"NJ",
    "wof:name":"A24 All Day Emergency A Locksm",
    "wof:placetype":"venue"
},
  "geometry": {"coordinates":[-74.390106,40.391603],"type":"Point"}
}