{
  "type": "Feature",
  "properties": {
    "addr:full":"300 Harmon Meadow Blvd Secaucus NJ 07094",
    "addr:housenumber":"300",
    "addr:postcode":"07094",
    "addr:street":"Harmon Meadow Blvd",
    "iso:country":"US",
    "sg:address":"300 Harmon Meadow Blvd",
    "sg:city":"Secaucus",
    "sg:classifiers":[
        {
            "category":"Professional",
            "subcategory":"Management & Consulting",
            "type":"Services"
        }
    ],
    "sg:phone":"+1 617 934 4358",
    "sg:postcode":"07094",
    "sg:province":"NJ",
    "sg:tags":[
        "industrial",
        "engineer"
    ],
    "sg:website":"www.warmthoughts.com",
    "wof:name":"Warm Thoughts Communication",
    "wof:placetype":"venue"
},
  "geometry": {"coordinates":[-74.045537,40.788589],"type":"Point"}
}