{
  "type": "Feature",
  "properties": {
    "iso:country":"US",
    "sg:address":"64 Colfax St",
    "sg:city":"South River",
    "sg:classifiers":[
        {
            "category":"Building & Trades",
            "subcategory":"Construction",
            "type":"Services"
        }
    ],
    "sg:phone":"+1 732 613 1098",
    "sg:postcode":"08882",
    "sg:province":"NJ",
    "sg:tags":[
        "concrete",
        "contractor"
    ],
    "wof:name":"Cristal Concrete Corp",
    "wof:placetype":"venue"
},
  "geometry": {"coordinates":[-74.39125199999999,40.446484],"type":"Point"}
}