{
  "type": "Feature",
  "properties": {
    "iso:country":"US",
    "sg:address":"98 Old Forge Rd",
    "sg:city":"Monroe Twp",
    "sg:classifiers":[
        {
            "category":"Building & Trades",
            "subcategory":"Construction",
            "type":"Services"
        }
    ],
    "sg:phone":"+1 732 521 1200",
    "sg:postcode":"08831",
    "sg:province":"NJ",
    "sg:tags":[
        "painter"
    ],
    "wof:name":"Gorcsos Paint & Paper",
    "wof:placetype":"venue"
},
  "geometry": {"coordinates":[-74.423892,40.35535],"type":"Point"}
}