{
  "type": "Feature",
  "properties": {
    "addr:full":"417 Kearny Ave Kearny NJ 07032",
    "addr:housenumber":"417",
    "addr:postcode":"07032",
    "addr:street":"Kearny Ave",
    "iso:country":"US",
    "sg:address":"417 Kearny Ave",
    "sg:city":"Kearny",
    "sg:classifiers":[
        {
            "category":"Banks & Credit Unions",
            "subcategory":"Bank",
            "type":"Services"
        }
    ],
    "sg:phone":"+1 201 991 4834",
    "sg:postcode":"07032",
    "sg:province":"NJ",
    "wof:name":"Fast Cash Atm",
    "wof:placetype":"venue"
},
  "geometry": {"coordinates":[-74.14818099999999,40.765122],"type":"Point"}
}