{
  "type": "Feature",
  "properties": {
    "addr:full":"177 Liberty Rd Englewood NJ 07631",
    "addr:housenumber":"177",
    "addr:postcode":"07631",
    "addr:street":"Liberty Rd",
    "iso:country":"US",
    "sg:address":"177 Liberty Rd",
    "sg:city":"Englewood",
    "sg:classifiers":[
        {
            "category":"Professional",
            "subcategory":"Art Services",
            "type":"Services"
        }
    ],
    "sg:phone":"+1   ",
    "sg:postcode":"07631",
    "sg:province":"NJ",
    "sg:tags":[
        "commercial",
        "design"
    ],
    "wof:name":"Abe Enterprises",
    "wof:placetype":"venue"
},
  "geometry": {"coordinates":[-73.98151799999999,40.899407],"type":"Point"}
}