{
  "type": "Feature",
  "properties": {
    "addr:full":"385 Morris Ave Ste 100 Springfield NJ 07081",
    "addr:housenumber":"385",
    "addr:postcode":"07081",
    "addr:street":"Morris Ave Ste 100",
    "iso:country":"US",
    "sg:address":"385 Morris Ave Ste 100",
    "sg:city":"Springfield",
    "sg:classifiers":[
        {
            "category":"Banks & Credit Unions",
            "subcategory":"Financial Services",
            "type":"Services"
        }
    ],
    "sg:phone":"+1 973 379 7447",
    "sg:postcode":"07081",
    "sg:province":"NJ",
    "sg:tags":[
        "broker",
        "mortgage"
    ],
    "sg:website":"www.mbanj.com",
    "wof:name":"Mortgage Bankers Association of Nj",
    "wof:placetype":"venue"
},
  "geometry": {"coordinates":[-74.315102,40.712399],"type":"Point"}
}