{
  "type": "Feature",
  "properties": {
    "addr:full":"5 Walnut Ter Keyport NJ 07735",
    "addr:housenumber":"5",
    "addr:postcode":"07735",
    "addr:street":"Walnut Ter",
    "iso:country":"US",
    "sg:address":"5 Walnut Ter",
    "sg:city":"Keyport",
    "sg:classifiers":[
        {
            "category":"Building & Trades",
            "subcategory":"Landscaping Services",
            "type":"Services"
        }
    ],
    "sg:phone":"+1 732 672 9676",
    "sg:postcode":"07735",
    "sg:province":"NJ",
    "sg:tags":[
        "lawn",
        "maintenance",
        "grounds"
    ],
    "wof:name":"Lady Bugs Lawn Maintenance",
    "wof:placetype":"venue"
},
  "geometry": {"coordinates":[-74.190371,40.441172],"type":"Point"}
}