{
  "type": "Feature",
  "properties": {
    "addr:full":"279 Central Ave Metuchen NJ 08840",
    "addr:housenumber":"279",
    "addr:postcode":"08840",
    "addr:street":"Central Ave",
    "iso:country":"US",
    "sg:address":"279 Central Ave",
    "sg:city":"Metuchen",
    "sg:classifiers":[
        {
            "category":"Wholesale",
            "subcategory":"Computers",
            "type":"Manufacturing & Wholesale Goods"
        },
        {
            "category":"Professional",
            "subcategory":"Computer Services",
            "type":"Services"
        }
    ],
    "sg:phone":"+1 732 635 1755",
    "sg:postcode":"08840",
    "sg:province":"NJ",
    "sg:tags":[
        "repair"
    ],
    "sg:website":"www.hypertechusa.com",
    "wof:name":"Hypertech Inc",
    "wof:placetype":"venue"
},
  "geometry": {"coordinates":[-74.37041499999999,40.546659],"type":"Point"}
}