{
  "type": "Feature",
  "properties": {
    "iso:country":"US",
    "sg:address":"155 Avenel St",
    "sg:city":"Avenel",
    "sg:classifiers":[
        {
            "category":"Organizations",
            "subcategory":"Labor Organization",
            "type":"Services"
        }
    ],
    "sg:phone":"+1 732 636 8546",
    "sg:postcode":"07001",
    "sg:province":"NJ",
    "wof:name":"PACE International Union",
    "wof:placetype":"venue"
},
  "geometry": {"coordinates":[-74.275898,40.576815],"type":"Point"}
}