{
  "type": "Feature",
  "properties": {
    "addr:full":"210 Ocean St Cape May NJ 08204",
    "addr:housenumber":"210",
    "addr:postcode":"08204",
    "addr:street":"Ocean St",
    "iso:country":"US",
    "sg:address":"210 Ocean St",
    "sg:city":"Cape May",
    "sg:classifiers":[
        {
            "category":"Restaurant",
            "type":"Food & Drink"
        }
    ],
    "sg:phone":"+1   ",
    "sg:postcode":"08204",
    "sg:province":"NJ",
    "sg:tags":[
        "eating"
    ],
    "wof:name":"Fredas Gourmet Shop & Deli",
    "wof:placetype":"venue"
},
  "geometry": {"coordinates":[-74.921339,38.932895],"type":"Point"}
}