{
  "type": "Feature",
  "properties": {
    "addr:full":"6201 Madison St West New York NJ 07093",
    "addr:housenumber":"6201",
    "addr:postcode":"nj 07093",
    "addr:street":"Madison St West",
    "iso:country":"US",
    "sg:address":"6201 Madison St",
    "sg:city":"West New York",
    "sg:classifiers":[
        {
            "category":"Personal",
            "subcategory":"Beauty Salon",
            "type":"Services"
        }
    ],
    "sg:phone":"+1 201 662 2424",
    "sg:postcode":"07093",
    "sg:province":"NJ",
    "sg:tags":[
        "shop"
    ],
    "wof:name":"Diamante Beauty Salon",
    "wof:placetype":"venue"
},
  "geometry": {"coordinates":[-74.01442900000001,40.792731],"type":"Point"}
}