{
  "type": "Feature",
  "properties": {
    "addr:full":"25 US Hwy 22 Springfield NJ 07081",
    "addr:housenumber":"25",
    "addr:postcode":"07081",
    "addr:street":"Us Hwy 22",
    "iso:country":"US",
    "sg:address":"25 US Hwy 22",
    "sg:city":"Springfield",
    "sg:classifiers":[
        {
            "category":"Real Estate",
            "subcategory":"Real Estate Agent",
            "type":"Services"
        }
    ],
    "sg:phone":"+1 973 258 0888",
    "sg:postcode":"07081",
    "sg:province":"NJ",
    "wof:name":"American Realty Group",
    "wof:placetype":"venue"
},
  "geometry": {"coordinates":[-74.312859,40.688004],"type":"Point"}
}