{
  "type": "Feature",
  "properties": {
    "iso:country":"US",
    "sg:address":"644 S Delsea Dr",
    "sg:city":"Clayton",
    "sg:classifiers":[
        {
            "category":"Restaurant",
            "type":"Food & Drink"
        }
    ],
    "sg:menulink":"http://www.allmenus.com/nj/clayton/12072-nicks-pizzeria/menu/",
    "sg:phone":"+1 856 307 1100",
    "sg:postcode":"08312",
    "sg:province":"NJ",
    "sg:tags":[
        "american",
        "steakhouse",
        "italian"
    ],
    "wof:name":"Nick's Pizzeria",
    "wof:placetype":"venue"
},
  "geometry": {"coordinates":[-75.088876,39.647219],"type":"Point"}
}