{
  "type": "Feature",
  "properties": {
    "iso:country":"US",
    "sg:address":"23 N 2nd St",
    "sg:city":"Cranford",
    "sg:classifiers":[
        {
            "category":"Real Estate",
            "subcategory":"Real Estate Operator",
            "type":"Services"
        }
    ],
    "sg:phone":"+1   ",
    "sg:postcode":"07029",
    "sg:province":"NJ",
    "sg:tags":[
        "apartment",
        "property"
    ],
    "wof:name":"Goodman Realty",
    "wof:placetype":"venue"
},
  "geometry": {"coordinates":[-74.160326,40.746304],"type":"Point"}
}