{
  "type": "Feature",
  "properties": {
    "addr:full":"55 Lexington St Fair Lawn NJ 07410",
    "addr:housenumber":"55",
    "addr:postcode":"07410",
    "addr:street":"Lexington St",
    "iso:country":"US",
    "sg:address":"55 Lexington St",
    "sg:city":"Fair Lawn",
    "sg:classifiers":[
        {
            "category":"Travel",
            "subcategory":"Travel Agent",
            "type":"Entertainment"
        }
    ],
    "sg:phone":"+1 201 797 3262",
    "sg:postcode":"07410",
    "sg:province":"NJ",
    "sg:tags":[
        "consultant"
    ],
    "wof:name":"Ro Z Tours",
    "wof:placetype":"venue"
},
  "geometry": {"coordinates":[-74.125962,40.933674],"type":"Point"}
}