{
  "type": "Feature",
  "properties": {
    "iso:country":"US",
    "sg:address":"101 College Rd E",
    "sg:city":"Princeton",
    "sg:classifiers":[
        {
            "category":"Shopping",
            "subcategory":"Pharmacy",
            "type":"Retail Goods"
        }
    ],
    "sg:phone":"+1   ",
    "sg:postcode":"08540",
    "sg:province":"NJ",
    "sg:tags":[
        "consulting",
        "management"
    ],
    "wof:name":"McKesson Drug Company",
    "wof:placetype":"venue"
},
  "geometry": {"coordinates":[-74.60086099999999,40.357003],"type":"Point"}
}