{
  "type": "Feature",
  "properties": {
    "iso:country":"US",
    "sg:address":"27 Bowers Ln",
    "sg:city":"Chatham",
    "sg:classifiers":[
        {
            "category":"Professional",
            "subcategory":"Computer Services",
            "type":"Services"
        }
    ],
    "sg:phone":"+1 973 665 0230",
    "sg:postcode":"07928",
    "sg:province":"NJ",
    "sg:tags":[
        "information",
        "technology"
    ],
    "wof:name":"Live Process",
    "wof:placetype":"venue"
},
  "geometry": {"coordinates":[-74.380905,40.73948],"type":"Point"}
}