{
  "type": "Feature",
  "properties": {
    "iso:country":"US",
    "sg:address":"2 Dewey Ln",
    "sg:city":"Glen Gardner",
    "sg:classifiers":[
        {
            "category":"Building & Trades",
            "subcategory":"Construction",
            "type":"Services"
        }
    ],
    "sg:phone":"+1 908 537 2850",
    "sg:postcode":"08826",
    "sg:province":"NJ",
    "sg:tags":[
        "marking",
        "maintenance",
        "parking"
    ],
    "wof:name":"Lebanon Twp Public Works Dept",
    "wof:placetype":"venue"
},
  "geometry": {"coordinates":[-74.907608,40.733411],"type":"Point"}
}