{
  "type": "Feature",
  "properties": {
    "iso:country":"US",
    "sg:address":"611 Embree Cres",
    "sg:city":"Westfield",
    "sg:classifiers":[
        {
            "category":"Professional",
            "subcategory":"Engineering",
            "type":"Services"
        }
    ],
    "sg:phone":"+1   ",
    "sg:postcode":"07090",
    "sg:province":"NJ",
    "wof:name":"Theodore Moss",
    "wof:placetype":"venue"
},
  "geometry": {"coordinates":[-74.36274400000001,40.653819],"type":"Point"}
}