{
  "type": "Feature",
  "properties": {
    "addr:full":"172 Woodport Rd Sparta NJ 07871",
    "addr:housenumber":"172",
    "addr:postcode":"07871",
    "addr:street":"Woodport Rd",
    "iso:country":"US",
    "sg:address":"172 Woodport Rd",
    "sg:city":"Sparta",
    "sg:classifiers":[
        {
            "category":"Health Services",
            "subcategory":"Chiropractor",
            "type":"Services"
        }
    ],
    "sg:phone":"+1 973 729 8884",
    "sg:postcode":"07871",
    "sg:province":"NJ",
    "wof:name":"Optimal Hlth Chiropractic Ctr",
    "wof:placetype":"venue"
},
  "geometry": {"coordinates":[-74.630667,41.024622],"type":"Point"}
}