{
  "type": "Feature",
  "properties": {
    "addr:full":"220 Lake Dr E Cherry Hill NJ 08002",
    "addr:housenumber":"220",
    "addr:postcode":"08002",
    "addr:street":"Lake Dr E",
    "iso:country":"US",
    "sg:address":"220 Lake Dr E",
    "sg:city":"Cherry Hill",
    "sg:classifiers":[
        {
            "category":"Health Services",
            "subcategory":"Clinic",
            "type":"Services"
        }
    ],
    "sg:phone":"+1 856 321 9460",
    "sg:postcode":"08002",
    "sg:province":"NJ",
    "wof:name":"21st Century Health & Benefits",
    "wof:placetype":"venue"
},
  "geometry": {"coordinates":[-75.003146,39.938701],"type":"Point"}
}