{
  "type": "Feature",
  "properties": {
    "iso:country":"US",
    "sg:address":"4 Lafite Ct",
    "sg:city":"Woodbury",
    "sg:classifiers":[
        {
            "category":"Health Services",
            "subcategory":"Doctor",
            "type":"Services"
        }
    ],
    "sg:phone":"+1   ",
    "sg:postcode":"08096",
    "sg:province":"NJ",
    "sg:tags":[
        "medical"
    ],
    "wof:name":"Edward Lewis Apetz",
    "wof:placetype":"venue"
},
  "geometry": {"coordinates":[-75.17902100000001,39.83276],"type":"Point"}
}