{
  "type": "Feature",
  "properties": {
    "iso:country":"US",
    "sg:address":"115 W Century Rd",
    "sg:city":"Paramus",
    "sg:classifiers":[
        {
            "category":"Professional",
            "type":"Services"
        }
    ],
    "sg:phone":"+1 201 813 1801",
    "sg:postcode":"07652",
    "sg:province":"NJ",
    "sg:tags":[
        "establishment"
    ],
    "wof:name":"Finnerty & Larocca",
    "wof:placetype":"venue"
},
  "geometry": {"coordinates":[-74.082421,40.935519],"type":"Point"}
}