{
  "type": "Feature",
  "properties": {
    "addr:full":"1010 Summit Ave Union City NJ 07087",
    "addr:housenumber":"1010",
    "addr:postcode":"07087",
    "addr:street":"Summit Ave",
    "iso:country":"US",
    "sg:address":"1010 Summit Ave",
    "sg:city":"Union City",
    "sg:classifiers":[
        {
            "category":"Professional",
            "subcategory":"Accounting & Tax Preparation",
            "type":"Services"
        }
    ],
    "sg:phone":"+1 201 864 1653",
    "sg:postcode":"07087",
    "sg:province":"NJ",
    "sg:tags":[
        "accountant"
    ],
    "wof:name":"Leonard's Tax Ctr",
    "wof:placetype":"venue"
},
  "geometry": {"coordinates":[-74.04226199999999,40.760448],"type":"Point"}
}