{
  "type": "Feature",
  "properties": {
    "iso:country":"US",
    "sg:address":"108 Eaton Crest Dr",
    "sg:city":"Eatontown",
    "sg:classifiers":[
        {
            "category":"Professional",
            "subcategory":"Research",
            "type":"Services"
        }
    ],
    "sg:phone":"+1 732 544 2142",
    "sg:postcode":"07724",
    "sg:province":"NJ",
    "sg:tags":[
        "nonphysical",
        "commercial"
    ],
    "wof:name":"SMI Research",
    "wof:placetype":"venue"
},
  "geometry": {"coordinates":[-74.072783,40.292619],"type":"Point"}
}