{
  "type": "Feature",
  "properties": {
    "addr:full":"10 Washington St Bridgeton NJ 08302",
    "addr:housenumber":"10",
    "addr:postcode":"08302",
    "addr:street":"Washington St",
    "iso:country":"US",
    "sg:address":"10 Washington St",
    "sg:city":"Bridgeton",
    "sg:classifiers":[
        {
            "category":"Education",
            "subcategory":"College",
            "type":"Public Place"
        }
    ],
    "sg:phone":"+1 856 459 0879",
    "sg:postcode":"08302",
    "sg:province":"NJ",
    "sg:tags":[
        "academic",
        "school"
    ],
    "wof:name":"Cumberland County College",
    "wof:placetype":"venue"
},
  "geometry": {"coordinates":[-75.235224,39.431521],"type":"Point"}
}