{
  "type": "Feature",
  "properties": {
    "iso:country":"US",
    "sg:address":"105 Tracy Pl",
    "sg:city":"Hackensack",
    "sg:classifiers":[
        {
            "category":"Health Services",
            "subcategory":"Doctor",
            "type":"Services"
        }
    ],
    "sg:phone":"+1 201 489 1843",
    "sg:postcode":"07601",
    "sg:province":"NJ",
    "sg:tags":[
        "physician",
        "surgeon"
    ],
    "wof:name":"Samuel K Dartey-Hayford MD",
    "wof:placetype":"venue"
},
  "geometry": {"coordinates":[-74.059281,40.891411],"type":"Point"}
}