{
  "type": "Feature",
  "properties": {
    "addr:full":"814 Wynetta Pl Paramus NJ 07652",
    "addr:housenumber":"814",
    "addr:postcode":"07652",
    "addr:street":"Wynetta Pl",
    "iso:country":"US",
    "sg:address":"814 Wynetta Pl",
    "sg:city":"Paramus",
    "sg:classifiers":[
        {
            "category":"Professional",
            "subcategory":"Computer Services",
            "type":"Services"
        }
    ],
    "sg:phone":"+1   ",
    "sg:postcode":"07652",
    "sg:province":"NJ",
    "sg:tags":[
        "related"
    ],
    "wof:name":"Pyramid Consulting Inc",
    "wof:placetype":"venue"
},
  "geometry": {"coordinates":[-74.08531499999999,40.976465],"type":"Point"}
}