{
  "type": "Feature",
  "properties": {
    "addr:full":"205 Paterson Ave West Paterson NJ 07424",
    "addr:housenumber":"205",
    "addr:postcode":"07424",
    "addr:street":"Paterson Ave West",
    "iso:country":"US",
    "sg:address":"205 Paterson Ave",
    "sg:city":"West Paterson",
    "sg:classifiers":[
        {
            "category":"Health Services",
            "subcategory":"Doctor",
            "type":"Services"
        }
    ],
    "sg:phone":"+1 973 256 0404",
    "sg:postcode":"07424",
    "sg:province":"NJ",
    "sg:tags":[
        "physician",
        "surgeon"
    ],
    "wof:name":"Womens Ob/Gyn",
    "wof:placetype":"venue"
},
  "geometry": {"coordinates":[-74.223316,40.884512],"type":"Point"}
}