{
  "type": "Feature",
  "properties": {
    "iso:country":"US",
    "sg:address":"124 Washington Ave",
    "sg:city":"Belleville",
    "sg:classifiers":[
        {
            "category":"Personal",
            "subcategory":"Nail Salon",
            "type":"Services"
        }
    ],
    "sg:phone":"+1 973 759 2111",
    "sg:postcode":"07109",
    "sg:province":"NJ",
    "wof:name":"New Honey Nails",
    "wof:placetype":"venue"
},
  "geometry": {"coordinates":[-74.15322399999999,40.785296],"type":"Point"}
}