{
  "type": "Feature",
  "properties": {
    "addr:full":"1115 Arnold Ave Pt Pleasant Bch NJ 08742",
    "addr:housenumber":"1115",
    "addr:postcode":"08742",
    "addr:street":"Arnold Ave Pt",
    "iso:country":"US",
    "sg:address":"1115 Arnold Ave",
    "sg:city":"Pt Pleasant Bch",
    "sg:classifiers":[
        {
            "category":"Health Services",
            "subcategory":"Doctor",
            "type":"Services"
        }
    ],
    "sg:phone":"+1 732 899 3363",
    "sg:postcode":"08742",
    "sg:province":"NJ",
    "sg:tags":[
        "dentist"
    ],
    "wof:name":"Fugedy & Mc Lees",
    "wof:placetype":"venue"
},
  "geometry": {"coordinates":[-74.06191099999999,40.08649],"type":"Point"}
}