{
  "type": "Feature",
  "properties": {
    "iso:country":"US",
    "sg:address":"6 Democracy Rd",
    "sg:city":"Columbia",
    "sg:classifiers":[
        {
            "category":"Government",
            "subcategory":"Office",
            "type":"Public Place"
        }
    ],
    "sg:phone":"+1 908 362 9443",
    "sg:postcode":"07832",
    "sg:province":"NJ",
    "sg:tags":[
        "village"
    ],
    "wof:name":"Blairstown Twp Animal Control",
    "wof:placetype":"venue"
},
  "geometry": {"coordinates":[-75.023853,40.975237],"type":"Point"}
}