{
  "type": "Feature",
  "properties": {
    "addr:full":"2768 John F Kennedy Blvd Jersey City NJ 07306",
    "addr:housenumber":"2768",
    "addr:postcode":"07306",
    "addr:street":"John F Kennedy Blvd",
    "iso:country":"US",
    "sg:address":"2768 John F Kennedy Blvd",
    "sg:city":"Jersey City",
    "sg:classifiers":[
        {
            "category":"Health Services",
            "subcategory":"Doctor",
            "type":"Services"
        }
    ],
    "sg:phone":"+1 201 451 0651",
    "sg:postcode":"07306",
    "sg:province":"NJ",
    "sg:tags":[
        "physician",
        "surgeon"
    ],
    "wof:name":"Nicanor Go MD",
    "wof:placetype":"venue"
},
  "geometry": {"coordinates":[-74.067972,40.730998],"type":"Point"}
}