{
  "type": "Feature",
  "properties": {
    "iso:country":"US",
    "sg:address":"151 Martin Luther King Jr Dr",
    "sg:city":"Jersey City",
    "sg:classifiers":[
        {
            "category":"Retail",
            "subcategory":"Event Space",
            "type":"Services"
        }
    ],
    "sg:phone":"+1 201 332 6322",
    "sg:postcode":"07305",
    "sg:province":"NJ",
    "sg:tags":[
        "venue"
    ],
    "wof:name":"Mossi Youth Council & Chocolate Ct",
    "wof:placetype":"venue"
},
  "geometry": {"coordinates":[-74.085843,40.705162],"type":"Point"}
}