{
  "type": "Feature",
  "properties": {
    "addr:full":"80 Main St Middlesex NJ 08846",
    "addr:housenumber":"80",
    "addr:postcode":"08846",
    "addr:street":"Main St",
    "iso:country":"US",
    "sg:address":"80 Main St",
    "sg:city":"Middlesex",
    "sg:classifiers":[
        {
            "category":"Building & Trades",
            "subcategory":"Electrical",
            "type":"Services"
        }
    ],
    "sg:phone":"+1 732 356 1110",
    "sg:postcode":"08846",
    "sg:province":"NJ",
    "sg:tags":[
        "communication",
        "telecommunication"
    ],
    "sg:website":"http://www.comcodata.com",
    "wof:name":"Comco Data Telecommunications Inc",
    "wof:placetype":"venue"
},
  "geometry": {"coordinates":[-74.489734,40.582781],"type":"Point"}
}