{
  "type": "Feature",
  "properties": {
    "iso:country":"US",
    "sg:address":"59 Rolling Hill Dr",
    "sg:city":"Chatham",
    "sg:classifiers":[
        {
            "category":"Professional",
            "subcategory":"Business Services",
            "type":"Services"
        }
    ],
    "sg:phone":"+1   ",
    "sg:postcode":"07928",
    "sg:province":"NJ",
    "wof:name":"Morgan Ld Co",
    "wof:placetype":"venue"
},
  "geometry": {"coordinates":[-74.411525,40.733027],"type":"Point"}
}