{
  "type": "Feature",
  "properties": {
    "addr:full":"11 E Winifred Ave Beach Haven NJ 08008",
    "addr:housenumber":"11",
    "addr:postcode":"08008",
    "addr:street":"E Winifred Ave",
    "iso:country":"US",
    "sg:address":"11 E Winifred Ave",
    "sg:city":"Beach Haven",
    "sg:classifiers":[
        {
            "category":"Organizations",
            "subcategory":"Community Association",
            "type":"Services"
        }
    ],
    "sg:phone":"+1   ",
    "sg:postcode":"08008",
    "sg:province":"NJ",
    "wof:name":"VFW 3729",
    "wof:placetype":"venue"
},
  "geometry": {"coordinates":[-74.204373,39.61093],"type":"Point"}
}