{
  "type": "Feature",
  "properties": {
    "addr:full":"73 Povershon Rd Nutley NJ 07110",
    "addr:housenumber":"73",
    "addr:postcode":"07110",
    "addr:street":"Povershon Rd",
    "iso:country":"US",
    "sg:address":"73 Povershon Rd",
    "sg:city":"Nutley",
    "sg:classifiers":[
        {
            "category":"Insurance",
            "subcategory":"Title Insurance",
            "type":"Services"
        },
        {
            "category":"Real Estate",
            "subcategory":"Real Estate Services",
            "type":"Services"
        }
    ],
    "sg:phone":"+1 973 662 0500",
    "sg:postcode":"07110",
    "sg:province":"NJ",
    "sg:tags":[
        "company",
        "carrier"
    ],
    "wof:name":"First Meridian Title Agcy Inc",
    "wof:placetype":"venue"
},
  "geometry": {"coordinates":[-74.171308,40.819153],"type":"Point"}
}