{
  "type": "Feature",
  "properties": {
    "addr:full":"676 US Hwy 206 Bordentown NJ 08505",
    "addr:housenumber":"676",
    "addr:postcode":"08505",
    "addr:street":"Us Hwy 206",
    "iso:country":"US",
    "sg:address":"676 US Hwy 206",
    "sg:city":"Bordentown",
    "sg:classifiers":[
        {
            "category":"Autos & Motor Vehicles",
            "subcategory":"Fuel & Gas Station",
            "type":"Retail Goods"
        }
    ],
    "sg:phone":"+1   ",
    "sg:postcode":"08505",
    "sg:province":"NJ",
    "sg:tags":[
        "station"
    ],
    "wof:name":"Pauls Service Center Inc",
    "wof:placetype":"venue"
},
  "geometry": {"coordinates":[-74.69965999999999,40.170462],"type":"Point"}
}