{
  "type": "Feature",
  "properties": {
    "addr:full":"226 School Rd E Marlboro NJ 07746",
    "addr:housenumber":"226",
    "addr:postcode":"07746",
    "addr:street":"School Rd E",
    "iso:country":"US",
    "sg:address":"226 School Rd E",
    "sg:city":"Marlboro",
    "sg:classifiers":[
        {
            "category":"Government",
            "subcategory":"Office",
            "type":"Public Place"
        }
    ],
    "sg:phone":"+1   ",
    "sg:postcode":"07746",
    "sg:province":"NJ",
    "sg:tags":[
        "conservation"
    ],
    "wof:name":"Fanelli Topsoil Inc",
    "wof:placetype":"venue"
},
  "geometry": {"coordinates":[-74.22860300000001,40.2886],"type":"Point"}
}