{
  "type": "Feature",
  "properties": {
    "addr:full":"617 Lafayette Ave Hawthorne NJ 07506",
    "addr:housenumber":"617",
    "addr:postcode":"07506",
    "addr:street":"Lafayette Ave",
    "iso:country":"US",
    "sg:address":"617 Lafayette Ave",
    "sg:city":"Hawthorne",
    "sg:classifiers":[
        {
            "category":"Banks & Credit Unions",
            "subcategory":"Bank",
            "type":"Services"
        }
    ],
    "sg:phone":"+1 973 423 0011",
    "sg:postcode":"07506",
    "sg:province":"NJ",
    "sg:tags":[
        "state",
        "commercial"
    ],
    "wof:name":"Commerce Bank NA",
    "wof:placetype":"venue"
},
  "geometry": {"coordinates":[-74.155559,40.959181],"type":"Point"}
}