{
  "type": "Feature",
  "properties": {
    "iso:country":"US",
    "sg:address":"2425 Pennington Rd",
    "sg:city":"Pennington",
    "sg:classifiers":[
        {
            "category":"Professional",
            "subcategory":"Computer Services",
            "type":"Services"
        }
    ],
    "sg:phone":"+1 609 818 0025",
    "sg:postcode":"08534",
    "sg:province":"NJ",
    "sg:tags":[
        "website",
        "design"
    ],
    "wof:name":"Newton Interactive",
    "wof:placetype":"venue"
},
  "geometry": {"coordinates":[-74.78375,40.299211],"type":"Point"}
}