{
  "type": "Feature",
  "properties": {
    "iso:country":"US",
    "sg:address":"30 Mall Dr W",
    "sg:city":"Jersey City",
    "sg:classifiers":[
        {
            "category":"Wholesale",
            "subcategory":"Drugs",
            "type":"Manufacturing & Wholesale Goods"
        }
    ],
    "sg:phone":"+1 201 217 5544",
    "sg:postcode":"07310",
    "sg:province":"NJ",
    "sg:tags":[
        "perfume"
    ],
    "wof:name":"Unlimited Scentsations",
    "wof:placetype":"venue"
},
  "geometry": {"coordinates":[-74.039326,40.729517],"type":"Point"}
}