{
  "type": "Feature",
  "properties": {
    "addr:full":"46 Journal Sq Jersey City NJ 07306",
    "addr:housenumber":"46",
    "addr:postcode":"07306",
    "addr:street":"Journal Sq",
    "iso:country":"US",
    "sg:address":"46 Journal Sq",
    "sg:city":"Jersey City",
    "sg:classifiers":[
        {
            "category":"Food & Beverages",
            "subcategory":"Groceries & Convenience Stores",
            "type":"Retail Goods"
        }
    ],
    "sg:phone":"+1 201 656 2665",
    "sg:postcode":"07306",
    "sg:province":"NJ",
    "wof:name":"Arjunnand Corp",
    "wof:placetype":"venue"
},
  "geometry": {"coordinates":[-74.06453500000001,40.73124],"type":"Point"}
}