{
  "type": "Feature",
  "properties": {
    "addr:full":"509 Pompton Ave Cedar Grove NJ 07009",
    "addr:housenumber":"509",
    "addr:postcode":"07009",
    "addr:street":"Pompton Ave",
    "iso:country":"US",
    "sg:address":"509 Pompton Ave",
    "sg:city":"Cedar Grove",
    "sg:classifiers":[
        {
            "category":"Shopping",
            "subcategory":"Bicycles & Sporting Goods",
            "type":"Retail Goods"
        }
    ],
    "sg:phone":"+1 973 239 8299",
    "sg:postcode":"07009",
    "sg:province":"NJ",
    "wof:name":"Non-Stop Hockey",
    "wof:placetype":"venue"
},
  "geometry": {"coordinates":[-74.22901400000001,40.850865],"type":"Point"}
}