{
  "type": "Feature",
  "properties": {
    "addr:full":"147 Speedwell Ave Morristown NJ 07960",
    "addr:housenumber":"147",
    "addr:postcode":"07960",
    "addr:street":"Speedwell Ave",
    "iso:country":"US",
    "sg:address":"147 Speedwell Ave",
    "sg:city":"Morristown",
    "sg:classifiers":[
        {
            "category":"Restaurant",
            "type":"Food & Drink"
        }
    ],
    "sg:menulink":"http://www.allmenus.com/nj/morristown/82422-dominos-pizza/menu/",
    "sg:phone":"+1 973 984 2900",
    "sg:postcode":"07960",
    "sg:province":"NJ",
    "sg:tags":[
        "american",
        "wing",
        "pizza"
    ],
    "wof:name":"Domino's Pizza",
    "wof:placetype":"venue"
},
  "geometry": {"coordinates":[-74.482426,40.803589],"type":"Point"}
}