{
  "type": "Feature",
  "properties": {
    "iso:country":"US",
    "sg:address":"555 US Hwy 46",
    "sg:city":"Kenvil",
    "sg:classifiers":[
        {
            "category":"Home & Garden",
            "subcategory":"Garden Supply",
            "type":"Retail Goods"
        }
    ],
    "sg:phone":"+1 973 927 0777",
    "sg:postcode":"07847",
    "sg:province":"NJ",
    "sg:tags":[
        "sprinkler"
    ],
    "wof:name":"Bert R Mittelstadt Landscaping",
    "wof:placetype":"venue"
},
  "geometry": {"coordinates":[-74.624386,40.879523],"type":"Point"}
}