{
  "type": "Feature",
  "properties": {
    "iso:country":"US",
    "sg:address":"352 High St",
    "sg:city":"Closter",
    "sg:classifiers":[
        {
            "category":"Building & Trades",
            "subcategory":"Construction",
            "type":"Services"
        }
    ],
    "sg:phone":"+1 201 784 9488",
    "sg:postcode":"07624",
    "sg:province":"NJ",
    "sg:tags":[
        "masonry",
        "contractor",
        "general"
    ],
    "wof:name":"Connolly Construction Inc",
    "wof:placetype":"venue"
},
  "geometry": {"coordinates":[-73.964738,40.972822],"type":"Point"}
}