{
  "type": "Feature",
  "properties": {
    "addr:full":"107 E Oak St Millville NJ 08332",
    "addr:housenumber":"107",
    "addr:postcode":"08332",
    "addr:street":"E Oak St",
    "iso:country":"US",
    "sg:address":"107 E Oak St",
    "sg:city":"Millville",
    "sg:classifiers":[
        {
            "category":"Home & Garden",
            "subcategory":"Building Materials",
            "type":"Retail Goods"
        }
    ],
    "sg:phone":"+1 856 825 1616",
    "sg:postcode":"08332",
    "sg:province":"NJ",
    "sg:tags":[
        "lumber"
    ],
    "wof:name":"Peter Lumber Roofing & Siding",
    "wof:placetype":"venue"
},
  "geometry": {"coordinates":[-75.03792199999999,39.400536],"type":"Point"}
}