{
  "type": "Feature",
  "properties": {
    "iso:country":"US",
    "sg:address":"111 Ingleside Ave",
    "sg:city":"Pennington",
    "sg:classifiers":[
        {
            "category":"Real Estate",
            "subcategory":"Real Estate Agent",
            "type":"Services"
        },
        {
            "category":"Professional",
            "subcategory":"Business Services",
            "type":"Services"
        }
    ],
    "sg:phone":"+1 609 737 0883",
    "sg:postcode":"08534",
    "sg:province":"NJ",
    "sg:tags":[
        "inspection"
    ],
    "wof:name":"All Star Home Inspections LLC",
    "wof:placetype":"venue"
},
  "geometry": {"coordinates":[-74.794214,40.31215],"type":"Point"}
}