{
  "type": "Feature",
  "properties": {
    "addr:full":"100 Springdale Rd Cherry Hill NJ 08003",
    "addr:housenumber":"100",
    "addr:postcode":"08003",
    "addr:street":"Springdale Rd",
    "iso:country":"US",
    "sg:address":"100 Springdale Rd",
    "sg:city":"Cherry Hill",
    "sg:classifiers":[
        {
            "category":"Food & Beverages",
            "subcategory":"Groceries & Convenience Stores",
            "type":"Retail Goods"
        }
    ],
    "sg:phone":"+1   ",
    "sg:postcode":"08003",
    "sg:province":"NJ",
    "wof:name":"Wawa",
    "wof:placetype":"venue"
},
  "geometry": {"coordinates":[-74.974912,39.860683],"type":"Point"}
}