{
  "type": "Feature",
  "properties": {
    "addr:full":"120 New England Ave Piscataway NJ 08854",
    "addr:housenumber":"120",
    "addr:postcode":"08854",
    "addr:street":"New England Ave",
    "iso:country":"US",
    "sg:address":"120 New England Ave",
    "sg:city":"Piscataway",
    "sg:classifiers":[
        {
            "category":"Manufacturing",
            "subcategory":"Food",
            "type":"Manufacturing & Wholesale Goods"
        }
    ],
    "sg:phone":"+1 732 445 6147",
    "sg:postcode":"08854",
    "sg:province":"NJ",
    "sg:tags":[
        "frozen",
        "specialty",
        "mfg"
    ],
    "wof:name":"Philadelphia Fresh Bake Co",
    "wof:placetype":"venue"
},
  "geometry": {"coordinates":[-74.467896,40.551657],"type":"Point"}
}