{
  "type": "Feature",
  "properties": {
    "addr:full":"168 E Front St Plainfield NJ 07060",
    "addr:housenumber":"168",
    "addr:postcode":"07060",
    "addr:street":"E Front St",
    "iso:country":"US",
    "sg:address":"168 E Front St",
    "sg:city":"Plainfield",
    "sg:classifiers":[
        {
            "category":"Professional",
            "type":"Services"
        }
    ],
    "sg:phone":"+1 908 769 3210",
    "sg:postcode":"07060",
    "sg:province":"NJ",
    "sg:tags":[
        "establishment"
    ],
    "wof:name":"A & A Gold",
    "wof:placetype":"venue"
},
  "geometry": {"coordinates":[-74.423019,40.619023],"type":"Point"}
}