{
  "type": "Feature",
  "properties": {
    "iso:country":"US",
    "sg:address":"12 Roszel Rd",
    "sg:city":"Princeton",
    "sg:classifiers":[
        {
            "category":"Social Services",
            "type":"Services"
        }
    ],
    "sg:phone":"+1 609 243 9779",
    "sg:postcode":"08540",
    "sg:province":"NJ",
    "wof:name":"Parents Anonymous of N J Inc",
    "wof:placetype":"venue"
},
  "geometry": {"coordinates":[-74.63752700000001,40.3214],"type":"Point"}
}