{
  "type": "Feature",
  "properties": {
    "iso:country":"US",
    "sg:address":"1254 US Hwy 22 Alt",
    "sg:city":"Phillipsburg",
    "sg:classifiers":[
        {
            "category":"Personal",
            "subcategory":"Beauty Salon",
            "type":"Services"
        }
    ],
    "sg:phone":"+1 908 454 5130",
    "sg:postcode":"08865",
    "sg:province":"NJ",
    "wof:name":"K-Nail",
    "wof:placetype":"venue"
},
  "geometry": {"coordinates":[-75.16874199999999,40.677477],"type":"Point"}
}