{
  "type": "Feature",
  "properties": {
    "addr:full":"8 Edwards Dr Hightstown NJ 08520",
    "addr:housenumber":"8",
    "addr:postcode":"08520",
    "addr:street":"Edwards Dr",
    "iso:country":"US",
    "sg:address":"8 Edwards Dr",
    "sg:city":"Hightstown",
    "sg:classifiers":[
        {
            "category":"Wholesale",
            "subcategory":"Apparel",
            "type":"Manufacturing & Wholesale Goods"
        }
    ],
    "sg:phone":"+1 609 443 9791",
    "sg:postcode":"08520",
    "sg:province":"NJ",
    "sg:tags":[
        "clothing"
    ],
    "wof:name":"Sarmite Wearable Art Inc",
    "wof:placetype":"venue"
},
  "geometry": {"coordinates":[-74.551699,40.267239],"type":"Point"}
}