{
  "type": "Feature",
  "properties": {
    "addr:full":"515 Bernita Dr Westwood NJ 07675",
    "addr:housenumber":"515",
    "addr:postcode":"07675",
    "addr:street":"Bernita Dr",
    "iso:country":"US",
    "sg:address":"515 Bernita Dr",
    "sg:city":"Westwood",
    "sg:classifiers":[
        {
            "category":"Real Estate",
            "subcategory":"Real Estate Agent",
            "type":"Services"
        }
    ],
    "sg:phone":"+1   ",
    "sg:postcode":"07675",
    "sg:province":"NJ",
    "wof:name":"Cadiz Property Management LLC",
    "wof:placetype":"venue"
},
  "geometry": {"coordinates":[-74.019234,41.01838],"type":"Point"}
}