{
  "type": "Feature",
  "properties": {
    "addr:full":"210 Talmage Ave Bound Brook NJ 08805",
    "addr:housenumber":"210",
    "addr:postcode":"08805",
    "addr:street":"Talmage Ave",
    "iso:country":"US",
    "sg:address":"210 Talmage Ave",
    "sg:city":"Bound Brook",
    "sg:classifiers":[
        {
            "category":"Restaurant",
            "type":"Food & Drink"
        }
    ],
    "sg:phone":"+1 732 868 9070",
    "sg:postcode":"08805",
    "sg:province":"NJ",
    "sg:tags":[
        "eating"
    ],
    "wof:name":"Sandra's Restaurant",
    "wof:placetype":"venue"
},
  "geometry": {"coordinates":[-74.54000000000001,40.561165],"type":"Point"}
}