{
  "type": "Feature",
  "properties": {
    "iso:country":"US",
    "sg:address":"12 Stockton St",
    "sg:city":"Princeton",
    "sg:classifiers":[
        {
            "category":"Government",
            "subcategory":"Office",
            "type":"Public Place"
        }
    ],
    "sg:phone":"+1 609 497 7607",
    "sg:postcode":"08540",
    "sg:province":"NJ",
    "sg:tags":[
        "city",
        "taxation"
    ],
    "wof:name":"Princeton Tax Assessor",
    "wof:placetype":"venue"
},
  "geometry": {"coordinates":[-74.664429,40.348231],"type":"Point"}
}