{
  "type": "Feature",
  "properties": {
    "iso:country":"US",
    "sg:address":"44 Tempe Wick Rd",
    "sg:city":"Mendham",
    "sg:classifiers":[
        {
            "category":"Health Services",
            "subcategory":"Doctor",
            "type":"Services"
        }
    ],
    "sg:phone":"+1 973 543 4336",
    "sg:postcode":"07945",
    "sg:province":"NJ",
    "sg:tags":[
        "physician",
        "surgeon",
        "medical"
    ],
    "wof:name":"David E Knoop MD PC",
    "wof:placetype":"venue"
},
  "geometry": {"coordinates":[-74.56935799999999,40.771494],"type":"Point"}
}