{
  "type": "Feature",
  "properties": {
    "addr:full":"8 Johnson Pl Oak Ridge NJ 07438",
    "addr:housenumber":"8",
    "addr:postcode":"07438",
    "addr:street":"Johnson Pl",
    "iso:country":"US",
    "sg:address":"8 Johnson Pl",
    "sg:city":"Oak Ridge",
    "sg:classifiers":[
        {
            "category":"Education",
            "subcategory":"Library",
            "type":"Public Place"
        }
    ],
    "sg:phone":"+1 973 697 7821",
    "sg:postcode":"07438",
    "sg:province":"NJ",
    "wof:name":"New Jersey Branch Shut In Soc",
    "wof:placetype":"venue"
},
  "geometry": {"coordinates":[-74.491957,41.029079],"type":"Point"}
}