{
  "type": "Feature",
  "properties": {
    "addr:full":"1701 N 2nd St Millville NJ 08332",
    "addr:housenumber":"1701",
    "addr:postcode":"08332",
    "addr:street":"N 2Nd St",
    "iso:country":"US",
    "sg:address":"1701 N 2nd St",
    "sg:city":"Millville",
    "sg:classifiers":[
        {
            "category":"Restaurant",
            "type":"Food & Drink"
        }
    ],
    "sg:phone":"+1 856 327 3331",
    "sg:postcode":"08332",
    "sg:province":"NJ",
    "wof:name":"Eagle Family Restaurant",
    "wof:placetype":"venue"
},
  "geometry": {"coordinates":[-75.038314,39.410643],"type":"Point"}
}