{
  "type": "Feature",
  "properties": {
    "iso:country":"US",
    "sg:address":"407 Bloomfield Dr",
    "sg:city":"West Berlin",
    "sg:classifiers":[
        {
            "category":"Utilities",
            "subcategory":"Telephone",
            "type":"Services"
        }
    ],
    "sg:phone":"+1 856 768 7799",
    "sg:postcode":"08091",
    "sg:province":"NJ",
    "sg:tags":[
        "telecommunication"
    ],
    "sg:website":"www.ititelecom.com",
    "wof:name":"Independence Telecommunication",
    "wof:placetype":"venue"
},
  "geometry": {"coordinates":[-74.92655000000001,39.81477],"type":"Point"}
}