{
  "type": "Feature",
  "properties": {
    "addr:full":"36 N Mill Rd Princeton Junction NJ 08550",
    "addr:housenumber":"36",
    "addr:postcode":"08550",
    "addr:street":"N Mill Rd",
    "iso:country":"US",
    "sg:address":"36 N Mill Rd",
    "sg:city":"Princeton Junction",
    "sg:classifiers":[
        {
            "category":"Arts & Performance",
            "subcategory":"Theater",
            "type":"Entertainment"
        }
    ],
    "sg:phone":"+1   ",
    "sg:postcode":"08550",
    "sg:province":"NJ",
    "sg:tags":[
        "group"
    ],
    "wof:name":"Inneract Theatre Co",
    "wof:placetype":"venue"
},
  "geometry": {"coordinates":[-74.609521,40.310061],"type":"Point"}
}