{
  "type": "Feature",
  "properties": {
    "iso:country":"US",
    "sg:address":"17 Kimberly Ct",
    "sg:city":"Red Bank",
    "sg:classifiers":[
        {
            "category":"Professional",
            "type":"Services"
        }
    ],
    "sg:phone":"+1   ",
    "sg:postcode":"07747",
    "sg:province":"NJ",
    "wof:name":"Erik Peter Cook",
    "wof:placetype":"venue"
},
  "geometry": {"coordinates":[-74.239797,40.405733],"type":"Point"}
}