{
  "type": "Feature",
  "properties": {
    "iso:country":"US",
    "sg:address":"3 Rockledge Rd",
    "sg:city":"Randolph",
    "sg:classifiers":[
        {
            "category":"Insurance",
            "subcategory":"Insurance Agent",
            "type":"Services"
        }
    ],
    "sg:phone":"+1 973 442 8185",
    "sg:postcode":"07869",
    "sg:province":"NJ",
    "sg:tags":[
        "consultant"
    ],
    "wof:name":"Cambridge Galaher",
    "wof:placetype":"venue"
},
  "geometry": {"coordinates":[-74.546424,40.838392],"type":"Point"}
}