{
  "type": "Feature",
  "properties": {
    "addr:full":"37 Johnson Rd Somerset NJ 08873",
    "addr:housenumber":"37",
    "addr:postcode":"08873",
    "addr:street":"Johnson Rd",
    "iso:country":"US",
    "sg:address":"37 Johnson Rd",
    "sg:city":"Somerset",
    "sg:classifiers":[
        {
            "category":"Freight",
            "type":"Transportation"
        }
    ],
    "sg:phone":"+1 732 296 0383",
    "sg:postcode":"08873",
    "sg:province":"NJ",
    "wof:name":"Scafe Logistics Inc",
    "wof:placetype":"venue"
},
  "geometry": {"coordinates":[-74.49325899999999,40.495878],"type":"Point"}
}