{
  "type": "Feature",
  "properties": {
    "addr:full":"7025 Colonial Hwy Pennsauken NJ 08109",
    "addr:housenumber":"7025",
    "addr:postcode":"08109",
    "addr:street":"Colonial Hwy",
    "iso:country":"US",
    "sg:address":"7025 Colonial Hwy",
    "sg:city":"Pennsauken",
    "sg:phone":"+1 856 663 8607",
    "sg:postcode":"08109",
    "sg:province":"NJ",
    "sg:tags":[
        "equipment",
        "station"
    ],
    "wof:name":"Phoenix Petroleum Distr LLC",
    "wof:placetype":"venue"
},
  "geometry": {"coordinates":[-75.07539300000001,39.931212],"type":"Point"}
}