{
  "type": "Feature",
  "properties": {
    "iso:country":"US",
    "sg:address":"200 Helen St",
    "sg:city":"South Plainfield",
    "sg:classifiers":[
        {
            "category":"Professional",
            "type":"Services"
        }
    ],
    "sg:phone":"+1 908 757 5800",
    "sg:postcode":"07080",
    "sg:province":"NJ",
    "sg:tags":[
        "establishment"
    ],
    "wof:name":"Rullo V & Sons Inc",
    "wof:placetype":"venue"
},
  "geometry": {"coordinates":[-74.413999,40.555863],"type":"Point"}
}