{
  "type": "Feature",
  "properties": {
    "addr:full":"40 Hope St East Rutherford NJ 07073",
    "addr:housenumber":"40",
    "addr:postcode":"07073",
    "addr:street":"Hope St",
    "iso:country":"US",
    "sg:address":"40 Hope St",
    "sg:city":"East Rutherford",
    "sg:classifiers":[
        {
            "category":"Building & Trades",
            "subcategory":"Cleaning & Sanitation",
            "type":"Services"
        }
    ],
    "sg:phone":"+1   ",
    "sg:postcode":"07073",
    "sg:province":"NJ",
    "sg:tags":[
        "maintenance"
    ],
    "wof:name":"Bos Cleaning Service",
    "wof:placetype":"venue"
},
  "geometry": {"coordinates":[-74.11506199999999,40.84875],"type":"Point"}
}