{
  "type": "Feature",
  "properties": {
    "iso:country":"US",
    "sg:address":"107 S Plainfield Ave",
    "sg:city":"South Plainfield",
    "sg:classifiers":[
        {
            "category":"Professional",
            "subcategory":"Management & Consulting",
            "type":"Services"
        }
    ],
    "sg:phone":"+1 908 755 6789",
    "sg:postcode":"07080",
    "sg:province":"NJ",
    "sg:tags":[
        "food"
    ],
    "wof:name":"Sodexho",
    "wof:placetype":"venue"
},
  "geometry": {"coordinates":[-74.40837399999999,40.580542],"type":"Point"}
}