{
  "type": "Feature",
  "properties": {
    "addr:full":"547 Main St East Orange NJ 07018",
    "addr:housenumber":"547",
    "addr:postcode":"07018",
    "addr:street":"Main St East",
    "iso:country":"US",
    "sg:address":"547 Main St",
    "sg:city":"East Orange",
    "sg:classifiers":[
        {
            "category":"Professional",
            "subcategory":"Accounting & Tax Preparation",
            "type":"Services"
        }
    ],
    "sg:phone":"+1 973 674 6089",
    "sg:postcode":"07018",
    "sg:province":"NJ",
    "sg:tags":[
        "return",
        "filing"
    ],
    "wof:name":"H & R Block Tax Svc",
    "wof:placetype":"venue"
},
  "geometry": {"coordinates":[-74.21932200000001,40.76721],"type":"Point"}
}