{
  "type": "Feature",
  "properties": {
    "addr:full":"380 Pine Tavern Rd Monroeville NJ 08343",
    "addr:housenumber":"380",
    "addr:postcode":"08343",
    "addr:street":"Pine Tavern Rd",
    "iso:country":"US",
    "sg:address":"380 Pine Tavern Rd",
    "sg:city":"Monroeville",
    "sg:classifiers":[
        {
            "category":"Building & Trades",
            "subcategory":"Construction",
            "type":"Services"
        }
    ],
    "sg:phone":"+1 856 358 8338",
    "sg:postcode":"08343",
    "sg:province":"NJ",
    "sg:tags":[
        "general",
        "contractor"
    ],
    "wof:name":"J & G Builders",
    "wof:placetype":"venue"
},
  "geometry": {"coordinates":[-75.208592,39.650185],"type":"Point"}
}