{
  "type": "Feature",
  "properties": {
    "addr:full":"173 Ellisen Rd Watchung NJ 07069",
    "addr:housenumber":"173",
    "addr:postcode":"07069",
    "addr:street":"Ellisen Rd",
    "iso:country":"US",
    "sg:address":"173 Ellisen Rd",
    "sg:city":"Watchung",
    "sg:classifiers":[
        {
            "category":"Professional",
            "subcategory":"Lawyer & Legal Services",
            "type":"Services"
        }
    ],
    "sg:phone":"+1 908 754 8186",
    "sg:postcode":"07069",
    "sg:province":"NJ",
    "wof:name":"Maglio Robert F Law Offices",
    "wof:placetype":"venue"
},
  "geometry": {"coordinates":[-74.428337,40.653101],"type":"Point"}
}