{
  "type": "Feature",
  "properties": {
    "addr:full":"600 State Rte 27 Iselin NJ 08830",
    "addr:housenumber":"600",
    "addr:postcode":"08830",
    "addr:street":"State Rte 27",
    "iso:country":"US",
    "sg:address":"600 State Rte 27",
    "sg:city":"Iselin",
    "sg:classifiers":[
        {
            "category":"Retail",
            "subcategory":"Auto Repair",
            "type":"Services"
        },
        {
            "category":"Autos & Motor Vehicles",
            "subcategory":"Auto Supplies",
            "type":"Retail Goods"
        }
    ],
    "sg:phone":"+1 732 283 2472",
    "sg:postcode":"08830",
    "sg:province":"NJ",
    "sg:tags":[
        "wheel",
        "axle",
        "alignment"
    ],
    "wof:name":"Deepa Auto Repairs",
    "wof:placetype":"venue"
},
  "geometry": {"coordinates":[-74.312111,40.5793],"type":"Point"}
}