{
  "type": "Feature",
  "properties": {
    "iso:country":"US",
    "sg:address":"140 Parker Rd",
    "sg:city":"Elizabeth",
    "sg:classifiers":[
        {
            "category":"Building & Trades",
            "subcategory":"Construction",
            "type":"Services"
        }
    ],
    "sg:phone":"+1 201 436 1099",
    "sg:postcode":"07208",
    "sg:province":"NJ",
    "sg:tags":[
        "hanging",
        "contractor"
    ],
    "wof:name":"Harveys Painting",
    "wof:placetype":"venue"
},
  "geometry": {"coordinates":[-74.218726,40.674802],"type":"Point"}
}