{
  "type": "Feature",
  "properties": {
    "iso:country":"US",
    "sg:address":"5 Industrial Rd",
    "sg:city":"Fairfield",
    "sg:classifiers":[
        {
            "category":"Building & Trades",
            "subcategory":"Plumbing",
            "type":"Services"
        }
    ],
    "sg:phone":"+1 973 882 8190",
    "sg:postcode":"07004",
    "sg:province":"NJ",
    "sg:website":"www.davidsonandhoward.com",
    "wof:name":"Davidson and Howard Inc",
    "wof:placetype":"venue"
},
  "geometry": {"coordinates":[-74.31259900000001,40.864498],"type":"Point"}
}