{
  "type": "Feature",
  "properties": {
    "iso:country":"US",
    "sg:address":"321 Pinedge Dr",
    "sg:city":"West Berlin",
    "sg:classifiers":[
        {
            "category":"Wholesale",
            "subcategory":"Machinery & Supplies",
            "type":"Manufacturing & Wholesale Goods"
        }
    ],
    "sg:phone":"+1 856 809 9799",
    "sg:postcode":"08091",
    "sg:province":"NJ",
    "sg:tags":[
        "equipment",
        "transportation"
    ],
    "wof:name":"BBA Project Inc",
    "wof:placetype":"venue"
},
  "geometry": {"coordinates":[-74.921271,39.811193],"type":"Point"}
}