{
  "type": "Feature",
  "properties": {
    "addr:full":"57 William St Newark NJ 07102",
    "addr:housenumber":"57",
    "addr:postcode":"07102",
    "addr:street":"William St",
    "iso:country":"US",
    "sg:address":"57 William St",
    "sg:city":"Newark",
    "sg:classifiers":[
        {
            "category":"Restaurant",
            "type":"Food & Drink"
        }
    ],
    "sg:menulink":"http://www.allmenus.com/nj/newark/27122-amins/menu/",
    "sg:phone":"+1 973 621 2111",
    "sg:postcode":"07102",
    "sg:province":"NJ",
    "sg:tags":[
        "asian",
        "chinese"
    ],
    "wof:name":"Amin's",
    "wof:placetype":"venue"
},
  "geometry": {"coordinates":[-74.176193,40.733979],"type":"Point"}
}