{
  "type": "Feature",
  "properties": {
    "addr:full":"7 N Beverwyck Rd Lake Hiawatha NJ 07034",
    "addr:housenumber":"7",
    "addr:postcode":"07034",
    "addr:street":"N Beverwyck Rd",
    "iso:country":"US",
    "sg:address":"7 N Beverwyck Rd",
    "sg:city":"Lake Hiawatha",
    "sg:classifiers":[
        {
            "category":"Restaurant",
            "type":"Food & Drink"
        }
    ],
    "sg:phone":"+1 973 263 2022",
    "sg:postcode":"07034",
    "sg:province":"NJ",
    "sg:tags":[
        "pizza"
    ],
    "wof:name":"Valentino's Pizza",
    "wof:placetype":"venue"
},
  "geometry": {"coordinates":[-74.382908,40.877542],"type":"Point"}
}