{
  "type": "Feature",
  "properties": {
    "addr:full":"24 Commerce St Newark NJ 07102",
    "addr:housenumber":"24",
    "addr:postcode":"07102",
    "addr:street":"Commerce St",
    "iso:country":"US",
    "sg:address":"24 Commerce St",
    "sg:city":"Newark",
    "sg:classifiers":[
        {
            "category":"Building & Trades",
            "subcategory":"Construction",
            "type":"Services"
        }
    ],
    "sg:phone":"+1 973 643 1000",
    "sg:postcode":"07102",
    "sg:province":"NJ",
    "sg:tags":[
        "contractor"
    ],
    "wof:name":"Arcade Cleaning Contractors Inc",
    "wof:placetype":"venue"
},
  "geometry": {"coordinates":[-74.170119,40.736545],"type":"Point"}
}