{
  "type": "Feature",
  "properties": {
    "addr:full":"50 Parker Rd Chester NJ 07930",
    "addr:housenumber":"50",
    "addr:postcode":"07930",
    "addr:street":"Parker Rd",
    "iso:country":"US",
    "sg:address":"50 Parker Rd",
    "sg:city":"Chester",
    "sg:classifiers":[
        {
            "category":"Autos & Motor Vehicles",
            "subcategory":"Fuel & Gas Station",
            "type":"Retail Goods"
        }
    ],
    "sg:phone":"+1 908 879 9355",
    "sg:postcode":"07930",
    "sg:province":"NJ",
    "sg:tags":[
        "oil"
    ],
    "wof:name":"Milltown Motor Works",
    "wof:placetype":"venue"
},
  "geometry": {"coordinates":[-74.74002900000001,40.765054],"type":"Point"}
}