{
  "type": "Feature",
  "properties": {
    "iso:country":"US",
    "sg:address":"28 53rd St",
    "sg:city":"Sea Isle City",
    "sg:classifiers":[
        {
            "category":"Building & Trades",
            "subcategory":"Construction",
            "type":"Services"
        }
    ],
    "sg:phone":"+1 609 263 0500",
    "sg:postcode":"08243",
    "sg:province":"NJ",
    "sg:tags":[
        "house",
        "builder",
        "deck"
    ],
    "wof:name":"Gannon Builders Inc",
    "wof:placetype":"venue"
},
  "geometry": {"coordinates":[-74.697703,39.147502],"type":"Point"}
}