{
  "type": "Feature",
  "properties": {
    "iso:country":"US",
    "sg:address":"24 Fenton Dr",
    "sg:city":"Short Hills",
    "sg:classifiers":[
        {
            "category":"Professional",
            "subcategory":"Management & Consulting",
            "type":"Services"
        }
    ],
    "sg:phone":"+1   ",
    "sg:postcode":"07078",
    "sg:province":"NJ",
    "sg:tags":[
        "public",
        "relations"
    ],
    "wof:name":"Deborah Green Co",
    "wof:placetype":"venue"
},
  "geometry": {"coordinates":[-74.309605,40.75298],"type":"Point"}
}