{
  "type": "Feature",
  "properties": {
    "iso:country":"US",
    "sg:address":"334 Somerset St",
    "sg:city":"North Plainfield",
    "sg:classifiers":[
        {
            "category":"Local Transit",
            "type":"Transportation"
        },
        {
            "category":"Organizations",
            "subcategory":"Community Association",
            "type":"Services"
        }
    ],
    "sg:phone":"+1 908 757 3054",
    "sg:postcode":"07060",
    "sg:province":"NJ",
    "sg:tags":[
        "squad",
        "rescue"
    ],
    "wof:name":"North Plainfield Rescue Squad",
    "wof:placetype":"venue"
},
  "geometry": {"coordinates":[-74.42988099999999,40.622038],"type":"Point"}
}