{
  "type": "Feature",
  "properties": {
    "iso:country":"US",
    "sg:address":"35 Locust Ave",
    "sg:city":"Roseland",
    "sg:classifiers":[
        {
            "category":"Real Estate",
            "subcategory":"Real Estate Operator",
            "type":"Services"
        }
    ],
    "sg:phone":"+1 973 226 8645",
    "sg:postcode":"07068",
    "sg:province":"NJ",
    "sg:tags":[
        "apartment"
    ],
    "wof:name":"Nob Hill Garden Apartment Swim Club",
    "wof:placetype":"venue"
},
  "geometry": {"coordinates":[-74.31710099999999,40.812599],"type":"Point"}
}