{
  "type": "Feature",
  "properties": {
    "iso:country":"US",
    "sg:address":"615 Co Rd 627",
    "sg:city":"Bloomsbury",
    "sg:classifiers":[
        {
            "category":"Food & Beverages",
            "subcategory":"Groceries & Convenience Stores",
            "type":"Retail Goods"
        }
    ],
    "sg:phone":"+1   ",
    "sg:postcode":"08804",
    "sg:province":"NJ",
    "wof:name":"Warren Glenn Grocery",
    "wof:placetype":"venue"
},
  "geometry": {"coordinates":[-75.14675699999999,40.628444],"type":"Point"}
}