{
  "type": "Feature",
  "properties": {
    "addr:full":"1 Franklin St Matawan NJ 07747",
    "addr:housenumber":"1",
    "addr:postcode":"07747",
    "addr:street":"Franklin St",
    "iso:country":"US",
    "sg:address":"1 Franklin St",
    "sg:city":"Matawan",
    "sg:classifiers":[
        {
            "category":"Real Estate",
            "subcategory":"Real Estate Operator",
            "type":"Services"
        }
    ],
    "sg:phone":"+1   ",
    "sg:postcode":"07747",
    "sg:province":"NJ",
    "sg:tags":[
        "building",
        "nonresidential"
    ],
    "wof:name":"Cherry Properties LLC",
    "wof:placetype":"venue"
},
  "geometry": {"coordinates":[-74.23650499999999,40.410771],"type":"Point"}
}