{
  "type": "Feature",
  "properties": {
    "iso:country":"US",
    "sg:address":"358 North Ave",
    "sg:city":"Dunellen",
    "sg:classifiers":[
        {
            "category":"Social Services",
            "subcategory":"Child Care",
            "type":"Services"
        }
    ],
    "sg:phone":"+1 732 424 0770",
    "sg:postcode":"08812",
    "sg:province":"NJ",
    "wof:name":"Precious Moments Academy",
    "wof:placetype":"venue"
},
  "geometry": {"coordinates":[-74.463002,40.591895],"type":"Point"}
}