{
  "type": "Feature",
  "properties": {
    "addr:full":"9130 Pennsauken Hwy Pennsauken NJ 08110",
    "addr:housenumber":"9130",
    "addr:postcode":"08110",
    "addr:street":"Pennsauken Hwy",
    "iso:country":"US",
    "sg:address":"9130 Pennsauken Hwy",
    "sg:city":"Pennsauken",
    "sg:classifiers":[
        {
            "category":"Wholesale",
            "subcategory":"Hardware",
            "type":"Manufacturing & Wholesale Goods"
        }
    ],
    "sg:phone":"+1 856 662 9114",
    "sg:postcode":"08110",
    "sg:province":"NJ",
    "sg:tags":[
        "fastener"
    ],
    "sg:website":"www.guidoncorp.com",
    "wof:name":"Guidon Corp",
    "wof:placetype":"venue"
},
  "geometry": {"coordinates":[-75.024839,39.977503],"type":"Point"}
}