{
  "type": "Feature",
  "properties": {
    "addr:full":"1182 State Rte 70 Cherry Hill NJ 08034",
    "addr:housenumber":"1182",
    "addr:postcode":"08034",
    "addr:street":"State Rte 70",
    "iso:country":"US",
    "sg:address":"1182 State Rte 70",
    "sg:city":"Cherry Hill",
    "sg:classifiers":[
        {
            "category":"Professional",
            "type":"Services"
        }
    ],
    "sg:phone":"+1 856 427 9444",
    "sg:postcode":"08034",
    "sg:province":"NJ",
    "sg:tags":[
        "establishment"
    ],
    "wof:name":"Sound Of Tristate",
    "wof:placetype":"venue"
},
  "geometry": {"coordinates":[-74.991514,39.91053],"type":"Point"}
}