{
  "type": "Feature",
  "properties": {
    "addr:full":"50 Thoreau Dr Freehold NJ 07728",
    "addr:housenumber":"50",
    "addr:postcode":"07728",
    "addr:street":"Thoreau Dr",
    "iso:country":"US",
    "sg:address":"50 Thoreau Dr",
    "sg:city":"Freehold",
    "sg:classifiers":[
        {
            "category":"Building & Trades",
            "subcategory":"Construction",
            "type":"Services"
        }
    ],
    "sg:phone":"+1 732 866 4011",
    "sg:postcode":"07728",
    "sg:province":"NJ",
    "sg:tags":[
        "company"
    ],
    "wof:name":"Huntington Knolls Construction",
    "wof:placetype":"venue"
},
  "geometry": {"coordinates":[-74.245723,40.254371],"type":"Point"}
}