{
  "type": "Feature",
  "properties": {
    "iso:country":"US",
    "sg:address":"623 Lacey Rd",
    "sg:city":"Forked River",
    "sg:classifiers":[
        {
            "category":"Professional",
            "subcategory":"Accounting & Tax Preparation",
            "type":"Services"
        }
    ],
    "sg:phone":"+1 609 693 3900",
    "sg:postcode":"08731",
    "sg:province":"NJ",
    "wof:name":"Thomas C Morrissey CPA",
    "wof:placetype":"venue"
},
  "geometry": {"coordinates":[-74.200695,39.853302],"type":"Point"}
}