{
  "type": "Feature",
  "properties": {
    "iso:country":"US",
    "sg:address":"25 Rockwood Pl",
    "sg:city":"Englewood",
    "sg:classifiers":[
        {
            "category":"Real Estate",
            "subcategory":"Real Estate Agent",
            "type":"Services"
        }
    ],
    "sg:phone":"+1 201 541 1210",
    "sg:postcode":"07631",
    "sg:province":"NJ",
    "wof:name":"Theodore P Engelbrecht Real Es",
    "wof:placetype":"venue"
},
  "geometry": {"coordinates":[-73.982062,40.878858],"type":"Point"}
}