{
  "type": "Feature",
  "properties": {
    "addr:full":"6 Pinecliff Ct Haledon NJ 07508",
    "addr:housenumber":"6",
    "addr:postcode":"07508",
    "addr:street":"Pinecliff Ct",
    "iso:country":"US",
    "sg:address":"6 Pinecliff Ct",
    "sg:city":"Haledon",
    "sg:classifiers":[
        {
            "category":"Building & Trades",
            "subcategory":"Construction",
            "type":"Services"
        }
    ],
    "sg:phone":"+1 973 427 7337",
    "sg:postcode":"07508",
    "sg:province":"NJ",
    "sg:tags":[
        "floor",
        "laying",
        "contractor"
    ],
    "wof:name":"Oak Tree Floor Refinishers",
    "wof:placetype":"venue"
},
  "geometry": {"coordinates":[-74.204503,40.976992],"type":"Point"}
}