{
  "type": "Feature",
  "properties": {
    "iso:country":"US",
    "sg:address":"155 Borden Rd",
    "sg:city":"Middletown",
    "sg:classifiers":[
        {
            "category":"Professional",
            "subcategory":"Computer Services",
            "type":"Services"
        }
    ],
    "sg:phone":"+1 732 671 2319",
    "sg:postcode":"07748",
    "sg:province":"NJ",
    "sg:tags":[
        "design",
        "system",
        "analysis"
    ],
    "wof:name":"M N R Computer Consultants",
    "wof:placetype":"venue"
},
  "geometry": {"coordinates":[-74.132428,40.37333],"type":"Point"}
}