{
  "type": "Feature",
  "properties": {
    "addr:full":"475 Franklin Ave Nutley NJ 07110",
    "addr:housenumber":"475",
    "addr:postcode":"07110",
    "addr:street":"Franklin Ave",
    "iso:country":"US",
    "sg:address":"475 Franklin Ave",
    "sg:city":"Nutley",
    "sg:classifiers":[
        {
            "category":"Retail",
            "subcategory":"Laundry & Dry Cleaning",
            "type":"Services"
        }
    ],
    "sg:phone":"+1 973 667 6973",
    "sg:postcode":"07110",
    "sg:province":"NJ",
    "wof:name":"Rite Cleaners",
    "wof:placetype":"venue"
},
  "geometry": {"coordinates":[-74.156998,40.822498],"type":"Point"}
}