{
  "type": "Feature",
  "properties": {
    "iso:country":"US",
    "sg:address":"59 South Rd",
    "sg:city":"Bloomingdale",
    "sg:classifiers":[
        {
            "category":"Professional",
            "type":"Services"
        }
    ],
    "sg:phone":"+1   ",
    "sg:postcode":"07403",
    "sg:province":"NJ",
    "wof:name":"Scott A Broadfoot",
    "wof:placetype":"venue"
},
  "geometry": {"coordinates":[-74.327094,41.025997],"type":"Point"}
}