{
  "type": "Feature",
  "properties": {
    "addr:full":"325 Main St Metuchen NJ 08840",
    "addr:housenumber":"325",
    "addr:postcode":"08840",
    "addr:street":"Main St",
    "iso:country":"US",
    "sg:address":"325 Main St",
    "sg:city":"Metuchen",
    "sg:classifiers":[
        {
            "category":"Building & Trades",
            "subcategory":"Construction",
            "type":"Services"
        },
        {
            "category":"Education",
            "subcategory":"Special Training",
            "type":"Public Place"
        }
    ],
    "sg:phone":"+1 732 549 8228",
    "sg:postcode":"08840",
    "sg:province":"NJ",
    "sg:tags":[
        "hanging",
        "school",
        "instruction",
        "art",
        "contractor"
    ],
    "wof:name":"Strokes From The Edge Paint",
    "wof:placetype":"venue"
},
  "geometry": {"coordinates":[-74.36041299999999,40.53864],"type":"Point"}
}