{
  "type": "Feature",
  "properties": {
    "iso:country":"US",
    "sg:address":"1719 E 2nd St",
    "sg:city":"Scotch Plains",
    "sg:classifiers":[
        {
            "category":"Wholesale",
            "subcategory":"Machinery & Supplies",
            "type":"Manufacturing & Wholesale Goods"
        },
        {
            "category":"Personal",
            "subcategory":"Beauty Salon",
            "type":"Services"
        }
    ],
    "sg:phone":"+1 908 322 1662",
    "sg:postcode":"07076",
    "sg:province":"NJ",
    "wof:name":"Independent Beauty Supply",
    "wof:placetype":"venue"
},
  "geometry": {"coordinates":[-74.399916,40.645594],"type":"Point"}
}