{
  "type": "Feature",
  "properties": {
    "addr:full":"5 Clydesdale Rd Scotch Plains NJ 07076",
    "addr:housenumber":"5",
    "addr:postcode":"07076",
    "addr:street":"Clydesdale Rd",
    "iso:country":"US",
    "sg:address":"5 Clydesdale Rd",
    "sg:city":"Scotch Plains",
    "sg:classifiers":[
        {
            "category":"Shopping",
            "subcategory":"Clothing, Apparel, & Fashions",
            "type":"Retail Goods"
        }
    ],
    "sg:phone":"+1   ",
    "sg:postcode":"07076",
    "sg:province":"NJ",
    "sg:tags":[
        "lingerie"
    ],
    "wof:name":"Lingerie and Lace",
    "wof:placetype":"venue"
},
  "geometry": {"coordinates":[-74.38120499999999,40.621318],"type":"Point"}
}