{
  "type": "Feature",
  "properties": {
    "addr:full":"103 Monmouth Rd Oakhurst NJ 07755",
    "addr:housenumber":"103",
    "addr:postcode":"07755",
    "addr:street":"Monmouth Rd",
    "iso:country":"US",
    "sg:address":"103 Monmouth Rd",
    "sg:city":"Oakhurst",
    "sg:classifiers":[
        {
            "category":"Organizations",
            "subcategory":"Religious Organization",
            "type":"Services"
        }
    ],
    "sg:phone":"+1   ",
    "sg:postcode":"07755",
    "sg:province":"NJ",
    "wof:name":"First United Methodist Church",
    "wof:placetype":"venue"
},
  "geometry": {"coordinates":[-74.014871,40.267888],"type":"Point"}
}