{
  "type": "Feature",
  "properties": {
    "iso:country":"US",
    "sg:address":"270 Upper Mountain Ave",
    "sg:city":"Montclair",
    "sg:classifiers":[
        {
            "category":"Professional",
            "subcategory":"Lawyer & Legal Services",
            "type":"Services"
        }
    ],
    "sg:phone":"+1 973 655 0505",
    "sg:postcode":"07043",
    "sg:province":"NJ",
    "sg:tags":[
        "attorney",
        "bureau"
    ],
    "wof:name":"Legal Ease",
    "wof:placetype":"venue"
},
  "geometry": {"coordinates":[-74.213157,40.838828],"type":"Point"}
}