{
  "type": "Feature",
  "properties": {
    "addr:full":"34 Chelsea Rd Jackson NJ 08527",
    "addr:housenumber":"34",
    "addr:postcode":"08527",
    "addr:street":"Chelsea Rd",
    "iso:country":"US",
    "sg:address":"34 Chelsea Rd",
    "sg:city":"Jackson",
    "sg:classifiers":[
        {
            "category":"Building & Trades",
            "subcategory":"Construction",
            "type":"Services"
        }
    ],
    "sg:phone":"+1 732 905 1341",
    "sg:postcode":"08527",
    "sg:province":"NJ",
    "sg:tags":[
        "general",
        "contractor"
    ],
    "wof:name":"Chelsea General Contractors",
    "wof:placetype":"venue"
},
  "geometry": {"coordinates":[-74.27358,40.115134],"type":"Point"}
}