{
  "type": "Feature",
  "properties": {
    "addr:full":"31 Norwood Ave Long Branch NJ 07740",
    "addr:housenumber":"31",
    "addr:postcode":"07740",
    "addr:street":"Norwood Ave",
    "iso:country":"US",
    "sg:address":"31 Norwood Ave",
    "sg:city":"Long Branch",
    "sg:classifiers":[
        {
            "category":"Building & Trades",
            "subcategory":"Construction",
            "type":"Services"
        }
    ],
    "sg:phone":"+1 732 222 8249",
    "sg:postcode":"07740",
    "sg:province":"NJ",
    "sg:tags":[
        "resurfacing",
        "laying",
        "refinishing",
        "floor"
    ],
    "wof:name":"Phoenix Wood Flooring Inc",
    "wof:placetype":"venue"
},
  "geometry": {"coordinates":[-74.00254099999999,40.298015],"type":"Point"}
}