{
  "type": "Feature",
  "properties": {
    "iso:country":"US",
    "sg:address":"30 Deer Hill Rd",
    "sg:city":"Lebanon",
    "sg:classifiers":[
        {
            "category":"Retail",
            "subcategory":"Repair Shop",
            "type":"Services"
        }
    ],
    "sg:phone":"+1 908 236 6386",
    "sg:postcode":"08833",
    "sg:province":"NJ",
    "sg:tags":[
        "reupholstery",
        "furniture"
    ],
    "wof:name":"Ben's Auto Upholstery",
    "wof:placetype":"venue"
},
  "geometry": {"coordinates":[-74.801697,40.652901],"type":"Point"}
}