{
  "type": "Feature",
  "properties": {
    "iso:country":"US",
    "sg:address":"16 E Main St",
    "sg:city":"Moorestown",
    "sg:classifiers":[
        {
            "category":"Social Services",
            "type":"Services"
        }
    ],
    "sg:phone":"+1 856 234 2200",
    "sg:postcode":"08057",
    "sg:province":"NJ",
    "wof:name":"Helping Other People Evolve",
    "wof:placetype":"venue"
},
  "geometry": {"coordinates":[-74.943359,39.965136],"type":"Point"}
}