{
  "type": "Feature",
  "properties": {
    "iso:country":"US",
    "sg:address":"600 Pompton Ave",
    "sg:city":"Cedar Grove",
    "sg:classifiers":[
        {
            "category":"Retail",
            "subcategory":"Auto Repair",
            "type":"Services"
        }
    ],
    "sg:phone":"+1 973 571 1000",
    "sg:postcode":"07009",
    "sg:province":"NJ",
    "sg:tags":[
        "automobile",
        "lubrication"
    ],
    "wof:name":"E Z Express Lube",
    "wof:placetype":"venue"
},
  "geometry": {"coordinates":[-74.229854,40.852946],"type":"Point"}
}