{
  "type": "Feature",
  "properties": {
    "addr:full":"610 US Hwy 206 Bordentown NJ 08505",
    "addr:housenumber":"610",
    "addr:postcode":"08505",
    "addr:street":"Us Hwy 206",
    "iso:country":"US",
    "sg:address":"610 US Hwy 206",
    "sg:city":"Bordentown",
    "sg:classifiers":[
        {
            "category":"Personal",
            "subcategory":"Beauty Salon",
            "type":"Services"
        }
    ],
    "sg:phone":"+1 609 392 4545",
    "sg:postcode":"08505",
    "sg:province":"NJ",
    "sg:tags":[
        "school"
    ],
    "sg:website":"www.empirebeauty.com",
    "wof:name":"Empire Beauty School",
    "wof:placetype":"venue"
},
  "geometry": {"coordinates":[-74.70244700000001,40.176224],"type":"Point"}
}