{
  "type": "Feature",
  "properties": {
    "iso:country":"US",
    "sg:address":"85 Old Delsea Dr",
    "sg:city":"Malaga",
    "sg:classifiers":[
        {
            "category":"Organizations",
            "subcategory":"Religious Organization",
            "type":"Services"
        }
    ],
    "sg:phone":"+1 856 694 3060",
    "sg:postcode":"08328",
    "sg:province":"NJ",
    "sg:tags":[
        "church"
    ],
    "wof:name":"Malaga United Methodist Church",
    "wof:placetype":"venue"
},
  "geometry": {"coordinates":[-75.05556799999999,39.570746],"type":"Point"}
}