{
  "type": "Feature",
  "properties": {
    "iso:country":"US",
    "sg:address":"67 Tricentennial Dr",
    "sg:city":"Freehold",
    "sg:classifiers":[
        {
            "category":"Professional",
            "subcategory":"Management & Consulting",
            "type":"Services"
        }
    ],
    "sg:phone":"+1   ",
    "sg:postcode":"07728",
    "sg:province":"NJ",
    "sg:tags":[
        "business"
    ],
    "wof:name":"Co Net Solutions Inc",
    "wof:placetype":"venue"
},
  "geometry": {"coordinates":[-74.28335199999999,40.24142],"type":"Point"}
}