{
  "type": "Feature",
  "properties": {
    "addr:full":"2116 State Rte 88 Brick NJ 08724",
    "addr:housenumber":"2116",
    "addr:postcode":"08724",
    "addr:street":"State Rte 88",
    "iso:country":"US",
    "sg:address":"2116 State Rte 88",
    "sg:city":"Brick",
    "sg:classifiers":[
        {
            "category":"Travel",
            "subcategory":"Hotels & Motels",
            "type":"Entertainment"
        }
    ],
    "sg:phone":"+1 732 892 3900",
    "sg:postcode":"08724",
    "sg:province":"NJ",
    "wof:name":"Gaslite Motel",
    "wof:placetype":"venue"
},
  "geometry": {"coordinates":[-74.101951,40.076409],"type":"Point"}
}