{
  "type": "Feature",
  "properties": {
    "iso:country":"US",
    "sg:address":"114 Amity St",
    "sg:city":"Jersey City",
    "sg:classifiers":[
        {
            "category":"Local Transit",
            "type":"Transportation"
        }
    ],
    "sg:phone":"+1 201 209 0033",
    "sg:postcode":"07304",
    "sg:province":"NJ",
    "sg:tags":[
        "public"
    ],
    "wof:name":"Amity Bus Company",
    "wof:placetype":"venue"
},
  "geometry": {"coordinates":[-74.063698,40.719101],"type":"Point"}
}