{
  "type": "Feature",
  "properties": {
    "iso:country":"US",
    "sg:address":"20 Chichester Rd",
    "sg:city":"Monroe Township",
    "sg:classifiers":[
        {
            "category":"Professional",
            "subcategory":"Accounting & Tax Preparation",
            "type":"Services"
        }
    ],
    "sg:phone":"+1 609 409 1212",
    "sg:postcode":"08831",
    "sg:province":"NJ",
    "wof:name":"Paskowitz H & Company CPA PC",
    "wof:placetype":"venue"
},
  "geometry": {"coordinates":[-74.44857,40.322859],"type":"Point"}
}