{
  "type": "Feature",
  "properties": {
    "addr:full":"100 E Camden Ave Moorestown NJ 08057",
    "addr:housenumber":"100",
    "addr:postcode":"08057",
    "addr:street":"E Camden Ave",
    "iso:country":"US",
    "sg:address":"100 E Camden Ave",
    "sg:city":"Moorestown",
    "sg:classifiers":[
        {
            "category":"Retail",
            "subcategory":"Auto Repair",
            "type":"Services"
        }
    ],
    "sg:phone":"+1 856 273 6606",
    "sg:postcode":"08057",
    "sg:province":"NJ",
    "sg:tags":[
        "repairing",
        "automobile"
    ],
    "wof:name":"Pascal's Automotive Svc",
    "wof:placetype":"venue"
},
  "geometry": {"coordinates":[-74.97530999999999,39.95814],"type":"Point"}
}