{
  "type": "Feature",
  "properties": {
    "addr:full":"10 Cedar St Keyport NJ 07735",
    "addr:housenumber":"10",
    "addr:postcode":"07735",
    "addr:street":"Cedar St",
    "iso:country":"US",
    "sg:address":"10 Cedar St",
    "sg:city":"Keyport",
    "sg:classifiers":[
        {
            "category":"Building & Trades",
            "subcategory":"Plumbing",
            "type":"Services"
        }
    ],
    "sg:phone":"+1 732 815 9191",
    "sg:postcode":"07735",
    "sg:province":"NJ",
    "sg:tags":[
        "conditioning",
        "air",
        "system",
        "contractor"
    ],
    "wof:name":"Abk Cooling & Heating Systems",
    "wof:placetype":"venue"
},
  "geometry": {"coordinates":[-74.193354,40.439422],"type":"Point"}
}