{
  "type": "Feature",
  "properties": {
    "iso:country":"US",
    "sg:address":"747 Vasser Ave",
    "sg:city":"Lakewood",
    "sg:classifiers":[
        {
            "category":"Professional",
            "type":"Services"
        },
        {
            "category":"Manufacturing",
            "subcategory":"Printing",
            "type":"Manufacturing & Wholesale Goods"
        }
    ],
    "sg:phone":"+1 732 229 0008",
    "sg:postcode":"08701",
    "sg:province":"NJ",
    "sg:tags":[
        "publisher",
        "author"
    ],
    "sg:website":"www.chefharvey.com",
    "wof:name":"International Culinary Cons",
    "wof:placetype":"venue"
},
  "geometry": {"coordinates":[-74.18226900000001,40.067244],"type":"Point"}
}