{
  "type": "Feature",
  "properties": {
    "iso:country":"US",
    "sg:address":"221 Evans Way",
    "sg:city":"Branchburg",
    "sg:classifiers":[
        {
            "category":"Professional",
            "subcategory":"Business Services",
            "type":"Services"
        }
    ],
    "sg:phone":"+1 908 575 7771",
    "sg:postcode":"08876",
    "sg:province":"NJ",
    "sg:tags":[
        "paper"
    ],
    "wof:name":"Mobileshred",
    "wof:placetype":"venue"
},
  "geometry": {"coordinates":[-74.705738,40.564659],"type":"Point"}
}