{
  "type": "Feature",
  "properties": {
    "iso:country":"US",
    "sg:address":"1215 Main St",
    "sg:city":"Asbury Park",
    "sg:classifiers":[
        {
            "category":"Professional",
            "subcategory":"Lawyer & Legal Services",
            "type":"Services"
        }
    ],
    "sg:phone":"+1 732 502 0337",
    "sg:postcode":"07712",
    "sg:province":"NJ",
    "sg:tags":[
        "attorney"
    ],
    "wof:name":"Millstone Financial Firm",
    "wof:placetype":"venue"
},
  "geometry": {"coordinates":[-74.010015,40.22552],"type":"Point"}
}