{
  "type": "Feature",
  "properties": {
    "addr:full":"4 Gatehall Dr Parsippany NJ 07054",
    "addr:housenumber":"4",
    "addr:postcode":"07054",
    "addr:street":"Gatehall Dr",
    "iso:country":"US",
    "sg:address":"4 Gatehall Dr",
    "sg:city":"Parsippany",
    "sg:classifiers":[
        {
            "category":"Professional",
            "subcategory":"Advertising",
            "type":"Services"
        }
    ],
    "sg:phone":"+1 973 292 8400",
    "sg:postcode":"07054",
    "sg:province":"NJ",
    "sg:tags":[
        "counselor",
        "agency"
    ],
    "sg:website":"www.natrelusa.com",
    "wof:name":"Natrel Communications Inc",
    "wof:placetype":"venue"
},
  "geometry": {"coordinates":[-74.46105300000001,40.846762],"type":"Point"}
}