{
  "type": "Feature",
  "properties": {
    "iso:country":"US",
    "sg:address":"31 Vandeventer Ave",
    "sg:city":"Princeton",
    "sg:classifiers":[
        {
            "category":"Professional",
            "subcategory":"Management & Consulting",
            "type":"Services"
        }
    ],
    "sg:phone":"+1   ",
    "sg:postcode":"08542",
    "sg:province":"NJ",
    "wof:name":"Katharine Salter Pinneo",
    "wof:placetype":"venue"
},
  "geometry": {"coordinates":[-74.658235,40.35262],"type":"Point"}
}