{
  "type": "Feature",
  "properties": {
    "addr:full":"91 New Bridge Rd Bergenfield NJ 07621",
    "addr:housenumber":"91",
    "addr:postcode":"07621",
    "addr:street":"New Bridge Rd",
    "iso:country":"US",
    "sg:address":"91 New Bridge Rd",
    "sg:city":"Bergenfield",
    "sg:classifiers":[
        {
            "category":"Shopping",
            "subcategory":"Pharmacy",
            "type":"Retail Goods"
        }
    ],
    "sg:phone":"+1 201 385 2550",
    "sg:postcode":"07621",
    "sg:province":"NJ",
    "wof:name":"Rite Aid Pharmacy",
    "wof:placetype":"venue"
},
  "geometry": {"coordinates":[-74.001507,40.914143],"type":"Point"}
}