{
  "type": "Feature",
  "properties": {
    "iso:country":"US",
    "sg:address":"427 Fayette St",
    "sg:city":"Perth Amboy",
    "sg:classifiers":[
        {
            "category":"Bars & Pubs",
            "type":"Food & Drink"
        }
    ],
    "sg:phone":"+1   ",
    "sg:postcode":"08861",
    "sg:province":"NJ",
    "sg:tags":[
        "drinking"
    ],
    "wof:name":"Galicia Tavern Inc",
    "wof:placetype":"venue"
},
  "geometry": {"coordinates":[-74.280925,40.514076],"type":"Point"}
}