{
  "type": "Feature",
  "properties": {
    "addr:full":"396 Bank St Bridgeton NJ 08302",
    "addr:housenumber":"396",
    "addr:postcode":"08302",
    "addr:street":"Bank St",
    "iso:country":"US",
    "sg:address":"396 Bank St",
    "sg:city":"Bridgeton",
    "sg:classifiers":[
        {
            "category":"Building & Trades",
            "subcategory":"Electrical",
            "type":"Services"
        }
    ],
    "sg:phone":"+1 856 455 1792",
    "sg:postcode":"08302",
    "sg:province":"NJ",
    "sg:tags":[
        "electrical",
        "contractor"
    ],
    "wof:name":"Granato Electric Service",
    "wof:placetype":"venue"
},
  "geometry": {"coordinates":[-75.224191,39.439779],"type":"Point"}
}