{
  "type": "Feature",
  "properties": {
    "iso:country":"US",
    "sg:address":"12 Ridge St",
    "sg:city":"Basking Ridge",
    "sg:classifiers":[
        {
            "category":"Health Services",
            "subcategory":"Doctor",
            "type":"Services"
        }
    ],
    "sg:phone":"+1 908 766 7777",
    "sg:postcode":"07920",
    "sg:province":"NJ",
    "sg:tags":[
        "dentist"
    ],
    "wof:name":"Morristown Oral & Maxiollfacl",
    "wof:placetype":"venue"
},
  "geometry": {"coordinates":[-74.553513,40.710732],"type":"Point"}
}