{
  "type": "Feature",
  "properties": {
    "iso:country":"US",
    "sg:address":"12 Tindall Rd",
    "sg:city":"Middletown",
    "sg:classifiers":[
        {
            "category":"Manufacturing",
            "subcategory":"Tools & Machinery",
            "type":"Manufacturing & Wholesale Goods"
        }
    ],
    "sg:phone":"+1 732 796 0777",
    "sg:postcode":"07748",
    "sg:province":"NJ",
    "sg:tags":[
        "surgical",
        "mfg"
    ],
    "wof:name":"Orthopedic & Prosthetic Center",
    "wof:placetype":"venue"
},
  "geometry": {"coordinates":[-74.10130100000001,40.396559],"type":"Point"}
}