{
  "type": "Feature",
  "properties": {
    "addr:full":"495 Cedar Ln Teaneck NJ 07666",
    "addr:housenumber":"495",
    "addr:postcode":"07666",
    "addr:street":"Cedar Ln",
    "iso:country":"US",
    "sg:address":"495 Cedar Ln",
    "sg:city":"Teaneck",
    "sg:classifiers":[
        {
            "category":"Shopping",
            "subcategory":"Gifts & Souvenirs",
            "type":"Retail Goods"
        }
    ],
    "sg:phone":"+1   ",
    "sg:postcode":"07666",
    "sg:province":"NJ",
    "wof:name":"Mazel Tov Gift & Religious",
    "wof:placetype":"venue"
},
  "geometry": {"coordinates":[-74.02386199999999,40.889729],"type":"Point"}
}