{
  "type": "Feature",
  "properties": {
    "addr:full":"811 Sergeantsville Rd Stockton NJ 08559",
    "addr:housenumber":"811",
    "addr:postcode":"08559",
    "addr:street":"Sergeantsville Rd",
    "iso:country":"US",
    "sg:address":"811 Sergeantsville Rd",
    "sg:city":"Stockton",
    "sg:classifiers":[
        {
            "category":"Retail",
            "subcategory":"Animal Services",
            "type":"Services"
        }
    ],
    "sg:phone":"+1 609 397 2434",
    "sg:postcode":"08559",
    "sg:province":"NJ",
    "wof:name":"Stockton Show Stables",
    "wof:placetype":"venue"
},
  "geometry": {"coordinates":[-74.95439500000001,40.433377],"type":"Point"}
}