{
  "type": "Feature",
  "properties": {
    "addr:full":"50 Spring Mills Rd Milford NJ 08848",
    "addr:housenumber":"50",
    "addr:postcode":"08848",
    "addr:street":"Spring Mills Rd",
    "iso:country":"US",
    "sg:address":"50 Spring Mills Rd",
    "sg:city":"Milford",
    "sg:classifiers":[
        {
            "category":"Professional",
            "type":"Services"
        }
    ],
    "sg:phone":"+1 908 995 4149",
    "sg:postcode":"08848",
    "sg:province":"NJ",
    "sg:tags":[
        "establishment"
    ],
    "wof:name":"Senior Advertures",
    "wof:placetype":"venue"
},
  "geometry": {"coordinates":[-75.11071699999999,40.595381],"type":"Point"}
}