{
  "type": "Feature",
  "properties": {
    "iso:country":"US",
    "sg:address":"10 Waterman Ave",
    "sg:city":"Rumson",
    "sg:classifiers":[
        {
            "category":"Arts & Performance",
            "subcategory":"Theater",
            "type":"Entertainment"
        }
    ],
    "sg:phone":"+1 732 842 5633",
    "sg:postcode":"07760",
    "sg:province":"NJ",
    "sg:tags":[
        "theatrical"
    ],
    "wof:name":"Falcon Entertain Group",
    "wof:placetype":"venue"
},
  "geometry": {"coordinates":[-73.977997,40.364688],"type":"Point"}
}