{
  "type": "Feature",
  "properties": {
    "iso:country":"US",
    "sg:address":"381 Main Rd",
    "sg:city":"Montville",
    "sg:classifiers":[
        {
            "category":"Professional",
            "subcategory":"Advertising",
            "type":"Services"
        }
    ],
    "sg:phone":"+1 973 257 0110",
    "sg:postcode":"07045",
    "sg:province":"NJ",
    "sg:website":"www.house.com",
    "wof:name":"HOUSE.COM",
    "wof:placetype":"venue"
},
  "geometry": {"coordinates":[-74.365078,40.915665],"type":"Point"}
}