{
  "type": "Feature",
  "properties": {
    "addr:full":"2503 Nottingham Way Trenton NJ 08619",
    "addr:housenumber":"2503",
    "addr:postcode":"08619",
    "addr:street":"Nottingham Way",
    "iso:country":"US",
    "sg:address":"2503 Nottingham Way",
    "sg:city":"Trenton",
    "sg:classifiers":[
        {
            "category":"Shopping",
            "subcategory":"Gifts & Souvenirs",
            "type":"Retail Goods"
        }
    ],
    "sg:phone":"+1   ",
    "sg:postcode":"08619",
    "sg:province":"NJ",
    "wof:name":"Carellas Hallmark 33",
    "wof:placetype":"venue"
},
  "geometry": {"coordinates":[-74.695967,40.234144],"type":"Point"}
}