{
  "type": "Feature",
  "properties": {
    "iso:country":"US",
    "sg:address":"401 58th St",
    "sg:city":"West New York",
    "sg:classifiers":[
        {
            "category":"Deli",
            "type":"Food & Drink"
        },
        {
            "category":"Food & Beverages",
            "subcategory":"Bakery",
            "type":"Retail Goods"
        }
    ],
    "sg:phone":"+1 201 861 5860",
    "sg:postcode":"07093",
    "sg:province":"NJ",
    "sg:tags":[
        "sandwich"
    ],
    "wof:name":"Naty Deli & Grocery",
    "wof:placetype":"venue"
},
  "geometry": {"coordinates":[-74.01520600000001,40.786445],"type":"Point"}
}