{
  "type": "Feature",
  "properties": {
    "addr:full":"612 Asbury Ave Ocean City NJ 08226",
    "addr:housenumber":"612",
    "addr:postcode":"08226",
    "addr:street":"Asbury Ave",
    "iso:country":"US",
    "sg:address":"612 Asbury Ave",
    "sg:city":"Ocean City",
    "sg:classifiers":[
        {
            "category":"Personal",
            "subcategory":"Tanning Parlor",
            "type":"Services"
        }
    ],
    "sg:phone":"+1 609 399 1670",
    "sg:postcode":"08226",
    "sg:province":"NJ",
    "sg:tags":[
        "salon"
    ],
    "wof:name":"Bodyworks Fitness Club",
    "wof:placetype":"venue"
},
  "geometry": {"coordinates":[-74.573391,39.281232],"type":"Point"}
}