{
  "type": "Feature",
  "properties": {
    "addr:full":"343 Haines Ave Barrington NJ 08007",
    "addr:housenumber":"343",
    "addr:postcode":"08007",
    "addr:street":"Haines Ave",
    "iso:country":"US",
    "sg:address":"343 Haines Ave",
    "sg:city":"Barrington",
    "sg:classifiers":[
        {
            "category":"Personal",
            "type":"Services"
        }
    ],
    "sg:phone":"+1   ",
    "sg:postcode":"08007",
    "sg:province":"NJ",
    "wof:name":"Dream Birthday",
    "wof:placetype":"venue"
},
  "geometry": {"coordinates":[-75.05520799999999,39.8706],"type":"Point"}
}