{
  "type": "Feature",
  "properties": {
    "addr:full":"245 E 17th St Paterson NJ 07524",
    "addr:housenumber":"245",
    "addr:postcode":"07524",
    "addr:street":"E 17Th St",
    "iso:country":"US",
    "sg:address":"245 E 17th St",
    "sg:city":"Paterson",
    "sg:classifiers":[
        {
            "category":"Wholesale",
            "subcategory":"Auto Parts",
            "type":"Manufacturing & Wholesale Goods"
        }
    ],
    "sg:phone":"+1 973 279 7711",
    "sg:postcode":"07524",
    "sg:province":"NJ",
    "sg:tags":[
        "warehouse"
    ],
    "wof:name":"S & S Intl Pdts & Manufactu",
    "wof:placetype":"venue"
},
  "geometry": {"coordinates":[-74.153201,40.929651],"type":"Point"}
}