{
  "type": "Feature",
  "properties": {
    "iso:country":"US",
    "sg:address":"1265 Paterson Plank Rd",
    "sg:city":"Secaucus",
    "sg:classifiers":[
        {
            "category":"Banks & Credit Unions",
            "subcategory":"Bank",
            "type":"Services"
        }
    ],
    "sg:phone":"+1   ",
    "sg:postcode":"07094",
    "sg:province":"NJ",
    "sg:tags":[
        "short",
        "institution",
        "business"
    ],
    "wof:name":"Legal Capital LLC",
    "wof:placetype":"venue"
},
  "geometry": {"coordinates":[-74.057782,40.790054],"type":"Point"}
}