{
  "type": "Feature",
  "properties": {
    "addr:full":"2152 Lemoine Ave Fort Lee NJ 07024",
    "addr:housenumber":"2152",
    "addr:postcode":"07024",
    "addr:street":"Lemoine Ave",
    "iso:country":"US",
    "sg:address":"2152 Lemoine Ave",
    "sg:city":"Fort Lee",
    "sg:classifiers":[
        {
            "category":"Fast Food",
            "type":"Food & Drink"
        }
    ],
    "sg:phone":"+1 201 944 4880",
    "sg:postcode":"07024",
    "sg:province":"NJ",
    "sg:website":"www.mcdonalds.com",
    "wof:name":"McDonald's",
    "wof:placetype":"venue"
},
  "geometry": {"coordinates":[-73.966877,40.855183],"type":"Point"}
}