{
  "type": "Feature",
  "properties": {
    "addr:full":"554 Morris St Orange NJ 07050",
    "addr:housenumber":"554",
    "addr:postcode":"07050",
    "addr:street":"Morris St",
    "iso:country":"US",
    "sg:address":"554 Morris St",
    "sg:city":"Orange",
    "sg:classifiers":[
        {
            "category":"Professional",
            "subcategory":"Employment Agencies",
            "type":"Services"
        }
    ],
    "sg:phone":"+1   ",
    "sg:postcode":"07050",
    "sg:province":"NJ",
    "sg:tags":[
        "firm",
        "search",
        "executive"
    ],
    "wof:name":"Falcon Wings LLC",
    "wof:placetype":"venue"
},
  "geometry": {"coordinates":[-74.25030099999999,40.759192],"type":"Point"}
}