{
  "type": "Feature",
  "properties": {
    "addr:full":"301 Church St Matawan NJ 07747",
    "addr:housenumber":"301",
    "addr:postcode":"07747",
    "addr:street":"Church St",
    "iso:country":"US",
    "sg:address":"301 Church St",
    "sg:city":"Matawan",
    "sg:classifiers":[
        {
            "category":"Health Services",
            "subcategory":"Doctor",
            "type":"Services"
        }
    ],
    "sg:phone":"+1 732 583 1616",
    "sg:postcode":"07747",
    "sg:province":"NJ",
    "sg:tags":[
        "dentist"
    ],
    "wof:name":"Adler Family Dental LLC",
    "wof:placetype":"venue"
},
  "geometry": {"coordinates":[-74.209053,40.405024],"type":"Point"}
}