{
  "type": "Feature",
  "properties": {
    "addr:full":"669 Southwick Rd Somerdale NJ 08083",
    "addr:housenumber":"669",
    "addr:postcode":"08083",
    "addr:street":"Southwick Rd",
    "iso:country":"US",
    "sg:address":"669 Southwick Rd",
    "sg:city":"Somerdale",
    "sg:classifiers":[
        {
            "category":"Insurance",
            "subcategory":"Insurance Agent",
            "type":"Services"
        }
    ],
    "sg:phone":"+1 856 784 8935",
    "sg:postcode":"08083",
    "sg:province":"NJ",
    "wof:name":"Frank Bruzzese Agency",
    "wof:placetype":"venue"
},
  "geometry": {"coordinates":[-75.046361,39.833307],"type":"Point"}
}