{
  "type": "Feature",
  "properties": {
    "iso:country":"US",
    "sg:address":"26 Hannah Dr",
    "sg:city":"Dayton",
    "sg:classifiers":[
        {
            "category":"Retail",
            "subcategory":"Portrait Studio",
            "type":"Services"
        }
    ],
    "sg:phone":"+1   ",
    "sg:postcode":"08810",
    "sg:province":"NJ",
    "sg:tags":[
        "photo"
    ],
    "wof:name":"Bryan Molter Photography",
    "wof:placetype":"venue"
},
  "geometry": {"coordinates":[-74.524637,40.379988],"type":"Point"}
}