{
  "type": "Feature",
  "properties": {
    "addr:full":"1604 State Rte 35 Oakhurst NJ 07755",
    "addr:housenumber":"1604",
    "addr:postcode":"07755",
    "addr:street":"State Rte 35",
    "iso:country":"US",
    "sg:address":"1604 State Rte 35",
    "sg:city":"Oakhurst",
    "sg:classifiers":[
        {
            "category":"Shopping",
            "subcategory":"Crafts & Fabrics",
            "type":"Retail Goods"
        }
    ],
    "sg:phone":"+1 732 531 1711",
    "sg:postcode":"07755",
    "sg:province":"NJ",
    "sg:tags":[
        "shop"
    ],
    "wof:name":"Fabric For Decorators",
    "wof:placetype":"venue"
},
  "geometry": {"coordinates":[-74.039945,40.254554],"type":"Point"}
}