{
  "type": "Feature",
  "properties": {
    "addr:full":"8 Main St Little Falls NJ 07424",
    "addr:housenumber":"8",
    "addr:postcode":"07424",
    "addr:street":"Main St",
    "iso:country":"US",
    "sg:address":"8 Main St",
    "sg:city":"Little Falls",
    "sg:classifiers":[
        {
            "category":"Autos & Motor Vehicles",
            "subcategory":"Automobile Sales",
            "type":"Retail Goods"
        },
        {
            "category":"Retail",
            "subcategory":"Auto Repair",
            "type":"Services"
        }
    ],
    "sg:phone":"+1 973 256 1065",
    "sg:postcode":"07424",
    "sg:province":"NJ",
    "sg:tags":[
        "car"
    ],
    "sg:website":"www.chevrolet.com",
    "wof:name":"Chevrolet Authorized Sales & Service",
    "wof:placetype":"venue"
},
  "geometry": {"coordinates":[-74.224998,40.881302],"type":"Point"}
}