{
  "type": "Feature",
  "properties": {
    "addr:full":"349 US Hwy 22 Dunellen NJ 08812",
    "addr:housenumber":"349",
    "addr:postcode":"08812",
    "addr:street":"Us Hwy 22",
    "iso:country":"US",
    "sg:address":"349 US Hwy 22",
    "sg:city":"Dunellen",
    "sg:classifiers":[
        {
            "category":"Home & Garden",
            "subcategory":"Furniture",
            "type":"Retail Goods"
        }
    ],
    "sg:phone":"+1 732 356 7555",
    "sg:postcode":"08812",
    "sg:province":"NJ",
    "sg:tags":[
        "mattress"
    ],
    "wof:name":"Rockaway Bedding Inc",
    "wof:placetype":"venue"
},
  "geometry": {"coordinates":[-74.50973,40.585752],"type":"Point"}
}