{
  "type": "Feature",
  "properties": {
    "addr:full":"1128 State Rte 31 Lebanon NJ 08833",
    "addr:housenumber":"1128",
    "addr:postcode":"08833",
    "addr:street":"State Rte 31",
    "iso:country":"US",
    "sg:address":"1128 State Rte 31",
    "sg:city":"Lebanon",
    "sg:classifiers":[
        {
            "category":"Professional",
            "subcategory":"Engineering",
            "type":"Services"
        }
    ],
    "sg:phone":"+1 908 735 9500",
    "sg:postcode":"08833",
    "sg:province":"NJ",
    "sg:tags":[
        "engineer"
    ],
    "wof:name":"Van Cleef Engineering Assoc",
    "wof:placetype":"venue"
},
  "geometry": {"coordinates":[-74.87172700000001,40.594789],"type":"Point"}
}