{
  "type": "Feature",
  "properties": {
    "addr:full":"23 Country Squire Rd Westwood NJ 07675",
    "addr:housenumber":"23",
    "addr:postcode":"07675",
    "addr:street":"Country Squire Rd",
    "iso:country":"US",
    "sg:address":"23 Country Squire Rd",
    "sg:city":"Westwood",
    "sg:classifiers":[
        {
            "category":"Professional",
            "subcategory":"Computer Services",
            "type":"Services"
        }
    ],
    "sg:phone":"+1 201 264 3505",
    "sg:postcode":"07675",
    "sg:province":"NJ",
    "sg:tags":[
        "software"
    ],
    "wof:name":"Lightnet Inc",
    "wof:placetype":"venue"
},
  "geometry": {"coordinates":[-73.993712,41.00664],"type":"Point"}
}