{
  "type": "Feature",
  "properties": {
    "addr:full":"2 Wagaraw Rd Hawthorne NJ 07506",
    "addr:housenumber":"2",
    "addr:postcode":"07506",
    "addr:street":"Wagaraw Rd",
    "iso:country":"US",
    "sg:address":"2 Wagaraw Rd",
    "sg:city":"Hawthorne",
    "sg:classifiers":[
        {
            "category":"Autos & Motor Vehicles",
            "subcategory":"Fuel & Gas Station",
            "type":"Retail Goods"
        }
    ],
    "sg:phone":"+1   ",
    "sg:postcode":"07506",
    "sg:province":"NJ",
    "sg:tags":[
        "used",
        "gasoline"
    ],
    "wof:name":"Mobil",
    "wof:placetype":"venue"
},
  "geometry": {"coordinates":[-74.16287199999999,40.93915],"type":"Point"}
}