{
  "type": "Feature",
  "properties": {
    "iso:country":"US",
    "sg:address":"43 Crescent Ave",
    "sg:city":"Passaic",
    "sg:classifiers":[
        {
            "category":"Wholesale",
            "subcategory":"Jewelry",
            "type":"Manufacturing & Wholesale Goods"
        }
    ],
    "sg:phone":"+1 973 778 9683",
    "sg:postcode":"07055",
    "sg:province":"NJ",
    "sg:tags":[
        "gem",
        "man"
    ],
    "wof:name":"Joseph Falkenstein Inc",
    "wof:placetype":"venue"
},
  "geometry": {"coordinates":[-74.13936699999999,40.847579],"type":"Point"}
}