{
  "type": "Feature",
  "properties": {
    "addr:full":"70 Elm Ave Iselin NJ 08830",
    "addr:housenumber":"70",
    "addr:postcode":"08830",
    "addr:street":"Elm Ave",
    "iso:country":"US",
    "sg:address":"70 Elm Ave",
    "sg:city":"Iselin",
    "sg:classifiers":[
        {
            "category":"Professional",
            "subcategory":"Computer Services",
            "type":"Services"
        }
    ],
    "sg:phone":"+1   ",
    "sg:postcode":"08830",
    "sg:province":"NJ",
    "sg:tags":[
        "consulting",
        "datum",
        "business"
    ],
    "wof:name":"Well Rounded Entertainment",
    "wof:placetype":"venue"
},
  "geometry": {"coordinates":[-74.333871,40.57183],"type":"Point"}
}