{
  "type": "Feature",
  "properties": {
    "addr:full":"1013 W Side Ave Jersey City NJ 07306",
    "addr:housenumber":"1013",
    "addr:postcode":"07306",
    "addr:street":"W Side Ave",
    "iso:country":"US",
    "sg:address":"1013 W Side Ave",
    "sg:city":"Jersey City",
    "sg:classifiers":[
        {
            "category":"Restaurant",
            "type":"Food & Drink"
        }
    ],
    "sg:phone":"+1 201 333 5665",
    "sg:postcode":"07306",
    "sg:province":"NJ",
    "sg:tags":[
        "eating",
        "pizza"
    ],
    "wof:name":"Zakaria's Pizza & Grill",
    "wof:placetype":"venue"
},
  "geometry": {"coordinates":[-74.07187500000001,40.734073],"type":"Point"}
}