{
  "type": "Feature",
  "properties": {
    "addr:full":"225 E State St Trenton NJ 08608",
    "addr:housenumber":"225",
    "addr:postcode":"08608",
    "addr:street":"E State St",
    "iso:country":"US",
    "sg:address":"225 E State St",
    "sg:city":"Trenton",
    "sg:classifiers":[
        {
            "category":"Social Services",
            "subcategory":"Child Care",
            "type":"Services"
        }
    ],
    "sg:phone":"+1   ",
    "sg:postcode":"08608",
    "sg:province":"NJ",
    "sg:tags":[
        "preschool"
    ],
    "wof:name":"Little Friends Pre-School",
    "wof:placetype":"venue"
},
  "geometry": {"coordinates":[-74.75975099999999,40.220505],"type":"Point"}
}