{
  "type": "Feature",
  "properties": {
    "addr:full":"30 Technology Drive Warren NJ 07059",
    "addr:housenumber":"30",
    "addr:postcode":"07059",
    "addr:street":"Technology Drive",
    "iso:country":"US",
    "sg:address":"30 Technology Drive",
    "sg:city":"Warren",
    "sg:classifiers":[
        {
            "category":"Professional",
            "subcategory":"Computer Services",
            "type":"Services"
        }
    ],
    "sg:phone":"+1 908 279 8111",
    "sg:postcode":"07059",
    "sg:province":"NJ",
    "sg:website":"http://www.ahsrcm.com/",
    "wof:name":"Advantedge Healthcare Solutions",
    "wof:placetype":"venue"
},
  "geometry": {"coordinates":[-74.505481,40.634116],"type":"Point"}
}