{
  "type": "Feature",
  "properties": {
    "iso:country":"US",
    "sg:address":"84 Albany St",
    "sg:city":"New Brunswick",
    "sg:classifiers":[
        {
            "category":"Banks & Credit Unions",
            "subcategory":"Bank",
            "type":"Services"
        }
    ],
    "sg:phone":"+1   ",
    "sg:postcode":"08901",
    "sg:province":"NJ",
    "sg:tags":[
        "federal"
    ],
    "wof:name":"Financial Rsrces Federal Cr Un",
    "wof:placetype":"venue"
},
  "geometry": {"coordinates":[-74.444022,40.496772],"type":"Point"}
}