{
  "type": "Feature",
  "properties": {
    "addr:full":"1168 State Rte 35 Middletown NJ 07748",
    "addr:housenumber":"1168",
    "addr:postcode":"07748",
    "addr:street":"State Rte 35",
    "iso:country":"US",
    "sg:address":"1168 State Rte 35",
    "sg:city":"Middletown",
    "sg:classifiers":[
        {
            "category":"Utilities",
            "subcategory":"Mobile Phone",
            "type":"Services"
        }
    ],
    "sg:phone":"+1 732 615 9896",
    "sg:postcode":"07748",
    "sg:province":"NJ",
    "sg:tags":[
        "communication",
        "radiotelephone"
    ],
    "wof:name":"Beeper Depot Inc",
    "wof:placetype":"venue"
},
  "geometry": {"coordinates":[-74.111501,40.397635],"type":"Point"}
}