{
  "type": "Feature",
  "properties": {
    "addr:full":"8 Partridge Trl Butler NJ 07405",
    "addr:housenumber":"8",
    "addr:postcode":"07405",
    "addr:street":"Partridge Trl",
    "iso:country":"US",
    "sg:address":"8 Partridge Trl",
    "sg:city":"Butler",
    "sg:classifiers":[
        {
            "category":"Utilities",
            "subcategory":"Telephone",
            "type":"Services"
        }
    ],
    "sg:phone":"+1 973 838 0633",
    "sg:postcode":"07405",
    "sg:province":"NJ",
    "sg:tags":[
        "communications"
    ],
    "wof:name":"Avaya Inc",
    "wof:placetype":"venue"
},
  "geometry": {"coordinates":[-74.372192,40.974866],"type":"Point"}
}