{
  "type": "Feature",
  "properties": {
    "addr:full":"63 Grand Ave Englewood NJ 07631",
    "addr:housenumber":"63",
    "addr:postcode":"07631",
    "addr:street":"Grand Ave",
    "iso:country":"US",
    "sg:address":"63 Grand Ave",
    "sg:city":"Englewood",
    "sg:classifiers":[
        {
            "category":"Retail",
            "subcategory":"Repair Shop",
            "type":"Services"
        }
    ],
    "sg:phone":"+1 201 786 0698",
    "sg:postcode":"07631",
    "sg:province":"NJ",
    "sg:tags":[
        "lock",
        "locksmith"
    ],
    "wof:name":"Emergency A Locksmith",
    "wof:placetype":"venue"
},
  "geometry": {"coordinates":[-73.975385,40.889737],"type":"Point"}
}