{
  "type": "Feature",
  "properties": {
    "addr:full":"801 Tilton Rd Northfield NJ 08225",
    "addr:housenumber":"801",
    "addr:postcode":"08225",
    "addr:street":"Tilton Rd",
    "iso:country":"US",
    "sg:address":"801 Tilton Rd",
    "sg:city":"Northfield",
    "sg:classifiers":[
        {
            "category":"Food & Beverages",
            "subcategory":"Specialty",
            "type":"Retail Goods"
        }
    ],
    "sg:phone":"+1   ",
    "sg:postcode":"08225",
    "sg:province":"NJ",
    "wof:name":"Rock Bottom Supplements",
    "wof:placetype":"venue"
},
  "geometry": {"coordinates":[-74.55486999999999,39.380717],"type":"Point"}
}