{
  "type": "Feature",
  "properties": {
    "iso:country":"US",
    "sg:address":"4 N Mississippi Ave",
    "sg:city":"Atlantic City",
    "sg:classifiers":[
        {
            "category":"Professional",
            "subcategory":"Business Services",
            "type":"Services"
        }
    ],
    "sg:phone":"+1 609 343 0080",
    "sg:postcode":"08401",
    "sg:province":"NJ",
    "sg:tags":[
        "broker",
        "merchandise"
    ],
    "wof:name":"Brokers & Lenders Property Svc",
    "wof:placetype":"venue"
},
  "geometry": {"coordinates":[-74.439819,39.358047],"type":"Point"}
}