{
  "type": "Feature",
  "properties": {
    "iso:country":"US",
    "sg:address":"357 Willis Rd",
    "sg:city":"Bridgeton",
    "sg:classifiers":[
        {
            "category":"Building & Trades",
            "subcategory":"Construction",
            "type":"Services"
        }
    ],
    "sg:phone":"+1 856 575 0202",
    "sg:postcode":"08302",
    "sg:province":"NJ",
    "sg:tags":[
        "general",
        "contractor"
    ],
    "wof:name":"St Aubyn Constr Inc",
    "wof:placetype":"venue"
},
  "geometry": {"coordinates":[-75.363929,39.437776],"type":"Point"}
}