{
  "type": "Feature",
  "properties": {
    "addr:full":"428 Bramhall Ave Jersey City NJ 07304",
    "addr:housenumber":"428",
    "addr:postcode":"07304",
    "addr:street":"Bramhall Ave",
    "iso:country":"US",
    "sg:address":"428 Bramhall Ave",
    "sg:city":"Jersey City",
    "sg:classifiers":[
        {
            "category":"Organizations",
            "subcategory":"Religious Organization",
            "type":"Services"
        }
    ],
    "sg:phone":"+1   ",
    "sg:postcode":"07304",
    "sg:province":"NJ",
    "wof:name":"J Williams Rev",
    "wof:placetype":"venue"
},
  "geometry": {"coordinates":[-74.069197,40.71229],"type":"Point"}
}