{
  "type": "Feature",
  "properties": {
    "addr:full":"900 Park Ave Plainfield NJ 07060",
    "addr:housenumber":"900",
    "addr:postcode":"07060",
    "addr:street":"Park Ave",
    "iso:country":"US",
    "sg:address":"900 Park Ave",
    "sg:city":"Plainfield",
    "sg:classifiers":[
        {
            "category":"Shopping",
            "subcategory":"Clothing, Apparel, & Fashions",
            "type":"Retail Goods"
        }
    ],
    "sg:phone":"+1   ",
    "sg:postcode":"07060",
    "sg:province":"NJ",
    "wof:name":"Silvis Boutique",
    "wof:placetype":"venue"
},
  "geometry": {"coordinates":[-74.411945,40.611832],"type":"Point"}
}