{
  "type": "Feature",
  "properties": {
    "addr:full":"1514 Roosevelt Ave Carteret NJ 07008",
    "addr:housenumber":"1514",
    "addr:postcode":"07008",
    "addr:street":"Roosevelt Ave",
    "iso:country":"US",
    "sg:address":"1514 Roosevelt Ave",
    "sg:city":"Carteret",
    "sg:classifiers":[
        {
            "category":"Building & Trades",
            "subcategory":"Locksmith",
            "type":"Services"
        }
    ],
    "sg:phone":"+1 732 839 2949",
    "sg:postcode":"07008",
    "sg:province":"NJ",
    "sg:tags":[
        "key"
    ],
    "wof:name":"A 24 Hour Always Available Emerg 24 Locksmith",
    "wof:placetype":"venue"
},
  "geometry": {"coordinates":[-74.251676,40.595612],"type":"Point"}
}