{
  "type": "Feature",
  "properties": {
    "iso:country":"US",
    "sg:address":"50 Bowden Rd",
    "sg:city":"Cedar Grove",
    "sg:classifiers":[
        {
            "category":"Professional",
            "subcategory":"Lawyer & Legal Services",
            "type":"Services"
        }
    ],
    "sg:phone":"+1 973 239 0177",
    "sg:postcode":"07009",
    "sg:province":"NJ",
    "sg:tags":[
        "attorney"
    ],
    "wof:name":"William J Maione",
    "wof:placetype":"venue"
},
  "geometry": {"coordinates":[-74.227271,40.85387],"type":"Point"}
}