{
  "type": "Feature",
  "properties": {
    "addr:full":"35 Felmley Rd Whitehouse Sta NJ 08889",
    "addr:housenumber":"35",
    "addr:postcode":"08889",
    "addr:street":"Felmley Rd",
    "iso:country":"US",
    "sg:address":"35 Felmley Rd",
    "sg:city":"Whitehouse Sta",
    "sg:classifiers":[
        {
            "category":"Recreation",
            "type":"Entertainment"
        }
    ],
    "sg:phone":"+1 908 439 3617",
    "sg:postcode":"08889",
    "sg:province":"NJ",
    "sg:tags":[
        "stable"
    ],
    "wof:name":"Black River Farm",
    "wof:placetype":"venue"
},
  "geometry": {"coordinates":[-74.742878,40.655944],"type":"Point"}
}