{
  "type": "Feature",
  "properties": {
    "iso:country":"US",
    "sg:address":"28 Cresci Blvd",
    "sg:city":"Hazlet",
    "sg:classifiers":[
        {
            "category":"Manufacturing",
            "subcategory":"Tools & Machinery",
            "type":"Manufacturing & Wholesale Goods"
        }
    ],
    "sg:phone":"+1 732 739 2080",
    "sg:postcode":"07730",
    "sg:province":"NJ",
    "sg:tags":[
        "industrial",
        "mfg"
    ],
    "wof:name":"H & L Machine & Tool",
    "wof:placetype":"venue"
},
  "geometry": {"coordinates":[-74.20571200000001,40.41137],"type":"Point"}
}