{
  "type": "Feature",
  "properties": {
    "addr:full":"11 Weber Ave Sayreville NJ 08872",
    "addr:housenumber":"11",
    "addr:postcode":"08872",
    "addr:street":"Weber Ave",
    "iso:country":"US",
    "sg:address":"11 Weber Ave",
    "sg:city":"Sayreville",
    "sg:classifiers":[
        {
            "category":"Building & Trades",
            "subcategory":"Construction",
            "type":"Services"
        }
    ],
    "sg:phone":"+1 732 432 4977",
    "sg:postcode":"08872",
    "sg:province":"NJ",
    "sg:tags":[
        "residential"
    ],
    "wof:name":"M Direwneski",
    "wof:placetype":"venue"
},
  "geometry": {"coordinates":[-74.368791,40.456779],"type":"Point"}
}