{
  "type": "Feature",
  "properties": {
    "iso:country":"US",
    "sg:address":"268 Ridgedale Ave",
    "sg:city":"East Hanover",
    "sg:classifiers":[
        {
            "category":"Retail",
            "subcategory":"Funeral Services",
            "type":"Services"
        }
    ],
    "sg:phone":"+1 973 887 0386",
    "sg:postcode":"07936",
    "sg:province":"NJ",
    "sg:tags":[
        "cemetery"
    ],
    "wof:name":"Heavenly Rest Memorial Park",
    "wof:placetype":"venue"
},
  "geometry": {"coordinates":[-74.37449599999999,40.819302],"type":"Point"}
}