{
  "type": "Feature",
  "properties": {
    "iso:country":"US",
    "sg:address":"11 Hillcrest Ter",
    "sg:city":"Verona",
    "sg:classifiers":[
        {
            "category":"Building & Trades",
            "subcategory":"Construction",
            "type":"Services"
        }
    ],
    "sg:phone":"+1 973 857 5460",
    "sg:postcode":"07044",
    "sg:province":"NJ",
    "sg:tags":[
        "house"
    ],
    "wof:name":"Quality A & Home Imprv Ctr",
    "wof:placetype":"venue"
},
  "geometry": {"coordinates":[-74.23559400000001,40.828688],"type":"Point"}
}