{
  "type": "Feature",
  "properties": {
    "addr:full":"693 Bergen Blvd Ridgefield NJ 07657",
    "addr:housenumber":"693",
    "addr:postcode":"07657",
    "addr:street":"Bergen Blvd",
    "iso:country":"US",
    "sg:address":"693 Bergen Blvd",
    "sg:city":"Ridgefield",
    "sg:classifiers":[
        {
            "category":"Real Estate",
            "subcategory":"Real Estate Agent",
            "type":"Services"
        }
    ],
    "sg:phone":"+1 201 313 8949",
    "sg:postcode":"07657",
    "sg:province":"NJ",
    "wof:name":"Kacy Promax Realty Inc",
    "wof:placetype":"venue"
},
  "geometry": {"coordinates":[-73.99250000000001,40.831261],"type":"Point"}
}