{
  "type": "Feature",
  "properties": {
    "addr:full":"6 Park St Bordentown NJ 08505",
    "addr:housenumber":"6",
    "addr:postcode":"08505",
    "addr:street":"Park St",
    "iso:country":"US",
    "sg:address":"6 Park St",
    "sg:city":"Bordentown",
    "sg:classifiers":[
        {
            "category":"Real Estate",
            "subcategory":"Real Estate Services",
            "type":"Services"
        }
    ],
    "sg:phone":"+1 609 291 5500",
    "sg:postcode":"08505",
    "sg:province":"NJ",
    "sg:tags":[
        "company",
        "title"
    ],
    "wof:name":"Surety Title Corp",
    "wof:placetype":"venue"
},
  "geometry": {"coordinates":[-74.712936,40.148951],"type":"Point"}
}