{
  "type": "Feature",
  "properties": {
    "iso:country":"US",
    "sg:address":"163 Chelsea Ave",
    "sg:city":"Long Branch",
    "sg:classifiers":[
        {
            "category":"Building & Trades",
            "subcategory":"Construction",
            "type":"Services"
        }
    ],
    "sg:phone":"+1 732 229 7506",
    "sg:postcode":"07740",
    "sg:province":"NJ",
    "sg:tags":[
        "floor",
        "laying",
        "contractor"
    ],
    "wof:name":"Val Hardwood Flooring",
    "wof:placetype":"venue"
},
  "geometry": {"coordinates":[-73.98633,40.301104],"type":"Point"}
}