{
  "type": "Feature",
  "properties": {
    "addr:full":"48 Rues Rd Creamridge NJ 08514",
    "addr:housenumber":"48",
    "addr:postcode":"08514",
    "addr:street":"Rues Rd",
    "iso:country":"US",
    "sg:address":"48 Rues Rd",
    "sg:city":"Creamridge",
    "sg:classifiers":[
        {
            "category":"Building & Trades",
            "subcategory":"Construction",
            "type":"Services"
        }
    ],
    "sg:phone":"+1 609 529 8955",
    "sg:postcode":"08514",
    "sg:province":"NJ",
    "sg:tags":[
        "housing",
        "family"
    ],
    "wof:name":"Cottrell Construction LLC",
    "wof:placetype":"venue"
},
  "geometry": {"coordinates":[-74.48670199999999,40.177776],"type":"Point"}
}