{
  "type": "Feature",
  "properties": {
    "addr:full":"61 Cleveland St Orange NJ 07050",
    "addr:housenumber":"61",
    "addr:postcode":"07050",
    "addr:street":"Cleveland St",
    "iso:country":"US",
    "sg:address":"61 Cleveland St",
    "sg:city":"Orange",
    "sg:classifiers":[
        {
            "category":"Retail",
            "subcategory":"Repair Shop",
            "type":"Services"
        }
    ],
    "sg:phone":"+1   ",
    "sg:postcode":"07050",
    "sg:province":"NJ",
    "wof:name":"Tenecela Cleaning Inc",
    "wof:placetype":"venue"
},
  "geometry": {"coordinates":[-74.23075,40.774302],"type":"Point"}
}