{
  "type": "Feature",
  "properties": {
    "iso:country":"US",
    "sg:address":"3000 Kozloski Rd",
    "sg:city":"Freehold",
    "sg:classifiers":[
        {
            "category":"Organizations",
            "subcategory":"Labor Organization",
            "type":"Services"
        }
    ],
    "sg:phone":"+1 732 780 1900",
    "sg:postcode":"07728",
    "sg:province":"NJ",
    "wof:name":"Communications Workers-America",
    "wof:placetype":"venue"
},
  "geometry": {"coordinates":[-74.244805,40.267248],"type":"Point"}
}