{
  "type": "Feature",
  "properties": {
    "addr:full":"137 Eaves Mill Rd Medford NJ 08055",
    "addr:housenumber":"137",
    "addr:postcode":"08055",
    "addr:street":"Eaves Mill Rd",
    "iso:country":"US",
    "sg:address":"137 Eaves Mill Rd",
    "sg:city":"Medford",
    "sg:classifiers":[
        {
            "category":"Building & Trades",
            "subcategory":"Landscaping Services",
            "type":"Services"
        }
    ],
    "sg:phone":"+1 856 904 6191",
    "sg:postcode":"08055",
    "sg:province":"NJ",
    "sg:tags":[
        "landscape"
    ],
    "wof:name":"As Good As It Gets Landscaping",
    "wof:placetype":"venue"
},
  "geometry": {"coordinates":[-74.829414,39.907038],"type":"Point"}
}