{
  "type": "Feature",
  "properties": {
    "iso:country":"US",
    "sg:address":"45 Wooley Rd",
    "sg:city":"West Milford",
    "sg:classifiers":[
        {
            "category":"Building & Trades",
            "subcategory":"Construction",
            "type":"Services"
        }
    ],
    "sg:phone":"+1 973 697 3554",
    "sg:postcode":"07480",
    "sg:province":"NJ",
    "sg:tags":[
        "house",
        "nonresidential"
    ],
    "wof:name":"Northern Pine Sheds Inc",
    "wof:placetype":"venue"
},
  "geometry": {"coordinates":[-74.401861,41.087241],"type":"Point"}
}