{
  "type": "Feature",
  "properties": {
    "iso:country":"US",
    "sg:address":"582 Plaza Ter",
    "sg:city":"Brick",
    "sg:classifiers":[
        {
            "category":"Professional",
            "subcategory":"Engineering",
            "type":"Services"
        }
    ],
    "sg:phone":"+1 732 477 3330",
    "sg:postcode":"08723",
    "sg:province":"NJ",
    "sg:tags":[
        "engineer"
    ],
    "wof:name":"LGA Engineering",
    "wof:placetype":"venue"
},
  "geometry": {"coordinates":[-74.14412299999999,40.056147],"type":"Point"}
}