{
  "type": "Feature",
  "properties": {
    "addr:full":"2328 W Main St Millville NJ 08332",
    "addr:housenumber":"2328",
    "addr:postcode":"08332",
    "addr:street":"W Main St",
    "iso:country":"US",
    "sg:address":"2328 W Main St",
    "sg:city":"Millville",
    "sg:classifiers":[
        {
            "category":"Professional",
            "subcategory":"Art Services",
            "type":"Services"
        }
    ],
    "sg:phone":"+1   ",
    "sg:postcode":"08332",
    "sg:province":"NJ",
    "sg:tags":[
        "commercial",
        "design"
    ],
    "wof:name":"Three GS Graphics",
    "wof:placetype":"venue"
},
  "geometry": {"coordinates":[-75.106662,39.406646],"type":"Point"}
}