{
  "type": "Feature",
  "properties": {
    "addr:full":"506 New Dover Rd Colonia NJ 07067",
    "addr:housenumber":"506",
    "addr:postcode":"07067",
    "addr:street":"New Dover Rd",
    "iso:country":"US",
    "sg:address":"506 New Dover Rd",
    "sg:city":"Colonia",
    "sg:classifiers":[
        {
            "category":"Local Transit",
            "type":"Transportation"
        }
    ],
    "sg:phone":"+1 732 855 0058",
    "sg:postcode":"07067",
    "sg:province":"NJ",
    "sg:tags":[
        "passenger"
    ],
    "wof:name":"Ultra Express Coaches",
    "wof:placetype":"venue"
},
  "geometry": {"coordinates":[-74.331715,40.585935],"type":"Point"}
}