{
  "type": "Feature",
  "properties": {
    "addr:full":"170 E 9th Ave Runnemede NJ 08078",
    "addr:housenumber":"170",
    "addr:postcode":"08078",
    "addr:street":"E 9Th Ave",
    "iso:country":"US",
    "sg:address":"170 E 9th Ave",
    "sg:city":"Runnemede",
    "sg:classifiers":[
        {
            "category":"Real Estate",
            "subcategory":"Developer",
            "type":"Services"
        }
    ],
    "sg:phone":"+1 856 939 3298",
    "sg:postcode":"08078",
    "sg:province":"NJ",
    "wof:name":"Richards Robbins Management Co",
    "wof:placetype":"venue"
},
  "geometry": {"coordinates":[-75.07143499999999,39.857685],"type":"Point"}
}