{
  "type": "Feature",
  "properties": {
    "iso:country":"US",
    "sg:address":"703 Warren Glen Rd",
    "sg:city":"Bloomsbury",
    "sg:classifiers":[
        {
            "category":"Professional",
            "subcategory":"Business Services",
            "type":"Services"
        }
    ],
    "sg:phone":"+1   ",
    "sg:postcode":"08804",
    "sg:province":"NJ",
    "wof:name":"Bull Dog Stuff com",
    "wof:placetype":"venue"
},
  "geometry": {"coordinates":[-75.094656,40.654671],"type":"Point"}
}