{
  "type": "Feature",
  "properties": {
    "addr:full":"196 Tuxedo Pkwy Newark NJ 07106",
    "addr:housenumber":"196",
    "addr:postcode":"07106",
    "addr:street":"Tuxedo Pkwy",
    "iso:country":"US",
    "sg:address":"196 Tuxedo Pkwy",
    "sg:city":"Newark",
    "sg:classifiers":[
        {
            "category":"Real Estate",
            "subcategory":"Real Estate Operator",
            "type":"Services"
        }
    ],
    "sg:phone":"+1   ",
    "sg:postcode":"07106",
    "sg:province":"NJ",
    "sg:tags":[
        "building",
        "nonresidential"
    ],
    "wof:name":"82 Jay Street Realty Corp",
    "wof:placetype":"venue"
},
  "geometry": {"coordinates":[-74.244579,40.736377],"type":"Point"}
}