{
  "type": "Feature",
  "properties": {
    "addr:full":"609 Rivervale Rd River Vale NJ 07675",
    "addr:housenumber":"609",
    "addr:postcode":"07675",
    "addr:street":"Rivervale Rd",
    "iso:country":"US",
    "sg:address":"609 Rivervale Rd",
    "sg:city":"River Vale",
    "sg:classifiers":[
        {
            "category":"Building & Trades",
            "subcategory":"Landscaping Services",
            "type":"Services"
        }
    ],
    "sg:phone":"+1 201 391 7411",
    "sg:postcode":"07675",
    "sg:province":"NJ",
    "sg:tags":[
        "designer",
        "landscape"
    ],
    "wof:name":"Community Landscaping",
    "wof:placetype":"venue"
},
  "geometry": {"coordinates":[-74.009787,41.022146],"type":"Point"}
}