{
  "type": "Feature",
  "properties": {
    "iso:country":"US",
    "sg:address":"7 Rockledge Rd",
    "sg:city":"Montville",
    "sg:classifiers":[
        {
            "category":"Professional",
            "subcategory":"Engineering",
            "type":"Services"
        }
    ],
    "sg:phone":"+1   ",
    "sg:postcode":"07045",
    "sg:province":"NJ",
    "wof:name":"Leonard F OReilly Associate",
    "wof:placetype":"venue"
},
  "geometry": {"coordinates":[-74.380135,40.928181],"type":"Point"}
}