{
  "type": "Feature",
  "properties": {
    "addr:full":"18 Paddock Ln Colts Neck NJ 07722",
    "addr:housenumber":"18",
    "addr:postcode":"07722",
    "addr:street":"Paddock Ln",
    "iso:country":"US",
    "sg:address":"18 Paddock Ln",
    "sg:city":"Colts Neck",
    "sg:classifiers":[
        {
            "category":"Farming",
            "subcategory":"Nursery",
            "type":"Manufacturing & Wholesale Goods"
        }
    ],
    "sg:phone":"+1 732 946 4293",
    "sg:postcode":"07722",
    "sg:province":"NJ",
    "sg:tags":[
        "ornamental"
    ],
    "wof:name":"Eileens Greens",
    "wof:placetype":"venue"
},
  "geometry": {"coordinates":[-74.194575,40.328258],"type":"Point"}
}