{
  "type": "Feature",
  "properties": {
    "iso:country":"US",
    "sg:address":"405 Windermere Ave",
    "sg:city":"Asbury Park",
    "sg:classifiers":[
        {
            "category":"Professional",
            "subcategory":"Computer Services",
            "type":"Services"
        }
    ],
    "sg:phone":"+1 732 517 1391",
    "sg:postcode":"07712",
    "sg:province":"NJ",
    "sg:tags":[
        "related"
    ],
    "wof:name":"Edix Information Inc",
    "wof:placetype":"venue"
},
  "geometry": {"coordinates":[-74.017352,40.232994],"type":"Point"}
}