{
  "type": "Feature",
  "properties": {
    "addr:full":"84 Glendale Ave Livingston NJ 07039",
    "addr:housenumber":"84",
    "addr:postcode":"07039",
    "addr:street":"Glendale Ave",
    "iso:country":"US",
    "sg:address":"84 Glendale Ave",
    "sg:city":"Livingston",
    "sg:classifiers":[
        {
            "category":"Arts & Performance",
            "subcategory":"Theater",
            "type":"Entertainment"
        }
    ],
    "sg:phone":"+1   ",
    "sg:postcode":"07039",
    "sg:province":"NJ",
    "sg:tags":[
        "group"
    ],
    "wof:name":"Consu Entertainment Media",
    "wof:placetype":"venue"
},
  "geometry": {"coordinates":[-74.313001,40.801455],"type":"Point"}
}