{
  "type": "Feature",
  "properties": {
    "addr:full":"2 Barnstable Ct Saddle River NJ 07458",
    "addr:housenumber":"2",
    "addr:postcode":"07458",
    "addr:street":"Barnstable Ct",
    "iso:country":"US",
    "sg:address":"2 Barnstable Ct",
    "sg:city":"Saddle River",
    "sg:classifiers":[
        {
            "category":"Retail",
            "subcategory":"Repair Shop",
            "type":"Services"
        }
    ],
    "sg:phone":"+1 201 334 3786",
    "sg:postcode":"07458",
    "sg:province":"NJ",
    "sg:tags":[
        "lock",
        "locksmith"
    ],
    "wof:name":"7 Day Emergency 24 Hour",
    "wof:placetype":"venue"
},
  "geometry": {"coordinates":[-74.102215,41.032134],"type":"Point"}
}