{
  "type": "Feature",
  "properties": {
    "addr:full":"13 Waverly Pl Madison NJ 07940",
    "addr:housenumber":"13",
    "addr:postcode":"07940",
    "addr:street":"Waverly Pl",
    "iso:country":"US",
    "sg:address":"13 Waverly Pl",
    "sg:city":"Madison",
    "sg:classifiers":[
        {
            "category":"Bars & Pubs",
            "type":"Food & Drink"
        },
        {
            "category":"Restaurant",
            "type":"Food & Drink"
        }
    ],
    "sg:phone":"+1 973 966 0211",
    "sg:postcode":"07940",
    "sg:province":"NJ",
    "sg:tags":[
        "lounge",
        "nightlife",
        "cocktail"
    ],
    "wof:name":"Poor Herbie's",
    "wof:placetype":"venue"
},
  "geometry": {"coordinates":[-74.415458,40.758321],"type":"Point"}
}