{
  "type": "Feature",
  "properties": {
    "addr:full":"60 Walnut Ave Clark NJ 07066",
    "addr:housenumber":"60",
    "addr:postcode":"07066",
    "addr:street":"Walnut Ave",
    "iso:country":"US",
    "sg:address":"60 Walnut Ave",
    "sg:city":"Clark",
    "sg:classifiers":[
        {
            "category":"Organizations",
            "subcategory":"Membership Organization",
            "type":"Services"
        }
    ],
    "sg:phone":"+1 732 382 5095",
    "sg:postcode":"07066",
    "sg:province":"NJ",
    "wof:name":"New Jersey Senior Golf Assn",
    "wof:placetype":"venue"
},
  "geometry": {"coordinates":[-74.30159399999999,40.629485],"type":"Point"}
}