{
  "type": "Feature",
  "properties": {
    "addr:full":"2039 John F Kennedy Blvd Jersey City NJ 07305",
    "addr:housenumber":"2039",
    "addr:postcode":"07305",
    "addr:street":"John F Kennedy Blvd",
    "iso:country":"US",
    "sg:address":"2039 John F Kennedy Blvd",
    "sg:city":"Jersey City",
    "sg:classifiers":[
        {
            "category":"Restaurant",
            "type":"Food & Drink"
        }
    ],
    "sg:menulink":"http://www.allmenus.com/nj/jersey-city/55776-subway/menu/",
    "sg:phone":"+1 201 200 2107",
    "sg:postcode":"07305",
    "sg:province":"NJ",
    "sg:tags":[
        "american",
        "sandwich"
    ],
    "wof:name":"Subway",
    "wof:placetype":"venue"
},
  "geometry": {"coordinates":[-74.086297,40.708756],"type":"Point"}
}