{
  "type": "Feature",
  "properties": {
    "addr:full":"13 Summerfield Blvd Dayton NJ 08810",
    "addr:housenumber":"13",
    "addr:postcode":"08810",
    "addr:street":"Summerfield Blvd",
    "iso:country":"US",
    "sg:address":"13 Summerfield Blvd",
    "sg:city":"Dayton",
    "sg:classifiers":[
        {
            "category":"Professional",
            "subcategory":"Business Services",
            "type":"Services"
        }
    ],
    "sg:phone":"+1   ",
    "sg:postcode":"08810",
    "sg:province":"NJ",
    "wof:name":"Ace Design",
    "wof:placetype":"venue"
},
  "geometry": {"coordinates":[-74.510983,40.379188],"type":"Point"}
}