{
  "type": "Feature",
  "properties": {
    "addr:full":"522 Boulevard Kenilworth NJ 07033",
    "addr:housenumber":"522",
    "addr:postcode":"07033",
    "addr:street":"Boulevard",
    "iso:country":"US",
    "sg:address":"522 Boulevard",
    "sg:city":"Kenilworth",
    "sg:classifiers":[
        {
            "category":"Real Estate",
            "subcategory":"Real Estate Operator",
            "type":"Services"
        }
    ],
    "sg:phone":"+1   ",
    "sg:postcode":"07033",
    "sg:province":"NJ",
    "sg:tags":[
        "building",
        "commercial"
    ],
    "wof:name":"Boulevard Barber Shop",
    "wof:placetype":"venue"
},
  "geometry": {"coordinates":[-74.29067499999999,40.676206],"type":"Point"}
}