{
  "type": "Feature",
  "properties": {
    "iso:country":"US",
    "sg:address":"500 Co Rd 530",
    "sg:city":"Lakehurst",
    "sg:classifiers":[
        {
            "category":"Banks & Credit Unions",
            "subcategory":"Bank",
            "type":"Services"
        }
    ],
    "sg:phone":"+1 732 350 6400",
    "sg:postcode":"08759",
    "sg:province":"NJ",
    "sg:tags":[
        "state",
        "commercial"
    ],
    "wof:name":"First Washington State Bank",
    "wof:placetype":"venue"
},
  "geometry": {"coordinates":[-74.352121,39.946811],"type":"Point"}
}