{
  "type": "Feature",
  "properties": {
    "addr:full":"3905 River Rd Pennsauken NJ 08110",
    "addr:housenumber":"3905",
    "addr:postcode":"08110",
    "addr:street":"River Rd",
    "iso:country":"US",
    "sg:address":"3905 River Rd",
    "sg:city":"Pennsauken",
    "sg:classifiers":[
        {
            "category":"Autos & Motor Vehicles",
            "subcategory":"Auto Supplies",
            "type":"Retail Goods"
        }
    ],
    "sg:phone":"+1 856 663 8132",
    "sg:postcode":"08110",
    "sg:province":"NJ",
    "sg:tags":[
        "tire"
    ],
    "wof:name":"IBM Continental Tire",
    "wof:placetype":"venue"
},
  "geometry": {"coordinates":[-75.077581,39.963049],"type":"Point"}
}