{
  "type": "Feature",
  "properties": {
    "addr:full":"612 Wesley Ave Ocean City NJ 08226",
    "addr:housenumber":"612",
    "addr:postcode":"08226",
    "addr:street":"Wesley Ave",
    "iso:country":"US",
    "sg:address":"612 Wesley Ave",
    "sg:city":"Ocean City",
    "sg:classifiers":[
        {
            "category":"Travel",
            "subcategory":"Hotels & Motels",
            "type":"Entertainment"
        }
    ],
    "sg:phone":"+1 609 398 0898",
    "sg:postcode":"08226",
    "sg:province":"NJ",
    "sg:tags":[
        "breakfast",
        "accommodation",
        "bed"
    ],
    "wof:name":"Serenity Inn",
    "wof:placetype":"venue"
},
  "geometry": {"coordinates":[-74.571898,39.280094],"type":"Point"}
}