{
  "type": "Feature",
  "properties": {
    "iso:country":"US",
    "sg:address":"1164 E Jersey St",
    "sg:city":"Elizabeth",
    "sg:classifiers":[
        {
            "category":"Home & Garden",
            "subcategory":"Household Appliances",
            "type":"Retail Goods"
        }
    ],
    "sg:phone":"+1 908 352 5840",
    "sg:postcode":"07201",
    "sg:province":"NJ",
    "sg:tags":[
        "machine",
        "sewing",
        "vacuum"
    ],
    "wof:name":"Singer Sewing Company Dealer",
    "wof:placetype":"venue"
},
  "geometry": {"coordinates":[-74.21390700000001,40.66492],"type":"Point"}
}