{
  "type": "Feature",
  "properties": {
    "iso:country":"US",
    "sg:address":"2590 US Hwy 22",
    "sg:city":"Scotch Plains",
    "sg:classifiers":[
        {
            "category":"Shopping",
            "subcategory":"Computers & Home Electronics",
            "type":"Retail Goods"
        }
    ],
    "sg:phone":"+1 908 232 7770",
    "sg:postcode":"07076",
    "sg:province":"NJ",
    "sg:tags":[
        "publishing"
    ],
    "sg:website":"www.lbtypo.com",
    "wof:name":"L & B Desktop Publishing",
    "wof:placetype":"venue"
},
  "geometry": {"coordinates":[-74.39132600000001,40.662709],"type":"Point"}
}