{
  "type": "Feature",
  "properties": {
    "iso:country":"US",
    "sg:address":"184 Walters St",
    "sg:city":"Rahway",
    "sg:classifiers":[
        {
            "category":"Bars & Pubs",
            "type":"Food & Drink"
        }
    ],
    "sg:phone":"+1   ",
    "sg:postcode":"07065",
    "sg:province":"NJ",
    "sg:tags":[
        "tavern"
    ],
    "wof:name":"Towne House",
    "wof:placetype":"venue"
},
  "geometry": {"coordinates":[-74.286784,40.600212],"type":"Point"}
}