{
  "type": "Feature",
  "properties": {
    "addr:full":"564 Shark River Rd Farmingdale NJ 07727",
    "addr:housenumber":"564",
    "addr:postcode":"07727",
    "addr:street":"Shark River Rd",
    "iso:country":"US",
    "sg:address":"564 Shark River Rd",
    "sg:city":"Farmingdale",
    "sg:classifiers":[
        {
            "category":"Professional",
            "type":"Services"
        }
    ],
    "sg:phone":"+1   ",
    "sg:postcode":"07727",
    "sg:province":"NJ",
    "wof:name":"Atkinsons Environmental & Lan",
    "wof:placetype":"venue"
},
  "geometry": {"coordinates":[-74.13135699999999,40.231987],"type":"Point"}
}