{
  "type": "Feature",
  "properties": {
    "iso:country":"US",
    "sg:address":"914 Madison Ave",
    "sg:city":"Paterson",
    "sg:classifiers":[
        {
            "category":"Real Estate",
            "subcategory":"Real Estate Agent",
            "type":"Services"
        }
    ],
    "sg:phone":"+1 973 942 4060",
    "sg:postcode":"07501",
    "sg:province":"NJ",
    "wof:name":"Uni Casa Home Realty Inc",
    "wof:placetype":"venue"
},
  "geometry": {"coordinates":[-74.156938,40.908565],"type":"Point"}
}