{
  "type": "Feature",
  "properties": {
    "addr:full":"1001 N 25th St Camden NJ 08105",
    "addr:housenumber":"1001",
    "addr:postcode":"08105",
    "addr:street":"N 25Th St",
    "iso:country":"US",
    "sg:address":"1001 N 25th St",
    "sg:city":"Camden",
    "sg:classifiers":[
        {
            "category":"Food & Beverages",
            "subcategory":"Liquor & Beverages",
            "type":"Retail Goods"
        }
    ],
    "sg:phone":"+1 856 964 2268",
    "sg:postcode":"08105",
    "sg:province":"NJ",
    "sg:tags":[
        "beer",
        "spirit",
        "wine"
    ],
    "wof:name":"Crescent Bottling Co",
    "wof:placetype":"venue"
},
  "geometry": {"coordinates":[-75.095596,39.954601],"type":"Point"}
}