{
  "type": "Feature",
  "properties": {
    "iso:country":"US",
    "sg:address":"181 Foul Rift Rd",
    "sg:city":"Belvidere",
    "sg:classifiers":[
        {
            "category":"Building & Trades",
            "subcategory":"Construction",
            "type":"Services"
        }
    ],
    "sg:phone":"+1 908 475 2448",
    "sg:postcode":"08865",
    "sg:province":"NJ",
    "sg:tags":[
        "home",
        "improvement"
    ],
    "wof:name":"Rainbow Repairs",
    "wof:placetype":"venue"
},
  "geometry": {"coordinates":[-75.11597999999999,40.787059],"type":"Point"}
}