{
  "type": "Feature",
  "properties": {
    "iso:country":"US",
    "sg:address":"10 State Rte 27",
    "sg:city":"Edison",
    "sg:classifiers":[
        {
            "category":"Shopping",
            "subcategory":"Pharmacy",
            "type":"Retail Goods"
        }
    ],
    "sg:phone":"+1 732 744 0705",
    "sg:postcode":"08820",
    "sg:province":"NJ",
    "wof:name":"Rite Aid Pharmacy",
    "wof:placetype":"venue"
},
  "geometry": {"coordinates":[-74.345636,40.555609],"type":"Point"}
}