{
  "type": "Feature",
  "properties": {
    "addr:full":"218 4th Ave Asbury Park NJ 07712",
    "addr:housenumber":"218",
    "addr:postcode":"07712",
    "addr:street":"4Th Ave Asbury",
    "iso:country":"US",
    "sg:address":"218 4th Ave",
    "sg:city":"Asbury Park",
    "sg:classifiers":[
        {
            "category":"Banks & Credit Unions",
            "subcategory":"Financial Services",
            "type":"Services"
        }
    ],
    "sg:phone":"+1   ",
    "sg:postcode":"07712",
    "sg:province":"NJ",
    "sg:tags":[
        "investor"
    ],
    "wof:name":"Rei Group Real Estate Investme",
    "wof:placetype":"venue"
},
  "geometry": {"coordinates":[-74.00291199999999,40.222945],"type":"Point"}
}