{
  "type": "Feature",
  "properties": {
    "iso:country":"US",
    "sg:address":"43 Deerfield Rd",
    "sg:city":"Somerset",
    "sg:classifiers":[
        {
            "category":"Wholesale",
            "subcategory":"Construction Materials",
            "type":"Manufacturing & Wholesale Goods"
        },
        {
            "category":"Building & Trades",
            "subcategory":"Construction",
            "type":"Services"
        }
    ],
    "sg:phone":"+1 732 828 9109",
    "sg:postcode":"08873",
    "sg:province":"NJ",
    "sg:tags":[
        "fence",
        "contractor"
    ],
    "wof:name":"Mar Nic Fence & Construction",
    "wof:placetype":"venue"
},
  "geometry": {"coordinates":[-74.49713800000001,40.517323],"type":"Point"}
}