{
  "type": "Feature",
  "properties": {
    "iso:country":"US",
    "sg:address":"2022 Brookside Dr",
    "sg:city":"Scotch Plains",
    "sg:classifiers":[
        {
            "category":"Wholesale",
            "subcategory":"Drugs",
            "type":"Manufacturing & Wholesale Goods"
        }
    ],
    "sg:phone":"+1 908 654 8404",
    "sg:postcode":"07076",
    "sg:province":"NJ",
    "wof:name":"Cattleya Inc",
    "wof:placetype":"venue"
},
  "geometry": {"coordinates":[-74.363102,40.633387],"type":"Point"}
}