{
  "type": "Feature",
  "properties": {
    "addr:full":"3 Swimming River Rd Lincroft NJ 07738",
    "addr:housenumber":"3",
    "addr:postcode":"07738",
    "addr:street":"Swimming River Rd",
    "iso:country":"US",
    "sg:address":"3 Swimming River Rd",
    "sg:city":"Lincroft",
    "sg:classifiers":[
        {
            "category":"Food & Beverages",
            "subcategory":"Liquor & Beverages",
            "type":"Retail Goods"
        }
    ],
    "sg:phone":"+1 732 747 0118",
    "sg:postcode":"07738",
    "sg:province":"NJ",
    "sg:tags":[
        "alcoholic"
    ],
    "wof:name":"Lincroft Wine & Liquors",
    "wof:placetype":"venue"
},
  "geometry": {"coordinates":[-74.118915,40.328859],"type":"Point"}
}