{
  "type": "Feature",
  "properties": {
    "iso:country":"US",
    "sg:address":"520 Jefferson Ave",
    "sg:city":"Secaucus",
    "sg:classifiers":[
        {
            "category":"Wholesale",
            "subcategory":"Groceries",
            "type":"Manufacturing & Wholesale Goods"
        }
    ],
    "sg:phone":"+1 201 319 0842",
    "sg:postcode":"07094",
    "sg:province":"NJ",
    "sg:tags":[
        "confectionery"
    ],
    "wof:name":"Frito-Lay",
    "wof:placetype":"venue"
},
  "geometry": {"coordinates":[-74.06703,40.774668],"type":"Point"}
}