{
  "type": "Feature",
  "properties": {
    "iso:country":"US",
    "sg:address":"1460 Morris Ave",
    "sg:city":"Union",
    "sg:classifiers":[
        {
            "category":"Banks & Credit Unions",
            "subcategory":"Bank",
            "type":"Services"
        }
    ],
    "sg:phone":"+1 908 688 4488",
    "sg:postcode":"07083",
    "sg:province":"NJ",
    "sg:tags":[
        "loan",
        "real estate"
    ],
    "wof:name":"First Homeland Mortgage",
    "wof:placetype":"venue"
},
  "geometry": {"coordinates":[-74.24877499999999,40.689877],"type":"Point"}
}