{
  "type": "Feature",
  "properties": {
    "iso:country":"US",
    "sg:address":"423 Fisher Ave",
    "sg:city":"Neptune",
    "sg:classifiers":[
        {
            "category":"Building & Trades",
            "subcategory":"Construction",
            "type":"Services"
        }
    ],
    "sg:phone":"+1 732 775 5008",
    "sg:postcode":"07753",
    "sg:province":"NJ",
    "sg:tags":[
        "general",
        "contractor"
    ],
    "wof:name":"We Do It All Contractors",
    "wof:placetype":"venue"
},
  "geometry": {"coordinates":[-74.02728999999999,40.217691],"type":"Point"}
}