{
  "type": "Feature",
  "properties": {
    "addr:full":"24 E Blackwell St Dover NJ 07801",
    "addr:housenumber":"24",
    "addr:postcode":"07801",
    "addr:street":"E Blackwell St",
    "iso:country":"US",
    "sg:address":"24 E Blackwell St",
    "sg:city":"Dover",
    "sg:classifiers":[
        {
            "category":"Retail",
            "subcategory":"Repair Shop",
            "type":"Services"
        }
    ],
    "sg:phone":"+1 973 361 0420",
    "sg:postcode":"07801",
    "sg:province":"NJ",
    "wof:name":"Essex Security Locksmiths",
    "wof:placetype":"venue"
},
  "geometry": {"coordinates":[-74.55677300000001,40.884267],"type":"Point"}
}