{
  "type": "Feature",
  "properties": {
    "addr:full":"38 Norma Rd Harrington Park NJ 07640",
    "addr:housenumber":"38",
    "addr:postcode":"07640",
    "addr:street":"Norma Rd",
    "iso:country":"US",
    "sg:address":"38 Norma Rd",
    "sg:city":"Harrington Park",
    "sg:classifiers":[
        {
            "category":"Professional",
            "type":"Services"
        }
    ],
    "sg:phone":"+1   ",
    "sg:postcode":"07640",
    "sg:province":"NJ",
    "wof:name":"Arthur Thorspecken",
    "wof:placetype":"venue"
},
  "geometry": {"coordinates":[-73.984525,40.981466],"type":"Point"}
}