{
  "type": "Feature",
  "properties": {
    "iso:country":"US",
    "sg:address":"236 Blackford Ave",
    "sg:city":"Middlesex",
    "sg:classifiers":[
        {
            "category":"Manufacturing",
            "subcategory":"Food",
            "type":"Manufacturing & Wholesale Goods"
        }
    ],
    "sg:phone":"+1 732 469 6615",
    "sg:postcode":"08846",
    "sg:province":"NJ",
    "sg:tags":[
        "flavor",
        "mfg",
        "fragrance",
        "compound"
    ],
    "sg:website":"www.premierfragrances.com",
    "wof:name":"Premier Specialties Inc",
    "wof:placetype":"venue"
},
  "geometry": {"coordinates":[-74.48765299999999,40.571698],"type":"Point"}
}