{
  "type": "Feature",
  "properties": {
    "addr:full":"3705 Quakerbridge Rd Trenton NJ 08619",
    "addr:housenumber":"3705",
    "addr:postcode":"08619",
    "addr:street":"Quakerbridge Rd",
    "iso:country":"US",
    "sg:address":"3705 Quakerbridge Rd",
    "sg:city":"Trenton",
    "sg:classifiers":[
        {
            "category":"Real Estate",
            "subcategory":"Real Estate Agent",
            "type":"Services"
        }
    ],
    "sg:phone":"+1 609 689 4670",
    "sg:postcode":"08619",
    "sg:province":"NJ",
    "sg:tags":[
        "management"
    ],
    "wof:name":"A B C Real Estate LLC",
    "wof:placetype":"venue"
},
  "geometry": {"coordinates":[-74.677156,40.259608],"type":"Point"}
}