{
  "type": "Feature",
  "properties": {
    "iso:country":"US",
    "sg:address":"120 Washington St",
    "sg:city":"Morristown",
    "sg:classifiers":[
        {
            "category":"Professional",
            "subcategory":"Secretarial Services",
            "type":"Services"
        }
    ],
    "sg:phone":"+1   ",
    "sg:postcode":"07960",
    "sg:province":"NJ",
    "sg:tags":[
        "reporting"
    ],
    "wof:name":"Brittany Transcription",
    "wof:placetype":"venue"
},
  "geometry": {"coordinates":[-74.489096,40.799622],"type":"Point"}
}