{
  "type": "Feature",
  "properties": {
    "iso:country":"US",
    "sg:address":"400 Main St",
    "sg:city":"Hackensack",
    "sg:classifiers":[
        {
            "category":"Education",
            "subcategory":"School",
            "type":"Public Place"
        }
    ],
    "sg:phone":"+1 201 488 2804",
    "sg:postcode":"07601",
    "sg:province":"NJ",
    "wof:name":"Citizen Policy & Education Fund of N J",
    "wof:placetype":"venue"
},
  "geometry": {"coordinates":[-74.039497,40.891201],"type":"Point"}
}