{
  "type": "Feature",
  "properties": {
    "iso:country":"US",
    "sg:address":"199 Sawmill Dr W",
    "sg:city":"Berkeley Heights",
    "sg:classifiers":[
        {
            "category":"Professional",
            "type":"Services"
        }
    ],
    "sg:phone":"+1   ",
    "sg:postcode":"07922",
    "sg:province":"NJ",
    "wof:name":"Victor Tek Inc",
    "wof:placetype":"venue"
},
  "geometry": {"coordinates":[-74.448853,40.672295],"type":"Point"}
}