{
  "type": "Feature",
  "properties": {
    "iso:country":"US",
    "sg:address":"25 Clifton Ave",
    "sg:city":"Newark",
    "sg:classifiers":[
        {
            "category":"Shopping",
            "subcategory":"Computers & Home Electronics",
            "type":"Retail Goods"
        }
    ],
    "sg:phone":"+1 973 484 4869",
    "sg:postcode":"07104",
    "sg:province":"NJ",
    "sg:tags":[
        "equipment",
        "dealer",
        "software"
    ],
    "wof:name":"Quantum Leaps",
    "wof:placetype":"venue"
},
  "geometry": {"coordinates":[-74.17960100000001,40.75141],"type":"Point"}
}