{
  "type": "Feature",
  "properties": {
    "addr:full":"18 Broad St Bloomfield NJ 07003",
    "addr:housenumber":"18",
    "addr:postcode":"07003",
    "addr:street":"Broad St",
    "iso:country":"US",
    "sg:address":"18 Broad St",
    "sg:city":"Bloomfield",
    "sg:classifiers":[
        {
            "category":"Restaurant",
            "type":"Food & Drink"
        }
    ],
    "sg:phone":"+1 973 680 9911",
    "sg:postcode":"07003",
    "sg:province":"NJ",
    "sg:website":"www.nicolesplace.com",
    "wof:name":"Nicole's Place",
    "wof:placetype":"venue"
},
  "geometry": {"coordinates":[-74.197615,40.794072],"type":"Point"}
}