{
  "type": "Feature",
  "properties": {
    "addr:full":"41 N Passaic Ave Chatham NJ 07928",
    "addr:housenumber":"41",
    "addr:postcode":"07928",
    "addr:street":"N Passaic Ave",
    "iso:country":"US",
    "sg:address":"41 N Passaic Ave",
    "sg:city":"Chatham",
    "sg:classifiers":[
        {
            "category":"Personal",
            "type":"Services"
        },
        {
            "category":"Retail",
            "subcategory":"Auto Repair",
            "type":"Services"
        }
    ],
    "sg:phone":"+1 973 635 9428",
    "sg:postcode":"07928",
    "sg:province":"NJ",
    "sg:tags":[
        "body",
        "shop",
        "towing"
    ],
    "wof:name":"Chatham Collision Repair Inc",
    "wof:placetype":"venue"
},
  "geometry": {"coordinates":[-74.38110399999999,40.742001],"type":"Point"}
}