{
  "type": "Feature",
  "properties": {
    "addr:full":"11 Hamburg Tpke Riverdale NJ 07457",
    "addr:housenumber":"11",
    "addr:postcode":"07457",
    "addr:street":"Hamburg Tpke",
    "iso:country":"US",
    "sg:address":"11 Hamburg Tpke",
    "sg:city":"Riverdale",
    "sg:classifiers":[
        {
            "category":"Wholesale",
            "subcategory":"Hardware",
            "type":"Manufacturing & Wholesale Goods"
        }
    ],
    "sg:phone":"+1 973 835 2024",
    "sg:postcode":"07457",
    "sg:province":"NJ",
    "sg:tags":[
        "plumbing",
        "fixture",
        "supply"
    ],
    "wof:name":"Pompton Plumbing & Heating Co",
    "wof:placetype":"venue"
},
  "geometry": {"coordinates":[-74.29959700000001,40.998623],"type":"Point"}
}