{
  "type": "Feature",
  "properties": {
    "addr:full":"152 Market St Paterson NJ 07505",
    "addr:housenumber":"152",
    "addr:postcode":"07505",
    "addr:street":"Market St",
    "iso:country":"US",
    "sg:address":"152 Market St",
    "sg:city":"Paterson",
    "sg:classifiers":[
        {
            "category":"Utilities",
            "subcategory":"Mobile Phone",
            "type":"Services"
        }
    ],
    "sg:phone":"+1 973 345 2258",
    "sg:postcode":"07505",
    "sg:province":"NJ",
    "sg:tags":[
        "telephone",
        "cellular"
    ],
    "wof:name":"Inter America Cellular Inc",
    "wof:placetype":"venue"
},
  "geometry": {"coordinates":[-74.172209,40.916652],"type":"Point"}
}