{
  "type": "Feature",
  "properties": {
    "addr:full":"825 W Park Ave Asbury Park NJ 07712",
    "addr:housenumber":"825",
    "addr:postcode":"07712",
    "addr:street":"W Park Ave Asbury",
    "iso:country":"US",
    "sg:address":"825 W Park Ave",
    "sg:city":"Asbury Park",
    "sg:classifiers":[
        {
            "category":"Recreation",
            "type":"Entertainment"
        },
        {
            "category":"Restaurant",
            "type":"Food & Drink"
        }
    ],
    "sg:phone":"+1 732 493 8002",
    "sg:postcode":"07712",
    "sg:province":"NJ",
    "sg:tags":[
        "club",
        "membership",
        "delicatessen"
    ],
    "wof:name":"Monmouth Clubhouse Deli LLC",
    "wof:placetype":"venue"
},
  "geometry": {"coordinates":[-74.042765,40.264368],"type":"Point"}
}