{
  "type": "Feature",
  "properties": {
    "addr:full":"54 Shrewsbury Ave Red Bank NJ 07701",
    "addr:housenumber":"54",
    "addr:postcode":"07701",
    "addr:street":"Shrewsbury Ave",
    "iso:country":"US",
    "sg:address":"54 Shrewsbury Ave",
    "sg:city":"Red Bank",
    "sg:classifiers":[
        {
            "category":"Professional",
            "subcategory":"Lawyer & Legal Services",
            "type":"Services"
        }
    ],
    "sg:phone":"+1 732 842 6500",
    "sg:postcode":"07701",
    "sg:province":"NJ",
    "sg:tags":[
        "attorney"
    ],
    "wof:name":"Mc Omber & Mc Omber",
    "wof:placetype":"venue"
},
  "geometry": {"coordinates":[-74.076649,40.350164],"type":"Point"}
}