{
  "type": "Feature",
  "properties": {
    "iso:country":"US",
    "sg:address":"169 Clinton Ave",
    "sg:city":"Clifton",
    "sg:classifiers":[
        {
            "category":"Health Services",
            "subcategory":"Clinic",
            "type":"Services"
        }
    ],
    "sg:phone":"+1 973 471 3484",
    "sg:postcode":"07011",
    "sg:province":"NJ",
    "sg:tags":[
        "home",
        "care"
    ],
    "wof:name":"Donna Unis",
    "wof:placetype":"venue"
},
  "geometry": {"coordinates":[-74.146613,40.871487],"type":"Point"}
}