{
  "type": "Feature",
  "properties": {
    "iso:country":"US",
    "sg:address":"145 N Franklin Tpke",
    "sg:city":"Ramsey",
    "sg:classifiers":[
        {
            "category":"Professional",
            "subcategory":"Advertising",
            "type":"Services"
        }
    ],
    "sg:phone":"+1 201 995 9944",
    "sg:postcode":"07446",
    "sg:province":"NJ",
    "sg:tags":[
        "counselor"
    ],
    "wof:name":"LJS Communications",
    "wof:placetype":"venue"
},
  "geometry": {"coordinates":[-74.133612,41.063124],"type":"Point"}
}