{
  "type": "Feature",
  "properties": {
    "iso:country":"US",
    "sg:address":"81 Grand Ave",
    "sg:city":"Englewood",
    "sg:classifiers":[
        {
            "category":"Building & Trades",
            "subcategory":"Cleaning & Sanitation",
            "type":"Services"
        }
    ],
    "sg:phone":"+1 201 871 2301",
    "sg:postcode":"07631",
    "sg:province":"NJ",
    "sg:tags":[
        "janitor"
    ],
    "wof:name":"Tower Cleaning",
    "wof:placetype":"venue"
},
  "geometry": {"coordinates":[-73.974991,40.890224],"type":"Point"}
}