{
  "type": "Feature",
  "properties": {
    "addr:full":"615 Rahway Ave Woodbridge NJ 07095",
    "addr:housenumber":"615",
    "addr:postcode":"07095",
    "addr:street":"Rahway Ave",
    "iso:country":"US",
    "sg:address":"615 Rahway Ave",
    "sg:city":"Woodbridge",
    "sg:classifiers":[
        {
            "category":"Retail",
            "subcategory":"Laundry & Dry Cleaning",
            "type":"Services"
        }
    ],
    "sg:phone":"+1 732 634 4313",
    "sg:postcode":"07095",
    "sg:province":"NJ",
    "sg:tags":[
        "drycleaning",
        "plant"
    ],
    "wof:name":"Elite Tailors & Cleaners",
    "wof:placetype":"venue"
},
  "geometry": {"coordinates":[-74.274002,40.562099],"type":"Point"}
}