{
  "type": "Feature",
  "properties": {
    "addr:full":"3 Fair Lawn Ave Fair Lawn NJ 07410",
    "addr:housenumber":"3",
    "addr:postcode":"07410",
    "addr:street":"Fair Lawn Ave",
    "iso:country":"US",
    "sg:address":"3 Fair Lawn Ave",
    "sg:city":"Fair Lawn",
    "sg:classifiers":[
        {
            "category":"Food & Beverages",
            "subcategory":"Groceries & Convenience Stores",
            "type":"Retail Goods"
        },
        {
            "category":"Restaurant",
            "type":"Food & Drink"
        }
    ],
    "sg:phone":"+1 201 797 5010",
    "sg:postcode":"07410",
    "sg:province":"NJ",
    "sg:tags":[
        "delicatessen",
        "caterer"
    ],
    "wof:name":"Petak's Glatt Kosher Fine Food",
    "wof:placetype":"venue"
},
  "geometry": {"coordinates":[-74.11392600000001,40.94095],"type":"Point"}
}