{
  "type": "Feature",
  "properties": {
    "iso:country":"US",
    "sg:address":"20 Union St",
    "sg:city":"Rockaway",
    "sg:classifiers":[
        {
            "category":"Building & Trades",
            "subcategory":"Construction",
            "type":"Services"
        }
    ],
    "sg:phone":"+1 973 627 1252",
    "sg:postcode":"07866",
    "sg:province":"NJ",
    "sg:tags":[
        "residential"
    ],
    "wof:name":"Pace Builders Inc",
    "wof:placetype":"venue"
},
  "geometry": {"coordinates":[-74.507948,40.903731],"type":"Point"}
}