{
  "type": "Feature",
  "properties": {
    "iso:country":"US",
    "sg:address":"100 Thanet Cir",
    "sg:city":"Princeton",
    "sg:classifiers":[
        {
            "category":"Professional",
            "subcategory":"Research",
            "type":"Services"
        }
    ],
    "sg:phone":"+1 609 924 0464",
    "sg:postcode":"08540",
    "sg:province":"NJ",
    "sg:tags":[
        "educational"
    ],
    "wof:name":"Applied Educational Research",
    "wof:placetype":"venue"
},
  "geometry": {"coordinates":[-74.652328,40.369001],"type":"Point"}
}