{
  "type": "Feature",
  "properties": {
    "iso:country":"US",
    "sg:address":"185 Cedar Ln Ste L1",
    "sg:city":"Teaneck",
    "sg:classifiers":[
        {
            "category":"Health Services",
            "subcategory":"Doctor",
            "type":"Services"
        }
    ],
    "sg:phone":"+1 201 836 5144",
    "sg:postcode":"07666",
    "sg:province":"NJ",
    "wof:name":"Tsai Philip H MD",
    "wof:placetype":"venue"
},
  "geometry": {"coordinates":[-74.01329800000001,40.8862],"type":"Point"}
}