{
  "type": "Feature",
  "properties": {
    "addr:full":"141 Lanza Ave Bldg 18D Garfield NJ 07026",
    "addr:housenumber":"141;18d",
    "addr:postcode":"07026",
    "addr:street":"Lanza Ave Bldg",
    "iso:country":"US",
    "sg:address":"141 Lanza Ave Bldg 18D",
    "sg:city":"Garfield",
    "sg:classifiers":[
        {
            "category":"Coffee & Tea",
            "type":"Food & Drink"
        }
    ],
    "sg:phone":"+1 973 253 7400",
    "sg:postcode":"07026",
    "sg:province":"NJ",
    "sg:website":"www.adagio.com",
    "wof:name":"Adagio Teas",
    "wof:placetype":"venue"
},
  "geometry": {"coordinates":[-74.122674,40.887628],"type":"Point"}
}