{
  "type": "Feature",
  "properties": {
    "addr:full":"36 Gates Ave Warren NJ 07059",
    "addr:housenumber":"36",
    "addr:postcode":"07059",
    "addr:street":"Gates Ave",
    "iso:country":"US",
    "sg:address":"36 Gates Ave",
    "sg:city":"Warren",
    "sg:classifiers":[
        {
            "category":"Building & Trades",
            "subcategory":"Construction",
            "type":"Services"
        }
    ],
    "sg:phone":"+1 908 756 4926",
    "sg:postcode":"07059",
    "sg:province":"NJ",
    "sg:tags":[
        "house"
    ],
    "wof:name":"Finer Home Improvement LLC",
    "wof:placetype":"venue"
},
  "geometry": {"coordinates":[-74.48115199999999,40.641447],"type":"Point"}
}