{
  "type": "Feature",
  "properties": {
    "iso:country":"US",
    "sg:address":"75 S Route 73",
    "sg:city":"Hammonton",
    "sg:classifiers":[
        {
            "category":"Building & Trades",
            "subcategory":"Construction",
            "type":"Services"
        }
    ],
    "sg:phone":"+1 856 235 8600",
    "sg:postcode":"08037",
    "sg:province":"NJ",
    "sg:tags":[
        "industrial",
        "wallcoverings-installation",
        "wallpaper",
        "contractor",
        "contractors-commercial",
        "painting"
    ],
    "sg:website":"http://www.stojanovbros.com",
    "wof:name":"Stojanov Bros Inc",
    "wof:placetype":"venue"
},
  "geometry": {"coordinates":[-74.897457,39.70768],"type":"Point"}
}