{
  "type": "Feature",
  "properties": {
    "addr:full":"877 N Concourse Keyport NJ 07735",
    "addr:housenumber":"877",
    "addr:postcode":"07735",
    "addr:street":"N Concourse",
    "iso:country":"US",
    "sg:address":"877 N Concourse",
    "sg:city":"Keyport",
    "sg:classifiers":[
        {
            "category":"Building & Trades",
            "subcategory":"Landscaping Services",
            "type":"Services"
        }
    ],
    "sg:phone":"+1 732 583 8387",
    "sg:postcode":"07735",
    "sg:province":"NJ",
    "wof:name":"Botanical Accents LLC",
    "wof:placetype":"venue"
},
  "geometry": {"coordinates":[-74.217332,40.445011],"type":"Point"}
}