{
  "type": "Feature",
  "properties": {
    "iso:country":"US",
    "sg:address":"39 W Broad St",
    "sg:city":"Paulsboro",
    "sg:classifiers":[
        {
            "category":"Home & Garden",
            "subcategory":"Hardware",
            "type":"Retail Goods"
        }
    ],
    "sg:phone":"+1 856 423 0600",
    "sg:postcode":"08066",
    "sg:province":"NJ",
    "wof:name":"Weiss True Value Hardware",
    "wof:placetype":"venue"
},
  "geometry": {"coordinates":[-75.24154900000001,39.830011],"type":"Point"}
}