{
  "type": "Feature",
  "properties": {
    "addr:full":"2 Kingston Blvd Trenton NJ 08690",
    "addr:housenumber":"2",
    "addr:postcode":"08690",
    "addr:street":"Kingston Blvd",
    "iso:country":"US",
    "sg:address":"2 Kingston Blvd",
    "sg:city":"Trenton",
    "sg:classifiers":[
        {
            "category":"Building & Trades",
            "subcategory":"Construction",
            "type":"Services"
        }
    ],
    "sg:phone":"+1 609 631 8898",
    "sg:postcode":"08690",
    "sg:province":"NJ",
    "sg:tags":[
        "contractor"
    ],
    "wof:name":"Deluca Enterprises Inc",
    "wof:placetype":"venue"
},
  "geometry": {"coordinates":[-74.675134,40.199028],"type":"Point"}
}