{
  "type": "Feature",
  "properties": {
    "addr:full":"156 Muhammad Ali Ave Newark NJ 07108",
    "addr:housenumber":"156",
    "addr:postcode":"07108",
    "addr:street":"Muhammad Ali Ave",
    "iso:country":"US",
    "sg:address":"156 Muhammad Ali Ave",
    "sg:city":"Newark",
    "sg:classifiers":[
        {
            "category":"Shopping",
            "type":"Retail Goods"
        }
    ],
    "sg:phone":"+1 973 824 9344",
    "sg:postcode":"07108",
    "sg:province":"NJ",
    "sg:tags":[
        "religious"
    ],
    "wof:name":"Mack Brown",
    "wof:placetype":"venue"
},
  "geometry": {"coordinates":[-74.193181,40.727363],"type":"Point"}
}