{
  "type": "Feature",
  "properties": {
    "addr:full":"166 Washington Ave Dumont NJ 07628",
    "addr:housenumber":"166",
    "addr:postcode":"07628",
    "addr:street":"Washington Ave",
    "iso:country":"US",
    "sg:address":"166 Washington Ave",
    "sg:city":"Dumont",
    "sg:classifiers":[
        {
            "category":"Health Services",
            "subcategory":"Doctor",
            "type":"Services"
        }
    ],
    "sg:phone":"+1 201 384 2112",
    "sg:postcode":"07628",
    "sg:province":"NJ",
    "sg:tags":[
        "dentist",
        "medical"
    ],
    "wof:name":"Jeffrey Manheimer DMD",
    "wof:placetype":"venue"
},
  "geometry": {"coordinates":[-73.993405,40.941659],"type":"Point"}
}