{
  "type": "Feature",
  "properties": {
    "addr:full":"312 Orange Rd Montclair NJ 07042",
    "addr:housenumber":"312",
    "addr:postcode":"07042",
    "addr:street":"Orange Rd",
    "iso:country":"US",
    "sg:address":"312 Orange Rd",
    "sg:city":"Montclair",
    "sg:classifiers":[
        {
            "category":"Restaurant",
            "type":"Food & Drink"
        }
    ],
    "sg:phone":"+1 973 509 9559",
    "sg:postcode":"07042",
    "sg:province":"NJ",
    "sg:tags":[
        "delicatessen"
    ],
    "wof:name":"South End New York Deli",
    "wof:placetype":"venue"
},
  "geometry": {"coordinates":[-74.219066,40.797675],"type":"Point"}
}