{
  "type": "Feature",
  "properties": {
    "addr:full":"224 Highwood Ave Ridgewood NJ 07450",
    "addr:housenumber":"224",
    "addr:postcode":"07450",
    "addr:street":"Highwood Ave",
    "iso:country":"US",
    "sg:address":"224 Highwood Ave",
    "sg:city":"Ridgewood",
    "sg:classifiers":[
        {
            "category":"Organizations",
            "subcategory":"Religious Organization",
            "type":"Services"
        }
    ],
    "sg:phone":"+1   ",
    "sg:postcode":"07450",
    "sg:province":"NJ",
    "wof:name":"Quakers Religious",
    "wof:placetype":"venue"
},
  "geometry": {"coordinates":[-74.12202000000001,40.974774],"type":"Point"}
}