{
  "type": "Feature",
  "properties": {
    "addr:full":"12 Saratoga Ave Bound Brook NJ 08805",
    "addr:housenumber":"12",
    "addr:postcode":"08805",
    "addr:street":"Saratoga Ave",
    "iso:country":"US",
    "sg:address":"12 Saratoga Ave",
    "sg:city":"Bound Brook",
    "sg:classifiers":[
        {
            "category":"Building & Trades",
            "subcategory":"Electrical",
            "type":"Services"
        }
    ],
    "sg:phone":"+1 732 356 2628",
    "sg:postcode":"08805",
    "sg:province":"NJ",
    "sg:tags":[
        "electric",
        "contractor"
    ],
    "wof:name":"State Wide Electrical Contr",
    "wof:placetype":"venue"
},
  "geometry": {"coordinates":[-74.546919,40.574131],"type":"Point"}
}