{
  "type": "Feature",
  "properties": {
    "iso:country":"US",
    "sg:address":"1001 Lower Landing Rd # 407",
    "sg:city":"Blackwood",
    "sg:classifiers":[
        {
            "category":"Home & Garden",
            "subcategory":"Home Furnishings",
            "type":"Retail Goods"
        },
        {
            "category":"Home & Garden",
            "subcategory":"Building Materials",
            "type":"Retail Goods"
        },
        {
            "category":"Building & Trades",
            "subcategory":"Construction",
            "type":"Services"
        }
    ],
    "sg:phone":"+1 856 232 0420",
    "sg:postcode":"08012",
    "sg:province":"NJ",
    "sg:tags":[
        "bathroom",
        "radiators-heating",
        "baths-equipment",
        "supply",
        "sales",
        "cabinet",
        "fixtures",
        "accessory"
    ],
    "sg:website":"http://www.soldiercity.com",
    "wof:name":"Soldiercity",
    "wof:placetype":"venue"
},
  "geometry": {"coordinates":[-75.08055899999999,39.817299],"type":"Point"}
}