{
  "type": "Feature",
  "properties": {
    "addr:full":"1571 6th St Trenton NJ 08638",
    "addr:housenumber":"1571",
    "addr:postcode":"08638",
    "addr:street":"6Th St",
    "iso:country":"US",
    "sg:address":"1571 6th St",
    "sg:city":"Trenton",
    "sg:classifiers":[
        {
            "category":"Home & Garden",
            "subcategory":"Building Materials",
            "type":"Retail Goods"
        }
    ],
    "sg:phone":"+1   ",
    "sg:postcode":"08638",
    "sg:province":"NJ",
    "sg:tags":[
        "glass",
        "install",
        "mirror"
    ],
    "wof:name":"Gebco Custom Mirror & Glass",
    "wof:placetype":"venue"
},
  "geometry": {"coordinates":[-74.76120400000001,40.247516],"type":"Point"}
}