{
  "type": "Feature",
  "properties": {
    "iso:country":"US",
    "sg:address":"41 Bloomfield Ave",
    "sg:city":"Caldwell",
    "sg:classifiers":[
        {
            "category":"Insurance",
            "subcategory":"Insurance Agent",
            "type":"Services"
        }
    ],
    "sg:phone":"+1 973 228 3006",
    "sg:postcode":"07006",
    "sg:province":"NJ",
    "wof:name":"Diversified Ins Inc",
    "wof:placetype":"venue"
},
  "geometry": {"coordinates":[-74.26370199999999,40.835175],"type":"Point"}
}