{
  "type": "Feature",
  "properties": {
    "addr:full":"317 Hopewell Amwell Rd Hopewell NJ 08525",
    "addr:housenumber":"317",
    "addr:postcode":"08525",
    "addr:street":"Hopewell Amwell Rd",
    "iso:country":"US",
    "sg:address":"317 Hopewell Amwell Rd",
    "sg:city":"Hopewell",
    "sg:classifiers":[
        {
            "category":"Building & Trades",
            "subcategory":"Construction",
            "type":"Services"
        }
    ],
    "sg:phone":"+1 609 466 2980",
    "sg:postcode":"08525",
    "sg:province":"NJ",
    "sg:tags":[
        "general",
        "contractor"
    ],
    "wof:name":"Geza Construction",
    "wof:placetype":"venue"
},
  "geometry": {"coordinates":[-74.750895,40.398273],"type":"Point"}
}