{
  "type": "Feature",
  "properties": {
    "addr:full":"269 Maple Ave Mantua NJ 08051",
    "addr:housenumber":"269",
    "addr:postcode":"08051",
    "addr:street":"Maple Ave",
    "iso:country":"US",
    "sg:address":"269 Maple Ave",
    "sg:city":"Mantua",
    "sg:classifiers":[
        {
            "category":"Building & Trades",
            "subcategory":"Construction",
            "type":"Services"
        },
        {
            "category":"Sports & Exercise",
            "subcategory":"Swimming Pool",
            "type":"Entertainment"
        }
    ],
    "sg:phone":"+1 856 468 8982",
    "sg:postcode":"08051",
    "sg:province":"NJ",
    "wof:name":"Huttchison Pools",
    "wof:placetype":"venue"
},
  "geometry": {"coordinates":[-75.16762199999999,39.784981],"type":"Point"}
}