{
  "type": "Feature",
  "properties": {
    "addr:full":"12 E Edsall Blvd Palisades Park NJ 07650",
    "addr:housenumber":"12",
    "addr:postcode":"07650",
    "addr:street":"E Edsall Blvd",
    "iso:country":"US",
    "sg:address":"12 E Edsall Blvd",
    "sg:city":"Palisades Park",
    "sg:classifiers":[
        {
            "category":"Home & Garden",
            "subcategory":"Furniture",
            "type":"Retail Goods"
        }
    ],
    "sg:phone":"+1 201 302 9955",
    "sg:postcode":"07650",
    "sg:province":"NJ",
    "sg:tags":[
        "equipment",
        "kitchen",
        "cabinet"
    ],
    "wof:name":"Hansem Interior",
    "wof:placetype":"venue"
},
  "geometry": {"coordinates":[-73.994265,40.852175],"type":"Point"}
}