{
  "type": "Feature",
  "properties": {
    "addr:full":"182 Main St Little Ferry NJ 07643",
    "addr:housenumber":"182",
    "addr:postcode":"07643",
    "addr:street":"Main St",
    "iso:country":"US",
    "sg:address":"182 Main St",
    "sg:city":"Little Ferry",
    "sg:classifiers":[
        {
            "category":"Personal",
            "subcategory":"Beauty Salon",
            "type":"Services"
        }
    ],
    "sg:phone":"+1   ",
    "sg:postcode":"07643",
    "sg:province":"NJ",
    "sg:tags":[
        "shop"
    ],
    "wof:name":"Estee Nail Salon",
    "wof:placetype":"venue"
},
  "geometry": {"coordinates":[-74.040683,40.851771],"type":"Point"}
}