{
  "type": "Feature",
  "properties": {
    "addr:full":"319 Hamilton St Harrison NJ 07029",
    "addr:housenumber":"319",
    "addr:postcode":"07029",
    "addr:street":"Hamilton St",
    "iso:country":"US",
    "sg:address":"319 Hamilton St",
    "sg:city":"Harrison",
    "sg:classifiers":[
        {
            "category":"Professional",
            "type":"Services"
        }
    ],
    "sg:phone":"+1   ",
    "sg:postcode":"07029",
    "sg:province":"NJ",
    "wof:name":"Otilia S Rduarte",
    "wof:placetype":"venue"
},
  "geometry": {"coordinates":[-74.156818,40.747799],"type":"Point"}
}