{
  "type": "Feature",
  "properties": {
    "iso:country":"US",
    "sg:address":"3716 Church Rd",
    "sg:city":"Mt Laurel",
    "sg:classifiers":[
        {
            "category":"Building & Trades",
            "subcategory":"Construction",
            "type":"Services"
        }
    ],
    "sg:phone":"+1 856 608 2900",
    "sg:postcode":"08054",
    "sg:province":"NJ",
    "sg:tags":[
        "contractor"
    ],
    "wof:name":"Administration Building Innova",
    "wof:placetype":"venue"
},
  "geometry": {"coordinates":[-74.976741,39.930002],"type":"Point"}
}