{
  "type": "Feature",
  "properties": {
    "iso:country":"US",
    "sg:address":"220 S Orange Ave Ste 106",
    "sg:city":"Livingston",
    "sg:classifiers":[
        {
            "category":"Shopping",
            "subcategory":"Hobbies, Toys, & Games",
            "type":"Retail Goods"
        }
    ],
    "sg:phone":"+1 973 740 8882",
    "sg:postcode":"07039",
    "sg:province":"NJ",
    "sg:tags":[
        "toy",
        "store"
    ],
    "wof:name":"Blue Box Toys",
    "wof:placetype":"venue"
},
  "geometry": {"coordinates":[-74.35332099999999,40.772054],"type":"Point"}
}