{
  "type": "Feature",
  "properties": {
    "addr:full":"18 Dalton Pl Fair Lawn NJ 07410",
    "addr:housenumber":"18",
    "addr:postcode":"07410",
    "addr:street":"Dalton Pl",
    "iso:country":"US",
    "sg:address":"18 Dalton Pl",
    "sg:city":"Fair Lawn",
    "sg:classifiers":[
        {
            "category":"Retail",
            "subcategory":"Laundry & Dry Cleaning",
            "type":"Services"
        }
    ],
    "sg:phone":"+1 845 356 8559",
    "sg:postcode":"07410",
    "sg:province":"NJ",
    "sg:tags":[
        "cleaners",
        "rug",
        "carpet"
    ],
    "wof:name":"Dr Do All",
    "wof:placetype":"venue"
},
  "geometry": {"coordinates":[-74.112793,40.920138],"type":"Point"}
}