{
  "type": "Feature",
  "properties": {
    "addr:full":"1355 15th St Ste 150 Fort Lee NJ 07024",
    "addr:housenumber":"1355",
    "addr:postcode":"07024",
    "addr:street":"15Th St Ste 150",
    "iso:country":"US",
    "sg:address":"1355 15th St Ste 150",
    "sg:city":"Fort Lee",
    "sg:classifiers":[
        {
            "category":"Health Services",
            "subcategory":"Chiropractor",
            "type":"Services"
        }
    ],
    "sg:phone":"+1 201 592 1378",
    "sg:postcode":"07024",
    "sg:province":"NJ",
    "wof:name":"Elliot Koziel, DC",
    "wof:placetype":"venue"
},
  "geometry": {"coordinates":[-73.981126,40.845636],"type":"Point"}
}