{
  "type": "Feature",
  "properties": {
    "iso:country":"US",
    "sg:address":"145 Lexington Ave",
    "sg:city":"Passaic",
    "sg:classifiers":[
        {
            "category":"Autos & Motor Vehicles",
            "subcategory":"Fuel & Gas Station",
            "type":"Retail Goods"
        }
    ],
    "sg:phone":"+1 973 779 3160",
    "sg:postcode":"07055",
    "sg:province":"NJ",
    "sg:tags":[
        "repair",
        "gasoline"
    ],
    "wof:name":"Janiak's Auto Service",
    "wof:placetype":"venue"
},
  "geometry": {"coordinates":[-74.127403,40.866798],"type":"Point"}
}