{
  "type": "Feature",
  "properties": {
    "iso:country":"US",
    "sg:address":"4214 Harbor Beach Blvd",
    "sg:city":"Brigantine",
    "sg:classifiers":[
        {
            "category":"Shopping",
            "subcategory":"Gifts & Souvenirs",
            "type":"Retail Goods"
        }
    ],
    "sg:phone":"+1 609 266 6998",
    "sg:postcode":"08203",
    "sg:province":"NJ",
    "sg:tags":[
        "collectible"
    ],
    "wof:name":"Yesterday's & Today's Treasure",
    "wof:placetype":"venue"
},
  "geometry": {"coordinates":[-74.397949,39.39422],"type":"Point"}
}