{
  "type": "Feature",
  "properties": {
    "addr:full":"517 Kearny Ave Kearny NJ 07032",
    "addr:housenumber":"517",
    "addr:postcode":"07032",
    "addr:street":"Kearny Ave",
    "iso:country":"US",
    "sg:address":"517 Kearny Ave",
    "sg:city":"Kearny",
    "sg:classifiers":[
        {
            "category":"Deli",
            "type":"Food & Drink"
        }
    ],
    "sg:phone":"+1 201 991 7707",
    "sg:postcode":"07032",
    "sg:province":"NJ",
    "wof:name":"Rita's Kitchen & Deli",
    "wof:placetype":"venue"
},
  "geometry": {"coordinates":[-74.146202,40.768799],"type":"Point"}
}