{
  "type": "Feature",
  "properties": {
    "addr:full":"1145 Loraine Ave Plainfield NJ 07062",
    "addr:housenumber":"1145",
    "addr:postcode":"07062",
    "addr:street":"Loraine Ave",
    "iso:country":"US",
    "sg:address":"1145 Loraine Ave",
    "sg:city":"Plainfield",
    "sg:classifiers":[
        {
            "category":"Organizations",
            "subcategory":"Professional Association",
            "type":"Services"
        }
    ],
    "sg:phone":"+1 908 757 4960",
    "sg:postcode":"07062",
    "sg:province":"NJ",
    "sg:tags":[
        "business"
    ],
    "wof:name":"North E Commerce Team Inc",
    "wof:placetype":"venue"
},
  "geometry": {"coordinates":[-74.39447,40.626443],"type":"Point"}
}