{
  "type": "Feature",
  "properties": {
    "iso:country":"US",
    "sg:address":"60 Temple St",
    "sg:city":"Paterson",
    "sg:classifiers":[
        {
            "category":"Social Services",
            "type":"Services"
        }
    ],
    "sg:phone":"+1 973 321 1264",
    "sg:postcode":"07522",
    "sg:province":"NJ",
    "sg:tags":[
        "government"
    ],
    "wof:name":"Paterson Youth Svc Bureau",
    "wof:placetype":"venue"
},
  "geometry": {"coordinates":[-74.17476499999999,40.924499],"type":"Point"}
}