{
  "type": "Feature",
  "properties": {
    "addr:full":"251 Steilen Ave Ridgewood NJ 07450",
    "addr:housenumber":"251",
    "addr:postcode":"07450",
    "addr:street":"Steilen Ave",
    "iso:country":"US",
    "sg:address":"251 Steilen Ave",
    "sg:city":"Ridgewood",
    "sg:classifiers":[
        {
            "category":"Manufacturing",
            "subcategory":"Printing",
            "type":"Manufacturing & Wholesale Goods"
        }
    ],
    "sg:phone":"+1 201 670 6756",
    "sg:postcode":"07450",
    "sg:province":"NJ",
    "sg:tags":[
        "cards",
        "greeting",
        "mfg"
    ],
    "wof:name":"Nuts & Olives Studio",
    "wof:placetype":"venue"
},
  "geometry": {"coordinates":[-74.09907200000001,40.981903],"type":"Point"}
}