{
  "type": "Feature",
  "properties": {
    "iso:country":"US",
    "sg:address":"244 Hasbrouck Ave",
    "sg:city":"Hasbrouck Heights",
    "sg:classifiers":[
        {
            "category":"Personal",
            "subcategory":"Barber",
            "type":"Services"
        }
    ],
    "sg:phone":"+1   ",
    "sg:postcode":"07604",
    "sg:province":"NJ",
    "sg:tags":[
        "shop"
    ],
    "wof:name":"Joes European Hair Stylist",
    "wof:placetype":"venue"
},
  "geometry": {"coordinates":[-74.06596500000001,40.86541],"type":"Point"}
}