{
  "type": "Feature",
  "properties": {
    "iso:country":"US",
    "sg:address":"321 Broad Ave",
    "sg:city":"Ridgefield",
    "sg:classifiers":[
        {
            "category":"Freight",
            "type":"Transportation"
        }
    ],
    "sg:phone":"+1 201 313 5009",
    "sg:postcode":"07657",
    "sg:province":"NJ",
    "sg:tags":[
        "shipping",
        "agent"
    ],
    "wof:name":"Asiana Express Svc Inc",
    "wof:placetype":"venue"
},
  "geometry": {"coordinates":[-74.009603,40.825646],"type":"Point"}
}