{
  "type": "Feature",
  "properties": {
    "addr:full":"11 Thornwood Dr Voorhees NJ 08043",
    "addr:housenumber":"11",
    "addr:postcode":"08043",
    "addr:street":"Thornwood Dr",
    "iso:country":"US",
    "sg:address":"11 Thornwood Dr",
    "sg:city":"Voorhees",
    "sg:classifiers":[
        {
            "category":"Professional",
            "subcategory":"Business Services",
            "type":"Services"
        }
    ],
    "sg:phone":"+1   ",
    "sg:postcode":"08043",
    "sg:province":"NJ",
    "wof:name":"Lomita Enterprises Inc",
    "wof:placetype":"venue"
},
  "geometry": {"coordinates":[-74.943679,39.840031],"type":"Point"}
}