{
  "type": "Feature",
  "properties": {
    "iso:country":"US",
    "sg:address":"57 S Washington Ave",
    "sg:city":"Bergenfield",
    "sg:classifiers":[
        {
            "category":"Personal",
            "subcategory":"Beauty Salon",
            "type":"Services"
        }
    ],
    "sg:phone":"+1   ",
    "sg:postcode":"07621",
    "sg:province":"NJ",
    "sg:tags":[
        "shop"
    ],
    "wof:name":"Evergreen Beauty Salon",
    "wof:placetype":"venue"
},
  "geometry": {"coordinates":[-73.996154,40.927792],"type":"Point"}
}