{
  "type": "Feature",
  "properties": {
    "iso:country":"US",
    "sg:address":"4410 Whalerman Rd",
    "sg:city":"Brigantine",
    "sg:classifiers":[
        {
            "category":"Food & Beverages",
            "subcategory":"Liquor & Beverages",
            "type":"Retail Goods"
        }
    ],
    "sg:phone":"+1   ",
    "sg:postcode":"08203",
    "sg:province":"NJ",
    "sg:tags":[
        "alcoholic"
    ],
    "wof:name":"Makays Buy Rite",
    "wof:placetype":"venue"
},
  "geometry": {"coordinates":[-74.39917,39.389999],"type":"Point"}
}