{
  "type": "Feature",
  "properties": {
    "addr:full":"187 Crosswicks Chesterfield Rd Chesterfield NJ 08515",
    "addr:housenumber":"187",
    "addr:postcode":"08515",
    "addr:street":"Crosswicks Chesterfield Rd",
    "iso:country":"US",
    "sg:address":"187 Crosswicks Chesterfield Rd",
    "sg:city":"Chesterfield",
    "sg:classifiers":[
        {
            "category":"Place Of Worship",
            "subcategory":"Church",
            "type":"Public Place"
        },
        {
            "category":"Place Of Worship",
            "type":"Public Place"
        }
    ],
    "sg:phone":"+1 609 298 1244",
    "sg:postcode":"08515",
    "sg:province":"NJ",
    "sg:tags":[
        "churches-interdenominational",
        "churches-various",
        "denomination"
    ],
    "wof:name":"Camp Shadyrest",
    "wof:placetype":"venue"
},
  "geometry": {"coordinates":[-74.641524,40.120119],"type":"Point"}
}