{
  "type": "Feature",
  "properties": {
    "addr:full":"131 Hudson Ave Keansburg NJ 07734",
    "addr:housenumber":"131",
    "addr:postcode":"07734",
    "addr:street":"Hudson Ave",
    "iso:country":"US",
    "sg:address":"131 Hudson Ave",
    "sg:city":"Keansburg",
    "sg:classifiers":[
        {
            "category":"Shopping",
            "subcategory":"Pharmacy",
            "type":"Retail Goods"
        }
    ],
    "sg:phone":"+1 732 495 0181",
    "sg:postcode":"07734",
    "sg:province":"NJ",
    "sg:tags":[
        "pharmaceutical",
        "consultant"
    ],
    "wof:name":"Donovan & Assoc",
    "wof:placetype":"venue"
},
  "geometry": {"coordinates":[-74.134511,40.430707],"type":"Point"}
}