{
  "type": "Feature",
  "properties": {
    "iso:country":"US",
    "sg:address":"2003 Lincoln Dr W",
    "sg:city":"Marlton",
    "sg:classifiers":[
        {
            "category":"Insurance",
            "subcategory":"Insurance Agent",
            "type":"Services"
        }
    ],
    "sg:phone":"+1 856 985 9172",
    "sg:postcode":"08053",
    "sg:province":"NJ",
    "sg:website":"www.kciinsurance.com",
    "wof:name":"Kaytes Cooperman Insurance",
    "wof:placetype":"venue"
},
  "geometry": {"coordinates":[-74.943186,39.910868],"type":"Point"}
}