{
  "type": "Feature",
  "properties": {
    "addr:full":"4 Glen Rd Parsippany NJ 07054",
    "addr:housenumber":"4",
    "addr:postcode":"07054",
    "addr:street":"Glen Rd",
    "iso:country":"US",
    "sg:address":"4 Glen Rd",
    "sg:city":"Parsippany",
    "sg:classifiers":[
        {
            "category":"Shopping",
            "subcategory":"Computers & Home Electronics",
            "type":"Retail Goods"
        }
    ],
    "sg:phone":"+1 973 361 6464",
    "sg:postcode":"07054",
    "sg:province":"NJ",
    "sg:tags":[
        "equipment",
        "dealer"
    ],
    "wof:name":"Rex Computer Svc",
    "wof:placetype":"venue"
},
  "geometry": {"coordinates":[-74.430317,40.87985],"type":"Point"}
}