{
  "type": "Feature",
  "properties": {
    "iso:country":"US",
    "sg:address":"30 Laurel Rd E",
    "sg:city":"Stratford",
    "sg:classifiers":[
        {
            "category":"Health Services",
            "subcategory":"Clinic",
            "type":"Services"
        }
    ],
    "sg:phone":"+1 856 784 1976",
    "sg:postcode":"08084",
    "sg:province":"NJ",
    "sg:tags":[
        "specialty",
        "legal",
        "outpatient"
    ],
    "wof:name":"Magnetic Imaging At Kennedy",
    "wof:placetype":"venue"
},
  "geometry": {"coordinates":[-75.008922,39.828431],"type":"Point"}
}