{
  "type": "Feature",
  "properties": {
    "iso:country":"US",
    "sg:address":"1 Imbrie Pl",
    "sg:city":"Sea Bright",
    "sg:classifiers":[
        {
            "category":"Retail",
            "subcategory":"Portrait Studio",
            "type":"Services"
        }
    ],
    "sg:phone":"+1 732 530 5045",
    "sg:postcode":"07760",
    "sg:province":"NJ",
    "sg:tags":[
        "photographer"
    ],
    "sg:website":"www.elizabethmariephoto.com",
    "wof:name":"Elizabeth Marie Photography",
    "wof:placetype":"venue"
},
  "geometry": {"coordinates":[-73.975774,40.350085],"type":"Point"}
}