{
  "type": "Feature",
  "properties": {
    "iso:country":"US",
    "sg:address":"1413 Arctic Ave",
    "sg:city":"Atlantic City",
    "sg:classifiers":[
        {
            "category":"Personal",
            "subcategory":"Barber",
            "type":"Services"
        }
    ],
    "sg:phone":"+1 609 340 0067",
    "sg:postcode":"08401",
    "sg:province":"NJ",
    "sg:tags":[
        "shop"
    ],
    "wof:name":"Can You Dig It",
    "wof:placetype":"venue"
},
  "geometry": {"coordinates":[-74.429903,39.363403],"type":"Point"}
}