{
  "type": "Feature",
  "properties": {
    "iso:country":"US",
    "sg:address":"1719 State Rt 10 Ste 127",
    "sg:city":"Parsippany",
    "sg:classifiers":[
        {
            "category":"Education",
            "subcategory":"Special Training",
            "type":"Public Place"
        }
    ],
    "sg:phone":"+1 973 387 2444",
    "sg:postcode":"07054",
    "sg:province":"NJ",
    "sg:tags":[
        "school",
        "specialty"
    ],
    "wof:name":"John Robert Powers",
    "wof:placetype":"venue"
},
  "geometry": {"coordinates":[-74.45850299999999,40.841546],"type":"Point"}
}