{
  "type": "Feature",
  "properties": {
    "iso:country":"US",
    "sg:address":"999 Moessner Ave",
    "sg:city":"Union",
    "sg:classifiers":[
        {
            "category":"Professional",
            "type":"Services"
        }
    ],
    "sg:phone":"+1 908 810 7360",
    "sg:postcode":"07083",
    "sg:province":"NJ",
    "sg:tags":[
        "establishment"
    ],
    "wof:name":"Allaire Urban Karzan",
    "wof:placetype":"venue"
},
  "geometry": {"coordinates":[-74.297794,40.703036],"type":"Point"}
}