{
  "type": "Feature",
  "properties": {
    "addr:full":"50 Kulick Rd Fairfield NJ 07004",
    "addr:housenumber":"50",
    "addr:postcode":"07004",
    "addr:street":"Kulick Rd",
    "iso:country":"US",
    "sg:address":"50 Kulick Rd",
    "sg:city":"Fairfield",
    "sg:classifiers":[
        {
            "category":"Professional",
            "type":"Services"
        }
    ],
    "sg:phone":"+1 973 276 0235",
    "sg:postcode":"07004",
    "sg:province":"NJ",
    "sg:tags":[
        "establishment"
    ],
    "wof:name":"LOCAL-Isp",
    "wof:placetype":"venue"
},
  "geometry": {"coordinates":[-74.29239099999999,40.870948],"type":"Point"}
}