{
  "type": "Feature",
  "properties": {
    "iso:country":"US",
    "sg:address":"445 Madison St",
    "sg:city":"Carlstadt",
    "sg:classifiers":[
        {
            "category":"Building & Trades",
            "subcategory":"Construction",
            "type":"Services"
        }
    ],
    "sg:phone":"+1 201 933 9789",
    "sg:postcode":"07072",
    "sg:province":"NJ",
    "sg:tags":[
        "painter"
    ],
    "wof:name":"Peter Van Herk",
    "wof:placetype":"venue"
},
  "geometry": {"coordinates":[-74.095164,40.840427],"type":"Point"}
}