{
  "type": "Feature",
  "properties": {
    "addr:full":"271 Main St Gladstone NJ 07934",
    "addr:housenumber":"271",
    "addr:postcode":"07934",
    "addr:street":"Main St",
    "iso:country":"US",
    "sg:address":"271 Main St",
    "sg:city":"Gladstone",
    "sg:classifiers":[
        {
            "category":"Restaurant",
            "type":"Food & Drink"
        }
    ],
    "sg:phone":"+1 908 719 3321",
    "sg:postcode":"07934",
    "sg:province":"NJ",
    "sg:tags":[
        "delicatessen"
    ],
    "wof:name":"Cait's Corner Deli",
    "wof:placetype":"venue"
},
  "geometry": {"coordinates":[-74.664962,40.71957],"type":"Point"}
}