{
  "type": "Feature",
  "properties": {
    "addr:full":"550 US Hwy 206 Bedminster NJ 07921",
    "addr:housenumber":"550",
    "addr:postcode":"07921",
    "addr:street":"Us Hwy 206",
    "iso:country":"US",
    "sg:address":"550 US Hwy 206",
    "sg:city":"Bedminster",
    "sg:classifiers":[
        {
            "category":"Professional",
            "subcategory":"Computer Services",
            "type":"Services"
        }
    ],
    "sg:phone":"+1   ",
    "sg:postcode":"07921",
    "sg:province":"NJ",
    "sg:tags":[
        "datum"
    ],
    "wof:name":"EDS",
    "wof:placetype":"venue"
},
  "geometry": {"coordinates":[-74.643828,40.653532],"type":"Point"}
}