{
  "type": "Feature",
  "properties": {
    "addr:full":"48 Briarcliff Rd Mountain Lakes NJ 07046",
    "addr:housenumber":"48",
    "addr:postcode":"07046",
    "addr:street":"Briarcliff Rd",
    "iso:country":"US",
    "sg:address":"48 Briarcliff Rd",
    "sg:city":"Mountain Lakes",
    "sg:classifiers":[
        {
            "category":"Organizations",
            "subcategory":"Religious Organization",
            "type":"Services"
        }
    ],
    "sg:phone":"+1 973 334 6500",
    "sg:postcode":"07046",
    "sg:province":"NJ",
    "sg:tags":[
        "church"
    ],
    "sg:website":"www.mlucc.org",
    "wof:name":"Community Church",
    "wof:placetype":"venue"
},
  "geometry": {"coordinates":[-74.435759,40.892732],"type":"Point"}
}