{
  "type": "Feature",
  "properties": {
    "addr:full":"701 Black Horse Pike Pleasantville NJ 08232",
    "addr:housenumber":"701",
    "addr:postcode":"08232",
    "addr:street":"Black Horse Pike",
    "iso:country":"US",
    "sg:address":"701 Black Horse Pike",
    "sg:city":"Pleasantville",
    "sg:classifiers":[
        {
            "category":"Restaurant",
            "type":"Food & Drink"
        },
        {
            "category":"Bars & Pubs",
            "type":"Food & Drink"
        }
    ],
    "sg:phone":"+1 609 407 2121",
    "sg:postcode":"08232",
    "sg:province":"NJ",
    "sg:tags":[
        "drinking",
        "eating"
    ],
    "wof:name":"Shogun Japanese Korean Restaur",
    "wof:placetype":"venue"
},
  "geometry": {"coordinates":[-74.539839,39.393872],"type":"Point"}
}