{
  "type": "Feature",
  "properties": {
    "iso:country":"US",
    "sg:address":"478 Lanza Ave",
    "sg:city":"Garfield",
    "sg:classifiers":[
        {
            "category":"Building & Trades",
            "subcategory":"Cleaning & Sanitation",
            "type":"Services"
        }
    ],
    "sg:phone":"+1 201 210 8038",
    "sg:postcode":"07026",
    "sg:province":"NJ",
    "sg:tags":[
        "carpet"
    ],
    "wof:name":"Superior Carpet & Upholstery Cleaning",
    "wof:placetype":"venue"
},
  "geometry": {"coordinates":[-74.10578700000001,40.890217],"type":"Point"}
}