{
  "type": "Feature",
  "properties": {
    "addr:full":"288 Hasbrouck Ave Hasbrouck Heights NJ 07604",
    "addr:housenumber":"288",
    "addr:postcode":"07604",
    "addr:street":"Hasbrouck Ave",
    "iso:country":"US",
    "sg:address":"288 Hasbrouck Ave",
    "sg:city":"Hasbrouck Heights",
    "sg:classifiers":[
        {
            "category":"Health Services",
            "subcategory":"Clinic",
            "type":"Services"
        }
    ],
    "sg:phone":"+1 201 288 4171",
    "sg:postcode":"07604",
    "sg:province":"NJ",
    "wof:name":"Balance Therapeutic Bodywork",
    "wof:placetype":"venue"
},
  "geometry": {"coordinates":[-74.06628499999999,40.865183],"type":"Point"}
}