{
  "type": "Feature",
  "properties": {
    "addr:full":"76 Bowne Station Rd Stockton NJ 08559",
    "addr:housenumber":"76",
    "addr:postcode":"08559",
    "addr:street":"Bowne Station Rd",
    "iso:country":"US",
    "sg:address":"76 Bowne Station Rd",
    "sg:city":"Stockton",
    "sg:classifiers":[
        {
            "category":"Professional",
            "subcategory":"Lawyer & Legal Services",
            "type":"Services"
        }
    ],
    "sg:phone":"+1 609 773 0900",
    "sg:postcode":"08559",
    "sg:province":"NJ",
    "wof:name":"Tl Gombar",
    "wof:placetype":"venue"
},
  "geometry": {"coordinates":[-74.915289,40.423451],"type":"Point"}
}