{
  "type": "Feature",
  "properties": {
    "iso:country":"US",
    "sg:address":"2083 Lawrenceville Rd",
    "sg:city":"Lawrenceville",
    "sg:classifiers":[
        {
            "category":"Education",
            "subcategory":"Special Training",
            "type":"Public Place"
        }
    ],
    "sg:phone":"+1 609 896 5381",
    "sg:postcode":"08648",
    "sg:province":"NJ",
    "sg:tags":[
        "educational"
    ],
    "wof:name":"Educational Opportunity Prgm",
    "wof:placetype":"venue"
},
  "geometry": {"coordinates":[-74.732687,40.27697],"type":"Point"}
}