{
  "type": "Feature",
  "properties": {
    "addr:full":"106 Washington St Hoboken NJ 07030",
    "addr:housenumber":"106",
    "addr:postcode":"07030",
    "addr:street":"Washington St",
    "iso:country":"US",
    "sg:address":"106 Washington St",
    "sg:city":"Hoboken",
    "sg:classifiers":[
        {
            "category":"Utilities",
            "subcategory":"Mobile Phone",
            "type":"Services"
        }
    ],
    "sg:phone":"+1 201 533 2372",
    "sg:postcode":"07030",
    "sg:province":"NJ",
    "sg:tags":[
        "telephone",
        "cellular"
    ],
    "wof:name":"Cingular Wireless",
    "wof:placetype":"venue"
},
  "geometry": {"coordinates":[-74.030603,40.738656],"type":"Point"}
}