{
  "type": "Feature",
  "properties": {
    "addr:full":"90 Woodbridge Center Dr Woodbridge NJ 07095",
    "addr:housenumber":"90",
    "addr:postcode":"07095",
    "addr:street":"Woodbridge Center Dr",
    "iso:country":"US",
    "sg:address":"90 Woodbridge Center Dr",
    "sg:city":"Woodbridge",
    "sg:classifiers":[
        {
            "category":"Real Estate",
            "subcategory":"Real Estate Services",
            "type":"Services"
        }
    ],
    "sg:phone":"+1 732 634 2200",
    "sg:postcode":"07095",
    "sg:province":"NJ",
    "sg:tags":[
        "company",
        "title"
    ],
    "wof:name":"Edison Education Foundation",
    "wof:placetype":"venue"
},
  "geometry": {"coordinates":[-74.298024,40.549953],"type":"Point"}
}