{
  "type": "Feature",
  "properties": {
    "iso:country":"US",
    "sg:address":"205 N 14th St",
    "sg:city":"Kenilworth",
    "sg:classifiers":[
        {
            "category":"Retail",
            "subcategory":"Laundry & Dry Cleaning",
            "type":"Services"
        }
    ],
    "sg:phone":"+1 908 620 3600",
    "sg:postcode":"07033",
    "sg:province":"NJ",
    "sg:tags":[
        "cleaners",
        "rug",
        "carpet"
    ],
    "wof:name":"Affordable Chem Dry",
    "wof:placetype":"venue"
},
  "geometry": {"coordinates":[-74.29844799999999,40.680321],"type":"Point"}
}