{
  "type": "Feature",
  "properties": {
    "iso:country":"US",
    "sg:address":"4 Beech St",
    "sg:city":"North Arlington",
    "sg:classifiers":[
        {
            "category":"Building & Trades",
            "subcategory":"Construction",
            "type":"Services"
        }
    ],
    "sg:phone":"+1 201 997 1923",
    "sg:postcode":"07031",
    "sg:province":"NJ",
    "sg:tags":[
        "contractor"
    ],
    "wof:name":"Russos Seamless Gutters",
    "wof:placetype":"venue"
},
  "geometry": {"coordinates":[-74.133668,40.780608],"type":"Point"}
}