{
  "type": "Feature",
  "properties": {
    "addr:full":"275 Tremont Ave Fort Lee NJ 07024",
    "addr:housenumber":"275",
    "addr:postcode":"07024",
    "addr:street":"Tremont Ave",
    "iso:country":"US",
    "sg:address":"275 Tremont Ave",
    "sg:city":"Fort Lee",
    "sg:classifiers":[
        {
            "category":"Food & Beverages",
            "subcategory":"Specialty",
            "type":"Retail Goods"
        }
    ],
    "sg:phone":"+1 201 944 4414",
    "sg:postcode":"07024",
    "sg:province":"NJ",
    "wof:name":"Miamax",
    "wof:placetype":"venue"
},
  "geometry": {"coordinates":[-73.975185,40.845049],"type":"Point"}
}