{
  "type": "Feature",
  "properties": {
    "iso:country":"US",
    "sg:address":"200 Fairfield Rd",
    "sg:city":"Fairfield",
    "sg:classifiers":[
        {
            "category":"Social Services",
            "subcategory":"Child Care",
            "type":"Services"
        }
    ],
    "sg:phone":"+1 973 808 6811",
    "sg:postcode":"07004",
    "sg:province":"NJ",
    "wof:name":"Discovery Kids",
    "wof:placetype":"venue"
},
  "geometry": {"coordinates":[-74.292411,40.878365],"type":"Point"}
}