{
  "type": "Feature",
  "properties": {
    "addr:full":"900 4th Ave Asbury Park NJ 07712",
    "addr:housenumber":"900",
    "addr:postcode":"07712",
    "addr:street":"4Th Ave Asbury",
    "iso:country":"US",
    "sg:address":"900 4th Ave",
    "sg:city":"Asbury Park",
    "sg:classifiers":[
        {
            "category":"Building & Trades",
            "subcategory":"Plumbing",
            "type":"Services"
        }
    ],
    "sg:phone":"+1 732 775 3193",
    "sg:postcode":"07712",
    "sg:province":"NJ",
    "sg:tags":[
        "plumbing",
        "contractor"
    ],
    "wof:name":"William R Hogg Co",
    "wof:placetype":"venue"
},
  "geometry": {"coordinates":[-74.013199,40.22522],"type":"Point"}
}