{
  "type": "Feature",
  "properties": {
    "iso:country":"US",
    "sg:address":"198 Montgomery St",
    "sg:city":"Paterson",
    "sg:classifiers":[
        {
            "category":"Professional",
            "type":"Services"
        }
    ],
    "sg:phone":"+1   ",
    "sg:postcode":"07501",
    "sg:province":"NJ",
    "wof:name":"Kellys Repair",
    "wof:placetype":"venue"
},
  "geometry": {"coordinates":[-74.157977,40.924689],"type":"Point"}
}