{
  "type": "Feature",
  "properties": {
    "iso:country":"US",
    "sg:address":"725 Raritan Ave",
    "sg:city":"Atco",
    "sg:classifiers":[
        {
            "category":"Shopping",
            "subcategory":"Pets & Pet Supplies",
            "type":"Retail Goods"
        }
    ],
    "sg:phone":"+1 856 767 3180",
    "sg:postcode":"08004",
    "sg:province":"NJ",
    "sg:tags":[
        "training"
    ],
    "sg:website":"www.cnidogtraining.com",
    "wof:name":"C N L Dog Training",
    "wof:placetype":"venue"
},
  "geometry": {"coordinates":[-74.857399,39.765099],"type":"Point"}
}