{
  "type": "Feature",
  "properties": {
    "iso:country":"US",
    "sg:address":"430 Bridge Plaza Dr",
    "sg:city":"Englishtown",
    "sg:classifiers":[
        {
            "category":"Health Services",
            "subcategory":"Doctor",
            "type":"Services"
        }
    ],
    "sg:phone":"+1 732 617 2830",
    "sg:postcode":"07726",
    "sg:province":"NJ",
    "sg:tags":[
        "dentist"
    ],
    "wof:name":"Advanced Dental Ctr",
    "wof:placetype":"venue"
},
  "geometry": {"coordinates":[-74.31950999999999,40.336694],"type":"Point"}
}