{
  "type": "Feature",
  "properties": {
    "addr:full":"73 Mary St Paterson NJ 07503",
    "addr:housenumber":"73",
    "addr:postcode":"07503",
    "addr:street":"Mary St",
    "iso:country":"US",
    "sg:address":"73 Mary St",
    "sg:city":"Paterson",
    "sg:classifiers":[
        {
            "category":"Food & Beverages",
            "subcategory":"Groceries & Convenience Stores",
            "type":"Retail Goods"
        }
    ],
    "sg:phone":"+1 973 569 4334",
    "sg:postcode":"07503",
    "sg:province":"NJ",
    "wof:name":"Mary's Grocery",
    "wof:placetype":"venue"
},
  "geometry": {"coordinates":[-74.168098,40.903],"type":"Point"}
}