{
  "type": "Feature",
  "properties": {
    "addr:full":"210 Haddon Ave Collingswood NJ 08108",
    "addr:housenumber":"210",
    "addr:postcode":"08108",
    "addr:street":"Haddon Ave",
    "iso:country":"US",
    "sg:address":"210 Haddon Ave",
    "sg:city":"Collingswood",
    "sg:classifiers":[
        {
            "category":"Professional",
            "subcategory":"Business Services",
            "type":"Services"
        }
    ],
    "sg:phone":"+1 856 869 3200",
    "sg:postcode":"08108",
    "sg:province":"NJ",
    "sg:tags":[
        "automobile",
        "appraiser"
    ],
    "wof:name":"Liberty Insurance Appraisers",
    "wof:placetype":"venue"
},
  "geometry": {"coordinates":[-75.082725,39.920809],"type":"Point"}
}