{
  "type": "Feature",
  "properties": {
    "addr:full":"104 Watchung Ave Montclair NJ 07043",
    "addr:housenumber":"104",
    "addr:postcode":"07043",
    "addr:street":"Watchung Ave",
    "iso:country":"US",
    "sg:address":"104 Watchung Ave",
    "sg:city":"Montclair",
    "sg:classifiers":[
        {
            "category":"Education",
            "subcategory":"Special Training",
            "type":"Public Place"
        },
        {
            "category":"Arts & Performance",
            "subcategory":"Theater",
            "type":"Entertainment"
        }
    ],
    "sg:phone":"+1 973 783 4330",
    "sg:postcode":"07043",
    "sg:province":"NJ",
    "sg:tags":[
        "instrument",
        "teacher",
        "orchestra",
        "musical",
        "band"
    ],
    "sg:website":"www.montclairmusic.com",
    "wof:name":"Montclair Music Studio",
    "wof:placetype":"venue"
},
  "geometry": {"coordinates":[-74.20729799999999,40.8307],"type":"Point"}
}