{
  "type": "Feature",
  "properties": {
    "iso:country":"US",
    "sg:address":"12 Brookrun Rd",
    "sg:city":"Mount Holly",
    "sg:classifiers":[
        {
            "category":"Building & Trades",
            "subcategory":"Electrical",
            "type":"Services"
        }
    ],
    "sg:phone":"+1 609 261 3405",
    "sg:postcode":"08060",
    "sg:province":"NJ",
    "sg:tags":[
        "electrical",
        "contractor"
    ],
    "wof:name":"T B Kelly Electric Inc",
    "wof:placetype":"venue"
},
  "geometry": {"coordinates":[-74.76964599999999,39.999133],"type":"Point"}
}