{
  "type": "Feature",
  "properties": {
    "addr:full":"35 Woodport Rd Sparta NJ 07871",
    "addr:housenumber":"35",
    "addr:postcode":"07871",
    "addr:street":"Woodport Rd",
    "iso:country":"US",
    "sg:address":"35 Woodport Rd",
    "sg:city":"Sparta",
    "sg:classifiers":[
        {
            "category":"Manufacturing",
            "subcategory":"Metals",
            "type":"Manufacturing & Wholesale Goods"
        },
        {
            "category":"Building & Trades",
            "subcategory":"Construction",
            "type":"Services"
        }
    ],
    "sg:phone":"+1 973 729 3460",
    "sg:postcode":"07871",
    "sg:province":"NJ",
    "sg:tags":[
        "steel",
        "fabricator",
        "erectors",
        "structural"
    ],
    "wof:name":"Sparta Steel Corporation",
    "wof:placetype":"venue"
},
  "geometry": {"coordinates":[-74.637827,41.033866],"type":"Point"}
}