{
  "type": "Feature",
  "properties": {
    "addr:full":"62 Roosevelt St South River NJ 08882",
    "addr:housenumber":"62",
    "addr:postcode":"08882",
    "addr:street":"Roosevelt St",
    "iso:country":"US",
    "sg:address":"62 Roosevelt St",
    "sg:city":"South River",
    "sg:classifiers":[
        {
            "category":"Building & Trades",
            "subcategory":"Landscaping Services",
            "type":"Services"
        }
    ],
    "sg:phone":"+1 732 651 7906",
    "sg:postcode":"08882",
    "sg:province":"NJ",
    "wof:name":"Jubas Lawn Service Inc",
    "wof:placetype":"venue"
},
  "geometry": {"coordinates":[-74.386101,40.443526],"type":"Point"}
}