{
  "type": "Feature",
  "properties": {
    "iso:country":"US",
    "sg:address":"356 Millburn Avenue",
    "sg:city":"Millburn",
    "sg:classifiers":[
        {
            "category":"Insurance",
            "subcategory":"Health Insurance",
            "type":"Services"
        }
    ],
    "sg:phone":"+1 973 218 6769",
    "sg:postcode":"07041",
    "sg:province":"NJ",
    "sg:tags":[
        "market"
    ],
    "sg:website":"www.teatogether.com",
    "wof:name":"Tea Together",
    "wof:placetype":"venue"
},
  "geometry": {"coordinates":[-74.30792700000001,40.723374],"type":"Point"}
}