{
  "type": "Feature",
  "properties": {
    "iso:country":"US",
    "sg:address":"2152 S Delsea Dr",
    "sg:city":"Vineland",
    "sg:classifiers":[
        {
            "category":"Autos & Motor Vehicles",
            "subcategory":"Automobile Sales",
            "type":"Retail Goods"
        }
    ],
    "sg:phone":"+1   ",
    "sg:postcode":"08360",
    "sg:province":"NJ",
    "sg:tags":[
        "used"
    ],
    "wof:name":"Blue Diamond Auto Sales",
    "wof:placetype":"venue"
},
  "geometry": {"coordinates":[-75.043301,39.458196],"type":"Point"}
}