{
  "type": "Feature",
  "properties": {
    "iso:country":"US",
    "sg:address":"332 S Black Horse Pike",
    "sg:city":"Williamstown",
    "sg:classifiers":[
        {
            "category":"Food & Beverages",
            "subcategory":"Groceries & Convenience Stores",
            "type":"Retail Goods"
        }
    ],
    "sg:phone":"+1 856 629 1325",
    "sg:postcode":"08094",
    "sg:province":"NJ",
    "wof:name":"Wawa Food Market",
    "wof:placetype":"venue"
},
  "geometry": {"coordinates":[-74.98891999999999,39.685623],"type":"Point"}
}