{
  "type": "Feature",
  "properties": {
    "iso:country":"US",
    "sg:address":"18 Willow Dr",
    "sg:city":"Asbury Park",
    "sg:classifiers":[
        {
            "category":"Freight",
            "type":"Transportation"
        }
    ],
    "sg:phone":"+1 732 493 9532",
    "sg:postcode":"07712",
    "sg:province":"NJ",
    "sg:tags":[
        "operator",
        "local",
        "trucking"
    ],
    "wof:name":"CHR Delivery Service",
    "wof:placetype":"venue"
},
  "geometry": {"coordinates":[-74.040695,40.254409],"type":"Point"}
}