{
  "type": "Feature",
  "properties": {
    "addr:full":"245 Livingston St Northvale NJ 07647",
    "addr:housenumber":"245",
    "addr:postcode":"07647",
    "addr:street":"Livingston St",
    "iso:country":"US",
    "sg:address":"245 Livingston St",
    "sg:city":"Northvale",
    "sg:classifiers":[
        {
            "category":"Manufacturing",
            "subcategory":"Rubber & Plastics",
            "type":"Manufacturing & Wholesale Goods"
        }
    ],
    "sg:phone":"+1 201 750 1680",
    "sg:postcode":"07647",
    "sg:province":"NJ",
    "sg:tags":[
        "manufacture",
        "product",
        "toy",
        "other"
    ],
    "wof:name":"Progard",
    "wof:placetype":"venue"
},
  "geometry": {"coordinates":[-73.946162,41.012972],"type":"Point"}
}