{
  "type": "Feature",
  "properties": {
    "addr:full":"22 Joyce Kilmer Ave New Brunswick NJ 08901",
    "addr:housenumber":"22",
    "addr:postcode":"08901",
    "addr:street":"Joyce Kilmer Ave",
    "iso:country":"US",
    "sg:address":"22 Joyce Kilmer Ave",
    "sg:city":"New Brunswick",
    "sg:classifiers":[
        {
            "category":"Organizations",
            "subcategory":"Religious Organization",
            "type":"Services"
        }
    ],
    "sg:phone":"+1 732 247 0384",
    "sg:postcode":"08901",
    "sg:province":"NJ",
    "sg:tags":[
        "church"
    ],
    "wof:name":"Bayard Street Presbyterian Chr",
    "wof:placetype":"venue"
},
  "geometry": {"coordinates":[-74.448437,40.49198],"type":"Point"}
}