{
  "type": "Feature",
  "properties": {
    "iso:country":"US",
    "sg:address":"2000 State Rte 27",
    "sg:city":"North Brunswick",
    "sg:classifiers":[
        {
            "category":"Sports & Exercise",
            "subcategory":"Gym",
            "type":"Entertainment"
        }
    ],
    "sg:phone":"+1 732 422 7100",
    "sg:postcode":"08902",
    "sg:province":"NJ",
    "sg:tags":[
        "club",
        "health",
        "studio",
        "gymnasium"
    ],
    "wof:name":"Contours Fitness",
    "wof:placetype":"venue"
},
  "geometry": {"coordinates":[-74.50954299999999,40.459275],"type":"Point"}
}