{
  "type": "Feature",
  "properties": {
    "addr:full":"2 Hackensack Ave Kearny NJ 07032",
    "addr:housenumber":"2",
    "addr:postcode":"07032",
    "addr:street":"Hackensack Ave",
    "iso:country":"US",
    "sg:address":"2 Hackensack Ave",
    "sg:city":"Kearny",
    "sg:classifiers":[
        {
            "category":"Real Estate",
            "subcategory":"Real Estate Agent",
            "type":"Services"
        }
    ],
    "sg:phone":"+1   ",
    "sg:postcode":"07032",
    "sg:province":"NJ",
    "wof:name":"S & R Realty Associates Inc",
    "wof:placetype":"venue"
},
  "geometry": {"coordinates":[-74.11125800000001,40.72565],"type":"Point"}
}