{
  "type": "Feature",
  "properties": {
    "addr:full":"1505 Blackwood Clementon Rd Blackwood NJ 08012",
    "addr:housenumber":"1505",
    "addr:postcode":"08012",
    "addr:street":"Blackwood Clementon Rd",
    "iso:country":"US",
    "sg:address":"1505 Blackwood Clementon Rd",
    "sg:city":"Blackwood",
    "sg:classifiers":[
        {
            "category":"Restaurant",
            "type":"Food & Drink"
        }
    ],
    "sg:phone":"+1 856 227 7123",
    "sg:postcode":"08012",
    "sg:province":"NJ",
    "wof:name":"Mc Donald's",
    "wof:placetype":"venue"
},
  "geometry": {"coordinates":[-75.044845,39.803204],"type":"Point"}
}