{
  "type": "Feature",
  "properties": {
    "addr:full":"270 Foothill Rd Bridgewater NJ 08807",
    "addr:housenumber":"270",
    "addr:postcode":"08807",
    "addr:street":"Foothill Rd",
    "iso:country":"US",
    "sg:address":"270 Foothill Rd",
    "sg:city":"Bridgewater",
    "sg:classifiers":[
        {
            "category":"Professional",
            "subcategory":"Business Services",
            "type":"Services"
        }
    ],
    "sg:phone":"+1   ",
    "sg:postcode":"08807",
    "sg:province":"NJ",
    "sg:tags":[
        "coffee"
    ],
    "wof:name":"Day Starter Coffee Service",
    "wof:placetype":"venue"
},
  "geometry": {"coordinates":[-74.57064099999999,40.572331],"type":"Point"}
}