{
  "type": "Feature",
  "properties": {
    "addr:full":"12 Waverly Pl Madison NJ 07940",
    "addr:housenumber":"12",
    "addr:postcode":"07940",
    "addr:street":"Waverly Pl",
    "iso:country":"US",
    "sg:address":"12 Waverly Pl",
    "sg:city":"Madison",
    "sg:classifiers":[
        {
            "category":"Shopping",
            "subcategory":"Gifts & Souvenirs",
            "type":"Retail Goods"
        }
    ],
    "sg:phone":"+1 973 410 1444",
    "sg:postcode":"07940",
    "sg:province":"NJ",
    "sg:tags":[
        "basket",
        "parcel"
    ],
    "wof:name":"Old Treasure Chest Co",
    "wof:placetype":"venue"
},
  "geometry": {"coordinates":[-74.415212,40.758259],"type":"Point"}
}