{
  "type": "Feature",
  "properties": {
    "addr:full":"373 Elizabeth Ave Somerset NJ 08873",
    "addr:housenumber":"373",
    "addr:postcode":"08873",
    "addr:street":"Elizabeth Ave",
    "iso:country":"US",
    "sg:address":"373 Elizabeth Ave",
    "sg:city":"Somerset",
    "sg:classifiers":[
        {
            "category":"Wholesale",
            "subcategory":"Machinery & Supplies",
            "type":"Manufacturing & Wholesale Goods"
        }
    ],
    "sg:phone":"+1 732 873 8668",
    "sg:postcode":"08873",
    "sg:province":"NJ",
    "sg:tags":[
        "generator"
    ],
    "sg:website":"http://www.nrfisher.com",
    "wof:name":"Norman Ray Fisher Electric Inc",
    "wof:placetype":"venue"
},
  "geometry": {"coordinates":[-74.535751,40.540401],"type":"Point"}
}