{
  "type": "Feature",
  "properties": {
    "addr:full":"19 Grant Ave Dumont NJ 07628",
    "addr:housenumber":"19",
    "addr:postcode":"07628",
    "addr:street":"Grant Ave",
    "iso:country":"US",
    "sg:address":"19 Grant Ave",
    "sg:city":"Dumont",
    "sg:classifiers":[
        {
            "category":"Personal",
            "subcategory":"Barber",
            "type":"Services"
        }
    ],
    "sg:phone":"+1 201 385 8683",
    "sg:postcode":"07628",
    "sg:province":"NJ",
    "sg:tags":[
        "shop"
    ],
    "wof:name":"Style N Trim",
    "wof:placetype":"venue"
},
  "geometry": {"coordinates":[-73.987594,40.948668],"type":"Point"}
}