{
  "type": "Feature",
  "properties": {
    "iso:country":"US",
    "sg:address":"217 Burlington Ave",
    "sg:city":"Delanco",
    "sg:classifiers":[
        {
            "category":"Real Estate",
            "subcategory":"Real Estate Agent",
            "type":"Services"
        }
    ],
    "sg:phone":"+1 856 461 1300",
    "sg:postcode":"08075",
    "sg:province":"NJ",
    "sg:website":"www.rossirealty.com",
    "wof:name":"Shirley M Rossi Realty Inc",
    "wof:placetype":"venue"
},
  "geometry": {"coordinates":[-74.95814900000001,40.045752],"type":"Point"}
}