{
  "type": "Feature",
  "properties": {
    "iso:country":"US",
    "sg:address":"121 Watchung Ave",
    "sg:city":"Plainfield",
    "sg:classifiers":[
        {
            "category":"Personal",
            "subcategory":"Beauty Salon",
            "type":"Services"
        }
    ],
    "sg:phone":"+1 908 754 4247",
    "sg:postcode":"07060",
    "sg:province":"NJ",
    "sg:tags":[
        "culture",
        "school"
    ],
    "wof:name":"Reignbow Beauty Academy Inc",
    "wof:placetype":"venue"
},
  "geometry": {"coordinates":[-74.426492,40.622403],"type":"Point"}
}