{
  "type": "Feature",
  "properties": {
    "iso:country":"US",
    "sg:address":"51 14th St",
    "sg:city":"Hoboken",
    "sg:classifiers":[
        {
            "category":"Building & Trades",
            "subcategory":"Locksmith",
            "type":"Services"
        }
    ],
    "sg:phone":"+1 201 549 1485",
    "sg:postcode":"07030",
    "sg:province":"NJ",
    "sg:tags":[
        "key"
    ],
    "wof:name":"024 Hour A Day Locksmith",
    "wof:placetype":"venue"
},
  "geometry": {"coordinates":[-74.02531399999999,40.752983],"type":"Point"}
}