{
  "type": "Feature",
  "properties": {
    "addr:full":"199 State Rte 70 Lakewood NJ 08701",
    "addr:housenumber":"199",
    "addr:postcode":"08701",
    "addr:street":"State Rte 70",
    "iso:country":"US",
    "sg:address":"199 State Rte 70",
    "sg:city":"Lakewood",
    "sg:classifiers":[
        {
            "category":"Autos & Motor Vehicles",
            "subcategory":"Fuel & Gas Station",
            "type":"Retail Goods"
        }
    ],
    "sg:phone":"+1 732 370 0371",
    "sg:postcode":"08701",
    "sg:province":"NJ",
    "sg:tags":[
        "oil"
    ],
    "wof:name":"Whitesville Exxon",
    "wof:placetype":"venue"
},
  "geometry": {"coordinates":[-74.214766,40.048078],"type":"Point"}
}