{
  "type": "Feature",
  "properties": {
    "iso:country":"US",
    "sg:address":"20 Jared Dr",
    "sg:city":"Trenton",
    "sg:classifiers":[
        {
            "category":"Banks & Credit Unions",
            "subcategory":"Financial Services",
            "type":"Services"
        }
    ],
    "sg:phone":"+1   ",
    "sg:postcode":"08691",
    "sg:province":"NJ",
    "sg:tags":[
        "investor"
    ],
    "wof:name":"Jdl Investments LLC",
    "wof:placetype":"venue"
},
  "geometry": {"coordinates":[-74.600863,40.242597],"type":"Point"}
}