{
  "type": "Feature",
  "properties": {
    "iso:country":"US",
    "sg:address":"421 35th St",
    "sg:city":"Union City",
    "sg:classifiers":[
        {
            "category":"Professional",
            "type":"Services"
        }
    ],
    "sg:phone":"+1   ",
    "sg:postcode":"07087",
    "sg:province":"NJ",
    "wof:name":"Mohammad Judeh",
    "wof:placetype":"venue"
},
  "geometry": {"coordinates":[-74.02802,40.773334],"type":"Point"}
}