{
  "type": "Feature",
  "properties": {
    "addr:full":"709 Route 70 Brick NJ 08723",
    "addr:housenumber":"709",
    "addr:postcode":"08723",
    "addr:street":"Route 70",
    "iso:country":"US",
    "sg:address":"709 Route 70",
    "sg:city":"Brick",
    "sg:classifiers":[
        {
            "category":"Restaurant",
            "type":"Food & Drink"
        }
    ],
    "sg:menulink":"http://www.allmenus.com/nj/brick/158967-arbys/menu/",
    "sg:phone":"+1 732 626 1339",
    "sg:postcode":"08723",
    "sg:province":"NJ",
    "sg:tags":[
        "burger",
        "american"
    ],
    "wof:name":"Arby's",
    "wof:placetype":"venue"
},
  "geometry": {"coordinates":[-74.140078,40.061092],"type":"Point"}
}