{
  "type": "Feature",
  "properties": {
    "addr:full":"619 Grove St Jersey City NJ 07310",
    "addr:housenumber":"619",
    "addr:postcode":"07310",
    "addr:street":"Grove St",
    "iso:country":"US",
    "sg:address":"619 Grove St",
    "sg:city":"Jersey City",
    "sg:classifiers":[
        {
            "category":"Health Services",
            "subcategory":"Nursing And Care Facility",
            "type":"Services"
        },
        {
            "category":"Social Services",
            "type":"Services"
        }
    ],
    "sg:phone":"+1 201 656 5771",
    "sg:postcode":"07310",
    "sg:province":"NJ",
    "sg:tags":[
        "shelter",
        "skilled",
        "homeless"
    ],
    "sg:website":"www.ccsnewark.org",
    "wof:name":"St Lucy S Shelter",
    "wof:placetype":"venue"
},
  "geometry": {"coordinates":[-74.04103499999999,40.732568],"type":"Point"}
}