{
  "type": "Feature",
  "properties": {
    "addr:full":"510 US Hwy 130 East Windsor NJ 08520",
    "addr:housenumber":"510",
    "addr:postcode":"08520",
    "addr:street":"Us Hwy 130 East",
    "iso:country":"US",
    "sg:address":"510 US Hwy 130",
    "sg:city":"East Windsor",
    "sg:classifiers":[
        {
            "category":"Sports & Exercise",
            "subcategory":"Gym",
            "type":"Entertainment"
        }
    ],
    "sg:phone":"+1 609 490 1688",
    "sg:postcode":"08520",
    "sg:province":"NJ",
    "sg:tags":[
        "spa",
        "health"
    ],
    "wof:name":"Life Therapy Spa Inc",
    "wof:placetype":"venue"
},
  "geometry": {"coordinates":[-74.5017,40.233052],"type":"Point"}
}