{
  "type": "Feature",
  "properties": {
    "addr:full":"422 S Main St Pleasantville NJ 08232",
    "addr:housenumber":"422",
    "addr:postcode":"08232",
    "addr:street":"S Main St",
    "iso:country":"US",
    "sg:address":"422 S Main St",
    "sg:city":"Pleasantville",
    "sg:classifiers":[
        {
            "category":"Food & Beverages",
            "subcategory":"Groceries & Convenience Stores",
            "type":"Retail Goods"
        }
    ],
    "sg:phone":"+1 609 407 9258",
    "sg:postcode":"08232",
    "sg:province":"NJ",
    "sg:tags":[
        "market"
    ],
    "wof:name":"TU Pais Market",
    "wof:placetype":"venue"
},
  "geometry": {"coordinates":[-74.52681699999999,39.386878],"type":"Point"}
}