{
  "type": "Feature",
  "properties": {
    "iso:country":"US",
    "sg:address":"77 Park Ave",
    "sg:city":"Hoboken",
    "sg:classifiers":[
        {
            "category":"Utilities",
            "subcategory":"Telephone",
            "type":"Services"
        }
    ],
    "sg:phone":"+1 201 420 8696",
    "sg:postcode":"07030",
    "sg:province":"NJ",
    "sg:tags":[
        "communications"
    ],
    "wof:name":"Critical Mail Inc",
    "wof:placetype":"venue"
},
  "geometry": {"coordinates":[-74.033968,40.736169],"type":"Point"}
}