{
  "type": "Feature",
  "properties": {
    "iso:country":"US",
    "sg:address":"670 Anderson Ave",
    "sg:city":"Cliffside Park",
    "sg:classifiers":[
        {
            "category":"Wholesale",
            "subcategory":"Machinery & Supplies",
            "type":"Manufacturing & Wholesale Goods"
        }
    ],
    "sg:phone":"+1 201 943 4560",
    "sg:postcode":"07010",
    "sg:province":"NJ",
    "sg:tags":[
        "salon",
        "beauty"
    ],
    "wof:name":"Olio Beauty Supply",
    "wof:placetype":"venue"
},
  "geometry": {"coordinates":[-73.98678200000001,40.827341],"type":"Point"}
}