{
  "type": "Feature",
  "properties": {
    "addr:full":"29 Whitehall Rd Monroe Township NJ 08831",
    "addr:housenumber":"29",
    "addr:postcode":"08831",
    "addr:street":"Whitehall Rd",
    "iso:country":"US",
    "sg:address":"29 Whitehall Rd",
    "sg:city":"Monroe Township",
    "sg:classifiers":[
        {
            "category":"Professional",
            "subcategory":"Accounting & Tax Preparation",
            "type":"Services"
        }
    ],
    "sg:phone":"+1 609 409 7753",
    "sg:postcode":"08831",
    "sg:province":"NJ",
    "wof:name":"Jules Scher CPA",
    "wof:placetype":"venue"
},
  "geometry": {"coordinates":[-74.44963799999999,40.338783],"type":"Point"}
}