{
  "type": "Feature",
  "properties": {
    "addr:full":"22 Jacqueline Pl Sewell NJ 08080",
    "addr:housenumber":"22",
    "addr:postcode":"08080",
    "addr:street":"Jacqueline Pl",
    "iso:country":"US",
    "sg:address":"22 Jacqueline Pl",
    "sg:city":"Sewell",
    "sg:classifiers":[
        {
            "category":"Manufacturing",
            "subcategory":"Printing",
            "type":"Manufacturing & Wholesale Goods"
        }
    ],
    "sg:phone":"+1 856 629 9765",
    "sg:postcode":"08080",
    "sg:province":"NJ",
    "sg:tags":[
        "commercial"
    ],
    "wof:name":"Logo Logix LLC",
    "wof:placetype":"venue"
},
  "geometry": {"coordinates":[-75.04256100000001,39.713927],"type":"Point"}
}