{
  "type": "Feature",
  "properties": {
    "addr:full":"806 80th St North Bergen NJ 07047",
    "addr:housenumber":"806",
    "addr:postcode":"07047",
    "addr:street":"80Th St",
    "iso:country":"US",
    "sg:address":"806 80th St",
    "sg:city":"North Bergen",
    "sg:classifiers":[
        {
            "category":"Wholesale",
            "subcategory":"Non-durable Goods",
            "type":"Manufacturing & Wholesale Goods"
        }
    ],
    "sg:phone":"+1 201 662 9280",
    "sg:postcode":"07047",
    "sg:province":"NJ",
    "wof:name":"Gid Trading Imports/Exports",
    "wof:placetype":"venue"
},
  "geometry": {"coordinates":[-74.009947,40.804188],"type":"Point"}
}