{
  "type": "Feature",
  "properties": {
    "iso:country":"US",
    "sg:address":"336 W Passaic St",
    "sg:city":"Rochelle Park",
    "sg:classifiers":[
        {
            "category":"Insurance",
            "subcategory":"Insurance Agent",
            "type":"Services"
        }
    ],
    "sg:phone":"+1 201 368 1370",
    "sg:postcode":"07662",
    "sg:province":"NJ",
    "sg:tags":[
        "adjuster"
    ],
    "wof:name":"A J Scala & Assoc Inc",
    "wof:placetype":"venue"
},
  "geometry": {"coordinates":[-74.084827,40.918387],"type":"Point"}
}