{
  "type": "Feature",
  "properties": {
    "iso:country":"US",
    "sg:address":"350 Baldwin Rd",
    "sg:city":"Parsippany",
    "sg:classifiers":[
        {
            "category":"Shopping",
            "subcategory":"Hobbies, Toys, & Games",
            "type":"Retail Goods"
        }
    ],
    "sg:phone":"+1 973 263 8088",
    "sg:postcode":"07054",
    "sg:province":"NJ",
    "sg:tags":[
        "craft"
    ],
    "wof:name":"Rainbow Rovers",
    "wof:placetype":"venue"
},
  "geometry": {"coordinates":[-74.39461900000001,40.865137],"type":"Point"}
}