{
  "type": "Feature",
  "properties": {
    "addr:full":"911 Cedar St Millville NJ 08332",
    "addr:housenumber":"911",
    "addr:postcode":"08332",
    "addr:street":"Cedar St",
    "iso:country":"US",
    "sg:address":"911 Cedar St",
    "sg:city":"Millville",
    "sg:classifiers":[
        {
            "category":"Manufacturing",
            "subcategory":"Signs",
            "type":"Manufacturing & Wholesale Goods"
        }
    ],
    "sg:phone":"+1 856 825 4787",
    "sg:postcode":"08332",
    "sg:province":"NJ",
    "wof:name":"Artisan Sign Works",
    "wof:placetype":"venue"
},
  "geometry": {"coordinates":[-75.05766199999999,39.386832],"type":"Point"}
}