{
  "type": "Feature",
  "properties": {
    "addr:full":"224 Market St Perth Amboy NJ 08861",
    "addr:housenumber":"224",
    "addr:postcode":"08861",
    "addr:street":"Market St",
    "iso:country":"US",
    "sg:address":"224 Market St",
    "sg:city":"Perth Amboy",
    "sg:classifiers":[
        {
            "category":"Manufacturing",
            "subcategory":"Furniture",
            "type":"Manufacturing & Wholesale Goods"
        }
    ],
    "sg:phone":"+1 732 442 1199",
    "sg:postcode":"08861",
    "sg:province":"NJ",
    "sg:tags":[
        "case",
        "display",
        "mfg"
    ],
    "wof:name":"Allstate Manufacturing Co",
    "wof:placetype":"venue"
},
  "geometry": {"coordinates":[-74.272699,40.50814],"type":"Point"}
}