{
  "type": "Feature",
  "properties": {
    "iso:country":"US",
    "sg:address":"1006 US Highway 46",
    "sg:city":"Clifton",
    "sg:classifiers":[
        {
            "category":"Building & Trades",
            "subcategory":"Locksmith",
            "type":"Services"
        }
    ],
    "sg:phone":"+1 866 408 0774",
    "sg:postcode":"07013",
    "sg:province":"NJ",
    "sg:tags":[
        "key"
    ],
    "wof:name":"0 0 24 Hour 1 Emergency Locksmith",
    "wof:placetype":"venue"
},
  "geometry": {"coordinates":[-74.17703,40.872673],"type":"Point"}
}