{
  "type": "Feature",
  "properties": {
    "iso:country":"US",
    "sg:address":"1328 River Ave",
    "sg:city":"Lakewood",
    "sg:classifiers":[
        {
            "category":"Personal",
            "subcategory":"Beauty Salon",
            "type":"Services"
        }
    ],
    "sg:phone":"+1 732 367 0001",
    "sg:postcode":"08701",
    "sg:province":"NJ",
    "sg:tags":[
        "shop"
    ],
    "wof:name":"Awards Beauty Salon",
    "wof:placetype":"venue"
},
  "geometry": {"coordinates":[-74.221181,40.051901],"type":"Point"}
}