{
  "type": "Feature",
  "properties": {
    "addr:full":"727 Frelinghuysen Ave Newark NJ 07114",
    "addr:housenumber":"727",
    "addr:postcode":"07114",
    "addr:street":"Frelinghuysen Ave",
    "iso:country":"US",
    "sg:address":"727 Frelinghuysen Ave",
    "sg:city":"Newark",
    "sg:classifiers":[
        {
            "category":"Building & Trades",
            "subcategory":"Equipment Rental",
            "type":"Services"
        }
    ],
    "sg:phone":"+1 973 242 3206",
    "sg:postcode":"07114",
    "sg:province":"NJ",
    "sg:tags":[
        "leasing"
    ],
    "wof:name":"Sirs Leasing Co",
    "wof:placetype":"venue"
},
  "geometry": {"coordinates":[-74.19915899999999,40.696398],"type":"Point"}
}