{
  "type": "Feature",
  "properties": {
    "iso:country":"US",
    "sg:address":"100 Springhill Rd",
    "sg:city":"Skillman",
    "sg:classifiers":[
        {
            "category":"Professional",
            "type":"Services"
        }
    ],
    "sg:phone":"+1 609 759 3202",
    "sg:postcode":"08558",
    "sg:province":"NJ",
    "sg:tags":[
        "establishment"
    ],
    "wof:name":"Huntington & Huntington",
    "wof:placetype":"venue"
},
  "geometry": {"coordinates":[-74.732007,40.40923],"type":"Point"}
}