{
  "type": "Feature",
  "properties": {
    "iso:country":"US",
    "sg:address":"434 State Rte 72",
    "sg:city":"Manahawkin",
    "sg:classifiers":[
        {
            "category":"Professional",
            "subcategory":"Lawyer & Legal Services",
            "type":"Services"
        }
    ],
    "sg:phone":"+1 609 597 1111",
    "sg:postcode":"08050",
    "sg:province":"NJ",
    "sg:tags":[
        "attorney"
    ],
    "wof:name":"George M Cafarelli",
    "wof:placetype":"venue"
},
  "geometry": {"coordinates":[-74.26708000000001,39.699421],"type":"Point"}
}