{
  "type": "Feature",
  "properties": {
    "addr:full":"129 Kosciuszko Rd White House Station NJ 08889",
    "addr:housenumber":"129",
    "addr:postcode":"08889",
    "addr:street":"Kosciuszko Rd",
    "iso:country":"US",
    "sg:address":"129 Kosciuszko Rd",
    "sg:city":"White House Station",
    "sg:classifiers":[
        {
            "category":"Retail",
            "subcategory":"Auto Repair",
            "type":"Services"
        }
    ],
    "sg:phone":"+1   ",
    "sg:postcode":"08889",
    "sg:province":"NJ",
    "sg:tags":[
        "shop",
        "automotive",
        "general"
    ],
    "wof:name":"The Car Doctor",
    "wof:placetype":"venue"
},
  "geometry": {"coordinates":[-74.771683,40.594344],"type":"Point"}
}