{
  "type": "Feature",
  "properties": {
    "iso:country":"US",
    "sg:address":"1600 Lawrence St",
    "sg:city":"Rahway",
    "sg:classifiers":[
        {
            "category":"Health Services",
            "subcategory":"Health Practitioner",
            "type":"Services"
        },
        {
            "category":"Professional",
            "subcategory":"Employment Agencies",
            "type":"Services"
        }
    ],
    "sg:phone":"+1 732 388 0736",
    "sg:postcode":"07065",
    "sg:province":"NJ",
    "sg:tags":[
        "nurse",
        "registry"
    ],
    "wof:name":"Elenora R Campbell Rn Mrs",
    "wof:placetype":"venue"
},
  "geometry": {"coordinates":[-74.269564,40.60536],"type":"Point"}
}