{
  "type": "Feature",
  "properties": {
    "iso:country":"US",
    "sg:address":"203 Santa Anita Ln",
    "sg:city":"Toms River",
    "sg:classifiers":[
        {
            "category":"Professional",
            "subcategory":"Lawyer & Legal Services",
            "type":"Services"
        }
    ],
    "sg:phone":"+1 732 370 6743",
    "sg:postcode":"08755",
    "sg:province":"NJ",
    "sg:tags":[
        "attorney"
    ],
    "wof:name":"William L Huneke PC",
    "wof:placetype":"venue"
},
  "geometry": {"coordinates":[-74.24216800000001,40.04294],"type":"Point"}
}