{
  "type": "Feature",
  "properties": {
    "addr:full":"600 Cricket Ln Woodbridge NJ 07095",
    "addr:housenumber":"600",
    "addr:postcode":"07095",
    "addr:street":"Cricket Ln",
    "iso:country":"US",
    "sg:address":"600 Cricket Ln",
    "sg:city":"Woodbridge",
    "sg:classifiers":[
        {
            "category":"Professional",
            "type":"Services"
        }
    ],
    "sg:phone":"+1 732 750 9639",
    "sg:postcode":"07095",
    "sg:province":"NJ",
    "sg:tags":[
        "establishment"
    ],
    "wof:name":"Wyndmoor At Woodbridge",
    "wof:placetype":"venue"
},
  "geometry": {"coordinates":[-74.282731,40.545574],"type":"Point"}
}