{
  "type": "Feature",
  "properties": {
    "addr:full":"69 Chestnut St Rochelle Park NJ 07662",
    "addr:housenumber":"69",
    "addr:postcode":"07662",
    "addr:street":"Chestnut St",
    "iso:country":"US",
    "sg:address":"69 Chestnut St",
    "sg:city":"Rochelle Park",
    "sg:classifiers":[
        {
            "category":"Building & Trades",
            "subcategory":"Construction",
            "type":"Services"
        }
    ],
    "sg:phone":"+1 201 843 4812",
    "sg:postcode":"07662",
    "sg:province":"NJ",
    "sg:tags":[
        "house"
    ],
    "wof:name":"Galambos & Sons Construction",
    "wof:placetype":"venue"
},
  "geometry": {"coordinates":[-74.080969,40.90862],"type":"Point"}
}