{
  "type": "Feature",
  "properties": {
    "iso:country":"US",
    "sg:address":"91 E 21st St",
    "sg:city":"Bayonne",
    "sg:classifiers":[
        {
            "category":"Retail",
            "subcategory":"Repair Shop",
            "type":"Services"
        }
    ],
    "sg:phone":"+1   ",
    "sg:postcode":"07002",
    "sg:province":"NJ",
    "sg:tags":[
        "electrical"
    ],
    "wof:name":"Compumatic",
    "wof:placetype":"venue"
},
  "geometry": {"coordinates":[-74.11518,40.660048],"type":"Point"}
}