{
  "type": "Feature",
  "properties": {
    "addr:full":"1853 Mays Landing Rd Millville NJ 08332",
    "addr:housenumber":"1853",
    "addr:postcode":"08332",
    "addr:street":"Mays Landing Rd",
    "iso:country":"US",
    "sg:address":"1853 Mays Landing Rd",
    "sg:city":"Millville",
    "sg:classifiers":[
        {
            "category":"Organizations",
            "subcategory":"Religious Organization",
            "type":"Services"
        }
    ],
    "sg:phone":"+1   ",
    "sg:postcode":"08332",
    "sg:province":"NJ",
    "wof:name":"Pilgrim Holiness Church",
    "wof:placetype":"venue"
},
  "geometry": {"coordinates":[-75.00564,39.40794],"type":"Point"}
}