{
  "type": "Feature",
  "properties": {
    "addr:full":"424 Davis Ave Northfield NJ 08225",
    "addr:housenumber":"424",
    "addr:postcode":"08225",
    "addr:street":"Davis Ave",
    "iso:country":"US",
    "sg:address":"424 Davis Ave",
    "sg:city":"Northfield",
    "sg:classifiers":[
        {
            "category":"Ice Cream",
            "type":"Food & Drink"
        }
    ],
    "sg:menulink":"http://www.allmenus.com/nj/northfield/234677-ritas-ice-custard-happiness/menu/",
    "sg:phone":"+1 609 485 2311",
    "sg:postcode":"08225",
    "sg:province":"NJ",
    "sg:tags":[
        "american"
    ],
    "wof:name":"Rita's Ice Custard Happiness",
    "wof:placetype":"venue"
},
  "geometry": {"coordinates":[-74.552164,39.374668],"type":"Point"}
}