{
  "type": "Feature",
  "properties": {
    "addr:full":"127 Russling Rd Hackettstown NJ 07840",
    "addr:housenumber":"127",
    "addr:postcode":"07840",
    "addr:street":"Russling Rd",
    "iso:country":"US",
    "sg:address":"127 Russling Rd",
    "sg:city":"Hackettstown",
    "sg:classifiers":[
        {
            "category":"Building & Trades",
            "subcategory":"Landscaping Services",
            "type":"Services"
        }
    ],
    "sg:phone":"+1 908 637 4771",
    "sg:postcode":"07840",
    "sg:province":"NJ",
    "sg:tags":[
        "landscape",
        "contractor"
    ],
    "wof:name":"Ed Chesney Landscape Inc",
    "wof:placetype":"venue"
},
  "geometry": {"coordinates":[-74.86446100000001,40.853359],"type":"Point"}
}