{
  "type": "Feature",
  "properties": {
    "iso:country":"US",
    "sg:address":"58 Hester St",
    "sg:city":"Little Ferry",
    "sg:classifiers":[
        {
            "category":"Building & Trades",
            "subcategory":"Plumbing",
            "type":"Services"
        }
    ],
    "sg:phone":"+1 201 440 8306",
    "sg:postcode":"07643",
    "sg:province":"NJ",
    "wof:name":"Dreams Kitchens & Baths",
    "wof:placetype":"venue"
},
  "geometry": {"coordinates":[-74.039584,40.843877],"type":"Point"}
}