{
  "type": "Feature",
  "properties": {
    "iso:country":"US",
    "sg:address":"206 W Kings Hwy",
    "sg:city":"Mount Ephraim",
    "sg:classifiers":[
        {
            "category":"Recreation",
            "type":"Entertainment"
        }
    ],
    "sg:phone":"+1   ",
    "sg:postcode":"08059",
    "sg:province":"NJ",
    "sg:tags":[
        "club",
        "membership"
    ],
    "wof:name":"Mount Ephraim Democratic Club",
    "wof:placetype":"venue"
},
  "geometry": {"coordinates":[-75.090703,39.880699],"type":"Point"}
}