{
  "type": "Feature",
  "properties": {
    "iso:country":"US",
    "sg:address":"182 Whitman Ave",
    "sg:city":"Edison",
    "sg:classifiers":[
        {
            "category":"Professional",
            "type":"Services"
        }
    ],
    "sg:phone":"+1 732 248 5700",
    "sg:postcode":"08817",
    "sg:province":"NJ",
    "sg:website":"www.aspservices.com",
    "wof:name":"ASP Svc Inc",
    "wof:placetype":"venue"
},
  "geometry": {"coordinates":[-74.374859,40.527964],"type":"Point"}
}