{
  "type": "Feature",
  "properties": {
    "addr:full":"109 Water St South River NJ 08882",
    "addr:housenumber":"109",
    "addr:postcode":"08882",
    "addr:street":"Water St",
    "iso:country":"US",
    "sg:address":"109 Water St",
    "sg:city":"South River",
    "sg:classifiers":[
        {
            "category":"Retail",
            "subcategory":"Auto Repair",
            "type":"Services"
        }
    ],
    "sg:phone":"+1 732 257 4464",
    "sg:postcode":"08882",
    "sg:province":"NJ",
    "sg:tags":[
        "body",
        "automobile",
        "painting"
    ],
    "wof:name":"Diorio's Auto Body Shop",
    "wof:placetype":"venue"
},
  "geometry": {"coordinates":[-74.377197,40.451215],"type":"Point"}
}