{
  "type": "Feature",
  "properties": {
    "iso:country":"US",
    "sg:address":"67 US Hwy 9",
    "sg:city":"Morganville",
    "sg:classifiers":[
        {
            "category":"Shopping",
            "subcategory":"Bicycles & Sporting Goods",
            "type":"Retail Goods"
        }
    ],
    "sg:phone":"+1   ",
    "sg:postcode":"07751",
    "sg:province":"NJ",
    "wof:name":"New Jersey Golf Headquarters",
    "wof:placetype":"venue"
},
  "geometry": {"coordinates":[-74.30629500000001,40.356635],"type":"Point"}
}