{
  "type": "Feature",
  "properties": {
    "addr:full":"604 Haifa Ct Toms River NJ 08753",
    "addr:housenumber":"604",
    "addr:postcode":"08753",
    "addr:street":"Haifa Ct",
    "iso:country":"US",
    "sg:address":"604 Haifa Ct",
    "sg:city":"Toms River",
    "sg:classifiers":[
        {
            "category":"Professional",
            "type":"Services"
        }
    ],
    "sg:phone":"+1   ",
    "sg:postcode":"08753",
    "sg:province":"NJ",
    "wof:name":"Totts Inc",
    "wof:placetype":"venue"
},
  "geometry": {"coordinates":[-74.15983300000001,39.982201],"type":"Point"}
}