{
  "type": "Feature",
  "properties": {
    "addr:full":"4385 US Hwy 1 Princeton NJ 08540",
    "addr:housenumber":"4385",
    "addr:postcode":"08540",
    "addr:street":"Us Hwy 1",
    "iso:country":"US",
    "sg:address":"4385 US Hwy 1",
    "sg:city":"Princeton",
    "sg:classifiers":[
        {
            "category":"Arts & Performance",
            "subcategory":"Theater",
            "type":"Entertainment"
        }
    ],
    "sg:phone":"+1 609 419 4341",
    "sg:postcode":"08540",
    "sg:province":"NJ",
    "sg:tags":[
        "bureau"
    ],
    "wof:name":"Lodgenet Entertainment Corp",
    "wof:placetype":"venue"
},
  "geometry": {"coordinates":[-74.59058400000001,40.371476],"type":"Point"}
}