{
  "type": "Feature",
  "properties": {
    "addr:full":"32 Denman Rd Cranford NJ 07016",
    "addr:housenumber":"32",
    "addr:postcode":"07016",
    "addr:street":"Denman Rd",
    "iso:country":"US",
    "sg:address":"32 Denman Rd",
    "sg:city":"Cranford",
    "sg:classifiers":[
        {
            "category":"Building & Trades",
            "subcategory":"Construction",
            "type":"Services"
        }
    ],
    "sg:phone":"+1 908 276 1922",
    "sg:postcode":"07016",
    "sg:province":"NJ",
    "sg:tags":[
        "nonresidential"
    ],
    "wof:name":"Crane Builders Inc",
    "wof:placetype":"venue"
},
  "geometry": {"coordinates":[-74.305442,40.648319],"type":"Point"}
}