{
  "type": "Feature",
  "properties": {
    "iso:country":"US",
    "sg:address":"2 Jefferson Ave",
    "sg:city":"Tenafly",
    "sg:classifiers":[
        {
            "category":"Social Services",
            "type":"Services"
        }
    ],
    "sg:phone":"+1 201 568 8407",
    "sg:postcode":"07670",
    "sg:province":"NJ",
    "sg:tags":[
        "youth",
        "organization",
        "center"
    ],
    "wof:name":"Tenafly Lions Little League",
    "wof:placetype":"venue"
},
  "geometry": {"coordinates":[-73.971453,40.926885],"type":"Point"}
}