{
  "type": "Feature",
  "properties": {
    "iso:country":"US",
    "sg:address":"40 US Hwy 130",
    "sg:city":"Burlington",
    "sg:classifiers":[
        {
            "category":"Autos & Motor Vehicles",
            "subcategory":"Automobile Sales",
            "type":"Retail Goods"
        }
    ],
    "sg:phone":"+1 609 386 4900",
    "sg:postcode":"08016",
    "sg:province":"NJ",
    "sg:tags":[
        "car",
        "dealer"
    ],
    "sg:website":"www.burlingtonlincolnmercury.com",
    "wof:name":"Burlington Lincoln-Mercury",
    "wof:placetype":"venue"
},
  "geometry": {"coordinates":[-74.857089,40.070375],"type":"Point"}
}