{
  "type": "Feature",
  "properties": {
    "iso:country":"US",
    "sg:address":"416 Tansboro Rd",
    "sg:city":"Atco",
    "sg:classifiers":[
        {
            "category":"Government",
            "subcategory":"Fire Station",
            "type":"Public Place"
        }
    ],
    "sg:phone":"+1   ",
    "sg:postcode":"08009",
    "sg:province":"NJ",
    "sg:tags":[
        "protection"
    ],
    "wof:name":"Tansboro Volunteer Fire Co",
    "wof:placetype":"venue"
},
  "geometry": {"coordinates":[-74.916695,39.76234],"type":"Point"}
}