{
  "type": "Feature",
  "properties": {
    "addr:full":"2501 Cavallo Dr Vineland NJ 08361",
    "addr:housenumber":"2501",
    "addr:postcode":"08361",
    "addr:street":"Cavallo Dr",
    "iso:country":"US",
    "sg:address":"2501 Cavallo Dr",
    "sg:city":"Vineland",
    "sg:classifiers":[
        {
            "category":"Real Estate",
            "subcategory":"Real Estate Operator",
            "type":"Services"
        }
    ],
    "sg:phone":"+1   ",
    "sg:postcode":"08361",
    "sg:province":"NJ",
    "sg:tags":[
        "building",
        "apartment"
    ],
    "wof:name":"Mia Apts LLC",
    "wof:placetype":"venue"
},
  "geometry": {"coordinates":[-74.98352800000001,39.447706],"type":"Point"}
}