{
  "type": "Feature",
  "properties": {
    "addr:full":"71 E Washington Ave Atlantic Highlands NJ 07716",
    "addr:housenumber":"71",
    "addr:postcode":"07716",
    "addr:street":"E Washington Ave",
    "iso:country":"US",
    "sg:address":"71 E Washington Ave",
    "sg:city":"Atlantic Highlands",
    "sg:classifiers":[
        {
            "category":"Professional",
            "subcategory":"Management & Consulting",
            "type":"Services"
        }
    ],
    "sg:phone":"+1 732 291 8217",
    "sg:postcode":"07716",
    "sg:province":"NJ",
    "sg:tags":[
        "marketing",
        "co",
        "business",
        "working"
    ],
    "wof:name":"Bcsi",
    "wof:placetype":"venue"
},
  "geometry": {"coordinates":[-74.034525,40.410747],"type":"Point"}
}