{
  "type": "Feature",
  "properties": {
    "addr:full":"208 Elmer St Westfield NJ 07090",
    "addr:housenumber":"208",
    "addr:postcode":"07090",
    "addr:street":"Elmer St",
    "iso:country":"US",
    "sg:address":"208 Elmer St",
    "sg:city":"Westfield",
    "sg:classifiers":[
        {
            "category":"Professional",
            "type":"Services"
        }
    ],
    "sg:phone":"+1 908 232 8393",
    "sg:postcode":"07090",
    "sg:province":"NJ",
    "wof:name":"Union County Ptg & Mailing Svc",
    "wof:placetype":"venue"
},
  "geometry": {"coordinates":[-74.343518,40.650813],"type":"Point"}
}