{
  "type": "Feature",
  "properties": {
    "iso:country":"US",
    "sg:address":"1183 Queen Anne Rd",
    "sg:city":"Teaneck",
    "sg:classifiers":[
        {
            "category":"Health Services",
            "subcategory":"Health Practitioner",
            "type":"Services"
        }
    ],
    "sg:phone":"+1 201 833 4587",
    "sg:postcode":"07666",
    "sg:province":"NJ",
    "sg:tags":[
        "gambling",
        "addiction-information",
        "treatment"
    ],
    "wof:name":"Jasons Sensory Gym",
    "wof:placetype":"venue"
},
  "geometry": {"coordinates":[-74.008741,40.895744],"type":"Point"}
}