{
  "type": "Feature",
  "properties": {
    "addr:full":"2510 River Ave Camden NJ 08105",
    "addr:housenumber":"2510",
    "addr:postcode":"08105",
    "addr:street":"River Ave",
    "iso:country":"US",
    "sg:address":"2510 River Ave",
    "sg:city":"Camden",
    "sg:classifiers":[
        {
            "category":"Restaurant",
            "type":"Food & Drink"
        }
    ],
    "sg:phone":"+1 856 541 4914",
    "sg:postcode":"08105",
    "sg:province":"NJ",
    "sg:tags":[
        "eating",
        "pizza"
    ],
    "wof:name":"Riccardo's Pizza No 1",
    "wof:placetype":"venue"
},
  "geometry": {"coordinates":[-75.094902,39.9548],"type":"Point"}
}