{
  "type": "Feature",
  "properties": {
    "iso:country":"US",
    "sg:address":"920 Harrison Ave",
    "sg:city":"Roselle",
    "sg:classifiers":[
        {
            "category":"Retail",
            "subcategory":"Auto Repair",
            "type":"Services"
        }
    ],
    "sg:phone":"+1   ",
    "sg:postcode":"07203",
    "sg:province":"NJ",
    "sg:tags":[
        "truck",
        "tire"
    ],
    "wof:name":"K & S Tire Svc & Lubrication",
    "wof:placetype":"venue"
},
  "geometry": {"coordinates":[-74.24874,40.650433],"type":"Point"}
}