{
  "type": "Feature",
  "properties": {
    "iso:country":"US",
    "sg:address":"106 Bridge Ave",
    "sg:city":"Bay Head",
    "sg:classifiers":[
        {
            "category":"Professional",
            "subcategory":"Accounting & Tax Preparation",
            "type":"Services"
        }
    ],
    "sg:phone":"+1 732 892 9902",
    "sg:postcode":"08742",
    "sg:province":"NJ",
    "sg:tags":[
        "consultant",
        "return"
    ],
    "wof:name":"Edward P Rigby Tax Consulting",
    "wof:placetype":"venue"
},
  "geometry": {"coordinates":[-74.048283,40.070956],"type":"Point"}
}