{
  "type": "Feature",
  "properties": {
    "addr:full":"34 N Beverwyck Rd Lake Hiawatha NJ 07034",
    "addr:housenumber":"34",
    "addr:postcode":"07034",
    "addr:street":"N Beverwyck Rd",
    "iso:country":"US",
    "sg:address":"34 N Beverwyck Rd",
    "sg:city":"Lake Hiawatha",
    "sg:classifiers":[
        {
            "category":"Retail",
            "subcategory":"Repair Shop",
            "type":"Services"
        }
    ],
    "sg:phone":"+1   ",
    "sg:postcode":"07034",
    "sg:province":"NJ",
    "sg:tags":[
        "sporting"
    ],
    "sg:website":"www.golf-doctor.com",
    "wof:name":"Golf Doctor",
    "wof:placetype":"venue"
},
  "geometry": {"coordinates":[-74.382668,40.876107],"type":"Point"}
}