{
  "type": "Feature",
  "properties": {
    "iso:country":"US",
    "sg:address":"7 Beacon Light Rd",
    "sg:city":"Califon",
    "sg:classifiers":[
        {
            "category":"Farming",
            "subcategory":"Farm",
            "type":"Manufacturing & Wholesale Goods"
        }
    ],
    "sg:phone":"+1 908 832 2298",
    "sg:postcode":"07830",
    "sg:province":"NJ",
    "sg:tags":[
        "crop",
        "general"
    ],
    "wof:name":"Alger Tree Farm",
    "wof:placetype":"venue"
},
  "geometry": {"coordinates":[-74.78094299999999,40.73766],"type":"Point"}
}