{
  "type": "Feature",
  "properties": {
    "iso:country":"US",
    "sg:address":"50-52 Metro Way Ste 2",
    "sg:city":"Secaucus",
    "sg:classifiers":[
        {
            "category":"Personal",
            "type":"Services"
        }
    ],
    "sg:phone":"+1 201 520 1540",
    "sg:postcode":"07094",
    "sg:province":"NJ",
    "sg:tags":[
        "mover"
    ],
    "sg:website":"www.omegashipping.com",
    "wof:name":"Omega Shipping",
    "wof:placetype":"venue"
},
  "geometry": {"coordinates":[-74.071782,40.773489],"type":"Point"}
}