{
  "type": "Feature",
  "properties": {
    "iso:country":"US",
    "sg:address":"40 Whitney Rd",
    "sg:city":"Short Hills",
    "sg:classifiers":[
        {
            "category":"Banks & Credit Unions",
            "subcategory":"Financial Services",
            "type":"Services"
        }
    ],
    "sg:phone":"+1 973 563 5197",
    "sg:postcode":"07078",
    "sg:province":"NJ",
    "sg:website":"www.actuarialconsortium.com",
    "wof:name":"Actuarial Consortium",
    "wof:placetype":"venue"
},
  "geometry": {"coordinates":[-74.311508,40.724896],"type":"Point"}
}