{
  "type": "Feature",
  "properties": {
    "iso:country":"US",
    "sg:address":"977 Mill Rd",
    "sg:city":"Pleasantville",
    "sg:classifiers":[
        {
            "category":"Building & Trades",
            "subcategory":"Equipment Rental",
            "type":"Services"
        },
        {
            "category":"Building & Trades",
            "subcategory":"Construction",
            "type":"Services"
        }
    ],
    "sg:phone":"+1 609 645 2165",
    "sg:postcode":"08232",
    "sg:province":"NJ",
    "sg:tags":[
        "excavation",
        "demolition",
        "contractor"
    ],
    "sg:website":"www.iaconelli.com",
    "wof:name":"Iaconelli Contracting Co Inc",
    "wof:placetype":"venue"
},
  "geometry": {"coordinates":[-74.526066,39.407127],"type":"Point"}
}