{
  "type": "Feature",
  "properties": {
    "iso:country":"US",
    "sg:address":"109 Meeker Ave",
    "sg:city":"Newark",
    "sg:classifiers":[
        {
            "category":"Wholesale",
            "subcategory":"Machinery & Supplies",
            "type":"Manufacturing & Wholesale Goods"
        },
        {
            "category":"Retail",
            "subcategory":"Repair Shop",
            "type":"Services"
        }
    ],
    "sg:phone":"+1 973 824 8000",
    "sg:postcode":"07114",
    "sg:province":"NJ",
    "sg:tags":[
        "machine",
        "equipment",
        "tool",
        "industrial"
    ],
    "wof:name":"C R S Machine Rebuilders Inc",
    "wof:placetype":"venue"
},
  "geometry": {"coordinates":[-74.19668299999999,40.7065],"type":"Point"}
}