{
  "type": "Feature",
  "properties": {
    "addr:full":"331 Church Rd Brick NJ 08723",
    "addr:housenumber":"331",
    "addr:postcode":"08723",
    "addr:street":"Church Rd",
    "iso:country":"US",
    "sg:address":"331 Church Rd",
    "sg:city":"Brick",
    "sg:classifiers":[
        {
            "category":"Building & Trades",
            "subcategory":"Construction",
            "type":"Services"
        }
    ],
    "sg:phone":"+1 732 477 0040",
    "sg:postcode":"08723",
    "sg:province":"NJ",
    "sg:tags":[
        "home",
        "remodeling",
        "family"
    ],
    "wof:name":"Osborn Smith Partnr Gen Contg",
    "wof:placetype":"venue"
},
  "geometry": {"coordinates":[-74.10981700000001,40.042123],"type":"Point"}
}