{
  "type": "Feature",
  "properties": {
    "addr:full":"75 Main St South River NJ 08882",
    "addr:housenumber":"75",
    "addr:postcode":"08882",
    "addr:street":"Main St",
    "iso:country":"US",
    "sg:address":"75 Main St",
    "sg:city":"South River",
    "sg:classifiers":[
        {
            "category":"Insurance",
            "subcategory":"Insurance Agent",
            "type":"Services"
        }
    ],
    "sg:phone":"+1   ",
    "sg:postcode":"08882",
    "sg:province":"NJ",
    "wof:name":"Price Ew Agency",
    "wof:placetype":"venue"
},
  "geometry": {"coordinates":[-74.38248900000001,40.450099],"type":"Point"}
}