{
  "type": "Feature",
  "properties": {
    "iso:country":"US",
    "sg:address":"3011 Adams St",
    "sg:city":"Belmar",
    "sg:classifiers":[
        {
            "category":"Building & Trades",
            "subcategory":"Construction",
            "type":"Services"
        }
    ],
    "sg:phone":"+1 732 681 0897",
    "sg:postcode":"07719",
    "sg:province":"NJ",
    "sg:tags":[
        "paving",
        "asphalt",
        "contractor"
    ],
    "wof:name":"De Sarno Bros",
    "wof:placetype":"venue"
},
  "geometry": {"coordinates":[-74.079853,40.176639],"type":"Point"}
}