{
  "type": "Feature",
  "properties": {
    "addr:full":"6709 Church Rd Merchantville NJ 08109",
    "addr:housenumber":"6709",
    "addr:postcode":"08109",
    "addr:street":"Church Rd",
    "iso:country":"US",
    "sg:address":"6709 Church Rd",
    "sg:city":"Merchantville",
    "sg:classifiers":[
        {
            "category":"Manufacturing",
            "subcategory":"Printing",
            "type":"Manufacturing & Wholesale Goods"
        }
    ],
    "sg:phone":"+1 856 910 0266",
    "sg:postcode":"08109",
    "sg:province":"NJ",
    "sg:tags":[
        "project",
        "p",
        "consulting",
        "management",
        "publishing"
    ],
    "wof:name":"H Dean Publishing LLC",
    "wof:placetype":"venue"
},
  "geometry": {"coordinates":[-75.03848000000001,39.950285],"type":"Point"}
}