{
  "type": "Feature",
  "properties": {
    "iso:country":"US",
    "sg:address":"9 Hickory Rd",
    "sg:city":"Denville",
    "sg:classifiers":[
        {
            "category":"Retail",
            "subcategory":"Repair Shop",
            "type":"Services"
        }
    ],
    "sg:phone":"+1   ",
    "sg:postcode":"07834",
    "sg:province":"NJ",
    "wof:name":"Unison Brothers Inc",
    "wof:placetype":"venue"
},
  "geometry": {"coordinates":[-74.497473,40.871487],"type":"Point"}
}