{
  "type": "Feature",
  "properties": {
    "iso:country":"US",
    "sg:address":"5 Kennedy Dr",
    "sg:city":"Marlboro",
    "sg:classifiers":[
        {
            "category":"Arts & Performance",
            "subcategory":"Theater",
            "type":"Entertainment"
        }
    ],
    "sg:phone":"+1   ",
    "sg:postcode":"07746",
    "sg:province":"NJ",
    "sg:tags":[
        "group"
    ],
    "wof:name":"Amazing Amusements",
    "wof:placetype":"venue"
},
  "geometry": {"coordinates":[-74.26251600000001,40.326778],"type":"Point"}
}