{
  "type": "Feature",
  "properties": {
    "iso:country":"US",
    "sg:address":"400 Market St",
    "sg:city":"Camden",
    "sg:classifiers":[
        {
            "category":"Wholesale",
            "subcategory":"Medical Equipment & Supplies",
            "type":"Manufacturing & Wholesale Goods"
        }
    ],
    "sg:phone":"+1 856 541 1700",
    "sg:postcode":"08102",
    "sg:province":"NJ",
    "sg:tags":[
        "assistive",
        "aid",
        "device",
        "hearing"
    ],
    "wof:name":"Rrc Deaf & Hearing Impaired Program TTY",
    "wof:placetype":"venue"
},
  "geometry": {"coordinates":[-75.12243700000001,39.945869],"type":"Point"}
}