{
  "type": "Feature",
  "properties": {
    "iso:country":"US",
    "sg:address":"248 Beach Ave",
    "sg:city":"Beachwood",
    "sg:classifiers":[
        {
            "category":"Home & Garden",
            "subcategory":"Carpets & Floor Coverings",
            "type":"Retail Goods"
        }
    ],
    "sg:phone":"+1 732 269 6514",
    "sg:postcode":"08722",
    "sg:province":"NJ",
    "sg:tags":[
        "dealer",
        "rug"
    ],
    "wof:name":"Jmj Carpet Care Co",
    "wof:placetype":"venue"
},
  "geometry": {"coordinates":[-74.19405500000001,39.939041],"type":"Point"}
}