{
  "type": "Feature",
  "properties": {
    "iso:country":"US",
    "sg:address":"1190 Route 40",
    "sg:city":"Pilesgrove",
    "sg:classifiers":[
        {
            "category":"Shopping",
            "subcategory":"Clothing, Apparel, & Fashions",
            "type":"Retail Goods"
        },
        {
            "category":"Autos & Motor Vehicles",
            "subcategory":"Auto Supplies",
            "type":"Retail Goods"
        }
    ],
    "sg:phone":"+1 856 769 0567",
    "sg:postcode":"08098",
    "sg:province":"NJ",
    "sg:tags":[
        "work",
        "equipment",
        "western",
        "apparel",
        "riding",
        "clothing",
        "store",
        "clothes"
    ],
    "sg:website":"http://www.zanewestern.com",
    "wof:name":"Zane Western Apparel",
    "wof:placetype":"venue"
},
  "geometry": {"coordinates":[-75.369469,39.65864],"type":"Point"}
}