{
  "type": "Feature",
  "properties": {
    "iso:country":"US",
    "sg:address":"1132 S Washington Ave",
    "sg:city":"Piscataway",
    "sg:classifiers":[
        {
            "category":"Health Services",
            "subcategory":"Doctor",
            "type":"Services"
        }
    ],
    "sg:phone":"+1 732 752 8484",
    "sg:postcode":"08854",
    "sg:province":"NJ",
    "sg:tags":[
        "medical"
    ],
    "wof:name":"Andrew Piskun MD",
    "wof:placetype":"venue"
},
  "geometry": {"coordinates":[-74.449243,40.562947],"type":"Point"}
}