{
  "type": "Feature",
  "properties": {
    "addr:full":"336 Park Ave Orange NJ 07050",
    "addr:housenumber":"336",
    "addr:postcode":"07050",
    "addr:street":"Park Ave",
    "iso:country":"US",
    "sg:address":"336 Park Ave",
    "sg:city":"Orange",
    "sg:classifiers":[
        {
            "category":"Health Services",
            "subcategory":"Health Practitioner",
            "type":"Services"
        }
    ],
    "sg:phone":"+1 973 673 4600",
    "sg:postcode":"07050",
    "sg:province":"NJ",
    "sg:tags":[
        "therapy",
        "physical"
    ],
    "wof:name":"Activa Physical Therapy PC",
    "wof:placetype":"venue"
},
  "geometry": {"coordinates":[-74.227737,40.776985],"type":"Point"}
}