{
  "type": "Feature",
  "properties": {
    "iso:country":"US",
    "sg:address":"Broadway",
    "sg:city":"Bayonne",
    "sg:classifiers":[
        {
            "category":"Building & Trades",
            "subcategory":"Locksmith",
            "type":"Services"
        }
    ],
    "sg:phone":"+1 201 858 8000",
    "sg:postcode":"07002",
    "sg:province":"NJ",
    "sg:tags":[
        "key"
    ],
    "wof:name":"888-USA Lock",
    "wof:placetype":"venue"
},
  "geometry": {"coordinates":[-74.12130000000001,40.667999],"type":"Point"}
}