{
  "type": "Feature",
  "properties": {
    "addr:full":"1200 US Hwy 22 Phillipsburg NJ 08865",
    "addr:housenumber":"1200",
    "addr:postcode":"08865",
    "addr:street":"Us Hwy 22",
    "iso:country":"US",
    "sg:address":"1200 US Hwy 22",
    "sg:city":"Phillipsburg",
    "sg:classifiers":[
        {
            "category":"Shopping",
            "subcategory":"Gifts & Souvenirs",
            "type":"Retail Goods"
        }
    ],
    "sg:phone":"+1 908 454 3290",
    "sg:postcode":"08865",
    "sg:province":"NJ",
    "sg:tags":[
        "shop"
    ],
    "sg:website":"www.thingsremembered.com",
    "wof:name":"Things Remembered",
    "wof:placetype":"venue"
},
  "geometry": {"coordinates":[-75.15013399999999,40.684631],"type":"Point"}
}