{
  "type": "Feature",
  "properties": {
    "addr:full":"256 Columbia Tpke Florham Park NJ 07932",
    "addr:housenumber":"256",
    "addr:postcode":"07932",
    "addr:street":"Columbia Tpke",
    "iso:country":"US",
    "sg:address":"256 Columbia Tpke",
    "sg:city":"Florham Park",
    "sg:classifiers":[
        {
            "category":"Professional",
            "subcategory":"Lawyer & Legal Services",
            "type":"Services"
        }
    ],
    "sg:phone":"+1 973 966 2770",
    "sg:postcode":"07932",
    "sg:province":"NJ",
    "wof:name":"Freireich Jay J Lawyer",
    "wof:placetype":"venue"
},
  "geometry": {"coordinates":[-74.398804,40.7892],"type":"Point"}
}