{
  "type": "Feature",
  "properties": {
    "iso:country":"US",
    "sg:address":"199 US Hwy 22",
    "sg:city":"Green Brook",
    "sg:classifiers":[
        {
            "category":"Social Services",
            "subcategory":"Child Care",
            "type":"Services"
        }
    ],
    "sg:phone":"+1 732 968 0440",
    "sg:postcode":"08812",
    "sg:province":"NJ",
    "wof:name":"Tiny TOTS-USA Baby",
    "wof:placetype":"venue"
},
  "geometry": {"coordinates":[-74.48175999999999,40.600654],"type":"Point"}
}