{
  "type": "Feature",
  "properties": {
    "iso:country":"US",
    "sg:address":"21 Fair Lawn Ave",
    "sg:city":"Fair Lawn",
    "sg:classifiers":[
        {
            "category":"Shopping",
            "type":"Retail Goods"
        }
    ],
    "sg:phone":"+1   ",
    "sg:postcode":"07410",
    "sg:province":"NJ",
    "sg:tags":[
        "merchandise"
    ],
    "wof:name":"Artful Framer",
    "wof:placetype":"venue"
},
  "geometry": {"coordinates":[-74.12675900000001,40.937526],"type":"Point"}
}