{
  "type": "Feature",
  "properties": {
    "addr:full":"24 Central Ave Ocean Grove NJ 07756",
    "addr:housenumber":"24",
    "addr:postcode":"07756",
    "addr:street":"Central Ave",
    "iso:country":"US",
    "sg:address":"24 Central Ave",
    "sg:city":"Ocean Grove",
    "sg:classifiers":[
        {
            "category":"Travel",
            "subcategory":"Hotels & Motels",
            "type":"Entertainment"
        }
    ],
    "sg:phone":"+1 732 775 3579",
    "sg:postcode":"07756",
    "sg:province":"NJ",
    "sg:tags":[
        "accommodation"
    ],
    "wof:name":"Central Avenue House",
    "wof:placetype":"venue"
},
  "geometry": {"coordinates":[-74.005779,40.212886],"type":"Point"}
}