{
  "type": "Feature",
  "properties": {
    "addr:full":"29 Sartori Ave Mount Ephraim NJ 08059",
    "addr:housenumber":"29",
    "addr:postcode":"08059",
    "addr:street":"Sartori Ave",
    "iso:country":"US",
    "sg:address":"29 Sartori Ave",
    "sg:city":"Mount Ephraim",
    "sg:classifiers":[
        {
            "category":"Building & Trades",
            "subcategory":"Construction",
            "type":"Services"
        }
    ],
    "sg:phone":"+1 856 933 2486",
    "sg:postcode":"08059",
    "sg:province":"NJ",
    "sg:tags":[
        "contractor"
    ],
    "wof:name":"New Generation Siding & Win Co",
    "wof:placetype":"venue"
},
  "geometry": {"coordinates":[-75.10054,39.881249],"type":"Point"}
}