{
  "type": "Feature",
  "properties": {
    "addr:full":"662 White Horse Pike Absecon NJ 08201",
    "addr:housenumber":"662",
    "addr:postcode":"08201",
    "addr:street":"White Horse Pike",
    "iso:country":"US",
    "sg:address":"662 White Horse Pike",
    "sg:city":"Absecon",
    "sg:classifiers":[
        {
            "category":"Restaurant",
            "type":"Food & Drink"
        }
    ],
    "sg:phone":"+1   ",
    "sg:postcode":"08201",
    "sg:province":"NJ",
    "sg:tags":[
        "cuisine",
        "chinese"
    ],
    "wof:name":"China Sea Of Absecon",
    "wof:placetype":"venue"
},
  "geometry": {"coordinates":[-74.51181200000001,39.43235],"type":"Point"}
}