{
  "type": "Feature",
  "properties": {
    "iso:country":"US",
    "sg:address":"133 Summit Ave",
    "sg:city":"Summit",
    "sg:classifiers":[
        {
            "category":"Professional",
            "subcategory":"Management & Consulting",
            "type":"Services"
        }
    ],
    "sg:phone":"+1 908 273 3443",
    "sg:postcode":"07901",
    "sg:province":"NJ",
    "sg:tags":[
        "property"
    ],
    "wof:name":"Rcp Management Co",
    "wof:placetype":"venue"
},
  "geometry": {"coordinates":[-74.35580400000001,40.719857],"type":"Point"}
}