{
  "type": "Feature",
  "properties": {
    "addr:full":"102 Mount Kemble Ave Morristown NJ 07960",
    "addr:housenumber":"102",
    "addr:postcode":"07960",
    "addr:street":"Mount Kemble Ave",
    "iso:country":"US",
    "sg:address":"102 Mount Kemble Ave",
    "sg:city":"Morristown",
    "sg:classifiers":[
        {
            "category":"Shopping",
            "subcategory":"Used Merchandise",
            "type":"Retail Goods"
        }
    ],
    "sg:phone":"+1   ",
    "sg:postcode":"07960",
    "sg:province":"NJ",
    "wof:name":"Bargain Box Thrift Shop",
    "wof:placetype":"venue"
},
  "geometry": {"coordinates":[-74.489137,40.789032],"type":"Point"}
}