{
  "type": "Feature",
  "properties": {
    "iso:country":"US",
    "sg:address":"1 Bethany Rd",
    "sg:city":"Hazlet",
    "sg:classifiers":[
        {
            "category":"Professional",
            "subcategory":"Computer Services",
            "type":"Services"
        }
    ],
    "sg:phone":"+1   ",
    "sg:postcode":"07730",
    "sg:province":"NJ",
    "sg:tags":[
        "development",
        "consulting",
        "software"
    ],
    "wof:name":"Saitech Inc",
    "wof:placetype":"venue"
},
  "geometry": {"coordinates":[-74.17793,40.417468],"type":"Point"}
}