{
  "type": "Feature",
  "properties": {
    "addr:full":"103 Park St Montclair NJ 07042",
    "addr:housenumber":"103",
    "addr:postcode":"07042",
    "addr:street":"Park St",
    "iso:country":"US",
    "sg:address":"103 Park St",
    "sg:city":"Montclair",
    "sg:classifiers":[
        {
            "category":"Health Services",
            "subcategory":"Doctor",
            "type":"Services"
        }
    ],
    "sg:phone":"+1 973 783 4117",
    "sg:postcode":"07042",
    "sg:province":"NJ",
    "sg:tags":[
        "physician",
        "surgeon"
    ],
    "wof:name":"Francis Berlingeri MD",
    "wof:placetype":"venue"
},
  "geometry": {"coordinates":[-74.213864,40.820451],"type":"Point"}
}