{
  "type": "Feature",
  "properties": {
    "addr:full":"64 Ridge Rd North Arlington NJ 07031",
    "addr:housenumber":"64",
    "addr:postcode":"07031",
    "addr:street":"Ridge Rd North",
    "iso:country":"US",
    "sg:address":"64 Ridge Rd",
    "sg:city":"North Arlington",
    "sg:classifiers":[
        {
            "category":"Health Services",
            "subcategory":"Dentist",
            "type":"Services"
        }
    ],
    "sg:phone":"+1 201 992 9172",
    "sg:postcode":"07031",
    "sg:province":"NJ",
    "wof:name":"Donald J Byk DMD PA",
    "wof:placetype":"venue"
},
  "geometry": {"coordinates":[-74.137001,40.783401],"type":"Point"}
}