{
  "type": "Feature",
  "properties": {
    "addr:full":"369 W Dewey Ave Wharton NJ 07885",
    "addr:housenumber":"369",
    "addr:postcode":"07885",
    "addr:street":"W Dewey Ave",
    "iso:country":"US",
    "sg:address":"369 W Dewey Ave",
    "sg:city":"Wharton",
    "sg:classifiers":[
        {
            "category":"Building & Trades",
            "subcategory":"Construction",
            "type":"Services"
        }
    ],
    "sg:phone":"+1 973 328 6465",
    "sg:postcode":"07885",
    "sg:province":"NJ",
    "sg:tags":[
        "hanging",
        "contractor"
    ],
    "wof:name":"Juan C Soto",
    "wof:placetype":"venue"
},
  "geometry": {"coordinates":[-74.607845,40.89933],"type":"Point"}
}