{
  "type": "Feature",
  "properties": {
    "addr:full":"334 Harding Hwy Penns Grove NJ 08069",
    "addr:housenumber":"334",
    "addr:postcode":"08069",
    "addr:street":"Harding Hwy",
    "iso:country":"US",
    "sg:address":"334 Harding Hwy",
    "sg:city":"Penns Grove",
    "sg:classifiers":[
        {
            "category":"Education",
            "subcategory":"School",
            "type":"Public Place"
        }
    ],
    "sg:phone":"+1 856 299 1909",
    "sg:postcode":"08069",
    "sg:province":"NJ",
    "sg:tags":[
        "special",
        "student",
        "for"
    ],
    "wof:name":"Salem County Spec Svcs School",
    "wof:placetype":"venue"
},
  "geometry": {"coordinates":[-75.454492,39.71656],"type":"Point"}
}