{
  "type": "Feature",
  "properties": {
    "iso:country":"US",
    "sg:address":"562 W Side Ave",
    "sg:city":"Jersey City",
    "sg:classifiers":[
        {
            "category":"Health Services",
            "subcategory":"Doctor",
            "type":"Services"
        }
    ],
    "sg:phone":"+1 201 434 7800",
    "sg:postcode":"07304",
    "sg:province":"NJ",
    "sg:tags":[
        "physician",
        "surgeon"
    ],
    "wof:name":"Newport Medical Assoc",
    "wof:placetype":"venue"
},
  "geometry": {"coordinates":[-74.082171,40.719657],"type":"Point"}
}