{
  "type": "Feature",
  "properties": {
    "iso:country":"US",
    "sg:address":"1000 82nd St",
    "sg:city":"North Bergen",
    "sg:classifiers":[
        {
            "category":"Wholesale",
            "subcategory":"Home Furnishings",
            "type":"Manufacturing & Wholesale Goods"
        }
    ],
    "sg:phone":"+1 201 861 6554",
    "sg:postcode":"07047",
    "sg:province":"NJ",
    "wof:name":"Skyline Verticals Inc",
    "wof:placetype":"venue"
},
  "geometry": {"coordinates":[-74.010059,40.805688],"type":"Point"}
}