{
  "type": "Feature",
  "properties": {
    "iso:country":"US",
    "sg:address":"65 Hudson St",
    "sg:city":"Hackensack",
    "sg:classifiers":[
        {
            "category":"Professional",
            "type":"Services"
        }
    ],
    "sg:phone":"+1 201 489 1918",
    "sg:postcode":"07601",
    "sg:province":"NJ",
    "sg:tags":[
        "establishment"
    ],
    "wof:name":"John Magic Abstractor",
    "wof:placetype":"venue"
},
  "geometry": {"coordinates":[-74.043397,40.876437],"type":"Point"}
}