{
  "type": "Feature",
  "properties": {
    "addr:full":"6 Benedek Rd Princeton NJ 08540",
    "addr:housenumber":"6",
    "addr:postcode":"08540",
    "addr:street":"Benedek Rd",
    "iso:country":"US",
    "sg:address":"6 Benedek Rd",
    "sg:city":"Princeton",
    "sg:classifiers":[
        {
            "category":"Banks & Credit Unions",
            "subcategory":"Financial Services",
            "type":"Services"
        }
    ],
    "sg:phone":"+1   ",
    "sg:postcode":"08540",
    "sg:province":"NJ",
    "sg:tags":[
        "company",
        "holding"
    ],
    "wof:name":"Jdt Holding Corp",
    "wof:placetype":"venue"
},
  "geometry": {"coordinates":[-74.71498699999999,40.337286],"type":"Point"}
}