{
  "type": "Feature",
  "properties": {
    "iso:country":"US",
    "sg:address":"3 Juniper Dr",
    "sg:city":"Mount Laurel",
    "sg:classifiers":[
        {
            "category":"Professional",
            "type":"Services"
        }
    ],
    "sg:phone":"+1   ",
    "sg:postcode":"08054",
    "sg:province":"NJ",
    "wof:name":"Svet Services",
    "wof:placetype":"venue"
},
  "geometry": {"coordinates":[-74.92193899999999,39.936402],"type":"Point"}
}