{
  "type": "Feature",
  "properties": {
    "iso:country":"US",
    "sg:address":"100 Piermont Rd",
    "sg:city":"Norwood",
    "sg:classifiers":[
        {
            "category":"Restaurant",
            "type":"Food & Drink"
        }
    ],
    "sg:menulink":"http://www.allmenus.com/nj/norwood/23919-dimora/menu/",
    "sg:phone":"+1 201 750 5000",
    "sg:postcode":"07648",
    "sg:province":"NJ",
    "sg:tags":[
        "italian"
    ],
    "wof:name":"Dimora",
    "wof:placetype":"venue"
},
  "geometry": {"coordinates":[-73.93808,40.984263],"type":"Point"}
}