{
  "type": "Feature",
  "properties": {
    "addr:full":"15 W Erie Ave Rutherford NJ 07070",
    "addr:housenumber":"15",
    "addr:postcode":"07070",
    "addr:street":"W Erie Ave",
    "iso:country":"US",
    "sg:address":"15 W Erie Ave",
    "sg:city":"Rutherford",
    "sg:classifiers":[
        {
            "category":"Food & Beverages",
            "subcategory":"Specialty",
            "type":"Retail Goods"
        }
    ],
    "sg:phone":"+1   ",
    "sg:postcode":"07070",
    "sg:province":"NJ",
    "wof:name":"Zen Studio Inc",
    "wof:placetype":"venue"
},
  "geometry": {"coordinates":[-74.101584,40.829816],"type":"Point"}
}