{
  "type": "Feature",
  "properties": {
    "addr:full":"1402 Saxony Dr Mount Laurel NJ 08054",
    "addr:housenumber":"1402",
    "addr:postcode":"08054",
    "addr:street":"Saxony Dr",
    "iso:country":"US",
    "sg:address":"1402 Saxony Dr",
    "sg:city":"Mount Laurel",
    "sg:classifiers":[
        {
            "category":"Professional",
            "subcategory":"Engineering",
            "type":"Services"
        }
    ],
    "sg:phone":"+1   ",
    "sg:postcode":"08054",
    "sg:province":"NJ",
    "wof:name":"Bernal Associates",
    "wof:placetype":"venue"
},
  "geometry": {"coordinates":[-74.87639900000001,39.976532],"type":"Point"}
}