{
  "type": "Feature",
  "properties": {
    "addr:full":"1 Crabbe Rd Toms River NJ 08757",
    "addr:housenumber":"1",
    "addr:postcode":"08757",
    "addr:street":"Crabbe Rd",
    "iso:country":"US",
    "sg:address":"1 Crabbe Rd",
    "sg:city":"Toms River",
    "sg:classifiers":[
        {
            "category":"Recreation",
            "subcategory":"Marina",
            "type":"Entertainment"
        }
    ],
    "sg:phone":"+1 732 341 1105",
    "sg:postcode":"08757",
    "sg:province":"NJ",
    "wof:name":"Lighthouse Point Marina",
    "wof:placetype":"venue"
},
  "geometry": {"coordinates":[-74.19350799999999,39.945872],"type":"Point"}
}