{
  "type": "Feature",
  "properties": {
    "iso:country":"US",
    "sg:address":"55 Horse Hill Rd",
    "sg:city":"Cedar Knolls",
    "sg:classifiers":[
        {
            "category":"Travel",
            "subcategory":"Travel Agent",
            "type":"Entertainment"
        }
    ],
    "sg:phone":"+1 973 538 1641",
    "sg:postcode":"07927",
    "sg:province":"NJ",
    "sg:tags":[
        "tours",
        "promoter"
    ],
    "wof:name":"Tour Bus Inc",
    "wof:placetype":"venue"
},
  "geometry": {"coordinates":[-74.45754599999999,40.816405],"type":"Point"}
}