{
  "type": "Feature",
  "properties": {
    "addr:full":"1205 Klockner Rd Trenton NJ 08619",
    "addr:housenumber":"1205",
    "addr:postcode":"08619",
    "addr:street":"Klockner Rd",
    "iso:country":"US",
    "sg:address":"1205 Klockner Rd",
    "sg:city":"Trenton",
    "sg:classifiers":[
        {
            "category":"Retail",
            "subcategory":"Laundry & Dry Cleaning",
            "type":"Services"
        }
    ],
    "sg:phone":"+1   ",
    "sg:postcode":"08619",
    "sg:province":"NJ",
    "wof:name":"Gaters Carpet Service",
    "wof:placetype":"venue"
},
  "geometry": {"coordinates":[-74.705288,40.22787],"type":"Point"}
}