{
  "type": "Feature",
  "properties": {
    "addr:full":"95 Mount Kemble Ave Morristown NJ 07960",
    "addr:housenumber":"95",
    "addr:postcode":"07960",
    "addr:street":"Mount Kemble Ave",
    "iso:country":"US",
    "sg:address":"95 Mount Kemble Ave",
    "sg:city":"Morristown",
    "sg:classifiers":[
        {
            "category":"Health Services",
            "subcategory":"Clinic",
            "type":"Services"
        },
        {
            "category":"Organizations",
            "subcategory":"Non-profit Organization",
            "type":"Services"
        }
    ],
    "sg:phone":"+1 973 971 4575",
    "sg:postcode":"07960",
    "sg:province":"NJ",
    "sg:tags":[
        "yoga",
        "holistic",
        "practitioner",
        "social"
    ],
    "wof:name":"Atlantic Mind Body Center",
    "wof:placetype":"venue"
},
  "geometry": {"coordinates":[-74.4888,40.7892],"type":"Point"}
}