{
  "type": "Feature",
  "properties": {
    "iso:country":"US",
    "sg:address":"701 New York Ave",
    "sg:city":"Union City",
    "sg:classifiers":[
        {
            "category":"Personal",
            "subcategory":"Beauty Salon",
            "type":"Services"
        }
    ],
    "sg:phone":"+1 201 867 5911",
    "sg:postcode":"07087",
    "sg:province":"NJ",
    "sg:tags":[
        "shop"
    ],
    "wof:name":"Chachis Beauty Salon",
    "wof:placetype":"venue"
},
  "geometry": {"coordinates":[-74.037846,40.756689],"type":"Point"}
}