{
  "type": "Feature",
  "properties": {
    "iso:country":"US",
    "sg:address":"810 Sunset Rd",
    "sg:city":"Burlington",
    "sg:classifiers":[
        {
            "category":"Retail",
            "subcategory":"Portrait Studio",
            "type":"Services"
        },
        {
            "category":"Shopping",
            "subcategory":"Pharmacy",
            "type":"Retail Goods"
        }
    ],
    "sg:phone":"+1 609 239 0922",
    "sg:postcode":"08016",
    "sg:province":"NJ",
    "sg:tags":[
        "photography",
        "drugstore",
        "store"
    ],
    "wof:name":"Eckerd Express Photo",
    "wof:placetype":"venue"
},
  "geometry": {"coordinates":[-74.8535,40.050098],"type":"Point"}
}