{
  "type": "Feature",
  "properties": {
    "iso:country":"US",
    "sg:address":"120 Passaic Ave",
    "sg:city":"Fairfield",
    "sg:classifiers":[
        {
            "category":"Banks & Credit Unions",
            "subcategory":"Bank",
            "type":"Services"
        }
    ],
    "sg:phone":"+1 973 575 7794",
    "sg:postcode":"07004",
    "sg:province":"NJ",
    "sg:website":"www.kearnyfederalsavings.com",
    "wof:name":"Kearny Federal Savings Bank",
    "wof:placetype":"venue"
},
  "geometry": {"coordinates":[-74.278051,40.872838],"type":"Point"}
}