{
  "type": "Feature",
  "properties": {
    "iso:country":"US",
    "sg:address":"103 Kline Blvd",
    "sg:city":"Berkeley Heights",
    "sg:classifiers":[
        {
            "category":"Building & Trades",
            "subcategory":"Construction",
            "type":"Services"
        }
    ],
    "sg:phone":"+1 908 665 9561",
    "sg:postcode":"07922",
    "sg:province":"NJ",
    "sg:tags":[
        "house"
    ],
    "wof:name":"Ray Nicastro Home Improvements",
    "wof:placetype":"venue"
},
  "geometry": {"coordinates":[-74.423374,40.685963],"type":"Point"}
}