{
  "type": "Feature",
  "properties": {
    "addr:full":"415 Worthington Ave Spring Lake NJ 07762",
    "addr:housenumber":"415",
    "addr:postcode":"07762",
    "addr:street":"Worthington Ave",
    "iso:country":"US",
    "sg:address":"415 Worthington Ave",
    "sg:city":"Spring Lake",
    "sg:classifiers":[
        {
            "category":"Shopping",
            "type":"Retail Goods"
        }
    ],
    "sg:phone":"+1 732 449 7299",
    "sg:postcode":"07762",
    "sg:province":"NJ",
    "sg:tags":[
        "awning",
        "canopy"
    ],
    "wof:name":"Coastal Awning Svc",
    "wof:placetype":"venue"
},
  "geometry": {"coordinates":[-74.032425,40.15948],"type":"Point"}
}