{
  "type": "Feature",
  "properties": {
    "iso:country":"US",
    "sg:address":"2668 Morris Ave",
    "sg:city":"Union",
    "sg:classifiers":[
        {
            "category":"Health Services",
            "subcategory":"Doctor",
            "type":"Services"
        }
    ],
    "sg:phone":"+1   ",
    "sg:postcode":"07083",
    "sg:province":"NJ",
    "sg:tags":[
        "medical"
    ],
    "wof:name":"Esculap",
    "wof:placetype":"venue"
},
  "geometry": {"coordinates":[-74.292911,40.703513],"type":"Point"}
}