{
  "type": "Feature",
  "properties": {
    "iso:country":"US",
    "sg:address":"231 Atlantic City Blvd",
    "sg:city":"Bayville",
    "sg:classifiers":[
        {
            "category":"Real Estate",
            "subcategory":"Real Estate Agent",
            "type":"Services"
        }
    ],
    "sg:phone":"+1 732 269 8589",
    "sg:postcode":"08721",
    "sg:province":"NJ",
    "wof:name":"Ann Schuld Realty",
    "wof:placetype":"venue"
},
  "geometry": {"coordinates":[-74.167643,39.923532],"type":"Point"}
}