{
  "type": "Feature",
  "properties": {
    "addr:full":"107 17th Ave Elmwood Park NJ 07407",
    "addr:housenumber":"107",
    "addr:postcode":"07407",
    "addr:street":"17Th Ave",
    "iso:country":"US",
    "sg:address":"107 17th Ave",
    "sg:city":"Elmwood Park",
    "sg:classifiers":[
        {
            "category":"Professional",
            "subcategory":"Management & Consulting",
            "type":"Services"
        }
    ],
    "sg:phone":"+1   ",
    "sg:postcode":"07407",
    "sg:province":"NJ",
    "sg:tags":[
        "business"
    ],
    "wof:name":"Mrk Consulting LLC",
    "wof:placetype":"venue"
},
  "geometry": {"coordinates":[-74.116687,40.917672],"type":"Point"}
}