{
  "type": "Feature",
  "properties": {
    "addr:full":"7508 Hana Rd Edison NJ 08817",
    "addr:housenumber":"7508",
    "addr:postcode":"08817",
    "addr:street":"Hana Rd",
    "iso:country":"US",
    "sg:address":"7508 Hana Rd",
    "sg:city":"Edison",
    "sg:classifiers":[
        {
            "category":"Professional",
            "subcategory":"Computer Services",
            "type":"Services"
        }
    ],
    "sg:phone":"+1   ",
    "sg:postcode":"08817",
    "sg:province":"NJ",
    "sg:tags":[
        "software"
    ],
    "wof:name":"DSM Software Inc",
    "wof:placetype":"venue"
},
  "geometry": {"coordinates":[-74.410556,40.534971],"type":"Point"}
}