{
  "type": "Feature",
  "properties": {
    "addr:full":"297 Columbus Pl New Brunswick NJ 08901",
    "addr:housenumber":"297",
    "addr:postcode":"08901",
    "addr:street":"Columbus Pl",
    "iso:country":"US",
    "sg:address":"297 Columbus Pl",
    "sg:city":"New Brunswick",
    "sg:classifiers":[
        {
            "category":"Professional",
            "subcategory":"Business Services",
            "type":"Services"
        }
    ],
    "sg:phone":"+1   ",
    "sg:postcode":"08901",
    "sg:province":"NJ",
    "sg:tags":[
        "production",
        "music"
    ],
    "wof:name":"Shaynorth Production",
    "wof:placetype":"venue"
},
  "geometry": {"coordinates":[-74.456672,40.485353],"type":"Point"}
}