{
  "type": "Feature",
  "properties": {
    "iso:country":"US",
    "sg:address":"408 Howard Rd",
    "sg:city":"Cherry Hill",
    "sg:classifiers":[
        {
            "category":"Professional",
            "subcategory":"Accounting & Tax Preparation",
            "type":"Services"
        }
    ],
    "sg:phone":"+1 856 667 5308",
    "sg:postcode":"08034",
    "sg:province":"NJ",
    "sg:tags":[
        "bookkeeping",
        "general"
    ],
    "wof:name":"Tjd Inc",
    "wof:placetype":"venue"
},
  "geometry": {"coordinates":[-74.988173,39.919235],"type":"Point"}
}