{
  "type": "Feature",
  "properties": {
    "addr:full":"373 Westfield Ave W Roselle Park NJ 07204",
    "addr:housenumber":"373",
    "addr:postcode":"07204",
    "addr:street":"Westfield Ave W",
    "iso:country":"US",
    "sg:address":"373 Westfield Ave W",
    "sg:city":"Roselle Park",
    "sg:classifiers":[
        {
            "category":"Building & Trades",
            "subcategory":"Construction",
            "type":"Services"
        }
    ],
    "sg:phone":"+1 908 232 3737",
    "sg:postcode":"07204",
    "sg:province":"NJ",
    "sg:tags":[
        "masonry",
        "contractor"
    ],
    "wof:name":"Mark Jameson Chimney",
    "wof:placetype":"venue"
},
  "geometry": {"coordinates":[-74.275671,40.660165],"type":"Point"}
}