{
  "type": "Feature",
  "properties": {
    "iso:country":"US",
    "sg:address":"637 Wyckoff Ave",
    "sg:city":"Wyckoff",
    "sg:classifiers":[
        {
            "category":"Building & Trades",
            "subcategory":"Electrical",
            "type":"Services"
        }
    ],
    "sg:phone":"+1 201 848 4800",
    "sg:postcode":"07481",
    "sg:province":"NJ",
    "sg:tags":[
        "electrician"
    ],
    "wof:name":"New Baldwin Associates Llc Fdn",
    "wof:placetype":"venue"
},
  "geometry": {"coordinates":[-74.172786,41.010754],"type":"Point"}
}