{
  "type": "Feature",
  "properties": {
    "iso:country":"US",
    "sg:address":"51 E Station Rd",
    "sg:city":"Ocean City",
    "sg:classifiers":[
        {
            "category":"Professional",
            "subcategory":"Credit Reporting & Collection",
            "type":"Services"
        }
    ],
    "sg:phone":"+1 609 398 2400",
    "sg:postcode":"08226",
    "sg:province":"NJ",
    "wof:name":"Transworld Systems Inc",
    "wof:placetype":"venue"
},
  "geometry": {"coordinates":[-74.563678,39.289904],"type":"Point"}
}