{
  "type": "Feature",
  "properties": {
    "addr:full":"42 Cranbury Neck Rd Cranbury NJ 08512",
    "addr:housenumber":"42",
    "addr:postcode":"08512",
    "addr:street":"Cranbury Neck Rd",
    "iso:country":"US",
    "sg:address":"42 Cranbury Neck Rd",
    "sg:city":"Cranbury",
    "sg:classifiers":[
        {
            "category":"Building & Trades",
            "subcategory":"Landscaping Services",
            "type":"Services"
        }
    ],
    "sg:phone":"+1 609 395 1441",
    "sg:postcode":"08512",
    "sg:province":"NJ",
    "wof:name":"R & H Landscaping & Excavation",
    "wof:placetype":"venue"
},
  "geometry": {"coordinates":[-74.538259,40.307033],"type":"Point"}
}