{
  "type": "Feature",
  "properties": {
    "addr:full":"101 Carnegie Center Princeton NJ 08540",
    "addr:housenumber":"101",
    "addr:postcode":"08540",
    "addr:street":"Carnegie Center",
    "iso:country":"US",
    "sg:address":"101 Carnegie Center",
    "sg:city":"Princeton",
    "sg:classifiers":[
        {
            "category":"Real Estate",
            "subcategory":"Real Estate Operator",
            "type":"Services"
        }
    ],
    "sg:phone":"+1   ",
    "sg:postcode":"08540",
    "sg:province":"NJ",
    "sg:tags":[
        "property",
        "commercial"
    ],
    "wof:name":"Carnegie Center Deli",
    "wof:placetype":"venue"
},
  "geometry": {"coordinates":[-74.65122,40.313508],"type":"Point"}
}