{
  "type": "Feature",
  "properties": {
    "addr:full":"17 W Palisade Ave Englewood NJ 07631",
    "addr:housenumber":"17",
    "addr:postcode":"07631",
    "addr:street":"W Palisade Ave",
    "iso:country":"US",
    "sg:address":"17 W Palisade Ave",
    "sg:city":"Englewood",
    "sg:classifiers":[
        {
            "category":"Shopping",
            "subcategory":"Clothing, Apparel, & Fashions",
            "type":"Retail Goods"
        }
    ],
    "sg:phone":"+1 201 568 6566",
    "sg:postcode":"07631",
    "sg:province":"NJ",
    "sg:tags":[
        "lingerie"
    ],
    "wof:name":"Victoria's Secret",
    "wof:placetype":"venue"
},
  "geometry": {"coordinates":[-73.97556899999999,40.894381],"type":"Point"}
}