{
  "type": "Feature",
  "properties": {
    "addr:full":"2965 US Hwy 9 Howell NJ 07731",
    "addr:housenumber":"2965",
    "addr:postcode":"07731",
    "addr:street":"Us Hwy 9",
    "iso:country":"US",
    "sg:address":"2965 US Hwy 9",
    "sg:city":"Howell",
    "sg:classifiers":[
        {
            "category":"Communications",
            "type":"Services"
        }
    ],
    "sg:phone":"+1 732 905 9898",
    "sg:postcode":"07731",
    "sg:province":"NJ",
    "wof:name":"Communications Depot",
    "wof:placetype":"venue"
},
  "geometry": {"coordinates":[-74.237838,40.168914],"type":"Point"}
}