{
  "type": "Feature",
  "properties": {
    "addr:full":"12 E Saddle River Rd Saddle River NJ 07458",
    "addr:housenumber":"12",
    "addr:postcode":"07458",
    "addr:street":"E Saddle River Rd",
    "iso:country":"US",
    "sg:address":"12 E Saddle River Rd",
    "sg:city":"Saddle River",
    "sg:classifiers":[
        {
            "category":"Health Services",
            "subcategory":"Nursing And Care Facility",
            "type":"Services"
        }
    ],
    "sg:phone":"+1 201 327 1325",
    "sg:postcode":"07458",
    "sg:province":"NJ",
    "sg:tags":[
        "home",
        "retirement",
        "community"
    ],
    "wof:name":"Villa Marie Claire",
    "wof:placetype":"venue"
},
  "geometry": {"coordinates":[-74.09510899999999,41.010086],"type":"Point"}
}