{
  "type": "Feature",
  "properties": {
    "addr:full":"823 State Rte 33 Freehold NJ 07728",
    "addr:housenumber":"823",
    "addr:postcode":"07728",
    "addr:street":"State Rte 33",
    "iso:country":"US",
    "sg:address":"823 State Rte 33",
    "sg:city":"Freehold",
    "sg:classifiers":[
        {
            "category":"Building & Trades",
            "subcategory":"Plumbing",
            "type":"Services"
        }
    ],
    "sg:phone":"+1 732 462 7800",
    "sg:postcode":"07728",
    "sg:province":"NJ",
    "sg:tags":[
        "system",
        "heating",
        "air",
        "ventilation",
        "conditioning",
        "contractor"
    ],
    "sg:website":"www.gardenstateac.com",
    "wof:name":"Garden State Air Conditioning",
    "wof:placetype":"venue"
},
  "geometry": {"coordinates":[-74.219272,40.233766],"type":"Point"}
}