{
  "type": "Feature",
  "properties": {
    "iso:country":"US",
    "sg:address":"2700 Allaire Rd",
    "sg:city":"Wall Township",
    "sg:classifiers":[
        {
            "category":"Government",
            "subcategory":"Police Station",
            "type":"Public Place"
        }
    ],
    "sg:phone":"+1 732 449 8774",
    "sg:postcode":"07719",
    "sg:province":"NJ",
    "sg:tags":[
        "department"
    ],
    "sg:website":"www.wallpolice.org",
    "wof:name":"Wall Twp Police Adm",
    "wof:placetype":"venue"
},
  "geometry": {"coordinates":[-74.065235,40.15278],"type":"Point"}
}