{
  "type": "Feature",
  "properties": {
    "iso:country":"US",
    "sg:address":"755 S Orange Ave",
    "sg:city":"Newark",
    "sg:classifiers":[
        {
            "category":"Social Services",
            "type":"Services"
        }
    ],
    "sg:phone":"+1 973 484 4446",
    "sg:postcode":"07106",
    "sg:province":"NJ",
    "sg:tags":[
        "organization",
        "welfare"
    ],
    "wof:name":"Battered Women's Svc",
    "wof:placetype":"venue"
},
  "geometry": {"coordinates":[-74.21492499999999,40.745022],"type":"Point"}
}