{
  "type": "Feature",
  "properties": {
    "iso:country":"US",
    "sg:address":"5552 Marlton Pike",
    "sg:city":"Pennsauken",
    "sg:classifiers":[
        {
            "category":"Professional",
            "subcategory":"Management & Consulting",
            "type":"Services"
        }
    ],
    "sg:phone":"+1 856 486 4929",
    "sg:postcode":"08109",
    "sg:province":"NJ",
    "sg:tags":[
        "food"
    ],
    "wof:name":"Navin Brothers Food Svc Inc",
    "wof:placetype":"venue"
},
  "geometry": {"coordinates":[-75.058942,39.929182],"type":"Point"}
}