{
  "type": "Feature",
  "properties": {
    "addr:full":"107 W Branch Ave Clementon NJ 08021",
    "addr:housenumber":"107",
    "addr:postcode":"08021",
    "addr:street":"W Branch Ave",
    "iso:country":"US",
    "sg:address":"107 W Branch Ave",
    "sg:city":"Clementon",
    "sg:classifiers":[
        {
            "category":"Personal",
            "subcategory":"Beauty Salon",
            "type":"Services"
        }
    ],
    "sg:phone":"+1 856 346 0046",
    "sg:postcode":"08021",
    "sg:province":"NJ",
    "sg:tags":[
        "shop"
    ],
    "wof:name":"Eileen's Magic Touch",
    "wof:placetype":"venue"
},
  "geometry": {"coordinates":[-74.994601,39.78744],"type":"Point"}
}