{
  "type": "Feature",
  "properties": {
    "iso:country":"US",
    "sg:address":"25 Ironia Rd",
    "sg:city":"Flanders",
    "sg:classifiers":[
        {
            "category":"Food & Beverages",
            "subcategory":"Dairy",
            "type":"Retail Goods"
        },
        {
            "category":"Restaurant",
            "type":"Food & Drink"
        }
    ],
    "sg:phone":"+1 973 252 7400",
    "sg:postcode":"07836",
    "sg:province":"NJ",
    "sg:tags":[
        "product",
        "parlor",
        "ice",
        "cream"
    ],
    "wof:name":"Chilly Willy's Ice Cream Co",
    "wof:placetype":"venue"
},
  "geometry": {"coordinates":[-74.66288299999999,40.834409],"type":"Point"}
}