{
  "type": "Feature",
  "properties": {
    "iso:country":"US",
    "sg:address":"7 Jewell St",
    "sg:city":"Garfield",
    "sg:classifiers":[
        {
            "category":"Wholesale",
            "subcategory":"Home Furnishings",
            "type":"Manufacturing & Wholesale Goods"
        }
    ],
    "sg:phone":"+1 973 478 3900",
    "sg:postcode":"07026",
    "sg:province":"NJ",
    "sg:tags":[
        "blind",
        "shade"
    ],
    "wof:name":"C-Mor Co the",
    "wof:placetype":"venue"
},
  "geometry": {"coordinates":[-74.118202,40.880402],"type":"Point"}
}