{
  "type": "Feature",
  "properties": {
    "iso:country":"US",
    "sg:address":"930 N Wood Ave",
    "sg:city":"Linden",
    "sg:classifiers":[
        {
            "category":"Real Estate",
            "subcategory":"Real Estate Services",
            "type":"Services"
        }
    ],
    "sg:phone":"+1   ",
    "sg:postcode":"07036",
    "sg:province":"NJ",
    "sg:tags":[
        "abstract",
        "title"
    ],
    "wof:name":"Counselors Title Agency Inc",
    "wof:placetype":"venue"
},
  "geometry": {"coordinates":[-74.26386100000001,40.636951],"type":"Point"}
}