{
  "type": "Feature",
  "properties": {
    "iso:country":"US",
    "sg:address":"485 Birchwood Rd",
    "sg:city":"Northvale",
    "sg:classifiers":[
        {
            "category":"Professional",
            "subcategory":"Detective & Security Services",
            "type":"Services"
        }
    ],
    "sg:phone":"+1 201 248 3790",
    "sg:postcode":"07647",
    "sg:province":"NJ",
    "sg:tags":[
        "information",
        "bureau"
    ],
    "wof:name":"M3 System Services",
    "wof:placetype":"venue"
},
  "geometry": {"coordinates":[-73.95192,41.016365],"type":"Point"}
}