{
  "type": "Feature",
  "properties": {
    "addr:full":"100 Mulberry St Newark NJ 07102",
    "addr:housenumber":"100",
    "addr:postcode":"07102",
    "addr:street":"Mulberry St",
    "iso:country":"US",
    "sg:address":"100 Mulberry St",
    "sg:city":"Newark",
    "sg:classifiers":[
        {
            "category":"Real Estate",
            "subcategory":"Real Estate Agent",
            "type":"Services"
        }
    ],
    "sg:phone":"+1   ",
    "sg:postcode":"07102",
    "sg:province":"NJ",
    "wof:name":"Hampton Realty",
    "wof:placetype":"venue"
},
  "geometry": {"coordinates":[-74.16852,40.736],"type":"Point"}
}