{
  "type": "Feature",
  "properties": {
    "addr:full":"388 Sicomac Ave Wyckoff NJ 07481",
    "addr:housenumber":"388",
    "addr:postcode":"07481",
    "addr:street":"Sicomac Ave",
    "iso:country":"US",
    "sg:address":"388 Sicomac Ave",
    "sg:city":"Wyckoff",
    "sg:classifiers":[
        {
            "category":"Retail",
            "subcategory":"Animal Services",
            "type":"Services"
        }
    ],
    "sg:phone":"+1 201 891 4233",
    "sg:postcode":"07481",
    "sg:province":"NJ",
    "wof:name":"Waterways Iws",
    "wof:placetype":"venue"
},
  "geometry": {"coordinates":[-74.178957,40.989032],"type":"Point"}
}