{
  "type": "Feature",
  "properties": {
    "addr:full":"202 Mountain Ave Hackettstown NJ 07840",
    "addr:housenumber":"202",
    "addr:postcode":"07840",
    "addr:street":"Mountain Ave",
    "iso:country":"US",
    "sg:address":"202 Mountain Ave",
    "sg:city":"Hackettstown",
    "sg:classifiers":[
        {
            "category":"Restaurant",
            "type":"Food & Drink"
        }
    ],
    "sg:menulink":"http://www.allmenus.com/nj/hackettstown/194773-mcdonalds/menu/",
    "sg:phone":"+1 908 852 3857",
    "sg:postcode":"07840",
    "sg:province":"NJ",
    "sg:tags":[
        "burger",
        "american"
    ],
    "wof:name":"McDonald's",
    "wof:placetype":"venue"
},
  "geometry": {"coordinates":[-74.823883,40.840959],"type":"Point"}
}