{
  "type": "Feature",
  "properties": {
    "addr:full":"1015 Bergenline Ave Union City NJ 07087",
    "addr:housenumber":"1015",
    "addr:postcode":"07087",
    "addr:street":"Bergenline Ave",
    "iso:country":"US",
    "sg:address":"1015 Bergenline Ave",
    "sg:city":"Union City",
    "sg:classifiers":[
        {
            "category":"Freight",
            "type":"Transportation"
        }
    ],
    "sg:phone":"+1 212 594 3452",
    "sg:postcode":"07087",
    "sg:province":"NJ",
    "sg:tags":[
        "packing",
        "crating"
    ],
    "wof:name":"Tobe Packing Co Inc",
    "wof:placetype":"venue"
},
  "geometry": {"coordinates":[-74.03825000000001,40.758795],"type":"Point"}
}