{
  "type": "Feature",
  "properties": {
    "iso:country":"US",
    "sg:address":"1441 Chester Ave",
    "sg:city":"Lakehurst",
    "sg:classifiers":[
        {
            "category":"Health Services",
            "subcategory":"Hospital",
            "type":"Services"
        }
    ],
    "sg:phone":"+1 732 849 9078",
    "sg:postcode":"08759",
    "sg:province":"NJ",
    "sg:tags":[
        "general"
    ],
    "wof:name":"Sisters In Faith",
    "wof:placetype":"venue"
},
  "geometry": {"coordinates":[-74.380464,39.918901],"type":"Point"}
}