{
  "type": "Feature",
  "properties": {
    "iso:country":"US",
    "sg:address":"2113 Springfield Ave",
    "sg:city":"Vauxhall",
    "sg:classifiers":[
        {
            "category":"Food & Beverages",
            "subcategory":"Groceries & Convenience Stores",
            "type":"Retail Goods"
        }
    ],
    "sg:phone":"+1 908 206 1639",
    "sg:postcode":"07088",
    "sg:province":"NJ",
    "sg:tags":[
        "grocer"
    ],
    "wof:name":"J & M Deli & Grocery",
    "wof:placetype":"venue"
},
  "geometry": {"coordinates":[-74.28011600000001,40.719029],"type":"Point"}
}