{
  "type": "Feature",
  "properties": {
    "iso:country":"US",
    "sg:address":"183 2nd St",
    "sg:city":"Elizabeth",
    "sg:classifiers":[
        {
            "category":"Food & Beverages",
            "subcategory":"Groceries & Convenience Stores",
            "type":"Retail Goods"
        }
    ],
    "sg:phone":"+1   ",
    "sg:postcode":"07206",
    "sg:province":"NJ",
    "wof:name":"Billar Supermarket",
    "wof:placetype":"venue"
},
  "geometry": {"coordinates":[-74.18590399999999,40.651875],"type":"Point"}
}