{
  "type": "Feature",
  "properties": {
    "iso:country":"US",
    "sg:address":"3221 Bergenline Ave",
    "sg:city":"Union City",
    "sg:classifiers":[
        {
            "category":"Professional",
            "subcategory":"Lawyer & Legal Services",
            "type":"Services"
        }
    ],
    "sg:phone":"+1 201 617 8595",
    "sg:postcode":"07087",
    "sg:province":"NJ",
    "wof:name":"Congett Horacio R ESQ",
    "wof:placetype":"venue"
},
  "geometry": {"coordinates":[-74.02919799999999,40.772202],"type":"Point"}
}