{
  "type": "Feature",
  "properties": {
    "iso:country":"US",
    "sg:address":"401 Omni Dr",
    "sg:city":"Somerville",
    "sg:classifiers":[
        {
            "category":"Professional",
            "subcategory":"Computer Services",
            "type":"Services"
        }
    ],
    "sg:phone":"+1   ",
    "sg:postcode":"08844",
    "sg:province":"NJ",
    "sg:tags":[
        "consultant"
    ],
    "wof:name":"Medical Manager Health Systems",
    "wof:placetype":"venue"
},
  "geometry": {"coordinates":[-74.629071,40.524378],"type":"Point"}
}