{
  "type": "Feature",
  "properties": {
    "iso:country":"US",
    "sg:address":"554 Bloomfield Ave",
    "sg:city":"Newark",
    "sg:classifiers":[
        {
            "category":"Health Services",
            "subcategory":"Doctor",
            "type":"Services"
        },
        {
            "category":"Health Services",
            "subcategory":"Chiropractor",
            "type":"Services"
        }
    ],
    "sg:phone":"+1 973 483 2277",
    "sg:postcode":"07107",
    "sg:province":"NJ",
    "sg:tags":[
        "medicine",
        "internal",
        "orthopedist",
        "psychiatrist"
    ],
    "wof:name":"Suburban Orthopedic At Medical Center Llc",
    "wof:placetype":"venue"
},
  "geometry": {"coordinates":[-74.185799,40.7742],"type":"Point"}
}