{
  "type": "Feature",
  "properties": {
    "iso:country":"US",
    "sg:address":"55 Morris Ave",
    "sg:city":"Springfield",
    "sg:classifiers":[
        {
            "category":"Professional",
            "subcategory":"Lawyer & Legal Services",
            "type":"Services"
        }
    ],
    "sg:phone":"+1 973 467 9204",
    "sg:postcode":"07081",
    "sg:province":"NJ",
    "wof:name":"Glen J Vida PC",
    "wof:placetype":"venue"
},
  "geometry": {"coordinates":[-74.304445,40.708812],"type":"Point"}
}