{
  "type": "Feature",
  "properties": {
    "iso:country":"US",
    "sg:address":"460 Grove St",
    "sg:city":"Irvington",
    "sg:classifiers":[
        {
            "category":"Shopping",
            "subcategory":"Clothing, Apparel, & Fashions",
            "type":"Retail Goods"
        }
    ],
    "sg:phone":"+1 973 351 8855",
    "sg:postcode":"07111",
    "sg:province":"NJ",
    "sg:tags":[
        "tailor"
    ],
    "wof:name":"All N One",
    "wof:placetype":"venue"
},
  "geometry": {"coordinates":[-74.212272,40.740849],"type":"Point"}
}