{
  "type": "Feature",
  "properties": {
    "iso:country":"US",
    "sg:address":"6200 Monroe Pl",
    "sg:city":"West New York",
    "sg:classifiers":[
        {
            "category":"Organizations",
            "subcategory":"Community Association",
            "type":"Services"
        }
    ],
    "sg:phone":"+1 201 854 9425",
    "sg:postcode":"07093",
    "sg:province":"NJ",
    "wof:name":"Independent Order of Odd",
    "wof:placetype":"venue"
},
  "geometry": {"coordinates":[-74.010986,40.7904],"type":"Point"}
}