{
  "type": "Feature",
  "properties": {
    "iso:country":"US",
    "sg:address":"116 Jackson Ave",
    "sg:city":"Rutherford",
    "sg:classifiers":[
        {
            "category":"Retail",
            "subcategory":"Self-service Laundry",
            "type":"Services"
        }
    ],
    "sg:phone":"+1 201 460 0101",
    "sg:postcode":"07070",
    "sg:province":"NJ",
    "wof:name":"Clothes Encounters",
    "wof:placetype":"venue"
},
  "geometry": {"coordinates":[-74.116878,40.837325],"type":"Point"}
}