{
  "type": "Feature",
  "properties": {
    "addr:full":"40 Princess Dr North Brunswick NJ 08902",
    "addr:housenumber":"40",
    "addr:postcode":"08902",
    "addr:street":"Princess Dr",
    "iso:country":"US",
    "sg:address":"40 Princess Dr",
    "sg:city":"North Brunswick",
    "sg:classifiers":[
        {
            "category":"Real Estate",
            "subcategory":"Real Estate Agent",
            "type":"Services"
        }
    ],
    "sg:phone":"+1   ",
    "sg:postcode":"08902",
    "sg:province":"NJ",
    "wof:name":"Wongs Grand Street Realt",
    "wof:placetype":"venue"
},
  "geometry": {"coordinates":[-74.492698,40.45587],"type":"Point"}
}