{
  "type": "Feature",
  "properties": {
    "iso:country":"US",
    "sg:address":"1501 Livingston Ave",
    "sg:city":"North Brunswick",
    "sg:classifiers":[
        {
            "category":"Shopping",
            "type":"Retail Goods"
        },
        {
            "category":"Manufacturing",
            "subcategory":"Tools & Machinery",
            "type":"Manufacturing & Wholesale Goods"
        }
    ],
    "sg:phone":"+1 732 545 2885",
    "sg:postcode":"08902",
    "sg:province":"NJ",
    "sg:tags":[
        "medical",
        "store",
        "miscellaneous",
        "devices",
        "mfg"
    ],
    "wof:name":"C G Medical Supply",
    "wof:placetype":"venue"
},
  "geometry": {"coordinates":[-74.481416,40.458956],"type":"Point"}
}