{
  "type": "Feature",
  "properties": {
    "addr:full":"282 White Horse Pike Clementon NJ 08021",
    "addr:housenumber":"282",
    "addr:postcode":"08021",
    "addr:street":"White Horse Pike",
    "iso:country":"US",
    "sg:address":"282 White Horse Pike",
    "sg:city":"Clementon",
    "sg:classifiers":[
        {
            "category":"Retail",
            "subcategory":"Auto Repair",
            "type":"Services"
        }
    ],
    "sg:phone":"+1 856 435 7112",
    "sg:postcode":"08021",
    "sg:province":"NJ",
    "sg:tags":[
        "wrecker"
    ],
    "wof:name":"Del Towing",
    "wof:placetype":"venue"
},
  "geometry": {"coordinates":[-74.975302,39.80831],"type":"Point"}
}