{
  "type": "Feature",
  "properties": {
    "addr:full":"320 Main St Paterson NJ 07505",
    "addr:housenumber":"320",
    "addr:postcode":"07505",
    "addr:street":"Main St",
    "iso:country":"US",
    "sg:address":"320 Main St",
    "sg:city":"Paterson",
    "sg:classifiers":[
        {
            "category":"Organizations",
            "subcategory":"Religious Organization",
            "type":"Services"
        }
    ],
    "sg:phone":"+1 973 278 1079",
    "sg:postcode":"07505",
    "sg:province":"NJ",
    "sg:tags":[
        "church"
    ],
    "wof:name":"First Presbyterian Church",
    "wof:placetype":"venue"
},
  "geometry": {"coordinates":[-74.17347100000001,40.9141],"type":"Point"}
}