{
  "type": "Feature",
  "properties": {
    "iso:country":"US",
    "sg:address":"144 Tices Ln",
    "sg:city":"East Brunswick",
    "sg:classifiers":[
        {
            "category":"Social Services",
            "subcategory":"Child Care",
            "type":"Services"
        }
    ],
    "sg:phone":"+1 732 257 4114",
    "sg:postcode":"08816",
    "sg:province":"NJ",
    "wof:name":"YMCA",
    "wof:placetype":"venue"
},
  "geometry": {"coordinates":[-74.415404,40.453264],"type":"Point"}
}