{
  "type": "Feature",
  "properties": {
    "iso:country":"US",
    "sg:address":"32 Essex Rd",
    "sg:city":"Maplewood",
    "sg:classifiers":[
        {
            "category":"Retail",
            "subcategory":"Self-service Laundry",
            "type":"Services"
        }
    ],
    "sg:phone":"+1 973 378 9022",
    "sg:postcode":"07040",
    "sg:province":"NJ",
    "sg:tags":[
        "coin"
    ],
    "wof:name":"Community Laundromat",
    "wof:placetype":"venue"
},
  "geometry": {"coordinates":[-74.257283,40.726487],"type":"Point"}
}