{
  "type": "Feature",
  "properties": {
    "addr:full":"1150 Paterson Plank Rd Secaucus NJ 07094",
    "addr:housenumber":"1150",
    "addr:postcode":"07094",
    "addr:street":"Paterson Plank Rd",
    "iso:country":"US",
    "sg:address":"1150 Paterson Plank Rd",
    "sg:city":"Secaucus",
    "sg:classifiers":[
        {
            "category":"Fast Food",
            "type":"Food & Drink"
        },
        {
            "category":"Restaurant",
            "type":"Food & Drink"
        },
        {
            "category":"Bars & Pubs",
            "subcategory":"Sports Bar",
            "type":"Food & Drink"
        }
    ],
    "sg:phone":"+1 201 869 3663",
    "sg:postcode":"07094",
    "sg:province":"NJ",
    "sg:tags":[
        "chicken",
        "indian",
        "wing"
    ],
    "sg:website":"www.mausamnj.com",
    "wof:name":"Mausam Indian Restaurant, Bar, and Banquet",
    "wof:placetype":"venue"
},
  "geometry": {"coordinates":[-74.052419,40.786518],"type":"Point"}
}