{
  "type": "Feature",
  "properties": {
    "addr:full":"356 Millburn Ave Millburn NJ 07041",
    "addr:housenumber":"356",
    "addr:postcode":"07041",
    "addr:street":"Millburn Ave",
    "iso:country":"US",
    "sg:address":"356 Millburn Ave",
    "sg:city":"Millburn",
    "sg:classifiers":[
        {
            "category":"Professional",
            "subcategory":"Advertising",
            "type":"Services"
        }
    ],
    "sg:phone":"+1 973 379 8555",
    "sg:postcode":"07041",
    "sg:province":"NJ",
    "sg:tags":[
        "counselor"
    ],
    "wof:name":"William Sullivan Advertising",
    "wof:placetype":"venue"
},
  "geometry": {"coordinates":[-74.309618,40.723248],"type":"Point"}
}