{
  "type": "Feature",
  "properties": {
    "addr:full":"1745 Silverton Rd Toms River NJ 08753",
    "addr:housenumber":"1745",
    "addr:postcode":"08753",
    "addr:street":"Silverton Rd",
    "iso:country":"US",
    "sg:address":"1745 Silverton Rd",
    "sg:city":"Toms River",
    "sg:classifiers":[
        {
            "category":"Building & Trades",
            "subcategory":"Construction",
            "type":"Services"
        }
    ],
    "sg:phone":"+1 732 262 9141",
    "sg:postcode":"08753",
    "sg:province":"NJ",
    "sg:tags":[
        "contractor"
    ],
    "wof:name":"JC Contracting Inc",
    "wof:placetype":"venue"
},
  "geometry": {"coordinates":[-74.175989,40.020593],"type":"Point"}
}