{
  "type": "Feature",
  "properties": {
    "addr:full":"805 School St Rahway NJ 07065",
    "addr:housenumber":"805",
    "addr:postcode":"07065",
    "addr:street":"School St",
    "iso:country":"US",
    "sg:address":"805 School St",
    "sg:city":"Rahway",
    "sg:classifiers":[
        {
            "category":"Health Services",
            "subcategory":"Nursing And Care Facility",
            "type":"Services"
        }
    ],
    "sg:phone":"+1 732 680 1160",
    "sg:postcode":"07065",
    "sg:province":"NJ",
    "sg:tags":[
        "home",
        "retirement",
        "community"
    ],
    "wof:name":"Park Terrace At Rahway LLC",
    "wof:placetype":"venue"
},
  "geometry": {"coordinates":[-74.281728,40.617991],"type":"Point"}
}