{
  "type": "Feature",
  "properties": {
    "iso:country":"US",
    "sg:address":"107 Gaisler Rd",
    "sg:city":"Blairstown",
    "sg:classifiers":[
        {
            "category":"Professional",
            "subcategory":"Computer Services",
            "type":"Services"
        }
    ],
    "sg:phone":"+1 908 362 5633",
    "sg:postcode":"07825",
    "sg:province":"NJ",
    "sg:tags":[
        "programing",
        "custom"
    ],
    "wof:name":"Intelliware Solutions Inc",
    "wof:placetype":"venue"
},
  "geometry": {"coordinates":[-74.99826299999999,41.022354],"type":"Point"}
}