{
  "type": "Feature",
  "properties": {
    "iso:country":"US",
    "sg:address":"310 E 8th Ave",
    "sg:city":"Roselle",
    "sg:classifiers":[
        {
            "category":"Banks & Credit Unions",
            "subcategory":"Bank",
            "type":"Services"
        }
    ],
    "sg:phone":"+1   ",
    "sg:postcode":"07203",
    "sg:province":"NJ",
    "sg:tags":[
        "federal",
        "state"
    ],
    "wof:name":"Heard AME Church",
    "wof:placetype":"venue"
},
  "geometry": {"coordinates":[-74.25503500000001,40.652203],"type":"Point"}
}