{
  "type": "Feature",
  "properties": {
    "addr:full":"525 Pompton Ave Cedar Grove NJ 07009",
    "addr:housenumber":"525",
    "addr:postcode":"07009",
    "addr:street":"Pompton Ave",
    "iso:country":"US",
    "sg:address":"525 Pompton Ave",
    "sg:city":"Cedar Grove",
    "sg:classifiers":[
        {
            "category":"Government",
            "subcategory":"Office",
            "type":"Public Place"
        }
    ],
    "sg:phone":"+1   ",
    "sg:postcode":"07009",
    "sg:province":"NJ",
    "sg:tags":[
        "municipality"
    ],
    "wof:name":"Cedar Grove Township",
    "wof:placetype":"venue"
},
  "geometry": {"coordinates":[-74.22942500000001,40.851904],"type":"Point"}
}