{
  "type": "Feature",
  "properties": {
    "addr:full":"44 Essex Ave Bellmawr NJ 08031",
    "addr:housenumber":"44",
    "addr:postcode":"08031",
    "addr:street":"Essex Ave",
    "iso:country":"US",
    "sg:address":"44 Essex Ave",
    "sg:city":"Bellmawr",
    "sg:classifiers":[
        {
            "category":"Freight",
            "type":"Transportation"
        }
    ],
    "sg:phone":"+1 856 931 7146",
    "sg:postcode":"08031",
    "sg:province":"NJ",
    "sg:tags":[
        "consultant"
    ],
    "wof:name":"Bill Seas Transport",
    "wof:placetype":"venue"
},
  "geometry": {"coordinates":[-75.104677,39.867252],"type":"Point"}
}