{
  "type": "Feature",
  "properties": {
    "addr:full":"100 Midland Ave River Edge NJ 07661",
    "addr:housenumber":"100",
    "addr:postcode":"07661",
    "addr:street":"Midland Ave",
    "iso:country":"US",
    "sg:address":"100 Midland Ave",
    "sg:city":"River Edge",
    "sg:classifiers":[
        {
            "category":"Shopping",
            "subcategory":"Clothing, Apparel, & Fashions",
            "type":"Retail Goods"
        }
    ],
    "sg:phone":"+1 201 599 0830",
    "sg:postcode":"07661",
    "sg:province":"NJ",
    "sg:tags":[
        "tailor",
        "custom"
    ],
    "wof:name":"Ani's Tailoring",
    "wof:placetype":"venue"
},
  "geometry": {"coordinates":[-74.031915,40.940201],"type":"Point"}
}