{
  "type": "Feature",
  "properties": {
    "addr:full":"249 Lexington Ave Passaic NJ 07055",
    "addr:housenumber":"249",
    "addr:postcode":"07055",
    "addr:street":"Lexington Ave",
    "iso:country":"US",
    "sg:address":"249 Lexington Ave",
    "sg:city":"Passaic",
    "sg:classifiers":[
        {
            "category":"Health Services",
            "subcategory":"Doctor",
            "type":"Services"
        }
    ],
    "sg:phone":"+1 973 473 3277",
    "sg:postcode":"07055",
    "sg:province":"NJ",
    "sg:tags":[
        "physician",
        "surgeon"
    ],
    "wof:name":"Nathan Michael D DO",
    "wof:placetype":"venue"
},
  "geometry": {"coordinates":[-74.12840300000001,40.870399],"type":"Point"}
}