{
  "type": "Feature",
  "properties": {
    "iso:country":"US",
    "sg:address":"42 Meadowburn Rd",
    "sg:city":"Vernon",
    "sg:classifiers":[
        {
            "category":"Food & Beverages",
            "subcategory":"Dairy",
            "type":"Retail Goods"
        }
    ],
    "sg:phone":"+1   ",
    "sg:postcode":"07462",
    "sg:province":"NJ",
    "sg:tags":[
        "product"
    ],
    "wof:name":"Bobolink Dairy",
    "wof:placetype":"venue"
},
  "geometry": {"coordinates":[-74.44060899999999,41.238],"type":"Point"}
}