{
  "type": "Feature",
  "properties": {
    "addr:full":"123 W 1st St Bayonne NJ 07002",
    "addr:housenumber":"123",
    "addr:postcode":"07002",
    "addr:street":"W 1St St",
    "iso:country":"US",
    "sg:address":"123 W 1st St",
    "sg:city":"Bayonne",
    "sg:classifiers":[
        {
            "category":"Professional",
            "type":"Services"
        }
    ],
    "sg:phone":"+1 201 876 1903",
    "sg:postcode":"07002",
    "sg:province":"NJ",
    "sg:tags":[
        "establishment"
    ],
    "wof:name":"Lee & Boyle Studios",
    "wof:placetype":"venue"
},
  "geometry": {"coordinates":[-74.134953,40.646083],"type":"Point"}
}