{
  "type": "Feature",
  "properties": {
    "addr:full":"137 Hudson St Newark NJ 07103",
    "addr:housenumber":"137",
    "addr:postcode":"07103",
    "addr:street":"Hudson St",
    "iso:country":"US",
    "sg:address":"137 Hudson St",
    "sg:city":"Newark",
    "sg:classifiers":[
        {
            "category":"Retail",
            "subcategory":"Auto Repair",
            "type":"Services"
        }
    ],
    "sg:phone":"+1 973 621 6669",
    "sg:postcode":"07103",
    "sg:province":"NJ",
    "sg:tags":[
        "body",
        "shop",
        "painting",
        "automobile"
    ],
    "wof:name":"Orlando Auto Body & Fender",
    "wof:placetype":"venue"
},
  "geometry": {"coordinates":[-74.18559999999999,40.744598],"type":"Point"}
}