{
  "type": "Feature",
  "properties": {
    "addr:full":"7000 Kennedy Blvd West New York NJ 07093",
    "addr:housenumber":"7000",
    "addr:postcode":"07093",
    "addr:street":"Kennedy Blvd West",
    "iso:country":"US",
    "sg:address":"7000 Kennedy Blvd",
    "sg:city":"West New York",
    "sg:classifiers":[
        {
            "category":"Education",
            "subcategory":"Library",
            "type":"Public Place"
        }
    ],
    "sg:phone":"+1   ",
    "sg:postcode":"07093",
    "sg:province":"NJ",
    "wof:name":"Summit Bank Guttenberg Branch",
    "wof:placetype":"venue"
},
  "geometry": {"coordinates":[-74.014889,40.798773],"type":"Point"}
}