{
  "type": "Feature",
  "properties": {
    "iso:country":"US",
    "sg:address":"145 Blanchard St",
    "sg:city":"Newark",
    "sg:classifiers":[
        {
            "category":"Shopping",
            "type":"Retail Goods"
        }
    ],
    "sg:phone":"+1   ",
    "sg:postcode":"07105",
    "sg:province":"NJ",
    "sg:tags":[
        "merchandise"
    ],
    "wof:name":"Engine Shop",
    "wof:placetype":"venue"
},
  "geometry": {"coordinates":[-74.128294,40.738753],"type":"Point"}
}