{
  "type": "Feature",
  "properties": {
    "iso:country":"US",
    "sg:address":"16 Hampton Rd",
    "sg:city":"Glen Gardner",
    "sg:classifiers":[
        {
            "category":"Organizations",
            "subcategory":"Professional Association",
            "type":"Services"
        }
    ],
    "sg:phone":"+1 908 537 2650",
    "sg:postcode":"08826",
    "sg:province":"NJ",
    "wof:name":"American Camp Assn",
    "wof:placetype":"venue"
},
  "geometry": {"coordinates":[-74.944766,40.701487],"type":"Point"}
}