{
  "type": "Feature",
  "properties": {
    "addr:full":"405 Cedar Ln Teaneck NJ 07666",
    "addr:housenumber":"405",
    "addr:postcode":"07666",
    "addr:street":"Cedar Ln",
    "iso:country":"US",
    "sg:address":"405 Cedar Ln",
    "sg:city":"Teaneck",
    "sg:classifiers":[
        {
            "category":"Building & Trades",
            "subcategory":"Construction",
            "type":"Services"
        }
    ],
    "sg:phone":"+1 201 836 3997",
    "sg:postcode":"07666",
    "sg:province":"NJ",
    "sg:tags":[
        "company"
    ],
    "wof:name":"Castle American Construction",
    "wof:placetype":"venue"
},
  "geometry": {"coordinates":[-74.020922,40.888762],"type":"Point"}
}