{
  "type": "Feature",
  "properties": {
    "iso:country":"US",
    "sg:address":"76 Bloomfield St",
    "sg:city":"Hoboken",
    "sg:classifiers":[
        {
            "category":"Real Estate",
            "subcategory":"Real Estate Agent",
            "type":"Services"
        }
    ],
    "sg:phone":"+1   ",
    "sg:postcode":"07030",
    "sg:province":"NJ",
    "wof:name":"Columbian Towers",
    "wof:placetype":"venue"
},
  "geometry": {"coordinates":[-74.03221000000001,40.735916],"type":"Point"}
}