{
  "type": "Feature",
  "properties": {
    "iso:country":"US",
    "sg:address":"1100 N 32nd St",
    "sg:city":"Camden",
    "sg:classifiers":[
        {
            "category":"Food & Beverages",
            "subcategory":"Groceries & Convenience Stores",
            "type":"Retail Goods"
        }
    ],
    "sg:phone":"+1 856 338 0208",
    "sg:postcode":"08105",
    "sg:province":"NJ",
    "sg:tags":[
        "pretzel"
    ],
    "wof:name":"A & A Soft Pretzel Baking Co",
    "wof:placetype":"venue"
},
  "geometry": {"coordinates":[-75.08766900000001,39.961449],"type":"Point"}
}