{
  "type": "Feature",
  "properties": {
    "addr:full":"200 N 14th St Ste B Kenilworth NJ 07033",
    "addr:housenumber":"200",
    "addr:postcode":"07033",
    "addr:street":"N 14Th St Ste B",
    "iso:country":"US",
    "sg:address":"200 N 14th St Ste B",
    "sg:city":"Kenilworth",
    "sg:classifiers":[
        {
            "category":"Professional",
            "subcategory":"Computer Services",
            "type":"Services"
        }
    ],
    "sg:phone":"+1 908 272 6150",
    "sg:postcode":"07033",
    "sg:province":"NJ",
    "sg:tags":[
        "repair"
    ],
    "sg:website":"www.compwize.com",
    "wof:name":"Compwize Solutions",
    "wof:placetype":"venue"
},
  "geometry": {"coordinates":[-74.298528,40.679386],"type":"Point"}
}