{
  "type": "Feature",
  "properties": {
    "addr:full":"299 Myrtle Ave Irvington NJ 07111",
    "addr:housenumber":"299",
    "addr:postcode":"07111",
    "addr:street":"Myrtle Ave",
    "iso:country":"US",
    "sg:address":"299 Myrtle Ave",
    "sg:city":"Irvington",
    "sg:classifiers":[
        {
            "category":"Food & Beverages",
            "subcategory":"Groceries & Convenience Stores",
            "type":"Retail Goods"
        }
    ],
    "sg:phone":"+1 973 375 7329",
    "sg:postcode":"07111",
    "sg:province":"NJ",
    "sg:tags":[
        "grocer"
    ],
    "wof:name":"Father Grocery",
    "wof:placetype":"venue"
},
  "geometry": {"coordinates":[-74.22047999999999,40.736235],"type":"Point"}
}