{
  "type": "Feature",
  "properties": {
    "iso:country":"US",
    "sg:address":"19 Hearthstone Dr",
    "sg:city":"Butler",
    "sg:classifiers":[
        {
            "category":"Building & Trades",
            "subcategory":"Construction",
            "type":"Services"
        }
    ],
    "sg:phone":"+1 973 283 0993",
    "sg:postcode":"07405",
    "sg:province":"NJ",
    "sg:tags":[
        "house",
        "contractor"
    ],
    "wof:name":"Fortunato Construction Co",
    "wof:placetype":"venue"
},
  "geometry": {"coordinates":[-74.372145,41.004807],"type":"Point"}
}