{
  "type": "Feature",
  "properties": {
    "iso:country":"US",
    "sg:address":"52 N Spruce St",
    "sg:city":"Ramsey",
    "sg:classifiers":[
        {
            "category":"Professional",
            "subcategory":"Detective & Security Services",
            "type":"Services"
        }
    ],
    "sg:phone":"+1 201 327 3301",
    "sg:postcode":"07446",
    "sg:province":"NJ",
    "sg:tags":[
        "agency"
    ],
    "wof:name":"RJ Montgomery & Assoc",
    "wof:placetype":"venue"
},
  "geometry": {"coordinates":[-74.140488,41.060234],"type":"Point"}
}