{
  "type": "Feature",
  "properties": {
    "addr:full":"401 Abbott Rd Paramus NJ 07652",
    "addr:housenumber":"401",
    "addr:postcode":"07652",
    "addr:street":"Abbott Rd",
    "iso:country":"US",
    "sg:address":"401 Abbott Rd",
    "sg:city":"Paramus",
    "sg:classifiers":[
        {
            "category":"Freight",
            "type":"Transportation"
        }
    ],
    "sg:phone":"+1 201 261 4046",
    "sg:postcode":"07652",
    "sg:province":"NJ",
    "wof:name":"TMRCA Inc",
    "wof:placetype":"venue"
},
  "geometry": {"coordinates":[-74.07972100000001,40.949543],"type":"Point"}
}