{
  "type": "Feature",
  "properties": {
    "iso:country":"US",
    "sg:address":"137 Ray St",
    "sg:city":"Garfield",
    "sg:classifiers":[
        {
            "category":"Restaurant",
            "type":"Food & Drink"
        }
    ],
    "sg:phone":"+1 973 478 5822",
    "sg:postcode":"07026",
    "sg:province":"NJ",
    "sg:tags":[
        "delicatessen"
    ],
    "wof:name":"Mieszko Delicatessen",
    "wof:placetype":"venue"
},
  "geometry": {"coordinates":[-74.117026,40.884364],"type":"Point"}
}