{
  "type": "Feature",
  "properties": {
    "addr:full":"40 State Rte 34 Colts Neck NJ 07722",
    "addr:housenumber":"40",
    "addr:postcode":"07722",
    "addr:street":"State Rte 34",
    "iso:country":"US",
    "sg:address":"40 State Rte 34",
    "sg:city":"Colts Neck",
    "sg:classifiers":[
        {
            "category":"Building & Trades",
            "subcategory":"Construction",
            "type":"Services"
        }
    ],
    "sg:phone":"+1 732 462 2397",
    "sg:postcode":"07722",
    "sg:province":"NJ",
    "sg:tags":[
        "water",
        "well",
        "drilling"
    ],
    "wof:name":"Tilton Pump Svc",
    "wof:placetype":"venue"
},
  "geometry": {"coordinates":[-74.172658,40.283588],"type":"Point"}
}