{
  "type": "Feature",
  "properties": {
    "addr:full":"29 Porete Ave North Arlington NJ 07031",
    "addr:housenumber":"29",
    "addr:postcode":"07031",
    "addr:street":"Porete Ave North",
    "iso:country":"US",
    "sg:address":"29 Porete Ave",
    "sg:city":"North Arlington",
    "sg:classifiers":[
        {
            "category":"Manufacturing",
            "subcategory":"Metals",
            "type":"Manufacturing & Wholesale Goods"
        }
    ],
    "sg:phone":"+1 201 991 8777",
    "sg:postcode":"07031",
    "sg:province":"NJ",
    "sg:tags":[
        "coating",
        "pl"
    ],
    "sg:website":"www.haward.com",
    "wof:name":"Haward Corp",
    "wof:placetype":"venue"
},
  "geometry": {"coordinates":[-74.125609,40.780038],"type":"Point"}
}