{
  "type": "Feature",
  "properties": {
    "iso:country":"US",
    "sg:address":"35 Park Ave",
    "sg:city":"Lyndhurst",
    "sg:classifiers":[
        {
            "category":"Personal",
            "subcategory":"Beauty Salon",
            "type":"Services"
        }
    ],
    "sg:phone":"+1 201 933 9650",
    "sg:postcode":"07071",
    "sg:province":"NJ",
    "sg:tags":[
        "shop"
    ],
    "wof:name":"2000 Hair Studio Inc",
    "wof:placetype":"venue"
},
  "geometry": {"coordinates":[-74.121191,40.820758],"type":"Point"}
}