{
  "type": "Feature",
  "properties": {
    "addr:full":"25 Independence Blvd Warren NJ 07059",
    "addr:housenumber":"25",
    "addr:postcode":"07059",
    "addr:street":"Independence Blvd",
    "iso:country":"US",
    "sg:address":"25 Independence Blvd",
    "sg:city":"Warren",
    "sg:classifiers":[
        {
            "category":"Professional",
            "type":"Services"
        }
    ],
    "sg:phone":"+1 908 626 0070",
    "sg:postcode":"07059",
    "sg:province":"NJ",
    "sg:tags":[
        "establishment"
    ],
    "wof:name":"J Net",
    "wof:placetype":"venue"
},
  "geometry": {"coordinates":[-74.571573,40.651645],"type":"Point"}
}