{
  "type": "Feature",
  "properties": {
    "iso:country":"US",
    "sg:address":"757 Blanche Ave",
    "sg:city":"Norwood",
    "sg:classifiers":[
        {
            "category":"Building & Trades",
            "subcategory":"Construction",
            "type":"Services"
        }
    ],
    "sg:phone":"+1 201 768 8297",
    "sg:postcode":"07648",
    "sg:province":"NJ",
    "sg:tags":[
        "house"
    ],
    "wof:name":"Jay Tee Homes Inc",
    "wof:placetype":"venue"
},
  "geometry": {"coordinates":[-73.96364800000001,40.99144],"type":"Point"}
}