{
  "type": "Feature",
  "properties": {
    "iso:country":"US",
    "sg:address":"1005 Eastpark Blvd",
    "sg:city":"Cranbury",
    "sg:classifiers":[
        {
            "category":"Professional",
            "subcategory":"Lawyer & Legal Services",
            "type":"Services"
        }
    ],
    "sg:phone":"+1   ",
    "sg:postcode":"08512",
    "sg:province":"NJ",
    "wof:name":"Dean Angler Inc",
    "wof:placetype":"venue"
},
  "geometry": {"coordinates":[-74.499341,40.34008],"type":"Point"}
}