{
  "type": "Feature",
  "properties": {
    "iso:country":"US",
    "sg:address":"6 Elm St",
    "sg:city":"Oakland",
    "sg:classifiers":[
        {
            "category":"Education",
            "subcategory":"Kindergarten",
            "type":"Public Place"
        }
    ],
    "sg:phone":"+1 201 405 0340",
    "sg:postcode":"07436",
    "sg:province":"NJ",
    "sg:tags":[
        "school",
        "driving"
    ],
    "sg:website":"www.fallonsdrivingschool.com",
    "wof:name":"Fallon's Driving School",
    "wof:placetype":"venue"
},
  "geometry": {"coordinates":[-74.242401,41.024502],"type":"Point"}
}