{
  "type": "Feature",
  "properties": {
    "addr:full":"29 Mountain Ave Bloomfield NJ 07003",
    "addr:housenumber":"29",
    "addr:postcode":"07003",
    "addr:street":"Mountain Ave",
    "iso:country":"US",
    "sg:address":"29 Mountain Ave",
    "sg:city":"Bloomfield",
    "sg:classifiers":[
        {
            "category":"Building & Trades",
            "subcategory":"Construction",
            "type":"Services"
        }
    ],
    "sg:phone":"+1 973 338 0862",
    "sg:postcode":"07003",
    "sg:province":"NJ",
    "sg:tags":[
        "light",
        "house"
    ],
    "wof:name":"Celidonio and Sons Inc",
    "wof:placetype":"venue"
},
  "geometry": {"coordinates":[-74.184136,40.834993],"type":"Point"}
}