{
  "type": "Feature",
  "properties": {
    "iso:country":"US",
    "sg:address":"3240 Windsor Ave",
    "sg:city":"Toms River",
    "sg:classifiers":[
        {
            "category":"Building & Trades",
            "subcategory":"Construction",
            "type":"Services"
        }
    ],
    "sg:phone":"+1 732 270 3927",
    "sg:postcode":"08753",
    "sg:province":"NJ",
    "sg:tags":[
        "painter"
    ],
    "wof:name":"Seniors Favorite Home Painting",
    "wof:placetype":"venue"
},
  "geometry": {"coordinates":[-74.12148500000001,39.959008],"type":"Point"}
}