{
  "type": "Feature",
  "properties": {
    "iso:country":"US",
    "sg:address":"121 Howe Ave",
    "sg:city":"Passaic",
    "sg:classifiers":[
        {
            "category":"Banks & Credit Unions",
            "subcategory":"Financial Services",
            "type":"Services"
        }
    ],
    "sg:phone":"+1   ",
    "sg:postcode":"07055",
    "sg:province":"NJ",
    "sg:tags":[
        "a",
        "substance",
        "charitable",
        "abuse",
        "organization",
        "providing"
    ],
    "wof:name":"Northeast Life Skills Assoc",
    "wof:placetype":"venue"
},
  "geometry": {"coordinates":[-74.132192,40.860935],"type":"Point"}
}