{
  "type": "Feature",
  "properties": {
    "addr:full":"17 Gudz Rd Lakewood NJ 08701",
    "addr:housenumber":"17",
    "addr:postcode":"08701",
    "addr:street":"Gudz Rd",
    "iso:country":"US",
    "sg:address":"17 Gudz Rd",
    "sg:city":"Lakewood",
    "sg:classifiers":[
        {
            "category":"Building & Trades",
            "subcategory":"Construction",
            "type":"Services"
        }
    ],
    "sg:phone":"+1 732 961 1080",
    "sg:postcode":"08701",
    "sg:province":"NJ",
    "sg:tags":[
        "contractor"
    ],
    "wof:name":"Imperial Contracting Inc",
    "wof:placetype":"venue"
},
  "geometry": {"coordinates":[-74.24807,40.090218],"type":"Point"}
}