{
  "type": "Feature",
  "properties": {
    "iso:country":"US",
    "sg:address":"1 Loomis Ave",
    "sg:city":"Sussex",
    "sg:classifiers":[
        {
            "category":"Retail",
            "subcategory":"Repair Shop",
            "type":"Services"
        }
    ],
    "sg:phone":"+1 973 702 8900",
    "sg:postcode":"07461",
    "sg:province":"NJ",
    "sg:tags":[
        "scooter",
        "motorcycle",
        "motor"
    ],
    "wof:name":"Blacksmith Cycles",
    "wof:placetype":"venue"
},
  "geometry": {"coordinates":[-74.61410600000001,41.204983],"type":"Point"}
}