{
  "type": "Feature",
  "properties": {
    "iso:country":"US",
    "sg:address":"200 Lanidex Plz",
    "sg:city":"Parsippany",
    "sg:classifiers":[
        {
            "category":"Insurance",
            "subcategory":"Hazard Insurance",
            "type":"Services"
        }
    ],
    "sg:phone":"+1   ",
    "sg:postcode":"07054",
    "sg:province":"NJ",
    "sg:tags":[
        "credit"
    ],
    "wof:name":"Euler A C I",
    "wof:placetype":"venue"
},
  "geometry": {"coordinates":[-74.420456,40.861333],"type":"Point"}
}