{
  "type": "Feature",
  "properties": {
    "iso:country":"US",
    "sg:address":"28 Fair Lawn Ave",
    "sg:city":"Fair Lawn",
    "sg:classifiers":[
        {
            "category":"Food & Beverages",
            "subcategory":"Groceries & Convenience Stores",
            "type":"Retail Goods"
        }
    ],
    "sg:phone":"+1   ",
    "sg:postcode":"07410",
    "sg:province":"NJ",
    "wof:name":"D & C Food",
    "wof:placetype":"venue"
},
  "geometry": {"coordinates":[-74.12277400000001,40.938604],"type":"Point"}
}