{
  "type": "Feature",
  "properties": {
    "iso:country":"US",
    "sg:address":"25 Delaware Trl",
    "sg:city":"Denville",
    "sg:classifiers":[
        {
            "category":"Retail",
            "subcategory":"Animal Services",
            "type":"Services"
        }
    ],
    "sg:phone":"+1 973 625 2667",
    "sg:postcode":"07834",
    "sg:province":"NJ",
    "sg:tags":[
        "breeder",
        "terrier"
    ],
    "wof:name":"Starcastle Bedlingtons",
    "wof:placetype":"venue"
},
  "geometry": {"coordinates":[-74.495918,40.883669],"type":"Point"}
}