{
  "type": "Feature",
  "properties": {
    "addr:full":"7 Bell St Montclair NJ 07042",
    "addr:housenumber":"7",
    "addr:postcode":"07042",
    "addr:street":"Bell St",
    "iso:country":"US",
    "sg:address":"7 Bell St",
    "sg:city":"Montclair",
    "sg:classifiers":[
        {
            "category":"Real Estate",
            "subcategory":"Real Estate Agent",
            "type":"Services"
        }
    ],
    "sg:phone":"+1   ",
    "sg:postcode":"07042",
    "sg:province":"NJ",
    "wof:name":"Hewitt Real Estate Associates",
    "wof:placetype":"venue"
},
  "geometry": {"coordinates":[-74.221829,40.819264],"type":"Point"}
}