{
  "type": "Feature",
  "properties": {
    "iso:country":"US",
    "sg:address":"375 Rockport Rd",
    "sg:city":"Port Murray",
    "sg:classifiers":[
        {
            "category":"Organizations",
            "subcategory":"Religious Organization",
            "type":"Services"
        }
    ],
    "sg:phone":"+1 908 852 6515",
    "sg:postcode":"07865",
    "sg:province":"NJ",
    "sg:tags":[
        "church"
    ],
    "wof:name":"Rockport Presbyterian Church",
    "wof:placetype":"venue"
},
  "geometry": {"coordinates":[-74.90137,40.806862],"type":"Point"}
}