{
  "type": "Feature",
  "properties": {
    "addr:full":"4109 Ventnor Ave Atlantic City NJ 08401",
    "addr:housenumber":"4109",
    "addr:postcode":"08401",
    "addr:street":"Ventnor Ave",
    "iso:country":"US",
    "sg:address":"4109 Ventnor Ave",
    "sg:city":"Atlantic City",
    "sg:classifiers":[
        {
            "category":"Shopping",
            "subcategory":"Discount & Variety Stores",
            "type":"Retail Goods"
        }
    ],
    "sg:phone":"+1 609 449 1177",
    "sg:postcode":"08401",
    "sg:province":"NJ",
    "wof:name":"BJS Dollar Express",
    "wof:placetype":"venue"
},
  "geometry": {"coordinates":[-74.45932999999999,39.349399],"type":"Point"}
}