{
  "type": "Feature",
  "properties": {
    "addr:full":"116 6th Ave Seaside Park NJ 08752",
    "addr:housenumber":"116",
    "addr:postcode":"08752",
    "addr:street":"6Th Ave",
    "iso:country":"US",
    "sg:address":"116 6th Ave",
    "sg:city":"Seaside Park",
    "sg:classifiers":[
        {
            "category":"Food & Beverages",
            "subcategory":"Groceries & Convenience Stores",
            "type":"Retail Goods"
        }
    ],
    "sg:phone":"+1 732 854 0585",
    "sg:postcode":"08752",
    "sg:province":"NJ",
    "sg:tags":[
        "product"
    ],
    "wof:name":"J P Foods",
    "wof:placetype":"venue"
},
  "geometry": {"coordinates":[-74.08010899999999,39.919117],"type":"Point"}
}