{
  "type": "Feature",
  "properties": {
    "iso:country":"US",
    "sg:address":"73 Forest St",
    "sg:city":"Kearny",
    "sg:classifiers":[
        {
            "category":"Building & Trades",
            "subcategory":"Construction",
            "type":"Services"
        }
    ],
    "sg:phone":"+1 201 955 0757",
    "sg:postcode":"07032",
    "sg:province":"NJ",
    "sg:tags":[
        "steel",
        "structural",
        "welding",
        "contractor"
    ],
    "wof:name":"Statewide Iron and Welding",
    "wof:placetype":"venue"
},
  "geometry": {"coordinates":[-74.14907599999999,40.756858],"type":"Point"}
}