{
  "type": "Feature",
  "properties": {
    "iso:country":"US",
    "sg:address":"938 Broad St",
    "sg:city":"Newark",
    "sg:classifiers":[
        {
            "category":"Professional",
            "subcategory":"Business Services",
            "type":"Services"
        }
    ],
    "sg:phone":"+1 973 643 6950",
    "sg:postcode":"07102",
    "sg:province":"NJ",
    "sg:tags":[
        "translator",
        "interpreter"
    ],
    "wof:name":"All Documents Translation Svc",
    "wof:placetype":"venue"
},
  "geometry": {"coordinates":[-74.174798,40.730795],"type":"Point"}
}