{
  "type": "Feature",
  "properties": {
    "iso:country":"US",
    "sg:address":"4 Willow Dr",
    "sg:city":"Rio Grande",
    "sg:classifiers":[
        {
            "category":"Building & Trades",
            "subcategory":"Construction",
            "type":"Services"
        }
    ],
    "sg:phone":"+1 609 886 8899",
    "sg:postcode":"08242",
    "sg:province":"NJ",
    "sg:tags":[
        "contractor"
    ],
    "wof:name":"Olson Dry Wall",
    "wof:placetype":"venue"
},
  "geometry": {"coordinates":[-74.88237700000001,39.011236],"type":"Point"}
}