{
  "type": "Feature",
  "properties": {
    "iso:country":"US",
    "sg:address":"400 S Plainfield Ave",
    "sg:city":"South Plainfield",
    "sg:classifiers":[
        {
            "category":"Manufacturing",
            "subcategory":"Chemicals & Compounds",
            "type":"Manufacturing & Wholesale Goods"
        }
    ],
    "sg:phone":"+1 973 242 4110",
    "sg:postcode":"07080",
    "sg:province":"NJ",
    "sg:website":"www.omgi.com",
    "wof:name":"Auric Corp",
    "wof:placetype":"venue"
},
  "geometry": {"coordinates":[-74.397707,40.585564],"type":"Point"}
}