{
  "type": "Feature",
  "properties": {
    "addr:full":"786 Haddon Ave Collingswood NJ 08108",
    "addr:housenumber":"786",
    "addr:postcode":"08108",
    "addr:street":"Haddon Ave",
    "iso:country":"US",
    "sg:address":"786 Haddon Ave",
    "sg:city":"Collingswood",
    "sg:classifiers":[
        {
            "category":"Professional",
            "subcategory":"Research",
            "type":"Services"
        }
    ],
    "sg:phone":"+1 856 858 5750",
    "sg:postcode":"08108",
    "sg:province":"NJ",
    "sg:tags":[
        "environmental",
        "ecological"
    ],
    "wof:name":"Water Resource Management Inc",
    "wof:placetype":"venue"
},
  "geometry": {"coordinates":[-75.066954,39.915631],"type":"Point"}
}