{
  "type": "Feature",
  "properties": {
    "addr:full":"1 S Main St Lodi NJ 07644",
    "addr:housenumber":"1",
    "addr:postcode":"07644",
    "addr:street":"S Main St",
    "iso:country":"US",
    "sg:address":"1 S Main St",
    "sg:city":"Lodi",
    "sg:classifiers":[
        {
            "category":"Real Estate",
            "subcategory":"Real Estate Operator",
            "type":"Services"
        }
    ],
    "sg:phone":"+1 973 472 9800",
    "sg:postcode":"07644",
    "sg:province":"NJ",
    "sg:tags":[
        "apartment"
    ],
    "wof:name":"Apartment Store",
    "wof:placetype":"venue"
},
  "geometry": {"coordinates":[-74.08760100000001,40.873194],"type":"Point"}
}