{
  "type": "Feature",
  "properties": {
    "iso:country":"US",
    "sg:address":"275 Parkertown Dr",
    "sg:city":"Tuckerton",
    "sg:classifiers":[
        {
            "category":"Building & Trades",
            "subcategory":"Electrical",
            "type":"Services"
        }
    ],
    "sg:phone":"+1 609 294 2337",
    "sg:postcode":"08087",
    "sg:province":"NJ",
    "sg:tags":[
        "electrical",
        "contractor"
    ],
    "wof:name":"Steve S Electrical Contracting",
    "wof:placetype":"venue"
},
  "geometry": {"coordinates":[-74.324325,39.631604],"type":"Point"}
}