{
  "type": "Feature",
  "properties": {
    "addr:full":"110 Allen Rd Liberty Corner NJ 07920",
    "addr:housenumber":"110",
    "addr:postcode":"07920",
    "addr:street":"Allen Rd",
    "iso:country":"US",
    "sg:address":"110 Allen Rd",
    "sg:city":"Liberty Corner",
    "sg:classifiers":[
        {
            "category":"Insurance",
            "subcategory":"Insurance Agent",
            "type":"Services"
        }
    ],
    "sg:phone":"+1   ",
    "sg:postcode":"07920",
    "sg:province":"NJ",
    "wof:name":"St Paul Fire & Marine Insur",
    "wof:placetype":"venue"
},
  "geometry": {"coordinates":[-74.586665,40.649899],"type":"Point"}
}