{
  "type": "Feature",
  "properties": {
    "addr:full":"711 Rivervale Rd River Vale NJ 07675",
    "addr:housenumber":"711",
    "addr:postcode":"07675",
    "addr:street":"Rivervale Rd",
    "iso:country":"US",
    "sg:address":"711 Rivervale Rd",
    "sg:city":"River Vale",
    "sg:classifiers":[
        {
            "category":"Bus Charters",
            "type":"Transportation"
        }
    ],
    "sg:phone":"+1 201 391 6213",
    "sg:postcode":"07675",
    "sg:province":"NJ",
    "sg:tags":[
        "rental"
    ],
    "wof:name":"Commodore Tours Inc",
    "wof:placetype":"venue"
},
  "geometry": {"coordinates":[-74.009039,41.027927],"type":"Point"}
}