{
  "type": "Feature",
  "properties": {
    "addr:full":"12 Ramapo Ter Fair Lawn NJ 07410",
    "addr:housenumber":"12",
    "addr:postcode":"07410",
    "addr:street":"Ramapo Ter",
    "iso:country":"US",
    "sg:address":"12 Ramapo Ter",
    "sg:city":"Fair Lawn",
    "sg:classifiers":[
        {
            "category":"Shopping",
            "subcategory":"Musical Instruments",
            "type":"Retail Goods"
        }
    ],
    "sg:phone":"+1 212 929 1681",
    "sg:postcode":"07410",
    "sg:province":"NJ",
    "sg:tags":[
        "music",
        "dealer"
    ],
    "wof:name":"A C Music Productions",
    "wof:placetype":"venue"
},
  "geometry": {"coordinates":[-74.117192,40.937635],"type":"Point"}
}