{
  "type": "Feature",
  "properties": {
    "iso:country":"US",
    "sg:address":"79 Lakeside Dr",
    "sg:city":"Nutley",
    "sg:classifiers":[
        {
            "category":"Professional",
            "subcategory":"Computer Services",
            "type":"Services"
        }
    ],
    "sg:phone":"+1 973 667 1416",
    "sg:postcode":"07110",
    "sg:province":"NJ",
    "sg:tags":[
        "prepackaged",
        "software"
    ],
    "wof:name":"Migrue Software",
    "wof:placetype":"venue"
},
  "geometry": {"coordinates":[-74.144392,40.825809],"type":"Point"}
}