{
  "type": "Feature",
  "properties": {
    "addr:full":"4219 US Hwy 9 Howell NJ 07731",
    "addr:housenumber":"4219",
    "addr:postcode":"07731",
    "addr:street":"Us Hwy 9",
    "iso:country":"US",
    "sg:address":"4219 US Hwy 9",
    "sg:city":"Howell",
    "sg:classifiers":[
        {
            "category":"Organizations",
            "subcategory":"Religious Organization",
            "type":"Services"
        }
    ],
    "sg:phone":"+1 732 364 4130",
    "sg:postcode":"07731",
    "sg:province":"NJ",
    "sg:website":"www.stveronica.com",
    "wof:name":"St Veronica School",
    "wof:placetype":"venue"
},
  "geometry": {"coordinates":[-74.226877,40.150331],"type":"Point"}
}