{
  "type": "Feature",
  "properties": {
    "addr:full":"517 Broadway Cape May NJ 08204",
    "addr:housenumber":"517",
    "addr:postcode":"08204",
    "addr:street":"Broadway",
    "iso:country":"US",
    "sg:address":"517 Broadway",
    "sg:city":"Cape May",
    "sg:classifiers":[
        {
            "category":"Food & Beverages",
            "subcategory":"Meat & Fish",
            "type":"Retail Goods"
        }
    ],
    "sg:phone":"+1 609 884 3061",
    "sg:postcode":"08204",
    "sg:province":"NJ",
    "sg:tags":[
        "sandwich"
    ],
    "wof:name":"Westside Market",
    "wof:placetype":"venue"
},
  "geometry": {"coordinates":[-74.93029799999999,38.939701],"type":"Point"}
}