{
  "type": "Feature",
  "properties": {
    "addr:full":"2604 Long Beach Blvd Ship Bottom NJ 08008",
    "addr:housenumber":"2604",
    "addr:postcode":"08008",
    "addr:street":"Long Beach Blvd",
    "iso:country":"US",
    "sg:address":"2604 Long Beach Blvd",
    "sg:city":"Ship Bottom",
    "sg:classifiers":[
        {
            "category":"Restaurant",
            "type":"Food & Drink"
        }
    ],
    "sg:phone":"+1 609 361 2425",
    "sg:postcode":"08008",
    "sg:province":"NJ",
    "wof:name":"Sand Box Cafe",
    "wof:placetype":"venue"
},
  "geometry": {"coordinates":[-74.22823200000001,39.580539],"type":"Point"}
}