{
  "type": "Feature",
  "properties": {
    "addr:full":"37 Palisades Ave Bergenfield NJ 07626",
    "addr:housenumber":"37",
    "addr:postcode":"07626",
    "addr:street":"Palisades Ave",
    "iso:country":"US",
    "sg:address":"37 Palisades Ave",
    "sg:city":"Bergenfield",
    "sg:classifiers":[
        {
            "category":"Retail",
            "subcategory":"Repair Shop",
            "type":"Services"
        }
    ],
    "sg:phone":"+1 201 384 3836",
    "sg:postcode":"07626",
    "sg:province":"NJ",
    "sg:tags":[
        "upholsterer"
    ],
    "wof:name":"Knowles Custom Upholstery",
    "wof:placetype":"venue"
},
  "geometry": {"coordinates":[-73.959029,40.938805],"type":"Point"}
}