{
  "type": "Feature",
  "properties": {
    "addr:full":"832 Chancellor Ave Irvington NJ 07111",
    "addr:housenumber":"832",
    "addr:postcode":"07111",
    "addr:street":"Chancellor Ave",
    "iso:country":"US",
    "sg:address":"832 Chancellor Ave",
    "sg:city":"Irvington",
    "sg:classifiers":[
        {
            "category":"Health Services",
            "subcategory":"Doctor",
            "type":"Services"
        }
    ],
    "sg:phone":"+1 973 399 6270",
    "sg:postcode":"07111",
    "sg:province":"NJ",
    "sg:tags":[
        "physician",
        "surgeon"
    ],
    "wof:name":"Health Excel",
    "wof:placetype":"venue"
},
  "geometry": {"coordinates":[-74.242457,40.717945],"type":"Point"}
}