{
  "type": "Feature",
  "properties": {
    "iso:country":"US",
    "sg:address":"445 E Stokes Rd",
    "sg:city":"Shamong",
    "sg:classifiers":[
        {
            "category":"Recreation",
            "type":"Entertainment"
        }
    ],
    "sg:phone":"+1 609 268 6300",
    "sg:postcode":"08088",
    "sg:province":"NJ",
    "sg:tags":[
        "stable"
    ],
    "wof:name":"East Stokes Stables",
    "wof:placetype":"venue"
},
  "geometry": {"coordinates":[-74.734696,39.769747],"type":"Point"}
}