{
  "type": "Feature",
  "properties": {
    "addr:full":"368 Delsea Dr Malaga NJ 08328",
    "addr:housenumber":"368",
    "addr:postcode":"08328",
    "addr:street":"Delsea Dr",
    "iso:country":"US",
    "sg:address":"368 Delsea Dr",
    "sg:city":"Malaga",
    "sg:classifiers":[
        {
            "category":"Restaurant",
            "type":"Food & Drink"
        }
    ],
    "sg:menulink":"http://www.allmenus.com/nj/franklin/194597-mcdonalds/menu/",
    "sg:phone":"+1 856 694 5116",
    "sg:postcode":"08328",
    "sg:province":"NJ",
    "sg:tags":[
        "burger",
        "american"
    ],
    "wof:name":"McDonald's",
    "wof:placetype":"venue"
},
  "geometry": {"coordinates":[-75.055178,39.570823],"type":"Point"}
}