{
  "type": "Feature",
  "properties": {
    "addr:full":"475 Main St Metuchen NJ 08840",
    "addr:housenumber":"475",
    "addr:postcode":"08840",
    "addr:street":"Main St",
    "iso:country":"US",
    "sg:address":"475 Main St",
    "sg:city":"Metuchen",
    "sg:classifiers":[
        {
            "category":"Banks & Credit Unions",
            "subcategory":"Bank",
            "type":"Services"
        }
    ],
    "sg:phone":"+1   ",
    "sg:postcode":"08840",
    "sg:province":"NJ",
    "sg:tags":[
        "state",
        "commercial"
    ],
    "wof:name":"Bank Of New York",
    "wof:placetype":"venue"
},
  "geometry": {"coordinates":[-74.362593,40.543235],"type":"Point"}
}