{
  "type": "Feature",
  "properties": {
    "addr:full":"2 Journal Sq Jersey City NJ 07306",
    "addr:housenumber":"2",
    "addr:postcode":"07306",
    "addr:street":"Journal Sq",
    "iso:country":"US",
    "sg:address":"2 Journal Sq",
    "sg:city":"Jersey City",
    "sg:classifiers":[
        {
            "category":"Professional",
            "subcategory":"Computer Services",
            "type":"Services"
        }
    ],
    "sg:phone":"+1 201 533 1762",
    "sg:postcode":"07306",
    "sg:province":"NJ",
    "sg:tags":[
        "processing",
        "datum"
    ],
    "wof:name":"Siac Sector Adp",
    "wof:placetype":"venue"
},
  "geometry": {"coordinates":[-74.063861,40.732048],"type":"Point"}
}