{
  "type": "Feature",
  "properties": {
    "addr:full":"455 Maryland St Orange NJ 07050",
    "addr:housenumber":"455",
    "addr:postcode":"07050",
    "addr:street":"Maryland St",
    "iso:country":"US",
    "sg:address":"455 Maryland St",
    "sg:city":"Orange",
    "sg:classifiers":[
        {
            "category":"Professional",
            "subcategory":"Management & Consulting",
            "type":"Services"
        }
    ],
    "sg:phone":"+1   ",
    "sg:postcode":"07050",
    "sg:province":"NJ",
    "sg:tags":[
        "contracting",
        "doe",
        "local",
        "area"
    ],
    "wof:name":"All Over The Place",
    "wof:placetype":"venue"
},
  "geometry": {"coordinates":[-74.236954,40.77277],"type":"Point"}
}