{
  "type": "Feature",
  "properties": {
    "iso:country":"US",
    "sg:address":"2900 US Hwy 130",
    "sg:city":"Delran",
    "sg:classifiers":[
        {
            "category":"Professional",
            "type":"Services"
        }
    ],
    "sg:phone":"+1 856 764 9229",
    "sg:postcode":"08075",
    "sg:province":"NJ",
    "sg:tags":[
        "establishment"
    ],
    "wof:name":"Jackal's",
    "wof:placetype":"venue"
},
  "geometry": {"coordinates":[-74.96608500000001,40.010065],"type":"Point"}
}