{
  "type": "Feature",
  "properties": {
    "addr:full":"2616 S Broad St Trenton NJ 08610",
    "addr:housenumber":"2616",
    "addr:postcode":"08610",
    "addr:street":"S Broad St",
    "iso:country":"US",
    "sg:address":"2616 S Broad St",
    "sg:city":"Trenton",
    "sg:classifiers":[
        {
            "category":"Professional",
            "type":"Services"
        }
    ],
    "sg:phone":"+1 609 888 4162",
    "sg:postcode":"08610",
    "sg:province":"NJ",
    "sg:tags":[
        "establishment"
    ],
    "wof:name":"Rednor Rainear",
    "wof:placetype":"venue"
},
  "geometry": {"coordinates":[-74.71451500000001,40.192333],"type":"Point"}
}