{
  "type": "Feature",
  "properties": {
    "addr:full":"542 Buck Rd Elmer NJ 08318",
    "addr:housenumber":"542",
    "addr:postcode":"08318",
    "addr:street":"Buck Rd",
    "iso:country":"US",
    "sg:address":"542 Buck Rd",
    "sg:city":"Elmer",
    "sg:classifiers":[
        {
            "category":"Organizations",
            "subcategory":"Religious Organization",
            "type":"Services"
        }
    ],
    "sg:phone":"+1 856 358 6997",
    "sg:postcode":"08318",
    "sg:province":"NJ",
    "sg:tags":[
        "clergy"
    ],
    "wof:name":"John Pinkerton",
    "wof:placetype":"venue"
},
  "geometry": {"coordinates":[-75.14666200000001,39.571765],"type":"Point"}
}