{
  "type": "Feature",
  "properties": {
    "iso:country":"US",
    "sg:address":"60 Easton Ave",
    "sg:city":"New Brunswick",
    "sg:classifiers":[
        {
            "category":"Restaurant",
            "type":"Food & Drink"
        }
    ],
    "sg:menulink":"http://www.allmenus.com/nj/new-brunswick/20229-giovannelis/menu/",
    "sg:phone":"+1 732 220 1220",
    "sg:postcode":"08901",
    "sg:province":"NJ",
    "sg:tags":[
        "sandwich",
        "middle",
        "cheesesteaks",
        "eastern",
        "dog",
        "burger",
        "hot",
        "wrap",
        "american",
        "pizza",
        "wing",
        "italian"
    ],
    "wof:name":"Giovanneli's",
    "wof:placetype":"venue"
},
  "geometry": {"coordinates":[-74.449185,40.497966],"type":"Point"}
}