{
  "type": "Feature",
  "properties": {
    "addr:full":"214 Cambridge Ct Clifton NJ 07014",
    "addr:housenumber":"214",
    "addr:postcode":"07014",
    "addr:street":"Cambridge Ct",
    "iso:country":"US",
    "sg:address":"214 Cambridge Ct",
    "sg:city":"Clifton",
    "sg:classifiers":[
        {
            "category":"Professional",
            "subcategory":"Management & Consulting",
            "type":"Services"
        }
    ],
    "sg:phone":"+1   ",
    "sg:postcode":"07014",
    "sg:province":"NJ",
    "sg:tags":[
        "business"
    ],
    "wof:name":"Castro Consultants",
    "wof:placetype":"venue"
},
  "geometry": {"coordinates":[-74.13364199999999,40.835996],"type":"Point"}
}