{
  "type": "Feature",
  "properties": {
    "addr:full":"2109 State Rte 35 Holmdel NJ 07733",
    "addr:housenumber":"2109",
    "addr:postcode":"07733",
    "addr:street":"State Rte 35",
    "iso:country":"US",
    "sg:address":"2109 State Rte 35",
    "sg:city":"Holmdel",
    "sg:classifiers":[
        {
            "category":"Home & Garden",
            "subcategory":"Furniture",
            "type":"Retail Goods"
        }
    ],
    "sg:phone":"+1 732 671 3443",
    "sg:postcode":"07733",
    "sg:province":"NJ",
    "sg:website":"www.jenniferfurniture.com",
    "wof:name":"Jennifer Convertibles Inc",
    "wof:placetype":"venue"
},
  "geometry": {"coordinates":[-74.13825900000001,40.411302],"type":"Point"}
}