{
  "type": "Feature",
  "properties": {
    "iso:country":"US",
    "sg:address":"17 Shrewsbury Dr",
    "sg:city":"Livingston",
    "sg:classifiers":[
        {
            "category":"Professional",
            "subcategory":"Accounting & Tax Preparation",
            "type":"Services"
        }
    ],
    "sg:phone":"+1 973 992 8337",
    "sg:postcode":"07039",
    "sg:province":"NJ",
    "wof:name":"Bert Perl",
    "wof:placetype":"venue"
},
  "geometry": {"coordinates":[-74.29598300000001,40.801161],"type":"Point"}
}