{
  "type": "Feature",
  "properties": {
    "addr:full":"95 Broad St Red Bank NJ 07701",
    "addr:housenumber":"95",
    "addr:postcode":"07701",
    "addr:street":"Broad St",
    "iso:country":"US",
    "sg:address":"95 Broad St",
    "sg:city":"Red Bank",
    "sg:classifiers":[
        {
            "category":"Manufacturing",
            "subcategory":"Tools & Machinery",
            "type":"Manufacturing & Wholesale Goods"
        }
    ],
    "sg:phone":"+1 732 758 6646",
    "sg:postcode":"07701",
    "sg:province":"NJ",
    "sg:tags":[
        "machine",
        "embroidering"
    ],
    "wof:name":"Champion Embroidery",
    "wof:placetype":"venue"
},
  "geometry": {"coordinates":[-74.065212,40.349429],"type":"Point"}
}