{
  "type": "Feature",
  "properties": {
    "addr:full":"17 N Main St Pennington NJ 08534",
    "addr:housenumber":"17",
    "addr:postcode":"08534",
    "addr:street":"N Main St",
    "iso:country":"US",
    "sg:address":"17 N Main St",
    "sg:city":"Pennington",
    "sg:classifiers":[
        {
            "category":"Personal",
            "subcategory":"Beauty Salon",
            "type":"Services"
        }
    ],
    "sg:phone":"+1 609 818 9030",
    "sg:postcode":"08534",
    "sg:province":"NJ",
    "sg:tags":[
        "shop"
    ],
    "wof:name":"Salon 17",
    "wof:placetype":"venue"
},
  "geometry": {"coordinates":[-74.79176099999999,40.330859],"type":"Point"}
}