{
  "type": "Feature",
  "properties": {
    "iso:country":"US",
    "sg:address":"735 Promenade Blvd",
    "sg:city":"Bridgewater",
    "sg:classifiers":[
        {
            "category":"Autos & Motor Vehicles",
            "subcategory":"Auto Supplies",
            "type":"Retail Goods"
        }
    ],
    "sg:phone":"+1   ",
    "sg:postcode":"08807",
    "sg:province":"NJ",
    "wof:name":"Pep Boys",
    "wof:placetype":"venue"
},
  "geometry": {"coordinates":[-74.558156,40.566832],"type":"Point"}
}