{
  "type": "Feature",
  "properties": {
    "iso:country":"US",
    "sg:address":"504 Willow Turn",
    "sg:city":"Mount Laurel",
    "sg:classifiers":[
        {
            "category":"Manufacturing",
            "subcategory":"Printing",
            "type":"Manufacturing & Wholesale Goods"
        }
    ],
    "sg:phone":"+1 856 231 8685",
    "sg:postcode":"08054",
    "sg:province":"NJ",
    "sg:tags":[
        "periodical"
    ],
    "wof:name":"Iris Studios Inc",
    "wof:placetype":"venue"
},
  "geometry": {"coordinates":[-74.87690000000001,39.967009],"type":"Point"}
}