{
  "type": "Feature",
  "properties": {
    "addr:full":"376 N Fullerton Ave Montclair NJ 07043",
    "addr:housenumber":"376",
    "addr:postcode":"07043",
    "addr:street":"N Fullerton Ave",
    "iso:country":"US",
    "sg:address":"376 N Fullerton Ave",
    "sg:city":"Montclair",
    "sg:classifiers":[
        {
            "category":"Professional",
            "subcategory":"Management & Consulting",
            "type":"Services"
        }
    ],
    "sg:phone":"+1   ",
    "sg:postcode":"07043",
    "sg:province":"NJ",
    "sg:tags":[
        "business"
    ],
    "wof:name":"Sheila Crowell",
    "wof:placetype":"venue"
},
  "geometry": {"coordinates":[-74.20306100000001,40.833099],"type":"Point"}
}