{
  "type": "Feature",
  "properties": {
    "iso:country":"US",
    "sg:address":"156 S Leswing Ave",
    "sg:city":"Saddle Brook",
    "sg:classifiers":[
        {
            "category":"Building & Trades",
            "subcategory":"Plumbing",
            "type":"Services"
        }
    ],
    "sg:phone":"+1 201 587 0908",
    "sg:postcode":"07663",
    "sg:province":"NJ",
    "sg:tags":[
        "contractor"
    ],
    "wof:name":"Sra Lawn Sprinklers",
    "wof:placetype":"venue"
},
  "geometry": {"coordinates":[-74.096633,40.904342],"type":"Point"}
}