{
  "type": "Feature",
  "properties": {
    "iso:country":"US",
    "sg:address":"21 Muncy Dr",
    "sg:city":"West Long Branch",
    "sg:classifiers":[
        {
            "category":"Professional",
            "subcategory":"Management & Consulting",
            "type":"Services"
        }
    ],
    "sg:phone":"+1   ",
    "sg:postcode":"07764",
    "sg:province":"NJ",
    "sg:tags":[
        "business"
    ],
    "wof:name":"Rj Consulting of NJ Inc",
    "wof:placetype":"venue"
},
  "geometry": {"coordinates":[-74.02679000000001,40.287325],"type":"Point"}
}