{
  "type": "Feature",
  "properties": {
    "iso:country":"US",
    "sg:address":"77 Oakridge Ln",
    "sg:city":"Watchung",
    "sg:classifiers":[
        {
            "category":"Building & Trades",
            "subcategory":"Equipment Rental",
            "type":"Services"
        }
    ],
    "sg:phone":"+1 908 561 3439",
    "sg:postcode":"07069",
    "sg:province":"NJ",
    "sg:tags":[
        "heavy",
        "construction"
    ],
    "wof:name":"Doering Equipment Inc",
    "wof:placetype":"venue"
},
  "geometry": {"coordinates":[-74.439245,40.638544],"type":"Point"}
}