{
  "type": "Feature",
  "properties": {
    "addr:full":"82 Sykesville Rd Wrightstown NJ 08515",
    "addr:housenumber":"82",
    "addr:postcode":"08515",
    "addr:street":"Sykesville Rd",
    "iso:country":"US",
    "sg:address":"82 Sykesville Rd",
    "sg:city":"Wrightstown",
    "sg:classifiers":[
        {
            "category":"Retail",
            "subcategory":"Animal Services",
            "type":"Services"
        }
    ],
    "sg:phone":"+1 609 291 0159",
    "sg:postcode":"08515",
    "sg:province":"NJ",
    "wof:name":"Kennels At Columbus Inc",
    "wof:placetype":"venue"
},
  "geometry": {"coordinates":[-74.63054,40.10071],"type":"Point"}
}