{
  "type": "Feature",
  "properties": {
    "iso:country":"US",
    "sg:address":"5 Lawrenceville Pennington Rd",
    "sg:city":"Lawrenceville",
    "sg:classifiers":[
        {
            "category":"Professional",
            "type":"Services"
        }
    ],
    "sg:phone":"+1 609 896 1131",
    "sg:postcode":"08648",
    "sg:province":"NJ",
    "sg:tags":[
        "establishment"
    ],
    "wof:name":"Michael Angelo's",
    "wof:placetype":"venue"
},
  "geometry": {"coordinates":[-74.735452,40.290044],"type":"Point"}
}