{
  "type": "Feature",
  "properties": {
    "addr:full":"59 Washington Valley Rd Warren NJ 07059",
    "addr:housenumber":"59",
    "addr:postcode":"07059",
    "addr:street":"Washington Valley Rd",
    "iso:country":"US",
    "sg:address":"59 Washington Valley Rd",
    "sg:city":"Warren",
    "sg:classifiers":[
        {
            "category":"Professional",
            "subcategory":"Accounting & Tax Preparation",
            "type":"Services"
        }
    ],
    "sg:phone":"+1 732 356 6252",
    "sg:postcode":"07059",
    "sg:province":"NJ",
    "sg:tags":[
        "accountant"
    ],
    "wof:name":"Charles S Lang CPA",
    "wof:placetype":"venue"
},
  "geometry": {"coordinates":[-74.52042,40.604123],"type":"Point"}
}