{
  "type": "Feature",
  "properties": {
    "iso:country":"US",
    "sg:address":"225 Hutton St",
    "sg:city":"Jersey City",
    "sg:classifiers":[
        {
            "category":"Bars & Pubs",
            "type":"Food & Drink"
        }
    ],
    "sg:phone":"+1   ",
    "sg:postcode":"07307",
    "sg:province":"NJ",
    "sg:tags":[
        "drinking"
    ],
    "wof:name":"Monaghan & Renner Inc",
    "wof:placetype":"venue"
},
  "geometry": {"coordinates":[-74.05655299999999,40.74722],"type":"Point"}
}