{
  "type": "Feature",
  "properties": {
    "addr:full":"183 Market St Newark NJ 07102",
    "addr:housenumber":"183",
    "addr:postcode":"07102",
    "addr:street":"Market St",
    "iso:country":"US",
    "sg:address":"183 Market St",
    "sg:city":"Newark",
    "sg:classifiers":[
        {
            "category":"Shopping",
            "subcategory":"Beauty & Cosmetics",
            "type":"Retail Goods"
        }
    ],
    "sg:phone":"+1   ",
    "sg:postcode":"07102",
    "sg:province":"NJ",
    "sg:tags":[
        "reta",
        "supply"
    ],
    "wof:name":"Lucky Beauty Supply",
    "wof:placetype":"venue"
},
  "geometry": {"coordinates":[-74.17099899999999,40.73534],"type":"Point"}
}