{
  "type": "Feature",
  "properties": {
    "addr:full":"41 Locust Ave Wallington NJ 07057",
    "addr:housenumber":"41",
    "addr:postcode":"07057",
    "addr:street":"Locust Ave",
    "iso:country":"US",
    "sg:address":"41 Locust Ave",
    "sg:city":"Wallington",
    "sg:classifiers":[
        {
            "category":"Autos & Motor Vehicles",
            "subcategory":"Automobile Sales",
            "type":"Retail Goods"
        }
    ],
    "sg:phone":"+1 973 778 9112",
    "sg:postcode":"07057",
    "sg:province":"NJ",
    "sg:tags":[
        "limo"
    ],
    "wof:name":"Am Pm Limousine Service Llc",
    "wof:placetype":"venue"
},
  "geometry": {"coordinates":[-74.113068,40.851277],"type":"Point"}
}