{
  "type": "Feature",
  "properties": {
    "iso:country":"US",
    "sg:address":"1595 5th St",
    "sg:city":"Trenton",
    "sg:classifiers":[
        {
            "category":"Professional",
            "subcategory":"Advertising",
            "type":"Services"
        }
    ],
    "sg:phone":"+1 609 771 3849",
    "sg:postcode":"08638",
    "sg:province":"NJ",
    "sg:tags":[
        "mailing",
        "shipping"
    ],
    "wof:name":"K & B Enterprises",
    "wof:placetype":"venue"
},
  "geometry": {"coordinates":[-74.76066899999999,40.246933],"type":"Point"}
}