{
  "type": "Feature",
  "properties": {
    "addr:full":"763 Stelton St Teaneck NJ 07666",
    "addr:housenumber":"763",
    "addr:postcode":"07666",
    "addr:street":"Stelton St",
    "iso:country":"US",
    "sg:address":"763 Stelton St",
    "sg:city":"Teaneck",
    "sg:classifiers":[
        {
            "category":"Professional",
            "subcategory":"Computer Services",
            "type":"Services"
        }
    ],
    "sg:phone":"+1 201 833 9411",
    "sg:postcode":"07666",
    "sg:province":"NJ",
    "sg:tags":[
        "prepackaged",
        "software"
    ],
    "wof:name":"Bible Tech",
    "wof:placetype":"venue"
},
  "geometry": {"coordinates":[-74.004046,40.882447],"type":"Point"}
}