{
  "type": "Feature",
  "properties": {
    "addr:full":"50 Magnolia Rd Pemberton NJ 08068",
    "addr:housenumber":"50",
    "addr:postcode":"08068",
    "addr:street":"Magnolia Rd",
    "iso:country":"US",
    "sg:address":"50 Magnolia Rd",
    "sg:city":"Pemberton",
    "sg:classifiers":[
        {
            "category":"Restaurant",
            "type":"Food & Drink"
        }
    ],
    "sg:phone":"+1 609 894 8073",
    "sg:postcode":"08068",
    "sg:province":"NJ",
    "wof:name":"Mario & Frank's Pizza & Subs",
    "wof:placetype":"venue"
},
  "geometry": {"coordinates":[-74.679315,39.963588],"type":"Point"}
}