{
  "type": "Feature",
  "properties": {
    "addr:full":"1904 Owl Ct Cherry Hill NJ 08003",
    "addr:housenumber":"1904",
    "addr:postcode":"08003",
    "addr:street":"Owl Ct",
    "iso:country":"US",
    "sg:address":"1904 Owl Ct",
    "sg:city":"Cherry Hill",
    "sg:classifiers":[
        {
            "category":"Professional",
            "subcategory":"Management & Consulting",
            "type":"Services"
        }
    ],
    "sg:phone":"+1   ",
    "sg:postcode":"08003",
    "sg:province":"NJ",
    "wof:name":"703 Management Corp",
    "wof:placetype":"venue"
},
  "geometry": {"coordinates":[-74.97617,39.876246],"type":"Point"}
}