{
  "type": "Feature",
  "properties": {
    "iso:country":"US",
    "sg:address":"2401 Good Intent Rd",
    "sg:city":"Deptford",
    "sg:classifiers":[
        {
            "category":"Government",
            "subcategory":"Fire Station",
            "type":"Public Place"
        }
    ],
    "sg:phone":"+1 856 232 6100",
    "sg:postcode":"08096",
    "sg:province":"NJ",
    "sg:tags":[
        "department"
    ],
    "wof:name":"Blackwood Terrace Firehouse",
    "wof:placetype":"venue"
},
  "geometry": {"coordinates":[-75.08796,39.807063],"type":"Point"}
}