{
  "type": "Feature",
  "properties": {
    "iso:country":"US",
    "sg:address":"93 Fostertown Rd",
    "sg:city":"Lumberton",
    "sg:classifiers":[
        {
            "category":"Real Estate",
            "subcategory":"Real Estate Operator",
            "type":"Services"
        }
    ],
    "sg:phone":"+1 609 261 8893",
    "sg:postcode":"08048",
    "sg:province":"NJ",
    "sg:tags":[
        "building",
        "ope",
        "apartment",
        "nonresidential"
    ],
    "wof:name":"Fessler Realty Partners",
    "wof:placetype":"venue"
},
  "geometry": {"coordinates":[-74.80988499999999,39.935601],"type":"Point"}
}