{
  "type": "Feature",
  "properties": {
    "iso:country":"US",
    "sg:address":"640 US Hwy 22",
    "sg:city":"Hillside",
    "sg:classifiers":[
        {
            "category":"Personal",
            "type":"Services"
        }
    ],
    "sg:phone":"+1   ",
    "sg:postcode":"07205",
    "sg:province":"NJ",
    "wof:name":"Absolute Relaxation",
    "wof:placetype":"venue"
},
  "geometry": {"coordinates":[-74.245548,40.697829],"type":"Point"}
}