{
  "type": "Feature",
  "properties": {
    "iso:country":"US",
    "sg:address":"77 Lime Kiln Rd",
    "sg:city":"Columbia",
    "sg:classifiers":[
        {
            "category":"Building & Trades",
            "subcategory":"Construction",
            "type":"Services"
        },
        {
            "category":"Building & Trades",
            "subcategory":"Plumbing",
            "type":"Services"
        }
    ],
    "sg:phone":"+1 908 459 4404",
    "sg:postcode":"07832",
    "sg:province":"NJ",
    "sg:tags":[
        "excavation",
        "excavating",
        "contractor"
    ],
    "wof:name":"John Osmun Excavating Inc",
    "wof:placetype":"venue"
},
  "geometry": {"coordinates":[-75.04003,40.91577],"type":"Point"}
}