{
  "type": "Feature",
  "properties": {
    "iso:country":"US",
    "sg:address":"2919 US Hwy 206",
    "sg:city":"Columbus",
    "sg:classifiers":[
        {
            "category":"Restaurant",
            "type":"Food & Drink"
        }
    ],
    "sg:phone":"+1 609 267 0166",
    "sg:postcode":"08022",
    "sg:province":"NJ",
    "sg:tags":[
        "pizza"
    ],
    "wof:name":"Pete's Pizza",
    "wof:placetype":"venue"
},
  "geometry": {"coordinates":[-74.72479300000001,40.053215],"type":"Point"}
}