{
  "type": "Feature",
  "properties": {
    "iso:country":"US",
    "sg:address":"3502 Westfield Ave",
    "sg:city":"Camden",
    "sg:classifiers":[
        {
            "category":"Communications",
            "type":"Services"
        }
    ],
    "sg:phone":"+1 856 365 8181",
    "sg:postcode":"08105",
    "sg:province":"NJ",
    "sg:tags":[
        "paging",
        "signaling"
    ],
    "wof:name":"Nsl Paging Svc.",
    "wof:placetype":"venue"
},
  "geometry": {"coordinates":[-75.075937,39.951972],"type":"Point"}
}