{
  "type": "Feature",
  "properties": {
    "addr:full":"775 Riverside Ave Lyndhurst NJ 07071",
    "addr:housenumber":"775",
    "addr:postcode":"07071",
    "addr:street":"Riverside Ave",
    "iso:country":"US",
    "sg:address":"775 Riverside Ave",
    "sg:city":"Lyndhurst",
    "sg:classifiers":[
        {
            "category":"Retail",
            "subcategory":"Repair Shop",
            "type":"Services"
        }
    ],
    "sg:phone":"+1 201 334 3425",
    "sg:postcode":"07071",
    "sg:province":"NJ",
    "sg:tags":[
        "lock",
        "locksmith"
    ],
    "wof:name":"All Day Emergency Locksmith",
    "wof:placetype":"venue"
},
  "geometry": {"coordinates":[-74.13497599999999,40.805345],"type":"Point"}
}