{
  "type": "Feature",
  "properties": {
    "iso:country":"US",
    "sg:address":"30 Chestnut Ridge Rd",
    "sg:city":"Montvale",
    "sg:classifiers":[
        {
            "category":"Shopping",
            "subcategory":"Hobbies, Toys, & Games",
            "type":"Retail Goods"
        }
    ],
    "sg:phone":"+1   ",
    "sg:postcode":"07645",
    "sg:province":"NJ",
    "wof:name":"Doll Heaven",
    "wof:placetype":"venue"
},
  "geometry": {"coordinates":[-74.069681,41.050504],"type":"Point"}
}