{
  "type": "Feature",
  "properties": {
    "addr:full":"46 Calder Ct Marlboro NJ 07746",
    "addr:housenumber":"46",
    "addr:postcode":"07746",
    "addr:street":"Calder Ct",
    "iso:country":"US",
    "sg:address":"46 Calder Ct",
    "sg:city":"Marlboro",
    "sg:classifiers":[
        {
            "category":"Professional",
            "subcategory":"Management & Consulting",
            "type":"Services"
        }
    ],
    "sg:phone":"+1   ",
    "sg:postcode":"07746",
    "sg:province":"NJ",
    "sg:tags":[
        "rep",
        "manufacturer"
    ],
    "wof:name":"Rak Global Holdings",
    "wof:placetype":"venue"
},
  "geometry": {"coordinates":[-74.253316,40.327927],"type":"Point"}
}