{
  "type": "Feature",
  "properties": {
    "iso:country":"US",
    "sg:address":"461 Central Ave",
    "sg:city":"Newark",
    "sg:classifiers":[
        {
            "category":"Government",
            "subcategory":"Office",
            "type":"Public Place"
        },
        {
            "category":"Government",
            "subcategory":"Jail",
            "type":"Public Place"
        }
    ],
    "sg:phone":"+1 973 648 7078",
    "sg:postcode":"07107",
    "sg:province":"NJ",
    "sg:tags":[
        "correctional",
        "center"
    ],
    "wof:name":"Essex Residential Group Center",
    "wof:placetype":"venue"
},
  "geometry": {"coordinates":[-74.191771,40.7478],"type":"Point"}
}