{
  "type": "Feature",
  "properties": {
    "iso:country":"US",
    "sg:address":"43 Ferry St",
    "sg:city":"Newark",
    "sg:classifiers":[
        {
            "category":"Education",
            "subcategory":"School",
            "type":"Public Place"
        }
    ],
    "sg:phone":"+1 973 465 4121",
    "sg:postcode":"07105",
    "sg:province":"NJ",
    "sg:tags":[
        "academic",
        "special"
    ],
    "wof:name":"American English Ctr",
    "wof:placetype":"venue"
},
  "geometry": {"coordinates":[-74.163399,40.732569],"type":"Point"}
}