{
  "type": "Feature",
  "properties": {
    "iso:country":"US",
    "sg:address":"888 Haddon Ave",
    "sg:city":"Collingswood",
    "sg:classifiers":[
        {
            "category":"Professional",
            "subcategory":"Lawyer & Legal Services",
            "type":"Services"
        }
    ],
    "sg:phone":"+1 856 869 8820",
    "sg:postcode":"08108",
    "sg:province":"NJ",
    "wof:name":"Hatzell James ESQ",
    "wof:placetype":"venue"
},
  "geometry": {"coordinates":[-75.063698,39.914799],"type":"Point"}
}