{
  "type": "Feature",
  "properties": {
    "addr:full":"614 Kennedy St Palmyra NJ 08065",
    "addr:housenumber":"614",
    "addr:postcode":"08065",
    "addr:street":"Kennedy St",
    "iso:country":"US",
    "sg:address":"614 Kennedy St",
    "sg:city":"Palmyra",
    "sg:classifiers":[
        {
            "category":"Home & Garden",
            "subcategory":"Kitchen Supply",
            "type":"Retail Goods"
        }
    ],
    "sg:phone":"+1 856 829 1800",
    "sg:postcode":"08065",
    "sg:province":"NJ",
    "sg:tags":[
        "food",
        "processing",
        "equipment"
    ],
    "sg:website":"http://www.bridgeonline.com",
    "wof:name":"Bridge Machine Co Inc",
    "wof:placetype":"venue"
},
  "geometry": {"coordinates":[-75.034452,40.002695],"type":"Point"}
}