{
  "type": "Feature",
  "properties": {
    "iso:country":"US",
    "sg:address":"469 S White Horse Pike",
    "sg:city":"Hammonton",
    "sg:classifiers":[
        {
            "category":"Professional",
            "subcategory":"Business Services",
            "type":"Services"
        }
    ],
    "sg:phone":"+1   ",
    "sg:postcode":"08037",
    "sg:province":"NJ",
    "wof:name":"South Jersey Argo Sales",
    "wof:placetype":"venue"
},
  "geometry": {"coordinates":[-74.84357300000001,39.696596],"type":"Point"}
}