{
  "type": "Feature",
  "properties": {
    "iso:country":"US",
    "sg:address":"76 Erie Ave",
    "sg:city":"Rockaway",
    "sg:classifiers":[
        {
            "category":"Wholesale",
            "subcategory":"Non-durable Goods",
            "type":"Manufacturing & Wholesale Goods"
        }
    ],
    "sg:phone":"+1 973 625 1644",
    "sg:postcode":"07866",
    "sg:province":"NJ",
    "wof:name":"Scorpion Distributors",
    "wof:placetype":"venue"
},
  "geometry": {"coordinates":[-74.50501199999999,40.936279],"type":"Point"}
}