{
  "type": "Feature",
  "properties": {
    "iso:country":"US",
    "sg:address":"436 W Frech Ave",
    "sg:city":"Manville",
    "sg:classifiers":[
        {
            "category":"Professional",
            "subcategory":"Computer Services",
            "type":"Services"
        }
    ],
    "sg:phone":"+1 908 627 7118",
    "sg:postcode":"08835",
    "sg:province":"NJ",
    "sg:tags":[
        "music",
        "blogs",
        "music-search",
        "music-news"
    ],
    "sg:website":"http://itmay.be",
    "wof:name":"itMayBe Media",
    "wof:placetype":"venue"
},
  "geometry": {"coordinates":[-74.600655,40.531066],"type":"Point"}
}