{
  "type": "Feature",
  "properties": {
    "iso:country":"US",
    "sg:address":"53 Beverly Rd",
    "sg:city":"Oradell",
    "sg:classifiers":[
        {
            "category":"Professional",
            "subcategory":"Management & Consulting",
            "type":"Services"
        }
    ],
    "sg:phone":"+1   ",
    "sg:postcode":"07649",
    "sg:province":"NJ",
    "sg:tags":[
        "business"
    ],
    "wof:name":"Ddc Inc",
    "wof:placetype":"venue"
},
  "geometry": {"coordinates":[-74.028419,40.942781],"type":"Point"}
}