{
  "type": "Feature",
  "properties": {
    "iso:country":"US",
    "sg:address":"314 Heather Dr",
    "sg:city":"Mount Laurel",
    "sg:classifiers":[
        {
            "category":"Manufacturing",
            "subcategory":"Printing",
            "type":"Manufacturing & Wholesale Goods"
        }
    ],
    "sg:phone":"+1 856 787 8409",
    "sg:postcode":"08054",
    "sg:province":"NJ",
    "sg:tags":[
        "lithographic",
        "commercial"
    ],
    "wof:name":"Freedom Press & Imaging",
    "wof:placetype":"venue"
},
  "geometry": {"coordinates":[-74.982799,39.927516],"type":"Point"}
}