{
  "type": "Feature",
  "properties": {
    "iso:country":"US",
    "sg:address":"219 N Delavan Ave",
    "sg:city":"Margate City",
    "sg:classifiers":[
        {
            "category":"Real Estate",
            "subcategory":"Real Estate Agent",
            "type":"Services"
        }
    ],
    "sg:phone":"+1   ",
    "sg:postcode":"08402",
    "sg:province":"NJ",
    "wof:name":"Veronica Realty LLC",
    "wof:placetype":"venue"
},
  "geometry": {"coordinates":[-74.499995,39.335297],"type":"Point"}
}