{
  "type": "Feature",
  "properties": {
    "iso:country":"US",
    "sg:address":"1049 Kingsland Ln",
    "sg:city":"Fort Lee",
    "sg:classifiers":[
        {
            "category":"Professional",
            "subcategory":"Management & Consulting",
            "type":"Services"
        }
    ],
    "sg:phone":"+1   ",
    "sg:postcode":"07024",
    "sg:province":"NJ",
    "sg:tags":[
        "business"
    ],
    "wof:name":"Jmz International Trading Inc",
    "wof:placetype":"venue"
},
  "geometry": {"coordinates":[-73.987627,40.838229],"type":"Point"}
}