{
  "type": "Feature",
  "properties": {
    "iso:country":"US",
    "sg:address":"578 Union Ave",
    "sg:city":"Middlesex",
    "sg:classifiers":[
        {
            "category":"Restaurant",
            "type":"Food & Drink"
        }
    ],
    "sg:phone":"+1 732 302 9920",
    "sg:postcode":"08846",
    "sg:province":"NJ",
    "sg:tags":[
        "management"
    ],
    "wof:name":"Cafe Havana",
    "wof:placetype":"venue"
},
  "geometry": {"coordinates":[-74.506756,40.577486],"type":"Point"}
}