{
  "type": "Feature",
  "properties": {
    "iso:country":"US",
    "sg:address":"477 3rd St",
    "sg:city":"Atco",
    "sg:classifiers":[
        {
            "category":"Building & Trades",
            "subcategory":"Construction",
            "type":"Services"
        }
    ],
    "sg:phone":"+1 856 768 0021",
    "sg:postcode":"08004",
    "sg:province":"NJ",
    "sg:tags":[
        "new",
        "remodeling",
        "home"
    ],
    "wof:name":"Everlast General Construction",
    "wof:placetype":"venue"
},
  "geometry": {"coordinates":[-74.8836,39.775869],"type":"Point"}
}