{
  "type": "Feature",
  "properties": {
    "addr:full":"825 S Concourse Keyport NJ 07735",
    "addr:housenumber":"825",
    "addr:postcode":"07735",
    "addr:street":"S Concourse",
    "iso:country":"US",
    "sg:address":"825 S Concourse",
    "sg:city":"Keyport",
    "sg:classifiers":[
        {
            "category":"Food & Beverages",
            "subcategory":"Groceries & Convenience Stores",
            "type":"Retail Goods"
        }
    ],
    "sg:phone":"+1 732 566 6906",
    "sg:postcode":"07735",
    "sg:province":"NJ",
    "sg:tags":[
        "market"
    ],
    "wof:name":"Krauszer's",
    "wof:placetype":"venue"
},
  "geometry": {"coordinates":[-74.218014,40.444238],"type":"Point"}
}