{
  "type": "Feature",
  "properties": {
    "iso:country":"US",
    "sg:address":"156 Mount Pleasant Ave",
    "sg:city":"Rockaway",
    "sg:classifiers":[
        {
            "category":"Organizations",
            "subcategory":"Religious Organization",
            "type":"Services"
        }
    ],
    "sg:phone":"+1   ",
    "sg:postcode":"07866",
    "sg:province":"NJ",
    "wof:name":"English Dver Cngrgtion Jhovahs",
    "wof:placetype":"venue"
},
  "geometry": {"coordinates":[-74.521119,40.899063],"type":"Point"}
}