{
  "type": "Feature",
  "properties": {
    "iso:country":"US",
    "sg:address":"935 Burnt Tavern Rd",
    "sg:city":"Brick",
    "sg:classifiers":[
        {
            "category":"Freight",
            "type":"Transportation"
        }
    ],
    "sg:phone":"+1 732 458 2700",
    "sg:postcode":"08724",
    "sg:province":"NJ",
    "sg:tags":[
        "special"
    ],
    "wof:name":"Ocean Monmouth Self Storage",
    "wof:placetype":"venue"
},
  "geometry": {"coordinates":[-74.122542,40.093968],"type":"Point"}
}