{
  "type": "Feature",
  "properties": {
    "iso:country":"US",
    "sg:address":"449 Central Ave",
    "sg:city":"Jersey City",
    "sg:classifiers":[
        {
            "category":"Restaurant",
            "type":"Food & Drink"
        }
    ],
    "sg:phone":"+1 201 798 0230",
    "sg:postcode":"07307",
    "sg:province":"NJ",
    "wof:name":"Francecso Restaurant",
    "wof:placetype":"venue"
},
  "geometry": {"coordinates":[-74.046587,40.750113],"type":"Point"}
}