{
  "type": "Feature",
  "properties": {
    "addr:full":"1048 N 19th St Camden NJ 08105",
    "addr:housenumber":"1048",
    "addr:postcode":"08105",
    "addr:street":"N 19Th St",
    "iso:country":"US",
    "sg:address":"1048 N 19th St",
    "sg:city":"Camden",
    "sg:classifiers":[
        {
            "category":"Food & Beverages",
            "subcategory":"Groceries & Convenience Stores",
            "type":"Retail Goods"
        }
    ],
    "sg:phone":"+1 856 635 0400",
    "sg:postcode":"08105",
    "sg:province":"NJ",
    "sg:tags":[
        "grocer"
    ],
    "wof:name":"Fermin Grocery",
    "wof:placetype":"venue"
},
  "geometry": {"coordinates":[-75.09940899999999,39.951626],"type":"Point"}
}