{
  "type": "Feature",
  "properties": {
    "iso:country":"US",
    "sg:address":"53 Braen Ave",
    "sg:city":"Hawthorne",
    "sg:classifiers":[
        {
            "category":"Shopping",
            "subcategory":"Clothing, Apparel, & Fashions",
            "type":"Retail Goods"
        }
    ],
    "sg:phone":"+1 973 427 0499",
    "sg:postcode":"07506",
    "sg:province":"NJ",
    "sg:tags":[
        "glove"
    ],
    "wof:name":"The Gun Glove",
    "wof:placetype":"venue"
},
  "geometry": {"coordinates":[-74.153676,40.971404],"type":"Point"}
}