{
  "type": "Feature",
  "properties": {
    "addr:full":"422 Willow Ave Hoboken NJ 07030",
    "addr:housenumber":"422",
    "addr:postcode":"07030",
    "addr:street":"Willow Ave",
    "iso:country":"US",
    "sg:address":"422 Willow Ave",
    "sg:city":"Hoboken",
    "sg:classifiers":[
        {
            "category":"Education",
            "subcategory":"School",
            "type":"Public Place"
        }
    ],
    "sg:phone":"+1 201 653 5548",
    "sg:postcode":"07030",
    "sg:province":"NJ",
    "sg:tags":[
        "elementary",
        "private"
    ],
    "sg:website":"www.mustardseedschool.org",
    "wof:name":"Mustard Seed School",
    "wof:placetype":"venue"
},
  "geometry": {"coordinates":[-74.03299699999999,40.7425],"type":"Point"}
}