{
  "type": "Feature",
  "properties": {
    "iso:country":"US",
    "sg:address":"651 Willow Grove St",
    "sg:city":"Hackettstown",
    "sg:classifiers":[
        {
            "category":"Health Services",
            "subcategory":"Doctor",
            "type":"Services"
        }
    ],
    "sg:phone":"+1 908 879 2222",
    "sg:postcode":"07840",
    "sg:province":"NJ",
    "sg:tags":[
        "physician",
        "surgeon"
    ],
    "wof:name":"Plastic Surgery Assoc",
    "wof:placetype":"venue"
},
  "geometry": {"coordinates":[-74.812106,40.863789],"type":"Point"}
}