{
  "type": "Feature",
  "properties": {
    "iso:country":"US",
    "sg:address":"810 Hamburg Tpke",
    "sg:city":"Wayne",
    "sg:classifiers":[
        {
            "category":"Coffee & Tea",
            "type":"Food & Drink"
        }
    ],
    "sg:menulink":"http://www.allmenus.com/nj/wayne/125820-starbucks-coffee/menu/",
    "sg:phone":"+1 973 872 6406",
    "sg:postcode":"07470",
    "sg:province":"NJ",
    "sg:tags":[
        "american"
    ],
    "wof:name":"Starbucks Coffee",
    "wof:placetype":"venue"
},
  "geometry": {"coordinates":[-74.225461,40.958383],"type":"Point"}
}