{
  "type": "Feature",
  "properties": {
    "addr:full":"835 Cooper Landing Rd Cherry Hill NJ 08002",
    "addr:housenumber":"835",
    "addr:postcode":"08002",
    "addr:street":"Cooper Landing Rd",
    "iso:country":"US",
    "sg:address":"835 Cooper Landing Rd",
    "sg:city":"Cherry Hill",
    "sg:classifiers":[
        {
            "category":"Shopping",
            "subcategory":"Jewelry",
            "type":"Retail Goods"
        }
    ],
    "sg:phone":"+1 856 667 2177",
    "sg:postcode":"08002",
    "sg:province":"NJ",
    "sg:tags":[
        "jeweler"
    ],
    "wof:name":"Crossroads Jewelers",
    "wof:placetype":"venue"
},
  "geometry": {"coordinates":[-75.010057,39.93918],"type":"Point"}
}