{
  "type": "Feature",
  "properties": {
    "addr:full":"36 Apple Tree Ln Old Bridge NJ 08857",
    "addr:housenumber":"36",
    "addr:postcode":"08857",
    "addr:street":"Apple Tree Ln",
    "iso:country":"US",
    "sg:address":"36 Apple Tree Ln",
    "sg:city":"Old Bridge",
    "sg:classifiers":[
        {
            "category":"Building & Trades",
            "subcategory":"Landscaping Services",
            "type":"Services"
        }
    ],
    "sg:phone":"+1 516 766 2863",
    "sg:postcode":"08857",
    "sg:province":"NJ",
    "sg:tags":[
        "designer",
        "landscape"
    ],
    "wof:name":"Asla Dstrbtng",
    "wof:placetype":"venue"
},
  "geometry": {"coordinates":[-74.292333,40.430442],"type":"Point"}
}