{
  "type": "Feature",
  "properties": {
    "addr:full":"24 Wingate Way Dunellen NJ 08812",
    "addr:housenumber":"24",
    "addr:postcode":"08812",
    "addr:street":"Wingate Way",
    "iso:country":"US",
    "sg:address":"24 Wingate Way",
    "sg:city":"Dunellen",
    "sg:classifiers":[
        {
            "category":"Professional",
            "type":"Services"
        }
    ],
    "sg:phone":"+1   ",
    "sg:postcode":"08812",
    "sg:province":"NJ",
    "wof:name":"Synergix Inc",
    "wof:placetype":"venue"
},
  "geometry": {"coordinates":[-74.49518999999999,40.596045],"type":"Point"}
}