{
  "type": "Feature",
  "properties": {
    "addr:full":"63 Grand Ave River Edge NJ 07661",
    "addr:housenumber":"63",
    "addr:postcode":"07661",
    "addr:street":"Grand Ave",
    "iso:country":"US",
    "sg:address":"63 Grand Ave",
    "sg:city":"River Edge",
    "sg:classifiers":[
        {
            "category":"Wholesale",
            "subcategory":"Apparel",
            "type":"Manufacturing & Wholesale Goods"
        }
    ],
    "sg:phone":"+1 201 342 8300",
    "sg:postcode":"07661",
    "sg:province":"NJ",
    "sg:tags":[
        "athletic",
        "foot",
        "wholesaling",
        "representative",
        "manufacturer"
    ],
    "wof:name":"Kittredge and Associates Inc",
    "wof:placetype":"venue"
},
  "geometry": {"coordinates":[-74.0361,40.911259],"type":"Point"}
}