{
  "type": "Feature",
  "properties": {
    "iso:country":"US",
    "sg:address":"247 Market St",
    "sg:city":"Elmwood Park",
    "sg:classifiers":[
        {
            "category":"Professional",
            "subcategory":"Business Services",
            "type":"Services"
        }
    ],
    "sg:phone":"+1   ",
    "sg:postcode":"07407",
    "sg:province":"NJ",
    "wof:name":"Rand Assoc",
    "wof:placetype":"venue"
},
  "geometry": {"coordinates":[-74.120169,40.900392],"type":"Point"}
}