{
  "type": "Feature",
  "properties": {
    "addr:full":"92 Shaler Ave Fairview NJ 07022",
    "addr:housenumber":"92",
    "addr:postcode":"07022",
    "addr:street":"Shaler Ave",
    "iso:country":"US",
    "sg:address":"92 Shaler Ave",
    "sg:city":"Fairview",
    "sg:classifiers":[
        {
            "category":"Building & Trades",
            "subcategory":"Plumbing",
            "type":"Services"
        }
    ],
    "sg:phone":"+1 201 840 9003",
    "sg:postcode":"07022",
    "sg:province":"NJ",
    "sg:tags":[
        "contractor"
    ],
    "wof:name":"Calibe Mechanical Prepping",
    "wof:placetype":"venue"
},
  "geometry": {"coordinates":[-73.99806100000001,40.810574],"type":"Point"}
}