{
  "type": "Feature",
  "properties": {
    "addr:full":"359 S Union Ave Cranford NJ 07016",
    "addr:housenumber":"359",
    "addr:postcode":"07016",
    "addr:street":"S Union Ave",
    "iso:country":"US",
    "sg:address":"359 S Union Ave",
    "sg:city":"Cranford",
    "sg:classifiers":[
        {
            "category":"Professional",
            "subcategory":"Business Services",
            "type":"Services"
        }
    ],
    "sg:phone":"+1 908 276 1818",
    "sg:postcode":"07016",
    "sg:province":"NJ",
    "wof:name":"R V G Inc",
    "wof:placetype":"venue"
},
  "geometry": {"coordinates":[-74.314818,40.645585],"type":"Point"}
}