{
  "type": "Feature",
  "properties": {
    "iso:country":"US",
    "sg:address":"338 Kearny Ave",
    "sg:city":"Kearny",
    "sg:classifiers":[
        {
            "category":"Food & Beverages",
            "subcategory":"Meat & Fish",
            "type":"Retail Goods"
        }
    ],
    "sg:phone":"+1   ",
    "sg:postcode":"07032",
    "sg:province":"NJ",
    "sg:tags":[
        "gourmet"
    ],
    "wof:name":"Stewarts",
    "wof:placetype":"venue"
},
  "geometry": {"coordinates":[-74.14994799999999,40.761802],"type":"Point"}
}