{
  "type": "Feature",
  "properties": {
    "addr:full":"200 Ave L Newark NJ 07105",
    "addr:housenumber":"200",
    "addr:postcode":"07105",
    "addr:street":"Ave",
    "iso:country":"US",
    "sg:address":"200 Ave L",
    "sg:city":"Newark",
    "sg:classifiers":[
        {
            "category":"Wholesale",
            "subcategory":"Electrical",
            "type":"Manufacturing & Wholesale Goods"
        }
    ],
    "sg:phone":"+1 973 344 3771",
    "sg:postcode":"07105",
    "sg:province":"NJ",
    "sg:tags":[
        "control",
        "security",
        "system"
    ],
    "sg:website":"www.thevikinggroup.com",
    "wof:name":"Viking Industrial Security Inc",
    "wof:placetype":"venue"
},
  "geometry": {"coordinates":[-74.142202,40.723785],"type":"Point"}
}