{
  "type": "Feature",
  "properties": {
    "iso:country":"US",
    "sg:address":"143 Little York Mount Pleasant Rd",
    "sg:city":"Milford",
    "sg:classifiers":[
        {
            "category":"Wholesale",
            "subcategory":"Auto Parts",
            "type":"Manufacturing & Wholesale Goods"
        }
    ],
    "sg:phone":"+1 908 578 0542",
    "sg:postcode":"08848",
    "sg:province":"NJ",
    "sg:tags":[
        "automotive",
        "supply"
    ],
    "wof:name":"Metric Solutions",
    "wof:placetype":"venue"
},
  "geometry": {"coordinates":[-75.054678,40.584052],"type":"Point"}
}