{
  "type": "Feature",
  "properties": {
    "addr:full":"1501 Buckingham Cir Middletown NJ 07748",
    "addr:housenumber":"1501",
    "addr:postcode":"07748",
    "addr:street":"Buckingham Cir",
    "iso:country":"US",
    "sg:address":"1501 Buckingham Cir",
    "sg:city":"Middletown",
    "sg:classifiers":[
        {
            "category":"Professional",
            "subcategory":"Advertising",
            "type":"Services"
        }
    ],
    "sg:phone":"+1 732 671 3121",
    "sg:postcode":"07748",
    "sg:province":"NJ",
    "sg:tags":[
        "guide"
    ],
    "wof:name":"Emily Sparano",
    "wof:placetype":"venue"
},
  "geometry": {"coordinates":[-74.091628,40.383254],"type":"Point"}
}