{
  "type": "Feature",
  "properties": {
    "addr:full":"75 Alexander Ave Livingston NJ 07043",
    "addr:housenumber":"75",
    "addr:postcode":"07043",
    "addr:street":"Alexander Ave",
    "iso:country":"US",
    "sg:address":"75 Alexander Ave",
    "sg:city":"Livingston",
    "sg:classifiers":[
        {
            "category":"Health Services",
            "subcategory":"Medical Lab",
            "type":"Services"
        }
    ],
    "sg:phone":"+1 973 422 1800",
    "sg:postcode":"07043",
    "sg:province":"NJ",
    "sg:tags":[
        "laboratory",
        "dental"
    ],
    "wof:name":"Reinoso Dental Studio Inc",
    "wof:placetype":"venue"
},
  "geometry": {"coordinates":[-74.189116,40.848142],"type":"Point"}
}