{
  "type": "Feature",
  "properties": {
    "addr:full":"139 Main St Little Falls NJ 07424",
    "addr:housenumber":"139",
    "addr:postcode":"07424",
    "addr:street":"Main St",
    "iso:country":"US",
    "sg:address":"139 Main St",
    "sg:city":"Little Falls",
    "sg:classifiers":[
        {
            "category":"Organizations",
            "subcategory":"Religious Organization",
            "type":"Services"
        }
    ],
    "sg:phone":"+1   ",
    "sg:postcode":"07424",
    "sg:province":"NJ",
    "wof:name":"United Methodist Church",
    "wof:placetype":"venue"
},
  "geometry": {"coordinates":[-74.23161,40.881936],"type":"Point"}
}