{
  "type": "Feature",
  "properties": {
    "iso:country":"US",
    "sg:address":"8 Bonnell St",
    "sg:city":"Flemington",
    "sg:classifiers":[
        {
            "category":"Building & Trades",
            "subcategory":"Construction",
            "type":"Services"
        }
    ],
    "sg:phone":"+1 908 782 1929",
    "sg:postcode":"08822",
    "sg:province":"NJ",
    "sg:tags":[
        "painter"
    ],
    "wof:name":"Scot Christopher Rule",
    "wof:placetype":"venue"
},
  "geometry": {"coordinates":[-74.861485,40.509366],"type":"Point"}
}