{
  "type": "Feature",
  "properties": {
    "iso:country":"US",
    "sg:address":"11 Tanglewood Ln",
    "sg:city":"Mountainside",
    "sg:classifiers":[
        {
            "category":"Autos & Motor Vehicles",
            "subcategory":"Automobile Sales",
            "type":"Retail Goods"
        }
    ],
    "sg:phone":"+1 908 654 6111",
    "sg:postcode":"07092",
    "sg:province":"NJ",
    "sg:tags":[
        "limo"
    ],
    "wof:name":"B & M Limousine Service",
    "wof:placetype":"venue"
},
  "geometry": {"coordinates":[-74.3484,40.6708],"type":"Point"}
}