{
  "type": "Feature",
  "properties": {
    "iso:country":"US",
    "sg:address":"201 Columbia Tpke",
    "sg:city":"Florham Park",
    "sg:classifiers":[
        {
            "category":"Health Services",
            "subcategory":"Chiropractor",
            "type":"Services"
        }
    ],
    "sg:phone":"+1 973 660 0090",
    "sg:postcode":"07932",
    "sg:province":"NJ",
    "wof:name":"Summers Spine Center PA",
    "wof:placetype":"venue"
},
  "geometry": {"coordinates":[-74.40428300000001,40.789742],"type":"Point"}
}