{
  "type": "Feature",
  "properties": {
    "iso:country":"US",
    "sg:address":"10 W Hanover Ave",
    "sg:city":"Randolph",
    "sg:classifiers":[
        {
            "category":"Health Services",
            "subcategory":"Doctor",
            "type":"Services"
        }
    ],
    "sg:phone":"+1 973 895 4600",
    "sg:postcode":"07869",
    "sg:province":"NJ",
    "sg:tags":[
        "physician",
        "surgeon",
        "medical"
    ],
    "wof:name":"Peter J Cetta MD",
    "wof:placetype":"venue"
},
  "geometry": {"coordinates":[-74.56797400000001,40.826694],"type":"Point"}
}