{
  "type": "Feature",
  "properties": {
    "addr:full":"151 Valley Rd Montclair NJ 07042",
    "addr:housenumber":"151",
    "addr:postcode":"07042",
    "addr:street":"Valley Rd",
    "iso:country":"US",
    "sg:address":"151 Valley Rd",
    "sg:city":"Montclair",
    "sg:classifiers":[
        {
            "category":"Building & Trades",
            "subcategory":"Locksmith",
            "type":"Services"
        }
    ],
    "sg:phone":"+1 973 854 5305",
    "sg:postcode":"07042",
    "sg:province":"NJ",
    "sg:tags":[
        "key"
    ],
    "wof:name":"1 24 Hour 7 Day A Emerg Locksmith",
    "wof:placetype":"venue"
},
  "geometry": {"coordinates":[-74.218952,40.823248],"type":"Point"}
}