{
  "type": "Feature",
  "properties": {
    "addr:full":"288 Main St Butler NJ 07405",
    "addr:housenumber":"288",
    "addr:postcode":"07405",
    "addr:street":"Main St",
    "iso:country":"US",
    "sg:address":"288 Main St",
    "sg:city":"Butler",
    "sg:classifiers":[
        {
            "category":"Personal",
            "subcategory":"Barber",
            "type":"Services"
        }
    ],
    "sg:phone":"+1 973 838 0541",
    "sg:postcode":"07405",
    "sg:province":"NJ",
    "wof:name":"Michael's Barber Shop",
    "wof:placetype":"venue"
},
  "geometry": {"coordinates":[-74.34252600000001,41.00594],"type":"Point"}
}