{
  "type": "Feature",
  "properties": {
    "iso:country":"US",
    "sg:address":"1316 N Broad St",
    "sg:city":"Hillside",
    "sg:classifiers":[
        {
            "category":"Home & Garden",
            "subcategory":"Home Furnishings",
            "type":"Retail Goods"
        }
    ],
    "sg:phone":"+1   ",
    "sg:postcode":"07205",
    "sg:province":"NJ",
    "wof:name":"Janet Decorators",
    "wof:placetype":"venue"
},
  "geometry": {"coordinates":[-74.21604499999999,40.694564],"type":"Point"}
}