{
  "type": "Feature",
  "properties": {
    "iso:country":"US",
    "sg:address":"469 Cranbury Rd",
    "sg:city":"East Brunswick",
    "sg:classifiers":[
        {
            "category":"Travel",
            "subcategory":"Travel Agent",
            "type":"Entertainment"
        }
    ],
    "sg:phone":"+1 732 254 6655",
    "sg:postcode":"08816",
    "sg:province":"NJ",
    "sg:tags":[
        "passenger",
        "agency",
        "transportation",
        "arrangement"
    ],
    "wof:name":"Sowas Travel Bureau",
    "wof:placetype":"venue"
},
  "geometry": {"coordinates":[-74.40614600000001,40.424754],"type":"Point"}
}