{
  "type": "Feature",
  "properties": {
    "iso:country":"US",
    "sg:address":"612 Ridge Rd",
    "sg:city":"North Arlington",
    "sg:classifiers":[
        {
            "category":"Personal",
            "subcategory":"Beauty Salon",
            "type":"Services"
        }
    ],
    "sg:phone":"+1 201 991 0888",
    "sg:postcode":"07031",
    "sg:province":"NJ",
    "sg:tags":[
        "shop"
    ],
    "wof:name":"Robert Palumbo Hair Designs",
    "wof:placetype":"venue"
},
  "geometry": {"coordinates":[-74.12691700000001,40.796908],"type":"Point"}
}