{
  "type": "Feature",
  "properties": {
    "addr:full":"120 Market St Newark NJ 07102",
    "addr:housenumber":"120",
    "addr:postcode":"07102",
    "addr:street":"Market St",
    "iso:country":"US",
    "sg:address":"120 Market St",
    "sg:city":"Newark",
    "sg:classifiers":[
        {
            "category":"Professional",
            "subcategory":"Management & Consulting",
            "type":"Services"
        }
    ],
    "sg:phone":"+1 973 623 7307",
    "sg:postcode":"07102",
    "sg:province":"NJ",
    "sg:tags":[
        "retail",
        "clothing",
        "store"
    ],
    "wof:name":"Lemonde Inc",
    "wof:placetype":"venue"
},
  "geometry": {"coordinates":[-74.174424,40.736199],"type":"Point"}
}