{
  "type": "Feature",
  "properties": {
    "addr:full":"114 Beemer Church Rd Branchville NJ 07461",
    "addr:housenumber":"114",
    "addr:postcode":"07461",
    "addr:street":"Beemer Church Rd",
    "iso:country":"US",
    "sg:address":"114 Beemer Church Rd",
    "sg:city":"Branchville",
    "sg:classifiers":[
        {
            "category":"Shopping",
            "subcategory":"Music",
            "type":"Retail Goods"
        }
    ],
    "sg:phone":"+1 973 702 3070",
    "sg:postcode":"07461",
    "sg:province":"NJ",
    "sg:tags":[
        "compact",
        "record",
        "disc",
        "tape"
    ],
    "wof:name":"C D Source Direct",
    "wof:placetype":"venue"
},
  "geometry": {"coordinates":[-74.690438,41.197302],"type":"Point"}
}