{
  "type": "Feature",
  "properties": {
    "addr:full":"700 W Browning Rd Oaklyn NJ 08107",
    "addr:housenumber":"700",
    "addr:postcode":"08107",
    "addr:street":"W Browning Rd",
    "iso:country":"US",
    "sg:address":"700 W Browning Rd",
    "sg:city":"Oaklyn",
    "sg:classifiers":[
        {
            "category":"Professional",
            "subcategory":"Detective & Security Services",
            "type":"Services"
        }
    ],
    "sg:phone":"+1 856 477 2259",
    "sg:postcode":"08107",
    "sg:province":"NJ",
    "sg:tags":[
        "information",
        "bureau"
    ],
    "wof:name":"S And S Property Services",
    "wof:placetype":"venue"
},
  "geometry": {"coordinates":[-75.079939,39.910841],"type":"Point"}
}