{
  "type": "Feature",
  "properties": {
    "addr:full":"293 S Central Ave Ramsey NJ 07446",
    "addr:housenumber":"293",
    "addr:postcode":"07446",
    "addr:street":"S Central Ave",
    "iso:country":"US",
    "sg:address":"293 S Central Ave",
    "sg:city":"Ramsey",
    "sg:classifiers":[
        {
            "category":"Professional",
            "subcategory":"Management & Consulting",
            "type":"Services"
        }
    ],
    "sg:phone":"+1 201 760 1685",
    "sg:postcode":"07446",
    "sg:province":"NJ",
    "sg:tags":[
        "consultant",
        "business"
    ],
    "sg:website":"www.proteusinternational.com",
    "wof:name":"Proteus International",
    "wof:placetype":"venue"
},
  "geometry": {"coordinates":[-74.14431399999999,41.047614],"type":"Point"}
}