{
  "type": "Feature",
  "properties": {
    "iso:country":"US",
    "sg:address":"36 Demarest Rd",
    "sg:city":"Lafayette",
    "sg:classifiers":[
        {
            "category":"Real Estate",
            "subcategory":"Architect",
            "type":"Services"
        }
    ],
    "sg:phone":"+1 973 300 1100",
    "sg:postcode":"07871",
    "sg:province":"NJ",
    "wof:name":"Andesign",
    "wof:placetype":"venue"
},
  "geometry": {"coordinates":[-74.670055,41.072326],"type":"Point"}
}