{
  "type": "Feature",
  "properties": {
    "iso:country":"US",
    "sg:address":"1007 Jersey Ave",
    "sg:city":"New Brunswick",
    "sg:classifiers":[
        {
            "category":"Manufacturing",
            "subcategory":"Soap",
            "type":"Manufacturing & Wholesale Goods"
        },
        {
            "category":"Building & Trades",
            "subcategory":"Cleaning & Sanitation",
            "type":"Services"
        }
    ],
    "sg:phone":"+1 732 249 6867",
    "sg:postcode":"08901",
    "sg:province":"NJ",
    "sg:tags":[
        "chemical",
        "detergent",
        "m",
        "mfg"
    ],
    "sg:website":"www.epicindustries.com",
    "wof:name":"Epic Industries Inc",
    "wof:placetype":"venue"
},
  "geometry": {"coordinates":[-74.471147,40.477359],"type":"Point"}
}