{
  "type": "Feature",
  "properties": {
    "addr:full":"13 Elizabeth Pl Englishtown NJ 07726",
    "addr:housenumber":"13",
    "addr:postcode":"07726",
    "addr:street":"Elizabeth Pl",
    "iso:country":"US",
    "sg:address":"13 Elizabeth Pl",
    "sg:city":"Englishtown",
    "sg:classifiers":[
        {
            "category":"Shopping",
            "subcategory":"Department Store",
            "type":"Retail Goods"
        }
    ],
    "sg:phone":"+1   ",
    "sg:postcode":"07726",
    "sg:province":"NJ",
    "wof:name":"Specialtees",
    "wof:placetype":"venue"
},
  "geometry": {"coordinates":[-74.343341,40.308866],"type":"Point"}
}