{
  "type": "Feature",
  "properties": {
    "addr:full":"313 S Harding Hwy Landisville NJ 08326",
    "addr:housenumber":"313",
    "addr:postcode":"08326",
    "addr:street":"S Harding Hwy",
    "iso:country":"US",
    "sg:address":"313 S Harding Hwy",
    "sg:city":"Landisville",
    "sg:classifiers":[
        {
            "category":"Real Estate",
            "subcategory":"Real Estate Agent",
            "type":"Services"
        }
    ],
    "sg:phone":"+1 856 697 2210",
    "sg:postcode":"08326",
    "sg:province":"NJ",
    "wof:name":"Integrity Realty Associates",
    "wof:placetype":"venue"
},
  "geometry": {"coordinates":[-74.93331499999999,39.520866],"type":"Point"}
}