{
  "type": "Feature",
  "properties": {
    "iso:country":"US",
    "sg:address":"13 River Rd",
    "sg:city":"Fair Lawn",
    "sg:classifiers":[
        {
            "category":"Retail",
            "subcategory":"Repair Shop",
            "type":"Services"
        }
    ],
    "sg:phone":"+1   ",
    "sg:postcode":"07410",
    "sg:province":"NJ",
    "wof:name":"14 Kt Gold Discount Outlet",
    "wof:placetype":"venue"
},
  "geometry": {"coordinates":[-74.130399,40.928063],"type":"Point"}
}