{
  "type": "Feature",
  "properties": {
    "addr:full":"409 Midland Ave Pompton Lakes NJ 07442",
    "addr:housenumber":"409",
    "addr:postcode":"07442",
    "addr:street":"Midland Ave",
    "iso:country":"US",
    "sg:address":"409 Midland Ave",
    "sg:city":"Pompton Lakes",
    "sg:classifiers":[
        {
            "category":"Professional",
            "subcategory":"Business Services",
            "type":"Services"
        }
    ],
    "sg:phone":"+1   ",
    "sg:postcode":"07442",
    "sg:province":"NJ",
    "wof:name":"New Jersey Business Exchange",
    "wof:placetype":"venue"
},
  "geometry": {"coordinates":[-74.297864,41.005999],"type":"Point"}
}