{
  "type": "Feature",
  "properties": {
    "addr:full":"25 Franklin St Verona NJ 07044",
    "addr:housenumber":"25",
    "addr:postcode":"07044",
    "addr:street":"Franklin St",
    "iso:country":"US",
    "sg:address":"25 Franklin St",
    "sg:city":"Verona",
    "sg:classifiers":[
        {
            "category":"Building & Trades",
            "subcategory":"Locksmith",
            "type":"Services"
        }
    ],
    "sg:phone":"+1 877 834 6708",
    "sg:postcode":"07044",
    "sg:province":"NJ",
    "sg:tags":[
        "key"
    ],
    "wof:name":"Always Available 24 Hour Emergency Locksmith",
    "wof:placetype":"venue"
},
  "geometry": {"coordinates":[-74.238157,40.836643],"type":"Point"}
}