{
  "type": "Feature",
  "properties": {
    "addr:full":"137 E Atlantic Ave Haddon Heights NJ 08035",
    "addr:housenumber":"137",
    "addr:postcode":"08035",
    "addr:street":"E Atlantic Ave",
    "iso:country":"US",
    "sg:address":"137 E Atlantic Ave",
    "sg:city":"Haddon Heights",
    "sg:classifiers":[
        {
            "category":"Professional",
            "subcategory":"Employment Agencies",
            "type":"Services"
        }
    ],
    "sg:phone":"+1 609 645 7787",
    "sg:postcode":"08035",
    "sg:province":"NJ",
    "wof:name":"Sure Staffing Inc",
    "wof:placetype":"venue"
},
  "geometry": {"coordinates":[-75.05966600000001,39.883813],"type":"Point"}
}