{
  "type": "Feature",
  "properties": {
    "addr:full":"123 Parkview Rd Stratford NJ 08084",
    "addr:housenumber":"123",
    "addr:postcode":"08084",
    "addr:street":"Parkview Rd",
    "iso:country":"US",
    "sg:address":"123 Parkview Rd",
    "sg:city":"Stratford",
    "sg:classifiers":[
        {
            "category":"Education",
            "subcategory":"School",
            "type":"Public Place"
        }
    ],
    "sg:phone":"+1   ",
    "sg:postcode":"08084",
    "sg:province":"NJ",
    "wof:name":"Stratford School District Boe",
    "wof:placetype":"venue"
},
  "geometry": {"coordinates":[-75.027434,39.830658],"type":"Point"}
}