{
  "type": "Feature",
  "properties": {
    "addr:full":"360 Fairfield Rd Freehold NJ 07728",
    "addr:housenumber":"360",
    "addr:postcode":"07728",
    "addr:street":"Fairfield Rd",
    "iso:country":"US",
    "sg:address":"360 Fairfield Rd",
    "sg:city":"Freehold",
    "sg:classifiers":[
        {
            "category":"Home & Garden",
            "subcategory":"Household Appliances",
            "type":"Retail Goods"
        },
        {
            "category":"Building & Trades",
            "subcategory":"Construction",
            "type":"Services"
        }
    ],
    "sg:phone":"+1 732 780 5113",
    "sg:postcode":"07728",
    "sg:province":"NJ",
    "sg:tags":[
        "tank",
        "storage",
        "contract",
        "pump",
        "above",
        "under",
        "ground"
    ],
    "wof:name":"Central Pump & Tank Inc",
    "wof:placetype":"venue"
},
  "geometry": {"coordinates":[-74.220444,40.224489],"type":"Point"}
}