{
  "type": "Feature",
  "properties": {
    "iso:country":"US",
    "sg:address":"1 Maple St",
    "sg:city":"Chatham",
    "sg:classifiers":[
        {
            "category":"Professional",
            "subcategory":"Computer Services",
            "type":"Services"
        }
    ],
    "sg:phone":"+1   ",
    "sg:postcode":"07928",
    "sg:province":"NJ",
    "sg:tags":[
        "related"
    ],
    "wof:name":"Grm Technologies Inc",
    "wof:placetype":"venue"
},
  "geometry": {"coordinates":[-74.40394499999999,40.733868],"type":"Point"}
}