{
  "type": "Feature",
  "properties": {
    "addr:full":"500 Melrose Ave Atlantic City NJ 08401",
    "addr:housenumber":"500",
    "addr:postcode":"08401",
    "addr:street":"Melrose Ave",
    "iso:country":"US",
    "sg:address":"500 Melrose Ave",
    "sg:city":"Atlantic City",
    "sg:classifiers":[
        {
            "category":"Professional",
            "subcategory":"Business Services",
            "type":"Services"
        },
        {
            "category":"Wholesale",
            "subcategory":"Electrical",
            "type":"Manufacturing & Wholesale Goods"
        }
    ],
    "sg:phone":"+1 609 348 2335",
    "sg:postcode":"08401",
    "sg:province":"NJ",
    "sg:tags":[
        "fire",
        "equipment",
        "protection",
        "extinguisher"
    ],
    "wof:name":"A W T Fire Equipment Co",
    "wof:placetype":"venue"
},
  "geometry": {"coordinates":[-74.42013300000001,39.370599],"type":"Point"}
}