{
  "type": "Feature",
  "properties": {
    "addr:full":"433 Stokes Rd Vincentown NJ 08088",
    "addr:housenumber":"433",
    "addr:postcode":"08088",
    "addr:street":"Stokes Rd",
    "iso:country":"US",
    "sg:address":"433 Stokes Rd",
    "sg:city":"Vincentown",
    "sg:classifiers":[
        {
            "category":"Shopping",
            "subcategory":"Hobbies, Toys, & Games",
            "type":"Retail Goods"
        }
    ],
    "sg:phone":"+1   ",
    "sg:postcode":"08088",
    "sg:province":"NJ",
    "sg:tags":[
        "equipment",
        "training",
        "dog"
    ],
    "wof:name":"Altmoor",
    "wof:placetype":"venue"
},
  "geometry": {"coordinates":[-74.778735,39.824909],"type":"Point"}
}