{
  "type": "Feature",
  "properties": {
    "addr:full":"48 Craig Dr Woodbury NJ 08096",
    "addr:housenumber":"48",
    "addr:postcode":"08096",
    "addr:street":"Craig Dr",
    "iso:country":"US",
    "sg:address":"48 Craig Dr",
    "sg:city":"Woodbury",
    "sg:classifiers":[
        {
            "category":"Retail",
            "subcategory":"Repair Shop",
            "type":"Services"
        }
    ],
    "sg:phone":"+1   ",
    "sg:postcode":"08096",
    "sg:province":"NJ",
    "sg:tags":[
        "locksmith"
    ],
    "wof:name":"Philip A Foschini Jr",
    "wof:placetype":"venue"
},
  "geometry": {"coordinates":[-75.1084,39.818942],"type":"Point"}
}