{
  "type": "Feature",
  "properties": {
    "addr:full":"370A Essex St Lodi NJ 07644",
    "addr:housenumber":"370a",
    "addr:postcode":"07644",
    "addr:street":"Essex St",
    "iso:country":"US",
    "sg:address":"370A Essex St",
    "sg:city":"Lodi",
    "sg:classifiers":[
        {
            "category":"Restaurant",
            "type":"Food & Drink"
        }
    ],
    "sg:phone":"+1 201 587 1087",
    "sg:postcode":"07644",
    "sg:province":"NJ",
    "sg:tags":[
        "indian"
    ],
    "wof:name":"Indian Chef",
    "wof:placetype":"venue"
},
  "geometry": {"coordinates":[-74.065296,40.887306],"type":"Point"}
}