{
  "type": "Feature",
  "properties": {
    "iso:country":"US",
    "sg:address":"302 W Red Bank Ave",
    "sg:city":"Woodbury",
    "sg:classifiers":[
        {
            "category":"Building & Trades",
            "subcategory":"Construction",
            "type":"Services"
        }
    ],
    "sg:phone":"+1 856 845 5175",
    "sg:postcode":"08096",
    "sg:province":"NJ",
    "sg:tags":[
        "roofing",
        "contractor"
    ],
    "wof:name":"W J Golle Custom Exteriors",
    "wof:placetype":"venue"
},
  "geometry": {"coordinates":[-75.156251,39.846282],"type":"Point"}
}