{
  "type": "Feature",
  "properties": {
    "iso:country":"US",
    "sg:address":"899 State Rte 18",
    "sg:city":"Old Bridge",
    "sg:classifiers":[
        {
            "category":"Autos & Motor Vehicles",
            "subcategory":"Recreational Vehicle Sales",
            "type":"Retail Goods"
        }
    ],
    "sg:phone":"+1 732 251 4383",
    "sg:postcode":"08857",
    "sg:province":"NJ",
    "sg:tags":[
        "parts",
        "trailer"
    ],
    "sg:website":"www.subcaps.com",
    "wof:name":"Abe Truck Caps By Suburban",
    "wof:placetype":"venue"
},
  "geometry": {"coordinates":[-74.35354599999999,40.40331],"type":"Point"}
}