{
  "type": "Feature",
  "properties": {
    "addr:full":"224 E Broad St Westfield NJ 07090",
    "addr:housenumber":"224",
    "addr:postcode":"07090",
    "addr:street":"E Broad St",
    "iso:country":"US",
    "sg:address":"224 E Broad St",
    "sg:city":"Westfield",
    "sg:classifiers":[
        {
            "category":"Personal",
            "subcategory":"Beauty Salon",
            "type":"Services"
        }
    ],
    "sg:phone":"+1 908 232 2329",
    "sg:postcode":"07090",
    "sg:province":"NJ",
    "sg:tags":[
        "shop"
    ],
    "wof:name":"Anthony Michael Ear Piercing",
    "wof:placetype":"venue"
},
  "geometry": {"coordinates":[-74.347734,40.652068],"type":"Point"}
}