{
  "type": "Feature",
  "properties": {
    "iso:country":"US",
    "sg:address":"720 Somerset St",
    "sg:city":"Watchung",
    "sg:classifiers":[
        {
            "category":"Restaurant",
            "type":"Food & Drink"
        }
    ],
    "sg:phone":"+1 908 769 8388",
    "sg:postcode":"07069",
    "sg:province":"NJ",
    "sg:tags":[
        "eating",
        "pizza"
    ],
    "wof:name":"Marino's Pizza",
    "wof:placetype":"venue"
},
  "geometry": {"coordinates":[-74.44295099999999,40.630854],"type":"Point"}
}