{
  "type": "Feature",
  "properties": {
    "addr:full":"54 Market St Paterson NJ 07505",
    "addr:housenumber":"54",
    "addr:postcode":"07505",
    "addr:street":"Market St",
    "iso:country":"US",
    "sg:address":"54 Market St",
    "sg:city":"Paterson",
    "sg:classifiers":[
        {
            "category":"Restaurant",
            "type":"Food & Drink"
        }
    ],
    "sg:phone":"+1 973 278 2648",
    "sg:postcode":"07505",
    "sg:province":"NJ",
    "sg:tags":[
        "eating"
    ],
    "wof:name":"Panchito's Restaurant",
    "wof:placetype":"venue"
},
  "geometry": {"coordinates":[-74.17559799999999,40.915298],"type":"Point"}
}