{
  "type": "Feature",
  "properties": {
    "iso:country":"US",
    "sg:address":"445 State Rte 37",
    "sg:city":"Toms River",
    "sg:classifiers":[
        {
            "category":"Restaurant",
            "type":"Food & Drink"
        }
    ],
    "sg:phone":"+1 732 929 0440",
    "sg:postcode":"08753",
    "sg:province":"NJ",
    "wof:name":"Toms River Diner",
    "wof:placetype":"venue"
},
  "geometry": {"coordinates":[-74.19144799999999,39.963477],"type":"Point"}
}