{
  "type": "Feature",
  "properties": {
    "iso:country":"US",
    "sg:address":"18 Holly Dr",
    "sg:city":"Morris Plains",
    "sg:classifiers":[
        {
            "category":"Professional",
            "type":"Services"
        }
    ],
    "sg:phone":"+1   ",
    "sg:postcode":"07950",
    "sg:province":"NJ",
    "sg:tags":[
        "lecturing"
    ],
    "wof:name":"Collerna A Joseph",
    "wof:placetype":"venue"
},
  "geometry": {"coordinates":[-74.464055,40.862669],"type":"Point"}
}