{
  "type": "Feature",
  "properties": {
    "addr:full":"6410 Ventnor Ave Ventnor City NJ 08406",
    "addr:housenumber":"6410",
    "addr:postcode":"08406",
    "addr:street":"Ventnor Ave",
    "iso:country":"US",
    "sg:address":"6410 Ventnor Ave",
    "sg:city":"Ventnor City",
    "sg:classifiers":[
        {
            "category":"Restaurant",
            "type":"Food & Drink"
        }
    ],
    "sg:phone":"+1   ",
    "sg:postcode":"08406",
    "sg:province":"NJ",
    "sg:tags":[
        "eating"
    ],
    "wof:name":"Jerusalem Kosher Restaurant",
    "wof:placetype":"venue"
},
  "geometry": {"coordinates":[-74.48293,39.337804],"type":"Point"}
}