{
  "type": "Feature",
  "properties": {
    "addr:full":"35 N Black Horse Pike Blackwood NJ 08012",
    "addr:housenumber":"35",
    "addr:postcode":"08012",
    "addr:street":"N Black Horse Pike",
    "iso:country":"US",
    "sg:address":"35 N Black Horse Pike",
    "sg:city":"Blackwood",
    "sg:classifiers":[
        {
            "category":"Insurance",
            "subcategory":"Insurance Agent",
            "type":"Services"
        },
        {
            "category":"Insurance",
            "subcategory":"Hazard Insurance",
            "type":"Services"
        }
    ],
    "sg:phone":"+1 856 227 0435",
    "sg:postcode":"08012",
    "sg:province":"NJ",
    "sg:tags":[
        "auto"
    ],
    "wof:name":"THOMAS M HUTCHINSON - Progressive Insurance",
    "wof:placetype":"venue"
},
  "geometry": {"coordinates":[-75.06710200000001,39.802472],"type":"Point"}
}