{
  "type": "Feature",
  "properties": {
    "iso:country":"US",
    "sg:address":"116 Home Pl",
    "sg:city":"Lodi",
    "sg:classifiers":[
        {
            "category":"Building & Trades",
            "subcategory":"Construction",
            "type":"Services"
        }
    ],
    "sg:phone":"+1 973 473 7090",
    "sg:postcode":"07644",
    "sg:province":"NJ",
    "sg:tags":[
        "contractor"
    ],
    "wof:name":"D&N Aluminum",
    "wof:placetype":"venue"
},
  "geometry": {"coordinates":[-74.091284,40.872164],"type":"Point"}
}