{
  "type": "Feature",
  "properties": {
    "addr:full":"50 Blue Heron Way Skillman NJ 08558",
    "addr:housenumber":"50",
    "addr:postcode":"08558",
    "addr:street":"Blue Heron Way",
    "iso:country":"US",
    "sg:address":"50 Blue Heron Way",
    "sg:city":"Skillman",
    "sg:classifiers":[
        {
            "category":"Manufacturing",
            "subcategory":"Tools & Machinery",
            "type":"Manufacturing & Wholesale Goods"
        }
    ],
    "sg:phone":"+1 609 333 1218",
    "sg:postcode":"08558",
    "sg:province":"NJ",
    "sg:tags":[
        "control",
        "video",
        "electronics",
        "electronic",
        "system"
    ],
    "wof:name":"Synthesis Electronics",
    "wof:placetype":"venue"
},
  "geometry": {"coordinates":[-74.726192,40.396349],"type":"Point"}
}