{
  "type": "Feature",
  "properties": {
    "addr:full":"31 N Westgate Rd Livingston NJ 07039",
    "addr:housenumber":"31",
    "addr:postcode":"07039",
    "addr:street":"N Westgate Rd",
    "iso:country":"US",
    "sg:address":"31 N Westgate Rd",
    "sg:city":"Livingston",
    "sg:classifiers":[
        {
            "category":"Retail",
            "subcategory":"Portrait Studio",
            "type":"Services"
        }
    ],
    "sg:phone":"+1   ",
    "sg:postcode":"07039",
    "sg:province":"NJ",
    "sg:tags":[
        "photo"
    ],
    "wof:name":"J Pottheiser Photography",
    "wof:placetype":"venue"
},
  "geometry": {"coordinates":[-74.34851,40.788591],"type":"Point"}
}