{
  "type": "Feature",
  "properties": {
    "iso:country":"US",
    "sg:address":"420 Commerce Ln",
    "sg:city":"West Berlin",
    "sg:classifiers":[
        {
            "category":"Wholesale",
            "subcategory":"Hardware",
            "type":"Manufacturing & Wholesale Goods"
        }
    ],
    "sg:phone":"+1 856 767 8900",
    "sg:postcode":"08091",
    "sg:province":"NJ",
    "sg:tags":[
        "supply",
        "support",
        "mfg",
        "parts",
        "air",
        "computer",
        "conditioning",
        "representative"
    ],
    "wof:name":"A & W Technical Sales Inc",
    "wof:placetype":"venue"
},
  "geometry": {"coordinates":[-74.928017,39.810197],"type":"Point"}
}