{
  "type": "Feature",
  "properties": {
    "addr:full":"900 Ocean Dr Cape May NJ 08204",
    "addr:housenumber":"900",
    "addr:postcode":"08204",
    "addr:street":"Ocean Dr",
    "iso:country":"US",
    "sg:address":"900 Ocean Dr",
    "sg:city":"Cape May",
    "sg:classifiers":[
        {
            "category":"Recreation",
            "subcategory":"Marina",
            "type":"Entertainment"
        }
    ],
    "sg:phone":"+1 609 884 0199",
    "sg:postcode":"08204",
    "sg:province":"NJ",
    "wof:name":"Canyon Club Marine",
    "wof:placetype":"venue"
},
  "geometry": {"coordinates":[-74.90308400000001,38.956461],"type":"Point"}
}