{
  "type": "Feature",
  "properties": {
    "addr:full":"1465 State Rte 23 Wayne NJ 07470",
    "addr:housenumber":"1465",
    "addr:postcode":"07470",
    "addr:street":"State Rte 23",
    "iso:country":"US",
    "sg:address":"1465 State Rte 23",
    "sg:city":"Wayne",
    "sg:classifiers":[
        {
            "category":"Professional",
            "subcategory":"Engineering",
            "type":"Services"
        }
    ],
    "sg:phone":"+1   ",
    "sg:postcode":"07470",
    "sg:province":"NJ",
    "wof:name":"Novotics",
    "wof:placetype":"venue"
},
  "geometry": {"coordinates":[-74.269088,40.933932],"type":"Point"}
}