{
  "type": "Feature",
  "properties": {
    "iso:country":"US",
    "sg:address":"173 S Black Horse Pike",
    "sg:city":"Blackwood",
    "sg:classifiers":[
        {
            "category":"Retail",
            "subcategory":"Auto Repair",
            "type":"Services"
        }
    ],
    "sg:phone":"+1 856 767 3697",
    "sg:postcode":"08012",
    "sg:province":"NJ",
    "sg:tags":[
        "repairing",
        "automobile"
    ],
    "wof:name":"Blackwood Car Care",
    "wof:placetype":"venue"
},
  "geometry": {"coordinates":[-75.064656,39.797684],"type":"Point"}
}