{
  "type": "Feature",
  "properties": {
    "iso:country":"US",
    "sg:address":"653 High St",
    "sg:city":"Burlington",
    "sg:classifiers":[
        {
            "category":"Food & Beverages",
            "subcategory":"Liquor & Beverages",
            "type":"Retail Goods"
        }
    ],
    "sg:phone":"+1 609 386 0710",
    "sg:postcode":"08016",
    "sg:province":"NJ",
    "sg:tags":[
        "beer",
        "spirit",
        "wine"
    ],
    "wof:name":"A P Liquors Corp",
    "wof:placetype":"venue"
},
  "geometry": {"coordinates":[-74.854755,40.070573],"type":"Point"}
}