{
  "type": "Feature",
  "properties": {
    "iso:country":"US",
    "sg:address":"25 Country Club Dr",
    "sg:city":"Ringoes",
    "sg:classifiers":[
        {
            "category":"Real Estate",
            "subcategory":"Real Estate Agent",
            "type":"Services"
        }
    ],
    "sg:phone":"+1 908 237 1190",
    "sg:postcode":"08551",
    "sg:province":"NJ",
    "wof:name":"Weichert Realtors",
    "wof:placetype":"venue"
},
  "geometry": {"coordinates":[-74.87049,40.472108],"type":"Point"}
}