{
  "type": "Feature",
  "properties": {
    "addr:full":"24 Bay St Rumson NJ 07760",
    "addr:housenumber":"24",
    "addr:postcode":"07760",
    "addr:street":"Bay St",
    "iso:country":"US",
    "sg:address":"24 Bay St",
    "sg:city":"Rumson",
    "sg:classifiers":[
        {
            "category":"Building & Trades",
            "subcategory":"Plumbing",
            "type":"Services"
        }
    ],
    "sg:phone":"+1 732 842 5467",
    "sg:postcode":"07760",
    "sg:province":"NJ",
    "sg:tags":[
        "heating",
        "contractor"
    ],
    "wof:name":"Herbert Moore Plumbing & Htg",
    "wof:placetype":"venue"
},
  "geometry": {"coordinates":[-73.993426,40.371871],"type":"Point"}
}