{
  "type": "Feature",
  "properties": {
    "addr:full":"521 Lakehurst Rd Toms River NJ 08755",
    "addr:housenumber":"521",
    "addr:postcode":"08755",
    "addr:street":"Lakehurst Rd",
    "iso:country":"US",
    "sg:address":"521 Lakehurst Rd",
    "sg:city":"Toms River",
    "sg:classifiers":[
        {
            "category":"Travel",
            "subcategory":"Travel Agent",
            "type":"Entertainment"
        }
    ],
    "sg:phone":"+1 732 349 5555",
    "sg:postcode":"08755",
    "sg:province":"NJ",
    "sg:tags":[
        "agency",
        "bureau"
    ],
    "wof:name":"Elsa Travel",
    "wof:placetype":"venue"
},
  "geometry": {"coordinates":[-74.223862,39.964486],"type":"Point"}
}