{
  "type": "Feature",
  "properties": {
    "addr:full":"321 New Rd Somers Point NJ 08244",
    "addr:housenumber":"321",
    "addr:postcode":"08244",
    "addr:street":"New Rd",
    "iso:country":"US",
    "sg:address":"321 New Rd",
    "sg:city":"Somers Point",
    "sg:classifiers":[
        {
            "category":"Banks & Credit Unions",
            "subcategory":"Bank",
            "type":"Services"
        }
    ],
    "sg:phone":"+1 609 927 1433",
    "sg:postcode":"08244",
    "sg:province":"NJ",
    "sg:website":"www.bankofamerica.com",
    "wof:name":"Bank Of America",
    "wof:placetype":"venue"
},
  "geometry": {"coordinates":[-74.59706,39.327889],"type":"Point"}
}