{
  "type": "Feature",
  "properties": {
    "iso:country":"US",
    "sg:address":"21 Lincoln Ave",
    "sg:city":"Princeton",
    "sg:classifiers":[
        {
            "category":"Professional",
            "subcategory":"Management & Consulting",
            "type":"Services"
        }
    ],
    "sg:phone":"+1   ",
    "sg:postcode":"08540",
    "sg:province":"NJ",
    "sg:tags":[
        "business"
    ],
    "wof:name":"Evan Williams Consulting LLC",
    "wof:placetype":"venue"
},
  "geometry": {"coordinates":[-74.59811500000001,40.439237],"type":"Point"}
}