{
  "type": "Feature",
  "properties": {
    "iso:country":"US",
    "sg:address":"310 S Orange Ave",
    "sg:city":"South Orange",
    "sg:classifiers":[
        {
            "category":"Manufacturing",
            "subcategory":"Printing",
            "type":"Manufacturing & Wholesale Goods"
        }
    ],
    "sg:phone":"+1 973 763 5780",
    "sg:postcode":"07079",
    "sg:province":"NJ",
    "sg:tags":[
        "periodical"
    ],
    "wof:name":"Dumbbell Press",
    "wof:placetype":"venue"
},
  "geometry": {"coordinates":[-74.250625,40.74477],"type":"Point"}
}