{
  "type": "Feature",
  "properties": {
    "addr:full":"600 Clements Bridge Rd Barrington NJ 08007",
    "addr:housenumber":"600",
    "addr:postcode":"08007",
    "addr:street":"Clements Bridge Rd",
    "iso:country":"US",
    "sg:address":"600 Clements Bridge Rd",
    "sg:city":"Barrington",
    "sg:classifiers":[
        {
            "category":"Health Services",
            "subcategory":"Doctor",
            "type":"Services"
        },
        {
            "category":"Health Services",
            "subcategory":"Nursing And Care Facility",
            "type":"Services"
        }
    ],
    "sg:phone":"+1 856 547 8000",
    "sg:postcode":"08007",
    "sg:province":"NJ",
    "sg:tags":[
        "wound"
    ],
    "sg:website":"www.woundhealingsolutions.com",
    "wof:name":"Wound Healing Solutions Llc",
    "wof:placetype":"venue"
},
  "geometry": {"coordinates":[-75.053967,39.866493],"type":"Point"}
}