{
  "type": "Feature",
  "properties": {
    "iso:country":"US",
    "sg:address":"430 Communipaw Ave",
    "sg:city":"Jersey City",
    "sg:classifiers":[
        {
            "category":"Building & Trades",
            "subcategory":"Construction",
            "type":"Services"
        }
    ],
    "sg:phone":"+1 201 432 8119",
    "sg:postcode":"07304",
    "sg:province":"NJ",
    "sg:tags":[
        "equipment",
        "installation",
        "repair"
    ],
    "wof:name":"Cui Elevator Specialists",
    "wof:placetype":"venue"
},
  "geometry": {"coordinates":[-74.0671,40.714847],"type":"Point"}
}