{
  "type": "Feature",
  "properties": {
    "iso:country":"US",
    "sg:address":"46 Park Rd",
    "sg:city":"Eatontown",
    "sg:classifiers":[
        {
            "category":"Shopping",
            "subcategory":"Music",
            "type":"Retail Goods"
        }
    ],
    "sg:phone":"+1   ",
    "sg:postcode":"07724",
    "sg:province":"NJ",
    "sg:tags":[
        "compact",
        "prerecorded",
        "tape"
    ],
    "wof:name":"Ritmo Latino Inc",
    "wof:placetype":"venue"
},
  "geometry": {"coordinates":[-74.08183200000001,40.287076],"type":"Point"}
}