{
  "type": "Feature",
  "properties": {
    "iso:country":"US",
    "sg:address":"112 S Plainfield Ave",
    "sg:city":"South Plainfield",
    "sg:classifiers":[
        {
            "category":"Wholesale",
            "subcategory":"Machinery & Supplies",
            "type":"Manufacturing & Wholesale Goods"
        },
        {
            "category":"Professional",
            "subcategory":"Employment Agencies",
            "type":"Services"
        }
    ],
    "sg:phone":"+1 908 757 5959",
    "sg:postcode":"07080",
    "sg:province":"NJ",
    "sg:tags":[
        "plant",
        "handling",
        "installers",
        "material",
        "equipment",
        "warehouse"
    ],
    "wof:name":"Diversified Installations Inc",
    "wof:placetype":"venue"
},
  "geometry": {"coordinates":[-74.408393,40.580356],"type":"Point"}
}