{
  "type": "Feature",
  "properties": {
    "addr:full":"2101 E State Street Ext # 6 Trenton NJ 08619",
    "addr:housenumber":"2101",
    "addr:postcode":"08619",
    "addr:street":"E State Street Ext # 6",
    "iso:country":"US",
    "sg:address":"2101 E State Street Ext # 6",
    "sg:city":"Trenton",
    "sg:classifiers":[
        {
            "category":"Government",
            "subcategory":"Fire Station",
            "type":"Public Place"
        },
        {
            "category":"Wholesale",
            "subcategory":"Machinery & Supplies",
            "type":"Manufacturing & Wholesale Goods"
        }
    ],
    "sg:phone":"+1 609 587 2600",
    "sg:postcode":"08619",
    "sg:province":"NJ",
    "sg:tags":[
        "department",
        "extinguisher",
        "protection",
        "equipment"
    ],
    "wof:name":"James B Hunt Mfg Co.",
    "wof:placetype":"venue"
},
  "geometry": {"coordinates":[-74.723083,40.239868],"type":"Point"}
}