{
  "type": "Feature",
  "properties": {
    "iso:country":"US",
    "sg:address":"221 Hancox Ave",
    "sg:city":"Nutley",
    "sg:classifiers":[
        {
            "category":"Professional",
            "type":"Services"
        }
    ],
    "sg:phone":"+1   ",
    "sg:postcode":"07110",
    "sg:province":"NJ",
    "wof:name":"Frank Edward Nora",
    "wof:placetype":"venue"
},
  "geometry": {"coordinates":[-74.157642,40.808638],"type":"Point"}
}