{
  "type": "Feature",
  "properties": {
    "iso:country":"US",
    "sg:address":"207 Northfield Ave",
    "sg:city":"Northfield",
    "sg:classifiers":[
        {
            "category":"Organizations",
            "subcategory":"Religious Organization",
            "type":"Services"
        }
    ],
    "sg:phone":"+1 609 272 3128",
    "sg:postcode":"08225",
    "sg:province":"NJ",
    "sg:tags":[
        "church"
    ],
    "sg:website":"www.gnjumc.org",
    "wof:name":"Cape Atlantic District",
    "wof:placetype":"venue"
},
  "geometry": {"coordinates":[-74.55281100000001,39.371316],"type":"Point"}
}