{
  "type": "Feature",
  "properties": {
    "addr:full":"23 Royal Rd Flemington NJ 08822",
    "addr:housenumber":"23",
    "addr:postcode":"08822",
    "addr:street":"Royal Rd",
    "iso:country":"US",
    "sg:address":"23 Royal Rd",
    "sg:city":"Flemington",
    "sg:classifiers":[
        {
            "category":"Building & Trades",
            "subcategory":"Construction",
            "type":"Services"
        }
    ],
    "sg:phone":"+1 908 806 7611",
    "sg:postcode":"08822",
    "sg:province":"NJ",
    "sg:tags":[
        "contractor"
    ],
    "wof:name":"Scozzari Builders Inc",
    "wof:placetype":"venue"
},
  "geometry": {"coordinates":[-74.84363399999999,40.510813],"type":"Point"}
}