{
  "type": "Feature",
  "properties": {
    "addr:full":"893 US Hwy 22 North Plainfield NJ 07060",
    "addr:housenumber":"893",
    "addr:postcode":"07060",
    "addr:street":"Us Hwy 22",
    "iso:country":"US",
    "sg:address":"893 US Hwy 22",
    "sg:city":"North Plainfield",
    "sg:classifiers":[
        {
            "category":"Real Estate",
            "subcategory":"Real Estate Agent",
            "type":"Services"
        }
    ],
    "sg:phone":"+1 908 757 4900",
    "sg:postcode":"07060",
    "sg:province":"NJ",
    "wof:name":"Levin Realty Svc Inc",
    "wof:placetype":"venue"
},
  "geometry": {"coordinates":[-74.444892,40.623181],"type":"Point"}
}