{
  "type": "Feature",
  "properties": {
    "addr:full":"125 Main Ave Elmwood Park NJ 07407",
    "addr:housenumber":"125",
    "addr:postcode":"07407",
    "addr:street":"Main Ave",
    "iso:country":"US",
    "sg:address":"125 Main Ave",
    "sg:city":"Elmwood Park",
    "sg:classifiers":[
        {
            "category":"Manufacturing",
            "subcategory":"Retail Goods",
            "type":"Manufacturing & Wholesale Goods"
        }
    ],
    "sg:phone":"+1 201 475 1855",
    "sg:postcode":"07407",
    "sg:province":"NJ",
    "sg:tags":[
        "manufacturer"
    ],
    "wof:name":"Grand Industries",
    "wof:placetype":"venue"
},
  "geometry": {"coordinates":[-74.112235,40.909293],"type":"Point"}
}