{
  "type": "Feature",
  "properties": {
    "iso:country":"US",
    "sg:address":"203 Sergeantsville Rd",
    "sg:city":"Flemington",
    "sg:phone":"+1 908 806 3196",
    "sg:postcode":"08822",
    "sg:province":"NJ",
    "sg:tags":[
        "farm",
        "field",
        "crop"
    ],
    "wof:name":"Kenneth Novak",
    "wof:placetype":"venue"
},
  "geometry": {"coordinates":[-74.90690499999999,40.480666],"type":"Point"}
}