{
  "type": "Feature",
  "properties": {
    "iso:country":"US",
    "sg:address":"55 Robbins St",
    "sg:city":"Brick",
    "sg:classifiers":[
        {
            "category":"Professional",
            "type":"Services"
        }
    ],
    "sg:phone":"+1 732 458 4381",
    "sg:postcode":"08724",
    "sg:province":"NJ",
    "wof:name":"Greater Images Services Inc",
    "wof:placetype":"venue"
},
  "geometry": {"coordinates":[-74.12309999999999,40.06646],"type":"Point"}
}