{
  "type": "Feature",
  "properties": {
    "iso:country":"US",
    "sg:address":"12 Baumer Rd",
    "sg:city":"Sayreville",
    "sg:classifiers":[
        {
            "category":"Building & Trades",
            "subcategory":"Plumbing",
            "type":"Services"
        }
    ],
    "sg:phone":"+1 732 257 6502",
    "sg:postcode":"08872",
    "sg:province":"NJ",
    "sg:tags":[
        "contractor"
    ],
    "wof:name":"Rodd Plumbing & Heating Co",
    "wof:placetype":"venue"
},
  "geometry": {"coordinates":[-74.35538699999999,40.454648],"type":"Point"}
}