{
  "type": "Feature",
  "properties": {
    "iso:country":"US",
    "sg:address":"260 Morris Ave",
    "sg:city":"Elizabeth",
    "sg:classifiers":[
        {
            "category":"Airline",
            "type":"Transportation"
        }
    ],
    "sg:phone":"+1 908 355 7020",
    "sg:postcode":"07208",
    "sg:province":"NJ",
    "sg:tags":[
        "courier",
        "air"
    ],
    "wof:name":"Avianca Express",
    "wof:placetype":"venue"
},
  "geometry": {"coordinates":[-74.21707499999999,40.668252],"type":"Point"}
}