{
  "type": "Feature",
  "properties": {
    "addr:full":"1500 Palisade Ave Fort Lee NJ 07024",
    "addr:housenumber":"1500",
    "addr:postcode":"07024",
    "addr:street":"Palisade Ave",
    "iso:country":"US",
    "sg:address":"1500 Palisade Ave",
    "sg:city":"Fort Lee",
    "sg:classifiers":[
        {
            "category":"Professional",
            "subcategory":"Business Services",
            "type":"Services"
        }
    ],
    "sg:phone":"+1 201 947 7880",
    "sg:postcode":"07024",
    "sg:province":"NJ",
    "sg:tags":[
        "interior",
        "consultant",
        "design",
        "decorator"
    ],
    "wof:name":"Marnice Designs",
    "wof:placetype":"venue"
},
  "geometry": {"coordinates":[-73.971351,40.845524],"type":"Point"}
}