{
  "type": "Feature",
  "properties": {
    "addr:full":"692 Main Ave Passaic NJ 07055",
    "addr:housenumber":"692",
    "addr:postcode":"07055",
    "addr:street":"Main Ave",
    "iso:country":"US",
    "sg:address":"692 Main Ave",
    "sg:city":"Passaic",
    "sg:classifiers":[
        {
            "category":"Professional",
            "subcategory":"Business Services",
            "type":"Services"
        }
    ],
    "sg:phone":"+1 973 591 0707",
    "sg:postcode":"07055",
    "sg:province":"NJ",
    "wof:name":"Conexion Latina Music",
    "wof:placetype":"venue"
},
  "geometry": {"coordinates":[-74.126791,40.861981],"type":"Point"}
}