{
  "type": "Feature",
  "properties": {
    "iso:country":"US",
    "sg:address":"34 Wesickaman Dr",
    "sg:city":"Vincentown",
    "sg:classifiers":[
        {
            "category":"Professional",
            "subcategory":"Business Services",
            "type":"Services"
        }
    ],
    "sg:phone":"+1   ",
    "sg:postcode":"08088",
    "sg:province":"NJ",
    "wof:name":"Youthful Creations",
    "wof:placetype":"venue"
},
  "geometry": {"coordinates":[-74.76659100000001,39.786511],"type":"Point"}
}