{
  "type": "Feature",
  "properties": {
    "iso:country":"US",
    "sg:address":"3800 N Mill Rd",
    "sg:city":"Vineland",
    "sg:classifiers":[
        {
            "category":"Professional",
            "type":"Services"
        }
    ],
    "sg:phone":"+1 856 696 5709",
    "sg:postcode":"08360",
    "sg:province":"NJ",
    "sg:tags":[
        "establishment"
    ],
    "wof:name":"Conectiv",
    "wof:placetype":"venue"
},
  "geometry": {"coordinates":[-75.058065,39.543057],"type":"Point"}
}