{
  "type": "Feature",
  "properties": {
    "addr:full":"505 Piaget Ave Clifton NJ 07011",
    "addr:housenumber":"505",
    "addr:postcode":"07011",
    "addr:street":"Piaget Ave",
    "iso:country":"US",
    "sg:address":"505 Piaget Ave",
    "sg:city":"Clifton",
    "sg:classifiers":[
        {
            "category":"Shopping",
            "subcategory":"Discount & Variety Stores",
            "type":"Retail Goods"
        }
    ],
    "sg:phone":"+1 973 772 1520",
    "sg:postcode":"07011",
    "sg:province":"NJ",
    "sg:tags":[
        "merchandise",
        "general"
    ],
    "wof:name":"Dollar Premium LLC",
    "wof:placetype":"venue"
},
  "geometry": {"coordinates":[-74.15807,40.878048],"type":"Point"}
}