{
  "type": "Feature",
  "properties": {
    "iso:country":"US",
    "sg:address":"18 E Park Ave",
    "sg:city":"Trenton",
    "sg:classifiers":[
        {
            "category":"Retail",
            "subcategory":"Veterinary Services",
            "type":"Services"
        }
    ],
    "sg:phone":"+1 609 888 3400",
    "sg:postcode":"08610",
    "sg:province":"NJ",
    "wof:name":"Hamilton Veterinary Hospital",
    "wof:placetype":"venue"
},
  "geometry": {"coordinates":[-74.723856,40.196826],"type":"Point"}
}