{
  "type": "Feature",
  "properties": {
    "iso:country":"US",
    "sg:address":"43 Citation Dr",
    "sg:city":"Freehold",
    "sg:classifiers":[
        {
            "category":"Professional",
            "subcategory":"Business Services",
            "type":"Services"
        }
    ],
    "sg:phone":"+1   ",
    "sg:postcode":"07728",
    "sg:province":"NJ",
    "wof:name":"Leslie Assoc",
    "wof:placetype":"venue"
},
  "geometry": {"coordinates":[-74.26019700000001,40.264645],"type":"Point"}
}