{
  "type": "Feature",
  "properties": {
    "iso:country":"US",
    "sg:address":"188 Eagle Rock Avenue Suite 7",
    "sg:city":"Roseland",
    "sg:classifiers":[
        {
            "category":"Health Services",
            "subcategory":"Clinic",
            "type":"Services"
        }
    ],
    "sg:phone":"+1 973 618 5333",
    "sg:postcode":"07068",
    "sg:province":"NJ",
    "sg:tags":[
        "medical"
    ],
    "sg:website":"www.drtrishjamison.com",
    "wof:name":"Jamison Family Chiropractic Center, Dr. Trish Jamison",
    "wof:placetype":"venue"
},
  "geometry": {"coordinates":[-74.295708,40.821257],"type":"Point"}
}