{
  "type": "Feature",
  "properties": {
    "addr:full":"170 Oberlin Ave N Lakewood NJ 08701",
    "addr:housenumber":"170",
    "addr:postcode":"08701",
    "addr:street":"Oberlin Ave N",
    "iso:country":"US",
    "sg:address":"170 Oberlin Ave N",
    "sg:city":"Lakewood",
    "sg:classifiers":[
        {
            "category":"Education",
            "subcategory":"School",
            "type":"Public Place"
        }
    ],
    "sg:phone":"+1 732 364 0311",
    "sg:postcode":"08701",
    "sg:province":"NJ",
    "sg:tags":[
        "religious"
    ],
    "wof:name":"Tiferes Bais Yaakov",
    "wof:placetype":"venue"
},
  "geometry": {"coordinates":[-74.17534999999999,40.078357],"type":"Point"}
}