{
  "type": "Feature",
  "properties": {
    "addr:full":"595 Haddon Ave Collingswood NJ 08108",
    "addr:housenumber":"595",
    "addr:postcode":"08108",
    "addr:street":"Haddon Ave",
    "iso:country":"US",
    "sg:address":"595 Haddon Ave",
    "sg:city":"Collingswood",
    "sg:classifiers":[
        {
            "category":"Health Services",
            "subcategory":"Medical Lab",
            "type":"Services"
        },
        {
            "category":"Insurance",
            "subcategory":"Health Insurance",
            "type":"Services"
        }
    ],
    "sg:phone":"+1 856 858 7860",
    "sg:postcode":"08108",
    "sg:province":"NJ",
    "sg:tags":[
        "maintenance"
    ],
    "wof:name":"Cme Interactive Tn 856 429 701",
    "wof:placetype":"venue"
},
  "geometry": {"coordinates":[-75.071849,39.917197],"type":"Point"}
}