{
  "type": "Feature",
  "properties": {
    "addr:full":"105 Leonardville Rd Belford NJ 07718",
    "addr:housenumber":"105",
    "addr:postcode":"07718",
    "addr:street":"Leonardville Rd",
    "iso:country":"US",
    "sg:address":"105 Leonardville Rd",
    "sg:city":"Belford",
    "sg:classifiers":[
        {
            "category":"Recreation",
            "type":"Entertainment"
        }
    ],
    "sg:phone":"+1 732 872 2956",
    "sg:postcode":"07718",
    "sg:province":"NJ",
    "wof:name":"New Age Insights",
    "wof:placetype":"venue"
},
  "geometry": {"coordinates":[-74.09330799999999,40.4147],"type":"Point"}
}