{
  "type": "Feature",
  "properties": {
    "iso:country":"US",
    "sg:address":"530 Huyler St",
    "sg:city":"South Hackensack",
    "sg:classifiers":[
        {
            "category":"Professional",
            "type":"Services"
        }
    ],
    "sg:phone":"+1 201 329 9453",
    "sg:postcode":"07606",
    "sg:province":"NJ",
    "sg:tags":[
        "establishment"
    ],
    "wof:name":"Branch 425 Hackensack",
    "wof:placetype":"venue"
},
  "geometry": {"coordinates":[-74.048841,40.863904],"type":"Point"}
}