{
  "type": "Feature",
  "properties": {
    "iso:country":"US",
    "sg:address":"10 Island Rd",
    "sg:city":"Whitehouse",
    "sg:classifiers":[
        {
            "category":"Recreation",
            "type":"Entertainment"
        }
    ],
    "sg:phone":"+1 908 534 7738",
    "sg:postcode":"08888",
    "sg:province":"NJ",
    "sg:tags":[
        "riding",
        "academy"
    ],
    "wof:name":"Tolleshunt Horse Farm",
    "wof:placetype":"venue"
},
  "geometry": {"coordinates":[-74.72207899999999,40.621608],"type":"Point"}
}