{
  "type": "Feature",
  "properties": {
    "addr:full":"12 Winding Hill Rd Vernon NJ 07462",
    "addr:housenumber":"12",
    "addr:postcode":"07462",
    "addr:street":"Winding Hill Rd",
    "iso:country":"US",
    "sg:address":"12 Winding Hill Rd",
    "sg:city":"Vernon",
    "sg:classifiers":[
        {
            "category":"Health Services",
            "subcategory":"Doctor",
            "type":"Services"
        }
    ],
    "sg:phone":"+1 973 827 4313",
    "sg:postcode":"07462",
    "sg:province":"NJ",
    "sg:tags":[
        "medical"
    ],
    "wof:name":"Quality Orthopedics",
    "wof:placetype":"venue"
},
  "geometry": {"coordinates":[-74.544555,41.177902],"type":"Point"}
}