{
  "type": "Feature",
  "properties": {
    "addr:full":"638 Lawrence Rd Trenton NJ 08648",
    "addr:housenumber":"638",
    "addr:postcode":"08648",
    "addr:street":"Lawrence Rd",
    "iso:country":"US",
    "sg:address":"638 Lawrence Rd",
    "sg:city":"Trenton",
    "sg:classifiers":[
        {
            "category":"Health Services",
            "subcategory":"Doctor",
            "type":"Services"
        }
    ],
    "sg:phone":"+1 609 883 8200",
    "sg:postcode":"08648",
    "sg:province":"NJ",
    "sg:tags":[
        "physician",
        "surgeon"
    ],
    "wof:name":"Mercer Ob/Gyn",
    "wof:placetype":"venue"
},
  "geometry": {"coordinates":[-74.741766,40.256459],"type":"Point"}
}