{
  "type": "Feature",
  "properties": {
    "addr:full":"256 Clifton Ave Newark NJ 07104",
    "addr:housenumber":"256",
    "addr:postcode":"07104",
    "addr:street":"Clifton Ave",
    "iso:country":"US",
    "sg:address":"256 Clifton Ave",
    "sg:city":"Newark",
    "sg:classifiers":[
        {
            "category":"Building & Trades",
            "subcategory":"Locksmith",
            "type":"Services"
        }
    ],
    "sg:phone":"+1 973 735 6049",
    "sg:postcode":"07104",
    "sg:province":"NJ",
    "sg:tags":[
        "key"
    ],
    "wof:name":"0 And 0 and 0 1 Emergency A 24 Hour A",
    "wof:placetype":"venue"
},
  "geometry": {"coordinates":[-74.176059,40.758734],"type":"Point"}
}