{
  "type": "Feature",
  "properties": {
    "iso:country":"US",
    "sg:address":"209 2nd St",
    "sg:city":"Lakewood",
    "sg:classifiers":[
        {
            "category":"Education",
            "subcategory":"School",
            "type":"Public Place"
        }
    ],
    "sg:phone":"+1 732 961 9731",
    "sg:postcode":"08701",
    "sg:province":"NJ",
    "wof:name":"Yeshivat Keter Torah",
    "wof:placetype":"venue"
},
  "geometry": {"coordinates":[-74.212352,40.092455],"type":"Point"}
}