{
  "type": "Feature",
  "properties": {
    "addr:full":"93 N Broadway Pennsville NJ 08070",
    "addr:housenumber":"93",
    "addr:postcode":"08070",
    "addr:street":"N Broadway",
    "iso:country":"US",
    "sg:address":"93 N Broadway",
    "sg:city":"Pennsville",
    "sg:classifiers":[
        {
            "category":"Personal",
            "subcategory":"Beauty Salon",
            "type":"Services"
        }
    ],
    "sg:phone":"+1 856 678 2537",
    "sg:postcode":"08070",
    "sg:province":"NJ",
    "sg:tags":[
        "shop"
    ],
    "wof:name":"Archers Beauty Center",
    "wof:placetype":"venue"
},
  "geometry": {"coordinates":[-75.515159,39.659885],"type":"Point"}
}