{
  "type": "Feature",
  "properties": {
    "iso:country":"US",
    "sg:address":"1 Cornell Pkwy",
    "sg:city":"Springfield",
    "sg:classifiers":[
        {
            "category":"Professional",
            "type":"Services"
        }
    ],
    "sg:phone":"+1 973 376 4581",
    "sg:postcode":"07081",
    "sg:province":"NJ",
    "sg:tags":[
        "establishment"
    ],
    "wof:name":"Community Action",
    "wof:placetype":"venue"
},
  "geometry": {"coordinates":[-74.334193,40.683901],"type":"Point"}
}