{
  "type": "Feature",
  "properties": {
    "iso:country":"US",
    "sg:address":"804 Willow Ave",
    "sg:city":"Hoboken",
    "sg:classifiers":[
        {
            "category":"Real Estate",
            "subcategory":"Real Estate Operator",
            "type":"Services"
        }
    ],
    "sg:phone":"+1 201 798 5889",
    "sg:postcode":"07030",
    "sg:province":"NJ",
    "sg:tags":[
        "apartment"
    ],
    "wof:name":"Elaires Corp Inc",
    "wof:placetype":"venue"
},
  "geometry": {"coordinates":[-74.031604,40.747882],"type":"Point"}
}