{
  "type": "Feature",
  "properties": {
    "addr:full":"20 Enterprise Ave N Secaucus NJ 07094",
    "addr:housenumber":"20",
    "addr:postcode":"07094",
    "addr:street":"Enterprise Ave N",
    "iso:country":"US",
    "sg:address":"20 Enterprise Ave N",
    "sg:city":"Secaucus",
    "sg:classifiers":[
        {
            "category":"Shopping",
            "subcategory":"Clothing, Apparel, & Fashions",
            "type":"Retail Goods"
        }
    ],
    "sg:phone":"+1 201 863 1545",
    "sg:postcode":"07094",
    "sg:province":"NJ",
    "sg:tags":[
        "accessory"
    ],
    "wof:name":"Bon Worth",
    "wof:placetype":"venue"
},
  "geometry": {"coordinates":[-74.06680299999999,40.787899],"type":"Point"}
}