{
  "type": "Feature",
  "properties": {
    "iso:country":"US",
    "sg:address":"44 Princeton Pl",
    "sg:city":"Princeton Jct",
    "sg:classifiers":[
        {
            "category":"Banks & Credit Unions",
            "subcategory":"Bank",
            "type":"Services"
        }
    ],
    "sg:phone":"+1 609 799 1500",
    "sg:postcode":"08550",
    "sg:province":"NJ",
    "sg:website":"www.sovereignbank.com",
    "wof:name":"Sovereign Bank",
    "wof:placetype":"venue"
},
  "geometry": {"coordinates":[-74.62079199999999,40.300757],"type":"Point"}
}