{
  "type": "Feature",
  "properties": {
    "addr:full":"1400 Willowbrook Mall Little Falls NJ 07470",
    "addr:housenumber":"1400",
    "addr:postcode":"07470",
    "addr:street":"Willowbrook Mall",
    "iso:country":"US",
    "sg:address":"1400 Willowbrook Mall",
    "sg:city":"Little Falls",
    "sg:classifiers":[
        {
            "category":"Utilities",
            "subcategory":"Mobile Phone",
            "type":"Services"
        }
    ],
    "sg:phone":"+1 973 237 9651",
    "sg:postcode":"07470",
    "sg:province":"NJ",
    "sg:tags":[
        "telephone",
        "cellular"
    ],
    "wof:name":"Cingular Wireless",
    "wof:placetype":"venue"
},
  "geometry": {"coordinates":[-74.255009,40.889541],"type":"Point"}
}