{
  "type": "Feature",
  "properties": {
    "iso:country":"US",
    "sg:address":"875 Lynnwood Ave",
    "sg:city":"Brick",
    "sg:classifiers":[
        {
            "category":"Building & Trades",
            "subcategory":"Electrical",
            "type":"Services"
        }
    ],
    "sg:phone":"+1 732 262 6403",
    "sg:postcode":"08723",
    "sg:province":"NJ",
    "sg:tags":[
        "electrical",
        "contractor"
    ],
    "wof:name":"RJR Electric Co",
    "wof:placetype":"venue"
},
  "geometry": {"coordinates":[-74.13074899999999,40.049552],"type":"Point"}
}