{
  "type": "Feature",
  "properties": {
    "iso:country":"US",
    "sg:address":"530 High Mountain Rd",
    "sg:city":"Haledon",
    "sg:classifiers":[
        {
            "category":"Banks & Credit Unions",
            "subcategory":"Bank",
            "type":"Services"
        }
    ],
    "sg:phone":"+1   ",
    "sg:postcode":"07508",
    "sg:province":"NJ",
    "sg:tags":[
        "state",
        "commercial"
    ],
    "wof:name":"Hudson United Bank",
    "wof:placetype":"venue"
},
  "geometry": {"coordinates":[-74.181613,40.95634],"type":"Point"}
}