{
  "type": "Feature",
  "properties": {
    "addr:full":"329 57th St West New York NJ 07093",
    "addr:housenumber":"329",
    "addr:postcode":"nj 07093",
    "addr:street":"57Th St West",
    "iso:country":"US",
    "sg:address":"329 57th St",
    "sg:city":"West New York",
    "sg:classifiers":[
        {
            "category":"Professional",
            "subcategory":"Business Services",
            "type":"Services"
        },
        {
            "category":"Manufacturing",
            "subcategory":"Apparel",
            "type":"Manufacturing & Wholesale Goods"
        }
    ],
    "sg:phone":"+1 201 348 1090",
    "sg:postcode":"07093",
    "sg:province":"NJ",
    "sg:tags":[
        "embroidery",
        "mfg"
    ],
    "wof:name":"Rome Embroidery Inc",
    "wof:placetype":"venue"
},
  "geometry": {"coordinates":[-74.01528999999999,40.785725],"type":"Point"}
}