{
  "type": "Feature",
  "properties": {
    "addr:full":"445 Brick Blvd Brick NJ 08723",
    "addr:housenumber":"445",
    "addr:postcode":"08723",
    "addr:street":"Brick Blvd",
    "iso:country":"US",
    "sg:address":"445 Brick Blvd",
    "sg:city":"Brick",
    "sg:classifiers":[
        {
            "category":"Professional",
            "subcategory":"Detective & Security Services",
            "type":"Services"
        }
    ],
    "sg:phone":"+1   ",
    "sg:postcode":"08723",
    "sg:province":"NJ",
    "sg:tags":[
        "car"
    ],
    "wof:name":"Argus Security Systems Corp",
    "wof:placetype":"venue"
},
  "geometry": {"coordinates":[-74.14201300000001,40.04632],"type":"Point"}
}