{
  "type": "Feature",
  "properties": {
    "addr:full":"24 Monroe St Union NJ 07083",
    "addr:housenumber":"24",
    "addr:postcode":"07083",
    "addr:street":"Monroe St",
    "iso:country":"US",
    "sg:address":"24 Monroe St",
    "sg:city":"Union",
    "sg:classifiers":[
        {
            "category":"Retail",
            "subcategory":"Laundry & Dry Cleaning",
            "type":"Services"
        }
    ],
    "sg:phone":"+1 908 686 3400",
    "sg:postcode":"07083",
    "sg:province":"NJ",
    "wof:name":"Coin Operated Laundry Equipmnt",
    "wof:placetype":"venue"
},
  "geometry": {"coordinates":[-74.301192,40.687133],"type":"Point"}
}