{
  "type": "Feature",
  "properties": {
    "iso:country":"US",
    "sg:address":"218 Whitehead Ave",
    "sg:city":"South River",
    "sg:classifiers":[
        {
            "category":"Retail",
            "subcategory":"Funeral Services",
            "type":"Services"
        }
    ],
    "sg:phone":"+1   ",
    "sg:postcode":"08882",
    "sg:province":"NJ",
    "wof:name":"Maliszewski Funeral Home",
    "wof:placetype":"venue"
},
  "geometry": {"coordinates":[-74.376625,40.44911],"type":"Point"}
}