{
  "type": "Feature",
  "properties": {
    "addr:full":"376 Broadway Newark NJ 07104",
    "addr:housenumber":"376",
    "addr:postcode":"07104",
    "addr:street":"Broadway",
    "iso:country":"US",
    "sg:address":"376 Broadway",
    "sg:city":"Newark",
    "sg:classifiers":[
        {
            "category":"Autos & Motor Vehicles",
            "subcategory":"Automobile Sales",
            "type":"Retail Goods"
        }
    ],
    "sg:phone":"+1 973 485 5516",
    "sg:postcode":"07104",
    "sg:province":"NJ",
    "sg:tags":[
        "car",
        "dealer"
    ],
    "wof:name":"J & C Auto Sales",
    "wof:placetype":"venue"
},
  "geometry": {"coordinates":[-74.165722,40.764961],"type":"Point"}
}