{
  "type": "Feature",
  "properties": {
    "addr:full":"1155 Hendricks Cswy Ridgefield NJ 07657",
    "addr:housenumber":"1155",
    "addr:postcode":"07657",
    "addr:street":"Hendricks Cswy",
    "iso:country":"US",
    "sg:address":"1155 Hendricks Cswy",
    "sg:city":"Ridgefield",
    "sg:classifiers":[
        {
            "category":"Organizations",
            "subcategory":"Religious Organization",
            "type":"Services"
        }
    ],
    "sg:phone":"+1 201 941 3077",
    "sg:postcode":"07657",
    "sg:province":"NJ",
    "wof:name":"Lord Jesus Love Church",
    "wof:placetype":"venue"
},
  "geometry": {"coordinates":[-74.015927,40.834945],"type":"Point"}
}