{
  "type": "Feature",
  "properties": {
    "addr:full":"380 Springfield Ave Summit NJ 07901",
    "addr:housenumber":"380",
    "addr:postcode":"07901",
    "addr:street":"Springfield Ave",
    "iso:country":"US",
    "sg:address":"380 Springfield Ave",
    "sg:city":"Summit",
    "sg:classifiers":[
        {
            "category":"Shopping",
            "subcategory":"Clothing, Apparel, & Fashions",
            "type":"Retail Goods"
        }
    ],
    "sg:phone":"+1 908 598 0043",
    "sg:postcode":"07901",
    "sg:province":"NJ",
    "sg:tags":[
        "accessory",
        "clothing",
        "women's"
    ],
    "wof:name":"Egoiste",
    "wof:placetype":"venue"
},
  "geometry": {"coordinates":[-74.357845,40.71788],"type":"Point"}
}