{
  "type": "Feature",
  "properties": {
    "iso:country":"US",
    "sg:address":"514 Bryant Ave",
    "sg:city":"Magnolia",
    "sg:classifiers":[
        {
            "category":"Retail",
            "subcategory":"Repair Shop",
            "type":"Services"
        }
    ],
    "sg:phone":"+1 856 547 0730",
    "sg:postcode":"08049",
    "sg:province":"NJ",
    "sg:tags":[
        "refinishing",
        "furniture"
    ],
    "wof:name":"Apex Refinishing & Uphlstrng",
    "wof:placetype":"venue"
},
  "geometry": {"coordinates":[-75.02968199999999,39.85958],"type":"Point"}
}