{
  "type": "Feature",
  "properties": {
    "addr:full":"242 W Saddle River Rd Saddle River NJ 07458",
    "addr:housenumber":"242",
    "addr:postcode":"07458",
    "addr:street":"W Saddle River Rd",
    "iso:country":"US",
    "sg:address":"242 W Saddle River Rd",
    "sg:city":"Saddle River",
    "sg:phone":"+1 201 236 8122",
    "sg:postcode":"07458",
    "sg:province":"NJ",
    "sg:tags":[
        "equipment",
        "commercial"
    ],
    "wof:name":"Frank Geiger Philatelists",
    "wof:placetype":"venue"
},
  "geometry": {"coordinates":[-74.101429,41.048171],"type":"Point"}
}