{
  "type": "Feature",
  "properties": {
    "iso:country":"US",
    "sg:address":"70 Middlesex Ave",
    "sg:city":"Metuchen",
    "sg:classifiers":[
        {
            "category":"Banks & Credit Unions",
            "subcategory":"Bank",
            "type":"Services"
        }
    ],
    "sg:phone":"+1 732 516 0824",
    "sg:postcode":"08840",
    "sg:province":"NJ",
    "sg:tags":[
        "state",
        "commercial"
    ],
    "wof:name":"Commerce Bank NA",
    "wof:placetype":"venue"
},
  "geometry": {"coordinates":[-74.347914,40.554228],"type":"Point"}
}