{
  "type": "Feature",
  "properties": {
    "addr:full":"174 Edison Ave Cherry Hill NJ 08002",
    "addr:housenumber":"174",
    "addr:postcode":"08002",
    "addr:street":"Edison Ave",
    "iso:country":"US",
    "sg:address":"174 Edison Ave",
    "sg:city":"Cherry Hill",
    "sg:classifiers":[
        {
            "category":"Building & Trades",
            "subcategory":"Electrical",
            "type":"Services"
        }
    ],
    "sg:phone":"+1 856 429 0457",
    "sg:postcode":"08002",
    "sg:province":"NJ",
    "sg:tags":[
        "electrician"
    ],
    "wof:name":"Griffeth Electric",
    "wof:placetype":"venue"
},
  "geometry": {"coordinates":[-75.02252300000001,39.910321],"type":"Point"}
}