{
  "type": "Feature",
  "properties": {
    "iso:country":"US",
    "sg:address":"196 Garibaldi Ave",
    "sg:city":"Lodi",
    "sg:classifiers":[
        {
            "category":"Health Services",
            "subcategory":"Chiropractor",
            "type":"Services"
        }
    ],
    "sg:phone":"+1 973 473 0092",
    "sg:postcode":"07644",
    "sg:province":"NJ",
    "wof:name":"D & A Chiropractic Ctr LLC",
    "wof:placetype":"venue"
},
  "geometry": {"coordinates":[-74.074263,40.880204],"type":"Point"}
}