{
  "type": "Feature",
  "properties": {
    "addr:full":"173 W Shore Trl Sparta NJ 07871",
    "addr:housenumber":"173",
    "addr:postcode":"07871",
    "addr:street":"W Shore Trl",
    "iso:country":"US",
    "sg:address":"173 W Shore Trl",
    "sg:city":"Sparta",
    "sg:classifiers":[
        {
            "category":"Wholesale",
            "subcategory":"Drugs",
            "type":"Manufacturing & Wholesale Goods"
        }
    ],
    "sg:phone":"+1 973 729 9242",
    "sg:postcode":"07871",
    "sg:province":"NJ",
    "sg:tags":[
        "pharmaceutical",
        "product"
    ],
    "wof:name":"Park Davis Pharmeceuticals",
    "wof:placetype":"venue"
},
  "geometry": {"coordinates":[-74.656002,41.032137],"type":"Point"}
}