{
  "type": "Feature",
  "properties": {
    "iso:country":"US",
    "sg:address":"19 Cutler Dr",
    "sg:city":"Morris Plains",
    "sg:classifiers":[
        {
            "category":"Professional",
            "subcategory":"Management & Consulting",
            "type":"Services"
        }
    ],
    "sg:phone":"+1 973 539 8080",
    "sg:postcode":"07950",
    "sg:province":"NJ",
    "wof:name":"Knowledge Plus Inc",
    "wof:placetype":"venue"
},
  "geometry": {"coordinates":[-74.49021500000001,40.831097],"type":"Point"}
}