{
  "type": "Feature",
  "properties": {
    "iso:country":"US",
    "sg:address":"309 13th Ave",
    "sg:city":"Belmar",
    "sg:classifiers":[
        {
            "category":"Shopping",
            "subcategory":"Discount & Variety Stores",
            "type":"Retail Goods"
        }
    ],
    "sg:phone":"+1   ",
    "sg:postcode":"07719",
    "sg:province":"NJ",
    "sg:tags":[
        "merchandise",
        "general"
    ],
    "wof:name":"Schutt Salvage",
    "wof:placetype":"venue"
},
  "geometry": {"coordinates":[-74.020625,40.175348],"type":"Point"}
}