{
  "type": "Feature",
  "properties": {
    "addr:full":"7 Hickory Ln Closter NJ 07624",
    "addr:housenumber":"7",
    "addr:postcode":"07624",
    "addr:street":"Hickory Ln",
    "iso:country":"US",
    "sg:address":"7 Hickory Ln",
    "sg:city":"Closter",
    "sg:classifiers":[
        {
            "category":"Wholesale",
            "subcategory":"Apparel",
            "type":"Manufacturing & Wholesale Goods"
        }
    ],
    "sg:phone":"+1 201 784 3834",
    "sg:postcode":"07624",
    "sg:province":"NJ",
    "sg:tags":[
        "footwear"
    ],
    "wof:name":"Tara Shoe Inc",
    "wof:placetype":"venue"
},
  "geometry": {"coordinates":[-73.94571000000001,40.973789],"type":"Point"}
}