{
  "type": "Feature",
  "properties": {
    "addr:full":"250 US Hwy 46 Budd Lake NJ 07828",
    "addr:housenumber":"250",
    "addr:postcode":"07828",
    "addr:street":"Us Hwy 46",
    "iso:country":"US",
    "sg:address":"250 US Hwy 46",
    "sg:city":"Budd Lake",
    "sg:classifiers":[
        {
            "category":"Real Estate",
            "subcategory":"Real Estate Agent",
            "type":"Services"
        }
    ],
    "sg:phone":"+1 973 691 1700",
    "sg:postcode":"07828",
    "sg:province":"NJ",
    "sg:tags":[
        "consultant"
    ],
    "wof:name":"Robert T Gall Realty",
    "wof:placetype":"venue"
},
  "geometry": {"coordinates":[-74.737735,40.869296],"type":"Point"}
}