{
  "type": "Feature",
  "properties": {
    "addr:full":"1052 Chanticleer Dr Cherry Hill NJ 08003",
    "addr:housenumber":"1052",
    "addr:postcode":"08003",
    "addr:street":"Chanticleer Dr",
    "iso:country":"US",
    "sg:address":"1052 Chanticleer Dr",
    "sg:city":"Cherry Hill",
    "sg:classifiers":[
        {
            "category":"Organizations",
            "subcategory":"Religious Organization",
            "type":"Services"
        }
    ],
    "sg:phone":"+1   ",
    "sg:postcode":"08003",
    "sg:province":"NJ",
    "wof:name":"Jewish Community Center",
    "wof:placetype":"venue"
},
  "geometry": {"coordinates":[-74.95314999999999,39.87087],"type":"Point"}
}