{
  "type": "Feature",
  "properties": {
    "iso:country":"US",
    "sg:address":"148 E Cliff St",
    "sg:city":"Somerville",
    "sg:classifiers":[
        {
            "category":"Building & Trades",
            "subcategory":"Construction",
            "type":"Services"
        }
    ],
    "sg:phone":"+1 908 725 2820",
    "sg:postcode":"08876",
    "sg:province":"NJ",
    "sg:tags":[
        "general",
        "contractor"
    ],
    "wof:name":"Bob Bocchino Inc",
    "wof:placetype":"venue"
},
  "geometry": {"coordinates":[-74.60358600000001,40.569643],"type":"Point"}
}