{
  "type": "Feature",
  "properties": {
    "iso:country":"US",
    "sg:address":"330 Grand St",
    "sg:city":"Paterson",
    "sg:classifiers":[
        {
            "category":"Travel",
            "subcategory":"Travel Agent",
            "type":"Entertainment"
        }
    ],
    "sg:phone":"+1 973 925 9800",
    "sg:postcode":"07505",
    "sg:province":"NJ",
    "sg:tags":[
        "agency",
        "bureau"
    ],
    "wof:name":"Amigo Travel Express",
    "wof:placetype":"venue"
},
  "geometry": {"coordinates":[-74.174311,40.911664],"type":"Point"}
}