{
  "type": "Feature",
  "properties": {
    "iso:country":"US",
    "sg:address":"345 State Rte 17",
    "sg:city":"Saddle River",
    "sg:classifiers":[
        {
            "category":"Manufacturing",
            "subcategory":"Tools & Machinery",
            "type":"Manufacturing & Wholesale Goods"
        }
    ],
    "sg:phone":"+1 201 934 4206",
    "sg:postcode":"07458",
    "sg:province":"NJ",
    "sg:tags":[
        "spray",
        "mfg",
        "outfit"
    ],
    "wof:name":"Usi of North America Inc",
    "wof:placetype":"venue"
},
  "geometry": {"coordinates":[-74.11976199999999,41.053948],"type":"Point"}
}