{
  "type": "Feature",
  "properties": {
    "iso:country":"US",
    "sg:address":"489 W 1st Ave",
    "sg:city":"Roselle",
    "sg:classifiers":[
        {
            "category":"Retail",
            "subcategory":"Auto Repair",
            "type":"Services"
        }
    ],
    "sg:phone":"+1 908 241 6020",
    "sg:postcode":"07203",
    "sg:province":"NJ",
    "sg:tags":[
        "repairing",
        "automobile"
    ],
    "wof:name":"M & C Auto Sales",
    "wof:placetype":"venue"
},
  "geometry": {"coordinates":[-74.277627,40.658123],"type":"Point"}
}