{
  "type": "Feature",
  "properties": {
    "addr:full":"154 Carlisle Ave Trenton NJ 08620",
    "addr:housenumber":"154",
    "addr:postcode":"08620",
    "addr:street":"Carlisle Ave",
    "iso:country":"US",
    "sg:address":"154 Carlisle Ave",
    "sg:city":"Trenton",
    "sg:classifiers":[
        {
            "category":"Recreation",
            "type":"Entertainment"
        }
    ],
    "sg:phone":"+1 609 631 8522",
    "sg:postcode":"08620",
    "sg:province":"NJ",
    "sg:tags":[
        "club",
        "membership"
    ],
    "wof:name":"Hhw Baseball Booster Club",
    "wof:placetype":"venue"
},
  "geometry": {"coordinates":[-74.65941100000001,40.180872],"type":"Point"}
}