{
  "type": "Feature",
  "properties": {
    "addr:full":"114 Country Ln Trenton NJ 08628",
    "addr:housenumber":"114",
    "addr:postcode":"08628",
    "addr:street":"Country Ln",
    "iso:country":"US",
    "sg:address":"114 Country Ln",
    "sg:city":"Trenton",
    "sg:classifiers":[
        {
            "category":"Health Services",
            "subcategory":"Clinic",
            "type":"Services"
        }
    ],
    "sg:phone":"+1 609 771 8939",
    "sg:postcode":"08628",
    "sg:province":"NJ",
    "wof:name":"Serv Health Systems",
    "wof:placetype":"venue"
},
  "geometry": {"coordinates":[-74.831226,40.248298],"type":"Point"}
}