{
  "type": "Feature",
  "properties": {
    "addr:full":"314 Heritage Rd Mickleton NJ 08056",
    "addr:housenumber":"314",
    "addr:postcode":"08056",
    "addr:street":"Heritage Rd",
    "iso:country":"US",
    "sg:address":"314 Heritage Rd",
    "sg:city":"Mickleton",
    "sg:classifiers":[
        {
            "category":"Professional",
            "type":"Services"
        }
    ],
    "sg:phone":"+1   ",
    "sg:postcode":"08056",
    "sg:province":"NJ",
    "wof:name":"Ronald F Mertz Son Inc",
    "wof:placetype":"venue"
},
  "geometry": {"coordinates":[-75.221282,39.772419],"type":"Point"}
}