{
  "type": "Feature",
  "properties": {
    "iso:country":"US",
    "sg:address":"663 Blackwood Clementon Rd",
    "sg:city":"Clementon",
    "sg:classifiers":[
        {
            "category":"Personal",
            "subcategory":"Beauty Salon",
            "type":"Services"
        }
    ],
    "sg:phone":"+1 856 784 2888",
    "sg:postcode":"08021",
    "sg:province":"NJ",
    "sg:tags":[
        "shop"
    ],
    "wof:name":"Jana's Unique Hair Salon",
    "wof:placetype":"venue"
},
  "geometry": {"coordinates":[-75.00623,39.805191],"type":"Point"}
}