{
  "type": "Feature",
  "properties": {
    "iso:country":"US",
    "sg:address":"124 E Palisades Blvd",
    "sg:city":"Palisades Park",
    "sg:classifiers":[
        {
            "category":"Restaurant",
            "type":"Food & Drink"
        }
    ],
    "sg:phone":"+1 201 489 7756",
    "sg:postcode":"07650",
    "sg:province":"NJ",
    "wof:name":"Joji Gourmet Pizza & Rstrnt",
    "wof:placetype":"venue"
},
  "geometry": {"coordinates":[-73.99203799999999,40.847201],"type":"Point"}
}