{
  "type": "Feature",
  "properties": {
    "iso:country":"US",
    "sg:address":"335 Chestnut St",
    "sg:city":"Norwood",
    "sg:classifiers":[
        {
            "category":"Freight",
            "type":"Transportation"
        }
    ],
    "sg:phone":"+1 201 767 0910",
    "sg:postcode":"07648",
    "sg:province":"NJ",
    "sg:tags":[
        "courier"
    ],
    "wof:name":"Courier Service-Northern Vly",
    "wof:placetype":"venue"
},
  "geometry": {"coordinates":[-73.95408500000001,40.993636],"type":"Point"}
}