{
  "type": "Feature",
  "properties": {
    "iso:country":"US",
    "sg:address":"36 State Rte 70",
    "sg:city":"Marlton",
    "sg:classifiers":[
        {
            "category":"Real Estate",
            "subcategory":"Architect",
            "type":"Services"
        }
    ],
    "sg:phone":"+1 856 983 1720",
    "sg:postcode":"08053",
    "sg:province":"NJ",
    "wof:name":"Architectural Assistance Std",
    "wof:placetype":"venue"
},
  "geometry": {"coordinates":[-74.920479,39.894047],"type":"Point"}
}