{
  "type": "Feature",
  "properties": {
    "addr:full":"609 Newman Pl Roselle NJ 07203",
    "addr:housenumber":"609",
    "addr:postcode":"07203",
    "addr:street":"Newman Pl",
    "iso:country":"US",
    "sg:address":"609 Newman Pl",
    "sg:city":"Roselle",
    "sg:classifiers":[
        {
            "category":"Real Estate",
            "subcategory":"Real Estate Operator",
            "type":"Services"
        }
    ],
    "sg:phone":"+1   ",
    "sg:postcode":"07203",
    "sg:province":"NJ",
    "sg:tags":[
        "building",
        "apartment"
    ],
    "wof:name":"Warinanco Garden Apartments",
    "wof:placetype":"venue"
},
  "geometry": {"coordinates":[-74.244461,40.650434],"type":"Point"}
}