{
  "type": "Feature",
  "properties": {
    "addr:full":"90 US Hwy 206 Flanders NJ 07836",
    "addr:housenumber":"90",
    "addr:postcode":"07836",
    "addr:street":"Us Hwy 206",
    "iso:country":"US",
    "sg:address":"90 US Hwy 206",
    "sg:city":"Flanders",
    "sg:classifiers":[
        {
            "category":"Autos & Motor Vehicles",
            "subcategory":"Fuel & Gas Station",
            "type":"Retail Goods"
        }
    ],
    "sg:phone":"+1 973 691 4443",
    "sg:postcode":"07836",
    "sg:province":"NJ",
    "sg:tags":[
        "oil"
    ],
    "wof:name":"Hoops Shell",
    "wof:placetype":"venue"
},
  "geometry": {"coordinates":[-74.69552,40.869951],"type":"Point"}
}