{
  "type": "Feature",
  "properties": {
    "addr:full":"675 Trenton St New Milford NJ 07646",
    "addr:housenumber":"675",
    "addr:postcode":"07646",
    "addr:street":"Trenton St",
    "iso:country":"US",
    "sg:address":"675 Trenton St",
    "sg:city":"New Milford",
    "sg:classifiers":[
        {
            "category":"Retail",
            "subcategory":"Auto Repair",
            "type":"Services"
        }
    ],
    "sg:phone":"+1 201 599 1554",
    "sg:postcode":"07646",
    "sg:province":"NJ",
    "sg:tags":[
        "general"
    ],
    "wof:name":"Melikian Garage Doors",
    "wof:placetype":"venue"
},
  "geometry": {"coordinates":[-74.024404,40.931559],"type":"Point"}
}