{
  "type": "Feature",
  "properties": {
    "iso:country":"US",
    "sg:address":"211 Benigno Blvd",
    "sg:city":"Bellmawr",
    "sg:classifiers":[
        {
            "category":"Professional",
            "subcategory":"Management & Consulting",
            "type":"Services"
        }
    ],
    "sg:phone":"+1 856 931 8163",
    "sg:postcode":"08031",
    "sg:province":"NJ",
    "sg:tags":[
        "marketing",
        "program"
    ],
    "wof:name":"International Thoroughbred",
    "wof:placetype":"venue"
},
  "geometry": {"coordinates":[-75.08701499999999,39.86088],"type":"Point"}
}