{
  "type": "Feature",
  "properties": {
    "iso:country":"US",
    "sg:address":"55 Passaic Ave",
    "sg:city":"Kearny",
    "sg:classifiers":[
        {
            "category":"Real Estate",
            "subcategory":"Real Estate Agent",
            "type":"Services"
        }
    ],
    "sg:phone":"+1   ",
    "sg:postcode":"07032",
    "sg:province":"NJ",
    "sg:tags":[
        "management"
    ],
    "wof:name":"American Interstate Corp",
    "wof:placetype":"venue"
},
  "geometry": {"coordinates":[-74.162465,40.755125],"type":"Point"}
}