{
  "type": "Feature",
  "properties": {
    "iso:country":"US",
    "sg:address":"11 W Elizabeth Ave",
    "sg:city":"Linden",
    "sg:classifiers":[
        {
            "category":"Food & Beverages",
            "subcategory":"Groceries & Convenience Stores",
            "type":"Retail Goods"
        }
    ],
    "sg:phone":"+1   ",
    "sg:postcode":"07036",
    "sg:province":"NJ",
    "wof:name":"Linden 6",
    "wof:placetype":"venue"
},
  "geometry": {"coordinates":[-74.254452,40.628615],"type":"Point"}
}