{
  "type": "Feature",
  "properties": {
    "iso:country":"US",
    "sg:address":"932 Madison Ave",
    "sg:city":"Toms River",
    "sg:classifiers":[
        {
            "category":"Professional",
            "type":"Services"
        }
    ],
    "sg:phone":"+1   ",
    "sg:postcode":"08757",
    "sg:province":"NJ",
    "wof:name":"Live Wire Communications",
    "wof:placetype":"venue"
},
  "geometry": {"coordinates":[-74.26512200000001,40.002847],"type":"Point"}
}