{
  "type": "Feature",
  "properties": {
    "addr:full":"219 Division St Boonton NJ 07005",
    "addr:housenumber":"219",
    "addr:postcode":"07005",
    "addr:street":"Division St",
    "iso:country":"US",
    "sg:address":"219 Division St",
    "sg:city":"Boonton",
    "sg:classifiers":[
        {
            "category":"Retail",
            "subcategory":"Auto Repair",
            "type":"Services"
        }
    ],
    "sg:phone":"+1   ",
    "sg:postcode":"07005",
    "sg:province":"NJ",
    "sg:tags":[
        "body",
        "automobile",
        "used"
    ],
    "sg:website":"www.nostalgia.com",
    "wof:name":"Nostalgia Motors Inc",
    "wof:placetype":"venue"
},
  "geometry": {"coordinates":[-74.405641,40.905255],"type":"Point"}
}