{
  "type": "Feature",
  "properties": {
    "addr:full":"376 Ocean Ave Sea Bright NJ 07760",
    "addr:housenumber":"376",
    "addr:postcode":"07760",
    "addr:street":"Ocean Ave",
    "iso:country":"US",
    "sg:address":"376 Ocean Ave",
    "sg:city":"Sea Bright",
    "sg:classifiers":[
        {
            "category":"Building & Trades",
            "subcategory":"Construction",
            "type":"Services"
        }
    ],
    "sg:phone":"+1 732 842 3544",
    "sg:postcode":"07760",
    "sg:province":"NJ",
    "sg:tags":[
        "designer",
        "marine",
        "contractor"
    ],
    "wof:name":"W Ken Bahrs Co",
    "wof:placetype":"venue"
},
  "geometry": {"coordinates":[-73.974885,40.384667],"type":"Point"}
}