{
  "type": "Feature",
  "properties": {
    "iso:country":"US",
    "sg:address":"207 Railroad Ave",
    "sg:city":"Harrison",
    "sg:classifiers":[
        {
            "category":"Manufacturing",
            "subcategory":"Textiles",
            "type":"Manufacturing & Wholesale Goods"
        }
    ],
    "sg:phone":"+1 973 481 9497",
    "sg:postcode":"07029",
    "sg:province":"NJ",
    "sg:tags":[
        "printing",
        "fabric",
        "cotton"
    ],
    "wof:name":"Peacock Printing",
    "wof:placetype":"venue"
},
  "geometry": {"coordinates":[-74.15591499999999,40.741581],"type":"Point"}
}