{
  "type": "Feature",
  "properties": {
    "iso:country":"US",
    "sg:address":"171 Broad St",
    "sg:city":"Red Bank",
    "sg:classifiers":[
        {
            "category":"Banks & Credit Unions",
            "subcategory":"Bank",
            "type":"Services"
        }
    ],
    "sg:phone":"+1 732 219 0009",
    "sg:postcode":"07701",
    "sg:province":"NJ",
    "sg:website":"www.monmouthpostalcu.org",
    "wof:name":"Monmouth County Postal EMP Cu",
    "wof:placetype":"venue"
},
  "geometry": {"coordinates":[-74.06476499999999,40.346291],"type":"Point"}
}