{
  "type": "Feature",
  "properties": {
    "addr:full":"26 New York Ave Wayne NJ 07470",
    "addr:housenumber":"26",
    "addr:postcode":"07470",
    "addr:street":"New York Ave",
    "iso:country":"US",
    "sg:address":"26 New York Ave",
    "sg:city":"Wayne",
    "sg:classifiers":[
        {
            "category":"Shopping",
            "subcategory":"Musical Instruments",
            "type":"Retail Goods"
        }
    ],
    "sg:phone":"+1   ",
    "sg:postcode":"07470",
    "sg:province":"NJ",
    "wof:name":"Waynes Piano Service",
    "wof:placetype":"venue"
},
  "geometry": {"coordinates":[-74.26822799999999,40.924735],"type":"Point"}
}