{
  "type": "Feature",
  "properties": {
    "addr:full":"6 Broadway Fair Lawn NJ 07410",
    "addr:housenumber":"6",
    "addr:postcode":"07410",
    "addr:street":"Broadway",
    "iso:country":"US",
    "sg:address":"6 Broadway",
    "sg:city":"Fair Lawn",
    "sg:classifiers":[
        {
            "category":"Professional",
            "subcategory":"Accounting & Tax Preparation",
            "type":"Services"
        }
    ],
    "sg:phone":"+1 201 794 1040",
    "sg:postcode":"07410",
    "sg:province":"NJ",
    "sg:tags":[
        "accountant"
    ],
    "wof:name":"H J Bookbinder CPA",
    "wof:placetype":"venue"
},
  "geometry": {"coordinates":[-74.121326,40.920178],"type":"Point"}
}