{
  "type": "Feature",
  "properties": {
    "iso:country":"US",
    "sg:address":"1106 W Somerdale Rd",
    "sg:city":"Somerdale",
    "sg:classifiers":[
        {
            "category":"Building & Trades",
            "subcategory":"Construction",
            "type":"Services"
        }
    ],
    "sg:phone":"+1 856 346 4167",
    "sg:postcode":"08083",
    "sg:province":"NJ",
    "sg:tags":[
        "hanging",
        "contractor"
    ],
    "wof:name":"Robert A Sexauer Pntg Contr",
    "wof:placetype":"venue"
},
  "geometry": {"coordinates":[-75.031335,39.84191],"type":"Point"}
}