{
  "type": "Feature",
  "properties": {
    "addr:full":"31 Innsbruck Dr Sicklerville NJ 08081",
    "addr:housenumber":"31",
    "addr:postcode":"08081",
    "addr:street":"Innsbruck Dr",
    "iso:country":"US",
    "sg:address":"31 Innsbruck Dr",
    "sg:city":"Sicklerville",
    "sg:classifiers":[
        {
            "category":"Manufacturing",
            "subcategory":"Furniture",
            "type":"Manufacturing & Wholesale Goods"
        }
    ],
    "sg:phone":"+1 856 784 4183",
    "sg:postcode":"08081",
    "sg:province":"NJ",
    "sg:tags":[
        "household",
        "wood",
        "mfg"
    ],
    "wof:name":"Rich Wood",
    "wof:placetype":"venue"
},
  "geometry": {"coordinates":[-74.98889200000001,39.761678],"type":"Point"}
}