{
  "type": "Feature",
  "properties": {
    "addr:full":"1979 Township Dr Marlboro NJ 07746",
    "addr:housenumber":"1979",
    "addr:postcode":"07746",
    "addr:street":"Township Dr",
    "iso:country":"US",
    "sg:address":"1979 Township Dr",
    "sg:city":"Marlboro",
    "sg:classifiers":[
        {
            "category":"Recreation",
            "type":"Entertainment"
        }
    ],
    "sg:phone":"+1 732 617 0100",
    "sg:postcode":"07746",
    "sg:province":"NJ",
    "sg:tags":[
        "parks"
    ],
    "wof:name":"Marlboro Twp Recreation Office",
    "wof:placetype":"venue"
},
  "geometry": {"coordinates":[-74.266071,40.326154],"type":"Point"}
}