{
  "type": "Feature",
  "properties": {
    "addr:full":"8 Industrial Park Ringwood NJ 07463",
    "addr:housenumber":"8",
    "addr:postcode":"07463",
    "addr:street":"Industrial Park",
    "iso:country":"US",
    "sg:address":"8 Industrial Park",
    "sg:city":"Ringwood",
    "sg:classifiers":[
        {
            "category":"Manufacturing",
            "subcategory":"Chemicals & Compounds",
            "type":"Manufacturing & Wholesale Goods"
        }
    ],
    "sg:phone":"+1 973 962 4234",
    "sg:postcode":"07463",
    "sg:province":"NJ",
    "sg:tags":[
        "prep",
        "perfume"
    ],
    "wof:name":"Belwood Aromatics",
    "wof:placetype":"venue"
},
  "geometry": {"coordinates":[-74.12637100000001,41.02071],"type":"Point"}
}