{
  "type": "Feature",
  "properties": {
    "iso:country":"US",
    "sg:address":"46 Haines Dr",
    "sg:city":"Sewell",
    "sg:classifiers":[
        {
            "category":"Arts & Performance",
            "subcategory":"Theater",
            "type":"Entertainment"
        }
    ],
    "sg:phone":"+1   ",
    "sg:postcode":"08080",
    "sg:province":"NJ",
    "sg:tags":[
        "group"
    ],
    "wof:name":"Ocular Entertainment LLP",
    "wof:placetype":"venue"
},
  "geometry": {"coordinates":[-75.093155,39.751877],"type":"Point"}
}