{
  "type": "Feature",
  "properties": {
    "addr:full":"245 Hamburg Tpke Bloomingdale NJ 07403",
    "addr:housenumber":"245",
    "addr:postcode":"07403",
    "addr:street":"Hamburg Tpke",
    "iso:country":"US",
    "sg:address":"245 Hamburg Tpke",
    "sg:city":"Bloomingdale",
    "sg:classifiers":[
        {
            "category":"Real Estate",
            "subcategory":"Real Estate Operator",
            "type":"Services"
        }
    ],
    "sg:phone":"+1 973 838 6363",
    "sg:postcode":"07403",
    "sg:province":"NJ",
    "sg:tags":[
        "building",
        "apartment"
    ],
    "wof:name":"Waterfall Village",
    "wof:placetype":"venue"
},
  "geometry": {"coordinates":[-74.351097,41.006599],"type":"Point"}
}