{
  "type": "Feature",
  "properties": {
    "iso:country":"US",
    "sg:address":"265 E Bay Ave",
    "sg:city":"Manahawkin",
    "sg:classifiers":[
        {
            "category":"Food & Beverages",
            "subcategory":"Fruits & Vegetables",
            "type":"Retail Goods"
        }
    ],
    "sg:phone":"+1 609 597 5463",
    "sg:postcode":"08050",
    "sg:province":"NJ",
    "sg:tags":[
        "produce"
    ],
    "wof:name":"Champion Produce Inc",
    "wof:placetype":"venue"
},
  "geometry": {"coordinates":[-74.25127500000001,39.691639],"type":"Point"}
}