{
  "type": "Feature",
  "properties": {
    "addr:full":"24 Kulick Rd Fairfield NJ 07004",
    "addr:housenumber":"24",
    "addr:postcode":"07004",
    "addr:street":"Kulick Rd",
    "iso:country":"US",
    "sg:address":"24 Kulick Rd",
    "sg:city":"Fairfield",
    "sg:classifiers":[
        {
            "category":"Brewery",
            "type":"Food & Drink"
        }
    ],
    "sg:phone":"+1 973 276 9415",
    "sg:postcode":"07004",
    "sg:province":"NJ",
    "sg:website":"www.crickethillbrewery.com",
    "wof:name":"Cricket Hill Brewing Co Inc",
    "wof:placetype":"venue"
},
  "geometry": {"coordinates":[-74.296359,40.872566],"type":"Point"}
}