{
  "type": "Feature",
  "properties": {
    "addr:full":"17 Greenbrook Dr Matawan NJ 07747",
    "addr:housenumber":"17",
    "addr:postcode":"07747",
    "addr:street":"Greenbrook Dr",
    "iso:country":"US",
    "sg:address":"17 Greenbrook Dr",
    "sg:city":"Matawan",
    "sg:classifiers":[
        {
            "category":"Banks & Credit Unions",
            "subcategory":"Financial Services",
            "type":"Services"
        }
    ],
    "sg:phone":"+1   ",
    "sg:postcode":"07747",
    "sg:province":"NJ",
    "sg:tags":[
        "investment"
    ],
    "wof:name":"S & P Investments Co",
    "wof:placetype":"venue"
},
  "geometry": {"coordinates":[-74.251947,40.405045],"type":"Point"}
}