{
  "type": "Feature",
  "properties": {
    "iso:country":"US",
    "sg:address":"33 Fairfield Ave",
    "sg:city":"Oceanport",
    "sg:classifiers":[
        {
            "category":"Building & Trades",
            "subcategory":"Plumbing",
            "type":"Services"
        }
    ],
    "sg:phone":"+1 732 728 1881",
    "sg:postcode":"07757",
    "sg:province":"NJ",
    "sg:tags":[
        "contractor"
    ],
    "wof:name":"James Koechlin Plumbing",
    "wof:placetype":"venue"
},
  "geometry": {"coordinates":[-74.018956,40.3042],"type":"Point"}
}