{
  "type": "Feature",
  "properties": {
    "iso:country":"US",
    "sg:address":"124 E Andrews Ave",
    "sg:city":"Wildwood",
    "sg:classifiers":[
        {
            "category":"Real Estate",
            "subcategory":"Real Estate Agent",
            "type":"Services"
        }
    ],
    "sg:phone":"+1   ",
    "sg:postcode":"08260",
    "sg:province":"NJ",
    "wof:name":"Grotto De Mare",
    "wof:placetype":"venue"
},
  "geometry": {"coordinates":[-74.823089,38.984674],"type":"Point"}
}