{
  "type": "Feature",
  "properties": {
    "iso:country":"US",
    "sg:address":"200 Fairview Rd",
    "sg:city":"Frenchtown",
    "sg:classifiers":[
        {
            "category":"Arts & Performance",
            "subcategory":"Theater",
            "type":"Entertainment"
        }
    ],
    "sg:phone":"+1 908 996 6744",
    "sg:postcode":"08825",
    "sg:province":"NJ",
    "sg:tags":[
        "theatrical"
    ],
    "wof:name":"Terpsichore Sand",
    "wof:placetype":"venue"
},
  "geometry": {"coordinates":[-75.053157,40.493306],"type":"Point"}
}