{
  "type": "Feature",
  "properties": {
    "addr:full":"25 S Orange Ave South Orange NJ 07079",
    "addr:housenumber":"25",
    "addr:postcode":"07079",
    "addr:street":"S Orange Ave",
    "iso:country":"US",
    "sg:address":"25 S Orange Ave",
    "sg:city":"South Orange",
    "sg:classifiers":[
        {
            "category":"Food & Beverages",
            "subcategory":"Liquor & Beverages",
            "type":"Retail Goods"
        }
    ],
    "sg:phone":"+1 973 762 9682",
    "sg:postcode":"07079",
    "sg:province":"NJ",
    "wof:name":"Wine Emporium",
    "wof:placetype":"venue"
},
  "geometry": {"coordinates":[-74.25999299999999,40.746474],"type":"Point"}
}