{
  "type": "Feature",
  "properties": {
    "iso:country":"US",
    "sg:address":"887 W Chestnut St",
    "sg:city":"Union",
    "sg:classifiers":[
        {
            "category":"Professional",
            "subcategory":"Computer Services",
            "type":"Services"
        }
    ],
    "sg:phone":"+1 908 688 3171",
    "sg:postcode":"07083",
    "sg:province":"NJ",
    "sg:tags":[
        "related"
    ],
    "wof:name":"Wys Group Inc",
    "wof:placetype":"venue"
},
  "geometry": {"coordinates":[-74.27412200000001,40.692469],"type":"Point"}
}