{
  "type": "Feature",
  "properties": {
    "iso:country":"US",
    "sg:address":"3600 N West Blvd",
    "sg:city":"Vineland",
    "sg:classifiers":[
        {
            "category":"Food & Beverages",
            "subcategory":"Groceries & Convenience Stores",
            "type":"Retail Goods"
        },
        {
            "category":"Food & Beverages",
            "subcategory":"Meat & Fish",
            "type":"Retail Goods"
        }
    ],
    "sg:phone":"+1 856 696 5777",
    "sg:postcode":"08360",
    "sg:province":"NJ",
    "wof:name":"Jamar Food Market Inc",
    "wof:placetype":"venue"
},
  "geometry": {"coordinates":[-75.022448,39.534997],"type":"Point"}
}