{
  "type": "Feature",
  "properties": {
    "addr:full":"17 Wendell Pl Fairview NJ 07022",
    "addr:housenumber":"17",
    "addr:postcode":"07022",
    "addr:street":"Wendell Pl",
    "iso:country":"US",
    "sg:address":"17 Wendell Pl",
    "sg:city":"Fairview",
    "sg:classifiers":[
        {
            "category":"Shopping",
            "subcategory":"Crafts & Fabrics",
            "type":"Retail Goods"
        }
    ],
    "sg:phone":"+1   ",
    "sg:postcode":"07022",
    "sg:province":"NJ",
    "sg:tags":[
        "sewing"
    ],
    "wof:name":"Capitan Embroidery Inc",
    "wof:placetype":"venue"
},
  "geometry": {"coordinates":[-74.001965,40.813149],"type":"Point"}
}