{
  "type": "Feature",
  "properties": {
    "addr:full":"98 Rte 10 W East Hanover NJ 07936",
    "addr:housenumber":"98",
    "addr:postcode":"07936",
    "addr:street":"Rte 10 W",
    "iso:country":"US",
    "sg:address":"98 Rte 10 W",
    "sg:city":"East Hanover",
    "sg:classifiers":[
        {
            "category":"Shopping",
            "type":"Retail Goods"
        }
    ],
    "sg:phone":"+1 973 503 1411",
    "sg:postcode":"07936",
    "sg:province":"NJ",
    "sg:website":"www.babiesrus.com",
    "wof:name":"Babies R Us",
    "wof:placetype":"venue"
},
  "geometry": {"coordinates":[-74.00881800000001,40.704886],"type":"Point"}
}