{
  "type": "Feature",
  "properties": {
    "addr:full":"3349 State Rte 138 Wall Township NJ 07719",
    "addr:housenumber":"3349",
    "addr:postcode":"07719",
    "addr:street":"State Rte 138 Wall",
    "iso:country":"US",
    "sg:address":"3349 State Rte 138",
    "sg:city":"Wall Township",
    "sg:classifiers":[
        {
            "category":"Real Estate",
            "subcategory":"Real Estate Services",
            "type":"Services"
        }
    ],
    "sg:phone":"+1 732 681 6006",
    "sg:postcode":"07719",
    "sg:province":"NJ",
    "sg:tags":[
        "company",
        "title"
    ],
    "wof:name":"Anchor Title Agency",
    "wof:placetype":"venue"
},
  "geometry": {"coordinates":[-74.092983,40.170653],"type":"Point"}
}