{
  "type": "Feature",
  "properties": {
    "iso:country":"US",
    "sg:address":"3713 US Highway 46",
    "sg:city":"Parsippany",
    "sg:classifiers":[
        {
            "category":"Autos & Motor Vehicles",
            "subcategory":"Motorcycle Sales",
            "type":"Retail Goods"
        }
    ],
    "sg:phone":"+1 973 402 5774",
    "sg:postcode":"07054",
    "sg:province":"NJ",
    "wof:name":"Alternative Custom Cycles",
    "wof:placetype":"venue"
},
  "geometry": {"coordinates":[-74.444199,40.877399],"type":"Point"}
}