{
  "type": "Feature",
  "properties": {
    "addr:full":"1205 Noreen Dr Burlington NJ 08016",
    "addr:housenumber":"1205",
    "addr:postcode":"08016",
    "addr:street":"Noreen Dr",
    "iso:country":"US",
    "sg:address":"1205 Noreen Dr",
    "sg:city":"Burlington",
    "sg:classifiers":[
        {
            "category":"Organizations",
            "subcategory":"Religious Organization",
            "type":"Services"
        }
    ],
    "sg:phone":"+1 609 239 1990",
    "sg:postcode":"08016",
    "sg:province":"NJ",
    "wof:name":"One Life Ministries",
    "wof:placetype":"venue"
},
  "geometry": {"coordinates":[-74.86774699999999,40.06125],"type":"Point"}
}