{
  "type": "Feature",
  "properties": {
    "iso:country":"US",
    "sg:address":"317 Bellevue Ave",
    "sg:city":"Trenton",
    "sg:classifiers":[
        {
            "category":"Professional",
            "subcategory":"Accounting & Tax Preparation",
            "type":"Services"
        }
    ],
    "sg:phone":"+1 609 561 1661",
    "sg:postcode":"08618",
    "sg:province":"NJ",
    "wof:name":"Malesich Richard & Assoc LLC",
    "wof:placetype":"venue"
},
  "geometry": {"coordinates":[-74.77565,40.228486],"type":"Point"}
}