{
  "type": "Feature",
  "properties": {
    "iso:country":"US",
    "sg:address":"1140 Lakeshore Dr",
    "sg:city":"Camden",
    "sg:classifiers":[
        {
            "category":"Communications",
            "subcategory":"Radio Station",
            "type":"Services"
        }
    ],
    "sg:phone":"+1 856 966 0675",
    "sg:postcode":"08104",
    "sg:province":"NJ",
    "sg:tags":[
        "broadcast"
    ],
    "wof:name":"Stylesetter Recording Company",
    "wof:placetype":"venue"
},
  "geometry": {"coordinates":[-75.105608,39.912041],"type":"Point"}
}