{
  "type": "Feature",
  "properties": {
    "iso:country":"US",
    "sg:address":"75 Martin St",
    "sg:city":"Bloomfield",
    "sg:classifiers":[
        {
            "category":"Local Transit",
            "type":"Transportation"
        }
    ],
    "sg:phone":"+1 973 743 8235",
    "sg:postcode":"07003",
    "sg:province":"NJ",
    "sg:tags":[
        "passenger"
    ],
    "wof:name":"E-Z Way Limo",
    "wof:placetype":"venue"
},
  "geometry": {"coordinates":[-74.184309,40.812533],"type":"Point"}
}