{
  "type": "Feature",
  "properties": {
    "iso:country":"US",
    "sg:address":"400 3rd St",
    "sg:city":"Lakewood",
    "sg:classifiers":[
        {
            "category":"Professional",
            "subcategory":"Business Services",
            "type":"Services"
        }
    ],
    "sg:phone":"+1 732 901 9156",
    "sg:postcode":"08701",
    "sg:province":"NJ",
    "wof:name":"Nefesh Hachaim Inc",
    "wof:placetype":"venue"
},
  "geometry": {"coordinates":[-74.216897,40.092893],"type":"Point"}
}