{
  "type": "Feature",
  "properties": {
    "addr:full":"807 Britton Pl Voorhees NJ 08043",
    "addr:housenumber":"807",
    "addr:postcode":"08043",
    "addr:street":"Britton Pl",
    "iso:country":"US",
    "sg:address":"807 Britton Pl",
    "sg:city":"Voorhees",
    "sg:classifiers":[
        {
            "category":"Wholesale",
            "subcategory":"Stationery",
            "type":"Manufacturing & Wholesale Goods"
        }
    ],
    "sg:phone":"+1 856 772 1396",
    "sg:postcode":"08043",
    "sg:province":"NJ",
    "sg:tags":[
        "packaging",
        "material"
    ],
    "wof:name":"Package America",
    "wof:placetype":"venue"
},
  "geometry": {"coordinates":[-75.00308699999999,39.846355],"type":"Point"}
}