{
  "type": "Feature",
  "properties": {
    "addr:full":"61 Buckingham Dr Lakewood NJ 08701",
    "addr:housenumber":"61",
    "addr:postcode":"08701",
    "addr:street":"Buckingham Dr",
    "iso:country":"US",
    "sg:address":"61 Buckingham Dr",
    "sg:city":"Lakewood",
    "sg:classifiers":[
        {
            "category":"Home & Garden",
            "subcategory":"Furniture",
            "type":"Retail Goods"
        }
    ],
    "sg:phone":"+1 908 696 0082",
    "sg:postcode":"08701",
    "sg:province":"NJ",
    "sg:tags":[
        "equipment",
        "kitchen",
        "cabinet"
    ],
    "wof:name":"Du Craft Kitchen & Bath Design",
    "wof:placetype":"venue"
},
  "geometry": {"coordinates":[-74.177898,40.051038],"type":"Point"}
}