{
  "type": "Feature",
  "properties": {
    "iso:country":"US",
    "sg:address":"115 N Gladstone Ave",
    "sg:city":"Margate City",
    "sg:classifiers":[
        {
            "category":"Health Services",
            "subcategory":"Doctor",
            "type":"Services"
        }
    ],
    "sg:phone":"+1 609 822 2339",
    "sg:postcode":"08402",
    "sg:province":"NJ",
    "sg:tags":[
        "physician",
        "surgeon"
    ],
    "wof:name":"Jos M Kane MD",
    "wof:placetype":"venue"
},
  "geometry": {"coordinates":[-74.502032,39.332683],"type":"Point"}
}