{
  "type": "Feature",
  "properties": {
    "addr:full":"1275 Main Ave Clifton NJ 07011",
    "addr:housenumber":"1275",
    "addr:postcode":"07011",
    "addr:street":"Main Ave",
    "iso:country":"US",
    "sg:address":"1275 Main Ave",
    "sg:city":"Clifton",
    "sg:classifiers":[
        {
            "category":"Shopping",
            "subcategory":"Hobbies, Toys, & Games",
            "type":"Retail Goods"
        }
    ],
    "sg:phone":"+1 973 772 7990",
    "sg:postcode":"07011",
    "sg:province":"NJ",
    "sg:tags":[
        "model",
        "supply"
    ],
    "wof:name":"Cunningham Motorsports Inc",
    "wof:placetype":"venue"
},
  "geometry": {"coordinates":[-74.141711,40.8774],"type":"Point"}
}