{
  "type": "Feature",
  "properties": {
    "iso:country":"US",
    "sg:address":"139 Rosa Parks Blvd",
    "sg:city":"Paterson",
    "sg:classifiers":[
        {
            "category":"Communications",
            "subcategory":"Film & Video Production",
            "type":"Services"
        }
    ],
    "sg:phone":"+1 973 523 9445",
    "sg:postcode":"07501",
    "sg:province":"NJ",
    "sg:tags":[
        "motion"
    ],
    "wof:name":"Nappi Boy Productions Liab",
    "wof:placetype":"venue"
},
  "geometry": {"coordinates":[-74.158862,40.923362],"type":"Point"}
}