{
  "type": "Feature",
  "properties": {
    "iso:country":"US",
    "sg:address":"12 Mount Laurel Rd",
    "sg:city":"Mt Laurel",
    "sg:classifiers":[
        {
            "category":"Building & Trades",
            "subcategory":"Plumbing",
            "type":"Services"
        }
    ],
    "sg:phone":"+1 856 914 0015",
    "sg:postcode":"08054",
    "sg:province":"NJ",
    "sg:tags":[
        "plumbing",
        "contractor"
    ],
    "wof:name":"Excel Plumbing & Heating",
    "wof:placetype":"venue"
},
  "geometry": {"coordinates":[-74.928775,39.959728],"type":"Point"}
}