{
  "type": "Feature",
  "properties": {
    "iso:country":"US",
    "sg:address":"5 Regent St Ste 508",
    "sg:city":"Livingston",
    "sg:classifiers":[
        {
            "category":"Professional",
            "subcategory":"Lawyer & Legal Services",
            "type":"Services"
        }
    ],
    "sg:phone":"+1 973 535 8840",
    "sg:postcode":"07039",
    "sg:province":"NJ",
    "wof:name":"Kurshan Peter Attorney",
    "wof:placetype":"venue"
},
  "geometry": {"coordinates":[-74.353996,40.798401],"type":"Point"}
}