{
  "type": "Feature",
  "properties": {
    "iso:country":"US",
    "sg:address":"1758 State Rte 35",
    "sg:city":"Seaside Heights",
    "sg:classifiers":[
        {
            "category":"Restaurant",
            "type":"Food & Drink"
        }
    ],
    "sg:phone":"+1 732 830 3733",
    "sg:postcode":"08751",
    "sg:province":"NJ",
    "sg:tags":[
        "parlor",
        "ice",
        "cream"
    ],
    "wof:name":"Lickity Split",
    "wof:placetype":"venue"
},
  "geometry": {"coordinates":[-74.07346200000001,39.952455],"type":"Point"}
}