{
  "type": "Feature",
  "properties": {
    "iso:country":"US",
    "sg:address":"16 Grove Ave",
    "sg:city":"Verona",
    "sg:classifiers":[
        {
            "category":"Real Estate",
            "subcategory":"Real Estate Agent",
            "type":"Services"
        }
    ],
    "sg:phone":"+1   ",
    "sg:postcode":"07044",
    "sg:province":"NJ",
    "wof:name":"Ultimate Real Estate Firm",
    "wof:placetype":"venue"
},
  "geometry": {"coordinates":[-74.247711,40.834249],"type":"Point"}
}