{
  "type": "Feature",
  "properties": {
    "iso:country":"US",
    "sg:address":"66 E Main St",
    "sg:city":"Moorestown",
    "sg:classifiers":[
        {
            "category":"Professional",
            "subcategory":"Accounting & Tax Preparation",
            "type":"Services"
        }
    ],
    "sg:phone":"+1 856 273 8855",
    "sg:postcode":"08057",
    "sg:province":"NJ",
    "sg:tags":[
        "accountant"
    ],
    "wof:name":"Boscarelli & Zaiss PC",
    "wof:placetype":"venue"
},
  "geometry": {"coordinates":[-74.94541599999999,39.964301],"type":"Point"}
}