{
  "type": "Feature",
  "properties": {
    "addr:full":"75 Garrison Rd Elmer NJ 08318",
    "addr:housenumber":"75",
    "addr:postcode":"08318",
    "addr:street":"Garrison Rd",
    "iso:country":"US",
    "sg:address":"75 Garrison Rd",
    "sg:city":"Elmer",
    "sg:classifiers":[
        {
            "category":"Freight",
            "type":"Transportation"
        }
    ],
    "sg:phone":"+1 856 358 2827",
    "sg:postcode":"08318",
    "sg:province":"NJ",
    "sg:tags":[
        "local",
        "without",
        "storage",
        "hauling"
    ],
    "wof:name":"C Harrell Inc",
    "wof:placetype":"venue"
},
  "geometry": {"coordinates":[-75.18416000000001,39.594624],"type":"Point"}
}