{
  "type": "Feature",
  "properties": {
    "addr:full":"738 N Broad St Woodbury NJ 08096",
    "addr:housenumber":"738",
    "addr:postcode":"08096",
    "addr:street":"N Broad St",
    "iso:country":"US",
    "sg:address":"738 N Broad St",
    "sg:city":"Woodbury",
    "sg:classifiers":[
        {
            "category":"Retail",
            "subcategory":"Car Wash",
            "type":"Services"
        }
    ],
    "sg:phone":"+1 856 845 8874",
    "sg:postcode":"08096",
    "sg:province":"NJ",
    "sg:tags":[
        "carwash"
    ],
    "wof:name":"Town & Country Auto Bath",
    "wof:placetype":"venue"
},
  "geometry": {"coordinates":[-75.146298,39.846521],"type":"Point"}
}