{
  "type": "Feature",
  "properties": {
    "iso:country":"US",
    "sg:address":"1019 E Landis Ave",
    "sg:city":"Vineland",
    "sg:classifiers":[
        {
            "category":"Restaurant",
            "type":"Food & Drink"
        }
    ],
    "sg:phone":"+1   ",
    "sg:postcode":"08360",
    "sg:province":"NJ",
    "sg:tags":[
        "eating"
    ],
    "wof:name":"Cousin Steaks & Hoagies",
    "wof:placetype":"venue"
},
  "geometry": {"coordinates":[-75.014561,39.485584],"type":"Point"}
}