{
  "type": "Feature",
  "properties": {
    "iso:country":"US",
    "sg:address":"125 Fairview Ave",
    "sg:city":"Cedar Grove",
    "sg:classifiers":[
        {
            "category":"Health Services",
            "subcategory":"Hospital",
            "type":"Services"
        }
    ],
    "sg:phone":"+1 973 228 8000",
    "sg:postcode":"07009",
    "sg:province":"NJ",
    "wof:name":"Essex County Hospital",
    "wof:placetype":"venue"
},
  "geometry": {"coordinates":[-74.24247099999999,40.853905],"type":"Point"}
}