{
  "type": "Feature",
  "properties": {
    "addr:full":"83 Brink Rd Sussex NJ 07461",
    "addr:housenumber":"83",
    "addr:postcode":"07461",
    "addr:street":"Brink Rd",
    "iso:country":"US",
    "sg:address":"83 Brink Rd",
    "sg:city":"Sussex",
    "sg:classifiers":[
        {
            "category":"Building & Trades",
            "subcategory":"Electrical",
            "type":"Services"
        }
    ],
    "sg:phone":"+1 973 702 1401",
    "sg:postcode":"07461",
    "sg:province":"NJ",
    "sg:tags":[
        "electric",
        "contractor"
    ],
    "wof:name":"A Plus Electric Co Inc",
    "wof:placetype":"venue"
},
  "geometry": {"coordinates":[-74.67004799999999,41.262478],"type":"Point"}
}