{
  "type": "Feature",
  "properties": {
    "iso:country":"US",
    "sg:address":"118 N Montgomery St",
    "sg:city":"Trenton",
    "sg:classifiers":[
        {
            "category":"Organizations",
            "subcategory":"Religious Organization",
            "type":"Services"
        }
    ],
    "sg:phone":"+1 609 989 1229",
    "sg:postcode":"08608",
    "sg:province":"NJ",
    "sg:tags":[
        "place",
        "worship",
        "church"
    ],
    "wof:name":"Elyon Bible Church",
    "wof:placetype":"venue"
},
  "geometry": {"coordinates":[-74.762187,40.221702],"type":"Point"}
}