{
  "type": "Feature",
  "properties": {
    "iso:country":"US",
    "sg:address":"5 Ski Dr",
    "sg:city":"Hillsborough",
    "sg:classifiers":[
        {
            "category":"Real Estate",
            "subcategory":"Real Estate Agent",
            "type":"Services"
        }
    ],
    "sg:phone":"+1   ",
    "sg:postcode":"08844",
    "sg:province":"NJ",
    "wof:name":"Arland Appraisal",
    "wof:placetype":"venue"
},
  "geometry": {"coordinates":[-74.69801200000001,40.495966],"type":"Point"}
}