{
  "type": "Feature",
  "properties": {
    "iso:country":"US",
    "sg:address":"116 Broad St",
    "sg:city":"Red Bank",
    "sg:classifiers":[
        {
            "category":"Shopping",
            "type":"Retail Goods"
        }
    ],
    "sg:phone":"+1 732 933 4191",
    "sg:postcode":"07701",
    "sg:province":"NJ",
    "sg:tags":[
        "telephone",
        "cellular"
    ],
    "wof:name":"Unlimited Communications",
    "wof:placetype":"venue"
},
  "geometry": {"coordinates":[-74.065133,40.348838],"type":"Point"}
}