{
  "type": "Feature",
  "properties": {
    "iso:country":"US",
    "sg:address":"70 Sam Bonnell Dr",
    "sg:city":"Clinton",
    "sg:classifiers":[
        {
            "category":"Utilities",
            "subcategory":"Electric",
            "type":"Services"
        }
    ],
    "sg:phone":"+1 908 735 0083",
    "sg:postcode":"08809",
    "sg:province":"NJ",
    "sg:tags":[
        "company"
    ],
    "wof:name":"Energy Companies",
    "wof:placetype":"venue"
},
  "geometry": {"coordinates":[-74.935878,40.634322],"type":"Point"}
}