{
  "type": "Feature",
  "properties": {
    "addr:full":"75 E Madison Ave Dumont NJ 07628",
    "addr:housenumber":"75",
    "addr:postcode":"07628",
    "addr:street":"E Madison Ave",
    "iso:country":"US",
    "sg:address":"75 E Madison Ave",
    "sg:city":"Dumont",
    "sg:classifiers":[
        {
            "category":"Real Estate",
            "subcategory":"Real Estate Agent",
            "type":"Services"
        }
    ],
    "sg:phone":"+1 201 387 7653",
    "sg:postcode":"07628",
    "sg:province":"NJ",
    "wof:name":"Integrity",
    "wof:placetype":"venue"
},
  "geometry": {"coordinates":[-73.991407,40.940461],"type":"Point"}
}