{
  "type": "Feature",
  "properties": {
    "addr:full":"111 Main St Newark NJ 07105",
    "addr:housenumber":"111",
    "addr:postcode":"07105",
    "addr:street":"Main St",
    "iso:country":"US",
    "sg:address":"111 Main St",
    "sg:city":"Newark",
    "sg:classifiers":[
        {
            "category":"Wholesale",
            "subcategory":"Construction Materials",
            "type":"Manufacturing & Wholesale Goods"
        }
    ],
    "sg:phone":"+1 973 491 0160",
    "sg:postcode":"07105",
    "sg:province":"NJ",
    "sg:tags":[
        "stucco"
    ],
    "wof:name":"Mediterranean Stucco Supply Co",
    "wof:placetype":"venue"
},
  "geometry": {"coordinates":[-74.145343,40.725643],"type":"Point"}
}