{
  "type": "Feature",
  "properties": {
    "iso:country":"US",
    "sg:address":"190 Rock Rd",
    "sg:city":"Glen Rock",
    "sg:classifiers":[
        {
            "category":"Education",
            "subcategory":"School",
            "type":"Public Place"
        },
        {
            "category":"Education",
            "subcategory":"Special Training",
            "type":"Public Place"
        }
    ],
    "sg:phone":"+1 201 444 6530",
    "sg:postcode":"07452",
    "sg:province":"NJ",
    "sg:tags":[
        "academic",
        "educational",
        "gifted",
        "for",
        "child"
    ],
    "wof:name":"Gifted Child Society Inc",
    "wof:placetype":"venue"
},
  "geometry": {"coordinates":[-74.13158199999999,40.962487],"type":"Point"}
}