{
  "type": "Feature",
  "properties": {
    "addr:full":"101 Plaza Rd Oakland NJ 07436",
    "addr:housenumber":"101",
    "addr:postcode":"07436",
    "addr:street":"Plaza Rd",
    "iso:country":"US",
    "sg:address":"101 Plaza Rd",
    "sg:city":"Oakland",
    "sg:classifiers":[
        {
            "category":"Restaurant",
            "type":"Food & Drink"
        }
    ],
    "sg:menulink":"http://www.allmenus.com/nj/oakland/191336-burger-king/menu/",
    "sg:phone":"+1 201 337 9713",
    "sg:postcode":"07436",
    "sg:province":"NJ",
    "sg:tags":[
        "burger",
        "american"
    ],
    "wof:name":"Burger King",
    "wof:placetype":"venue"
},
  "geometry": {"coordinates":[-74.255132,41.014225],"type":"Point"}
}