{
  "type": "Feature",
  "properties": {
    "addr:full":"299 Jackson Rd Waterford Works NJ 08089",
    "addr:housenumber":"299",
    "addr:postcode":"08089",
    "addr:street":"Jackson Rd",
    "iso:country":"US",
    "sg:address":"299 Jackson Rd",
    "sg:city":"Waterford Works",
    "sg:classifiers":[
        {
            "category":"Sports & Exercise",
            "subcategory":"Gym",
            "type":"Entertainment"
        }
    ],
    "sg:phone":"+1 856 753 8100",
    "sg:postcode":"08089",
    "sg:province":"NJ",
    "wof:name":"Curves For Women",
    "wof:placetype":"venue"
},
  "geometry": {"coordinates":[-74.857803,39.7257],"type":"Point"}
}