{
  "type": "Feature",
  "properties": {
    "iso:country":"US",
    "sg:address":"46 Trudy Dr",
    "sg:city":"Lodi",
    "sg:classifiers":[
        {
            "category":"Building & Trades",
            "subcategory":"Cleaning & Sanitation",
            "type":"Services"
        }
    ],
    "sg:phone":"+1 201 368 9049",
    "sg:postcode":"07644",
    "sg:province":"NJ",
    "sg:tags":[
        "janitor"
    ],
    "wof:name":"S G T's Maintenance",
    "wof:placetype":"venue"
},
  "geometry": {"coordinates":[-74.076245,40.88792],"type":"Point"}
}