{
  "type": "Feature",
  "properties": {
    "addr:full":"8 High St Mullica Hill NJ 08062",
    "addr:housenumber":"8",
    "addr:postcode":"08062",
    "addr:street":"High St",
    "iso:country":"US",
    "sg:address":"8 High St",
    "sg:city":"Mullica Hill",
    "sg:classifiers":[
        {
            "category":"Health Services",
            "subcategory":"Doctor",
            "type":"Services"
        }
    ],
    "sg:phone":"+1 856 223 8660",
    "sg:postcode":"08062",
    "sg:province":"NJ",
    "sg:tags":[
        "physician",
        "surgeon"
    ],
    "wof:name":"Pitman Internal Medicine Assoc",
    "wof:placetype":"venue"
},
  "geometry": {"coordinates":[-75.225545,39.732277],"type":"Point"}
}