{
  "type": "Feature",
  "properties": {
    "addr:full":"1207 River Ave Lakewood NJ 08701",
    "addr:housenumber":"1207",
    "addr:postcode":"08701",
    "addr:street":"River Ave",
    "iso:country":"US",
    "sg:address":"1207 River Ave",
    "sg:city":"Lakewood",
    "sg:classifiers":[
        {
            "category":"Personal",
            "subcategory":"Beauty Salon",
            "type":"Services"
        }
    ],
    "sg:phone":"+1 732 942 0080",
    "sg:postcode":"08701",
    "sg:province":"NJ",
    "sg:tags":[
        "shop"
    ],
    "wof:name":"Lemothsho Essence Beauty Salon",
    "wof:placetype":"venue"
},
  "geometry": {"coordinates":[-74.220544,40.054712],"type":"Point"}
}