{
  "type": "Feature",
  "properties": {
    "addr:full":"278 Monmouth St Jersey City NJ 07302",
    "addr:housenumber":"278",
    "addr:postcode":"07302",
    "addr:street":"Monmouth St",
    "iso:country":"US",
    "sg:address":"278 Monmouth St",
    "sg:city":"Jersey City",
    "sg:classifiers":[
        {
            "category":"Autos & Motor Vehicles",
            "subcategory":"Automobile Sales",
            "type":"Retail Goods"
        }
    ],
    "sg:phone":"+1 201 435 3873",
    "sg:postcode":"07302",
    "sg:province":"NJ",
    "sg:tags":[
        "limo"
    ],
    "wof:name":"All County Transportation Inc",
    "wof:placetype":"venue"
},
  "geometry": {"coordinates":[-74.051598,40.718102],"type":"Point"}
}