{
  "type": "Feature",
  "properties": {
    "addr:full":"238 Autumn Rd Lakewood NJ 08701",
    "addr:housenumber":"238",
    "addr:postcode":"08701",
    "addr:street":"Autumn Rd",
    "iso:country":"US",
    "sg:address":"238 Autumn Rd",
    "sg:city":"Lakewood",
    "sg:classifiers":[
        {
            "category":"Professional",
            "subcategory":"Computer Services",
            "type":"Services"
        }
    ],
    "sg:phone":"+1 732 370 8822",
    "sg:postcode":"08701",
    "sg:province":"NJ",
    "sg:tags":[
        "repair"
    ],
    "wof:name":"Anything & Everything Computer",
    "wof:placetype":"venue"
},
  "geometry": {"coordinates":[-74.23287999999999,40.100271],"type":"Point"}
}