{
  "type": "Feature",
  "properties": {
    "addr:full":"210 Central Ave East Newark NJ 07029",
    "addr:housenumber":"210",
    "addr:postcode":"07029",
    "addr:street":"Central Ave",
    "iso:country":"US",
    "sg:address":"210 Central Ave",
    "sg:city":"East Newark",
    "sg:classifiers":[
        {
            "category":"Restaurant",
            "type":"Food & Drink"
        }
    ],
    "sg:phone":"+1 973 481 7788",
    "sg:postcode":"07029",
    "sg:province":"NJ",
    "wof:name":"Rincon Hispano Restaurant",
    "wof:placetype":"venue"
},
  "geometry": {"coordinates":[-74.158776,40.750066],"type":"Point"}
}