{
  "type": "Feature",
  "properties": {
    "addr:full":"298 Butler Blvd Bayville NJ 08721",
    "addr:housenumber":"298",
    "addr:postcode":"08721",
    "addr:street":"Butler Blvd",
    "iso:country":"US",
    "sg:address":"298 Butler Blvd",
    "sg:city":"Bayville",
    "sg:classifiers":[
        {
            "category":"Recreation",
            "subcategory":"Marina",
            "type":"Entertainment"
        },
        {
            "category":"Shopping",
            "subcategory":"Bicycles & Sporting Goods",
            "type":"Retail Goods"
        }
    ],
    "sg:phone":"+1 732 269 1186",
    "sg:postcode":"08721",
    "sg:province":"NJ",
    "sg:tags":[
        "repairing",
        "boat"
    ],
    "wof:name":"Whitey's Landing",
    "wof:placetype":"venue"
},
  "geometry": {"coordinates":[-74.141679,39.887618],"type":"Point"}
}