{
  "type": "Feature",
  "properties": {
    "iso:country":"US",
    "sg:address":"1234 Windrow Dr",
    "sg:city":"Hightstown",
    "sg:classifiers":[
        {
            "category":"Manufacturing",
            "subcategory":"Tools & Machinery",
            "type":"Manufacturing & Wholesale Goods"
        }
    ],
    "sg:phone":"+1 609 443 5817",
    "sg:postcode":"08540",
    "sg:province":"NJ",
    "sg:tags":[
        "farm",
        "mfg"
    ],
    "wof:name":"Rustin Farms",
    "wof:placetype":"venue"
},
  "geometry": {"coordinates":[-74.624669,40.383618],"type":"Point"}
}