{
  "type": "Feature",
  "properties": {
    "addr:full":"186 Rochelle Ave Rochelle Park NJ 07662",
    "addr:housenumber":"186",
    "addr:postcode":"07662",
    "addr:street":"Rochelle Ave",
    "iso:country":"US",
    "sg:address":"186 Rochelle Ave",
    "sg:city":"Rochelle Park",
    "sg:classifiers":[
        {
            "category":"Health Services",
            "subcategory":"Hospital",
            "type":"Services"
        }
    ],
    "sg:phone":"+1 201 843 9711",
    "sg:postcode":"07662",
    "sg:province":"NJ",
    "wof:name":"Woo Judy MD",
    "wof:placetype":"venue"
},
  "geometry": {"coordinates":[-74.078103,40.902179],"type":"Point"}
}