{
  "type": "Feature",
  "properties": {
    "addr:full":"1715 State Rte 35 Middletown NJ 07748",
    "addr:housenumber":"1715",
    "addr:postcode":"07748",
    "addr:street":"State Rte 35",
    "iso:country":"US",
    "sg:address":"1715 State Rte 35",
    "sg:city":"Middletown",
    "sg:classifiers":[
        {
            "category":"Government",
            "subcategory":"Office",
            "type":"Public Place"
        }
    ],
    "sg:phone":"+1 732 671 6488",
    "sg:postcode":"07748",
    "sg:province":"NJ",
    "wof:name":"Battleship New Jersey Fndtn",
    "wof:placetype":"venue"
},
  "geometry": {"coordinates":[-74.12947,40.407154],"type":"Point"}
}