{
  "type": "Feature",
  "properties": {
    "iso:country":"US",
    "sg:address":"561 N Evergreen Ave",
    "sg:city":"Woodbury",
    "sg:classifiers":[
        {
            "category":"Shopping",
            "subcategory":"Books",
            "type":"Retail Goods"
        }
    ],
    "sg:phone":"+1   ",
    "sg:postcode":"08096",
    "sg:province":"NJ",
    "sg:tags":[
        "bookstore",
        "christian",
        "family"
    ],
    "wof:name":"Joshua Tree Christian Shoppe",
    "wof:placetype":"venue"
},
  "geometry": {"coordinates":[-75.144368,39.841508],"type":"Point"}
}