{
  "type": "Feature",
  "properties": {
    "iso:country":"US",
    "sg:address":"7611 Park Ave",
    "sg:city":"North Bergen",
    "sg:classifiers":[
        {
            "category":"Shopping",
            "subcategory":"Luggage & Leather Goods",
            "type":"Retail Goods"
        }
    ],
    "sg:phone":"+1   ",
    "sg:postcode":"07047",
    "sg:province":"NJ",
    "wof:name":"Atocha Leathergoods",
    "wof:placetype":"venue"
},
  "geometry": {"coordinates":[-74.000328,40.796754],"type":"Point"}
}