{
  "type": "Feature",
  "properties": {
    "iso:country":"US",
    "sg:address":"650 9th St",
    "sg:city":"Lakewood",
    "sg:classifiers":[
        {
            "category":"Real Estate",
            "subcategory":"Real Estate Agent",
            "type":"Services"
        }
    ],
    "sg:phone":"+1   ",
    "sg:postcode":"08701",
    "sg:province":"NJ",
    "wof:name":"Pinetree Apts LLC",
    "wof:placetype":"venue"
},
  "geometry": {"coordinates":[-74.22349800000001,40.098014],"type":"Point"}
}