{
  "type": "Feature",
  "properties": {
    "iso:country":"US",
    "sg:address":"73 Lambert Pl",
    "sg:city":"Paramus",
    "sg:classifiers":[
        {
            "category":"Building & Trades",
            "subcategory":"Landscaping Services",
            "type":"Services"
        }
    ],
    "sg:phone":"+1 201 670 6059",
    "sg:postcode":"07652",
    "sg:province":"NJ",
    "sg:tags":[
        "landscape"
    ],
    "wof:name":"Turf Tech Landscaping",
    "wof:placetype":"venue"
},
  "geometry": {"coordinates":[-74.073988,40.976202],"type":"Point"}
}