{
  "type": "Feature",
  "properties": {
    "addr:full":"1165 Broad St Newark NJ 07114",
    "addr:housenumber":"1165",
    "addr:postcode":"07114",
    "addr:street":"Broad St",
    "iso:country":"US",
    "sg:address":"1165 Broad St",
    "sg:city":"Newark",
    "sg:classifiers":[
        {
            "category":"Retail",
            "subcategory":"Laundry & Dry Cleaning",
            "type":"Services"
        }
    ],
    "sg:phone":"+1 973 824 7406",
    "sg:postcode":"07114",
    "sg:province":"NJ",
    "wof:name":"Adco's Wash & Dry",
    "wof:placetype":"venue"
},
  "geometry": {"coordinates":[-74.18049000000001,40.72167],"type":"Point"}
}