{
  "type": "Feature",
  "properties": {
    "iso:country":"US",
    "sg:address":"6957 Miller Ave",
    "sg:city":"Port Norris",
    "sg:classifiers":[
        {
            "category":"Wholesale",
            "subcategory":"Seafood",
            "type":"Manufacturing & Wholesale Goods"
        }
    ],
    "sg:phone":"+1 856 785 0270",
    "sg:postcode":"08349",
    "sg:province":"NJ",
    "wof:name":"Bivalve Packing Co",
    "wof:placetype":"venue"
},
  "geometry": {"coordinates":[-75.028015,39.237167],"type":"Point"}
}