{
  "type": "Feature",
  "properties": {
    "addr:full":"51 Chestnut St New Providence NJ 07974",
    "addr:housenumber":"51",
    "addr:postcode":"07974",
    "addr:street":"Chestnut St",
    "iso:country":"US",
    "sg:address":"51 Chestnut St",
    "sg:city":"New Providence",
    "sg:classifiers":[
        {
            "category":"Building & Trades",
            "subcategory":"Construction",
            "type":"Services"
        }
    ],
    "sg:phone":"+1 908 464 3826",
    "sg:postcode":"07974",
    "sg:province":"NJ",
    "sg:tags":[
        "carpentry",
        "contractor"
    ],
    "wof:name":"Oak Mountain Carpentry",
    "wof:placetype":"venue"
},
  "geometry": {"coordinates":[-74.391381,40.695576],"type":"Point"}
}