{
  "type": "Feature",
  "properties": {
    "addr:full":"56 Wilkshire Blvd Randolph NJ 07869",
    "addr:housenumber":"56",
    "addr:postcode":"07869",
    "addr:street":"Wilkshire Blvd",
    "iso:country":"US",
    "sg:address":"56 Wilkshire Blvd",
    "sg:city":"Randolph",
    "sg:classifiers":[
        {
            "category":"Professional",
            "type":"Services"
        }
    ],
    "sg:phone":"+1   ",
    "sg:postcode":"07869",
    "sg:province":"NJ",
    "wof:name":"R Alper & Assoc LLC",
    "wof:placetype":"venue"
},
  "geometry": {"coordinates":[-74.590823,40.84865],"type":"Point"}
}