{
  "type": "Feature",
  "properties": {
    "addr:full":"1061 Amboy Ave Edison NJ 08837",
    "addr:housenumber":"1061",
    "addr:postcode":"08837",
    "addr:street":"Amboy Ave",
    "iso:country":"US",
    "sg:address":"1061 Amboy Ave",
    "sg:city":"Edison",
    "sg:classifiers":[
        {
            "category":"Retail",
            "subcategory":"Repair Shop",
            "type":"Services"
        }
    ],
    "sg:phone":"+1   ",
    "sg:postcode":"08837",
    "sg:province":"NJ",
    "wof:name":"0 & 0 24 Hour Locksmith",
    "wof:placetype":"venue"
},
  "geometry": {"coordinates":[-74.340064,40.535528],"type":"Point"}
}