{
  "type": "Feature",
  "properties": {
    "iso:country":"US",
    "sg:address":"605 Ardmore Ave",
    "sg:city":"Pitman",
    "sg:classifiers":[
        {
            "category":"Building & Trades",
            "subcategory":"Construction",
            "type":"Services"
        }
    ],
    "sg:phone":"+1 856 218 1275",
    "sg:postcode":"08071",
    "sg:province":"NJ",
    "sg:tags":[
        "hanging",
        "contractor"
    ],
    "wof:name":"Bpc Painting",
    "wof:placetype":"venue"
},
  "geometry": {"coordinates":[-75.115185,39.737157],"type":"Point"}
}