{
  "type": "Feature",
  "properties": {
    "addr:full":"253 Broadway Newark NJ 07104",
    "addr:housenumber":"253",
    "addr:postcode":"07104",
    "addr:street":"Broadway",
    "iso:country":"US",
    "sg:address":"253 Broadway",
    "sg:city":"Newark",
    "sg:classifiers":[
        {
            "category":"Food & Beverages",
            "subcategory":"Groceries & Convenience Stores",
            "type":"Retail Goods"
        }
    ],
    "sg:phone":"+1 973 483 5494",
    "sg:postcode":"07104",
    "sg:province":"NJ",
    "wof:name":"Small Apple V Grocery",
    "wof:placetype":"venue"
},
  "geometry": {"coordinates":[-74.169296,40.7593],"type":"Point"}
}