{
  "type": "Feature",
  "properties": {
    "addr:full":"377 Hasbrouck Ave Hasbrouck Heights NJ 07604",
    "addr:housenumber":"377",
    "addr:postcode":"07604",
    "addr:street":"Hasbrouck Ave",
    "iso:country":"US",
    "sg:address":"377 Hasbrouck Ave",
    "sg:city":"Hasbrouck Heights",
    "sg:classifiers":[
        {
            "category":"Wholesale",
            "subcategory":"Non-durable Goods",
            "type":"Manufacturing & Wholesale Goods"
        }
    ],
    "sg:phone":"+1 201 288 8450",
    "sg:postcode":"07604",
    "sg:province":"NJ",
    "sg:tags":[
        "machine",
        "mfg"
    ],
    "wof:name":"Card Data Systems",
    "wof:placetype":"venue"
},
  "geometry": {"coordinates":[-74.066953,40.864499],"type":"Point"}
}