{
  "type": "Feature",
  "properties": {
    "iso:country":"US",
    "sg:address":"75 Christie St",
    "sg:city":"Ridgefield Park",
    "sg:classifiers":[
        {
            "category":"Manufacturing",
            "subcategory":"Jewelry",
            "type":"Manufacturing & Wholesale Goods"
        }
    ],
    "sg:phone":"+1 201 440 8133",
    "sg:postcode":"07660",
    "sg:province":"NJ",
    "sg:tags":[
        "precious",
        "metal",
        "mfg"
    ],
    "wof:name":"Joshua Creation",
    "wof:placetype":"venue"
},
  "geometry": {"coordinates":[-74.02499400000001,40.853095],"type":"Point"}
}