{
  "type": "Feature",
  "properties": {
    "iso:country":"US",
    "sg:address":"20 Broadway",
    "sg:city":"Clark",
    "sg:classifiers":[
        {
            "category":"Professional",
            "subcategory":"Secretarial Services",
            "type":"Services"
        }
    ],
    "sg:phone":"+1   ",
    "sg:postcode":"07066",
    "sg:province":"NJ",
    "sg:tags":[
        "reporting"
    ],
    "wof:name":"EMR Medical Transcription",
    "wof:placetype":"venue"
},
  "geometry": {"coordinates":[-74.295322,40.619042],"type":"Point"}
}