{
  "type": "Feature",
  "properties": {
    "addr:full":"89 Ridge Rd North Arlington NJ 07031",
    "addr:housenumber":"89",
    "addr:postcode":"07031",
    "addr:street":"Ridge Rd North",
    "iso:country":"US",
    "sg:address":"89 Ridge Rd",
    "sg:city":"North Arlington",
    "sg:classifiers":[
        {
            "category":"Wholesale",
            "subcategory":"Dairy",
            "type":"Manufacturing & Wholesale Goods"
        }
    ],
    "sg:phone":"+1 201 955 4419",
    "sg:postcode":"07031",
    "sg:province":"NJ",
    "sg:tags":[
        "frozen",
        "dessert",
        "ice",
        "cream"
    ],
    "wof:name":"Flips Dessert Cafe",
    "wof:placetype":"venue"
},
  "geometry": {"coordinates":[-74.13575899999999,40.785184],"type":"Point"}
}