{
  "type": "Feature",
  "properties": {
    "iso:country":"US",
    "sg:address":"189 Texas Rd",
    "sg:city":"Old Bridge",
    "sg:classifiers":[
        {
            "category":"Retail",
            "subcategory":"Auto Repair",
            "type":"Services"
        }
    ],
    "sg:phone":"+1 732 605 0995",
    "sg:postcode":"08857",
    "sg:province":"NJ",
    "sg:tags":[
        "wrecker"
    ],
    "wof:name":"Mendola's Towing",
    "wof:placetype":"venue"
},
  "geometry": {"coordinates":[-74.30460600000001,40.364008],"type":"Point"}
}