{
  "type": "Feature",
  "properties": {
    "iso:country":"US",
    "sg:address":"494 Riverview Dr",
    "sg:city":"Totowa",
    "sg:classifiers":[
        {
            "category":"Building & Trades",
            "subcategory":"Pest Control",
            "type":"Services"
        }
    ],
    "sg:phone":"+1   ",
    "sg:postcode":"07512",
    "sg:province":"NJ",
    "wof:name":"ServiceMaster",
    "wof:placetype":"venue"
},
  "geometry": {"coordinates":[-74.219678,40.891861],"type":"Point"}
}