{
  "type": "Feature",
  "properties": {
    "addr:full":"11 Saddle River Ave Garfield NJ 07026",
    "addr:housenumber":"11",
    "addr:postcode":"07026",
    "addr:street":"Saddle River Ave",
    "iso:country":"US",
    "sg:address":"11 Saddle River Ave",
    "sg:city":"Garfield",
    "sg:classifiers":[
        {
            "category":"Building & Trades",
            "subcategory":"Construction",
            "type":"Services"
        }
    ],
    "sg:phone":"+1 973 614 8100",
    "sg:postcode":"07026",
    "sg:province":"NJ",
    "sg:tags":[
        "contractor"
    ],
    "wof:name":"Built Rite Corp",
    "wof:placetype":"venue"
},
  "geometry": {"coordinates":[-74.101266,40.864184],"type":"Point"}
}