{
  "type": "Feature",
  "properties": {
    "addr:full":"12 Depot Sq Englewood NJ 07631",
    "addr:housenumber":"12",
    "addr:postcode":"07631",
    "addr:street":"Depot Sq",
    "iso:country":"US",
    "sg:address":"12 Depot Sq",
    "sg:city":"Englewood",
    "sg:classifiers":[
        {
            "category":"Personal",
            "subcategory":"Barber",
            "type":"Services"
        }
    ],
    "sg:phone":"+1 201 567 3136",
    "sg:postcode":"07631",
    "sg:province":"NJ",
    "sg:tags":[
        "shop"
    ],
    "wof:name":"Bob's Barber Shop & Stylist",
    "wof:placetype":"venue"
},
  "geometry": {"coordinates":[-73.973874,40.895526],"type":"Point"}
}