{
  "type": "Feature",
  "properties": {
    "addr:full":"1735 Saint Georges Ave Rahway NJ 07065",
    "addr:housenumber":"1735",
    "addr:postcode":"07065",
    "addr:street":"Saint Georges Ave",
    "iso:country":"US",
    "sg:address":"1735 Saint Georges Ave",
    "sg:city":"Rahway",
    "sg:classifiers":[
        {
            "category":"Personal",
            "subcategory":"Beauty Salon",
            "type":"Services"
        }
    ],
    "sg:phone":"+1 732 381 1116",
    "sg:postcode":"07065",
    "sg:province":"NJ",
    "wof:name":"Golden Touch Salon",
    "wof:placetype":"venue"
},
  "geometry": {"coordinates":[-74.283762,40.617434],"type":"Point"}
}