{
  "type": "Feature",
  "properties": {
    "addr:full":"56 Village Center Dr Freehold NJ 07728",
    "addr:housenumber":"56",
    "addr:postcode":"07728",
    "addr:street":"Village Center Dr",
    "iso:country":"US",
    "sg:address":"56 Village Center Dr",
    "sg:city":"Freehold",
    "sg:classifiers":[
        {
            "category":"Shopping",
            "subcategory":"Jewelry",
            "type":"Retail Goods"
        }
    ],
    "sg:phone":"+1   ",
    "sg:postcode":"07728",
    "sg:province":"NJ",
    "sg:tags":[
        "retailer"
    ],
    "wof:name":"Abe Presman Jeweler",
    "wof:placetype":"venue"
},
  "geometry": {"coordinates":[-74.30597899999999,40.239848],"type":"Point"}
}