{
  "type": "Feature",
  "properties": {
    "iso:country":"US",
    "sg:address":"60 Washington St",
    "sg:city":"Clark",
    "sg:classifiers":[
        {
            "category":"Wholesale",
            "subcategory":"Stationery",
            "type":"Manufacturing & Wholesale Goods"
        }
    ],
    "sg:phone":"+1 732 388 9664",
    "sg:postcode":"07066",
    "sg:province":"NJ",
    "sg:tags":[
        "business",
        "form",
        "system"
    ],
    "wof:name":"Nu Plan Business Systems Inc",
    "wof:placetype":"venue"
},
  "geometry": {"coordinates":[-74.297608,40.617796],"type":"Point"}
}