{
  "type": "Feature",
  "properties": {
    "addr:full":"37 Mountain Blvd Warren NJ 07059",
    "addr:housenumber":"37",
    "addr:postcode":"07059",
    "addr:street":"Mountain Blvd",
    "iso:country":"US",
    "sg:address":"37 Mountain Blvd",
    "sg:city":"Warren",
    "sg:classifiers":[
        {
            "category":"Health Services",
            "subcategory":"Medical Lab",
            "type":"Services"
        }
    ],
    "sg:phone":"+1 908 756 5787",
    "sg:postcode":"07059",
    "sg:province":"NJ",
    "sg:tags":[
        "laboratory"
    ],
    "wof:name":"Quest Diagnotics",
    "wof:placetype":"venue"
},
  "geometry": {"coordinates":[-74.488074,40.620003],"type":"Point"}
}