{
  "type": "Feature",
  "properties": {
    "iso:country":"US",
    "sg:address":"9 Rockhill Dr",
    "sg:city":"Hampton",
    "sg:classifiers":[
        {
            "category":"Professional",
            "type":"Services"
        }
    ],
    "sg:phone":"+1   ",
    "sg:postcode":"08827",
    "sg:province":"NJ",
    "wof:name":"Wendy Theurer",
    "wof:placetype":"venue"
},
  "geometry": {"coordinates":[-74.993869,40.688037],"type":"Point"}
}