{
  "type": "Feature",
  "properties": {
    "addr:full":"501 Jamestown Rd Beverly NJ 08010",
    "addr:housenumber":"501",
    "addr:postcode":"08010",
    "addr:street":"Jamestown Rd",
    "iso:country":"US",
    "sg:address":"501 Jamestown Rd",
    "sg:city":"Beverly",
    "sg:classifiers":[
        {
            "category":"Wholesale",
            "subcategory":"Apparel",
            "type":"Manufacturing & Wholesale Goods"
        }
    ],
    "sg:phone":"+1 609 387 1326",
    "sg:postcode":"08010",
    "sg:province":"NJ",
    "sg:tags":[
        "clothing"
    ],
    "wof:name":"M Kay International Inc",
    "wof:placetype":"venue"
},
  "geometry": {"coordinates":[-74.893715,40.060373],"type":"Point"}
}