{
  "type": "Feature",
  "properties": {
    "iso:country":"US",
    "sg:address":"169 Palisade Ave",
    "sg:city":"Garfield",
    "sg:classifiers":[
        {
            "category":"Restaurant",
            "type":"Food & Drink"
        }
    ],
    "sg:phone":"+1 973 340 4800",
    "sg:postcode":"07026",
    "sg:province":"NJ",
    "sg:tags":[
        "delicatessen"
    ],
    "wof:name":"Barry's Olde Tyme Deli",
    "wof:placetype":"venue"
},
  "geometry": {"coordinates":[-74.108588,40.87031],"type":"Point"}
}