{
  "type": "Feature",
  "properties": {
    "iso:country":"US",
    "sg:address":"1285 Martin Luther King Jr Blvd",
    "sg:city":"Trenton",
    "sg:classifiers":[
        {
            "category":"Professional",
            "subcategory":"Business Services",
            "type":"Services"
        }
    ],
    "sg:phone":"+1 609 396 4747",
    "sg:postcode":"08638",
    "sg:province":"NJ",
    "sg:tags":[
        "fire",
        "equipment"
    ],
    "wof:name":"Quick Stop Fire Protection",
    "wof:placetype":"venue"
},
  "geometry": {"coordinates":[-74.75548999999999,40.237263],"type":"Point"}
}