{
  "type": "Feature",
  "properties": {
    "iso:country":"US",
    "sg:address":"6 Craig Dr",
    "sg:city":"Clementon",
    "sg:classifiers":[
        {
            "category":"Manufacturing",
            "subcategory":"Buildings",
            "type":"Manufacturing & Wholesale Goods"
        },
        {
            "category":"Building & Trades",
            "subcategory":"Construction",
            "type":"Services"
        }
    ],
    "sg:phone":"+1 856 784 7991",
    "sg:postcode":"08021",
    "sg:province":"NJ",
    "sg:tags":[
        "home",
        "builder",
        "contractor"
    ],
    "wof:name":"Excel Home Improvements",
    "wof:placetype":"venue"
},
  "geometry": {"coordinates":[-75.027733,39.814018],"type":"Point"}
}