{
  "type": "Feature",
  "properties": {
    "iso:country":"US",
    "sg:address":"133 Starlight Rd",
    "sg:city":"Howell",
    "sg:classifiers":[
        {
            "category":"Building & Trades",
            "subcategory":"Construction",
            "type":"Services"
        }
    ],
    "sg:phone":"+1 732 462 5751",
    "sg:postcode":"07731",
    "sg:province":"NJ",
    "sg:tags":[
        "finishing",
        "carpentry"
    ],
    "wof:name":"Chris Finishing Carpentry",
    "wof:placetype":"venue"
},
  "geometry": {"coordinates":[-74.203835,40.161356],"type":"Point"}
}