{
  "type": "Feature",
  "properties": {
    "addr:full":"US 30 Camden NJ 08102",
    "addr:postcode":"08102",
    "addr:street":"Us 30",
    "iso:country":"US",
    "sg:address":"US 30",
    "sg:city":"Camden",
    "sg:classifiers":[
        {
            "category":"Landmark",
            "subcategory":"Historic",
            "type":"Public Place"
        },
        {
            "category":"Restaurant",
            "type":"Food & Drink"
        }
    ],
    "sg:phone":"+1 856 968 3300",
    "sg:postcode":"08102",
    "sg:province":"NJ",
    "sg:tags":[
        "building",
        "flavor",
        "local",
        "historical"
    ],
    "wof:name":"Ben Franklin Bridge",
    "wof:placetype":"venue"
},
  "geometry": {"coordinates":[-75.12949,39.952122],"type":"Point"}
}