{
  "type": "Feature",
  "properties": {
    "iso:country":"US",
    "sg:address":"10 Robert St",
    "sg:city":"Wharton",
    "sg:classifiers":[
        {
            "category":"Government",
            "subcategory":"Police Station",
            "type":"Public Place"
        }
    ],
    "sg:phone":"+1   ",
    "sg:postcode":"07866",
    "sg:province":"NJ",
    "sg:tags":[
        "protection"
    ],
    "wof:name":"Police Dept Other Business",
    "wof:placetype":"venue"
},
  "geometry": {"coordinates":[-74.531874,40.895913],"type":"Point"}
}