{
  "type": "Feature",
  "properties": {
    "addr:full":"3 Mountain Ave Little Falls NJ 07501",
    "addr:housenumber":"3",
    "addr:postcode":"07501",
    "addr:street":"Mountain Ave",
    "iso:country":"US",
    "sg:address":"3 Mountain Ave",
    "sg:city":"Little Falls",
    "sg:classifiers":[
        {
            "category":"Restaurant",
            "type":"Food & Drink"
        }
    ],
    "sg:phone":"+1   ",
    "sg:postcode":"07501",
    "sg:province":"NJ",
    "sg:tags":[
        "eating"
    ],
    "wof:name":"Gienozzo Cafe",
    "wof:placetype":"venue"
},
  "geometry": {"coordinates":[-74.18277500000001,40.900699],"type":"Point"}
}