{
  "type": "Feature",
  "properties": {
    "addr:full":"35 Wagner Ln Hillsborough NJ 08844",
    "addr:housenumber":"35",
    "addr:postcode":"08844",
    "addr:street":"Wagner Ln",
    "iso:country":"US",
    "sg:address":"35 Wagner Ln",
    "sg:city":"Hillsborough",
    "sg:classifiers":[
        {
            "category":"Building & Trades",
            "subcategory":"Construction",
            "type":"Services"
        }
    ],
    "sg:phone":"+1 908 369 1775",
    "sg:postcode":"08844",
    "sg:province":"NJ",
    "sg:tags":[
        "general",
        "contractor"
    ],
    "wof:name":"Expo Construction Corp",
    "wof:placetype":"venue"
},
  "geometry": {"coordinates":[-74.69844500000001,40.528762],"type":"Point"}
}