{
  "type": "Feature",
  "properties": {
    "iso:country":"US",
    "sg:address":"15 Bergen Ave",
    "sg:city":"Paramus",
    "sg:classifiers":[
        {
            "category":"Shopping",
            "subcategory":"Department Store",
            "type":"Retail Goods"
        }
    ],
    "sg:phone":"+1 201 845 5500",
    "sg:postcode":"07621",
    "sg:province":"NJ",
    "wof:name":"Stern's",
    "wof:placetype":"venue"
},
  "geometry": {"coordinates":[-73.995587,40.925243],"type":"Point"}
}