{
  "type": "Feature",
  "properties": {
    "iso:country":"US",
    "sg:address":"78 Main St",
    "sg:city":"Flemington",
    "sg:classifiers":[
        {
            "category":"Shopping",
            "subcategory":"Gifts & Souvenirs",
            "type":"Retail Goods"
        }
    ],
    "sg:phone":"+1   ",
    "sg:postcode":"08822",
    "sg:province":"NJ",
    "sg:tags":[
        "store"
    ],
    "wof:name":"Potting Shed",
    "wof:placetype":"venue"
},
  "geometry": {"coordinates":[-74.85879300000001,40.509924],"type":"Point"}
}