{
  "type": "Feature",
  "properties": {
    "addr:full":"51 Stagecoach Rd Cape May Court House NJ 08210",
    "addr:housenumber":"51",
    "addr:postcode":"08210",
    "addr:street":"Stagecoach Rd",
    "iso:country":"US",
    "sg:address":"51 Stagecoach Rd",
    "sg:city":"Cape May Court House",
    "sg:classifiers":[
        {
            "category":"Building & Trades",
            "subcategory":"Construction",
            "type":"Services"
        }
    ],
    "sg:phone":"+1 609 463 0010",
    "sg:postcode":"08210",
    "sg:province":"NJ",
    "sg:tags":[
        "hanging",
        "contractor"
    ],
    "wof:name":"David Crews Painting",
    "wof:placetype":"venue"
},
  "geometry": {"coordinates":[-74.846733,39.075897],"type":"Point"}
}