{
  "type": "Feature",
  "properties": {
    "addr:full":"14 Highland Dr Englishtown NJ 07726",
    "addr:housenumber":"14",
    "addr:postcode":"07726",
    "addr:street":"Highland Dr",
    "iso:country":"US",
    "sg:address":"14 Highland Dr",
    "sg:city":"Englishtown",
    "sg:classifiers":[
        {
            "category":"Professional",
            "subcategory":"Research",
            "type":"Services"
        }
    ],
    "sg:phone":"+1   ",
    "sg:postcode":"07726",
    "sg:province":"NJ",
    "sg:tags":[
        "development"
    ],
    "wof:name":"Merits",
    "wof:placetype":"venue"
},
  "geometry": {"coordinates":[-74.29874100000001,40.320164],"type":"Point"}
}