{
  "type": "Feature",
  "properties": {
    "addr:full":"400 Pathway Manor Wyckoff NJ 07481",
    "addr:housenumber":"400",
    "addr:postcode":"07481",
    "addr:street":"Pathway Manor",
    "iso:country":"US",
    "sg:address":"400 Pathway Manor",
    "sg:city":"Wyckoff",
    "sg:classifiers":[
        {
            "category":"Real Estate",
            "subcategory":"Real Estate Operator",
            "type":"Services"
        }
    ],
    "sg:phone":"+1   ",
    "sg:postcode":"07481",
    "sg:province":"NJ",
    "sg:tags":[
        "building",
        "nonresidential"
    ],
    "wof:name":"Green Street Realty Inc",
    "wof:placetype":"venue"
},
  "geometry": {"coordinates":[-74.166556,40.999901],"type":"Point"}
}