{
  "type": "Feature",
  "properties": {
    "iso:country":"US",
    "sg:address":"44 Distribution Blvd",
    "sg:city":"Edison",
    "sg:classifiers":[
        {
            "category":"Professional",
            "subcategory":"Management & Consulting",
            "type":"Services"
        }
    ],
    "sg:phone":"+1   ",
    "sg:postcode":"08837",
    "sg:province":"NJ",
    "sg:tags":[
        "import",
        "business"
    ],
    "wof:name":"New Spec Inc",
    "wof:placetype":"venue"
},
  "geometry": {"coordinates":[-74.379857,40.499023],"type":"Point"}
}