{
  "type": "Feature",
  "properties": {
    "iso:country":"US",
    "sg:address":"12 Holly Dr",
    "sg:city":"Saddle River",
    "sg:classifiers":[
        {
            "category":"Shopping",
            "type":"Retail Goods"
        }
    ],
    "sg:phone":"+1 201 327 1533",
    "sg:postcode":"07458",
    "sg:province":"NJ",
    "sg:tags":[
        "candle"
    ],
    "wof:name":"North Country Candle Co",
    "wof:placetype":"venue"
},
  "geometry": {"coordinates":[-74.101067,41.060656],"type":"Point"}
}