{
  "type": "Feature",
  "properties": {
    "iso:country":"US",
    "sg:address":"310 Main St",
    "sg:city":"West Orange",
    "sg:classifiers":[
        {
            "category":"Professional",
            "type":"Services"
        }
    ],
    "sg:phone":"+1 973 736 7254",
    "sg:postcode":"07052",
    "sg:province":"NJ",
    "sg:tags":[
        "establishment"
    ],
    "wof:name":"Le Jourdain Early Chldhd Ctr",
    "wof:placetype":"venue"
},
  "geometry": {"coordinates":[-74.231325,40.788479],"type":"Point"}
}