{
  "type": "Feature",
  "properties": {
    "addr:full":"3 Lochalsh Ln Rio Grande NJ 08242",
    "addr:housenumber":"3",
    "addr:postcode":"08242",
    "addr:street":"Lochalsh Ln",
    "iso:country":"US",
    "sg:address":"3 Lochalsh Ln",
    "sg:city":"Rio Grande",
    "sg:classifiers":[
        {
            "category":"Building & Trades",
            "subcategory":"Construction",
            "type":"Services"
        }
    ],
    "sg:phone":"+1 609 463 0284",
    "sg:postcode":"08242",
    "sg:province":"NJ",
    "sg:tags":[
        "contractor"
    ],
    "wof:name":"Beazer Homes",
    "wof:placetype":"venue"
},
  "geometry": {"coordinates":[-74.870333,39.017496],"type":"Point"}
}