{
  "type": "Feature",
  "properties": {
    "addr:full":"218 Hawthorne Ave Haddonfield NJ 08033",
    "addr:housenumber":"218",
    "addr:postcode":"08033",
    "addr:street":"Hawthorne Ave",
    "iso:country":"US",
    "sg:address":"218 Hawthorne Ave",
    "sg:city":"Haddonfield",
    "sg:classifiers":[
        {
            "category":"Real Estate",
            "subcategory":"Architect",
            "type":"Services"
        }
    ],
    "sg:phone":"+1 856 354 9083",
    "sg:postcode":"08033",
    "sg:province":"NJ",
    "sg:tags":[
        "architectural"
    ],
    "wof:name":"Zobel Architects",
    "wof:placetype":"venue"
},
  "geometry": {"coordinates":[-75.033559,39.906594],"type":"Point"}
}