{
  "type": "Feature",
  "properties": {
    "addr:full":"600 Leesville Ave Rahway NJ 07065",
    "addr:housenumber":"600",
    "addr:postcode":"07065",
    "addr:street":"Leesville Ave",
    "iso:country":"US",
    "sg:address":"600 Leesville Ave",
    "sg:city":"Rahway",
    "sg:classifiers":[
        {
            "category":"Wholesale",
            "subcategory":"Auto Parts",
            "type":"Manufacturing & Wholesale Goods"
        }
    ],
    "sg:phone":"+1 732 388 0709",
    "sg:postcode":"07065",
    "sg:province":"NJ",
    "sg:tags":[
        "automobile",
        "rebuilt"
    ],
    "sg:website":"www.riversidenj.com",
    "wof:name":"Riverside Auto Parts",
    "wof:placetype":"venue"
},
  "geometry": {"coordinates":[-74.27835399999999,40.595001],"type":"Point"}
}