{
  "type": "Feature",
  "properties": {
    "addr:full":"909 Westfield Rd Scotch Plains NJ 07076",
    "addr:housenumber":"909",
    "addr:postcode":"07076",
    "addr:street":"Westfield Rd",
    "iso:country":"US",
    "sg:address":"909 Westfield Rd",
    "sg:city":"Scotch Plains",
    "sg:classifiers":[
        {
            "category":"Health Services",
            "subcategory":"Doctor",
            "type":"Services"
        }
    ],
    "sg:phone":"+1 973 743 4748",
    "sg:postcode":"07076",
    "sg:province":"NJ",
    "sg:tags":[
        "physician",
        "surgeon"
    ],
    "wof:name":"Matthew D Horn MD",
    "wof:placetype":"venue"
},
  "geometry": {"coordinates":[-74.375063,40.646732],"type":"Point"}
}