{
  "type": "Feature",
  "properties": {
    "iso:country":"US",
    "sg:address":"57 Berkeley Sq",
    "sg:city":"Berkeley Heights",
    "sg:classifiers":[
        {
            "category":"Wholesale",
            "subcategory":"Durable Goods & Equipment",
            "type":"Manufacturing & Wholesale Goods"
        }
    ],
    "sg:phone":"+1 908 665 0404",
    "sg:postcode":"07922",
    "sg:province":"NJ",
    "sg:tags":[
        "representative",
        "manufacturer"
    ],
    "sg:website":"www.jbcindustries.com",
    "wof:name":"JBC Industries",
    "wof:placetype":"venue"
},
  "geometry": {"coordinates":[-74.421111,40.673494],"type":"Point"}
}