{
  "type": "Feature",
  "properties": {
    "addr:full":"350 Morrissee Ave Haledon NJ 07508",
    "addr:housenumber":"350",
    "addr:postcode":"07508",
    "addr:street":"Morrissee Ave",
    "iso:country":"US",
    "sg:address":"350 Morrissee Ave",
    "sg:city":"Haledon",
    "sg:classifiers":[
        {
            "category":"Building & Trades",
            "subcategory":"Plumbing",
            "type":"Services"
        }
    ],
    "sg:phone":"+1 973 942 6299",
    "sg:postcode":"07508",
    "sg:province":"NJ",
    "sg:tags":[
        "conditioning",
        "air",
        "system",
        "contractor"
    ],
    "wof:name":"All City",
    "wof:placetype":"venue"
},
  "geometry": {"coordinates":[-74.18512200000001,40.93375],"type":"Point"}
}