{
  "type": "Feature",
  "properties": {
    "iso:country":"US",
    "sg:address":"311 Paramus Rd",
    "sg:city":"Paramus",
    "sg:classifiers":[
        {
            "category":"Shopping",
            "type":"Retail Goods"
        }
    ],
    "sg:phone":"+1   ",
    "sg:postcode":"07652",
    "sg:province":"NJ",
    "sg:tags":[
        "sunglasses",
        "accessory"
    ],
    "wof:name":"Sunglass Hut 735",
    "wof:placetype":"venue"
},
  "geometry": {"coordinates":[-74.092738,40.942312],"type":"Point"}
}