{
  "type": "Feature",
  "properties": {
    "iso:country":"US",
    "sg:address":"966 E 25th St",
    "sg:city":"Paterson",
    "sg:classifiers":[
        {
            "category":"Building & Trades",
            "subcategory":"Construction",
            "type":"Services"
        }
    ],
    "sg:phone":"+1 973 573 0023",
    "sg:postcode":"07513",
    "sg:province":"NJ",
    "sg:tags":[
        "general",
        "contractor"
    ],
    "wof:name":"Precise Construction",
    "wof:placetype":"venue"
},
  "geometry": {"coordinates":[-74.151914,40.907142],"type":"Point"}
}