{
  "type": "Feature",
  "properties": {
    "addr:full":"45 Barbour Pond Dr Wayne NJ 07470",
    "addr:housenumber":"45",
    "addr:postcode":"07470",
    "addr:street":"Barbour Pond Dr",
    "iso:country":"US",
    "sg:address":"45 Barbour Pond Dr",
    "sg:city":"Wayne",
    "sg:classifiers":[
        {
            "category":"Professional",
            "type":"Services"
        }
    ],
    "sg:phone":"+1 973 709 4500",
    "sg:postcode":"07470",
    "sg:province":"NJ",
    "sg:tags":[
        "establishment"
    ],
    "wof:name":"SYNAVANT",
    "wof:placetype":"venue"
},
  "geometry": {"coordinates":[-74.22538900000001,40.96234],"type":"Point"}
}