{
  "type": "Feature",
  "properties": {
    "iso:country":"US",
    "sg:address":"1666 US Hwy 206",
    "sg:city":"Southampton",
    "sg:classifiers":[
        {
            "category":"Professional",
            "subcategory":"Art Services",
            "type":"Services"
        }
    ],
    "sg:phone":"+1 609 859 8400",
    "sg:postcode":"08088",
    "sg:province":"NJ",
    "sg:tags":[
        "production",
        "layout",
        "advertising"
    ],
    "sg:website":"www.jmsco.com",
    "wof:name":"JMS Visual Communications",
    "wof:placetype":"venue"
},
  "geometry": {"coordinates":[-74.73532,39.875309],"type":"Point"}
}