{
  "type": "Feature",
  "properties": {
    "iso:country":"US",
    "sg:address":"3 E Clinton Ave",
    "sg:city":"Bergenfield",
    "sg:classifiers":[
        {
            "category":"Organizations",
            "subcategory":"Religious Organization",
            "type":"Services"
        }
    ],
    "sg:phone":"+1 201 501 0851",
    "sg:postcode":"07621",
    "sg:province":"NJ",
    "sg:tags":[
        "church"
    ],
    "wof:name":"Living Faith Christian Ctr",
    "wof:placetype":"venue"
},
  "geometry": {"coordinates":[-73.995561,40.923887],"type":"Point"}
}