{
  "type": "Feature",
  "properties": {
    "addr:full":"119 Mac Intyre Ln Allendale NJ 07401",
    "addr:housenumber":"119",
    "addr:postcode":"07401",
    "addr:street":"Mac Intyre Ln",
    "iso:country":"US",
    "sg:address":"119 Mac Intyre Ln",
    "sg:city":"Allendale",
    "sg:classifiers":[
        {
            "category":"Professional",
            "subcategory":"Research",
            "type":"Services"
        }
    ],
    "sg:phone":"+1 201 934 0074",
    "sg:postcode":"07401",
    "sg:province":"NJ",
    "sg:tags":[
        "nonphysical",
        "commercial"
    ],
    "wof:name":"N2 Square",
    "wof:placetype":"venue"
},
  "geometry": {"coordinates":[-74.14753,41.028595],"type":"Point"}
}