{
  "type": "Feature",
  "properties": {
    "iso:country":"US",
    "sg:address":"979 Littleton Rd",
    "sg:city":"Parsippany",
    "sg:classifiers":[
        {
            "category":"Real Estate",
            "subcategory":"Real Estate Agent",
            "type":"Services"
        }
    ],
    "sg:phone":"+1   ",
    "sg:postcode":"07054",
    "sg:province":"NJ",
    "wof:name":"Century 21",
    "wof:placetype":"venue"
},
  "geometry": {"coordinates":[-74.446465,40.861857],"type":"Point"}
}