{
  "type": "Feature",
  "properties": {
    "addr:full":"276 Passaic St Passaic NJ 07055",
    "addr:housenumber":"276",
    "addr:postcode":"07055",
    "addr:street":"Passaic St",
    "iso:country":"US",
    "sg:address":"276 Passaic St",
    "sg:city":"Passaic",
    "sg:classifiers":[
        {
            "category":"Home & Garden",
            "subcategory":"Furniture",
            "type":"Retail Goods"
        }
    ],
    "sg:phone":"+1   ",
    "sg:postcode":"07055",
    "sg:province":"NJ",
    "wof:name":"F & F Furniture Inc",
    "wof:placetype":"venue"
},
  "geometry": {"coordinates":[-74.122198,40.861128],"type":"Point"}
}