{
  "type": "Feature",
  "properties": {
    "addr:full":"12 Riverside Rd Hewitt NJ 07421",
    "addr:housenumber":"12",
    "addr:postcode":"07421",
    "addr:street":"Riverside Rd",
    "iso:country":"US",
    "sg:address":"12 Riverside Rd",
    "sg:city":"Hewitt",
    "sg:classifiers":[
        {
            "category":"Retail",
            "subcategory":"Portrait Studio",
            "type":"Services"
        }
    ],
    "sg:phone":"+1 973 853 2000",
    "sg:postcode":"07421",
    "sg:province":"NJ",
    "sg:tags":[
        "photo"
    ],
    "wof:name":"White Studio Inc",
    "wof:placetype":"venue"
},
  "geometry": {"coordinates":[-74.3699,41.186485],"type":"Point"}
}