{
  "type": "Feature",
  "properties": {
    "addr:full":"178 State Rte 17 Paramus NJ 07652",
    "addr:housenumber":"178",
    "addr:postcode":"07652",
    "addr:street":"State Rte 17",
    "iso:country":"US",
    "sg:address":"178 State Rte 17",
    "sg:city":"Paramus",
    "sg:classifiers":[
        {
            "category":"Shopping",
            "type":"Retail Goods"
        }
    ],
    "sg:phone":"+1 201 599 2635",
    "sg:postcode":"07652",
    "sg:province":"NJ",
    "sg:tags":[
        "plant",
        "flower",
        "tree",
        "artificial",
        "merchandise"
    ],
    "wof:name":"Silk Flowers Just For You",
    "wof:placetype":"venue"
},
  "geometry": {"coordinates":[-74.07069,40.90982],"type":"Point"}
}