{
  "type": "Feature",
  "properties": {
    "iso:country":"US",
    "sg:address":"525 Basso St",
    "sg:city":"Jackson",
    "sg:classifiers":[
        {
            "category":"Building & Trades",
            "subcategory":"Landscaping Services",
            "type":"Services"
        }
    ],
    "sg:phone":"+1 732 657 2852",
    "sg:postcode":"08527",
    "sg:province":"NJ",
    "sg:tags":[
        "maintenance",
        "grounds"
    ],
    "wof:name":"BA Manetti Landscaping",
    "wof:placetype":"venue"
},
  "geometry": {"coordinates":[-74.303822,40.047662],"type":"Point"}
}