{
  "type": "Feature",
  "properties": {
    "iso:country":"US",
    "sg:address":"563 E Main St",
    "sg:city":"Little Egg Hbr",
    "sg:classifiers":[
        {
            "category":"Real Estate",
            "subcategory":"Real Estate Operator",
            "type":"Services"
        }
    ],
    "sg:phone":"+1 609 294 8829",
    "sg:postcode":"08087",
    "sg:province":"NJ",
    "sg:tags":[
        "mall",
        "shopping",
        "center"
    ],
    "wof:name":"Village Shoppes At Middle",
    "wof:placetype":"venue"
},
  "geometry": {"coordinates":[-74.322171,39.615686],"type":"Point"}
}