{
  "type": "Feature",
  "properties": {
    "iso:country":"US",
    "sg:address":"142 Totowa Rd Ste 1",
    "sg:city":"Totowa",
    "sg:classifiers":[
        {
            "category":"Home & Garden",
            "subcategory":"Garden Supply",
            "type":"Retail Goods"
        },
        {
            "category":"Shopping",
            "subcategory":"Florist",
            "type":"Retail Goods"
        }
    ],
    "sg:phone":"+1 973 956 9159",
    "sg:postcode":"07512",
    "sg:province":"NJ",
    "sg:tags":[
        "nursery",
        "gardening"
    ],
    "wof:name":"Riverview Florist",
    "wof:placetype":"venue"
},
  "geometry": {"coordinates":[-74.21410400000001,40.905998],"type":"Point"}
}