{
  "type": "Feature",
  "properties": {
    "addr:full":"7 Lake Ave Helmetta NJ 08828",
    "addr:housenumber":"7",
    "addr:postcode":"08828",
    "addr:street":"Lake Ave",
    "iso:country":"US",
    "sg:address":"7 Lake Ave",
    "sg:city":"Helmetta",
    "sg:classifiers":[
        {
            "category":"Building & Trades",
            "subcategory":"Landscaping Services",
            "type":"Services"
        }
    ],
    "sg:phone":"+1 732 254 8863",
    "sg:postcode":"08828",
    "sg:province":"NJ",
    "sg:tags":[
        "landscape",
        "contractor"
    ],
    "wof:name":"Modern View Landscaping Co",
    "wof:placetype":"venue"
},
  "geometry": {"coordinates":[-74.41803,40.380953],"type":"Point"}
}