{
  "type": "Feature",
  "properties": {
    "addr:full":"21 Tompkins St Ocean View NJ 08230",
    "addr:housenumber":"21",
    "addr:postcode":"08230",
    "addr:street":"Tompkins St",
    "iso:country":"US",
    "sg:address":"21 Tompkins St",
    "sg:city":"Ocean View",
    "sg:classifiers":[
        {
            "category":"Sports & Exercise",
            "subcategory":"Race Track",
            "type":"Entertainment"
        }
    ],
    "sg:phone":"+1 609 624 3093",
    "sg:postcode":"08230",
    "sg:province":"NJ",
    "sg:tags":[
        "cross",
        "motor"
    ],
    "wof:name":"Mount Pleasant Moto Cross",
    "wof:placetype":"venue"
},
  "geometry": {"coordinates":[-74.72662200000001,39.187577],"type":"Point"}
}