{
  "type": "Feature",
  "properties": {
    "iso:country":"US",
    "sg:address":"265 Woodward Rd",
    "sg:city":"Englishtown",
    "sg:classifiers":[
        {
            "category":"Wholesale",
            "subcategory":"Home Furnishings",
            "type":"Manufacturing & Wholesale Goods"
        }
    ],
    "sg:phone":"+1 732 792 8300",
    "sg:postcode":"07726",
    "sg:province":"NJ",
    "sg:tags":[
        "closet",
        "accessory"
    ],
    "wof:name":"Closets For Less",
    "wof:placetype":"venue"
},
  "geometry": {"coordinates":[-74.368894,40.242413],"type":"Point"}
}