{
  "type": "Feature",
  "properties": {
    "iso:country":"US",
    "sg:address":"491 Closter Dock Rd",
    "sg:city":"Closter",
    "sg:classifiers":[
        {
            "category":"Professional",
            "subcategory":"Accounting & Tax Preparation",
            "type":"Services"
        }
    ],
    "sg:phone":"+1 201 784 3383",
    "sg:postcode":"07624",
    "sg:province":"NJ",
    "sg:tags":[
        "accountant"
    ],
    "wof:name":"Bruce Litt CPA PA",
    "wof:placetype":"venue"
},
  "geometry": {"coordinates":[-73.95484,40.965472],"type":"Point"}
}