{
  "type": "Feature",
  "properties": {
    "addr:full":"569 Bloomfield Ave Verona NJ 07044",
    "addr:housenumber":"569",
    "addr:postcode":"07044",
    "addr:street":"Bloomfield Ave",
    "iso:country":"US",
    "sg:address":"569 Bloomfield Ave",
    "sg:city":"Verona",
    "sg:classifiers":[
        {
            "category":"Personal",
            "subcategory":"Beauty Salon",
            "type":"Services"
        }
    ],
    "sg:phone":"+1 973 482 5333",
    "sg:postcode":"07044",
    "sg:province":"NJ",
    "sg:tags":[
        "shop"
    ],
    "wof:name":"Funky Nail",
    "wof:placetype":"venue"
},
  "geometry": {"coordinates":[-74.24643399999999,40.831964],"type":"Point"}
}