{
  "type": "Feature",
  "properties": {
    "addr:full":"316 Elbo Ln Mt Laurel NJ 08054",
    "addr:housenumber":"316",
    "addr:postcode":"08054",
    "addr:street":"Elbo Ln",
    "iso:country":"US",
    "sg:address":"316 Elbo Ln",
    "sg:city":"Mt Laurel",
    "sg:classifiers":[
        {
            "category":"Organizations",
            "subcategory":"Religious Organization",
            "type":"Services"
        }
    ],
    "sg:phone":"+1 856 234 1728",
    "sg:postcode":"08054",
    "sg:province":"NJ",
    "sg:tags":[
        "church"
    ],
    "wof:name":"Jacobs Chapel AME",
    "wof:placetype":"venue"
},
  "geometry": {"coordinates":[-74.883743,39.929928],"type":"Point"}
}