{
  "type": "Feature",
  "properties": {
    "addr:full":"720 S Church St Mount Laurel NJ 08054",
    "addr:housenumber":"720",
    "addr:postcode":"08054",
    "addr:street":"S Church St",
    "iso:country":"US",
    "sg:address":"720 S Church St",
    "sg:city":"Mount Laurel",
    "sg:classifiers":[
        {
            "category":"Shopping",
            "subcategory":"Pharmacy",
            "type":"Retail Goods"
        }
    ],
    "sg:phone":"+1   ",
    "sg:postcode":"08054",
    "sg:province":"NJ",
    "sg:tags":[
        "drug",
        "store"
    ],
    "wof:name":"Rite Aid",
    "wof:placetype":"venue"
},
  "geometry": {"coordinates":[-74.93886999999999,39.941814],"type":"Point"}
}