{
  "type": "Feature",
  "properties": {
    "addr:full":"340 Haddonfield Rd Cherry Hill NJ 08002",
    "addr:housenumber":"340",
    "addr:postcode":"08002",
    "addr:street":"Haddonfield Rd",
    "iso:country":"US",
    "sg:address":"340 Haddonfield Rd",
    "sg:city":"Cherry Hill",
    "sg:classifiers":[
        {
            "category":"Home & Garden",
            "subcategory":"Furniture",
            "type":"Retail Goods"
        }
    ],
    "sg:phone":"+1 856 486 0999",
    "sg:postcode":"08002",
    "sg:province":"NJ",
    "sg:tags":[
        "store"
    ],
    "wof:name":"Rooms To Dream",
    "wof:placetype":"venue"
},
  "geometry": {"coordinates":[-75.029701,39.9408],"type":"Point"}
}