{
  "type": "Feature",
  "properties": {
    "iso:country":"US",
    "sg:address":"109 Heritage Rd",
    "sg:city":"Sewell",
    "sg:classifiers":[
        {
            "category":"Professional",
            "subcategory":"Business Services",
            "type":"Services"
        }
    ],
    "sg:phone":"+1 856 464 0897",
    "sg:postcode":"08080",
    "sg:province":"NJ",
    "sg:tags":[
        "interior",
        "design"
    ],
    "wof:name":"Global",
    "wof:placetype":"venue"
},
  "geometry": {"coordinates":[-75.17954,39.76668],"type":"Point"}
}