{
  "type": "Feature",
  "properties": {
    "iso:country":"US",
    "sg:address":"331 Washington St",
    "sg:city":"Hoboken",
    "sg:classifiers":[
        {
            "category":"Utilities",
            "subcategory":"Mobile Phone",
            "type":"Services"
        }
    ],
    "sg:phone":"+1 201 420 7447",
    "sg:postcode":"07030",
    "sg:province":"NJ",
    "sg:tags":[
        "telephone",
        "cellular"
    ],
    "wof:name":"Verizon Wireless Unitel",
    "wof:placetype":"venue"
},
  "geometry": {"coordinates":[-74.02976099999999,40.740841],"type":"Point"}
}