{
  "type": "Feature",
  "properties": {
    "iso:country":"US",
    "sg:address":"189 Elm St",
    "sg:city":"Westfield",
    "sg:classifiers":[
        {
            "category":"Health Services",
            "subcategory":"Doctor",
            "type":"Services"
        }
    ],
    "sg:phone":"+1 908 232 3435",
    "sg:postcode":"07090",
    "sg:province":"NJ",
    "sg:tags":[
        "medical"
    ],
    "wof:name":"Rudofsky Marc MD",
    "wof:placetype":"venue"
},
  "geometry": {"coordinates":[-74.34900399999999,40.651839],"type":"Point"}
}