{
  "type": "Feature",
  "properties": {
    "iso:country":"US",
    "sg:address":"143 Lincoln Ave",
    "sg:city":"Orange",
    "sg:classifiers":[
        {
            "category":"Retail",
            "subcategory":"Repair Shop",
            "type":"Services"
        }
    ],
    "sg:phone":"+1 973 854 5304",
    "sg:postcode":"07050",
    "sg:province":"NJ",
    "sg:tags":[
        "lock",
        "key",
        "locksmith"
    ],
    "wof:name":"1 24 Hour 7 Day Emerg A Lock A Locksmith",
    "wof:placetype":"venue"
},
  "geometry": {"coordinates":[-74.235974,40.77007],"type":"Point"}
}