{
  "type": "Feature",
  "properties": {
    "addr:full":"800 5th St Riverside NJ 08075",
    "addr:housenumber":"800",
    "addr:postcode":"08075",
    "addr:street":"5Th St",
    "iso:country":"US",
    "sg:address":"800 5th St",
    "sg:city":"Riverside",
    "sg:classifiers":[
        {
            "category":"Professional",
            "type":"Services"
        }
    ],
    "sg:phone":"+1   ",
    "sg:postcode":"08075",
    "sg:province":"NJ",
    "wof:name":"Free & Accepted Masons of",
    "wof:placetype":"venue"
},
  "geometry": {"coordinates":[-74.973609,40.023384],"type":"Point"}
}