{
  "type": "Feature",
  "properties": {
    "iso:country":"US",
    "sg:address":"89 Westminster Ave",
    "sg:city":"Bergenfield",
    "sg:classifiers":[
        {
            "category":"Shopping",
            "subcategory":"Used Merchandise",
            "type":"Retail Goods"
        }
    ],
    "sg:phone":"+1   ",
    "sg:postcode":"07621",
    "sg:province":"NJ",
    "wof:name":"Caught In Time",
    "wof:placetype":"venue"
},
  "geometry": {"coordinates":[-74.013068,40.912065],"type":"Point"}
}