{
  "type": "Feature",
  "properties": {
    "iso:country":"US",
    "sg:address":"286 Clarksville Rd",
    "sg:city":"Princeton Junction",
    "sg:classifiers":[
        {
            "category":"Wholesale",
            "subcategory":"Plants",
            "type":"Manufacturing & Wholesale Goods"
        }
    ],
    "sg:phone":"+1 609 716 0074",
    "sg:postcode":"08550",
    "sg:province":"NJ",
    "sg:tags":[
        "supply"
    ],
    "wof:name":"Logan Associates",
    "wof:placetype":"venue"
},
  "geometry": {"coordinates":[-74.630574,40.30423],"type":"Point"}
}