{
  "type": "Feature",
  "properties": {
    "iso:country":"US",
    "sg:address":"19 W Main St",
    "sg:city":"Mendham",
    "sg:classifiers":[
        {
            "category":"Shopping",
            "type":"Retail Goods"
        },
        {
            "category":"Building & Trades",
            "subcategory":"Construction",
            "type":"Services"
        }
    ],
    "sg:phone":"+1 973 543 6591",
    "sg:postcode":"07945",
    "sg:province":"NJ",
    "sg:tags":[
        "plastering",
        "supply",
        "coping",
        "spa",
        "tiling",
        "pool",
        "swimming"
    ],
    "wof:name":"Blue Ridge Pool & Spa Center",
    "wof:placetype":"venue"
},
  "geometry": {"coordinates":[-74.603138,40.775457],"type":"Point"}
}