{
  "type": "Feature",
  "properties": {
    "iso:country":"US",
    "sg:address":"223 Beach Front",
    "sg:city":"Manasquan",
    "sg:classifiers":[
        {
            "category":"Food & Beverages",
            "subcategory":"Bakery",
            "type":"Retail Goods"
        }
    ],
    "sg:phone":"+1 732 528 2275",
    "sg:postcode":"08736",
    "sg:province":"NJ",
    "sg:tags":[
        "baker"
    ],
    "wof:name":"Bagel On A Beach",
    "wof:placetype":"venue"
},
  "geometry": {"coordinates":[-74.03372299999999,40.110703],"type":"Point"}
}