{
  "type": "Feature",
  "properties": {
    "addr:full":"102 US Hwy 1 Linden NJ 07036",
    "addr:housenumber":"102",
    "addr:postcode":"07036",
    "addr:street":"Us Hwy 1",
    "iso:country":"US",
    "sg:address":"102 US Hwy 1",
    "sg:city":"Linden",
    "sg:classifiers":[
        {
            "category":"Shopping",
            "type":"Retail Goods"
        }
    ],
    "sg:phone":"+1   ",
    "sg:postcode":"07036",
    "sg:province":"NJ",
    "sg:tags":[
        "merchandise",
        "business"
    ],
    "wof:name":"Blue Ribbon Pools Inc",
    "wof:placetype":"venue"
},
  "geometry": {"coordinates":[-74.245088,40.624753],"type":"Point"}
}