{
  "type": "Feature",
  "properties": {
    "iso:country":"US",
    "sg:address":"5918 New Jersey Ave",
    "sg:city":"Wildwood",
    "sg:classifiers":[
        {
            "category":"Real Estate",
            "subcategory":"Real Estate Agent",
            "type":"Services"
        }
    ],
    "sg:phone":"+1 609 522 5757",
    "sg:postcode":"08260",
    "sg:province":"NJ",
    "sg:tags":[
        "insurance"
    ],
    "sg:website":"www.gallagher-realestate.com",
    "wof:name":"Gallagher Real Estate",
    "wof:placetype":"venue"
},
  "geometry": {"coordinates":[-74.831902,38.979],"type":"Point"}
}