{
  "type": "Feature",
  "properties": {
    "addr:full":"364 Georges Rd Dayton NJ 08810",
    "addr:housenumber":"364",
    "addr:postcode":"08810",
    "addr:street":"Georges Rd",
    "iso:country":"US",
    "sg:address":"364 Georges Rd",
    "sg:city":"Dayton",
    "sg:classifiers":[
        {
            "category":"Social Services",
            "subcategory":"Child Care",
            "type":"Services"
        },
        {
            "category":"Education",
            "subcategory":"Preschool",
            "type":"Public Place"
        },
        {
            "category":"Education",
            "subcategory":"School",
            "type":"Public Place"
        },
        {
            "category":"Recreation",
            "type":"Entertainment"
        }
    ],
    "sg:phone":"+1 732 329 3577",
    "sg:postcode":"08810",
    "sg:province":"NJ",
    "sg:tags":[
        "camps-recreational",
        "private",
        "kindergarten",
        "nursery",
        "k-",
        "day"
    ],
    "sg:website":"http://www.montessorischoolnj.com",
    "wof:name":"Montessori Children's House",
    "wof:placetype":"venue"
},
  "geometry": {"coordinates":[-74.51130499999999,40.374219],"type":"Point"}
}