{
  "type": "Feature",
  "properties": {
    "iso:country":"US",
    "sg:address":"1301 W State St",
    "sg:city":"Trenton",
    "sg:classifiers":[
        {
            "category":"Social Services",
            "type":"Services"
        }
    ],
    "sg:phone":"+1 609 394 6747",
    "sg:postcode":"08618",
    "sg:province":"NJ",
    "sg:tags":[
        "organization",
        "welfare"
    ],
    "wof:name":"Rainbow House Inc",
    "wof:placetype":"venue"
},
  "geometry": {"coordinates":[-74.796098,40.234725],"type":"Point"}
}