{
  "type": "Feature",
  "properties": {
    "iso:country":"US",
    "sg:address":"2028 New York Ave",
    "sg:city":"Union City",
    "sg:classifiers":[
        {
            "category":"Food & Beverages",
            "subcategory":"Groceries & Convenience Stores",
            "type":"Retail Goods"
        }
    ],
    "sg:phone":"+1   ",
    "sg:postcode":"07087",
    "sg:province":"NJ",
    "wof:name":"J & D Delicatessan",
    "wof:placetype":"venue"
},
  "geometry": {"coordinates":[-74.03251400000001,40.764904],"type":"Point"}
}