{
  "type": "Feature",
  "properties": {
    "iso:country":"US",
    "sg:address":"38 Clifford Dr",
    "sg:city":"Montville",
    "sg:classifiers":[
        {
            "category":"Autos & Motor Vehicles",
            "subcategory":"Fuel & Gas Station",
            "type":"Retail Goods"
        }
    ],
    "sg:phone":"+1 973 334 6554",
    "sg:postcode":"07045",
    "sg:province":"NJ",
    "wof:name":"Clifford Dr Pump Station",
    "wof:placetype":"venue"
},
  "geometry": {"coordinates":[-74.371201,40.900299],"type":"Point"}
}