{
  "type": "Feature",
  "properties": {
    "addr:full":"1693 US Highway 46 Parsippany NJ 07054",
    "addr:housenumber":"1693",
    "addr:postcode":"07054",
    "addr:street":"Us Highway 46",
    "iso:country":"US",
    "sg:address":"1693 US Highway 46",
    "sg:city":"Parsippany",
    "sg:classifiers":[
        {
            "category":"Shopping",
            "subcategory":"Florist",
            "type":"Retail Goods"
        }
    ],
    "sg:phone":"+1 973 335 4100",
    "sg:postcode":"07054",
    "sg:province":"NJ",
    "wof:name":"Cottage Flowers",
    "wof:placetype":"venue"
},
  "geometry": {"coordinates":[-74.40010100000001,40.863998],"type":"Point"}
}