{
  "type": "Feature",
  "properties": {
    "addr:full":"303 Jonathan Ln Marlton NJ 08053",
    "addr:housenumber":"303",
    "addr:postcode":"08053",
    "addr:street":"Jonathan Ln",
    "iso:country":"US",
    "sg:address":"303 Jonathan Ln",
    "sg:city":"Marlton",
    "sg:classifiers":[
        {
            "category":"Shopping",
            "subcategory":"Optical Goods",
            "type":"Retail Goods"
        }
    ],
    "sg:phone":"+1   ",
    "sg:postcode":"08053",
    "sg:province":"NJ",
    "wof:name":"Lenard Ostroff Optical",
    "wof:placetype":"venue"
},
  "geometry": {"coordinates":[-74.933311,39.903213],"type":"Point"}
}