{
  "type": "Feature",
  "properties": {
    "addr:full":"29 Beach Rd Monmouth Beach NJ 07750",
    "addr:housenumber":"29",
    "addr:postcode":"07750",
    "addr:street":"Beach Rd",
    "iso:country":"US",
    "sg:address":"29 Beach Rd",
    "sg:city":"Monmouth Beach",
    "sg:classifiers":[
        {
            "category":"Restaurant",
            "type":"Food & Drink"
        }
    ],
    "sg:phone":"+1 732 229 3033",
    "sg:postcode":"07750",
    "sg:province":"NJ",
    "wof:name":"Acuna's Cafe",
    "wof:placetype":"venue"
},
  "geometry": {"coordinates":[-73.980231,40.331338],"type":"Point"}
}