{
  "type": "Feature",
  "properties": {
    "iso:country":"US",
    "sg:address":"7 Orange Pl",
    "sg:city":"West Orange",
    "sg:classifiers":[
        {
            "category":"Health Services",
            "subcategory":"Doctor",
            "type":"Services"
        }
    ],
    "sg:phone":"+1 973 731 5049",
    "sg:postcode":"07052",
    "sg:province":"NJ",
    "sg:tags":[
        "physician",
        "surgeon"
    ],
    "wof:name":"Sheo Prasad MD",
    "wof:placetype":"venue"
},
  "geometry": {"coordinates":[-74.232258,40.792554],"type":"Point"}
}