{
  "type": "Feature",
  "properties": {
    "addr:full":"100 Madison Ave Westwood NJ 07675",
    "addr:housenumber":"100",
    "addr:postcode":"07675",
    "addr:street":"Madison Ave",
    "iso:country":"US",
    "sg:address":"100 Madison Ave",
    "sg:city":"Westwood",
    "sg:classifiers":[
        {
            "category":"Real Estate",
            "subcategory":"Real Estate Agent",
            "type":"Services"
        }
    ],
    "sg:phone":"+1 201 664 9145",
    "sg:postcode":"07675",
    "sg:province":"NJ",
    "sg:tags":[
        "manager",
        "management"
    ],
    "wof:name":"Emerald Management Corporation",
    "wof:placetype":"venue"
},
  "geometry": {"coordinates":[-74.035628,40.993659],"type":"Point"}
}