{
  "type": "Feature",
  "properties": {
    "addr:full":"745 State Rte 3 Rutherford NJ 07070",
    "addr:housenumber":"745",
    "addr:postcode":"07070",
    "addr:street":"State Rte 3",
    "iso:country":"US",
    "sg:address":"745 State Rte 3",
    "sg:city":"Rutherford",
    "sg:classifiers":[
        {
            "category":"Banks & Credit Unions",
            "subcategory":"Bank",
            "type":"Services"
        }
    ],
    "sg:phone":"+1   ",
    "sg:postcode":"07070",
    "sg:province":"NJ",
    "sg:tags":[
        "security",
        "institution",
        "business"
    ],
    "wof:name":"Citicorp",
    "wof:placetype":"venue"
},
  "geometry": {"coordinates":[-74.09593,40.81048],"type":"Point"}
}