{
  "type": "Feature",
  "properties": {
    "addr:full":"142 Casterline Rd Denville NJ 07834",
    "addr:housenumber":"142",
    "addr:postcode":"07834",
    "addr:street":"Casterline Rd",
    "iso:country":"US",
    "sg:address":"142 Casterline Rd",
    "sg:city":"Denville",
    "sg:classifiers":[
        {
            "category":"Building & Trades",
            "subcategory":"Construction",
            "type":"Services"
        }
    ],
    "sg:phone":"+1 973 537 9100",
    "sg:postcode":"07834",
    "sg:province":"NJ",
    "sg:tags":[
        "house"
    ],
    "wof:name":"Eagle Builders & Contractors",
    "wof:placetype":"venue"
},
  "geometry": {"coordinates":[-74.516637,40.852736],"type":"Point"}
}