{
  "type": "Feature",
  "properties": {
    "iso:country":"US",
    "sg:address":"387 Maple St",
    "sg:city":"New Providence",
    "sg:classifiers":[
        {
            "category":"Education",
            "subcategory":"Preschool",
            "type":"Public Place"
        },
        {
            "category":"Education",
            "subcategory":"School",
            "type":"Public Place"
        }
    ],
    "sg:phone":"+1 908 461 3311",
    "sg:postcode":"07974",
    "sg:province":"NJ",
    "sg:tags":[
        "elementary"
    ],
    "wof:name":"Josa Nursery School Inc",
    "wof:placetype":"venue"
},
  "geometry": {"coordinates":[-74.38800000000001,40.696201],"type":"Point"}
}