{
  "type": "Feature",
  "properties": {
    "addr:full":"29 William St Belleville NJ 07109",
    "addr:housenumber":"29",
    "addr:postcode":"07109",
    "addr:street":"William St",
    "iso:country":"US",
    "sg:address":"29 William St",
    "sg:city":"Belleville",
    "sg:classifiers":[
        {
            "category":"Real Estate",
            "subcategory":"Developer",
            "type":"Services"
        }
    ],
    "sg:phone":"+1 973 751 0616",
    "sg:postcode":"07109",
    "sg:province":"NJ",
    "sg:tags":[
        "cemetery"
    ],
    "sg:website":"www.christchurchbelleville.org",
    "wof:name":"Christ Church Cemetery",
    "wof:placetype":"venue"
},
  "geometry": {"coordinates":[-74.15078800000001,40.784429],"type":"Point"}
}