{
  "type": "Feature",
  "properties": {
    "addr:full":"24 Hogan Way Moorestown NJ 08057",
    "addr:housenumber":"24",
    "addr:postcode":"08057",
    "addr:street":"Hogan Way",
    "iso:country":"US",
    "sg:address":"24 Hogan Way",
    "sg:city":"Moorestown",
    "sg:classifiers":[
        {
            "category":"Professional",
            "subcategory":"Management & Consulting",
            "type":"Services"
        }
    ],
    "sg:phone":"+1 856 234 4334",
    "sg:postcode":"08057",
    "sg:province":"NJ",
    "sg:tags":[
        "marketing",
        "consultant"
    ],
    "wof:name":"H T M Lawyers Inc",
    "wof:placetype":"venue"
},
  "geometry": {"coordinates":[-74.901729,39.984245],"type":"Point"}
}