{
  "type": "Feature",
  "properties": {
    "iso:country":"US",
    "sg:address":"7317 Broadway",
    "sg:city":"North Bergen",
    "sg:classifiers":[
        {
            "category":"Shopping",
            "subcategory":"Jewelry",
            "type":"Retail Goods"
        }
    ],
    "sg:phone":"+1 201 868 5404",
    "sg:postcode":"07047",
    "sg:province":"NJ",
    "sg:tags":[
        "jeweler"
    ],
    "wof:name":"Gold & Siver Concepts",
    "wof:placetype":"venue"
},
  "geometry": {"coordinates":[-74.003998,40.7957],"type":"Point"}
}