{
  "type": "Feature",
  "properties": {
    "iso:country":"US",
    "sg:address":"4 Marc Ln",
    "sg:city":"Brigantine",
    "sg:classifiers":[
        {
            "category":"Professional",
            "type":"Services"
        }
    ],
    "sg:phone":"+1   ",
    "sg:postcode":"08203",
    "sg:province":"NJ",
    "wof:name":"L A White Inc",
    "wof:placetype":"venue"
},
  "geometry": {"coordinates":[-74.394834,39.392291],"type":"Point"}
}