{
  "type": "Feature",
  "properties": {
    "iso:country":"US",
    "sg:address":"200 Morris Ave",
    "sg:city":"Denville",
    "sg:classifiers":[
        {
            "category":"Education",
            "subcategory":"School",
            "type":"Public Place"
        }
    ],
    "sg:phone":"+1   ",
    "sg:postcode":"07834",
    "sg:province":"NJ",
    "wof:name":"Morris Catholic High School",
    "wof:placetype":"venue"
},
  "geometry": {"coordinates":[-74.488637,40.9038],"type":"Point"}
}