{
  "type": "Feature",
  "properties": {
    "addr:full":"577 E County Line Rd Lakewood NJ 08701",
    "addr:housenumber":"577",
    "addr:postcode":"08701",
    "addr:street":"E County Line Rd",
    "iso:country":"US",
    "sg:address":"577 E County Line Rd",
    "sg:city":"Lakewood",
    "sg:classifiers":[
        {
            "category":"Retail",
            "subcategory":"Auto Repair",
            "type":"Services"
        }
    ],
    "sg:phone":"+1 732 363 2085",
    "sg:postcode":"08701",
    "sg:province":"NJ",
    "sg:tags":[
        "repairing",
        "automobile"
    ],
    "wof:name":"Barney's Tire",
    "wof:placetype":"venue"
},
  "geometry": {"coordinates":[-74.206694,40.105388],"type":"Point"}
}