{
  "type": "Feature",
  "properties": {
    "addr:full":"119 Woodbridge Ter Woodbridge NJ 07095",
    "addr:housenumber":"119",
    "addr:postcode":"07095",
    "addr:street":"Woodbridge Ter",
    "iso:country":"US",
    "sg:address":"119 Woodbridge Ter",
    "sg:city":"Woodbridge",
    "sg:classifiers":[
        {
            "category":"Shopping",
            "subcategory":"Clothing, Apparel, & Fashions",
            "type":"Retail Goods"
        }
    ],
    "sg:phone":"+1 732 636 2361",
    "sg:postcode":"07095",
    "sg:province":"NJ",
    "sg:tags":[
        "sportswear"
    ],
    "wof:name":"American Eagle Outfitters",
    "wof:placetype":"venue"
},
  "geometry": {"coordinates":[-74.30369,40.553691],"type":"Point"}
}