{
  "type": "Feature",
  "properties": {
    "addr:full":"1150 Ocean Ave Ste 1 Lakewood NJ 08701",
    "addr:housenumber":"1150",
    "addr:postcode":"08701",
    "addr:street":"Ocean Ave Ste 1",
    "iso:country":"US",
    "sg:address":"1150 Ocean Ave Ste 1",
    "sg:city":"Lakewood",
    "sg:classifiers":[
        {
            "category":"Autos & Motor Vehicles",
            "subcategory":"Automobile Sales",
            "type":"Retail Goods"
        },
        {
            "category":"Wholesale",
            "subcategory":"Farm Supplies",
            "type":"Manufacturing & Wholesale Goods"
        }
    ],
    "sg:phone":"+1 732 363 8100",
    "sg:postcode":"08701",
    "sg:province":"NJ",
    "sg:tags":[
        "car",
        "trailer",
        "transport",
        "tractor",
        "new"
    ],
    "sg:website":"http://www.fordvehicles.com",
    "wof:name":"Larson Ford Suzuki",
    "wof:placetype":"venue"
},
  "geometry": {"coordinates":[-74.170687,40.082864],"type":"Point"}
}