{
  "type": "Feature",
  "properties": {
    "addr:full":"8 High St E Glassboro NJ 08028",
    "addr:housenumber":"8",
    "addr:postcode":"08028",
    "addr:street":"High St E",
    "iso:country":"US",
    "sg:address":"8 High St E",
    "sg:city":"Glassboro",
    "sg:classifiers":[
        {
            "category":"Wholesale",
            "subcategory":"Machinery & Supplies",
            "type":"Manufacturing & Wholesale Goods"
        }
    ],
    "sg:phone":"+1 856 863 3712",
    "sg:postcode":"08028",
    "sg:province":"NJ",
    "sg:tags":[
        "equipment",
        "establishment"
    ],
    "wof:name":"Sunpay Beauty Supply",
    "wof:placetype":"venue"
},
  "geometry": {"coordinates":[-75.111052,39.702477],"type":"Point"}
}