{
  "type": "Feature",
  "properties": {
    "addr:full":"1030 West Marlton Pike Cherry Hill NJ 08002",
    "addr:housenumber":"1030",
    "addr:postcode":"08002",
    "addr:street":"West Marlton Pike",
    "iso:country":"US",
    "sg:address":"1030 West Marlton Pike",
    "sg:city":"Cherry Hill",
    "sg:classifiers":[
        {
            "category":"Food & Beverages",
            "subcategory":"Groceries & Convenience Stores",
            "type":"Retail Goods"
        }
    ],
    "sg:phone":"+1 856 429 1202",
    "sg:postcode":"08002",
    "sg:province":"NJ",
    "sg:website":"www.wawa.com",
    "wof:name":"WaWa",
    "wof:placetype":"venue"
},
  "geometry": {"coordinates":[-75.023568,39.91643],"type":"Point"}
}