{
  "type": "Feature",
  "properties": {
    "iso:country":"US",
    "sg:address":"48 Little Silver Point Rd",
    "sg:city":"Little Silver",
    "sg:classifiers":[
        {
            "category":"Building & Trades",
            "subcategory":"Construction",
            "type":"Services"
        }
    ],
    "sg:phone":"+1 732 842 7424",
    "sg:postcode":"07739",
    "sg:province":"NJ",
    "sg:tags":[
        "carpentry",
        "contractor"
    ],
    "wof:name":"Richard Foster Carpentry",
    "wof:placetype":"venue"
},
  "geometry": {"coordinates":[-74.039091,40.330129],"type":"Point"}
}