{
  "type": "Feature",
  "properties": {
    "iso:country":"US",
    "sg:address":"1238 Stuyvesant Ave",
    "sg:city":"Union",
    "sg:classifiers":[
        {
            "category":"Real Estate",
            "subcategory":"Real Estate Agent",
            "type":"Services"
        }
    ],
    "sg:phone":"+1 908 810 8102",
    "sg:postcode":"07083",
    "sg:province":"NJ",
    "wof:name":"Investors Realty",
    "wof:placetype":"venue"
},
  "geometry": {"coordinates":[-74.266762,40.698387],"type":"Point"}
}