{
  "type": "Feature",
  "properties": {
    "addr:full":"49 Barkalow St South Amboy NJ 08879",
    "addr:housenumber":"49",
    "addr:postcode":"08879",
    "addr:street":"Barkalow St",
    "iso:country":"US",
    "sg:address":"49 Barkalow St",
    "sg:city":"South Amboy",
    "sg:classifiers":[
        {
            "category":"Building & Trades",
            "subcategory":"Construction",
            "type":"Services"
        }
    ],
    "sg:phone":"+1 732 727 7408",
    "sg:postcode":"08879",
    "sg:province":"NJ",
    "sg:tags":[
        "floor",
        "laying",
        "contractor"
    ],
    "wof:name":"Dannys Carpet Service Inc",
    "wof:placetype":"venue"
},
  "geometry": {"coordinates":[-74.28668999999999,40.487653],"type":"Point"}
}