{
  "type": "Feature",
  "properties": {
    "addr:full":"26 Raymond Ln Belle Mead NJ 08502",
    "addr:housenumber":"26",
    "addr:postcode":"08502",
    "addr:street":"Raymond Ln Belle Mead",
    "iso:country":"US",
    "sg:address":"26 Raymond Ln",
    "sg:city":"Belle Mead",
    "sg:classifiers":[
        {
            "category":"Home & Garden",
            "subcategory":"Home Furnishings",
            "type":"Retail Goods"
        }
    ],
    "sg:phone":"+1 908 874 5002",
    "sg:postcode":"08502",
    "sg:province":"NJ",
    "sg:tags":[
        "curtain",
        "made",
        "drapery"
    ],
    "wof:name":"Interiors Plus",
    "wof:placetype":"venue"
},
  "geometry": {"coordinates":[-74.67365599999999,40.44778],"type":"Point"}
}