{
  "type": "Feature",
  "properties": {
    "iso:country":"US",
    "sg:address":"67 N Main St",
    "sg:city":"Wharton",
    "sg:classifiers":[
        {
            "category":"Retail",
            "subcategory":"Car Wash",
            "type":"Services"
        }
    ],
    "sg:phone":"+1 973 328 0067",
    "sg:postcode":"07885",
    "sg:province":"NJ",
    "sg:tags":[
        "automobile",
        "detail",
        "clean"
    ],
    "wof:name":"Priority Towing",
    "wof:placetype":"venue"
},
  "geometry": {"coordinates":[-74.581506,40.901457],"type":"Point"}
}