{
  "type": "Feature",
  "properties": {
    "addr:full":"470 Prospect Ave Ste 100 West Orange NJ 07052",
    "addr:housenumber":"470",
    "addr:postcode":"07052",
    "addr:street":"Prospect Ave Ste 100",
    "iso:country":"US",
    "sg:address":"470 Prospect Ave Ste 100",
    "sg:city":"West Orange",
    "sg:classifiers":[
        {
            "category":"Health Services",
            "subcategory":"Health Practitioner",
            "type":"Services"
        }
    ],
    "sg:phone":"+1 973 731 7877",
    "sg:postcode":"07052",
    "sg:province":"NJ",
    "sg:tags":[
        "therapy",
        "physical"
    ],
    "wof:name":"Legaspi Owen Dpt",
    "wof:placetype":"venue"
},
  "geometry": {"coordinates":[-74.25467500000001,40.791103],"type":"Point"}
}