{
  "type": "Feature",
  "properties": {
    "iso:country":"US",
    "sg:address":"251 Benigno Blvd",
    "sg:city":"Bellmawr",
    "sg:classifiers":[
        {
            "category":"Professional",
            "subcategory":"Business Services",
            "type":"Services"
        }
    ],
    "sg:phone":"+1   ",
    "sg:postcode":"08031",
    "sg:province":"NJ",
    "wof:name":"Jessmar Holding Inc",
    "wof:placetype":"venue"
},
  "geometry": {"coordinates":[-75.088449,39.861123],"type":"Point"}
}