{
  "type": "Feature",
  "properties": {
    "addr:full":"644 Bamford Rd Cherry Hill NJ 08003",
    "addr:housenumber":"644",
    "addr:postcode":"08003",
    "addr:street":"Bamford Rd",
    "iso:country":"US",
    "sg:address":"644 Bamford Rd",
    "sg:city":"Cherry Hill",
    "sg:classifiers":[
        {
            "category":"Professional",
            "subcategory":"Management & Consulting",
            "type":"Services"
        }
    ],
    "sg:phone":"+1 856 424 6421",
    "sg:postcode":"08003",
    "sg:province":"NJ",
    "sg:tags":[
        "business"
    ],
    "wof:name":"Resource Enterprises",
    "wof:placetype":"venue"
},
  "geometry": {"coordinates":[-74.93976600000001,39.890367],"type":"Point"}
}