{
  "type": "Feature",
  "properties": {
    "addr:full":"335 George St New Brunswick NJ 08901",
    "addr:housenumber":"335",
    "addr:postcode":"08901",
    "addr:street":"George St",
    "iso:country":"US",
    "sg:address":"335 George St",
    "sg:city":"New Brunswick",
    "sg:classifiers":[
        {
            "category":"Shopping",
            "subcategory":"Clothing, Apparel, & Fashions",
            "type":"Retail Goods"
        }
    ],
    "sg:phone":"+1   ",
    "sg:postcode":"08901",
    "sg:province":"NJ",
    "wof:name":"Opitical Boutique",
    "wof:placetype":"venue"
},
  "geometry": {"coordinates":[-74.44360500000001,40.494329],"type":"Point"}
}