{
  "type": "Feature",
  "properties": {
    "addr:full":"281 Browertown Rd Ste 102 West Paterson NJ 07424",
    "addr:housenumber":"281",
    "addr:postcode":"07424",
    "addr:street":"Browertown Rd Ste 102 West",
    "iso:country":"US",
    "sg:address":"281 Browertown Rd Ste 102",
    "sg:city":"West Paterson",
    "sg:classifiers":[
        {
            "category":"Personal",
            "subcategory":"Tanning Parlor",
            "type":"Services"
        }
    ],
    "sg:phone":"+1 973 256 8760",
    "sg:postcode":"07424",
    "sg:province":"NJ",
    "wof:name":"Heat-Wave Tanning Salon",
    "wof:placetype":"venue"
},
  "geometry": {"coordinates":[-74.20500199999999,40.888199],"type":"Point"}
}