{
  "type": "Feature",
  "properties": {
    "iso:country":"US",
    "sg:address":"736 E Village Dr",
    "sg:city":"Absecon",
    "sg:classifiers":[
        {
            "category":"Professional",
            "subcategory":"Management & Consulting",
            "type":"Services"
        },
        {
            "category":"Professional",
            "subcategory":"Advertising",
            "type":"Services"
        }
    ],
    "sg:phone":"+1 609 748 4850",
    "sg:postcode":"08205",
    "sg:province":"NJ",
    "sg:tags":[
        "counselor",
        "public",
        "relations"
    ],
    "wof:name":"Publicity Pros Inc",
    "wof:placetype":"venue"
},
  "geometry": {"coordinates":[-74.47260300000001,39.444099],"type":"Point"}
}