{
  "type": "Feature",
  "properties": {
    "iso:country":"US",
    "sg:address":"1201 W Brigantine Ave",
    "sg:city":"Brigantine",
    "sg:classifiers":[
        {
            "category":"Real Estate",
            "subcategory":"Real Estate Agent",
            "type":"Services"
        }
    ],
    "sg:phone":"+1   ",
    "sg:postcode":"08203",
    "sg:province":"NJ",
    "sg:tags":[
        "agency"
    ],
    "wof:name":"Re/Max",
    "wof:placetype":"venue"
},
  "geometry": {"coordinates":[-74.372089,39.402311],"type":"Point"}
}