{
  "type": "Feature",
  "properties": {
    "addr:full":"92 Railroad Ave Hasbrouck Hts NJ 07604",
    "addr:housenumber":"92",
    "addr:postcode":"07604",
    "addr:street":"Railroad Ave",
    "iso:country":"US",
    "sg:address":"92 Railroad Ave",
    "sg:city":"Hasbrouck Hts",
    "sg:classifiers":[
        {
            "category":"Autos & Motor Vehicles",
            "subcategory":"Automobile Sales",
            "type":"Retail Goods"
        }
    ],
    "sg:phone":"+1 201 288 4333",
    "sg:postcode":"07604",
    "sg:province":"NJ",
    "sg:tags":[
        "car",
        "dealer"
    ],
    "wof:name":"Nesub Auto Sales LLC",
    "wof:placetype":"venue"
},
  "geometry": {"coordinates":[-74.069762,40.854912],"type":"Point"}
}