{
  "type": "Feature",
  "properties": {
    "iso:country":"US",
    "sg:address":"750 Fox Run Rd",
    "sg:city":"Sewell",
    "sg:classifiers":[
        {
            "category":"Freight",
            "type":"Transportation"
        }
    ],
    "sg:phone":"+1 856 468 7747",
    "sg:postcode":"08096",
    "sg:province":"NJ",
    "sg:tags":[
        "commercial",
        "storage"
    ],
    "wof:name":"Fox Run Self Storage",
    "wof:placetype":"venue"
},
  "geometry": {"coordinates":[-75.115345,39.79999],"type":"Point"}
}