{
  "type": "Feature",
  "properties": {
    "iso:country":"US",
    "sg:address":"1040 Grand St",
    "sg:city":"Hoboken",
    "sg:classifiers":[
        {
            "category":"Retail",
            "subcategory":"Storage",
            "type":"Services"
        },
        {
            "category":"Manufacturing",
            "subcategory":"Paper Products",
            "type":"Manufacturing & Wholesale Goods"
        }
    ],
    "sg:phone":"+1 201 659 0700",
    "sg:postcode":"07030",
    "sg:province":"NJ",
    "sg:tags":[
        "fiber",
        "automobile",
        "household",
        "commercial",
        "boxes-corrugated",
        "self",
        "boat"
    ],
    "sg:website":"http://www.ustoreit.com/?utm_source=yellowpages&utm_medium=premium&utm_campaign=yp2010&phid=0437",
    "wof:name":"U-Store-It",
    "wof:placetype":"venue"
},
  "geometry": {"coordinates":[-74.03282799999999,40.750034],"type":"Point"}
}