{
  "type": "Feature",
  "properties": {
    "iso:country":"US",
    "sg:address":"2 North Rd",
    "sg:city":"Warren",
    "sg:classifiers":[
        {
            "category":"Real Estate",
            "subcategory":"Real Estate Agent",
            "type":"Services"
        }
    ],
    "sg:phone":"+1 732 356 0413",
    "sg:postcode":"07059",
    "sg:province":"NJ",
    "wof:name":"First Nj Realty Inc",
    "wof:placetype":"venue"
},
  "geometry": {"coordinates":[-74.501391,40.61569],"type":"Point"}
}