{
  "type": "Feature",
  "properties": {
    "iso:country":"US",
    "sg:address":"484 Kearny Ave",
    "sg:city":"Kearny",
    "sg:classifiers":[
        {
            "category":"Education",
            "subcategory":"Music School",
            "type":"Public Place"
        }
    ],
    "sg:phone":"+1 201 991 3334",
    "sg:postcode":"07032",
    "sg:province":"NJ",
    "sg:tags":[
        "instrument",
        "teacher",
        "musical"
    ],
    "wof:name":"Paz Music Center",
    "wof:placetype":"venue"
},
  "geometry": {"coordinates":[-74.146896,40.7668],"type":"Point"}
}