{
  "type": "Feature",
  "properties": {
    "iso:country":"US",
    "sg:address":"21 Piermont Rd",
    "sg:city":"Closter",
    "sg:classifiers":[
        {
            "category":"Wholesale",
            "subcategory":"Auto Parts",
            "type":"Manufacturing & Wholesale Goods"
        }
    ],
    "sg:phone":"+1 201 768 6112",
    "sg:postcode":"07624",
    "sg:province":"NJ",
    "sg:tags":[
        "equipment",
        "product",
        "supply",
        "wash",
        "car"
    ],
    "wof:name":"Crystal Care Industries Inc",
    "wof:placetype":"venue"
},
  "geometry": {"coordinates":[-73.94266500000001,40.981119],"type":"Point"}
}