{
  "type": "Feature",
  "properties": {
    "addr:full":"691 US Hwy 1 Edison NJ 08817",
    "addr:housenumber":"691",
    "addr:postcode":"08817",
    "addr:street":"Us Hwy 1",
    "iso:country":"US",
    "sg:address":"691 US Hwy 1",
    "sg:city":"Edison",
    "sg:classifiers":[
        {
            "category":"Restaurant",
            "type":"Food & Drink"
        }
    ],
    "sg:phone":"+1 732 819 9110",
    "sg:postcode":"08817",
    "sg:province":"NJ",
    "wof:name":"Delhi Garden",
    "wof:placetype":"venue"
},
  "geometry": {"coordinates":[-74.390947,40.508293],"type":"Point"}
}