{
  "type": "Feature",
  "properties": {
    "iso:country":"US",
    "sg:address":"1901 N Ocean Ave",
    "sg:city":"Seaside Park",
    "sg:classifiers":[
        {
            "category":"Parking",
            "type":"Transportation"
        }
    ],
    "sg:phone":"+1 732 793 4506",
    "sg:postcode":"08752",
    "sg:province":"NJ",
    "sg:tags":[
        "attendant"
    ],
    "wof:name":"Stu's Parking Lot",
    "wof:placetype":"venue"
},
  "geometry": {"coordinates":[-74.072158,39.93691],"type":"Point"}
}