{
  "type": "Feature",
  "properties": {
    "iso:country":"US",
    "sg:address":"28 Wintermute Rd",
    "sg:city":"Newton",
    "sg:classifiers":[
        {
            "category":"Retail",
            "subcategory":"Repair Shop",
            "type":"Services"
        }
    ],
    "sg:phone":"+1   ",
    "sg:postcode":"07860",
    "sg:province":"NJ",
    "wof:name":"Hammer & Tack Upholstery Shop",
    "wof:placetype":"venue"
},
  "geometry": {"coordinates":[-74.84176600000001,40.984641],"type":"Point"}
}