{
  "type": "Feature",
  "properties": {
    "iso:country":"US",
    "sg:address":"110 Harmon Dr",
    "sg:city":"Blackwood",
    "sg:classifiers":[
        {
            "category":"Building & Trades",
            "subcategory":"Landscaping Services",
            "type":"Services"
        }
    ],
    "sg:phone":"+1 856 228 8838",
    "sg:postcode":"08012",
    "sg:province":"NJ",
    "sg:tags":[
        "designer",
        "landscape"
    ],
    "wof:name":"Stb Customs Landscape Designs",
    "wof:placetype":"venue"
},
  "geometry": {"coordinates":[-75.072114,39.832089],"type":"Point"}
}