{
  "type": "Feature",
  "properties": {
    "addr:full":"3 Larson Ct Clifton NJ 07011",
    "addr:housenumber":"3",
    "addr:postcode":"07011",
    "addr:street":"Larson Ct",
    "iso:country":"US",
    "sg:address":"3 Larson Ct",
    "sg:city":"Clifton",
    "sg:classifiers":[
        {
            "category":"Building & Trades",
            "subcategory":"Construction",
            "type":"Services"
        }
    ],
    "sg:phone":"+1 973 478 3095",
    "sg:postcode":"07011",
    "sg:province":"NJ",
    "sg:tags":[
        "hanging",
        "contractor"
    ],
    "wof:name":"Wilbers Painting",
    "wof:placetype":"venue"
},
  "geometry": {"coordinates":[-74.142076,40.877295],"type":"Point"}
}