{
  "type": "Feature",
  "properties": {
    "addr:full":"7 Roberta Dr Middletown NJ 07748",
    "addr:housenumber":"7",
    "addr:postcode":"07748",
    "addr:street":"Roberta Dr",
    "iso:country":"US",
    "sg:address":"7 Roberta Dr",
    "sg:city":"Middletown",
    "sg:classifiers":[
        {
            "category":"Food & Beverages",
            "subcategory":"Fruits & Vegetables",
            "type":"Retail Goods"
        }
    ],
    "sg:phone":"+1   ",
    "sg:postcode":"07748",
    "sg:province":"NJ",
    "wof:name":"Pepper Tienda",
    "wof:placetype":"venue"
},
  "geometry": {"coordinates":[-74.123965,40.411263],"type":"Point"}
}