{
  "type": "Feature",
  "properties": {
    "addr:full":"1049 Raritan Rd Clark NJ 07066",
    "addr:housenumber":"1049",
    "addr:postcode":"07066",
    "addr:street":"Raritan Rd",
    "iso:country":"US",
    "sg:address":"1049 Raritan Rd",
    "sg:city":"Clark",
    "sg:classifiers":[
        {
            "category":"Communications",
            "type":"Services"
        }
    ],
    "sg:phone":"+1 732 669 1049",
    "sg:postcode":"07066",
    "sg:province":"NJ",
    "sg:tags":[
        "communication"
    ],
    "wof:name":"Unlimited Communication III",
    "wof:placetype":"venue"
},
  "geometry": {"coordinates":[-74.31417999999999,40.628424],"type":"Point"}
}