{
  "type": "Feature",
  "properties": {
    "iso:country":"US",
    "sg:address":"323 Broad St",
    "sg:city":"Carlstadt",
    "sg:classifiers":[
        {
            "category":"Food & Beverages",
            "subcategory":"Groceries & Convenience Stores",
            "type":"Retail Goods"
        },
        {
            "category":"Restaurant",
            "type":"Food & Drink"
        }
    ],
    "sg:phone":"+1 201 939 0248",
    "sg:postcode":"07072",
    "sg:province":"NJ",
    "sg:tags":[
        "delicatessen",
        "alcoholic"
    ],
    "wof:name":"Cobblestone Hill Deli Inc",
    "wof:placetype":"venue"
},
  "geometry": {"coordinates":[-74.088998,40.835919],"type":"Point"}
}