{
  "type": "Feature",
  "properties": {
    "iso:country":"US",
    "sg:address":"1 Runyons Ln",
    "sg:city":"Edison",
    "sg:classifiers":[
        {
            "category":"Professional",
            "subcategory":"Management & Consulting",
            "type":"Services"
        }
    ],
    "sg:phone":"+1 732 248 1500",
    "sg:postcode":"08817",
    "sg:province":"NJ",
    "sg:tags":[
        "marketing",
        "program"
    ],
    "sg:website":"www.gund.com",
    "wof:name":"Gund Inc",
    "wof:placetype":"venue"
},
  "geometry": {"coordinates":[-74.406685,40.546198],"type":"Point"}
}