{
  "type": "Feature",
  "properties": {
    "addr:full":"996 Stuyvesant Ave Union NJ 07083",
    "addr:housenumber":"996",
    "addr:postcode":"07083",
    "addr:street":"Stuyvesant Ave",
    "iso:country":"US",
    "sg:address":"996 Stuyvesant Ave",
    "sg:city":"Union",
    "sg:classifiers":[
        {
            "category":"Shopping",
            "subcategory":"Computers & Home Electronics",
            "type":"Retail Goods"
        }
    ],
    "sg:phone":"+1 908 624 9050",
    "sg:postcode":"07083",
    "sg:province":"NJ",
    "sg:tags":[
        "equipment",
        "dealer"
    ],
    "wof:name":"Main Gear",
    "wof:placetype":"venue"
},
  "geometry": {"coordinates":[-74.27023199999999,40.696098],"type":"Point"}
}