{
  "type": "Feature",
  "properties": {
    "iso:country":"US",
    "sg:address":"100 Orchard Ave",
    "sg:city":"Runnemede",
    "sg:classifiers":[
        {
            "category":"Education",
            "subcategory":"School",
            "type":"Public Place"
        }
    ],
    "sg:phone":"+1   ",
    "sg:postcode":"08078",
    "sg:province":"NJ",
    "sg:tags":[
        "executive"
    ],
    "wof:name":"Bingham Elementary School",
    "wof:placetype":"venue"
},
  "geometry": {"coordinates":[-75.079775,39.850767],"type":"Point"}
}