{
  "type": "Feature",
  "properties": {
    "iso:country":"US",
    "sg:address":"822 S 5th St",
    "sg:city":"Camden",
    "sg:classifiers":[
        {
            "category":"Deli",
            "type":"Food & Drink"
        },
        {
            "category":"Food & Beverages",
            "subcategory":"Bakery",
            "type":"Retail Goods"
        }
    ],
    "sg:phone":"+1 856 966 0238",
    "sg:postcode":"08103",
    "sg:province":"NJ",
    "sg:tags":[
        "sandwich"
    ],
    "wof:name":"South 5th Street Deli",
    "wof:placetype":"venue"
},
  "geometry": {"coordinates":[-75.12069200000001,39.935686],"type":"Point"}
}