{
  "type": "Feature",
  "properties": {
    "iso:country":"US",
    "sg:address":"350 Palisade Ave",
    "sg:city":"Bogota",
    "sg:classifiers":[
        {
            "category":"Restaurant",
            "type":"Food & Drink"
        }
    ],
    "sg:phone":"+1 201 968 9777",
    "sg:postcode":"07603",
    "sg:province":"NJ",
    "wof:name":"Goldi Luck Inc",
    "wof:placetype":"venue"
},
  "geometry": {"coordinates":[-74.024902,40.8773],"type":"Point"}
}