{
  "type": "Feature",
  "properties": {
    "addr:full":"138 N Central Ave Ramsey NJ 07446",
    "addr:housenumber":"138",
    "addr:postcode":"07446",
    "addr:street":"N Central Ave",
    "iso:country":"US",
    "sg:address":"138 N Central Ave",
    "sg:city":"Ramsey",
    "sg:classifiers":[
        {
            "category":"Real Estate",
            "subcategory":"Real Estate Operator",
            "type":"Services"
        }
    ],
    "sg:phone":"+1   ",
    "sg:postcode":"07446",
    "sg:province":"NJ",
    "sg:tags":[
        "building",
        "nonresidential"
    ],
    "wof:name":"Ramsey Stores Inc",
    "wof:placetype":"venue"
},
  "geometry": {"coordinates":[-74.14664399999999,41.063428],"type":"Point"}
}