{
  "type": "Feature",
  "properties": {
    "iso:country":"US",
    "sg:address":"576 River St",
    "sg:city":"Paterson",
    "sg:classifiers":[
        {
            "category":"Travel",
            "subcategory":"Travel Agent",
            "type":"Entertainment"
        }
    ],
    "sg:phone":"+1 973 278 9200",
    "sg:postcode":"07524",
    "sg:province":"NJ",
    "sg:tags":[
        "agency",
        "bureau"
    ],
    "wof:name":"Europa Travel & Immigration",
    "wof:placetype":"venue"
},
  "geometry": {"coordinates":[-74.15716399999999,40.933021],"type":"Point"}
}