{
  "type": "Feature",
  "properties": {
    "iso:country":"US",
    "sg:address":"335 Union Ave",
    "sg:city":"Rutherford",
    "sg:classifiers":[
        {
            "category":"Wholesale",
            "subcategory":"Furniture",
            "type":"Manufacturing & Wholesale Goods"
        }
    ],
    "sg:phone":"+1 201 939 0510",
    "sg:postcode":"07070",
    "sg:province":"NJ",
    "wof:name":"Thomas Printing & Office",
    "wof:placetype":"venue"
},
  "geometry": {"coordinates":[-74.11361599999999,40.836035],"type":"Point"}
}