{
  "type": "Feature",
  "properties": {
    "addr:full":"134 Howard Ave South Bound Brook NJ 08880",
    "addr:housenumber":"134",
    "addr:postcode":"08880",
    "addr:street":"Howard Ave",
    "iso:country":"US",
    "sg:address":"134 Howard Ave",
    "sg:city":"South Bound Brook",
    "sg:classifiers":[
        {
            "category":"Professional",
            "type":"Services"
        }
    ],
    "sg:phone":"+1   ",
    "sg:postcode":"08880",
    "sg:province":"NJ",
    "wof:name":"Artpoint LLC",
    "wof:placetype":"venue"
},
  "geometry": {"coordinates":[-74.539939,40.555317],"type":"Point"}
}