{
  "type": "Feature",
  "properties": {
    "iso:country":"US",
    "sg:address":"498 E 30th St",
    "sg:city":"Paterson",
    "sg:classifiers":[
        {
            "category":"Banks & Credit Unions",
            "subcategory":"Bank",
            "type":"Services"
        }
    ],
    "sg:phone":"+1   ",
    "sg:postcode":"07504",
    "sg:province":"NJ",
    "sg:tags":[
        "state",
        "commercial"
    ],
    "wof:name":"Fleet",
    "wof:placetype":"venue"
},
  "geometry": {"coordinates":[-74.14651499999999,40.910314],"type":"Point"}
}