{
  "type": "Feature",
  "properties": {
    "addr:full":"Berlin Cross Keys Rd Sicklerville NJ 08081",
    "addr:postcode":"08081",
    "addr:street":"Berlin Cross Keys Rd",
    "iso:country":"US",
    "sg:address":"Berlin Cross Keys Rd",
    "sg:city":"Sicklerville",
    "sg:classifiers":[
        {
            "category":"Education",
            "subcategory":"School",
            "type":"Public Place"
        }
    ],
    "sg:phone":"+1 856 767 7000",
    "sg:postcode":"08081",
    "sg:province":"NJ",
    "sg:tags":[
        "high",
        "middle",
        "elementary"
    ],
    "wof:name":"Camden County Technical School",
    "wof:placetype":"venue"
},
  "geometry": {"coordinates":[-74.980103,39.740898],"type":"Point"}
}