{
  "type": "Feature",
  "properties": {
    "addr:full":"1202 Mindy Ln Piscataway NJ 08854",
    "addr:housenumber":"1202",
    "addr:postcode":"08854",
    "addr:street":"Mindy Ln",
    "iso:country":"US",
    "sg:address":"1202 Mindy Ln",
    "sg:city":"Piscataway",
    "sg:classifiers":[
        {
            "category":"Building & Trades",
            "subcategory":"Cleaning & Sanitation",
            "type":"Services"
        }
    ],
    "sg:phone":"+1   ",
    "sg:postcode":"08854",
    "sg:province":"NJ",
    "sg:tags":[
        "maintenance"
    ],
    "wof:name":"AJS Cleaning Services",
    "wof:placetype":"venue"
},
  "geometry": {"coordinates":[-74.41777399999999,40.528783],"type":"Point"}
}