{
  "type": "Feature",
  "properties": {
    "iso:country":"US",
    "sg:address":"686 Oak Tree Rd",
    "sg:city":"South Plainfield",
    "sg:classifiers":[
        {
            "category":"Professional",
            "subcategory":"Management & Consulting",
            "type":"Services"
        }
    ],
    "sg:phone":"+1 908 226 0199",
    "sg:postcode":"07080",
    "sg:province":"NJ",
    "sg:tags":[
        "fuel"
    ],
    "wof:name":"Skyline Management Corp",
    "wof:placetype":"venue"
},
  "geometry": {"coordinates":[-74.39322799999999,40.577435],"type":"Point"}
}