{
  "type": "Feature",
  "properties": {
    "addr:full":"626 Washington Ave Vineland NJ 08360",
    "addr:housenumber":"626",
    "addr:postcode":"08360",
    "addr:street":"Washington Ave",
    "iso:country":"US",
    "sg:address":"626 Washington Ave",
    "sg:city":"Vineland",
    "sg:classifiers":[
        {
            "category":"Organizations",
            "subcategory":"Community Association",
            "type":"Services"
        }
    ],
    "sg:phone":"+1   ",
    "sg:postcode":"08360",
    "sg:province":"NJ",
    "sg:tags":[
        "drinking"
    ],
    "wof:name":"Recreation Club",
    "wof:placetype":"venue"
},
  "geometry": {"coordinates":[-75.02233200000001,39.476939],"type":"Point"}
}