{
  "type": "Feature",
  "properties": {
    "addr:full":"608 Englishtown Rd Monroe Twp NJ 08831",
    "addr:housenumber":"608",
    "addr:postcode":"08831",
    "addr:street":"Englishtown Rd",
    "iso:country":"US",
    "sg:address":"608 Englishtown Rd",
    "sg:city":"Monroe Twp",
    "sg:classifiers":[
        {
            "category":"Recreation",
            "type":"Entertainment"
        }
    ],
    "sg:phone":"+1 732 656 4553",
    "sg:postcode":"08831",
    "sg:province":"NJ",
    "sg:tags":[
        "instruction",
        "golf"
    ],
    "wof:name":"Dayton Golf Learning Ctr",
    "wof:placetype":"venue"
},
  "geometry": {"coordinates":[-74.360986,40.330549],"type":"Point"}
}