{
  "type": "Feature",
  "properties": {
    "addr:full":"100 Gaither Dr Mount Laurel NJ 08054",
    "addr:housenumber":"100",
    "addr:postcode":"08054",
    "addr:street":"Gaither Dr",
    "iso:country":"US",
    "sg:address":"100 Gaither Dr",
    "sg:city":"Mount Laurel",
    "sg:classifiers":[
        {
            "category":"Professional",
            "subcategory":"Computer Services",
            "type":"Services"
        }
    ],
    "sg:phone":"+1 856 222 9000",
    "sg:postcode":"08054",
    "sg:province":"NJ",
    "wof:name":"One Call Communications",
    "wof:placetype":"venue"
},
  "geometry": {"coordinates":[-74.95654999999999,39.937239],"type":"Point"}
}