{
  "type": "Feature",
  "properties": {
    "iso:country":"US",
    "sg:address":"46 Windfall Ln",
    "sg:city":"Marlboro",
    "sg:classifiers":[
        {
            "category":"Professional",
            "subcategory":"Management & Consulting",
            "type":"Services"
        },
        {
            "category":"Professional",
            "subcategory":"Computer Services",
            "type":"Services"
        }
    ],
    "sg:phone":"+1 732 617 1499",
    "sg:postcode":"07746",
    "sg:province":"NJ",
    "sg:tags":[
        "marketing",
        "related",
        "consultant"
    ],
    "sg:website":"www.advinfoserv.com",
    "wof:name":"Advanced Information Services",
    "wof:placetype":"venue"
},
  "geometry": {"coordinates":[-74.277485,40.317508],"type":"Point"}
}