{
  "type": "Feature",
  "properties": {
    "iso:country":"US",
    "sg:address":"37 Maolis Ave",
    "sg:city":"Bloomfield",
    "sg:classifiers":[
        {
            "category":"Professional",
            "subcategory":"Management & Consulting",
            "type":"Services"
        }
    ],
    "sg:phone":"+1 973 680 0441",
    "sg:postcode":"07003",
    "sg:province":"NJ",
    "sg:tags":[
        "public",
        "relations"
    ],
    "wof:name":"Brown & Partners",
    "wof:placetype":"venue"
},
  "geometry": {"coordinates":[-74.20411799999999,40.788608],"type":"Point"}
}