{
  "type": "Feature",
  "properties": {
    "addr:full":"141 Palisade Ave Garfield NJ 07026",
    "addr:housenumber":"141",
    "addr:postcode":"07026",
    "addr:street":"Palisade Ave",
    "iso:country":"US",
    "sg:address":"141 Palisade Ave",
    "sg:city":"Garfield",
    "sg:classifiers":[
        {
            "category":"Food & Beverages",
            "subcategory":"Groceries & Convenience Stores",
            "type":"Retail Goods"
        }
    ],
    "sg:phone":"+1 973 471 0940",
    "sg:postcode":"07026",
    "sg:province":"NJ",
    "sg:tags":[
        "grocer"
    ],
    "wof:name":"Family Deli & Groceries",
    "wof:placetype":"venue"
},
  "geometry": {"coordinates":[-74.108237,40.869704],"type":"Point"}
}