{
  "type": "Feature",
  "properties": {
    "addr:full":"133 Lancewood Ct Lakewood NJ 08701",
    "addr:housenumber":"133",
    "addr:postcode":"08701",
    "addr:street":"Lancewood Ct",
    "iso:country":"US",
    "sg:address":"133 Lancewood Ct",
    "sg:city":"Lakewood",
    "sg:classifiers":[
        {
            "category":"Professional",
            "subcategory":"Computer Services",
            "type":"Services"
        }
    ],
    "sg:phone":"+1 732 367 9380",
    "sg:postcode":"08701",
    "sg:province":"NJ",
    "sg:tags":[
        "datum",
        "publishing"
    ],
    "wof:name":"Lra Associates",
    "wof:placetype":"venue"
},
  "geometry": {"coordinates":[-74.225702,40.062653],"type":"Point"}
}