{
  "type": "Feature",
  "properties": {
    "addr:full":"8 Prescott Ct Basking Ridge NJ 07920",
    "addr:housenumber":"8",
    "addr:postcode":"07920",
    "addr:street":"Prescott Ct",
    "iso:country":"US",
    "sg:address":"8 Prescott Ct",
    "sg:city":"Basking Ridge",
    "sg:classifiers":[
        {
            "category":"Local Transit",
            "type":"Transportation"
        }
    ],
    "sg:phone":"+1 908 781 0200",
    "sg:postcode":"07920",
    "sg:province":"NJ",
    "sg:tags":[
        "passenger"
    ],
    "wof:name":"Limoges Limousines Inc",
    "wof:placetype":"venue"
},
  "geometry": {"coordinates":[-74.616866,40.653372],"type":"Point"}
}