{
  "type": "Feature",
  "properties": {
    "addr:full":"370 Atlantic City Blvd Bayville NJ 08721",
    "addr:housenumber":"370",
    "addr:postcode":"08721",
    "addr:street":"Atlantic City Blvd",
    "iso:country":"US",
    "sg:address":"370 Atlantic City Blvd",
    "sg:city":"Bayville",
    "sg:classifiers":[
        {
            "category":"Food & Beverages",
            "subcategory":"Liquor & Beverages",
            "type":"Retail Goods"
        }
    ],
    "sg:phone":"+1   ",
    "sg:postcode":"08721",
    "sg:province":"NJ",
    "sg:tags":[
        "tavern",
        "store",
        "package"
    ],
    "wof:name":"Friendlys Bar & Grill",
    "wof:placetype":"venue"
},
  "geometry": {"coordinates":[-74.157707,39.917995],"type":"Point"}
}