{
  "type": "Feature",
  "properties": {
    "addr:full":"309 Mount Laurel Rd Mt Laurel NJ 08054",
    "addr:housenumber":"309",
    "addr:postcode":"08054",
    "addr:street":"Mount Laurel Rd",
    "iso:country":"US",
    "sg:address":"309 Mount Laurel Rd",
    "sg:city":"Mt Laurel",
    "sg:classifiers":[
        {
            "category":"Building & Trades",
            "subcategory":"Electrical",
            "type":"Services"
        }
    ],
    "sg:phone":"+1 856 642 4024",
    "sg:postcode":"08054",
    "sg:province":"NJ",
    "sg:tags":[
        "electric",
        "contractor"
    ],
    "wof:name":"Egs Electrical",
    "wof:placetype":"venue"
},
  "geometry": {"coordinates":[-74.907419,39.945196],"type":"Point"}
}