{
  "type": "Feature",
  "properties": {
    "addr:full":"508 Bethel Ave Moorestown NJ 08057",
    "addr:housenumber":"508",
    "addr:postcode":"08057",
    "addr:street":"Bethel Ave",
    "iso:country":"US",
    "sg:address":"508 Bethel Ave",
    "sg:city":"Moorestown",
    "sg:classifiers":[
        {
            "category":"Retail",
            "subcategory":"Auto Repair",
            "type":"Services"
        }
    ],
    "sg:phone":"+1 856 866 9535",
    "sg:postcode":"08057",
    "sg:province":"NJ",
    "sg:tags":[
        "automotive"
    ],
    "wof:name":"Lemance Corporation",
    "wof:placetype":"venue"
},
  "geometry": {"coordinates":[-74.957324,39.967207],"type":"Point"}
}