{
  "type": "Feature",
  "properties": {
    "iso:country":"US",
    "sg:address":"99 Murray Hill Pkwy",
    "sg:city":"East Rutherford",
    "sg:classifiers":[
        {
            "category":"Wholesale",
            "subcategory":"Electrical",
            "type":"Manufacturing & Wholesale Goods"
        }
    ],
    "sg:phone":"+1 201 804 0101",
    "sg:postcode":"07073",
    "sg:province":"NJ",
    "sg:tags":[
        "equipment",
        "tube",
        "bulb",
        "light"
    ],
    "sg:website":"www.regencylighting.com",
    "wof:name":"Regency Lighting Inc",
    "wof:placetype":"venue"
},
  "geometry": {"coordinates":[-74.084981,40.827412],"type":"Point"}
}