{
  "type": "Feature",
  "properties": {
    "addr:full":"302 Main St Fort Lee NJ 07024",
    "addr:housenumber":"302",
    "addr:postcode":"07024",
    "addr:street":"Main St",
    "iso:country":"US",
    "sg:address":"302 Main St",
    "sg:city":"Fort Lee",
    "sg:classifiers":[
        {
            "category":"Shopping",
            "subcategory":"Clothing, Apparel, & Fashions",
            "type":"Retail Goods"
        }
    ],
    "sg:phone":"+1 201 461 9933",
    "sg:postcode":"07024",
    "sg:province":"NJ",
    "sg:tags":[
        "alteration"
    ],
    "wof:name":"Fort Lee Alterations",
    "wof:placetype":"venue"
},
  "geometry": {"coordinates":[-73.974383,40.853316],"type":"Point"}
}