{
  "type": "Feature",
  "properties": {
    "iso:country":"US",
    "sg:address":"603 Hanson Ave",
    "sg:city":"Piscataway",
    "sg:classifiers":[
        {
            "category":"Social Services",
            "subcategory":"Child Care",
            "type":"Services"
        }
    ],
    "sg:phone":"+1 732 463 1442",
    "sg:postcode":"08854",
    "sg:province":"NJ",
    "sg:tags":[
        "consulting",
        "management",
        "day"
    ],
    "wof:name":"Learn Assoc",
    "wof:placetype":"venue"
},
  "geometry": {"coordinates":[-74.472219,40.531651],"type":"Point"}
}