{
  "type": "Feature",
  "properties": {
    "addr:full":"85 State Rte 35 Keyport NJ 07735",
    "addr:housenumber":"85",
    "addr:postcode":"07735",
    "addr:street":"State Rte 35",
    "iso:country":"US",
    "sg:address":"85 State Rte 35",
    "sg:city":"Keyport",
    "sg:classifiers":[
        {
            "category":"Building & Trades",
            "subcategory":"Construction",
            "type":"Services"
        }
    ],
    "sg:phone":"+1 732 739 6682",
    "sg:postcode":"07735",
    "sg:province":"NJ",
    "sg:tags":[
        "home",
        "improvement"
    ],
    "wof:name":"Svenson Brothers Inc",
    "wof:placetype":"venue"
},
  "geometry": {"coordinates":[-74.236243,40.44839],"type":"Point"}
}