{
  "type": "Feature",
  "properties": {
    "iso:country":"US",
    "sg:address":"64 W 23rd St",
    "sg:city":"Bayonne",
    "sg:classifiers":[
        {
            "category":"Professional",
            "subcategory":"Accounting & Tax Preparation",
            "type":"Services"
        }
    ],
    "sg:phone":"+1 201 823 0644",
    "sg:postcode":"07002",
    "sg:province":"NJ",
    "sg:tags":[
        "auditing",
        "bookkeeping"
    ],
    "wof:name":"Phils Tax Service",
    "wof:placetype":"venue"
},
  "geometry": {"coordinates":[-74.12258799999999,40.665983],"type":"Point"}
}