{
  "type": "Feature",
  "properties": {
    "iso:country":"US",
    "sg:address":"241 Shiloh Rd",
    "sg:city":"Bridgeton",
    "sg:classifiers":[
        {
            "category":"Building & Trades",
            "subcategory":"Construction",
            "type":"Services"
        }
    ],
    "sg:phone":"+1 856 451 4512",
    "sg:postcode":"08302",
    "sg:province":"NJ",
    "sg:tags":[
        "excavation",
        "contractor"
    ],
    "wof:name":"Raymond W Harvey Jr Inc",
    "wof:placetype":"venue"
},
  "geometry": {"coordinates":[-75.312926,39.449697],"type":"Point"}
}