{
  "type": "Feature",
  "properties": {
    "iso:country":"US",
    "sg:address":"34 Cathy Ann Ct",
    "sg:city":"Wayne",
    "sg:classifiers":[
        {
            "category":"Professional",
            "subcategory":"Management & Consulting",
            "type":"Services"
        }
    ],
    "sg:phone":"+1   ",
    "sg:postcode":"07470",
    "sg:province":"NJ",
    "sg:tags":[
        "business"
    ],
    "wof:name":"American Health Care",
    "wof:placetype":"venue"
},
  "geometry": {"coordinates":[-74.227352,40.921415],"type":"Point"}
}