{
  "type": "Feature",
  "properties": {
    "iso:country":"US",
    "sg:address":"27 Cindy Ln",
    "sg:city":"Holmdel",
    "sg:classifiers":[
        {
            "category":"Professional",
            "subcategory":"Advertising",
            "type":"Services"
        }
    ],
    "sg:phone":"+1 732 203 9001",
    "sg:postcode":"07733",
    "sg:province":"NJ",
    "sg:tags":[
        "mail",
        "direct",
        "marketing"
    ],
    "wof:name":"On The Mark Communications LLC",
    "wof:placetype":"venue"
},
  "geometry": {"coordinates":[-74.20021199999999,40.372725],"type":"Point"}
}