{
  "type": "Feature",
  "properties": {
    "iso:country":"US",
    "sg:address":"260 W Union Ave",
    "sg:city":"Bound Brook",
    "sg:classifiers":[
        {
            "category":"Food & Beverages",
            "subcategory":"Liquor & Beverages",
            "type":"Retail Goods"
        }
    ],
    "sg:phone":"+1 732 469 5020",
    "sg:postcode":"08805",
    "sg:province":"NJ",
    "wof:name":"Buy Rite Liquors-Bound Brook",
    "wof:placetype":"venue"
},
  "geometry": {"coordinates":[-74.53985400000001,40.567207],"type":"Point"}
}