{
  "type": "Feature",
  "properties": {
    "addr:full":"443 Lake Ave Colonia NJ 07067",
    "addr:housenumber":"443",
    "addr:postcode":"07067",
    "addr:street":"Lake Ave",
    "iso:country":"US",
    "sg:address":"443 Lake Ave",
    "sg:city":"Colonia",
    "sg:classifiers":[
        {
            "category":"Deli",
            "type":"Food & Drink"
        }
    ],
    "sg:phone":"+1 732 574 3400",
    "sg:postcode":"07067",
    "sg:province":"NJ",
    "wof:name":"Bella Roma Gourmet Deli & Catering",
    "wof:placetype":"venue"
},
  "geometry": {"coordinates":[-74.323097,40.606602],"type":"Point"}
}