{
  "type": "Feature",
  "properties": {
    "iso:country":"US",
    "sg:address":"2319 Bridge Ave",
    "sg:city":"Pt Pleasant Bch",
    "sg:classifiers":[
        {
            "category":"Professional",
            "subcategory":"Business Services",
            "type":"Services"
        }
    ],
    "sg:phone":"+1 732 899 2700",
    "sg:postcode":"08742",
    "sg:province":"NJ",
    "sg:tags":[
        "embroidery"
    ],
    "wof:name":"Mc Laughlin's",
    "wof:placetype":"venue"
},
  "geometry": {"coordinates":[-74.073381,40.072632],"type":"Point"}
}