{
  "type": "Feature",
  "properties": {
    "addr:full":"329 Roseville Ave Newark NJ 07107",
    "addr:housenumber":"329",
    "addr:postcode":"07107",
    "addr:street":"Roseville Ave",
    "iso:country":"US",
    "sg:address":"329 Roseville Ave",
    "sg:city":"Newark",
    "sg:classifiers":[
        {
            "category":"Shopping",
            "subcategory":"Pharmacy",
            "type":"Retail Goods"
        }
    ],
    "sg:phone":"+1 973 483 3872",
    "sg:postcode":"07107",
    "sg:province":"NJ",
    "sg:tags":[
        "drugstore"
    ],
    "wof:name":"Fourth Ave Pharmacies",
    "wof:placetype":"venue"
},
  "geometry": {"coordinates":[-74.187665,40.761909],"type":"Point"}
}