{
  "type": "Feature",
  "properties": {
    "addr:full":"509 Rahway Ave Westfield NJ 07090",
    "addr:housenumber":"509",
    "addr:postcode":"07090",
    "addr:street":"Rahway Ave",
    "iso:country":"US",
    "sg:address":"509 Rahway Ave",
    "sg:city":"Westfield",
    "sg:classifiers":[
        {
            "category":"Professional",
            "subcategory":"Advertising",
            "type":"Services"
        }
    ],
    "sg:phone":"+1 732 499 8622",
    "sg:postcode":"07090",
    "sg:province":"NJ",
    "wof:name":"Netspace",
    "wof:placetype":"venue"
},
  "geometry": {"coordinates":[-74.35127799999999,40.646261],"type":"Point"}
}