{
  "type": "Feature",
  "properties": {
    "iso:country":"US",
    "sg:address":"24 Merchants Way",
    "sg:city":"Colts Neck",
    "sg:classifiers":[
        {
            "category":"Building & Trades",
            "subcategory":"Construction",
            "type":"Services"
        }
    ],
    "sg:phone":"+1 732 462 0046",
    "sg:postcode":"07722",
    "sg:province":"NJ",
    "sg:tags":[
        "contractor"
    ],
    "wof:name":"Monmouth Design & Development",
    "wof:placetype":"venue"
},
  "geometry": {"coordinates":[-74.17478,40.290724],"type":"Point"}
}