{
  "type": "Feature",
  "properties": {
    "addr:full":"5 Timberline Dr Howell NJ 07731",
    "addr:housenumber":"5",
    "addr:postcode":"07731",
    "addr:street":"Timberline Dr",
    "iso:country":"US",
    "sg:address":"5 Timberline Dr",
    "sg:city":"Howell",
    "sg:classifiers":[
        {
            "category":"Home & Garden",
            "subcategory":"Home Furnishings",
            "type":"Retail Goods"
        }
    ],
    "sg:phone":"+1   ",
    "sg:postcode":"07731",
    "sg:province":"NJ",
    "wof:name":"Neil Russo Lighting Design",
    "wof:placetype":"venue"
},
  "geometry": {"coordinates":[-74.23641600000001,40.149921],"type":"Point"}
}