{
  "type": "Feature",
  "properties": {
    "iso:country":"US",
    "sg:address":"960 Mount Kemble Ave",
    "sg:city":"Morristown",
    "sg:classifiers":[
        {
            "category":"Retail",
            "subcategory":"Repair Shop",
            "type":"Services"
        }
    ],
    "sg:phone":"+1 973 425 1300",
    "sg:postcode":"07960",
    "sg:province":"NJ",
    "sg:tags":[
        "upholsterer"
    ],
    "wof:name":"Maximilian Classics",
    "wof:placetype":"venue"
},
  "geometry": {"coordinates":[-74.53254800000001,40.74554],"type":"Point"}
}