{
  "type": "Feature",
  "properties": {
    "iso:country":"US",
    "sg:address":"1 Herning Ave",
    "sg:city":"Cranford",
    "sg:classifiers":[
        {
            "category":"Professional",
            "subcategory":"Management & Consulting",
            "type":"Services"
        }
    ],
    "sg:phone":"+1 908 709 1310",
    "sg:postcode":"07016",
    "sg:province":"NJ",
    "sg:tags":[
        "consultant",
        "resource",
        "human"
    ],
    "wof:name":"Travers Consulting",
    "wof:placetype":"venue"
},
  "geometry": {"coordinates":[-74.306039,40.669588],"type":"Point"}
}