{
  "type": "Feature",
  "properties": {
    "addr:full":"25 Neptune Blvd Neptune NJ 07753",
    "addr:housenumber":"25",
    "addr:postcode":"07753",
    "addr:street":"Neptune Blvd",
    "iso:country":"US",
    "sg:address":"25 Neptune Blvd",
    "sg:city":"Neptune",
    "sg:classifiers":[
        {
            "category":"Government",
            "subcategory":"Police Station",
            "type":"Public Place"
        }
    ],
    "sg:phone":"+1 732 988 8000",
    "sg:postcode":"07753",
    "sg:province":"NJ",
    "sg:tags":[
        "department"
    ],
    "wof:name":"Neptune Police Department",
    "wof:placetype":"venue"
},
  "geometry": {"coordinates":[-74.035886,40.210111],"type":"Point"}
}