{
  "type": "Feature",
  "properties": {
    "iso:country":"US",
    "sg:address":"3302 Cricket Cir",
    "sg:city":"Edison",
    "sg:classifiers":[
        {
            "category":"Professional",
            "subcategory":"Management & Consulting",
            "type":"Services"
        }
    ],
    "sg:phone":"+1 908 756 7045",
    "sg:postcode":"08820",
    "sg:province":"NJ",
    "sg:tags":[
        "business"
    ],
    "wof:name":"E2e Technologies Inc",
    "wof:placetype":"venue"
},
  "geometry": {"coordinates":[-74.36951000000001,40.586257],"type":"Point"}
}