{
  "type": "Feature",
  "properties": {
    "addr:full":"6701 Kennedy Blvd West New York NJ 07047",
    "addr:housenumber":"6701",
    "addr:postcode":"07047",
    "addr:street":"Kennedy Blvd West",
    "iso:country":"US",
    "sg:address":"6701 Kennedy Blvd",
    "sg:city":"West New York",
    "sg:classifiers":[
        {
            "category":"Professional",
            "subcategory":"Lawyer & Legal Services",
            "type":"Services"
        }
    ],
    "sg:phone":"+1 201 854 3072",
    "sg:postcode":"07047",
    "sg:province":"NJ",
    "sg:tags":[
        "attorney"
    ],
    "wof:name":"Sheldon Cohen",
    "wof:placetype":"venue"
},
  "geometry": {"coordinates":[-73.996934,40.80723],"type":"Point"}
}