{
  "type": "Feature",
  "properties": {
    "addr:full":"9 Haynes Creek Ln Medford NJ 08055",
    "addr:housenumber":"9",
    "addr:postcode":"08055",
    "addr:street":"Haynes Creek Ln",
    "iso:country":"US",
    "sg:address":"9 Haynes Creek Ln",
    "sg:city":"Medford",
    "sg:classifiers":[
        {
            "category":"Real Estate",
            "subcategory":"Architect",
            "type":"Services"
        }
    ],
    "sg:phone":"+1 609 654 8343",
    "sg:postcode":"08055",
    "sg:province":"NJ",
    "wof:name":"Pagnotta Architecture",
    "wof:placetype":"venue"
},
  "geometry": {"coordinates":[-74.811896,39.905521],"type":"Point"}
}