{
  "type": "Feature",
  "properties": {
    "iso:country":"US",
    "sg:address":"86 River Rd",
    "sg:city":"Montville",
    "sg:classifiers":[
        {
            "category":"Building & Trades",
            "subcategory":"Construction",
            "type":"Services"
        }
    ],
    "sg:phone":"+1 973 334 6900",
    "sg:postcode":"07045",
    "sg:province":"NJ",
    "sg:tags":[
        "marking",
        "maintenance",
        "parking"
    ],
    "wof:name":"Montville Twp Public Works",
    "wof:placetype":"venue"
},
  "geometry": {"coordinates":[-74.37467100000001,40.89192],"type":"Point"}
}