{
  "type": "Feature",
  "properties": {
    "iso:country":"US",
    "sg:address":"110 Cherry St",
    "sg:city":"South Bound Brook",
    "sg:classifiers":[
        {
            "category":"Building & Trades",
            "subcategory":"Construction",
            "type":"Services"
        }
    ],
    "sg:phone":"+1 732 560 0034",
    "sg:postcode":"08880",
    "sg:province":"NJ",
    "sg:tags":[
        "house"
    ],
    "wof:name":"Allison Construction",
    "wof:placetype":"venue"
},
  "geometry": {"coordinates":[-74.52713300000001,40.553694],"type":"Point"}
}