{
  "type": "Feature",
  "properties": {
    "iso:country":"US",
    "sg:address":"2 W Main St",
    "sg:city":"Clinton",
    "sg:classifiers":[
        {
            "category":"Restaurant",
            "type":"Food & Drink"
        }
    ],
    "sg:phone":"+1 908 730 9300",
    "sg:postcode":"08809",
    "sg:province":"NJ",
    "sg:tags":[
        "tavern"
    ],
    "sg:website":"http://www.clintonhouse.com",
    "wof:name":"Clinton House",
    "wof:placetype":"venue"
},
  "geometry": {"coordinates":[-74.912102,40.634945],"type":"Point"}
}