{
  "type": "Feature",
  "properties": {
    "addr:full":"39 Brighton Rd Mount Holly NJ 08060",
    "addr:housenumber":"39",
    "addr:postcode":"08060",
    "addr:street":"Brighton Rd",
    "iso:country":"US",
    "sg:address":"39 Brighton Rd",
    "sg:city":"Mount Holly",
    "sg:classifiers":[
        {
            "category":"Shopping",
            "subcategory":"Pharmacy",
            "type":"Retail Goods"
        }
    ],
    "sg:phone":"+1   ",
    "sg:postcode":"08060",
    "sg:province":"NJ",
    "wof:name":"Tanners Corner",
    "wof:placetype":"venue"
},
  "geometry": {"coordinates":[-74.80981800000001,40.009926],"type":"Point"}
}