{
  "type": "Feature",
  "properties": {
    "addr:full":"5 Hollywood Ct South Plainfield NJ 07080",
    "addr:housenumber":"5",
    "addr:postcode":"07080",
    "addr:street":"Hollywood Ct",
    "iso:country":"US",
    "sg:address":"5 Hollywood Ct",
    "sg:city":"South Plainfield",
    "sg:classifiers":[
        {
            "category":"Building & Trades",
            "subcategory":"Electrical",
            "type":"Services"
        },
        {
            "category":"Manufacturing",
            "subcategory":"Tools & Machinery",
            "type":"Manufacturing & Wholesale Goods"
        }
    ],
    "sg:phone":"+1 908 791 2828",
    "sg:postcode":"07080",
    "sg:province":"NJ",
    "sg:tags":[
        "equipment",
        "contractor",
        "electrical",
        "electric",
        "mfg"
    ],
    "wof:name":"Pirelli Power Cables & Systems",
    "wof:placetype":"venue"
},
  "geometry": {"coordinates":[-74.41388999999999,40.562512],"type":"Point"}
}