{
  "type": "Feature",
  "properties": {
    "addr:full":"364 Main St East Orange NJ 07018",
    "addr:housenumber":"364",
    "addr:postcode":"07018",
    "addr:street":"Main St East",
    "iso:country":"US",
    "sg:address":"364 Main St",
    "sg:city":"East Orange",
    "sg:classifiers":[
        {
            "category":"Banks & Credit Unions",
            "subcategory":"Bank",
            "type":"Services"
        }
    ],
    "sg:phone":"+1 973 675 4731",
    "sg:postcode":"07018",
    "sg:province":"NJ",
    "sg:tags":[
        "cashing",
        "check"
    ],
    "wof:name":"Fast Cash ATM",
    "wof:placetype":"venue"
},
  "geometry": {"coordinates":[-74.212785,40.762629],"type":"Point"}
}