{
  "type": "Feature",
  "properties": {
    "iso:country":"US",
    "sg:address":"350 W Oakland Ave Ste A",
    "sg:city":"Oakland",
    "sg:classifiers":[
        {
            "category":"Personal",
            "type":"Services"
        },
        {
            "category":"Retail",
            "subcategory":"Auto Repair",
            "type":"Services"
        }
    ],
    "sg:phone":"+1 201 337 1200",
    "sg:postcode":"07436",
    "sg:province":"NJ",
    "sg:tags":[
        "body",
        "shop",
        "towing"
    ],
    "wof:name":"Peters Body & Fender",
    "wof:placetype":"venue"
},
  "geometry": {"coordinates":[-74.264099,41.0191],"type":"Point"}
}