{
  "type": "Feature",
  "properties": {
    "iso:country":"US",
    "sg:address":"305 S Fairview St",
    "sg:city":"Riverside",
    "sg:classifiers":[
        {
            "category":"Building & Trades",
            "subcategory":"Construction",
            "type":"Services"
        }
    ],
    "sg:phone":"+1 856 764 3286",
    "sg:postcode":"08075",
    "sg:province":"NJ",
    "sg:tags":[
        "house"
    ],
    "wof:name":"Julio Construction",
    "wof:placetype":"venue"
},
  "geometry": {"coordinates":[-74.95910600000001,40.033886],"type":"Point"}
}