{
  "type": "Feature",
  "properties": {
    "addr:full":"13 Mountain Trl Vernon NJ 07462",
    "addr:housenumber":"13",
    "addr:postcode":"07462",
    "addr:street":"Mountain Trl",
    "iso:country":"US",
    "sg:address":"13 Mountain Trl",
    "sg:city":"Vernon",
    "sg:classifiers":[
        {
            "category":"Building & Trades",
            "subcategory":"Construction",
            "type":"Services"
        }
    ],
    "sg:phone":"+1 973 209 4013",
    "sg:postcode":"07462",
    "sg:province":"NJ",
    "sg:tags":[
        "painter"
    ],
    "wof:name":"Decorative Painting By Brian",
    "wof:placetype":"venue"
},
  "geometry": {"coordinates":[-74.495328,41.171352],"type":"Point"}
}