{
  "type": "Feature",
  "properties": {
    "iso:country":"US",
    "sg:address":"100 Paterson Ave",
    "sg:city":"Hoboken",
    "sg:classifiers":[
        {
            "category":"Retail",
            "subcategory":"Auto Repair",
            "type":"Services"
        }
    ],
    "sg:phone":"+1 201 222 6900",
    "sg:postcode":"07030",
    "sg:province":"NJ",
    "sg:tags":[
        "body"
    ],
    "wof:name":"Plaza Classic Cars Inc",
    "wof:placetype":"venue"
},
  "geometry": {"coordinates":[-74.04293199999999,40.739354],"type":"Point"}
}