{
  "type": "Feature",
  "properties": {
    "addr:full":"81 Two Bridges Rd Fairfield NJ 07004",
    "addr:housenumber":"81",
    "addr:postcode":"07004",
    "addr:street":"Two Bridges Rd",
    "iso:country":"US",
    "sg:address":"81 Two Bridges Rd",
    "sg:city":"Fairfield",
    "sg:classifiers":[
        {
            "category":"Health Services",
            "subcategory":"Doctor",
            "type":"Services"
        },
        {
            "category":"Health Services",
            "subcategory":"Hospital",
            "type":"Services"
        }
    ],
    "sg:phone":"+1 973 754 3800",
    "sg:postcode":"07004",
    "sg:province":"NJ",
    "sg:tags":[
        "obstetrician",
        "gynecologist"
    ],
    "wof:name":"Principe David MD",
    "wof:placetype":"venue"
},
  "geometry": {"coordinates":[-74.272903,40.896],"type":"Point"}
}