{
  "type": "Feature",
  "properties": {
    "iso:country":"US",
    "sg:address":"165 E Kennedy Blvd",
    "sg:city":"Lakewood",
    "sg:classifiers":[
        {
            "category":"Shopping",
            "subcategory":"Clothing, Apparel, & Fashions",
            "type":"Retail Goods"
        }
    ],
    "sg:phone":"+1   ",
    "sg:postcode":"08701",
    "sg:province":"NJ",
    "wof:name":"Hosiery Plus",
    "wof:placetype":"venue"
},
  "geometry": {"coordinates":[-74.215565,40.106791],"type":"Point"}
}