{
  "type": "Feature",
  "properties": {
    "addr:full":"450 Almond Rd Pittsgrove NJ 08318",
    "addr:housenumber":"450",
    "addr:postcode":"08318",
    "addr:street":"Almond Rd",
    "iso:country":"US",
    "sg:address":"450 Almond Rd",
    "sg:city":"Pittsgrove",
    "sg:classifiers":[
        {
            "category":"Organizations",
            "subcategory":"Religious Organization",
            "type":"Services"
        }
    ],
    "sg:phone":"+1 856 696 7254",
    "sg:postcode":"08318",
    "sg:province":"NJ",
    "sg:tags":[
        "clergy"
    ],
    "wof:name":"W T West",
    "wof:placetype":"venue"
},
  "geometry": {"coordinates":[-75.11187700000001,39.50449],"type":"Point"}
}