{
  "type": "Feature",
  "properties": {
    "addr:full":"164 Howe Ave Passaic NJ 07055",
    "addr:housenumber":"164",
    "addr:postcode":"07055",
    "addr:street":"Howe Ave",
    "iso:country":"US",
    "sg:address":"164 Howe Ave",
    "sg:city":"Passaic",
    "sg:classifiers":[
        {
            "category":"Building & Trades",
            "subcategory":"Construction",
            "type":"Services"
        }
    ],
    "sg:phone":"+1 973 777 0554",
    "sg:postcode":"07055",
    "sg:province":"NJ",
    "sg:tags":[
        "house"
    ],
    "wof:name":"Gonzalez Construction",
    "wof:placetype":"venue"
},
  "geometry": {"coordinates":[-74.133674,40.860164],"type":"Point"}
}