{
  "type": "Feature",
  "properties": {
    "iso:country":"US",
    "sg:address":"360 1st St",
    "sg:city":"Hoboken",
    "sg:classifiers":[
        {
            "category":"Professional",
            "type":"Services"
        }
    ],
    "sg:phone":"+1   ",
    "sg:postcode":"07030",
    "sg:province":"NJ",
    "wof:name":"Danielle Frankenthal",
    "wof:placetype":"venue"
},
  "geometry": {"coordinates":[-74.036035,40.738394],"type":"Point"}
}