{
  "type": "Feature",
  "properties": {
    "addr:full":"3111 Quakerbridge Rd Trenton NJ 08619",
    "addr:housenumber":"3111",
    "addr:postcode":"08619",
    "addr:street":"Quakerbridge Rd",
    "iso:country":"US",
    "sg:address":"3111 Quakerbridge Rd",
    "sg:city":"Trenton",
    "sg:classifiers":[
        {
            "category":"Banks & Credit Unions",
            "subcategory":"Bank",
            "type":"Services"
        }
    ],
    "sg:phone":"+1 609 585 5100",
    "sg:postcode":"08619",
    "sg:province":"NJ",
    "sg:website":"www.ynb.com",
    "wof:name":"Yardville National Bank",
    "wof:placetype":"venue"
},
  "geometry": {"coordinates":[-74.68619700000001,40.247414],"type":"Point"}
}