{
  "type": "Feature",
  "properties": {
    "addr:full":"425 Grand Ave Leonia NJ 07605",
    "addr:housenumber":"425",
    "addr:postcode":"07605",
    "addr:street":"Grand Ave",
    "iso:country":"US",
    "sg:address":"425 Grand Ave",
    "sg:city":"Leonia",
    "sg:classifiers":[
        {
            "category":"Autos & Motor Vehicles",
            "subcategory":"Fuel & Gas Station",
            "type":"Retail Goods"
        }
    ],
    "sg:phone":"+1   ",
    "sg:postcode":"07605",
    "sg:province":"NJ",
    "sg:tags":[
        "station",
        "gasoline"
    ],
    "wof:name":"Amoco",
    "wof:placetype":"venue"
},
  "geometry": {"coordinates":[-73.98953899999999,40.867043],"type":"Point"}
}