{
  "type": "Feature",
  "properties": {
    "iso:country":"US",
    "sg:address":"189 US Hwy 9",
    "sg:city":"Englishtown",
    "sg:classifiers":[
        {
            "category":"Professional",
            "subcategory":"Accounting & Tax Preparation",
            "type":"Services"
        }
    ],
    "sg:phone":"+1 732 409 2400",
    "sg:postcode":"07726",
    "sg:province":"NJ",
    "sg:tags":[
        "consultant"
    ],
    "wof:name":"Allan Korman",
    "wof:placetype":"venue"
},
  "geometry": {"coordinates":[-74.303819,40.301988],"type":"Point"}
}