{
  "type": "Feature",
  "properties": {
    "iso:country":"US",
    "sg:address":"45 Barnsdale Rd",
    "sg:city":"Short Hills",
    "sg:classifiers":[
        {
            "category":"Education",
            "subcategory":"Special Training",
            "type":"Public Place"
        }
    ],
    "sg:phone":"+1   ",
    "sg:postcode":"07078",
    "sg:province":"NJ",
    "wof:name":"Jacqelin E Payer",
    "wof:placetype":"venue"
},
  "geometry": {"coordinates":[-74.319639,40.73214],"type":"Point"}
}