{
  "type": "Feature",
  "properties": {
    "addr:full":"56 Wildwood Ave Montclair NJ 07043",
    "addr:housenumber":"56",
    "addr:postcode":"07043",
    "addr:street":"Wildwood Ave",
    "iso:country":"US",
    "sg:address":"56 Wildwood Ave",
    "sg:city":"Montclair",
    "sg:classifiers":[
        {
            "category":"Professional",
            "subcategory":"Management & Consulting",
            "type":"Services"
        }
    ],
    "sg:phone":"+1   ",
    "sg:postcode":"07043",
    "sg:province":"NJ",
    "sg:tags":[
        "business"
    ],
    "wof:name":"Shoham Consulting Inc",
    "wof:placetype":"venue"
},
  "geometry": {"coordinates":[-74.19421800000001,40.834103],"type":"Point"}
}