{
  "type": "Feature",
  "properties": {
    "addr:full":"1600 Paterson Plank Rd Secaucus NJ 07094",
    "addr:housenumber":"1600",
    "addr:postcode":"07094",
    "addr:street":"Paterson Plank Rd",
    "iso:country":"US",
    "sg:address":"1600 Paterson Plank Rd",
    "sg:city":"Secaucus",
    "sg:classifiers":[
        {
            "category":"Professional",
            "type":"Services"
        }
    ],
    "sg:phone":"+1   ",
    "sg:postcode":"07094",
    "sg:province":"NJ",
    "wof:name":"Fitzland Corp",
    "wof:placetype":"venue"
},
  "geometry": {"coordinates":[-74.058781,40.80201],"type":"Point"}
}