{
  "type": "Feature",
  "properties": {
    "iso:country":"US",
    "sg:address":"6 Amherst Rd",
    "sg:city":"Marlboro",
    "sg:classifiers":[
        {
            "category":"Professional",
            "type":"Services"
        }
    ],
    "sg:phone":"+1   ",
    "sg:postcode":"07746",
    "sg:province":"NJ",
    "wof:name":"Eulica Inc",
    "wof:placetype":"venue"
},
  "geometry": {"coordinates":[-74.252585,40.314709],"type":"Point"}
}