{
  "type": "Feature",
  "properties": {
    "addr:full":"1632 W Garden Rd Vineland NJ 08360",
    "addr:housenumber":"1632",
    "addr:postcode":"08360",
    "addr:street":"W Garden Rd",
    "iso:country":"US",
    "sg:address":"1632 W Garden Rd",
    "sg:city":"Vineland",
    "sg:classifiers":[
        {
            "category":"Recreation",
            "type":"Entertainment"
        }
    ],
    "sg:phone":"+1   ",
    "sg:postcode":"08360",
    "sg:province":"NJ",
    "sg:tags":[
        "club",
        "membership"
    ],
    "wof:name":"Little League Baseball Inc",
    "wof:placetype":"venue"
},
  "geometry": {"coordinates":[-75.046481,39.520882],"type":"Point"}
}