{
  "type": "Feature",
  "properties": {
    "addr:full":"1113 4th Ave Asbury Park NJ 07712",
    "addr:housenumber":"1113",
    "addr:postcode":"07712",
    "addr:street":"4Th Ave Asbury",
    "iso:country":"US",
    "sg:address":"1113 4th Ave",
    "sg:city":"Asbury Park",
    "sg:classifiers":[
        {
            "category":"Autos & Motor Vehicles",
            "subcategory":"Fuel & Gas Station",
            "type":"Retail Goods"
        }
    ],
    "sg:phone":"+1 732 774 1918",
    "sg:postcode":"07712",
    "sg:province":"NJ",
    "sg:tags":[
        "oil"
    ],
    "wof:name":"Asbury Park Getty",
    "wof:placetype":"venue"
},
  "geometry": {"coordinates":[-74.016876,40.226065],"type":"Point"}
}