{
  "type": "Feature",
  "properties": {
    "iso:country":"US",
    "sg:address":"100 Washington Ave",
    "sg:city":"Little Ferry",
    "sg:classifiers":[
        {
            "category":"Banks & Credit Unions",
            "subcategory":"Bank",
            "type":"Services"
        }
    ],
    "sg:phone":"+1 201 641 6755",
    "sg:postcode":"07643",
    "sg:province":"NJ",
    "wof:name":"Bergen Commercial Bank",
    "wof:placetype":"venue"
},
  "geometry": {"coordinates":[-74.036903,40.8475],"type":"Point"}
}