{
  "type": "Feature",
  "properties": {
    "addr:full":"664 Brace Ave Perth Amboy NJ 08861",
    "addr:housenumber":"664",
    "addr:postcode":"08861",
    "addr:street":"Brace Ave",
    "iso:country":"US",
    "sg:address":"664 Brace Ave",
    "sg:city":"Perth Amboy",
    "sg:classifiers":[
        {
            "category":"Building & Trades",
            "subcategory":"Locksmith",
            "type":"Services"
        }
    ],
    "sg:phone":"+1 732 839 2549",
    "sg:postcode":"08861",
    "sg:province":"NJ",
    "sg:tags":[
        "key"
    ],
    "wof:name":"1 24 Hour 7 Day A Emerg Locksmith",
    "wof:placetype":"venue"
},
  "geometry": {"coordinates":[-74.286851,40.52425],"type":"Point"}
}