{
  "type": "Feature",
  "properties": {
    "iso:country":"US",
    "sg:address":"3729 US Hwy 1",
    "sg:city":"Princeton",
    "sg:classifiers":[
        {
            "category":"Building & Trades",
            "subcategory":"Equipment Rental",
            "type":"Services"
        }
    ],
    "sg:phone":"+1 609 452 7926",
    "sg:postcode":"08540",
    "sg:province":"NJ",
    "sg:tags":[
        "leasing"
    ],
    "wof:name":"Penske Truck Leasing",
    "wof:placetype":"venue"
},
  "geometry": {"coordinates":[-74.63445,40.33469],"type":"Point"}
}