{
  "type": "Feature",
  "properties": {
    "addr:full":"67 US Hwy 46 Hackettstown NJ 07840",
    "addr:housenumber":"67",
    "addr:postcode":"07840",
    "addr:street":"Us Hwy 46",
    "iso:country":"US",
    "sg:address":"67 US Hwy 46",
    "sg:city":"Hackettstown",
    "sg:classifiers":[
        {
            "category":"Arts & Performance",
            "subcategory":"Theater",
            "type":"Entertainment"
        }
    ],
    "sg:phone":"+1 908 813 2626",
    "sg:postcode":"07840",
    "sg:province":"NJ",
    "sg:tags":[
        "musician"
    ],
    "wof:name":"Kindermusik Of Independance",
    "wof:placetype":"venue"
},
  "geometry": {"coordinates":[-74.85157599999999,40.857491],"type":"Point"}
}