{
  "type": "Feature",
  "properties": {
    "iso:country":"US",
    "sg:address":"16 Troth Ave",
    "sg:city":"Gibbsboro",
    "sg:classifiers":[
        {
            "category":"Building & Trades",
            "subcategory":"Construction",
            "type":"Services"
        }
    ],
    "sg:phone":"+1 856 782 9468",
    "sg:postcode":"08026",
    "sg:province":"NJ",
    "sg:tags":[
        "house"
    ],
    "wof:name":"Thomas Michael Remodeling",
    "wof:placetype":"venue"
},
  "geometry": {"coordinates":[-74.96375999999999,39.841805],"type":"Point"}
}