{
  "type": "Feature",
  "properties": {
    "addr:full":"200 US Highway 46 Parsippany NJ 07054",
    "addr:housenumber":"200",
    "addr:postcode":"07054",
    "addr:street":"Us Highway 46",
    "iso:country":"US",
    "sg:address":"200 US Highway 46",
    "sg:city":"Parsippany",
    "sg:classifiers":[
        {
            "category":"Health Services",
            "subcategory":"Doctor",
            "type":"Services"
        }
    ],
    "sg:phone":"+1 973 882 0443",
    "sg:postcode":"07054",
    "sg:province":"NJ",
    "sg:tags":[
        "practice",
        "family"
    ],
    "wof:name":"Immediate Medical Care Center",
    "wof:placetype":"venue"
},
  "geometry": {"coordinates":[-74.355598,40.858601],"type":"Point"}
}