{
  "type": "Feature",
  "properties": {
    "addr:full":"20 White Rd Shrewsbury NJ 07702",
    "addr:housenumber":"20",
    "addr:postcode":"07702",
    "addr:street":"White Rd",
    "iso:country":"US",
    "sg:address":"20 White Rd",
    "sg:city":"Shrewsbury",
    "sg:classifiers":[
        {
            "category":"Health Services",
            "subcategory":"Doctor",
            "type":"Services"
        }
    ],
    "sg:phone":"+1 732 747 4723",
    "sg:postcode":"07702",
    "sg:province":"NJ",
    "sg:tags":[
        "medical"
    ],
    "wof:name":"Shahid W Farooqui MD PA",
    "wof:placetype":"venue"
},
  "geometry": {"coordinates":[-74.063052,40.336118],"type":"Point"}
}