{
  "type": "Feature",
  "properties": {
    "iso:country":"US",
    "sg:address":"3103 W Brigantine Ave",
    "sg:city":"Brigantine",
    "sg:classifiers":[
        {
            "category":"Personal",
            "subcategory":"Tanning Parlor",
            "type":"Services"
        }
    ],
    "sg:phone":"+1 609 266 0566",
    "sg:postcode":"08203",
    "sg:province":"NJ",
    "sg:tags":[
        "salon"
    ],
    "wof:name":"Island Sun Tanning",
    "wof:placetype":"venue"
},
  "geometry": {"coordinates":[-74.38554499999999,39.394287],"type":"Point"}
}