{
  "type": "Feature",
  "properties": {
    "iso:country":"US",
    "sg:address":"861 Brown Rd",
    "sg:city":"Bridgewater",
    "sg:classifiers":[
        {
            "category":"Education",
            "subcategory":"Special Training",
            "type":"Public Place"
        }
    ],
    "sg:phone":"+1 908 595 1843",
    "sg:postcode":"08807",
    "sg:province":"NJ",
    "sg:tags":[
        "program"
    ],
    "wof:name":"Successfullife Coaching Svc",
    "wof:placetype":"venue"
},
  "geometry": {"coordinates":[-74.62724799999999,40.629487],"type":"Point"}
}