{
  "type": "Feature",
  "properties": {
    "iso:country":"US",
    "sg:address":"36 Parkside Ct",
    "sg:city":"Glen Gardner",
    "sg:classifiers":[
        {
            "category":"Arts & Performance",
            "subcategory":"Theater",
            "type":"Entertainment"
        }
    ],
    "sg:phone":"+1 908 537 9002",
    "sg:postcode":"08826",
    "sg:province":"NJ",
    "sg:tags":[
        "entertainer"
    ],
    "wof:name":"J R Jackson Entertainment",
    "wof:placetype":"venue"
},
  "geometry": {"coordinates":[-74.94611500000001,40.698953],"type":"Point"}
}