{
  "type": "Feature",
  "properties": {
    "iso:country":"US",
    "sg:address":"930 Mountain Ave",
    "sg:city":"Mountainside",
    "sg:classifiers":[
        {
            "category":"Building & Trades",
            "subcategory":"Electrical",
            "type":"Services"
        }
    ],
    "sg:phone":"+1 908 233 1314",
    "sg:postcode":"07092",
    "sg:province":"NJ",
    "sg:tags":[
        "electrical",
        "contractor"
    ],
    "wof:name":"Dellisanti Electrical Contg",
    "wof:placetype":"venue"
},
  "geometry": {"coordinates":[-74.350171,40.668961],"type":"Point"}
}