{
  "type": "Feature",
  "properties": {
    "iso:country":"US",
    "sg:address":"9 S Main St",
    "sg:city":"Marlboro",
    "sg:classifiers":[
        {
            "category":"Banks & Credit Unions",
            "subcategory":"Investment Brokerage",
            "type":"Services"
        },
        {
            "category":"Banks & Credit Unions",
            "subcategory":"Bank",
            "type":"Services"
        }
    ],
    "sg:phone":"+1 732 683 9222",
    "sg:postcode":"07746",
    "sg:province":"NJ",
    "sg:tags":[
        "security",
        "financing"
    ],
    "wof:name":"Government Perspectives LLC",
    "wof:placetype":"venue"
},
  "geometry": {"coordinates":[-74.24921000000001,40.312561],"type":"Point"}
}