{
  "type": "Feature",
  "properties": {
    "iso:country":"US",
    "sg:address":"114 Essex St Ste G",
    "sg:city":"Rochelle Park",
    "sg:classifiers":[
        {
            "category":"Professional",
            "subcategory":"Lawyer & Legal Services",
            "type":"Services"
        }
    ],
    "sg:phone":"+1 201 368 0677",
    "sg:postcode":"07662",
    "sg:province":"NJ",
    "wof:name":"Long Rachel A",
    "wof:placetype":"venue"
},
  "geometry": {"coordinates":[-74.072647,40.892031],"type":"Point"}
}