{
  "type": "Feature",
  "properties": {
    "addr:full":"609 Boardwalk Seaside Heights NJ 08751",
    "addr:housenumber":"609",
    "addr:postcode":"08751",
    "addr:street":"Boardwalk Seaside",
    "iso:country":"US",
    "sg:address":"609 Boardwalk",
    "sg:city":"Seaside Heights",
    "sg:classifiers":[
        {
            "category":"Shopping",
            "subcategory":"Clothing, Apparel, & Fashions",
            "type":"Retail Goods"
        }
    ],
    "sg:phone":"+1 732 830 8222",
    "sg:postcode":"08751",
    "sg:province":"NJ",
    "sg:tags":[
        "item",
        "boutique"
    ],
    "wof:name":"One Of A Kind",
    "wof:placetype":"venue"
},
  "geometry": {"coordinates":[-74.07049499999999,39.941509],"type":"Point"}
}