{
  "type": "Feature",
  "properties": {
    "addr:full":"433 State St Perth Amboy NJ 08861",
    "addr:housenumber":"433",
    "addr:postcode":"08861",
    "addr:street":"State St",
    "iso:country":"US",
    "sg:address":"433 State St",
    "sg:city":"Perth Amboy",
    "sg:classifiers":[
        {
            "category":"Organizations",
            "subcategory":"Religious Organization",
            "type":"Services"
        }
    ],
    "sg:phone":"+1 732 826 7040",
    "sg:postcode":"08861",
    "sg:province":"NJ",
    "sg:website":"www.salvationarmy.org",
    "wof:name":"Salvation Army",
    "wof:placetype":"venue"
},
  "geometry": {"coordinates":[-74.265297,40.5135],"type":"Point"}
}