{
  "type": "Feature",
  "properties": {
    "addr:full":"1009 Main Rd Newfield NJ 08344",
    "addr:housenumber":"1009",
    "addr:postcode":"08344",
    "addr:street":"Main Rd",
    "iso:country":"US",
    "sg:address":"1009 Main Rd",
    "sg:city":"Newfield",
    "sg:classifiers":[
        {
            "category":"Organizations",
            "subcategory":"Religious Organization",
            "type":"Services"
        }
    ],
    "sg:phone":"+1 856 697 2983",
    "sg:postcode":"08344",
    "sg:province":"NJ",
    "sg:tags":[
        "monastery",
        "convent"
    ],
    "wof:name":"Villa Rossello Sisters",
    "wof:placetype":"venue"
},
  "geometry": {"coordinates":[-74.99415999999999,39.544498],"type":"Point"}
}