{
  "type": "Feature",
  "properties": {
    "iso:country":"US",
    "sg:address":"40 South Ave",
    "sg:city":"Fanwood",
    "sg:classifiers":[
        {
            "category":"Autos & Motor Vehicles",
            "subcategory":"Automobile Sales",
            "type":"Retail Goods"
        }
    ],
    "sg:phone":"+1   ",
    "sg:postcode":"07023",
    "sg:province":"NJ",
    "sg:tags":[
        "used"
    ],
    "wof:name":"Plainfield Auto Sales",
    "wof:placetype":"venue"
},
  "geometry": {"coordinates":[-74.391772,40.635433],"type":"Point"}
}