{
  "type": "Feature",
  "properties": {
    "addr:full":"359 Mountain View Ter Dunellen NJ 08812",
    "addr:housenumber":"359",
    "addr:postcode":"08812",
    "addr:street":"Mountain View Ter",
    "iso:country":"US",
    "sg:address":"359 Mountain View Ter",
    "sg:city":"Dunellen",
    "sg:classifiers":[
        {
            "category":"Wholesale",
            "subcategory":"Non-durable Goods",
            "type":"Manufacturing & Wholesale Goods"
        }
    ],
    "sg:phone":"+1 732 752 2234",
    "sg:postcode":"08812",
    "sg:province":"NJ",
    "sg:tags":[
        "advertising"
    ],
    "sg:website":"www.geiger.com",
    "wof:name":"Geiger Brothers",
    "wof:placetype":"venue"
},
  "geometry": {"coordinates":[-74.470181,40.596683],"type":"Point"}
}