{
  "type": "Feature",
  "properties": {
    "addr:full":"12 Clavendon Ct Middletown NJ 07748",
    "addr:housenumber":"12",
    "addr:postcode":"07748",
    "addr:street":"Clavendon Ct",
    "iso:country":"US",
    "sg:address":"12 Clavendon Ct",
    "sg:city":"Middletown",
    "sg:classifiers":[
        {
            "category":"Shopping",
            "subcategory":"Musical Instruments",
            "type":"Retail Goods"
        }
    ],
    "sg:phone":"+1 732 671 9576",
    "sg:postcode":"07748",
    "sg:province":"NJ",
    "sg:tags":[
        "music",
        "dealer"
    ],
    "wof:name":"Music N Arts Expolration",
    "wof:placetype":"venue"
},
  "geometry": {"coordinates":[-74.09263199999999,40.393795],"type":"Point"}
}