{
  "type": "Feature",
  "properties": {
    "addr:full":"218 Jersey St Harrison NJ 07029",
    "addr:housenumber":"218",
    "addr:postcode":"07029",
    "addr:street":"Jersey St",
    "iso:country":"US",
    "sg:address":"218 Jersey St",
    "sg:city":"Harrison",
    "sg:classifiers":[
        {
            "category":"Building & Trades",
            "subcategory":"Construction",
            "type":"Services"
        }
    ],
    "sg:phone":"+1 973 484 1398",
    "sg:postcode":"07029",
    "sg:province":"NJ",
    "sg:tags":[
        "contractor"
    ],
    "wof:name":"Barreras Gutters Co",
    "wof:placetype":"venue"
},
  "geometry": {"coordinates":[-74.158357,40.745335],"type":"Point"}
}