{
  "type": "Feature",
  "properties": {
    "addr:full":"210 E Main St Somerville NJ 08876",
    "addr:housenumber":"210",
    "addr:postcode":"08876",
    "addr:street":"E Main St",
    "iso:country":"US",
    "sg:address":"210 E Main St",
    "sg:city":"Somerville",
    "sg:classifiers":[
        {
            "category":"Professional",
            "subcategory":"Business Services",
            "type":"Services"
        },
        {
            "category":"Health Services",
            "subcategory":"Doctor",
            "type":"Services"
        }
    ],
    "sg:phone":"+1 908 526 0545",
    "sg:postcode":"08876",
    "sg:province":"NJ",
    "sg:tags":[
        "dentist"
    ],
    "wof:name":"Cornick Martin H DDS",
    "wof:placetype":"venue"
},
  "geometry": {"coordinates":[-74.601994,40.565891],"type":"Point"}
}