{
  "type": "Feature",
  "properties": {
    "addr:full":"2810 Morris Ave Union NJ 07083",
    "addr:housenumber":"2810",
    "addr:postcode":"07083",
    "addr:street":"Morris Ave",
    "iso:country":"US",
    "sg:address":"2810 Morris Ave",
    "sg:city":"Union",
    "sg:classifiers":[
        {
            "category":"Health Services",
            "subcategory":"Health Practitioner",
            "type":"Services"
        }
    ],
    "sg:phone":"+1 973 810 6330",
    "sg:postcode":"07083",
    "sg:province":"NJ",
    "sg:tags":[
        "psychologist"
    ],
    "wof:name":"Jeffrey C Singer PHD",
    "wof:placetype":"venue"
},
  "geometry": {"coordinates":[-74.29977,40.706908],"type":"Point"}
}