{
  "type": "Feature",
  "properties": {
    "iso:country":"US",
    "sg:address":"62 Main St",
    "sg:city":"Madison",
    "sg:classifiers":[
        {
            "category":"Travel",
            "subcategory":"Travel Agent",
            "type":"Entertainment"
        }
    ],
    "sg:phone":"+1 973 822 3222",
    "sg:postcode":"07940",
    "sg:province":"NJ",
    "wof:name":"Avenue Travel",
    "wof:placetype":"venue"
},
  "geometry": {"coordinates":[-74.415007,40.758766],"type":"Point"}
}