{
  "type": "Feature",
  "properties": {
    "iso:country":"US",
    "sg:address":"251 Beach Dr",
    "sg:city":"Cape May",
    "sg:classifiers":[
        {
            "category":"Shopping",
            "subcategory":"Jewelry",
            "type":"Retail Goods"
        }
    ],
    "sg:phone":"+1 609 898 1777",
    "sg:postcode":"08204",
    "sg:province":"NJ",
    "sg:tags":[
        "jeweler"
    ],
    "wof:name":"Victorious Antiques",
    "wof:placetype":"venue"
},
  "geometry": {"coordinates":[-74.924588,38.930257],"type":"Point"}
}