{
  "type": "Feature",
  "properties": {
    "addr:full":"300 Mac Ln Keasbey NJ 08832",
    "addr:housenumber":"300",
    "addr:postcode":"08832",
    "addr:street":"Mac Ln",
    "iso:country":"US",
    "sg:address":"300 Mac Ln",
    "sg:city":"Keasbey",
    "sg:classifiers":[
        {
            "category":"Professional",
            "subcategory":"Business Services",
            "type":"Services"
        }
    ],
    "sg:phone":"+1   ",
    "sg:postcode":"08832",
    "sg:province":"NJ",
    "wof:name":"Federal Business Centers",
    "wof:placetype":"venue"
},
  "geometry": {"coordinates":[-74.322902,40.51763],"type":"Point"}
}