{
  "type": "Feature",
  "properties": {
    "iso:country":"US",
    "sg:address":"2200 Kuser Rd",
    "sg:city":"Trenton",
    "sg:classifiers":[
        {
            "category":"Museum",
            "type":"Entertainment"
        }
    ],
    "sg:phone":"+1   ",
    "sg:postcode":"08690",
    "sg:province":"NJ",
    "sg:tags":[
        "gallery"
    ],
    "wof:name":"Abbott John House",
    "wof:placetype":"venue"
},
  "geometry": {"coordinates":[-74.682076,40.202593],"type":"Point"}
}