{
  "type": "Feature",
  "properties": {
    "addr:full":"13 Kings Rd Chatham NJ 07928",
    "addr:housenumber":"13",
    "addr:postcode":"07928",
    "addr:street":"Kings Rd",
    "iso:country":"US",
    "sg:address":"13 Kings Rd",
    "sg:city":"Chatham",
    "sg:classifiers":[
        {
            "category":"Professional",
            "subcategory":"Advertising",
            "type":"Services"
        }
    ],
    "sg:phone":"+1   ",
    "sg:postcode":"07928",
    "sg:province":"NJ",
    "sg:tags":[
        "agency"
    ],
    "wof:name":"Kingston Media Group",
    "wof:placetype":"venue"
},
  "geometry": {"coordinates":[-74.398043,40.744946],"type":"Point"}
}