{
  "type": "Feature",
  "properties": {
    "addr:full":"561 McCarter Hwy Newark NJ 07102",
    "addr:housenumber":"561",
    "addr:postcode":"07102",
    "addr:street":"Mccarter Hwy",
    "iso:country":"US",
    "sg:address":"561 McCarter Hwy",
    "sg:city":"Newark",
    "sg:classifiers":[
        {
            "category":"Restaurant",
            "type":"Food & Drink"
        }
    ],
    "sg:phone":"+1 973 643 0810",
    "sg:postcode":"07102",
    "sg:province":"NJ",
    "wof:name":"Mc Donald's",
    "wof:placetype":"venue"
},
  "geometry": {"coordinates":[-74.17243999999999,40.726862],"type":"Point"}
}