{
  "type": "Feature",
  "properties": {
    "addr:full":"96 Hobart St Hackensack NJ 07601",
    "addr:housenumber":"96",
    "addr:postcode":"07601",
    "addr:street":"Hobart St",
    "iso:country":"US",
    "sg:address":"96 Hobart St",
    "sg:city":"Hackensack",
    "sg:classifiers":[
        {
            "category":"Wholesale",
            "subcategory":"Computers",
            "type":"Manufacturing & Wholesale Goods"
        }
    ],
    "sg:phone":"+1 201 489 3370",
    "sg:postcode":"07601",
    "sg:province":"NJ",
    "wof:name":"BDI Laguna",
    "wof:placetype":"venue"
},
  "geometry": {"coordinates":[-74.050652,40.875411],"type":"Point"}
}