{
  "type": "Feature",
  "properties": {
    "iso:country":"US",
    "sg:address":"246 2nd St",
    "sg:city":"Elizabeth",
    "sg:classifiers":[
        {
            "category":"Restaurant",
            "type":"Food & Drink"
        }
    ],
    "sg:phone":"+1   ",
    "sg:postcode":"07206",
    "sg:province":"NJ",
    "sg:tags":[
        "eating"
    ],
    "wof:name":"Rio Lima Restaurant",
    "wof:placetype":"venue"
},
  "geometry": {"coordinates":[-74.18382,40.653091],"type":"Point"}
}