{
  "type": "Feature",
  "properties": {
    "addr:full":"227 Rose St Metuchen NJ 08840",
    "addr:housenumber":"227",
    "addr:postcode":"08840",
    "addr:street":"Rose St",
    "iso:country":"US",
    "sg:address":"227 Rose St",
    "sg:city":"Metuchen",
    "sg:classifiers":[
        {
            "category":"Insurance",
            "subcategory":"Insurance Agent",
            "type":"Services"
        }
    ],
    "sg:phone":"+1 732 321 9283",
    "sg:postcode":"08840",
    "sg:province":"NJ",
    "sg:tags":[
        "agency"
    ],
    "wof:name":"Carmine Insurance Agency",
    "wof:placetype":"venue"
},
  "geometry": {"coordinates":[-74.367521,40.530884],"type":"Point"}
}