{
  "type": "Feature",
  "properties": {
    "iso:country":"US",
    "sg:address":"1224 Andover Rd",
    "sg:city":"Forked River",
    "sg:classifiers":[
        {
            "category":"Building & Trades",
            "subcategory":"Construction",
            "type":"Services"
        }
    ],
    "sg:phone":"+1 609 693 9614",
    "sg:postcode":"08731",
    "sg:province":"NJ",
    "sg:tags":[
        "contractor"
    ],
    "wof:name":"S&S Contracting",
    "wof:placetype":"venue"
},
  "geometry": {"coordinates":[-74.23182199999999,39.873379],"type":"Point"}
}