{
  "type": "Feature",
  "properties": {
    "addr:full":"85 Bassett Hwy Dover NJ 07801",
    "addr:housenumber":"85",
    "addr:postcode":"07801",
    "addr:street":"Bassett Hwy",
    "iso:country":"US",
    "sg:address":"85 Bassett Hwy",
    "sg:city":"Dover",
    "sg:classifiers":[
        {
            "category":"Professional",
            "subcategory":"Testing Lab",
            "type":"Services"
        }
    ],
    "sg:phone":"+1 973 989 0010",
    "sg:postcode":"07801",
    "sg:province":"NJ",
    "sg:tags":[
        "laboratory"
    ],
    "wof:name":"Agra Environmental Svc Inc",
    "wof:placetype":"venue"
},
  "geometry": {"coordinates":[-74.561995,40.88488],"type":"Point"}
}