{
  "type": "Feature",
  "properties": {
    "iso:country":"US",
    "sg:address":"10 Tall Oaks Dr",
    "sg:city":"Jackson",
    "sg:classifiers":[
        {
            "category":"Retail",
            "subcategory":"Repair Shop",
            "type":"Services"
        }
    ],
    "sg:phone":"+1   ",
    "sg:postcode":"08527",
    "sg:province":"NJ",
    "sg:tags":[
        "welding"
    ],
    "wof:name":"K Hadden Welding Service",
    "wof:placetype":"venue"
},
  "geometry": {"coordinates":[-74.38076,40.091271],"type":"Point"}
}