{
  "type": "Feature",
  "properties": {
    "iso:country":"US",
    "sg:address":"202 State Rte 37",
    "sg:city":"Toms River",
    "sg:classifiers":[
        {
            "category":"Personal",
            "type":"Services"
        }
    ],
    "sg:phone":"+1 732 286 0599",
    "sg:postcode":"08755",
    "sg:province":"NJ",
    "sg:tags":[
        "therapist",
        "massage"
    ],
    "wof:name":"Ocean County Massage",
    "wof:placetype":"venue"
},
  "geometry": {"coordinates":[-74.22266,39.966583],"type":"Point"}
}