{
  "type": "Feature",
  "properties": {
    "addr:full":"636 Morris Ave Short Hills NJ 07078",
    "addr:housenumber":"636",
    "addr:postcode":"07078",
    "addr:street":"Morris Ave",
    "iso:country":"US",
    "sg:address":"636 Morris Ave",
    "sg:city":"Short Hills",
    "sg:classifiers":[
        {
            "category":"Professional",
            "subcategory":"Management & Consulting",
            "type":"Services"
        }
    ],
    "sg:phone":"+1   ",
    "sg:postcode":"07078",
    "sg:province":"NJ",
    "sg:tags":[
        "hospital"
    ],
    "wof:name":"Ula Management Corp",
    "wof:placetype":"venue"
},
  "geometry": {"coordinates":[-74.326194,40.717442],"type":"Point"}
}