{
  "type": "Feature",
  "properties": {
    "iso:country":"US",
    "sg:address":"491 State Rte 73",
    "sg:city":"Marlton",
    "sg:classifiers":[
        {
            "category":"Banks & Credit Unions",
            "subcategory":"Bank",
            "type":"Services"
        }
    ],
    "sg:phone":"+1 856 489 3140",
    "sg:postcode":"08053",
    "sg:province":"NJ",
    "sg:website":"www.sunnb.com",
    "wof:name":"Sun National Bank",
    "wof:placetype":"venue"
},
  "geometry": {"coordinates":[-74.92219799999999,39.881421],"type":"Point"}
}