{
  "type": "Feature",
  "properties": {
    "addr:full":"93 Kerrs Corner Rd Blairstown NJ 07825",
    "addr:housenumber":"93",
    "addr:postcode":"07825",
    "addr:street":"Kerrs Corner Rd",
    "iso:country":"US",
    "sg:address":"93 Kerrs Corner Rd",
    "sg:city":"Blairstown",
    "sg:classifiers":[
        {
            "category":"Education",
            "subcategory":"School",
            "type":"Public Place"
        }
    ],
    "sg:phone":"+1 908 362 1114",
    "sg:postcode":"07825",
    "sg:province":"NJ",
    "wof:name":"Ridge & Valley Charter School",
    "wof:placetype":"venue"
},
  "geometry": {"coordinates":[-74.90562199999999,40.9693],"type":"Point"}
}