{
  "type": "Feature",
  "properties": {
    "iso:country":"US",
    "sg:address":"472 State Rte 31 N",
    "sg:city":"Ringoes",
    "sg:classifiers":[
        {
            "category":"Building & Trades",
            "subcategory":"Landscaping Services",
            "type":"Services"
        }
    ],
    "sg:phone":"+1 609 466 4392",
    "sg:postcode":"08551",
    "sg:province":"NJ",
    "wof:name":"Kapps Nurs Rocktown Wtr Grdns",
    "wof:placetype":"venue"
},
  "geometry": {"coordinates":[-74.85915,40.405032],"type":"Point"}
}