{
  "type": "Feature",
  "properties": {
    "addr:full":"352 Ryders Ln Milltown NJ 08850",
    "addr:housenumber":"352",
    "addr:postcode":"08850",
    "addr:street":"Ryders Ln",
    "iso:country":"US",
    "sg:address":"352 Ryders Ln",
    "sg:city":"Milltown",
    "sg:classifiers":[
        {
            "category":"Shopping",
            "subcategory":"Clothing, Apparel, & Fashions",
            "type":"Retail Goods"
        },
        {
            "category":"Autos & Motor Vehicles",
            "subcategory":"Auto Supplies",
            "type":"Retail Goods"
        },
        {
            "category":"Retail",
            "subcategory":"Auto Repair",
            "type":"Services"
        }
    ],
    "sg:phone":"+1 732 390 5557",
    "sg:postcode":"08850",
    "sg:province":"NJ",
    "sg:tags":[
        "automobile",
        "part",
        "clothing",
        "store",
        "accessory"
    ],
    "wof:name":"Strauss Discount Auto",
    "wof:placetype":"venue"
},
  "geometry": {"coordinates":[-74.42321699999999,40.440967],"type":"Point"}
}