{
  "type": "Feature",
  "properties": {
    "addr:full":"5 S Broad St Woodbury NJ 08096",
    "addr:housenumber":"5",
    "addr:postcode":"08096",
    "addr:street":"S Broad St",
    "iso:country":"US",
    "sg:address":"5 S Broad St",
    "sg:city":"Woodbury",
    "sg:classifiers":[
        {
            "category":"Shopping",
            "subcategory":"Jewelry",
            "type":"Retail Goods"
        }
    ],
    "sg:phone":"+1   ",
    "sg:postcode":"08096",
    "sg:province":"NJ",
    "wof:name":"Saloff Jewelers",
    "wof:placetype":"venue"
},
  "geometry": {"coordinates":[-75.15392300000001,39.837328],"type":"Point"}
}