{
  "type": "Feature",
  "properties": {
    "iso:country":"US",
    "sg:address":"613 Sagamore Ave",
    "sg:city":"Teaneck",
    "sg:classifiers":[
        {
            "category":"Health Services",
            "subcategory":"Doctor",
            "type":"Services"
        }
    ],
    "sg:phone":"+1 201 836 7447",
    "sg:postcode":"07666",
    "sg:province":"NJ",
    "sg:tags":[
        "dentist"
    ],
    "wof:name":"M Millstein DDS",
    "wof:placetype":"venue"
},
  "geometry": {"coordinates":[-74.025904,40.895034],"type":"Point"}
}