{
  "type": "Feature",
  "properties": {
    "iso:country":"US",
    "sg:address":"530 Galahad Ct",
    "sg:city":"Mantua",
    "sg:classifiers":[
        {
            "category":"Restaurant",
            "type":"Food & Drink"
        }
    ],
    "sg:phone":"+1   ",
    "sg:postcode":"08051",
    "sg:province":"NJ",
    "wof:name":"Benjamins Restaurant",
    "wof:placetype":"venue"
},
  "geometry": {"coordinates":[-75.18342,39.789094],"type":"Point"}
}