{
  "type": "Feature",
  "properties": {
    "iso:country":"US",
    "sg:address":"429 W Rio Grande Ave",
    "sg:city":"Wildwood",
    "sg:classifiers":[
        {
            "category":"Retail",
            "subcategory":"Auto Rental",
            "type":"Services"
        }
    ],
    "sg:phone":"+1 609 522 0049",
    "sg:postcode":"08260",
    "sg:province":"NJ",
    "sg:tags":[
        "renting",
        "car",
        "leasing",
        "truck"
    ],
    "wof:name":"Just Four Wheels Inc",
    "wof:placetype":"venue"
},
  "geometry": {"coordinates":[-74.829498,38.9879],"type":"Point"}
}