{
  "type": "Feature",
  "properties": {
    "iso:country":"US",
    "sg:address":"510 S Burnt Mill Rd",
    "sg:city":"Voorhees",
    "sg:classifiers":[
        {
            "category":"Insurance",
            "subcategory":"Insurance Agent",
            "type":"Services"
        }
    ],
    "sg:phone":"+1 856 354 0970",
    "sg:postcode":"08043",
    "sg:province":"NJ",
    "wof:name":"Dominic A Dilelsi",
    "wof:placetype":"venue"
},
  "geometry": {"coordinates":[-75.00704,39.850427],"type":"Point"}
}