{
  "type": "Feature",
  "properties": {
    "addr:full":"399 Marlton Pike E Cherry Hill NJ 08034",
    "addr:housenumber":"399",
    "addr:postcode":"08034",
    "addr:street":"Marlton Pike E",
    "iso:country":"US",
    "sg:address":"399 Marlton Pike E",
    "sg:city":"Cherry Hill",
    "sg:classifiers":[
        {
            "category":"Banks & Credit Unions",
            "subcategory":"Bank",
            "type":"Services"
        }
    ],
    "sg:phone":"+1   ",
    "sg:postcode":"08034",
    "sg:province":"NJ",
    "sg:tags":[
        "national",
        "commercial"
    ],
    "wof:name":"Wachovia Bank National Assn",
    "wof:placetype":"venue"
},
  "geometry": {"coordinates":[-75.00283399999999,39.912396],"type":"Point"}
}