{
  "type": "Feature",
  "properties": {
    "addr:full":"1039 Clayton Rd Williamstown NJ 08094",
    "addr:housenumber":"1039",
    "addr:postcode":"08094",
    "addr:street":"Clayton Rd",
    "iso:country":"US",
    "sg:address":"1039 Clayton Rd",
    "sg:city":"Williamstown",
    "sg:classifiers":[
        {
            "category":"Recreation",
            "type":"Entertainment"
        }
    ],
    "sg:phone":"+1 856 629 9708",
    "sg:postcode":"08094",
    "sg:province":"NJ",
    "wof:name":"Ruggiano Diving Co Inc",
    "wof:placetype":"venue"
},
  "geometry": {"coordinates":[-75.01953899999999,39.667487],"type":"Point"}
}