{
  "type": "Feature",
  "properties": {
    "addr:full":"370 Morris Ave Elizabeth NJ 07208",
    "addr:housenumber":"370",
    "addr:postcode":"07208",
    "addr:street":"Morris Ave",
    "iso:country":"US",
    "sg:address":"370 Morris Ave",
    "sg:city":"Elizabeth",
    "sg:classifiers":[
        {
            "category":"Restaurant",
            "type":"Food & Drink"
        }
    ],
    "sg:phone":"+1 908 353 8825",
    "sg:postcode":"07208",
    "sg:province":"NJ",
    "sg:tags":[
        "parlor",
        "ice",
        "cream"
    ],
    "sg:website":"www.baskinrobbins.com",
    "wof:name":"Baskin-Robbins",
    "wof:placetype":"venue"
},
  "geometry": {"coordinates":[-74.220006,40.670539],"type":"Point"}
}