{
  "type": "Feature",
  "properties": {
    "iso:country":"US",
    "sg:address":"90 Wilson Ave",
    "sg:city":"Englishtown",
    "sg:classifiers":[
        {
            "category":"Shopping",
            "subcategory":"Hobbies, Toys, & Games",
            "type":"Retail Goods"
        },
        {
            "category":"Shopping",
            "subcategory":"Jewelry",
            "type":"Retail Goods"
        }
    ],
    "sg:phone":"+1 732 446 3400",
    "sg:postcode":"07726",
    "sg:province":"NJ",
    "sg:tags":[
        "diamond"
    ],
    "wof:name":"Fine Jeweler Inc",
    "wof:placetype":"venue"
},
  "geometry": {"coordinates":[-74.360759,40.311917],"type":"Point"}
}