{
  "type": "Feature",
  "properties": {
    "iso:country":"US",
    "sg:address":"1311 Market St",
    "sg:city":"Gloucester City",
    "sg:classifiers":[
        {
            "category":"Home & Garden",
            "subcategory":"Hardware",
            "type":"Retail Goods"
        }
    ],
    "sg:phone":"+1 856 456 9506",
    "sg:postcode":"08030",
    "sg:province":"NJ",
    "sg:tags":[
        "store"
    ],
    "wof:name":"Gloucester Hardware & Paints",
    "wof:placetype":"venue"
},
  "geometry": {"coordinates":[-75.11176500000001,39.887915],"type":"Point"}
}