{
  "type": "Feature",
  "properties": {
    "iso:country":"US",
    "sg:address":"241 Pleasant Plains Rd",
    "sg:city":"Stirling",
    "sg:classifiers":[
        {
            "category":"Building & Trades",
            "subcategory":"Construction",
            "type":"Services"
        }
    ],
    "sg:phone":"+1 908 647 7967",
    "sg:postcode":"07980",
    "sg:province":"NJ",
    "sg:tags":[
        "home",
        "builder"
    ],
    "wof:name":"Green Hill Development Co",
    "wof:placetype":"venue"
},
  "geometry": {"coordinates":[-74.496027,40.6955],"type":"Point"}
}