{
  "type": "Feature",
  "properties": {
    "addr:full":"77 Littleton Ave Newark NJ 07107",
    "addr:housenumber":"77",
    "addr:postcode":"07107",
    "addr:street":"Littleton Ave",
    "iso:country":"US",
    "sg:address":"77 Littleton Ave",
    "sg:city":"Newark",
    "sg:classifiers":[
        {
            "category":"Personal",
            "type":"Services"
        }
    ],
    "sg:phone":"+1 973 242 0338",
    "sg:postcode":"07107",
    "sg:province":"NJ",
    "sg:tags":[
        "therapist",
        "massage"
    ],
    "wof:name":"DTI Back Massage Parlour",
    "wof:placetype":"venue"
},
  "geometry": {"coordinates":[-74.193912,40.743673],"type":"Point"}
}