{
  "type": "Feature",
  "properties": {
    "iso:country":"US",
    "sg:address":"11 Ocean Ave",
    "sg:city":"Ocean City",
    "sg:classifiers":[
        {
            "category":"Travel",
            "subcategory":"Hotels & Motels",
            "type":"Entertainment"
        }
    ],
    "sg:phone":"+1   ",
    "sg:postcode":"08226",
    "sg:province":"NJ",
    "sg:tags":[
        "operation"
    ],
    "wof:name":"Ocean Manor Hotel",
    "wof:placetype":"venue"
},
  "geometry": {"coordinates":[-74.562659,39.285907],"type":"Point"}
}