{
  "type": "Feature",
  "properties": {
    "addr:full":"101 E Main St Moorestown NJ 08057",
    "addr:housenumber":"101",
    "addr:postcode":"08057",
    "addr:street":"E Main St",
    "iso:country":"US",
    "sg:address":"101 E Main St",
    "sg:city":"Moorestown",
    "sg:classifiers":[
        {
            "category":"Real Estate",
            "subcategory":"Architect",
            "type":"Services"
        },
        {
            "category":"Professional",
            "subcategory":"Business Services",
            "type":"Services"
        }
    ],
    "sg:phone":"+1 856 235 0175",
    "sg:postcode":"08057",
    "sg:province":"NJ",
    "sg:tags":[
        "interior",
        "consultant",
        "design",
        "decorator",
        "architectural"
    ],
    "wof:name":"Duca Huder & Kumlin",
    "wof:placetype":"venue"
},
  "geometry": {"coordinates":[-74.940507,39.965835],"type":"Point"}
}