{
  "type": "Feature",
  "properties": {
    "addr:full":"239 Long Pond Rd Hewitt NJ 07421",
    "addr:housenumber":"239",
    "addr:postcode":"07421",
    "addr:street":"Long Pond Rd",
    "iso:country":"US",
    "sg:address":"239 Long Pond Rd",
    "sg:city":"Hewitt",
    "sg:classifiers":[
        {
            "category":"Professional",
            "type":"Services"
        }
    ],
    "sg:phone":"+1   ",
    "sg:postcode":"07421",
    "sg:province":"NJ",
    "wof:name":"Jones R & Bass A",
    "wof:placetype":"venue"
},
  "geometry": {"coordinates":[-74.339082,41.151213],"type":"Point"}
}