{
  "type": "Feature",
  "properties": {
    "addr:full":"1420 Irving St Rahway NJ 07065",
    "addr:housenumber":"1420",
    "addr:postcode":"07065",
    "addr:street":"Irving St",
    "iso:country":"US",
    "sg:address":"1420 Irving St",
    "sg:city":"Rahway",
    "sg:classifiers":[
        {
            "category":"Professional",
            "subcategory":"Lawyer & Legal Services",
            "type":"Services"
        }
    ],
    "sg:phone":"+1 732 382 5111",
    "sg:postcode":"07065",
    "sg:province":"NJ",
    "sg:tags":[
        "attorney"
    ],
    "wof:name":"Anthony V Caruso",
    "wof:placetype":"venue"
},
  "geometry": {"coordinates":[-74.275638,40.606907],"type":"Point"}
}