{
  "type": "Feature",
  "properties": {
    "iso:country":"US",
    "sg:address":"550 Co Rd 530",
    "sg:city":"Whiting",
    "sg:classifiers":[
        {
            "category":"Personal",
            "type":"Services"
        }
    ],
    "sg:phone":"+1 732 716 0600",
    "sg:postcode":"08759",
    "sg:province":"NJ",
    "sg:tags":[
        "therapist",
        "massage"
    ],
    "wof:name":"Miracle Touch Therapeutic",
    "wof:placetype":"venue"
},
  "geometry": {"coordinates":[-74.351456,39.946804],"type":"Point"}
}