{
  "type": "Feature",
  "properties": {
    "addr:full":"470 2nd St Palisades Park NJ 07650",
    "addr:housenumber":"470",
    "addr:postcode":"07650",
    "addr:street":"2Nd St",
    "iso:country":"US",
    "sg:address":"470 2nd St",
    "sg:city":"Palisades Park",
    "sg:classifiers":[
        {
            "category":"Retail",
            "subcategory":"Repair Shop",
            "type":"Services"
        }
    ],
    "sg:phone":"+1 201 947 5222",
    "sg:postcode":"07650",
    "sg:province":"NJ",
    "sg:tags":[
        "equipment",
        "telephone",
        "system"
    ],
    "wof:name":"Tel It Communications Inc",
    "wof:placetype":"venue"
},
  "geometry": {"coordinates":[-73.99358700000001,40.849398],"type":"Point"}
}