{
  "type": "Feature",
  "properties": {
    "iso:country":"US",
    "sg:address":"1 Corrigan Ave",
    "sg:city":"Bayville",
    "sg:classifiers":[
        {
            "category":"Recreation",
            "subcategory":"Marina",
            "type":"Entertainment"
        }
    ],
    "sg:phone":"+1 732 244 2106",
    "sg:postcode":"08741",
    "sg:province":"NJ",
    "wof:name":"Riverbank Marina",
    "wof:placetype":"venue"
},
  "geometry": {"coordinates":[-74.15486199999999,39.934622],"type":"Point"}
}