{
  "type": "Feature",
  "properties": {
    "addr:full":"1309 Main St Belmar NJ 07719",
    "addr:housenumber":"1309",
    "addr:postcode":"07719",
    "addr:street":"Main St",
    "iso:country":"US",
    "sg:address":"1309 Main St",
    "sg:city":"Belmar",
    "sg:classifiers":[
        {
            "category":"Bars & Pubs",
            "type":"Food & Drink"
        }
    ],
    "sg:phone":"+1   ",
    "sg:postcode":"07719",
    "sg:province":"NJ",
    "sg:tags":[
        "tavern",
        "liquor",
        "packaged"
    ],
    "wof:name":"Boat House Bar & Grill",
    "wof:placetype":"venue"
},
  "geometry": {"coordinates":[-74.026765,40.176375],"type":"Point"}
}