{
  "type": "Feature",
  "properties": {
    "iso:country":"US",
    "sg:address":"400 Valentine St",
    "sg:city":"Hackettstown",
    "sg:classifiers":[
        {
            "category":"Building & Trades",
            "subcategory":"Construction",
            "type":"Services"
        }
    ],
    "sg:phone":"+1 908 813 8383",
    "sg:postcode":"07840",
    "sg:province":"NJ",
    "sg:tags":[
        "new",
        "remodeling",
        "commercial"
    ],
    "wof:name":"Internorth Contracting Corp",
    "wof:placetype":"venue"
},
  "geometry": {"coordinates":[-74.834249,40.851521],"type":"Point"}
}