{
  "type": "Feature",
  "properties": {
    "addr:full":"3 Anderson Ct Marlton NJ 08053",
    "addr:housenumber":"3",
    "addr:postcode":"08053",
    "addr:street":"Anderson Ct",
    "iso:country":"US",
    "sg:address":"3 Anderson Ct",
    "sg:city":"Marlton",
    "sg:classifiers":[
        {
            "category":"Travel",
            "subcategory":"Travel Agent",
            "type":"Entertainment"
        }
    ],
    "sg:phone":"+1 856 596 2525",
    "sg:postcode":"08053",
    "sg:province":"NJ",
    "sg:tags":[
        "agency",
        "bureau"
    ],
    "wof:name":"Cousin Frank's Travel",
    "wof:placetype":"venue"
},
  "geometry": {"coordinates":[-74.870666,39.903874],"type":"Point"}
}