{
  "type": "Feature",
  "properties": {
    "addr:full":"96 Hilltop Rd Basking Ridge NJ 07920",
    "addr:housenumber":"96",
    "addr:postcode":"07920",
    "addr:street":"Hilltop Rd",
    "iso:country":"US",
    "sg:address":"96 Hilltop Rd",
    "sg:city":"Basking Ridge",
    "sg:classifiers":[
        {
            "category":"Utilities",
            "subcategory":"Telephone",
            "type":"Services"
        }
    ],
    "sg:phone":"+1 908 696 9135",
    "sg:postcode":"07920",
    "sg:province":"NJ",
    "sg:tags":[
        "company"
    ],
    "wof:name":"A T & T",
    "wof:placetype":"venue"
},
  "geometry": {"coordinates":[-74.531588,40.686628],"type":"Point"}
}