{
  "type": "Feature",
  "properties": {
    "iso:country":"US",
    "sg:address":"4130 US Highway 130 North N",
    "sg:city":"Willingboro",
    "sg:classifiers":[
        {
            "category":"Professional",
            "subcategory":"Accounting & Tax Preparation",
            "type":"Services"
        }
    ],
    "sg:phone":"+1 856 461 8900",
    "sg:postcode":"08046",
    "sg:province":"NJ",
    "sg:tags":[
        "accountant"
    ],
    "sg:website":"www.confidentialtaxservice.com",
    "wof:name":"Confidential Tax Service",
    "wof:placetype":"venue"
},
  "geometry": {"coordinates":[-74.92138300000001,40.035309],"type":"Point"}
}