{
  "type": "Feature",
  "properties": {
    "addr:full":"Phoenix Ave Morristown NJ 07960",
    "addr:postcode":"07960",
    "addr:street":"Phoenix Ave",
    "iso:country":"US",
    "sg:address":"Phoenix Ave",
    "sg:city":"Morristown",
    "sg:classifiers":[
        {
            "category":"Professional",
            "subcategory":"Advertising",
            "type":"Services"
        }
    ],
    "sg:phone":"+1 973 538 9066",
    "sg:postcode":"07960",
    "sg:province":"NJ",
    "sg:tags":[
        "development",
        "programming",
        "seo",
        "marketing",
        "web-design"
    ],
    "sg:website":"http://www.itcn.com",
    "wof:name":"ITCN Web Development",
    "wof:placetype":"venue"
},
  "geometry": {"coordinates":[-74.488784,40.797388],"type":"Point"}
}