{
  "type": "Feature",
  "properties": {
    "iso:country":"US",
    "sg:address":"44 Brooklake Rd",
    "sg:city":"Madison",
    "sg:classifiers":[
        {
            "category":"Professional",
            "subcategory":"Advertising",
            "type":"Services"
        }
    ],
    "sg:phone":"+1 973 377 6866",
    "sg:postcode":"07940",
    "sg:province":"NJ",
    "sg:tags":[
        "agency"
    ],
    "wof:name":"Home-Work",
    "wof:placetype":"venue"
},
  "geometry": {"coordinates":[-74.39375099999999,40.749531],"type":"Point"}
}