{
  "type": "Feature",
  "properties": {
    "iso:country":"US",
    "sg:address":"111 Grand Pl",
    "sg:city":"Kearny",
    "sg:classifiers":[
        {
            "category":"Health Services",
            "subcategory":"Doctor",
            "type":"Services"
        }
    ],
    "sg:phone":"+1 201 998 2142",
    "sg:postcode":"07032",
    "sg:province":"NJ",
    "wof:name":"Killilea Edward M MD",
    "wof:placetype":"venue"
},
  "geometry": {"coordinates":[-74.139999,40.781502],"type":"Point"}
}