{
  "type": "Feature",
  "properties": {
    "iso:country":"US",
    "sg:address":"77 Buckingham Rd",
    "sg:city":"Montclair",
    "sg:classifiers":[
        {
            "category":"Professional",
            "subcategory":"Computer Services",
            "type":"Services"
        }
    ],
    "sg:phone":"+1 973 746 8395",
    "sg:postcode":"07043",
    "sg:province":"NJ",
    "sg:tags":[
        "consultant",
        "designer"
    ],
    "wof:name":"Aztek Computer Svc",
    "wof:placetype":"venue"
},
  "geometry": {"coordinates":[-74.19391899999999,40.844404],"type":"Point"}
}