{
  "type": "Feature",
  "properties": {
    "addr:full":"21 Treeview Cir Scotch Plains NJ 07076",
    "addr:housenumber":"21",
    "addr:postcode":"07076",
    "addr:street":"Treeview Cir",
    "iso:country":"US",
    "sg:address":"21 Treeview Cir",
    "sg:city":"Scotch Plains",
    "sg:classifiers":[
        {
            "category":"Professional",
            "subcategory":"Management & Consulting",
            "type":"Services"
        }
    ],
    "sg:phone":"+1 908 322 0767",
    "sg:postcode":"07076",
    "sg:province":"NJ",
    "wof:name":"Ssi Advisors Inc",
    "wof:placetype":"venue"
},
  "geometry": {"coordinates":[-74.382532,40.616741],"type":"Point"}
}