{
  "type": "Feature",
  "properties": {
    "iso:country":"US",
    "sg:address":"39 Roseberry St Ste B",
    "sg:city":"Phillipsburg",
    "sg:classifiers":[
        {
            "category":"Health Services",
            "subcategory":"Doctor",
            "type":"Services"
        }
    ],
    "sg:phone":"+1 908 859 5323",
    "sg:postcode":"08865",
    "sg:province":"NJ",
    "sg:tags":[
        "medicine",
        "physician",
        "surgeon",
        "internal",
        "surgeons"
    ],
    "wof:name":"Dilip Bera Md",
    "wof:placetype":"venue"
},
  "geometry": {"coordinates":[-75.18124899999999,40.704292],"type":"Point"}
}