{
  "type": "Feature",
  "properties": {
    "iso:country":"US",
    "sg:address":"1668 Irene Ct",
    "sg:city":"Teaneck",
    "sg:classifiers":[
        {
            "category":"Real Estate",
            "subcategory":"Developer",
            "type":"Services"
        }
    ],
    "sg:phone":"+1   ",
    "sg:postcode":"07666",
    "sg:province":"NJ",
    "sg:tags":[
        "development",
        "land"
    ],
    "wof:name":"White Development LLC",
    "wof:placetype":"venue"
},
  "geometry": {"coordinates":[-73.992788,40.904906],"type":"Point"}
}