{
  "type": "Feature",
  "properties": {
    "addr:full":"500 Valley Rd. Clifton NJ 07013",
    "addr:housenumber":"500",
    "addr:postcode":"07013",
    "addr:street":"Valley Rd.",
    "iso:country":"US",
    "sg:address":"500 Valley Rd.",
    "sg:city":"Clifton",
    "sg:classifiers":[
        {
            "category":"Professional",
            "type":"Services"
        }
    ],
    "sg:phone":"+1 973 684 9993",
    "sg:postcode":"07013",
    "sg:province":"NJ",
    "sg:tags":[
        "planning",
        "event"
    ],
    "sg:website":"www.circusfun.net",
    "wof:name":"Circus \u00a0Fun Entertainment",
    "wof:placetype":"venue"
},
  "geometry": {"coordinates":[-74.18078300000001,40.882075],"type":"Point"}
}