{
  "type": "Feature",
  "properties": {
    "addr:full":"69 Broadway Park Ridge NJ 07656",
    "addr:housenumber":"69",
    "addr:postcode":"07656",
    "addr:street":"Broadway",
    "iso:country":"US",
    "sg:address":"69 Broadway",
    "sg:city":"Park Ridge",
    "sg:classifiers":[
        {
            "category":"Building & Trades",
            "subcategory":"Landscaping Services",
            "type":"Services"
        }
    ],
    "sg:phone":"+1 201 391 9471",
    "sg:postcode":"07656",
    "sg:province":"NJ",
    "sg:tags":[
        "landscape",
        "contractor"
    ],
    "wof:name":"Rob Paton Landscaping Inc",
    "wof:placetype":"venue"
},
  "geometry": {"coordinates":[-74.038663,41.028664],"type":"Point"}
}