{
  "type": "Feature",
  "properties": {
    "addr:full":"214 Dunellen Ave Dunellen NJ 08812",
    "addr:housenumber":"214",
    "addr:postcode":"08812",
    "addr:street":"Dunellen Ave",
    "iso:country":"US",
    "sg:address":"214 Dunellen Ave",
    "sg:city":"Dunellen",
    "sg:classifiers":[
        {
            "category":"Social Services",
            "type":"Services"
        }
    ],
    "sg:phone":"+1   ",
    "sg:postcode":"08812",
    "sg:province":"NJ",
    "sg:tags":[
        "outreach",
        "ministry"
    ],
    "wof:name":"Palabra De Fuego Ministires",
    "wof:placetype":"venue"
},
  "geometry": {"coordinates":[-74.46320299999999,40.594539],"type":"Point"}
}