{
  "type": "Feature",
  "properties": {
    "addr:full":"23 Westfield Ave E Roselle Park NJ 07204",
    "addr:housenumber":"23",
    "addr:postcode":"07204",
    "addr:street":"Westfield Ave E",
    "iso:country":"US",
    "sg:address":"23 Westfield Ave E",
    "sg:city":"Roselle Park",
    "sg:classifiers":[
        {
            "category":"Cinema",
            "subcategory":"Movie Theater",
            "type":"Entertainment"
        }
    ],
    "sg:phone":"+1 908 241 2525",
    "sg:postcode":"07204",
    "sg:province":"NJ",
    "wof:name":"New Park Cinemas",
    "wof:placetype":"venue"
},
  "geometry": {"coordinates":[-74.26151900000001,40.662049],"type":"Point"}
}