{
  "type": "Feature",
  "properties": {
    "addr:full":"70 S Broad St Woodbury NJ 08096",
    "addr:housenumber":"70",
    "addr:postcode":"08096",
    "addr:street":"S Broad St",
    "iso:country":"US",
    "sg:address":"70 S Broad St",
    "sg:city":"Woodbury",
    "sg:classifiers":[
        {
            "category":"Professional",
            "subcategory":"Lawyer & Legal Services",
            "type":"Services"
        }
    ],
    "sg:phone":"+1 856 853 5995",
    "sg:postcode":"08096",
    "sg:province":"NJ",
    "wof:name":"Allan E Richardson",
    "wof:placetype":"venue"
},
  "geometry": {"coordinates":[-75.154083,39.836872],"type":"Point"}
}