{
  "type": "Feature",
  "properties": {
    "iso:country":"US",
    "sg:address":"42 Daylily Dr",
    "sg:city":"Mount Laurel",
    "sg:classifiers":[
        {
            "category":"Wholesale",
            "subcategory":"Computers",
            "type":"Manufacturing & Wholesale Goods"
        }
    ],
    "sg:phone":"+1 856 234 9298",
    "sg:postcode":"08054",
    "sg:province":"NJ",
    "wof:name":"Sympro Inc",
    "wof:placetype":"venue"
},
  "geometry": {"coordinates":[-74.873689,39.927157],"type":"Point"}
}