{
  "type": "Feature",
  "properties": {
    "iso:country":"US",
    "sg:address":"26 Port Imperial Blvd",
    "sg:city":"West New York",
    "sg:classifiers":[
        {
            "category":"Building & Trades",
            "subcategory":"Construction",
            "type":"Services"
        }
    ],
    "sg:phone":"+1 201 974 8870",
    "sg:postcode":"07093",
    "sg:province":"NJ",
    "sg:tags":[
        "home",
        "builder"
    ],
    "wof:name":"Provident Homes",
    "wof:placetype":"venue"
},
  "geometry": {"coordinates":[-74.01015,40.782832],"type":"Point"}
}