{
  "type": "Feature",
  "properties": {
    "iso:country":"US",
    "sg:address":"28 Fox Hill Rd",
    "sg:city":"Califon",
    "sg:classifiers":[
        {
            "category":"Recreation",
            "type":"Entertainment"
        }
    ],
    "sg:phone":"+1 908 439 3901",
    "sg:postcode":"07830",
    "sg:province":"NJ",
    "sg:tags":[
        "riding",
        "academy"
    ],
    "wof:name":"Ponyshare's Party Ponies",
    "wof:placetype":"venue"
},
  "geometry": {"coordinates":[-74.75916599999999,40.699045],"type":"Point"}
}