{
  "type": "Feature",
  "properties": {
    "iso:country":"US",
    "sg:address":"2740 W Bangs Ave",
    "sg:city":"Neptune",
    "sg:classifiers":[
        {
            "category":"Building & Trades",
            "subcategory":"Cleaning & Sanitation",
            "type":"Services"
        }
    ],
    "sg:phone":"+1   ",
    "sg:postcode":"07753",
    "sg:province":"NJ",
    "sg:tags":[
        "maintenance"
    ],
    "wof:name":"Dons Maintenance",
    "wof:placetype":"venue"
},
  "geometry": {"coordinates":[-74.05679600000001,40.219968],"type":"Point"}
}