{
  "type": "Feature",
  "properties": {
    "iso:country":"US",
    "sg:address":"2012 86th St",
    "sg:city":"North Bergen",
    "sg:classifiers":[
        {
            "category":"Wholesale",
            "subcategory":"Construction Materials",
            "type":"Manufacturing & Wholesale Goods"
        }
    ],
    "sg:phone":"+1 201 869 4181",
    "sg:postcode":"07047",
    "sg:province":"NJ",
    "sg:tags":[
        "metal",
        "mfg"
    ],
    "sg:website":"www.fivestarwindows.com",
    "wof:name":"Five Star Building Products",
    "wof:placetype":"venue"
},
  "geometry": {"coordinates":[-74.01395599999999,40.811123],"type":"Point"}
}