{
  "type": "Feature",
  "properties": {
    "iso:country":"US",
    "sg:address":"89 Compton St",
    "sg:city":"Belford",
    "sg:classifiers":[
        {
            "category":"Building & Trades",
            "subcategory":"Construction",
            "type":"Services"
        }
    ],
    "sg:phone":"+1 732 495 3527",
    "sg:postcode":"07718",
    "sg:province":"NJ",
    "sg:tags":[
        "home",
        "contractor"
    ],
    "wof:name":"Vincent Walsh Construction",
    "wof:placetype":"venue"
},
  "geometry": {"coordinates":[-74.089618,40.425721],"type":"Point"}
}