{
  "type": "Feature",
  "properties": {
    "addr:full":"100 Regional Ct Flemington NJ 08822",
    "addr:housenumber":"100",
    "addr:postcode":"08822",
    "addr:street":"Regional Ct",
    "iso:country":"US",
    "sg:address":"100 Regional Ct",
    "sg:city":"Flemington",
    "sg:classifiers":[
        {
            "category":"Real Estate",
            "subcategory":"Real Estate Operator",
            "type":"Services"
        }
    ],
    "sg:phone":"+1 908 782 1756",
    "sg:postcode":"08822",
    "sg:province":"NJ",
    "sg:tags":[
        "apartment"
    ],
    "wof:name":"Regional Court Apartments",
    "wof:placetype":"venue"
},
  "geometry": {"coordinates":[-74.85464399999999,40.51723],"type":"Point"}
}