{
  "type": "Feature",
  "properties": {
    "addr:full":"115 Elm Ave Maple Shade NJ 08052",
    "addr:housenumber":"115",
    "addr:postcode":"08052",
    "addr:street":"Elm Ave",
    "iso:country":"US",
    "sg:address":"115 Elm Ave",
    "sg:city":"Maple Shade",
    "sg:classifiers":[
        {
            "category":"Building & Trades",
            "subcategory":"Construction",
            "type":"Services"
        }
    ],
    "sg:phone":"+1 856 779 7477",
    "sg:postcode":"08052",
    "sg:province":"NJ",
    "sg:tags":[
        "remodeling",
        "contractor"
    ],
    "wof:name":"Rebco Wndows Doors Siding More",
    "wof:placetype":"venue"
},
  "geometry": {"coordinates":[-75.000456,39.952908],"type":"Point"}
}