{
  "type": "Feature",
  "properties": {
    "addr:full":"4 Main St Allenhurst NJ 07711",
    "addr:housenumber":"4",
    "addr:postcode":"07711",
    "addr:street":"Main St",
    "iso:country":"US",
    "sg:address":"4 Main St",
    "sg:city":"Allenhurst",
    "sg:classifiers":[
        {
            "category":"Government",
            "subcategory":"Post Office",
            "type":"Public Place"
        }
    ],
    "sg:phone":"+1 732 531 3114",
    "sg:postcode":"07711",
    "sg:province":"NJ",
    "wof:name":"US Post Office",
    "wof:placetype":"venue"
},
  "geometry": {"coordinates":[-74.005415,40.238888],"type":"Point"}
}