{
  "type": "Feature",
  "properties": {
    "addr:full":"266 E Main St Ramsey NJ 07446",
    "addr:housenumber":"266",
    "addr:postcode":"07446",
    "addr:street":"E Main St",
    "iso:country":"US",
    "sg:address":"266 E Main St",
    "sg:city":"Ramsey",
    "sg:classifiers":[
        {
            "category":"Education",
            "subcategory":"School",
            "type":"Public Place"
        }
    ],
    "sg:phone":"+1   ",
    "sg:postcode":"07446",
    "sg:province":"NJ",
    "sg:tags":[
        "elementary",
        "secondary"
    ],
    "wof:name":"Ramsey School Dist",
    "wof:placetype":"venue"
},
  "geometry": {"coordinates":[-74.13382900000001,41.057899],"type":"Point"}
}