{
  "type": "Feature",
  "properties": {
    "addr:full":"1301 State Rt 23 Butler NJ 07405",
    "addr:housenumber":"1301",
    "addr:postcode":"07405",
    "addr:street":"State Rt 23",
    "iso:country":"US",
    "sg:address":"1301 State Rt 23",
    "sg:city":"Butler",
    "sg:classifiers":[
        {
            "category":"Autos & Motor Vehicles",
            "subcategory":"Automobile Sales",
            "type":"Retail Goods"
        },
        {
            "category":"Retail",
            "subcategory":"Auto Rental",
            "type":"Services"
        }
    ],
    "sg:phone":"+1 973 838 0820",
    "sg:postcode":"07405",
    "sg:province":"NJ",
    "sg:tags":[
        "car"
    ],
    "wof:name":"Route 23 Auto Mall Llc",
    "wof:placetype":"venue"
},
  "geometry": {"coordinates":[-74.348099,40.992401],"type":"Point"}
}