{
  "type": "Feature",
  "properties": {
    "addr:full":"11 Sommer Ave Maplewood NJ 07040",
    "addr:housenumber":"11",
    "addr:postcode":"07040",
    "addr:street":"Sommer Ave",
    "iso:country":"US",
    "sg:address":"11 Sommer Ave",
    "sg:city":"Maplewood",
    "sg:classifiers":[
        {
            "category":"Professional",
            "subcategory":"Management & Consulting",
            "type":"Services"
        }
    ],
    "sg:phone":"+1   ",
    "sg:postcode":"07040",
    "sg:province":"NJ",
    "sg:tags":[
        "consultant",
        "planning"
    ],
    "wof:name":"Diversified Rick Inc",
    "wof:placetype":"venue"
},
  "geometry": {"coordinates":[-74.275189,40.724482],"type":"Point"}
}