{
  "type": "Feature",
  "properties": {
    "iso:country":"US",
    "sg:address":"115 Newfield Ave",
    "sg:city":"Edison",
    "sg:classifiers":[
        {
            "category":"Communications",
            "subcategory":"Film & Video Production",
            "type":"Services"
        }
    ],
    "sg:phone":"+1 732 225 0001",
    "sg:postcode":"08837",
    "sg:province":"NJ",
    "sg:tags":[
        "duplication",
        "tape"
    ],
    "wof:name":"Synergem",
    "wof:placetype":"venue"
},
  "geometry": {"coordinates":[-74.34685399999999,40.502074],"type":"Point"}
}