{
  "type": "Feature",
  "properties": {
    "addr:full":"81 Franklin Ave Nutley NJ 07110",
    "addr:housenumber":"81",
    "addr:postcode":"07110",
    "addr:street":"Franklin Ave",
    "iso:country":"US",
    "sg:address":"81 Franklin Ave",
    "sg:city":"Nutley",
    "sg:classifiers":[
        {
            "category":"Banks & Credit Unions",
            "subcategory":"Investment Brokerage",
            "type":"Services"
        }
    ],
    "sg:phone":"+1 973 667 1942",
    "sg:postcode":"07110",
    "sg:province":"NJ",
    "sg:tags":[
        "advisory",
        "financial"
    ],
    "wof:name":"Franklin Financial Group",
    "wof:placetype":"venue"
},
  "geometry": {"coordinates":[-74.165043,40.811484],"type":"Point"}
}