{
  "type": "Feature",
  "properties": {
    "addr:full":"24 Church St Paterson NJ 07505",
    "addr:housenumber":"24",
    "addr:postcode":"07505",
    "addr:street":"Church St",
    "iso:country":"US",
    "sg:address":"24 Church St",
    "sg:city":"Paterson",
    "sg:classifiers":[
        {
            "category":"Professional",
            "subcategory":"Lawyer & Legal Services",
            "type":"Services"
        }
    ],
    "sg:phone":"+1 973 684 2745",
    "sg:postcode":"07505",
    "sg:province":"NJ",
    "wof:name":"Yacono Norberto Attorney At Law",
    "wof:placetype":"venue"
},
  "geometry": {"coordinates":[-74.170601,40.917801],"type":"Point"}
}