{
  "type": "Feature",
  "properties": {
    "addr:full":"400 Bloomfield Ave Bloomfield NJ 07003",
    "addr:housenumber":"400",
    "addr:postcode":"07003",
    "addr:street":"Bloomfield Ave",
    "iso:country":"US",
    "sg:address":"400 Bloomfield Ave",
    "sg:city":"Bloomfield",
    "sg:classifiers":[
        {
            "category":"Retail",
            "subcategory":"Auto Repair",
            "type":"Services"
        }
    ],
    "sg:phone":"+1 973 748 3210",
    "sg:postcode":"07003",
    "sg:province":"NJ",
    "wof:name":"Ajar Auto Body",
    "wof:placetype":"venue"
},
  "geometry": {"coordinates":[-74.194397,40.7878],"type":"Point"}
}