{
  "type": "Feature",
  "properties": {
    "addr:full":"886 Springfield Ave Irvington NJ 07111",
    "addr:housenumber":"886",
    "addr:postcode":"07111",
    "addr:street":"Springfield Ave",
    "iso:country":"US",
    "sg:address":"886 Springfield Ave",
    "sg:city":"Irvington",
    "sg:classifiers":[
        {
            "category":"Restaurant",
            "type":"Food & Drink"
        }
    ],
    "sg:phone":"+1   ",
    "sg:postcode":"07111",
    "sg:province":"NJ",
    "sg:tags":[
        "eating"
    ],
    "wof:name":"Jumbo Family Buffet",
    "wof:placetype":"venue"
},
  "geometry": {"coordinates":[-74.22264800000001,40.727876],"type":"Point"}
}