{
  "type": "Feature",
  "properties": {
    "addr:full":"1200 W Park Ave Ocean NJ 07712",
    "addr:housenumber":"1200",
    "addr:postcode":"07712",
    "addr:street":"W Park Ave",
    "iso:country":"US",
    "sg:address":"1200 W Park Ave",
    "sg:city":"Ocean",
    "sg:classifiers":[
        {
            "category":"Travel",
            "subcategory":"Campground",
            "type":"Entertainment"
        }
    ],
    "sg:phone":"+1 732 493 3780",
    "sg:postcode":"07712",
    "sg:province":"NJ",
    "sg:tags":[
        "camp"
    ],
    "wof:name":"David Day Camp Nursery",
    "wof:placetype":"venue"
},
  "geometry": {"coordinates":[-74.065203,40.25959],"type":"Point"}
}