{
  "type": "Feature",
  "properties": {
    "iso:country":"US",
    "sg:address":"513 Pleasant Valley Ave",
    "sg:city":"Moorestown",
    "sg:classifiers":[
        {
            "category":"Shopping",
            "subcategory":"Bicycles & Sporting Goods",
            "type":"Retail Goods"
        },
        {
            "category":"Wholesale",
            "subcategory":"Sporting Goods",
            "type":"Manufacturing & Wholesale Goods"
        }
    ],
    "sg:phone":"+1 856 234 4448",
    "sg:postcode":"08057",
    "sg:province":"NJ",
    "sg:tags":[
        "golf",
        "supply",
        "equipment",
        "supplies-wholesale",
        "manufacturer"
    ],
    "wof:name":"Jack Jolly & Son Inc",
    "wof:placetype":"venue"
},
  "geometry": {"coordinates":[-74.951134,39.948818],"type":"Point"}
}