{
  "type": "Feature",
  "properties": {
    "addr:full":"16 Montrose St Newark NJ 07106",
    "addr:housenumber":"16",
    "addr:postcode":"07106",
    "addr:street":"Montrose St",
    "iso:country":"US",
    "sg:address":"16 Montrose St",
    "sg:city":"Newark",
    "sg:classifiers":[
        {
            "category":"Social Services",
            "subcategory":"Child Care",
            "type":"Services"
        }
    ],
    "sg:phone":"+1   ",
    "sg:postcode":"07106",
    "sg:province":"NJ",
    "sg:tags":[
        "day"
    ],
    "wof:name":"Cribs & Rattles",
    "wof:placetype":"venue"
},
  "geometry": {"coordinates":[-74.238001,40.744581],"type":"Point"}
}