{
  "type": "Feature",
  "properties": {
    "iso:country":"US",
    "sg:address":"5051 Westfield Ave",
    "sg:city":"Pennsauken",
    "sg:classifiers":[
        {
            "category":"Personal",
            "subcategory":"Nail Salon",
            "type":"Services"
        }
    ],
    "sg:phone":"+1 856 317 5700",
    "sg:postcode":"08110",
    "sg:province":"NJ",
    "wof:name":"Escape Nails & Spa",
    "wof:placetype":"venue"
},
  "geometry": {"coordinates":[-75.06387700000001,39.959737],"type":"Point"}
}