{
  "type": "Feature",
  "properties": {
    "iso:country":"US",
    "sg:address":"325 Main St",
    "sg:city":"Paterson",
    "sg:classifiers":[
        {
            "category":"Banks & Credit Unions",
            "subcategory":"Bank",
            "type":"Services"
        }
    ],
    "sg:phone":"+1 973 523 3000",
    "sg:postcode":"07505",
    "sg:province":"NJ",
    "sg:tags":[
        "financing"
    ],
    "wof:name":"United Auto Finance Inc",
    "wof:placetype":"venue"
},
  "geometry": {"coordinates":[-74.173323,40.914516],"type":"Point"}
}