{
  "type": "Feature",
  "properties": {
    "iso:country":"US",
    "sg:address":"28 Wendy Ct",
    "sg:city":"Jackson",
    "sg:classifiers":[
        {
            "category":"Wholesale",
            "subcategory":"Durable Goods & Equipment",
            "type":"Manufacturing & Wholesale Goods"
        }
    ],
    "sg:phone":"+1 732 364 5035",
    "sg:postcode":"08527",
    "sg:province":"NJ",
    "sg:tags":[
        "fire",
        "extinguisher"
    ],
    "wof:name":"Phoenix Fire Protection",
    "wof:placetype":"venue"
},
  "geometry": {"coordinates":[-74.280344,40.145392],"type":"Point"}
}