{
  "type": "Feature",
  "properties": {
    "addr:full":"128 Woodcrest Rd Cherry Hill NJ 08003",
    "addr:housenumber":"128",
    "addr:postcode":"08003",
    "addr:street":"Woodcrest Rd",
    "iso:country":"US",
    "sg:address":"128 Woodcrest Rd",
    "sg:city":"Cherry Hill",
    "sg:classifiers":[
        {
            "category":"Education",
            "subcategory":"Dance Studio",
            "type":"Public Place"
        }
    ],
    "sg:phone":"+1 856 429 0783",
    "sg:postcode":"08003",
    "sg:province":"NJ",
    "sg:tags":[
        "instruction",
        "dancing"
    ],
    "wof:name":"Happy Feet Dance Studio",
    "wof:placetype":"venue"
},
  "geometry": {"coordinates":[-75.009653,39.8728],"type":"Point"}
}