{
  "type": "Feature",
  "properties": {
    "iso:country":"US",
    "sg:address":"121 Kelly Dr",
    "sg:city":"Edison",
    "sg:classifiers":[
        {
            "category":"Wholesale",
            "subcategory":"Computers",
            "type":"Manufacturing & Wholesale Goods"
        }
    ],
    "sg:phone":"+1 732 549 9264",
    "sg:postcode":"08820",
    "sg:province":"NJ",
    "sg:tags":[
        "textile"
    ],
    "wof:name":"HN International Group Inc",
    "wof:placetype":"venue"
},
  "geometry": {"coordinates":[-74.399618,40.549284],"type":"Point"}
}