{
  "type": "Feature",
  "properties": {
    "addr:full":"121 Hamburg Tpke Bloomingdale NJ 07403",
    "addr:housenumber":"121",
    "addr:postcode":"07403",
    "addr:street":"Hamburg Tpke",
    "iso:country":"US",
    "sg:address":"121 Hamburg Tpke",
    "sg:city":"Bloomingdale",
    "sg:classifiers":[
        {
            "category":"Wholesale",
            "subcategory":"Hardware",
            "type":"Manufacturing & Wholesale Goods"
        }
    ],
    "sg:phone":"+1 973 492 1205",
    "sg:postcode":"07403",
    "sg:province":"NJ",
    "sg:tags":[
        "plumbing"
    ],
    "wof:name":"Nutley Supply",
    "wof:placetype":"venue"
},
  "geometry": {"coordinates":[-74.3409,41.007717],"type":"Point"}
}