{
  "type": "Feature",
  "properties": {
    "addr:full":"100 Clark Ave Ocean Grove NJ 07756",
    "addr:housenumber":"100",
    "addr:postcode":"07756",
    "addr:street":"Clark Ave",
    "iso:country":"US",
    "sg:address":"100 Clark Ave",
    "sg:city":"Ocean Grove",
    "sg:classifiers":[
        {
            "category":"Organizations",
            "subcategory":"Religious Organization",
            "type":"Services"
        }
    ],
    "sg:phone":"+1 732 774 0582",
    "sg:postcode":"07756",
    "sg:province":"NJ",
    "sg:tags":[
        "clergy"
    ],
    "wof:name":"W B Gritman",
    "wof:placetype":"venue"
},
  "geometry": {"coordinates":[-74.011144,40.209135],"type":"Point"}
}