{
  "type": "Feature",
  "properties": {
    "iso:country":"US",
    "sg:address":"1 Broad St",
    "sg:city":"Clifton",
    "sg:classifiers":[
        {
            "category":"Manufacturing",
            "subcategory":"Metals",
            "type":"Manufacturing & Wholesale Goods"
        }
    ],
    "sg:phone":"+1 973 684 3900",
    "sg:postcode":"07011",
    "sg:province":"NJ",
    "sg:tags":[
        "fabricator",
        "sheet"
    ],
    "wof:name":"Denman & Davis",
    "wof:placetype":"venue"
},
  "geometry": {"coordinates":[-74.16807,40.893932],"type":"Point"}
}