{
  "type": "Feature",
  "properties": {
    "iso:country":"US",
    "sg:address":"961 Cherokee Ct",
    "sg:city":"Westfield",
    "sg:classifiers":[
        {
            "category":"Professional",
            "subcategory":"Employment Agencies",
            "type":"Services"
        }
    ],
    "sg:phone":"+1   ",
    "sg:postcode":"07090",
    "sg:province":"NJ",
    "sg:tags":[
        "executive",
        "recruiting"
    ],
    "wof:name":"Garbarini William & Associates",
    "wof:placetype":"venue"
},
  "geometry": {"coordinates":[-74.336319,40.636968],"type":"Point"}
}