{
  "type": "Feature",
  "properties": {
    "addr:full":"362 Griscom Dr Salem NJ 08079",
    "addr:housenumber":"362",
    "addr:postcode":"08079",
    "addr:street":"Griscom Dr",
    "iso:country":"US",
    "sg:address":"362 Griscom Dr",
    "sg:city":"Salem",
    "sg:classifiers":[
        {
            "category":"Building & Trades",
            "subcategory":"Construction",
            "type":"Services"
        }
    ],
    "sg:phone":"+1 856 935 0156",
    "sg:postcode":"08079",
    "sg:province":"NJ",
    "sg:tags":[
        "house"
    ],
    "wof:name":"Robert L Carr",
    "wof:placetype":"venue"
},
  "geometry": {"coordinates":[-75.440327,39.593965],"type":"Point"}
}