{
  "type": "Feature",
  "properties": {
    "iso:country":"US",
    "sg:address":"231 Hamburg Tpke",
    "sg:city":"Bloomingdale",
    "sg:classifiers":[
        {
            "category":"Bars & Pubs",
            "type":"Food & Drink"
        }
    ],
    "sg:phone":"+1 973 838 7365",
    "sg:postcode":"07403",
    "sg:province":"NJ",
    "wof:name":"Stumble Inn",
    "wof:placetype":"venue"
},
  "geometry": {"coordinates":[-74.350098,41.005798],"type":"Point"}
}