{
  "type": "Feature",
  "properties": {
    "iso:country":"US",
    "sg:address":"44 State Rte 35",
    "sg:city":"Neptune",
    "sg:classifiers":[
        {
            "category":"Building & Trades",
            "subcategory":"Construction",
            "type":"Services"
        }
    ],
    "sg:phone":"+1 732 869 0011",
    "sg:postcode":"07753",
    "sg:province":"NJ",
    "sg:tags":[
        "contracting",
        "general"
    ],
    "wof:name":"All Turf Power",
    "wof:placetype":"venue"
},
  "geometry": {"coordinates":[-74.028761,40.212586],"type":"Point"}
}