{
  "type": "Feature",
  "properties": {
    "addr:full":"4 Cambridge Rd Freehold NJ 07728",
    "addr:housenumber":"4",
    "addr:postcode":"07728",
    "addr:street":"Cambridge Rd",
    "iso:country":"US",
    "sg:address":"4 Cambridge Rd",
    "sg:city":"Freehold",
    "sg:classifiers":[
        {
            "category":"Retail",
            "subcategory":"Auto Repair",
            "type":"Services"
        }
    ],
    "sg:phone":"+1 732 462 6314",
    "sg:postcode":"07728",
    "sg:province":"NJ",
    "sg:tags":[
        "automotive"
    ],
    "wof:name":"Bobs Automotive",
    "wof:placetype":"venue"
},
  "geometry": {"coordinates":[-74.29119300000001,40.228826],"type":"Point"}
}