{
  "type": "Feature",
  "properties": {
    "iso:country":"US",
    "sg:address":"201 Laurel Rd",
    "sg:city":"Voorhees",
    "sg:classifiers":[
        {
            "category":"Professional",
            "subcategory":"Business Services",
            "type":"Services"
        }
    ],
    "sg:phone":"+1 856 770 5700",
    "sg:postcode":"08043",
    "sg:province":"NJ",
    "wof:name":"UMD Faculty Business",
    "wof:placetype":"venue"
},
  "geometry": {"coordinates":[-75.001893,39.848307],"type":"Point"}
}