{
  "type": "Feature",
  "properties": {
    "addr:full":"22 Park Hill Ter Princeton Junction NJ 08550",
    "addr:housenumber":"22",
    "addr:postcode":"08550",
    "addr:street":"Park Hill Ter",
    "iso:country":"US",
    "sg:address":"22 Park Hill Ter",
    "sg:city":"Princeton Junction",
    "sg:classifiers":[
        {
            "category":"Professional",
            "subcategory":"Business Services",
            "type":"Services"
        }
    ],
    "sg:phone":"+1   ",
    "sg:postcode":"08550",
    "sg:province":"NJ",
    "wof:name":"Technocality Inc",
    "wof:placetype":"venue"
},
  "geometry": {"coordinates":[-74.610657,40.291656],"type":"Point"}
}