{
  "type": "Feature",
  "properties": {
    "iso:country":"US",
    "sg:address":"1339 US Hwy 9",
    "sg:city":"Cape May Ct Hse",
    "sg:classifiers":[
        {
            "category":"Shopping",
            "subcategory":"Used Merchandise",
            "type":"Retail Goods"
        }
    ],
    "sg:phone":"+1 609 463 1685",
    "sg:postcode":"08210",
    "sg:province":"NJ",
    "sg:tags":[
        "antique"
    ],
    "wof:name":"Cape May Cottage",
    "wof:placetype":"venue"
},
  "geometry": {"coordinates":[-74.85194,39.045491],"type":"Point"}
}