{
  "type": "Feature",
  "properties": {
    "iso:country":"US",
    "sg:address":"135 Burlington Ave",
    "sg:city":"Leonardo",
    "sg:classifiers":[
        {
            "category":"Building & Trades",
            "subcategory":"Construction",
            "type":"Services"
        }
    ],
    "sg:phone":"+1 732 872 8730",
    "sg:postcode":"07737",
    "sg:province":"NJ",
    "sg:tags":[
        "pressure",
        "cleaning"
    ],
    "wof:name":"Precision Pressure Cleaning",
    "wof:placetype":"venue"
},
  "geometry": {"coordinates":[-74.067306,40.421203],"type":"Point"}
}