{
  "type": "Feature",
  "properties": {
    "iso:country":"US",
    "sg:address":"458 Main Rd",
    "sg:city":"Vineland",
    "sg:classifiers":[
        {
            "category":"Farming",
            "subcategory":"Farm & Veterinary Services",
            "type":"Manufacturing & Wholesale Goods"
        }
    ],
    "sg:phone":"+1 856 697 8127",
    "sg:postcode":"08360",
    "sg:province":"NJ",
    "sg:tags":[
        "breeder",
        "livestock"
    ],
    "wof:name":"Forever Precious Alpacas",
    "wof:placetype":"venue"
},
  "geometry": {"coordinates":[-74.989379,39.530021],"type":"Point"}
}