{
  "type": "Feature",
  "properties": {
    "iso:country":"US",
    "sg:address":"45 Commerce Way",
    "sg:city":"Totowa",
    "sg:classifiers":[
        {
            "category":"Professional",
            "subcategory":"Testing Lab",
            "type":"Services"
        }
    ],
    "sg:phone":"+1 973 256 0494",
    "sg:postcode":"07512",
    "sg:province":"NJ",
    "sg:tags":[
        "laboratory"
    ],
    "wof:name":"Geotesting Services Inc",
    "wof:placetype":"venue"
},
  "geometry": {"coordinates":[-74.237475,40.908609],"type":"Point"}
}