{
  "type": "Feature",
  "properties": {
    "iso:country":"US",
    "sg:address":"298 Townsend St",
    "sg:city":"New Brunswick",
    "sg:classifiers":[
        {
            "category":"Professional",
            "type":"Services"
        }
    ],
    "sg:phone":"+1   ",
    "sg:postcode":"08901",
    "sg:province":"NJ",
    "wof:name":"Ahmad Hamid",
    "wof:placetype":"venue"
},
  "geometry": {"coordinates":[-74.450579,40.491749],"type":"Point"}
}