{
  "type": "Feature",
  "properties": {
    "iso:country":"US",
    "sg:address":"27 Marlboro Ln",
    "sg:city":"Colonia",
    "sg:classifiers":[
        {
            "category":"Autos & Motor Vehicles",
            "subcategory":"Automobile Sales",
            "type":"Retail Goods"
        }
    ],
    "sg:phone":"+1 732 382 1686",
    "sg:postcode":"07067",
    "sg:province":"NJ",
    "sg:tags":[
        "limo"
    ],
    "wof:name":"Un Limousine Corp",
    "wof:placetype":"venue"
},
  "geometry": {"coordinates":[-74.32884799999999,40.591047],"type":"Point"}
}