{
  "type": "Feature",
  "properties": {
    "addr:full":"225 Lincoln Pl Garfield NJ 07026",
    "addr:housenumber":"225",
    "addr:postcode":"07026",
    "addr:street":"Lincoln Pl",
    "iso:country":"US",
    "sg:address":"225 Lincoln Pl",
    "sg:city":"Garfield",
    "sg:classifiers":[
        {
            "category":"Professional",
            "type":"Services"
        }
    ],
    "sg:phone":"+1 973 772 0790",
    "sg:postcode":"07026",
    "sg:province":"NJ",
    "sg:tags":[
        "establishment"
    ],
    "wof:name":"Horizon Group Of New England",
    "wof:placetype":"venue"
},
  "geometry": {"coordinates":[-74.10298400000001,40.87445],"type":"Point"}
}