{
  "type": "Feature",
  "properties": {
    "iso:country":"US",
    "sg:address":"71 S Newman St",
    "sg:city":"Hackensack",
    "sg:classifiers":[
        {
            "category":"Home & Garden",
            "subcategory":"Building Materials",
            "type":"Retail Goods"
        }
    ],
    "sg:phone":"+1 201 951 1457",
    "sg:postcode":"07601",
    "sg:province":"NJ",
    "sg:tags":[
        "supply"
    ],
    "sg:website":"www.eastcoastgranite.com",
    "wof:name":"East Coast Granite",
    "wof:placetype":"venue"
},
  "geometry": {"coordinates":[-74.053933,40.878556],"type":"Point"}
}