{
  "type": "Feature",
  "properties": {
    "iso:country":"US",
    "sg:address":"2035 Willowbrook Mall",
    "sg:city":"Wayne",
    "sg:classifiers":[
        {
            "category":"Shopping",
            "subcategory":"Clothing, Apparel, & Fashions",
            "type":"Retail Goods"
        }
    ],
    "sg:phone":"+1 973 837 9455",
    "sg:postcode":"07470",
    "sg:province":"NJ",
    "sg:tags":[
        "accessory",
        "clothing",
        "women's"
    ],
    "wof:name":"Mandee #95",
    "wof:placetype":"venue"
},
  "geometry": {"coordinates":[-74.260634,40.890613],"type":"Point"}
}