{
  "type": "Feature",
  "properties": {
    "addr:full":"140 Franklin Tpke Waldwick NJ 07463",
    "addr:housenumber":"140",
    "addr:postcode":"07463",
    "addr:street":"Franklin Tpke",
    "iso:country":"US",
    "sg:address":"140 Franklin Tpke",
    "sg:city":"Waldwick",
    "sg:classifiers":[
        {
            "category":"Personal",
            "subcategory":"Beauty Salon",
            "type":"Services"
        }
    ],
    "sg:phone":"+1 201 251 1234",
    "sg:postcode":"07463",
    "sg:province":"NJ",
    "sg:tags":[
        "shop"
    ],
    "wof:name":"Hairtique",
    "wof:placetype":"venue"
},
  "geometry": {"coordinates":[-74.122687,41.019377],"type":"Point"}
}