{
  "type": "Feature",
  "properties": {
    "iso:country":"US",
    "sg:address":"1291 Saint Georges Ave",
    "sg:city":"Colonia",
    "sg:classifiers":[
        {
            "category":"Professional",
            "type":"Services"
        }
    ],
    "sg:phone":"+1 732 750 2625",
    "sg:postcode":"07067",
    "sg:province":"NJ",
    "sg:tags":[
        "establishment"
    ],
    "wof:name":"Sun And",
    "wof:placetype":"venue"
},
  "geometry": {"coordinates":[-74.293802,40.58191],"type":"Point"}
}