{
  "type": "Feature",
  "properties": {
    "iso:country":"US",
    "sg:address":"217 Beechwood Rd",
    "sg:city":"Oradell",
    "sg:classifiers":[
        {
            "category":"Professional",
            "subcategory":"Engineering",
            "type":"Services"
        }
    ],
    "sg:phone":"+1 201 986 9141",
    "sg:postcode":"07649",
    "sg:province":"NJ",
    "sg:tags":[
        "general",
        "contractor"
    ],
    "wof:name":"Engineering Shapes",
    "wof:placetype":"venue"
},
  "geometry": {"coordinates":[-74.011589,40.953297],"type":"Point"}
}