{
  "type": "Feature",
  "properties": {
    "iso:country":"US",
    "sg:address":"460 Faraday Ave",
    "sg:city":"Jackson",
    "sg:classifiers":[
        {
            "category":"Building & Trades",
            "subcategory":"Construction",
            "type":"Services"
        }
    ],
    "sg:phone":"+1 732 886 0776",
    "sg:postcode":"08527",
    "sg:province":"NJ",
    "sg:tags":[
        "steel",
        "erectors",
        "structural"
    ],
    "wof:name":"On The Level Steel Erectors",
    "wof:placetype":"venue"
},
  "geometry": {"coordinates":[-74.25591,40.062414],"type":"Point"}
}