{
  "type": "Feature",
  "properties": {
    "iso:country":"US",
    "sg:address":"1074 N Black Horse Pike",
    "sg:city":"Williamstown",
    "sg:classifiers":[
        {
            "category":"Bus Charters",
            "type":"Transportation"
        }
    ],
    "sg:phone":"+1 856 740 1199",
    "sg:postcode":"08094",
    "sg:province":"NJ",
    "sg:tags":[
        "school",
        "b",
        "local"
    ],
    "wof:name":"Student Transportation America",
    "wof:placetype":"venue"
},
  "geometry": {"coordinates":[-75.00500099999999,39.701745],"type":"Point"}
}