{
  "type": "Feature",
  "properties": {
    "addr:full":"1104 US Hwy 130 Riverton NJ 08077",
    "addr:housenumber":"1104",
    "addr:postcode":"08077",
    "addr:street":"Us Hwy 130",
    "iso:country":"US",
    "sg:address":"1104 US Hwy 130",
    "sg:city":"Riverton",
    "sg:classifiers":[
        {
            "category":"Restaurant",
            "type":"Food & Drink"
        }
    ],
    "sg:phone":"+1   ",
    "sg:postcode":"08077",
    "sg:province":"NJ",
    "sg:tags":[
        "eating"
    ],
    "wof:name":"Hunan Garden Chinese Kitchen",
    "wof:placetype":"venue"
},
  "geometry": {"coordinates":[-74.989357,39.99838],"type":"Point"}
}