{
  "type": "Feature",
  "properties": {
    "addr:full":"24 Commerce Rd Fairfield NJ 07004",
    "addr:housenumber":"24",
    "addr:postcode":"07004",
    "addr:street":"Commerce Rd",
    "iso:country":"US",
    "sg:address":"24 Commerce Rd",
    "sg:city":"Fairfield",
    "sg:classifiers":[
        {
            "category":"Shopping",
            "subcategory":"Catalog Store",
            "type":"Retail Goods"
        }
    ],
    "sg:phone":"+1   ",
    "sg:postcode":"07004",
    "sg:province":"NJ",
    "sg:tags":[
        "mail",
        "house"
    ],
    "wof:name":"Direct Buyers Network Inc",
    "wof:placetype":"venue"
},
  "geometry": {"coordinates":[-74.316947,40.871946],"type":"Point"}
}