{
  "type": "Feature",
  "properties": {
    "addr:full":"310 White Horse Pike N Lawnside NJ 08045",
    "addr:housenumber":"310",
    "addr:postcode":"08045",
    "addr:street":"White Horse Pike N",
    "iso:country":"US",
    "sg:address":"310 White Horse Pike N",
    "sg:city":"Lawnside",
    "sg:classifiers":[
        {
            "category":"Retail",
            "subcategory":"Veterinary Services",
            "type":"Services"
        }
    ],
    "sg:phone":"+1 856 547 1800",
    "sg:postcode":"08045",
    "sg:province":"NJ",
    "sg:tags":[
        "clinic",
        "hospital",
        "veterinarian",
        "specialty"
    ],
    "sg:website":"http://www.banfield.net/ypoffer/?source=yp",
    "wof:name":"Banfield the Pet Hospital",
    "wof:placetype":"venue"
},
  "geometry": {"coordinates":[-75.04303400000001,39.870024],"type":"Point"}
}