{
  "type": "Feature",
  "properties": {
    "iso:country":"US",
    "sg:address":"44 Bryant Ave",
    "sg:city":"Jersey City",
    "sg:classifiers":[
        {
            "category":"Food & Beverages",
            "subcategory":"Groceries & Convenience Stores",
            "type":"Retail Goods"
        }
    ],
    "sg:phone":"+1 201 435 2522",
    "sg:postcode":"07306",
    "sg:province":"NJ",
    "sg:tags":[
        "deli"
    ],
    "wof:name":"Andy's Deli",
    "wof:placetype":"venue"
},
  "geometry": {"coordinates":[-74.074997,40.733398],"type":"Point"}
}