{
  "type": "Feature",
  "properties": {
    "addr:full":"303 RT-10 Ledgewood NJ 07852",
    "addr:housenumber":"303",
    "addr:postcode":"07852",
    "addr:street":"Rt-10",
    "iso:country":"US",
    "sg:address":"303 RT-10",
    "sg:city":"Ledgewood",
    "sg:classifiers":[
        {
            "category":"Restaurant",
            "type":"Food & Drink"
        }
    ],
    "sg:menulink":"http://www.allmenus.com/nj/roxbury/127907-red-lobster/menu/",
    "sg:phone":"+1 973 927 3713",
    "sg:postcode":"07852",
    "sg:province":"NJ",
    "sg:tags":[
        "seafood",
        "american"
    ],
    "wof:name":"Red Lobster",
    "wof:placetype":"venue"
},
  "geometry": {"coordinates":[-74.64859300000001,40.874393],"type":"Point"}
}