{
  "type": "Feature",
  "properties": {
    "iso:country":"US",
    "sg:address":"18 Shackletown Rd",
    "sg:city":"Bloomsbury",
    "sg:classifiers":[
        {
            "category":"Building & Trades",
            "subcategory":"Construction",
            "type":"Services"
        }
    ],
    "sg:phone":"+1 908 995 7919",
    "sg:postcode":"08804",
    "sg:province":"NJ",
    "sg:tags":[
        "excavation",
        "concrete",
        "contractor"
    ],
    "wof:name":"Magnum Paving & Contracting",
    "wof:placetype":"venue"
},
  "geometry": {"coordinates":[-75.116816,40.646381],"type":"Point"}
}