{
  "type": "Feature",
  "properties": {
    "iso:country":"US",
    "sg:address":"107 Haddon Ave",
    "sg:city":"Haddon Twp",
    "sg:classifiers":[
        {
            "category":"Professional",
            "subcategory":"Testing Lab",
            "type":"Services"
        }
    ],
    "sg:phone":"+1 856 858 4800",
    "sg:postcode":"08108",
    "sg:province":"NJ",
    "sg:tags":[
        "laboratory"
    ],
    "sg:website":"www.emsl.com",
    "wof:name":"EMSL Analytical Inc",
    "wof:placetype":"venue"
},
  "geometry": {"coordinates":[-75.084796,39.921576],"type":"Point"}
}