{
  "type": "Feature",
  "properties": {
    "addr:full":"91 Jackson St South River NJ 08882",
    "addr:housenumber":"91",
    "addr:postcode":"08882",
    "addr:street":"Jackson St",
    "iso:country":"US",
    "sg:address":"91 Jackson St",
    "sg:city":"South River",
    "sg:classifiers":[
        {
            "category":"Autos & Motor Vehicles",
            "subcategory":"Fuel & Gas Station",
            "type":"Retail Goods"
        }
    ],
    "sg:phone":"+1   ",
    "sg:postcode":"08882",
    "sg:province":"NJ",
    "sg:tags":[
        "station"
    ],
    "wof:name":"Mateckis Service Center Inc",
    "wof:placetype":"venue"
},
  "geometry": {"coordinates":[-74.381052,40.448205],"type":"Point"}
}