{
  "type": "Feature",
  "properties": {
    "iso:country":"US",
    "sg:address":"50 Port St",
    "sg:city":"Newark",
    "sg:classifiers":[
        {
            "category":"Parking",
            "type":"Transportation"
        }
    ],
    "sg:phone":"+1 973 465 9400",
    "sg:postcode":"07114",
    "sg:province":"NJ",
    "sg:tags":[
        "garage"
    ],
    "wof:name":"Vista Parking",
    "wof:placetype":"venue"
},
  "geometry": {"coordinates":[-74.155378,40.703116],"type":"Point"}
}