{
  "type": "Feature",
  "properties": {
    "addr:full":"352 Stanford St Perth Amboy NJ 08861",
    "addr:housenumber":"352",
    "addr:postcode":"08861",
    "addr:street":"Stanford St",
    "iso:country":"US",
    "sg:address":"352 Stanford St",
    "sg:city":"Perth Amboy",
    "sg:classifiers":[
        {
            "category":"Building & Trades",
            "subcategory":"Locksmith",
            "type":"Services"
        }
    ],
    "sg:phone":"+1 888 277 4556",
    "sg:postcode":"08861",
    "sg:province":"NJ",
    "sg:tags":[
        "key"
    ],
    "wof:name":"7 Day 24 Hour Emergency Locksmith",
    "wof:placetype":"venue"
},
  "geometry": {"coordinates":[-74.275402,40.513228],"type":"Point"}
}