{
  "type": "Feature",
  "properties": {
    "iso:country":"US",
    "sg:address":"2 Station Rd Ste A",
    "sg:city":"Lincoln Park",
    "sg:classifiers":[
        {
            "category":"Arena",
            "subcategory":"Sports Club",
            "type":"Entertainment"
        }
    ],
    "sg:phone":"+1 973 696 7369",
    "sg:postcode":"07035",
    "sg:province":"NJ",
    "sg:tags":[
        "martial art"
    ],
    "sg:website":"www.makotomartialarts.com",
    "wof:name":"Makoto Martial Arts",
    "wof:placetype":"venue"
},
  "geometry": {"coordinates":[-74.30287199999999,40.923605],"type":"Point"}
}