{
  "type": "Feature",
  "properties": {
    "iso:country":"US",
    "sg:address":"425 State Rte 50",
    "sg:city":"Woodbine",
    "sg:classifiers":[
        {
            "category":"Social Services",
            "subcategory":"Adult Care",
            "type":"Services"
        }
    ],
    "sg:phone":"+1 609 628 3300",
    "sg:postcode":"08270",
    "sg:province":"NJ",
    "sg:tags":[
        "residential"
    ],
    "wof:name":"Voca Corp of NJ",
    "wof:placetype":"venue"
},
  "geometry": {"coordinates":[-74.764338,39.31037],"type":"Point"}
}