{
  "type": "Feature",
  "properties": {
    "addr:full":"3091 State Rte 35 Lavallette NJ 08735",
    "addr:housenumber":"3091",
    "addr:postcode":"08735",
    "addr:street":"State Rte 35",
    "iso:country":"US",
    "sg:address":"3091 State Rte 35",
    "sg:city":"Lavallette",
    "sg:classifiers":[
        {
            "category":"Food & Beverages",
            "subcategory":"Bakery",
            "type":"Retail Goods"
        }
    ],
    "sg:phone":"+1 732 793 3960",
    "sg:postcode":"08735",
    "sg:province":"NJ",
    "sg:tags":[
        "baker"
    ],
    "wof:name":"Colonial Bakery Inc",
    "wof:placetype":"venue"
},
  "geometry": {"coordinates":[-74.066374,39.982547],"type":"Point"}
}