{
  "type": "Feature",
  "properties": {
    "iso:country":"US",
    "sg:address":"312 Rahway Ave",
    "sg:city":"Elizabeth",
    "sg:classifiers":[
        {
            "category":"Restaurant",
            "type":"Food & Drink"
        }
    ],
    "sg:phone":"+1 908 354 6586",
    "sg:postcode":"07202",
    "sg:province":"NJ",
    "wof:name":"Kam-Tim",
    "wof:placetype":"venue"
},
  "geometry": {"coordinates":[-74.22539999999999,40.658315],"type":"Point"}
}