{
  "type": "Feature",
  "properties": {
    "addr:full":"266 Bloomfield Ave Caldwell NJ 07006",
    "addr:housenumber":"266",
    "addr:postcode":"07006",
    "addr:street":"Bloomfield Ave",
    "iso:country":"US",
    "sg:address":"266 Bloomfield Ave",
    "sg:city":"Caldwell",
    "sg:classifiers":[
        {
            "category":"Professional",
            "subcategory":"Art Services",
            "type":"Services"
        }
    ],
    "sg:phone":"+1 973 226 2040",
    "sg:postcode":"07006",
    "sg:province":"NJ",
    "sg:tags":[
        "photographer"
    ],
    "wof:name":"Airphoto Services",
    "wof:placetype":"venue"
},
  "geometry": {"coordinates":[-74.274024,40.83817],"type":"Point"}
}