{
  "type": "Feature",
  "properties": {
    "addr:full":"17 Mount Run Tinton Falls NJ 07753",
    "addr:housenumber":"17",
    "addr:postcode":"07753",
    "addr:street":"Mount Run",
    "iso:country":"US",
    "sg:address":"17 Mount Run",
    "sg:city":"Tinton Falls",
    "sg:classifiers":[
        {
            "category":"Building & Trades",
            "subcategory":"Cleaning & Sanitation",
            "type":"Services"
        }
    ],
    "sg:phone":"+1 732 922 6480",
    "sg:postcode":"07753",
    "sg:province":"NJ",
    "sg:tags":[
        "window"
    ],
    "wof:name":"W O Window Cleaning Co",
    "wof:placetype":"venue"
},
  "geometry": {"coordinates":[-74.099214,40.24392],"type":"Point"}
}