{
  "type": "Feature",
  "properties": {
    "iso:country":"US",
    "sg:address":"407 Lacey Rd",
    "sg:city":"Forked River",
    "sg:classifiers":[
        {
            "category":"Shopping",
            "subcategory":"Bicycles & Sporting Goods",
            "type":"Retail Goods"
        }
    ],
    "sg:phone":"+1 609 971 6220",
    "sg:postcode":"08731",
    "sg:province":"NJ",
    "wof:name":"Bicycles Unlimited",
    "wof:placetype":"venue"
},
  "geometry": {"coordinates":[-74.197574,39.848731],"type":"Point"}
}