{
  "type": "Feature",
  "properties": {
    "addr:full":"2015 US Hwy 22 Scotch Plains NJ 07076",
    "addr:housenumber":"2015",
    "addr:postcode":"07076",
    "addr:street":"Us Hwy 22",
    "iso:country":"US",
    "sg:address":"2015 US Hwy 22",
    "sg:city":"Scotch Plains",
    "sg:classifiers":[
        {
            "category":"Retail",
            "subcategory":"Auto Rental",
            "type":"Services"
        }
    ],
    "sg:phone":"+1 908 322 4291",
    "sg:postcode":"07076",
    "sg:province":"NJ",
    "sg:tags":[
        "renting",
        "truck",
        "leasing"
    ],
    "wof:name":"U-Haul Co",
    "wof:placetype":"venue"
},
  "geometry": {"coordinates":[-74.39845099999999,40.658522],"type":"Point"}
}