{
  "type": "Feature",
  "properties": {
    "iso:country":"US",
    "sg:address":"53 Franklin Rd",
    "sg:city":"Teaneck",
    "sg:classifiers":[
        {
            "category":"Professional",
            "type":"Services"
        }
    ],
    "sg:phone":"+1   ",
    "sg:postcode":"07666",
    "sg:province":"NJ",
    "wof:name":"T Russell",
    "wof:placetype":"venue"
},
  "geometry": {"coordinates":[-73.99817,40.896804],"type":"Point"}
}