{
  "type": "Feature",
  "properties": {
    "addr:full":"201 Leonardville Rd Belford NJ 07718",
    "addr:housenumber":"201",
    "addr:postcode":"07718",
    "addr:street":"Leonardville Rd",
    "iso:country":"US",
    "sg:address":"201 Leonardville Rd",
    "sg:city":"Belford",
    "sg:classifiers":[
        {
            "category":"Utilities",
            "subcategory":"Electric",
            "type":"Services"
        }
    ],
    "sg:phone":"+1 732 531 3277",
    "sg:postcode":"07718",
    "sg:province":"NJ",
    "wof:name":"Jersey Central",
    "wof:placetype":"venue"
},
  "geometry": {"coordinates":[-74.087132,40.414581],"type":"Point"}
}