{
  "type": "Feature",
  "properties": {
    "iso:country":"US",
    "sg:address":"184 5th Ave",
    "sg:city":"Neptune",
    "sg:classifiers":[
        {
            "category":"Building & Trades",
            "subcategory":"Construction",
            "type":"Services"
        }
    ],
    "sg:phone":"+1 732 988 4772",
    "sg:postcode":"07753",
    "sg:province":"NJ",
    "sg:tags":[
        "excavating",
        "contractor"
    ],
    "wof:name":"Emmons Tennet Excavating",
    "wof:placetype":"venue"
},
  "geometry": {"coordinates":[-74.036417,40.205047],"type":"Point"}
}