{
  "type": "Feature",
  "properties": {
    "iso:country":"US",
    "sg:address":"1520 Holly Blvd",
    "sg:city":"Manasquan",
    "sg:classifiers":[
        {
            "category":"Real Estate",
            "subcategory":"Real Estate Operator",
            "type":"Services"
        }
    ],
    "sg:phone":"+1   ",
    "sg:postcode":"08736",
    "sg:province":"NJ",
    "sg:tags":[
        "building",
        "nonresidential"
    ],
    "wof:name":"Cedar View Homes Inc",
    "wof:placetype":"venue"
},
  "geometry": {"coordinates":[-74.081934,40.124472],"type":"Point"}
}