{
  "type": "Feature",
  "properties": {
    "addr:full":"178 County Rd Cresskill NJ 07626",
    "addr:housenumber":"178",
    "addr:postcode":"07626",
    "addr:street":"County Rd",
    "iso:country":"US",
    "sg:address":"178 County Rd",
    "sg:city":"Cresskill",
    "sg:classifiers":[
        {
            "category":"Restaurant",
            "type":"Food & Drink"
        }
    ],
    "sg:phone":"+1   ",
    "sg:postcode":"07626",
    "sg:province":"NJ",
    "sg:tags":[
        "eating"
    ],
    "wof:name":"TW International",
    "wof:placetype":"venue"
},
  "geometry": {"coordinates":[-73.957353,40.940737],"type":"Point"}
}