{
  "type": "Feature",
  "properties": {
    "addr:full":"30 S Doughty Ave Somerville NJ 08876",
    "addr:housenumber":"30",
    "addr:postcode":"08876",
    "addr:street":"S Doughty Ave",
    "iso:country":"US",
    "sg:address":"30 S Doughty Ave",
    "sg:city":"Somerville",
    "sg:classifiers":[
        {
            "category":"Professional",
            "subcategory":"Computer Services",
            "type":"Services"
        }
    ],
    "sg:phone":"+1 908 252 4490",
    "sg:postcode":"08876",
    "sg:province":"NJ",
    "sg:tags":[
        "prepackaged",
        "software"
    ],
    "wof:name":"Michaelson Inc",
    "wof:placetype":"venue"
},
  "geometry": {"coordinates":[-74.618115,40.569642],"type":"Point"}
}