{
  "type": "Feature",
  "properties": {
    "addr:full":"34 Mattawang Dr Somerset NJ 08873",
    "addr:housenumber":"34",
    "addr:postcode":"08873",
    "addr:street":"Mattawang Dr",
    "iso:country":"US",
    "sg:address":"34 Mattawang Dr",
    "sg:city":"Somerset",
    "sg:classifiers":[
        {
            "category":"Health Services",
            "subcategory":"Doctor",
            "type":"Services"
        }
    ],
    "sg:phone":"+1   ",
    "sg:postcode":"08873",
    "sg:province":"NJ",
    "sg:tags":[
        "medical"
    ],
    "wof:name":"Lilibeth Rubio MD",
    "wof:placetype":"venue"
},
  "geometry": {"coordinates":[-74.549927,40.445714],"type":"Point"}
}