{
  "type": "Feature",
  "properties": {
    "iso:country":"US",
    "sg:address":"1368 State Rte 38",
    "sg:city":"Hainesport",
    "sg:classifiers":[
        {
            "category":"Building & Trades",
            "subcategory":"Construction",
            "type":"Services"
        }
    ],
    "sg:phone":"+1 609 265 1000",
    "sg:postcode":"08036",
    "sg:province":"NJ",
    "sg:tags":[
        "residential",
        "remodeling",
        "commercial"
    ],
    "wof:name":"Powell Building Corporation",
    "wof:placetype":"venue"
},
  "geometry": {"coordinates":[-74.82233600000001,39.979748],"type":"Point"}
}