{
  "type": "Feature",
  "properties": {
    "iso:country":"US",
    "sg:address":"1126 Englishtown Rd",
    "sg:city":"Old Bridge",
    "sg:classifiers":[
        {
            "category":"Restaurant",
            "type":"Food & Drink"
        }
    ],
    "sg:menulink":"http://www.allmenus.com/nj/old-bridge/32883-market-boy/menu/",
    "sg:phone":"+1 732 723 0888",
    "sg:postcode":"08857",
    "sg:province":"NJ",
    "sg:tags":[
        "asian",
        "chinese"
    ],
    "wof:name":"Market Boy",
    "wof:placetype":"venue"
},
  "geometry": {"coordinates":[-74.360697,40.4024],"type":"Point"}
}