{
  "type": "Feature",
  "properties": {
    "addr:full":"220 N 15th St Bloomfield NJ 07003",
    "addr:housenumber":"220",
    "addr:postcode":"07003",
    "addr:street":"N 15Th St",
    "iso:country":"US",
    "sg:address":"220 N 15th St",
    "sg:city":"Bloomfield",
    "sg:classifiers":[
        {
            "category":"Building & Trades",
            "subcategory":"Plumbing",
            "type":"Services"
        }
    ],
    "sg:phone":"+1 973 680 0465",
    "sg:postcode":"07003",
    "sg:province":"NJ",
    "sg:tags":[
        "contractor"
    ],
    "wof:name":"Tarantola Plumbing",
    "wof:placetype":"venue"
},
  "geometry": {"coordinates":[-74.188143,40.772257],"type":"Point"}
}