{
  "type": "Feature",
  "properties": {
    "addr:full":"642 Summit Ave Westfield NJ 07090",
    "addr:housenumber":"642",
    "addr:postcode":"07090",
    "addr:street":"Summit Ave",
    "iso:country":"US",
    "sg:address":"642 Summit Ave",
    "sg:city":"Westfield",
    "sg:classifiers":[
        {
            "category":"Professional",
            "subcategory":"Management & Consulting",
            "type":"Services"
        }
    ],
    "sg:phone":"+1   ",
    "sg:postcode":"07090",
    "sg:province":"NJ",
    "sg:tags":[
        "public",
        "relations"
    ],
    "wof:name":"Ronald A Margulis",
    "wof:placetype":"venue"
},
  "geometry": {"coordinates":[-74.342823,40.644098],"type":"Point"}
}