{
  "type": "Feature",
  "properties": {
    "addr:full":"7816 Kennedy Blvd North Bergen NJ 07047",
    "addr:housenumber":"7816",
    "addr:postcode":"07047",
    "addr:street":"Kennedy Blvd",
    "iso:country":"US",
    "sg:address":"7816 Kennedy Blvd",
    "sg:city":"North Bergen",
    "sg:classifiers":[
        {
            "category":"Health Services",
            "subcategory":"Dentist",
            "type":"Services"
        }
    ],
    "sg:phone":"+1 201 869 5156",
    "sg:postcode":"07047",
    "sg:province":"NJ",
    "wof:name":"Ultimate Dental of North Bergen PA",
    "wof:placetype":"venue"
},
  "geometry": {"coordinates":[-74.01149700000001,40.803501],"type":"Point"}
}