{
  "type": "Feature",
  "properties": {
    "iso:country":"US",
    "sg:address":"230 Cristiani St",
    "sg:city":"Cranford",
    "sg:classifiers":[
        {
            "category":"Shopping",
            "subcategory":"Stationery & Office Supplies",
            "type":"Retail Goods"
        }
    ],
    "sg:phone":"+1   ",
    "sg:postcode":"07016",
    "sg:province":"NJ",
    "wof:name":"Rand Paper Company",
    "wof:placetype":"venue"
},
  "geometry": {"coordinates":[-74.284297,40.65405],"type":"Point"}
}