{
  "type": "Feature",
  "properties": {
    "addr:full":"4 Millbrook Ln Colts Neck NJ 07722",
    "addr:housenumber":"4",
    "addr:postcode":"07722",
    "addr:street":"Millbrook Ln",
    "iso:country":"US",
    "sg:address":"4 Millbrook Ln",
    "sg:city":"Colts Neck",
    "sg:classifiers":[
        {
            "category":"Building & Trades",
            "subcategory":"Construction",
            "type":"Services"
        }
    ],
    "sg:phone":"+1 732 780 2199",
    "sg:postcode":"07722",
    "sg:province":"NJ",
    "sg:tags":[
        "house",
        "contractor"
    ],
    "wof:name":"Michael Pezzuto Inc",
    "wof:placetype":"venue"
},
  "geometry": {"coordinates":[-74.187213,40.287027],"type":"Point"}
}