{
  "type": "Feature",
  "properties": {
    "addr:full":"188 Essex St Millburn NJ 07041",
    "addr:housenumber":"188",
    "addr:postcode":"07041",
    "addr:street":"Essex St",
    "iso:country":"US",
    "sg:address":"188 Essex St",
    "sg:city":"Millburn",
    "sg:classifiers":[
        {
            "category":"Shopping",
            "subcategory":"Gifts & Souvenirs",
            "type":"Retail Goods"
        }
    ],
    "sg:phone":"+1   ",
    "sg:postcode":"07041",
    "sg:province":"NJ",
    "sg:tags":[
        "shop",
        "antique",
        "linen"
    ],
    "wof:name":"Molly Too",
    "wof:placetype":"venue"
},
  "geometry": {"coordinates":[-74.306924,40.724855],"type":"Point"}
}