{
  "type": "Feature",
  "properties": {
    "iso:country":"US",
    "sg:address":"377 Palisade Ave",
    "sg:city":"Jersey City",
    "sg:classifiers":[
        {
            "category":"Social Services",
            "subcategory":"Child Care",
            "type":"Services"
        }
    ],
    "sg:phone":"+1 201 876 0303",
    "sg:postcode":"07307",
    "sg:province":"NJ",
    "sg:tags":[
        "day"
    ],
    "wof:name":"Happy Face 3 Inc",
    "wof:placetype":"venue"
},
  "geometry": {"coordinates":[-74.045445,40.742262],"type":"Point"}
}