{
  "type": "Feature",
  "properties": {
    "iso:country":"US",
    "sg:address":"115 River Rd",
    "sg:city":"Edgewater",
    "sg:classifiers":[
        {
            "category":"Professional",
            "subcategory":"Advertising",
            "type":"Services"
        }
    ],
    "sg:phone":"+1 201 941 4894",
    "sg:postcode":"07020",
    "sg:province":"NJ",
    "sg:website":"www.amsvoice.com",
    "wof:name":"AMSVOICE.COM",
    "wof:placetype":"venue"
},
  "geometry": {"coordinates":[-73.991339,40.806422],"type":"Point"}
}