{
  "type": "Feature",
  "properties": {
    "addr:full":"224 Ridgedale Ave Cedar Knolls NJ 07927",
    "addr:housenumber":"224",
    "addr:postcode":"07927",
    "addr:street":"Ridgedale Ave",
    "iso:country":"US",
    "sg:address":"224 Ridgedale Ave",
    "sg:city":"Cedar Knolls",
    "sg:classifiers":[
        {
            "category":"Banks & Credit Unions",
            "subcategory":"Bank",
            "type":"Services"
        }
    ],
    "sg:phone":"+1 973 285 1632",
    "sg:postcode":"07927",
    "sg:province":"NJ",
    "wof:name":"Commerce Bank",
    "wof:placetype":"venue"
},
  "geometry": {"coordinates":[-74.460302,40.809002],"type":"Point"}
}