{
  "type": "Feature",
  "properties": {
    "iso:country":"US",
    "sg:address":"54 Schooleys Mountain Rd",
    "sg:city":"Long Valley",
    "sg:classifiers":[
        {
            "category":"Real Estate",
            "subcategory":"Surveying",
            "type":"Services"
        }
    ],
    "sg:phone":"+1 908 876 3210",
    "sg:postcode":"07853",
    "sg:province":"NJ",
    "sg:tags":[
        "surveyor"
    ],
    "wof:name":"Harley L Wilson Surveyor",
    "wof:placetype":"venue"
},
  "geometry": {"coordinates":[-74.783393,40.788939],"type":"Point"}
}