{
  "type": "Feature",
  "properties": {
    "iso:country":"US",
    "sg:address":"1008 W Kings Hwy",
    "sg:city":"Mount Ephraim",
    "sg:classifiers":[
        {
            "category":"Shopping",
            "subcategory":"Computers & Home Electronics",
            "type":"Retail Goods"
        }
    ],
    "sg:phone":"+1   ",
    "sg:postcode":"08059",
    "sg:province":"NJ",
    "wof:name":"Tri State Computer",
    "wof:placetype":"venue"
},
  "geometry": {"coordinates":[-75.09772100000001,39.879557],"type":"Point"}
}