{
  "type": "Feature",
  "properties": {
    "addr:full":"1628 Prospect St Trenton NJ 08638",
    "addr:housenumber":"1628",
    "addr:postcode":"08638",
    "addr:street":"Prospect St",
    "iso:country":"US",
    "sg:address":"1628 Prospect St",
    "sg:city":"Trenton",
    "sg:classifiers":[
        {
            "category":"Organizations",
            "subcategory":"Religious Organization",
            "type":"Services"
        }
    ],
    "sg:phone":"+1 609 882 7614",
    "sg:postcode":"08638",
    "sg:province":"NJ",
    "sg:tags":[
        "church"
    ],
    "sg:website":"www.stlukesewing.org",
    "wof:name":"St Luke's Episcopal Church",
    "wof:placetype":"venue"
},
  "geometry": {"coordinates":[-74.76366,40.250184],"type":"Point"}
}