{
  "type": "Feature",
  "properties": {
    "iso:country":"US",
    "sg:address":"50 Kulick Rd",
    "sg:city":"Fairfield",
    "sg:classifiers":[
        {
            "category":"Manufacturing",
            "subcategory":"Paper Products",
            "type":"Manufacturing & Wholesale Goods"
        }
    ],
    "sg:phone":"+1 973 882 9688",
    "sg:postcode":"07004",
    "sg:province":"NJ",
    "sg:tags":[
        "label"
    ],
    "sg:website":"www.e-ilsi.com",
    "wof:name":"Industrial Labeling Systems",
    "wof:placetype":"venue"
},
  "geometry": {"coordinates":[-74.29239099999999,40.870948],"type":"Point"}
}