{
  "type": "Feature",
  "properties": {
    "iso:country":"US",
    "sg:address":"728 Princeton Ave",
    "sg:city":"Brick",
    "sg:classifiers":[
        {
            "category":"Recreation",
            "type":"Entertainment"
        }
    ],
    "sg:phone":"+1 732 892 7558",
    "sg:postcode":"08724",
    "sg:province":"NJ",
    "sg:tags":[
        "charter",
        "boat"
    ],
    "wof:name":"Starcks Landing",
    "wof:placetype":"venue"
},
  "geometry": {"coordinates":[-74.070312,40.058806],"type":"Point"}
}