{
  "type": "Feature",
  "properties": {
    "addr:full":"487 Broadway Westwood NJ 07675",
    "addr:housenumber":"487",
    "addr:postcode":"07675",
    "addr:street":"Broadway",
    "iso:country":"US",
    "sg:address":"487 Broadway",
    "sg:city":"Westwood",
    "sg:phone":"+1 201 722 3511",
    "sg:postcode":"07675",
    "sg:province":"NJ",
    "wof:name":"It's Greek To Me",
    "wof:placetype":"venue"
},
  "geometry": {"coordinates":[-74.033531,40.992304],"type":"Point"}
}