{
  "type": "Feature",
  "properties": {
    "iso:country":"US",
    "sg:address":"338 Locust Ave",
    "sg:city":"Garwood",
    "sg:classifiers":[
        {
            "category":"Real Estate",
            "subcategory":"Real Estate Agent",
            "type":"Services"
        }
    ],
    "sg:phone":"+1 908 789 0408",
    "sg:postcode":"07027",
    "sg:province":"NJ",
    "wof:name":"J M Koenig",
    "wof:placetype":"venue"
},
  "geometry": {"coordinates":[-74.323392,40.64865],"type":"Point"}
}