{
  "type": "Feature",
  "properties": {
    "iso:country":"US",
    "sg:address":"340 E Northfield Rd",
    "sg:city":"Livingston",
    "sg:classifiers":[
        {
            "category":"Professional",
            "type":"Services"
        }
    ],
    "sg:phone":"+1 973 992 9191",
    "sg:postcode":"07039",
    "sg:province":"NJ",
    "sg:tags":[
        "establishment"
    ],
    "wof:name":"Aliman Corp",
    "wof:placetype":"venue"
},
  "geometry": {"coordinates":[-74.29969699999999,40.770227],"type":"Point"}
}