{
  "type": "Feature",
  "properties": {
    "iso:country":"US",
    "sg:address":"1571 Blackwood Clementon Rd",
    "sg:city":"Blackwood",
    "sg:classifiers":[
        {
            "category":"Restaurant",
            "type":"Food & Drink"
        }
    ],
    "sg:phone":"+1   ",
    "sg:postcode":"08012",
    "sg:province":"NJ",
    "sg:tags":[
        "eating"
    ],
    "wof:name":"J DS Homedale Grille",
    "wof:placetype":"venue"
},
  "geometry": {"coordinates":[-75.05098700000001,39.8029],"type":"Point"}
}