{
  "type": "Feature",
  "properties": {
    "addr:full":"358 Highland Ave Passaic NJ 07055",
    "addr:housenumber":"358",
    "addr:postcode":"07055",
    "addr:street":"Highland Ave",
    "iso:country":"US",
    "sg:address":"358 Highland Ave",
    "sg:city":"Passaic",
    "sg:classifiers":[
        {
            "category":"Professional",
            "subcategory":"Computer Services",
            "type":"Services"
        }
    ],
    "sg:phone":"+1 973 928 1166",
    "sg:postcode":"07055",
    "sg:province":"NJ",
    "sg:tags":[
        "stereo",
        "installation"
    ],
    "wof:name":"Extreme Audio Sound",
    "wof:placetype":"venue"
},
  "geometry": {"coordinates":[-74.135595,40.870476],"type":"Point"}
}