{
  "type": "Feature",
  "properties": {
    "addr:full":"1155 E Jersey St Elizabeth NJ 07201",
    "addr:housenumber":"1155",
    "addr:postcode":"07201",
    "addr:street":"E Jersey St",
    "iso:country":"US",
    "sg:address":"1155 E Jersey St",
    "sg:city":"Elizabeth",
    "sg:classifiers":[
        {
            "category":"Health Services",
            "subcategory":"Nursing And Care Facility",
            "type":"Services"
        }
    ],
    "sg:phone":"+1 908 352 9200",
    "sg:postcode":"07201",
    "sg:province":"NJ",
    "sg:tags":[
        "skilled"
    ],
    "wof:name":"Carteret Senior Living",
    "wof:placetype":"venue"
},
  "geometry": {"coordinates":[-74.214206,40.665216],"type":"Point"}
}