{
  "type": "Feature",
  "properties": {
    "iso:country":"US",
    "sg:address":"744 W Side Ave",
    "sg:city":"Jersey City",
    "sg:classifiers":[
        {
            "category":"Insurance",
            "subcategory":"Insurance Agent",
            "type":"Services"
        }
    ],
    "sg:phone":"+1 201 332 1200",
    "sg:postcode":"07306",
    "sg:province":"NJ",
    "wof:name":"Jersey One Insurance Agency",
    "wof:placetype":"venue"
},
  "geometry": {"coordinates":[-74.076623,40.726505],"type":"Point"}
}