{
  "type": "Feature",
  "properties": {
    "addr:full":"81 McWhorter St Newark NJ 07105",
    "addr:housenumber":"81",
    "addr:postcode":"07105",
    "addr:street":"Mcwhorter St",
    "iso:country":"US",
    "sg:address":"81 McWhorter St",
    "sg:city":"Newark",
    "sg:classifiers":[
        {
            "category":"Building & Trades",
            "subcategory":"Locksmith",
            "type":"Services"
        }
    ],
    "sg:phone":"+1 973 854 5180",
    "sg:postcode":"07105",
    "sg:province":"NJ",
    "sg:tags":[
        "key"
    ],
    "wof:name":"0 7 7 Day Emergency A 24 Hour Locksmith",
    "wof:placetype":"venue"
},
  "geometry": {"coordinates":[-74.16614300000001,40.730346],"type":"Point"}
}