{
  "type": "Feature",
  "properties": {
    "addr:full":"21 Saddle River Rd South Hackensack NJ 07606",
    "addr:housenumber":"21",
    "addr:postcode":"07606",
    "addr:street":"Saddle River Rd",
    "iso:country":"US",
    "sg:address":"21 Saddle River Rd",
    "sg:city":"South Hackensack",
    "sg:classifiers":[
        {
            "category":"Education",
            "subcategory":"Special Training",
            "type":"Public Place"
        }
    ],
    "sg:phone":"+1 973 471 4800",
    "sg:postcode":"07606",
    "sg:province":"NJ",
    "sg:tags":[
        "school",
        "specialty"
    ],
    "wof:name":"Bergen County Career Advancement Training Inc",
    "wof:placetype":"venue"
},
  "geometry": {"coordinates":[-74.099417,40.86389],"type":"Point"}
}