{
  "type": "Feature",
  "properties": {
    "iso:country":"US",
    "sg:address":"61 Grand Ave",
    "sg:city":"Palisades Park",
    "sg:classifiers":[
        {
            "category":"Personal",
            "subcategory":"Nail Salon",
            "type":"Services"
        }
    ],
    "sg:phone":"+1 201 313 8700",
    "sg:postcode":"07650",
    "sg:province":"NJ",
    "wof:name":"Nana USA Nail Corp",
    "wof:placetype":"venue"
},
  "geometry": {"coordinates":[-74.004504,40.845801],"type":"Point"}
}