{
  "type": "Feature",
  "properties": {
    "addr:full":"400 Valatia Ave Millville NJ 08332",
    "addr:housenumber":"400",
    "addr:postcode":"08332",
    "addr:street":"Valatia Ave",
    "iso:country":"US",
    "sg:address":"400 Valatia Ave",
    "sg:city":"Millville",
    "sg:classifiers":[
        {
            "category":"Professional",
            "subcategory":"Business Services",
            "type":"Services"
        }
    ],
    "sg:phone":"+1   ",
    "sg:postcode":"08332",
    "sg:province":"NJ",
    "wof:name":"Easmunt Enterprises",
    "wof:placetype":"venue"
},
  "geometry": {"coordinates":[-75.02672099999999,39.384678],"type":"Point"}
}