{
  "type": "Feature",
  "properties": {
    "iso:country":"US",
    "sg:address":"5401 Boardwalk",
    "sg:city":"Ventnor City",
    "sg:classifiers":[
        {
            "category":"Building & Trades",
            "subcategory":"Construction",
            "type":"Services"
        }
    ],
    "sg:phone":"+1 609 487 7750",
    "sg:postcode":"08406",
    "sg:province":"NJ",
    "sg:tags":[
        "contractor"
    ],
    "wof:name":"Irons Custom Homes Inc",
    "wof:placetype":"venue"
},
  "geometry": {"coordinates":[-74.471772,39.33979],"type":"Point"}
}