{
  "type": "Feature",
  "properties": {
    "addr:full":"84 Mandon Dr Wayne NJ 07470",
    "addr:housenumber":"84",
    "addr:postcode":"07470",
    "addr:street":"Mandon Dr",
    "iso:country":"US",
    "sg:address":"84 Mandon Dr",
    "sg:city":"Wayne",
    "sg:classifiers":[
        {
            "category":"Real Estate",
            "subcategory":"Real Estate Operator",
            "type":"Services"
        }
    ],
    "sg:phone":"+1   ",
    "sg:postcode":"07470",
    "sg:province":"NJ",
    "sg:tags":[
        "building",
        "nonresidential"
    ],
    "wof:name":"Stolat Properties Liabilit",
    "wof:placetype":"venue"
},
  "geometry": {"coordinates":[-74.24078299999999,40.940421],"type":"Point"}
}