{
  "type": "Feature",
  "properties": {
    "addr:full":"304 Brookmere Ct Ridgewood NJ 07450",
    "addr:housenumber":"304",
    "addr:postcode":"07450",
    "addr:street":"Brookmere Ct",
    "iso:country":"US",
    "sg:address":"304 Brookmere Ct",
    "sg:city":"Ridgewood",
    "sg:classifiers":[
        {
            "category":"Professional",
            "type":"Services"
        }
    ],
    "sg:phone":"+1   ",
    "sg:postcode":"07450",
    "sg:province":"NJ",
    "wof:name":"Resurgens Foundation Inc",
    "wof:placetype":"venue"
},
  "geometry": {"coordinates":[-74.114135,40.987686],"type":"Point"}
}