{
  "type": "Feature",
  "properties": {
    "addr:full":"400 Dennisville-Petersburg Rd Woodbine NJ 08270",
    "addr:housenumber":"400",
    "addr:postcode":"08270",
    "addr:street":"Dennisville-Petersburg Rd",
    "iso:country":"US",
    "sg:address":"400 Dennisville-Petersburg Rd",
    "sg:city":"Woodbine",
    "sg:classifiers":[
        {
            "category":"Organizations",
            "subcategory":"Religious Organization",
            "type":"Services"
        }
    ],
    "sg:phone":"+1 609 628 2224",
    "sg:postcode":"08270",
    "sg:province":"NJ",
    "sg:tags":[
        "church"
    ],
    "wof:name":"Petersburg Wesley Untd Mthdst",
    "wof:placetype":"venue"
},
  "geometry": {"coordinates":[-74.727532,39.253034],"type":"Point"}
}