{
  "type": "Feature",
  "properties": {
    "iso:country":"US",
    "sg:address":"114 Prince St",
    "sg:city":"Newark",
    "sg:classifiers":[
        {
            "category":"Organizations",
            "subcategory":"Religious Organization",
            "type":"Services"
        }
    ],
    "sg:phone":"+1   ",
    "sg:postcode":"07103",
    "sg:province":"NJ",
    "wof:name":"Trumpet Ministries",
    "wof:placetype":"venue"
},
  "geometry": {"coordinates":[-74.187175,40.73169],"type":"Point"}
}