{
  "type": "Feature",
  "properties": {
    "iso:country":"US",
    "sg:address":"65 S Main St",
    "sg:city":"Lodi",
    "sg:classifiers":[
        {
            "category":"Retail",
            "subcategory":"Auto Repair",
            "type":"Services"
        }
    ],
    "sg:phone":"+1 973 779 1411",
    "sg:postcode":"07644",
    "sg:province":"NJ",
    "sg:tags":[
        "body",
        "automobile",
        "painting"
    ],
    "wof:name":"Danco Motors Inc",
    "wof:placetype":"venue"
},
  "geometry": {"coordinates":[-74.088109,40.870755],"type":"Point"}
}