{
  "type": "Feature",
  "properties": {
    "addr:full":"151 Fries Mill Rd Blackwood NJ 08012",
    "addr:housenumber":"151",
    "addr:postcode":"08012",
    "addr:street":"Fries Mill Rd",
    "iso:country":"US",
    "sg:address":"151 Fries Mill Rd",
    "sg:city":"Blackwood",
    "sg:classifiers":[
        {
            "category":"Personal",
            "subcategory":"Beauty Salon",
            "type":"Services"
        }
    ],
    "sg:phone":"+1 856 228 5333",
    "sg:postcode":"08012",
    "sg:province":"NJ",
    "sg:tags":[
        "shop"
    ],
    "wof:name":"Body Basics",
    "wof:placetype":"venue"
},
  "geometry": {"coordinates":[-75.04713599999999,39.739619],"type":"Point"}
}