{
  "type": "Feature",
  "properties": {
    "addr:full":"43 Tamarack Cir Skillman NJ 08558",
    "addr:housenumber":"43",
    "addr:postcode":"08558",
    "addr:street":"Tamarack Cir",
    "iso:country":"US",
    "sg:address":"43 Tamarack Cir",
    "sg:city":"Skillman",
    "sg:classifiers":[
        {
            "category":"Health Services",
            "subcategory":"Health Practitioner",
            "type":"Services"
        }
    ],
    "sg:phone":"+1 609 279 2171",
    "sg:postcode":"08558",
    "sg:province":"NJ",
    "sg:tags":[
        "psychologist"
    ],
    "wof:name":"Adolescent & Children's Ctr",
    "wof:placetype":"venue"
},
  "geometry": {"coordinates":[-74.647907,40.407096],"type":"Point"}
}