{
  "type": "Feature",
  "properties": {
    "addr:full":"455 Co Rd 520 Marlboro NJ 07746",
    "addr:housenumber":"455",
    "addr:postcode":"07746",
    "addr:street":"Co Rd 520",
    "iso:country":"US",
    "sg:address":"455 Co Rd 520",
    "sg:city":"Marlboro",
    "sg:classifiers":[
        {
            "category":"Shopping",
            "subcategory":"Discount & Variety Stores",
            "type":"Retail Goods"
        }
    ],
    "sg:phone":"+1 732 536 6800",
    "sg:postcode":"07746",
    "sg:province":"NJ",
    "wof:name":"Dollar Eddies",
    "wof:placetype":"venue"
},
  "geometry": {"coordinates":[-74.247253,40.333229],"type":"Point"}
}