{
  "type": "Feature",
  "properties": {
    "iso:country":"US",
    "sg:address":"505 Middle Rd",
    "sg:city":"Hammonton",
    "sg:classifiers":[
        {
            "category":"Building & Trades",
            "subcategory":"Construction",
            "type":"Services"
        }
    ],
    "sg:phone":"+1 609 704 9374",
    "sg:postcode":"08037",
    "sg:province":"NJ",
    "sg:tags":[
        "contractor"
    ],
    "wof:name":"Peretti Contractors",
    "wof:placetype":"venue"
},
  "geometry": {"coordinates":[-74.773369,39.660446],"type":"Point"}
}