{
  "type": "Feature",
  "properties": {
    "addr:full":"407 Broad St Bloomfield NJ 07003",
    "addr:housenumber":"407",
    "addr:postcode":"07003",
    "addr:street":"Broad St",
    "iso:country":"US",
    "sg:address":"407 Broad St",
    "sg:city":"Bloomfield",
    "sg:classifiers":[
        {
            "category":"Restaurant",
            "type":"Food & Drink"
        }
    ],
    "sg:phone":"+1 973 748 9410",
    "sg:postcode":"07003",
    "sg:province":"NJ",
    "sg:tags":[
        "caterer"
    ],
    "wof:name":"Royal Meat Market Catering",
    "wof:placetype":"venue"
},
  "geometry": {"coordinates":[-74.192365,40.808938],"type":"Point"}
}