{
  "type": "Feature",
  "properties": {
    "addr:full":"19 Trapper Rd Sewell NJ 08080",
    "addr:housenumber":"19",
    "addr:postcode":"08080",
    "addr:street":"Trapper Rd",
    "iso:country":"US",
    "sg:address":"19 Trapper Rd",
    "sg:city":"Sewell",
    "sg:classifiers":[
        {
            "category":"Health Services",
            "subcategory":"Health Practitioner",
            "type":"Services"
        }
    ],
    "sg:phone":"+1   ",
    "sg:postcode":"08080",
    "sg:province":"NJ",
    "wof:name":"Yoko Spa",
    "wof:placetype":"venue"
},
  "geometry": {"coordinates":[-75.09276199999999,39.768604],"type":"Point"}
}