{
  "type": "Feature",
  "properties": {
    "addr:full":"59 Sherwood Rd Dumont NJ 07628",
    "addr:housenumber":"59",
    "addr:postcode":"07628",
    "addr:street":"Sherwood Rd",
    "iso:country":"US",
    "sg:address":"59 Sherwood Rd",
    "sg:city":"Dumont",
    "sg:classifiers":[
        {
            "category":"Building & Trades",
            "subcategory":"Construction",
            "type":"Services"
        }
    ],
    "sg:phone":"+1 201 384 6948",
    "sg:postcode":"07628",
    "sg:province":"NJ",
    "sg:tags":[
        "home",
        "builder"
    ],
    "wof:name":"Bethesda Lutheran Homes & Svc",
    "wof:placetype":"venue"
},
  "geometry": {"coordinates":[-73.999905,40.946717],"type":"Point"}
}