{
  "type": "Feature",
  "properties": {
    "addr:full":"2007 Valley Ave Scotch Plains NJ 07076",
    "addr:housenumber":"2007",
    "addr:postcode":"07076",
    "addr:street":"Valley Ave",
    "iso:country":"US",
    "sg:address":"2007 Valley Ave",
    "sg:city":"Scotch Plains",
    "sg:classifiers":[
        {
            "category":"Building & Trades",
            "subcategory":"Landscaping Services",
            "type":"Services"
        }
    ],
    "sg:phone":"+1 908 322 0075",
    "sg:postcode":"07076",
    "sg:province":"NJ",
    "sg:tags":[
        "landscape",
        "contractor"
    ],
    "wof:name":"New Creations Landscaping",
    "wof:placetype":"venue"
},
  "geometry": {"coordinates":[-74.40006700000001,40.655644],"type":"Point"}
}