{
  "type": "Feature",
  "properties": {
    "addr:full":"201 Main St Allenhurst NJ 07711",
    "addr:housenumber":"201",
    "addr:postcode":"07711",
    "addr:street":"Main St",
    "iso:country":"US",
    "sg:address":"201 Main St",
    "sg:city":"Allenhurst",
    "sg:classifiers":[
        {
            "category":"Real Estate",
            "subcategory":"Real Estate Agent",
            "type":"Services"
        }
    ],
    "sg:phone":"+1 732 531 4200",
    "sg:postcode":"07711",
    "sg:province":"NJ",
    "wof:name":"Bielat Santore & Co",
    "wof:placetype":"venue"
},
  "geometry": {"coordinates":[-74.00617699999999,40.236975],"type":"Point"}
}