{
  "type": "Feature",
  "properties": {
    "iso:country":"US",
    "sg:address":"632 Maurice River Pkwy",
    "sg:city":"Vineland",
    "sg:classifiers":[
        {
            "category":"Communications",
            "subcategory":"Radio Station",
            "type":"Services"
        }
    ],
    "sg:phone":"+1 856 696 7111",
    "sg:postcode":"08360",
    "sg:province":"NJ",
    "sg:tags":[
        "company",
        "broadcasting"
    ],
    "wof:name":"Clear Communications Inc",
    "wof:placetype":"venue"
},
  "geometry": {"coordinates":[-75.073489,39.496105],"type":"Point"}
}