{
  "type": "Feature",
  "properties": {
    "iso:country":"US",
    "sg:address":"183 Broad St",
    "sg:city":"Red Bank",
    "sg:classifiers":[
        {
            "category":"Wholesale",
            "subcategory":"Machinery & Supplies",
            "type":"Manufacturing & Wholesale Goods"
        }
    ],
    "sg:phone":"+1 732 530 9780",
    "sg:postcode":"07701",
    "sg:province":"NJ",
    "sg:tags":[
        "pump"
    ],
    "wof:name":"D Bank Area",
    "wof:placetype":"venue"
},
  "geometry": {"coordinates":[-74.064837,40.346722],"type":"Point"}
}