{
  "type": "Feature",
  "properties": {
    "addr:full":"2603 Barton Ct Cinnaminson NJ 08077",
    "addr:housenumber":"2603",
    "addr:postcode":"08077",
    "addr:street":"Barton Ct",
    "iso:country":"US",
    "sg:address":"2603 Barton Ct",
    "sg:city":"Cinnaminson",
    "sg:classifiers":[
        {
            "category":"Building & Trades",
            "subcategory":"Plumbing",
            "type":"Services"
        }
    ],
    "sg:phone":"+1 856 786 1245",
    "sg:postcode":"08077",
    "sg:province":"NJ",
    "sg:tags":[
        "plumbing",
        "contractor"
    ],
    "wof:name":"Wood Plumbing",
    "wof:placetype":"venue"
},
  "geometry": {"coordinates":[-74.979837,39.986866],"type":"Point"}
}