{
  "type": "Feature",
  "properties": {
    "addr:full":"55 Ellison Rd Somerset NJ 08873",
    "addr:housenumber":"55",
    "addr:postcode":"08873",
    "addr:street":"Ellison Rd",
    "iso:country":"US",
    "sg:address":"55 Ellison Rd",
    "sg:city":"Somerset",
    "sg:classifiers":[
        {
            "category":"Building & Trades",
            "subcategory":"Landscaping Services",
            "type":"Services"
        }
    ],
    "sg:phone":"+1 732 873 2248",
    "sg:postcode":"08873",
    "sg:province":"NJ",
    "sg:tags":[
        "landscape",
        "contractor"
    ],
    "wof:name":"TJS Lawn & Landscaping",
    "wof:placetype":"venue"
},
  "geometry": {"coordinates":[-74.50877800000001,40.505228],"type":"Point"}
}