{
  "type": "Feature",
  "properties": {
    "addr:full":"63 Catalpa Ave Perth Amboy NJ 08861",
    "addr:housenumber":"63",
    "addr:postcode":"08861",
    "addr:street":"Catalpa Ave",
    "iso:country":"US",
    "sg:address":"63 Catalpa Ave",
    "sg:city":"Perth Amboy",
    "sg:classifiers":[
        {
            "category":"Museum",
            "type":"Entertainment"
        }
    ],
    "sg:phone":"+1 732 826 1826",
    "sg:postcode":"08861",
    "sg:province":"NJ",
    "wof:name":"Kearny Cottage Museum",
    "wof:placetype":"venue"
},
  "geometry": {"coordinates":[-74.27220199999999,40.500099],"type":"Point"}
}