{
  "type": "Feature",
  "properties": {
    "iso:country":"US",
    "sg:address":"20 Lewis St",
    "sg:city":"Paterson",
    "sg:classifiers":[
        {
            "category":"Building & Trades",
            "subcategory":"Cleaning & Sanitation",
            "type":"Services"
        }
    ],
    "sg:phone":"+1 973 523 3529",
    "sg:postcode":"07501",
    "sg:province":"NJ",
    "sg:tags":[
        "maintenance"
    ],
    "wof:name":"Professional Building Mntnc",
    "wof:placetype":"venue"
},
  "geometry": {"coordinates":[-74.158569,40.91093],"type":"Point"}
}