{
  "type": "Feature",
  "properties": {
    "iso:country":"US",
    "sg:address":"2023 State Rte 88",
    "sg:city":"Brick",
    "sg:classifiers":[
        {
            "category":"Health Services",
            "subcategory":"Chiropractor",
            "type":"Services"
        }
    ],
    "sg:phone":"+1 732 458 5885",
    "sg:postcode":"08724",
    "sg:province":"NJ",
    "wof:name":"Center For Wellness",
    "wof:placetype":"venue"
},
  "geometry": {"coordinates":[-74.112938,40.073988],"type":"Point"}
}