{
  "type": "Feature",
  "properties": {
    "iso:country":"US",
    "sg:address":"212 Powder Mill Rd",
    "sg:city":"Morris Plains",
    "sg:classifiers":[
        {
            "category":"Wholesale",
            "subcategory":"Electrical",
            "type":"Manufacturing & Wholesale Goods"
        }
    ],
    "sg:phone":"+1 973 539 2009",
    "sg:postcode":"07950",
    "sg:province":"NJ",
    "sg:tags":[
        "electronic",
        "computer",
        "component"
    ],
    "wof:name":"Advanced Circuits Exchange",
    "wof:placetype":"venue"
},
  "geometry": {"coordinates":[-74.47684700000001,40.866495],"type":"Point"}
}