{
  "type": "Feature",
  "properties": {
    "addr:full":"151 Cedar Lake Rd Blairstown NJ 07825",
    "addr:housenumber":"151",
    "addr:postcode":"07825",
    "addr:street":"Cedar Lake Rd",
    "iso:country":"US",
    "sg:address":"151 Cedar Lake Rd",
    "sg:city":"Blairstown",
    "sg:classifiers":[
        {
            "category":"Professional",
            "subcategory":"Computer Services",
            "type":"Services"
        }
    ],
    "sg:phone":"+1 908 362 5238",
    "sg:postcode":"07825",
    "sg:province":"NJ",
    "sg:tags":[
        "consultant",
        "designer"
    ],
    "wof:name":"Third Wave Builders",
    "wof:placetype":"venue"
},
  "geometry": {"coordinates":[-75.00303099999999,40.961414],"type":"Point"}
}