{
  "type": "Feature",
  "properties": {
    "iso:country":"US",
    "sg:address":"1914 Birchwood Park Dr N",
    "sg:city":"Cherry Hill",
    "sg:classifiers":[
        {
            "category":"Health Services",
            "subcategory":"Doctor",
            "type":"Services"
        }
    ],
    "sg:phone":"+1 609 505 3031",
    "sg:postcode":"08003",
    "sg:province":"NJ",
    "sg:tags":[
        "physician",
        "surgeon"
    ],
    "wof:name":"Cancare",
    "wof:placetype":"venue"
},
  "geometry": {"coordinates":[-74.963576,39.912605],"type":"Point"}
}