{
  "type": "Feature",
  "properties": {
    "addr:full":"479 Conklintown Rd Ringwood NJ 07456",
    "addr:housenumber":"479",
    "addr:postcode":"07456",
    "addr:street":"Conklintown Rd",
    "iso:country":"US",
    "sg:address":"479 Conklintown Rd",
    "sg:city":"Ringwood",
    "sg:classifiers":[
        {
            "category":"Professional",
            "subcategory":"Detective & Security Services",
            "type":"Services"
        }
    ],
    "sg:phone":"+1 973 839 0601",
    "sg:postcode":"07456",
    "sg:province":"NJ",
    "sg:tags":[
        "information",
        "bureau"
    ],
    "wof:name":"Gk Confidential Services",
    "wof:placetype":"venue"
},
  "geometry": {"coordinates":[-74.25635,41.072867],"type":"Point"}
}