{
  "type": "Feature",
  "properties": {
    "addr:full":"23 Glenside Dr Annandale NJ 08801",
    "addr:housenumber":"23",
    "addr:postcode":"08801",
    "addr:street":"Glenside Dr",
    "iso:country":"US",
    "sg:address":"23 Glenside Dr",
    "sg:city":"Annandale",
    "sg:classifiers":[
        {
            "category":"Professional",
            "subcategory":"Computer Services",
            "type":"Services"
        }
    ],
    "sg:phone":"+1 908 730 8336",
    "sg:postcode":"08801",
    "sg:province":"NJ",
    "sg:tags":[
        "web",
        "design",
        "hosting",
        "site"
    ],
    "wof:name":"Uberfish Corp",
    "wof:placetype":"venue"
},
  "geometry": {"coordinates":[-74.899703,40.610236],"type":"Point"}
}