{
  "type": "Feature",
  "properties": {
    "addr:full":"264 Coles St Jersey City NJ 07310",
    "addr:housenumber":"264",
    "addr:postcode":"07310",
    "addr:street":"Coles St",
    "iso:country":"US",
    "sg:address":"264 Coles St",
    "sg:city":"Jersey City",
    "sg:classifiers":[
        {
            "category":"Autos & Motor Vehicles",
            "subcategory":"Automobile Sales",
            "type":"Retail Goods"
        },
        {
            "category":"Taxi",
            "type":"Transportation"
        },
        {
            "category":"Airline",
            "type":"Transportation"
        }
    ],
    "sg:phone":"+1 201 795 1131",
    "sg:postcode":"07310",
    "sg:province":"NJ",
    "sg:tags":[
        "shuttle",
        "airport",
        "limo"
    ],
    "wof:name":"Buscanero Taxi",
    "wof:placetype":"venue"
},
  "geometry": {"coordinates":[-74.046204,40.7328],"type":"Point"}
}