{
  "type": "Feature",
  "properties": {
    "iso:country":"US",
    "sg:address":"1231 Burnet Ave",
    "sg:city":"Union",
    "sg:classifiers":[
        {
            "category":"Education",
            "subcategory":"School",
            "type":"Public Place"
        }
    ],
    "sg:phone":"+1 908 810 1501",
    "sg:postcode":"07083",
    "sg:province":"NJ",
    "sg:website":"www.mujc.org",
    "wof:name":"Developmental Learning Center",
    "wof:placetype":"venue"
},
  "geometry": {"coordinates":[-74.284389,40.708281],"type":"Point"}
}