{
  "type": "Feature",
  "properties": {
    "iso:country":"US",
    "sg:address":"144 Pulaski Ave",
    "sg:city":"Sayreville",
    "sg:classifiers":[
        {
            "category":"Professional",
            "subcategory":"Business Services",
            "type":"Services"
        }
    ],
    "sg:phone":"+1 732 238 5573",
    "sg:postcode":"08872",
    "sg:province":"NJ",
    "wof:name":"K B R D Inc",
    "wof:placetype":"venue"
},
  "geometry": {"coordinates":[-74.347917,40.466717],"type":"Point"}
}