{
  "type": "Feature",
  "properties": {
    "addr:full":"280 Godwin Ave Midland Park NJ 07432",
    "addr:housenumber":"280",
    "addr:postcode":"07432",
    "addr:street":"Godwin Ave",
    "iso:country":"US",
    "sg:address":"280 Godwin Ave",
    "sg:city":"Midland Park",
    "sg:classifiers":[
        {
            "category":"Personal",
            "type":"Services"
        }
    ],
    "sg:phone":"+1   ",
    "sg:postcode":"07432",
    "sg:province":"NJ",
    "sg:tags":[
        "registrar",
        "deputy"
    ],
    "wof:name":"Midland Park Deputy Registrar",
    "wof:placetype":"venue"
},
  "geometry": {"coordinates":[-74.14117299999999,40.990132],"type":"Point"}
}