{
  "type": "Feature",
  "properties": {
    "addr:full":"120 W 12th St Bayonne NJ 07002",
    "addr:housenumber":"120",
    "addr:postcode":"07002",
    "addr:street":"W 12Th St",
    "iso:country":"US",
    "sg:address":"120 W 12th St",
    "sg:city":"Bayonne",
    "sg:classifiers":[
        {
            "category":"Building & Trades",
            "subcategory":"Construction",
            "type":"Services"
        }
    ],
    "sg:phone":"+1 201 437 6026",
    "sg:postcode":"07002",
    "sg:province":"NJ",
    "sg:tags":[
        "house"
    ],
    "wof:name":"McCarry Construction Inc",
    "wof:placetype":"venue"
},
  "geometry": {"coordinates":[-74.13055,40.659174],"type":"Point"}
}