{
  "type": "Feature",
  "properties": {
    "iso:country":"US",
    "sg:address":"497 W Scott Ave",
    "sg:city":"Rahway",
    "sg:classifiers":[
        {
            "category":"Deli",
            "type":"Food & Drink"
        },
        {
            "category":"Food & Beverages",
            "subcategory":"Bakery",
            "type":"Retail Goods"
        }
    ],
    "sg:phone":"+1 732 340 0184",
    "sg:postcode":"07065",
    "sg:province":"NJ",
    "sg:tags":[
        "sandwich"
    ],
    "wof:name":"Scott Ave Grocery and Deli",
    "wof:placetype":"venue"
},
  "geometry": {"coordinates":[-74.27593899999999,40.617995],"type":"Point"}
}