{
  "type": "Feature",
  "properties": {
    "addr:full":"188 Howard Ave Passaic NJ 07055",
    "addr:housenumber":"188",
    "addr:postcode":"07055",
    "addr:street":"Howard Ave",
    "iso:country":"US",
    "sg:address":"188 Howard Ave",
    "sg:city":"Passaic",
    "sg:classifiers":[
        {
            "category":"Professional",
            "subcategory":"Art Services",
            "type":"Services"
        }
    ],
    "sg:phone":"+1   ",
    "sg:postcode":"07055",
    "sg:province":"NJ",
    "sg:tags":[
        "commercial",
        "design"
    ],
    "wof:name":"Jared Bernstein Photography",
    "wof:placetype":"venue"
},
  "geometry": {"coordinates":[-74.13091900000001,40.84474],"type":"Point"}
}