{
  "type": "Feature",
  "properties": {
    "addr:full":"210 Lake Dr E Cherry Hill NJ 08002",
    "addr:housenumber":"210",
    "addr:postcode":"08002",
    "addr:street":"Lake Dr E",
    "iso:country":"US",
    "sg:address":"210 Lake Dr E",
    "sg:city":"Cherry Hill",
    "sg:classifiers":[
        {
            "category":"Insurance",
            "subcategory":"Insurance Agent",
            "type":"Services"
        }
    ],
    "sg:phone":"+1 856 482 9900",
    "sg:postcode":"08002",
    "sg:province":"NJ",
    "sg:website":"www.mcintyre-group.com",
    "wof:name":"Mc Intyre Group",
    "wof:placetype":"venue"
},
  "geometry": {"coordinates":[-75.003146,39.938636],"type":"Point"}
}