{
  "type": "Feature",
  "properties": {
    "iso:country":"US",
    "sg:address":"55 Hook Rd",
    "sg:city":"Bayonne",
    "sg:classifiers":[
        {
            "category":"Freight",
            "type":"Transportation"
        }
    ],
    "sg:phone":"+1 201 437 4347",
    "sg:postcode":"07002",
    "sg:province":"NJ",
    "sg:tags":[
        "local",
        "storage",
        "trucking"
    ],
    "wof:name":"McGovern Trucking & Whse Co",
    "wof:placetype":"venue"
},
  "geometry": {"coordinates":[-74.102194,40.664862],"type":"Point"}
}