{
  "type": "Feature",
  "properties": {
    "addr:full":"5 Hinsdale Ln Willingboro NJ 08046",
    "addr:housenumber":"5",
    "addr:postcode":"08046",
    "addr:street":"Hinsdale Ln",
    "iso:country":"US",
    "sg:address":"5 Hinsdale Ln",
    "sg:city":"Willingboro",
    "sg:classifiers":[
        {
            "category":"Personal",
            "type":"Services"
        }
    ],
    "sg:phone":"+1   ",
    "sg:postcode":"08046",
    "sg:province":"NJ",
    "wof:name":"Stribling E Officiatng Serv",
    "wof:placetype":"venue"
},
  "geometry": {"coordinates":[-74.872472,40.042448],"type":"Point"}
}