{
  "type": "Feature",
  "properties": {
    "addr:full":"62 Dover St Paterson NJ 07501",
    "addr:housenumber":"62",
    "addr:postcode":"07501",
    "addr:street":"Dover St",
    "iso:country":"US",
    "sg:address":"62 Dover St",
    "sg:city":"Paterson",
    "sg:classifiers":[
        {
            "category":"Bars & Pubs",
            "subcategory":"Nightclub",
            "type":"Food & Drink"
        }
    ],
    "sg:phone":"+1 973 742 1435",
    "sg:postcode":"07501",
    "sg:province":"NJ",
    "sg:tags":[
        "nightlife"
    ],
    "wof:name":"Laura's Night Club",
    "wof:placetype":"venue"
},
  "geometry": {"coordinates":[-74.159108,40.909642],"type":"Point"}
}