{
  "type": "Feature",
  "properties": {
    "iso:country":"US",
    "sg:address":"1207 Springfield Ave",
    "sg:city":"Irvington",
    "sg:classifiers":[
        {
            "category":"Insurance",
            "subcategory":"Insurance Agent",
            "type":"Services"
        }
    ],
    "sg:phone":"+1   ",
    "sg:postcode":"07111",
    "sg:province":"NJ",
    "wof:name":"C B S Insurance Agency Inc",
    "wof:placetype":"venue"
},
  "geometry": {"coordinates":[-74.238426,40.725004],"type":"Point"}
}