{
  "type": "Feature",
  "properties": {
    "addr:full":"6 Branchwood Dr Lakewood NJ 08701",
    "addr:housenumber":"6",
    "addr:postcode":"08701",
    "addr:street":"Branchwood Dr",
    "iso:country":"US",
    "sg:address":"6 Branchwood Dr",
    "sg:city":"Lakewood",
    "sg:classifiers":[
        {
            "category":"Professional",
            "subcategory":"Management & Consulting",
            "type":"Services"
        }
    ],
    "sg:phone":"+1   ",
    "sg:postcode":"08701",
    "sg:province":"NJ",
    "wof:name":"Cuva Inc",
    "wof:placetype":"venue"
},
  "geometry": {"coordinates":[-74.210919,40.075527],"type":"Point"}
}