{
  "type": "Feature",
  "properties": {
    "addr:full":"111 E Ridgewood Ave Ridgewood NJ 07450",
    "addr:housenumber":"111",
    "addr:postcode":"07450",
    "addr:street":"E Ridgewood Ave",
    "iso:country":"US",
    "sg:address":"111 E Ridgewood Ave",
    "sg:city":"Ridgewood",
    "sg:classifiers":[
        {
            "category":"Banks & Credit Unions",
            "subcategory":"Investment Brokerage",
            "type":"Services"
        }
    ],
    "sg:phone":"+1   ",
    "sg:postcode":"07450",
    "sg:province":"NJ",
    "sg:tags":[
        "security"
    ],
    "wof:name":"H & R Block Financial Advisors",
    "wof:placetype":"venue"
},
  "geometry": {"coordinates":[-74.117468,40.979537],"type":"Point"}
}