{
  "type": "Feature",
  "properties": {
    "addr:full":"99 Hornerstown Arneytown Rd Allentown NJ 08501",
    "addr:housenumber":"99",
    "addr:postcode":"08501",
    "addr:street":"Hornerstown Arneytown Rd",
    "iso:country":"US",
    "sg:address":"99 Hornerstown Arneytown Rd",
    "sg:city":"Allentown",
    "sg:classifiers":[
        {
            "category":"Farming",
            "subcategory":"Farm",
            "type":"Manufacturing & Wholesale Goods"
        }
    ],
    "sg:phone":"+1 609 758 1745",
    "sg:postcode":"08501",
    "sg:province":"NJ",
    "wof:name":"Blaso Family Farms",
    "wof:placetype":"venue"
},
  "geometry": {"coordinates":[-74.549824,40.102304],"type":"Point"}
}