{
  "type": "Feature",
  "properties": {
    "addr:full":"625 Green Ln Union NJ 07083",
    "addr:housenumber":"625",
    "addr:postcode":"07083",
    "addr:street":"Green Ln",
    "iso:country":"US",
    "sg:address":"625 Green Ln",
    "sg:city":"Union",
    "sg:classifiers":[
        {
            "category":"Wholesale",
            "subcategory":"Fruits & Vegetables",
            "type":"Manufacturing & Wholesale Goods"
        }
    ],
    "sg:phone":"+1 908 527 6611",
    "sg:postcode":"07083",
    "sg:province":"NJ",
    "sg:tags":[
        "importer",
        "produce"
    ],
    "wof:name":"Apple A Day Fruits Inc",
    "wof:placetype":"venue"
},
  "geometry": {"coordinates":[-74.245464,40.677538],"type":"Point"}
}