{
  "type": "Feature",
  "properties": {
    "iso:country":"US",
    "sg:address":"27 Little John Dr",
    "sg:city":"Medford",
    "sg:classifiers":[
        {
            "category":"Manufacturing",
            "subcategory":"Retail Goods",
            "type":"Manufacturing & Wholesale Goods"
        }
    ],
    "sg:phone":"+1 609 953 7820",
    "sg:postcode":"08055",
    "sg:province":"NJ",
    "sg:tags":[
        "product",
        "mfg"
    ],
    "wof:name":"Medical Alloy Industries",
    "wof:placetype":"venue"
},
  "geometry": {"coordinates":[-74.827268,39.865865],"type":"Point"}
}