{
  "type": "Feature",
  "properties": {
    "iso:country":"US",
    "sg:address":"2811 Fairmount Ave",
    "sg:city":"Atlantic City",
    "sg:classifiers":[
        {
            "category":"Real Estate",
            "subcategory":"Real Estate Agent",
            "type":"Services"
        }
    ],
    "sg:phone":"+1 609 347 8003",
    "sg:postcode":"08401",
    "sg:province":"NJ",
    "wof:name":"Anjus Corp",
    "wof:placetype":"venue"
},
  "geometry": {"coordinates":[-74.448832,39.357423],"type":"Point"}
}