{
  "type": "Feature",
  "properties": {
    "iso:country":"US",
    "sg:address":"2797 Brunswick Ave",
    "sg:city":"Trenton",
    "sg:classifiers":[
        {
            "category":"Restaurant",
            "type":"Food & Drink"
        }
    ],
    "sg:phone":"+1   ",
    "sg:postcode":"08648",
    "sg:province":"NJ",
    "sg:tags":[
        "eating"
    ],
    "wof:name":"Cafe Domenico Pizza & Rest",
    "wof:placetype":"venue"
},
  "geometry": {"coordinates":[-74.717236,40.266023],"type":"Point"}
}