{
  "type": "Feature",
  "properties": {
    "iso:country":"US",
    "sg:address":"601 Ocean Ave",
    "sg:city":"Spring Lake",
    "sg:classifiers":[
        {
            "category":"Building & Trades",
            "subcategory":"Construction",
            "type":"Services"
        }
    ],
    "sg:phone":"+1 732 449 6005",
    "sg:postcode":"07762",
    "sg:province":"NJ",
    "sg:tags":[
        "house",
        "carpentry",
        "t",
        "contractor"
    ],
    "wof:name":"Gemcon Inc",
    "wof:placetype":"venue"
},
  "geometry": {"coordinates":[-74.024479,40.145287],"type":"Point"}
}