{
  "type": "Feature",
  "properties": {
    "addr:full":"658 Floyd St Englewood Cliffs NJ 07632",
    "addr:housenumber":"658",
    "addr:postcode":"07632",
    "addr:street":"Floyd St",
    "iso:country":"US",
    "sg:address":"658 Floyd St",
    "sg:city":"Englewood Cliffs",
    "sg:classifiers":[
        {
            "category":"Real Estate",
            "subcategory":"Real Estate Agent",
            "type":"Services"
        }
    ],
    "sg:phone":"+1   ",
    "sg:postcode":"07632",
    "sg:province":"NJ",
    "wof:name":"210 Walker Street LLC",
    "wof:placetype":"venue"
},
  "geometry": {"coordinates":[-73.947699,40.890514],"type":"Point"}
}