{
  "type": "Feature",
  "properties": {
    "addr:full":"603 Belmont Dr Hackettstown NJ 07840",
    "addr:housenumber":"603",
    "addr:postcode":"07840",
    "addr:street":"Belmont Dr",
    "iso:country":"US",
    "sg:address":"603 Belmont Dr",
    "sg:city":"Hackettstown",
    "sg:classifiers":[
        {
            "category":"Food & Beverages",
            "subcategory":"Specialty",
            "type":"Retail Goods"
        }
    ],
    "sg:phone":"+1   ",
    "sg:postcode":"07840",
    "sg:province":"NJ",
    "wof:name":"Sunrise Herbs",
    "wof:placetype":"venue"
},
  "geometry": {"coordinates":[-74.822964,40.8682],"type":"Point"}
}