{
  "type": "Feature",
  "properties": {
    "iso:country":"US",
    "sg:address":"4808 Bergenline Ave",
    "sg:city":"Union City",
    "sg:classifiers":[
        {
            "category":"Health Services",
            "subcategory":"Doctor",
            "type":"Services"
        }
    ],
    "sg:phone":"+1 201 863 3344",
    "sg:postcode":"07087",
    "sg:province":"NJ",
    "sg:tags":[
        "dentist"
    ],
    "wof:name":"Jack Levi & Assoc",
    "wof:placetype":"venue"
},
  "geometry": {"coordinates":[-74.021947,40.781479],"type":"Point"}
}