{
  "type": "Feature",
  "properties": {
    "iso:country":"US",
    "sg:address":"217 Malone Ave",
    "sg:city":"Belleville",
    "sg:classifiers":[
        {
            "category":"Wholesale",
            "subcategory":"Groceries",
            "type":"Manufacturing & Wholesale Goods"
        }
    ],
    "sg:phone":"+1 973 751 0100",
    "sg:postcode":"07109",
    "sg:province":"NJ",
    "sg:tags":[
        "food",
        "product",
        "health"
    ],
    "sg:website":"www.helptherep.com",
    "wof:name":"HELPTHEREP.COM",
    "wof:placetype":"venue"
},
  "geometry": {"coordinates":[-74.159145,40.798922],"type":"Point"}
}