{
  "type": "Feature",
  "properties": {
    "iso:country":"US",
    "sg:address":"1865 Long Ter",
    "sg:city":"Union",
    "sg:classifiers":[
        {
            "category":"Building & Trades",
            "subcategory":"Plumbing",
            "type":"Services"
        }
    ],
    "sg:phone":"+1 908 964 6429",
    "sg:postcode":"07083",
    "sg:province":"NJ",
    "sg:tags":[
        "contractor"
    ],
    "wof:name":"Carmona Plumbing & Heating",
    "wof:placetype":"venue"
},
  "geometry": {"coordinates":[-74.25905899999999,40.702627],"type":"Point"}
}