{
  "type": "Feature",
  "properties": {
    "addr:full":"6 Devine Dr Mahwah NJ 07430",
    "addr:housenumber":"6",
    "addr:postcode":"07430",
    "addr:street":"Devine Dr",
    "iso:country":"US",
    "sg:address":"6 Devine Dr",
    "sg:city":"Mahwah",
    "sg:classifiers":[
        {
            "category":"Freight",
            "type":"Transportation"
        }
    ],
    "sg:phone":"+1 201 529 1442",
    "sg:postcode":"07430",
    "sg:province":"NJ",
    "wof:name":"Bl Morey & Sons Transport",
    "wof:placetype":"venue"
},
  "geometry": {"coordinates":[-74.149963,41.097684],"type":"Point"}
}