{
  "type": "Feature",
  "properties": {
    "addr:full":"2 Vista Pl Red Bank NJ 07701",
    "addr:housenumber":"2",
    "addr:postcode":"07701",
    "addr:street":"Vista Pl",
    "iso:country":"US",
    "sg:address":"2 Vista Pl",
    "sg:city":"Red Bank",
    "sg:classifiers":[
        {
            "category":"Professional",
            "subcategory":"Business Services",
            "type":"Services"
        }
    ],
    "sg:phone":"+1   ",
    "sg:postcode":"07701",
    "sg:province":"NJ",
    "wof:name":"Navista Enterprises LLC",
    "wof:placetype":"venue"
},
  "geometry": {"coordinates":[-74.05683500000001,40.356066],"type":"Point"}
}