{
  "type": "Feature",
  "properties": {
    "iso:country":"US",
    "sg:address":"161 Princeton Hightstown Rd",
    "sg:city":"Princeton Junction",
    "sg:classifiers":[
        {
            "category":"Social Services",
            "type":"Services"
        }
    ],
    "sg:phone":"+1 609 799 3035",
    "sg:postcode":"08550",
    "sg:province":"NJ",
    "wof:name":"Princeton Road Center",
    "wof:placetype":"venue"
},
  "geometry": {"coordinates":[-74.60805999999999,40.301929],"type":"Point"}
}