{
  "type": "Feature",
  "properties": {
    "iso:country":"US",
    "sg:address":"5914 Main St",
    "sg:city":"Mays Landing",
    "sg:classifiers":[
        {
            "category":"Health Services",
            "subcategory":"Clinic",
            "type":"Services"
        }
    ],
    "sg:phone":"+1 609 625 4004",
    "sg:postcode":"08330",
    "sg:province":"NJ",
    "wof:name":"Group 6 Healthcare Consltng",
    "wof:placetype":"venue"
},
  "geometry": {"coordinates":[-74.72699900000001,39.451832],"type":"Point"}
}