{
  "type": "Feature",
  "properties": {
    "addr:full":"721 Mountain Ave Springfield NJ 07081",
    "addr:housenumber":"721",
    "addr:postcode":"07081",
    "addr:street":"Mountain Ave",
    "iso:country":"US",
    "sg:address":"721 Mountain Ave",
    "sg:city":"Springfield",
    "sg:classifiers":[
        {
            "category":"Building & Trades",
            "subcategory":"Locksmith",
            "type":"Services"
        }
    ],
    "sg:phone":"+1 973 689 0497",
    "sg:postcode":"07081",
    "sg:province":"NJ",
    "sg:tags":[
        "key"
    ],
    "wof:name":"24 All Day Emergency Locksmith",
    "wof:placetype":"venue"
},
  "geometry": {"coordinates":[-74.33148199999999,40.690373],"type":"Point"}
}