{
  "type": "Feature",
  "properties": {
    "iso:country":"US",
    "sg:address":"213 South St",
    "sg:city":"Morristown",
    "sg:classifiers":[
        {
            "category":"Shopping",
            "subcategory":"Pharmacy",
            "type":"Retail Goods"
        }
    ],
    "sg:phone":"+1   ",
    "sg:postcode":"07960",
    "sg:province":"NJ",
    "wof:name":"Community Pharmacy",
    "wof:placetype":"venue"
},
  "geometry": {"coordinates":[-74.4722,40.788776],"type":"Point"}
}