{
  "type": "Feature",
  "properties": {
    "addr:full":"111 Dorsa Ave Livingston NJ 07039",
    "addr:housenumber":"111",
    "addr:postcode":"07039",
    "addr:street":"Dorsa Ave",
    "iso:country":"US",
    "sg:address":"111 Dorsa Ave",
    "sg:city":"Livingston",
    "sg:classifiers":[
        {
            "category":"Manufacturing",
            "subcategory":"Signs",
            "type":"Manufacturing & Wholesale Goods"
        }
    ],
    "sg:phone":"+1 973 535 9277",
    "sg:postcode":"07039",
    "sg:province":"NJ",
    "sg:tags":[
        "manufacture",
        "metal",
        "made",
        "neon",
        "plastic"
    ],
    "sg:website":"www.signalsign.com",
    "wof:name":"Signal Sign Co",
    "wof:placetype":"venue"
},
  "geometry": {"coordinates":[-74.340687,40.80866],"type":"Point"}
}