{
  "type": "Feature",
  "properties": {
    "addr:full":"393 Crescent Ave Wyckoff NJ 07481",
    "addr:housenumber":"393",
    "addr:postcode":"07481",
    "addr:street":"Crescent Ave",
    "iso:country":"US",
    "sg:address":"393 Crescent Ave",
    "sg:city":"Wyckoff",
    "sg:classifiers":[
        {
            "category":"Personal",
            "type":"Services"
        }
    ],
    "sg:phone":"+1 201 891 0470",
    "sg:postcode":"07481",
    "sg:province":"NJ",
    "sg:tags":[
        "control",
        "weight"
    ],
    "wof:name":"Diet Center",
    "wof:placetype":"venue"
},
  "geometry": {"coordinates":[-74.166417,41.0205],"type":"Point"}
}