{
  "type": "Feature",
  "properties": {
    "iso:country":"US",
    "sg:address":"200 US Hwy 9",
    "sg:city":"Englishtown",
    "sg:classifiers":[
        {
            "category":"Shopping",
            "subcategory":"Computers & Home Electronics",
            "type":"Retail Goods"
        }
    ],
    "sg:phone":"+1 732 577 6000",
    "sg:postcode":"07726",
    "sg:province":"NJ",
    "sg:tags":[
        "equipment",
        "dealer"
    ],
    "wof:name":"Compaq Computer Corp",
    "wof:placetype":"venue"
},
  "geometry": {"coordinates":[-74.303736,40.304153],"type":"Point"}
}