{
  "type": "Feature",
  "properties": {
    "addr:full":"224 Hoover Pl Union NJ 07083",
    "addr:housenumber":"224",
    "addr:postcode":"07083",
    "addr:street":"Hoover Pl",
    "iso:country":"US",
    "sg:address":"224 Hoover Pl",
    "sg:city":"Union",
    "sg:classifiers":[
        {
            "category":"Autos & Motor Vehicles",
            "subcategory":"Auto Supplies",
            "type":"Retail Goods"
        }
    ],
    "sg:phone":"+1   ",
    "sg:postcode":"07083",
    "sg:province":"NJ",
    "wof:name":"Sound & Secure Installations",
    "wof:placetype":"venue"
},
  "geometry": {"coordinates":[-74.281494,40.696543],"type":"Point"}
}