{
  "type": "Feature",
  "properties": {
    "iso:country":"US",
    "sg:address":"1941 Oak Tree Rd",
    "sg:city":"Edison",
    "sg:classifiers":[
        {
            "category":"Shopping",
            "subcategory":"Computers & Home Electronics",
            "type":"Retail Goods"
        }
    ],
    "sg:phone":"+1 732 549 6868",
    "sg:postcode":"08820",
    "sg:province":"NJ",
    "sg:tags":[
        "software"
    ],
    "wof:name":"Allsoft Corp",
    "wof:placetype":"venue"
},
  "geometry": {"coordinates":[-74.362442,40.573038],"type":"Point"}
}