{
  "type": "Feature",
  "properties": {
    "addr:full":"433 Lincoln Ave Orange NJ 07050",
    "addr:housenumber":"433",
    "addr:postcode":"07050",
    "addr:street":"Lincoln Ave",
    "iso:country":"US",
    "sg:address":"433 Lincoln Ave",
    "sg:city":"Orange",
    "sg:classifiers":[
        {
            "category":"Professional",
            "type":"Services"
        }
    ],
    "sg:phone":"+1   ",
    "sg:postcode":"07050",
    "sg:province":"NJ",
    "wof:name":"Granite Riegh",
    "wof:placetype":"venue"
},
  "geometry": {"coordinates":[-74.241794,40.764397],"type":"Point"}
}