{
  "type": "Feature",
  "properties": {
    "addr:full":"92 Mandeville Ave Pequannock NJ 07440",
    "addr:housenumber":"92",
    "addr:postcode":"07440",
    "addr:street":"Mandeville Ave",
    "iso:country":"US",
    "sg:address":"92 Mandeville Ave",
    "sg:city":"Pequannock",
    "sg:classifiers":[
        {
            "category":"Professional",
            "subcategory":"Computer Services",
            "type":"Services"
        }
    ],
    "sg:phone":"+1 973 464 2524",
    "sg:postcode":"07440",
    "sg:province":"NJ",
    "sg:tags":[
        "design",
        "datum",
        "system"
    ],
    "wof:name":"Greek Bridal and Bapt",
    "wof:placetype":"venue"
},
  "geometry": {"coordinates":[-74.30442499999999,40.944162],"type":"Point"}
}