{
  "type": "Feature",
  "properties": {
    "iso:country":"US",
    "sg:address":"549 West Ave",
    "sg:city":"Pitman",
    "sg:classifiers":[
        {
            "category":"Manufacturing",
            "subcategory":"Toys & Sporting Goods",
            "type":"Manufacturing & Wholesale Goods"
        }
    ],
    "sg:phone":"+1 609 970 1481",
    "sg:postcode":"08071",
    "sg:province":"NJ",
    "sg:tags":[
        "equipment",
        "arts",
        "mfg",
        "martial"
    ],
    "wof:name":"Aggressive Manufacturing",
    "wof:placetype":"venue"
},
  "geometry": {"coordinates":[-75.128603,39.725563],"type":"Point"}
}