{
  "type": "Feature",
  "properties": {
    "iso:country":"US",
    "sg:address":"179 Delaware Ave",
    "sg:city":"Cliffwood",
    "sg:classifiers":[
        {
            "category":"Local Transit",
            "type":"Transportation"
        }
    ],
    "sg:phone":"+1 732 583 7575",
    "sg:postcode":"07721",
    "sg:province":"NJ",
    "sg:tags":[
        "airport"
    ],
    "wof:name":"Limo-R-Us Car & Limousine Svc",
    "wof:placetype":"venue"
},
  "geometry": {"coordinates":[-74.240769,40.436496],"type":"Point"}
}