{
  "type": "Feature",
  "properties": {
    "addr:full":"695 US Hwy 46 Fairfield NJ 07004",
    "addr:housenumber":"695",
    "addr:postcode":"07004",
    "addr:street":"Us Hwy 46",
    "iso:country":"US",
    "sg:address":"695 US Hwy 46",
    "sg:city":"Fairfield",
    "sg:classifiers":[
        {
            "category":"Banks & Credit Unions",
            "subcategory":"Bank",
            "type":"Services"
        }
    ],
    "sg:phone":"+1   ",
    "sg:postcode":"07004",
    "sg:province":"NJ",
    "sg:tags":[
        "state"
    ],
    "wof:name":"Chase Manhattan",
    "wof:placetype":"venue"
},
  "geometry": {"coordinates":[-74.267886,40.892018],"type":"Point"}
}