{
  "type": "Feature",
  "properties": {
    "iso:country":"US",
    "sg:address":"35 US Hwy 206",
    "sg:city":"Chester",
    "sg:classifiers":[
        {
            "category":"Restaurant",
            "type":"Food & Drink"
        }
    ],
    "sg:phone":"+1 908 879 8867",
    "sg:postcode":"07930",
    "sg:province":"NJ",
    "sg:website":"www.wendys.com",
    "wof:name":"Wendy's",
    "wof:placetype":"venue"
},
  "geometry": {"coordinates":[-74.70128699999999,40.787787],"type":"Point"}
}