{
  "type": "Feature",
  "properties": {
    "iso:country":"US",
    "sg:address":"23 South St",
    "sg:city":"Morristown",
    "sg:classifiers":[
        {
            "category":"Shopping",
            "subcategory":"Music",
            "type":"Retail Goods"
        },
        {
            "category":"Shopping",
            "subcategory":"Computers & Home Electronics",
            "type":"Retail Goods"
        }
    ],
    "sg:phone":"+1 973 538 5164",
    "sg:postcode":"07960",
    "sg:province":"NJ",
    "sg:tags":[
        "dvd's"
    ],
    "wof:name":"Scotti's Record Shop of Morristown",
    "wof:placetype":"venue"
},
  "geometry": {"coordinates":[-74.480103,40.7957],"type":"Point"}
}