{
  "type": "Feature",
  "properties": {
    "addr:full":"29 Van Bolton Rd Hillsborough NJ 08844",
    "addr:housenumber":"29",
    "addr:postcode":"08844",
    "addr:street":"Van Bolton Rd",
    "iso:country":"US",
    "sg:address":"29 Van Bolton Rd",
    "sg:city":"Hillsborough",
    "sg:classifiers":[
        {
            "category":"Building & Trades",
            "subcategory":"Plumbing",
            "type":"Services"
        }
    ],
    "sg:phone":"+1 908 369 1338",
    "sg:postcode":"08844",
    "sg:province":"NJ",
    "sg:tags":[
        "contractor"
    ],
    "wof:name":"Premier Fire Systems LLC",
    "wof:placetype":"venue"
},
  "geometry": {"coordinates":[-74.675822,40.509108],"type":"Point"}
}