{
  "type": "Feature",
  "properties": {
    "addr:full":"1080 Belle Ave Teaneck NJ 07666",
    "addr:housenumber":"1080",
    "addr:postcode":"07666",
    "addr:street":"Belle Ave",
    "iso:country":"US",
    "sg:address":"1080 Belle Ave",
    "sg:city":"Teaneck",
    "sg:classifiers":[
        {
            "category":"Local Transit",
            "type":"Transportation"
        }
    ],
    "sg:phone":"+1 201 907 0902",
    "sg:postcode":"07666",
    "sg:province":"NJ",
    "sg:tags":[
        "passenger"
    ],
    "wof:name":"Jt Limousine Service Inc",
    "wof:placetype":"venue"
},
  "geometry": {"coordinates":[-74.015353,40.896801],"type":"Point"}
}