{
  "type": "Feature",
  "properties": {
    "addr:full":"75 Tenafly Rd Tenafly NJ 07670",
    "addr:housenumber":"75",
    "addr:postcode":"07670",
    "addr:street":"Tenafly Rd",
    "iso:country":"US",
    "sg:address":"75 Tenafly Rd",
    "sg:city":"Tenafly",
    "sg:classifiers":[
        {
            "category":"Education",
            "subcategory":"School",
            "type":"Public Place"
        }
    ],
    "sg:phone":"+1 201 816 7710",
    "sg:postcode":"07670",
    "sg:province":"NJ",
    "wof:name":"Stillman School",
    "wof:placetype":"venue"
},
  "geometry": {"coordinates":[-73.971343,40.91577],"type":"Point"}
}