{
  "type": "Feature",
  "properties": {
    "iso:country":"US",
    "sg:address":"360 W Commodore Blvd",
    "sg:city":"Jackson",
    "sg:classifiers":[
        {
            "category":"Retail",
            "subcategory":"Auto Repair",
            "type":"Services"
        }
    ],
    "sg:phone":"+1 732 928 6388",
    "sg:postcode":"08527",
    "sg:province":"NJ",
    "sg:tags":[
        "body",
        "automobile",
        "painting"
    ],
    "wof:name":"Tilton Body Works",
    "wof:placetype":"venue"
},
  "geometry": {"coordinates":[-74.37416899999999,40.152458],"type":"Point"}
}