{
  "type": "Feature",
  "properties": {
    "iso:country":"US",
    "sg:address":"23 N Chelsea Ave",
    "sg:city":"Atlantic City",
    "sg:classifiers":[
        {
            "category":"Wholesale",
            "subcategory":"Electrical",
            "type":"Manufacturing & Wholesale Goods"
        }
    ],
    "sg:phone":"+1 609 345 3800",
    "sg:postcode":"08401",
    "sg:province":"NJ",
    "sg:tags":[
        "sound",
        "equipment",
        "system"
    ],
    "wof:name":"Yeoman Service",
    "wof:placetype":"venue"
},
  "geometry": {"coordinates":[-74.449681,39.354906],"type":"Point"}
}