{
  "type": "Feature",
  "properties": {
    "iso:country":"US",
    "sg:address":"194 Wood Ave",
    "sg:city":"Iselin",
    "sg:classifiers":[
        {
            "category":"Freight",
            "type":"Transportation"
        }
    ],
    "sg:phone":"+1 732 452 5400",
    "sg:postcode":"08830",
    "sg:province":"NJ",
    "sg:tags":[
        "deep",
        "sea"
    ],
    "wof:name":"A C L",
    "wof:placetype":"venue"
},
  "geometry": {"coordinates":[-74.336028,40.572937],"type":"Point"}
}