{
  "type": "Feature",
  "properties": {
    "iso:country":"US",
    "sg:address":"15 Jacksonville Rd",
    "sg:city":"Towaco",
    "sg:classifiers":[
        {
            "category":"Professional",
            "subcategory":"Art Services",
            "type":"Services"
        }
    ],
    "sg:phone":"+1   ",
    "sg:postcode":"07082",
    "sg:province":"NJ",
    "sg:tags":[
        "photography",
        "commercial"
    ],
    "wof:name":"George Kamper",
    "wof:placetype":"venue"
},
  "geometry": {"coordinates":[-74.338308,40.927349],"type":"Point"}
}