{
  "type": "Feature",
  "properties": {
    "iso:country":"US",
    "sg:address":"2015 Wabash Ave",
    "sg:city":"Linwood",
    "sg:classifiers":[
        {
            "category":"Education",
            "subcategory":"School",
            "type":"Public Place"
        }
    ],
    "sg:phone":"+1 609 926 6726",
    "sg:postcode":"08221",
    "sg:province":"NJ",
    "sg:website":"www.linwoodschools.org",
    "wof:name":"Seaview School",
    "wof:placetype":"venue"
},
  "geometry": {"coordinates":[-74.58351999999999,39.334309],"type":"Point"}
}