{
  "type": "Feature",
  "properties": {
    "addr:full":"1045 E Park Ave Vineland NJ 08360",
    "addr:housenumber":"1045",
    "addr:postcode":"08360",
    "addr:street":"E Park Ave",
    "iso:country":"US",
    "sg:address":"1045 E Park Ave",
    "sg:city":"Vineland",
    "sg:classifiers":[
        {
            "category":"Real Estate",
            "subcategory":"Real Estate Operator",
            "type":"Services"
        }
    ],
    "sg:phone":"+1   ",
    "sg:postcode":"08360",
    "sg:province":"NJ",
    "sg:tags":[
        "building",
        "apartment"
    ],
    "wof:name":"East Park Avenue Apartments",
    "wof:placetype":"venue"
},
  "geometry": {"coordinates":[-75.008253,39.490795],"type":"Point"}
}