{
  "type": "Feature",
  "properties": {
    "addr:full":"29 Studer Rd Clinton NJ 08809",
    "addr:housenumber":"29",
    "addr:postcode":"08809",
    "addr:street":"Studer Rd",
    "iso:country":"US",
    "sg:address":"29 Studer Rd",
    "sg:city":"Clinton",
    "sg:classifiers":[
        {
            "category":"Real Estate",
            "subcategory":"Real Estate Services",
            "type":"Services"
        }
    ],
    "sg:phone":"+1 908 735 7747",
    "sg:postcode":"08809",
    "sg:province":"NJ",
    "sg:tags":[
        "home",
        "inspector"
    ],
    "wof:name":"American Dream",
    "wof:placetype":"venue"
},
  "geometry": {"coordinates":[-74.894203,40.646999],"type":"Point"}
}