{
  "type": "Feature",
  "properties": {
    "iso:country":"US",
    "sg:address":"2909 Driftwood Ln",
    "sg:city":"Vineland",
    "sg:classifiers":[
        {
            "category":"Organizations",
            "subcategory":"Membership Organization",
            "type":"Services"
        }
    ],
    "sg:phone":"+1 856 691 9341",
    "sg:postcode":"08361",
    "sg:province":"NJ",
    "wof:name":"Hadassah",
    "wof:placetype":"venue"
},
  "geometry": {"coordinates":[-74.972464,39.456479],"type":"Point"}
}