{
  "type": "Feature",
  "properties": {
    "addr:full":"11 Court House South Dennis Rd Cape May Court House NJ 08210",
    "addr:housenumber":"11",
    "addr:postcode":"08210",
    "addr:street":"Court;South Dennis Rd",
    "iso:country":"US",
    "sg:address":"11 Court House South Dennis Rd",
    "sg:city":"Cape May Court House",
    "sg:classifiers":[
        {
            "category":"Food & Beverages",
            "subcategory":"Groceries & Convenience Stores",
            "type":"Retail Goods"
        }
    ],
    "sg:phone":"+1 609 465 2175",
    "sg:postcode":"08210",
    "sg:province":"NJ",
    "wof:name":"Acme Stores",
    "wof:placetype":"venue"
},
  "geometry": {"coordinates":[-74.819703,39.088383],"type":"Point"}
}