{
  "type": "Feature",
  "properties": {
    "addr:full":"19 Pine St Midland Park NJ 07432",
    "addr:housenumber":"19",
    "addr:postcode":"07432",
    "addr:street":"Pine St",
    "iso:country":"US",
    "sg:address":"19 Pine St",
    "sg:city":"Midland Park",
    "sg:classifiers":[
        {
            "category":"Retail",
            "subcategory":"Laundry & Dry Cleaning",
            "type":"Services"
        }
    ],
    "sg:phone":"+1 201 445 7866",
    "sg:postcode":"07432",
    "sg:province":"NJ",
    "sg:tags":[
        "cleaners",
        "rug",
        "carpet"
    ],
    "wof:name":"Dynaclean Rug Cleaners",
    "wof:placetype":"venue"
},
  "geometry": {"coordinates":[-74.135597,41.004741],"type":"Point"}
}