{
  "type": "Feature",
  "properties": {
    "iso:country":"US",
    "sg:address":"1071 Springfield Rd",
    "sg:city":"Union",
    "sg:classifiers":[
        {
            "category":"Shopping",
            "subcategory":"Stationery & Office Supplies",
            "type":"Retail Goods"
        }
    ],
    "sg:phone":"+1 908 688 9400",
    "sg:postcode":"07083",
    "sg:province":"NJ",
    "sg:tags":[
        "equipment"
    ],
    "wof:name":"General Office Supply Co Inc",
    "wof:placetype":"venue"
},
  "geometry": {"coordinates":[-74.3004,40.692799],"type":"Point"}
}