{
  "type": "Feature",
  "properties": {
    "addr:full":"207 Sheridan Ave Roselle NJ 07203",
    "addr:housenumber":"207",
    "addr:postcode":"07203",
    "addr:street":"Sheridan Ave",
    "iso:country":"US",
    "sg:address":"207 Sheridan Ave",
    "sg:city":"Roselle",
    "sg:classifiers":[
        {
            "category":"Retail",
            "subcategory":"Repair Shop",
            "type":"Services"
        }
    ],
    "sg:phone":"+1 908 241 6156",
    "sg:postcode":"07203",
    "sg:province":"NJ",
    "sg:tags":[
        "television",
        "radio"
    ],
    "wof:name":"R & R T V",
    "wof:placetype":"venue"
},
  "geometry": {"coordinates":[-74.24970500000001,40.660284],"type":"Point"}
}