{
  "type": "Feature",
  "properties": {
    "iso:country":"US",
    "sg:address":"4 Cherokee Trl",
    "sg:city":"Blairstown",
    "sg:classifiers":[
        {
            "category":"Health Services",
            "subcategory":"Doctor",
            "type":"Services"
        }
    ],
    "sg:phone":"+1 908 362 8042",
    "sg:postcode":"07825",
    "sg:province":"NJ",
    "sg:tags":[
        "dentist"
    ],
    "wof:name":"Robert Schwartz DMD",
    "wof:placetype":"venue"
},
  "geometry": {"coordinates":[-75.028904,40.953573],"type":"Point"}
}