{
  "type": "Feature",
  "properties": {
    "addr:full":"444 61st St West New York NJ 07093",
    "addr:housenumber":"444",
    "addr:postcode":"nj 07093",
    "addr:street":"61St St West",
    "iso:country":"US",
    "sg:address":"444 61st St",
    "sg:city":"West New York",
    "sg:classifiers":[
        {
            "category":"Food & Beverages",
            "subcategory":"Groceries & Convenience Stores",
            "type":"Retail Goods"
        }
    ],
    "sg:phone":"+1   ",
    "sg:postcode":"07093",
    "sg:province":"NJ",
    "wof:name":"Reyes Grocery",
    "wof:placetype":"venue"
},
  "geometry": {"coordinates":[-74.015235,40.790265],"type":"Point"}
}