{
  "type": "Feature",
  "properties": {
    "iso:country":"US",
    "sg:address":"135 Bloomfield Ave",
    "sg:city":"Bloomfield",
    "sg:classifiers":[
        {
            "category":"Health Services",
            "subcategory":"Doctor",
            "type":"Services"
        }
    ],
    "sg:phone":"+1 973 743 3556",
    "sg:postcode":"07003",
    "sg:province":"NJ",
    "wof:name":"Prudencio Reyes MD",
    "wof:placetype":"venue"
},
  "geometry": {"coordinates":[-74.18940000000001,40.779301],"type":"Point"}
}