{
  "type": "Feature",
  "properties": {
    "iso:country":"US",
    "sg:address":"572 Boulevard",
    "sg:city":"Kenilworth",
    "sg:classifiers":[
        {
            "category":"Restaurant",
            "type":"Food & Drink"
        }
    ],
    "sg:phone":"+1 908 709 1200",
    "sg:postcode":"07033",
    "sg:province":"NJ",
    "sg:tags":[
        "new",
        "american"
    ],
    "sg:website":"www.boulevardfive72.com",
    "wof:name":"Boulevard Five 72",
    "wof:placetype":"venue"
},
  "geometry": {"coordinates":[-74.288679,40.676522],"type":"Point"}
}