{
  "type": "Feature",
  "properties": {
    "addr:full":"19 Interstate Shop Ctr Ramsey NJ 07446",
    "addr:housenumber":"19",
    "addr:postcode":"07446",
    "iso:country":"US",
    "sg:address":"19 Interstate Shop Ctr",
    "sg:city":"Ramsey",
    "sg:classifiers":[
        {
            "category":"Restaurant",
            "type":"Food & Drink"
        }
    ],
    "sg:menulink":"http://www.allmenus.com/nj/ramsey/24920-new-york-pizza/menu/",
    "sg:phone":"+1 201 327 0808",
    "sg:postcode":"07446",
    "sg:province":"NJ",
    "sg:tags":[
        "sandwich",
        "salad",
        "cheesesteaks",
        "american",
        "pasta",
        "pizza"
    ],
    "wof:name":"New York Pizza",
    "wof:placetype":"venue"
},
  "geometry": {"coordinates":[-74.13633299999999,41.067545],"type":"Point"}
}