{
  "type": "Feature",
  "properties": {
    "addr:full":"1810 Cedarwood Dr Piscataway NJ 08854",
    "addr:housenumber":"1810",
    "addr:postcode":"08854",
    "addr:street":"Cedarwood Dr",
    "iso:country":"US",
    "sg:address":"1810 Cedarwood Dr",
    "sg:city":"Piscataway",
    "sg:classifiers":[
        {
            "category":"Shopping",
            "subcategory":"Discount & Variety Stores",
            "type":"Retail Goods"
        }
    ],
    "sg:phone":"+1   ",
    "sg:postcode":"08854",
    "sg:province":"NJ",
    "sg:tags":[
        "merchandise",
        "general"
    ],
    "wof:name":"Sullivan General",
    "wof:placetype":"venue"
},
  "geometry": {"coordinates":[-74.44626,40.586505],"type":"Point"}
}