{
  "type": "Feature",
  "properties": {
    "addr:full":"700 Allaire Rd Spring Lake NJ 07762",
    "addr:housenumber":"700",
    "addr:postcode":"07762",
    "addr:street":"Allaire Rd",
    "iso:country":"US",
    "sg:address":"700 Allaire Rd",
    "sg:city":"Spring Lake",
    "sg:classifiers":[
        {
            "category":"Banks & Credit Unions",
            "subcategory":"Bank",
            "type":"Services"
        }
    ],
    "sg:phone":"+1 732 974 9800",
    "sg:postcode":"07762",
    "sg:province":"NJ",
    "wof:name":"Central Jersey Bank",
    "wof:placetype":"venue"
},
  "geometry": {"coordinates":[-74.036571,40.158106],"type":"Point"}
}