{
  "type": "Feature",
  "properties": {
    "iso:country":"US",
    "sg:address":"280 Main St",
    "sg:city":"Little Falls",
    "sg:classifiers":[
        {
            "category":"Building & Trades",
            "subcategory":"Construction",
            "type":"Services"
        }
    ],
    "sg:phone":"+1 973 256 0644",
    "sg:postcode":"07424",
    "sg:province":"NJ",
    "sg:tags":[
        "residential",
        "nonresidential"
    ],
    "wof:name":"Edward Caiola Construction",
    "wof:placetype":"venue"
},
  "geometry": {"coordinates":[-74.23387099999999,40.882895],"type":"Point"}
}