{
  "type": "Feature",
  "properties": {
    "iso:country":"US",
    "sg:address":"216 Joseph St",
    "sg:city":"East Brunswick",
    "sg:classifiers":[
        {
            "category":"Government",
            "subcategory":"Fire Station",
            "type":"Public Place"
        }
    ],
    "sg:phone":"+1 732 257 2846",
    "sg:postcode":"08816",
    "sg:province":"NJ",
    "sg:tags":[
        "department"
    ],
    "wof:name":"East Brunswick Fire Dept",
    "wof:placetype":"venue"
},
  "geometry": {"coordinates":[-74.391282,40.439499],"type":"Point"}
}