{
  "type": "Feature",
  "properties": {
    "addr:full":"63 Pehle Ave Saddle Brook NJ 07663",
    "addr:housenumber":"63",
    "addr:postcode":"07663",
    "addr:street":"Pehle Ave",
    "iso:country":"US",
    "sg:address":"63 Pehle Ave",
    "sg:city":"Saddle Brook",
    "sg:classifiers":[
        {
            "category":"Social Services",
            "subcategory":"Child Care",
            "type":"Services"
        }
    ],
    "sg:phone":"+1 201 368 0755",
    "sg:postcode":"07663",
    "sg:province":"NJ",
    "wof:name":"Daddio Dorothy",
    "wof:placetype":"venue"
},
  "geometry": {"coordinates":[-74.093676,40.90786],"type":"Point"}
}