{
  "type": "Feature",
  "properties": {
    "addr:full":"1255 Raritan Rd Clark NJ 07066",
    "addr:housenumber":"1255",
    "addr:postcode":"07066",
    "addr:street":"Raritan Rd",
    "iso:country":"US",
    "sg:address":"1255 Raritan Rd",
    "sg:city":"Clark",
    "sg:classifiers":[
        {
            "category":"Manufacturing",
            "subcategory":"Glass & Minerals",
            "type":"Manufacturing & Wholesale Goods"
        },
        {
            "category":"Manufacturing",
            "subcategory":"Paper Products",
            "type":"Manufacturing & Wholesale Goods"
        }
    ],
    "sg:phone":"+1 732 388 9100",
    "sg:postcode":"07066",
    "sg:province":"NJ",
    "sg:tags":[
        "mill",
        "gypsum",
        "paperboard",
        "mfg"
    ],
    "wof:name":"United States Gypsum Company",
    "wof:placetype":"venue"
},
  "geometry": {"coordinates":[-74.306073,40.632107],"type":"Point"}
}