{
  "type": "Feature",
  "properties": {
    "iso:country":"US",
    "sg:address":"1361 S Fairview St",
    "sg:city":"Delran",
    "sg:classifiers":[
        {
            "category":"Organizations",
            "subcategory":"Religious Organization",
            "type":"Services"
        }
    ],
    "sg:phone":"+1 856 461 9446",
    "sg:postcode":"08075",
    "sg:province":"NJ",
    "sg:tags":[
        "church"
    ],
    "wof:name":"Zion Total Wellness Salon",
    "wof:placetype":"venue"
},
  "geometry": {"coordinates":[-74.947863,40.023961],"type":"Point"}
}