{
  "type": "Feature",
  "properties": {
    "addr:full":"329 Broad St Bloomfield NJ 07003",
    "addr:housenumber":"329",
    "addr:postcode":"07003",
    "addr:street":"Broad St",
    "iso:country":"US",
    "sg:address":"329 Broad St",
    "sg:city":"Bloomfield",
    "sg:classifiers":[
        {
            "category":"Real Estate",
            "subcategory":"Real Estate Agent",
            "type":"Services"
        }
    ],
    "sg:phone":"+1   ",
    "sg:postcode":"07003",
    "sg:province":"NJ",
    "wof:name":"Jay Baumgardner",
    "wof:placetype":"venue"
},
  "geometry": {"coordinates":[-74.194507,40.804154],"type":"Point"}
}