{
  "type": "Feature",
  "properties": {
    "addr:full":"1400 Willowbrook Mall Wayne NJ 07470",
    "addr:housenumber":"1400",
    "addr:postcode":"07470",
    "addr:street":"Willowbrook Mall",
    "iso:country":"US",
    "sg:address":"1400 Willowbrook Mall",
    "sg:city":"Wayne",
    "sg:classifiers":[
        {
            "category":"Personal",
            "subcategory":"Tattoo Parlor",
            "type":"Services"
        },
        {
            "category":"Personal",
            "subcategory":"Piercing",
            "type":"Services"
        }
    ],
    "sg:phone":"+1 973 785 1616",
    "sg:postcode":"07470",
    "sg:province":"NJ",
    "sg:tags":[
        "body"
    ],
    "wof:name":"Willowbrook",
    "wof:placetype":"venue"
},
  "geometry": {"coordinates":[-74.26220000000001,40.891421],"type":"Point"}
}