{
  "type": "Feature",
  "properties": {
    "addr:full":"190 River Rd Edgewater NJ 07020",
    "addr:housenumber":"190",
    "addr:postcode":"07020",
    "addr:street":"River Rd",
    "iso:country":"US",
    "sg:address":"190 River Rd",
    "sg:city":"Edgewater",
    "sg:classifiers":[
        {
            "category":"Banks & Credit Unions",
            "subcategory":"Bank",
            "type":"Services"
        }
    ],
    "sg:phone":"+1 201 943 9888",
    "sg:postcode":"07020",
    "sg:province":"NJ",
    "wof:name":"Mariner's Bank",
    "wof:placetype":"venue"
},
  "geometry": {"coordinates":[-73.990649,40.807341],"type":"Point"}
}