{
  "type": "Feature",
  "properties": {
    "addr:full":"1176 Old Indian Mills Rd Vincentown NJ 08088",
    "addr:housenumber":"1176",
    "addr:postcode":"08088",
    "addr:street":"Old Indian Mills Rd",
    "iso:country":"US",
    "sg:address":"1176 Old Indian Mills Rd",
    "sg:city":"Vincentown",
    "sg:classifiers":[
        {
            "category":"Professional",
            "subcategory":"Computer Services",
            "type":"Services"
        }
    ],
    "sg:phone":"+1   ",
    "sg:postcode":"08088",
    "sg:province":"NJ",
    "sg:tags":[
        "related"
    ],
    "wof:name":"Justin Taylor",
    "wof:placetype":"venue"
},
  "geometry": {"coordinates":[-74.727197,39.817837],"type":"Point"}
}