{
  "type": "Feature",
  "properties": {
    "iso:country":"US",
    "sg:address":"662 Goffle Rd",
    "sg:city":"Hawthorne",
    "sg:classifiers":[
        {
            "category":"Wholesale",
            "subcategory":"Stationery",
            "type":"Manufacturing & Wholesale Goods"
        }
    ],
    "sg:phone":"+1 973 636 2801",
    "sg:postcode":"07506",
    "sg:province":"NJ",
    "sg:tags":[
        "sales",
        "film",
        "papers"
    ],
    "wof:name":"Papertec Inc",
    "wof:placetype":"venue"
},
  "geometry": {"coordinates":[-74.162882,40.954348],"type":"Point"}
}