{
  "type": "Feature",
  "properties": {
    "iso:country":"US",
    "sg:address":"169 Lincoln Ave",
    "sg:city":"Fair Lawn",
    "sg:classifiers":[
        {
            "category":"Professional",
            "subcategory":"Lawyer & Legal Services",
            "type":"Services"
        }
    ],
    "sg:phone":"+1   ",
    "sg:postcode":"07506",
    "sg:province":"NJ",
    "wof:name":"Bartel & Bartel",
    "wof:placetype":"venue"
},
  "geometry": {"coordinates":[-74.146974,40.946011],"type":"Point"}
}