{
  "type": "Feature",
  "properties": {
    "addr:full":"228 Carlton Ave East Rutherford NJ 07073",
    "addr:housenumber":"228",
    "addr:postcode":"07073",
    "addr:street":"Carlton Ave",
    "iso:country":"US",
    "sg:address":"228 Carlton Ave",
    "sg:city":"East Rutherford",
    "sg:classifiers":[
        {
            "category":"Wholesale",
            "subcategory":"Vending Machines",
            "type":"Manufacturing & Wholesale Goods"
        }
    ],
    "sg:phone":"+1 973 472 9491",
    "sg:postcode":"07073",
    "sg:province":"NJ",
    "wof:name":"Biancamano Enterprises Inc",
    "wof:placetype":"venue"
},
  "geometry": {"coordinates":[-74.117158,40.848929],"type":"Point"}
}