{
  "type": "Feature",
  "properties": {
    "iso:country":"US",
    "sg:address":"206 Belleville Ave",
    "sg:city":"Bloomfield",
    "sg:classifiers":[
        {
            "category":"Health Services",
            "subcategory":"Health Practitioner",
            "type":"Services"
        }
    ],
    "sg:phone":"+1 973 743 9700",
    "sg:postcode":"07003",
    "sg:province":"NJ",
    "sg:tags":[
        "therapy",
        "physical"
    ],
    "wof:name":"Advanced Rehab Professionals Llc",
    "wof:placetype":"venue"
},
  "geometry": {"coordinates":[-74.188615,40.799044],"type":"Point"}
}