{
  "type": "Feature",
  "properties": {
    "addr:full":"82 Lawrence Rd Randolph NJ 07869",
    "addr:housenumber":"82",
    "addr:postcode":"07869",
    "addr:street":"Lawrence Rd",
    "iso:country":"US",
    "sg:address":"82 Lawrence Rd",
    "sg:city":"Randolph",
    "sg:classifiers":[
        {
            "category":"Shopping",
            "subcategory":"Used Merchandise",
            "type":"Retail Goods"
        }
    ],
    "sg:phone":"+1   ",
    "sg:postcode":"07869",
    "sg:province":"NJ",
    "sg:tags":[
        "antique",
        "vintage",
        "book",
        "clothing"
    ],
    "wof:name":"ABRA Cadaver",
    "wof:placetype":"venue"
},
  "geometry": {"coordinates":[-74.57278599999999,40.852862],"type":"Point"}
}