{
  "type": "Feature",
  "properties": {
    "addr:full":"3270 State Rte 27 Kendall Park NJ 08824",
    "addr:housenumber":"3270",
    "addr:postcode":"08824",
    "addr:street":"State Rte 27",
    "iso:country":"US",
    "sg:address":"3270 State Rte 27",
    "sg:city":"Kendall Park",
    "sg:classifiers":[
        {
            "category":"Real Estate",
            "subcategory":"Real Estate Operator",
            "type":"Services"
        }
    ],
    "sg:phone":"+1   ",
    "sg:postcode":"08824",
    "sg:province":"NJ",
    "sg:tags":[
        "company",
        "holding"
    ],
    "wof:name":"3270 Professional Associates",
    "wof:placetype":"venue"
},
  "geometry": {"coordinates":[-74.56332399999999,40.426913],"type":"Point"}
}