{
  "type": "Feature",
  "properties": {
    "iso:country":"US",
    "sg:address":"8 S Orange Ave",
    "sg:city":"South Orange",
    "sg:classifiers":[
        {
            "category":"Shopping",
            "subcategory":"Discount & Variety Stores",
            "type":"Retail Goods"
        }
    ],
    "sg:phone":"+1   ",
    "sg:postcode":"07079",
    "sg:province":"NJ",
    "wof:name":"Glory Gift & News",
    "wof:placetype":"venue"
},
  "geometry": {"coordinates":[-74.260037,40.74633],"type":"Point"}
}