{
  "type": "Feature",
  "properties": {
    "addr:full":"624 N Clinton Ave Trenton NJ 08638",
    "addr:housenumber":"624",
    "addr:postcode":"08638",
    "addr:street":"N Clinton Ave",
    "iso:country":"US",
    "sg:address":"624 N Clinton Ave",
    "sg:city":"Trenton",
    "sg:classifiers":[
        {
            "category":"Shopping",
            "subcategory":"Clothing, Apparel, & Fashions",
            "type":"Retail Goods"
        }
    ],
    "sg:phone":"+1   ",
    "sg:postcode":"08638",
    "sg:province":"NJ",
    "wof:name":"Jeannettes Boutique",
    "wof:placetype":"venue"
},
  "geometry": {"coordinates":[-74.74403599999999,40.231959],"type":"Point"}
}