{
  "type": "Feature",
  "properties": {
    "addr:full":"1051 Springfield Ave Irvington NJ 07111",
    "addr:housenumber":"1051",
    "addr:postcode":"07111",
    "addr:street":"Springfield Ave",
    "iso:country":"US",
    "sg:address":"1051 Springfield Ave",
    "sg:city":"Irvington",
    "sg:classifiers":[
        {
            "category":"Real Estate",
            "subcategory":"Real Estate Agent",
            "type":"Services"
        }
    ],
    "sg:phone":"+1 973 373 7800",
    "sg:postcode":"07111",
    "sg:province":"NJ",
    "wof:name":"Schelane Realty",
    "wof:placetype":"venue"
},
  "geometry": {"coordinates":[-74.237724,40.725055],"type":"Point"}
}