{
  "type": "Feature",
  "properties": {
    "iso:country":"US",
    "sg:address":"511 White Horse Pike",
    "sg:city":"Oaklyn",
    "sg:classifiers":[
        {
            "category":"Personal",
            "subcategory":"Barber",
            "type":"Services"
        }
    ],
    "sg:phone":"+1 856 854 4844",
    "sg:postcode":"08107",
    "sg:province":"NJ",
    "sg:tags":[
        "wig",
        "hair",
        "piece"
    ],
    "wof:name":"Razor's Edge",
    "wof:placetype":"venue"
},
  "geometry": {"coordinates":[-75.078311,39.903781],"type":"Point"}
}