{
  "type": "Feature",
  "properties": {
    "iso:country":"US",
    "sg:address":"220 Roosevelt Ave",
    "sg:city":"Carteret",
    "sg:classifiers":[
        {
            "category":"Retail",
            "subcategory":"Auto Repair",
            "type":"Services"
        }
    ],
    "sg:phone":"+1 732 969 2110",
    "sg:postcode":"07008",
    "sg:province":"NJ",
    "sg:tags":[
        "body",
        "automobile",
        "painting"
    ],
    "wof:name":"P & E Auto Body Inc",
    "wof:placetype":"venue"
},
  "geometry": {"coordinates":[-74.21892099999999,40.574982],"type":"Point"}
}