{
  "type": "Feature",
  "properties": {
    "iso:country":"US",
    "sg:address":"259 Stephens St",
    "sg:city":"Belleville",
    "sg:classifiers":[
        {
            "category":"Building & Trades",
            "subcategory":"Construction",
            "type":"Services"
        }
    ],
    "sg:phone":"+1 973 450 1235",
    "sg:postcode":"07109",
    "sg:province":"NJ",
    "sg:tags":[
        "general",
        "contractor"
    ],
    "sg:website":"www.idea-aec.com",
    "wof:name":"Integrated Construction Entps",
    "wof:placetype":"venue"
},
  "geometry": {"coordinates":[-74.14825,40.790323],"type":"Point"}
}