{
  "type": "Feature",
  "properties": {
    "addr:full":"42 Fardale Ave Mahwah NJ 07430",
    "addr:housenumber":"42",
    "addr:postcode":"07430",
    "addr:street":"Fardale Ave",
    "iso:country":"US",
    "sg:address":"42 Fardale Ave",
    "sg:city":"Mahwah",
    "sg:classifiers":[
        {
            "category":"Wholesale",
            "subcategory":"Jewelry",
            "type":"Manufacturing & Wholesale Goods"
        }
    ],
    "sg:phone":"+1 201 818 9224",
    "sg:postcode":"07430",
    "sg:province":"NJ",
    "sg:tags":[
        "stone"
    ],
    "wof:name":"All About Charms",
    "wof:placetype":"venue"
},
  "geometry": {"coordinates":[-74.176947,41.040862],"type":"Point"}
}