{
  "type": "Feature",
  "properties": {
    "iso:country":"US",
    "sg:address":"443 21st Ave",
    "sg:city":"Paterson",
    "sg:classifiers":[
        {
            "category":"Restaurant",
            "type":"Food & Drink"
        }
    ],
    "sg:phone":"+1   ",
    "sg:postcode":"07513",
    "sg:province":"NJ",
    "sg:tags":[
        "eating"
    ],
    "wof:name":"Altagracia Restaurant",
    "wof:placetype":"venue"
},
  "geometry": {"coordinates":[-74.155731,40.906487],"type":"Point"}
}