{
  "type": "Feature",
  "properties": {
    "iso:country":"US",
    "sg:address":"15 Independence Blvd",
    "sg:city":"Warren",
    "sg:classifiers":[
        {
            "category":"Manufacturing",
            "subcategory":"Tools & Machinery",
            "type":"Manufacturing & Wholesale Goods"
        },
        {
            "category":"Professional",
            "subcategory":"Computer Services",
            "type":"Services"
        }
    ],
    "sg:phone":"+1 908 626 2800",
    "sg:postcode":"07059",
    "sg:province":"NJ",
    "sg:tags":[
        "prepackaged",
        "software"
    ],
    "sg:website":"www.mentor.com",
    "wof:name":"Mentor Graphics Corporation",
    "wof:placetype":"venue"
},
  "geometry": {"coordinates":[-74.572446,40.651027],"type":"Point"}
}