{
  "type": "Feature",
  "properties": {
    "addr:full":"361 State Rte 17 Paramus NJ 07652",
    "addr:housenumber":"361",
    "addr:postcode":"07652",
    "addr:street":"State Rte 17",
    "iso:country":"US",
    "sg:address":"361 State Rte 17",
    "sg:city":"Paramus",
    "sg:classifiers":[
        {
            "category":"Autos & Motor Vehicles",
            "subcategory":"Auto Supplies",
            "type":"Retail Goods"
        }
    ],
    "sg:phone":"+1 201 265 9181",
    "sg:postcode":"07652",
    "sg:province":"NJ",
    "sg:tags":[
        "tire"
    ],
    "sg:website":"www.paramusdiscounttire.com",
    "wof:name":"Discount Tire Co",
    "wof:placetype":"venue"
},
  "geometry": {"coordinates":[-74.07082699999999,40.910585],"type":"Point"}
}