{
  "type": "Feature",
  "properties": {
    "addr:full":"Foot of Potter & Ell Haddonfield NJ 08033",
    "addr:postcode":"08033",
    "iso:country":"US",
    "sg:address":"Foot of Potter & Ell",
    "sg:city":"Haddonfield",
    "sg:classifiers":[
        {
            "category":"Sports & Exercise",
            "subcategory":"Sports Center",
            "type":"Entertainment"
        },
        {
            "category":"Arena",
            "subcategory":"Sports Club",
            "type":"Entertainment"
        }
    ],
    "sg:phone":"+1 856 428 0140",
    "sg:postcode":"08033",
    "sg:province":"NJ",
    "sg:tags":[
        "professional",
        "amateur",
        "team"
    ],
    "wof:name":"Haddonfield Little League",
    "wof:placetype":"venue"
},
  "geometry": {"coordinates":[-75.042,39.896198],"type":"Point"}
}