{
  "type": "Feature",
  "properties": {
    "iso:country":"US",
    "sg:address":"231 Van Riper Ave",
    "sg:city":"Elmwood Park",
    "sg:classifiers":[
        {
            "category":"Manufacturing",
            "subcategory":"Tools & Machinery",
            "type":"Manufacturing & Wholesale Goods"
        }
    ],
    "sg:phone":"+1 201 791 6804",
    "sg:postcode":"07407",
    "sg:province":"NJ",
    "sg:tags":[
        "machine",
        "shop"
    ],
    "wof:name":"Precision Instrument Co",
    "wof:placetype":"venue"
},
  "geometry": {"coordinates":[-74.11811299999999,40.902536],"type":"Point"}
}