{
  "type": "Feature",
  "properties": {
    "addr:full":"50 Essex St Rochelle Park NJ 07662",
    "addr:housenumber":"50",
    "addr:postcode":"07662",
    "addr:street":"Essex St",
    "iso:country":"US",
    "sg:address":"50 Essex St",
    "sg:city":"Rochelle Park",
    "sg:classifiers":[
        {
            "category":"Building & Trades",
            "subcategory":"Construction",
            "type":"Services"
        }
    ],
    "sg:phone":"+1 201 845 4838",
    "sg:postcode":"07662",
    "sg:province":"NJ",
    "sg:tags":[
        "general",
        "contractor"
    ],
    "wof:name":"B & J Construction Svc",
    "wof:placetype":"venue"
},
  "geometry": {"coordinates":[-74.076798,40.894365],"type":"Point"}
}