{
  "type": "Feature",
  "properties": {
    "iso:country":"US",
    "sg:address":"114 Glen Ave",
    "sg:city":"Midland Park",
    "sg:classifiers":[
        {
            "category":"Building & Trades",
            "subcategory":"Electrical",
            "type":"Services"
        }
    ],
    "sg:phone":"+1 201 445 5156",
    "sg:postcode":"07432",
    "sg:province":"NJ",
    "sg:tags":[
        "repair",
        "electrical",
        "electric",
        "contractor"
    ],
    "wof:name":"Van's Electric",
    "wof:placetype":"venue"
},
  "geometry": {"coordinates":[-74.133303,40.995101],"type":"Point"}
}