{
  "type": "Feature",
  "properties": {
    "addr:full":"1331 N Black Horse Pike Williamstown NJ 08094",
    "addr:housenumber":"1331",
    "addr:postcode":"08094",
    "addr:street":"N Black Horse Pike",
    "iso:country":"US",
    "sg:address":"1331 N Black Horse Pike",
    "sg:city":"Williamstown",
    "sg:classifiers":[
        {
            "category":"Shopping",
            "subcategory":"Department Store",
            "type":"Retail Goods"
        }
    ],
    "sg:phone":"+1 856 875 8335",
    "sg:postcode":"08094",
    "sg:province":"NJ",
    "sg:tags":[
        "shop"
    ],
    "wof:name":"Discount Domestics",
    "wof:placetype":"venue"
},
  "geometry": {"coordinates":[-75.00854699999999,39.704885],"type":"Point"}
}