{
  "type": "Feature",
  "properties": {
    "addr:full":"200 Country Club Pkwy Mount Laurel NJ 08054",
    "addr:housenumber":"200",
    "addr:postcode":"08054",
    "addr:street":"Country Club Pkwy",
    "iso:country":"US",
    "sg:address":"200 Country Club Pkwy",
    "sg:city":"Mount Laurel",
    "sg:classifiers":[
        {
            "category":"Recreation",
            "type":"Entertainment"
        }
    ],
    "sg:phone":"+1   ",
    "sg:postcode":"08054",
    "sg:province":"NJ",
    "sg:tags":[
        "club",
        "country"
    ],
    "wof:name":"Ramblewood Country Club",
    "wof:placetype":"venue"
},
  "geometry": {"coordinates":[-74.938446,39.92037],"type":"Point"}
}