{
  "type": "Feature",
  "properties": {
    "addr:full":"7 Church St Vernon NJ 07462",
    "addr:housenumber":"7",
    "addr:postcode":"07462",
    "addr:street":"Church St",
    "iso:country":"US",
    "sg:address":"7 Church St",
    "sg:city":"Vernon",
    "sg:classifiers":[
        {
            "category":"Banks & Credit Unions",
            "subcategory":"Bank",
            "type":"Services"
        }
    ],
    "sg:phone":"+1 973 764 6175",
    "sg:postcode":"07462",
    "sg:province":"NJ",
    "sg:tags":[
        "saving",
        "commercial"
    ],
    "wof:name":"Sussexbank",
    "wof:placetype":"venue"
},
  "geometry": {"coordinates":[-74.48537399999999,41.200059],"type":"Point"}
}