{
  "type": "Feature",
  "properties": {
    "iso:country":"US",
    "sg:address":"250 N Broad St",
    "sg:city":"Penns Grove",
    "sg:classifiers":[
        {
            "category":"Building & Trades",
            "subcategory":"Construction",
            "type":"Services"
        }
    ],
    "sg:phone":"+1 856 299 8240",
    "sg:postcode":"08069",
    "sg:province":"NJ",
    "sg:tags":[
        "general",
        "contractor"
    ],
    "wof:name":"W J V General Contractors",
    "wof:placetype":"venue"
},
  "geometry": {"coordinates":[-75.46122099999999,39.739197],"type":"Point"}
}