{
  "type": "Feature",
  "properties": {
    "iso:country":"US",
    "sg:address":"9 Eastman St",
    "sg:city":"Cranford",
    "sg:classifiers":[
        {
            "category":"Shopping",
            "type":"Retail Goods"
        }
    ],
    "sg:phone":"+1 908 276 8843",
    "sg:postcode":"07016",
    "sg:province":"NJ",
    "sg:tags":[
        "picture",
        "frame",
        "art",
        "gallery"
    ],
    "wof:name":"Framing Center & Fine Art Gallery",
    "wof:placetype":"venue"
},
  "geometry": {"coordinates":[-74.30500000000001,40.655399],"type":"Point"}
}