{
  "type": "Feature",
  "properties": {
    "iso:country":"US",
    "sg:address":"251 Vreeland Ave",
    "sg:city":"Paterson",
    "sg:classifiers":[
        {
            "category":"Manufacturing",
            "subcategory":"Printing",
            "type":"Manufacturing & Wholesale Goods"
        }
    ],
    "sg:phone":"+1 973 523 7543",
    "sg:postcode":"07504",
    "sg:province":"NJ",
    "sg:tags":[
        "periodical"
    ],
    "wof:name":"Garden State Periodical",
    "wof:placetype":"venue"
},
  "geometry": {"coordinates":[-74.139652,40.905113],"type":"Point"}
}