{
  "type": "Feature",
  "properties": {
    "addr:full":"31 Faith Ln Matawan NJ 07747",
    "addr:housenumber":"31",
    "addr:postcode":"07747",
    "addr:street":"Faith Ln",
    "iso:country":"US",
    "sg:address":"31 Faith Ln",
    "sg:city":"Matawan",
    "sg:classifiers":[
        {
            "category":"Professional",
            "subcategory":"Computer Services",
            "type":"Services"
        }
    ],
    "sg:phone":"+1   ",
    "sg:postcode":"07747",
    "sg:province":"NJ",
    "sg:tags":[
        "related"
    ],
    "wof:name":"W A M Network Services",
    "wof:placetype":"venue"
},
  "geometry": {"coordinates":[-74.22991500000001,40.392739],"type":"Point"}
}