{
  "type": "Feature",
  "properties": {
    "iso:country":"US",
    "sg:address":"15 State St",
    "sg:city":"Bloomfield",
    "sg:classifiers":[
        {
            "category":"Autos & Motor Vehicles",
            "subcategory":"Fuel & Gas Station",
            "type":"Retail Goods"
        }
    ],
    "sg:phone":"+1 973 338 0212",
    "sg:postcode":"07003",
    "sg:province":"NJ",
    "sg:tags":[
        "oil"
    ],
    "wof:name":"Brookdale South Mobil",
    "wof:placetype":"venue"
},
  "geometry": {"coordinates":[-74.19851800000001,40.797641],"type":"Point"}
}