{
  "type": "Feature",
  "properties": {
    "addr:full":"29 South St New Providence NJ 07974",
    "addr:housenumber":"29",
    "addr:postcode":"07974",
    "addr:street":"South St",
    "iso:country":"US",
    "sg:address":"29 South St",
    "sg:city":"New Providence",
    "sg:classifiers":[
        {
            "category":"Health Services",
            "subcategory":"Doctor",
            "type":"Services"
        }
    ],
    "sg:phone":"+1 908 464 1294",
    "sg:postcode":"07974",
    "sg:province":"NJ",
    "wof:name":"Sorvino A Ronald MD",
    "wof:placetype":"venue"
},
  "geometry": {"coordinates":[-74.40629199999999,40.705092],"type":"Point"}
}