{
  "type": "Feature",
  "properties": {
    "iso:country":"US",
    "sg:address":"301 New York Ave",
    "sg:city":"Wildwood",
    "sg:classifiers":[
        {
            "category":"Restaurant",
            "type":"Food & Drink"
        }
    ],
    "sg:phone":"+1 609 522 7759",
    "sg:postcode":"08260",
    "sg:province":"NJ",
    "wof:name":"J D Mcgillicuddys",
    "wof:placetype":"venue"
},
  "geometry": {"coordinates":[-74.7966,39.007833],"type":"Point"}
}