{
  "type": "Feature",
  "properties": {
    "addr:full":"609 Beverly Rancocas Rd Willingboro NJ 08046",
    "addr:housenumber":"609",
    "addr:postcode":"08046",
    "addr:street":"Beverly Rancocas Rd",
    "iso:country":"US",
    "sg:address":"609 Beverly Rancocas Rd",
    "sg:city":"Willingboro",
    "sg:classifiers":[
        {
            "category":"Restaurant",
            "type":"Food & Drink"
        }
    ],
    "sg:phone":"+1   ",
    "sg:postcode":"08046",
    "sg:province":"NJ",
    "sg:tags":[
        "eating"
    ],
    "wof:name":"Pizza Express",
    "wof:placetype":"venue"
},
  "geometry": {"coordinates":[-74.874658,40.013148],"type":"Point"}
}