{
  "type": "Feature",
  "properties": {
    "addr:full":"1210 Grand Ave Mays Landing NJ 08330",
    "addr:housenumber":"1210",
    "addr:postcode":"08330",
    "addr:street":"Grand Ave",
    "iso:country":"US",
    "sg:address":"1210 Grand Ave",
    "sg:city":"Mays Landing",
    "sg:classifiers":[
        {
            "category":"Arts & Performance",
            "subcategory":"Theater",
            "type":"Entertainment"
        }
    ],
    "sg:phone":"+1 609 645 0607",
    "sg:postcode":"08330",
    "sg:province":"NJ",
    "sg:tags":[
        "television",
        "program",
        "producer"
    ],
    "wof:name":"Videophreak Productions",
    "wof:placetype":"venue"
},
  "geometry": {"coordinates":[-74.643658,39.425706],"type":"Point"}
}