{
  "type": "Feature",
  "properties": {
    "iso:country":"US",
    "sg:address":"12 Sayre St",
    "sg:city":"Elizabeth",
    "sg:classifiers":[
        {
            "category":"Building & Trades",
            "subcategory":"Construction",
            "type":"Services"
        }
    ],
    "sg:phone":"+1 908 289 1655",
    "sg:postcode":"07208",
    "sg:province":"NJ",
    "sg:tags":[
        "general",
        "contractor"
    ],
    "wof:name":"J K Construction",
    "wof:placetype":"venue"
},
  "geometry": {"coordinates":[-74.220311,40.669534],"type":"Point"}
}