{
  "type": "Feature",
  "properties": {
    "addr:full":"179 Flanders Dr Somerville NJ 08844",
    "addr:housenumber":"179",
    "addr:postcode":"08844",
    "addr:street":"Flanders Dr",
    "iso:country":"US",
    "sg:address":"179 Flanders Dr",
    "sg:city":"Somerville",
    "sg:classifiers":[
        {
            "category":"Manufacturing",
            "subcategory":"Paper Products",
            "type":"Manufacturing & Wholesale Goods"
        }
    ],
    "sg:phone":"+1 908 281 7522",
    "sg:postcode":"08844",
    "sg:province":"NJ",
    "sg:tags":[
        "mill"
    ],
    "wof:name":"Simply Splendid",
    "wof:placetype":"venue"
},
  "geometry": {"coordinates":[-74.630861,40.508025],"type":"Point"}
}