{
  "type": "Feature",
  "properties": {
    "addr:full":"1117 US Highway 46 Clifton NJ 07013",
    "addr:housenumber":"1117",
    "addr:postcode":"07013",
    "addr:street":"Us Highway 46",
    "iso:country":"US",
    "sg:address":"1117 US Highway 46",
    "sg:city":"Clifton",
    "sg:classifiers":[
        {
            "category":"Health Services",
            "subcategory":"Doctor",
            "type":"Services"
        }
    ],
    "sg:phone":"+1 973 365 2208",
    "sg:postcode":"07013",
    "sg:province":"NJ",
    "sg:tags":[
        "podiatrist"
    ],
    "sg:website":"www.affiliatedfootandanklespecia...",
    "wof:name":"Miller Jeffrey DPM",
    "wof:placetype":"venue"
},
  "geometry": {"coordinates":[-74.18229700000001,40.870201],"type":"Point"}
}