{
  "type": "Feature",
  "properties": {
    "iso:country":"US",
    "sg:address":"229 Edwards Ave",
    "sg:city":"Long Branch",
    "sg:classifiers":[
        {
            "category":"Banks & Credit Unions",
            "subcategory":"Financial Services",
            "type":"Services"
        }
    ],
    "sg:phone":"+1   ",
    "sg:postcode":"07740",
    "sg:province":"NJ",
    "sg:tags":[
        "investor"
    ],
    "wof:name":"Tresor Investments Inc",
    "wof:placetype":"venue"
},
  "geometry": {"coordinates":[-74.002075,40.31011],"type":"Point"}
}