{
  "type": "Feature",
  "properties": {
    "addr:full":"4 Route Us 9 N Marmora NJ 08223",
    "addr:housenumber":"4",
    "addr:postcode":"08223",
    "addr:street":"Route Us 9 N",
    "iso:country":"US",
    "sg:address":"4 Route Us 9 N",
    "sg:city":"Marmora",
    "sg:classifiers":[
        {
            "category":"Restaurant",
            "type":"Food & Drink"
        }
    ],
    "sg:menulink":"http://www.allmenus.com/nj/upper/181708-wendys/menu/",
    "sg:phone":"+1 609 390 1104",
    "sg:postcode":"08223",
    "sg:province":"NJ",
    "sg:tags":[
        "burger",
        "american",
        "soup"
    ],
    "wof:name":"Wendy's",
    "wof:placetype":"venue"
},
  "geometry": {"coordinates":[-74.647493,39.264424],"type":"Point"}
}