{
  "type": "Feature",
  "properties": {
    "iso:country":"US",
    "sg:address":"15 Regina Dr",
    "sg:city":"Howell",
    "sg:classifiers":[
        {
            "category":"Professional",
            "subcategory":"Detective & Security Services",
            "type":"Services"
        }
    ],
    "sg:phone":"+1 732 961 0354",
    "sg:postcode":"07731",
    "sg:province":"NJ",
    "sg:tags":[
        "car"
    ],
    "wof:name":"M&S United Security Con",
    "wof:placetype":"venue"
},
  "geometry": {"coordinates":[-74.233486,40.139988],"type":"Point"}
}