{
  "type": "Feature",
  "properties": {
    "iso:country":"US",
    "sg:address":"456 Monroe St",
    "sg:city":"Passaic",
    "sg:classifiers":[
        {
            "category":"Travel",
            "subcategory":"Travel Agent",
            "type":"Entertainment"
        }
    ],
    "sg:phone":"+1 973 471 5588",
    "sg:postcode":"07055",
    "sg:province":"NJ",
    "sg:tags":[
        "agency"
    ],
    "wof:name":"NM Travel Agency Inc",
    "wof:placetype":"venue"
},
  "geometry": {"coordinates":[-74.135181,40.862429],"type":"Point"}
}