{
  "type": "Feature",
  "properties": {
    "iso:country":"US",
    "sg:address":"913 State Rte 23",
    "sg:city":"Pompton Plains",
    "sg:classifiers":[
        {
            "category":"Home & Garden",
            "subcategory":"Home Furnishings",
            "type":"Retail Goods"
        }
    ],
    "sg:phone":"+1 973 839 9333",
    "sg:postcode":"07444",
    "sg:province":"NJ",
    "sg:tags":[
        "lighting",
        "fixture"
    ],
    "wof:name":"Double Click Mall Inc",
    "wof:placetype":"venue"
},
  "geometry": {"coordinates":[-74.29789100000001,40.978262],"type":"Point"}
}