{
  "type": "Feature",
  "properties": {
    "iso:country":"US",
    "sg:address":"613 Hope Rd",
    "sg:city":"Eatontown",
    "sg:classifiers":[
        {
            "category":"Banks & Credit Unions",
            "subcategory":"Bank",
            "type":"Services"
        }
    ],
    "sg:phone":"+1 732 380 1200",
    "sg:postcode":"07724",
    "sg:province":"NJ",
    "sg:tags":[
        "loan",
        "mortgage",
        "real estate"
    ],
    "wof:name":"H & R Block Mortgage Corp",
    "wof:placetype":"venue"
},
  "geometry": {"coordinates":[-74.079016,40.289269],"type":"Point"}
}