{
  "type": "Feature",
  "properties": {
    "iso:country":"US",
    "sg:address":"282 E State Rt 4",
    "sg:city":"Paramus",
    "sg:classifiers":[
        {
            "category":"Fast Food",
            "type":"Food & Drink"
        }
    ],
    "sg:phone":"+1 201 343 4533",
    "sg:postcode":"07652",
    "sg:province":"NJ",
    "sg:tags":[
        "burger"
    ],
    "sg:website":"www.fuddruckers.com/",
    "wof:name":"Fuddruckers",
    "wof:placetype":"venue"
},
  "geometry": {"coordinates":[-74.049908,40.914758],"type":"Point"}
}