{
  "type": "Feature",
  "properties": {
    "addr:full":"86 Woodcliff Ave Woodcliff Lake NJ 07677",
    "addr:housenumber":"86",
    "addr:postcode":"07677",
    "addr:street":"Woodcliff Ave",
    "iso:country":"US",
    "sg:address":"86 Woodcliff Ave",
    "sg:city":"Woodcliff Lake",
    "sg:classifiers":[
        {
            "category":"Building & Trades",
            "subcategory":"Plumbing",
            "type":"Services"
        }
    ],
    "sg:phone":"+1 201 573 0526",
    "sg:postcode":"07677",
    "sg:province":"NJ",
    "sg:tags":[
        "contractor"
    ],
    "wof:name":"Neubauer John Htg AC Plumbling",
    "wof:placetype":"venue"
},
  "geometry": {"coordinates":[-74.05226,41.020795],"type":"Point"}
}