{
  "type": "Feature",
  "properties": {
    "iso:country":"US",
    "sg:address":"91 Bleecker St",
    "sg:city":"Jersey City",
    "sg:classifiers":[
        {
            "category":"Building & Trades",
            "subcategory":"Equipment Rental",
            "type":"Services"
        }
    ],
    "sg:phone":"+1 201 656 5091",
    "sg:postcode":"07307",
    "sg:province":"NJ",
    "wof:name":"Finmark Leasing LLC",
    "wof:placetype":"venue"
},
  "geometry": {"coordinates":[-74.05263600000001,40.751901],"type":"Point"}
}