{
  "type": "Feature",
  "properties": {
    "addr:full":"467 Sylvan Ave Englewood Cliffs NJ 07632",
    "addr:housenumber":"467",
    "addr:postcode":"07632",
    "addr:street":"Sylvan Ave",
    "iso:country":"US",
    "sg:address":"467 Sylvan Ave",
    "sg:city":"Englewood Cliffs",
    "sg:classifiers":[
        {
            "category":"Organizations",
            "subcategory":"Labor Organization",
            "type":"Services"
        }
    ],
    "sg:phone":"+1 201 567 5552",
    "sg:postcode":"07632",
    "sg:province":"NJ",
    "wof:name":"IBEW",
    "wof:placetype":"venue"
},
  "geometry": {"coordinates":[-73.95187799999999,40.878612],"type":"Point"}
}