{
  "type": "Feature",
  "properties": {
    "addr:full":"1255 State Rte 77 Bridgeton NJ 08302",
    "addr:housenumber":"1255",
    "addr:postcode":"08302",
    "addr:street":"State Rte 77",
    "iso:country":"US",
    "sg:address":"1255 State Rte 77",
    "sg:city":"Bridgeton",
    "sg:classifiers":[
        {
            "category":"Real Estate",
            "subcategory":"Real Estate Agent",
            "type":"Services"
        }
    ],
    "sg:phone":"+1 856 451 9200",
    "sg:postcode":"08302",
    "sg:province":"NJ",
    "wof:name":"Turner-Dean Real Estate Agency",
    "wof:placetype":"venue"
},
  "geometry": {"coordinates":[-75.209906,39.488331],"type":"Point"}
}