{
  "type": "Feature",
  "properties": {
    "iso:country":"US",
    "sg:address":"9 N Main St",
    "sg:city":"Cape May Ct Hse",
    "sg:classifiers":[
        {
            "category":"Professional",
            "subcategory":"Business Services",
            "type":"Services"
        }
    ],
    "sg:phone":"+1 609 463 0323",
    "sg:postcode":"08210",
    "sg:province":"NJ",
    "sg:tags":[
        "arbitration"
    ],
    "wof:name":"Cape Mediation Svc",
    "wof:placetype":"venue"
},
  "geometry": {"coordinates":[-74.82326,39.083219],"type":"Point"}
}