{
  "type": "Feature",
  "properties": {
    "addr:full":"3123 State Rte 88 Pt Pleasant Bch NJ 08742",
    "addr:housenumber":"3123",
    "addr:postcode":"08742",
    "addr:street":"State Rte 88 Pt",
    "iso:country":"US",
    "sg:address":"3123 State Rte 88",
    "sg:city":"Pt Pleasant Bch",
    "sg:classifiers":[
        {
            "category":"Retail",
            "subcategory":"Auto Rental",
            "type":"Services"
        }
    ],
    "sg:phone":"+1 732 295 0851",
    "sg:postcode":"08742",
    "sg:province":"NJ",
    "sg:tags":[
        "renting",
        "truck",
        "leasing"
    ],
    "wof:name":"Budget Truck Rental",
    "wof:placetype":"venue"
},
  "geometry": {"coordinates":[-74.084135,40.080182],"type":"Point"}
}