{
  "type": "Feature",
  "properties": {
    "addr:full":"531 US Hwy 22 E White House Station NJ 08889",
    "addr:housenumber":"531",
    "addr:postcode":"08889",
    "addr:street":"Us Hwy 22 E;Station",
    "iso:country":"US",
    "sg:address":"531 US Hwy 22 E",
    "sg:city":"White House Station",
    "sg:classifiers":[
        {
            "category":"Retail",
            "subcategory":"Photofinishing",
            "type":"Services"
        }
    ],
    "sg:phone":"+1 908 534 2455",
    "sg:postcode":"08889",
    "sg:province":"NJ",
    "wof:name":"Moto Photo",
    "wof:placetype":"venue"
},
  "geometry": {"coordinates":[-74.753877,40.618652],"type":"Point"}
}