{
  "type": "Feature",
  "properties": {
    "iso:country":"US",
    "sg:address":"29 S Maple Ave",
    "sg:city":"Marlton",
    "sg:classifiers":[
        {
            "category":"Professional",
            "subcategory":"Computer Services",
            "type":"Services"
        }
    ],
    "sg:phone":"+1   ",
    "sg:postcode":"08053",
    "sg:province":"NJ",
    "wof:name":"Hollow Fox PC",
    "wof:placetype":"venue"
},
  "geometry": {"coordinates":[-74.921995,39.888818],"type":"Point"}
}