{
  "type": "Feature",
  "properties": {
    "addr:full":"75 Throckmorton St Freehold NJ 07728",
    "addr:housenumber":"75",
    "addr:postcode":"07728",
    "addr:street":"Throckmorton St",
    "iso:country":"US",
    "sg:address":"75 Throckmorton St",
    "sg:city":"Freehold",
    "sg:classifiers":[
        {
            "category":"Organizations",
            "subcategory":"Professional Association",
            "type":"Services"
        }
    ],
    "sg:phone":"+1   ",
    "sg:postcode":"07728",
    "sg:province":"NJ",
    "sg:tags":[
        "profit",
        "trade"
    ],
    "wof:name":"Imaging Spectrum Magazine",
    "wof:placetype":"venue"
},
  "geometry": {"coordinates":[-74.278541,40.261194],"type":"Point"}
}