{
  "type": "Feature",
  "properties": {
    "addr:full":"1208 Prospect Ave Plainfield NJ 07060",
    "addr:housenumber":"1208",
    "addr:postcode":"07060",
    "addr:street":"Prospect Ave",
    "iso:country":"US",
    "sg:address":"1208 Prospect Ave",
    "sg:city":"Plainfield",
    "sg:classifiers":[
        {
            "category":"Organizations",
            "subcategory":"Religious Organization",
            "type":"Services"
        }
    ],
    "sg:phone":"+1 908 754 9486",
    "sg:postcode":"07060",
    "sg:province":"NJ",
    "sg:tags":[
        "clergy"
    ],
    "wof:name":"Leroy A Lyons Rev",
    "wof:placetype":"venue"
},
  "geometry": {"coordinates":[-74.404911,40.614302],"type":"Point"}
}