{
  "type": "Feature",
  "properties": {
    "iso:country":"US",
    "sg:address":"20 W Broad St",
    "sg:city":"Palmyra",
    "sg:classifiers":[
        {
            "category":"Government",
            "subcategory":"City Hall",
            "type":"Public Place"
        },
        {
            "category":"Government",
            "subcategory":"Office",
            "type":"Public Place"
        }
    ],
    "sg:phone":"+1 856 829 6100",
    "sg:postcode":"08065",
    "sg:province":"NJ",
    "sg:tags":[
        "town",
        "planner",
        "village",
        "township",
        "government-city"
    ],
    "sg:website":"http://www.boroughofpalmyra.com",
    "wof:name":"Palmyra Borough",
    "wof:placetype":"venue"
},
  "geometry": {"coordinates":[-75.02184800000001,40.003621],"type":"Point"}
}