{
  "type": "Feature",
  "properties": {
    "addr:full":"6858 Brown St Port Norris NJ 08349",
    "addr:housenumber":"6858",
    "addr:postcode":"08349",
    "addr:street":"Brown St",
    "iso:country":"US",
    "sg:address":"6858 Brown St",
    "sg:city":"Port Norris",
    "sg:classifiers":[
        {
            "category":"Government",
            "subcategory":"Fire Station",
            "type":"Public Place"
        }
    ],
    "sg:phone":"+1 856 785 1313",
    "sg:postcode":"08349",
    "sg:province":"NJ",
    "sg:tags":[
        "department"
    ],
    "wof:name":"Port Norris Fire Co",
    "wof:placetype":"venue"
},
  "geometry": {"coordinates":[-75.033434,39.246768],"type":"Point"}
}