{
  "type": "Feature",
  "properties": {
    "iso:country":"US",
    "sg:address":"5424 Oak St",
    "sg:city":"Mays Landing",
    "sg:classifiers":[
        {
            "category":"Building & Trades",
            "subcategory":"Construction",
            "type":"Services"
        }
    ],
    "sg:phone":"+1 609 965 7180",
    "sg:postcode":"08330",
    "sg:province":"NJ",
    "sg:tags":[
        "house"
    ],
    "wof:name":"Valcole Construction Co",
    "wof:placetype":"venue"
},
  "geometry": {"coordinates":[-74.676214,39.4842],"type":"Point"}
}