{
  "type": "Feature",
  "properties": {
    "addr:full":"464 Broadway Bayonne NJ 07002",
    "addr:housenumber":"464",
    "addr:postcode":"07002",
    "addr:street":"Broadway",
    "iso:country":"US",
    "sg:address":"464 Broadway",
    "sg:city":"Bayonne",
    "sg:classifiers":[
        {
            "category":"Shopping",
            "subcategory":"Discount & Variety Stores",
            "type":"Retail Goods"
        },
        {
            "category":"Shopping",
            "subcategory":"Hobbies, Toys, & Games",
            "type":"Retail Goods"
        }
    ],
    "sg:phone":"+1 201 437 8048",
    "sg:postcode":"07002",
    "sg:province":"NJ",
    "wof:name":"M & L Discount Store",
    "wof:placetype":"venue"
},
  "geometry": {"coordinates":[-74.119029,40.662847],"type":"Point"}
}