{
  "type": "Feature",
  "properties": {
    "addr:full":"315 Ampere Pkwy Bloomfield NJ 07003",
    "addr:housenumber":"315",
    "addr:postcode":"07003",
    "addr:street":"Ampere Pkwy",
    "iso:country":"US",
    "sg:address":"315 Ampere Pkwy",
    "sg:city":"Bloomfield",
    "sg:phone":"+1 973 429 4848",
    "sg:postcode":"07003",
    "sg:province":"NJ",
    "sg:tags":[
        "equipment",
        "oil"
    ],
    "wof:name":"Guy Oil Inc",
    "wof:placetype":"venue"
},
  "geometry": {"coordinates":[-74.189438,40.776744],"type":"Point"}
}