{
  "type": "Feature",
  "properties": {
    "addr:full":"57 Inlet Dr Pt Pleasant Beach NJ 08742",
    "addr:housenumber":"57",
    "addr:postcode":"08742",
    "addr:street":"Inlet Dr Pt Pleasant",
    "iso:country":"US",
    "sg:address":"57 Inlet Dr",
    "sg:city":"Pt Pleasant Beach",
    "sg:classifiers":[
        {
            "category":"Restaurant",
            "type":"Food & Drink"
        }
    ],
    "sg:menulink":"http://www.allmenus.com/nj/point-pleasant-beach/281888-reds-lobster-pot/menu/",
    "sg:phone":"+1 732 295 6622",
    "sg:postcode":"08742",
    "sg:province":"NJ",
    "sg:tags":[
        "seafood",
        "american"
    ],
    "wof:name":"Red's Lobster Pot",
    "wof:placetype":"venue"
},
  "geometry": {"coordinates":[-74.03820899999999,40.102695],"type":"Point"}
}