{
  "type": "Feature",
  "properties": {
    "iso:country":"US",
    "sg:address":"54 East Ave",
    "sg:city":"Woodstown",
    "sg:classifiers":[
        {
            "category":"Health Services",
            "subcategory":"Doctor",
            "type":"Services"
        }
    ],
    "sg:phone":"+1 856 769 0505",
    "sg:postcode":"08098",
    "sg:province":"NJ",
    "wof:name":"Steven R Scheule DDS",
    "wof:placetype":"venue"
},
  "geometry": {"coordinates":[-75.325695,39.651379],"type":"Point"}
}