{
  "type": "Feature",
  "properties": {
    "addr:full":"27 Hamlin Rd East Brunswick NJ 08816",
    "addr:housenumber":"27",
    "addr:postcode":"08816",
    "addr:street":"Hamlin Rd",
    "iso:country":"US",
    "sg:address":"27 Hamlin Rd",
    "sg:city":"East Brunswick",
    "sg:classifiers":[
        {
            "category":"Social Services",
            "subcategory":"Child Care",
            "type":"Services"
        }
    ],
    "sg:phone":"+1   ",
    "sg:postcode":"08816",
    "sg:province":"NJ",
    "sg:tags":[
        "day"
    ],
    "wof:name":"Glove Miff Inc",
    "wof:placetype":"venue"
},
  "geometry": {"coordinates":[-74.420069,40.464056],"type":"Point"}
}