{
  "type": "Feature",
  "properties": {
    "iso:country":"US",
    "sg:address":"5 Windymere Ln",
    "sg:city":"Mendham",
    "sg:classifiers":[
        {
            "category":"Professional",
            "subcategory":"Business Services",
            "type":"Services"
        }
    ],
    "sg:phone":"+1   ",
    "sg:postcode":"07945",
    "sg:province":"NJ",
    "wof:name":"Town & Country Interiors",
    "wof:placetype":"venue"
},
  "geometry": {"coordinates":[-74.595247,40.771929],"type":"Point"}
}