{
  "type": "Feature",
  "properties": {
    "addr:full":"892 18th Ave Irvington NJ 07111",
    "addr:housenumber":"892",
    "addr:postcode":"07111",
    "addr:street":"18Th Ave",
    "iso:country":"US",
    "sg:address":"892 18th Ave",
    "sg:city":"Irvington",
    "sg:classifiers":[
        {
            "category":"Shopping",
            "subcategory":"Discount & Variety Stores",
            "type":"Retail Goods"
        }
    ],
    "sg:phone":"+1 973 374 7528",
    "sg:postcode":"07111",
    "sg:province":"NJ",
    "sg:tags":[
        "merchandise",
        "general"
    ],
    "wof:name":"Pine Discount Store",
    "wof:placetype":"venue"
},
  "geometry": {"coordinates":[-74.22353099999999,40.738004],"type":"Point"}
}