{
  "type": "Feature",
  "properties": {
    "addr:full":"2 Randolph Ave Randolph NJ 07869",
    "addr:housenumber":"2",
    "addr:postcode":"07869",
    "addr:street":"Randolph Ave",
    "iso:country":"US",
    "sg:address":"2 Randolph Ave",
    "sg:city":"Randolph",
    "sg:classifiers":[
        {
            "category":"Real Estate",
            "subcategory":"Real Estate Agent",
            "type":"Services"
        }
    ],
    "sg:phone":"+1   ",
    "sg:postcode":"07869",
    "sg:province":"NJ",
    "wof:name":"Marketing Enterprises",
    "wof:placetype":"venue"
},
  "geometry": {"coordinates":[-74.586726,40.866908],"type":"Point"}
}