{
  "type": "Feature",
  "properties": {
    "addr:full":"25 W Pleasant Ave Maywood NJ 07607",
    "addr:housenumber":"25",
    "addr:postcode":"07607",
    "addr:street":"W Pleasant Ave",
    "iso:country":"US",
    "sg:address":"25 W Pleasant Ave",
    "sg:city":"Maywood",
    "sg:classifiers":[
        {
            "category":"Banks & Credit Unions",
            "subcategory":"Bank",
            "type":"Services"
        }
    ],
    "sg:phone":"+1 201 843 5530",
    "sg:postcode":"07607",
    "sg:province":"NJ",
    "sg:tags":[
        "state",
        "commercial"
    ],
    "wof:name":"Hudson United Bank",
    "wof:placetype":"venue"
},
  "geometry": {"coordinates":[-74.06199599999999,40.903999],"type":"Point"}
}