{
  "type": "Feature",
  "properties": {
    "addr:full":"555 High St Mount Holly NJ 08060",
    "addr:housenumber":"555",
    "addr:postcode":"08060",
    "addr:street":"High St",
    "iso:country":"US",
    "sg:address":"555 High St",
    "sg:city":"Mount Holly",
    "sg:classifiers":[
        {
            "category":"Ice Cream",
            "type":"Food & Drink"
        }
    ],
    "sg:menulink":"http://www.allmenus.com/nj/mount-holly/99235-friendlys/menu/",
    "sg:phone":"+1 609 518 1904",
    "sg:postcode":"08060",
    "sg:province":"NJ",
    "sg:tags":[
        "burger",
        "american"
    ],
    "wof:name":"Friendly's",
    "wof:placetype":"venue"
},
  "geometry": {"coordinates":[-74.795081,40.005401],"type":"Point"}
}