{
  "type": "Feature",
  "properties": {
    "addr:full":"539 Piermont Ave Hillsdale NJ 07642",
    "addr:housenumber":"539",
    "addr:postcode":"07642",
    "addr:street":"Piermont Ave",
    "iso:country":"US",
    "sg:address":"539 Piermont Ave",
    "sg:city":"Hillsdale",
    "sg:classifiers":[
        {
            "category":"Autos & Motor Vehicles",
            "subcategory":"Automobile Sales",
            "type":"Retail Goods"
        }
    ],
    "sg:phone":"+1 201 666 7909",
    "sg:postcode":"07642",
    "sg:province":"NJ",
    "sg:tags":[
        "car",
        "dealer"
    ],
    "wof:name":"Eurocars Inc",
    "wof:placetype":"venue"
},
  "geometry": {"coordinates":[-74.044284,41.006015],"type":"Point"}
}