{
  "type": "Feature",
  "properties": {
    "iso:country":"US",
    "sg:address":"333 S Egg Harbor Rd",
    "sg:city":"Hammonton",
    "sg:classifiers":[
        {
            "category":"Restaurant",
            "type":"Food & Drink"
        }
    ],
    "sg:phone":"+1 609 704 0766",
    "sg:postcode":"08037",
    "sg:province":"NJ",
    "sg:tags":[
        "delicatessen"
    ],
    "wof:name":"Hammonton Deli & Grocery",
    "wof:placetype":"venue"
},
  "geometry": {"coordinates":[-74.868533,39.671386],"type":"Point"}
}