{
  "type": "Feature",
  "properties": {
    "addr:full":"705 N Lenola Rd Moorestown NJ 08057",
    "addr:housenumber":"705",
    "addr:postcode":"08057",
    "addr:street":"N Lenola Rd",
    "iso:country":"US",
    "sg:address":"705 N Lenola Rd",
    "sg:city":"Moorestown",
    "sg:classifiers":[
        {
            "category":"Building & Trades",
            "subcategory":"Construction",
            "type":"Services"
        }
    ],
    "sg:phone":"+1 856 235 4538",
    "sg:postcode":"08057",
    "sg:province":"NJ",
    "sg:tags":[
        "contractor"
    ],
    "wof:name":"R Zell General Contractor",
    "wof:placetype":"venue"
},
  "geometry": {"coordinates":[-74.983575,39.963643],"type":"Point"}
}