{
  "type": "Feature",
  "properties": {
    "addr:full":"160 Summit Ave Montvale NJ 07645",
    "addr:housenumber":"160",
    "addr:postcode":"07645",
    "addr:street":"Summit Ave",
    "iso:country":"US",
    "sg:address":"160 Summit Ave",
    "sg:city":"Montvale",
    "sg:classifiers":[
        {
            "category":"Wholesale",
            "subcategory":"Medical Equipment & Supplies",
            "type":"Manufacturing & Wholesale Goods"
        },
        {
            "category":"Shopping",
            "subcategory":"Pharmacy",
            "type":"Retail Goods"
        }
    ],
    "sg:phone":"+1 201 391 6000",
    "sg:postcode":"07645",
    "sg:province":"NJ",
    "sg:tags":[
        "pharmaceutical",
        "medicines-patent",
        "proprietary",
        "products-wholesale",
        "manufacturer"
    ],
    "sg:website":"http://www.dkidirect.com",
    "wof:name":"Daniella Koren Inc.",
    "wof:placetype":"venue"
},
  "geometry": {"coordinates":[-74.063187,41.058609],"type":"Point"}
}