{
  "type": "Feature",
  "properties": {
    "iso:country":"US",
    "sg:address":"667 Paxson Ave",
    "sg:city":"Trenton",
    "sg:classifiers":[
        {
            "category":"Professional",
            "subcategory":"Management & Consulting",
            "type":"Services"
        }
    ],
    "sg:phone":"+1 609 890 8871",
    "sg:postcode":"08619",
    "sg:province":"NJ",
    "sg:tags":[
        "business"
    ],
    "wof:name":"Taylor Consulting Group LLC",
    "wof:placetype":"venue"
},
  "geometry": {"coordinates":[-74.66870900000001,40.257558],"type":"Point"}
}