{
  "type": "Feature",
  "properties": {
    "addr:full":"1026 Main St Paterson NJ 07503",
    "addr:housenumber":"1026",
    "addr:postcode":"07503",
    "addr:street":"Main St",
    "iso:country":"US",
    "sg:address":"1026 Main St",
    "sg:city":"Paterson",
    "sg:classifiers":[
        {
            "category":"Food & Beverages",
            "subcategory":"Meat & Fish",
            "type":"Retail Goods"
        }
    ],
    "sg:phone":"+1   ",
    "sg:postcode":"07503",
    "sg:province":"NJ",
    "wof:name":"Halal Meat Market",
    "wof:placetype":"venue"
},
  "geometry": {"coordinates":[-74.15741199999999,40.892497],"type":"Point"}
}