{
  "type": "Feature",
  "properties": {
    "iso:country":"US",
    "sg:address":"63 York St",
    "sg:city":"Old Bridge",
    "sg:classifiers":[
        {
            "category":"Building & Trades",
            "subcategory":"Construction",
            "type":"Services"
        }
    ],
    "sg:phone":"+1 732 679 8958",
    "sg:postcode":"08857",
    "sg:province":"NJ",
    "sg:tags":[
        "house"
    ],
    "wof:name":"G & G & Sons Construction",
    "wof:placetype":"venue"
},
  "geometry": {"coordinates":[-74.334526,40.397948],"type":"Point"}
}