{
  "type": "Feature",
  "properties": {
    "iso:country":"US",
    "sg:address":"107 Douglas Dr",
    "sg:city":"Westwood",
    "sg:classifiers":[
        {
            "category":"Wholesale",
            "subcategory":"Medical Equipment & Supplies",
            "type":"Manufacturing & Wholesale Goods"
        }
    ],
    "sg:phone":"+1 201 670 4719",
    "sg:postcode":"07676",
    "sg:province":"NJ",
    "sg:tags":[
        "dental"
    ],
    "wof:name":"Eastern Medical Systems Inc",
    "wof:placetype":"venue"
},
  "geometry": {"coordinates":[-74.074172,40.985487],"type":"Point"}
}