{
  "type": "Feature",
  "properties": {
    "iso:country":"US",
    "sg:address":"110 W 6th St",
    "sg:city":"Ocean City",
    "sg:classifiers":[
        {
            "category":"Restaurant",
            "type":"Food & Drink"
        }
    ],
    "sg:phone":"+1 609 391 7800",
    "sg:postcode":"08226",
    "sg:province":"NJ",
    "sg:tags":[
        "parlor",
        "ice",
        "cream"
    ],
    "wof:name":"Anthony's Wholesale & Festival",
    "wof:placetype":"venue"
},
  "geometry": {"coordinates":[-74.57590999999999,39.284987],"type":"Point"}
}