{
  "type": "Feature",
  "properties": {
    "addr:full":"409 Straight St Paterson NJ 07501",
    "addr:housenumber":"409",
    "addr:postcode":"07501",
    "addr:street":"Straight St",
    "iso:country":"US",
    "sg:address":"409 Straight St",
    "sg:city":"Paterson",
    "sg:classifiers":[
        {
            "category":"Food & Beverages",
            "subcategory":"Groceries & Convenience Stores",
            "type":"Retail Goods"
        }
    ],
    "sg:phone":"+1 973 279 0224",
    "sg:postcode":"07501",
    "sg:province":"NJ",
    "wof:name":"Fernandez Food Market",
    "wof:placetype":"venue"
},
  "geometry": {"coordinates":[-74.166158,40.910228],"type":"Point"}
}