{
  "type": "Feature",
  "properties": {
    "iso:country":"US",
    "sg:address":"415 Elmwood Ter",
    "sg:city":"Linden",
    "sg:classifiers":[
        {
            "category":"Wholesale",
            "subcategory":"Durable Goods & Equipment",
            "type":"Manufacturing & Wholesale Goods"
        }
    ],
    "sg:phone":"+1 609 294 3500",
    "sg:postcode":"07036",
    "sg:province":"NJ",
    "sg:tags":[
        "representative",
        "manufacturer"
    ],
    "wof:name":"H White Sales Co",
    "wof:placetype":"venue"
},
  "geometry": {"coordinates":[-74.279028,40.636684],"type":"Point"}
}