{
  "type": "Feature",
  "properties": {
    "iso:country":"US",
    "sg:address":"76 S Orange Ave",
    "sg:city":"South Orange",
    "sg:classifiers":[
        {
            "category":"Insurance",
            "subcategory":"Insurance Agent",
            "type":"Services"
        }
    ],
    "sg:phone":"+1 973 763 2640",
    "sg:postcode":"07079",
    "sg:province":"NJ",
    "wof:name":"Frasco Albert J Agency",
    "wof:placetype":"venue"
},
  "geometry": {"coordinates":[-74.25766900000001,40.745587],"type":"Point"}
}