{
  "type": "Feature",
  "properties": {
    "addr:full":"709 Harrison Ave Harrison NJ 07029",
    "addr:housenumber":"709",
    "addr:postcode":"07029",
    "addr:street":"Harrison Ave",
    "iso:country":"US",
    "sg:address":"709 Harrison Ave",
    "sg:city":"Harrison",
    "sg:classifiers":[
        {
            "category":"Building & Trades",
            "subcategory":"Construction",
            "type":"Services"
        }
    ],
    "sg:phone":"+1 732 340 0700",
    "sg:postcode":"07029",
    "sg:province":"NJ",
    "sg:tags":[
        "contractor"
    ],
    "wof:name":"Tak Construction Inc",
    "wof:placetype":"venue"
},
  "geometry": {"coordinates":[-74.146748,40.747935],"type":"Point"}
}