{
  "type": "Feature",
  "properties": {
    "iso:country":"US",
    "sg:address":"358 State Rt 3 W",
    "sg:city":"Clifton",
    "sg:classifiers":[
        {
            "category":"Travel",
            "subcategory":"Travel Agent",
            "type":"Entertainment"
        },
        {
            "category":"Marine",
            "type":"Transportation"
        }
    ],
    "sg:phone":"+1 888 909 3500",
    "sg:postcode":"07014",
    "sg:province":"NJ",
    "sg:tags":[
        "agency",
        "services-commercial",
        "steamship"
    ],
    "sg:website":"http://www.libertytravel.com",
    "wof:name":"Liberty Travel",
    "wof:placetype":"venue"
},
  "geometry": {"coordinates":[-74.138919,40.83011],"type":"Point"}
}