{
  "type": "Feature",
  "properties": {
    "iso:country":"US",
    "sg:address":"67 State Rte 37",
    "sg:city":"Toms River",
    "sg:classifiers":[
        {
            "category":"Health Services",
            "subcategory":"Clinic",
            "type":"Services"
        }
    ],
    "sg:phone":"+1   ",
    "sg:postcode":"08755",
    "sg:province":"NJ",
    "sg:tags":[
        "company",
        "holding"
    ],
    "wof:name":"Center State Health Svcs Corp",
    "wof:placetype":"venue"
},
  "geometry": {"coordinates":[-74.212081,39.9647],"type":"Point"}
}