{
  "type": "Feature",
  "properties": {
    "addr:full":"1692 State Rte 88 Brick NJ 08724",
    "addr:housenumber":"1692",
    "addr:postcode":"08724",
    "addr:street":"State Rte 88",
    "iso:country":"US",
    "sg:address":"1692 State Rte 88",
    "sg:city":"Brick",
    "sg:classifiers":[
        {
            "category":"Freight",
            "type":"Transportation"
        }
    ],
    "sg:phone":"+1 732 202 0889",
    "sg:postcode":"08724",
    "sg:province":"NJ",
    "sg:tags":[
        "operator",
        "trucking"
    ],
    "wof:name":"Sst Logistics",
    "wof:placetype":"venue"
},
  "geometry": {"coordinates":[-74.13312999999999,40.072503],"type":"Point"}
}