{
  "type": "Feature",
  "properties": {
    "addr:full":"435 Somerville Rd Bridgewater NJ 08807",
    "addr:housenumber":"435",
    "addr:postcode":"08807",
    "addr:street":"Somerville Rd",
    "iso:country":"US",
    "sg:address":"435 Somerville Rd",
    "sg:city":"Bridgewater",
    "sg:classifiers":[
        {
            "category":"Building & Trades",
            "subcategory":"Construction",
            "type":"Services"
        }
    ],
    "sg:phone":"+1 908 722 2908",
    "sg:postcode":"08807",
    "sg:province":"NJ",
    "sg:tags":[
        "house"
    ],
    "wof:name":"Wilmark Bldg Contrs",
    "wof:placetype":"venue"
},
  "geometry": {"coordinates":[-74.597628,40.582637],"type":"Point"}
}