{
  "type": "Feature",
  "properties": {
    "addr:full":"365 Livingston St Norwood NJ 07648",
    "addr:housenumber":"365",
    "addr:postcode":"07648",
    "addr:street":"Livingston St",
    "iso:country":"US",
    "sg:address":"365 Livingston St",
    "sg:city":"Norwood",
    "sg:classifiers":[
        {
            "category":"Building & Trades",
            "subcategory":"Construction",
            "type":"Services"
        }
    ],
    "sg:phone":"+1 201 767 8841",
    "sg:postcode":"07648",
    "sg:province":"NJ",
    "sg:tags":[
        "carpentry",
        "contractor"
    ],
    "wof:name":"Sjg Carpentry",
    "wof:placetype":"venue"
},
  "geometry": {"coordinates":[-73.95655499999999,40.994701],"type":"Point"}
}