{
  "type": "Feature",
  "properties": {
    "addr:full":"438 Raritan Ave Highland Park NJ 08904",
    "addr:housenumber":"438",
    "addr:postcode":"08904",
    "addr:street":"Raritan Ave",
    "iso:country":"US",
    "sg:address":"438 Raritan Ave",
    "sg:city":"Highland Park",
    "sg:phone":"+1 732 846 9111",
    "sg:postcode":"08904",
    "sg:province":"NJ",
    "sg:tags":[
        "equipment",
        "supply"
    ],
    "wof:name":"Brunswick Supply Co Inc",
    "wof:placetype":"venue"
},
  "geometry": {"coordinates":[-74.424812,40.500124],"type":"Point"}
}