{
  "type": "Feature",
  "properties": {
    "addr:full":"3 Bucky Ln Vernon NJ 07462",
    "addr:housenumber":"3",
    "addr:postcode":"07462",
    "addr:street":"Bucky Ln",
    "iso:country":"US",
    "sg:address":"3 Bucky Ln",
    "sg:city":"Vernon",
    "sg:classifiers":[
        {
            "category":"Professional",
            "subcategory":"Secretarial Services",
            "type":"Services"
        }
    ],
    "sg:phone":"+1   ",
    "sg:postcode":"07462",
    "sg:province":"NJ",
    "sg:tags":[
        "reporting"
    ],
    "wof:name":"Star Transcription",
    "wof:placetype":"venue"
},
  "geometry": {"coordinates":[-74.461265,41.231206],"type":"Point"}
}