{
  "type": "Feature",
  "properties": {
    "addr:full":"757 N Broad St Elizabeth NJ 07208",
    "addr:housenumber":"757",
    "addr:postcode":"07208",
    "addr:street":"N Broad St",
    "iso:country":"US",
    "sg:address":"757 N Broad St",
    "sg:city":"Elizabeth",
    "sg:classifiers":[
        {
            "category":"Health Services",
            "subcategory":"Doctor",
            "type":"Services"
        }
    ],
    "sg:phone":"+1 908 352 7730",
    "sg:postcode":"07208",
    "sg:province":"NJ",
    "wof:name":"Elvira Delatorre DDS",
    "wof:placetype":"venue"
},
  "geometry": {"coordinates":[-74.213823,40.680756],"type":"Point"}
}