{
  "type": "Feature",
  "properties": {
    "iso:country":"US",
    "sg:address":"5 N Bayard Ln",
    "sg:city":"Mahwah",
    "sg:classifiers":[
        {
            "category":"Professional",
            "subcategory":"Computer Services",
            "type":"Services"
        }
    ],
    "sg:phone":"+1 201 327 8400",
    "sg:postcode":"07430",
    "sg:province":"NJ",
    "sg:tags":[
        "life",
        "co",
        "consultant",
        "agent",
        "insurance",
        "lease"
    ],
    "wof:name":"Assured Solutions Technologies",
    "wof:placetype":"venue"
},
  "geometry": {"coordinates":[-74.13221799999999,41.082553],"type":"Point"}
}