{
  "type": "Feature",
  "properties": {
    "addr:full":"5800 Bergenline Ave West New York NJ 07093",
    "addr:housenumber":"5800",
    "addr:postcode":"07093",
    "addr:street":"Bergenline Ave West",
    "iso:country":"US",
    "sg:address":"5800 Bergenline Ave",
    "sg:city":"West New York",
    "sg:classifiers":[
        {
            "category":"Shopping",
            "subcategory":"Clothing, Apparel, & Fashions",
            "type":"Retail Goods"
        }
    ],
    "sg:phone":"+1 201 662 7953",
    "sg:postcode":"07093",
    "sg:province":"NJ",
    "sg:tags":[
        "accessory",
        "clothing",
        "women's"
    ],
    "wof:name":"Ten Spot Plus",
    "wof:placetype":"venue"
},
  "geometry": {"coordinates":[-74.01709700000001,40.787701],"type":"Point"}
}