{
  "type": "Feature",
  "properties": {
    "iso:country":"US",
    "sg:address":"15 E Centre St",
    "sg:city":"Deptford",
    "sg:classifiers":[
        {
            "category":"Professional",
            "subcategory":"Credit Reporting & Collection",
            "type":"Services"
        }
    ],
    "sg:phone":"+1 856 845 0202",
    "sg:postcode":"08096",
    "sg:province":"NJ",
    "sg:tags":[
        "agency"
    ],
    "wof:name":"Asset Acceptance LLC",
    "wof:placetype":"venue"
},
  "geometry": {"coordinates":[-75.15114199999999,39.835448],"type":"Point"}
}