{
  "type": "Feature",
  "properties": {
    "iso:country":"US",
    "sg:address":"840 Kearny Ave",
    "sg:city":"Kearny",
    "sg:classifiers":[
        {
            "category":"Real Estate",
            "subcategory":"Real Estate Agent",
            "type":"Services"
        }
    ],
    "sg:phone":"+1   ",
    "sg:postcode":"07032",
    "sg:province":"NJ",
    "wof:name":"Realty Executives",
    "wof:placetype":"venue"
},
  "geometry": {"coordinates":[-74.139126,40.780877],"type":"Point"}
}