{
  "type": "Feature",
  "properties": {
    "addr:full":"1 Enterprise Ave N Secaucus NJ 07094",
    "addr:housenumber":"1",
    "addr:postcode":"07094",
    "addr:street":"Enterprise Ave N",
    "iso:country":"US",
    "sg:address":"1 Enterprise Ave N",
    "sg:city":"Secaucus",
    "sg:classifiers":[
        {
            "category":"Building & Trades",
            "subcategory":"Locksmith",
            "type":"Services"
        }
    ],
    "sg:phone":"+1 201 297 0640",
    "sg:postcode":"07094",
    "sg:province":"NJ",
    "sg:tags":[
        "key"
    ],
    "wof:name":"0 24 Hour 7 Day Emerg Locksmith",
    "wof:placetype":"venue"
},
  "geometry": {"coordinates":[-74.06670099999999,40.788542],"type":"Point"}
}