{
  "type": "Feature",
  "properties": {
    "iso:country":"US",
    "sg:address":"720 Monroe St",
    "sg:city":"Hoboken",
    "sg:classifiers":[
        {
            "category":"Arts & Performance",
            "subcategory":"Theater",
            "type":"Entertainment"
        }
    ],
    "sg:phone":"+1 201 239 9912",
    "sg:postcode":"07030",
    "sg:province":"NJ",
    "sg:tags":[
        "group"
    ],
    "wof:name":"Tape Kingz Inc",
    "wof:placetype":"venue"
},
  "geometry": {"coordinates":[-74.037616,40.747344],"type":"Point"}
}