{
  "type": "Feature",
  "properties": {
    "iso:country":"US",
    "sg:address":"1139 Wesley Ave",
    "sg:city":"Ocean City",
    "sg:classifiers":[
        {
            "category":"Museum",
            "type":"Entertainment"
        }
    ],
    "sg:phone":"+1   ",
    "sg:postcode":"08226",
    "sg:province":"NJ",
    "sg:tags":[
        "gallery"
    ],
    "wof:name":"Ocean City Historical Museum",
    "wof:placetype":"venue"
},
  "geometry": {"coordinates":[-74.578704,39.274783],"type":"Point"}
}