{
  "type": "Feature",
  "properties": {
    "addr:full":"65 Grove Ave Verona NJ 07044",
    "addr:housenumber":"65",
    "addr:postcode":"07044",
    "addr:street":"Grove Ave",
    "iso:country":"US",
    "sg:address":"65 Grove Ave",
    "sg:city":"Verona",
    "sg:classifiers":[
        {
            "category":"Building & Trades",
            "subcategory":"Construction",
            "type":"Services"
        }
    ],
    "sg:phone":"+1 973 571 0077",
    "sg:postcode":"07044",
    "sg:province":"NJ",
    "sg:tags":[
        "bathroom",
        "remodeling"
    ],
    "wof:name":"Premier Refinishing Inc",
    "wof:placetype":"venue"
},
  "geometry": {"coordinates":[-74.24556800000001,40.836667],"type":"Point"}
}