{
  "type": "Feature",
  "properties": {
    "addr:full":"200 9th Ave Belmar NJ 07719",
    "addr:housenumber":"200",
    "addr:postcode":"07719",
    "addr:street":"9Th Ave",
    "iso:country":"US",
    "sg:address":"200 9th Ave",
    "sg:city":"Belmar",
    "sg:classifiers":[
        {
            "category":"Travel",
            "subcategory":"Hotels & Motels",
            "type":"Entertainment"
        }
    ],
    "sg:phone":"+1 732 681 1388",
    "sg:postcode":"07719",
    "sg:province":"NJ",
    "sg:tags":[
        "operation"
    ],
    "wof:name":"Shannon Inn",
    "wof:placetype":"venue"
},
  "geometry": {"coordinates":[-74.01747899999999,40.178725],"type":"Point"}
}