{
  "type": "Feature",
  "properties": {
    "addr:full":"2553 S 8th St Camden NJ 08104",
    "addr:housenumber":"2553",
    "addr:postcode":"08104",
    "addr:street":"S 8Th St",
    "iso:country":"US",
    "sg:address":"2553 S 8th St",
    "sg:city":"Camden",
    "sg:classifiers":[
        {
            "category":"Real Estate",
            "subcategory":"Real Estate Operator",
            "type":"Services"
        }
    ],
    "sg:phone":"+1 856 541 6424",
    "sg:postcode":"08104",
    "sg:province":"NJ",
    "sg:tags":[
        "apartment"
    ],
    "wof:name":"Crestbury Apartments",
    "wof:placetype":"venue"
},
  "geometry": {"coordinates":[-75.112297,39.9119],"type":"Point"}
}