{
  "type": "Feature",
  "properties": {
    "addr:full":"50 Mount Bethel Rd Warren NJ 07059",
    "addr:housenumber":"50",
    "addr:postcode":"07059",
    "addr:street":"Mount Bethel Rd",
    "iso:country":"US",
    "sg:address":"50 Mount Bethel Rd",
    "sg:city":"Warren",
    "sg:classifiers":[
        {
            "category":"Retail",
            "subcategory":"Portrait Studio",
            "type":"Services"
        }
    ],
    "sg:phone":"+1 908 226 0160",
    "sg:postcode":"07059",
    "sg:province":"NJ",
    "sg:tags":[
        "photography"
    ],
    "sg:website":"www.ldbright.com",
    "wof:name":"L D Bright Photography",
    "wof:placetype":"venue"
},
  "geometry": {"coordinates":[-74.496391,40.620521],"type":"Point"}
}