{
  "type": "Feature",
  "properties": {
    "iso:country":"US",
    "sg:address":"901 Heidelberg Ave",
    "sg:city":"Egg Harbor City",
    "sg:classifiers":[
        {
            "category":"Retail",
            "subcategory":"Repair Shop",
            "type":"Services"
        }
    ],
    "sg:phone":"+1   ",
    "sg:postcode":"08215",
    "sg:province":"NJ",
    "wof:name":"Key Way Loksmith Services LLC",
    "wof:placetype":"venue"
},
  "geometry": {"coordinates":[-74.652766,39.545395],"type":"Point"}
}