{
  "type": "Feature",
  "properties": {
    "addr:full":"58 Sunrise Ter Cedar Grove NJ 07009",
    "addr:housenumber":"58",
    "addr:postcode":"07009",
    "addr:street":"Sunrise Ter",
    "iso:country":"US",
    "sg:address":"58 Sunrise Ter",
    "sg:city":"Cedar Grove",
    "sg:classifiers":[
        {
            "category":"Health Services",
            "subcategory":"Doctor",
            "type":"Services"
        }
    ],
    "sg:phone":"+1 973 433 4244",
    "sg:postcode":"07009",
    "sg:province":"NJ",
    "wof:name":"George Younan Inc",
    "wof:placetype":"venue"
},
  "geometry": {"coordinates":[-74.234821,40.855308],"type":"Point"}
}