{
  "type": "Feature",
  "properties": {
    "iso:country":"US",
    "sg:address":"512 Anderson Ave",
    "sg:city":"Cliffside Park",
    "sg:classifiers":[
        {
            "category":"Bars & Pubs",
            "type":"Food & Drink"
        }
    ],
    "sg:phone":"+1   ",
    "sg:postcode":"07010",
    "sg:province":"NJ",
    "sg:tags":[
        "tavern"
    ],
    "wof:name":"Papa Bears",
    "wof:placetype":"venue"
},
  "geometry": {"coordinates":[-73.990219,40.821924],"type":"Point"}
}