{
  "type": "Feature",
  "properties": {
    "iso:country":"US",
    "sg:address":"5600 State Rte 42",
    "sg:city":"Blackwood",
    "sg:classifiers":[
        {
            "category":"Personal",
            "subcategory":"Beauty Salon",
            "type":"Services"
        }
    ],
    "sg:phone":"+1 856 374 1467",
    "sg:postcode":"08012",
    "sg:province":"NJ",
    "sg:tags":[
        "shop"
    ],
    "wof:name":"N J Nails",
    "wof:placetype":"venue"
},
  "geometry": {"coordinates":[-75.047196,39.758218],"type":"Point"}
}