{
  "type": "Feature",
  "properties": {
    "addr:full":"155 Polifly Rd Hackensack NJ 07601",
    "addr:housenumber":"155",
    "addr:postcode":"07601",
    "addr:street":"Polifly Rd",
    "iso:country":"US",
    "sg:address":"155 Polifly Rd",
    "sg:city":"Hackensack",
    "sg:classifiers":[
        {
            "category":"Health Services",
            "subcategory":"Doctor",
            "type":"Services"
        }
    ],
    "sg:phone":"+1 201 487 7617",
    "sg:postcode":"07601",
    "sg:province":"NJ",
    "sg:tags":[
        "physician",
        "surgeon"
    ],
    "sg:website":"www.pediatric-heartdisease.com",
    "wof:name":"Pediatric Center-Heart Disease",
    "wof:placetype":"venue"
},
  "geometry": {"coordinates":[-74.05839400000001,40.876841],"type":"Point"}
}