{
  "type": "Feature",
  "properties": {
    "addr:full":"1591 E 2nd St Scotch Plains NJ 07076",
    "addr:housenumber":"1591",
    "addr:postcode":"07076",
    "addr:street":"E 2Nd St",
    "iso:country":"US",
    "sg:address":"1591 E 2nd St",
    "sg:city":"Scotch Plains",
    "sg:classifiers":[
        {
            "category":"Personal",
            "subcategory":"Beauty Salon",
            "type":"Services"
        }
    ],
    "sg:phone":"+1 908 322 0009",
    "sg:postcode":"07076",
    "sg:province":"NJ",
    "sg:tags":[
        "shop"
    ],
    "wof:name":"Livay Nail Spa Inc",
    "wof:placetype":"venue"
},
  "geometry": {"coordinates":[-74.401578,40.643747],"type":"Point"}
}