{
  "type": "Feature",
  "properties": {
    "iso:country":"US",
    "sg:address":"634 Spring Ave",
    "sg:city":"Ridgewood",
    "sg:classifiers":[
        {
            "category":"Professional",
            "subcategory":"Business Services",
            "type":"Services"
        }
    ],
    "sg:phone":"+1   ",
    "sg:postcode":"07450",
    "sg:province":"NJ",
    "wof:name":"Sls Solutions LLC",
    "wof:placetype":"venue"
},
  "geometry": {"coordinates":[-74.098382,40.971667],"type":"Point"}
}