{
  "type": "Feature",
  "properties": {
    "addr:full":"208 N Main St Hightstown NJ 08520",
    "addr:housenumber":"208",
    "addr:postcode":"08520",
    "addr:street":"N Main St",
    "iso:country":"US",
    "sg:address":"208 N Main St",
    "sg:city":"Hightstown",
    "sg:classifiers":[
        {
            "category":"Shopping",
            "subcategory":"Clothing, Apparel, & Fashions",
            "type":"Retail Goods"
        },
        {
            "category":"Manufacturing",
            "subcategory":"Leather Goods",
            "type":"Manufacturing & Wholesale Goods"
        }
    ],
    "sg:phone":"+1 609 443 6886",
    "sg:postcode":"08520",
    "sg:province":"NJ",
    "sg:tags":[
        "clothing",
        "sale",
        "alterations-clothing",
        "tailor",
        "wear",
        "manufacturer",
        "rental",
        "formal"
    ],
    "sg:website":"http://tailoringunlimited.com",
    "wof:name":"Tailoring Unlimited",
    "wof:placetype":"venue"
},
  "geometry": {"coordinates":[-74.568245,40.248592],"type":"Point"}
}