{
  "type": "Feature",
  "properties": {
    "addr:full":"28 Evergreen Rd Summit NJ 07901",
    "addr:housenumber":"28",
    "addr:postcode":"07901",
    "addr:street":"Evergreen Rd",
    "iso:country":"US",
    "sg:address":"28 Evergreen Rd",
    "sg:city":"Summit",
    "sg:classifiers":[
        {
            "category":"Building & Trades",
            "subcategory":"Construction",
            "type":"Services"
        }
    ],
    "sg:phone":"+1 908 277 3557",
    "sg:postcode":"07901",
    "sg:province":"NJ",
    "sg:tags":[
        "house"
    ],
    "wof:name":"Sdk Building Contrators",
    "wof:placetype":"venue"
},
  "geometry": {"coordinates":[-74.37833500000001,40.722345],"type":"Point"}
}