{
  "type": "Feature",
  "properties": {
    "iso:country":"US",
    "sg:address":"9 Anderson St",
    "sg:city":"Morristown",
    "sg:classifiers":[
        {
            "category":"Professional",
            "subcategory":"Business Services",
            "type":"Services"
        },
        {
            "category":"Building & Trades",
            "subcategory":"Construction",
            "type":"Services"
        }
    ],
    "sg:phone":"+1 973 455 7440",
    "sg:postcode":"07960",
    "sg:province":"NJ",
    "sg:tags":[
        "resurfacing",
        "laying",
        "refinishing",
        "floor"
    ],
    "wof:name":"Jet Floors",
    "wof:placetype":"venue"
},
  "geometry": {"coordinates":[-74.479527,40.811055],"type":"Point"}
}