{
  "type": "Feature",
  "properties": {
    "addr:full":"41 Tuers Ave Jersey City NJ 07306",
    "addr:housenumber":"41",
    "addr:postcode":"07306",
    "addr:street":"Tuers Ave",
    "iso:country":"US",
    "sg:address":"41 Tuers Ave",
    "sg:city":"Jersey City",
    "sg:classifiers":[
        {
            "category":"Education",
            "subcategory":"School",
            "type":"Public Place"
        }
    ],
    "sg:phone":"+1 201 435 6528",
    "sg:postcode":"07306",
    "sg:province":"NJ",
    "sg:tags":[
        "religious",
        "secondary"
    ],
    "wof:name":"St Aedan's School",
    "wof:placetype":"venue"
},
  "geometry": {"coordinates":[-74.06567200000001,40.727369],"type":"Point"}
}