{
  "type": "Feature",
  "properties": {
    "iso:country":"US",
    "sg:address":"10 Bay Aire Rd",
    "sg:city":"Marmora",
    "sg:classifiers":[
        {
            "category":"Building & Trades",
            "subcategory":"Construction",
            "type":"Services"
        }
    ],
    "sg:phone":"+1 609 390 3146",
    "sg:postcode":"08223",
    "sg:province":"NJ",
    "sg:tags":[
        "concrete",
        "contractor"
    ],
    "wof:name":"E C Concrete",
    "wof:placetype":"venue"
},
  "geometry": {"coordinates":[-74.641938,39.271044],"type":"Point"}
}