{
  "type": "Feature",
  "properties": {
    "iso:country":"US",
    "sg:address":"529 Hurffville Crosskeys Rd",
    "sg:city":"Sewell",
    "sg:classifiers":[
        {
            "category":"Sports & Exercise",
            "subcategory":"Sports Center",
            "type":"Entertainment"
        },
        {
            "category":"Community Center",
            "type":"Public Place"
        }
    ],
    "sg:phone":"+1 856 256 8660",
    "sg:postcode":"08080",
    "sg:province":"NJ",
    "sg:tags":[
        "recreation"
    ],
    "wof:name":"TD Bank Arts Centre (formerly Commerce Bank Arts Centre)",
    "wof:placetype":"venue"
},
  "geometry": {"coordinates":[-75.080421,39.74234],"type":"Point"}
}