{
  "type": "Feature",
  "properties": {
    "iso:country":"US",
    "sg:address":"596 River Rd",
    "sg:city":"Edgewater",
    "sg:classifiers":[
        {
            "category":"Manufacturing",
            "subcategory":"Chemicals & Compounds",
            "type":"Manufacturing & Wholesale Goods"
        }
    ],
    "sg:phone":"+1 201 945 9400",
    "sg:postcode":"07020",
    "sg:province":"NJ",
    "sg:tags":[
        "mfg",
        "de",
        "fluid",
        "specialty"
    ],
    "wof:name":"Octagon Process Inc",
    "wof:placetype":"venue"
},
  "geometry": {"coordinates":[-73.981471,40.816101],"type":"Point"}
}