{
  "type": "Feature",
  "properties": {
    "iso:country":"US",
    "sg:address":"323 Madison Ave W",
    "sg:city":"Magnolia",
    "sg:classifiers":[
        {
            "category":"Building & Trades",
            "subcategory":"Construction",
            "type":"Services"
        }
    ],
    "sg:phone":"+1 856 435 4587",
    "sg:postcode":"08049",
    "sg:province":"NJ",
    "sg:tags":[
        "hanging",
        "contractor"
    ],
    "wof:name":"AP Painting",
    "wof:placetype":"venue"
},
  "geometry": {"coordinates":[-75.038482,39.854528],"type":"Point"}
}