{
  "type": "Feature",
  "properties": {
    "iso:country":"US",
    "sg:address":"4819 US Hwy 9",
    "sg:city":"Howell",
    "sg:classifiers":[
        {
            "category":"Shopping",
            "subcategory":"Shoes",
            "type":"Retail Goods"
        }
    ],
    "sg:phone":"+1 732 905 4970",
    "sg:postcode":"07731",
    "sg:province":"NJ",
    "wof:name":"Payless Shoe Source",
    "wof:placetype":"venue"
},
  "geometry": {"coordinates":[-74.22380699999999,40.13384],"type":"Point"}
}