{
  "type": "Feature",
  "properties": {
    "iso:country":"US",
    "sg:address":"121 Chambersbridge Rd",
    "sg:city":"Brick",
    "sg:classifiers":[
        {
            "category":"Professional",
            "subcategory":"Lawyer & Legal Services",
            "type":"Services"
        }
    ],
    "sg:phone":"+1 732 451 9555",
    "sg:postcode":"08723",
    "sg:province":"NJ",
    "sg:tags":[
        "attorney"
    ],
    "wof:name":"Christine N Rossi",
    "wof:placetype":"venue"
},
  "geometry": {"coordinates":[-74.14251299999999,40.062919],"type":"Point"}
}