{
  "type": "Feature",
  "properties": {
    "iso:country":"US",
    "sg:address":"50 Berkeley Sq",
    "sg:city":"Berkeley Heights",
    "sg:classifiers":[
        {
            "category":"Insurance",
            "subcategory":"Insurance Agent",
            "type":"Services"
        }
    ],
    "sg:phone":"+1   ",
    "sg:postcode":"07922",
    "sg:province":"NJ",
    "sg:tags":[
        "company",
        "finance"
    ],
    "wof:name":"United Premium Services Inc",
    "wof:placetype":"venue"
},
  "geometry": {"coordinates":[-74.420807,40.673396],"type":"Point"}
}