{
  "type": "Feature",
  "properties": {
    "addr:full":"816 Delsea Dr N Glassboro NJ 08028",
    "addr:housenumber":"816",
    "addr:postcode":"08028",
    "addr:street":"Delsea Dr N",
    "iso:country":"US",
    "sg:address":"816 Delsea Dr N",
    "sg:city":"Glassboro",
    "sg:classifiers":[
        {
            "category":"Professional",
            "subcategory":"Business Services",
            "type":"Services"
        }
    ],
    "sg:phone":"+1   ",
    "sg:postcode":"08028",
    "sg:province":"NJ",
    "sg:tags":[
        "box",
        "related",
        "packaging",
        "shipping",
        "copying",
        "mail",
        "rental",
        "se"
    ],
    "wof:name":"UPS Stores 2270 The",
    "wof:placetype":"venue"
},
  "geometry": {"coordinates":[-75.115864,39.724132],"type":"Point"}
}