{
  "type": "Feature",
  "properties": {
    "iso:country":"US",
    "sg:address":"309 Grove Rd",
    "sg:city":"South Orange",
    "sg:classifiers":[
        {
            "category":"Professional",
            "subcategory":"Research",
            "type":"Services"
        }
    ],
    "sg:phone":"+1   ",
    "sg:postcode":"07079",
    "sg:province":"NJ",
    "sg:tags":[
        "consultant"
    ],
    "wof:name":"Hollis Scarborough",
    "wof:placetype":"venue"
},
  "geometry": {"coordinates":[-74.24672700000001,40.748755],"type":"Point"}
}