{
  "type": "Feature",
  "properties": {
    "iso:country":"US",
    "sg:address":"50 Sade St",
    "sg:city":"Clifton",
    "sg:classifiers":[
        {
            "category":"Real Estate",
            "subcategory":"Real Estate Operator",
            "type":"Services"
        }
    ],
    "sg:phone":"+1   ",
    "sg:postcode":"07013",
    "sg:province":"NJ",
    "sg:tags":[
        "owner",
        "housing",
        "complex",
        "senior",
        "citizen"
    ],
    "wof:name":"Evergreen Manor",
    "wof:placetype":"venue"
},
  "geometry": {"coordinates":[-74.146997,40.859046],"type":"Point"}
}