{
  "type": "Feature",
  "properties": {
    "addr:full":"460 Memorial Pkwy Phillipsburg NJ 08865",
    "addr:housenumber":"460",
    "addr:postcode":"08865",
    "addr:street":"Memorial Pkwy",
    "iso:country":"US",
    "sg:address":"460 Memorial Pkwy",
    "sg:city":"Phillipsburg",
    "sg:classifiers":[
        {
            "category":"Utilities",
            "subcategory":"Fuel Oil & Lpg",
            "type":"Services"
        },
        {
            "category":"Building & Trades",
            "subcategory":"Construction",
            "type":"Services"
        }
    ],
    "sg:phone":"+1 908 859 0982",
    "sg:postcode":"08865",
    "sg:province":"NJ",
    "sg:tags":[
        "system",
        "specialty",
        "kerosene",
        "heating",
        "ventilating",
        "oils-fuel",
        "contractor",
        "air conditioning"
    ],
    "sg:website":"http://www.coopersoil.com",
    "wof:name":"Cooper's Oil Company",
    "wof:placetype":"venue"
},
  "geometry": {"coordinates":[-75.18794800000001,40.695886],"type":"Point"}
}