{
  "type": "Feature",
  "properties": {
    "iso:country":"US",
    "sg:address":"25 E Salem St",
    "sg:city":"Hackensack",
    "sg:classifiers":[
        {
            "category":"Health Services",
            "subcategory":"Hospital",
            "type":"Services"
        }
    ],
    "sg:phone":"+1 201 996 5994",
    "sg:postcode":"07601",
    "sg:province":"NJ",
    "sg:tags":[
        "mental"
    ],
    "sg:website":"www.humcmd.net",
    "wof:name":"Hackensack Univ Med Ctr-Access",
    "wof:placetype":"venue"
},
  "geometry": {"coordinates":[-74.040525,40.885285],"type":"Point"}
}