{
  "type": "Feature",
  "properties": {
    "addr:full":"1641 Springfield Ave Maplewood NJ 07040",
    "addr:housenumber":"1641",
    "addr:postcode":"07040",
    "addr:street":"Springfield Ave",
    "iso:country":"US",
    "sg:address":"1641 Springfield Ave",
    "sg:city":"Maplewood",
    "sg:classifiers":[
        {
            "category":"Retail",
            "subcategory":"Repair Shop",
            "type":"Services"
        }
    ],
    "sg:phone":"+1   ",
    "sg:postcode":"07040",
    "sg:province":"NJ",
    "wof:name":"A 24 Hour Locksmith",
    "wof:placetype":"venue"
},
  "geometry": {"coordinates":[-74.2593,40.722075],"type":"Point"}
}