{
  "type": "Feature",
  "properties": {
    "iso:country":"US",
    "sg:address":"554 State Rte 35",
    "sg:city":"Mantoloking",
    "sg:classifiers":[
        {
            "category":"Real Estate",
            "subcategory":"Real Estate Agent",
            "type":"Services"
        }
    ],
    "sg:phone":"+1 732 793 5500",
    "sg:postcode":"08738",
    "sg:province":"NJ",
    "sg:website":"www.childers-re.com",
    "wof:name":"Lee Childers Real Estate",
    "wof:placetype":"venue"
},
  "geometry": {"coordinates":[-74.06071300000001,40.002621],"type":"Point"}
}