{
  "type": "Feature",
  "properties": {
    "iso:country":"US",
    "sg:address":"21 Clifton Rd",
    "sg:city":"Oak Ridge",
    "sg:classifiers":[
        {
            "category":"Retail",
            "subcategory":"Laundry & Dry Cleaning",
            "type":"Services"
        }
    ],
    "sg:phone":"+1 973 697 3617",
    "sg:postcode":"07438",
    "sg:province":"NJ",
    "sg:tags":[
        "cleaners",
        "rug",
        "carpet"
    ],
    "wof:name":"Service Master Of Jersey Hills",
    "wof:placetype":"venue"
},
  "geometry": {"coordinates":[-74.523487,41.027566],"type":"Point"}
}