{
  "type": "Feature",
  "properties": {
    "iso:country":"US",
    "sg:address":"135 Bellevue Ave",
    "sg:city":"Hammonton",
    "sg:classifiers":[
        {
            "category":"Professional",
            "subcategory":"Accounting & Tax Preparation",
            "type":"Services"
        }
    ],
    "sg:phone":"+1 609 345 1228",
    "sg:postcode":"08037",
    "sg:province":"NJ",
    "sg:tags":[
        "return",
        "filing"
    ],
    "wof:name":"Professional Tax Svc",
    "wof:placetype":"venue"
},
  "geometry": {"coordinates":[-74.803819,39.635774],"type":"Point"}
}