{
  "type": "Feature",
  "properties": {
    "iso:country":"US",
    "sg:address":"52 Edgewood Ave",
    "sg:city":"Nutley",
    "sg:classifiers":[
        {
            "category":"Professional",
            "subcategory":"Lawyer & Legal Services",
            "type":"Services"
        }
    ],
    "sg:phone":"+1 973 667 8600",
    "sg:postcode":"07110",
    "sg:province":"NJ",
    "wof:name":"Cozine Michael E Attorney",
    "wof:placetype":"venue"
},
  "geometry": {"coordinates":[-74.146698,40.8218],"type":"Point"}
}