{
  "type": "Feature",
  "properties": {
    "iso:country":"US",
    "sg:address":"11 Lanning St",
    "sg:city":"Trenton",
    "sg:classifiers":[
        {
            "category":"Professional",
            "subcategory":"Management & Consulting",
            "type":"Services"
        }
    ],
    "sg:phone":"+1 609 883 7443",
    "sg:postcode":"08618",
    "sg:province":"NJ",
    "sg:tags":[
        "consultant",
        "educational"
    ],
    "wof:name":"SET",
    "wof:placetype":"venue"
},
  "geometry": {"coordinates":[-74.783907,40.265942],"type":"Point"}
}