{
  "type": "Feature",
  "properties": {
    "iso:country":"US",
    "sg:address":"46 N Hillside Ave",
    "sg:city":"Kenvil",
    "sg:classifiers":[
        {
            "category":"Personal",
            "subcategory":"Beauty Salon",
            "type":"Services"
        }
    ],
    "sg:phone":"+1   ",
    "sg:postcode":"07847",
    "sg:province":"NJ",
    "wof:name":"Right Angle",
    "wof:placetype":"venue"
},
  "geometry": {"coordinates":[-74.635904,40.874893],"type":"Point"}
}