{
  "type": "Feature",
  "properties": {
    "addr:full":"120 Essex St Millburn NJ 07041",
    "addr:housenumber":"120",
    "addr:postcode":"07041",
    "addr:street":"Essex St",
    "iso:country":"US",
    "sg:address":"120 Essex St",
    "sg:city":"Millburn",
    "sg:classifiers":[
        {
            "category":"Shopping",
            "subcategory":"Clothing, Apparel, & Fashions",
            "type":"Retail Goods"
        }
    ],
    "sg:phone":"+1 973 376 2466",
    "sg:postcode":"07041",
    "sg:province":"NJ",
    "sg:tags":[
        "shop",
        "bridal",
        "store"
    ],
    "wof:name":"Calvary Bridal House Inc",
    "wof:placetype":"venue"
},
  "geometry": {"coordinates":[-74.305977,40.725093],"type":"Point"}
}