{
  "type": "Feature",
  "properties": {
    "iso:country":"US",
    "sg:address":"26 N Main St",
    "sg:city":"Toms River",
    "sg:classifiers":[
        {
            "category":"Health Services",
            "subcategory":"Hospital",
            "type":"Services"
        },
        {
            "category":"Health Services",
            "subcategory":"Clinic",
            "type":"Services"
        }
    ],
    "sg:phone":"+1 732 341 8255",
    "sg:postcode":"08753",
    "sg:province":"NJ",
    "sg:tags":[
        "mental",
        "outpatient",
        "specialty"
    ],
    "wof:name":"Community Children & Family Co",
    "wof:placetype":"venue"
},
  "geometry": {"coordinates":[-74.19826,39.953016],"type":"Point"}
}