{
  "type": "Feature",
  "properties": {
    "iso:country":"US",
    "sg:address":"808 Lowell Ave",
    "sg:city":"Toms River",
    "sg:classifiers":[
        {
            "category":"Professional",
            "subcategory":"Computer Services",
            "type":"Services"
        }
    ],
    "sg:phone":"+1   ",
    "sg:postcode":"08753",
    "sg:province":"NJ",
    "sg:tags":[
        "mail",
        "direct"
    ],
    "wof:name":"Trec",
    "wof:placetype":"venue"
},
  "geometry": {"coordinates":[-74.187245,39.961717],"type":"Point"}
}