{
  "type": "Feature",
  "properties": {
    "iso:country":"US",
    "sg:address":"43 Meadows Ln",
    "sg:city":"Asbury Park",
    "sg:classifiers":[
        {
            "category":"Professional",
            "subcategory":"Accounting & Tax Preparation",
            "type":"Services"
        }
    ],
    "sg:phone":"+1 732 671 6305",
    "sg:postcode":"07712",
    "sg:province":"NJ",
    "sg:tags":[
        "accountant"
    ],
    "wof:name":"Alan J Rothstein",
    "wof:placetype":"venue"
},
  "geometry": {"coordinates":[-74.051249,40.246241],"type":"Point"}
}