{
  "type": "Feature",
  "properties": {
    "iso:country":"US",
    "sg:address":"869 Ringwood Ave",
    "sg:city":"Haskell",
    "sg:classifiers":[
        {
            "category":"Building & Trades",
            "subcategory":"Pest Control",
            "type":"Services"
        }
    ],
    "sg:phone":"+1 973 839 6228",
    "sg:postcode":"07420",
    "sg:province":"NJ",
    "sg:website":"www.abarbpest.com",
    "wof:name":"Abarb Pest Svc Inc",
    "wof:placetype":"venue"
},
  "geometry": {"coordinates":[-74.29290899999999,41.041511],"type":"Point"}
}