{
  "type": "Feature",
  "properties": {
    "addr:full":"110 Pomponio Ave South Plainfield NJ 07080",
    "addr:housenumber":"110",
    "addr:postcode":"07080",
    "addr:street":"Pomponio Ave",
    "iso:country":"US",
    "sg:address":"110 Pomponio Ave",
    "sg:city":"South Plainfield",
    "sg:classifiers":[
        {
            "category":"Manufacturing",
            "subcategory":"Chemicals & Compounds",
            "type":"Manufacturing & Wholesale Goods"
        }
    ],
    "sg:phone":"+1 908 754 7306",
    "sg:postcode":"07080",
    "sg:province":"NJ",
    "sg:tags":[
        "lacquer",
        "enamel",
        "mfg",
        "remover",
        "nail",
        "polish"
    ],
    "wof:name":"Durlin USA",
    "wof:placetype":"venue"
},
  "geometry": {"coordinates":[-74.427611,40.569187],"type":"Point"}
}