{
  "type": "Feature",
  "properties": {
    "iso:country":"US",
    "sg:address":"2175 Hudson Ter",
    "sg:city":"Fort Lee",
    "sg:classifiers":[
        {
            "category":"Manufacturing",
            "subcategory":"Printing",
            "type":"Manufacturing & Wholesale Goods"
        }
    ],
    "sg:phone":"+1 201 585 1963",
    "sg:postcode":"07024",
    "sg:province":"NJ",
    "wof:name":"Alephbet Printing & Typsg LLC",
    "wof:placetype":"venue"
},
  "geometry": {"coordinates":[-73.960786,40.85961],"type":"Point"}
}