{
  "type": "Feature",
  "properties": {
    "iso:country":"US",
    "sg:address":"45 Holt Cir",
    "sg:city":"Trenton",
    "sg:classifiers":[
        {
            "category":"Building & Trades",
            "subcategory":"Electrical",
            "type":"Services"
        }
    ],
    "sg:phone":"+1 609 890 8334",
    "sg:postcode":"08619",
    "sg:province":"NJ",
    "sg:tags":[
        "electrical",
        "contractor"
    ],
    "wof:name":"Robert Jewell Electrical",
    "wof:placetype":"venue"
},
  "geometry": {"coordinates":[-74.683205,40.242195],"type":"Point"}
}