{
  "type": "Feature",
  "properties": {
    "iso:country":"US",
    "sg:address":"3067 Lakewood Allenwood Rd",
    "sg:city":"Howell",
    "sg:classifiers":[
        {
            "category":"Social Services",
            "subcategory":"Child Care",
            "type":"Services"
        }
    ],
    "sg:phone":"+1 732 901 1234",
    "sg:postcode":"07731",
    "sg:province":"NJ",
    "sg:tags":[
        "kindergarten",
        "academic",
        "school",
        "day"
    ],
    "wof:name":"Little People's Preschool Ctr",
    "wof:placetype":"venue"
},
  "geometry": {"coordinates":[-74.178697,40.114302],"type":"Point"}
}