{
  "type": "Feature",
  "properties": {
    "iso:country":"US",
    "sg:address":"1086 Teaneck Rd Ste 2C",
    "sg:city":"Teaneck",
    "sg:classifiers":[
        {
            "category":"Professional",
            "subcategory":"Accounting & Tax Preparation",
            "type":"Services"
        }
    ],
    "sg:phone":"+1 201 833 2266",
    "sg:postcode":"07666",
    "sg:province":"NJ",
    "sg:tags":[
        "accountant"
    ],
    "wof:name":"Feld Levine & Co Llc",
    "wof:placetype":"venue"
},
  "geometry": {"coordinates":[-74.00369999999999,40.8904],"type":"Point"}
}