{
  "type": "Feature",
  "properties": {
    "addr:full":"480 Heller Park Ct Dayton NJ 08810",
    "addr:housenumber":"480",
    "addr:postcode":"08810",
    "addr:street":"Heller Park Ct",
    "iso:country":"US",
    "sg:address":"480 Heller Park Ct",
    "sg:city":"Dayton",
    "sg:classifiers":[
        {
            "category":"Professional",
            "type":"Services"
        }
    ],
    "sg:phone":"+1 732 355 1300",
    "sg:postcode":"08810",
    "sg:province":"NJ",
    "sg:tags":[
        "establishment"
    ],
    "wof:name":"Unitrade",
    "wof:placetype":"venue"
},
  "geometry": {"coordinates":[-74.49722,40.372876],"type":"Point"}
}