{
  "type": "Feature",
  "properties": {
    "iso:country":"US",
    "sg:address":"484 Adams Ave",
    "sg:city":"Elizabeth",
    "sg:classifiers":[
        {
            "category":"Arts & Performance",
            "subcategory":"Theater",
            "type":"Entertainment"
        }
    ],
    "sg:phone":"+1   ",
    "sg:postcode":"07201",
    "sg:province":"NJ",
    "sg:tags":[
        "group"
    ],
    "wof:name":"Destiny Entertainment Inc",
    "wof:placetype":"venue"
},
  "geometry": {"coordinates":[-74.205535,40.670328],"type":"Point"}
}