{
  "type": "Feature",
  "properties": {
    "addr:full":"12 Pheasant Dr Marlboro NJ 07746",
    "addr:housenumber":"12",
    "addr:postcode":"07746",
    "addr:street":"Pheasant Dr",
    "iso:country":"US",
    "sg:address":"12 Pheasant Dr",
    "sg:city":"Marlboro",
    "sg:classifiers":[
        {
            "category":"Shopping",
            "subcategory":"Computers & Home Electronics",
            "type":"Retail Goods"
        }
    ],
    "sg:phone":"+1   ",
    "sg:postcode":"07746",
    "sg:province":"NJ",
    "wof:name":"Nfusion Interactive LLC",
    "wof:placetype":"venue"
},
  "geometry": {"coordinates":[-74.283002,40.30143],"type":"Point"}
}