{
  "type": "Feature",
  "properties": {
    "iso:country":"US",
    "sg:address":"12 Pheasant Dr",
    "sg:city":"Marlboro",
    "sg:classifiers":[
        {
            "category":"Shopping",
            "subcategory":"Computers & Home Electronics",
            "type":"Retail Goods"
        }
    ],
    "sg:phone":"+1   ",
    "sg:postcode":"07746",
    "sg:province":"NJ",
    "wof:name":"Nfusion Interactive LLC",
    "wof:placetype":"venue"
},
  "geometry": {"coordinates":[-74.283002,40.30143],"type":"Point"}
}