{
  "type": "Feature",
  "properties": {
    "iso:country":"US",
    "sg:address":"280 US Hwy 46",
    "sg:city":"Dover",
    "sg:classifiers":[
        {
            "category":"Banks & Credit Unions",
            "subcategory":"Financial Services",
            "type":"Services"
        }
    ],
    "sg:phone":"+1   ",
    "sg:postcode":"07801",
    "sg:province":"NJ",
    "sg:tags":[
        "charitable",
        "foundation"
    ],
    "wof:name":"Wish Fulfilment Foundation",
    "wof:placetype":"venue"
},
  "geometry": {"coordinates":[-74.57262299999999,40.886348],"type":"Point"}
}