{
  "type": "Feature",
  "properties": {
    "iso:country":"US",
    "sg:address":"457 State Rte 79",
    "sg:city":"Morganville",
    "sg:classifiers":[
        {
            "category":"Banks & Credit Unions",
            "subcategory":"Bank",
            "type":"Services"
        }
    ],
    "sg:phone":"+1 732 970 9210",
    "sg:postcode":"07751",
    "sg:province":"NJ",
    "sg:tags":[
        "loan",
        "real estate"
    ],
    "wof:name":"New Jersey Home Funding",
    "wof:placetype":"venue"
},
  "geometry": {"coordinates":[-74.24219600000001,40.381062],"type":"Point"}
}