{
  "type": "Feature",
  "properties": {
    "iso:country":"US",
    "sg:address":"200 State Rte 10",
    "sg:city":"Succasunna",
    "sg:classifiers":[
        {
            "category":"Social Services",
            "subcategory":"Job Training",
            "type":"Services"
        }
    ],
    "sg:phone":"+1 732 297 8848",
    "sg:postcode":"07876",
    "sg:province":"NJ",
    "sg:tags":[
        "rehabilitation"
    ],
    "wof:name":"Ansa Consultant",
    "wof:placetype":"venue"
},
  "geometry": {"coordinates":[-74.644386,40.871356],"type":"Point"}
}