{
  "type": "Feature",
  "properties": {
    "addr:full":"63 E Main St Penns Grove NJ 08069",
    "addr:housenumber":"63",
    "addr:postcode":"08069",
    "addr:street":"E Main St",
    "iso:country":"US",
    "sg:address":"63 E Main St",
    "sg:city":"Penns Grove",
    "sg:classifiers":[
        {
            "category":"Food & Beverages",
            "subcategory":"Groceries & Convenience Stores",
            "type":"Retail Goods"
        }
    ],
    "sg:phone":"+1 856 299 1996",
    "sg:postcode":"08069",
    "sg:province":"NJ",
    "sg:tags":[
        "grocer"
    ],
    "wof:name":"Crescent Food Market",
    "wof:placetype":"venue"
},
  "geometry": {"coordinates":[-75.466391,39.728128],"type":"Point"}
}