{
  "type": "Feature",
  "properties": {
    "iso:country":"US",
    "sg:address":"203 South Ave E",
    "sg:city":"Westfield",
    "sg:classifiers":[
        {
            "category":"Health Services",
            "subcategory":"Health Practitioner",
            "type":"Services"
        }
    ],
    "sg:phone":"+1 908 232 4331",
    "sg:postcode":"07090",
    "sg:province":"NJ",
    "wof:name":"Angela Provenzano",
    "wof:placetype":"venue"
},
  "geometry": {"coordinates":[-74.33910400000001,40.649645],"type":"Point"}
}