{
  "type": "Feature",
  "properties": {
    "iso:country":"US",
    "sg:address":"3 Glengarry Way",
    "sg:city":"Princeton Junction",
    "sg:classifiers":[
        {
            "category":"Shopping",
            "type":"Retail Goods"
        }
    ],
    "sg:phone":"+1   ",
    "sg:postcode":"08550",
    "sg:province":"NJ",
    "sg:tags":[
        "merchandise"
    ],
    "wof:name":"Newweave Corporation",
    "wof:placetype":"venue"
},
  "geometry": {"coordinates":[-74.589513,40.294377],"type":"Point"}
}