{
  "type": "Feature",
  "properties": {
    "addr:full":"101 N Pennsylvania Ave Atlantic City NJ 08401",
    "addr:housenumber":"101",
    "addr:postcode":"08401",
    "addr:street":"N Pennsylvania Ave",
    "iso:country":"US",
    "sg:address":"101 N Pennsylvania Ave",
    "sg:city":"Atlantic City",
    "sg:classifiers":[
        {
            "category":"Retail",
            "subcategory":"Laundry & Dry Cleaning",
            "type":"Services"
        }
    ],
    "sg:phone":"+1   ",
    "sg:postcode":"08401",
    "sg:province":"NJ",
    "sg:tags":[
        "drycleaning",
        "plant",
        "agent",
        "garment"
    ],
    "wof:name":"Seabreeze Cleaners",
    "wof:placetype":"venue"
},
  "geometry": {"coordinates":[-74.42616599999999,39.366492],"type":"Point"}
}