{
  "type": "Feature",
  "properties": {
    "addr:full":"487 Fulton Ct West New York NJ 07093",
    "addr:housenumber":"487",
    "addr:postcode":"07093",
    "addr:street":"Fulton Ct West",
    "iso:country":"US",
    "sg:address":"487 Fulton Ct",
    "sg:city":"West New York",
    "sg:classifiers":[
        {
            "category":"Professional",
            "type":"Services"
        }
    ],
    "sg:phone":"+1   ",
    "sg:postcode":"07093",
    "sg:province":"NJ",
    "wof:name":"North River Systems",
    "wof:placetype":"venue"
},
  "geometry": {"coordinates":[-74.00887299999999,40.782848],"type":"Point"}
}