{
  "type": "Feature",
  "properties": {
    "addr:full":"141 Stone Hill Rd Freehold NJ 07728",
    "addr:housenumber":"141",
    "addr:postcode":"07728",
    "addr:street":"Stone Hill Rd",
    "iso:country":"US",
    "sg:address":"141 Stone Hill Rd",
    "sg:city":"Freehold",
    "sg:classifiers":[
        {
            "category":"Building & Trades",
            "subcategory":"Construction",
            "type":"Services"
        }
    ],
    "sg:phone":"+1 732 462 9532",
    "sg:postcode":"07728",
    "sg:province":"NJ",
    "sg:tags":[
        "work",
        "fence",
        "carpentry"
    ],
    "wof:name":"M S Reed Inc",
    "wof:placetype":"venue"
},
  "geometry": {"coordinates":[-74.287103,40.207268],"type":"Point"}
}