{
  "type": "Feature",
  "properties": {
    "iso:country":"US",
    "sg:address":"216 Stelton Rd",
    "sg:city":"Piscataway",
    "sg:classifiers":[
        {
            "category":"Professional",
            "subcategory":"Lawyer & Legal Services",
            "type":"Services"
        }
    ],
    "sg:phone":"+1 732 424 9388",
    "sg:postcode":"08854",
    "sg:province":"NJ",
    "sg:tags":[
        "law"
    ],
    "wof:name":"The Law Offices Lee R Lederman",
    "wof:placetype":"venue"
},
  "geometry": {"coordinates":[-74.456642,40.567942],"type":"Point"}
}