{
  "type": "Feature",
  "properties": {
    "addr:full":"1184 Main Ave Clifton NJ 07011",
    "addr:housenumber":"1184",
    "addr:postcode":"07011",
    "addr:street":"Main Ave",
    "iso:country":"US",
    "sg:address":"1184 Main Ave",
    "sg:city":"Clifton",
    "sg:classifiers":[
        {
            "category":"Building & Trades",
            "subcategory":"Construction",
            "type":"Services"
        }
    ],
    "sg:phone":"+1 973 470 8664",
    "sg:postcode":"07011",
    "sg:province":"NJ",
    "sg:tags":[
        "personal",
        "residential",
        "contractor"
    ],
    "wof:name":"A-1 Construction Inc",
    "wof:placetype":"venue"
},
  "geometry": {"coordinates":[-74.140152,40.875924],"type":"Point"}
}