{
  "type": "Feature",
  "properties": {
    "addr:full":"598 Central Ave New Providence NJ 07974",
    "addr:housenumber":"598",
    "addr:postcode":"07974",
    "addr:street":"Central Ave",
    "iso:country":"US",
    "sg:address":"598 Central Ave",
    "sg:city":"New Providence",
    "sg:classifiers":[
        {
            "category":"Retail",
            "subcategory":"Repair Shop",
            "type":"Services"
        }
    ],
    "sg:phone":"+1   ",
    "sg:postcode":"07974",
    "sg:province":"NJ",
    "wof:name":"124 Hour 7 Day A Lock A Locksm",
    "wof:placetype":"venue"
},
  "geometry": {"coordinates":[-74.403802,40.698042],"type":"Point"}
}