{
  "type": "Feature",
  "properties": {
    "iso:country":"US",
    "sg:address":"138 S Broad St",
    "sg:city":"Woodbury",
    "sg:classifiers":[
        {
            "category":"Personal",
            "subcategory":"Beauty Salon",
            "type":"Services"
        }
    ],
    "sg:phone":"+1 856 845 1433",
    "sg:postcode":"08096",
    "sg:province":"NJ",
    "sg:tags":[
        "shop"
    ],
    "wof:name":"Aztech Hair Designs",
    "wof:placetype":"venue"
},
  "geometry": {"coordinates":[-75.154796,39.835853],"type":"Point"}
}