{
  "type": "Feature",
  "properties": {
    "iso:country":"US",
    "sg:address":"5918 Bergenline Pl",
    "sg:city":"West New York",
    "sg:classifiers":[
        {
            "category":"Professional",
            "subcategory":"Lawyer & Legal Services",
            "type":"Services"
        }
    ],
    "sg:phone":"+1   ",
    "sg:postcode":"07093",
    "sg:province":"NJ",
    "wof:name":"Ronald R Kazanchy",
    "wof:placetype":"venue"
},
  "geometry": {"coordinates":[-74.01634199999999,40.788732],"type":"Point"}
}