{
  "type": "Feature",
  "properties": {
    "addr:full":"291 US Hwy 22 Lebanon NJ 08833",
    "addr:housenumber":"291",
    "addr:postcode":"08833",
    "addr:street":"Us Hwy 22",
    "iso:country":"US",
    "sg:address":"291 US Hwy 22",
    "sg:city":"Lebanon",
    "sg:phone":"+1 908 534 9242",
    "sg:postcode":"08833",
    "sg:province":"NJ",
    "sg:tags":[
        "equipment",
        "supply"
    ],
    "wof:name":"Sudek International",
    "wof:placetype":"venue"
},
  "geometry": {"coordinates":[-74.79060200000001,40.637163],"type":"Point"}
}