{
  "type": "Feature",
  "properties": {
    "iso:country":"US",
    "sg:address":"450 N King St",
    "sg:city":"Gloucester City",
    "sg:classifiers":[
        {
            "category":"Manufacturing",
            "subcategory":"Tools & Machinery",
            "type":"Manufacturing & Wholesale Goods"
        }
    ],
    "sg:phone":"+1 856 456 2554",
    "sg:postcode":"08030",
    "sg:province":"NJ",
    "sg:tags":[
        "machine",
        "shop"
    ],
    "wof:name":"O S Johnson & Co",
    "wof:placetype":"venue"
},
  "geometry": {"coordinates":[-75.12137800000001,39.903233],"type":"Point"}
}