{
  "type": "Feature",
  "properties": {
    "iso:country":"US",
    "sg:address":"1312 Adams St",
    "sg:city":"Hoboken",
    "sg:classifiers":[
        {
            "category":"Manufacturing",
            "subcategory":"Metals",
            "type":"Manufacturing & Wholesale Goods"
        }
    ],
    "sg:phone":"+1 201 659 0911",
    "sg:postcode":"07030",
    "sg:province":"NJ",
    "sg:tags":[
        "casting",
        "aluminum",
        "mfg",
        "foundry",
        "brass",
        "bronze"
    ],
    "wof:name":"High Purity Alloys Inc",
    "wof:placetype":"venue"
},
  "geometry": {"coordinates":[-74.032622,40.754255],"type":"Point"}
}