{
  "type": "Feature",
  "properties": {
    "addr:full":"225 Admiral Ave Beachwood NJ 08722",
    "addr:housenumber":"225",
    "addr:postcode":"08722",
    "addr:street":"Admiral Ave",
    "iso:country":"US",
    "sg:address":"225 Admiral Ave",
    "sg:city":"Beachwood",
    "sg:classifiers":[
        {
            "category":"Building & Trades",
            "subcategory":"Pest Control",
            "type":"Services"
        }
    ],
    "sg:phone":"+1 732 505 8800",
    "sg:postcode":"08722",
    "sg:province":"NJ",
    "wof:name":"Best Pest Control",
    "wof:placetype":"venue"
},
  "geometry": {"coordinates":[-74.195919,39.941161],"type":"Point"}
}