{
  "type": "Feature",
  "properties": {
    "iso:country":"US",
    "sg:address":"175 Union Ave",
    "sg:city":"Rutherford",
    "sg:classifiers":[
        {
            "category":"Building & Trades",
            "subcategory":"Plumbing",
            "type":"Services"
        }
    ],
    "sg:phone":"+1 201 935 7355",
    "sg:postcode":"07070",
    "sg:province":"NJ",
    "sg:tags":[
        "plumbing",
        "contractor"
    ],
    "wof:name":"Bob Eubanks Plumbing & Heating",
    "wof:placetype":"venue"
},
  "geometry": {"coordinates":[-74.10817900000001,40.833001],"type":"Point"}
}