{
  "type": "Feature",
  "properties": {
    "addr:full":"23 Gallop Ln Somerset NJ 08873",
    "addr:housenumber":"23",
    "addr:postcode":"08873",
    "addr:street":"Gallop Ln",
    "iso:country":"US",
    "sg:address":"23 Gallop Ln",
    "sg:city":"Somerset",
    "sg:classifiers":[
        {
            "category":"Professional",
            "subcategory":"Computer Services",
            "type":"Services"
        }
    ],
    "sg:phone":"+1   ",
    "sg:postcode":"08873",
    "sg:province":"NJ",
    "sg:tags":[
        "related"
    ],
    "wof:name":"Cyberline Corp",
    "wof:placetype":"venue"
},
  "geometry": {"coordinates":[-74.511422,40.461145],"type":"Point"}
}