{
  "type": "Feature",
  "properties": {
    "addr:full":"16 Fairview Ave Bound Brook NJ 08805",
    "addr:housenumber":"16",
    "addr:postcode":"08805",
    "addr:street":"Fairview Ave",
    "iso:country":"US",
    "sg:address":"16 Fairview Ave",
    "sg:city":"Bound Brook",
    "sg:classifiers":[
        {
            "category":"Building & Trades",
            "subcategory":"Electrical",
            "type":"Services"
        }
    ],
    "sg:phone":"+1 732 271 1404",
    "sg:postcode":"08805",
    "sg:province":"NJ",
    "sg:tags":[
        "electrical",
        "contractor"
    ],
    "wof:name":"R Dietrich & Son Elec Contr",
    "wof:placetype":"venue"
},
  "geometry": {"coordinates":[-74.538439,40.563116],"type":"Point"}
}