{
  "type": "Feature",
  "properties": {
    "addr:full":"3 W Washington Ave Washington NJ 07882",
    "addr:housenumber":"3",
    "addr:postcode":"07882",
    "addr:street":"W Washington Ave",
    "iso:country":"US",
    "sg:address":"3 W Washington Ave",
    "sg:city":"Washington",
    "sg:classifiers":[
        {
            "category":"Food & Beverages",
            "subcategory":"Candy",
            "type":"Retail Goods"
        },
        {
            "category":"Communications",
            "subcategory":"Newspaper",
            "type":"Services"
        }
    ],
    "sg:phone":"+1 908 689 2890",
    "sg:postcode":"07882",
    "sg:province":"NJ",
    "sg:tags":[
        "magazine",
        "store"
    ],
    "wof:name":"Sln News",
    "wof:placetype":"venue"
},
  "geometry": {"coordinates":[-74.981796,40.7579],"type":"Point"}
}