{
  "type": "Feature",
  "properties": {
    "addr:full":"111 Madison Ave Ste 311 Morristown NJ 07960",
    "addr:housenumber":"111",
    "addr:postcode":"07960",
    "addr:street":"Madison Ave Ste 311",
    "iso:country":"US",
    "sg:address":"111 Madison Ave Ste 311",
    "sg:city":"Morristown",
    "sg:classifiers":[
        {
            "category":"Health Services",
            "subcategory":"Doctor",
            "type":"Services"
        }
    ],
    "sg:phone":"+1 973 971 9950",
    "sg:postcode":"07960",
    "sg:province":"NJ",
    "sg:tags":[
        "obstetrician",
        "gynecologist"
    ],
    "wof:name":"Iammatteo Matthew D MD",
    "wof:placetype":"venue"
},
  "geometry": {"coordinates":[-74.462232,40.787434],"type":"Point"}
}