{
  "type": "Feature",
  "properties": {
    "iso:country":"US",
    "sg:address":"71 Grand Ave",
    "sg:city":"Englewood",
    "sg:classifiers":[
        {
            "category":"Banks & Credit Unions",
            "subcategory":"Bank",
            "type":"Services"
        }
    ],
    "sg:phone":"+1   ",
    "sg:postcode":"07631",
    "sg:province":"NJ",
    "sg:tags":[
        "broker",
        "mortgage"
    ],
    "wof:name":"UNI-Link Mortgage Corporation",
    "wof:placetype":"venue"
},
  "geometry": {"coordinates":[-73.975179,40.889953],"type":"Point"}
}