{
  "type": "Feature",
  "properties": {
    "addr:full":"16 Harwick Dr Trenton NJ 08619",
    "addr:housenumber":"16",
    "addr:postcode":"08619",
    "addr:street":"Harwick Dr",
    "iso:country":"US",
    "sg:address":"16 Harwick Dr",
    "sg:city":"Trenton",
    "sg:classifiers":[
        {
            "category":"Professional",
            "type":"Services"
        }
    ],
    "sg:phone":"+1   ",
    "sg:postcode":"08619",
    "sg:province":"NJ",
    "wof:name":"Glenn Ward Inc",
    "wof:placetype":"venue"
},
  "geometry": {"coordinates":[-74.701502,40.230326],"type":"Point"}
}