{
  "type": "Feature",
  "properties": {
    "addr:full":"26 Essex Dr Monmouth Junction NJ 08852",
    "addr:housenumber":"26",
    "addr:postcode":"08852",
    "addr:street":"Essex Dr",
    "iso:country":"US",
    "sg:address":"26 Essex Dr",
    "sg:city":"Monmouth Junction",
    "sg:classifiers":[
        {
            "category":"Professional",
            "subcategory":"Management & Consulting",
            "type":"Services"
        }
    ],
    "sg:phone":"+1   ",
    "sg:postcode":"08852",
    "sg:province":"NJ",
    "sg:tags":[
        "business"
    ],
    "wof:name":"Gecko Consulting LLC",
    "wof:placetype":"venue"
},
  "geometry": {"coordinates":[-74.57445,40.388551],"type":"Point"}
}