{
  "type": "Feature",
  "properties": {
    "iso:country":"US",
    "sg:address":"745 Chancellor Ave",
    "sg:city":"Irvington",
    "sg:classifiers":[
        {
            "category":"Organizations",
            "subcategory":"Religious Organization",
            "type":"Services"
        }
    ],
    "sg:phone":"+1 973 374 9363",
    "sg:postcode":"07111",
    "sg:province":"NJ",
    "sg:tags":[
        "church"
    ],
    "wof:name":"Fellowship Baptist Church Inc",
    "wof:placetype":"venue"
},
  "geometry": {"coordinates":[-74.23932499999999,40.716503],"type":"Point"}
}