{
  "type": "Feature",
  "properties": {
    "addr:full":"300-3 State Rt 17 S Ste 4A Hackensack NJ 07644",
    "addr:housenumber":"300-3",
    "addr:postcode":"07644",
    "addr:street":"State Rt 17 S Ste 4A",
    "iso:country":"US",
    "sg:address":"300-3 State Rt 17 S Ste 4A",
    "sg:city":"Hackensack",
    "sg:classifiers":[
        {
            "category":"Professional",
            "subcategory":"Lawyer & Legal Services",
            "type":"Services"
        }
    ],
    "sg:phone":"+1 201 489 1889",
    "sg:postcode":"07644",
    "sg:province":"NJ",
    "wof:name":"Occupational Assessment Services Inc",
    "wof:placetype":"venue"
},
  "geometry": {"coordinates":[-74.04740700000001,40.878499],"type":"Point"}
}