{
  "type": "Feature",
  "properties": {
    "addr:full":"6 Windsor Dr Eatontown NJ 07724",
    "addr:housenumber":"6",
    "addr:postcode":"07724",
    "addr:street":"Windsor Dr",
    "iso:country":"US",
    "sg:address":"6 Windsor Dr",
    "sg:city":"Eatontown",
    "sg:classifiers":[
        {
            "category":"Manufacturing",
            "subcategory":"Printing",
            "type":"Manufacturing & Wholesale Goods"
        }
    ],
    "sg:phone":"+1 732 460 9404",
    "sg:postcode":"07724",
    "sg:province":"NJ",
    "sg:tags":[
        "periodical"
    ],
    "wof:name":"International Data Group Inc",
    "wof:placetype":"venue"
},
  "geometry": {"coordinates":[-74.06432100000001,40.281848],"type":"Point"}
}