{
  "type": "Feature",
  "properties": {
    "addr:full":"49 Oxford St Paterson NJ 07522",
    "addr:housenumber":"49",
    "addr:postcode":"07522",
    "addr:street":"Oxford St",
    "iso:country":"US",
    "sg:address":"49 Oxford St",
    "sg:city":"Paterson",
    "sg:classifiers":[
        {
            "category":"Retail",
            "subcategory":"Auto Repair",
            "type":"Services"
        }
    ],
    "sg:phone":"+1 973 942 6059",
    "sg:postcode":"07522",
    "sg:province":"NJ",
    "sg:tags":[
        "body",
        "automobile",
        "painting"
    ],
    "wof:name":"Victor S Autobody",
    "wof:placetype":"venue"
},
  "geometry": {"coordinates":[-74.17904299999999,40.923964],"type":"Point"}
}