{
  "type": "Feature",
  "properties": {
    "iso:country":"US",
    "sg:address":"797 Park Dr",
    "sg:city":"Cherry Hill",
    "sg:classifiers":[
        {
            "category":"Organizations",
            "subcategory":"Membership Organization",
            "type":"Services"
        }
    ],
    "sg:phone":"+1 856 354 1487",
    "sg:postcode":"08002",
    "sg:province":"NJ",
    "wof:name":"Amato Association Inc",
    "wof:placetype":"venue"
},
  "geometry": {"coordinates":[-75.018997,39.910381],"type":"Point"}
}