{
  "type": "Feature",
  "properties": {
    "iso:country":"US",
    "sg:address":"169 W Front St",
    "sg:city":"Red Bank",
    "sg:classifiers":[
        {
            "category":"Shopping",
            "subcategory":"Used Merchandise",
            "type":"Retail Goods"
        }
    ],
    "sg:phone":"+1   ",
    "sg:postcode":"07701",
    "sg:province":"NJ",
    "sg:tags":[
        "antique",
        "home",
        "furnishing"
    ],
    "wof:name":"Riverbank Antiques & Interiors",
    "wof:placetype":"venue"
},
  "geometry": {"coordinates":[-74.071883,40.350795],"type":"Point"}
}