{
  "type": "Feature",
  "properties": {
    "iso:country":"US",
    "sg:address":"107 Surrey Ct",
    "sg:city":"Oceanport",
    "sg:classifiers":[
        {
            "category":"Shopping",
            "subcategory":"Computers & Home Electronics",
            "type":"Retail Goods"
        }
    ],
    "sg:phone":"+1 732 578 0091",
    "sg:postcode":"07757",
    "sg:province":"NJ",
    "sg:tags":[
        "software"
    ],
    "wof:name":"Kamino",
    "wof:placetype":"venue"
},
  "geometry": {"coordinates":[-74.02896699999999,40.309937],"type":"Point"}
}