{
  "type": "Feature",
  "properties": {
    "iso:country":"US",
    "sg:address":"705 W Saint Georges Ave",
    "sg:city":"Linden",
    "sg:classifiers":[
        {
            "category":"Banks & Credit Unions",
            "subcategory":"Bank",
            "type":"Services"
        }
    ],
    "sg:phone":"+1 908 709 5591",
    "sg:postcode":"07036",
    "sg:province":"NJ",
    "sg:tags":[
        "commercial",
        "saving"
    ],
    "sg:website":"https://www.wachovia.com/?DCMP=KNL-CPS-DS-Directory-0703&HBX_PK=Banks&HBX_OU=71",
    "wof:name":"Wachovia Bank",
    "wof:placetype":"venue"
},
  "geometry": {"coordinates":[-74.270561,40.630049],"type":"Point"}
}