{
  "type": "Feature",
  "properties": {
    "addr:full":"782 Kinderkamack Rd River Edge NJ 07661",
    "addr:housenumber":"782",
    "addr:postcode":"07661",
    "addr:street":"Kinderkamack Rd",
    "iso:country":"US",
    "sg:address":"782 Kinderkamack Rd",
    "sg:city":"River Edge",
    "sg:classifiers":[
        {
            "category":"Professional",
            "subcategory":"Management & Consulting",
            "type":"Services"
        }
    ],
    "sg:phone":"+1 201 261 0700",
    "sg:postcode":"07661",
    "sg:province":"NJ",
    "sg:tags":[
        "consultant",
        "telecommunication"
    ],
    "wof:name":"Gain Communications Inc",
    "wof:placetype":"venue"
},
  "geometry": {"coordinates":[-74.031749,40.934466],"type":"Point"}
}