{
  "type": "Feature",
  "properties": {
    "iso:country":"US",
    "sg:address":"300 Broadacres Dr",
    "sg:city":"Bloomfield",
    "sg:classifiers":[
        {
            "category":"Wholesale",
            "subcategory":"Durable Goods & Equipment",
            "type":"Manufacturing & Wholesale Goods"
        }
    ],
    "sg:phone":"+1 973 338 0300",
    "sg:postcode":"07003",
    "sg:province":"NJ",
    "sg:tags":[
        "importer"
    ],
    "wof:name":"World Finer Foods Inc",
    "wof:placetype":"venue"
},
  "geometry": {"coordinates":[-74.181962,40.838401],"type":"Point"}
}