{
  "type": "Feature",
  "properties": {
    "iso:country":"US",
    "sg:address":"39 S Main St",
    "sg:city":"Medford",
    "sg:classifiers":[
        {
            "category":"Restaurant",
            "type":"Food & Drink"
        }
    ],
    "sg:menulink":"http://www.allmenus.com/nj/medford/270189-braddocks/menu/",
    "sg:phone":"+1 609 654 1604",
    "sg:postcode":"08055",
    "sg:province":"NJ",
    "sg:tags":[
        "american"
    ],
    "wof:name":"Braddock's",
    "wof:placetype":"venue"
},
  "geometry": {"coordinates":[-74.822926,39.898276],"type":"Point"}
}