{
  "type": "Feature",
  "properties": {
    "iso:country":"US",
    "sg:address":"960 Spruce St",
    "sg:city":"Trenton",
    "sg:classifiers":[
        {
            "category":"Restaurant",
            "type":"Food & Drink"
        }
    ],
    "sg:phone":"+1 609 599 4206",
    "sg:postcode":"08648",
    "sg:province":"NJ",
    "sg:tags":[
        "delicatessen"
    ],
    "wof:name":"Pulaski Meat Products",
    "wof:placetype":"venue"
},
  "geometry": {"coordinates":[-74.75068899999999,40.241872],"type":"Point"}
}