{
  "type": "Feature",
  "properties": {
    "addr:full":"28 Gibson Blvd Clark NJ 07066",
    "addr:housenumber":"28",
    "addr:postcode":"07066",
    "addr:street":"Gibson Blvd",
    "iso:country":"US",
    "sg:address":"28 Gibson Blvd",
    "sg:city":"Clark",
    "sg:classifiers":[
        {
            "category":"Banks & Credit Unions",
            "subcategory":"Financial Services",
            "type":"Services"
        }
    ],
    "sg:phone":"+1 732 499 8200",
    "sg:postcode":"07066",
    "sg:province":"NJ",
    "sg:tags":[
        "broker",
        "mortgage"
    ],
    "wof:name":"Sterling National Mortgage Co Inc",
    "wof:placetype":"venue"
},
  "geometry": {"coordinates":[-74.30410000000001,40.624599],"type":"Point"}
}