{
  "type": "Feature",
  "properties": {
    "addr:full":"1275 Bloomfield Ave Fairfield NJ 07004",
    "addr:housenumber":"1275",
    "addr:postcode":"07004",
    "addr:street":"Bloomfield Ave",
    "iso:country":"US",
    "sg:address":"1275 Bloomfield Ave",
    "sg:city":"Fairfield",
    "sg:classifiers":[
        {
            "category":"Professional",
            "subcategory":"Computer Services",
            "type":"Services"
        }
    ],
    "sg:phone":"+1 973 808 4479",
    "sg:postcode":"07004",
    "sg:province":"NJ",
    "sg:tags":[
        "internet"
    ],
    "wof:name":"Hippie Shop LLC",
    "wof:placetype":"venue"
},
  "geometry": {"coordinates":[-74.318907,40.858492],"type":"Point"}
}