{
  "type": "Feature",
  "properties": {
    "iso:country":"US",
    "sg:address":"1544 Irving St",
    "sg:city":"Rahway",
    "sg:classifiers":[
        {
            "category":"Professional",
            "subcategory":"Business Services",
            "type":"Services"
        }
    ],
    "sg:phone":"+1 732 396 1818",
    "sg:postcode":"07065",
    "sg:province":"NJ",
    "sg:tags":[
        "recording",
        "studio"
    ],
    "wof:name":"Leo RECORDS-Cmb Enterprise",
    "wof:placetype":"venue"
},
  "geometry": {"coordinates":[-74.27627099999999,40.608519],"type":"Point"}
}