{
  "type": "Feature",
  "properties": {
    "addr:full":"166 State Rte 31 Flemington NJ 08822",
    "addr:housenumber":"166",
    "addr:postcode":"08822",
    "addr:street":"State Rte 31",
    "iso:country":"US",
    "sg:address":"166 State Rte 31",
    "sg:city":"Flemington",
    "sg:classifiers":[
        {
            "category":"Banks & Credit Unions",
            "subcategory":"Bank",
            "type":"Services"
        }
    ],
    "sg:phone":"+1 908 806 2685",
    "sg:postcode":"08822",
    "sg:province":"NJ",
    "wof:name":"Unitedtrust Bank",
    "wof:placetype":"venue"
},
  "geometry": {"coordinates":[-74.85664199999999,40.528859],"type":"Point"}
}