{
  "type": "Feature",
  "properties": {
    "iso:country":"US",
    "sg:address":"2302 Zion Rd",
    "sg:city":"Northfield",
    "sg:classifiers":[
        {
            "category":"Banks & Credit Unions",
            "subcategory":"Investment Brokerage",
            "type":"Services"
        }
    ],
    "sg:phone":"+1   ",
    "sg:postcode":"08225",
    "sg:province":"NJ",
    "sg:tags":[
        "advisory"
    ],
    "wof:name":"American Express",
    "wof:placetype":"venue"
},
  "geometry": {"coordinates":[-74.56967899999999,39.36889],"type":"Point"}
}