{
  "type": "Feature",
  "properties": {
    "addr:full":"228 Franklin Ave Ste 1 Nutley NJ 07110",
    "addr:housenumber":"228",
    "addr:postcode":"07110",
    "addr:street":"Franklin Ave Ste 1",
    "iso:country":"US",
    "sg:address":"228 Franklin Ave Ste 1",
    "sg:city":"Nutley",
    "sg:classifiers":[
        {
            "category":"Professional",
            "subcategory":"Accounting & Tax Preparation",
            "type":"Services"
        }
    ],
    "sg:phone":"+1 973 661 0048",
    "sg:postcode":"07110",
    "sg:province":"NJ",
    "sg:tags":[
        "accountant"
    ],
    "wof:name":"Marinello J CPA",
    "wof:placetype":"venue"
},
  "geometry": {"coordinates":[-74.16239899999999,40.815201],"type":"Point"}
}