{
  "type": "Feature",
  "properties": {
    "iso:country":"US",
    "sg:address":"20 W State St",
    "sg:city":"Trenton",
    "sg:classifiers":[
        {
            "category":"Building & Trades",
            "subcategory":"Cleaning & Sanitation",
            "type":"Services"
        }
    ],
    "sg:phone":"+1   ",
    "sg:postcode":"08608",
    "sg:province":"NJ",
    "sg:tags":[
        "maintenance"
    ],
    "wof:name":"Mercer Cnty N J Assn For Rtard",
    "wof:placetype":"venue"
},
  "geometry": {"coordinates":[-74.766199,40.220392],"type":"Point"}
}