{
  "type": "Feature",
  "properties": {
    "iso:country":"US",
    "sg:address":"13 Sleepy Hollow Dr",
    "sg:city":"Oak Ridge",
    "sg:classifiers":[
        {
            "category":"Professional",
            "subcategory":"Computer Services",
            "type":"Services"
        }
    ],
    "sg:phone":"+1   ",
    "sg:postcode":"07438",
    "sg:province":"NJ",
    "sg:tags":[
        "related"
    ],
    "wof:name":"Richton Inc",
    "wof:placetype":"venue"
},
  "geometry": {"coordinates":[-74.523749,41.012916],"type":"Point"}
}