{
  "type": "Feature",
  "properties": {
    "addr:full":"570 Broadway Long Branch NJ 07740",
    "addr:housenumber":"570",
    "addr:postcode":"07740",
    "addr:street":"Broadway",
    "iso:country":"US",
    "sg:address":"570 Broadway",
    "sg:city":"Long Branch",
    "sg:classifiers":[
        {
            "category":"Manufacturing",
            "subcategory":"Printing",
            "type":"Manufacturing & Wholesale Goods"
        }
    ],
    "sg:phone":"+1 732 571 3390",
    "sg:postcode":"07740",
    "sg:province":"NJ",
    "sg:tags":[
        "screen"
    ],
    "wof:name":"Stelair Design Corp",
    "wof:placetype":"venue"
},
  "geometry": {"coordinates":[-74.00147200000001,40.299771],"type":"Point"}
}