{
  "type": "Feature",
  "properties": {
    "iso:country":"US",
    "sg:address":"590 Shiloh Pike",
    "sg:city":"Bridgeton",
    "sg:classifiers":[
        {
            "category":"Social Services",
            "type":"Services"
        }
    ],
    "sg:phone":"+1 856 455 4323",
    "sg:postcode":"08302",
    "sg:province":"NJ",
    "sg:tags":[
        "senior",
        "citizen"
    ],
    "wof:name":"Nutrition Project Bridgeton",
    "wof:placetype":"venue"
},
  "geometry": {"coordinates":[-75.264983,39.43991],"type":"Point"}
}