{
  "type": "Feature",
  "properties": {
    "iso:country":"US",
    "sg:address":"351 Fairton Gouldtown Rd",
    "sg:city":"Bridgeton",
    "sg:classifiers":[
        {
            "category":"Organizations",
            "subcategory":"Religious Organization",
            "type":"Services"
        }
    ],
    "sg:phone":"+1 856 451 3435",
    "sg:postcode":"08302",
    "sg:province":"NJ",
    "sg:tags":[
        "clergy"
    ],
    "wof:name":"K Ferguson",
    "wof:placetype":"venue"
},
  "geometry": {"coordinates":[-75.195521,39.406338],"type":"Point"}
}