{
  "type": "Feature",
  "properties": {
    "addr:full":"174 Main St Eatontown NJ 07724",
    "addr:housenumber":"174",
    "addr:postcode":"07724",
    "addr:street":"Main St",
    "iso:country":"US",
    "sg:address":"174 Main St",
    "sg:city":"Eatontown",
    "sg:classifiers":[
        {
            "category":"Travel",
            "subcategory":"Travel Agent",
            "type":"Entertainment"
        }
    ],
    "sg:phone":"+1 732 578 0500",
    "sg:postcode":"07724",
    "sg:province":"NJ",
    "sg:tags":[
        "agency"
    ],
    "wof:name":"June C Spaulding",
    "wof:placetype":"venue"
},
  "geometry": {"coordinates":[-74.05534900000001,40.298594],"type":"Point"}
}