{
  "type": "Feature",
  "properties": {
    "iso:country":"US",
    "sg:address":"111 New Jersey Ave",
    "sg:city":"Absecon",
    "sg:classifiers":[
        {
            "category":"Professional",
            "type":"Services"
        }
    ],
    "sg:phone":"+1 609 677 6834",
    "sg:postcode":"08201",
    "sg:province":"NJ",
    "sg:tags":[
        "establishment"
    ],
    "wof:name":"Anoop Sondhi",
    "wof:placetype":"venue"
},
  "geometry": {"coordinates":[-74.5009,39.424753],"type":"Point"}
}