{
  "type": "Feature",
  "properties": {
    "addr:full":"5 Dickerson Dr Piscataway NJ 08854",
    "addr:housenumber":"5",
    "addr:postcode":"08854",
    "addr:street":"Dickerson Dr",
    "iso:country":"US",
    "sg:address":"5 Dickerson Dr",
    "sg:city":"Piscataway",
    "sg:classifiers":[
        {
            "category":"Professional",
            "subcategory":"Business Services",
            "type":"Services"
        }
    ],
    "sg:phone":"+1   ",
    "sg:postcode":"08854",
    "sg:province":"NJ",
    "wof:name":"Deeptechsketch Technologies",
    "wof:placetype":"venue"
},
  "geometry": {"coordinates":[-74.4766,40.575443],"type":"Point"}
}