{
  "type": "Feature",
  "properties": {
    "iso:country":"US",
    "sg:address":"2291 N 2nd St",
    "sg:city":"Millville",
    "sg:classifiers":[
        {
            "category":"Shopping",
            "subcategory":"Department Store",
            "type":"Retail Goods"
        }
    ],
    "sg:phone":"+1   ",
    "sg:postcode":"08332",
    "sg:province":"NJ",
    "sg:tags":[
        "laboratory",
        "goo",
        "optical"
    ],
    "sg:website":"www.walmart.com",
    "wof:name":"Wal-Mart",
    "wof:placetype":"venue"
},
  "geometry": {"coordinates":[-75.039885,39.426604],"type":"Point"}
}