{
  "type": "Feature",
  "properties": {
    "iso:country":"US",
    "sg:address":"1231 State Rte 166",
    "sg:city":"Toms River",
    "sg:classifiers":[
        {
            "category":"Autos & Motor Vehicles",
            "subcategory":"Auto Supplies",
            "type":"Retail Goods"
        }
    ],
    "sg:phone":"+1   ",
    "sg:postcode":"08753",
    "sg:province":"NJ",
    "wof:name":"Plaza Tire & Auto Serv",
    "wof:placetype":"venue"
},
  "geometry": {"coordinates":[-74.21032599999999,39.9854],"type":"Point"}
}