{
  "type": "Feature",
  "properties": {
    "addr:full":"781 Brick Blvd Brick NJ 08723",
    "addr:housenumber":"781",
    "addr:postcode":"08723",
    "addr:street":"Brick Blvd",
    "iso:country":"US",
    "sg:address":"781 Brick Blvd",
    "sg:city":"Brick",
    "sg:classifiers":[
        {
            "category":"Health Services",
            "subcategory":"Chiropractor",
            "type":"Services"
        }
    ],
    "sg:phone":"+1 732 920 5646",
    "sg:postcode":"08723",
    "sg:province":"NJ",
    "wof:name":"DC Chiropractic Life Center",
    "wof:placetype":"venue"
},
  "geometry": {"coordinates":[-74.13674899999999,40.061371],"type":"Point"}
}