{
  "type": "Feature",
  "properties": {
    "addr:full":"18 Overlook Ave Ste 200 Rochelle Park NJ 07662",
    "addr:housenumber":"18",
    "addr:postcode":"07662",
    "addr:street":"Overlook Ave Ste 200",
    "iso:country":"US",
    "sg:address":"18 Overlook Ave Ste 200",
    "sg:city":"Rochelle Park",
    "sg:classifiers":[
        {
            "category":"Arts & Performance",
            "subcategory":"Arts Center",
            "type":"Entertainment"
        },
        {
            "category":"Arts & Performance",
            "subcategory":"Music",
            "type":"Entertainment"
        }
    ],
    "sg:phone":"+1 866 587 1066",
    "sg:postcode":"07662",
    "sg:province":"NJ",
    "sg:tags":[
        "dj"
    ],
    "sg:website":"www.craigscott.com",
    "wof:name":"Craig Scott Entertainment",
    "wof:placetype":"venue"
},
  "geometry": {"coordinates":[-74.074021,40.911361],"type":"Point"}
}