{
  "type": "Feature",
  "properties": {
    "iso:country":"US",
    "sg:address":"185 Cedar Ln",
    "sg:city":"Teaneck",
    "sg:classifiers":[
        {
            "category":"Health Services",
            "subcategory":"Doctor",
            "type":"Services"
        }
    ],
    "sg:phone":"+1 201 692 1777",
    "sg:postcode":"07666",
    "sg:province":"NJ",
    "sg:tags":[
        "dentists-endodontists"
    ],
    "wof:name":"Jacob Englander",
    "wof:placetype":"venue"
},
  "geometry": {"coordinates":[-74.013321,40.886226],"type":"Point"}
}