{
  "type": "Feature",
  "properties": {
    "addr:full":"652 US Hwy 22 North Plainfield NJ 07060",
    "addr:housenumber":"652",
    "addr:postcode":"07060",
    "addr:street":"Us Hwy 22",
    "iso:country":"US",
    "sg:address":"652 US Hwy 22",
    "sg:city":"North Plainfield",
    "sg:classifiers":[
        {
            "category":"Retail",
            "subcategory":"Auto Rental",
            "type":"Services"
        }
    ],
    "sg:phone":"+1 908 222 7673",
    "sg:postcode":"07060",
    "sg:province":"NJ",
    "sg:tags":[
        "renting",
        "truck",
        "leasing"
    ],
    "wof:name":"U-Haul Co",
    "wof:placetype":"venue"
},
  "geometry": {"coordinates":[-74.43651,40.627644],"type":"Point"}
}