{
  "type": "Feature",
  "properties": {
    "addr:full":"16 Arcadian Way Paramus NJ 07652",
    "addr:housenumber":"16",
    "addr:postcode":"07652",
    "addr:street":"Arcadian Way",
    "iso:country":"US",
    "sg:address":"16 Arcadian Way",
    "sg:city":"Paramus",
    "sg:classifiers":[
        {
            "category":"Parking",
            "type":"Transportation"
        },
        {
            "category":"Manufacturing",
            "subcategory":"Printing",
            "type":"Manufacturing & Wholesale Goods"
        }
    ],
    "sg:phone":"+1 201 291 7878",
    "sg:postcode":"07652",
    "sg:province":"NJ",
    "sg:tags":[
        "attendant",
        "company",
        "publishing"
    ],
    "wof:name":"Parking Survival Experts",
    "wof:placetype":"venue"
},
  "geometry": {"coordinates":[-74.08399300000001,40.923458],"type":"Point"}
}