{
  "type": "Feature",
  "properties": {
    "iso:country":"US",
    "sg:address":"665 Van Houten Ave Ste 4",
    "sg:city":"Clifton",
    "sg:classifiers":[
        {
            "category":"Personal",
            "subcategory":"Barber",
            "type":"Services"
        }
    ],
    "sg:phone":"+1 973 473 6105",
    "sg:postcode":"07013",
    "sg:province":"NJ",
    "wof:name":"Fascination Beauty Salon",
    "wof:placetype":"venue"
},
  "geometry": {"coordinates":[-74.149681,40.858946],"type":"Point"}
}