{
  "type": "Feature",
  "properties": {
    "iso:country":"US",
    "sg:address":"240 US Hwy 46",
    "sg:city":"Dover",
    "sg:classifiers":[
        {
            "category":"Shopping",
            "subcategory":"Florist",
            "type":"Retail Goods"
        }
    ],
    "sg:phone":"+1   ",
    "sg:postcode":"07803",
    "sg:province":"NJ",
    "wof:name":"Retail Flower Shop",
    "wof:placetype":"venue"
},
  "geometry": {"coordinates":[-74.599789,40.879876],"type":"Point"}
}