{
  "type": "Feature",
  "properties": {
    "iso:country":"US",
    "sg:address":"100 Barrack St",
    "sg:city":"Trenton",
    "sg:classifiers":[
        {
            "category":"Organizations",
            "subcategory":"Community Association",
            "type":"Services"
        }
    ],
    "sg:phone":"+1 609 392 1656",
    "sg:postcode":"08608",
    "sg:province":"NJ",
    "wof:name":"Masonic Temple",
    "wof:placetype":"venue"
},
  "geometry": {"coordinates":[-74.768565,40.219048],"type":"Point"}
}