{
  "type": "Feature",
  "properties": {
    "iso:country":"US",
    "sg:address":"115 N Church St",
    "sg:city":"Moorestown",
    "sg:classifiers":[
        {
            "category":"Professional",
            "subcategory":"Lawyer & Legal Services",
            "type":"Services"
        }
    ],
    "sg:phone":"+1 856 273 9569",
    "sg:postcode":"08057",
    "sg:province":"NJ",
    "sg:tags":[
        "attorney"
    ],
    "wof:name":"Jerome A Bacchetti",
    "wof:placetype":"venue"
},
  "geometry": {"coordinates":[-74.95041500000001,39.963446],"type":"Point"}
}