{
  "type": "Feature",
  "properties": {
    "addr:full":"3 32nd St Fair Lawn NJ 07410",
    "addr:housenumber":"3",
    "addr:postcode":"07410",
    "addr:street":"32Nd St",
    "iso:country":"US",
    "sg:address":"3 32nd St",
    "sg:city":"Fair Lawn",
    "sg:classifiers":[
        {
            "category":"Building & Trades",
            "subcategory":"Electrical",
            "type":"Services"
        }
    ],
    "sg:phone":"+1 201 791 1495",
    "sg:postcode":"07410",
    "sg:province":"NJ",
    "sg:tags":[
        "electrical",
        "contractor"
    ],
    "wof:name":"Cianci Security Systems",
    "wof:placetype":"venue"
},
  "geometry": {"coordinates":[-74.104828,40.926209],"type":"Point"}
}