{
  "type": "Feature",
  "properties": {
    "iso:country":"US",
    "sg:address":"10 Woodgate Dr",
    "sg:city":"Monmouth Junction",
    "sg:classifiers":[
        {
            "category":"Health Services",
            "subcategory":"Doctor",
            "type":"Services"
        }
    ],
    "sg:phone":"+1 732 821 4750",
    "sg:postcode":"08852",
    "sg:province":"NJ",
    "sg:tags":[
        "medical"
    ],
    "wof:name":"Stephen J Gordon MD PC",
    "wof:placetype":"venue"
},
  "geometry": {"coordinates":[-74.55413799999999,40.411223],"type":"Point"}
}