{
  "type": "Feature",
  "properties": {
    "iso:country":"US",
    "sg:address":"38 Dumont Pl",
    "sg:city":"Morristown",
    "sg:classifiers":[
        {
            "category":"Banks & Credit Unions",
            "subcategory":"Investment Brokerage",
            "type":"Services"
        }
    ],
    "sg:phone":"+1 973 455 7135",
    "sg:postcode":"07960",
    "sg:province":"NJ",
    "sg:tags":[
        "investing"
    ],
    "wof:name":"Eple Investment Co",
    "wof:placetype":"venue"
},
  "geometry": {"coordinates":[-74.478921,40.79648],"type":"Point"}
}