{
  "type": "Feature",
  "properties": {
    "addr:full":"101 Pompton Ave Cedar Grove NJ 07009",
    "addr:housenumber":"101",
    "addr:postcode":"07009",
    "addr:street":"Pompton Ave",
    "iso:country":"US",
    "sg:address":"101 Pompton Ave",
    "sg:city":"Cedar Grove",
    "sg:classifiers":[
        {
            "category":"Cinema",
            "subcategory":"Movie Theater",
            "type":"Entertainment"
        }
    ],
    "sg:phone":"+1 973 377 4646",
    "sg:postcode":"07009",
    "sg:province":"NJ",
    "wof:name":"Ccg Holdings Inc",
    "wof:placetype":"venue"
},
  "geometry": {"coordinates":[-74.227152,40.836851],"type":"Point"}
}