{
  "type": "Feature",
  "properties": {
    "iso:country":"US",
    "sg:address":"40 Magnolia Ave",
    "sg:city":"Denville",
    "sg:classifiers":[
        {
            "category":"Professional",
            "type":"Services"
        }
    ],
    "sg:phone":"+1   ",
    "sg:postcode":"07834",
    "sg:province":"NJ",
    "wof:name":"Steven Swarts",
    "wof:placetype":"venue"
},
  "geometry": {"coordinates":[-74.494377,40.87663],"type":"Point"}
}