{
  "type": "Feature",
  "properties": {
    "addr:full":"1957 State Rte 35 Seaside Heights NJ 08751",
    "addr:housenumber":"1957",
    "addr:postcode":"08751",
    "addr:street":"State Rte 35;Heights",
    "iso:country":"US",
    "sg:address":"1957 State Rte 35",
    "sg:city":"Seaside Heights",
    "sg:classifiers":[
        {
            "category":"Professional",
            "subcategory":"Lawyer & Legal Services",
            "type":"Services"
        }
    ],
    "sg:phone":"+1 732 793 2226",
    "sg:postcode":"08751",
    "sg:province":"NJ",
    "sg:tags":[
        "attorney"
    ],
    "wof:name":"Frank M Crivelli Atty At Law",
    "wof:placetype":"venue"
},
  "geometry": {"coordinates":[-74.073151,39.95525],"type":"Point"}
}