{
  "type": "Feature",
  "properties": {
    "iso:country":"US",
    "sg:address":"101 New Broadway",
    "sg:city":"Brooklawn",
    "sg:classifiers":[
        {
            "category":"Utilities",
            "subcategory":"Water",
            "type":"Services"
        }
    ],
    "sg:phone":"+1 856 456 2638",
    "sg:postcode":"08030",
    "sg:province":"NJ",
    "sg:tags":[
        "company",
        "sewage"
    ],
    "wof:name":"Brooklawn Water Works",
    "wof:placetype":"venue"
},
  "geometry": {"coordinates":[-75.122472,39.879442],"type":"Point"}
}