{
  "type": "Feature",
  "properties": {
    "iso:country":"US",
    "sg:address":"18 Dogwood Rd",
    "sg:city":"Moorestown",
    "sg:classifiers":[
        {
            "category":"Wholesale",
            "subcategory":"Stationery",
            "type":"Manufacturing & Wholesale Goods"
        }
    ],
    "sg:phone":"+1 856 914 0332",
    "sg:postcode":"08057",
    "sg:province":"NJ",
    "sg:tags":[
        "supply"
    ],
    "wof:name":"Shamrock Sales/Mktg",
    "wof:placetype":"venue"
},
  "geometry": {"coordinates":[-74.918183,39.987594],"type":"Point"}
}