{
  "type": "Feature",
  "properties": {
    "iso:country":"US",
    "sg:address":"2129 State Rte 33",
    "sg:city":"Trenton",
    "sg:classifiers":[
        {
            "category":"Insurance",
            "subcategory":"Insurance Agent",
            "type":"Services"
        }
    ],
    "sg:phone":"+1 609 584 9700",
    "sg:postcode":"08690",
    "sg:province":"NJ",
    "wof:name":"Dominici Insurance & Invstmnt",
    "wof:placetype":"venue"
},
  "geometry": {"coordinates":[-74.644792,40.222536],"type":"Point"}
}