{
  "type": "Feature",
  "properties": {
    "iso:country":"US",
    "sg:address":"6709 Bergenline Pl",
    "sg:city":"West New York",
    "sg:classifiers":[
        {
            "category":"Retail",
            "subcategory":"Photofinishing",
            "type":"Services"
        }
    ],
    "sg:phone":"+1 201 453 2333",
    "sg:postcode":"07093",
    "sg:province":"NJ",
    "sg:tags":[
        "laboratory"
    ],
    "wof:name":"E-Z Photo",
    "wof:placetype":"venue"
},
  "geometry": {"coordinates":[-74.01250400000001,40.793954],"type":"Point"}
}