{
  "type": "Feature",
  "properties": {
    "iso:country":"US",
    "sg:address":"512 Garfield Ave",
    "sg:city":"Linwood",
    "sg:classifiers":[
        {
            "category":"Professional",
            "type":"Services"
        }
    ],
    "sg:phone":"+1   ",
    "sg:postcode":"08221",
    "sg:province":"NJ",
    "wof:name":"Hassons Pool Service LLC",
    "wof:placetype":"venue"
},
  "geometry": {"coordinates":[-74.590183,39.335724],"type":"Point"}
}