{
  "type": "Feature",
  "properties": {
    "iso:country":"US",
    "sg:address":"111 Palisade Ave",
    "sg:city":"Bogota",
    "sg:classifiers":[
        {
            "category":"Freight",
            "type":"Transportation"
        }
    ],
    "sg:phone":"+1 201 342 3265",
    "sg:postcode":"07603",
    "sg:province":"NJ",
    "sg:tags":[
        "operator",
        "local",
        "trucking"
    ],
    "wof:name":"Sy Trucking Inc",
    "wof:placetype":"venue"
},
  "geometry": {"coordinates":[-74.027762,40.870749],"type":"Point"}
}