{
  "type": "Feature",
  "properties": {
    "addr:full":"9 Stites Ave Gloucester City NJ 08030",
    "addr:housenumber":"9",
    "addr:postcode":"08030",
    "addr:street":"Stites Ave",
    "iso:country":"US",
    "sg:address":"9 Stites Ave",
    "sg:city":"Gloucester City",
    "sg:classifiers":[
        {
            "category":"Building & Trades",
            "subcategory":"Construction",
            "type":"Services"
        }
    ],
    "sg:phone":"+1 856 456 8130",
    "sg:postcode":"08030",
    "sg:province":"NJ",
    "sg:tags":[
        "housing"
    ],
    "wof:name":"Bruce Barton Bldr & Remodeler",
    "wof:placetype":"venue"
},
  "geometry": {"coordinates":[-75.118241,39.890522],"type":"Point"}
}