{
  "type": "Feature",
  "properties": {
    "addr:full":"12308 Crystal Ridge Dr Watchung NJ 07069",
    "addr:housenumber":"12308",
    "addr:postcode":"07069",
    "addr:street":"Crystal Ridge Dr",
    "iso:country":"US",
    "sg:address":"12308 Crystal Ridge Dr",
    "sg:city":"Watchung",
    "sg:classifiers":[
        {
            "category":"Professional",
            "type":"Services"
        }
    ],
    "sg:phone":"+1   ",
    "sg:postcode":"07069",
    "sg:province":"NJ",
    "wof:name":"Chiaphua Components Ltd",
    "wof:placetype":"venue"
},
  "geometry": {"coordinates":[-74.42805799999999,40.635506],"type":"Point"}
}