{
  "type": "Feature",
  "properties": {
    "addr:full":"19 State Rte 5 Edgewater NJ 07020",
    "addr:housenumber":"19",
    "addr:postcode":"07020",
    "addr:street":"State Rte 5",
    "iso:country":"US",
    "sg:address":"19 State Rte 5",
    "sg:city":"Edgewater",
    "sg:classifiers":[
        {
            "category":"Retail",
            "subcategory":"Repair Shop",
            "type":"Services"
        }
    ],
    "sg:phone":"+1 201 328 0635",
    "sg:postcode":"07020",
    "sg:province":"NJ",
    "sg:tags":[
        "lock",
        "locksmith"
    ],
    "wof:name":"24 Hour 7 Day Emergency Lcksmt",
    "wof:placetype":"venue"
},
  "geometry": {"coordinates":[-73.97326700000001,40.831734],"type":"Point"}
}