{
  "type": "Feature",
  "properties": {
    "iso:country":"US",
    "sg:address":"911 Valley St",
    "sg:city":"Vauxhall",
    "sg:classifiers":[
        {
            "category":"Wholesale",
            "subcategory":"Machinery & Supplies",
            "type":"Manufacturing & Wholesale Goods"
        }
    ],
    "sg:phone":"+1 908 688 8310",
    "sg:postcode":"07088",
    "sg:province":"NJ",
    "sg:tags":[
        "equipment",
        "resin",
        "dispensing"
    ],
    "wof:name":"Methods Engineering",
    "wof:placetype":"venue"
},
  "geometry": {"coordinates":[-74.288352,40.719683],"type":"Point"}
}