{
  "type": "Feature",
  "properties": {
    "iso:country":"US",
    "sg:address":"6205 Central Ave",
    "sg:city":"Sea Isle City",
    "sg:classifiers":[
        {
            "category":"Building & Trades",
            "subcategory":"Electrical",
            "type":"Services"
        }
    ],
    "sg:phone":"+1 609 263 1444",
    "sg:postcode":"08243",
    "sg:province":"NJ",
    "sg:tags":[
        "electrical",
        "electric",
        "contractor"
    ],
    "wof:name":"Pittaluga's Electric",
    "wof:placetype":"venue"
},
  "geometry": {"coordinates":[-74.704019,39.14235],"type":"Point"}
}