{
  "type": "Feature",
  "properties": {
    "iso:country":"US",
    "sg:address":"31 S Richmond Ave",
    "sg:city":"Atlantic City",
    "sg:classifiers":[
        {
            "category":"Professional",
            "subcategory":"Accounting & Tax Preparation",
            "type":"Services"
        }
    ],
    "sg:phone":"+1 609 345 1228",
    "sg:postcode":"08401",
    "sg:province":"NJ",
    "sg:tags":[
        "return",
        "filing"
    ],
    "wof:name":"Professional Tax Svc",
    "wof:placetype":"venue"
},
  "geometry": {"coordinates":[-74.45928499999999,39.347962],"type":"Point"}
}