{
  "type": "Feature",
  "properties": {
    "iso:country":"US",
    "sg:address":"99 Serpentine Rd",
    "sg:city":"Demarest",
    "sg:classifiers":[
        {
            "category":"Travel",
            "subcategory":"Campground",
            "type":"Entertainment"
        }
    ],
    "sg:phone":"+1 201 784 9047",
    "sg:postcode":"07627",
    "sg:province":"NJ",
    "sg:tags":[
        "trailer"
    ],
    "wof:name":"Whip O Will Campsite",
    "wof:placetype":"venue"
},
  "geometry": {"coordinates":[-73.965698,40.955499],"type":"Point"}
}