{
  "type": "Feature",
  "properties": {
    "addr:full":"170 State St Hackensack NJ 07601",
    "addr:housenumber":"170",
    "addr:postcode":"07601",
    "addr:street":"State St",
    "iso:country":"US",
    "sg:address":"170 State St",
    "sg:city":"Hackensack",
    "sg:classifiers":[
        {
            "category":"Professional",
            "subcategory":"Lawyer & Legal Services",
            "type":"Services"
        }
    ],
    "sg:phone":"+1 201 343 0200",
    "sg:postcode":"07601",
    "sg:province":"NJ",
    "wof:name":"Immigrants United Services",
    "wof:placetype":"venue"
},
  "geometry": {"coordinates":[-74.04444599999999,40.883712],"type":"Point"}
}