{
  "type": "Feature",
  "properties": {
    "iso:country":"US",
    "sg:address":"10 McKinley St",
    "sg:city":"Linden",
    "sg:classifiers":[
        {
            "category":"Manufacturing",
            "subcategory":"Textiles",
            "type":"Manufacturing & Wholesale Goods"
        },
        {
            "category":"Manufacturing",
            "subcategory":"Printing",
            "type":"Manufacturing & Wholesale Goods"
        }
    ],
    "sg:phone":"+1 908 925 3773",
    "sg:postcode":"07036",
    "sg:province":"NJ",
    "sg:tags":[
        "plant",
        "fiber",
        "screen",
        "p",
        "finishing",
        "silk",
        "cotton"
    ],
    "sg:website":"www.uniquescreenprinting.com",
    "wof:name":"Unique Screen Printing Corp",
    "wof:placetype":"venue"
},
  "geometry": {"coordinates":[-74.235298,40.646768],"type":"Point"}
}