{
  "type": "Feature",
  "properties": {
    "addr:full":"18 Quail Run Warren NJ 07059",
    "addr:housenumber":"18",
    "addr:postcode":"07059",
    "addr:street":"Quail Run",
    "iso:country":"US",
    "sg:address":"18 Quail Run",
    "sg:city":"Warren",
    "sg:classifiers":[
        {
            "category":"Wholesale",
            "subcategory":"Groceries",
            "type":"Manufacturing & Wholesale Goods"
        }
    ],
    "sg:phone":"+1 732 563 6930",
    "sg:postcode":"07059",
    "sg:province":"NJ",
    "wof:name":"Newark Mobile Inc",
    "wof:placetype":"venue"
},
  "geometry": {"coordinates":[-74.508876,40.61398],"type":"Point"}
}