{
  "type": "Feature",
  "properties": {
    "addr:full":"130 Skyline Dr Ste 16 Wanaque NJ 07456",
    "addr:housenumber":"130",
    "addr:postcode":"07456",
    "addr:street":"Skyline Dr Ste 16",
    "iso:country":"US",
    "sg:address":"130 Skyline Dr Ste 16",
    "sg:city":"Wanaque",
    "sg:classifiers":[
        {
            "category":"Building & Trades",
            "subcategory":"Construction",
            "type":"Services"
        }
    ],
    "sg:phone":"+1 973 835 0128",
    "sg:postcode":"07456",
    "sg:province":"NJ",
    "sg:tags":[
        "contractor"
    ],
    "wof:name":"Skyview Builders Inc",
    "wof:placetype":"venue"
},
  "geometry": {"coordinates":[-74.248942,41.03675],"type":"Point"}
}