{
  "type": "Feature",
  "properties": {
    "addr:full":"522 Central Ave Jersey City NJ 07307",
    "addr:housenumber":"522",
    "addr:postcode":"07307",
    "addr:street":"Central Ave",
    "iso:country":"US",
    "sg:address":"522 Central Ave",
    "sg:city":"Jersey City",
    "sg:classifiers":[
        {
            "category":"Health Services",
            "subcategory":"Optometrist",
            "type":"Services"
        }
    ],
    "sg:phone":"+1 201 217 3091",
    "sg:postcode":"07307",
    "sg:province":"NJ",
    "wof:name":"Khalid Sawaged DO",
    "wof:placetype":"venue"
},
  "geometry": {"coordinates":[-74.044906,40.752321],"type":"Point"}
}