{
  "type": "Feature",
  "properties": {
    "addr:full":"452 New Providence Rd Mountainside NJ 07092",
    "addr:housenumber":"452",
    "addr:postcode":"07092",
    "addr:street":"New Providence Rd",
    "iso:country":"US",
    "sg:address":"452 New Providence Rd",
    "sg:city":"Mountainside",
    "sg:classifiers":[
        {
            "category":"Building & Trades",
            "subcategory":"Construction",
            "type":"Services"
        }
    ],
    "sg:phone":"+1 908 233 0841",
    "sg:postcode":"07092",
    "sg:province":"NJ",
    "sg:tags":[
        "house"
    ],
    "wof:name":"Hall Building Corp",
    "wof:placetype":"venue"
},
  "geometry": {"coordinates":[-74.372316,40.682659],"type":"Point"}
}