{
  "type": "Feature",
  "properties": {
    "addr:full":"3009 State Route 10 Morris Plains NJ 07950",
    "addr:housenumber":"3009",
    "addr:postcode":"07950",
    "addr:street":"State Route 10",
    "iso:country":"US",
    "sg:address":"3009 State Route 10",
    "sg:city":"Morris Plains",
    "sg:classifiers":[
        {
            "category":"Retail",
            "subcategory":"Veterinary Services",
            "type":"Services"
        }
    ],
    "sg:phone":"+1 973 366 2568",
    "sg:postcode":"07950",
    "sg:province":"NJ",
    "sg:tags":[
        "veterinarian"
    ],
    "wof:name":"Animal Clinic Pet Supply",
    "wof:placetype":"venue"
},
  "geometry": {"coordinates":[-74.497398,40.862202],"type":"Point"}
}