{
  "type": "Feature",
  "properties": {
    "addr:full":"316 Monroe St Carlstadt NJ 07072",
    "addr:housenumber":"316",
    "addr:postcode":"07072",
    "addr:street":"Monroe St",
    "iso:country":"US",
    "sg:address":"316 Monroe St",
    "sg:city":"Carlstadt",
    "sg:classifiers":[
        {
            "category":"Professional",
            "subcategory":"Art Services",
            "type":"Services"
        }
    ],
    "sg:phone":"+1   ",
    "sg:postcode":"07072",
    "sg:province":"NJ",
    "sg:tags":[
        "graphic",
        "design"
    ],
    "wof:name":"APV Communications Inc",
    "wof:placetype":"venue"
},
  "geometry": {"coordinates":[-74.095665,40.839121],"type":"Point"}
}