{
  "type": "Feature",
  "properties": {
    "addr:full":"764 Palisade Ave Teaneck NJ 07666",
    "addr:housenumber":"764",
    "addr:postcode":"07666",
    "addr:street":"Palisade Ave",
    "iso:country":"US",
    "sg:address":"764 Palisade Ave",
    "sg:city":"Teaneck",
    "sg:classifiers":[
        {
            "category":"Professional",
            "subcategory":"Computer Services",
            "type":"Services"
        }
    ],
    "sg:phone":"+1 201 530 9885",
    "sg:postcode":"07666",
    "sg:province":"NJ",
    "sg:tags":[
        "related"
    ],
    "wof:name":"Interactive Computing Corp",
    "wof:placetype":"venue"
},
  "geometry": {"coordinates":[-74.01966299999999,40.886599],"type":"Point"}
}