{
  "type": "Feature",
  "properties": {
    "addr:full":"286 Barrow St Jersey City NJ 07302",
    "addr:housenumber":"286",
    "addr:postcode":"07302",
    "addr:street":"Barrow St",
    "iso:country":"US",
    "sg:address":"286 Barrow St",
    "sg:city":"Jersey City",
    "sg:classifiers":[
        {
            "category":"Professional",
            "subcategory":"Advertising",
            "type":"Services"
        }
    ],
    "sg:phone":"+1 201 938 0592",
    "sg:postcode":"07302",
    "sg:province":"NJ",
    "sg:tags":[
        "design"
    ],
    "wof:name":"Lenok Designs Inc",
    "wof:placetype":"venue"
},
  "geometry": {"coordinates":[-74.045992,40.718298],"type":"Point"}
}