{
  "type": "Feature",
  "properties": {
    "iso:country":"US",
    "sg:address":"265 Garden Rd",
    "sg:city":"Elmer",
    "sg:classifiers":[
        {
            "category":"Manufacturing",
            "subcategory":"Retail Goods",
            "type":"Manufacturing & Wholesale Goods"
        },
        {
            "category":"Wholesale",
            "subcategory":"Sporting Goods",
            "type":"Manufacturing & Wholesale Goods"
        }
    ],
    "sg:phone":"+1 856 358 6016",
    "sg:postcode":"08318",
    "sg:province":"NJ",
    "sg:tags":[
        "marking",
        "golf",
        "course",
        "mfg",
        "devices",
        "equipment"
    ],
    "wof:name":"Fairway Products Co",
    "wof:placetype":"venue"
},
  "geometry": {"coordinates":[-75.143339,39.538642],"type":"Point"}
}