{
  "type": "Feature",
  "properties": {
    "iso:country":"US",
    "sg:address":"105 Waterway Rd",
    "sg:city":"Ocean City",
    "sg:classifiers":[
        {
            "category":"Marine",
            "type":"Transportation"
        }
    ],
    "sg:phone":"+1 609 391 9878",
    "sg:postcode":"08226",
    "sg:province":"NJ",
    "sg:tags":[
        "towing"
    ],
    "wof:name":"Boat US Towing",
    "wof:placetype":"venue"
},
  "geometry": {"coordinates":[-74.613985,39.256712],"type":"Point"}
}