{
  "type": "Feature",
  "properties": {
    "iso:country":"US",
    "sg:address":"80 New Bridge Rd",
    "sg:city":"Bergenfield",
    "sg:classifiers":[
        {
            "category":"Food & Beverages",
            "subcategory":"Groceries & Convenience Stores",
            "type":"Retail Goods"
        }
    ],
    "sg:phone":"+1   ",
    "sg:postcode":"07621",
    "sg:province":"NJ",
    "sg:tags":[
        "pharmacy"
    ],
    "sg:website":"www.pathmark.com",
    "wof:name":"Pathmark",
    "wof:placetype":"venue"
},
  "geometry": {"coordinates":[-74.00175400000001,40.913978],"type":"Point"}
}