{
  "type": "Feature",
  "properties": {
    "addr:full":"28 Heath Dr Neptune NJ 07753",
    "addr:housenumber":"28",
    "addr:postcode":"07753",
    "addr:street":"Heath Dr",
    "iso:country":"US",
    "sg:address":"28 Heath Dr",
    "sg:city":"Neptune",
    "sg:classifiers":[
        {
            "category":"Building & Trades",
            "subcategory":"Construction",
            "type":"Services"
        }
    ],
    "sg:phone":"+1 732 895 4504",
    "sg:postcode":"07753",
    "sg:province":"NJ",
    "sg:tags":[
        "contractor"
    ],
    "wof:name":"USA Spatafora",
    "wof:placetype":"venue"
},
  "geometry": {"coordinates":[-74.062252,40.216613],"type":"Point"}
}