{
  "type": "Feature",
  "properties": {
    "addr:full":"196 Eyland Ave Succasunna NJ 07876",
    "addr:housenumber":"196",
    "addr:postcode":"07876",
    "addr:street":"Eyland Ave",
    "iso:country":"US",
    "sg:address":"196 Eyland Ave",
    "sg:city":"Succasunna",
    "sg:classifiers":[
        {
            "category":"Professional",
            "subcategory":"Management & Consulting",
            "type":"Services"
        }
    ],
    "sg:phone":"+1   ",
    "sg:postcode":"07876",
    "sg:province":"NJ",
    "wof:name":"Mm Consulting",
    "wof:placetype":"venue"
},
  "geometry": {"coordinates":[-74.656094,40.848682],"type":"Point"}
}