{
  "type": "Feature",
  "properties": {
    "addr:full":"2503 Bergenline Ave Union City NJ 07087",
    "addr:housenumber":"2503",
    "addr:postcode":"07087",
    "addr:street":"Bergenline Ave",
    "iso:country":"US",
    "sg:address":"2503 Bergenline Ave",
    "sg:city":"Union City",
    "sg:classifiers":[
        {
            "category":"Restaurant",
            "type":"Food & Drink"
        }
    ],
    "sg:phone":"+1 201 770 9993",
    "sg:postcode":"07087",
    "sg:province":"NJ",
    "wof:name":"Esperanza's Ecuadorian Food",
    "wof:placetype":"venue"
},
  "geometry": {"coordinates":[-74.03182700000001,40.76883],"type":"Point"}
}