{
  "type": "Feature",
  "properties": {
    "addr:full":"194 Avenue L Newark NJ 07105",
    "addr:housenumber":"194",
    "addr:postcode":"07105",
    "addr:street":"Avenue L",
    "iso:country":"US",
    "sg:address":"194 Avenue L",
    "sg:city":"Newark",
    "sg:classifiers":[
        {
            "category":"Building & Trades",
            "subcategory":"Locksmith",
            "type":"Services"
        }
    ],
    "sg:phone":"+1 888 239 3903",
    "sg:postcode":"07105",
    "sg:province":"NJ",
    "sg:tags":[
        "key"
    ],
    "wof:name":"AAA Emergency Locksmith",
    "wof:placetype":"venue"
},
  "geometry": {"coordinates":[-74.142684,40.723222],"type":"Point"}
}