{
  "type": "Feature",
  "properties": {
    "addr:full":"224 Passaic Ave Fairfield NJ 07004",
    "addr:housenumber":"224",
    "addr:postcode":"07004",
    "addr:street":"Passaic Ave",
    "iso:country":"US",
    "sg:address":"224 Passaic Ave",
    "sg:city":"Fairfield",
    "sg:classifiers":[
        {
            "category":"Manufacturing",
            "subcategory":"Tools & Machinery",
            "type":"Manufacturing & Wholesale Goods"
        }
    ],
    "sg:phone":"+1 973 227 6300",
    "sg:postcode":"07004",
    "sg:province":"NJ",
    "sg:tags":[
        "packaging"
    ],
    "sg:website":"www.heislerind.com",
    "wof:name":"Heisler Machine & Tool Co",
    "wof:placetype":"venue"
},
  "geometry": {"coordinates":[-74.27171800000001,40.87916],"type":"Point"}
}