{
  "type": "Feature",
  "properties": {
    "iso:country":"US",
    "sg:address":"375 Market St",
    "sg:city":"Elmwood Park",
    "sg:classifiers":[
        {
            "category":"Restaurant",
            "type":"Food & Drink"
        }
    ],
    "sg:phone":"+1 201 796 6641",
    "sg:postcode":"07407",
    "sg:province":"NJ",
    "wof:name":"Elmwood Park Diner",
    "wof:placetype":"venue"
},
  "geometry": {"coordinates":[-74.114403,40.899502],"type":"Point"}
}