{
  "type": "Feature",
  "properties": {
    "addr:full":"89 Highland Ave Harrington Park NJ 07640",
    "addr:housenumber":"89",
    "addr:postcode":"07640",
    "addr:street":"Highland Ave",
    "iso:country":"US",
    "sg:address":"89 Highland Ave",
    "sg:city":"Harrington Park",
    "sg:classifiers":[
        {
            "category":"Professional",
            "subcategory":"Accounting & Tax Preparation",
            "type":"Services"
        }
    ],
    "sg:phone":"+1 201 768 1658",
    "sg:postcode":"07640",
    "sg:province":"NJ",
    "wof:name":"Joanne",
    "wof:placetype":"venue"
},
  "geometry": {"coordinates":[-73.970837,40.987503],"type":"Point"}
}