{
  "type": "Feature",
  "properties": {
    "iso:country":"US",
    "sg:address":"1012 Mantua Pike",
    "sg:city":"Woodbury Heights",
    "sg:classifiers":[
        {
            "category":"Real Estate",
            "subcategory":"Real Estate Agent",
            "type":"Services"
        }
    ],
    "sg:phone":"+1 609 299 7800",
    "sg:postcode":"08096",
    "sg:province":"NJ",
    "wof:name":"Premier Realty",
    "wof:placetype":"venue"
},
  "geometry": {"coordinates":[-75.165975,39.8101],"type":"Point"}
}