{
  "type": "Feature",
  "properties": {
    "addr:full":"325 Anchor Ave Beachwood NJ 08722",
    "addr:housenumber":"325",
    "addr:postcode":"08722",
    "addr:street":"Anchor Ave",
    "iso:country":"US",
    "sg:address":"325 Anchor Ave",
    "sg:city":"Beachwood",
    "sg:classifiers":[
        {
            "category":"Building & Trades",
            "subcategory":"Plumbing",
            "type":"Services"
        }
    ],
    "sg:phone":"+1 732 341 4205",
    "sg:postcode":"08722",
    "sg:province":"NJ",
    "sg:tags":[
        "contractor"
    ],
    "wof:name":"Quality Plumbing/Htg",
    "wof:placetype":"venue"
},
  "geometry": {"coordinates":[-74.19156599999999,39.935954],"type":"Point"}
}