{
  "type": "Feature",
  "properties": {
    "addr:full":"Jersey Gardens Mall 651 Kapkowski Road Elizabeth NJ 07201",
    "addr:housenumber":"651",
    "addr:postcode":"07201",
    "addr:street":"Jersey Gardens;Kapkowski Road",
    "iso:country":"US",
    "sg:address":"Jersey Gardens Mall 651 Kapkowski Road",
    "sg:city":"Elizabeth",
    "sg:classifiers":[
        {
            "category":"Restaurant",
            "type":"Food & Drink"
        }
    ],
    "sg:phone":"+1 908 282 4813",
    "sg:postcode":"07201",
    "sg:province":"NJ",
    "sg:website":"www.chilis.com",
    "wof:name":"Chili's",
    "wof:placetype":"venue"
},
  "geometry": {"coordinates":[-74.17449999999999,40.662569],"type":"Point"}
}