{
  "type": "Feature",
  "properties": {
    "iso:country":"US",
    "sg:address":"250 Tilton Rd",
    "sg:city":"Pleasantville",
    "sg:classifiers":[
        {
            "category":"Home & Garden",
            "subcategory":"Furniture",
            "type":"Retail Goods"
        }
    ],
    "sg:phone":"+1   ",
    "sg:postcode":"08232",
    "sg:province":"NJ",
    "sg:tags":[
        "discount",
        "brass",
        "bed",
        "mattress"
    ],
    "wof:name":"Mattress Giant Corporation",
    "wof:placetype":"venue"
},
  "geometry": {"coordinates":[-74.539421,39.381483],"type":"Point"}
}