{
  "type": "Feature",
  "properties": {
    "addr:full":"18 McDermott Pl Bergenfield NJ 07621",
    "addr:housenumber":"18",
    "addr:postcode":"07621",
    "addr:street":"Mcdermott Pl",
    "iso:country":"US",
    "sg:address":"18 McDermott Pl",
    "sg:city":"Bergenfield",
    "sg:classifiers":[
        {
            "category":"Retail",
            "subcategory":"Auto Repair",
            "type":"Services"
        }
    ],
    "sg:phone":"+1 201 385 7104",
    "sg:postcode":"07621",
    "sg:province":"NJ",
    "sg:tags":[
        "repairing",
        "automobile"
    ],
    "wof:name":"S & I Auto Repair",
    "wof:placetype":"venue"
},
  "geometry": {"coordinates":[-73.99900100000001,40.916801],"type":"Point"}
}