{
  "type": "Feature",
  "properties": {
    "iso:country":"US",
    "sg:address":"260 Chase Ave",
    "sg:city":"Lyndhurst",
    "sg:classifiers":[
        {
            "category":"Building & Trades",
            "subcategory":"Construction",
            "type":"Services"
        }
    ],
    "sg:phone":"+1 201 939 1304",
    "sg:postcode":"07071",
    "sg:province":"NJ",
    "sg:tags":[
        "contractor"
    ],
    "wof:name":"Anc Construction Inc",
    "wof:placetype":"venue"
},
  "geometry": {"coordinates":[-74.120468,40.811042],"type":"Point"}
}