{
  "type": "Feature",
  "properties": {
    "addr:full":"450 Schuyler Ave Kearny NJ 07032",
    "addr:housenumber":"450",
    "addr:postcode":"07032",
    "addr:street":"Schuyler Ave",
    "iso:country":"US",
    "sg:address":"450 Schuyler Ave",
    "sg:city":"Kearny",
    "sg:classifiers":[
        {
            "category":"Manufacturing",
            "subcategory":"Chemicals & Compounds",
            "type":"Manufacturing & Wholesale Goods"
        }
    ],
    "sg:phone":"+1 201 997 1880",
    "sg:postcode":"07032",
    "sg:province":"NJ",
    "sg:tags":[
        "cellulose",
        "sheet",
        "acetate",
        "film",
        "mfg"
    ],
    "wof:name":"King Finishing",
    "wof:placetype":"venue"
},
  "geometry": {"coordinates":[-74.140259,40.763588],"type":"Point"}
}