{
  "type": "Feature",
  "properties": {
    "addr:full":"200 Sylvan Ave Englewood Cliffs NJ 07632",
    "addr:housenumber":"200",
    "addr:postcode":"07632",
    "addr:street":"Sylvan Ave",
    "iso:country":"US",
    "sg:address":"200 Sylvan Ave",
    "sg:city":"Englewood Cliffs",
    "sg:classifiers":[
        {
            "category":"Sports & Exercise",
            "subcategory":"Gym",
            "type":"Entertainment"
        }
    ],
    "sg:phone":"+1 201 541 1919",
    "sg:postcode":"07632",
    "sg:province":"NJ",
    "sg:tags":[
        "facility",
        "club",
        "gymnasium",
        "health",
        "fitness",
        "studio",
        "physical"
    ],
    "sg:website":"www.thetrainingzone.com",
    "wof:name":"Training Zone",
    "wof:placetype":"venue"
},
  "geometry": {"coordinates":[-73.95466,40.871666],"type":"Point"}
}