{
  "type": "Feature",
  "properties": {
    "iso:country":"US",
    "sg:address":"38 E 33rd St",
    "sg:city":"Paterson",
    "sg:classifiers":[
        {
            "category":"Banks & Credit Unions",
            "subcategory":"Bank",
            "type":"Services"
        }
    ],
    "sg:phone":"+1 973 977 6060",
    "sg:postcode":"07514",
    "sg:province":"NJ",
    "sg:tags":[
        "depository",
        "banking",
        "check",
        "cashing"
    ],
    "wof:name":"Garden State Check Cashing Svc",
    "wof:placetype":"venue"
},
  "geometry": {"coordinates":[-74.141319,40.921272],"type":"Point"}
}