{
  "type": "Feature",
  "properties": {
    "iso:country":"US",
    "sg:address":"1504 West Ave",
    "sg:city":"Phillipsburg",
    "sg:classifiers":[
        {
            "category":"Restaurant",
            "type":"Food & Drink"
        }
    ],
    "sg:phone":"+1   ",
    "sg:postcode":"08865",
    "sg:province":"NJ",
    "sg:tags":[
        "eating"
    ],
    "wof:name":"Almond Tree",
    "wof:placetype":"venue"
},
  "geometry": {"coordinates":[-75.16683,40.658253],"type":"Point"}
}