{
  "type": "Feature",
  "properties": {
    "iso:country":"US",
    "sg:address":"226 S White Horse Pike",
    "sg:city":"Audubon",
    "sg:classifiers":[
        {
            "category":"Manufacturing",
            "subcategory":"Chemicals & Compounds",
            "type":"Manufacturing & Wholesale Goods"
        },
        {
            "category":"Home & Garden",
            "subcategory":"Home Furnishings",
            "type":"Retail Goods"
        },
        {
            "category":"Home & Garden",
            "subcategory":"Furniture",
            "type":"Retail Goods"
        }
    ],
    "sg:phone":"+1 856 547 4025",
    "sg:postcode":"08106",
    "sg:province":"NJ",
    "sg:tags":[
        "wicker",
        "product",
        "store",
        "house"
    ],
    "wof:name":"Wicker Dynasty",
    "wof:placetype":"venue"
},
  "geometry": {"coordinates":[-75.0672,39.892502],"type":"Point"}
}