{
  "type": "Feature",
  "properties": {
    "iso:country":"US",
    "sg:address":"1500 Saint Georges Ave",
    "sg:city":"Avenel",
    "sg:classifiers":[
        {
            "category":"Real Estate",
            "subcategory":"Real Estate Agent",
            "type":"Services"
        }
    ],
    "sg:phone":"+1   ",
    "sg:postcode":"07001",
    "sg:province":"NJ",
    "wof:name":"Sra Realty LLC",
    "wof:placetype":"venue"
},
  "geometry": {"coordinates":[-74.290764,40.590244],"type":"Point"}
}