{
  "type": "Feature",
  "properties": {
    "addr:full":"203 Livingston St Northvale NJ 07647",
    "addr:housenumber":"203",
    "addr:postcode":"07647",
    "addr:street":"Livingston St",
    "iso:country":"US",
    "sg:address":"203 Livingston St",
    "sg:city":"Northvale",
    "sg:classifiers":[
        {
            "category":"Restaurant",
            "type":"Food & Drink"
        }
    ],
    "sg:phone":"+1 201 750 2626",
    "sg:postcode":"07647",
    "sg:province":"NJ",
    "sg:tags":[
        "eating"
    ],
    "wof:name":"World Sushi Catering Inc",
    "wof:placetype":"venue"
},
  "geometry": {"coordinates":[-73.948567,41.007674],"type":"Point"}
}