{
  "type": "Feature",
  "properties": {
    "iso:country":"US",
    "sg:address":"1110 Delsea Dr",
    "sg:city":"Westville",
    "sg:classifiers":[
        {
            "category":"Deli",
            "type":"Food & Drink"
        },
        {
            "category":"Food & Beverages",
            "subcategory":"Bakery",
            "type":"Retail Goods"
        }
    ],
    "sg:phone":"+1 856 579 4265",
    "sg:postcode":"08093",
    "sg:province":"NJ",
    "sg:tags":[
        "sandwich"
    ],
    "wof:name":"Dacostas Variety Deli",
    "wof:placetype":"venue"
},
  "geometry": {"coordinates":[-75.125299,39.850152],"type":"Point"}
}