{
  "type": "Feature",
  "properties": {
    "iso:country":"US",
    "sg:address":"780 State Rte 10",
    "sg:city":"Randolph",
    "sg:classifiers":[
        {
            "category":"Government",
            "subcategory":"Fire Station",
            "type":"Public Place"
        }
    ],
    "sg:phone":"+1 973 584 1235",
    "sg:postcode":"07869",
    "sg:province":"NJ",
    "sg:tags":[
        "department"
    ],
    "wof:name":"Mount Freedom Fire Dept",
    "wof:placetype":"venue"
},
  "geometry": {"coordinates":[-74.586851,40.860964],"type":"Point"}
}