{
  "type": "Feature",
  "properties": {
    "iso:country":"US",
    "sg:address":"1911 Brunswick Ave",
    "sg:city":"Lawrenceville",
    "sg:classifiers":[
        {
            "category":"Shopping",
            "subcategory":"Musical Instruments",
            "type":"Retail Goods"
        }
    ],
    "sg:phone":"+1 609 599 2700",
    "sg:postcode":"08648",
    "sg:province":"NJ",
    "sg:tags":[
        "organs"
    ],
    "wof:name":"Altenburg Piano House",
    "wof:placetype":"venue"
},
  "geometry": {"coordinates":[-74.736099,40.250425],"type":"Point"}
}