{
  "type": "Feature",
  "properties": {
    "addr:full":"251 Chambersbridge Rd Brick NJ 08723",
    "addr:housenumber":"251",
    "addr:postcode":"08723",
    "addr:street":"Chambersbridge Rd",
    "iso:country":"US",
    "sg:address":"251 Chambersbridge Rd",
    "sg:city":"Brick",
    "sg:classifiers":[
        {
            "category":"Retail",
            "subcategory":"Veterinary Services",
            "type":"Services"
        }
    ],
    "sg:phone":"+1 732 477 9440",
    "sg:postcode":"08723",
    "sg:province":"NJ",
    "sg:tags":[
        "veterinarian"
    ],
    "wof:name":"Brick Town Veterinary Hospital",
    "wof:placetype":"venue"
},
  "geometry": {"coordinates":[-74.14882900000001,40.07026],"type":"Point"}
}