{
  "type": "Feature",
  "properties": {
    "iso:country":"US",
    "sg:address":"59 Cedar Lake Rd",
    "sg:city":"Blairstown",
    "sg:classifiers":[
        {
            "category":"Retail",
            "subcategory":"Animal Services",
            "type":"Services"
        }
    ],
    "sg:phone":"+1 908 362 6006",
    "sg:postcode":"07825",
    "sg:province":"NJ",
    "sg:tags":[
        "pet",
        "crematory",
        "cemetery"
    ],
    "wof:name":"Blairstown Pet Cemetery",
    "wof:placetype":"venue"
},
  "geometry": {"coordinates":[-74.97358699999999,40.975708],"type":"Point"}
}