{
  "type": "Feature",
  "properties": {
    "iso:country":"US",
    "sg:address":"222 Clifton Ave",
    "sg:city":"Lakewood",
    "sg:classifiers":[
        {
            "category":"Food & Beverages",
            "subcategory":"Specialty",
            "type":"Retail Goods"
        }
    ],
    "sg:phone":"+1 732 364 5877",
    "sg:postcode":"08701",
    "sg:province":"NJ",
    "sg:tags":[
        "group",
        "health",
        "diet"
    ],
    "wof:name":"Goodman Health Foods",
    "wof:placetype":"venue"
},
  "geometry": {"coordinates":[-74.214845,40.092878],"type":"Point"}
}