{
  "type": "Feature",
  "properties": {
    "iso:country":"US",
    "sg:address":"401 Hackensack Ave",
    "sg:city":"Hackensack",
    "sg:classifiers":[
        {
            "category":"Wholesale",
            "subcategory":"Drugs",
            "type":"Manufacturing & Wholesale Goods"
        },
        {
            "category":"Manufacturing",
            "subcategory":"Chemicals & Compounds",
            "type":"Manufacturing & Wholesale Goods"
        }
    ],
    "sg:phone":"+1 201 342 6002",
    "sg:postcode":"07601",
    "sg:province":"NJ",
    "sg:tags":[
        "pharmaceutical",
        "product"
    ],
    "wof:name":"Tanabe Seiyaku Co Ltd",
    "wof:placetype":"venue"
},
  "geometry": {"coordinates":[-74.033342,40.910774],"type":"Point"}
}