{
  "type": "Feature",
  "properties": {
    "addr:full":"52 Lake Dr Howell NJ 07731",
    "addr:housenumber":"52",
    "addr:postcode":"07731",
    "addr:street":"Lake Dr",
    "iso:country":"US",
    "sg:address":"52 Lake Dr",
    "sg:city":"Howell",
    "sg:classifiers":[
        {
            "category":"Building & Trades",
            "subcategory":"Construction",
            "type":"Services"
        }
    ],
    "sg:phone":"+1 732 364 9783",
    "sg:postcode":"07731",
    "sg:province":"NJ",
    "sg:tags":[
        "contractor"
    ],
    "wof:name":"Mobile Home Contractors",
    "wof:placetype":"venue"
},
  "geometry": {"coordinates":[-74.24843199999999,40.144128],"type":"Point"}
}