{
  "type": "Feature",
  "properties": {
    "addr:full":"348 96th St Stone Harbor NJ 08247",
    "addr:housenumber":"348",
    "addr:postcode":"08247",
    "addr:street":"96Th St",
    "iso:country":"US",
    "sg:address":"348 96th St",
    "sg:city":"Stone Harbor",
    "sg:classifiers":[
        {
            "category":"Personal",
            "subcategory":"Beauty Salon",
            "type":"Services"
        }
    ],
    "sg:phone":"+1 609 231 3902",
    "sg:postcode":"08247",
    "sg:province":"NJ",
    "sg:tags":[
        "manicuring"
    ],
    "wof:name":"M Ocean Nails",
    "wof:placetype":"venue"
},
  "geometry": {"coordinates":[-74.763147,39.055837],"type":"Point"}
}