{
  "type": "Feature",
  "properties": {
    "addr:full":"198 Hilton Ave Bayville NJ 08721",
    "addr:housenumber":"198",
    "addr:postcode":"08721",
    "addr:street":"Hilton Ave",
    "iso:country":"US",
    "sg:address":"198 Hilton Ave",
    "sg:city":"Bayville",
    "sg:classifiers":[
        {
            "category":"Manufacturing",
            "subcategory":"Watercraft",
            "type":"Manufacturing & Wholesale Goods"
        }
    ],
    "sg:phone":"+1 732 269 1180",
    "sg:postcode":"08721",
    "sg:province":"NJ",
    "sg:tags":[
        "builder",
        "boat"
    ],
    "wof:name":"Henriques Yachts Inc",
    "wof:placetype":"venue"
},
  "geometry": {"coordinates":[-74.17564900000001,39.90658],"type":"Point"}
}