{
  "type": "Feature",
  "properties": {
    "addr:full":"21 Heron Dr Marlboro NJ 07746",
    "addr:housenumber":"21",
    "addr:postcode":"07746",
    "addr:street":"Heron Dr",
    "iso:country":"US",
    "sg:address":"21 Heron Dr",
    "sg:city":"Marlboro",
    "sg:classifiers":[
        {
            "category":"Freight",
            "type":"Transportation"
        }
    ],
    "sg:phone":"+1 732 431 9513",
    "sg:postcode":"07746",
    "sg:province":"NJ",
    "sg:tags":[
        "operator",
        "local",
        "trucking"
    ],
    "wof:name":"Frank Lowry",
    "wof:placetype":"venue"
},
  "geometry": {"coordinates":[-74.267967,40.309978],"type":"Point"}
}