{
  "type": "Feature",
  "properties": {
    "addr:full":"172 W Englewood Ave Teaneck NJ 07666",
    "addr:housenumber":"172",
    "addr:postcode":"07666",
    "addr:street":"W Englewood Ave",
    "iso:country":"US",
    "sg:address":"172 W Englewood Ave",
    "sg:city":"Teaneck",
    "sg:classifiers":[
        {
            "category":"Restaurant",
            "type":"Food & Drink"
        }
    ],
    "sg:phone":"+1 201 833 0200",
    "sg:postcode":"07666",
    "sg:province":"NJ",
    "sg:tags":[
        "chinese"
    ],
    "wof:name":"Chopstix Glatt Kosher Chinese Take-Out & Catering",
    "wof:placetype":"venue"
},
  "geometry": {"coordinates":[-74.008202,40.902],"type":"Point"}
}