{
  "type": "Feature",
  "properties": {
    "iso:country":"US",
    "sg:address":"36 Green Grove Ave",
    "sg:city":"Keyport",
    "sg:classifiers":[
        {
            "category":"Arts & Performance",
            "subcategory":"Theater",
            "type":"Entertainment"
        }
    ],
    "sg:phone":"+1   ",
    "sg:postcode":"07735",
    "sg:province":"NJ",
    "sg:tags":[
        "group"
    ],
    "wof:name":"Courtjester Entertainment LLC",
    "wof:placetype":"venue"
},
  "geometry": {"coordinates":[-74.195776,40.436554],"type":"Point"}
}