{
  "type": "Feature",
  "properties": {
    "iso:country":"US",
    "sg:address":"354 State St",
    "sg:city":"Hackensack",
    "sg:classifiers":[
        {
            "category":"Professional",
            "subcategory":"Employment Agencies",
            "type":"Services"
        }
    ],
    "sg:phone":"+1 201 343 9675",
    "sg:postcode":"07601",
    "sg:province":"NJ",
    "wof:name":"Jobs Across America Inc",
    "wof:placetype":"venue"
},
  "geometry": {"coordinates":[-74.04142299999999,40.889704],"type":"Point"}
}