{
  "type": "Feature",
  "properties": {
    "iso:country":"US",
    "sg:address":"610 US Hwy 9",
    "sg:city":"Manahawkin",
    "sg:classifiers":[
        {
            "category":"Organizations",
            "subcategory":"Religious Organization",
            "type":"Services"
        }
    ],
    "sg:phone":"+1 609 597 4393",
    "sg:postcode":"08050",
    "sg:province":"NJ",
    "wof:name":"Calvary Chapel of Southern",
    "wof:placetype":"venue"
},
  "geometry": {"coordinates":[-74.252605,39.706931],"type":"Point"}
}