{
  "type": "Feature",
  "properties": {
    "iso:country":"US",
    "sg:address":"47 Eckert Ave",
    "sg:city":"Newark",
    "sg:classifiers":[
        {
            "category":"Health Services",
            "subcategory":"Clinic",
            "type":"Services"
        }
    ],
    "sg:phone":"+1 973 923 8887",
    "sg:postcode":"07112",
    "sg:province":"NJ",
    "sg:tags":[
        "home"
    ],
    "wof:name":"Tri State Home Healthcare Agcy",
    "wof:placetype":"venue"
},
  "geometry": {"coordinates":[-74.2075,40.713331],"type":"Point"}
}