{
  "type": "Feature",
  "properties": {
    "iso:country":"US",
    "sg:address":"1151 70th St",
    "sg:city":"North Bergen",
    "sg:classifiers":[
        {
            "category":"Retail",
            "subcategory":"Repair Shop",
            "type":"Services"
        }
    ],
    "sg:phone":"+1 201 861 5050",
    "sg:postcode":"07047",
    "sg:province":"NJ",
    "sg:tags":[
        "hardware"
    ],
    "wof:name":"Automatic Saw & Tool Co Inc",
    "wof:placetype":"venue"
},
  "geometry": {"coordinates":[-74.01655599999999,40.797988],"type":"Point"}
}