{
  "type": "Feature",
  "properties": {
    "iso:country":"US",
    "sg:address":"59 Flagler St",
    "sg:city":"East Brunswick",
    "sg:classifiers":[
        {
            "category":"Professional",
            "subcategory":"Computer Services",
            "type":"Services"
        }
    ],
    "sg:phone":"+1 732 698 9229",
    "sg:postcode":"08816",
    "sg:province":"NJ",
    "sg:tags":[
        "related"
    ],
    "wof:name":"Phyks Inc",
    "wof:placetype":"venue"
},
  "geometry": {"coordinates":[-74.367831,40.428166],"type":"Point"}
}