{
  "type": "Feature",
  "properties": {
    "iso:country":"US",
    "sg:address":"1283 US Hwy 22",
    "sg:city":"Mountainside",
    "sg:classifiers":[
        {
            "category":"Professional",
            "subcategory":"Lawyer & Legal Services",
            "type":"Services"
        }
    ],
    "sg:phone":"+1 908 389 0733",
    "sg:postcode":"07092",
    "sg:province":"NJ",
    "sg:tags":[
        "attorney"
    ],
    "wof:name":"Ronald J Korybski Law Office",
    "wof:placetype":"venue"
},
  "geometry": {"coordinates":[-74.350156,40.67402],"type":"Point"}
}