{
  "type": "Feature",
  "properties": {
    "iso:country":"US",
    "sg:address":"18 Mount Prospect Ave",
    "sg:city":"Belleville",
    "sg:classifiers":[
        {
            "category":"Travel",
            "subcategory":"Travel Agent",
            "type":"Entertainment"
        }
    ],
    "sg:phone":"+1 973 751 7400",
    "sg:postcode":"07109",
    "sg:province":"NJ",
    "sg:tags":[
        "operator",
        "tour"
    ],
    "wof:name":"Honey Bee Tours",
    "wof:placetype":"venue"
},
  "geometry": {"coordinates":[-74.160107,40.789901],"type":"Point"}
}