{
  "type": "Feature",
  "properties": {
    "addr:full":"3535 Quakerbridge Rd Trenton NJ 08619",
    "addr:housenumber":"3535",
    "addr:postcode":"08619",
    "addr:street":"Quakerbridge Rd",
    "iso:country":"US",
    "sg:address":"3535 Quakerbridge Rd",
    "sg:city":"Trenton",
    "sg:classifiers":[
        {
            "category":"Health Services",
            "subcategory":"Health Practitioner",
            "type":"Services"
        }
    ],
    "sg:phone":"+1 609 890 9195",
    "sg:postcode":"08619",
    "sg:province":"NJ",
    "sg:tags":[
        "therapist",
        "physical"
    ],
    "wof:name":"Nova Care",
    "wof:placetype":"venue"
},
  "geometry": {"coordinates":[-74.674916,40.263767],"type":"Point"}
}