{
  "type": "Feature",
  "properties": {
    "iso:country":"US",
    "sg:address":"364 15th Ave",
    "sg:city":"Newark",
    "sg:classifiers":[
        {
            "category":"Food & Beverages",
            "subcategory":"Groceries & Convenience Stores",
            "type":"Retail Goods"
        }
    ],
    "sg:phone":"+1 973 901 9311",
    "sg:postcode":"07103",
    "sg:province":"NJ",
    "sg:tags":[
        "grocer"
    ],
    "wof:name":"Brother's Supermarket",
    "wof:placetype":"venue"
},
  "geometry": {"coordinates":[-74.19499999999999,40.736099],"type":"Point"}
}