{
  "type": "Feature",
  "properties": {
    "iso:country":"US",
    "sg:address":"1215 S 6th St",
    "sg:city":"Camden",
    "sg:classifiers":[
        {
            "category":"Manufacturing",
            "subcategory":"Retail Goods",
            "type":"Manufacturing & Wholesale Goods"
        }
    ],
    "sg:phone":"+1 856 541 6200",
    "sg:postcode":"08104",
    "sg:province":"NJ",
    "sg:tags":[
        "product",
        "mfg"
    ],
    "wof:name":"B-2 Custom Manufacturing",
    "wof:placetype":"venue"
},
  "geometry": {"coordinates":[-75.11778,39.930309],"type":"Point"}
}