{
  "type": "Feature",
  "properties": {
    "iso:country":"US",
    "sg:address":"276 Essex St",
    "sg:city":"Millburn",
    "sg:classifiers":[
        {
            "category":"Professional",
            "type":"Services"
        }
    ],
    "sg:phone":"+1 973 376 6756",
    "sg:postcode":"07041",
    "sg:province":"NJ",
    "sg:tags":[
        "establishment"
    ],
    "wof:name":"Burke Family Trust",
    "wof:placetype":"venue"
},
  "geometry": {"coordinates":[-74.30967699999999,40.724124],"type":"Point"}
}