{
  "type": "Feature",
  "properties": {
    "addr:full":"419 Valley St Orange NJ 07050",
    "addr:housenumber":"419",
    "addr:postcode":"07050",
    "addr:street":"Valley St",
    "iso:country":"US",
    "sg:address":"419 Valley St",
    "sg:city":"Orange",
    "sg:classifiers":[
        {
            "category":"Building & Trades",
            "subcategory":"Construction",
            "type":"Services"
        }
    ],
    "sg:phone":"+1 973 678 2545",
    "sg:postcode":"07050",
    "sg:province":"NJ",
    "sg:tags":[
        "contractor"
    ],
    "wof:name":"Apple Tank Co",
    "wof:placetype":"venue"
},
  "geometry": {"coordinates":[-74.247597,40.766998],"type":"Point"}
}