{
  "type": "Feature",
  "properties": {
    "iso:country":"US",
    "sg:address":"373 Sunshine Cir",
    "sg:city":"Englishtown",
    "sg:classifiers":[
        {
            "category":"Professional",
            "subcategory":"Computer Services",
            "type":"Services"
        }
    ],
    "sg:phone":"+1 732 577 8115",
    "sg:postcode":"07726",
    "sg:province":"NJ",
    "sg:tags":[
        "development",
        "software"
    ],
    "wof:name":"L & M Technologies Inc",
    "wof:placetype":"venue"
},
  "geometry": {"coordinates":[-74.31117999999999,40.333884],"type":"Point"}
}