{
  "type": "Feature",
  "properties": {
    "addr:full":"417 Bridgeboro St Riverside NJ 08075",
    "addr:housenumber":"417",
    "addr:postcode":"08075",
    "addr:street":"Bridgeboro St",
    "iso:country":"US",
    "sg:address":"417 Bridgeboro St",
    "sg:city":"Riverside",
    "sg:classifiers":[
        {
            "category":"Professional",
            "subcategory":"Business Services",
            "type":"Services"
        }
    ],
    "sg:phone":"+1   ",
    "sg:postcode":"08075",
    "sg:province":"NJ",
    "wof:name":"Macktel Communications",
    "wof:placetype":"venue"
},
  "geometry": {"coordinates":[-74.952493,40.036273],"type":"Point"}
}