{
  "type": "Feature",
  "properties": {
    "iso:country":"US",
    "sg:address":"485 S Edgemere Dr",
    "sg:city":"Allenhurst",
    "sg:classifiers":[
        {
            "category":"Professional",
            "subcategory":"Employment Agencies",
            "type":"Services"
        }
    ],
    "sg:phone":"+1   ",
    "sg:postcode":"07711",
    "sg:province":"NJ",
    "wof:name":"Margaret Ruvoldt Assoc Inc",
    "wof:placetype":"venue"
},
  "geometry": {"coordinates":[-74.009259,40.236779],"type":"Point"}
}