{
  "type": "Feature",
  "properties": {
    "iso:country":"US",
    "sg:address":"21 Grove Ave",
    "sg:city":"Verona",
    "sg:classifiers":[
        {
            "category":"Wholesale",
            "subcategory":"Machinery & Supplies",
            "type":"Manufacturing & Wholesale Goods"
        }
    ],
    "sg:phone":"+1 973 571 1401",
    "sg:postcode":"07044",
    "sg:province":"NJ",
    "wof:name":"Northeast Compost & Ldscp Sup",
    "wof:placetype":"venue"
},
  "geometry": {"coordinates":[-74.24763400000001,40.83405],"type":"Point"}
}