{
  "type": "Feature",
  "properties": {
    "iso:country":"US",
    "sg:address":"567 52nd St",
    "sg:city":"West New York",
    "sg:classifiers":[
        {
            "category":"Wholesale",
            "subcategory":"Non-durable Goods",
            "type":"Manufacturing & Wholesale Goods"
        }
    ],
    "sg:phone":"+1 201 558 1800",
    "sg:postcode":"07093",
    "sg:province":"NJ",
    "wof:name":"Remeli Enterprises",
    "wof:placetype":"venue"
},
  "geometry": {"coordinates":[-74.02230400000001,40.785125],"type":"Point"}
}