{
  "type": "Feature",
  "properties": {
    "iso:country":"US",
    "sg:address":"5517 Hudson Ave",
    "sg:city":"West New York",
    "sg:classifiers":[
        {
            "category":"Restaurant",
            "type":"Food & Drink"
        }
    ],
    "sg:phone":"+1 201 867 4566",
    "sg:postcode":"07093",
    "sg:province":"NJ",
    "sg:tags":[
        "pizza"
    ],
    "wof:name":"La Tinatjita",
    "wof:placetype":"venue"
},
  "geometry": {"coordinates":[-74.01480100000001,40.784599],"type":"Point"}
}