{
  "type": "Feature",
  "properties": {
    "addr:full":"10 Church St Salem NJ 08079",
    "addr:housenumber":"10",
    "addr:postcode":"08079",
    "addr:street":"Church St",
    "iso:country":"US",
    "sg:address":"10 Church St",
    "sg:city":"Salem",
    "sg:classifiers":[
        {
            "category":"Organizations",
            "subcategory":"Religious Organization",
            "type":"Services"
        }
    ],
    "sg:phone":"+1 856 935 0605",
    "sg:postcode":"08079",
    "sg:province":"NJ",
    "sg:tags":[
        "church"
    ],
    "wof:name":"Alloway United Methodist Chr",
    "wof:placetype":"venue"
},
  "geometry": {"coordinates":[-75.46475700000001,39.569124],"type":"Point"}
}