{
  "type": "Feature",
  "properties": {
    "iso:country":"US",
    "sg:address":"1213 Hamilton Ave",
    "sg:city":"Trenton",
    "sg:classifiers":[
        {
            "category":"Professional",
            "subcategory":"Lawyer & Legal Services",
            "type":"Services"
        }
    ],
    "sg:phone":"+1 609 631 7771",
    "sg:postcode":"08629",
    "sg:province":"NJ",
    "wof:name":"Ortiz & Associates",
    "wof:placetype":"venue"
},
  "geometry": {"coordinates":[-74.731194,40.220036],"type":"Point"}
}