{
  "type": "Feature",
  "properties": {
    "addr:full":"499 W Shore Trl Sparta NJ 07871",
    "addr:housenumber":"499",
    "addr:postcode":"07871",
    "addr:street":"W Shore Trl",
    "iso:country":"US",
    "sg:address":"499 W Shore Trl",
    "sg:city":"Sparta",
    "sg:classifiers":[
        {
            "category":"Building & Trades",
            "subcategory":"Cleaning & Sanitation",
            "type":"Services"
        }
    ],
    "sg:phone":"+1   ",
    "sg:postcode":"07871",
    "sg:province":"NJ",
    "sg:tags":[
        "maintenance"
    ],
    "wof:name":"Kathy S Window Cleaning",
    "wof:placetype":"venue"
},
  "geometry": {"coordinates":[-74.666585,41.015281],"type":"Point"}
}