{
  "type": "Feature",
  "properties": {
    "iso:country":"US",
    "sg:address":"139 Ploch Rd",
    "sg:city":"Clifton",
    "sg:classifiers":[
        {
            "category":"Professional",
            "subcategory":"Art Services",
            "type":"Services"
        }
    ],
    "sg:phone":"+1 973 278 2646",
    "sg:postcode":"07013",
    "sg:province":"NJ",
    "sg:tags":[
        "agent",
        "artist"
    ],
    "wof:name":"Woodsnowflakes",
    "wof:placetype":"venue"
},
  "geometry": {"coordinates":[-74.17577799999999,40.881389],"type":"Point"}
}