{
  "type": "Feature",
  "properties": {
    "iso:country":"US",
    "sg:address":"41 Loch Ln",
    "sg:city":"Ledgewood",
    "sg:classifiers":[
        {
            "category":"Professional",
            "subcategory":"Management & Consulting",
            "type":"Services"
        }
    ],
    "sg:phone":"+1   ",
    "sg:postcode":"07852",
    "sg:province":"NJ",
    "sg:tags":[
        "business"
    ],
    "wof:name":"Trf Inc",
    "wof:placetype":"venue"
},
  "geometry": {"coordinates":[-74.65853300000001,40.869332],"type":"Point"}
}