{
  "type": "Feature",
  "properties": {
    "iso:country":"US",
    "sg:address":"649 Magnolia Ave",
    "sg:city":"Elizabeth",
    "sg:classifiers":[
        {
            "category":"Autos & Motor Vehicles",
            "subcategory":"Automobile Sales",
            "type":"Retail Goods"
        }
    ],
    "sg:phone":"+1 908 469 1385",
    "sg:postcode":"07206",
    "sg:province":"NJ",
    "sg:tags":[
        "limo"
    ],
    "wof:name":"Princess Limo",
    "wof:placetype":"venue"
},
  "geometry": {"coordinates":[-74.193597,40.660811],"type":"Point"}
}