{
  "type": "Feature",
  "properties": {
    "addr:full":"4 Marietta Ln Trenton NJ 08619",
    "addr:housenumber":"4",
    "addr:postcode":"08619",
    "addr:street":"Marietta Ln",
    "iso:country":"US",
    "sg:address":"4 Marietta Ln",
    "sg:city":"Trenton",
    "sg:classifiers":[
        {
            "category":"Professional",
            "subcategory":"Engineering",
            "type":"Services"
        }
    ],
    "sg:phone":"+1   ",
    "sg:postcode":"08619",
    "sg:province":"NJ",
    "wof:name":"Rococo LLc",
    "wof:placetype":"venue"
},
  "geometry": {"coordinates":[-74.695443,40.243463],"type":"Point"}
}