{
  "type": "Feature",
  "properties": {
    "iso:country":"US",
    "sg:address":"99 Lakeview Dr E",
    "sg:city":"Egg Harbor Twp",
    "sg:classifiers":[
        {
            "category":"Shopping",
            "type":"Retail Goods"
        }
    ],
    "sg:phone":"+1 609 927 3334",
    "sg:postcode":"08234",
    "sg:province":"NJ",
    "sg:tags":[
        "candle"
    ],
    "wof:name":"P K Enterprises",
    "wof:placetype":"venue"
},
  "geometry": {"coordinates":[-74.61325600000001,39.341092],"type":"Point"}
}