{
  "type": "Feature",
  "properties": {
    "iso:country":"US",
    "sg:address":"30 Stockton St",
    "sg:city":"Bloomfield",
    "sg:classifiers":[
        {
            "category":"Building & Trades",
            "subcategory":"Construction",
            "type":"Services"
        }
    ],
    "sg:phone":"+1 973 680 9848",
    "sg:postcode":"07003",
    "sg:province":"NJ",
    "sg:tags":[
        "house"
    ],
    "wof:name":"Bonfante Construction",
    "wof:placetype":"venue"
},
  "geometry": {"coordinates":[-74.188946,40.792743],"type":"Point"}
}