{
  "type": "Feature",
  "properties": {
    "addr:full":"24 Hillside Ave Metuchen NJ 08840",
    "addr:housenumber":"24",
    "addr:postcode":"08840",
    "addr:street":"Hillside Ave",
    "iso:country":"US",
    "sg:address":"24 Hillside Ave",
    "sg:city":"Metuchen",
    "sg:classifiers":[
        {
            "category":"Real Estate",
            "subcategory":"Real Estate Agent",
            "type":"Services"
        }
    ],
    "sg:phone":"+1 732 549 9404",
    "sg:postcode":"08840",
    "sg:province":"NJ",
    "wof:name":"Docs Agency Inc",
    "wof:placetype":"venue"
},
  "geometry": {"coordinates":[-74.35984999999999,40.542317],"type":"Point"}
}