{
  "type": "Feature",
  "properties": {
    "iso:country":"US",
    "sg:address":"233 N Franklin Tpke",
    "sg:city":"Ramsey",
    "sg:classifiers":[
        {
            "category":"Restaurant",
            "type":"Food & Drink"
        }
    ],
    "sg:phone":"+1 201 825 2272",
    "sg:postcode":"07446",
    "sg:province":"NJ",
    "sg:tags":[
        "eating"
    ],
    "wof:name":"Friendly's",
    "wof:placetype":"venue"
},
  "geometry": {"coordinates":[-74.134604,41.065663],"type":"Point"}
}