{
  "type": "Feature",
  "properties": {
    "iso:country":"US",
    "sg:address":"346 Bloomfield Ave",
    "sg:city":"Caldwell",
    "sg:classifiers":[
        {
            "category":"Restaurant",
            "type":"Food & Drink"
        }
    ],
    "sg:phone":"+1 973 364 0020",
    "sg:postcode":"07006",
    "sg:province":"NJ",
    "wof:name":"Cafe Express",
    "wof:placetype":"venue"
},
  "geometry": {"coordinates":[-74.27679000000001,40.840132],"type":"Point"}
}