{
  "type": "Feature",
  "properties": {
    "addr:full":"98 Grove Ave Verona NJ 07044",
    "addr:housenumber":"98",
    "addr:postcode":"07044",
    "addr:street":"Grove Ave",
    "iso:country":"US",
    "sg:address":"98 Grove Ave",
    "sg:city":"Verona",
    "sg:classifiers":[
        {
            "category":"Building & Trades",
            "subcategory":"Construction",
            "type":"Services"
        }
    ],
    "sg:phone":"+1 973 857 9114",
    "sg:postcode":"07044",
    "sg:province":"NJ",
    "sg:tags":[
        "painter"
    ],
    "wof:name":"Garden State Painting & Design",
    "wof:placetype":"venue"
},
  "geometry": {"coordinates":[-74.245217,40.837509],"type":"Point"}
}