{
  "type": "Feature",
  "properties": {
    "iso:country":"US",
    "sg:address":"1005 Chesterwood Ct",
    "sg:city":"Marlton",
    "sg:classifiers":[
        {
            "category":"Shopping",
            "subcategory":"Discount & Variety Stores",
            "type":"Retail Goods"
        }
    ],
    "sg:phone":"+1 856 797 9556",
    "sg:postcode":"08053",
    "sg:province":"NJ",
    "sg:tags":[
        "merchandise",
        "general"
    ],
    "wof:name":"Eagle Phillies 76er's Flyers",
    "wof:placetype":"venue"
},
  "geometry": {"coordinates":[-74.937889,39.90147],"type":"Point"}
}