{
  "type": "Feature",
  "properties": {
    "iso:country":"US",
    "sg:address":"215 Warren St",
    "sg:city":"Beverly",
    "sg:classifiers":[
        {
            "category":"Building & Trades",
            "subcategory":"Construction",
            "type":"Services"
        }
    ],
    "sg:phone":"+1 609 747 8100",
    "sg:postcode":"08010",
    "sg:province":"NJ",
    "sg:tags":[
        "home",
        "builder"
    ],
    "wof:name":"Thomas Lynn Homes LLC",
    "wof:placetype":"venue"
},
  "geometry": {"coordinates":[-74.918279,40.065351],"type":"Point"}
}