{
  "type": "Feature",
  "properties": {
    "addr:full":"902 Main St Belford NJ 07718",
    "addr:housenumber":"902",
    "addr:postcode":"07718",
    "addr:street":"Main St",
    "iso:country":"US",
    "sg:address":"902 Main St",
    "sg:city":"Belford",
    "sg:classifiers":[
        {
            "category":"Retail",
            "subcategory":"Auto Repair",
            "type":"Services"
        }
    ],
    "sg:phone":"+1 732 787 0800",
    "sg:postcode":"07718",
    "sg:province":"NJ",
    "sg:tags":[
        "body"
    ],
    "wof:name":"Lentz Auto Body Shop",
    "wof:placetype":"venue"
},
  "geometry": {"coordinates":[-74.08286,40.432354],"type":"Point"}
}