{
  "type": "Feature",
  "properties": {
    "iso:country":"US",
    "sg:address":"17 Oakwood Dr",
    "sg:city":"Medford",
    "sg:classifiers":[
        {
            "category":"Professional",
            "subcategory":"Business Services",
            "type":"Services"
        }
    ],
    "sg:phone":"+1   ",
    "sg:postcode":"08055",
    "sg:province":"NJ",
    "wof:name":"Powell Solutions LLC",
    "wof:placetype":"venue"
},
  "geometry": {"coordinates":[-74.83706100000001,39.871787],"type":"Point"}
}