{
  "type": "Feature",
  "properties": {
    "addr:full":"9 Oak Ln Tuckerton NJ 08087",
    "addr:housenumber":"9",
    "addr:postcode":"08087",
    "addr:street":"Oak Ln",
    "iso:country":"US",
    "sg:address":"9 Oak Ln",
    "sg:city":"Tuckerton",
    "sg:classifiers":[
        {
            "category":"Retail",
            "subcategory":"Car Wash",
            "type":"Services"
        }
    ],
    "sg:phone":"+1 609 294 3530",
    "sg:postcode":"08087",
    "sg:province":"NJ",
    "sg:tags":[
        "carwash"
    ],
    "wof:name":"Captain Car Wash II",
    "wof:placetype":"venue"
},
  "geometry": {"coordinates":[-74.356758,39.600141],"type":"Point"}
}