{
  "type": "Feature",
  "properties": {
    "addr:full":"228 S Main St Manville NJ 08835",
    "addr:housenumber":"228",
    "addr:postcode":"08835",
    "addr:street":"S Main St",
    "iso:country":"US",
    "sg:address":"228 S Main St",
    "sg:city":"Manville",
    "sg:classifiers":[
        {
            "category":"Organizations",
            "subcategory":"Religious Organization",
            "type":"Services"
        }
    ],
    "sg:phone":"+1 908 252 1617",
    "sg:postcode":"08835",
    "sg:province":"NJ",
    "sg:tags":[
        "church"
    ],
    "wof:name":"Faith In Action Church",
    "wof:placetype":"venue"
},
  "geometry": {"coordinates":[-74.587774,40.540516],"type":"Point"}
}