{
  "type": "Feature",
  "properties": {
    "iso:country":"US",
    "sg:address":"45 Oxycocus Rd",
    "sg:city":"Manahawkin",
    "sg:classifiers":[
        {
            "category":"Building & Trades",
            "subcategory":"Construction",
            "type":"Services"
        }
    ],
    "sg:phone":"+1 609 978 5151",
    "sg:postcode":"08050",
    "sg:province":"NJ",
    "sg:tags":[
        "house"
    ],
    "wof:name":"Dd Construction Inc",
    "wof:placetype":"venue"
},
  "geometry": {"coordinates":[-74.25859,39.702009],"type":"Point"}
}