{
  "type": "Feature",
  "properties": {
    "addr:full":"4 Lathrop Ave Madison NJ 07940",
    "addr:housenumber":"4",
    "addr:postcode":"07940",
    "addr:street":"Lathrop Ave",
    "iso:country":"US",
    "sg:address":"4 Lathrop Ave",
    "sg:city":"Madison",
    "sg:classifiers":[
        {
            "category":"Insurance",
            "subcategory":"Insurance Agent",
            "type":"Services"
        }
    ],
    "sg:phone":"+1   ",
    "sg:postcode":"07940",
    "sg:province":"NJ",
    "wof:name":"Papathomas Ins Agency Inc",
    "wof:placetype":"venue"
},
  "geometry": {"coordinates":[-74.430319,40.753492],"type":"Point"}
}