{
  "type": "Feature",
  "properties": {
    "iso:country":"US",
    "sg:address":"820 Bear Tavern Rd",
    "sg:city":"Trenton",
    "sg:classifiers":[
        {
            "category":"Professional",
            "subcategory":"Advertising",
            "type":"Services"
        }
    ],
    "sg:phone":"+1   ",
    "sg:postcode":"08628",
    "sg:province":"NJ",
    "sg:tags":[
        "mail",
        "datum",
        "direct",
        "business",
        "ad"
    ],
    "wof:name":"Dmfs",
    "wof:placetype":"venue"
},
  "geometry": {"coordinates":[-74.83063300000001,40.278258],"type":"Point"}
}