{
  "type": "Feature",
  "properties": {
    "addr:full":"613 Barnegat Ave Toms River NJ 08753",
    "addr:housenumber":"613",
    "addr:postcode":"08753",
    "addr:street":"Barnegat Ave",
    "iso:country":"US",
    "sg:address":"613 Barnegat Ave",
    "sg:city":"Toms River",
    "sg:classifiers":[
        {
            "category":"Building & Trades",
            "subcategory":"Construction",
            "type":"Services"
        }
    ],
    "sg:phone":"+1 732 270 1693",
    "sg:postcode":"08753",
    "sg:province":"NJ",
    "sg:tags":[
        "contractor"
    ],
    "wof:name":"A Parks Contracting LLC",
    "wof:placetype":"venue"
},
  "geometry": {"coordinates":[-74.131758,39.948895],"type":"Point"}
}