{
  "type": "Feature",
  "properties": {
    "iso:country":"US",
    "sg:address":"305 Wolfert Station Rd",
    "sg:city":"Mullica Hill",
    "sg:phone":"+1 856 478 2478",
    "sg:postcode":"08062",
    "sg:province":"NJ",
    "sg:tags":[
        "farm",
        "wheat"
    ],
    "wof:name":"Sunny Acres Farm",
    "wof:placetype":"venue"
},
  "geometry": {"coordinates":[-75.22894700000001,39.757517],"type":"Point"}
}