{
  "type": "Feature",
  "properties": {
    "iso:country":"US",
    "sg:address":"1251 Terrill Rd",
    "sg:city":"Scotch Plains",
    "sg:classifiers":[
        {
            "category":"Organizations",
            "subcategory":"Religious Organization",
            "type":"Services"
        }
    ],
    "sg:phone":"+1 908 322 9300",
    "sg:postcode":"07076",
    "sg:province":"NJ",
    "sg:tags":[
        "church"
    ],
    "sg:website":"www.evangelchurch.com",
    "wof:name":"Evangel Church",
    "wof:placetype":"venue"
},
  "geometry": {"coordinates":[-74.373884,40.624412],"type":"Point"}
}