{
  "type": "Feature",
  "properties": {
    "iso:country":"US",
    "sg:address":"168 Ashland Rd",
    "sg:city":"Summit",
    "sg:classifiers":[
        {
            "category":"Building & Trades",
            "subcategory":"Construction",
            "type":"Services"
        }
    ],
    "sg:phone":"+1 908 522 0399",
    "sg:postcode":"07901",
    "sg:province":"NJ",
    "sg:tags":[
        "house"
    ],
    "wof:name":"Wheeler Construction",
    "wof:placetype":"venue"
},
  "geometry": {"coordinates":[-74.368737,40.706024],"type":"Point"}
}