{
  "type": "Feature",
  "properties": {
    "iso:country":"US",
    "sg:address":"243 State Rte 166",
    "sg:city":"Toms River",
    "sg:classifiers":[
        {
            "category":"Professional",
            "subcategory":"Business Services",
            "type":"Services"
        }
    ],
    "sg:phone":"+1 732 281 3210",
    "sg:postcode":"08753",
    "sg:province":"NJ",
    "sg:tags":[
        "painter",
        "sign"
    ],
    "wof:name":"Stuck Up Sticker Co",
    "wof:placetype":"venue"
},
  "geometry": {"coordinates":[-74.198363,39.954733],"type":"Point"}
}