{
  "type": "Feature",
  "properties": {
    "iso:country":"US",
    "sg:address":"35 US Hwy 206",
    "sg:city":"Stanhope",
    "sg:classifiers":[
        {
            "category":"Shopping",
            "subcategory":"Florist",
            "type":"Retail Goods"
        }
    ],
    "sg:phone":"+1 973 347 3010",
    "sg:postcode":"07874",
    "sg:province":"NJ",
    "wof:name":"Lockwood Farms Garden & Gifts",
    "wof:placetype":"venue"
},
  "geometry": {"coordinates":[-74.71873600000001,40.92697],"type":"Point"}
}