{
  "type": "Feature",
  "properties": {
    "addr:full":"3131 Princeton Pike 1A Lawrenceville NJ 08648",
    "addr:housenumber":"3131;1a",
    "addr:postcode":"08648",
    "addr:street":"Princeton Pike",
    "iso:country":"US",
    "sg:address":"3131 Princeton Pike 1A",
    "sg:city":"Lawrenceville",
    "sg:classifiers":[
        {
            "category":"Health Services",
            "subcategory":"Dentist",
            "type":"Services"
        }
    ],
    "sg:phone":"+1 609 394 1670",
    "sg:postcode":"08648",
    "sg:province":"NJ",
    "sg:tags":[
        "product",
        "dentists-cosmetic",
        "denture",
        "dentists-prosthodontists",
        "teeth",
        "dentists-pediatric",
        "whitening",
        "dentistry",
        "implant",
        "dentists-implantology"
    ],
    "sg:website":"http://wolfdds.com",
    "wof:name":"Robert B. Wolf, DDS., PA",
    "wof:placetype":"venue"
},
  "geometry": {"coordinates":[-74.71529099999999,40.282823],"type":"Point"}
}