{
  "type": "Feature",
  "properties": {
    "addr:full":"609 Sicklerville Rd Sicklerville NJ 08081",
    "addr:housenumber":"609",
    "addr:postcode":"08081",
    "addr:street":"Sicklerville Rd",
    "iso:country":"US",
    "sg:address":"609 Sicklerville Rd",
    "sg:city":"Sicklerville",
    "sg:classifiers":[
        {
            "category":"Retail",
            "subcategory":"Laundry & Dry Cleaning",
            "type":"Services"
        }
    ],
    "sg:phone":"+1 856 875 9406",
    "sg:postcode":"08081",
    "sg:province":"NJ",
    "sg:tags":[
        "cleaners"
    ],
    "wof:name":"Winslow Cleaners",
    "wof:placetype":"venue"
},
  "geometry": {"coordinates":[-74.993876,39.732025],"type":"Point"}
}