{
  "type": "Feature",
  "properties": {
    "addr:full":"1 Fellner Pl Totowa NJ 07512",
    "addr:housenumber":"1",
    "addr:postcode":"07512",
    "addr:street":"Fellner Pl",
    "iso:country":"US",
    "sg:address":"1 Fellner Pl",
    "sg:city":"Totowa",
    "sg:classifiers":[
        {
            "category":"Organizations",
            "subcategory":"Community Association",
            "type":"Services"
        }
    ],
    "sg:phone":"+1 973 942 2111",
    "sg:postcode":"07512",
    "sg:province":"NJ",
    "sg:tags":[
        "fraternal"
    ],
    "wof:name":"Elks Lodge",
    "wof:placetype":"venue"
},
  "geometry": {"coordinates":[-74.206065,40.916888],"type":"Point"}
}