{
  "type": "Feature",
  "properties": {
    "iso:country":"US",
    "sg:address":"100 E 9th St",
    "sg:city":"Lakewood",
    "sg:classifiers":[
        {
            "category":"Manufacturing",
            "subcategory":"Printing",
            "type":"Manufacturing & Wholesale Goods"
        }
    ],
    "sg:phone":"+1 732 901 9399",
    "sg:postcode":"08701",
    "sg:province":"NJ",
    "sg:tags":[
        "commercial"
    ],
    "wof:name":"Magnadata Usa Inc",
    "wof:placetype":"venue"
},
  "geometry": {"coordinates":[-74.200373,40.100882],"type":"Point"}
}