{
  "type": "Feature",
  "properties": {
    "addr:full":"750 US Hwy 130 Trenton NJ 08691",
    "addr:housenumber":"750",
    "addr:postcode":"08691",
    "addr:street":"Us Hwy 130",
    "iso:country":"US",
    "sg:address":"750 US Hwy 130",
    "sg:city":"Trenton",
    "sg:classifiers":[
        {
            "category":"Home & Garden",
            "subcategory":"Building Materials",
            "type":"Retail Goods"
        }
    ],
    "sg:phone":"+1   ",
    "sg:postcode":"08691",
    "sg:province":"NJ",
    "wof:name":"Home Depot",
    "wof:placetype":"venue"
},
  "geometry": {"coordinates":[-74.642804,40.195503],"type":"Point"}
}