{
  "type": "Feature",
  "properties": {
    "addr:full":"1634 Martin Rd Neptune NJ 07753",
    "addr:housenumber":"1634",
    "addr:postcode":"07753",
    "addr:street":"Martin Rd",
    "iso:country":"US",
    "sg:address":"1634 Martin Rd",
    "sg:city":"Neptune",
    "sg:classifiers":[
        {
            "category":"Professional",
            "type":"Services"
        }
    ],
    "sg:phone":"+1   ",
    "sg:postcode":"07753",
    "sg:province":"NJ",
    "wof:name":"Krystal Watkins",
    "wof:placetype":"venue"
},
  "geometry": {"coordinates":[-74.105705,40.191106],"type":"Point"}
}