{
  "type": "Feature",
  "properties": {
    "addr:full":"61 Kansas St Hackensack NJ 07601",
    "addr:housenumber":"61",
    "addr:postcode":"07601",
    "addr:street":"Kansas St",
    "iso:country":"US",
    "sg:address":"61 Kansas St",
    "sg:city":"Hackensack",
    "sg:classifiers":[
        {
            "category":"Professional",
            "subcategory":"Lawyer & Legal Services",
            "type":"Services"
        }
    ],
    "sg:phone":"+1 201 487 2166",
    "sg:postcode":"07601",
    "sg:province":"NJ",
    "wof:name":"North East New Jersey Legal Services",
    "wof:placetype":"venue"
},
  "geometry": {"coordinates":[-74.0457,40.876598],"type":"Point"}
}