{
  "type": "Feature",
  "properties": {
    "iso:country":"US",
    "sg:address":"237 Glenn Ave",
    "sg:city":"Trenton",
    "sg:classifiers":[
        {
            "category":"Personal",
            "type":"Services"
        }
    ],
    "sg:phone":"+1   ",
    "sg:postcode":"08648",
    "sg:province":"NJ",
    "wof:name":"Crossman Productions",
    "wof:placetype":"venue"
},
  "geometry": {"coordinates":[-74.72715599999999,40.262651],"type":"Point"}
}