{
  "type": "Feature",
  "properties": {
    "addr:full":"1154 Jolson Ct Lakehurst NJ 08759",
    "addr:housenumber":"1154",
    "addr:postcode":"08759",
    "addr:street":"Jolson Ct",
    "iso:country":"US",
    "sg:address":"1154 Jolson Ct",
    "sg:city":"Lakehurst",
    "sg:classifiers":[
        {
            "category":"Building & Trades",
            "subcategory":"Cleaning & Sanitation",
            "type":"Services"
        }
    ],
    "sg:phone":"+1 732 657 0044",
    "sg:postcode":"08759",
    "sg:province":"NJ",
    "sg:tags":[
        "maintenance"
    ],
    "wof:name":"Thompson & Thompson Jantr Svc",
    "wof:placetype":"venue"
},
  "geometry": {"coordinates":[-74.28525999999999,39.995978],"type":"Point"}
}