{
  "type": "Feature",
  "properties": {
    "addr:full":"305 Deer Creek Dr Plainsboro NJ 08536",
    "addr:housenumber":"305",
    "addr:postcode":"08536",
    "addr:street":"Deer Creek Dr",
    "iso:country":"US",
    "sg:address":"305 Deer Creek Dr",
    "sg:city":"Plainsboro",
    "sg:classifiers":[
        {
            "category":"Real Estate",
            "subcategory":"Real Estate Operator",
            "type":"Services"
        }
    ],
    "sg:phone":"+1   ",
    "sg:postcode":"08536",
    "sg:province":"NJ",
    "sg:tags":[
        "building",
        "apartment"
    ],
    "wof:name":"Deer Creek",
    "wof:placetype":"venue"
},
  "geometry": {"coordinates":[-74.57281399999999,40.327124],"type":"Point"}
}