{
  "type": "Feature",
  "properties": {
    "iso:country":"US",
    "sg:address":"710 E Saint Georges Ave",
    "sg:city":"Linden",
    "sg:classifiers":[
        {
            "category":"Autos & Motor Vehicles",
            "subcategory":"Auto Supplies",
            "type":"Retail Goods"
        }
    ],
    "sg:phone":"+1   ",
    "sg:postcode":"07036",
    "sg:province":"NJ",
    "sg:tags":[
        "body",
        "e"
    ],
    "wof:name":"Easco Auto Seat Covers",
    "wof:placetype":"venue"
},
  "geometry": {"coordinates":[-74.257864,40.643684],"type":"Point"}
}