{
  "type": "Feature",
  "properties": {
    "addr:full":"3402 State Rte 37 Toms River NJ 08753",
    "addr:housenumber":"3402",
    "addr:postcode":"08753",
    "addr:street":"State Rte 37",
    "iso:country":"US",
    "sg:address":"3402 State Rte 37",
    "sg:city":"Toms River",
    "sg:classifiers":[
        {
            "category":"Shopping",
            "subcategory":"Clothing, Apparel, & Fashions",
            "type":"Retail Goods"
        }
    ],
    "sg:phone":"+1   ",
    "sg:postcode":"08753",
    "sg:province":"NJ",
    "sg:tags":[
        "family"
    ],
    "wof:name":"Aloha Tommys",
    "wof:placetype":"venue"
},
  "geometry": {"coordinates":[-74.11521399999999,39.949502],"type":"Point"}
}