{
  "type": "Feature",
  "properties": {
    "addr:full":"73 Cornelison Ave Jersey City NJ 07304",
    "addr:housenumber":"73",
    "addr:postcode":"07304",
    "addr:street":"Cornelison Ave",
    "iso:country":"US",
    "sg:address":"73 Cornelison Ave",
    "sg:city":"Jersey City",
    "sg:classifiers":[
        {
            "category":"Wholesale",
            "subcategory":"Scrap",
            "type":"Manufacturing & Wholesale Goods"
        }
    ],
    "sg:phone":"+1 201 433 4751",
    "sg:postcode":"07304",
    "sg:province":"NJ",
    "sg:tags":[
        "metal"
    ],
    "wof:name":"Pace Scrap Metals Inc",
    "wof:placetype":"venue"
},
  "geometry": {"coordinates":[-74.065753,40.718396],"type":"Point"}
}