{
  "type": "Feature",
  "properties": {
    "iso:country":"US",
    "sg:address":"222 Grand St",
    "sg:city":"Hoboken",
    "sg:classifiers":[
        {
            "category":"Real Estate",
            "subcategory":"Real Estate Operator",
            "type":"Services"
        }
    ],
    "sg:phone":"+1 201 610 0190",
    "sg:postcode":"07030",
    "sg:province":"NJ",
    "sg:tags":[
        "condominium"
    ],
    "wof:name":"Grand Court Condo Assoc",
    "wof:placetype":"venue"
},
  "geometry": {"coordinates":[-74.035752,40.74067],"type":"Point"}
}