{
  "type": "Feature",
  "properties": {
    "addr:full":"30 State Route 31 S Washington NJ 07882",
    "addr:housenumber":"30",
    "addr:postcode":"07882",
    "addr:street":"State Route 31 S",
    "iso:country":"US",
    "sg:address":"30 State Route 31 S",
    "sg:city":"Washington",
    "sg:classifiers":[
        {
            "category":"Autos & Motor Vehicles",
            "subcategory":"Automobile Sales",
            "type":"Retail Goods"
        },
        {
            "category":"Retail",
            "subcategory":"Auto Repair",
            "type":"Services"
        }
    ],
    "sg:phone":"+1 908 689 0224",
    "sg:postcode":"07882",
    "sg:province":"NJ",
    "sg:tags":[
        "car"
    ],
    "wof:name":"Rossi Chevrolet Pontiac Buick GMC Truck",
    "wof:placetype":"venue"
},
  "geometry": {"coordinates":[-74.97519699999999,40.758801],"type":"Point"}
}