{
  "type": "Feature",
  "properties": {
    "iso:country":"US",
    "sg:address":"720 Monroe St Ste C414",
    "sg:city":"Hoboken",
    "sg:classifiers":[
        {
            "category":"Travel",
            "subcategory":"Travel Agent",
            "type":"Entertainment"
        },
        {
            "category":"Landmark",
            "subcategory":"Tourist Information",
            "type":"Public Place"
        }
    ],
    "sg:phone":"+1 800 283 7262",
    "sg:postcode":"07030",
    "sg:province":"NJ",
    "sg:tags":[
        "tour"
    ],
    "sg:website":"www.italiatours.com",
    "wof:name":"Italiatours travel Agency",
    "wof:placetype":"venue"
},
  "geometry": {"coordinates":[-74.037724,40.746997],"type":"Point"}
}