{
  "type": "Feature",
  "properties": {
    "addr:full":"406 Taft Pl Beverly NJ 08010",
    "addr:housenumber":"406",
    "addr:postcode":"08010",
    "addr:street":"Taft Pl",
    "iso:country":"US",
    "sg:address":"406 Taft Pl",
    "sg:city":"Beverly",
    "sg:classifiers":[
        {
            "category":"Building & Trades",
            "subcategory":"Construction",
            "type":"Services"
        }
    ],
    "sg:phone":"+1 609 871 0653",
    "sg:postcode":"08010",
    "sg:province":"NJ",
    "sg:tags":[
        "roofing",
        "contractor"
    ],
    "wof:name":"Brody Alan G Siding & Roofing",
    "wof:placetype":"venue"
},
  "geometry": {"coordinates":[-74.907049,40.057215],"type":"Point"}
}