{
  "type": "Feature",
  "properties": {
    "iso:country":"US",
    "sg:address":"124 Edison St",
    "sg:city":"Clifton",
    "sg:classifiers":[
        {
            "category":"Building & Trades",
            "subcategory":"Cleaning & Sanitation",
            "type":"Services"
        }
    ],
    "sg:phone":"+1   ",
    "sg:postcode":"07013",
    "sg:province":"NJ",
    "sg:tags":[
        "maintenance"
    ],
    "wof:name":"Aadvantage Duct Cleaning",
    "wof:placetype":"venue"
},
  "geometry": {"coordinates":[-74.17333000000001,40.883989],"type":"Point"}
}