{
  "type": "Feature",
  "properties": {
    "iso:country":"US",
    "sg:address":"265 Millstone River Rd",
    "sg:city":"Belle Mead",
    "sg:classifiers":[
        {
            "category":"Retail",
            "subcategory":"Auto Repair",
            "type":"Services"
        }
    ],
    "sg:phone":"+1 908 359 4170",
    "sg:postcode":"08502",
    "sg:province":"NJ",
    "sg:tags":[
        "general"
    ],
    "wof:name":"Drift Automotive Inc",
    "wof:placetype":"venue"
},
  "geometry": {"coordinates":[-74.630793,40.424793],"type":"Point"}
}