{
  "type": "Feature",
  "properties": {
    "iso:country":"US",
    "sg:address":"114 Nassau St",
    "sg:city":"Princeton",
    "sg:classifiers":[
        {
            "category":"Professional",
            "subcategory":"Business Services",
            "type":"Services"
        }
    ],
    "sg:phone":"+1   ",
    "sg:postcode":"08542",
    "sg:province":"NJ",
    "wof:name":"Clarksville Associates LP",
    "wof:placetype":"venue"
},
  "geometry": {"coordinates":[-74.659379,40.349859],"type":"Point"}
}