{
  "type": "Feature",
  "properties": {
    "iso:country":"US",
    "sg:address":"14 Fairclough Pl",
    "sg:city":"Fair Lawn",
    "sg:classifiers":[
        {
            "category":"Professional",
            "type":"Services"
        }
    ],
    "sg:phone":"+1   ",
    "sg:postcode":"07410",
    "sg:province":"NJ",
    "wof:name":"A Way With Words",
    "wof:placetype":"venue"
},
  "geometry": {"coordinates":[-74.12473199999999,40.935297],"type":"Point"}
}