{
  "type": "Feature",
  "properties": {
    "iso:country":"US",
    "sg:address":"256 Central Ave",
    "sg:city":"Jersey City",
    "sg:classifiers":[
        {
            "category":"Shopping",
            "subcategory":"Discount & Variety Stores",
            "type":"Retail Goods"
        }
    ],
    "sg:phone":"+1   ",
    "sg:postcode":"07307",
    "sg:province":"NJ",
    "wof:name":"C H Martin Co Of New Jersey",
    "wof:placetype":"venue"
},
  "geometry": {"coordinates":[-74.050951,40.743466],"type":"Point"}
}