{
  "type": "Feature",
  "properties": {
    "addr:full":"5627 Berkshire Valley Rd Oak Ridge NJ 07438",
    "addr:housenumber":"5627",
    "addr:postcode":"07438",
    "addr:street":"Berkshire Valley Rd",
    "iso:country":"US",
    "sg:address":"5627 Berkshire Valley Rd",
    "sg:city":"Oak Ridge",
    "sg:classifiers":[
        {
            "category":"Building & Trades",
            "subcategory":"Construction",
            "type":"Services"
        }
    ],
    "sg:phone":"+1 973 697 3105",
    "sg:postcode":"07438",
    "sg:province":"NJ",
    "sg:tags":[
        "general",
        "contractor"
    ],
    "wof:name":"Fein Construction Inc",
    "wof:placetype":"venue"
},
  "geometry": {"coordinates":[-74.51244,41.028191],"type":"Point"}
}