{
  "type": "Feature",
  "properties": {
    "iso:country":"US",
    "sg:address":"306 Sudbury Rd",
    "sg:city":"Point Pleasant Beach",
    "sg:classifiers":[
        {
            "category":"Manufacturing",
            "subcategory":"Watercraft",
            "type":"Manufacturing & Wholesale Goods"
        }
    ],
    "sg:phone":"+1 732 295 2123",
    "sg:postcode":"08742",
    "sg:province":"NJ",
    "wof:name":"Leah Enterprises Inc",
    "wof:placetype":"venue"
},
  "geometry": {"coordinates":[-74.08667,40.090522],"type":"Point"}
}