{
  "type": "Feature",
  "properties": {
    "iso:country":"US",
    "sg:address":"296 Stuyvesant Ave",
    "sg:city":"Lyndhurst",
    "sg:classifiers":[
        {
            "category":"Retail",
            "subcategory":"Laundry & Dry Cleaning",
            "type":"Services"
        }
    ],
    "sg:phone":"+1 201 964 0327",
    "sg:postcode":"07071",
    "sg:province":"NJ",
    "wof:name":"Sook's Cleaner",
    "wof:placetype":"venue"
},
  "geometry": {"coordinates":[-74.126801,40.813801],"type":"Point"}
}