{
  "type": "Feature",
  "properties": {
    "addr:full":"1735 Union Ave Hazlet NJ 07730",
    "addr:housenumber":"1735",
    "addr:postcode":"07730",
    "addr:street":"Union Ave",
    "iso:country":"US",
    "sg:address":"1735 Union Ave",
    "sg:city":"Hazlet",
    "sg:classifiers":[
        {
            "category":"Professional",
            "type":"Services"
        }
    ],
    "sg:phone":"+1   ",
    "sg:postcode":"07730",
    "sg:province":"NJ",
    "wof:name":"Ammj Inc",
    "wof:placetype":"venue"
},
  "geometry": {"coordinates":[-74.159712,40.423121],"type":"Point"}
}