{
  "type": "Feature",
  "properties": {
    "iso:country":"US",
    "sg:address":"107 Watchung Ave",
    "sg:city":"Plainfield",
    "sg:classifiers":[
        {
            "category":"Retail",
            "subcategory":"Portrait Studio",
            "type":"Services"
        }
    ],
    "sg:phone":"+1   ",
    "sg:postcode":"07060",
    "sg:province":"NJ",
    "sg:tags":[
        "photo",
        "photography",
        "commercial"
    ],
    "sg:website":"www.normandystudio.com",
    "wof:name":"Normandy Studio",
    "wof:placetype":"venue"
},
  "geometry": {"coordinates":[-74.426275,40.62217],"type":"Point"}
}