{
  "type": "Feature",
  "properties": {
    "iso:country":"US",
    "sg:address":"237 Randolph Ave",
    "sg:city":"Jersey City",
    "sg:classifiers":[
        {
            "category":"Recreation",
            "type":"Entertainment"
        }
    ],
    "sg:phone":"+1 201 451 2888",
    "sg:postcode":"07304",
    "sg:province":"NJ",
    "wof:name":"Corner Pocket Lounge",
    "wof:placetype":"venue"
},
  "geometry": {"coordinates":[-74.069689,40.71254],"type":"Point"}
}