{
  "type": "Feature",
  "properties": {
    "iso:country":"US",
    "sg:address":"243 Pierce St",
    "sg:city":"Fairfield",
    "sg:classifiers":[
        {
            "category":"Home & Garden",
            "subcategory":"Home Furnishings",
            "type":"Retail Goods"
        }
    ],
    "sg:phone":"+1   ",
    "sg:postcode":"07080",
    "sg:province":"NJ",
    "wof:name":"Creatively Yours",
    "wof:placetype":"venue"
},
  "geometry": {"coordinates":[-74.40142400000001,40.580712],"type":"Point"}
}