{
  "type": "Feature",
  "properties": {
    "iso:country":"US",
    "sg:address":"87 Cooper Ave",
    "sg:city":"Montclair",
    "sg:classifiers":[
        {
            "category":"Professional",
            "type":"Services"
        }
    ],
    "sg:phone":"+1 973 746 8721",
    "sg:postcode":"07043",
    "sg:province":"NJ",
    "sg:tags":[
        "establishment"
    ],
    "wof:name":"Canelo & Assoc",
    "wof:placetype":"venue"
},
  "geometry": {"coordinates":[-74.201069,40.838321],"type":"Point"}
}