{
  "type": "Feature",
  "properties": {
    "addr:full":"255 Main St Ridgefield Park NJ 07660",
    "addr:housenumber":"255",
    "addr:postcode":"07660",
    "addr:street":"Main St",
    "iso:country":"US",
    "sg:address":"255 Main St",
    "sg:city":"Ridgefield Park",
    "sg:classifiers":[
        {
            "category":"Professional",
            "subcategory":"Management & Consulting",
            "type":"Services"
        }
    ],
    "sg:phone":"+1 201 807 0580",
    "sg:postcode":"07660",
    "sg:province":"NJ",
    "wof:name":"Evans Varelas Associates Inc",
    "wof:placetype":"venue"
},
  "geometry": {"coordinates":[-74.024619,40.858678],"type":"Point"}
}