{
  "type": "Feature",
  "properties": {
    "addr:full":"500 E Front St Florence NJ 08518",
    "addr:housenumber":"500",
    "addr:postcode":"08518",
    "addr:street":"E Front St",
    "iso:country":"US",
    "sg:address":"500 E Front St",
    "sg:city":"Florence",
    "sg:classifiers":[
        {
            "category":"Education",
            "subcategory":"School",
            "type":"Public Place"
        }
    ],
    "sg:phone":"+1 609 499 4647",
    "sg:postcode":"08518",
    "sg:province":"NJ",
    "sg:tags":[
        "high",
        "middle",
        "elementary"
    ],
    "sg:website":"florence.k12.nj.us",
    "wof:name":"Florence Township of",
    "wof:placetype":"venue"
},
  "geometry": {"coordinates":[-74.79704099999999,40.119897],"type":"Point"}
}