{
  "type": "Feature",
  "properties": {
    "iso:country":"US",
    "sg:address":"8 Hadrian Dr",
    "sg:city":"Livingston",
    "sg:classifiers":[
        {
            "category":"Shopping",
            "subcategory":"Computers & Home Electronics",
            "type":"Retail Goods"
        }
    ],
    "sg:phone":"+1 973 597 1400",
    "sg:postcode":"07039",
    "sg:province":"NJ",
    "sg:tags":[
        "parts",
        "supply"
    ],
    "wof:name":"Micro Fine Intl Inc",
    "wof:placetype":"venue"
},
  "geometry": {"coordinates":[-74.292823,40.795487],"type":"Point"}
}