{
  "type": "Feature",
  "properties": {
    "addr:full":"138 Redwood Ave Paterson NJ 07522",
    "addr:housenumber":"138",
    "addr:postcode":"07522",
    "addr:street":"Redwood Ave",
    "iso:country":"US",
    "sg:address":"138 Redwood Ave",
    "sg:city":"Paterson",
    "sg:classifiers":[
        {
            "category":"Manufacturing",
            "subcategory":"Printing",
            "type":"Manufacturing & Wholesale Goods"
        }
    ],
    "sg:phone":"+1 973 956 7344",
    "sg:postcode":"07522",
    "sg:province":"NJ",
    "sg:tags":[
        "commercial"
    ],
    "wof:name":"Tanbil Publications",
    "wof:placetype":"venue"
},
  "geometry": {"coordinates":[-74.18635999999999,40.923603],"type":"Point"}
}