{
  "type": "Feature",
  "properties": {
    "addr:full":"27 Briar Cir Green Brook NJ 08812",
    "addr:housenumber":"27",
    "addr:postcode":"08812",
    "addr:street":"Briar Cir",
    "iso:country":"US",
    "sg:address":"27 Briar Cir",
    "sg:city":"Green Brook",
    "sg:classifiers":[
        {
            "category":"Restaurant",
            "type":"Food & Drink"
        }
    ],
    "sg:phone":"+1 732 469 4066",
    "sg:postcode":"08812",
    "sg:province":"NJ",
    "wof:name":"Phil's Place",
    "wof:placetype":"venue"
},
  "geometry": {"coordinates":[-74.460739,40.603633],"type":"Point"}
}