{
  "type": "Feature",
  "properties": {
    "iso:country":"US",
    "sg:address":"16 Lakeview Rd",
    "sg:city":"Deal",
    "sg:classifiers":[
        {
            "category":"Building & Trades",
            "subcategory":"Construction",
            "type":"Services"
        }
    ],
    "sg:phone":"+1 732 531 1510",
    "sg:postcode":"07723",
    "sg:province":"NJ",
    "sg:tags":[
        "carpentry",
        "contractor"
    ],
    "wof:name":"Kelly Contracting",
    "wof:placetype":"venue"
},
  "geometry": {"coordinates":[-74.003658,40.242628],"type":"Point"}
}