{
  "type": "Feature",
  "properties": {
    "addr:full":"50 N Black Horse Pike Bellmawr NJ 08031",
    "addr:housenumber":"50",
    "addr:postcode":"08031",
    "addr:street":"N Black Horse Pike",
    "iso:country":"US",
    "sg:address":"50 N Black Horse Pike",
    "sg:city":"Bellmawr",
    "sg:classifiers":[
        {
            "category":"Retail",
            "subcategory":"Auto Repair",
            "type":"Services"
        }
    ],
    "sg:phone":"+1 856 931 9834",
    "sg:postcode":"08031",
    "sg:province":"NJ",
    "wof:name":"Deangelis Auto Repair",
    "wof:placetype":"venue"
},
  "geometry": {"coordinates":[-75.08094699999999,39.868826],"type":"Point"}
}