{
  "type": "Feature",
  "properties": {
    "addr:full":"100 Passaic Ave Ste 220 Fairfield NJ 07004",
    "addr:housenumber":"100",
    "addr:postcode":"07004",
    "addr:street":"Passaic Ave Ste 220",
    "iso:country":"US",
    "sg:address":"100 Passaic Ave Ste 220",
    "sg:city":"Fairfield",
    "sg:classifiers":[
        {
            "category":"Communications",
            "subcategory":"Newspaper",
            "type":"Services"
        }
    ],
    "sg:phone":"+1 973 882 4700",
    "sg:postcode":"07004",
    "sg:province":"NJ",
    "sg:tags":[
        "print",
        "medium"
    ],
    "sg:website":"www.dentistrytoday.com",
    "wof:name":"Dentistry Today",
    "wof:placetype":"venue"
},
  "geometry": {"coordinates":[-74.279258,40.870956],"type":"Point"}
}