{
  "type": "Feature",
  "properties": {
    "iso:country":"US",
    "sg:address":"494 Prospect Ave",
    "sg:city":"West Orange",
    "sg:classifiers":[
        {
            "category":"Health Services",
            "subcategory":"Chiropractor",
            "type":"Services"
        }
    ],
    "sg:phone":"+1 973 736 9797",
    "sg:postcode":"07052",
    "sg:province":"NJ",
    "wof:name":"Nadelberg William DC",
    "wof:placetype":"venue"
},
  "geometry": {"coordinates":[-74.25520899999999,40.78938],"type":"Point"}
}