{
  "type": "Feature",
  "properties": {
    "iso:country":"US",
    "sg:address":"4 Woolf Rd",
    "sg:city":"Milford",
    "sg:classifiers":[
        {
            "category":"Professional",
            "subcategory":"Business Services",
            "type":"Services"
        }
    ],
    "sg:phone":"+1   ",
    "sg:postcode":"08848",
    "sg:province":"NJ",
    "wof:name":"Plantings",
    "wof:placetype":"venue"
},
  "geometry": {"coordinates":[-75.03237799999999,40.606657],"type":"Point"}
}