{
  "type": "Feature",
  "properties": {
    "iso:country":"US",
    "sg:address":"110 Oakford Ave",
    "sg:city":"Delanco",
    "sg:classifiers":[
        {
            "category":"Real Estate",
            "subcategory":"Real Estate Agent",
            "type":"Services"
        }
    ],
    "sg:phone":"+1 856 303 2456",
    "sg:postcode":"08075",
    "sg:province":"NJ",
    "sg:tags":[
        "inspection"
    ],
    "sg:website":"www.daytoninspection.com",
    "wof:name":"Dayton Inspection Svc Inc",
    "wof:placetype":"venue"
},
  "geometry": {"coordinates":[-74.951801,40.054165],"type":"Point"}
}