{
  "type": "Feature",
  "properties": {
    "addr:full":"51 Everett Dr Princeton Jct NJ 08550",
    "addr:housenumber":"51",
    "addr:postcode":"08550",
    "addr:street":"Everett Dr",
    "iso:country":"US",
    "sg:address":"51 Everett Dr",
    "sg:city":"Princeton Jct",
    "sg:classifiers":[
        {
            "category":"Professional",
            "subcategory":"Research",
            "type":"Services"
        }
    ],
    "sg:phone":"+1 609 799 7300",
    "sg:postcode":"08550",
    "sg:province":"NJ",
    "sg:tags":[
        "environmental",
        "ecological"
    ],
    "sg:website":"www.ewma.com",
    "wof:name":"Environmental Waste Management",
    "wof:placetype":"venue"
},
  "geometry": {"coordinates":[-74.637956,40.303686],"type":"Point"}
}