{
  "type": "Feature",
  "properties": {
    "addr:full":"230 Franklin Ave Cliffside Park NJ 07010",
    "addr:housenumber":"230",
    "addr:postcode":"07010",
    "addr:street":"Franklin Ave",
    "iso:country":"US",
    "sg:address":"230 Franklin Ave",
    "sg:city":"Cliffside Park",
    "sg:classifiers":[
        {
            "category":"Professional",
            "subcategory":"Business Services",
            "type":"Services"
        }
    ],
    "sg:phone":"+1   ",
    "sg:postcode":"07010",
    "sg:province":"NJ",
    "wof:name":"Oster Group Inc",
    "wof:placetype":"venue"
},
  "geometry": {"coordinates":[-73.982242,40.828264],"type":"Point"}
}