{
  "type": "Feature",
  "properties": {
    "addr:full":"643 Washington St Cape May NJ 08204",
    "addr:housenumber":"643",
    "addr:postcode":"08204",
    "addr:street":"Washington St",
    "iso:country":"US",
    "sg:address":"643 Washington St",
    "sg:city":"Cape May",
    "sg:classifiers":[
        {
            "category":"Government",
            "subcategory":"Office",
            "type":"Public Place"
        }
    ],
    "sg:phone":"+1   ",
    "sg:postcode":"08204",
    "sg:province":"NJ",
    "sg:tags":[
        "hall",
        "convention"
    ],
    "wof:name":"Convention Hall",
    "wof:placetype":"venue"
},
  "geometry": {"coordinates":[-74.91967099999999,38.935027],"type":"Point"}
}