{
  "type": "Feature",
  "properties": {
    "iso:country":"US",
    "sg:address":"1001 Teaneck Rd",
    "sg:city":"Teaneck",
    "sg:classifiers":[
        {
            "category":"Professional",
            "subcategory":"Lawyer & Legal Services",
            "type":"Services"
        }
    ],
    "sg:phone":"+1 201 357 4259",
    "sg:postcode":"07666",
    "sg:province":"NJ",
    "wof:name":"Barry D Friedman ESQ",
    "wof:placetype":"venue"
},
  "geometry": {"coordinates":[-74.00463999999999,40.888713],"type":"Point"}
}