{
  "type": "Feature",
  "properties": {
    "addr:full":"50 Goodale Ave Dover NJ 07801",
    "addr:housenumber":"50",
    "addr:postcode":"07801",
    "addr:street":"Goodale Ave",
    "iso:country":"US",
    "sg:address":"50 Goodale Ave",
    "sg:city":"Dover",
    "sg:classifiers":[
        {
            "category":"Building & Trades",
            "subcategory":"Construction",
            "type":"Services"
        }
    ],
    "sg:phone":"+1 973 989 5888",
    "sg:postcode":"07801",
    "sg:province":"NJ",
    "sg:tags":[
        "painter"
    ],
    "wof:name":"Paradigm Services Inc",
    "wof:placetype":"venue"
},
  "geometry": {"coordinates":[-74.56377999999999,40.890211],"type":"Point"}
}