{
  "type": "Feature",
  "properties": {
    "iso:country":"US",
    "sg:address":"33 S Fullerton Ave",
    "sg:city":"Montclair",
    "sg:classifiers":[
        {
            "category":"Health Services",
            "subcategory":"Doctor",
            "type":"Services"
        }
    ],
    "sg:phone":"+1 973 509 0177",
    "sg:postcode":"07042",
    "sg:province":"NJ",
    "wof:name":"Family Resource Center",
    "wof:placetype":"venue"
},
  "geometry": {"coordinates":[-74.21790300000001,40.8125],"type":"Point"}
}