{
  "type": "Feature",
  "properties": {
    "addr:full":"43 Stiles Ln Ste 2 Pine Brook NJ 07058",
    "addr:housenumber":"43",
    "addr:postcode":"07058",
    "addr:street":"Stiles Ln Ste 2 Pine",
    "iso:country":"US",
    "sg:address":"43 Stiles Ln Ste 2",
    "sg:city":"Pine Brook",
    "sg:classifiers":[
        {
            "category":"Wholesale",
            "subcategory":"Computers",
            "type":"Manufacturing & Wholesale Goods"
        }
    ],
    "sg:phone":"+1 973 396 2903",
    "sg:postcode":"07058",
    "sg:province":"NJ",
    "wof:name":"Electric Turnpike",
    "wof:placetype":"venue"
},
  "geometry": {"coordinates":[-74.36081299999999,40.870349],"type":"Point"}
}