{
  "type": "Feature",
  "properties": {
    "iso:country":"US",
    "sg:address":"164 San Joaquin Ct",
    "sg:city":"Holmdel",
    "sg:classifiers":[
        {
            "category":"Professional",
            "type":"Services"
        }
    ],
    "sg:phone":"+1   ",
    "sg:postcode":"07733",
    "sg:province":"NJ",
    "wof:name":"RG Tool Co Corp",
    "wof:placetype":"venue"
},
  "geometry": {"coordinates":[-74.147566,40.397442],"type":"Point"}
}