{
  "type": "Feature",
  "properties": {
    "addr:full":"16 Bloomfield Ave Verona NJ 07044",
    "addr:housenumber":"16",
    "addr:postcode":"07044",
    "addr:street":"Bloomfield Ave",
    "iso:country":"US",
    "sg:address":"16 Bloomfield Ave",
    "sg:city":"Verona",
    "sg:classifiers":[
        {
            "category":"Retail",
            "subcategory":"Auto Repair",
            "type":"Services"
        }
    ],
    "sg:phone":"+1 973 744 1021",
    "sg:postcode":"07044",
    "sg:province":"NJ",
    "sg:tags":[
        "body",
        "towing"
    ],
    "wof:name":"Mountain Auto Body Inc",
    "wof:placetype":"venue"
},
  "geometry": {"coordinates":[-74.228302,40.825199],"type":"Point"}
}