{
  "type": "Feature",
  "properties": {
    "addr:full":"14 Hollywood Ave Somerset NJ 08873",
    "addr:housenumber":"14",
    "addr:postcode":"08873",
    "addr:street":"Hollywood Ave",
    "iso:country":"US",
    "sg:address":"14 Hollywood Ave",
    "sg:city":"Somerset",
    "sg:classifiers":[
        {
            "category":"Government",
            "subcategory":"Fire Station",
            "type":"Public Place"
        }
    ],
    "sg:phone":"+1   ",
    "sg:postcode":"08873",
    "sg:province":"NJ",
    "sg:tags":[
        "protection"
    ],
    "wof:name":"Somerset Vlntr Fire Rescue Co",
    "wof:placetype":"venue"
},
  "geometry": {"coordinates":[-74.49829200000001,40.526489],"type":"Point"}
}