{
  "type": "Feature",
  "properties": {
    "iso:country":"US",
    "sg:address":"2700 Allaire Rd",
    "sg:city":"Wall Township",
    "sg:classifiers":[
        {
            "category":"Education",
            "subcategory":"Library",
            "type":"Public Place"
        }
    ],
    "sg:phone":"+1 732 449 8877",
    "sg:postcode":"07719",
    "sg:province":"NJ",
    "wof:name":"Wall Township Library",
    "wof:placetype":"venue"
},
  "geometry": {"coordinates":[-74.065235,40.15278],"type":"Point"}
}