{
  "type": "Feature",
  "properties": {
    "iso:country":"US",
    "sg:address":"124 Elliott Pl",
    "sg:city":"Rutherford",
    "sg:classifiers":[
        {
            "category":"Retail",
            "subcategory":"Repair Shop",
            "type":"Services"
        }
    ],
    "sg:phone":"+1   ",
    "sg:postcode":"07070",
    "sg:province":"NJ",
    "wof:name":"Door Jamb Repair LLC",
    "wof:placetype":"venue"
},
  "geometry": {"coordinates":[-74.110344,40.829264],"type":"Point"}
}