{
  "type": "Feature",
  "properties": {
    "addr:full":"184 Doretta St Westwood NJ 07675",
    "addr:housenumber":"184",
    "addr:postcode":"07675",
    "addr:street":"Doretta St",
    "iso:country":"US",
    "sg:address":"184 Doretta St",
    "sg:city":"Westwood",
    "sg:classifiers":[
        {
            "category":"Professional",
            "subcategory":"Lawyer & Legal Services",
            "type":"Services"
        }
    ],
    "sg:phone":"+1   ",
    "sg:postcode":"07675",
    "sg:province":"NJ",
    "wof:name":"Dbt Home Office",
    "wof:placetype":"venue"
},
  "geometry": {"coordinates":[-74.00812999999999,40.992142],"type":"Point"}
}