{
  "type": "Feature",
  "properties": {
    "iso:country":"US",
    "sg:address":"138 Market St",
    "sg:city":"Perth Amboy",
    "sg:classifiers":[
        {
            "category":"Health Services",
            "subcategory":"Doctor",
            "type":"Services"
        }
    ],
    "sg:phone":"+1 732 826 8284",
    "sg:postcode":"08861",
    "sg:province":"NJ",
    "wof:name":"Benites Margarita MD",
    "wof:placetype":"venue"
},
  "geometry": {"coordinates":[-74.269096,40.507301],"type":"Point"}
}