{
  "type": "Feature",
  "properties": {
    "iso:country":"US",
    "sg:address":"9 Bakers Ct",
    "sg:city":"Clifton",
    "sg:classifiers":[
        {
            "category":"Building & Trades",
            "subcategory":"Construction",
            "type":"Services"
        }
    ],
    "sg:phone":"+1 973 546 6100",
    "sg:postcode":"07011",
    "sg:province":"NJ",
    "sg:tags":[
        "contractor"
    ],
    "wof:name":"Morlot Construction Corp",
    "wof:placetype":"venue"
},
  "geometry": {"coordinates":[-74.13224200000001,40.891027],"type":"Point"}
}