{
  "type": "Feature",
  "properties": {
    "iso:country":"US",
    "sg:address":"14 Courtright Rd",
    "sg:city":"Sussex",
    "sg:classifiers":[
        {
            "category":"Professional",
            "subcategory":"Art Services",
            "type":"Services"
        }
    ],
    "sg:phone":"+1 973 875 1547",
    "sg:postcode":"07461",
    "sg:province":"NJ",
    "sg:tags":[
        "photography",
        "commercial"
    ],
    "wof:name":"A Different Perspective",
    "wof:placetype":"venue"
},
  "geometry": {"coordinates":[-74.632137,41.32362],"type":"Point"}
}