{
  "type": "Feature",
  "properties": {
    "addr:full":"1224 Anderson Ave Fort Lee NJ 07024",
    "addr:housenumber":"1224",
    "addr:postcode":"07024",
    "addr:street":"Anderson Ave",
    "iso:country":"US",
    "sg:address":"1224 Anderson Ave",
    "sg:city":"Fort Lee",
    "sg:classifiers":[
        {
            "category":"Home & Garden",
            "subcategory":"Carpets & Floor Coverings",
            "type":"Retail Goods"
        }
    ],
    "sg:phone":"+1   ",
    "sg:postcode":"07024",
    "sg:province":"NJ",
    "wof:name":"Manganos",
    "wof:placetype":"venue"
},
  "geometry": {"coordinates":[-73.98100700000001,40.840335],"type":"Point"}
}