{
  "type": "Feature",
  "properties": {
    "iso:country":"US",
    "sg:address":"225 W Kings Hwy",
    "sg:city":"Mount Ephraim",
    "sg:classifiers":[
        {
            "category":"Education",
            "subcategory":"School",
            "type":"Public Place"
        }
    ],
    "sg:phone":"+1   ",
    "sg:postcode":"08059",
    "sg:province":"NJ",
    "wof:name":"Mary Bray Elementary School",
    "wof:placetype":"venue"
},
  "geometry": {"coordinates":[-75.089868,39.88098],"type":"Point"}
}