{
  "type": "Feature",
  "properties": {
    "iso:country":"US",
    "sg:address":"122 Peach St",
    "sg:city":"Tinton Falls",
    "sg:classifiers":[
        {
            "category":"Taxi",
            "type":"Transportation"
        }
    ],
    "sg:phone":"+1 732 741 6405",
    "sg:postcode":"07724",
    "sg:province":"NJ",
    "sg:tags":[
        "taxicab"
    ],
    "wof:name":"Little Silver Cab",
    "wof:placetype":"venue"
},
  "geometry": {"coordinates":[-74.083035,40.3309],"type":"Point"}
}