{
  "type": "Feature",
  "properties": {
    "addr:full":"19 19th Ave Belleville NJ 07103",
    "addr:housenumber":"19",
    "addr:postcode":"07103",
    "addr:street":"19Th Ave",
    "iso:country":"US",
    "sg:address":"19 19th Ave",
    "sg:city":"Belleville",
    "sg:classifiers":[
        {
            "category":"Building & Trades",
            "subcategory":"Construction",
            "type":"Services"
        }
    ],
    "sg:phone":"+1 973 450 4312",
    "sg:postcode":"07103",
    "sg:province":"NJ",
    "sg:tags":[
        "house"
    ],
    "wof:name":"Franklin Home Improvement",
    "wof:placetype":"venue"
},
  "geometry": {"coordinates":[-74.208511,40.73094],"type":"Point"}
}