{
  "type": "Feature",
  "properties": {
    "iso:country":"US",
    "sg:address":"30 Magnolia St",
    "sg:city":"Belleville",
    "sg:classifiers":[
        {
            "category":"Education",
            "subcategory":"School",
            "type":"Public Place"
        }
    ],
    "sg:phone":"+1 973 450 3540",
    "sg:postcode":"07109",
    "sg:province":"NJ",
    "wof:name":"Grammar School #4",
    "wof:placetype":"venue"
},
  "geometry": {"coordinates":[-74.180589,40.781674],"type":"Point"}
}