{
  "type": "Feature",
  "properties": {
    "addr:full":"45 Goffle Rd Hawthorne NJ 07506",
    "addr:housenumber":"45",
    "addr:postcode":"07506",
    "addr:street":"Goffle Rd",
    "iso:country":"US",
    "sg:address":"45 Goffle Rd",
    "sg:city":"Hawthorne",
    "sg:classifiers":[
        {
            "category":"Wholesale",
            "subcategory":"Electrical",
            "type":"Manufacturing & Wholesale Goods"
        }
    ],
    "sg:phone":"+1 973 427 4283",
    "sg:postcode":"07506",
    "sg:province":"NJ",
    "wof:name":"U S Appliance",
    "wof:placetype":"venue"
},
  "geometry": {"coordinates":[-74.1653,40.936681],"type":"Point"}
}