{
  "type": "Feature",
  "properties": {
    "addr:full":"10 Elm St Allendale NJ 07401",
    "addr:housenumber":"10",
    "addr:postcode":"07401",
    "addr:street":"Elm St",
    "iso:country":"US",
    "sg:address":"10 Elm St",
    "sg:city":"Allendale",
    "sg:classifiers":[
        {
            "category":"Real Estate",
            "subcategory":"Real Estate Operator",
            "type":"Services"
        }
    ],
    "sg:phone":"+1   ",
    "sg:postcode":"07401",
    "sg:province":"NJ",
    "sg:tags":[
        "company",
        "mortgage",
        "holding"
    ],
    "wof:name":"DJakhar Construction Co Inc",
    "wof:placetype":"venue"
},
  "geometry": {"coordinates":[-74.128507,41.03216],"type":"Point"}
}