{
  "type": "Feature",
  "properties": {
    "addr:full":"301 Center Ave Westwood NJ 07675",
    "addr:housenumber":"301",
    "addr:postcode":"07675",
    "addr:street":"Center Ave",
    "iso:country":"US",
    "sg:address":"301 Center Ave",
    "sg:city":"Westwood",
    "sg:classifiers":[
        {
            "category":"Food & Beverages",
            "subcategory":"Groceries & Convenience Stores",
            "type":"Retail Goods"
        }
    ],
    "sg:phone":"+1 201 263 0656",
    "sg:postcode":"07675",
    "sg:province":"NJ",
    "wof:name":"Center Store Food",
    "wof:placetype":"venue"
},
  "geometry": {"coordinates":[-74.032506,40.99286],"type":"Point"}
}