{
  "type": "Feature",
  "properties": {
    "iso:country":"US",
    "sg:address":"501 Spruce St",
    "sg:city":"Trenton",
    "sg:classifiers":[
        {
            "category":"Building & Trades",
            "subcategory":"Cleaning & Sanitation",
            "type":"Services"
        }
    ],
    "sg:phone":"+1 609 989 7711",
    "sg:postcode":"08638",
    "sg:province":"NJ",
    "sg:tags":[
        "supply"
    ],
    "wof:name":"Whistle Building Maintenance",
    "wof:placetype":"venue"
},
  "geometry": {"coordinates":[-74.746436,40.237653],"type":"Point"}
}