{
  "type": "Feature",
  "properties": {
    "iso:country":"US",
    "sg:address":"2 N Main St",
    "sg:city":"Cranbury",
    "sg:classifiers":[
        {
            "category":"Building & Trades",
            "subcategory":"Construction",
            "type":"Services"
        }
    ],
    "sg:phone":"+1 609 395 7272",
    "sg:postcode":"08512",
    "sg:province":"NJ",
    "sg:tags":[
        "hanging",
        "painter",
        "contractor"
    ],
    "wof:name":"Meyer & Meyer",
    "wof:placetype":"venue"
},
  "geometry": {"coordinates":[-74.51617,40.311093],"type":"Point"}
}