{
  "type": "Feature",
  "properties": {
    "addr:full":"5 Simpson Ave Mt Tabor NJ 07878",
    "addr:housenumber":"5",
    "addr:postcode":"07878",
    "addr:street":"Simpson Ave",
    "iso:country":"US",
    "sg:address":"5 Simpson Ave",
    "sg:city":"Mt Tabor",
    "sg:classifiers":[
        {
            "category":"Organizations",
            "subcategory":"Religious Organization",
            "type":"Services"
        }
    ],
    "sg:phone":"+1 973 627 4243",
    "sg:postcode":"07878",
    "sg:province":"NJ",
    "sg:tags":[
        "church"
    ],
    "wof:name":"United Methodist Church",
    "wof:placetype":"venue"
},
  "geometry": {"coordinates":[-74.480492,40.872316],"type":"Point"}
}