{
  "type": "Feature",
  "properties": {
    "iso:country":"US",
    "sg:address":"2100 Central Rd",
    "sg:city":"Fort Lee",
    "sg:classifiers":[
        {
            "category":"Insurance",
            "subcategory":"Hazard Insurance",
            "type":"Services"
        }
    ],
    "sg:phone":"+1 201 592 1300",
    "sg:postcode":"07024",
    "sg:province":"NJ",
    "sg:tags":[
        "profit",
        "sharing",
        "pension",
        "plan"
    ],
    "sg:website":"www.melon.com",
    "wof:name":"Affiliated Computer Svc",
    "wof:placetype":"venue"
},
  "geometry": {"coordinates":[-73.965283,40.852686],"type":"Point"}
}