{
  "type": "Feature",
  "properties": {
    "iso:country":"US",
    "sg:address":"94 Old Camplain Rd",
    "sg:city":"Hillsborough",
    "sg:classifiers":[
        {
            "category":"Shopping",
            "subcategory":"Computers & Home Electronics",
            "type":"Retail Goods"
        }
    ],
    "sg:phone":"+1 908 359 9266",
    "sg:postcode":"08844",
    "sg:province":"NJ",
    "sg:tags":[
        "equipment",
        "dealer"
    ],
    "sg:website":"www.image-land.com",
    "wof:name":"Image-Land Technologies Inc",
    "wof:placetype":"venue"
},
  "geometry": {"coordinates":[-74.617373,40.534586],"type":"Point"}
}