{
  "type": "Feature",
  "properties": {
    "addr:full":"321 Main St Boonton NJ 07005",
    "addr:housenumber":"321",
    "addr:postcode":"07005",
    "addr:street":"Main St",
    "iso:country":"US",
    "sg:address":"321 Main St",
    "sg:city":"Boonton",
    "sg:classifiers":[
        {
            "category":"Retail",
            "subcategory":"Repair Shop",
            "type":"Services"
        }
    ],
    "sg:phone":"+1 973 299 1344",
    "sg:postcode":"07005",
    "sg:province":"NJ",
    "sg:tags":[
        "repairing",
        "lamp"
    ],
    "wof:name":"Blue Shutters Antiques",
    "wof:placetype":"venue"
},
  "geometry": {"coordinates":[-74.408675,40.904036],"type":"Point"}
}