{
  "type": "Feature",
  "properties": {
    "iso:country":"US",
    "sg:address":"1200 Ocean St",
    "sg:city":"Forked River",
    "sg:classifiers":[
        {
            "category":"Retail",
            "subcategory":"Auto Repair",
            "type":"Services"
        }
    ],
    "sg:phone":"+1 609 971 3258",
    "sg:postcode":"08731",
    "sg:province":"NJ",
    "sg:tags":[
        "body"
    ],
    "wof:name":"Spatz Exteriors Improveme",
    "wof:placetype":"venue"
},
  "geometry": {"coordinates":[-74.203242,39.833186],"type":"Point"}
}