{
  "type": "Feature",
  "properties": {
    "iso:country":"US",
    "sg:address":"158 S White Horse Pike",
    "sg:city":"Audubon",
    "sg:classifiers":[
        {
            "category":"Retail",
            "subcategory":"Car Wash",
            "type":"Services"
        }
    ],
    "sg:phone":"+1 856 546 8439",
    "sg:postcode":"08106",
    "sg:province":"NJ",
    "sg:tags":[
        "automobile",
        "detail",
        "clean",
        "accessory"
    ],
    "sg:website":"www.autodogz.com",
    "wof:name":"Auto Dogz",
    "wof:placetype":"venue"
},
  "geometry": {"coordinates":[-75.06849699999999,39.893902],"type":"Point"}
}