{
  "type": "Feature",
  "properties": {
    "addr:full":"38 Laurel St Woodbury NJ 08096",
    "addr:housenumber":"38",
    "addr:postcode":"08096",
    "addr:street":"Laurel St",
    "iso:country":"US",
    "sg:address":"38 Laurel St",
    "sg:city":"Woodbury",
    "sg:classifiers":[
        {
            "category":"Train Station",
            "subcategory":"Rail",
            "type":"Transportation"
        }
    ],
    "sg:phone":"+1 856 845 8574",
    "sg:postcode":"08096",
    "sg:province":"NJ",
    "sg:tags":[
        "stairway",
        "railing",
        "rails",
        "accessory"
    ],
    "wof:name":"Woodbury Iron Works",
    "wof:placetype":"venue"
},
  "geometry": {"coordinates":[-75.14912699999999,39.837246],"type":"Point"}
}