{
  "type": "Feature",
  "properties": {
    "addr:full":"10 Garber Sq Ridgewood NJ 07450",
    "addr:housenumber":"10",
    "addr:postcode":"07450",
    "addr:street":"Garber Sq",
    "iso:country":"US",
    "sg:address":"10 Garber Sq",
    "sg:city":"Ridgewood",
    "sg:classifiers":[
        {
            "category":"Personal",
            "type":"Services"
        }
    ],
    "sg:phone":"+1   ",
    "sg:postcode":"07450",
    "sg:province":"NJ",
    "wof:name":"Balance Theraputic Massage",
    "wof:placetype":"venue"
},
  "geometry": {"coordinates":[-74.121599,40.980538],"type":"Point"}
}