{
  "type": "Feature",
  "properties": {
    "iso:country":"US",
    "sg:address":"37 Hanover Rd",
    "sg:city":"East Hanover",
    "sg:classifiers":[
        {
            "category":"Health Services",
            "subcategory":"Chiropractor",
            "type":"Services"
        }
    ],
    "sg:phone":"+1 973 887 1660",
    "sg:postcode":"07936",
    "sg:province":"NJ",
    "wof:name":"Chiropractic Health Ctr",
    "wof:placetype":"venue"
},
  "geometry": {"coordinates":[-74.37090999999999,40.80096],"type":"Point"}
}