{
  "type": "Feature",
  "properties": {
    "addr:full":"259 US Hwy 46 Budd Lake NJ 07828",
    "addr:housenumber":"259",
    "addr:postcode":"07828",
    "addr:street":"Us Hwy 46",
    "iso:country":"US",
    "sg:address":"259 US Hwy 46",
    "sg:city":"Budd Lake",
    "sg:classifiers":[
        {
            "category":"Home & Garden",
            "subcategory":"Hardware",
            "type":"Retail Goods"
        }
    ],
    "sg:phone":"+1 973 691 1315",
    "sg:postcode":"07828",
    "sg:province":"NJ",
    "wof:name":"Mount Olive Hardware",
    "wof:placetype":"venue"
},
  "geometry": {"coordinates":[-74.737033,40.869524],"type":"Point"}
}