{
  "type": "Feature",
  "properties": {
    "addr:full":"321 3rd St Lakewood NJ 08701",
    "addr:housenumber":"321",
    "addr:postcode":"08701",
    "addr:street":"3Rd St",
    "iso:country":"US",
    "sg:address":"321 3rd St",
    "sg:city":"Lakewood",
    "sg:classifiers":[
        {
            "category":"Building & Trades",
            "subcategory":"Construction",
            "type":"Services"
        }
    ],
    "sg:phone":"+1 732 363 0557",
    "sg:postcode":"08701",
    "sg:province":"NJ",
    "sg:tags":[
        "marking",
        "maintenance",
        "parking"
    ],
    "sg:website":"www.twp.lakewood.nj.us",
    "wof:name":"Lakewood Public Works",
    "wof:placetype":"venue"
},
  "geometry": {"coordinates":[-74.215125,40.093143],"type":"Point"}
}