{
  "type": "Feature",
  "properties": {
    "iso:country":"US",
    "sg:address":"302 Frank W Burr Blvd",
    "sg:city":"Teaneck",
    "sg:classifiers":[
        {
            "category":"Retail",
            "subcategory":"Repair Shop",
            "type":"Services"
        }
    ],
    "sg:phone":"+1 201 498 0404",
    "sg:postcode":"07666",
    "sg:province":"NJ",
    "sg:tags":[
        "lock",
        "locksmith"
    ],
    "wof:name":"Five Star Locksmith",
    "wof:placetype":"venue"
},
  "geometry": {"coordinates":[-74.00678600000001,40.872852],"type":"Point"}
}