{
  "type": "Feature",
  "properties": {
    "addr:full":"7 Cypress Ln Willingboro NJ 08046",
    "addr:housenumber":"7",
    "addr:postcode":"08046",
    "addr:street":"Cypress Ln",
    "iso:country":"US",
    "sg:address":"7 Cypress Ln",
    "sg:city":"Willingboro",
    "sg:classifiers":[
        {
            "category":"Organizations",
            "subcategory":"Community Association",
            "type":"Services"
        }
    ],
    "sg:phone":"+1 973 760 7155",
    "sg:postcode":"08046",
    "sg:province":"NJ",
    "wof:name":"Metamorphoo - Transforming Power Ministries, Inc.",
    "wof:placetype":"venue"
},
  "geometry": {"coordinates":[-74.90101900000001,40.024155],"type":"Point"}
}