{
  "type": "Feature",
  "properties": {
    "addr:full":"29 E 29th St Bayonne NJ 07002",
    "addr:housenumber":"29",
    "addr:postcode":"07002",
    "addr:street":"E 29Th St",
    "iso:country":"US",
    "sg:address":"29 E 29th St",
    "sg:city":"Bayonne",
    "sg:classifiers":[
        {
            "category":"Health Services",
            "subcategory":"Doctor",
            "type":"Services"
        }
    ],
    "sg:phone":"+1 201 436 8606",
    "sg:postcode":"07002",
    "sg:province":"NJ",
    "sg:tags":[
        "medical"
    ],
    "wof:name":"Ratzker Paul K MD",
    "wof:placetype":"venue"
},
  "geometry": {"coordinates":[-74.112773,40.667954],"type":"Point"}
}