{
  "type": "Feature",
  "properties": {
    "iso:country":"US",
    "sg:address":"5031 Industrial Rd",
    "sg:city":"Wall Township",
    "sg:classifiers":[
        {
            "category":"Wholesale",
            "subcategory":"Electrical",
            "type":"Manufacturing & Wholesale Goods"
        }
    ],
    "sg:phone":"+1 732 938 7592",
    "sg:postcode":"07727",
    "sg:province":"NJ",
    "sg:tags":[
        "equipment",
        "electronic",
        "supply"
    ],
    "sg:website":"www.sonetronics.com",
    "wof:name":"Sonetronics International",
    "wof:placetype":"venue"
},
  "geometry": {"coordinates":[-74.124135,40.192766],"type":"Point"}
}