{
  "type": "Feature",
  "properties": {
    "iso:country":"US",
    "sg:address":"743 Roosevelt Ave",
    "sg:city":"Carteret",
    "sg:classifiers":[
        {
            "category":"Autos & Motor Vehicles",
            "subcategory":"Fuel & Gas Station",
            "type":"Retail Goods"
        }
    ],
    "sg:phone":"+1 732 541 0844",
    "sg:postcode":"07008",
    "sg:province":"NJ",
    "sg:tags":[
        "repair",
        "oil"
    ],
    "wof:name":"Paul's Carteret Gulf",
    "wof:placetype":"venue"
},
  "geometry": {"coordinates":[-74.22580000000001,40.585999],"type":"Point"}
}