{
  "type": "Feature",
  "properties": {
    "iso:country":"US",
    "sg:address":"208 Pequest Dr",
    "sg:city":"Belvidere",
    "sg:classifiers":[
        {
            "category":"Recreation",
            "type":"Entertainment"
        }
    ],
    "sg:phone":"+1 908 475 8418",
    "sg:postcode":"07823",
    "sg:province":"NJ",
    "sg:tags":[
        "club",
        "membership"
    ],
    "wof:name":"Fairway Valley Golf Club",
    "wof:placetype":"venue"
},
  "geometry": {"coordinates":[-75.058627,40.828446],"type":"Point"}
}