{
  "type": "Feature",
  "properties": {
    "iso:country":"US",
    "sg:address":"44 Koeck Rd",
    "sg:city":"Hope",
    "sg:classifiers":[
        {
            "category":"Travel",
            "subcategory":"Campground",
            "type":"Entertainment"
        }
    ],
    "sg:phone":"+1 908 459 4370",
    "sg:postcode":"07832",
    "sg:province":"NJ",
    "sg:tags":[
        "camp"
    ],
    "wof:name":"Camp Warren",
    "wof:placetype":"venue"
},
  "geometry": {"coordinates":[-75.03178200000001,40.896605],"type":"Point"}
}