{
  "type": "Feature",
  "properties": {
    "addr:full":"1279 US Highway 46 Parsippany NJ 07054",
    "addr:housenumber":"1279",
    "addr:postcode":"07054",
    "addr:street":"Us Highway 46",
    "iso:country":"US",
    "sg:address":"1279 US Highway 46",
    "sg:city":"Parsippany",
    "sg:classifiers":[
        {
            "category":"Education",
            "subcategory":"Special Training",
            "type":"Public Place"
        }
    ],
    "sg:phone":"+1 973 335 5988",
    "sg:postcode":"07054",
    "sg:province":"NJ",
    "sg:tags":[
        "tutoring"
    ],
    "wof:name":"Jei Parsippanny Learning Center",
    "wof:placetype":"venue"
},
  "geometry": {"coordinates":[-74.390602,40.8633],"type":"Point"}
}