{
  "type": "Feature",
  "properties": {
    "addr:full":"1814 Kennedy Blvd Union City NJ 07087",
    "addr:housenumber":"1814",
    "addr:postcode":"07087",
    "addr:street":"Kennedy Blvd",
    "iso:country":"US",
    "sg:address":"1814 Kennedy Blvd",
    "sg:city":"Union City",
    "sg:classifiers":[
        {
            "category":"Professional",
            "subcategory":"Engineering",
            "type":"Services"
        }
    ],
    "sg:phone":"+1 201 392 8500",
    "sg:postcode":"07087",
    "sg:province":"NJ",
    "sg:tags":[
        "engineer"
    ],
    "wof:name":"Munoz Engineering",
    "wof:placetype":"venue"
},
  "geometry": {"coordinates":[-74.041695,40.767064],"type":"Point"}
}