{
  "type": "Feature",
  "properties": {
    "addr:full":"452 New Bridge Rd Bergenfield NJ 07621",
    "addr:housenumber":"452",
    "addr:postcode":"07621",
    "addr:street":"New Bridge Rd",
    "iso:country":"US",
    "sg:address":"452 New Bridge Rd",
    "sg:city":"Bergenfield",
    "sg:classifiers":[
        {
            "category":"Retail",
            "subcategory":"Veterinary Services",
            "type":"Services"
        }
    ],
    "sg:phone":"+1 201 384 4699",
    "sg:postcode":"07621",
    "sg:province":"NJ",
    "sg:tags":[
        "veterinarian"
    ],
    "wof:name":"Corrao James A Veterinarian",
    "wof:placetype":"venue"
},
  "geometry": {"coordinates":[-74.014503,40.9146],"type":"Point"}
}