{
  "type": "Feature",
  "properties": {
    "addr:full":"160 Franklin Ave Ste C Nutley NJ 07110",
    "addr:housenumber":"160",
    "addr:postcode":"07110",
    "addr:street":"Franklin Ave Ste C Nutley",
    "iso:country":"US",
    "sg:address":"160 Franklin Ave Ste C",
    "sg:city":"Nutley",
    "sg:classifiers":[
        {
            "category":"Deli",
            "type":"Food & Drink"
        },
        {
            "category":"Food & Beverages",
            "subcategory":"Bakery",
            "type":"Retail Goods"
        }
    ],
    "sg:phone":"+1 973 235 9866",
    "sg:postcode":"07110",
    "sg:province":"NJ",
    "sg:tags":[
        "sandwich"
    ],
    "wof:name":"Bagels N More",
    "wof:placetype":"venue"
},
  "geometry": {"coordinates":[-74.163524,40.813429],"type":"Point"}
}