{
  "type": "Feature",
  "properties": {
    "addr:full":"177 Industrial Ave Teterboro NJ 07608",
    "addr:housenumber":"177",
    "addr:postcode":"07608",
    "addr:street":"Industrial Ave",
    "iso:country":"US",
    "sg:address":"177 Industrial Ave",
    "sg:city":"Teterboro",
    "sg:classifiers":[
        {
            "category":"Autos & Motor Vehicles",
            "subcategory":"Automobile Sales",
            "type":"Retail Goods"
        }
    ],
    "sg:phone":"+1 201 288 0871",
    "sg:postcode":"07608",
    "sg:province":"NJ",
    "sg:tags":[
        "aircraft"
    ],
    "wof:name":"Atlantic Aviation",
    "wof:placetype":"venue"
},
  "geometry": {"coordinates":[-74.06746099999999,40.85282],"type":"Point"}
}