{
  "type": "Feature",
  "properties": {
    "addr:full":"451 Black Horse Ln New Brunswick NJ 08902",
    "addr:housenumber":"451",
    "addr:postcode":"08902",
    "addr:street":"Black Horse Ln",
    "iso:country":"US",
    "sg:address":"451 Black Horse Ln",
    "sg:city":"New Brunswick",
    "sg:classifiers":[
        {
            "category":"Retail",
            "subcategory":"Auto Repair",
            "type":"Services"
        }
    ],
    "sg:phone":"+1 732 422 1620",
    "sg:postcode":"08902",
    "sg:province":"NJ",
    "sg:tags":[
        "transmission"
    ],
    "wof:name":"Family Transmissions",
    "wof:placetype":"venue"
},
  "geometry": {"coordinates":[-74.515367,40.412567],"type":"Point"}
}