{
  "type": "Feature",
  "properties": {
    "addr:full":"159 Dennisville Rd Cape May Court House NJ 08210",
    "addr:housenumber":"159",
    "addr:postcode":"08210",
    "addr:street":"Dennisville Rd",
    "iso:country":"US",
    "sg:address":"159 Dennisville Rd",
    "sg:city":"Cape May Court House",
    "sg:classifiers":[
        {
            "category":"Professional",
            "type":"Services"
        }
    ],
    "sg:phone":"+1   ",
    "sg:postcode":"08210",
    "sg:province":"NJ",
    "wof:name":"Gary Gans",
    "wof:placetype":"venue"
},
  "geometry": {"coordinates":[-74.763491,39.176658],"type":"Point"}
}