{
  "type": "Feature",
  "properties": {
    "addr:full":"24 E Summit Ave Midland Park NJ 07432",
    "addr:housenumber":"24",
    "addr:postcode":"07432",
    "addr:street":"E Summit Ave",
    "iso:country":"US",
    "sg:address":"24 E Summit Ave",
    "sg:city":"Midland Park",
    "sg:classifiers":[
        {
            "category":"Building & Trades",
            "subcategory":"Construction",
            "type":"Services"
        }
    ],
    "sg:phone":"+1 201 444 2689",
    "sg:postcode":"07432",
    "sg:province":"NJ",
    "sg:tags":[
        "carpenter"
    ],
    "wof:name":"Braunius Brothers Inc",
    "wof:placetype":"venue"
},
  "geometry": {"coordinates":[-74.138679,40.998001],"type":"Point"}
}