{
  "type": "Feature",
  "properties": {
    "addr:full":"60 Front St Belvidere NJ 07823",
    "addr:housenumber":"60",
    "addr:postcode":"07823",
    "addr:street":"Front St",
    "iso:country":"US",
    "sg:address":"60 Front St",
    "sg:city":"Belvidere",
    "sg:classifiers":[
        {
            "category":"Wholesale",
            "subcategory":"Hardware",
            "type":"Manufacturing & Wholesale Goods"
        }
    ],
    "sg:phone":"+1 908 475 8394",
    "sg:postcode":"07823",
    "sg:province":"NJ",
    "sg:tags":[
        "water",
        "cooler",
        "equipment"
    ],
    "wof:name":"R J Distributing",
    "wof:placetype":"venue"
},
  "geometry": {"coordinates":[-75.08108300000001,40.828182],"type":"Point"}
}