{
  "type": "Feature",
  "properties": {
    "iso:country":"US",
    "sg:address":"306 Ave A",
    "sg:city":"Garwood",
    "sg:classifiers":[
        {
            "category":"Recreation",
            "type":"Entertainment"
        }
    ],
    "sg:phone":"+1 908 654 4558",
    "sg:postcode":"07002",
    "sg:province":"NJ",
    "sg:tags":[
        "astrologer"
    ],
    "wof:name":"Astrology Unlimited",
    "wof:placetype":"venue"
},
  "geometry": {"coordinates":[-74.13061999999999,40.659197],"type":"Point"}
}