{
  "type": "Feature",
  "properties": {
    "iso:country":"US",
    "sg:address":"8 Frederick Pl",
    "sg:city":"Cedar Knolls",
    "sg:classifiers":[
        {
            "category":"Manufacturing",
            "subcategory":"Apparel",
            "type":"Manufacturing & Wholesale Goods"
        }
    ],
    "sg:phone":"+1 973 401 9333",
    "sg:postcode":"07927",
    "sg:province":"NJ",
    "sg:tags":[
        "clothing",
        "outerwear",
        "mfg"
    ],
    "wof:name":"Branded Apparel Sales Group",
    "wof:placetype":"venue"
},
  "geometry": {"coordinates":[-74.456564,40.815585],"type":"Point"}
}