{
  "type": "Feature",
  "properties": {
    "addr:full":"20 W Church St Milltown NJ 08850",
    "addr:housenumber":"20",
    "addr:postcode":"08850",
    "addr:street":"W Church St",
    "iso:country":"US",
    "sg:address":"20 W Church St",
    "sg:city":"Milltown",
    "sg:classifiers":[
        {
            "category":"Education",
            "subcategory":"Library",
            "type":"Public Place"
        }
    ],
    "sg:phone":"+1   ",
    "sg:postcode":"08850",
    "sg:province":"NJ",
    "wof:name":"Milltown Public Library",
    "wof:placetype":"venue"
},
  "geometry": {"coordinates":[-74.440569,40.451456],"type":"Point"}
}