{
  "type": "Feature",
  "properties": {
    "iso:country":"US",
    "sg:address":"110 N Montgomery St",
    "sg:city":"Trenton",
    "sg:classifiers":[
        {
            "category":"Personal",
            "subcategory":"Beauty Salon",
            "type":"Services"
        }
    ],
    "sg:phone":"+1 609 392 1883",
    "sg:postcode":"08608",
    "sg:province":"NJ",
    "wof:name":"Tima Fashion African Hair",
    "wof:placetype":"venue"
},
  "geometry": {"coordinates":[-74.76232299999999,40.222285],"type":"Point"}
}