{
  "type": "Feature",
  "properties": {
    "iso:country":"US",
    "sg:address":"1066 Allenwood Dr",
    "sg:city":"Plainfield",
    "sg:classifiers":[
        {
            "category":"Professional",
            "subcategory":"Management & Consulting",
            "type":"Services"
        }
    ],
    "sg:phone":"+1 908 753 1184",
    "sg:postcode":"07060",
    "sg:province":"NJ",
    "wof:name":"C H Sanders Construction Co",
    "wof:placetype":"venue"
},
  "geometry": {"coordinates":[-74.41252,40.602677],"type":"Point"}
}