{
  "type": "Feature",
  "properties": {
    "addr:full":"383 US Highway 46 Rockaway NJ 07866",
    "addr:housenumber":"383",
    "addr:postcode":"07866",
    "addr:street":"Us Highway 46",
    "iso:country":"US",
    "sg:address":"383 US Highway 46",
    "sg:city":"Rockaway",
    "sg:classifiers":[
        {
            "category":"Autos & Motor Vehicles",
            "subcategory":"Automobile Sales",
            "type":"Retail Goods"
        },
        {
            "category":"Retail",
            "subcategory":"Auto Rental",
            "type":"Services"
        },
        {
            "category":"Retail",
            "subcategory":"Auto Repair",
            "type":"Services"
        }
    ],
    "sg:phone":"+1 973 366 9205",
    "sg:postcode":"07866",
    "sg:province":"NJ",
    "sg:tags":[
        "car"
    ],
    "wof:name":"Bisson Motor Sales",
    "wof:placetype":"venue"
},
  "geometry": {"coordinates":[-74.522003,40.890301],"type":"Point"}
}