{
  "type": "Feature",
  "properties": {
    "iso:country":"US",
    "sg:address":"457 Harmon Meadow Blvd",
    "sg:city":"Secaucus",
    "sg:classifiers":[
        {
            "category":"Bars & Pubs",
            "subcategory":"Sports Bar",
            "type":"Food & Drink"
        },
        {
            "category":"Restaurant",
            "type":"Food & Drink"
        }
    ],
    "sg:phone":"+1 201 223 1234",
    "sg:postcode":"07094",
    "sg:province":"NJ",
    "sg:tags":[
        "traditional",
        "american"
    ],
    "sg:website":"www.bazookassportsbar.com/",
    "wof:name":"Bazooka's Restaurant",
    "wof:placetype":"venue"
},
  "geometry": {"coordinates":[-74.045151,40.789017],"type":"Point"}
}