{
  "type": "Feature",
  "properties": {
    "addr:full":"2 Firethorn Rd Old Bridge NJ 08857",
    "addr:housenumber":"2",
    "addr:postcode":"08857",
    "addr:street":"Firethorn Rd",
    "iso:country":"US",
    "sg:address":"2 Firethorn Rd",
    "sg:city":"Old Bridge",
    "sg:classifiers":[
        {
            "category":"Building & Trades",
            "subcategory":"Landscaping Services",
            "type":"Services"
        }
    ],
    "sg:phone":"+1 732 679 9300",
    "sg:postcode":"08857",
    "sg:province":"NJ",
    "sg:tags":[
        "landscape",
        "contractor"
    ],
    "wof:name":"Blue Grass Cutting LLC Lawn",
    "wof:placetype":"venue"
},
  "geometry": {"coordinates":[-74.300825,40.386815],"type":"Point"}
}