{
  "type": "Feature",
  "properties": {
    "iso:country":"US",
    "sg:address":"50 Northfield Ave Fl 2",
    "sg:city":"West Orange",
    "sg:classifiers":[
        {
            "category":"Professional",
            "subcategory":"Lawyer & Legal Services",
            "type":"Services"
        }
    ],
    "sg:phone":"+1 973 325 7444",
    "sg:postcode":"07052",
    "sg:province":"NJ",
    "wof:name":"Tartini Michael ESQ",
    "wof:placetype":"venue"
},
  "geometry": {"coordinates":[-74.24218999999999,40.775955],"type":"Point"}
}