{
  "type": "Feature",
  "properties": {
    "iso:country":"US",
    "sg:address":"634 Arena Dr",
    "sg:city":"Trenton",
    "sg:classifiers":[
        {
            "category":"Professional",
            "type":"Services"
        }
    ],
    "sg:phone":"+1 609 888 0582",
    "sg:postcode":"08610",
    "sg:province":"NJ",
    "sg:tags":[
        "establishment"
    ],
    "wof:name":"A Ginis & Assoc",
    "wof:placetype":"venue"
},
  "geometry": {"coordinates":[-74.714849,40.20715],"type":"Point"}
}