{
  "type": "Feature",
  "properties": {
    "addr:full":"223 High St Mount Holly NJ 08060",
    "addr:housenumber":"223",
    "addr:postcode":"08060",
    "addr:street":"High St",
    "iso:country":"US",
    "sg:address":"223 High St",
    "sg:city":"Mount Holly",
    "sg:classifiers":[
        {
            "category":"Professional",
            "subcategory":"Lawyer & Legal Services",
            "type":"Services"
        }
    ],
    "sg:phone":"+1 609 267 7711",
    "sg:postcode":"08060",
    "sg:province":"NJ",
    "wof:name":"Pilles John F Jr",
    "wof:placetype":"venue"
},
  "geometry": {"coordinates":[-74.789497,39.997398],"type":"Point"}
}