{
  "type": "Feature",
  "properties": {
    "addr:full":"95 Leesville Ave Avenel NJ 07001",
    "addr:housenumber":"95",
    "addr:postcode":"07001",
    "addr:street":"Leesville Ave",
    "iso:country":"US",
    "sg:address":"95 Leesville Ave",
    "sg:city":"Avenel",
    "sg:classifiers":[
        {
            "category":"Retail",
            "subcategory":"Auto Repair",
            "type":"Services"
        }
    ],
    "sg:phone":"+1 732 382 2170",
    "sg:postcode":"07001",
    "sg:province":"NJ",
    "sg:tags":[
        "body",
        "automobile",
        "painting"
    ],
    "wof:name":"E & F Auto Body",
    "wof:placetype":"venue"
},
  "geometry": {"coordinates":[-74.28177599999999,40.587759],"type":"Point"}
}