{
  "type": "Feature",
  "properties": {
    "addr:full":"158 Blue Heron Ct Holmdel NJ 07733",
    "addr:housenumber":"158",
    "addr:postcode":"07733",
    "addr:street":"Blue Heron Ct",
    "iso:country":"US",
    "sg:address":"158 Blue Heron Ct",
    "sg:city":"Holmdel",
    "sg:classifiers":[
        {
            "category":"Professional",
            "type":"Services"
        }
    ],
    "sg:phone":"+1   ",
    "sg:postcode":"07733",
    "sg:province":"NJ",
    "wof:name":"Matthew A Segall & Co Inc",
    "wof:placetype":"venue"
},
  "geometry": {"coordinates":[-74.14684,40.39753],"type":"Point"}
}