{
  "type": "Feature",
  "properties": {
    "iso:country":"US",
    "sg:address":"18 Vanderveer Dr",
    "sg:city":"Basking Ridge",
    "sg:classifiers":[
        {
            "category":"Professional",
            "subcategory":"Business Services",
            "type":"Services"
        }
    ],
    "sg:phone":"+1   ",
    "sg:postcode":"07920",
    "sg:province":"NJ",
    "wof:name":"Showmont Enterprises Liabi",
    "wof:placetype":"venue"
},
  "geometry": {"coordinates":[-74.628258,40.666379],"type":"Point"}
}