{
  "type": "Feature",
  "properties": {
    "addr:full":"622 Eagle Rock Ave West Orange NJ 07052",
    "addr:housenumber":"622",
    "addr:postcode":"07052",
    "addr:street":"Eagle Rock Ave",
    "iso:country":"US",
    "sg:address":"622 Eagle Rock Ave",
    "sg:city":"West Orange",
    "sg:classifiers":[
        {
            "category":"Health Services",
            "subcategory":"Doctor",
            "type":"Services"
        }
    ],
    "sg:phone":"+1 973 731 0123",
    "sg:postcode":"07052",
    "sg:province":"NJ",
    "wof:name":"Maniar M MD",
    "wof:placetype":"venue"
},
  "geometry": {"coordinates":[-74.257599,40.8097],"type":"Point"}
}