{
  "type": "Feature",
  "properties": {
    "addr:full":"2714 Kennedy Blvd Union City NJ 07087",
    "addr:housenumber":"2714",
    "addr:postcode":"07087",
    "addr:street":"Kennedy Blvd",
    "iso:country":"US",
    "sg:address":"2714 Kennedy Blvd",
    "sg:city":"Union City",
    "sg:classifiers":[
        {
            "category":"Manufacturing",
            "subcategory":"Apparel",
            "type":"Manufacturing & Wholesale Goods"
        }
    ],
    "sg:phone":"+1 201 866 4040",
    "sg:postcode":"07087",
    "sg:province":"NJ",
    "wof:name":"Rami Embroidery Corp",
    "wof:placetype":"venue"
},
  "geometry": {"coordinates":[-74.035904,40.771999],"type":"Point"}
}