{
  "type": "Feature",
  "properties": {
    "iso:country":"US",
    "sg:address":"7570 S Crescent Blvd",
    "sg:city":"Pennsauken",
    "sg:classifiers":[
        {
            "category":"Health Services",
            "subcategory":"Dentist",
            "type":"Services"
        }
    ],
    "sg:phone":"+1 856 942 0300",
    "sg:postcode":"08109",
    "sg:province":"NJ",
    "sg:website":"www.acdent.com",
    "wof:name":"Ac Dental",
    "wof:placetype":"venue"
},
  "geometry": {"coordinates":[-75.08295099999999,39.930693],"type":"Point"}
}