{
  "type": "Feature",
  "properties": {
    "iso:country":"US",
    "sg:address":"205 May St",
    "sg:city":"Edison",
    "sg:classifiers":[
        {
            "category":"Health Services",
            "subcategory":"Doctor",
            "type":"Services"
        }
    ],
    "sg:phone":"+1 908 757 1520",
    "sg:postcode":"08837",
    "sg:province":"NJ",
    "sg:tags":[
        "medicine",
        "sport",
        "orthopedist"
    ],
    "wof:name":"Zimmerman Joshua MD",
    "wof:placetype":"venue"
},
  "geometry": {"coordinates":[-74.324799,40.528186],"type":"Point"}
}