{
  "type": "Feature",
  "properties": {
    "addr:full":"28 Old Milford Ln West Milford NJ 07480",
    "addr:housenumber":"28",
    "addr:postcode":"07480",
    "addr:street":"Old Milford Ln",
    "iso:country":"US",
    "sg:address":"28 Old Milford Ln",
    "sg:city":"West Milford",
    "sg:classifiers":[
        {
            "category":"Building & Trades",
            "subcategory":"Cleaning & Sanitation",
            "type":"Services"
        }
    ],
    "sg:phone":"+1 973 728 7991",
    "sg:postcode":"07480",
    "sg:province":"NJ",
    "sg:tags":[
        "janitor"
    ],
    "wof:name":"Compulsive Cleaning Svc",
    "wof:placetype":"venue"
},
  "geometry": {"coordinates":[-74.40800900000001,41.103325],"type":"Point"}
}