{
  "type": "Feature",
  "properties": {
    "iso:country":"US",
    "sg:address":"200 5th Ave",
    "sg:city":"Belmar",
    "sg:classifiers":[
        {
            "category":"Shopping",
            "subcategory":"Bicycles & Sporting Goods",
            "type":"Retail Goods"
        }
    ],
    "sg:phone":"+1 732 280 1166",
    "sg:postcode":"07719",
    "sg:province":"NJ",
    "sg:tags":[
        "equipment",
        "exercise"
    ],
    "wof:name":"Leisure Fitness",
    "wof:placetype":"venue"
},
  "geometry": {"coordinates":[-74.01541899999999,40.182598],"type":"Point"}
}