{
  "type": "Feature",
  "properties": {
    "addr:full":"317 1st St Dunellen NJ 08812",
    "addr:housenumber":"317",
    "addr:postcode":"08812",
    "addr:street":"1St St",
    "iso:country":"US",
    "sg:address":"317 1st St",
    "sg:city":"Dunellen",
    "sg:classifiers":[
        {
            "category":"Building & Trades",
            "subcategory":"Construction",
            "type":"Services"
        }
    ],
    "sg:phone":"+1   ",
    "sg:postcode":"08812",
    "sg:province":"NJ",
    "sg:tags":[
        "house",
        "construct",
        "contractor"
    ],
    "wof:name":"Dhi Contracting",
    "wof:placetype":"venue"
},
  "geometry": {"coordinates":[-74.467521,40.592913],"type":"Point"}
}