{
  "type": "Feature",
  "properties": {
    "iso:country":"US",
    "sg:address":"905 State Rte 33",
    "sg:city":"Freehold",
    "sg:classifiers":[
        {
            "category":"Autos & Motor Vehicles",
            "subcategory":"Fuel & Gas Station",
            "type":"Retail Goods"
        }
    ],
    "sg:phone":"+1   ",
    "sg:postcode":"07728",
    "sg:province":"NJ",
    "sg:tags":[
        "station",
        "gasoline"
    ],
    "wof:name":"Five Points Petroleum LLC",
    "wof:placetype":"venue"
},
  "geometry": {"coordinates":[-74.21068200000001,40.231419],"type":"Point"}
}