{
  "type": "Feature",
  "properties": {
    "addr:full":"111 Commerce Rd Carlstadt NJ 07072",
    "addr:housenumber":"111",
    "addr:postcode":"07072",
    "addr:street":"Commerce Rd",
    "iso:country":"US",
    "sg:address":"111 Commerce Rd",
    "sg:city":"Carlstadt",
    "sg:classifiers":[
        {
            "category":"Shopping",
            "subcategory":"Stationery & Office Supplies",
            "type":"Retail Goods"
        }
    ],
    "sg:phone":"+1 201 507 0300",
    "sg:postcode":"07072",
    "sg:province":"NJ",
    "sg:tags":[
        "equipment"
    ],
    "wof:name":"Advantage Team Sales Llc",
    "wof:placetype":"venue"
},
  "geometry": {"coordinates":[-74.059158,40.830519],"type":"Point"}
}