{
  "type": "Feature",
  "properties": {
    "iso:country":"US",
    "sg:address":"317 Asbury Ave",
    "sg:city":"National Park",
    "sg:classifiers":[
        {
            "category":"Personal",
            "type":"Services"
        }
    ],
    "sg:phone":"+1 856 693 0291",
    "sg:postcode":"08063",
    "sg:province":"NJ",
    "sg:tags":[
        "towing"
    ],
    "sg:website":"www.billquidonetowing.com",
    "wof:name":"Bill Quidone Towing",
    "wof:placetype":"venue"
},
  "geometry": {"coordinates":[-75.18362,39.869036],"type":"Point"}
}