{
  "type": "Feature",
  "properties": {
    "iso:country":"US",
    "sg:address":"156 French St",
    "sg:city":"New Brunswick",
    "sg:classifiers":[
        {
            "category":"Banks & Credit Unions",
            "subcategory":"Bank",
            "type":"Services"
        }
    ],
    "sg:phone":"+1 732 249 0599",
    "sg:postcode":"08901",
    "sg:province":"NJ",
    "sg:tags":[
        "cashing",
        "money",
        "check",
        "issuance",
        "transfer",
        "mai",
        "order"
    ],
    "wof:name":"Latin Brothers Check Cashing",
    "wof:placetype":"venue"
},
  "geometry": {"coordinates":[-74.453226,40.492269],"type":"Point"}
}