{
  "type": "Feature",
  "properties": {
    "iso:country":"US",
    "sg:address":"254 Applegarth Rd",
    "sg:city":"Monroe Township",
    "sg:classifiers":[
        {
            "category":"Recreation",
            "type":"Entertainment"
        }
    ],
    "sg:phone":"+1 609 655 3311",
    "sg:postcode":"08831",
    "sg:province":"NJ",
    "sg:tags":[
        "range",
        "golf",
        "driving"
    ],
    "wof:name":"Applegarth Golf Center Inc",
    "wof:placetype":"venue"
},
  "geometry": {"coordinates":[-74.473196,40.302549],"type":"Point"}
}