{
  "type": "Feature",
  "properties": {
    "iso:country":"US",
    "sg:address":"24 Spruce Run",
    "sg:city":"Ramsey",
    "sg:classifiers":[
        {
            "category":"Professional",
            "subcategory":"Computer Services",
            "type":"Services"
        }
    ],
    "sg:phone":"+1   ",
    "sg:postcode":"07446",
    "sg:province":"NJ",
    "sg:tags":[
        "prepackaged",
        "software"
    ],
    "wof:name":"DC Software Consulting Inc",
    "wof:placetype":"venue"
},
  "geometry": {"coordinates":[-74.13909200000001,41.055646],"type":"Point"}
}