{
  "type": "Feature",
  "properties": {
    "addr:full":"627 River St Paterson NJ 07524",
    "addr:housenumber":"627",
    "addr:postcode":"07524",
    "addr:street":"River St",
    "iso:country":"US",
    "sg:address":"627 River St",
    "sg:city":"Paterson",
    "sg:classifiers":[
        {
            "category":"Shopping",
            "type":"Retail Goods"
        }
    ],
    "sg:phone":"+1   ",
    "sg:postcode":"07524",
    "sg:province":"NJ",
    "sg:tags":[
        "merchandise"
    ],
    "wof:name":"Riverside Bargains",
    "wof:placetype":"venue"
},
  "geometry": {"coordinates":[-74.155253,40.934658],"type":"Point"}
}