{
  "type": "Feature",
  "properties": {
    "addr:full":"210 Clinton Ave Newark NJ 07108",
    "addr:housenumber":"210",
    "addr:postcode":"07108",
    "addr:street":"Clinton Ave",
    "iso:country":"US",
    "sg:address":"210 Clinton Ave",
    "sg:city":"Newark",
    "sg:classifiers":[
        {
            "category":"Organizations",
            "subcategory":"Religious Organization",
            "type":"Services"
        }
    ],
    "sg:phone":"+1   ",
    "sg:postcode":"07108",
    "sg:province":"NJ",
    "sg:tags":[
        "child",
        "day",
        "care"
    ],
    "wof:name":"Greater Mt Mrriah Bptst Church",
    "wof:placetype":"venue"
},
  "geometry": {"coordinates":[-74.186598,40.723419],"type":"Point"}
}