{
  "type": "Feature",
  "properties": {
    "iso:country":"US",
    "sg:address":"1 Corporate Way",
    "sg:city":"Mine Hill",
    "sg:classifiers":[
        {
            "category":"Professional",
            "subcategory":"Lawyer & Legal Services",
            "type":"Services"
        }
    ],
    "sg:phone":"+1 973 344 0555",
    "sg:postcode":"07803",
    "sg:province":"NJ",
    "sg:tags":[
        "attorney"
    ],
    "wof:name":"Jeffrey E Michelson",
    "wof:placetype":"venue"
},
  "geometry": {"coordinates":[-74.593924,40.879622],"type":"Point"}
}