{
  "type": "Feature",
  "properties": {
    "iso:country":"US",
    "sg:address":"8 Knickerbocker Ave",
    "sg:city":"Paterson",
    "sg:classifiers":[
        {
            "category":"Wholesale",
            "subcategory":"Computers",
            "type":"Manufacturing & Wholesale Goods"
        }
    ],
    "sg:phone":"+1 973 953 9887",
    "sg:postcode":"07503",
    "sg:province":"NJ",
    "wof:name":"Premo Computer Professionals",
    "wof:placetype":"venue"
},
  "geometry": {"coordinates":[-74.157961,40.889675],"type":"Point"}
}