{
  "type": "Feature",
  "properties": {
    "addr:full":"309 Chestnut St Hammonton NJ 08037",
    "addr:housenumber":"309",
    "addr:postcode":"08037",
    "addr:street":"Chestnut St",
    "iso:country":"US",
    "sg:address":"309 Chestnut St",
    "sg:city":"Hammonton",
    "sg:classifiers":[
        {
            "category":"Building & Trades",
            "subcategory":"Plumbing",
            "type":"Services"
        }
    ],
    "sg:phone":"+1 609 561 3800",
    "sg:postcode":"08037",
    "sg:province":"NJ",
    "sg:tags":[
        "tank",
        "installation"
    ],
    "sg:website":"www.ruberton.com",
    "wof:name":"M L Ruberton Construction Co",
    "wof:placetype":"venue"
},
  "geometry": {"coordinates":[-74.790615,39.634003],"type":"Point"}
}