{
  "type": "Feature",
  "properties": {
    "iso:country":"US",
    "sg:address":"1570 Grandview Ave",
    "sg:city":"Paulsboro",
    "sg:classifiers":[
        {
            "category":"Wholesale",
            "subcategory":"Groceries",
            "type":"Manufacturing & Wholesale Goods"
        }
    ],
    "sg:phone":"+1 856 845 5585",
    "sg:postcode":"08066",
    "sg:province":"NJ",
    "sg:tags":[
        "food",
        "product"
    ],
    "sg:website":"www.utzsnacks.com",
    "wof:name":"UTZ Quality Foods Inc",
    "wof:placetype":"venue"
},
  "geometry": {"coordinates":[-75.203514,39.83271],"type":"Point"}
}