{
  "type": "Feature",
  "properties": {
    "iso:country":"US",
    "sg:address":"263 Kearny Ave",
    "sg:city":"Kearny",
    "sg:classifiers":[
        {
            "category":"Restaurant",
            "type":"Food & Drink"
        }
    ],
    "sg:phone":"+1 201 997 4211",
    "sg:postcode":"07032",
    "sg:province":"NJ",
    "wof:name":"Mango's Cuban Cafe",
    "wof:placetype":"venue"
},
  "geometry": {"coordinates":[-74.143997,40.763199],"type":"Point"}
}