{
  "type": "Feature",
  "properties": {
    "addr:full":"60 W Church St Bergenfield NJ 07621",
    "addr:housenumber":"60",
    "addr:postcode":"07621",
    "addr:street":"W Church St",
    "iso:country":"US",
    "sg:address":"60 W Church St",
    "sg:city":"Bergenfield",
    "sg:classifiers":[
        {
            "category":"Retail",
            "subcategory":"Repair Shop",
            "type":"Services"
        }
    ],
    "sg:phone":"+1 201 244 9611",
    "sg:postcode":"07621",
    "sg:province":"NJ",
    "sg:tags":[
        "lock",
        "locksmith"
    ],
    "wof:name":"24 Hour Emergency Locksmith",
    "wof:placetype":"venue"
},
  "geometry": {"coordinates":[-73.99899499999999,40.929255],"type":"Point"}
}