{
  "type": "Feature",
  "properties": {
    "iso:country":"US",
    "sg:address":"535 Ave A",
    "sg:city":"Bayonne",
    "sg:classifiers":[
        {
            "category":"Social Services",
            "type":"Services"
        }
    ],
    "sg:phone":"+1 201 339 2430",
    "sg:postcode":"07002",
    "sg:province":"NJ",
    "sg:tags":[
        "organization",
        "welfare"
    ],
    "wof:name":"Backbay Gardens Assoc",
    "wof:placetype":"venue"
},
  "geometry": {"coordinates":[-74.124785,40.666882],"type":"Point"}
}