{
  "type": "Feature",
  "properties": {
    "iso:country":"US",
    "sg:address":"340 Calhoun St",
    "sg:city":"Trenton",
    "sg:classifiers":[
        {
            "category":"Social Services",
            "type":"Services"
        }
    ],
    "sg:phone":"+1 609 396 0944",
    "sg:postcode":"08618",
    "sg:province":"NJ",
    "sg:tags":[
        "organization",
        "welfare"
    ],
    "wof:name":"Trenton Head Start Inc",
    "wof:placetype":"venue"
},
  "geometry": {"coordinates":[-74.77172299999999,40.225738],"type":"Point"}
}