{
  "type": "Feature",
  "properties": {
    "addr:full":"87 Park St Montclair NJ 07042",
    "addr:housenumber":"87",
    "addr:postcode":"07042",
    "addr:street":"Park St",
    "iso:country":"US",
    "sg:address":"87 Park St",
    "sg:city":"Montclair",
    "sg:classifiers":[
        {
            "category":"Real Estate",
            "subcategory":"Real Estate Services",
            "type":"Services"
        }
    ],
    "sg:phone":"+1 973 509 1100",
    "sg:postcode":"07042",
    "sg:province":"NJ",
    "sg:tags":[
        "company",
        "title"
    ],
    "sg:website":"www.tristatetitle.com",
    "wof:name":"Tri-State Title Agency Inc",
    "wof:placetype":"venue"
},
  "geometry": {"coordinates":[-74.214748,40.819435],"type":"Point"}
}