{
  "type": "Feature",
  "properties": {
    "iso:country":"US",
    "sg:address":"9 Canterbury Way",
    "sg:city":"Morristown",
    "sg:classifiers":[
        {
            "category":"Shopping",
            "subcategory":"Gifts & Souvenirs",
            "type":"Retail Goods"
        }
    ],
    "sg:phone":"+1   ",
    "sg:postcode":"07960",
    "sg:province":"NJ",
    "wof:name":"Yi Xing Teapots",
    "wof:placetype":"venue"
},
  "geometry": {"coordinates":[-74.504459,40.806797],"type":"Point"}
}