{
  "type": "Feature",
  "properties": {
    "iso:country":"US",
    "sg:address":"148 Ferry St",
    "sg:city":"Newark",
    "sg:classifiers":[
        {
            "category":"Banks & Credit Unions",
            "subcategory":"Bank",
            "type":"Services"
        }
    ],
    "sg:phone":"+1 973 589 0643",
    "sg:postcode":"07105",
    "sg:province":"NJ",
    "wof:name":"Investors Savings Bank",
    "wof:placetype":"venue"
},
  "geometry": {"coordinates":[-74.158719,40.729517],"type":"Point"}
}