{
  "type": "Feature",
  "properties": {
    "addr:full":"38 Baltusrol St Trenton NJ 08690",
    "addr:housenumber":"38",
    "addr:postcode":"08690",
    "addr:street":"Baltusrol St",
    "iso:country":"US",
    "sg:address":"38 Baltusrol St",
    "sg:city":"Trenton",
    "sg:classifiers":[
        {
            "category":"Building & Trades",
            "subcategory":"Construction",
            "type":"Services"
        }
    ],
    "sg:phone":"+1 609 587 3920",
    "sg:postcode":"08690",
    "sg:province":"NJ",
    "sg:tags":[
        "house"
    ],
    "wof:name":"Falcone Builders",
    "wof:placetype":"venue"
},
  "geometry": {"coordinates":[-74.642146,40.227341],"type":"Point"}
}