{
  "type": "Feature",
  "properties": {
    "iso:country":"US",
    "sg:address":"19 Orange Pl",
    "sg:city":"West Orange",
    "sg:classifiers":[
        {
            "category":"Social Services",
            "type":"Services"
        }
    ],
    "sg:phone":"+1 973 325 2990",
    "sg:postcode":"07052",
    "sg:province":"NJ",
    "sg:tags":[
        "organization",
        "welfare"
    ],
    "sg:website":"www.projectlive.org",
    "wof:name":"Project Live Inc",
    "wof:placetype":"venue"
},
  "geometry": {"coordinates":[-74.231616,40.792721],"type":"Point"}
}