{
  "type": "Feature",
  "properties": {
    "iso:country":"US",
    "sg:address":"164 Klinesville Rd",
    "sg:city":"Flemington",
    "sg:classifiers":[
        {
            "category":"Autos & Motor Vehicles",
            "subcategory":"Automobile Sales",
            "type":"Retail Goods"
        }
    ],
    "sg:phone":"+1   ",
    "sg:postcode":"08822",
    "sg:province":"NJ",
    "sg:tags":[
        "used"
    ],
    "wof:name":"Trans Ocean Auto Inc",
    "wof:placetype":"venue"
},
  "geometry": {"coordinates":[-74.89490499999999,40.548592],"type":"Point"}
}