{
  "type": "Feature",
  "properties": {
    "iso:country":"US",
    "sg:address":"571 Central Ave Ste 120",
    "sg:city":"New Providence",
    "sg:classifiers":[
        {
            "category":"Professional",
            "subcategory":"Lawyer & Legal Services",
            "type":"Services"
        }
    ],
    "sg:phone":"+1 908 898 0100",
    "sg:postcode":"07974",
    "sg:province":"NJ",
    "wof:name":"McManus John & Associates",
    "wof:placetype":"venue"
},
  "geometry": {"coordinates":[-74.404554,40.698147],"type":"Point"}
}