{
  "type": "Feature",
  "properties": {
    "addr:full":"4758 Oak Ter Merchantville NJ 08109",
    "addr:housenumber":"4758",
    "addr:postcode":"08109",
    "addr:street":"Oak Ter",
    "iso:country":"US",
    "sg:address":"4758 Oak Ter",
    "sg:city":"Merchantville",
    "sg:classifiers":[
        {
            "category":"Wholesale",
            "subcategory":"Jewelry",
            "type":"Manufacturing & Wholesale Goods"
        }
    ],
    "sg:phone":"+1 856 486 7790",
    "sg:postcode":"08109",
    "sg:province":"NJ",
    "sg:tags":[
        "stone"
    ],
    "wof:name":"Clarkes USA",
    "wof:placetype":"venue"
},
  "geometry": {"coordinates":[-75.05775199999999,39.94367],"type":"Point"}
}