{
  "type": "Feature",
  "properties": {
    "addr:full":"1950 N Black Horse Pike Williamstown NJ 08094",
    "addr:housenumber":"1950",
    "addr:postcode":"08094",
    "addr:street":"N Black Horse Pike",
    "iso:country":"US",
    "sg:address":"1950 N Black Horse Pike",
    "sg:city":"Williamstown",
    "sg:classifiers":[
        {
            "category":"Shopping",
            "type":"Retail Goods"
        }
    ],
    "sg:phone":"+1   ",
    "sg:postcode":"08094",
    "sg:province":"NJ",
    "sg:tags":[
        "tropical",
        "fish"
    ],
    "wof:name":"J B Tropical Fish",
    "wof:placetype":"venue"
},
  "geometry": {"coordinates":[-75.017606,39.714277],"type":"Point"}
}