{
  "type": "Feature",
  "properties": {
    "iso:country":"US",
    "sg:address":"1050 Jeanette Ave",
    "sg:city":"Union",
    "sg:classifiers":[
        {
            "category":"Social Services",
            "type":"Services"
        }
    ],
    "sg:phone":"+1   ",
    "sg:postcode":"07083",
    "sg:province":"NJ",
    "sg:tags":[
        "child",
        "day",
        "care"
    ],
    "wof:name":"Union Club",
    "wof:placetype":"venue"
},
  "geometry": {"coordinates":[-74.278644,40.700068],"type":"Point"}
}