{
  "type": "Feature",
  "properties": {
    "iso:country":"US",
    "sg:address":"651 Anderson Ave",
    "sg:city":"Cliffside Park",
    "sg:classifiers":[
        {
            "category":"Retail",
            "subcategory":"Repair Shop",
            "type":"Services"
        }
    ],
    "sg:phone":"+1 201 334 3821",
    "sg:postcode":"07010",
    "sg:province":"NJ",
    "sg:tags":[
        "lock",
        "locksmith"
    ],
    "wof:name":"24 7 Emergency Locksmith",
    "wof:placetype":"venue"
},
  "geometry": {"coordinates":[-73.987207,40.826734],"type":"Point"}
}