{
  "type": "Feature",
  "properties": {
    "iso:country":"US",
    "sg:address":"1460 US Highway 9 N",
    "sg:city":"Woodbridge",
    "sg:classifiers":[
        {
            "category":"Banks & Credit Unions",
            "subcategory":"Financial Services",
            "type":"Services"
        }
    ],
    "sg:phone":"+1 732 218 5383",
    "sg:postcode":"07095",
    "sg:province":"NJ",
    "sg:tags":[
        "broker",
        "mortgage"
    ],
    "wof:name":"Cenmark Mortgage Company",
    "wof:placetype":"venue"
},
  "geometry": {"coordinates":[-74.295772,40.560645],"type":"Point"}
}