{
  "type": "Feature",
  "properties": {
    "iso:country":"US",
    "sg:address":"17 Witherspoon St",
    "sg:city":"Princeton",
    "sg:classifiers":[
        {
            "category":"Shopping",
            "subcategory":"Clothing, Apparel, & Fashions",
            "type":"Retail Goods"
        }
    ],
    "sg:phone":"+1   ",
    "sg:postcode":"08542",
    "sg:province":"NJ",
    "sg:tags":[
        "family"
    ],
    "wof:name":"Jay McLaughlin",
    "wof:placetype":"venue"
},
  "geometry": {"coordinates":[-74.660004,40.350342],"type":"Point"}
}