{
  "type": "Feature",
  "properties": {
    "iso:country":"US",
    "sg:address":"2352 Rt 70 W",
    "sg:city":"Cherry Hill",
    "sg:classifiers":[
        {
            "category":"Retail",
            "subcategory":"Car Wash",
            "type":"Services"
        },
        {
            "category":"Retail",
            "subcategory":"Auto Repair",
            "type":"Services"
        }
    ],
    "sg:phone":"+1 856 665 1172",
    "sg:postcode":"08002",
    "sg:province":"NJ",
    "sg:tags":[
        "oil",
        "detailing",
        "change"
    ],
    "wof:name":"Magic Touch Car Wash",
    "wof:placetype":"venue"
},
  "geometry": {"coordinates":[-75.044073,39.924076],"type":"Point"}
}