{
  "type": "Feature",
  "properties": {
    "addr:full":"710 W Laurel Rd Stratford NJ 08084",
    "addr:housenumber":"710",
    "addr:postcode":"08084",
    "addr:street":"W Laurel Rd",
    "iso:country":"US",
    "sg:address":"710 W Laurel Rd",
    "sg:city":"Stratford",
    "sg:classifiers":[
        {
            "category":"Social Services",
            "type":"Services"
        }
    ],
    "sg:phone":"+1 856 435 8505",
    "sg:postcode":"08084",
    "sg:province":"NJ",
    "wof:name":"Y W C A Counseling Center",
    "wof:placetype":"venue"
},
  "geometry": {"coordinates":[-75.01508,39.818834],"type":"Point"}
}