{
  "type": "Feature",
  "properties": {
    "iso:country":"US",
    "sg:address":"10 Hawkin Rd",
    "sg:city":"Medford",
    "sg:classifiers":[
        {
            "category":"Education",
            "subcategory":"Vocational School",
            "type":"Public Place"
        }
    ],
    "sg:phone":"+1   ",
    "sg:postcode":"08055",
    "sg:province":"NJ",
    "sg:tags":[
        "executive"
    ],
    "wof:name":"Medford Campus",
    "wof:placetype":"venue"
},
  "geometry": {"coordinates":[-74.80314199999999,39.896418],"type":"Point"}
}