{
  "type": "Feature",
  "properties": {
    "iso:country":"US",
    "sg:address":"473 Adamston Rd",
    "sg:city":"Brick",
    "sg:classifiers":[
        {
            "category":"Organizations",
            "subcategory":"Religious Organization",
            "type":"Services"
        }
    ],
    "sg:phone":"+1 732 920 1665",
    "sg:postcode":"08723",
    "sg:province":"NJ",
    "sg:tags":[
        "church"
    ],
    "wof:name":"Kingdom Hall-Jehovah's Witness",
    "wof:placetype":"venue"
},
  "geometry": {"coordinates":[-74.09740600000001,40.042735],"type":"Point"}
}