{
  "type": "Feature",
  "properties": {
    "iso:country":"US",
    "sg:address":"115 River Rd",
    "sg:city":"Edgewater",
    "sg:classifiers":[
        {
            "category":"Shopping",
            "subcategory":"Clothing, Apparel, & Fashions",
            "type":"Retail Goods"
        }
    ],
    "sg:phone":"+1 201 840 9020",
    "sg:postcode":"07020",
    "sg:province":"NJ",
    "sg:tags":[
        "handbag"
    ],
    "wof:name":"European Importers Intl",
    "wof:placetype":"venue"
},
  "geometry": {"coordinates":[-73.991339,40.806422],"type":"Point"}
}