{
  "type": "Feature",
  "properties": {
    "iso:country":"US",
    "sg:address":"410 2nd Ave",
    "sg:city":"Piscataway",
    "sg:classifiers":[
        {
            "category":"Building & Trades",
            "subcategory":"Construction",
            "type":"Services"
        }
    ],
    "sg:phone":"+1 732 563 9185",
    "sg:postcode":"08854",
    "sg:province":"NJ",
    "sg:tags":[
        "house"
    ],
    "wof:name":"Sensational Homes Inc",
    "wof:placetype":"venue"
},
  "geometry": {"coordinates":[-74.493403,40.553468],"type":"Point"}
}