{
  "type": "Feature",
  "properties": {
    "addr:full":"3 Barkley Ct East Brunswick NJ 08816",
    "addr:housenumber":"3",
    "addr:postcode":"08816",
    "addr:street":"Barkley Ct",
    "iso:country":"US",
    "sg:address":"3 Barkley Ct",
    "sg:city":"East Brunswick",
    "sg:classifiers":[
        {
            "category":"Professional",
            "subcategory":"Computer Services",
            "type":"Services"
        }
    ],
    "sg:phone":"+1   ",
    "sg:postcode":"08816",
    "sg:province":"NJ",
    "sg:tags":[
        "wide",
        "network",
        "area",
        "integration",
        "develops",
        "local",
        "man"
    ],
    "wof:name":"Ficomp Systems Inc",
    "wof:placetype":"venue"
},
  "geometry": {"coordinates":[-74.42771999999999,40.423799],"type":"Point"}
}