{
  "type": "Feature",
  "properties": {
    "addr:full":"19 Appleby Ave Old Bridge NJ 08857",
    "addr:housenumber":"19",
    "addr:postcode":"08857",
    "addr:street":"Appleby Ave",
    "iso:country":"US",
    "sg:address":"19 Appleby Ave",
    "sg:city":"Old Bridge",
    "sg:classifiers":[
        {
            "category":"Retail",
            "subcategory":"Auto Repair",
            "type":"Services"
        }
    ],
    "sg:phone":"+1 732 251 4313",
    "sg:postcode":"08857",
    "sg:province":"NJ",
    "sg:tags":[
        "automotive"
    ],
    "wof:name":"D & M Auto Body Shop",
    "wof:placetype":"venue"
},
  "geometry": {"coordinates":[-74.36022699999999,40.404198],"type":"Point"}
}