{
  "type": "Feature",
  "properties": {
    "iso:country":"US",
    "sg:address":"510 Hughes St",
    "sg:city":"Cape May",
    "sg:classifiers":[
        {
            "category":"Travel",
            "subcategory":"Hotels & Motels",
            "type":"Entertainment"
        }
    ],
    "sg:phone":"+1 609 884 0116",
    "sg:postcode":"08204",
    "sg:province":"NJ",
    "sg:tags":[
        "operation"
    ],
    "wof:name":"Manse the",
    "wof:placetype":"venue"
},
  "geometry": {"coordinates":[-74.921204,38.932098],"type":"Point"}
}