{
  "type": "Feature",
  "properties": {
    "addr:full":"130 Black Horse Pike Ste 500 Audubon NJ 08106",
    "addr:housenumber":"130",
    "addr:postcode":"08106",
    "addr:street":"Black Horse Pike Ste 500",
    "iso:country":"US",
    "sg:address":"130 Black Horse Pike Ste 500",
    "sg:city":"Audubon",
    "sg:classifiers":[
        {
            "category":"Shopping",
            "subcategory":"Computers & Home Electronics",
            "type":"Retail Goods"
        },
        {
            "category":"Wholesale",
            "subcategory":"Office Equipment",
            "type":"Manufacturing & Wholesale Goods"
        },
        {
            "category":"Professional",
            "subcategory":"Printing & Photocopies",
            "type":"Services"
        },
        {
            "category":"Professional",
            "subcategory":"Computer Services",
            "type":"Services"
        },
        {
            "category":"Shopping",
            "subcategory":"Stationery & Office Supplies",
            "type":"Retail Goods"
        },
        {
            "category":"Wholesale",
            "subcategory":"Computers",
            "type":"Manufacturing & Wholesale Goods"
        }
    ],
    "sg:phone":"+1 856 310 0814",
    "sg:postcode":"08106",
    "sg:province":"NJ",
    "sg:tags":[
        "printer",
        "register",
        "autographic",
        "duplicating",
        "hardware",
        "copying",
        "software",
        "furniture"
    ],
    "sg:website":"www.staples.com",
    "wof:name":"Staples",
    "wof:placetype":"venue"
},
  "geometry": {"coordinates":[-75.09352800000001,39.898483],"type":"Point"}
}