{
  "type": "Feature",
  "properties": {
    "iso:country":"US",
    "sg:address":"101 Channel Dr",
    "sg:city":"Pt Pleasant Beach",
    "sg:classifiers":[
        {
            "category":"Restaurant",
            "type":"Food & Drink"
        }
    ],
    "sg:menulink":"http://www.allmenus.com/nj/point-pleasant-beach/281801-jack-bakers-wharfside/menu/",
    "sg:phone":"+1 732 892 9100",
    "sg:postcode":"08742",
    "sg:province":"NJ",
    "sg:tags":[
        "seafood",
        "american"
    ],
    "wof:name":"Jack Baker's Wharfside",
    "wof:placetype":"venue"
},
  "geometry": {"coordinates":[-74.04061900000001,40.101812],"type":"Point"}
}