{
  "type": "Feature",
  "properties": {
    "iso:country":"US",
    "sg:address":"219 Pleasant Valley Ave",
    "sg:city":"Moorestown",
    "sg:classifiers":[
        {
            "category":"Retail",
            "subcategory":"Auto Repair",
            "type":"Services"
        }
    ],
    "sg:phone":"+1   ",
    "sg:postcode":"08057",
    "sg:province":"NJ",
    "sg:tags":[
        "general"
    ],
    "wof:name":"Motorcar Garage LLC",
    "wof:placetype":"venue"
},
  "geometry": {"coordinates":[-74.95740600000001,39.955367],"type":"Point"}
}