{
  "type": "Feature",
  "properties": {
    "addr:full":"285 Boulevard New Milford NJ 07646",
    "addr:housenumber":"285",
    "addr:postcode":"07646",
    "addr:street":"Boulevard",
    "iso:country":"US",
    "sg:address":"285 Boulevard",
    "sg:city":"New Milford",
    "sg:classifiers":[
        {
            "category":"Building & Trades",
            "subcategory":"Construction",
            "type":"Services"
        }
    ],
    "sg:phone":"+1 201 986 0665",
    "sg:postcode":"07646",
    "sg:province":"NJ",
    "sg:tags":[
        "contractor"
    ],
    "wof:name":"K C B Construction L L C",
    "wof:placetype":"venue"
},
  "geometry": {"coordinates":[-74.016141,40.943251],"type":"Point"}
}