{
  "type": "Feature",
  "properties": {
    "iso:country":"US",
    "sg:address":"46 Wallington Ave",
    "sg:city":"Wallington",
    "sg:classifiers":[
        {
            "category":"Home & Garden",
            "subcategory":"Household Appliances",
            "type":"Retail Goods"
        }
    ],
    "sg:phone":"+1   ",
    "sg:postcode":"07057",
    "sg:province":"NJ",
    "wof:name":"Wallington Discount Appliances",
    "wof:placetype":"venue"
},
  "geometry": {"coordinates":[-74.11525399999999,40.856549],"type":"Point"}
}