{
  "type": "Feature",
  "properties": {
    "addr:full":"990 Chancellor Ave Irvington NJ 07111",
    "addr:housenumber":"990",
    "addr:postcode":"07111",
    "addr:street":"Chancellor Ave",
    "iso:country":"US",
    "sg:address":"990 Chancellor Ave",
    "sg:city":"Irvington",
    "sg:classifiers":[
        {
            "category":"Manufacturing",
            "subcategory":"Food",
            "type":"Manufacturing & Wholesale Goods"
        }
    ],
    "sg:phone":"+1 973 375 8108",
    "sg:postcode":"07111",
    "sg:province":"NJ",
    "sg:tags":[
        "bakery",
        "product"
    ],
    "wof:name":"Wonder Bread",
    "wof:placetype":"venue"
},
  "geometry": {"coordinates":[-74.248778,40.721513],"type":"Point"}
}