{
  "type": "Feature",
  "properties": {
    "addr:full":"1636 State Rte 38 Lumberton NJ 08048",
    "addr:housenumber":"1636",
    "addr:postcode":"08048",
    "addr:street":"State Rte 38",
    "iso:country":"US",
    "sg:address":"1636 State Rte 38",
    "sg:city":"Lumberton",
    "sg:classifiers":[
        {
            "category":"Social Services",
            "subcategory":"Child Care",
            "type":"Services"
        }
    ],
    "sg:phone":"+1 609 265 3887",
    "sg:postcode":"08048",
    "sg:province":"NJ",
    "sg:tags":[
        "kindergarten",
        "academic",
        "school"
    ],
    "wof:name":"Kids Will Always Be Special",
    "wof:placetype":"venue"
},
  "geometry": {"coordinates":[-74.83168999999999,39.977219],"type":"Point"}
}