{
  "type": "Feature",
  "properties": {
    "addr:full":"1209 US Hwy 9 Howell NJ 07731",
    "addr:housenumber":"1209",
    "addr:postcode":"07731",
    "addr:street":"Us Hwy 9",
    "iso:country":"US",
    "sg:address":"1209 US Hwy 9",
    "sg:city":"Howell",
    "sg:classifiers":[
        {
            "category":"Autos & Motor Vehicles",
            "subcategory":"Automobile Sales",
            "type":"Retail Goods"
        }
    ],
    "sg:phone":"+1 732 780 5050",
    "sg:postcode":"07731",
    "sg:province":"NJ",
    "sg:tags":[
        "car",
        "dealer"
    ],
    "wof:name":"One Stop Auto Sales",
    "wof:placetype":"venue"
},
  "geometry": {"coordinates":[-74.254122,40.198679],"type":"Point"}
}