{
  "type": "Feature",
  "properties": {
    "addr:full":"349 Drum Point Rd Brick NJ 08723",
    "addr:housenumber":"349",
    "addr:postcode":"08723",
    "addr:street":"Drum Point Rd",
    "iso:country":"US",
    "sg:address":"349 Drum Point Rd",
    "sg:city":"Brick",
    "sg:classifiers":[
        {
            "category":"Building & Trades",
            "subcategory":"Construction",
            "type":"Services"
        }
    ],
    "sg:phone":"+1 732 920 2379",
    "sg:postcode":"08723",
    "sg:province":"NJ",
    "sg:tags":[
        "maker",
        "cabinet"
    ],
    "wof:name":"South Bay Carpentry",
    "wof:placetype":"venue"
},
  "geometry": {"coordinates":[-74.110799,40.040223],"type":"Point"}
}