{
  "type": "Feature",
  "properties": {
    "addr:full":"1213 Fairmount Ave Elizabeth NJ 07208",
    "addr:housenumber":"1213",
    "addr:postcode":"07208",
    "addr:street":"Fairmount Ave",
    "iso:country":"US",
    "sg:address":"1213 Fairmount Ave",
    "sg:city":"Elizabeth",
    "sg:classifiers":[
        {
            "category":"Building & Trades",
            "subcategory":"Construction",
            "type":"Services"
        }
    ],
    "sg:phone":"+1 908 289 4700",
    "sg:postcode":"07208",
    "sg:province":"NJ",
    "sg:tags":[
        "contractor"
    ],
    "wof:name":"Mag General Contractors",
    "wof:placetype":"venue"
},
  "geometry": {"coordinates":[-74.21060199999999,40.676498],"type":"Point"}
}