{
  "type": "Feature",
  "properties": {
    "addr:full":"19 S New York Ave Atlantic City NJ 08401",
    "addr:housenumber":"19",
    "addr:postcode":"08401",
    "addr:street":"S New York Ave",
    "iso:country":"US",
    "sg:address":"19 S New York Ave",
    "sg:city":"Atlantic City",
    "sg:classifiers":[
        {
            "category":"Communications",
            "subcategory":"Radio Station",
            "type":"Services"
        }
    ],
    "sg:phone":"+1 609 441 1120",
    "sg:postcode":"08401",
    "sg:province":"NJ",
    "sg:tags":[
        "company",
        "broadcasting"
    ],
    "wof:name":"Lenfest Broadcasting",
    "wof:placetype":"venue"
},
  "geometry": {"coordinates":[-74.42846299999999,39.360518],"type":"Point"}
}