{
  "type": "Feature",
  "properties": {
    "iso:country":"US",
    "sg:address":"321 W Franklin Ave",
    "sg:city":"Oaklyn",
    "sg:classifiers":[
        {
            "category":"Health Services",
            "subcategory":"Doctor",
            "type":"Services"
        }
    ],
    "sg:phone":"+1 856 854 0683",
    "sg:postcode":"08107",
    "sg:province":"NJ",
    "sg:tags":[
        "medical"
    ],
    "wof:name":"James A Potter Dm",
    "wof:placetype":"venue"
},
  "geometry": {"coordinates":[-75.08386900000001,39.914578],"type":"Point"}
}