{
  "type": "Feature",
  "properties": {
    "addr:full":"585 W Mount Pleasant Ave Livingston NJ 07039",
    "addr:housenumber":"585",
    "addr:postcode":"07039",
    "addr:street":"W Mount Pleasant Ave",
    "iso:country":"US",
    "sg:address":"585 W Mount Pleasant Ave",
    "sg:city":"Livingston",
    "sg:classifiers":[
        {
            "category":"Building & Trades",
            "subcategory":"Construction",
            "type":"Services"
        }
    ],
    "sg:phone":"+1 973 533 0301",
    "sg:postcode":"07039",
    "sg:province":"NJ",
    "sg:tags":[
        "house"
    ],
    "wof:name":"Melito Construction Corp",
    "wof:placetype":"venue"
},
  "geometry": {"coordinates":[-74.353289,40.797672],"type":"Point"}
}