{
  "type": "Feature",
  "properties": {
    "iso:country":"US",
    "sg:address":"801 W Kennedy Blvd",
    "sg:city":"Lakewood",
    "sg:classifiers":[
        {
            "category":"Education",
            "subcategory":"School",
            "type":"Public Place"
        }
    ],
    "sg:phone":"+1 732 364 0888",
    "sg:postcode":"08701",
    "sg:province":"NJ",
    "wof:name":"Mesivta Of Lakewood",
    "wof:placetype":"venue"
},
  "geometry": {"coordinates":[-74.232235,40.108385],"type":"Point"}
}