{
  "type": "Feature",
  "properties": {
    "iso:country":"US",
    "sg:address":"428 Central Ave",
    "sg:city":"Rahway",
    "sg:classifiers":[
        {
            "category":"Shopping",
            "subcategory":"Clothing, Apparel, & Fashions",
            "type":"Retail Goods"
        }
    ],
    "sg:phone":"+1 732 574 1862",
    "sg:postcode":"07065",
    "sg:province":"NJ",
    "wof:name":"Oceanviews",
    "wof:placetype":"venue"
},
  "geometry": {"coordinates":[-74.283986,40.609661],"type":"Point"}
}