{
  "type": "Feature",
  "properties": {
    "addr:full":"19 Central Ave Toms River NJ 08753",
    "addr:housenumber":"19",
    "addr:postcode":"08753",
    "addr:street":"Central Ave",
    "iso:country":"US",
    "sg:address":"19 Central Ave",
    "sg:city":"Toms River",
    "sg:classifiers":[
        {
            "category":"Building & Trades",
            "subcategory":"Construction",
            "type":"Services"
        }
    ],
    "sg:phone":"+1 732 349 9134",
    "sg:postcode":"08753",
    "sg:province":"NJ",
    "sg:tags":[
        "contractor"
    ],
    "wof:name":"Central Siding & Roofing",
    "wof:placetype":"venue"
},
  "geometry": {"coordinates":[-74.186494,39.954072],"type":"Point"}
}