{
  "type": "Feature",
  "properties": {
    "addr:full":"253 Washington Dr Watchung NJ 07069",
    "addr:housenumber":"253",
    "addr:postcode":"07069",
    "addr:street":"Washington Dr",
    "iso:country":"US",
    "sg:address":"253 Washington Dr",
    "sg:city":"Watchung",
    "sg:classifiers":[
        {
            "category":"Professional",
            "subcategory":"Computer Services",
            "type":"Services"
        }
    ],
    "sg:phone":"+1   ",
    "sg:postcode":"07069",
    "sg:province":"NJ",
    "sg:tags":[
        "company",
        "design",
        "network"
    ],
    "wof:name":"Wandl Inc",
    "wof:placetype":"venue"
},
  "geometry": {"coordinates":[-74.451159,40.62577],"type":"Point"}
}