{
  "type": "Feature",
  "properties": {
    "addr:full":"419 Broadway Bayonne NJ 07002",
    "addr:housenumber":"419",
    "addr:postcode":"07002",
    "addr:street":"Broadway",
    "iso:country":"US",
    "sg:address":"419 Broadway",
    "sg:city":"Bayonne",
    "sg:classifiers":[
        {
            "category":"Real Estate",
            "subcategory":"Developer",
            "type":"Services"
        }
    ],
    "sg:phone":"+1 201 243 9400",
    "sg:postcode":"07002",
    "sg:province":"NJ",
    "wof:name":"B & G Development LLC",
    "wof:placetype":"venue"
},
  "geometry": {"coordinates":[-74.12076999999999,40.660975],"type":"Point"}
}