{
  "type": "Feature",
  "properties": {
    "iso:country":"US",
    "sg:address":"175 E Cohawkin Rd",
    "sg:city":"Clarksboro",
    "sg:classifiers":[
        {
            "category":"Professional",
            "subcategory":"Accounting & Tax Preparation",
            "type":"Services"
        }
    ],
    "sg:phone":"+1 856 423 7700",
    "sg:postcode":"08020",
    "sg:province":"NJ",
    "sg:tags":[
        "billing"
    ],
    "wof:name":"Medical Management Alternative",
    "wof:placetype":"venue"
},
  "geometry": {"coordinates":[-75.218774,39.782913],"type":"Point"}
}