{
  "type": "Feature",
  "properties": {
    "iso:country":"US",
    "sg:address":"33 Lafayette St",
    "sg:city":"Riverside",
    "sg:classifiers":[
        {
            "category":"Bars & Pubs",
            "type":"Food & Drink"
        }
    ],
    "sg:phone":"+1   ",
    "sg:postcode":"08075",
    "sg:province":"NJ",
    "sg:tags":[
        "drinking"
    ],
    "wof:name":"33 Lafayette St Inc",
    "wof:placetype":"venue"
},
  "geometry": {"coordinates":[-74.960464,40.038646],"type":"Point"}
}