{
  "type": "Feature",
  "properties": {
    "addr:full":"1509 3rd Ave Toms River NJ 08757",
    "addr:housenumber":"1509",
    "addr:postcode":"08757",
    "addr:street":"3Rd Ave",
    "iso:country":"US",
    "sg:address":"1509 3rd Ave",
    "sg:city":"Toms River",
    "sg:classifiers":[
        {
            "category":"Building & Trades",
            "subcategory":"Landscaping Services",
            "type":"Services"
        }
    ],
    "sg:phone":"+1 732 505 1230",
    "sg:postcode":"08757",
    "sg:province":"NJ",
    "sg:tags":[
        "landscape"
    ],
    "wof:name":"Steven N Sprague Lndscp/Lwn",
    "wof:placetype":"venue"
},
  "geometry": {"coordinates":[-74.250558,39.997418],"type":"Point"}
}