{
  "type": "Feature",
  "properties": {
    "addr:full":"45 Academy St Ste 501 Newark NJ 07102",
    "addr:housenumber":"45",
    "addr:postcode":"07102",
    "addr:street":"Academy St Ste 501",
    "iso:country":"US",
    "sg:address":"45 Academy St Ste 501",
    "sg:city":"Newark",
    "sg:classifiers":[
        {
            "category":"Education",
            "subcategory":"School",
            "type":"Public Place"
        }
    ],
    "sg:phone":"+1 973 623 0705",
    "sg:postcode":"07102",
    "sg:province":"NJ",
    "wof:name":"Excellent Education For Everyone",
    "wof:placetype":"venue"
},
  "geometry": {"coordinates":[-74.17325700000001,40.737792],"type":"Point"}
}