{
  "type": "Feature",
  "properties": {
    "iso:country":"US",
    "sg:address":"99 Erial Rd",
    "sg:city":"Blackwood",
    "sg:classifiers":[
        {
            "category":"Education",
            "subcategory":"Vocational School",
            "type":"Public Place"
        }
    ],
    "sg:phone":"+1 856 232 0310",
    "sg:postcode":"08012",
    "sg:province":"NJ",
    "sg:tags":[
        "technical",
        "trade"
    ],
    "wof:name":"Pennco Tech",
    "wof:placetype":"venue"
},
  "geometry": {"coordinates":[-75.015118,39.781321],"type":"Point"}
}