{
  "type": "Feature",
  "properties": {
    "addr:full":"19 Greystone Ln Sicklerville NJ 08081",
    "addr:housenumber":"19",
    "addr:postcode":"08081",
    "addr:street":"Greystone Ln",
    "iso:country":"US",
    "sg:address":"19 Greystone Ln",
    "sg:city":"Sicklerville",
    "sg:classifiers":[
        {
            "category":"Building & Trades",
            "subcategory":"Construction",
            "type":"Services"
        }
    ],
    "sg:phone":"+1 856 875 4718",
    "sg:postcode":"08081",
    "sg:province":"NJ",
    "sg:tags":[
        "general",
        "contractor"
    ],
    "wof:name":"Steven Schmerling",
    "wof:placetype":"venue"
},
  "geometry": {"coordinates":[-74.97310400000001,39.737944],"type":"Point"}
}