{
  "type": "Feature",
  "properties": {
    "addr:full":"574 Newark Ave Jersey City NJ 07306",
    "addr:housenumber":"574",
    "addr:postcode":"07306",
    "addr:street":"Newark Ave",
    "iso:country":"US",
    "sg:address":"574 Newark Ave",
    "sg:city":"Jersey City",
    "sg:classifiers":[
        {
            "category":"Organizations",
            "subcategory":"Non-profit Organization",
            "type":"Services"
        },
        {
            "category":"Social Services",
            "type":"Services"
        }
    ],
    "sg:phone":"+1 201 795 5615",
    "sg:postcode":"07306",
    "sg:province":"NJ",
    "sg:tags":[
        "individual",
        "family"
    ],
    "wof:name":"Hudson County Housing Resource",
    "wof:placetype":"venue"
},
  "geometry": {"coordinates":[-74.057142,40.732212],"type":"Point"}
}