{
  "type": "Feature",
  "properties": {
    "iso:country":"US",
    "sg:address":"699 Bay Blvd",
    "sg:city":"Bayville",
    "sg:classifiers":[
        {
            "category":"Restaurant",
            "type":"Food & Drink"
        }
    ],
    "sg:phone":"+1 732 269 6161",
    "sg:postcode":"08721",
    "sg:province":"NJ",
    "sg:website":"www.windowsonthebayrestaurant.com",
    "wof:name":"Windows On The Bay",
    "wof:placetype":"venue"
},
  "geometry": {"coordinates":[-74.140818,39.896636],"type":"Point"}
}