{
  "type": "Feature",
  "properties": {
    "addr:full":"1576 US Hwy 206 Tabernacle NJ 08088",
    "addr:housenumber":"1576",
    "addr:postcode":"08088",
    "addr:street":"Us Hwy 206",
    "iso:country":"US",
    "sg:address":"1576 US Hwy 206",
    "sg:city":"Tabernacle",
    "sg:classifiers":[
        {
            "category":"Personal",
            "subcategory":"Barber",
            "type":"Services"
        }
    ],
    "sg:phone":"+1 609 268 9833",
    "sg:postcode":"08088",
    "sg:province":"NJ",
    "sg:tags":[
        "shop"
    ],
    "wof:name":"Jim's Barber Shop",
    "wof:placetype":"venue"
},
  "geometry": {"coordinates":[-74.733186,39.861208],"type":"Point"}
}