{
  "type": "Feature",
  "properties": {
    "addr:full":"88 Ford Rd Denville NJ 07834",
    "addr:housenumber":"88",
    "addr:postcode":"07834",
    "addr:street":"Ford Rd",
    "iso:country":"US",
    "sg:address":"88 Ford Rd",
    "sg:city":"Denville",
    "sg:classifiers":[
        {
            "category":"Professional",
            "type":"Services"
        }
    ],
    "sg:phone":"+1   ",
    "sg:postcode":"07834",
    "sg:province":"NJ",
    "wof:name":"More Trench America Corp",
    "wof:placetype":"venue"
},
  "geometry": {"coordinates":[-74.48965699999999,40.915362],"type":"Point"}
}