{
  "type": "Feature",
  "properties": {
    "addr:full":"30 Winter Ln Burlington NJ 08016",
    "addr:housenumber":"30",
    "addr:postcode":"08016",
    "addr:street":"Winter Ln",
    "iso:country":"US",
    "sg:address":"30 Winter Ln",
    "sg:city":"Burlington",
    "sg:classifiers":[
        {
            "category":"Professional",
            "subcategory":"Business Services",
            "type":"Services"
        }
    ],
    "sg:phone":"+1   ",
    "sg:postcode":"08016",
    "sg:province":"NJ",
    "wof:name":"G A Communication Corporation",
    "wof:placetype":"venue"
},
  "geometry": {"coordinates":[-74.81902700000001,40.050798],"type":"Point"}
}