{
  "type": "Feature",
  "properties": {
    "addr:full":"319 Central Ave Hackensack NJ 07601",
    "addr:housenumber":"319",
    "addr:postcode":"07601",
    "addr:street":"Central Ave",
    "iso:country":"US",
    "sg:address":"319 Central Ave",
    "sg:city":"Hackensack",
    "sg:classifiers":[
        {
            "category":"Personal",
            "subcategory":"Beauty Salon",
            "type":"Services"
        }
    ],
    "sg:phone":"+1 201 343 6502",
    "sg:postcode":"07601",
    "sg:province":"NJ",
    "sg:tags":[
        "shop"
    ],
    "wof:name":"Lydias Hair Braiding Salon",
    "wof:placetype":"venue"
},
  "geometry": {"coordinates":[-74.05369399999999,40.889948],"type":"Point"}
}