{
  "type": "Feature",
  "properties": {
    "iso:country":"US",
    "sg:address":"54 Hillcrest Rd",
    "sg:city":"Caldwell",
    "sg:classifiers":[
        {
            "category":"Professional",
            "type":"Services"
        }
    ],
    "sg:phone":"+1   ",
    "sg:postcode":"07006",
    "sg:province":"NJ",
    "wof:name":"Bookmarkcom Inc",
    "wof:placetype":"venue"
},
  "geometry": {"coordinates":[-74.279082,40.850068],"type":"Point"}
}