{
  "type": "Feature",
  "properties": {
    "addr:full":"24 Rolling Views Dr Little Falls NJ 07424",
    "addr:housenumber":"24",
    "addr:postcode":"07424",
    "addr:street":"Rolling Views Dr",
    "iso:country":"US",
    "sg:address":"24 Rolling Views Dr",
    "sg:city":"Little Falls",
    "sg:classifiers":[
        {
            "category":"Building & Trades",
            "subcategory":"Construction",
            "type":"Services"
        }
    ],
    "sg:phone":"+1 973 812 3990",
    "sg:postcode":"07424",
    "sg:province":"NJ",
    "sg:tags":[
        "house"
    ],
    "wof:name":"Joseph B Coan Construction Co",
    "wof:placetype":"venue"
},
  "geometry": {"coordinates":[-74.19726,40.883398],"type":"Point"}
}