{
  "type": "Feature",
  "properties": {
    "addr:full":"7520 Bergenline Ave North Bergen NJ 07047",
    "addr:housenumber":"7520",
    "addr:postcode":"07047",
    "addr:street":"Bergenline Ave",
    "iso:country":"US",
    "sg:address":"7520 Bergenline Ave",
    "sg:city":"North Bergen",
    "sg:classifiers":[
        {
            "category":"Banks & Credit Unions",
            "subcategory":"Financial Services",
            "type":"Services"
        }
    ],
    "sg:phone":"+1 201 453 0023",
    "sg:postcode":"07047",
    "sg:province":"NJ",
    "sg:tags":[
        "broker",
        "mortgage"
    ],
    "wof:name":"Zarate Anthony",
    "wof:placetype":"venue"
},
  "geometry": {"coordinates":[-74.00835600000001,40.799135],"type":"Point"}
}