{
  "type": "Feature",
  "properties": {
    "iso:country":"US",
    "sg:address":"200 Wood Ave",
    "sg:city":"Iselin",
    "sg:classifiers":[
        {
            "category":"Insurance",
            "subcategory":"Insurance Agent",
            "type":"Services"
        }
    ],
    "sg:phone":"+1   ",
    "sg:postcode":"08830",
    "sg:province":"NJ",
    "sg:tags":[
        "broker"
    ],
    "wof:name":"Prudential",
    "wof:placetype":"venue"
},
  "geometry": {"coordinates":[-74.336164,40.573682],"type":"Point"}
}