{
  "type": "Feature",
  "properties": {
    "addr:full":"145 Main Ave Clifton NJ 07014",
    "addr:housenumber":"145",
    "addr:postcode":"07014",
    "addr:street":"Main Ave",
    "iso:country":"US",
    "sg:address":"145 Main Ave",
    "sg:city":"Clifton",
    "sg:classifiers":[
        {
            "category":"Shopping",
            "subcategory":"Computers & Home Electronics",
            "type":"Retail Goods"
        }
    ],
    "sg:phone":"+1 973 473 8822",
    "sg:postcode":"07014",
    "sg:province":"NJ",
    "sg:website":"www.telemeasurements.com",
    "wof:name":"Tele-Measurements Inc",
    "wof:placetype":"venue"
},
  "geometry": {"coordinates":[-74.141502,40.831902],"type":"Point"}
}