{
  "type": "Feature",
  "properties": {
    "addr:full":"706 Madison St Hoboken NJ 07030",
    "addr:housenumber":"706",
    "addr:postcode":"07030",
    "addr:street":"Madison St",
    "iso:country":"US",
    "sg:address":"706 Madison St",
    "sg:city":"Hoboken",
    "sg:classifiers":[
        {
            "category":"Building & Trades",
            "subcategory":"Construction",
            "type":"Services"
        }
    ],
    "sg:phone":"+1 201 659 0968",
    "sg:postcode":"07030",
    "sg:province":"NJ",
    "sg:tags":[
        "roofing",
        "contractor"
    ],
    "wof:name":"Schwarz Roofing",
    "wof:placetype":"venue"
},
  "geometry": {"coordinates":[-74.03666200000001,40.74737],"type":"Point"}
}