{
  "type": "Feature",
  "properties": {
    "addr:full":"4 Keith Jeffries Ave Cranford NJ 07016",
    "addr:housenumber":"4",
    "addr:postcode":"07016",
    "addr:street":"Keith Jeffries Ave",
    "iso:country":"US",
    "sg:address":"4 Keith Jeffries Ave",
    "sg:city":"Cranford",
    "sg:classifiers":[
        {
            "category":"Organizations",
            "subcategory":"Community Association",
            "type":"Services"
        }
    ],
    "sg:phone":"+1 908 276 2636",
    "sg:postcode":"07016",
    "sg:province":"NJ",
    "wof:name":"International Assoc of LI",
    "wof:placetype":"venue"
},
  "geometry": {"coordinates":[-74.316755,40.64157],"type":"Point"}
}