{
  "type": "Feature",
  "properties": {
    "addr:full":"59 E Cherry St Rahway NJ 07065",
    "addr:housenumber":"59",
    "addr:postcode":"07065",
    "addr:street":"E Cherry St",
    "iso:country":"US",
    "sg:address":"59 E Cherry St",
    "sg:city":"Rahway",
    "sg:classifiers":[
        {
            "category":"Shopping",
            "subcategory":"Clothing, Apparel, & Fashions",
            "type":"Retail Goods"
        }
    ],
    "sg:phone":"+1 732 340 9000",
    "sg:postcode":"07065",
    "sg:province":"NJ",
    "sg:tags":[
        "sport",
        "wear",
        "sportswear",
        "footwear"
    ],
    "wof:name":"New Era Sportswear Inc",
    "wof:placetype":"venue"
},
  "geometry": {"coordinates":[-74.275002,40.607101],"type":"Point"}
}