{
  "type": "Feature",
  "properties": {
    "iso:country":"US",
    "sg:address":"2801 Highland Ave",
    "sg:city":"Linden",
    "sg:classifiers":[
        {
            "category":"Education",
            "subcategory":"School",
            "type":"Public Place"
        }
    ],
    "sg:phone":"+1 908 486 2043",
    "sg:postcode":"07036",
    "sg:province":"NJ",
    "sg:tags":[
        "high",
        "middle",
        "elementary"
    ],
    "wof:name":"Linden City of",
    "wof:placetype":"venue"
},
  "geometry": {"coordinates":[-74.28281800000001,40.64107],"type":"Point"}
}