{
  "type": "Feature",
  "properties": {
    "addr:full":"1000 Haddonfield Berlin Rd Gibbsboro NJ 08026",
    "addr:housenumber":"1000",
    "addr:postcode":"08026",
    "addr:street":"Haddonfield Berlin Rd",
    "iso:country":"US",
    "sg:address":"1000 Haddonfield Berlin Rd",
    "sg:city":"Gibbsboro",
    "sg:classifiers":[
        {
            "category":"Social Services",
            "type":"Services"
        }
    ],
    "sg:phone":"+1 856 784 1001",
    "sg:postcode":"08026",
    "sg:province":"NJ",
    "sg:tags":[
        "counseling"
    ],
    "wof:name":"Regional Counseling Svc",
    "wof:placetype":"venue"
},
  "geometry": {"coordinates":[-74.951488,39.82373],"type":"Point"}
}