{
  "type": "Feature",
  "properties": {
    "addr:full":"62 Park Ave Park Ridge NJ 07656",
    "addr:housenumber":"62",
    "addr:postcode":"07656",
    "addr:street":"Park Ave",
    "iso:country":"US",
    "sg:address":"62 Park Ave",
    "sg:city":"Park Ridge",
    "sg:classifiers":[
        {
            "category":"Personal",
            "subcategory":"Beauty Salon",
            "type":"Services"
        }
    ],
    "sg:phone":"+1 201 391 3947",
    "sg:postcode":"07656",
    "sg:province":"NJ",
    "sg:tags":[
        "shop"
    ],
    "wof:name":"Mania's Hairstyling",
    "wof:placetype":"venue"
},
  "geometry": {"coordinates":[-74.037812,41.033293],"type":"Point"}
}