{
  "type": "Feature",
  "properties": {
    "iso:country":"US",
    "sg:address":"5 Vaughn Dr",
    "sg:city":"Princeton",
    "sg:classifiers":[
        {
            "category":"Wholesale",
            "subcategory":"Office Equipment",
            "type":"Manufacturing & Wholesale Goods"
        }
    ],
    "sg:phone":"+1 609 987 0350",
    "sg:postcode":"08540",
    "sg:province":"NJ",
    "sg:tags":[
        "copying"
    ],
    "wof:name":"Oce-Office Systems",
    "wof:placetype":"venue"
},
  "geometry": {"coordinates":[-74.628122,40.316235],"type":"Point"}
}