{
  "type": "Feature",
  "properties": {
    "iso:country":"US",
    "sg:address":"193 State Rte 17",
    "sg:city":"Paramus",
    "sg:classifiers":[
        {
            "category":"Retail",
            "subcategory":"Portrait Studio",
            "type":"Services"
        }
    ],
    "sg:phone":"+1 201 265 9140",
    "sg:postcode":"07652",
    "sg:province":"NJ",
    "sg:tags":[
        "photographer"
    ],
    "wof:name":"Magique Studios",
    "wof:placetype":"venue"
},
  "geometry": {"coordinates":[-74.07083799999999,40.909903],"type":"Point"}
}