{
  "type": "Feature",
  "properties": {
    "iso:country":"US",
    "sg:address":"235 Drum Point Rd",
    "sg:city":"Brick",
    "sg:classifiers":[
        {
            "category":"Building & Trades",
            "subcategory":"Electrical",
            "type":"Services"
        }
    ],
    "sg:phone":"+1 732 920 6611",
    "sg:postcode":"08723",
    "sg:province":"NJ",
    "sg:tags":[
        "electrical",
        "electric",
        "contractor"
    ],
    "wof:name":"Lubeck Company South Inc",
    "wof:placetype":"venue"
},
  "geometry": {"coordinates":[-74.120183,40.043668],"type":"Point"}
}