{
  "type": "Feature",
  "properties": {
    "iso:country":"US",
    "sg:address":"382 Springfield Ave",
    "sg:city":"Summit",
    "sg:classifiers":[
        {
            "category":"Wholesale",
            "subcategory":"Photographic Equipment",
            "type":"Manufacturing & Wholesale Goods"
        }
    ],
    "sg:phone":"+1 908 273 3696",
    "sg:postcode":"07901",
    "sg:province":"NJ",
    "sg:tags":[
        "motion",
        "picture"
    ],
    "wof:name":"Roney International Inc",
    "wof:placetype":"venue"
},
  "geometry": {"coordinates":[-74.358345,40.717935],"type":"Point"}
}