{
  "type": "Feature",
  "properties": {
    "iso:country":"US",
    "sg:address":"750 State Rte 73",
    "sg:city":"Marlton",
    "sg:classifiers":[
        {
            "category":"Banks & Credit Unions",
            "subcategory":"Investment Brokerage",
            "type":"Services"
        },
        {
            "category":"Professional",
            "subcategory":"Management & Consulting",
            "type":"Services"
        }
    ],
    "sg:phone":"+1 856 988 1414",
    "sg:postcode":"08053",
    "sg:province":"NJ",
    "sg:tags":[
        "consultant",
        "planning",
        "financial"
    ],
    "wof:name":"Kothare & Kornicki LLC",
    "wof:placetype":"venue"
},
  "geometry": {"coordinates":[-74.921694,39.867715],"type":"Point"}
}