{
  "type": "Feature",
  "properties": {
    "iso:country":"US",
    "sg:address":"152 Ridge Rd",
    "sg:city":"Dayton",
    "sg:classifiers":[
        {
            "category":"Wholesale",
            "subcategory":"Apparel",
            "type":"Manufacturing & Wholesale Goods"
        }
    ],
    "sg:phone":"+1 732 438 1690",
    "sg:postcode":"08831",
    "sg:province":"NJ",
    "sg:tags":[
        "infant",
        "wear"
    ],
    "wof:name":"Hawk Industries",
    "wof:placetype":"venue"
},
  "geometry": {"coordinates":[-74.469024,40.374627],"type":"Point"}
}