{
  "type": "Feature",
  "properties": {
    "iso:country":"US",
    "sg:address":"53 Colt Rd",
    "sg:city":"Summit",
    "sg:classifiers":[
        {
            "category":"Professional",
            "type":"Services"
        }
    ],
    "sg:phone":"+1   ",
    "sg:postcode":"07901",
    "sg:province":"NJ",
    "wof:name":"Kramer Stephaine Co",
    "wof:placetype":"venue"
},
  "geometry": {"coordinates":[-74.374675,40.705043],"type":"Point"}
}