{
  "type": "Feature",
  "properties": {
    "iso:country":"US",
    "sg:address":"102 Magnolia Ave",
    "sg:city":"New Egypt",
    "sg:classifiers":[
        {
            "category":"Professional",
            "subcategory":"Accounting & Tax Preparation",
            "type":"Services"
        }
    ],
    "sg:phone":"+1 609 758 3394",
    "sg:postcode":"08533",
    "sg:province":"NJ",
    "sg:tags":[
        "return",
        "filing"
    ],
    "wof:name":"Kiernan Tax Svc",
    "wof:placetype":"venue"
},
  "geometry": {"coordinates":[-74.517709,40.066438],"type":"Point"}
}