{
  "type": "Feature",
  "properties": {
    "addr:full":"2111 Herbertsville Rd Pt Pleasant Boro NJ 08742",
    "addr:housenumber":"2111",
    "addr:postcode":"08742",
    "addr:street":"Herbertsville Rd Pt",
    "iso:country":"US",
    "sg:address":"2111 Herbertsville Rd",
    "sg:city":"Pt Pleasant Boro",
    "sg:classifiers":[
        {
            "category":"Wholesale",
            "subcategory":"Electrical",
            "type":"Manufacturing & Wholesale Goods"
        }
    ],
    "sg:phone":"+1 732 899 2292",
    "sg:postcode":"08742",
    "sg:province":"NJ",
    "sg:tags":[
        "electric",
        "motor"
    ],
    "wof:name":"Eagle Drives & Controls",
    "wof:placetype":"venue"
},
  "geometry": {"coordinates":[-74.06901999999999,40.083341],"type":"Point"}
}