{
  "type": "Feature",
  "properties": {
    "addr:full":"4 W Park St Bordentown NJ 08505",
    "addr:housenumber":"4",
    "addr:postcode":"08505",
    "addr:street":"W Park St",
    "iso:country":"US",
    "sg:address":"4 W Park St",
    "sg:city":"Bordentown",
    "sg:classifiers":[
        {
            "category":"Shopping",
            "subcategory":"Used Merchandise",
            "type":"Retail Goods"
        }
    ],
    "sg:phone":"+1 609 291 7170",
    "sg:postcode":"08505",
    "sg:province":"NJ",
    "sg:tags":[
        "book",
        "rare",
        "dealer"
    ],
    "wof:name":"Bohemian Bookworm",
    "wof:placetype":"venue"
},
  "geometry": {"coordinates":[-74.71417599999999,40.148366],"type":"Point"}
}