{
  "type": "Feature",
  "properties": {
    "addr:full":"146 W Broad St Bridgeton NJ 08302",
    "addr:housenumber":"146",
    "addr:postcode":"08302",
    "addr:street":"W Broad St",
    "iso:country":"US",
    "sg:address":"146 W Broad St",
    "sg:city":"Bridgeton",
    "sg:classifiers":[
        {
            "category":"Professional",
            "subcategory":"Lawyer & Legal Services",
            "type":"Services"
        }
    ],
    "sg:phone":"+1 856 451 7100",
    "sg:postcode":"08302",
    "sg:province":"NJ",
    "sg:tags":[
        "attorney"
    ],
    "wof:name":"David J Eddowes Esq LLC",
    "wof:placetype":"venue"
},
  "geometry": {"coordinates":[-75.242693,39.428757],"type":"Point"}
}