{
  "type": "Feature",
  "properties": {
    "iso:country":"US",
    "sg:address":"701 Springfield Rd",
    "sg:city":"Kenilworth",
    "sg:classifiers":[
        {
            "category":"Retail",
            "subcategory":"Repair Shop",
            "type":"Services"
        }
    ],
    "sg:phone":"+1 908 624 9990",
    "sg:postcode":"07033",
    "sg:province":"NJ",
    "sg:tags":[
        "equipment",
        "hydraulic"
    ],
    "wof:name":"Pirtek Newark",
    "wof:placetype":"venue"
},
  "geometry": {"coordinates":[-74.29836899999999,40.684647],"type":"Point"}
}