{
  "type": "Feature",
  "properties": {
    "iso:country":"US",
    "sg:address":"107 Essex Ave",
    "sg:city":"Boonton",
    "sg:classifiers":[
        {
            "category":"Real Estate",
            "subcategory":"Developer",
            "type":"Services"
        }
    ],
    "sg:phone":"+1   ",
    "sg:postcode":"07005",
    "sg:province":"NJ",
    "sg:tags":[
        "cemetery"
    ],
    "wof:name":"Cemetery Greenwood Assoc",
    "wof:placetype":"venue"
},
  "geometry": {"coordinates":[-74.420299,40.907096],"type":"Point"}
}