{
  "type": "Feature",
  "properties": {
    "iso:country":"US",
    "sg:address":"632 20th Ave",
    "sg:city":"Paterson",
    "sg:classifiers":[
        {
            "category":"Professional",
            "subcategory":"Accounting & Tax Preparation",
            "type":"Services"
        }
    ],
    "sg:phone":"+1   ",
    "sg:postcode":"07504",
    "sg:province":"NJ",
    "wof:name":"Gil Expertax Plus",
    "wof:placetype":"venue"
},
  "geometry": {"coordinates":[-74.14187,40.906629],"type":"Point"}
}