{
  "type": "Feature",
  "properties": {
    "iso:country":"US",
    "sg:address":"200 Garden St",
    "sg:city":"Hoboken",
    "sg:classifiers":[
        {
            "category":"Building & Trades",
            "subcategory":"Locksmith",
            "type":"Services"
        }
    ],
    "sg:phone":"+1 877 800 4109",
    "sg:postcode":"07030",
    "sg:province":"NJ",
    "sg:tags":[
        "key"
    ],
    "wof:name":"Always Available 24 Hour Emergency Locksmith",
    "wof:placetype":"venue"
},
  "geometry": {"coordinates":[-74.032414,40.739059],"type":"Point"}
}