{
  "type": "Feature",
  "properties": {
    "iso:country":"US",
    "sg:address":"185 Montross Ave",
    "sg:city":"Rutherford",
    "sg:classifiers":[
        {
            "category":"Organizations",
            "subcategory":"Religious Organization",
            "type":"Services"
        }
    ],
    "sg:phone":"+1 201 438 4931",
    "sg:postcode":"07070",
    "sg:province":"NJ",
    "sg:tags":[
        "synagogue"
    ],
    "wof:name":"Temple Beth-El",
    "wof:placetype":"venue"
},
  "geometry": {"coordinates":[-74.111099,40.832699],"type":"Point"}
}