{
  "type": "Feature",
  "properties": {
    "iso:country":"US",
    "sg:address":"1391 Oak Tree Rd",
    "sg:city":"Iselin",
    "sg:classifiers":[
        {
            "category":"Real Estate",
            "subcategory":"Real Estate Agent",
            "type":"Services"
        }
    ],
    "sg:phone":"+1 732 283 2405",
    "sg:postcode":"08830",
    "sg:province":"NJ",
    "wof:name":"Iselin Property LLC",
    "wof:placetype":"venue"
},
  "geometry": {"coordinates":[-74.325264,40.573728],"type":"Point"}
}