{
  "type": "Feature",
  "properties": {
    "iso:country":"US",
    "sg:address":"17 Tanglewood Dr",
    "sg:city":"Livingston",
    "sg:classifiers":[
        {
            "category":"Shopping",
            "subcategory":"Computers & Home Electronics",
            "type":"Retail Goods"
        }
    ],
    "sg:phone":"+1   ",
    "sg:postcode":"07039",
    "sg:province":"NJ",
    "sg:tags":[
        "product",
        "sales"
    ],
    "wof:name":"Wholesale Computer Products",
    "wof:placetype":"venue"
},
  "geometry": {"coordinates":[-74.30656999999999,40.79958],"type":"Point"}
}