{
  "type": "Feature",
  "properties": {
    "iso:country":"US",
    "sg:address":"1600 Queen Anne Rd",
    "sg:city":"Teaneck",
    "sg:classifiers":[
        {
            "category":"Education",
            "subcategory":"School",
            "type":"Public Place"
        }
    ],
    "sg:phone":"+1 201 862 0032",
    "sg:postcode":"07666",
    "sg:province":"NJ",
    "wof:name":"Sinai High School For Boys",
    "wof:placetype":"venue"
},
  "geometry": {"coordinates":[-74.001684,40.904678],"type":"Point"}
}