{
  "type": "Feature",
  "properties": {
    "addr:full":"197 Jefferson St Passaic NJ 07055",
    "addr:housenumber":"197",
    "addr:postcode":"07055",
    "addr:street":"Jefferson St",
    "iso:country":"US",
    "sg:address":"197 Jefferson St",
    "sg:city":"Passaic",
    "sg:classifiers":[
        {
            "category":"Travel",
            "subcategory":"Travel Agent",
            "type":"Entertainment"
        }
    ],
    "sg:phone":"+1 973 473 9626",
    "sg:postcode":"07055",
    "sg:province":"NJ",
    "sg:tags":[
        "agency",
        "bureau"
    ],
    "wof:name":"Continental Travel Inc",
    "wof:placetype":"venue"
},
  "geometry": {"coordinates":[-74.125817,40.86201],"type":"Point"}
}