{
  "type": "Feature",
  "properties": {
    "iso:country":"US",
    "sg:address":"720 Sloan Ave",
    "sg:city":"Trenton",
    "sg:classifiers":[
        {
            "category":"Freight",
            "type":"Transportation"
        }
    ],
    "sg:phone":"+1 609 586 1370",
    "sg:postcode":"08619",
    "sg:province":"NJ",
    "sg:tags":[
        "local",
        "storage",
        "trucking"
    ],
    "wof:name":"Allied Van",
    "wof:placetype":"venue"
},
  "geometry": {"coordinates":[-74.70363999999999,40.252164],"type":"Point"}
}