{
  "type": "Feature",
  "properties": {
    "addr:full":"170 Flintlock Rd Morris Plains NJ 07950",
    "addr:housenumber":"170",
    "addr:postcode":"07950",
    "addr:street":"Flintlock Rd",
    "iso:country":"US",
    "sg:address":"170 Flintlock Rd",
    "sg:city":"Morris Plains",
    "sg:classifiers":[
        {
            "category":"Professional",
            "subcategory":"Management & Consulting",
            "type":"Services"
        }
    ],
    "sg:phone":"+1   ",
    "sg:postcode":"07950",
    "sg:province":"NJ",
    "sg:tags":[
        "business"
    ],
    "wof:name":"Comfort Systems Consulting LLC",
    "wof:placetype":"venue"
},
  "geometry": {"coordinates":[-74.48259299999999,40.857766],"type":"Point"}
}