{
  "type": "Feature",
  "properties": {
    "iso:country":"US",
    "sg:address":"4212 Harbor Beach Blvd",
    "sg:city":"Brigantine",
    "sg:classifiers":[
        {
            "category":"Retail",
            "subcategory":"Laundry & Dry Cleaning",
            "type":"Services"
        }
    ],
    "sg:phone":"+1 609 266 6247",
    "sg:postcode":"08203",
    "sg:province":"NJ",
    "wof:name":"Brigantine Dry Cleaners",
    "wof:placetype":"venue"
},
  "geometry": {"coordinates":[-74.397942,39.394204],"type":"Point"}
}