{
  "type": "Feature",
  "properties": {
    "iso:country":"US",
    "sg:address":"23 Stone Hill Rd",
    "sg:city":"Cream Ridge",
    "sg:classifiers":[
        {
            "category":"Manufacturing",
            "subcategory":"Tools & Machinery",
            "type":"Manufacturing & Wholesale Goods"
        }
    ],
    "sg:phone":"+1 609 259 6757",
    "sg:postcode":"08514",
    "sg:province":"NJ",
    "sg:tags":[
        "model",
        "maker"
    ],
    "wof:name":"David A Ramsey Model Design",
    "wof:placetype":"venue"
},
  "geometry": {"coordinates":[-74.476281,40.185917],"type":"Point"}
}