{
  "type": "Feature",
  "properties": {
    "iso:country":"US",
    "sg:address":"110 Chestnut Ridge Rd",
    "sg:city":"Montvale",
    "sg:classifiers":[
        {
            "category":"Wholesale",
            "subcategory":"Home Furnishings",
            "type":"Manufacturing & Wholesale Goods"
        }
    ],
    "sg:phone":"+1 877 558 1491",
    "sg:postcode":"07645",
    "sg:province":"NJ",
    "sg:tags":[
        "fixtures-wholesale",
        "lighting",
        "manufacturer"
    ],
    "wof:name":"Us Lighting Products",
    "wof:placetype":"venue"
},
  "geometry": {"coordinates":[-74.067961,41.056371],"type":"Point"}
}