{
  "type": "Feature",
  "properties": {
    "iso:country":"US",
    "sg:address":"343 Avon Ave",
    "sg:city":"Newark",
    "sg:classifiers":[
        {
            "category":"Food & Beverages",
            "subcategory":"Liquor & Beverages",
            "type":"Retail Goods"
        }
    ],
    "sg:phone":"+1 973 624 1242",
    "sg:postcode":"07108",
    "sg:province":"NJ",
    "wof:name":"Avon Liquor",
    "wof:placetype":"venue"
},
  "geometry": {"coordinates":[-74.20679,40.726892],"type":"Point"}
}