{
  "type": "Feature",
  "properties": {
    "addr:full":"12 Roszel Rd Princeton NJ 08540",
    "addr:housenumber":"12",
    "addr:postcode":"08540",
    "addr:street":"Roszel Rd",
    "iso:country":"US",
    "sg:address":"12 Roszel Rd",
    "sg:city":"Princeton",
    "sg:classifiers":[
        {
            "category":"Organizations",
            "subcategory":"Membership Organization",
            "type":"Services"
        },
        {
            "category":"Museum",
            "type":"Entertainment"
        }
    ],
    "sg:phone":"+1 609 243 9000",
    "sg:postcode":"08540",
    "sg:province":"NJ",
    "sg:tags":[
        "information",
        "arts",
        "education",
        "nonprofit"
    ],
    "sg:website":"www.yanj.org",
    "wof:name":"Young Audiences of New Jersey",
    "wof:placetype":"venue"
},
  "geometry": {"coordinates":[-74.63752700000001,40.3214],"type":"Point"}
}