{
  "type": "Feature",
  "properties": {
    "addr:full":"776 Radix Rd Williamstown NJ 08094",
    "addr:housenumber":"776",
    "addr:postcode":"08094",
    "addr:street":"Radix Rd",
    "iso:country":"US",
    "sg:address":"776 Radix Rd",
    "sg:city":"Williamstown",
    "sg:classifiers":[
        {
            "category":"Building & Trades",
            "subcategory":"Construction",
            "type":"Services"
        }
    ],
    "sg:phone":"+1 856 728 5599",
    "sg:postcode":"08094",
    "sg:province":"NJ",
    "sg:tags":[
        "refacing",
        "kitchen",
        "cabinet"
    ],
    "wof:name":"American Kitchen Refacing Inc",
    "wof:placetype":"venue"
},
  "geometry": {"coordinates":[-74.96214999999999,39.691827],"type":"Point"}
}