{
  "type": "Feature",
  "properties": {
    "addr:full":"214 Essex St Hackensack NJ 07601",
    "addr:housenumber":"214",
    "addr:postcode":"07601",
    "addr:street":"Essex St",
    "iso:country":"US",
    "sg:address":"214 Essex St",
    "sg:city":"Hackensack",
    "sg:classifiers":[
        {
            "category":"Restaurant",
            "type":"Food & Drink"
        }
    ],
    "sg:phone":"+1 201 343 6080",
    "sg:postcode":"07601",
    "sg:province":"NJ",
    "sg:tags":[
        "eating"
    ],
    "wof:name":"Hop Shing Restaurant",
    "wof:placetype":"venue"
},
  "geometry": {"coordinates":[-74.053409,40.880433],"type":"Point"}
}