{
  "type": "Feature",
  "properties": {
    "addr:full":"225 E State St Trenton NJ 08608",
    "addr:housenumber":"225",
    "addr:postcode":"08608",
    "addr:street":"E State St",
    "iso:country":"US",
    "sg:address":"225 E State St",
    "sg:city":"Trenton",
    "sg:classifiers":[
        {
            "category":"Government",
            "subcategory":"Office",
            "type":"Public Place"
        }
    ],
    "sg:phone":"+1 609 292 4580",
    "sg:postcode":"08608",
    "sg:province":"NJ",
    "wof:name":"Nj State Motor Vhcl Commission",
    "wof:placetype":"venue"
},
  "geometry": {"coordinates":[-74.75975099999999,40.220505],"type":"Point"}
}