{
  "type": "Feature",
  "properties": {
    "addr:full":"597 Pompton Ave Cedar Grove NJ 07009",
    "addr:housenumber":"597",
    "addr:postcode":"07009",
    "addr:street":"Pompton Ave",
    "iso:country":"US",
    "sg:address":"597 Pompton Ave",
    "sg:city":"Cedar Grove",
    "sg:classifiers":[
        {
            "category":"Food & Beverages",
            "subcategory":"Groceries & Convenience Stores",
            "type":"Retail Goods"
        }
    ],
    "sg:phone":"+1   ",
    "sg:postcode":"07009",
    "sg:province":"NJ",
    "wof:name":"Food Town",
    "wof:placetype":"venue"
},
  "geometry": {"coordinates":[-74.22969399999999,40.852894],"type":"Point"}
}