{
  "type": "Feature",
  "properties": {
    "addr:full":"104 Union Ave Stratford NJ 08084",
    "addr:housenumber":"104",
    "addr:postcode":"08084",
    "addr:street":"Union Ave",
    "iso:country":"US",
    "sg:address":"104 Union Ave",
    "sg:city":"Stratford",
    "sg:classifiers":[
        {
            "category":"Building & Trades",
            "subcategory":"Plumbing",
            "type":"Services"
        }
    ],
    "sg:phone":"+1 856 627 8606",
    "sg:postcode":"08084",
    "sg:province":"NJ",
    "sg:tags":[
        "conditioning",
        "air",
        "system",
        "contractor"
    ],
    "wof:name":"Air Crafters",
    "wof:placetype":"venue"
},
  "geometry": {"coordinates":[-75.009298,39.83126],"type":"Point"}
}