{
  "type": "Feature",
  "properties": {
    "iso:country":"US",
    "sg:address":"435 S Shore Rd",
    "sg:city":"Absecon",
    "sg:classifiers":[
        {
            "category":"Building & Trades",
            "subcategory":"Construction",
            "type":"Services"
        }
    ],
    "sg:phone":"+1 609 272 0370",
    "sg:postcode":"08201",
    "sg:province":"NJ",
    "sg:tags":[
        "house",
        "business"
    ],
    "wof:name":"Stankus Home Inspection",
    "wof:placetype":"venue"
},
  "geometry": {"coordinates":[-74.501065,39.418174],"type":"Point"}
}