{
  "type": "Feature",
  "properties": {
    "addr:full":"766 Lidgerwood Ave Elizabeth NJ 07202",
    "addr:housenumber":"766",
    "addr:postcode":"07202",
    "addr:street":"Lidgerwood Ave",
    "iso:country":"US",
    "sg:address":"766 Lidgerwood Ave",
    "sg:city":"Elizabeth",
    "sg:classifiers":[
        {
            "category":"Organizations",
            "subcategory":"Religious Organization",
            "type":"Services"
        }
    ],
    "sg:phone":"+1 908 354 8000",
    "sg:postcode":"07202",
    "sg:province":"NJ",
    "wof:name":"Sant Nirankari Mission",
    "wof:placetype":"venue"
},
  "geometry": {"coordinates":[-74.22550200000001,40.651001],"type":"Point"}
}