{
  "type": "Feature",
  "properties": {
    "addr:full":"407 Ocean Ave Belmar NJ 07719",
    "addr:housenumber":"407",
    "addr:postcode":"07719",
    "addr:street":"Ocean Ave",
    "iso:country":"US",
    "sg:address":"407 Ocean Ave",
    "sg:city":"Belmar",
    "sg:classifiers":[
        {
            "category":"Professional",
            "subcategory":"Management & Consulting",
            "type":"Services"
        }
    ],
    "sg:phone":"+1 732 735 7275",
    "sg:postcode":"07719",
    "sg:province":"NJ",
    "sg:tags":[
        "fuel"
    ],
    "wof:name":"Storrelle Management Inc",
    "wof:placetype":"venue"
},
  "geometry": {"coordinates":[-74.011636,40.182824],"type":"Point"}
}