{
  "type": "Feature",
  "properties": {
    "addr:full":"577 Schaefer Ave Oradell NJ 07649",
    "addr:housenumber":"577",
    "addr:postcode":"07649",
    "addr:street":"Schaefer Ave",
    "iso:country":"US",
    "sg:address":"577 Schaefer Ave",
    "sg:city":"Oradell",
    "sg:classifiers":[
        {
            "category":"Utilities",
            "subcategory":"Telephone",
            "type":"Services"
        }
    ],
    "sg:phone":"+1 201 986 9886",
    "sg:postcode":"07649",
    "sg:province":"NJ",
    "sg:tags":[
        "computer",
        "electronic"
    ],
    "wof:name":"Changedirectory",
    "wof:placetype":"venue"
},
  "geometry": {"coordinates":[-74.032661,40.945638],"type":"Point"}
}