{
  "type": "Feature",
  "properties": {
    "iso:country":"US",
    "sg:address":"129 Godwin Ave",
    "sg:city":"Midland Park",
    "sg:classifiers":[
        {
            "category":"Banks & Credit Unions",
            "subcategory":"Bank",
            "type":"Services"
        }
    ],
    "sg:phone":"+1   ",
    "sg:postcode":"07432",
    "sg:province":"NJ",
    "sg:tags":[
        "national",
        "commercial"
    ],
    "wof:name":"Bank Of New York",
    "wof:placetype":"venue"
},
  "geometry": {"coordinates":[-74.139206,40.985921],"type":"Point"}
}