{
  "type": "Feature",
  "properties": {
    "iso:country":"US",
    "sg:address":"116 Paris Ave",
    "sg:city":"Northvale",
    "sg:classifiers":[
        {
            "category":"Education",
            "subcategory":"School",
            "type":"Public Place"
        }
    ],
    "sg:phone":"+1   ",
    "sg:postcode":"07647",
    "sg:province":"NJ",
    "sg:tags":[
        "executive"
    ],
    "wof:name":"Northvale Borough Of Inc",
    "wof:placetype":"venue"
},
  "geometry": {"coordinates":[-73.95219299999999,41.007863],"type":"Point"}
}