{
  "type": "Feature",
  "properties": {
    "iso:country":"US",
    "sg:address":"197 Long Swamp Rd",
    "sg:city":"New Egypt",
    "sg:classifiers":[
        {
            "category":"Restaurant",
            "type":"Food & Drink"
        }
    ],
    "sg:phone":"+1   ",
    "sg:postcode":"08533",
    "sg:province":"NJ",
    "sg:tags":[
        "eating"
    ],
    "wof:name":"Harpers Ice Cream",
    "wof:placetype":"venue"
},
  "geometry": {"coordinates":[-74.500412,40.048332],"type":"Point"}
}