{
  "type": "Feature",
  "properties": {
    "addr:full":"4 Apollo Ave Sewell NJ 08080",
    "addr:housenumber":"4",
    "addr:postcode":"08080",
    "addr:street":"Apollo Ave",
    "iso:country":"US",
    "sg:address":"4 Apollo Ave",
    "sg:city":"Sewell",
    "sg:classifiers":[
        {
            "category":"Shopping",
            "subcategory":"Musical Instruments",
            "type":"Retail Goods"
        }
    ],
    "sg:phone":"+1 856 582 1984",
    "sg:postcode":"08080",
    "sg:province":"NJ",
    "sg:tags":[
        "piano",
        "organ"
    ],
    "wof:name":"Glenda's Piano Studio",
    "wof:placetype":"venue"
},
  "geometry": {"coordinates":[-75.09563799999999,39.726086],"type":"Point"}
}