{
  "type": "Feature",
  "properties": {
    "addr:full":"22 Sunset Trl Rockaway NJ 07866",
    "addr:housenumber":"22",
    "addr:postcode":"07866",
    "addr:street":"Sunset Trl",
    "iso:country":"US",
    "sg:address":"22 Sunset Trl",
    "sg:city":"Rockaway",
    "sg:classifiers":[
        {
            "category":"Building & Trades",
            "subcategory":"Construction",
            "type":"Services"
        }
    ],
    "sg:phone":"+1 973 586 6889",
    "sg:postcode":"07866",
    "sg:province":"NJ",
    "sg:tags":[
        "addition",
        "home",
        "remodeling",
        "repair"
    ],
    "wof:name":"Blume Construction",
    "wof:placetype":"venue"
},
  "geometry": {"coordinates":[-74.49896099999999,40.953334],"type":"Point"}
}