{
  "type": "Feature",
  "properties": {
    "addr:full":"10 Smith Ct Vincentown NJ 08088",
    "addr:housenumber":"10",
    "addr:postcode":"08088",
    "addr:street":"Smith Ct",
    "iso:country":"US",
    "sg:address":"10 Smith Ct",
    "sg:city":"Vincentown",
    "sg:classifiers":[
        {
            "category":"Professional",
            "subcategory":"Business Services",
            "type":"Services"
        }
    ],
    "sg:phone":"+1 609 859 3823",
    "sg:postcode":"08088",
    "sg:province":"NJ",
    "wof:name":"Interiors By George LLC",
    "wof:placetype":"venue"
},
  "geometry": {"coordinates":[-74.75248000000001,39.933891],"type":"Point"}
}