{
  "type": "Feature",
  "properties": {
    "addr:full":"136 Mehrhof Rd Little Ferry NJ 07643",
    "addr:housenumber":"136",
    "addr:postcode":"07643",
    "addr:street":"Mehrhof Rd",
    "iso:country":"US",
    "sg:address":"136 Mehrhof Rd",
    "sg:city":"Little Ferry",
    "sg:classifiers":[
        {
            "category":"Restaurant",
            "type":"Food & Drink"
        }
    ],
    "sg:phone":"+1 201 641 2892",
    "sg:postcode":"07643",
    "sg:province":"NJ",
    "sg:tags":[
        "eating"
    ],
    "wof:name":"Empire Club the",
    "wof:placetype":"venue"
},
  "geometry": {"coordinates":[-74.037102,40.842201],"type":"Point"}
}