{
  "type": "Feature",
  "properties": {
    "addr:full":"185 High St Nutley NJ 07110",
    "addr:housenumber":"185",
    "addr:postcode":"07110",
    "addr:street":"High St",
    "iso:country":"US",
    "sg:address":"185 High St",
    "sg:city":"Nutley",
    "sg:classifiers":[
        {
            "category":"Building & Trades",
            "subcategory":"Construction",
            "type":"Services"
        }
    ],
    "sg:phone":"+1 973 667 7300",
    "sg:postcode":"07110",
    "sg:province":"NJ",
    "sg:tags":[
        "paving",
        "contractor"
    ],
    "wof:name":"D & L Paving Contractors",
    "wof:placetype":"venue"
},
  "geometry": {"coordinates":[-74.15961900000001,40.828807],"type":"Point"}
}