{
  "type": "Feature",
  "properties": {
    "iso:country":"US",
    "sg:address":"246 Industrial Way W",
    "sg:city":"Eatontown",
    "sg:classifiers":[
        {
            "category":"Wholesale",
            "subcategory":"Electrical",
            "type":"Manufacturing & Wholesale Goods"
        }
    ],
    "sg:phone":"+1 732 544 3194",
    "sg:postcode":"07724",
    "sg:province":"NJ",
    "sg:tags":[
        "electronic"
    ],
    "wof:name":"Vtech Innovation Ltd Partnr",
    "wof:placetype":"venue"
},
  "geometry": {"coordinates":[-74.067047,40.273885],"type":"Point"}
}