{
  "type": "Feature",
  "properties": {
    "addr:full":"57 Malibu Dr Eatontown NJ 07724",
    "addr:housenumber":"57",
    "addr:postcode":"07724",
    "addr:street":"Malibu Dr",
    "iso:country":"US",
    "sg:address":"57 Malibu Dr",
    "sg:city":"Eatontown",
    "sg:classifiers":[
        {
            "category":"Food & Beverages",
            "subcategory":"Groceries & Convenience Stores",
            "type":"Retail Goods"
        }
    ],
    "sg:phone":"+1   ",
    "sg:postcode":"07724",
    "sg:province":"NJ",
    "wof:name":"Seva Arti Inc",
    "wof:placetype":"venue"
},
  "geometry": {"coordinates":[-74.046054,40.294227],"type":"Point"}
}