{
  "type": "Feature",
  "properties": {
    "addr:full":"156 King St Mt Holly NJ 08060",
    "addr:housenumber":"156",
    "addr:postcode":"08060",
    "addr:street":"King St",
    "iso:country":"US",
    "sg:address":"156 King St",
    "sg:city":"Mt Holly",
    "sg:classifiers":[
        {
            "category":"Organizations",
            "subcategory":"Religious Organization",
            "type":"Services"
        }
    ],
    "sg:phone":"+1 609 261 6564",
    "sg:postcode":"08060",
    "sg:province":"NJ",
    "sg:tags":[
        "church"
    ],
    "wof:name":"Faith Chapel AME Zion Church",
    "wof:placetype":"venue"
},
  "geometry": {"coordinates":[-74.792805,39.99506],"type":"Point"}
}