{
  "type": "Feature",
  "properties": {
    "addr:full":"9 S Washington Ave Bergenfield NJ 07621",
    "addr:housenumber":"9",
    "addr:postcode":"07621",
    "addr:street":"S Washington Ave",
    "iso:country":"US",
    "sg:address":"9 S Washington Ave",
    "sg:city":"Bergenfield",
    "sg:classifiers":[
        {
            "category":"Wholesale",
            "subcategory":"Drugs",
            "type":"Manufacturing & Wholesale Goods"
        }
    ],
    "sg:phone":"+1 201 385 0773",
    "sg:postcode":"07621",
    "sg:province":"NJ",
    "wof:name":"Amsera Beauty Supply",
    "wof:placetype":"venue"
},
  "geometry": {"coordinates":[-73.99651799999999,40.926173],"type":"Point"}
}