{
  "type": "Feature",
  "properties": {
    "iso:country":"US",
    "sg:address":"1222 Sussex Tpke",
    "sg:city":"Randolph",
    "sg:classifiers":[
        {
            "category":"Restaurant",
            "type":"Food & Drink"
        }
    ],
    "sg:phone":"+1 973 895 1300",
    "sg:postcode":"07869",
    "sg:province":"NJ",
    "sg:tags":[
        "barbecue"
    ],
    "wof:name":"American BBQ Co Inc",
    "wof:placetype":"venue"
},
  "geometry": {"coordinates":[-74.580977,40.825685],"type":"Point"}
}