{
  "type": "Feature",
  "properties": {
    "addr:full":"645 Hermann Rd North Brunswick NJ 08902",
    "addr:housenumber":"645",
    "addr:postcode":"08902",
    "addr:street":"Hermann Rd",
    "iso:country":"US",
    "sg:address":"645 Hermann Rd",
    "sg:city":"North Brunswick",
    "sg:classifiers":[
        {
            "category":"Shopping",
            "type":"Retail Goods"
        }
    ],
    "sg:phone":"+1   ",
    "sg:postcode":"08902",
    "sg:province":"NJ",
    "sg:tags":[
        "merchandise"
    ],
    "wof:name":"Grooming Tails",
    "wof:placetype":"venue"
},
  "geometry": {"coordinates":[-74.454832,40.466781],"type":"Point"}
}