{
  "type": "Feature",
  "properties": {
    "addr:full":"417 Prospect Ave Union Beach NJ 07735",
    "addr:housenumber":"417",
    "addr:postcode":"07735",
    "addr:street":"Prospect Ave",
    "iso:country":"US",
    "sg:address":"417 Prospect Ave",
    "sg:city":"Union Beach",
    "sg:classifiers":[
        {
            "category":"Building & Trades",
            "subcategory":"Cleaning & Sanitation",
            "type":"Services"
        }
    ],
    "sg:phone":"+1 732 264 4274",
    "sg:postcode":"07735",
    "sg:province":"NJ",
    "sg:tags":[
        "janitor"
    ],
    "wof:name":"Tony's Cleaning Svc",
    "wof:placetype":"venue"
},
  "geometry": {"coordinates":[-74.16995199999999,40.446354],"type":"Point"}
}