{
  "type": "Feature",
  "properties": {
    "iso:country":"US",
    "sg:address":"718 Sergeantsville Rd",
    "sg:city":"Stockton",
    "sg:classifiers":[
        {
            "category":"Farming",
            "subcategory":"Farm",
            "type":"Manufacturing & Wholesale Goods"
        }
    ],
    "sg:phone":"+1 908 782 9706",
    "sg:postcode":"08559",
    "sg:province":"NJ",
    "sg:tags":[
        "crop",
        "general"
    ],
    "wof:name":"Nancy Polozker Warren Hill Frm",
    "wof:placetype":"venue"
},
  "geometry": {"coordinates":[-74.937854,40.452293],"type":"Point"}
}