{
  "type": "Feature",
  "properties": {
    "iso:country":"US",
    "sg:address":"30 Montgomery St",
    "sg:city":"Clifton",
    "sg:classifiers":[
        {
            "category":"Shopping",
            "subcategory":"Hobbies, Toys, & Games",
            "type":"Retail Goods"
        }
    ],
    "sg:phone":"+1 973 772 3854",
    "sg:postcode":"07011",
    "sg:province":"NJ",
    "sg:tags":[
        "equipment",
        "ceramic",
        "supply"
    ],
    "wof:name":"Dolly Ceramics",
    "wof:placetype":"venue"
},
  "geometry": {"coordinates":[-74.15280300000001,40.878927],"type":"Point"}
}