{
  "type": "Feature",
  "properties": {
    "addr:full":"10 3rd St Raritan NJ 08869",
    "addr:housenumber":"10",
    "addr:postcode":"08869",
    "addr:street":"3Rd St",
    "iso:country":"US",
    "sg:address":"10 3rd St",
    "sg:city":"Raritan",
    "sg:classifiers":[
        {
            "category":"Shopping",
            "subcategory":"Computers & Home Electronics",
            "type":"Retail Goods"
        }
    ],
    "sg:phone":"+1   ",
    "sg:postcode":"08869",
    "sg:province":"NJ",
    "wof:name":"Insyte Auto",
    "wof:placetype":"venue"
},
  "geometry": {"coordinates":[-74.637665,40.569817],"type":"Point"}
}