{
  "type": "Feature",
  "properties": {
    "addr:full":"27 Omaha Rd Wayne NJ 07470",
    "addr:housenumber":"27",
    "addr:postcode":"07470",
    "addr:street":"Omaha Rd",
    "iso:country":"US",
    "sg:address":"27 Omaha Rd",
    "sg:city":"Wayne",
    "sg:classifiers":[
        {
            "category":"Building & Trades",
            "subcategory":"Construction",
            "type":"Services"
        }
    ],
    "sg:phone":"+1 973 835 8515",
    "sg:postcode":"07470",
    "sg:province":"NJ",
    "sg:tags":[
        "house"
    ],
    "wof:name":"Mdm Builders Inc",
    "wof:placetype":"venue"
},
  "geometry": {"coordinates":[-74.25173700000001,40.989941],"type":"Point"}
}