{
  "type": "Feature",
  "properties": {
    "addr:full":"47 Silver Spring Rd Short Hills NJ 07078",
    "addr:housenumber":"47",
    "addr:postcode":"07078",
    "addr:street":"Silver Spring Rd",
    "iso:country":"US",
    "sg:address":"47 Silver Spring Rd",
    "sg:city":"Short Hills",
    "sg:classifiers":[
        {
            "category":"Communications",
            "type":"Services"
        }
    ],
    "sg:phone":"+1 973 258 0858",
    "sg:postcode":"07078",
    "sg:province":"NJ",
    "sg:tags":[
        "communication"
    ],
    "wof:name":"Silverback Communications Ltd",
    "wof:placetype":"venue"
},
  "geometry": {"coordinates":[-74.311808,40.752072],"type":"Point"}
}