{
  "type": "Feature",
  "properties": {
    "iso:country":"US",
    "sg:address":"217 Sunset Rd",
    "sg:city":"Willingboro",
    "sg:classifiers":[
        {
            "category":"Retail",
            "subcategory":"Portrait Studio",
            "type":"Services"
        },
        {
            "category":"Shopping",
            "subcategory":"Pharmacy",
            "type":"Retail Goods"
        }
    ],
    "sg:phone":"+1 609 877 0700",
    "sg:postcode":"08046",
    "sg:province":"NJ",
    "sg:tags":[
        "photography",
        "drugstore",
        "store"
    ],
    "wof:name":"Rite Aid",
    "wof:placetype":"venue"
},
  "geometry": {"coordinates":[-74.88629899999999,40.048302],"type":"Point"}
}