{
  "type": "Feature",
  "properties": {
    "iso:country":"US",
    "sg:address":"26 Rose Ln",
    "sg:city":"Villas",
    "sg:classifiers":[
        {
            "category":"Building & Trades",
            "subcategory":"Construction",
            "type":"Services"
        }
    ],
    "sg:phone":"+1 609 889 5197",
    "sg:postcode":"08251",
    "sg:province":"NJ",
    "sg:tags":[
        "contractor"
    ],
    "wof:name":"3 Brothers Masonary Cnstr",
    "wof:placetype":"venue"
},
  "geometry": {"coordinates":[-74.938457,39.02189],"type":"Point"}
}