{
  "type": "Feature",
  "properties": {
    "iso:country":"US",
    "sg:address":"166 Village Dr",
    "sg:city":"Barnegat",
    "sg:classifiers":[
        {
            "category":"Communications",
            "subcategory":"Film & Video Production",
            "type":"Services"
        }
    ],
    "sg:phone":"+1   ",
    "sg:postcode":"08005",
    "sg:province":"NJ",
    "sg:tags":[
        "motion"
    ],
    "wof:name":"Eerie Creek Productions",
    "wof:placetype":"venue"
},
  "geometry": {"coordinates":[-74.241848,39.744963],"type":"Point"}
}