{
  "type": "Feature",
  "properties": {
    "iso:country":"US",
    "sg:address":"20 W Main St",
    "sg:city":"Ramsey",
    "sg:classifiers":[
        {
            "category":"Restaurant",
            "type":"Food & Drink"
        }
    ],
    "sg:menulink":"http://www.allmenus.com/nj/ramsey/24900-ramsey-gourmet/menu/",
    "sg:phone":"+1 201 825 4141",
    "sg:postcode":"07446",
    "sg:province":"NJ",
    "sg:tags":[
        "wrap",
        "american",
        "sandwich"
    ],
    "wof:name":"Ramsey Gourmet",
    "wof:placetype":"venue"
},
  "geometry": {"coordinates":[-74.14287,41.057365],"type":"Point"}
}