{
  "type": "Feature",
  "properties": {
    "addr:full":"15 Indian Ter Sparta NJ 07871",
    "addr:housenumber":"15",
    "addr:postcode":"07871",
    "addr:street":"Indian Ter",
    "iso:country":"US",
    "sg:address":"15 Indian Ter",
    "sg:city":"Sparta",
    "sg:classifiers":[
        {
            "category":"Wholesale",
            "subcategory":"Construction Materials",
            "type":"Manufacturing & Wholesale Goods"
        }
    ],
    "sg:phone":"+1 973 875 9828",
    "sg:postcode":"07871",
    "sg:province":"NJ",
    "wof:name":"Wizard Interior Cleaning",
    "wof:placetype":"venue"
},
  "geometry": {"coordinates":[-74.643901,41.035068],"type":"Point"}
}