{
  "type": "Feature",
  "properties": {
    "addr:full":"32 Reynolds Dr Eatontown NJ 07724",
    "addr:housenumber":"32",
    "addr:postcode":"07724",
    "addr:street":"Reynolds Dr",
    "iso:country":"US",
    "sg:address":"32 Reynolds Dr",
    "sg:city":"Eatontown",
    "sg:classifiers":[
        {
            "category":"Professional",
            "subcategory":"Management & Consulting",
            "type":"Services"
        }
    ],
    "sg:phone":"+1   ",
    "sg:postcode":"07724",
    "sg:province":"NJ",
    "sg:tags":[
        "business"
    ],
    "wof:name":"Quinn Consulting Services Inc",
    "wof:placetype":"venue"
},
  "geometry": {"coordinates":[-74.041651,40.300261],"type":"Point"}
}