{
  "type": "Feature",
  "properties": {
    "addr:full":"4 Manhatten Dr Burlington NJ 08016",
    "addr:housenumber":"4",
    "addr:postcode":"08016",
    "addr:street":"Manhatten Dr",
    "iso:country":"US",
    "sg:address":"4 Manhatten Dr",
    "sg:city":"Burlington",
    "sg:classifiers":[
        {
            "category":"Farming",
            "subcategory":"Farm",
            "type":"Manufacturing & Wholesale Goods"
        }
    ],
    "sg:phone":"+1 609 747 9542",
    "sg:postcode":"08016",
    "sg:province":"NJ",
    "sg:tags":[
        "crop",
        "general"
    ],
    "wof:name":"Balford Farms",
    "wof:placetype":"venue"
},
  "geometry": {"coordinates":[-74.845185,40.034447],"type":"Point"}
}