{
  "type": "Feature",
  "properties": {
    "iso:country":"US",
    "sg:address":"3 Julie Ct",
    "sg:city":"Somerset",
    "sg:classifiers":[
        {
            "category":"Professional",
            "subcategory":"Computer Services",
            "type":"Services"
        }
    ],
    "sg:phone":"+1 732 398 0196",
    "sg:postcode":"08873",
    "sg:province":"NJ",
    "sg:tags":[
        "programing",
        "custom"
    ],
    "wof:name":"Catalyst Systems Inc",
    "wof:placetype":"venue"
},
  "geometry": {"coordinates":[-74.533117,40.449125],"type":"Point"}
}