{
  "type": "Feature",
  "properties": {
    "addr:full":"238 Stuyvesant Ave Lyndhurst NJ 07071",
    "addr:housenumber":"238",
    "addr:postcode":"07071",
    "addr:street":"Stuyvesant Ave",
    "iso:country":"US",
    "sg:address":"238 Stuyvesant Ave",
    "sg:city":"Lyndhurst",
    "sg:classifiers":[
        {
            "category":"Organizations",
            "subcategory":"Professional Association",
            "type":"Services"
        },
        {
            "category":"Organizations",
            "subcategory":"Community Association",
            "type":"Services"
        }
    ],
    "sg:phone":"+1 201 935 6011",
    "sg:postcode":"07071",
    "sg:province":"NJ",
    "wof:name":"Associazione Nazionale MA",
    "wof:placetype":"venue"
},
  "geometry": {"coordinates":[-74.125343,40.815078],"type":"Point"}
}