{
  "type": "Feature",
  "properties": {
    "addr:full":"199 Ogden Rd Wenonah NJ 08090",
    "addr:housenumber":"199",
    "addr:postcode":"08090",
    "addr:street":"Ogden Rd",
    "iso:country":"US",
    "sg:address":"199 Ogden Rd",
    "sg:city":"Wenonah",
    "sg:classifiers":[
        {
            "category":"Personal",
            "subcategory":"Beauty Salon",
            "type":"Services"
        }
    ],
    "sg:phone":"+1 856 468 3518",
    "sg:postcode":"08090",
    "sg:province":"NJ",
    "sg:tags":[
        "shop",
        "physical",
        "fitness"
    ],
    "wof:name":"Warren Collins Salons",
    "wof:placetype":"venue"
},
  "geometry": {"coordinates":[-75.165538,39.80057],"type":"Point"}
}