{
  "type": "Feature",
  "properties": {
    "addr:full":"85 Chapel Rd Mahwah NJ 07430",
    "addr:housenumber":"85",
    "addr:postcode":"07430",
    "addr:street":"Chapel Rd",
    "iso:country":"US",
    "sg:address":"85 Chapel Rd",
    "sg:city":"Mahwah",
    "sg:classifiers":[
        {
            "category":"Organizations",
            "subcategory":"Religious Organization",
            "type":"Services"
        }
    ],
    "sg:phone":"+1 201 529 4558",
    "sg:postcode":"07430",
    "sg:province":"NJ",
    "sg:tags":[
        "church"
    ],
    "wof:name":"Fardale Chapel",
    "wof:placetype":"venue"
},
  "geometry": {"coordinates":[-74.17923,41.039995],"type":"Point"}
}