{
  "type": "Feature",
  "properties": {
    "iso:country":"US",
    "sg:address":"4 Angela Ct",
    "sg:city":"Monsey",
    "sg:classifiers":[
        {
            "category":"Professional",
            "subcategory":"Lawyer & Legal Services",
            "type":"Services"
        }
    ],
    "sg:phone":"+1   ",
    "sg:postcode":"10952",
    "sg:province":"NY",
    "wof:name":"Frank J Bonura",
    "wof:placetype":"venue"
},
  "geometry": {"coordinates":[-74.0718,41.076757],"type":"Point"}
}