{
  "type": "Feature",
  "properties": {
    "addr:full":"229 Dayton Ave Clifton NJ 07011",
    "addr:housenumber":"229",
    "addr:postcode":"07011",
    "addr:street":"Dayton Ave",
    "iso:country":"US",
    "sg:address":"229 Dayton Ave",
    "sg:city":"Clifton",
    "sg:classifiers":[
        {
            "category":"Health Services",
            "subcategory":"Chiropractor",
            "type":"Services"
        }
    ],
    "sg:phone":"+1 973 757 0607",
    "sg:postcode":"07011",
    "sg:province":"NJ",
    "wof:name":"Clifton Spine & Injury Center",
    "wof:placetype":"venue"
},
  "geometry": {"coordinates":[-74.12285,40.87543],"type":"Point"}
}