{
  "type": "Feature",
  "properties": {
    "iso:country":"US",
    "sg:address":"76 Prospect St",
    "sg:city":"Lodi",
    "sg:classifiers":[
        {
            "category":"Real Estate",
            "subcategory":"Real Estate Agent",
            "type":"Services"
        }
    ],
    "sg:phone":"+1 973 472 9326",
    "sg:postcode":"07644",
    "sg:province":"NJ",
    "sg:tags":[
        "appraiser"
    ],
    "wof:name":"Darr Realty",
    "wof:placetype":"venue"
},
  "geometry": {"coordinates":[-74.083595,40.873703],"type":"Point"}
}