{
  "type": "Feature",
  "properties": {
    "addr:full":"687 Woodport Rd Sparta NJ 07871",
    "addr:housenumber":"687",
    "addr:postcode":"07871",
    "addr:street":"Woodport Rd",
    "iso:country":"US",
    "sg:address":"687 Woodport Rd",
    "sg:city":"Sparta",
    "sg:classifiers":[
        {
            "category":"Professional",
            "subcategory":"Business Services",
            "type":"Services"
        }
    ],
    "sg:phone":"+1   ",
    "sg:postcode":"07871",
    "sg:province":"NJ",
    "sg:tags":[
        "good"
    ],
    "wof:name":"Nastasi Imports Inc",
    "wof:placetype":"venue"
},
  "geometry": {"coordinates":[-74.615494,41.005168],"type":"Point"}
}