{
  "type": "Feature",
  "properties": {
    "iso:country":"US",
    "sg:address":"125 Canhouse Rd",
    "sg:city":"Elmer",
    "sg:classifiers":[
        {
            "category":"Farming",
            "subcategory":"Farm & Veterinary Services",
            "type":"Manufacturing & Wholesale Goods"
        }
    ],
    "sg:phone":"+1 856 358 8528",
    "sg:postcode":"08318",
    "sg:province":"NJ",
    "sg:tags":[
        "corn",
        "ma",
        "crop"
    ],
    "wof:name":"George A Coleman",
    "wof:placetype":"venue"
},
  "geometry": {"coordinates":[-75.269212,39.562171],"type":"Point"}
}