{
  "type": "Feature",
  "properties": {
    "addr:full":"2392 Linden Pl Manasquan NJ 08736",
    "addr:housenumber":"2392",
    "addr:postcode":"08736",
    "addr:street":"Linden Pl",
    "iso:country":"US",
    "sg:address":"2392 Linden Pl",
    "sg:city":"Manasquan",
    "sg:classifiers":[
        {
            "category":"Building & Trades",
            "subcategory":"Construction",
            "type":"Services"
        }
    ],
    "sg:phone":"+1 732 528 5460",
    "sg:postcode":"08736",
    "sg:province":"NJ",
    "sg:tags":[
        "house"
    ],
    "wof:name":"Lukowitz Contracting",
    "wof:placetype":"venue"
},
  "geometry": {"coordinates":[-74.088526,40.123443],"type":"Point"}
}