{
  "type": "Feature",
  "properties": {
    "addr:full":"787 Woodland Ave Oradell NJ 07649",
    "addr:housenumber":"787",
    "addr:postcode":"07649",
    "addr:street":"Woodland Ave",
    "iso:country":"US",
    "sg:address":"787 Woodland Ave",
    "sg:city":"Oradell",
    "sg:classifiers":[
        {
            "category":"Professional",
            "subcategory":"Computer Services",
            "type":"Services"
        }
    ],
    "sg:phone":"+1 201 255 0037",
    "sg:postcode":"07649",
    "sg:province":"NJ",
    "sg:tags":[
        "design",
        "system",
        "network"
    ],
    "sg:website":"http://www.yellowspeed.com",
    "wof:name":"Yellowspeed",
    "wof:placetype":"venue"
},
  "geometry": {"coordinates":[-74.03776000000001,40.957714],"type":"Point"}
}