{
  "type": "Feature",
  "properties": {
    "addr:full":"96 N Sussex St Dover NJ 07801",
    "addr:housenumber":"96",
    "addr:postcode":"07801",
    "addr:street":"N Sussex St",
    "iso:country":"US",
    "sg:address":"96 N Sussex St",
    "sg:city":"Dover",
    "sg:classifiers":[
        {
            "category":"Organizations",
            "subcategory":"Religious Organization",
            "type":"Services"
        }
    ],
    "sg:phone":"+1 973 366 3681",
    "sg:postcode":"07801",
    "sg:province":"NJ",
    "sg:tags":[
        "church"
    ],
    "wof:name":"Grace United Methodist",
    "wof:placetype":"venue"
},
  "geometry": {"coordinates":[-74.55909699999999,40.888112],"type":"Point"}
}