{
  "type": "Feature",
  "properties": {
    "addr:full":"321 Commercial Ave Palisades Park NJ 07650",
    "addr:housenumber":"321",
    "addr:postcode":"07650",
    "addr:street":"Commercial Ave",
    "iso:country":"US",
    "sg:address":"321 Commercial Ave",
    "sg:city":"Palisades Park",
    "sg:classifiers":[
        {
            "category":"Professional",
            "subcategory":"Lawyer & Legal Services",
            "type":"Services"
        }
    ],
    "sg:phone":"+1 201 894 5812",
    "sg:postcode":"07650",
    "sg:province":"NJ",
    "wof:name":"Garber Klein & Nelson PC",
    "wof:placetype":"venue"
},
  "geometry": {"coordinates":[-74.00235600000001,40.851828],"type":"Point"}
}