{
  "type": "Feature",
  "properties": {
    "iso:country":"US",
    "sg:address":"1985 Springfield Ave",
    "sg:city":"Maplewood",
    "sg:classifiers":[
        {
            "category":"Health Services",
            "subcategory":"Doctor",
            "type":"Services"
        }
    ],
    "sg:phone":"+1 973 763 5010",
    "sg:postcode":"07040",
    "sg:province":"NJ",
    "sg:tags":[
        "physician",
        "surgeon"
    ],
    "wof:name":"Wallen & Jacobson",
    "wof:placetype":"venue"
},
  "geometry": {"coordinates":[-74.27414400000001,40.720036],"type":"Point"}
}