{
  "type": "Feature",
  "properties": {
    "iso:country":"US",
    "sg:address":"10 Broad St",
    "sg:city":"Red Bank",
    "sg:classifiers":[
        {
            "category":"Real Estate",
            "subcategory":"Architect",
            "type":"Services"
        }
    ],
    "sg:phone":"+1   ",
    "sg:postcode":"07701",
    "sg:province":"NJ",
    "sg:tags":[
        "architectural"
    ],
    "wof:name":"Gassert Design Consultant",
    "wof:placetype":"venue"
},
  "geometry": {"coordinates":[-74.065438,40.351274],"type":"Point"}
}