{
  "type": "Feature",
  "properties": {
    "iso:country":"US",
    "sg:address":"260 Wawayanda Rd",
    "sg:city":"Highland Lakes",
    "sg:classifiers":[
        {
            "category":"Professional",
            "subcategory":"Business Services",
            "type":"Services"
        }
    ],
    "sg:phone":"+1 973 764 6905",
    "sg:postcode":"07422",
    "sg:province":"NJ",
    "sg:tags":[
        "specialty",
        "mfg"
    ],
    "wof:name":"Sign Design",
    "wof:placetype":"venue"
},
  "geometry": {"coordinates":[-74.472189,41.173095],"type":"Point"}
}