{
  "type": "Feature",
  "properties": {
    "addr:full":"18 Christopher Rd Voorhees NJ 08043",
    "addr:housenumber":"18",
    "addr:postcode":"08043",
    "addr:street":"Christopher Rd",
    "iso:country":"US",
    "sg:address":"18 Christopher Rd",
    "sg:city":"Voorhees",
    "sg:classifiers":[
        {
            "category":"Wholesale",
            "subcategory":"Machinery & Supplies",
            "type":"Manufacturing & Wholesale Goods"
        }
    ],
    "sg:phone":"+1 856 424 8542",
    "sg:postcode":"08043",
    "sg:province":"NJ",
    "sg:tags":[
        "equipment",
        "establishment"
    ],
    "wof:name":"Giadon Corp",
    "wof:placetype":"venue"
},
  "geometry": {"coordinates":[-74.92878899999999,39.868822],"type":"Point"}
}