{
  "type": "Feature",
  "properties": {
    "iso:country":"US",
    "sg:address":"539 Roseville Ave",
    "sg:city":"Newark",
    "sg:classifiers":[
        {
            "category":"Organizations",
            "subcategory":"Religious Organization",
            "type":"Services"
        }
    ],
    "sg:phone":"+1 973 485 1003",
    "sg:postcode":"07107",
    "sg:province":"NJ",
    "sg:tags":[
        "clergy"
    ],
    "wof:name":"R P Derricotte",
    "wof:placetype":"venue"
},
  "geometry": {"coordinates":[-74.183635,40.769339],"type":"Point"}
}