{
  "type": "Feature",
  "properties": {
    "iso:country":"US",
    "sg:address":"2177 Millburn Ave",
    "sg:city":"Maplewood",
    "sg:classifiers":[
        {
            "category":"Retail",
            "subcategory":"Auto Repair",
            "type":"Services"
        }
    ],
    "sg:phone":"+1 973 762 2277",
    "sg:postcode":"07040",
    "sg:province":"NJ",
    "sg:tags":[
        "repairing",
        "automobile"
    ],
    "wof:name":"Euromotive Inc",
    "wof:placetype":"venue"
},
  "geometry": {"coordinates":[-74.284406,40.72255],"type":"Point"}
}