{
  "type": "Feature",
  "properties": {
    "addr:full":"36 Webster Ave Summit NJ 07901",
    "addr:housenumber":"36",
    "addr:postcode":"07901",
    "addr:street":"Webster Ave",
    "iso:country":"US",
    "sg:address":"36 Webster Ave",
    "sg:city":"Summit",
    "sg:classifiers":[
        {
            "category":"Real Estate",
            "subcategory":"Surveying",
            "type":"Services"
        }
    ],
    "sg:phone":"+1 908 522 9419",
    "sg:postcode":"07901",
    "sg:province":"NJ",
    "wof:name":"Blum Surveying Mapng",
    "wof:placetype":"venue"
},
  "geometry": {"coordinates":[-74.372698,40.724198],"type":"Point"}
}