{
  "type": "Feature",
  "properties": {
    "addr:full":"772 Prospect Ave Keyport NJ 07735",
    "addr:housenumber":"772",
    "addr:postcode":"07735",
    "addr:street":"Prospect Ave",
    "iso:country":"US",
    "sg:address":"772 Prospect Ave",
    "sg:city":"Keyport",
    "sg:classifiers":[
        {
            "category":"Building & Trades",
            "subcategory":"Plumbing",
            "type":"Services"
        }
    ],
    "sg:phone":"+1 732 290 7776",
    "sg:postcode":"07735",
    "sg:province":"NJ",
    "sg:tags":[
        "contractor"
    ],
    "wof:name":"Town & Country Plumbing & Htg",
    "wof:placetype":"venue"
},
  "geometry": {"coordinates":[-74.216403,40.441296],"type":"Point"}
}