{
  "type": "Feature",
  "properties": {
    "iso:country":"US",
    "sg:address":"182 Merseles St",
    "sg:city":"Jersey City",
    "sg:classifiers":[
        {
            "category":"Education",
            "subcategory":"School",
            "type":"Public Place"
        }
    ],
    "sg:phone":"+1 201 714 4300",
    "sg:postcode":"07302",
    "sg:province":"NJ",
    "wof:name":"Elementary School 5",
    "wof:placetype":"venue"
},
  "geometry": {"coordinates":[-74.052543,40.724724],"type":"Point"}
}