{
  "type": "Feature",
  "properties": {
    "addr:full":"712 Wood St Vineland NJ 08360",
    "addr:housenumber":"712",
    "addr:postcode":"08360",
    "addr:street":"Wood St",
    "iso:country":"US",
    "sg:address":"712 Wood St",
    "sg:city":"Vineland",
    "sg:classifiers":[
        {
            "category":"Real Estate",
            "subcategory":"Real Estate Agent",
            "type":"Services"
        }
    ],
    "sg:phone":"+1 856 696 8200",
    "sg:postcode":"08360",
    "sg:province":"NJ",
    "wof:name":"Barry B Levin",
    "wof:placetype":"venue"
},
  "geometry": {"coordinates":[-75.01884099999999,39.486986],"type":"Point"}
}