{
  "type": "Feature",
  "properties": {
    "iso:country":"US",
    "sg:address":"19 Lincoln Ave",
    "sg:city":"Piscataway",
    "sg:classifiers":[
        {
            "category":"Health Services",
            "subcategory":"Health Practitioner",
            "type":"Services"
        }
    ],
    "sg:phone":"+1   ",
    "sg:postcode":"08854",
    "sg:province":"NJ",
    "wof:name":"Jarowicz Richard J Psy D",
    "wof:placetype":"venue"
},
  "geometry": {"coordinates":[-74.49042,40.53035],"type":"Point"}
}