{
  "type": "Feature",
  "properties": {
    "addr:full":"9 Jillian Ct Jamesburg NJ 08831",
    "addr:housenumber":"9",
    "addr:postcode":"08831",
    "addr:street":"Jillian Ct",
    "iso:country":"US",
    "sg:address":"9 Jillian Ct",
    "sg:city":"Jamesburg",
    "sg:classifiers":[
        {
            "category":"Wholesale",
            "subcategory":"Furniture",
            "type":"Manufacturing & Wholesale Goods"
        }
    ],
    "sg:phone":"+1 732 723 0984",
    "sg:postcode":"08831",
    "sg:province":"NJ",
    "wof:name":"K & K Enterprises",
    "wof:placetype":"venue"
},
  "geometry": {"coordinates":[-74.386894,40.366063],"type":"Point"}
}