{
  "type": "Feature",
  "properties": {
    "addr:full":"625 3rd St Newark NJ 07107",
    "addr:housenumber":"625",
    "addr:postcode":"07107",
    "addr:street":"3Rd St",
    "iso:country":"US",
    "sg:address":"625 3rd St",
    "sg:city":"Newark",
    "sg:classifiers":[
        {
            "category":"Manufacturing",
            "subcategory":"Metals",
            "type":"Manufacturing & Wholesale Goods"
        }
    ],
    "sg:phone":"+1 973 485 3630",
    "sg:postcode":"07107",
    "sg:province":"NJ",
    "sg:tags":[
        "hardware",
        "mfg"
    ],
    "sg:website":"www.charlesegreen.com",
    "wof:name":"Charles E Green & Son Inc",
    "wof:placetype":"venue"
},
  "geometry": {"coordinates":[-74.179027,40.767791],"type":"Point"}
}