{
  "type": "Feature",
  "properties": {
    "iso:country":"US",
    "sg:address":"424 N Black Horse Pike",
    "sg:city":"Runnemede",
    "sg:classifiers":[
        {
            "category":"Real Estate",
            "subcategory":"Real Estate Operator",
            "type":"Services"
        }
    ],
    "sg:phone":"+1 856 939 9271",
    "sg:postcode":"08078",
    "sg:province":"NJ",
    "sg:tags":[
        "apartment"
    ],
    "wof:name":"K D C Associates",
    "wof:placetype":"venue"
},
  "geometry": {"coordinates":[-75.073964,39.852725],"type":"Point"}
}