{
  "type": "Feature",
  "properties": {
    "iso:country":"US",
    "sg:address":"170 Hillman Ave",
    "sg:city":"Glen Rock",
    "sg:classifiers":[
        {
            "category":"Manufacturing",
            "subcategory":"Textiles",
            "type":"Manufacturing & Wholesale Goods"
        }
    ],
    "sg:phone":"+1 201 447 9782",
    "sg:postcode":"07452",
    "sg:province":"NJ",
    "sg:tags":[
        "fabric",
        "mfg"
    ],
    "wof:name":"JMS Textile Creations Inc",
    "wof:placetype":"venue"
},
  "geometry": {"coordinates":[-74.110636,40.953017],"type":"Point"}
}