{
  "type": "Feature",
  "properties": {
    "iso:country":"US",
    "sg:address":"317 Harrington Ave",
    "sg:city":"Closter",
    "sg:classifiers":[
        {
            "category":"Wholesale",
            "subcategory":"Stationery",
            "type":"Manufacturing & Wholesale Goods"
        }
    ],
    "sg:phone":"+1 201 768 8411",
    "sg:postcode":"07624",
    "sg:province":"NJ",
    "sg:tags":[
        "box",
        "fiber"
    ],
    "wof:name":"Sharon Paper Co",
    "wof:placetype":"venue"
},
  "geometry": {"coordinates":[-73.96395,40.974466],"type":"Point"}
}