{
  "type": "Feature",
  "properties": {
    "iso:country":"US",
    "sg:address":"320 W State St",
    "sg:city":"Trenton",
    "sg:classifiers":[
        {
            "category":"Social Services",
            "type":"Services"
        }
    ],
    "sg:phone":"+1 609 394 0401",
    "sg:postcode":"08618",
    "sg:province":"NJ",
    "wof:name":"Counsling Edcatn Fmly Dynamics",
    "wof:placetype":"venue"
},
  "geometry": {"coordinates":[-74.775351,40.22286],"type":"Point"}
}