{
  "type": "Feature",
  "properties": {
    "iso:country":"US",
    "sg:address":"2211 Millburn Ave",
    "sg:city":"Maplewood",
    "sg:classifiers":[
        {
            "category":"Professional",
            "type":"Services"
        }
    ],
    "sg:phone":"+1 973 762 1435",
    "sg:postcode":"07040",
    "sg:province":"NJ",
    "sg:tags":[
        "establishment"
    ],
    "wof:name":"DCH Essex Inc",
    "wof:placetype":"venue"
},
  "geometry": {"coordinates":[-74.285158,40.722677],"type":"Point"}
}