{
  "type": "Feature",
  "properties": {
    "iso:country":"US",
    "sg:address":"10 S Grove Ave",
    "sg:city":"National Park",
    "sg:classifiers":[
        {
            "category":"Professional",
            "type":"Services"
        }
    ],
    "sg:phone":"+1 856 848 4443",
    "sg:postcode":"08063",
    "sg:province":"NJ",
    "wof:name":"Altrade Professional Svc",
    "wof:placetype":"venue"
},
  "geometry": {"coordinates":[-75.18012,39.865099],"type":"Point"}
}