{
  "type": "Feature",
  "properties": {
    "iso:country":"US",
    "sg:address":"Sharp Plaza",
    "sg:city":"Mahwah",
    "sg:classifiers":[
        {
            "category":"Manufacturing",
            "subcategory":"Electronics",
            "type":"Manufacturing & Wholesale Goods"
        }
    ],
    "sg:phone":"+1 201 529 8200",
    "sg:province":"NJ",
    "sg:website":"http://www.sharpusa.com",
    "wof:name":"Sharp Electronics",
    "wof:placetype":"venue"
},
  "geometry": {"coordinates":[-74.185895,41.083159],"type":"Point"}
}