{
  "type": "Feature",
  "properties": {
    "addr:full":"32 S Martine Ave Fanwood NJ 07023",
    "addr:housenumber":"32",
    "addr:postcode":"07023",
    "addr:street":"S Martine Ave",
    "iso:country":"US",
    "sg:address":"32 S Martine Ave",
    "sg:city":"Fanwood",
    "sg:classifiers":[
        {
            "category":"Food & Beverages",
            "subcategory":"Bakery",
            "type":"Retail Goods"
        }
    ],
    "sg:phone":"+1 908 322 4200",
    "sg:postcode":"07023",
    "sg:province":"NJ",
    "sg:tags":[
        "bagel"
    ],
    "wof:name":"Fanwood Bagels & Deli",
    "wof:placetype":"venue"
},
  "geometry": {"coordinates":[-74.38258399999999,40.639956],"type":"Point"}
}