{
  "type": "Feature",
  "properties": {
    "addr:full":"522 S Plainfield Ave South Plainfield NJ 07080",
    "addr:housenumber":"522",
    "addr:postcode":"07080",
    "addr:street":"S Plainfield Ave",
    "iso:country":"US",
    "sg:address":"522 S Plainfield Ave",
    "sg:city":"South Plainfield",
    "sg:classifiers":[
        {
            "category":"Wholesale",
            "subcategory":"Durable Goods & Equipment",
            "type":"Manufacturing & Wholesale Goods"
        }
    ],
    "sg:phone":"+1 908 486 0492",
    "sg:postcode":"07080",
    "sg:province":"NJ",
    "sg:tags":[
        "fire",
        "extinguisher"
    ],
    "wof:name":"Linden Fire Protection Inc",
    "wof:placetype":"venue"
},
  "geometry": {"coordinates":[-74.39598700000001,40.586249],"type":"Point"}
}