{
  "type": "Feature",
  "properties": {
    "iso:country":"US",
    "sg:address":"42 Old Farm Rd",
    "sg:city":"Basking Ridge",
    "sg:classifiers":[
        {
            "category":"Retail",
            "subcategory":"Portrait Studio",
            "type":"Services"
        }
    ],
    "sg:phone":"+1   ",
    "sg:postcode":"07920",
    "sg:province":"NJ",
    "sg:tags":[
        "photo"
    ],
    "wof:name":"Wls Photography",
    "wof:placetype":"venue"
},
  "geometry": {"coordinates":[-74.558843,40.73022],"type":"Point"}
}