{
  "type": "Feature",
  "properties": {
    "addr:full":"703 32nd St Union City NJ 07087",
    "addr:housenumber":"703",
    "addr:postcode":"07087",
    "addr:street":"32Nd St",
    "iso:country":"US",
    "sg:address":"703 32nd St",
    "sg:city":"Union City",
    "sg:classifiers":[
        {
            "category":"Restaurant",
            "type":"Food & Drink"
        }
    ],
    "sg:phone":"+1 201 867 1934",
    "sg:postcode":"07087",
    "sg:province":"NJ",
    "sg:tags":[
        "eating",
        "italian"
    ],
    "wof:name":"Casa Di Napoli",
    "wof:placetype":"venue"
},
  "geometry": {"coordinates":[-74.030582,40.773744],"type":"Point"}
}