{
  "type": "Feature",
  "properties": {
    "addr:full":"2401 Federal St Camden NJ 08105",
    "addr:housenumber":"2401",
    "addr:postcode":"08105",
    "addr:street":"Federal St",
    "iso:country":"US",
    "sg:address":"2401 Federal St",
    "sg:city":"Camden",
    "sg:classifiers":[
        {
            "category":"Restaurant",
            "type":"Food & Drink"
        }
    ],
    "sg:phone":"+1 856 225 0100",
    "sg:postcode":"08105",
    "sg:province":"NJ",
    "sg:website":"www.crownfriedchicken.com",
    "wof:name":"Crown Fried Chicken",
    "wof:placetype":"venue"
},
  "geometry": {"coordinates":[-75.09050000000001,39.945999],"type":"Point"}
}