{
  "type": "Feature",
  "properties": {
    "iso:country":"US",
    "sg:address":"248 S Lagoon Rd",
    "sg:city":"Lavallette",
    "sg:classifiers":[
        {
            "category":"Retail",
            "subcategory":"Animal Services",
            "type":"Services"
        }
    ],
    "sg:phone":"+1 732 830 0750",
    "sg:postcode":"08735",
    "sg:province":"NJ",
    "wof:name":"Mbf Dog Training",
    "wof:placetype":"venue"
},
  "geometry": {"coordinates":[-74.06545,39.996523],"type":"Point"}
}