{
  "type": "Feature",
  "properties": {
    "iso:country":"US",
    "sg:address":"211 S Main St",
    "sg:city":"Cape May Court House",
    "sg:classifiers":[
        {
            "category":"Health Services",
            "subcategory":"Doctor",
            "type":"Services"
        }
    ],
    "sg:phone":"+1 609 463 1577",
    "sg:postcode":"08210",
    "sg:province":"NJ",
    "wof:name":"Hackford Robert MD",
    "wof:placetype":"venue"
},
  "geometry": {"coordinates":[-74.82514999999999,39.080012],"type":"Point"}
}