{
  "type": "Feature",
  "properties": {
    "iso:country":"US",
    "sg:address":"134 Lamar Ave",
    "sg:city":"Edison",
    "sg:classifiers":[
        {
            "category":"Building & Trades",
            "subcategory":"Construction",
            "type":"Services"
        }
    ],
    "sg:phone":"+1 732 549 4548",
    "sg:postcode":"08820",
    "sg:province":"NJ",
    "sg:tags":[
        "hanging",
        "contractor"
    ],
    "wof:name":"Heros Painting",
    "wof:placetype":"venue"
},
  "geometry": {"coordinates":[-74.364761,40.582509],"type":"Point"}
}