{
  "type": "Feature",
  "properties": {
    "iso:country":"US",
    "sg:address":"37 South St",
    "sg:city":"New Providence",
    "sg:classifiers":[
        {
            "category":"Retail",
            "subcategory":"Laundry & Dry Cleaning",
            "type":"Services"
        }
    ],
    "sg:phone":"+1 908 464 5784",
    "sg:postcode":"07974",
    "sg:province":"NJ",
    "sg:tags":[
        "cleaner",
        "plant",
        "drycleaning"
    ],
    "wof:name":"Boro Cleaners Inc",
    "wof:placetype":"venue"
},
  "geometry": {"coordinates":[-74.40570099999999,40.704102],"type":"Point"}
}