{
  "type": "Feature",
  "properties": {
    "iso:country":"US",
    "sg:address":"336 Main St",
    "sg:city":"Hackensack",
    "sg:classifiers":[
        {
            "category":"Manufacturing",
            "subcategory":"Signs",
            "type":"Manufacturing & Wholesale Goods"
        },
        {
            "category":"Shopping",
            "type":"Retail Goods"
        }
    ],
    "sg:phone":"+1 201 883 1499",
    "sg:postcode":"07601",
    "sg:province":"NJ",
    "sg:tags":[
        "specialty",
        "merchandise",
        "mfg"
    ],
    "wof:name":"Signworks",
    "wof:placetype":"venue"
},
  "geometry": {"coordinates":[-74.04001599999999,40.888955],"type":"Point"}
}