{
  "type": "Feature",
  "properties": {
    "addr:full":"108 North St Madison NJ 07940",
    "addr:housenumber":"108",
    "addr:postcode":"07940",
    "addr:street":"North St",
    "iso:country":"US",
    "sg:address":"108 North St",
    "sg:city":"Madison",
    "sg:classifiers":[
        {
            "category":"Building & Trades",
            "subcategory":"Construction",
            "type":"Services"
        }
    ],
    "sg:phone":"+1 973 377 8666",
    "sg:postcode":"07940",
    "sg:province":"NJ",
    "sg:tags":[
        "heavy",
        "cargo",
        "handler",
        "marine"
    ],
    "wof:name":"Floating Docks Corp",
    "wof:placetype":"venue"
},
  "geometry": {"coordinates":[-74.41379499999999,40.769963],"type":"Point"}
}