{
  "type": "Feature",
  "properties": {
    "iso:country":"US",
    "sg:address":"880 Garrison Ave",
    "sg:city":"Teaneck",
    "sg:classifiers":[
        {
            "category":"Health Services",
            "subcategory":"Doctor",
            "type":"Services"
        }
    ],
    "sg:phone":"+1 201 836 3616",
    "sg:postcode":"07666",
    "sg:province":"NJ",
    "sg:tags":[
        "physician",
        "surgeon"
    ],
    "wof:name":"Rabinowitz & Rabinowitz",
    "wof:placetype":"venue"
},
  "geometry": {"coordinates":[-74.020933,40.89198],"type":"Point"}
}