{
  "type": "Feature",
  "properties": {
    "iso:country":"US",
    "sg:address":"261 Buffalo Ave",
    "sg:city":"Paterson",
    "sg:classifiers":[
        {
            "category":"Professional",
            "type":"Services"
        }
    ],
    "sg:phone":"+1 973 523 8009",
    "sg:postcode":"07503",
    "sg:province":"NJ",
    "wof:name":"Buffalo Office Svc",
    "wof:placetype":"venue"
},
  "geometry": {"coordinates":[-74.14909,40.893801],"type":"Point"}
}