{
  "type": "Feature",
  "properties": {
    "iso:country":"US",
    "sg:address":"13 Old Bilby Rd",
    "sg:city":"Hackettstown",
    "sg:classifiers":[
        {
            "category":"Building & Trades",
            "subcategory":"Construction",
            "type":"Services"
        }
    ],
    "sg:phone":"+1 908 850 8615",
    "sg:postcode":"07840",
    "sg:province":"NJ",
    "sg:tags":[
        "well",
        "pump",
        "installation"
    ],
    "wof:name":"A & B Well Pump Service",
    "wof:placetype":"venue"
},
  "geometry": {"coordinates":[-74.816086,40.870038],"type":"Point"}
}