{
  "type": "Feature",
  "properties": {
    "addr:full":"21 Old Queens Blvd Englishtown NJ 07726",
    "addr:housenumber":"21",
    "addr:postcode":"07726",
    "addr:street":"Old Queens Blvd",
    "iso:country":"US",
    "sg:address":"21 Old Queens Blvd",
    "sg:city":"Englishtown",
    "sg:classifiers":[
        {
            "category":"Travel",
            "subcategory":"Campground",
            "type":"Entertainment"
        }
    ],
    "sg:phone":"+1   ",
    "sg:postcode":"07726",
    "sg:province":"NJ",
    "sg:tags":[
        "camp"
    ],
    "wof:name":"Trade Winds Lake Camp Inc",
    "wof:placetype":"venue"
},
  "geometry": {"coordinates":[-74.34011700000001,40.306539],"type":"Point"}
}