{
  "type": "Feature",
  "properties": {
    "iso:country":"US",
    "sg:address":"1130 Ship Ave",
    "sg:city":"Beachwood",
    "sg:classifiers":[
        {
            "category":"Wholesale",
            "subcategory":"Non-durable Goods",
            "type":"Manufacturing & Wholesale Goods"
        }
    ],
    "sg:phone":"+1 732 240 3131",
    "sg:postcode":"08722",
    "sg:province":"NJ",
    "sg:tags":[
        "supply"
    ],
    "sg:website":"www.candlefactoryproducts.com",
    "wof:name":"Candle Factory Products",
    "wof:placetype":"venue"
},
  "geometry": {"coordinates":[-74.20478,39.92641],"type":"Point"}
}