{
  "type": "Feature",
  "properties": {
    "iso:country":"US",
    "sg:address":"110 Bay Ave",
    "sg:city":"Forked River",
    "sg:classifiers":[
        {
            "category":"Manufacturing",
            "subcategory":"Signs",
            "type":"Manufacturing & Wholesale Goods"
        }
    ],
    "sg:phone":"+1 609 971 9699",
    "sg:postcode":"08731",
    "sg:province":"NJ",
    "sg:tags":[
        "body",
        "auto",
        "specialty",
        "mfg"
    ],
    "wof:name":"Debis Signs",
    "wof:placetype":"venue"
},
  "geometry": {"coordinates":[-74.19035599999999,39.834883],"type":"Point"}
}