{
  "type": "Feature",
  "properties": {
    "iso:country":"US",
    "sg:address":"1058 Ave C",
    "sg:city":"Bayonne",
    "sg:classifiers":[
        {
            "category":"Retail",
            "subcategory":"Self-service Laundry",
            "type":"Services"
        }
    ],
    "sg:phone":"+1 201 436 8828",
    "sg:postcode":"07002",
    "sg:province":"NJ",
    "sg:tags":[
        "coin"
    ],
    "wof:name":"Tonys Laudromat",
    "wof:placetype":"venue"
},
  "geometry": {"coordinates":[-74.104658,40.683915],"type":"Point"}
}