{
  "type": "Feature",
  "properties": {
    "iso:country":"US",
    "sg:address":"88 East Ave",
    "sg:city":"Bridgeton",
    "sg:classifiers":[
        {
            "category":"Organizations",
            "subcategory":"Community Association",
            "type":"Services"
        }
    ],
    "sg:phone":"+1 856 451 9877",
    "sg:postcode":"08302",
    "sg:province":"NJ",
    "sg:tags":[
        "club"
    ],
    "wof:name":"Bridgeton Independent Club",
    "wof:placetype":"venue"
},
  "geometry": {"coordinates":[-75.225561,39.430623],"type":"Point"}
}