{
  "type": "Feature",
  "properties": {
    "addr:full":"2051 Briggs Rd Mount Laurel NJ 08054",
    "addr:housenumber":"2051",
    "addr:postcode":"08054",
    "addr:street":"Briggs Rd",
    "iso:country":"US",
    "sg:address":"2051 Briggs Rd",
    "sg:city":"Mount Laurel",
    "sg:classifiers":[
        {
            "category":"Health Services",
            "subcategory":"Doctor",
            "type":"Services"
        }
    ],
    "sg:phone":"+1 856 234 3332",
    "sg:postcode":"08054",
    "sg:province":"NJ",
    "sg:tags":[
        "medical"
    ],
    "wof:name":"Cha SE Do MD Fscai",
    "wof:placetype":"venue"
},
  "geometry": {"coordinates":[-74.894825,39.960617],"type":"Point"}
}