{
  "type": "Feature",
  "properties": {
    "addr:full":"13 Maple Ave Mendham NJ 07945",
    "addr:housenumber":"13",
    "addr:postcode":"07945",
    "addr:street":"Maple Ave",
    "iso:country":"US",
    "sg:address":"13 Maple Ave",
    "sg:city":"Mendham",
    "sg:classifiers":[
        {
            "category":"Manufacturing",
            "subcategory":"Tools & Machinery",
            "type":"Manufacturing & Wholesale Goods"
        }
    ],
    "sg:phone":"+1 973 714 7737",
    "sg:postcode":"07945",
    "sg:province":"NJ",
    "sg:tags":[
        "equipment",
        "peripheral",
        "computer",
        "mfg"
    ],
    "wof:name":"Gw Monitors & Pcs",
    "wof:placetype":"venue"
},
  "geometry": {"coordinates":[-74.609722,40.778662],"type":"Point"}
}