{
  "type": "Feature",
  "properties": {
    "addr:full":"13 Cypress Ave Verona NJ 07044",
    "addr:housenumber":"13",
    "addr:postcode":"07044",
    "addr:street":"Cypress Ave",
    "iso:country":"US",
    "sg:address":"13 Cypress Ave",
    "sg:city":"Verona",
    "sg:classifiers":[
        {
            "category":"Building & Trades",
            "subcategory":"Plumbing",
            "type":"Services"
        }
    ],
    "sg:phone":"+1 973 239 1661",
    "sg:postcode":"07044",
    "sg:province":"NJ",
    "wof:name":"Garthwaite Contractors Plumbing & Heating",
    "wof:placetype":"venue"
},
  "geometry": {"coordinates":[-74.242302,40.839699],"type":"Point"}
}