{
  "type": "Feature",
  "properties": {
    "iso:country":"US",
    "sg:address":"170 Colonial Ct",
    "sg:city":"Galloway",
    "sg:classifiers":[
        {
            "category":"Real Estate",
            "subcategory":"Real Estate Operator",
            "type":"Services"
        }
    ],
    "sg:phone":"+1 609 652 5535",
    "sg:postcode":"08205",
    "sg:province":"NJ",
    "sg:tags":[
        "condominium"
    ],
    "wof:name":"Mattix Crossing Condo Assoc",
    "wof:placetype":"venue"
},
  "geometry": {"coordinates":[-74.49802099999999,39.490167],"type":"Point"}
}