{
  "type": "Feature",
  "properties": {
    "iso:country":"US",
    "sg:address":"392 Chancellor Ave",
    "sg:city":"Newark",
    "sg:classifiers":[
        {
            "category":"Organizations",
            "subcategory":"Religious Organization",
            "type":"Services"
        }
    ],
    "sg:phone":"+1 973 705 9109",
    "sg:postcode":"07112",
    "sg:province":"NJ",
    "sg:tags":[
        "church"
    ],
    "wof:name":"New Life Missionary Baptist",
    "wof:placetype":"venue"
},
  "geometry": {"coordinates":[-74.22371699999999,40.710428],"type":"Point"}
}