{
  "type": "Feature",
  "properties": {
    "addr:full":"290 S Main St Phillipsburg NJ 08865",
    "addr:housenumber":"290",
    "addr:postcode":"08865",
    "addr:street":"S Main St",
    "iso:country":"US",
    "sg:address":"290 S Main St",
    "sg:city":"Phillipsburg",
    "sg:classifiers":[
        {
            "category":"Utilities",
            "subcategory":"Mobile Phone",
            "type":"Services"
        }
    ],
    "sg:phone":"+1 908 859 1051",
    "sg:postcode":"08865",
    "sg:province":"NJ",
    "sg:tags":[
        "sound",
        "automotive",
        "telephone",
        "system",
        "cellular",
        "se"
    ],
    "wof:name":"Audiocom",
    "wof:placetype":"venue"
},
  "geometry": {"coordinates":[-75.196163,40.686825],"type":"Point"}
}