{
  "type": "Feature",
  "properties": {
    "addr:full":"144 Broadway Long Branch NJ 07740",
    "addr:housenumber":"144",
    "addr:postcode":"07740",
    "addr:street":"Broadway",
    "iso:country":"US",
    "sg:address":"144 Broadway",
    "sg:city":"Long Branch",
    "sg:classifiers":[
        {
            "category":"Shopping",
            "subcategory":"Clothing, Apparel, & Fashions",
            "type":"Retail Goods"
        }
    ],
    "sg:phone":"+1   ",
    "sg:postcode":"07740",
    "sg:province":"NJ",
    "wof:name":"Via Brazil Boutique Inc",
    "wof:placetype":"venue"
},
  "geometry": {"coordinates":[-73.984255,40.304869],"type":"Point"}
}