{
  "type": "Feature",
  "properties": {
    "addr:full":"50 US Hwy 46 Elmwood Park NJ 07407",
    "addr:housenumber":"50",
    "addr:postcode":"07407",
    "addr:street":"Us Hwy 46",
    "iso:country":"US",
    "sg:address":"50 US Hwy 46",
    "sg:city":"Elmwood Park",
    "sg:classifiers":[
        {
            "category":"Travel",
            "subcategory":"Hotels & Motels",
            "type":"Entertainment"
        }
    ],
    "sg:phone":"+1   ",
    "sg:postcode":"07407",
    "sg:province":"NJ",
    "sg:tags":[
        "operation"
    ],
    "wof:name":"Town House Motor Hotels",
    "wof:placetype":"venue"
},
  "geometry": {"coordinates":[-74.12675299999999,40.893588],"type":"Point"}
}