{
  "type": "Feature",
  "properties": {
    "iso:country":"US",
    "sg:address":"42 Mill St",
    "sg:city":"Medford",
    "sg:classifiers":[
        {
            "category":"Building & Trades",
            "subcategory":"Construction",
            "type":"Services"
        }
    ],
    "sg:phone":"+1 609 714 8935",
    "sg:postcode":"08055",
    "sg:province":"NJ",
    "sg:tags":[
        "house"
    ],
    "wof:name":"Dugan Builders Inc",
    "wof:placetype":"venue"
},
  "geometry": {"coordinates":[-74.825974,39.891644],"type":"Point"}
}