{
  "type": "Feature",
  "properties": {
    "addr:full":"402 Oncrest Ter Cliffside Park NJ 07010",
    "addr:housenumber":"402",
    "addr:postcode":"07010",
    "addr:street":"Oncrest Ter;Park",
    "iso:country":"US",
    "sg:address":"402 Oncrest Ter",
    "sg:city":"Cliffside Park",
    "sg:classifiers":[
        {
            "category":"Building & Trades",
            "subcategory":"Construction",
            "type":"Services"
        }
    ],
    "sg:phone":"+1 201 941 9698",
    "sg:postcode":"07010",
    "sg:province":"NJ",
    "sg:tags":[
        "contractor"
    ],
    "wof:name":"Frank Letizia",
    "wof:placetype":"venue"
},
  "geometry": {"coordinates":[-73.986127,40.817617],"type":"Point"}
}