{
  "type": "Feature",
  "properties": {
    "iso:country":"US",
    "sg:address":"1878 Springfield Ave",
    "sg:city":"Maplewood",
    "sg:classifiers":[
        {
            "category":"Banks & Credit Unions",
            "subcategory":"Bank",
            "type":"Services"
        }
    ],
    "sg:phone":"+1   ",
    "sg:postcode":"07040",
    "sg:province":"NJ",
    "sg:tags":[
        "real estate",
        "business",
        "broker"
    ],
    "wof:name":"A A A Business Brokers & Cons",
    "wof:placetype":"venue"
},
  "geometry": {"coordinates":[-74.269656,40.720805],"type":"Point"}
}