{
  "type": "Feature",
  "properties": {
    "addr:full":"200 Larchmont Blvd Mount Laurel NJ 08054",
    "addr:housenumber":"200",
    "addr:postcode":"08054",
    "addr:street":"Larchmont Blvd",
    "iso:country":"US",
    "sg:address":"200 Larchmont Blvd",
    "sg:city":"Mount Laurel",
    "sg:classifiers":[
        {
            "category":"Restaurant",
            "type":"Food & Drink"
        }
    ],
    "sg:phone":"+1   ",
    "sg:postcode":"08054",
    "sg:province":"NJ",
    "sg:tags":[
        "eating"
    ],
    "wof:name":"Angelos Pizza Shop",
    "wof:placetype":"venue"
},
  "geometry": {"coordinates":[-74.875061,39.961427],"type":"Point"}
}