{
  "type": "Feature",
  "properties": {
    "addr:full":"501 Forrestal Rd Princeton NJ 08540",
    "addr:housenumber":"501",
    "addr:postcode":"08540",
    "addr:street":"Forrestal Rd",
    "iso:country":"US",
    "sg:address":"501 Forrestal Rd",
    "sg:city":"Princeton",
    "sg:classifiers":[
        {
            "category":"Professional",
            "subcategory":"Research",
            "type":"Services"
        }
    ],
    "sg:phone":"+1 609 921 3534",
    "sg:postcode":"08540",
    "sg:province":"NJ",
    "sg:tags":[
        "foundation",
        "philanthropic"
    ],
    "sg:website":"www.marine-scholars.org",
    "wof:name":"Marine Corps Scholarship",
    "wof:placetype":"venue"
},
  "geometry": {"coordinates":[-74.616911,40.348893],"type":"Point"}
}