{
  "type": "Feature",
  "properties": {
    "iso:country":"US",
    "sg:address":"4213 Ventnor Ave",
    "sg:city":"Atlantic City",
    "sg:classifiers":[
        {
            "category":"Personal",
            "subcategory":"Beauty Salon",
            "type":"Services"
        }
    ],
    "sg:phone":"+1 609 441 1511",
    "sg:postcode":"08401",
    "sg:province":"NJ",
    "sg:tags":[
        "shop"
    ],
    "wof:name":"Salon Pintame",
    "wof:placetype":"venue"
},
  "geometry": {"coordinates":[-74.461246,39.34843],"type":"Point"}
}