{
  "type": "Feature",
  "properties": {
    "addr:full":"54 State Rte 12 Flemington NJ 08822",
    "addr:housenumber":"54",
    "addr:postcode":"08822",
    "addr:street":"State Rte 12",
    "iso:country":"US",
    "sg:address":"54 State Rte 12",
    "sg:city":"Flemington",
    "sg:classifiers":[
        {
            "category":"Manufacturing",
            "subcategory":"Paper Products",
            "type":"Manufacturing & Wholesale Goods"
        }
    ],
    "sg:phone":"+1 908 782 5858",
    "sg:postcode":"08822",
    "sg:province":"NJ",
    "sg:tags":[
        "bag"
    ],
    "sg:website":"www.bemis.com",
    "wof:name":"Bemis Co",
    "wof:placetype":"venue"
},
  "geometry": {"coordinates":[-74.855844,40.501909],"type":"Point"}
}