{
  "type": "Feature",
  "properties": {
    "iso:country":"US",
    "sg:address":"17 Bridge St",
    "sg:city":"Stockton",
    "sg:classifiers":[
        {
            "category":"Food & Beverages",
            "subcategory":"Liquor & Beverages",
            "type":"Retail Goods"
        }
    ],
    "sg:phone":"+1 609 397 0587",
    "sg:postcode":"08559",
    "sg:province":"NJ",
    "sg:tags":[
        "beer",
        "spirit",
        "wine"
    ],
    "sg:website":"phillipsfinewines.com",
    "wof:name":"Phillips Fine Wine",
    "wof:placetype":"venue"
},
  "geometry": {"coordinates":[-74.977968,40.405758],"type":"Point"}
}