{
  "type": "Feature",
  "properties": {
    "addr:full":"250 S Burnt Mill Rd Voorhees NJ 08043",
    "addr:housenumber":"250",
    "addr:postcode":"08043",
    "addr:street":"S Burnt Mill Rd",
    "iso:country":"US",
    "sg:address":"250 S Burnt Mill Rd",
    "sg:city":"Voorhees",
    "sg:classifiers":[
        {
            "category":"Real Estate",
            "subcategory":"Real Estate Operator",
            "type":"Services"
        }
    ],
    "sg:phone":"+1 856 795 5337",
    "sg:postcode":"08043",
    "sg:province":"NJ",
    "sg:tags":[
        "apartment"
    ],
    "wof:name":"Burnt Mill Apartment-Homes",
    "wof:placetype":"venue"
},
  "geometry": {"coordinates":[-75.007519,39.853761],"type":"Point"}
}