{
  "type": "Feature",
  "properties": {
    "iso:country":"US",
    "sg:address":"202 Broadway",
    "sg:city":"Point Pleasant",
    "sg:classifiers":[
        {
            "category":"Professional",
            "subcategory":"Lawyer & Legal Services",
            "type":"Services"
        }
    ],
    "sg:phone":"+1 732 295 8266",
    "sg:postcode":"08742",
    "sg:province":"NJ",
    "sg:tags":[
        "attorney"
    ],
    "wof:name":"Michael Schaller Esq",
    "wof:placetype":"venue"
},
  "geometry": {"coordinates":[-74.04246500000001,40.10045],"type":"Point"}
}