{
  "type": "Feature",
  "properties": {
    "iso:country":"US",
    "sg:address":"8 Turnberry Dr",
    "sg:city":"Englishtown",
    "sg:classifiers":[
        {
            "category":"Social Services",
            "subcategory":"Child Care",
            "type":"Services"
        }
    ],
    "sg:phone":"+1   ",
    "sg:postcode":"07726",
    "sg:province":"NJ",
    "sg:tags":[
        "day"
    ],
    "wof:name":"Wee Design Group",
    "wof:placetype":"venue"
},
  "geometry": {"coordinates":[-74.374247,40.259486],"type":"Point"}
}