{
  "type": "Feature",
  "properties": {
    "addr:full":"26 Columbia Tpke Florham Park NJ 07932",
    "addr:housenumber":"26",
    "addr:postcode":"07932",
    "addr:street":"Columbia Tpke",
    "iso:country":"US",
    "sg:address":"26 Columbia Tpke",
    "sg:city":"Florham Park",
    "sg:classifiers":[
        {
            "category":"Professional",
            "subcategory":"Lawyer & Legal Services",
            "type":"Services"
        }
    ],
    "sg:phone":"+1 973 822 0220",
    "sg:postcode":"07932",
    "sg:province":"NJ",
    "wof:name":"Mazzu Anne Marie ESQ",
    "wof:placetype":"venue"
},
  "geometry": {"coordinates":[-74.373497,40.7813],"type":"Point"}
}