{
  "type": "Feature",
  "properties": {
    "iso:country":"US",
    "sg:address":"6801 Ocean Avenue",
    "sg:city":"Wildwood",
    "sg:classifiers":[
        {
            "category":"Travel",
            "subcategory":"Hotels & Motels",
            "type":"Entertainment"
        }
    ],
    "sg:phone":"+1 609 729 2000",
    "sg:postcode":"08260",
    "sg:province":"NJ",
    "sg:website":"www.portroyalhotel.com/index.htm",
    "wof:name":"Port Royal Hotel",
    "wof:placetype":"venue"
},
  "geometry": {"coordinates":[-74.832927,38.970953],"type":"Point"}
}