{
  "type": "Feature",
  "properties": {
    "iso:country":"US",
    "sg:address":"590 Park Ave",
    "sg:city":"Freehold",
    "sg:classifiers":[
        {
            "category":"Health Services",
            "subcategory":"Health Practitioner",
            "type":"Services"
        }
    ],
    "sg:phone":"+1   ",
    "sg:postcode":"07728",
    "sg:province":"NJ",
    "wof:name":"Donna H Mc Gee PHD",
    "wof:placetype":"venue"
},
  "geometry": {"coordinates":[-74.268237,40.249666],"type":"Point"}
}