{
  "type": "Feature",
  "properties": {
    "addr:full":"16 Hemlock Ln Marlboro NJ 07746",
    "addr:housenumber":"16",
    "addr:postcode":"07746",
    "addr:street":"Hemlock Ln",
    "iso:country":"US",
    "sg:address":"16 Hemlock Ln",
    "sg:city":"Marlboro",
    "sg:classifiers":[
        {
            "category":"Retail",
            "subcategory":"Veterinary Services",
            "type":"Services"
        }
    ],
    "sg:phone":"+1 732 972 8006",
    "sg:postcode":"07746",
    "sg:province":"NJ",
    "sg:tags":[
        "veterinarian"
    ],
    "wof:name":"Larry Weiner DVM",
    "wof:placetype":"venue"
},
  "geometry": {"coordinates":[-74.288065,40.326907],"type":"Point"}
}