{
  "type": "Feature",
  "properties": {
    "addr:full":"325 Columbia Tpke Florham Park NJ 07932",
    "addr:housenumber":"325",
    "addr:postcode":"07932",
    "addr:street":"Columbia Tpke",
    "iso:country":"US",
    "sg:address":"325 Columbia Tpke",
    "sg:city":"Florham Park",
    "sg:classifiers":[
        {
            "category":"Banks & Credit Unions",
            "subcategory":"Investment Brokerage",
            "type":"Services"
        }
    ],
    "sg:phone":"+1 973 660 4700",
    "sg:postcode":"07932",
    "sg:province":"NJ",
    "sg:tags":[
        "stock",
        "bond"
    ],
    "sg:website":"www.smithbarney.com",
    "wof:name":"Smith Barney",
    "wof:placetype":"venue"
},
  "geometry": {"coordinates":[-74.41770099999999,40.790989],"type":"Point"}
}