{
  "type": "Feature",
  "properties": {
    "iso:country":"US",
    "sg:address":"600 N Delsea Dr",
    "sg:city":"Cape May Ct Hse",
    "sg:classifiers":[
        {
            "category":"Autos & Motor Vehicles",
            "subcategory":"Boat Sales",
            "type":"Retail Goods"
        }
    ],
    "sg:phone":"+1 609 889 8228",
    "sg:postcode":"08210",
    "sg:province":"NJ",
    "sg:tags":[
        "dealer",
        "sales"
    ],
    "wof:name":"Mac Marine Svc",
    "wof:placetype":"venue"
},
  "geometry": {"coordinates":[-74.82109199999999,39.170593],"type":"Point"}
}