{
  "type": "Feature",
  "properties": {
    "iso:country":"US",
    "sg:address":"190 Oliver St",
    "sg:city":"Paterson",
    "sg:classifiers":[
        {
            "category":"Organizations",
            "subcategory":"Non-profit Organization",
            "type":"Services"
        }
    ],
    "sg:phone":"+1 973 523 1785",
    "sg:postcode":"07501",
    "sg:province":"NJ",
    "wof:name":"Windsor Academy & Prep",
    "wof:placetype":"venue"
},
  "geometry": {"coordinates":[-74.174024,40.913579],"type":"Point"}
}