{
  "type": "Feature",
  "properties": {
    "iso:country":"US",
    "sg:address":"108 Swedesboro Rd",
    "sg:city":"Mullica Hill",
    "sg:classifiers":[
        {
            "category":"Health Services",
            "subcategory":"Health Practitioner",
            "type":"Services"
        }
    ],
    "sg:phone":"+1 856 223 8898",
    "sg:postcode":"08062",
    "sg:province":"NJ",
    "sg:tags":[
        "therapist",
        "physical"
    ],
    "wof:name":"Victory Physical Therapy",
    "wof:placetype":"venue"
},
  "geometry": {"coordinates":[-75.22475799999999,39.742756],"type":"Point"}
}