{
  "type": "Feature",
  "properties": {
    "addr:full":"240 Meadow Rd Edison NJ 08817",
    "addr:housenumber":"240",
    "addr:postcode":"08817",
    "addr:street":"Meadow Rd",
    "iso:country":"US",
    "sg:address":"240 Meadow Rd",
    "sg:city":"Edison",
    "sg:classifiers":[
        {
            "category":"Freight",
            "type":"Transportation"
        }
    ],
    "sg:phone":"+1 732 572 7400",
    "sg:postcode":"08817",
    "sg:province":"NJ",
    "sg:tags":[
        "warehouse"
    ],
    "wof:name":"Lithonia Lighting",
    "wof:placetype":"venue"
},
  "geometry": {"coordinates":[-74.38631599999999,40.494755],"type":"Point"}
}