{
  "type": "Feature",
  "properties": {
    "addr:full":"46 Arlington Ave Jersey City NJ 07305",
    "addr:housenumber":"46",
    "addr:postcode":"07305",
    "addr:street":"Arlington Ave",
    "iso:country":"US",
    "sg:address":"46 Arlington Ave",
    "sg:city":"Jersey City",
    "sg:classifiers":[
        {
            "category":"Building & Trades",
            "subcategory":"Construction",
            "type":"Services"
        }
    ],
    "sg:phone":"+1 201 985 9400",
    "sg:postcode":"07305",
    "sg:province":"NJ",
    "sg:tags":[
        "commercial",
        "general",
        "remodeling",
        "contractor"
    ],
    "wof:name":"Black Dog Construction",
    "wof:placetype":"venue"
},
  "geometry": {"coordinates":[-74.077623,40.703942],"type":"Point"}
}