{
  "type": "Feature",
  "properties": {
    "addr:full":"1508 Route 47 Rio Grande NJ 08242",
    "addr:housenumber":"1508",
    "addr:postcode":"08242",
    "addr:street":"Route 47",
    "iso:country":"US",
    "sg:address":"1508 Route 47",
    "sg:city":"Rio Grande",
    "sg:classifiers":[
        {
            "category":"Professional",
            "subcategory":"Lawyer & Legal Services",
            "type":"Services"
        }
    ],
    "sg:phone":"+1 609 886 4333",
    "sg:postcode":"08242",
    "sg:province":"NJ",
    "sg:tags":[
        "personal",
        "injury"
    ],
    "wof:name":"Mintz Lawrence",
    "wof:placetype":"venue"
},
  "geometry": {"coordinates":[-74.87249799999999,39.0126],"type":"Point"}
}