{
  "type": "Feature",
  "properties": {
    "addr:full":"101 Park Ave Collingswood NJ 08108",
    "addr:housenumber":"101",
    "addr:postcode":"08108",
    "addr:street":"Park Ave",
    "iso:country":"US",
    "sg:address":"101 Park Ave",
    "sg:city":"Collingswood",
    "sg:classifiers":[
        {
            "category":"Autos & Motor Vehicles",
            "subcategory":"Automobile Sales",
            "type":"Retail Goods"
        }
    ],
    "sg:phone":"+1   ",
    "sg:postcode":"08108",
    "sg:province":"NJ",
    "sg:tags":[
        "used"
    ],
    "wof:name":"Park Ave Autos",
    "wof:placetype":"venue"
},
  "geometry": {"coordinates":[-75.08533199999999,39.918794],"type":"Point"}
}