{
  "type": "Feature",
  "properties": {
    "addr:full":"631 N Broad St Elizabeth NJ 07208",
    "addr:housenumber":"631",
    "addr:postcode":"07208",
    "addr:street":"N Broad St",
    "iso:country":"US",
    "sg:address":"631 N Broad St",
    "sg:city":"Elizabeth",
    "sg:classifiers":[
        {
            "category":"Organizations",
            "subcategory":"Religious Organization",
            "type":"Services"
        }
    ],
    "sg:phone":"+1   ",
    "sg:postcode":"07208",
    "sg:province":"NJ",
    "wof:name":"Rev Jacqueline Reeves",
    "wof:placetype":"venue"
},
  "geometry": {"coordinates":[-74.213444,40.678608],"type":"Point"}
}