{
  "type": "Feature",
  "properties": {
    "addr:full":"5 Country Ln Holmdel NJ 07733",
    "addr:housenumber":"5",
    "addr:postcode":"07733",
    "addr:street":"Country Ln",
    "iso:country":"US",
    "sg:address":"5 Country Ln",
    "sg:city":"Holmdel",
    "sg:classifiers":[
        {
            "category":"Building & Trades",
            "subcategory":"Electrical",
            "type":"Services"
        }
    ],
    "sg:phone":"+1 732 933 1807",
    "sg:postcode":"07733",
    "sg:province":"NJ",
    "sg:tags":[
        "electrical",
        "contractor"
    ],
    "wof:name":"In Petrilla Electric Co",
    "wof:placetype":"venue"
},
  "geometry": {"coordinates":[-74.14982000000001,40.362643],"type":"Point"}
}