{
  "type": "Feature",
  "properties": {
    "addr:full":"123 Hillside Rd Elizabeth NJ 07208",
    "addr:housenumber":"123",
    "addr:postcode":"07208",
    "addr:street":"Hillside Rd",
    "iso:country":"US",
    "sg:address":"123 Hillside Rd",
    "sg:city":"Elizabeth",
    "sg:classifiers":[
        {
            "category":"Organizations",
            "subcategory":"Religious Organization",
            "type":"Services"
        }
    ],
    "sg:phone":"+1 908 355 0470",
    "sg:postcode":"07208",
    "sg:province":"NJ",
    "sg:tags":[
        "clergy"
    ],
    "wof:name":"Yitzchok Burnstein",
    "wof:placetype":"venue"
},
  "geometry": {"coordinates":[-74.241243,40.669914],"type":"Point"}
}