{
  "type": "Feature",
  "properties": {
    "iso:country":"US",
    "sg:address":"199 Adelaide St",
    "sg:city":"Belleville",
    "sg:classifiers":[
        {
            "category":"Organizations",
            "subcategory":"Religious Organization",
            "type":"Services"
        }
    ],
    "sg:phone":"+1   ",
    "sg:postcode":"07109",
    "sg:province":"NJ",
    "wof:name":"Bethsaida Christian Fellowship",
    "wof:placetype":"venue"
},
  "geometry": {"coordinates":[-74.15530699999999,40.803784],"type":"Point"}
}