{
  "type": "Feature",
  "properties": {
    "iso:country":"US",
    "sg:address":"133 Burlington Path Rd",
    "sg:city":"Creamridge",
    "sg:classifiers":[
        {
            "category":"Professional",
            "subcategory":"Business Services",
            "type":"Services"
        }
    ],
    "sg:phone":"+1   ",
    "sg:postcode":"08514",
    "sg:province":"NJ",
    "wof:name":"Katco Sales & Marketing LLC",
    "wof:placetype":"venue"
},
  "geometry": {"coordinates":[-74.51819399999999,40.13534],"type":"Point"}
}