{
  "type": "Feature",
  "properties": {
    "addr:full":"278 New Brunswick Ave Perth Amboy NJ 08861",
    "addr:housenumber":"278",
    "addr:postcode":"08861",
    "addr:street":"New Brunswick Ave",
    "iso:country":"US",
    "sg:address":"278 New Brunswick Ave",
    "sg:city":"Perth Amboy",
    "sg:classifiers":[
        {
            "category":"Autos & Motor Vehicles",
            "subcategory":"Automobile Sales",
            "type":"Retail Goods"
        }
    ],
    "sg:phone":"+1   ",
    "sg:postcode":"08861",
    "sg:province":"NJ",
    "sg:tags":[
        "used"
    ],
    "wof:name":"Carvan Used Car Dealers",
    "wof:placetype":"venue"
},
  "geometry": {"coordinates":[-74.272836,40.513447],"type":"Point"}
}