{
  "type": "Feature",
  "properties": {
    "addr:full":"92 W Main St Rockaway NJ 07866",
    "addr:housenumber":"92",
    "addr:postcode":"07866",
    "addr:street":"W Main St",
    "iso:country":"US",
    "sg:address":"92 W Main St",
    "sg:city":"Rockaway",
    "sg:classifiers":[
        {
            "category":"Manufacturing",
            "subcategory":"Tools & Machinery",
            "type":"Manufacturing & Wholesale Goods"
        }
    ],
    "sg:phone":"+1 973 983 1844",
    "sg:postcode":"07866",
    "sg:province":"NJ",
    "sg:tags":[
        "machine",
        "shop"
    ],
    "sg:website":"www.faberprecision.com",
    "wof:name":"Faber Precision Inc",
    "wof:placetype":"venue"
},
  "geometry": {"coordinates":[-74.514014,40.901192],"type":"Point"}
}