{
  "type": "Feature",
  "properties": {
    "iso:country":"US",
    "sg:address":"95 Orchard St",
    "sg:city":"Summit",
    "sg:classifiers":[
        {
            "category":"Retail",
            "subcategory":"Laundry & Dry Cleaning",
            "type":"Services"
        }
    ],
    "sg:phone":"+1 908 277 0409",
    "sg:postcode":"07901",
    "sg:province":"NJ",
    "wof:name":"J&D Carpet & Floor Care Inc",
    "wof:placetype":"venue"
},
  "geometry": {"coordinates":[-74.34232799999999,40.713505],"type":"Point"}
}