{
  "type": "Feature",
  "properties": {
    "addr:full":"1500 Morris Ave Union NJ 07083",
    "addr:housenumber":"1500",
    "addr:postcode":"07083",
    "addr:street":"Morris Ave",
    "iso:country":"US",
    "sg:address":"1500 Morris Ave",
    "sg:city":"Union",
    "sg:classifiers":[
        {
            "category":"Retail",
            "subcategory":"Funeral Services",
            "type":"Services"
        }
    ],
    "sg:phone":"+1 973 374 5400",
    "sg:postcode":"07083",
    "sg:province":"NJ",
    "sg:tags":[
        "director"
    ],
    "wof:name":"Charles F Hausmann & Son",
    "wof:placetype":"venue"
},
  "geometry": {"coordinates":[-74.250696,40.690571],"type":"Point"}
}