{
  "type": "Feature",
  "properties": {
    "iso:country":"US",
    "sg:address":"48 Henry Ct",
    "sg:city":"Mount Arlington",
    "sg:classifiers":[
        {
            "category":"Real Estate",
            "subcategory":"Real Estate Operator",
            "type":"Services"
        }
    ],
    "sg:phone":"+1   ",
    "sg:postcode":"07856",
    "sg:province":"NJ",
    "sg:tags":[
        "building",
        "apartment"
    ],
    "wof:name":"Mount Arlington Gardens",
    "wof:placetype":"venue"
},
  "geometry": {"coordinates":[-74.637562,40.918758],"type":"Point"}
}