{
  "type": "Feature",
  "properties": {
    "iso:country":"US",
    "sg:address":"138 Eagle Rock Ave",
    "sg:city":"East Hanover",
    "sg:classifiers":[
        {
            "category":"Building & Trades",
            "subcategory":"Locksmith",
            "type":"Services"
        }
    ],
    "sg:phone":"+1 973 795 9282",
    "sg:postcode":"07936",
    "sg:province":"NJ",
    "sg:tags":[
        "key"
    ],
    "wof:name":"East Hanover 24 Hour Emergency Locksmith",
    "wof:placetype":"venue"
},
  "geometry": {"coordinates":[-74.337264,40.8297],"type":"Point"}
}