{
  "type": "Feature",
  "properties": {
    "addr:full":"508 7th St Union City NJ 07087",
    "addr:housenumber":"508",
    "addr:postcode":"07087",
    "addr:street":"7Th St",
    "iso:country":"US",
    "sg:address":"508 7th St",
    "sg:city":"Union City",
    "sg:classifiers":[
        {
            "category":"Professional",
            "subcategory":"Secretarial Services",
            "type":"Services"
        }
    ],
    "sg:phone":"+1   ",
    "sg:postcode":"07087",
    "sg:province":"NJ",
    "sg:tags":[
        "reporting"
    ],
    "wof:name":"Typing By Daniel",
    "wof:placetype":"venue"
},
  "geometry": {"coordinates":[-74.040747,40.757093],"type":"Point"}
}