{
  "type": "Feature",
  "properties": {
    "addr:full":"6905 Bergenline Ave West New York NJ 07093",
    "addr:housenumber":"6905",
    "addr:postcode":"07093",
    "addr:street":"Bergenline Ave West",
    "iso:country":"US",
    "sg:address":"6905 Bergenline Ave",
    "sg:city":"West New York",
    "sg:classifiers":[
        {
            "category":"Restaurant",
            "type":"Food & Drink"
        }
    ],
    "sg:menulink":"http://www.allmenus.com/nj/guttenberg/146054-subway/menu/",
    "sg:phone":"+1 201 453 2600",
    "sg:postcode":"07093",
    "sg:province":"NJ",
    "sg:tags":[
        "american",
        "sandwich"
    ],
    "wof:name":"Subway",
    "wof:placetype":"venue"
},
  "geometry": {"coordinates":[-74.01114699999999,40.795821],"type":"Point"}
}