{
  "type": "Feature",
  "properties": {
    "iso:country":"US",
    "sg:address":"481 Main Rd",
    "sg:city":"Towaco",
    "sg:classifiers":[
        {
            "category":"Wholesale",
            "subcategory":"Auto Parts",
            "type":"Manufacturing & Wholesale Goods"
        }
    ],
    "sg:phone":"+1 973 808 0066",
    "sg:postcode":"07082",
    "sg:province":"NJ",
    "sg:tags":[
        "automobile",
        "supply"
    ],
    "wof:name":"Just Suspension",
    "wof:placetype":"venue"
},
  "geometry": {"coordinates":[-74.352593,40.918507],"type":"Point"}
}