{
  "type": "Feature",
  "properties": {
    "iso:country":"US",
    "sg:address":"109 Pacific Ave",
    "sg:city":"Jersey City",
    "sg:classifiers":[
        {
            "category":"Health Services",
            "subcategory":"Doctor",
            "type":"Services"
        }
    ],
    "sg:phone":"+1 201 434 0008",
    "sg:postcode":"07304",
    "sg:province":"NJ",
    "sg:tags":[
        "physician",
        "surgeon"
    ],
    "wof:name":"Barry Weiner MD Pa",
    "wof:placetype":"venue"
},
  "geometry": {"coordinates":[-74.067458,40.708058],"type":"Point"}
}