{
  "type": "Feature",
  "properties": {
    "iso:country":"US",
    "sg:address":"16 Riverside Dr",
    "sg:city":"Rumson",
    "sg:classifiers":[
        {
            "category":"Professional",
            "subcategory":"Management & Consulting",
            "type":"Services"
        }
    ],
    "sg:phone":"+1 732 758 8500",
    "sg:postcode":"07760",
    "sg:province":"NJ",
    "sg:tags":[
        "consultant",
        "business"
    ],
    "wof:name":"Crocker & Hull Advertising Inc",
    "wof:placetype":"venue"
},
  "geometry": {"coordinates":[-74.026095,40.342487],"type":"Point"}
}