{
  "type": "Feature",
  "properties": {
    "addr:full":"430 Taylor St Riverside NJ 08075",
    "addr:housenumber":"430",
    "addr:postcode":"08075",
    "addr:street":"Taylor St",
    "iso:country":"US",
    "sg:address":"430 Taylor St",
    "sg:city":"Riverside",
    "sg:classifiers":[
        {
            "category":"Bars & Pubs",
            "type":"Food & Drink"
        }
    ],
    "sg:phone":"+1 856 461 2435",
    "sg:postcode":"08075",
    "sg:province":"NJ",
    "sg:tags":[
        "drinking"
    ],
    "wof:name":"Derby's Tavern",
    "wof:placetype":"venue"
},
  "geometry": {"coordinates":[-74.95240200000001,40.037698],"type":"Point"}
}