{
  "type": "Feature",
  "properties": {
    "addr:full":"40 Treaty Elm Ln Haddonfield NJ 08033",
    "addr:housenumber":"40",
    "addr:postcode":"08033",
    "addr:street":"Treaty Elm Ln",
    "iso:country":"US",
    "sg:address":"40 Treaty Elm Ln",
    "sg:city":"Haddonfield",
    "sg:classifiers":[
        {
            "category":"Professional",
            "subcategory":"Computer Services",
            "type":"Services"
        }
    ],
    "sg:phone":"+1 856 429 6121",
    "sg:postcode":"08033",
    "sg:province":"NJ",
    "sg:tags":[
        "systems-consultants",
        "designer",
        "data"
    ],
    "wof:name":"Colonial Computer Associates",
    "wof:placetype":"venue"
},
  "geometry": {"coordinates":[-75.032428,39.886651],"type":"Point"}
}