{
  "type": "Feature",
  "properties": {
    "addr:full":"603 Daniel St Middletown NJ 07748",
    "addr:housenumber":"603",
    "addr:postcode":"07748",
    "addr:street":"Daniel St",
    "iso:country":"US",
    "sg:address":"603 Daniel St",
    "sg:city":"Middletown",
    "sg:classifiers":[
        {
            "category":"Retail",
            "subcategory":"Repair Shop",
            "type":"Services"
        }
    ],
    "sg:phone":"+1 732 222 2744",
    "sg:postcode":"07748",
    "sg:province":"NJ",
    "sg:tags":[
        "refrigeration"
    ],
    "wof:name":"County Refrigeration Service",
    "wof:placetype":"venue"
},
  "geometry": {"coordinates":[-74.111926,40.41931],"type":"Point"}
}