{
  "type": "Feature",
  "properties": {
    "iso:country":"US",
    "sg:address":"18 North Ave",
    "sg:city":"Garwood",
    "sg:classifiers":[
        {
            "category":"Bakery",
            "type":"Food & Drink"
        }
    ],
    "sg:phone":"+1 908 232 9003",
    "sg:postcode":"07027",
    "sg:province":"NJ",
    "sg:website":"www.sugarhousebaking.com",
    "wof:name":"Sugar House Bakery",
    "wof:placetype":"venue"
},
  "geometry": {"coordinates":[-74.31480000000001,40.6548],"type":"Point"}
}