{
  "type": "Feature",
  "properties": {
    "addr:full":"5 Wyckoff Rd Whitehouse Sta NJ 08889",
    "addr:housenumber":"5",
    "addr:postcode":"08889",
    "addr:street":"Wyckoff Rd",
    "iso:country":"US",
    "sg:address":"5 Wyckoff Rd",
    "sg:city":"Whitehouse Sta",
    "sg:classifiers":[
        {
            "category":"Professional",
            "subcategory":"Computer Services",
            "type":"Services"
        },
        {
            "category":"Shopping",
            "subcategory":"Computers & Home Electronics",
            "type":"Retail Goods"
        }
    ],
    "sg:phone":"+1 908 534 4885",
    "sg:postcode":"08889",
    "sg:province":"NJ",
    "sg:tags":[
        "publishing",
        "related"
    ],
    "wof:name":"Words of Art",
    "wof:placetype":"venue"
},
  "geometry": {"coordinates":[-74.779663,40.601104],"type":"Point"}
}