{
  "type": "Feature",
  "properties": {
    "addr:full":"300 Promenade Blvd Bridgewater NJ 08807",
    "addr:housenumber":"300",
    "addr:postcode":"08807",
    "addr:street":"Promenade Blvd",
    "iso:country":"US",
    "sg:address":"300 Promenade Blvd",
    "sg:city":"Bridgewater",
    "sg:classifiers":[
        {
            "category":"Shopping",
            "subcategory":"Clothing, Apparel, & Fashions",
            "type":"Retail Goods"
        }
    ],
    "sg:phone":"+1   ",
    "sg:postcode":"08807",
    "sg:province":"NJ",
    "sg:tags":[
        "family"
    ],
    "sg:website":"www.oldnavy.com",
    "wof:name":"Old Navy",
    "wof:placetype":"venue"
},
  "geometry": {"coordinates":[-74.555398,40.564794],"type":"Point"}
}