{
  "type": "Feature",
  "properties": {
    "addr:full":"205 4th St Lakewood NJ 08701",
    "addr:housenumber":"205",
    "addr:postcode":"08701",
    "addr:street":"4Th St",
    "iso:country":"US",
    "sg:address":"205 4th St",
    "sg:city":"Lakewood",
    "sg:classifiers":[
        {
            "category":"Restaurant",
            "type":"Food & Drink"
        }
    ],
    "sg:phone":"+1   ",
    "sg:postcode":"08701",
    "sg:province":"NJ",
    "sg:tags":[
        "eating"
    ],
    "wof:name":"Eladardo Restaurant",
    "wof:placetype":"venue"
},
  "geometry": {"coordinates":[-74.212653,40.094413],"type":"Point"}
}