{
  "type": "Feature",
  "properties": {
    "iso:country":"US",
    "sg:address":"177 Columbia Tpke",
    "sg:city":"Florham Park",
    "sg:classifiers":[
        {
            "category":"Personal",
            "subcategory":"Nail Salon",
            "type":"Services"
        }
    ],
    "sg:phone":"+1 973 765 9030",
    "sg:postcode":"07932",
    "sg:province":"NJ",
    "wof:name":"Luxury Nails",
    "wof:placetype":"venue"
},
  "geometry": {"coordinates":[-74.391098,40.7883],"type":"Point"}
}