{
  "type": "Feature",
  "properties": {
    "addr:full":"4 Edison Pl Fairfield NJ 07004",
    "addr:housenumber":"4",
    "addr:postcode":"07004",
    "addr:street":"Edison Pl",
    "iso:country":"US",
    "sg:address":"4 Edison Pl",
    "sg:city":"Fairfield",
    "sg:classifiers":[
        {
            "category":"Professional",
            "subcategory":"Computer Services",
            "type":"Services"
        }
    ],
    "sg:phone":"+1   ",
    "sg:postcode":"07004",
    "sg:province":"NJ",
    "sg:tags":[
        "mailing"
    ],
    "wof:name":"Computer Dimensions Inc",
    "wof:placetype":"venue"
},
  "geometry": {"coordinates":[-74.28546299999999,40.882529],"type":"Point"}
}