{
  "type": "Feature",
  "properties": {
    "iso:country":"US",
    "sg:address":"503 Monmouth Dr",
    "sg:city":"Mount Laurel",
    "sg:classifiers":[
        {
            "category":"Building & Trades",
            "subcategory":"Electrical",
            "type":"Services"
        }
    ],
    "sg:phone":"+1 856 778 7889",
    "sg:postcode":"08054",
    "sg:province":"NJ",
    "sg:tags":[
        "electrical",
        "contractor"
    ],
    "wof:name":"Trinity Electric Services LLC",
    "wof:placetype":"venue"
},
  "geometry": {"coordinates":[-74.868775,39.924151],"type":"Point"}
}