{
  "type": "Feature",
  "properties": {
    "addr:full":"911 Sunset Rd Burlington NJ 08016",
    "addr:housenumber":"911",
    "addr:postcode":"08016",
    "addr:street":"Sunset Rd",
    "iso:country":"US",
    "sg:address":"911 Sunset Rd",
    "sg:city":"Burlington",
    "sg:classifiers":[
        {
            "category":"Health Services",
            "subcategory":"Health Practitioner",
            "type":"Services"
        }
    ],
    "sg:phone":"+1 609 386 2291",
    "sg:postcode":"08016",
    "sg:province":"NJ",
    "sg:tags":[
        "therapy",
        "physical"
    ],
    "wof:name":"Cardio Stat Physical Therapy Center Inc",
    "wof:placetype":"venue"
},
  "geometry": {"coordinates":[-74.849403,40.050499],"type":"Point"}
}