{
  "type": "Feature",
  "properties": {
    "addr:full":"319 Swarthmore Rd Glassboro NJ 08028",
    "addr:housenumber":"319",
    "addr:postcode":"08028",
    "addr:street":"Swarthmore Rd",
    "iso:country":"US",
    "sg:address":"319 Swarthmore Rd",
    "sg:city":"Glassboro",
    "sg:classifiers":[
        {
            "category":"Home & Garden",
            "subcategory":"Building Materials",
            "type":"Retail Goods"
        }
    ],
    "sg:phone":"+1 856 863 1988",
    "sg:postcode":"08028",
    "sg:province":"NJ",
    "sg:tags":[
        "windows"
    ],
    "wof:name":"Pristine Window Repair",
    "wof:placetype":"venue"
},
  "geometry": {"coordinates":[-75.12822799999999,39.709348],"type":"Point"}
}