{
  "type": "Feature",
  "properties": {
    "iso:country":"US",
    "sg:address":"3322 US Hwy 22",
    "sg:city":"Branchburg",
    "sg:classifiers":[
        {
            "category":"Wholesale",
            "subcategory":"Durable Goods & Equipment",
            "type":"Manufacturing & Wholesale Goods"
        }
    ],
    "sg:phone":"+1 908 203 1833",
    "sg:postcode":"08876",
    "sg:province":"NJ",
    "sg:tags":[
        "institution",
        "supply"
    ],
    "wof:name":"Safeco Mutual Funds Instnl Svc",
    "wof:placetype":"venue"
},
  "geometry": {"coordinates":[-74.70017799999999,40.606604],"type":"Point"}
}