{
  "type": "Feature",
  "properties": {
    "addr:full":"7 Bank St Summit NJ 07901",
    "addr:housenumber":"7",
    "addr:postcode":"07901",
    "addr:street":"Bank St",
    "iso:country":"US",
    "sg:address":"7 Bank St",
    "sg:city":"Summit",
    "sg:classifiers":[
        {
            "category":"Building & Trades",
            "subcategory":"Construction",
            "type":"Services"
        }
    ],
    "sg:phone":"+1 908 277 4242",
    "sg:postcode":"07901",
    "sg:province":"NJ",
    "sg:tags":[
        "window",
        "installation"
    ],
    "wof:name":"GlassWorks Of Summit",
    "wof:placetype":"venue"
},
  "geometry": {"coordinates":[-74.357116,40.717559],"type":"Point"}
}