{
  "type": "Feature",
  "properties": {
    "addr:full":"293 Main St Metuchen NJ 08840",
    "addr:housenumber":"293",
    "addr:postcode":"08840",
    "addr:street":"Main St",
    "iso:country":"US",
    "sg:address":"293 Main St",
    "sg:city":"Metuchen",
    "sg:classifiers":[
        {
            "category":"Health Services",
            "subcategory":"Medical Lab",
            "type":"Services"
        }
    ],
    "sg:phone":"+1 732 494 5600",
    "sg:postcode":"08840",
    "sg:province":"NJ",
    "sg:tags":[
        "laboratory"
    ],
    "wof:name":"Community Medical Laboratories",
    "wof:placetype":"venue"
},
  "geometry": {"coordinates":[-74.360241,40.536959],"type":"Point"}
}