{
  "type": "Feature",
  "properties": {
    "addr:full":"50 Grand Ave Englewood NJ 07631",
    "addr:housenumber":"50",
    "addr:postcode":"07631",
    "addr:street":"Grand Ave",
    "iso:country":"US",
    "sg:address":"50 Grand Ave",
    "sg:city":"Englewood",
    "sg:classifiers":[
        {
            "category":"Professional",
            "type":"Services"
        }
    ],
    "sg:phone":"+1 201 567 2711",
    "sg:postcode":"07631",
    "sg:province":"NJ",
    "sg:tags":[
        "establishment"
    ],
    "wof:name":"Prism Capital Partners",
    "wof:placetype":"venue"
},
  "geometry": {"coordinates":[-73.975499,40.889835],"type":"Point"}
}