{
  "type": "Feature",
  "properties": {
    "addr:full":"401 Mount Prospect Ave Newark NJ 07104",
    "addr:housenumber":"401",
    "addr:postcode":"07104",
    "addr:street":"Mount Prospect Ave",
    "iso:country":"US",
    "sg:address":"401 Mount Prospect Ave",
    "sg:city":"Newark",
    "sg:classifiers":[
        {
            "category":"Health Services",
            "subcategory":"Doctor",
            "type":"Services"
        }
    ],
    "sg:phone":"+1 973 482 9193",
    "sg:postcode":"07104",
    "sg:province":"NJ",
    "wof:name":"Daniel Martinelli DMD",
    "wof:placetype":"venue"
},
  "geometry": {"coordinates":[-74.17053,40.765039],"type":"Point"}
}