{
  "type": "Feature",
  "properties": {
    "addr:full":"51 Woodbine St Bergenfield NJ 07621",
    "addr:housenumber":"51",
    "addr:postcode":"07621",
    "addr:street":"Woodbine St",
    "iso:country":"US",
    "sg:address":"51 Woodbine St",
    "sg:city":"Bergenfield",
    "sg:classifiers":[
        {
            "category":"Retail",
            "subcategory":"Auto Repair",
            "type":"Services"
        }
    ],
    "sg:phone":"+1 201 384 8787",
    "sg:postcode":"07621",
    "sg:province":"NJ",
    "sg:tags":[
        "automotive",
        "general"
    ],
    "wof:name":"Central Bergen Auto",
    "wof:placetype":"venue"
},
  "geometry": {"coordinates":[-74.000257,40.918563],"type":"Point"}
}