{
  "type": "Feature",
  "properties": {
    "addr:full":"5200 Ocean Ave Wildwood NJ 08260",
    "addr:housenumber":"5200",
    "addr:postcode":"08260",
    "addr:street":"Ocean Ave",
    "iso:country":"US",
    "sg:address":"5200 Ocean Ave",
    "sg:city":"Wildwood",
    "sg:classifiers":[
        {
            "category":"Travel",
            "subcategory":"Hotels & Motels",
            "type":"Entertainment"
        }
    ],
    "sg:phone":"+1 609 522 5667",
    "sg:postcode":"08260",
    "sg:province":"NJ",
    "sg:tags":[
        "operation"
    ],
    "wof:name":"Windward Motel",
    "wof:placetype":"venue"
},
  "geometry": {"coordinates":[-74.82246499999999,38.979088],"type":"Point"}
}