{
  "type": "Feature",
  "properties": {
    "addr:full":"38 Borden St Monmouth Beach NJ 07750",
    "addr:housenumber":"38",
    "addr:postcode":"07750",
    "addr:street":"Borden St",
    "iso:country":"US",
    "sg:address":"38 Borden St",
    "sg:city":"Monmouth Beach",
    "sg:classifiers":[
        {
            "category":"Utilities",
            "type":"Services"
        }
    ],
    "sg:phone":"+1 732 222 7230",
    "sg:postcode":"07750",
    "sg:province":"NJ",
    "sg:tags":[
        "sanitary"
    ],
    "wof:name":"Lawn Baron Lawn Service",
    "wof:placetype":"venue"
},
  "geometry": {"coordinates":[-73.981382,40.332089],"type":"Point"}
}