{
  "type": "Feature",
  "properties": {
    "addr:full":"6 Heron Dr Marlboro NJ 07746",
    "addr:housenumber":"6",
    "addr:postcode":"07746",
    "addr:street":"Heron Dr",
    "iso:country":"US",
    "sg:address":"6 Heron Dr",
    "sg:city":"Marlboro",
    "sg:classifiers":[
        {
            "category":"Shopping",
            "subcategory":"Gifts & Souvenirs",
            "type":"Retail Goods"
        }
    ],
    "sg:phone":"+1   ",
    "sg:postcode":"07746",
    "sg:province":"NJ",
    "wof:name":"Trendy Baby Inc",
    "wof:placetype":"venue"
},
  "geometry": {"coordinates":[-74.267172,40.307766],"type":"Point"}
}