{
  "type": "Feature",
  "properties": {
    "addr:full":"5110 Homestead Ave Pennsauken NJ 08109",
    "addr:housenumber":"5110",
    "addr:postcode":"08109",
    "addr:street":"Homestead Ave",
    "iso:country":"US",
    "sg:address":"5110 Homestead Ave",
    "sg:city":"Pennsauken",
    "sg:classifiers":[
        {
            "category":"Personal",
            "subcategory":"Beauty Salon",
            "type":"Services"
        },
        {
            "category":"Personal",
            "subcategory":"Barber",
            "type":"Services"
        }
    ],
    "sg:phone":"+1 856 488 9003",
    "sg:postcode":"08109",
    "sg:province":"NJ",
    "sg:tags":[
        "hair",
        "stylist"
    ],
    "wof:name":"Faith Woks Salon And Spa For Men",
    "wof:placetype":"venue"
},
  "geometry": {"coordinates":[-75.06390399999999,39.939419],"type":"Point"}
}