{
  "type": "Feature",
  "properties": {
    "iso:country":"US",
    "sg:address":"1200 Brookside Rd",
    "sg:city":"Piscataway",
    "sg:classifiers":[
        {
            "category":"Building & Trades",
            "subcategory":"Construction",
            "type":"Services"
        }
    ],
    "sg:phone":"+1 732 819 9734",
    "sg:postcode":"08854",
    "sg:province":"NJ",
    "wof:name":"Arrow Paving Inc",
    "wof:placetype":"venue"
},
  "geometry": {"coordinates":[-74.43154699999999,40.538657],"type":"Point"}
}