{
  "type": "Feature",
  "properties": {
    "addr:full":"35 N Main St Medford NJ 08055",
    "addr:housenumber":"35",
    "addr:postcode":"08055",
    "addr:street":"N Main St",
    "iso:country":"US",
    "sg:address":"35 N Main St",
    "sg:city":"Medford",
    "sg:classifiers":[
        {
            "category":"Real Estate",
            "subcategory":"Real Estate Agent",
            "type":"Services"
        }
    ],
    "sg:phone":"+1   ",
    "sg:postcode":"08055",
    "sg:province":"NJ",
    "wof:name":"Referral Express RE Svcs",
    "wof:placetype":"venue"
},
  "geometry": {"coordinates":[-74.82401900000001,39.903044],"type":"Point"}
}