{
  "type": "Feature",
  "properties": {
    "addr:full":"50 Watson Ave Elizabeth NJ 07202",
    "addr:housenumber":"50",
    "addr:postcode":"07202",
    "addr:street":"Watson Ave",
    "iso:country":"US",
    "sg:address":"50 Watson Ave",
    "sg:city":"Elizabeth",
    "sg:classifiers":[
        {
            "category":"Real Estate",
            "subcategory":"Real Estate Operator",
            "type":"Services"
        }
    ],
    "sg:phone":"+1 908 352 0280",
    "sg:postcode":"07202",
    "sg:province":"NJ",
    "sg:tags":[
        "apartment"
    ],
    "wof:name":"Watson Apts",
    "wof:placetype":"venue"
},
  "geometry": {"coordinates":[-74.234291,40.656244],"type":"Point"}
}