{
  "type": "Feature",
  "properties": {
    "addr:full":"1 Stanley St East Rutherford NJ 07073",
    "addr:housenumber":"1",
    "addr:postcode":"07073",
    "addr:street":"Stanley St",
    "iso:country":"US",
    "sg:address":"1 Stanley St",
    "sg:city":"East Rutherford",
    "sg:classifiers":[
        {
            "category":"Shopping",
            "subcategory":"Department Store",
            "type":"Retail Goods"
        }
    ],
    "sg:phone":"+1 201 939 2923",
    "sg:postcode":"07073",
    "sg:province":"NJ",
    "sg:website":"www.marshallsonline.com",
    "wof:name":"Marshalls Store",
    "wof:placetype":"venue"
},
  "geometry": {"coordinates":[-74.092799,40.828929],"type":"Point"}
}