{
  "type": "Feature",
  "properties": {
    "addr:full":"192 Christopher St Montclair NJ 07042",
    "addr:housenumber":"192",
    "addr:postcode":"07042",
    "addr:street":"Christopher St",
    "iso:country":"US",
    "sg:address":"192 Christopher St",
    "sg:city":"Montclair",
    "sg:classifiers":[
        {
            "category":"Professional",
            "subcategory":"Management & Consulting",
            "type":"Services"
        }
    ],
    "sg:phone":"+1   ",
    "sg:postcode":"07042",
    "sg:province":"NJ",
    "sg:tags":[
        "business"
    ],
    "wof:name":"M Polaner",
    "wof:placetype":"venue"
},
  "geometry": {"coordinates":[-74.201831,40.825099],"type":"Point"}
}