{
  "type": "Feature",
  "properties": {
    "iso:country":"US",
    "sg:address":"6725 River Rd",
    "sg:city":"Pennsauken",
    "sg:classifiers":[
        {
            "category":"Personal",
            "type":"Services"
        },
        {
            "category":"Sports & Exercise",
            "subcategory":"Ice Rink",
            "type":"Entertainment"
        },
        {
            "category":"Shopping",
            "subcategory":"Bicycles & Sporting Goods",
            "type":"Retail Goods"
        }
    ],
    "sg:phone":"+1 856 488 9300",
    "sg:postcode":"08110",
    "sg:province":"NJ",
    "sg:tags":[
        "skating",
        "party",
        "planning",
        "event"
    ],
    "sg:website":"www.flyersskatezone.com",
    "wof:name":"Flyers Skate Zone",
    "wof:placetype":"venue"
},
  "geometry": {"coordinates":[-75.060997,39.9739],"type":"Point"}
}