{
  "type": "Feature",
  "properties": {
    "iso:country":"US",
    "sg:address":"200 Warren St",
    "sg:city":"Newark",
    "sg:classifiers":[
        {
            "category":"Education",
            "subcategory":"School",
            "type":"Public Place"
        }
    ],
    "sg:phone":"+1 973 353 0707",
    "sg:postcode":"07103",
    "sg:province":"NJ",
    "wof:name":"Communities In Schools of New Jersey Inc",
    "wof:placetype":"venue"
},
  "geometry": {"coordinates":[-74.18139600000001,40.7421],"type":"Point"}
}