{
  "type": "Feature",
  "properties": {
    "addr:full":"855 Valley Rd Ste 105 Clifton NJ 07013",
    "addr:housenumber":"855",
    "addr:postcode":"07013",
    "addr:street":"Valley Rd Ste 105",
    "iso:country":"US",
    "sg:address":"855 Valley Rd Ste 105",
    "sg:city":"Clifton",
    "sg:classifiers":[
        {
            "category":"Professional",
            "subcategory":"Lawyer & Legal Services",
            "type":"Services"
        }
    ],
    "sg:phone":"+1 973 249 8330",
    "sg:postcode":"07013",
    "sg:province":"NJ",
    "wof:name":"Crm Consultants",
    "wof:placetype":"venue"
},
  "geometry": {"coordinates":[-74.189475,40.870979],"type":"Point"}
}