{
  "type": "Feature",
  "properties": {
    "iso:country":"US",
    "sg:address":"225 Tabor Rd",
    "sg:city":"Morris Plains",
    "sg:classifiers":[
        {
            "category":"Social Services",
            "subcategory":"Child Care",
            "type":"Services"
        }
    ],
    "sg:phone":"+1 973 605 5051",
    "sg:postcode":"07950",
    "sg:province":"NJ",
    "wof:name":"Kids Next Door",
    "wof:placetype":"venue"
},
  "geometry": {"coordinates":[-74.474805,40.847713],"type":"Point"}
}