{
  "type": "Feature",
  "properties": {
    "iso:country":"US",
    "sg:address":"555 Prospect Ave",
    "sg:city":"Ridgefield",
    "sg:classifiers":[
        {
            "category":"Social Services",
            "subcategory":"Child Care",
            "type":"Services"
        }
    ],
    "sg:phone":"+1 201 943 5757",
    "sg:postcode":"07657",
    "sg:province":"NJ",
    "sg:tags":[
        "kindergarten",
        "academic",
        "school"
    ],
    "wof:name":"Notre Dame-Primary Div",
    "wof:placetype":"venue"
},
  "geometry": {"coordinates":[-74.007291,40.832654],"type":"Point"}
}