{
  "type": "Feature",
  "properties": {
    "addr:full":"900 Township Ln Cherry Hill NJ 08002",
    "addr:housenumber":"900",
    "addr:postcode":"08002",
    "addr:street":"Township Ln",
    "iso:country":"US",
    "sg:address":"900 Township Ln",
    "sg:city":"Cherry Hill",
    "sg:classifiers":[
        {
            "category":"Shopping",
            "subcategory":"Clothing, Apparel, & Fashions",
            "type":"Retail Goods"
        },
        {
            "category":"Shopping",
            "subcategory":"Shoes",
            "type":"Retail Goods"
        }
    ],
    "sg:phone":"+1 856 428 8844",
    "sg:postcode":"08002",
    "sg:province":"NJ",
    "sg:tags":[
        "accessory",
        "clothing",
        "store",
        "women's"
    ],
    "sg:website":"www.mydancebag.com",
    "wof:name":"My Dance Bag",
    "wof:placetype":"venue"
},
  "geometry": {"coordinates":[-75.021004,39.9165],"type":"Point"}
}