{
  "type": "Feature",
  "properties": {
    "addr:full":"3 Vose Ave South Orange NJ 07079",
    "addr:housenumber":"3",
    "addr:postcode":"07079",
    "addr:street":"Vose Ave",
    "iso:country":"US",
    "sg:address":"3 Vose Ave",
    "sg:city":"South Orange",
    "sg:classifiers":[
        {
            "category":"Professional",
            "subcategory":"Accounting & Tax Preparation",
            "type":"Services"
        }
    ],
    "sg:phone":"+1 973 378 3552",
    "sg:postcode":"07079",
    "sg:province":"NJ",
    "wof:name":"Edwin Davis Jr CPA",
    "wof:placetype":"venue"
},
  "geometry": {"coordinates":[-74.258669,40.746924],"type":"Point"}
}