{
  "type": "Feature",
  "properties": {
    "addr:full":"156 US Hwy 9 Englishtown NJ 07726",
    "addr:housenumber":"156",
    "addr:postcode":"07726",
    "addr:street":"Us Hwy 9",
    "iso:country":"US",
    "sg:address":"156 US Hwy 9",
    "sg:city":"Englishtown",
    "sg:classifiers":[
        {
            "category":"Real Estate",
            "subcategory":"Real Estate Agent",
            "type":"Services"
        }
    ],
    "sg:phone":"+1 732 536 9010",
    "sg:postcode":"07726",
    "sg:province":"NJ",
    "wof:name":"Keller Williams",
    "wof:placetype":"venue"
},
  "geometry": {"coordinates":[-74.307284,40.351109],"type":"Point"}
}