{
  "type": "Feature",
  "properties": {
    "addr:full":"215 Main St Ledgewood NJ 07852",
    "addr:housenumber":"215",
    "addr:postcode":"07852",
    "addr:street":"Main St",
    "iso:country":"US",
    "sg:address":"215 Main St",
    "sg:city":"Ledgewood",
    "sg:classifiers":[
        {
            "category":"Museum",
            "type":"Entertainment"
        }
    ],
    "sg:phone":"+1 973 927 7603",
    "sg:postcode":"07852",
    "sg:province":"NJ",
    "sg:tags":[
        "gallery"
    ],
    "wof:name":"King Canal Store Museum",
    "wof:placetype":"venue"
},
  "geometry": {"coordinates":[-74.651195,40.877722],"type":"Point"}
}