{
  "type": "Feature",
  "properties": {
    "iso:country":"US",
    "sg:address":"41 Watchung Plz",
    "sg:city":"Montclair",
    "sg:classifiers":[
        {
            "category":"Building & Trades",
            "subcategory":"Construction",
            "type":"Services"
        }
    ],
    "sg:phone":"+1 973 882 3122",
    "sg:postcode":"07042",
    "sg:province":"NJ",
    "sg:tags":[
        "roofing",
        "contractor"
    ],
    "wof:name":"B Scymanski Enterprise",
    "wof:placetype":"venue"
},
  "geometry": {"coordinates":[-74.20622,40.829932],"type":"Point"}
}