{
  "type": "Feature",
  "properties": {
    "iso:country":"US",
    "sg:address":"105 Main St",
    "sg:city":"West Orange",
    "sg:classifiers":[
        {
            "category":"Professional",
            "subcategory":"Business Services",
            "type":"Services"
        }
    ],
    "sg:phone":"+1 973 325 8773",
    "sg:postcode":"07052",
    "sg:province":"NJ",
    "sg:tags":[
        "delivery",
        "courier"
    ],
    "wof:name":"Mi Casa Envios Services",
    "wof:placetype":"venue"
},
  "geometry": {"coordinates":[-74.237701,40.780399],"type":"Point"}
}