{
  "type": "Feature",
  "properties": {
    "addr:full":"14 Peppermill Dr Cherry Hill NJ 08002",
    "addr:housenumber":"14",
    "addr:postcode":"08002",
    "addr:street":"Peppermill Dr",
    "iso:country":"US",
    "sg:address":"14 Peppermill Dr",
    "sg:city":"Cherry Hill",
    "sg:classifiers":[
        {
            "category":"Building & Trades",
            "subcategory":"Landscaping Services",
            "type":"Services"
        }
    ],
    "sg:phone":"+1 856 482 6669",
    "sg:postcode":"08002",
    "sg:province":"NJ",
    "wof:name":"All Phase Ldscpg & Lawn Care",
    "wof:placetype":"venue"
},
  "geometry": {"coordinates":[-74.987388,39.938581],"type":"Point"}
}