{
  "type": "Feature",
  "properties": {
    "iso:country":"US",
    "sg:address":"3148 Asbury Ave",
    "sg:city":"Ocean City",
    "sg:classifiers":[
        {
            "category":"Food & Beverages",
            "subcategory":"Bakery",
            "type":"Retail Goods"
        }
    ],
    "sg:phone":"+1   ",
    "sg:postcode":"08226",
    "sg:province":"NJ",
    "wof:name":"Dots Pastry Shop",
    "wof:placetype":"venue"
},
  "geometry": {"coordinates":[-74.607772,39.254229],"type":"Point"}
}