{
  "type": "Feature",
  "properties": {
    "iso:country":"US",
    "sg:address":"1200 Highland Dr",
    "sg:city":"Mount Holly",
    "sg:classifiers":[
        {
            "category":"Wholesale",
            "subcategory":"Stationery",
            "type":"Manufacturing & Wholesale Goods"
        }
    ],
    "sg:phone":"+1 609 518 9700",
    "sg:postcode":"08060",
    "sg:province":"NJ",
    "sg:tags":[
        "product",
        "paper"
    ],
    "wof:name":"Central Lewmar",
    "wof:placetype":"venue"
},
  "geometry": {"coordinates":[-74.86165699999999,40.002531],"type":"Point"}
}