{
  "type": "Feature",
  "properties": {
    "iso:country":"US",
    "sg:address":"449 Market St",
    "sg:city":"Saddle Brook",
    "sg:classifiers":[
        {
            "category":"Health Services",
            "subcategory":"Doctor",
            "type":"Services"
        }
    ],
    "sg:phone":"+1 201 843 7942",
    "sg:postcode":"07663",
    "sg:province":"NJ",
    "wof:name":"Maggio B E DO",
    "wof:placetype":"venue"
},
  "geometry": {"coordinates":[-74.099701,40.897202],"type":"Point"}
}