{
  "type": "Feature",
  "properties": {
    "addr:full":"1340 US Hwy 206 Skillman NJ 08558",
    "addr:housenumber":"1340",
    "addr:postcode":"08558",
    "addr:street":"Us Hwy 206",
    "iso:country":"US",
    "sg:address":"1340 US Hwy 206",
    "sg:city":"Skillman",
    "sg:classifiers":[
        {
            "category":"Shopping",
            "subcategory":"Computers & Home Electronics",
            "type":"Retail Goods"
        }
    ],
    "sg:phone":"+1 609 681 1120",
    "sg:postcode":"08558",
    "sg:province":"NJ",
    "sg:tags":[
        "equipment",
        "dealer"
    ],
    "wof:name":"Princeton Computers Inc",
    "wof:placetype":"venue"
},
  "geometry": {"coordinates":[-74.64955999999999,40.403062],"type":"Point"}
}