{
  "type": "Feature",
  "properties": {
    "iso:country":"US",
    "sg:address":"76 Valley Rd",
    "sg:city":"Haworth",
    "sg:classifiers":[
        {
            "category":"Health Services",
            "subcategory":"Doctor",
            "type":"Services"
        }
    ],
    "sg:phone":"+1   ",
    "sg:postcode":"07641",
    "sg:province":"NJ",
    "sg:tags":[
        "medical"
    ],
    "wof:name":"M Kahn MD",
    "wof:placetype":"venue"
},
  "geometry": {"coordinates":[-73.986531,40.954743],"type":"Point"}
}