{
  "type": "Feature",
  "properties": {
    "iso:country":"US",
    "sg:address":"219 US Hwy 206",
    "sg:city":"Andover",
    "sg:classifiers":[
        {
            "category":"Building & Trades",
            "subcategory":"Plumbing",
            "type":"Services"
        }
    ],
    "sg:phone":"+1 973 786 7179",
    "sg:postcode":"07821",
    "sg:province":"NJ",
    "sg:tags":[
        "contractor"
    ],
    "wof:name":"W P Ducts",
    "wof:placetype":"venue"
},
  "geometry": {"coordinates":[-74.731821,40.947771],"type":"Point"}
}