{
  "type": "Feature",
  "properties": {
    "iso:country":"US",
    "sg:address":"45 State Rte 36",
    "sg:city":"Eatontown",
    "sg:classifiers":[
        {
            "category":"Shopping",
            "subcategory":"Clothing, Apparel, & Fashions",
            "type":"Retail Goods"
        }
    ],
    "sg:phone":"+1 732 542 7494",
    "sg:postcode":"07724",
    "sg:province":"NJ",
    "sg:tags":[
        "furnishing"
    ],
    "wof:name":"Men's Wearhouse",
    "wof:placetype":"venue"
},
  "geometry": {"coordinates":[-74.048152,40.291304],"type":"Point"}
}