{
  "type": "Feature",
  "properties": {
    "addr:full":"311 Enterprise Dr Plainsboro NJ 08536",
    "addr:housenumber":"311",
    "addr:postcode":"08536",
    "addr:street":"Enterprise Dr",
    "iso:country":"US",
    "sg:address":"311 Enterprise Dr",
    "sg:city":"Plainsboro",
    "sg:classifiers":[
        {
            "category":"Manufacturing",
            "subcategory":"Paper Products",
            "type":"Manufacturing & Wholesale Goods"
        }
    ],
    "sg:phone":"+1 201 936 9210",
    "sg:postcode":"08536",
    "sg:province":"NJ",
    "sg:tags":[
        "sanitary",
        "mfg"
    ],
    "wof:name":"Johnson & Johnson",
    "wof:placetype":"venue"
},
  "geometry": {"coordinates":[-74.584507,40.329575],"type":"Point"}
}