{
  "type": "Feature",
  "properties": {
    "addr:full":"464 S Green St Tuckerton NJ 08087",
    "addr:housenumber":"464",
    "addr:postcode":"08087",
    "addr:street":"S Green St",
    "iso:country":"US",
    "sg:address":"464 S Green St",
    "sg:city":"Tuckerton",
    "sg:classifiers":[
        {
            "category":"Recreation",
            "subcategory":"Marina",
            "type":"Entertainment"
        }
    ],
    "sg:phone":"+1 609 296 1820",
    "sg:postcode":"08087",
    "sg:province":"NJ",
    "sg:tags":[
        "repair",
        "boat"
    ],
    "wof:name":"Tuckerton Marine Servicenter",
    "wof:placetype":"venue"
},
  "geometry": {"coordinates":[-74.338964,39.589759],"type":"Point"}
}