{
  "type": "Feature",
  "properties": {
    "addr:full":"17 Allocco Dr Holmdel NJ 07733",
    "addr:housenumber":"17",
    "addr:postcode":"07733",
    "addr:street":"Allocco Dr",
    "iso:country":"US",
    "sg:address":"17 Allocco Dr",
    "sg:city":"Holmdel",
    "sg:classifiers":[
        {
            "category":"Professional",
            "subcategory":"Business Services",
            "type":"Services"
        }
    ],
    "sg:phone":"+1   ",
    "sg:postcode":"07733",
    "sg:province":"NJ",
    "wof:name":"Golden Apple Enterprise",
    "wof:placetype":"venue"
},
  "geometry": {"coordinates":[-74.17576800000001,40.399778],"type":"Point"}
}