{
  "type": "Feature",
  "properties": {
    "addr:full":"1515 State Rte 36 Union Beach NJ 07735",
    "addr:housenumber":"1515",
    "addr:postcode":"07735",
    "addr:street":"State Rte 36",
    "iso:country":"US",
    "sg:address":"1515 State Rte 36",
    "sg:city":"Union Beach",
    "sg:classifiers":[
        {
            "category":"Professional",
            "type":"Services"
        },
        {
            "category":"Manufacturing",
            "subcategory":"Chemicals & Compounds",
            "type":"Manufacturing & Wholesale Goods"
        }
    ],
    "sg:phone":"+1 732 264 8250",
    "sg:postcode":"07735",
    "sg:province":"NJ",
    "sg:tags":[
        "establishment",
        "prep",
        "perfume"
    ],
    "wof:name":"International Flavors & Frgncs",
    "wof:placetype":"venue"
},
  "geometry": {"coordinates":[-74.15580799999999,40.438466],"type":"Point"}
}