{
  "type": "Feature",
  "properties": {
    "iso:country":"US",
    "sg:address":"29 N Newton Ave",
    "sg:city":"Atlantic City",
    "sg:classifiers":[
        {
            "category":"Organizations",
            "subcategory":"Religious Organization",
            "type":"Services"
        }
    ],
    "sg:phone":"+1 609 340 8628",
    "sg:postcode":"08401",
    "sg:province":"NJ",
    "sg:tags":[
        "clergy"
    ],
    "wof:name":"Noemi R Perez Rev",
    "wof:placetype":"venue"
},
  "geometry": {"coordinates":[-74.46675999999999,39.346879],"type":"Point"}
}