{
  "type": "Feature",
  "properties": {
    "addr:full":"6025 Westfield Ave Ste B Pennsauken NJ 08110",
    "addr:housenumber":"6025",
    "addr:postcode":"08110",
    "addr:street":"Westfield Ave Ste B",
    "iso:country":"US",
    "sg:address":"6025 Westfield Ave Ste B",
    "sg:city":"Pennsauken",
    "sg:classifiers":[
        {
            "category":"Personal",
            "subcategory":"Nail Salon",
            "type":"Services"
        }
    ],
    "sg:phone":"+1 856 661 9090",
    "sg:postcode":"08110",
    "sg:province":"NJ",
    "wof:name":"Diana's Beauty Salon",
    "wof:placetype":"venue"
},
  "geometry": {"coordinates":[-75.059539,39.962523],"type":"Point"}
}