{
  "type": "Feature",
  "properties": {
    "addr:full":"200 Plaza Dr Secaucus NJ 07094",
    "addr:housenumber":"200",
    "addr:postcode":"07094",
    "addr:street":"Plaza Dr",
    "iso:country":"US",
    "sg:address":"200 Plaza Dr",
    "sg:city":"Secaucus",
    "sg:classifiers":[
        {
            "category":"Banks & Credit Unions",
            "subcategory":"Investment Brokerage",
            "type":"Services"
        }
    ],
    "sg:phone":"+1   ",
    "sg:postcode":"07094",
    "sg:province":"NJ",
    "sg:tags":[
        "security"
    ],
    "wof:name":"Axa Financial Inc",
    "wof:placetype":"venue"
},
  "geometry": {"coordinates":[-74.04295500000001,40.786687],"type":"Point"}
}