{
  "type": "Feature",
  "properties": {
    "iso:country":"US",
    "sg:address":"1832 S Black Horse Pike",
    "sg:city":"Williamstown",
    "sg:classifiers":[
        {
            "category":"Home & Garden",
            "subcategory":"Building Materials",
            "type":"Retail Goods"
        }
    ],
    "sg:phone":"+1 856 794 9191",
    "sg:postcode":"08094",
    "sg:province":"NJ",
    "sg:tags":[
        "windows"
    ],
    "wof:name":"Westergaard Construction",
    "wof:placetype":"venue"
},
  "geometry": {"coordinates":[-74.963607,39.661041],"type":"Point"}
}