{
  "type": "Feature",
  "properties": {
    "addr:full":"20 Louisa Ct Wayne NJ 07470",
    "addr:housenumber":"20",
    "addr:postcode":"07470",
    "addr:street":"Louisa Ct",
    "iso:country":"US",
    "sg:address":"20 Louisa Ct",
    "sg:city":"Wayne",
    "sg:classifiers":[
        {
            "category":"Building & Trades",
            "subcategory":"Cleaning & Sanitation",
            "type":"Services"
        },
        {
            "category":"Retail",
            "subcategory":"Repair Shop",
            "type":"Services"
        }
    ],
    "sg:phone":"+1 973 389 1055",
    "sg:postcode":"07470",
    "sg:province":"NJ",
    "sg:tags":[
        "repairing",
        "window",
        "shades"
    ],
    "wof:name":"Mary Ellen's Blind Cleaning",
    "wof:placetype":"venue"
},
  "geometry": {"coordinates":[-74.223073,40.925356],"type":"Point"}
}