{
  "type": "Feature",
  "properties": {
    "addr:full":"106 Ct House S Dennis Rd Cape May Court House NJ 08210",
    "addr:postcode":"nj 08210",
    "addr:street":"106 Ct House S Dennis Rd",
    "iso:country":"US",
    "sg:address":"106 Ct House S Dennis Rd",
    "sg:city":"Cape May Court House",
    "sg:classifiers":[
        {
            "category":"Health Services",
            "subcategory":"Hospital",
            "type":"Services"
        }
    ],
    "sg:phone":"+1 609 465 0300",
    "sg:postcode":"08210",
    "sg:province":"NJ",
    "wof:name":"Wills Eye Surgical Network",
    "wof:placetype":"venue"
},
  "geometry": {"coordinates":[-74.818703,39.090401],"type":"Point"}
}