{
  "type": "Feature",
  "properties": {
    "iso:country":"US",
    "sg:address":"1001 E Brigantine Ave",
    "sg:city":"Brigantine",
    "sg:classifiers":[
        {
            "category":"Freight",
            "type":"Transportation"
        }
    ],
    "sg:phone":"+1 609 266 1400",
    "sg:postcode":"08203",
    "sg:province":"NJ",
    "sg:tags":[
        "operator",
        "local",
        "trucking"
    ],
    "wof:name":"Kan Kan Girls",
    "wof:placetype":"venue"
},
  "geometry": {"coordinates":[-74.356357,39.412833],"type":"Point"}
}