{
  "type": "Feature",
  "properties": {
    "iso:country":"US",
    "sg:address":"1232 Barnesdale Ct",
    "sg:city":"Woodbury",
    "sg:classifiers":[
        {
            "category":"Building & Trades",
            "subcategory":"Pest Control",
            "type":"Services"
        }
    ],
    "sg:phone":"+1 856 251 0064",
    "sg:postcode":"08096",
    "sg:province":"NJ",
    "wof:name":"Brothers Exterminating",
    "wof:placetype":"venue"
},
  "geometry": {"coordinates":[-75.17925700000001,39.829064],"type":"Point"}
}