{
  "type": "Feature",
  "properties": {
    "iso:country":"US",
    "sg:address":"195 US Hwy 46",
    "sg:city":"Mine Hill",
    "sg:classifiers":[
        {
            "category":"Health Services",
            "subcategory":"Doctor",
            "type":"Services"
        }
    ],
    "sg:phone":"+1 973 328 7772",
    "sg:postcode":"07803",
    "sg:province":"NJ",
    "sg:tags":[
        "physician",
        "surgeon"
    ],
    "wof:name":"Savitri Sundaram MD",
    "wof:placetype":"venue"
},
  "geometry": {"coordinates":[-74.54992799999999,40.888621],"type":"Point"}
}