{
  "type": "Feature",
  "properties": {
    "addr:full":"940 Easton Ave Somerset NJ 08873",
    "addr:housenumber":"940",
    "addr:postcode":"08873",
    "addr:street":"Easton Ave",
    "iso:country":"US",
    "sg:address":"940 Easton Ave",
    "sg:city":"Somerset",
    "sg:classifiers":[
        {
            "category":"Restaurant",
            "type":"Food & Drink"
        }
    ],
    "sg:phone":"+1   ",
    "sg:postcode":"08873",
    "sg:province":"NJ",
    "sg:tags":[
        "eating"
    ],
    "wof:name":"Burger King",
    "wof:placetype":"venue"
},
  "geometry": {"coordinates":[-74.48545,40.512526],"type":"Point"}
}