{
  "type": "Feature",
  "properties": {
    "addr:full":"560 60th St West New York NJ 07093",
    "addr:housenumber":"560",
    "addr:postcode":"nj 07093",
    "addr:street":"60Th St West",
    "iso:country":"US",
    "sg:address":"560 60th St",
    "sg:city":"West New York",
    "sg:classifiers":[
        {
            "category":"Real Estate",
            "subcategory":"Real Estate Agent",
            "type":"Services"
        }
    ],
    "sg:phone":"+1 201 854 4000",
    "sg:postcode":"07093",
    "sg:province":"NJ",
    "wof:name":"Hernandez Realty",
    "wof:placetype":"venue"
},
  "geometry": {"coordinates":[-74.017544,40.789503],"type":"Point"}
}