{
  "type": "Feature",
  "properties": {
    "addr:full":"263 Hackensack St Wood-Ridge NJ 07075",
    "addr:housenumber":"263",
    "addr:postcode":"07075",
    "addr:street":"Hackensack St",
    "iso:country":"US",
    "sg:address":"263 Hackensack St",
    "sg:city":"Wood-Ridge",
    "sg:classifiers":[
        {
            "category":"Shopping",
            "subcategory":"Clothing, Apparel, & Fashions",
            "type":"Retail Goods"
        }
    ],
    "sg:phone":"+1   ",
    "sg:postcode":"07075",
    "sg:province":"NJ",
    "wof:name":"Karens Dancewear Plus Inc",
    "wof:placetype":"venue"
},
  "geometry": {"coordinates":[-74.08079600000001,40.848735],"type":"Point"}
}