{
  "type": "Feature",
  "properties": {
    "iso:country":"US",
    "sg:address":"8 Stony Rd",
    "sg:city":"Edison",
    "sg:classifiers":[
        {
            "category":"Retail",
            "subcategory":"Auto Rental",
            "type":"Services"
        }
    ],
    "sg:phone":"+1   ",
    "sg:postcode":"08817",
    "sg:province":"NJ",
    "sg:tags":[
        "passenger",
        "car"
    ],
    "wof:name":"Wilsons Messenger",
    "wof:placetype":"venue"
},
  "geometry": {"coordinates":[-74.399688,40.51639],"type":"Point"}
}