{
  "type": "Feature",
  "properties": {
    "iso:country":"US",
    "sg:address":"761 Americana Ct",
    "sg:city":"Toms River",
    "sg:classifiers":[
        {
            "category":"Building & Trades",
            "subcategory":"Construction",
            "type":"Services"
        }
    ],
    "sg:phone":"+1 732 929 3065",
    "sg:postcode":"08753",
    "sg:province":"NJ",
    "sg:tags":[
        "house"
    ],
    "wof:name":"S Carter Construction LLC",
    "wof:placetype":"venue"
},
  "geometry": {"coordinates":[-74.147459,39.967702],"type":"Point"}
}