{
  "type": "Feature",
  "properties": {
    "iso:country":"US",
    "sg:address":"651 John F Kennedy Way",
    "sg:city":"Willingboro",
    "sg:classifiers":[
        {
            "category":"Health Services",
            "subcategory":"Doctor",
            "type":"Services"
        }
    ],
    "sg:phone":"+1 609 871 7070",
    "sg:postcode":"08046",
    "sg:province":"NJ",
    "sg:tags":[
        "cardiologist"
    ],
    "wof:name":"Kimmel Bruce M MD",
    "wof:placetype":"venue"
},
  "geometry": {"coordinates":[-74.87809799999999,40.043301],"type":"Point"}
}