{
  "type": "Feature",
  "properties": {
    "addr:full":"429 Atlantic Ave Trenton NJ 08629",
    "addr:housenumber":"429",
    "addr:postcode":"08629",
    "addr:street":"Atlantic Ave",
    "iso:country":"US",
    "sg:address":"429 Atlantic Ave",
    "sg:city":"Trenton",
    "sg:classifiers":[
        {
            "category":"Food & Beverages",
            "subcategory":"Groceries & Convenience Stores",
            "type":"Retail Goods"
        }
    ],
    "sg:phone":"+1   ",
    "sg:postcode":"08629",
    "sg:province":"NJ",
    "wof:name":"Dinis Deli Mart",
    "wof:placetype":"venue"
},
  "geometry": {"coordinates":[-74.730178,40.225593],"type":"Point"}
}