{
  "type": "Feature",
  "properties": {
    "iso:country":"US",
    "sg:address":"32 Brookside Ave",
    "sg:city":"Demarest",
    "sg:classifiers":[
        {
            "category":"Retail",
            "subcategory":"Laundry & Dry Cleaning",
            "type":"Services"
        }
    ],
    "sg:phone":"+1 201 784 0962",
    "sg:postcode":"07627",
    "sg:province":"NJ",
    "sg:tags":[
        "drycleaning",
        "plant"
    ],
    "wof:name":"No 1 Cleaners",
    "wof:placetype":"venue"
},
  "geometry": {"coordinates":[-73.96867399999999,40.954631],"type":"Point"}
}