{
  "type": "Feature",
  "properties": {
    "addr:full":"165 White Horse Pike Clementon NJ 08021",
    "addr:housenumber":"165",
    "addr:postcode":"08021",
    "addr:street":"White Horse Pike",
    "iso:country":"US",
    "sg:address":"165 White Horse Pike",
    "sg:city":"Clementon",
    "sg:classifiers":[
        {
            "category":"Shopping",
            "subcategory":"Discount & Variety Stores",
            "type":"Retail Goods"
        }
    ],
    "sg:phone":"+1   ",
    "sg:postcode":"08021",
    "sg:province":"NJ",
    "wof:name":"Big Lots",
    "wof:placetype":"venue"
},
  "geometry": {"coordinates":[-74.980642,39.810482],"type":"Point"}
}