{
  "type": "Feature",
  "properties": {
    "iso:country":"US",
    "sg:address":"795 Brick Blvd",
    "sg:city":"Brick",
    "sg:classifiers":[
        {
            "category":"Home & Garden",
            "subcategory":"Furniture",
            "type":"Retail Goods"
        }
    ],
    "sg:phone":"+1   ",
    "sg:postcode":"08723",
    "sg:province":"NJ",
    "sg:tags":[
        "store"
    ],
    "wof:name":"Dinette World Inc",
    "wof:placetype":"venue"
},
  "geometry": {"coordinates":[-74.136,40.063956],"type":"Point"}
}