{
  "type": "Feature",
  "properties": {
    "iso:country":"US",
    "sg:address":"42 Stony Ridge Dr",
    "sg:city":"Hillsdale",
    "sg:classifiers":[
        {
            "category":"Professional",
            "subcategory":"Business Services",
            "type":"Services"
        }
    ],
    "sg:phone":"+1   ",
    "sg:postcode":"07642",
    "sg:province":"NJ",
    "wof:name":"Frank Ferrante Inc",
    "wof:placetype":"venue"
},
  "geometry": {"coordinates":[-74.06047100000001,41.009163],"type":"Point"}
}