{
  "type": "Feature",
  "properties": {
    "addr:full":"1325 Warren Ave Spring Lake NJ 07762",
    "addr:housenumber":"1325",
    "addr:postcode":"07762",
    "addr:street":"Warren Ave",
    "iso:country":"US",
    "sg:address":"1325 Warren Ave",
    "sg:city":"Spring Lake",
    "sg:classifiers":[
        {
            "category":"Banks & Credit Unions",
            "subcategory":"Investment Brokerage",
            "type":"Services"
        }
    ],
    "sg:phone":"+1 732 449 3711",
    "sg:postcode":"07762",
    "sg:province":"NJ",
    "sg:tags":[
        "management"
    ],
    "wof:name":"Midatlantic Wealth Management",
    "wof:placetype":"venue"
},
  "geometry": {"coordinates":[-74.05058099999999,40.152837],"type":"Point"}
}