{
  "type": "Feature",
  "properties": {
    "addr:full":"44 S Clinton Ave Trenton NJ 08609",
    "addr:housenumber":"44",
    "addr:postcode":"08609",
    "addr:street":"S Clinton Ave",
    "iso:country":"US",
    "sg:address":"44 S Clinton Ave",
    "sg:city":"Trenton",
    "sg:classifiers":[
        {
            "category":"Manufacturing",
            "subcategory":"Printing",
            "type":"Manufacturing & Wholesale Goods"
        }
    ],
    "sg:phone":"+1 609 984 6408",
    "sg:postcode":"08609",
    "sg:province":"NJ",
    "sg:tags":[
        "print",
        "shop"
    ],
    "wof:name":"Print Shop",
    "wof:placetype":"venue"
},
  "geometry": {"coordinates":[-74.754963,40.219141],"type":"Point"}
}