{
  "type": "Feature",
  "properties": {
    "iso:country":"US",
    "sg:address":"38 Kirkwood Rd",
    "sg:city":"Gibbsboro",
    "sg:classifiers":[
        {
            "category":"Professional",
            "subcategory":"Lawyer & Legal Services",
            "type":"Services"
        }
    ],
    "sg:phone":"+1 856 309 1234",
    "sg:postcode":"08026",
    "sg:province":"NJ",
    "wof:name":"John F Wilson Esq",
    "wof:placetype":"venue"
},
  "geometry": {"coordinates":[-74.97208000000001,39.837177],"type":"Point"}
}