{
  "type": "Feature",
  "properties": {
    "iso:country":"US",
    "sg:address":"536 21st Ave",
    "sg:city":"Paterson",
    "sg:classifiers":[
        {
            "category":"Restaurant",
            "type":"Food & Drink"
        }
    ],
    "sg:phone":"+1   ",
    "sg:postcode":"07513",
    "sg:province":"NJ",
    "sg:tags":[
        "eating"
    ],
    "wof:name":"Rivero Inc",
    "wof:placetype":"venue"
},
  "geometry": {"coordinates":[-74.15107999999999,40.905929],"type":"Point"}
}