{
  "type": "Feature",
  "properties": {
    "addr:full":"910 N Main St Pleasantville NJ 08232",
    "addr:housenumber":"910",
    "addr:postcode":"08232",
    "addr:street":"N Main St",
    "iso:country":"US",
    "sg:address":"910 N Main St",
    "sg:city":"Pleasantville",
    "sg:classifiers":[
        {
            "category":"Autos & Motor Vehicles",
            "subcategory":"Fuel & Gas Station",
            "type":"Retail Goods"
        }
    ],
    "sg:phone":"+1 609 641 2010",
    "sg:postcode":"08232",
    "sg:province":"NJ",
    "sg:tags":[
        "oil"
    ],
    "wof:name":"Parisi's Sunoco",
    "wof:placetype":"venue"
},
  "geometry": {"coordinates":[-74.511093,39.404338],"type":"Point"}
}