{
  "type": "Feature",
  "properties": {
    "iso:country":"US",
    "sg:address":"121 Warhol Ave",
    "sg:city":"Mahwah",
    "sg:classifiers":[
        {
            "category":"Professional",
            "subcategory":"Computer Services",
            "type":"Services"
        }
    ],
    "sg:phone":"+1   ",
    "sg:postcode":"07430",
    "sg:province":"NJ",
    "sg:tags":[
        "related"
    ],
    "wof:name":"Icon Computer Consultants",
    "wof:placetype":"venue"
},
  "geometry": {"coordinates":[-74.153227,41.101008],"type":"Point"}
}