{
  "type": "Feature",
  "properties": {
    "iso:country":"US",
    "sg:address":"82 E Allendale Rd",
    "sg:city":"Saddle River",
    "sg:classifiers":[
        {
            "category":"Banks & Credit Unions",
            "subcategory":"Investment Brokerage",
            "type":"Services"
        }
    ],
    "sg:phone":"+1 201 236 8151",
    "sg:postcode":"07458",
    "sg:province":"NJ",
    "sg:tags":[
        "consultant",
        "planning",
        "financial"
    ],
    "wof:name":"Royal Alliance Assoc",
    "wof:placetype":"venue"
},
  "geometry": {"coordinates":[-74.095157,41.030913],"type":"Point"}
}