{
  "type": "Feature",
  "properties": {
    "addr:full":"100 Perry St Keyport NJ 07735",
    "addr:housenumber":"100",
    "addr:postcode":"07735",
    "addr:street":"Perry St",
    "iso:country":"US",
    "sg:address":"100 Perry St",
    "sg:city":"Keyport",
    "sg:classifiers":[
        {
            "category":"Professional",
            "type":"Services"
        }
    ],
    "sg:phone":"+1   ",
    "sg:postcode":"07735",
    "sg:province":"NJ",
    "wof:name":"Dimitrios Koufidis",
    "wof:placetype":"venue"
},
  "geometry": {"coordinates":[-74.20343800000001,40.426308],"type":"Point"}
}