{
  "type": "Feature",
  "properties": {
    "iso:country":"US",
    "sg:address":"325 W Clinton St",
    "sg:city":"Dover",
    "sg:classifiers":[
        {
            "category":"Food & Beverages",
            "subcategory":"Liquor & Beverages",
            "type":"Retail Goods"
        }
    ],
    "sg:phone":"+1 973 361 0650",
    "sg:postcode":"07801",
    "sg:province":"NJ",
    "sg:tags":[
        "alcoholic"
    ],
    "wof:name":"Lori's Wine Liquor & Deli",
    "wof:placetype":"venue"
},
  "geometry": {"coordinates":[-74.56636899999999,40.896375],"type":"Point"}
}