{
  "type": "Feature",
  "properties": {
    "addr:full":"330 Washington Ave Carlstadt NJ 07072",
    "addr:housenumber":"330",
    "addr:postcode":"07072",
    "addr:street":"Washington Ave",
    "iso:country":"US",
    "sg:address":"330 Washington Ave",
    "sg:city":"Carlstadt",
    "sg:classifiers":[
        {
            "category":"Professional",
            "subcategory":"Advertising",
            "type":"Services"
        }
    ],
    "sg:phone":"+1 201 508 6000",
    "sg:postcode":"07072",
    "sg:province":"NJ",
    "sg:tags":[
        "datum",
        "management",
        "electronic",
        "representative"
    ],
    "wof:name":"Data Communique Inc",
    "wof:placetype":"venue"
},
  "geometry": {"coordinates":[-74.066231,40.817387],"type":"Point"}
}