{
  "type": "Feature",
  "properties": {
    "addr:full":"14 Francine Pl Millington NJ 07946",
    "addr:housenumber":"14",
    "addr:postcode":"07946",
    "addr:street":"Francine Pl",
    "iso:country":"US",
    "sg:address":"14 Francine Pl",
    "sg:city":"Millington",
    "sg:classifiers":[
        {
            "category":"Professional",
            "type":"Services"
        }
    ],
    "sg:phone":"+1   ",
    "sg:postcode":"07946",
    "sg:province":"NJ",
    "wof:name":"Stefamy Inc",
    "wof:placetype":"venue"
},
  "geometry": {"coordinates":[-74.52598999999999,40.667719],"type":"Point"}
}