{
  "type": "Feature",
  "properties": {
    "iso:country":"US",
    "sg:address":"2330 New Rd",
    "sg:city":"Northfield",
    "sg:classifiers":[
        {
            "category":"Professional",
            "subcategory":"Management & Consulting",
            "type":"Services"
        }
    ],
    "sg:phone":"+1   ",
    "sg:postcode":"08225",
    "sg:province":"NJ",
    "sg:tags":[
        "business"
    ],
    "wof:name":"Powervision LLC",
    "wof:placetype":"venue"
},
  "geometry": {"coordinates":[-74.564244,39.363721],"type":"Point"}
}