{
  "type": "Feature",
  "properties": {
    "iso:country":"US",
    "sg:address":"2 Pemberton Ave",
    "sg:city":"Oceanport",
    "sg:classifiers":[
        {
            "category":"Health Services",
            "subcategory":"Clinic",
            "type":"Services"
        }
    ],
    "sg:phone":"+1 732 544 0864",
    "sg:postcode":"07757",
    "sg:province":"NJ",
    "wof:name":"Oceanport First Aid Squad",
    "wof:placetype":"venue"
},
  "geometry": {"coordinates":[-74.030081,40.312391],"type":"Point"}
}