{
  "type": "Feature",
  "properties": {
    "addr:full":"5 Deerpath Rd Califon NJ 07830",
    "addr:housenumber":"5",
    "addr:postcode":"07830",
    "addr:street":"Deerpath Rd",
    "iso:country":"US",
    "sg:address":"5 Deerpath Rd",
    "sg:city":"Califon",
    "sg:classifiers":[
        {
            "category":"Building & Trades",
            "subcategory":"Cleaning & Sanitation",
            "type":"Services"
        }
    ],
    "sg:phone":"+1 908 832 2273",
    "sg:postcode":"07830",
    "sg:province":"NJ",
    "sg:tags":[
        "snow",
        "removal"
    ],
    "wof:name":"Lawn Care Landscaping",
    "wof:placetype":"venue"
},
  "geometry": {"coordinates":[-74.863345,40.696372],"type":"Point"}
}