{
  "type": "Feature",
  "properties": {
    "iso:country":"US",
    "sg:address":"554 Broadway",
    "sg:city":"Bayonne",
    "sg:classifiers":[
        {
            "category":"Shopping",
            "subcategory":"Clothing, Apparel, & Fashions",
            "type":"Retail Goods"
        }
    ],
    "sg:phone":"+1   ",
    "sg:postcode":"07002",
    "sg:province":"NJ",
    "wof:name":"Mandee 30",
    "wof:placetype":"venue"
},
  "geometry": {"coordinates":[-74.116259,40.666097],"type":"Point"}
}