{
  "type": "Feature",
  "properties": {
    "iso:country":"US",
    "sg:address":"154 Cooper Rd",
    "sg:city":"West Berlin",
    "sg:classifiers":[
        {
            "category":"Building & Trades",
            "subcategory":"Construction",
            "type":"Services"
        }
    ],
    "sg:phone":"+1 856 719 1001",
    "sg:postcode":"08091",
    "sg:province":"NJ",
    "sg:tags":[
        "repairing",
        "remodeling",
        "contractor"
    ],
    "wof:name":"Restoration Management Inc",
    "wof:placetype":"venue"
},
  "geometry": {"coordinates":[-74.92271700000001,39.816312],"type":"Point"}
}