{
  "type": "Feature",
  "properties": {
    "iso:country":"US",
    "sg:address":"1030 Delsea Dr Bldg 8E",
    "sg:city":"Westville",
    "sg:classifiers":[
        {
            "category":"Manufacturing",
            "subcategory":"Tools & Machinery",
            "type":"Manufacturing & Wholesale Goods"
        },
        {
            "category":"Wholesale",
            "subcategory":"Machinery & Supplies",
            "type":"Manufacturing & Wholesale Goods"
        },
        {
            "category":"Building & Trades",
            "subcategory":"Equipment Rental",
            "type":"Services"
        }
    ],
    "sg:phone":"+1 856 848 5480",
    "sg:postcode":"08093",
    "sg:province":"NJ",
    "sg:tags":[
        "pump",
        "hydraulic"
    ],
    "wof:name":"Technol Inc",
    "wof:placetype":"venue"
},
  "geometry": {"coordinates":[-75.125153,39.857491],"type":"Point"}
}