{
  "type": "Feature",
  "properties": {
    "addr:full":"140 Prospect Ave Ste 1 Hackensack NJ 07601",
    "addr:housenumber":"140",
    "addr:postcode":"07601",
    "addr:street":"Prospect Ave Ste 1",
    "iso:country":"US",
    "sg:address":"140 Prospect Ave Ste 1",
    "sg:city":"Hackensack",
    "sg:classifiers":[
        {
            "category":"Health Services",
            "subcategory":"Dentist",
            "type":"Services"
        }
    ],
    "sg:phone":"+1 201 343 8090",
    "sg:postcode":"07601",
    "sg:province":"NJ",
    "wof:name":"Weiss Richard DMD",
    "wof:placetype":"venue"
},
  "geometry": {"coordinates":[-74.056,40.887798],"type":"Point"}
}