{
  "type": "Feature",
  "properties": {
    "iso:country":"US",
    "sg:address":"50 Olmstead Rd",
    "sg:city":"Morristown",
    "sg:classifiers":[
        {
            "category":"Professional",
            "subcategory":"Computer Services",
            "type":"Services"
        }
    ],
    "sg:phone":"+1 973 267 0088",
    "sg:postcode":"07960",
    "sg:province":"NJ",
    "sg:tags":[
        "designer"
    ],
    "wof:name":"Microcomputer Consulting Group",
    "wof:placetype":"venue"
},
  "geometry": {"coordinates":[-74.457145,40.795413],"type":"Point"}
}