{
  "type": "Feature",
  "properties": {
    "addr:full":"1050 Wall St W Lyndhurst NJ 07071",
    "addr:housenumber":"1050",
    "addr:postcode":"07071",
    "addr:street":"Wall St W",
    "iso:country":"US",
    "sg:address":"1050 Wall St W",
    "sg:city":"Lyndhurst",
    "sg:classifiers":[
        {
            "category":"Bars & Pubs",
            "type":"Food & Drink"
        },
        {
            "category":"Restaurant",
            "type":"Food & Drink"
        }
    ],
    "sg:phone":"+1 201 939 4889",
    "sg:postcode":"07071",
    "sg:province":"NJ",
    "sg:tags":[
        "traditional",
        "american"
    ],
    "wof:name":"Whiskey Cafe",
    "wof:placetype":"venue"
},
  "geometry": {"coordinates":[-74.105003,40.8069],"type":"Point"}
}