{
  "type": "Feature",
  "properties": {
    "addr:full":"715 Cranbury Cross Rd North Brunswick NJ 08902",
    "addr:housenumber":"715",
    "addr:postcode":"08902",
    "addr:street":"Cranbury Cross Rd",
    "iso:country":"US",
    "sg:address":"715 Cranbury Cross Rd",
    "sg:city":"North Brunswick",
    "sg:classifiers":[
        {
            "category":"Health Services",
            "subcategory":"Hospital",
            "type":"Services"
        }
    ],
    "sg:phone":"+1 732 321 7173",
    "sg:postcode":"08902",
    "sg:province":"NJ",
    "sg:tags":[
        "general"
    ],
    "wof:name":"Angelina B Decapua",
    "wof:placetype":"venue"
},
  "geometry": {"coordinates":[-74.459329,40.465038],"type":"Point"}
}