{
  "type": "Feature",
  "properties": {
    "addr:full":"465 Bloomfield Ave Bloomfield NJ 07003",
    "addr:housenumber":"465",
    "addr:postcode":"07003",
    "addr:street":"Bloomfield Ave",
    "iso:country":"US",
    "sg:address":"465 Bloomfield Ave",
    "sg:city":"Bloomfield",
    "sg:classifiers":[
        {
            "category":"Sports & Exercise",
            "subcategory":"Gym",
            "type":"Entertainment"
        }
    ],
    "sg:phone":"+1 973 743 7900",
    "sg:postcode":"07003",
    "sg:province":"NJ",
    "sg:tags":[
        "gymnasium"
    ],
    "sg:website":"www.powerhousegym.com",
    "wof:name":"Powerhouse Gym",
    "wof:placetype":"venue"
},
  "geometry": {"coordinates":[-74.19553000000001,40.790212],"type":"Point"}
}