{
  "type": "Feature",
  "properties": {
    "iso:country":"US",
    "sg:address":"1455 Oak Tree Dr",
    "sg:city":"North Brunswick",
    "sg:classifiers":[
        {
            "category":"Building & Trades",
            "subcategory":"Construction",
            "type":"Services"
        }
    ],
    "sg:phone":"+1 732 545 4285",
    "sg:postcode":"08902",
    "sg:province":"NJ",
    "sg:tags":[
        "contractor"
    ],
    "wof:name":"Banjo Kitchen & Bath",
    "wof:placetype":"venue"
},
  "geometry": {"coordinates":[-74.49158,40.471891],"type":"Point"}
}