{
  "type": "Feature",
  "properties": {
    "addr:full":"575 Boulevard Kenilworth NJ 07033",
    "addr:housenumber":"575",
    "addr:postcode":"07033",
    "addr:street":"Boulevard",
    "iso:country":"US",
    "sg:address":"575 Boulevard",
    "sg:city":"Kenilworth",
    "sg:classifiers":[
        {
            "category":"Government",
            "subcategory":"Office",
            "type":"Public Place"
        }
    ],
    "sg:phone":"+1 908 276 2740",
    "sg:postcode":"07033",
    "sg:province":"NJ",
    "sg:tags":[
        "health",
        "program",
        "administrative"
    ],
    "sg:website":"http://www.kenilworthnj.org",
    "wof:name":"Kenilworth Health Dept",
    "wof:placetype":"venue"
},
  "geometry": {"coordinates":[-74.28945,40.67628],"type":"Point"}
}