{
  "type": "Feature",
  "properties": {
    "addr:full":"19 W Hudson Ave Englewood NJ 07631",
    "addr:housenumber":"19",
    "addr:postcode":"07631",
    "addr:street":"W Hudson Ave",
    "iso:country":"US",
    "sg:address":"19 W Hudson Ave",
    "sg:city":"Englewood",
    "sg:classifiers":[
        {
            "category":"Shopping",
            "subcategory":"Clothing, Apparel, & Fashions",
            "type":"Retail Goods"
        }
    ],
    "sg:phone":"+1   ",
    "sg:postcode":"07631",
    "sg:province":"NJ",
    "wof:name":"Joy",
    "wof:placetype":"venue"
},
  "geometry": {"coordinates":[-73.96896599999999,40.91033],"type":"Point"}
}