{
  "type": "Feature",
  "properties": {
    "iso:country":"US",
    "sg:address":"510 Bridge Plaza Dr",
    "sg:city":"Englishtown",
    "sg:classifiers":[
        {
            "category":"Health Services",
            "subcategory":"Doctor",
            "type":"Services"
        }
    ],
    "sg:phone":"+1 732 536 5552",
    "sg:postcode":"07726",
    "sg:province":"NJ",
    "sg:tags":[
        "physician",
        "surgeon"
    ],
    "wof:name":"Women's Physicians & Surgeons",
    "wof:placetype":"venue"
},
  "geometry": {"coordinates":[-74.31998299999999,40.337237],"type":"Point"}
}