{
  "type": "Feature",
  "properties": {
    "addr:full":"46 Outlook Ave Budd Lake NJ 07828",
    "addr:housenumber":"46",
    "addr:postcode":"07828",
    "addr:street":"Outlook Ave",
    "iso:country":"US",
    "sg:address":"46 Outlook Ave",
    "sg:city":"Budd Lake",
    "sg:classifiers":[
        {
            "category":"Autos & Motor Vehicles",
            "subcategory":"Fuel & Gas Station",
            "type":"Retail Goods"
        }
    ],
    "sg:phone":"+1   ",
    "sg:postcode":"07828",
    "sg:province":"NJ",
    "sg:tags":[
        "car",
        "station",
        "dealer",
        "used"
    ],
    "wof:name":"D & D Motors",
    "wof:placetype":"venue"
},
  "geometry": {"coordinates":[-74.739177,40.863042],"type":"Point"}
}