{
  "type": "Feature",
  "properties": {
    "iso:country":"US",
    "sg:address":"1271 US Hwy 22",
    "sg:city":"Lebanon",
    "sg:classifiers":[
        {
            "category":"Shopping",
            "subcategory":"Hobbies, Toys, & Games",
            "type":"Retail Goods"
        },
        {
            "category":"Shopping",
            "subcategory":"Gifts & Souvenirs",
            "type":"Retail Goods"
        }
    ],
    "sg:phone":"+1 908 437 6145",
    "sg:postcode":"08833",
    "sg:province":"NJ",
    "sg:tags":[
        "product",
        "ceramic"
    ],
    "wof:name":"Caron Ceramics Inc",
    "wof:placetype":"venue"
},
  "geometry": {"coordinates":[-74.835184,40.643811],"type":"Point"}
}