{
  "type": "Feature",
  "properties": {
    "addr:full":"20 Bartles Corner Rd Flemington NJ 08822",
    "addr:housenumber":"20",
    "addr:postcode":"08822",
    "addr:street":"Bartles Corner Rd",
    "iso:country":"US",
    "sg:address":"20 Bartles Corner Rd",
    "sg:city":"Flemington",
    "sg:classifiers":[
        {
            "category":"Building & Trades",
            "subcategory":"Construction",
            "type":"Services"
        }
    ],
    "sg:phone":"+1   ",
    "sg:postcode":"08822",
    "sg:province":"NJ",
    "sg:tags":[
        "house"
    ],
    "wof:name":"Genesis Building Inc",
    "wof:placetype":"venue"
},
  "geometry": {"coordinates":[-74.856351,40.536419],"type":"Point"}
}