{
  "type": "Feature",
  "properties": {
    "iso:country":"US",
    "sg:address":"1200 US Hwy 22 Alt",
    "sg:city":"Phillipsburg",
    "sg:classifiers":[
        {
            "category":"Shopping",
            "subcategory":"Gifts & Souvenirs",
            "type":"Retail Goods"
        }
    ],
    "sg:phone":"+1   ",
    "sg:postcode":"08865",
    "sg:province":"NJ",
    "sg:tags":[
        "engraving",
        "custom"
    ],
    "wof:name":"Things Remembered",
    "wof:placetype":"venue"
},
  "geometry": {"coordinates":[-75.16809499999999,40.677453],"type":"Point"}
}