{
  "type": "Feature",
  "properties": {
    "addr:full":"1655 N Olden Ave Exd Trenton NJ 08638",
    "addr:housenumber":"1655",
    "addr:postcode":"08638",
    "addr:street":"N Olden Ave Exd",
    "iso:country":"US",
    "sg:address":"1655 N Olden Ave Exd",
    "sg:city":"Trenton",
    "sg:classifiers":[
        {
            "category":"Shopping",
            "subcategory":"Discount & Variety Stores",
            "type":"Retail Goods"
        }
    ],
    "sg:phone":"+1 609 883 4220",
    "sg:postcode":"08638",
    "sg:province":"NJ",
    "sg:tags":[
        "merchandise",
        "general"
    ],
    "wof:name":"Cadillac Authorized Sales",
    "wof:placetype":"venue"
},
  "geometry": {"coordinates":[-74.76273399999999,40.245408],"type":"Point"}
}