{
  "type": "Feature",
  "properties": {
    "iso:country":"US",
    "sg:address":"12 Melody Ln",
    "sg:city":"Middletown",
    "sg:classifiers":[
        {
            "category":"Building & Trades",
            "subcategory":"Plumbing",
            "type":"Services"
        }
    ],
    "sg:phone":"+1 732 671 7919",
    "sg:postcode":"07748",
    "sg:province":"NJ",
    "sg:tags":[
        "contractor"
    ],
    "wof:name":"Bayshore Services",
    "wof:placetype":"venue"
},
  "geometry": {"coordinates":[-74.12291,40.418068],"type":"Point"}
}