{
  "type": "Feature",
  "properties": {
    "addr:full":"1734 State Rte 35 Belmar NJ 07719",
    "addr:housenumber":"1734",
    "addr:postcode":"07719",
    "addr:street":"State Rte 35",
    "iso:country":"US",
    "sg:address":"1734 State Rte 35",
    "sg:city":"Belmar",
    "sg:classifiers":[
        {
            "category":"Autos & Motor Vehicles",
            "subcategory":"Fuel & Gas Station",
            "type":"Retail Goods"
        }
    ],
    "sg:phone":"+1   ",
    "sg:postcode":"07719",
    "sg:province":"NJ",
    "sg:tags":[
        "station",
        "gasoline"
    ],
    "wof:name":"Raj Gas Inc",
    "wof:placetype":"venue"
},
  "geometry": {"coordinates":[-74.04221200000001,40.175665],"type":"Point"}
}