{
  "type": "Feature",
  "properties": {
    "addr:full":"206 Ash Rd Marlton NJ 08053",
    "addr:housenumber":"206",
    "addr:postcode":"08053",
    "addr:street":"Ash Rd",
    "iso:country":"US",
    "sg:address":"206 Ash Rd",
    "sg:city":"Marlton",
    "sg:classifiers":[
        {
            "category":"Building & Trades",
            "subcategory":"Cleaning & Sanitation",
            "type":"Services"
        }
    ],
    "sg:phone":"+1   ",
    "sg:postcode":"08053",
    "sg:province":"NJ",
    "sg:tags":[
        "maintenance"
    ],
    "wof:name":"Cheap Sweep Chimney Clean",
    "wof:placetype":"venue"
},
  "geometry": {"coordinates":[-74.895793,39.809623],"type":"Point"}
}