{
  "type": "Feature",
  "properties": {
    "addr:full":"104 Cedar Row Toms River NJ 08753",
    "addr:housenumber":"104",
    "addr:postcode":"08753",
    "addr:street":"Cedar Row",
    "iso:country":"US",
    "sg:address":"104 Cedar Row",
    "sg:city":"Toms River",
    "sg:classifiers":[
        {
            "category":"Home & Garden",
            "subcategory":"Building Materials",
            "type":"Retail Goods"
        }
    ],
    "sg:phone":"+1 732 573 0375",
    "sg:postcode":"08753",
    "sg:province":"NJ",
    "sg:tags":[
        "door"
    ],
    "wof:name":"Affordable Garage Doors",
    "wof:placetype":"venue"
},
  "geometry": {"coordinates":[-74.202876,39.997499],"type":"Point"}
}