{
  "type": "Feature",
  "properties": {
    "addr:full":"486 Boulevard Kenilworth NJ 07033",
    "addr:housenumber":"486",
    "addr:postcode":"07033",
    "addr:street":"Boulevard",
    "iso:country":"US",
    "sg:address":"486 Boulevard",
    "sg:city":"Kenilworth",
    "sg:classifiers":[
        {
            "category":"Shopping",
            "subcategory":"Department Store",
            "type":"Retail Goods"
        }
    ],
    "sg:phone":"+1 908 272 1099",
    "sg:postcode":"07033",
    "sg:province":"NJ",
    "sg:tags":[
        "shop"
    ],
    "wof:name":"E J Dollar Store",
    "wof:placetype":"venue"
},
  "geometry": {"coordinates":[-74.292422,40.676028],"type":"Point"}
}