{
  "type": "Feature",
  "properties": {
    "addr:full":"1420 E Linden Ave Linden NJ 07036",
    "addr:housenumber":"1420",
    "addr:postcode":"07036",
    "addr:street":"E Linden Ave",
    "iso:country":"US",
    "sg:address":"1420 E Linden Ave",
    "sg:city":"Linden",
    "sg:classifiers":[
        {
            "category":"Wholesale",
            "subcategory":"Furniture",
            "type":"Manufacturing & Wholesale Goods"
        },
        {
            "category":"Wholesale",
            "subcategory":"Durable Goods & Equipment",
            "type":"Manufacturing & Wholesale Goods"
        }
    ],
    "sg:phone":"+1 908 486 5600",
    "sg:postcode":"07036",
    "sg:province":"NJ",
    "sg:tags":[
        "importer"
    ],
    "sg:website":"www.lavitainc.com",
    "wof:name":"La Vita Industries Inc",
    "wof:placetype":"venue"
},
  "geometry": {"coordinates":[-74.231464,40.646482],"type":"Point"}
}