{
  "type": "Feature",
  "properties": {
    "addr:full":"989 Lenox Dr Lawrenceville NJ 08648",
    "addr:housenumber":"989",
    "addr:postcode":"08648",
    "addr:street":"Lenox Dr",
    "iso:country":"US",
    "sg:address":"989 Lenox Dr",
    "sg:city":"Lawrenceville",
    "sg:classifiers":[
        {
            "category":"Banks & Credit Unions",
            "subcategory":"Investment Brokerage",
            "type":"Services"
        }
    ],
    "sg:phone":"+1 609 896 0200",
    "sg:postcode":"08648",
    "sg:province":"NJ",
    "sg:tags":[
        "security",
        "stock",
        "bond"
    ],
    "sg:website":"www.wachoviasec.com",
    "wof:name":"Wachovia Securities LLC",
    "wof:placetype":"venue"
},
  "geometry": {"coordinates":[-74.704882,40.287628],"type":"Point"}
}