{
  "type": "Feature",
  "properties": {
    "iso:country":"US",
    "sg:address":"243 River Rd",
    "sg:city":"Annandale",
    "sg:classifiers":[
        {
            "category":"Professional",
            "type":"Services"
        }
    ],
    "sg:phone":"+1   ",
    "sg:postcode":"08801",
    "sg:province":"NJ",
    "wof:name":"River House 243",
    "wof:placetype":"venue"
},
  "geometry": {"coordinates":[-74.88472,40.575906],"type":"Point"}
}