{
  "type": "Feature",
  "properties": {
    "iso:country":"US",
    "sg:address":"4 Village Mall",
    "sg:city":"Monroe Township",
    "sg:classifiers":[
        {
            "category":"Retail",
            "subcategory":"Photofinishing",
            "type":"Services"
        }
    ],
    "sg:phone":"+1 609 409 2640",
    "sg:postcode":"08831",
    "sg:province":"NJ",
    "sg:tags":[
        "laboratory"
    ],
    "wof:name":"Photos From Marz",
    "wof:placetype":"venue"
},
  "geometry": {"coordinates":[-74.470979,40.34222],"type":"Point"}
}