{
  "type": "Feature",
  "properties": {
    "addr:full":"20 Durand Dr Freehold NJ 07728",
    "addr:housenumber":"20",
    "addr:postcode":"07728",
    "addr:street":"Durand Dr",
    "iso:country":"US",
    "sg:address":"20 Durand Dr",
    "sg:city":"Freehold",
    "sg:classifiers":[
        {
            "category":"Professional",
            "subcategory":"Management & Consulting",
            "type":"Services"
        }
    ],
    "sg:phone":"+1   ",
    "sg:postcode":"07728",
    "sg:province":"NJ",
    "sg:tags":[
        "business"
    ],
    "wof:name":"Information Network Consultant",
    "wof:placetype":"venue"
},
  "geometry": {"coordinates":[-74.237683,40.284955],"type":"Point"}
}