{
  "type": "Feature",
  "properties": {
    "iso:country":"US",
    "sg:address":"49 Ravine Dr",
    "sg:city":"Matawan",
    "sg:classifiers":[
        {
            "category":"Personal",
            "type":"Services"
        }
    ],
    "sg:phone":"+1 732 566 7089",
    "sg:postcode":"07747",
    "sg:province":"NJ",
    "sg:tags":[
        "miscellaneous"
    ],
    "wof:name":"Dave's In Your Home Cooking",
    "wof:placetype":"venue"
},
  "geometry": {"coordinates":[-74.23923000000001,40.41719],"type":"Point"}
}