{
  "type": "Feature",
  "properties": {
    "addr:full":"140 County Rd Tenafly NJ 07670",
    "addr:housenumber":"140",
    "addr:postcode":"07670",
    "addr:street":"County Rd",
    "iso:country":"US",
    "sg:address":"140 County Rd",
    "sg:city":"Tenafly",
    "sg:classifiers":[
        {
            "category":"Professional",
            "type":"Services"
        }
    ],
    "sg:phone":"+1   ",
    "sg:postcode":"07670",
    "sg:province":"NJ",
    "wof:name":"Lifemed",
    "wof:placetype":"venue"
},
  "geometry": {"coordinates":[-73.961268,40.929452],"type":"Point"}
}