{
  "type": "Feature",
  "properties": {
    "addr:full":"11 Debby Ln Warren NJ 07059",
    "addr:housenumber":"11",
    "addr:postcode":"07059",
    "addr:street":"Debby Ln",
    "iso:country":"US",
    "sg:address":"11 Debby Ln",
    "sg:city":"Warren",
    "sg:classifiers":[
        {
            "category":"Professional",
            "subcategory":"Advertising",
            "type":"Services"
        }
    ],
    "sg:phone":"+1 908 903 1010",
    "sg:postcode":"07059",
    "sg:province":"NJ",
    "sg:tags":[
        "industry",
        "health",
        "promotion",
        "for",
        "care"
    ],
    "wof:name":"Orion Associates Inc",
    "wof:placetype":"venue"
},
  "geometry": {"coordinates":[-74.54251499999999,40.637309],"type":"Point"}
}