{
  "type": "Feature",
  "properties": {
    "iso:country":"US",
    "sg:address":"59 Walter Dr",
    "sg:city":"Jackson",
    "sg:classifiers":[
        {
            "category":"Manufacturing",
            "subcategory":"Metals",
            "type":"Manufacturing & Wholesale Goods"
        },
        {
            "category":"Retail",
            "subcategory":"Repair Shop",
            "type":"Services"
        }
    ],
    "sg:phone":"+1 732 928 2327",
    "sg:postcode":"08527",
    "sg:province":"NJ",
    "sg:tags":[
        "structural",
        "fabrication",
        "welding"
    ],
    "wof:name":"B Johnson Welding Service",
    "wof:placetype":"venue"
},
  "geometry": {"coordinates":[-74.366603,40.109337],"type":"Point"}
}