{
  "type": "Feature",
  "properties": {
    "addr:full":"1304 Aaron Rd North Brunswick NJ 08902",
    "addr:housenumber":"1304",
    "addr:postcode":"08902",
    "addr:street":"Aaron Rd",
    "iso:country":"US",
    "sg:address":"1304 Aaron Rd",
    "sg:city":"North Brunswick",
    "sg:classifiers":[
        {
            "category":"Insurance",
            "subcategory":"Life Insurance",
            "type":"Services"
        }
    ],
    "sg:phone":"+1   ",
    "sg:postcode":"08902",
    "sg:province":"NJ",
    "sg:tags":[
        "carrier",
        "carrie"
    ],
    "wof:name":"Gregg Astel Associates",
    "wof:placetype":"venue"
},
  "geometry": {"coordinates":[-74.51825599999999,40.44475],"type":"Point"}
}