{
  "type": "Feature",
  "properties": {
    "addr:full":"7714 Bergenline Ave North Bergen NJ 07047",
    "addr:housenumber":"7714",
    "addr:postcode":"07047",
    "addr:street":"Bergenline Ave",
    "iso:country":"US",
    "sg:address":"7714 Bergenline Ave",
    "sg:city":"North Bergen",
    "sg:classifiers":[
        {
            "category":"Bakery",
            "type":"Food & Drink"
        }
    ],
    "sg:phone":"+1 201 869 9868",
    "sg:postcode":"07047",
    "sg:province":"NJ",
    "sg:website":"www.losandesbakery.com",
    "wof:name":"Los Andes Bakery",
    "wof:placetype":"venue"
},
  "geometry": {"coordinates":[-74.007401,40.800598],"type":"Point"}
}