{
  "type": "Feature",
  "properties": {
    "iso:country":"US",
    "sg:address":"147 Kings Hwy",
    "sg:city":"Middletown",
    "sg:classifiers":[
        {
            "category":"Education",
            "subcategory":"School",
            "type":"Public Place"
        }
    ],
    "sg:phone":"+1 732 671 0267",
    "sg:postcode":"07748",
    "sg:province":"NJ",
    "sg:tags":[
        "executive"
    ],
    "wof:name":"Middletown Village Elementary",
    "wof:placetype":"venue"
},
  "geometry": {"coordinates":[-74.122434,40.394838],"type":"Point"}
}