{
  "type": "Feature",
  "properties": {
    "iso:country":"US",
    "sg:address":"1245 Paterson Plank Rd",
    "sg:city":"Secaucus",
    "sg:classifiers":[
        {
            "category":"Retail",
            "subcategory":"Funeral Services",
            "type":"Services"
        }
    ],
    "sg:phone":"+1 201 865 2250",
    "sg:postcode":"07094",
    "sg:province":"NJ",
    "sg:tags":[
        "director"
    ],
    "wof:name":"Mack Memorial Home",
    "wof:placetype":"venue"
},
  "geometry": {"coordinates":[-74.05676099999999,40.789452],"type":"Point"}
}