{
  "type": "Feature",
  "properties": {
    "addr:full":"630 1st Ave Elizabeth NJ 07206",
    "addr:housenumber":"630",
    "addr:postcode":"07206",
    "addr:street":"1St Ave",
    "iso:country":"US",
    "sg:address":"630 1st Ave",
    "sg:city":"Elizabeth",
    "sg:classifiers":[
        {
            "category":"Organizations",
            "subcategory":"Religious Organization",
            "type":"Services"
        }
    ],
    "sg:phone":"+1   ",
    "sg:postcode":"07206",
    "sg:province":"NJ",
    "wof:name":"Buenas Nuevas Calvary Chapel",
    "wof:placetype":"venue"
},
  "geometry": {"coordinates":[-74.201769,40.656832],"type":"Point"}
}