{
  "type": "Feature",
  "properties": {
    "iso:country":"US",
    "sg:address":"41 Watchung Plz Ste 116",
    "sg:city":"Montclair",
    "sg:classifiers":[
        {
            "category":"Building & Trades",
            "subcategory":"Construction",
            "type":"Services"
        }
    ],
    "sg:phone":"+1 201 674 9475",
    "sg:postcode":"07042",
    "sg:province":"NJ",
    "sg:tags":[
        "contractor"
    ],
    "sg:website":"www.montclairgeneralcontractors.com",
    "wof:name":"Montclair General Contractors",
    "wof:placetype":"venue"
},
  "geometry": {"coordinates":[-74.206187,40.830296],"type":"Point"}
}