{
  "type": "Feature",
  "properties": {
    "iso:country":"US",
    "sg:address":"1 Fair Lawn Ave",
    "sg:city":"Fair Lawn",
    "sg:classifiers":[
        {
            "category":"Government",
            "subcategory":"Office",
            "type":"Public Place"
        }
    ],
    "sg:phone":"+1 201 794 5315",
    "sg:postcode":"07410",
    "sg:province":"NJ",
    "sg:tags":[
        "department",
        "purchasing",
        "village"
    ],
    "sg:website":"www.fairlawn.org",
    "wof:name":"Fair Lawn Purchasing Dept",
    "wof:placetype":"venue"
},
  "geometry": {"coordinates":[-74.121965,40.938823],"type":"Point"}
}