{
  "type": "Feature",
  "properties": {
    "iso:country":"US",
    "sg:address":"60 Forest Dr",
    "sg:city":"Lakewood",
    "sg:classifiers":[
        {
            "category":"Professional",
            "subcategory":"Management & Consulting",
            "type":"Services"
        }
    ],
    "sg:phone":"+1   ",
    "sg:postcode":"08701",
    "sg:province":"NJ",
    "sg:tags":[
        "consultant",
        "botanical"
    ],
    "wof:name":"Linda Kelly",
    "wof:placetype":"venue"
},
  "geometry": {"coordinates":[-74.244731,40.098124],"type":"Point"}
}