{
  "type": "Feature",
  "properties": {
    "addr:full":"429 John F Kennedy Way Willingboro NJ 08046",
    "addr:housenumber":"429",
    "addr:postcode":"08046",
    "addr:street":"John F Kennedy Way",
    "iso:country":"US",
    "sg:address":"429 John F Kennedy Way",
    "sg:city":"Willingboro",
    "sg:classifiers":[
        {
            "category":"Building & Trades",
            "subcategory":"Construction",
            "type":"Services"
        }
    ],
    "sg:phone":"+1 609 877 2200",
    "sg:postcode":"08046",
    "sg:province":"NJ",
    "sg:tags":[
        "marking",
        "maintenance",
        "parking"
    ],
    "wof:name":"Willingboro Public Works",
    "wof:placetype":"venue"
},
  "geometry": {"coordinates":[-74.880747,40.02897],"type":"Point"}
}