{
  "type": "Feature",
  "properties": {
    "iso:country":"US",
    "sg:address":"28 S Orange Ave",
    "sg:city":"South Orange",
    "sg:classifiers":[
        {
            "category":"Professional",
            "subcategory":"Lawyer & Legal Services",
            "type":"Services"
        }
    ],
    "sg:phone":"+1 973 763 0760",
    "sg:postcode":"07079",
    "sg:province":"NJ",
    "sg:tags":[
        "attorney"
    ],
    "wof:name":"Martin Bressler",
    "wof:placetype":"venue"
},
  "geometry": {"coordinates":[-74.258815,40.745927],"type":"Point"}
}