{
  "type": "Feature",
  "properties": {
    "addr:full":"355 N Gaston Ave Somerville NJ 08876",
    "addr:housenumber":"355",
    "addr:postcode":"08876",
    "addr:street":"N Gaston Ave",
    "iso:country":"US",
    "sg:address":"355 N Gaston Ave",
    "sg:city":"Somerville",
    "sg:classifiers":[
        {
            "category":"Autos & Motor Vehicles",
            "subcategory":"Automobile Sales",
            "type":"Retail Goods"
        }
    ],
    "sg:phone":"+1   ",
    "sg:postcode":"08876",
    "sg:province":"NJ",
    "sg:tags":[
        "used"
    ],
    "sg:website":"www.millenniumvw.com",
    "wof:name":"Millennium Volkswagen",
    "wof:placetype":"venue"
},
  "geometry": {"coordinates":[-74.59869500000001,40.57975],"type":"Point"}
}