{
  "type": "Feature",
  "properties": {
    "addr:full":"1911 Brunswick Ave Trenton NJ 08648",
    "addr:housenumber":"1911",
    "addr:postcode":"08648",
    "addr:street":"Brunswick Ave",
    "iso:country":"US",
    "sg:address":"1911 Brunswick Ave",
    "sg:city":"Trenton",
    "sg:classifiers":[
        {
            "category":"Shopping",
            "subcategory":"Musical Instruments",
            "type":"Retail Goods"
        }
    ],
    "sg:phone":"+1   ",
    "sg:postcode":"08648",
    "sg:province":"NJ",
    "wof:name":"Baldwin Hammond Music Center",
    "wof:placetype":"venue"
},
  "geometry": {"coordinates":[-74.736099,40.250425],"type":"Point"}
}