{
  "type": "Feature",
  "properties": {
    "addr:full":"401 N Main St Ofc Williamstown NJ 08094",
    "addr:housenumber":"401",
    "addr:postcode":"08094",
    "addr:street":"N Main St",
    "iso:country":"US",
    "sg:address":"401 N Main St Ofc",
    "sg:city":"Williamstown",
    "sg:classifiers":[
        {
            "category":"Real Estate",
            "subcategory":"Real Estate Operator",
            "type":"Services"
        }
    ],
    "sg:phone":"+1 856 629 0200",
    "sg:postcode":"08094",
    "sg:province":"NJ",
    "sg:tags":[
        "apartment"
    ],
    "wof:name":"Jefferson Village Apartments",
    "wof:placetype":"venue"
},
  "geometry": {"coordinates":[-74.97489899999999,39.663898],"type":"Point"}
}