{
  "type": "Feature",
  "properties": {
    "iso:country":"US",
    "sg:address":"554 Allen Rd",
    "sg:city":"Basking Ridge",
    "sg:classifiers":[
        {
            "category":"Restaurant",
            "type":"Food & Drink"
        }
    ],
    "sg:phone":"+1 908 901 0111",
    "sg:postcode":"07920",
    "sg:province":"NJ",
    "sg:tags":[
        "delicatessen"
    ],
    "wof:name":"Veneto Tratorria",
    "wof:placetype":"venue"
},
  "geometry": {"coordinates":[-74.595608,40.653308],"type":"Point"}
}