{
  "type": "Feature",
  "properties": {
    "iso:country":"US",
    "sg:address":"10 E Prospect St",
    "sg:city":"Waldwick",
    "sg:classifiers":[
        {
            "category":"Shopping",
            "subcategory":"Jewelry",
            "type":"Retail Goods"
        }
    ],
    "sg:phone":"+1   ",
    "sg:postcode":"07463",
    "sg:province":"NJ",
    "sg:tags":[
        "repair"
    ],
    "wof:name":"Plaza Gift & Jewelry Shop",
    "wof:placetype":"venue"
},
  "geometry": {"coordinates":[-74.117779,41.010721],"type":"Point"}
}