{
  "type": "Feature",
  "properties": {
    "addr:full":"221 Orient Way Lyndhurst NJ 07071",
    "addr:housenumber":"221",
    "addr:postcode":"07071",
    "addr:street":"Orient Way",
    "iso:country":"US",
    "sg:address":"221 Orient Way",
    "sg:city":"Lyndhurst",
    "sg:classifiers":[
        {
            "category":"Professional",
            "subcategory":"Business Services",
            "type":"Services"
        }
    ],
    "sg:phone":"+1   ",
    "sg:postcode":"07071",
    "sg:province":"NJ",
    "wof:name":"Agent Andy",
    "wof:placetype":"venue"
},
  "geometry": {"coordinates":[-74.11244499999999,40.808449],"type":"Point"}
}