{
  "type": "Feature",
  "properties": {
    "addr:full":"1865 Swarthmore Ave Lakewood NJ 08701",
    "addr:housenumber":"1865",
    "addr:postcode":"08701",
    "addr:street":"Swarthmore Ave",
    "iso:country":"US",
    "sg:address":"1865 Swarthmore Ave",
    "sg:city":"Lakewood",
    "sg:classifiers":[
        {
            "category":"Freight",
            "type":"Transportation"
        }
    ],
    "sg:phone":"+1 732 364 7575",
    "sg:postcode":"08701",
    "sg:province":"NJ",
    "sg:tags":[
        "over",
        "road",
        "trucking"
    ],
    "sg:website":"www.idealwaymovers.com",
    "wof:name":"Ideal Way Movers Inc",
    "wof:placetype":"venue"
},
  "geometry": {"coordinates":[-74.17071199999999,40.077548],"type":"Point"}
}