{
  "type": "Feature",
  "properties": {
    "iso:country":"US",
    "sg:address":"413 Wayne Dr",
    "sg:city":"Cinnaminson",
    "sg:classifiers":[
        {
            "category":"Building & Trades",
            "subcategory":"Cleaning & Sanitation",
            "type":"Services"
        },
        {
            "category":"Retail",
            "subcategory":"Laundry & Dry Cleaning",
            "type":"Services"
        }
    ],
    "sg:phone":"+1 856 786 9082",
    "sg:postcode":"08077",
    "sg:province":"NJ",
    "sg:tags":[
        "cleaners",
        "rug",
        "maintenance",
        "carpet"
    ],
    "wof:name":"New Life Maintenance Co",
    "wof:placetype":"venue"
},
  "geometry": {"coordinates":[-74.977079,39.996323],"type":"Point"}
}