{
  "type": "Feature",
  "properties": {
    "addr:full":"131 Trinity Ave Blackwood NJ 08012",
    "addr:housenumber":"131",
    "addr:postcode":"08012",
    "addr:street":"Trinity Ave",
    "iso:country":"US",
    "sg:address":"131 Trinity Ave",
    "sg:city":"Blackwood",
    "sg:classifiers":[
        {
            "category":"Building & Trades",
            "subcategory":"Construction",
            "type":"Services"
        }
    ],
    "sg:phone":"+1 856 228 2420",
    "sg:postcode":"08012",
    "sg:province":"NJ",
    "sg:tags":[
        "general",
        "contractor"
    ],
    "wof:name":"Jeff Rickenbach General Contr",
    "wof:placetype":"venue"
},
  "geometry": {"coordinates":[-75.05877099999999,39.797719],"type":"Point"}
}