{
  "type": "Feature",
  "properties": {
    "iso:country":"US",
    "sg:address":"62 S Main St",
    "sg:city":"Milltown",
    "sg:classifiers":[
        {
            "category":"Social Services",
            "type":"Services"
        }
    ],
    "sg:phone":"+1 732 247 1655",
    "sg:postcode":"08850",
    "sg:province":"NJ",
    "wof:name":"Interfaith Network Of Care",
    "wof:placetype":"venue"
},
  "geometry": {"coordinates":[-74.435665,40.450392],"type":"Point"}
}