{
  "type": "Feature",
  "properties": {
    "iso:country":"US",
    "sg:address":"1 Roseld Ave",
    "sg:city":"Deal",
    "sg:classifiers":[
        {
            "category":"Professional",
            "type":"Services"
        }
    ],
    "sg:phone":"+1 732 531 0031",
    "sg:postcode":"07723",
    "sg:province":"NJ",
    "sg:tags":[
        "establishment"
    ],
    "wof:name":"Ritota & Ritota",
    "wof:placetype":"venue"
},
  "geometry": {"coordinates":[-73.99274699999999,40.245619],"type":"Point"}
}