{
  "type": "Feature",
  "properties": {
    "addr:full":"100 Sherwood Ave Paterson NJ 07502",
    "addr:housenumber":"100",
    "addr:postcode":"07502",
    "addr:street":"Sherwood Ave",
    "iso:country":"US",
    "sg:address":"100 Sherwood Ave",
    "sg:city":"Paterson",
    "sg:classifiers":[
        {
            "category":"Retail",
            "subcategory":"Auto Repair",
            "type":"Services"
        }
    ],
    "sg:phone":"+1   ",
    "sg:postcode":"07502",
    "sg:province":"NJ",
    "sg:tags":[
        "body"
    ],
    "wof:name":"Tonys Auto Body Service",
    "wof:placetype":"venue"
},
  "geometry": {"coordinates":[-74.19426799999999,40.91851],"type":"Point"}
}