{
  "type": "Feature",
  "properties": {
    "iso:country":"US",
    "sg:address":"222 Livingston Ave",
    "sg:city":"New Brunswick",
    "sg:classifiers":[
        {
            "category":"Social Services",
            "subcategory":"Child Care",
            "type":"Services"
        }
    ],
    "sg:phone":"+1 732 545 6555",
    "sg:postcode":"08901",
    "sg:province":"NJ",
    "wof:name":"Gan Yeladeem Child Care Ctr",
    "wof:placetype":"venue"
},
  "geometry": {"coordinates":[-74.45214799999999,40.48557],"type":"Point"}
}