{
  "type": "Feature",
  "properties": {
    "iso:country":"US",
    "sg:address":"1145 Thomas Busch Mem Hwy",
    "sg:city":"Pennsauken",
    "sg:classifiers":[
        {
            "category":"Manufacturing",
            "subcategory":"Printing",
            "type":"Manufacturing & Wholesale Goods"
        }
    ],
    "sg:phone":"+1 856 661 1801",
    "sg:postcode":"08110",
    "sg:province":"NJ",
    "sg:tags":[
        "lithographic",
        "commercial"
    ],
    "wof:name":"Datanet",
    "wof:placetype":"venue"
},
  "geometry": {"coordinates":[-75.032892,39.987326],"type":"Point"}
}