{
  "type": "Feature",
  "properties": {
    "addr:full":"100 Main St Manasquan NJ 08736",
    "addr:housenumber":"100",
    "addr:postcode":"08736",
    "addr:street":"Main St",
    "iso:country":"US",
    "sg:address":"100 Main St",
    "sg:city":"Manasquan",
    "sg:classifiers":[
        {
            "category":"Shopping",
            "subcategory":"Hobbies, Toys, & Games",
            "type":"Retail Goods"
        }
    ],
    "sg:phone":"+1 732 223 0224",
    "sg:postcode":"08736",
    "sg:province":"NJ",
    "wof:name":"Timm's Variety Store",
    "wof:placetype":"venue"
},
  "geometry": {"coordinates":[-74.050652,40.123275],"type":"Point"}
}