{
  "type": "Feature",
  "properties": {
    "iso:country":"US",
    "sg:address":"125 Holly Ln",
    "sg:city":"Boonton",
    "sg:classifiers":[
        {
            "category":"Real Estate",
            "subcategory":"Real Estate Agent",
            "type":"Services"
        }
    ],
    "sg:phone":"+1   ",
    "sg:postcode":"07005",
    "sg:province":"NJ",
    "wof:name":"Chopin Realty Co",
    "wof:placetype":"venue"
},
  "geometry": {"coordinates":[-74.41139800000001,40.917878],"type":"Point"}
}