{
  "type": "Feature",
  "properties": {
    "iso:country":"US",
    "sg:address":"2900 State Rte 42",
    "sg:city":"Sicklerville",
    "sg:classifiers":[
        {
            "category":"Autos & Motor Vehicles",
            "subcategory":"Automobile Sales",
            "type":"Retail Goods"
        }
    ],
    "sg:phone":"+1   ",
    "sg:postcode":"08081",
    "sg:province":"NJ",
    "wof:name":"Martin Dealership",
    "wof:placetype":"venue"
},
  "geometry": {"coordinates":[-75.024225,39.720914],"type":"Point"}
}