{
  "type": "Feature",
  "properties": {
    "iso:country":"US",
    "sg:address":"3 Broadway",
    "sg:city":"Fair Lawn",
    "sg:classifiers":[
        {
            "category":"Wholesale",
            "subcategory":"Home Furnishings",
            "type":"Manufacturing & Wholesale Goods"
        }
    ],
    "sg:phone":"+1 201 797 2220",
    "sg:postcode":"07410",
    "sg:province":"NJ",
    "sg:tags":[
        "frame"
    ],
    "wof:name":"Broadway Picture Frame Outlet",
    "wof:placetype":"venue"
},
  "geometry": {"coordinates":[-74.107726,40.923636],"type":"Point"}
}