{
  "type": "Feature",
  "properties": {
    "addr:full":"31 Sweet Briar Ln Holmdel NJ 07733",
    "addr:housenumber":"31",
    "addr:postcode":"07733",
    "addr:street":"Sweet Briar Ln",
    "iso:country":"US",
    "sg:address":"31 Sweet Briar Ln",
    "sg:city":"Holmdel",
    "sg:classifiers":[
        {
            "category":"Building & Trades",
            "subcategory":"Construction",
            "type":"Services"
        }
    ],
    "sg:phone":"+1 732 946 0095",
    "sg:postcode":"07733",
    "sg:province":"NJ",
    "wof:name":"Briar Construction Corp",
    "wof:placetype":"venue"
},
  "geometry": {"coordinates":[-74.201655,40.359365],"type":"Point"}
}