{
  "type": "Feature",
  "properties": {
    "iso:country":"US",
    "sg:address":"15 Fulton St",
    "sg:city":"Newark",
    "sg:classifiers":[
        {
            "category":"Professional",
            "subcategory":"Research",
            "type":"Services"
        }
    ],
    "sg:phone":"+1 973 648 0200",
    "sg:postcode":"07102",
    "sg:province":"NJ",
    "sg:tags":[
        "organization",
        "noncommercial"
    ],
    "wof:name":"North Jersey Aids Alliance",
    "wof:placetype":"venue"
},
  "geometry": {"coordinates":[-74.16705,40.74197],"type":"Point"}
}