{
  "type": "Feature",
  "properties": {
    "iso:country":"US",
    "sg:address":"1022 Butlers Park Rd",
    "sg:city":"Washington",
    "sg:classifiers":[
        {
            "category":"Wholesale",
            "subcategory":"Electrical",
            "type":"Manufacturing & Wholesale Goods"
        }
    ],
    "sg:phone":"+1 908 689 5810",
    "sg:postcode":"07882",
    "sg:province":"NJ",
    "sg:tags":[
        "electronic"
    ],
    "wof:name":"Electronic Circuit Supply",
    "wof:placetype":"venue"
},
  "geometry": {"coordinates":[-74.936927,40.756051],"type":"Point"}
}