{
  "type": "Feature",
  "properties": {
    "iso:country":"US",
    "sg:address":"307 Willow Ave",
    "sg:city":"Hoboken",
    "sg:classifiers":[
        {
            "category":"Organizations",
            "subcategory":"Religious Organization",
            "type":"Services"
        }
    ],
    "sg:phone":"+1   ",
    "sg:postcode":"07030",
    "sg:province":"NJ",
    "sg:tags":[
        "management"
    ],
    "wof:name":"Faith Services",
    "wof:placetype":"venue"
},
  "geometry": {"coordinates":[-74.033305,40.741769],"type":"Point"}
}