{
  "type": "Feature",
  "properties": {
    "iso:country":"US",
    "sg:address":"35 3rd Ave",
    "sg:city":"Little Falls",
    "sg:classifiers":[
        {
            "category":"Food & Beverages",
            "subcategory":"Liquor & Beverages",
            "type":"Retail Goods"
        }
    ],
    "sg:phone":"+1   ",
    "sg:postcode":"07424",
    "sg:province":"NJ",
    "sg:tags":[
        "alcoholic"
    ],
    "wof:name":"Chalice Wines",
    "wof:placetype":"venue"
},
  "geometry": {"coordinates":[-74.22405000000001,40.877308],"type":"Point"}
}