{
  "type": "Feature",
  "properties": {
    "iso:country":"US",
    "sg:address":"15 Schuyler Ave",
    "sg:city":"North Arlington",
    "sg:classifiers":[
        {
            "category":"Restaurant",
            "type":"Food & Drink"
        }
    ],
    "sg:phone":"+1 201 246 9300",
    "sg:postcode":"07031",
    "sg:province":"NJ",
    "sg:tags":[
        "chinese"
    ],
    "wof:name":"Golden China Kitchen",
    "wof:placetype":"venue"
},
  "geometry": {"coordinates":[-74.1297,40.7784],"type":"Point"}
}