{
  "type": "Feature",
  "properties": {
    "addr:full":"21 Hilton St Belleville NJ 07109",
    "addr:housenumber":"21",
    "addr:postcode":"07109",
    "addr:street":"Hilton St",
    "iso:country":"US",
    "sg:address":"21 Hilton St",
    "sg:city":"Belleville",
    "sg:classifiers":[
        {
            "category":"Building & Trades",
            "subcategory":"Landscaping Services",
            "type":"Services"
        }
    ],
    "sg:phone":"+1 973 751 3753",
    "sg:postcode":"07109",
    "sg:province":"NJ",
    "sg:tags":[
        "landscape"
    ],
    "wof:name":"Gencarellis Landscaping",
    "wof:placetype":"venue"
},
  "geometry": {"coordinates":[-74.165981,40.808319],"type":"Point"}
}