{
  "type": "Feature",
  "properties": {
    "addr:full":"534 Justice Dr Marlton NJ 08053",
    "addr:housenumber":"534",
    "addr:postcode":"08053",
    "addr:street":"Justice Dr",
    "iso:country":"US",
    "sg:address":"534 Justice Dr",
    "sg:city":"Marlton",
    "sg:classifiers":[
        {
            "category":"Professional",
            "subcategory":"Management & Consulting",
            "type":"Services"
        }
    ],
    "sg:phone":"+1   ",
    "sg:postcode":"08053",
    "sg:province":"NJ",
    "sg:tags":[
        "business"
    ],
    "wof:name":"Rnh Consulting Inc",
    "wof:placetype":"venue"
},
  "geometry": {"coordinates":[-74.90490800000001,39.917048],"type":"Point"}
}