{
  "type": "Feature",
  "properties": {
    "iso:country":"US",
    "sg:address":"26 Church St",
    "sg:city":"Basking Ridge",
    "sg:classifiers":[
        {
            "category":"Restaurant",
            "type":"Food & Drink"
        }
    ],
    "sg:phone":"+1 908 604 2440",
    "sg:postcode":"07920",
    "sg:province":"NJ",
    "wof:name":"Focacceria",
    "wof:placetype":"venue"
},
  "geometry": {"coordinates":[-74.585094,40.666295],"type":"Point"}
}