{
  "type": "Feature",
  "properties": {
    "iso:country":"US",
    "sg:address":"245 Teaneck Rd",
    "sg:city":"Ridgefield Park",
    "sg:classifiers":[
        {
            "category":"Arena",
            "subcategory":"Sports Club",
            "type":"Entertainment"
        }
    ],
    "sg:phone":"+1 201 994 1033",
    "sg:postcode":"07660",
    "sg:province":"NJ",
    "sg:tags":[
        "martial art"
    ],
    "sg:website":"www.eastbergenaikidoacademy.com",
    "wof:name":"East Bergen Aikido Academy",
    "wof:placetype":"venue"
},
  "geometry": {"coordinates":[-74.020481,40.851143],"type":"Point"}
}