{
  "type": "Feature",
  "properties": {
    "iso:country":"US",
    "sg:address":"300 Esplanade Ave",
    "sg:city":"Pitman",
    "sg:classifiers":[
        {
            "category":"Building & Trades",
            "subcategory":"Construction",
            "type":"Services"
        }
    ],
    "sg:phone":"+1 856 589 0091",
    "sg:postcode":"08071",
    "sg:province":"NJ",
    "sg:tags":[
        "concrete",
        "work"
    ],
    "wof:name":"Penn Jersey Building Mtls Co",
    "wof:placetype":"venue"
},
  "geometry": {"coordinates":[-75.13073799999999,39.7418],"type":"Point"}
}