{
  "type": "Feature",
  "properties": {
    "addr:full":"681 W Delilah Rd Pleasantville NJ 08232",
    "addr:housenumber":"681",
    "addr:postcode":"08232",
    "addr:street":"W Delilah Rd",
    "iso:country":"US",
    "sg:address":"681 W Delilah Rd",
    "sg:city":"Pleasantville",
    "sg:classifiers":[
        {
            "category":"Building & Trades",
            "subcategory":"Construction",
            "type":"Services"
        }
    ],
    "sg:phone":"+1 609 641 2503",
    "sg:postcode":"08232",
    "sg:province":"NJ",
    "sg:tags":[
        "general",
        "contractor"
    ],
    "wof:name":"Massett Building Co",
    "wof:placetype":"venue"
},
  "geometry": {"coordinates":[-74.52392999999999,39.409289],"type":"Point"}
}