{
  "type": "Feature",
  "properties": {
    "iso:country":"US",
    "sg:address":"434 Midland Ave",
    "sg:city":"Garfield",
    "sg:classifiers":[
        {
            "category":"Shopping",
            "subcategory":"Florist",
            "type":"Retail Goods"
        }
    ],
    "sg:phone":"+1 973 685 7750",
    "sg:postcode":"07026",
    "sg:province":"NJ",
    "wof:name":"G and M Wholesale Flowers",
    "wof:placetype":"venue"
},
  "geometry": {"coordinates":[-74.10232999999999,40.878283],"type":"Point"}
}