{
  "type": "Feature",
  "properties": {
    "addr:full":"110 Walnut St Toms River NJ 08753",
    "addr:housenumber":"110",
    "addr:postcode":"08753",
    "addr:street":"Walnut St",
    "iso:country":"US",
    "sg:address":"110 Walnut St",
    "sg:city":"Toms River",
    "sg:classifiers":[
        {
            "category":"Building & Trades",
            "subcategory":"Construction",
            "type":"Services"
        }
    ],
    "sg:phone":"+1 732 244 6340",
    "sg:postcode":"08753",
    "sg:province":"NJ",
    "sg:tags":[
        "home",
        "builder"
    ],
    "wof:name":"T & H Homes Inc",
    "wof:placetype":"venue"
},
  "geometry": {"coordinates":[-74.190437,39.968083],"type":"Point"}
}