{
  "type": "Feature",
  "properties": {
    "iso:country":"US",
    "sg:address":"87 Passaic St",
    "sg:city":"Garfield",
    "sg:classifiers":[
        {
            "category":"Personal",
            "subcategory":"Barber",
            "type":"Services"
        }
    ],
    "sg:phone":"+1 973 470 9777",
    "sg:postcode":"07026",
    "sg:province":"NJ",
    "wof:name":"Majestic Barber Shop",
    "wof:placetype":"venue"
},
  "geometry": {"coordinates":[-74.10576,40.866375],"type":"Point"}
}