{
  "type": "Feature",
  "properties": {
    "iso:country":"US",
    "sg:address":"43 E Gramercy Pl",
    "sg:city":"Glen Rock",
    "sg:classifiers":[
        {
            "category":"Social Services",
            "subcategory":"Child Care",
            "type":"Services"
        }
    ],
    "sg:phone":"+1   ",
    "sg:postcode":"07452",
    "sg:province":"NJ",
    "sg:tags":[
        "day"
    ],
    "wof:name":"Marty Lyons Foundation Inc",
    "wof:placetype":"venue"
},
  "geometry": {"coordinates":[-74.114966,40.961847],"type":"Point"}
}