{
  "type": "Feature",
  "properties": {
    "iso:country":"US",
    "sg:address":"4 US Hwy 130",
    "sg:city":"Cinnaminson",
    "sg:classifiers":[
        {
            "category":"Autos & Motor Vehicles",
            "subcategory":"Fuel & Gas Station",
            "type":"Retail Goods"
        }
    ],
    "sg:phone":"+1 856 786 9855",
    "sg:postcode":"08077",
    "sg:province":"NJ",
    "sg:tags":[
        "oil"
    ],
    "wof:name":"Crossroads Exxon",
    "wof:placetype":"venue"
},
  "geometry": {"coordinates":[-75.01433299999999,39.985422],"type":"Point"}
}