{
  "type": "Feature",
  "properties": {
    "iso:country":"US",
    "sg:address":"5523 Berkshire Valley Rd",
    "sg:city":"Oak Ridge",
    "sg:classifiers":[
        {
            "category":"Food & Beverages",
            "subcategory":"Groceries & Convenience Stores",
            "type":"Retail Goods"
        }
    ],
    "sg:phone":"+1   ",
    "sg:postcode":"07438",
    "sg:province":"NJ",
    "sg:tags":[
        "delicatessen"
    ],
    "wof:name":"Ding Dong Dairy",
    "wof:placetype":"venue"
},
  "geometry": {"coordinates":[-74.512888,41.016626],"type":"Point"}
}