{
  "type": "Feature",
  "properties": {
    "iso:country":"US",
    "sg:address":"9215 Ventnor Ave",
    "sg:city":"Margate City",
    "sg:classifiers":[
        {
            "category":"Personal",
            "subcategory":"Beauty Salon",
            "type":"Services"
        }
    ],
    "sg:phone":"+1 609 822 2049",
    "sg:postcode":"08402",
    "sg:province":"NJ",
    "wof:name":"Kevin D's",
    "wof:placetype":"venue"
},
  "geometry": {"coordinates":[-74.513864,39.322482],"type":"Point"}
}