{
  "type": "Feature",
  "properties": {
    "iso:country":"US",
    "sg:address":"120 Summit Ave",
    "sg:city":"Summit",
    "sg:classifiers":[
        {
            "category":"Organizations",
            "subcategory":"Membership Organization",
            "type":"Services"
        }
    ],
    "sg:phone":"+1 908 790 6509",
    "sg:postcode":"07901",
    "sg:province":"NJ",
    "wof:name":"Joseph Enright Foundation",
    "wof:placetype":"venue"
},
  "geometry": {"coordinates":[-74.35623099999999,40.718801],"type":"Point"}
}