{
  "type": "Feature",
  "properties": {
    "iso:country":"US",
    "sg:address":"625 N Maple Ave",
    "sg:city":"Ho Ho Kus",
    "sg:classifiers":[
        {
            "category":"Professional",
            "subcategory":"Lawyer & Legal Services",
            "type":"Services"
        }
    ],
    "sg:phone":"+1   ",
    "sg:postcode":"07423",
    "sg:province":"NJ",
    "wof:name":"Paul D Kreisinger",
    "wof:placetype":"venue"
},
  "geometry": {"coordinates":[-74.11019400000001,40.997054],"type":"Point"}
}