{
  "type": "Feature",
  "properties": {
    "addr:full":"18 S Orange Ave South Orange NJ 07079",
    "addr:housenumber":"18",
    "addr:postcode":"07079",
    "addr:street":"S Orange Ave",
    "iso:country":"US",
    "sg:address":"18 S Orange Ave",
    "sg:city":"South Orange",
    "sg:classifiers":[
        {
            "category":"Banks & Credit Unions",
            "subcategory":"Bank",
            "type":"Services"
        }
    ],
    "sg:phone":"+1 973 763 3943",
    "sg:postcode":"07079",
    "sg:province":"NJ",
    "wof:name":"Washington Mutual",
    "wof:placetype":"venue"
},
  "geometry": {"coordinates":[-74.258623,40.745849],"type":"Point"}
}