{
  "type": "Feature",
  "properties": {
    "addr:full":"2760 US Hwy 9 Howell NJ 07731",
    "addr:housenumber":"2760",
    "addr:postcode":"07731",
    "addr:street":"Us Hwy 9",
    "iso:country":"US",
    "sg:address":"2760 US Hwy 9",
    "sg:city":"Howell",
    "sg:classifiers":[
        {
            "category":"Building & Trades",
            "subcategory":"Pest Control",
            "type":"Services"
        }
    ],
    "sg:phone":"+1 732 363 5460",
    "sg:postcode":"07731",
    "sg:province":"NJ",
    "wof:name":"A Abstract Termite & Pest",
    "wof:placetype":"venue"
},
  "geometry": {"coordinates":[-74.23955100000001,40.170956],"type":"Point"}
}