{
  "type": "Feature",
  "properties": {
    "addr:full":"2656 Baird Blvd Camden NJ 08105",
    "addr:housenumber":"2656",
    "addr:postcode":"08105",
    "addr:street":"Baird Blvd",
    "iso:country":"US",
    "sg:address":"2656 Baird Blvd",
    "sg:city":"Camden",
    "sg:classifiers":[
        {
            "category":"Travel",
            "subcategory":"Hotels & Motels",
            "type":"Entertainment"
        }
    ],
    "sg:phone":"+1 856 963 4001",
    "sg:postcode":"08105",
    "sg:province":"NJ",
    "wof:name":"King Salomon Lodge",
    "wof:placetype":"venue"
},
  "geometry": {"coordinates":[-75.086601,39.945999],"type":"Point"}
}