{
  "type": "Feature",
  "properties": {
    "addr:full":"1402 Teaneck Rd Teaneck NJ 07666",
    "addr:housenumber":"1402",
    "addr:postcode":"07666",
    "addr:street":"Teaneck Rd",
    "iso:country":"US",
    "sg:address":"1402 Teaneck Rd",
    "sg:city":"Teaneck",
    "sg:classifiers":[
        {
            "category":"Shopping",
            "subcategory":"Clothing, Apparel, & Fashions",
            "type":"Retail Goods"
        }
    ],
    "sg:phone":"+1   ",
    "sg:postcode":"07666",
    "sg:province":"NJ",
    "wof:name":"Ladies Knight",
    "wof:placetype":"venue"
},
  "geometry": {"coordinates":[-73.99971499999999,40.900565],"type":"Point"}
}