{
  "type": "Feature",
  "properties": {
    "iso:country":"US",
    "sg:address":"40 N Hideaway Dr",
    "sg:city":"Beach Haven",
    "sg:classifiers":[
        {
            "category":"Building & Trades",
            "subcategory":"Construction",
            "type":"Services"
        }
    ],
    "sg:phone":"+1 609 207 0210",
    "sg:postcode":"08008",
    "sg:province":"NJ",
    "sg:tags":[
        "equipment",
        "installation"
    ],
    "wof:name":"Nu-Beacon Erectors Inc",
    "wof:placetype":"venue"
},
  "geometry": {"coordinates":[-74.216452,39.597753],"type":"Point"}
}