{
  "type": "Feature",
  "properties": {
    "addr:full":"53 Pennington Hopewell Rd Pennington NJ 08534",
    "addr:housenumber":"53",
    "addr:postcode":"08534",
    "addr:street":"Pennington Hopewell Rd",
    "iso:country":"US",
    "sg:address":"53 Pennington Hopewell Rd",
    "sg:city":"Pennington",
    "sg:classifiers":[
        {
            "category":"Professional",
            "subcategory":"Management & Consulting",
            "type":"Services"
        }
    ],
    "sg:phone":"+1 609 466 4100",
    "sg:postcode":"08534",
    "sg:province":"NJ",
    "sg:tags":[
        "party",
        "planning"
    ],
    "wof:name":"Activities",
    "wof:placetype":"venue"
},
  "geometry": {"coordinates":[-74.79587100000001,40.359231],"type":"Point"}
}