{
  "type": "Feature",
  "properties": {
    "addr:full":"430 Franklin St Bloomfield NJ 07003",
    "addr:housenumber":"430",
    "addr:postcode":"07003",
    "addr:street":"Franklin St",
    "iso:country":"US",
    "sg:address":"430 Franklin St",
    "sg:city":"Bloomfield",
    "sg:classifiers":[
        {
            "category":"Organizations",
            "subcategory":"Religious Organization",
            "type":"Services"
        }
    ],
    "sg:phone":"+1   ",
    "sg:postcode":"07003",
    "sg:province":"NJ",
    "wof:name":"Kiddie Kare",
    "wof:placetype":"venue"
},
  "geometry": {"coordinates":[-74.19626,40.79336],"type":"Point"}
}