{
  "type": "Feature",
  "properties": {
    "iso:country":"US",
    "sg:address":"143 Overmount Ave Apt B",
    "sg:city":"West Paterson",
    "sg:classifiers":[
        {
            "category":"Building & Trades",
            "subcategory":"Construction",
            "type":"Services"
        }
    ],
    "sg:phone":"+1 973 256 9401",
    "sg:postcode":"07424",
    "sg:province":"NJ",
    "sg:tags":[
        "contractor"
    ],
    "wof:name":"A. Lodato Constrction Llc",
    "wof:placetype":"venue"
},
  "geometry": {"coordinates":[-74.19744,40.887259],"type":"Point"}
}