{
  "type": "Feature",
  "properties": {
    "addr:full":"197 Princeton Ave Brick NJ 08724",
    "addr:housenumber":"197",
    "addr:postcode":"08724",
    "addr:street":"Princeton Ave",
    "iso:country":"US",
    "sg:address":"197 Princeton Ave",
    "sg:city":"Brick",
    "sg:classifiers":[
        {
            "category":"Recreation",
            "type":"Entertainment"
        }
    ],
    "sg:phone":"+1 732 899 8345",
    "sg:postcode":"08724",
    "sg:province":"NJ",
    "sg:tags":[
        "party",
        "fishing"
    ],
    "wof:name":"Scorpion Charters",
    "wof:placetype":"venue"
},
  "geometry": {"coordinates":[-74.115781,40.062163],"type":"Point"}
}