{
  "type": "Feature",
  "properties": {
    "iso:country":"US",
    "sg:address":"8 Huemmer Ter",
    "sg:city":"Clifton",
    "sg:classifiers":[
        {
            "category":"Building & Trades",
            "subcategory":"Electrical",
            "type":"Services"
        }
    ],
    "sg:phone":"+1 973 478 3123",
    "sg:postcode":"07013",
    "sg:province":"NJ",
    "sg:tags":[
        "electrical",
        "contractor"
    ],
    "wof:name":"Direct Electrical Construction",
    "wof:placetype":"venue"
},
  "geometry": {"coordinates":[-74.17689300000001,40.85769],"type":"Point"}
}