{
  "type": "Feature",
  "properties": {
    "addr:full":"519 Main St South Amboy NJ 08879",
    "addr:housenumber":"519",
    "addr:postcode":"08879",
    "addr:street":"Main St",
    "iso:country":"US",
    "sg:address":"519 Main St",
    "sg:city":"South Amboy",
    "sg:classifiers":[
        {
            "category":"Autos & Motor Vehicles",
            "subcategory":"Automobile Sales",
            "type":"Retail Goods"
        }
    ],
    "sg:phone":"+1   ",
    "sg:postcode":"08879",
    "sg:province":"NJ",
    "sg:tags":[
        "used"
    ],
    "wof:name":"Electro Tech Systems",
    "wof:placetype":"venue"
},
  "geometry": {"coordinates":[-74.289525,40.479318],"type":"Point"}
}