{
  "type": "Feature",
  "properties": {
    "iso:country":"US",
    "sg:address":"835 Clinton Ave",
    "sg:city":"Newark",
    "sg:classifiers":[
        {
            "category":"Health Services",
            "subcategory":"Doctor",
            "type":"Services"
        }
    ],
    "sg:phone":"+1 973 399 3323",
    "sg:postcode":"07108",
    "sg:province":"NJ",
    "sg:tags":[
        "physician",
        "surgeon"
    ],
    "wof:name":"Internal Medicine",
    "wof:placetype":"venue"
},
  "geometry": {"coordinates":[-74.215107,40.723278],"type":"Point"}
}