{
  "type": "Feature",
  "properties": {
    "iso:country":"US",
    "sg:address":"166 S Main St",
    "sg:city":"Manahawkin",
    "sg:classifiers":[
        {
            "category":"Restaurant",
            "type":"Food & Drink"
        }
    ],
    "sg:phone":"+1 609 597 2651",
    "sg:postcode":"08050",
    "sg:province":"NJ",
    "wof:name":"Broadwalk Grill",
    "wof:placetype":"venue"
},
  "geometry": {"coordinates":[-74.260232,39.69429],"type":"Point"}
}