{
  "type": "Feature",
  "properties": {
    "addr:full":"14 Green St Newark NJ 07102",
    "addr:housenumber":"14",
    "addr:postcode":"07102",
    "addr:street":"Green St",
    "iso:country":"US",
    "sg:address":"14 Green St",
    "sg:city":"Newark",
    "sg:classifiers":[
        {
            "category":"Restaurant",
            "type":"Food & Drink"
        }
    ],
    "sg:menulink":"http://www.allmenus.com/nj/newark/5130-tasty-too!/menu/",
    "sg:phone":"+1 973 624 0600",
    "sg:postcode":"07102",
    "sg:province":"NJ",
    "sg:tags":[
        "italian"
    ],
    "wof:name":"Tasty Too!",
    "wof:placetype":"venue"
},
  "geometry": {"coordinates":[-74.172567,40.731918],"type":"Point"}
}