{
  "type": "Feature",
  "properties": {
    "iso:country":"US",
    "sg:address":"411 State St",
    "sg:city":"Hackensack",
    "sg:classifiers":[
        {
            "category":"Restaurant",
            "type":"Food & Drink"
        }
    ],
    "sg:phone":"+1 201 441 9096",
    "sg:postcode":"07601",
    "sg:province":"NJ",
    "wof:name":"Baja Fresh Mexican Grill",
    "wof:placetype":"venue"
},
  "geometry": {"coordinates":[-74.04083300000001,40.890444],"type":"Point"}
}