{
  "type": "Feature",
  "properties": {
    "iso:country":"US",
    "sg:address":"124 Reservoir Ave",
    "sg:city":"Randolph",
    "sg:classifiers":[
        {
            "category":"Building & Trades",
            "subcategory":"Construction",
            "type":"Services"
        }
    ],
    "sg:phone":"+1   ",
    "sg:postcode":"07869",
    "sg:province":"NJ",
    "sg:tags":[
        "industrial",
        "executive"
    ],
    "wof:name":"Hedden Park",
    "wof:placetype":"venue"
},
  "geometry": {"coordinates":[-74.573654,40.87185],"type":"Point"}
}