{
  "type": "Feature",
  "properties": {
    "addr:full":"954 Spofford Ave Elizabeth NJ 07202",
    "addr:housenumber":"954",
    "addr:postcode":"07202",
    "addr:street":"Spofford Ave",
    "iso:country":"US",
    "sg:address":"954 Spofford Ave",
    "sg:city":"Elizabeth",
    "sg:classifiers":[
        {
            "category":"Retail",
            "subcategory":"Laundry & Dry Cleaning",
            "type":"Services"
        }
    ],
    "sg:phone":"+1 908 351 7842",
    "sg:postcode":"07202",
    "sg:province":"NJ",
    "sg:tags":[
        "cleaners",
        "rug",
        "carpet"
    ],
    "wof:name":"Arevulo Carpet & Upholstery",
    "wof:placetype":"venue"
},
  "geometry": {"coordinates":[-74.224767,40.64977],"type":"Point"}
}