{
  "type": "Feature",
  "properties": {
    "iso:country":"US",
    "sg:address":"188 Woodcliff Ave",
    "sg:city":"Woodcliff Lake",
    "sg:classifiers":[
        {
            "category":"Arts & Performance",
            "subcategory":"Theater",
            "type":"Entertainment"
        }
    ],
    "sg:phone":"+1 201 802 0035",
    "sg:postcode":"07677",
    "sg:province":"NJ",
    "sg:tags":[
        "band",
        "orchestra"
    ],
    "wof:name":"Opus 5 Music",
    "wof:placetype":"venue"
},
  "geometry": {"coordinates":[-74.06298700000001,41.021235],"type":"Point"}
}