{
  "type": "Feature",
  "properties": {
    "iso:country":"US",
    "sg:address":"818 Lincoln Ave",
    "sg:city":"Palmyra",
    "sg:classifiers":[
        {
            "category":"Shopping",
            "subcategory":"Hobbies, Toys, & Games",
            "type":"Retail Goods"
        }
    ],
    "sg:phone":"+1 856 786 0080",
    "sg:postcode":"08065",
    "sg:province":"NJ",
    "sg:tags":[
        "model",
        "supply"
    ],
    "sg:website":"www.trackntrains.com",
    "wof:name":"Track-N-Trains",
    "wof:placetype":"venue"
},
  "geometry": {"coordinates":[-75.013047,40.003975],"type":"Point"}
}