{
  "type": "Feature",
  "properties": {
    "iso:country":"US",
    "sg:address":"156 Newark Pompton Tpke",
    "sg:city":"Wayne",
    "sg:classifiers":[
        {
            "category":"Retail",
            "subcategory":"Portrait Studio",
            "type":"Services"
        },
        {
            "category":"Shopping",
            "subcategory":"Pharmacy",
            "type":"Retail Goods"
        }
    ],
    "sg:phone":"+1 973 692 1220",
    "sg:postcode":"07470",
    "sg:province":"NJ",
    "sg:tags":[
        "photography",
        "drugstore",
        "store"
    ],
    "sg:website":"www.cvs.com",
    "wof:name":"Cvs Pharmacy",
    "wof:placetype":"venue"
},
  "geometry": {"coordinates":[-74.271896,40.9263],"type":"Point"}
}