{
  "type": "Feature",
  "properties": {
    "iso:country":"US",
    "sg:address":"90A Bristol Station Ct",
    "sg:city":"Carteret",
    "sg:classifiers":[
        {
            "category":"Building & Trades",
            "subcategory":"Construction",
            "type":"Services"
        }
    ],
    "sg:phone":"+1 732 969 9119",
    "sg:postcode":"07008",
    "sg:province":"NJ",
    "sg:tags":[
        "contractor"
    ],
    "wof:name":"Bristol Station Construction",
    "wof:placetype":"venue"
},
  "geometry": {"coordinates":[-74.21775100000001,40.587713],"type":"Point"}
}