{
  "type": "Feature",
  "properties": {
    "addr:full":"11 Franklin Pl Maplewood NJ 07040",
    "addr:housenumber":"11",
    "addr:postcode":"07040",
    "addr:street":"Franklin Pl",
    "iso:country":"US",
    "sg:address":"11 Franklin Pl",
    "sg:city":"Maplewood",
    "sg:classifiers":[
        {
            "category":"Professional",
            "subcategory":"Engineering",
            "type":"Services"
        }
    ],
    "sg:phone":"+1 973 313 0877",
    "sg:postcode":"07040",
    "sg:province":"NJ",
    "sg:tags":[
        "engineer"
    ],
    "wof:name":"Team Global Network Inc",
    "wof:placetype":"venue"
},
  "geometry": {"coordinates":[-74.264886,40.733033],"type":"Point"}
}