{
  "type": "Feature",
  "properties": {
    "iso:country":"US",
    "sg:address":"237 Kossuth St",
    "sg:city":"Riverside",
    "sg:classifiers":[
        {
            "category":"Building & Trades",
            "subcategory":"Construction",
            "type":"Services"
        }
    ],
    "sg:phone":"+1 856 824 0467",
    "sg:postcode":"08075",
    "sg:province":"NJ",
    "sg:tags":[
        "carpentry",
        "contractor"
    ],
    "wof:name":"E F Carpenter Inc",
    "wof:placetype":"venue"
},
  "geometry": {"coordinates":[-74.95543499999999,40.038431],"type":"Point"}
}