{
  "type": "Feature",
  "properties": {
    "iso:country":"US",
    "sg:address":"2 Sarah Ct",
    "sg:city":"Monmouth Jct",
    "sg:classifiers":[
        {
            "category":"Building & Trades",
            "subcategory":"Construction",
            "type":"Services"
        }
    ],
    "sg:phone":"+1 732 940 1301",
    "sg:postcode":"08852",
    "sg:province":"NJ",
    "sg:tags":[
        "general",
        "contractor"
    ],
    "wof:name":"Olcott Construction Co Inc",
    "wof:placetype":"venue"
},
  "geometry": {"coordinates":[-74.51685500000001,40.401753],"type":"Point"}
}