{
  "type": "Feature",
  "properties": {
    "iso:country":"US",
    "sg:address":"4043 State Rte 33",
    "sg:city":"Neptune",
    "sg:classifiers":[
        {
            "category":"Social Services",
            "subcategory":"Child Care",
            "type":"Services"
        }
    ],
    "sg:phone":"+1   ",
    "sg:postcode":"07753",
    "sg:province":"NJ",
    "sg:tags":[
        "day"
    ],
    "wof:name":"Love and Learn Preschool",
    "wof:placetype":"venue"
},
  "geometry": {"coordinates":[-74.10336700000001,40.217516],"type":"Point"}
}