{
  "type": "Feature",
  "properties": {
    "addr:full":"75 Brunswick Woods Dr East Brunswick NJ 08816",
    "addr:housenumber":"75",
    "addr:postcode":"08816",
    "addr:street":"Brunswick Woods Dr",
    "iso:country":"US",
    "sg:address":"75 Brunswick Woods Dr",
    "sg:city":"East Brunswick",
    "sg:classifiers":[
        {
            "category":"Health Services",
            "subcategory":"Doctor",
            "type":"Services"
        }
    ],
    "sg:phone":"+1 732 254 1450",
    "sg:postcode":"08816",
    "sg:province":"NJ",
    "sg:tags":[
        "physician",
        "medical",
        "surgeon"
    ],
    "wof:name":"Ashok Kumar MD",
    "wof:placetype":"venue"
},
  "geometry": {"coordinates":[-74.391216,40.421995],"type":"Point"}
}