{
  "type": "Feature",
  "properties": {
    "addr:full":"680 Broadway Paterson NJ 07514",
    "addr:housenumber":"680",
    "addr:postcode":"07514",
    "addr:street":"Broadway",
    "iso:country":"US",
    "sg:address":"680 Broadway",
    "sg:city":"Paterson",
    "sg:classifiers":[
        {
            "category":"Health Services",
            "subcategory":"Doctor",
            "type":"Services"
        }
    ],
    "sg:phone":"+1 973 653 9207",
    "sg:postcode":"07514",
    "sg:province":"NJ",
    "wof:name":"Med Solutions",
    "wof:placetype":"venue"
},
  "geometry": {"coordinates":[-74.14425799999999,40.918114],"type":"Point"}
}