{
  "type": "Feature",
  "properties": {
    "addr:full":"500 Horizon Center Trenton NJ 08691",
    "addr:housenumber":"500",
    "addr:postcode":"08691",
    "addr:street":"Horizon Center",
    "iso:country":"US",
    "sg:address":"500 Horizon Center",
    "sg:city":"Trenton",
    "sg:classifiers":[
        {
            "category":"Banks & Credit Unions",
            "subcategory":"Bank",
            "type":"Services"
        }
    ],
    "sg:phone":"+1 609 890 3973",
    "sg:postcode":"08691",
    "sg:province":"NJ",
    "sg:tags":[
        "national"
    ],
    "sg:website":"www.yanb.com",
    "wof:name":"The Yardville National Bank",
    "wof:placetype":"venue"
},
  "geometry": {"coordinates":[-74.641334,40.199483],"type":"Point"}
}