{
  "type": "Feature",
  "properties": {
    "addr:full":"1820 Hessian Dr Williamstown NJ 08094",
    "addr:housenumber":"1820",
    "addr:postcode":"08094",
    "addr:street":"Hessian Dr",
    "iso:country":"US",
    "sg:address":"1820 Hessian Dr",
    "sg:city":"Williamstown",
    "sg:classifiers":[
        {
            "category":"Building & Trades",
            "subcategory":"Construction",
            "type":"Services"
        }
    ],
    "sg:phone":"+1 856 881 8613",
    "sg:postcode":"08094",
    "sg:province":"NJ",
    "sg:tags":[
        "house"
    ],
    "wof:name":"Bulldog Builders New Jersey",
    "wof:placetype":"venue"
},
  "geometry": {"coordinates":[-75.04663499999999,39.674375],"type":"Point"}
}