{
  "type": "Feature",
  "properties": {
    "addr:full":"1569 US Hwy 22 Watchung NJ 07069",
    "addr:housenumber":"1569",
    "addr:postcode":"07069",
    "addr:street":"Us Hwy 22",
    "iso:country":"US",
    "sg:address":"1569 US Hwy 22",
    "sg:city":"Watchung",
    "sg:classifiers":[
        {
            "category":"Food & Beverages",
            "subcategory":"Meat & Fish",
            "type":"Retail Goods"
        }
    ],
    "sg:phone":"+1 908 668 8131",
    "sg:postcode":"07069",
    "sg:province":"NJ",
    "sg:tags":[
        "seafood"
    ],
    "wof:name":"Captain Fresh Seafood Sprmrkt",
    "wof:placetype":"venue"
},
  "geometry": {"coordinates":[-74.415983,40.641109],"type":"Point"}
}