{
  "type": "Feature",
  "properties": {
    "addr:full":"5140 W Hurley Pond Rd Wall Township NJ 07727",
    "addr:housenumber":"5140",
    "addr:postcode":"07727",
    "addr:street":"W Hurley Pond Rd Wall",
    "iso:country":"US",
    "sg:address":"5140 W Hurley Pond Rd",
    "sg:city":"Wall Township",
    "sg:classifiers":[
        {
            "category":"Retail",
            "subcategory":"Auto Repair",
            "type":"Services"
        }
    ],
    "sg:phone":"+1 732 901 7055",
    "sg:postcode":"07727",
    "sg:province":"NJ",
    "sg:tags":[
        "machine",
        "automobile",
        "shop"
    ],
    "wof:name":"Simonek Automotive",
    "wof:placetype":"venue"
},
  "geometry": {"coordinates":[-74.135177,40.179945],"type":"Point"}
}