{
  "type": "Feature",
  "properties": {
    "addr:full":"329 Stamets Rd Milford NJ 08848",
    "addr:housenumber":"329",
    "addr:postcode":"08848",
    "addr:street":"Stamets Rd",
    "iso:country":"US",
    "sg:address":"329 Stamets Rd",
    "sg:city":"Milford",
    "sg:classifiers":[
        {
            "category":"Manufacturing",
            "subcategory":"Tools & Machinery",
            "type":"Manufacturing & Wholesale Goods"
        }
    ],
    "sg:phone":"+1 908 996 2006",
    "sg:postcode":"08848",
    "sg:province":"NJ",
    "sg:tags":[
        "machine",
        "mfg"
    ],
    "wof:name":"Diamond Point Knife & Tool Co",
    "wof:placetype":"venue"
},
  "geometry": {"coordinates":[-75.06207000000001,40.562659],"type":"Point"}
}