{
  "type": "Feature",
  "properties": {
    "addr:full":"111 Main St Camden NJ 08102",
    "addr:housenumber":"111",
    "addr:postcode":"08102",
    "addr:street":"Main St",
    "iso:country":"US",
    "sg:address":"111 Main St",
    "sg:city":"Camden",
    "sg:classifiers":[
        {
            "category":"Retail",
            "subcategory":"Auto Repair",
            "type":"Services"
        }
    ],
    "sg:phone":"+1 856 365 9341",
    "sg:postcode":"08102",
    "sg:province":"NJ",
    "sg:tags":[
        "body",
        "automobile",
        "painting"
    ],
    "wof:name":"Cordero Auto Body",
    "wof:placetype":"venue"
},
  "geometry": {"coordinates":[-75.123901,39.9533],"type":"Point"}
}