{
  "type": "Feature",
  "properties": {
    "iso:country":"US",
    "sg:address":"1801 Bay Ave",
    "sg:city":"Ocean City",
    "sg:classifiers":[
        {
            "category":"Education",
            "subcategory":"School",
            "type":"Public Place"
        }
    ],
    "sg:phone":"+1 609 399 5611",
    "sg:postcode":"08226",
    "sg:province":"NJ",
    "sg:website":"www.ocean.city.k12.nj.us",
    "wof:name":"Intermediate Middle School",
    "wof:placetype":"venue"
},
  "geometry": {"coordinates":[-74.592235,39.271756],"type":"Point"}
}