{
  "type": "Feature",
  "properties": {
    "addr:full":"1876 State Rte 27 Edison NJ 08817",
    "addr:housenumber":"1876",
    "addr:postcode":"08817",
    "addr:street":"State Rte 27",
    "iso:country":"US",
    "sg:address":"1876 State Rte 27",
    "sg:city":"Edison",
    "sg:classifiers":[
        {
            "category":"Banks & Credit Unions",
            "subcategory":"Bank",
            "type":"Services"
        }
    ],
    "sg:phone":"+1 732 287 0648",
    "sg:postcode":"08817",
    "sg:province":"NJ",
    "wof:name":"Independence Community Bank",
    "wof:placetype":"venue"
},
  "geometry": {"coordinates":[-74.401133,40.515982],"type":"Point"}
}