{
  "type": "Feature",
  "properties": {
    "iso:country":"US",
    "sg:address":"60 Livingston Ave",
    "sg:city":"New Brunswick",
    "sg:classifiers":[
        {
            "category":"Education",
            "subcategory":"Library",
            "type":"Public Place"
        }
    ],
    "sg:phone":"+1 732 745 5108",
    "sg:postcode":"08901",
    "sg:province":"NJ",
    "sg:tags":[
        "executive"
    ],
    "wof:name":"New Brunswick Free Public Lib",
    "wof:placetype":"venue"
},
  "geometry": {"coordinates":[-74.446067,40.49135],"type":"Point"}
}