{
  "type": "Feature",
  "properties": {
    "addr:full":"900 Mill Rd Pleasantville NJ 08232",
    "addr:housenumber":"900",
    "addr:postcode":"08232",
    "addr:street":"Mill Rd",
    "iso:country":"US",
    "sg:address":"900 Mill Rd",
    "sg:city":"Pleasantville",
    "sg:classifiers":[
        {
            "category":"Building & Trades",
            "subcategory":"Plumbing",
            "type":"Services"
        }
    ],
    "sg:phone":"+1 609 641 4960",
    "sg:postcode":"08232",
    "sg:province":"NJ",
    "sg:tags":[
        "contractor"
    ],
    "wof:name":"Rich Goldner Joint Venture Co",
    "wof:placetype":"venue"
},
  "geometry": {"coordinates":[-74.525807,39.40825],"type":"Point"}
}