{
  "type": "Feature",
  "properties": {
    "iso:country":"US",
    "sg:address":"41 State Rte 34",
    "sg:city":"Colts Neck",
    "sg:classifiers":[
        {
            "category":"Building & Trades",
            "subcategory":"Construction",
            "type":"Services"
        }
    ],
    "sg:phone":"+1 732 303 6965",
    "sg:postcode":"07722",
    "sg:province":"NJ",
    "sg:tags":[
        "coping",
        "plastering",
        "tiling",
        "pool",
        "swimming"
    ],
    "wof:name":"De Falco Pol & Spa Inc",
    "wof:placetype":"venue"
},
  "geometry": {"coordinates":[-74.172484,40.283398],"type":"Point"}
}