{
  "type": "Feature",
  "properties": {
    "addr:full":"9 Howard Ct Newark NJ 07103",
    "addr:housenumber":"9",
    "addr:postcode":"07103",
    "addr:street":"Howard Ct",
    "iso:country":"US",
    "sg:address":"9 Howard Ct",
    "sg:city":"Newark",
    "sg:classifiers":[
        {
            "category":"Building & Trades",
            "subcategory":"Locksmith",
            "type":"Services"
        }
    ],
    "sg:phone":"+1 973 854 5435",
    "sg:postcode":"07103",
    "sg:province":"NJ",
    "sg:tags":[
        "key"
    ],
    "wof:name":"A 24-7 Emergency A Locksmith",
    "wof:placetype":"venue"
},
  "geometry": {"coordinates":[-74.183538,40.737639],"type":"Point"}
}