{
  "type": "Feature",
  "properties": {
    "iso:country":"US",
    "sg:address":"313 Philadelphia Ave",
    "sg:city":"Point Pleasant Beach",
    "sg:classifiers":[
        {
            "category":"Building & Trades",
            "subcategory":"Cleaning & Sanitation",
            "type":"Services"
        }
    ],
    "sg:phone":"+1   ",
    "sg:postcode":"08742",
    "sg:province":"NJ",
    "sg:tags":[
        "maintenance"
    ],
    "wof:name":"Maintenance Made Easy",
    "wof:placetype":"venue"
},
  "geometry": {"coordinates":[-74.045089,40.085782],"type":"Point"}
}