{
  "type": "Feature",
  "properties": {
    "iso:country":"US",
    "sg:address":"65 Ramapo Valley Rd",
    "sg:city":"Mahwah",
    "sg:classifiers":[
        {
            "category":"Building & Trades",
            "subcategory":"Electrical",
            "type":"Services"
        }
    ],
    "sg:phone":"+1 201 512 1792",
    "sg:postcode":"07430",
    "sg:province":"NJ",
    "sg:tags":[
        "electrical",
        "contractor"
    ],
    "wof:name":"J C Electric Inc",
    "wof:placetype":"venue"
},
  "geometry": {"coordinates":[-74.15091099999999,41.103255],"type":"Point"}
}