{
  "type": "Feature",
  "properties": {
    "iso:country":"US",
    "sg:address":"10 Franklin Tpke",
    "sg:city":"Waldwick",
    "sg:classifiers":[
        {
            "category":"Personal",
            "type":"Services"
        }
    ],
    "sg:phone":"+1   ",
    "sg:postcode":"07463",
    "sg:province":"NJ",
    "wof:name":"Monograms Unlimited",
    "wof:placetype":"venue"
},
  "geometry": {"coordinates":[-74.118815,41.00869],"type":"Point"}
}