{
  "type": "Feature",
  "properties": {
    "iso:country":"US",
    "sg:address":"103 Valencia Dr",
    "sg:city":"Brick",
    "sg:classifiers":[
        {
            "category":"Health Services",
            "subcategory":"Health Practitioner",
            "type":"Services"
        }
    ],
    "sg:phone":"+1 732 451 1182",
    "sg:postcode":"08723",
    "sg:province":"NJ",
    "sg:tags":[
        "nurse",
        "registry"
    ],
    "wof:name":"M D Haines",
    "wof:placetype":"venue"
},
  "geometry": {"coordinates":[-74.08461699999999,40.020654],"type":"Point"}
}