{
  "type": "Feature",
  "properties": {
    "addr:full":"555 2nd St Trenton NJ 08611",
    "addr:housenumber":"555",
    "addr:postcode":"08611",
    "addr:street":"2Nd St",
    "iso:country":"US",
    "sg:address":"555 2nd St",
    "sg:city":"Trenton",
    "sg:classifiers":[
        {
            "category":"Social Services",
            "subcategory":"Child Care",
            "type":"Services"
        }
    ],
    "sg:phone":"+1 609 394 3283",
    "sg:postcode":"08611",
    "sg:province":"NJ",
    "sg:tags":[
        "kindergarten",
        "academic",
        "school"
    ],
    "wof:name":"Howley School Pre-School",
    "wof:placetype":"venue"
},
  "geometry": {"coordinates":[-74.756381,40.203031],"type":"Point"}
}