{
  "type": "Feature",
  "properties": {
    "addr:full":"1610 State Rte 88 Brick NJ 08724",
    "addr:housenumber":"1610",
    "addr:postcode":"08724",
    "addr:street":"State Rte 88",
    "iso:country":"US",
    "sg:address":"1610 State Rte 88",
    "sg:city":"Brick",
    "sg:classifiers":[
        {
            "category":"Social Services",
            "type":"Services"
        }
    ],
    "sg:phone":"+1 732 202 0666",
    "sg:postcode":"08724",
    "sg:province":"NJ",
    "sg:tags":[
        "organization",
        "welfare"
    ],
    "wof:name":"Ocean Partnership-Children Inc",
    "wof:placetype":"venue"
},
  "geometry": {"coordinates":[-74.13686199999999,40.07843],"type":"Point"}
}