{
  "type": "Feature",
  "properties": {
    "addr:full":"179 Woodbridge Ave Highland Park NJ 08904",
    "addr:housenumber":"179",
    "addr:postcode":"08904",
    "addr:street":"Woodbridge Ave",
    "iso:country":"US",
    "sg:address":"179 Woodbridge Ave",
    "sg:city":"Highland Park",
    "sg:classifiers":[
        {
            "category":"Shopping",
            "subcategory":"Gifts & Souvenirs",
            "type":"Retail Goods"
        }
    ],
    "sg:phone":"+1 732 572 3286",
    "sg:postcode":"08904",
    "sg:province":"NJ",
    "sg:tags":[
        "shop"
    ],
    "wof:name":"Neil's Classic Novelty",
    "wof:placetype":"venue"
},
  "geometry": {"coordinates":[-74.413522,40.501347],"type":"Point"}
}