{
  "type": "Feature",
  "properties": {
    "iso:country":"US",
    "sg:address":"464 North Ave",
    "sg:city":"Elizabeth",
    "sg:classifiers":[
        {
            "category":"Wholesale",
            "subcategory":"Medical Equipment & Supplies",
            "type":"Manufacturing & Wholesale Goods"
        }
    ],
    "sg:phone":"+1 908 355 0200",
    "sg:postcode":"07208",
    "sg:province":"NJ",
    "wof:name":"Advanced Medical Rejuvenation",
    "wof:placetype":"venue"
},
  "geometry": {"coordinates":[-74.231236,40.670509],"type":"Point"}
}