{
  "type": "Feature",
  "properties": {
    "addr:full":"87 Newark Pompton Tpke Little Falls NJ 07424",
    "addr:housenumber":"87",
    "addr:postcode":"07424",
    "addr:street":"Newark Pompton Tpke",
    "iso:country":"US",
    "sg:address":"87 Newark Pompton Tpke",
    "sg:city":"Little Falls",
    "sg:classifiers":[
        {
            "category":"Professional",
            "type":"Services"
        },
        {
            "category":"Deli",
            "type":"Food & Drink"
        },
        {
            "category":"Bakery",
            "type":"Food & Drink"
        }
    ],
    "sg:phone":"+1 973 256 2246",
    "sg:postcode":"07424",
    "sg:province":"NJ",
    "sg:tags":[
        "caterer"
    ],
    "wof:name":"Farnese Pastry Shop & Delicatessen",
    "wof:placetype":"venue"
},
  "geometry": {"coordinates":[-74.24400300000001,40.883598],"type":"Point"}
}