{
  "type": "Feature",
  "properties": {
    "iso:country":"US",
    "sg:address":"28 Lower Main St",
    "sg:city":"Matawan",
    "sg:classifiers":[
        {
            "category":"Building & Trades",
            "subcategory":"Construction",
            "type":"Services"
        }
    ],
    "sg:phone":"+1 732 583 6034",
    "sg:postcode":"07747",
    "sg:province":"NJ",
    "sg:tags":[
        "house"
    ],
    "wof:name":"Galant Contracting Company",
    "wof:placetype":"venue"
},
  "geometry": {"coordinates":[-74.214592,40.425483],"type":"Point"}
}