{
  "type": "Feature",
  "properties": {
    "addr:full":"8 Dorchester Dr Jamesburg NJ 08831",
    "addr:housenumber":"8",
    "addr:postcode":"08831",
    "addr:street":"Dorchester Dr",
    "iso:country":"US",
    "sg:address":"8 Dorchester Dr",
    "sg:city":"Jamesburg",
    "sg:classifiers":[
        {
            "category":"Real Estate",
            "subcategory":"Real Estate Operator",
            "type":"Services"
        }
    ],
    "sg:phone":"+1 609 448 4801",
    "sg:postcode":"08831",
    "sg:province":"NJ",
    "sg:tags":[
        "apartment"
    ],
    "wof:name":"Princeton Arms",
    "wof:placetype":"venue"
},
  "geometry": {"coordinates":[-74.444749,40.312708],"type":"Point"}
}