{
  "type": "Feature",
  "properties": {
    "addr:full":"59 Brighton Ave Long Branch NJ 07740",
    "addr:housenumber":"59",
    "addr:postcode":"07740",
    "addr:street":"Brighton Ave",
    "iso:country":"US",
    "sg:address":"59 Brighton Ave",
    "sg:city":"Long Branch",
    "sg:classifiers":[
        {
            "category":"Professional",
            "subcategory":"Computer Services",
            "type":"Services"
        }
    ],
    "sg:phone":"+1 732 222 2810",
    "sg:postcode":"07740",
    "sg:province":"NJ",
    "sg:tags":[
        "prepackaged",
        "software"
    ],
    "wof:name":"Corporate Software Tech",
    "wof:placetype":"venue"
},
  "geometry": {"coordinates":[-73.98423099999999,40.284632],"type":"Point"}
}