{
  "type": "Feature",
  "properties": {
    "iso:country":"US",
    "sg:address":"540 State Rte 47",
    "sg:city":"Cape May",
    "sg:phone":"+1 609 889 8810",
    "sg:postcode":"08204",
    "sg:province":"NJ",
    "sg:tags":[
        "product",
        "petroleum"
    ],
    "wof:name":"Mini Mart",
    "wof:placetype":"venue"
},
  "geometry": {"coordinates":[-74.899168,39.042024],"type":"Point"}
}