{
  "type": "Feature",
  "properties": {
    "addr:full":"626 Springfield Ave Cranford NJ 07016",
    "addr:housenumber":"626",
    "addr:postcode":"07016",
    "addr:street":"Springfield Ave",
    "iso:country":"US",
    "sg:address":"626 Springfield Ave",
    "sg:city":"Cranford",
    "sg:classifiers":[
        {
            "category":"Professional",
            "type":"Services"
        }
    ],
    "sg:phone":"+1   ",
    "sg:postcode":"07016",
    "sg:province":"NJ",
    "wof:name":"C T ONeill General Contracto",
    "wof:placetype":"venue"
},
  "geometry": {"coordinates":[-74.31182,40.663418],"type":"Point"}
}