{
  "type": "Feature",
  "properties": {
    "iso:country":"US",
    "sg:address":"685 Van Houten Ave",
    "sg:city":"Clifton",
    "sg:classifiers":[
        {
            "category":"Professional",
            "subcategory":"Lawyer & Legal Services",
            "type":"Services"
        }
    ],
    "sg:phone":"+1 973 778 7777",
    "sg:postcode":"07013",
    "sg:province":"NJ",
    "wof:name":"Kyles Theodore ESQ",
    "wof:placetype":"venue"
},
  "geometry": {"coordinates":[-74.15010100000001,40.8591],"type":"Point"}
}