{
  "type": "Feature",
  "properties": {
    "iso:country":"US",
    "sg:address":"201 State Rte 10",
    "sg:city":"Succasunna",
    "sg:classifiers":[
        {
            "category":"Real Estate",
            "subcategory":"Real Estate Agent",
            "type":"Services"
        }
    ],
    "sg:phone":"+1 973 584 7580",
    "sg:postcode":"07876",
    "sg:province":"NJ",
    "wof:name":"Joe Tekula Realtors",
    "wof:placetype":"venue"
},
  "geometry": {"coordinates":[-74.640619,40.868345],"type":"Point"}
}