{
  "type": "Feature",
  "properties": {
    "iso:country":"US",
    "sg:address":"106 Harbor Dr",
    "sg:city":"Jersey City",
    "sg:classifiers":[
        {
            "category":"Wholesale",
            "subcategory":"Durable Goods & Equipment",
            "type":"Manufacturing & Wholesale Goods"
        }
    ],
    "sg:phone":"+1 201 332 7600",
    "sg:postcode":"07305",
    "sg:province":"NJ",
    "sg:tags":[
        "importer"
    ],
    "wof:name":"Dan-Dee Intl LTD",
    "wof:placetype":"venue"
},
  "geometry": {"coordinates":[-74.088712,40.680707],"type":"Point"}
}