{
  "type": "Feature",
  "properties": {
    "iso:country":"US",
    "sg:address":"6001 Echelon Mall",
    "sg:city":"Voorhees",
    "sg:classifiers":[
        {
            "category":"Shopping",
            "subcategory":"Department Store",
            "type":"Retail Goods"
        }
    ],
    "sg:phone":"+1 856 772 6400",
    "sg:postcode":"08043",
    "sg:province":"NJ",
    "wof:name":"Boscov's Department Store",
    "wof:placetype":"venue"
},
  "geometry": {"coordinates":[-75.002196,39.848656],"type":"Point"}
}