{
  "type": "Feature",
  "properties": {
    "iso:country":"US",
    "sg:address":"3003 Route 130",
    "sg:city":"Delran",
    "sg:classifiers":[
        {
            "category":"Retail",
            "subcategory":"Portrait Studio",
            "type":"Services"
        },
        {
            "category":"Shopping",
            "subcategory":"Pharmacy",
            "type":"Retail Goods"
        }
    ],
    "sg:phone":"+1 856 764 5507",
    "sg:postcode":"08075",
    "sg:province":"NJ",
    "sg:tags":[
        "photography",
        "drugstore",
        "store"
    ],
    "sg:website":"www.cvs.com",
    "wof:name":"Cvs-Pharmacy",
    "wof:placetype":"venue"
},
  "geometry": {"coordinates":[-74.950897,40.027199],"type":"Point"}
}