{
  "type": "Feature",
  "properties": {
    "addr:full":"1500 Route 38 Cherry Hill NJ 08002",
    "addr:housenumber":"1500",
    "addr:postcode":"08002",
    "addr:street":"Route 38",
    "iso:country":"US",
    "sg:address":"1500 Route 38",
    "sg:city":"Cherry Hill",
    "sg:classifiers":[
        {
            "category":"Building & Trades",
            "subcategory":"Locksmith",
            "type":"Services"
        }
    ],
    "sg:phone":"+1 856 324 4633",
    "sg:postcode":"08002",
    "sg:province":"NJ",
    "sg:tags":[
        "key"
    ],
    "wof:name":"24 Hour Emergency Locksmith",
    "wof:placetype":"venue"
},
  "geometry": {"coordinates":[-75.035175,39.937604],"type":"Point"}
}