{
  "type": "Feature",
  "properties": {
    "addr:full":"231 Longwood Dr Englishtown NJ 07726",
    "addr:housenumber":"231",
    "addr:postcode":"07726",
    "addr:street":"Longwood Dr",
    "iso:country":"US",
    "sg:address":"231 Longwood Dr",
    "sg:city":"Englishtown",
    "sg:classifiers":[
        {
            "category":"Professional",
            "subcategory":"Management & Consulting",
            "type":"Services"
        }
    ],
    "sg:phone":"+1   ",
    "sg:postcode":"07726",
    "sg:province":"NJ",
    "sg:tags":[
        "business"
    ],
    "wof:name":"Direct Perception L L C",
    "wof:placetype":"venue"
},
  "geometry": {"coordinates":[-74.35130599999999,40.31033],"type":"Point"}
}