{
  "type": "Feature",
  "properties": {
    "addr:full":"49 Sunset Inn Rd Lafayette NJ 07848",
    "addr:housenumber":"49",
    "addr:postcode":"07848",
    "addr:street":"Sunset Inn Rd",
    "iso:country":"US",
    "sg:address":"49 Sunset Inn Rd",
    "sg:city":"Lafayette",
    "sg:classifiers":[
        {
            "category":"Arts & Performance",
            "subcategory":"Theater",
            "type":"Entertainment"
        }
    ],
    "sg:phone":"+1   ",
    "sg:postcode":"07848",
    "sg:province":"NJ",
    "sg:tags":[
        "group"
    ],
    "wof:name":"Mountainside Stables & Pony Ex",
    "wof:placetype":"venue"
},
  "geometry": {"coordinates":[-74.688085,41.076888],"type":"Point"}
}