{
  "type": "Feature",
  "properties": {
    "addr:full":"7 S Davis Ave Audubon NJ 08106",
    "addr:housenumber":"7",
    "addr:postcode":"08106",
    "addr:street":"S Davis Ave",
    "iso:country":"US",
    "sg:address":"7 S Davis Ave",
    "sg:city":"Audubon",
    "sg:classifiers":[
        {
            "category":"Organizations",
            "subcategory":"Labor Organization",
            "type":"Services"
        }
    ],
    "sg:phone":"+1 856 547 8037",
    "sg:postcode":"08106",
    "sg:province":"NJ",
    "wof:name":"Matthew Gaehring",
    "wof:placetype":"venue"
},
  "geometry": {"coordinates":[-75.06604400000001,39.897965],"type":"Point"}
}