{
  "type": "Feature",
  "properties": {
    "addr:full":"227 Monticello Ave Jersey City NJ 07304",
    "addr:housenumber":"227",
    "addr:postcode":"07304",
    "addr:street":"Monticello Ave",
    "iso:country":"US",
    "sg:address":"227 Monticello Ave",
    "sg:city":"Jersey City",
    "sg:classifiers":[
        {
            "category":"Retail",
            "subcategory":"Auto Repair",
            "type":"Services"
        }
    ],
    "sg:phone":"+1 201 332 8542",
    "sg:postcode":"07304",
    "sg:province":"NJ",
    "sg:tags":[
        "automobile",
        "inspection",
        "automotive"
    ],
    "wof:name":"S & S Auto Repairs Inc",
    "wof:placetype":"venue"
},
  "geometry": {"coordinates":[-74.069503,40.722357],"type":"Point"}
}