{
  "type": "Feature",
  "properties": {
    "addr:full":"2 Lincoln St Jersey City NJ 07307",
    "addr:housenumber":"2",
    "addr:postcode":"07307",
    "addr:street":"Lincoln St",
    "iso:country":"US",
    "sg:address":"2 Lincoln St",
    "sg:city":"Jersey City",
    "sg:classifiers":[
        {
            "category":"Building & Trades",
            "subcategory":"Locksmith",
            "type":"Services"
        }
    ],
    "sg:phone":"+1 201 793 1461",
    "sg:postcode":"07307",
    "sg:province":"NJ",
    "sg:tags":[
        "key"
    ],
    "wof:name":"Always Available Emergency Locksmith",
    "wof:placetype":"venue"
},
  "geometry": {"coordinates":[-74.04886399999999,40.746738],"type":"Point"}
}