{
  "type": "Feature",
  "properties": {
    "iso:country":"US",
    "sg:address":"127 Wilson Ave",
    "sg:city":"Matawan",
    "sg:classifiers":[
        {
            "category":"Real Estate",
            "subcategory":"Architect",
            "type":"Services"
        }
    ],
    "sg:phone":"+1 732 566 9668",
    "sg:postcode":"07747",
    "sg:province":"NJ",
    "wof:name":"Mark Teichman",
    "wof:placetype":"venue"
},
  "geometry": {"coordinates":[-74.244038,40.396504],"type":"Point"}
}