{
  "type": "Feature",
  "properties": {
    "iso:country":"US",
    "sg:address":"219 Carroll St",
    "sg:city":"Paterson",
    "sg:classifiers":[
        {
            "category":"Organizations",
            "subcategory":"Religious Organization",
            "type":"Services"
        }
    ],
    "sg:phone":"+1 973 742 5553",
    "sg:postcode":"07501",
    "sg:province":"NJ",
    "sg:tags":[
        "church"
    ],
    "wof:name":"Church Of The Holy Communion",
    "wof:placetype":"venue"
},
  "geometry": {"coordinates":[-74.161886,40.917099],"type":"Point"}
}