{
  "type": "Feature",
  "properties": {
    "addr:full":"2089 State Rte 70 Cherry Hill NJ 08003",
    "addr:housenumber":"2089",
    "addr:postcode":"08003",
    "addr:street":"State Rte 70",
    "iso:country":"US",
    "sg:address":"2089 State Rte 70",
    "sg:city":"Cherry Hill",
    "sg:classifiers":[
        {
            "category":"Professional",
            "type":"Services"
        }
    ],
    "sg:phone":"+1 856 424 4776",
    "sg:postcode":"08003",
    "sg:province":"NJ",
    "sg:tags":[
        "establishment"
    ],
    "wof:name":"Forty Winks Inc",
    "wof:placetype":"venue"
},
  "geometry": {"coordinates":[-74.952084,39.897603],"type":"Point"}
}