{
  "type": "Feature",
  "properties": {
    "iso:country":"US",
    "sg:address":"505 Morris Ave",
    "sg:city":"Springfield",
    "sg:classifiers":[
        {
            "category":"Professional",
            "subcategory":"Lawyer & Legal Services",
            "type":"Services"
        }
    ],
    "sg:phone":"+1 973 593 4900",
    "sg:postcode":"07081",
    "sg:province":"NJ",
    "sg:tags":[
        "personal",
        "injury"
    ],
    "wof:name":"Epstein Epstein Brown & Bosek",
    "wof:placetype":"venue"
},
  "geometry": {"coordinates":[-74.319801,40.714802],"type":"Point"}
}