{
  "type": "Feature",
  "properties": {
    "iso:country":"US",
    "sg:address":"402 Kennedy Blvd",
    "sg:city":"Bayonne",
    "sg:classifiers":[
        {
            "category":"Retail",
            "subcategory":"Auto Repair",
            "type":"Services"
        }
    ],
    "sg:phone":"+1 201 858 4447",
    "sg:postcode":"07002",
    "sg:province":"NJ",
    "sg:tags":[
        "body",
        "shop"
    ],
    "wof:name":"Boulevard Automotive Center",
    "wof:placetype":"venue"
},
  "geometry": {"coordinates":[-74.128027,40.660139],"type":"Point"}
}