{
  "type": "Feature",
  "properties": {
    "addr:full":"29 Cross St West Orange NJ 07052",
    "addr:housenumber":"29",
    "addr:postcode":"07052",
    "addr:street":"Cross St",
    "iso:country":"US",
    "sg:address":"29 Cross St",
    "sg:city":"West Orange",
    "sg:classifiers":[
        {
            "category":"Organizations",
            "subcategory":"Religious Organization",
            "type":"Services"
        }
    ],
    "sg:phone":"+1 973 643 8414",
    "sg:postcode":"07052",
    "sg:province":"NJ",
    "wof:name":"New Zion Revival Temple Church",
    "wof:placetype":"venue"
},
  "geometry": {"coordinates":[-74.247733,40.768801],"type":"Point"}
}