{
  "type": "Feature",
  "properties": {
    "iso:country":"US",
    "sg:address":"1301 State Rte 73",
    "sg:city":"Mt Laurel",
    "sg:classifiers":[
        {
            "category":"Autos & Motor Vehicles",
            "subcategory":"Automobile Sales",
            "type":"Retail Goods"
        }
    ],
    "sg:phone":"+1 856 866 0111",
    "sg:postcode":"08054",
    "sg:province":"NJ",
    "sg:tags":[
        "car",
        "dealer"
    ],
    "sg:website":"www.holmanauto.com",
    "wof:name":"Holman Enterprises Rice & Hlmn",
    "wof:placetype":"venue"
},
  "geometry": {"coordinates":[-74.87873399999999,39.920819],"type":"Point"}
}