{
  "type": "Feature",
  "properties": {
    "iso:country":"US",
    "sg:address":"500 Market St",
    "sg:city":"Perth Amboy",
    "sg:classifiers":[
        {
            "category":"Wholesale",
            "subcategory":"Machinery & Supplies",
            "type":"Manufacturing & Wholesale Goods"
        }
    ],
    "sg:phone":"+1 732 442 1200",
    "sg:postcode":"08861",
    "sg:province":"NJ",
    "sg:tags":[
        "abrasive"
    ],
    "wof:name":"Abrasive Machine & Supply",
    "wof:placetype":"venue"
},
  "geometry": {"coordinates":[-74.285825,40.51184],"type":"Point"}
}