{
  "type": "Feature",
  "properties": {
    "addr:full":"4 Smith Branch Rd White House Station NJ 08889",
    "addr:housenumber":"4",
    "addr:postcode":"08889",
    "addr:street":"Smith Branch Rd",
    "iso:country":"US",
    "sg:address":"4 Smith Branch Rd",
    "sg:city":"White House Station",
    "sg:classifiers":[
        {
            "category":"Building & Trades",
            "subcategory":"Construction",
            "type":"Services"
        }
    ],
    "sg:phone":"+1 908 534 8991",
    "sg:postcode":"08889",
    "sg:province":"NJ",
    "sg:tags":[
        "house"
    ],
    "wof:name":"Dlh Construction",
    "wof:placetype":"venue"
},
  "geometry": {"coordinates":[-74.730908,40.601973],"type":"Point"}
}