{
  "type": "Feature",
  "properties": {
    "addr:full":"273 Edwards St Ridgewood NJ 07450",
    "addr:housenumber":"273",
    "addr:postcode":"07450",
    "addr:street":"Edwards St",
    "iso:country":"US",
    "sg:address":"273 Edwards St",
    "sg:city":"Ridgewood",
    "sg:classifiers":[
        {
            "category":"Building & Trades",
            "subcategory":"Construction",
            "type":"Services"
        }
    ],
    "sg:phone":"+1 201 612 1355",
    "sg:postcode":"07450",
    "sg:province":"NJ",
    "sg:tags":[
        "general",
        "contractor"
    ],
    "wof:name":"Dragonetti Construction Co",
    "wof:placetype":"venue"
},
  "geometry": {"coordinates":[-74.12248099999999,40.973474],"type":"Point"}
}