{
  "type": "Feature",
  "properties": {
    "addr:full":"2001 State Rte 35 Matawan NJ 07735",
    "addr:housenumber":"2001",
    "addr:postcode":"07735",
    "addr:street":"State Rte 35",
    "iso:country":"US",
    "sg:address":"2001 State Rte 35",
    "sg:city":"Matawan",
    "sg:classifiers":[
        {
            "category":"Restaurant",
            "type":"Food & Drink"
        }
    ],
    "sg:phone":"+1   ",
    "sg:postcode":"07735",
    "sg:province":"NJ",
    "sg:tags":[
        "eating"
    ],
    "wof:name":"Starbucks",
    "wof:placetype":"venue"
},
  "geometry": {"coordinates":[-74.23676500000001,40.448948],"type":"Point"}
}