{
  "type": "Feature",
  "properties": {
    "iso:country":"US",
    "sg:address":"1311 Route 37 W",
    "sg:city":"Toms River",
    "sg:classifiers":[
        {
            "category":"Restaurant",
            "type":"Food & Drink"
        }
    ],
    "sg:menulink":"http://www.allmenus.com/nj/toms-river/291148-picassos-ii-pizza--italian/menu/",
    "sg:phone":"+1 732 341 1167",
    "sg:postcode":"08755",
    "sg:province":"NJ",
    "sg:tags":[
        "american",
        "pizza"
    ],
    "wof:name":"Picasso's II Pizza & Italian",
    "wof:placetype":"venue"
},
  "geometry": {"coordinates":[-74.256248,39.981576],"type":"Point"}
}