{
  "type": "Feature",
  "properties": {
    "iso:country":"US",
    "sg:address":"1642 Glassboro Rd",
    "sg:city":"Williamstown",
    "sg:classifiers":[
        {
            "category":"Autos & Motor Vehicles",
            "subcategory":"Automobile Sales",
            "type":"Retail Goods"
        }
    ],
    "sg:phone":"+1   ",
    "sg:postcode":"08094",
    "sg:province":"NJ",
    "sg:tags":[
        "used"
    ],
    "wof:name":"Carousel Cars Inc",
    "wof:placetype":"venue"
},
  "geometry": {"coordinates":[-75.06737800000001,39.697554],"type":"Point"}
}