{
  "type": "Feature",
  "properties": {
    "iso:country":"US",
    "sg:address":"93 Apple Ridge Rd",
    "sg:city":"Woodcliff Lake",
    "sg:classifiers":[
        {
            "category":"Insurance",
            "subcategory":"Insurance Agent",
            "type":"Services"
        }
    ],
    "sg:phone":"+1   ",
    "sg:postcode":"07677",
    "sg:province":"NJ",
    "sg:tags":[
        "consulting"
    ],
    "wof:name":"Risk Logic Inc",
    "wof:placetype":"venue"
},
  "geometry": {"coordinates":[-74.07790199999999,41.021327],"type":"Point"}
}