{
  "type": "Feature",
  "properties": {
    "addr:full":"175 Main St Orange NJ 07050",
    "addr:housenumber":"175",
    "addr:postcode":"07050",
    "addr:street":"Main St",
    "iso:country":"US",
    "sg:address":"175 Main St",
    "sg:city":"Orange",
    "sg:classifiers":[
        {
            "category":"Professional",
            "subcategory":"Employment Agencies",
            "type":"Services"
        }
    ],
    "sg:phone":"+1 973 675 0249",
    "sg:postcode":"07050",
    "sg:province":"NJ",
    "sg:tags":[
        "help",
        "contractor"
    ],
    "wof:name":"Temporary Solutions Inc",
    "wof:placetype":"venue"
},
  "geometry": {"coordinates":[-74.225459,40.770507],"type":"Point"}
}