{
  "type": "Feature",
  "properties": {
    "iso:country":"US",
    "sg:address":"6721 Town Ct N",
    "sg:city":"Lawrenceville",
    "sg:classifiers":[
        {
            "category":"Shopping",
            "subcategory":"Computers & Home Electronics",
            "type":"Retail Goods"
        }
    ],
    "sg:phone":"+1 732 928 0177",
    "sg:postcode":"08648",
    "sg:province":"NJ",
    "sg:tags":[
        "software"
    ],
    "wof:name":"G V Software",
    "wof:placetype":"venue"
},
  "geometry": {"coordinates":[-74.677555,40.285621],"type":"Point"}
}