{
  "type": "Feature",
  "properties": {
    "iso:country":"US",
    "sg:address":"22 Tall Oaks Ln",
    "sg:city":"Budd Lake",
    "sg:classifiers":[
        {
            "category":"Manufacturing",
            "subcategory":"Glass & Minerals",
            "type":"Manufacturing & Wholesale Goods"
        }
    ],
    "sg:phone":"+1 973 448 2445",
    "sg:postcode":"07828",
    "sg:province":"NJ",
    "sg:tags":[
        "ready",
        "concrete",
        "mfg"
    ],
    "wof:name":"Ready Set Go LLC",
    "wof:placetype":"venue"
},
  "geometry": {"coordinates":[-74.724373,40.878906],"type":"Point"}
}