{
  "type": "Feature",
  "properties": {
    "iso:country":"US",
    "sg:address":"20 Bloomfield Ave",
    "sg:city":"Flemington",
    "sg:classifiers":[
        {
            "category":"Insurance",
            "subcategory":"Insurance Agent",
            "type":"Services"
        },
        {
            "category":"Insurance",
            "subcategory":"Hazard Insurance",
            "type":"Services"
        }
    ],
    "sg:phone":"+1 908 782 3710",
    "sg:postcode":"08822",
    "sg:province":"NJ",
    "sg:tags":[
        "auto",
        "recreational",
        "motorcycle",
        "vehicle",
        "marine",
        "boat"
    ],
    "sg:website":"http://www.M-NINS.COM",
    "wof:name":"McPherson & Newland Insurance Services",
    "wof:placetype":"venue"
},
  "geometry": {"coordinates":[-74.85776,40.51121],"type":"Point"}
}