{
  "type": "Feature",
  "properties": {
    "addr:full":"165 Passaic St Passaic NJ 07055",
    "addr:housenumber":"165",
    "addr:postcode":"07055",
    "addr:street":"Passaic St",
    "iso:country":"US",
    "sg:address":"165 Passaic St",
    "sg:city":"Passaic",
    "sg:classifiers":[
        {
            "category":"Bars & Pubs",
            "type":"Food & Drink"
        }
    ],
    "sg:phone":"+1 973 458 1106",
    "sg:postcode":"07055",
    "sg:province":"NJ",
    "sg:tags":[
        "lounge",
        "drinking",
        "cocktail"
    ],
    "wof:name":"Jaguar Night Club",
    "wof:placetype":"venue"
},
  "geometry": {"coordinates":[-74.11558100000001,40.862212],"type":"Point"}
}