{
  "type": "Feature",
  "properties": {
    "iso:country":"US",
    "sg:address":"730 Garden St",
    "sg:city":"Carlstadt",
    "sg:classifiers":[
        {
            "category":"Wholesale",
            "subcategory":"Durable Goods & Equipment",
            "type":"Manufacturing & Wholesale Goods"
        }
    ],
    "sg:phone":"+1 201 933 6557",
    "sg:postcode":"07072",
    "sg:province":"NJ",
    "sg:tags":[
        "importer"
    ],
    "wof:name":"Maxxon USA Corp",
    "wof:placetype":"venue"
},
  "geometry": {"coordinates":[-74.09615100000001,40.846791],"type":"Point"}
}