{
  "type": "Feature",
  "properties": {
    "addr:full":"9 Paris Ave Edison NJ 08820",
    "addr:housenumber":"9",
    "addr:postcode":"08820",
    "addr:street":"Paris Ave",
    "iso:country":"US",
    "sg:address":"9 Paris Ave",
    "sg:city":"Edison",
    "sg:classifiers":[
        {
            "category":"Real Estate",
            "subcategory":"Architect",
            "type":"Services"
        }
    ],
    "sg:phone":"+1   ",
    "sg:postcode":"08820",
    "sg:province":"NJ",
    "sg:tags":[
        "construction",
        "design",
        "architectural"
    ],
    "wof:name":"Katan Inc",
    "wof:placetype":"venue"
},
  "geometry": {"coordinates":[-74.342405,40.566433],"type":"Point"}
}