{
  "type": "Feature",
  "properties": {
    "iso:country":"US",
    "sg:address":"181 N Main St",
    "sg:city":"Lambertville",
    "sg:classifiers":[
        {
            "category":"Organizations",
            "subcategory":"Non-profit Organization",
            "type":"Services"
        }
    ],
    "sg:phone":"+1 609 397 1130",
    "sg:postcode":"08530",
    "sg:province":"NJ",
    "wof:name":"S Hunterdon Apartments",
    "wof:placetype":"venue"
},
  "geometry": {"coordinates":[-74.94465099999999,40.372243],"type":"Point"}
}