{
  "type": "Feature",
  "properties": {
    "iso:country":"US",
    "sg:address":"17 Ackerman Ave",
    "sg:city":"Oradell",
    "sg:classifiers":[
        {
            "category":"Organizations",
            "subcategory":"Community Association",
            "type":"Services"
        }
    ],
    "sg:phone":"+1 201 265 4499",
    "sg:postcode":"07649",
    "sg:province":"NJ",
    "sg:tags":[
        "fraternal"
    ],
    "wof:name":"Pascack Valley PBA",
    "wof:placetype":"venue"
},
  "geometry": {"coordinates":[-74.03086399999999,40.943689],"type":"Point"}
}