{
  "type": "Feature",
  "properties": {
    "iso:country":"US",
    "sg:address":"339 Communipaw Ave",
    "sg:city":"Jersey City",
    "sg:classifiers":[
        {
            "category":"Building & Trades",
            "subcategory":"Pest Control",
            "type":"Services"
        }
    ],
    "sg:phone":"+1 201 433 2777",
    "sg:postcode":"07304",
    "sg:province":"NJ",
    "wof:name":"Brownstone Pest Control",
    "wof:placetype":"venue"
},
  "geometry": {"coordinates":[-74.06210799999999,40.710776],"type":"Point"}
}