{
  "type": "Feature",
  "properties": {
    "addr:full":"589 Blackwood Clementon Rd Clementon NJ 08021",
    "addr:housenumber":"589",
    "addr:postcode":"08021",
    "addr:street":"Blackwood Clementon Rd",
    "iso:country":"US",
    "sg:address":"589 Blackwood Clementon Rd",
    "sg:city":"Clementon",
    "sg:classifiers":[
        {
            "category":"Personal",
            "subcategory":"Beauty Salon",
            "type":"Services"
        }
    ],
    "sg:phone":"+1 856 566 4499",
    "sg:postcode":"08021",
    "sg:province":"NJ",
    "sg:tags":[
        "shop"
    ],
    "wof:name":"So It Is African Market",
    "wof:placetype":"venue"
},
  "geometry": {"coordinates":[-75.00536,39.805227],"type":"Point"}
}