{
  "type": "Feature",
  "properties": {
    "addr:full":"16 Edgeworth Pl New Brunswick NJ 08901",
    "addr:housenumber":"16",
    "addr:postcode":"08901",
    "addr:street":"Edgeworth Pl",
    "iso:country":"US",
    "sg:address":"16 Edgeworth Pl",
    "sg:city":"New Brunswick",
    "sg:classifiers":[
        {
            "category":"Professional",
            "subcategory":"Employment Agencies",
            "type":"Services"
        }
    ],
    "sg:phone":"+1 732 684 2440",
    "sg:postcode":"08901",
    "sg:province":"NJ",
    "sg:tags":[
        "help",
        "supply"
    ],
    "wof:name":"Zayas Transport Company LLP",
    "wof:placetype":"venue"
},
  "geometry": {"coordinates":[-74.45794100000001,40.48508],"type":"Point"}
}