{
  "type": "Feature",
  "properties": {
    "iso:country":"US",
    "sg:address":"1903 Colonial Gardens Dr",
    "sg:city":"Avenel",
    "sg:classifiers":[
        {
            "category":"Real Estate",
            "subcategory":"Real Estate Agent",
            "type":"Services"
        }
    ],
    "sg:phone":"+1 732 382 9699",
    "sg:postcode":"07001",
    "sg:province":"NJ",
    "wof:name":"Atlantic Realty",
    "wof:placetype":"venue"
},
  "geometry": {"coordinates":[-74.281391,40.586097],"type":"Point"}
}