{
  "type": "Feature",
  "properties": {
    "iso:country":"US",
    "sg:address":"53 Broad St",
    "sg:city":"Bloomfield",
    "sg:classifiers":[
        {
            "category":"Shopping",
            "subcategory":"Clothing, Apparel, & Fashions",
            "type":"Retail Goods"
        }
    ],
    "sg:phone":"+1 973 429 5722",
    "sg:postcode":"07003",
    "sg:province":"NJ",
    "wof:name":"Fashion Lady",
    "wof:placetype":"venue"
},
  "geometry": {"coordinates":[-74.197383,40.795406],"type":"Point"}
}