{
  "type": "Feature",
  "properties": {
    "iso:country":"US",
    "sg:address":"1217 Main St",
    "sg:city":"Bradley Beach",
    "sg:classifiers":[
        {
            "category":"Sports & Exercise",
            "subcategory":"Bowling",
            "type":"Entertainment"
        }
    ],
    "sg:phone":"+1 732 774 4540",
    "sg:postcode":"07720",
    "sg:province":"NJ",
    "sg:tags":[
        "center"
    ],
    "wof:name":"Brunswick Bradley Beach Lanes",
    "wof:placetype":"venue"
},
  "geometry": {"coordinates":[-74.01612900000001,40.208374],"type":"Point"}
}