{
  "type": "Feature",
  "properties": {
    "iso:country":"US",
    "sg:address":"624 Washington St",
    "sg:city":"Hoboken",
    "sg:classifiers":[
        {
            "category":"Real Estate",
            "subcategory":"Real Estate Agent",
            "type":"Services"
        }
    ],
    "sg:phone":"+1   ",
    "sg:postcode":"07030",
    "sg:province":"NJ",
    "wof:name":"624 Realty LLP",
    "wof:placetype":"venue"
},
  "geometry": {"coordinates":[-74.02881499999999,40.744435],"type":"Point"}
}