{
  "type": "Feature",
  "properties": {
    "iso:country":"US",
    "sg:address":"187 State Rte 94",
    "sg:city":"Lafayette",
    "sg:classifiers":[
        {
            "category":"Farming",
            "subcategory":"Orchard",
            "type":"Manufacturing & Wholesale Goods"
        }
    ],
    "sg:phone":"+1 973 579 5860",
    "sg:postcode":"07848",
    "sg:province":"NJ",
    "wof:name":"Orchard Hill Special WSTE Mgmt",
    "wof:placetype":"venue"
},
  "geometry": {"coordinates":[-74.70431499999999,41.091038],"type":"Point"}
}