{
  "type": "Feature",
  "properties": {
    "iso:country":"US",
    "sg:address":"46 Wehrli Rd",
    "sg:city":"Long Valley",
    "sg:classifiers":[
        {
            "category":"Community Center",
            "type":"Public Place"
        }
    ],
    "sg:phone":"+1 908 876 4114",
    "sg:postcode":"07853",
    "sg:province":"NJ",
    "sg:tags":[
        "medical"
    ],
    "wof:name":"Mountain Medical Systems Inc",
    "wof:placetype":"venue"
},
  "geometry": {"coordinates":[-74.811897,40.791199],"type":"Point"}
}