{
  "type": "Feature",
  "properties": {
    "iso:country":"US",
    "sg:address":"1 Beverly Rd",
    "sg:city":"Summit",
    "sg:classifiers":[
        {
            "category":"Education",
            "subcategory":"School",
            "type":"Public Place"
        }
    ],
    "sg:phone":"+1 908 273 1157",
    "sg:postcode":"07901",
    "sg:province":"NJ",
    "sg:tags":[
        "elementary"
    ],
    "wof:name":"Oratory Prep School",
    "wof:placetype":"venue"
},
  "geometry": {"coordinates":[-74.369698,40.7243],"type":"Point"}
}