{
  "type": "Feature",
  "properties": {
    "addr:full":"103 Washington Ave Egg Harbor City NJ 08215",
    "addr:housenumber":"103",
    "addr:postcode":"08215",
    "addr:street":"Washington Ave",
    "iso:country":"US",
    "sg:address":"103 Washington Ave",
    "sg:city":"Egg Harbor City",
    "sg:classifiers":[
        {
            "category":"Restaurant",
            "type":"Food & Drink"
        }
    ],
    "sg:phone":"+1   ",
    "sg:postcode":"08215",
    "sg:province":"NJ",
    "sg:tags":[
        "eating"
    ],
    "wof:name":"Last Resort Grill & Bar",
    "wof:placetype":"venue"
},
  "geometry": {"coordinates":[-74.64933600000001,39.532369],"type":"Point"}
}