{
  "type": "Feature",
  "properties": {
    "addr:full":"606 Delsea Dr Sewell NJ 08080",
    "addr:housenumber":"606",
    "addr:postcode":"08080",
    "addr:street":"Delsea Dr",
    "iso:country":"US",
    "sg:address":"606 Delsea Dr",
    "sg:city":"Sewell",
    "sg:classifiers":[
        {
            "category":"Social Services",
            "subcategory":"Child Care",
            "type":"Services"
        }
    ],
    "sg:phone":"+1 856 582 8282",
    "sg:postcode":"08080",
    "sg:province":"NJ",
    "wof:name":"Southern Regional Child Care",
    "wof:placetype":"venue"
},
  "geometry": {"coordinates":[-75.11337899999999,39.747019],"type":"Point"}
}