{
  "type": "Feature",
  "properties": {
    "addr:full":"19 Monmouth St Red Bank NJ 07701",
    "addr:housenumber":"19",
    "addr:postcode":"07701",
    "addr:street":"Monmouth St",
    "iso:country":"US",
    "sg:address":"19 Monmouth St",
    "sg:city":"Red Bank",
    "sg:classifiers":[
        {
            "category":"Home & Garden",
            "subcategory":"Furniture",
            "type":"Retail Goods"
        }
    ],
    "sg:phone":"+1   ",
    "sg:postcode":"07701",
    "sg:province":"NJ",
    "wof:name":"Yasmina LLC",
    "wof:placetype":"venue"
},
  "geometry": {"coordinates":[-74.066506,40.349536],"type":"Point"}
}