{
  "type": "Feature",
  "properties": {
    "iso:country":"US",
    "sg:address":"54 Farmbrook Rd",
    "sg:city":"Sparta",
    "sg:classifiers":[
        {
            "category":"Building & Trades",
            "subcategory":"Construction",
            "type":"Services"
        }
    ],
    "sg:phone":"+1 973 729 2230",
    "sg:postcode":"07871",
    "sg:province":"NJ",
    "sg:tags":[
        "renovation",
        "family"
    ],
    "wof:name":"Lse Inc",
    "wof:placetype":"venue"
},
  "geometry": {"coordinates":[-74.680013,41.04619],"type":"Point"}
}