{
  "type": "Feature",
  "properties": {
    "iso:country":"US",
    "sg:address":"281 Reynolds Ter",
    "sg:city":"Orange",
    "sg:classifiers":[
        {
            "category":"Freight",
            "type":"Transportation"
        }
    ],
    "sg:phone":"+1 973 673 4966",
    "sg:postcode":"07050",
    "sg:province":"NJ",
    "sg:tags":[
        "operator",
        "trucking"
    ],
    "wof:name":"Ms Alexander Trucking",
    "wof:placetype":"venue"
},
  "geometry": {"coordinates":[-74.235765,40.764355],"type":"Point"}
}