{
  "type": "Feature",
  "properties": {
    "iso:country":"US",
    "sg:address":"23 Charleston Rd",
    "sg:city":"Willingboro",
    "sg:classifiers":[
        {
            "category":"Restaurant",
            "type":"Food & Drink"
        }
    ],
    "sg:phone":"+1 609 835 9111",
    "sg:postcode":"08046",
    "sg:province":"NJ",
    "sg:tags":[
        "pizza"
    ],
    "wof:name":"Vincenzo's Pizza and Grill",
    "wof:placetype":"venue"
},
  "geometry": {"coordinates":[-74.9011,40.045101],"type":"Point"}
}