{
  "type": "Feature",
  "properties": {
    "addr:full":"426 US Hwy 22 E Whitehouse Sta NJ 08889",
    "addr:housenumber":"426",
    "addr:postcode":"08889",
    "addr:street":"Us Hwy 22 E",
    "iso:country":"US",
    "sg:address":"426 US Hwy 22 E",
    "sg:city":"Whitehouse Sta",
    "sg:classifiers":[
        {
            "category":"Retail",
            "subcategory":"Auto Repair",
            "type":"Services"
        }
    ],
    "sg:phone":"+1 908 534 4147",
    "sg:postcode":"08889",
    "sg:province":"NJ",
    "sg:tags":[
        "transmission"
    ],
    "wof:name":"Cokesbury Automotive & Trans",
    "wof:placetype":"venue"
},
  "geometry": {"coordinates":[-74.75909299999999,40.619316],"type":"Point"}
}