{
  "type": "Feature",
  "properties": {
    "iso:country":"US",
    "sg:address":"311 Reynolds Ter",
    "sg:city":"Orange",
    "sg:classifiers":[
        {
            "category":"Real Estate",
            "subcategory":"Real Estate Operator",
            "type":"Services"
        }
    ],
    "sg:phone":"+1   ",
    "sg:postcode":"07050",
    "sg:province":"NJ",
    "sg:tags":[
        "building",
        "apartment"
    ],
    "wof:name":"Rey-Car Co",
    "wof:placetype":"venue"
},
  "geometry": {"coordinates":[-74.23499200000001,40.763965],"type":"Point"}
}