{
  "type": "Feature",
  "properties": {
    "addr:full":"100 S Michigan Ave Kenilworth NJ 07033",
    "addr:housenumber":"100",
    "addr:postcode":"07033",
    "addr:street":"S Michigan Ave",
    "iso:country":"US",
    "sg:address":"100 S Michigan Ave",
    "sg:city":"Kenilworth",
    "sg:classifiers":[
        {
            "category":"Professional",
            "type":"Services"
        }
    ],
    "sg:phone":"+1 908 245 8719",
    "sg:postcode":"07033",
    "sg:province":"NJ",
    "sg:tags":[
        "caterer"
    ],
    "wof:name":"Michigan Deli",
    "wof:placetype":"venue"
},
  "geometry": {"coordinates":[-74.285004,40.6744],"type":"Point"}
}