{
  "type": "Feature",
  "properties": {
    "iso:country":"US",
    "sg:address":"396 Broad St",
    "sg:city":"Bloomfield",
    "sg:classifiers":[
        {
            "category":"Restaurant",
            "type":"Food & Drink"
        }
    ],
    "sg:phone":"+1   ",
    "sg:postcode":"07003",
    "sg:province":"NJ",
    "sg:tags":[
        "eating"
    ],
    "wof:name":"Chengs Garden",
    "wof:placetype":"venue"
},
  "geometry": {"coordinates":[-74.19280999999999,40.806558],"type":"Point"}
}