{
  "type": "Feature",
  "properties": {
    "iso:country":"US",
    "sg:address":"25 Grove Ave Ste 8",
    "sg:city":"Verona",
    "sg:classifiers":[
        {
            "category":"Food & Beverages",
            "subcategory":"Groceries & Convenience Stores",
            "type":"Retail Goods"
        }
    ],
    "sg:phone":"+1 973 239 1871",
    "sg:postcode":"07044",
    "sg:province":"NJ",
    "wof:name":"Rosina Foods Inc",
    "wof:placetype":"venue"
},
  "geometry": {"coordinates":[-74.24771,40.833979],"type":"Point"}
}