{
  "type": "Feature",
  "properties": {
    "iso:country":"US",
    "sg:address":"510 Oaklawn Ave",
    "sg:city":"Oaklyn",
    "sg:classifiers":[
        {
            "category":"Building & Trades",
            "subcategory":"Cleaning & Sanitation",
            "type":"Services"
        }
    ],
    "sg:phone":"+1   ",
    "sg:postcode":"08107",
    "sg:province":"NJ",
    "sg:tags":[
        "maintenance"
    ],
    "wof:name":"Giordanos Home Cleaning",
    "wof:placetype":"venue"
},
  "geometry": {"coordinates":[-75.071653,39.906316],"type":"Point"}
}