{
  "type": "Feature",
  "properties": {
    "iso:country":"US",
    "sg:address":"21 Amagansett Dr",
    "sg:city":"Morganville",
    "sg:classifiers":[
        {
            "category":"Banks & Credit Unions",
            "subcategory":"Financial Services",
            "type":"Services"
        }
    ],
    "sg:phone":"+1   ",
    "sg:postcode":"07751",
    "sg:province":"NJ",
    "sg:tags":[
        "company",
        "holding"
    ],
    "wof:name":"Sherman Holdings LLC",
    "wof:placetype":"venue"
},
  "geometry": {"coordinates":[-74.263513,40.341392],"type":"Point"}
}