{
  "type": "Feature",
  "properties": {
    "addr:full":"176 Belmont Ave Belleville NJ 07109",
    "addr:housenumber":"176",
    "addr:postcode":"07109",
    "addr:street":"Belmont Ave",
    "iso:country":"US",
    "sg:address":"176 Belmont Ave",
    "sg:city":"Belleville",
    "sg:classifiers":[
        {
            "category":"Retail",
            "subcategory":"Repair Shop",
            "type":"Services"
        }
    ],
    "sg:phone":"+1 973 751 4611",
    "sg:postcode":"07109",
    "sg:province":"NJ",
    "sg:tags":[
        "reupholstery",
        "furniture"
    ],
    "wof:name":"Banner Upholstery & Dinette Sales",
    "wof:placetype":"venue"
},
  "geometry": {"coordinates":[-74.18150300000001,40.780102],"type":"Point"}
}