{
  "type": "Feature",
  "properties": {
    "iso:country":"US",
    "sg:address":"6207 New Jersey Ave",
    "sg:city":"Wildwood",
    "sg:classifiers":[
        {
            "category":"Shopping",
            "subcategory":"Bicycles & Sporting Goods",
            "type":"Retail Goods"
        }
    ],
    "sg:phone":"+1 609 729 5669",
    "sg:postcode":"08260",
    "sg:province":"NJ",
    "sg:tags":[
        "bike"
    ],
    "sg:website":"www.algiesplace.com",
    "wof:name":"Algie's Place",
    "wof:placetype":"venue"
},
  "geometry": {"coordinates":[-74.833603,38.977299],"type":"Point"}
}