{
  "type": "Feature",
  "properties": {
    "iso:country":"US",
    "sg:address":"412 Springfield Ave",
    "sg:city":"Newark",
    "sg:classifiers":[
        {
            "category":"Shopping",
            "subcategory":"Clothing, Apparel, & Fashions",
            "type":"Retail Goods"
        }
    ],
    "sg:phone":"+1   ",
    "sg:postcode":"07103",
    "sg:province":"NJ",
    "sg:tags":[
        "sportswear"
    ],
    "wof:name":"Buy Wise Choice",
    "wof:placetype":"venue"
},
  "geometry": {"coordinates":[-74.198098,40.732851],"type":"Point"}
}