{
  "type": "Feature",
  "properties": {
    "addr:full":"789 US Hwy 22 Plainfield NJ 07060",
    "addr:housenumber":"789",
    "addr:postcode":"07060",
    "addr:street":"Us Hwy 22",
    "iso:country":"US",
    "sg:address":"789 US Hwy 22",
    "sg:city":"Plainfield",
    "sg:classifiers":[
        {
            "category":"Manufacturing",
            "subcategory":"Electronics",
            "type":"Manufacturing & Wholesale Goods"
        }
    ],
    "sg:phone":"+1 908 754 2877",
    "sg:postcode":"07060",
    "sg:province":"NJ",
    "sg:tags":[
        "equipment",
        "mfg",
        "home"
    ],
    "wof:name":"Kenvon LLC",
    "wof:placetype":"venue"
},
  "geometry": {"coordinates":[-74.44072,40.625468],"type":"Point"}
}