{
  "type": "Feature",
  "properties": {
    "iso:country":"US",
    "sg:address":"1 University Plz",
    "sg:city":"Hackensack",
    "sg:classifiers":[
        {
            "category":"Professional",
            "subcategory":"Detective & Security Services",
            "type":"Services"
        }
    ],
    "sg:phone":"+1 201 500 8961",
    "sg:postcode":"07601",
    "sg:province":"NJ",
    "sg:tags":[
        "system"
    ],
    "wof:name":"Atech Home Alarm Bergen NJ",
    "wof:placetype":"venue"
},
  "geometry": {"coordinates":[-74.03296,40.89843],"type":"Point"}
}