{
  "type": "Feature",
  "properties": {
    "addr:full":"9 Gull Rd Middletown NJ 07748",
    "addr:housenumber":"9",
    "addr:postcode":"07748",
    "addr:street":"Gull Rd",
    "iso:country":"US",
    "sg:address":"9 Gull Rd",
    "sg:city":"Middletown",
    "sg:classifiers":[
        {
            "category":"Professional",
            "subcategory":"Employment Agencies",
            "type":"Services"
        }
    ],
    "sg:phone":"+1   ",
    "sg:postcode":"07748",
    "sg:province":"NJ",
    "sg:tags":[
        "help",
        "supply"
    ],
    "wof:name":"Edward Britton",
    "wof:placetype":"venue"
},
  "geometry": {"coordinates":[-74.123541,40.374929],"type":"Point"}
}