{
  "type": "Feature",
  "properties": {
    "addr:full":"70 State Rte 36 Eatontown NJ 07724",
    "addr:housenumber":"70",
    "addr:postcode":"07724",
    "addr:street":"State Rte 36",
    "iso:country":"US",
    "sg:address":"70 State Rte 36",
    "sg:city":"Eatontown",
    "sg:classifiers":[
        {
            "category":"Shopping",
            "subcategory":"Clothing, Apparel, & Fashions",
            "type":"Retail Goods"
        }
    ],
    "sg:phone":"+1 732 935 9366",
    "sg:postcode":"07724",
    "sg:province":"NJ",
    "sg:tags":[
        "infant",
        "wear",
        "furniture"
    ],
    "wof:name":"Babies R Us",
    "wof:placetype":"venue"
},
  "geometry": {"coordinates":[-74.043459,40.291211],"type":"Point"}
}