{
  "type": "Feature",
  "properties": {
    "iso:country":"US",
    "sg:address":"89 Hampton House Rd",
    "sg:city":"Newton",
    "sg:classifiers":[
        {
            "category":"Autos & Motor Vehicles",
            "subcategory":"Auto Supplies",
            "type":"Retail Goods"
        }
    ],
    "sg:phone":"+1   ",
    "sg:postcode":"07860",
    "sg:province":"NJ",
    "sg:tags":[
        "automotive",
        "repair"
    ],
    "wof:name":"North Jersey Truck & Track LLC",
    "wof:placetype":"venue"
},
  "geometry": {"coordinates":[-74.733896,41.083906],"type":"Point"}
}