{
  "type": "Feature",
  "properties": {
    "addr:full":"81 Morton Dr Ramsey NJ 07446",
    "addr:housenumber":"81",
    "addr:postcode":"07446",
    "addr:street":"Morton Dr",
    "iso:country":"US",
    "sg:address":"81 Morton Dr",
    "sg:city":"Ramsey",
    "sg:classifiers":[
        {
            "category":"Professional",
            "type":"Services"
        }
    ],
    "sg:phone":"+1   ",
    "sg:postcode":"07446",
    "sg:province":"NJ",
    "wof:name":"Businessview Inc",
    "wof:placetype":"venue"
},
  "geometry": {"coordinates":[-74.13658700000001,41.050618],"type":"Point"}
}