{
  "type": "Feature",
  "properties": {
    "addr:full":"34 Hanover Rd East Hanover NJ 07936",
    "addr:housenumber":"34",
    "addr:postcode":"07936",
    "addr:street":"Hanover Rd",
    "iso:country":"US",
    "sg:address":"34 Hanover Rd",
    "sg:city":"East Hanover",
    "sg:classifiers":[
        {
            "category":"Personal",
            "subcategory":"Beauty Salon",
            "type":"Services"
        }
    ],
    "sg:phone":"+1 973 887 8794",
    "sg:postcode":"07936",
    "sg:province":"NJ",
    "sg:tags":[
        "shop"
    ],
    "wof:name":"Snips",
    "wof:placetype":"venue"
},
  "geometry": {"coordinates":[-74.370853,40.80073],"type":"Point"}
}