{
  "type": "Feature",
  "properties": {
    "addr:full":"225 Riveredge Dr Chatham NJ 07928",
    "addr:housenumber":"225",
    "addr:postcode":"07928",
    "addr:street":"Riveredge Dr",
    "iso:country":"US",
    "sg:address":"225 Riveredge Dr",
    "sg:city":"Chatham",
    "sg:classifiers":[
        {
            "category":"Government",
            "subcategory":"Office",
            "type":"Public Place"
        }
    ],
    "sg:phone":"+1   ",
    "sg:postcode":"07928",
    "sg:province":"NJ",
    "sg:tags":[
        "housing",
        "program"
    ],
    "wof:name":"Gfm Health Services Dr S Hous",
    "wof:placetype":"venue"
},
  "geometry": {"coordinates":[-74.39802299999999,40.718903],"type":"Point"}
}