{
  "type": "Feature",
  "properties": {
    "addr:full":"628 Boulevard E Weehawken NJ 07086",
    "addr:housenumber":"628;e",
    "addr:postcode":"07086",
    "addr:street":"Boulevard",
    "iso:country":"US",
    "sg:address":"628 Boulevard E",
    "sg:city":"Weehawken",
    "sg:classifiers":[
        {
            "category":"Travel",
            "subcategory":"Travel Agent",
            "type":"Entertainment"
        }
    ],
    "sg:phone":"+1 201 330 8797",
    "sg:postcode":"07086",
    "sg:province":"NJ",
    "sg:tags":[
        "turkey",
        "istanbul",
        "receptive",
        "located",
        "tour",
        "operator"
    ],
    "wof:name":"Intra Tourism Inc",
    "wof:placetype":"venue"
},
  "geometry": {"coordinates":[-74.02114,40.768264],"type":"Point"}
}