{
  "type": "Feature",
  "properties": {
    "addr:full":"491 Valley Rd Gillette NJ 07933",
    "addr:housenumber":"491",
    "addr:postcode":"07933",
    "addr:street":"Valley Rd",
    "iso:country":"US",
    "sg:address":"491 Valley Rd",
    "sg:city":"Gillette",
    "sg:classifiers":[
        {
            "category":"Professional",
            "subcategory":"Computer Services",
            "type":"Services"
        }
    ],
    "sg:phone":"+1 908 604 0273",
    "sg:postcode":"07933",
    "sg:province":"NJ",
    "sg:tags":[
        "related"
    ],
    "wof:name":"Open 4 Success",
    "wof:placetype":"venue"
},
  "geometry": {"coordinates":[-74.463537,40.675297],"type":"Point"}
}