{
  "type": "Feature",
  "properties": {
    "iso:country":"US",
    "sg:address":"201 Reillywood Ave",
    "sg:city":"Haddonfield",
    "sg:classifiers":[
        {
            "category":"Manufacturing",
            "subcategory":"Tools & Machinery",
            "type":"Manufacturing & Wholesale Goods"
        }
    ],
    "sg:phone":"+1 856 429 9399",
    "sg:postcode":"08033",
    "sg:province":"NJ",
    "sg:tags":[
        "control",
        "mfg",
        "suppl",
        "electrical",
        "mechanical",
        "panel"
    ],
    "wof:name":"Precision Panel Fabricators",
    "wof:placetype":"venue"
},
  "geometry": {"coordinates":[-75.02882099999999,39.890194],"type":"Point"}
}