{
  "type": "Feature",
  "properties": {
    "iso:country":"US",
    "sg:address":"327 Beebe Run Rd",
    "sg:city":"Bridgeton",
    "sg:classifiers":[
        {
            "category":"Home & Garden",
            "subcategory":"Garden Supply",
            "type":"Retail Goods"
        }
    ],
    "sg:phone":"+1 856 451 2162",
    "sg:postcode":"08302",
    "sg:province":"NJ",
    "sg:tags":[
        "nurseryman"
    ],
    "wof:name":"Woodside Nursery",
    "wof:placetype":"venue"
},
  "geometry": {"coordinates":[-75.26234100000001,39.472577],"type":"Point"}
}