{
  "type": "Feature",
  "properties": {
    "addr:full":"246 Fernwood Dr Bayville NJ 08721",
    "addr:housenumber":"246",
    "addr:postcode":"08721",
    "addr:street":"Fernwood Dr",
    "iso:country":"US",
    "sg:address":"246 Fernwood Dr",
    "sg:city":"Bayville",
    "sg:classifiers":[
        {
            "category":"Retail",
            "subcategory":"Auto Repair",
            "type":"Services"
        }
    ],
    "sg:phone":"+1 732 269 4475",
    "sg:postcode":"08721",
    "sg:province":"NJ",
    "sg:tags":[
        "automotive"
    ],
    "wof:name":"Wonder Muffler & Brake",
    "wof:placetype":"venue"
},
  "geometry": {"coordinates":[-74.143596,39.885096],"type":"Point"}
}