{
  "type": "Feature",
  "properties": {
    "iso:country":"US",
    "sg:address":"1512 State Rte 138",
    "sg:city":"Belmar",
    "sg:classifiers":[
        {
            "category":"Insurance",
            "subcategory":"Insurance Agent",
            "type":"Services"
        }
    ],
    "sg:phone":"+1   ",
    "sg:postcode":"07719",
    "sg:province":"NJ",
    "wof:name":"Crm",
    "wof:placetype":"venue"
},
  "geometry": {"coordinates":[-74.05041199999999,40.173234],"type":"Point"}
}