{
  "type": "Feature",
  "properties": {
    "addr:full":"7 W Front St Keyport NJ 07735",
    "addr:housenumber":"7",
    "addr:postcode":"07735",
    "addr:street":"W Front St",
    "iso:country":"US",
    "sg:address":"7 W Front St",
    "sg:city":"Keyport",
    "sg:classifiers":[
        {
            "category":"Retail",
            "subcategory":"Laundry & Dry Cleaning",
            "type":"Services"
        }
    ],
    "sg:phone":"+1 732 888 8333",
    "sg:postcode":"07735",
    "sg:province":"NJ",
    "sg:tags":[
        "cleaners"
    ],
    "wof:name":"Middle Road Cleaners III",
    "wof:placetype":"venue"
},
  "geometry": {"coordinates":[-74.20327899999999,40.437276],"type":"Point"}
}