{
  "type": "Feature",
  "properties": {
    "iso:country":"US",
    "sg:address":"401 W Route 38 # 812A",
    "sg:city":"Moorestown",
    "sg:classifiers":[
        {
            "category":"Building & Trades",
            "subcategory":"Construction",
            "type":"Services"
        }
    ],
    "sg:phone":"+1 856 235 0198",
    "sg:postcode":"08057",
    "sg:province":"NJ",
    "sg:tags":[
        "tile-contractors"
    ],
    "wof:name":"Tile Shop",
    "wof:placetype":"venue"
},
  "geometry": {"coordinates":[-74.96328699999999,39.9464],"type":"Point"}
}