{
  "type": "Feature",
  "properties": {
    "iso:country":"US",
    "sg:address":"314 Carr Ave",
    "sg:city":"Keansburg",
    "sg:classifiers":[
        {
            "category":"Professional",
            "subcategory":"Lawyer & Legal Services",
            "type":"Services"
        }
    ],
    "sg:phone":"+1 732 566 3401",
    "sg:postcode":"07734",
    "sg:province":"NJ",
    "sg:tags":[
        "attorney"
    ],
    "wof:name":"Paul Granick",
    "wof:placetype":"venue"
},
  "geometry": {"coordinates":[-74.132459,40.445222],"type":"Point"}
}