{
  "type": "Feature",
  "properties": {
    "iso:country":"US",
    "sg:address":"109 S Main St",
    "sg:city":"Cranbury",
    "sg:classifiers":[
        {
            "category":"Health Services",
            "subcategory":"Clinic",
            "type":"Services"
        }
    ],
    "sg:phone":"+1 609 490 0310",
    "sg:postcode":"08512",
    "sg:province":"NJ",
    "sg:tags":[
        "organization",
        "medical",
        "surgical"
    ],
    "sg:website":"www.tarcweb.org",
    "wof:name":"Trans-Atlantic Renal Council",
    "wof:placetype":"venue"
},
  "geometry": {"coordinates":[-74.52016999999999,40.298293],"type":"Point"}
}