{
  "type": "Feature",
  "properties": {
    "addr:full":"903 W Chicago Blvd Sea Girt NJ 08750",
    "addr:housenumber":"903",
    "addr:postcode":"08750",
    "addr:street":"W Chicago Blvd",
    "iso:country":"US",
    "sg:address":"903 W Chicago Blvd",
    "sg:city":"Sea Girt",
    "sg:classifiers":[
        {
            "category":"Real Estate",
            "subcategory":"Architect",
            "type":"Services"
        }
    ],
    "sg:phone":"+1 732 449 0074",
    "sg:postcode":"08750",
    "sg:province":"NJ",
    "wof:name":"R E Wilson Architects",
    "wof:placetype":"venue"
},
  "geometry": {"coordinates":[-74.044636,40.137947],"type":"Point"}
}