{
  "type": "Feature",
  "properties": {
    "iso:country":"US",
    "sg:address":"128 N Portland Ave",
    "sg:city":"Ventnor City",
    "sg:classifiers":[
        {
            "category":"Building & Trades",
            "subcategory":"Construction",
            "type":"Services"
        }
    ],
    "sg:phone":"+1 609 487 1587",
    "sg:postcode":"08406",
    "sg:province":"NJ",
    "sg:tags":[
        "contractor"
    ],
    "wof:name":"Richmond Brothers Builders",
    "wof:placetype":"venue"
},
  "geometry": {"coordinates":[-74.484132,39.340325],"type":"Point"}
}