{
  "type": "Feature",
  "properties": {
    "addr:full":"503 Kennedy Blvd Bayonne NJ 07002",
    "addr:housenumber":"503",
    "addr:postcode":"07002",
    "addr:street":"Kennedy Blvd",
    "iso:country":"US",
    "sg:address":"503 Kennedy Blvd",
    "sg:city":"Bayonne",
    "sg:classifiers":[
        {
            "category":"Social Services",
            "type":"Services"
        }
    ],
    "sg:phone":"+1   ",
    "sg:postcode":"07002",
    "sg:province":"NJ",
    "sg:tags":[
        "program"
    ],
    "wof:name":"Sow & Grow Childrens Charity",
    "wof:placetype":"venue"
},
  "geometry": {"coordinates":[-74.125367,40.663269],"type":"Point"}
}