{
  "type": "Feature",
  "properties": {
    "addr:full":"210 Orchard St East Rutherford NJ 07073",
    "addr:housenumber":"210",
    "addr:postcode":"07073",
    "addr:street":"Orchard St",
    "iso:country":"US",
    "sg:address":"210 Orchard St",
    "sg:city":"East Rutherford",
    "sg:classifiers":[
        {
            "category":"Real Estate",
            "subcategory":"Developer",
            "type":"Services"
        }
    ],
    "sg:phone":"+1 201 672 0080",
    "sg:postcode":"07073",
    "sg:province":"NJ",
    "wof:name":"Millennium Homes",
    "wof:placetype":"venue"
},
  "geometry": {"coordinates":[-74.099952,40.830152],"type":"Point"}
}