{
  "type": "Feature",
  "properties": {
    "addr:full":"612 Glassboro Rd Woodbury Heights NJ 08097",
    "addr:housenumber":"612",
    "addr:postcode":"08097",
    "addr:street":"Glassboro Rd",
    "iso:country":"US",
    "sg:address":"612 Glassboro Rd",
    "sg:city":"Woodbury Heights",
    "sg:classifiers":[
        {
            "category":"Health Services",
            "subcategory":"Doctor",
            "type":"Services"
        }
    ],
    "sg:phone":"+1   ",
    "sg:postcode":"08097",
    "sg:province":"NJ",
    "sg:tags":[
        "medical"
    ],
    "wof:name":"Robert R Wolf MD",
    "wof:placetype":"venue"
},
  "geometry": {"coordinates":[-75.149196,39.818144],"type":"Point"}
}