{
  "type": "Feature",
  "properties": {
    "addr:full":"638 US Hwy 206 Hillsborough NJ 08844",
    "addr:housenumber":"638",
    "addr:postcode":"08844",
    "addr:street":"Us Hwy 206",
    "iso:country":"US",
    "sg:address":"638 US Hwy 206",
    "sg:city":"Hillsborough",
    "sg:classifiers":[
        {
            "category":"Real Estate",
            "subcategory":"Real Estate Agent",
            "type":"Services"
        }
    ],
    "sg:phone":"+1 908 874 7797",
    "sg:postcode":"08844",
    "sg:province":"NJ",
    "sg:website":"www.erastatewide.com",
    "wof:name":"Statewide Realty",
    "wof:placetype":"venue"
},
  "geometry": {"coordinates":[-74.646126,40.499777],"type":"Point"}
}