{
  "type": "Feature",
  "properties": {
    "addr:full":"5 Pemberton Ln Hightstown NJ 08520",
    "addr:housenumber":"5",
    "addr:postcode":"08520",
    "addr:street":"Pemberton Ln",
    "iso:country":"US",
    "sg:address":"5 Pemberton Ln",
    "sg:city":"Hightstown",
    "sg:classifiers":[
        {
            "category":"Banks & Credit Unions",
            "subcategory":"Financial Services",
            "type":"Services"
        }
    ],
    "sg:phone":"+1   ",
    "sg:postcode":"08520",
    "sg:province":"NJ",
    "sg:tags":[
        "company",
        "holding"
    ],
    "wof:name":"Sren & Ed Holdings LLC",
    "wof:placetype":"venue"
},
  "geometry": {"coordinates":[-74.533359,40.2419],"type":"Point"}
}