{
  "type": "Feature",
  "properties": {
    "iso:country":"US",
    "sg:address":"163 Pleasant Valley Rd",
    "sg:city":"Titusville",
    "sg:classifiers":[
        {
            "category":"Real Estate",
            "subcategory":"Real Estate Agent",
            "type":"Services"
        }
    ],
    "sg:phone":"+1 609 737 8536",
    "sg:postcode":"08560",
    "sg:province":"NJ",
    "sg:tags":[
        "appraiser"
    ],
    "wof:name":"Evalutions By Etchells",
    "wof:placetype":"venue"
},
  "geometry": {"coordinates":[-74.85152600000001,40.334989],"type":"Point"}
}