{
  "type": "Feature",
  "properties": {
    "addr:full":"147 Prospect St Passaic NJ 07055",
    "addr:housenumber":"147",
    "addr:postcode":"07055",
    "addr:street":"Prospect St",
    "iso:country":"US",
    "sg:address":"147 Prospect St",
    "sg:city":"Passaic",
    "sg:classifiers":[
        {
            "category":"Real Estate",
            "subcategory":"Real Estate Agent",
            "type":"Services"
        }
    ],
    "sg:phone":"+1 973 777 5440",
    "sg:postcode":"07055",
    "sg:province":"NJ",
    "sg:website":"www.realtyone.com",
    "wof:name":"Realty One",
    "wof:placetype":"venue"
},
  "geometry": {"coordinates":[-74.12676999999999,40.860088],"type":"Point"}
}