{
  "type": "Feature",
  "properties": {
    "addr:full":"1 Plaza Pl Monmouth Junction NJ 08817",
    "addr:postcode":"08817",
    "addr:street":"Plaza Pl",
    "iso:country":"US",
    "sg:address":"1 Plaza Pl",
    "sg:city":"Monmouth Junction",
    "sg:classifiers":[
        {
            "category":"Government",
            "subcategory":"Police Station",
            "type":"Public Place"
        }
    ],
    "sg:phone":"+1   ",
    "sg:postcode":"08817",
    "sg:province":"NJ",
    "sg:tags":[
        "protection"
    ],
    "wof:name":"South Brunswick Police Dept",
    "wof:placetype":"venue"
},
  "geometry": {"coordinates":[-74.398104,40.502418],"type":"Point"}
}