{
  "type": "Feature",
  "properties": {
    "addr:full":"573 E 19th St Paterson NJ 07514",
    "addr:housenumber":"573",
    "addr:postcode":"07514",
    "addr:street":"E 19Th St",
    "iso:country":"US",
    "sg:address":"573 E 19th St",
    "sg:city":"Paterson",
    "sg:classifiers":[
        {
            "category":"Manufacturing",
            "subcategory":"Metals",
            "type":"Manufacturing & Wholesale Goods"
        },
        {
            "category":"Manufacturing",
            "subcategory":"Tools & Machinery",
            "type":"Manufacturing & Wholesale Goods"
        }
    ],
    "sg:phone":"+1 973 278 1058",
    "sg:postcode":"07514",
    "sg:province":"NJ",
    "sg:tags":[
        "machine",
        "screw",
        "product",
        "industrial",
        "mfg"
    ],
    "sg:website":"www.galiciametal.com",
    "wof:name":"Galicia Metal Inc",
    "wof:placetype":"venue"
},
  "geometry": {"coordinates":[-74.15378200000001,40.921646],"type":"Point"}
}