{
  "type": "Feature",
  "properties": {
    "addr:full":"39 Stenton Ct Trenton NJ 08610",
    "addr:housenumber":"39",
    "addr:postcode":"08610",
    "addr:street":"Stenton Ct",
    "iso:country":"US",
    "sg:address":"39 Stenton Ct",
    "sg:city":"Trenton",
    "sg:classifiers":[
        {
            "category":"Communications",
            "type":"Services"
        }
    ],
    "sg:phone":"+1 609 392 8710",
    "sg:postcode":"08610",
    "sg:province":"NJ",
    "sg:tags":[
        "communication"
    ],
    "wof:name":"Viking Communications",
    "wof:placetype":"venue"
},
  "geometry": {"coordinates":[-74.745705,40.197112],"type":"Point"}
}