{
  "type": "Feature",
  "properties": {
    "addr:full":"957 State Rte 33 Trenton NJ 08690",
    "addr:housenumber":"957",
    "addr:postcode":"08690",
    "addr:street":"State Rte 33",
    "iso:country":"US",
    "sg:address":"957 State Rte 33",
    "sg:city":"Trenton",
    "sg:classifiers":[
        {
            "category":"Professional",
            "subcategory":"Management & Consulting",
            "type":"Services"
        }
    ],
    "sg:phone":"+1   ",
    "sg:postcode":"08690",
    "sg:province":"NJ",
    "wof:name":"Bottomline Reimbursement",
    "wof:placetype":"venue"
},
  "geometry": {"coordinates":[-74.66653599999999,40.228418],"type":"Point"}
}