{
  "type": "Feature",
  "properties": {
    "addr:full":"60 Altamawr Ave Trenton NJ 08648",
    "addr:housenumber":"60",
    "addr:postcode":"08648",
    "addr:street":"Altamawr Ave",
    "iso:country":"US",
    "sg:address":"60 Altamawr Ave",
    "sg:city":"Trenton",
    "sg:classifiers":[
        {
            "category":"Professional",
            "subcategory":"Business Services",
            "type":"Services"
        }
    ],
    "sg:phone":"+1   ",
    "sg:postcode":"08648",
    "sg:province":"NJ",
    "wof:name":"Aibm Group Corp",
    "wof:placetype":"venue"
},
  "geometry": {"coordinates":[-74.742968,40.264197],"type":"Point"}
}