{
  "type": "Feature",
  "properties": {
    "addr:full":"411 E 26th Ave Wildwood NJ 08260",
    "addr:housenumber":"411",
    "addr:postcode":"08260",
    "addr:street":"E 26Th Ave",
    "iso:country":"US",
    "sg:address":"411 E 26th Ave",
    "sg:city":"Wildwood",
    "sg:classifiers":[
        {
            "category":"Travel",
            "subcategory":"Hotels & Motels",
            "type":"Entertainment"
        },
        {
            "category":"Real Estate",
            "subcategory":"Real Estate Operator",
            "type":"Services"
        }
    ],
    "sg:phone":"+1 609 522 8409",
    "sg:postcode":"08260",
    "sg:province":"NJ",
    "sg:tags":[
        "apartment"
    ],
    "wof:name":"Avalon Motel & Apartments Inc",
    "wof:placetype":"venue"
},
  "geometry": {"coordinates":[-74.805199,38.990898],"type":"Point"}
}