{
  "type": "Feature",
  "properties": {
    "addr:full":"1 Short Hills Ave Short Hills NJ 07078",
    "addr:housenumber":"1",
    "addr:postcode":"07078",
    "addr:street":"Short Hills Ave",
    "iso:country":"US",
    "sg:address":"1 Short Hills Ave",
    "sg:city":"Short Hills",
    "sg:classifiers":[
        {
            "category":"Health Services",
            "subcategory":"Health Practitioner",
            "type":"Services"
        }
    ],
    "sg:phone":"+1   ",
    "sg:postcode":"07078",
    "sg:province":"NJ",
    "wof:name":"Chapman Cheryl Rn Ncmt",
    "wof:placetype":"venue"
},
  "geometry": {"coordinates":[-74.318607,40.719223],"type":"Point"}
}