{
  "type": "Feature",
  "properties": {
    "addr:full":"406 54th St West New York NJ 07093",
    "addr:housenumber":"406",
    "addr:postcode":"nj 07093",
    "addr:street":"54Th St West",
    "iso:country":"US",
    "sg:address":"406 54th St",
    "sg:city":"West New York",
    "sg:classifiers":[
        {
            "category":"Wholesale",
            "subcategory":"Sporting Goods",
            "type":"Manufacturing & Wholesale Goods"
        }
    ],
    "sg:phone":"+1 201 330 0025",
    "sg:postcode":"07093",
    "sg:province":"NJ",
    "wof:name":"Bruant Mfg",
    "wof:placetype":"venue"
},
  "geometry": {"coordinates":[-74.019002,40.785103],"type":"Point"}
}