{
  "type": "Feature",
  "properties": {
    "iso:country":"US",
    "sg:address":"843 Hamilton St",
    "sg:city":"Somerset",
    "sg:classifiers":[
        {
            "category":"Professional",
            "subcategory":"Accounting & Tax Preparation",
            "type":"Services"
        }
    ],
    "sg:phone":"+1   ",
    "sg:postcode":"08873",
    "sg:province":"NJ",
    "sg:tags":[
        "auditing",
        "bookkeeping"
    ],
    "wof:name":"Raposo Assoc Inc PC",
    "wof:placetype":"venue"
},
  "geometry": {"coordinates":[-74.48077000000001,40.488529],"type":"Point"}
}