{
  "type": "Feature",
  "properties": {
    "addr:full":"1061 N Pearl St Bridgeton NJ 08302",
    "addr:housenumber":"1061",
    "addr:postcode":"08302",
    "addr:street":"N Pearl St",
    "iso:country":"US",
    "sg:address":"1061 N Pearl St",
    "sg:city":"Bridgeton",
    "sg:classifiers":[
        {
            "category":"Retail",
            "subcategory":"Auto Repair",
            "type":"Services"
        }
    ],
    "sg:phone":"+1 856 451 7611",
    "sg:postcode":"08302",
    "sg:province":"NJ",
    "sg:tags":[
        "repairing",
        "automotive",
        "under",
        "automobile",
        "provides",
        "car"
    ],
    "wof:name":"Monro Muffler Brake & Svc",
    "wof:placetype":"venue"
},
  "geometry": {"coordinates":[-75.213616,39.453658],"type":"Point"}
}