{
  "type": "Feature",
  "properties": {
    "iso:country":"US",
    "sg:address":"33 Washington St",
    "sg:city":"Newark",
    "sg:classifiers":[
        {
            "category":"Professional",
            "subcategory":"Lawyer & Legal Services",
            "type":"Services"
        }
    ],
    "sg:phone":"+1 973 792 1820",
    "sg:postcode":"07102",
    "sg:province":"NJ",
    "sg:tags":[
        "attorney"
    ],
    "wof:name":"Patricia Nichols",
    "wof:placetype":"venue"
},
  "geometry": {"coordinates":[-74.17120199999999,40.742968],"type":"Point"}
}