{
  "type": "Feature",
  "properties": {
    "addr:full":"158 Edison Rd Lake Hopatcong NJ 07849",
    "addr:housenumber":"158",
    "addr:postcode":"07849",
    "addr:street":"Edison Rd",
    "iso:country":"US",
    "sg:address":"158 Edison Rd",
    "sg:city":"Lake Hopatcong",
    "sg:classifiers":[
        {
            "category":"Wholesale",
            "subcategory":"Electrical",
            "type":"Manufacturing & Wholesale Goods"
        }
    ],
    "sg:phone":"+1 973 663 9522",
    "sg:postcode":"07849",
    "sg:province":"NJ",
    "sg:tags":[
        "electronic"
    ],
    "wof:name":"Tracer Electronics Inc",
    "wof:placetype":"venue"
},
  "geometry": {"coordinates":[-74.60051199999999,40.957949],"type":"Point"}
}