{
  "type": "Feature",
  "properties": {
    "addr:full":"283 Main St Chatham NJ 07928",
    "addr:housenumber":"283",
    "addr:postcode":"07928",
    "addr:street":"Main St",
    "iso:country":"US",
    "sg:address":"283 Main St",
    "sg:city":"Chatham",
    "sg:classifiers":[
        {
            "category":"Health Services",
            "subcategory":"Doctor",
            "type":"Services"
        }
    ],
    "sg:phone":"+1   ",
    "sg:postcode":"07928",
    "sg:province":"NJ",
    "sg:tags":[
        "medical"
    ],
    "wof:name":"Clarita L Garces MD PC",
    "wof:placetype":"venue"
},
  "geometry": {"coordinates":[-74.385398,40.741285],"type":"Point"}
}