{
  "type": "Feature",
  "properties": {
    "addr:full":"3 Firethorn Ln Sicklerville NJ 08081",
    "addr:housenumber":"3",
    "addr:postcode":"08081",
    "addr:street":"Firethorn Ln",
    "iso:country":"US",
    "sg:address":"3 Firethorn Ln",
    "sg:city":"Sicklerville",
    "sg:classifiers":[
        {
            "category":"Home & Garden",
            "subcategory":"Home Furnishings",
            "type":"Retail Goods"
        }
    ],
    "sg:phone":"+1   ",
    "sg:postcode":"08081",
    "sg:province":"NJ",
    "wof:name":"Paradise Pleasures Inc",
    "wof:placetype":"venue"
},
  "geometry": {"coordinates":[-75.01751400000001,39.736892],"type":"Point"}
}