{
  "type": "Feature",
  "properties": {
    "addr:full":"38 W Taunton Rd Berlin NJ 08009",
    "addr:housenumber":"38",
    "addr:postcode":"08009",
    "addr:street":"W Taunton Rd",
    "iso:country":"US",
    "sg:address":"38 W Taunton Rd",
    "sg:city":"Berlin",
    "sg:classifiers":[
        {
            "category":"Professional",
            "type":"Services"
        },
        {
            "category":"Food & Beverages",
            "subcategory":"Meat & Fish",
            "type":"Retail Goods"
        }
    ],
    "sg:phone":"+1 856 767 0110",
    "sg:postcode":"08009",
    "sg:province":"NJ",
    "sg:tags":[
        "shop",
        "caterer"
    ],
    "sg:website":"www.bringhurstmeats.com",
    "wof:name":"Bringhurst Meats",
    "wof:placetype":"venue"
},
  "geometry": {"coordinates":[-74.912201,39.778301],"type":"Point"}
}