{
  "type": "Feature",
  "properties": {
    "iso:country":"US",
    "sg:address":"152 Hickory Corner Rd",
    "sg:city":"Hightstown",
    "sg:classifiers":[
        {
            "category":"Real Estate",
            "subcategory":"Real Estate Operator",
            "type":"Services"
        }
    ],
    "sg:phone":"+1   ",
    "sg:postcode":"08520",
    "sg:province":"NJ",
    "sg:tags":[
        "building",
        "apartment"
    ],
    "wof:name":"Brookwood Garden Apts",
    "wof:placetype":"venue"
},
  "geometry": {"coordinates":[-74.556619,40.2632],"type":"Point"}
}