{
  "type": "Feature",
  "properties": {
    "addr:full":"26 Crescent Rd Livingston NJ 07039",
    "addr:housenumber":"26",
    "addr:postcode":"07039",
    "addr:street":"Crescent Rd",
    "iso:country":"US",
    "sg:address":"26 Crescent Rd",
    "sg:city":"Livingston",
    "sg:classifiers":[
        {
            "category":"Retail",
            "subcategory":"Repair Shop",
            "type":"Services"
        }
    ],
    "sg:phone":"+1   ",
    "sg:postcode":"07039",
    "sg:province":"NJ",
    "wof:name":"Enverge Architectural Systems",
    "wof:placetype":"venue"
},
  "geometry": {"coordinates":[-74.32999100000001,40.773871],"type":"Point"}
}