{
  "type": "Feature",
  "properties": {
    "iso:country":"US",
    "sg:address":"75 Mishemokwa Trl",
    "sg:city":"Medford",
    "sg:classifiers":[
        {
            "category":"Real Estate",
            "subcategory":"Real Estate Operator",
            "type":"Services"
        }
    ],
    "sg:phone":"+1   ",
    "sg:postcode":"08055",
    "sg:province":"NJ",
    "sg:tags":[
        "building",
        "nonresidential"
    ],
    "wof:name":"A & J Real Properties LLC",
    "wof:placetype":"venue"
},
  "geometry": {"coordinates":[-74.810692,39.85586],"type":"Point"}
}