{
  "type": "Feature",
  "properties": {
    "iso:country":"US",
    "sg:address":"3587 US Hwy 9",
    "sg:city":"Freehold",
    "sg:classifiers":[
        {
            "category":"Professional",
            "subcategory":"Advertising",
            "type":"Services"
        }
    ],
    "sg:phone":"+1 732 303 1331",
    "sg:postcode":"07728",
    "sg:province":"NJ",
    "sg:tags":[
        "mailing",
        "shipping"
    ],
    "wof:name":"Mail Boxes Etc",
    "wof:placetype":"venue"
},
  "geometry": {"coordinates":[-74.275096,40.239419],"type":"Point"}
}