{
  "type": "Feature",
  "properties": {
    "iso:country":"US",
    "sg:address":"30 Upper Warren Way",
    "sg:city":"Warren",
    "sg:classifiers":[
        {
            "category":"Professional",
            "subcategory":"Management & Consulting",
            "type":"Services"
        }
    ],
    "sg:phone":"+1 908 542 0390",
    "sg:postcode":"07059",
    "sg:province":"NJ",
    "wof:name":"Expert Ms Inc",
    "wof:placetype":"venue"
},
  "geometry": {"coordinates":[-74.46548199999999,40.657421],"type":"Point"}
}