{
  "type": "Feature",
  "properties": {
    "addr:full":"43 Delancey St Newark NJ 07105",
    "addr:housenumber":"43",
    "addr:postcode":"07105",
    "addr:street":"Delancey St",
    "iso:country":"US",
    "sg:address":"43 Delancey St",
    "sg:city":"Newark",
    "sg:classifiers":[
        {
            "category":"Building & Trades",
            "subcategory":"Locksmith",
            "type":"Services"
        }
    ],
    "sg:phone":"+1 973 854 5074",
    "sg:postcode":"07105",
    "sg:province":"NJ",
    "sg:tags":[
        "key"
    ],
    "wof:name":"A-1 24 Hour 7 Day Emerg A Locksmith",
    "wof:placetype":"venue"
},
  "geometry": {"coordinates":[-74.166197,40.721686],"type":"Point"}
}