{
  "type": "Feature",
  "properties": {
    "addr:full":"11 E Colmar Cir Margate City NJ 08402",
    "addr:housenumber":"11",
    "addr:postcode":"08402",
    "addr:street":"E Colmar Cir Margate",
    "iso:country":"US",
    "sg:address":"11 E Colmar Cir",
    "sg:city":"Margate City",
    "sg:classifiers":[
        {
            "category":"Professional",
            "subcategory":"Business Services",
            "type":"Services"
        }
    ],
    "sg:phone":"+1   ",
    "sg:postcode":"08402",
    "sg:province":"NJ",
    "wof:name":"Larry Nelson Sales",
    "wof:placetype":"venue"
},
  "geometry": {"coordinates":[-74.503681,39.334183],"type":"Point"}
}