{
  "type": "Feature",
  "properties": {
    "addr:full":"201 Newark Pompton Tpke Little Falls NJ 07424",
    "addr:housenumber":"201",
    "addr:postcode":"07424",
    "addr:street":"Newark Pompton Tpke",
    "iso:country":"US",
    "sg:address":"201 Newark Pompton Tpke",
    "sg:city":"Little Falls",
    "sg:classifiers":[
        {
            "category":"Retail",
            "subcategory":"Auto Repair",
            "type":"Services"
        }
    ],
    "sg:phone":"+1   ",
    "sg:postcode":"07424",
    "sg:province":"NJ",
    "sg:tags":[
        "general"
    ],
    "wof:name":"Safety Lights & Stripes",
    "wof:placetype":"venue"
},
  "geometry": {"coordinates":[-74.24327099999999,40.882098],"type":"Point"}
}