{
  "type": "Feature",
  "properties": {
    "iso:country":"US",
    "sg:address":"463 Cove Rd",
    "sg:city":"Pennsauken",
    "sg:classifiers":[
        {
            "category":"Professional",
            "subcategory":"Art Services",
            "type":"Services"
        }
    ],
    "sg:phone":"+1 856 663 0305",
    "sg:postcode":"08110",
    "sg:province":"NJ",
    "sg:tags":[
        "designer",
        "display",
        "producer"
    ],
    "wof:name":"Susan Hopkins Interior Design",
    "wof:placetype":"venue"
},
  "geometry": {"coordinates":[-75.066439,39.970032],"type":"Point"}
}