{
  "type": "Feature",
  "properties": {
    "addr:full":"47 Hunters Cir Lebanon NJ 08833",
    "addr:housenumber":"47",
    "addr:postcode":"08833",
    "addr:street":"Hunters Cir",
    "iso:country":"US",
    "sg:address":"47 Hunters Cir",
    "sg:city":"Lebanon",
    "sg:classifiers":[
        {
            "category":"Shopping",
            "subcategory":"Gifts & Souvenirs",
            "type":"Retail Goods"
        }
    ],
    "sg:phone":"+1 908 534 2146",
    "sg:postcode":"08833",
    "sg:province":"NJ",
    "sg:tags":[
        "collectible"
    ],
    "sg:website":"www.bearamore.com",
    "wof:name":"Bearamore",
    "wof:placetype":"venue"
},
  "geometry": {"coordinates":[-74.783789,40.661699],"type":"Point"}
}