{
  "type": "Feature",
  "properties": {
    "addr:full":"128 Spring Valley Rd Montvale NJ 07645",
    "addr:housenumber":"128",
    "addr:postcode":"07645",
    "addr:street":"Spring Valley Rd",
    "iso:country":"US",
    "sg:address":"128 Spring Valley Rd",
    "sg:city":"Montvale",
    "sg:classifiers":[
        {
            "category":"Building & Trades",
            "subcategory":"Landscaping Services",
            "type":"Services"
        }
    ],
    "sg:phone":"+1 201 391 1383",
    "sg:postcode":"07645",
    "sg:province":"NJ",
    "sg:tags":[
        "land",
        "maintenance",
        "garden",
        "landscape",
        "contractor"
    ],
    "wof:name":"De Rosa Landscaping Inc",
    "wof:placetype":"venue"
},
  "geometry": {"coordinates":[-74.052643,41.059591],"type":"Point"}
}