{
  "type": "Feature",
  "properties": {
    "iso:country":"US",
    "sg:address":"515 Valley Brook Ave",
    "sg:city":"Lyndhurst",
    "sg:classifiers":[
        {
            "category":"Shopping",
            "subcategory":"Stationery & Office Supplies",
            "type":"Retail Goods"
        },
        {
            "category":"Professional",
            "subcategory":"Advertising",
            "type":"Services"
        }
    ],
    "sg:phone":"+1 201 933 2782",
    "sg:postcode":"07071",
    "sg:province":"NJ",
    "sg:tags":[
        "mailing",
        "shipping"
    ],
    "wof:name":"Mail Direct Paper Co",
    "wof:placetype":"venue"
},
  "geometry": {"coordinates":[-74.12118,40.810249],"type":"Point"}
}