{
  "type": "Feature",
  "properties": {
    "iso:country":"US",
    "sg:address":"46 Longview Dr",
    "sg:city":"Emerson",
    "sg:classifiers":[
        {
            "category":"Wholesale",
            "subcategory":"Electrical",
            "type":"Manufacturing & Wholesale Goods"
        }
    ],
    "sg:phone":"+1 201 265 7684",
    "sg:postcode":"07630",
    "sg:province":"NJ",
    "sg:tags":[
        "light",
        "bulb"
    ],
    "wof:name":"United Enviromental Network",
    "wof:placetype":"venue"
},
  "geometry": {"coordinates":[-74.04044,40.965181],"type":"Point"}
}