{
  "type": "Feature",
  "properties": {
    "addr:full":"2339 State Rte 70 Cherry Hill NJ 08002",
    "addr:housenumber":"2339",
    "addr:postcode":"08002",
    "addr:street":"State Rte 70",
    "iso:country":"US",
    "sg:address":"2339 State Rte 70",
    "sg:city":"Cherry Hill",
    "sg:classifiers":[
        {
            "category":"Professional",
            "subcategory":"Computer Services",
            "type":"Services"
        }
    ],
    "sg:phone":"+1 856 486 5252",
    "sg:postcode":"08002",
    "sg:province":"NJ",
    "sg:tags":[
        "information",
        "technology"
    ],
    "wof:name":"Oao Corporation",
    "wof:placetype":"venue"
},
  "geometry": {"coordinates":[-75.04958499999999,39.925391],"type":"Point"}
}