{
  "type": "Feature",
  "properties": {
    "iso:country":"US",
    "sg:address":"63 Wolfe Rd",
    "sg:city":"Budd Lake",
    "sg:classifiers":[
        {
            "category":"Building & Trades",
            "subcategory":"Construction",
            "type":"Services"
        }
    ],
    "sg:phone":"+1 973 448 0744",
    "sg:postcode":"07828",
    "sg:province":"NJ",
    "sg:tags":[
        "layer",
        "carpet"
    ],
    "wof:name":"Bary Carpet Svc",
    "wof:placetype":"venue"
},
  "geometry": {"coordinates":[-74.754471,40.854998],"type":"Point"}
}