{
  "type": "Feature",
  "properties": {
    "addr:full":"20 S Park St Montclair NJ 07042",
    "addr:housenumber":"20",
    "addr:postcode":"07042",
    "addr:street":"S Park St",
    "iso:country":"US",
    "sg:address":"20 S Park St",
    "sg:city":"Montclair",
    "sg:classifiers":[
        {
            "category":"Home & Garden",
            "subcategory":"Furniture",
            "type":"Retail Goods"
        }
    ],
    "sg:phone":"+1   ",
    "sg:postcode":"07042",
    "sg:province":"NJ",
    "wof:name":"D Marie Home",
    "wof:placetype":"venue"
},
  "geometry": {"coordinates":[-74.21977,40.814743],"type":"Point"}
}