{
  "type": "Feature",
  "properties": {
    "iso:country":"US",
    "sg:address":"55 Chandler Ave",
    "sg:city":"Keyport",
    "sg:classifiers":[
        {
            "category":"Retail",
            "subcategory":"Repair Shop",
            "type":"Services"
        }
    ],
    "sg:phone":"+1   ",
    "sg:postcode":"07735",
    "sg:province":"NJ",
    "wof:name":"Marine Engine Service",
    "wof:placetype":"venue"
},
  "geometry": {"coordinates":[-74.21326999999999,40.432298],"type":"Point"}
}