{
  "type": "Feature",
  "properties": {
    "addr:full":"12 Emery Ave Mendham NJ 07945",
    "addr:housenumber":"12",
    "addr:postcode":"07945",
    "addr:street":"Emery Ave",
    "iso:country":"US",
    "sg:address":"12 Emery Ave",
    "sg:city":"Mendham",
    "sg:classifiers":[
        {
            "category":"Professional",
            "subcategory":"Management & Consulting",
            "type":"Services"
        }
    ],
    "sg:phone":"+1   ",
    "sg:postcode":"07945",
    "sg:province":"NJ",
    "wof:name":"V W Gilligan & Company",
    "wof:placetype":"venue"
},
  "geometry": {"coordinates":[-74.59790700000001,40.781308],"type":"Point"}
}