{
  "type": "Feature",
  "properties": {
    "iso:country":"US",
    "sg:address":"125 S Beverly Dr",
    "sg:city":"Brick",
    "sg:classifiers":[
        {
            "category":"Banks & Credit Unions",
            "subcategory":"Investment Brokerage",
            "type":"Services"
        }
    ],
    "sg:phone":"+1 732 840 0567",
    "sg:postcode":"08724",
    "sg:province":"NJ",
    "sg:tags":[
        "consultant",
        "planning",
        "financial"
    ],
    "wof:name":"Le Blanc Personal Financial",
    "wof:placetype":"venue"
},
  "geometry": {"coordinates":[-74.097843,40.104641],"type":"Point"}
}