{
  "type": "Feature",
  "properties": {
    "addr:full":"86 Trinity St Wyckoff NJ 07460",
    "addr:housenumber":"86",
    "addr:postcode":"07460",
    "addr:street":"Trinity St",
    "iso:country":"US",
    "sg:address":"86 Trinity St",
    "sg:city":"Wyckoff",
    "sg:classifiers":[
        {
            "category":"Banks & Credit Unions",
            "subcategory":"Investment Brokerage",
            "type":"Services"
        }
    ],
    "sg:phone":"+1   ",
    "sg:postcode":"07460",
    "sg:province":"NJ",
    "sg:tags":[
        "exchange"
    ],
    "wof:name":"American Stock Exchange",
    "wof:placetype":"venue"
},
  "geometry": {"coordinates":[-74.74660799999999,41.055384],"type":"Point"}
}