{
  "type": "Feature",
  "properties": {
    "addr:full":"200 Fries Ln Cherry Hill NJ 08003",
    "addr:housenumber":"200",
    "addr:postcode":"08003",
    "addr:street":"Fries Ln",
    "iso:country":"US",
    "sg:address":"200 Fries Ln",
    "sg:city":"Cherry Hill",
    "sg:classifiers":[
        {
            "category":"Professional",
            "type":"Services"
        }
    ],
    "sg:phone":"+1   ",
    "sg:postcode":"08003",
    "sg:province":"NJ",
    "wof:name":"Yale Asbell PC",
    "wof:placetype":"venue"
},
  "geometry": {"coordinates":[-74.962947,39.870512],"type":"Point"}
}