{
  "type": "Feature",
  "properties": {
    "addr:full":"35 Pine Pl Harrington Park NJ 07640",
    "addr:housenumber":"35",
    "addr:postcode":"07640",
    "addr:street":"Pine Pl",
    "iso:country":"US",
    "sg:address":"35 Pine Pl",
    "sg:city":"Harrington Park",
    "sg:classifiers":[
        {
            "category":"Professional",
            "subcategory":"Management & Consulting",
            "type":"Services"
        }
    ],
    "sg:phone":"+1 201 767 4644",
    "sg:postcode":"07640",
    "sg:province":"NJ",
    "sg:tags":[
        "counselor",
        "public",
        "relations"
    ],
    "wof:name":"Kermish-Geylin Public Rltns",
    "wof:placetype":"venue"
},
  "geometry": {"coordinates":[-73.983127,40.997209],"type":"Point"}
}