{
  "type": "Feature",
  "properties": {
    "iso:country":"US",
    "sg:address":"3 Lewis St",
    "sg:city":"Closter",
    "sg:classifiers":[
        {
            "category":"Education",
            "subcategory":"Special Training",
            "type":"Public Place"
        }
    ],
    "sg:phone":"+1 201 768 6116",
    "sg:postcode":"07624",
    "sg:province":"NJ",
    "sg:tags":[
        "school",
        "language"
    ],
    "wof:name":"Hi Q Academy",
    "wof:placetype":"venue"
},
  "geometry": {"coordinates":[-73.95834600000001,40.972273],"type":"Point"}
}