{
  "type": "Feature",
  "properties": {
    "addr:full":"453 State Rte 17 Paramus NJ 07652",
    "addr:housenumber":"453",
    "addr:postcode":"07652",
    "addr:street":"State Rte 17",
    "iso:country":"US",
    "sg:address":"453 State Rte 17",
    "sg:city":"Paramus",
    "sg:classifiers":[
        {
            "category":"Home & Garden",
            "subcategory":"Carpets & Floor Coverings",
            "type":"Retail Goods"
        }
    ],
    "sg:phone":"+1   ",
    "sg:postcode":"07652",
    "sg:province":"NJ",
    "wof:name":"Saba Oriental Rugs Inc",
    "wof:placetype":"venue"
},
  "geometry": {"coordinates":[-74.072881,40.952815],"type":"Point"}
}