{
  "type": "Feature",
  "properties": {
    "iso:country":"US",
    "sg:address":"1301 Bacharach Blvd",
    "sg:city":"Atlantic City",
    "sg:classifiers":[
        {
            "category":"Government",
            "subcategory":"Office",
            "type":"Public Place"
        }
    ],
    "sg:phone":"+1 609 347 5570",
    "sg:postcode":"08401",
    "sg:province":"NJ",
    "sg:tags":[
        "city",
        "resource",
        "human"
    ],
    "wof:name":"Atlantic City Welfare",
    "wof:placetype":"venue"
},
  "geometry": {"coordinates":[-74.428608,39.36293],"type":"Point"}
}