{
  "type": "Feature",
  "properties": {
    "iso:country":"US",
    "sg:address":"9001 Winchester Ave",
    "sg:city":"Margate City",
    "sg:classifiers":[
        {
            "category":"Education",
            "subcategory":"School",
            "type":"Public Place"
        }
    ],
    "sg:phone":"+1 609 822 2391",
    "sg:postcode":"08402",
    "sg:province":"NJ",
    "sg:website":"www.margateschools.org",
    "wof:name":"Union Avenue Elementary School",
    "wof:placetype":"venue"
},
  "geometry": {"coordinates":[-74.512705,39.324881],"type":"Point"}
}