{
  "type": "Feature",
  "properties": {
    "addr:full":"557 Cleveland Ave Linden NJ 07036",
    "addr:housenumber":"557",
    "addr:postcode":"07036",
    "addr:street":"Cleveland Ave",
    "iso:country":"US",
    "sg:address":"557 Cleveland Ave",
    "sg:city":"Linden",
    "sg:classifiers":[
        {
            "category":"Building & Trades",
            "subcategory":"Plumbing",
            "type":"Services"
        }
    ],
    "sg:phone":"+1 908 486 7970",
    "sg:postcode":"07036",
    "sg:province":"NJ",
    "sg:tags":[
        "heating",
        "contractor"
    ],
    "wof:name":"Atlantic Heating Corp",
    "wof:placetype":"venue"
},
  "geometry": {"coordinates":[-74.2565,40.640202],"type":"Point"}
}