{
  "type": "Feature",
  "properties": {
    "addr:full":"3300 Churchill Dr Toms River NJ 08753",
    "addr:housenumber":"3300",
    "addr:postcode":"08753",
    "addr:street":"Churchill Dr",
    "iso:country":"US",
    "sg:address":"3300 Churchill Dr",
    "sg:city":"Toms River",
    "sg:classifiers":[
        {
            "category":"Insurance",
            "subcategory":"Insurance Agent",
            "type":"Services"
        }
    ],
    "sg:phone":"+1 732 270 1200",
    "sg:postcode":"08753",
    "sg:province":"NJ",
    "wof:name":"Robert D Ilaria Insurance",
    "wof:placetype":"venue"
},
  "geometry": {"coordinates":[-74.111311,39.961513],"type":"Point"}
}