{
  "type": "Feature",
  "properties": {
    "iso:country":"US",
    "sg:address":"12 1st Ave",
    "sg:city":"Bloomfield",
    "sg:classifiers":[
        {
            "category":"Food & Beverages",
            "subcategory":"Groceries & Convenience Stores",
            "type":"Retail Goods"
        }
    ],
    "sg:phone":"+1 973 743 0477",
    "sg:postcode":"07003",
    "sg:province":"NJ",
    "wof:name":"Sanita Grocery Store",
    "wof:placetype":"venue"
},
  "geometry": {"coordinates":[-74.189134,40.769862],"type":"Point"}
}