{
  "type": "Feature",
  "properties": {
    "iso:country":"US",
    "sg:address":"144 Farnsworth Ave",
    "sg:city":"Bordentown",
    "sg:classifiers":[
        {
            "category":"Shopping",
            "subcategory":"Musical Instruments",
            "type":"Retail Goods"
        },
        {
            "category":"Personal",
            "type":"Services"
        },
        {
            "category":"Retail",
            "subcategory":"Repair Shop",
            "type":"Services"
        }
    ],
    "sg:phone":"+1 609 298 9922",
    "sg:postcode":"08505",
    "sg:province":"NJ",
    "sg:tags":[
        "organ",
        "refinish",
        "organ-tuning",
        "moving",
        "piano",
        "restoration",
        "furniture"
    ],
    "wof:name":"Mozart Piano Co",
    "wof:placetype":"venue"
},
  "geometry": {"coordinates":[-74.713082,40.147849],"type":"Point"}
}