{
  "type": "Feature",
  "properties": {
    "addr:full":"6475 US Hwy 9 Howell NJ 07731",
    "addr:housenumber":"6475",
    "addr:postcode":"07731",
    "addr:street":"Us Hwy 9",
    "iso:country":"US",
    "sg:address":"6475 US Hwy 9",
    "sg:city":"Howell",
    "sg:classifiers":[
        {
            "category":"Home & Garden",
            "subcategory":"Carpets & Floor Coverings",
            "type":"Retail Goods"
        }
    ],
    "sg:phone":"+1   ",
    "sg:postcode":"07731",
    "sg:province":"NJ",
    "wof:name":"Lakewood Floor Covering LTD",
    "wof:placetype":"venue"
},
  "geometry": {"coordinates":[-74.219549,40.119303],"type":"Point"}
}