{
  "type": "Feature",
  "properties": {
    "iso:country":"US",
    "sg:address":"1 Hudson Pl",
    "sg:city":"Hoboken",
    "sg:classifiers":[
        {
            "category":"Food & Beverages",
            "subcategory":"Liquor & Beverages",
            "type":"Retail Goods"
        }
    ],
    "sg:phone":"+1 201 963 0761",
    "sg:postcode":"07030",
    "sg:province":"NJ",
    "sg:tags":[
        "beer",
        "spirit",
        "wine"
    ],
    "wof:name":"Lackawanna Liquors",
    "wof:placetype":"venue"
},
  "geometry": {"coordinates":[-74.026398,40.735401],"type":"Point"}
}