{
  "type": "Feature",
  "properties": {
    "iso:country":"US",
    "sg:address":"1500 Saint Georges Ave",
    "sg:city":"Avenel",
    "sg:classifiers":[
        {
            "category":"Restaurant",
            "type":"Food & Drink"
        }
    ],
    "sg:phone":"+1   ",
    "sg:postcode":"07001",
    "sg:province":"NJ",
    "sg:tags":[
        "eating"
    ],
    "wof:name":"Jtd Inc",
    "wof:placetype":"venue"
},
  "geometry": {"coordinates":[-74.290764,40.590244],"type":"Point"}
}