{
  "type": "Feature",
  "properties": {
    "iso:country":"US",
    "sg:address":"315 E Northfield Rd Ste 2A",
    "sg:city":"Livingston",
    "sg:classifiers":[
        {
            "category":"Health Services",
            "subcategory":"Doctor",
            "type":"Services"
        }
    ],
    "sg:phone":"+1 973 535 3200",
    "sg:postcode":"07039",
    "sg:province":"NJ",
    "sg:tags":[
        "dermatologist"
    ],
    "sg:website":"www.drcitron.com",
    "wof:name":"Citron Cheryl S MD",
    "wof:placetype":"venue"
},
  "geometry": {"coordinates":[-74.304703,40.7714],"type":"Point"}
}