{
  "type": "Feature",
  "properties": {
    "addr:full":"127 Red Lion Rd Southampton NJ 08088",
    "addr:housenumber":"127",
    "addr:postcode":"red;08088",
    "addr:street":"Lion Rd",
    "iso:country":"US",
    "sg:address":"127 Red Lion Rd",
    "sg:city":"Southampton",
    "sg:classifiers":[
        {
            "category":"Health Services",
            "subcategory":"Doctor",
            "type":"Services"
        }
    ],
    "sg:phone":"+1 609 801 0077",
    "sg:postcode":"08088",
    "sg:province":"NJ",
    "sg:tags":[
        "physician",
        "surgeon"
    ],
    "wof:name":"Nuclear Cardiology Consultants",
    "wof:placetype":"venue"
},
  "geometry": {"coordinates":[-74.74402499999999,39.894103],"type":"Point"}
}