{
  "type": "Feature",
  "properties": {
    "addr:full":"130 State Rte 31 Pennington NJ 08534",
    "addr:housenumber":"130",
    "addr:postcode":"08534",
    "addr:street":"State Rte 31",
    "iso:country":"US",
    "sg:address":"130 State Rte 31",
    "sg:city":"Pennington",
    "sg:classifiers":[
        {
            "category":"Education",
            "subcategory":"School",
            "type":"Public Place"
        }
    ],
    "sg:phone":"+1 609 737 1525",
    "sg:postcode":"08534",
    "sg:province":"NJ",
    "wof:name":"Princeton School-Real Estate",
    "wof:placetype":"venue"
},
  "geometry": {"coordinates":[-74.798481,40.359347],"type":"Point"}
}