{
  "type": "Feature",
  "properties": {
    "addr:full":"207 Bellevue Ave Montclair NJ 07043",
    "addr:housenumber":"207",
    "addr:postcode":"07043",
    "addr:street":"Bellevue Ave",
    "iso:country":"US",
    "sg:address":"207 Bellevue Ave",
    "sg:city":"Montclair",
    "sg:classifiers":[
        {
            "category":"Social Services",
            "type":"Services"
        }
    ],
    "sg:phone":"+1 973 744 0049",
    "sg:postcode":"07043",
    "sg:province":"NJ",
    "sg:tags":[
        "worker"
    ],
    "wof:name":"Elisabeth Dagress",
    "wof:placetype":"venue"
},
  "geometry": {"coordinates":[-74.20771999999999,40.841108],"type":"Point"}
}