{
  "type": "Feature",
  "properties": {
    "iso:country":"US",
    "sg:address":"9 Mulberry Ln",
    "sg:city":"Holmdel",
    "sg:classifiers":[
        {
            "category":"Banks & Credit Unions",
            "subcategory":"Investment Brokerage",
            "type":"Services"
        }
    ],
    "sg:phone":"+1   ",
    "sg:postcode":"07722",
    "sg:province":"NJ",
    "sg:tags":[
        "advisory"
    ],
    "wof:name":"Lynns Financial Services LLC",
    "wof:placetype":"venue"
},
  "geometry": {"coordinates":[-74.19764000000001,40.326834],"type":"Point"}
}