{
  "type": "Feature",
  "properties": {
    "addr:full":"69 Portland Pl Montclair NJ 07042",
    "addr:housenumber":"69",
    "addr:postcode":"07042",
    "addr:street":"Portland Pl",
    "iso:country":"US",
    "sg:address":"69 Portland Pl",
    "sg:city":"Montclair",
    "sg:classifiers":[
        {
            "category":"Bars & Pubs",
            "subcategory":"Nightclub",
            "type":"Food & Drink"
        }
    ],
    "sg:phone":"+1 973 744 4850",
    "sg:postcode":"07042",
    "sg:province":"NJ",
    "sg:tags":[
        "nightlife"
    ],
    "wof:name":"Wohleo Club",
    "wof:placetype":"venue"
},
  "geometry": {"coordinates":[-74.22110000000001,40.817699],"type":"Point"}
}