{
  "type": "Feature",
  "properties": {
    "iso:country":"US",
    "sg:address":"165 Whippany Rd",
    "sg:city":"Whippany",
    "sg:classifiers":[
        {
            "category":"Education",
            "subcategory":"School",
            "type":"Public Place"
        }
    ],
    "sg:phone":"+1 973 887 3004",
    "sg:postcode":"07981",
    "sg:province":"NJ",
    "sg:tags":[
        "high",
        "middle",
        "elementary"
    ],
    "wof:name":"Hanover Park Regional Board of Education",
    "wof:placetype":"venue"
},
  "geometry": {"coordinates":[-74.42440999999999,40.816123],"type":"Point"}
}