{
  "type": "Feature",
  "properties": {
    "addr:full":"18 Beechwood Ave Lake Hiawatha NJ 07034",
    "addr:housenumber":"18",
    "addr:postcode":"07034",
    "addr:street":"Beechwood Ave",
    "iso:country":"US",
    "sg:address":"18 Beechwood Ave",
    "sg:city":"Lake Hiawatha",
    "sg:classifiers":[
        {
            "category":"Building & Trades",
            "subcategory":"Plumbing",
            "type":"Services"
        }
    ],
    "sg:phone":"+1 973 334 2835",
    "sg:postcode":"07034",
    "sg:province":"NJ",
    "sg:tags":[
        "contractor"
    ],
    "wof:name":"Kuber & Sons Plumbing",
    "wof:placetype":"venue"
},
  "geometry": {"coordinates":[-74.388284,40.885088],"type":"Point"}
}