{
  "type": "Feature",
  "properties": {
    "addr:full":"7 Regent St Livingston NJ 07039",
    "addr:housenumber":"7",
    "addr:postcode":"07039",
    "addr:street":"Regent St",
    "iso:country":"US",
    "sg:address":"7 Regent St",
    "sg:city":"Livingston",
    "sg:classifiers":[
        {
            "category":"Professional",
            "subcategory":"Lawyer & Legal Services",
            "type":"Services"
        }
    ],
    "sg:phone":"+1 973 422 0422",
    "sg:postcode":"07039",
    "sg:province":"NJ",
    "sg:website":"www.labbatebalkan.com",
    "wof:name":"L'sbbate Balkan Colavita & Contini",
    "wof:placetype":"venue"
},
  "geometry": {"coordinates":[-74.353996,40.798599],"type":"Point"}
}