{
  "type": "Feature",
  "properties": {
    "iso:country":"US",
    "sg:address":"633 Water St",
    "sg:city":"Belvidere",
    "sg:classifiers":[
        {
            "category":"Retail",
            "subcategory":"Auto Repair",
            "type":"Services"
        }
    ],
    "sg:phone":"+1   ",
    "sg:postcode":"07823",
    "sg:province":"NJ",
    "sg:tags":[
        "station",
        "gasoline"
    ],
    "wof:name":"Texaco",
    "wof:placetype":"venue"
},
  "geometry": {"coordinates":[-75.065979,40.832784],"type":"Point"}
}