{
  "type": "Feature",
  "properties": {
    "iso:country":"US",
    "sg:address":"645 Lenox Ave",
    "sg:city":"Westfield",
    "sg:classifiers":[
        {
            "category":"Professional",
            "subcategory":"Computer Services",
            "type":"Services"
        }
    ],
    "sg:phone":"+1 908 654 5415",
    "sg:postcode":"07090",
    "sg:province":"NJ",
    "sg:tags":[
        "related"
    ],
    "wof:name":"Computerosity Shop",
    "wof:placetype":"venue"
},
  "geometry": {"coordinates":[-74.33926099999999,40.656828],"type":"Point"}
}