{
  "type": "Feature",
  "properties": {
    "addr:full":"245 Adams St Newark NJ 07105",
    "addr:housenumber":"245",
    "addr:postcode":"07105",
    "addr:street":"Adams St",
    "iso:country":"US",
    "sg:address":"245 Adams St",
    "sg:city":"Newark",
    "sg:classifiers":[
        {
            "category":"Building & Trades",
            "subcategory":"Locksmith",
            "type":"Services"
        }
    ],
    "sg:phone":"+1 973 854 5192",
    "sg:postcode":"07105",
    "sg:province":"NJ",
    "sg:tags":[
        "key"
    ],
    "wof:name":"0 0 24 Hour 7 Day A Emergency Locksmith",
    "wof:placetype":"venue"
},
  "geometry": {"coordinates":[-74.161777,40.724211],"type":"Point"}
}