{
  "type": "Feature",
  "properties": {
    "iso:country":"US",
    "sg:address":"364 Echo Valley Ln",
    "sg:city":"Butler",
    "sg:classifiers":[
        {
            "category":"Professional",
            "subcategory":"Management & Consulting",
            "type":"Services"
        }
    ],
    "sg:phone":"+1   ",
    "sg:postcode":"07405",
    "sg:province":"NJ",
    "wof:name":"Right Track Marketing",
    "wof:placetype":"venue"
},
  "geometry": {"coordinates":[-74.40354499999999,41.009372],"type":"Point"}
}