{
  "type": "Feature",
  "properties": {
    "addr:full":"311 Knollwood Dr Egg Harbor Township NJ 08234",
    "addr:housenumber":"311",
    "addr:postcode":"08234",
    "addr:street":"Knollwood Dr",
    "iso:country":"US",
    "sg:address":"311 Knollwood Dr",
    "sg:city":"Egg Harbor Township",
    "sg:classifiers":[
        {
            "category":"Restaurant",
            "type":"Food & Drink"
        }
    ],
    "sg:phone":"+1   ",
    "sg:postcode":"08234",
    "sg:province":"NJ",
    "sg:tags":[
        "eating"
    ],
    "wof:name":"Beverage & Restaurant Services",
    "wof:placetype":"venue"
},
  "geometry": {"coordinates":[-74.595117,39.36195],"type":"Point"}
}