{
  "type": "Feature",
  "properties": {
    "iso:country":"US",
    "sg:address":"2 Garfield St",
    "sg:city":"Linden",
    "sg:classifiers":[
        {
            "category":"Retail",
            "subcategory":"Auto Repair",
            "type":"Services"
        }
    ],
    "sg:phone":"+1 908 925 9077",
    "sg:postcode":"07036",
    "sg:province":"NJ",
    "wof:name":"Classic Coach Repair Inc",
    "wof:placetype":"venue"
},
  "geometry": {"coordinates":[-74.23343300000001,40.647376],"type":"Point"}
}