{
  "type": "Feature",
  "properties": {
    "addr:full":"27 Long Valley Rd Lodi NJ 07644",
    "addr:housenumber":"27",
    "addr:postcode":"07644",
    "addr:street":"Long Valley Rd",
    "iso:country":"US",
    "sg:address":"27 Long Valley Rd",
    "sg:city":"Lodi",
    "sg:classifiers":[
        {
            "category":"Retail",
            "subcategory":"Repair Shop",
            "type":"Services"
        }
    ],
    "sg:phone":"+1 201 843 2992",
    "sg:postcode":"07644",
    "sg:province":"NJ",
    "sg:tags":[
        "electrical",
        "range",
        "appliance",
        "oven"
    ],
    "wof:name":"Pride Appliances",
    "wof:placetype":"venue"
},
  "geometry": {"coordinates":[-74.074668,40.89065],"type":"Point"}
}