{
  "type": "Feature",
  "properties": {
    "addr:full":"35 N New Hampshire Ave Atlantic City NJ 08401",
    "addr:housenumber":"35",
    "addr:postcode":"08401",
    "addr:street":"N New Hampshire Ave",
    "iso:country":"US",
    "sg:address":"35 N New Hampshire Ave",
    "sg:city":"Atlantic City",
    "sg:classifiers":[
        {
            "category":"Building & Trades",
            "subcategory":"Construction",
            "type":"Services"
        }
    ],
    "sg:phone":"+1 609 340 9961",
    "sg:postcode":"08401",
    "sg:province":"NJ",
    "sg:tags":[
        "residential"
    ],
    "wof:name":"Affordable Housing Developers",
    "wof:placetype":"venue"
},
  "geometry": {"coordinates":[-74.413839,39.369716],"type":"Point"}
}