{
  "type": "Feature",
  "properties": {
    "addr:full":"56 Parker Ave Hawthorne NJ 07506",
    "addr:housenumber":"56",
    "addr:postcode":"07506",
    "addr:street":"Parker Ave",
    "iso:country":"US",
    "sg:address":"56 Parker Ave",
    "sg:city":"Hawthorne",
    "sg:classifiers":[
        {
            "category":"Building & Trades",
            "subcategory":"Construction",
            "type":"Services"
        }
    ],
    "sg:phone":"+1 973 423 3330",
    "sg:postcode":"07506",
    "sg:province":"NJ",
    "sg:tags":[
        "house"
    ],
    "wof:name":"Mansion Ridge Building Company",
    "wof:placetype":"venue"
},
  "geometry": {"coordinates":[-74.149214,40.957168],"type":"Point"}
}