{
  "type": "Feature",
  "properties": {
    "addr:full":"617 Heron Dr Swedesboro NJ 08085",
    "addr:housenumber":"617",
    "addr:postcode":"08085",
    "addr:street":"Heron Dr",
    "iso:country":"US",
    "sg:address":"617 Heron Dr",
    "sg:city":"Swedesboro",
    "sg:classifiers":[
        {
            "category":"Manufacturing",
            "subcategory":"Food",
            "type":"Manufacturing & Wholesale Goods"
        }
    ],
    "sg:phone":"+1 856 467 4949",
    "sg:postcode":"08085",
    "sg:province":"NJ",
    "sg:tags":[
        "cocoa",
        "chocolate"
    ],
    "wof:name":"Coco Tech",
    "wof:placetype":"venue"
},
  "geometry": {"coordinates":[-75.36012599999999,39.76641],"type":"Point"}
}