{
  "type": "Feature",
  "properties": {
    "iso:country":"US",
    "sg:address":"763 Galda Rd",
    "sg:city":"Paramus",
    "sg:classifiers":[
        {
            "category":"Real Estate",
            "subcategory":"Real Estate Agent",
            "type":"Services"
        }
    ],
    "sg:phone":"+1   ",
    "sg:postcode":"07652",
    "sg:province":"NJ",
    "wof:name":"Precision Appraisers Inc",
    "wof:placetype":"venue"
},
  "geometry": {"coordinates":[-74.069907,40.971601],"type":"Point"}
}