{
  "type": "Feature",
  "properties": {
    "addr:full":"707 Dow Ave Oakhurst NJ 07755",
    "addr:housenumber":"707",
    "addr:postcode":"07755",
    "addr:street":"Dow Ave",
    "iso:country":"US",
    "sg:address":"707 Dow Ave",
    "sg:city":"Oakhurst",
    "sg:classifiers":[
        {
            "category":"Professional",
            "type":"Services"
        }
    ],
    "sg:phone":"+1 732 922 2604",
    "sg:postcode":"07755",
    "sg:province":"NJ",
    "sg:tags":[
        "establishment"
    ],
    "wof:name":"Protective Coating Develpmt",
    "wof:placetype":"venue"
},
  "geometry": {"coordinates":[-74.036878,40.261965],"type":"Point"}
}