{
  "type": "Feature",
  "properties": {
    "iso:country":"US",
    "sg:address":"11 Linda Ln",
    "sg:city":"Summit",
    "sg:classifiers":[
        {
            "category":"Professional",
            "subcategory":"Lawyer & Legal Services",
            "type":"Services"
        }
    ],
    "sg:phone":"+1 908 273 6595",
    "sg:postcode":"07901",
    "sg:province":"NJ",
    "wof:name":"Jhdcg Associates Inc",
    "wof:placetype":"venue"
},
  "geometry": {"coordinates":[-74.37249799999999,40.704201],"type":"Point"}
}