{
  "type": "Feature",
  "properties": {
    "addr:full":"620 Easton Ave Somerset NJ 08873",
    "addr:housenumber":"620",
    "addr:postcode":"08873",
    "addr:street":"Easton Ave",
    "iso:country":"US",
    "sg:address":"620 Easton Ave",
    "sg:city":"Somerset",
    "sg:classifiers":[
        {
            "category":"Retail",
            "subcategory":"Auto Repair",
            "type":"Services"
        }
    ],
    "sg:phone":"+1 732 246 9719",
    "sg:postcode":"08873",
    "sg:province":"NJ",
    "sg:tags":[
        "automotive"
    ],
    "wof:name":"Brake Place",
    "wof:placetype":"venue"
},
  "geometry": {"coordinates":[-74.47300799999999,40.507197],"type":"Point"}
}