{
  "type": "Feature",
  "properties": {
    "addr:full":"51 Kings Hwy E Haddonfield NJ 08033",
    "addr:housenumber":"51",
    "addr:postcode":"08033",
    "addr:street":"Kings Hwy E",
    "iso:country":"US",
    "sg:address":"51 Kings Hwy E",
    "sg:city":"Haddonfield",
    "sg:classifiers":[
        {
            "category":"Restaurant",
            "type":"Food & Drink"
        }
    ],
    "sg:phone":"+1 856 429 2055",
    "sg:postcode":"08033",
    "sg:province":"NJ",
    "wof:name":"Russ's Cafe",
    "wof:placetype":"venue"
},
  "geometry": {"coordinates":[-75.03516399999999,39.896485],"type":"Point"}
}