{
  "type": "Feature",
  "properties": {
    "addr:full":"575 Miller Rd Wyckoff NJ 07481",
    "addr:housenumber":"575",
    "addr:postcode":"07481",
    "addr:street":"Miller Rd",
    "iso:country":"US",
    "sg:address":"575 Miller Rd",
    "sg:city":"Wyckoff",
    "sg:classifiers":[
        {
            "category":"Home & Garden",
            "subcategory":"Furniture",
            "type":"Retail Goods"
        }
    ],
    "sg:phone":"+1   ",
    "sg:postcode":"07481",
    "sg:province":"NJ",
    "wof:name":"American British Cabinetry LLC",
    "wof:placetype":"venue"
},
  "geometry": {"coordinates":[-74.18772199999999,40.997637],"type":"Point"}
}