{
  "type": "Feature",
  "properties": {
    "addr:full":"293 Essex Ave Thorofare NJ 08086",
    "addr:housenumber":"293",
    "addr:postcode":"08086",
    "addr:street":"Essex Ave",
    "iso:country":"US",
    "sg:address":"293 Essex Ave",
    "sg:city":"Thorofare",
    "sg:classifiers":[
        {
            "category":"Professional",
            "type":"Services"
        }
    ],
    "sg:phone":"+1   ",
    "sg:postcode":"08086",
    "sg:province":"NJ",
    "wof:name":"Iwantmyownwebpagecom",
    "wof:placetype":"venue"
},
  "geometry": {"coordinates":[-75.171148,39.840218],"type":"Point"}
}