{
  "type": "Feature",
  "properties": {
    "iso:country":"US",
    "sg:address":"15 Fuller Pl",
    "sg:city":"Kearny",
    "sg:classifiers":[
        {
            "category":"Food & Beverages",
            "subcategory":"Groceries & Convenience Stores",
            "type":"Retail Goods"
        }
    ],
    "sg:phone":"+1   ",
    "sg:postcode":"07032",
    "sg:province":"NJ",
    "wof:name":"Ras Marketing",
    "wof:placetype":"venue"
},
  "geometry": {"coordinates":[-74.15045499999999,40.770547],"type":"Point"}
}