{
  "type": "Feature",
  "properties": {
    "addr:full":"12 Edgewater Dr Toms River NJ 08757",
    "addr:housenumber":"12",
    "addr:postcode":"08757",
    "addr:street":"Edgewater Dr",
    "iso:country":"US",
    "sg:address":"12 Edgewater Dr",
    "sg:city":"Toms River",
    "sg:classifiers":[
        {
            "category":"Insurance",
            "subcategory":"Insurance Agent",
            "type":"Services"
        }
    ],
    "sg:phone":"+1   ",
    "sg:postcode":"08757",
    "sg:province":"NJ",
    "wof:name":"Navy Seabee Veterans of A",
    "wof:placetype":"venue"
},
  "geometry": {"coordinates":[-74.281638,39.954955],"type":"Point"}
}