{
  "type": "Feature",
  "properties": {
    "addr:full":"3801 Park Blvd Wildwood NJ 08260",
    "addr:housenumber":"3801",
    "addr:postcode":"08260",
    "addr:street":"Park Blvd",
    "iso:country":"US",
    "sg:address":"3801 Park Blvd",
    "sg:city":"Wildwood",
    "sg:classifiers":[
        {
            "category":"Wholesale",
            "subcategory":"Hardware",
            "type":"Manufacturing & Wholesale Goods"
        }
    ],
    "sg:phone":"+1 609 522 1449",
    "sg:postcode":"08260",
    "sg:province":"NJ",
    "sg:tags":[
        "plumbing",
        "equipment",
        "fixture",
        "supply"
    ],
    "wof:name":"Grove Supply Inc",
    "wof:placetype":"venue"
},
  "geometry": {"coordinates":[-74.819585,38.991322],"type":"Point"}
}