{
  "type": "Feature",
  "properties": {
    "addr:full":"1185 Morris Ave Union NJ 07083",
    "addr:housenumber":"1185",
    "addr:postcode":"07083",
    "addr:street":"Morris Ave",
    "iso:country":"US",
    "sg:address":"1185 Morris Ave",
    "sg:city":"Union",
    "sg:classifiers":[
        {
            "category":"Freight",
            "type":"Transportation"
        }
    ],
    "sg:phone":"+1 908 624 0070",
    "sg:postcode":"07083",
    "sg:province":"NJ",
    "sg:tags":[
        "arrangement"
    ],
    "wof:name":"Trans Global Shipping",
    "wof:placetype":"venue"
},
  "geometry": {"coordinates":[-74.240179,40.686285],"type":"Point"}
}