{
  "type": "Feature",
  "properties": {
    "addr:full":"911 Charles Dr Toms River NJ 08753",
    "addr:housenumber":"911",
    "addr:postcode":"08753",
    "addr:street":"Charles Dr",
    "iso:country":"US",
    "sg:address":"911 Charles Dr",
    "sg:city":"Toms River",
    "sg:classifiers":[
        {
            "category":"Manufacturing",
            "subcategory":"Printing",
            "type":"Manufacturing & Wholesale Goods"
        }
    ],
    "sg:phone":"+1 732 240 2038",
    "sg:postcode":"08753",
    "sg:province":"NJ",
    "sg:tags":[
        "printer"
    ],
    "wof:name":"Three Cent Copies Inc",
    "wof:placetype":"venue"
},
  "geometry": {"coordinates":[-74.182951,39.963064],"type":"Point"}
}