{
  "type": "Feature",
  "properties": {
    "iso:country":"US",
    "sg:address":"1270 Whitehorse Mercerville Rd",
    "sg:city":"Mercerville",
    "sg:classifiers":[
        {
            "category":"Government",
            "subcategory":"Police Station",
            "type":"Public Place"
        }
    ],
    "sg:phone":"+1 609 581 4045",
    "sg:postcode":"08619",
    "sg:province":"NJ",
    "sg:tags":[
        "department"
    ],
    "wof:name":"Hamilton Township Police Div",
    "wof:placetype":"venue"
},
  "geometry": {"coordinates":[-74.69167400000001,40.213696],"type":"Point"}
}