{
  "type": "Feature",
  "properties": {
    "addr:full":"14 Stockton Ct East Brunswick NJ 08816",
    "addr:housenumber":"14",
    "addr:postcode":"08816",
    "addr:street":"Stockton Ct",
    "iso:country":"US",
    "sg:address":"14 Stockton Ct",
    "sg:city":"East Brunswick",
    "sg:classifiers":[
        {
            "category":"Professional",
            "subcategory":"Lawyer & Legal Services",
            "type":"Services"
        }
    ],
    "sg:phone":"+1 732 432 7602",
    "sg:postcode":"08816",
    "sg:province":"NJ",
    "sg:tags":[
        "attorney"
    ],
    "wof:name":"Alfred Polizzotto",
    "wof:placetype":"venue"
},
  "geometry": {"coordinates":[-74.42547999999999,40.420116],"type":"Point"}
}