{
  "type": "Feature",
  "properties": {
    "iso:country":"US",
    "sg:address":"77 Martin Luther King Ave",
    "sg:city":"Morristown",
    "sg:classifiers":[
        {
            "category":"Deli",
            "type":"Food & Drink"
        },
        {
            "category":"Food & Beverages",
            "subcategory":"Bakery",
            "type":"Retail Goods"
        }
    ],
    "sg:phone":"+1 973 605 5236",
    "sg:postcode":"07960",
    "sg:province":"NJ",
    "sg:tags":[
        "sandwich"
    ],
    "wof:name":"Cafe Y Canela Colombian Restaurant",
    "wof:placetype":"venue"
},
  "geometry": {"coordinates":[-74.473657,40.805716],"type":"Point"}
}