{
  "type": "Feature",
  "properties": {
    "addr:full":"1 Harmon Plz Secaucus NJ 07094",
    "addr:housenumber":"1",
    "addr:postcode":"07094",
    "addr:street":"Harmon Plz",
    "iso:country":"US",
    "sg:address":"1 Harmon Plz",
    "sg:city":"Secaucus",
    "sg:classifiers":[
        {
            "category":"Insurance",
            "subcategory":"Insurance Agent",
            "type":"Services"
        }
    ],
    "sg:phone":"+1 201 867 6871",
    "sg:postcode":"07094",
    "sg:province":"NJ",
    "wof:name":"Lichtenberger Agency LLC",
    "wof:placetype":"venue"
},
  "geometry": {"coordinates":[-74.07261099999999,40.795601],"type":"Point"}
}