{
  "type": "Feature",
  "properties": {
    "iso:country":"US",
    "sg:address":"54 Kings Land Ct",
    "sg:city":"Fair Lawn",
    "sg:classifiers":[
        {
            "category":"Real Estate",
            "subcategory":"Real Estate Agent",
            "type":"Services"
        }
    ],
    "sg:phone":"+1   ",
    "sg:postcode":"07410",
    "sg:province":"NJ",
    "wof:name":"Garden Homes Inc",
    "wof:placetype":"venue"
},
  "geometry": {"coordinates":[-74.125507,40.941976],"type":"Point"}
}