{
  "type": "Feature",
  "properties": {
    "addr:full":"32 Kinderkamack Rd Oradell NJ 07649",
    "addr:housenumber":"32",
    "addr:postcode":"07649",
    "addr:street":"Kinderkamack Rd",
    "iso:country":"US",
    "sg:address":"32 Kinderkamack Rd",
    "sg:city":"Oradell",
    "sg:classifiers":[
        {
            "category":"Home & Garden",
            "subcategory":"Building Materials",
            "type":"Retail Goods"
        }
    ],
    "sg:phone":"+1   ",
    "sg:postcode":"07649",
    "sg:province":"NJ",
    "sg:tags":[
        "trade",
        "contractor"
    ],
    "wof:name":"Town & Country Kitchens Inc",
    "wof:placetype":"venue"
},
  "geometry": {"coordinates":[-74.029265,40.943397],"type":"Point"}
}