{
  "type": "Feature",
  "properties": {
    "addr:full":"55 Main St East Brunswick NJ 08816",
    "addr:housenumber":"55",
    "addr:postcode":"08816",
    "addr:street":"Main St",
    "iso:country":"US",
    "sg:address":"55 Main St",
    "sg:city":"East Brunswick",
    "sg:classifiers":[
        {
            "category":"Retail",
            "subcategory":"Auto Repair",
            "type":"Services"
        }
    ],
    "sg:phone":"+1 732 723 0055",
    "sg:postcode":"08816",
    "sg:province":"NJ",
    "sg:tags":[
        "repairing",
        "automobile"
    ],
    "wof:name":"Mazzio's Auto Ctr",
    "wof:placetype":"venue"
},
  "geometry": {"coordinates":[-74.373108,40.408685],"type":"Point"}
}