{
  "type": "Feature",
  "properties": {
    "addr:full":"16 Bacorn Rd Flemington NJ 08822",
    "addr:housenumber":"16",
    "addr:postcode":"08822",
    "addr:street":"Bacorn Rd",
    "iso:country":"US",
    "sg:address":"16 Bacorn Rd",
    "sg:city":"Flemington",
    "sg:classifiers":[
        {
            "category":"Manufacturing",
            "subcategory":"Glass & Minerals",
            "type":"Manufacturing & Wholesale Goods"
        }
    ],
    "sg:phone":"+1 908 788 2929",
    "sg:postcode":"08822",
    "sg:province":"NJ",
    "sg:tags":[
        "abrasive",
        "product",
        "mfg"
    ],
    "wof:name":"Fusion Abrasives Inc",
    "wof:placetype":"venue"
},
  "geometry": {"coordinates":[-74.82912,40.504285],"type":"Point"}
}