{
  "type": "Feature",
  "properties": {
    "iso:country":"US",
    "sg:address":"1705 Clifton Ave",
    "sg:city":"Lakewood",
    "sg:classifiers":[
        {
            "category":"Personal",
            "subcategory":"Beauty Salon",
            "type":"Services"
        }
    ],
    "sg:phone":"+1 732 363 9860",
    "sg:postcode":"08701",
    "sg:province":"NJ",
    "sg:tags":[
        "shop"
    ],
    "wof:name":"Margarets Split Designs",
    "wof:placetype":"venue"
},
  "geometry": {"coordinates":[-74.21716499999999,40.106048],"type":"Point"}
}