{
  "type": "Feature",
  "properties": {
    "addr:full":"205 Quakerbridge Mall Trenton NJ 08648",
    "addr:housenumber":"205",
    "addr:postcode":"08648",
    "addr:street":"Quakerbridge Mall",
    "iso:country":"US",
    "sg:address":"205 Quakerbridge Mall",
    "sg:city":"Trenton",
    "sg:classifiers":[
        {
            "category":"Shopping",
            "subcategory":"Optical Goods",
            "type":"Retail Goods"
        }
    ],
    "sg:phone":"+1   ",
    "sg:postcode":"08648",
    "sg:province":"NJ",
    "wof:name":"Pearle Vision Express",
    "wof:placetype":"venue"
},
  "geometry": {"coordinates":[-74.685166,40.289605],"type":"Point"}
}