{
  "type": "Feature",
  "properties": {
    "addr:full":"514 E Saddle River Rd Upper Saddle Rvr NJ 07458",
    "addr:housenumber":"514",
    "addr:postcode":"07458",
    "addr:street":"E Saddle River Rd Upper Saddle Rvr",
    "iso:country":"US",
    "sg:address":"514 E Saddle River Rd",
    "sg:city":"Upper Saddle Rvr",
    "sg:classifiers":[
        {
            "category":"Organizations",
            "subcategory":"Religious Organization",
            "type":"Services"
        }
    ],
    "sg:phone":"+1 201 934 5081",
    "sg:postcode":"07458",
    "sg:province":"NJ",
    "sg:tags":[
        "clergy"
    ],
    "wof:name":"Robert Fretz",
    "wof:placetype":"venue"
},
  "geometry": {"coordinates":[-74.08446600000001,41.071401],"type":"Point"}
}