{
  "type": "Feature",
  "properties": {
    "addr:full":"32 Sterling St Lakehurst NJ 08759",
    "addr:housenumber":"32",
    "addr:postcode":"08759",
    "addr:street":"Sterling St",
    "iso:country":"US",
    "sg:address":"32 Sterling St",
    "sg:city":"Lakehurst",
    "sg:classifiers":[
        {
            "category":"Manufacturing",
            "subcategory":"Printing",
            "type":"Manufacturing & Wholesale Goods"
        }
    ],
    "sg:phone":"+1 732 657 3212",
    "sg:postcode":"08759",
    "sg:province":"NJ",
    "sg:tags":[
        "lithographic",
        "commercial"
    ],
    "wof:name":"BEm Printing",
    "wof:placetype":"venue"
},
  "geometry": {"coordinates":[-74.270256,40.014106],"type":"Point"}
}