{
  "type": "Feature",
  "properties": {
    "addr:full":"90 Main St Hackensack NJ 07601",
    "addr:housenumber":"90",
    "addr:postcode":"07601",
    "addr:street":"Main St",
    "iso:country":"US",
    "sg:address":"90 Main St",
    "sg:city":"Hackensack",
    "sg:classifiers":[
        {
            "category":"Professional",
            "subcategory":"Lawyer & Legal Services",
            "type":"Services"
        }
    ],
    "sg:phone":"+1 201 488 8666",
    "sg:postcode":"07601",
    "sg:province":"NJ",
    "wof:name":"Weinstein David Attorney",
    "wof:placetype":"venue"
},
  "geometry": {"coordinates":[-74.043504,40.880901],"type":"Point"}
}