{
  "type": "Feature",
  "properties": {
    "iso:country":"US",
    "sg:address":"211 Camden St",
    "sg:city":"Newark",
    "sg:classifiers":[
        {
            "category":"Manufacturing",
            "subcategory":"Metals",
            "type":"Manufacturing & Wholesale Goods"
        },
        {
            "category":"Manufacturing",
            "subcategory":"Tools & Machinery",
            "type":"Manufacturing & Wholesale Goods"
        }
    ],
    "sg:phone":"+1 973 642 6181",
    "sg:postcode":"07103",
    "sg:province":"NJ",
    "sg:tags":[
        "cutting",
        "gear",
        "mfg"
    ],
    "sg:website":"www.statetoolgear.com",
    "wof:name":"State Tool Gear Co Inc",
    "wof:placetype":"venue"
},
  "geometry": {"coordinates":[-74.194655,40.738112],"type":"Point"}
}