{
  "type": "Feature",
  "properties": {
    "addr:full":"165 Halsey St Newark NJ 07102",
    "addr:housenumber":"165",
    "addr:postcode":"07102",
    "addr:street":"Halsey St",
    "iso:country":"US",
    "sg:address":"165 Halsey St",
    "sg:city":"Newark",
    "sg:classifiers":[
        {
            "category":"Banks & Credit Unions",
            "subcategory":"Investment Brokerage",
            "type":"Services"
        }
    ],
    "sg:phone":"+1 973 623 3909",
    "sg:postcode":"07102",
    "sg:province":"NJ",
    "sg:tags":[
        "advisory",
        "financial"
    ],
    "wof:name":"Thales Funds Management",
    "wof:placetype":"venue"
},
  "geometry": {"coordinates":[-74.173717,40.736224],"type":"Point"}
}