{
  "type": "Feature",
  "properties": {
    "addr:full":"435 Chestnut Ridge Rd Woodcliff Lake NJ 07677",
    "addr:housenumber":"435",
    "addr:postcode":"07677",
    "addr:street":"Chestnut Ridge Rd",
    "iso:country":"US",
    "sg:address":"435 Chestnut Ridge Rd",
    "sg:city":"Woodcliff Lake",
    "sg:classifiers":[
        {
            "category":"Shopping",
            "subcategory":"Clothing, Apparel, & Fashions",
            "type":"Retail Goods"
        }
    ],
    "sg:phone":"+1 201 391 0662",
    "sg:postcode":"07677",
    "sg:province":"NJ",
    "sg:tags":[
        "infant",
        "wear"
    ],
    "wof:name":"Children's Place",
    "wof:placetype":"venue"
},
  "geometry": {"coordinates":[-74.072012,41.04408],"type":"Point"}
}