{
  "type": "Feature",
  "properties": {
    "iso:country":"US",
    "sg:address":"3101 Dune Dr",
    "sg:city":"Avalon",
    "sg:classifiers":[
        {
            "category":"Shopping",
            "subcategory":"Clothing, Apparel, & Fashions",
            "type":"Retail Goods"
        }
    ],
    "sg:phone":"+1 609 368 2252",
    "sg:postcode":"08202",
    "sg:province":"NJ",
    "sg:tags":[
        "sportswear"
    ],
    "wof:name":"Summersalt",
    "wof:placetype":"venue"
},
  "geometry": {"coordinates":[-74.723422,39.095217],"type":"Point"}
}