{
  "type": "Feature",
  "properties": {
    "addr:full":"833 Willow Ave Hoboken NJ 07030",
    "addr:housenumber":"833",
    "addr:postcode":"07030",
    "addr:street":"Willow Ave",
    "iso:country":"US",
    "sg:address":"833 Willow Ave",
    "sg:city":"Hoboken",
    "sg:classifiers":[
        {
            "category":"Retail",
            "subcategory":"Repair Shop",
            "type":"Services"
        }
    ],
    "sg:phone":"+1 201 334 3996",
    "sg:postcode":"07030",
    "sg:province":"NJ",
    "sg:tags":[
        "lock",
        "locksmith"
    ],
    "wof:name":"7 Day Emergency 24 Hour",
    "wof:placetype":"venue"
},
  "geometry": {"coordinates":[-74.031541,40.747482],"type":"Point"}
}