{
  "type": "Feature",
  "properties": {
    "addr:full":"470 W Commodore Blvd Jackson NJ 08527",
    "addr:housenumber":"470",
    "addr:postcode":"08527",
    "addr:street":"W Commodore Blvd",
    "iso:country":"US",
    "sg:address":"470 W Commodore Blvd",
    "sg:city":"Jackson",
    "sg:classifiers":[
        {
            "category":"Retail",
            "subcategory":"Animal Services",
            "type":"Services"
        }
    ],
    "sg:phone":"+1 732 928 2244",
    "sg:postcode":"08527",
    "sg:province":"NJ",
    "sg:tags":[
        "pet",
        "boarding",
        "sitting"
    ],
    "wof:name":"Allstar Kennel",
    "wof:placetype":"venue"
},
  "geometry": {"coordinates":[-74.38124500000001,40.153711],"type":"Point"}
}