{
  "type": "Feature",
  "properties": {
    "iso:country":"US",
    "sg:address":"603 Long Beach Blvd",
    "sg:city":"Ship Bottom",
    "sg:classifiers":[
        {
            "category":"Recreation",
            "type":"Entertainment"
        }
    ],
    "sg:phone":"+1 609 494 1709",
    "sg:postcode":"08008",
    "sg:province":"NJ",
    "sg:tags":[
        "course",
        "golf"
    ],
    "wof:name":"Surf City Island Golf",
    "wof:placetype":"venue"
},
  "geometry": {"coordinates":[-74.17459100000001,39.651096],"type":"Point"}
}