{
  "type": "Feature",
  "properties": {
    "addr:full":"301 Charles Ave Bellmawr NJ 08031",
    "addr:housenumber":"301",
    "addr:postcode":"08031",
    "addr:street":"Charles Ave",
    "iso:country":"US",
    "sg:address":"301 Charles Ave",
    "sg:city":"Bellmawr",
    "sg:classifiers":[
        {
            "category":"Arena",
            "subcategory":"Sports Club",
            "type":"Entertainment"
        }
    ],
    "sg:phone":"+1 856 931 1490",
    "sg:postcode":"08031",
    "sg:province":"NJ",
    "sg:tags":[
        "hockey"
    ],
    "wof:name":"Red Line Officials",
    "wof:placetype":"venue"
},
  "geometry": {"coordinates":[-75.109818,39.870216],"type":"Point"}
}