{
  "type": "Feature",
  "properties": {
    "addr:full":"1711 US Hwy 46 Parsippany NJ 07054",
    "addr:housenumber":"1711",
    "addr:postcode":"07054",
    "addr:street":"Us Hwy 46",
    "iso:country":"US",
    "sg:address":"1711 US Hwy 46",
    "sg:city":"Parsippany",
    "sg:classifiers":[
        {
            "category":"Professional",
            "subcategory":"Management & Consulting",
            "type":"Services"
        }
    ],
    "sg:phone":"+1 973 402 1000",
    "sg:postcode":"07054",
    "sg:province":"NJ",
    "wof:name":"Crow Holdings",
    "wof:placetype":"venue"
},
  "geometry": {"coordinates":[-74.411097,40.866811],"type":"Point"}
}