{
  "type": "Feature",
  "properties": {
    "iso:country":"US",
    "sg:address":"149 Evergreen Pl",
    "sg:city":"Teaneck",
    "sg:classifiers":[
        {
            "category":"Organizations",
            "subcategory":"Religious Organization",
            "type":"Services"
        }
    ],
    "sg:phone":"+1   ",
    "sg:postcode":"07666",
    "sg:province":"NJ",
    "wof:name":"James P Coleman",
    "wof:placetype":"venue"
},
  "geometry": {"coordinates":[-74.005895,40.898183],"type":"Point"}
}