{
  "type": "Feature",
  "properties": {
    "addr:full":"97 S Bridge St Somerville NJ 08876",
    "addr:housenumber":"97",
    "addr:postcode":"08876",
    "addr:street":"S Bridge St",
    "iso:country":"US",
    "sg:address":"97 S Bridge St",
    "sg:city":"Somerville",
    "sg:classifiers":[
        {
            "category":"Food & Beverages",
            "subcategory":"Groceries & Convenience Stores",
            "type":"Retail Goods"
        }
    ],
    "sg:phone":"+1   ",
    "sg:postcode":"08876",
    "sg:province":"NJ",
    "sg:tags":[
        "video",
        "rental"
    ],
    "wof:name":"Spanish American Grocery Inc",
    "wof:placetype":"venue"
},
  "geometry": {"coordinates":[-74.612641,40.564934],"type":"Point"}
}