{
  "type": "Feature",
  "properties": {
    "iso:country":"US",
    "sg:address":"1006 Arnold Ave",
    "sg:city":"Point Pleasant",
    "sg:classifiers":[
        {
            "category":"Professional",
            "subcategory":"Management & Consulting",
            "type":"Services"
        }
    ],
    "sg:phone":"+1 732 295 8092",
    "sg:postcode":"08742",
    "sg:province":"NJ",
    "sg:tags":[
        "marketing",
        "program"
    ],
    "wof:name":"Gfa Marketing Group",
    "wof:placetype":"venue"
},
  "geometry": {"coordinates":[-74.06191099999999,40.08649],"type":"Point"}
}