{
  "type": "Feature",
  "properties": {
    "addr:full":"6 Deer Ct Chester NJ 07930",
    "addr:housenumber":"6",
    "addr:postcode":"07930",
    "addr:street":"Deer Ct",
    "iso:country":"US",
    "sg:address":"6 Deer Ct",
    "sg:city":"Chester",
    "sg:classifiers":[
        {
            "category":"Wholesale",
            "subcategory":"Non-durable Goods",
            "type":"Manufacturing & Wholesale Goods"
        }
    ],
    "sg:phone":"+1 908 470 9300",
    "sg:postcode":"07930",
    "sg:province":"NJ",
    "sg:tags":[
        "advertising"
    ],
    "wof:name":"Promotions Unlimted",
    "wof:placetype":"venue"
},
  "geometry": {"coordinates":[-74.63367700000001,40.811642],"type":"Point"}
}