{
  "type": "Feature",
  "properties": {
    "iso:country":"US",
    "sg:address":"814 Whitaker Ave",
    "sg:city":"Millville",
    "sg:classifiers":[
        {
            "category":"Professional",
            "type":"Services"
        }
    ],
    "sg:phone":"+1 856 825 5028",
    "sg:postcode":"08332",
    "sg:province":"NJ",
    "sg:tags":[
        "arts",
        "artist"
    ],
    "wof:name":"Pat WITT Barn Studio",
    "wof:placetype":"venue"
},
  "geometry": {"coordinates":[-75.02240999999999,39.416627],"type":"Point"}
}