{
  "type": "Feature",
  "properties": {
    "addr:full":"340 US Hwy 9 Englishtown NJ 07726",
    "addr:housenumber":"340",
    "addr:postcode":"07726",
    "addr:street":"Us Hwy 9",
    "iso:country":"US",
    "sg:address":"340 US Hwy 9",
    "sg:city":"Englishtown",
    "sg:classifiers":[
        {
            "category":"Personal",
            "subcategory":"Beauty Salon",
            "type":"Services"
        }
    ],
    "sg:phone":"+1 732 536 5110",
    "sg:postcode":"07726",
    "sg:province":"NJ",
    "wof:name":"Maxim Hair Designers",
    "wof:placetype":"venue"
},
  "geometry": {"coordinates":[-74.303999,40.311843],"type":"Point"}
}