{
  "type": "Feature",
  "properties": {
    "addr:full":"123 Franklin Ave Saddle Brook NJ 07663",
    "addr:housenumber":"123",
    "addr:postcode":"07663",
    "addr:street":"Franklin Ave",
    "iso:country":"US",
    "sg:address":"123 Franklin Ave",
    "sg:city":"Saddle Brook",
    "sg:classifiers":[
        {
            "category":"Building & Trades",
            "subcategory":"Landscaping Services",
            "type":"Services"
        }
    ],
    "sg:phone":"+1 201 843 3744",
    "sg:postcode":"07663",
    "sg:province":"NJ",
    "wof:name":"Fine Design Landscaping",
    "wof:placetype":"venue"
},
  "geometry": {"coordinates":[-74.087204,40.89711],"type":"Point"}
}