{
  "type": "Feature",
  "properties": {
    "iso:country":"US",
    "sg:address":"61 Pemberton Ave",
    "sg:city":"Oceanport",
    "sg:classifiers":[
        {
            "category":"Professional",
            "subcategory":"Business Services",
            "type":"Services"
        }
    ],
    "sg:phone":"+1   ",
    "sg:postcode":"07757",
    "sg:province":"NJ",
    "wof:name":"Consolidated Business Support",
    "wof:placetype":"venue"
},
  "geometry": {"coordinates":[-74.03185499999999,40.310871],"type":"Point"}
}