{
  "type": "Feature",
  "properties": {
    "addr:full":"125 Broad St Red Bank NJ 07701",
    "addr:housenumber":"125",
    "addr:postcode":"07701",
    "addr:street":"Broad St",
    "iso:country":"US",
    "sg:address":"125 Broad St",
    "sg:city":"Red Bank",
    "sg:classifiers":[
        {
            "category":"Shopping",
            "subcategory":"Luggage & Leather Goods",
            "type":"Retail Goods"
        }
    ],
    "sg:phone":"+1   ",
    "sg:postcode":"07701",
    "sg:province":"NJ",
    "wof:name":"Surray Luggage of Inc",
    "wof:placetype":"venue"
},
  "geometry": {"coordinates":[-74.06528,40.349312],"type":"Point"}
}