{
  "type": "Feature",
  "properties": {
    "iso:country":"US",
    "sg:address":"830 Derry Dr",
    "sg:city":"Toms River",
    "sg:classifiers":[
        {
            "category":"Building & Trades",
            "subcategory":"Electrical",
            "type":"Services"
        }
    ],
    "sg:phone":"+1 732 288 1482",
    "sg:postcode":"08753",
    "sg:province":"NJ",
    "sg:tags":[
        "electronic",
        "install"
    ],
    "wof:name":"Cross Pacific Electronics",
    "wof:placetype":"venue"
},
  "geometry": {"coordinates":[-74.16197099999999,39.974157],"type":"Point"}
}