{
  "type": "Feature",
  "properties": {
    "addr:full":"3 Kearny Ave Kearny NJ 07032",
    "addr:housenumber":"3",
    "addr:postcode":"07032",
    "addr:street":"Kearny Ave",
    "iso:country":"US",
    "sg:address":"3 Kearny Ave",
    "sg:city":"Kearny",
    "sg:classifiers":[
        {
            "category":"Restaurant",
            "type":"Food & Drink"
        }
    ],
    "sg:phone":"+1 201 997 4846",
    "sg:postcode":"07032",
    "sg:province":"NJ",
    "wof:name":"Ponte Romana Restaurant",
    "wof:placetype":"venue"
},
  "geometry": {"coordinates":[-74.157472,40.752509],"type":"Point"}
}