{
  "type": "Feature",
  "properties": {
    "iso:country":"US",
    "sg:address":"4 Meadowbrook Dr",
    "sg:city":"Somerville",
    "sg:classifiers":[
        {
            "category":"Building & Trades",
            "subcategory":"Construction",
            "type":"Services"
        }
    ],
    "sg:phone":"+1 908 359 3072",
    "sg:postcode":"08844",
    "sg:province":"NJ",
    "sg:tags":[
        "floor",
        "laying",
        "contractor"
    ],
    "wof:name":"Bratek Floor Service",
    "wof:placetype":"venue"
},
  "geometry": {"coordinates":[-74.64034700000001,40.507446],"type":"Point"}
}