{
  "type": "Feature",
  "properties": {
    "iso:country":"US",
    "sg:address":"889 Springfield Ave",
    "sg:city":"Irvington",
    "sg:classifiers":[
        {
            "category":"Personal",
            "subcategory":"Beauty Salon",
            "type":"Services"
        }
    ],
    "sg:phone":"+1 973 375 3700",
    "sg:postcode":"07111",
    "sg:province":"NJ",
    "sg:tags":[
        "shop"
    ],
    "wof:name":"Zina's African Hair Braiding",
    "wof:placetype":"venue"
},
  "geometry": {"coordinates":[-74.222539,40.727752],"type":"Point"}
}