{
  "type": "Feature",
  "properties": {
    "addr:full":"19 Armour Rd Princeton NJ 08540",
    "addr:housenumber":"19",
    "addr:postcode":"08540",
    "addr:street":"Armour Rd",
    "iso:country":"US",
    "sg:address":"19 Armour Rd",
    "sg:city":"Princeton",
    "sg:classifiers":[
        {
            "category":"Professional",
            "subcategory":"Management & Consulting",
            "type":"Services"
        }
    ],
    "sg:phone":"+1 609 683 1770",
    "sg:postcode":"08540",
    "sg:province":"NJ",
    "sg:tags":[
        "consultant",
        "educational"
    ],
    "sg:website":"www.educationresourcesgroup.org",
    "wof:name":"Education Resources Group Inc",
    "wof:placetype":"venue"
},
  "geometry": {"coordinates":[-74.67256999999999,40.344378],"type":"Point"}
}