{
  "type": "Feature",
  "properties": {
    "addr:full":"14 Gibson Ter Bridgewater NJ 08807",
    "addr:housenumber":"14",
    "addr:postcode":"08807",
    "addr:street":"Gibson Ter",
    "iso:country":"US",
    "sg:address":"14 Gibson Ter",
    "sg:city":"Bridgewater",
    "sg:classifiers":[
        {
            "category":"Building & Trades",
            "subcategory":"Construction",
            "type":"Services"
        }
    ],
    "sg:phone":"+1 908 725 1621",
    "sg:postcode":"08807",
    "sg:province":"NJ",
    "wof:name":"Nishnac Associates LP",
    "wof:placetype":"venue"
},
  "geometry": {"coordinates":[-74.59715799999999,40.592815],"type":"Point"}
}