{
  "type": "Feature",
  "properties": {
    "addr:full":"322 University Blvd Glassboro NJ 08028",
    "addr:housenumber":"322",
    "addr:postcode":"08028",
    "addr:street":"University Blvd",
    "iso:country":"US",
    "sg:address":"322 University Blvd",
    "sg:city":"Glassboro",
    "sg:classifiers":[
        {
            "category":"Building & Trades",
            "subcategory":"Construction",
            "type":"Services"
        }
    ],
    "sg:phone":"+1 856 863 0938",
    "sg:postcode":"08028",
    "sg:province":"NJ",
    "sg:tags":[
        "industrial",
        "commercial",
        "general",
        "concrete",
        "contractor",
        "carpentry"
    ],
    "wof:name":"Jessco Construction Inc",
    "wof:placetype":"venue"
},
  "geometry": {"coordinates":[-75.12926400000001,39.707278],"type":"Point"}
}