{
  "type": "Feature",
  "properties": {
    "iso:country":"US",
    "sg:address":"2428 State Rte 38",
    "sg:city":"Cherry Hill",
    "sg:classifiers":[
        {
            "category":"Communications",
            "subcategory":"Film & Video Production",
            "type":"Services"
        }
    ],
    "sg:phone":"+1 856 482 9090",
    "sg:postcode":"08002",
    "sg:province":"NJ",
    "sg:tags":[
        "motion",
        "taping"
    ],
    "wof:name":"Shooters Post & Transfer",
    "wof:placetype":"venue"
},
  "geometry": {"coordinates":[-75.016257,39.939733],"type":"Point"}
}