{
  "type": "Feature",
  "properties": {
    "iso:country":"US",
    "sg:address":"132 S Orange Ave",
    "sg:city":"South Orange",
    "sg:classifiers":[
        {
            "category":"Food & Beverages",
            "subcategory":"Groceries & Convenience Stores",
            "type":"Retail Goods"
        }
    ],
    "sg:phone":"+1   ",
    "sg:postcode":"07079",
    "sg:province":"NJ",
    "wof:name":"A & W Convenience Store",
    "wof:placetype":"venue"
},
  "geometry": {"coordinates":[-74.256106,40.745341],"type":"Point"}
}