{
  "type": "Feature",
  "properties": {
    "iso:country":"US",
    "sg:address":"120 Hoboken Rd",
    "sg:city":"East Rutherford",
    "sg:classifiers":[
        {
            "category":"Organizations",
            "subcategory":"Religious Organization",
            "type":"Services"
        }
    ],
    "sg:phone":"+1 201 939 0457",
    "sg:postcode":"07073",
    "sg:province":"NJ",
    "sg:tags":[
        "church"
    ],
    "wof:name":"St Joseph's",
    "wof:placetype":"venue"
},
  "geometry": {"coordinates":[-74.092322,40.835498],"type":"Point"}
}