{
  "type": "Feature",
  "properties": {
    "iso:country":"US",
    "sg:address":"213 Broad St",
    "sg:city":"Keyport",
    "sg:classifiers":[
        {
            "category":"Utilities",
            "subcategory":"Fuel Oil & Lpg",
            "type":"Services"
        }
    ],
    "sg:phone":"+1   ",
    "sg:postcode":"07735",
    "sg:province":"NJ",
    "sg:tags":[
        "dealer"
    ],
    "wof:name":"STULTZ FUEL",
    "wof:placetype":"venue"
},
  "geometry": {"coordinates":[-74.19945300000001,40.432676],"type":"Point"}
}