{
  "type": "Feature",
  "properties": {
    "iso:country":"US",
    "sg:address":"444 Summer St",
    "sg:city":"Paterson",
    "sg:classifiers":[
        {
            "category":"Retail",
            "subcategory":"Auto Repair",
            "type":"Services"
        }
    ],
    "sg:phone":"+1 973 754 1124",
    "sg:postcode":"07501",
    "sg:province":"NJ",
    "sg:tags":[
        "repairing",
        "automobile"
    ],
    "wof:name":"Chief Car & Truck Repair",
    "wof:placetype":"venue"
},
  "geometry": {"coordinates":[-74.163696,40.9123],"type":"Point"}
}