{
  "type": "Feature",
  "properties": {
    "iso:country":"US",
    "sg:address":"2607 White Horse Hamilton Rd",
    "sg:city":"Trenton",
    "sg:classifiers":[
        {
            "category":"Shopping",
            "subcategory":"Clothing, Apparel, & Fashions",
            "type":"Retail Goods"
        }
    ],
    "sg:phone":"+1 609 588 4976",
    "sg:postcode":"08690",
    "sg:province":"NJ",
    "sg:tags":[
        "shop",
        "bridal"
    ],
    "wof:name":"Bridal Suite",
    "wof:placetype":"venue"
},
  "geometry": {"coordinates":[-74.663083,40.228968],"type":"Point"}
}