{
  "type": "Feature",
  "properties": {
    "addr:full":"444 Boulevard Elmwood Park NJ 07407",
    "addr:housenumber":"444",
    "addr:postcode":"07407",
    "addr:street":"Boulevard",
    "iso:country":"US",
    "sg:address":"444 Boulevard",
    "sg:city":"Elmwood Park",
    "sg:classifiers":[
        {
            "category":"Banks & Credit Unions",
            "subcategory":"Bank",
            "type":"Services"
        },
        {
            "category":"Banks & Credit Unions",
            "subcategory":"Financial Services",
            "type":"Services"
        }
    ],
    "sg:phone":"+1 201 703 2265",
    "sg:postcode":"07407",
    "sg:province":"NJ",
    "sg:tags":[
        "broker",
        "mortgage"
    ],
    "wof:name":"Interchange Bank",
    "wof:placetype":"venue"
},
  "geometry": {"coordinates":[-74.11777600000001,40.903131],"type":"Point"}
}