{
  "type": "Feature",
  "properties": {
    "addr:full":"12 State Rte 17 Paramus NJ 07652",
    "addr:housenumber":"12",
    "addr:postcode":"07652",
    "addr:street":"State Rte 17",
    "iso:country":"US",
    "sg:address":"12 State Rte 17",
    "sg:city":"Paramus",
    "sg:classifiers":[
        {
            "category":"Personal",
            "type":"Services"
        }
    ],
    "sg:phone":"+1   ",
    "sg:postcode":"07652",
    "sg:province":"NJ",
    "wof:name":"Ghazal Z Campbell Msw Lcsw",
    "wof:placetype":"venue"
},
  "geometry": {"coordinates":[-74.07250999999999,40.916049],"type":"Point"}
}