{
  "type": "Feature",
  "properties": {
    "iso:country":"US",
    "sg:address":"301 Neptune Ave",
    "sg:city":"Bayville",
    "sg:classifiers":[
        {
            "category":"Building & Trades",
            "subcategory":"Electrical",
            "type":"Services"
        }
    ],
    "sg:phone":"+1 732 921 0441",
    "sg:postcode":"08721",
    "sg:province":"NJ",
    "sg:tags":[
        "electric",
        "contractor"
    ],
    "wof:name":"Ace Electric",
    "wof:placetype":"venue"
},
  "geometry": {"coordinates":[-74.152731,39.925139],"type":"Point"}
}