{
  "type": "Feature",
  "properties": {
    "addr:full":"436 US Hwy 206 Branchville NJ 07826",
    "addr:housenumber":"436",
    "addr:postcode":"07826",
    "addr:street":"Us Hwy 206",
    "iso:country":"US",
    "sg:address":"436 US Hwy 206",
    "sg:city":"Branchville",
    "sg:classifiers":[
        {
            "category":"Bars & Pubs",
            "type":"Food & Drink"
        }
    ],
    "sg:phone":"+1 973 948 3334",
    "sg:postcode":"07826",
    "sg:province":"NJ",
    "wof:name":"Lakeside Tavern",
    "wof:placetype":"venue"
},
  "geometry": {"coordinates":[-74.788404,41.163304],"type":"Point"}
}