{
  "type": "Feature",
  "properties": {
    "iso:country":"US",
    "sg:address":"700 Jefferson Ave",
    "sg:city":"Cliffside Park",
    "sg:classifiers":[
        {
            "category":"Building & Trades",
            "subcategory":"Electrical",
            "type":"Services"
        }
    ],
    "sg:phone":"+1 201 943 8079",
    "sg:postcode":"07010",
    "sg:province":"NJ",
    "sg:tags":[
        "electrician"
    ],
    "wof:name":"Mancini Electric Inc",
    "wof:placetype":"venue"
},
  "geometry": {"coordinates":[-73.989998,40.8298],"type":"Point"}
}