{
  "type": "Feature",
  "properties": {
    "iso:country":"US",
    "sg:address":"323 S Main St",
    "sg:city":"Barnegat",
    "sg:classifiers":[
        {
            "category":"Real Estate",
            "subcategory":"Real Estate Agent",
            "type":"Services"
        }
    ],
    "sg:phone":"+1 609 698 0122",
    "sg:postcode":"08005",
    "sg:province":"NJ",
    "sg:tags":[
        "appraiser"
    ],
    "sg:website":"www.beaconappraisal.com",
    "wof:name":"Beacon Appraisal Svc",
    "wof:placetype":"venue"
},
  "geometry": {"coordinates":[-74.224495,39.750666],"type":"Point"}
}