{
  "type": "Feature",
  "properties": {
    "iso:country":"US",
    "sg:address":"480 Bara St",
    "sg:city":"Brick",
    "sg:classifiers":[
        {
            "category":"Retail",
            "subcategory":"Laundry & Dry Cleaning",
            "type":"Services"
        }
    ],
    "sg:phone":"+1 732 288 0100",
    "sg:postcode":"08723",
    "sg:province":"NJ",
    "sg:tags":[
        "cleaners",
        "rug",
        "carpet"
    ],
    "wof:name":"ENR Cleaning",
    "wof:placetype":"venue"
},
  "geometry": {"coordinates":[-74.09785599999999,40.042831],"type":"Point"}
}