{
  "type": "Feature",
  "properties": {
    "iso:country":"US",
    "sg:address":"813 Central Ave",
    "sg:city":"Union City",
    "sg:classifiers":[
        {
            "category":"Building & Trades",
            "subcategory":"Construction",
            "type":"Services"
        }
    ],
    "sg:phone":"+1 201 865 1110",
    "sg:postcode":"07087",
    "sg:province":"NJ",
    "sg:tags":[
        "contractor"
    ],
    "wof:name":"Consec Builders Inc",
    "wof:placetype":"venue"
},
  "geometry": {"coordinates":[-74.041595,40.758697],"type":"Point"}
}