{
  "type": "Feature",
  "properties": {
    "iso:country":"US",
    "sg:address":"475 State Rte 70",
    "sg:city":"Lakewood",
    "sg:classifiers":[
        {
            "category":"Health Services",
            "subcategory":"Doctor",
            "type":"Services"
        }
    ],
    "sg:phone":"+1 732 905 7706",
    "sg:postcode":"08701",
    "sg:province":"NJ",
    "sg:tags":[
        "dentist"
    ],
    "wof:name":"Venditto Dental Assoc",
    "wof:placetype":"venue"
},
  "geometry": {"coordinates":[-74.202282,40.049533],"type":"Point"}
}