{
  "type": "Feature",
  "properties": {
    "addr:full":"10 State Rte 35 Red Bank NJ 07701",
    "addr:housenumber":"10",
    "addr:postcode":"07701",
    "addr:street":"State Rte 35",
    "iso:country":"US",
    "sg:address":"10 State Rte 35",
    "sg:city":"Red Bank",
    "sg:classifiers":[
        {
            "category":"Building & Trades",
            "subcategory":"Construction",
            "type":"Services"
        }
    ],
    "sg:phone":"+1 732 888 1055",
    "sg:postcode":"07701",
    "sg:province":"NJ",
    "sg:tags":[
        "residential",
        "contractor"
    ],
    "wof:name":"Matzel & Mumford Organization",
    "wof:placetype":"venue"
},
  "geometry": {"coordinates":[-74.075507,40.35162],"type":"Point"}
}