{
  "type": "Feature",
  "properties": {
    "addr:full":"845 N New Rd Pleasantville NJ 08232",
    "addr:housenumber":"845",
    "addr:postcode":"08232",
    "addr:street":"N New Rd",
    "iso:country":"US",
    "sg:address":"845 N New Rd",
    "sg:city":"Pleasantville",
    "sg:classifiers":[
        {
            "category":"Personal",
            "subcategory":"Beauty Salon",
            "type":"Services"
        }
    ],
    "sg:phone":"+1 609 272 0222",
    "sg:postcode":"08232",
    "sg:province":"NJ",
    "sg:tags":[
        "shop"
    ],
    "wof:name":"Mae Ja Hair Studio",
    "wof:placetype":"venue"
},
  "geometry": {"coordinates":[-74.520253,39.407865],"type":"Point"}
}