{
  "type": "Feature",
  "properties": {
    "iso:country":"US",
    "sg:address":"1503 Saint Georges Ave Ste 201",
    "sg:city":"Colonia",
    "sg:classifiers":[
        {
            "category":"Health Services",
            "subcategory":"Doctor",
            "type":"Services"
        }
    ],
    "sg:phone":"+1 732 382 5534",
    "sg:postcode":"07067",
    "sg:province":"NJ",
    "wof:name":"Joseph Serena M MD",
    "wof:placetype":"venue"
},
  "geometry": {"coordinates":[-74.29103600000001,40.588767],"type":"Point"}
}