{
  "type": "Feature",
  "properties": {
    "iso:country":"US",
    "sg:address":"25 E Willow St",
    "sg:city":"Millburn",
    "sg:classifiers":[
        {
            "category":"Health Services",
            "subcategory":"Doctor",
            "type":"Services"
        }
    ],
    "sg:phone":"+1 973 921 9222",
    "sg:postcode":"07041",
    "sg:province":"NJ",
    "sg:tags":[
        "orthopedist"
    ],
    "wof:name":"Orthopaedic & Spine Center of New Jersey",
    "wof:placetype":"venue"
},
  "geometry": {"coordinates":[-74.305702,40.717098],"type":"Point"}
}