{
  "type": "Feature",
  "properties": {
    "addr:full":"106 Frederick St Hackensack NJ 07601",
    "addr:housenumber":"106",
    "addr:postcode":"07601",
    "addr:street":"Frederick St",
    "iso:country":"US",
    "sg:address":"106 Frederick St",
    "sg:city":"Hackensack",
    "sg:classifiers":[
        {
            "category":"Retail",
            "subcategory":"Repair Shop",
            "type":"Services"
        }
    ],
    "sg:phone":"+1 201 487 1115",
    "sg:postcode":"07601",
    "sg:province":"NJ",
    "sg:tags":[
        "refinishing",
        "furniture"
    ],
    "wof:name":"Dip N Strip Inc",
    "wof:placetype":"venue"
},
  "geometry": {"coordinates":[-74.04607799999999,40.870829],"type":"Point"}
}