{
  "type": "Feature",
  "properties": {
    "addr:full":"400 S Main St Wharton NJ 07885",
    "addr:housenumber":"400",
    "addr:postcode":"07885",
    "addr:street":"S Main St",
    "iso:country":"US",
    "sg:address":"400 S Main St",
    "sg:city":"Wharton",
    "sg:classifiers":[
        {
            "category":"Health Services",
            "subcategory":"Medical Lab",
            "type":"Services"
        }
    ],
    "sg:phone":"+1 973 366 4213",
    "sg:postcode":"07885",
    "sg:province":"NJ",
    "sg:tags":[
        "laboratory"
    ],
    "wof:name":"Laboratory Corp Of America",
    "wof:placetype":"venue"
},
  "geometry": {"coordinates":[-74.57943,40.887997],"type":"Point"}
}