{
  "type": "Feature",
  "properties": {
    "iso:country":"US",
    "sg:address":"28 W 3rd St",
    "sg:city":"South Orange",
    "sg:classifiers":[
        {
            "category":"Professional",
            "subcategory":"Business Services",
            "type":"Services"
        }
    ],
    "sg:phone":"+1   ",
    "sg:postcode":"07079",
    "sg:province":"NJ",
    "wof:name":"Chatterbox Group LLC",
    "wof:placetype":"venue"
},
  "geometry": {"coordinates":[-74.263474,40.744902],"type":"Point"}
}