{
  "type": "Feature",
  "properties": {
    "iso:country":"US",
    "sg:address":"201 Oak St",
    "sg:city":"South Amboy",
    "sg:classifiers":[
        {
            "category":"Professional",
            "subcategory":"Computer Services",
            "type":"Services"
        }
    ],
    "sg:phone":"+1 732 721 1031",
    "sg:postcode":"08879",
    "sg:province":"NJ",
    "sg:tags":[
        "design",
        "system"
    ],
    "wof:name":"Frontier Intgrtn Sys Inc",
    "wof:placetype":"venue"
},
  "geometry": {"coordinates":[-74.29894,40.486408],"type":"Point"}
}