{
  "type": "Feature",
  "properties": {
    "iso:country":"US",
    "sg:address":"6 Clementon Rd E",
    "sg:city":"Gibbsboro",
    "sg:classifiers":[
        {
            "category":"Professional",
            "type":"Services"
        },
        {
            "category":"Banks & Credit Unions",
            "subcategory":"Bank",
            "type":"Services"
        }
    ],
    "sg:phone":"+1 856 435 6266",
    "sg:postcode":"08026",
    "sg:province":"NJ",
    "sg:tags":[
        "loan",
        "real estate"
    ],
    "wof:name":"Madison Equity Corp",
    "wof:placetype":"venue"
},
  "geometry": {"coordinates":[-74.96484,39.837964],"type":"Point"}
}