{
  "type": "Feature",
  "properties": {
    "iso:country":"US",
    "sg:address":"167 Hancock Ave",
    "sg:city":"Jersey City",
    "sg:classifiers":[
        {
            "category":"Professional",
            "subcategory":"Management & Consulting",
            "type":"Services"
        }
    ],
    "sg:phone":"+1 201 963 5069",
    "sg:postcode":"07307",
    "sg:province":"NJ",
    "wof:name":"Construction Tri Con",
    "wof:placetype":"venue"
},
  "geometry": {"coordinates":[-74.04611800000001,40.747248],"type":"Point"}
}