{
  "type": "Feature",
  "properties": {
    "addr:full":"20 Union Ave Lakehurst NJ 08733",
    "addr:housenumber":"20",
    "addr:postcode":"08733",
    "addr:street":"Union Ave",
    "iso:country":"US",
    "sg:address":"20 Union Ave",
    "sg:city":"Lakehurst",
    "sg:classifiers":[
        {
            "category":"Organizations",
            "subcategory":"Community Association",
            "type":"Services"
        }
    ],
    "sg:phone":"+1 732 657 6609",
    "sg:postcode":"08733",
    "sg:province":"NJ",
    "sg:tags":[
        "military"
    ],
    "sg:website":"www.vfw.org",
    "wof:name":"Veterans Of Foreign Wars",
    "wof:placetype":"venue"
},
  "geometry": {"coordinates":[-74.312077,40.012164],"type":"Point"}
}