{
  "type": "Feature",
  "properties": {
    "iso:country":"US",
    "sg:address":"192 US Hwy 22",
    "sg:city":"Green Brook",
    "sg:classifiers":[
        {
            "category":"Building & Trades",
            "subcategory":"Construction",
            "type":"Services"
        }
    ],
    "sg:phone":"+1 732 752 2600",
    "sg:postcode":"08812",
    "sg:province":"NJ",
    "sg:tags":[
        "general",
        "contractor"
    ],
    "sg:website":"www.homeimprovementnj.com",
    "wof:name":"Home Improvement Ctr",
    "wof:placetype":"venue"
},
  "geometry": {"coordinates":[-74.48048199999999,40.601289],"type":"Point"}
}