{
  "type": "Feature",
  "properties": {
    "iso:country":"US",
    "sg:address":"19 Brainard Ave",
    "sg:city":"Port Monmouth",
    "sg:classifiers":[
        {
            "category":"Building & Trades",
            "subcategory":"Construction",
            "type":"Services"
        }
    ],
    "sg:phone":"+1 732 787 8920",
    "sg:postcode":"07758",
    "sg:province":"NJ",
    "sg:tags":[
        "contractor"
    ],
    "wof:name":"Elite Fence Co",
    "wof:placetype":"venue"
},
  "geometry": {"coordinates":[-74.09182,40.437708],"type":"Point"}
}