{
  "type": "Feature",
  "properties": {
    "iso:country":"US",
    "sg:address":"18 E Main St",
    "sg:city":"Ramsey",
    "sg:classifiers":[
        {
            "category":"Restaurant",
            "type":"Food & Drink"
        }
    ],
    "sg:phone":"+1   ",
    "sg:postcode":"07446",
    "sg:province":"NJ",
    "sg:tags":[
        "eating"
    ],
    "wof:name":"Papa Lorenzos Ristorante Cafe",
    "wof:placetype":"venue"
},
  "geometry": {"coordinates":[-74.141858,41.057235],"type":"Point"}
}