{
  "type": "Feature",
  "properties": {
    "iso:country":"US",
    "sg:address":"601 E Edgar Rd",
    "sg:city":"Linden",
    "sg:classifiers":[
        {
            "category":"Shopping",
            "type":"Retail Goods"
        }
    ],
    "sg:phone":"+1   ",
    "sg:postcode":"07036",
    "sg:province":"NJ",
    "sg:tags":[
        "security",
        "system"
    ],
    "wof:name":"Wired For Sound & Security",
    "wof:placetype":"venue"
},
  "geometry": {"coordinates":[-74.23701800000001,40.632994],"type":"Point"}
}