{
  "type": "Feature",
  "properties": {
    "iso:country":"US",
    "sg:address":"4 Orono St",
    "sg:city":"Clifton",
    "sg:classifiers":[
        {
            "category":"Manufacturing",
            "subcategory":"Tools & Machinery",
            "type":"Manufacturing & Wholesale Goods"
        }
    ],
    "sg:phone":"+1 973 779 3900",
    "sg:postcode":"07013",
    "sg:province":"NJ",
    "sg:tags":[
        "industry",
        "special"
    ],
    "wof:name":"Century Engineering Co",
    "wof:placetype":"venue"
},
  "geometry": {"coordinates":[-74.15167599999999,40.864898],"type":"Point"}
}