{
  "type": "Feature",
  "properties": {
    "addr:full":"30 E Long Branch Ave Ocean Gate NJ 08740",
    "addr:housenumber":"30",
    "addr:postcode":"08740",
    "addr:street":"E Long Branch Ave;Gate",
    "iso:country":"US",
    "sg:address":"30 E Long Branch Ave",
    "sg:city":"Ocean Gate",
    "sg:classifiers":[
        {
            "category":"Retail",
            "subcategory":"Auto Repair",
            "type":"Services"
        }
    ],
    "sg:phone":"+1 732 269 3675",
    "sg:postcode":"08740",
    "sg:province":"NJ",
    "sg:tags":[
        "repairing",
        "automobile"
    ],
    "wof:name":"P J's Automotive Svc",
    "wof:placetype":"venue"
},
  "geometry": {"coordinates":[-74.139325,39.926024],"type":"Point"}
}