{
  "type": "Feature",
  "properties": {
    "addr:full":"264 Hurffville Grenloch Rd Sewell NJ 08080",
    "addr:housenumber":"264",
    "addr:postcode":"08080",
    "addr:street":"Hurffville Grenloch Rd",
    "iso:country":"US",
    "sg:address":"264 Hurffville Grenloch Rd",
    "sg:city":"Sewell",
    "sg:classifiers":[
        {
            "category":"Wholesale",
            "subcategory":"Durable Goods & Equipment",
            "type":"Manufacturing & Wholesale Goods"
        }
    ],
    "sg:phone":"+1 856 582 1405",
    "sg:postcode":"08080",
    "sg:province":"NJ",
    "wof:name":"Jaymar Products",
    "wof:placetype":"venue"
},
  "geometry": {"coordinates":[-75.08973,39.762639],"type":"Point"}
}