{
  "type": "Feature",
  "properties": {
    "iso:country":"US",
    "sg:address":"216 Delaware Ave",
    "sg:city":"Palmyra",
    "sg:classifiers":[
        {
            "category":"Building & Trades",
            "subcategory":"Construction",
            "type":"Services"
        }
    ],
    "sg:phone":"+1 856 829 1086",
    "sg:postcode":"08065",
    "sg:province":"NJ",
    "sg:tags":[
        "concrete",
        "cutting",
        "breaking",
        "sawing"
    ],
    "wof:name":"Quick Core Co",
    "wof:placetype":"venue"
},
  "geometry": {"coordinates":[-75.02709,40.003655],"type":"Point"}
}