{
  "type": "Feature",
  "properties": {
    "addr:full":"1547 Stuyvesant Ave Union NJ 07083",
    "addr:housenumber":"1547",
    "addr:postcode":"07083",
    "addr:street":"Stuyvesant Ave",
    "iso:country":"US",
    "sg:address":"1547 Stuyvesant Ave",
    "sg:city":"Union",
    "sg:classifiers":[
        {
            "category":"Health Services",
            "subcategory":"Doctor",
            "type":"Services"
        }
    ],
    "sg:phone":"+1 908 687 7101",
    "sg:postcode":"07083",
    "sg:province":"NJ",
    "sg:tags":[
        "physician",
        "surgeon"
    ],
    "wof:name":"P G Lalla MD",
    "wof:placetype":"venue"
},
  "geometry": {"coordinates":[-74.25990400000001,40.708469],"type":"Point"}
}