{
  "type": "Feature",
  "properties": {
    "addr:full":"1000 Cooper St Woodbury NJ 08096",
    "addr:housenumber":"1000",
    "addr:postcode":"08096",
    "addr:street":"Cooper St",
    "iso:country":"US",
    "sg:address":"1000 Cooper St",
    "sg:city":"Woodbury",
    "sg:classifiers":[
        {
            "category":"Fast Food",
            "type":"Food & Drink"
        },
        {
            "category":"Personal",
            "type":"Services"
        },
        {
            "category":"Restaurant",
            "type":"Food & Drink"
        },
        {
            "category":"Professional",
            "type":"Services"
        }
    ],
    "sg:phone":"+1 856 251 1115",
    "sg:postcode":"08096",
    "sg:province":"NJ",
    "sg:tags":[
        "delivery",
        "take",
        "pizza"
    ],
    "sg:website":"http://www.papajohns.com",
    "wof:name":"Papa John's Pizza",
    "wof:placetype":"venue"
},
  "geometry": {"coordinates":[-75.124863,39.828522],"type":"Point"}
}