{
  "type": "Feature",
  "properties": {
    "iso:country":"US",
    "sg:address":"110 US Hwy 206",
    "sg:city":"Hammonton",
    "sg:classifiers":[
        {
            "category":"Organizations",
            "subcategory":"Labor Organization",
            "type":"Services"
        }
    ],
    "sg:phone":"+1 609 561 9588",
    "sg:postcode":"08037",
    "sg:province":"NJ",
    "wof:name":"United Workers Labor Union",
    "wof:placetype":"venue"
},
  "geometry": {"coordinates":[-74.787452,39.649184],"type":"Point"}
}