{
  "type": "Feature",
  "properties": {
    "addr:full":"1011 Bloomfield Ave # 1B West Caldwell NJ 07006",
    "addr:housenumber":"1011;1b",
    "addr:postcode":"07006",
    "addr:street":"Bloomfield Ave #",
    "iso:country":"US",
    "sg:address":"1011 Bloomfield Ave # 1B",
    "sg:city":"West Caldwell",
    "sg:classifiers":[
        {
            "category":"Banks & Credit Unions",
            "subcategory":"Atm",
            "type":"Services"
        }
    ],
    "sg:phone":"+1 973 227 5544",
    "sg:postcode":"07006",
    "sg:province":"NJ",
    "sg:tags":[
        "bankruptcy"
    ],
    "wof:name":"Wronko Terence J Lawyer",
    "wof:placetype":"venue"
},
  "geometry": {"coordinates":[-74.304199,40.853199],"type":"Point"}
}