{
  "type": "Feature",
  "properties": {
    "addr:full":"159 State Rt 23 Sussex NJ 07461",
    "addr:housenumber":"159",
    "addr:postcode":"07461",
    "addr:street":"State Rt 23",
    "iso:country":"US",
    "sg:address":"159 State Rt 23",
    "sg:city":"Sussex",
    "sg:classifiers":[
        {
            "category":"Autos & Motor Vehicles",
            "subcategory":"Auto Supplies",
            "type":"Retail Goods"
        },
        {
            "category":"Sports & Exercise",
            "subcategory":"Race Track",
            "type":"Entertainment"
        }
    ],
    "sg:phone":"+1 973 702 0819",
    "sg:postcode":"07461",
    "sg:province":"NJ",
    "sg:tags":[
        "performance",
        "automobile",
        "racing",
        "car",
        "equipment"
    ],
    "wof:name":"B H Racing Enterprises",
    "wof:placetype":"venue"
},
  "geometry": {"coordinates":[-74.589973,41.178909],"type":"Point"}
}