{
  "type": "Feature",
  "properties": {
    "addr:full":"503 Delsea Dr N Glassboro NJ 08028",
    "addr:housenumber":"503",
    "addr:postcode":"08028",
    "addr:street":"Delsea Dr N",
    "iso:country":"US",
    "sg:address":"503 Delsea Dr N",
    "sg:city":"Glassboro",
    "sg:classifiers":[
        {
            "category":"Sports & Exercise",
            "subcategory":"Bowling",
            "type":"Entertainment"
        }
    ],
    "sg:phone":"+1 856 881 1013",
    "sg:postcode":"08028",
    "sg:province":"NJ",
    "wof:name":"Brunswick Recreation Ctr",
    "wof:placetype":"venue"
},
  "geometry": {"coordinates":[-75.111524,39.71308],"type":"Point"}
}