{
  "type": "Feature",
  "properties": {
    "iso:country":"US",
    "sg:address":"440 N Richmond Ave",
    "sg:city":"Atlantic City",
    "sg:classifiers":[
        {
            "category":"Local Transit",
            "type":"Transportation"
        }
    ],
    "sg:phone":"+1 609 287 7244",
    "sg:postcode":"08401",
    "sg:province":"NJ",
    "sg:tags":[
        "passenger"
    ],
    "wof:name":"Holiday Limousine",
    "wof:placetype":"venue"
},
  "geometry": {"coordinates":[-74.46459,39.354094],"type":"Point"}
}