{
  "type": "Feature",
  "properties": {
    "addr:full":"678 US Hwy 206 Bridgewater NJ 08807",
    "addr:housenumber":"678",
    "addr:postcode":"08807",
    "addr:street":"Us Hwy 206",
    "iso:country":"US",
    "sg:address":"678 US Hwy 206",
    "sg:city":"Bridgewater",
    "sg:classifiers":[
        {
            "category":"Professional",
            "subcategory":"Computer Services",
            "type":"Services"
        }
    ],
    "sg:phone":"+1 908 429 4300",
    "sg:postcode":"08807",
    "sg:province":"NJ",
    "sg:tags":[
        "consultant",
        "designer"
    ],
    "wof:name":"KCI",
    "wof:placetype":"venue"
},
  "geometry": {"coordinates":[-74.623836,40.602412],"type":"Point"}
}