{
  "type": "Feature",
  "properties": {
    "addr:full":"77 Halsey St Newark NJ 07102",
    "addr:housenumber":"77",
    "addr:postcode":"07102",
    "addr:street":"Halsey St",
    "iso:country":"US",
    "sg:address":"77 Halsey St",
    "sg:city":"Newark",
    "sg:classifiers":[
        {
            "category":"Organizations",
            "subcategory":"Community Association",
            "type":"Services"
        }
    ],
    "sg:phone":"+1 973 645 5954",
    "sg:postcode":"07102",
    "sg:province":"NJ",
    "sg:tags":[
        "military"
    ],
    "wof:name":"Veterans Center",
    "wof:placetype":"venue"
},
  "geometry": {"coordinates":[-74.171711,40.739825],"type":"Point"}
}