{
  "type": "Feature",
  "properties": {
    "iso:country":"US",
    "sg:address":"686 Amwell Rd",
    "sg:city":"Hillsborough",
    "sg:classifiers":[
        {
            "category":"Building & Trades",
            "subcategory":"Landscaping Services",
            "type":"Services"
        }
    ],
    "sg:phone":"+1 908 369 5776",
    "sg:postcode":"08844",
    "sg:province":"NJ",
    "sg:tags":[
        "lawn",
        "tree"
    ],
    "wof:name":"Mc Cabe Equipment Leasing",
    "wof:placetype":"venue"
},
  "geometry": {"coordinates":[-74.709096,40.500822],"type":"Point"}
}