{
  "type": "Feature",
  "properties": {
    "addr:full":"833 1st St Ocean City NJ 08226",
    "addr:housenumber":"833",
    "addr:postcode":"08226",
    "addr:street":"1St St",
    "iso:country":"US",
    "sg:address":"833 1st St",
    "sg:city":"Ocean City",
    "sg:classifiers":[
        {
            "category":"Shopping",
            "subcategory":"Discount & Variety Stores",
            "type":"Retail Goods"
        }
    ],
    "sg:phone":"+1   ",
    "sg:postcode":"08226",
    "sg:province":"NJ",
    "wof:name":"Down Town Dollar Store",
    "wof:placetype":"venue"
},
  "geometry": {"coordinates":[-74.559889,39.283858],"type":"Point"}
}