{
  "type": "Feature",
  "properties": {
    "addr:full":"14 Ridgedale Ave Cedar Knolls NJ 07927",
    "addr:postcode":"07927",
    "addr:street":"Ridgedale Ave",
    "iso:country":"US",
    "sg:address":"14 Ridgedale Ave",
    "sg:city":"Cedar Knolls",
    "sg:classifiers":[
        {
            "category":"Professional",
            "subcategory":"Advertising",
            "type":"Services"
        }
    ],
    "sg:phone":"+1 973 539 6000",
    "sg:postcode":"07927",
    "sg:province":"NJ",
    "sg:tags":[
        "counselor"
    ],
    "wof:name":"Camares Communications",
    "wof:placetype":"venue"
},
  "geometry": {"coordinates":[-74.44508399999999,40.831748],"type":"Point"}
}