{
  "type": "Feature",
  "properties": {
    "addr:full":"8409 Ventnor Ave Margate City NJ 08402",
    "addr:housenumber":"8409",
    "addr:postcode":"08402",
    "addr:street":"Ventnor Ave Margate",
    "iso:country":"US",
    "sg:address":"8409 Ventnor Ave",
    "sg:city":"Margate City",
    "sg:classifiers":[
        {
            "category":"Restaurant",
            "type":"Food & Drink"
        }
    ],
    "sg:phone":"+1 609 822 0600",
    "sg:postcode":"08402",
    "sg:province":"NJ",
    "wof:name":"Lobianco & Coastal Cuisine",
    "wof:placetype":"venue"
},
  "geometry": {"coordinates":[-74.504124,39.327626],"type":"Point"}
}