{
  "type": "Feature",
  "properties": {
    "iso:country":"US",
    "sg:address":"103 W 1st Ave",
    "sg:city":"Pine Hill",
    "sg:classifiers":[
        {
            "category":"Building & Trades",
            "subcategory":"Plumbing",
            "type":"Services"
        }
    ],
    "sg:phone":"+1 856 566 4212",
    "sg:postcode":"08021",
    "sg:province":"NJ",
    "sg:tags":[
        "plumbing",
        "contractor"
    ],
    "wof:name":"Applause Plumbing Inc",
    "wof:placetype":"venue"
},
  "geometry": {"coordinates":[-74.993578,39.793437],"type":"Point"}
}