{
  "type": "Feature",
  "properties": {
    "addr:full":"626 2nd Ave Long Branch NJ 07740",
    "addr:housenumber":"626",
    "addr:postcode":"07740",
    "addr:street":"2Nd Ave",
    "iso:country":"US",
    "sg:address":"626 2nd Ave",
    "sg:city":"Long Branch",
    "sg:classifiers":[
        {
            "category":"Shopping",
            "subcategory":"Florist",
            "type":"Retail Goods"
        }
    ],
    "sg:phone":"+1   ",
    "sg:postcode":"07740",
    "sg:province":"NJ",
    "wof:name":"Lily Tiger Florist",
    "wof:placetype":"venue"
},
  "geometry": {"coordinates":[-73.98657799999999,40.283829],"type":"Point"}
}