{
  "type": "Feature",
  "properties": {
    "addr:full":"93 Pinegrove Ave Summit NJ 07901",
    "addr:housenumber":"93",
    "addr:postcode":"07901",
    "addr:street":"Pinegrove Ave",
    "iso:country":"US",
    "sg:address":"93 Pinegrove Ave",
    "sg:city":"Summit",
    "sg:classifiers":[
        {
            "category":"Professional",
            "subcategory":"Lawyer & Legal Services",
            "type":"Services"
        }
    ],
    "sg:phone":"+1 908 522 1121",
    "sg:postcode":"07901",
    "sg:province":"NJ",
    "wof:name":"McDonough Bauman Law Firm",
    "wof:placetype":"venue"
},
  "geometry": {"coordinates":[-74.37200199999999,40.708422],"type":"Point"}
}