{
  "type": "Feature",
  "properties": {
    "iso:country":"US",
    "sg:address":"655 Fairview Ave",
    "sg:city":"Fairview",
    "sg:classifiers":[
        {
            "category":"Retail",
            "subcategory":"Funeral Services",
            "type":"Services"
        }
    ],
    "sg:phone":"+1 201 941 1300",
    "sg:postcode":"07022",
    "sg:province":"NJ",
    "sg:tags":[
        "cemetery"
    ],
    "wof:name":"Fairview Monuments At Mt Moriah Cemetery",
    "wof:placetype":"venue"
},
  "geometry": {"coordinates":[-74.00520299999999,40.819599],"type":"Point"}
}