{
  "type": "Feature",
  "properties": {
    "iso:country":"US",
    "sg:address":"810 Stamford Dr",
    "sg:city":"Neptune",
    "sg:classifiers":[
        {
            "category":"Professional",
            "subcategory":"Computer Services",
            "type":"Services"
        }
    ],
    "sg:phone":"+1   ",
    "sg:postcode":"07753",
    "sg:province":"NJ",
    "wof:name":"Linwood S Johnson II Conslt",
    "wof:placetype":"venue"
},
  "geometry": {"coordinates":[-74.047287,40.216563],"type":"Point"}
}