{
  "type": "Feature",
  "properties": {
    "addr:full":"339 Park Ave Old Bridge NJ 08857",
    "addr:housenumber":"339",
    "addr:postcode":"08857",
    "addr:street":"Park Ave",
    "iso:country":"US",
    "sg:address":"339 Park Ave",
    "sg:city":"Old Bridge",
    "sg:classifiers":[
        {
            "category":"Building & Trades",
            "subcategory":"Construction",
            "type":"Services"
        }
    ],
    "sg:phone":"+1 732 723 3715",
    "sg:postcode":"08857",
    "sg:province":"NJ",
    "sg:tags":[
        "house"
    ],
    "wof:name":"Stat Home Repair",
    "wof:placetype":"venue"
},
  "geometry": {"coordinates":[-74.361189,40.398588],"type":"Point"}
}