{
  "type": "Feature",
  "properties": {
    "addr:full":"546 Maple Ave Elizabeth NJ 07202",
    "addr:housenumber":"546",
    "addr:postcode":"07202",
    "addr:street":"Maple Ave",
    "iso:country":"US",
    "sg:address":"546 Maple Ave",
    "sg:city":"Elizabeth",
    "sg:classifiers":[
        {
            "category":"Building & Trades",
            "subcategory":"Construction",
            "type":"Services"
        }
    ],
    "sg:phone":"+1 908 527 6642",
    "sg:postcode":"07202",
    "sg:province":"NJ",
    "sg:tags":[
        "concrete",
        "contractor"
    ],
    "wof:name":"Two Countries Contractors",
    "wof:placetype":"venue"
},
  "geometry": {"coordinates":[-74.214292,40.651403],"type":"Point"}
}