{
  "type": "Feature",
  "properties": {
    "iso:country":"US",
    "sg:address":"644 Martin Luther King Jr Blvd",
    "sg:city":"Newark",
    "sg:classifiers":[
        {
            "category":"Wholesale",
            "subcategory":"Seafood",
            "type":"Manufacturing & Wholesale Goods"
        }
    ],
    "sg:phone":"+1 973 623 3282",
    "sg:postcode":"07102",
    "sg:province":"NJ",
    "wof:name":"Woori Fish Market",
    "wof:placetype":"venue"
},
  "geometry": {"coordinates":[-74.18178899999999,40.730721],"type":"Point"}
}