{
  "type": "Feature",
  "properties": {
    "addr:full":"195 River Rd Edgewater NJ 07020",
    "addr:housenumber":"195",
    "addr:postcode":"07020",
    "addr:street":"River Rd",
    "iso:country":"US",
    "sg:address":"195 River Rd",
    "sg:city":"Edgewater",
    "sg:classifiers":[
        {
            "category":"Sports & Exercise",
            "subcategory":"Golf",
            "type":"Entertainment"
        }
    ],
    "sg:phone":"+1 201 943 2010",
    "sg:postcode":"07020",
    "sg:province":"NJ",
    "sg:tags":[
        "mini"
    ],
    "wof:name":"The Promenade",
    "wof:placetype":"venue"
},
  "geometry": {"coordinates":[-73.99185900000001,40.805386],"type":"Point"}
}