{
  "type": "Feature",
  "properties": {
    "addr:full":"131 N Main St Forked River NJ 08731",
    "addr:housenumber":"131",
    "addr:postcode":"08731",
    "addr:street":"N Main St",
    "iso:country":"US",
    "sg:address":"131 N Main St",
    "sg:city":"Forked River",
    "sg:classifiers":[
        {
            "category":"Organizations",
            "subcategory":"Religious Organization",
            "type":"Services"
        }
    ],
    "sg:phone":"+1 609 693 5624",
    "sg:postcode":"08731",
    "sg:province":"NJ",
    "sg:tags":[
        "church"
    ],
    "sg:website":"www.forkedriverpres.net",
    "wof:name":"Forked River Presbyterian Chr",
    "wof:placetype":"venue"
},
  "geometry": {"coordinates":[-74.189464,39.842149],"type":"Point"}
}