{
  "type": "Feature",
  "properties": {
    "iso:country":"US",
    "sg:address":"200 Ludlow Dr",
    "sg:city":"Trenton",
    "sg:classifiers":[
        {
            "category":"Real Estate",
            "subcategory":"Real Estate Agent",
            "type":"Services"
        }
    ],
    "sg:phone":"+1   ",
    "sg:postcode":"08638",
    "sg:province":"NJ",
    "sg:tags":[
        "manager",
        "industrial",
        "commercial",
        "developer"
    ],
    "wof:name":"Sorce Properties Inc",
    "wof:placetype":"venue"
},
  "geometry": {"coordinates":[-74.75782100000001,40.261876],"type":"Point"}
}