{
  "type": "Feature",
  "properties": {
    "addr:full":"944 Summit Ave Jersey City NJ 07307",
    "addr:housenumber":"944",
    "addr:postcode":"07307",
    "addr:street":"Summit Ave",
    "iso:country":"US",
    "sg:address":"944 Summit Ave",
    "sg:city":"Jersey City",
    "sg:classifiers":[
        {
            "category":"Building & Trades",
            "subcategory":"Locksmith",
            "type":"Services"
        }
    ],
    "sg:phone":"+1 877 898 9181",
    "sg:postcode":"07307",
    "sg:province":"NJ",
    "sg:tags":[
        "key"
    ],
    "wof:name":"Emergency 24 Hour 7 Day Locksmith",
    "wof:placetype":"venue"
},
  "geometry": {"coordinates":[-74.05206,40.746213],"type":"Point"}
}