{
  "type": "Feature",
  "properties": {
    "addr:full":"553 Monmouth Ave Belford NJ 07718",
    "addr:housenumber":"553",
    "addr:postcode":"07718",
    "addr:street":"Monmouth Ave",
    "iso:country":"US",
    "sg:address":"553 Monmouth Ave",
    "sg:city":"Belford",
    "sg:phone":"+1 732 471 8165",
    "sg:postcode":"07718",
    "sg:province":"NJ",
    "wof:name":"Global Sign Advantage",
    "wof:placetype":"venue"
},
  "geometry": {"coordinates":[-74.078227,40.413276],"type":"Point"}
}