{
  "type": "Feature",
  "properties": {
    "iso:country":"US",
    "sg:address":"59 S Main St",
    "sg:city":"Lambertville",
    "sg:classifiers":[
        {
            "category":"Professional",
            "type":"Services"
        }
    ],
    "sg:phone":"+1   ",
    "sg:postcode":"08530",
    "sg:province":"NJ",
    "wof:name":"My Italian Family LLC",
    "wof:placetype":"venue"
},
  "geometry": {"coordinates":[-74.942482,40.364401],"type":"Point"}
}