{
  "type": "Feature",
  "properties": {
    "iso:country":"US",
    "sg:address":"250 Moonachie Rd",
    "sg:city":"Moonachie",
    "sg:classifiers":[
        {
            "category":"Building & Trades",
            "subcategory":"Locksmith",
            "type":"Services"
        }
    ],
    "sg:phone":"+1 888 505 6353",
    "sg:postcode":"07074",
    "sg:province":"NJ",
    "sg:tags":[
        "key"
    ],
    "wof:name":"AAA Emergency Locksmith",
    "wof:placetype":"venue"
},
  "geometry": {"coordinates":[-74.052468,40.834889],"type":"Point"}
}