{
  "type": "Feature",
  "properties": {
    "iso:country":"US",
    "sg:address":"30 Water St",
    "sg:city":"Lebanon",
    "sg:classifiers":[
        {
            "category":"Banks & Credit Unions",
            "subcategory":"Financial Services",
            "type":"Services"
        }
    ],
    "sg:phone":"+1   ",
    "sg:postcode":"08833",
    "sg:province":"NJ",
    "sg:tags":[
        "company",
        "holding"
    ],
    "wof:name":"Mahalick Holding LLC",
    "wof:placetype":"venue"
},
  "geometry": {"coordinates":[-74.82858299999999,40.689162],"type":"Point"}
}