{
  "type": "Feature",
  "properties": {
    "addr:full":"535 High Mountain Rd Haledon NJ 07508",
    "addr:housenumber":"535",
    "addr:postcode":"07508",
    "addr:street":"High Mountain Rd",
    "iso:country":"US",
    "sg:address":"535 High Mountain Rd",
    "sg:city":"Haledon",
    "sg:classifiers":[
        {
            "category":"Personal",
            "subcategory":"Beauty Salon",
            "type":"Services"
        }
    ],
    "sg:phone":"+1 973 423 2499",
    "sg:postcode":"07508",
    "sg:province":"NJ",
    "sg:tags":[
        "shop"
    ],
    "wof:name":"Freedom Cuts Ect",
    "wof:placetype":"venue"
},
  "geometry": {"coordinates":[-74.18166100000001,40.955852],"type":"Point"}
}