{
  "type": "Feature",
  "properties": {
    "addr:full":"1025 Broadway Bayonne NJ 07002",
    "addr:housenumber":"1025",
    "addr:postcode":"07002",
    "addr:street":"Broadway",
    "iso:country":"US",
    "sg:address":"1025 Broadway",
    "sg:city":"Bayonne",
    "sg:classifiers":[
        {
            "category":"Wholesale",
            "subcategory":"Construction Materials",
            "type":"Manufacturing & Wholesale Goods"
        }
    ],
    "sg:phone":"+1 201 436 1708",
    "sg:postcode":"07002",
    "sg:province":"NJ",
    "sg:tags":[
        "gates"
    ],
    "wof:name":"Bayonne Fence Co Inc",
    "wof:placetype":"venue"
},
  "geometry": {"coordinates":[-74.101979,40.68324],"type":"Point"}
}