{
  "type": "Feature",
  "properties": {
    "addr:full":"35 Schooner Ave Barnegat NJ 08005",
    "addr:housenumber":"35",
    "addr:postcode":"08005",
    "addr:street":"Schooner Ave",
    "iso:country":"US",
    "sg:address":"35 Schooner Ave",
    "sg:city":"Barnegat",
    "sg:classifiers":[
        {
            "category":"Manufacturing",
            "subcategory":"Jewelry",
            "type":"Manufacturing & Wholesale Goods"
        }
    ],
    "sg:phone":"+1 609 698 3706",
    "sg:postcode":"08005",
    "sg:province":"NJ",
    "sg:tags":[
        "material",
        "mfg"
    ],
    "wof:name":"GTC Inc",
    "wof:placetype":"venue"
},
  "geometry": {"coordinates":[-74.245552,39.746328],"type":"Point"}
}