{
  "type": "Feature",
  "properties": {
    "iso:country":"US",
    "sg:address":"713 Prospect St",
    "sg:city":"Maplewood",
    "sg:classifiers":[
        {
            "category":"Home & Garden",
            "subcategory":"Building Materials",
            "type":"Retail Goods"
        }
    ],
    "sg:phone":"+1 973 762 5986",
    "sg:postcode":"07040",
    "sg:province":"NJ",
    "sg:tags":[
        "windows",
        "replacement"
    ],
    "wof:name":"True Thermal Window Co Inc",
    "wof:placetype":"venue"
},
  "geometry": {"coordinates":[-74.271338,40.722044],"type":"Point"}
}