{
  "type": "Feature",
  "properties": {
    "iso:country":"US",
    "sg:address":"6 Mayfarth Ter",
    "sg:city":"Plainsboro",
    "sg:classifiers":[
        {
            "category":"Building & Trades",
            "subcategory":"Cleaning & Sanitation",
            "type":"Services"
        }
    ],
    "sg:phone":"+1 609 443 6399",
    "sg:postcode":"08536",
    "sg:province":"NJ",
    "wof:name":"Princeton Janitorial Mntnc",
    "wof:placetype":"venue"
},
  "geometry": {"coordinates":[-74.605228,40.324097],"type":"Point"}
}