{
  "type": "Feature",
  "properties": {
    "addr:full":"21 Parker Ct Florham Park NJ 07932",
    "addr:housenumber":"21",
    "addr:postcode":"07932",
    "addr:street":"Parker Ct",
    "iso:country":"US",
    "sg:address":"21 Parker Ct",
    "sg:city":"Florham Park",
    "sg:classifiers":[
        {
            "category":"Professional",
            "type":"Services"
        }
    ],
    "sg:phone":"+1   ",
    "sg:postcode":"07932",
    "sg:province":"NJ",
    "wof:name":"Persis Loveys",
    "wof:placetype":"venue"
},
  "geometry": {"coordinates":[-74.396449,40.78016],"type":"Point"}
}