{
  "type": "Feature",
  "properties": {
    "addr:full":"30 Jefferson Ave Jersey City NJ 07306",
    "addr:housenumber":"30",
    "addr:postcode":"07306",
    "addr:street":"Jefferson Ave",
    "iso:country":"US",
    "sg:address":"30 Jefferson Ave",
    "sg:city":"Jersey City",
    "sg:classifiers":[
        {
            "category":"Professional",
            "type":"Services"
        }
    ],
    "sg:phone":"+1   ",
    "sg:postcode":"07306",
    "sg:province":"NJ",
    "wof:name":"AK Bazar Corporation",
    "wof:placetype":"venue"
},
  "geometry": {"coordinates":[-74.050224,40.736425],"type":"Point"}
}