{
  "type": "Feature",
  "properties": {
    "iso:country":"US",
    "sg:address":"363 S 1st Rd",
    "sg:city":"Hammonton",
    "sg:classifiers":[
        {
            "category":"Freight",
            "type":"Transportation"
        }
    ],
    "sg:phone":"+1 856 461 6217",
    "sg:postcode":"08037",
    "sg:province":"NJ",
    "sg:tags":[
        "forwarder"
    ],
    "wof:name":"Saint Catherines Trnsp LLC",
    "wof:placetype":"venue"
},
  "geometry": {"coordinates":[-74.801182,39.623003],"type":"Point"}
}