{
  "type": "Feature",
  "properties": {
    "iso:country":"US",
    "sg:address":"1951 State Rte 33",
    "sg:city":"Trenton",
    "sg:classifiers":[
        {
            "category":"Home & Garden",
            "subcategory":"Furniture",
            "type":"Retail Goods"
        }
    ],
    "sg:phone":"+1   ",
    "sg:postcode":"08690",
    "sg:province":"NJ",
    "wof:name":"Capital Bedding Co",
    "wof:placetype":"venue"
},
  "geometry": {"coordinates":[-74.654067,40.225049],"type":"Point"}
}