{
  "type": "Feature",
  "properties": {
    "addr:full":"6 Keyes St Florham Park NJ 07932",
    "addr:housenumber":"6",
    "addr:postcode":"07932",
    "addr:street":"Keyes St",
    "iso:country":"US",
    "sg:address":"6 Keyes St",
    "sg:city":"Florham Park",
    "sg:classifiers":[
        {
            "category":"Professional",
            "type":"Services"
        }
    ],
    "sg:phone":"+1   ",
    "sg:postcode":"07932",
    "sg:province":"NJ",
    "wof:name":"Reef USA Inc",
    "wof:placetype":"venue"
},
  "geometry": {"coordinates":[-74.392336,40.784291],"type":"Point"}
}