{
  "type": "Feature",
  "properties": {
    "iso:country":"US",
    "sg:address":"1924 Marlton Pike E",
    "sg:city":"Cherry Hill",
    "sg:classifiers":[
        {
            "category":"Shopping",
            "type":"Retail Goods"
        }
    ],
    "sg:phone":"+1 856 424 2212",
    "sg:postcode":"08003",
    "sg:province":"NJ",
    "sg:tags":[
        "hearing",
        "equipment",
        "supply",
        "impaired"
    ],
    "wof:name":"New Jersey Hearing Aid Ctr",
    "wof:placetype":"venue"
},
  "geometry": {"coordinates":[-74.964217,39.902255],"type":"Point"}
}