{
  "type": "Feature",
  "properties": {
    "addr:full":"2 Main St Hackensack NJ 07601",
    "addr:housenumber":"2",
    "addr:postcode":"07601",
    "addr:street":"Main St",
    "iso:country":"US",
    "sg:address":"2 Main St",
    "sg:city":"Hackensack",
    "sg:classifiers":[
        {
            "category":"Banks & Credit Unions",
            "subcategory":"Bank",
            "type":"Services"
        }
    ],
    "sg:phone":"+1 201 712 3085",
    "sg:postcode":"07601",
    "sg:province":"NJ",
    "wof:name":"Wachovia",
    "wof:placetype":"venue"
},
  "geometry": {"coordinates":[-74.044421,40.877953],"type":"Point"}
}