{
  "type": "Feature",
  "properties": {
    "iso:country":"US",
    "sg:address":"990 US Hwy 202",
    "sg:city":"Somerville",
    "sg:classifiers":[
        {
            "category":"Recreation",
            "type":"Entertainment"
        }
    ],
    "sg:phone":"+1 908 722 1120",
    "sg:postcode":"08876",
    "sg:province":"NJ",
    "wof:name":"Mr OS Tae Kwon Do Oriental AR",
    "wof:placetype":"venue"
},
  "geometry": {"coordinates":[-74.689531,40.565639],"type":"Point"}
}