{
  "type": "Feature",
  "properties": {
    "iso:country":"US",
    "sg:address":"1405 Oak Tree Rd",
    "sg:city":"Iselin",
    "sg:classifiers":[
        {
            "category":"Wholesale",
            "subcategory":"Computers",
            "type":"Manufacturing & Wholesale Goods"
        },
        {
            "category":"Professional",
            "subcategory":"Computer Services",
            "type":"Services"
        }
    ],
    "sg:phone":"+1 732 283 9898",
    "sg:postcode":"08830",
    "sg:province":"NJ",
    "sg:tags":[
        "repair"
    ],
    "sg:website":"www.computercareus.com",
    "wof:name":"Computer Care US Corp",
    "wof:placetype":"venue"
},
  "geometry": {"coordinates":[-74.327003,40.573502],"type":"Point"}
}