{
  "type": "Feature",
  "properties": {
    "addr:full":"426 E Millstream Rd Creamridge NJ 08533",
    "addr:housenumber":"426",
    "addr:postcode":"08533",
    "addr:street":"E Millstream Rd",
    "iso:country":"US",
    "sg:address":"426 E Millstream Rd",
    "sg:city":"Creamridge",
    "sg:classifiers":[
        {
            "category":"Real Estate",
            "subcategory":"Real Estate Agent",
            "type":"Services"
        }
    ],
    "sg:phone":"+1   ",
    "sg:postcode":"08533",
    "sg:province":"NJ",
    "wof:name":"C Conner Real Estate",
    "wof:placetype":"venue"
},
  "geometry": {"coordinates":[-74.491553,40.110054],"type":"Point"}
}