{
  "type": "Feature",
  "properties": {
    "iso:country":"US",
    "sg:address":"528 Arnold Ave",
    "sg:city":"Pt Pleasant Bch",
    "sg:classifiers":[
        {
            "category":"Home & Garden",
            "subcategory":"Hardware",
            "type":"Retail Goods"
        }
    ],
    "sg:phone":"+1 732 892 5200",
    "sg:postcode":"08742",
    "sg:province":"NJ",
    "wof:name":"Point Hardware & Gifts",
    "wof:placetype":"venue"
},
  "geometry": {"coordinates":[-74.04941599999999,40.091705],"type":"Point"}
}