{
  "type": "Feature",
  "properties": {
    "addr:full":"1173 S Route 9 Cape May Court House NJ 08210",
    "addr:housenumber":"1173",
    "addr:postcode":"08210",
    "addr:street":"S Route 9 Cape May",
    "iso:country":"US",
    "sg:address":"1173 S Route 9",
    "sg:city":"Cape May Court House",
    "sg:classifiers":[
        {
            "category":"Retail",
            "subcategory":"Veterinary Services",
            "type":"Services"
        }
    ],
    "sg:phone":"+1 609 465 5590",
    "sg:postcode":"08210",
    "sg:province":"NJ",
    "sg:tags":[
        "veterinarian"
    ],
    "wof:name":"Mosson Clifford F Vmd",
    "wof:placetype":"venue"
},
  "geometry": {"coordinates":[-74.834999,39.062599],"type":"Point"}
}