{
  "type": "Feature",
  "properties": {
    "iso:country":"US",
    "sg:address":"9 Hanover Ave",
    "sg:city":"Warren",
    "sg:classifiers":[
        {
            "category":"Professional",
            "subcategory":"Management & Consulting",
            "type":"Services"
        }
    ],
    "sg:phone":"+1   ",
    "sg:postcode":"07059",
    "sg:province":"NJ",
    "sg:tags":[
        "business"
    ],
    "wof:name":"Keenan Consulting Inc",
    "wof:placetype":"venue"
},
  "geometry": {"coordinates":[-74.48388300000001,40.642503],"type":"Point"}
}