{
  "type": "Feature",
  "properties": {
    "addr:full":"117 Racetrack Dr Cape May NJ 08204",
    "addr:housenumber":"117",
    "addr:postcode":"08204",
    "addr:street":"Racetrack Dr",
    "iso:country":"US",
    "sg:address":"117 Racetrack Dr",
    "sg:city":"Cape May",
    "sg:classifiers":[
        {
            "category":"Farming",
            "subcategory":"Fish & Marine Products",
            "type":"Manufacturing & Wholesale Goods"
        }
    ],
    "sg:phone":"+1 609 517 5653",
    "sg:postcode":"08204",
    "sg:province":"NJ",
    "sg:tags":[
        "fishing"
    ],
    "wof:name":"B Nightwatch",
    "wof:placetype":"venue"
},
  "geometry": {"coordinates":[-74.95311700000001,38.989149],"type":"Point"}
}