{
  "type": "Feature",
  "properties": {
    "addr:full":"6 Dumont Pl Ste 3 Morristown NJ 07960",
    "addr:housenumber":"6",
    "addr:postcode":"07960",
    "addr:street":"Dumont Pl Ste 3",
    "iso:country":"US",
    "sg:address":"6 Dumont Pl Ste 3",
    "sg:city":"Morristown",
    "sg:classifiers":[
        {
            "category":"Professional",
            "subcategory":"Lawyer & Legal Services",
            "type":"Services"
        }
    ],
    "sg:phone":"+1 973 984 8484",
    "sg:postcode":"07960",
    "sg:province":"NJ",
    "wof:name":"Mambelli Dino Attorney",
    "wof:placetype":"venue"
},
  "geometry": {"coordinates":[-74.479572,40.79701],"type":"Point"}
}