{
  "type": "Feature",
  "properties": {
    "addr:full":"435 Allwood Rd Clifton NJ 07012",
    "addr:housenumber":"435",
    "addr:postcode":"07012",
    "addr:street":"Allwood Rd",
    "iso:country":"US",
    "sg:address":"435 Allwood Rd",
    "sg:city":"Clifton",
    "sg:classifiers":[
        {
            "category":"Freight",
            "type":"Transportation"
        }
    ],
    "sg:phone":"+1 973 773 7336",
    "sg:postcode":"07012",
    "sg:province":"NJ",
    "sg:tags":[
        "trucking"
    ],
    "wof:name":"Clifford B Finkle Jr Inc",
    "wof:placetype":"venue"
},
  "geometry": {"coordinates":[-74.147311,40.835353],"type":"Point"}
}