{
  "type": "Feature",
  "properties": {
    "addr:full":"44 W Sylvania Ave Neptune NJ 07753",
    "addr:housenumber":"44",
    "addr:postcode":"07753",
    "addr:street":"W Sylvania Ave",
    "iso:country":"US",
    "sg:address":"44 W Sylvania Ave",
    "sg:city":"Neptune",
    "sg:classifiers":[
        {
            "category":"Professional",
            "subcategory":"Lawyer & Legal Services",
            "type":"Services"
        }
    ],
    "sg:phone":"+1 732 988 3333",
    "sg:postcode":"07753",
    "sg:province":"NJ",
    "wof:name":"Christopher G Kilbridge",
    "wof:placetype":"venue"
},
  "geometry": {"coordinates":[-74.028614,40.197047],"type":"Point"}
}