{
  "type": "Feature",
  "properties": {
    "iso:country":"US",
    "sg:address":"1185 Briarwood Dr",
    "sg:city":"Williamstown",
    "sg:classifiers":[
        {
            "category":"Building & Trades",
            "subcategory":"Plumbing",
            "type":"Services"
        }
    ],
    "sg:phone":"+1 856 875 1268",
    "sg:postcode":"08094",
    "sg:province":"NJ",
    "sg:tags":[
        "air",
        "heating",
        "refrigeration",
        "conditioning",
        "contractor"
    ],
    "wof:name":"Endres Stephen F Heating & AC",
    "wof:placetype":"venue"
},
  "geometry": {"coordinates":[-74.986609,39.654695],"type":"Point"}
}