{
  "type": "Feature",
  "properties": {
    "iso:country":"US",
    "sg:address":"80 W Harwood Ave",
    "sg:city":"Palisades Park",
    "sg:classifiers":[
        {
            "category":"Professional",
            "type":"Services"
        }
    ],
    "sg:phone":"+1   ",
    "sg:postcode":"07650",
    "sg:province":"NJ",
    "wof:name":"Gradus Ad Parnassum Inc",
    "wof:placetype":"venue"
},
  "geometry": {"coordinates":[-74.001518,40.844974],"type":"Point"}
}