{
  "type": "Feature",
  "properties": {
    "addr:full":"242 10th St Jersey City NJ 07302",
    "addr:housenumber":"242",
    "addr:postcode":"07302",
    "addr:street":"10Th St",
    "iso:country":"US",
    "sg:address":"242 10th St",
    "sg:city":"Jersey City",
    "sg:classifiers":[
        {
            "category":"Real Estate",
            "subcategory":"Real Estate Operator",
            "type":"Services"
        }
    ],
    "sg:phone":"+1 201 653 2861",
    "sg:postcode":"07302",
    "sg:province":"NJ",
    "sg:tags":[
        "building",
        "apartment"
    ],
    "wof:name":"Hamilton Lofts",
    "wof:placetype":"venue"
},
  "geometry": {"coordinates":[-74.043999,40.729],"type":"Point"}
}