{
  "type": "Feature",
  "properties": {
    "iso:country":"US",
    "sg:address":"98 George St",
    "sg:city":"Tenafly",
    "sg:classifiers":[
        {
            "category":"Professional",
            "subcategory":"Business Services",
            "type":"Services"
        }
    ],
    "sg:phone":"+1   ",
    "sg:postcode":"07670",
    "sg:province":"NJ",
    "wof:name":"Dee Kay Associates Inc",
    "wof:placetype":"venue"
},
  "geometry": {"coordinates":[-73.968907,40.917874],"type":"Point"}
}