{
  "type": "Feature",
  "properties": {
    "iso:country":"US",
    "sg:address":"474 Wilson Ave",
    "sg:city":"Newark",
    "sg:classifiers":[
        {
            "category":"Freight",
            "type":"Transportation"
        }
    ],
    "sg:phone":"+1 973 522 1855",
    "sg:postcode":"07105",
    "sg:province":"NJ",
    "sg:tags":[
        "broker",
        "trucking"
    ],
    "wof:name":"San-Ber Carriers Inc",
    "wof:placetype":"venue"
},
  "geometry": {"coordinates":[-74.139697,40.716505],"type":"Point"}
}