{
  "type": "Feature",
  "properties": {
    "iso:country":"US",
    "sg:address":"186 W Market St",
    "sg:city":"Newark",
    "sg:classifiers":[
        {
            "category":"Internet Cafe",
            "subcategory":"None",
            "type":"Food & Drink"
        },
        {
            "category":"Professional",
            "subcategory":"Computer Services",
            "type":"Services"
        }
    ],
    "sg:phone":"+1 800 772 4719",
    "sg:postcode":"07103",
    "sg:province":"NJ",
    "sg:tags":[
        "consultant",
        "product"
    ],
    "sg:website":"http://ad.doubleclick.net/clk;221975114;45582064;f?http://www.optimum.com/online/",
    "wof:name":"Optimum Online",
    "wof:placetype":"venue"
},
  "geometry": {"coordinates":[-74.18622999999999,40.741105],"type":"Point"}
}