{
  "type": "Feature",
  "properties": {
    "addr:full":"1001 W State St Trenton NJ 08618",
    "addr:housenumber":"1001",
    "addr:postcode":"08618",
    "addr:street":"W State St",
    "iso:country":"US",
    "sg:address":"1001 W State St",
    "sg:city":"Trenton",
    "sg:classifiers":[
        {
            "category":"Education",
            "subcategory":"School",
            "type":"Public Place"
        }
    ],
    "sg:phone":"+1   ",
    "sg:postcode":"08618",
    "sg:province":"NJ",
    "sg:tags":[
        "middle"
    ],
    "wof:name":"Arthur J Holland Middle School",
    "wof:placetype":"venue"
},
  "geometry": {"coordinates":[-74.792794,40.23323],"type":"Point"}
}