{
  "type": "Feature",
  "properties": {
    "addr:full":"345 Prospect Ave West Orange NJ 07052",
    "addr:housenumber":"345",
    "addr:postcode":"07052",
    "addr:street":"Prospect Ave",
    "iso:country":"US",
    "sg:address":"345 Prospect Ave",
    "sg:city":"West Orange",
    "sg:classifiers":[
        {
            "category":"Shopping",
            "subcategory":"Crafts & Fabrics",
            "type":"Retail Goods"
        }
    ],
    "sg:phone":"+1 973 736 2602",
    "sg:postcode":"07052",
    "sg:province":"NJ",
    "sg:tags":[
        "art",
        "supply"
    ],
    "wof:name":"Rag Shop Fabrics & Crafts",
    "wof:placetype":"venue"
},
  "geometry": {"coordinates":[-74.253798,40.793944],"type":"Point"}
}