{
  "type": "Feature",
  "properties": {
    "iso:country":"US",
    "sg:address":"305 Kelly Dr",
    "sg:city":"Neshanic Station",
    "sg:classifiers":[
        {
            "category":"Professional",
            "type":"Services"
        }
    ],
    "sg:phone":"+1   ",
    "sg:postcode":"08853",
    "sg:province":"NJ",
    "wof:name":"Greenspan Consulting",
    "wof:placetype":"venue"
},
  "geometry": {"coordinates":[-74.754113,40.530585],"type":"Point"}
}