{
  "type": "Feature",
  "properties": {
    "iso:country":"US",
    "sg:address":"549 2nd Ave",
    "sg:city":"Lyndhurst",
    "sg:classifiers":[
        {
            "category":"Shopping",
            "subcategory":"Clothing, Apparel, & Fashions",
            "type":"Retail Goods"
        }
    ],
    "sg:phone":"+1   ",
    "sg:postcode":"07071",
    "sg:province":"NJ",
    "wof:name":"Crosstown Sportswear Inc",
    "wof:placetype":"venue"
},
  "geometry": {"coordinates":[-74.11675099999999,40.813157],"type":"Point"}
}