{
  "type": "Feature",
  "properties": {
    "addr:full":"1200 Little Gloucester Rd Clementon NJ 08021",
    "addr:housenumber":"1200",
    "addr:postcode":"08021",
    "addr:street":"Little Gloucester Rd",
    "iso:country":"US",
    "sg:address":"1200 Little Gloucester Rd",
    "sg:city":"Clementon",
    "sg:classifiers":[
        {
            "category":"Real Estate",
            "subcategory":"Real Estate Operator",
            "type":"Services"
        }
    ],
    "sg:phone":"+1   ",
    "sg:postcode":"08021",
    "sg:province":"NJ",
    "sg:tags":[
        "building",
        "apartment"
    ],
    "wof:name":"Cherrywood Apartments",
    "wof:placetype":"venue"
},
  "geometry": {"coordinates":[-75.04066899999999,39.799687],"type":"Point"}
}