{
  "type": "Feature",
  "properties": {
    "addr:full":"5 Morgan Ln Great Meadows NJ 07838",
    "addr:housenumber":"5",
    "addr:postcode":"07838",
    "addr:street":"Morgan Ln",
    "iso:country":"US",
    "sg:address":"5 Morgan Ln",
    "sg:city":"Great Meadows",
    "sg:classifiers":[
        {
            "category":"Professional",
            "type":"Services"
        }
    ],
    "sg:phone":"+1   ",
    "sg:postcode":"07838",
    "sg:province":"NJ",
    "wof:name":"Vinyls Final LLC",
    "wof:placetype":"venue"
},
  "geometry": {"coordinates":[-74.92766899999999,40.857288],"type":"Point"}
}