{
  "type": "Feature",
  "properties": {
    "iso:country":"US",
    "sg:address":"406 S Washington Ave",
    "sg:city":"Bergenfield",
    "sg:classifiers":[
        {
            "category":"Shopping",
            "subcategory":"Pharmacy",
            "type":"Retail Goods"
        }
    ],
    "sg:phone":"+1 201 384 4447",
    "sg:postcode":"07621",
    "sg:province":"NJ",
    "sg:tags":[
        "drugstore"
    ],
    "sg:website":"www.walgreens.com",
    "wof:name":"Walgreen Drug Stores",
    "wof:placetype":"venue"
},
  "geometry": {"coordinates":[-73.997637,40.913983],"type":"Point"}
}