{
  "type": "Feature",
  "properties": {
    "iso:country":"US",
    "sg:address":"1727 County Line Rd",
    "sg:city":"Lakewood",
    "sg:classifiers":[
        {
            "category":"Professional",
            "type":"Services"
        }
    ],
    "sg:phone":"+1   ",
    "sg:postcode":"08701",
    "sg:province":"NJ",
    "wof:name":"Misty Valley Acres",
    "wof:placetype":"venue"
},
  "geometry": {"coordinates":[-74.251587,40.116203],"type":"Point"}
}