{
  "type": "Feature",
  "properties": {
    "addr:full":"1727 County Line Rd Lakewood NJ 08701",
    "addr:housenumber":"1727",
    "addr:postcode":"08701",
    "addr:street":"County Line Rd",
    "iso:country":"US",
    "sg:address":"1727 County Line Rd",
    "sg:city":"Lakewood",
    "sg:classifiers":[
        {
            "category":"Professional",
            "type":"Services"
        }
    ],
    "sg:phone":"+1   ",
    "sg:postcode":"08701",
    "sg:province":"NJ",
    "wof:name":"Misty Valley Acres",
    "wof:placetype":"venue"
},
  "geometry": {"coordinates":[-74.251587,40.116203],"type":"Point"}
}