{
  "type": "Feature",
  "properties": {
    "iso:country":"US",
    "sg:address":"650-672 Kapowski Road",
    "sg:city":"Elizabeth",
    "sg:classifiers":[
        {
            "category":"Restaurant",
            "type":"Food & Drink"
        }
    ],
    "sg:phone":"+1 908 353 7600",
    "sg:postcode":"07201",
    "sg:province":"NJ",
    "sg:tags":[
        "breakfast",
        "brunch"
    ],
    "sg:website":"www.ihop.com/",
    "wof:name":"International House of Pancakes",
    "wof:placetype":"venue"
},
  "geometry": {"coordinates":[-74.174091,40.663559],"type":"Point"}
}