{
  "type": "Feature",
  "properties": {
    "iso:country":"US",
    "sg:address":"296 Main St",
    "sg:city":"West Orange",
    "sg:classifiers":[
        {
            "category":"Shopping",
            "subcategory":"Beauty & Cosmetics",
            "type":"Retail Goods"
        }
    ],
    "sg:phone":"+1 973 731 0311",
    "sg:postcode":"07052",
    "sg:province":"NJ",
    "sg:tags":[
        "supply"
    ],
    "wof:name":"Wkw Beauty Supply",
    "wof:placetype":"venue"
},
  "geometry": {"coordinates":[-74.23130399999999,40.787613],"type":"Point"}
}