{
  "type": "Feature",
  "properties": {
    "iso:country":"US",
    "sg:address":"136 Main St Ste 250",
    "sg:city":"Princeton",
    "sg:classifiers":[
        {
            "category":"Professional",
            "subcategory":"Lawyer & Legal Services",
            "type":"Services"
        }
    ],
    "sg:phone":"+1 609 987 0050",
    "sg:postcode":"08540",
    "sg:province":"NJ",
    "sg:tags":[
        "attorney",
        "practice",
        "plan",
        "business",
        "law"
    ],
    "sg:website":"http://www.reedsmith.com",
    "wof:name":"Mantell, Nanette W - Reed Smith Llp",
    "wof:placetype":"venue"
},
  "geometry": {"coordinates":[-74.61451700000001,40.35611],"type":"Point"}
}