{
  "type": "Feature",
  "properties": {
    "addr:full":"119 Genesee St Trenton NJ 08611",
    "addr:housenumber":"119",
    "addr:postcode":"08611",
    "addr:street":"Genesee St",
    "iso:country":"US",
    "sg:address":"119 Genesee St",
    "sg:city":"Trenton",
    "sg:classifiers":[
        {
            "category":"Building & Trades",
            "subcategory":"Construction",
            "type":"Services"
        }
    ],
    "sg:phone":"+1 609 278 9751",
    "sg:postcode":"08611",
    "sg:province":"NJ",
    "sg:tags":[
        "contractor"
    ],
    "wof:name":"Leos Contractor Inc",
    "wof:placetype":"venue"
},
  "geometry": {"coordinates":[-74.751631,40.208495],"type":"Point"}
}