{
  "type": "Feature",
  "properties": {
    "iso:country":"US",
    "sg:address":"55 Homer St",
    "sg:city":"Clifton",
    "sg:classifiers":[
        {
            "category":"Professional",
            "type":"Services"
        }
    ],
    "sg:phone":"+1   ",
    "sg:postcode":"07014",
    "sg:province":"NJ",
    "wof:name":"Marlene Lee",
    "wof:placetype":"venue"
},
  "geometry": {"coordinates":[-74.134795,40.835575],"type":"Point"}
}