{
  "type": "Feature",
  "properties": {
    "addr:full":"5 E Somerset St Raritan NJ 08869",
    "addr:housenumber":"5",
    "addr:postcode":"08869",
    "addr:street":"E Somerset St",
    "iso:country":"US",
    "sg:address":"5 E Somerset St",
    "sg:city":"Raritan",
    "sg:classifiers":[
        {
            "category":"Restaurant",
            "type":"Food & Drink"
        }
    ],
    "sg:phone":"+1 908 526 9887",
    "sg:postcode":"08869",
    "sg:province":"NJ",
    "sg:tags":[
        "eating"
    ],
    "wof:name":"Uncle Vinnie's",
    "wof:placetype":"venue"
},
  "geometry": {"coordinates":[-74.63159899999999,40.568312],"type":"Point"}
}