{
  "type": "Feature",
  "properties": {
    "addr:full":"127 Loretta St Perth Amboy NJ 08861",
    "addr:housenumber":"127",
    "addr:postcode":"08861",
    "addr:street":"Loretta St",
    "iso:country":"US",
    "sg:address":"127 Loretta St",
    "sg:city":"Perth Amboy",
    "sg:classifiers":[
        {
            "category":"Government",
            "subcategory":"Fire Station",
            "type":"Public Place"
        }
    ],
    "sg:phone":"+1   ",
    "sg:postcode":"08861",
    "sg:province":"NJ",
    "sg:tags":[
        "dept",
        "v"
    ],
    "wof:name":"Woodbridge Fire Dist 8",
    "wof:placetype":"venue"
},
  "geometry": {"coordinates":[-74.296397,40.52493],"type":"Point"}
}