{
  "type": "Feature",
  "properties": {
    "addr:full":"1447 Walden Ave Lakewood NJ 08701",
    "addr:housenumber":"1447",
    "addr:postcode":"08701",
    "addr:street":"Walden Ave",
    "iso:country":"US",
    "sg:address":"1447 Walden Ave",
    "sg:city":"Lakewood",
    "sg:classifiers":[
        {
            "category":"Building & Trades",
            "subcategory":"Electrical",
            "type":"Services"
        },
        {
            "category":"Wholesale",
            "subcategory":"Electrical",
            "type":"Manufacturing & Wholesale Goods"
        }
    ],
    "sg:phone":"+1 732 363 1189",
    "sg:postcode":"08701",
    "sg:province":"NJ",
    "sg:tags":[
        "system",
        "alarm",
        "security",
        "telecommunication"
    ],
    "wof:name":"Superior Communication & SEC",
    "wof:placetype":"venue"
},
  "geometry": {"coordinates":[-74.235919,40.105875],"type":"Point"}
}