{
  "type": "Feature",
  "properties": {
    "iso:country":"US",
    "sg:address":"719 3rd Ave",
    "sg:city":"Lyndhurst",
    "sg:classifiers":[
        {
            "category":"Professional",
            "subcategory":"Business Services",
            "type":"Services"
        }
    ],
    "sg:phone":"+1 201 507 0909",
    "sg:postcode":"07071",
    "sg:province":"NJ",
    "sg:tags":[
        "messenger"
    ],
    "wof:name":"Kadima Messenger Svc",
    "wof:placetype":"venue"
},
  "geometry": {"coordinates":[-74.11136500000001,40.811002],"type":"Point"}
}