{
  "type": "Feature",
  "properties": {
    "addr:full":"96 Garfield Rd Parsippany NJ 07054",
    "addr:housenumber":"96",
    "addr:postcode":"07054",
    "addr:street":"Garfield Rd",
    "iso:country":"US",
    "sg:address":"96 Garfield Rd",
    "sg:city":"Parsippany",
    "sg:classifiers":[
        {
            "category":"Retail",
            "subcategory":"Animal Services",
            "type":"Services"
        }
    ],
    "sg:phone":"+1 973 884 2093",
    "sg:postcode":"07054",
    "sg:province":"NJ",
    "wof:name":"Mobile Pet Salon",
    "wof:placetype":"venue"
},
  "geometry": {"coordinates":[-74.43338199999999,40.846431],"type":"Point"}
}