{
  "type": "Feature",
  "properties": {
    "iso:country":"US",
    "sg:address":"256 Columbia Tpke",
    "sg:city":"Florham Park",
    "sg:classifiers":[
        {
            "category":"Professional",
            "subcategory":"Management & Consulting",
            "type":"Services"
        }
    ],
    "sg:phone":"+1 973 966 0866",
    "sg:postcode":"07932",
    "sg:province":"NJ",
    "sg:tags":[
        "consultant",
        "business"
    ],
    "wof:name":"Leadership Solutions Inc",
    "wof:placetype":"venue"
},
  "geometry": {"coordinates":[-74.404185,40.789803],"type":"Point"}
}