{
  "type": "Feature",
  "properties": {
    "iso:country":"US",
    "sg:address":"3000 US Hwy 130",
    "sg:city":"Delran",
    "sg:classifiers":[
        {
            "category":"Autos & Motor Vehicles",
            "subcategory":"Fuel & Gas Station",
            "type":"Retail Goods"
        }
    ],
    "sg:phone":"+1 856 461 7444",
    "sg:postcode":"08075",
    "sg:province":"NJ",
    "sg:tags":[
        "station",
        "gasoline",
        "oil"
    ],
    "wof:name":"Bridgepoint Operating Co",
    "wof:placetype":"venue"
},
  "geometry": {"coordinates":[-74.96639399999999,40.009784],"type":"Point"}
}