{
  "type": "Feature",
  "properties": {
    "addr:full":"1247 Sussex Tpke Randolph NJ 07869",
    "addr:housenumber":"1247",
    "addr:postcode":"07869",
    "addr:street":"Sussex Tpke",
    "iso:country":"US",
    "sg:address":"1247 Sussex Tpke",
    "sg:city":"Randolph",
    "sg:classifiers":[
        {
            "category":"Wholesale",
            "subcategory":"Drugs",
            "type":"Manufacturing & Wholesale Goods"
        }
    ],
    "sg:phone":"+1 973 895 6449",
    "sg:postcode":"07869",
    "sg:province":"NJ",
    "sg:tags":[
        "dermatology",
        "pharmaceutical",
        "product"
    ],
    "sg:website":"www.speardermatology.com",
    "wof:name":"Spear Dermatology Prod Inc",
    "wof:placetype":"venue"
},
  "geometry": {"coordinates":[-74.582605,40.827386],"type":"Point"}
}