{
  "type": "Feature",
  "properties": {
    "addr:full":"123 Fairfield Rd Fairfield NJ 07004",
    "addr:housenumber":"123",
    "addr:postcode":"07004",
    "addr:street":"Fairfield Rd",
    "iso:country":"US",
    "sg:address":"123 Fairfield Rd",
    "sg:city":"Fairfield",
    "sg:classifiers":[
        {
            "category":"Real Estate",
            "subcategory":"Architect",
            "type":"Services"
        }
    ],
    "sg:phone":"+1   ",
    "sg:postcode":"07004",
    "sg:province":"NJ",
    "sg:tags":[
        "consulting",
        "management",
        "architectural"
    ],
    "wof:name":"Gorski Waldron Jefferson Assoc",
    "wof:placetype":"venue"
},
  "geometry": {"coordinates":[-74.299188,40.873656],"type":"Point"}
}