{
  "type": "Feature",
  "properties": {
    "addr:full":"1026 Haddon Ave Collingswood NJ 08108",
    "addr:housenumber":"1026",
    "addr:postcode":"08108",
    "addr:street":"Haddon Ave",
    "iso:country":"US",
    "sg:address":"1026 Haddon Ave",
    "sg:city":"Collingswood",
    "sg:classifiers":[
        {
            "category":"Insurance",
            "subcategory":"Insurance Agent",
            "type":"Services"
        },
        {
            "category":"Insurance",
            "subcategory":"Hazard Insurance",
            "type":"Services"
        },
        {
            "category":"Professional",
            "subcategory":"Business Services",
            "type":"Services"
        }
    ],
    "sg:phone":"+1 856 240 1065",
    "sg:postcode":"08108",
    "sg:province":"NJ",
    "sg:tags":[
        "consultant",
        "commercial",
        "analyst",
        "notary",
        "public"
    ],
    "sg:website":"http://www.westjerseyinsurance.com",
    "wof:name":"West Jersey Insurance Agency Inc",
    "wof:placetype":"venue"
},
  "geometry": {"coordinates":[-75.060239,39.91382],"type":"Point"}
}