{
  "type": "Feature",
  "properties": {
    "iso:country":"US",
    "sg:address":"706 Burnt Tavern Rd",
    "sg:city":"Point Pleasant Beach",
    "sg:classifiers":[
        {
            "category":"Building & Trades",
            "subcategory":"Construction",
            "type":"Services"
        }
    ],
    "sg:phone":"+1 732 892 1561",
    "sg:postcode":"08742",
    "sg:province":"NJ",
    "sg:tags":[
        "contractor"
    ],
    "wof:name":"Jersey Boy Pools & Spas",
    "wof:placetype":"venue"
},
  "geometry": {"coordinates":[-74.055829,40.077026],"type":"Point"}
}