{
  "type": "Feature",
  "properties": {
    "iso:country":"US",
    "sg:address":"206 Tern Dr",
    "sg:city":"Brick",
    "sg:classifiers":[
        {
            "category":"Autos & Motor Vehicles",
            "subcategory":"Automobile Sales",
            "type":"Retail Goods"
        }
    ],
    "sg:phone":"+1 732 644 9888",
    "sg:postcode":"08723",
    "sg:province":"NJ",
    "sg:tags":[
        "new",
        "car"
    ],
    "wof:name":"Blue Star Auto Sales",
    "wof:placetype":"venue"
},
  "geometry": {"coordinates":[-74.07512,40.043759],"type":"Point"}
}