{
  "type": "Feature",
  "properties": {
    "iso:country":"US",
    "sg:address":"240 State St",
    "sg:city":"Perth Amboy",
    "sg:classifiers":[
        {
            "category":"Building & Trades",
            "subcategory":"Construction",
            "type":"Services"
        }
    ],
    "sg:phone":"+1 732 293 1580",
    "sg:postcode":"08861",
    "sg:province":"NJ",
    "sg:tags":[
        "contractor"
    ],
    "wof:name":"I B C General Contractors Llc",
    "wof:placetype":"venue"
},
  "geometry": {"coordinates":[-74.268552,40.506699],"type":"Point"}
}