{
  "type": "Feature",
  "properties": {
    "addr:full":"40 Canoe Brook Pkwy Summit NJ 07901",
    "addr:housenumber":"40",
    "addr:postcode":"07901",
    "addr:street":"Canoe Brook Pkwy",
    "iso:country":"US",
    "sg:address":"40 Canoe Brook Pkwy",
    "sg:city":"Summit",
    "sg:classifiers":[
        {
            "category":"Food & Beverages",
            "subcategory":"Liquor & Beverages",
            "type":"Retail Goods"
        }
    ],
    "sg:phone":"+1   ",
    "sg:postcode":"07901",
    "sg:province":"NJ",
    "sg:tags":[
        "tavern",
        "store"
    ],
    "wof:name":"Burkes Discount Liquors",
    "wof:placetype":"venue"
},
  "geometry": {"coordinates":[-74.36769200000001,40.73431],"type":"Point"}
}