{
  "type": "Feature",
  "properties": {
    "addr:full":"120 N Washington Ave Dunellen NJ 08812",
    "addr:housenumber":"120",
    "addr:postcode":"08812",
    "addr:street":"N Washington Ave",
    "iso:country":"US",
    "sg:address":"120 N Washington Ave",
    "sg:city":"Dunellen",
    "sg:classifiers":[
        {
            "category":"Restaurant",
            "type":"Food & Drink"
        }
    ],
    "sg:menulink":"http://www.allmenus.com/nj/dunellen/27535-dunellen-hotel/menu/",
    "sg:phone":"+1 732 968 2900",
    "sg:postcode":"08812",
    "sg:province":"NJ",
    "sg:tags":[
        "american"
    ],
    "wof:name":"Dunellen Hotel",
    "wof:placetype":"venue"
},
  "geometry": {"coordinates":[-74.46326500000001,40.592073],"type":"Point"}
}