{
  "type": "Feature",
  "properties": {
    "iso:country":"US",
    "sg:address":"229 Harrison Ave",
    "sg:city":"Garfield",
    "sg:classifiers":[
        {
            "category":"Building & Trades",
            "subcategory":"Locksmith",
            "type":"Services"
        }
    ],
    "sg:phone":"+1 973 478 6660",
    "sg:postcode":"07026",
    "sg:province":"NJ",
    "sg:tags":[
        "key"
    ],
    "wof:name":"A 1 2 3 24Hour Locksmith",
    "wof:placetype":"venue"
},
  "geometry": {"coordinates":[-74.098,40.874001],"type":"Point"}
}