{
  "type": "Feature",
  "properties": {
    "addr:full":"271 US Hwy 46 Fairfield NJ 07004",
    "addr:housenumber":"271",
    "addr:postcode":"07004",
    "addr:street":"Us Hwy 46",
    "iso:country":"US",
    "sg:address":"271 US Hwy 46",
    "sg:city":"Fairfield",
    "sg:classifiers":[
        {
            "category":"Professional",
            "subcategory":"Computer Services",
            "type":"Services"
        }
    ],
    "sg:phone":"+1 973 882 8008",
    "sg:postcode":"07004",
    "sg:province":"NJ",
    "sg:tags":[
        "engineering",
        "architectural",
        "software"
    ],
    "wof:name":"AMS",
    "wof:placetype":"venue"
},
  "geometry": {"coordinates":[-74.29274700000001,40.881313],"type":"Point"}
}