{
  "type": "Feature",
  "properties": {
    "iso:country":"US",
    "sg:address":"1520 Long Beach Ave",
    "sg:city":"Lakewood",
    "sg:classifiers":[
        {
            "category":"Building & Trades",
            "subcategory":"Landscaping Services",
            "type":"Services"
        }
    ],
    "sg:phone":"+1 732 363 5564",
    "sg:postcode":"08701",
    "sg:province":"NJ",
    "sg:tags":[
        "landscape",
        "contractor"
    ],
    "wof:name":"Reinaldo Landscaping & Lawn",
    "wof:placetype":"venue"
},
  "geometry": {"coordinates":[-74.163569,40.096812],"type":"Point"}
}