{
  "type": "Feature",
  "properties": {
    "addr:full":"7424 Bergenline Ave North Bergen NJ 07047",
    "addr:housenumber":"7424",
    "addr:postcode":"07047",
    "addr:street":"Bergenline Ave",
    "iso:country":"US",
    "sg:address":"7424 Bergenline Ave",
    "sg:city":"North Bergen",
    "sg:classifiers":[
        {
            "category":"Food & Beverages",
            "subcategory":"Meat & Fish",
            "type":"Retail Goods"
        }
    ],
    "sg:phone":"+1 201 861 6635",
    "sg:postcode":"07047",
    "sg:province":"NJ",
    "sg:tags":[
        "shop"
    ],
    "wof:name":"Al-Qsa Meat",
    "wof:placetype":"venue"
},
  "geometry": {"coordinates":[-74.008904,40.798698],"type":"Point"}
}