{
  "type": "Feature",
  "properties": {
    "iso:country":"US",
    "sg:address":"175 Hudson St",
    "sg:city":"Hackensack",
    "sg:classifiers":[
        {
            "category":"Real Estate",
            "subcategory":"Real Estate Services",
            "type":"Services"
        }
    ],
    "sg:phone":"+1 201 996 1099",
    "sg:postcode":"07601",
    "sg:province":"NJ",
    "sg:tags":[
        "title"
    ],
    "sg:website":"http://www.towntitle.us",
    "wof:name":"Town Title Agency",
    "wof:placetype":"venue"
},
  "geometry": {"coordinates":[-74.042084,40.87318],"type":"Point"}
}