{
  "type": "Feature",
  "properties": {
    "iso:country":"US",
    "sg:address":"2446 Coles Mill Rd",
    "sg:city":"Franklinville",
    "sg:classifiers":[
        {
            "category":"Building & Trades",
            "subcategory":"Landscaping Services",
            "type":"Services"
        }
    ],
    "sg:phone":"+1 856 694 3487",
    "sg:postcode":"08322",
    "sg:province":"NJ",
    "wof:name":"Resino Tree Service",
    "wof:placetype":"venue"
},
  "geometry": {"coordinates":[-75.050213,39.619983],"type":"Point"}
}