{
  "type": "Feature",
  "properties": {
    "addr:full":"21 Rolling Ridge Rd Randolph NJ 07869",
    "addr:housenumber":"21",
    "addr:postcode":"07869",
    "addr:street":"Rolling Ridge Rd",
    "iso:country":"US",
    "sg:address":"21 Rolling Ridge Rd",
    "sg:city":"Randolph",
    "sg:classifiers":[
        {
            "category":"Professional",
            "subcategory":"Management & Consulting",
            "type":"Services"
        }
    ],
    "sg:phone":"+1 973 366 2409",
    "sg:postcode":"07869",
    "sg:province":"NJ",
    "sg:tags":[
        "business"
    ],
    "wof:name":"Whelpley Associates Inc",
    "wof:placetype":"venue"
},
  "geometry": {"coordinates":[-74.54016799999999,40.838824],"type":"Point"}
}