{
  "type": "Feature",
  "properties": {
    "iso:country":"US",
    "sg:address":"48 Evergreen Dr",
    "sg:city":"Ocean View",
    "sg:classifiers":[
        {
            "category":"Building & Trades",
            "subcategory":"Landscaping Services",
            "type":"Services"
        }
    ],
    "sg:phone":"+1 609 390 8559",
    "sg:postcode":"08230",
    "sg:province":"NJ",
    "sg:tags":[
        "landscape",
        "contractor"
    ],
    "wof:name":"Rainmaker Lawn Irrigation",
    "wof:placetype":"venue"
},
  "geometry": {"coordinates":[-74.693592,39.231325],"type":"Point"}
}