{
  "type": "Feature",
  "properties": {
    "iso:country":"US",
    "sg:address":"329 Elbo Ln",
    "sg:city":"Mount Laurel",
    "sg:classifiers":[
        {
            "category":"Manufacturing",
            "subcategory":"Printing",
            "type":"Manufacturing & Wholesale Goods"
        }
    ],
    "sg:phone":"+1 866 727 3483",
    "sg:postcode":"08054",
    "sg:province":"NJ",
    "sg:tags":[
        "commercial"
    ],
    "wof:name":"Play A Round LLC",
    "wof:placetype":"venue"
},
  "geometry": {"coordinates":[-74.88601800000001,39.929761],"type":"Point"}
}