{
  "type": "Feature",
  "properties": {
    "iso:country":"US",
    "sg:address":"18 Horseshoe Bend Rd",
    "sg:city":"Mendham",
    "sg:classifiers":[
        {
            "category":"Professional",
            "type":"Services"
        }
    ],
    "sg:phone":"+1   ",
    "sg:postcode":"07945",
    "sg:province":"NJ",
    "wof:name":"N Andrew Baker",
    "wof:placetype":"venue"
},
  "geometry": {"coordinates":[-74.589602,40.754208],"type":"Point"}
}