{
  "type": "Feature",
  "properties": {
    "iso:country":"US",
    "sg:address":"43 Washington Pl",
    "sg:city":"Somerville",
    "sg:classifiers":[
        {
            "category":"Building & Trades",
            "subcategory":"Plumbing",
            "type":"Services"
        }
    ],
    "sg:phone":"+1 908 295 7827",
    "sg:postcode":"08876",
    "sg:province":"NJ",
    "sg:tags":[
        "contractor"
    ],
    "wof:name":"J E Service",
    "wof:placetype":"venue"
},
  "geometry": {"coordinates":[-74.622333,40.568688],"type":"Point"}
}