{
  "type": "Feature",
  "properties": {
    "addr:full":"1512 Middlesex St Toms River NJ 08757",
    "addr:housenumber":"1512",
    "addr:postcode":"08757",
    "addr:street":"Middlesex St",
    "iso:country":"US",
    "sg:address":"1512 Middlesex St",
    "sg:city":"Toms River",
    "sg:classifiers":[
        {
            "category":"Arts & Performance",
            "subcategory":"Theater",
            "type":"Entertainment"
        }
    ],
    "sg:phone":"+1 732 914 0406",
    "sg:postcode":"08757",
    "sg:province":"NJ",
    "sg:tags":[
        "entertainer",
        "family"
    ],
    "wof:name":"N J Pony Rides",
    "wof:placetype":"venue"
},
  "geometry": {"coordinates":[-74.264977,40.004422],"type":"Point"}
}