{
  "type": "Feature",
  "properties": {
    "addr:full":"262 S Main St Flemington NJ 08822",
    "addr:housenumber":"262",
    "addr:postcode":"08822",
    "addr:street":"S Main St",
    "iso:country":"US",
    "sg:address":"262 S Main St",
    "sg:city":"Flemington",
    "sg:classifiers":[
        {
            "category":"Organizations",
            "subcategory":"Religious Organization",
            "type":"Services"
        }
    ],
    "sg:phone":"+1 908 782 6608",
    "sg:postcode":"08822",
    "sg:province":"NJ",
    "wof:name":"Calvary Baptist Church",
    "wof:placetype":"venue"
},
  "geometry": {"coordinates":[-74.861744,40.497362],"type":"Point"}
}