{
  "type": "Feature",
  "properties": {
    "addr:full":"230 E Montgomery Ave Wildwood NJ 08260",
    "addr:housenumber":"230",
    "addr:postcode":"08260",
    "addr:street":"E Montgomery Ave",
    "iso:country":"US",
    "sg:address":"230 E Montgomery Ave",
    "sg:city":"Wildwood",
    "sg:classifiers":[
        {
            "category":"Real Estate",
            "subcategory":"Real Estate Operator",
            "type":"Services"
        }
    ],
    "sg:phone":"+1 609 729 5441",
    "sg:postcode":"08260",
    "sg:province":"NJ",
    "sg:tags":[
        "apartment"
    ],
    "wof:name":"Montgomery Manor",
    "wof:placetype":"venue"
},
  "geometry": {"coordinates":[-74.818929,38.984216],"type":"Point"}
}