{
  "type": "Feature",
  "properties": {
    "iso:country":"US",
    "sg:address":"57 Cornell Dr",
    "sg:city":"Riverside",
    "sg:classifiers":[
        {
            "category":"Personal",
            "type":"Services"
        }
    ],
    "sg:phone":"+1   ",
    "sg:postcode":"08075",
    "sg:province":"NJ",
    "sg:tags":[
        "handyman"
    ],
    "wof:name":"Johns Handyman",
    "wof:placetype":"venue"
},
  "geometry": {"coordinates":[-74.94606,40.007575],"type":"Point"}
}