{
  "type": "Feature",
  "properties": {
    "addr:full":"4204 Harbor Beach Blvd Brigantine NJ 08203",
    "addr:housenumber":"4204",
    "addr:postcode":"08203",
    "addr:street":"Harbor Beach Blvd",
    "iso:country":"US",
    "sg:address":"4204 Harbor Beach Blvd",
    "sg:city":"Brigantine",
    "sg:classifiers":[
        {
            "category":"Arts & Performance",
            "subcategory":"Theater",
            "type":"Entertainment"
        }
    ],
    "sg:phone":"+1 609 266 1099",
    "sg:postcode":"08203",
    "sg:province":"NJ",
    "sg:tags":[
        "live",
        "music"
    ],
    "wof:name":"Above & Beyond DJ Entrtn",
    "wof:placetype":"venue"
},
  "geometry": {"coordinates":[-74.397913,39.394141],"type":"Point"}
}