{
  "type": "Feature",
  "properties": {
    "iso:country":"US",
    "sg:address":"1511 W State St",
    "sg:city":"Trenton",
    "sg:classifiers":[
        {
            "category":"Utilities",
            "subcategory":"Fuel Oil & Lpg",
            "type":"Services"
        }
    ],
    "sg:phone":"+1 609 394 1069",
    "sg:postcode":"08618",
    "sg:province":"NJ",
    "sg:tags":[
        "equipment",
        "system",
        "heating"
    ],
    "wof:name":"Joe Brown Fuel Oil",
    "wof:placetype":"venue"
},
  "geometry": {"coordinates":[-74.798338,40.235899],"type":"Point"}
}