{
  "type": "Feature",
  "properties": {
    "addr:full":"26 Oberlin St Maplewood NJ 07040",
    "addr:housenumber":"26",
    "addr:postcode":"07040",
    "addr:street":"Oberlin St",
    "iso:country":"US",
    "sg:address":"26 Oberlin St",
    "sg:city":"Maplewood",
    "sg:classifiers":[
        {
            "category":"Professional",
            "subcategory":"Business Services",
            "type":"Services"
        }
    ],
    "sg:phone":"+1   ",
    "sg:postcode":"07040",
    "sg:province":"NJ",
    "wof:name":"Inprints NY LLC",
    "wof:placetype":"venue"
},
  "geometry": {"coordinates":[-74.26651099999999,40.724349],"type":"Point"}
}