{
  "type": "Feature",
  "properties": {
    "addr:full":"133 Royal Dr Brick NJ 08723",
    "addr:housenumber":"133",
    "addr:postcode":"08723",
    "addr:street":"Royal Dr",
    "iso:country":"US",
    "sg:address":"133 Royal Dr",
    "sg:city":"Brick",
    "sg:classifiers":[
        {
            "category":"Professional",
            "subcategory":"Accounting & Tax Preparation",
            "type":"Services"
        }
    ],
    "sg:phone":"+1 732 262 0734",
    "sg:postcode":"08723",
    "sg:province":"NJ",
    "wof:name":"Stanley J Kryla CPA",
    "wof:placetype":"venue"
},
  "geometry": {"coordinates":[-74.117408,40.02789],"type":"Point"}
}