{
  "type": "Feature",
  "properties": {
    "iso:country":"US",
    "sg:address":"708 Baltimore Blvd",
    "sg:city":"Sea Girt",
    "sg:classifiers":[
        {
            "category":"Professional",
            "subcategory":"Management & Consulting",
            "type":"Services"
        }
    ],
    "sg:phone":"+1   ",
    "sg:postcode":"08750",
    "sg:province":"NJ",
    "sg:tags":[
        "business"
    ],
    "wof:name":"Fusco Associates",
    "wof:placetype":"venue"
},
  "geometry": {"coordinates":[-74.04459199999999,40.134762],"type":"Point"}
}