{
  "type": "Feature",
  "properties": {
    "addr:full":"104 Hudson St Hoboken NJ 07030",
    "addr:housenumber":"104",
    "addr:postcode":"07030",
    "addr:street":"Hudson St",
    "iso:country":"US",
    "sg:address":"104 Hudson St",
    "sg:city":"Hoboken",
    "sg:classifiers":[
        {
            "category":"Professional",
            "subcategory":"Business Services",
            "type":"Services"
        }
    ],
    "sg:phone":"+1 201 795 1878",
    "sg:postcode":"07030",
    "sg:province":"NJ",
    "sg:tags":[
        "recording",
        "studio"
    ],
    "wof:name":"Vinvarg Recording",
    "wof:placetype":"venue"
},
  "geometry": {"coordinates":[-74.02948600000001,40.738492],"type":"Point"}
}