{
  "type": "Feature",
  "properties": {
    "iso:country":"US",
    "sg:address":"723 Haddon Ave",
    "sg:city":"Collingswood",
    "sg:classifiers":[
        {
            "category":"Shopping",
            "subcategory":"Music",
            "type":"Retail Goods"
        }
    ],
    "sg:phone":"+1   ",
    "sg:postcode":"08108",
    "sg:province":"NJ",
    "wof:name":"Abbie Road New and Used Cds",
    "wof:placetype":"venue"
},
  "geometry": {"coordinates":[-75.068218,39.916152],"type":"Point"}
}