{
  "type": "Feature",
  "properties": {
    "iso:country":"US",
    "sg:address":"32 Montvale Ave",
    "sg:city":"Montvale",
    "sg:classifiers":[
        {
            "category":"Professional",
            "subcategory":"Business Services",
            "type":"Services"
        }
    ],
    "sg:phone":"+1   ",
    "sg:postcode":"07645",
    "sg:province":"NJ",
    "wof:name":"Studio 3",
    "wof:placetype":"venue"
},
  "geometry": {"coordinates":[-74.026044,41.046825],"type":"Point"}
}