{
  "type": "Feature",
  "properties": {
    "addr:full":"51 Railroad Ave Ste 5 Closter NJ 07624",
    "addr:housenumber":"51",
    "addr:postcode":"07624",
    "addr:street":"Railroad Ave Ste 5",
    "iso:country":"US",
    "sg:address":"51 Railroad Ave Ste 5",
    "sg:city":"Closter",
    "sg:classifiers":[
        {
            "category":"Building & Trades",
            "subcategory":"Plumbing",
            "type":"Services"
        },
        {
            "category":"Building & Trades",
            "subcategory":"Construction",
            "type":"Services"
        }
    ],
    "sg:phone":"+1 201 767 1192",
    "sg:postcode":"07624",
    "sg:province":"NJ",
    "sg:tags":[
        "plumber",
        "industrial",
        "system",
        "specialty",
        "heating",
        "contractors-commercial",
        "mechanical",
        "contractor",
        "air conditioning"
    ],
    "sg:website":"http://www.interstatemechanicalservices.com",
    "wof:name":"Interstate Mechanical Services Inc.",
    "wof:placetype":"venue"
},
  "geometry": {"coordinates":[-73.960718,40.977301],"type":"Point"}
}