{
  "type": "Feature",
  "properties": {
    "iso:country":"US",
    "sg:address":"1431 State Rte 23",
    "sg:city":"Wayne",
    "sg:classifiers":[
        {
            "category":"Autos & Motor Vehicles",
            "subcategory":"Fuel & Gas Station",
            "type":"Retail Goods"
        }
    ],
    "sg:phone":"+1   ",
    "sg:postcode":"07470",
    "sg:province":"NJ",
    "sg:tags":[
        "station",
        "gasoline"
    ],
    "wof:name":"J & L Service Center Inc",
    "wof:placetype":"venue"
},
  "geometry": {"coordinates":[-74.26822799999999,40.924735],"type":"Point"}
}