{
  "type": "Feature",
  "properties": {
    "iso:country":"US",
    "sg:address":"87 Overlook Dr",
    "sg:city":"Woodcliff Lake",
    "sg:classifiers":[
        {
            "category":"Education",
            "subcategory":"School",
            "type":"Public Place"
        }
    ],
    "sg:phone":"+1 201 391 8323",
    "sg:postcode":"07677",
    "sg:province":"NJ",
    "wof:name":"Hebrew School",
    "wof:placetype":"venue"
},
  "geometry": {"coordinates":[-74.070041,41.019362],"type":"Point"}
}