{
  "type": "Feature",
  "properties": {
    "iso:country":"US",
    "sg:address":"517 Hollywood Ave",
    "sg:city":"Toms River",
    "sg:classifiers":[
        {
            "category":"Health Services",
            "subcategory":"Doctor",
            "type":"Services"
        }
    ],
    "sg:phone":"+1 732 349 2067",
    "sg:postcode":"08753",
    "sg:province":"NJ",
    "sg:tags":[
        "physician",
        "surgeon"
    ],
    "wof:name":"Edward D Fiore MD",
    "wof:placetype":"venue"
},
  "geometry": {"coordinates":[-74.174165,39.954125],"type":"Point"}
}