{
  "type": "Feature",
  "properties": {
    "addr:full":"474 Burke Rd Jackson NJ 08527",
    "addr:housenumber":"474",
    "addr:postcode":"08527",
    "addr:street":"Burke Rd",
    "iso:country":"US",
    "sg:address":"474 Burke Rd",
    "sg:city":"Jackson",
    "sg:classifiers":[
        {
            "category":"Organizations",
            "subcategory":"Religious Organization",
            "type":"Services"
        }
    ],
    "sg:phone":"+1 732 780 3158",
    "sg:postcode":"08527",
    "sg:province":"NJ",
    "sg:tags":[
        "church"
    ],
    "wof:name":"St Paul Apostle Orthodox Chr",
    "wof:placetype":"venue"
},
  "geometry": {"coordinates":[-74.381844,40.140694],"type":"Point"}
}