{
  "type": "Feature",
  "properties": {
    "addr:full":"202 Main Ave Clifton NJ 07014",
    "addr:housenumber":"202",
    "addr:postcode":"07014",
    "addr:street":"Main Ave",
    "iso:country":"US",
    "sg:address":"202 Main Ave",
    "sg:city":"Clifton",
    "sg:classifiers":[
        {
            "category":"Health Services",
            "subcategory":"Health Practitioner",
            "type":"Services"
        }
    ],
    "sg:phone":"+1 973 777 3301",
    "sg:postcode":"07014",
    "sg:province":"NJ",
    "sg:tags":[
        "therapy",
        "physical"
    ],
    "wof:name":"Miles Square Physical Therapy",
    "wof:placetype":"venue"
},
  "geometry": {"coordinates":[-74.138755,40.833403],"type":"Point"}
}