{
  "type": "Feature",
  "properties": {
    "iso:country":"US",
    "sg:address":"43 Palfrey Ln",
    "sg:city":"Willingboro",
    "sg:classifiers":[
        {
            "category":"Professional",
            "subcategory":"Management & Consulting",
            "type":"Services"
        }
    ],
    "sg:phone":"+1 609 835 1177",
    "sg:postcode":"08046",
    "sg:province":"NJ",
    "sg:tags":[
        "business"
    ],
    "wof:name":"Shelton Educational Entps",
    "wof:placetype":"venue"
},
  "geometry": {"coordinates":[-74.90055099999999,40.035032],"type":"Point"}
}