{
  "type": "Feature",
  "properties": {
    "iso:country":"US",
    "sg:address":"70 Clinton Ave",
    "sg:city":"Newark",
    "sg:classifiers":[
        {
            "category":"Professional",
            "subcategory":"Lawyer & Legal Services",
            "type":"Services"
        }
    ],
    "sg:phone":"+1 973 642 7655",
    "sg:postcode":"07114",
    "sg:province":"NJ",
    "wof:name":"Jones Hirsch Connors & Bull PC",
    "wof:placetype":"venue"
},
  "geometry": {"coordinates":[-74.181172,40.725704],"type":"Point"}
}