{
  "type": "Feature",
  "properties": {
    "iso:country":"US",
    "sg:address":"178 Tamarack Cir",
    "sg:city":"Skillman",
    "sg:classifiers":[
        {
            "category":"Health Services",
            "subcategory":"Health Practitioner",
            "type":"Services"
        }
    ],
    "sg:phone":"+1 609 683 5064",
    "sg:postcode":"08558",
    "sg:province":"NJ",
    "wof:name":"Nathan Schwartz-Salant PHD",
    "wof:placetype":"venue"
},
  "geometry": {"coordinates":[-74.64887,40.408593],"type":"Point"}
}