{
  "type": "Feature",
  "properties": {
    "addr:full":"32 Johnston Dr Watchung NJ 07069",
    "addr:housenumber":"32",
    "addr:postcode":"07069",
    "addr:street":"Johnston Dr",
    "iso:country":"US",
    "sg:address":"32 Johnston Dr",
    "sg:city":"Watchung",
    "sg:classifiers":[
        {
            "category":"Health Services",
            "subcategory":"Health Practitioner",
            "type":"Services"
        }
    ],
    "sg:phone":"+1 908 757 4921",
    "sg:postcode":"07069",
    "sg:province":"NJ",
    "sg:tags":[
        "psychologist"
    ],
    "wof:name":"Plainfield Consultation Center",
    "wof:placetype":"venue"
},
  "geometry": {"coordinates":[-74.441312,40.629606],"type":"Point"}
}