{
  "type": "Feature",
  "properties": {
    "addr:full":"24 Cokesbury Rd Lebanon NJ 08833",
    "addr:housenumber":"24",
    "addr:postcode":"08833",
    "addr:street":"Cokesbury Rd",
    "iso:country":"US",
    "sg:address":"24 Cokesbury Rd",
    "sg:city":"Lebanon",
    "sg:classifiers":[
        {
            "category":"Recreation",
            "type":"Entertainment"
        }
    ],
    "sg:phone":"+1   ",
    "sg:postcode":"08833",
    "sg:province":"NJ",
    "wof:name":"Aero Champion Gymnastic & Spt",
    "wof:placetype":"venue"
},
  "geometry": {"coordinates":[-74.834484,40.646684],"type":"Point"}
}