{
  "type": "Feature",
  "properties": {
    "iso:country":"US",
    "sg:address":"145 11th St",
    "sg:city":"Piscataway",
    "sg:classifiers":[
        {
            "category":"Manufacturing",
            "subcategory":"Tools & Machinery",
            "type":"Manufacturing & Wholesale Goods"
        }
    ],
    "sg:phone":"+1 732 424 1700",
    "sg:postcode":"08854",
    "sg:province":"NJ",
    "sg:tags":[
        "machine",
        "shop"
    ],
    "wof:name":"Millson Precision Machining",
    "wof:placetype":"venue"
},
  "geometry": {"coordinates":[-74.450256,40.580002],"type":"Point"}
}