{
  "type": "Feature",
  "properties": {
    "iso:country":"US",
    "sg:address":"1911 Rolling Ln",
    "sg:city":"Cherry Hill",
    "sg:classifiers":[
        {
            "category":"Professional",
            "type":"Services"
        }
    ],
    "sg:phone":"+1   ",
    "sg:postcode":"08003",
    "sg:province":"NJ",
    "wof:name":"Jamsco Inc",
    "wof:placetype":"venue"
},
  "geometry": {"coordinates":[-74.978889,39.865997],"type":"Point"}
}