{
  "type": "Feature",
  "properties": {
    "iso:country":"US",
    "sg:address":"596 Elder Ave",
    "sg:city":"Phillipsburg",
    "sg:phone":"+1 908 387 8383",
    "sg:postcode":"08865",
    "sg:province":"NJ",
    "wof:name":"Makoto Japanese Restaurant",
    "wof:placetype":"venue"
},
  "geometry": {"coordinates":[-75.183222,40.697353],"type":"Point"}
}