{
  "type": "Feature",
  "properties": {
    "iso:country":"US",
    "sg:address":"147 State Rte 37",
    "sg:city":"Toms River",
    "sg:classifiers":[
        {
            "category":"Health Services",
            "subcategory":"Doctor",
            "type":"Services"
        }
    ],
    "sg:phone":"+1 732 505 9227",
    "sg:postcode":"08755",
    "sg:province":"NJ",
    "sg:tags":[
        "medical"
    ],
    "wof:name":"Howard M Berger MD",
    "wof:placetype":"venue"
},
  "geometry": {"coordinates":[-74.219314,39.965834],"type":"Point"}
}