{
  "type": "Feature",
  "properties": {
    "iso:country":"US",
    "sg:address":"45 Lexington Ave",
    "sg:city":"Trenton",
    "sg:classifiers":[
        {
            "category":"Building & Trades",
            "subcategory":"Plumbing",
            "type":"Services"
        }
    ],
    "sg:phone":"+1 609 882 1164",
    "sg:postcode":"08618",
    "sg:province":"NJ",
    "sg:tags":[
        "contractor"
    ],
    "wof:name":"Williard Inc",
    "wof:placetype":"venue"
},
  "geometry": {"coordinates":[-74.791905,40.250941],"type":"Point"}
}