{
  "type": "Feature",
  "properties": {
    "addr:full":"5139 Bergenline Pl West New York NJ 07093",
    "addr:housenumber":"5139",
    "addr:postcode":"07093",
    "addr:street":"Bergenline Pl West",
    "iso:country":"US",
    "sg:address":"5139 Bergenline Pl",
    "sg:city":"West New York",
    "sg:classifiers":[
        {
            "category":"Shopping",
            "subcategory":"Computers & Home Electronics",
            "type":"Retail Goods"
        }
    ],
    "sg:phone":"+1   ",
    "sg:postcode":"07093",
    "sg:province":"NJ",
    "wof:name":"Camera & Cellular City",
    "wof:placetype":"venue"
},
  "geometry": {"coordinates":[-74.02043399999999,40.783411],"type":"Point"}
}