{
  "type": "Feature",
  "properties": {
    "addr:full":"19 Woodland Ave Glen Ridge NJ 07028",
    "addr:housenumber":"19",
    "addr:postcode":"07028",
    "addr:street":"Woodland Ave",
    "iso:country":"US",
    "sg:address":"19 Woodland Ave",
    "sg:city":"Glen Ridge",
    "sg:classifiers":[
        {
            "category":"Professional",
            "type":"Services"
        }
    ],
    "sg:phone":"+1   ",
    "sg:postcode":"07028",
    "sg:province":"NJ",
    "wof:name":"Trusty Tree Service",
    "wof:placetype":"venue"
},
  "geometry": {"coordinates":[-74.20747799999999,40.801832],"type":"Point"}
}