{
  "type": "Feature",
  "properties": {
    "iso:country":"US",
    "sg:address":"516 River St",
    "sg:city":"Hackensack",
    "sg:classifiers":[
        {
            "category":"Autos & Motor Vehicles",
            "subcategory":"Automobile Sales",
            "type":"Retail Goods"
        },
        {
            "category":"Autos & Motor Vehicles",
            "subcategory":"Motorcycle Sales",
            "type":"Retail Goods"
        },
        {
            "category":"Retail",
            "subcategory":"Auto Repair",
            "type":"Services"
        }
    ],
    "sg:phone":"+1 201 487 6700",
    "sg:postcode":"07601",
    "sg:province":"NJ",
    "sg:tags":[
        "car"
    ],
    "wof:name":"All American Ford Inc",
    "wof:placetype":"venue"
},
  "geometry": {"coordinates":[-74.0382,40.894901],"type":"Point"}
}