{
  "type": "Feature",
  "properties": {
    "addr:full":"508 North Ave Union NJ 07083",
    "addr:housenumber":"508",
    "addr:postcode":"07083",
    "addr:street":"North Ave",
    "iso:country":"US",
    "sg:address":"508 North Ave",
    "sg:city":"Union",
    "sg:classifiers":[
        {
            "category":"Retail",
            "subcategory":"Auto Repair",
            "type":"Services"
        }
    ],
    "sg:phone":"+1 908 354 0889",
    "sg:postcode":"07083",
    "sg:province":"NJ",
    "sg:tags":[
        "repairing",
        "automobile"
    ],
    "wof:name":"Torres Auto Repair",
    "wof:placetype":"venue"
},
  "geometry": {"coordinates":[-74.230974,40.672095],"type":"Point"}
}