{
  "type": "Feature",
  "properties": {
    "addr:full":"19 Wildflower Trl Robbinsville NJ 08691",
    "addr:housenumber":"19",
    "addr:postcode":"08691",
    "addr:street":"Wildflower Trl",
    "iso:country":"US",
    "sg:address":"19 Wildflower Trl",
    "sg:city":"Robbinsville",
    "sg:classifiers":[
        {
            "category":"Professional",
            "subcategory":"Management & Consulting",
            "type":"Services"
        }
    ],
    "sg:phone":"+1 609 426 0110",
    "sg:postcode":"08691",
    "sg:province":"NJ",
    "sg:tags":[
        "consultant",
        "business"
    ],
    "wof:name":"BTD Inc",
    "wof:placetype":"venue"
},
  "geometry": {"coordinates":[-74.599192,40.233059],"type":"Point"}
}