{
  "type": "Feature",
  "properties": {
    "iso:country":"US",
    "sg:address":"139 Harristown Rd",
    "sg:city":"Glen Rock",
    "sg:classifiers":[
        {
            "category":"Building & Trades",
            "subcategory":"Construction",
            "type":"Services"
        }
    ],
    "sg:phone":"+1 201 612 7772",
    "sg:postcode":"07452",
    "sg:province":"NJ",
    "sg:tags":[
        "caulking",
        "contractor"
    ],
    "wof:name":"Raven Restoration & Waterproof",
    "wof:placetype":"venue"
},
  "geometry": {"coordinates":[-74.139864,40.951049],"type":"Point"}
}