{
  "type": "Feature",
  "properties": {
    "addr:full":"83 Woodport Rd Sparta NJ 07871",
    "addr:housenumber":"83",
    "addr:postcode":"07871",
    "addr:street":"Woodport Rd",
    "iso:country":"US",
    "sg:address":"83 Woodport Rd",
    "sg:city":"Sparta",
    "sg:classifiers":[
        {
            "category":"Personal",
            "subcategory":"Beauty Salon",
            "type":"Services"
        }
    ],
    "sg:phone":"+1 973 729 4417",
    "sg:postcode":"07871",
    "sg:province":"NJ",
    "sg:tags":[
        "manicuring"
    ],
    "wof:name":"Anna Beth's Aesthetics LLC",
    "wof:placetype":"venue"
},
  "geometry": {"coordinates":[-74.637365,41.031401],"type":"Point"}
}