{
  "type": "Feature",
  "properties": {
    "addr:full":"500 Ocean Ave North Wildwood NJ 08260",
    "addr:housenumber":"500",
    "addr:postcode":"08260",
    "addr:street":"Ocean Ave North",
    "iso:country":"US",
    "sg:address":"500 Ocean Ave",
    "sg:city":"North Wildwood",
    "sg:classifiers":[
        {
            "category":"Travel",
            "subcategory":"Hotels & Motels",
            "type":"Entertainment"
        }
    ],
    "sg:phone":"+1 609 522 1991",
    "sg:postcode":"08260",
    "sg:province":"NJ",
    "wof:name":"Isle Of Capri Motel",
    "wof:placetype":"venue"
},
  "geometry": {"coordinates":[-74.790311,39.001165],"type":"Point"}
}