{
  "type": "Feature",
  "properties": {
    "addr:full":"107 Church St Fair Haven NJ 07704",
    "addr:housenumber":"107",
    "addr:postcode":"07704",
    "addr:street":"Church St",
    "iso:country":"US",
    "sg:address":"107 Church St",
    "sg:city":"Fair Haven",
    "sg:classifiers":[
        {
            "category":"Health Services",
            "subcategory":"Clinic",
            "type":"Services"
        },
        {
            "category":"Social Services",
            "type":"Services"
        }
    ],
    "sg:phone":"+1 732 933 4011",
    "sg:postcode":"07704",
    "sg:province":"NJ",
    "sg:tags":[
        "instruction",
        "care"
    ],
    "wof:name":"Nature's Garden Of Health",
    "wof:placetype":"venue"
},
  "geometry": {"coordinates":[-74.03327400000001,40.359404],"type":"Point"}
}