{
  "type": "Feature",
  "properties": {
    "addr:full":"125 State St Hackensack NJ 07601",
    "addr:housenumber":"125",
    "addr:postcode":"07601",
    "addr:street":"State St",
    "iso:country":"US",
    "sg:address":"125 State St",
    "sg:city":"Hackensack",
    "sg:classifiers":[
        {
            "category":"Professional",
            "subcategory":"Lawyer & Legal Services",
            "type":"Services"
        }
    ],
    "sg:phone":"+1 201 342 7686",
    "sg:postcode":"07601",
    "sg:province":"NJ",
    "sg:tags":[
        "divorce",
        "law",
        "family"
    ],
    "wof:name":"Powers Michael J Attorney",
    "wof:placetype":"venue"
},
  "geometry": {"coordinates":[-74.045502,40.882401],"type":"Point"}
}