{
  "type": "Feature",
  "properties": {
    "iso:country":"US",
    "sg:address":"535 Bowling Green",
    "sg:city":"Moorestown",
    "sg:classifiers":[
        {
            "category":"Professional",
            "subcategory":"Management & Consulting",
            "type":"Services"
        }
    ],
    "sg:phone":"+1 856 222 1098",
    "sg:postcode":"08057",
    "sg:province":"NJ",
    "sg:tags":[
        "consultant"
    ],
    "wof:name":"Sales Imperative",
    "wof:placetype":"venue"
},
  "geometry": {"coordinates":[-74.96626500000001,39.960549],"type":"Point"}
}