{
  "type": "Feature",
  "properties": {
    "addr:full":"55 Fairview Ave Long Valley NJ 07853",
    "addr:housenumber":"55",
    "addr:postcode":"07853",
    "addr:street":"Fairview Ave",
    "iso:country":"US",
    "sg:address":"55 Fairview Ave",
    "sg:city":"Long Valley",
    "sg:classifiers":[
        {
            "category":"Museum",
            "type":"Entertainment"
        }
    ],
    "sg:phone":"+1 908 876 9696",
    "sg:postcode":"07853",
    "sg:province":"NJ",
    "wof:name":"Washington Township Historical Society",
    "wof:placetype":"venue"
},
  "geometry": {"coordinates":[-74.778702,40.787701],"type":"Point"}
}