{
  "type": "Feature",
  "properties": {
    "iso:country":"US",
    "sg:address":"95 Belleville Ave",
    "sg:city":"Bloomfield",
    "sg:classifiers":[
        {
            "category":"Building & Trades",
            "subcategory":"Construction",
            "type":"Services"
        }
    ],
    "sg:phone":"+1 973 680 4230",
    "sg:postcode":"07003",
    "sg:province":"NJ",
    "sg:tags":[
        "residential",
        "commercial"
    ],
    "wof:name":"Mpb Construction Corp",
    "wof:placetype":"venue"
},
  "geometry": {"coordinates":[-74.183463,40.797883],"type":"Point"}
}