{
  "type": "Feature",
  "properties": {
    "iso:country":"US",
    "sg:address":"471 21st Ave",
    "sg:city":"Paterson",
    "sg:classifiers":[
        {
            "category":"Personal",
            "subcategory":"Beauty Salon",
            "type":"Services"
        }
    ],
    "sg:phone":"+1 973 684 9356",
    "sg:postcode":"07513",
    "sg:province":"NJ",
    "sg:tags":[
        "shop"
    ],
    "wof:name":"Community Hair Fashions",
    "wof:placetype":"venue"
},
  "geometry": {"coordinates":[-74.153239,40.906278],"type":"Point"}
}