{
  "type": "Feature",
  "properties": {
    "addr:full":"277 S Orange Ave Newark NJ 07103",
    "addr:housenumber":"277",
    "addr:postcode":"07103",
    "addr:street":"S Orange Ave",
    "iso:country":"US",
    "sg:address":"277 S Orange Ave",
    "sg:city":"Newark",
    "sg:classifiers":[
        {
            "category":"Manufacturing",
            "subcategory":"Printing",
            "type":"Manufacturing & Wholesale Goods"
        }
    ],
    "sg:phone":"+1 973 273 1166",
    "sg:postcode":"07103",
    "sg:province":"NJ",
    "sg:tags":[
        "commercial"
    ],
    "wof:name":"Jersey Flyers II",
    "wof:placetype":"venue"
},
  "geometry": {"coordinates":[-74.195595,40.739267],"type":"Point"}
}