{
  "type": "Feature",
  "properties": {
    "addr:full":"173 State Rte 37 Toms River NJ 08755",
    "addr:housenumber":"173",
    "addr:postcode":"08755",
    "addr:street":"State Rte 37",
    "iso:country":"US",
    "sg:address":"173 State Rte 37",
    "sg:city":"Toms River",
    "sg:classifiers":[
        {
            "category":"Banks & Credit Unions",
            "subcategory":"Investment Brokerage",
            "type":"Services"
        }
    ],
    "sg:phone":"+1 732 505 8443",
    "sg:postcode":"08755",
    "sg:province":"NJ",
    "sg:tags":[
        "security"
    ],
    "wof:name":"Edward Jones Co",
    "wof:placetype":"venue"
},
  "geometry": {"coordinates":[-74.220967,39.966026],"type":"Point"}
}