{
  "type": "Feature",
  "properties": {
    "addr:full":"334 Bloomfield Ave Ste A Newark NJ 07107",
    "addr:housenumber":"334",
    "addr:postcode":"07107",
    "addr:street":"Bloomfield Ave Ste A",
    "iso:country":"US",
    "sg:address":"334 Bloomfield Ave Ste A",
    "sg:city":"Newark",
    "sg:classifiers":[
        {
            "category":"Restaurant",
            "type":"Food & Drink"
        }
    ],
    "sg:phone":"+1 973 481 6664",
    "sg:postcode":"07107",
    "sg:province":"NJ",
    "sg:tags":[
        "chinese"
    ],
    "wof:name":"Imperial Restaurant",
    "wof:placetype":"venue"
},
  "geometry": {"coordinates":[-74.180832,40.7665],"type":"Point"}
}