{
  "type": "Feature",
  "properties": {
    "addr:full":"48 W Railroad Ave Tenafly NJ 07670",
    "addr:housenumber":"48",
    "addr:postcode":"07670",
    "addr:street":"W Railroad Ave",
    "iso:country":"US",
    "sg:address":"48 W Railroad Ave",
    "sg:city":"Tenafly",
    "sg:classifiers":[
        {
            "category":"Building & Trades",
            "subcategory":"Electrical",
            "type":"Services"
        }
    ],
    "sg:phone":"+1 201 227 8100",
    "sg:postcode":"07670",
    "sg:province":"NJ",
    "sg:tags":[
        "electrical",
        "contractor"
    ],
    "wof:name":"J & A Electrical Contractors L",
    "wof:placetype":"venue"
},
  "geometry": {"coordinates":[-73.964145,40.927961],"type":"Point"}
}