{
  "type": "Feature",
  "properties": {
    "iso:country":"US",
    "sg:address":"300 2nd Ave",
    "sg:city":"Haddon Heights",
    "sg:classifiers":[
        {
            "category":"Education",
            "subcategory":"School",
            "type":"Public Place"
        }
    ],
    "sg:phone":"+1 856 547 1412",
    "sg:postcode":"08035",
    "sg:province":"NJ",
    "sg:tags":[
        "high",
        "middle",
        "elementary"
    ],
    "wof:name":"Haddon Heights School District",
    "wof:placetype":"venue"
},
  "geometry": {"coordinates":[-75.05161200000001,39.88404],"type":"Point"}
}