{
  "type": "Feature",
  "properties": {
    "iso:country":"US",
    "sg:address":"200 Fairfield Ave",
    "sg:city":"West Caldwell",
    "sg:classifiers":[
        {
            "category":"Building & Trades",
            "subcategory":"Locksmith",
            "type":"Services"
        }
    ],
    "sg:phone":"+1 888 271 6803",
    "sg:postcode":"07006",
    "sg:province":"NJ",
    "sg:tags":[
        "key"
    ],
    "wof:name":"24 Emergency Locksmith",
    "wof:placetype":"venue"
},
  "geometry": {"coordinates":[-74.28442,40.860497],"type":"Point"}
}