{
  "type": "Feature",
  "properties": {
    "iso:country":"US",
    "sg:address":"244 E Hanover St",
    "sg:city":"Trenton",
    "sg:classifiers":[
        {
            "category":"Professional",
            "type":"Services"
        }
    ],
    "sg:phone":"+1 609 392 8379",
    "sg:postcode":"08608",
    "sg:province":"NJ",
    "sg:tags":[
        "establishment"
    ],
    "wof:name":"Standard Office Systems",
    "wof:placetype":"venue"
},
  "geometry": {"coordinates":[-74.76074300000001,40.221478],"type":"Point"}
}