{
  "type": "Feature",
  "properties": {
    "iso:country":"US",
    "sg:address":"336 Dutch Neck Rd",
    "sg:city":"Hightstown",
    "sg:classifiers":[
        {
            "category":"Professional",
            "subcategory":"Computer Services",
            "type":"Services"
        }
    ],
    "sg:phone":"+1 609 334 9384",
    "sg:postcode":"08520",
    "sg:province":"NJ",
    "wof:name":"Masswell",
    "wof:placetype":"venue"
},
  "geometry": {"coordinates":[-74.554723,40.272123],"type":"Point"}
}