{
  "type": "Feature",
  "properties": {
    "iso:country":"US",
    "sg:address":"17 State Rte 208",
    "sg:city":"Fair Lawn",
    "sg:classifiers":[
        {
            "category":"Wholesale",
            "subcategory":"Machinery & Supplies",
            "type":"Manufacturing & Wholesale Goods"
        }
    ],
    "sg:phone":"+1 201 796 5445",
    "sg:postcode":"07410",
    "sg:province":"NJ",
    "sg:tags":[
        "machine",
        "tool"
    ],
    "sg:website":"www.tru-volute.com",
    "wof:name":"Russell Holbrook & Henderson",
    "wof:placetype":"venue"
},
  "geometry": {"coordinates":[-74.13148,40.944459],"type":"Point"}
}