{
  "type": "Feature",
  "properties": {
    "iso:country":"US",
    "sg:address":"179 Commerce Rd",
    "sg:city":"Carlstadt",
    "sg:classifiers":[
        {
            "category":"Manufacturing",
            "subcategory":"Glass & Minerals",
            "type":"Manufacturing & Wholesale Goods"
        },
        {
            "category":"Wholesale",
            "subcategory":"Metals & Minerals",
            "type":"Manufacturing & Wholesale Goods"
        }
    ],
    "sg:phone":"+1 201 804 1800",
    "sg:postcode":"07072",
    "sg:province":"NJ",
    "sg:tags":[
        "product",
        "ceramic",
        "center"
    ],
    "wof:name":"Certech  Inc",
    "wof:placetype":"venue"
},
  "geometry": {"coordinates":[-74.058243,40.829893],"type":"Point"}
}