{
  "type": "Feature",
  "properties": {
    "addr:full":"1302 Monmouth Rd Mount Holly NJ 08060",
    "addr:housenumber":"1302",
    "addr:postcode":"08060",
    "addr:street":"Monmouth Rd",
    "iso:country":"US",
    "sg:address":"1302 Monmouth Rd",
    "sg:city":"Mount Holly",
    "sg:classifiers":[
        {
            "category":"Personal",
            "subcategory":"Beauty Salon",
            "type":"Services"
        }
    ],
    "sg:phone":"+1   ",
    "sg:postcode":"08060",
    "sg:province":"NJ",
    "sg:tags":[
        "shop"
    ],
    "wof:name":"Hair Magic",
    "wof:placetype":"venue"
},
  "geometry": {"coordinates":[-74.746111,40.012567],"type":"Point"}
}