{
  "type": "Feature",
  "properties": {
    "addr:full":"34 Bernard Dr Trenton NJ 08628",
    "addr:housenumber":"34",
    "addr:postcode":"08628",
    "addr:street":"Bernard Dr",
    "iso:country":"US",
    "sg:address":"34 Bernard Dr",
    "sg:city":"Trenton",
    "sg:classifiers":[
        {
            "category":"Wholesale",
            "subcategory":"Stationery",
            "type":"Manufacturing & Wholesale Goods"
        }
    ],
    "sg:phone":"+1 609 882 6252",
    "sg:postcode":"08628",
    "sg:province":"NJ",
    "sg:tags":[
        "balloon",
        "novelty",
        "gift",
        "supply"
    ],
    "wof:name":"B & L Quik Check",
    "wof:placetype":"venue"
},
  "geometry": {"coordinates":[-74.841319,40.265697],"type":"Point"}
}