{
  "type": "Feature",
  "properties": {
    "addr:full":"1675 White Horse Hamilton Rd Trenton NJ 08690",
    "addr:housenumber":"1675",
    "addr:postcode":"08690",
    "addr:street":"White;Hamilton Rd",
    "iso:country":"US",
    "sg:address":"1675 White Horse Hamilton Rd",
    "sg:city":"Trenton",
    "sg:classifiers":[
        {
            "category":"Health Services",
            "subcategory":"Doctor",
            "type":"Services"
        }
    ],
    "sg:phone":"+1 609 587 9544",
    "sg:postcode":"08690",
    "sg:province":"NJ",
    "wof:name":"Martin L Kowalski DDS",
    "wof:placetype":"venue"
},
  "geometry": {"coordinates":[-74.68095099999999,40.211028],"type":"Point"}
}