{
  "type": "Feature",
  "properties": {
    "iso:country":"US",
    "sg:address":"720 Federal Ave",
    "sg:city":"Kenilworth",
    "sg:classifiers":[
        {
            "category":"Real Estate",
            "subcategory":"Real Estate Operator",
            "type":"Services"
        }
    ],
    "sg:phone":"+1   ",
    "sg:postcode":"07033",
    "sg:province":"NJ",
    "sg:tags":[
        "property",
        "lessor"
    ],
    "wof:name":"Jo Barb Inc",
    "wof:placetype":"venue"
},
  "geometry": {"coordinates":[-74.28732599999999,40.678577],"type":"Point"}
}