{
  "type": "Feature",
  "properties": {
    "addr:full":"370 North St Teterboro NJ 07608",
    "addr:housenumber":"370",
    "addr:postcode":"07608",
    "addr:street":"North St",
    "iso:country":"US",
    "sg:address":"370 North St",
    "sg:city":"Teterboro",
    "sg:classifiers":[
        {
            "category":"Restaurant",
            "type":"Food & Drink"
        }
    ],
    "sg:phone":"+1   ",
    "sg:postcode":"07608",
    "sg:province":"NJ",
    "sg:tags":[
        "industrial",
        "catering"
    ],
    "wof:name":"ATT Your Service Cafe",
    "wof:placetype":"venue"
},
  "geometry": {"coordinates":[-74.0579,40.867411],"type":"Point"}
}