{
  "type": "Feature",
  "properties": {
    "iso:country":"US",
    "sg:address":"34 Ridgedale Ave",
    "sg:city":"Morristown",
    "sg:classifiers":[
        {
            "category":"Autos & Motor Vehicles",
            "subcategory":"Automobile Sales",
            "type":"Retail Goods"
        }
    ],
    "sg:phone":"+1 212 819 9558",
    "sg:postcode":"07960",
    "sg:province":"NJ",
    "sg:tags":[
        "car"
    ],
    "wof:name":"Mercedes Benz Cumming Motors Authorized Dealer",
    "wof:placetype":"venue"
},
  "geometry": {"coordinates":[-74.470901,40.797001],"type":"Point"}
}