{
  "type": "Feature",
  "properties": {
    "addr:full":"44 Brunswick Woods Dr East Brunswick NJ 08816",
    "addr:housenumber":"44",
    "addr:postcode":"08816",
    "addr:street":"Brunswick Woods Dr",
    "iso:country":"US",
    "sg:address":"44 Brunswick Woods Dr",
    "sg:city":"East Brunswick",
    "sg:classifiers":[
        {
            "category":"Professional",
            "subcategory":"Computer Services",
            "type":"Services"
        }
    ],
    "sg:phone":"+1 732 846 5816",
    "sg:postcode":"08816",
    "sg:province":"NJ",
    "sg:tags":[
        "related"
    ],
    "wof:name":"Auric Systems Inc",
    "wof:placetype":"venue"
},
  "geometry": {"coordinates":[-74.391819,40.421238],"type":"Point"}
}