{
  "type": "Feature",
  "properties": {
    "iso:country":"US",
    "sg:address":"447 State Rte 10",
    "sg:city":"Randolph",
    "sg:classifiers":[
        {
            "category":"Health Services",
            "subcategory":"Doctor",
            "type":"Services"
        }
    ],
    "sg:phone":"+1 973 361 4555",
    "sg:postcode":"07869",
    "sg:province":"NJ",
    "sg:tags":[
        "physician",
        "surgeon",
        "religious",
        "medical",
        "organization"
    ],
    "wof:name":"Gautam Desai MD PA",
    "wof:placetype":"venue"
},
  "geometry": {"coordinates":[-74.564685,40.862825],"type":"Point"}
}