{
  "type": "Feature",
  "properties": {
    "addr:full":"85 Parlin Ln Watchung NJ 07069",
    "addr:housenumber":"85",
    "addr:postcode":"07069",
    "addr:street":"Parlin Ln",
    "iso:country":"US",
    "sg:address":"85 Parlin Ln",
    "sg:city":"Watchung",
    "sg:classifiers":[
        {
            "category":"Communications",
            "type":"Services"
        }
    ],
    "sg:phone":"+1 908 753 8453",
    "sg:postcode":"07069",
    "sg:province":"NJ",
    "sg:tags":[
        "data"
    ],
    "wof:name":"Lockline",
    "wof:placetype":"venue"
},
  "geometry": {"coordinates":[-74.44507900000001,40.654021],"type":"Point"}
}