{
  "type": "Feature",
  "properties": {
    "addr:full":"275 Market St Saddle Brook NJ 07663",
    "addr:housenumber":"275",
    "addr:postcode":"07663",
    "addr:street":"Market St",
    "iso:country":"US",
    "sg:address":"275 Market St",
    "sg:city":"Saddle Brook",
    "sg:classifiers":[
        {
            "category":"Insurance",
            "subcategory":"Insurance Agent",
            "type":"Services"
        }
    ],
    "sg:phone":"+1   ",
    "sg:postcode":"07663",
    "sg:province":"NJ",
    "wof:name":"State Farm Insurance",
    "wof:placetype":"venue"
},
  "geometry": {"coordinates":[-74.09192,40.896468],"type":"Point"}
}