{
  "type": "Feature",
  "properties": {
    "iso:country":"US",
    "sg:address":"19 Cloverhill Ln",
    "sg:city":"Freehold",
    "sg:classifiers":[
        {
            "category":"Autos & Motor Vehicles",
            "subcategory":"Automobile Sales",
            "type":"Retail Goods"
        }
    ],
    "sg:phone":"+1 732 462 3228",
    "sg:postcode":"07728",
    "sg:province":"NJ",
    "sg:tags":[
        "car",
        "dealer"
    ],
    "wof:name":"Wholesale Auto Group Inc",
    "wof:placetype":"venue"
},
  "geometry": {"coordinates":[-74.22363,40.254431],"type":"Point"}
}