{
  "type": "Feature",
  "properties": {
    "iso:country":"US",
    "sg:address":"94 Main St",
    "sg:city":"Butler",
    "sg:classifiers":[
        {
            "category":"Shopping",
            "subcategory":"Bicycles & Sporting Goods",
            "type":"Retail Goods"
        }
    ],
    "sg:phone":"+1 973 291 6405",
    "sg:postcode":"07405",
    "sg:province":"NJ",
    "wof:name":"Hiking Resupply",
    "wof:placetype":"venue"
},
  "geometry": {"coordinates":[-74.338061,41.002432],"type":"Point"}
}