{
  "type": "Feature",
  "properties": {
    "addr:full":"437 Bloy St Hillside NJ 07205",
    "addr:housenumber":"437",
    "addr:postcode":"07205",
    "addr:street":"Bloy St",
    "iso:country":"US",
    "sg:address":"437 Bloy St",
    "sg:city":"Hillside",
    "sg:classifiers":[
        {
            "category":"Food & Beverages",
            "subcategory":"Candy",
            "type":"Retail Goods"
        },
        {
            "category":"Banks & Credit Unions",
            "subcategory":"Bank",
            "type":"Services"
        }
    ],
    "sg:phone":"+1 908 964 4775",
    "sg:postcode":"07205",
    "sg:province":"NJ",
    "sg:tags":[
        "confectionery",
        "lottery",
        "money",
        "agent",
        "newsstand",
        "tobacconist",
        "order"
    ],
    "wof:name":"Phil's Candy Store",
    "wof:placetype":"venue"
},
  "geometry": {"coordinates":[-74.238506,40.699111],"type":"Point"}
}