{
  "type": "Feature",
  "properties": {
    "addr:full":"346 State Rte 7 Fanwood NJ 07031",
    "addr:housenumber":"346",
    "addr:postcode":"07031",
    "addr:street":"State Rte 7",
    "iso:country":"US",
    "sg:address":"346 State Rte 7",
    "sg:city":"Fanwood",
    "sg:classifiers":[
        {
            "category":"Health Services",
            "subcategory":"Doctor",
            "type":"Services"
        }
    ],
    "sg:phone":"+1 908 889 2020",
    "sg:postcode":"07031",
    "sg:province":"NJ",
    "wof:name":"William F Ricciani DDS PA",
    "wof:placetype":"venue"
},
  "geometry": {"coordinates":[-74.13454900000001,40.77972],"type":"Point"}
}