{
  "type": "Feature",
  "properties": {
    "addr:full":"42 Morris Ave Summit NJ 07901",
    "addr:housenumber":"42",
    "addr:postcode":"07901",
    "addr:street":"Morris Ave",
    "iso:country":"US",
    "sg:address":"42 Morris Ave",
    "sg:city":"Summit",
    "sg:classifiers":[
        {
            "category":"Autos & Motor Vehicles",
            "subcategory":"Fuel & Gas Station",
            "type":"Retail Goods"
        }
    ],
    "sg:phone":"+1 973 379 9873",
    "sg:postcode":"07901",
    "sg:province":"NJ",
    "sg:tags":[
        "oil"
    ],
    "wof:name":"Sunoco-Arch",
    "wof:placetype":"venue"
},
  "geometry": {"coordinates":[-74.341662,40.714053],"type":"Point"}
}