{
  "type": "Feature",
  "properties": {
    "iso:country":"US",
    "sg:address":"20 West Ave",
    "sg:city":"Atlantic Hghlnds",
    "sg:classifiers":[
        {
            "category":"Freight",
            "type":"Transportation"
        }
    ],
    "sg:phone":"+1 732 291 2034",
    "sg:postcode":"07716",
    "sg:province":"NJ",
    "sg:tags":[
        "commercial",
        "storage",
        "special"
    ],
    "wof:name":"Atlantic Self Storage LLC",
    "wof:placetype":"venue"
},
  "geometry": {"coordinates":[-74.041057,40.41063],"type":"Point"}
}