{
  "type": "Feature",
  "properties": {
    "addr:full":"15 Jefferson St Newton NJ 07882",
    "addr:housenumber":"15",
    "addr:postcode":"07882",
    "addr:street":"Jefferson St",
    "iso:country":"US",
    "sg:address":"15 Jefferson St",
    "sg:city":"Newton",
    "sg:classifiers":[
        {
            "category":"Wholesale",
            "subcategory":"Auto Parts",
            "type":"Manufacturing & Wholesale Goods"
        }
    ],
    "sg:phone":"+1 973 383 2110",
    "sg:postcode":"07882",
    "sg:province":"NJ",
    "sg:tags":[
        "body",
        "automotive"
    ],
    "wof:name":"Newton Auto Body",
    "wof:placetype":"venue"
},
  "geometry": {"coordinates":[-74.972004,40.760865],"type":"Point"}
}