{
  "type": "Feature",
  "properties": {
    "addr:full":"553 W Side Ave Jersey City NJ 07304",
    "addr:housenumber":"553",
    "addr:postcode":"07304",
    "addr:street":"W Side Ave",
    "iso:country":"US",
    "sg:address":"553 W Side Ave",
    "sg:city":"Jersey City",
    "sg:classifiers":[
        {
            "category":"Personal",
            "subcategory":"Beauty Salon",
            "type":"Services"
        }
    ],
    "sg:phone":"+1 201 432 2207",
    "sg:postcode":"07304",
    "sg:province":"NJ",
    "wof:name":"Diva's",
    "wof:placetype":"venue"
},
  "geometry": {"coordinates":[-74.08207299999999,40.720086],"type":"Point"}
}