{
  "type": "Feature",
  "properties": {
    "addr:full":"527 Commerce St Franklin Lakes NJ 07417",
    "addr:housenumber":"527",
    "addr:postcode":"07417",
    "addr:street":"Commerce St",
    "iso:country":"US",
    "sg:address":"527 Commerce St",
    "sg:city":"Franklin Lakes",
    "sg:classifiers":[
        {
            "category":"Manufacturing",
            "subcategory":"Tools & Machinery",
            "type":"Manufacturing & Wholesale Goods"
        }
    ],
    "sg:phone":"+1 201 337 1500",
    "sg:postcode":"07417",
    "sg:province":"NJ",
    "sg:tags":[
        "machine"
    ],
    "sg:website":"www.glebar.com",
    "wof:name":"Glebar Co",
    "wof:placetype":"venue"
},
  "geometry": {"coordinates":[-74.21587100000001,41.022001],"type":"Point"}
}