{
  "type": "Feature",
  "properties": {
    "addr:full":"761 Asbury Ave Ocean City NJ 08226",
    "addr:housenumber":"761",
    "addr:postcode":"08226",
    "addr:street":"Asbury Ave",
    "iso:country":"US",
    "sg:address":"761 Asbury Ave",
    "sg:city":"Ocean City",
    "sg:classifiers":[
        {
            "category":"Real Estate",
            "subcategory":"Real Estate Agent",
            "type":"Services"
        }
    ],
    "sg:phone":"+1 609 398 1700",
    "sg:postcode":"08226",
    "sg:province":"NJ",
    "wof:name":"James M Dwyer Real Estate",
    "wof:placetype":"venue"
},
  "geometry": {"coordinates":[-74.574077,39.280315],"type":"Point"}
}