{
  "type": "Feature",
  "properties": {
    "iso:country":"US",
    "sg:address":"7 Montclair Ave",
    "sg:city":"Montclair",
    "sg:classifiers":[
        {
            "category":"Building & Trades",
            "subcategory":"Plumbing",
            "type":"Services"
        }
    ],
    "sg:phone":"+1 973 744 4309",
    "sg:postcode":"07042",
    "sg:province":"NJ",
    "sg:tags":[
        "contractor"
    ],
    "wof:name":"L Russomanno Plumbing and Htg",
    "wof:placetype":"venue"
},
  "geometry": {"coordinates":[-74.207132,40.819184],"type":"Point"}
}