{
  "type": "Feature",
  "properties": {
    "iso:country":"US",
    "sg:address":"7 Leighton Pl",
    "sg:city":"Mahwah",
    "sg:classifiers":[
        {
            "category":"Health Services",
            "subcategory":"Health Practitioner",
            "type":"Services"
        }
    ],
    "sg:phone":"+1 201 818 1114",
    "sg:postcode":"07430",
    "sg:province":"NJ",
    "sg:tags":[
        "therapist",
        "physical"
    ],
    "sg:website":"www.questphysicaltherapy.com",
    "wof:name":"Physical Therapy & Sports Med",
    "wof:placetype":"venue"
},
  "geometry": {"coordinates":[-74.164604,41.024791],"type":"Point"}
}