{
  "type": "Feature",
  "properties": {
    "addr:full":"213 1st St Ho Ho Kus NJ 07423",
    "addr:housenumber":"213",
    "addr:postcode":"07423",
    "addr:street":"1St St",
    "iso:country":"US",
    "sg:address":"213 1st St",
    "sg:city":"Ho Ho Kus",
    "sg:classifiers":[
        {
            "category":"Professional",
            "type":"Services"
        }
    ],
    "sg:phone":"+1 201 689 6893",
    "sg:postcode":"07423",
    "sg:province":"NJ",
    "sg:tags":[
        "establishment"
    ],
    "wof:name":"Lusty Loom LTD",
    "wof:placetype":"venue"
},
  "geometry": {"coordinates":[-74.110011,40.996038],"type":"Point"}
}