{
  "type": "Feature",
  "properties": {
    "addr:full":"2900 Dune Dr Ste 6 Avalon NJ 08202",
    "addr:housenumber":"2900",
    "addr:postcode":"08202",
    "addr:street":"Dune Dr Ste 6",
    "iso:country":"US",
    "sg:address":"2900 Dune Dr Ste 6",
    "sg:city":"Avalon",
    "sg:classifiers":[
        {
            "category":"Arts & Performance",
            "subcategory":"Art Gallery",
            "type":"Entertainment"
        }
    ],
    "sg:phone":"+1 609 368 3838",
    "sg:postcode":"08202",
    "sg:province":"NJ",
    "wof:name":"Accents by Sherry",
    "wof:placetype":"venue"
},
  "geometry": {"coordinates":[-74.72219800000001,39.096401],"type":"Point"}
}