{
  "type": "Feature",
  "properties": {
    "addr:full":"1299 W Forest Grove Rd Vineland NJ 08360",
    "addr:housenumber":"1299",
    "addr:postcode":"08360",
    "addr:street":"W Forest Grove Rd",
    "iso:country":"US",
    "sg:address":"1299 W Forest Grove Rd",
    "sg:city":"Vineland",
    "sg:classifiers":[
        {
            "category":"Freight",
            "type":"Transportation"
        }
    ],
    "sg:phone":"+1 856 794 5000",
    "sg:postcode":"08360",
    "sg:province":"NJ",
    "sg:tags":[
        "warehouse"
    ],
    "wof:name":"GE",
    "wof:placetype":"venue"
},
  "geometry": {"coordinates":[-75.046042,39.52737],"type":"Point"}
}