{
  "type": "Feature",
  "properties": {
    "iso:country":"US",
    "sg:address":"115 Franklin Tpke",
    "sg:city":"Mahwah",
    "sg:classifiers":[
        {
            "category":"Health Services",
            "subcategory":"Chiropractor",
            "type":"Services"
        }
    ],
    "sg:phone":"+1 201 818 3010",
    "sg:postcode":"07430",
    "sg:province":"NJ",
    "wof:name":"Back To Health Chiro Ctr",
    "wof:placetype":"venue"
},
  "geometry": {"coordinates":[-74.146354,41.097737],"type":"Point"}
}