{
  "type": "Feature",
  "properties": {
    "addr:full":"301 Greenwood Ave Florham Park NJ 07932",
    "addr:housenumber":"301",
    "addr:postcode":"07932",
    "addr:street":"Greenwood Ave",
    "iso:country":"US",
    "sg:address":"301 Greenwood Ave",
    "sg:city":"Florham Park",
    "sg:classifiers":[
        {
            "category":"Professional",
            "type":"Services"
        }
    ],
    "sg:phone":"+1 973 301 1979",
    "sg:postcode":"07932",
    "sg:province":"NJ",
    "sg:tags":[
        "arts",
        "merchandise",
        "artist"
    ],
    "wof:name":"Wayne Artist Mauro Studio",
    "wof:placetype":"venue"
},
  "geometry": {"coordinates":[-74.40063600000001,40.773421],"type":"Point"}
}