{
  "type": "Feature",
  "properties": {
    "addr:full":"9 Deborah Dr Edison NJ 08820",
    "addr:housenumber":"9",
    "addr:postcode":"08820",
    "addr:street":"Deborah Dr",
    "iso:country":"US",
    "sg:address":"9 Deborah Dr",
    "sg:city":"Edison",
    "sg:classifiers":[
        {
            "category":"Professional",
            "subcategory":"Management & Consulting",
            "type":"Services"
        }
    ],
    "sg:phone":"+1 732 549 2915",
    "sg:postcode":"08820",
    "sg:province":"NJ",
    "sg:tags":[
        "consultant"
    ],
    "wof:name":"JTP & Assoc",
    "wof:placetype":"venue"
},
  "geometry": {"coordinates":[-74.35105299999999,40.581117],"type":"Point"}
}