{
  "type": "Feature",
  "properties": {
    "iso:country":"US",
    "sg:address":"127 E 20th St",
    "sg:city":"Paterson",
    "sg:classifiers":[
        {
            "category":"Building & Trades",
            "subcategory":"Construction",
            "type":"Services"
        }
    ],
    "sg:phone":"+1 201 757 7046",
    "sg:postcode":"07513",
    "sg:province":"NJ",
    "sg:tags":[
        "general",
        "contractor"
    ],
    "wof:name":"A & A General Contracting",
    "wof:placetype":"venue"
},
  "geometry": {"coordinates":[-74.157072,40.904401],"type":"Point"}
}