{
  "type": "Feature",
  "properties": {
    "iso:country":"US",
    "sg:address":"42 Upper Montclair Plz",
    "sg:city":"Montclair",
    "sg:classifiers":[
        {
            "category":"Food & Beverages",
            "subcategory":"Liquor & Beverages",
            "type":"Retail Goods"
        }
    ],
    "sg:phone":"+1 973 746 7337",
    "sg:postcode":"07043",
    "sg:province":"NJ",
    "sg:tags":[
        "beer",
        "wine",
        "spirit",
        "alcoholic"
    ],
    "wof:name":"Magnolia's Wines & Spirits",
    "wof:placetype":"venue"
},
  "geometry": {"coordinates":[-74.208702,40.840302],"type":"Point"}
}