{
  "type": "Feature",
  "properties": {
    "addr:full":"10 Pier Ln Fairfield NJ 07004",
    "addr:housenumber":"10",
    "addr:postcode":"07004",
    "addr:street":"Pier Ln",
    "iso:country":"US",
    "sg:address":"10 Pier Ln",
    "sg:city":"Fairfield",
    "sg:classifiers":[
        {
            "category":"Building & Trades",
            "subcategory":"Locksmith",
            "type":"Services"
        }
    ],
    "sg:phone":"+1 888 421 2434",
    "sg:postcode":"07004",
    "sg:province":"NJ",
    "sg:tags":[
        "key"
    ],
    "wof:name":"Always Affective Available Emergency Locksmith",
    "wof:placetype":"venue"
},
  "geometry": {"coordinates":[-74.27097000000001,40.880857],"type":"Point"}
}