{
  "type": "Feature",
  "properties": {
    "iso:country":"US",
    "sg:address":"621 US Hwy 130",
    "sg:city":"Trenton",
    "sg:classifiers":[
        {
            "category":"Shopping",
            "subcategory":"Bicycles & Sporting Goods",
            "type":"Retail Goods"
        }
    ],
    "sg:phone":"+1   ",
    "sg:postcode":"08691",
    "sg:province":"NJ",
    "wof:name":"Golf Etc Of Hamilton",
    "wof:placetype":"venue"
},
  "geometry": {"coordinates":[-74.64718000000001,40.192064],"type":"Point"}
}