{
  "type": "Feature",
  "properties": {
    "iso:country":"US",
    "sg:address":"451 Bloomfield Ave",
    "sg:city":"Newark",
    "sg:classifiers":[
        {
            "category":"Shopping",
            "subcategory":"Pharmacy",
            "type":"Retail Goods"
        }
    ],
    "sg:phone":"+1   ",
    "sg:postcode":"07107",
    "sg:province":"NJ",
    "wof:name":"CVS",
    "wof:placetype":"venue"
},
  "geometry": {"coordinates":[-74.18347799999999,40.770668],"type":"Point"}
}