{
  "type": "Feature",
  "properties": {
    "iso:country":"US",
    "sg:address":"455 Plaza Dr",
    "sg:city":"Secaucus",
    "sg:classifiers":[
        {
            "category":"Travel",
            "subcategory":"Hotels & Motels",
            "type":"Entertainment"
        }
    ],
    "sg:phone":"+1 201 809 4117",
    "sg:postcode":"07094",
    "sg:province":"NJ",
    "sg:website":"www.embassysuites.com",
    "wof:name":"Embassy Suites Hotel",
    "wof:placetype":"venue"
},
  "geometry": {"coordinates":[-74.043402,40.787863],"type":"Point"}
}