{
  "type": "Feature",
  "properties": {
    "iso:country":"US",
    "sg:address":"207 Edison Ave",
    "sg:city":"Stewartsville",
    "sg:classifiers":[
        {
            "category":"Building & Trades",
            "subcategory":"Construction",
            "type":"Services"
        }
    ],
    "sg:phone":"+1 908 454 0556",
    "sg:postcode":"08886",
    "sg:province":"NJ",
    "sg:tags":[
        "house",
        "residential"
    ],
    "wof:name":"Richard Mazzariello Contg",
    "wof:placetype":"venue"
},
  "geometry": {"coordinates":[-75.118926,40.702034],"type":"Point"}
}