{
  "type": "Feature",
  "properties": {
    "addr:full":"181 Ackerman Ave Clifton NJ 07011",
    "addr:housenumber":"181",
    "addr:postcode":"07011",
    "addr:street":"Ackerman Ave",
    "iso:country":"US",
    "sg:address":"181 Ackerman Ave",
    "sg:city":"Clifton",
    "sg:classifiers":[
        {
            "category":"Building & Trades",
            "subcategory":"Cleaning & Sanitation",
            "type":"Services"
        }
    ],
    "sg:phone":"+1   ",
    "sg:postcode":"07011",
    "sg:province":"NJ",
    "sg:tags":[
        "maintenance"
    ],
    "wof:name":"Rosario Cleaning Service",
    "wof:placetype":"venue"
},
  "geometry": {"coordinates":[-74.127696,40.876815],"type":"Point"}
}