{
  "type": "Feature",
  "properties": {
    "addr:full":"346 Palisade Ave Bogota NJ 07603",
    "addr:housenumber":"346",
    "addr:postcode":"07603",
    "addr:street":"Palisade Ave",
    "iso:country":"US",
    "sg:address":"346 Palisade Ave",
    "sg:city":"Bogota",
    "sg:classifiers":[
        {
            "category":"Real Estate",
            "subcategory":"Real Estate Services",
            "type":"Services"
        }
    ],
    "sg:phone":"+1 201 342 1110",
    "sg:postcode":"07603",
    "sg:province":"NJ",
    "sg:tags":[
        "management",
        "property"
    ],
    "wof:name":"J&m Realty Management",
    "wof:placetype":"venue"
},
  "geometry": {"coordinates":[-74.025267,40.877183],"type":"Point"}
}