{
  "type": "Feature",
  "properties": {
    "iso:country":"US",
    "sg:address":"245 N Main St",
    "sg:city":"Manville",
    "sg:classifiers":[
        {
            "category":"Retail",
            "subcategory":"Auto Repair",
            "type":"Services"
        }
    ],
    "sg:phone":"+1 908 526 3570",
    "sg:postcode":"08835",
    "sg:province":"NJ",
    "sg:tags":[
        "body",
        "general"
    ],
    "wof:name":"Gifford Auto Body",
    "wof:placetype":"venue"
},
  "geometry": {"coordinates":[-74.58672199999999,40.546085],"type":"Point"}
}