{
  "type": "Feature",
  "properties": {
    "addr:full":"920 Broadway Newark NJ 07104",
    "addr:housenumber":"920",
    "addr:postcode":"07104",
    "addr:street":"Broadway",
    "iso:country":"US",
    "sg:address":"920 Broadway",
    "sg:city":"Newark",
    "sg:classifiers":[
        {
            "category":"Freight",
            "type":"Transportation"
        }
    ],
    "sg:phone":"+1 973 412 8488",
    "sg:postcode":"07104",
    "sg:province":"NJ",
    "sg:tags":[
        "shipping",
        "agent"
    ],
    "wof:name":"Canoa Shipping",
    "wof:placetype":"venue"
},
  "geometry": {"coordinates":[-74.154737,40.781078],"type":"Point"}
}