{
  "type": "Feature",
  "properties": {
    "iso:country":"US",
    "sg:address":"139 Bessida St",
    "sg:city":"Bloomfield",
    "sg:classifiers":[
        {
            "category":"Professional",
            "type":"Services"
        }
    ],
    "sg:phone":"+1   ",
    "sg:postcode":"07003",
    "sg:province":"NJ",
    "wof:name":"Benjamin Publng/Nvlt",
    "wof:placetype":"venue"
},
  "geometry": {"coordinates":[-74.18125999999999,40.823028],"type":"Point"}
}