{
  "type": "Feature",
  "properties": {
    "addr:full":"200 N 17th St Bloomfield NJ 07003",
    "addr:housenumber":"200",
    "addr:postcode":"07003",
    "addr:street":"N 17Th St",
    "iso:country":"US",
    "sg:address":"200 N 17th St",
    "sg:city":"Bloomfield",
    "sg:classifiers":[
        {
            "category":"Manufacturing",
            "subcategory":"Food",
            "type":"Manufacturing & Wholesale Goods"
        }
    ],
    "sg:phone":"+1 973 748 2265",
    "sg:postcode":"07003",
    "sg:province":"NJ",
    "sg:tags":[
        "product",
        "mfg"
    ],
    "wof:name":"Sweet Mgnolia Carrot Cakes Etc",
    "wof:placetype":"venue"
},
  "geometry": {"coordinates":[-74.189621,40.773475],"type":"Point"}
}