{
  "type": "Feature",
  "properties": {
    "iso:country":"US",
    "sg:address":"35 E Broad St",
    "sg:city":"Hopewell",
    "sg:classifiers":[
        {
            "category":"Professional",
            "type":"Services"
        },
        {
            "category":"Retail",
            "subcategory":"Portrait Studio",
            "type":"Services"
        }
    ],
    "sg:phone":"+1 609 466 0267",
    "sg:postcode":"08525",
    "sg:province":"NJ",
    "sg:tags":[
        "photographer"
    ],
    "sg:website":"www.lewiskassel.com",
    "wof:name":"Lewis Kassel Photography",
    "wof:placetype":"venue"
},
  "geometry": {"coordinates":[-74.75985300000001,40.389671],"type":"Point"}
}