{
  "type": "Feature",
  "properties": {
    "iso:country":"US",
    "sg:address":"746 Paterson Ave",
    "sg:city":"East Rutherford",
    "sg:classifiers":[
        {
            "category":"Arts & Performance",
            "subcategory":"Arts Center",
            "type":"Entertainment"
        }
    ],
    "sg:phone":"+1 201 935 0686",
    "sg:postcode":"07073",
    "sg:province":"NJ",
    "sg:tags":[
        "performing"
    ],
    "wof:name":"Jelotte Pamela School of Creative Dance",
    "wof:placetype":"venue"
},
  "geometry": {"coordinates":[-74.111397,40.847099],"type":"Point"}
}