{
  "type": "Feature",
  "properties": {
    "addr:full":"622 Sketch Pl S Ridgefield NJ 07657",
    "addr:housenumber":"622",
    "addr:postcode":"07657",
    "addr:street":"Sketch Pl",
    "iso:country":"US",
    "sg:address":"622 Sketch Pl S",
    "sg:city":"Ridgefield",
    "sg:classifiers":[
        {
            "category":"Professional",
            "subcategory":"Advertising",
            "type":"Services"
        }
    ],
    "sg:phone":"+1   ",
    "sg:postcode":"07657",
    "sg:province":"NJ",
    "wof:name":"Onhold Promotional Productions",
    "wof:placetype":"venue"
},
  "geometry": {"coordinates":[-74.00041400000001,40.825776],"type":"Point"}
}