{
  "type": "Feature",
  "properties": {
    "addr:full":"8 Apple Tree Ln Warren NJ 07059",
    "addr:housenumber":"8",
    "addr:postcode":"07059",
    "addr:street":"Apple Tree Ln",
    "iso:country":"US",
    "sg:address":"8 Apple Tree Ln",
    "sg:city":"Warren",
    "sg:classifiers":[
        {
            "category":"Professional",
            "subcategory":"Accounting & Tax Preparation",
            "type":"Services"
        }
    ],
    "sg:phone":"+1 908 561 6640",
    "sg:postcode":"07059",
    "sg:province":"NJ",
    "sg:tags":[
        "accountant"
    ],
    "wof:name":"Peter Gelwarg",
    "wof:placetype":"venue"
},
  "geometry": {"coordinates":[-74.487409,40.620719],"type":"Point"}
}