{
  "type": "Feature",
  "properties": {
    "iso:country":"US",
    "sg:address":"77 Main St Ste 2",
    "sg:city":"West Orange",
    "sg:classifiers":[
        {
            "category":"Health Services",
            "subcategory":"Doctor",
            "type":"Services"
        }
    ],
    "sg:phone":"+1 973 324 2090",
    "sg:postcode":"07052",
    "sg:province":"NJ",
    "wof:name":"Rajiyah Gitendra MD",
    "wof:placetype":"venue"
},
  "geometry": {"coordinates":[-74.23814,40.779397],"type":"Point"}
}