{
  "type": "Feature",
  "properties": {
    "addr:full":"20 Orlando Dr Fairfield NJ 07004",
    "addr:housenumber":"20",
    "addr:postcode":"07004",
    "addr:street":"Orlando Dr",
    "iso:country":"US",
    "sg:address":"20 Orlando Dr",
    "sg:city":"Fairfield",
    "sg:classifiers":[
        {
            "category":"Wholesale",
            "subcategory":"Medical Equipment & Supplies",
            "type":"Manufacturing & Wholesale Goods"
        }
    ],
    "sg:phone":"+1 973 227 0031",
    "sg:postcode":"07004",
    "sg:province":"NJ",
    "wof:name":"Stat-Tech Surgical Supply Co",
    "wof:placetype":"venue"
},
  "geometry": {"coordinates":[-74.26931999999999,40.881437],"type":"Point"}
}