{
  "type": "Feature",
  "properties": {
    "iso:country":"US",
    "sg:address":"2966 S Main Rd",
    "sg:city":"Vineland",
    "sg:classifiers":[
        {
            "category":"Retail",
            "subcategory":"Auto Repair",
            "type":"Services"
        }
    ],
    "sg:phone":"+1 856 690 8655",
    "sg:postcode":"08360",
    "sg:province":"NJ",
    "sg:tags":[
        "general"
    ],
    "wof:name":"East Vnland Auto Rpir Detaling",
    "wof:placetype":"venue"
},
  "geometry": {"coordinates":[-75.015131,39.445367],"type":"Point"}
}