{
  "type": "Feature",
  "properties": {
    "iso:country":"US",
    "sg:address":"137 Haven Ave",
    "sg:city":"Ocean City",
    "sg:classifiers":[
        {
            "category":"Professional",
            "subcategory":"Computer Services",
            "type":"Services"
        }
    ],
    "sg:phone":"+1   ",
    "sg:postcode":"08226",
    "sg:province":"NJ",
    "sg:tags":[
        "related"
    ],
    "wof:name":"Cordi Computer Consulting",
    "wof:placetype":"venue"
},
  "geometry": {"coordinates":[-74.56759599999999,39.28803],"type":"Point"}
}