{
  "type": "Feature",
  "properties": {
    "iso:country":"US",
    "sg:address":"911 Billingsport Rd",
    "sg:city":"Gibbstown",
    "sg:classifiers":[
        {
            "category":"Recreation",
            "type":"Entertainment"
        }
    ],
    "sg:phone":"+1 856 423 3615",
    "sg:postcode":"08066",
    "sg:province":"NJ",
    "sg:tags":[
        "hall",
        "auditorium"
    ],
    "wof:name":"INDEPENDENT Oil Workers",
    "wof:placetype":"venue"
},
  "geometry": {"coordinates":[-75.252128,39.833361],"type":"Point"}
}