{
  "type": "Feature",
  "properties": {
    "iso:country":"US",
    "sg:address":"318 Allens Ln",
    "sg:city":"Mullica Hill",
    "sg:classifiers":[
        {
            "category":"Wholesale",
            "subcategory":"Durable Goods & Equipment",
            "type":"Manufacturing & Wholesale Goods"
        }
    ],
    "sg:phone":"+1 856 223 9214",
    "sg:postcode":"08062",
    "sg:province":"NJ",
    "wof:name":"Garden State Fire Extinguisher",
    "wof:placetype":"venue"
},
  "geometry": {"coordinates":[-75.217263,39.725673],"type":"Point"}
}