{
  "type": "Feature",
  "properties": {
    "iso:country":"US",
    "sg:address":"67 E Jimmie Leeds Rd",
    "sg:city":"Absecon",
    "sg:classifiers":[
        {
            "category":"Banks & Credit Unions",
            "subcategory":"Bank",
            "type":"Services"
        }
    ],
    "sg:phone":"+1 609 748 3123",
    "sg:postcode":"08201",
    "sg:province":"NJ",
    "wof:name":"Boardwalk Bank",
    "wof:placetype":"venue"
},
  "geometry": {"coordinates":[-74.521064,39.473408],"type":"Point"}
}