{
  "type": "Feature",
  "properties": {
    "addr:full":"515 Wellfleet Rd Cinnaminson NJ 08077",
    "addr:housenumber":"515",
    "addr:postcode":"08077",
    "addr:street":"Wellfleet Rd",
    "iso:country":"US",
    "sg:address":"515 Wellfleet Rd",
    "sg:city":"Cinnaminson",
    "sg:classifiers":[
        {
            "category":"Building & Trades",
            "subcategory":"Construction",
            "type":"Services"
        }
    ],
    "sg:phone":"+1 856 829 0410",
    "sg:postcode":"08077",
    "sg:province":"NJ",
    "sg:tags":[
        "boring",
        "drilling",
        "contractor"
    ],
    "wof:name":"Foundation Monitoring & Water",
    "wof:placetype":"venue"
},
  "geometry": {"coordinates":[-74.96514500000001,39.98967],"type":"Point"}
}