{
  "type": "Feature",
  "properties": {
    "iso:country":"US",
    "sg:address":"31 Virginia Trl",
    "sg:city":"Medford",
    "sg:classifiers":[
        {
            "category":"Professional",
            "type":"Services"
        }
    ],
    "sg:phone":"+1   ",
    "sg:postcode":"08055",
    "sg:province":"NJ",
    "wof:name":"Albert Crossen",
    "wof:placetype":"venue"
},
  "geometry": {"coordinates":[-74.841976,39.884493],"type":"Point"}
}