{
  "type": "Feature",
  "properties": {
    "iso:country":"US",
    "sg:address":"6001 Monroe Pl",
    "sg:city":"West New York",
    "sg:classifiers":[
        {
            "category":"Real Estate",
            "subcategory":"Real Estate Operator",
            "type":"Services"
        }
    ],
    "sg:phone":"+1 201 295 1898",
    "sg:postcode":"07093",
    "sg:province":"NJ",
    "sg:tags":[
        "condominium"
    ],
    "wof:name":"West New York Condo Assn",
    "wof:placetype":"venue"
},
  "geometry": {"coordinates":[-74.01225599999999,40.78881],"type":"Point"}
}