{
  "type": "Feature",
  "properties": {
    "addr:full":"39 Wanaque Ave Pompton Lakes NJ 07442",
    "addr:housenumber":"39",
    "addr:postcode":"07442",
    "addr:street":"Wanaque Ave",
    "iso:country":"US",
    "sg:address":"39 Wanaque Ave",
    "sg:city":"Pompton Lakes",
    "sg:classifiers":[
        {
            "category":"Personal",
            "subcategory":"Beauty Salon",
            "type":"Services"
        }
    ],
    "sg:phone":"+1 973 248 8866",
    "sg:postcode":"07442",
    "sg:province":"NJ",
    "sg:tags":[
        "nail",
        "shop",
        "manicuring"
    ],
    "wof:name":"Angel Tips Nail Spa",
    "wof:placetype":"venue"
},
  "geometry": {"coordinates":[-74.29360200000001,41.007401],"type":"Point"}
}