{
  "type": "Feature",
  "properties": {
    "iso:country":"US",
    "sg:address":"120 W Commercial Ave",
    "sg:city":"Moonachie",
    "sg:classifiers":[
        {
            "category":"Wholesale",
            "subcategory":"Medical Equipment & Supplies",
            "type":"Manufacturing & Wholesale Goods"
        },
        {
            "category":"Manufacturing",
            "subcategory":"Tools & Machinery",
            "type":"Manufacturing & Wholesale Goods"
        }
    ],
    "sg:phone":"+1 201 939 0716",
    "sg:postcode":"07074",
    "sg:province":"NJ",
    "sg:tags":[
        "physician",
        "surgeon",
        "mfg"
    ],
    "sg:website":"www.biocompression.com",
    "wof:name":"Bio Compression Systems Inc",
    "wof:placetype":"venue"
},
  "geometry": {"coordinates":[-74.061887,40.833151],"type":"Point"}
}