{
  "type": "Feature",
  "properties": {
    "iso:country":"US",
    "sg:address":"21 Cedar Ave",
    "sg:city":"Fair Haven",
    "sg:classifiers":[
        {
            "category":"Health Services",
            "subcategory":"Health Practitioner",
            "type":"Services"
        }
    ],
    "sg:phone":"+1 732 741 3077",
    "sg:postcode":"07704",
    "sg:province":"NJ",
    "sg:tags":[
        "psychologist"
    ],
    "wof:name":"Adriane Gullotta-Gsell PHD",
    "wof:placetype":"venue"
},
  "geometry": {"coordinates":[-74.04070299999999,40.361641],"type":"Point"}
}