{
  "type": "Feature",
  "properties": {
    "addr:full":"235 Washington Ave Avon By The Sea NJ 07717",
    "addr:housenumber":"235",
    "addr:postcode":"07717",
    "addr:street":"Washington Ave",
    "iso:country":"US",
    "sg:address":"235 Washington Ave",
    "sg:city":"Avon By The Sea",
    "sg:classifiers":[
        {
            "category":"Health Services",
            "subcategory":"Health Practitioner",
            "type":"Services"
        }
    ],
    "sg:phone":"+1 732 776 8569",
    "sg:postcode":"07717",
    "sg:province":"NJ",
    "wof:name":"Eric Riss PHD",
    "wof:placetype":"venue"
},
  "geometry": {"coordinates":[-74.015907,40.189029],"type":"Point"}
}