{
  "type": "Feature",
  "properties": {
    "iso:country":"US",
    "sg:address":"308 Cedar Rd",
    "sg:city":"Point Pleasant Beach",
    "sg:classifiers":[
        {
            "category":"Building & Trades",
            "subcategory":"Construction",
            "type":"Services"
        }
    ],
    "sg:phone":"+1 732 899 9247",
    "sg:postcode":"08742",
    "sg:province":"NJ",
    "sg:tags":[
        "house"
    ],
    "wof:name":"Allert Home Improvements",
    "wof:placetype":"venue"
},
  "geometry": {"coordinates":[-74.069216,40.084271],"type":"Point"}
}