{
  "type": "Feature",
  "properties": {
    "addr:full":"6 Lyons Ave Newark NJ 07112",
    "addr:housenumber":"6",
    "addr:postcode":"07112",
    "addr:street":"Lyons Ave",
    "iso:country":"US",
    "sg:address":"6 Lyons Ave",
    "sg:city":"Newark",
    "sg:classifiers":[
        {
            "category":"Shopping",
            "type":"Retail Goods"
        }
    ],
    "sg:phone":"+1 973 926 6170",
    "sg:postcode":"07112",
    "sg:province":"NJ",
    "sg:tags":[
        "religious"
    ],
    "wof:name":"Community Of AHAD",
    "wof:placetype":"venue"
},
  "geometry": {"coordinates":[-74.207233,40.706358],"type":"Point"}
}