{
  "type": "Feature",
  "properties": {
    "iso:country":"US",
    "sg:address":"284 US Hwy 206",
    "sg:city":"Hillsborough",
    "sg:classifiers":[
        {
            "category":"Wholesale",
            "subcategory":"Non-durable Goods",
            "type":"Manufacturing & Wholesale Goods"
        }
    ],
    "sg:phone":"+1 908 281 5333",
    "sg:postcode":"08844",
    "sg:province":"NJ",
    "sg:tags":[
        "canvas"
    ],
    "wof:name":"Canvas & Craft",
    "wof:placetype":"venue"
},
  "geometry": {"coordinates":[-74.627797,40.524479],"type":"Point"}
}