{
  "type": "Feature",
  "properties": {
    "iso:country":"US",
    "sg:address":"521 Coventry Dr",
    "sg:city":"Nutley",
    "sg:classifiers":[
        {
            "category":"Real Estate",
            "subcategory":"Real Estate Operator",
            "type":"Services"
        }
    ],
    "sg:phone":"+1 973 667 0864",
    "sg:postcode":"07110",
    "sg:province":"NJ",
    "sg:tags":[
        "apartment"
    ],
    "wof:name":"Cambridge Heights Condo Assn Inc",
    "wof:placetype":"venue"
},
  "geometry": {"coordinates":[-74.136661,40.820941],"type":"Point"}
}