{
  "type": "Feature",
  "properties": {
    "addr:full":"1501 Bayshore Rd Villas NJ 08251",
    "addr:housenumber":"1501",
    "addr:postcode":"08251",
    "addr:street":"Bayshore Rd",
    "iso:country":"US",
    "sg:address":"1501 Bayshore Rd",
    "sg:city":"Villas",
    "sg:classifiers":[
        {
            "category":"Home & Garden",
            "subcategory":"Building Materials",
            "type":"Retail Goods"
        }
    ],
    "sg:phone":"+1   ",
    "sg:postcode":"08251",
    "sg:province":"NJ",
    "sg:tags":[
        "lumber",
        "supply"
    ],
    "wof:name":"Villas Home Center",
    "wof:placetype":"venue"
},
  "geometry": {"coordinates":[-74.933027,39.023984],"type":"Point"}
}