{
  "type": "Feature",
  "properties": {
    "iso:country":"US",
    "sg:address":"279 Pancoast Mill Rd",
    "sg:city":"Buena",
    "sg:classifiers":[
        {
            "category":"Farming",
            "subcategory":"Livestock Farm",
            "type":"Manufacturing & Wholesale Goods"
        }
    ],
    "sg:phone":"+1   ",
    "sg:postcode":"08310",
    "sg:province":"NJ",
    "sg:tags":[
        "horse",
        "dealer"
    ],
    "wof:name":"D & D Stables",
    "wof:placetype":"venue"
},
  "geometry": {"coordinates":[-74.876527,39.523508],"type":"Point"}
}