{
  "type": "Feature",
  "properties": {
    "iso:country":"US",
    "sg:address":"121 Lakeview Ave",
    "sg:city":"Clifton",
    "sg:classifiers":[
        {
            "category":"Shopping",
            "subcategory":"Tobacco",
            "type":"Retail Goods"
        },
        {
            "category":"Food & Beverages",
            "subcategory":"Candy",
            "type":"Retail Goods"
        }
    ],
    "sg:phone":"+1 973 478 3310",
    "sg:postcode":"07011",
    "sg:province":"NJ",
    "sg:tags":[
        "shop",
        "store"
    ],
    "wof:name":"Lesser Pine & Sons Tobacco",
    "wof:placetype":"venue"
},
  "geometry": {"coordinates":[-74.137001,40.879398],"type":"Point"}
}