{
  "type": "Feature",
  "properties": {
    "iso:country":"US",
    "sg:address":"1000 1st St",
    "sg:city":"Harrison",
    "sg:classifiers":[
        {
            "category":"Museum",
            "type":"Entertainment"
        }
    ],
    "sg:phone":"+1 973 482 5270",
    "sg:postcode":"07029",
    "sg:province":"NJ",
    "wof:name":"East River Arts",
    "wof:placetype":"venue"
},
  "geometry": {"coordinates":[-74.161484,40.73827],"type":"Point"}
}