{
  "type": "Feature",
  "properties": {
    "iso:country":"US",
    "sg:address":"55 Hopper Ave",
    "sg:city":"Nutley",
    "sg:classifiers":[
        {
            "category":"Home & Garden",
            "subcategory":"Home Furnishings",
            "type":"Retail Goods"
        }
    ],
    "sg:phone":"+1   ",
    "sg:postcode":"07110",
    "sg:province":"NJ",
    "wof:name":"J C Vertical Blinds",
    "wof:placetype":"venue"
},
  "geometry": {"coordinates":[-74.17235100000001,40.815875],"type":"Point"}
}