{
  "type": "Feature",
  "properties": {
    "iso:country":"US",
    "sg:address":"350 Marshall St",
    "sg:city":"Phillipsburg",
    "sg:classifiers":[
        {
            "category":"Social Services",
            "type":"Services"
        },
        {
            "category":"Organizations",
            "subcategory":"Community Association",
            "type":"Services"
        }
    ],
    "sg:phone":"+1 908 454 1078",
    "sg:postcode":"08865",
    "sg:province":"NJ",
    "sg:website":"http://www.communityactionpartnership.com/",
    "wof:name":"Community Action Agency",
    "wof:placetype":"venue"
},
  "geometry": {"coordinates":[-75.184764,40.693811],"type":"Point"}
}