{
  "type": "Feature",
  "properties": {
    "iso:country":"US",
    "sg:address":"109 Midland Ave",
    "sg:city":"Kearny",
    "sg:classifiers":[
        {
            "category":"Government",
            "subcategory":"Fire Station",
            "type":"Public Place"
        }
    ],
    "sg:phone":"+1   ",
    "sg:postcode":"07032",
    "sg:province":"NJ",
    "sg:tags":[
        "protection"
    ],
    "wof:name":"Kearny Fire Dept",
    "wof:placetype":"venue"
},
  "geometry": {"coordinates":[-74.143753,40.77019],"type":"Point"}
}