{
  "type": "Feature",
  "properties": {
    "addr:full":"107 Grove St Waldwick NJ 07463",
    "addr:housenumber":"107",
    "addr:postcode":"07463",
    "addr:street":"Grove St",
    "iso:country":"US",
    "sg:address":"107 Grove St",
    "sg:city":"Waldwick",
    "sg:classifiers":[
        {
            "category":"Professional",
            "subcategory":"Lawyer & Legal Services",
            "type":"Services"
        }
    ],
    "sg:phone":"+1   ",
    "sg:postcode":"07463",
    "sg:province":"NJ",
    "wof:name":"D Fitzpatrick Esq",
    "wof:placetype":"venue"
},
  "geometry": {"coordinates":[-74.110804,41.012154],"type":"Point"}
}