{
  "type": "Feature",
  "properties": {
    "addr:full":"102 North Ave W Cranford NJ 07016",
    "addr:housenumber":"102",
    "addr:postcode":"07016",
    "addr:street":"North Ave W",
    "iso:country":"US",
    "sg:address":"102 North Ave W",
    "sg:city":"Cranford",
    "sg:classifiers":[
        {
            "category":"Retail",
            "subcategory":"Auto Repair",
            "type":"Services"
        }
    ],
    "sg:phone":"+1 908 272 2454",
    "sg:postcode":"07016",
    "sg:province":"NJ",
    "sg:tags":[
        "automotive"
    ],
    "sg:website":"www.jiffylube.com",
    "wof:name":"Jiffy Lube",
    "wof:placetype":"venue"
},
  "geometry": {"coordinates":[-74.309196,40.655602],"type":"Point"}
}