{
  "type": "Feature",
  "properties": {
    "addr:full":"5 Woodmont Dr Chatham NJ 07928",
    "addr:housenumber":"5",
    "addr:postcode":"07928",
    "addr:street":"Woodmont Dr",
    "iso:country":"US",
    "sg:address":"5 Woodmont Dr",
    "sg:city":"Chatham",
    "sg:classifiers":[
        {
            "category":"Building & Trades",
            "subcategory":"Construction",
            "type":"Services"
        }
    ],
    "sg:phone":"+1 973 360 9778",
    "sg:postcode":"07928",
    "sg:province":"NJ",
    "sg:tags":[
        "general",
        "contractor"
    ],
    "wof:name":"Pilot Construction",
    "wof:placetype":"venue"
},
  "geometry": {"coordinates":[-74.42002599999999,40.73734],"type":"Point"}
}