{
  "type": "Feature",
  "properties": {
    "addr:full":"2306 Dellwood Rd Point Pleasant Beach NJ 08742",
    "addr:housenumber":"2306",
    "addr:postcode":"08742",
    "addr:street":"Dellwood Rd",
    "iso:country":"US",
    "sg:address":"2306 Dellwood Rd",
    "sg:city":"Point Pleasant Beach",
    "sg:classifiers":[
        {
            "category":"Building & Trades",
            "subcategory":"Construction",
            "type":"Services"
        }
    ],
    "sg:phone":"+1 732 892 3467",
    "sg:postcode":"08742",
    "sg:province":"NJ",
    "sg:tags":[
        "drywall",
        "contractor"
    ],
    "wof:name":"Johns Drywall Co",
    "wof:placetype":"venue"
},
  "geometry": {"coordinates":[-74.07319699999999,40.069626],"type":"Point"}
}