{
  "type": "Feature",
  "properties": {
    "addr:full":"222 Greenmount Ave Cliffside Park NJ 07010",
    "addr:housenumber":"222",
    "addr:postcode":"07010",
    "addr:street":"Greenmount Ave",
    "iso:country":"US",
    "sg:address":"222 Greenmount Ave",
    "sg:city":"Cliffside Park",
    "sg:classifiers":[
        {
            "category":"Health Services",
            "subcategory":"Doctor",
            "type":"Services"
        }
    ],
    "sg:phone":"+1   ",
    "sg:postcode":"07010",
    "sg:province":"NJ",
    "sg:tags":[
        "medical"
    ],
    "wof:name":"Heart Center",
    "wof:placetype":"venue"
},
  "geometry": {"coordinates":[-73.98863799999999,40.821873],"type":"Point"}
}