{
  "type": "Feature",
  "properties": {
    "addr:full":"81 Monmouth St Red Bank NJ 07701",
    "addr:housenumber":"81",
    "addr:postcode":"07701",
    "addr:street":"Monmouth St",
    "iso:country":"US",
    "sg:address":"81 Monmouth St",
    "sg:city":"Red Bank",
    "sg:classifiers":[
        {
            "category":"Personal",
            "subcategory":"Barber",
            "type":"Services"
        }
    ],
    "sg:phone":"+1 732 741 9463",
    "sg:postcode":"07701",
    "sg:province":"NJ",
    "sg:tags":[
        "shop"
    ],
    "wof:name":"Art's Barber Shop",
    "wof:placetype":"venue"
},
  "geometry": {"coordinates":[-74.068451,40.34935],"type":"Point"}
}