{
  "type": "Feature",
  "properties": {
    "iso:country":"US",
    "sg:address":"19 Southside Ave",
    "sg:city":"South River",
    "sg:classifiers":[
        {
            "category":"Health Services",
            "subcategory":"Clinic",
            "type":"Services"
        }
    ],
    "sg:phone":"+1 732 679 1598",
    "sg:postcode":"08882",
    "sg:province":"NJ",
    "wof:name":"Universal Medical Exams",
    "wof:placetype":"venue"
},
  "geometry": {"coordinates":[-74.373757,40.443731],"type":"Point"}
}