{
  "type": "Feature",
  "properties": {
    "addr:full":"82 Walnut Ct Englewood NJ 07631",
    "addr:housenumber":"82",
    "addr:postcode":"07631",
    "addr:street":"Walnut Ct",
    "iso:country":"US",
    "sg:address":"82 Walnut Ct",
    "sg:city":"Englewood",
    "sg:classifiers":[
        {
            "category":"Professional",
            "subcategory":"Business Services",
            "type":"Services"
        }
    ],
    "sg:phone":"+1 201 569 4939",
    "sg:postcode":"07631",
    "sg:province":"NJ",
    "wof:name":"Leiderman Assoc",
    "wof:placetype":"venue"
},
  "geometry": {"coordinates":[-73.965508,40.891722],"type":"Point"}
}