{
  "type": "Feature",
  "properties": {
    "iso:country":"US",
    "sg:address":"30 River Ct",
    "sg:city":"Jersey City",
    "sg:classifiers":[
        {
            "category":"Professional",
            "subcategory":"Computer Services",
            "type":"Services"
        }
    ],
    "sg:phone":"+1 201 222 9202",
    "sg:postcode":"07310",
    "sg:province":"NJ",
    "sg:tags":[
        "repair"
    ],
    "sg:website":"www.fastteks.com",
    "wof:name":"Fast-Teks Onsite Computer Services",
    "wof:placetype":"venue"
},
  "geometry": {"coordinates":[-74.03189399999999,40.727164],"type":"Point"}
}