{
  "type": "Feature",
  "properties": {
    "iso:country":"US",
    "sg:address":"10 Fair Lawn Ave",
    "sg:city":"Fair Lawn",
    "sg:classifiers":[
        {
            "category":"Health Services",
            "subcategory":"Doctor",
            "type":"Services"
        }
    ],
    "sg:phone":"+1 201 794 8585",
    "sg:postcode":"07410",
    "sg:province":"NJ",
    "sg:tags":[
        "physician",
        "surgeon",
        "medical"
    ],
    "wof:name":"North Jersey Pediatrics",
    "wof:placetype":"venue"
},
  "geometry": {"coordinates":[-74.13011899999999,40.936581],"type":"Point"}
}