{
  "type": "Feature",
  "properties": {
    "iso:country":"US",
    "sg:address":"1212 Plover Ct",
    "sg:city":"Forked River",
    "sg:classifiers":[
        {
            "category":"Professional",
            "subcategory":"Engineering",
            "type":"Services"
        }
    ],
    "sg:phone":"+1   ",
    "sg:postcode":"08731",
    "sg:province":"NJ",
    "wof:name":"Kenneally Assoc",
    "wof:placetype":"venue"
},
  "geometry": {"coordinates":[-74.171725,39.815835],"type":"Point"}
}