{
  "type": "Feature",
  "properties": {
    "iso:country":"US",
    "sg:address":"50 Round Hill Dr",
    "sg:city":"Freehold",
    "sg:classifiers":[
        {
            "category":"Professional",
            "subcategory":"Engineering",
            "type":"Services"
        }
    ],
    "sg:phone":"+1 732 866 9729",
    "sg:postcode":"07728",
    "sg:province":"NJ",
    "sg:tags":[
        "engineer"
    ],
    "wof:name":"D B Engineering",
    "wof:placetype":"venue"
},
  "geometry": {"coordinates":[-74.320626,40.228041],"type":"Point"}
}