{
  "type": "Feature",
  "properties": {
    "iso:country":"US",
    "sg:address":"240 Mary St",
    "sg:city":"Hackensack",
    "sg:classifiers":[
        {
            "category":"Restaurant",
            "type":"Food & Drink"
        }
    ],
    "sg:phone":"+1   ",
    "sg:postcode":"07601",
    "sg:province":"NJ",
    "sg:tags":[
        "fast"
    ],
    "wof:name":"5877 Corporation",
    "wof:placetype":"venue"
},
  "geometry": {"coordinates":[-74.060141,40.875684],"type":"Point"}
}