{
  "type": "Feature",
  "properties": {
    "addr:full":"1870 Kuser Rd Trenton NJ 08690",
    "addr:housenumber":"1870",
    "addr:postcode":"08690",
    "addr:street":"Kuser Rd",
    "iso:country":"US",
    "sg:address":"1870 Kuser Rd",
    "sg:city":"Trenton",
    "sg:classifiers":[
        {
            "category":"Retail",
            "subcategory":"Auto Repair",
            "type":"Services"
        }
    ],
    "sg:phone":"+1 609 581 4885",
    "sg:postcode":"08690",
    "sg:province":"NJ",
    "sg:tags":[
        "automotive"
    ],
    "wof:name":"Hamilton Auto Clinic Inc",
    "wof:placetype":"venue"
},
  "geometry": {"coordinates":[-74.68919699999999,40.205664],"type":"Point"}
}