{
  "type": "Feature",
  "properties": {
    "iso:country":"US",
    "sg:address":"999 Stuyvesant Ave",
    "sg:city":"Irvington",
    "sg:classifiers":[
        {
            "category":"Freight",
            "type":"Transportation"
        }
    ],
    "sg:phone":"+1 973 416 0746",
    "sg:postcode":"07111",
    "sg:province":"NJ",
    "sg:tags":[
        "operator",
        "local",
        "trucking"
    ],
    "wof:name":"Tony Commercial Delivery Svcs",
    "wof:placetype":"venue"
},
  "geometry": {"coordinates":[-74.24802099999999,40.716775],"type":"Point"}
}