{
  "type": "Feature",
  "properties": {
    "addr:full":"147 Cincinnati Ave Egg Harbor City NJ 08215",
    "addr:housenumber":"147",
    "addr:postcode":"08215",
    "addr:street":"Cincinnati Ave",
    "iso:country":"US",
    "sg:address":"147 Cincinnati Ave",
    "sg:city":"Egg Harbor City",
    "sg:classifiers":[
        {
            "category":"Retail",
            "subcategory":"Auto Repair",
            "type":"Services"
        }
    ],
    "sg:phone":"+1   ",
    "sg:postcode":"08215",
    "sg:province":"NJ",
    "sg:tags":[
        "general"
    ],
    "wof:name":"Reliable Home & Auto Repairs",
    "wof:placetype":"venue"
},
  "geometry": {"coordinates":[-74.645544,39.528776],"type":"Point"}
}