{
  "type": "Feature",
  "properties": {
    "iso:country":"US",
    "sg:address":"17 N Essex Ave",
    "sg:city":"Orange",
    "sg:classifiers":[
        {
            "category":"Manufacturing",
            "subcategory":"Printing",
            "type":"Manufacturing & Wholesale Goods"
        }
    ],
    "sg:phone":"+1 973 674 8000",
    "sg:postcode":"07050",
    "sg:province":"NJ",
    "sg:tags":[
        "newspaper"
    ],
    "wof:name":"East Orange Record",
    "wof:placetype":"venue"
},
  "geometry": {"coordinates":[-74.22926200000001,40.775025],"type":"Point"}
}