{
  "type": "Feature",
  "properties": {
    "addr:full":"381 Chestnut St Union NJ 07083",
    "addr:housenumber":"381",
    "addr:postcode":"07083",
    "addr:street":"Chestnut St",
    "iso:country":"US",
    "sg:address":"381 Chestnut St",
    "sg:city":"Union",
    "sg:classifiers":[
        {
            "category":"Health Services",
            "subcategory":"Doctor",
            "type":"Services"
        }
    ],
    "sg:phone":"+1 908 688 8007",
    "sg:postcode":"07083",
    "sg:province":"NJ",
    "sg:tags":[
        "physician",
        "surgeon",
        "medical"
    ],
    "wof:name":"Union Pediatric Association",
    "wof:placetype":"venue"
},
  "geometry": {"coordinates":[-74.268429,40.680443],"type":"Point"}
}