{
  "type": "Feature",
  "properties": {
    "iso:country":"US",
    "sg:address":"149 South St",
    "sg:city":"Newark",
    "sg:classifiers":[
        {
            "category":"Restaurant",
            "type":"Food & Drink"
        }
    ],
    "sg:phone":"+1 973 465 1895",
    "sg:postcode":"07114",
    "sg:province":"NJ",
    "sg:tags":[
        "delicatessen"
    ],
    "wof:name":"Maria's Sweet Deli",
    "wof:placetype":"venue"
},
  "geometry": {"coordinates":[-74.175155,40.723335],"type":"Point"}
}