{
  "type": "Feature",
  "properties": {
    "iso:country":"US",
    "sg:address":"90 Maple Ave",
    "sg:city":"Morristown",
    "sg:classifiers":[
        {
            "category":"Banks & Credit Unions",
            "subcategory":"Atm",
            "type":"Services"
        }
    ],
    "sg:phone":"+1 973 267 0220",
    "sg:postcode":"07960",
    "sg:province":"NJ",
    "sg:tags":[
        "bankruptcy"
    ],
    "wof:name":"Mellinger Sanders & Kartzman Llc",
    "wof:placetype":"venue"
},
  "geometry": {"coordinates":[-74.477898,40.791599],"type":"Point"}
}