{
  "type": "Feature",
  "properties": {
    "iso:country":"US",
    "sg:address":"7211 Elm Ct",
    "sg:city":"Monmouth Junction",
    "sg:classifiers":[
        {
            "category":"Communications",
            "type":"Services"
        }
    ],
    "sg:phone":"+1 732 669 6731",
    "sg:postcode":"08852",
    "sg:province":"NJ",
    "sg:tags":[
        "communication"
    ],
    "wof:name":"Wang Communications",
    "wof:placetype":"venue"
},
  "geometry": {"coordinates":[-74.55712699999999,40.388836],"type":"Point"}
}