{
  "type": "Feature",
  "properties": {
    "addr:full":"338 President St Saddle Brook NJ 07663",
    "addr:housenumber":"338",
    "addr:postcode":"07663",
    "addr:street":"President St",
    "iso:country":"US",
    "sg:address":"338 President St",
    "sg:city":"Saddle Brook",
    "sg:classifiers":[
        {
            "category":"Real Estate",
            "subcategory":"Surveying",
            "type":"Services"
        }
    ],
    "sg:phone":"+1 201 262 5308",
    "sg:postcode":"07663",
    "sg:province":"NJ",
    "sg:tags":[
        "surveyor"
    ],
    "wof:name":"Troast Surveying",
    "wof:placetype":"venue"
},
  "geometry": {"coordinates":[-74.097689,40.887102],"type":"Point"}
}