{
  "type": "Feature",
  "properties": {
    "addr:full":"65 State Rte 17 Paramus NJ 07652",
    "addr:housenumber":"65",
    "addr:postcode":"07652",
    "addr:street":"State Rte 17",
    "iso:country":"US",
    "sg:address":"65 State Rte 17",
    "sg:city":"Paramus",
    "sg:classifiers":[
        {
            "category":"Building & Trades",
            "subcategory":"Construction",
            "type":"Services"
        }
    ],
    "sg:phone":"+1 201 599 1499",
    "sg:postcode":"07652",
    "sg:province":"NJ",
    "sg:tags":[
        "tile",
        "dealer"
    ],
    "wof:name":"Porcelanosa",
    "wof:placetype":"venue"
},
  "geometry": {"coordinates":[-74.072641,40.917995],"type":"Point"}
}