{
  "type": "Feature",
  "properties": {
    "addr:full":"700 Cinnaminson Ave Ste 2 Palmyra NJ 08065",
    "addr:housenumber":"700",
    "addr:postcode":"08065",
    "addr:street":"Cinnaminson Ave Ste 2",
    "iso:country":"US",
    "sg:address":"700 Cinnaminson Ave Ste 2",
    "sg:city":"Palmyra",
    "sg:classifiers":[
        {
            "category":"Real Estate",
            "subcategory":"Real Estate Services",
            "type":"Services"
        },
        {
            "category":"Real Estate",
            "subcategory":"Surveying",
            "type":"Services"
        }
    ],
    "sg:phone":"+1 856 786 6566",
    "sg:postcode":"08065",
    "sg:province":"NJ",
    "sg:tags":[
        "industrial",
        "appraisers-commercial",
        "appraiser"
    ],
    "wof:name":"Stephen D Neely & Associates",
    "wof:placetype":"venue"
},
  "geometry": {"coordinates":[-75.021027,40.00222],"type":"Point"}
}