{
  "type": "Feature",
  "properties": {
    "addr:full":"200 Grand Cove Way Edgewater NJ 07020",
    "addr:housenumber":"200",
    "addr:postcode":"07020",
    "addr:street":"Grand Cove Way",
    "iso:country":"US",
    "sg:address":"200 Grand Cove Way",
    "sg:city":"Edgewater",
    "sg:classifiers":[
        {
            "category":"Health Services",
            "subcategory":"Doctor",
            "type":"Services"
        }
    ],
    "sg:phone":"+1 201 941 4204",
    "sg:postcode":"07020",
    "sg:province":"NJ",
    "wof:name":"Todd Sherwood",
    "wof:placetype":"venue"
},
  "geometry": {"coordinates":[-73.97436399999999,40.825313],"type":"Point"}
}