{
  "type": "Feature",
  "properties": {
    "iso:country":"US",
    "sg:address":"101 N Beverwyck Rd",
    "sg:city":"Lake Hiawatha",
    "sg:classifiers":[
        {
            "category":"Professional",
            "subcategory":"Credit Reporting & Collection",
            "type":"Services"
        }
    ],
    "sg:phone":"+1 973 402 0229",
    "sg:postcode":"07034",
    "sg:province":"NJ",
    "wof:name":"Collection Services Enterprise",
    "wof:placetype":"venue"
},
  "geometry": {"coordinates":[-74.381934,40.883903],"type":"Point"}
}