{
  "type": "Feature",
  "properties": {
    "addr:full":"330 E Virginia Ave Penns Grove NJ 08008",
    "addr:housenumber":"330",
    "addr:postcode":"08008",
    "addr:street":"E Virginia Ave",
    "iso:country":"US",
    "sg:address":"330 E Virginia Ave",
    "sg:city":"Penns Grove",
    "sg:classifiers":[
        {
            "category":"Personal",
            "type":"Services"
        }
    ],
    "sg:phone":"+1   ",
    "sg:postcode":"08008",
    "sg:province":"NJ",
    "wof:name":"Rays Makin",
    "wof:placetype":"venue"
},
  "geometry": {"coordinates":[-74.25471899999999,39.55257],"type":"Point"}
}