{
  "type": "Feature",
  "properties": {
    "iso:country":"US",
    "sg:address":"60 Washington St",
    "sg:city":"Morristown",
    "sg:classifiers":[
        {
            "category":"Government",
            "subcategory":"Office",
            "type":"Public Place"
        }
    ],
    "sg:phone":"+1 973 656 4058",
    "sg:postcode":"07960",
    "sg:province":"NJ",
    "wof:name":"Honorable Deanne Wilson",
    "wof:placetype":"venue"
},
  "geometry": {"coordinates":[-74.485045,40.798693],"type":"Point"}
}