{
  "type": "Feature",
  "properties": {
    "iso:country":"US",
    "sg:address":"208 Harrison St # 1",
    "sg:city":"Nutley",
    "sg:classifiers":[
        {
            "category":"Building & Trades",
            "subcategory":"Plumbing",
            "type":"Services"
        }
    ],
    "sg:phone":"+1 973 284 1173",
    "sg:postcode":"07110",
    "sg:province":"NJ",
    "wof:name":"T-Mont Inc",
    "wof:placetype":"venue"
},
  "geometry": {"coordinates":[-74.16573,40.812552],"type":"Point"}
}