{
  "type": "Feature",
  "properties": {
    "iso:country":"US",
    "sg:address":"262 Harrison St",
    "sg:city":"Passaic",
    "sg:classifiers":[
        {
            "category":"Real Estate",
            "subcategory":"Real Estate Operator",
            "type":"Services"
        }
    ],
    "sg:phone":"+1 973 779 4748",
    "sg:postcode":"07055",
    "sg:province":"NJ",
    "sg:tags":[
        "apartment"
    ],
    "wof:name":"Lexington Garden Apartments",
    "wof:placetype":"venue"
},
  "geometry": {"coordinates":[-74.127197,40.869099],"type":"Point"}
}