{
  "type": "Feature",
  "properties": {
    "iso:country":"US",
    "sg:address":"948 Cherry Valley Rd",
    "sg:city":"Princeton",
    "sg:classifiers":[
        {
            "category":"Professional",
            "subcategory":"Employment Agencies",
            "type":"Services"
        }
    ],
    "sg:phone":"+1   ",
    "sg:postcode":"08540",
    "sg:province":"NJ",
    "sg:tags":[
        "technical",
        "recruiter"
    ],
    "wof:name":"Princeton Technology Solutions",
    "wof:placetype":"venue"
},
  "geometry": {"coordinates":[-74.72176,40.375375],"type":"Point"}
}