{
  "type": "Feature",
  "properties": {
    "addr:full":"401 Park Ave Scotch Plains NJ 07076",
    "addr:housenumber":"401",
    "addr:postcode":"07076",
    "addr:street":"Park Ave",
    "iso:country":"US",
    "sg:address":"401 Park Ave",
    "sg:city":"Scotch Plains",
    "sg:classifiers":[
        {
            "category":"Shopping",
            "subcategory":"Hobbies, Toys, & Games",
            "type":"Retail Goods"
        }
    ],
    "sg:phone":"+1 908 322 2676",
    "sg:postcode":"07076",
    "sg:province":"NJ",
    "sg:tags":[
        "model",
        "supply"
    ],
    "wof:name":"Collection",
    "wof:placetype":"venue"
},
  "geometry": {"coordinates":[-74.396636,40.649525],"type":"Point"}
}