{
  "type": "Feature",
  "properties": {
    "addr:full":"2322 Route 38 Cherry Hill NJ 08002",
    "addr:housenumber":"2322",
    "addr:postcode":"08002",
    "addr:street":"Route 38",
    "iso:country":"US",
    "sg:address":"2322 Route 38",
    "sg:city":"Cherry Hill",
    "sg:classifiers":[
        {
            "category":"Airline",
            "type":"Transportation"
        },
        {
            "category":"Retail",
            "subcategory":"Auto Repair",
            "type":"Services"
        }
    ],
    "sg:phone":"+1 856 667 8400",
    "sg:postcode":"08002",
    "sg:province":"NJ",
    "sg:tags":[
        "airport"
    ],
    "wof:name":"Budget",
    "wof:placetype":"venue"
},
  "geometry": {"coordinates":[-75.024902,39.938801],"type":"Point"}
}