{
  "type": "Feature",
  "properties": {
    "addr:full":"519 Kennedy St Palmyra NJ 08065",
    "addr:housenumber":"519",
    "addr:postcode":"08065",
    "addr:street":"Kennedy St",
    "iso:country":"US",
    "sg:address":"519 Kennedy St",
    "sg:city":"Palmyra",
    "sg:classifiers":[
        {
            "category":"Organizations",
            "subcategory":"Religious Organization",
            "type":"Services"
        }
    ],
    "sg:phone":"+1 856 829 9811",
    "sg:postcode":"08065",
    "sg:province":"NJ",
    "sg:tags":[
        "church"
    ],
    "wof:name":"Miller's Temple Church Of God",
    "wof:placetype":"venue"
},
  "geometry": {"coordinates":[-75.034049,40.002993],"type":"Point"}
}