{
  "type": "Feature",
  "properties": {
    "addr:full":"2 Fair Lawn Ave Fair Lawn NJ 07410",
    "addr:housenumber":"2",
    "addr:postcode":"07410",
    "addr:street":"Fair Lawn Ave",
    "iso:country":"US",
    "sg:address":"2 Fair Lawn Ave",
    "sg:city":"Fair Lawn",
    "sg:classifiers":[
        {
            "category":"Insurance",
            "subcategory":"Insurance Agent",
            "type":"Services"
        }
    ],
    "sg:phone":"+1 201 797 4800",
    "sg:postcode":"07410",
    "sg:province":"NJ",
    "sg:tags":[
        "audit"
    ],
    "sg:website":"www.geninfoserv.com",
    "wof:name":"General Information Svc LLC",
    "wof:placetype":"venue"
},
  "geometry": {"coordinates":[-74.113941,40.941024],"type":"Point"}
}