{
  "type": "Feature",
  "properties": {
    "iso:country":"US",
    "sg:address":"1305 Blackwood Clementon Rd",
    "sg:city":"Clementon",
    "sg:classifiers":[
        {
            "category":"Education",
            "subcategory":"College",
            "type":"Public Place"
        },
        {
            "category":"Education",
            "subcategory":"Vocational School",
            "type":"Public Place"
        },
        {
            "category":"Education",
            "subcategory":"School",
            "type":"Public Place"
        }
    ],
    "sg:phone":"+1 888 259 4664",
    "sg:postcode":"08021",
    "sg:province":"NJ",
    "sg:tags":[
        "business",
        "beauty"
    ],
    "sg:website":"http://www.beautyschools.edu/yp",
    "wof:name":"Empire Beauty Schools",
    "wof:placetype":"venue"
},
  "geometry": {"coordinates":[-75.029169,39.803938],"type":"Point"}
}