{
  "type": "Feature",
  "properties": {
    "iso:country":"US",
    "sg:address":"502 Springfield Ave",
    "sg:city":"Newark",
    "sg:classifiers":[
        {
            "category":"Shopping",
            "type":"Retail Goods"
        }
    ],
    "sg:phone":"+1 973 824 0808",
    "sg:postcode":"07103",
    "sg:province":"NJ",
    "sg:tags":[
        "cosmetic",
        "perfume"
    ],
    "wof:name":"Ziah's Beauty Supply",
    "wof:placetype":"venue"
},
  "geometry": {"coordinates":[-74.20285800000001,40.731901],"type":"Point"}
}