{
  "type": "Feature",
  "properties": {
    "addr:full":"2738 John F Kennedy Blvd Jersey City NJ 07306",
    "addr:housenumber":"2738",
    "addr:postcode":"07306",
    "addr:street":"John F Kennedy Blvd",
    "iso:country":"US",
    "sg:address":"2738 John F Kennedy Blvd",
    "sg:city":"Jersey City",
    "sg:classifiers":[
        {
            "category":"Health Services",
            "subcategory":"Doctor",
            "type":"Services"
        }
    ],
    "sg:phone":"+1 201 653 4474",
    "sg:postcode":"07306",
    "sg:province":"NJ",
    "sg:tags":[
        "dentist"
    ],
    "wof:name":"Hudson County Orthodontics",
    "wof:placetype":"venue"
},
  "geometry": {"coordinates":[-74.068794,40.729731],"type":"Point"}
}