{
  "type": "Feature",
  "properties": {
    "addr:full":"18 Deerfield Rd Wayne NJ 07470",
    "addr:housenumber":"18",
    "addr:postcode":"07470",
    "addr:street":"Deerfield Rd",
    "iso:country":"US",
    "sg:address":"18 Deerfield Rd",
    "sg:city":"Wayne",
    "sg:classifiers":[
        {
            "category":"Travel",
            "subcategory":"Travel Agent",
            "type":"Entertainment"
        }
    ],
    "sg:phone":"+1 973 616 7423",
    "sg:postcode":"07470",
    "sg:province":"NJ",
    "sg:tags":[
        "agency",
        "bureau"
    ],
    "wof:name":"Caputo's Travel World",
    "wof:placetype":"venue"
},
  "geometry": {"coordinates":[-74.270118,40.965995],"type":"Point"}
}