{
  "type": "Feature",
  "properties": {
    "addr:full":"288 Spring Valley Rd Park Ridge NJ 07656",
    "addr:housenumber":"288",
    "addr:postcode":"07656",
    "addr:street":"Spring Valley;Park",
    "iso:country":"US",
    "sg:address":"288 Spring Valley Rd",
    "sg:city":"Park Ridge",
    "sg:classifiers":[
        {
            "category":"Home & Garden",
            "subcategory":"Building Materials",
            "type":"Retail Goods"
        }
    ],
    "sg:phone":"+1   ",
    "sg:postcode":"07656",
    "sg:province":"NJ",
    "wof:name":"Aparteny Inc",
    "wof:placetype":"venue"
},
  "geometry": {"coordinates":[-74.05144199999999,41.048281],"type":"Point"}
}