{
  "type": "Feature",
  "properties": {
    "addr:full":"4009 US Hwy 9 Howell NJ 07731",
    "addr:housenumber":"4009",
    "addr:postcode":"07731",
    "addr:street":"Us Hwy 9",
    "iso:country":"US",
    "sg:address":"4009 US Hwy 9",
    "sg:city":"Howell",
    "sg:classifiers":[
        {
            "category":"Shopping",
            "subcategory":"Pharmacy",
            "type":"Retail Goods"
        }
    ],
    "sg:phone":"+1 732 905 1150",
    "sg:postcode":"07731",
    "sg:province":"NJ",
    "wof:name":"Drug Fair",
    "wof:placetype":"venue"
},
  "geometry": {"coordinates":[-74.22816,40.152945],"type":"Point"}
}