{
  "type": "Feature",
  "properties": {
    "iso:country":"US",
    "sg:address":"77 Brookwood Rd",
    "sg:city":"Stanhope",
    "sg:classifiers":[
        {
            "category":"Professional",
            "type":"Services"
        }
    ],
    "sg:phone":"+1   ",
    "sg:postcode":"07874",
    "sg:province":"NJ",
    "wof:name":"Air Safe Tech Inc",
    "wof:placetype":"venue"
},
  "geometry": {"coordinates":[-74.698109,40.931326],"type":"Point"}
}