{
  "type": "Feature",
  "properties": {
    "addr:full":"302 11th St Lakewood NJ 08701",
    "addr:housenumber":"302",
    "addr:postcode":"08701",
    "addr:street":"11Th St",
    "iso:country":"US",
    "sg:address":"302 11th St",
    "sg:city":"Lakewood",
    "sg:classifiers":[
        {
            "category":"Professional",
            "type":"Services"
        }
    ],
    "sg:phone":"+1   ",
    "sg:postcode":"08701",
    "sg:province":"NJ",
    "wof:name":"Zicron Gem",
    "wof:placetype":"venue"
},
  "geometry": {"coordinates":[-74.216291,40.10084],"type":"Point"}
}