{
  "type": "Feature",
  "properties": {
    "iso:country":"US",
    "sg:address":"417 Grand St",
    "sg:city":"Roselle",
    "sg:classifiers":[
        {
            "category":"Organizations",
            "subcategory":"Religious Organization",
            "type":"Services"
        }
    ],
    "sg:phone":"+1 908 241 7097",
    "sg:postcode":"07203",
    "sg:province":"NJ",
    "wof:name":"Victory Fellowship Ministries",
    "wof:placetype":"venue"
},
  "geometry": {"coordinates":[-74.248988,40.64957],"type":"Point"}
}