{
  "type": "Feature",
  "properties": {
    "addr:full":"1302 Squirrel Rd Marlton NJ 08053",
    "addr:housenumber":"1302",
    "addr:postcode":"08053",
    "addr:street":"Squirrel Rd",
    "iso:country":"US",
    "sg:address":"1302 Squirrel Rd",
    "sg:city":"Marlton",
    "sg:classifiers":[
        {
            "category":"Wholesale",
            "subcategory":"Apparel",
            "type":"Manufacturing & Wholesale Goods"
        }
    ],
    "sg:phone":"+1 856 985 8367",
    "sg:postcode":"08053",
    "sg:province":"NJ",
    "sg:tags":[
        "shoes-wholesale",
        "footwear",
        "manufacturer"
    ],
    "wof:name":"S T Sales Inc",
    "wof:placetype":"venue"
},
  "geometry": {"coordinates":[-74.866946,39.893132],"type":"Point"}
}