{
  "type": "Feature",
  "properties": {
    "iso:country":"US",
    "sg:address":"89 Plaza Ctr",
    "sg:city":"Secaucus",
    "sg:classifiers":[
        {
            "category":"Restaurant",
            "type":"Food & Drink"
        }
    ],
    "sg:phone":"+1 201 864 0858",
    "sg:postcode":"07094",
    "sg:province":"NJ",
    "sg:tags":[
        "pizza"
    ],
    "sg:website":"plazapizzanj.com/",
    "wof:name":"Plaza Pizza",
    "wof:placetype":"venue"
},
  "geometry": {"coordinates":[-74.057467,40.790365],"type":"Point"}
}