{
  "type": "Feature",
  "properties": {
    "addr:full":"7251 Browning Rd Merchantville NJ 08109",
    "addr:housenumber":"7251",
    "addr:postcode":"08109",
    "addr:street":"Browning Rd",
    "iso:country":"US",
    "sg:address":"7251 Browning Rd",
    "sg:city":"Merchantville",
    "sg:classifiers":[
        {
            "category":"Professional",
            "type":"Services"
        }
    ],
    "sg:phone":"+1   ",
    "sg:postcode":"08109",
    "sg:province":"NJ",
    "wof:name":"Clear Choice USA",
    "wof:placetype":"venue"
},
  "geometry": {"coordinates":[-75.07342,39.931676],"type":"Point"}
}