{
  "type": "Feature",
  "properties": {
    "iso:country":"US",
    "sg:address":"35 Vance Ave",
    "sg:city":"Sicklerville",
    "sg:classifiers":[
        {
            "category":"Freight",
            "type":"Transportation"
        }
    ],
    "sg:phone":"+1 856 232 5593",
    "sg:postcode":"08081",
    "sg:province":"NJ",
    "sg:tags":[
        "operator",
        "local",
        "trucking"
    ],
    "wof:name":"MB Delivery LLC",
    "wof:placetype":"venue"
},
  "geometry": {"coordinates":[-75.015575,39.754184],"type":"Point"}
}