{
  "type": "Feature",
  "properties": {
    "addr:full":"142 E Front St Plainfield NJ 07060",
    "addr:housenumber":"142",
    "addr:postcode":"07060",
    "addr:street":"E Front St",
    "iso:country":"US",
    "sg:address":"142 E Front St",
    "sg:city":"Plainfield",
    "sg:classifiers":[
        {
            "category":"Shopping",
            "subcategory":"Computers & Home Electronics",
            "type":"Retail Goods"
        }
    ],
    "sg:phone":"+1   ",
    "sg:postcode":"07060",
    "sg:province":"NJ",
    "sg:tags":[
        "detector",
        "metal"
    ],
    "wof:name":"Security International LLC",
    "wof:placetype":"venue"
},
  "geometry": {"coordinates":[-74.422669,40.619461],"type":"Point"}
}