{
  "type": "Feature",
  "properties": {
    "addr:full":"36 Atlantic Dr Brick NJ 08723",
    "addr:housenumber":"36",
    "addr:postcode":"08723",
    "addr:street":"Atlantic Dr",
    "iso:country":"US",
    "sg:address":"36 Atlantic Dr",
    "sg:city":"Brick",
    "sg:classifiers":[
        {
            "category":"Shopping",
            "type":"Retail Goods"
        }
    ],
    "sg:phone":"+1   ",
    "sg:postcode":"08723",
    "sg:province":"NJ",
    "sg:tags":[
        "merchandise"
    ],
    "wof:name":"Canopy Connection",
    "wof:placetype":"venue"
},
  "geometry": {"coordinates":[-74.100104,40.028364],"type":"Point"}
}