{
  "type": "Feature",
  "properties": {
    "iso:country":"US",
    "sg:address":"11 Charlton St",
    "sg:city":"Princeton",
    "sg:classifiers":[
        {
            "category":"Social Services",
            "type":"Services"
        }
    ],
    "sg:phone":"+1 609 683 0336",
    "sg:postcode":"08540",
    "sg:province":"NJ",
    "sg:tags":[
        "worker"
    ],
    "wof:name":"Joan Gottfried Msw",
    "wof:placetype":"venue"
},
  "geometry": {"coordinates":[-74.653662,40.350548],"type":"Point"}
}