{
  "type": "Feature",
  "properties": {
    "iso:country":"US",
    "sg:address":"3104 Atlantic Ave",
    "sg:city":"Atlantic City",
    "sg:classifiers":[
        {
            "category":"Shopping",
            "subcategory":"Gifts & Souvenirs",
            "type":"Retail Goods"
        }
    ],
    "sg:phone":"+1   ",
    "sg:postcode":"08401",
    "sg:province":"NJ",
    "wof:name":"Abedins",
    "wof:placetype":"venue"
},
  "geometry": {"coordinates":[-74.44984100000001,39.353231],"type":"Point"}
}