{
  "type": "Feature",
  "properties": {
    "iso:country":"US",
    "sg:address":"256 Norwood Ave",
    "sg:city":"Deal",
    "sg:classifiers":[
        {
            "category":"Real Estate",
            "subcategory":"Real Estate Operator",
            "type":"Services"
        }
    ],
    "sg:phone":"+1   ",
    "sg:postcode":"07723",
    "sg:province":"NJ",
    "sg:tags":[
        "property",
        "management"
    ],
    "wof:name":"University Property Management",
    "wof:placetype":"venue"
},
  "geometry": {"coordinates":[-74.000839,40.241477],"type":"Point"}
}