{
  "type": "Feature",
  "properties": {
    "iso:country":"US",
    "sg:address":"1459 Lower Ferry Rd",
    "sg:city":"Trenton",
    "sg:classifiers":[
        {
            "category":"Social Services",
            "subcategory":"Child Care",
            "type":"Services"
        }
    ],
    "sg:phone":"+1 609 771 6040",
    "sg:postcode":"08618",
    "sg:province":"NJ",
    "wof:name":"Kids Inc",
    "wof:placetype":"venue"
},
  "geometry": {"coordinates":[-74.79821800000001,40.287166],"type":"Point"}
}