{
  "type": "Feature",
  "properties": {
    "iso:country":"US",
    "sg:address":"2 Cherry Hill Area",
    "sg:city":"Haddonfield",
    "sg:classifiers":[
        {
            "category":"Building & Trades",
            "subcategory":"Plumbing",
            "type":"Services"
        }
    ],
    "sg:phone":"+1 856 428 7377",
    "sg:postcode":"08033",
    "sg:province":"NJ",
    "sg:website":"www.ryanplumbingco.com",
    "wof:name":"Ryan Plumbing Co",
    "wof:placetype":"venue"
},
  "geometry": {"coordinates":[-75.042,39.896198],"type":"Point"}
}