{
  "type": "Feature",
  "properties": {
    "iso:country":"US",
    "sg:address":"720 Monroe St",
    "sg:city":"Hoboken",
    "sg:classifiers":[
        {
            "category":"Education",
            "subcategory":"Dance Studio",
            "type":"Public Place"
        }
    ],
    "sg:phone":"+1 212 686 5678",
    "sg:postcode":"07030",
    "sg:province":"NJ",
    "sg:tags":[
        "instruction",
        "dancing"
    ],
    "sg:website":"www.nycdance.com",
    "wof:name":"N Y City Dance Alliance Inc",
    "wof:placetype":"venue"
},
  "geometry": {"coordinates":[-74.037616,40.747344],"type":"Point"}
}