{
  "type": "Feature",
  "properties": {
    "iso:country":"US",
    "sg:address":"26 Elinora Dr",
    "sg:city":"Wanaque",
    "sg:classifiers":[
        {
            "category":"Shopping",
            "subcategory":"Computers & Home Electronics",
            "type":"Retail Goods"
        }
    ],
    "sg:phone":"+1   ",
    "sg:postcode":"07465",
    "sg:province":"NJ",
    "wof:name":"Mommy Is Watching",
    "wof:placetype":"venue"
},
  "geometry": {"coordinates":[-74.276663,41.059304],"type":"Point"}
}