{
  "type": "Feature",
  "properties": {
    "addr:full":"800 E Park Ave Vineland NJ 08360",
    "addr:housenumber":"800",
    "addr:postcode":"08360",
    "addr:street":"E Park Ave",
    "iso:country":"US",
    "sg:address":"800 E Park Ave",
    "sg:city":"Vineland",
    "sg:classifiers":[
        {
            "category":"Health Services",
            "subcategory":"Hospital",
            "type":"Services"
        }
    ],
    "sg:phone":"+1 856 696 7261",
    "sg:postcode":"08360",
    "sg:province":"NJ",
    "sg:tags":[
        "specialty"
    ],
    "wof:name":"Broken Bottle Club",
    "wof:placetype":"venue"
},
  "geometry": {"coordinates":[-75.01731100000001,39.491294],"type":"Point"}
}