{
  "type": "Feature",
  "properties": {
    "iso:country":"US",
    "sg:address":"229 Main St",
    "sg:city":"Hackettstown",
    "sg:classifiers":[
        {
            "category":"Shopping",
            "subcategory":"Used Merchandise",
            "type":"Retail Goods"
        }
    ],
    "sg:phone":"+1   ",
    "sg:postcode":"07840",
    "sg:province":"NJ",
    "wof:name":"Zofia Consignment",
    "wof:placetype":"venue"
},
  "geometry": {"coordinates":[-74.826899,40.85181],"type":"Point"}
}