{
  "type": "Feature",
  "properties": {
    "addr:full":"21 N Haledon Ave North Haledon NJ 07508",
    "addr:housenumber":"21",
    "addr:postcode":"07508",
    "addr:street":"N Haledon Ave",
    "iso:country":"US",
    "sg:address":"21 N Haledon Ave",
    "sg:city":"North Haledon",
    "sg:classifiers":[
        {
            "category":"Government",
            "subcategory":"Office",
            "type":"Public Place"
        }
    ],
    "sg:phone":"+1 973 247 9660",
    "sg:postcode":"07508",
    "sg:province":"NJ",
    "sg:tags":[
        "armed",
        "force",
        "recruiting"
    ],
    "wof:name":"US Naval Recruiting",
    "wof:placetype":"venue"
},
  "geometry": {"coordinates":[-74.184594,40.962025],"type":"Point"}
}