{
  "type": "Feature",
  "properties": {
    "iso:country":"US",
    "sg:address":"116 Norwood Ave",
    "sg:city":"Deal",
    "sg:classifiers":[
        {
            "category":"Restaurant",
            "type":"Food & Drink"
        }
    ],
    "sg:phone":"+1   ",
    "sg:postcode":"07723",
    "sg:province":"NJ",
    "sg:tags":[
        "eating"
    ],
    "wof:name":"Dalia Restaurant Inc",
    "wof:placetype":"venue"
},
  "geometry": {"coordinates":[-74.000483,40.253816],"type":"Point"}
}