{
  "type": "Feature",
  "properties": {
    "addr:full":"26 Morningside Rd Ocean City NJ 08226",
    "addr:housenumber":"26",
    "addr:postcode":"08226",
    "addr:street":"Morningside Rd",
    "iso:country":"US",
    "sg:address":"26 Morningside Rd",
    "sg:city":"Ocean City",
    "sg:classifiers":[
        {
            "category":"Shopping",
            "subcategory":"Musical Instruments",
            "type":"Retail Goods"
        }
    ],
    "sg:phone":"+1 609 814 1804",
    "sg:postcode":"08226",
    "sg:province":"NJ",
    "sg:tags":[
        "music",
        "dealer"
    ],
    "wof:name":"Strings By The Sea",
    "wof:placetype":"venue"
},
  "geometry": {"coordinates":[-74.55840000000001,39.28593],"type":"Point"}
}