{
  "type": "Feature",
  "properties": {
    "addr:full":"39 W 19th St Bayonne NJ 07002",
    "addr:housenumber":"39",
    "addr:postcode":"07002",
    "addr:street":"W 19Th St",
    "iso:country":"US",
    "sg:address":"39 W 19th St",
    "sg:city":"Bayonne",
    "sg:classifiers":[
        {
            "category":"Professional",
            "type":"Services"
        }
    ],
    "sg:phone":"+1   ",
    "sg:postcode":"07002",
    "sg:province":"NJ",
    "wof:name":"Ofs Corp",
    "wof:placetype":"venue"
},
  "geometry": {"coordinates":[-74.12141099999999,40.661745],"type":"Point"}
}