{
  "type": "Feature",
  "properties": {
    "iso:country":"US",
    "sg:address":"20 Beechwood Ln",
    "sg:city":"Butler",
    "sg:classifiers":[
        {
            "category":"Professional",
            "subcategory":"Management & Consulting",
            "type":"Services"
        }
    ],
    "sg:phone":"+1   ",
    "sg:postcode":"07405",
    "sg:province":"NJ",
    "wof:name":"Tem International Inc",
    "wof:placetype":"venue"
},
  "geometry": {"coordinates":[-74.41464999999999,41.003858],"type":"Point"}
}