{
  "type": "Feature",
  "properties": {
    "iso:country":"US",
    "sg:address":"20 Plains Gap Rd",
    "sg:city":"North Brunswick",
    "sg:classifiers":[
        {
            "category":"Utilities",
            "subcategory":"Telephone",
            "type":"Services"
        }
    ],
    "sg:phone":"+1 732 398 0177",
    "sg:postcode":"08902",
    "sg:province":"NJ",
    "sg:tags":[
        "web",
        "consulting",
        "hosting"
    ],
    "wof:name":"Bigstar Networks Inc",
    "wof:placetype":"venue"
},
  "geometry": {"coordinates":[-74.466795,40.450414],"type":"Point"}
}