{
  "type": "Feature",
  "properties": {
    "iso:country":"US",
    "sg:address":"330 Lanza Ave",
    "sg:city":"Garfield",
    "sg:classifiers":[
        {
            "category":"Building & Trades",
            "subcategory":"Locksmith",
            "type":"Services"
        }
    ],
    "sg:phone":"+1 973 478 3030",
    "sg:postcode":"07026",
    "sg:province":"NJ",
    "sg:tags":[
        "key"
    ],
    "wof:name":"Ace Auto Glass Co",
    "wof:placetype":"venue"
},
  "geometry": {"coordinates":[-74.11170199999999,40.888699],"type":"Point"}
}