{
  "type": "Feature",
  "properties": {
    "addr:full":"1660 White Horse Hamilton Rd Trenton NJ 08690",
    "addr:housenumber":"1660",
    "addr:postcode":"08690",
    "addr:street":"White;Hamilton Rd",
    "iso:country":"US",
    "sg:address":"1660 White Horse Hamilton Rd",
    "sg:city":"Trenton",
    "sg:classifiers":[
        {
            "category":"Health Services",
            "subcategory":"Nursing And Care Facility",
            "type":"Services"
        },
        {
            "category":"Social Services",
            "subcategory":"Adult Care",
            "type":"Services"
        }
    ],
    "sg:phone":"+1 609 586 4600",
    "sg:postcode":"08690",
    "sg:province":"NJ",
    "sg:tags":[
        "home",
        "intermediate",
        "residential"
    ],
    "sg:website":"www.care-one.com",
    "wof:name":"Care One At Hamilton LLC",
    "wof:placetype":"venue"
},
  "geometry": {"coordinates":[-74.675342,40.216644],"type":"Point"}
}