{
  "type": "Feature",
  "properties": {
    "addr:full":"889 Co Rd 519 Blairstown NJ 07825",
    "addr:housenumber":"889",
    "addr:postcode":"07825",
    "addr:street":"Co Rd 519",
    "iso:country":"US",
    "sg:address":"889 Co Rd 519",
    "sg:city":"Blairstown",
    "sg:classifiers":[
        {
            "category":"Building & Trades",
            "subcategory":"Construction",
            "type":"Services"
        }
    ],
    "sg:phone":"+1 908 979 9681",
    "sg:postcode":"07825",
    "sg:province":"NJ",
    "sg:tags":[
        "house"
    ],
    "wof:name":"Burns Construction Maintenance",
    "wof:placetype":"venue"
},
  "geometry": {"coordinates":[-74.880979,40.958836],"type":"Point"}
}