{
  "type": "Feature",
  "properties": {
    "iso:country":"US",
    "sg:address":"88 Tyler Pl",
    "sg:city":"South Plainfield",
    "sg:classifiers":[
        {
            "category":"Professional",
            "type":"Services"
        }
    ],
    "sg:phone":"+1 908 757 5557",
    "sg:postcode":"07080",
    "sg:province":"NJ",
    "sg:tags":[
        "establishment"
    ],
    "wof:name":"Cardre Inc",
    "wof:placetype":"venue"
},
  "geometry": {"coordinates":[-74.430363,40.562127],"type":"Point"}
}