{
  "type": "Feature",
  "properties": {
    "addr:full":"300 Belvidere Ave Washington NJ 07882",
    "addr:housenumber":"300",
    "addr:postcode":"07882",
    "addr:street":"Belvidere Ave",
    "iso:country":"US",
    "sg:address":"300 Belvidere Ave",
    "sg:city":"Washington",
    "sg:classifiers":[
        {
            "category":"Building & Trades",
            "subcategory":"Construction",
            "type":"Services"
        }
    ],
    "sg:phone":"+1 908 689 8196",
    "sg:postcode":"07882",
    "sg:province":"NJ",
    "sg:tags":[
        "house"
    ],
    "wof:name":"Andrew Turner Woodworking",
    "wof:placetype":"venue"
},
  "geometry": {"coordinates":[-74.985884,40.766449],"type":"Point"}
}