{
  "type": "Feature",
  "properties": {
    "iso:country":"US",
    "sg:address":"229 Main St",
    "sg:city":"Hackettstown",
    "sg:classifiers":[
        {
            "category":"Building & Trades",
            "subcategory":"Plumbing",
            "type":"Services"
        }
    ],
    "sg:phone":"+1 908 852 4497",
    "sg:postcode":"07840",
    "sg:province":"NJ",
    "sg:tags":[
        "contractor"
    ],
    "wof:name":"All Temp Service Company Inc",
    "wof:placetype":"venue"
},
  "geometry": {"coordinates":[-74.826899,40.85181],"type":"Point"}
}