{
  "type": "Feature",
  "properties": {
    "addr:full":"15 Ln of Acres Vincentown NJ 08088",
    "addr:postcode":"08088",
    "addr:street":"15 Ln",
    "iso:country":"US",
    "sg:address":"15 Ln of Acres",
    "sg:city":"Vincentown",
    "sg:classifiers":[
        {
            "category":"Professional",
            "subcategory":"Business Services",
            "type":"Services"
        }
    ],
    "sg:phone":"+1 609 268 8426",
    "sg:postcode":"08088",
    "sg:province":"NJ",
    "wof:name":"Spectrum Maping LLC",
    "wof:placetype":"venue"
},
  "geometry": {"coordinates":[-74.709874,39.80574],"type":"Point"}
}