{
  "type": "Feature",
  "properties": {
    "iso:country":"US",
    "sg:address":"1375 River Rd",
    "sg:city":"Edgewater",
    "sg:classifiers":[
        {
            "category":"Professional",
            "subcategory":"Lawyer & Legal Services",
            "type":"Services"
        }
    ],
    "sg:phone":"+1 201 343 5665",
    "sg:postcode":"07020",
    "sg:province":"NJ",
    "wof:name":"Lois Lipton Attourny At Law",
    "wof:placetype":"venue"
},
  "geometry": {"coordinates":[-73.969419,40.841432],"type":"Point"}
}