{
  "type": "Feature",
  "properties": {
    "addr:full":"1045 Asbury Ave Ocean City NJ 08226",
    "addr:housenumber":"1045",
    "addr:postcode":"08226",
    "addr:street":"Asbury Ave",
    "iso:country":"US",
    "sg:address":"1045 Asbury Ave",
    "sg:city":"Ocean City",
    "sg:classifiers":[
        {
            "category":"Manufacturing",
            "subcategory":"Printing",
            "type":"Manufacturing & Wholesale Goods"
        }
    ],
    "sg:phone":"+1 609 398 4414",
    "sg:postcode":"08226",
    "sg:province":"NJ",
    "sg:tags":[
        "lithographic",
        "commercial"
    ],
    "wof:name":"OCS Printing",
    "wof:placetype":"venue"
},
  "geometry": {"coordinates":[-74.578622,39.277085],"type":"Point"}
}