{
  "type": "Feature",
  "properties": {
    "iso:country":"US",
    "sg:address":"1125 Ironwood St",
    "sg:city":"Trenton",
    "sg:classifiers":[
        {
            "category":"Professional",
            "subcategory":"Management & Consulting",
            "type":"Services"
        }
    ],
    "sg:phone":"+1   ",
    "sg:postcode":"08640",
    "sg:province":"NJ",
    "sg:tags":[
        "retail",
        "direct",
        "sales"
    ],
    "wof:name":"Derek Nemier",
    "wof:placetype":"venue"
},
  "geometry": {"coordinates":[-74.632949,39.99181],"type":"Point"}
}