{
  "type": "Feature",
  "properties": {
    "iso:country":"US",
    "sg:address":"303 Sicomac Ave",
    "sg:city":"Wyckoff",
    "sg:classifiers":[
        {
            "category":"Real Estate",
            "subcategory":"Real Estate Operator",
            "type":"Services"
        }
    ],
    "sg:phone":"+1 201 848 5952",
    "sg:postcode":"07481",
    "sg:province":"NJ",
    "sg:tags":[
        "apartment"
    ],
    "wof:name":"Evergreen Court",
    "wof:placetype":"venue"
},
  "geometry": {"coordinates":[-74.170441,40.983856],"type":"Point"}
}