{
  "type": "Feature",
  "properties": {
    "iso:country":"US",
    "sg:address":"18 Faber Pl",
    "sg:city":"Garfield",
    "sg:classifiers":[
        {
            "category":"Autos & Motor Vehicles",
            "subcategory":"Automobile Sales",
            "type":"Retail Goods"
        }
    ],
    "sg:phone":"+1 845 624 1914",
    "sg:postcode":"07026",
    "sg:province":"NJ",
    "sg:tags":[
        "limo"
    ],
    "wof:name":"Empress Limousine Inc",
    "wof:placetype":"venue"
},
  "geometry": {"coordinates":[-74.111844,40.871293],"type":"Point"}
}