{
  "type": "Feature",
  "properties": {
    "iso:country":"US",
    "sg:address":"130 Division St",
    "sg:city":"Manahawkin",
    "sg:classifiers":[
        {
            "category":"Professional",
            "subcategory":"Lawyer & Legal Services",
            "type":"Services"
        }
    ],
    "sg:phone":"+1 609 597 8149",
    "sg:postcode":"08050",
    "sg:province":"NJ",
    "sg:tags":[
        "attorney"
    ],
    "wof:name":"Timothy Mar Cunha",
    "wof:placetype":"venue"
},
  "geometry": {"coordinates":[-74.255353,39.699782],"type":"Point"}
}