{
  "type": "Feature",
  "properties": {
    "addr:full":"20 E Forest Ave Englewood NJ 07631",
    "addr:housenumber":"20",
    "addr:postcode":"07631",
    "addr:street":"E Forest Ave",
    "iso:country":"US",
    "sg:address":"20 E Forest Ave",
    "sg:city":"Englewood",
    "sg:classifiers":[
        {
            "category":"Personal",
            "subcategory":"Beauty Salon",
            "type":"Services"
        }
    ],
    "sg:phone":"+1 201 569 7319",
    "sg:postcode":"07631",
    "sg:province":"NJ",
    "wof:name":"Max Doobie Unisex",
    "wof:placetype":"venue"
},
  "geometry": {"coordinates":[-73.979006,40.884469],"type":"Point"}
}