{
  "type": "Feature",
  "properties": {
    "iso:country":"US",
    "sg:address":"7 Alan Dr",
    "sg:city":"Fairfield",
    "sg:classifiers":[
        {
            "category":"Shopping",
            "subcategory":"Clothing, Apparel, & Fashions",
            "type":"Retail Goods"
        }
    ],
    "sg:phone":"+1 973 882 3802",
    "sg:postcode":"07004",
    "sg:province":"NJ",
    "sg:tags":[
        "item",
        "boutique"
    ],
    "wof:name":"Holiday House Boutique",
    "wof:placetype":"venue"
},
  "geometry": {"coordinates":[-74.305907,40.883486],"type":"Point"}
}