{
  "type": "Feature",
  "properties": {
    "addr:full":"612 N Maple Ave Ho Ho Kus NJ 07423",
    "addr:housenumber":"612",
    "addr:postcode":"07423",
    "addr:street":"N Maple Ave",
    "iso:country":"US",
    "sg:address":"612 N Maple Ave",
    "sg:city":"Ho Ho Kus",
    "sg:classifiers":[
        {
            "category":"Education",
            "subcategory":"Special Training",
            "type":"Public Place"
        }
    ],
    "sg:phone":"+1 201 652 1994",
    "sg:postcode":"07423",
    "sg:province":"NJ",
    "sg:tags":[
        "craft"
    ],
    "wof:name":"Close Knit",
    "wof:placetype":"venue"
},
  "geometry": {"coordinates":[-74.11050299999999,40.996498],"type":"Point"}
}