{
  "type": "Feature",
  "properties": {
    "addr:full":"100 Front St Elmer NJ 08318",
    "addr:housenumber":"100",
    "addr:postcode":"08318",
    "addr:street":"Front St",
    "iso:country":"US",
    "sg:address":"100 Front St",
    "sg:city":"Elmer",
    "sg:classifiers":[
        {
            "category":"Wholesale",
            "subcategory":"Painting Supplies",
            "type":"Manufacturing & Wholesale Goods"
        },
        {
            "category":"Home & Garden",
            "subcategory":"Garden Supply",
            "type":"Retail Goods"
        },
        {
            "category":"Wholesale",
            "subcategory":"Construction Materials",
            "type":"Manufacturing & Wholesale Goods"
        },
        {
            "category":"Home & Garden",
            "subcategory":"Hardware",
            "type":"Retail Goods"
        }
    ],
    "sg:phone":"+1 856 358 2323",
    "sg:postcode":"08318",
    "sg:province":"NJ",
    "sg:tags":[
        "lawn",
        "paint",
        "equipment",
        "part",
        "plumbing",
        "fixtures",
        "store"
    ],
    "sg:website":"http://www.truevalue.com/schalickmills",
    "wof:name":"Schalick Mills Inc",
    "wof:placetype":"venue"
},
  "geometry": {"coordinates":[-75.171341,39.59494],"type":"Point"}
}