{
  "type": "Feature",
  "properties": {
    "addr:full":"103 W Broadway Paterson NJ 07522",
    "addr:housenumber":"103",
    "addr:postcode":"07522",
    "addr:street":"W Broadway",
    "iso:country":"US",
    "sg:address":"103 W Broadway",
    "sg:city":"Paterson",
    "sg:classifiers":[
        {
            "category":"Restaurant",
            "type":"Food & Drink"
        }
    ],
    "sg:phone":"+1 973 389 0089",
    "sg:postcode":"07522",
    "sg:province":"NJ",
    "wof:name":"Aunt Peggy's Restaurant",
    "wof:placetype":"venue"
},
  "geometry": {"coordinates":[-74.1769,40.922055],"type":"Point"}
}