{
  "type": "Feature",
  "properties": {
    "iso:country":"US",
    "sg:address":"304 Newark Ave",
    "sg:city":"Jersey City",
    "sg:classifiers":[
        {
            "category":"Professional",
            "subcategory":"Lawyer & Legal Services",
            "type":"Services"
        }
    ],
    "sg:phone":"+1 201 386 1777",
    "sg:postcode":"07302",
    "sg:province":"NJ",
    "sg:tags":[
        "attorney"
    ],
    "wof:name":"Jason T Brown Law Office",
    "wof:placetype":"venue"
},
  "geometry": {"coordinates":[-74.05024299999999,40.723976],"type":"Point"}
}