{
  "type": "Feature",
  "properties": {
    "iso:country":"US",
    "sg:address":"80 13th Ave",
    "sg:city":"Paterson",
    "sg:classifiers":[
        {
            "category":"Organizations",
            "subcategory":"Religious Organization",
            "type":"Services"
        }
    ],
    "sg:phone":"+1 973 881 7638",
    "sg:postcode":"07504",
    "sg:province":"NJ",
    "sg:tags":[
        "church"
    ],
    "wof:name":"St Theresa's Church",
    "wof:placetype":"venue"
},
  "geometry": {"coordinates":[-74.141389,40.917099],"type":"Point"}
}