{
  "type": "Feature",
  "properties": {
    "addr:full":"784 Holly Pl Rahway NJ 07065",
    "addr:housenumber":"784",
    "addr:postcode":"07065",
    "addr:street":"Holly Pl",
    "iso:country":"US",
    "sg:address":"784 Holly Pl",
    "sg:city":"Rahway",
    "sg:classifiers":[
        {
            "category":"Professional",
            "subcategory":"Employment Agencies",
            "type":"Services"
        }
    ],
    "sg:phone":"+1 908 337 9420",
    "sg:postcode":"07065",
    "sg:province":"NJ",
    "sg:website":"lighthouse-talent.com/",
    "wof:name":"Lighthouse Recruiting",
    "wof:placetype":"venue"
},
  "geometry": {"coordinates":[-74.2799,40.5977],"type":"Point"}
}