{
  "type": "Feature",
  "properties": {
    "addr:full":"1900 Bell Pl South Plainfield NJ 07080",
    "addr:housenumber":"1900",
    "addr:postcode":"07080",
    "addr:street":"Bell Pl",
    "iso:country":"US",
    "sg:address":"1900 Bell Pl",
    "sg:city":"South Plainfield",
    "sg:classifiers":[
        {
            "category":"Retail",
            "subcategory":"Repair Shop",
            "type":"Services"
        }
    ],
    "sg:phone":"+1   ",
    "sg:postcode":"07080",
    "sg:province":"NJ",
    "wof:name":"Professional Plumbing & Htg",
    "wof:placetype":"venue"
},
  "geometry": {"coordinates":[-74.420596,40.564625],"type":"Point"}
}