{
  "type": "Feature",
  "properties": {
    "addr:full":"131 Wood Ave Middlesex NJ 08846",
    "addr:housenumber":"131",
    "addr:postcode":"08846",
    "addr:street":"Wood Ave",
    "iso:country":"US",
    "sg:address":"131 Wood Ave",
    "sg:city":"Middlesex",
    "sg:classifiers":[
        {
            "category":"Wholesale",
            "subcategory":"Scrap",
            "type":"Manufacturing & Wholesale Goods"
        }
    ],
    "sg:phone":"+1 732 560 5900",
    "sg:postcode":"08846",
    "sg:province":"NJ",
    "sg:tags":[
        "waste"
    ],
    "wof:name":"Premier Environmental Svc",
    "wof:placetype":"venue"
},
  "geometry": {"coordinates":[-74.488247,40.571286],"type":"Point"}
}