{
  "type": "Feature",
  "properties": {
    "iso:country":"US",
    "sg:address":"3015 Atlantic Ave",
    "sg:city":"Atlantic City",
    "sg:classifiers":[
        {
            "category":"Shopping",
            "subcategory":"Department Store",
            "type":"Retail Goods"
        }
    ],
    "sg:phone":"+1 609 340 9969",
    "sg:postcode":"08401",
    "sg:province":"NJ",
    "sg:tags":[
        "shop"
    ],
    "wof:name":"New LA Fiesta Discountdollar",
    "wof:placetype":"venue"
},
  "geometry": {"coordinates":[-74.448466,39.354005],"type":"Point"}
}