{
  "type": "Feature",
  "properties": {
    "iso:country":"US",
    "sg:address":"3576 Quakerbridge Rd",
    "sg:city":"Trenton",
    "sg:classifiers":[
        {
            "category":"Real Estate",
            "subcategory":"Real Estate Agent",
            "type":"Services"
        }
    ],
    "sg:phone":"+1 609 890 4970",
    "sg:postcode":"08619",
    "sg:province":"NJ",
    "sg:tags":[
        "management"
    ],
    "wof:name":"E W Murray Assocs Inc",
    "wof:placetype":"venue"
},
  "geometry": {"coordinates":[-74.675916,40.262187],"type":"Point"}
}