{
  "type": "Feature",
  "properties": {
    "iso:country":"US",
    "sg:address":"22 W Front St",
    "sg:city":"Keyport",
    "sg:classifiers":[
        {
            "category":"Sports & Exercise",
            "subcategory":"Gym",
            "type":"Entertainment"
        }
    ],
    "sg:phone":"+1   ",
    "sg:postcode":"07735",
    "sg:province":"NJ",
    "sg:tags":[
        "food",
        "fitness",
        "physical",
        "facility"
    ],
    "wof:name":"Tnt Health Clubs",
    "wof:placetype":"venue"
},
  "geometry": {"coordinates":[-74.202668,40.437359],"type":"Point"}
}