{
  "type": "Feature",
  "properties": {
    "iso:country":"US",
    "sg:address":"5 Passaic St",
    "sg:city":"Garfield",
    "sg:classifiers":[
        {
            "category":"Food & Beverages",
            "subcategory":"Groceries & Convenience Stores",
            "type":"Retail Goods"
        }
    ],
    "sg:phone":"+1   ",
    "sg:postcode":"07026",
    "sg:province":"NJ",
    "wof:name":"Neves Super Market",
    "wof:placetype":"venue"
},
  "geometry": {"coordinates":[-74.10939,40.865433],"type":"Point"}
}