{
  "type": "Feature",
  "properties": {
    "addr:full":"215 Eldredge Rd Cape May Court House NJ 08210",
    "addr:housenumber":"215",
    "addr:postcode":"08210",
    "addr:street":"Eldredge Rd",
    "iso:country":"US",
    "sg:address":"215 Eldredge Rd",
    "sg:city":"Cape May Court House",
    "sg:classifiers":[
        {
            "category":"Education",
            "subcategory":"School",
            "type":"Public Place"
        }
    ],
    "sg:phone":"+1 609 463 1900",
    "sg:postcode":"08210",
    "sg:province":"NJ",
    "sg:tags":[
        "elementary"
    ],
    "wof:name":"Middle Twp Elementary School No 1",
    "wof:placetype":"venue"
},
  "geometry": {"coordinates":[-74.82379899999999,39.078499],"type":"Point"}
}