{
  "type": "Feature",
  "properties": {
    "addr:full":"718 Brunswick Ave Trenton NJ 08638",
    "addr:housenumber":"718",
    "addr:postcode":"08638",
    "addr:street":"Brunswick Ave",
    "iso:country":"US",
    "sg:address":"718 Brunswick Ave",
    "sg:city":"Trenton",
    "sg:classifiers":[
        {
            "category":"Personal",
            "subcategory":"Barber",
            "type":"Services"
        }
    ],
    "sg:phone":"+1 609 396 6399",
    "sg:postcode":"08638",
    "sg:province":"NJ",
    "sg:tags":[
        "shop"
    ],
    "wof:name":"De Luxe Barber Shop",
    "wof:placetype":"venue"
},
  "geometry": {"coordinates":[-74.753299,40.234838],"type":"Point"}
}