{
  "type": "Feature",
  "properties": {
    "iso:country":"US",
    "sg:address":"503 Covington Pl",
    "sg:city":"Wyckoff",
    "sg:classifiers":[
        {
            "category":"Professional",
            "subcategory":"Lawyer & Legal Services",
            "type":"Services"
        }
    ],
    "sg:phone":"+1 201 847 0438",
    "sg:postcode":"07481",
    "sg:province":"NJ",
    "wof:name":"Maryann D Striano Esq",
    "wof:placetype":"venue"
},
  "geometry": {"coordinates":[-74.184012,41.007561],"type":"Point"}
}