{
  "type": "Feature",
  "properties": {
    "iso:country":"US",
    "sg:address":"181 William Feather Dr",
    "sg:city":"Voorhees",
    "sg:classifiers":[
        {
            "category":"Professional",
            "subcategory":"Accounting & Tax Preparation",
            "type":"Services"
        }
    ],
    "sg:phone":"+1 856 768 6375",
    "sg:postcode":"08043",
    "sg:province":"NJ",
    "wof:name":"Marc I Alexander CPA",
    "wof:placetype":"venue"
},
  "geometry": {"coordinates":[-74.921813,39.82497],"type":"Point"}
}