{
  "type": "Feature",
  "properties": {
    "addr:full":"2200 83rd St North Bergen NJ 07047",
    "addr:housenumber":"2200",
    "addr:postcode":"07047",
    "addr:street":"83Rd St",
    "iso:country":"US",
    "sg:address":"2200 83rd St",
    "sg:city":"North Bergen",
    "sg:classifiers":[
        {
            "category":"Marine",
            "type":"Transportation"
        }
    ],
    "sg:phone":"+1 201 313 1540",
    "sg:postcode":"07047",
    "sg:province":"NJ",
    "sg:tags":[
        "towing"
    ],
    "wof:name":"Mi-Jack Products Inc",
    "wof:placetype":"venue"
},
  "geometry": {"coordinates":[-74.01973599999999,40.81081],"type":"Point"}
}