{
  "type": "Feature",
  "properties": {
    "iso:country":"US",
    "sg:address":"146 S Orange Ave",
    "sg:city":"South Orange",
    "sg:classifiers":[
        {
            "category":"Manufacturing",
            "subcategory":"Building Materials",
            "type":"Manufacturing & Wholesale Goods"
        }
    ],
    "sg:phone":"+1 973 762 7700",
    "sg:postcode":"07079",
    "sg:province":"NJ",
    "sg:tags":[
        "crown",
        "market",
        "easy",
        "molding"
    ],
    "wof:name":"Easy Crown Molding",
    "wof:placetype":"venue"
},
  "geometry": {"coordinates":[-74.253651,40.745033],"type":"Point"}
}