{
  "type": "Feature",
  "properties": {
    "iso:country":"US",
    "sg:address":"33 Carla Way",
    "sg:city":"Trenton",
    "sg:classifiers":[
        {
            "category":"Professional",
            "subcategory":"Business Services",
            "type":"Services"
        }
    ],
    "sg:phone":"+1 609 912 1020",
    "sg:postcode":"08648",
    "sg:province":"NJ",
    "wof:name":"Rama Sasty Kalapatapv",
    "wof:placetype":"venue"
},
  "geometry": {"coordinates":[-74.75088,40.2879],"type":"Point"}
}