{
  "type": "Feature",
  "properties": {
    "iso:country":"US",
    "sg:address":"416 Deuce Dr",
    "sg:city":"Wall Township",
    "sg:classifiers":[
        {
            "category":"Insurance",
            "subcategory":"Insurance Agent",
            "type":"Services"
        }
    ],
    "sg:phone":"+1 732 682 8255",
    "sg:postcode":"07719",
    "sg:province":"NJ",
    "sg:tags":[
        "accident"
    ],
    "wof:name":"Model Benefits",
    "wof:placetype":"venue"
},
  "geometry": {"coordinates":[-74.076662,40.166912],"type":"Point"}
}