{
  "type": "Feature",
  "properties": {
    "addr:full":"514 Williamstown Rd Sicklerville NJ 08081",
    "addr:housenumber":"514",
    "addr:postcode":"08081",
    "addr:street":"Williamstown Rd",
    "iso:country":"US",
    "sg:address":"514 Williamstown Rd",
    "sg:city":"Sicklerville",
    "sg:classifiers":[
        {
            "category":"Shopping",
            "subcategory":"Department Store",
            "type":"Retail Goods"
        },
        {
            "category":"Shopping",
            "subcategory":"Discount & Variety Stores",
            "type":"Retail Goods"
        }
    ],
    "sg:phone":"+1 856 262 8324",
    "sg:postcode":"08081",
    "sg:province":"NJ",
    "wof:name":"Family Dollar Stores",
    "wof:placetype":"venue"
},
  "geometry": {"coordinates":[-74.96790300000001,39.718719],"type":"Point"}
}