{
  "type": "Feature",
  "properties": {
    "iso:country":"US",
    "sg:address":"216 Keats Ave",
    "sg:city":"Elizabeth",
    "sg:classifiers":[
        {
            "category":"Wholesale",
            "subcategory":"Stationery",
            "type":"Manufacturing & Wholesale Goods"
        }
    ],
    "sg:phone":"+1 201 432 1855",
    "sg:postcode":"07208",
    "sg:province":"NJ",
    "sg:tags":[
        "school",
        "toy",
        "ca",
        "drug",
        "supply"
    ],
    "wof:name":"Thrifti House Distributors",
    "wof:placetype":"venue"
},
  "geometry": {"coordinates":[-74.244062,40.671733],"type":"Point"}
}