{
  "type": "Feature",
  "properties": {
    "iso:country":"US",
    "sg:address":"44 Plum Tree Dr",
    "sg:city":"Sewell",
    "sg:classifiers":[
        {
            "category":"Building & Trades",
            "subcategory":"Landscaping Services",
            "type":"Services"
        }
    ],
    "sg:phone":"+1 856 304 5591",
    "sg:postcode":"08080",
    "sg:province":"NJ",
    "sg:tags":[
        "lawn",
        "maintenance",
        "grounds"
    ],
    "wof:name":"Chapman Lawn Care",
    "wof:placetype":"venue"
},
  "geometry": {"coordinates":[-75.08083000000001,39.713954],"type":"Point"}
}