{
  "type": "Feature",
  "properties": {
    "addr:full":"309 Barr Ave Linwood NJ 08221",
    "addr:housenumber":"309",
    "addr:postcode":"08221",
    "addr:street":"Barr Ave",
    "iso:country":"US",
    "sg:address":"309 Barr Ave",
    "sg:city":"Linwood",
    "sg:classifiers":[
        {
            "category":"Building & Trades",
            "subcategory":"Construction",
            "type":"Services"
        }
    ],
    "sg:phone":"+1 609 601 2732",
    "sg:postcode":"08221",
    "sg:province":"NJ",
    "sg:tags":[
        "painter"
    ],
    "wof:name":"Sea Shore Painting & Rstrtn",
    "wof:placetype":"venue"
},
  "geometry": {"coordinates":[-74.571521,39.35596],"type":"Point"}
}