{
  "type": "Feature",
  "properties": {
    "addr:full":"110 State Rte 45 Waterford Works NJ 08062",
    "addr:housenumber":"110",
    "addr:postcode":"08062",
    "addr:street":"State Rte 45",
    "iso:country":"US",
    "sg:address":"110 State Rte 45",
    "sg:city":"Waterford Works",
    "sg:classifiers":[
        {
            "category":"Professional",
            "subcategory":"Employment Agencies",
            "type":"Services"
        }
    ],
    "sg:phone":"+1   ",
    "sg:postcode":"08062",
    "sg:province":"NJ",
    "sg:tags":[
        "help",
        "supply"
    ],
    "wof:name":"Accustaff",
    "wof:placetype":"venue"
},
  "geometry": {"coordinates":[-75.23221700000001,39.725857],"type":"Point"}
}