{
  "type": "Feature",
  "properties": {
    "iso:country":"US",
    "sg:address":"715 Pittsburg Ave",
    "sg:city":"Cape May",
    "sg:classifiers":[
        {
            "category":"Travel",
            "subcategory":"Hotels & Motels",
            "type":"Entertainment"
        }
    ],
    "sg:phone":"+1 609 884 0018",
    "sg:postcode":"08204",
    "sg:province":"NJ",
    "sg:website":"www.capeharbormotorinn.com",
    "wof:name":"Cape Harbor Motor Inn",
    "wof:placetype":"venue"
},
  "geometry": {"coordinates":[-74.90479999999999,38.941101],"type":"Point"}
}