{
  "type": "Feature",
  "properties": {
    "addr:full":"175 Hackensack St East Rutherford NJ 07073",
    "addr:housenumber":"175",
    "addr:postcode":"07073",
    "addr:street":"Hackensack St",
    "iso:country":"US",
    "sg:address":"175 Hackensack St",
    "sg:city":"East Rutherford",
    "sg:classifiers":[
        {
            "category":"Manufacturing",
            "subcategory":"Metals",
            "type":"Manufacturing & Wholesale Goods"
        }
    ],
    "sg:phone":"+1 201 933 2173",
    "sg:postcode":"07073",
    "sg:province":"NJ",
    "sg:tags":[
        "plate",
        "workshop",
        "fabricated"
    ],
    "wof:name":"F P Metal Products Inc",
    "wof:placetype":"venue"
},
  "geometry": {"coordinates":[-74.096451,40.830503],"type":"Point"}
}