{
  "type": "Feature",
  "properties": {
    "addr:full":"11 Pinewood Ln Sicklerville NJ 08081",
    "addr:housenumber":"11",
    "addr:postcode":"08081",
    "addr:street":"Pinewood Ln",
    "iso:country":"US",
    "sg:address":"11 Pinewood Ln",
    "sg:city":"Sicklerville",
    "sg:classifiers":[
        {
            "category":"Organizations",
            "subcategory":"Religious Organization",
            "type":"Services"
        }
    ],
    "sg:phone":"+1 856 728 9446",
    "sg:postcode":"08081",
    "sg:province":"NJ",
    "sg:tags":[
        "clergy"
    ],
    "wof:name":"Faith United Christian Church",
    "wof:placetype":"venue"
},
  "geometry": {"coordinates":[-74.962057,39.707596],"type":"Point"}
}