{
  "type": "Feature",
  "properties": {
    "iso:country":"US",
    "sg:address":"417 Euclid Ave",
    "sg:city":"Allenhurst",
    "sg:classifiers":[
        {
            "category":"Health Services",
            "subcategory":"Doctor",
            "type":"Services"
        }
    ],
    "sg:phone":"+1 732 531 5333",
    "sg:postcode":"07711",
    "sg:province":"NJ",
    "wof:name":"R P Nobile DDS",
    "wof:placetype":"venue"
},
  "geometry": {"coordinates":[-74.005841,40.232987],"type":"Point"}
}