{
  "type": "Feature",
  "properties": {
    "iso:country":"US",
    "sg:address":"501 Rahway Ave",
    "sg:city":"Elizabeth",
    "sg:classifiers":[
        {
            "category":"Shopping",
            "subcategory":"Gifts & Souvenirs",
            "type":"Retail Goods"
        }
    ],
    "sg:phone":"+1 908 354 0326",
    "sg:postcode":"07202",
    "sg:province":"NJ",
    "sg:tags":[
        "party",
        "supply"
    ],
    "wof:name":"Bibi's Flowers & Gifts",
    "wof:placetype":"venue"
},
  "geometry": {"coordinates":[-74.228461,40.656912],"type":"Point"}
}