{
  "type": "Feature",
  "properties": {
    "iso:country":"US",
    "sg:address":"36 4th St",
    "sg:city":"Somerville",
    "sg:classifiers":[
        {
            "category":"Manufacturing",
            "subcategory":"Tools & Machinery",
            "type":"Manufacturing & Wholesale Goods"
        }
    ],
    "sg:phone":"+1 908 685 0025",
    "sg:postcode":"08876",
    "sg:province":"NJ",
    "sg:tags":[
        "packaging",
        "machine",
        "wrapping",
        "mfg"
    ],
    "wof:name":"Kalish",
    "wof:placetype":"venue"
},
  "geometry": {"coordinates":[-74.61261399999999,40.56116],"type":"Point"}
}