{
  "type": "Feature",
  "properties": {
    "iso:country":"US",
    "sg:address":"357 Long Ave",
    "sg:city":"Hillside",
    "sg:classifiers":[
        {
            "category":"Home & Garden",
            "subcategory":"Furniture",
            "type":"Retail Goods"
        }
    ],
    "sg:phone":"+1 908 686 0818",
    "sg:postcode":"07205",
    "sg:province":"NJ",
    "wof:name":"Nationwide Warehouse & Storage",
    "wof:placetype":"venue"
},
  "geometry": {"coordinates":[-74.23781,40.698816],"type":"Point"}
}