{
  "type": "Feature",
  "properties": {
    "addr:full":"464 Sylvan Ave Englewood Cliffs NJ 07632",
    "addr:housenumber":"464",
    "addr:postcode":"07632",
    "addr:street":"Sylvan Ave",
    "iso:country":"US",
    "sg:address":"464 Sylvan Ave",
    "sg:city":"Englewood Cliffs",
    "sg:classifiers":[
        {
            "category":"Restaurant",
            "type":"Food & Drink"
        }
    ],
    "sg:phone":"+1   ",
    "sg:postcode":"07632",
    "sg:province":"NJ",
    "sg:tags":[
        "japanese"
    ],
    "wof:name":"Yong Su San Inc",
    "wof:placetype":"venue"
},
  "geometry": {"coordinates":[-73.952068,40.877135],"type":"Point"}
}