{
  "type": "Feature",
  "properties": {
    "addr:full":"737 Lincoln Blvd Glassboro NJ 08028",
    "addr:housenumber":"737",
    "addr:postcode":"08028",
    "addr:street":"Lincoln Blvd",
    "iso:country":"US",
    "sg:address":"737 Lincoln Blvd",
    "sg:city":"Glassboro",
    "sg:classifiers":[
        {
            "category":"Real Estate",
            "subcategory":"Real Estate Agent",
            "type":"Services"
        }
    ],
    "sg:phone":"+1 856 881 5211",
    "sg:postcode":"08028",
    "sg:province":"NJ",
    "sg:tags":[
        "authorities",
        "housing"
    ],
    "wof:name":"Glassboro Housing Authority",
    "wof:placetype":"venue"
},
  "geometry": {"coordinates":[-75.13068800000001,39.696783],"type":"Point"}
}