{
  "type": "Feature",
  "properties": {
    "iso:country":"US",
    "sg:address":"912 Vanburen Ave",
    "sg:city":"Elizabeth",
    "sg:classifiers":[
        {
            "category":"Wholesale",
            "subcategory":"Scrap",
            "type":"Manufacturing & Wholesale Goods"
        }
    ],
    "sg:phone":"+1 908 355 2468",
    "sg:postcode":"07201",
    "sg:province":"NJ",
    "sg:tags":[
        "material",
        "waste"
    ],
    "wof:name":"John Rocco Scrap Material Inc",
    "wof:placetype":"venue"
},
  "geometry": {"coordinates":[-74.195958,40.681645],"type":"Point"}
}