{
  "type": "Feature",
  "properties": {
    "addr:full":"358 Greenmount Ave Cliffside Park NJ 07010",
    "addr:housenumber":"358",
    "addr:postcode":"07010",
    "addr:street":"Greenmount Ave",
    "iso:country":"US",
    "sg:address":"358 Greenmount Ave",
    "sg:city":"Cliffside Park",
    "sg:classifiers":[
        {
            "category":"Professional",
            "type":"Services"
        }
    ],
    "sg:phone":"+1 201 861 1314",
    "sg:postcode":"07010",
    "sg:province":"NJ",
    "wof:name":"All Service Partition Corp",
    "wof:placetype":"venue"
},
  "geometry": {"coordinates":[-73.990223,40.822667],"type":"Point"}
}