{
  "type": "Feature",
  "properties": {
    "iso:country":"US",
    "sg:address":"109 Nichols St",
    "sg:city":"Newark",
    "sg:classifiers":[
        {
            "category":"Professional",
            "subcategory":"Lawyer & Legal Services",
            "type":"Services"
        }
    ],
    "sg:phone":"+1   ",
    "sg:postcode":"07105",
    "sg:province":"NJ",
    "wof:name":"Turco Law Offices",
    "wof:placetype":"venue"
},
  "geometry": {"coordinates":[-74.163241,40.725094],"type":"Point"}
}