{
  "type": "Feature",
  "properties": {
    "iso:country":"US",
    "sg:address":"108 Cornelia St",
    "sg:city":"Boonton",
    "sg:classifiers":[
        {
            "category":"Personal",
            "subcategory":"Beauty Salon",
            "type":"Services"
        }
    ],
    "sg:phone":"+1 973 316 0500",
    "sg:postcode":"07005",
    "sg:province":"NJ",
    "wof:name":"Cuts Plus More Inc",
    "wof:placetype":"venue"
},
  "geometry": {"coordinates":[-74.409415,40.905933],"type":"Point"}
}