{
  "type": "Feature",
  "properties": {
    "addr:full":"349 E Northfield Rd Livingston NJ 07039",
    "addr:housenumber":"349",
    "addr:postcode":"07039",
    "addr:street":"E Northfield Rd",
    "iso:country":"US",
    "sg:address":"349 E Northfield Rd",
    "sg:city":"Livingston",
    "sg:classifiers":[
        {
            "category":"Personal",
            "subcategory":"Beauty Salon",
            "type":"Services"
        }
    ],
    "sg:phone":"+1 973 669 3335",
    "sg:postcode":"07039",
    "sg:province":"NJ",
    "sg:tags":[
        "treatment",
        "skin"
    ],
    "wof:name":"All Natural Skin Care",
    "wof:placetype":"venue"
},
  "geometry": {"coordinates":[-74.30055400000001,40.770762],"type":"Point"}
}