{
  "type": "Feature",
  "properties": {
    "iso:country":"US",
    "sg:address":"1201 Hampton Ln",
    "sg:city":"Iselin",
    "sg:classifiers":[
        {
            "category":"Real Estate",
            "subcategory":"Real Estate Operator",
            "type":"Services"
        }
    ],
    "sg:phone":"+1 732 283 2617",
    "sg:postcode":"08830",
    "sg:province":"NJ",
    "sg:tags":[
        "apartment"
    ],
    "wof:name":"Woodbridge Hills",
    "wof:placetype":"venue"
},
  "geometry": {"coordinates":[-74.30451100000001,40.562966],"type":"Point"}
}