{
  "type": "Feature",
  "properties": {
    "addr:full":"30 Mount Prospect Ave Belleville NJ 07109",
    "addr:housenumber":"30",
    "addr:postcode":"07109",
    "addr:street":"Mount Prospect Ave",
    "iso:country":"US",
    "sg:address":"30 Mount Prospect Ave",
    "sg:city":"Belleville",
    "sg:classifiers":[
        {
            "category":"Building & Trades",
            "subcategory":"Locksmith",
            "type":"Services"
        }
    ],
    "sg:phone":"+1 973 854 4926",
    "sg:postcode":"07109",
    "sg:province":"NJ",
    "sg:tags":[
        "key"
    ],
    "wof:name":"0 0 24 Hour 7 Day A Emergency Locksmith",
    "wof:placetype":"venue"
},
  "geometry": {"coordinates":[-74.160303,40.788967],"type":"Point"}
}