{
  "type": "Feature",
  "properties": {
    "addr:full":"300 White Horse Pike Stratford NJ 08084",
    "addr:housenumber":"300",
    "addr:postcode":"08084",
    "addr:street":"White Horse Pike",
    "iso:country":"US",
    "sg:address":"300 White Horse Pike",
    "sg:city":"Stratford",
    "sg:classifiers":[
        {
            "category":"Banks & Credit Unions",
            "subcategory":"Bank",
            "type":"Services"
        }
    ],
    "sg:phone":"+1   ",
    "sg:postcode":"08084",
    "sg:province":"NJ",
    "sg:tags":[
        "national"
    ],
    "wof:name":"PNC",
    "wof:placetype":"venue"
},
  "geometry": {"coordinates":[-75.007919,39.836101],"type":"Point"}
}