{
  "type": "Feature",
  "properties": {
    "iso:country":"US",
    "sg:address":"8021 N Crescent Blvd Ste 6",
    "sg:city":"Pennsauken",
    "sg:classifiers":[
        {
            "category":"Wholesale",
            "subcategory":"Machinery & Supplies",
            "type":"Manufacturing & Wholesale Goods"
        },
        {
            "category":"Building & Trades",
            "subcategory":"Electrical",
            "type":"Services"
        }
    ],
    "sg:phone":"+1 856 663 6121",
    "sg:postcode":"08110",
    "sg:province":"NJ",
    "sg:tags":[
        "transmission",
        "industrial",
        "power",
        "equipment"
    ],
    "sg:website":"http://www.powerquip.com",
    "wof:name":"Power Quip Inc",
    "wof:placetype":"venue"
},
  "geometry": {"coordinates":[-75.03694900000001,39.974159],"type":"Point"}
}