{
  "type": "Feature",
  "properties": {
    "addr:full":"88 Pompton Ave Verona NJ 07044",
    "addr:housenumber":"88",
    "addr:postcode":"07044",
    "addr:street":"Pompton Ave",
    "iso:country":"US",
    "sg:address":"88 Pompton Ave",
    "sg:city":"Verona",
    "sg:classifiers":[
        {
            "category":"Professional",
            "subcategory":"Accounting & Tax Preparation",
            "type":"Services"
        }
    ],
    "sg:phone":"+1 973 239 8014",
    "sg:postcode":"07044",
    "sg:province":"NJ",
    "sg:tags":[
        "accountant"
    ],
    "wof:name":"William Tobie Assoc",
    "wof:placetype":"venue"
},
  "geometry": {"coordinates":[-74.229642,40.827421],"type":"Point"}
}