{
  "type": "Feature",
  "properties": {
    "iso:country":"US",
    "sg:address":"746 Black Horse Pike",
    "sg:city":"Pleasantville",
    "sg:classifiers":[
        {
            "category":"Restaurant",
            "type":"Food & Drink"
        }
    ],
    "sg:phone":"+1 609 641 5533",
    "sg:postcode":"08232",
    "sg:province":"NJ",
    "sg:tags":[
        "chinese"
    ],
    "wof:name":"New China Buffet Inc",
    "wof:placetype":"venue"
},
  "geometry": {"coordinates":[-74.539277,39.393812],"type":"Point"}
}