{
  "type": "Feature",
  "properties": {
    "addr:full":"502 Jackson St Camden NJ 08104",
    "addr:housenumber":"502",
    "addr:postcode":"08104",
    "addr:street":"Jackson St",
    "iso:country":"US",
    "sg:address":"502 Jackson St",
    "sg:city":"Camden",
    "sg:classifiers":[
        {
            "category":"Building & Trades",
            "subcategory":"Construction",
            "type":"Services"
        }
    ],
    "sg:phone":"+1 856 757 9486",
    "sg:postcode":"08104",
    "sg:province":"NJ",
    "sg:tags":[
        "residential"
    ],
    "wof:name":"CT General Contractor",
    "wof:placetype":"venue"
},
  "geometry": {"coordinates":[-75.118785,39.924735],"type":"Point"}
}