{
  "type": "Feature",
  "properties": {
    "addr:full":"67 Walnut Ave Clark NJ 07066",
    "addr:housenumber":"67",
    "addr:postcode":"07066",
    "addr:street":"Walnut Ave",
    "iso:country":"US",
    "sg:address":"67 Walnut Ave",
    "sg:city":"Clark",
    "sg:classifiers":[
        {
            "category":"Banks & Credit Unions",
            "subcategory":"Bank",
            "type":"Services"
        }
    ],
    "sg:phone":"+1 732 382 8038",
    "sg:postcode":"07066",
    "sg:province":"NJ",
    "sg:tags":[
        "loan",
        "real estate"
    ],
    "wof:name":"National City Mortgage",
    "wof:placetype":"venue"
},
  "geometry": {"coordinates":[-74.30159399999999,40.629485],"type":"Point"}
}