{
  "type": "Feature",
  "properties": {
    "addr:full":"5505 Marlton Pike Pennsauken NJ 08109",
    "addr:housenumber":"5505",
    "addr:postcode":"08109",
    "addr:street":"Marlton Pike",
    "iso:country":"US",
    "sg:address":"5505 Marlton Pike",
    "sg:city":"Pennsauken",
    "sg:classifiers":[
        {
            "category":"Banks & Credit Unions",
            "subcategory":"Bank",
            "type":"Services"
        }
    ],
    "sg:phone":"+1 856 661 1707",
    "sg:postcode":"08109",
    "sg:province":"NJ",
    "sg:tags":[
        "loan",
        "real estate"
    ],
    "wof:name":"Mortgage Factory",
    "wof:placetype":"venue"
},
  "geometry": {"coordinates":[-75.05879899999999,39.929481],"type":"Point"}
}