{
  "type": "Feature",
  "properties": {
    "addr:full":"1521 Blackwood Clementon Rd Blackwood NJ 08012",
    "addr:housenumber":"1521",
    "addr:postcode":"08012",
    "addr:street":"Blackwood Clementon Rd",
    "iso:country":"US",
    "sg:address":"1521 Blackwood Clementon Rd",
    "sg:city":"Blackwood",
    "sg:classifiers":[
        {
            "category":"Restaurant",
            "type":"Food & Drink"
        }
    ],
    "sg:phone":"+1   ",
    "sg:postcode":"08012",
    "sg:province":"NJ",
    "sg:tags":[
        "eating"
    ],
    "wof:name":"McDonalds",
    "wof:placetype":"venue"
},
  "geometry": {"coordinates":[-75.04441799999999,39.803235],"type":"Point"}
}