{
  "type": "Feature",
  "properties": {
    "addr:full":"216 Newark Ave Jersey City NJ 07302",
    "addr:housenumber":"216",
    "addr:postcode":"07302",
    "addr:street":"Newark Ave",
    "iso:country":"US",
    "sg:address":"216 Newark Ave",
    "sg:city":"Jersey City",
    "sg:classifiers":[
        {
            "category":"Restaurant",
            "type":"Food & Drink"
        }
    ],
    "sg:menulink":"http://www.allmenus.com/nj/jersey-city/55354-taco-king/menu/",
    "sg:phone":"+1 201 420 3352",
    "sg:postcode":"07302",
    "sg:province":"NJ",
    "sg:tags":[
        "mexican"
    ],
    "wof:name":"Taco King",
    "wof:placetype":"venue"
},
  "geometry": {"coordinates":[-74.047284,40.722168],"type":"Point"}
}