{
  "type": "Feature",
  "properties": {
    "addr:full":"14 Village Way Budd Lake NJ 07828",
    "addr:housenumber":"14",
    "addr:postcode":"07828",
    "addr:street":"Village Way",
    "iso:country":"US",
    "sg:address":"14 Village Way",
    "sg:city":"Budd Lake",
    "sg:classifiers":[
        {
            "category":"Professional",
            "subcategory":"Computer Services",
            "type":"Services"
        }
    ],
    "sg:phone":"+1   ",
    "sg:postcode":"07828",
    "sg:province":"NJ",
    "sg:tags":[
        "information",
        "technology",
        "solution",
        "business"
    ],
    "wof:name":"Epinaki Business Solutions",
    "wof:placetype":"venue"
},
  "geometry": {"coordinates":[-74.72493299999999,40.888505],"type":"Point"}
}