{
  "type": "Feature",
  "properties": {
    "addr:full":"104 Park Ave Rutherford NJ 07070",
    "addr:housenumber":"104",
    "addr:postcode":"07070",
    "addr:street":"Park Ave",
    "iso:country":"US",
    "sg:address":"104 Park Ave",
    "sg:city":"Rutherford",
    "sg:classifiers":[
        {
            "category":"Home & Garden",
            "subcategory":"Home Furnishings",
            "type":"Retail Goods"
        },
        {
            "category":"Home & Garden",
            "subcategory":"Furniture",
            "type":"Retail Goods"
        }
    ],
    "sg:phone":"+1 201 438 5400",
    "sg:postcode":"07070",
    "sg:province":"NJ",
    "sg:tags":[
        "kitchen",
        "equipment",
        "cabinet",
        "accessory",
        "bath"
    ],
    "wof:name":"Rutherford Kitchens and Bath",
    "wof:placetype":"venue"
},
  "geometry": {"coordinates":[-74.10684500000001,40.826403],"type":"Point"}
}