{
  "type": "Feature",
  "properties": {
    "iso:country":"US",
    "sg:address":"433 Cleveland Ave",
    "sg:city":"Harrison",
    "sg:classifiers":[
        {
            "category":"Building & Trades",
            "subcategory":"Electrical",
            "type":"Services"
        }
    ],
    "sg:phone":"+1 973 482 9408",
    "sg:postcode":"07029",
    "sg:province":"NJ",
    "sg:tags":[
        "electrical",
        "contractor"
    ],
    "wof:name":"Mullin Electric",
    "wof:placetype":"venue"
},
  "geometry": {"coordinates":[-74.154799,40.74737],"type":"Point"}
}