{
  "type": "Feature",
  "properties": {
    "iso:country":"US",
    "sg:address":"51 Columbus Jobstown Rd",
    "sg:city":"Columbus",
    "sg:classifiers":[
        {
            "category":"Farming",
            "subcategory":"Livestock Farm",
            "type":"Manufacturing & Wholesale Goods"
        }
    ],
    "sg:phone":"+1 609 723 1155",
    "sg:postcode":"08022",
    "sg:province":"NJ",
    "sg:tags":[
        "breeder",
        "horse"
    ],
    "wof:name":"Blairwood Farms Inc",
    "wof:placetype":"venue"
},
  "geometry": {"coordinates":[-74.719527,40.050671],"type":"Point"}
}