{
  "type": "Feature",
  "properties": {
    "addr:full":"8405 E Landis Ave Sea Isle City NJ 08243",
    "addr:housenumber":"8405",
    "addr:postcode":"08243",
    "addr:street":"E Landis Ave",
    "iso:country":"US",
    "sg:address":"8405 E Landis Ave",
    "sg:city":"Sea Isle City",
    "sg:classifiers":[
        {
            "category":"Building & Trades",
            "subcategory":"Cleaning & Sanitation",
            "type":"Services"
        }
    ],
    "sg:phone":"+1   ",
    "sg:postcode":"08243",
    "sg:province":"NJ",
    "sg:tags":[
        "maintenance"
    ],
    "wof:name":"KB Properties Inc",
    "wof:placetype":"venue"
},
  "geometry": {"coordinates":[-74.710421,39.126979],"type":"Point"}
}