{
  "type": "Feature",
  "properties": {
    "iso:country":"US",
    "sg:address":"1 Applegate Ter",
    "sg:city":"Englishtown",
    "sg:classifiers":[
        {
            "category":"Manufacturing",
            "subcategory":"Tools & Machinery",
            "type":"Manufacturing & Wholesale Goods"
        }
    ],
    "sg:phone":"+1 732 294 5525",
    "sg:postcode":"07726",
    "sg:province":"NJ",
    "sg:tags":[
        "steel",
        "stainless",
        "mfg",
        "flow",
        "instrumentation"
    ],
    "wof:name":"Nice Instrumentation Inc",
    "wof:placetype":"venue"
},
  "geometry": {"coordinates":[-74.330958,40.248107],"type":"Point"}
}