{
  "type": "Feature",
  "properties": {
    "addr:full":"14 US Hwy 9 Englishtown NJ 07726",
    "addr:housenumber":"14",
    "addr:postcode":"07726",
    "addr:street":"Us Hwy 9",
    "iso:country":"US",
    "sg:address":"14 US Hwy 9",
    "sg:city":"Englishtown",
    "sg:classifiers":[
        {
            "category":"Building & Trades",
            "subcategory":"Construction",
            "type":"Services"
        }
    ],
    "sg:phone":"+1 732 536 0390",
    "sg:postcode":"07726",
    "sg:province":"NJ",
    "sg:tags":[
        "designer",
        "dealer",
        "pool",
        "swimming"
    ],
    "wof:name":"Blue Haven Pools",
    "wof:placetype":"venue"
},
  "geometry": {"coordinates":[-74.295276,40.28738],"type":"Point"}
}