{
  "type": "Feature",
  "properties": {
    "addr:full":"602 US Hwy 130 Trenton NJ 08691",
    "addr:housenumber":"602",
    "addr:postcode":"08691",
    "addr:street":"Us Hwy 130",
    "iso:country":"US",
    "sg:address":"602 US Hwy 130",
    "sg:city":"Trenton",
    "sg:classifiers":[
        {
            "category":"Shopping",
            "type":"Retail Goods"
        }
    ],
    "sg:phone":"+1 609 585 5985",
    "sg:postcode":"08691",
    "sg:province":"NJ",
    "sg:tags":[
        "monument"
    ],
    "wof:name":"VMG Monuments",
    "wof:placetype":"venue"
},
  "geometry": {"coordinates":[-74.652447,40.189307],"type":"Point"}
}