{
  "type": "Feature",
  "properties": {
    "addr:full":"1424 Brace Rd Cherry Hill NJ 08034",
    "addr:housenumber":"1424",
    "addr:postcode":"08034",
    "addr:street":"Brace Rd",
    "iso:country":"US",
    "sg:address":"1424 Brace Rd",
    "sg:city":"Cherry Hill",
    "sg:classifiers":[
        {
            "category":"Bars & Pubs",
            "type":"Food & Drink"
        }
    ],
    "sg:phone":"+1 856 428 2555",
    "sg:postcode":"08034",
    "sg:province":"NJ",
    "wof:name":"Kaminski's",
    "wof:placetype":"venue"
},
  "geometry": {"coordinates":[-75.01830699999999,39.891833],"type":"Point"}
}