{
  "type": "Feature",
  "properties": {
    "iso:country":"US",
    "sg:address":"3 Cherry Ln",
    "sg:city":"Brookside",
    "sg:classifiers":[
        {
            "category":"Government",
            "subcategory":"Police Station",
            "type":"Public Place"
        }
    ],
    "sg:phone":"+1 973 543 2581",
    "sg:postcode":"07945",
    "sg:province":"NJ",
    "sg:tags":[
        "department"
    ],
    "sg:website":"www.mendhamtownship.org",
    "wof:name":"Mendham Twp POLICE Dept",
    "wof:placetype":"venue"
},
  "geometry": {"coordinates":[-74.567573,40.790974],"type":"Point"}
}