{
  "type": "Feature",
  "properties": {
    "iso:country":"US",
    "sg:address":"23 Orange St",
    "sg:city":"Bloomfield",
    "sg:classifiers":[
        {
            "category":"Social Services",
            "subcategory":"Child Care",
            "type":"Services"
        }
    ],
    "sg:phone":"+1 973 707 7461",
    "sg:postcode":"07003",
    "sg:province":"NJ",
    "sg:tags":[
        "day"
    ],
    "wof:name":"My First Child Care",
    "wof:placetype":"venue"
},
  "geometry": {"coordinates":[-74.198199,40.784006],"type":"Point"}
}