{
  "type": "Feature",
  "properties": {
    "addr:full":"28 Whitehall Way Englishtown NJ 07726",
    "addr:housenumber":"28",
    "addr:postcode":"07726",
    "addr:street":"Whitehall Way",
    "iso:country":"US",
    "sg:address":"28 Whitehall Way",
    "sg:city":"Englishtown",
    "sg:classifiers":[
        {
            "category":"Building & Trades",
            "subcategory":"Landscaping Services",
            "type":"Services"
        }
    ],
    "sg:phone":"+1 732 446 9438",
    "sg:postcode":"07726",
    "sg:province":"NJ",
    "sg:tags":[
        "landscape"
    ],
    "wof:name":"M&K Lawn & Landscap Services",
    "wof:placetype":"venue"
},
  "geometry": {"coordinates":[-74.33273800000001,40.310351],"type":"Point"}
}