{
  "type": "Feature",
  "properties": {
    "iso:country":"US",
    "sg:address":"320 Beverly Rancocas Rd",
    "sg:city":"Willingboro",
    "sg:classifiers":[
        {
            "category":"Wholesale",
            "subcategory":"Machinery & Supplies",
            "type":"Manufacturing & Wholesale Goods"
        }
    ],
    "sg:phone":"+1 609 877 3337",
    "sg:postcode":"08046",
    "sg:province":"NJ",
    "sg:tags":[
        "cleaners",
        "vacuum"
    ],
    "wof:name":"Model Vac & Sew Ctr",
    "wof:placetype":"venue"
},
  "geometry": {"coordinates":[-74.906813,40.027513],"type":"Point"}
}