{
  "type": "Feature",
  "properties": {
    "iso:country":"US",
    "sg:address":"84 Maple Ave",
    "sg:city":"Montclair",
    "sg:classifiers":[
        {
            "category":"Building & Trades",
            "subcategory":"Locksmith",
            "type":"Services"
        }
    ],
    "sg:phone":"+1 888 458 1768",
    "sg:postcode":"07042",
    "sg:province":"NJ",
    "sg:tags":[
        "key"
    ],
    "wof:name":"Emergency 24 Hour 7 Day Locksmith",
    "wof:placetype":"venue"
},
  "geometry": {"coordinates":[-74.213399,40.804173],"type":"Point"}
}