{
  "type": "Feature",
  "properties": {
    "addr:full":"397 Hope Ave Roselle NJ 07203",
    "addr:housenumber":"397",
    "addr:postcode":"07203",
    "addr:street":"Hope Ave",
    "iso:country":"US",
    "sg:address":"397 Hope Ave",
    "sg:city":"Roselle",
    "sg:classifiers":[
        {
            "category":"Building & Trades",
            "subcategory":"Plumbing",
            "type":"Services"
        }
    ],
    "sg:phone":"+1 908 241 4477",
    "sg:postcode":"07203",
    "sg:province":"NJ",
    "sg:tags":[
        "contractor",
        "air"
    ],
    "wof:name":"United Cooling & Refrigeration",
    "wof:placetype":"venue"
},
  "geometry": {"coordinates":[-74.25548999999999,40.661601],"type":"Point"}
}