{
  "type": "Feature",
  "properties": {
    "addr:full":"1047 Elizabeth Ave Elizabeth NJ 07201",
    "addr:housenumber":"1047",
    "addr:postcode":"07201",
    "addr:street":"Elizabeth Ave",
    "iso:country":"US",
    "sg:address":"1047 Elizabeth Ave",
    "sg:city":"Elizabeth",
    "sg:classifiers":[
        {
            "category":"Home & Garden",
            "subcategory":"Household Appliances",
            "type":"Retail Goods"
        }
    ],
    "sg:phone":"+1   ",
    "sg:postcode":"07201",
    "sg:province":"NJ",
    "wof:name":"Economy Stove Supply",
    "wof:placetype":"venue"
},
  "geometry": {"coordinates":[-74.209383,40.661202],"type":"Point"}
}