{
  "type": "Feature",
  "properties": {
    "addr:full":"20 Banta Pl Hackensack NJ 07601",
    "addr:housenumber":"20",
    "addr:postcode":"07601",
    "addr:street":"Banta Pl",
    "iso:country":"US",
    "sg:address":"20 Banta Pl",
    "sg:city":"Hackensack",
    "sg:classifiers":[
        {
            "category":"Shopping",
            "type":"Retail Goods"
        },
        {
            "category":"Health Services",
            "subcategory":"Clinic",
            "type":"Services"
        }
    ],
    "sg:phone":"+1 201 343 2300",
    "sg:postcode":"07601",
    "sg:province":"NJ",
    "sg:tags":[
        "home",
        "agency",
        "employment",
        "merchandise"
    ],
    "wof:name":"All Metro Health Care",
    "wof:placetype":"venue"
},
  "geometry": {"coordinates":[-74.043389,40.885246],"type":"Point"}
}