{
  "type": "Feature",
  "properties": {
    "iso:country":"US",
    "sg:address":"111 N Albany Ave",
    "sg:city":"Atlantic City",
    "sg:classifiers":[
        {
            "category":"Autos & Motor Vehicles",
            "subcategory":"Fuel & Gas Station",
            "type":"Retail Goods"
        }
    ],
    "sg:phone":"+1 609 347 8110",
    "sg:postcode":"08401",
    "sg:province":"NJ",
    "sg:tags":[
        "oil"
    ],
    "wof:name":"Sunoco",
    "wof:placetype":"venue"
},
  "geometry": {"coordinates":[-74.456124,39.353037],"type":"Point"}
}