{
  "type": "Feature",
  "properties": {
    "iso:country":"US",
    "sg:address":"251 Knoll Dr",
    "sg:city":"Park Ridge",
    "sg:classifiers":[
        {
            "category":"Shopping",
            "subcategory":"Hobbies, Toys, & Games",
            "type":"Retail Goods"
        }
    ],
    "sg:phone":"+1 201 505 0092",
    "sg:postcode":"07656",
    "sg:province":"NJ",
    "wof:name":"Brighter Starts LLC",
    "wof:placetype":"venue"
},
  "geometry": {"coordinates":[-74.021495,41.023364],"type":"Point"}
}