{
  "type": "Feature",
  "properties": {
    "addr:full":"1612 State Rte 27 North Brunswick NJ 08902",
    "addr:housenumber":"1612",
    "addr:postcode":"08902",
    "addr:street":"State Rte 27",
    "iso:country":"US",
    "sg:address":"1612 State Rte 27",
    "sg:city":"North Brunswick",
    "sg:classifiers":[
        {
            "category":"Health Services",
            "subcategory":"Doctor",
            "type":"Services"
        }
    ],
    "sg:phone":"+1 732 846 6767",
    "sg:postcode":"08902",
    "sg:province":"NJ",
    "sg:tags":[
        "dentist"
    ],
    "wof:name":"Doctor D Dental",
    "wof:placetype":"venue"
},
  "geometry": {"coordinates":[-74.49858500000001,40.46673],"type":"Point"}
}