{
  "type": "Feature",
  "properties": {
    "addr:full":"17 Kent Place Blvd Summit NJ 07901",
    "addr:housenumber":"17",
    "addr:postcode":"07901",
    "addr:street":"Kent Place Blvd",
    "iso:country":"US",
    "sg:address":"17 Kent Place Blvd",
    "sg:city":"Summit",
    "sg:classifiers":[
        {
            "category":"Organizations",
            "subcategory":"Religious Organization",
            "type":"Services"
        }
    ],
    "sg:phone":"+1 908 277 1700",
    "sg:postcode":"07901",
    "sg:province":"NJ",
    "sg:tags":[
        "church"
    ],
    "sg:website":"www.umcsummit.org",
    "wof:name":"United Methodist Church Summit",
    "wof:placetype":"venue"
},
  "geometry": {"coordinates":[-74.361699,40.718147],"type":"Point"}
}