{
  "type": "Feature",
  "properties": {
    "addr:full":"361 Springfield Ave Summit NJ 07901",
    "addr:housenumber":"361",
    "addr:postcode":"07901",
    "addr:street":"Springfield Ave",
    "iso:country":"US",
    "sg:address":"361 Springfield Ave",
    "sg:city":"Summit",
    "sg:classifiers":[
        {
            "category":"Travel",
            "subcategory":"Travel Agent",
            "type":"Entertainment"
        }
    ],
    "sg:phone":"+1 908 273 5500",
    "sg:postcode":"07901",
    "sg:province":"NJ",
    "sg:tags":[
        "agency",
        "bureau"
    ],
    "wof:name":"American Express Travel Rltd",
    "wof:placetype":"venue"
},
  "geometry": {"coordinates":[-74.356703,40.718216],"type":"Point"}
}