{
  "type": "Feature",
  "properties": {
    "iso:country":"US",
    "sg:address":"351 Shea Dr",
    "sg:city":"New Milford",
    "sg:classifiers":[
        {
            "category":"Professional",
            "subcategory":"Business Services",
            "type":"Services"
        }
    ],
    "sg:phone":"+1   ",
    "sg:postcode":"07646",
    "sg:province":"NJ",
    "wof:name":"Paul Kronick",
    "wof:placetype":"venue"
},
  "geometry": {"coordinates":[-74.007948,40.947959],"type":"Point"}
}