{
  "type": "Feature",
  "properties": {
    "iso:country":"US",
    "sg:address":"90 Matawan Rd",
    "sg:city":"South Amboy",
    "sg:classifiers":[
        {
            "category":"Health Services",
            "subcategory":"Clinic",
            "type":"Services"
        }
    ],
    "sg:phone":"+1 732 353 7200",
    "sg:postcode":"08879",
    "sg:province":"NJ",
    "wof:name":"Health Net Inc",
    "wof:placetype":"venue"
},
  "geometry": {"coordinates":[-74.250077,40.4459],"type":"Point"}
}