{
  "type": "Feature",
  "properties": {
    "addr:full":"262 Monroe St Passaic NJ 07055",
    "addr:housenumber":"262",
    "addr:postcode":"07055",
    "addr:street":"Monroe St",
    "iso:country":"US",
    "sg:address":"262 Monroe St",
    "sg:city":"Passaic",
    "sg:classifiers":[
        {
            "category":"Personal",
            "subcategory":"Beauty Salon",
            "type":"Services"
        }
    ],
    "sg:phone":"+1 973 778 2393",
    "sg:postcode":"07055",
    "sg:province":"NJ",
    "sg:tags":[
        "nail",
        "manicuring"
    ],
    "wof:name":"Tony's City Nail Salon",
    "wof:placetype":"venue"
},
  "geometry": {"coordinates":[-74.124996,40.865451],"type":"Point"}
}