{
  "type": "Feature",
  "properties": {
    "iso:country":"US",
    "sg:address":"123 Danforth Ave",
    "sg:city":"Jersey City",
    "sg:classifiers":[
        {
            "category":"Retail",
            "subcategory":"Self-service Laundry",
            "type":"Services"
        }
    ],
    "sg:phone":"+1   ",
    "sg:postcode":"07305",
    "sg:province":"NJ",
    "sg:tags":[
        "coin",
        "laundromat"
    ],
    "wof:name":"Danforth Laundromat",
    "wof:placetype":"venue"
},
  "geometry": {"coordinates":[-74.092355,40.697403],"type":"Point"}
}