{
  "type": "Feature",
  "properties": {
    "iso:country":"US",
    "sg:address":"892 State Rte 73",
    "sg:city":"Marlton",
    "sg:classifiers":[
        {
            "category":"Professional",
            "subcategory":"Computer Services",
            "type":"Services"
        }
    ],
    "sg:phone":"+1 856 988 3922",
    "sg:postcode":"08053",
    "sg:province":"NJ",
    "sg:tags":[
        "software"
    ],
    "wof:name":"Industri-Matematik",
    "wof:placetype":"venue"
},
  "geometry": {"coordinates":[-74.92167600000001,39.862611],"type":"Point"}
}