{
  "type": "Feature",
  "properties": {
    "iso:country":"US",
    "sg:address":"1907 Bay Blvd",
    "sg:city":"Lavallette",
    "sg:classifiers":[
        {
            "category":"Restaurant",
            "type":"Food & Drink"
        }
    ],
    "sg:phone":"+1 732 830 5030",
    "sg:postcode":"08735",
    "sg:province":"NJ",
    "sg:tags":[
        "pizza"
    ],
    "wof:name":"Mia's Pizza & Cafe",
    "wof:placetype":"venue"
},
  "geometry": {"coordinates":[-74.074528,39.964705],"type":"Point"}
}