{
  "type": "Feature",
  "properties": {
    "iso:country":"US",
    "sg:address":"6914 Kennedy Blvd E",
    "sg:city":"Guttenberg",
    "sg:classifiers":[
        {
            "category":"Restaurant",
            "type":"Food & Drink"
        }
    ],
    "sg:phone":"+1 201 868 8088",
    "sg:postcode":"07093",
    "sg:province":"NJ",
    "wof:name":"China Village",
    "wof:placetype":"venue"
},
  "geometry": {"coordinates":[-74.000596,40.791241],"type":"Point"}
}