{
  "type": "Feature",
  "properties": {
    "iso:country":"US",
    "sg:address":"269 Lincoln Ave",
    "sg:city":"Elmwood Park",
    "sg:classifiers":[
        {
            "category":"Wholesale",
            "subcategory":"Books, Periodicals, & Newspapers",
            "type":"Manufacturing & Wholesale Goods"
        }
    ],
    "sg:phone":"+1 201 794 8525",
    "sg:postcode":"07407",
    "sg:province":"NJ",
    "wof:name":"Haines Associates",
    "wof:placetype":"venue"
},
  "geometry": {"coordinates":[-74.121089,40.91366],"type":"Point"}
}