{
  "type": "Feature",
  "properties": {
    "addr:full":"16 Highwood Ave Englewood NJ 07631",
    "addr:housenumber":"16",
    "addr:postcode":"07631",
    "addr:street":"Highwood Ave",
    "iso:country":"US",
    "sg:address":"16 Highwood Ave",
    "sg:city":"Englewood",
    "sg:classifiers":[
        {
            "category":"Wholesale",
            "subcategory":"Electrical",
            "type":"Manufacturing & Wholesale Goods"
        }
    ],
    "sg:phone":"+1 201 569 0975",
    "sg:postcode":"07631",
    "sg:province":"NJ",
    "sg:tags":[
        "component",
        "material",
        "wiring",
        "wire",
        "cable"
    ],
    "wof:name":"Q C Electronics Inc",
    "wof:placetype":"venue"
},
  "geometry": {"coordinates":[-73.970089,40.90804],"type":"Point"}
}