{
  "type": "Feature",
  "properties": {
    "addr:full":"54 Clydesdale Rd Scotch Plains NJ 07076",
    "addr:housenumber":"54",
    "addr:postcode":"07076",
    "addr:street":"Clydesdale Rd",
    "iso:country":"US",
    "sg:address":"54 Clydesdale Rd",
    "sg:city":"Scotch Plains",
    "sg:classifiers":[
        {
            "category":"Professional",
            "subcategory":"Accounting & Tax Preparation",
            "type":"Services"
        }
    ],
    "sg:phone":"+1 908 222 7435",
    "sg:postcode":"07076",
    "sg:province":"NJ",
    "wof:name":"Essenfeld Business Services",
    "wof:placetype":"venue"
},
  "geometry": {"coordinates":[-74.383405,40.615144],"type":"Point"}
}