{
  "type": "Feature",
  "properties": {
    "iso:country":"US",
    "sg:address":"65 Mine Brook Rd",
    "sg:city":"Bernardsville",
    "sg:classifiers":[
        {
            "category":"Professional",
            "type":"Services"
        }
    ],
    "sg:phone":"+1 908 766 3005",
    "sg:postcode":"07924",
    "sg:province":"NJ",
    "sg:tags":[
        "establishment"
    ],
    "wof:name":"C C Ford Group",
    "wof:placetype":"venue"
},
  "geometry": {"coordinates":[-74.572165,40.716707],"type":"Point"}
}