{
  "type": "Feature",
  "properties": {
    "addr:full":"20 Waverly Pl Madison NJ 07940",
    "addr:housenumber":"20",
    "addr:postcode":"07940",
    "addr:street":"Waverly Pl",
    "iso:country":"US",
    "sg:address":"20 Waverly Pl",
    "sg:city":"Madison",
    "sg:classifiers":[
        {
            "category":"Professional",
            "subcategory":"Credit Reporting & Collection",
            "type":"Services"
        }
    ],
    "sg:phone":"+1   ",
    "sg:postcode":"07940",
    "sg:province":"NJ",
    "sg:tags":[
        "agency"
    ],
    "wof:name":"OConnor-Ravell Associates",
    "wof:placetype":"venue"
},
  "geometry": {"coordinates":[-74.41578699999999,40.758046],"type":"Point"}
}