{
  "type": "Feature",
  "properties": {
    "addr:full":"56 Newman Springs Rd Red Bank NJ 07701",
    "addr:housenumber":"56",
    "addr:postcode":"07701",
    "addr:street":"Newman Springs Rd",
    "iso:country":"US",
    "sg:address":"56 Newman Springs Rd",
    "sg:city":"Red Bank",
    "sg:classifiers":[
        {
            "category":"Food & Beverages",
            "subcategory":"Liquor & Beverages",
            "type":"Retail Goods"
        }
    ],
    "sg:phone":"+1   ",
    "sg:postcode":"07701",
    "sg:province":"NJ",
    "sg:tags":[
        "store"
    ],
    "wof:name":"Spirits Unlimited",
    "wof:placetype":"venue"
},
  "geometry": {"coordinates":[-74.063676,40.338136],"type":"Point"}
}