{
  "type": "Feature",
  "properties": {
    "addr:full":"1313 Paterson Plank Rd Secaucus NJ 07094",
    "addr:housenumber":"1313",
    "addr:postcode":"07094",
    "addr:street":"Paterson Plank Rd",
    "iso:country":"US",
    "sg:address":"1313 Paterson Plank Rd",
    "sg:city":"Secaucus",
    "sg:classifiers":[
        {
            "category":"Personal",
            "type":"Services"
        }
    ],
    "sg:phone":"+1 201 392 3890",
    "sg:postcode":"07094",
    "sg:province":"NJ",
    "sg:tags":[
        "therapist",
        "massage"
    ],
    "wof:name":"168",
    "wof:placetype":"venue"
},
  "geometry": {"coordinates":[-74.058257,40.791068],"type":"Point"}
}