{
  "type": "Feature",
  "properties": {
    "addr:full":"135 Overmount Ave Little Falls NJ 07424",
    "addr:housenumber":"135",
    "addr:postcode":"07424",
    "addr:street":"Overmount Ave",
    "iso:country":"US",
    "sg:address":"135 Overmount Ave",
    "sg:city":"Little Falls",
    "sg:classifiers":[
        {
            "category":"Freight",
            "type":"Transportation"
        }
    ],
    "sg:phone":"+1 908 247 5532",
    "sg:postcode":"07424",
    "sg:province":"NJ",
    "sg:tags":[
        "operator",
        "local",
        "trucking"
    ],
    "wof:name":"Goce Trucking",
    "wof:placetype":"venue"
},
  "geometry": {"coordinates":[-74.197639,40.88726],"type":"Point"}
}