{
  "type": "Feature",
  "properties": {
    "iso:country":"US",
    "sg:address":"62 State Rte 50",
    "sg:city":"Ocean View",
    "sg:classifiers":[
        {
            "category":"Travel",
            "subcategory":"Campground",
            "type":"Entertainment"
        }
    ],
    "sg:phone":"+1 609 390 0431",
    "sg:postcode":"08230",
    "sg:province":"NJ",
    "wof:name":"Shady Oaks Campground",
    "wof:placetype":"venue"
},
  "geometry": {"coordinates":[-74.707007,39.217253],"type":"Point"}
}