{
  "type": "Feature",
  "properties": {
    "addr:full":"1203 8th Ave Neptune NJ 07753",
    "addr:housenumber":"1203",
    "addr:postcode":"07753",
    "addr:street":"8Th Ave",
    "iso:country":"US",
    "sg:address":"1203 8th Ave",
    "sg:city":"Neptune",
    "sg:classifiers":[
        {
            "category":"Social Services",
            "subcategory":"Child Care",
            "type":"Services"
        }
    ],
    "sg:phone":"+1 732 502 0104",
    "sg:postcode":"07753",
    "sg:province":"NJ",
    "wof:name":"Veneta Drinkard Day Care Ctr",
    "wof:placetype":"venue"
},
  "geometry": {"coordinates":[-74.02362100000001,40.20618],"type":"Point"}
}