{
  "type": "Feature",
  "properties": {
    "iso:country":"US",
    "sg:address":"1871 State Rte 27",
    "sg:city":"Edison",
    "sg:classifiers":[
        {
            "category":"Shopping",
            "subcategory":"Clothing, Apparel, & Fashions",
            "type":"Retail Goods"
        }
    ],
    "sg:phone":"+1 732 985 9088",
    "sg:postcode":"08817",
    "sg:province":"NJ",
    "sg:tags":[
        "shop",
        "bridal"
    ],
    "wof:name":"Marry Me Wedding Palace",
    "wof:placetype":"venue"
},
  "geometry": {"coordinates":[-74.40217699999999,40.515446],"type":"Point"}
}