{
  "type": "Feature",
  "properties": {
    "iso:country":"US",
    "sg:address":"6579 Delilah Rd",
    "sg:city":"Egg Harbor Twp",
    "sg:classifiers":[
        {
            "category":"Wholesale",
            "subcategory":"Hardware",
            "type":"Manufacturing & Wholesale Goods"
        }
    ],
    "sg:phone":"+1 609 641 3017",
    "sg:postcode":"08234",
    "sg:province":"NJ",
    "sg:tags":[
        "supply",
        "air",
        "p",
        "parts",
        "conditioning",
        "electronic"
    ],
    "wof:name":"Peirce-Phelps Inc",
    "wof:placetype":"venue"
},
  "geometry": {"coordinates":[-74.557575,39.423874],"type":"Point"}
}