{
  "type": "Feature",
  "properties": {
    "addr:full":"11 Sanford St Englishtown NJ 07726",
    "addr:housenumber":"11",
    "addr:postcode":"07726",
    "addr:street":"Sanford St",
    "iso:country":"US",
    "sg:address":"11 Sanford St",
    "sg:city":"Englishtown",
    "sg:classifiers":[
        {
            "category":"Organizations",
            "subcategory":"Community Association",
            "type":"Services"
        }
    ],
    "sg:phone":"+1 732 446 9872",
    "sg:postcode":"07726",
    "sg:province":"NJ",
    "sg:tags":[
        "military"
    ],
    "wof:name":"American Legion",
    "wof:placetype":"venue"
},
  "geometry": {"coordinates":[-74.35694599999999,40.305102],"type":"Point"}
}