{
  "type": "Feature",
  "properties": {
    "iso:country":"US",
    "sg:address":"48 Broad St",
    "sg:city":"Elizabeth",
    "sg:classifiers":[
        {
            "category":"Shopping",
            "subcategory":"Jewelry",
            "type":"Retail Goods"
        }
    ],
    "sg:phone":"+1   ",
    "sg:postcode":"07201",
    "sg:province":"NJ",
    "wof:name":"Mikes Jewelers Corp",
    "wof:placetype":"venue"
},
  "geometry": {"coordinates":[-74.21480699999999,40.665269],"type":"Point"}
}