{
  "type": "Feature",
  "properties": {
    "iso:country":"US",
    "sg:address":"349 Cortlandt St",
    "sg:city":"Belleville",
    "sg:classifiers":[
        {
            "category":"Manufacturing",
            "subcategory":"Toys & Sporting Goods",
            "type":"Manufacturing & Wholesale Goods"
        }
    ],
    "sg:phone":"+1 973 844 9500",
    "sg:postcode":"07109",
    "sg:province":"NJ",
    "sg:tags":[
        "pool",
        "swimming"
    ],
    "sg:website":"www.poolcoindustries.com",
    "wof:name":"Poolco Industries Inc",
    "wof:placetype":"venue"
},
  "geometry": {"coordinates":[-74.149047,40.790855],"type":"Point"}
}