{
  "type": "Feature",
  "properties": {
    "iso:country":"US",
    "sg:address":"633 Haven Ave",
    "sg:city":"Ocean City",
    "sg:classifiers":[
        {
            "category":"Retail",
            "subcategory":"Auto Repair",
            "type":"Services"
        }
    ],
    "sg:phone":"+1 609 399 2824",
    "sg:postcode":"08226",
    "sg:province":"NJ",
    "sg:tags":[
        "automotive"
    ],
    "wof:name":"Christophers Foreign Cars",
    "wof:placetype":"venue"
},
  "geometry": {"coordinates":[-74.57457700000001,39.282506],"type":"Point"}
}