{
  "type": "Feature",
  "properties": {
    "addr:full":"3 Prickett Ct Medford NJ 08055",
    "addr:housenumber":"3",
    "addr:postcode":"08055",
    "addr:street":"Prickett Ct",
    "iso:country":"US",
    "sg:address":"3 Prickett Ct",
    "sg:city":"Medford",
    "sg:classifiers":[
        {
            "category":"Wholesale",
            "subcategory":"Drugs",
            "type":"Manufacturing & Wholesale Goods"
        }
    ],
    "sg:phone":"+1 609 953 8896",
    "sg:postcode":"08055",
    "sg:province":"NJ",
    "sg:tags":[
        "pharmaceutical",
        "product"
    ],
    "wof:name":"Glaxosmithkline",
    "wof:placetype":"venue"
},
  "geometry": {"coordinates":[-74.823196,39.907535],"type":"Point"}
}