{
  "type": "Feature",
  "properties": {
    "addr:full":"1030 S Chester Ave Delran NJ 08075",
    "addr:housenumber":"1030",
    "addr:postcode":"08075",
    "addr:street":"S Chester Ave",
    "iso:country":"US",
    "sg:address":"1030 S Chester Ave",
    "sg:city":"Delran",
    "sg:classifiers":[
        {
            "category":"Personal",
            "subcategory":"Beauty Salon",
            "type":"Services"
        },
        {
            "category":"Personal",
            "subcategory":"Barber",
            "type":"Services"
        }
    ],
    "sg:phone":"+1 856 461 9876",
    "sg:postcode":"08075",
    "sg:province":"NJ",
    "wof:name":"Gene Hairstyling & Barbering",
    "wof:placetype":"venue"
},
  "geometry": {"coordinates":[-74.95694899999999,40.018076],"type":"Point"}
}