{
  "type": "Feature",
  "properties": {
    "iso:country":"US",
    "sg:address":"376 Cherry Valley Rd",
    "sg:city":"Princeton",
    "sg:classifiers":[
        {
            "category":"Wholesale",
            "subcategory":"Apparel",
            "type":"Manufacturing & Wholesale Goods"
        }
    ],
    "sg:phone":"+1 609 279 0678",
    "sg:postcode":"08540",
    "sg:province":"NJ",
    "sg:tags":[
        "clothing"
    ],
    "wof:name":"Bambola Inc",
    "wof:placetype":"venue"
},
  "geometry": {"coordinates":[-74.692634,40.381481],"type":"Point"}
}