{
  "type": "Feature",
  "properties": {
    "addr:full":"237 Northfield Ave Northfield NJ 08225",
    "addr:housenumber":"237",
    "addr:postcode":"08225",
    "addr:street":"Northfield Ave",
    "iso:country":"US",
    "sg:address":"237 Northfield Ave",
    "sg:city":"Northfield",
    "sg:classifiers":[
        {
            "category":"Personal",
            "subcategory":"Barber",
            "type":"Services"
        }
    ],
    "sg:phone":"+1 609 646 7544",
    "sg:postcode":"08225",
    "sg:province":"NJ",
    "sg:tags":[
        "shop"
    ],
    "wof:name":"Frank's Barber Shop",
    "wof:placetype":"venue"
},
  "geometry": {"coordinates":[-74.552173,39.371034],"type":"Point"}
}