{
  "type": "Feature",
  "properties": {
    "iso:country":"US",
    "sg:address":"16 Forrestal Rd",
    "sg:city":"Kendall Park",
    "sg:classifiers":[
        {
            "category":"Insurance",
            "subcategory":"Health Insurance",
            "type":"Services"
        }
    ],
    "sg:phone":"+1   ",
    "sg:postcode":"08824",
    "sg:province":"NJ",
    "sg:tags":[
        "carrier"
    ],
    "wof:name":"Principal Life Insurance Co",
    "wof:placetype":"venue"
},
  "geometry": {"coordinates":[-74.56249200000001,40.420287],"type":"Point"}
}