{
  "type": "Feature",
  "properties": {
    "addr:full":"9 W Katherine Ave Ocean View NJ 08230",
    "addr:housenumber":"9",
    "addr:postcode":"08230",
    "addr:street":"W Katherine Ave",
    "iso:country":"US",
    "sg:address":"9 W Katherine Ave",
    "sg:city":"Ocean View",
    "sg:classifiers":[
        {
            "category":"Building & Trades",
            "subcategory":"Construction",
            "type":"Services"
        }
    ],
    "sg:phone":"+1 609 390 5646",
    "sg:postcode":"08230",
    "sg:province":"NJ",
    "sg:tags":[
        "excavation",
        "contractor",
        "general"
    ],
    "wof:name":"De Vaul Excavating",
    "wof:placetype":"venue"
},
  "geometry": {"coordinates":[-74.69748,39.215321],"type":"Point"}
}