{
  "type": "Feature",
  "properties": {
    "iso:country":"US",
    "sg:address":"1015 N Wood Ave",
    "sg:city":"Linden",
    "sg:classifiers":[
        {
            "category":"Restaurant",
            "type":"Food & Drink"
        }
    ],
    "sg:phone":"+1 908 245 8948",
    "sg:postcode":"07036",
    "sg:province":"NJ",
    "sg:tags":[
        "caterer"
    ],
    "wof:name":"E Z Check Food Store",
    "wof:placetype":"venue"
},
  "geometry": {"coordinates":[-74.26460299999999,40.637299],"type":"Point"}
}