{
  "type": "Feature",
  "properties": {
    "addr:full":"301 Aycrigg Ave Passaic NJ 07055",
    "addr:housenumber":"301",
    "addr:postcode":"07055",
    "addr:street":"Aycrigg Ave",
    "iso:country":"US",
    "sg:address":"301 Aycrigg Ave",
    "sg:city":"Passaic",
    "sg:classifiers":[
        {
            "category":"Professional",
            "subcategory":"Management & Consulting",
            "type":"Services"
        }
    ],
    "sg:phone":"+1   ",
    "sg:postcode":"07055",
    "sg:province":"NJ",
    "sg:tags":[
        "business"
    ],
    "wof:name":"Spirited Consulting Inc",
    "wof:placetype":"venue"
},
  "geometry": {"coordinates":[-74.133933,40.8547],"type":"Point"}
}