{
  "type": "Feature",
  "properties": {
    "addr:full":"611 Windsor Cmns Cranbury NJ 08512",
    "addr:housenumber":"611",
    "addr:postcode":"08512",
    "addr:street":"Windsor Cmns",
    "iso:country":"US",
    "sg:address":"611 Windsor Cmns",
    "sg:city":"Cranbury",
    "sg:classifiers":[
        {
            "category":"Shopping",
            "subcategory":"Clothing, Apparel, & Fashions",
            "type":"Retail Goods"
        }
    ],
    "sg:phone":"+1   ",
    "sg:postcode":"08512",
    "sg:province":"NJ",
    "wof:name":"Metallic TRC Accssrs",
    "wof:placetype":"venue"
},
  "geometry": {"coordinates":[-74.54728900000001,40.286933],"type":"Point"}
}