{
  "type": "Feature",
  "properties": {
    "iso:country":"US",
    "sg:address":"898 State Rte 37",
    "sg:city":"Toms River",
    "sg:classifiers":[
        {
            "category":"Organizations",
            "subcategory":"Religious Organization",
            "type":"Services"
        }
    ],
    "sg:phone":"+1 732 349 7557",
    "sg:postcode":"08755",
    "sg:province":"NJ",
    "sg:tags":[
        "church"
    ],
    "sg:website":"www.pinelandsrc.org",
    "wof:name":"Pinelands Reformed Church",
    "wof:placetype":"venue"
},
  "geometry": {"coordinates":[-74.23936399999999,39.973417],"type":"Point"}
}