{
  "type": "Feature",
  "properties": {
    "addr:full":"90 Essex St Hackensack NJ 07601",
    "addr:housenumber":"90",
    "addr:postcode":"07601",
    "addr:street":"Essex St",
    "iso:country":"US",
    "sg:address":"90 Essex St",
    "sg:city":"Hackensack",
    "sg:classifiers":[
        {
            "category":"Freight",
            "type":"Transportation"
        }
    ],
    "sg:phone":"+1 201 489 2393",
    "sg:postcode":"07601",
    "sg:province":"NJ",
    "sg:tags":[
        "operator",
        "trucking"
    ],
    "wof:name":"Raynards Trucking Co",
    "wof:placetype":"venue"
},
  "geometry": {"coordinates":[-74.04771100000001,40.878416],"type":"Point"}
}