{
  "type": "Feature",
  "properties": {
    "iso:country":"US",
    "sg:address":"77 Knickerbocker Rd",
    "sg:city":"Demarest",
    "sg:classifiers":[
        {
            "category":"Organizations",
            "subcategory":"Religious Organization",
            "type":"Services"
        }
    ],
    "sg:phone":"+1   ",
    "sg:postcode":"07627",
    "sg:province":"NJ",
    "wof:name":"Lord Jesus Christ Bible Church",
    "wof:placetype":"venue"
},
  "geometry": {"coordinates":[-73.974962,40.95955],"type":"Point"}
}