{
  "type": "Feature",
  "properties": {
    "iso:country":"US",
    "sg:address":"216 N 12th St",
    "sg:city":"Newark",
    "sg:classifiers":[
        {
            "category":"Retail",
            "subcategory":"Laundry & Dry Cleaning",
            "type":"Services"
        }
    ],
    "sg:phone":"+1 973 350 1055",
    "sg:postcode":"07107",
    "sg:province":"NJ",
    "sg:tags":[
        "valet"
    ],
    "wof:name":"Valet Parking Svc",
    "wof:placetype":"venue"
},
  "geometry": {"coordinates":[-74.190753,40.76383],"type":"Point"}
}