{
  "type": "Feature",
  "properties": {
    "iso:country":"US",
    "sg:address":"413 Bound Brook Rd",
    "sg:city":"Middlesex",
    "sg:classifiers":[
        {
            "category":"Personal",
            "subcategory":"Beauty Salon",
            "type":"Services"
        }
    ],
    "sg:phone":"+1   ",
    "sg:postcode":"08846",
    "sg:province":"NJ",
    "sg:tags":[
        "shop"
    ],
    "wof:name":"Royal Beauty Shop",
    "wof:placetype":"venue"
},
  "geometry": {"coordinates":[-74.482454,40.584414],"type":"Point"}
}