{
  "type": "Feature",
  "properties": {
    "iso:country":"US",
    "sg:address":"200 Campus Dr",
    "sg:city":"Florham Park",
    "sg:classifiers":[
        {
            "category":"Organizations",
            "subcategory":"Professional Association",
            "type":"Services"
        }
    ],
    "sg:phone":"+1 973 236 0177",
    "sg:postcode":"07932",
    "sg:province":"NJ",
    "sg:tags":[
        "business",
        "trade"
    ],
    "wof:name":"Financial Executive Intl",
    "wof:placetype":"venue"
},
  "geometry": {"coordinates":[-74.42964000000001,40.782882],"type":"Point"}
}