{
  "type": "Feature",
  "properties": {
    "iso:country":"US",
    "sg:address":"333 Ralph St",
    "sg:city":"Belleville",
    "sg:classifiers":[
        {
            "category":"Communications",
            "subcategory":"Film & Video Production",
            "type":"Services"
        }
    ],
    "sg:phone":"+1 973 751 5115",
    "sg:postcode":"07109",
    "sg:province":"NJ",
    "sg:tags":[
        "taping"
    ],
    "wof:name":"Kondreck Video Productions",
    "wof:placetype":"venue"
},
  "geometry": {"coordinates":[-74.142808,40.798346],"type":"Point"}
}