{
  "type": "Feature",
  "properties": {
    "iso:country":"US",
    "sg:address":"283 Mullica Hill Rd",
    "sg:city":"Mullica Hill",
    "sg:classifiers":[
        {
            "category":"Retail",
            "subcategory":"Animal Services",
            "type":"Services"
        }
    ],
    "sg:phone":"+1 856 478 2223",
    "sg:postcode":"08062",
    "sg:province":"NJ",
    "sg:tags":[
        "pet",
        "grooming",
        "washing"
    ],
    "wof:name":"Stags Leap Ranch Pet Grooming",
    "wof:placetype":"venue"
},
  "geometry": {"coordinates":[-75.199786,39.731617],"type":"Point"}
}