{
  "type": "Feature",
  "properties": {
    "iso:country":"US",
    "sg:address":"660 Grand St",
    "sg:city":"Jersey City",
    "sg:classifiers":[
        {
            "category":"Retail",
            "subcategory":"Repair Shop",
            "type":"Services"
        }
    ],
    "sg:phone":"+1   ",
    "sg:postcode":"07304",
    "sg:province":"NJ",
    "wof:name":"Village Upholstery",
    "wof:placetype":"venue"
},
  "geometry": {"coordinates":[-74.065296,40.716264],"type":"Point"}
}