{
  "type": "Feature",
  "properties": {
    "addr:full":"582 Ridgewood Rd Maplewood NJ 07040",
    "addr:housenumber":"582",
    "addr:postcode":"07040",
    "addr:street":"Ridgewood Rd",
    "iso:country":"US",
    "sg:address":"582 Ridgewood Rd",
    "sg:city":"Maplewood",
    "sg:classifiers":[
        {
            "category":"Professional",
            "subcategory":"Lawyer & Legal Services",
            "type":"Services"
        }
    ],
    "sg:phone":"+1 973 763 6438",
    "sg:postcode":"07040",
    "sg:province":"NJ",
    "wof:name":"John G Guyet",
    "wof:placetype":"venue"
},
  "geometry": {"coordinates":[-74.28167999999999,40.731661],"type":"Point"}
}