{
  "type": "Feature",
  "properties": {
    "addr:full":"1304 South Ave Plainfield NJ 07062",
    "addr:housenumber":"1304",
    "addr:postcode":"07062",
    "addr:street":"South Ave",
    "iso:country":"US",
    "sg:address":"1304 South Ave",
    "sg:city":"Plainfield",
    "sg:classifiers":[
        {
            "category":"Health Services",
            "subcategory":"Doctor",
            "type":"Services"
        }
    ],
    "sg:phone":"+1 908 769 7999",
    "sg:postcode":"07062",
    "sg:province":"NJ",
    "sg:tags":[
        "physician",
        "surgeon"
    ],
    "wof:name":"Orthopedic Medicine Center",
    "wof:placetype":"venue"
},
  "geometry": {"coordinates":[-74.39962300000001,40.630403],"type":"Point"}
}