{
  "type": "Feature",
  "properties": {
    "iso:country":"US",
    "sg:address":"207 Centre St",
    "sg:city":"Lakehurst",
    "sg:classifiers":[
        {
            "category":"Recreation",
            "type":"Entertainment"
        }
    ],
    "sg:phone":"+1 732 657 0361",
    "sg:postcode":"08733",
    "sg:province":"NJ",
    "sg:tags":[
        "hall",
        "auditorium"
    ],
    "wof:name":"Lakehurst Community Ctr",
    "wof:placetype":"venue"
},
  "geometry": {"coordinates":[-74.312234,40.013231],"type":"Point"}
}