{
  "type": "Feature",
  "properties": {
    "addr:full":"743 Jane Dr Manahawkin NJ 08050",
    "addr:housenumber":"743",
    "addr:postcode":"08050",
    "addr:street":"Jane Dr",
    "iso:country":"US",
    "sg:address":"743 Jane Dr",
    "sg:city":"Manahawkin",
    "sg:classifiers":[
        {
            "category":"Building & Trades",
            "subcategory":"Construction",
            "type":"Services"
        }
    ],
    "sg:phone":"+1 609 597 4433",
    "sg:postcode":"08050",
    "sg:province":"NJ",
    "sg:tags":[
        "house"
    ],
    "wof:name":"Seacriss Const",
    "wof:placetype":"venue"
},
  "geometry": {"coordinates":[-74.244056,39.680786],"type":"Point"}
}