{
  "type": "Feature",
  "properties": {
    "addr:full":"818 12th St Hammonton NJ 08037",
    "addr:housenumber":"818",
    "addr:postcode":"08037",
    "addr:street":"12Th St",
    "iso:country":"US",
    "sg:address":"818 12th St",
    "sg:city":"Hammonton",
    "sg:classifiers":[
        {
            "category":"Professional",
            "subcategory":"Secretarial Services",
            "type":"Services"
        }
    ],
    "sg:phone":"+1 609 561 4105",
    "sg:postcode":"08037",
    "sg:province":"NJ",
    "sg:tags":[
        "typing"
    ],
    "wof:name":"Joann Milazzo",
    "wof:placetype":"venue"
},
  "geometry": {"coordinates":[-74.81966,39.622057],"type":"Point"}
}