{
  "type": "Feature",
  "properties": {
    "addr:full":"1414 Burnet Ave Union NJ 07083",
    "addr:housenumber":"1414",
    "addr:postcode":"07083",
    "addr:street":"Burnet Ave",
    "iso:country":"US",
    "sg:address":"1414 Burnet Ave",
    "sg:city":"Union",
    "sg:classifiers":[
        {
            "category":"Education",
            "subcategory":"Kindergarten",
            "type":"Public Place"
        }
    ],
    "sg:phone":"+1 908 206 9977",
    "sg:postcode":"07083",
    "sg:province":"NJ",
    "sg:tags":[
        "school",
        "driving"
    ],
    "wof:name":"Dontre Professional Driving School Inc",
    "wof:placetype":"venue"
},
  "geometry": {"coordinates":[-74.28119700000001,40.711102],"type":"Point"}
}