{
  "type": "Feature",
  "properties": {
    "addr:full":"14 Washington Ave Tenafly NJ 07670",
    "addr:housenumber":"14",
    "addr:postcode":"07670",
    "addr:street":"Washington Ave",
    "iso:country":"US",
    "sg:address":"14 Washington Ave",
    "sg:city":"Tenafly",
    "sg:classifiers":[
        {
            "category":"Restaurant",
            "type":"Food & Drink"
        }
    ],
    "sg:menulink":"http://www.allmenus.com/nj/tenafly/23906-tea-garden/menu/",
    "sg:phone":"+1 201 816 2521",
    "sg:postcode":"07670",
    "sg:province":"NJ",
    "sg:tags":[
        "asian",
        "chinese"
    ],
    "wof:name":"Tea Garden",
    "wof:placetype":"venue"
},
  "geometry": {"coordinates":[-73.965411,40.925256],"type":"Point"}
}