{
  "type": "Feature",
  "properties": {
    "iso:country":"US",
    "sg:address":"1401 Roselle St",
    "sg:city":"Linden",
    "sg:classifiers":[
        {
            "category":"Banks & Credit Unions",
            "subcategory":"Financial Services",
            "type":"Services"
        },
        {
            "category":"Building & Trades",
            "subcategory":"Construction",
            "type":"Services"
        }
    ],
    "sg:phone":"+1 908 925 5400",
    "sg:postcode":"07036",
    "sg:province":"NJ",
    "sg:tags":[
        "company",
        "dry wall",
        "contractor",
        "holding"
    ],
    "wof:name":"Manhattan Partition Assoc",
    "wof:placetype":"venue"
},
  "geometry": {"coordinates":[-74.257876,40.64219],"type":"Point"}
}