{
  "type": "Feature",
  "properties": {
    "addr:full":"47 W Allendale Ave Ste A Allendale NJ 07401",
    "addr:housenumber":"47",
    "addr:postcode":"07401",
    "addr:street":"W Allendale Ave Ste A",
    "iso:country":"US",
    "sg:address":"47 W Allendale Ave Ste A",
    "sg:city":"Allendale",
    "sg:classifiers":[
        {
            "category":"Restaurant",
            "type":"Food & Drink"
        },
        {
            "category":"Food & Beverages",
            "subcategory":"Ethnic Foods",
            "type":"Retail Goods"
        }
    ],
    "sg:phone":"+1 201 818 9288",
    "sg:postcode":"07401",
    "sg:province":"NJ",
    "sg:tags":[
        "asian",
        "pan",
        "vietnamese"
    ],
    "wof:name":"Asian Cuisine",
    "wof:placetype":"venue"
},
  "geometry": {"coordinates":[-74.127683,41.030308],"type":"Point"}
}