{
  "type": "Feature",
  "properties": {
    "addr:full":"101 State Rte 50 Ocean View NJ 08230",
    "addr:housenumber":"101",
    "addr:postcode":"08230",
    "addr:street":"State Rte 50",
    "iso:country":"US",
    "sg:address":"101 State Rte 50",
    "sg:city":"Ocean View",
    "sg:classifiers":[
        {
            "category":"Retail",
            "subcategory":"Auto Repair",
            "type":"Services"
        }
    ],
    "sg:phone":"+1 609 390 0923",
    "sg:postcode":"08230",
    "sg:province":"NJ",
    "sg:tags":[
        "machine",
        "automobile",
        "shop"
    ],
    "wof:name":"Cylinder Head Svc",
    "wof:placetype":"venue"
},
  "geometry": {"coordinates":[-74.705293,39.219764],"type":"Point"}
}