{
  "type": "Feature",
  "properties": {
    "iso:country":"US",
    "sg:address":"1131 US Hwy 46",
    "sg:city":"Parsippany",
    "sg:classifiers":[
        {
            "category":"Retail",
            "subcategory":"Repair Shop",
            "type":"Services"
        }
    ],
    "sg:phone":"+1 973 947 0403",
    "sg:postcode":"07054",
    "sg:province":"NJ",
    "sg:tags":[
        "lock",
        "locksmith"
    ],
    "wof:name":"24 Hour A Emergency A Lcksmth",
    "wof:placetype":"venue"
},
  "geometry": {"coordinates":[-74.384675,40.86272],"type":"Point"}
}