{
  "type": "Feature",
  "properties": {
    "addr:full":"615 Henley Ave Pine Beach NJ 08741",
    "addr:housenumber":"615",
    "addr:postcode":"08741",
    "addr:street":"Henley Ave",
    "iso:country":"US",
    "sg:address":"615 Henley Ave",
    "sg:city":"Pine Beach",
    "sg:classifiers":[
        {
            "category":"Organizations",
            "subcategory":"Membership Organization",
            "type":"Services"
        }
    ],
    "sg:phone":"+1   ",
    "sg:postcode":"08741",
    "sg:province":"NJ",
    "wof:name":"Marine Corps League",
    "wof:placetype":"venue"
},
  "geometry": {"coordinates":[-74.164507,39.93427],"type":"Point"}
}