{
  "type": "Feature",
  "properties": {
    "addr:full":"649 E 18th St Paterson NJ 07501",
    "addr:housenumber":"649",
    "addr:postcode":"07501",
    "addr:street":"E 18Th St",
    "iso:country":"US",
    "sg:address":"649 E 18th St",
    "sg:city":"Paterson",
    "sg:classifiers":[
        {
            "category":"Autos & Motor Vehicles",
            "subcategory":"Auto Supplies",
            "type":"Retail Goods"
        }
    ],
    "sg:phone":"+1 973 345 0176",
    "sg:postcode":"07501",
    "sg:province":"NJ",
    "sg:tags":[
        "automobile",
        "parts"
    ],
    "wof:name":"Autozone",
    "wof:placetype":"venue"
},
  "geometry": {"coordinates":[-74.156063,40.917024],"type":"Point"}
}