{
  "type": "Feature",
  "properties": {
    "iso:country":"US",
    "sg:address":"168 Berkley Ave",
    "sg:city":"Belle Mead",
    "sg:classifiers":[
        {
            "category":"Professional",
            "type":"Services"
        }
    ],
    "sg:phone":"+1   ",
    "sg:postcode":"08502",
    "sg:province":"NJ",
    "wof:name":"Fedak Bohdan & Mary",
    "wof:placetype":"venue"
},
  "geometry": {"coordinates":[-74.61556899999999,40.45542],"type":"Point"}
}