{
  "type": "Feature",
  "properties": {
    "iso:country":"US",
    "sg:address":"305 N 11th St",
    "sg:city":"Millville",
    "sg:classifiers":[
        {
            "category":"Professional",
            "subcategory":"Business Services",
            "type":"Services"
        }
    ],
    "sg:phone":"+1 856 825 1359",
    "sg:postcode":"08332",
    "sg:province":"NJ",
    "sg:tags":[
        "merchandise",
        "mfg"
    ],
    "sg:website":"www.actionsignsonline.com",
    "wof:name":"Action Signs & Awards",
    "wof:placetype":"venue"
},
  "geometry": {"coordinates":[-75.024654,39.399412],"type":"Point"}
}