{
  "type": "Feature",
  "properties": {
    "iso:country":"US",
    "sg:address":"13 E Fort Lee Rd",
    "sg:city":"Bogota",
    "sg:classifiers":[
        {
            "category":"Retail",
            "subcategory":"Laundry & Dry Cleaning",
            "type":"Services"
        }
    ],
    "sg:phone":"+1   ",
    "sg:postcode":"07603",
    "sg:province":"NJ",
    "sg:tags":[
        "installs",
        "carpet"
    ],
    "wof:name":"Mollayan & Co",
    "wof:placetype":"venue"
},
  "geometry": {"coordinates":[-74.028659,40.876014],"type":"Point"}
}