{
  "type": "Feature",
  "properties": {
    "addr:full":"260 Teaneck Rd Teaneck NJ 07666",
    "addr:housenumber":"260",
    "addr:postcode":"07666",
    "addr:street":"Teaneck Rd",
    "iso:country":"US",
    "sg:address":"260 Teaneck Rd",
    "sg:city":"Teaneck",
    "sg:classifiers":[
        {
            "category":"Restaurant",
            "type":"Food & Drink"
        },
        {
            "category":"Ice Cream",
            "type":"Food & Drink"
        }
    ],
    "sg:menulink":"http://www.allmenus.com/nj/teaneck/167801-dairy-queen/menu/",
    "sg:phone":"+1 201 836 1597",
    "sg:postcode":"07666",
    "sg:province":"NJ",
    "sg:tags":[
        "burger",
        "american",
        "ice",
        "cream"
    ],
    "wof:name":"Dairy Queen",
    "wof:placetype":"venue"
},
  "geometry": {"coordinates":[-74.013801,40.870684],"type":"Point"}
}