{
  "type": "Feature",
  "properties": {
    "iso:country":"US",
    "sg:address":"603 New York Ave",
    "sg:city":"Union City",
    "sg:classifiers":[
        {
            "category":"Building & Trades",
            "subcategory":"Locksmith",
            "type":"Services"
        }
    ],
    "sg:phone":"+1 201 520 1081",
    "sg:postcode":"07087",
    "sg:province":"NJ",
    "sg:tags":[
        "key"
    ],
    "wof:name":"Locksmith 24 Hour Emergency",
    "wof:placetype":"venue"
},
  "geometry": {"coordinates":[-74.03873900000001,40.755592],"type":"Point"}
}