{
  "type": "Feature",
  "properties": {
    "addr:full":"218 Lower Creek Rd Stockton NJ 08559",
    "addr:housenumber":"218",
    "addr:postcode":"08559",
    "addr:street":"Lower Creek Rd",
    "iso:country":"US",
    "sg:address":"218 Lower Creek Rd",
    "sg:city":"Stockton",
    "sg:classifiers":[
        {
            "category":"Wholesale",
            "subcategory":"Non-durable Goods",
            "type":"Manufacturing & Wholesale Goods"
        }
    ],
    "sg:phone":"+1 609 397 3246",
    "sg:postcode":"08559",
    "sg:province":"NJ",
    "wof:name":"Norteman Packaging",
    "wof:placetype":"venue"
},
  "geometry": {"coordinates":[-74.965626,40.436672],"type":"Point"}
}