{
  "type": "Feature",
  "properties": {
    "iso:country":"US",
    "sg:address":"113 Church St",
    "sg:city":"Newfield",
    "sg:classifiers":[
        {
            "category":"Manufacturing",
            "subcategory":"Glass & Minerals",
            "type":"Manufacturing & Wholesale Goods"
        }
    ],
    "sg:phone":"+1 856 697 5895",
    "sg:postcode":"08344",
    "sg:province":"NJ",
    "sg:tags":[
        "concrete",
        "brick",
        "prod",
        "block"
    ],
    "wof:name":"Paul Brothers Inc",
    "wof:placetype":"venue"
},
  "geometry": {"coordinates":[-75.022459,39.548279],"type":"Point"}
}