{
  "type": "Feature",
  "properties": {
    "iso:country":"US",
    "sg:address":"410 State Route 10",
    "sg:city":"East Hanover",
    "sg:classifiers":[
        {
            "category":"Shopping",
            "subcategory":"Crafts & Fabrics",
            "type":"Retail Goods"
        }
    ],
    "sg:phone":"+1 973 887 3024",
    "sg:postcode":"07936",
    "sg:province":"NJ",
    "sg:tags":[
        "art",
        "supply"
    ],
    "sg:website":"www.michaels.com",
    "wof:name":"Michaels-Arts & Crafts",
    "wof:placetype":"venue"
},
  "geometry": {"coordinates":[-74.362099,40.802399],"type":"Point"}
}