{
  "type": "Feature",
  "properties": {
    "iso:country":"US",
    "sg:address":"700 New Jersey Ave",
    "sg:city":"Wildwood",
    "sg:classifiers":[
        {
            "category":"Building & Trades",
            "subcategory":"Construction",
            "type":"Services"
        }
    ],
    "sg:phone":"+1 609 523 8006",
    "sg:postcode":"08260",
    "sg:province":"NJ",
    "sg:tags":[
        "contractor"
    ],
    "wof:name":"Ocean Point Developers LLC",
    "wof:placetype":"venue"
},
  "geometry": {"coordinates":[-74.797747,39.004605],"type":"Point"}
}