{
  "type": "Feature",
  "properties": {
    "iso:country":"US",
    "sg:address":"1621 State Rte 71",
    "sg:city":"Wall Township",
    "sg:classifiers":[
        {
            "category":"Recreation",
            "type":"Entertainment"
        }
    ],
    "sg:phone":"+1 732 280 3786",
    "sg:postcode":"07719",
    "sg:province":"NJ",
    "sg:tags":[
        "amusement"
    ],
    "wof:name":"Not Just Music",
    "wof:placetype":"venue"
},
  "geometry": {"coordinates":[-74.032479,40.173677],"type":"Point"}
}