{
  "type": "Feature",
  "properties": {
    "iso:country":"US",
    "sg:address":"1317 Morris Ave",
    "sg:city":"Union",
    "sg:classifiers":[
        {
            "category":"Health Services",
            "subcategory":"Doctor",
            "type":"Services"
        }
    ],
    "sg:phone":"+1 732 776 8500",
    "sg:postcode":"07083",
    "sg:province":"NJ",
    "sg:tags":[
        "physician",
        "surgeon"
    ],
    "wof:name":"David J Pinnelas MD",
    "wof:placetype":"venue"
},
  "geometry": {"coordinates":[-74.242054,40.687113],"type":"Point"}
}