{
  "type": "Feature",
  "properties": {
    "addr:full":"412 N Nassau Ave Margate City NJ 08402",
    "addr:housenumber":"412",
    "addr:postcode":"08402",
    "addr:street":"N Nassau Ave Margate",
    "iso:country":"US",
    "sg:address":"412 N Nassau Ave",
    "sg:city":"Margate City",
    "sg:classifiers":[
        {
            "category":"Shopping",
            "subcategory":"Catalog Store",
            "type":"Retail Goods"
        }
    ],
    "sg:phone":"+1   ",
    "sg:postcode":"08402",
    "sg:province":"NJ",
    "sg:tags":[
        "mail",
        "house"
    ],
    "wof:name":"J T Sports",
    "wof:placetype":"venue"
},
  "geometry": {"coordinates":[-74.51120299999999,39.331735],"type":"Point"}
}