{
  "type": "Feature",
  "properties": {
    "addr:full":"182 3rd St Jersey City NJ 07302",
    "addr:housenumber":"182",
    "addr:postcode":"07302",
    "addr:street":"3Rd St",
    "iso:country":"US",
    "sg:address":"182 3rd St",
    "sg:city":"Jersey City",
    "sg:classifiers":[
        {
            "category":"Government",
            "subcategory":"Office",
            "type":"Public Place"
        }
    ],
    "sg:phone":"+1   ",
    "sg:postcode":"07302",
    "sg:province":"NJ",
    "sg:tags":[
        "national",
        "security"
    ],
    "wof:name":"Civil Air Patrol Inc",
    "wof:placetype":"venue"
},
  "geometry": {"coordinates":[-74.04207700000001,40.723129],"type":"Point"}
}