{
  "type": "Feature",
  "properties": {
    "addr:full":"45 W Main St Ramsey NJ 07446",
    "addr:housenumber":"45",
    "addr:postcode":"07446",
    "addr:street":"W Main St",
    "iso:country":"US",
    "sg:address":"45 W Main St",
    "sg:city":"Ramsey",
    "sg:classifiers":[
        {
            "category":"Banks & Credit Unions",
            "subcategory":"Financial Services",
            "type":"Services"
        }
    ],
    "sg:phone":"+1 201 825 3222",
    "sg:postcode":"07446",
    "sg:province":"NJ",
    "sg:tags":[
        "mortgage"
    ],
    "sg:website":"http://www.nwecorp.com",
    "wof:name":"Nationwide Equities Corporation",
    "wof:placetype":"venue"
},
  "geometry": {"coordinates":[-74.143525,41.057169],"type":"Point"}
}