{
  "type": "Feature",
  "properties": {
    "addr:full":"23 W Main St Freehold NJ 07728",
    "addr:housenumber":"23",
    "addr:postcode":"07728",
    "addr:street":"W Main St",
    "iso:country":"US",
    "sg:address":"23 W Main St",
    "sg:city":"Freehold",
    "sg:classifiers":[
        {
            "category":"Professional",
            "subcategory":"Accounting & Tax Preparation",
            "type":"Services"
        }
    ],
    "sg:phone":"+1   ",
    "sg:postcode":"07728",
    "sg:province":"NJ",
    "wof:name":"Kenneth R Deitz CPA",
    "wof:placetype":"venue"
},
  "geometry": {"coordinates":[-74.275058,40.25951],"type":"Point"}
}