{
  "type": "Feature",
  "properties": {
    "iso:country":"US",
    "sg:address":"321 Windsor Cmns",
    "sg:city":"Cranbury",
    "sg:classifiers":[
        {
            "category":"Professional",
            "type":"Services"
        }
    ],
    "sg:phone":"+1   ",
    "sg:postcode":"08512",
    "sg:province":"NJ",
    "wof:name":"Bgenterprises Inc",
    "wof:placetype":"venue"
},
  "geometry": {"coordinates":[-74.546505,40.286667],"type":"Point"}
}