{
  "type": "Feature",
  "properties": {
    "iso:country":"US",
    "sg:address":"41 Central Ave",
    "sg:city":"Passaic",
    "sg:classifiers":[
        {
            "category":"Home & Garden",
            "subcategory":"Home Furnishings",
            "type":"Retail Goods"
        }
    ],
    "sg:phone":"+1 973 773 3008",
    "sg:postcode":"07055",
    "sg:province":"NJ",
    "sg:tags":[
        "curtain",
        "made",
        "drapery"
    ],
    "wof:name":"Stanley Decorators",
    "wof:placetype":"venue"
},
  "geometry": {"coordinates":[-74.128765,40.865072],"type":"Point"}
}