{
  "type": "Feature",
  "properties": {
    "addr:full":"897 Columbus Dr Teaneck NJ 07666",
    "addr:housenumber":"897",
    "addr:postcode":"07666",
    "addr:street":"Columbus Dr",
    "iso:country":"US",
    "sg:address":"897 Columbus Dr",
    "sg:city":"Teaneck",
    "sg:classifiers":[
        {
            "category":"Building & Trades",
            "subcategory":"Construction",
            "type":"Services"
        }
    ],
    "sg:phone":"+1 917 640 8340",
    "sg:postcode":"07666",
    "sg:province":"NJ",
    "sg:tags":[
        "residential"
    ],
    "wof:name":"S L Systems LLC",
    "wof:placetype":"venue"
},
  "geometry": {"coordinates":[-73.99579900000001,40.882983],"type":"Point"}
}