{
  "type": "Feature",
  "properties": {
    "addr:full":"2 Stephenville Pkwy Edison NJ 08820",
    "addr:housenumber":"2",
    "addr:postcode":"08820",
    "addr:street":"Stephenville Pkwy",
    "iso:country":"US",
    "sg:address":"2 Stephenville Pkwy",
    "sg:city":"Edison",
    "sg:classifiers":[
        {
            "category":"Wholesale",
            "subcategory":"Groceries",
            "type":"Manufacturing & Wholesale Goods"
        }
    ],
    "sg:phone":"+1 732 603 5077",
    "sg:postcode":"08820",
    "sg:province":"NJ",
    "sg:tags":[
        "food",
        "broker"
    ],
    "wof:name":"SGS International Rice Inc",
    "wof:placetype":"venue"
},
  "geometry": {"coordinates":[-74.381827,40.564881],"type":"Point"}
}