{
  "type": "Feature",
  "properties": {
    "iso:country":"US",
    "sg:address":"100 W Pond Rd",
    "sg:city":"Perth Amboy",
    "sg:classifiers":[
        {
            "category":"Personal",
            "subcategory":"Beauty Salon",
            "type":"Services"
        }
    ],
    "sg:phone":"+1 732 771 2205",
    "sg:postcode":"08861",
    "sg:province":"NJ",
    "sg:tags":[
        "shop"
    ],
    "wof:name":"Prime Design Realty Inc",
    "wof:placetype":"venue"
},
  "geometry": {"coordinates":[-74.296052,40.534185],"type":"Point"}
}