{
  "type": "Feature",
  "properties": {
    "addr:full":"433 Rutherford Blvd Clifton NJ 07014",
    "addr:housenumber":"433",
    "addr:postcode":"07014",
    "addr:street":"Rutherford Blvd",
    "iso:country":"US",
    "sg:address":"433 Rutherford Blvd",
    "sg:city":"Clifton",
    "sg:classifiers":[
        {
            "category":"Real Estate",
            "subcategory":"Architect",
            "type":"Services"
        },
        {
            "category":"Building & Trades",
            "subcategory":"Landscaping Services",
            "type":"Services"
        }
    ],
    "sg:phone":"+1 973 779 2078",
    "sg:postcode":"07014",
    "sg:province":"NJ",
    "sg:tags":[
        "engineering",
        "landscape"
    ],
    "wof:name":"Camlet J Thomas & Sons",
    "wof:placetype":"venue"
},
  "geometry": {"coordinates":[-74.139934,40.841747],"type":"Point"}
}