{
  "type": "Feature",
  "properties": {
    "iso:country":"US",
    "sg:address":"286 Central Ave",
    "sg:city":"Kearny",
    "sg:classifiers":[
        {
            "category":"Real Estate",
            "subcategory":"Real Estate Operator",
            "type":"Services"
        }
    ],
    "sg:phone":"+1   ",
    "sg:postcode":"07032",
    "sg:province":"NJ",
    "sg:tags":[
        "building",
        "nonresidential"
    ],
    "wof:name":"Lauren Ventures",
    "wof:placetype":"venue"
},
  "geometry": {"coordinates":[-74.10694100000001,40.734533],"type":"Point"}
}