{
  "type": "Feature",
  "properties": {
    "iso:country":"US",
    "sg:address":"1509 Parker Rd",
    "sg:city":"Highland Park",
    "sg:classifiers":[
        {
            "category":"Wholesale",
            "subcategory":"Sporting Goods",
            "type":"Manufacturing & Wholesale Goods"
        },
        {
            "category":"Shopping",
            "subcategory":"Bicycles & Sporting Goods",
            "type":"Retail Goods"
        }
    ],
    "sg:phone":"+1 732 777 9876",
    "sg:postcode":"08904",
    "sg:province":"NJ",
    "sg:tags":[
        "instrument",
        "surgical",
        "beauty",
        "import"
    ],
    "wof:name":"Peak Industries Inc",
    "wof:placetype":"venue"
},
  "geometry": {"coordinates":[-74.41386,40.504528],"type":"Point"}
}