{
  "type": "Feature",
  "properties": {
    "iso:country":"US",
    "sg:address":"1802 Kuser Rd",
    "sg:city":"Trenton",
    "sg:classifiers":[
        {
            "category":"Real Estate",
            "subcategory":"Real Estate Operator",
            "type":"Services"
        }
    ],
    "sg:phone":"+1 609 585 8181",
    "sg:postcode":"08690",
    "sg:province":"NJ",
    "sg:tags":[
        "building",
        "apartment"
    ],
    "wof:name":"Royal Crest Apartments",
    "wof:placetype":"venue"
},
  "geometry": {"coordinates":[-74.69256,40.206999],"type":"Point"}
}