{
  "type": "Feature",
  "properties": {
    "iso:country":"US",
    "sg:address":"788 Haddon Ave",
    "sg:city":"Collingswood",
    "sg:classifiers":[
        {
            "category":"Personal",
            "subcategory":"Beauty Salon",
            "type":"Services"
        },
        {
            "category":"Arts & Performance",
            "subcategory":"Art Gallery",
            "type":"Entertainment"
        }
    ],
    "sg:phone":"+1 856 833 1116",
    "sg:postcode":"08108",
    "sg:province":"NJ",
    "sg:tags":[
        "hair"
    ],
    "sg:website":"www.bauhaushairdesign.com",
    "wof:name":"Bauhaus Hair Design",
    "wof:placetype":"venue"
},
  "geometry": {"coordinates":[-75.066892,39.915639],"type":"Point"}
}