{
  "type": "Feature",
  "properties": {
    "addr:full":"612 Summer Ave Newark NJ 07104",
    "addr:housenumber":"612",
    "addr:postcode":"07104",
    "addr:street":"Summer Ave",
    "iso:country":"US",
    "sg:address":"612 Summer Ave",
    "sg:city":"Newark",
    "sg:classifiers":[
        {
            "category":"Real Estate",
            "subcategory":"Real Estate Agent",
            "type":"Services"
        }
    ],
    "sg:phone":"+1   ",
    "sg:postcode":"07104",
    "sg:province":"NJ",
    "wof:name":"Mahoney Assoc",
    "wof:placetype":"venue"
},
  "geometry": {"coordinates":[-74.165257,40.771238],"type":"Point"}
}