{
  "type": "Feature",
  "properties": {
    "addr:full":"1119 State Rte 77 Bridgeton NJ 08302",
    "addr:housenumber":"1119",
    "addr:postcode":"08302",
    "addr:street":"State Rte 77",
    "iso:country":"US",
    "sg:address":"1119 State Rte 77",
    "sg:city":"Bridgeton",
    "sg:classifiers":[
        {
            "category":"Manufacturing",
            "subcategory":"Metals",
            "type":"Manufacturing & Wholesale Goods"
        }
    ],
    "sg:phone":"+1 856 459 3061",
    "sg:postcode":"08302",
    "sg:province":"NJ",
    "sg:tags":[
        "plumbing",
        "fixture",
        "supply"
    ],
    "wof:name":"P F Valente Assoc",
    "wof:placetype":"venue"
},
  "geometry": {"coordinates":[-75.206604,39.468841],"type":"Point"}
}