{
  "type": "Feature",
  "properties": {
    "addr:full":"51 French St New Brunswick NJ 08901",
    "addr:housenumber":"51",
    "addr:postcode":"08901",
    "addr:street":"French St",
    "iso:country":"US",
    "sg:address":"51 French St",
    "sg:city":"New Brunswick",
    "sg:classifiers":[
        {
            "category":"Education",
            "subcategory":"College",
            "type":"Public Place"
        }
    ],
    "sg:phone":"+1 732 235 7600",
    "sg:postcode":"08901",
    "sg:province":"NJ",
    "wof:name":"University Medicine/Dentistry",
    "wof:placetype":"venue"
},
  "geometry": {"coordinates":[-74.44977,40.494844],"type":"Point"}
}