{
  "type": "Feature",
  "properties": {
    "iso:country":"US",
    "sg:address":"102 Burrs Rd",
    "sg:city":"Westampton",
    "sg:classifiers":[
        {
            "category":"Retail",
            "subcategory":"Veterinary Services",
            "type":"Services"
        }
    ],
    "sg:phone":"+1 609 267 0296",
    "sg:postcode":"08060",
    "sg:province":"NJ",
    "sg:tags":[
        "veterinarian"
    ],
    "wof:name":"Calder Christine D DVM",
    "wof:placetype":"venue"
},
  "geometry": {"coordinates":[-74.807503,40.018101],"type":"Point"}
}