{
  "type": "Feature",
  "properties": {
    "iso:country":"US",
    "sg:address":"112 Main Rd",
    "sg:city":"Montville",
    "sg:classifiers":[
        {
            "category":"Building & Trades",
            "subcategory":"Electrical",
            "type":"Services"
        }
    ],
    "sg:phone":"+1   ",
    "sg:postcode":"07045",
    "sg:province":"NJ",
    "sg:tags":[
        "video",
        "audio",
        "installation",
        "sales"
    ],
    "wof:name":"Innovation Inhome Entrmt",
    "wof:placetype":"venue"
},
  "geometry": {"coordinates":[-74.384125,40.915033],"type":"Point"}
}