{
  "type": "Feature",
  "properties": {
    "iso:country":"US",
    "sg:address":"2010 W County Line Rd",
    "sg:city":"Jackson",
    "sg:classifiers":[
        {
            "category":"Retail",
            "subcategory":"Laundry & Dry Cleaning",
            "type":"Services"
        }
    ],
    "sg:phone":"+1   ",
    "sg:postcode":"08527",
    "sg:province":"NJ",
    "sg:tags":[
        "floor",
        "covering"
    ],
    "wof:name":"Superb Carpet & Upholstery",
    "wof:placetype":"venue"
},
  "geometry": {"coordinates":[-74.25227099999999,40.116777],"type":"Point"}
}