{
  "type": "Feature",
  "properties": {
    "addr:full":"19 Kipp St Fair Lawn NJ 07410",
    "addr:housenumber":"19",
    "addr:postcode":"07410",
    "addr:street":"Kipp St",
    "iso:country":"US",
    "sg:address":"19 Kipp St",
    "sg:city":"Fair Lawn",
    "sg:classifiers":[
        {
            "category":"Professional",
            "type":"Services"
        }
    ],
    "sg:phone":"+1   ",
    "sg:postcode":"07410",
    "sg:province":"NJ",
    "wof:name":"JD Colors & Coatings Inc",
    "wof:placetype":"venue"
},
  "geometry": {"coordinates":[-74.12188500000001,40.932967],"type":"Point"}
}