{
  "type": "Feature",
  "properties": {
    "addr:full":"369 W Blackwell St Dover NJ 07801",
    "addr:housenumber":"369",
    "addr:postcode":"07801",
    "addr:street":"W Blackwell St",
    "iso:country":"US",
    "sg:address":"369 W Blackwell St",
    "sg:city":"Dover",
    "sg:classifiers":[
        {
            "category":"Health Services",
            "subcategory":"Doctor",
            "type":"Services"
        }
    ],
    "sg:phone":"+1 973 366 4800",
    "sg:postcode":"07801",
    "sg:province":"NJ",
    "sg:tags":[
        "physician",
        "surgeon"
    ],
    "wof:name":"Anthony D'Alessio MD",
    "wof:placetype":"venue"
},
  "geometry": {"coordinates":[-74.57481,40.886206],"type":"Point"}
}