{
  "type": "Feature",
  "properties": {
    "addr:full":"31 Kensington Ter Maplewood NJ 07040",
    "addr:housenumber":"31",
    "addr:postcode":"07040",
    "addr:street":"Kensington Ter",
    "iso:country":"US",
    "sg:address":"31 Kensington Ter",
    "sg:city":"Maplewood",
    "sg:classifiers":[
        {
            "category":"Professional",
            "subcategory":"Computer Services",
            "type":"Services"
        }
    ],
    "sg:phone":"+1   ",
    "sg:postcode":"07040",
    "sg:province":"NJ",
    "sg:tags":[
        "related"
    ],
    "wof:name":"Harcait Technologies Inc",
    "wof:placetype":"venue"
},
  "geometry": {"coordinates":[-74.268575,40.73256],"type":"Point"}
}