{
  "type": "Feature",
  "properties": {
    "addr:full":"1016 State Rte 37 Toms River NJ 08755",
    "addr:housenumber":"1016",
    "addr:postcode":"08755",
    "addr:street":"State Rte 37",
    "iso:country":"US",
    "sg:address":"1016 State Rte 37",
    "sg:city":"Toms River",
    "sg:classifiers":[
        {
            "category":"Health Services",
            "subcategory":"Doctor",
            "type":"Services"
        }
    ],
    "sg:phone":"+1 732 349 5004",
    "sg:postcode":"08755",
    "sg:province":"NJ",
    "sg:tags":[
        "dentist"
    ],
    "wof:name":"West Dover Family Dental",
    "wof:placetype":"venue"
},
  "geometry": {"coordinates":[-74.24273100000001,39.975454],"type":"Point"}
}