{
  "type": "Feature",
  "properties": {
    "iso:country":"US",
    "sg:address":"79 Main St",
    "sg:city":"Hackensack",
    "sg:classifiers":[
        {
            "category":"Professional",
            "subcategory":"Lawyer & Legal Services",
            "type":"Services"
        }
    ],
    "sg:phone":"+1   ",
    "sg:postcode":"07601",
    "sg:province":"NJ",
    "wof:name":"Mark S Carter Esquire",
    "wof:placetype":"venue"
},
  "geometry": {"coordinates":[-74.04396300000001,40.88087],"type":"Point"}
}