{
  "type": "Feature",
  "properties": {
    "addr:full":"200 Creek Rd Riverside NJ 08075",
    "addr:housenumber":"200",
    "addr:postcode":"08075",
    "addr:street":"Creek Rd",
    "iso:country":"US",
    "sg:address":"200 Creek Rd",
    "sg:city":"Riverside",
    "sg:classifiers":[
        {
            "category":"Building & Trades",
            "subcategory":"Construction",
            "type":"Services"
        }
    ],
    "sg:phone":"+1 856 824 0643",
    "sg:postcode":"08075",
    "sg:province":"NJ",
    "sg:tags":[
        "house"
    ],
    "wof:name":"Zema Construction Co",
    "wof:placetype":"venue"
},
  "geometry": {"coordinates":[-74.92177100000001,40.016242],"type":"Point"}
}