{
  "type": "Feature",
  "properties": {
    "addr:full":"299 Flyatt Rd Tabernacle NJ 08088",
    "addr:housenumber":"299",
    "addr:postcode":"08088",
    "addr:street":"Flyatt Rd",
    "iso:country":"US",
    "sg:address":"299 Flyatt Rd",
    "sg:city":"Tabernacle",
    "sg:classifiers":[
        {
            "category":"Farming",
            "subcategory":"Farm",
            "type":"Manufacturing & Wholesale Goods"
        }
    ],
    "sg:phone":"+1 609 268 1010",
    "sg:postcode":"08088",
    "sg:province":"NJ",
    "wof:name":"Conte Farm",
    "wof:placetype":"venue"
},
  "geometry": {"coordinates":[-74.71020300000001,39.842521],"type":"Point"}
}