{
  "type": "Feature",
  "properties": {
    "addr:full":"53 S Washington Ave Bergenfield NJ 07621",
    "addr:housenumber":"53",
    "addr:postcode":"07621",
    "addr:street":"S Washington Ave",
    "iso:country":"US",
    "sg:address":"53 S Washington Ave",
    "sg:city":"Bergenfield",
    "sg:classifiers":[
        {
            "category":"Recreation",
            "type":"Entertainment"
        }
    ],
    "sg:phone":"+1   ",
    "sg:postcode":"07621",
    "sg:province":"NJ",
    "sg:tags":[
        "amusement"
    ],
    "wof:name":"Bergen Kung Fu Academy",
    "wof:placetype":"venue"
},
  "geometry": {"coordinates":[-73.996185,40.927657],"type":"Point"}
}