{
  "type": "Feature",
  "properties": {
    "iso:country":"US",
    "sg:address":"105 Atlantic City Blvd",
    "sg:city":"Bayville",
    "sg:classifiers":[
        {
            "category":"Professional",
            "type":"Services"
        }
    ],
    "sg:phone":"+1 732 505 5332",
    "sg:postcode":"08721",
    "sg:province":"NJ",
    "sg:website":"www.njairports.com",
    "wof:name":"New Jersey Outboards Svc Toms",
    "wof:placetype":"venue"
},
  "geometry": {"coordinates":[-74.17519799999999,39.929241],"type":"Point"}
}