{
  "type": "Feature",
  "properties": {
    "iso:country":"US",
    "sg:address":"2 Broad St",
    "sg:city":"Bloomfield",
    "sg:classifiers":[
        {
            "category":"Real Estate",
            "subcategory":"Developer",
            "type":"Services"
        }
    ],
    "sg:phone":"+1 973 259 9804",
    "sg:postcode":"07003",
    "sg:province":"NJ",
    "wof:name":"Homestart America Inc",
    "wof:placetype":"venue"
},
  "geometry": {"coordinates":[-74.197487,40.7946],"type":"Point"}
}