{
  "type": "Feature",
  "properties": {
    "iso:country":"US",
    "sg:address":"708 Boulevard E",
    "sg:city":"Weehawken",
    "sg:classifiers":[
        {
            "category":"Professional",
            "subcategory":"Computer Services",
            "type":"Services"
        }
    ],
    "sg:phone":"+1   ",
    "sg:postcode":"07086",
    "sg:province":"NJ",
    "sg:tags":[
        "consultant"
    ],
    "wof:name":"Jeanines",
    "wof:placetype":"venue"
},
  "geometry": {"coordinates":[-74.019976,40.770987],"type":"Point"}
}