{
  "type": "Feature",
  "properties": {
    "addr:full":"405 Central Blvd Fort Lee NJ 07024",
    "addr:housenumber":"405",
    "addr:postcode":"07024",
    "addr:street":"Central Blvd",
    "iso:country":"US",
    "sg:address":"405 Central Blvd",
    "sg:city":"Fort Lee",
    "sg:classifiers":[
        {
            "category":"Retail",
            "subcategory":"Laundry & Dry Cleaning",
            "type":"Services"
        }
    ],
    "sg:phone":"+1 201 224 4420",
    "sg:postcode":"07024",
    "sg:province":"NJ",
    "sg:tags":[
        "drycleaning",
        "plant"
    ],
    "wof:name":"T & J Cleaners",
    "wof:placetype":"venue"
},
  "geometry": {"coordinates":[-73.982613,40.839604],"type":"Point"}
}