{
  "type": "Feature",
  "properties": {
    "iso:country":"US",
    "sg:address":"499 Washington Blvd",
    "sg:city":"Jersey City",
    "sg:classifiers":[
        {
            "category":"Banks & Credit Unions",
            "subcategory":"Investment Brokerage",
            "type":"Services"
        }
    ],
    "sg:phone":"+1   ",
    "sg:postcode":"07310",
    "sg:province":"NJ",
    "sg:tags":[
        "security"
    ],
    "wof:name":"A B N Amro Incorporated",
    "wof:placetype":"venue"
},
  "geometry": {"coordinates":[-74.03468100000001,40.729936],"type":"Point"}
}