{
  "type": "Feature",
  "properties": {
    "iso:country":"US",
    "sg:address":"275 Hoym St",
    "sg:city":"Fort Lee",
    "sg:classifiers":[
        {
            "category":"Professional",
            "subcategory":"Computer Services",
            "type":"Services"
        }
    ],
    "sg:phone":"+1   ",
    "sg:postcode":"07024",
    "sg:province":"NJ",
    "sg:tags":[
        "programing",
        "custom"
    ],
    "wof:name":"Sheffer Consulting and Dev",
    "wof:placetype":"venue"
},
  "geometry": {"coordinates":[-73.97287300000001,40.850806],"type":"Point"}
}