{
  "type": "Feature",
  "properties": {
    "addr:full":"6 Littlefield Ln Hammonton NJ 08087",
    "addr:housenumber":"6",
    "addr:postcode":"08087",
    "addr:street":"Littlefield Ln",
    "iso:country":"US",
    "sg:address":"6 Littlefield Ln",
    "sg:city":"Hammonton",
    "sg:classifiers":[
        {
            "category":"Building & Trades",
            "subcategory":"Construction",
            "type":"Services"
        }
    ],
    "sg:phone":"+1 609 561 4200",
    "sg:postcode":"08087",
    "sg:province":"NJ",
    "sg:tags":[
        "downspouts",
        "gutter",
        "contractor"
    ],
    "wof:name":"Guttersmart",
    "wof:placetype":"venue"
},
  "geometry": {"coordinates":[-74.314199,39.620329],"type":"Point"}
}