{
  "type": "Feature",
  "properties": {
    "addr:full":"24 Dayton St Bernardsville NJ 07924",
    "addr:housenumber":"24",
    "addr:postcode":"07924",
    "addr:street":"Dayton St",
    "iso:country":"US",
    "sg:address":"24 Dayton St",
    "sg:city":"Bernardsville",
    "sg:classifiers":[
        {
            "category":"Building & Trades",
            "subcategory":"Electrical",
            "type":"Services"
        }
    ],
    "sg:phone":"+1 908 630 9322",
    "sg:postcode":"07924",
    "sg:province":"NJ",
    "sg:tags":[
        "electric",
        "contractor"
    ],
    "wof:name":"Glenn Miller Electrical Contr",
    "wof:placetype":"venue"
},
  "geometry": {"coordinates":[-74.566436,40.714012],"type":"Point"}
}