{
  "type": "Feature",
  "properties": {
    "iso:country":"US",
    "sg:address":"1023 Lafayette Ave",
    "sg:city":"Hawthorne",
    "sg:classifiers":[
        {
            "category":"Professional",
            "subcategory":"Management & Consulting",
            "type":"Services"
        }
    ],
    "sg:phone":"+1   ",
    "sg:postcode":"07506",
    "sg:province":"NJ",
    "sg:tags":[
        "business"
    ],
    "wof:name":"FBC Fire Bear Consultants",
    "wof:placetype":"venue"
},
  "geometry": {"coordinates":[-74.156323,40.971719],"type":"Point"}
}