{
  "type": "Feature",
  "properties": {
    "iso:country":"US",
    "sg:address":"7 Morningside Ct",
    "sg:city":"Lakewood",
    "sg:classifiers":[
        {
            "category":"Professional",
            "subcategory":"Management & Consulting",
            "type":"Services"
        }
    ],
    "sg:phone":"+1   ",
    "sg:postcode":"08701",
    "sg:province":"NJ",
    "wof:name":"White River Corp",
    "wof:placetype":"venue"
},
  "geometry": {"coordinates":[-74.17307,40.039587],"type":"Point"}
}