{
  "type": "Feature",
  "properties": {
    "addr:full":"324 New Jersey Ave Absecon NJ 08201",
    "addr:housenumber":"324",
    "addr:postcode":"08201",
    "addr:street":"New Jersey Ave",
    "iso:country":"US",
    "sg:address":"324 New Jersey Ave",
    "sg:city":"Absecon",
    "sg:classifiers":[
        {
            "category":"Retail",
            "subcategory":"Funeral Services",
            "type":"Services"
        }
    ],
    "sg:phone":"+1 609 641 0071",
    "sg:postcode":"08201",
    "sg:province":"NJ",
    "wof:name":"SCI",
    "wof:placetype":"venue"
},
  "geometry": {"coordinates":[-74.50470199999999,39.428834],"type":"Point"}
}