{
  "type": "Feature",
  "properties": {
    "addr:full":"1820 State Rte 33 Neptune NJ 07753",
    "addr:housenumber":"1820",
    "addr:postcode":"07753",
    "addr:street":"State Rte 33",
    "iso:country":"US",
    "sg:address":"1820 State Rte 33",
    "sg:city":"Neptune",
    "sg:classifiers":[
        {
            "category":"Wholesale",
            "subcategory":"Medical Equipment & Supplies",
            "type":"Manufacturing & Wholesale Goods"
        }
    ],
    "sg:phone":"+1 732 775 7104",
    "sg:postcode":"07753",
    "sg:province":"NJ",
    "sg:tags":[
        "physician",
        "surgeon"
    ],
    "wof:name":"Neptune Medical Supply",
    "wof:placetype":"venue"
},
  "geometry": {"coordinates":[-74.035794,40.208099],"type":"Point"}
}