{
  "type": "Feature",
  "properties": {
    "addr:full":"1010 Coolidge Rd Elizabeth NJ 07208",
    "addr:housenumber":"1010",
    "addr:postcode":"07208",
    "addr:street":"Coolidge Rd",
    "iso:country":"US",
    "sg:address":"1010 Coolidge Rd",
    "sg:city":"Elizabeth",
    "sg:classifiers":[
        {
            "category":"Building & Trades",
            "subcategory":"Landscaping Services",
            "type":"Services"
        }
    ],
    "sg:phone":"+1 908 352 3680",
    "sg:postcode":"07208",
    "sg:province":"NJ",
    "sg:tags":[
        "landscape",
        "contractor"
    ],
    "wof:name":"Gus' Landscaping",
    "wof:placetype":"venue"
},
  "geometry": {"coordinates":[-74.249697,40.669764],"type":"Point"}
}