{
  "type": "Feature",
  "properties": {
    "addr:full":"1999 State Rte 70 Cherry Hill NJ 08003",
    "addr:housenumber":"1999",
    "addr:postcode":"08003",
    "addr:street":"State Rte 70",
    "iso:country":"US",
    "sg:address":"1999 State Rte 70",
    "sg:city":"Cherry Hill",
    "sg:classifiers":[
        {
            "category":"Professional",
            "subcategory":"Engineering",
            "type":"Services"
        }
    ],
    "sg:phone":"+1 856 424 5206",
    "sg:postcode":"08003",
    "sg:province":"NJ",
    "sg:tags":[
        "engineer"
    ],
    "wof:name":"Lukoff Engineering Assoc",
    "wof:placetype":"venue"
},
  "geometry": {"coordinates":[-74.958294,39.899767],"type":"Point"}
}