{
  "type": "Feature",
  "properties": {
    "addr:full":"478 Pleasant Valley Way West Orange NJ 07052",
    "addr:housenumber":"478",
    "addr:postcode":"07052",
    "addr:street":"Pleasant Valley Way",
    "iso:country":"US",
    "sg:address":"478 Pleasant Valley Way",
    "sg:city":"West Orange",
    "sg:classifiers":[
        {
            "category":"Restaurant",
            "type":"Food & Drink"
        }
    ],
    "sg:menulink":"http://www.allmenus.com/nj/west-orange/258997-chopstix/menu/",
    "sg:phone":"+1 973 324 8000",
    "sg:postcode":"07052",
    "sg:province":"NJ",
    "sg:tags":[
        "sushi",
        "japanese",
        "chinese",
        "asian"
    ],
    "wof:name":"Chopstix",
    "wof:placetype":"venue"
},
  "geometry": {"coordinates":[-74.26049999999999,40.809674],"type":"Point"}
}