{
  "type": "Feature",
  "properties": {
    "iso:country":"US",
    "sg:address":"305 Monmouth Dr",
    "sg:city":"Cherry Hill",
    "sg:classifiers":[
        {
            "category":"Professional",
            "type":"Services"
        }
    ],
    "sg:phone":"+1   ",
    "sg:postcode":"08002",
    "sg:province":"NJ",
    "wof:name":"Children Of Terror",
    "wof:placetype":"venue"
},
  "geometry": {"coordinates":[-75.01710300000001,39.935072],"type":"Point"}
}