{
  "type": "Feature",
  "properties": {
    "iso:country":"US",
    "sg:address":"5678 Berkshire Valley Rd",
    "sg:city":"Oak Ridge",
    "sg:classifiers":[
        {
            "category":"Professional",
            "subcategory":"Management & Consulting",
            "type":"Services"
        }
    ],
    "sg:phone":"+1 973 697 8935",
    "sg:postcode":"07438",
    "sg:province":"NJ",
    "sg:tags":[
        "consultant",
        "energy",
        "conservation"
    ],
    "wof:name":"Sesco Inc",
    "wof:placetype":"venue"
},
  "geometry": {"coordinates":[-74.50639700000001,41.035696],"type":"Point"}
}