{
  "type": "Feature",
  "properties": {
    "addr:full":"7 Highland Pl Maplewood NJ 07040",
    "addr:housenumber":"7",
    "addr:postcode":"07040",
    "addr:street":"Highland Pl",
    "iso:country":"US",
    "sg:address":"7 Highland Pl",
    "sg:city":"Maplewood",
    "sg:classifiers":[
        {
            "category":"Retail",
            "subcategory":"Portrait Studio",
            "type":"Services"
        }
    ],
    "sg:phone":"+1 973 762 9341",
    "sg:postcode":"07040",
    "sg:province":"NJ",
    "sg:tags":[
        "photographer"
    ],
    "sg:website":"www.williamtomlinphotography.com",
    "wof:name":"Photography By William Tomlin",
    "wof:placetype":"venue"
},
  "geometry": {"coordinates":[-74.279184,40.731417],"type":"Point"}
}