{
  "type": "Feature",
  "properties": {
    "iso:country":"US",
    "sg:address":"1000 N Pearl St",
    "sg:city":"Bridgeton",
    "sg:classifiers":[
        {
            "category":"Food & Beverages",
            "subcategory":"Groceries & Convenience Stores",
            "type":"Retail Goods"
        }
    ],
    "sg:phone":"+1   ",
    "sg:postcode":"08302",
    "sg:province":"NJ",
    "wof:name":"Shoprite of Bridgeton",
    "wof:placetype":"venue"
},
  "geometry": {"coordinates":[-75.212875,39.454418],"type":"Point"}
}