{
  "type": "Feature",
  "properties": {
    "iso:country":"US",
    "sg:address":"2504 Birchwood Ct",
    "sg:city":"Scotch Plains",
    "sg:classifiers":[
        {
            "category":"Health Services",
            "subcategory":"Clinic",
            "type":"Services"
        }
    ],
    "sg:phone":"+1   ",
    "sg:postcode":"07076",
    "sg:province":"NJ",
    "wof:name":"Peggy Finkelstein",
    "wof:placetype":"venue"
},
  "geometry": {"coordinates":[-74.381545,40.661551],"type":"Point"}
}