{
  "type": "Feature",
  "properties": {
    "iso:country":"US",
    "sg:address":"263 10th St",
    "sg:city":"Jersey City",
    "sg:classifiers":[
        {
            "category":"Professional",
            "subcategory":"Management & Consulting",
            "type":"Services"
        }
    ],
    "sg:phone":"+1 201 386 9463",
    "sg:postcode":"07302",
    "sg:province":"NJ",
    "wof:name":"Ofer Management Inc",
    "wof:placetype":"venue"
},
  "geometry": {"coordinates":[-74.046344,40.729109],"type":"Point"}
}