{
  "type": "Feature",
  "properties": {
    "iso:country":"US",
    "sg:address":"85 Myer St",
    "sg:city":"Hackensack",
    "sg:classifiers":[
        {
            "category":"Shopping",
            "subcategory":"Crafts & Fabrics",
            "type":"Retail Goods"
        },
        {
            "category":"Home & Garden",
            "subcategory":"Building Materials",
            "type":"Retail Goods"
        }
    ],
    "sg:phone":"+1 201 525 0024",
    "sg:postcode":"07601",
    "sg:province":"NJ",
    "sg:tags":[
        "art",
        "supply"
    ],
    "sg:website":"www.soapstones.com",
    "wof:name":"M Teixeira International Inc",
    "wof:placetype":"venue"
},
  "geometry": {"coordinates":[-74.047679,40.881305],"type":"Point"}
}