{
  "type": "Feature",
  "properties": {
    "iso:country":"US",
    "sg:address":"19 Freeman Ave",
    "sg:city":"Denville",
    "sg:classifiers":[
        {
            "category":"Retail",
            "subcategory":"Portrait Studio",
            "type":"Services"
        }
    ],
    "sg:phone":"+1   ",
    "sg:postcode":"07834",
    "sg:province":"NJ",
    "sg:tags":[
        "photo"
    ],
    "wof:name":"Coakley Photography",
    "wof:placetype":"venue"
},
  "geometry": {"coordinates":[-74.485416,40.876342],"type":"Point"}
}