{
  "type": "Feature",
  "properties": {
    "iso:country":"US",
    "sg:address":"15 Plymouth Dr",
    "sg:city":"Barnegat",
    "sg:classifiers":[
        {
            "category":"Professional",
            "type":"Services"
        }
    ],
    "sg:phone":"+1 609 660 8181",
    "sg:postcode":"08053",
    "sg:province":"NJ",
    "sg:tags":[
        "establishment"
    ],
    "wof:name":"KARA Horizon",
    "wof:placetype":"venue"
},
  "geometry": {"coordinates":[-74.910898,39.89183],"type":"Point"}
}