{
  "type": "Feature",
  "properties": {
    "addr:full":"29 Ridge Rd Lyndhurst NJ 07071",
    "addr:housenumber":"29",
    "addr:postcode":"07071",
    "addr:street":"Ridge Rd",
    "iso:country":"US",
    "sg:address":"29 Ridge Rd",
    "sg:city":"Lyndhurst",
    "sg:classifiers":[
        {
            "category":"Restaurant",
            "type":"Food & Drink"
        },
        {
            "category":"Food & Beverages",
            "subcategory":"Bakery",
            "type":"Retail Goods"
        },
        {
            "category":"Professional",
            "subcategory":"Business Services",
            "type":"Services"
        }
    ],
    "sg:phone":"+1 201 964 1210",
    "sg:postcode":"07071",
    "sg:province":"NJ",
    "sg:tags":[
        "delivery",
        "sandwich",
        "pizza"
    ],
    "wof:name":"Lyndhurst Pizza and Restaurant",
    "wof:placetype":"venue"
},
  "geometry": {"coordinates":[-74.114108,40.815064],"type":"Point"}
}