{
  "type": "Feature",
  "properties": {
    "addr:full":"1319 Long Beach Blvd Beach Haven NJ 08008",
    "addr:housenumber":"1319",
    "addr:postcode":"08008",
    "addr:street":"Long Beach Blvd",
    "iso:country":"US",
    "sg:address":"1319 Long Beach Blvd",
    "sg:city":"Beach Haven",
    "sg:classifiers":[
        {
            "category":"Home & Garden",
            "subcategory":"Building Materials",
            "type":"Retail Goods"
        }
    ],
    "sg:phone":"+1   ",
    "sg:postcode":"08008",
    "sg:province":"NJ",
    "wof:name":"M A B Paint 166",
    "wof:placetype":"venue"
},
  "geometry": {"coordinates":[-74.17818800000001,39.646768],"type":"Point"}
}