{
  "type": "Feature",
  "properties": {
    "iso:country":"US",
    "sg:address":"15 Vervalen St",
    "sg:city":"Closter",
    "sg:classifiers":[
        {
            "category":"Professional",
            "type":"Services"
        }
    ],
    "sg:phone":"+1 201 784 7920",
    "sg:postcode":"07624",
    "sg:province":"NJ",
    "sg:tags":[
        "establishment"
    ],
    "wof:name":"Jim Cor Agency",
    "wof:placetype":"venue"
},
  "geometry": {"coordinates":[-73.957413,40.970014],"type":"Point"}
}