{
  "type": "Feature",
  "properties": {
    "addr:full":"222 Haddon Ave Ste 2A Haddon Township NJ 08108",
    "addr:housenumber":"222",
    "addr:postcode":"08108",
    "addr:street":"Haddon Ave Ste 2A",
    "iso:country":"US",
    "sg:address":"222 Haddon Ave Ste 2A",
    "sg:city":"Haddon Township",
    "sg:classifiers":[
        {
            "category":"Banks & Credit Unions",
            "subcategory":"Financial Services",
            "type":"Services"
        }
    ],
    "sg:phone":"+1 856 671 0020",
    "sg:postcode":"08108",
    "sg:province":"NJ",
    "sg:tags":[
        "broker",
        "mortgage"
    ],
    "wof:name":"E Mortgage Solutions",
    "wof:placetype":"venue"
},
  "geometry": {"coordinates":[-75.08311500000001,39.920882],"type":"Point"}
}