{
  "type": "Feature",
  "properties": {
    "addr:full":"4 Venice Ave Middlesex NJ 08846",
    "addr:housenumber":"4",
    "addr:postcode":"08846",
    "addr:street":"Venice Ave",
    "iso:country":"US",
    "sg:address":"4 Venice Ave",
    "sg:city":"Middlesex",
    "sg:classifiers":[
        {
            "category":"Building & Trades",
            "subcategory":"Cleaning & Sanitation",
            "type":"Services"
        }
    ],
    "sg:phone":"+1 732 249 6886",
    "sg:postcode":"08846",
    "sg:province":"NJ",
    "sg:tags":[
        "maintenance"
    ],
    "wof:name":"Puffin Chimney Service Inc",
    "wof:placetype":"venue"
},
  "geometry": {"coordinates":[-74.50542299999999,40.580257],"type":"Point"}
}