{
  "type": "Feature",
  "properties": {
    "iso:country":"US",
    "sg:address":"68 River Rd",
    "sg:city":"Fair Lawn",
    "sg:classifiers":[
        {
            "category":"Manufacturing",
            "subcategory":"Glass & Minerals",
            "type":"Manufacturing & Wholesale Goods"
        }
    ],
    "sg:phone":"+1 201 796 1556",
    "sg:postcode":"07410",
    "sg:province":"NJ",
    "sg:tags":[
        "ready",
        "concrete",
        "hydraulic",
        "cement",
        "mfg"
    ],
    "wof:name":"Joel Tanis & Sons Inc",
    "wof:placetype":"venue"
},
  "geometry": {"coordinates":[-74.13649599999999,40.937684],"type":"Point"}
}