{
  "type": "Feature",
  "properties": {
    "iso:country":"US",
    "sg:address":"23 Palisade Ave",
    "sg:city":"Piscataway",
    "sg:classifiers":[
        {
            "category":"Professional",
            "subcategory":"Accounting & Tax Preparation",
            "type":"Services"
        }
    ],
    "sg:phone":"+1   ",
    "sg:postcode":"08854",
    "sg:province":"NJ",
    "sg:tags":[
        "consulting",
        "management",
        "business"
    ],
    "wof:name":"James H Blow & Associates",
    "wof:placetype":"venue"
},
  "geometry": {"coordinates":[-74.431158,40.543788],"type":"Point"}
}