{
  "type": "Feature",
  "properties": {
    "addr:full":"1075 Cranbury South River Rd Monroe Township NJ 08831",
    "addr:housenumber":"1075",
    "addr:postcode":"08831",
    "addr:street":"Cranbury South River Rd",
    "iso:country":"US",
    "sg:address":"1075 Cranbury South River Rd",
    "sg:city":"Monroe Township",
    "sg:classifiers":[
        {
            "category":"Home & Garden",
            "subcategory":"Furniture",
            "type":"Retail Goods"
        }
    ],
    "sg:phone":"+1   ",
    "sg:postcode":"08831",
    "sg:province":"NJ",
    "sg:tags":[
        "store"
    ],
    "wof:name":"Factory The Sofa Inc",
    "wof:placetype":"venue"
},
  "geometry": {"coordinates":[-74.47120200000001,40.357498],"type":"Point"}
}