{
  "type": "Feature",
  "properties": {
    "addr:full":"824 Highland Ave Paramus NJ 07652",
    "addr:housenumber":"824",
    "addr:postcode":"07652",
    "addr:street":"Highland Ave",
    "iso:country":"US",
    "sg:address":"824 Highland Ave",
    "sg:city":"Paramus",
    "sg:classifiers":[
        {
            "category":"Wholesale",
            "subcategory":"Construction Materials",
            "type":"Manufacturing & Wholesale Goods"
        }
    ],
    "sg:phone":"+1 201 262 0404",
    "sg:postcode":"07652",
    "sg:province":"NJ",
    "sg:tags":[
        "fence"
    ],
    "wof:name":"Caminiti Associates",
    "wof:placetype":"venue"
},
  "geometry": {"coordinates":[-74.07206499999999,40.974053],"type":"Point"}
}