{
  "type": "Feature",
  "properties": {
    "addr:full":"340 Front St Elmer NJ 08318",
    "addr:housenumber":"340",
    "addr:postcode":"08318",
    "addr:street":"Front St",
    "iso:country":"US",
    "sg:address":"340 Front St",
    "sg:city":"Elmer",
    "sg:classifiers":[
        {
            "category":"Health Services",
            "subcategory":"Doctor",
            "type":"Services"
        }
    ],
    "sg:phone":"+1 856 358 6155",
    "sg:postcode":"08318",
    "sg:province":"NJ",
    "sg:tags":[
        "medical"
    ],
    "wof:name":"Weiss Robert J MD PC",
    "wof:placetype":"venue"
},
  "geometry": {"coordinates":[-75.179996,39.587011],"type":"Point"}
}