{
  "type": "Feature",
  "properties": {
    "addr:full":"100 Bull Run Rd Pennington NJ 08638",
    "addr:housenumber":"100",
    "addr:postcode":"08638",
    "addr:street":"Bull Run Rd",
    "iso:country":"US",
    "sg:address":"100 Bull Run Rd",
    "sg:city":"Pennington",
    "sg:classifiers":[
        {
            "category":"Organizations",
            "subcategory":"Religious Organization",
            "type":"Services"
        }
    ],
    "sg:phone":"+1 609 737 3184",
    "sg:postcode":"08638",
    "sg:province":"NJ",
    "sg:tags":[
        "church"
    ],
    "sg:website":"www.trentonnaz.org",
    "wof:name":"First Church Of The Nazarene",
    "wof:placetype":"venue"
},
  "geometry": {"coordinates":[-74.76306099999999,40.284413],"type":"Point"}
}