{
  "type": "Feature",
  "properties": {
    "iso:country":"US",
    "sg:address":"319 US Hwy 130",
    "sg:city":"Hightstown",
    "sg:classifiers":[
        {
            "category":"Personal",
            "subcategory":"Beauty Salon",
            "type":"Services"
        }
    ],
    "sg:phone":"+1 609 371 9802",
    "sg:postcode":"08520",
    "sg:province":"NJ",
    "sg:tags":[
        "hair"
    ],
    "wof:name":"Hair Cuttery",
    "wof:placetype":"venue"
},
  "geometry": {"coordinates":[-74.533624,40.277517],"type":"Point"}
}