{
  "type": "Feature",
  "properties": {
    "addr:full":"479 N Midland Ave Saddle Brook NJ 07663",
    "addr:housenumber":"479",
    "addr:postcode":"07663",
    "addr:street":"N Midland Ave",
    "iso:country":"US",
    "sg:address":"479 N Midland Ave",
    "sg:city":"Saddle Brook",
    "sg:classifiers":[
        {
            "category":"Health Services",
            "subcategory":"Doctor",
            "type":"Services"
        }
    ],
    "sg:phone":"+1 201 794 1117",
    "sg:postcode":"07663",
    "sg:province":"NJ",
    "sg:tags":[
        "medicine",
        "internal"
    ],
    "wof:name":"Savelyev Mariana MD",
    "wof:placetype":"venue"
},
  "geometry": {"coordinates":[-74.10839799999999,40.912899],"type":"Point"}
}