{
  "type": "Feature",
  "properties": {
    "addr:full":"19 Old York Rd Bridgewater NJ 08807",
    "addr:housenumber":"19",
    "addr:postcode":"08807",
    "addr:street":"Old York Rd",
    "iso:country":"US",
    "sg:address":"19 Old York Rd",
    "sg:city":"Bridgewater",
    "sg:classifiers":[
        {
            "category":"Retail",
            "subcategory":"Repair Shop",
            "type":"Services"
        }
    ],
    "sg:phone":"+1   ",
    "sg:postcode":"08807",
    "sg:province":"NJ",
    "wof:name":"24 Hour Emergency Locksmith",
    "wof:placetype":"venue"
},
  "geometry": {"coordinates":[-74.64944199999999,40.560554],"type":"Point"}
}