{
  "type": "Feature",
  "properties": {
    "iso:country":"US",
    "sg:address":"2151 Lemoine Ave",
    "sg:city":"Fort Lee",
    "sg:classifiers":[
        {
            "category":"Retail",
            "subcategory":"Laundry & Dry Cleaning",
            "type":"Services"
        }
    ],
    "sg:phone":"+1 201 944 2002",
    "sg:postcode":"07024",
    "sg:province":"NJ",
    "sg:tags":[
        "drycleaning",
        "plant"
    ],
    "wof:name":"Maxcare Cleaners",
    "wof:placetype":"venue"
},
  "geometry": {"coordinates":[-73.966641,40.856624],"type":"Point"}
}