{
  "type": "Feature",
  "properties": {
    "iso:country":"US",
    "sg:address":"60 Concord Ave",
    "sg:city":"Metuchen",
    "sg:classifiers":[
        {
            "category":"Professional",
            "subcategory":"Management & Consulting",
            "type":"Services"
        }
    ],
    "sg:phone":"+1   ",
    "sg:postcode":"08840",
    "sg:province":"NJ",
    "sg:tags":[
        "business"
    ],
    "wof:name":"Cyber Consulting",
    "wof:placetype":"venue"
},
  "geometry": {"coordinates":[-74.35101899999999,40.549345],"type":"Point"}
}