{
  "type": "Feature",
  "properties": {
    "iso:country":"US",
    "sg:address":"561 Homer Ter",
    "sg:city":"Union",
    "sg:classifiers":[
        {
            "category":"Professional",
            "subcategory":"Business Services",
            "type":"Services"
        }
    ],
    "sg:phone":"+1   ",
    "sg:postcode":"07083",
    "sg:province":"NJ",
    "wof:name":"Jne Enterprises Ltd Liability",
    "wof:placetype":"venue"
},
  "geometry": {"coordinates":[-74.262102,40.684249],"type":"Point"}
}