{
  "type": "Feature",
  "properties": {
    "iso:country":"US",
    "sg:address":"969 Lawrence Rd",
    "sg:city":"Trenton",
    "sg:classifiers":[
        {
            "category":"Professional",
            "type":"Services"
        }
    ],
    "sg:phone":"+1   ",
    "sg:postcode":"08648",
    "sg:province":"NJ",
    "wof:name":"Jean Marcelonis",
    "wof:placetype":"venue"
},
  "geometry": {"coordinates":[-74.741387,40.261325],"type":"Point"}
}