{
  "type": "Feature",
  "properties": {
    "iso:country":"US",
    "sg:address":"64 S Main St",
    "sg:city":"Marlboro",
    "sg:classifiers":[
        {
            "category":"Shopping",
            "subcategory":"Gifts & Souvenirs",
            "type":"Retail Goods"
        }
    ],
    "sg:phone":"+1   ",
    "sg:postcode":"07746",
    "sg:province":"NJ",
    "wof:name":"5th Avenue Gift Baskets",
    "wof:placetype":"venue"
},
  "geometry": {"coordinates":[-74.252799,40.304388],"type":"Point"}
}