{
  "type": "Feature",
  "properties": {
    "iso:country":"US",
    "sg:address":"1410 Orchard Ter",
    "sg:city":"Linden",
    "sg:classifiers":[
        {
            "category":"Professional",
            "subcategory":"Advertising",
            "type":"Services"
        }
    ],
    "sg:phone":"+1   ",
    "sg:postcode":"07036",
    "sg:province":"NJ",
    "sg:tags":[
        "commercial",
        "agency",
        "design"
    ],
    "wof:name":"Worthington Design",
    "wof:placetype":"venue"
},
  "geometry": {"coordinates":[-74.269263,40.638607],"type":"Point"}
}