{
  "type": "Feature",
  "properties": {
    "iso:country":"US",
    "sg:address":"109 Orchard Rd",
    "sg:city":"Skillman",
    "sg:classifiers":[
        {
            "category":"Education",
            "subcategory":"School",
            "type":"Public Place"
        },
        {
            "category":"Health Services",
            "subcategory":"Health Practitioner",
            "type":"Services"
        }
    ],
    "sg:phone":"+1 908 431 9500",
    "sg:postcode":"08558",
    "sg:province":"NJ",
    "sg:tags":[
        "academic",
        "special"
    ],
    "sg:website":"www.rock-brook.org",
    "wof:name":"Rock Brook School",
    "wof:placetype":"venue"
},
  "geometry": {"coordinates":[-74.660517,40.416643],"type":"Point"}
}