{
  "type": "Feature",
  "properties": {
    "iso:country":"US",
    "sg:address":"229 Littleton Rd",
    "sg:city":"Parsippany",
    "sg:classifiers":[
        {
            "category":"Retail",
            "subcategory":"Laundry & Dry Cleaning",
            "type":"Services"
        }
    ],
    "sg:phone":"+1   ",
    "sg:postcode":"07054",
    "sg:province":"NJ",
    "sg:tags":[
        "drycleaning",
        "plant"
    ],
    "wof:name":"Dryex Cleaners",
    "wof:placetype":"venue"
},
  "geometry": {"coordinates":[-74.419383,40.866376],"type":"Point"}
}