{
  "type": "Feature",
  "properties": {
    "iso:country":"US",
    "sg:address":"345 Commercial Ave",
    "sg:city":"Palisades Park",
    "sg:classifiers":[
        {
            "category":"Organizations",
            "subcategory":"Membership Organization",
            "type":"Services"
        }
    ],
    "sg:phone":"+1 201 242 0018",
    "sg:postcode":"07650",
    "sg:province":"NJ",
    "wof:name":"Korean Amateur Sports Assn N J",
    "wof:placetype":"venue"
},
  "geometry": {"coordinates":[-74.000682,40.853297],"type":"Point"}
}