{
  "type": "Feature",
  "properties": {
    "iso:country":"US",
    "sg:address":"5 75th St",
    "sg:city":"North Bergen",
    "sg:classifiers":[
        {
            "category":"Professional",
            "subcategory":"Lawyer & Legal Services",
            "type":"Services"
        }
    ],
    "sg:phone":"+1 201 868 0144",
    "sg:postcode":"07047",
    "sg:province":"NJ",
    "sg:tags":[
        "attorney"
    ],
    "wof:name":"Edward Pesin Law Offices",
    "wof:placetype":"venue"
},
  "geometry": {"coordinates":[-74.001025,40.795464],"type":"Point"}
}