{
  "type": "Feature",
  "properties": {
    "iso:country":"US",
    "sg:address":"10 Berkshire Ct",
    "sg:city":"Englishtown",
    "sg:classifiers":[
        {
            "category":"Wholesale",
            "subcategory":"Apparel",
            "type":"Manufacturing & Wholesale Goods"
        }
    ],
    "sg:phone":"+1 732 446 2832",
    "sg:postcode":"07726",
    "sg:province":"NJ",
    "sg:tags":[
        "representative",
        "manufacturer"
    ],
    "wof:name":"Jerry Eichhorn",
    "wof:placetype":"venue"
},
  "geometry": {"coordinates":[-74.374076,40.258994],"type":"Point"}
}