{
  "type": "Feature",
  "properties": {
    "addr:full":"604 W Main St Malaga NJ 08328",
    "addr:housenumber":"604",
    "addr:postcode":"08328",
    "addr:street":"W Main St",
    "iso:country":"US",
    "sg:address":"604 W Main St",
    "sg:city":"Malaga",
    "sg:classifiers":[
        {
            "category":"Government",
            "subcategory":"Fire Station",
            "type":"Public Place"
        }
    ],
    "sg:phone":"+1 856 694 9850",
    "sg:postcode":"08328",
    "sg:province":"NJ",
    "sg:tags":[
        "department"
    ],
    "wof:name":"Malaga Volunteer Fire Co",
    "wof:placetype":"venue"
},
  "geometry": {"coordinates":[-75.04792399999999,39.572293],"type":"Point"}
}