{
  "type": "Feature",
  "properties": {
    "addr:full":"80 Morristown Rd Bernardsville NJ 07924",
    "addr:housenumber":"80",
    "addr:postcode":"07924",
    "addr:street":"Morristown Rd",
    "iso:country":"US",
    "sg:address":"80 Morristown Rd",
    "sg:city":"Bernardsville",
    "sg:classifiers":[
        {
            "category":"Professional",
            "subcategory":"Advertising",
            "type":"Services"
        }
    ],
    "sg:phone":"+1 908 696 9005",
    "sg:postcode":"07924",
    "sg:province":"NJ",
    "sg:tags":[
        "mailing",
        "shipping"
    ],
    "wof:name":"UPS Store",
    "wof:placetype":"venue"
},
  "geometry": {"coordinates":[-74.565428,40.718922],"type":"Point"}
}