{
  "type": "Feature",
  "properties": {
    "addr:full":"160 Lincoln Ave Hawthorne NJ 07506",
    "addr:housenumber":"160",
    "addr:postcode":"07506",
    "addr:street":"Lincoln Ave",
    "iso:country":"US",
    "sg:address":"160 Lincoln Ave",
    "sg:city":"Hawthorne",
    "sg:classifiers":[
        {
            "category":"Restaurant",
            "type":"Food & Drink"
        }
    ],
    "sg:phone":"+1   ",
    "sg:postcode":"07506",
    "sg:province":"NJ",
    "wof:name":"Ossys Restaurant",
    "wof:placetype":"venue"
},
  "geometry": {"coordinates":[-74.146895,40.94633],"type":"Point"}
}