{
  "type": "Feature",
  "properties": {
    "iso:country":"US",
    "sg:address":"275 Hudson St",
    "sg:city":"Hackensack",
    "sg:classifiers":[
        {
            "category":"Manufacturing",
            "subcategory":"Tools & Machinery",
            "type":"Manufacturing & Wholesale Goods"
        }
    ],
    "sg:phone":"+1 201 342 3684",
    "sg:postcode":"07601",
    "sg:province":"NJ",
    "sg:tags":[
        "packaging",
        "machinery-wholesale",
        "manufacturer"
    ],
    "sg:website":"http://www.pmc-industries.com",
    "wof:name":"Pmc Industries Inc",
    "wof:placetype":"venue"
},
  "geometry": {"coordinates":[-74.04086100000001,40.870133],"type":"Point"}
}