{
  "type": "Feature",
  "properties": {
    "iso:country":"US",
    "sg:address":"261 Broad Ave",
    "sg:city":"Fairview",
    "sg:classifiers":[
        {
            "category":"Personal",
            "subcategory":"Beauty Salon",
            "type":"Services"
        }
    ],
    "sg:phone":"+1 201 313 1912",
    "sg:postcode":"07022",
    "sg:province":"NJ",
    "wof:name":"Kang Soon Hair Gallery",
    "wof:placetype":"venue"
},
  "geometry": {"coordinates":[-74.008667,40.823835],"type":"Point"}
}