{
  "type": "Feature",
  "properties": {
    "addr:full":"287 S Main St Barnegat NJ 08005",
    "addr:housenumber":"287",
    "addr:postcode":"08005",
    "addr:street":"S Main St",
    "iso:country":"US",
    "sg:address":"287 S Main St",
    "sg:city":"Barnegat",
    "sg:classifiers":[
        {
            "category":"Shopping",
            "type":"Retail Goods"
        }
    ],
    "sg:phone":"+1   ",
    "sg:postcode":"08005",
    "sg:province":"NJ",
    "sg:tags":[
        "merchandise"
    ],
    "wof:name":"Rock Shop",
    "wof:placetype":"venue"
},
  "geometry": {"coordinates":[-74.22716800000001,39.748027],"type":"Point"}
}