{
  "type": "Feature",
  "properties": {
    "addr:full":"255 South St Newark NJ 07114",
    "addr:housenumber":"255",
    "addr:postcode":"07114",
    "addr:street":"South St",
    "iso:country":"US",
    "sg:address":"255 South St",
    "sg:city":"Newark",
    "sg:classifiers":[
        {
            "category":"Building & Trades",
            "subcategory":"Construction",
            "type":"Services"
        }
    ],
    "sg:phone":"+1 973 344 1342",
    "sg:postcode":"07114",
    "sg:province":"NJ",
    "sg:tags":[
        "steel",
        "erection",
        "structural"
    ],
    "wof:name":"Portuguese Structural Steel",
    "wof:placetype":"venue"
},
  "geometry": {"coordinates":[-74.167723,40.720797],"type":"Point"}
}