{
  "type": "Feature",
  "properties": {
    "iso:country":"US",
    "sg:address":"1711 Pennsylvania Ave",
    "sg:city":"Linden",
    "sg:classifiers":[
        {
            "category":"Retail",
            "subcategory":"Repair Shop",
            "type":"Services"
        }
    ],
    "sg:phone":"+1 908 925 5588",
    "sg:postcode":"07036",
    "sg:province":"NJ",
    "sg:tags":[
        "upholsterer"
    ],
    "wof:name":"Silvandi's Seats",
    "wof:placetype":"venue"
},
  "geometry": {"coordinates":[-74.234419,40.646372],"type":"Point"}
}