{
  "type": "Feature",
  "properties": {
    "iso:country":"US",
    "sg:address":"2029 State Rte 35",
    "sg:city":"Wall Township",
    "sg:classifiers":[
        {
            "category":"Real Estate",
            "subcategory":"Real Estate Agent",
            "type":"Services"
        }
    ],
    "sg:phone":"+1 732 449 5555",
    "sg:postcode":"07719",
    "sg:province":"NJ",
    "sg:website":"www.harrylaneagency.com",
    "wof:name":"Harry M Lane Agency",
    "wof:placetype":"venue"
},
  "geometry": {"coordinates":[-74.055477,40.153194],"type":"Point"}
}