{
  "type": "Feature",
  "properties": {
    "iso:country":"US",
    "sg:address":"62 Hampton Rd",
    "sg:city":"Pittstown",
    "sg:classifiers":[
        {
            "category":"Farming",
            "subcategory":"Nursery",
            "type":"Manufacturing & Wholesale Goods"
        },
        {
            "category":"Building & Trades",
            "subcategory":"Landscaping Services",
            "type":"Services"
        }
    ],
    "sg:phone":"+1 908 996 2165",
    "sg:postcode":"08867",
    "sg:province":"NJ",
    "sg:tags":[
        "ornamental",
        "sod",
        "sodding"
    ],
    "wof:name":"Hunterdon Turf Farm",
    "wof:placetype":"venue"
},
  "geometry": {"coordinates":[-74.986777,40.545279],"type":"Point"}
}