{
  "type": "Feature",
  "properties": {
    "iso:country":"US",
    "sg:address":"13 Crest Haven Rd",
    "sg:city":"Cape May Ct Hse",
    "sg:classifiers":[
        {
            "category":"Organizations",
            "subcategory":"Professional Association",
            "type":"Services"
        }
    ],
    "sg:phone":"+1 609 465 7181",
    "sg:postcode":"08210",
    "sg:province":"NJ",
    "sg:tags":[
        "chambers",
        "commerce"
    ],
    "sg:website":"www.capemaycountychamber.com",
    "wof:name":"Cape May County Chamber-Cmmrce",
    "wof:placetype":"venue"
},
  "geometry": {"coordinates":[-74.809695,39.101299],"type":"Point"}
}