{
  "type": "Feature",
  "properties": {
    "iso:country":"US",
    "sg:address":"3 Meade Ln",
    "sg:city":"Mount Holly",
    "sg:classifiers":[
        {
            "category":"Professional",
            "subcategory":"Detective & Security Services",
            "type":"Services"
        }
    ],
    "sg:phone":"+1   ",
    "sg:postcode":"08060",
    "sg:province":"NJ",
    "sg:tags":[
        "car"
    ],
    "wof:name":"Borman Enterprises",
    "wof:placetype":"venue"
},
  "geometry": {"coordinates":[-74.752996,39.987439],"type":"Point"}
}