{
  "type": "Feature",
  "properties": {
    "iso:country":"US",
    "sg:address":"112 Kings Hwy E",
    "sg:city":"Haddonfield",
    "sg:classifiers":[
        {
            "category":"Shopping",
            "subcategory":"Clothing, Apparel, & Fashions",
            "type":"Retail Goods"
        }
    ],
    "sg:phone":"+1 856 216 1670",
    "sg:postcode":"08033",
    "sg:province":"NJ",
    "sg:tags":[
        "snowboard"
    ],
    "wof:name":"Powder Room Womens Surf & Snow",
    "wof:placetype":"venue"
},
  "geometry": {"coordinates":[-75.03363,39.897202],"type":"Point"}
}