{
  "type": "Feature",
  "properties": {
    "addr:full":"510 Hunter St Gloucester City NJ 08030",
    "addr:housenumber":"510",
    "addr:postcode":"08030",
    "addr:street":"Hunter St",
    "iso:country":"US",
    "sg:address":"510 Hunter St",
    "sg:city":"Gloucester City",
    "sg:classifiers":[
        {
            "category":"Building & Trades",
            "subcategory":"Plumbing",
            "type":"Services"
        }
    ],
    "sg:phone":"+1 856 456 7500",
    "sg:postcode":"08030",
    "sg:province":"NJ",
    "sg:tags":[
        "contractor"
    ],
    "wof:name":"Fire Tech Automatic Sprinkler",
    "wof:placetype":"venue"
},
  "geometry": {"coordinates":[-75.123634,39.892889],"type":"Point"}
}