{
  "type": "Feature",
  "properties": {
    "iso:country":"US",
    "sg:address":"139 Gibbs Ave",
    "sg:city":"Somers Point",
    "sg:classifiers":[
        {
            "category":"Building & Trades",
            "subcategory":"Construction",
            "type":"Services"
        }
    ],
    "sg:phone":"+1 609 927 0797",
    "sg:postcode":"08244",
    "sg:province":"NJ",
    "sg:tags":[
        "floor",
        "laying",
        "contractor"
    ],
    "wof:name":"Doebleys Flooring",
    "wof:placetype":"venue"
},
  "geometry": {"coordinates":[-74.59164800000001,39.312069],"type":"Point"}
}