{
  "type": "Feature",
  "properties": {
    "addr:full":"755 W Side Ave Jersey City NJ 07306",
    "addr:housenumber":"755",
    "addr:postcode":"07306",
    "addr:street":"W Side Ave",
    "iso:country":"US",
    "sg:address":"755 W Side Ave",
    "sg:city":"Jersey City",
    "sg:classifiers":[
        {
            "category":"Professional",
            "subcategory":"Lawyer & Legal Services",
            "type":"Services"
        }
    ],
    "sg:phone":"+1 201 332 1800",
    "sg:postcode":"07306",
    "sg:province":"NJ",
    "sg:tags":[
        "attorney"
    ],
    "wof:name":"Anna C Moreira Law Offices",
    "wof:placetype":"venue"
},
  "geometry": {"coordinates":[-74.076915,40.726247],"type":"Point"}
}