{
  "type": "Feature",
  "properties": {
    "addr:full":"57 Glen Ave E Harrington Park NJ 07640",
    "addr:housenumber":"57",
    "addr:postcode":"07640",
    "addr:street":"Glen Ave E",
    "iso:country":"US",
    "sg:address":"57 Glen Ave E",
    "sg:city":"Harrington Park",
    "sg:classifiers":[
        {
            "category":"Professional",
            "subcategory":"Business Services",
            "type":"Services"
        }
    ],
    "sg:phone":"+1   ",
    "sg:postcode":"07640",
    "sg:province":"NJ",
    "sg:tags":[
        "house",
        "mail"
    ],
    "wof:name":"Coffee Dog Inc",
    "wof:placetype":"venue"
},
  "geometry": {"coordinates":[-73.978768,40.988179],"type":"Point"}
}