{
  "type": "Feature",
  "properties": {
    "addr:full":"58 Woodland Ave Mullica Hill NJ 08062",
    "addr:housenumber":"58",
    "addr:postcode":"08062",
    "addr:street":"Woodland Ave",
    "iso:country":"US",
    "sg:address":"58 Woodland Ave",
    "sg:city":"Mullica Hill",
    "sg:classifiers":[
        {
            "category":"Professional",
            "type":"Services"
        }
    ],
    "sg:phone":"+1   ",
    "sg:postcode":"08062",
    "sg:province":"NJ",
    "sg:website":"www.advanced-analytics.com",
    "wof:name":"Advanced Analytics",
    "wof:placetype":"venue"
},
  "geometry": {"coordinates":[-75.237292,39.739217],"type":"Point"}
}