{
  "type": "Feature",
  "properties": {
    "addr:full":"474 Getty Ave Clifton NJ 07011",
    "addr:housenumber":"474",
    "addr:postcode":"07011",
    "addr:street":"Getty Ave",
    "iso:country":"US",
    "sg:address":"474 Getty Ave",
    "sg:city":"Clifton",
    "sg:classifiers":[
        {
            "category":"Manufacturing",
            "subcategory":"Textiles",
            "type":"Manufacturing & Wholesale Goods"
        },
        {
            "category":"Wholesale",
            "subcategory":"Home Furnishings",
            "type":"Manufacturing & Wholesale Goods"
        }
    ],
    "sg:phone":"+1 973 772 8019",
    "sg:postcode":"07011",
    "sg:province":"NJ",
    "sg:tags":[
        "linen",
        "mfg"
    ],
    "sg:website":"www.tablecloths.net",
    "wof:name":"Something Different Linen Inc",
    "wof:placetype":"venue"
},
  "geometry": {"coordinates":[-74.150806,40.888311],"type":"Point"}
}