{
  "type": "Feature",
  "properties": {
    "addr:full":"19 Delaware Ave Passaic NJ 07055",
    "addr:housenumber":"19",
    "addr:postcode":"07055",
    "addr:street":"Delaware Ave",
    "iso:country":"US",
    "sg:address":"19 Delaware Ave",
    "sg:city":"Passaic",
    "sg:classifiers":[
        {
            "category":"Manufacturing",
            "subcategory":"Printing",
            "type":"Manufacturing & Wholesale Goods"
        }
    ],
    "sg:phone":"+1 973 778 0885",
    "sg:postcode":"07055",
    "sg:province":"NJ",
    "sg:tags":[
        "engraver",
        "wood"
    ],
    "sg:website":"www.acmeengraving.com",
    "wof:name":"Acme Engraving Co",
    "wof:placetype":"venue"
},
  "geometry": {"coordinates":[-74.13977800000001,40.855517],"type":"Point"}
}