{
  "type": "Feature",
  "properties": {
    "iso:country":"US",
    "sg:address":"462 Millburn Ave",
    "sg:city":"Millburn",
    "sg:classifiers":[
        {
            "category":"Professional",
            "type":"Services"
        }
    ],
    "sg:phone":"+1 973 467 9031",
    "sg:postcode":"07041",
    "sg:province":"NJ",
    "sg:tags":[
        "establishment"
    ],
    "wof:name":"Aramark",
    "wof:placetype":"venue"
},
  "geometry": {"coordinates":[-74.315251,40.721703],"type":"Point"}
}