{
  "type": "Feature",
  "properties": {
    "iso:country":"US",
    "sg:address":"16 Springhouse Rd",
    "sg:city":"Ocean",
    "sg:classifiers":[
        {
            "category":"Shopping",
            "subcategory":"Catalog Store",
            "type":"Retail Goods"
        }
    ],
    "sg:phone":"+1 732 922 0116",
    "sg:postcode":"07712",
    "sg:province":"NJ",
    "sg:tags":[
        "internet"
    ],
    "wof:name":"J & A Enterprises Inc",
    "wof:placetype":"venue"
},
  "geometry": {"coordinates":[-74.062181,40.242471],"type":"Point"}
}