{
  "type": "Feature",
  "properties": {
    "addr:full":"513 Bloomfield Ave Montclair NJ 07042",
    "addr:housenumber":"513",
    "addr:postcode":"07042",
    "addr:street":"Bloomfield Ave",
    "iso:country":"US",
    "sg:address":"513 Bloomfield Ave",
    "sg:city":"Montclair",
    "sg:classifiers":[
        {
            "category":"Wholesale",
            "subcategory":"Machinery & Supplies",
            "type":"Manufacturing & Wholesale Goods"
        }
    ],
    "sg:phone":"+1 973 509 0080",
    "sg:postcode":"07042",
    "sg:province":"NJ",
    "sg:tags":[
        "industrial"
    ],
    "wof:name":"Frame-M-Art Inc",
    "wof:placetype":"venue"
},
  "geometry": {"coordinates":[-74.21914099999999,40.815124],"type":"Point"}
}