{
  "type": "Feature",
  "properties": {
    "addr:full":"94 Tappan St Kearny NJ 07032",
    "addr:housenumber":"94",
    "addr:postcode":"07032",
    "addr:street":"Tappan St",
    "iso:country":"US",
    "sg:address":"94 Tappan St",
    "sg:city":"Kearny",
    "sg:classifiers":[
        {
            "category":"Building & Trades",
            "subcategory":"Construction",
            "type":"Services"
        }
    ],
    "sg:phone":"+1 201 991 3064",
    "sg:postcode":"07032",
    "sg:province":"NJ",
    "sg:tags":[
        "house"
    ],
    "wof:name":"Antonio Simoes",
    "wof:placetype":"venue"
},
  "geometry": {"coordinates":[-74.14605299999999,40.753005],"type":"Point"}
}