{
  "type": "Feature",
  "properties": {
    "iso:country":"US",
    "sg:address":"320A Bloomfield ave",
    "sg:city":"Verona",
    "sg:classifiers":[
        {
            "category":"Health Services",
            "subcategory":"Clinic",
            "type":"Services"
        }
    ],
    "sg:phone":"+1 973 857 9090",
    "sg:postcode":"07044",
    "sg:province":"NJ",
    "sg:tags":[
        "counseling",
        "mental"
    ],
    "sg:website":"www.SueWaldman.com",
    "wof:name":"Sue Waldman MA, LPC,CEC",
    "wof:placetype":"venue"
},
  "geometry": {"coordinates":[-74.240728,40.828733],"type":"Point"}
}