{
  "type": "Feature",
  "properties": {
    "iso:country":"US",
    "sg:address":"2 Fairview Ave",
    "sg:city":"Little Silver",
    "sg:classifiers":[
        {
            "category":"Building & Trades",
            "subcategory":"Construction",
            "type":"Services"
        },
        {
            "category":"Home & Garden",
            "subcategory":"Furniture",
            "type":"Retail Goods"
        }
    ],
    "sg:phone":"+1 732 842 7393",
    "sg:postcode":"07739",
    "sg:province":"NJ",
    "sg:tags":[
        "cabinet",
        "contractor"
    ],
    "wof:name":"S D Designs Inc",
    "wof:placetype":"venue"
},
  "geometry": {"coordinates":[-74.03613199999999,40.323454],"type":"Point"}
}