{
  "type": "Feature",
  "properties": {
    "addr:full":"116 Tomlin Ave Villas NJ 08251",
    "addr:housenumber":"116",
    "addr:postcode":"08251",
    "addr:street":"Tomlin Ave Villas",
    "iso:country":"US",
    "sg:address":"116 Tomlin Ave",
    "sg:city":"Villas",
    "sg:classifiers":[
        {
            "category":"Airport",
            "type":"Transportation"
        }
    ],
    "sg:phone":"+1 609 886 8865",
    "sg:postcode":"08251",
    "sg:province":"NJ",
    "sg:tags":[
        "aircraft",
        "maintenance"
    ],
    "sg:website":"www.tekaircraft.4t.com",
    "wof:name":"Tek Aircraft Svc",
    "wof:placetype":"venue"
},
  "geometry": {"coordinates":[-74.929681,39.025984],"type":"Point"}
}