{
  "type": "Feature",
  "properties": {
    "addr:full":"363 Cliff St Fairview NJ 07022",
    "addr:housenumber":"363",
    "addr:postcode":"07022",
    "addr:street":"Cliff St",
    "iso:country":"US",
    "sg:address":"363 Cliff St",
    "sg:city":"Fairview",
    "sg:classifiers":[
        {
            "category":"Wholesale",
            "subcategory":"Non-durable Goods",
            "type":"Manufacturing & Wholesale Goods"
        },
        {
            "category":"Wholesale",
            "subcategory":"Durable Goods & Equipment",
            "type":"Manufacturing & Wholesale Goods"
        }
    ],
    "sg:phone":"+1 201 840 5150",
    "sg:postcode":"07022",
    "sg:province":"NJ",
    "sg:tags":[
        "importer"
    ],
    "wof:name":"Trade Gentleman Inc",
    "wof:placetype":"venue"
},
  "geometry": {"coordinates":[-73.994153,40.817599],"type":"Point"}
}