{
  "type": "Feature",
  "properties": {
    "iso:country":"US",
    "sg:address":"217 Washington Ave",
    "sg:city":"Carlstadt",
    "sg:classifiers":[
        {
            "category":"Freight",
            "type":"Transportation"
        }
    ],
    "sg:phone":"+1 201 438 9461",
    "sg:postcode":"07072",
    "sg:province":"NJ",
    "sg:tags":[
        "operator",
        "local",
        "trucking"
    ],
    "wof:name":"Rew Forwarding Inc",
    "wof:placetype":"venue"
},
  "geometry": {"coordinates":[-74.065296,40.818197],"type":"Point"}
}