{
  "type": "Feature",
  "properties": {
    "addr:full":"71 Livingston Dr Belle Mead NJ 08502",
    "addr:housenumber":"71",
    "addr:postcode":"08502",
    "addr:street":"Livingston Dr Belle Mead",
    "iso:country":"US",
    "sg:address":"71 Livingston Dr",
    "sg:city":"Belle Mead",
    "sg:classifiers":[
        {
            "category":"Manufacturing",
            "subcategory":"Electronics",
            "type":"Manufacturing & Wholesale Goods"
        }
    ],
    "sg:phone":"+1 908 410 4530",
    "sg:postcode":"08502",
    "sg:province":"NJ",
    "sg:tags":[
        "equipment",
        "mfg",
        "communications"
    ],
    "wof:name":"Grid Gateways Inc",
    "wof:placetype":"venue"
},
  "geometry": {"coordinates":[-74.609275,40.45352],"type":"Point"}
}