{
  "type": "Feature",
  "properties": {
    "iso:country":"US",
    "sg:address":"80 Walnut St",
    "sg:city":"Oakland",
    "sg:classifiers":[
        {
            "category":"Wholesale",
            "subcategory":"Machinery & Supplies",
            "type":"Manufacturing & Wholesale Goods"
        }
    ],
    "sg:phone":"+1 201 651 2003",
    "sg:postcode":"07436",
    "sg:province":"NJ",
    "sg:tags":[
        "equipment",
        "industrial"
    ],
    "wof:name":"Valquip Corp",
    "wof:placetype":"venue"
},
  "geometry": {"coordinates":[-74.238719,41.02005],"type":"Point"}
}