{
  "type": "Feature",
  "properties": {
    "addr:full":"416 W Grand St Elizabeth NJ 07202",
    "addr:housenumber":"416",
    "addr:postcode":"07202",
    "addr:street":"W Grand St",
    "iso:country":"US",
    "sg:address":"416 W Grand St",
    "sg:city":"Elizabeth",
    "sg:classifiers":[
        {
            "category":"Manufacturing",
            "subcategory":"Tools & Machinery",
            "type":"Manufacturing & Wholesale Goods"
        }
    ],
    "sg:phone":"+1 908 351 0300",
    "sg:postcode":"07202",
    "sg:province":"NJ",
    "sg:tags":[
        "air",
        "parts",
        "conditioning",
        "supply"
    ],
    "sg:website":"www.abegruber.com",
    "wof:name":"Abe Gruber & Co",
    "wof:placetype":"venue"
},
  "geometry": {"coordinates":[-74.23292600000001,40.664222],"type":"Point"}
}