{
  "type": "Feature",
  "properties": {
    "iso:country":"US",
    "sg:address":"5 Rosemary Dr",
    "sg:city":"Hazlet",
    "sg:classifiers":[
        {
            "category":"Manufacturing",
            "subcategory":"Paper Products",
            "type":"Manufacturing & Wholesale Goods"
        },
        {
            "category":"Wholesale",
            "subcategory":"Durable Goods & Equipment",
            "type":"Manufacturing & Wholesale Goods"
        }
    ],
    "sg:phone":"+1 732 739 3632",
    "sg:postcode":"07730",
    "sg:province":"NJ",
    "sg:tags":[
        "importer",
        "paperboard",
        "mill"
    ],
    "wof:name":"Mac Sipes Enterprises",
    "wof:placetype":"venue"
},
  "geometry": {"coordinates":[-74.199974,40.419591],"type":"Point"}
}