{
  "type": "Feature",
  "properties": {
    "addr:full":"200 Park Ave Hoboken NJ 07030",
    "addr:housenumber":"200",
    "addr:postcode":"07030",
    "addr:street":"Park Ave",
    "iso:country":"US",
    "sg:address":"200 Park Ave",
    "sg:city":"Hoboken",
    "sg:classifiers":[
        {
            "category":"Retail",
            "subcategory":"Laundry & Dry Cleaning",
            "type":"Services"
        }
    ],
    "sg:phone":"+1 201 798 9005",
    "sg:postcode":"07030",
    "sg:province":"NJ",
    "wof:name":"Park Fashion Cleaner",
    "wof:placetype":"venue"
},
  "geometry": {"coordinates":[-74.03299699999999,40.739399],"type":"Point"}
}