{
  "type": "Feature",
  "properties": {
    "iso:country":"US",
    "sg:address":"218 Ewingville Rd",
    "sg:city":"Trenton",
    "sg:classifiers":[
        {
            "category":"Communications",
            "subcategory":"Radio Station",
            "type":"Services"
        }
    ],
    "sg:phone":"+1 609 882 8224",
    "sg:postcode":"08638",
    "sg:province":"NJ",
    "sg:tags":[
        "company",
        "broadcasting"
    ],
    "wof:name":"Shadow Traffic Network",
    "wof:placetype":"venue"
},
  "geometry": {"coordinates":[-74.75998800000001,40.265276],"type":"Point"}
}