{
  "type": "Feature",
  "properties": {
    "iso:country":"US",
    "sg:address":"1692 Oak Tree Rd",
    "sg:city":"Edison",
    "sg:classifiers":[
        {
            "category":"Health Services",
            "subcategory":"Doctor",
            "type":"Services"
        }
    ],
    "sg:phone":"+1   ",
    "sg:postcode":"08820",
    "sg:province":"NJ",
    "sg:tags":[
        "medical"
    ],
    "wof:name":"Dunn Jonathan C MD",
    "wof:placetype":"venue"
},
  "geometry": {"coordinates":[-74.34666799999999,40.572514],"type":"Point"}
}