{
  "type": "Feature",
  "properties": {
    "iso:country":"US",
    "sg:address":"33 Haran Cir",
    "sg:city":"Millburn",
    "sg:classifiers":[
        {
            "category":"Freight",
            "type":"Transportation"
        }
    ],
    "sg:phone":"+1 973 376 7071",
    "sg:postcode":"07041",
    "sg:province":"NJ",
    "sg:tags":[
        "courier"
    ],
    "wof:name":"Best Parcel Service",
    "wof:placetype":"venue"
},
  "geometry": {"coordinates":[-74.296131,40.71729],"type":"Point"}
}