{
  "type": "Feature",
  "properties": {
    "addr:full":"3158 Westfield Ave Camden NJ 08105",
    "addr:housenumber":"3158",
    "addr:postcode":"08105",
    "addr:street":"Westfield Ave",
    "iso:country":"US",
    "sg:address":"3158 Westfield Ave",
    "sg:city":"Camden",
    "sg:classifiers":[
        {
            "category":"Food & Beverages",
            "subcategory":"Fruits & Vegetables",
            "type":"Retail Goods"
        }
    ],
    "sg:phone":"+1   ",
    "sg:postcode":"08105",
    "sg:province":"NJ",
    "wof:name":"Ha Tien Produce",
    "wof:placetype":"venue"
},
  "geometry": {"coordinates":[-75.07974900000001,39.949782],"type":"Point"}
}