{
  "type": "Feature",
  "properties": {
    "iso:country":"US",
    "sg:address":"243 Ellin Dr",
    "sg:city":"Park Ridge",
    "sg:classifiers":[
        {
            "category":"Professional",
            "type":"Services"
        }
    ],
    "sg:phone":"+1   ",
    "sg:postcode":"07656",
    "sg:province":"NJ",
    "sg:website":"www.barhoppingusa.com",
    "wof:name":"TGB Assoc",
    "wof:placetype":"venue"
},
  "geometry": {"coordinates":[-74.021818,41.022388],"type":"Point"}
}