{
  "type": "Feature",
  "properties": {
    "iso:country":"US",
    "sg:address":"282 Chancellor Ave",
    "sg:city":"Newark",
    "sg:classifiers":[
        {
            "category":"Personal",
            "subcategory":"Beauty Salon",
            "type":"Services"
        }
    ],
    "sg:phone":"+1 973 705 8800",
    "sg:postcode":"07112",
    "sg:province":"NJ",
    "wof:name":"Chocolate City Hair Salon",
    "wof:placetype":"venue"
},
  "geometry": {"coordinates":[-74.220224,40.708709],"type":"Point"}
}