{
  "type": "Feature",
  "properties": {
    "addr:full":"535 Sycamore Ave Shrewsbury NJ 07702",
    "addr:housenumber":"535",
    "addr:postcode":"07702",
    "addr:street":"Sycamore Ave",
    "iso:country":"US",
    "sg:address":"535 Sycamore Ave",
    "sg:city":"Shrewsbury",
    "sg:classifiers":[
        {
            "category":"Social Services",
            "type":"Services"
        }
    ],
    "sg:phone":"+1   ",
    "sg:postcode":"07702",
    "sg:province":"NJ",
    "wof:name":"Levitt Adrian Restivo MA Ncc",
    "wof:placetype":"venue"
},
  "geometry": {"coordinates":[-74.072536,40.323165],"type":"Point"}
}