{
  "type": "Feature",
  "properties": {
    "iso:country":"US",
    "sg:address":"330 Market St",
    "sg:city":"Paterson",
    "sg:classifiers":[
        {
            "category":"Retail",
            "subcategory":"Auto Repair",
            "type":"Services"
        }
    ],
    "sg:phone":"+1 973 523 5900",
    "sg:postcode":"07501",
    "sg:province":"NJ",
    "sg:tags":[
        "automotive"
    ],
    "wof:name":"Market Trucking Corp",
    "wof:placetype":"venue"
},
  "geometry": {"coordinates":[-74.16498799999999,40.914714],"type":"Point"}
}