{
  "type": "Feature",
  "properties": {
    "iso:country":"US",
    "sg:address":"590 Midwood Dr",
    "sg:city":"Brick",
    "sg:classifiers":[
        {
            "category":"Professional",
            "type":"Services"
        }
    ],
    "sg:phone":"+1 732 714 0327",
    "sg:postcode":"08724",
    "sg:province":"NJ",
    "sg:tags":[
        "establishment"
    ],
    "wof:name":"Regent International Sltn",
    "wof:placetype":"venue"
},
  "geometry": {"coordinates":[-74.083309,40.063899],"type":"Point"}
}