{
  "type": "Feature",
  "properties": {
    "addr:full":"301 S Main Rd Vineland NJ 08360",
    "addr:housenumber":"301",
    "addr:postcode":"08360",
    "addr:street":"S Main Rd",
    "iso:country":"US",
    "sg:address":"301 S Main Rd",
    "sg:city":"Vineland",
    "sg:classifiers":[
        {
            "category":"Restaurant",
            "type":"Food & Drink"
        }
    ],
    "sg:menulink":"http://www.allmenus.com/nj/vineland/94160-boston-market/menu/",
    "sg:phone":"+1 856 507 7970",
    "sg:postcode":"08360",
    "sg:province":"NJ",
    "sg:tags":[
        "barbecue",
        "american",
        "soup"
    ],
    "wof:name":"Boston Market",
    "wof:placetype":"venue"
},
  "geometry": {"coordinates":[-75.00051499999999,39.480761],"type":"Point"}
}