{
  "type": "Feature",
  "properties": {
    "iso:country":"US",
    "sg:address":"325 Hudson St",
    "sg:city":"Hackensack",
    "sg:classifiers":[
        {
            "category":"Shopping",
            "subcategory":"Bicycles & Sporting Goods",
            "type":"Retail Goods"
        }
    ],
    "sg:phone":"+1 201 678 0123",
    "sg:postcode":"07601",
    "sg:province":"NJ",
    "wof:name":"All American Sports Shop",
    "wof:placetype":"venue"
},
  "geometry": {"coordinates":[-74.040001,40.868401],"type":"Point"}
}