{
  "type": "Feature",
  "properties": {
    "addr:full":"487 Springfield Ave Berkeley Heights NJ 07922",
    "addr:housenumber":"487",
    "addr:postcode":"07922",
    "addr:street":"Springfield Ave",
    "iso:country":"US",
    "sg:address":"487 Springfield Ave",
    "sg:city":"Berkeley Heights",
    "sg:classifiers":[
        {
            "category":"Building & Trades",
            "subcategory":"Locksmith",
            "type":"Services"
        }
    ],
    "sg:phone":"+1 888 277 6682",
    "sg:postcode":"07922",
    "sg:province":"NJ",
    "sg:tags":[
        "key"
    ],
    "wof:name":"1 24 Hour Emergency Locksmith",
    "wof:placetype":"venue"
},
  "geometry": {"coordinates":[-74.441433,40.684087],"type":"Point"}
}