{
  "type": "Feature",
  "properties": {
    "addr:full":"242 Court Pl Plainfield NJ 07060",
    "addr:housenumber":"242",
    "addr:postcode":"07060",
    "addr:street":"Court Pl",
    "iso:country":"US",
    "sg:address":"242 Court Pl",
    "sg:city":"Plainfield",
    "sg:classifiers":[
        {
            "category":"Insurance",
            "subcategory":"Hazard Insurance",
            "type":"Services"
        },
        {
            "category":"Professional",
            "subcategory":"Business Services",
            "type":"Services"
        }
    ],
    "sg:phone":"+1 908 226 1557",
    "sg:postcode":"07060",
    "sg:province":"NJ",
    "sg:tags":[
        "bond"
    ],
    "wof:name":"In & Out Bail Bond Inc",
    "wof:placetype":"venue"
},
  "geometry": {"coordinates":[-74.417312,40.619039],"type":"Point"}
}