{
  "type": "Feature",
  "properties": {
    "addr:full":"64 Winding Rd Iselin NJ 08830",
    "addr:housenumber":"64",
    "addr:postcode":"08830",
    "addr:street":"Winding Rd",
    "iso:country":"US",
    "sg:address":"64 Winding Rd",
    "sg:city":"Iselin",
    "sg:classifiers":[
        {
            "category":"Building & Trades",
            "subcategory":"Landscaping Services",
            "type":"Services"
        }
    ],
    "sg:phone":"+1 732 283 5051",
    "sg:postcode":"08830",
    "sg:province":"NJ",
    "wof:name":"Grace Landscaping",
    "wof:placetype":"venue"
},
  "geometry": {"coordinates":[-74.316061,40.566266],"type":"Point"}
}