{
  "type": "Feature",
  "properties": {
    "addr:full":"130 Hardenburgh Ave Demarest NJ 07627",
    "addr:housenumber":"130",
    "addr:postcode":"07627",
    "addr:street":"Hardenburgh Ave",
    "iso:country":"US",
    "sg:address":"130 Hardenburgh Ave",
    "sg:city":"Demarest",
    "sg:classifiers":[
        {
            "category":"Retail",
            "subcategory":"Repair Shop",
            "type":"Services"
        }
    ],
    "sg:phone":"+1 201 334 3436",
    "sg:postcode":"07627",
    "sg:province":"NJ",
    "sg:tags":[
        "lock",
        "locksmith"
    ],
    "wof:name":"24 Hour Locksmith",
    "wof:placetype":"venue"
},
  "geometry": {"coordinates":[-73.96383400000001,40.957278],"type":"Point"}
}