{
  "type": "Feature",
  "properties": {
    "addr:full":"427 Haddon Ave Collingswood NJ 08108",
    "addr:housenumber":"427",
    "addr:postcode":"08108",
    "addr:street":"Haddon Ave",
    "iso:country":"US",
    "sg:address":"427 Haddon Ave",
    "sg:city":"Collingswood",
    "sg:classifiers":[
        {
            "category":"Retail",
            "subcategory":"Portrait Studio",
            "type":"Services"
        }
    ],
    "sg:phone":"+1   ",
    "sg:postcode":"08108",
    "sg:province":"NJ",
    "sg:tags":[
        "photo"
    ],
    "wof:name":"Tom Mihalek Photography",
    "wof:placetype":"venue"
},
  "geometry": {"coordinates":[-75.07681599999999,39.918957],"type":"Point"}
}