{
  "type": "Feature",
  "properties": {
    "addr:full":"303 US Hwy 206 Bridgewater NJ 08807",
    "addr:housenumber":"303",
    "addr:postcode":"08807",
    "addr:street":"Us Hwy 206",
    "iso:country":"US",
    "sg:address":"303 US Hwy 206",
    "sg:city":"Bridgewater",
    "sg:classifiers":[
        {
            "category":"Utilities",
            "subcategory":"Mobile Phone",
            "type":"Services"
        }
    ],
    "sg:phone":"+1 908 252 0282",
    "sg:postcode":"08807",
    "sg:province":"NJ",
    "sg:tags":[
        "telephone",
        "cellular"
    ],
    "wof:name":"Go Wireless",
    "wof:placetype":"venue"
},
  "geometry": {"coordinates":[-74.622051,40.582567],"type":"Point"}
}