{
  "type": "Feature",
  "properties": {
    "iso:country":"US",
    "sg:address":"172 US Hwy 9",
    "sg:city":"Englishtown",
    "sg:classifiers":[
        {
            "category":"Personal",
            "type":"Services"
        }
    ],
    "sg:phone":"+1 732 972 9559",
    "sg:postcode":"07726",
    "sg:province":"NJ",
    "sg:tags":[
        "therapist",
        "massage"
    ],
    "wof:name":"Lily's Body Works",
    "wof:placetype":"venue"
},
  "geometry": {"coordinates":[-74.308001,40.347083],"type":"Point"}
}