{
  "type": "Feature",
  "properties": {
    "addr:full":"180 S Broadway Fair Lawn NJ 07663",
    "addr:housenumber":"180",
    "addr:postcode":"07663",
    "addr:street":"S Broadway",
    "iso:country":"US",
    "sg:address":"180 S Broadway",
    "sg:city":"Fair Lawn",
    "sg:classifiers":[
        {
            "category":"Manufacturing",
            "subcategory":"Chemicals & Compounds",
            "type":"Manufacturing & Wholesale Goods"
        }
    ],
    "sg:phone":"+1 201 791 2218",
    "sg:postcode":"07663",
    "sg:province":"NJ",
    "sg:tags":[
        "preparation",
        "pharmaceutical",
        "mfg"
    ],
    "wof:name":"Kmart",
    "wof:placetype":"venue"
},
  "geometry": {"coordinates":[-74.098889,40.921032],"type":"Point"}
}