{
  "type": "Feature",
  "properties": {
    "addr:full":"946 S 4th St Camden NJ 08103",
    "addr:housenumber":"946",
    "addr:postcode":"08103",
    "addr:street":"S 4Th St",
    "iso:country":"US",
    "sg:address":"946 S 4th St",
    "sg:city":"Camden",
    "sg:classifiers":[
        {
            "category":"Food & Beverages",
            "subcategory":"Groceries & Convenience Stores",
            "type":"Retail Goods"
        }
    ],
    "sg:phone":"+1 856 541 5718",
    "sg:postcode":"08103",
    "sg:province":"NJ",
    "wof:name":"Nunec Brothers",
    "wof:placetype":"venue"
},
  "geometry": {"coordinates":[-75.12249799999999,39.933601],"type":"Point"}
}