{
  "type": "Feature",
  "properties": {
    "addr:full":"11 E Church St Bordentown NJ 08505",
    "addr:housenumber":"11",
    "addr:postcode":"08505",
    "addr:street":"E Church St",
    "iso:country":"US",
    "sg:address":"11 E Church St",
    "sg:city":"Bordentown",
    "sg:classifiers":[
        {
            "category":"Home & Garden",
            "subcategory":"Furniture",
            "type":"Retail Goods"
        }
    ],
    "sg:phone":"+1 609 298 4456",
    "sg:postcode":"08505",
    "sg:province":"NJ",
    "sg:tags":[
        "store"
    ],
    "wof:name":"Silk & Tweed",
    "wof:placetype":"venue"
},
  "geometry": {"coordinates":[-74.712394,40.147244],"type":"Point"}
}