{
  "type": "Feature",
  "properties": {
    "addr:full":"336 Kings Hwy Swedesboro NJ 08085",
    "addr:housenumber":"336",
    "addr:postcode":"08085",
    "addr:street":"Kings Hwy",
    "iso:country":"US",
    "sg:address":"336 Kings Hwy",
    "sg:city":"Swedesboro",
    "sg:classifiers":[
        {
            "category":"Restaurant",
            "type":"Food & Drink"
        }
    ],
    "sg:phone":"+1 856 241 8988",
    "sg:postcode":"08085",
    "sg:province":"NJ",
    "wof:name":"Great Wall",
    "wof:placetype":"venue"
},
  "geometry": {"coordinates":[-75.308622,39.748901],"type":"Point"}
}