{
  "type": "Feature",
  "properties": {
    "iso:country":"US",
    "sg:address":"25 Marcia St",
    "sg:city":"Parlin",
    "sg:classifiers":[
        {
            "category":"Professional",
            "subcategory":"Management & Consulting",
            "type":"Services"
        }
    ],
    "sg:phone":"+1   ",
    "sg:postcode":"08859",
    "sg:province":"NJ",
    "sg:tags":[
        "retail",
        "direct",
        "sales"
    ],
    "wof:name":"Richard D Ciavarro",
    "wof:placetype":"venue"
},
  "geometry": {"coordinates":[-74.30844999999999,40.463541],"type":"Point"}
}