{
  "type": "Feature",
  "properties": {
    "iso:country":"US",
    "sg:address":"345 Elbert St",
    "sg:city":"Ramsey",
    "sg:classifiers":[
        {
            "category":"Professional",
            "subcategory":"Management & Consulting",
            "type":"Services"
        }
    ],
    "sg:phone":"+1   ",
    "sg:postcode":"07446",
    "sg:province":"NJ",
    "wof:name":"Acadia Consulting Group Inc",
    "wof:placetype":"venue"
},
  "geometry": {"coordinates":[-74.15039299999999,41.069336],"type":"Point"}
}