{
  "type": "Feature",
  "properties": {
    "addr:full":"22 Leslie Pl Tenafly NJ 07670",
    "addr:housenumber":"22",
    "addr:postcode":"07670",
    "addr:street":"Leslie Pl",
    "iso:country":"US",
    "sg:address":"22 Leslie Pl",
    "sg:city":"Tenafly",
    "sg:classifiers":[
        {
            "category":"Manufacturing",
            "subcategory":"Textiles",
            "type":"Manufacturing & Wholesale Goods"
        }
    ],
    "sg:phone":"+1 201 569 2914",
    "sg:postcode":"07670",
    "sg:province":"NJ",
    "sg:tags":[
        "mfg"
    ],
    "wof:name":"Barrington Textiles",
    "wof:placetype":"venue"
},
  "geometry": {"coordinates":[-73.95216499999999,40.922324],"type":"Point"}
}