{
  "type": "Feature",
  "properties": {
    "iso:country":"US",
    "sg:address":"22 E Quackenbush Ave",
    "sg:city":"Dumont",
    "sg:classifiers":[
        {
            "category":"Banks & Credit Unions",
            "subcategory":"Bank",
            "type":"Services"
        }
    ],
    "sg:phone":"+1   ",
    "sg:postcode":"07628",
    "sg:province":"NJ",
    "sg:tags":[
        "state",
        "commercial"
    ],
    "wof:name":"River Edge News",
    "wof:placetype":"venue"
},
  "geometry": {"coordinates":[-73.99350099999999,40.938587],"type":"Point"}
}