{
  "type": "Feature",
  "properties": {
    "iso:country":"US",
    "sg:address":"1 Reuten Dr",
    "sg:city":"Closter",
    "sg:classifiers":[
        {
            "category":"Shopping",
            "subcategory":"Clothing, Apparel, & Fashions",
            "type":"Retail Goods"
        }
    ],
    "sg:phone":"+1 201 767 2088",
    "sg:postcode":"07624",
    "sg:province":"NJ",
    "sg:tags":[
        "lingerie"
    ],
    "wof:name":"Eight & Eight Intl Inc",
    "wof:placetype":"venue"
},
  "geometry": {"coordinates":[-73.957897,40.975756],"type":"Point"}
}