{
  "type": "Feature",
  "properties": {
    "iso:country":"US",
    "sg:address":"1820 Marlton Pike",
    "sg:city":"Cherry Hill",
    "sg:classifiers":[
        {
            "category":"Autos & Motor Vehicles",
            "subcategory":"Fuel & Gas Station",
            "type":"Retail Goods"
        },
        {
            "category":"Retail",
            "subcategory":"Auto Repair",
            "type":"Services"
        }
    ],
    "sg:phone":"+1 856 665 7057",
    "sg:postcode":"08002",
    "sg:province":"NJ",
    "sg:tags":[
        "automotive",
        "oil",
        "general"
    ],
    "wof:name":"Sunoco Auto Care",
    "wof:placetype":"venue"
},
  "geometry": {"coordinates":[-75.03332,39.919101],"type":"Point"}
}