{
  "type": "Feature",
  "properties": {
    "addr:full":"2911 State Rte 88 Point Pleasant Beach NJ 08742",
    "addr:housenumber":"2911",
    "addr:postcode":"08742",
    "addr:street":"State Rte 88",
    "iso:country":"US",
    "sg:address":"2911 State Rte 88",
    "sg:city":"Point Pleasant Beach",
    "sg:classifiers":[
        {
            "category":"Health Services",
            "subcategory":"Doctor",
            "type":"Services"
        }
    ],
    "sg:phone":"+1 732 295 2337",
    "sg:postcode":"08742",
    "sg:province":"NJ",
    "sg:tags":[
        "medical"
    ],
    "wof:name":"Sure Health Group Inc",
    "wof:placetype":"venue"
},
  "geometry": {"coordinates":[-74.07979899999999,40.081089],"type":"Point"}
}