{
  "type": "Feature",
  "properties": {
    "iso:country":"US",
    "sg:address":"24 Spruce Run Rd",
    "sg:city":"Clinton",
    "sg:classifiers":[
        {
            "category":"Real Estate",
            "subcategory":"Architect",
            "type":"Services"
        }
    ],
    "sg:phone":"+1 908 735 2323",
    "sg:postcode":"08809",
    "sg:province":"NJ",
    "wof:name":"Alexander T Polaski",
    "wof:placetype":"venue"
},
  "geometry": {"coordinates":[-74.916714,40.637277],"type":"Point"}
}