{
  "type": "Feature",
  "properties": {
    "iso:country":"US",
    "sg:address":"198 Spring Hill Rd",
    "sg:city":"Skillman",
    "sg:classifiers":[
        {
            "category":"Professional",
            "subcategory":"Art Services",
            "type":"Services"
        }
    ],
    "sg:phone":"+1 609 466 4724",
    "sg:postcode":"08558",
    "sg:province":"NJ",
    "sg:tags":[
        "commercial",
        "design"
    ],
    "wof:name":"Mistretta Design Group LLC",
    "wof:placetype":"venue"
},
  "geometry": {"coordinates":[-74.73536199999999,40.414509],"type":"Point"}
}