{
  "type": "Feature",
  "properties": {
    "iso:country":"US",
    "sg:address":"4 Courtney Dr",
    "sg:city":"Princeton Junction",
    "sg:classifiers":[
        {
            "category":"Professional",
            "subcategory":"Management & Consulting",
            "type":"Services"
        }
    ],
    "sg:phone":"+1 609 275 1303",
    "sg:postcode":"08550",
    "sg:province":"NJ",
    "sg:tags":[
        "public",
        "relations"
    ],
    "wof:name":"Hs Marketing LLC",
    "wof:placetype":"venue"
},
  "geometry": {"coordinates":[-74.63069400000001,40.306379],"type":"Point"}
}