{
  "type": "Feature",
  "properties": {
    "iso:country":"US",
    "sg:address":"321 Hamburg Tpke",
    "sg:city":"Wayne",
    "sg:classifiers":[
        {
            "category":"Building & Trades",
            "subcategory":"Construction",
            "type":"Services"
        }
    ],
    "sg:phone":"+1 973 942 4500",
    "sg:postcode":"07470",
    "sg:province":"NJ",
    "sg:tags":[
        "contractor",
        "commercial",
        "general"
    ],
    "wof:name":"Benard Associates Inc",
    "wof:placetype":"venue"
},
  "geometry": {"coordinates":[-74.206943,40.947872],"type":"Point"}
}