{
  "type": "Feature",
  "properties": {
    "addr:full":"2995 US Hwy 1 Trenton NJ 08648",
    "addr:housenumber":"2995",
    "addr:postcode":"08648",
    "addr:street":"Us Hwy 1",
    "iso:country":"US",
    "sg:address":"2995 US Hwy 1",
    "sg:city":"Trenton",
    "sg:classifiers":[
        {
            "category":"Travel",
            "subcategory":"Hotels & Motels",
            "type":"Entertainment"
        }
    ],
    "sg:phone":"+1 609 896 1100",
    "sg:postcode":"08648",
    "sg:province":"NJ",
    "sg:website":"www.hojo.com",
    "wof:name":"Howard Johnson",
    "wof:placetype":"venue"
},
  "geometry": {"coordinates":[-74.7024,40.278152],"type":"Point"}
}