{
  "type": "Feature",
  "properties": {
    "iso:country":"US",
    "sg:address":"1455 Ferry Ave",
    "sg:city":"Camden",
    "sg:classifiers":[
        {
            "category":"Retail",
            "subcategory":"Auto Repair",
            "type":"Services"
        }
    ],
    "sg:phone":"+1 856 963 0060",
    "sg:postcode":"08104",
    "sg:province":"NJ",
    "sg:tags":[
        "general",
        "truck",
        "supply"
    ],
    "wof:name":"Jock's Truck Repair",
    "wof:placetype":"venue"
},
  "geometry": {"coordinates":[-75.123631,39.925438],"type":"Point"}
}