{
  "type": "Feature",
  "properties": {
    "iso:country":"US",
    "sg:address":"239 New Rd Ste B208",
    "sg:city":"Parsippany",
    "sg:classifiers":[
        {
            "category":"Real Estate",
            "subcategory":"Architect",
            "type":"Services"
        }
    ],
    "sg:phone":"+1 973 396 2698",
    "sg:postcode":"07054",
    "sg:province":"NJ",
    "wof:name":"Pci",
    "wof:placetype":"venue"
},
  "geometry": {"coordinates":[-74.347857,40.852512],"type":"Point"}
}