{
  "type": "Feature",
  "properties": {
    "addr:full":"270 Davidson Ave Somerset NJ 08873",
    "addr:housenumber":"270",
    "addr:postcode":"08873",
    "addr:street":"Davidson Ave",
    "iso:country":"US",
    "sg:address":"270 Davidson Ave",
    "sg:city":"Somerset",
    "sg:classifiers":[
        {
            "category":"Wholesale",
            "subcategory":"Electrical",
            "type":"Manufacturing & Wholesale Goods"
        }
    ],
    "sg:phone":"+1 732 563 0632",
    "sg:postcode":"08873",
    "sg:province":"NJ",
    "sg:tags":[
        "communication",
        "radio",
        "system"
    ],
    "sg:website":"www.macom.com",
    "wof:name":"M/A-Com Inc",
    "wof:placetype":"venue"
},
  "geometry": {"coordinates":[-74.527371,40.533721],"type":"Point"}
}