{
  "type": "Feature",
  "properties": {
    "addr:full":"295 Travers Pl Lyndhurst NJ 07071",
    "addr:housenumber":"295",
    "addr:postcode":"07071",
    "addr:street":"Travers Pl",
    "iso:country":"US",
    "sg:address":"295 Travers Pl",
    "sg:city":"Lyndhurst",
    "sg:classifiers":[
        {
            "category":"Organizations",
            "subcategory":"Religious Organization",
            "type":"Services"
        }
    ],
    "sg:phone":"+1 201 939 2134",
    "sg:postcode":"07071",
    "sg:province":"NJ",
    "sg:tags":[
        "church"
    ],
    "wof:name":"St Matthew's Lutheran Church",
    "wof:placetype":"venue"
},
  "geometry": {"coordinates":[-74.127072,40.815348],"type":"Point"}
}