{
  "type": "Feature",
  "properties": {
    "iso:country":"US",
    "sg:address":"18 Morris Ave",
    "sg:city":"Springfield",
    "sg:classifiers":[
        {
            "category":"Real Estate",
            "subcategory":"Real Estate Agent",
            "type":"Services"
        }
    ],
    "sg:phone":"+1   ",
    "sg:postcode":"07081",
    "sg:province":"NJ",
    "wof:name":"Executive Appraisals",
    "wof:placetype":"venue"
},
  "geometry": {"coordinates":[-74.326742,40.717527],"type":"Point"}
}