{
  "type": "Feature",
  "properties": {
    "addr:full":"90 Franklin St Englewood NJ 07631",
    "addr:housenumber":"90",
    "addr:postcode":"07631",
    "addr:street":"Franklin St",
    "iso:country":"US",
    "sg:address":"90 Franklin St",
    "sg:city":"Englewood",
    "sg:classifiers":[
        {
            "category":"Building & Trades",
            "subcategory":"Construction",
            "type":"Services"
        }
    ],
    "sg:phone":"+1 201 871 3559",
    "sg:postcode":"07631",
    "sg:province":"NJ",
    "sg:tags":[
        "planning",
        "remodeling",
        "kitchen"
    ],
    "wof:name":"Quintessence Kitchens Inc",
    "wof:placetype":"venue"
},
  "geometry": {"coordinates":[-73.97613,40.888277],"type":"Point"}
}