{
  "type": "Feature",
  "properties": {
    "iso:country":"US",
    "sg:address":"257 Lyons Ave",
    "sg:city":"Newark",
    "sg:classifiers":[
        {
            "category":"Food & Beverages",
            "subcategory":"Liquor & Beverages",
            "type":"Retail Goods"
        }
    ],
    "sg:phone":"+1 973 923 5504",
    "sg:postcode":"07112",
    "sg:province":"NJ",
    "wof:name":"Cash Service Distributors Inc",
    "wof:placetype":"venue"
},
  "geometry": {"coordinates":[-74.216097,40.711362],"type":"Point"}
}