{
  "type": "Feature",
  "properties": {
    "addr:full":"726 Mill Ln Hillsborough NJ 08844",
    "addr:housenumber":"726",
    "addr:postcode":"08844",
    "addr:street":"Mill Ln",
    "iso:country":"US",
    "sg:address":"726 Mill Ln",
    "sg:city":"Hillsborough",
    "sg:classifiers":[
        {
            "category":"Home & Garden",
            "subcategory":"Home Furnishings",
            "type":"Retail Goods"
        }
    ],
    "sg:phone":"+1 908 359 6612",
    "sg:postcode":"08844",
    "sg:province":"NJ",
    "sg:tags":[
        "window",
        "treatment"
    ],
    "wof:name":"Dynamic Concepts",
    "wof:placetype":"venue"
},
  "geometry": {"coordinates":[-74.69907000000001,40.505902],"type":"Point"}
}