{
  "type": "Feature",
  "properties": {
    "iso:country":"US",
    "sg:address":"3 Marshall St",
    "sg:city":"Irvington",
    "sg:classifiers":[
        {
            "category":"Retail",
            "subcategory":"Auto Rental",
            "type":"Services"
        }
    ],
    "sg:phone":"+1 973 399 5931",
    "sg:postcode":"07111",
    "sg:province":"NJ",
    "sg:tags":[
        "truck"
    ],
    "wof:name":"Road Ranger Truck Leasing",
    "wof:placetype":"venue"
},
  "geometry": {"coordinates":[-74.22234899999999,40.72922],"type":"Point"}
}