{
  "type": "Feature",
  "properties": {
    "addr:full":"682 Garfield Ave Jersey City NJ 07305",
    "addr:housenumber":"682",
    "addr:postcode":"07305",
    "addr:street":"Garfield Ave",
    "iso:country":"US",
    "sg:address":"682 Garfield Ave",
    "sg:city":"Jersey City",
    "sg:classifiers":[
        {
            "category":"Autos & Motor Vehicles",
            "subcategory":"Automobile Sales",
            "type":"Retail Goods"
        }
    ],
    "sg:phone":"+1 201 433 6637",
    "sg:postcode":"07305",
    "sg:province":"NJ",
    "sg:tags":[
        "used",
        "truck"
    ],
    "wof:name":"Ryder",
    "wof:placetype":"venue"
},
  "geometry": {"coordinates":[-74.075639,40.70372],"type":"Point"}
}