{
  "type": "Feature",
  "properties": {
    "addr:full":"13 S Orange Ave South Orange NJ 07079",
    "addr:housenumber":"13",
    "addr:postcode":"07079",
    "addr:street":"S Orange Ave",
    "iso:country":"US",
    "sg:address":"13 S Orange Ave",
    "sg:city":"South Orange",
    "sg:classifiers":[
        {
            "category":"Cinema",
            "subcategory":"Movie Rental",
            "type":"Entertainment"
        }
    ],
    "sg:phone":"+1 973 762 3627",
    "sg:postcode":"07079",
    "sg:province":"NJ",
    "sg:tags":[
        "leasing",
        "video",
        "disc",
        "tape"
    ],
    "wof:name":"We Got Movies",
    "wof:placetype":"venue"
},
  "geometry": {"coordinates":[-74.25986899999999,40.74642],"type":"Point"}
}