{
  "type": "Feature",
  "properties": {
    "iso:country":"US",
    "sg:address":"76 Walnut St W",
    "sg:city":"Mahwah",
    "sg:classifiers":[
        {
            "category":"Wholesale",
            "subcategory":"Painting Supplies",
            "type":"Manufacturing & Wholesale Goods"
        },
        {
            "category":"Retail",
            "subcategory":"Car Wash",
            "type":"Services"
        },
        {
            "category":"Professional",
            "subcategory":"Art Services",
            "type":"Services"
        },
        {
            "category":"Building & Trades",
            "subcategory":"Construction",
            "type":"Services"
        }
    ],
    "sg:phone":"+1 201 652 8989",
    "sg:postcode":"07430",
    "sg:province":"NJ",
    "sg:tags":[
        "washing",
        "pressure",
        "wall",
        "coating",
        "contractor",
        "equipment",
        "faux",
        "finishing",
        "drywall"
    ],
    "sg:website":"http://www.garyvalentinepainting.com",
    "wof:name":"Gary Valentine Painting and Powerwashing",
    "wof:placetype":"venue"
},
  "geometry": {"coordinates":[-74.15997299999999,41.033699],"type":"Point"}
}