{
  "type": "Feature",
  "properties": {
    "addr:full":"949 Central Ave Plainfield NJ 07060",
    "addr:housenumber":"949",
    "addr:postcode":"07060",
    "addr:street":"Central Ave",
    "iso:country":"US",
    "sg:address":"949 Central Ave",
    "sg:city":"Plainfield",
    "sg:classifiers":[
        {
            "category":"Shopping",
            "subcategory":"Clothing, Apparel, & Fashions",
            "type":"Retail Goods"
        }
    ],
    "sg:phone":"+1 908 226 8878",
    "sg:postcode":"07060",
    "sg:province":"NJ",
    "sg:tags":[
        "lingerie"
    ],
    "wof:name":"Fashion Cuisine LLC",
    "wof:placetype":"venue"
},
  "geometry": {"coordinates":[-74.417008,40.610041],"type":"Point"}
}