{
  "type": "Feature",
  "properties": {
    "iso:country":"US",
    "sg:address":"2100 Central Rd",
    "sg:city":"Fort Lee",
    "sg:classifiers":[
        {
            "category":"Professional",
            "subcategory":"Lawyer & Legal Services",
            "type":"Services"
        }
    ],
    "sg:phone":"+1 845 735 1615",
    "sg:postcode":"07024",
    "sg:province":"NJ",
    "sg:tags":[
        "attorney"
    ],
    "wof:name":"Jordan B Delflora",
    "wof:placetype":"venue"
},
  "geometry": {"coordinates":[-73.965283,40.852686],"type":"Point"}
}