{
  "type": "Feature",
  "properties": {
    "iso:country":"US",
    "sg:address":"150 Commerce Rd",
    "sg:city":"Carlstadt",
    "sg:classifiers":[
        {
            "category":"Professional",
            "type":"Services"
        }
    ],
    "sg:phone":"+1 201 372 3160",
    "sg:postcode":"07072",
    "sg:province":"NJ",
    "sg:tags":[
        "establishment"
    ],
    "wof:name":"LGHAI",
    "wof:placetype":"venue"
},
  "geometry": {"coordinates":[-74.05901,40.830013],"type":"Point"}
}