{
  "type": "Feature",
  "properties": {
    "addr:full":"Mount Hebron Rd Montclair NJ 07043",
    "addr:postcode":"07043",
    "addr:street":"Mount Hebron Rd",
    "iso:country":"US",
    "sg:address":"Mount Hebron Rd",
    "sg:city":"Montclair",
    "sg:classifiers":[
        {
            "category":"Retail",
            "subcategory":"Funeral Services",
            "type":"Services"
        }
    ],
    "sg:phone":"+1 973 744 5939",
    "sg:postcode":"07043",
    "sg:province":"NJ",
    "sg:tags":[
        "cemetery"
    ],
    "wof:name":"Immaculate Conception Cemetery",
    "wof:placetype":"venue"
},
  "geometry": {"coordinates":[-74.20349899999999,40.842999],"type":"Point"}
}