{
  "type": "Feature",
  "properties": {
    "iso:country":"US",
    "sg:address":"13 Watts Ave",
    "sg:city":"Burlington",
    "sg:classifiers":[
        {
            "category":"Retail",
            "subcategory":"Repair Shop",
            "type":"Services"
        }
    ],
    "sg:phone":"+1 609 239 0235",
    "sg:postcode":"08016",
    "sg:province":"NJ",
    "sg:tags":[
        "air",
        "heating",
        "conditioning"
    ],
    "wof:name":"B & L Svc Corp",
    "wof:placetype":"venue"
},
  "geometry": {"coordinates":[-74.821896,40.091612],"type":"Point"}
}