{
  "type": "Feature",
  "properties": {
    "iso:country":"US",
    "sg:address":"254 Easton Ave",
    "sg:city":"New Brunswick",
    "sg:classifiers":[
        {
            "category":"Health Services",
            "subcategory":"Doctor",
            "type":"Services"
        }
    ],
    "sg:phone":"+1   ",
    "sg:postcode":"08901",
    "sg:province":"NJ",
    "sg:tags":[
        "medical"
    ],
    "wof:name":"Bukhari Amar MD",
    "wof:placetype":"venue"
},
  "geometry": {"coordinates":[-74.46249,40.503127],"type":"Point"}
}