{
  "type": "Feature",
  "properties": {
    "addr:full":"1 Garden State Plz Paramus NJ 07652",
    "addr:housenumber":"1",
    "addr:postcode":"07652",
    "addr:street":"Garden State Plz",
    "iso:country":"US",
    "sg:address":"1 Garden State Plz",
    "sg:city":"Paramus",
    "sg:classifiers":[
        {
            "category":"Restaurant",
            "type":"Food & Drink"
        }
    ],
    "sg:phone":"+1 201 291 1700",
    "sg:postcode":"07652",
    "sg:province":"NJ",
    "wof:name":"Johnny Rockets",
    "wof:placetype":"venue"
},
  "geometry": {"coordinates":[-74.073868,40.915751],"type":"Point"}
}