{
  "type": "Feature",
  "properties": {
    "addr:full":"69 Broad St Red Bank NJ 07701",
    "addr:housenumber":"69",
    "addr:postcode":"07701",
    "addr:street":"Broad St",
    "iso:country":"US",
    "sg:address":"69 Broad St",
    "sg:city":"Red Bank",
    "sg:classifiers":[
        {
            "category":"Professional",
            "subcategory":"Lawyer & Legal Services",
            "type":"Services"
        }
    ],
    "sg:phone":"+1 732 530 8000",
    "sg:postcode":"07701",
    "sg:province":"NJ",
    "sg:tags":[
        "attorney"
    ],
    "wof:name":"Brian Duncan PC",
    "wof:placetype":"venue"
},
  "geometry": {"coordinates":[-74.065465,40.350572],"type":"Point"}
}