{
  "type": "Feature",
  "properties": {
    "iso:country":"US",
    "sg:address":"9 Morrell St",
    "sg:city":"Elizabeth",
    "sg:classifiers":[
        {
            "category":"Social Services",
            "type":"Services"
        }
    ],
    "sg:phone":"+1 908 353 3708",
    "sg:postcode":"07201",
    "sg:province":"NJ",
    "wof:name":"Procuba Social Club",
    "wof:placetype":"venue"
},
  "geometry": {"coordinates":[-74.209552,40.663447],"type":"Point"}
}