{
  "type": "Feature",
  "properties": {
    "iso:country":"US",
    "sg:address":"9 Broad St",
    "sg:city":"Elizabeth",
    "sg:classifiers":[
        {
            "category":"Health Services",
            "subcategory":"Optometrist",
            "type":"Services"
        }
    ],
    "sg:phone":"+1   ",
    "sg:postcode":"07201",
    "sg:province":"NJ",
    "wof:name":"Dennis Bruder OD",
    "wof:placetype":"venue"
},
  "geometry": {"coordinates":[-74.2149,40.662794],"type":"Point"}
}