{
  "type": "Feature",
  "properties": {
    "iso:country":"US",
    "sg:address":"416 Amherst Rd",
    "sg:city":"Audubon",
    "sg:classifiers":[
        {
            "category":"Social Services",
            "subcategory":"Child Care",
            "type":"Services"
        }
    ],
    "sg:phone":"+1 856 546 6042",
    "sg:postcode":"08106",
    "sg:province":"NJ",
    "sg:tags":[
        "foster",
        "agency"
    ],
    "wof:name":"Audubon Group Home",
    "wof:placetype":"venue"
},
  "geometry": {"coordinates":[-75.06281,39.891885],"type":"Point"}
}