{
  "type": "Feature",
  "properties": {
    "iso:country":"US",
    "sg:address":"19 Airport Rd",
    "sg:city":"Morristown",
    "sg:classifiers":[
        {
            "category":"Building & Trades",
            "subcategory":"Equipment Rental",
            "type":"Services"
        }
    ],
    "sg:phone":"+1 973 326 1006",
    "sg:postcode":"07960",
    "sg:province":"NJ",
    "sg:tags":[
        "aircraft",
        "leasing",
        "charter"
    ],
    "wof:name":"S L Systems Inc",
    "wof:placetype":"venue"
},
  "geometry": {"coordinates":[-74.428365,40.796216],"type":"Point"}
}