{
  "type": "Feature",
  "properties": {
    "addr:full":"86 Olden St Princeton NJ 08540",
    "addr:housenumber":"86",
    "addr:postcode":"08540",
    "addr:street":"Olden St",
    "iso:country":"US",
    "sg:address":"86 Olden St",
    "sg:city":"Princeton",
    "sg:classifiers":[
        {
            "category":"Organizations",
            "subcategory":"Professional Association",
            "type":"Services"
        }
    ],
    "sg:phone":"+1 609 258 5494",
    "sg:postcode":"08540",
    "sg:province":"NJ",
    "wof:name":"Thrid World",
    "wof:placetype":"venue"
},
  "geometry": {"coordinates":[-74.65157000000001,40.350407],"type":"Point"}
}