{
  "type": "Feature",
  "properties": {
    "iso:country":"US",
    "sg:address":"211 State Rte 73",
    "sg:city":"Marlton",
    "sg:classifiers":[
        {
            "category":"Personal",
            "subcategory":"Beauty Salon",
            "type":"Services"
        }
    ],
    "sg:phone":"+1 856 797 5888",
    "sg:postcode":"08053",
    "sg:province":"NJ",
    "sg:tags":[
        "shop"
    ],
    "wof:name":"Oriental Nails Salon",
    "wof:placetype":"venue"
},
  "geometry": {"coordinates":[-74.924699,39.88923],"type":"Point"}
}