{
  "type": "Feature",
  "properties": {
    "addr:full":"487 Division St Boonton NJ 07005",
    "addr:housenumber":"487",
    "addr:postcode":"07005",
    "addr:street":"Division St",
    "iso:country":"US",
    "sg:address":"487 Division St",
    "sg:city":"Boonton",
    "sg:classifiers":[
        {
            "category":"Shopping",
            "subcategory":"Stationery & Office Supplies",
            "type":"Retail Goods"
        }
    ],
    "sg:phone":"+1 973 334 2525",
    "sg:postcode":"07005",
    "sg:province":"NJ",
    "sg:tags":[
        "stationer"
    ],
    "wof:name":"Sea Wash Intl",
    "wof:placetype":"venue"
},
  "geometry": {"coordinates":[-74.40187,40.907632],"type":"Point"}
}