{
  "type": "Feature",
  "properties": {
    "addr:full":"48 Eden Rock Ln Willingboro NJ 08046",
    "addr:housenumber":"48",
    "addr:postcode":"08046",
    "addr:street":"Eden Rock Ln",
    "iso:country":"US",
    "sg:address":"48 Eden Rock Ln",
    "sg:city":"Willingboro",
    "sg:classifiers":[
        {
            "category":"Professional",
            "subcategory":"Employment Agencies",
            "type":"Services"
        }
    ],
    "sg:phone":"+1 609 871 2165",
    "sg:postcode":"08046",
    "sg:province":"NJ",
    "sg:tags":[
        "executive",
        "placement"
    ],
    "wof:name":"Ingram Recruiting Solutions",
    "wof:placetype":"venue"
},
  "geometry": {"coordinates":[-74.871775,40.019003],"type":"Point"}
}