{
  "type": "Feature",
  "properties": {
    "addr:full":"930 Main St Shiloh NJ 08302",
    "addr:housenumber":"930",
    "addr:postcode":"08302",
    "addr:street":"Main St",
    "iso:country":"US",
    "sg:address":"930 Main St",
    "sg:city":"Shiloh",
    "sg:classifiers":[
        {
            "category":"Restaurant",
            "type":"Food & Drink"
        }
    ],
    "sg:phone":"+1   ",
    "sg:postcode":"08302",
    "sg:province":"NJ",
    "sg:tags":[
        "eating"
    ],
    "wof:name":"Brian Ale",
    "wof:placetype":"venue"
},
  "geometry": {"coordinates":[-75.298906,39.458464],"type":"Point"}
}