{
  "type": "Feature",
  "properties": {
    "addr:full":"65 Hillside Ave Tenafly NJ 07670",
    "addr:housenumber":"65",
    "addr:postcode":"07670",
    "addr:street":"Hillside Ave",
    "iso:country":"US",
    "sg:address":"65 Hillside Ave",
    "sg:city":"Tenafly",
    "sg:classifiers":[
        {
            "category":"Real Estate",
            "subcategory":"Architect",
            "type":"Services"
        }
    ],
    "sg:phone":"+1   ",
    "sg:postcode":"07670",
    "sg:province":"NJ",
    "sg:tags":[
        "architectural"
    ],
    "wof:name":"Chris Blake Architect",
    "wof:placetype":"venue"
},
  "geometry": {"coordinates":[-73.959727,40.922517],"type":"Point"}
}