{
  "type": "Feature",
  "properties": {
    "addr:full":"145 Main St Fort Lee NJ 07024",
    "addr:housenumber":"145",
    "addr:postcode":"07024",
    "addr:street":"Main St",
    "iso:country":"US",
    "sg:address":"145 Main St",
    "sg:city":"Fort Lee",
    "sg:classifiers":[
        {
            "category":"Shopping",
            "subcategory":"Used Merchandise",
            "type":"Retail Goods"
        }
    ],
    "sg:phone":"+1 201 585 2882",
    "sg:postcode":"07024",
    "sg:province":"NJ",
    "sg:tags":[
        "shop",
        "consignment"
    ],
    "wof:name":"Boutique Lily",
    "wof:placetype":"venue"
},
  "geometry": {"coordinates":[-73.96767199999999,40.850854],"type":"Point"}
}