{
  "type": "Feature",
  "properties": {
    "iso:country":"US",
    "sg:address":"15 Randall Dr",
    "sg:city":"Manalapan",
    "sg:classifiers":[
        {
            "category":"Shopping",
            "subcategory":"Computers & Home Electronics",
            "type":"Retail Goods"
        }
    ],
    "sg:phone":"+1 732 409 5490",
    "sg:postcode":"07726",
    "sg:province":"NJ",
    "sg:tags":[
        "software"
    ],
    "wof:name":"Corporate Software Solutions",
    "wof:placetype":"venue"
},
  "geometry": {"coordinates":[-74.356157,40.21689],"type":"Point"}
}