{
  "type": "Feature",
  "properties": {
    "addr:full":"72 Hanover Rd East Hanover NJ 07936",
    "addr:housenumber":"72",
    "addr:postcode":"07936",
    "addr:street":"Hanover Rd",
    "iso:country":"US",
    "sg:address":"72 Hanover Rd",
    "sg:city":"East Hanover",
    "sg:classifiers":[
        {
            "category":"Restaurant",
            "type":"Food & Drink"
        }
    ],
    "sg:phone":"+1   ",
    "sg:postcode":"07936",
    "sg:province":"NJ",
    "sg:tags":[
        "eating"
    ],
    "wof:name":"Seasons Cafe",
    "wof:placetype":"venue"
},
  "geometry": {"coordinates":[-74.37426499999999,40.796347],"type":"Point"}
}