{
  "type": "Feature",
  "properties": {
    "addr:full":"7 Cliff Rd Wayne NJ 07470",
    "addr:housenumber":"7",
    "addr:postcode":"07470",
    "addr:street":"Cliff Rd",
    "iso:country":"US",
    "sg:address":"7 Cliff Rd",
    "sg:city":"Wayne",
    "sg:classifiers":[
        {
            "category":"Food & Beverages",
            "subcategory":"Dairy",
            "type":"Retail Goods"
        }
    ],
    "sg:phone":"+1 973 835 6440",
    "sg:postcode":"07470",
    "sg:province":"NJ",
    "sg:tags":[
        "cheese"
    ],
    "wof:name":"Churny Co",
    "wof:placetype":"venue"
},
  "geometry": {"coordinates":[-74.272458,40.987159],"type":"Point"}
}