{
  "type": "Feature",
  "properties": {
    "addr:full":"2615 Westfield Ave Camden NJ 08105",
    "addr:housenumber":"2615",
    "addr:postcode":"08105",
    "addr:street":"Westfield Ave",
    "iso:country":"US",
    "sg:address":"2615 Westfield Ave",
    "sg:city":"Camden",
    "sg:classifiers":[
        {
            "category":"Professional",
            "type":"Services"
        }
    ],
    "sg:phone":"+1 856 541 7300",
    "sg:postcode":"08105",
    "sg:province":"NJ",
    "sg:tags":[
        "establishment"
    ],
    "wof:name":"Megaboy Records",
    "wof:placetype":"venue"
},
  "geometry": {"coordinates":[-75.088356,39.946383],"type":"Point"}
}