{
  "type": "Feature",
  "properties": {
    "addr:full":"22 Carrie Ct Nutley NJ 07110",
    "addr:housenumber":"22",
    "addr:postcode":"07110",
    "addr:street":"Carrie Ct",
    "iso:country":"US",
    "sg:address":"22 Carrie Ct",
    "sg:city":"Nutley",
    "sg:classifiers":[
        {
            "category":"Retail",
            "subcategory":"Car Wash",
            "type":"Services"
        }
    ],
    "sg:phone":"+1 973 667 2249",
    "sg:postcode":"07110",
    "sg:province":"NJ",
    "sg:tags":[
        "carwash"
    ],
    "wof:name":"USA Painting & Power Wash",
    "wof:placetype":"venue"
},
  "geometry": {"coordinates":[-74.177025,40.811762],"type":"Point"}
}