{
  "type": "Feature",
  "properties": {
    "addr:full":"139 Sunset Ave Butler NJ 07405",
    "addr:housenumber":"139",
    "addr:postcode":"07405",
    "addr:street":"Sunset Ave",
    "iso:country":"US",
    "sg:address":"139 Sunset Ave",
    "sg:city":"Butler",
    "sg:classifiers":[
        {
            "category":"Building & Trades",
            "subcategory":"Construction",
            "type":"Services"
        }
    ],
    "sg:phone":"+1 973 492 7323",
    "sg:postcode":"07405",
    "sg:province":"NJ",
    "sg:tags":[
        "house"
    ],
    "wof:name":"Sunset Remodeling Inc",
    "wof:placetype":"venue"
},
  "geometry": {"coordinates":[-74.357668,41.008452],"type":"Point"}
}