{
  "type": "Feature",
  "properties": {
    "addr:full":"2025 Hamburg Tpke Ste H Wayne NJ 07470",
    "addr:housenumber":"2025",
    "addr:postcode":"07470",
    "addr:street":"Hamburg Tpke Ste H",
    "iso:country":"US",
    "sg:address":"2025 Hamburg Tpke Ste H",
    "sg:city":"Wayne",
    "sg:classifiers":[
        {
            "category":"Health Services",
            "subcategory":"Doctor",
            "type":"Services"
        }
    ],
    "sg:phone":"+1 973 831 0122",
    "sg:postcode":"07470",
    "sg:province":"NJ",
    "wof:name":"Macek Deanna Z MD",
    "wof:placetype":"venue"
},
  "geometry": {"coordinates":[-74.26979799999999,40.976101],"type":"Point"}
}