{
  "type": "Feature",
  "properties": {
    "iso:country":"US",
    "sg:address":"117 Chestnut St",
    "sg:city":"Roselle",
    "sg:classifiers":[
        {
            "category":"Education",
            "subcategory":"Dance Studio",
            "type":"Public Place"
        }
    ],
    "sg:phone":"+1 908 688 7224",
    "sg:postcode":"07203",
    "sg:province":"NJ",
    "sg:tags":[
        "instruction",
        "dancing"
    ],
    "wof:name":"Michelle Oxendine Dance Studio",
    "wof:placetype":"venue"
},
  "geometry": {"coordinates":[-74.263255,40.659052],"type":"Point"}
}