{
  "type": "Feature",
  "properties": {
    "addr:full":"400 9th St Hoboken NJ 07030",
    "addr:housenumber":"400",
    "addr:postcode":"07030",
    "addr:street":"9Th St",
    "iso:country":"US",
    "sg:address":"400 9th St",
    "sg:city":"Hoboken",
    "sg:classifiers":[
        {
            "category":"Communications",
            "subcategory":"Film & Video Production",
            "type":"Services"
        }
    ],
    "sg:phone":"+1   ",
    "sg:postcode":"07030",
    "sg:province":"NJ",
    "sg:tags":[
        "motion"
    ],
    "wof:name":"Tnplh Productions LLC",
    "wof:placetype":"venue"
},
  "geometry": {"coordinates":[-74.03430299999999,40.748419],"type":"Point"}
}