{
  "type": "Feature",
  "properties": {
    "addr:full":"1021 US Hwy 1 Edison NJ 08817",
    "addr:housenumber":"1021",
    "addr:postcode":"08817",
    "addr:street":"Us Hwy 1",
    "iso:country":"US",
    "sg:address":"1021 US Hwy 1",
    "sg:city":"Edison",
    "sg:classifiers":[
        {
            "category":"Restaurant",
            "type":"Food & Drink"
        }
    ],
    "sg:phone":"+1 732 602 8863",
    "sg:postcode":"08817",
    "sg:province":"NJ",
    "sg:website":"www.19restaurant.com",
    "wof:name":"I-9 Seafood Plaza Restaurant",
    "wof:placetype":"venue"
},
  "geometry": {"coordinates":[-74.364622,40.520504],"type":"Point"}
}