{
  "type": "Feature",
  "properties": {
    "addr:full":"321 S 9th St Newark NJ 07103",
    "addr:housenumber":"321",
    "addr:postcode":"07103",
    "addr:street":"S 9Th St",
    "iso:country":"US",
    "sg:address":"321 S 9th St",
    "sg:city":"Newark",
    "sg:classifiers":[
        {
            "category":"Personal",
            "subcategory":"Nail Salon",
            "type":"Services"
        }
    ],
    "sg:phone":"+1 973 824 5654",
    "sg:postcode":"07103",
    "sg:province":"NJ",
    "wof:name":"T & T Nail Salon",
    "wof:placetype":"venue"
},
  "geometry": {"coordinates":[-74.199744,40.740616],"type":"Point"}
}