{
  "type": "Feature",
  "properties": {
    "addr:full":"318 Franklin Pl Plainfield NJ 07060",
    "addr:housenumber":"318",
    "addr:postcode":"07060",
    "addr:street":"Franklin Pl",
    "iso:country":"US",
    "sg:address":"318 Franklin Pl",
    "sg:city":"Plainfield",
    "sg:classifiers":[
        {
            "category":"Freight",
            "type":"Transportation"
        }
    ],
    "sg:phone":"+1 908 769 0124",
    "sg:postcode":"07060",
    "sg:province":"NJ",
    "sg:tags":[
        "trucking"
    ],
    "wof:name":"J & F Leasing",
    "wof:placetype":"venue"
},
  "geometry": {"coordinates":[-74.41285499999999,40.618999],"type":"Point"}
}