{
  "type": "Feature",
  "properties": {
    "addr:full":"2000 State Rte 38 Cherry Hill NJ 08002",
    "addr:housenumber":"2000",
    "addr:postcode":"08002",
    "addr:street":"State Rte 38",
    "iso:country":"US",
    "sg:address":"2000 State Rte 38",
    "sg:city":"Cherry Hill",
    "sg:classifiers":[
        {
            "category":"Shopping",
            "subcategory":"Clothing, Apparel, & Fashions",
            "type":"Retail Goods"
        }
    ],
    "sg:phone":"+1   ",
    "sg:postcode":"08002",
    "sg:province":"NJ",
    "wof:name":"Chicos Fas Inc",
    "wof:placetype":"venue"
},
  "geometry": {"coordinates":[-75.027717,39.938711],"type":"Point"}
}