{
  "type": "Feature",
  "properties": {
    "addr:full":"333 Littleton Rd Parsippany NJ 07054",
    "addr:housenumber":"333",
    "addr:postcode":"07054",
    "addr:street":"Littleton Rd",
    "iso:country":"US",
    "sg:address":"333 Littleton Rd",
    "sg:city":"Parsippany",
    "sg:classifiers":[
        {
            "category":"Banks & Credit Unions",
            "subcategory":"Financial Services",
            "type":"Services"
        }
    ],
    "sg:phone":"+1 973 263 2800",
    "sg:postcode":"07054",
    "sg:province":"NJ",
    "sg:tags":[
        "broker",
        "mortgage"
    ],
    "wof:name":"Parsippany Funding",
    "wof:placetype":"venue"
},
  "geometry": {"coordinates":[-74.428254,40.865893],"type":"Point"}
}