{
  "type": "Feature",
  "properties": {
    "iso:country":"US",
    "sg:address":"100 State Rte 36",
    "sg:city":"West Long Branch",
    "sg:classifiers":[
        {
            "category":"Professional",
            "subcategory":"Management & Consulting",
            "type":"Services"
        }
    ],
    "sg:phone":"+1   ",
    "sg:postcode":"07764",
    "sg:province":"NJ",
    "wof:name":"Mommouth Medical Fincl Svcs",
    "wof:placetype":"venue"
},
  "geometry": {"coordinates":[-74.019414,40.301504],"type":"Point"}
}