{
  "type": "Feature",
  "properties": {
    "addr:full":"64 Bernice Dr Freehold NJ 07728",
    "addr:housenumber":"64",
    "addr:postcode":"07728",
    "addr:street":"Bernice Dr",
    "iso:country":"US",
    "sg:address":"64 Bernice Dr",
    "sg:city":"Freehold",
    "sg:classifiers":[
        {
            "category":"Organizations",
            "subcategory":"Religious Organization",
            "type":"Services"
        }
    ],
    "sg:phone":"+1   ",
    "sg:postcode":"07728",
    "sg:province":"NJ",
    "wof:name":"Crayon Rosary",
    "wof:placetype":"venue"
},
  "geometry": {"coordinates":[-74.23048900000001,40.271618],"type":"Point"}
}