{
  "type": "Feature",
  "properties": {
    "addr:full":"214 96th St Stone Harbor NJ 08247",
    "addr:housenumber":"214",
    "addr:postcode":"08247",
    "addr:street":"96Th St",
    "iso:country":"US",
    "sg:address":"214 96th St",
    "sg:city":"Stone Harbor",
    "sg:classifiers":[
        {
            "category":"Shopping",
            "subcategory":"Clothing, Apparel, & Fashions",
            "type":"Retail Goods"
        }
    ],
    "sg:phone":"+1 609 967 5355",
    "sg:postcode":"08247",
    "sg:province":"NJ",
    "sg:tags":[
        "item",
        "boutique"
    ],
    "wof:name":"New Image",
    "wof:placetype":"venue"
},
  "geometry": {"coordinates":[-74.760383,39.054493],"type":"Point"}
}