{
  "type": "Feature",
  "properties": {
    "addr:full":"73 Elizabeth St Basking Ridge NJ 07920",
    "addr:housenumber":"73",
    "addr:postcode":"07920",
    "addr:street":"Elizabeth St",
    "iso:country":"US",
    "sg:address":"73 Elizabeth St",
    "sg:city":"Basking Ridge",
    "sg:classifiers":[
        {
            "category":"Professional",
            "type":"Services"
        }
    ],
    "sg:phone":"+1   ",
    "sg:postcode":"07920",
    "sg:province":"NJ",
    "wof:name":"Peter B Hilgedorff",
    "wof:placetype":"venue"
},
  "geometry": {"coordinates":[-74.542204,40.665878],"type":"Point"}
}