{
  "type": "Feature",
  "properties": {
    "addr:full":"9 Bradley Ct Hewitt NJ 07421",
    "addr:housenumber":"9",
    "addr:postcode":"07421",
    "addr:street":"Bradley Ct",
    "iso:country":"US",
    "sg:address":"9 Bradley Ct",
    "sg:city":"Hewitt",
    "sg:classifiers":[
        {
            "category":"Home & Garden",
            "subcategory":"Furniture",
            "type":"Retail Goods"
        }
    ],
    "sg:phone":"+1 973 853 4604",
    "sg:postcode":"07421",
    "sg:province":"NJ",
    "sg:tags":[
        "top",
        "counter"
    ],
    "wof:name":"Countertops Inc",
    "wof:placetype":"venue"
},
  "geometry": {"coordinates":[-74.356595,41.190366],"type":"Point"}
}