{
  "type": "Feature",
  "properties": {
    "addr:full":"838 River Ave Lakewood NJ 08701",
    "addr:housenumber":"838",
    "addr:postcode":"08701",
    "addr:street":"River Ave",
    "iso:country":"US",
    "sg:address":"838 River Ave",
    "sg:city":"Lakewood",
    "sg:classifiers":[
        {
            "category":"Health Services",
            "subcategory":"Doctor",
            "type":"Services"
        }
    ],
    "sg:phone":"+1 732 363 4477",
    "sg:postcode":"08701",
    "sg:province":"NJ",
    "sg:tags":[
        "dentist"
    ],
    "sg:website":"www.smilenj.com",
    "wof:name":"Oleske Family Dental",
    "wof:placetype":"venue"
},
  "geometry": {"coordinates":[-74.218344,40.069058],"type":"Point"}
}