{
  "type": "Feature",
  "properties": {
    "addr:full":"2 Madison St Belleville NJ 07109",
    "addr:housenumber":"2",
    "addr:postcode":"07109",
    "addr:street":"Madison St",
    "iso:country":"US",
    "sg:address":"2 Madison St",
    "sg:city":"Belleville",
    "sg:classifiers":[
        {
            "category":"Manufacturing",
            "subcategory":"Metals",
            "type":"Manufacturing & Wholesale Goods"
        }
    ],
    "sg:phone":"+1 973 751 3447",
    "sg:postcode":"07109",
    "sg:province":"NJ",
    "wof:name":"Dynamic Metal Company",
    "wof:placetype":"venue"
},
  "geometry": {"coordinates":[-74.16455999999999,40.804514],"type":"Point"}
}