{
  "type": "Feature",
  "properties": {
    "addr:full":"239 Sylvan St Rutherford NJ 07070",
    "addr:housenumber":"239",
    "addr:postcode":"07070",
    "addr:street":"Sylvan St",
    "iso:country":"US",
    "sg:address":"239 Sylvan St",
    "sg:city":"Rutherford",
    "sg:classifiers":[
        {
            "category":"Wholesale",
            "subcategory":"Non-durable Goods",
            "type":"Manufacturing & Wholesale Goods"
        }
    ],
    "sg:phone":"+1 201 438 7720",
    "sg:postcode":"07070",
    "sg:province":"NJ",
    "wof:name":"Misung Industrial Inc",
    "wof:placetype":"venue"
},
  "geometry": {"coordinates":[-74.10981099999999,40.818798],"type":"Point"}
}