{
  "type": "Feature",
  "properties": {
    "iso:country":"US",
    "sg:address":"79 Division Ave",
    "sg:city":"Summit",
    "sg:classifiers":[
        {
            "category":"Building & Trades",
            "subcategory":"Construction",
            "type":"Services"
        }
    ],
    "sg:phone":"+1 908 522 0687",
    "sg:postcode":"07901",
    "sg:province":"NJ",
    "sg:tags":[
        "contractor"
    ],
    "wof:name":"Homebrite Cleaning Services",
    "wof:placetype":"venue"
},
  "geometry": {"coordinates":[-74.38426200000001,40.706941],"type":"Point"}
}