{
  "type": "Feature",
  "properties": {
    "addr:full":"2288 Brunswick Ave Trenton NJ 08648",
    "addr:housenumber":"2288",
    "addr:postcode":"08648",
    "addr:street":"Brunswick Ave",
    "iso:country":"US",
    "sg:address":"2288 Brunswick Ave",
    "sg:city":"Trenton",
    "sg:classifiers":[
        {
            "category":"Health Services",
            "subcategory":"Doctor",
            "type":"Services"
        }
    ],
    "sg:phone":"+1   ",
    "sg:postcode":"08648",
    "sg:province":"NJ",
    "wof:name":"Total Dental Care PC",
    "wof:placetype":"venue"
},
  "geometry": {"coordinates":[-74.730673,40.254678],"type":"Point"}
}