{
  "type": "Feature",
  "properties": {
    "iso:country":"US",
    "sg:address":"1263 Stuyvesant Ave",
    "sg:city":"Union",
    "sg:classifiers":[
        {
            "category":"Personal",
            "subcategory":"Beauty Salon",
            "type":"Services"
        }
    ],
    "sg:phone":"+1 908 964 1425",
    "sg:postcode":"07083",
    "sg:province":"NJ",
    "wof:name":"Prime Cut Hair Design",
    "wof:placetype":"venue"
},
  "geometry": {"coordinates":[-74.26525100000001,40.700079],"type":"Point"}
}