{
  "type": "Feature",
  "properties": {
    "addr:full":"731 Georges Rd North Brunswick NJ 08902",
    "addr:housenumber":"731",
    "addr:postcode":"08902",
    "addr:street":"Georges Rd",
    "iso:country":"US",
    "sg:address":"731 Georges Rd",
    "sg:city":"North Brunswick",
    "sg:classifiers":[
        {
            "category":"Professional",
            "subcategory":"Computer Services",
            "type":"Services"
        }
    ],
    "sg:phone":"+1 732 296 0789",
    "sg:postcode":"08902",
    "sg:province":"NJ",
    "sg:tags":[
        "design",
        "system"
    ],
    "wof:name":"Aiko Consulting Inc",
    "wof:placetype":"venue"
},
  "geometry": {"coordinates":[-74.454323,40.46696],"type":"Point"}
}