{
  "type": "Feature",
  "properties": {
    "addr:full":"1107 Mantua Pike Mantua NJ 08051",
    "addr:housenumber":"1107",
    "addr:postcode":"08051",
    "addr:street":"Mantua Pike",
    "iso:country":"US",
    "sg:address":"1107 Mantua Pike",
    "sg:city":"Mantua",
    "sg:classifiers":[
        {
            "category":"Sports & Exercise",
            "subcategory":"Gym",
            "type":"Entertainment"
        }
    ],
    "sg:phone":"+1 856 468 6400",
    "sg:postcode":"08051",
    "sg:province":"NJ",
    "sg:tags":[
        "club",
        "health",
        "studio",
        "gymnasium"
    ],
    "wof:name":"Curves",
    "wof:placetype":"venue"
},
  "geometry": {"coordinates":[-75.169732,39.801243],"type":"Point"}
}