{
  "type": "Feature",
  "properties": {
    "iso:country":"US",
    "sg:address":"1045 Beach Dr",
    "sg:city":"Cape May",
    "sg:classifiers":[
        {
            "category":"Personal",
            "subcategory":"Beauty Salon",
            "type":"Services"
        }
    ],
    "sg:phone":"+1   ",
    "sg:postcode":"08204",
    "sg:province":"NJ",
    "sg:tags":[
        "shop"
    ],
    "wof:name":"Lorraines Hair Salon",
    "wof:placetype":"venue"
},
  "geometry": {"coordinates":[-74.90821,38.932475],"type":"Point"}
}