{
  "type": "Feature",
  "properties": {
    "iso:country":"US",
    "sg:address":"62 Ford St",
    "sg:city":"Wayne",
    "sg:classifiers":[
        {
            "category":"Professional",
            "subcategory":"Business Services",
            "type":"Services"
        }
    ],
    "sg:phone":"+1   ",
    "sg:postcode":"07470",
    "sg:province":"NJ",
    "sg:tags":[
        "garden"
    ],
    "wof:name":"All Terrain Tanks",
    "wof:placetype":"venue"
},
  "geometry": {"coordinates":[-74.28245,40.924484],"type":"Point"}
}