{
  "type": "Feature",
  "properties": {
    "addr:full":"35 Brookvale Rd Butler NJ 07405",
    "addr:housenumber":"35",
    "addr:postcode":"07405",
    "addr:street":"Brookvale Rd",
    "iso:country":"US",
    "sg:address":"35 Brookvale Rd",
    "sg:city":"Butler",
    "sg:classifiers":[
        {
            "category":"Professional",
            "subcategory":"Management & Consulting",
            "type":"Services"
        }
    ],
    "sg:phone":"+1   ",
    "sg:postcode":"07405",
    "sg:province":"NJ",
    "sg:tags":[
        "selling",
        "establishment",
        "direct"
    ],
    "wof:name":"Brigade Games & Hobby Sup LLP",
    "wof:placetype":"venue"
},
  "geometry": {"coordinates":[-74.399259,41.007865],"type":"Point"}
}