{
  "type": "Feature",
  "properties": {
    "addr:full":"31 Washington Ave Tenafly NJ 07670",
    "addr:housenumber":"31",
    "addr:postcode":"07670",
    "addr:street":"Washington Ave",
    "iso:country":"US",
    "sg:address":"31 Washington Ave",
    "sg:city":"Tenafly",
    "sg:classifiers":[
        {
            "category":"Personal",
            "subcategory":"Beauty Salon",
            "type":"Services"
        }
    ],
    "sg:phone":"+1 201 567 8889",
    "sg:postcode":"07670",
    "sg:province":"NJ",
    "sg:tags":[
        "shop"
    ],
    "wof:name":"Nail Spa Of Tenafly",
    "wof:placetype":"venue"
},
  "geometry": {"coordinates":[-73.964761,40.925188],"type":"Point"}
}