{
  "type": "Feature",
  "properties": {
    "addr:full":"4201 Pacific Ave Wildwood NJ 08260",
    "addr:housenumber":"4201",
    "addr:postcode":"08260",
    "addr:street":"Pacific Ave",
    "iso:country":"US",
    "sg:address":"4201 Pacific Ave",
    "sg:city":"Wildwood",
    "sg:classifiers":[
        {
            "category":"Personal",
            "subcategory":"Barber",
            "type":"Services"
        }
    ],
    "sg:phone":"+1 609 522 5529",
    "sg:postcode":"08260",
    "sg:province":"NJ",
    "sg:tags":[
        "shop"
    ],
    "wof:name":"Pete's Barber Shop",
    "wof:placetype":"venue"
},
  "geometry": {"coordinates":[-74.81837299999999,38.986129],"type":"Point"}
}