{
  "type": "Feature",
  "properties": {
    "iso:country":"US",
    "sg:address":"437 Lakehurst Rd",
    "sg:city":"Toms River",
    "sg:classifiers":[
        {
            "category":"Health Services",
            "subcategory":"Doctor",
            "type":"Services"
        }
    ],
    "sg:phone":"+1 732 557 4777",
    "sg:postcode":"08755",
    "sg:province":"NJ",
    "sg:tags":[
        "physician",
        "surgeon"
    ],
    "wof:name":"Dover Cardiology Ctr",
    "wof:placetype":"venue"
},
  "geometry": {"coordinates":[-74.217958,39.960905],"type":"Point"}
}