{
  "type": "Feature",
  "properties": {
    "iso:country":"US",
    "sg:address":"141 W Paul Ave",
    "sg:city":"Trenton",
    "sg:classifiers":[
        {
            "category":"Manufacturing",
            "subcategory":"Tools & Machinery",
            "type":"Manufacturing & Wholesale Goods"
        }
    ],
    "sg:phone":"+1 609 599 1999",
    "sg:postcode":"08638",
    "sg:province":"NJ",
    "sg:tags":[
        "mfg"
    ],
    "wof:name":"Superior Mold & Die Inc",
    "wof:placetype":"venue"
},
  "geometry": {"coordinates":[-74.759311,40.236452],"type":"Point"}
}