{
  "type": "Feature",
  "properties": {
    "addr:full":"2217 Holly Hill Rd Lakehurst NJ 08759",
    "addr:housenumber":"2217",
    "addr:postcode":"08759",
    "addr:street":"Holly Hill Rd",
    "iso:country":"US",
    "sg:address":"2217 Holly Hill Rd",
    "sg:city":"Lakehurst",
    "sg:classifiers":[
        {
            "category":"Shopping",
            "subcategory":"Jewelry",
            "type":"Retail Goods"
        }
    ],
    "sg:phone":"+1   ",
    "sg:postcode":"08759",
    "sg:province":"NJ",
    "wof:name":"All That Glitters Gifts",
    "wof:placetype":"venue"
},
  "geometry": {"coordinates":[-74.26378200000001,40.030459],"type":"Point"}
}