{
  "type": "Feature",
  "properties": {
    "iso:country":"US",
    "sg:address":"162 Old Rd",
    "sg:city":"Old Bridge",
    "sg:classifiers":[
        {
            "category":"Education",
            "subcategory":"Dance Studio",
            "type":"Public Place"
        }
    ],
    "sg:phone":"+1 732 566 6774",
    "sg:postcode":"08831",
    "sg:province":"NJ",
    "sg:tags":[
        "instruction",
        "dancing"
    ],
    "wof:name":"Old Bridge School Of Dance",
    "wof:placetype":"venue"
},
  "geometry": {"coordinates":[-74.434223,40.274477],"type":"Point"}
}