{
  "type": "Feature",
  "properties": {
    "addr:full":"2112 Boardwalk Wildwood NJ 08260",
    "addr:housenumber":"2112",
    "addr:postcode":"08260",
    "addr:street":"Boardwalk",
    "iso:country":"US",
    "sg:address":"2112 Boardwalk",
    "sg:city":"Wildwood",
    "sg:classifiers":[
        {
            "category":"Shopping",
            "subcategory":"Musical Instruments",
            "type":"Retail Goods"
        }
    ],
    "sg:phone":"+1 609 729 9292",
    "sg:postcode":"08260",
    "sg:province":"NJ",
    "sg:tags":[
        "music",
        "dealer"
    ],
    "wof:name":"Spin Music",
    "wof:placetype":"venue"
},
  "geometry": {"coordinates":[-74.80003600000001,38.99195],"type":"Point"}
}