{
  "type": "Feature",
  "properties": {
    "iso:country":"US",
    "sg:address":"1113 Hospital Dr Ste 302",
    "sg:city":"Willingboro",
    "sg:classifiers":[
        {
            "category":"Health Services",
            "subcategory":"Doctor",
            "type":"Services"
        }
    ],
    "sg:phone":"+1 609 871 3366",
    "sg:postcode":"08046",
    "sg:province":"NJ",
    "sg:tags":[
        "throat",
        "surgeon",
        "ear",
        "cosmetic",
        "nose"
    ],
    "wof:name":"Belafsky Robert B MD Facs",
    "wof:placetype":"venue"
},
  "geometry": {"coordinates":[-74.878899,40.045399],"type":"Point"}
}