{
  "type": "Feature",
  "properties": {
    "iso:country":"US",
    "sg:address":"634 Glen Ct",
    "sg:city":"Blackwood",
    "sg:classifiers":[
        {
            "category":"Building & Trades",
            "subcategory":"Landscaping Services",
            "type":"Services"
        }
    ],
    "sg:phone":"+1 856 227 1779",
    "sg:postcode":"08012",
    "sg:province":"NJ",
    "sg:tags":[
        "landscape"
    ],
    "wof:name":"Dileo Landscaping",
    "wof:placetype":"venue"
},
  "geometry": {"coordinates":[-75.06101099999999,39.762651],"type":"Point"}
}