{
  "type": "Feature",
  "properties": {
    "addr:full":"289 Timberline Pl Brick NJ 08723",
    "addr:housenumber":"289",
    "addr:postcode":"08723",
    "addr:street":"Timberline Pl",
    "iso:country":"US",
    "sg:address":"289 Timberline Pl",
    "sg:city":"Brick",
    "sg:classifiers":[
        {
            "category":"Insurance",
            "subcategory":"Insurance Agent",
            "type":"Services"
        }
    ],
    "sg:phone":"+1 732 477 0084",
    "sg:postcode":"08723",
    "sg:province":"NJ",
    "wof:name":"Fireman's Fund Insurance",
    "wof:placetype":"venue"
},
  "geometry": {"coordinates":[-74.157589,40.040965],"type":"Point"}
}