{
  "type": "Feature",
  "properties": {
    "iso:country":"US",
    "sg:address":"232 N Shore Rd",
    "sg:city":"Marmora",
    "sg:classifiers":[
        {
            "category":"Government",
            "subcategory":"Office",
            "type":"Public Place"
        }
    ],
    "sg:phone":"+1 609 390 8303",
    "sg:postcode":"08223",
    "sg:province":"NJ",
    "sg:tags":[
        "federal",
        "program",
        "adm"
    ],
    "wof:name":"US Commerce Dept",
    "wof:placetype":"venue"
},
  "geometry": {"coordinates":[-74.642754,39.271147],"type":"Point"}
}