{
  "type": "Feature",
  "properties": {
    "iso:country":"US",
    "sg:address":"420 Totowa Rd",
    "sg:city":"Totowa",
    "sg:classifiers":[
        {
            "category":"Professional",
            "subcategory":"Lawyer & Legal Services",
            "type":"Services"
        }
    ],
    "sg:phone":"+1 973 790 8400",
    "sg:postcode":"07512",
    "sg:province":"NJ",
    "wof:name":"Marotta James S Attorney",
    "wof:placetype":"venue"
},
  "geometry": {"coordinates":[-74.212502,40.904701],"type":"Point"}
}