{
  "type": "Feature",
  "properties": {
    "iso:country":"US",
    "sg:address":"201 Chambers Brook Rd",
    "sg:city":"Branchburg",
    "sg:classifiers":[
        {
            "category":"Wholesale",
            "subcategory":"Machinery & Supplies",
            "type":"Manufacturing & Wholesale Goods"
        }
    ],
    "sg:phone":"+1 908 252 9350",
    "sg:postcode":"08876",
    "sg:province":"NJ",
    "sg:tags":[
        "equipment",
        "material",
        "industrial",
        "sh",
        "plastic"
    ],
    "wof:name":"Kautex Machines  Inc",
    "wof:placetype":"venue"
},
  "geometry": {"coordinates":[-74.69161699999999,40.596839],"type":"Point"}
}