{
  "type": "Feature",
  "properties": {
    "addr:full":"6 Karen Pl Budd Lake NJ 07828",
    "addr:housenumber":"6",
    "addr:postcode":"07828",
    "addr:street":"Karen Pl",
    "iso:country":"US",
    "sg:address":"6 Karen Pl",
    "sg:city":"Budd Lake",
    "sg:classifiers":[
        {
            "category":"Shopping",
            "type":"Retail Goods"
        }
    ],
    "sg:phone":"+1   ",
    "sg:postcode":"07828",
    "sg:province":"NJ",
    "sg:tags":[
        "merchandise"
    ],
    "wof:name":"Exotic Pet Supply",
    "wof:placetype":"venue"
},
  "geometry": {"coordinates":[-74.77362599999999,40.876392],"type":"Point"}
}