{
  "type": "Feature",
  "properties": {
    "iso:country":"US",
    "sg:address":"4808 Bergenline Ave",
    "sg:city":"Union City",
    "sg:classifiers":[
        {
            "category":"Health Services",
            "subcategory":"Dentist",
            "type":"Services"
        }
    ],
    "sg:phone":"+1 201 863 3344",
    "sg:postcode":"07087",
    "sg:province":"NJ",
    "wof:name":"Levi Jack DDS PA & Associates",
    "wof:placetype":"venue"
},
  "geometry": {"coordinates":[-74.02179700000001,40.7817],"type":"Point"}
}