{
  "type": "Feature",
  "properties": {
    "addr:full":"133 Landing Rd Cape May Court House NJ 08210",
    "addr:housenumber":"133",
    "addr:postcode":"08210",
    "addr:street":"Landing Rd",
    "iso:country":"US",
    "sg:address":"133 Landing Rd",
    "sg:city":"Cape May Court House",
    "sg:classifiers":[
        {
            "category":"Manufacturing",
            "subcategory":"Tools & Machinery",
            "type":"Manufacturing & Wholesale Goods"
        }
    ],
    "sg:phone":"+1 609 624 2630",
    "sg:postcode":"08210",
    "sg:province":"NJ",
    "sg:tags":[
        "manufacture",
        "control",
        "program",
        "design",
        "computer"
    ],
    "wof:name":"Thomas Instrumentation Inc",
    "wof:placetype":"venue"
},
  "geometry": {"coordinates":[-74.75511,39.155001],"type":"Point"}
}