{
  "type": "Feature",
  "properties": {
    "addr:full":"716 W Saint Georges Ave Linden NJ 07036",
    "addr:housenumber":"716",
    "addr:postcode":"07036",
    "addr:street":"W Saint Georges Ave",
    "iso:country":"US",
    "sg:address":"716 W Saint Georges Ave",
    "sg:city":"Linden",
    "sg:classifiers":[
        {
            "category":"Real Estate",
            "subcategory":"Real Estate Services",
            "type":"Services"
        },
        {
            "category":"Real Estate",
            "subcategory":"Real Estate Agent",
            "type":"Services"
        }
    ],
    "sg:phone":"+1 908 925 1400",
    "sg:postcode":"07036",
    "sg:province":"NJ",
    "sg:tags":[
        "buyer",
        "broker"
    ],
    "sg:website":"http://www.century21.com",
    "wof:name":"Vision Realty",
    "wof:placetype":"venue"
},
  "geometry": {"coordinates":[-74.27068300000001,40.629853],"type":"Point"}
}