{
  "type": "Feature",
  "properties": {
    "addr:full":"625 Elm Ave Woodbury Heights NJ 08097",
    "addr:housenumber":"625",
    "addr:postcode":"08097",
    "addr:street":"Elm Ave",
    "iso:country":"US",
    "sg:address":"625 Elm Ave",
    "sg:city":"Woodbury Heights",
    "sg:classifiers":[
        {
            "category":"Insurance",
            "subcategory":"Insurance Agent",
            "type":"Services"
        }
    ],
    "sg:phone":"+1 856 845 0453",
    "sg:postcode":"08097",
    "sg:province":"NJ",
    "wof:name":"Robert C Shunk Insurance",
    "wof:placetype":"venue"
},
  "geometry": {"coordinates":[-75.149996,39.818037],"type":"Point"}
}