{
  "type": "Feature",
  "properties": {
    "iso:country":"US",
    "sg:address":"333 Washington Street, Suite 400",
    "sg:city":"Jersey City",
    "sg:classifiers":[
        {
            "category":"Professional",
            "subcategory":"Computer Services",
            "type":"Services"
        }
    ],
    "sg:phone":"+1 201 938 1000",
    "sg:postcode":"07302",
    "sg:province":"NJ",
    "sg:tags":[
        "telematics",
        "fleet-management",
        "public-transit-systems",
        "avl"
    ],
    "sg:website":"http://www.telargo.com",
    "wof:name":"Telargo Inc.",
    "wof:placetype":"venue"
},
  "geometry": {"coordinates":[-74.03628999999999,40.722863],"type":"Point"}
}