{
  "type": "Feature",
  "properties": {
    "iso:country":"US",
    "sg:address":"512 Green Ave",
    "sg:city":"Brielle",
    "sg:classifiers":[
        {
            "category":"Recreation",
            "subcategory":"Marina",
            "type":"Entertainment"
        }
    ],
    "sg:phone":"+1 732 528 5588",
    "sg:postcode":"08730",
    "sg:province":"NJ",
    "wof:name":"Brielle Anchorage",
    "wof:placetype":"venue"
},
  "geometry": {"coordinates":[-74.049092,40.108197],"type":"Point"}
}