{
  "type": "Feature",
  "properties": {
    "addr:full":"23 E 22nd St Bayonne NJ 07002",
    "addr:housenumber":"23",
    "addr:postcode":"07002",
    "addr:street":"E 22Nd St",
    "iso:country":"US",
    "sg:address":"23 E 22nd St",
    "sg:city":"Bayonne",
    "sg:classifiers":[
        {
            "category":"Organizations",
            "subcategory":"Religious Organization",
            "type":"Services"
        },
        {
            "category":"Education",
            "subcategory":"School",
            "type":"Public Place"
        }
    ],
    "sg:phone":"+1 201 339 1839",
    "sg:postcode":"07002",
    "sg:province":"NJ",
    "sg:website":"www.olmc.bayonne.net",
    "wof:name":"Our Lady of Mt Carmel School",
    "wof:placetype":"venue"
},
  "geometry": {"coordinates":[-74.116736,40.662164],"type":"Point"}
}