{
  "type": "Feature",
  "properties": {
    "addr:full":"1605 Main St Belmar NJ 07719",
    "addr:housenumber":"1605",
    "addr:postcode":"07719",
    "addr:street":"Main St",
    "iso:country":"US",
    "sg:address":"1605 Main St",
    "sg:city":"Belmar",
    "sg:classifiers":[
        {
            "category":"Shopping",
            "subcategory":"Computers & Home Electronics",
            "type":"Retail Goods"
        }
    ],
    "sg:phone":"+1 732 280 2601",
    "sg:postcode":"07719",
    "sg:province":"NJ",
    "sg:tags":[
        "equipment",
        "dealer"
    ],
    "wof:name":"Answers",
    "wof:placetype":"venue"
},
  "geometry": {"coordinates":[-74.027415,40.173509],"type":"Point"}
}