{
  "type": "Feature",
  "properties": {
    "iso:country":"US",
    "sg:address":"213 Northampton Blvd",
    "sg:city":"Toms River",
    "sg:classifiers":[
        {
            "category":"Building & Trades",
            "subcategory":"Plumbing",
            "type":"Services"
        }
    ],
    "sg:phone":"+1 732 797 0114",
    "sg:postcode":"08757",
    "sg:province":"NJ",
    "sg:tags":[
        "plumbing",
        "contractor"
    ],
    "wof:name":"Genuine Plumbing & Heating Co",
    "wof:placetype":"venue"
},
  "geometry": {"coordinates":[-74.266311,39.994436],"type":"Point"}
}