{
  "type": "Feature",
  "properties": {
    "addr:full":"23 Taunton Dr Howell NJ 07731",
    "addr:housenumber":"23",
    "addr:postcode":"07731",
    "addr:street":"Taunton Dr",
    "iso:country":"US",
    "sg:address":"23 Taunton Dr",
    "sg:city":"Howell",
    "sg:classifiers":[
        {
            "category":"Building & Trades",
            "subcategory":"Electrical",
            "type":"Services"
        }
    ],
    "sg:phone":"+1 732 364 0940",
    "sg:postcode":"07731",
    "sg:province":"NJ",
    "sg:tags":[
        "electrical",
        "contractor"
    ],
    "wof:name":"Secon Electric",
    "wof:placetype":"venue"
},
  "geometry": {"coordinates":[-74.21082199999999,40.150757],"type":"Point"}
}