{
  "type": "Feature",
  "properties": {
    "addr:full":"419 Knickerbocker Ave Paterson NJ 07503",
    "addr:housenumber":"419",
    "addr:postcode":"07503",
    "addr:street":"Knickerbocker Ave",
    "iso:country":"US",
    "sg:address":"419 Knickerbocker Ave",
    "sg:city":"Paterson",
    "sg:classifiers":[
        {
            "category":"Health Services",
            "subcategory":"Doctor",
            "type":"Services"
        }
    ],
    "sg:phone":"+1 973 523 8718",
    "sg:postcode":"07503",
    "sg:province":"NJ",
    "sg:tags":[
        "medical"
    ],
    "wof:name":"Linda M Graves MD",
    "wof:placetype":"venue"
},
  "geometry": {"coordinates":[-74.140535,40.893227],"type":"Point"}
}