{
  "type": "Feature",
  "properties": {
    "addr:full":"131 Carteret Ave Jersey City NJ 07305",
    "addr:housenumber":"131",
    "addr:postcode":"07305",
    "addr:street":"Carteret Ave",
    "iso:country":"US",
    "sg:address":"131 Carteret Ave",
    "sg:city":"Jersey City",
    "sg:classifiers":[
        {
            "category":"Food & Beverages",
            "subcategory":"Groceries & Convenience Stores",
            "type":"Retail Goods"
        }
    ],
    "sg:phone":"+1   ",
    "sg:postcode":"07305",
    "sg:province":"NJ",
    "wof:name":"Denia Grocery",
    "wof:placetype":"venue"
},
  "geometry": {"coordinates":[-74.074364,40.709109],"type":"Point"}
}