{
  "type": "Feature",
  "properties": {
    "addr:full":"3114 Willowbrook Mall Wayne NJ 07470",
    "addr:housenumber":"3114",
    "addr:postcode":"07470",
    "addr:street":"Willowbrook Mall",
    "iso:country":"US",
    "sg:address":"3114 Willowbrook Mall",
    "sg:city":"Wayne",
    "sg:classifiers":[
        {
            "category":"Restaurant",
            "type":"Food & Drink"
        }
    ],
    "sg:phone":"+1   ",
    "sg:postcode":"07470",
    "sg:province":"NJ",
    "sg:tags":[
        "eating"
    ],
    "wof:name":"Sandwich Depot",
    "wof:placetype":"venue"
},
  "geometry": {"coordinates":[-74.255191,40.889512],"type":"Point"}
}