{
  "type": "Feature",
  "properties": {
    "iso:country":"US",
    "sg:address":"309 7th St",
    "sg:city":"Jersey City",
    "sg:classifiers":[
        {
            "category":"Arts & Performance",
            "subcategory":"Theater",
            "type":"Entertainment"
        }
    ],
    "sg:phone":"+1 201 420 1333",
    "sg:postcode":"07302",
    "sg:province":"NJ",
    "sg:tags":[
        "musician"
    ],
    "wof:name":"Mac Daddy",
    "wof:placetype":"venue"
},
  "geometry": {"coordinates":[-74.048095,40.726349],"type":"Point"}
}