{
  "type": "Feature",
  "properties": {
    "iso:country":"US",
    "sg:address":"144 N Beverwyck Rd",
    "sg:city":"Lake Hiawatha",
    "sg:classifiers":[
        {
            "category":"Arts & Performance",
            "subcategory":"Theater",
            "type":"Entertainment"
        }
    ],
    "sg:phone":"+1 973 331 0151",
    "sg:postcode":"07034",
    "sg:province":"NJ",
    "sg:tags":[
        "group"
    ],
    "wof:name":"Big Boyz Entertainment",
    "wof:placetype":"venue"
},
  "geometry": {"coordinates":[-74.381608,40.884434],"type":"Point"}
}