{
  "type": "Feature",
  "properties": {
    "addr:full":"434 Aldrich Rd Howell NJ 07731",
    "addr:housenumber":"434",
    "addr:postcode":"07731",
    "addr:street":"Aldrich Rd",
    "iso:country":"US",
    "sg:address":"434 Aldrich Rd",
    "sg:city":"Howell",
    "sg:classifiers":[
        {
            "category":"Social Services",
            "subcategory":"Child Care",
            "type":"Services"
        }
    ],
    "sg:phone":"+1 732 367 2544",
    "sg:postcode":"07731",
    "sg:province":"NJ",
    "sg:tags":[
        "kindergarten",
        "academic",
        "school"
    ],
    "wof:name":"Prince Of Peace Ctr",
    "wof:placetype":"venue"
},
  "geometry": {"coordinates":[-74.227993,40.156064],"type":"Point"}
}