{
  "type": "Feature",
  "properties": {
    "addr:full":"489 Clifton Ave Clifton NJ 07011",
    "addr:housenumber":"489",
    "addr:postcode":"07011",
    "addr:street":"Clifton Ave",
    "iso:country":"US",
    "sg:address":"489 Clifton Ave",
    "sg:city":"Clifton",
    "sg:classifiers":[
        {
            "category":"Freight",
            "type":"Transportation"
        }
    ],
    "sg:phone":"+1 973 340 8524",
    "sg:postcode":"07011",
    "sg:province":"NJ",
    "wof:name":"Tayem Transport Svc",
    "wof:placetype":"venue"
},
  "geometry": {"coordinates":[-74.146782,40.874005],"type":"Point"}
}