{
  "type": "Feature",
  "properties": {
    "iso:country":"US",
    "sg:address":"25 Henry Ave",
    "sg:city":"Park Ridge",
    "sg:classifiers":[
        {
            "category":"Building & Trades",
            "subcategory":"Electrical",
            "type":"Services"
        }
    ],
    "sg:phone":"+1 201 573 1933",
    "sg:postcode":"07656",
    "sg:province":"NJ",
    "sg:tags":[
        "electrical",
        "contractor"
    ],
    "wof:name":"Danny B Electric Inc",
    "wof:placetype":"venue"
},
  "geometry": {"coordinates":[-74.026347,41.036226],"type":"Point"}
}