{
  "type": "Feature",
  "properties": {
    "addr:full":"871 Landis Ave Elmer NJ 08318",
    "addr:housenumber":"871",
    "addr:postcode":"08318",
    "addr:street":"Landis Ave",
    "iso:country":"US",
    "sg:address":"871 Landis Ave",
    "sg:city":"Elmer",
    "sg:classifiers":[
        {
            "category":"Banks & Credit Unions",
            "subcategory":"Bank",
            "type":"Services"
        }
    ],
    "sg:phone":"+1 856 455 3500",
    "sg:postcode":"08318",
    "sg:province":"NJ",
    "wof:name":"Bank",
    "wof:placetype":"venue"
},
  "geometry": {"coordinates":[-75.119523,39.485391],"type":"Point"}
}