{
  "type": "Feature",
  "properties": {
    "addr:full":"159 E Railway Ave Paterson NJ 07503",
    "addr:housenumber":"159",
    "addr:postcode":"07503",
    "addr:street":"E Railway Ave",
    "iso:country":"US",
    "sg:address":"159 E Railway Ave",
    "sg:city":"Paterson",
    "sg:classifiers":[
        {
            "category":"Building & Trades",
            "subcategory":"Construction",
            "type":"Services"
        }
    ],
    "sg:phone":"+1 973 523 3505",
    "sg:postcode":"07503",
    "sg:province":"NJ",
    "sg:tags":[
        "roofing",
        "contractor"
    ],
    "wof:name":"Amana Construction",
    "wof:placetype":"venue"
},
  "geometry": {"coordinates":[-74.15389999999999,40.896198],"type":"Point"}
}