{
  "type": "Feature",
  "properties": {
    "addr:full":"22 Paterson Ave Midland Park NJ 07432",
    "addr:housenumber":"22",
    "addr:postcode":"07432",
    "addr:street":"Paterson Ave",
    "iso:country":"US",
    "sg:address":"22 Paterson Ave",
    "sg:city":"Midland Park",
    "sg:classifiers":[
        {
            "category":"Professional",
            "subcategory":"Business Services",
            "type":"Services"
        }
    ],
    "sg:phone":"+1 201 670 0100",
    "sg:postcode":"07432",
    "sg:province":"NJ",
    "sg:tags":[
        "arbitration"
    ],
    "wof:name":"Charles F Ryan Law Offices",
    "wof:placetype":"venue"
},
  "geometry": {"coordinates":[-74.14078600000001,40.985365],"type":"Point"}
}