{
  "type": "Feature",
  "properties": {
    "addr:full":"623 East Dr Paramus NJ 07652",
    "addr:housenumber":"623",
    "addr:postcode":"07652",
    "addr:street":"East Dr",
    "iso:country":"US",
    "sg:address":"623 East Dr",
    "sg:city":"Paramus",
    "sg:classifiers":[
        {
            "category":"Building & Trades",
            "subcategory":"Electrical",
            "type":"Services"
        }
    ],
    "sg:phone":"+1 201 261 7747",
    "sg:postcode":"07652",
    "sg:province":"NJ",
    "sg:tags":[
        "electrical",
        "contractor"
    ],
    "wof:name":"M B Electric Inc",
    "wof:placetype":"venue"
},
  "geometry": {"coordinates":[-74.053421,40.959781],"type":"Point"}
}