{
  "type": "Feature",
  "properties": {
    "addr:full":"10 Eastbrook Rd Parsippany NJ 07054",
    "addr:housenumber":"10",
    "addr:postcode":"07054",
    "addr:street":"Eastbrook Rd",
    "iso:country":"US",
    "sg:address":"10 Eastbrook Rd",
    "sg:city":"Parsippany",
    "sg:classifiers":[
        {
            "category":"Professional",
            "type":"Services"
        }
    ],
    "sg:phone":"+1   ",
    "sg:postcode":"07054",
    "sg:province":"NJ",
    "wof:name":"Procom Americxan Inc",
    "wof:placetype":"venue"
},
  "geometry": {"coordinates":[-74.41207,40.848879],"type":"Point"}
}