{
  "type": "Feature",
  "properties": {
    "addr:full":"3 Weston Rd Trenton NJ 08618",
    "addr:housenumber":"3",
    "addr:postcode":"08618",
    "addr:street":"Weston Rd",
    "iso:country":"US",
    "sg:address":"3 Weston Rd",
    "sg:city":"Trenton",
    "sg:classifiers":[
        {
            "category":"Building & Trades",
            "subcategory":"Construction",
            "type":"Services"
        }
    ],
    "sg:phone":"+1 609 510 0791",
    "sg:postcode":"08618",
    "sg:province":"NJ",
    "sg:tags":[
        "carpentry",
        "contractor"
    ],
    "wof:name":"Dab Carpentry",
    "wof:placetype":"venue"
},
  "geometry": {"coordinates":[-74.78522100000001,40.251472],"type":"Point"}
}