{
  "type": "Feature",
  "properties": {
    "iso:country":"US",
    "sg:address":"25 W Highland Ave",
    "sg:city":"Atlantic Hghlnds",
    "sg:classifiers":[
        {
            "category":"Retail",
            "subcategory":"Auto Repair",
            "type":"Services"
        }
    ],
    "sg:phone":"+1 732 872 8160",
    "sg:postcode":"07716",
    "sg:province":"NJ",
    "sg:tags":[
        "body",
        "automobile",
        "painting"
    ],
    "wof:name":"Finelines",
    "wof:placetype":"venue"
},
  "geometry": {"coordinates":[-74.04028099999999,40.412761],"type":"Point"}
}