{
  "type": "Feature",
  "properties": {
    "addr:full":"21 Spencer Rd Basking Ridge NJ 07920",
    "addr:housenumber":"21",
    "addr:postcode":"07920",
    "addr:street":"Spencer Rd",
    "iso:country":"US",
    "sg:address":"21 Spencer Rd",
    "sg:city":"Basking Ridge",
    "sg:classifiers":[
        {
            "category":"Building & Trades",
            "subcategory":"Construction",
            "type":"Services"
        }
    ],
    "sg:phone":"+1 908 696 1555",
    "sg:postcode":"07920",
    "sg:province":"NJ",
    "sg:tags":[
        "carpentry",
        "contractor"
    ],
    "wof:name":"K&S Design",
    "wof:placetype":"venue"
},
  "geometry": {"coordinates":[-74.554395,40.702929],"type":"Point"}
}