{
  "type": "Feature",
  "properties": {
    "addr:full":"116 State Rte 10 Succasunna NJ 07876",
    "addr:housenumber":"116",
    "addr:postcode":"07876",
    "addr:street":"State Rte 10",
    "iso:country":"US",
    "sg:address":"116 State Rte 10",
    "sg:city":"Succasunna",
    "sg:classifiers":[
        {
            "category":"Retail",
            "subcategory":"Car Wash",
            "type":"Services"
        }
    ],
    "sg:phone":"+1 973 927 1050",
    "sg:postcode":"07876",
    "sg:province":"NJ",
    "sg:tags":[
        "polishing",
        "washing"
    ],
    "wof:name":"West 10 Car Wash & Detail Inc",
    "wof:placetype":"venue"
},
  "geometry": {"coordinates":[-74.637985,40.86648],"type":"Point"}
}