{
  "type": "Feature",
  "properties": {
    "addr:full":"10 Terhune Ave Jersey City NJ 07305",
    "addr:housenumber":"10",
    "addr:postcode":"07305",
    "addr:street":"Terhune Ave",
    "iso:country":"US",
    "sg:address":"10 Terhune Ave",
    "sg:city":"Jersey City",
    "sg:classifiers":[
        {
            "category":"Organizations",
            "subcategory":"Religious Organization",
            "type":"Services"
        }
    ],
    "sg:phone":"+1   ",
    "sg:postcode":"07305",
    "sg:province":"NJ",
    "wof:name":"Braun-Storck Arnd Rev",
    "wof:placetype":"venue"
},
  "geometry": {"coordinates":[-74.093873,40.702228],"type":"Point"}
}