{
  "type": "Feature",
  "properties": {
    "iso:country":"US",
    "sg:address":"29 Brookside Pl",
    "sg:city":"Hillsdale",
    "sg:classifiers":[
        {
            "category":"Communications",
            "type":"Services"
        }
    ],
    "sg:phone":"+1 201 664 5171",
    "sg:postcode":"07642",
    "sg:province":"NJ",
    "sg:tags":[
        "communication"
    ],
    "wof:name":"Accellerate Communications",
    "wof:placetype":"venue"
},
  "geometry": {"coordinates":[-74.042647,41.006882],"type":"Point"}
}