{
  "type": "Feature",
  "properties": {
    "iso:country":"US",
    "sg:address":"109 Oak St",
    "sg:city":"Old Bridge",
    "sg:classifiers":[
        {
            "category":"Retail",
            "subcategory":"Auto Repair",
            "type":"Services"
        },
        {
            "category":"Wholesale",
            "subcategory":"Auto Parts",
            "type":"Manufacturing & Wholesale Goods"
        }
    ],
    "sg:phone":"+1 732 679 9980",
    "sg:postcode":"08857",
    "sg:province":"NJ",
    "sg:tags":[
        "repairing",
        "automobile",
        "industrial",
        "radiator"
    ],
    "wof:name":"Lucent Auto & Casting Inc",
    "wof:placetype":"venue"
},
  "geometry": {"coordinates":[-74.355182,40.390448],"type":"Point"}
}