{
  "type": "Feature",
  "properties": {
    "iso:country":"US",
    "sg:address":"974 Main St",
    "sg:city":"Paterson",
    "sg:classifiers":[
        {
            "category":"Personal",
            "subcategory":"Beauty Salon",
            "type":"Services"
        }
    ],
    "sg:phone":"+1 973 684 3830",
    "sg:postcode":"07503",
    "sg:province":"NJ",
    "sg:tags":[
        "shop"
    ],
    "wof:name":"Dynasty Hair Design Inc",
    "wof:placetype":"venue"
},
  "geometry": {"coordinates":[-74.160084,40.895287],"type":"Point"}
}