{
  "type": "Feature",
  "properties": {
    "iso:country":"US",
    "sg:address":"308 Tuckerton Rd",
    "sg:city":"Medford",
    "sg:classifiers":[
        {
            "category":"Health Services",
            "subcategory":"Doctor",
            "type":"Services"
        }
    ],
    "sg:phone":"+1 609 714 2273",
    "sg:postcode":"08055",
    "sg:province":"NJ",
    "sg:tags":[
        "dentist"
    ],
    "sg:website":"www.mfdc.com",
    "wof:name":"Medford Family Dental Care PA",
    "wof:placetype":"venue"
},
  "geometry": {"coordinates":[-74.820975,39.855033],"type":"Point"}
}