{
  "type": "Feature",
  "properties": {
    "iso:country":"US",
    "sg:address":"2260 State Rte 33",
    "sg:city":"Neptune",
    "sg:classifiers":[
        {
            "category":"Building & Trades",
            "subcategory":"Construction",
            "type":"Services"
        }
    ],
    "sg:phone":"+1 732 775 5666",
    "sg:postcode":"07753",
    "sg:province":"NJ",
    "sg:tags":[
        "home",
        "builder",
        "general",
        "contractor"
    ],
    "wof:name":"Pittenger Builders",
    "wof:placetype":"venue"
},
  "geometry": {"coordinates":[-74.050405,40.206249],"type":"Point"}
}