{
  "type": "Feature",
  "properties": {
    "addr:full":"1020 S Orange Ave Newark NJ 07106",
    "addr:housenumber":"1020",
    "addr:postcode":"07106",
    "addr:street":"S Orange Ave",
    "iso:country":"US",
    "sg:address":"1020 S Orange Ave",
    "sg:city":"Newark",
    "sg:classifiers":[
        {
            "category":"Personal",
            "subcategory":"Beauty Salon",
            "type":"Services"
        }
    ],
    "sg:phone":"+1 973 371 7200",
    "sg:postcode":"07106",
    "sg:province":"NJ",
    "sg:tags":[
        "shop"
    ],
    "wof:name":"Total Concept Hair Studio",
    "wof:placetype":"venue"
},
  "geometry": {"coordinates":[-74.23026,40.746347],"type":"Point"}
}