{
  "type": "Feature",
  "properties": {
    "iso:country":"US",
    "sg:address":"502 State St",
    "sg:city":"Camden",
    "sg:classifiers":[
        {
            "category":"Social Services",
            "subcategory":"Retirement Home",
            "type":"Services"
        }
    ],
    "sg:phone":"+1 856 963 2115",
    "sg:postcode":"08102",
    "sg:province":"NJ",
    "sg:tags":[
        "rooming",
        "house"
    ],
    "wof:name":"Rooming House",
    "wof:placetype":"venue"
},
  "geometry": {"coordinates":[-75.118779,39.952832],"type":"Point"}
}