{
  "type": "Feature",
  "properties": {
    "iso:country":"US",
    "sg:address":"631 Shunpike Rd",
    "sg:city":"Cape May",
    "sg:classifiers":[
        {
            "category":"Wholesale",
            "subcategory":"Machinery & Supplies",
            "type":"Manufacturing & Wholesale Goods"
        }
    ],
    "sg:phone":"+1 609 898 0624",
    "sg:postcode":"08204",
    "sg:province":"NJ",
    "sg:tags":[
        "truck"
    ],
    "wof:name":"Seafood Transport Inc",
    "wof:placetype":"venue"
},
  "geometry": {"coordinates":[-74.912436,38.992822],"type":"Point"}
}