{
  "type": "Feature",
  "properties": {
    "addr:full":"61 Bracken Hill Rd Hamburg NJ 07419",
    "addr:housenumber":"61",
    "addr:postcode":"07419",
    "addr:street":"Bracken Hill Rd",
    "iso:country":"US",
    "sg:address":"61 Bracken Hill Rd",
    "sg:city":"Hamburg",
    "sg:classifiers":[
        {
            "category":"Home & Garden",
            "subcategory":"Home Furnishings",
            "type":"Retail Goods"
        }
    ],
    "sg:phone":"+1 866 839 4770",
    "sg:postcode":"07419",
    "sg:province":"NJ",
    "sg:tags":[
        "draperies",
        "curtain",
        "window",
        "treatment"
    ],
    "wof:name":"Budget Blinds of Hamburg",
    "wof:placetype":"venue"
},
  "geometry": {"coordinates":[-74.563147,41.153924],"type":"Point"}
}