{
  "type": "Feature",
  "properties": {
    "addr:full":"2078 Saint Georges Ave Rahway NJ 07065",
    "addr:housenumber":"2078",
    "addr:postcode":"07065",
    "addr:street":"Saint Georges Ave",
    "iso:country":"US",
    "sg:address":"2078 Saint Georges Ave",
    "sg:city":"Rahway",
    "sg:classifiers":[
        {
            "category":"Arts & Performance",
            "subcategory":"Theater",
            "type":"Entertainment"
        }
    ],
    "sg:phone":"+1   ",
    "sg:postcode":"07065",
    "sg:province":"NJ",
    "sg:tags":[
        "group"
    ],
    "wof:name":"Club Oasis",
    "wof:placetype":"venue"
},
  "geometry": {"coordinates":[-74.28019999999999,40.6212],"type":"Point"}
}