{
  "type": "Feature",
  "properties": {
    "addr:full":"512 Main St Bradley Beach NJ 07720",
    "addr:housenumber":"512",
    "addr:postcode":"07720",
    "addr:street":"Main St",
    "iso:country":"US",
    "sg:address":"512 Main St",
    "sg:city":"Bradley Beach",
    "sg:classifiers":[
        {
            "category":"Shopping",
            "subcategory":"Optical Goods",
            "type":"Retail Goods"
        }
    ],
    "sg:phone":"+1 732 776 8364",
    "sg:postcode":"07720",
    "sg:province":"NJ",
    "sg:tags":[
        "optician"
    ],
    "wof:name":"Andrew H Mennie Optician",
    "wof:placetype":"venue"
},
  "geometry": {"coordinates":[-74.017933,40.202937],"type":"Point"}
}