{
  "type": "Feature",
  "properties": {
    "iso:country":"US",
    "sg:address":"100 Pemberton Browns Mill Rd",
    "sg:city":"Browns Mills",
    "sg:classifiers":[
        {
            "category":"Shopping",
            "subcategory":"Pharmacy",
            "type":"Retail Goods"
        }
    ],
    "sg:phone":"+1 609 893 1437",
    "sg:postcode":"08015",
    "sg:province":"NJ",
    "wof:name":"Rite Aid Pharmacy",
    "wof:placetype":"venue"
},
  "geometry": {"coordinates":[-74.588954,39.970424],"type":"Point"}
}