{
  "type": "Feature",
  "properties": {
    "iso:country":"US",
    "sg:address":"400 Lincoln Blvd",
    "sg:city":"Middlesex",
    "sg:classifiers":[
        {
            "category":"Professional",
            "subcategory":"Management & Consulting",
            "type":"Services"
        }
    ],
    "sg:phone":"+1   ",
    "sg:postcode":"08846",
    "sg:province":"NJ",
    "wof:name":"DMK Global Marketing LLC",
    "wof:placetype":"venue"
},
  "geometry": {"coordinates":[-74.49749199999999,40.569607],"type":"Point"}
}