{
  "type": "Feature",
  "properties": {
    "addr:full":"153 Logan Ave Audubon NJ 08106",
    "addr:housenumber":"153",
    "addr:postcode":"08106",
    "addr:street":"Logan Ave",
    "iso:country":"US",
    "sg:address":"153 Logan Ave",
    "sg:city":"Audubon",
    "sg:classifiers":[
        {
            "category":"Building & Trades",
            "subcategory":"Construction",
            "type":"Services"
        }
    ],
    "sg:phone":"+1 856 547 1544",
    "sg:postcode":"08106",
    "sg:province":"NJ",
    "sg:tags":[
        "contractor"
    ],
    "wof:name":"Complete Maintenance Repa",
    "wof:placetype":"venue"
},
  "geometry": {"coordinates":[-75.06693,39.89581],"type":"Point"}
}