{
  "type": "Feature",
  "properties": {
    "iso:country":"US",
    "sg:address":"875 State Rte 17",
    "sg:city":"Ramsey",
    "sg:classifiers":[
        {
            "category":"Retail",
            "subcategory":"Repair Shop",
            "type":"Services"
        }
    ],
    "sg:phone":"+1 201 596 0401",
    "sg:postcode":"07446",
    "sg:province":"NJ",
    "sg:tags":[
        "lock",
        "locksmith"
    ],
    "wof:name":"A 1 24 Hour A Emerg Locksmith",
    "wof:placetype":"venue"
},
  "geometry": {"coordinates":[-74.126454,41.06323],"type":"Point"}
}