{
  "type": "Feature",
  "properties": {
    "addr:full":"21 Coventry Cir W Marlton NJ 08053",
    "addr:housenumber":"21",
    "addr:postcode":"08053",
    "addr:street":"Coventry Cir W Marlton",
    "iso:country":"US",
    "sg:address":"21 Coventry Cir W",
    "sg:city":"Marlton",
    "sg:classifiers":[
        {
            "category":"Health Services",
            "subcategory":"Chiropractor",
            "type":"Services"
        }
    ],
    "sg:phone":"+1 856 983 7455",
    "sg:postcode":"08053",
    "sg:province":"NJ",
    "wof:name":"J Horning DC",
    "wof:placetype":"venue"
},
  "geometry": {"coordinates":[-74.886443,39.858594],"type":"Point"}
}