{
  "type": "Feature",
  "properties": {
    "addr:full":"61 Memorial Pkwy Atlantic Hghlnds NJ 07716",
    "addr:housenumber":"61",
    "addr:postcode":"07716",
    "addr:street":"Memorial Pkwy",
    "iso:country":"US",
    "sg:address":"61 Memorial Pkwy",
    "sg:city":"Atlantic Hghlnds",
    "sg:classifiers":[
        {
            "category":"Professional",
            "subcategory":"Lawyer & Legal Services",
            "type":"Services"
        }
    ],
    "sg:phone":"+1 732 872 6900",
    "sg:postcode":"07716",
    "sg:province":"NJ",
    "sg:tags":[
        "attorney"
    ],
    "wof:name":"Lawrence W Luttrell",
    "wof:placetype":"venue"
},
  "geometry": {"coordinates":[-74.036018,40.406866],"type":"Point"}
}