{
  "type": "Feature",
  "properties": {
    "addr:full":"946 Ave C Bayonne NJ 07002",
    "addr:housenumber":"946",
    "addr:postcode":"07002",
    "addr:street":"Ave C",
    "iso:country":"US",
    "sg:address":"946 Ave C",
    "sg:city":"Bayonne",
    "sg:classifiers":[
        {
            "category":"Health Services",
            "subcategory":"Doctor",
            "type":"Services"
        }
    ],
    "sg:phone":"+1 201 823 0243",
    "sg:postcode":"07002",
    "sg:province":"NJ",
    "sg:tags":[
        "physician",
        "surgeon"
    ],
    "wof:name":"Temprosa Colanta MD",
    "wof:placetype":"venue"
},
  "geometry": {"coordinates":[-74.10821,40.679719],"type":"Point"}
}