{
  "type": "Feature",
  "properties": {
    "iso:country":"US",
    "sg:address":"277 Closter Dock Rd",
    "sg:city":"Closter",
    "sg:classifiers":[
        {
            "category":"Government",
            "subcategory":"Office",
            "type":"Public Place"
        }
    ],
    "sg:phone":"+1 201 784 0759",
    "sg:postcode":"07624",
    "sg:province":"NJ",
    "sg:tags":[
        "village"
    ],
    "wof:name":"Closter Building Dept",
    "wof:placetype":"venue"
},
  "geometry": {"coordinates":[-73.959643,40.971358],"type":"Point"}
}