{
  "type": "Feature",
  "properties": {
    "iso:country":"US",
    "sg:address":"33 Normandy Rd",
    "sg:city":"Colonia",
    "sg:classifiers":[
        {
            "category":"Freight",
            "type":"Transportation"
        }
    ],
    "sg:phone":"+1 732 499 0766",
    "sg:postcode":"07067",
    "sg:province":"NJ",
    "sg:tags":[
        "company",
        "trucking"
    ],
    "wof:name":"Lauro Corp",
    "wof:placetype":"venue"
},
  "geometry": {"coordinates":[-74.33728000000001,40.604304],"type":"Point"}
}