{
  "type": "Feature",
  "properties": {
    "addr:full":"3800 Dune Dr Avalon NJ 08202",
    "addr:housenumber":"3800",
    "addr:postcode":"08202",
    "addr:street":"Dune Dr",
    "iso:country":"US",
    "sg:address":"3800 Dune Dr",
    "sg:city":"Avalon",
    "sg:classifiers":[
        {
            "category":"Utilities",
            "subcategory":"Mobile Phone",
            "type":"Services"
        }
    ],
    "sg:phone":"+1 609 368 6450",
    "sg:postcode":"08202",
    "sg:province":"NJ",
    "sg:tags":[
        "telephone",
        "cellular"
    ],
    "wof:name":"Cingular Wireless",
    "wof:placetype":"venue"
},
  "geometry": {"coordinates":[-74.72720700000001,39.09071],"type":"Point"}
}