{
  "type": "Feature",
  "properties": {
    "iso:country":"US",
    "sg:address":"23 State Rte 71",
    "sg:city":"Manasquan",
    "sg:classifiers":[
        {
            "category":"Health Services",
            "subcategory":"Doctor",
            "type":"Services"
        }
    ],
    "sg:phone":"+1   ",
    "sg:postcode":"08736",
    "sg:province":"NJ",
    "sg:tags":[
        "medical"
    ],
    "wof:name":"Mommouth Medical",
    "wof:placetype":"venue"
},
  "geometry": {"coordinates":[-74.04900600000001,40.121858],"type":"Point"}
}