{
  "type": "Feature",
  "properties": {
    "addr:full":"10 Stanley St Clifton NJ 07013",
    "addr:housenumber":"10",
    "addr:postcode":"07013",
    "addr:street":"Stanley St",
    "iso:country":"US",
    "sg:address":"10 Stanley St",
    "sg:city":"Clifton",
    "sg:classifiers":[
        {
            "category":"Organizations",
            "subcategory":"Religious Organization",
            "type":"Services"
        }
    ],
    "sg:phone":"+1 973 278 0110",
    "sg:postcode":"07013",
    "sg:province":"NJ",
    "sg:tags":[
        "clergy"
    ],
    "wof:name":"P D'Angelo",
    "wof:placetype":"venue"
},
  "geometry": {"coordinates":[-74.172286,40.885148],"type":"Point"}
}