{
  "type": "Feature",
  "properties": {
    "iso:country":"US",
    "sg:address":"115 River Rd",
    "sg:city":"Edgewater",
    "sg:classifiers":[
        {
            "category":"Building & Trades",
            "subcategory":"Construction",
            "type":"Services"
        }
    ],
    "sg:phone":"+1 201 941 5500",
    "sg:postcode":"07020",
    "sg:province":"NJ",
    "sg:tags":[
        "designer"
    ],
    "wof:name":"Innovations & Development Inc",
    "wof:placetype":"venue"
},
  "geometry": {"coordinates":[-73.991339,40.806422],"type":"Point"}
}