{
  "type": "Feature",
  "properties": {
    "addr:full":"9 South St Morristown NJ 07960",
    "addr:housenumber":"9",
    "addr:postcode":"07960",
    "addr:street":"South St",
    "iso:country":"US",
    "sg:address":"9 South St",
    "sg:city":"Morristown",
    "sg:classifiers":[
        {
            "category":"Coffee & Tea",
            "type":"Food & Drink"
        },
        {
            "category":"Bakery",
            "type":"Food & Drink"
        }
    ],
    "sg:phone":"+1 973 538 0890",
    "sg:postcode":"07960",
    "sg:province":"NJ",
    "sg:website":"www.facebook.com/zebumorristown",
    "wof:name":"Zebu Forno",
    "wof:placetype":"venue"
},
  "geometry": {"coordinates":[-74.481009,40.795805],"type":"Point"}
}