{
  "type": "Feature",
  "properties": {
    "iso:country":"US",
    "sg:address":"324 Chestnut St",
    "sg:city":"Union",
    "sg:classifiers":[
        {
            "category":"Retail",
            "subcategory":"Laundry & Dry Cleaning",
            "type":"Services"
        }
    ],
    "sg:phone":"+1 908 851 9010",
    "sg:postcode":"07083",
    "sg:province":"NJ",
    "sg:tags":[
        "drycleaning",
        "plant"
    ],
    "wof:name":"Rich Cleaners",
    "wof:placetype":"venue"
},
  "geometry": {"coordinates":[-74.26702899999999,40.674737],"type":"Point"}
}