{
  "type": "Feature",
  "properties": {
    "iso:country":"US",
    "sg:address":"400 Delanco Rd",
    "sg:city":"Beverly",
    "sg:classifiers":[
        {
            "category":"Government",
            "subcategory":"Office",
            "type":"Public Place"
        }
    ],
    "sg:phone":"+1 609 877 1411",
    "sg:postcode":"08010",
    "sg:province":"NJ",
    "sg:tags":[
        "village"
    ],
    "wof:name":"Edgewater Park Twp Sewerage",
    "wof:placetype":"venue"
},
  "geometry": {"coordinates":[-74.911558,40.044962],"type":"Point"}
}