{
  "type": "Feature",
  "properties": {
    "iso:country":"US",
    "sg:address":"37 E Palisade Ave",
    "sg:city":"Englewood",
    "sg:classifiers":[
        {
            "category":"Shopping",
            "subcategory":"Jewelry",
            "type":"Retail Goods"
        }
    ],
    "sg:phone":"+1   ",
    "sg:postcode":"07631",
    "sg:province":"NJ",
    "sg:tags":[
        "repair"
    ],
    "wof:name":"Englewood Jewelers",
    "wof:placetype":"venue"
},
  "geometry": {"coordinates":[-73.97385300000001,40.893565],"type":"Point"}
}