{
  "type": "Feature",
  "properties": {
    "addr:full":"143 N Farview Ave Paramus NJ 07652",
    "addr:housenumber":"143",
    "addr:postcode":"07652",
    "addr:street":"N Farview Ave",
    "iso:country":"US",
    "sg:address":"143 N Farview Ave",
    "sg:city":"Paramus",
    "sg:classifiers":[
        {
            "category":"Retail",
            "subcategory":"Laundry & Dry Cleaning",
            "type":"Services"
        }
    ],
    "sg:phone":"+1 201 265 6318",
    "sg:postcode":"07652",
    "sg:province":"NJ",
    "sg:tags":[
        "cleaners",
        "rug",
        "carpet"
    ],
    "wof:name":"All-Brite Cleaning Svc",
    "wof:placetype":"venue"
},
  "geometry": {"coordinates":[-74.06448399999999,40.931682],"type":"Point"}
}