{
  "type": "Feature",
  "properties": {
    "iso:country":"US",
    "sg:address":"4271 State Rte 27",
    "sg:city":"Princeton",
    "sg:classifiers":[
        {
            "category":"Shopping",
            "subcategory":"Florist",
            "type":"Retail Goods"
        }
    ],
    "sg:phone":"+1 732 821 7077",
    "sg:postcode":"08540",
    "sg:province":"NJ",
    "wof:name":"Just Because Flower Shop",
    "wof:placetype":"venue"
},
  "geometry": {"coordinates":[-74.60739700000001,40.378287],"type":"Point"}
}