{
  "type": "Feature",
  "properties": {
    "addr:full":"215 Trimble Ave Clifton NJ 07011",
    "addr:housenumber":"215",
    "addr:postcode":"07011",
    "addr:street":"Trimble Ave",
    "iso:country":"US",
    "sg:address":"215 Trimble Ave",
    "sg:city":"Clifton",
    "sg:classifiers":[
        {
            "category":"Wholesale",
            "subcategory":"Machinery & Supplies",
            "type":"Manufacturing & Wholesale Goods"
        }
    ],
    "sg:phone":"+1 973 546 6377",
    "sg:postcode":"07011",
    "sg:province":"NJ",
    "sg:tags":[
        "engine"
    ],
    "wof:name":"North Jersey Marine Ents Inc",
    "wof:placetype":"venue"
},
  "geometry": {"coordinates":[-74.14173,40.883241],"type":"Point"}
}