{
  "type": "Feature",
  "properties": {
    "addr:full":"27 Davis Ave Mt Ephraim NJ 08059",
    "addr:housenumber":"27",
    "addr:postcode":"08059",
    "addr:street":"Davis Ave Mt",
    "iso:country":"US",
    "sg:address":"27 Davis Ave",
    "sg:city":"Mt Ephraim",
    "sg:classifiers":[
        {
            "category":"Manufacturing",
            "subcategory":"Tools & Machinery",
            "type":"Manufacturing & Wholesale Goods"
        }
    ],
    "sg:phone":"+1 856 931 0300",
    "sg:postcode":"08059",
    "sg:province":"NJ",
    "sg:tags":[
        "beverage",
        "dispensing"
    ],
    "sg:website":"www.coldstarinc.com",
    "wof:name":"Cold Star",
    "wof:placetype":"venue"
},
  "geometry": {"coordinates":[-75.089625,39.879822],"type":"Point"}
}