{
  "type": "Feature",
  "properties": {
    "iso:country":"US",
    "sg:address":"38 E Palisade Ave",
    "sg:city":"Englewood",
    "sg:classifiers":[
        {
            "category":"Shopping",
            "type":"Retail Goods"
        }
    ],
    "sg:phone":"+1 201 503 9797",
    "sg:postcode":"07631",
    "sg:province":"NJ",
    "sg:tags":[
        "telephone",
        "cellular"
    ],
    "wof:name":"American Telecommunications",
    "wof:placetype":"venue"
},
  "geometry": {"coordinates":[-73.973544,40.893143],"type":"Point"}
}