{
  "type": "Feature",
  "properties": {
    "addr:full":"117 Victoria Pl W Fort Lee NJ 07024",
    "addr:housenumber":"117",
    "addr:postcode":"07024",
    "addr:street":"Victoria Pl W",
    "iso:country":"US",
    "sg:address":"117 Victoria Pl W",
    "sg:city":"Fort Lee",
    "sg:classifiers":[
        {
            "category":"Professional",
            "subcategory":"Management & Consulting",
            "type":"Services"
        }
    ],
    "sg:phone":"+1   ",
    "sg:postcode":"07024",
    "sg:province":"NJ",
    "sg:tags":[
        "business"
    ],
    "wof:name":"Gillman Farris & Associates",
    "wof:placetype":"venue"
},
  "geometry": {"coordinates":[-73.977862,40.829558],"type":"Point"}
}