{
  "type": "Feature",
  "properties": {
    "iso:country":"US",
    "sg:address":"12 Dartmouth Rd",
    "sg:city":"Annandale",
    "sg:classifiers":[
        {
            "category":"Professional",
            "subcategory":"Engineering",
            "type":"Services"
        }
    ],
    "sg:phone":"+1 908 730 6653",
    "sg:postcode":"08801",
    "sg:province":"NJ",
    "sg:tags":[
        "engineer"
    ],
    "wof:name":"Energy Research Co",
    "wof:placetype":"venue"
},
  "geometry": {"coordinates":[-74.892878,40.613354],"type":"Point"}
}