{
  "type": "Feature",
  "properties": {
    "addr:full":"618 Van Houten Ave Clifton NJ 07013",
    "addr:housenumber":"618",
    "addr:postcode":"07013",
    "addr:street":"Van Houten Ave",
    "iso:country":"US",
    "sg:address":"618 Van Houten Ave",
    "sg:city":"Clifton",
    "sg:classifiers":[
        {
            "category":"Health Services",
            "subcategory":"Clinic",
            "type":"Services"
        }
    ],
    "sg:phone":"+1 973 779 8777",
    "sg:postcode":"07013",
    "sg:province":"NJ",
    "sg:tags":[
        "information",
        "program",
        "referral"
    ],
    "wof:name":"Cuts Fitness For Men",
    "wof:placetype":"venue"
},
  "geometry": {"coordinates":[-74.147479,40.857744],"type":"Point"}
}