{
  "type": "Feature",
  "properties": {
    "addr:full":"753 Warren St Westfield NJ 07090",
    "addr:housenumber":"753",
    "addr:postcode":"07090",
    "addr:street":"Warren St",
    "iso:country":"US",
    "sg:address":"753 Warren St",
    "sg:city":"Westfield",
    "sg:classifiers":[
        {
            "category":"Professional",
            "subcategory":"Computer Services",
            "type":"Services"
        }
    ],
    "sg:phone":"+1   ",
    "sg:postcode":"07090",
    "sg:province":"NJ",
    "sg:tags":[
        "programing",
        "custom"
    ],
    "wof:name":"Sharetech",
    "wof:placetype":"venue"
},
  "geometry": {"coordinates":[-74.35687900000001,40.637453],"type":"Point"}
}