{
  "type": "Feature",
  "properties": {
    "addr:full":"14 Morgan Rd Flemington NJ 08822",
    "addr:housenumber":"14",
    "addr:postcode":"08822",
    "addr:street":"Morgan Rd",
    "iso:country":"US",
    "sg:address":"14 Morgan Rd",
    "sg:city":"Flemington",
    "sg:classifiers":[
        {
            "category":"Real Estate",
            "subcategory":"Real Estate Operator",
            "type":"Services"
        }
    ],
    "sg:phone":"+1   ",
    "sg:postcode":"08822",
    "sg:province":"NJ",
    "sg:tags":[
        "building",
        "nonresidential"
    ],
    "wof:name":"Kmb Investments",
    "wof:placetype":"venue"
},
  "geometry": {"coordinates":[-74.789997,40.49299],"type":"Point"}
}