{
  "type": "Feature",
  "properties": {
    "addr:full":"1114 Goffle Rd Hawthorne NJ 07506",
    "addr:housenumber":"1114",
    "addr:postcode":"07506",
    "addr:street":"Goffle Rd",
    "iso:country":"US",
    "sg:address":"1114 Goffle Rd",
    "sg:city":"Hawthorne",
    "sg:classifiers":[
        {
            "category":"Professional",
            "subcategory":"Accounting & Tax Preparation",
            "type":"Services"
        }
    ],
    "sg:phone":"+1 973 423 4878",
    "sg:postcode":"07506",
    "sg:province":"NJ",
    "sg:tags":[
        "accountant"
    ],
    "wof:name":"Yedwab Kantzos & Co",
    "wof:placetype":"venue"
},
  "geometry": {"coordinates":[-74.150862,40.97001],"type":"Point"}
}