{
  "type": "Feature",
  "properties": {
    "addr:full":"60 Penn St Woodbury NJ 08096",
    "addr:housenumber":"60",
    "addr:postcode":"08096",
    "addr:street":"Penn St",
    "iso:country":"US",
    "sg:address":"60 Penn St",
    "sg:city":"Woodbury",
    "sg:classifiers":[
        {
            "category":"Retail",
            "subcategory":"Auto Repair",
            "type":"Services"
        }
    ],
    "sg:phone":"+1   ",
    "sg:postcode":"08096",
    "sg:province":"NJ",
    "sg:tags":[
        "general"
    ],
    "wof:name":"Dickson Truck Service",
    "wof:placetype":"venue"
},
  "geometry": {"coordinates":[-75.158781,39.833532],"type":"Point"}
}