{
  "type": "Feature",
  "properties": {
    "addr:full":"545 Lexington Ave Clifton NJ 07011",
    "addr:housenumber":"545",
    "addr:postcode":"07011",
    "addr:street":"Lexington Ave",
    "iso:country":"US",
    "sg:address":"545 Lexington Ave",
    "sg:city":"Clifton",
    "sg:classifiers":[
        {
            "category":"Building & Trades",
            "subcategory":"Locksmith",
            "type":"Services"
        }
    ],
    "sg:phone":"+1 888 271 1713",
    "sg:postcode":"07011",
    "sg:province":"NJ",
    "sg:tags":[
        "key"
    ],
    "wof:name":"A 1 Emergency Locksmith",
    "wof:placetype":"venue"
},
  "geometry": {"coordinates":[-74.135186,40.879467],"type":"Point"}
}