{
  "type": "Feature",
  "properties": {
    "addr:full":"9 Hulfish St Princeton NJ 08542",
    "addr:housenumber":"9",
    "addr:postcode":"08542",
    "addr:street":"Hulfish St",
    "iso:country":"US",
    "sg:address":"9 Hulfish St",
    "sg:city":"Princeton",
    "sg:classifiers":[
        {
            "category":"Bars & Pubs",
            "type":"Food & Drink"
        },
        {
            "category":"Restaurant",
            "type":"Food & Drink"
        },
        {
            "category":"Bars & Pubs",
            "subcategory":"Lounge",
            "type":"Food & Drink"
        }
    ],
    "sg:phone":"+1 609 921 1710",
    "sg:postcode":"08542",
    "sg:province":"NJ",
    "sg:tags":[
        "cocktail"
    ],
    "wof:name":"Halo Pub",
    "wof:placetype":"venue"
},
  "geometry": {"coordinates":[-74.660673,40.351176],"type":"Point"}
}