{
  "type": "Feature",
  "properties": {
    "addr:full":"131 Madison Ave Morristown NJ 07960",
    "addr:housenumber":"131",
    "addr:postcode":"07960",
    "addr:street":"Madison Ave",
    "iso:country":"US",
    "sg:address":"131 Madison Ave",
    "sg:city":"Morristown",
    "sg:classifiers":[
        {
            "category":"Professional",
            "subcategory":"Lawyer & Legal Services",
            "type":"Services"
        }
    ],
    "sg:phone":"+1 973 360 1100",
    "sg:postcode":"07960",
    "sg:province":"NJ",
    "sg:tags":[
        "attorney"
    ],
    "wof:name":"Shanley & Fisher",
    "wof:placetype":"venue"
},
  "geometry": {"coordinates":[-74.461225,40.788286],"type":"Point"}
}