{
  "type": "Feature",
  "properties": {
    "iso:country":"US",
    "sg:address":"1554 Teaneck Rd",
    "sg:city":"Teaneck",
    "sg:classifiers":[
        {
            "category":"Restaurant",
            "type":"Food & Drink"
        }
    ],
    "sg:phone":"+1 201 833 4005",
    "sg:postcode":"07666",
    "sg:province":"NJ",
    "sg:tags":[
        "pizza"
    ],
    "wof:name":"The Right Pizza",
    "wof:placetype":"venue"
},
  "geometry": {"coordinates":[-73.99889899999999,40.903938],"type":"Point"}
}