{
  "type": "Feature",
  "properties": {
    "iso:country":"US",
    "sg:address":"1066 Springfield Ave",
    "sg:city":"Irvington",
    "sg:classifiers":[
        {
            "category":"Personal",
            "subcategory":"Beauty Salon",
            "type":"Services"
        }
    ],
    "sg:phone":"+1 973 373 1355",
    "sg:postcode":"07111",
    "sg:province":"NJ",
    "sg:tags":[
        "manicuring"
    ],
    "wof:name":"Na Na Nail Salon",
    "wof:placetype":"venue"
},
  "geometry": {"coordinates":[-74.231864,40.72607],"type":"Point"}
}