{
  "type": "Feature",
  "properties": {
    "iso:country":"US",
    "sg:address":"112 N 10th St",
    "sg:city":"Kenilworth",
    "sg:classifiers":[
        {
            "category":"Retail",
            "subcategory":"Auto Repair",
            "type":"Services"
        }
    ],
    "sg:phone":"+1 908 653 1188",
    "sg:postcode":"07033",
    "sg:province":"NJ",
    "sg:tags":[
        "repairing",
        "automobile"
    ],
    "wof:name":"Details",
    "wof:placetype":"venue"
},
  "geometry": {"coordinates":[-74.301839,40.678043],"type":"Point"}
}