{
  "type": "Feature",
  "properties": {
    "addr:full":"102 Seminary Dr Mahwah NJ 07430",
    "addr:housenumber":"102",
    "addr:postcode":"07430",
    "addr:street":"Seminary Dr",
    "iso:country":"US",
    "sg:address":"102 Seminary Dr",
    "sg:city":"Mahwah",
    "sg:classifiers":[
        {
            "category":"Shopping",
            "subcategory":"Crafts & Fabrics",
            "type":"Retail Goods"
        }
    ],
    "sg:phone":"+1   ",
    "sg:postcode":"07430",
    "sg:province":"NJ",
    "sg:tags":[
        "company",
        "knitting"
    ],
    "wof:name":"Karabella Inc",
    "wof:placetype":"venue"
},
  "geometry": {"coordinates":[-74.18323599999999,41.071456],"type":"Point"}
}