{
  "type": "Feature",
  "properties": {
    "iso:country":"US",
    "sg:address":"39 W Main St",
    "sg:city":"Mendham",
    "sg:classifiers":[
        {
            "category":"Wholesale",
            "subcategory":"Machinery & Supplies",
            "type":"Manufacturing & Wholesale Goods"
        }
    ],
    "sg:phone":"+1 973 543 2700",
    "sg:postcode":"07945",
    "sg:province":"NJ",
    "sg:tags":[
        "equipment",
        "industrial"
    ],
    "wof:name":"Goding Compliance Systems",
    "wof:placetype":"venue"
},
  "geometry": {"coordinates":[-74.60610200000001,40.774955],"type":"Point"}
}