{
  "type": "Feature",
  "properties": {
    "iso:country":"US",
    "sg:address":"72 Patty Bowker Rd",
    "sg:city":"Vincentown",
    "sg:classifiers":[
        {
            "category":"Professional",
            "type":"Services"
        }
    ],
    "sg:phone":"+1   ",
    "sg:postcode":"08088",
    "sg:province":"NJ",
    "wof:name":"Im Kitba Co",
    "wof:placetype":"venue"
},
  "geometry": {"coordinates":[-74.702173,39.865245],"type":"Point"}
}