{
  "type": "Feature",
  "properties": {
    "addr:full":"59 Mount Pleasant Rd Columbia NJ 07832",
    "addr:housenumber":"59",
    "addr:postcode":"07832",
    "addr:street":"Mount Pleasant Rd",
    "iso:country":"US",
    "sg:address":"59 Mount Pleasant Rd",
    "sg:city":"Columbia",
    "sg:classifiers":[
        {
            "category":"Wholesale",
            "subcategory":"Construction Materials",
            "type":"Manufacturing & Wholesale Goods"
        }
    ],
    "sg:phone":"+1 908 496 4454",
    "sg:postcode":"07832",
    "sg:province":"NJ",
    "sg:tags":[
        "fence"
    ],
    "wof:name":"Chris Carmeci Fencing Plygrnd",
    "wof:placetype":"venue"
},
  "geometry": {"coordinates":[-75.062051,40.954],"type":"Point"}
}