{
  "type": "Feature",
  "properties": {
    "iso:country":"US",
    "sg:address":"469 S Main St",
    "sg:city":"Forked River",
    "sg:classifiers":[
        {
            "category":"Building & Trades",
            "subcategory":"Plumbing",
            "type":"Services"
        }
    ],
    "sg:phone":"+1 609 693 6410",
    "sg:postcode":"08731",
    "sg:province":"NJ",
    "sg:tags":[
        "mechanical",
        "contractor"
    ],
    "wof:name":"Legrand Mechanical Inc",
    "wof:placetype":"venue"
},
  "geometry": {"coordinates":[-74.197731,39.831553],"type":"Point"}
}