{
  "type": "Feature",
  "properties": {
    "iso:country":"US",
    "sg:address":"1135 Chestnut St",
    "sg:city":"Elizabeth",
    "sg:classifiers":[
        {
            "category":"Manufacturing",
            "subcategory":"Tools & Machinery",
            "type":"Manufacturing & Wholesale Goods"
        }
    ],
    "sg:phone":"+1 908 355 1515",
    "sg:postcode":"07201",
    "sg:province":"NJ",
    "sg:tags":[
        "mfg"
    ],
    "wof:name":"Air Clean Co Inc",
    "wof:placetype":"venue"
},
  "geometry": {"coordinates":[-74.211873,40.668588],"type":"Point"}
}