{
  "type": "Feature",
  "properties": {
    "iso:country":"US",
    "sg:address":"69 4th Ave",
    "sg:city":"East Orange",
    "sg:classifiers":[
        {
            "category":"Shopping",
            "subcategory":"Pharmacy",
            "type":"Retail Goods"
        }
    ],
    "sg:phone":"+1 973 672 3331",
    "sg:postcode":"07017",
    "sg:province":"NJ",
    "wof:name":"Ampere Drugs",
    "wof:placetype":"venue"
},
  "geometry": {"coordinates":[-74.196646,40.765325],"type":"Point"}
}