{
  "type": "Feature",
  "properties": {
    "addr:full":"59 Tindall Rd Middletown NJ 07748",
    "addr:housenumber":"59",
    "addr:postcode":"07748",
    "addr:street":"Tindall Rd",
    "iso:country":"US",
    "sg:address":"59 Tindall Rd",
    "sg:city":"Middletown",
    "sg:classifiers":[
        {
            "category":"Government",
            "subcategory":"Office",
            "type":"Public Place"
        }
    ],
    "sg:phone":"+1   ",
    "sg:postcode":"07748",
    "sg:province":"NJ",
    "sg:tags":[
        "civil",
        "defense"
    ],
    "wof:name":"Emergency Management Civil Def",
    "wof:placetype":"venue"
},
  "geometry": {"coordinates":[-74.100554,40.401976],"type":"Point"}
}