{
  "type": "Feature",
  "properties": {
    "addr:full":"762 Ramsey Ave Hillside NJ 07205",
    "addr:housenumber":"762",
    "addr:postcode":"07205",
    "addr:street":"Ramsey Ave",
    "iso:country":"US",
    "sg:address":"762 Ramsey Ave",
    "sg:city":"Hillside",
    "sg:classifiers":[
        {
            "category":"Manufacturing",
            "subcategory":"Metals",
            "type":"Manufacturing & Wholesale Goods"
        }
    ],
    "sg:phone":"+1 908 688 4600",
    "sg:postcode":"07205",
    "sg:province":"NJ",
    "sg:tags":[
        "product",
        "wire",
        "mfg",
        "wiring",
        "fabricated",
        "conductive"
    ],
    "sg:website":"www.uniquewire.com",
    "wof:name":"Unique Wire Weaving Co Inc",
    "wof:placetype":"venue"
},
  "geometry": {"coordinates":[-74.232878,40.70862],"type":"Point"}
}