{
  "type": "Feature",
  "properties": {
    "iso:country":"US",
    "sg:address":"307 N 2nd St",
    "sg:city":"Harrison",
    "sg:classifiers":[
        {
            "category":"Utilities",
            "subcategory":"Telephone",
            "type":"Services"
        }
    ],
    "sg:phone":"+1 973 350 0555",
    "sg:postcode":"07029",
    "sg:province":"NJ",
    "sg:tags":[
        "telecommunication"
    ],
    "wof:name":"Mac Ler Telecom",
    "wof:placetype":"venue"
},
  "geometry": {"coordinates":[-74.159961,40.748929],"type":"Point"}
}