{
  "type": "Feature",
  "properties": {
    "addr:full":"102 E Broad St Westfield NJ 07090",
    "addr:housenumber":"102",
    "addr:postcode":"07090",
    "addr:street":"E Broad St",
    "iso:country":"US",
    "sg:address":"102 E Broad St",
    "sg:city":"Westfield",
    "sg:classifiers":[
        {
            "category":"Restaurant",
            "type":"Food & Drink"
        }
    ],
    "sg:phone":"+1 908 233 3337",
    "sg:postcode":"07090",
    "sg:province":"NJ",
    "wof:name":"Wild Noodles Westfield",
    "wof:placetype":"venue"
},
  "geometry": {"coordinates":[-74.348191,40.651686],"type":"Point"}
}