{
  "type": "Feature",
  "properties": {
    "addr:full":"672 E 24th St Paterson NJ 07504",
    "addr:housenumber":"672",
    "addr:postcode":"07504",
    "addr:street":"E 24Th St",
    "iso:country":"US",
    "sg:address":"672 E 24th St",
    "sg:city":"Paterson",
    "sg:classifiers":[
        {
            "category":"Retail",
            "subcategory":"Repair Shop",
            "type":"Services"
        }
    ],
    "sg:phone":"+1   ",
    "sg:postcode":"07504",
    "sg:province":"NJ",
    "sg:tags":[
        "refrigeration"
    ],
    "wof:name":"Caribas Refrigeration",
    "wof:placetype":"venue"
},
  "geometry": {"coordinates":[-74.150617,40.917991],"type":"Point"}
}