{
  "type": "Feature",
  "properties": {
    "iso:country":"US",
    "sg:address":"271 Millburn Ave",
    "sg:city":"Millburn",
    "sg:classifiers":[
        {
            "category":"Restaurant",
            "type":"Food & Drink"
        }
    ],
    "sg:phone":"+1 973 218 9888",
    "sg:postcode":"07041",
    "sg:province":"NJ",
    "sg:tags":[
        "thai",
        "chinese"
    ],
    "sg:website":"www.qjgreengarden.com",
    "wof:name":"Q J Green Garden",
    "wof:placetype":"venue"
},
  "geometry": {"coordinates":[-74.30218499999999,40.724699],"type":"Point"}
}