{
  "type": "Feature",
  "properties": {
    "addr:full":"3 Rimmele Rd Glen Gardner NJ 08826",
    "addr:housenumber":"3",
    "addr:postcode":"08826",
    "addr:street":"Rimmele Rd",
    "iso:country":"US",
    "sg:address":"3 Rimmele Rd",
    "sg:city":"Glen Gardner",
    "sg:classifiers":[
        {
            "category":"Building & Trades",
            "subcategory":"Construction",
            "type":"Services"
        }
    ],
    "sg:phone":"+1 908 832 6898",
    "sg:postcode":"08826",
    "sg:province":"NJ",
    "sg:tags":[
        "contractor"
    ],
    "wof:name":"R P I Contracting",
    "wof:placetype":"venue"
},
  "geometry": {"coordinates":[-74.87190200000001,40.732201],"type":"Point"}
}