{
  "type": "Feature",
  "properties": {
    "addr:full":"12 Stevenson Ln Califon NJ 07830",
    "addr:housenumber":"12",
    "addr:postcode":"07830",
    "addr:street":"Stevenson Ln",
    "iso:country":"US",
    "sg:address":"12 Stevenson Ln",
    "sg:city":"Califon",
    "sg:classifiers":[
        {
            "category":"Real Estate",
            "subcategory":"Architect",
            "type":"Services"
        }
    ],
    "sg:phone":"+1   ",
    "sg:postcode":"07830",
    "sg:province":"NJ",
    "sg:tags":[
        "architectural"
    ],
    "wof:name":"Lupo W A I A-Architecht",
    "wof:placetype":"venue"
},
  "geometry": {"coordinates":[-74.85380499999999,40.692671],"type":"Point"}
}