{
  "type": "Feature",
  "properties": {
    "addr:full":"2 Main St Belleville NJ 07109",
    "addr:housenumber":"2",
    "addr:postcode":"07109",
    "addr:street":"Main St",
    "iso:country":"US",
    "sg:address":"2 Main St",
    "sg:city":"Belleville",
    "sg:classifiers":[
        {
            "category":"Manufacturing",
            "subcategory":"Metals",
            "type":"Manufacturing & Wholesale Goods"
        }
    ],
    "sg:phone":"+1 973 751 3447",
    "sg:postcode":"07109",
    "sg:province":"NJ",
    "sg:tags":[
        "finisher"
    ],
    "wof:name":"Dynamic Metal Co",
    "wof:placetype":"venue"
},
  "geometry": {"coordinates":[-74.151022,40.780243],"type":"Point"}
}