{
  "type": "Feature",
  "properties": {
    "iso:country":"US",
    "sg:address":"731 Asbury Ave",
    "sg:city":"Ocean City",
    "sg:classifiers":[
        {
            "category":"Shopping",
            "subcategory":"Gifts & Souvenirs",
            "type":"Retail Goods"
        }
    ],
    "sg:phone":"+1 609 398 9623",
    "sg:postcode":"08226",
    "sg:province":"NJ",
    "sg:tags":[
        "shop"
    ],
    "wof:name":"Ruth's Hallmark",
    "wof:placetype":"venue"
},
  "geometry": {"coordinates":[-74.573746,39.280654],"type":"Point"}
}