{
  "type": "Feature",
  "properties": {
    "iso:country":"US",
    "sg:address":"1023 E 25th St",
    "sg:city":"Paterson",
    "sg:classifiers":[
        {
            "category":"Utilities",
            "subcategory":"Mobile Phone",
            "type":"Services"
        }
    ],
    "sg:phone":"+1 973 247 2332",
    "sg:postcode":"07513",
    "sg:province":"NJ",
    "sg:tags":[
        "communication",
        "radiotelephone"
    ],
    "wof:name":"NY Wireless",
    "wof:placetype":"venue"
},
  "geometry": {"coordinates":[-74.152179,40.90518],"type":"Point"}
}