{
  "type": "Feature",
  "properties": {
    "addr:full":"447 Boulder Dr Morganville NJ 07751",
    "addr:housenumber":"447",
    "addr:postcode":"07751",
    "addr:street":"Boulder Dr",
    "iso:country":"US",
    "sg:address":"447 Boulder Dr",
    "sg:city":"Morganville",
    "sg:classifiers":[
        {
            "category":"Professional",
            "subcategory":"Computer Services",
            "type":"Services"
        }
    ],
    "sg:phone":"+1   ",
    "sg:postcode":"07751",
    "sg:province":"NJ",
    "sg:tags":[
        "related"
    ],
    "wof:name":"S W A Stream Inc",
    "wof:placetype":"venue"
},
  "geometry": {"coordinates":[-74.215459,40.382094],"type":"Point"}
}