{
  "type": "Feature",
  "properties": {
    "iso:country":"US",
    "sg:address":"71 Hackensack St",
    "sg:city":"Wood-Ridge",
    "sg:classifiers":[
        {
            "category":"Professional",
            "subcategory":"Engineering",
            "type":"Services"
        }
    ],
    "sg:phone":"+1 201 438 5110",
    "sg:postcode":"07075",
    "sg:province":"NJ",
    "sg:tags":[
        "technical",
        "advertising"
    ],
    "wof:name":"Com Det Inc",
    "wof:placetype":"venue"
},
  "geometry": {"coordinates":[-74.086923,40.843871],"type":"Point"}
}