{
  "type": "Feature",
  "properties": {
    "addr:full":"449 Westside Ave Jersey City NJ 07304",
    "addr:housenumber":"449",
    "addr:postcode":"07304",
    "addr:street":"Westside Ave",
    "iso:country":"US",
    "sg:address":"449 Westside Ave",
    "sg:city":"Jersey City",
    "sg:classifiers":[
        {
            "category":"Shopping",
            "subcategory":"Computers & Home Electronics",
            "type":"Retail Goods"
        }
    ],
    "sg:phone":"+1 201 332 4973",
    "sg:postcode":"07304",
    "sg:province":"NJ",
    "wof:name":"Top Notch Electronics & Apparel",
    "wof:placetype":"venue"
},
  "geometry": {"coordinates":[-74.085697,40.716634],"type":"Point"}
}