{
  "type": "Feature",
  "properties": {
    "iso:country":"US",
    "sg:address":"23 Indian Spring Trl",
    "sg:city":"Denville",
    "sg:classifiers":[
        {
            "category":"Building & Trades",
            "subcategory":"Construction",
            "type":"Services"
        }
    ],
    "sg:phone":"+1 973 625 8081",
    "sg:postcode":"07834",
    "sg:province":"NJ",
    "sg:tags":[
        "house",
        "nonresidential"
    ],
    "wof:name":"Gantert Construction Inc",
    "wof:placetype":"venue"
},
  "geometry": {"coordinates":[-74.487978,40.885144],"type":"Point"}
}