{
  "type": "Feature",
  "properties": {
    "addr:full":"5 Paulson Pl Haworth NJ 07641",
    "addr:housenumber":"5",
    "addr:postcode":"07641",
    "addr:street":"Paulson Pl",
    "iso:country":"US",
    "sg:address":"5 Paulson Pl",
    "sg:city":"Haworth",
    "sg:classifiers":[
        {
            "category":"Health Services",
            "subcategory":"Doctor",
            "type":"Services"
        }
    ],
    "sg:phone":"+1 201 385 2795",
    "sg:postcode":"07641",
    "sg:province":"NJ",
    "sg:tags":[
        "physician",
        "surgeon"
    ],
    "wof:name":"Mark Kahn MD",
    "wof:placetype":"venue"
},
  "geometry": {"coordinates":[-73.996576,40.955602],"type":"Point"}
}