{
  "type": "Feature",
  "properties": {
    "addr:full":"290 Red School Ln Phillipsburg NJ 08865",
    "addr:housenumber":"290",
    "addr:postcode":"08865",
    "addr:street":"Red School Ln",
    "iso:country":"US",
    "sg:address":"290 Red School Ln",
    "sg:city":"Phillipsburg",
    "sg:classifiers":[
        {
            "category":"Health Services",
            "subcategory":"Nursing And Care Facility",
            "type":"Services"
        }
    ],
    "sg:phone":"+1 908 859 2800",
    "sg:postcode":"08865",
    "sg:province":"NJ",
    "sg:tags":[
        "home",
        "convalescent"
    ],
    "wof:name":"Brakeley Park Villas",
    "wof:placetype":"venue"
},
  "geometry": {"coordinates":[-75.166562,40.704632],"type":"Point"}
}