{
  "type": "Feature",
  "properties": {
    "addr:full":"20 Craig Rd Montvale NJ 07645",
    "addr:housenumber":"20",
    "addr:postcode":"07645",
    "addr:street":"Craig Rd",
    "iso:country":"US",
    "sg:address":"20 Craig Rd",
    "sg:city":"Montvale",
    "sg:classifiers":[
        {
            "category":"Professional",
            "type":"Services"
        }
    ],
    "sg:phone":"+1 201 476 9557",
    "sg:postcode":"07645",
    "sg:province":"NJ",
    "sg:tags":[
        "establishment"
    ],
    "wof:name":"Penn Color",
    "wof:placetype":"venue"
},
  "geometry": {"coordinates":[-74.06121400000001,41.053992],"type":"Point"}
}