{
  "type": "Feature",
  "properties": {
    "addr:full":"35 Blanchard St Newark NJ 07105",
    "addr:housenumber":"35",
    "addr:postcode":"07105",
    "addr:street":"Blanchard St",
    "iso:country":"US",
    "sg:address":"35 Blanchard St",
    "sg:city":"Newark",
    "sg:classifiers":[
        {
            "category":"Professional",
            "type":"Services"
        }
    ],
    "sg:phone":"+1 973 817 7936",
    "sg:postcode":"07105",
    "sg:province":"NJ",
    "sg:tags":[
        "establishment"
    ],
    "wof:name":"Nrg Generating Us Newark",
    "wof:placetype":"venue"
},
  "geometry": {"coordinates":[-74.128685,40.735943],"type":"Point"}
}