{
  "type": "Feature",
  "properties": {
    "addr:full":"116 Ravine Ave Wyckoff NJ 07481",
    "addr:housenumber":"116",
    "addr:postcode":"07481",
    "addr:street":"Ravine Ave",
    "iso:country":"US",
    "sg:address":"116 Ravine Ave",
    "sg:city":"Wyckoff",
    "sg:classifiers":[
        {
            "category":"Organizations",
            "subcategory":"Religious Organization",
            "type":"Services"
        }
    ],
    "sg:phone":"+1 201 445 0004",
    "sg:postcode":"07481",
    "sg:province":"NJ",
    "sg:tags":[
        "church"
    ],
    "wof:name":"Second Reformed Church-Wyckoff",
    "wof:placetype":"venue"
},
  "geometry": {"coordinates":[-74.154826,40.981388],"type":"Point"}
}