{
  "type": "Feature",
  "properties": {
    "iso:country":"US",
    "sg:address":"13 Peach Hill Ct",
    "sg:city":"Ramsey",
    "sg:classifiers":[
        {
            "category":"Professional",
            "subcategory":"Management & Consulting",
            "type":"Services"
        }
    ],
    "sg:phone":"+1 201 785 9022",
    "sg:postcode":"07446",
    "sg:province":"NJ",
    "wof:name":"Merino Sales & Marketing",
    "wof:placetype":"venue"
},
  "geometry": {"coordinates":[-74.12484499999999,41.071028],"type":"Point"}
}