{
  "type": "Feature",
  "properties": {
    "iso:country":"US",
    "sg:address":"344 Broadway",
    "sg:city":"Long Branch",
    "sg:classifiers":[
        {
            "category":"Government",
            "subcategory":"Police Station",
            "type":"Public Place"
        }
    ],
    "sg:phone":"+1   ",
    "sg:postcode":"07740",
    "sg:province":"NJ",
    "sg:tags":[
        "juvenile",
        "bureau"
    ],
    "wof:name":"Long Branch Juvenile Bureau",
    "wof:placetype":"venue"
},
  "geometry": {"coordinates":[-73.993134,40.303853],"type":"Point"}
}