{
  "type": "Feature",
  "properties": {
    "addr:full":"6052 Tyler Pl West New York NJ 07093",
    "addr:housenumber":"6052",
    "addr:postcode":"07093",
    "addr:street":"Tyler Pl West",
    "iso:country":"US",
    "sg:address":"6052 Tyler Pl",
    "sg:city":"West New York",
    "sg:classifiers":[
        {
            "category":"Building & Trades",
            "subcategory":"Locksmith",
            "type":"Services"
        }
    ],
    "sg:phone":"+1 888 291 9792",
    "sg:postcode":"07093",
    "sg:province":"NJ",
    "sg:tags":[
        "key"
    ],
    "wof:name":"24 Hour 7 Day Emergency Locksmith",
    "wof:placetype":"venue"
},
  "geometry": {"coordinates":[-74.014173,40.788751],"type":"Point"}
}