{
  "type": "Feature",
  "properties": {
    "iso:country":"US",
    "sg:address":"13 Johnny Ct",
    "sg:city":"Red Bank",
    "sg:classifiers":[
        {
            "category":"Professional",
            "subcategory":"Business Services",
            "type":"Services"
        }
    ],
    "sg:phone":"+1 732 530 6528",
    "sg:postcode":"07701",
    "sg:province":"NJ",
    "wof:name":"Sha La Music Inc",
    "wof:placetype":"venue"
},
  "geometry": {"coordinates":[-74.09662899999999,40.371174],"type":"Point"}
}