{
  "type": "Feature",
  "properties": {
    "iso:country":"US",
    "sg:address":"1031 Tuckerton Rd",
    "sg:city":"Marlton",
    "sg:classifiers":[
        {
            "category":"Professional",
            "type":"Services"
        }
    ],
    "sg:phone":"+1 856 797 3402",
    "sg:postcode":"08053",
    "sg:province":"NJ",
    "sg:tags":[
        "establishment"
    ],
    "wof:name":"Solutran",
    "wof:placetype":"venue"
},
  "geometry": {"coordinates":[-74.86811899999999,39.880948],"type":"Point"}
}