{
  "type": "Feature",
  "properties": {
    "iso:country":"US",
    "sg:address":"6 Berkeley Pl",
    "sg:city":"Montclair",
    "sg:classifiers":[
        {
            "category":"Professional",
            "subcategory":"Management & Consulting",
            "type":"Services"
        }
    ],
    "sg:phone":"+1 973 509 8863",
    "sg:postcode":"07042",
    "sg:province":"NJ",
    "sg:tags":[
        "public",
        "relations"
    ],
    "wof:name":"Torsney Communications",
    "wof:placetype":"venue"
},
  "geometry": {"coordinates":[-74.21527500000001,40.828955],"type":"Point"}
}