{
  "type": "Feature",
  "properties": {
    "iso:country":"US",
    "sg:address":"1945 Morris Ave",
    "sg:city":"Union",
    "sg:classifiers":[
        {
            "category":"Real Estate",
            "subcategory":"Real Estate Agent",
            "type":"Services"
        }
    ],
    "sg:phone":"+1 908 687 3200",
    "sg:postcode":"07083",
    "sg:province":"NJ",
    "sg:tags":[
        "management"
    ],
    "wof:name":"Winding Brook Apartments",
    "wof:placetype":"venue"
},
  "geometry": {"coordinates":[-74.26904999999999,40.696235],"type":"Point"}
}