{
  "type": "Feature",
  "properties": {
    "iso:country":"US",
    "sg:address":"7 Cuthbert Blvd",
    "sg:city":"Haddon Twp",
    "sg:classifiers":[
        {
            "category":"Professional",
            "subcategory":"Accounting & Tax Preparation",
            "type":"Services"
        }
    ],
    "sg:phone":"+1 856 854 6634",
    "sg:postcode":"08107",
    "sg:province":"NJ",
    "sg:tags":[
        "accountant"
    ],
    "wof:name":"Garagozzo Petchon Ryan Rotella",
    "wof:placetype":"venue"
},
  "geometry": {"coordinates":[-75.07212699999999,39.898866],"type":"Point"}
}