{
  "type": "Feature",
  "properties": {
    "addr:full":"89 Ringwood Ave Wanaque NJ 07465",
    "addr:housenumber":"89",
    "addr:postcode":"07465",
    "addr:street":"Ringwood Ave",
    "iso:country":"US",
    "sg:address":"89 Ringwood Ave",
    "sg:city":"Wanaque",
    "sg:classifiers":[
        {
            "category":"Building & Trades",
            "subcategory":"Construction",
            "type":"Services"
        }
    ],
    "sg:phone":"+1 973 835 0128",
    "sg:postcode":"07465",
    "sg:province":"NJ",
    "sg:tags":[
        "house"
    ],
    "wof:name":"Skyview Builders Inc",
    "wof:placetype":"venue"
},
  "geometry": {"coordinates":[-74.28380199999999,41.065563],"type":"Point"}
}