{
  "type": "Feature",
  "properties": {
    "addr:full":"301 Blair Rd Avenel NJ 07001",
    "addr:housenumber":"301",
    "addr:postcode":"07001",
    "addr:street":"Blair Rd",
    "iso:country":"US",
    "sg:address":"301 Blair Rd",
    "sg:city":"Avenel",
    "sg:classifiers":[
        {
            "category":"Building & Trades",
            "subcategory":"Locksmith",
            "type":"Services"
        }
    ],
    "sg:phone":"+1 877 800 1820",
    "sg:postcode":"07001",
    "sg:province":"NJ",
    "sg:tags":[
        "key"
    ],
    "wof:name":"AAA Emergency Locksmith",
    "wof:placetype":"venue"
},
  "geometry": {"coordinates":[-74.25584600000001,40.578103],"type":"Point"}
}