{
  "type": "Feature",
  "properties": {
    "addr:full":"42 Oakwood Ave Kearny NJ 07032",
    "addr:housenumber":"42",
    "addr:postcode":"07032",
    "addr:street":"Oakwood Ave",
    "iso:country":"US",
    "sg:address":"42 Oakwood Ave",
    "sg:city":"Kearny",
    "sg:classifiers":[
        {
            "category":"Shopping",
            "subcategory":"Clothing, Apparel, & Fashions",
            "type":"Retail Goods"
        }
    ],
    "sg:phone":"+1   ",
    "sg:postcode":"07032",
    "sg:province":"NJ",
    "wof:name":"Deva Ravi",
    "wof:placetype":"venue"
},
  "geometry": {"coordinates":[-74.14879000000001,40.769865],"type":"Point"}
}