{
  "type": "Feature",
  "properties": {
    "iso:country":"US",
    "sg:address":"126 Main St",
    "sg:city":"Andover",
    "sg:classifiers":[
        {
            "category":"Shopping",
            "subcategory":"Crafts & Fabrics",
            "type":"Retail Goods"
        }
    ],
    "sg:phone":"+1 973 786 7511",
    "sg:postcode":"07821",
    "sg:province":"NJ",
    "sg:tags":[
        "material",
        "needlework"
    ],
    "wof:name":"Banbury Cross",
    "wof:placetype":"venue"
},
  "geometry": {"coordinates":[-74.742047,40.986301],"type":"Point"}
}