{
  "type": "Feature",
  "properties": {
    "addr:full":"116 US Hwy 46 Rockaway NJ 07866",
    "addr:housenumber":"116",
    "addr:postcode":"07866",
    "addr:street":"Us Hwy 46",
    "iso:country":"US",
    "sg:address":"116 US Hwy 46",
    "sg:city":"Rockaway",
    "sg:classifiers":[
        {
            "category":"Restaurant",
            "type":"Food & Drink"
        }
    ],
    "sg:phone":"+1   ",
    "sg:postcode":"07866",
    "sg:province":"NJ",
    "sg:tags":[
        "caterer"
    ],
    "wof:name":"Septembers",
    "wof:placetype":"venue"
},
  "geometry": {"coordinates":[-74.507266,40.893342],"type":"Point"}
}