{
  "type": "Feature",
  "properties": {
    "addr:full":"820 Spruce St Trenton NJ 08638",
    "addr:housenumber":"820",
    "addr:postcode":"08638",
    "addr:street":"Spruce St",
    "iso:country":"US",
    "sg:address":"820 Spruce St",
    "sg:city":"Trenton",
    "sg:classifiers":[
        {
            "category":"Food & Beverages",
            "subcategory":"Groceries & Convenience Stores",
            "type":"Retail Goods"
        }
    ],
    "sg:phone":"+1   ",
    "sg:postcode":"08638",
    "sg:province":"NJ",
    "wof:name":"Kozik Polish Deli",
    "wof:placetype":"venue"
},
  "geometry": {"coordinates":[-74.748105,40.239127],"type":"Point"}
}