{
  "type": "Feature",
  "properties": {
    "iso:country":"US",
    "sg:address":"4 Scottsdale Ct",
    "sg:city":"Jackson",
    "sg:classifiers":[
        {
            "category":"Professional",
            "subcategory":"Lawyer & Legal Services",
            "type":"Services"
        }
    ],
    "sg:phone":"+1 732 928 1663",
    "sg:postcode":"08527",
    "sg:province":"NJ",
    "wof:name":"ATT Gregory Saffold",
    "wof:placetype":"venue"
},
  "geometry": {"coordinates":[-74.387387,40.150209],"type":"Point"}
}