{
  "type": "Feature",
  "properties": {
    "addr:full":"411 South Ave W Westfield NJ 07090",
    "addr:housenumber":"411",
    "addr:postcode":"07090",
    "addr:street":"South Ave W",
    "iso:country":"US",
    "sg:address":"411 South Ave W",
    "sg:city":"Westfield",
    "sg:classifiers":[
        {
            "category":"Food & Beverages",
            "subcategory":"Specialty",
            "type":"Retail Goods"
        }
    ],
    "sg:phone":"+1   ",
    "sg:postcode":"07090",
    "sg:province":"NJ",
    "sg:tags":[
        "basket",
        "gift"
    ],
    "wof:name":"Classic Basket",
    "wof:placetype":"venue"
},
  "geometry": {"coordinates":[-74.349148,40.648361],"type":"Point"}
}