{
  "type": "Feature",
  "properties": {
    "iso:country":"US",
    "sg:address":"1015 Park Ave",
    "sg:city":"Plainfield",
    "sg:classifiers":[
        {
            "category":"Wholesale",
            "subcategory":"Furniture",
            "type":"Manufacturing & Wholesale Goods"
        }
    ],
    "sg:phone":"+1 908 222 1156",
    "sg:postcode":"07060",
    "sg:province":"NJ",
    "wof:name":"Office Resources & Design Inc",
    "wof:placetype":"venue"
},
  "geometry": {"coordinates":[-74.40919100000001,40.610306],"type":"Point"}
}