{
  "type": "Feature",
  "properties": {
    "addr:full":"53 Campbell Ave Belleville NJ 07109",
    "addr:housenumber":"53",
    "addr:postcode":"07109",
    "addr:street":"Campbell Ave",
    "iso:country":"US",
    "sg:address":"53 Campbell Ave",
    "sg:city":"Belleville",
    "sg:classifiers":[
        {
            "category":"Organizations",
            "subcategory":"Religious Organization",
            "type":"Services"
        }
    ],
    "sg:phone":"+1 973 751 8517",
    "sg:postcode":"07109",
    "sg:province":"NJ",
    "wof:name":"Downes George A Rev",
    "wof:placetype":"venue"
},
  "geometry": {"coordinates":[-74.15450300000001,40.803501],"type":"Point"}
}