{
  "type": "Feature",
  "properties": {
    "addr:full":"6 Hillside Rd Butler NJ 07405",
    "addr:housenumber":"6",
    "addr:postcode":"07405",
    "addr:street":"Hillside Rd",
    "iso:country":"US",
    "sg:address":"6 Hillside Rd",
    "sg:city":"Butler",
    "sg:classifiers":[
        {
            "category":"Personal",
            "type":"Services"
        },
        {
            "category":"Social Services",
            "type":"Services"
        }
    ],
    "sg:phone":"+1 973 838 8375",
    "sg:postcode":"07405",
    "sg:province":"NJ",
    "sg:tags":[
        "counselor",
        "marriage",
        "family"
    ],
    "wof:name":"Center For Optimum Living Inc",
    "wof:placetype":"venue"
},
  "geometry": {"coordinates":[-74.37326899999999,41.003896],"type":"Point"}
}