{
  "type": "Feature",
  "properties": {
    "iso:country":"US",
    "sg:address":"7 Melrose Pl",
    "sg:city":"South River",
    "sg:classifiers":[
        {
            "category":"Professional",
            "subcategory":"Accounting & Tax Preparation",
            "type":"Services"
        }
    ],
    "sg:phone":"+1   ",
    "sg:postcode":"08882",
    "sg:province":"NJ",
    "sg:tags":[
        "for",
        "billing",
        "collection",
        "doctor"
    ],
    "wof:name":"Billing 4 Doctors",
    "wof:placetype":"venue"
},
  "geometry": {"coordinates":[-74.38591,40.441145],"type":"Point"}
}