{
  "type": "Feature",
  "properties": {
    "iso:country":"US",
    "sg:address":"416 Lawton Ave",
    "sg:city":"Cliffside Park",
    "sg:classifiers":[
        {
            "category":"Building & Trades",
            "subcategory":"Construction",
            "type":"Services"
        }
    ],
    "sg:phone":"+1 201 943 3623",
    "sg:postcode":"07010",
    "sg:province":"NJ",
    "sg:tags":[
        "general",
        "contractor"
    ],
    "wof:name":"Quality Plus Construction LLC",
    "wof:placetype":"venue"
},
  "geometry": {"coordinates":[-73.989205,40.828848],"type":"Point"}
}