{
  "type": "Feature",
  "properties": {
    "addr:full":"88 Cemetery Rd Great Meadows NJ 07838",
    "addr:housenumber":"88",
    "addr:postcode":"07838",
    "addr:street":"Cemetery Rd",
    "iso:country":"US",
    "sg:address":"88 Cemetery Rd",
    "sg:city":"Great Meadows",
    "sg:classifiers":[
        {
            "category":"Autos & Motor Vehicles",
            "subcategory":"Fuel & Gas Station",
            "type":"Retail Goods"
        }
    ],
    "sg:phone":"+1 908 637 4357",
    "sg:postcode":"07838",
    "sg:province":"NJ",
    "sg:tags":[
        "oil"
    ],
    "wof:name":"Shell",
    "wof:placetype":"venue"
},
  "geometry": {"coordinates":[-74.896496,40.858171],"type":"Point"}
}