{
  "type": "Feature",
  "properties": {
    "iso:country":"US",
    "sg:address":"144 Belmont Ave",
    "sg:city":"Belleville",
    "sg:classifiers":[
        {
            "category":"Home & Garden",
            "subcategory":"Building Materials",
            "type":"Retail Goods"
        }
    ],
    "sg:phone":"+1 973 759 2840",
    "sg:postcode":"07109",
    "sg:province":"NJ",
    "sg:tags":[
        "glass",
        "window",
        "plate"
    ],
    "wof:name":"Crystal Clear Glass Works",
    "wof:placetype":"venue"
},
  "geometry": {"coordinates":[-74.183528,40.777916],"type":"Point"}
}