{
  "type": "Feature",
  "properties": {
    "addr:full":"688 N Mill Rd Vineland NJ 08360",
    "addr:housenumber":"688",
    "addr:postcode":"08360",
    "addr:street":"N Mill Rd",
    "iso:country":"US",
    "sg:address":"688 N Mill Rd",
    "sg:city":"Vineland",
    "sg:classifiers":[
        {
            "category":"Building & Trades",
            "subcategory":"Plumbing",
            "type":"Services"
        }
    ],
    "sg:phone":"+1 856 691 6691",
    "sg:postcode":"08360",
    "sg:province":"NJ",
    "sg:tags":[
        "plumbing",
        "contractor"
    ],
    "wof:name":"Kisby Shore Corp",
    "wof:placetype":"venue"
},
  "geometry": {"coordinates":[-75.060834,39.49705],"type":"Point"}
}