{
  "type": "Feature",
  "properties": {
    "addr:full":"76 Passaic St Wood Ridge NJ 07075",
    "addr:housenumber":"76",
    "addr:postcode":"07075",
    "addr:street":"Passaic St",
    "iso:country":"US",
    "sg:address":"76 Passaic St",
    "sg:city":"Wood Ridge",
    "sg:classifiers":[
        {
            "category":"Manufacturing",
            "subcategory":"Tools & Machinery",
            "type":"Manufacturing & Wholesale Goods"
        }
    ],
    "sg:phone":"+1 973 777 2900",
    "sg:postcode":"07075",
    "sg:province":"NJ",
    "sg:tags":[
        "measuring",
        "material",
        "temperature"
    ],
    "wof:name":"Springfield Precision Instrmnt",
    "wof:placetype":"venue"
},
  "geometry": {"coordinates":[-74.09204200000001,40.864008],"type":"Point"}
}