{
  "type": "Feature",
  "properties": {
    "addr:full":"167 Vreeland Ave Rutherford NJ 07070",
    "addr:housenumber":"167",
    "addr:postcode":"07070",
    "addr:street":"Vreeland Ave",
    "iso:country":"US",
    "sg:address":"167 Vreeland Ave",
    "sg:city":"Rutherford",
    "sg:classifiers":[
        {
            "category":"Travel",
            "subcategory":"Travel Agent",
            "type":"Entertainment"
        }
    ],
    "sg:phone":"+1 201 933 5252",
    "sg:postcode":"07070",
    "sg:province":"NJ",
    "sg:tags":[
        "agency",
        "bureau"
    ],
    "wof:name":"Regis Travel",
    "wof:placetype":"venue"
},
  "geometry": {"coordinates":[-74.11863700000001,40.827237],"type":"Point"}
}