{
  "type": "Feature",
  "properties": {
    "addr:full":"9 Pittsburgh Ave Piscataway NJ 08854",
    "addr:housenumber":"9",
    "addr:postcode":"08854",
    "addr:street":"Pittsburgh Ave",
    "iso:country":"US",
    "sg:address":"9 Pittsburgh Ave",
    "sg:city":"Piscataway",
    "sg:classifiers":[
        {
            "category":"Building & Trades",
            "subcategory":"Cleaning & Sanitation",
            "type":"Services"
        }
    ],
    "sg:phone":"+1   ",
    "sg:postcode":"08854",
    "sg:province":"NJ",
    "sg:tags":[
        "maintenance"
    ],
    "wof:name":"Heavenly Janitorial Services L",
    "wof:placetype":"venue"
},
  "geometry": {"coordinates":[-74.48841899999999,40.564036],"type":"Point"}
}