{
  "type": "Feature",
  "properties": {
    "iso:country":"US",
    "sg:address":"111 Main St",
    "sg:city":"Chatham",
    "sg:classifiers":[
        {
            "category":"Autos & Motor Vehicles",
            "subcategory":"Fuel & Gas Station",
            "type":"Retail Goods"
        }
    ],
    "sg:phone":"+1 973 701 2217",
    "sg:postcode":"07928",
    "sg:province":"NJ",
    "sg:tags":[
        "repair",
        "oil"
    ],
    "sg:website":"www.chathamshell.com",
    "wof:name":"Chatham Shell",
    "wof:placetype":"venue"
},
  "geometry": {"coordinates":[-74.37629699999999,40.739201],"type":"Point"}
}