{
  "type": "Feature",
  "properties": {
    "addr:full":"151 Main St Eatontown NJ 07724",
    "addr:housenumber":"151",
    "addr:postcode":"07724",
    "addr:street":"Main St",
    "iso:country":"US",
    "sg:address":"151 Main St",
    "sg:city":"Eatontown",
    "sg:classifiers":[
        {
            "category":"Home & Garden",
            "subcategory":"Mobile Homes",
            "type":"Retail Goods"
        }
    ],
    "sg:phone":"+1 732 542 0820",
    "sg:postcode":"07724",
    "sg:province":"NJ",
    "wof:name":"Circle Trailer Sales & Court",
    "wof:placetype":"venue"
},
  "geometry": {"coordinates":[-74.054654,40.297563],"type":"Point"}
}