{
  "type": "Feature",
  "properties": {
    "addr:full":"2 Walling Rd Freehold NJ 07728",
    "addr:housenumber":"2",
    "addr:postcode":"07728",
    "addr:street":"Walling Rd",
    "iso:country":"US",
    "sg:address":"2 Walling Rd",
    "sg:city":"Freehold",
    "sg:classifiers":[
        {
            "category":"Freight",
            "type":"Transportation"
        }
    ],
    "sg:phone":"+1 732 431 0278",
    "sg:postcode":"07728",
    "sg:province":"NJ",
    "wof:name":"Richer Transportation Inc",
    "wof:placetype":"venue"
},
  "geometry": {"coordinates":[-74.224555,40.275901],"type":"Point"}
}