{
  "type": "Feature",
  "properties": {
    "iso:country":"US",
    "sg:address":"925 Main St",
    "sg:city":"Sayreville",
    "sg:classifiers":[
        {
            "category":"Retail",
            "subcategory":"Auto Repair",
            "type":"Services"
        }
    ],
    "sg:phone":"+1 732 721 1010",
    "sg:postcode":"08872",
    "sg:province":"NJ",
    "sg:tags":[
        "body",
        "automobile",
        "painting"
    ],
    "wof:name":"Parlin Collision II",
    "wof:placetype":"venue"
},
  "geometry": {"coordinates":[-74.31384199999999,40.477656],"type":"Point"}
}