{
  "type": "Feature",
  "properties": {
    "iso:country":"US",
    "sg:address":"371 State Rt 17",
    "sg:city":"Mahwah",
    "sg:classifiers":[
        {
            "category":"Wholesale",
            "subcategory":"Office Equipment",
            "type":"Manufacturing & Wholesale Goods"
        },
        {
            "category":"Professional",
            "subcategory":"Printing & Photocopies",
            "type":"Services"
        },
        {
            "category":"Shopping",
            "subcategory":"Computers & Home Electronics",
            "type":"Retail Goods"
        }
    ],
    "sg:phone":"+1 201 684 0900",
    "sg:postcode":"07430",
    "sg:province":"NJ",
    "sg:tags":[
        "scanning",
        "printer",
        "supply",
        "services-commercial",
        "lithographer",
        "plotting"
    ],
    "sg:website":"http://www.globalsoftdigital.com",
    "wof:name":"Global Soft Digital Solutions Incorporated",
    "wof:placetype":"venue"
},
  "geometry": {"coordinates":[-74.151212,41.083681],"type":"Point"}
}