{
  "type": "Feature",
  "properties": {
    "addr:full":"437 US Highway 46 Rockaway NJ 07866",
    "addr:housenumber":"437",
    "addr:postcode":"07866",
    "addr:street":"Us Highway 46",
    "iso:country":"US",
    "sg:address":"437 US Highway 46",
    "sg:city":"Rockaway",
    "sg:classifiers":[
        {
            "category":"Personal",
            "subcategory":"Nail Salon",
            "type":"Services"
        }
    ],
    "sg:phone":"+1 973 537 8060",
    "sg:postcode":"07866",
    "sg:province":"NJ",
    "wof:name":"Attractive Nails",
    "wof:placetype":"venue"
},
  "geometry": {"coordinates":[-74.523903,40.889301],"type":"Point"}
}