{
  "type": "Feature",
  "properties": {
    "addr:full":"202 Carnegie Center Princeton NJ 08540",
    "addr:housenumber":"202",
    "addr:postcode":"08540",
    "addr:street":"Carnegie Center",
    "iso:country":"US",
    "sg:address":"202 Carnegie Center",
    "sg:city":"Princeton",
    "sg:classifiers":[
        {
            "category":"Education",
            "subcategory":"Vocational School",
            "type":"Public Place"
        }
    ],
    "sg:phone":"+1   ",
    "sg:postcode":"08540",
    "sg:province":"NJ",
    "wof:name":"Meditech Media Group",
    "wof:placetype":"venue"
},
  "geometry": {"coordinates":[-74.651031,40.317676],"type":"Point"}
}