{
  "type": "Feature",
  "properties": {
    "addr:full":"146 N Main St Manville NJ 08835",
    "addr:housenumber":"146",
    "addr:postcode":"08835",
    "addr:street":"N Main St",
    "iso:country":"US",
    "sg:address":"146 N Main St",
    "sg:city":"Manville",
    "sg:classifiers":[
        {
            "category":"Personal",
            "subcategory":"Beauty Salon",
            "type":"Services"
        }
    ],
    "sg:phone":"+1 908 707 0006",
    "sg:postcode":"08835",
    "sg:province":"NJ",
    "sg:website":"www.greatclips.com",
    "wof:name":"Great Clips",
    "wof:placetype":"venue"
},
  "geometry": {"coordinates":[-74.58647000000001,40.546999],"type":"Point"}
}