{
  "type": "Feature",
  "properties": {
    "addr:full":"81 Mount Hope Ave Dover NJ 07801",
    "addr:housenumber":"81",
    "addr:postcode":"07801",
    "addr:street":"Mount Hope Ave",
    "iso:country":"US",
    "sg:address":"81 Mount Hope Ave",
    "sg:city":"Dover",
    "sg:classifiers":[
        {
            "category":"Building & Trades",
            "subcategory":"Construction",
            "type":"Services"
        }
    ],
    "sg:phone":"+1 973 328 0859",
    "sg:postcode":"07801",
    "sg:province":"NJ",
    "sg:tags":[
        "house"
    ],
    "wof:name":"Black Sea Construction Inc",
    "wof:placetype":"venue"
},
  "geometry": {"coordinates":[-74.555964,40.889681],"type":"Point"}
}