{
  "type": "Feature",
  "properties": {
    "addr:full":"654 Lacey Rd Forked River NJ 08731",
    "addr:housenumber":"654",
    "addr:postcode":"08731",
    "addr:street":"Lacey Rd",
    "iso:country":"US",
    "sg:address":"654 Lacey Rd",
    "sg:city":"Forked River",
    "sg:classifiers":[
        {
            "category":"Professional",
            "subcategory":"Lawyer & Legal Services",
            "type":"Services"
        }
    ],
    "sg:phone":"+1   ",
    "sg:postcode":"08731",
    "sg:province":"NJ",
    "wof:name":"Axelrod Levinson PC",
    "wof:placetype":"venue"
},
  "geometry": {"coordinates":[-74.20269999999999,39.856266],"type":"Point"}
}