{
  "type": "Feature",
  "properties": {
    "iso:country":"US",
    "sg:address":"One Tower Center Fourteenth Floor",
    "sg:city":"East Brunswick",
    "sg:classifiers":[
        {
            "category":"Professional",
            "subcategory":"Research",
            "type":"Services"
        }
    ],
    "sg:phone":"+1 732 418 9300",
    "sg:postcode":"08816",
    "sg:province":"NJ",
    "sg:website":"http://www.savientpharma.com",
    "wof:name":"Savient Pharmaceuticals",
    "wof:placetype":"venue"
},
  "geometry": {"coordinates":[-74.409131,40.478662],"type":"Point"}
}