{
  "type": "Feature",
  "properties": {
    "iso:country":"US",
    "sg:address":"30 Greenvale Rd",
    "sg:city":"Cherry Hill",
    "sg:classifiers":[
        {
            "category":"Utilities",
            "subcategory":"Telephone",
            "type":"Services"
        }
    ],
    "sg:phone":"+1 856 482 8581",
    "sg:postcode":"08034",
    "sg:province":"NJ",
    "sg:tags":[
        "telecommunication"
    ],
    "wof:name":"Mkc Communications",
    "wof:placetype":"venue"
},
  "geometry": {"coordinates":[-74.982553,39.919717],"type":"Point"}
}