{
  "type": "Feature",
  "properties": {
    "addr:full":"99 E Granada Dr Brick NJ 08723",
    "addr:housenumber":"99",
    "addr:postcode":"08723",
    "addr:street":"E Granada Dr",
    "iso:country":"US",
    "sg:address":"99 E Granada Dr",
    "sg:city":"Brick",
    "sg:classifiers":[
        {
            "category":"Shopping",
            "subcategory":"Bicycles & Sporting Goods",
            "type":"Retail Goods"
        }
    ],
    "sg:phone":"+1   ",
    "sg:postcode":"08723",
    "sg:province":"NJ",
    "wof:name":"Bodyworks Massage & Sport",
    "wof:placetype":"venue"
},
  "geometry": {"coordinates":[-74.084687,40.023664],"type":"Point"}
}