{
  "type": "Feature",
  "properties": {
    "iso:country":"US",
    "sg:address":"354 State Route 10",
    "sg:city":"East Hanover",
    "sg:classifiers":[
        {
            "category":"Restaurant",
            "type":"Food & Drink"
        }
    ],
    "sg:phone":"+1 973 515 0023",
    "sg:postcode":"07936",
    "sg:province":"NJ",
    "wof:name":"New Chun Bo Restaurant",
    "wof:placetype":"venue"
},
  "geometry": {"coordinates":[-74.363899,40.803398],"type":"Point"}
}