{
  "type": "Feature",
  "properties": {
    "iso:country":"US",
    "sg:address":"350 Passaic Ave",
    "sg:city":"Fairfield",
    "sg:classifiers":[
        {
            "category":"Insurance",
            "subcategory":"Insurance Agent",
            "type":"Services"
        }
    ],
    "sg:phone":"+1   ",
    "sg:postcode":"07004",
    "sg:province":"NJ",
    "sg:tags":[
        "agency",
        "general"
    ],
    "wof:name":"Ross & Co",
    "wof:placetype":"venue"
},
  "geometry": {"coordinates":[-74.273037,40.887673],"type":"Point"}
}