{
  "type": "Feature",
  "properties": {
    "iso:country":"US",
    "sg:address":"120 N High St",
    "sg:city":"Millville",
    "sg:classifiers":[
        {
            "category":"Professional",
            "subcategory":"Accounting & Tax Preparation",
            "type":"Services"
        }
    ],
    "sg:phone":"+1 856 825 7795",
    "sg:postcode":"08332",
    "sg:province":"NJ",
    "sg:tags":[
        "bookkeeping",
        "general"
    ],
    "wof:name":"Van Hook Enterprises",
    "wof:placetype":"venue"
},
  "geometry": {"coordinates":[-75.038543,39.397073],"type":"Point"}
}