{
  "type": "Feature",
  "properties": {
    "addr:full":"1007 S Black Horse Pike Blackwood NJ 08012",
    "addr:housenumber":"1007",
    "addr:postcode":"08012",
    "addr:street":"S Black Horse Pike",
    "iso:country":"US",
    "sg:address":"1007 S Black Horse Pike",
    "sg:city":"Blackwood",
    "sg:classifiers":[
        {
            "category":"Bars & Pubs",
            "type":"Food & Drink"
        }
    ],
    "sg:phone":"+1 856 227 0770",
    "sg:postcode":"08012",
    "sg:province":"NJ",
    "wof:name":"Sam's Bar & Grille",
    "wof:placetype":"venue"
},
  "geometry": {"coordinates":[-75.057058,39.787459],"type":"Point"}
}