{
  "type": "Feature",
  "properties": {
    "iso:country":"US",
    "sg:address":"278 Broadway",
    "sg:city":"Elmwood Park",
    "sg:classifiers":[
        {
            "category":"Professional",
            "subcategory":"Lawyer & Legal Services",
            "type":"Services"
        }
    ],
    "sg:phone":"+1 201 791 4888",
    "sg:postcode":"07407",
    "sg:province":"NJ",
    "wof:name":"Burstein Noah M Attrney At Law",
    "wof:placetype":"venue"
},
  "geometry": {"coordinates":[-74.119235,40.920656],"type":"Point"}
}