{
  "type": "Feature",
  "properties": {
    "addr:full":"1710 Rue Mirador Point Pleasant Beach NJ 08742",
    "addr:housenumber":"1710",
    "addr:postcode":"08742",
    "addr:street":"Rue Mirador",
    "iso:country":"US",
    "sg:address":"1710 Rue Mirador",
    "sg:city":"Point Pleasant Beach",
    "sg:classifiers":[
        {
            "category":"Building & Trades",
            "subcategory":"Construction",
            "type":"Services"
        }
    ],
    "sg:phone":"+1 732 899 6329",
    "sg:postcode":"08742",
    "sg:province":"NJ",
    "sg:tags":[
        "house"
    ],
    "wof:name":"Jack Vitale Jr",
    "wof:placetype":"venue"
},
  "geometry": {"coordinates":[-74.058207,40.063364],"type":"Point"}
}