{
  "type": "Feature",
  "properties": {
    "addr:full":"231 Throckmorton St Freehold NJ 07728",
    "addr:housenumber":"231",
    "addr:postcode":"07728",
    "addr:street":"Throckmorton St",
    "iso:country":"US",
    "sg:address":"231 Throckmorton St",
    "sg:city":"Freehold",
    "sg:classifiers":[
        {
            "category":"Shopping",
            "subcategory":"Jewelry",
            "type":"Retail Goods"
        }
    ],
    "sg:phone":"+1 732 431 0012",
    "sg:postcode":"07728",
    "sg:province":"NJ",
    "sg:tags":[
        "jeweler"
    ],
    "wof:name":"Agnos Jeweler",
    "wof:placetype":"venue"
},
  "geometry": {"coordinates":[-74.285946,40.264971],"type":"Point"}
}