{
  "type": "Feature",
  "properties": {
    "addr:full":"819 New Rd Northfield NJ 08225",
    "addr:housenumber":"819",
    "addr:postcode":"08225",
    "addr:street":"New Rd",
    "iso:country":"US",
    "sg:address":"819 New Rd",
    "sg:city":"Northfield",
    "sg:classifiers":[
        {
            "category":"Building & Trades",
            "subcategory":"Construction",
            "type":"Services"
        }
    ],
    "sg:phone":"+1 609 822 5018",
    "sg:postcode":"08225",
    "sg:province":"NJ",
    "sg:tags":[
        "masonry",
        "contractor"
    ],
    "wof:name":"Peterson Brickwork Inc",
    "wof:placetype":"venue"
},
  "geometry": {"coordinates":[-74.550721,39.377912],"type":"Point"}
}