{
  "type": "Feature",
  "properties": {
    "addr:full":"250 Skillman Rd Skillman NJ 08558",
    "addr:housenumber":"250",
    "addr:postcode":"08558",
    "addr:street":"Skillman Rd",
    "iso:country":"US",
    "sg:address":"250 Skillman Rd",
    "sg:city":"Skillman",
    "sg:classifiers":[
        {
            "category":"Professional",
            "subcategory":"Business Services",
            "type":"Services"
        },
        {
            "category":"Building & Trades",
            "subcategory":"Construction",
            "type":"Services"
        }
    ],
    "sg:phone":"+1 609 921 6468",
    "sg:postcode":"08558",
    "sg:province":"NJ",
    "sg:tags":[
        "consultant",
        "contractor",
        "design",
        "painter",
        "hanging",
        "interior",
        "decorator"
    ],
    "wof:name":"B R Perone Painting & Dcrtng",
    "wof:placetype":"venue"
},
  "geometry": {"coordinates":[-74.69838,40.421666],"type":"Point"}
}