{
  "type": "Feature",
  "properties": {
    "iso:country":"US",
    "sg:address":"26 4th St",
    "sg:city":"Park Ridge",
    "sg:classifiers":[
        {
            "category":"Wholesale",
            "subcategory":"Machinery & Supplies",
            "type":"Manufacturing & Wholesale Goods"
        }
    ],
    "sg:phone":"+1 201 476 9155",
    "sg:postcode":"07656",
    "sg:province":"NJ",
    "sg:tags":[
        "equipment",
        "industrial"
    ],
    "wof:name":"Colortech",
    "wof:placetype":"venue"
},
  "geometry": {"coordinates":[-74.048073,41.036739],"type":"Point"}
}