{
  "type": "Feature",
  "properties": {
    "addr:full":"94 Old Short Hills Rd Livingston NJ 07039",
    "addr:housenumber":"94",
    "addr:postcode":"07039",
    "addr:street":"Old Short Hills Rd",
    "iso:country":"US",
    "sg:address":"94 Old Short Hills Rd",
    "sg:city":"Livingston",
    "sg:classifiers":[
        {
            "category":"Health Services",
            "subcategory":"Hospital",
            "type":"Services"
        }
    ],
    "sg:phone":"+1 973 533 5000",
    "sg:postcode":"07039",
    "sg:province":"NJ",
    "sg:tags":[
        "medical",
        "general"
    ],
    "wof:name":"Saint Barnabas Hospital",
    "wof:placetype":"venue"
},
  "geometry": {"coordinates":[-74.304073,40.760114],"type":"Point"}
}