{
  "type": "Feature",
  "properties": {
    "iso:country":"US",
    "sg:address":"303 Spier Ave",
    "sg:city":"Allenhurst",
    "sg:classifiers":[
        {
            "category":"Wholesale",
            "subcategory":"Sporting Goods",
            "type":"Manufacturing & Wholesale Goods"
        }
    ],
    "sg:phone":"+1 732 531 4929",
    "sg:postcode":"07711",
    "sg:province":"NJ",
    "sg:tags":[
        "equipment",
        "pool",
        "swimming"
    ],
    "wof:name":"Liner Specialist",
    "wof:placetype":"venue"
},
  "geometry": {"coordinates":[-74.005768,40.238053],"type":"Point"}
}