{
  "type": "Feature",
  "properties": {
    "addr:full":"574 Newark Pompton Tpke Pompton Plains NJ 07444",
    "addr:housenumber":"574",
    "addr:postcode":"07444",
    "addr:street":"Newark Pompton Tpke",
    "iso:country":"US",
    "sg:address":"574 Newark Pompton Tpke",
    "sg:city":"Pompton Plains",
    "sg:classifiers":[
        {
            "category":"Shopping",
            "subcategory":"Bicycles & Sporting Goods",
            "type":"Retail Goods"
        }
    ],
    "sg:phone":"+1 973 839 5305",
    "sg:postcode":"07444",
    "sg:province":"NJ",
    "wof:name":"Marco's Sports",
    "wof:placetype":"venue"
},
  "geometry": {"coordinates":[-74.295601,40.967098],"type":"Point"}
}