{
  "type": "Feature",
  "properties": {
    "iso:country":"US",
    "sg:address":"1177 Main St",
    "sg:city":"Boonton",
    "sg:classifiers":[
        {
            "category":"Retail",
            "subcategory":"Auto Repair",
            "type":"Services"
        }
    ],
    "sg:phone":"+1   ",
    "sg:postcode":"07005",
    "sg:province":"NJ",
    "sg:tags":[
        "installs",
        "automobile",
        "accessory"
    ],
    "wof:name":"Air & Sound Installation Ctr",
    "wof:placetype":"venue"
},
  "geometry": {"coordinates":[-74.415347,40.907495],"type":"Point"}
}