{
  "type": "Feature",
  "properties": {
    "iso:country":"US",
    "sg:address":"371 Essex Rd",
    "sg:city":"Neptune",
    "sg:classifiers":[
        {
            "category":"Manufacturing",
            "subcategory":"Signs",
            "type":"Manufacturing & Wholesale Goods"
        },
        {
            "category":"Professional",
            "subcategory":"Advertising",
            "type":"Services"
        }
    ],
    "sg:phone":"+1 732 918 6600",
    "sg:postcode":"07753",
    "sg:province":"NJ",
    "sg:tags":[
        "designer",
        "producer",
        "mfg",
        "fixture",
        "display",
        "store"
    ],
    "wof:name":"Renaissance Display Company",
    "wof:placetype":"venue"
},
  "geometry": {"coordinates":[-74.09090999999999,40.232953],"type":"Point"}
}