{
  "type": "Feature",
  "properties": {
    "addr:full":"3 Cooper Plz Camden NJ 08103",
    "addr:housenumber":"3",
    "addr:postcode":"08103",
    "addr:street":"Cooper Plz",
    "iso:country":"US",
    "sg:address":"3 Cooper Plz",
    "sg:city":"Camden",
    "sg:classifiers":[
        {
            "category":"Health Services",
            "subcategory":"Doctor",
            "type":"Services"
        }
    ],
    "sg:phone":"+1 856 342 2141",
    "sg:postcode":"08103",
    "sg:province":"NJ",
    "wof:name":"Marra Steven MD",
    "wof:placetype":"venue"
},
  "geometry": {"coordinates":[-75.11579500000001,39.940925],"type":"Point"}
}