{
  "type": "Feature",
  "properties": {
    "addr:full":"32 Morrissee Ave Exd Haledon NJ 07508",
    "addr:housenumber":"32",
    "addr:postcode":"07508",
    "addr:street":"Morrissee Ave Exd",
    "iso:country":"US",
    "sg:address":"32 Morrissee Ave Exd",
    "sg:city":"Haledon",
    "sg:classifiers":[
        {
            "category":"Recreation",
            "type":"Entertainment"
        }
    ],
    "sg:phone":"+1 973 942 4483",
    "sg:postcode":"07508",
    "sg:province":"NJ",
    "sg:tags":[
        "club",
        "membership"
    ],
    "wof:name":"Haledon Benefit & Social Club",
    "wof:placetype":"venue"
},
  "geometry": {"coordinates":[-74.18509899999999,40.933462],"type":"Point"}
}