{
  "type": "Feature",
  "properties": {
    "addr:full":"524 Tindall Ave Trenton NJ 08610",
    "addr:housenumber":"524",
    "addr:postcode":"08610",
    "addr:street":"Tindall Ave",
    "iso:country":"US",
    "sg:address":"524 Tindall Ave",
    "sg:city":"Trenton",
    "sg:classifiers":[
        {
            "category":"Manufacturing",
            "subcategory":"Jewelry",
            "type":"Manufacturing & Wholesale Goods"
        }
    ],
    "sg:phone":"+1 609 396 1577",
    "sg:postcode":"08610",
    "sg:province":"NJ",
    "sg:tags":[
        "synthetic",
        "bearing",
        "jewel",
        "mfg"
    ],
    "wof:name":"Aurele M Gatti Inc",
    "wof:placetype":"venue"
},
  "geometry": {"coordinates":[-74.730936,40.214557],"type":"Point"}
}