{
  "type": "Feature",
  "properties": {
    "addr:full":"111 Haytown Rd Lebanon NJ 08833",
    "addr:housenumber":"111",
    "addr:postcode":"08833",
    "addr:street":"Haytown Rd",
    "iso:country":"US",
    "sg:address":"111 Haytown Rd",
    "sg:city":"Lebanon",
    "sg:classifiers":[
        {
            "category":"Home & Garden",
            "subcategory":"Home Furnishings",
            "type":"Retail Goods"
        }
    ],
    "sg:phone":"+1   ",
    "sg:postcode":"08833",
    "sg:province":"NJ",
    "wof:name":"All About Windows",
    "wof:placetype":"venue"
},
  "geometry": {"coordinates":[-74.85235,40.668502],"type":"Point"}
}