{
  "type": "Feature",
  "properties": {
    "iso:country":"US",
    "sg:address":"1 Carmen Ct",
    "sg:city":"Spring Valley",
    "sg:classifiers":[
        {
            "category":"Building & Trades",
            "subcategory":"Landscaping Services",
            "type":"Services"
        }
    ],
    "sg:phone":"+1 845 353 6414",
    "sg:postcode":"10977",
    "sg:province":"NY",
    "sg:tags":[
        "landscape",
        "contractor"
    ],
    "wof:name":"Rick's Landscaping",
    "wof:placetype":"venue"
},
  "geometry": {"coordinates":[-74.066628,41.09214],"type":"Point"}
}