{
  "type": "Feature",
  "properties": {
    "iso:country":"US",
    "sg:address":"267 Myrtle Ave",
    "sg:city":"Boonton",
    "sg:classifiers":[
        {
            "category":"Retail",
            "subcategory":"Auto Repair",
            "type":"Services"
        }
    ],
    "sg:phone":"+1 973 334 9593",
    "sg:postcode":"07005",
    "sg:province":"NJ",
    "sg:tags":[
        "repairing",
        "automobile",
        "general"
    ],
    "wof:name":"Grieco Brothers Automotive Inc",
    "wof:placetype":"venue"
},
  "geometry": {"coordinates":[-74.398883,40.906796],"type":"Point"}
}