{
  "type": "Feature",
  "properties": {
    "addr:full":"44 Paterson Ave West Paterson NJ 07424",
    "addr:housenumber":"44",
    "addr:postcode":"07424",
    "addr:street":"Paterson Ave West",
    "iso:country":"US",
    "sg:address":"44 Paterson Ave",
    "sg:city":"West Paterson",
    "sg:classifiers":[
        {
            "category":"Social Services",
            "subcategory":"Child Care",
            "type":"Services"
        }
    ],
    "sg:phone":"+1 973 279 3966",
    "sg:postcode":"07424",
    "sg:province":"NJ",
    "sg:tags":[
        "kindergarten",
        "academic",
        "school"
    ],
    "sg:website":"www.nj4c.org",
    "wof:name":"Berkley College Child Care Ctr",
    "wof:placetype":"venue"
},
  "geometry": {"coordinates":[-74.225775,40.882387],"type":"Point"}
}