{
  "type": "Feature",
  "properties": {
    "addr:full":"70 Armour Ave Trenton NJ 08619",
    "addr:housenumber":"70",
    "addr:postcode":"08619",
    "addr:street":"Armour Ave",
    "iso:country":"US",
    "sg:address":"70 Armour Ave",
    "sg:city":"Trenton",
    "sg:classifiers":[
        {
            "category":"Retail",
            "subcategory":"Repair Shop",
            "type":"Services"
        }
    ],
    "sg:phone":"+1   ",
    "sg:postcode":"08619",
    "sg:province":"NJ",
    "wof:name":"Gregs Lock & Key Service",
    "wof:placetype":"venue"
},
  "geometry": {"coordinates":[-74.707345,40.236538],"type":"Point"}
}