{
  "type": "Feature",
  "properties": {
    "addr:full":"1 Westwood Ave Westwood NJ 07675",
    "addr:housenumber":"1",
    "addr:postcode":"07675",
    "addr:street":"Westwood Ave",
    "iso:country":"US",
    "sg:address":"1 Westwood Ave",
    "sg:city":"Westwood",
    "sg:classifiers":[
        {
            "category":"Banks & Credit Unions",
            "subcategory":"Bank",
            "type":"Services"
        }
    ],
    "sg:phone":"+1 201 000 1111",
    "sg:postcode":"07675",
    "sg:province":"NJ",
    "wof:name":"Bank Of America",
    "wof:placetype":"venue"
},
  "geometry": {"coordinates":[-74.032819,40.991292],"type":"Point"}
}