{
  "type": "Feature",
  "properties": {
    "addr:full":"1000 Main St Voorhees NJ 08043",
    "addr:housenumber":"1000",
    "addr:postcode":"08043",
    "addr:street":"Main St",
    "iso:country":"US",
    "sg:address":"1000 Main St",
    "sg:city":"Voorhees",
    "sg:classifiers":[
        {
            "category":"Wholesale",
            "subcategory":"Groceries",
            "type":"Manufacturing & Wholesale Goods"
        }
    ],
    "sg:phone":"+1 856 751 1474",
    "sg:postcode":"08043",
    "sg:province":"NJ",
    "wof:name":"Ub North America Inc",
    "wof:placetype":"venue"
},
  "geometry": {"coordinates":[-74.94753,39.867018],"type":"Point"}
}