{
  "type": "Feature",
  "properties": {
    "iso:country":"US",
    "sg:address":"67 Church St",
    "sg:city":"Flemington",
    "sg:classifiers":[
        {
            "category":"Shopping",
            "subcategory":"Clothing, Apparel, & Fashions",
            "type":"Retail Goods"
        }
    ],
    "sg:phone":"+1   ",
    "sg:postcode":"08822",
    "sg:province":"NJ",
    "sg:tags":[
        "family"
    ],
    "wof:name":"Levis Outlet By Designs 966",
    "wof:placetype":"venue"
},
  "geometry": {"coordinates":[-74.852313,40.505846],"type":"Point"}
}