{
  "type": "Feature",
  "properties": {
    "addr:full":"5309 Atlantic Ave Ventnor City NJ 08406",
    "addr:housenumber":"5309",
    "addr:postcode":"08406",
    "addr:street":"Atlantic Ave",
    "iso:country":"US",
    "sg:address":"5309 Atlantic Ave",
    "sg:city":"Ventnor City",
    "sg:classifiers":[
        {
            "category":"Insurance",
            "subcategory":"Insurance Agent",
            "type":"Services"
        }
    ],
    "sg:phone":"+1 609 677 0088",
    "sg:postcode":"08406",
    "sg:province":"NJ",
    "sg:tags":[
        "processing"
    ],
    "wof:name":"GMP Claims Specialists",
    "wof:placetype":"venue"
},
  "geometry": {"coordinates":[-74.471715,39.341481],"type":"Point"}
}