{
  "type": "Feature",
  "properties": {
    "iso:country":"US",
    "sg:address":"343 Elliot Pl",
    "sg:city":"Paramus",
    "sg:classifiers":[
        {
            "category":"Manufacturing",
            "subcategory":"Paper Products",
            "type":"Manufacturing & Wholesale Goods"
        },
        {
            "category":"Manufacturing",
            "subcategory":"Printing",
            "type":"Manufacturing & Wholesale Goods"
        }
    ],
    "sg:phone":"+1 201 599 0909",
    "sg:postcode":"07652",
    "sg:province":"NJ",
    "sg:tags":[
        "lithographic",
        "commercial",
        "label"
    ],
    "sg:website":"www.labelsolutions.net",
    "wof:name":"Label Solutions Inc",
    "wof:placetype":"venue"
},
  "geometry": {"coordinates":[-74.05761800000001,40.940625],"type":"Point"}
}