{
  "type": "Feature",
  "properties": {
    "addr:full":"1301 N East Blvd Vineland NJ 08360",
    "addr:housenumber":"1301",
    "addr:postcode":"08360",
    "addr:street":"N East Blvd",
    "iso:country":"US",
    "sg:address":"1301 N East Blvd",
    "sg:city":"Vineland",
    "sg:classifiers":[
        {
            "category":"Real Estate",
            "subcategory":"Real Estate Operator",
            "type":"Services"
        }
    ],
    "sg:phone":"+1   ",
    "sg:postcode":"08360",
    "sg:province":"NJ",
    "sg:tags":[
        "park",
        "trailer"
    ],
    "wof:name":"Happy Acres Mobile Park",
    "wof:placetype":"venue"
},
  "geometry": {"coordinates":[-75.024389,39.505029],"type":"Point"}
}