{
  "type": "Feature",
  "properties": {
    "iso:country":"US",
    "sg:address":"261 Page Ave",
    "sg:city":"Lyndhurst",
    "sg:classifiers":[
        {
            "category":"Social Services",
            "type":"Services"
        }
    ],
    "sg:phone":"+1 201 804 0415",
    "sg:postcode":"07071",
    "sg:province":"NJ",
    "wof:name":"Parents Without Partners",
    "wof:placetype":"venue"
},
  "geometry": {"coordinates":[-74.132661,40.810876],"type":"Point"}
}