{
  "type": "Feature",
  "properties": {
    "iso:country":"US",
    "sg:address":"22 Palisade Ter",
    "sg:city":"Edgewater",
    "sg:classifiers":[
        {
            "category":"Professional",
            "subcategory":"Engineering",
            "type":"Services"
        }
    ],
    "sg:phone":"+1 201 750 7888",
    "sg:postcode":"07020",
    "sg:province":"NJ",
    "sg:tags":[
        "engineer"
    ],
    "wof:name":"Maxieg",
    "wof:placetype":"venue"
},
  "geometry": {"coordinates":[-73.96938,40.842555],"type":"Point"}
}