{
  "type": "Feature",
  "properties": {
    "addr:full":"15 Main St Hackensack NJ 07601",
    "addr:housenumber":"15",
    "addr:postcode":"07601",
    "addr:street":"Main St",
    "iso:country":"US",
    "sg:address":"15 Main St",
    "sg:city":"Hackensack",
    "sg:classifiers":[
        {
            "category":"Banks & Credit Unions",
            "subcategory":"Bank",
            "type":"Services"
        }
    ],
    "sg:phone":"+1   ",
    "sg:postcode":"07601",
    "sg:province":"NJ",
    "sg:tags":[
        "state",
        "commercial"
    ],
    "wof:name":"Fleet",
    "wof:placetype":"venue"
},
  "geometry": {"coordinates":[-74.044487,40.878928],"type":"Point"}
}