{
  "type": "Feature",
  "properties": {
    "addr:full":"53 Passaic Ave Passaic NJ 07055",
    "addr:housenumber":"53",
    "addr:postcode":"07055",
    "addr:street":"Passaic Ave",
    "iso:country":"US",
    "sg:address":"53 Passaic Ave",
    "sg:city":"Passaic",
    "sg:classifiers":[
        {
            "category":"Health Services",
            "subcategory":"Doctor",
            "type":"Services"
        }
    ],
    "sg:phone":"+1 973 471 4440",
    "sg:postcode":"07055",
    "sg:province":"NJ",
    "wof:name":"Ahmadi Cyrus MD",
    "wof:placetype":"venue"
},
  "geometry": {"coordinates":[-74.127403,40.858101],"type":"Point"}
}