{
  "type": "Feature",
  "properties": {
    "addr:full":"25 Castle Ave Jackson NJ 08527",
    "addr:housenumber":"25",
    "addr:postcode":"08527",
    "addr:street":"Castle Ave",
    "iso:country":"US",
    "sg:address":"25 Castle Ave",
    "sg:city":"Jackson",
    "sg:classifiers":[
        {
            "category":"Arts & Performance",
            "subcategory":"Theater",
            "type":"Entertainment"
        }
    ],
    "sg:phone":"+1   ",
    "sg:postcode":"08527",
    "sg:province":"NJ",
    "sg:tags":[
        "group"
    ],
    "wof:name":"Soundman Disc Jockeys",
    "wof:placetype":"venue"
},
  "geometry": {"coordinates":[-74.29292100000001,40.117382],"type":"Point"}
}