{
  "type": "Feature",
  "properties": {
    "iso:country":"US",
    "sg:address":"180 East St",
    "sg:city":"Colonia",
    "sg:classifiers":[
        {
            "category":"Education",
            "subcategory":"School",
            "type":"Public Place"
        }
    ],
    "sg:phone":"+1   ",
    "sg:postcode":"07067",
    "sg:province":"NJ",
    "wof:name":"Colonia High School",
    "wof:placetype":"venue"
},
  "geometry": {"coordinates":[-74.319802,40.593253],"type":"Point"}
}