{
  "type": "Feature",
  "properties": {
    "addr:full":"1505 Rancocas Rd Burlington NJ 08016",
    "addr:housenumber":"1505",
    "addr:postcode":"08016",
    "addr:street":"Rancocas Rd",
    "iso:country":"US",
    "sg:address":"1505 Rancocas Rd",
    "sg:city":"Burlington",
    "sg:classifiers":[
        {
            "category":"Home & Garden",
            "subcategory":"Building Materials",
            "type":"Retail Goods"
        }
    ],
    "sg:phone":"+1 609 386 0266",
    "sg:postcode":"08016",
    "sg:province":"NJ",
    "sg:tags":[
        "hardware",
        "lumber",
        "store"
    ],
    "sg:website":"www.cbm1946.com",
    "wof:name":"Construction Building Materials",
    "wof:placetype":"venue"
},
  "geometry": {"coordinates":[-74.850403,40.057598],"type":"Point"}
}