{
  "type": "Feature",
  "properties": {
    "addr:full":"776 S White Horse Pike Audubon NJ 08106",
    "addr:housenumber":"776",
    "addr:postcode":"08106",
    "addr:street":"S White Horse Pike",
    "iso:country":"US",
    "sg:address":"776 S White Horse Pike",
    "sg:city":"Audubon",
    "sg:classifiers":[
        {
            "category":"Professional",
            "subcategory":"Lawyer & Legal Services",
            "type":"Services"
        }
    ],
    "sg:phone":"+1 856 547 5370",
    "sg:postcode":"08106",
    "sg:province":"NJ",
    "sg:tags":[
        "attorney"
    ],
    "wof:name":"Timothy P Reilly",
    "wof:placetype":"venue"
},
  "geometry": {"coordinates":[-75.061116,39.887009],"type":"Point"}
}