{
  "type": "Feature",
  "properties": {
    "addr:full":"21 Ernston Rd Parlin NJ 08859",
    "addr:housenumber":"21",
    "addr:postcode":"08859",
    "addr:street":"Ernston Rd",
    "iso:country":"US",
    "sg:address":"21 Ernston Rd",
    "sg:city":"Parlin",
    "sg:classifiers":[
        {
            "category":"Health Services",
            "subcategory":"Doctor",
            "type":"Services"
        }
    ],
    "sg:phone":"+1 732 727 9310",
    "sg:postcode":"08859",
    "sg:province":"NJ",
    "wof:name":"Joseph C Molino DDS",
    "wof:placetype":"venue"
},
  "geometry": {"coordinates":[-74.31350999999999,40.46415],"type":"Point"}
}