{
  "type": "Feature",
  "properties": {
    "iso:country":"US",
    "sg:address":"405 State Rte 18",
    "sg:city":"East Brunswick",
    "sg:classifiers":[
        {
            "category":"Health Services",
            "subcategory":"Clinic",
            "type":"Services"
        },
        {
            "category":"Sports & Exercise",
            "subcategory":"Gym",
            "type":"Entertainment"
        }
    ],
    "sg:phone":"+1 732 613 6331",
    "sg:postcode":"08816",
    "sg:province":"NJ",
    "sg:tags":[
        "club",
        "home",
        "studio",
        "gymnasium",
        "care"
    ],
    "wof:name":"American Woman Fitness Centers",
    "wof:placetype":"venue"
},
  "geometry": {"coordinates":[-74.389832,40.42218],"type":"Point"}
}