{
  "type": "Feature",
  "properties": {
    "iso:country":"US",
    "sg:address":"35 New Star Ridge Rd",
    "sg:city":"Sparta",
    "sg:classifiers":[
        {
            "category":"Shopping",
            "subcategory":"Hobbies, Toys, & Games",
            "type":"Retail Goods"
        }
    ],
    "sg:phone":"+1 973 729 5699",
    "sg:postcode":"07871",
    "sg:province":"NJ",
    "sg:tags":[
        "equipment",
        "video",
        "rental"
    ],
    "wof:name":"Audio Visual Assoc Inc",
    "wof:placetype":"venue"
},
  "geometry": {"coordinates":[-74.635881,40.999163],"type":"Point"}
}