{
  "type": "Feature",
  "properties": {
    "addr:full":"19 Troy Dr Livingston NJ 07039",
    "addr:housenumber":"19",
    "addr:postcode":"07039",
    "addr:street":"Troy Dr",
    "iso:country":"US",
    "sg:address":"19 Troy Dr",
    "sg:city":"Livingston",
    "sg:classifiers":[
        {
            "category":"Manufacturing",
            "subcategory":"Apparel",
            "type":"Manufacturing & Wholesale Goods"
        },
        {
            "category":"Shopping",
            "subcategory":"Clothing, Apparel, & Fashions",
            "type":"Retail Goods"
        }
    ],
    "sg:phone":"+1 973 740 9494",
    "sg:postcode":"07039",
    "sg:province":"NJ",
    "sg:tags":[
        "manufacture",
        "item",
        "boutique",
        "woman"
    ],
    "sg:website":"www.tinabobker.com",
    "wof:name":"Tina Bobker's Artcessories",
    "wof:placetype":"venue"
},
  "geometry": {"coordinates":[-74.30036,40.801532],"type":"Point"}
}