{
  "type": "Feature",
  "properties": {
    "addr:full":"1 Woodside Rd Springfield NJ 07081",
    "addr:housenumber":"1",
    "addr:postcode":"07081",
    "addr:street":"Woodside Rd",
    "iso:country":"US",
    "sg:address":"1 Woodside Rd",
    "sg:city":"Springfield",
    "sg:classifiers":[
        {
            "category":"Building & Trades",
            "subcategory":"Construction",
            "type":"Services"
        }
    ],
    "sg:phone":"+1 973 564 6485",
    "sg:postcode":"07081",
    "sg:province":"NJ",
    "sg:tags":[
        "house"
    ],
    "wof:name":"Bronsteins Construction Inc",
    "wof:placetype":"venue"
},
  "geometry": {"coordinates":[-74.31463599999999,40.695236],"type":"Point"}
}