{
  "type": "Feature",
  "properties": {
    "addr:full":"63 Arlington Ave Jersey City NJ 07305",
    "addr:housenumber":"63",
    "addr:postcode":"07305",
    "addr:street":"Arlington Ave",
    "iso:country":"US",
    "sg:address":"63 Arlington Ave",
    "sg:city":"Jersey City",
    "sg:classifiers":[
        {
            "category":"Professional",
            "subcategory":"Computer Services",
            "type":"Services"
        }
    ],
    "sg:phone":"+1   ",
    "sg:postcode":"07305",
    "sg:province":"NJ",
    "sg:tags":[
        "management",
        "design",
        "it",
        "network"
    ],
    "wof:name":"NRJ Tech Inc",
    "wof:placetype":"venue"
},
  "geometry": {"coordinates":[-74.07790199999999,40.703821],"type":"Point"}
}