{
  "type": "Feature",
  "properties": {
    "addr:full":"6002 Main St Mays Landing NJ 08330",
    "addr:housenumber":"6002",
    "addr:postcode":"08330",
    "addr:street":"Main St",
    "iso:country":"US",
    "sg:address":"6002 Main St",
    "sg:city":"Mays Landing",
    "sg:classifiers":[
        {
            "category":"Education",
            "subcategory":"Dance Studio",
            "type":"Public Place"
        }
    ],
    "sg:phone":"+1 609 625 5525",
    "sg:postcode":"08330",
    "sg:province":"NJ",
    "sg:tags":[
        "instruction",
        "dancing"
    ],
    "wof:name":"Mays Landing Dance Works",
    "wof:placetype":"venue"
},
  "geometry": {"coordinates":[-74.729277,39.452751],"type":"Point"}
}