{
  "type": "Feature",
  "properties": {
    "addr:full":"37 Merchant St Newark NJ 07105",
    "addr:housenumber":"37",
    "addr:postcode":"07105",
    "addr:street":"Merchant St",
    "iso:country":"US",
    "sg:address":"37 Merchant St",
    "sg:city":"Newark",
    "sg:classifiers":[
        {
            "category":"Restaurant",
            "type":"Food & Drink"
        }
    ],
    "sg:phone":"+1   ",
    "sg:postcode":"07105",
    "sg:province":"NJ",
    "sg:tags":[
        "eating"
    ],
    "wof:name":"Ce Qui Sabe II",
    "wof:placetype":"venue"
},
  "geometry": {"coordinates":[-74.154634,40.729156],"type":"Point"}
}