{
  "type": "Feature",
  "properties": {
    "addr:full":"310 Klockner Rd Mercerville NJ 08619",
    "addr:housenumber":"310",
    "addr:postcode":"08619",
    "addr:street":"Klockner Rd",
    "iso:country":"US",
    "sg:address":"310 Klockner Rd",
    "sg:city":"Mercerville",
    "sg:classifiers":[
        {
            "category":"Restaurant",
            "type":"Food & Drink"
        }
    ],
    "sg:phone":"+1 609 587 4232",
    "sg:postcode":"08619",
    "sg:province":"NJ",
    "wof:name":"Leonard's Hurry-Back Inn",
    "wof:placetype":"venue"
},
  "geometry": {"coordinates":[-74.710339,40.244842],"type":"Point"}
}