{
  "type": "Feature",
  "properties": {
    "iso:country":"US",
    "sg:address":"4500 New Brunswick Ave",
    "sg:city":"Piscataway",
    "sg:classifiers":[
        {
            "category":"Professional",
            "subcategory":"Computer Services",
            "type":"Services"
        }
    ],
    "sg:phone":"+1   ",
    "sg:postcode":"08854",
    "sg:province":"NJ",
    "sg:tags":[
        "related"
    ],
    "wof:name":"My Portal Solutions",
    "wof:placetype":"venue"
},
  "geometry": {"coordinates":[-74.439632,40.559359],"type":"Point"}
}