{
  "type": "Feature",
  "properties": {
    "iso:country":"US",
    "sg:address":"17 Silver Birch Ave",
    "sg:city":"Oakland",
    "sg:classifiers":[
        {
            "category":"Building & Trades",
            "subcategory":"Construction",
            "type":"Services"
        }
    ],
    "sg:phone":"+1 201 785 0607",
    "sg:postcode":"07436",
    "sg:province":"NJ",
    "sg:tags":[
        "contractor"
    ],
    "wof:name":"Windmill Originals Custom Builders",
    "wof:placetype":"venue"
},
  "geometry": {"coordinates":[-74.246173,41.026922],"type":"Point"}
}