{
  "type": "Feature",
  "properties": {
    "iso:country":"US",
    "sg:address":"303 Jefferson St",
    "sg:city":"Hoboken",
    "sg:classifiers":[
        {
            "category":"Organizations",
            "subcategory":"Religious Organization",
            "type":"Services"
        }
    ],
    "sg:phone":"+1   ",
    "sg:postcode":"07030",
    "sg:province":"NJ",
    "wof:name":"G J Cleffi Rev",
    "wof:placetype":"venue"
},
  "geometry": {"coordinates":[-74.037013,40.742476],"type":"Point"}
}