{
  "type": "Feature",
  "properties": {
    "iso:country":"US",
    "sg:address":"1 Pleasant Pl",
    "sg:city":"Hopatcong",
    "sg:classifiers":[
        {
            "category":"Professional",
            "subcategory":"Art Services",
            "type":"Services"
        }
    ],
    "sg:phone":"+1   ",
    "sg:postcode":"07866",
    "sg:province":"NJ",
    "sg:tags":[
        "commercial",
        "design"
    ],
    "wof:name":"Twin Graphics Inc",
    "wof:placetype":"venue"
},
  "geometry": {"coordinates":[-74.51667399999999,40.901807],"type":"Point"}
}