{
  "type": "Feature",
  "properties": {
    "addr:full":"299 Browning Ln Cherry Hill NJ 08003",
    "addr:housenumber":"299",
    "addr:postcode":"08003",
    "addr:street":"Browning Ln",
    "iso:country":"US",
    "sg:address":"299 Browning Ln",
    "sg:city":"Cherry Hill",
    "sg:classifiers":[
        {
            "category":"Organizations",
            "subcategory":"Religious Organization",
            "type":"Services"
        }
    ],
    "sg:phone":"+1 856 428 6137",
    "sg:postcode":"08003",
    "sg:province":"NJ",
    "sg:tags":[
        "church"
    ],
    "sg:website":"www.cherryhillbaptist.org",
    "wof:name":"Cherry Hill Baptist Church",
    "wof:placetype":"venue"
},
  "geometry": {"coordinates":[-75.00302600000001,39.878441],"type":"Point"}
}