{
  "type": "Feature",
  "properties": {
    "addr:full":"1085 Dumont Cir Voorhees NJ 08043",
    "addr:housenumber":"1085",
    "addr:postcode":"08043",
    "addr:street":"Dumont Cir",
    "iso:country":"US",
    "sg:address":"1085 Dumont Cir",
    "sg:city":"Voorhees",
    "sg:classifiers":[
        {
            "category":"Utilities",
            "subcategory":"Telephone",
            "type":"Services"
        },
        {
            "category":"Shopping",
            "subcategory":"Musical Instruments",
            "type":"Retail Goods"
        }
    ],
    "sg:phone":"+1 856 346 6905",
    "sg:postcode":"08043",
    "sg:province":"NJ",
    "sg:tags":[
        "on",
        "provider",
        "music",
        "dealer",
        "sheet"
    ],
    "wof:name":"Music Notes Inc",
    "wof:placetype":"venue"
},
  "geometry": {"coordinates":[-74.978041,39.843556],"type":"Point"}
}