{
  "type": "Feature",
  "properties": {
    "iso:country":"US",
    "sg:address":"218 Hunterdon St",
    "sg:city":"Newark",
    "sg:classifiers":[
        {
            "category":"Organizations",
            "subcategory":"Religious Organization",
            "type":"Services"
        }
    ],
    "sg:phone":"+1   ",
    "sg:postcode":"07103",
    "sg:province":"NJ",
    "wof:name":"Shiloh Progressv Primtv Baptst",
    "wof:placetype":"venue"
},
  "geometry": {"coordinates":[-74.19347399999999,40.73565],"type":"Point"}
}