{
  "type": "Feature",
  "properties": {
    "iso:country":"US",
    "sg:address":"120 North Ave",
    "sg:city":"Plainfield",
    "sg:classifiers":[
        {
            "category":"Shopping",
            "subcategory":"Musical Instruments",
            "type":"Retail Goods"
        }
    ],
    "sg:phone":"+1 908 754 3718",
    "sg:postcode":"07060",
    "sg:province":"NJ",
    "sg:tags":[
        "music",
        "sheet",
        "dealer"
    ],
    "wof:name":"Plainfield Music Store Inc",
    "wof:placetype":"venue"
},
  "geometry": {"coordinates":[-74.42119,40.618194],"type":"Point"}
}