{
  "type": "Feature",
  "properties": {
    "addr:full":"28 Shrewsbury Dr Livingston NJ 07039",
    "addr:housenumber":"28",
    "addr:postcode":"07039",
    "addr:street":"Shrewsbury Dr",
    "iso:country":"US",
    "sg:address":"28 Shrewsbury Dr",
    "sg:city":"Livingston",
    "sg:classifiers":[
        {
            "category":"Professional",
            "type":"Services"
        }
    ],
    "sg:phone":"+1 973 994 0843",
    "sg:postcode":"07039",
    "sg:province":"NJ",
    "sg:tags":[
        "establishment"
    ],
    "wof:name":"Confidence Achievement Through",
    "wof:placetype":"venue"
},
  "geometry": {"coordinates":[-74.296599,40.800346],"type":"Point"}
}