{
  "type": "Feature",
  "properties": {
    "iso:country":"US",
    "sg:address":"192 Orange Ave",
    "sg:city":"Irvington",
    "sg:classifiers":[
        {
            "category":"Restaurant",
            "type":"Food & Drink"
        }
    ],
    "sg:phone":"+1 973 399 4905",
    "sg:postcode":"07111",
    "sg:province":"NJ",
    "sg:tags":[
        "delicatessen"
    ],
    "wof:name":"4 Corner's Food Market",
    "wof:placetype":"venue"
},
  "geometry": {"coordinates":[-74.229089,40.733049],"type":"Point"}
}