{
  "type": "Feature",
  "properties": {
    "iso:country":"US",
    "sg:address":"150 Middlesex Ave",
    "sg:city":"Metuchen",
    "sg:classifiers":[
        {
            "category":"Health Services",
            "subcategory":"Chiropractor",
            "type":"Services"
        }
    ],
    "sg:phone":"+1 732 548 3113",
    "sg:postcode":"08840",
    "sg:province":"NJ",
    "wof:name":"Mandell Chiropractic PA",
    "wof:placetype":"venue"
},
  "geometry": {"coordinates":[-74.352298,40.551088],"type":"Point"}
}