{
  "type": "Feature",
  "properties": {
    "iso:country":"US",
    "sg:address":"1351 Prince Rodgers Ave",
    "sg:city":"Bridgewater",
    "sg:classifiers":[
        {
            "category":"Restaurant",
            "type":"Food & Drink"
        }
    ],
    "sg:phone":"+1 908 231 8822",
    "sg:postcode":"08807",
    "sg:province":"NJ",
    "wof:name":"Thai Kitchen",
    "wof:placetype":"venue"
},
  "geometry": {"coordinates":[-74.61196200000001,40.588724],"type":"Point"}
}