{
  "type": "Feature",
  "properties": {
    "iso:country":"US",
    "sg:address":"777 Shannon Ave",
    "sg:city":"Perth Amboy",
    "sg:classifiers":[
        {
            "category":"Shopping",
            "type":"Retail Goods"
        }
    ],
    "sg:phone":"+1   ",
    "sg:postcode":"08861",
    "sg:province":"NJ",
    "sg:tags":[
        "merchandise"
    ],
    "wof:name":"Videoprotected Co",
    "wof:placetype":"venue"
},
  "geometry": {"coordinates":[-74.28686500000001,40.535491],"type":"Point"}
}