{
  "type": "Feature",
  "properties": {
    "addr:full":"313 Glenwood Ave Bloomfield NJ 07003",
    "addr:housenumber":"313",
    "addr:postcode":"07003",
    "addr:street":"Glenwood Ave",
    "iso:country":"US",
    "sg:address":"313 Glenwood Ave",
    "sg:city":"Bloomfield",
    "sg:classifiers":[
        {
            "category":"Food & Beverages",
            "subcategory":"Groceries & Convenience Stores",
            "type":"Retail Goods"
        }
    ],
    "sg:phone":"+1 973 429 1550",
    "sg:postcode":"07003",
    "sg:province":"NJ",
    "wof:name":"Bloomfield Food Mart Inc",
    "wof:placetype":"venue"
},
  "geometry": {"coordinates":[-74.198752,40.792319],"type":"Point"}
}