{
  "type": "Feature",
  "properties": {
    "iso:country":"US",
    "sg:address":"2 Powell Ln",
    "sg:city":"Collingswood",
    "sg:classifiers":[
        {
            "category":"Restaurant",
            "type":"Food & Drink"
        }
    ],
    "sg:phone":"+1 856 854 4500",
    "sg:postcode":"08108",
    "sg:province":"NJ",
    "sg:tags":[
        "new",
        "american"
    ],
    "sg:website":"www.restaurantlobianco.com",
    "wof:name":"LoBianco New American Cuisine",
    "wof:placetype":"venue"
},
  "geometry": {"coordinates":[-75.125063,39.894899],"type":"Point"}
}