{
  "type": "Feature",
  "properties": {
    "addr:full":"1214 State Rte 37 Toms River NJ 08753",
    "addr:housenumber":"1214",
    "addr:postcode":"08753",
    "addr:street":"State Rte 37",
    "iso:country":"US",
    "sg:address":"1214 State Rte 37",
    "sg:city":"Toms River",
    "sg:classifiers":[
        {
            "category":"Professional",
            "subcategory":"Accounting & Tax Preparation",
            "type":"Services"
        }
    ],
    "sg:phone":"+1 732 929 2244",
    "sg:postcode":"08753",
    "sg:province":"NJ",
    "sg:tags":[
        "return",
        "filing"
    ],
    "wof:name":"H & R Block Tax Svc",
    "wof:placetype":"venue"
},
  "geometry": {"coordinates":[-74.15985499999999,39.953729],"type":"Point"}
}