{
  "type": "Feature",
  "properties": {
    "addr:full":"615 E Moss Mill Rd Absecon NJ 08205",
    "addr:housenumber":"615",
    "addr:postcode":"08205",
    "addr:street":"E Moss Mill Rd",
    "iso:country":"US",
    "sg:address":"615 E Moss Mill Rd",
    "sg:city":"Absecon",
    "sg:classifiers":[
        {
            "category":"Restaurant",
            "type":"Food & Drink"
        }
    ],
    "sg:phone":"+1   ",
    "sg:postcode":"08205",
    "sg:province":"NJ",
    "sg:tags":[
        "eating"
    ],
    "wof:name":"Scoops Place 2",
    "wof:placetype":"venue"
},
  "geometry": {"coordinates":[-74.46472199999999,39.495079],"type":"Point"}
}