{
  "type": "Feature",
  "properties": {
    "iso:country":"US",
    "sg:address":"10 S River Rd",
    "sg:city":"Cranbury",
    "sg:classifiers":[
        {
            "category":"Wholesale",
            "subcategory":"Machinery & Supplies",
            "type":"Manufacturing & Wholesale Goods"
        },
        {
            "category":"Wholesale",
            "subcategory":"Electrical",
            "type":"Manufacturing & Wholesale Goods"
        }
    ],
    "sg:phone":"+1 609 409 3590",
    "sg:postcode":"08535",
    "sg:province":"NJ",
    "sg:tags":[
        "fire",
        "sporting",
        "system",
        "equipment",
        "establishment",
        "alarm"
    ],
    "wof:name":"Garden State Fire & Safety Svc",
    "wof:placetype":"venue"
},
  "geometry": {"coordinates":[-74.443918,40.225698],"type":"Point"}
}