{
  "type": "Feature",
  "properties": {
    "iso:country":"US",
    "sg:address":"3 3rd St",
    "sg:city":"Oakland",
    "sg:classifiers":[
        {
            "category":"Banks & Credit Unions",
            "subcategory":"Investment Brokerage",
            "type":"Services"
        }
    ],
    "sg:phone":"+1   ",
    "sg:postcode":"07436",
    "sg:province":"NJ",
    "sg:tags":[
        "security"
    ],
    "wof:name":"Morlyn Financial Group LLC",
    "wof:placetype":"venue"
},
  "geometry": {"coordinates":[-74.24570900000001,41.0326],"type":"Point"}
}