{
  "type": "Feature",
  "properties": {
    "addr:full":"34 Chambers St Princeton NJ 08542",
    "addr:housenumber":"34",
    "addr:postcode":"08542",
    "addr:street":"Chambers St",
    "iso:country":"US",
    "sg:address":"34 Chambers St",
    "sg:city":"Princeton",
    "sg:classifiers":[
        {
            "category":"Professional",
            "subcategory":"Lawyer & Legal Services",
            "type":"Services"
        }
    ],
    "sg:phone":"+1 609 924 9155",
    "sg:postcode":"08542",
    "sg:province":"NJ",
    "sg:tags":[
        "attorney"
    ],
    "wof:name":"Thomas M Badenhausen",
    "wof:placetype":"venue"
},
  "geometry": {"coordinates":[-74.662435,40.348925],"type":"Point"}
}