{
  "type": "Feature",
  "properties": {
    "iso:country":"US",
    "sg:address":"95 Union Ave",
    "sg:city":"Paterson",
    "sg:phone":"+1 973 790 0690",
    "sg:postcode":"07502",
    "sg:province":"NJ",
    "sg:tags":[
        "oil"
    ],
    "wof:name":"TSS Oil Inc",
    "wof:placetype":"venue"
},
  "geometry": {"coordinates":[-74.197053,40.913676],"type":"Point"}
}