{
  "type": "Feature",
  "properties": {
    "iso:country":"US",
    "sg:address":"17 Hampshire Dr",
    "sg:city":"Mendham",
    "sg:classifiers":[
        {
            "category":"Professional",
            "subcategory":"Management & Consulting",
            "type":"Services"
        }
    ],
    "sg:phone":"+1 973 543 6695",
    "sg:postcode":"07945",
    "sg:province":"NJ",
    "sg:tags":[
        "communications",
        "consultant"
    ],
    "sg:website":"www.media-strategies.com",
    "wof:name":"Media Strategies",
    "wof:placetype":"venue"
},
  "geometry": {"coordinates":[-74.590478,40.788714],"type":"Point"}
}