{
  "type": "Feature",
  "properties": {
    "iso:country":"US",
    "sg:address":"554 Haddon Ave",
    "sg:city":"Collingswood",
    "sg:classifiers":[
        {
            "category":"Shopping",
            "type":"Retail Goods"
        }
    ],
    "sg:phone":"+1 856 854 3727",
    "sg:postcode":"08108",
    "sg:province":"NJ",
    "sg:tags":[
        "picture",
        "frame"
    ],
    "wof:name":"Traveling Framer Inc",
    "wof:placetype":"venue"
},
  "geometry": {"coordinates":[-75.07370899999999,39.917843],"type":"Point"}
}