{
  "type": "Feature",
  "properties": {
    "iso:country":"US",
    "sg:address":"3131 State Rte 38",
    "sg:city":"Mt Laurel",
    "sg:classifiers":[
        {
            "category":"Health Services",
            "subcategory":"Health Practitioner",
            "type":"Services"
        }
    ],
    "sg:phone":"+1 856 235 0080",
    "sg:postcode":"08054",
    "sg:province":"NJ",
    "sg:tags":[
        "therapist",
        "physical"
    ],
    "wof:name":"Workright Physical Therapy",
    "wof:placetype":"venue"
},
  "geometry": {"coordinates":[-74.87873399999999,39.920819],"type":"Point"}
}