{
  "type": "Feature",
  "properties": {
    "iso:country":"US",
    "sg:address":"519 Morningside Pl",
    "sg:city":"Middletown",
    "sg:classifiers":[
        {
            "category":"Personal",
            "subcategory":"Beauty Salon",
            "type":"Services"
        }
    ],
    "sg:phone":"+1   ",
    "sg:postcode":"07748",
    "sg:province":"NJ",
    "sg:tags":[
        "shop"
    ],
    "wof:name":"Jet Set Pet MBL Grooming LLC",
    "wof:placetype":"venue"
},
  "geometry": {"coordinates":[-74.119452,40.437509],"type":"Point"}
}