{
  "type": "Feature",
  "properties": {
    "addr:full":"173 US Hwy 46 Englewood NJ 07663",
    "addr:housenumber":"173",
    "addr:postcode":"07663",
    "addr:street":"Us Hwy 46",
    "iso:country":"US",
    "sg:address":"173 US Hwy 46",
    "sg:city":"Englewood",
    "sg:classifiers":[
        {
            "category":"Professional",
            "subcategory":"Business Services",
            "type":"Services"
        }
    ],
    "sg:phone":"+1 201 627 1490",
    "sg:postcode":"07663",
    "sg:province":"NJ",
    "sg:tags":[
        "broker"
    ],
    "wof:name":"Dickman Business Brokers",
    "wof:placetype":"venue"
},
  "geometry": {"coordinates":[-74.092418,40.887332],"type":"Point"}
}