{
  "type": "Feature",
  "properties": {
    "addr:full":"600 Cape May St Harrison NJ 07029",
    "addr:housenumber":"600",
    "addr:postcode":"07029",
    "addr:street":"Cape May St",
    "iso:country":"US",
    "sg:address":"600 Cape May St",
    "sg:city":"Harrison",
    "sg:classifiers":[
        {
            "category":"Building & Trades",
            "subcategory":"Construction",
            "type":"Services"
        }
    ],
    "sg:phone":"+1 973 485 1112",
    "sg:postcode":"07029",
    "sg:province":"NJ",
    "sg:tags":[
        "contractor"
    ],
    "wof:name":"Prismatic Development Corp",
    "wof:placetype":"venue"
},
  "geometry": {"coordinates":[-74.14712,40.739034],"type":"Point"}
}