{
  "type": "Feature",
  "properties": {
    "addr:full":"369 Aurora Ave Cliffside Park NJ 07010",
    "addr:housenumber":"369",
    "addr:postcode":"07010",
    "addr:street":"Aurora Ave",
    "iso:country":"US",
    "sg:address":"369 Aurora Ave",
    "sg:city":"Cliffside Park",
    "sg:classifiers":[
        {
            "category":"Professional",
            "type":"Services"
        }
    ],
    "sg:phone":"+1 201 943 2488",
    "sg:postcode":"07010",
    "sg:province":"NJ",
    "sg:tags":[
        "establishment"
    ],
    "wof:name":"Reverand Crespo",
    "wof:placetype":"venue"
},
  "geometry": {"coordinates":[-73.985135,40.831418],"type":"Point"}
}