{
  "type": "Feature",
  "properties": {
    "iso:country":"US",
    "sg:address":"216 48th St",
    "sg:city":"Union City",
    "sg:classifiers":[
        {
            "category":"Restaurant",
            "type":"Food & Drink"
        }
    ],
    "sg:phone":"+1 201 601 3110",
    "sg:postcode":"07087",
    "sg:province":"NJ",
    "wof:name":"Mambo's",
    "wof:placetype":"venue"
},
  "geometry": {"coordinates":[-74.019595,40.780667],"type":"Point"}
}