{
  "type": "Feature",
  "properties": {
    "addr:full":"216 48th St Union City NJ 07087",
    "addr:housenumber":"216",
    "addr:postcode":"07087",
    "addr:street":"48Th St",
    "iso:country":"US",
    "sg:address":"216 48th St",
    "sg:city":"Union City",
    "sg:classifiers":[
        {
            "category":"Restaurant",
            "type":"Food & Drink"
        }
    ],
    "sg:phone":"+1 201 601 3110",
    "sg:postcode":"07087",
    "sg:province":"NJ",
    "wof:name":"Mambo's",
    "wof:placetype":"venue"
},
  "geometry": {"coordinates":[-74.019595,40.780667],"type":"Point"}
}