{
  "type": "Feature",
  "properties": {
    "iso:country":"US",
    "sg:address":"424 US Hwy 206",
    "sg:city":"Hillsborough",
    "sg:classifiers":[
        {
            "category":"Personal",
            "subcategory":"Tanning Parlor",
            "type":"Services"
        }
    ],
    "sg:phone":"+1 908 904 9044",
    "sg:postcode":"08844",
    "sg:province":"NJ",
    "sg:tags":[
        "salon"
    ],
    "wof:name":"Ultimate Tan",
    "wof:placetype":"venue"
},
  "geometry": {"coordinates":[-74.63976599999999,40.507394],"type":"Point"}
}