{
  "type": "Feature",
  "properties": {
    "addr:full":"431 Amwell Rd Hillsborough NJ 08844",
    "addr:housenumber":"431",
    "addr:postcode":"08844",
    "addr:street":"Amwell Rd",
    "iso:country":"US",
    "sg:address":"431 Amwell Rd",
    "sg:city":"Hillsborough",
    "sg:classifiers":[
        {
            "category":"Autos & Motor Vehicles",
            "subcategory":"Auto Supplies",
            "type":"Retail Goods"
        },
        {
            "category":"Retail",
            "subcategory":"Auto Repair",
            "type":"Services"
        }
    ],
    "sg:phone":"+1 908 904 4720",
    "sg:postcode":"08844",
    "sg:province":"NJ",
    "sg:tags":[
        "brake",
        "tire"
    ],
    "sg:website":"http://www.ststire.com",
    "wof:name":"Sts Tire & Auto Ctr",
    "wof:placetype":"venue"
},
  "geometry": {"coordinates":[-74.648746,40.500293],"type":"Point"}
}