{
  "type": "Feature",
  "properties": {
    "addr:full":"7 Railroad Ave Runnemede NJ 08078",
    "addr:housenumber":"7",
    "addr:postcode":"08078",
    "addr:street":"Railroad Ave",
    "iso:country":"US",
    "sg:address":"7 Railroad Ave",
    "sg:city":"Runnemede",
    "sg:classifiers":[
        {
            "category":"Wholesale",
            "subcategory":"Seafood",
            "type":"Manufacturing & Wholesale Goods"
        }
    ],
    "sg:phone":"+1 856 939 8883",
    "sg:postcode":"08078",
    "sg:province":"NJ",
    "wof:name":"Edward P Obrien",
    "wof:placetype":"venue"
},
  "geometry": {"coordinates":[-75.074944,39.849673],"type":"Point"}
}