{
  "type": "Feature",
  "properties": {
    "iso:country":"US",
    "sg:address":"1163 Asbury Ave",
    "sg:city":"Ocean City",
    "sg:classifiers":[
        {
            "category":"Recreation",
            "type":"Entertainment"
        }
    ],
    "sg:phone":"+1 609 399 0022",
    "sg:postcode":"08226",
    "sg:province":"NJ",
    "sg:tags":[
        "karate",
        "judo",
        "instr"
    ],
    "wof:name":"Modern Bujutsu Center",
    "wof:placetype":"venue"
},
  "geometry": {"coordinates":[-74.57986,39.276225],"type":"Point"}
}