{
  "type": "Feature",
  "properties": {
    "iso:country":"US",
    "sg:address":"242 Thomas Ave",
    "sg:city":"Lyndhurst",
    "sg:classifiers":[
        {
            "category":"Building & Trades",
            "subcategory":"Construction",
            "type":"Services"
        }
    ],
    "sg:phone":"+1 201 935 2080",
    "sg:postcode":"07071",
    "sg:province":"NJ",
    "sg:tags":[
        "hanging",
        "contractor"
    ],
    "wof:name":"Creatino Painting & Rfrbs",
    "wof:placetype":"venue"
},
  "geometry": {"coordinates":[-74.13357499999999,40.805248],"type":"Point"}
}