{
  "type": "Feature",
  "properties": {
    "addr:full":"40 Sunrise Rd Old Bridge NJ 08857",
    "addr:housenumber":"40",
    "addr:postcode":"08857",
    "addr:street":"Sunrise Rd",
    "iso:country":"US",
    "sg:address":"40 Sunrise Rd",
    "sg:city":"Old Bridge",
    "sg:classifiers":[
        {
            "category":"Arts & Performance",
            "subcategory":"Theater",
            "type":"Entertainment"
        }
    ],
    "sg:phone":"+1 732 651 8464",
    "sg:postcode":"08857",
    "sg:province":"NJ",
    "sg:tags":[
        "live",
        "music"
    ],
    "wof:name":"Elite D J's Co",
    "wof:placetype":"venue"
},
  "geometry": {"coordinates":[-74.353216,40.408055],"type":"Point"}
}