{
  "type": "Feature",
  "properties": {
    "iso:country":"US",
    "sg:address":"3263 State Rte 35",
    "sg:city":"Lavallette",
    "sg:classifiers":[
        {
            "category":"Professional",
            "subcategory":"Art Services",
            "type":"Services"
        }
    ],
    "sg:phone":"+1 732 793 1234",
    "sg:postcode":"08735",
    "sg:province":"NJ",
    "sg:tags":[
        "commercial",
        "mfg",
        "design",
        "trimming"
    ],
    "wof:name":"Z-Line",
    "wof:placetype":"venue"
},
  "geometry": {"coordinates":[-74.06483799999999,39.989002],"type":"Point"}
}