{
  "type": "Feature",
  "properties": {
    "addr:full":"18 Sheppard Pl Edison NJ 08817",
    "addr:housenumber":"18",
    "addr:postcode":"08817",
    "addr:street":"Sheppard Pl",
    "iso:country":"US",
    "sg:address":"18 Sheppard Pl",
    "sg:city":"Edison",
    "sg:classifiers":[
        {
            "category":"Professional",
            "type":"Services"
        }
    ],
    "sg:phone":"+1 201 650 6932",
    "sg:postcode":"08817",
    "sg:province":"NJ",
    "wof:name":"United Business Mailing Svc",
    "wof:placetype":"venue"
},
  "geometry": {"coordinates":[-74.402987,40.516919],"type":"Point"}
}