{
  "type": "Feature",
  "properties": {
    "iso:country":"US",
    "sg:address":"369 W Saddle River Rd",
    "sg:city":"Upper Saddle Rvr",
    "sg:classifiers":[
        {
            "category":"Health Services",
            "subcategory":"Doctor",
            "type":"Services"
        }
    ],
    "sg:phone":"+1 201 327 5642",
    "sg:postcode":"07458",
    "sg:province":"NJ",
    "sg:tags":[
        "dentist"
    ],
    "wof:name":"James O'Bosky DDS",
    "wof:placetype":"venue"
},
  "geometry": {"coordinates":[-74.098185,41.059861],"type":"Point"}
}