{
  "type": "Feature",
  "properties": {
    "addr:full":"7 Sorbello Rd Paramus NJ 07652",
    "addr:housenumber":"7",
    "addr:postcode":"07652",
    "addr:street":"Sorbello Rd",
    "iso:country":"US",
    "sg:address":"7 Sorbello Rd",
    "sg:city":"Paramus",
    "sg:classifiers":[
        {
            "category":"Wholesale",
            "subcategory":"Hardware",
            "type":"Manufacturing & Wholesale Goods"
        }
    ],
    "sg:phone":"+1 201 262 4836",
    "sg:postcode":"07652",
    "sg:province":"NJ",
    "sg:tags":[
        "plumbing"
    ],
    "wof:name":"Shanxi Minmetal USA",
    "wof:placetype":"venue"
},
  "geometry": {"coordinates":[-74.065257,40.958106],"type":"Point"}
}