{
  "type": "Feature",
  "properties": {
    "iso:country":"US",
    "sg:address":"5 Enterprise Dr",
    "sg:city":"Cape May Ct Hse",
    "sg:classifiers":[
        {
            "category":"Shopping",
            "subcategory":"Clothing, Apparel, & Fashions",
            "type":"Retail Goods"
        }
    ],
    "sg:phone":"+1 609 465 3147",
    "sg:postcode":"08210",
    "sg:province":"NJ",
    "sg:tags":[
        "garment"
    ],
    "wof:name":"Network Apparel Sales",
    "wof:placetype":"venue"
},
  "geometry": {"coordinates":[-74.855335,39.046452],"type":"Point"}
}