{
  "type": "Feature",
  "properties": {
    "addr:full":"127 Headley Ter Union NJ 07083",
    "addr:housenumber":"127",
    "addr:postcode":"07083",
    "addr:street":"Headley Ter",
    "iso:country":"US",
    "sg:address":"127 Headley Ter",
    "sg:city":"Union",
    "sg:classifiers":[
        {
            "category":"Retail",
            "subcategory":"Repair Shop",
            "type":"Services"
        }
    ],
    "sg:phone":"+1 908 851 4520",
    "sg:postcode":"07083",
    "sg:province":"NJ",
    "sg:tags":[
        "plumbing"
    ],
    "wof:name":"Jts Oil Burner Svc",
    "wof:placetype":"venue"
},
  "geometry": {"coordinates":[-74.27759500000001,40.695351],"type":"Point"}
}