{
  "type": "Feature",
  "properties": {
    "iso:country":"US",
    "sg:address":"234 W Englewood Ave",
    "sg:city":"Englewood",
    "sg:classifiers":[
        {
            "category":"Retail",
            "subcategory":"Repair Shop",
            "type":"Services"
        }
    ],
    "sg:phone":"+1 201 334 3118",
    "sg:postcode":"07631",
    "sg:province":"NJ",
    "sg:tags":[
        "lock",
        "locksmith"
    ],
    "wof:name":"7 Day Emergency 24 Hour",
    "wof:placetype":"venue"
},
  "geometry": {"coordinates":[-73.98466999999999,40.896186],"type":"Point"}
}