{
  "type": "Feature",
  "properties": {
    "addr:full":"2600 Federal St Camden NJ 08105",
    "addr:housenumber":"2600",
    "addr:postcode":"08105",
    "addr:street":"Federal St",
    "iso:country":"US",
    "sg:address":"2600 Federal St",
    "sg:city":"Camden",
    "sg:classifiers":[
        {
            "category":"Restaurant",
            "type":"Food & Drink"
        }
    ],
    "sg:phone":"+1 856 966 3556",
    "sg:postcode":"08105",
    "sg:province":"NJ",
    "sg:tags":[
        "mexican"
    ],
    "wof:name":"San Lucas Mexican Restaurant",
    "wof:placetype":"venue"
},
  "geometry": {"coordinates":[-75.088717,39.945933],"type":"Point"}
}