{
  "type": "Feature",
  "properties": {
    "addr:full":"48 Ironia Rd Randolph NJ 07836",
    "addr:housenumber":"48",
    "addr:postcode":"07836",
    "addr:street":"Ironia Rd",
    "iso:country":"US",
    "sg:address":"48 Ironia Rd",
    "sg:city":"Randolph",
    "sg:classifiers":[
        {
            "category":"Building & Trades",
            "subcategory":"Construction",
            "type":"Services"
        }
    ],
    "sg:phone":"+1 973 543 0766",
    "sg:postcode":"07836",
    "sg:province":"NJ",
    "sg:tags":[
        "contractor"
    ],
    "wof:name":"Wayne Nolting",
    "wof:placetype":"venue"
},
  "geometry": {"coordinates":[-74.690882,40.835971],"type":"Point"}
}