{
  "type": "Feature",
  "properties": {
    "iso:country":"US",
    "sg:address":"21 Sunrise Dr",
    "sg:city":"Gillette",
    "sg:classifiers":[
        {
            "category":"Wholesale",
            "subcategory":"Non-durable Goods",
            "type":"Manufacturing & Wholesale Goods"
        }
    ],
    "sg:phone":"+1 908 580 1528",
    "sg:postcode":"07933",
    "sg:province":"NJ",
    "wof:name":"America International Trading",
    "wof:placetype":"venue"
},
  "geometry": {"coordinates":[-74.46888199999999,40.671672],"type":"Point"}
}