{
  "type": "Feature",
  "properties": {
    "addr:full":"1490 Cedar Row Lakewood NJ 08701",
    "addr:housenumber":"1490",
    "addr:postcode":"08701",
    "addr:street":"Cedar Row",
    "iso:country":"US",
    "sg:address":"1490 Cedar Row",
    "sg:city":"Lakewood",
    "sg:classifiers":[
        {
            "category":"Real Estate",
            "subcategory":"Real Estate Operator",
            "type":"Services"
        }
    ],
    "sg:phone":"+1   ",
    "sg:postcode":"08701",
    "sg:province":"NJ",
    "sg:tags":[
        "building",
        "commercial"
    ],
    "wof:name":"Goldsing LLC",
    "wof:placetype":"venue"
},
  "geometry": {"coordinates":[-74.236103,40.107641],"type":"Point"}
}