{
  "type": "Feature",
  "properties": {
    "addr:full":"5810 Palisade Ave West New York NJ 07093",
    "addr:housenumber":"5810",
    "addr:postcode":"07093",
    "addr:street":"Palisade Ave West",
    "iso:country":"US",
    "sg:address":"5810 Palisade Ave",
    "sg:city":"West New York",
    "sg:classifiers":[
        {
            "category":"Building & Trades",
            "subcategory":"Construction",
            "type":"Services"
        }
    ],
    "sg:phone":"+1 201 868 5535",
    "sg:postcode":"07093",
    "sg:province":"NJ",
    "sg:tags":[
        "resurfacing",
        "floor",
        "laying",
        "refinishing",
        "contractor"
    ],
    "wof:name":"E V Wood Floors",
    "wof:placetype":"venue"
},
  "geometry": {"coordinates":[-74.014619,40.787076],"type":"Point"}
}