{
  "type": "Feature",
  "properties": {
    "iso:country":"US",
    "sg:address":"6 Mill Ct",
    "sg:city":"Linden",
    "sg:classifiers":[
        {
            "category":"Building & Trades",
            "subcategory":"Construction",
            "type":"Services"
        }
    ],
    "sg:phone":"+1 908 587 9509",
    "sg:postcode":"07036",
    "sg:province":"NJ",
    "sg:tags":[
        "contractor"
    ],
    "wof:name":"Porto General Contractors Co I",
    "wof:placetype":"venue"
},
  "geometry": {"coordinates":[-74.270374,40.634296],"type":"Point"}
}