{
  "type": "Feature",
  "properties": {
    "iso:country":"US",
    "sg:address":"51 Broad Ave",
    "sg:city":"Fairview",
    "sg:classifiers":[
        {
            "category":"Home & Garden",
            "subcategory":"Home Furnishings",
            "type":"Retail Goods"
        }
    ],
    "sg:phone":"+1   ",
    "sg:postcode":"07022",
    "sg:province":"NJ",
    "wof:name":"Barba Sales",
    "wof:placetype":"venue"
},
  "geometry": {"coordinates":[-74.008319,40.816282],"type":"Point"}
}