{
  "type": "Feature",
  "properties": {
    "iso:country":"US",
    "sg:address":"31 Gravel Hill Rd",
    "sg:city":"Butler",
    "sg:classifiers":[
        {
            "category":"Manufacturing",
            "subcategory":"Tools & Machinery",
            "type":"Manufacturing & Wholesale Goods"
        }
    ],
    "sg:phone":"+1 973 492 0355",
    "sg:postcode":"07405",
    "sg:province":"NJ",
    "sg:tags":[
        "equipment",
        "construction"
    ],
    "wof:name":"Canam Industries",
    "wof:placetype":"venue"
},
  "geometry": {"coordinates":[-74.407425,41.009033],"type":"Point"}
}