{
  "type": "Feature",
  "properties": {
    "iso:country":"US",
    "sg:address":"64 Gardenia Dr",
    "sg:city":"Maple Shade",
    "sg:classifiers":[
        {
            "category":"Professional",
            "subcategory":"Management & Consulting",
            "type":"Services"
        }
    ],
    "sg:phone":"+1   ",
    "sg:postcode":"08052",
    "sg:province":"NJ",
    "wof:name":"Mortgage Services",
    "wof:placetype":"venue"
},
  "geometry": {"coordinates":[-74.984292,39.947377],"type":"Point"}
}