{
  "type": "Feature",
  "properties": {
    "addr:full":"415 Main St Bradley Beach NJ 07720",
    "addr:housenumber":"415",
    "addr:postcode":"07720",
    "addr:street":"Main St",
    "iso:country":"US",
    "sg:address":"415 Main St",
    "sg:city":"Bradley Beach",
    "sg:classifiers":[
        {
            "category":"Food & Beverages",
            "subcategory":"Groceries & Convenience Stores",
            "type":"Retail Goods"
        }
    ],
    "sg:phone":"+1   ",
    "sg:postcode":"07720",
    "sg:province":"NJ",
    "wof:name":"Food Mart Deli & Grocery",
    "wof:placetype":"venue"
},
  "geometry": {"coordinates":[-74.01844,40.201971],"type":"Point"}
}