{
  "type": "Feature",
  "properties": {
    "addr:full":"Uhland & Grove East Rutherford NJ 07073",
    "addr:postcode":"07073",
    "iso:country":"US",
    "sg:address":"Uhland & Grove",
    "sg:city":"East Rutherford",
    "sg:classifiers":[
        {
            "category":"Education",
            "subcategory":"School",
            "type":"Public Place"
        }
    ],
    "sg:phone":"+1 201 804 3100",
    "sg:postcode":"07073",
    "sg:province":"NJ",
    "sg:tags":[
        "high",
        "middle",
        "elementary"
    ],
    "wof:name":"East Rutherford Borough of",
    "wof:placetype":"venue"
},
  "geometry": {"coordinates":[-74.099698,40.834993],"type":"Point"}
}