{
  "type": "Feature",
  "properties": {
    "addr:full":"52 Welisewitz Rd Ringoes NJ 08551",
    "addr:housenumber":"52",
    "addr:postcode":"08551",
    "addr:street":"Welisewitz Rd",
    "iso:country":"US",
    "sg:address":"52 Welisewitz Rd",
    "sg:city":"Ringoes",
    "sg:classifiers":[
        {
            "category":"Wholesale",
            "subcategory":"Chemicals & Plastics",
            "type":"Manufacturing & Wholesale Goods"
        }
    ],
    "sg:phone":"+1 609 466 3469",
    "sg:postcode":"08551",
    "sg:province":"NJ",
    "sg:tags":[
        "product",
        "allied"
    ],
    "wof:name":"Robert B Myers Co Inc",
    "wof:placetype":"venue"
},
  "geometry": {"coordinates":[-74.79569499999999,40.46393],"type":"Point"}
}