{
  "type": "Feature",
  "properties": {
    "iso:country":"US",
    "sg:address":"3715 River Rd",
    "sg:city":"Point Pleasant Beach",
    "sg:classifiers":[
        {
            "category":"Organizations",
            "subcategory":"Professional Association",
            "type":"Services"
        }
    ],
    "sg:phone":"+1 732 892 6076",
    "sg:postcode":"08742",
    "sg:province":"NJ",
    "sg:tags":[
        "business"
    ],
    "wof:name":"Silk & Rayon Printers & Dyers",
    "wof:placetype":"venue"
},
  "geometry": {"coordinates":[-74.084649,40.092151],"type":"Point"}
}