{
  "type": "Feature",
  "properties": {
    "iso:country":"US",
    "sg:address":"832 Bayway Ave",
    "sg:city":"Elizabeth",
    "sg:classifiers":[
        {
            "category":"Retail",
            "subcategory":"Portrait Studio",
            "type":"Services"
        },
        {
            "category":"Professional",
            "subcategory":"Art Services",
            "type":"Services"
        }
    ],
    "sg:phone":"+1 908 662 3108",
    "sg:postcode":"07202",
    "sg:province":"NJ",
    "sg:tags":[
        "photographer",
        "photography",
        "store"
    ],
    "wof:name":"Ks Photography",
    "wof:placetype":"venue"
},
  "geometry": {"coordinates":[-74.220412,40.649987],"type":"Point"}
}