{
  "type": "Feature",
  "properties": {
    "iso:country":"US",
    "sg:address":"35 Verona Pl",
    "sg:city":"Verona",
    "sg:classifiers":[
        {
            "category":"Professional",
            "subcategory":"Business Services",
            "type":"Services"
        }
    ],
    "sg:phone":"+1   ",
    "sg:postcode":"07044",
    "sg:province":"NJ",
    "wof:name":"Gary Ruccia",
    "wof:placetype":"venue"
},
  "geometry": {"coordinates":[-74.24264599999999,40.829348],"type":"Point"}
}