{
  "type": "Feature",
  "properties": {
    "iso:country":"US",
    "sg:address":"504 Summit Ave",
    "sg:city":"Maplewood",
    "sg:classifiers":[
        {
            "category":"Arts & Performance",
            "subcategory":"Theater",
            "type":"Entertainment"
        }
    ],
    "sg:phone":"+1   ",
    "sg:postcode":"07040",
    "sg:province":"NJ",
    "sg:tags":[
        "group"
    ],
    "wof:name":"Douglas Suzzanne Inc",
    "wof:placetype":"venue"
},
  "geometry": {"coordinates":[-74.261307,40.734957],"type":"Point"}
}