{
  "type": "Feature",
  "properties": {
    "iso:country":"US",
    "sg:address":"7 Oakwood Ave",
    "sg:city":"Livingston",
    "sg:classifiers":[
        {
            "category":"Personal",
            "subcategory":"Beauty Salon",
            "type":"Services"
        }
    ],
    "sg:phone":"+1 973 994 0492",
    "sg:postcode":"07039",
    "sg:province":"NJ",
    "sg:tags":[
        "shop"
    ],
    "wof:name":"Park Avenue Salon Systems Inc",
    "wof:placetype":"venue"
},
  "geometry": {"coordinates":[-74.306595,40.778153],"type":"Point"}
}