{
  "type": "Feature",
  "properties": {
    "addr:full":"333 Cedar Ave Middlesex NJ 08846",
    "addr:housenumber":"333",
    "addr:postcode":"08846",
    "addr:street":"Cedar Ave",
    "iso:country":"US",
    "sg:address":"333 Cedar Ave",
    "sg:city":"Middlesex",
    "sg:classifiers":[
        {
            "category":"Wholesale",
            "subcategory":"Machinery & Supplies",
            "type":"Manufacturing & Wholesale Goods"
        }
    ],
    "sg:phone":"+1 732 225 4000",
    "sg:postcode":"08846",
    "sg:province":"NJ",
    "sg:tags":[
        "company",
        "holding"
    ],
    "wof:name":"Powerlift of New Jersey Inc",
    "wof:placetype":"venue"
},
  "geometry": {"coordinates":[-74.499472,40.566283],"type":"Point"}
}