{
  "type": "Feature",
  "properties": {
    "addr:full":"1 Aldgate Ct Brick NJ 08724",
    "addr:housenumber":"1",
    "addr:postcode":"08724",
    "addr:street":"Aldgate Ct",
    "iso:country":"US",
    "sg:address":"1 Aldgate Ct",
    "sg:city":"Brick",
    "sg:classifiers":[
        {
            "category":"Building & Trades",
            "subcategory":"Construction",
            "type":"Services"
        }
    ],
    "sg:phone":"+1 732 892 0998",
    "sg:postcode":"08724",
    "sg:province":"NJ",
    "sg:tags":[
        "painter"
    ],
    "wof:name":"Randy Derousse Painting",
    "wof:placetype":"venue"
},
  "geometry": {"coordinates":[-74.09367399999999,40.079874],"type":"Point"}
}