{
  "type": "Feature",
  "properties": {
    "iso:country":"US",
    "sg:address":"3731 Bayshore Rd",
    "sg:city":"Cape May",
    "sg:classifiers":[
        {
            "category":"Retail",
            "subcategory":"Car Wash",
            "type":"Services"
        }
    ],
    "sg:phone":"+1 609 884 8595",
    "sg:postcode":"08204",
    "sg:province":"NJ",
    "wof:name":"Towne Texaco",
    "wof:placetype":"venue"
},
  "geometry": {"coordinates":[-74.94180299999999,38.9832],"type":"Point"}
}