{
  "type": "Feature",
  "properties": {
    "addr:full":"115 Mountainside Vw Morganville NJ 07751",
    "addr:housenumber":"115",
    "addr:postcode":"07751",
    "addr:street":"Mountainside Vw",
    "iso:country":"US",
    "sg:address":"115 Mountainside Vw",
    "sg:city":"Morganville",
    "sg:classifiers":[
        {
            "category":"Health Services",
            "subcategory":"Clinic",
            "type":"Services"
        }
    ],
    "sg:phone":"+1   ",
    "sg:postcode":"07751",
    "sg:province":"NJ",
    "wof:name":"Global Healthcare Alliance LLC",
    "wof:placetype":"venue"
},
  "geometry": {"coordinates":[-74.21354599999999,40.375475],"type":"Point"}
}