{
  "type": "Feature",
  "properties": {
    "iso:country":"US",
    "sg:address":"1131 Arnold Ave",
    "sg:city":"Pt Pleasant Bch",
    "sg:classifiers":[
        {
            "category":"Professional",
            "subcategory":"Lawyer & Legal Services",
            "type":"Services"
        }
    ],
    "sg:phone":"+1 732 295 9500",
    "sg:postcode":"08742",
    "sg:province":"NJ",
    "sg:tags":[
        "attorney"
    ],
    "wof:name":"A Joseph Guarino Law Office",
    "wof:placetype":"venue"
},
  "geometry": {"coordinates":[-74.06369599999999,40.084664],"type":"Point"}
}