{
  "type": "Feature",
  "properties": {
    "addr:full":"2 Purple Ash Ct Jackson NJ 08527",
    "addr:housenumber":"2",
    "addr:postcode":"08527",
    "addr:street":"Purple Ash Ct",
    "iso:country":"US",
    "sg:address":"2 Purple Ash Ct",
    "sg:city":"Jackson",
    "sg:classifiers":[
        {
            "category":"Wholesale",
            "subcategory":"Medical Equipment & Supplies",
            "type":"Manufacturing & Wholesale Goods"
        }
    ],
    "sg:phone":"+1 732 901 0969",
    "sg:postcode":"08527",
    "sg:province":"NJ",
    "sg:tags":[
        "physician",
        "surgeon"
    ],
    "wof:name":"Dornier Medical Systems Inc",
    "wof:placetype":"venue"
},
  "geometry": {"coordinates":[-74.27846,40.140313],"type":"Point"}
}