{
  "type": "Feature",
  "properties": {
    "iso:country":"US",
    "sg:address":"2479 Pennington Rd",
    "sg:city":"Pennington",
    "sg:classifiers":[
        {
            "category":"Building & Trades",
            "subcategory":"Construction",
            "type":"Services"
        }
    ],
    "sg:phone":"+1 609 737 7243",
    "sg:postcode":"08534",
    "sg:province":"NJ",
    "sg:tags":[
        "general",
        "contractor"
    ],
    "wof:name":"Iew Construction Group",
    "wof:placetype":"venue"
},
  "geometry": {"coordinates":[-74.78425,40.302278],"type":"Point"}
}