{
  "type": "Feature",
  "properties": {
    "addr:full":"230 Middle Rd Hammonton NJ 08037",
    "addr:housenumber":"230",
    "addr:postcode":"08037",
    "addr:street":"Middle Rd",
    "iso:country":"US",
    "sg:address":"230 Middle Rd",
    "sg:city":"Hammonton",
    "sg:classifiers":[
        {
            "category":"Shopping",
            "type":"Retail Goods"
        }
    ],
    "sg:phone":"+1   ",
    "sg:postcode":"08037",
    "sg:province":"NJ",
    "sg:tags":[
        "merchandise"
    ],
    "wof:name":"Coaches Cards",
    "wof:placetype":"venue"
},
  "geometry": {"coordinates":[-74.780666,39.654049],"type":"Point"}
}