{
  "type": "Feature",
  "properties": {
    "iso:country":"US",
    "sg:address":"716 Timberline Dr",
    "sg:city":"Wyckoff",
    "sg:classifiers":[
        {
            "category":"Building & Trades",
            "subcategory":"Plumbing",
            "type":"Services"
        }
    ],
    "sg:phone":"+1 201 227 0068",
    "sg:postcode":"07481",
    "sg:province":"NJ",
    "sg:tags":[
        "contractor"
    ],
    "wof:name":"J&J Plumbing & Htg",
    "wof:placetype":"venue"
},
  "geometry": {"coordinates":[-74.187596,40.994989],"type":"Point"}
}