{
  "type": "Feature",
  "properties": {
    "addr:full":"11 Madison Rd Fairfield NJ 07004",
    "addr:housenumber":"11",
    "addr:postcode":"07004",
    "addr:street":"Madison Rd",
    "iso:country":"US",
    "sg:address":"11 Madison Rd",
    "sg:city":"Fairfield",
    "sg:classifiers":[
        {
            "category":"Wholesale",
            "subcategory":"Office Equipment",
            "type":"Manufacturing & Wholesale Goods"
        }
    ],
    "sg:phone":"+1 973 244 8517",
    "sg:postcode":"07004",
    "sg:province":"NJ",
    "wof:name":"American Office Equipment",
    "wof:placetype":"venue"
},
  "geometry": {"coordinates":[-74.310847,40.871754],"type":"Point"}
}