{
  "type": "Feature",
  "properties": {
    "addr:full":"221 Sherman Ave Berkeley Heights NJ 07922",
    "addr:housenumber":"221",
    "addr:postcode":"07922",
    "addr:street":"Sherman Ave",
    "iso:country":"US",
    "sg:address":"221 Sherman Ave",
    "sg:city":"Berkeley Heights",
    "sg:classifiers":[
        {
            "category":"Freight",
            "type":"Transportation"
        }
    ],
    "sg:phone":"+1 908 790 8800",
    "sg:postcode":"07922",
    "sg:province":"NJ",
    "sg:tags":[
        "arrangement"
    ],
    "wof:name":"UPS Stores",
    "wof:placetype":"venue"
},
  "geometry": {"coordinates":[-74.439818,40.683624],"type":"Point"}
}