{
  "type": "Feature",
  "properties": {
    "addr:full":"29 Main St Allamuchy NJ 07857",
    "addr:housenumber":"29",
    "addr:postcode":"07857",
    "addr:street":"Main St",
    "iso:country":"US",
    "sg:address":"29 Main St",
    "sg:city":"Allamuchy",
    "sg:classifiers":[
        {
            "category":"Retail",
            "subcategory":"Auto Repair",
            "type":"Services"
        }
    ],
    "sg:phone":"+1 908 852 4616",
    "sg:postcode":"07857",
    "sg:province":"NJ",
    "sg:tags":[
        "repairing",
        "automobile"
    ],
    "wof:name":"Allamuchy Garage",
    "wof:placetype":"venue"
},
  "geometry": {"coordinates":[-74.705192,40.90074],"type":"Point"}
}