{
  "type": "Feature",
  "properties": {
    "iso:country":"US",
    "sg:address":"PO Box 382",
    "sg:city":"Pequannock Township",
    "sg:classifiers":[
        {
            "category":"Building & Trades",
            "subcategory":"Construction",
            "type":"Services"
        }
    ],
    "sg:phone":"+1 973 616 5500",
    "sg:postcode":"07444",
    "sg:province":"NJ",
    "sg:tags":[
        "handyman",
        "contractor"
    ],
    "sg:website":"www.housedoctors.com/northjersey",
    "wof:name":"House Doctors of North Jersey",
    "wof:placetype":"venue"
},
  "geometry": {"coordinates":[-74.297222,40.960278],"type":"Point"}
}