{
  "type": "Feature",
  "properties": {
    "addr:full":"417 Main St Manasquan NJ 08736",
    "addr:housenumber":"417",
    "addr:postcode":"08736",
    "addr:street":"Main St",
    "iso:country":"US",
    "sg:address":"417 Main St",
    "sg:city":"Manasquan",
    "sg:classifiers":[
        {
            "category":"Personal",
            "subcategory":"Barber",
            "type":"Services"
        }
    ],
    "sg:phone":"+1 732 449 6004",
    "sg:postcode":"08736",
    "sg:province":"NJ",
    "wof:name":"Towne Barber Shoppe",
    "wof:placetype":"venue"
},
  "geometry": {"coordinates":[-74.04134500000001,40.117201],"type":"Point"}
}