{
  "type": "Feature",
  "properties": {
    "iso:country":"US",
    "sg:address":"1804 Pitney St",
    "sg:city":"Oakhurst",
    "sg:classifiers":[
        {
            "category":"Professional",
            "subcategory":"Detective & Security Services",
            "type":"Services"
        }
    ],
    "sg:phone":"+1 732 531 6192",
    "sg:postcode":"07755",
    "sg:province":"NJ",
    "sg:tags":[
        "investigator"
    ],
    "wof:name":"PAV Investigations",
    "wof:placetype":"venue"
},
  "geometry": {"coordinates":[-74.033152,40.261098],"type":"Point"}
}