{
  "type": "Feature",
  "properties": {
    "addr:full":"50 Winding Wood Dr Sayreville NJ 08872",
    "addr:housenumber":"50",
    "addr:postcode":"08872",
    "addr:street":"Winding Wood Dr",
    "iso:country":"US",
    "sg:address":"50 Winding Wood Dr",
    "sg:city":"Sayreville",
    "sg:classifiers":[
        {
            "category":"Professional",
            "subcategory":"Computer Services",
            "type":"Services"
        }
    ],
    "sg:phone":"+1   ",
    "sg:postcode":"08872",
    "sg:province":"NJ",
    "sg:tags":[
        "processing",
        "datum"
    ],
    "wof:name":"Vertex Data Corporation",
    "wof:placetype":"venue"
},
  "geometry": {"coordinates":[-74.34756,40.427937],"type":"Point"}
}