{
  "type": "Feature",
  "properties": {
    "addr:full":"230 Chandler Rd Jackson NJ 08527",
    "addr:housenumber":"230",
    "addr:postcode":"08527",
    "addr:street":"Chandler Rd",
    "iso:country":"US",
    "sg:address":"230 Chandler Rd",
    "sg:city":"Jackson",
    "sg:classifiers":[
        {
            "category":"Building & Trades",
            "subcategory":"Construction",
            "type":"Services"
        }
    ],
    "sg:phone":"+1 732 367 3743",
    "sg:postcode":"08527",
    "sg:province":"NJ",
    "sg:tags":[
        "masonry",
        "contractor"
    ],
    "wof:name":"Bill's Construction Corp",
    "wof:placetype":"venue"
},
  "geometry": {"coordinates":[-74.28165,40.155724],"type":"Point"}
}