{
  "type": "Feature",
  "properties": {
    "addr:full":"76 Cypress Ln Matawan NJ 07747",
    "addr:housenumber":"76",
    "addr:postcode":"07747",
    "addr:street":"Cypress Ln",
    "iso:country":"US",
    "sg:address":"76 Cypress Ln",
    "sg:city":"Matawan",
    "sg:classifiers":[
        {
            "category":"Personal",
            "type":"Services"
        },
        {
            "category":"Retail",
            "subcategory":"Animal Services",
            "type":"Services"
        }
    ],
    "sg:phone":"+1 732 566 7387",
    "sg:postcode":"07747",
    "sg:province":"NJ",
    "sg:tags":[
        "pet",
        "exercising"
    ],
    "wof:name":"Donna Doolittle's Pet Sitting",
    "wof:placetype":"venue"
},
  "geometry": {"coordinates":[-74.218591,40.403632],"type":"Point"}
}