{
  "type": "Feature",
  "properties": {
    "addr:full":"16 Pocono Rd Denville NJ 07834",
    "addr:housenumber":"16",
    "addr:postcode":"07834",
    "addr:street":"Pocono Rd",
    "iso:country":"US",
    "sg:address":"16 Pocono Rd",
    "sg:city":"Denville",
    "sg:classifiers":[
        {
            "category":"Health Services",
            "subcategory":"Doctor",
            "type":"Services"
        },
        {
            "category":"Wholesale",
            "subcategory":"Computers",
            "type":"Manufacturing & Wholesale Goods"
        }
    ],
    "sg:phone":"+1 973 627 7610",
    "sg:postcode":"07834",
    "sg:province":"NJ",
    "wof:name":"Gastroenterology Associates of North Jersey",
    "wof:placetype":"venue"
},
  "geometry": {"coordinates":[-74.47339599999999,40.894402],"type":"Point"}
}