{
  "type": "Feature",
  "properties": {
    "iso:country":"US",
    "sg:address":"792 E 3rd Ave",
    "sg:city":"Roselle",
    "sg:classifiers":[
        {
            "category":"Manufacturing",
            "subcategory":"Printing",
            "type":"Manufacturing & Wholesale Goods"
        }
    ],
    "sg:phone":"+1 908 298 0604",
    "sg:postcode":"07203",
    "sg:province":"NJ",
    "sg:tags":[
        "lithographic",
        "commercial"
    ],
    "wof:name":"Client Instant Access",
    "wof:placetype":"venue"
},
  "geometry": {"coordinates":[-74.241916,40.660297],"type":"Point"}
}