{
  "type": "Feature",
  "properties": {
    "addr:full":"2211 Whitehorse Mercerville Rd Mercerville NJ 08619",
    "addr:housenumber":"2211",
    "addr:postcode":"08619",
    "addr:street":"Whitehorse Mercerville Rd",
    "iso:country":"US",
    "sg:address":"2211 Whitehorse Mercerville Rd",
    "sg:city":"Mercerville",
    "sg:classifiers":[
        {
            "category":"Insurance",
            "subcategory":"Insurance Agent",
            "type":"Services"
        }
    ],
    "sg:phone":"+1 609 587 4333",
    "sg:postcode":"08619",
    "sg:province":"NJ",
    "sg:website":"www.iianj.org",
    "wof:name":"Independent Insurance Agents",
    "wof:placetype":"venue"
},
  "geometry": {"coordinates":[-74.687141,40.228569],"type":"Point"}
}