{
  "type": "Feature",
  "properties": {
    "iso:country":"US",
    "sg:address":"1037 State Rte 28",
    "sg:city":"Somerville",
    "sg:classifiers":[
        {
            "category":"Food & Beverages",
            "subcategory":"Groceries & Convenience Stores",
            "type":"Retail Goods"
        }
    ],
    "sg:phone":"+1   ",
    "sg:postcode":"08876",
    "sg:province":"NJ",
    "wof:name":"North Branch Gen Stores LLC",
    "wof:placetype":"venue"
},
  "geometry": {"coordinates":[-74.677424,40.601937],"type":"Point"}
}