{
  "type": "Feature",
  "properties": {
    "addr:full":"9 Dorado Dr Morristown NJ 07960",
    "addr:housenumber":"9",
    "addr:postcode":"07960",
    "addr:street":"Dorado Dr",
    "iso:country":"US",
    "sg:address":"9 Dorado Dr",
    "sg:city":"Morristown",
    "sg:classifiers":[
        {
            "category":"Professional",
            "subcategory":"Management & Consulting",
            "type":"Services"
        }
    ],
    "sg:phone":"+1   ",
    "sg:postcode":"07960",
    "sg:province":"NJ",
    "sg:tags":[
        "business",
        "general"
    ],
    "wof:name":"Human Needs Network",
    "wof:placetype":"venue"
},
  "geometry": {"coordinates":[-74.460572,40.787602],"type":"Point"}
}