{
  "type": "Feature",
  "properties": {
    "iso:country":"US",
    "sg:address":"51 Phillips Dr",
    "sg:city":"Old Bridge",
    "sg:classifiers":[
        {
            "category":"Building & Trades",
            "subcategory":"Plumbing",
            "type":"Services"
        }
    ],
    "sg:phone":"+1 732 721 3490",
    "sg:postcode":"08857",
    "sg:province":"NJ",
    "sg:tags":[
        "contractor"
    ],
    "wof:name":"Aqua Spray Lawn Sprinkler",
    "wof:placetype":"venue"
},
  "geometry": {"coordinates":[-74.301413,40.408502],"type":"Point"}
}