{
  "type": "Feature",
  "properties": {
    "iso:country":"US",
    "sg:address":"1580 US Highway 46",
    "sg:city":"Fort Lee",
    "sg:classifiers":[
        {
            "category":"Retail",
            "subcategory":"Auto Repair",
            "type":"Services"
        }
    ],
    "sg:phone":"+1 201 585 0974",
    "sg:postcode":"07024",
    "sg:province":"NJ",
    "wof:name":"ABC Automotive Inc",
    "wof:placetype":"venue"
},
  "geometry": {"coordinates":[-73.983498,40.855301],"type":"Point"}
}