{
  "type": "Feature",
  "properties": {
    "addr:full":"58 Cottage St Bayonne NJ 07002",
    "addr:housenumber":"58",
    "addr:postcode":"07002",
    "addr:street":"Cottage St",
    "iso:country":"US",
    "sg:address":"58 Cottage St",
    "sg:city":"Bayonne",
    "sg:classifiers":[
        {
            "category":"Building & Trades",
            "subcategory":"Construction",
            "type":"Services"
        }
    ],
    "sg:phone":"+1 201 436 8223",
    "sg:postcode":"07002",
    "sg:province":"NJ",
    "sg:tags":[
        "house",
        "contractor"
    ],
    "wof:name":"Ultra Contracting Inc",
    "wof:placetype":"venue"
},
  "geometry": {"coordinates":[-74.124268,40.652314],"type":"Point"}
}