{
  "type": "Feature",
  "properties": {
    "addr:full":"6 Arrow Rd Ramsey NJ 07446",
    "addr:housenumber":"6",
    "addr:postcode":"07446",
    "addr:street":"Arrow Rd",
    "iso:country":"US",
    "sg:address":"6 Arrow Rd",
    "sg:city":"Ramsey",
    "sg:classifiers":[
        {
            "category":"Communications",
            "subcategory":"Film & Video Production",
            "type":"Services"
        }
    ],
    "sg:phone":"+1 201 327 7944",
    "sg:postcode":"07446",
    "sg:province":"NJ",
    "sg:tags":[
        "transference"
    ],
    "wof:name":"Pro Video Services",
    "wof:placetype":"venue"
},
  "geometry": {"coordinates":[-74.123384,41.067903],"type":"Point"}
}