{
  "type": "Feature",
  "properties": {
    "iso:country":"US",
    "sg:address":"309 Warren St",
    "sg:city":"Beverly",
    "sg:classifiers":[
        {
            "category":"Restaurant",
            "type":"Food & Drink"
        }
    ],
    "sg:phone":"+1 609 747 7778",
    "sg:postcode":"08010",
    "sg:province":"NJ",
    "wof:name":"Caribbean Passion Cuisine",
    "wof:placetype":"venue"
},
  "geometry": {"coordinates":[-74.920444,40.064924],"type":"Point"}
}