{
  "type": "Feature",
  "properties": {
    "iso:country":"US",
    "sg:address":"360 Rutherford Blvd",
    "sg:city":"Clifton",
    "sg:classifiers":[
        {
            "category":"Wholesale",
            "subcategory":"Motor Vehicles",
            "type":"Manufacturing & Wholesale Goods"
        },
        {
            "category":"Retail",
            "subcategory":"Auto Repair",
            "type":"Services"
        }
    ],
    "sg:phone":"+1 973 614 1658",
    "sg:postcode":"07014",
    "sg:province":"NJ",
    "sg:tags":[
        "automobile",
        "truck",
        "broker",
        "general"
    ],
    "wof:name":"Jrf Auto Traders Inc",
    "wof:placetype":"venue"
},
  "geometry": {"coordinates":[-74.13845000000001,40.841123],"type":"Point"}
}