{
  "type": "Feature",
  "properties": {
    "iso:country":"US",
    "sg:address":"230 Jackson Mills Rd",
    "sg:city":"Freehold",
    "sg:classifiers":[
        {
            "category":"Building & Trades",
            "subcategory":"Construction",
            "type":"Services"
        }
    ],
    "sg:phone":"+1 732 462 2221",
    "sg:postcode":"07728",
    "sg:province":"NJ",
    "sg:tags":[
        "house"
    ],
    "wof:name":"Preferred Handyman Servic",
    "wof:placetype":"venue"
},
  "geometry": {"coordinates":[-74.282729,40.193503],"type":"Point"}
}