{
  "type": "Feature",
  "properties": {
    "addr:full":"900 Darlington Ave Mahwah NJ 07430",
    "addr:housenumber":"900",
    "addr:postcode":"07430",
    "addr:street":"Darlington Ave",
    "iso:country":"US",
    "sg:address":"900 Darlington Ave",
    "sg:city":"Mahwah",
    "sg:classifiers":[
        {
            "category":"Organizations",
            "subcategory":"Religious Organization",
            "type":"Services"
        }
    ],
    "sg:phone":"+1 201 327 1276",
    "sg:postcode":"07430",
    "sg:province":"NJ",
    "sg:tags":[
        "church"
    ],
    "wof:name":"Immaculate Conception Church",
    "wof:placetype":"venue"
},
  "geometry": {"coordinates":[-74.18164,41.076244],"type":"Point"}
}