{
  "type": "Feature",
  "properties": {
    "addr:full":"254 2nd St Elizabeth NJ 07206",
    "addr:housenumber":"254",
    "addr:postcode":"07206",
    "addr:street":"2Nd St",
    "iso:country":"US",
    "sg:address":"254 2nd St",
    "sg:city":"Elizabeth",
    "sg:classifiers":[
        {
            "category":"Health Services",
            "subcategory":"Doctor",
            "type":"Services"
        }
    ],
    "sg:phone":"+1 908 355 4459",
    "sg:postcode":"07206",
    "sg:province":"NJ",
    "wof:name":"Elizabethport Community Health Center",
    "wof:placetype":"venue"
},
  "geometry": {"coordinates":[-74.1831,40.6538],"type":"Point"}
}