{
  "type": "Feature",
  "properties": {
    "addr:full":"1041 Glassboro Rd Ste C2 Williamstown NJ 08094",
    "addr:housenumber":"1041",
    "addr:postcode":"08094",
    "addr:street":"Glassboro Rd Ste C2",
    "iso:country":"US",
    "sg:address":"1041 Glassboro Rd Ste C2",
    "sg:city":"Williamstown",
    "sg:phone":"+1 856 728 5900",
    "sg:postcode":"08094",
    "sg:province":"NJ",
    "wof:name":"Sunrooms America Inc",
    "wof:placetype":"venue"
},
  "geometry": {"coordinates":[-75.02404,39.690534],"type":"Point"}
}