{
  "type": "Feature",
  "properties": {
    "addr:full":"1200 Summit Ave Union City NJ 07087",
    "addr:housenumber":"1200",
    "addr:postcode":"07087",
    "addr:street":"Summit Ave",
    "iso:country":"US",
    "sg:address":"1200 Summit Ave",
    "sg:city":"Union City",
    "sg:classifiers":[
        {
            "category":"Food & Beverages",
            "subcategory":"Groceries & Convenience Stores",
            "type":"Retail Goods"
        }
    ],
    "sg:phone":"+1 201 617 5580",
    "sg:postcode":"07087",
    "sg:province":"NJ",
    "wof:name":"Summit News",
    "wof:placetype":"venue"
},
  "geometry": {"coordinates":[-74.041303,40.76191],"type":"Point"}
}