{
  "type": "Feature",
  "properties": {
    "iso:country":"US",
    "sg:address":"9 Waterloo Dr",
    "sg:city":"Morris Plains",
    "sg:classifiers":[
        {
            "category":"Building & Trades",
            "subcategory":"Construction",
            "type":"Services"
        }
    ],
    "sg:phone":"+1 973 644 9201",
    "sg:postcode":"07950",
    "sg:province":"NJ",
    "sg:tags":[
        "house"
    ],
    "wof:name":"Ritz Home Improvements",
    "wof:placetype":"venue"
},
  "geometry": {"coordinates":[-74.49165499999999,40.86387],"type":"Point"}
}