{
  "type": "Feature",
  "properties": {
    "iso:country":"US",
    "sg:address":"5 Dellmead Dr",
    "sg:city":"Livingston",
    "sg:classifiers":[
        {
            "category":"Professional",
            "type":"Services"
        }
    ],
    "sg:phone":"+1   ",
    "sg:postcode":"07039",
    "sg:province":"NJ",
    "wof:name":"R C Giobbe Dr",
    "wof:placetype":"venue"
},
  "geometry": {"coordinates":[-74.352177,40.785014],"type":"Point"}
}