{
  "type": "Feature",
  "properties": {
    "iso:country":"US",
    "sg:address":"10 Walton St",
    "sg:city":"Edison",
    "sg:classifiers":[
        {
            "category":"Professional",
            "type":"Services"
        }
    ],
    "sg:phone":"+1 732 393 1197",
    "sg:postcode":"08817",
    "sg:province":"NJ",
    "sg:tags":[
        "establishment"
    ],
    "wof:name":"T&A Studios",
    "wof:placetype":"venue"
},
  "geometry": {"coordinates":[-74.40040999999999,40.497364],"type":"Point"}
}