{
  "type": "Feature",
  "properties": {
    "iso:country":"US",
    "sg:address":"51 Warren Pl",
    "sg:city":"Montclair",
    "sg:classifiers":[
        {
            "category":"Professional",
            "subcategory":"Lawyer & Legal Services",
            "type":"Services"
        }
    ],
    "sg:phone":"+1   ",
    "sg:postcode":"07042",
    "sg:province":"NJ",
    "wof:name":"Janet Pew Attourney",
    "wof:placetype":"venue"
},
  "geometry": {"coordinates":[-74.226392,40.805506],"type":"Point"}
}