{
  "type": "Feature",
  "properties": {
    "iso:country":"US",
    "sg:address":"375 Bloomfield Ave",
    "sg:city":"Newark",
    "sg:classifiers":[
        {
            "category":"Utilities",
            "subcategory":"Telephone",
            "type":"Services"
        }
    ],
    "sg:phone":"+1 973 485 1770",
    "sg:postcode":"07107",
    "sg:province":"NJ",
    "sg:tags":[
        "international",
        "restaurant",
        "facility"
    ],
    "wof:name":"Ecuador Express",
    "wof:placetype":"venue"
},
  "geometry": {"coordinates":[-74.18180099999999,40.7682],"type":"Point"}
}