{
  "type": "Feature",
  "properties": {
    "addr:full":"114 Quinton Alloway Rd Salem NJ 08079",
    "addr:housenumber":"114",
    "addr:postcode":"08079",
    "addr:street":"Quinton Alloway Rd",
    "iso:country":"US",
    "sg:address":"114 Quinton Alloway Rd",
    "sg:city":"Salem",
    "sg:classifiers":[
        {
            "category":"Farming",
            "subcategory":"Farm",
            "type":"Manufacturing & Wholesale Goods"
        }
    ],
    "sg:phone":"+1 856 935 5554",
    "sg:postcode":"08079",
    "sg:province":"NJ",
    "wof:name":"Starlight Farms",
    "wof:placetype":"venue"
},
  "geometry": {"coordinates":[-75.397702,39.553644],"type":"Point"}
}