{
  "type": "Feature",
  "properties": {
    "addr:full":"368 Volley Ct Belmar NJ 07719",
    "addr:housenumber":"368",
    "addr:postcode":"07719",
    "addr:street":"Volley Ct",
    "iso:country":"US",
    "sg:address":"368 Volley Ct",
    "sg:city":"Belmar",
    "sg:classifiers":[
        {
            "category":"Professional",
            "type":"Services"
        }
    ],
    "sg:phone":"+1   ",
    "sg:postcode":"07719",
    "sg:province":"NJ",
    "wof:name":"Griffcom Inc",
    "wof:placetype":"venue"
},
  "geometry": {"coordinates":[-74.076348,40.165593],"type":"Point"}
}