{
  "type": "Feature",
  "properties": {
    "iso:country":"US",
    "sg:address":"34 Arlington Ave",
    "sg:city":"Kearny",
    "sg:classifiers":[
        {
            "category":"Retail",
            "subcategory":"Auto Repair",
            "type":"Services"
        }
    ],
    "sg:phone":"+1 201 997 1811",
    "sg:postcode":"07032",
    "sg:province":"NJ",
    "sg:tags":[
        "automotive"
    ],
    "wof:name":"Wayne Auto Repair",
    "wof:placetype":"venue"
},
  "geometry": {"coordinates":[-74.139297,40.760101],"type":"Point"}
}