{
  "type": "Feature",
  "properties": {
    "addr:full":"756 Centre St Trenton NJ 08611",
    "addr:housenumber":"756",
    "addr:postcode":"08611",
    "addr:street":"Centre St",
    "iso:country":"US",
    "sg:address":"756 Centre St",
    "sg:city":"Trenton",
    "sg:classifiers":[
        {
            "category":"Professional",
            "type":"Services"
        }
    ],
    "sg:phone":"+1 609 599 1736",
    "sg:postcode":"08611",
    "sg:province":"NJ",
    "sg:tags":[
        "establishment"
    ],
    "wof:name":"Internet Concept & Technology",
    "wof:placetype":"venue"
},
  "geometry": {"coordinates":[-74.756455,40.198087],"type":"Point"}
}