{
  "type": "Feature",
  "properties": {
    "iso:country":"US",
    "sg:address":"361 W Dewey Ave",
    "sg:city":"Wharton",
    "sg:classifiers":[
        {
            "category":"Building & Trades",
            "subcategory":"Construction",
            "type":"Services"
        }
    ],
    "sg:phone":"+1 973 989 2626",
    "sg:postcode":"07885",
    "sg:province":"NJ",
    "sg:tags":[
        "masonry",
        "contractor"
    ],
    "wof:name":"T Polito Enterprise Inc",
    "wof:placetype":"venue"
},
  "geometry": {"coordinates":[-74.601581,40.903145],"type":"Point"}
}