{
  "type": "Feature",
  "properties": {
    "iso:country":"US",
    "sg:address":"137 Midland Ave",
    "sg:city":"Kearny",
    "sg:classifiers":[
        {
            "category":"Health Services",
            "subcategory":"Doctor",
            "type":"Services"
        }
    ],
    "sg:phone":"+1 201 246 1400",
    "sg:postcode":"07032",
    "sg:province":"NJ",
    "sg:tags":[
        "dentist"
    ],
    "wof:name":"Midland Family Dentistry",
    "wof:placetype":"venue"
},
  "geometry": {"coordinates":[-74.14311499999999,40.769792],"type":"Point"}
}