{
  "type": "Feature",
  "properties": {
    "addr:full":"639 Glassboro Rd Woodbury Heights NJ 08097",
    "addr:housenumber":"639",
    "addr:postcode":"08097",
    "addr:street":"Glassboro Rd",
    "iso:country":"US",
    "sg:address":"639 Glassboro Rd",
    "sg:city":"Woodbury Heights",
    "sg:classifiers":[
        {
            "category":"Food & Beverages",
            "subcategory":"Groceries & Convenience Stores",
            "type":"Retail Goods"
        }
    ],
    "sg:phone":"+1 856 468 5459",
    "sg:postcode":"08097",
    "sg:province":"NJ",
    "sg:tags":[
        "grocer"
    ],
    "wof:name":"Bernie's Market",
    "wof:placetype":"venue"
},
  "geometry": {"coordinates":[-75.148932,39.817132],"type":"Point"}
}