{
  "type": "Feature",
  "properties": {
    "iso:country":"US",
    "sg:address":"98 Skyline Dr",
    "sg:city":"Morristown",
    "sg:classifiers":[
        {
            "category":"Professional",
            "type":"Services"
        }
    ],
    "sg:phone":"+1   ",
    "sg:postcode":"07960",
    "sg:province":"NJ",
    "wof:name":"Kdds III LLC",
    "wof:placetype":"venue"
},
  "geometry": {"coordinates":[-74.500457,40.782569],"type":"Point"}
}