{
  "type": "Feature",
  "properties": {
    "iso:country":"US",
    "sg:address":"407 Boardwalk",
    "sg:city":"Point Pleasant",
    "sg:classifiers":[
        {
            "category":"Recreation",
            "subcategory":"Arcade",
            "type":"Entertainment"
        }
    ],
    "sg:phone":"+1 732 892 8981",
    "sg:postcode":"08742",
    "sg:province":"NJ",
    "wof:name":"Frank's Fun Ctr",
    "wof:placetype":"venue"
},
  "geometry": {"coordinates":[-74.03665599999999,40.093667],"type":"Point"}
}