{
  "type": "Feature",
  "properties": {
    "iso:country":"US",
    "sg:address":"108 Troy Hills Rd",
    "sg:city":"Whippany",
    "sg:classifiers":[
        {
            "category":"Professional",
            "subcategory":"Employment Agencies",
            "type":"Services"
        }
    ],
    "sg:phone":"+1 973 386 9532",
    "sg:postcode":"07981",
    "sg:province":"NJ",
    "wof:name":"L A Michalski Miss Rn",
    "wof:placetype":"venue"
},
  "geometry": {"coordinates":[-74.39673500000001,40.8287],"type":"Point"}
}