{
  "type": "Feature",
  "properties": {
    "iso:country":"US",
    "sg:address":"690 State Rte 70",
    "sg:city":"Brick",
    "sg:classifiers":[
        {
            "category":"Shopping",
            "type":"Retail Goods"
        }
    ],
    "sg:phone":"+1 732 262 4890",
    "sg:postcode":"08723",
    "sg:province":"NJ",
    "sg:tags":[
        "telephone",
        "cellular"
    ],
    "wof:name":"T Mobile Brick",
    "wof:placetype":"venue"
},
  "geometry": {"coordinates":[-74.141316,40.060363],"type":"Point"}
}