{
  "type": "Feature",
  "properties": {
    "iso:country":"US",
    "sg:address":"1537 State Rte 77",
    "sg:city":"Bridgeton",
    "sg:classifiers":[
        {
            "category":"Restaurant",
            "type":"Food & Drink"
        }
    ],
    "sg:phone":"+1 856 459 0999",
    "sg:postcode":"08302",
    "sg:province":"NJ",
    "sg:tags":[
        "delicatessen"
    ],
    "wof:name":"Red Barn Deli",
    "wof:placetype":"venue"
},
  "geometry": {"coordinates":[-75.235687,39.522807],"type":"Point"}
}