{
  "type": "Feature",
  "properties": {
    "addr:full":"820 Main Ave Passaic NJ 07055",
    "addr:housenumber":"820",
    "addr:postcode":"07055",
    "addr:street":"Main Ave",
    "iso:country":"US",
    "sg:address":"820 Main Ave",
    "sg:city":"Passaic",
    "sg:classifiers":[
        {
            "category":"Home & Garden",
            "subcategory":"Furniture",
            "type":"Retail Goods"
        }
    ],
    "sg:phone":"+1   ",
    "sg:postcode":"07055",
    "sg:province":"NJ",
    "wof:name":"Perry Rosenblum",
    "wof:placetype":"venue"
},
  "geometry": {"coordinates":[-74.13065899999999,40.865741],"type":"Point"}
}