{
  "type": "Feature",
  "properties": {
    "iso:country":"US",
    "sg:address":"243 Clove Rd",
    "sg:city":"Montague",
    "sg:classifiers":[
        {
            "category":"Building & Trades",
            "subcategory":"Construction",
            "type":"Services"
        }
    ],
    "sg:phone":"+1 973 293 3120",
    "sg:postcode":"07827",
    "sg:province":"NJ",
    "sg:tags":[
        "residence",
        "speculative",
        "general",
        "builder",
        "contractor"
    ],
    "wof:name":"Eagle Construction Co",
    "wof:placetype":"venue"
},
  "geometry": {"coordinates":[-74.760493,41.313076],"type":"Point"}
}