{
  "type": "Feature",
  "properties": {
    "addr:full":"8 State Rt 5 Palisades Park NJ 07650",
    "addr:housenumber":"8",
    "addr:postcode":"07650",
    "addr:street":"State Rt 5",
    "iso:country":"US",
    "sg:address":"8 State Rt 5",
    "sg:city":"Palisades Park",
    "sg:classifiers":[
        {
            "category":"Restaurant",
            "type":"Food & Drink"
        }
    ],
    "sg:phone":"+1 201 943 8228",
    "sg:postcode":"07650",
    "sg:province":"NJ",
    "sg:tags":[
        "chinese"
    ],
    "wof:name":"Taste of China",
    "wof:placetype":"venue"
},
  "geometry": {"coordinates":[-73.9991,40.840302],"type":"Point"}
}