{
  "type": "Feature",
  "properties": {
    "iso:country":"US",
    "sg:address":"125 Randolph St",
    "sg:city":"Carteret",
    "sg:classifiers":[
        {
            "category":"Shopping",
            "subcategory":"Hobbies, Toys, & Games",
            "type":"Retail Goods"
        }
    ],
    "sg:phone":"+1 732 969 1302",
    "sg:postcode":"07008",
    "sg:province":"NJ",
    "sg:tags":[
        "craft"
    ],
    "wof:name":"C & C Creation Inc",
    "wof:placetype":"venue"
},
  "geometry": {"coordinates":[-74.219769,40.581573],"type":"Point"}
}