{
  "type": "Feature",
  "properties": {
    "iso:country":"US",
    "sg:address":"833 Kings Hwy",
    "sg:city":"Woodbury",
    "sg:classifiers":[
        {
            "category":"Insurance",
            "subcategory":"Insurance Agent",
            "type":"Services"
        }
    ],
    "sg:phone":"+1 856 686 9306",
    "sg:postcode":"08096",
    "sg:province":"NJ",
    "sg:tags":[
        "consultant"
    ],
    "wof:name":"Insurance & Investment Svc",
    "wof:placetype":"venue"
},
  "geometry": {"coordinates":[-75.174678,39.825297],"type":"Point"}
}