{
  "type": "Feature",
  "properties": {
    "iso:country":"US",
    "sg:address":"637 White Horse Pike",
    "sg:city":"Oaklyn",
    "sg:classifiers":[
        {
            "category":"Shopping",
            "subcategory":"Clothing, Apparel, & Fashions",
            "type":"Retail Goods"
        }
    ],
    "sg:phone":"+1 856 833 1100",
    "sg:postcode":"08107",
    "sg:province":"NJ",
    "sg:tags":[
        "accessory"
    ],
    "sg:website":"www.pinklace6227.com",
    "wof:name":"Pinklace",
    "wof:placetype":"venue"
},
  "geometry": {"coordinates":[-75.076691,39.902351],"type":"Point"}
}