{
  "type": "Feature",
  "properties": {
    "iso:country":"US",
    "sg:address":"484 Macarthur Ave",
    "sg:city":"Garfield",
    "sg:classifiers":[
        {
            "category":"Building & Trades",
            "subcategory":"Construction",
            "type":"Services"
        }
    ],
    "sg:phone":"+1 973 772 8010",
    "sg:postcode":"07026",
    "sg:province":"NJ",
    "sg:tags":[
        "hanging",
        "contractor"
    ],
    "wof:name":"Quality Painting",
    "wof:placetype":"venue"
},
  "geometry": {"coordinates":[-74.09416,40.883914],"type":"Point"}
}