{
  "type": "Feature",
  "properties": {
    "iso:country":"US",
    "sg:address":"205 Main St",
    "sg:city":"Chester",
    "sg:classifiers":[
        {
            "category":"Professional",
            "subcategory":"Business Services",
            "type":"Services"
        }
    ],
    "sg:phone":"+1 908 879 2600",
    "sg:postcode":"07930",
    "sg:province":"NJ",
    "sg:tags":[
        "interior",
        "consultant",
        "design",
        "decorator"
    ],
    "wof:name":"Interior Flooring Solutions",
    "wof:placetype":"venue"
},
  "geometry": {"coordinates":[-74.691935,40.786709],"type":"Point"}
}