{
  "type": "Feature",
  "properties": {
    "addr:full":"121 Summit Ave Summit NJ 07901",
    "addr:housenumber":"121",
    "addr:postcode":"07901",
    "addr:street":"Summit Ave",
    "iso:country":"US",
    "sg:address":"121 Summit Ave",
    "sg:city":"Summit",
    "sg:classifiers":[
        {
            "category":"Health Services",
            "subcategory":"Dentist",
            "type":"Services"
        }
    ],
    "sg:phone":"+1 908 277 4050",
    "sg:postcode":"07901",
    "sg:province":"NJ",
    "wof:name":"Tymeson W Robert Jr DDS",
    "wof:placetype":"venue"
},
  "geometry": {"coordinates":[-74.35603500000001,40.719095],"type":"Point"}
}