{
  "type": "Feature",
  "properties": {
    "iso:country":"US",
    "sg:address":"362 State Rte 33",
    "sg:city":"Trenton",
    "sg:classifiers":[
        {
            "category":"Shopping",
            "subcategory":"Computers & Home Electronics",
            "type":"Retail Goods"
        }
    ],
    "sg:phone":"+1 609 588 5303",
    "sg:postcode":"08619",
    "sg:province":"NJ",
    "sg:tags":[
        "high",
        "fidelity",
        "stereophonic"
    ],
    "wof:name":"Dream Sound & Vision",
    "wof:placetype":"venue"
},
  "geometry": {"coordinates":[-74.68649000000001,40.233396],"type":"Point"}
}