{
  "type": "Feature",
  "properties": {
    "addr:full":"2181 Springfield Ave Vauxhall NJ 07088",
    "addr:housenumber":"2181",
    "addr:postcode":"07088",
    "addr:street":"Springfield Ave",
    "iso:country":"US",
    "sg:address":"2181 Springfield Ave",
    "sg:city":"Vauxhall",
    "sg:classifiers":[
        {
            "category":"Personal",
            "subcategory":"Beauty Salon",
            "type":"Services"
        }
    ],
    "sg:phone":"+1 908 687 8115",
    "sg:postcode":"07088",
    "sg:province":"NJ",
    "sg:tags":[
        "hair"
    ],
    "wof:name":"Shear Essence Hair Studio LLC",
    "wof:placetype":"venue"
},
  "geometry": {"coordinates":[-74.28272699999999,40.718624],"type":"Point"}
}