{
  "type": "Feature",
  "properties": {
    "iso:country":"US",
    "sg:address":"31 Main St",
    "sg:city":"Englishtown",
    "sg:classifiers":[
        {
            "category":"Retail",
            "subcategory":"Laundry & Dry Cleaning",
            "type":"Services"
        }
    ],
    "sg:phone":"+1 732 786 9111",
    "sg:postcode":"07726",
    "sg:province":"NJ",
    "sg:tags":[
        "cleaners"
    ],
    "wof:name":"Main Steet Drive-Thru Cleaners",
    "wof:placetype":"venue"
},
  "geometry": {"coordinates":[-74.358391,40.296413],"type":"Point"}
}