{
  "type": "Feature",
  "properties": {
    "iso:country":"US",
    "sg:address":"2518 Boardwalk",
    "sg:city":"Wildwood",
    "sg:classifiers":[
        {
            "category":"Wholesale",
            "subcategory":"Dairy",
            "type":"Manufacturing & Wholesale Goods"
        }
    ],
    "sg:phone":"+1 609 522 0496",
    "sg:postcode":"08260",
    "sg:province":"NJ",
    "sg:tags":[
        "frozen",
        "dessert",
        "yogurt",
        "ice",
        "cream"
    ],
    "sg:website":"www.kohrbros.com",
    "wof:name":"Kohr Bros Frozen Custard",
    "wof:placetype":"venue"
},
  "geometry": {"coordinates":[-74.80410000000001,38.9902],"type":"Point"}
}