{
  "type": "Feature",
  "properties": {
    "iso:country":"US",
    "sg:address":"199 Grandview Rd",
    "sg:city":"Skillman",
    "sg:classifiers":[
        {
            "category":"Manufacturing",
            "subcategory":"Tools & Machinery",
            "type":"Manufacturing & Wholesale Goods"
        }
    ],
    "sg:phone":"+1 908 874 1000",
    "sg:postcode":"08558",
    "sg:province":"NJ",
    "sg:tags":[
        "adhesive",
        "mfg",
        "wound",
        "bandage",
        "tape"
    ],
    "wof:name":"Johnson Jhnson Cnsmr Companies",
    "wof:placetype":"venue"
},
  "geometry": {"coordinates":[-74.696415,40.436001],"type":"Point"}
}