{
  "type": "Feature",
  "properties": {
    "addr:full":"186 Haddon Ave West Berlin NJ 08091",
    "addr:housenumber":"186",
    "addr:postcode":"08091",
    "addr:street":"Haddon Ave",
    "iso:country":"US",
    "sg:address":"186 Haddon Ave",
    "sg:city":"West Berlin",
    "sg:classifiers":[
        {
            "category":"Government",
            "subcategory":"Fire Station",
            "type":"Public Place"
        }
    ],
    "sg:phone":"+1   ",
    "sg:postcode":"08091",
    "sg:province":"NJ",
    "sg:tags":[
        "company",
        "volunteer"
    ],
    "wof:name":"Fire Dist 1 Twp",
    "wof:placetype":"venue"
},
  "geometry": {"coordinates":[-74.94338399999999,39.811587],"type":"Point"}
}