{
  "type": "Feature",
  "properties": {
    "addr:full":"3037 State Rte 23 Franklin NJ 07416",
    "addr:housenumber":"3037",
    "addr:postcode":"07416",
    "addr:street":"State Rte 23",
    "iso:country":"US",
    "sg:address":"3037 State Rte 23",
    "sg:city":"Franklin",
    "sg:classifiers":[
        {
            "category":"Wholesale",
            "subcategory":"Office Equipment",
            "type":"Manufacturing & Wholesale Goods"
        }
    ],
    "sg:phone":"+1 973 762 0192",
    "sg:postcode":"07416",
    "sg:province":"NJ",
    "sg:tags":[
        "register",
        "cash",
        "supply"
    ],
    "wof:name":"Buyer's Network Retail Bus",
    "wof:placetype":"venue"
},
  "geometry": {"coordinates":[-74.57708700000001,41.101172],"type":"Point"}
}