{
  "type": "Feature",
  "properties": {
    "addr:full":"111 Melrich Rd Cranbury NJ 08512",
    "addr:housenumber":"111",
    "addr:postcode":"08512",
    "addr:street":"Melrich Rd",
    "iso:country":"US",
    "sg:address":"111 Melrich Rd",
    "sg:city":"Cranbury",
    "sg:classifiers":[
        {
            "category":"Manufacturing",
            "subcategory":"Glass & Minerals",
            "type":"Manufacturing & Wholesale Goods"
        }
    ],
    "sg:phone":"+1 732 225 7200",
    "sg:postcode":"08512",
    "sg:province":"NJ",
    "sg:tags":[
        "mfg",
        "candy",
        "arrangement"
    ],
    "wof:name":"Candy Art LLC",
    "wof:placetype":"venue"
},
  "geometry": {"coordinates":[-74.50752,40.340988],"type":"Point"}
}