{
  "type": "Feature",
  "properties": {
    "iso:country":"US",
    "sg:address":"1451 State Rte 88",
    "sg:city":"Brick",
    "sg:classifiers":[
        {
            "category":"Professional",
            "subcategory":"Accounting & Tax Preparation",
            "type":"Services"
        }
    ],
    "sg:phone":"+1 732 836 1040",
    "sg:postcode":"08724",
    "sg:province":"NJ",
    "sg:tags":[
        "accountant"
    ],
    "wof:name":"Andrew M Baer CPA",
    "wof:placetype":"venue"
},
  "geometry": {"coordinates":[-74.147364,40.082503],"type":"Point"}
}