{
  "type": "Feature",
  "properties": {
    "addr:full":"625 Summit Ave Westville NJ 08093",
    "addr:housenumber":"625",
    "addr:postcode":"08093",
    "addr:street":"Summit Ave",
    "iso:country":"US",
    "sg:address":"625 Summit Ave",
    "sg:city":"Westville",
    "sg:classifiers":[
        {
            "category":"Building & Trades",
            "subcategory":"Construction",
            "type":"Services"
        }
    ],
    "sg:phone":"+1 856 742 0290",
    "sg:postcode":"08093",
    "sg:province":"NJ",
    "sg:tags":[
        "house",
        "real estate"
    ],
    "wof:name":"Albright Home Improvements",
    "wof:placetype":"venue"
},
  "geometry": {"coordinates":[-75.13489300000001,39.87794],"type":"Point"}
}