{
  "type": "Feature",
  "properties": {
    "iso:country":"US",
    "sg:address":"700 Washington St",
    "sg:city":"Boonton",
    "sg:classifiers":[
        {
            "category":"Manufacturing",
            "subcategory":"Printing",
            "type":"Manufacturing & Wholesale Goods"
        }
    ],
    "sg:phone":"+1 973 263 6933",
    "sg:postcode":"07005",
    "sg:province":"NJ",
    "sg:tags":[
        "book"
    ],
    "wof:name":"Frank Tarsitano",
    "wof:placetype":"venue"
},
  "geometry": {"coordinates":[-74.410192,40.894908],"type":"Point"}
}