{
  "type": "Feature",
  "properties": {
    "addr:full":"132 Magnolia Ave Sea Girt NJ 08750",
    "addr:housenumber":"132",
    "addr:postcode":"08750",
    "addr:street":"Magnolia Ave",
    "iso:country":"US",
    "sg:address":"132 Magnolia Ave",
    "sg:city":"Sea Girt",
    "sg:classifiers":[
        {
            "category":"Insurance",
            "subcategory":"Life Insurance",
            "type":"Services"
        }
    ],
    "sg:phone":"+1   ",
    "sg:postcode":"08750",
    "sg:province":"NJ",
    "sg:tags":[
        "carrier"
    ],
    "wof:name":"Sons of Norway",
    "wof:placetype":"venue"
},
  "geometry": {"coordinates":[-74.050905,40.134848],"type":"Point"}
}