{
  "type": "Feature",
  "properties": {
    "iso:country":"US",
    "sg:address":"7 Mitchell Ave",
    "sg:city":"New Brunswick",
    "sg:classifiers":[
        {
            "category":"Professional",
            "type":"Services"
        }
    ],
    "sg:phone":"+1   ",
    "sg:postcode":"08901",
    "sg:province":"NJ",
    "wof:name":"Vilas Urtekar",
    "wof:placetype":"venue"
},
  "geometry": {"coordinates":[-74.465157,40.484514],"type":"Point"}
}