{
  "type": "Feature",
  "properties": {
    "addr:full":"21 Industrial Dr Keyport NJ 07735",
    "addr:housenumber":"21",
    "addr:postcode":"07735",
    "addr:street":"Industrial Dr",
    "iso:country":"US",
    "sg:address":"21 Industrial Dr",
    "sg:city":"Keyport",
    "sg:classifiers":[
        {
            "category":"Wholesale",
            "subcategory":"Non-durable Goods",
            "type":"Manufacturing & Wholesale Goods"
        }
    ],
    "sg:phone":"+1 732 290 3000",
    "sg:postcode":"07735",
    "sg:province":"NJ",
    "wof:name":"Intec Corp",
    "wof:placetype":"venue"
},
  "geometry": {"coordinates":[-74.24285,40.44752],"type":"Point"}
}