{
  "type": "Feature",
  "properties": {
    "iso:country":"US",
    "sg:address":"107 S Main St",
    "sg:city":"Pleasantville",
    "sg:classifiers":[
        {
            "category":"Education",
            "subcategory":"Special Training",
            "type":"Public Place"
        }
    ],
    "sg:phone":"+1 609 383 2500",
    "sg:postcode":"08232",
    "sg:province":"NJ",
    "sg:tags":[
        "instruction",
        "driving"
    ],
    "wof:name":"Superior Tractor Trailer Trng",
    "wof:placetype":"venue"
},
  "geometry": {"coordinates":[-74.523532,39.390781],"type":"Point"}
}