{
  "type": "Feature",
  "properties": {
    "iso:country":"US",
    "sg:address":"11 N Main St",
    "sg:city":"Woodstown",
    "sg:classifiers":[
        {
            "category":"Professional",
            "subcategory":"Lawyer & Legal Services",
            "type":"Services"
        }
    ],
    "sg:phone":"+1 856 769 3100",
    "sg:postcode":"08098",
    "sg:province":"NJ",
    "wof:name":"John G Hoffman",
    "wof:placetype":"venue"
},
  "geometry": {"coordinates":[-75.327941,39.652197],"type":"Point"}
}