{
  "type": "Feature",
  "properties": {
    "iso:country":"US",
    "sg:address":"321 Broadway",
    "sg:city":"Westwood",
    "sg:classifiers":[
        {
            "category":"Banks & Credit Unions",
            "subcategory":"Financial Services",
            "type":"Services"
        }
    ],
    "sg:phone":"+1 201 666 6813",
    "sg:postcode":"07675",
    "sg:province":"NJ",
    "sg:tags":[
        "investor"
    ],
    "wof:name":"R L Investors",
    "wof:placetype":"venue"
},
  "geometry": {"coordinates":[-74.032562,40.990969],"type":"Point"}
}