{
  "type": "Feature",
  "properties": {
    "addr:full":"888 Newark Ave Jersey City NJ 07306",
    "addr:housenumber":"888",
    "addr:postcode":"07306",
    "addr:street":"Newark Ave",
    "iso:country":"US",
    "sg:address":"888 Newark Ave",
    "sg:city":"Jersey City",
    "sg:classifiers":[
        {
            "category":"Professional",
            "subcategory":"Management & Consulting",
            "type":"Services"
        }
    ],
    "sg:phone":"+1   ",
    "sg:postcode":"07306",
    "sg:province":"NJ",
    "sg:tags":[
        "environmental",
        "engineering"
    ],
    "wof:name":"Mak Technologies",
    "wof:placetype":"venue"
},
  "geometry": {"coordinates":[-74.068528,40.736343],"type":"Point"}
}