{
  "type": "Feature",
  "properties": {
    "iso:country":"US",
    "sg:address":"600 Martin Luther King Jr Ave",
    "sg:city":"Pleasantville",
    "sg:classifiers":[
        {
            "category":"Manufacturing",
            "subcategory":"Signs",
            "type":"Manufacturing & Wholesale Goods"
        },
        {
            "category":"Manufacturing",
            "subcategory":"Printing",
            "type":"Manufacturing & Wholesale Goods"
        }
    ],
    "sg:phone":"+1 609 645 9268",
    "sg:postcode":"08232",
    "sg:province":"NJ",
    "sg:tags":[
        "screen",
        "specialty",
        "mfg"
    ],
    "wof:name":"Allen Signs",
    "wof:placetype":"venue"
},
  "geometry": {"coordinates":[-74.529706,39.396639],"type":"Point"}
}