{
  "type": "Feature",
  "properties": {
    "iso:country":"US",
    "sg:address":"206 Lakewood Dr",
    "sg:city":"Bloomfield",
    "sg:classifiers":[
        {
            "category":"Building & Trades",
            "subcategory":"Construction",
            "type":"Services"
        }
    ],
    "sg:phone":"+1 973 566 9010",
    "sg:postcode":"07003",
    "sg:province":"NJ",
    "sg:tags":[
        "contractor"
    ],
    "wof:name":"Family Construction",
    "wof:placetype":"venue"
},
  "geometry": {"coordinates":[-74.189775,40.815836],"type":"Point"}
}