{
  "type": "Feature",
  "properties": {
    "addr:full":"275 93rd St Stone Harbor NJ 08247",
    "addr:housenumber":"275",
    "addr:postcode":"08247",
    "addr:street":"93Rd St",
    "iso:country":"US",
    "sg:address":"275 93rd St",
    "sg:city":"Stone Harbor",
    "sg:classifiers":[
        {
            "category":"Education",
            "subcategory":"School",
            "type":"Public Place"
        }
    ],
    "sg:phone":"+1 609 368 4413",
    "sg:postcode":"08247",
    "sg:province":"NJ",
    "sg:tags":[
        "high",
        "middle",
        "elementary"
    ],
    "wof:name":"Stone Harbor School District",
    "wof:placetype":"venue"
},
  "geometry": {"coordinates":[-74.758002,39.056094],"type":"Point"}
}