{
  "type": "Feature",
  "properties": {
    "addr:full":"141 Stuyvesant Ave Newark NJ 07106",
    "addr:housenumber":"141",
    "addr:postcode":"07106",
    "addr:street":"Stuyvesant Ave",
    "iso:country":"US",
    "sg:address":"141 Stuyvesant Ave",
    "sg:city":"Newark",
    "sg:classifiers":[
        {
            "category":"Building & Trades",
            "subcategory":"Construction",
            "type":"Services"
        }
    ],
    "sg:phone":"+1 973 371 1696",
    "sg:postcode":"07106",
    "sg:province":"NJ",
    "sg:tags":[
        "contractor"
    ],
    "wof:name":"Universal Contracting LLC",
    "wof:placetype":"venue"
},
  "geometry": {"coordinates":[-74.23048199999999,40.741846],"type":"Point"}
}