{
  "type": "Feature",
  "properties": {
    "iso:country":"US",
    "sg:address":"2234 Marlton Pike",
    "sg:city":"Cherry Hill",
    "sg:classifiers":[
        {
            "category":"Retail",
            "subcategory":"Laundry & Dry Cleaning",
            "type":"Services"
        }
    ],
    "sg:phone":"+1 856 964 9467",
    "sg:postcode":"08002",
    "sg:province":"NJ",
    "sg:tags":[
        "launderer",
        "industrial"
    ],
    "wof:name":"Onavy",
    "wof:placetype":"venue"
},
  "geometry": {"coordinates":[-75.045767,39.924206],"type":"Point"}
}