{
  "type": "Feature",
  "properties": {
    "addr:full":"219 Intervale Rd Boonton NJ 07046",
    "addr:housenumber":"219",
    "addr:postcode":"07046",
    "addr:street":"Intervale Rd",
    "iso:country":"US",
    "sg:address":"219 Intervale Rd",
    "sg:city":"Boonton",
    "sg:classifiers":[
        {
            "category":"Professional",
            "subcategory":"Computer Services",
            "type":"Services"
        }
    ],
    "sg:phone":"+1   ",
    "sg:postcode":"07046",
    "sg:province":"NJ",
    "sg:tags":[
        "related"
    ],
    "wof:name":"Elangeni Consulting Inc",
    "wof:placetype":"venue"
},
  "geometry": {"coordinates":[-74.43116499999999,40.88091],"type":"Point"}
}