{
  "type": "Feature",
  "properties": {
    "addr:full":"275 E US Highway 22 N Springfield NJ 07081",
    "addr:housenumber":"275",
    "addr:postcode":"07081",
    "addr:street":"E Us Highway 22 N",
    "iso:country":"US",
    "sg:address":"275 E US Highway 22 N",
    "sg:city":"Springfield",
    "sg:classifiers":[
        {
            "category":"Health Services",
            "subcategory":"Optometrist",
            "type":"Services"
        }
    ],
    "sg:phone":"+1 973 376 9465",
    "sg:postcode":"07081",
    "sg:province":"NJ",
    "sg:website":"www.pearlevision.com",
    "wof:name":"Pearle Vision Express",
    "wof:placetype":"venue"
},
  "geometry": {"coordinates":[-74.325469,40.684925],"type":"Point"}
}