{
  "type": "Feature",
  "properties": {
    "iso:country":"US",
    "sg:address":"18 Exeter Pass",
    "sg:city":"Colts Neck",
    "sg:classifiers":[
        {
            "category":"Retail",
            "subcategory":"Portrait Studio",
            "type":"Services"
        }
    ],
    "sg:phone":"+1 732 780 1870",
    "sg:postcode":"07722",
    "sg:province":"NJ",
    "sg:tags":[
        "photographer"
    ],
    "wof:name":"Backyard Photography",
    "wof:placetype":"venue"
},
  "geometry": {"coordinates":[-74.22113,40.268847],"type":"Point"}
}