{
  "type": "Feature",
  "properties": {
    "iso:country":"US",
    "sg:address":"107 Stella Ct",
    "sg:city":"Paramus",
    "sg:classifiers":[
        {
            "category":"Social Services",
            "type":"Services"
        }
    ],
    "sg:phone":"+1 201 261 2818",
    "sg:postcode":"07652",
    "sg:province":"NJ",
    "sg:tags":[
        "counselor",
        "marriage",
        "family"
    ],
    "wof:name":"Paramus Counseling Ctr",
    "wof:placetype":"venue"
},
  "geometry": {"coordinates":[-74.07317399999999,40.973988],"type":"Point"}
}