{
  "type": "Feature",
  "properties": {
    "addr:full":"539 Elizabeth Ave Elizabeth NJ 07206",
    "addr:housenumber":"539",
    "addr:postcode":"07206",
    "addr:street":"Elizabeth Ave",
    "iso:country":"US",
    "sg:address":"539 Elizabeth Ave",
    "sg:city":"Elizabeth",
    "sg:classifiers":[
        {
            "category":"Restaurant",
            "type":"Food & Drink"
        }
    ],
    "sg:phone":"+1   ",
    "sg:postcode":"07206",
    "sg:province":"NJ",
    "sg:tags":[
        "eating"
    ],
    "wof:name":"Girasol Restaurant",
    "wof:placetype":"venue"
},
  "geometry": {"coordinates":[-74.199279,40.655287],"type":"Point"}
}