{
  "type": "Feature",
  "properties": {
    "iso:country":"US",
    "sg:address":"912 Warwick Tpke",
    "sg:city":"Hewitt",
    "sg:classifiers":[
        {
            "category":"Building & Trades",
            "subcategory":"Construction",
            "type":"Services"
        }
    ],
    "sg:phone":"+1 973 853 4666",
    "sg:postcode":"07421",
    "sg:province":"NJ",
    "sg:tags":[
        "home",
        "improvement",
        "contractor"
    ],
    "wof:name":"Clauss Construction Company",
    "wof:placetype":"venue"
},
  "geometry": {"coordinates":[-74.383582,41.210867],"type":"Point"}
}