{
  "type": "Feature",
  "properties": {
    "addr:full":"106 Pine St Hackensack NJ 07601",
    "addr:housenumber":"106",
    "addr:postcode":"07601",
    "addr:street":"Pine St",
    "iso:country":"US",
    "sg:address":"106 Pine St",
    "sg:city":"Hackensack",
    "sg:classifiers":[
        {
            "category":"Professional",
            "subcategory":"Computer Services",
            "type":"Services"
        }
    ],
    "sg:phone":"+1 201 342 6905",
    "sg:postcode":"07601",
    "sg:province":"NJ",
    "sg:tags":[
        "design",
        "system"
    ],
    "wof:name":"Solve It Computer Svcs",
    "wof:placetype":"venue"
},
  "geometry": {"coordinates":[-74.043717,40.903446],"type":"Point"}
}