{
  "type": "Feature",
  "properties": {
    "addr:full":"3 Executive Campus Cherry Hill NJ 08002",
    "addr:housenumber":"3",
    "addr:postcode":"08002",
    "iso:country":"US",
    "sg:address":"3 Executive Campus",
    "sg:city":"Cherry Hill",
    "sg:classifiers":[
        {
            "category":"Community Center",
            "type":"Public Place"
        }
    ],
    "sg:phone":"+1 856 665 4597",
    "sg:postcode":"08002",
    "sg:province":"NJ",
    "sg:tags":[
        "medical"
    ],
    "wof:name":"Cooper Medical Center",
    "wof:placetype":"venue"
},
  "geometry": {"coordinates":[-75.045303,39.925499],"type":"Point"}
}