{
  "type": "Feature",
  "properties": {
    "addr:full":"243 E State St Trenton NJ 08608",
    "addr:housenumber":"243",
    "addr:postcode":"08608",
    "addr:street":"E State St",
    "iso:country":"US",
    "sg:address":"243 E State St",
    "sg:city":"Trenton",
    "sg:classifiers":[
        {
            "category":"Utilities",
            "subcategory":"Telephone",
            "type":"Services"
        }
    ],
    "sg:phone":"+1 609 890 3014",
    "sg:postcode":"08608",
    "sg:province":"NJ",
    "sg:tags":[
        "communications"
    ],
    "wof:name":"Verizon",
    "wof:placetype":"venue"
},
  "geometry": {"coordinates":[-74.75998300000001,40.220479],"type":"Point"}
}