{
  "type": "Feature",
  "properties": {
    "addr:full":"1117 State Rte 33 Trenton NJ 08690",
    "addr:housenumber":"1117",
    "addr:postcode":"08690",
    "addr:street":"State Rte 33",
    "iso:country":"US",
    "sg:address":"1117 State Rte 33",
    "sg:city":"Trenton",
    "sg:classifiers":[
        {
            "category":"Autos & Motor Vehicles",
            "subcategory":"Boat Sales",
            "type":"Retail Goods"
        }
    ],
    "sg:phone":"+1 609 586 0445",
    "sg:postcode":"08690",
    "sg:province":"NJ",
    "sg:tags":[
        "dealer",
        "sales"
    ],
    "wof:name":"Mercer Marine Supply",
    "wof:placetype":"venue"
},
  "geometry": {"coordinates":[-74.66554499999999,40.228173],"type":"Point"}
}