{
  "type": "Feature",
  "properties": {
    "addr:full":"1033 Bloomfield Ave Clifton NJ 07012",
    "addr:housenumber":"1033",
    "addr:postcode":"07012",
    "addr:street":"Bloomfield Ave",
    "iso:country":"US",
    "sg:address":"1033 Bloomfield Ave",
    "sg:city":"Clifton",
    "sg:classifiers":[
        {
            "category":"Shopping",
            "subcategory":"Music",
            "type":"Retail Goods"
        }
    ],
    "sg:phone":"+1 973 778 7440",
    "sg:postcode":"07012",
    "sg:province":"NJ",
    "sg:tags":[
        "compact",
        "record",
        "disc",
        "tape"
    ],
    "wof:name":"Trans World Entertainment",
    "wof:placetype":"venue"
},
  "geometry": {"coordinates":[-74.162499,40.83796],"type":"Point"}
}