{
  "type": "Feature",
  "properties": {
    "addr:full":"19 Brentwood Dr Jackson NJ 08527",
    "addr:housenumber":"19",
    "addr:postcode":"08527",
    "addr:street":"Brentwood Dr",
    "iso:country":"US",
    "sg:address":"19 Brentwood Dr",
    "sg:city":"Jackson",
    "sg:classifiers":[
        {
            "category":"Wholesale",
            "subcategory":"Computers",
            "type":"Manufacturing & Wholesale Goods"
        }
    ],
    "sg:phone":"+1 732 928 5735",
    "sg:postcode":"08527",
    "sg:province":"NJ",
    "wof:name":"Brentwood Technology Group LLC",
    "wof:placetype":"venue"
},
  "geometry": {"coordinates":[-74.36400999999999,40.114745],"type":"Point"}
}