{
  "type": "Feature",
  "properties": {
    "addr:full":"42 Laurel Dr Springfield NJ 07081",
    "addr:housenumber":"42",
    "addr:postcode":"07081",
    "addr:street":"Laurel Dr",
    "iso:country":"US",
    "sg:address":"42 Laurel Dr",
    "sg:city":"Springfield",
    "sg:classifiers":[
        {
            "category":"Professional",
            "subcategory":"Accounting & Tax Preparation",
            "type":"Services"
        }
    ],
    "sg:phone":"+1 973 564 9464",
    "sg:postcode":"07081",
    "sg:province":"NJ",
    "wof:name":"Ira A Ginsberg CPA",
    "wof:placetype":"venue"
},
  "geometry": {"coordinates":[-74.311697,40.699268],"type":"Point"}
}