{
  "type": "Feature",
  "properties": {
    "addr:full":"1201 US Hwy 130 Burlington NJ 08016",
    "addr:housenumber":"1201",
    "addr:postcode":"08016",
    "addr:street":"Us Hwy 130",
    "iso:country":"US",
    "sg:address":"1201 US Hwy 130",
    "sg:city":"Burlington",
    "sg:classifiers":[
        {
            "category":"Autos & Motor Vehicles",
            "subcategory":"Automobile Sales",
            "type":"Retail Goods"
        }
    ],
    "sg:phone":"+1   ",
    "sg:postcode":"08016",
    "sg:province":"NJ",
    "sg:tags":[
        "repair",
        "general"
    ],
    "sg:website":"www.willishonda.com",
    "wof:name":"Willis Honda",
    "wof:placetype":"venue"
},
  "geometry": {"coordinates":[-74.877208,40.063576],"type":"Point"}
}