{
  "type": "Feature",
  "properties": {
    "iso:country":"US",
    "sg:address":"45 Roseland Ave",
    "sg:city":"Roseland",
    "sg:classifiers":[
        {
            "category":"Retail",
            "subcategory":"Funeral Services",
            "type":"Services"
        }
    ],
    "sg:phone":"+1 973 226 1111",
    "sg:postcode":"07068",
    "sg:province":"NJ",
    "sg:tags":[
        "cemetery"
    ],
    "wof:name":"Farmer Funeral Home",
    "wof:placetype":"venue"
},
  "geometry": {"coordinates":[-74.293198,40.8218],"type":"Point"}
}