{
  "type": "Feature",
  "properties": {
    "iso:country":"US",
    "sg:address":"1106 80th St",
    "sg:city":"North Bergen",
    "sg:classifiers":[
        {
            "category":"Communications",
            "type":"Services"
        }
    ],
    "sg:phone":"+1 201 861 6200",
    "sg:postcode":"07047",
    "sg:province":"NJ",
    "sg:tags":[
        "communication"
    ],
    "wof:name":"Magnum Force Communications",
    "wof:placetype":"venue"
},
  "geometry": {"coordinates":[-74.01439499999999,40.805891],"type":"Point"}
}