{
  "type": "Feature",
  "properties": {
    "iso:country":"US",
    "sg:address":"1501 Hamburg Tpke",
    "sg:city":"Wayne",
    "sg:classifiers":[
        {
            "category":"Wholesale",
            "subcategory":"Stationery",
            "type":"Manufacturing & Wholesale Goods"
        }
    ],
    "sg:phone":"+1 973 831 0087",
    "sg:postcode":"07470",
    "sg:province":"NJ",
    "sg:tags":[
        "business",
        "form",
        "system"
    ],
    "wof:name":"Newman Business Forms",
    "wof:placetype":"venue"
},
  "geometry": {"coordinates":[-74.25427000000001,40.964522],"type":"Point"}
}