{
  "type": "Feature",
  "properties": {
    "iso:country":"US",
    "sg:address":"25 Brookside Ave",
    "sg:city":"Sussex",
    "sg:classifiers":[
        {
            "category":"Education",
            "subcategory":"Vocational School",
            "type":"Public Place"
        }
    ],
    "sg:phone":"+1   ",
    "sg:postcode":"07461",
    "sg:province":"NJ",
    "sg:tags":[
        "training",
        "computer"
    ],
    "wof:name":"Bbti",
    "wof:placetype":"venue"
},
  "geometry": {"coordinates":[-74.606898,41.205632],"type":"Point"}
}