{
  "type": "Feature",
  "properties": {
    "addr:full":"352 Chelsea Ave Long Branch NJ 07740",
    "addr:housenumber":"352",
    "addr:postcode":"07740",
    "addr:street":"Chelsea Ave",
    "iso:country":"US",
    "sg:address":"352 Chelsea Ave",
    "sg:city":"Long Branch",
    "sg:classifiers":[
        {
            "category":"Health Services",
            "subcategory":"Nursing And Care Facility",
            "type":"Services"
        }
    ],
    "sg:phone":"+1 732 222 8125",
    "sg:postcode":"07740",
    "sg:province":"NJ",
    "sg:tags":[
        "home",
        "convalescent"
    ],
    "wof:name":"Chelsea Rest Home Inc",
    "wof:placetype":"venue"
},
  "geometry": {"coordinates":[-73.993385,40.30019],"type":"Point"}
}