{
  "type": "Feature",
  "properties": {
    "iso:country":"US",
    "sg:address":"RR 322",
    "sg:city":"Williamstown",
    "sg:classifiers":[
        {
            "category":"Restaurant",
            "type":"Food & Drink"
        },
        {
            "category":"Sports & Exercise",
            "subcategory":"Golf",
            "type":"Entertainment"
        }
    ],
    "sg:phone":"+1 856 863 3737",
    "sg:postcode":"08094",
    "sg:province":"NJ",
    "wof:name":"Highlander Pub & Grille At Scotland Run Golf Club",
    "wof:placetype":"venue"
},
  "geometry": {"coordinates":[-74.97489899999999,39.663898],"type":"Point"}
}