{
  "type": "Feature",
  "properties": {
    "addr:full":"22 Brandon Rd Trenton NJ 08648",
    "addr:housenumber":"22",
    "addr:postcode":"08648",
    "addr:street":"Brandon Rd",
    "iso:country":"US",
    "sg:address":"22 Brandon Rd",
    "sg:city":"Trenton",
    "sg:classifiers":[
        {
            "category":"Building & Trades",
            "subcategory":"Electrical",
            "type":"Services"
        }
    ],
    "sg:phone":"+1 609 737 3997",
    "sg:postcode":"08648",
    "sg:province":"NJ",
    "sg:tags":[
        "electrical",
        "contractor"
    ],
    "wof:name":"P C Electric",
    "wof:placetype":"venue"
},
  "geometry": {"coordinates":[-74.75558599999999,40.296269],"type":"Point"}
}