{
  "type": "Feature",
  "properties": {
    "addr:full":"2913 Bergenline Ave Union City NJ 07087",
    "addr:housenumber":"2913",
    "addr:postcode":"07087",
    "addr:street":"Bergenline Ave",
    "iso:country":"US",
    "sg:address":"2913 Bergenline Ave",
    "sg:city":"Union City",
    "sg:classifiers":[
        {
            "category":"Food & Beverages",
            "subcategory":"Groceries & Convenience Stores",
            "type":"Retail Goods"
        }
    ],
    "sg:phone":"+1 201 766 1992",
    "sg:postcode":"07087",
    "sg:province":"NJ",
    "wof:name":"Fiji In and Out Food Store",
    "wof:placetype":"venue"
},
  "geometry": {"coordinates":[-74.030394,40.770813],"type":"Point"}
}