{
  "type": "Feature",
  "properties": {
    "addr:full":"344 Washington St Perth Amboy NJ 08861",
    "addr:housenumber":"344",
    "addr:postcode":"08861",
    "addr:street":"Washington St",
    "iso:country":"US",
    "sg:address":"344 Washington St",
    "sg:city":"Perth Amboy",
    "sg:classifiers":[
        {
            "category":"Building & Trades",
            "subcategory":"Locksmith",
            "type":"Services"
        }
    ],
    "sg:phone":"+1 732 857 3552",
    "sg:postcode":"08861",
    "sg:province":"NJ",
    "sg:tags":[
        "key"
    ],
    "wof:name":"Locksmith 24 Hr 7 Days",
    "wof:placetype":"venue"
},
  "geometry": {"coordinates":[-74.27508899999999,40.516394],"type":"Point"}
}