{
  "type": "Feature",
  "properties": {
    "iso:country":"US",
    "sg:address":"8 Highview Ter",
    "sg:city":"Bloomfield",
    "sg:classifiers":[
        {
            "category":"Professional",
            "subcategory":"Management & Consulting",
            "type":"Services"
        }
    ],
    "sg:phone":"+1 973 338 0500",
    "sg:postcode":"07003",
    "sg:province":"NJ",
    "sg:tags":[
        "consultant"
    ],
    "wof:name":"New Heights Consulting",
    "wof:placetype":"venue"
},
  "geometry": {"coordinates":[-74.18276299999999,40.847893],"type":"Point"}
}