{
  "type": "Feature",
  "properties": {
    "iso:country":"US",
    "sg:address":"709 State Rte 70",
    "sg:city":"Brick",
    "sg:classifiers":[
        {
            "category":"Restaurant",
            "type":"Food & Drink"
        }
    ],
    "sg:phone":"+1   ",
    "sg:postcode":"08723",
    "sg:province":"NJ",
    "sg:tags":[
        "drinking",
        "eating"
    ],
    "wof:name":"TGI Fridays",
    "wof:placetype":"venue"
},
  "geometry": {"coordinates":[-74.137681,40.062626],"type":"Point"}
}