{
  "type": "Feature",
  "properties": {
    "iso:country":"US",
    "sg:address":"910 Union Ave",
    "sg:city":"Union Beach",
    "sg:classifiers":[
        {
            "category":"Bars & Pubs",
            "type":"Food & Drink"
        }
    ],
    "sg:phone":"+1 732 203 9700",
    "sg:postcode":"07735",
    "sg:province":"NJ",
    "wof:name":"Seven Days",
    "wof:placetype":"venue"
},
  "geometry": {"coordinates":[-74.165372,40.44203],"type":"Point"}
}