{
  "type": "Feature",
  "properties": {
    "iso:country":"US",
    "sg:address":"267 E Main St",
    "sg:city":"Denville",
    "sg:classifiers":[
        {
            "category":"Building & Trades",
            "subcategory":"Pest Control",
            "type":"Services"
        }
    ],
    "sg:phone":"+1 973 983 8000",
    "sg:postcode":"07834",
    "sg:province":"NJ",
    "wof:name":"Viking Termite & Pest Control",
    "wof:placetype":"venue"
},
  "geometry": {"coordinates":[-74.47972900000001,40.884105],"type":"Point"}
}