{
  "type": "Feature",
  "properties": {
    "addr:full":"7 Hague St Jersey City NJ 07307",
    "addr:housenumber":"7",
    "addr:postcode":"07307",
    "addr:street":"Hague St",
    "iso:country":"US",
    "sg:address":"7 Hague St",
    "sg:city":"Jersey City",
    "sg:classifiers":[
        {
            "category":"Professional",
            "type":"Services"
        }
    ],
    "sg:phone":"+1   ",
    "sg:postcode":"07307",
    "sg:province":"NJ",
    "wof:name":"Francisca C Reyes",
    "wof:placetype":"venue"
},
  "geometry": {"coordinates":[-74.045174,40.756105],"type":"Point"}
}