{
  "type": "Feature",
  "properties": {
    "addr:full":"407 N Broad St Elizabeth NJ 07208",
    "addr:housenumber":"407",
    "addr:postcode":"07208",
    "addr:street":"N Broad St",
    "iso:country":"US",
    "sg:address":"407 N Broad St",
    "sg:city":"Elizabeth",
    "sg:classifiers":[
        {
            "category":"Professional",
            "type":"Services"
        },
        {
            "category":"Organizations",
            "subcategory":"Religious Organization",
            "type":"Services"
        }
    ],
    "sg:phone":"+1 908 351 4997",
    "sg:postcode":"07208",
    "sg:province":"NJ",
    "sg:tags":[
        "church"
    ],
    "wof:name":"Centro Familiar De Adoracion I",
    "wof:placetype":"venue"
},
  "geometry": {"coordinates":[-74.21404099999999,40.671983],"type":"Point"}
}