{
  "type": "Feature",
  "properties": {
    "iso:country":"US",
    "sg:address":"979 Church Rd",
    "sg:city":"Cherry Hill",
    "sg:classifiers":[
        {
            "category":"Shopping",
            "subcategory":"Pharmacy",
            "type":"Retail Goods"
        }
    ],
    "sg:phone":"+1 856 482 5120",
    "sg:postcode":"08002",
    "sg:province":"NJ",
    "wof:name":"Pathmark Pharmacy",
    "wof:placetype":"venue"
},
  "geometry": {"coordinates":[-75.02155,39.944601],"type":"Point"}
}