{
  "type": "Feature",
  "properties": {
    "addr:full":"472 11th St Palisades Park NJ 07650",
    "addr:housenumber":"472",
    "addr:postcode":"07650",
    "addr:street":"11Th St",
    "iso:country":"US",
    "sg:address":"472 11th St",
    "sg:city":"Palisades Park",
    "sg:classifiers":[
        {
            "category":"Professional",
            "subcategory":"Computer Services",
            "type":"Services"
        }
    ],
    "sg:phone":"+1   ",
    "sg:postcode":"07650",
    "sg:province":"NJ",
    "sg:tags":[
        "repair",
        "maintenance"
    ],
    "wof:name":"C B S",
    "wof:placetype":"venue"
},
  "geometry": {"coordinates":[-73.98454099999999,40.846048],"type":"Point"}
}