{
  "type": "Feature",
  "properties": {
    "iso:country":"US",
    "sg:address":"71 E Palisade Ave",
    "sg:city":"Englewood",
    "sg:classifiers":[
        {
            "category":"Wholesale",
            "subcategory":"Drugs",
            "type":"Manufacturing & Wholesale Goods"
        }
    ],
    "sg:phone":"+1 201 871 5850",
    "sg:postcode":"07631",
    "sg:province":"NJ",
    "sg:tags":[
        "importer",
        "trader",
        "fragrance"
    ],
    "wof:name":"Fragrance Xtreme",
    "wof:placetype":"venue"
},
  "geometry": {"coordinates":[-73.970879,40.891712],"type":"Point"}
}