{
  "type": "Feature",
  "properties": {
    "addr:full":"4302 Hana Rd Edison NJ 08817",
    "addr:housenumber":"4302",
    "addr:postcode":"08817",
    "addr:street":"Hana Rd",
    "iso:country":"US",
    "sg:address":"4302 Hana Rd",
    "sg:city":"Edison",
    "sg:classifiers":[
        {
            "category":"Building & Trades",
            "subcategory":"Plumbing",
            "type":"Services"
        }
    ],
    "sg:phone":"+1 732 287 6230",
    "sg:postcode":"08817",
    "sg:province":"NJ",
    "sg:tags":[
        "contractor"
    ],
    "wof:name":"Main St Plumbers Inc",
    "wof:placetype":"venue"
},
  "geometry": {"coordinates":[-74.406778,40.534036],"type":"Point"}
}