{
  "type": "Feature",
  "properties": {
    "iso:country":"US",
    "sg:address":"95 Broadway",
    "sg:city":"Newark",
    "sg:classifiers":[
        {
            "category":"Home & Garden",
            "subcategory":"Household Appliances",
            "type":"Retail Goods"
        },
        {
            "category":"Home & Garden",
            "subcategory":"Hardware",
            "type":"Retail Goods"
        }
    ],
    "sg:phone":"+1 973 482 3420",
    "sg:postcode":"07104",
    "sg:province":"NJ",
    "sg:tags":[
        "repair",
        "store"
    ],
    "wof:name":"Peskins Furniture & Appliances",
    "wof:placetype":"venue"
},
  "geometry": {"coordinates":[-74.17040299999999,40.753399],"type":"Point"}
}