{
  "type": "Feature",
  "properties": {
    "iso:country":"US",
    "sg:address":"136 Mosle Rd",
    "sg:city":"Far Hills",
    "sg:classifiers":[
        {
            "category":"Farming",
            "subcategory":"Livestock Farm",
            "type":"Manufacturing & Wholesale Goods"
        }
    ],
    "sg:phone":"+1 908 781 2464",
    "sg:postcode":"07931",
    "sg:province":"NJ",
    "sg:tags":[
        "equine"
    ],
    "wof:name":"Horse Land LLC",
    "wof:placetype":"venue"
},
  "geometry": {"coordinates":[-74.633432,40.746899],"type":"Point"}
}