{
  "type": "Feature",
  "properties": {
    "iso:country":"US",
    "sg:address":"1373 Broad St",
    "sg:city":"Clifton",
    "sg:classifiers":[
        {
            "category":"Real Estate",
            "subcategory":"Real Estate Services",
            "type":"Services"
        }
    ],
    "sg:phone":"+1 973 779 7738",
    "sg:postcode":"07013",
    "sg:province":"NJ",
    "sg:tags":[
        "company",
        "abstract",
        "title"
    ],
    "wof:name":"Clear Advantage Title",
    "wof:placetype":"venue"
},
  "geometry": {"coordinates":[-74.181095,40.848172],"type":"Point"}
}