{
  "type": "Feature",
  "properties": {
    "addr:full":"348 Woodbine Way South Amboy NJ 08879",
    "addr:housenumber":"348",
    "addr:postcode":"08879",
    "addr:street":"Woodbine Way",
    "iso:country":"US",
    "sg:address":"348 Woodbine Way",
    "sg:city":"South Amboy",
    "sg:classifiers":[
        {
            "category":"Recreation",
            "type":"Entertainment"
        }
    ],
    "sg:phone":"+1   ",
    "sg:postcode":"08879",
    "sg:province":"NJ",
    "wof:name":"William J Anderson",
    "wof:placetype":"venue"
},
  "geometry": {"coordinates":[-74.249954,40.452301],"type":"Point"}
}