{
  "type": "Feature",
  "properties": {
    "iso:country":"US",
    "sg:address":"221 Tantum Dr",
    "sg:city":"Trenton",
    "sg:classifiers":[
        {
            "category":"Building & Trades",
            "subcategory":"Plumbing",
            "type":"Services"
        }
    ],
    "sg:phone":"+1 609 581 9500",
    "sg:postcode":"08610",
    "sg:province":"NJ",
    "sg:tags":[
        "conditioning",
        "air",
        "system",
        "contractor"
    ],
    "wof:name":"Aced Air Conditioning Inc",
    "wof:placetype":"venue"
},
  "geometry": {"coordinates":[-74.68538700000001,40.192266],"type":"Point"}
}