{
  "type": "Feature",
  "properties": {
    "addr:full":"74 Hillyer Cir Middletown NJ 07748",
    "addr:housenumber":"74",
    "addr:postcode":"07748",
    "addr:street":"Hillyer Cir",
    "iso:country":"US",
    "sg:address":"74 Hillyer Cir",
    "sg:city":"Middletown",
    "sg:classifiers":[
        {
            "category":"Wholesale",
            "subcategory":"Electrical",
            "type":"Manufacturing & Wholesale Goods"
        }
    ],
    "sg:phone":"+1 732 615 0102",
    "sg:postcode":"07748",
    "sg:province":"NJ",
    "sg:tags":[
        "mfr",
        "wire",
        "rep",
        "cable"
    ],
    "wof:name":"Shorelectric Sales Inc",
    "wof:placetype":"venue"
},
  "geometry": {"coordinates":[-74.116626,40.377304],"type":"Point"}
}