{
  "type": "Feature",
  "properties": {
    "iso:country":"US",
    "sg:address":"20 Empire Blvd",
    "sg:city":"Moonachie",
    "sg:classifiers":[
        {
            "category":"Manufacturing",
            "subcategory":"Tools & Machinery",
            "type":"Manufacturing & Wholesale Goods"
        }
    ],
    "sg:phone":"+1 201 440 8300",
    "sg:postcode":"07074",
    "sg:province":"NJ",
    "sg:tags":[
        "control",
        "industrial",
        "equipment",
        "process",
        "mfg",
        "instrument"
    ],
    "sg:website":"www.acrison.com",
    "wof:name":"Acrison Inc",
    "wof:placetype":"venue"
},
  "geometry": {"coordinates":[-74.041445,40.831379],"type":"Point"}
}