{
  "type": "Feature",
  "properties": {
    "iso:country":"US",
    "sg:address":"47 Broad St",
    "sg:city":"Eatontown",
    "sg:classifiers":[
        {
            "category":"Recreation",
            "type":"Entertainment"
        }
    ],
    "sg:phone":"+1 732 389 7651",
    "sg:postcode":"07724",
    "sg:province":"NJ",
    "sg:tags":[
        "parks"
    ],
    "wof:name":"Eatontown Parks Dept",
    "wof:placetype":"venue"
},
  "geometry": {"coordinates":[-74.0592,40.304877],"type":"Point"}
}