{
  "type": "Feature",
  "properties": {
    "addr:full":"71 Cheyenne Way Wayne NJ 07470",
    "addr:housenumber":"71",
    "addr:postcode":"07470",
    "addr:street":"Cheyenne Way",
    "iso:country":"US",
    "sg:address":"71 Cheyenne Way",
    "sg:city":"Wayne",
    "sg:classifiers":[
        {
            "category":"Shopping",
            "subcategory":"Clothing, Apparel, & Fashions",
            "type":"Retail Goods"
        }
    ],
    "sg:phone":"+1   ",
    "sg:postcode":"07470",
    "sg:province":"NJ",
    "wof:name":"Syndetic Associates Inc",
    "wof:placetype":"venue"
},
  "geometry": {"coordinates":[-74.25889100000001,40.998703],"type":"Point"}
}