{
  "type": "Feature",
  "properties": {
    "iso:country":"US",
    "sg:address":"1400 Willowbrook Mall",
    "sg:city":"Wayne",
    "sg:classifiers":[
        {
            "category":"Shopping",
            "subcategory":"Gifts & Souvenirs",
            "type":"Retail Goods"
        }
    ],
    "sg:phone":"+1 973 837 0600",
    "sg:postcode":"07470",
    "sg:province":"NJ",
    "sg:tags":[
        "collectible"
    ],
    "wof:name":"Collectibles",
    "wof:placetype":"venue"
},
  "geometry": {"coordinates":[-74.255009,40.889541],"type":"Point"}
}