{
  "type": "Feature",
  "properties": {
    "addr:full":"152 Speedwell Ave Morristown NJ 07960",
    "addr:housenumber":"152",
    "addr:postcode":"07960",
    "addr:street":"Speedwell Ave",
    "iso:country":"US",
    "sg:address":"152 Speedwell Ave",
    "sg:city":"Morristown",
    "sg:classifiers":[
        {
            "category":"Professional",
            "type":"Services"
        }
    ],
    "sg:phone":"+1   ",
    "sg:postcode":"07960",
    "sg:province":"NJ",
    "wof:name":"People Helping People",
    "wof:placetype":"venue"
},
  "geometry": {"coordinates":[-74.482432,40.803528],"type":"Point"}
}