{
  "type": "Feature",
  "properties": {
    "addr:full":"116 W 3rd Ave Roselle NJ 07203",
    "addr:housenumber":"116",
    "addr:postcode":"07203",
    "addr:street":"W 3Rd Ave",
    "iso:country":"US",
    "sg:address":"116 W 3rd Ave",
    "sg:city":"Roselle",
    "sg:classifiers":[
        {
            "category":"Food & Beverages",
            "subcategory":"Groceries & Convenience Stores",
            "type":"Retail Goods"
        }
    ],
    "sg:phone":"+1   ",
    "sg:postcode":"07203",
    "sg:province":"NJ",
    "wof:name":"Las Palmas Grocery Store",
    "wof:placetype":"venue"
},
  "geometry": {"coordinates":[-74.26566699999999,40.657325],"type":"Point"}
}