{
  "type": "Feature",
  "properties": {
    "iso:country":"US",
    "sg:address":"46 Yard Rd",
    "sg:city":"Pennington",
    "sg:classifiers":[
        {
            "category":"Farming",
            "subcategory":"Vineyard",
            "type":"Manufacturing & Wholesale Goods"
        },
        {
            "category":"Food & Beverages",
            "subcategory":"Liquor & Beverages",
            "type":"Retail Goods"
        }
    ],
    "sg:phone":"+1 609 737 4465",
    "sg:postcode":"08534",
    "sg:province":"NJ",
    "wof:name":"Hopewell Valley Vineyard LLC",
    "wof:placetype":"venue"
},
  "geometry": {"coordinates":[-74.80622,40.338743],"type":"Point"}
}