{
  "type": "Feature",
  "properties": {
    "iso:country":"US",
    "sg:address":"521 Pleasant Valley Ave",
    "sg:city":"Moorestown",
    "sg:classifiers":[
        {
            "category":"Professional",
            "subcategory":"Management & Consulting",
            "type":"Services"
        }
    ],
    "sg:phone":"+1 856 778 5963",
    "sg:postcode":"08057",
    "sg:province":"NJ",
    "sg:tags":[
        "report",
        "construction"
    ],
    "wof:name":"F W Dodge Mc Graw-Hill",
    "wof:placetype":"venue"
},
  "geometry": {"coordinates":[-74.953439,39.951159],"type":"Point"}
}