{
  "type": "Feature",
  "properties": {
    "iso:country":"US",
    "sg:address":"88 Park Ln",
    "sg:city":"Fair Haven",
    "sg:classifiers":[
        {
            "category":"Real Estate",
            "subcategory":"Real Estate Agent",
            "type":"Services"
        }
    ],
    "sg:phone":"+1   ",
    "sg:postcode":"07704",
    "sg:province":"NJ",
    "wof:name":"R Patrick Powers Appraiser",
    "wof:placetype":"venue"
},
  "geometry": {"coordinates":[-74.032122,40.363369],"type":"Point"}
}