{
  "type": "Feature",
  "properties": {
    "iso:country":"US",
    "sg:address":"201 W Passaic St",
    "sg:city":"Rochelle Park",
    "sg:classifiers":[
        {
            "category":"Building & Trades",
            "subcategory":"Equipment Rental",
            "type":"Services"
        }
    ],
    "sg:phone":"+1 201 712 1999",
    "sg:postcode":"07662",
    "sg:province":"NJ",
    "sg:tags":[
        "leasing"
    ],
    "wof:name":"Essex Capital Corp",
    "wof:placetype":"venue"
},
  "geometry": {"coordinates":[-74.082438,40.914961],"type":"Point"}
}