{
  "type": "Feature",
  "properties": {
    "iso:country":"US",
    "sg:address":"123 Madison Ave",
    "sg:city":"Blackwood",
    "sg:classifiers":[
        {
            "category":"Building & Trades",
            "subcategory":"Construction",
            "type":"Services"
        }
    ],
    "sg:phone":"+1 856 228 2723",
    "sg:postcode":"08012",
    "sg:province":"NJ",
    "sg:tags":[
        "painter"
    ],
    "wof:name":"Pete Gentili's Painting",
    "wof:placetype":"venue"
},
  "geometry": {"coordinates":[-75.038408,39.739276],"type":"Point"}
}