{
  "type": "Feature",
  "properties": {
    "addr:full":"955 Lincoln Ave Glen Rock NJ 07452",
    "addr:housenumber":"955",
    "addr:postcode":"07452",
    "addr:street":"Lincoln Ave",
    "iso:country":"US",
    "sg:address":"955 Lincoln Ave",
    "sg:city":"Glen Rock",
    "sg:classifiers":[
        {
            "category":"Professional",
            "subcategory":"Testing Lab",
            "type":"Services"
        },
        {
            "category":"Manufacturing",
            "subcategory":"Furniture",
            "type":"Manufacturing & Wholesale Goods"
        }
    ],
    "sg:phone":"+1 201 251 4727",
    "sg:postcode":"07452",
    "sg:province":"NJ",
    "sg:tags":[
        "household",
        "mfg",
        "consulting",
        "plastic"
    ],
    "wof:name":"Corex Design Group Inc",
    "wof:placetype":"venue"
},
  "geometry": {"coordinates":[-74.145809,40.950738],"type":"Point"}
}