{
  "type": "Feature",
  "properties": {
    "iso:country":"US",
    "sg:address":"74 Wallington Ave",
    "sg:city":"Wallington",
    "sg:classifiers":[
        {
            "category":"Building & Trades",
            "subcategory":"Construction",
            "type":"Services"
        }
    ],
    "sg:phone":"+1 973 594 8142",
    "sg:postcode":"07057",
    "sg:province":"NJ",
    "sg:tags":[
        "hanging",
        "contractor"
    ],
    "wof:name":"Gregs Painting",
    "wof:placetype":"venue"
},
  "geometry": {"coordinates":[-74.115539,40.857575],"type":"Point"}
}