{
  "type": "Feature",
  "properties": {
    "iso:country":"US",
    "sg:address":"3 N Union St",
    "sg:city":"Lambertville",
    "sg:classifiers":[
        {
            "category":"Manufacturing",
            "subcategory":"Jewelry",
            "type":"Manufacturing & Wholesale Goods"
        }
    ],
    "sg:phone":"+1 609 397 0809",
    "sg:postcode":"08530",
    "sg:province":"NJ",
    "sg:tags":[
        "precious",
        "metal",
        "mfg"
    ],
    "wof:name":"Castor Jewelry",
    "wof:placetype":"venue"
},
  "geometry": {"coordinates":[-74.945223,40.366623],"type":"Point"}
}