{
  "type": "Feature",
  "properties": {
    "addr:full":"1350 16th St Fort Lee NJ 07024",
    "addr:housenumber":"1350",
    "addr:postcode":"07024",
    "addr:street":"16Th St",
    "iso:country":"US",
    "sg:address":"1350 16th St",
    "sg:city":"Fort Lee",
    "sg:classifiers":[
        {
            "category":"Insurance",
            "subcategory":"Insurance Agent",
            "type":"Services"
        }
    ],
    "sg:phone":"+1 201 363 6431",
    "sg:postcode":"07024",
    "sg:province":"NJ",
    "wof:name":"M & M Insurance",
    "wof:placetype":"venue"
},
  "geometry": {"coordinates":[-73.979201,40.84574],"type":"Point"}
}