{
  "type": "Feature",
  "properties": {
    "addr:full":"30 International Dr S Flanders NJ 07836",
    "addr:housenumber":"30",
    "addr:postcode":"07836",
    "addr:street":"International Dr S",
    "iso:country":"US",
    "sg:address":"30 International Dr S",
    "sg:city":"Flanders",
    "sg:classifiers":[
        {
            "category":"Shopping",
            "subcategory":"Department Store",
            "type":"Retail Goods"
        }
    ],
    "sg:phone":"+1   ",
    "sg:postcode":"07836",
    "sg:province":"NJ",
    "wof:name":"TJ Maxx",
    "wof:placetype":"venue"
},
  "geometry": {"coordinates":[-74.70454100000001,40.882926],"type":"Point"}
}