{
  "type": "Feature",
  "properties": {
    "addr:full":"108 Lacey Rd Whiting NJ 08759",
    "addr:housenumber":"108",
    "addr:postcode":"08759",
    "addr:street":"Lacey Rd",
    "iso:country":"US",
    "sg:address":"108 Lacey Rd",
    "sg:city":"Whiting",
    "sg:classifiers":[
        {
            "category":"Utilities",
            "subcategory":"Cable",
            "type":"Services"
        }
    ],
    "sg:phone":"+1 732 849 4646",
    "sg:postcode":"08759",
    "sg:province":"NJ",
    "sg:tags":[
        "television"
    ],
    "wof:name":"Comcast Cable",
    "wof:placetype":"venue"
},
  "geometry": {"coordinates":[-74.37931500000001,39.954409],"type":"Point"}
}