{
  "type": "Feature",
  "properties": {
    "addr:full":"3816 Bayshore Rd Cape May NJ 08204",
    "addr:housenumber":"3816",
    "addr:postcode":"08204",
    "addr:street":"Bayshore Rd",
    "iso:country":"US",
    "sg:address":"3816 Bayshore Rd",
    "sg:city":"Cape May",
    "sg:classifiers":[
        {
            "category":"Health Services",
            "subcategory":"Doctor",
            "type":"Services"
        }
    ],
    "sg:phone":"+1 609 889 1900",
    "sg:postcode":"08204",
    "sg:province":"NJ",
    "wof:name":"Leisner William R MD",
    "wof:placetype":"venue"
},
  "geometry": {"coordinates":[-74.94259599999999,38.980301],"type":"Point"}
}