{
  "type": "Feature",
  "properties": {
    "addr:full":"170 State Rte 23 Hamburg NJ 07419",
    "addr:housenumber":"170",
    "addr:postcode":"07419",
    "addr:street":"State Rte 23",
    "iso:country":"US",
    "sg:address":"170 State Rte 23",
    "sg:city":"Hamburg",
    "sg:classifiers":[
        {
            "category":"Retail",
            "subcategory":"Auto Repair",
            "type":"Services"
        }
    ],
    "sg:phone":"+1   ",
    "sg:postcode":"07419",
    "sg:province":"NJ",
    "sg:tags":[
        "general"
    ],
    "wof:name":"Superior Auto Repair",
    "wof:placetype":"venue"
},
  "geometry": {"coordinates":[-74.57235799999999,41.142588],"type":"Point"}
}