{
  "type": "Feature",
  "properties": {
    "iso:country":"US",
    "sg:address":"50 Wheeler Point Rd",
    "sg:city":"Newark",
    "sg:classifiers":[
        {
            "category":"Wholesale",
            "subcategory":"Machinery & Supplies",
            "type":"Manufacturing & Wholesale Goods"
        }
    ],
    "sg:phone":"+1 973 589 4930",
    "sg:postcode":"07105",
    "sg:province":"NJ",
    "sg:tags":[
        "bearing"
    ],
    "wof:name":"Wisconsin Centrifugal Inc",
    "wof:placetype":"venue"
},
  "geometry": {"coordinates":[-74.15746,40.718038],"type":"Point"}
}