{
  "type": "Feature",
  "properties": {
    "addr:full":"29 Perry St Dover NJ 07801",
    "addr:housenumber":"29",
    "addr:postcode":"07801",
    "addr:street":"Perry St",
    "iso:country":"US",
    "sg:address":"29 Perry St",
    "sg:city":"Dover",
    "sg:classifiers":[
        {
            "category":"Banks & Credit Unions",
            "subcategory":"Bank",
            "type":"Services"
        }
    ],
    "sg:phone":"+1 973 989 1377",
    "sg:postcode":"07801",
    "sg:province":"NJ",
    "sg:tags":[
        "loan",
        "real estate"
    ],
    "wof:name":"First Second Mortgage Co-Nj",
    "wof:placetype":"venue"
},
  "geometry": {"coordinates":[-74.544765,40.887551],"type":"Point"}
}