{
  "type": "Feature",
  "properties": {
    "addr:full":"138 Woodcrest Rd Cherry Hill NJ 08003",
    "addr:housenumber":"138",
    "addr:postcode":"08003",
    "addr:street":"Woodcrest Rd",
    "iso:country":"US",
    "sg:address":"138 Woodcrest Rd",
    "sg:city":"Cherry Hill",
    "sg:classifiers":[
        {
            "category":"Restaurant",
            "type":"Food & Drink"
        }
    ],
    "sg:phone":"+1 856 795 1223",
    "sg:postcode":"08003",
    "sg:province":"NJ",
    "sg:tags":[
        "pizza"
    ],
    "wof:name":"Nopoli Pizza",
    "wof:placetype":"venue"
},
  "geometry": {"coordinates":[-75.01014499999999,39.872667],"type":"Point"}
}