{
  "type": "Feature",
  "properties": {
    "addr:full":"625 Gotham Pkwy Carlstadt NJ 07072",
    "addr:housenumber":"625",
    "addr:postcode":"07072",
    "addr:street":"Gotham Pkwy",
    "iso:country":"US",
    "sg:address":"625 Gotham Pkwy",
    "sg:city":"Carlstadt",
    "sg:classifiers":[
        {
            "category":"Shopping",
            "subcategory":"Clothing, Apparel, & Fashions",
            "type":"Retail Goods"
        }
    ],
    "sg:phone":"+1 201 507 4530",
    "sg:postcode":"07072",
    "sg:province":"NJ",
    "sg:tags":[
        "wig",
        "toupee",
        "hairpiece"
    ],
    "wof:name":"Isis Hair Collection",
    "wof:placetype":"venue"
},
  "geometry": {"coordinates":[-74.06600899999999,40.83105],"type":"Point"}
}