{
  "type": "Feature",
  "properties": {
    "iso:country":"US",
    "sg:address":"1535 Bacharach Blvd",
    "sg:city":"Atlantic City",
    "sg:classifiers":[
        {
            "category":"Education",
            "subcategory":"Junior College",
            "type":"Public Place"
        }
    ],
    "sg:phone":"+1 609 343 4800",
    "sg:postcode":"08401",
    "sg:province":"NJ",
    "sg:tags":[
        "technical",
        "institute"
    ],
    "wof:name":"Atlantic Cape Community Clg",
    "wof:placetype":"venue"
},
  "geometry": {"coordinates":[-74.43056300000001,39.362985],"type":"Point"}
}