{
  "type": "Feature",
  "properties": {
    "iso:country":"US",
    "sg:address":"428 Field House Way",
    "sg:city":"Williamstown",
    "sg:classifiers":[
        {
            "category":"Professional",
            "subcategory":"Business Services",
            "type":"Services"
        }
    ],
    "sg:phone":"+1   ",
    "sg:postcode":"08094",
    "sg:province":"NJ",
    "wof:name":"Rolax Enterprises Inc",
    "wof:placetype":"venue"
},
  "geometry": {"coordinates":[-74.97126900000001,39.695831],"type":"Point"}
}