{
  "type": "Feature",
  "properties": {
    "iso:country":"US",
    "sg:address":"3 Olcott Sq",
    "sg:city":"Bernardsville",
    "sg:classifiers":[
        {
            "category":"Retail",
            "subcategory":"Portrait Studio",
            "type":"Services"
        }
    ],
    "sg:phone":"+1 908 696 1100",
    "sg:postcode":"07924",
    "sg:province":"NJ",
    "sg:tags":[
        "photographer"
    ],
    "sg:website":"www.stephentaylorphoto.com",
    "wof:name":"Stephen Taylor Photography",
    "wof:placetype":"venue"
},
  "geometry": {"coordinates":[-74.56928000000001,40.718788],"type":"Point"}
}