{
  "type": "Feature",
  "properties": {
    "iso:country":"US",
    "sg:address":"432 Danforth Ave",
    "sg:city":"Jersey City",
    "sg:classifiers":[
        {
            "category":"Building & Trades",
            "subcategory":"Locksmith",
            "type":"Services"
        }
    ],
    "sg:phone":"+1 201 793 9092",
    "sg:postcode":"07305",
    "sg:province":"NJ",
    "sg:tags":[
        "key"
    ],
    "wof:name":"Locksmith A 24 Emergency",
    "wof:placetype":"venue"
},
  "geometry": {"coordinates":[-74.099149,40.705951],"type":"Point"}
}