{
  "type": "Feature",
  "properties": {
    "iso:country":"US",
    "sg:address":"120 Summit Rd",
    "sg:city":"Sparta",
    "sg:classifiers":[
        {
            "category":"Wholesale",
            "subcategory":"Chemicals & Plastics",
            "type":"Manufacturing & Wholesale Goods"
        }
    ],
    "sg:phone":"+1 973 729 5269",
    "sg:postcode":"07871",
    "sg:province":"NJ",
    "wof:name":"Amway Home Products Distr",
    "wof:placetype":"venue"
},
  "geometry": {"coordinates":[-74.67905,41.019302],"type":"Point"}
}