{
  "type": "Feature",
  "properties": {
    "addr:full":"31 South St Morristown NJ 07960",
    "addr:housenumber":"31",
    "addr:postcode":"07960",
    "addr:street":"South St",
    "iso:country":"US",
    "sg:address":"31 South St",
    "sg:city":"Morristown",
    "sg:classifiers":[
        {
            "category":"Government",
            "subcategory":"Office",
            "type":"Public Place"
        }
    ],
    "sg:phone":"+1 973 538 2439",
    "sg:postcode":"07960",
    "sg:province":"NJ",
    "sg:tags":[
        "armed",
        "force",
        "recruiting"
    ],
    "wof:name":"US Army Recruiting",
    "wof:placetype":"venue"
},
  "geometry": {"coordinates":[-74.479727,40.795094],"type":"Point"}
}