{
  "type": "Feature",
  "properties": {
    "iso:country":"US",
    "sg:address":"2 Executive Dr",
    "sg:city":"Somerset",
    "sg:classifiers":[
        {
            "category":"Real Estate",
            "subcategory":"Real Estate Agent",
            "type":"Services"
        }
    ],
    "sg:phone":"+1 732 302 9373",
    "sg:postcode":"08873",
    "sg:province":"NJ",
    "wof:name":"Darien Management Realty Co",
    "wof:placetype":"venue"
},
  "geometry": {"coordinates":[-74.521058,40.543436],"type":"Point"}
}