{
  "type": "Feature",
  "properties": {
    "iso:country":"US",
    "sg:address":"900 Chestnut Ave Ste E",
    "sg:city":"Somerdale",
    "sg:classifiers":[
        {
            "category":"Wholesale",
            "subcategory":"Medical Equipment & Supplies",
            "type":"Manufacturing & Wholesale Goods"
        }
    ],
    "sg:phone":"+1 856 783 6436",
    "sg:postcode":"08083",
    "sg:province":"NJ",
    "sg:tags":[
        "device",
        "orthopedic",
        "appliance",
        "prosthetic"
    ],
    "wof:name":"Creative Orthotics",
    "wof:placetype":"venue"
},
  "geometry": {"coordinates":[-75.021733,39.852861],"type":"Point"}
}