{
  "type": "Feature",
  "properties": {
    "iso:country":"US",
    "sg:address":"11 Gray St",
    "sg:city":"Newark",
    "sg:classifiers":[
        {
            "category":"Education",
            "subcategory":"School",
            "type":"Public Place"
        }
    ],
    "sg:phone":"+1 973 481 5582",
    "sg:postcode":"07107",
    "sg:province":"NJ",
    "sg:tags":[
        "religious"
    ],
    "wof:name":"St Rose Of Lima School",
    "wof:placetype":"venue"
},
  "geometry": {"coordinates":[-74.19389700000001,40.754217],"type":"Point"}
}