{
  "type": "Feature",
  "properties": {
    "addr:full":"403 N Main St Manville NJ 08835",
    "addr:housenumber":"403",
    "addr:postcode":"08835",
    "addr:street":"N Main St",
    "iso:country":"US",
    "sg:address":"403 N Main St",
    "sg:city":"Manville",
    "sg:classifiers":[
        {
            "category":"Shopping",
            "subcategory":"Used Merchandise",
            "type":"Retail Goods"
        }
    ],
    "sg:phone":"+1 732 951 2100",
    "sg:postcode":"08835",
    "sg:province":"NJ",
    "sg:tags":[
        "antique"
    ],
    "wof:name":"Bodner's Auctions",
    "wof:placetype":"venue"
},
  "geometry": {"coordinates":[-74.585219,40.551092],"type":"Point"}
}