{
  "type": "Feature",
  "properties": {
    "iso:country":"US",
    "sg:address":"628 Henry St",
    "sg:city":"Elizabeth",
    "sg:classifiers":[
        {
            "category":"Professional",
            "subcategory":"Business Services",
            "type":"Services"
        },
        {
            "category":"Home & Garden",
            "subcategory":"Building Materials",
            "type":"Retail Goods"
        }
    ],
    "sg:phone":"+1 908 965 1700",
    "sg:postcode":"07201",
    "sg:province":"NJ",
    "sg:tags":[
        "delivery",
        "courier",
        "supply"
    ],
    "wof:name":"Metropolitan Distribution Inc",
    "wof:placetype":"venue"
},
  "geometry": {"coordinates":[-74.197304,40.672501],"type":"Point"}
}