{
  "type": "Feature",
  "properties": {
    "iso:country":"US",
    "sg:address":"26 Journal Sq",
    "sg:city":"Jersey City",
    "sg:classifiers":[
        {
            "category":"Health Services",
            "subcategory":"Nursing And Care Facility",
            "type":"Services"
        }
    ],
    "sg:phone":"+1 201 659 9993",
    "sg:postcode":"07306",
    "sg:province":"NJ",
    "wof:name":"Maxim Healthcare Svc Inc",
    "wof:placetype":"venue"
},
  "geometry": {"coordinates":[-74.063984,40.731995],"type":"Point"}
}