{
  "type": "Feature",
  "properties": {
    "iso:country":"US",
    "sg:address":"244 Manor Blvd",
    "sg:city":"Trenton",
    "sg:classifiers":[
        {
            "category":"Autos & Motor Vehicles",
            "subcategory":"Fuel & Gas Station",
            "type":"Retail Goods"
        }
    ],
    "sg:phone":"+1   ",
    "sg:postcode":"08620",
    "sg:province":"NJ",
    "sg:tags":[
        "station",
        "gasoline"
    ],
    "wof:name":"Citco Gas Station",
    "wof:placetype":"venue"
},
  "geometry": {"coordinates":[-74.669445,40.183163],"type":"Point"}
}