{
  "type": "Feature",
  "properties": {
    "addr:full":"2215 Rivendell Way Edison NJ 08817",
    "addr:housenumber":"2215",
    "addr:postcode":"08817",
    "addr:street":"Rivendell Way",
    "iso:country":"US",
    "sg:address":"2215 Rivendell Way",
    "sg:city":"Edison",
    "sg:classifiers":[
        {
            "category":"Building & Trades",
            "subcategory":"Construction",
            "type":"Services"
        }
    ],
    "sg:phone":"+1 732 393 1010",
    "sg:postcode":"08817",
    "sg:province":"NJ",
    "sg:tags":[
        "contractor"
    ],
    "wof:name":"Rizco Contracting Inc",
    "wof:placetype":"venue"
},
  "geometry": {"coordinates":[-74.41472899999999,40.52852],"type":"Point"}
}