{
  "type": "Feature",
  "properties": {
    "addr:full":"329 Culver Rd Monmouth Jct NJ 08852",
    "addr:housenumber":"329",
    "addr:postcode":"08852",
    "addr:street":"Culver Rd",
    "iso:country":"US",
    "sg:address":"329 Culver Rd",
    "sg:city":"Monmouth Jct",
    "sg:classifiers":[
        {
            "category":"Health Services",
            "subcategory":"Health Practitioner",
            "type":"Services"
        }
    ],
    "sg:phone":"+1 732 438 8486",
    "sg:postcode":"08852",
    "sg:province":"NJ",
    "sg:tags":[
        "therapist",
        "physical"
    ],
    "wof:name":"Twin Boro Physical Thrpy Assoc",
    "wof:placetype":"venue"
},
  "geometry": {"coordinates":[-74.538583,40.363639],"type":"Point"}
}