{
  "type": "Feature",
  "properties": {
    "addr:full":"150 E 7th St Paterson NJ 07524",
    "addr:housenumber":"150",
    "addr:postcode":"07524",
    "addr:street":"E 7Th St",
    "iso:country":"US",
    "sg:address":"150 E 7th St",
    "sg:city":"Paterson",
    "sg:classifiers":[
        {
            "category":"Professional",
            "subcategory":"Management & Consulting",
            "type":"Services"
        }
    ],
    "sg:phone":"+1 201 684 4400",
    "sg:postcode":"07524",
    "sg:province":"NJ",
    "sg:tags":[
        "marketing",
        "program"
    ],
    "wof:name":"Thermwell Products Co Inc",
    "wof:placetype":"venue"
},
  "geometry": {"coordinates":[-74.16226,40.930614],"type":"Point"}
}