{
  "type": "Feature",
  "properties": {
    "addr:full":"690 Green Pond Rd Rockaway NJ 07866",
    "addr:housenumber":"690",
    "addr:postcode":"07866",
    "addr:street":"Green Pond Rd",
    "iso:country":"US",
    "sg:address":"690 Green Pond Rd",
    "sg:city":"Rockaway",
    "sg:classifiers":[
        {
            "category":"Home & Garden",
            "subcategory":"Building Materials",
            "type":"Retail Goods"
        }
    ],
    "sg:phone":"+1 973 838 4031",
    "sg:postcode":"07866",
    "sg:province":"NJ",
    "sg:tags":[
        "glass",
        "window",
        "plate"
    ],
    "wof:name":"Economy Glass Inc",
    "wof:placetype":"venue"
},
  "geometry": {"coordinates":[-74.49073799999999,40.974565],"type":"Point"}
}