{
  "type": "Feature",
  "properties": {
    "addr:full":"2900 Burlington Ave Delanco NJ 08075",
    "addr:housenumber":"2900",
    "addr:postcode":"08075",
    "addr:street":"Burlington Ave",
    "iso:country":"US",
    "sg:address":"2900 Burlington Ave",
    "sg:city":"Delanco",
    "sg:classifiers":[
        {
            "category":"Retail",
            "subcategory":"Auto Repair",
            "type":"Services"
        }
    ],
    "sg:phone":"+1 856 764 0774",
    "sg:postcode":"08075",
    "sg:province":"NJ",
    "sg:tags":[
        "repairing",
        "automobile"
    ],
    "wof:name":"Safety Auto Repair",
    "wof:placetype":"venue"
},
  "geometry": {"coordinates":[-74.931099,40.060398],"type":"Point"}
}