{
  "type": "Feature",
  "properties": {
    "iso:country":"US",
    "sg:address":"17 Revere Ct",
    "sg:city":"Trenton",
    "sg:classifiers":[
        {
            "category":"Shopping",
            "subcategory":"Clothing, Apparel, & Fashions",
            "type":"Retail Goods"
        }
    ],
    "sg:phone":"+1   ",
    "sg:postcode":"08628",
    "sg:province":"NJ",
    "wof:name":"David Cat",
    "wof:placetype":"venue"
},
  "geometry": {"coordinates":[-74.832331,40.276206],"type":"Point"}
}