{
  "type": "Feature",
  "properties": {
    "addr:full":"2 Enos Pl Jersey City NJ 07306",
    "addr:housenumber":"2",
    "addr:postcode":"07306",
    "addr:street":"Enos Pl",
    "iso:country":"US",
    "sg:address":"2 Enos Pl",
    "sg:city":"Jersey City",
    "sg:classifiers":[
        {
            "category":"Government",
            "subcategory":"Office",
            "type":"Public Place"
        }
    ],
    "sg:phone":"+1 201 420 3172",
    "sg:postcode":"07306",
    "sg:province":"NJ",
    "sg:tags":[
        "county",
        "resource"
    ],
    "wof:name":"Hudson County Food Stamps",
    "wof:placetype":"venue"
},
  "geometry": {"coordinates":[-74.063233,40.730641],"type":"Point"}
}