{
  "type": "Feature",
  "properties": {
    "addr:full":"139 Pine Brook Rd Englishtown NJ 07726",
    "addr:housenumber":"139",
    "addr:postcode":"07726",
    "addr:street":"Pine Brook Rd",
    "iso:country":"US",
    "sg:address":"139 Pine Brook Rd",
    "sg:city":"Englishtown",
    "sg:classifiers":[
        {
            "category":"Social Services",
            "subcategory":"Child Care",
            "type":"Services"
        },
        {
            "category":"Travel",
            "subcategory":"Campground",
            "type":"Entertainment"
        }
    ],
    "sg:phone":"+1 732 446 4700",
    "sg:postcode":"07726",
    "sg:province":"NJ",
    "sg:tags":[
        "kindergarten",
        "academic",
        "school",
        "camp",
        "day"
    ],
    "wof:name":"Yellow Duck Nursery Inc",
    "wof:placetype":"venue"
},
  "geometry": {"coordinates":[-74.33897,40.317764],"type":"Point"}
}