{
  "type": "Feature",
  "properties": {
    "iso:country":"US",
    "sg:address":"75 W Allendale Ave",
    "sg:city":"Allendale",
    "sg:classifiers":[
        {
            "category":"Autos & Motor Vehicles",
            "subcategory":"Auto Supplies",
            "type":"Retail Goods"
        },
        {
            "category":"Wholesale",
            "subcategory":"Auto Parts",
            "type":"Manufacturing & Wholesale Goods"
        }
    ],
    "sg:phone":"+1 201 327 3460",
    "sg:postcode":"07401",
    "sg:province":"NJ",
    "sg:tags":[
        "automobile",
        "used",
        "new",
        "accessory"
    ],
    "wof:name":"Allendale Auto Parts Inc",
    "wof:placetype":"venue"
},
  "geometry": {"coordinates":[-74.128214,41.030299],"type":"Point"}
}