{
  "type": "Feature",
  "properties": {
    "iso:country":"US",
    "sg:address":"101 N Benson Ave",
    "sg:city":"Margate City",
    "sg:classifiers":[
        {
            "category":"Building & Trades",
            "subcategory":"Construction",
            "type":"Services"
        }
    ],
    "sg:phone":"+1 609 822 5038",
    "sg:postcode":"08402",
    "sg:province":"NJ",
    "sg:tags":[
        "marking",
        "maintenance",
        "parking"
    ],
    "wof:name":"Margate City Public Works",
    "wof:placetype":"venue"
},
  "geometry": {"coordinates":[-74.514994,39.32545],"type":"Point"}
}