{
  "type": "Feature",
  "properties": {
    "iso:country":"US",
    "sg:address":"205 W End Ave",
    "sg:city":"Long Branch",
    "sg:classifiers":[
        {
            "category":"Building & Trades",
            "subcategory":"Construction",
            "type":"Services"
        }
    ],
    "sg:phone":"+1 732 996 8732",
    "sg:postcode":"07740",
    "sg:province":"NJ",
    "sg:tags":[
        "resurfacing",
        "laying",
        "refinishing",
        "floor"
    ],
    "wof:name":"Splendid Hardwood Floors",
    "wof:placetype":"venue"
},
  "geometry": {"coordinates":[-73.990092,40.28614],"type":"Point"}
}