{
  "type": "Feature",
  "properties": {
    "addr:full":"11 Marcy St Freehold NJ 07728",
    "addr:housenumber":"11",
    "addr:postcode":"07728",
    "addr:street":"Marcy St",
    "iso:country":"US",
    "sg:address":"11 Marcy St",
    "sg:city":"Freehold",
    "sg:classifiers":[
        {
            "category":"Freight",
            "type":"Transportation"
        },
        {
            "category":"Building & Trades",
            "subcategory":"Construction",
            "type":"Services"
        }
    ],
    "sg:phone":"+1 732 462 3036",
    "sg:postcode":"07728",
    "sg:province":"NJ",
    "sg:tags":[
        "home",
        "general",
        "improvement"
    ],
    "wof:name":"Froehlich Building & Cnstr Co",
    "wof:placetype":"venue"
},
  "geometry": {"coordinates":[-74.27251800000001,40.257016],"type":"Point"}
}