{
  "type": "Feature",
  "properties": {
    "iso:country":"US",
    "sg:address":"1307 W Union Ln",
    "sg:city":"Manasquan",
    "sg:classifiers":[
        {
            "category":"Professional",
            "type":"Services"
        }
    ],
    "sg:phone":"+1   ",
    "sg:postcode":"08736",
    "sg:province":"NJ",
    "wof:name":"Cordially Yours",
    "wof:placetype":"venue"
},
  "geometry": {"coordinates":[-74.068386,40.115581],"type":"Point"}
}