{
  "type": "Feature",
  "properties": {
    "addr:full":"701 US Highway 9 North S Cape May Court House NJ 08210",
    "addr:housenumber":"701",
    "addr:postcode":"08210",
    "addr:street":"Us Highway 9 North S;May Court",
    "iso:country":"US",
    "sg:address":"701 US Highway 9 North S",
    "sg:city":"Cape May Court House",
    "sg:classifiers":[
        {
            "category":"Shopping",
            "subcategory":"Crafts & Fabrics",
            "type":"Retail Goods"
        }
    ],
    "sg:phone":"+1 609 465 6701",
    "sg:postcode":"08210",
    "sg:province":"NJ",
    "sg:tags":[
        "store"
    ],
    "wof:name":"The Red Schoolhouse",
    "wof:placetype":"venue"
},
  "geometry": {"coordinates":[-74.812637,39.098691],"type":"Point"}
}