{
  "type": "Feature",
  "properties": {
    "addr:full":"820 Kearny Ave Kearny NJ 07032",
    "addr:housenumber":"820",
    "addr:postcode":"07032",
    "addr:street":"Kearny Ave",
    "iso:country":"US",
    "sg:address":"820 Kearny Ave",
    "sg:city":"Kearny",
    "sg:classifiers":[
        {
            "category":"Shopping",
            "subcategory":"Gifts & Souvenirs",
            "type":"Retail Goods"
        }
    ],
    "sg:phone":"+1   ",
    "sg:postcode":"07032",
    "sg:province":"NJ",
    "wof:name":"FLP Book Gifts & Thrift Shop",
    "wof:placetype":"venue"
},
  "geometry": {"coordinates":[-74.139505,40.780437],"type":"Point"}
}