{
  "type": "Feature",
  "properties": {
    "iso:country":"US",
    "sg:address":"55 Sitgreaves St",
    "sg:city":"Phillipsburg",
    "sg:classifiers":[
        {
            "category":"Autos & Motor Vehicles",
            "subcategory":"Automobile Sales",
            "type":"Retail Goods"
        }
    ],
    "sg:phone":"+1 908 213 8832",
    "sg:postcode":"08865",
    "sg:province":"NJ",
    "sg:tags":[
        "classic"
    ],
    "wof:name":"Grossmueller's Classic Crvtt",
    "wof:placetype":"venue"
},
  "geometry": {"coordinates":[-75.190499,40.686492],"type":"Point"}
}