{
  "type": "Feature",
  "properties": {
    "addr:full":"20 Conkling Rd Flanders NJ 07836",
    "addr:housenumber":"20",
    "addr:postcode":"07836",
    "addr:street":"Conkling Rd",
    "iso:country":"US",
    "sg:address":"20 Conkling Rd",
    "sg:city":"Flanders",
    "sg:classifiers":[
        {
            "category":"Professional",
            "subcategory":"Lawyer & Legal Services",
            "type":"Services"
        }
    ],
    "sg:phone":"+1   ",
    "sg:postcode":"07836",
    "sg:province":"NJ",
    "wof:name":"James L Barrett Jr",
    "wof:placetype":"venue"
},
  "geometry": {"coordinates":[-74.682698,40.874277],"type":"Point"}
}