{
  "type": "Feature",
  "properties": {
    "iso:country":"US",
    "sg:address":"400 State Rte 38",
    "sg:city":"Moorestown",
    "sg:classifiers":[
        {
            "category":"Shopping",
            "subcategory":"Music",
            "type":"Retail Goods"
        }
    ],
    "sg:phone":"+1 856 235 2200",
    "sg:postcode":"08057",
    "sg:province":"NJ",
    "sg:tags":[
        "compact",
        "record",
        "disc",
        "tape"
    ],
    "wof:name":"Fye",
    "wof:placetype":"venue"
},
  "geometry": {"coordinates":[-74.963235,39.946261],"type":"Point"}
}