{
  "type": "Feature",
  "properties": {
    "iso:country":"US",
    "sg:address":"357 Buckelew Ave",
    "sg:city":"Jamesburg",
    "sg:classifiers":[
        {
            "category":"Health Services",
            "subcategory":"Nursing And Care Facility",
            "type":"Services"
        }
    ],
    "sg:phone":"+1 732 521 1194",
    "sg:postcode":"08831",
    "sg:province":"NJ",
    "sg:tags":[
        "home",
        "convalescent",
        "rest"
    ],
    "wof:name":"Pamid Haven Rest Home Inc",
    "wof:placetype":"venue"
},
  "geometry": {"coordinates":[-74.433027,40.34673],"type":"Point"}
}