{
  "type": "Feature",
  "properties": {
    "addr:full":"250 Woodbridge Ctr Woodbridge NJ 07095",
    "addr:housenumber":"250",
    "addr:postcode":"07095",
    "addr:street":"Woodbridge Ctr",
    "iso:country":"US",
    "sg:address":"250 Woodbridge Ctr",
    "sg:city":"Woodbridge",
    "sg:classifiers":[
        {
            "category":"Shopping",
            "subcategory":"Jewelry",
            "type":"Retail Goods"
        }
    ],
    "sg:phone":"+1 732 636 2023",
    "sg:postcode":"07095",
    "sg:province":"NJ",
    "wof:name":"Brighton Collectibles",
    "wof:placetype":"venue"
},
  "geometry": {"coordinates":[-74.297363,40.55822],"type":"Point"}
}