{
  "type": "Feature",
  "properties": {
    "addr:full":"2029 State Rte 35 Laurence Harbor NJ 08879",
    "addr:housenumber":"2029",
    "addr:postcode":"08879",
    "addr:street":"State Rte 35",
    "iso:country":"US",
    "sg:address":"2029 State Rte 35",
    "sg:city":"Laurence Harbor",
    "sg:classifiers":[
        {
            "category":"Retail",
            "subcategory":"Auto Repair",
            "type":"Services"
        }
    ],
    "sg:phone":"+1 732 727 8899",
    "sg:postcode":"08879",
    "sg:province":"NJ",
    "sg:tags":[
        "repairing",
        "automobile"
    ],
    "wof:name":"Gallucci's Auto Svc & Sale",
    "wof:placetype":"venue"
},
  "geometry": {"coordinates":[-74.27672200000001,40.46469],"type":"Point"}
}