{
  "type": "Feature",
  "properties": {
    "addr:full":"40 Goble St Newark NJ 07114",
    "addr:housenumber":"40",
    "addr:postcode":"07114",
    "addr:street":"Goble St",
    "iso:country":"US",
    "sg:address":"40 Goble St",
    "sg:city":"Newark",
    "sg:classifiers":[
        {
            "category":"Building & Trades",
            "subcategory":"Electrical",
            "type":"Services"
        }
    ],
    "sg:phone":"+1 973 242 1188",
    "sg:postcode":"07114",
    "sg:province":"NJ",
    "sg:tags":[
        "electrical",
        "contractor"
    ],
    "wof:name":"JM Electric",
    "wof:placetype":"venue"
},
  "geometry": {"coordinates":[-74.17400499999999,40.720144],"type":"Point"}
}