{
  "type": "Feature",
  "properties": {
    "addr:full":"1625 Princeton Ave Trenton NJ 08648",
    "addr:housenumber":"1625",
    "addr:postcode":"08648",
    "addr:street":"Princeton Ave",
    "iso:country":"US",
    "sg:address":"1625 Princeton Ave",
    "sg:city":"Trenton",
    "sg:classifiers":[
        {
            "category":"Manufacturing",
            "subcategory":"Chemicals & Compounds",
            "type":"Manufacturing & Wholesale Goods"
        }
    ],
    "sg:phone":"+1 609 599 4519",
    "sg:postcode":"08648",
    "sg:province":"NJ",
    "sg:tags":[
        "plumbing",
        "industrial",
        "gas",
        "mfg"
    ],
    "wof:name":"Praxair",
    "wof:placetype":"venue"
},
  "geometry": {"coordinates":[-74.749748,40.242857],"type":"Point"}
}