{
  "type": "Feature",
  "properties": {
    "iso:country":"US",
    "sg:address":"467 Madison Ave",
    "sg:city":"Paterson",
    "sg:classifiers":[
        {
            "category":"Shopping",
            "subcategory":"Beauty & Cosmetics",
            "type":"Retail Goods"
        }
    ],
    "sg:phone":"+1 973 279 6700",
    "sg:postcode":"07524",
    "sg:province":"NJ",
    "sg:tags":[
        "supply"
    ],
    "wof:name":"Hair's Everything",
    "wof:placetype":"venue"
},
  "geometry": {"coordinates":[-74.15160400000001,40.924999],"type":"Point"}
}