{
  "type": "Feature",
  "properties": {
    "iso:country":"US",
    "sg:address":"10 Valley Rd",
    "sg:city":"Englishtown",
    "sg:classifiers":[
        {
            "category":"Professional",
            "subcategory":"Research",
            "type":"Services"
        }
    ],
    "sg:phone":"+1   ",
    "sg:postcode":"07726",
    "sg:province":"NJ",
    "sg:tags":[
        "commercial",
        "physical"
    ],
    "wof:name":"Rjf Research",
    "wof:placetype":"venue"
},
  "geometry": {"coordinates":[-74.366162,40.242],"type":"Point"}
}