{
  "type": "Feature",
  "properties": {
    "addr:full":"678 White Horse Pike Absecon NJ 08201",
    "addr:housenumber":"678",
    "addr:postcode":"08201",
    "addr:street":"White Horse Pike",
    "iso:country":"US",
    "sg:address":"678 White Horse Pike",
    "sg:city":"Absecon",
    "sg:classifiers":[
        {
            "category":"Retail",
            "subcategory":"Portrait Studio",
            "type":"Services"
        }
    ],
    "sg:phone":"+1 609 641 0101",
    "sg:postcode":"08201",
    "sg:province":"NJ",
    "sg:tags":[
        "photographer"
    ],
    "wof:name":"Moto Photo",
    "wof:placetype":"venue"
},
  "geometry": {"coordinates":[-74.51161,39.432165],"type":"Point"}
}