{
  "type": "Feature",
  "properties": {
    "addr:full":"82 Grant Ave Cresskill NJ 07626",
    "addr:housenumber":"82",
    "addr:postcode":"07626",
    "addr:street":"Grant Ave",
    "iso:country":"US",
    "sg:address":"82 Grant Ave",
    "sg:city":"Cresskill",
    "sg:classifiers":[
        {
            "category":"Professional",
            "subcategory":"Management & Consulting",
            "type":"Services"
        }
    ],
    "sg:phone":"+1 201 894 1565",
    "sg:postcode":"07626",
    "sg:province":"NJ",
    "sg:tags":[
        "fuel"
    ],
    "wof:name":"VMH Enterprise",
    "wof:placetype":"venue"
},
  "geometry": {"coordinates":[-73.964951,40.945171],"type":"Point"}
}