{
  "type": "Feature",
  "properties": {
    "addr:full":"30 Main St Chester NJ 07930",
    "addr:housenumber":"30",
    "addr:postcode":"07930",
    "addr:street":"Main St",
    "iso:country":"US",
    "sg:address":"30 Main St",
    "sg:city":"Chester",
    "sg:classifiers":[
        {
            "category":"Ice Cream",
            "type":"Food & Drink"
        }
    ],
    "sg:menulink":"http://www.allmenus.com/nj/chester/167816-dairy-queen/menu/",
    "sg:phone":"+1 908 879 5546",
    "sg:postcode":"07930",
    "sg:province":"NJ",
    "sg:tags":[
        "burger",
        "american"
    ],
    "wof:name":"Dairy Queen",
    "wof:placetype":"venue"
},
  "geometry": {"coordinates":[-74.696904,40.784469],"type":"Point"}
}