{
  "type": "Feature",
  "properties": {
    "addr:full":"1161 Main Ave Clifton NJ 07011",
    "addr:housenumber":"1161",
    "addr:postcode":"07011",
    "addr:street":"Main Ave",
    "iso:country":"US",
    "sg:address":"1161 Main Ave",
    "sg:city":"Clifton",
    "sg:classifiers":[
        {
            "category":"Shopping",
            "subcategory":"Florist",
            "type":"Retail Goods"
        }
    ],
    "sg:phone":"+1 973 773 2229",
    "sg:postcode":"07011",
    "sg:province":"NJ",
    "wof:name":"Martha Dream Florist",
    "wof:placetype":"venue"
},
  "geometry": {"coordinates":[-74.139926,40.875444],"type":"Point"}
}