{
  "type": "Feature",
  "properties": {
    "addr:full":"3640 State Rte 94 Hamburg NJ 07419",
    "addr:housenumber":"3640",
    "addr:postcode":"07419",
    "addr:street":"State Rte 94",
    "iso:country":"US",
    "sg:address":"3640 State Rte 94",
    "sg:city":"Hamburg",
    "sg:classifiers":[
        {
            "category":"Professional",
            "subcategory":"Computer Services",
            "type":"Services"
        }
    ],
    "sg:phone":"+1 973 702 3005",
    "sg:postcode":"07419",
    "sg:province":"NJ",
    "wof:name":"Secure Enterprise Solutions",
    "wof:placetype":"venue"
},
  "geometry": {"coordinates":[-74.568258,41.159938],"type":"Point"}
}