{
  "type": "Feature",
  "properties": {
    "iso:country":"US",
    "sg:address":"730 Anderson Ave",
    "sg:city":"Cliffside Park",
    "sg:classifiers":[
        {
            "category":"Food & Beverages",
            "subcategory":"Liquor & Beverages",
            "type":"Retail Goods"
        },
        {
            "category":"Food & Beverages",
            "subcategory":"Groceries & Convenience Stores",
            "type":"Retail Goods"
        }
    ],
    "sg:phone":"+1 201 941 3886",
    "sg:postcode":"07010",
    "sg:province":"NJ",
    "sg:tags":[
        "deli"
    ],
    "wof:name":"Campbell's Deli",
    "wof:placetype":"venue"
},
  "geometry": {"coordinates":[-73.985901,40.829498],"type":"Point"}
}