{
  "type": "Feature",
  "properties": {
    "iso:country":"US",
    "sg:address":"96 8th Ave",
    "sg:city":"Montclair",
    "sg:classifiers":[
        {
            "category":"Health Services",
            "subcategory":"Doctor",
            "type":"Services"
        }
    ],
    "sg:phone":"+1 973 744 0098",
    "sg:postcode":"07055",
    "sg:province":"NJ",
    "sg:tags":[
        "medical"
    ],
    "wof:name":"Neuro Surgial Group",
    "wof:placetype":"venue"
},
  "geometry": {"coordinates":[-74.140632,40.860679],"type":"Point"}
}