{
  "type": "Feature",
  "properties": {
    "iso:country":"US",
    "sg:address":"254 Vose Ave",
    "sg:city":"South Orange",
    "sg:classifiers":[
        {
            "category":"Organizations",
            "subcategory":"Non-profit Organization",
            "type":"Services"
        }
    ],
    "sg:phone":"+1 973 699 7510",
    "sg:postcode":"07079",
    "sg:province":"NJ",
    "sg:tags":[
        "info",
        "addiction",
        "abuse",
        "treatment",
        "drug"
    ],
    "wof:name":"New Directions Counseling Ctr",
    "wof:placetype":"venue"
},
  "geometry": {"coordinates":[-74.25335099999999,40.753391],"type":"Point"}
}