{
  "type": "Feature",
  "properties": {
    "addr:full":"30 Obal Ave Elmwood Park NJ 07407",
    "addr:housenumber":"30",
    "addr:postcode":"07407",
    "addr:street":"Obal Ave",
    "iso:country":"US",
    "sg:address":"30 Obal Ave",
    "sg:city":"Elmwood Park",
    "sg:classifiers":[
        {
            "category":"Building & Trades",
            "subcategory":"Construction",
            "type":"Services"
        }
    ],
    "sg:phone":"+1 201 796 5558",
    "sg:postcode":"07407",
    "sg:province":"NJ",
    "sg:tags":[
        "contractor"
    ],
    "wof:name":"New Image Tile",
    "wof:placetype":"venue"
},
  "geometry": {"coordinates":[-74.106482,40.898073],"type":"Point"}
}