{
  "type": "Feature",
  "properties": {
    "iso:country":"US",
    "sg:address":"2400 Hudson Ter",
    "sg:city":"Fort Lee",
    "sg:classifiers":[
        {
            "category":"Real Estate",
            "subcategory":"Real Estate Operator",
            "type":"Services"
        }
    ],
    "sg:phone":"+1 201 461 8665",
    "sg:postcode":"07024",
    "sg:province":"NJ",
    "sg:tags":[
        "apartment"
    ],
    "wof:name":"Half Moon House",
    "wof:placetype":"venue"
},
  "geometry": {"coordinates":[-73.958298,40.862],"type":"Point"}
}