{
  "type": "Feature",
  "properties": {
    "addr:full":"440 N Broadway Gloucester City NJ 08030",
    "addr:housenumber":"440",
    "addr:postcode":"08030",
    "addr:street":"N Broadway",
    "iso:country":"US",
    "sg:address":"440 N Broadway",
    "sg:city":"Gloucester City",
    "sg:classifiers":[
        {
            "category":"Professional",
            "type":"Services"
        }
    ],
    "sg:phone":"+1 856 456 6262",
    "sg:postcode":"08030",
    "sg:province":"NJ",
    "sg:tags":[
        "establishment"
    ],
    "wof:name":"Philadelphia Newspapers Inc",
    "wof:placetype":"venue"
},
  "geometry": {"coordinates":[-75.120074,39.902832],"type":"Point"}
}