{
  "type": "Feature",
  "properties": {
    "iso:country":"US",
    "sg:address":"478 Bloomfield Ave",
    "sg:city":"Caldwell",
    "sg:classifiers":[
        {
            "category":"Food & Beverages",
            "subcategory":"Liquor & Beverages",
            "type":"Retail Goods"
        }
    ],
    "sg:phone":"+1 973 226 8400",
    "sg:postcode":"07006",
    "sg:province":"NJ",
    "sg:tags":[
        "beer",
        "spirit",
        "wine"
    ],
    "wof:name":"Shop Rite Liquors of Caldwell",
    "wof:placetype":"venue"
},
  "geometry": {"coordinates":[-74.281403,40.843102],"type":"Point"}
}