{
  "type": "Feature",
  "properties": {
    "iso:country":"US",
    "sg:address":"437 Main St",
    "sg:city":"Little Falls",
    "sg:classifiers":[
        {
            "category":"Professional",
            "type":"Services"
        }
    ],
    "sg:phone":"+1   ",
    "sg:postcode":"07424",
    "sg:province":"NJ",
    "wof:name":"Rose Little Spa",
    "wof:placetype":"venue"
},
  "geometry": {"coordinates":[-74.24097500000001,40.886096],"type":"Point"}
}