{
  "type": "Feature",
  "properties": {
    "addr:full":"365 State Rte 17 Ramsey NJ 07446",
    "addr:housenumber":"365",
    "addr:postcode":"07446",
    "addr:street":"State Rte 17",
    "iso:country":"US",
    "sg:address":"365 State Rte 17",
    "sg:city":"Ramsey",
    "sg:classifiers":[
        {
            "category":"Autos & Motor Vehicles",
            "subcategory":"Automobile Sales",
            "type":"Retail Goods"
        }
    ],
    "sg:phone":"+1 201 327 5100",
    "sg:postcode":"07446",
    "sg:province":"NJ",
    "sg:tags":[
        "car",
        "dealer"
    ],
    "wof:name":"Ramsey Infiniti",
    "wof:placetype":"venue"
},
  "geometry": {"coordinates":[-74.11888500000001,41.051385],"type":"Point"}
}