{
  "type": "Feature",
  "properties": {
    "addr:full":"8 Germack Dr Carteret NJ 07008",
    "addr:housenumber":"8",
    "addr:postcode":"07008",
    "addr:street":"Germack Dr",
    "iso:country":"US",
    "sg:address":"8 Germack Dr",
    "sg:city":"Carteret",
    "sg:classifiers":[
        {
            "category":"Manufacturing",
            "subcategory":"Wood Products",
            "type":"Manufacturing & Wholesale Goods"
        }
    ],
    "sg:phone":"+1 732 541 7000",
    "sg:postcode":"07008",
    "sg:province":"NJ",
    "sg:tags":[
        "packaging",
        "pallet",
        "crate",
        "reconditions",
        "mfg"
    ],
    "wof:name":"Millwood Inc",
    "wof:placetype":"venue"
},
  "geometry": {"coordinates":[-74.24067599999999,40.592504],"type":"Point"}
}