{
  "type": "Feature",
  "properties": {
    "addr:full":"387 Neville St Perth Amboy NJ 08861",
    "addr:housenumber":"387",
    "addr:postcode":"08861",
    "addr:street":"Neville St",
    "iso:country":"US",
    "sg:address":"387 Neville St",
    "sg:city":"Perth Amboy",
    "sg:classifiers":[
        {
            "category":"Health Services",
            "subcategory":"Hospital",
            "type":"Services"
        }
    ],
    "sg:phone":"+1 732 324 8812",
    "sg:postcode":"08861",
    "sg:province":"NJ",
    "sg:tags":[
        "mental"
    ],
    "wof:name":"Sunrise Instution For Mental",
    "wof:placetype":"venue"
},
  "geometry": {"coordinates":[-74.277153,40.51901],"type":"Point"}
}