{
  "type": "Feature",
  "properties": {
    "addr:full":"300 N 32nd St Camden NJ 08105",
    "addr:housenumber":"300",
    "addr:postcode":"08105",
    "addr:street":"N 32Nd St",
    "iso:country":"US",
    "sg:address":"300 N 32nd St",
    "sg:city":"Camden",
    "sg:classifiers":[
        {
            "category":"Building & Trades",
            "subcategory":"Construction",
            "type":"Services"
        }
    ],
    "sg:phone":"+1 856 966 8220",
    "sg:postcode":"08105",
    "sg:province":"NJ",
    "sg:tags":[
        "carpenter"
    ],
    "wof:name":"Carpenter Hill",
    "wof:placetype":"venue"
},
  "geometry": {"coordinates":[-75.079984,39.952504],"type":"Point"}
}