{
  "type": "Feature",
  "properties": {
    "addr:full":"144 Linden Ave Verona NJ 07044",
    "addr:housenumber":"144",
    "addr:postcode":"07044",
    "addr:street":"Linden Ave",
    "iso:country":"US",
    "sg:address":"144 Linden Ave",
    "sg:city":"Verona",
    "sg:classifiers":[
        {
            "category":"Building & Trades",
            "subcategory":"Plumbing",
            "type":"Services"
        }
    ],
    "sg:phone":"+1 973 571 9803",
    "sg:postcode":"07044",
    "sg:province":"NJ",
    "sg:tags":[
        "contractor"
    ],
    "wof:name":"Pena Plumbing",
    "wof:placetype":"venue"
},
  "geometry": {"coordinates":[-74.239332,40.835181],"type":"Point"}
}