{
  "type": "Feature",
  "properties": {
    "iso:country":"US",
    "sg:address":"105 Bucks Mill Rd",
    "sg:city":"Colts Neck",
    "sg:classifiers":[
        {
            "category":"Farming",
            "subcategory":"Livestock Farm",
            "type":"Manufacturing & Wholesale Goods"
        }
    ],
    "sg:phone":"+1 732 409 6074",
    "sg:postcode":"07722",
    "sg:province":"NJ",
    "sg:tags":[
        "equine"
    ],
    "wof:name":"Bucks Mill Farm",
    "wof:placetype":"venue"
},
  "geometry": {"coordinates":[-74.198947,40.289382],"type":"Point"}
}