{
  "type": "Feature",
  "properties": {
    "iso:country":"US",
    "sg:address":"100 Willow Brook Rd",
    "sg:city":"Colts Neck",
    "sg:classifiers":[
        {
            "category":"Retail",
            "subcategory":"Animal Services",
            "type":"Services"
        }
    ],
    "sg:phone":"+1 732 946 8258",
    "sg:postcode":"07722",
    "sg:province":"NJ",
    "sg:tags":[
        "breeder",
        "horse"
    ],
    "wof:name":"Greenfields Farm Inc",
    "wof:placetype":"venue"
},
  "geometry": {"coordinates":[-74.18120399999999,40.329384],"type":"Point"}
}