{
  "type": "Feature",
  "properties": {
    "addr:full":"240 Van Sciver Pkwy Willingboro NJ 08046",
    "addr:housenumber":"240",
    "addr:postcode":"08046",
    "addr:street":"Van Sciver Pkwy",
    "iso:country":"US",
    "sg:address":"240 Van Sciver Pkwy",
    "sg:city":"Willingboro",
    "sg:classifiers":[
        {
            "category":"Food & Beverages",
            "subcategory":"Groceries & Convenience Stores",
            "type":"Retail Goods"
        }
    ],
    "sg:phone":"+1   ",
    "sg:postcode":"08046",
    "sg:province":"NJ",
    "wof:name":"Jai Maa Santoshi LLC",
    "wof:placetype":"venue"
},
  "geometry": {"coordinates":[-74.87804800000001,40.042054],"type":"Point"}
}