{
  "type": "Feature",
  "properties": {
    "addr:full":"815 W Park Ave Ocean NJ 07712",
    "addr:housenumber":"815",
    "addr:postcode":"07712",
    "addr:street":"W Park Ave",
    "iso:country":"US",
    "sg:address":"815 W Park Ave",
    "sg:city":"Ocean",
    "sg:classifiers":[
        {
            "category":"Restaurant",
            "type":"Food & Drink"
        }
    ],
    "sg:phone":"+1 732 493 6398",
    "sg:postcode":"07712",
    "sg:province":"NJ",
    "wof:name":"Golden Sun Chinese",
    "wof:placetype":"venue"
},
  "geometry": {"coordinates":[-74.04333099999999,40.264191],"type":"Point"}
}