{
  "type": "Feature",
  "properties": {
    "iso:country":"US",
    "sg:address":"4308 New York Ave",
    "sg:city":"Union City",
    "sg:classifiers":[
        {
            "category":"Food & Beverages",
            "subcategory":"Groceries & Convenience Stores",
            "type":"Retail Goods"
        }
    ],
    "sg:phone":"+1 201 392 8552",
    "sg:postcode":"07087",
    "sg:province":"NJ",
    "wof:name":"Mi Pequeno Rincon De Mexico",
    "wof:placetype":"venue"
},
  "geometry": {"coordinates":[-74.02330000000001,40.777599],"type":"Point"}
}