{
  "type": "Feature",
  "properties": {
    "iso:country":"US",
    "sg:address":"247 Rosebay Ct",
    "sg:city":"Riverside",
    "sg:classifiers":[
        {
            "category":"Professional",
            "subcategory":"Business Services",
            "type":"Services"
        }
    ],
    "sg:phone":"+1   ",
    "sg:postcode":"08075",
    "sg:province":"NJ",
    "wof:name":"In Design Creative Studios LLC",
    "wof:placetype":"venue"
},
  "geometry": {"coordinates":[-74.924972,40.010759],"type":"Point"}
}