{
  "type": "Feature",
  "properties": {
    "iso:country":"US",
    "sg:address":"191 Grandview Ave",
    "sg:city":"Caldwell",
    "sg:classifiers":[
        {
            "category":"Wholesale",
            "subcategory":"Stationery",
            "type":"Manufacturing & Wholesale Goods"
        }
    ],
    "sg:phone":"+1 973 228 0995",
    "sg:postcode":"07006",
    "sg:province":"NJ",
    "sg:tags":[
        "mill",
        "paper",
        "broker",
        "representative"
    ],
    "wof:name":"Cartacel Inc",
    "wof:placetype":"venue"
},
  "geometry": {"coordinates":[-74.25775899999999,40.879754],"type":"Point"}
}