{
  "type": "Feature",
  "properties": {
    "addr:full":"4 Baird Dr Hillsborough NJ 08844",
    "addr:housenumber":"4",
    "addr:postcode":"08844",
    "addr:street":"Baird Dr",
    "iso:country":"US",
    "sg:address":"4 Baird Dr",
    "sg:city":"Hillsborough",
    "sg:classifiers":[
        {
            "category":"Professional",
            "type":"Services"
        }
    ],
    "sg:phone":"+1 732 446 9867",
    "sg:postcode":"08844",
    "sg:province":"NJ",
    "sg:tags":[
        "establishment"
    ],
    "wof:name":"Wagner Farm Park",
    "wof:placetype":"venue"
},
  "geometry": {"coordinates":[-74.597813,40.474227],"type":"Point"}
}