{
  "type": "Feature",
  "properties": {
    "iso:country":"US",
    "sg:address":"128 Tappan Rd",
    "sg:city":"Harrington Park",
    "sg:classifiers":[
        {
            "category":"Professional",
            "subcategory":"Computer Services",
            "type":"Services"
        }
    ],
    "sg:phone":"+1   ",
    "sg:postcode":"07640",
    "sg:province":"NJ",
    "sg:tags":[
        "related"
    ],
    "wof:name":"Ensa Systems Inc",
    "wof:placetype":"venue"
},
  "geometry": {"coordinates":[-73.969455,40.990333],"type":"Point"}
}