{
  "type": "Feature",
  "properties": {
    "addr:full":"19 N Broad St Woodbury NJ 08096",
    "addr:housenumber":"19",
    "addr:postcode":"08096",
    "addr:street":"N Broad St",
    "iso:country":"US",
    "sg:address":"19 N Broad St",
    "sg:city":"Woodbury",
    "sg:classifiers":[
        {
            "category":"Government",
            "subcategory":"Office",
            "type":"Public Place"
        }
    ],
    "sg:phone":"+1 856 853 3479",
    "sg:postcode":"08096",
    "sg:province":"NJ",
    "wof:name":"Honorable James Rafferty",
    "wof:placetype":"venue"
},
  "geometry": {"coordinates":[-75.15309999999999,39.838341],"type":"Point"}
}