{
  "type": "Feature",
  "properties": {
    "iso:country":"US",
    "sg:address":"4611 US Hwy 9",
    "sg:city":"Howell",
    "sg:classifiers":[
        {
            "category":"Recreation",
            "type":"Entertainment"
        }
    ],
    "sg:phone":"+1 732 370 6336",
    "sg:postcode":"07731",
    "sg:province":"NJ",
    "sg:tags":[
        "hall",
        "auditorium"
    ],
    "wof:name":"Southard Fire Hall Rentals",
    "wof:placetype":"venue"
},
  "geometry": {"coordinates":[-74.22471899999999,40.138714],"type":"Point"}
}