{
  "type": "Feature",
  "properties": {
    "addr:full":"2091 Springdale Rd Cherry Hill NJ 08003",
    "addr:housenumber":"2091",
    "addr:postcode":"08003",
    "addr:street":"Springdale Rd",
    "iso:country":"US",
    "sg:address":"2091 Springdale Rd",
    "sg:city":"Cherry Hill",
    "sg:classifiers":[
        {
            "category":"Manufacturing",
            "subcategory":"Tools & Machinery",
            "type":"Manufacturing & Wholesale Goods"
        }
    ],
    "sg:phone":"+1 856 489 9453",
    "sg:postcode":"08003",
    "sg:province":"NJ",
    "wof:name":"Transcat",
    "wof:placetype":"venue"
},
  "geometry": {"coordinates":[-74.96436199999999,39.919917],"type":"Point"}
}