{
  "type": "Feature",
  "properties": {
    "addr:full":"2309 Bergenline Ave Union City NJ 07087",
    "addr:housenumber":"2309",
    "addr:postcode":"07087",
    "addr:street":"Bergenline Ave",
    "iso:country":"US",
    "sg:address":"2309 Bergenline Ave",
    "sg:city":"Union City",
    "sg:classifiers":[
        {
            "category":"Personal",
            "subcategory":"Barber",
            "type":"Services"
        }
    ],
    "sg:phone":"+1 201 472 9040",
    "sg:postcode":"07087",
    "sg:province":"NJ",
    "wof:name":"Pronto Barber Shop",
    "wof:placetype":"venue"
},
  "geometry": {"coordinates":[-74.03285099999999,40.767393],"type":"Point"}
}