{
  "type": "Feature",
  "properties": {
    "iso:country":"US",
    "sg:address":"137 Main St",
    "sg:city":"Metuchen",
    "sg:classifiers":[
        {
            "category":"Building & Trades",
            "subcategory":"Construction",
            "type":"Services"
        }
    ],
    "sg:phone":"+1 732 270 5526",
    "sg:postcode":"08840",
    "sg:province":"NJ",
    "sg:tags":[
        "contractor"
    ],
    "wof:name":"Staten Island Contractors",
    "wof:placetype":"venue"
},
  "geometry": {"coordinates":[-74.359002,40.532858],"type":"Point"}
}