{
  "type": "Feature",
  "properties": {
    "iso:country":"US",
    "sg:address":"12 Washington Pl",
    "sg:city":"Kearny",
    "sg:classifiers":[
        {
            "category":"Recreation",
            "type":"Entertainment"
        },
        {
            "category":"Organizations",
            "subcategory":"Community Association",
            "type":"Services"
        }
    ],
    "sg:phone":"+1 201 991 9514",
    "sg:postcode":"07032",
    "sg:province":"NJ",
    "sg:tags":[
        "club",
        "membership"
    ],
    "wof:name":"Arlington Players Club Inc",
    "wof:placetype":"venue"
},
  "geometry": {"coordinates":[-74.144666,40.773892],"type":"Point"}
}