{
  "type": "Feature",
  "properties": {
    "addr:full":"430 Broadway Bayonne NJ 07002",
    "addr:housenumber":"430",
    "addr:postcode":"07002",
    "addr:street":"Broadway",
    "iso:country":"US",
    "sg:address":"430 Broadway",
    "sg:city":"Bayonne",
    "sg:classifiers":[
        {
            "category":"Food & Beverages",
            "subcategory":"Specialty",
            "type":"Retail Goods"
        }
    ],
    "sg:phone":"+1 201 823 9797",
    "sg:postcode":"07002",
    "sg:province":"NJ",
    "sg:tags":[
        "herb",
        "shopping"
    ],
    "sg:website":"http://www.gnc.com",
    "wof:name":"GNC",
    "wof:placetype":"venue"
},
  "geometry": {"coordinates":[-74.12009,40.66174],"type":"Point"}
}