{
  "type": "Feature",
  "properties": {
    "iso:country":"US",
    "sg:address":"202 Wood St",
    "sg:city":"Rutherford",
    "sg:classifiers":[
        {
            "category":"Retail",
            "subcategory":"Auto Repair",
            "type":"Services"
        }
    ],
    "sg:phone":"+1 201 460 4737",
    "sg:postcode":"07070",
    "sg:province":"NJ",
    "sg:tags":[
        "truck"
    ],
    "wof:name":"Blue & Gold Truck & Trailer",
    "wof:placetype":"venue"
},
  "geometry": {"coordinates":[-74.110466,40.830288],"type":"Point"}
}