{
  "type": "Feature",
  "properties": {
    "iso:country":"US",
    "sg:address":"207 St George Ave",
    "sg:city":"Roselle",
    "sg:classifiers":[
        {
            "category":"Home & Garden",
            "subcategory":"Garden Supply",
            "type":"Retail Goods"
        }
    ],
    "sg:phone":"+1 908 298 8808",
    "sg:postcode":"07203",
    "sg:province":"NJ",
    "sg:tags":[
        "nursery",
        "gardening"
    ],
    "wof:name":"Juzefyk's Tree Stand",
    "wof:placetype":"venue"
},
  "geometry": {"coordinates":[-74.261647,40.640371],"type":"Point"}
}