{
  "type": "Feature",
  "properties": {
    "addr:full":"107 Beech St Rutherford NJ 07070",
    "addr:housenumber":"107",
    "addr:postcode":"07070",
    "addr:street":"Beech St",
    "iso:country":"US",
    "sg:address":"107 Beech St",
    "sg:city":"Rutherford",
    "sg:classifiers":[
        {
            "category":"Professional",
            "subcategory":"Detective & Security Services",
            "type":"Services"
        }
    ],
    "sg:phone":"+1 201 939 0778",
    "sg:postcode":"07070",
    "sg:province":"NJ",
    "sg:tags":[
        "car"
    ],
    "wof:name":"Rod Leith Investigations",
    "wof:placetype":"venue"
},
  "geometry": {"coordinates":[-74.11392600000001,40.836939],"type":"Point"}
}