{
  "type": "Feature",
  "properties": {
    "addr:full":"540 Delsea Dr Malaga NJ 08328",
    "addr:housenumber":"540",
    "addr:postcode":"08328",
    "addr:street":"Delsea Dr",
    "iso:country":"US",
    "sg:address":"540 Delsea Dr",
    "sg:city":"Malaga",
    "sg:classifiers":[
        {
            "category":"Food & Beverages",
            "subcategory":"Liquor & Beverages",
            "type":"Retail Goods"
        }
    ],
    "sg:phone":"+1 856 694 3308",
    "sg:postcode":"08328",
    "sg:province":"NJ",
    "sg:tags":[
        "beer",
        "ale"
    ],
    "wof:name":"Wright's Liquor Store",
    "wof:placetype":"venue"
},
  "geometry": {"coordinates":[-75.050223,39.573384],"type":"Point"}
}