{
  "type": "Feature",
  "properties": {
    "iso:country":"US",
    "sg:address":"49 S Main St",
    "sg:city":"Mullica Hill",
    "sg:classifiers":[
        {
            "category":"Shopping",
            "subcategory":"Jewelry",
            "type":"Retail Goods"
        }
    ],
    "sg:phone":"+1 856 223 9449",
    "sg:postcode":"08062",
    "sg:province":"NJ",
    "sg:tags":[
        "jeweler"
    ],
    "wof:name":"Millica Hill Jewelry & Repair",
    "wof:placetype":"venue"
},
  "geometry": {"coordinates":[-75.224192,39.732089],"type":"Point"}
}