{
  "type": "Feature",
  "properties": {
    "addr:full":"597 Brass Castle Rd Oxford NJ 07863",
    "addr:housenumber":"597",
    "addr:postcode":"07863",
    "addr:street":"Brass Castle Rd",
    "iso:country":"US",
    "sg:address":"597 Brass Castle Rd",
    "sg:city":"Oxford",
    "sg:classifiers":[
        {
            "category":"Building & Trades",
            "subcategory":"Locksmith",
            "type":"Services"
        }
    ],
    "sg:phone":"+1 877 803 1110",
    "sg:postcode":"07863",
    "sg:province":"NJ",
    "sg:tags":[
        "key"
    ],
    "wof:name":"Emergency 24 Hour 7 Day Locksmith",
    "wof:placetype":"venue"
},
  "geometry": {"coordinates":[-75.047304,40.818214],"type":"Point"}
}