{
  "type": "Feature",
  "properties": {
    "iso:country":"US",
    "sg:address":"3221 New York Ave",
    "sg:city":"Union City",
    "sg:classifiers":[
        {
            "category":"Manufacturing",
            "subcategory":"Food",
            "type":"Manufacturing & Wholesale Goods"
        }
    ],
    "sg:phone":"+1 201 867 5915",
    "sg:postcode":"07087",
    "sg:province":"NJ",
    "sg:tags":[
        "mfg"
    ],
    "wof:name":"Nicomar Chile International In",
    "wof:placetype":"venue"
},
  "geometry": {"coordinates":[-74.028232,40.771431],"type":"Point"}
}