{
  "type": "Feature",
  "properties": {
    "iso:country":"US",
    "sg:address":"1512 Marion St",
    "sg:city":"Wall Township",
    "sg:classifiers":[
        {
            "category":"Organizations",
            "subcategory":"Professional Association",
            "type":"Services"
        }
    ],
    "sg:phone":"+1 732 280 3737",
    "sg:postcode":"07719",
    "sg:province":"NJ",
    "wof:name":"Argent Associates Inc",
    "wof:placetype":"venue"
},
  "geometry": {"coordinates":[-74.04814,40.178339],"type":"Point"}
}