{
  "type": "Feature",
  "properties": {
    "iso:country":"US",
    "sg:address":"103 W 2nd St",
    "sg:city":"Howell",
    "sg:classifiers":[
        {
            "category":"Building & Trades",
            "subcategory":"Construction",
            "type":"Services"
        }
    ],
    "sg:phone":"+1 732 370 2228",
    "sg:postcode":"07731",
    "sg:province":"NJ",
    "sg:tags":[
        "general",
        "contractor"
    ],
    "wof:name":"Marathon Construction",
    "wof:placetype":"venue"
},
  "geometry": {"coordinates":[-74.240409,40.172492],"type":"Point"}
}