{
  "type": "Feature",
  "properties": {
    "iso:country":"US",
    "sg:address":"15 Quincy Ln",
    "sg:city":"Bergenfield",
    "sg:classifiers":[
        {
            "category":"Professional",
            "subcategory":"Management & Consulting",
            "type":"Services"
        }
    ],
    "sg:phone":"+1 201 385 4444",
    "sg:postcode":"07621",
    "sg:province":"NJ",
    "wof:name":"Advanced Hlthcr Mgmt",
    "wof:placetype":"venue"
},
  "geometry": {"coordinates":[-74.005703,40.909866],"type":"Point"}
}