{
  "type": "Feature",
  "properties": {
    "addr:full":"7 S Park Ct Holmdel NJ 07733",
    "addr:housenumber":"7",
    "addr:postcode":"07733",
    "addr:street":"S Park Ct",
    "iso:country":"US",
    "sg:address":"7 S Park Ct",
    "sg:city":"Holmdel",
    "sg:classifiers":[
        {
            "category":"Insurance",
            "subcategory":"Insurance Agent",
            "type":"Services"
        }
    ],
    "sg:phone":"+1 732 817 1008",
    "sg:postcode":"07733",
    "sg:province":"NJ",
    "wof:name":"Vincent A Parisi",
    "wof:placetype":"venue"
},
  "geometry": {"coordinates":[-74.16376700000001,40.374289],"type":"Point"}
}