{
  "type": "Feature",
  "properties": {
    "addr:full":"6 Erie St Camden NJ 08102",
    "addr:housenumber":"6",
    "addr:postcode":"08102",
    "addr:street":"Erie St",
    "iso:country":"US",
    "sg:address":"6 Erie St",
    "sg:city":"Camden",
    "sg:classifiers":[
        {
            "category":"Health Services",
            "subcategory":"Doctor",
            "type":"Services"
        }
    ],
    "sg:phone":"+1 856 757 9180",
    "sg:postcode":"08102",
    "sg:province":"NJ",
    "sg:tags":[
        "physician",
        "pediatrics",
        "surgeons",
        "internal",
        "medicine",
        "surgeon"
    ],
    "wof:name":"Williams, Karen, Md - Camcare Health Corp",
    "wof:placetype":"venue"
},
  "geometry": {"coordinates":[-75.12594799999999,39.956344],"type":"Point"}
}