{
  "type": "Feature",
  "properties": {
    "iso:country":"US",
    "sg:address":"4 Mariners Cove",
    "sg:city":"Freehold",
    "sg:classifiers":[
        {
            "category":"Real Estate",
            "subcategory":"Real Estate Agent",
            "type":"Services"
        }
    ],
    "sg:phone":"+1   ",
    "sg:postcode":"07728",
    "sg:province":"NJ",
    "wof:name":"Pointe O Woods Town Homes",
    "wof:placetype":"venue"
},
  "geometry": {"coordinates":[-74.260633,40.20832],"type":"Point"}
}