{
  "type": "Feature",
  "properties": {
    "iso:country":"US",
    "sg:address":"999 Airport Rd",
    "sg:city":"Lakewood",
    "sg:classifiers":[
        {
            "category":"Health Services",
            "subcategory":"Hospital",
            "type":"Services"
        }
    ],
    "sg:phone":"+1 732 367 1710",
    "sg:postcode":"08701",
    "sg:province":"NJ",
    "sg:tags":[
        "mental"
    ],
    "sg:website":"www.preferredbehavioral.org",
    "wof:name":"Preferred Behavioral Health",
    "wof:placetype":"venue"
},
  "geometry": {"coordinates":[-74.17994299999999,40.058648],"type":"Point"}
}