{
  "type": "Feature",
  "properties": {
    "iso:country":"US",
    "sg:address":"70 Main St",
    "sg:city":"S Bound Brook",
    "sg:classifiers":[
        {
            "category":"Retail",
            "subcategory":"Self-service Laundry",
            "type":"Services"
        }
    ],
    "sg:phone":"+1 732 356 8426",
    "sg:postcode":"08880",
    "sg:province":"NJ",
    "wof:name":"Scrubboard Wash & Dry Inc",
    "wof:placetype":"venue"
},
  "geometry": {"coordinates":[-74.52591700000001,40.555322],"type":"Point"}
}