{
  "type": "Feature",
  "properties": {
    "addr:full":"811 Paulison Ave Clifton NJ 07011",
    "addr:housenumber":"811",
    "addr:postcode":"07011",
    "addr:street":"Paulison Ave",
    "iso:country":"US",
    "sg:address":"811 Paulison Ave",
    "sg:city":"Clifton",
    "sg:classifiers":[
        {
            "category":"Banks & Credit Unions",
            "subcategory":"Bank",
            "type":"Services"
        }
    ],
    "sg:phone":"+1 973 773 5492",
    "sg:postcode":"07011",
    "sg:province":"NJ",
    "wof:name":"Clifton New Jersey Postal Employees Federl Crdt Un",
    "wof:placetype":"venue"
},
  "geometry": {"coordinates":[-74.15100099999999,40.869499],"type":"Point"}
}