{
  "type": "Feature",
  "properties": {
    "iso:country":"US",
    "sg:address":"100 Northfield Ave",
    "sg:city":"West Orange",
    "sg:classifiers":[
        {
            "category":"Health Services",
            "subcategory":"Dentist",
            "type":"Services"
        }
    ],
    "sg:phone":"+1 973 731 4800",
    "sg:postcode":"07052",
    "sg:province":"NJ",
    "wof:name":"Baer Stanley M DMD",
    "wof:placetype":"venue"
},
  "geometry": {"coordinates":[-74.243599,40.7757],"type":"Point"}
}