{
  "type": "Feature",
  "properties": {
    "iso:country":"US",
    "sg:address":"4500 Cottage Pl",
    "sg:city":"Union City",
    "sg:classifiers":[
        {
            "category":"Professional",
            "subcategory":"Lawyer & Legal Services",
            "type":"Services"
        }
    ],
    "sg:phone":"+1 201 223 1803",
    "sg:postcode":"07087",
    "sg:province":"NJ",
    "wof:name":"Espinosa Thomas Attorney-At Law",
    "wof:placetype":"venue"
},
  "geometry": {"coordinates":[-74.024101,40.7798],"type":"Point"}
}