{
  "type": "Feature",
  "properties": {
    "iso:country":"US",
    "sg:address":"789 Broadway",
    "sg:city":"Bayonne",
    "sg:classifiers":[
        {
            "category":"Sports & Exercise",
            "subcategory":"Gym",
            "type":"Entertainment"
        }
    ],
    "sg:phone":"+1 201 339 0400",
    "sg:postcode":"07002",
    "sg:province":"NJ",
    "sg:website":"www.curves.com",
    "wof:name":"Curves For Women",
    "wof:placetype":"venue"
},
  "geometry": {"coordinates":[-74.109675,40.674124],"type":"Point"}
}