{
  "type": "Feature",
  "properties": {
    "addr:full":"311 Vine St Riverside NJ 08075",
    "addr:housenumber":"311",
    "addr:postcode":"08075",
    "addr:street":"Vine St",
    "iso:country":"US",
    "sg:address":"311 Vine St",
    "sg:city":"Riverside",
    "sg:classifiers":[
        {
            "category":"Professional",
            "subcategory":"Computer Services",
            "type":"Services"
        }
    ],
    "sg:phone":"+1 856 764 5817",
    "sg:postcode":"08075",
    "sg:province":"NJ",
    "sg:tags":[
        "programing",
        "custom"
    ],
    "wof:name":"Software Support Computer",
    "wof:placetype":"venue"
},
  "geometry": {"coordinates":[-74.958399,40.047451],"type":"Point"}
}