{
  "type": "Feature",
  "properties": {
    "addr:full":"70 E Ridgewood Ave Ridgewood NJ 07450",
    "addr:housenumber":"70",
    "addr:postcode":"07450",
    "addr:street":"E Ridgewood Ave",
    "iso:country":"US",
    "sg:address":"70 E Ridgewood Ave",
    "sg:city":"Ridgewood",
    "sg:classifiers":[
        {
            "category":"Education",
            "subcategory":"Special Training",
            "type":"Public Place"
        }
    ],
    "sg:phone":"+1   ",
    "sg:postcode":"07450",
    "sg:province":"NJ",
    "wof:name":"Score Learning Corporation",
    "wof:placetype":"venue"
},
  "geometry": {"coordinates":[-74.118484,40.979502],"type":"Point"}
}