{
  "type": "Feature",
  "properties": {
    "addr:full":"109 Dover Ave Egg Harbor Twp NJ 08234",
    "addr:housenumber":"109",
    "addr:postcode":"08234",
    "addr:street":"Dover Ave",
    "iso:country":"US",
    "sg:address":"109 Dover Ave",
    "sg:city":"Egg Harbor Twp",
    "sg:classifiers":[
        {
            "category":"Professional",
            "subcategory":"Business Services",
            "type":"Services"
        }
    ],
    "sg:phone":"+1 609 653 2210",
    "sg:postcode":"08234",
    "sg:province":"NJ",
    "sg:tags":[
        "transcribing",
        "disc"
    ],
    "wof:name":"Coastal Transcription",
    "wof:placetype":"venue"
},
  "geometry": {"coordinates":[-74.62602699999999,39.35933],"type":"Point"}
}