{
  "type": "Feature",
  "properties": {
    "addr:full":"20 Fairfield Pl West Caldwell NJ 07006",
    "addr:housenumber":"20",
    "addr:postcode":"07006",
    "addr:street":"Fairfield Pl",
    "iso:country":"US",
    "sg:address":"20 Fairfield Pl",
    "sg:city":"West Caldwell",
    "sg:classifiers":[
        {
            "category":"Wholesale",
            "subcategory":"Machinery & Supplies",
            "type":"Manufacturing & Wholesale Goods"
        }
    ],
    "sg:phone":"+1 973 227 8170",
    "sg:postcode":"07006",
    "sg:province":"NJ",
    "sg:tags":[
        "tool"
    ],
    "sg:website":"www.etwcorp.com",
    "wof:name":"Eastern Tool Warehouse Corp",
    "wof:placetype":"venue"
},
  "geometry": {"coordinates":[-74.287216,40.8636],"type":"Point"}
}