{
  "type": "Feature",
  "properties": {
    "addr:full":"622 Calderone Ct South Plainfield NJ 07080",
    "addr:housenumber":"622",
    "addr:postcode":"07080",
    "addr:street":"Calderone Ct",
    "iso:country":"US",
    "sg:address":"622 Calderone Ct",
    "sg:city":"South Plainfield",
    "sg:classifiers":[
        {
            "category":"Professional",
            "subcategory":"Computer Services",
            "type":"Services"
        }
    ],
    "sg:phone":"+1 908 732 7770",
    "sg:postcode":"07080",
    "sg:province":"NJ",
    "sg:tags":[
        "consultant",
        "designer"
    ],
    "wof:name":"Ray Tech Inc",
    "wof:placetype":"venue"
},
  "geometry": {"coordinates":[-74.425416,40.569915],"type":"Point"}
}