{
  "type": "Feature",
  "properties": {
    "iso:country":"US",
    "sg:address":"5824 Browning Rd",
    "sg:city":"Pennsauken",
    "sg:classifiers":[
        {
            "category":"Travel",
            "subcategory":"Travel Agent",
            "type":"Entertainment"
        }
    ],
    "sg:phone":"+1 856 488 4424",
    "sg:postcode":"08109",
    "sg:province":"NJ",
    "sg:tags":[
        "agency",
        "bureau"
    ],
    "sg:website":"http://www.allpointstravelnj.net",
    "wof:name":"All Points Travel",
    "wof:placetype":"venue"
},
  "geometry": {"coordinates":[-75.065856,39.940589],"type":"Point"}
}