{
  "type": "Feature",
  "properties": {
    "addr:full":"3113 Westfield Ave Camden NJ 08105",
    "addr:housenumber":"3113",
    "addr:postcode":"08105",
    "addr:street":"Westfield Ave",
    "iso:country":"US",
    "sg:address":"3113 Westfield Ave",
    "sg:city":"Camden",
    "sg:classifiers":[
        {
            "category":"Health Services",
            "subcategory":"Doctor",
            "type":"Services"
        }
    ],
    "sg:phone":"+1 856 963 0739",
    "sg:postcode":"08105",
    "sg:province":"NJ",
    "wof:name":"Peterzell Morris DO",
    "wof:placetype":"venue"
},
  "geometry": {"coordinates":[-75.0821,39.9491],"type":"Point"}
}