{
  "type": "Feature",
  "properties": {
    "addr:full":"333 Kings Hwy Swedesboro NJ 08085",
    "addr:housenumber":"333",
    "addr:postcode":"08085",
    "addr:street":"Kings Hwy",
    "iso:country":"US",
    "sg:address":"333 Kings Hwy",
    "sg:city":"Swedesboro",
    "sg:classifiers":[
        {
            "category":"Personal",
            "type":"Services"
        }
    ],
    "sg:phone":"+1 856 467 9907",
    "sg:postcode":"08085",
    "sg:province":"NJ",
    "wof:name":"Dragonworks",
    "wof:placetype":"venue"
},
  "geometry": {"coordinates":[-75.308689,39.749045],"type":"Point"}
}