{
  "type": "Feature",
  "properties": {
    "addr:full":"7 Lefferts Ct East Brunswick NJ 08816",
    "addr:housenumber":"7",
    "addr:postcode":"08816",
    "addr:street":"Lefferts Ct",
    "iso:country":"US",
    "sg:address":"7 Lefferts Ct",
    "sg:city":"East Brunswick",
    "sg:classifiers":[
        {
            "category":"Professional",
            "subcategory":"Management & Consulting",
            "type":"Services"
        }
    ],
    "sg:phone":"+1   ",
    "sg:postcode":"08816",
    "sg:province":"NJ",
    "wof:name":"Euthena LLC",
    "wof:placetype":"venue"
},
  "geometry": {"coordinates":[-74.43259999999999,40.409771],"type":"Point"}
}