{
  "type": "Feature",
  "properties": {
    "addr:full":"514 Main St Fort Lee NJ 07024",
    "addr:housenumber":"514",
    "addr:postcode":"07024",
    "addr:street":"Main St",
    "iso:country":"US",
    "sg:address":"514 Main St",
    "sg:city":"Fort Lee",
    "sg:classifiers":[
        {
            "category":"Personal",
            "subcategory":"Beauty Salon",
            "type":"Services"
        }
    ],
    "sg:phone":"+1 201 947 5370",
    "sg:postcode":"07024",
    "sg:province":"NJ",
    "wof:name":"Au Courant",
    "wof:placetype":"venue"
},
  "geometry": {"coordinates":[-73.979895,40.857297],"type":"Point"}
}