{
  "type": "Feature",
  "properties": {
    "addr:full":"12 W Broadway Paterson NJ 07505",
    "addr:housenumber":"12",
    "addr:postcode":"07505",
    "addr:street":"W Broadway",
    "iso:country":"US",
    "sg:address":"12 W Broadway",
    "sg:city":"Paterson",
    "sg:classifiers":[
        {
            "category":"Education",
            "subcategory":"Kindergarten",
            "type":"Public Place"
        }
    ],
    "sg:phone":"+1 973 977 9926",
    "sg:postcode":"07505",
    "sg:province":"NJ",
    "sg:tags":[
        "school",
        "driving"
    ],
    "sg:website":"www.masterdrivingschool.com",
    "wof:name":"Master Driving School Inc",
    "wof:placetype":"venue"
},
  "geometry": {"coordinates":[-74.172983,40.919243],"type":"Point"}
}