{
  "type": "Feature",
  "properties": {
    "addr:full":"1417 Stuyvesant Ave Union NJ 07083",
    "addr:housenumber":"1417",
    "addr:postcode":"07083",
    "addr:street":"Stuyvesant Ave",
    "iso:country":"US",
    "sg:address":"1417 Stuyvesant Ave",
    "sg:city":"Union",
    "sg:classifiers":[
        {
            "category":"Government",
            "subcategory":"Office",
            "type":"Public Place"
        }
    ],
    "sg:phone":"+1 908 687 1467",
    "sg:postcode":"07083",
    "sg:province":"NJ",
    "sg:tags":[
        "county"
    ],
    "wof:name":"Ed Weisman's Union County Tire",
    "wof:placetype":"venue"
},
  "geometry": {"coordinates":[-74.261515,40.70501],"type":"Point"}
}