{
  "type": "Feature",
  "properties": {
    "iso:country":"US",
    "sg:address":"76 US Hwy 9",
    "sg:city":"Barnegat",
    "sg:classifiers":[
        {
            "category":"Building & Trades",
            "subcategory":"Landscaping Services",
            "type":"Services"
        }
    ],
    "sg:phone":"+1 609 693 0444",
    "sg:postcode":"08005",
    "sg:province":"NJ",
    "sg:tags":[
        "landscape",
        "contractor"
    ],
    "wof:name":"Bay Tree Svc & Landscaping Inc",
    "wof:placetype":"venue"
},
  "geometry": {"coordinates":[-74.234382,39.736596],"type":"Point"}
}