{
  "type": "Feature",
  "properties": {
    "addr:full":"1040 Belmont Ave Haledon NJ 07508",
    "addr:housenumber":"1040",
    "addr:postcode":"07508",
    "addr:street":"Belmont Ave",
    "iso:country":"US",
    "sg:address":"1040 Belmont Ave",
    "sg:city":"Haledon",
    "sg:classifiers":[
        {
            "category":"Retail",
            "subcategory":"Auto Repair",
            "type":"Services"
        }
    ],
    "sg:phone":"+1   ",
    "sg:postcode":"07508",
    "sg:province":"NJ",
    "sg:tags":[
        "station",
        "gasoline",
        "general"
    ],
    "wof:name":"Walts Hilltop Garage Inc",
    "wof:placetype":"venue"
},
  "geometry": {"coordinates":[-74.190219,40.957238],"type":"Point"}
}