{
  "type": "Feature",
  "properties": {
    "iso:country":"US",
    "sg:address":"751 Hamilton St",
    "sg:city":"Somerset",
    "sg:classifiers":[
        {
            "category":"Home & Garden",
            "subcategory":"Building Materials",
            "type":"Retail Goods"
        },
        {
            "category":"Building & Trades",
            "subcategory":"Construction",
            "type":"Services"
        }
    ],
    "sg:phone":"+1 732 249 1223",
    "sg:postcode":"08873",
    "sg:province":"NJ",
    "sg:tags":[
        "glass",
        "window",
        "contractor",
        "plate"
    ],
    "wof:name":"Ben Franklin Glass Co Inc",
    "wof:placetype":"venue"
},
  "geometry": {"coordinates":[-74.47504600000001,40.490793],"type":"Point"}
}