{
  "type": "Feature",
  "properties": {
    "addr:full":"175 Ridge St Newark NJ 07104",
    "addr:housenumber":"175",
    "addr:postcode":"07104",
    "addr:street":"Ridge St",
    "iso:country":"US",
    "sg:address":"175 Ridge St",
    "sg:city":"Newark",
    "sg:classifiers":[
        {
            "category":"Manufacturing",
            "subcategory":"Metals",
            "type":"Manufacturing & Wholesale Goods"
        }
    ],
    "sg:phone":"+1 973 484 5900",
    "sg:postcode":"07104",
    "sg:province":"NJ",
    "sg:tags":[
        "ceramic",
        "coating"
    ],
    "wof:name":"Ceramco Inc Chemists",
    "wof:placetype":"venue"
},
  "geometry": {"coordinates":[-74.177092,40.757584],"type":"Point"}
}