{
  "type": "Feature",
  "properties": {
    "iso:country":"US",
    "sg:address":"358 Union Ave",
    "sg:city":"Paterson",
    "sg:classifiers":[
        {
            "category":"Shopping",
            "subcategory":"Jewelry",
            "type":"Retail Goods"
        }
    ],
    "sg:phone":"+1 973 942 1622",
    "sg:postcode":"07502",
    "sg:province":"NJ",
    "sg:tags":[
        "jeweler"
    ],
    "wof:name":"Jerry's Jewelry Store",
    "wof:placetype":"venue"
},
  "geometry": {"coordinates":[-74.18759900000001,40.91949],"type":"Point"}
}