{
  "type": "Feature",
  "properties": {
    "iso:country":"US",
    "sg:address":"228 Long Pond Rd",
    "sg:city":"Hewitt",
    "sg:classifiers":[
        {
            "category":"Wholesale",
            "subcategory":"Medical Equipment & Supplies",
            "type":"Manufacturing & Wholesale Goods"
        }
    ],
    "sg:phone":"+1 973 657 1301",
    "sg:postcode":"07421",
    "sg:province":"NJ",
    "sg:tags":[
        "microscope"
    ],
    "wof:name":"Optical Imaging",
    "wof:placetype":"venue"
},
  "geometry": {"coordinates":[-74.338705,41.152214],"type":"Point"}
}