{
  "type": "Feature",
  "properties": {
    "iso:country":"US",
    "sg:address":"167 Siloam Rd",
    "sg:city":"Freehold",
    "sg:classifiers":[
        {
            "category":"Organizations",
            "subcategory":"Religious Organization",
            "type":"Services"
        }
    ],
    "sg:phone":"+1 732 780 9199",
    "sg:postcode":"07728",
    "sg:province":"NJ",
    "sg:tags":[
        "church"
    ],
    "wof:name":"Siloam United Methodist Church",
    "wof:placetype":"venue"
},
  "geometry": {"coordinates":[-74.34745100000001,40.191687],"type":"Point"}
}