{
  "type": "Feature",
  "properties": {
    "iso:country":"US",
    "sg:address":"469 State Rte 79",
    "sg:city":"Morganville",
    "sg:classifiers":[
        {
            "category":"Autos & Motor Vehicles",
            "subcategory":"Fuel & Gas Station",
            "type":"Retail Goods"
        }
    ],
    "sg:phone":"+1 732 591 2533",
    "sg:postcode":"07751",
    "sg:province":"NJ",
    "sg:tags":[
        "oil"
    ],
    "wof:name":"Morganville Exxon",
    "wof:placetype":"venue"
},
  "geometry": {"coordinates":[-74.241669,40.38236],"type":"Point"}
}