{
  "type": "Feature",
  "properties": {
    "iso:country":"US",
    "sg:address":"26 Scottsdale Ct",
    "sg:city":"Cranbury",
    "sg:classifiers":[
        {
            "category":"Professional",
            "subcategory":"Lawyer & Legal Services",
            "type":"Services"
        }
    ],
    "sg:phone":"+1 609 395 0750",
    "sg:postcode":"08512",
    "sg:province":"NJ",
    "wof:name":"C Judson Hamlin Esq",
    "wof:placetype":"venue"
},
  "geometry": {"coordinates":[-74.530914,40.297391],"type":"Point"}
}