{
  "type": "Feature",
  "properties": {
    "addr:full":"195 E 16th St Paterson NJ 07524",
    "addr:housenumber":"195",
    "addr:postcode":"07524",
    "addr:street":"E 16Th St",
    "iso:country":"US",
    "sg:address":"195 E 16th St",
    "sg:city":"Paterson",
    "sg:classifiers":[
        {
            "category":"Personal",
            "subcategory":"Beauty Salon",
            "type":"Services"
        }
    ],
    "sg:phone":"+1 973 742 0889",
    "sg:postcode":"07524",
    "sg:province":"NJ",
    "sg:tags":[
        "shop"
    ],
    "wof:name":"Melanie Beauty",
    "wof:placetype":"venue"
},
  "geometry": {"coordinates":[-74.154314,40.929286],"type":"Point"}
}