{
  "type": "Feature",
  "properties": {
    "iso:country":"US",
    "sg:address":"5035 Church Rd",
    "sg:city":"Mt Laurel",
    "sg:classifiers":[
        {
            "category":"Professional",
            "subcategory":"Business Services",
            "type":"Services"
        }
    ],
    "sg:phone":"+1 856 727 7871",
    "sg:postcode":"08054",
    "sg:province":"NJ",
    "sg:tags":[
        "recording",
        "studio"
    ],
    "wof:name":"Nuvoman Recording Studio",
    "wof:placetype":"venue"
},
  "geometry": {"coordinates":[-74.88195,39.921097],"type":"Point"}
}