{
  "type": "Feature",
  "properties": {
    "iso:country":"US",
    "sg:address":"2 Marineview Plz",
    "sg:city":"Hoboken",
    "sg:classifiers":[
        {
            "category":"Professional",
            "subcategory":"Computer Services",
            "type":"Services"
        }
    ],
    "sg:phone":"+1 201 420 9570",
    "sg:postcode":"07047",
    "sg:province":"NJ",
    "sg:tags":[
        "hardware"
    ],
    "wof:name":"Chip Pc Inc",
    "wof:placetype":"venue"
},
  "geometry": {"coordinates":[-74.04725999999999,40.75832],"type":"Point"}
}