{
  "type": "Feature",
  "properties": {
    "iso:country":"US",
    "sg:address":"48 Franklin Ave",
    "sg:city":"Nutley",
    "sg:classifiers":[
        {
            "category":"Manufacturing",
            "subcategory":"Printing",
            "type":"Manufacturing & Wholesale Goods"
        }
    ],
    "sg:phone":"+1 973 667 2606",
    "sg:postcode":"07110",
    "sg:province":"NJ",
    "sg:tags":[
        "lithographic",
        "commercial"
    ],
    "wof:name":"Printing Techniques",
    "wof:placetype":"venue"
},
  "geometry": {"coordinates":[-74.165837,40.809594],"type":"Point"}
}