{
  "type": "Feature",
  "properties": {
    "addr:full":"200 Warren St Newark NJ 07103",
    "addr:housenumber":"200",
    "addr:postcode":"07103",
    "addr:street":"Warren St",
    "iso:country":"US",
    "sg:address":"200 Warren St",
    "sg:city":"Newark",
    "sg:classifiers":[
        {
            "category":"Education",
            "subcategory":"School",
            "type":"Public Place"
        }
    ],
    "sg:phone":"+1   ",
    "sg:postcode":"07103",
    "sg:province":"NJ",
    "wof:name":"Warren Street School",
    "wof:placetype":"venue"
},
  "geometry": {"coordinates":[-74.182326,40.742214],"type":"Point"}
}