{
  "type": "Feature",
  "properties": {
    "iso:country":"US",
    "sg:address":"4301 Bergenline Ave",
    "sg:city":"Union City",
    "sg:classifiers":[
        {
            "category":"Building & Trades",
            "subcategory":"Locksmith",
            "type":"Services"
        }
    ],
    "sg:phone":"+1 201 617 0330",
    "sg:postcode":"07087",
    "sg:province":"NJ",
    "sg:tags":[
        "key"
    ],
    "wof:name":"Emergency Locksmith",
    "wof:placetype":"venue"
},
  "geometry": {"coordinates":[-74.02469600000001,40.778198],"type":"Point"}
}