{
  "type": "Feature",
  "properties": {
    "iso:country":"US",
    "sg:address":"15 Sumner Ave",
    "sg:city":"Seaside Heights",
    "sg:classifiers":[
        {
            "category":"Real Estate",
            "subcategory":"Real Estate Agent",
            "type":"Services"
        }
    ],
    "sg:phone":"+1 732 830 0140",
    "sg:postcode":"08751",
    "sg:province":"NJ",
    "wof:name":"Rachel Manor Properties",
    "wof:placetype":"venue"
},
  "geometry": {"coordinates":[-74.071545,39.940968],"type":"Point"}
}