{
  "type": "Feature",
  "properties": {
    "iso:country":"US",
    "sg:address":"700 US Hwy 46",
    "sg:city":"Fairfield",
    "sg:classifiers":[
        {
            "category":"Banks & Credit Unions",
            "subcategory":"Financial Services",
            "type":"Services"
        }
    ],
    "sg:phone":"+1   ",
    "sg:postcode":"07004",
    "sg:province":"NJ",
    "sg:tags":[
        "company",
        "holding"
    ],
    "wof:name":"Glen Rock Holding Corp",
    "wof:placetype":"venue"
},
  "geometry": {"coordinates":[-74.26724400000001,40.892031],"type":"Point"}
}