{
  "type": "Feature",
  "properties": {
    "addr:full":"2 Tingley Ln Edison NJ 08820",
    "addr:housenumber":"2",
    "addr:postcode":"08820",
    "addr:street":"Tingley Ln",
    "iso:country":"US",
    "sg:address":"2 Tingley Ln",
    "sg:city":"Edison",
    "sg:classifiers":[
        {
            "category":"Real Estate",
            "subcategory":"Real Estate Agent",
            "type":"Services"
        }
    ],
    "sg:phone":"+1   ",
    "sg:postcode":"08820",
    "sg:province":"NJ",
    "wof:name":"Vijay Kale",
    "wof:placetype":"venue"
},
  "geometry": {"coordinates":[-74.375564,40.579698],"type":"Point"}
}