{
  "type": "Feature",
  "properties": {
    "addr:full":"101 Lansing Ave Trenton NJ 08619",
    "addr:housenumber":"101",
    "addr:postcode":"08619",
    "addr:street":"Lansing Ave",
    "iso:country":"US",
    "sg:address":"101 Lansing Ave",
    "sg:city":"Trenton",
    "sg:classifiers":[
        {
            "category":"Building & Trades",
            "subcategory":"Plumbing",
            "type":"Services"
        }
    ],
    "sg:phone":"+1 609 584 1345",
    "sg:postcode":"08619",
    "sg:province":"NJ",
    "sg:tags":[
        "product",
        "management",
        "energy",
        "system"
    ],
    "wof:name":"Foster Wheeler Energy Corp",
    "wof:placetype":"venue"
},
  "geometry": {"coordinates":[-74.6807,40.237593],"type":"Point"}
}