{
  "type": "Feature",
  "properties": {
    "iso:country":"US",
    "sg:address":"106 US Hwy 206",
    "sg:city":"Chester",
    "sg:classifiers":[
        {
            "category":"Retail",
            "subcategory":"Laundry & Dry Cleaning",
            "type":"Services"
        }
    ],
    "sg:phone":"+1 908 879 7575",
    "sg:postcode":"07930",
    "sg:province":"NJ",
    "sg:tags":[
        "cleaners",
        "plant",
        "drycleaning",
        "rug",
        "except"
    ],
    "wof:name":"My Heart Cleaners Inc",
    "wof:placetype":"venue"
},
  "geometry": {"coordinates":[-74.699568,40.785401],"type":"Point"}
}