{
  "type": "Feature",
  "properties": {
    "addr:full":"24 Commerce St Newark NJ 07102",
    "addr:housenumber":"24",
    "addr:postcode":"07102",
    "addr:street":"Commerce St",
    "iso:country":"US",
    "sg:address":"24 Commerce St",
    "sg:city":"Newark",
    "sg:classifiers":[
        {
            "category":"Professional",
            "subcategory":"Detective & Security Services",
            "type":"Services"
        }
    ],
    "sg:phone":"+1 973 242 4388",
    "sg:postcode":"07102",
    "sg:province":"NJ",
    "sg:tags":[
        "guard",
        "patrol"
    ],
    "wof:name":"Risk Management Group LTD",
    "wof:placetype":"venue"
},
  "geometry": {"coordinates":[-74.170901,40.737009],"type":"Point"}
}