{
  "type": "Feature",
  "properties": {
    "addr:full":"164 Main St Hackensack NJ 07601",
    "addr:housenumber":"164",
    "addr:postcode":"07601",
    "addr:street":"Main St",
    "iso:country":"US",
    "sg:address":"164 Main St",
    "sg:city":"Hackensack",
    "sg:classifiers":[
        {
            "category":"Restaurant",
            "type":"Food & Drink"
        },
        {
            "category":"Bars & Pubs",
            "subcategory":"Nightclub",
            "type":"Food & Drink"
        }
    ],
    "sg:phone":"+1 201 880 1080",
    "sg:postcode":"07601",
    "sg:province":"NJ",
    "sg:tags":[
        "middle",
        "nightlife",
        "eastern"
    ],
    "sg:website":"www.cafearabicanj.com/",
    "wof:name":"Cafe Arabica",
    "wof:placetype":"venue"
},
  "geometry": {"coordinates":[-74.045692,40.872515],"type":"Point"}
}