{
  "type": "Feature",
  "properties": {
    "addr:full":"42 Snake Den Rd Ringwood NJ 07456",
    "addr:housenumber":"42",
    "addr:postcode":"07456",
    "addr:street":"Snake Den Rd",
    "iso:country":"US",
    "sg:address":"42 Snake Den Rd",
    "sg:city":"Ringwood",
    "sg:classifiers":[
        {
            "category":"Building & Trades",
            "subcategory":"Construction",
            "type":"Services"
        }
    ],
    "sg:phone":"+1 973 728 4796",
    "sg:postcode":"07456",
    "sg:province":"NJ",
    "sg:tags":[
        "masonry",
        "contractor"
    ],
    "wof:name":"DHB Masonry",
    "wof:placetype":"venue"
},
  "geometry": {"coordinates":[-74.318254,41.071146],"type":"Point"}
}