{
  "type": "Feature",
  "properties": {
    "iso:country":"US",
    "sg:address":"83 High St",
    "sg:city":"Newton",
    "sg:classifiers":[
        {
            "category":"Retail",
            "subcategory":"Portrait Studio",
            "type":"Services"
        }
    ],
    "sg:phone":"+1 973 579 5575",
    "sg:postcode":"07869",
    "sg:province":"NJ",
    "sg:tags":[
        "photographer"
    ],
    "wof:name":"Annmarie Sciascia Photography",
    "wof:placetype":"venue"
},
  "geometry": {"coordinates":[-74.553555,40.865022],"type":"Point"}
}