{
  "type": "Feature",
  "properties": {
    "addr:full":"88 Gardenbrook Ln Willingboro NJ 08046",
    "addr:housenumber":"88",
    "addr:postcode":"08046",
    "addr:street":"Gardenbrook Ln",
    "iso:country":"US",
    "sg:address":"88 Gardenbrook Ln",
    "sg:city":"Willingboro",
    "sg:classifiers":[
        {
            "category":"Professional",
            "subcategory":"Engineering",
            "type":"Services"
        }
    ],
    "sg:phone":"+1   ",
    "sg:postcode":"08046",
    "sg:province":"NJ",
    "wof:name":"Pine Barrens Engineering",
    "wof:placetype":"venue"
},
  "geometry": {"coordinates":[-74.876587,40.022746],"type":"Point"}
}