{
  "type": "Feature",
  "properties": {
    "addr:full":"801 Shrewsbury Ave Shrewsbury NJ 07701",
    "addr:housenumber":"801",
    "addr:postcode":"07701",
    "addr:street":"Shrewsbury Ave",
    "iso:country":"US",
    "sg:address":"801 Shrewsbury Ave",
    "sg:city":"Shrewsbury",
    "sg:classifiers":[
        {
            "category":"Autos & Motor Vehicles",
            "subcategory":"Auto Supplies",
            "type":"Retail Goods"
        }
    ],
    "sg:phone":"+1 732 741 6501",
    "sg:postcode":"07701",
    "sg:province":"NJ",
    "sg:tags":[
        "tire"
    ],
    "wof:name":"STS Tire & Auto",
    "wof:placetype":"venue"
},
  "geometry": {"coordinates":[-74.072886,40.323205],"type":"Point"}
}