{
  "type": "Feature",
  "properties": {
    "iso:country":"US",
    "sg:address":"701 Frank E Rodgers Blvd N",
    "sg:city":"Harrison",
    "sg:classifiers":[
        {
            "category":"Restaurant",
            "type":"Food & Drink"
        }
    ],
    "sg:phone":"+1 973 482 1800",
    "sg:postcode":"07029",
    "sg:province":"NJ",
    "wof:name":"Vino's Pizzeria & Italian Restaurant",
    "wof:placetype":"venue"
},
  "geometry": {"coordinates":[-74.157166,40.751432],"type":"Point"}
}