{
  "type": "Feature",
  "properties": {
    "iso:country":"US",
    "sg:address":"94 Walnut St",
    "sg:city":"Montclair",
    "sg:classifiers":[
        {
            "category":"Shopping",
            "subcategory":"Shoes",
            "type":"Retail Goods"
        }
    ],
    "sg:phone":"+1 973 744 6655",
    "sg:postcode":"07042",
    "sg:province":"NJ",
    "sg:tags":[
        "store"
    ],
    "sg:website":"www.toryjanes.com",
    "wof:name":"Tory Jane's",
    "wof:placetype":"venue"
},
  "geometry": {"coordinates":[-74.21082,40.817182],"type":"Point"}
}