{
  "type": "Feature",
  "properties": {
    "addr:full":"7111 Maple Ave Pennsauken NJ 08109",
    "addr:housenumber":"7111",
    "addr:postcode":"08109",
    "addr:street":"Maple Ave",
    "iso:country":"US",
    "sg:address":"7111 Maple Ave",
    "sg:city":"Pennsauken",
    "sg:classifiers":[
        {
            "category":"Bars & Pubs",
            "type":"Food & Drink"
        },
        {
            "category":"Personal",
            "type":"Services"
        },
        {
            "category":"Sports & Exercise",
            "subcategory":"Bowling",
            "type":"Entertainment"
        }
    ],
    "sg:phone":"+1 856 665 3377",
    "sg:postcode":"08109",
    "sg:province":"NJ",
    "sg:tags":[
        "party",
        "planning",
        "event"
    ],
    "sg:website":"www.pinsetterbowl.com",
    "wof:name":"Pinsetter Bar & Bowl",
    "wof:placetype":"venue"
},
  "geometry": {"coordinates":[-75.035447,39.951865],"type":"Point"}
}