{
  "type": "Feature",
  "properties": {
    "iso:country":"US",
    "sg:address":"234 McLean Pl",
    "sg:city":"Paterson",
    "sg:classifiers":[
        {
            "category":"Health Services",
            "subcategory":"Chiropractor",
            "type":"Services"
        }
    ],
    "sg:phone":"+1 973 523 5252",
    "sg:postcode":"07205",
    "sg:province":"NJ",
    "sg:website":"www.eastchiropractic.com",
    "wof:name":"East Chiropractic",
    "wof:placetype":"venue"
},
  "geometry": {"coordinates":[-74.134255,40.909064],"type":"Point"}
}