{
  "type": "Feature",
  "properties": {
    "iso:country":"US",
    "sg:address":"1079 Amboy Ave",
    "sg:city":"Edison",
    "sg:classifiers":[
        {
            "category":"Social Services",
            "type":"Services"
        }
    ],
    "sg:phone":"+1   ",
    "sg:postcode":"08837",
    "sg:province":"NJ",
    "sg:tags":[
        "aid",
        "first"
    ],
    "wof:name":"Clara Barton First Aid Squad",
    "wof:placetype":"venue"
},
  "geometry": {"coordinates":[-74.341137,40.535604],"type":"Point"}
}