{
  "type": "Feature",
  "properties": {
    "iso:country":"US",
    "sg:address":"1240 Main Ave",
    "sg:city":"Clifton",
    "sg:classifiers":[
        {
            "category":"Professional",
            "subcategory":"Testing Lab",
            "type":"Services"
        }
    ],
    "sg:phone":"+1   ",
    "sg:postcode":"07011",
    "sg:province":"NJ",
    "sg:tags":[
        "laboratory",
        "electronic",
        "for",
        "devices"
    ],
    "wof:name":"New Jrsey McRo-Electronic Tstg",
    "wof:placetype":"venue"
},
  "geometry": {"coordinates":[-74.141435,40.877169],"type":"Point"}
}