{
  "type": "Feature",
  "properties": {
    "addr:full":"107 Maine St Toms River NJ 08753",
    "addr:housenumber":"107",
    "addr:postcode":"08753",
    "addr:street":"Maine St",
    "iso:country":"US",
    "sg:address":"107 Maine St",
    "sg:city":"Toms River",
    "sg:classifiers":[
        {
            "category":"Wholesale",
            "subcategory":"Jewelry",
            "type":"Manufacturing & Wholesale Goods"
        }
    ],
    "sg:phone":"+1 732 814 4993",
    "sg:postcode":"08753",
    "sg:province":"NJ",
    "sg:tags":[
        "stone"
    ],
    "wof:name":"Designs By Amy",
    "wof:placetype":"venue"
},
  "geometry": {"coordinates":[-74.13632,40.011193],"type":"Point"}
}