{
  "type": "Feature",
  "properties": {
    "addr:full":"84 Liberty Corner Rd Warren NJ 07059",
    "addr:housenumber":"84",
    "addr:postcode":"07059",
    "addr:street":"Liberty Corner Rd",
    "iso:country":"US",
    "sg:address":"84 Liberty Corner Rd",
    "sg:city":"Warren",
    "sg:classifiers":[
        {
            "category":"Building & Trades",
            "subcategory":"Construction",
            "type":"Services"
        }
    ],
    "sg:phone":"+1 908 604 6512",
    "sg:postcode":"07059",
    "sg:province":"NJ",
    "sg:tags":[
        "house"
    ],
    "wof:name":"Warren Builders LLC",
    "wof:placetype":"venue"
},
  "geometry": {"coordinates":[-74.566495,40.623372],"type":"Point"}
}