{
  "type": "Feature",
  "properties": {
    "iso:country":"US",
    "sg:address":"9 Carpenters Pl",
    "sg:city":"Sparta",
    "sg:classifiers":[
        {
            "category":"Museum",
            "type":"Entertainment"
        }
    ],
    "sg:phone":"+1   ",
    "sg:postcode":"07871",
    "sg:province":"NJ",
    "sg:tags":[
        "gallery"
    ],
    "wof:name":"Decore LLC",
    "wof:placetype":"venue"
},
  "geometry": {"coordinates":[-74.67109499999999,41.05565],"type":"Point"}
}