{
  "type": "Feature",
  "properties": {
    "iso:country":"US",
    "sg:address":"81 N Beverwyck Rd",
    "sg:city":"Lake Hiawatha",
    "sg:classifiers":[
        {
            "category":"Restaurant",
            "type":"Food & Drink"
        }
    ],
    "sg:phone":"+1   ",
    "sg:postcode":"07034",
    "sg:province":"NJ",
    "sg:tags":[
        "eating"
    ],
    "wof:name":"Lucky Kitchen",
    "wof:placetype":"venue"
},
  "geometry": {"coordinates":[-74.382291,40.882841],"type":"Point"}
}