{
  "type": "Feature",
  "properties": {
    "addr:full":"4 Lincoln Pl Madison NJ 07940",
    "addr:housenumber":"4",
    "addr:postcode":"07940",
    "addr:street":"Lincoln Pl",
    "iso:country":"US",
    "sg:address":"4 Lincoln Pl",
    "sg:city":"Madison",
    "sg:classifiers":[
        {
            "category":"Social Services",
            "subcategory":"Job Training",
            "type":"Services"
        }
    ],
    "sg:phone":"+1 973 236 9200",
    "sg:postcode":"07940",
    "sg:province":"NJ",
    "sg:tags":[
        "career",
        "counseling",
        "vocational"
    ],
    "wof:name":"Management Career Solutions",
    "wof:placetype":"venue"
},
  "geometry": {"coordinates":[-74.414117,40.756541],"type":"Point"}
}