{
  "type": "Feature",
  "properties": {
    "addr:full":"17 State Rte 23 Hamburg NJ 07419",
    "addr:housenumber":"17",
    "addr:postcode":"07419",
    "addr:street":"State Rte 23",
    "iso:country":"US",
    "sg:address":"17 State Rte 23",
    "sg:city":"Hamburg",
    "sg:classifiers":[
        {
            "category":"Professional",
            "subcategory":"Business Services",
            "type":"Services"
        }
    ],
    "sg:phone":"+1 973 827 7600",
    "sg:postcode":"07419",
    "sg:province":"NJ",
    "sg:tags":[
        "attorney"
    ],
    "wof:name":"Leonard & Honig Esqs",
    "wof:placetype":"venue"
},
  "geometry": {"coordinates":[-74.574483,41.149493],"type":"Point"}
}