{
  "type": "Feature",
  "properties": {
    "iso:country":"US",
    "sg:address":"143 Red Oak Way",
    "sg:city":"Belle Mead",
    "sg:classifiers":[
        {
            "category":"Health Services",
            "subcategory":"Doctor",
            "type":"Services"
        }
    ],
    "sg:phone":"+1 908 281 7858",
    "sg:postcode":"08502",
    "sg:province":"NJ",
    "wof:name":"Richard A Mann",
    "wof:placetype":"venue"
},
  "geometry": {"coordinates":[-74.640497,40.454418],"type":"Point"}
}