{
  "type": "Feature",
  "properties": {
    "iso:country":"US",
    "sg:address":"10 E Broad St",
    "sg:city":"Burlington",
    "sg:classifiers":[
        {
            "category":"Organizations",
            "subcategory":"Non-profit Organization",
            "type":"Services"
        }
    ],
    "sg:phone":"+1 609 239 1020",
    "sg:postcode":"08016",
    "sg:province":"NJ",
    "sg:tags":[
        "service/non-profit",
        "community"
    ],
    "wof:name":"Main Street Burlington Nj",
    "wof:placetype":"venue"
},
  "geometry": {"coordinates":[-74.857831,40.077582],"type":"Point"}
}