{
  "type": "Feature",
  "properties": {
    "iso:country":"US",
    "sg:address":"308 Hoym St",
    "sg:city":"Fort Lee",
    "sg:classifiers":[
        {
            "category":"Professional",
            "subcategory":"Business Services",
            "type":"Services"
        }
    ],
    "sg:phone":"+1   ",
    "sg:postcode":"07024",
    "sg:province":"NJ",
    "wof:name":"Adana Group LLC",
    "wof:placetype":"venue"
},
  "geometry": {"coordinates":[-73.97388599999999,40.851367],"type":"Point"}
}