{
  "type": "Feature",
  "properties": {
    "iso:country":"US",
    "sg:address":"19 Washington Ave",
    "sg:city":"Chatham",
    "sg:classifiers":[
        {
            "category":"Health Services",
            "subcategory":"Clinic",
            "type":"Services"
        }
    ],
    "sg:phone":"+1 973 635 8875",
    "sg:postcode":"07928",
    "sg:province":"NJ",
    "sg:tags":[
        "counseling",
        "mental"
    ],
    "wof:name":"Browning Cindy J Msw Cadc",
    "wof:placetype":"venue"
},
  "geometry": {"coordinates":[-74.387604,40.741001],"type":"Point"}
}