{
  "type": "Feature",
  "properties": {
    "addr:full":"4 Furnace Rd Chester NJ 07930",
    "addr:housenumber":"4",
    "addr:postcode":"07930",
    "addr:street":"Furnace Rd",
    "iso:country":"US",
    "sg:address":"4 Furnace Rd",
    "sg:city":"Chester",
    "sg:classifiers":[
        {
            "category":"Home & Garden",
            "subcategory":"Building Materials",
            "type":"Retail Goods"
        }
    ],
    "sg:phone":"+1   ",
    "sg:postcode":"07930",
    "sg:province":"NJ",
    "wof:name":"Fair Weather Enteprises Inc",
    "wof:placetype":"venue"
},
  "geometry": {"coordinates":[-74.699029,40.796096],"type":"Point"}
}