{
  "type": "Feature",
  "properties": {
    "iso:country":"US",
    "sg:address":"1601 Tilton Rd",
    "sg:city":"Northfield",
    "sg:classifiers":[
        {
            "category":"Professional",
            "subcategory":"Lawyer & Legal Services",
            "type":"Services"
        }
    ],
    "sg:phone":"+1 609 272 6674",
    "sg:postcode":"08225",
    "sg:province":"NJ",
    "sg:tags":[
        "attorney"
    ],
    "wof:name":"Levine Staller Sklar Chan",
    "wof:placetype":"venue"
},
  "geometry": {"coordinates":[-74.55274799999999,39.36931],"type":"Point"}
}