{
  "type": "Feature",
  "properties": {
    "addr:full":"2468 Brookhaven Dr Vineland NJ 08361",
    "addr:housenumber":"2468",
    "addr:postcode":"08361",
    "addr:street":"Brookhaven Dr",
    "iso:country":"US",
    "sg:address":"2468 Brookhaven Dr",
    "sg:city":"Vineland",
    "sg:classifiers":[
        {
            "category":"Professional",
            "subcategory":"Advertising",
            "type":"Services"
        }
    ],
    "sg:phone":"+1   ",
    "sg:postcode":"08361",
    "sg:province":"NJ",
    "wof:name":"Mias Signs",
    "wof:placetype":"venue"
},
  "geometry": {"coordinates":[-74.957419,39.4471],"type":"Point"}
}