{
  "type": "Feature",
  "properties": {
    "iso:country":"US",
    "sg:address":"1410 State Rte 57",
    "sg:city":"Port Murray",
    "sg:classifiers":[
        {
            "category":"Wholesale",
            "subcategory":"Non-durable Goods",
            "type":"Manufacturing & Wholesale Goods"
        }
    ],
    "sg:phone":"+1 908 850 3078",
    "sg:postcode":"07865",
    "sg:province":"NJ",
    "wof:name":"Marketing By Design",
    "wof:placetype":"venue"
},
  "geometry": {"coordinates":[-74.86456800000001,40.803187],"type":"Point"}
}