{
  "type": "Feature",
  "properties": {
    "addr:full":"85 Bond St Bridgewater NJ 08807",
    "addr:housenumber":"85",
    "addr:postcode":"08807",
    "addr:street":"Bond St",
    "iso:country":"US",
    "sg:address":"85 Bond St",
    "sg:city":"Bridgewater",
    "sg:classifiers":[
        {
            "category":"Professional",
            "subcategory":"Advertising",
            "type":"Services"
        }
    ],
    "sg:phone":"+1 908 429 9400",
    "sg:postcode":"08807",
    "sg:province":"NJ",
    "sg:tags":[
        "agency"
    ],
    "wof:name":"Kmg Assoc Inc",
    "wof:placetype":"venue"
},
  "geometry": {"coordinates":[-74.629912,40.581983],"type":"Point"}
}