{
  "type": "Feature",
  "properties": {
    "addr:full":"624 White Horse Pike Somerdale NJ 08083",
    "addr:housenumber":"624",
    "addr:postcode":"08083",
    "addr:street":"White Horse Pike",
    "iso:country":"US",
    "sg:address":"624 White Horse Pike",
    "sg:city":"Somerdale",
    "sg:classifiers":[
        {
            "category":"Shopping",
            "subcategory":"Bicycles & Sporting Goods",
            "type":"Retail Goods"
        }
    ],
    "sg:phone":"+1 856 566 9477",
    "sg:postcode":"08083",
    "sg:province":"NJ",
    "sg:tags":[
        "skating",
        "equipment",
        "supply"
    ],
    "wof:name":"Powerplay",
    "wof:placetype":"venue"
},
  "geometry": {"coordinates":[-75.02287099999999,39.849714],"type":"Point"}
}