{
  "type": "Feature",
  "properties": {
    "addr:full":"520 State Rte 70 Brick NJ 08723",
    "addr:housenumber":"520",
    "addr:postcode":"08723",
    "addr:street":"State Rte 70",
    "iso:country":"US",
    "sg:address":"520 State Rte 70",
    "sg:city":"Brick",
    "sg:classifiers":[
        {
            "category":"Building & Trades",
            "subcategory":"Construction",
            "type":"Services"
        }
    ],
    "sg:phone":"+1 732 920 8600",
    "sg:postcode":"08723",
    "sg:province":"NJ",
    "sg:tags":[
        "company"
    ],
    "wof:name":"Jayeff Construction",
    "wof:placetype":"venue"
},
  "geometry": {"coordinates":[-74.14978000000001,40.057331],"type":"Point"}
}