{
  "type": "Feature",
  "properties": {
    "addr:full":"53 Vervalen St Closter NJ 07624",
    "addr:housenumber":"53",
    "addr:postcode":"07624",
    "addr:street":"Vervalen St",
    "iso:country":"US",
    "sg:address":"53 Vervalen St",
    "sg:city":"Closter",
    "sg:classifiers":[
        {
            "category":"Shopping",
            "subcategory":"Department Store",
            "type":"Retail Goods"
        }
    ],
    "sg:phone":"+1 201 768 5431",
    "sg:postcode":"07624",
    "sg:province":"NJ",
    "wof:name":"Kmart",
    "wof:placetype":"venue"
},
  "geometry": {"coordinates":[-73.95926,40.970945],"type":"Point"}
}