{
  "type": "Feature",
  "properties": {
    "addr:full":"119 Pavonia Ave Jersey City NJ 07310",
    "addr:housenumber":"119",
    "addr:postcode":"07310",
    "addr:street":"Pavonia Ave",
    "iso:country":"US",
    "sg:address":"119 Pavonia Ave",
    "sg:city":"Jersey City",
    "sg:classifiers":[
        {
            "category":"Retail",
            "subcategory":"Laundry & Dry Cleaning",
            "type":"Services"
        }
    ],
    "sg:phone":"+1 201 626 3333",
    "sg:postcode":"07310",
    "sg:province":"NJ",
    "sg:tags":[
        "drycleaning",
        "plant"
    ],
    "wof:name":"Newport Dry Cleaners",
    "wof:placetype":"venue"
},
  "geometry": {"coordinates":[-74.033677,40.72648],"type":"Point"}
}