{
  "type": "Feature",
  "properties": {
    "addr:full":"185 Smith St Perth Amboy NJ 08861",
    "addr:housenumber":"185",
    "addr:postcode":"08861",
    "addr:street":"Smith St",
    "iso:country":"US",
    "sg:address":"185 Smith St",
    "sg:city":"Perth Amboy",
    "sg:classifiers":[
        {
            "category":"Shopping",
            "subcategory":"Clothing, Apparel, & Fashions",
            "type":"Retail Goods"
        }
    ],
    "sg:phone":"+1   ",
    "sg:postcode":"08861",
    "sg:province":"NJ",
    "sg:tags":[
        "menswear"
    ],
    "wof:name":"Duli II",
    "wof:placetype":"venue"
},
  "geometry": {"coordinates":[-74.270516,40.509167],"type":"Point"}
}