{
  "type": "Feature",
  "properties": {
    "addr:full":"872 Savitt Pl Union NJ 07083",
    "addr:housenumber":"872",
    "addr:postcode":"07083",
    "addr:street":"Savitt Pl",
    "iso:country":"US",
    "sg:address":"872 Savitt Pl",
    "sg:city":"Union",
    "sg:classifiers":[
        {
            "category":"Freight",
            "type":"Transportation"
        }
    ],
    "sg:phone":"+1 908 964 1216",
    "sg:postcode":"07083",
    "sg:province":"NJ",
    "sg:tags":[
        "operator",
        "mover",
        "local",
        "trucking"
    ],
    "wof:name":"Schaefer Moving",
    "wof:placetype":"venue"
},
  "geometry": {"coordinates":[-74.28360000000001,40.696201],"type":"Point"}
}