{
  "type": "Feature",
  "properties": {
    "iso:country":"US",
    "sg:address":"112 Worth St",
    "sg:city":"Toms River",
    "sg:classifiers":[
        {
            "category":"Autos & Motor Vehicles",
            "subcategory":"Auto Supplies",
            "type":"Retail Goods"
        }
    ],
    "sg:phone":"+1 732 736 0046",
    "sg:postcode":"08757",
    "sg:province":"NJ",
    "sg:tags":[
        "tire"
    ],
    "wof:name":"All Time Tire",
    "wof:placetype":"venue"
},
  "geometry": {"coordinates":[-74.204649,39.944434],"type":"Point"}
}