{
  "type": "Feature",
  "properties": {
    "addr:full":"45 Godwin Ave Midland Park NJ 07432",
    "addr:housenumber":"45",
    "addr:postcode":"07432",
    "addr:street":"Godwin Ave",
    "iso:country":"US",
    "sg:address":"45 Godwin Ave",
    "sg:city":"Midland Park",
    "sg:classifiers":[
        {
            "category":"Recreation",
            "type":"Entertainment"
        }
    ],
    "sg:phone":"+1 201 670 4080",
    "sg:postcode":"07432",
    "sg:province":"NJ",
    "sg:tags":[
        "karate",
        "judo",
        "instr"
    ],
    "wof:name":"Kim's Martial Arts & Fitness",
    "wof:placetype":"venue"
},
  "geometry": {"coordinates":[-74.136258,40.983594],"type":"Point"}
}