{
  "type": "Feature",
  "properties": {
    "addr:full":"69 Sussex St Jersey City NJ 07302",
    "addr:housenumber":"69",
    "addr:postcode":"07302",
    "addr:street":"Sussex St",
    "iso:country":"US",
    "sg:address":"69 Sussex St",
    "sg:city":"Jersey City",
    "sg:classifiers":[
        {
            "category":"Professional",
            "subcategory":"Management & Consulting",
            "type":"Services"
        }
    ],
    "sg:phone":"+1   ",
    "sg:postcode":"07302",
    "sg:province":"NJ",
    "sg:tags":[
        "business"
    ],
    "wof:name":"Partnrships For Crative Action",
    "wof:placetype":"venue"
},
  "geometry": {"coordinates":[-74.037519,40.714494],"type":"Point"}
}