{
  "type": "Feature",
  "properties": {
    "iso:country":"US",
    "sg:address":"55 Stalter Dr",
    "sg:city":"Wayne",
    "sg:classifiers":[
        {
            "category":"Personal",
            "type":"Services"
        }
    ],
    "sg:phone":"+1 973 633 0874",
    "sg:postcode":"07470",
    "sg:province":"NJ",
    "sg:tags":[
        "party",
        "planning",
        "event"
    ],
    "sg:website":"www.favorsbydorinda.com",
    "wof:name":"Favors by Dorinda",
    "wof:placetype":"venue"
},
  "geometry": {"coordinates":[-74.256371,40.951565],"type":"Point"}
}