{
  "type": "Feature",
  "properties": {
    "iso:country":"US",
    "sg:address":"939 Lyndale Ave",
    "sg:city":"Trenton",
    "sg:classifiers":[
        {
            "category":"Wholesale",
            "subcategory":"Machinery & Supplies",
            "type":"Manufacturing & Wholesale Goods"
        }
    ],
    "sg:phone":"+1 609 392 1700",
    "sg:postcode":"08629",
    "sg:province":"NJ",
    "sg:tags":[
        "industrial",
        "tool",
        "hydraulic",
        "packaging",
        "equipment",
        "mfr",
        "tape",
        "rep"
    ],
    "wof:name":"Brejo Corporation",
    "wof:placetype":"venue"
},
  "geometry": {"coordinates":[-74.734967,40.216313],"type":"Point"}
}