{
  "type": "Feature",
  "properties": {
    "iso:country":"US",
    "sg:address":"32 S Willow St",
    "sg:city":"Montclair",
    "sg:classifiers":[
        {
            "category":"Social Services",
            "subcategory":"Adult Care",
            "type":"Services"
        },
        {
            "category":"Social Services",
            "type":"Services"
        }
    ],
    "sg:phone":"+1 973 655 0700",
    "sg:postcode":"07042",
    "sg:province":"NJ",
    "sg:tags":[
        "organization",
        "residential",
        "welfare"
    ],
    "wof:name":"Amethyst House LLC",
    "wof:placetype":"venue"
},
  "geometry": {"coordinates":[-74.21555600000001,40.812189],"type":"Point"}
}