{
  "type": "Feature",
  "properties": {
    "iso:country":"US",
    "sg:address":"2555 Brunswick Ave",
    "sg:city":"Linden",
    "sg:classifiers":[
        {
            "category":"Wholesale",
            "subcategory":"Furniture",
            "type":"Manufacturing & Wholesale Goods"
        }
    ],
    "sg:phone":"+1 908 523 0300",
    "sg:postcode":"07036",
    "sg:province":"NJ",
    "wof:name":"Darian Furniture Inc",
    "wof:placetype":"venue"
},
  "geometry": {"coordinates":[-74.21602300000001,40.639804],"type":"Point"}
}