{
  "type": "Feature",
  "properties": {
    "addr:full":"85 Raritan Ave Highland Park NJ 08904",
    "addr:housenumber":"85",
    "addr:postcode":"08904",
    "addr:street":"Raritan Ave",
    "iso:country":"US",
    "sg:address":"85 Raritan Ave",
    "sg:city":"Highland Park",
    "sg:classifiers":[
        {
            "category":"Organizations",
            "subcategory":"Membership Organization",
            "type":"Services"
        }
    ],
    "sg:phone":"+1 732 214 8385",
    "sg:postcode":"08904",
    "sg:province":"NJ",
    "wof:name":"Citizens Policy/Education Fund",
    "wof:placetype":"venue"
},
  "geometry": {"coordinates":[-74.433088,40.498145],"type":"Point"}
}