{
  "type": "Feature",
  "properties": {
    "iso:country":"US",
    "sg:address":"2 Oak Way",
    "sg:city":"Berkeley Heights",
    "sg:classifiers":[
        {
            "category":"Manufacturing",
            "subcategory":"Printing",
            "type":"Manufacturing & Wholesale Goods"
        }
    ],
    "sg:phone":"+1 908 286 0534",
    "sg:postcode":"07922",
    "sg:province":"NJ",
    "sg:tags":[
        "multimedia"
    ],
    "wof:name":"Yellow Pages Integrated Media",
    "wof:placetype":"venue"
},
  "geometry": {"coordinates":[-74.40894299999999,40.666181],"type":"Point"}
}