{
  "type": "Feature",
  "properties": {
    "iso:country":"US",
    "sg:address":"1019 Cedar Bridge Ave",
    "sg:city":"Brick",
    "sg:classifiers":[
        {
            "category":"Personal",
            "subcategory":"Beauty Salon",
            "type":"Services"
        }
    ],
    "sg:phone":"+1 732 451 0333",
    "sg:postcode":"08723",
    "sg:province":"NJ",
    "sg:tags":[
        "shop"
    ],
    "wof:name":"Lovely Nails",
    "wof:placetype":"venue"
},
  "geometry": {"coordinates":[-74.138257,40.053802],"type":"Point"}
}