{
  "type": "Feature",
  "properties": {
    "iso:country":"US",
    "sg:address":"182 Main St",
    "sg:city":"Metuchen",
    "sg:classifiers":[
        {
            "category":"Shopping",
            "subcategory":"Florist",
            "type":"Retail Goods"
        }
    ],
    "sg:phone":"+1 732 548 2601",
    "sg:postcode":"08840",
    "sg:province":"NJ",
    "wof:name":"Creative Crafts Balloons",
    "wof:placetype":"venue"
},
  "geometry": {"coordinates":[-74.359094,40.533291],"type":"Point"}
}