{
  "type": "Feature",
  "properties": {
    "iso:country":"US",
    "sg:address":"281 State Rte 79",
    "sg:city":"Morganville",
    "sg:classifiers":[
        {
            "category":"Shopping",
            "type":"Retail Goods"
        },
        {
            "category":"Health Services",
            "subcategory":"Doctor",
            "type":"Services"
        }
    ],
    "sg:phone":"+1 732 591 8010",
    "sg:postcode":"07751",
    "sg:province":"NJ",
    "sg:tags":[
        "dentist",
        "merchandise"
    ],
    "wof:name":"Discount Dental NJ",
    "wof:placetype":"venue"
},
  "geometry": {"coordinates":[-74.249211,40.357504],"type":"Point"}
}