{
  "type": "Feature",
  "properties": {
    "addr:full":"3151 River Rd Camden NJ 08105",
    "addr:housenumber":"3151",
    "addr:postcode":"08105",
    "addr:street":"River Rd",
    "iso:country":"US",
    "sg:address":"3151 River Rd",
    "sg:city":"Camden",
    "sg:classifiers":[
        {
            "category":"Health Services",
            "subcategory":"Hospital",
            "type":"Services"
        }
    ],
    "sg:phone":"+1 856 757 9500",
    "sg:postcode":"08105",
    "sg:province":"NJ",
    "wof:name":"Our Lady of Lourdes Medical Center",
    "wof:placetype":"venue"
},
  "geometry": {"coordinates":[-75.087082,39.959621],"type":"Point"}
}