{
  "type": "Feature",
  "properties": {
    "iso:country":"US",
    "sg:address":"1101 Bergen St",
    "sg:city":"Newark",
    "sg:classifiers":[
        {
            "category":"Restaurant",
            "type":"Food & Drink"
        }
    ],
    "sg:phone":"+1   ",
    "sg:postcode":"07112",
    "sg:province":"NJ",
    "sg:tags":[
        "eating"
    ],
    "wof:name":"Eat To Live",
    "wof:placetype":"venue"
},
  "geometry": {"coordinates":[-74.20991600000001,40.70626],"type":"Point"}
}