{
  "type": "Feature",
  "properties": {
    "iso:country":"US",
    "sg:address":"16 7th Ave",
    "sg:city":"Atlantic Hghlnds",
    "sg:classifiers":[
        {
            "category":"Shopping",
            "type":"Retail Goods"
        }
    ],
    "sg:phone":"+1 732 547 5198",
    "sg:postcode":"07716",
    "sg:province":"NJ",
    "sg:tags":[
        "wedding",
        "supply"
    ],
    "wof:name":"Uncommon Cake",
    "wof:placetype":"venue"
},
  "geometry": {"coordinates":[-74.03407900000001,40.413007],"type":"Point"}
}