{
  "type": "Feature",
  "properties": {
    "iso:country":"US",
    "sg:address":"206 French St",
    "sg:city":"New Brunswick",
    "sg:classifiers":[
        {
            "category":"Restaurant",
            "type":"Food & Drink"
        }
    ],
    "sg:menulink":"http://www.allmenus.com/nj/new-brunswick/254099-cinco-de-mayo/menu/",
    "sg:phone":"+1 732 214 1588",
    "sg:postcode":"08901",
    "sg:province":"NJ",
    "sg:tags":[
        "mexican"
    ],
    "wof:name":"Cinco De Mayo",
    "wof:placetype":"venue"
},
  "geometry": {"coordinates":[-74.456915,40.491014],"type":"Point"}
}