{
  "type": "Feature",
  "properties": {
    "addr:full":"27 Grant Ave East Hanover NJ 07936",
    "addr:housenumber":"27",
    "addr:postcode":"07936",
    "addr:street":"Grant Ave",
    "iso:country":"US",
    "sg:address":"27 Grant Ave",
    "sg:city":"East Hanover",
    "sg:classifiers":[
        {
            "category":"Professional",
            "subcategory":"Management & Consulting",
            "type":"Services"
        }
    ],
    "sg:phone":"+1   ",
    "sg:postcode":"07936",
    "sg:province":"NJ",
    "wof:name":"Magee James Marketing & Search",
    "wof:placetype":"venue"
},
  "geometry": {"coordinates":[-74.358881,40.826602],"type":"Point"}
}