{
  "type": "Feature",
  "properties": {
    "iso:country":"US",
    "sg:address":"33 Bouwrey Pl",
    "sg:city":"Whitehouse Sta",
    "sg:classifiers":[
        {
            "category":"Building & Trades",
            "subcategory":"Cleaning & Sanitation",
            "type":"Services"
        }
    ],
    "sg:phone":"+1 908 534 0085",
    "sg:postcode":"08889",
    "sg:province":"NJ",
    "sg:tags":[
        "house"
    ],
    "wof:name":"C & J Cleaning Svc",
    "wof:placetype":"venue"
},
  "geometry": {"coordinates":[-74.78340799999999,40.62478],"type":"Point"}
}