{
  "type": "Feature",
  "properties": {
    "iso:country":"US",
    "sg:address":"209 Rancocas Ave",
    "sg:city":"Riverside",
    "sg:classifiers":[
        {
            "category":"Building & Trades",
            "subcategory":"Construction",
            "type":"Services"
        }
    ],
    "sg:phone":"+1 856 764 1644",
    "sg:postcode":"08075",
    "sg:province":"NJ",
    "sg:tags":[
        "specializing",
        "home",
        "family",
        "contractor"
    ],
    "wof:name":"Jedi Building Contractors",
    "wof:placetype":"venue"
},
  "geometry": {"coordinates":[-74.965863,40.032143],"type":"Point"}
}