{
  "type": "Feature",
  "properties": {
    "iso:country":"US",
    "sg:address":"1754 Wynnewood Dr",
    "sg:city":"Vineland",
    "sg:classifiers":[
        {
            "category":"Marine",
            "type":"Transportation"
        }
    ],
    "sg:phone":"+1 856 405 0898",
    "sg:postcode":"08361",
    "sg:province":"NJ",
    "sg:tags":[
        "water",
        "transport"
    ],
    "wof:name":"Team Bartus Fishing LLC",
    "wof:placetype":"venue"
},
  "geometry": {"coordinates":[-74.972628,39.455414],"type":"Point"}
}