{
  "type": "Feature",
  "properties": {
    "iso:country":"US",
    "sg:address":"3 Ave A",
    "sg:city":"Lodi",
    "sg:classifiers":[
        {
            "category":"Professional",
            "subcategory":"Business Services",
            "type":"Services"
        }
    ],
    "sg:phone":"+1   ",
    "sg:postcode":"07644",
    "sg:province":"NJ",
    "wof:name":"Czarnwski Exhbt Svc Spcialists",
    "wof:placetype":"venue"
},
  "geometry": {"coordinates":[-74.078473,40.884111],"type":"Point"}
}