{
  "type": "Feature",
  "properties": {
    "addr:full":"1106 Cohocton Pl Point Pleasant Beach NJ 08742",
    "addr:housenumber":"1106",
    "addr:postcode":"08742",
    "addr:street":"Cohocton Pl",
    "iso:country":"US",
    "sg:address":"1106 Cohocton Pl",
    "sg:city":"Point Pleasant Beach",
    "sg:classifiers":[
        {
            "category":"Professional",
            "subcategory":"Management & Consulting",
            "type":"Services"
        }
    ],
    "sg:phone":"+1 732 892 8729",
    "sg:postcode":"08742",
    "sg:province":"NJ",
    "wof:name":"G N McGrady LLC",
    "wof:placetype":"venue"
},
  "geometry": {"coordinates":[-74.08860799999999,40.077207],"type":"Point"}
}