{
  "type": "Feature",
  "properties": {
    "iso:country":"US",
    "sg:address":"7 S Prospect St",
    "sg:city":"Verona",
    "sg:classifiers":[
        {
            "category":"Health Services",
            "subcategory":"Doctor",
            "type":"Services"
        }
    ],
    "sg:phone":"+1 973 239 1006",
    "sg:postcode":"07044",
    "sg:province":"NJ",
    "sg:tags":[
        "surgeon",
        "oral"
    ],
    "wof:name":"Perdikis Harris N DDS",
    "wof:placetype":"venue"
},
  "geometry": {"coordinates":[-74.24870300000001,40.832699],"type":"Point"}
}