{
  "type": "Feature",
  "properties": {
    "addr:full":"322 Franklin Blvd Somerset NJ 08873",
    "addr:housenumber":"322",
    "addr:postcode":"08873",
    "addr:street":"Franklin Blvd",
    "iso:country":"US",
    "sg:address":"322 Franklin Blvd",
    "sg:city":"Somerset",
    "sg:classifiers":[
        {
            "category":"Social Services",
            "subcategory":"Child Care",
            "type":"Services"
        }
    ],
    "sg:phone":"+1   ",
    "sg:postcode":"08873",
    "sg:province":"NJ",
    "sg:tags":[
        "day"
    ],
    "wof:name":"Little Chld of God Pre Sch Kin",
    "wof:placetype":"venue"
},
  "geometry": {"coordinates":[-74.477636,40.49655],"type":"Point"}
}