{
  "type": "Feature",
  "properties": {
    "addr:full":"260 Wayne St Wayne NJ 07470",
    "addr:housenumber":"260",
    "addr:postcode":"07470",
    "addr:street":"Wayne St",
    "iso:country":"US",
    "sg:address":"260 Wayne St",
    "sg:city":"Wayne",
    "sg:classifiers":[
        {
            "category":"Retail",
            "subcategory":"Portrait Studio",
            "type":"Services"
        }
    ],
    "sg:phone":"+1   ",
    "sg:postcode":"07470",
    "sg:province":"NJ",
    "sg:tags":[
        "photo"
    ],
    "wof:name":"JC Penny Portrait Studio",
    "wof:placetype":"venue"
},
  "geometry": {"coordinates":[-74.279572,40.922528],"type":"Point"}
}