{
  "type": "Feature",
  "properties": {
    "iso:country":"US",
    "sg:address":"61 E Bradford Ave",
    "sg:city":"Cedar Grove",
    "sg:classifiers":[
        {
            "category":"Building & Trades",
            "subcategory":"Construction",
            "type":"Services"
        }
    ],
    "sg:phone":"+1 973 857 5491",
    "sg:postcode":"07009",
    "sg:province":"NJ",
    "sg:tags":[
        "carpentry",
        "contractor"
    ],
    "wof:name":"Handyman Plus",
    "wof:placetype":"venue"
},
  "geometry": {"coordinates":[-74.226266,40.845496],"type":"Point"}
}