{
  "type": "Feature",
  "properties": {
    "iso:country":"US",
    "sg:address":"84 Park Ave",
    "sg:city":"Hillsdale",
    "sg:classifiers":[
        {
            "category":"Banks & Credit Unions",
            "subcategory":"Bank",
            "type":"Services"
        }
    ],
    "sg:phone":"+1   ",
    "sg:postcode":"07642",
    "sg:province":"NJ",
    "sg:tags":[
        "national",
        "commercial"
    ],
    "wof:name":"Fleet",
    "wof:placetype":"venue"
},
  "geometry": {"coordinates":[-74.041735,41.0034],"type":"Point"}
}