{
  "type": "Feature",
  "properties": {
    "iso:country":"US",
    "sg:address":"108 N Union Ave",
    "sg:city":"Cranford",
    "sg:classifiers":[
        {
            "category":"Health Services",
            "subcategory":"Doctor",
            "type":"Services"
        }
    ],
    "sg:phone":"+1   ",
    "sg:postcode":"07016",
    "sg:province":"NJ",
    "wof:name":"Arthur F Haliczer DDS",
    "wof:placetype":"venue"
},
  "geometry": {"coordinates":[-74.30266,40.657244],"type":"Point"}
}