{
  "type": "Feature",
  "properties": {
    "iso:country":"US",
    "sg:address":"95 Ivy Hill Rd",
    "sg:city":"Red Bank",
    "sg:classifiers":[
        {
            "category":"Wholesale",
            "subcategory":"Medical Equipment & Supplies",
            "type":"Manufacturing & Wholesale Goods"
        }
    ],
    "sg:phone":"+1 732 842 7998",
    "sg:postcode":"07701",
    "sg:province":"NJ",
    "sg:tags":[
        "diagnostic"
    ],
    "wof:name":"County Surgical Supply",
    "wof:placetype":"venue"
},
  "geometry": {"coordinates":[-74.108345,40.371446],"type":"Point"}
}