{
  "type": "Feature",
  "properties": {
    "iso:country":"US",
    "sg:address":"158 Seeley Ave",
    "sg:city":"Kearny",
    "sg:classifiers":[
        {
            "category":"Building & Trades",
            "subcategory":"Construction",
            "type":"Services"
        }
    ],
    "sg:phone":"+1 201 997 9268",
    "sg:postcode":"07032",
    "sg:province":"NJ",
    "sg:tags":[
        "house"
    ],
    "wof:name":"Rm Construction Corp",
    "wof:placetype":"venue"
},
  "geometry": {"coordinates":[-74.134197,40.776629],"type":"Point"}
}