{
  "type": "Feature",
  "properties": {
    "iso:country":"US",
    "sg:address":"510 Monmouth Rd",
    "sg:city":"Allenhurst",
    "sg:classifiers":[
        {
            "category":"Recreation",
            "type":"Entertainment"
        }
    ],
    "sg:phone":"+1   ",
    "sg:postcode":"07711",
    "sg:province":"NJ",
    "sg:tags":[
        "operated",
        "coin",
        "amusement"
    ],
    "wof:name":"V & J Amusements",
    "wof:placetype":"venue"
},
  "geometry": {"coordinates":[-74.01380399999999,40.240261],"type":"Point"}
}