{
  "type": "Feature",
  "properties": {
    "iso:country":"US",
    "sg:address":"183 Cedar Rd",
    "sg:city":"Mickleton",
    "sg:phone":"+1 856 478 2336",
    "sg:postcode":"08056",
    "sg:province":"NJ",
    "sg:tags":[
        "farm",
        "field",
        "crop"
    ],
    "wof:name":"Brown Bros Farm",
    "wof:placetype":"venue"
},
  "geometry": {"coordinates":[-75.21961400000001,39.771061],"type":"Point"}
}