{
  "type": "Feature",
  "properties": {
    "iso:country":"US",
    "sg:address":"500 Palisade Ave",
    "sg:city":"Garfield",
    "sg:classifiers":[
        {
            "category":"Education",
            "subcategory":"School",
            "type":"Public Place"
        }
    ],
    "sg:phone":"+1 973 340 5044",
    "sg:postcode":"07026",
    "sg:province":"NJ",
    "wof:name":"Garfield Special Education",
    "wof:placetype":"venue"
},
  "geometry": {"coordinates":[-74.11212999999999,40.882356],"type":"Point"}
}