{
  "type": "Feature",
  "properties": {
    "addr:full":"131 Gladstone Dr Parsippany NJ 07054",
    "addr:housenumber":"131",
    "addr:postcode":"07054",
    "addr:street":"Gladstone Dr",
    "iso:country":"US",
    "sg:address":"131 Gladstone Dr",
    "sg:city":"Parsippany",
    "sg:classifiers":[
        {
            "category":"Professional",
            "subcategory":"Management & Consulting",
            "type":"Services"
        }
    ],
    "sg:phone":"+1 973 335 6631",
    "sg:postcode":"07054",
    "sg:province":"NJ",
    "sg:tags":[
        "packaging",
        "industry",
        "broker",
        "for"
    ],
    "wof:name":"Bel-Mar Packaging",
    "wof:placetype":"venue"
},
  "geometry": {"coordinates":[-74.379964,40.864289],"type":"Point"}
}