{
  "type": "Feature",
  "properties": {
    "addr:full":"542 N Delsea Dr Green Creek NJ 08210",
    "addr:housenumber":"542",
    "addr:postcode":"08210",
    "addr:street":"N Delsea Dr Green",
    "iso:country":"US",
    "sg:address":"542 N Delsea Dr",
    "sg:city":"Green Creek",
    "sg:classifiers":[
        {
            "category":"Building & Trades",
            "subcategory":"Construction",
            "type":"Services"
        }
    ],
    "sg:phone":"+1 609 886 6437",
    "sg:postcode":"08210",
    "sg:province":"NJ",
    "sg:tags":[
        "excavating",
        "contractor"
    ],
    "wof:name":"Bradway Construction Inc",
    "wof:placetype":"venue"
},
  "geometry": {"coordinates":[-74.833877,39.16107],"type":"Point"}
}