{
  "type": "Feature",
  "properties": {
    "addr:full":"26 Erie St Jersey City NJ 07302",
    "addr:housenumber":"26",
    "addr:postcode":"07302",
    "addr:street":"Erie St",
    "iso:country":"US",
    "sg:address":"26 Erie St",
    "sg:city":"Jersey City",
    "sg:classifiers":[
        {
            "category":"Personal",
            "subcategory":"Beauty Salon",
            "type":"Services"
        }
    ],
    "sg:phone":"+1 201 798 3433",
    "sg:postcode":"07302",
    "sg:province":"NJ",
    "sg:tags":[
        "shop"
    ],
    "wof:name":"Ruthie's Cutting Edge",
    "wof:placetype":"venue"
},
  "geometry": {"coordinates":[-74.044206,40.721692],"type":"Point"}
}