{
  "type": "Feature",
  "properties": {
    "addr:full":"52 S Broadway Pitman NJ 08071",
    "addr:housenumber":"52",
    "addr:postcode":"08071",
    "addr:street":"S Broadway",
    "iso:country":"US",
    "sg:address":"52 S Broadway",
    "sg:city":"Pitman",
    "sg:classifiers":[
        {
            "category":"Professional",
            "type":"Services"
        }
    ],
    "sg:phone":"+1 856 218 1061",
    "sg:postcode":"08071",
    "sg:province":"NJ",
    "sg:tags":[
        "establishment"
    ],
    "wof:name":"Sunbeams & Daydreams",
    "wof:placetype":"venue"
},
  "geometry": {"coordinates":[-75.13142499999999,39.733108],"type":"Point"}
}