{
  "type": "Feature",
  "properties": {
    "iso:country":"US",
    "sg:address":"70 Cresci Blvd",
    "sg:city":"Hazlet",
    "sg:classifiers":[
        {
            "category":"Restaurant",
            "type":"Food & Drink"
        }
    ],
    "sg:phone":"+1   ",
    "sg:postcode":"07730",
    "sg:province":"NJ",
    "sg:tags":[
        "eating"
    ],
    "wof:name":"Colixon Inc",
    "wof:placetype":"venue"
},
  "geometry": {"coordinates":[-74.204753,40.408963],"type":"Point"}
}