{
  "type": "Feature",
  "properties": {
    "addr:full":"1144 E Ridgewood Ave Ridgewood NJ 07450",
    "addr:housenumber":"1144",
    "addr:postcode":"07450",
    "addr:street":"E Ridgewood Ave",
    "iso:country":"US",
    "sg:address":"1144 E Ridgewood Ave",
    "sg:city":"Ridgewood",
    "sg:classifiers":[
        {
            "category":"Health Services",
            "subcategory":"Doctor",
            "type":"Services"
        }
    ],
    "sg:phone":"+1 201 445 9968",
    "sg:postcode":"07450",
    "sg:province":"NJ",
    "sg:tags":[
        "physician",
        "surgeon"
    ],
    "wof:name":"Tatiana Sharahy MD",
    "wof:placetype":"venue"
},
  "geometry": {"coordinates":[-74.093872,40.973302],"type":"Point"}
}