{
  "type": "Feature",
  "properties": {
    "addr:full":"70 N Grist Mill Pl Absecon NJ 08205",
    "addr:housenumber":"70",
    "addr:postcode":"08205",
    "addr:street":"N Grist Mill Pl",
    "iso:country":"US",
    "sg:address":"70 N Grist Mill Pl",
    "sg:city":"Absecon",
    "sg:classifiers":[
        {
            "category":"Social Services",
            "type":"Services"
        }
    ],
    "sg:phone":"+1   ",
    "sg:postcode":"08205",
    "sg:province":"NJ",
    "wof:name":"Court Appointed Special Advoca",
    "wof:placetype":"venue"
},
  "geometry": {"coordinates":[-74.45278399999999,39.49468],"type":"Point"}
}