{
  "type": "Feature",
  "properties": {
    "iso:country":"US",
    "sg:address":"13 Jefferson Ave",
    "sg:city":"Stratford",
    "sg:classifiers":[
        {
            "category":"Building & Trades",
            "subcategory":"Construction",
            "type":"Services"
        }
    ],
    "sg:phone":"+1 856 783 3118",
    "sg:postcode":"08084",
    "sg:province":"NJ",
    "sg:tags":[
        "wallpaper"
    ],
    "wof:name":"Ray's Wallpapering & Painting",
    "wof:placetype":"venue"
},
  "geometry": {"coordinates":[-75.01035400000001,39.829514],"type":"Point"}
}