{
  "type": "Feature",
  "properties": {
    "addr:full":"184 Lincoln Pl Garfield NJ 07026",
    "addr:housenumber":"184",
    "addr:postcode":"07026",
    "addr:street":"Lincoln Pl",
    "iso:country":"US",
    "sg:address":"184 Lincoln Pl",
    "sg:city":"Garfield",
    "sg:classifiers":[
        {
            "category":"Social Services",
            "subcategory":"Child Care",
            "type":"Services"
        }
    ],
    "sg:phone":"+1 973 546 0600",
    "sg:postcode":"07026",
    "sg:province":"NJ",
    "sg:tags":[
        "day"
    ],
    "wof:name":"Susana's Daycare",
    "wof:placetype":"venue"
},
  "geometry": {"coordinates":[-74.103042,40.871944],"type":"Point"}
}