{
  "type": "Feature",
  "properties": {
    "addr:full":"34 Meadow Rd Rutherford NJ 07070",
    "addr:housenumber":"34",
    "addr:postcode":"07070",
    "addr:street":"Meadow Rd",
    "iso:country":"US",
    "sg:address":"34 Meadow Rd",
    "sg:city":"Rutherford",
    "sg:classifiers":[
        {
            "category":"Communications",
            "subcategory":"Film & Video Production",
            "type":"Services"
        }
    ],
    "sg:phone":"+1 201 939 3024",
    "sg:postcode":"07070",
    "sg:province":"NJ",
    "sg:tags":[
        "wholesale",
        "visual",
        "program",
        "rent",
        "audio",
        "audi"
    ],
    "wof:name":"Avcoa Inc",
    "wof:placetype":"venue"
},
  "geometry": {"coordinates":[-74.099895,40.824922],"type":"Point"}
}