{
  "type": "Feature",
  "properties": {
    "addr:full":"128 Orange St Newark NJ 07102",
    "addr:housenumber":"128",
    "addr:postcode":"07102",
    "addr:street":"Orange St",
    "iso:country":"US",
    "sg:address":"128 Orange St",
    "sg:city":"Newark",
    "sg:classifiers":[
        {
            "category":"Wholesale",
            "subcategory":"Meat",
            "type":"Manufacturing & Wholesale Goods"
        }
    ],
    "sg:phone":"+1 973 624 3331",
    "sg:postcode":"07102",
    "sg:province":"NJ",
    "sg:tags":[
        "product"
    ],
    "wof:name":"Three Star Beef Co Inc",
    "wof:placetype":"venue"
},
  "geometry": {"coordinates":[-74.172336,40.746525],"type":"Point"}
}