{
  "type": "Feature",
  "properties": {
    "addr:full":"273 Myler Rd Bloomsbury NJ 08804",
    "addr:housenumber":"273",
    "addr:postcode":"08804",
    "addr:street":"Myler Rd",
    "iso:country":"US",
    "sg:address":"273 Myler Rd",
    "sg:city":"Bloomsbury",
    "sg:classifiers":[
        {
            "category":"Travel",
            "subcategory":"Travel Agent",
            "type":"Entertainment"
        }
    ],
    "sg:phone":"+1 908 479 4861",
    "sg:postcode":"08804",
    "sg:province":"NJ",
    "sg:tags":[
        "agency",
        "bureau"
    ],
    "wof:name":"A-Three Mermaid Travel Service",
    "wof:placetype":"venue"
},
  "geometry": {"coordinates":[-75.097104,40.631493],"type":"Point"}
}