{
  "type": "Feature",
  "properties": {
    "addr:full":"114 Walt Whitman Blvd Cherry Hill NJ 08003",
    "addr:housenumber":"114",
    "addr:postcode":"08003",
    "addr:street":"Walt Whitman Blvd",
    "iso:country":"US",
    "sg:address":"114 Walt Whitman Blvd",
    "sg:city":"Cherry Hill",
    "sg:classifiers":[
        {
            "category":"Professional",
            "subcategory":"Business Services",
            "type":"Services"
        }
    ],
    "sg:phone":"+1   ",
    "sg:postcode":"08003",
    "sg:province":"NJ",
    "wof:name":"Joe Callari Music Inc",
    "wof:placetype":"venue"
},
  "geometry": {"coordinates":[-74.998043,39.864127],"type":"Point"}
}