{
  "type": "Feature",
  "properties": {
    "iso:country":"US",
    "sg:address":"1174 Kaye Ct",
    "sg:city":"Burlington",
    "sg:classifiers":[
        {
            "category":"Taxi",
            "type":"Transportation"
        }
    ],
    "sg:phone":"+1 609 291 7855",
    "sg:postcode":"08016",
    "sg:province":"NJ",
    "wof:name":"Bordentown Jj Taxi",
    "wof:placetype":"venue"
},
  "geometry": {"coordinates":[-74.87869600000001,40.049586],"type":"Point"}
}