{
  "type": "Feature",
  "properties": {
    "addr:full":"302 US Hwy 46 Fairfield NJ 07004",
    "addr:housenumber":"302",
    "addr:postcode":"07004",
    "addr:street":"Us Hwy 46",
    "iso:country":"US",
    "sg:address":"302 US Hwy 46",
    "sg:city":"Fairfield",
    "sg:classifiers":[
        {
            "category":"Wholesale",
            "subcategory":"Groceries",
            "type":"Manufacturing & Wholesale Goods"
        }
    ],
    "sg:phone":"+1 973 439 0040",
    "sg:postcode":"07004",
    "sg:province":"NJ",
    "sg:tags":[
        "food",
        "distributor"
    ],
    "wof:name":"Vel-Mac Food Distributors",
    "wof:placetype":"venue"
},
  "geometry": {"coordinates":[-74.29461499999999,40.879875],"type":"Point"}
}