{
  "type": "Feature",
  "properties": {
    "addr:full":"146 Lakeview Dr S Gibbsboro NJ 08026",
    "addr:housenumber":"146",
    "addr:postcode":"08026",
    "addr:street":"Lakeview Dr S",
    "iso:country":"US",
    "sg:address":"146 Lakeview Dr S",
    "sg:city":"Gibbsboro",
    "sg:classifiers":[
        {
            "category":"Wholesale",
            "subcategory":"Durable Goods & Equipment",
            "type":"Manufacturing & Wholesale Goods"
        }
    ],
    "sg:phone":"+1 856 435 5700",
    "sg:postcode":"08026",
    "sg:province":"NJ",
    "sg:tags":[
        "importer"
    ],
    "wof:name":"C E Sweeney & Assoc",
    "wof:placetype":"venue"
},
  "geometry": {"coordinates":[-74.958231,39.834563],"type":"Point"}
}