{
  "type": "Feature",
  "properties": {
    "addr:full":"2172 Echelon Mall Voorhees NJ 08043",
    "addr:housenumber":"2172",
    "addr:postcode":"08043",
    "addr:street":"Echelon Mall",
    "iso:country":"US",
    "sg:address":"2172 Echelon Mall",
    "sg:city":"Voorhees",
    "sg:classifiers":[
        {
            "category":"Shopping",
            "subcategory":"Optical Goods",
            "type":"Retail Goods"
        }
    ],
    "sg:phone":"+1 856 770 1799",
    "sg:postcode":"08043",
    "sg:province":"NJ",
    "sg:tags":[
        "sun",
        "goggles",
        "sunglasses"
    ],
    "wof:name":"Sunglass Hut",
    "wof:placetype":"venue"
},
  "geometry": {"coordinates":[-75.001893,39.848307],"type":"Point"}
}