{
  "type": "Feature",
  "properties": {
    "iso:country":"US",
    "sg:address":"321 Broadway",
    "sg:city":"Hillsdale",
    "sg:classifiers":[
        {
            "category":"Banks & Credit Unions",
            "subcategory":"Bank",
            "type":"Services"
        }
    ],
    "sg:phone":"+1 201 703 2265",
    "sg:postcode":"07642",
    "sg:province":"NJ",
    "wof:name":"Interchange Bank",
    "wof:placetype":"venue"
},
  "geometry": {"coordinates":[-74.04199800000001,41.013306],"type":"Point"}
}