{
  "type": "Feature",
  "properties": {
    "iso:country":"US",
    "sg:address":"110 Main St",
    "sg:city":"South Amboy",
    "sg:classifiers":[
        {
            "category":"Building & Trades",
            "subcategory":"Construction",
            "type":"Services"
        }
    ],
    "sg:phone":"+1 732 727 2022",
    "sg:postcode":"08879",
    "sg:province":"NJ",
    "sg:tags":[
        "concrete",
        "contractor"
    ],
    "wof:name":"Accurate Concrete-South Amboy",
    "wof:placetype":"venue"
},
  "geometry": {"coordinates":[-74.289192,40.492425],"type":"Point"}
}