{
  "type": "Feature",
  "properties": {
    "addr:full":"189 Cumberland Ave Estell Manor NJ 08319",
    "addr:housenumber":"189",
    "addr:postcode":"08319",
    "addr:street":"Cumberland Ave",
    "iso:country":"US",
    "sg:address":"189 Cumberland Ave",
    "sg:city":"Estell Manor",
    "sg:classifiers":[
        {
            "category":"Wholesale",
            "subcategory":"Groceries",
            "type":"Manufacturing & Wholesale Goods"
        }
    ],
    "sg:phone":"+1 609 476 3374",
    "sg:postcode":"08319",
    "sg:province":"NJ",
    "wof:name":"Sugar Plums",
    "wof:placetype":"venue"
},
  "geometry": {"coordinates":[-74.824091,39.376666],"type":"Point"}
}