{
  "type": "Feature",
  "properties": {
    "addr:full":"504 N Main St Williamstown NJ 08094",
    "addr:housenumber":"504",
    "addr:postcode":"08094",
    "addr:street":"N Main St",
    "iso:country":"US",
    "sg:address":"504 N Main St",
    "sg:city":"Williamstown",
    "sg:classifiers":[
        {
            "category":"Retail",
            "subcategory":"Funeral Services",
            "type":"Services"
        }
    ],
    "sg:phone":"+1 856 629 5291",
    "sg:postcode":"08094",
    "sg:province":"NJ",
    "sg:tags":[
        "cemetery"
    ],
    "sg:website":"www.farnellifuneralhome.com",
    "wof:name":"Farnelli Funeral Home",
    "wof:placetype":"venue"
},
  "geometry": {"coordinates":[-75.00190000000001,39.691502],"type":"Point"}
}