{
  "type": "Feature",
  "properties": {
    "addr:full":"559 Speedwell Ave Morris Plains NJ 07950",
    "addr:housenumber":"559",
    "addr:postcode":"07950",
    "addr:street":"Speedwell Ave",
    "iso:country":"US",
    "sg:address":"559 Speedwell Ave",
    "sg:city":"Morris Plains",
    "sg:classifiers":[
        {
            "category":"Arts & Performance",
            "subcategory":"Arts Center",
            "type":"Entertainment"
        }
    ],
    "sg:phone":"+1 973 605 2888",
    "sg:postcode":"07950",
    "sg:province":"NJ",
    "sg:tags":[
        "performing"
    ],
    "wof:name":"Touch Dancing Studio",
    "wof:placetype":"venue"
},
  "geometry": {"coordinates":[-74.480003,40.8265],"type":"Point"}
}