{
  "type": "Feature",
  "properties": {
    "iso:country":"US",
    "sg:address":"901 US Hwy 1",
    "sg:city":"North Brunswick",
    "sg:classifiers":[
        {
            "category":"Utilities",
            "subcategory":"Mobile Phone",
            "type":"Services"
        }
    ],
    "sg:phone":"+1 732 247 2233",
    "sg:postcode":"08902",
    "sg:province":"NJ",
    "sg:tags":[
        "communication",
        "radiotelephone"
    ],
    "wof:name":"Cingular Wireless",
    "wof:placetype":"venue"
},
  "geometry": {"coordinates":[-74.47075700000001,40.458624],"type":"Point"}
}