{
  "type": "Feature",
  "properties": {
    "addr:full":"301 Cherry Hill Blvd Cherry Hill NJ 08002",
    "addr:housenumber":"301",
    "addr:postcode":"08002",
    "addr:street":"Cherry Hill Blvd",
    "iso:country":"US",
    "sg:address":"301 Cherry Hill Blvd",
    "sg:city":"Cherry Hill",
    "sg:classifiers":[
        {
            "category":"Home & Garden",
            "subcategory":"Home Furnishings",
            "type":"Retail Goods"
        }
    ],
    "sg:phone":"+1   ",
    "sg:postcode":"08002",
    "sg:province":"NJ",
    "sg:tags":[
        "cookware",
        "kitchen",
        "accessory"
    ],
    "wof:name":"Kitchen Kapers Inc",
    "wof:placetype":"venue"
},
  "geometry": {"coordinates":[-75.01690000000001,39.93633],"type":"Point"}
}