{
  "type": "Feature",
  "properties": {
    "addr:full":"33 N Haledon Ave North Haledon NJ 07508",
    "addr:housenumber":"33",
    "addr:postcode":"07508",
    "addr:street":"N Haledon Ave",
    "iso:country":"US",
    "sg:address":"33 N Haledon Ave",
    "sg:city":"North Haledon",
    "sg:classifiers":[
        {
            "category":"Shopping",
            "subcategory":"Computers & Home Electronics",
            "type":"Retail Goods"
        }
    ],
    "sg:phone":"+1 201 337 0051",
    "sg:postcode":"07508",
    "sg:province":"NJ",
    "sg:tags":[
        "software"
    ],
    "sg:website":"www.reyconsulting.com",
    "wof:name":"Rey Consulting",
    "wof:placetype":"venue"
},
  "geometry": {"coordinates":[-74.182957,40.962198],"type":"Point"}
}