{
  "type": "Feature",
  "properties": {
    "addr:full":"400 Atlantic Ave Ocean City NJ 08226",
    "addr:housenumber":"400",
    "addr:postcode":"08226",
    "addr:street":"Atlantic Ave",
    "iso:country":"US",
    "sg:address":"400 Atlantic Ave",
    "sg:city":"Ocean City",
    "sg:classifiers":[
        {
            "category":"Travel",
            "subcategory":"Hotels & Motels",
            "type":"Entertainment"
        }
    ],
    "sg:phone":"+1 609 814 1886",
    "sg:postcode":"08226",
    "sg:province":"NJ",
    "sg:tags":[
        "breakfast",
        "accommodation",
        "bed"
    ],
    "wof:name":"Laurel Bay Bed & Breakfast",
    "wof:placetype":"venue"
},
  "geometry": {"coordinates":[-74.566453,39.281628],"type":"Point"}
}