{
  "type": "Feature",
  "properties": {
    "addr:full":"901 Wood Ave Roselle NJ 07203",
    "addr:housenumber":"901",
    "addr:postcode":"07203",
    "addr:street":"Wood Ave",
    "iso:country":"US",
    "sg:address":"901 Wood Ave",
    "sg:city":"Roselle",
    "sg:classifiers":[
        {
            "category":"Personal",
            "subcategory":"Beauty Salon",
            "type":"Services"
        }
    ],
    "sg:phone":"+1 908 245 5252",
    "sg:postcode":"07203",
    "sg:province":"NJ",
    "sg:tags":[
        "shop"
    ],
    "wof:name":"Golden Nails Salon Inc",
    "wof:placetype":"venue"
},
  "geometry": {"coordinates":[-74.273946,40.644501],"type":"Point"}
}