{
  "type": "Feature",
  "properties": {
    "iso:country":"US",
    "sg:address":"1014 Anderson Ave",
    "sg:city":"Fort Lee",
    "sg:classifiers":[
        {
            "category":"Personal",
            "subcategory":"Beauty Salon",
            "type":"Services"
        }
    ],
    "sg:phone":"+1   ",
    "sg:postcode":"07024",
    "sg:province":"NJ",
    "sg:tags":[
        "shop"
    ],
    "wof:name":"Wsrl LLC",
    "wof:placetype":"venue"
},
  "geometry": {"coordinates":[-73.984054,40.833529],"type":"Point"}
}