{
  "type": "Feature",
  "properties": {
    "addr:full":"20 Split Rock Rd Haledon NJ 07508",
    "addr:housenumber":"20",
    "addr:postcode":"07508",
    "addr:street":"Split Rock Rd",
    "iso:country":"US",
    "sg:address":"20 Split Rock Rd",
    "sg:city":"Haledon",
    "sg:classifiers":[
        {
            "category":"Professional",
            "subcategory":"Management & Consulting",
            "type":"Services"
        }
    ],
    "sg:phone":"+1 973 238 4433",
    "sg:postcode":"07508",
    "sg:province":"NJ",
    "wof:name":"Parks Financial Management",
    "wof:placetype":"venue"
},
  "geometry": {"coordinates":[-74.203743,40.978504],"type":"Point"}
}