{
  "type": "Feature",
  "properties": {
    "addr:full":"605 State Rte 35 Shrewsbury NJ 07702",
    "addr:housenumber":"605",
    "addr:postcode":"07702",
    "addr:street":"State Rte 35",
    "iso:country":"US",
    "sg:address":"605 State Rte 35",
    "sg:city":"Shrewsbury",
    "sg:classifiers":[
        {
            "category":"Shopping",
            "subcategory":"Clothing, Apparel, & Fashions",
            "type":"Retail Goods"
        }
    ],
    "sg:phone":"+1   ",
    "sg:postcode":"07702",
    "sg:province":"NJ",
    "sg:tags":[
        "jewelry",
        "family"
    ],
    "wof:name":"Belmondo",
    "wof:placetype":"venue"
},
  "geometry": {"coordinates":[-74.06252000000001,40.33118],"type":"Point"}
}