{
  "type": "Feature",
  "properties": {
    "addr:full":"147 W End Ave Englewood NJ 07631",
    "addr:housenumber":"147",
    "addr:postcode":"07631",
    "addr:street":"W End Ave",
    "iso:country":"US",
    "sg:address":"147 W End Ave",
    "sg:city":"Englewood",
    "sg:classifiers":[
        {
            "category":"Shopping",
            "subcategory":"Clothing, Apparel, & Fashions",
            "type":"Retail Goods"
        }
    ],
    "sg:phone":"+1   ",
    "sg:postcode":"07631",
    "sg:province":"NJ",
    "wof:name":"Handbag Department",
    "wof:placetype":"venue"
},
  "geometry": {"coordinates":[-73.97899099999999,40.899058],"type":"Point"}
}