{
  "type": "Feature",
  "properties": {
    "iso:country":"US",
    "sg:address":"630 Old Chester-Gladstone Rd",
    "sg:city":"Far Hills",
    "sg:classifiers":[
        {
            "category":"Shopping",
            "subcategory":"Clothing, Apparel, & Fashions",
            "type":"Retail Goods"
        }
    ],
    "sg:phone":"+1 908 234 9441",
    "sg:postcode":"07931",
    "sg:province":"NJ",
    "wof:name":"B D Diana Inc",
    "wof:placetype":"venue"
},
  "geometry": {"coordinates":[-74.681065,40.744048],"type":"Point"}
}