{
  "type": "Feature",
  "properties": {
    "addr:full":"1525 State Rte 35 Neptune NJ 07753",
    "addr:housenumber":"1525",
    "addr:postcode":"07753",
    "addr:street":"State Rte 35",
    "iso:country":"US",
    "sg:address":"1525 State Rte 35",
    "sg:city":"Neptune",
    "sg:classifiers":[
        {
            "category":"Retail",
            "subcategory":"Auto Repair",
            "type":"Services"
        }
    ],
    "sg:phone":"+1 732 774 7999",
    "sg:postcode":"07753",
    "sg:province":"NJ",
    "sg:tags":[
        "repairing",
        "automobile"
    ],
    "wof:name":"Cottman Transmission Ctr",
    "wof:placetype":"venue"
},
  "geometry": {"coordinates":[-74.02510599999999,40.187928],"type":"Point"}
}