{
  "type": "Feature",
  "properties": {
    "iso:country":"US",
    "sg:address":"107 Franklin St",
    "sg:city":"Hightstown",
    "sg:classifiers":[
        {
            "category":"Restaurant",
            "type":"Food & Drink"
        }
    ],
    "sg:phone":"+1   ",
    "sg:postcode":"08520",
    "sg:province":"NJ",
    "sg:tags":[
        "eating"
    ],
    "wof:name":"Bella Calabria Italian CA",
    "wof:placetype":"venue"
},
  "geometry": {"coordinates":[-74.521884,40.27057],"type":"Point"}
}