{
  "type": "Feature",
  "properties": {
    "addr:full":"1218 Route 166 Toms River NJ 08753",
    "addr:housenumber":"1218",
    "addr:postcode":"08753",
    "addr:street":"Route 166",
    "iso:country":"US",
    "sg:address":"1218 Route 166",
    "sg:city":"Toms River",
    "sg:classifiers":[
        {
            "category":"Cafe",
            "type":"Food & Drink"
        }
    ],
    "sg:menulink":"http://www.allmenus.com/nj/toms-river/28187-the-oil-house-cafe/menu/",
    "sg:phone":"+1 732 244 4060",
    "sg:postcode":"08753",
    "sg:province":"NJ",
    "sg:tags":[
        "american"
    ],
    "wof:name":"The Oil House Cafe",
    "wof:placetype":"venue"
},
  "geometry": {"coordinates":[-74.21017000000001,39.984235],"type":"Point"}
}