{
  "type": "Feature",
  "properties": {
    "addr:full":"69 Ravona St Clifton NJ 07012",
    "addr:housenumber":"69",
    "addr:postcode":"07012",
    "addr:street":"Ravona St",
    "iso:country":"US",
    "sg:address":"69 Ravona St",
    "sg:city":"Clifton",
    "sg:classifiers":[
        {
            "category":"Professional",
            "subcategory":"Lawyer & Legal Services",
            "type":"Services"
        }
    ],
    "sg:phone":"+1 973 472 8842",
    "sg:postcode":"07012",
    "sg:province":"NJ",
    "wof:name":"Novick Robert M Atty At Law",
    "wof:placetype":"venue"
},
  "geometry": {"coordinates":[-74.146175,40.843343],"type":"Point"}
}