{
  "type": "Feature",
  "properties": {
    "addr:full":"28 Speir Dr South Orange NJ 07079",
    "addr:housenumber":"28",
    "addr:postcode":"07079",
    "addr:street":"Speir Dr",
    "iso:country":"US",
    "sg:address":"28 Speir Dr",
    "sg:city":"South Orange",
    "sg:classifiers":[
        {
            "category":"Health Services",
            "subcategory":"Doctor",
            "type":"Services"
        }
    ],
    "sg:phone":"+1   ",
    "sg:postcode":"07079",
    "sg:province":"NJ",
    "sg:tags":[
        "medical"
    ],
    "wof:name":"Marano Matthew J Jr MD",
    "wof:placetype":"venue"
},
  "geometry": {"coordinates":[-74.280862,40.747674],"type":"Point"}
}