{
  "type": "Feature",
  "properties": {
    "iso:country":"US",
    "sg:address":"1110 13th St",
    "sg:city":"North Bergen",
    "sg:classifiers":[
        {
            "category":"Wholesale",
            "subcategory":"Stationery",
            "type":"Manufacturing & Wholesale Goods"
        }
    ],
    "sg:phone":"+1 201 865 8114",
    "sg:postcode":"07047",
    "sg:province":"NJ",
    "sg:tags":[
        "beauty",
        "bag",
        "paper",
        "health",
        "aides",
        "candle"
    ],
    "wof:name":"MAN Wholesale Inc",
    "wof:placetype":"venue"
},
  "geometry": {"coordinates":[-74.04514399999999,40.763444],"type":"Point"}
}