{
  "type": "Feature",
  "properties": {
    "iso:country":"US",
    "sg:address":"356 Rahway Ave",
    "sg:city":"Elizabeth",
    "sg:classifiers":[
        {
            "category":"Restaurant",
            "type":"Food & Drink"
        }
    ],
    "sg:phone":"+1 908 354 9270",
    "sg:postcode":"07202",
    "sg:province":"NJ",
    "wof:name":"Don Alex Restaurant",
    "wof:placetype":"venue"
},
  "geometry": {"coordinates":[-74.224549,40.658807],"type":"Point"}
}