{
  "type": "Feature",
  "properties": {
    "addr:full":"36 Cambridge Rd Freehold NJ 07728",
    "addr:housenumber":"36",
    "addr:postcode":"07728",
    "addr:street":"Cambridge Rd",
    "iso:country":"US",
    "sg:address":"36 Cambridge Rd",
    "sg:city":"Freehold",
    "sg:classifiers":[
        {
            "category":"Building & Trades",
            "subcategory":"Landscaping Services",
            "type":"Services"
        }
    ],
    "sg:phone":"+1 732 780 8782",
    "sg:postcode":"07728",
    "sg:province":"NJ",
    "wof:name":"Alta Lawn & Landscape",
    "wof:placetype":"venue"
},
  "geometry": {"coordinates":[-74.291487,40.222243],"type":"Point"}
}