{
  "type": "Feature",
  "properties": {
    "iso:country":"US",
    "sg:address":"34 Lyons Mall",
    "sg:city":"Basking Ridge",
    "sg:classifiers":[
        {
            "category":"Restaurant",
            "type":"Food & Drink"
        }
    ],
    "sg:phone":"+1 908 221 9222",
    "sg:postcode":"07920",
    "sg:province":"NJ",
    "wof:name":"Lotus Deli",
    "wof:placetype":"venue"
},
  "geometry": {"coordinates":[-74.549982,40.682843],"type":"Point"}
}