{
  "type": "Feature",
  "properties": {
    "addr:full":"4 Roxy Ave Edison NJ 08820",
    "addr:housenumber":"4",
    "addr:postcode":"08820",
    "addr:street":"Roxy Ave",
    "iso:country":"US",
    "sg:address":"4 Roxy Ave",
    "sg:city":"Edison",
    "sg:classifiers":[
        {
            "category":"Professional",
            "type":"Services"
        }
    ],
    "sg:phone":"+1 732 388 5708",
    "sg:postcode":"08820",
    "sg:province":"NJ",
    "sg:tags":[
        "second",
        "hand"
    ],
    "wof:name":"Amin, Shilen",
    "wof:placetype":"venue"
},
  "geometry": {"coordinates":[-74.349665,40.597046],"type":"Point"}
}