{
  "type": "Feature",
  "properties": {
    "iso:country":"US",
    "sg:address":"3513 Park Ave",
    "sg:city":"Union City",
    "sg:classifiers":[
        {
            "category":"Food & Beverages",
            "subcategory":"Groceries & Convenience Stores",
            "type":"Retail Goods"
        }
    ],
    "sg:phone":"+1 201 319 9360",
    "sg:postcode":"07087",
    "sg:province":"NJ",
    "sg:tags":[
        "grocer"
    ],
    "wof:name":"LA Victoria Grocery",
    "wof:placetype":"venue"
},
  "geometry": {"coordinates":[-74.022417,40.771478],"type":"Point"}
}