{
  "type": "Feature",
  "properties": {
    "addr:full":"7 Wilson Ave Rutherford NJ 07070",
    "addr:housenumber":"7",
    "addr:postcode":"07070",
    "addr:street":"Wilson Ave",
    "iso:country":"US",
    "sg:address":"7 Wilson Ave",
    "sg:city":"Rutherford",
    "sg:classifiers":[
        {
            "category":"Travel",
            "subcategory":"Campground",
            "type":"Entertainment"
        }
    ],
    "sg:phone":"+1 201 935 0511",
    "sg:postcode":"07070",
    "sg:province":"NJ",
    "sg:tags":[
        "camp",
        "camps-recreational"
    ],
    "wof:name":"Joe Wladyka Camps Inc",
    "wof:placetype":"venue"
},
  "geometry": {"coordinates":[-74.111031,40.820706],"type":"Point"}
}