{
  "type": "Feature",
  "properties": {
    "iso:country":"US",
    "sg:address":"75 Cooper St",
    "sg:city":"Deptford",
    "sg:classifiers":[
        {
            "category":"Professional",
            "subcategory":"Lawyer & Legal Services",
            "type":"Services"
        }
    ],
    "sg:phone":"+1 856 848 6440",
    "sg:postcode":"08096",
    "sg:province":"NJ",
    "sg:tags":[
        "attorney"
    ],
    "wof:name":"Long Marmero & Mayer LLP",
    "wof:placetype":"venue"
},
  "geometry": {"coordinates":[-75.150193,39.836866],"type":"Point"}
}