{
  "type": "Feature",
  "properties": {
    "addr:full":"1021 Marlton Pike Cherry Hill NJ 08002",
    "addr:housenumber":"1021",
    "addr:postcode":"08002",
    "addr:street":"Marlton Pike",
    "iso:country":"US",
    "sg:address":"1021 Marlton Pike",
    "sg:city":"Cherry Hill",
    "sg:classifiers":[
        {
            "category":"Health Services",
            "subcategory":"Doctor",
            "type":"Services"
        }
    ],
    "sg:phone":"+1 856 429 4249",
    "sg:postcode":"08002",
    "sg:province":"NJ",
    "sg:tags":[
        "dentist"
    ],
    "wof:name":"Mitchell Brudno DDS",
    "wof:placetype":"venue"
},
  "geometry": {"coordinates":[-75.022841,39.916047],"type":"Point"}
}