{
  "type": "Feature",
  "properties": {
    "iso:country":"US",
    "sg:address":"704 E Main St",
    "sg:city":"Moorestown",
    "sg:classifiers":[
        {
            "category":"Professional",
            "subcategory":"Management & Consulting",
            "type":"Services"
        }
    ],
    "sg:phone":"+1 856 234 3536",
    "sg:postcode":"08057",
    "sg:province":"NJ",
    "sg:tags":[
        "consultant",
        "business"
    ],
    "sg:website":"www.ameriprac.com",
    "wof:name":"American Practice Consultants",
    "wof:placetype":"venue"
},
  "geometry": {"coordinates":[-74.917693,39.97307],"type":"Point"}
}