{
  "type": "Feature",
  "properties": {
    "addr:full":"1402 S Branch Dr Lebanon NJ 08889",
    "addr:housenumber":"1402",
    "addr:postcode":"08889",
    "addr:street":"S Branch Dr",
    "iso:country":"US",
    "sg:address":"1402 S Branch Dr",
    "sg:city":"Lebanon",
    "sg:classifiers":[
        {
            "category":"Home & Garden",
            "subcategory":"Home Furnishings",
            "type":"Retail Goods"
        }
    ],
    "sg:phone":"+1   ",
    "sg:postcode":"08889",
    "sg:province":"NJ",
    "wof:name":"Windows Etc",
    "wof:placetype":"venue"
},
  "geometry": {"coordinates":[-74.77752599999999,40.619516],"type":"Point"}
}