{
  "type": "Feature",
  "properties": {
    "addr:full":"22 Bentley Ct Hazlet NJ 07728",
    "addr:housenumber":"22",
    "addr:postcode":"07728",
    "addr:street":"Bentley Ct",
    "iso:country":"US",
    "sg:address":"22 Bentley Ct",
    "sg:city":"Hazlet",
    "sg:classifiers":[
        {
            "category":"Building & Trades",
            "subcategory":"Construction",
            "type":"Services"
        }
    ],
    "sg:phone":"+1 732 888 8392",
    "sg:postcode":"07728",
    "sg:province":"NJ",
    "sg:tags":[
        "contractor"
    ],
    "wof:name":"Daley Fence Co",
    "wof:placetype":"venue"
},
  "geometry": {"coordinates":[-74.273134,40.290692],"type":"Point"}
}