{
  "type": "Feature",
  "properties": {
    "addr:full":"672 Speedwell Ave Morris Plains NJ 07950",
    "addr:housenumber":"672",
    "addr:postcode":"07950",
    "addr:street":"Speedwell Ave",
    "iso:country":"US",
    "sg:address":"672 Speedwell Ave",
    "sg:city":"Morris Plains",
    "sg:classifiers":[
        {
            "category":"Personal",
            "subcategory":"Barber",
            "type":"Services"
        }
    ],
    "sg:phone":"+1 973 538 1000",
    "sg:postcode":"07950",
    "sg:province":"NJ",
    "wof:name":"Ryan's Clip Joint",
    "wof:placetype":"venue"
},
  "geometry": {"coordinates":[-74.47941299999999,40.82842],"type":"Point"}
}