{
  "type": "Feature",
  "properties": {
    "addr:full":"785 Central Ave New Providence NJ 07974",
    "addr:housenumber":"785",
    "addr:postcode":"07974",
    "addr:street":"Central Ave",
    "iso:country":"US",
    "sg:address":"785 Central Ave",
    "sg:city":"New Providence",
    "sg:classifiers":[
        {
            "category":"Banks & Credit Unions",
            "subcategory":"Bank",
            "type":"Services"
        }
    ],
    "sg:phone":"+1 908 771 0300",
    "sg:postcode":"07974",
    "sg:province":"NJ",
    "wof:name":"Advanced Financial Services Federal Credit Union",
    "wof:placetype":"venue"
},
  "geometry": {"coordinates":[-74.41529800000001,40.696899],"type":"Point"}
}