{
  "type": "Feature",
  "properties": {
    "iso:country":"US",
    "sg:address":"296 Herbert St",
    "sg:city":"Perth Amboy",
    "sg:classifiers":[
        {
            "category":"Professional",
            "subcategory":"Business Services",
            "type":"Services"
        }
    ],
    "sg:phone":"+1 732 826 5242",
    "sg:postcode":"08861",
    "sg:province":"NJ",
    "sg:tags":[
        "shop",
        "lettering",
        "painting",
        "sign"
    ],
    "wof:name":"Beacon Signs",
    "wof:placetype":"venue"
},
  "geometry": {"coordinates":[-74.28482,40.511554],"type":"Point"}
}