{
  "type": "Feature",
  "properties": {
    "iso:country":"US",
    "sg:address":"205 S Atlantic Ave",
    "sg:city":"Haddonfield",
    "sg:classifiers":[
        {
            "category":"Building & Trades",
            "subcategory":"Construction",
            "type":"Services"
        }
    ],
    "sg:phone":"+1 856 354 6046",
    "sg:postcode":"08033",
    "sg:province":"NJ",
    "sg:tags":[
        "contractor"
    ],
    "wof:name":"All Surface Plastering Inc",
    "wof:placetype":"venue"
},
  "geometry": {"coordinates":[-75.033765,39.891424],"type":"Point"}
}