{
  "type": "Feature",
  "properties": {
    "iso:country":"US",
    "sg:address":"42 Locust Ave Ste 6",
    "sg:city":"Wallington",
    "sg:classifiers":[
        {
            "category":"Health Services",
            "subcategory":"Doctor",
            "type":"Services"
        }
    ],
    "sg:phone":"+1 973 777 0340",
    "sg:postcode":"07057",
    "sg:province":"NJ",
    "wof:name":"Rozdeba Joseph MD",
    "wof:placetype":"venue"
},
  "geometry": {"coordinates":[-74.11299200000001,40.850856],"type":"Point"}
}