{
  "type": "Feature",
  "properties": {
    "addr:full":"1027 Route 70 Whiting NJ 08759",
    "addr:housenumber":"1027",
    "addr:postcode":"08759",
    "addr:street":"Route 70",
    "iso:country":"US",
    "sg:address":"1027 Route 70",
    "sg:city":"Whiting",
    "sg:classifiers":[
        {
            "category":"Cafe",
            "type":"Food & Drink"
        }
    ],
    "sg:menulink":"http://www.allmenus.com/nj/manchester/27486-cafe-napoli/menu/",
    "sg:phone":"+1 732 657 4200",
    "sg:postcode":"08759",
    "sg:province":"NJ",
    "sg:tags":[
        "italian"
    ],
    "wof:name":"Cafe Napoli",
    "wof:placetype":"venue"
},
  "geometry": {"coordinates":[-74.384747,39.965798],"type":"Point"}
}