{
  "type": "Feature",
  "properties": {
    "addr:full":"1426 State Rt 23 Butler NJ 07405",
    "addr:housenumber":"1426",
    "addr:postcode":"07405",
    "addr:street":"State Rt 23",
    "iso:country":"US",
    "sg:address":"1426 State Rt 23",
    "sg:city":"Butler",
    "sg:classifiers":[
        {
            "category":"Shopping",
            "subcategory":"Optician",
            "type":"Retail Goods"
        }
    ],
    "sg:phone":"+1 973 838 6666",
    "sg:postcode":"07405",
    "sg:province":"NJ",
    "sg:tags":[
        "eyewear"
    ],
    "wof:name":"Hillcrest Opticians",
    "wof:placetype":"venue"
},
  "geometry": {"coordinates":[-74.35410299999999,40.998699],"type":"Point"}
}