{
  "type": "Feature",
  "properties": {
    "iso:country":"US",
    "sg:address":"15 Albany Rd",
    "sg:city":"Marlton",
    "sg:classifiers":[
        {
            "category":"Retail",
            "subcategory":"Photofinishing",
            "type":"Services"
        }
    ],
    "sg:phone":"+1 856 424 1602",
    "sg:postcode":"08053",
    "sg:province":"NJ",
    "sg:tags":[
        "laboratory"
    ],
    "wof:name":"Feeny Foto",
    "wof:placetype":"venue"
},
  "geometry": {"coordinates":[-74.91500000000001,39.898094],"type":"Point"}
}