{
  "type": "Feature",
  "properties": {
    "addr:full":"4340 Route 130 N Willingboro NJ 08046",
    "addr:housenumber":"4340",
    "addr:postcode":"08046",
    "addr:street":"Route 130 N",
    "iso:country":"US",
    "sg:address":"4340 Route 130 N",
    "sg:city":"Willingboro",
    "sg:classifiers":[
        {
            "category":"Shopping Center",
            "type":"Public Place"
        }
    ],
    "sg:postcode":"08046",
    "sg:province":"NJ",
    "sg:website":"www.thegrandmarketplace.com/",
    "wof:name":"Grand Market Place",
    "wof:placetype":"venue"
},
  "geometry": {"coordinates":[-74.89727499999999,40.04863],"type":"Point"}
}