{
  "type": "Feature",
  "properties": {
    "iso:country":"US",
    "sg:address":"7 Cooper Ave",
    "sg:city":"Marlton",
    "sg:classifiers":[
        {
            "category":"Home & Garden",
            "subcategory":"Building Materials",
            "type":"Retail Goods"
        }
    ],
    "sg:phone":"+1 856 983 0805",
    "sg:postcode":"08053",
    "sg:province":"NJ",
    "sg:tags":[
        "windows"
    ],
    "wof:name":"Window Treatment Showroom",
    "wof:placetype":"venue"
},
  "geometry": {"coordinates":[-74.918537,39.893603],"type":"Point"}
}