{
  "type": "Feature",
  "properties": {
    "addr:full":"561 Winding River Rd Brick NJ 08724",
    "addr:housenumber":"561",
    "addr:postcode":"08724",
    "addr:street":"Winding River Rd",
    "iso:country":"US",
    "sg:address":"561 Winding River Rd",
    "sg:city":"Brick",
    "sg:classifiers":[
        {
            "category":"Building & Trades",
            "subcategory":"Construction",
            "type":"Services"
        }
    ],
    "sg:phone":"+1 732 785 1922",
    "sg:postcode":"08724",
    "sg:province":"NJ",
    "sg:tags":[
        "house"
    ],
    "wof:name":"Norton Enterprises Inc",
    "wof:placetype":"venue"
},
  "geometry": {"coordinates":[-74.10018599999999,40.111897],"type":"Point"}
}