{
  "type": "Feature",
  "properties": {
    "addr:full":"8000 Midlantic Dr Mount Laurel NJ 08054",
    "addr:postcode":"8000;08054",
    "addr:street":"Midlantic Dr",
    "iso:country":"US",
    "sg:address":"8000 Midlantic Dr",
    "sg:city":"Mount Laurel",
    "sg:classifiers":[
        {
            "category":"Insurance",
            "subcategory":"Health Insurance",
            "type":"Services"
        }
    ],
    "sg:phone":"+1   ",
    "sg:postcode":"08054",
    "sg:province":"NJ",
    "sg:tags":[
        "care"
    ],
    "wof:name":"Amerihealth",
    "wof:placetype":"venue"
},
  "geometry": {"coordinates":[-74.919005,39.963601],"type":"Point"}
}