{
  "type": "Feature",
  "properties": {
    "iso:country":"US",
    "sg:address":"2426 Arbor Ct",
    "sg:city":"Mays Landing",
    "sg:classifiers":[
        {
            "category":"Arts & Performance",
            "subcategory":"Theater",
            "type":"Entertainment"
        }
    ],
    "sg:phone":"+1   ",
    "sg:postcode":"08330",
    "sg:province":"NJ",
    "sg:tags":[
        "group"
    ],
    "wof:name":"Sound Emotions",
    "wof:placetype":"venue"
},
  "geometry": {"coordinates":[-74.651354,39.454355],"type":"Point"}
}