{
  "type": "Feature",
  "properties": {
    "addr:full":"37 Woodland Rd Roseland NJ 07068",
    "addr:housenumber":"37",
    "addr:postcode":"07068",
    "addr:street":"Woodland Rd",
    "iso:country":"US",
    "sg:address":"37 Woodland Rd",
    "sg:city":"Roseland",
    "sg:classifiers":[
        {
            "category":"Sports & Exercise",
            "subcategory":"Gym",
            "type":"Entertainment"
        }
    ],
    "sg:phone":"+1   ",
    "sg:postcode":"07068",
    "sg:province":"NJ",
    "sg:tags":[
        "fitness",
        "physical",
        "facility"
    ],
    "wof:name":"Butchs Bodyshop",
    "wof:placetype":"venue"
},
  "geometry": {"coordinates":[-74.300633,40.826707],"type":"Point"}
}