{
  "type": "Feature",
  "properties": {
    "iso:country":"US",
    "sg:address":"13 Morningside Cir",
    "sg:city":"Little Falls",
    "sg:classifiers":[
        {
            "category":"Organizations",
            "subcategory":"Membership Organization",
            "type":"Services"
        }
    ],
    "sg:phone":"+1 973 785 4275",
    "sg:postcode":"07424",
    "sg:province":"NJ",
    "wof:name":"Rick Miedema Scholarship",
    "wof:placetype":"venue"
},
  "geometry": {"coordinates":[-74.215414,40.873621],"type":"Point"}
}