{
  "type": "Feature",
  "properties": {
    "addr:full":"543 Bath Ave Long Branch NJ 07740",
    "addr:housenumber":"543",
    "addr:postcode":"07740",
    "addr:street":"Bath Ave",
    "iso:country":"US",
    "sg:address":"543 Bath Ave",
    "sg:city":"Long Branch",
    "sg:classifiers":[
        {
            "category":"Professional",
            "type":"Services"
        }
    ],
    "sg:phone":"+1   ",
    "sg:postcode":"07740",
    "sg:province":"NJ",
    "wof:name":"Lozanos",
    "wof:placetype":"venue"
},
  "geometry": {"coordinates":[-74.00193299999999,40.298899],"type":"Point"}
}