{
  "type": "Feature",
  "properties": {
    "addr:full":"186 Morris St Morristown NJ 07960",
    "addr:housenumber":"186",
    "addr:postcode":"07960",
    "addr:street":"Morris St",
    "iso:country":"US",
    "sg:address":"186 Morris St",
    "sg:city":"Morristown",
    "sg:classifiers":[
        {
            "category":"Real Estate",
            "subcategory":"Developer",
            "type":"Services"
        }
    ],
    "sg:phone":"+1 973 267 4944",
    "sg:postcode":"07960",
    "sg:province":"NJ",
    "wof:name":"Matzel & Mumford",
    "wof:placetype":"venue"
},
  "geometry": {"coordinates":[-74.470215,40.795557],"type":"Point"}
}