{
  "type": "Feature",
  "properties": {
    "addr:full":"270 US Highway 46 Denville NJ 07834",
    "addr:housenumber":"270",
    "addr:postcode":"07834",
    "addr:street":"Us Highway 46",
    "iso:country":"US",
    "sg:address":"270 US Highway 46",
    "sg:city":"Denville",
    "sg:classifiers":[
        {
            "category":"Autos & Motor Vehicles",
            "subcategory":"Fuel & Gas Station",
            "type":"Retail Goods"
        }
    ],
    "sg:phone":"+1 973 627 0068",
    "sg:postcode":"07834",
    "sg:province":"NJ",
    "sg:website":"www.shell.com",
    "wof:name":"Shell Gas Station",
    "wof:placetype":"venue"
},
  "geometry": {"coordinates":[-74.49028199999999,40.897367],"type":"Point"}
}