{
  "type": "Feature",
  "properties": {
    "iso:country":"US",
    "sg:address":"3 High Ct",
    "sg:city":"High Bridge",
    "sg:classifiers":[
        {
            "category":"Communications",
            "subcategory":"Film & Video Production",
            "type":"Services"
        }
    ],
    "sg:phone":"+1 908 638 6070",
    "sg:postcode":"08829",
    "sg:province":"NJ",
    "sg:tags":[
        "audio"
    ],
    "wof:name":"TMW Enterprises",
    "wof:placetype":"venue"
},
  "geometry": {"coordinates":[-74.878263,40.672159],"type":"Point"}
}