{
  "type": "Feature",
  "properties": {
    "iso:country":"US",
    "sg:address":"61 Goble St",
    "sg:city":"Newark",
    "sg:classifiers":[
        {
            "category":"Building & Trades",
            "subcategory":"Construction",
            "type":"Services"
        }
    ],
    "sg:phone":"+1 973 621 0010",
    "sg:postcode":"07114",
    "sg:province":"NJ",
    "sg:tags":[
        "contractor"
    ],
    "wof:name":"Nesbith Construction Inc",
    "wof:placetype":"venue"
},
  "geometry": {"coordinates":[-74.174187,40.719484],"type":"Point"}
}