{
  "type": "Feature",
  "properties": {
    "addr:full":"451 E Bay Ave Barnegat NJ 08005",
    "addr:housenumber":"451",
    "addr:postcode":"08005",
    "addr:street":"E Bay Ave",
    "iso:country":"US",
    "sg:address":"451 E Bay Ave",
    "sg:city":"Barnegat",
    "sg:classifiers":[
        {
            "category":"Restaurant",
            "type":"Food & Drink"
        }
    ],
    "sg:phone":"+1 609 607 9240",
    "sg:postcode":"08005",
    "sg:province":"NJ",
    "wof:name":"Osaka At Sun Harbor Marina",
    "wof:placetype":"venue"
},
  "geometry": {"coordinates":[-74.195746,39.748597],"type":"Point"}
}