{
  "type": "Feature",
  "properties": {
    "iso:country":"US",
    "sg:address":"302 72nd St",
    "sg:city":"North Bergen",
    "sg:classifiers":[
        {
            "category":"Building & Trades",
            "subcategory":"Cleaning & Sanitation",
            "type":"Services"
        }
    ],
    "sg:phone":"+1 201 295 0037",
    "sg:postcode":"07047",
    "sg:province":"NJ",
    "sg:tags":[
        "janitor"
    ],
    "wof:name":"New Concept Env Cleaning Corp",
    "wof:placetype":"venue"
},
  "geometry": {"coordinates":[-74.007983,40.796493],"type":"Point"}
}