{
  "type": "Feature",
  "properties": {
    "addr:full":"129 Paterson Ave Little Falls NJ 07424",
    "addr:housenumber":"129",
    "addr:postcode":"07424",
    "addr:street":"Paterson Ave",
    "iso:country":"US",
    "sg:address":"129 Paterson Ave",
    "sg:city":"Little Falls",
    "sg:classifiers":[
        {
            "category":"Manufacturing",
            "subcategory":"Tools & Machinery",
            "type":"Manufacturing & Wholesale Goods"
        }
    ],
    "sg:phone":"+1 973 785 9254",
    "sg:postcode":"07424",
    "sg:province":"NJ",
    "sg:tags":[
        "shop",
        "repair",
        "mfg",
        "jobbing",
        "hardware",
        "machine"
    ],
    "wof:name":"Taurus Precision Inc",
    "wof:placetype":"venue"
},
  "geometry": {"coordinates":[-74.22305299999999,40.88491],"type":"Point"}
}