{
  "type": "Feature",
  "properties": {
    "addr:full":"117 Fort Lee Rd Leonia NJ 07605",
    "addr:housenumber":"117",
    "addr:postcode":"07605",
    "addr:street":"Fort Lee Rd",
    "iso:country":"US",
    "sg:address":"117 Fort Lee Rd",
    "sg:city":"Leonia",
    "sg:classifiers":[
        {
            "category":"Wholesale",
            "subcategory":"Groceries",
            "type":"Manufacturing & Wholesale Goods"
        }
    ],
    "sg:phone":"+1 201 592 5950",
    "sg:postcode":"07605",
    "sg:province":"NJ",
    "sg:tags":[
        "pasta",
        "import",
        "olive",
        "oil"
    ],
    "wof:name":"Agrusa Inc",
    "wof:placetype":"venue"
},
  "geometry": {"coordinates":[-73.993139,40.864622],"type":"Point"}
}