{
  "type": "Feature",
  "properties": {
    "iso:country":"US",
    "sg:address":"1707 State Route 31",
    "sg:city":"Clinton",
    "sg:classifiers":[
        {
            "category":"Autos & Motor Vehicles",
            "subcategory":"Auto Supplies",
            "type":"Retail Goods"
        }
    ],
    "sg:phone":"+1 908 735 0055",
    "sg:postcode":"08809",
    "sg:province":"NJ",
    "sg:tags":[
        "tire"
    ],
    "wof:name":"Scott's Pro Automotive Llc",
    "wof:placetype":"venue"
},
  "geometry": {"coordinates":[-74.91123399999999,40.647359],"type":"Point"}
}