{
  "type": "Feature",
  "properties": {
    "iso:country":"US",
    "sg:address":"6 Stegman Pl",
    "sg:city":"Jersey City",
    "sg:classifiers":[
        {
            "category":"Professional",
            "subcategory":"Computer Services",
            "type":"Services"
        }
    ],
    "sg:phone":"+1   ",
    "sg:postcode":"07305",
    "sg:province":"NJ",
    "sg:tags":[
        "related"
    ],
    "wof:name":"Rainbows Modern Tech",
    "wof:placetype":"venue"
},
  "geometry": {"coordinates":[-74.091751,40.709904],"type":"Point"}
}