{
  "type": "Feature",
  "properties": {
    "iso:country":"US",
    "sg:address":"504 Sunset Ter",
    "sg:city":"Ridgefield",
    "sg:classifiers":[
        {
            "category":"Professional",
            "subcategory":"Lawyer & Legal Services",
            "type":"Services"
        }
    ],
    "sg:phone":"+1 201 313 8600",
    "sg:postcode":"07657",
    "sg:province":"NJ",
    "wof:name":"Servis Susan ESQ",
    "wof:placetype":"venue"
},
  "geometry": {"coordinates":[-73.997704,40.8228],"type":"Point"}
}