{
  "type": "Feature",
  "properties": {
    "addr:full":"1501 Rahway Rd Scotch Plains NJ 07076",
    "addr:housenumber":"1501",
    "addr:postcode":"07076",
    "addr:street":"Rahway Rd",
    "iso:country":"US",
    "sg:address":"1501 Rahway Rd",
    "sg:city":"Scotch Plains",
    "sg:classifiers":[
        {
            "category":"Arts & Performance",
            "subcategory":"Theater",
            "type":"Entertainment"
        }
    ],
    "sg:phone":"+1 908 620 0668",
    "sg:postcode":"07076",
    "sg:province":"NJ",
    "sg:tags":[
        "group"
    ],
    "wof:name":"Output Music LLC",
    "wof:placetype":"venue"
},
  "geometry": {"coordinates":[-74.38173500000001,40.609036],"type":"Point"}
}