{
  "type": "Feature",
  "properties": {
    "iso:country":"US",
    "sg:address":"600 Meadowlands Pkwy",
    "sg:city":"Secaucus",
    "sg:classifiers":[
        {
            "category":"Building & Trades",
            "subcategory":"Construction",
            "type":"Services"
        }
    ],
    "sg:phone":"+1 201 271 1137",
    "sg:postcode":"07094",
    "sg:province":"NJ",
    "sg:tags":[
        "contractor"
    ],
    "wof:name":"Patti Roofing",
    "wof:placetype":"venue"
},
  "geometry": {"coordinates":[-74.081641,40.779007],"type":"Point"}
}