{
  "type": "Feature",
  "properties": {
    "iso:country":"US",
    "sg:address":"23 Commerce Rd",
    "sg:city":"Fairfield",
    "sg:classifiers":[
        {
            "category":"Building & Trades",
            "subcategory":"Construction",
            "type":"Services"
        }
    ],
    "sg:phone":"+1 973 882 7377",
    "sg:postcode":"07004",
    "sg:province":"NJ",
    "sg:tags":[
        "stone",
        "limestone",
        "installs",
        "contractor",
        "prefabricated",
        "mfr",
        "setting",
        "granite",
        "marble"
    ],
    "wof:name":"Stone Truss Systems Inc",
    "wof:placetype":"venue"
},
  "geometry": {"coordinates":[-74.31699399999999,40.871773],"type":"Point"}
}