{
  "type": "Feature",
  "properties": {
    "iso:country":"US",
    "sg:address":"23 Arlington Rd",
    "sg:city":"Cranford",
    "sg:classifiers":[
        {
            "category":"Arts & Performance",
            "subcategory":"Theater",
            "type":"Entertainment"
        }
    ],
    "sg:phone":"+1 908 419 4775",
    "sg:postcode":"07016",
    "sg:province":"NJ",
    "sg:tags":[
        "magician"
    ],
    "wof:name":"Henry Carlyle Entertainment",
    "wof:placetype":"venue"
},
  "geometry": {"coordinates":[-74.297164,40.6591],"type":"Point"}
}