{
  "type": "Feature",
  "properties": {
    "addr:full":"92 Liberty St Bloomfield NJ 07003",
    "addr:housenumber":"92",
    "addr:postcode":"07003",
    "addr:street":"Liberty St",
    "iso:country":"US",
    "sg:address":"92 Liberty St",
    "sg:city":"Bloomfield",
    "sg:classifiers":[
        {
            "category":"Building & Trades",
            "subcategory":"Construction",
            "type":"Services"
        }
    ],
    "sg:phone":"+1 973 429 3373",
    "sg:postcode":"07003",
    "sg:province":"NJ",
    "sg:tags":[
        "house"
    ],
    "wof:name":"Dimichele Construction Inc",
    "wof:placetype":"venue"
},
  "geometry": {"coordinates":[-74.190022,40.795332],"type":"Point"}
}