{
  "type": "Feature",
  "properties": {
    "iso:country":"US",
    "sg:address":"224 State St",
    "sg:city":"Camden",
    "sg:classifiers":[
        {
            "category":"Bars & Pubs",
            "type":"Food & Drink"
        }
    ],
    "sg:phone":"+1   ",
    "sg:postcode":"08102",
    "sg:province":"NJ",
    "sg:tags":[
        "drinking"
    ],
    "wof:name":"State Bar",
    "wof:placetype":"venue"
},
  "geometry": {"coordinates":[-75.121747,39.953333],"type":"Point"}
}