{
  "type": "Feature",
  "properties": {
    "addr:full":"6 Trudy Dr Lodi NJ 07644",
    "addr:housenumber":"6",
    "addr:postcode":"07644",
    "addr:street":"Trudy Dr",
    "iso:country":"US",
    "sg:address":"6 Trudy Dr",
    "sg:city":"Lodi",
    "sg:classifiers":[
        {
            "category":"Shopping",
            "subcategory":"Pharmacy",
            "type":"Retail Goods"
        }
    ],
    "sg:phone":"+1   ",
    "sg:postcode":"07644",
    "sg:province":"NJ",
    "wof:name":"Medicine Man Inc",
    "wof:placetype":"venue"
},
  "geometry": {"coordinates":[-74.080111,40.890248],"type":"Point"}
}