{
  "type": "Feature",
  "properties": {
    "iso:country":"US",
    "sg:address":"85 State Rte 27",
    "sg:city":"Edison",
    "sg:classifiers":[
        {
            "category":"Shopping",
            "subcategory":"Clothing, Apparel, & Fashions",
            "type":"Retail Goods"
        }
    ],
    "sg:phone":"+1 732 321 9090",
    "sg:postcode":"08820",
    "sg:province":"NJ",
    "sg:tags":[
        "swimwear",
        "accessory"
    ],
    "wof:name":"Sun Your Buns 2 LLC",
    "wof:placetype":"venue"
},
  "geometry": {"coordinates":[-74.34172599999999,40.558352],"type":"Point"}
}