{
  "type": "Feature",
  "properties": {
    "addr:full":"121 S Day St Orange NJ 07050",
    "addr:housenumber":"121",
    "addr:postcode":"07050",
    "addr:street":"S Day St",
    "iso:country":"US",
    "sg:address":"121 S Day St",
    "sg:city":"Orange",
    "sg:classifiers":[
        {
            "category":"Building & Trades",
            "subcategory":"Construction",
            "type":"Services"
        }
    ],
    "sg:phone":"+1 973 674 8868",
    "sg:postcode":"07050",
    "sg:province":"NJ",
    "sg:tags":[
        "railing"
    ],
    "wof:name":"Weld All Welding & Iron Works",
    "wof:placetype":"venue"
},
  "geometry": {"coordinates":[-74.232001,40.769396],"type":"Point"}
}