{
  "type": "Feature",
  "properties": {
    "addr:full":"2 Peach Tree Hill Rd Livingston NJ 07039",
    "addr:housenumber":"2",
    "addr:postcode":"07039",
    "addr:street":"Peach Tree Hill Rd",
    "iso:country":"US",
    "sg:address":"2 Peach Tree Hill Rd",
    "sg:city":"Livingston",
    "sg:classifiers":[
        {
            "category":"Professional",
            "type":"Services"
        }
    ],
    "sg:phone":"+1 973 740 0160",
    "sg:postcode":"07039",
    "sg:province":"NJ",
    "sg:tags":[
        "establishment"
    ],
    "wof:name":"Lehman Brothers",
    "wof:placetype":"venue"
},
  "geometry": {"coordinates":[-74.362127,40.773047],"type":"Point"}
}