{
  "type": "Feature",
  "properties": {
    "addr:full":"14 Parkview Dr Succasunna NJ 07876",
    "addr:housenumber":"14",
    "addr:postcode":"07876",
    "addr:street":"Parkview Dr",
    "iso:country":"US",
    "sg:address":"14 Parkview Dr",
    "sg:city":"Succasunna",
    "sg:classifiers":[
        {
            "category":"Wholesale",
            "subcategory":"Computers",
            "type":"Manufacturing & Wholesale Goods"
        }
    ],
    "sg:phone":"+1 973 335 7881",
    "sg:postcode":"07876",
    "sg:province":"NJ",
    "sg:tags":[
        "industry",
        "representative",
        "for",
        "manufacturer"
    ],
    "wof:name":"CTS",
    "wof:placetype":"venue"
},
  "geometry": {"coordinates":[-74.673877,40.83872],"type":"Point"}
}