{
  "type": "Feature",
  "properties": {
    "iso:country":"US",
    "sg:address":"3601 Boardwalk",
    "sg:city":"Wildwood",
    "sg:classifiers":[
        {
            "category":"Recreation",
            "subcategory":"Amusement Park",
            "type":"Entertainment"
        }
    ],
    "sg:phone":"+1 609 729 3100",
    "sg:postcode":"08260",
    "sg:province":"NJ",
    "wof:name":"Carousels Inc",
    "wof:placetype":"venue"
},
  "geometry": {"coordinates":[-74.81123599999999,38.98647],"type":"Point"}
}