{
  "type": "Feature",
  "properties": {
    "addr:full":"439 9th St Palisades Park NJ 07650",
    "addr:housenumber":"439",
    "addr:postcode":"07650",
    "addr:street":"9Th St",
    "iso:country":"US",
    "sg:address":"439 9th St",
    "sg:city":"Palisades Park",
    "sg:classifiers":[
        {
            "category":"Professional",
            "subcategory":"Detective & Security Services",
            "type":"Services"
        }
    ],
    "sg:phone":"+1   ",
    "sg:postcode":"07650",
    "sg:province":"NJ",
    "sg:tags":[
        "system"
    ],
    "wof:name":"Alltech Security Systems Inc",
    "wof:placetype":"venue"
},
  "geometry": {"coordinates":[-73.986514,40.846403],"type":"Point"}
}