{
  "type": "Feature",
  "properties": {
    "addr:full":"489 Fairview Ave Orange NJ 07050",
    "addr:housenumber":"489",
    "addr:postcode":"07050",
    "addr:street":"Fairview Ave",
    "iso:country":"US",
    "sg:address":"489 Fairview Ave",
    "sg:city":"Orange",
    "sg:classifiers":[
        {
            "category":"Building & Trades",
            "subcategory":"Electrical",
            "type":"Services"
        }
    ],
    "sg:phone":"+1 973 673 7651",
    "sg:postcode":"07050",
    "sg:province":"NJ",
    "sg:tags":[
        "electric",
        "contractor"
    ],
    "wof:name":"Duval Electric Svc",
    "wof:placetype":"venue"
},
  "geometry": {"coordinates":[-74.24450899999999,40.763065],"type":"Point"}
}