{
  "type": "Feature",
  "properties": {
    "iso:country":"US",
    "sg:address":"2290 US Hwy 22",
    "sg:city":"Union",
    "sg:classifiers":[
        {
            "category":"Shopping",
            "subcategory":"Jewelry",
            "type":"Retail Goods"
        }
    ],
    "sg:phone":"+1 908 964 8900",
    "sg:postcode":"07083",
    "sg:province":"NJ",
    "sg:tags":[
        "jeweler"
    ],
    "wof:name":"Zaz Jewelry Inc",
    "wof:placetype":"venue"
},
  "geometry": {"coordinates":[-74.28762399999999,40.691114],"type":"Point"}
}