{
  "type": "Feature",
  "properties": {
    "addr:full":"11 Hancock Dr Florham Park NJ 07932",
    "addr:housenumber":"11",
    "addr:postcode":"07932",
    "addr:street":"Hancock Dr",
    "iso:country":"US",
    "sg:address":"11 Hancock Dr",
    "sg:city":"Florham Park",
    "sg:classifiers":[
        {
            "category":"Banks & Credit Unions",
            "subcategory":"Investment Brokerage",
            "type":"Services"
        }
    ],
    "sg:phone":"+1   ",
    "sg:postcode":"07932",
    "sg:province":"NJ",
    "sg:tags":[
        "security"
    ],
    "wof:name":"Heraeus Investment Corp",
    "wof:placetype":"venue"
},
  "geometry": {"coordinates":[-74.402308,40.775157],"type":"Point"}
}