{
  "type": "Feature",
  "properties": {
    "addr:full":"112 E Spring Valley Ave Maywood NJ 07607",
    "addr:housenumber":"112",
    "addr:postcode":"07607",
    "addr:street":"E Spring Valley Ave",
    "iso:country":"US",
    "sg:address":"112 E Spring Valley Ave",
    "sg:city":"Maywood",
    "sg:classifiers":[
        {
            "category":"Organizations",
            "subcategory":"Religious Organization",
            "type":"Services"
        }
    ],
    "sg:phone":"+1 201 843 7028",
    "sg:postcode":"07607",
    "sg:province":"NJ",
    "sg:tags":[
        "clergy"
    ],
    "wof:name":"Robert Buche",
    "wof:placetype":"venue"
},
  "geometry": {"coordinates":[-74.054363,40.910369],"type":"Point"}
}