{
  "type": "Feature",
  "properties": {
    "addr:full":"420 Forest Rd Villas NJ 08251",
    "addr:housenumber":"420",
    "addr:postcode":"08251",
    "addr:street":"Forest Rd",
    "iso:country":"US",
    "sg:address":"420 Forest Rd",
    "sg:city":"Villas",
    "sg:classifiers":[
        {
            "category":"Professional",
            "type":"Services"
        }
    ],
    "sg:phone":"+1   ",
    "sg:postcode":"08251",
    "sg:province":"NJ",
    "wof:name":"Preston John & Sons",
    "wof:placetype":"venue"
},
  "geometry": {"coordinates":[-74.95152899999999,38.998579],"type":"Point"}
}