{
  "type": "Feature",
  "properties": {
    "iso:country":"US",
    "sg:address":"171 Ridgedale Ave",
    "sg:city":"Florham Park",
    "sg:classifiers":[
        {
            "category":"Health Services",
            "subcategory":"Chiropractor",
            "type":"Services"
        }
    ],
    "sg:phone":"+1   ",
    "sg:postcode":"07932",
    "sg:province":"NJ",
    "wof:name":"Total Health Physcl MD Rehab",
    "wof:placetype":"venue"
},
  "geometry": {"coordinates":[-74.392027,40.786576],"type":"Point"}
}