{
  "type": "Feature",
  "properties": {
    "iso:country":"US",
    "sg:address":"720 Monroe St Ste C414",
    "sg:city":"Hoboken",
    "sg:classifiers":[
        {
            "category":"Travel",
            "subcategory":"Travel Agent",
            "type":"Entertainment"
        }
    ],
    "sg:phone":"+1 212 986 3800",
    "sg:postcode":"07030",
    "sg:province":"NJ",
    "sg:website":"www.euroquest.com",
    "wof:name":"Euroquest",
    "wof:placetype":"venue"
},
  "geometry": {"coordinates":[-74.037724,40.746997],"type":"Point"}
}