{
  "type": "Feature",
  "properties": {
    "addr:full":"23 Birch Ridge Rd Blairstown NJ 07825",
    "addr:housenumber":"23",
    "addr:postcode":"07825",
    "addr:street":"Birch Ridge Rd",
    "iso:country":"US",
    "sg:address":"23 Birch Ridge Rd",
    "sg:city":"Blairstown",
    "sg:classifiers":[
        {
            "category":"Organizations",
            "subcategory":"Community Association",
            "type":"Services"
        }
    ],
    "sg:phone":"+1   ",
    "sg:postcode":"07825",
    "sg:province":"NJ",
    "sg:tags":[
        "trailer"
    ],
    "wof:name":"YMCA Camp Ralph S Mason Inc",
    "wof:placetype":"venue"
},
  "geometry": {"coordinates":[-74.94950300000001,41.036435],"type":"Point"}
}