{
  "type": "Feature",
  "properties": {
    "addr:full":"390 Burnt Mills Rd Branchburg NJ 08876",
    "addr:housenumber":"390",
    "addr:postcode":"08876",
    "addr:street":"Burnt Mills Rd",
    "iso:country":"US",
    "sg:address":"390 Burnt Mills Rd",
    "sg:city":"Branchburg",
    "sg:classifiers":[
        {
            "category":"Retail",
            "subcategory":"Auto Repair",
            "type":"Services"
        }
    ],
    "sg:phone":"+1 908 725 6262",
    "sg:postcode":"08876",
    "sg:province":"NJ",
    "sg:tags":[
        "wrecker"
    ],
    "wof:name":"De Lucas Towing & Recovering",
    "wof:placetype":"venue"
},
  "geometry": {"coordinates":[-74.683358,40.615821],"type":"Point"}
}