{
  "type": "Feature",
  "properties": {
    "addr:full":"26 Old Chestnut Ridge Rd Montvale NJ 07645",
    "addr:housenumber":"26",
    "addr:postcode":"07645",
    "addr:street":"Old Chestnut Ridge Rd",
    "iso:country":"US",
    "sg:address":"26 Old Chestnut Ridge Rd",
    "sg:city":"Montvale",
    "sg:classifiers":[
        {
            "category":"Professional",
            "subcategory":"Management & Consulting",
            "type":"Services"
        }
    ],
    "sg:phone":"+1 201 391 4139",
    "sg:postcode":"07645",
    "sg:province":"NJ",
    "wof:name":"Greybarn",
    "wof:placetype":"venue"
},
  "geometry": {"coordinates":[-74.06963399999999,41.063897],"type":"Point"}
}