{
  "type": "Feature",
  "properties": {
    "iso:country":"US",
    "sg:address":"51 Winding Way",
    "sg:city":"Cedar Grove",
    "sg:classifiers":[
        {
            "category":"Organizations",
            "subcategory":"Religious Organization",
            "type":"Services"
        }
    ],
    "sg:phone":"+1 973 857 2176",
    "sg:postcode":"07009",
    "sg:province":"NJ",
    "wof:name":"Storbeck C R Rev",
    "wof:placetype":"venue"
},
  "geometry": {"coordinates":[-74.236099,40.854401],"type":"Point"}
}