{
  "type": "Feature",
  "properties": {
    "iso:country":"US",
    "sg:address":"108 Homecrest Ave",
    "sg:city":"Trenton",
    "sg:classifiers":[
        {
            "category":"Building & Trades",
            "subcategory":"Plumbing",
            "type":"Services"
        }
    ],
    "sg:phone":"+1 609 883 9572",
    "sg:postcode":"08638",
    "sg:province":"NJ",
    "sg:tags":[
        "contractor"
    ],
    "wof:name":"Hillman Heating Co",
    "wof:placetype":"venue"
},
  "geometry": {"coordinates":[-74.772476,40.24215],"type":"Point"}
}