{
  "type": "Feature",
  "properties": {
    "addr:full":"243 Burke Ave Woodbury NJ 08096",
    "addr:housenumber":"243",
    "addr:postcode":"08096",
    "addr:street":"Burke Ave",
    "iso:country":"US",
    "sg:address":"243 Burke Ave",
    "sg:city":"Woodbury",
    "sg:classifiers":[
        {
            "category":"Manufacturing",
            "subcategory":"Petroleum Products",
            "type":"Manufacturing & Wholesale Goods"
        },
        {
            "category":"Wholesale",
            "subcategory":"Petroleum",
            "type":"Manufacturing & Wholesale Goods"
        }
    ],
    "sg:phone":"+1 856 845 0218",
    "sg:postcode":"08096",
    "sg:province":"NJ",
    "sg:tags":[
        "manufacturer",
        "products-wholesale",
        "oils-petroleum"
    ],
    "wof:name":"Weavers Oil Co Inc",
    "wof:placetype":"venue"
},
  "geometry": {"coordinates":[-75.12240300000001,39.833214],"type":"Point"}
}