{
  "type": "Feature",
  "properties": {
    "iso:country":"US",
    "sg:address":"171 Coit St",
    "sg:city":"Irvington",
    "sg:classifiers":[
        {
            "category":"Building & Trades",
            "subcategory":"Construction",
            "type":"Services"
        }
    ],
    "sg:phone":"+1 973 374 6980",
    "sg:postcode":"07111",
    "sg:province":"NJ",
    "sg:tags":[
        "contractor"
    ],
    "wof:name":"Aluminum Tower Fence",
    "wof:placetype":"venue"
},
  "geometry": {"coordinates":[-74.225207,40.719938],"type":"Point"}
}