{
  "type": "Feature",
  "properties": {
    "iso:country":"US",
    "sg:address":"757 Rahway Ave",
    "sg:city":"Elizabeth",
    "sg:classifiers":[
        {
            "category":"Autos & Motor Vehicles",
            "subcategory":"Automobile Sales",
            "type":"Retail Goods"
        }
    ],
    "sg:phone":"+1   ",
    "sg:postcode":"07202",
    "sg:province":"NJ",
    "sg:tags":[
        "used"
    ],
    "wof:name":"Typhoon Motors Inc",
    "wof:placetype":"venue"
},
  "geometry": {"coordinates":[-74.23139999999999,40.655581],"type":"Point"}
}