{
  "type": "Feature",
  "properties": {
    "iso:country":"US",
    "sg:address":"2125 Maple View Ct",
    "sg:city":"Scotch Plains",
    "sg:classifiers":[
        {
            "category":"Professional",
            "subcategory":"Management & Consulting",
            "type":"Services"
        }
    ],
    "sg:phone":"+1   ",
    "sg:postcode":"07076",
    "sg:province":"NJ",
    "wof:name":"Focus Marketing Consulting",
    "wof:placetype":"venue"
},
  "geometry": {"coordinates":[-74.371168,40.641818],"type":"Point"}
}