{
  "type": "Feature",
  "properties": {
    "iso:country":"US",
    "sg:address":"11 Raymond Plz W",
    "sg:city":"Newark",
    "sg:classifiers":[
        {
            "category":"Shopping",
            "type":"Retail Goods"
        }
    ],
    "sg:phone":"+1 973 645 1945",
    "sg:postcode":"07102",
    "sg:province":"NJ",
    "sg:tags":[
        "perfume"
    ],
    "wof:name":"Gateway Cosmetics",
    "wof:placetype":"venue"
},
  "geometry": {"coordinates":[-74.165469,40.734232],"type":"Point"}
}