{
  "type": "Feature",
  "properties": {
    "addr:full":"10 Roberts Rd New Brunswick NJ 08901",
    "addr:housenumber":"10",
    "addr:postcode":"08901",
    "addr:street":"Roberts Rd",
    "iso:country":"US",
    "sg:address":"10 Roberts Rd",
    "sg:city":"New Brunswick",
    "sg:classifiers":[
        {
            "category":"Building & Trades",
            "subcategory":"Plumbing",
            "type":"Services"
        }
    ],
    "sg:phone":"+1 732 246 9900",
    "sg:postcode":"08901",
    "sg:province":"NJ",
    "sg:tags":[
        "mechanical",
        "contractor"
    ],
    "wof:name":"Ward Brothers Inc",
    "wof:placetype":"venue"
},
  "geometry": {"coordinates":[-74.400839,40.487215],"type":"Point"}
}