{
  "type": "Feature",
  "properties": {
    "iso:country":"US",
    "sg:address":"120 Midland Ave",
    "sg:city":"Kearny",
    "sg:classifiers":[
        {
            "category":"Utilities",
            "subcategory":"Mobile Phone",
            "type":"Services"
        },
        {
            "category":"Shopping",
            "type":"Retail Goods"
        }
    ],
    "sg:phone":"+1 201 991 6661",
    "sg:postcode":"07032",
    "sg:province":"NJ",
    "sg:tags":[
        "communications",
        "telephone",
        "cellular"
    ],
    "wof:name":"Business Center Plus",
    "wof:placetype":"venue"
},
  "geometry": {"coordinates":[-74.144329,40.770402],"type":"Point"}
}