{
  "type": "Feature",
  "properties": {
    "addr:full":"100 W Broad St Burlington NJ 08016",
    "addr:housenumber":"100",
    "addr:postcode":"08016",
    "addr:street":"W Broad St",
    "iso:country":"US",
    "sg:address":"100 W Broad St",
    "sg:city":"Burlington",
    "sg:classifiers":[
        {
            "category":"Retail",
            "subcategory":"Portrait Studio",
            "type":"Services"
        }
    ],
    "sg:phone":"+1 609 386 0592",
    "sg:postcode":"08016",
    "sg:province":"NJ",
    "sg:tags":[
        "commercial"
    ],
    "wof:name":"Torre Studios",
    "wof:placetype":"venue"
},
  "geometry": {"coordinates":[-74.86254,40.076409],"type":"Point"}
}