{
  "type": "Feature",
  "properties": {
    "addr:full":"200 Gregg St Lodi NJ 07644",
    "addr:housenumber":"200",
    "addr:postcode":"07644",
    "addr:street":"Gregg St",
    "iso:country":"US",
    "sg:address":"200 Gregg St",
    "sg:city":"Lodi",
    "sg:classifiers":[
        {
            "category":"Manufacturing",
            "subcategory":"Motor Vehicles & Parts",
            "type":"Manufacturing & Wholesale Goods"
        }
    ],
    "sg:phone":"+1 201 843 6401",
    "sg:postcode":"07644",
    "sg:province":"NJ",
    "sg:tags":[
        "mfg"
    ],
    "wof:name":"United Technologies Corp",
    "wof:placetype":"venue"
},
  "geometry": {"coordinates":[-74.069875,40.884699],"type":"Point"}
}