{
  "type": "Feature",
  "properties": {
    "addr:full":"1610 Calamus Pl Point Pleasant Beach NJ 08742",
    "addr:housenumber":"1610",
    "addr:postcode":"08742",
    "addr:street":"Calamus Pl",
    "iso:country":"US",
    "sg:address":"1610 Calamus Pl",
    "sg:city":"Point Pleasant Beach",
    "sg:classifiers":[
        {
            "category":"Building & Trades",
            "subcategory":"Plumbing",
            "type":"Services"
        }
    ],
    "sg:phone":"+1 732 892 3523",
    "sg:postcode":"08742",
    "sg:province":"NJ",
    "sg:tags":[
        "contractor"
    ],
    "wof:name":"Callander John",
    "wof:placetype":"venue"
},
  "geometry": {"coordinates":[-74.082973,40.067747],"type":"Point"}
}