{
  "type": "Feature",
  "properties": {
    "addr:full":"619 Amboy Ave Ste 1 Edison NJ 08837",
    "addr:housenumber":"619",
    "addr:postcode":"08837",
    "addr:street":"Amboy Ave Ste 1",
    "iso:country":"US",
    "sg:address":"619 Amboy Ave Ste 1",
    "sg:city":"Edison",
    "sg:classifiers":[
        {
            "category":"Health Services",
            "subcategory":"Dentist",
            "type":"Services"
        }
    ],
    "sg:phone":"+1 732 738 6555",
    "sg:postcode":"08837",
    "sg:province":"NJ",
    "wof:name":"Raritan Valley Oral & Maxillofacial Surgery PA",
    "wof:placetype":"venue"
},
  "geometry": {"coordinates":[-74.316931,40.529064],"type":"Point"}
}