{
  "type": "Feature",
  "properties": {
    "iso:country":"US",
    "sg:address":"41 Jackson Valley Rd",
    "sg:city":"Washington",
    "sg:classifiers":[
        {
            "category":"Education",
            "subcategory":"School",
            "type":"Public Place"
        }
    ],
    "sg:phone":"+1 908 689 3050",
    "sg:postcode":"07882",
    "sg:province":"NJ",
    "wof:name":"Warren Hills Senior High Schl",
    "wof:placetype":"venue"
},
  "geometry": {"coordinates":[-74.983812,40.771446],"type":"Point"}
}