{
  "type": "Feature",
  "properties": {
    "iso:country":"US",
    "sg:address":"250 E 17th St",
    "sg:city":"Paterson",
    "sg:classifiers":[
        {
            "category":"Professional",
            "subcategory":"Computer Services",
            "type":"Services"
        }
    ],
    "sg:phone":"+1   ",
    "sg:postcode":"07524",
    "sg:province":"NJ",
    "sg:tags":[
        "internet",
        "provider"
    ],
    "wof:name":"Digital Fusion Inc",
    "wof:placetype":"venue"
},
  "geometry": {"coordinates":[-74.153316,40.92982],"type":"Point"}
}