{
  "type": "Feature",
  "properties": {
    "addr:full":"228 Lalor St Trenton NJ 08611",
    "addr:housenumber":"228",
    "addr:postcode":"08611",
    "addr:street":"Lalor St",
    "iso:country":"US",
    "sg:address":"228 Lalor St",
    "sg:city":"Trenton",
    "sg:classifiers":[
        {
            "category":"Retail",
            "subcategory":"Car Wash",
            "type":"Services"
        }
    ],
    "sg:phone":"+1 609 394 8300",
    "sg:postcode":"08611",
    "sg:province":"NJ",
    "sg:tags":[
        "polishing",
        "washing"
    ],
    "wof:name":"Auto Valet Car Wash",
    "wof:placetype":"venue"
},
  "geometry": {"coordinates":[-74.75451099999999,40.198167],"type":"Point"}
}