{
  "type": "Feature",
  "properties": {
    "iso:country":"US",
    "sg:address":"741 Roseld Ave",
    "sg:city":"Asbury Park",
    "sg:classifiers":[
        {
            "category":"Professional",
            "subcategory":"Management & Consulting",
            "type":"Services"
        }
    ],
    "sg:phone":"+1   ",
    "sg:postcode":"07712",
    "sg:province":"NJ",
    "sg:tags":[
        "business"
    ],
    "wof:name":"Edward V Kolling Pp Aicp",
    "wof:placetype":"venue"
},
  "geometry": {"coordinates":[-74.026273,40.246575],"type":"Point"}
}