{
  "type": "Feature",
  "properties": {
    "addr:full":"10 Whittier Ave Trenton NJ 08618",
    "addr:housenumber":"10",
    "addr:postcode":"08618",
    "addr:street":"Whittier Ave",
    "iso:country":"US",
    "sg:address":"10 Whittier Ave",
    "sg:city":"Trenton",
    "sg:classifiers":[
        {
            "category":"Organizations",
            "subcategory":"Religious Organization",
            "type":"Services"
        }
    ],
    "sg:phone":"+1 609 392 6736",
    "sg:postcode":"08618",
    "sg:province":"NJ",
    "sg:tags":[
        "clergy"
    ],
    "wof:name":"Willie J Smith Rev",
    "wof:placetype":"venue"
},
  "geometry": {"coordinates":[-74.786649,40.236041],"type":"Point"}
}