{
  "type": "Feature",
  "properties": {
    "iso:country":"US",
    "sg:address":"208 Anderson St",
    "sg:city":"Hackensack",
    "sg:classifiers":[
        {
            "category":"Professional",
            "subcategory":"Lawyer & Legal Services",
            "type":"Services"
        }
    ],
    "sg:phone":"+1 201 343 4032",
    "sg:postcode":"07601",
    "sg:province":"NJ",
    "wof:name":"Berkley Arms Associates",
    "wof:placetype":"venue"
},
  "geometry": {"coordinates":[-74.04589799999999,40.8955],"type":"Point"}
}