{
  "type": "Feature",
  "properties": {
    "iso:country":"US",
    "sg:address":"177 State Rte 37",
    "sg:city":"Toms River",
    "sg:classifiers":[
        {
            "category":"Building & Trades",
            "subcategory":"Pest Control",
            "type":"Services"
        }
    ],
    "sg:phone":"+1   ",
    "sg:postcode":"08755",
    "sg:province":"NJ",
    "wof:name":"Western Pest Services",
    "wof:placetype":"venue"
},
  "geometry": {"coordinates":[-74.221104,39.966054],"type":"Point"}
}