{
  "type": "Feature",
  "properties": {
    "iso:country":"US",
    "sg:address":"1347 Monmouth Rd",
    "sg:city":"Mount Holly",
    "sg:classifiers":[
        {
            "category":"Home & Garden",
            "subcategory":"Garden Supply",
            "type":"Retail Goods"
        }
    ],
    "sg:phone":"+1   ",
    "sg:postcode":"08060",
    "sg:province":"NJ",
    "wof:name":"Perennial Garden Nurs & Ldscp",
    "wof:placetype":"venue"
},
  "geometry": {"coordinates":[-74.756165,40.008885],"type":"Point"}
}