{
  "type": "Feature",
  "properties": {
    "iso:country":"US",
    "sg:address":"440 US Hwy 22",
    "sg:city":"Hillside",
    "sg:classifiers":[
        {
            "category":"Food & Beverages",
            "subcategory":"Groceries & Convenience Stores",
            "type":"Retail Goods"
        }
    ],
    "sg:phone":"+1   ",
    "sg:postcode":"07205",
    "sg:province":"NJ",
    "wof:name":"Ace & A J Food Inc",
    "wof:placetype":"venue"
},
  "geometry": {"coordinates":[-74.235446,40.699207],"type":"Point"}
}