{
  "type": "Feature",
  "properties": {
    "addr:full":"526 S Burnt Mill Rd Voorhees NJ 08043",
    "addr:housenumber":"526",
    "addr:postcode":"08043",
    "addr:street":"S Burnt Mill Rd",
    "iso:country":"US",
    "sg:address":"526 S Burnt Mill Rd",
    "sg:city":"Voorhees",
    "sg:classifiers":[
        {
            "category":"Health Services",
            "subcategory":"Doctor",
            "type":"Services"
        }
    ],
    "sg:phone":"+1   ",
    "sg:postcode":"08043",
    "sg:province":"NJ",
    "wof:name":"Anthony Frattali DDS",
    "wof:placetype":"venue"
},
  "geometry": {"coordinates":[-75.00706,39.850562],"type":"Point"}
}