{
  "type": "Feature",
  "properties": {
    "iso:country":"US",
    "sg:address":"10 Gordon Dr",
    "sg:city":"Totowa",
    "sg:classifiers":[
        {
            "category":"Manufacturing",
            "subcategory":"Chemicals & Compounds",
            "type":"Manufacturing & Wholesale Goods"
        }
    ],
    "sg:phone":"+1 973 256 3850",
    "sg:postcode":"07512",
    "sg:province":"NJ",
    "sg:tags":[
        "flavor",
        "fragrance",
        "mfg"
    ],
    "wof:name":"Symrise Inc",
    "wof:placetype":"venue"
},
  "geometry": {"coordinates":[-74.224728,40.890023],"type":"Point"}
}