{
  "type": "Feature",
  "properties": {
    "iso:country":"US",
    "sg:address":"8 Railroad Ave",
    "sg:city":"Rochelle Park",
    "sg:classifiers":[
        {
            "category":"Recreation",
            "type":"Entertainment"
        }
    ],
    "sg:phone":"+1 201 556 9799",
    "sg:postcode":"07662",
    "sg:province":"NJ",
    "sg:tags":[
        "martial",
        "arts",
        "instruction"
    ],
    "wof:name":"MVP Tae KWON Do Ctr",
    "wof:placetype":"venue"
},
  "geometry": {"coordinates":[-74.081143,40.900371],"type":"Point"}
}