{
  "type": "Feature",
  "properties": {
    "addr:full":"34 Ingraham Ter Wayne NJ 07470",
    "addr:housenumber":"34",
    "addr:postcode":"07470",
    "addr:street":"Ingraham Ter",
    "iso:country":"US",
    "sg:address":"34 Ingraham Ter",
    "sg:city":"Wayne",
    "sg:classifiers":[
        {
            "category":"Professional",
            "subcategory":"Advertising",
            "type":"Services"
        }
    ],
    "sg:phone":"+1 973 686 1557",
    "sg:postcode":"07470",
    "sg:province":"NJ",
    "wof:name":"See A Car",
    "wof:placetype":"venue"
},
  "geometry": {"coordinates":[-74.251896,40.946833],"type":"Point"}
}