{
  "type": "Feature",
  "properties": {
    "addr:full":"385 White Horse Pike Atco NJ 08004",
    "addr:housenumber":"385",
    "addr:postcode":"08004",
    "addr:street":"White Horse Pike",
    "iso:country":"US",
    "sg:address":"385 White Horse Pike",
    "sg:city":"Atco",
    "sg:classifiers":[
        {
            "category":"Banks & Credit Unions",
            "subcategory":"Bank",
            "type":"Services"
        }
    ],
    "sg:phone":"+1   ",
    "sg:postcode":"08004",
    "sg:province":"NJ",
    "sg:tags":[
        "state",
        "commercial"
    ],
    "sg:website":"www.commerceonline.com",
    "wof:name":"Commerce Bank",
    "wof:placetype":"venue"
},
  "geometry": {"coordinates":[-74.895869,39.768311],"type":"Point"}
}