{
  "type": "Feature",
  "properties": {
    "iso:country":"US",
    "sg:address":"30 Laird St",
    "sg:city":"Long Branch",
    "sg:classifiers":[
        {
            "category":"Shopping",
            "subcategory":"Florist",
            "type":"Retail Goods"
        }
    ],
    "sg:phone":"+1 732 222 4141",
    "sg:postcode":"07740",
    "sg:province":"NJ",
    "wof:name":"Red Bank Florist",
    "wof:placetype":"venue"
},
  "geometry": {"coordinates":[-73.98001499999999,40.303054],"type":"Point"}
}