{
  "type": "Feature",
  "properties": {
    "iso:country":"US",
    "sg:address":"1430 Bridgeton Millville Pike",
    "sg:city":"Millville",
    "sg:classifiers":[
        {
            "category":"Autos & Motor Vehicles",
            "subcategory":"Automobile Sales",
            "type":"Retail Goods"
        }
    ],
    "sg:phone":"+1 856 453 2700",
    "sg:postcode":"08332",
    "sg:province":"NJ",
    "sg:tags":[
        "car",
        "dealer"
    ],
    "wof:name":"B W Auto Sales",
    "wof:placetype":"venue"
},
  "geometry": {"coordinates":[-75.15042,39.414606],"type":"Point"}
}