{
  "type": "Feature",
  "properties": {
    "addr:full":"1 University Plaza Dr Hackensack NJ 07601",
    "addr:housenumber":"1",
    "addr:postcode":"07601",
    "addr:street":"University Plaza Dr",
    "iso:country":"US",
    "sg:address":"1 University Plaza Dr",
    "sg:city":"Hackensack",
    "sg:classifiers":[
        {
            "category":"Banks & Credit Unions",
            "subcategory":"Bank",
            "type":"Services"
        }
    ],
    "sg:phone":"+1   ",
    "sg:postcode":"07601",
    "sg:province":"NJ",
    "sg:tags":[
        "high",
        "leasing",
        "technology",
        "finance",
        "equipment"
    ],
    "wof:name":"CFI Financial Services Inc",
    "wof:placetype":"venue"
},
  "geometry": {"coordinates":[-74.039788,40.895967],"type":"Point"}
}