{
  "type": "Feature",
  "properties": {
    "addr:full":"135 Promenade Blvd Bridgewater NJ 08807",
    "addr:housenumber":"135",
    "addr:postcode":"08807",
    "addr:street":"Promenade Blvd",
    "iso:country":"US",
    "sg:address":"135 Promenade Blvd",
    "sg:city":"Bridgewater",
    "sg:classifiers":[
        {
            "category":"Shopping",
            "subcategory":"Hobbies, Toys, & Games",
            "type":"Retail Goods"
        }
    ],
    "sg:phone":"+1   ",
    "sg:postcode":"08807",
    "sg:province":"NJ",
    "sg:tags":[
        "arts",
        "craft"
    ],
    "wof:name":"Michaels 9938",
    "wof:placetype":"venue"
},
  "geometry": {"coordinates":[-74.55500499999999,40.562276],"type":"Point"}
}