{
  "type": "Feature",
  "properties": {
    "addr:full":"72 Tamboer Dr Haledon NJ 07508",
    "addr:housenumber":"72",
    "addr:postcode":"07508",
    "addr:street":"Tamboer Dr",
    "iso:country":"US",
    "sg:address":"72 Tamboer Dr",
    "sg:city":"Haledon",
    "sg:classifiers":[
        {
            "category":"Building & Trades",
            "subcategory":"Construction",
            "type":"Services"
        }
    ],
    "sg:phone":"+1 973 427 8274",
    "sg:postcode":"07508",
    "sg:province":"NJ",
    "sg:tags":[
        "p",
        "industrial",
        "commercial",
        "contractor"
    ],
    "wof:name":"Avtech Construction Engrg",
    "wof:placetype":"venue"
},
  "geometry": {"coordinates":[-74.18552200000001,40.969971],"type":"Point"}
}