{
  "type": "Feature",
  "properties": {
    "addr:full":"4 Stillo Dr Airmont NY 10952",
    "addr:housenumber":"4",
    "addr:postcode":"10952",
    "addr:street":"Stillo Dr",
    "iso:country":"US",
    "sg:address":"4 Stillo Dr",
    "sg:city":"Airmont",
    "sg:classifiers":[
        {
            "category":"Real Estate",
            "subcategory":"Real Estate Agent",
            "type":"Services"
        }
    ],
    "sg:phone":"+1 845 357 2221",
    "sg:postcode":"10952",
    "sg:province":"NY",
    "wof:name":"Larry Weinsein Real Estate Inc",
    "wof:placetype":"venue"
},
  "geometry": {"coordinates":[-74.10666500000001,41.096664],"type":"Point"}
}