{
  "type": "Feature",
  "properties": {
    "iso:country":"US",
    "sg:address":"250 E Broad St",
    "sg:city":"Westfield",
    "sg:classifiers":[
        {
            "category":"Professional",
            "subcategory":"Management & Consulting",
            "type":"Services"
        }
    ],
    "sg:phone":"+1   ",
    "sg:postcode":"07090",
    "sg:province":"NJ",
    "sg:tags":[
        "marketing",
        "educational"
    ],
    "wof:name":"Ceanytime",
    "wof:placetype":"venue"
},
  "geometry": {"coordinates":[-74.347105,40.65274],"type":"Point"}
}