{
  "type": "Feature",
  "properties": {
    "addr:full":"619 E 28th St Paterson NJ 07504",
    "addr:housenumber":"619",
    "addr:postcode":"07504",
    "addr:street":"E 28Th St",
    "iso:country":"US",
    "sg:address":"619 E 28th St",
    "sg:city":"Paterson",
    "sg:classifiers":[
        {
            "category":"Organizations",
            "subcategory":"Religious Organization",
            "type":"Services"
        }
    ],
    "sg:phone":"+1 973 345 5476",
    "sg:postcode":"07504",
    "sg:province":"NJ",
    "wof:name":"Passaic New Tstment Church God",
    "wof:placetype":"venue"
},
  "geometry": {"coordinates":[-74.147026,40.916149],"type":"Point"}
}