{
  "type": "Feature",
  "properties": {
    "iso:country":"US",
    "sg:address":"103 Strawberry Dr",
    "sg:city":"Vincentown",
    "sg:classifiers":[
        {
            "category":"Professional",
            "subcategory":"Computer Services",
            "type":"Services"
        }
    ],
    "sg:phone":"+1 609 268 2924",
    "sg:postcode":"08088",
    "sg:province":"NJ",
    "sg:tags":[
        "related"
    ],
    "wof:name":"Borowsky Consulting",
    "wof:placetype":"venue"
},
  "geometry": {"coordinates":[-74.749842,39.828458],"type":"Point"}
}