{
  "type": "Feature",
  "properties": {
    "iso:country":"US",
    "sg:address":"915 Chapel Dr",
    "sg:city":"Vineland",
    "sg:classifiers":[
        {
            "category":"Professional",
            "subcategory":"Detective & Security Services",
            "type":"Services"
        }
    ],
    "sg:phone":"+1   ",
    "sg:postcode":"08361",
    "sg:province":"NJ",
    "sg:tags":[
        "car",
        "armored"
    ],
    "wof:name":"Pickett Starlord",
    "wof:placetype":"venue"
},
  "geometry": {"coordinates":[-74.981555,39.496353],"type":"Point"}
}