{
  "type": "Feature",
  "properties": {
    "iso:country":"US",
    "sg:address":"277 Newton Swartswood Rd",
    "sg:city":"Newton",
    "sg:classifiers":[
        {
            "category":"Personal",
            "subcategory":"Beauty Salon",
            "type":"Services"
        }
    ],
    "sg:phone":"+1 973 579 0033",
    "sg:postcode":"07860",
    "sg:province":"NJ",
    "sg:tags":[
        "shop"
    ],
    "wof:name":"At Your Finger Tips Nail Salon",
    "wof:placetype":"venue"
},
  "geometry": {"coordinates":[-74.804986,41.079481],"type":"Point"}
}