{
  "type": "Feature",
  "properties": {
    "addr:full":"547 Amboy Ave Woodbridge NJ 07095",
    "addr:housenumber":"547",
    "addr:postcode":"07095",
    "addr:street":"Amboy Ave",
    "iso:country":"US",
    "sg:address":"547 Amboy Ave",
    "sg:city":"Woodbridge",
    "sg:classifiers":[
        {
            "category":"Professional",
            "type":"Services"
        }
    ],
    "sg:phone":"+1 908 925 6066",
    "sg:postcode":"07095",
    "sg:province":"NJ",
    "sg:tags":[
        "establishment"
    ],
    "wof:name":"Roosevelt Television",
    "wof:placetype":"venue"
},
  "geometry": {"coordinates":[-74.285472,40.559781],"type":"Point"}
}