{
  "type": "Feature",
  "properties": {
    "addr:full":"238 Jerseyville Ave Freehold NJ 07728",
    "addr:housenumber":"238",
    "addr:postcode":"07728",
    "addr:street":"Jerseyville Ave",
    "iso:country":"US",
    "sg:address":"238 Jerseyville Ave",
    "sg:city":"Freehold",
    "sg:classifiers":[
        {
            "category":"Autos & Motor Vehicles",
            "subcategory":"Fuel & Gas Station",
            "type":"Retail Goods"
        }
    ],
    "sg:phone":"+1 732 431 0396",
    "sg:postcode":"07728",
    "sg:province":"NJ",
    "sg:tags":[
        "oil"
    ],
    "wof:name":"Fast Fuel Svc",
    "wof:placetype":"venue"
},
  "geometry": {"coordinates":[-74.271562,40.252094],"type":"Point"}
}