{
  "type": "Feature",
  "properties": {
    "iso:country":"US",
    "sg:address":"184 Market St",
    "sg:city":"Newark",
    "sg:classifiers":[
        {
            "category":"Professional",
            "type":"Services"
        }
    ],
    "sg:phone":"+1 973 565 9255",
    "sg:postcode":"07102",
    "sg:province":"NJ",
    "sg:tags":[
        "establishment"
    ],
    "wof:name":"K Photos",
    "wof:placetype":"venue"
},
  "geometry": {"coordinates":[-74.171018,40.735187],"type":"Point"}
}