{
  "type": "Feature",
  "properties": {
    "iso:country":"US",
    "sg:address":"24 Farmhouse Ln",
    "sg:city":"Voorhees",
    "sg:classifiers":[
        {
            "category":"Professional",
            "subcategory":"Business Services",
            "type":"Services"
        }
    ],
    "sg:phone":"+1   ",
    "sg:postcode":"08043",
    "sg:province":"NJ",
    "wof:name":"Rooms Retouched",
    "wof:placetype":"venue"
},
  "geometry": {"coordinates":[-74.982868,39.837392],"type":"Point"}
}