{
  "type": "Feature",
  "properties": {
    "iso:country":"US",
    "sg:address":"151 Washington St",
    "sg:city":"Newark",
    "sg:classifiers":[
        {
            "category":"Organizations",
            "subcategory":"Non-profit Organization",
            "type":"Services"
        }
    ],
    "sg:phone":"+1 973 622 2425",
    "sg:postcode":"07102",
    "sg:province":"NJ",
    "sg:tags":[
        "service/non-profit",
        "community"
    ],
    "wof:name":"N J Family Planning League",
    "wof:placetype":"venue"
},
  "geometry": {"coordinates":[-74.172798,40.739899],"type":"Point"}
}