{
  "type": "Feature",
  "properties": {
    "iso:country":"US",
    "sg:address":"26 Plaza Rd",
    "sg:city":"Fair Lawn",
    "sg:classifiers":[
        {
            "category":"Restaurant",
            "type":"Food & Drink"
        }
    ],
    "sg:phone":"+1   ",
    "sg:postcode":"07410",
    "sg:province":"NJ",
    "wof:name":"Track Side Grille Inc",
    "wof:placetype":"venue"
},
  "geometry": {"coordinates":[-74.11991999999999,40.939377],"type":"Point"}
}