{
  "type": "Feature",
  "properties": {
    "addr:full":"95 E Main St Denville NJ 07834",
    "addr:housenumber":"95",
    "addr:postcode":"07834",
    "addr:street":"E Main St",
    "iso:country":"US",
    "sg:address":"95 E Main St",
    "sg:city":"Denville",
    "sg:classifiers":[
        {
            "category":"Food & Beverages",
            "subcategory":"Specialty",
            "type":"Retail Goods"
        }
    ],
    "sg:phone":"+1   ",
    "sg:postcode":"07834",
    "sg:province":"NJ",
    "wof:name":"Nutrition Center",
    "wof:placetype":"venue"
},
  "geometry": {"coordinates":[-74.478396,40.88947],"type":"Point"}
}