{
  "type": "Feature",
  "properties": {
    "iso:country":"US",
    "sg:address":"401 State Rte 70",
    "sg:city":"Cherry Hill",
    "sg:classifiers":[
        {
            "category":"Building & Trades",
            "subcategory":"Electrical",
            "type":"Services"
        }
    ],
    "sg:phone":"+1 856 931 7800",
    "sg:postcode":"08034",
    "sg:province":"NJ",
    "sg:tags":[
        "electrical",
        "contractor"
    ],
    "wof:name":"Gems General Electrical",
    "wof:placetype":"venue"
},
  "geometry": {"coordinates":[-75.000558,39.911981],"type":"Point"}
}