{
  "type": "Feature",
  "properties": {
    "addr:full":"475 Old Post Rd Edison NJ 08817",
    "addr:housenumber":"475",
    "addr:postcode":"08817",
    "addr:street":"Old Post Rd",
    "iso:country":"US",
    "sg:address":"475 Old Post Rd",
    "sg:city":"Edison",
    "sg:classifiers":[
        {
            "category":"Restaurant",
            "type":"Food & Drink"
        }
    ],
    "sg:menulink":"http://www.allmenus.com/nj/edison/31599-hama-korean-cusine/menu/",
    "sg:phone":"+1 732 248 1775",
    "sg:postcode":"08817",
    "sg:province":"NJ",
    "sg:tags":[
        "korean",
        "asian"
    ],
    "wof:name":"Hama Korean Cusine",
    "wof:placetype":"venue"
},
  "geometry": {"coordinates":[-74.381184,40.515234],"type":"Point"}
}