{
  "type": "Feature",
  "properties": {
    "iso:country":"US",
    "sg:address":"44 Washington St",
    "sg:city":"Morristown",
    "sg:classifiers":[
        {
            "category":"Personal",
            "subcategory":"Beauty Salon",
            "type":"Services"
        }
    ],
    "sg:phone":"+1 973 455 1515",
    "sg:postcode":"07960",
    "sg:province":"NJ",
    "sg:tags":[
        "hair"
    ],
    "sg:website":"nikossalon.com",
    "wof:name":"Niko's Hair Studio",
    "wof:placetype":"venue"
},
  "geometry": {"coordinates":[-74.483271,40.797604],"type":"Point"}
}