{
  "type": "Feature",
  "properties": {
    "iso:country":"US",
    "sg:address":"19 du Bois Ave",
    "sg:city":"Alpine",
    "sg:classifiers":[
        {
            "category":"Building & Trades",
            "subcategory":"Construction",
            "type":"Services"
        }
    ],
    "sg:phone":"+1 201 784 9760",
    "sg:postcode":"07620",
    "sg:province":"NJ",
    "sg:tags":[
        "contractor"
    ],
    "wof:name":"Tectonic Co",
    "wof:placetype":"venue"
},
  "geometry": {"coordinates":[-73.927386,40.947792],"type":"Point"}
}