{
  "type": "Feature",
  "properties": {
    "addr:full":"675 New County Road Secaucus NJ 07094",
    "addr:housenumber":"675",
    "addr:postcode":"07094",
    "addr:street":"New County Road",
    "iso:country":"US",
    "sg:address":"675 New County Road",
    "sg:city":"Secaucus",
    "sg:classifiers":[
        {
            "category":"Parking",
            "type":"Transportation"
        }
    ],
    "sg:postcode":"07094",
    "sg:province":"NJ",
    "sg:website":"www.parkfast.com",
    "wof:name":"Edison Park Fast",
    "wof:placetype":"venue"
},
  "geometry": {"coordinates":[-74.081863,40.761967],"type":"Point"}
}