{
  "type": "Feature",
  "properties": {
    "addr:full":"35 Grabowski Ct Monroe Township NJ 08831",
    "addr:housenumber":"35",
    "addr:postcode":"08831",
    "addr:street":"Grabowski Ct",
    "iso:country":"US",
    "sg:address":"35 Grabowski Ct",
    "sg:city":"Monroe Township",
    "sg:classifiers":[
        {
            "category":"Building & Trades",
            "subcategory":"Construction",
            "type":"Services"
        }
    ],
    "sg:phone":"+1 732 521 0899",
    "sg:postcode":"08831",
    "sg:province":"NJ",
    "sg:tags":[
        "interior",
        "hanging"
    ],
    "wof:name":"Worden Ken Pntg & Ppr Hangings",
    "wof:placetype":"venue"
},
  "geometry": {"coordinates":[-74.435301,40.361619],"type":"Point"}
}