{
  "type": "Feature",
  "properties": {
    "addr:full":"116 Shadeland Ave Villas NJ 08251",
    "addr:housenumber":"116",
    "addr:postcode":"08251",
    "addr:street":"Shadeland Ave Villas",
    "iso:country":"US",
    "sg:address":"116 Shadeland Ave",
    "sg:city":"Villas",
    "sg:classifiers":[
        {
            "category":"Shopping",
            "type":"Retail Goods"
        }
    ],
    "sg:phone":"+1 609 886 6771",
    "sg:postcode":"08251",
    "sg:province":"NJ",
    "sg:tags":[
        "picture"
    ],
    "wof:name":"Picture This",
    "wof:placetype":"venue"
},
  "geometry": {"coordinates":[-74.944759,39.005616],"type":"Point"}
}