{
  "type": "Feature",
  "properties": {
    "addr:full":"392 Harding Hwy Carneys Point NJ 08069",
    "addr:housenumber":"392",
    "addr:postcode":"08069",
    "addr:street":"Harding Hwy",
    "iso:country":"US",
    "sg:address":"392 Harding Hwy",
    "sg:city":"Carneys Point",
    "sg:classifiers":[
        {
            "category":"Freight",
            "type":"Transportation"
        }
    ],
    "sg:phone":"+1 856 299 7666",
    "sg:postcode":"08069",
    "sg:province":"NJ",
    "sg:tags":[
        "commercial",
        "storage"
    ],
    "wof:name":"Spare Room",
    "wof:placetype":"venue"
},
  "geometry": {"coordinates":[-75.451555,39.71367],"type":"Point"}
}