{
  "type": "Feature",
  "properties": {
    "iso:country":"US",
    "sg:address":"36 Feronia Way",
    "sg:city":"Rutherford",
    "sg:classifiers":[
        {
            "category":"Professional",
            "subcategory":"Detective & Security Services",
            "type":"Services"
        }
    ],
    "sg:phone":"+1 201 939 5764",
    "sg:postcode":"07070",
    "sg:province":"NJ",
    "sg:tags":[
        "system"
    ],
    "wof:name":"Woessner Security Systems",
    "wof:placetype":"venue"
},
  "geometry": {"coordinates":[-74.100898,40.825945],"type":"Point"}
}