{
  "type": "Feature",
  "properties": {
    "iso:country":"US",
    "sg:address":"321 Burnt Mills Rd",
    "sg:city":"Branchburg",
    "sg:classifiers":[
        {
            "category":"Farming",
            "subcategory":"Farm",
            "type":"Manufacturing & Wholesale Goods"
        }
    ],
    "sg:phone":"+1 908 707 8877",
    "sg:postcode":"08876",
    "sg:province":"NJ",
    "sg:tags":[
        "crop",
        "general"
    ],
    "wof:name":"Fentondale Farm",
    "wof:placetype":"venue"
},
  "geometry": {"coordinates":[-74.68788000000001,40.628227],"type":"Point"}
}