{
  "type": "Feature",
  "properties": {
    "addr:full":"120 S Martine Ave Fanwood NJ 07023",
    "addr:housenumber":"120",
    "addr:postcode":"07023",
    "addr:street":"S Martine Ave",
    "iso:country":"US",
    "sg:address":"120 S Martine Ave",
    "sg:city":"Fanwood",
    "sg:classifiers":[
        {
            "category":"Health Services",
            "subcategory":"Chiropractor",
            "type":"Services"
        }
    ],
    "sg:phone":"+1 908 935 0013",
    "sg:postcode":"07023",
    "sg:province":"NJ",
    "wof:name":"Babbitt Chiropractic Ctr",
    "wof:placetype":"venue"
},
  "geometry": {"coordinates":[-74.38073300000001,40.639018],"type":"Point"}
}