{
  "type": "Feature",
  "properties": {
    "addr:full":"7119 Chandler Ave Pennsauken NJ 08110",
    "addr:housenumber":"7119",
    "addr:postcode":"08110",
    "addr:street":"Chandler Ave",
    "iso:country":"US",
    "sg:address":"7119 Chandler Ave",
    "sg:city":"Pennsauken",
    "sg:classifiers":[
        {
            "category":"Fast Food",
            "type":"Food & Drink"
        },
        {
            "category":"Restaurant",
            "type":"Food & Drink"
        }
    ],
    "sg:phone":"+1 856 663 8248",
    "sg:postcode":"08110",
    "sg:province":"NJ",
    "sg:tags":[
        "take"
    ],
    "wof:name":"Cheryls Kitchen",
    "wof:placetype":"venue"
},
  "geometry": {"coordinates":[-75.081316,39.935343],"type":"Point"}
}