{
  "type": "Feature",
  "properties": {
    "iso:country":"US",
    "sg:address":"40 Bramshill Dr",
    "sg:city":"Mahwah",
    "sg:classifiers":[
        {
            "category":"Professional",
            "type":"Services"
        }
    ],
    "sg:phone":"+1   ",
    "sg:postcode":"07430",
    "sg:province":"NJ",
    "wof:name":"Surplus Services LLC",
    "wof:placetype":"venue"
},
  "geometry": {"coordinates":[-74.195876,41.070862],"type":"Point"}
}