{
  "type": "Feature",
  "properties": {
    "addr:full":"120 Watchung Ave North Plainfield NJ 07060",
    "addr:housenumber":"120",
    "addr:postcode":"07060",
    "addr:street":"Watchung Ave",
    "iso:country":"US",
    "sg:address":"120 Watchung Ave",
    "sg:city":"North Plainfield",
    "sg:classifiers":[
        {
            "category":"Professional",
            "type":"Services"
        }
    ],
    "sg:phone":"+1 908 756 6896",
    "sg:postcode":"07060",
    "sg:province":"NJ",
    "wof:name":"Harper's Auto Svc",
    "wof:placetype":"venue"
},
  "geometry": {"coordinates":[-74.42683,40.622688],"type":"Point"}
}