{
  "type": "Feature",
  "properties": {
    "iso:country":"US",
    "sg:address":"1755 Williamstown Erial Rd",
    "sg:city":"Sicklerville",
    "sg:classifiers":[
        {
            "category":"Professional",
            "subcategory":"Art Services",
            "type":"Services"
        },
        {
            "category":"Manufacturing",
            "subcategory":"Printing",
            "type":"Manufacturing & Wholesale Goods"
        }
    ],
    "sg:phone":"+1 856 435 6800",
    "sg:postcode":"08081",
    "sg:province":"NJ",
    "sg:tags":[
        "commercial",
        "printer",
        "design"
    ],
    "wof:name":"National Color Graphics",
    "wof:placetype":"venue"
},
  "geometry": {"coordinates":[-75.004548,39.768058],"type":"Point"}
}