{
  "type": "Feature",
  "properties": {
    "addr:full":"4375 US Hwy 1 Princeton NJ 08540",
    "addr:housenumber":"4375",
    "addr:postcode":"08540",
    "addr:street":"Us Hwy 1",
    "iso:country":"US",
    "sg:address":"4375 US Hwy 1",
    "sg:city":"Princeton",
    "sg:classifiers":[
        {
            "category":"Travel",
            "subcategory":"Hotels & Motels",
            "type":"Entertainment"
        }
    ],
    "sg:phone":"+1 609 951 0009",
    "sg:postcode":"08540",
    "sg:province":"NJ",
    "wof:name":"Stay Bridge Suites",
    "wof:placetype":"venue"
},
  "geometry": {"coordinates":[-74.59168099999999,40.370291],"type":"Point"}
}