{
  "type": "Feature",
  "properties": {
    "addr:full":"93 2nd St Hackensack NJ 07601",
    "addr:housenumber":"93",
    "addr:postcode":"07601",
    "addr:street":"2Nd St",
    "iso:country":"US",
    "sg:address":"93 2nd St",
    "sg:city":"Hackensack",
    "sg:classifiers":[
        {
            "category":"Building & Trades",
            "subcategory":"Construction",
            "type":"Services"
        }
    ],
    "sg:phone":"+1 201 488 3318",
    "sg:postcode":"07601",
    "sg:province":"NJ",
    "sg:tags":[
        "industrial"
    ],
    "wof:name":"Wm Blanchard Co",
    "wof:placetype":"venue"
},
  "geometry": {"coordinates":[-74.053788,40.885206],"type":"Point"}
}