{
  "type": "Feature",
  "properties": {
    "addr:full":"2789 Dune Dr Avalon NJ 08202",
    "addr:housenumber":"2789",
    "addr:postcode":"08202",
    "addr:street":"Dune Dr",
    "iso:country":"US",
    "sg:address":"2789 Dune Dr",
    "sg:city":"Avalon",
    "sg:classifiers":[
        {
            "category":"Real Estate",
            "subcategory":"Real Estate Services",
            "type":"Services"
        }
    ],
    "sg:phone":"+1 609 967 0147",
    "sg:postcode":"08202",
    "sg:province":"NJ",
    "wof:name":"Ahern Stephen Realtor",
    "wof:placetype":"venue"
},
  "geometry": {"coordinates":[-74.721603,39.097301],"type":"Point"}
}