{
  "type": "Feature",
  "properties": {
    "iso:country":"US",
    "sg:address":"8 Boxwood Ct",
    "sg:city":"Trenton",
    "sg:classifiers":[
        {
            "category":"Building & Trades",
            "subcategory":"Construction",
            "type":"Services"
        }
    ],
    "sg:phone":"+1 609 882 0675",
    "sg:postcode":"08628",
    "sg:province":"NJ",
    "sg:tags":[
        "general",
        "industrial",
        "commercial",
        "contractor"
    ],
    "wof:name":"Federal Construction Co",
    "wof:placetype":"venue"
},
  "geometry": {"coordinates":[-74.83911999999999,40.253246],"type":"Point"}
}