{
  "type": "Feature",
  "properties": {
    "addr:full":"1 Millbrook Rd Hardwick NJ 07825",
    "addr:housenumber":"1",
    "addr:postcode":"07825",
    "addr:street":"Millbrook Rd",
    "iso:country":"US",
    "sg:address":"1 Millbrook Rd",
    "sg:city":"Hardwick",
    "sg:classifiers":[
        {
            "category":"Restaurant",
            "type":"Food & Drink"
        }
    ],
    "sg:phone":"+1 908 459 4860",
    "sg:postcode":"07825",
    "sg:province":"NJ",
    "wof:name":"Village Cafe",
    "wof:placetype":"venue"
},
  "geometry": {"coordinates":[-74.967517,40.912756],"type":"Point"}
}