{
  "type": "Feature",
  "properties": {
    "iso:country":"US",
    "sg:address":"50 Harrison St",
    "sg:city":"Hoboken",
    "sg:classifiers":[
        {
            "category":"Professional",
            "subcategory":"Management & Consulting",
            "type":"Services"
        }
    ],
    "sg:phone":"+1 201 656 9945",
    "sg:postcode":"07030",
    "sg:province":"NJ",
    "sg:tags":[
        "consultant",
        "business"
    ],
    "wof:name":"Quantitative Analysis",
    "wof:placetype":"venue"
},
  "geometry": {"coordinates":[-74.039861,40.745833],"type":"Point"}
}