{
  "type": "Feature",
  "properties": {
    "iso:country":"US",
    "sg:address":"806 85th St",
    "sg:city":"North Bergen",
    "sg:classifiers":[
        {
            "category":"Freight",
            "type":"Transportation"
        }
    ],
    "sg:phone":"+1 201 538 3433",
    "sg:postcode":"07047",
    "sg:province":"NJ",
    "sg:tags":[
        "operator",
        "trucking"
    ],
    "wof:name":"Santa Clara Association",
    "wof:placetype":"venue"
},
  "geometry": {"coordinates":[-74.007329,40.806539],"type":"Point"}
}