{
  "type": "Feature",
  "properties": {
    "iso:country":"US",
    "sg:address":"1477 State Route 23",
    "sg:city":"Wayne",
    "sg:classifiers":[
        {
            "category":"Shopping",
            "subcategory":"Mobile Phones",
            "type":"Retail Goods"
        }
    ],
    "sg:phone":"+1 973 694 2332",
    "sg:postcode":"07470",
    "sg:province":"NJ",
    "wof:name":"Wireless Zone",
    "wof:placetype":"venue"
},
  "geometry": {"coordinates":[-74.269203,40.935501],"type":"Point"}
}