{
  "type": "Feature",
  "properties": {
    "addr:full":"529 Mountainview Dr Plainfield NJ 07063",
    "addr:housenumber":"529",
    "addr:postcode":"07063",
    "addr:street":"Mountainview Dr",
    "iso:country":"US",
    "sg:address":"529 Mountainview Dr",
    "sg:city":"Plainfield",
    "sg:classifiers":[
        {
            "category":"Professional",
            "subcategory":"Business Services",
            "type":"Services"
        }
    ],
    "sg:phone":"+1 908 754 6657",
    "sg:postcode":"07063",
    "sg:province":"NJ",
    "wof:name":"Aok Telecom",
    "wof:placetype":"venue"
},
  "geometry": {"coordinates":[-74.452254,40.612058],"type":"Point"}
}