{
  "type": "Feature",
  "properties": {
    "addr:full":"1150 Indiana Ave Trenton NJ 08638",
    "addr:housenumber":"1150",
    "addr:postcode":"08638",
    "addr:street":"Indiana Ave",
    "iso:country":"US",
    "sg:address":"1150 Indiana Ave",
    "sg:city":"Trenton",
    "sg:classifiers":[
        {
            "category":"Organizations",
            "subcategory":"Religious Organization",
            "type":"Services"
        }
    ],
    "sg:phone":"+1 609 393 3445",
    "sg:postcode":"08638",
    "sg:province":"NJ",
    "sg:tags":[
        "church"
    ],
    "wof:name":"Living Word Ministries Chrstn",
    "wof:placetype":"venue"
},
  "geometry": {"coordinates":[-74.742941,40.242336],"type":"Point"}
}