{
  "type": "Feature",
  "properties": {
    "iso:country":"US",
    "sg:address":"4 Berwick Cir",
    "sg:city":"North Brunswick",
    "sg:classifiers":[
        {
            "category":"Building & Trades",
            "subcategory":"Electrical",
            "type":"Services"
        }
    ],
    "sg:phone":"+1 732 246 1716",
    "sg:postcode":"08902",
    "sg:province":"NJ",
    "sg:tags":[
        "electrical",
        "contractor"
    ],
    "wof:name":"Deepa Electric Corp",
    "wof:placetype":"venue"
},
  "geometry": {"coordinates":[-74.497539,40.464368],"type":"Point"}
}