{
  "type": "Feature",
  "properties": {
    "iso:country":"US",
    "sg:address":"101 N Beverwyck Rd",
    "sg:city":"Lake Hiawatha",
    "sg:classifiers":[
        {
            "category":"Professional",
            "subcategory":"Lawyer & Legal Services",
            "type":"Services"
        }
    ],
    "sg:phone":"+1 973 402 1400",
    "sg:postcode":"07034",
    "sg:province":"NJ",
    "wof:name":"Onorevole Richard M Attorney",
    "wof:placetype":"venue"
},
  "geometry": {"coordinates":[-74.38200399999999,40.883701],"type":"Point"}
}