{
  "type": "Feature",
  "properties": {
    "addr:full":"11 Central Ave Caldwell NJ 07006",
    "addr:housenumber":"11",
    "addr:postcode":"07006",
    "addr:street":"Central Ave",
    "iso:country":"US",
    "sg:address":"11 Central Ave",
    "sg:city":"Caldwell",
    "sg:classifiers":[
        {
            "category":"Education",
            "subcategory":"Special Training",
            "type":"Public Place"
        }
    ],
    "sg:phone":"+1   ",
    "sg:postcode":"07006",
    "sg:province":"NJ",
    "wof:name":"Sound Connection Inc",
    "wof:placetype":"venue"
},
  "geometry": {"coordinates":[-74.27964299999999,40.843456],"type":"Point"}
}