{
  "type": "Feature",
  "properties": {
    "iso:country":"US",
    "sg:address":"7 Richlyn Ct",
    "sg:city":"Morristown",
    "sg:classifiers":[
        {
            "category":"Museum",
            "type":"Entertainment"
        }
    ],
    "sg:phone":"+1 973 267 4363",
    "sg:postcode":"07960",
    "sg:province":"NJ",
    "sg:tags":[
        "gallery"
    ],
    "wof:name":"De Mos Enterprises",
    "wof:placetype":"venue"
},
  "geometry": {"coordinates":[-74.493803,40.811285],"type":"Point"}
}