{
  "type": "Feature",
  "properties": {
    "addr:full":"617 Morris Ave Springfield NJ 07081",
    "addr:housenumber":"617",
    "addr:postcode":"07081",
    "addr:street":"Morris Ave",
    "iso:country":"US",
    "sg:address":"617 Morris Ave",
    "sg:city":"Springfield",
    "sg:classifiers":[
        {
            "category":"Banks & Credit Unions",
            "subcategory":"Investment Brokerage",
            "type":"Services"
        }
    ],
    "sg:phone":"+1   ",
    "sg:postcode":"07081",
    "sg:province":"NJ",
    "sg:tags":[
        "security"
    ],
    "wof:name":"Edward Jones 02552",
    "wof:placetype":"venue"
},
  "geometry": {"coordinates":[-74.32727300000001,40.717267],"type":"Point"}
}