{
  "type": "Feature",
  "properties": {
    "addr:full":"7 Jules Ln New Brunswick NJ 08901",
    "addr:housenumber":"7",
    "addr:postcode":"08901",
    "addr:street":"Jules Ln",
    "iso:country":"US",
    "sg:address":"7 Jules Ln",
    "sg:city":"New Brunswick",
    "sg:classifiers":[
        {
            "category":"Wholesale",
            "subcategory":"Electrical",
            "type":"Manufacturing & Wholesale Goods"
        }
    ],
    "sg:phone":"+1 732 249 2230",
    "sg:postcode":"08901",
    "sg:province":"NJ",
    "sg:tags":[
        "light",
        "tube",
        "bulb"
    ],
    "wof:name":"Sylvania Lighting Svc",
    "wof:placetype":"venue"
},
  "geometry": {"coordinates":[-74.479449,40.472413],"type":"Point"}
}