{
  "type": "Feature",
  "properties": {
    "iso:country":"US",
    "sg:address":"360 Kennedy Blvd",
    "sg:city":"Bayonne",
    "sg:classifiers":[
        {
            "category":"Personal",
            "subcategory":"Beauty Salon",
            "type":"Services"
        }
    ],
    "sg:phone":"+1 201 823 8866",
    "sg:postcode":"07002",
    "sg:province":"NJ",
    "sg:tags":[
        "shop"
    ],
    "wof:name":"River View Life Styles",
    "wof:placetype":"venue"
},
  "geometry": {"coordinates":[-74.129758,40.658069],"type":"Point"}
}