{
  "type": "Feature",
  "properties": {
    "addr:full":"1731 Boardwalk Atlantic City NJ 08401",
    "addr:housenumber":"1731",
    "addr:postcode":"08401",
    "addr:street":"Boardwalk",
    "iso:country":"US",
    "sg:address":"1731 Boardwalk",
    "sg:city":"Atlantic City",
    "sg:classifiers":[
        {
            "category":"Shopping",
            "subcategory":"Clothing, Apparel, & Fashions",
            "type":"Retail Goods"
        }
    ],
    "sg:phone":"+1 609 343 4984",
    "sg:postcode":"08401",
    "sg:province":"NJ",
    "wof:name":"Mermaid Fashions",
    "wof:placetype":"venue"
},
  "geometry": {"coordinates":[-74.429954,39.356072],"type":"Point"}
}