{
  "type": "Feature",
  "properties": {
    "iso:country":"US",
    "sg:address":"15 Mako Ct",
    "sg:city":"South River",
    "sg:classifiers":[
        {
            "category":"Professional",
            "subcategory":"Art Services",
            "type":"Services"
        }
    ],
    "sg:phone":"+1   ",
    "sg:postcode":"08882",
    "sg:province":"NJ",
    "sg:tags":[
        "commercial",
        "design"
    ],
    "wof:name":"J P Grafx",
    "wof:placetype":"venue"
},
  "geometry": {"coordinates":[-74.389359,40.453744],"type":"Point"}
}