{
  "type": "Feature",
  "properties": {
    "iso:country":"US",
    "sg:address":"189 Route 70",
    "sg:city":"Toms River",
    "sg:classifiers":[
        {
            "category":"Restaurant",
            "type":"Food & Drink"
        }
    ],
    "sg:menulink":"http://www.allmenus.com/nj/toms-river/29431-rosted-king/menu/",
    "sg:phone":"+1 732 901 7130",
    "sg:postcode":"08755",
    "sg:province":"NJ",
    "sg:tags":[
        "spanish"
    ],
    "wof:name":"Rosted King",
    "wof:placetype":"venue"
},
  "geometry": {"coordinates":[-74.244924,40.036319],"type":"Point"}
}