{
  "type": "Feature",
  "properties": {
    "addr:full":"245 Union Ave Bridgewater NJ 08807",
    "addr:housenumber":"245",
    "addr:postcode":"08807",
    "addr:street":"Union Ave",
    "iso:country":"US",
    "sg:address":"245 Union Ave",
    "sg:city":"Bridgewater",
    "sg:classifiers":[
        {
            "category":"Professional",
            "subcategory":"Testing Lab",
            "type":"Services"
        }
    ],
    "sg:phone":"+1 908 575 8751",
    "sg:postcode":"08807",
    "sg:province":"NJ",
    "sg:tags":[
        "laboratory"
    ],
    "wof:name":"Quest Diagnostics",
    "wof:placetype":"venue"
},
  "geometry": {"coordinates":[-74.593327,40.571106],"type":"Point"}
}