{
  "type": "Feature",
  "properties": {
    "iso:country":"US",
    "sg:address":"2553 Delsea Dr",
    "sg:city":"Franklinville",
    "sg:classifiers":[
        {
            "category":"Restaurant",
            "type":"Food & Drink"
        }
    ],
    "sg:phone":"+1 856 694 3440",
    "sg:postcode":"08322",
    "sg:province":"NJ",
    "wof:name":"Nick's Pizzeria & Steak House",
    "wof:placetype":"venue"
},
  "geometry": {"coordinates":[-75.081141,39.618503],"type":"Point"}
}