{
  "type": "Feature",
  "properties": {
    "addr:full":"680 Delsea Dr N Glassboro NJ 08028",
    "addr:housenumber":"680",
    "addr:postcode":"08028",
    "addr:street":"Delsea Dr N",
    "iso:country":"US",
    "sg:address":"680 Delsea Dr N",
    "sg:city":"Glassboro",
    "sg:classifiers":[
        {
            "category":"Banks & Credit Unions",
            "subcategory":"Bank",
            "type":"Services"
        }
    ],
    "sg:phone":"+1   ",
    "sg:postcode":"08028",
    "sg:province":"NJ",
    "sg:tags":[
        "federal",
        "savings",
        "institution"
    ],
    "wof:name":"Gloucster Cnty Federal Sav Bnk",
    "wof:placetype":"venue"
},
  "geometry": {"coordinates":[-75.11283400000001,39.715899],"type":"Point"}
}