{
  "type": "Feature",
  "properties": {
    "addr:full":"212 Frank E Rodgers Blvd N Harrison NJ 07029",
    "addr:housenumber":"212",
    "addr:postcode":"07029",
    "addr:street":"Frank E Rodgers Blvd N",
    "iso:country":"US",
    "sg:address":"212 Frank E Rodgers Blvd N",
    "sg:city":"Harrison",
    "sg:classifiers":[
        {
            "category":"Professional",
            "subcategory":"Lawyer & Legal Services",
            "type":"Services"
        }
    ],
    "sg:phone":"+1 973 485 8883",
    "sg:postcode":"07029",
    "sg:province":"NJ",
    "sg:tags":[
        "attorney"
    ],
    "wof:name":"Gregory P Kowalski",
    "wof:placetype":"venue"
},
  "geometry": {"coordinates":[-74.15679,40.748526],"type":"Point"}
}