{
  "type": "Feature",
  "properties": {
    "addr:full":"16 Van Breemen Ct Montclair NJ 07043",
    "addr:housenumber":"16",
    "addr:postcode":"07043",
    "addr:street":"Van Breemen Ct",
    "iso:country":"US",
    "sg:address":"16 Van Breemen Ct",
    "sg:city":"Montclair",
    "sg:classifiers":[
        {
            "category":"Wholesale",
            "subcategory":"Groceries",
            "type":"Manufacturing & Wholesale Goods"
        }
    ],
    "sg:phone":"+1 973 509 0676",
    "sg:postcode":"07043",
    "sg:province":"NJ",
    "sg:tags":[
        "confectionery"
    ],
    "wof:name":"Les Truffes DIsabelle LLC",
    "wof:placetype":"venue"
},
  "geometry": {"coordinates":[-74.18530699999999,40.848487],"type":"Point"}
}