{
  "type": "Feature",
  "properties": {
    "iso:country":"US",
    "sg:address":"35 Madison Ln",
    "sg:city":"Sicklerville",
    "sg:classifiers":[
        {
            "category":"Manufacturing",
            "subcategory":"Petroleum Products",
            "type":"Manufacturing & Wholesale Goods"
        }
    ],
    "sg:phone":"+1 856 875 0244",
    "sg:postcode":"08081",
    "sg:province":"NJ",
    "sg:tags":[
        "contract"
    ],
    "wof:name":"Ronnell Industries Inc",
    "wof:placetype":"venue"
},
  "geometry": {"coordinates":[-74.982033,39.742882],"type":"Point"}
}