{
  "type": "Feature",
  "properties": {
    "addr:full":"63 Goshen St Paterson NJ 07503",
    "addr:housenumber":"63",
    "addr:postcode":"07503",
    "addr:street":"Goshen St",
    "iso:country":"US",
    "sg:address":"63 Goshen St",
    "sg:city":"Paterson",
    "sg:classifiers":[
        {
            "category":"Professional",
            "subcategory":"Computer Services",
            "type":"Services"
        }
    ],
    "sg:phone":"+1 973 684 0091",
    "sg:postcode":"07503",
    "sg:province":"NJ",
    "sg:tags":[
        "related"
    ],
    "wof:name":"Hcr Network Consulting",
    "wof:placetype":"venue"
},
  "geometry": {"coordinates":[-74.154764,40.895692],"type":"Point"}
}