{
  "type": "Feature",
  "properties": {
    "iso:country":"US",
    "sg:address":"93 Ridgedale Ave",
    "sg:city":"Florham Park",
    "sg:classifiers":[
        {
            "category":"Professional",
            "subcategory":"Management & Consulting",
            "type":"Services"
        }
    ],
    "sg:phone":"+1   ",
    "sg:postcode":"07932",
    "sg:province":"NJ",
    "sg:tags":[
        "building",
        "control",
        "automation",
        "system",
        "temperature"
    ],
    "wof:name":"Proactive Consulting Services",
    "wof:placetype":"venue"
},
  "geometry": {"coordinates":[-74.39963299999999,40.779392],"type":"Point"}
}