{
  "type": "Feature",
  "properties": {
    "iso:country":"US",
    "sg:address":"50 Demott Ln",
    "sg:city":"Somerset",
    "sg:classifiers":[
        {
            "category":"Building & Trades",
            "subcategory":"Electrical",
            "type":"Services"
        }
    ],
    "sg:phone":"+1 732 828 6008",
    "sg:postcode":"08873",
    "sg:province":"NJ",
    "sg:tags":[
        "electrical",
        "contractor"
    ],
    "wof:name":"Lyon Electric Company Inc",
    "wof:placetype":"venue"
},
  "geometry": {"coordinates":[-74.495851,40.52117],"type":"Point"}
}