{
  "type": "Feature",
  "properties": {
    "iso:country":"US",
    "sg:address":"10 Jackson Dr",
    "sg:city":"Cranford",
    "sg:classifiers":[
        {
            "category":"Organizations",
            "subcategory":"Labor Organization",
            "type":"Services"
        }
    ],
    "sg:phone":"+1 908 276 9644",
    "sg:postcode":"07016",
    "sg:province":"NJ",
    "wof:name":"Communications Workers-America",
    "wof:placetype":"venue"
},
  "geometry": {"coordinates":[-74.287278,40.641925],"type":"Point"}
}