{
  "type": "Feature",
  "properties": {
    "iso:country":"US",
    "sg:address":"11 Meadow Rd",
    "sg:city":"East Brunswick",
    "sg:classifiers":[
        {
            "category":"Education",
            "subcategory":"Special Training",
            "type":"Public Place"
        }
    ],
    "sg:phone":"+1   ",
    "sg:postcode":"08816",
    "sg:province":"NJ",
    "wof:name":"Maximum Art Workshop Inc",
    "wof:placetype":"venue"
},
  "geometry": {"coordinates":[-74.374273,40.412859],"type":"Point"}
}