{
  "type": "Feature",
  "properties": {
    "iso:country":"US",
    "sg:address":"630 E 6th St",
    "sg:city":"Plainfield",
    "sg:classifiers":[
        {
            "category":"Organizations",
            "subcategory":"Religious Organization",
            "type":"Services"
        }
    ],
    "sg:phone":"+1 908 756 9581",
    "sg:postcode":"07060",
    "sg:province":"NJ",
    "wof:name":"New Life Deliverance",
    "wof:placetype":"venue"
},
  "geometry": {"coordinates":[-74.409119,40.623405],"type":"Point"}
}