{
  "type": "Feature",
  "properties": {
    "addr:full":"71 Green Village Rd Madison NJ 07940",
    "addr:housenumber":"71",
    "addr:postcode":"07940",
    "addr:street":"Green Village Rd",
    "iso:country":"US",
    "sg:address":"71 Green Village Rd",
    "sg:city":"Madison",
    "sg:classifiers":[
        {
            "category":"Real Estate",
            "subcategory":"Architect",
            "type":"Services"
        }
    ],
    "sg:phone":"+1 973 593 8244",
    "sg:postcode":"07940",
    "sg:province":"NJ",
    "wof:name":"Heinrich R Aia",
    "wof:placetype":"venue"
},
  "geometry": {"coordinates":[-74.422302,40.757801],"type":"Point"}
}