{
  "type": "Feature",
  "properties": {
    "addr:full":"127 Locust Ave Howell NJ 07731",
    "addr:housenumber":"127",
    "addr:postcode":"07731",
    "addr:street":"Locust Ave",
    "iso:country":"US",
    "sg:address":"127 Locust Ave",
    "sg:city":"Howell",
    "sg:classifiers":[
        {
            "category":"Shopping",
            "subcategory":"Jewelry",
            "type":"Retail Goods"
        }
    ],
    "sg:phone":"+1 732 367 1071",
    "sg:postcode":"07731",
    "sg:province":"NJ",
    "sg:tags":[
        "jeweler"
    ],
    "wof:name":"G & L 14k Gold Jewelry",
    "wof:placetype":"venue"
},
  "geometry": {"coordinates":[-74.213842,40.138373],"type":"Point"}
}