{
  "type": "Feature",
  "properties": {
    "addr:full":"251 2nd St Lakewood NJ 08701",
    "addr:housenumber":"251",
    "addr:postcode":"08701",
    "addr:street":"2Nd St",
    "iso:country":"US",
    "sg:address":"251 2nd St",
    "sg:city":"Lakewood",
    "sg:classifiers":[
        {
            "category":"Professional",
            "subcategory":"Management & Consulting",
            "type":"Services"
        }
    ],
    "sg:phone":"+1 732 942 3894",
    "sg:postcode":"08701",
    "sg:province":"NJ",
    "sg:tags":[
        "consultant",
        "business"
    ],
    "wof:name":"Management",
    "wof:placetype":"venue"
},
  "geometry": {"coordinates":[-74.213145,40.092337],"type":"Point"}
}