{
  "type": "Feature",
  "properties": {
    "iso:country":"US",
    "sg:address":"143 Brewster Rd",
    "sg:city":"Wyckoff",
    "sg:classifiers":[
        {
            "category":"Professional",
            "subcategory":"Business Services",
            "type":"Services"
        }
    ],
    "sg:phone":"+1 201 652 6010",
    "sg:postcode":"07481",
    "sg:province":"NJ",
    "sg:tags":[
        "interior",
        "designer"
    ],
    "wof:name":"Erica Ged Interior Inc",
    "wof:placetype":"venue"
},
  "geometry": {"coordinates":[-74.169298,40.983891],"type":"Point"}
}