{
  "type": "Feature",
  "properties": {
    "addr:full":"220 Mount Vernon Pl Newark NJ 07106",
    "addr:housenumber":"220",
    "addr:postcode":"07106",
    "addr:street":"Mount Vernon Pl",
    "iso:country":"US",
    "sg:address":"220 Mount Vernon Pl",
    "sg:city":"Newark",
    "sg:classifiers":[
        {
            "category":"Building & Trades",
            "subcategory":"Construction",
            "type":"Services"
        }
    ],
    "sg:phone":"+1 973 372 7594",
    "sg:postcode":"07106",
    "sg:province":"NJ",
    "sg:tags":[
        "contractor"
    ],
    "wof:name":"Castillo Bthtub Sink Rfnishing",
    "wof:placetype":"venue"
},
  "geometry": {"coordinates":[-74.247159,40.738465],"type":"Point"}
}