{
  "type": "Feature",
  "properties": {
    "iso:country":"US",
    "sg:address":"761 Bergen Ave",
    "sg:city":"Jersey City",
    "sg:classifiers":[
        {
            "category":"Food & Beverages",
            "subcategory":"Bakery",
            "type":"Retail Goods"
        }
    ],
    "sg:phone":"+1 201 433 9154",
    "sg:postcode":"07306",
    "sg:province":"NJ",
    "sg:tags":[
        "party",
        "baker",
        "supply"
    ],
    "wof:name":"Neida's Bakery",
    "wof:placetype":"venue"
},
  "geometry": {"coordinates":[-74.0681,40.725399],"type":"Point"}
}