{
  "type": "Feature",
  "properties": {
    "addr:full":"78 Franklin Ave Oakland NJ 07436",
    "addr:housenumber":"78",
    "addr:postcode":"07436",
    "addr:street":"Franklin Ave",
    "iso:country":"US",
    "sg:address":"78 Franklin Ave",
    "sg:city":"Oakland",
    "sg:classifiers":[
        {
            "category":"Shopping",
            "subcategory":"Bicycles & Sporting Goods",
            "type":"Retail Goods"
        }
    ],
    "sg:phone":"+1   ",
    "sg:postcode":"07436",
    "sg:province":"NJ",
    "wof:name":"Razor Cycle Sports",
    "wof:placetype":"venue"
},
  "geometry": {"coordinates":[-74.23078599999999,41.02744],"type":"Point"}
}