{
  "type": "Feature",
  "properties": {
    "addr:full":"47 Elmary Pl Fair Lawn NJ 07410",
    "addr:housenumber":"47",
    "addr:postcode":"07410",
    "addr:street":"Elmary Pl",
    "iso:country":"US",
    "sg:address":"47 Elmary Pl",
    "sg:city":"Fair Lawn",
    "sg:classifiers":[
        {
            "category":"Home & Garden",
            "subcategory":"Building Materials",
            "type":"Retail Goods"
        }
    ],
    "sg:phone":"+1 609 209 2091",
    "sg:postcode":"07410",
    "sg:province":"NJ",
    "sg:tags":[
        "plumbing",
        "fixture",
        "supply"
    ],
    "wof:name":"Regba USA",
    "wof:placetype":"venue"
},
  "geometry": {"coordinates":[-74.12822300000001,40.939477],"type":"Point"}
}