{
  "type": "Feature",
  "properties": {
    "addr:full":"67 Pippins Way Morristown NJ 07960",
    "addr:housenumber":"67",
    "addr:postcode":"07960",
    "addr:street":"Pippins Way",
    "iso:country":"US",
    "sg:address":"67 Pippins Way",
    "sg:city":"Morristown",
    "sg:classifiers":[
        {
            "category":"Shopping",
            "subcategory":"Clothing, Apparel, & Fashions",
            "type":"Retail Goods"
        }
    ],
    "sg:phone":"+1   ",
    "sg:postcode":"07960",
    "sg:province":"NJ",
    "sg:tags":[
        "shop",
        "bridal"
    ],
    "wof:name":"Elizabeths Bridal Elegance Sp",
    "wof:placetype":"venue"
},
  "geometry": {"coordinates":[-74.45239599999999,40.773639],"type":"Point"}
}