{
  "type": "Feature",
  "properties": {
    "addr:full":"1205 Summit Ave Jersey City NJ 07307",
    "addr:housenumber":"1205",
    "addr:postcode":"07307",
    "addr:street":"Summit Ave",
    "iso:country":"US",
    "sg:address":"1205 Summit Ave",
    "sg:city":"Jersey City",
    "sg:classifiers":[
        {
            "category":"Restaurant",
            "type":"Food & Drink"
        }
    ],
    "sg:phone":"+1   ",
    "sg:postcode":"07307",
    "sg:province":"NJ",
    "sg:tags":[
        "eating"
    ],
    "wof:name":"Celina",
    "wof:placetype":"venue"
},
  "geometry": {"coordinates":[-74.04484600000001,40.757008],"type":"Point"}
}