{
  "type": "Feature",
  "properties": {
    "iso:country":"US",
    "sg:address":"50 Henley St",
    "sg:city":"Woodbridge",
    "sg:classifiers":[
        {
            "category":"Building & Trades",
            "subcategory":"Cleaning & Sanitation",
            "type":"Services"
        }
    ],
    "sg:phone":"+1   ",
    "sg:postcode":"07095",
    "sg:province":"NJ",
    "sg:tags":[
        "maintenance"
    ],
    "wof:name":"No Speck Office Cleaners",
    "wof:placetype":"venue"
},
  "geometry": {"coordinates":[-74.273832,40.555568],"type":"Point"}
}