{
  "type": "Feature",
  "properties": {
    "addr:full":"61 Norman Rd Rockaway NJ 07866",
    "addr:housenumber":"61",
    "addr:postcode":"07866",
    "addr:street":"Norman Rd",
    "iso:country":"US",
    "sg:address":"61 Norman Rd",
    "sg:city":"Rockaway",
    "sg:classifiers":[
        {
            "category":"Health Services",
            "subcategory":"Medical Lab",
            "type":"Services"
        }
    ],
    "sg:phone":"+1 973 784 3341",
    "sg:postcode":"07866",
    "sg:province":"NJ",
    "sg:tags":[
        "laboratory"
    ],
    "wof:name":"Ceramic Dental Studio",
    "wof:placetype":"venue"
},
  "geometry": {"coordinates":[-74.509677,40.920439],"type":"Point"}
}