{
  "type": "Feature",
  "properties": {
    "addr:full":"356 State Rte 33 Mercerville NJ 08619",
    "addr:housenumber":"356",
    "addr:postcode":"08619",
    "addr:street":"State Rte 33",
    "iso:country":"US",
    "sg:address":"356 State Rte 33",
    "sg:city":"Mercerville",
    "sg:classifiers":[
        {
            "category":"Shopping",
            "subcategory":"News",
            "type":"Retail Goods"
        }
    ],
    "sg:phone":"+1 609 890 0231",
    "sg:postcode":"08619",
    "sg:province":"NJ",
    "sg:tags":[
        "magazine"
    ],
    "wof:name":"John's Reading Ctr",
    "wof:placetype":"venue"
},
  "geometry": {"coordinates":[-74.686086,40.23336],"type":"Point"}
}