{
  "type": "Feature",
  "properties": {
    "iso:country":"US",
    "sg:address":"728 Plymouth Pl",
    "sg:city":"Ocean City",
    "sg:classifiers":[
        {
            "category":"Restaurant",
            "type":"Food & Drink"
        }
    ],
    "sg:phone":"+1   ",
    "sg:postcode":"08226",
    "sg:province":"NJ",
    "sg:tags":[
        "eating"
    ],
    "wof:name":"Philly Twist Soft Pretzel Co",
    "wof:placetype":"venue"
},
  "geometry": {"coordinates":[-74.57109199999999,39.278291],"type":"Point"}
}