{
  "type": "Feature",
  "properties": {
    "addr:full":"21 Northfield Ter Clifton NJ 07013",
    "addr:housenumber":"21",
    "addr:postcode":"07013",
    "addr:street":"Northfield Ter",
    "iso:country":"US",
    "sg:address":"21 Northfield Ter",
    "sg:city":"Clifton",
    "sg:classifiers":[
        {
            "category":"Building & Trades",
            "subcategory":"Construction",
            "type":"Services"
        }
    ],
    "sg:phone":"+1 973 472 8617",
    "sg:postcode":"07013",
    "sg:province":"NJ",
    "sg:tags":[
        "contractor"
    ],
    "wof:name":"Expert Pool RPS Installations",
    "wof:placetype":"venue"
},
  "geometry": {"coordinates":[-74.185419,40.857966],"type":"Point"}
}