{
  "type": "Feature",
  "properties": {
    "addr:full":"8900 Landis Ave Sea Isle City NJ 08243",
    "addr:housenumber":"8900",
    "addr:postcode":"08243",
    "addr:street":"Landis Ave",
    "iso:country":"US",
    "sg:address":"8900 Landis Ave",
    "sg:city":"Sea Isle City",
    "sg:classifiers":[
        {
            "category":"Professional",
            "subcategory":"Business Services",
            "type":"Services"
        }
    ],
    "sg:phone":"+1 609 263 3723",
    "sg:postcode":"08243",
    "sg:province":"NJ",
    "wof:name":"Exchange Open Business",
    "wof:placetype":"venue"
},
  "geometry": {"coordinates":[-74.713112,39.123984],"type":"Point"}
}