{
  "type": "Feature",
  "properties": {
    "addr:full":"225 W Clinton Ave Bergenfield NJ 07621",
    "addr:housenumber":"225",
    "addr:postcode":"07621",
    "addr:street":"W Clinton Ave",
    "iso:country":"US",
    "sg:address":"225 W Clinton Ave",
    "sg:city":"Bergenfield",
    "sg:classifiers":[
        {
            "category":"Education",
            "subcategory":"School",
            "type":"Public Place"
        }
    ],
    "sg:phone":"+1 201 385 8801",
    "sg:postcode":"07621",
    "sg:province":"NJ",
    "sg:tags":[
        "district"
    ],
    "wof:name":"Bergenfield Board Of Education",
    "wof:placetype":"venue"
},
  "geometry": {"coordinates":[-74.00725300000001,40.924189],"type":"Point"}
}