{
  "type": "Feature",
  "properties": {
    "iso:country":"US",
    "sg:address":"73 S Main St",
    "sg:city":"Allentown",
    "sg:classifiers":[
        {
            "category":"Organizations",
            "subcategory":"Religious Organization",
            "type":"Services"
        }
    ],
    "sg:phone":"+1 609 291 0703",
    "sg:postcode":"08501",
    "sg:province":"NJ",
    "sg:tags":[
        "clergy"
    ],
    "wof:name":"Goggins & Goggins",
    "wof:placetype":"venue"
},
  "geometry": {"coordinates":[-74.587709,40.175323],"type":"Point"}
}