{
  "type": "Feature",
  "properties": {
    "iso:country":"US",
    "sg:address":"1691 E 2nd St",
    "sg:city":"Scotch Plains",
    "sg:classifiers":[
        {
            "category":"Shopping",
            "subcategory":"Computers & Home Electronics",
            "type":"Retail Goods"
        }
    ],
    "sg:phone":"+1 908 322 8033",
    "sg:postcode":"07076",
    "sg:province":"NJ",
    "sg:tags":[
        "television",
        "radio"
    ],
    "wof:name":"New TV Image",
    "wof:placetype":"venue"
},
  "geometry": {"coordinates":[-74.400516,40.644916],"type":"Point"}
}