{
  "type": "Feature",
  "properties": {
    "addr:full":"64 4th Ave East Orange NJ 07017",
    "addr:housenumber":"64",
    "addr:postcode":"07017",
    "addr:street":"4Th Ave East",
    "iso:country":"US",
    "sg:address":"64 4th Ave",
    "sg:city":"East Orange",
    "sg:classifiers":[
        {
            "category":"Shopping",
            "subcategory":"Clothing, Apparel, & Fashions",
            "type":"Retail Goods"
        }
    ],
    "sg:phone":"+1 973 675 9445",
    "sg:postcode":"07017",
    "sg:province":"NJ",
    "wof:name":"Under The Jilbab",
    "wof:placetype":"venue"
},
  "geometry": {"coordinates":[-74.194363,40.764077],"type":"Point"}
}