{
  "type": "Feature",
  "properties": {
    "addr:full":"18 S Dean St Englewood NJ 07631",
    "addr:housenumber":"18",
    "addr:postcode":"07631",
    "addr:street":"S Dean St",
    "iso:country":"US",
    "sg:address":"18 S Dean St",
    "sg:city":"Englewood",
    "sg:classifiers":[
        {
            "category":"Restaurant",
            "type":"Food & Drink"
        }
    ],
    "sg:menulink":"http://www.allmenus.com/nj/englewood/9489-cassies-pizzeria/menu/",
    "sg:phone":"+1 201 541 6760",
    "sg:postcode":"07631",
    "sg:province":"NJ",
    "sg:tags":[
        "italian"
    ],
    "wof:name":"Cassie's Pizzeria",
    "wof:placetype":"venue"
},
  "geometry": {"coordinates":[-73.97472,40.892973],"type":"Point"}
}