{
  "type": "Feature",
  "properties": {
    "addr:full":"29 Tioga Pass Short Hills NJ 07078",
    "addr:housenumber":"29",
    "addr:postcode":"07078",
    "addr:street":"Tioga Pass",
    "iso:country":"US",
    "sg:address":"29 Tioga Pass",
    "sg:city":"Short Hills",
    "sg:classifiers":[
        {
            "category":"Professional",
            "subcategory":"Management & Consulting",
            "type":"Services"
        }
    ],
    "sg:phone":"+1   ",
    "sg:postcode":"07078",
    "sg:province":"NJ",
    "wof:name":"David S Rothberg",
    "wof:placetype":"venue"
},
  "geometry": {"coordinates":[-74.327416,40.745014],"type":"Point"}
}