{
  "type": "Feature",
  "properties": {
    "iso:country":"US",
    "sg:address":"169 Midland Ave",
    "sg:city":"Montclair",
    "sg:classifiers":[
        {
            "category":"Professional",
            "subcategory":"Art Services",
            "type":"Services"
        }
    ],
    "sg:phone":"+1   ",
    "sg:postcode":"07042",
    "sg:province":"NJ",
    "sg:tags":[
        "commercial",
        "design"
    ],
    "wof:name":"Stanger Graphics",
    "wof:placetype":"venue"
},
  "geometry": {"coordinates":[-74.213615,40.823575],"type":"Point"}
}