{
  "type": "Feature",
  "properties": {
    "addr:full":"10 Delaware Ave Salem NJ 08079",
    "addr:housenumber":"10",
    "addr:postcode":"08079",
    "addr:street":"Delaware Ave",
    "iso:country":"US",
    "sg:address":"10 Delaware Ave",
    "sg:city":"Salem",
    "sg:classifiers":[
        {
            "category":"Building & Trades",
            "subcategory":"Construction",
            "type":"Services"
        }
    ],
    "sg:phone":"+1 856 935 5050",
    "sg:postcode":"08079",
    "sg:province":"NJ",
    "sg:tags":[
        "concrete",
        "contractor"
    ],
    "wof:name":"Davenboyz Concrete Work",
    "wof:placetype":"venue"
},
  "geometry": {"coordinates":[-75.51854899999999,39.554404],"type":"Point"}
}