{
  "type": "Feature",
  "properties": {
    "addr:full":"1 E Virginia Ave Penns Grove NJ 08008",
    "addr:housenumber":"1",
    "addr:postcode":"08008",
    "addr:street":"E Virginia Ave",
    "iso:country":"US",
    "sg:address":"1 E Virginia Ave",
    "sg:city":"Penns Grove",
    "sg:classifiers":[
        {
            "category":"Restaurant",
            "type":"Food & Drink"
        }
    ],
    "sg:phone":"+1 856 299 1670",
    "sg:postcode":"08008",
    "sg:province":"NJ",
    "sg:tags":[
        "eating",
        "pizza"
    ],
    "wof:name":"Marinos Pizzeria",
    "wof:placetype":"venue"
},
  "geometry": {"coordinates":[-74.254516,39.552803],"type":"Point"}
}