{
  "type": "Feature",
  "properties": {
    "iso:country":"US",
    "sg:address":"6311 Broadway",
    "sg:city":"West New York",
    "sg:classifiers":[
        {
            "category":"Building & Trades",
            "subcategory":"Locksmith",
            "type":"Services"
        }
    ],
    "sg:phone":"+1 201 786 0700",
    "sg:postcode":"07093",
    "sg:province":"NJ",
    "sg:tags":[
        "key"
    ],
    "wof:name":"1 24 Hour A Emergency A Locksmith",
    "wof:placetype":"venue"
},
  "geometry": {"coordinates":[-74.008822,40.789407],"type":"Point"}
}