{
  "type": "Feature",
  "properties": {
    "addr:full":"19 Landis Ave Bridgeton NJ 08302",
    "addr:housenumber":"19",
    "addr:postcode":"08302",
    "addr:street":"Landis Ave",
    "iso:country":"US",
    "sg:address":"19 Landis Ave",
    "sg:city":"Bridgeton",
    "sg:classifiers":[
        {
            "category":"Education",
            "subcategory":"School",
            "type":"Public Place"
        }
    ],
    "sg:phone":"+1 856 451 0211",
    "sg:postcode":"08302",
    "sg:province":"NJ",
    "wof:name":"Cumberland Cnty Superintendent",
    "wof:placetype":"venue"
},
  "geometry": {"coordinates":[-75.206895,39.461391],"type":"Point"}
}