{
  "type": "Feature",
  "properties": {
    "iso:country":"US",
    "sg:address":"55 River Ct",
    "sg:city":"Jersey City",
    "sg:classifiers":[
        {
            "category":"Manufacturing",
            "subcategory":"Apparel",
            "type":"Manufacturing & Wholesale Goods"
        }
    ],
    "sg:phone":"+1 201 626 4979",
    "sg:postcode":"07310",
    "sg:province":"NJ",
    "sg:tags":[
        "clothing",
        "mfg"
    ],
    "wof:name":"Senior Group",
    "wof:placetype":"venue"
},
  "geometry": {"coordinates":[-74.03076299999999,40.727192],"type":"Point"}
}