{
  "type": "Feature",
  "properties": {
    "iso:country":"US",
    "sg:address":"7 Carlson Pl",
    "sg:city":"Lake Hiawatha",
    "sg:classifiers":[
        {
            "category":"Manufacturing",
            "subcategory":"Tools & Machinery",
            "type":"Manufacturing & Wholesale Goods"
        }
    ],
    "sg:phone":"+1 973 334 6350",
    "sg:postcode":"07034",
    "sg:province":"NJ",
    "sg:tags":[
        "industrial",
        "mfg"
    ],
    "wof:name":"P&L Machine Co",
    "wof:placetype":"venue"
},
  "geometry": {"coordinates":[-74.36802900000001,40.869893],"type":"Point"}
}