{
  "type": "Feature",
  "properties": {
    "addr:full":"44 Upper Montclair Plaza Montclair NJ 07043",
    "addr:housenumber":"44",
    "addr:postcode":"07043",
    "addr:street":"Upper Montclair Plaza",
    "iso:country":"US",
    "sg:address":"44 Upper Montclair Plaza",
    "sg:city":"Montclair",
    "sg:classifiers":[
        {
            "category":"Restaurant",
            "type":"Food & Drink"
        }
    ],
    "sg:phone":"+1 973 746 8555",
    "sg:postcode":"07043",
    "sg:province":"NJ",
    "sg:tags":[
        "sushi",
        "bar"
    ],
    "sg:website":"torosushibar.com",
    "wof:name":"Toro Sushi Bar",
    "wof:placetype":"venue"
},
  "geometry": {"coordinates":[-74.208826,40.839892],"type":"Point"}
}