{
  "type": "Feature",
  "properties": {
    "addr:full":"2 Village Ct Hazlet NJ 07730",
    "addr:housenumber":"2",
    "addr:postcode":"07730",
    "addr:street":"Village Ct",
    "iso:country":"US",
    "sg:address":"2 Village Ct",
    "sg:city":"Hazlet",
    "sg:classifiers":[
        {
            "category":"Professional",
            "subcategory":"Lawyer & Legal Services",
            "type":"Services"
        }
    ],
    "sg:phone":"+1   ",
    "sg:postcode":"07730",
    "sg:province":"NJ",
    "wof:name":"Law Offices of Jeffrey H Ward",
    "wof:placetype":"venue"
},
  "geometry": {"coordinates":[-74.174386,40.416031],"type":"Point"}
}