{
  "type": "Feature",
  "properties": {
    "addr:full":"212 Bergen Town Ctr Paramus NJ 07652",
    "addr:housenumber":"212",
    "addr:postcode":"07652",
    "addr:street":"Bergen Town Ctr",
    "iso:country":"US",
    "sg:address":"212 Bergen Town Ctr",
    "sg:city":"Paramus",
    "sg:classifiers":[
        {
            "category":"Ice Cream",
            "type":"Food & Drink"
        }
    ],
    "sg:phone":"+1 201 843 2340",
    "sg:postcode":"07652",
    "sg:province":"NJ",
    "sg:tags":[
        "frozen",
        "yogurt"
    ],
    "sg:website":"www.baskinrobbins.com",
    "wof:name":"Baskin Robbins",
    "wof:placetype":"venue"
},
  "geometry": {"coordinates":[-74.05958,40.914904],"type":"Point"}
}