{
  "type": "Feature",
  "properties": {
    "iso:country":"US",
    "sg:address":"1292 State Rte 28",
    "sg:city":"Branchburg",
    "sg:classifiers":[
        {
            "category":"Retail",
            "subcategory":"Laundry & Dry Cleaning",
            "type":"Services"
        }
    ],
    "sg:phone":"+1 908 541 1661",
    "sg:postcode":"08876",
    "sg:province":"NJ",
    "sg:tags":[
        "cleaners"
    ],
    "wof:name":"Best Choice Cleaners",
    "wof:placetype":"venue"
},
  "geometry": {"coordinates":[-74.69738599999999,40.606708],"type":"Point"}
}