{
  "type": "Feature",
  "properties": {
    "addr:full":"39 Chelsea Dr Oak Ridge NJ 07438",
    "addr:housenumber":"39",
    "addr:postcode":"07438",
    "addr:street":"Chelsea Dr",
    "iso:country":"US",
    "sg:address":"39 Chelsea Dr",
    "sg:city":"Oak Ridge",
    "sg:classifiers":[
        {
            "category":"Wholesale",
            "subcategory":"Meat",
            "type":"Manufacturing & Wholesale Goods"
        }
    ],
    "sg:phone":"+1 973 208 2346",
    "sg:postcode":"07438",
    "sg:province":"NJ",
    "sg:tags":[
        "wholesaler",
        "broker"
    ],
    "wof:name":"Cultural Cuisine Inc",
    "wof:placetype":"venue"
},
  "geometry": {"coordinates":[-74.500387,41.028047],"type":"Point"}
}