{
  "type": "Feature",
  "properties": {
    "iso:country":"US",
    "sg:address":"124 Lincoln Blvd",
    "sg:city":"Middlesex",
    "sg:classifiers":[
        {
            "category":"Arts & Performance",
            "subcategory":"Theater",
            "type":"Entertainment"
        }
    ],
    "sg:phone":"+1 732 752 6108",
    "sg:postcode":"08846",
    "sg:province":"NJ",
    "sg:tags":[
        "live",
        "music"
    ],
    "wof:name":"Santillo Productions",
    "wof:placetype":"venue"
},
  "geometry": {"coordinates":[-74.52229,40.562136],"type":"Point"}
}