{
  "type": "Feature",
  "properties": {
    "addr:full":"1713 Park Ave South Plainfield NJ 07080",
    "addr:housenumber":"1713",
    "addr:postcode":"07080",
    "addr:street":"Park Ave",
    "iso:country":"US",
    "sg:address":"1713 Park Ave",
    "sg:city":"South Plainfield",
    "sg:classifiers":[
        {
            "category":"Retail",
            "subcategory":"Repair Shop",
            "type":"Services"
        }
    ],
    "sg:phone":"+1 908 372 6745",
    "sg:postcode":"07080",
    "sg:province":"NJ",
    "sg:tags":[
        "lock",
        "locksmith"
    ],
    "wof:name":"24 Hour 7 Day Emergency",
    "wof:placetype":"venue"
},
  "geometry": {"coordinates":[-74.400921,40.597297],"type":"Point"}
}