{
  "type": "Feature",
  "properties": {
    "iso:country":"US",
    "sg:address":"8 Robert Dr",
    "sg:city":"Princeton Junction",
    "sg:classifiers":[
        {
            "category":"Building & Trades",
            "subcategory":"Construction",
            "type":"Services"
        }
    ],
    "sg:phone":"+1 609 936 8100",
    "sg:postcode":"08550",
    "sg:province":"NJ",
    "sg:tags":[
        "commercial"
    ],
    "wof:name":"G & T Erectors LLC",
    "wof:placetype":"venue"
},
  "geometry": {"coordinates":[-74.586612,40.301014],"type":"Point"}
}