{
  "type": "Feature",
  "properties": {
    "addr:full":"82 Albert Dr Parlin NJ 08859",
    "addr:housenumber":"82",
    "addr:postcode":"08859",
    "addr:street":"Albert Dr",
    "iso:country":"US",
    "sg:address":"82 Albert Dr",
    "sg:city":"Parlin",
    "sg:classifiers":[
        {
            "category":"Freight",
            "type":"Transportation"
        }
    ],
    "sg:phone":"+1 732 727 0656",
    "sg:postcode":"08859",
    "sg:province":"NJ",
    "sg:tags":[
        "operator",
        "local",
        "trucking"
    ],
    "wof:name":"Grasso Trucking",
    "wof:placetype":"venue"
},
  "geometry": {"coordinates":[-74.29727800000001,40.461395],"type":"Point"}
}