{
  "type": "Feature",
  "properties": {
    "iso:country":"US",
    "sg:address":"7135 Colonial Ln",
    "sg:city":"Pennsauken",
    "sg:classifiers":[
        {
            "category":"Manufacturing",
            "subcategory":"Food",
            "type":"Manufacturing & Wholesale Goods"
        }
    ],
    "sg:phone":"+1 856 662 1040",
    "sg:postcode":"08109",
    "sg:province":"NJ",
    "sg:tags":[
        "corn",
        "chips",
        "potato"
    ],
    "wof:name":"J & J Snack Foods Corp",
    "wof:placetype":"venue"
},
  "geometry": {"coordinates":[-75.074674,39.931603],"type":"Point"}
}