{
  "type": "Feature",
  "properties": {
    "addr:full":"379 Chestnut Ridge Rd Woodcliff Lake NJ 07677",
    "addr:housenumber":"379",
    "addr:postcode":"07677",
    "addr:street":"Chestnut Ridge Rd",
    "iso:country":"US",
    "sg:address":"379 Chestnut Ridge Rd",
    "sg:city":"Woodcliff Lake",
    "sg:classifiers":[
        {
            "category":"Professional",
            "subcategory":"Accounting & Tax Preparation",
            "type":"Services"
        }
    ],
    "sg:phone":"+1 201 391 4321",
    "sg:postcode":"07677",
    "sg:province":"NJ",
    "wof:name":"Anthropology Inc",
    "wof:placetype":"venue"
},
  "geometry": {"coordinates":[-74.071793,41.044682],"type":"Point"}
}