{
  "type": "Feature",
  "properties": {
    "addr:full":"909 Madison Ave Plainfield NJ 07060",
    "addr:housenumber":"909",
    "addr:postcode":"07060",
    "addr:street":"Madison Ave",
    "iso:country":"US",
    "sg:address":"909 Madison Ave",
    "sg:city":"Plainfield",
    "sg:classifiers":[
        {
            "category":"Shopping",
            "subcategory":"Used Merchandise",
            "type":"Retail Goods"
        }
    ],
    "sg:phone":"+1   ",
    "sg:postcode":"07060",
    "sg:province":"NJ",
    "wof:name":"Tierneys Antiques",
    "wof:placetype":"venue"
},
  "geometry": {"coordinates":[-74.415375,40.608929],"type":"Point"}
}