{
  "type": "Feature",
  "properties": {
    "iso:country":"US",
    "sg:address":"720 Monroe St",
    "sg:city":"Hoboken",
    "sg:classifiers":[
        {
            "category":"Professional",
            "subcategory":"Advertising",
            "type":"Services"
        }
    ],
    "sg:phone":"+1 201 610 1313",
    "sg:postcode":"07030",
    "sg:province":"NJ",
    "sg:tags":[
        "counselor",
        "agency"
    ],
    "wof:name":"Hammerhead Advertising",
    "wof:placetype":"venue"
},
  "geometry": {"coordinates":[-74.037616,40.747344],"type":"Point"}
}