{
  "type": "Feature",
  "properties": {
    "iso:country":"US",
    "sg:address":"1066 White Horse Ave",
    "sg:city":"Trenton",
    "sg:classifiers":[
        {
            "category":"Restaurant",
            "type":"Food & Drink"
        }
    ],
    "sg:menulink":"http://www.allmenus.com/nj/hamilton/274771-chicken-holiday/menu/",
    "sg:phone":"+1 609 585 4855",
    "sg:postcode":"08610",
    "sg:province":"NJ",
    "sg:tags":[
        "chicken",
        "american"
    ],
    "wof:name":"Chicken Holiday",
    "wof:placetype":"venue"
},
  "geometry": {"coordinates":[-74.695526,40.205979],"type":"Point"}
}