{
  "type": "Feature",
  "properties": {
    "addr:full":"629 Eagle Rock Ave West Orange NJ 07052",
    "addr:housenumber":"629",
    "addr:postcode":"07052",
    "addr:street":"Eagle Rock Ave",
    "iso:country":"US",
    "sg:address":"629 Eagle Rock Ave",
    "sg:city":"West Orange",
    "sg:classifiers":[
        {
            "category":"Shopping",
            "subcategory":"Pharmacy",
            "type":"Retail Goods"
        }
    ],
    "sg:phone":"+1 973 736 8685",
    "sg:postcode":"07052",
    "sg:province":"NJ",
    "sg:tags":[
        "drugstore"
    ],
    "sg:website":"www.cvs.com",
    "wof:name":"Cvs Pharmacy",
    "wof:placetype":"venue"
},
  "geometry": {"coordinates":[-74.257909,40.80996],"type":"Point"}
}