{
  "type": "Feature",
  "properties": {
    "addr:full":"27 Walnut St Salem NJ 08079",
    "addr:housenumber":"27",
    "addr:postcode":"08079",
    "addr:street":"Walnut St",
    "iso:country":"US",
    "sg:address":"27 Walnut St",
    "sg:city":"Salem",
    "sg:classifiers":[
        {
            "category":"Organizations",
            "subcategory":"Religious Organization",
            "type":"Services"
        }
    ],
    "sg:phone":"+1 856 935 0856",
    "sg:postcode":"08079",
    "sg:province":"NJ",
    "wof:name":"First United Methodist Church",
    "wof:placetype":"venue"
},
  "geometry": {"coordinates":[-75.466733,39.569789],"type":"Point"}
}