{
  "type": "Feature",
  "properties": {
    "iso:country":"US",
    "sg:address":"473 N Main St",
    "sg:city":"Barnegat",
    "sg:classifiers":[
        {
            "category":"Travel",
            "subcategory":"Campground",
            "type":"Entertainment"
        }
    ],
    "sg:phone":"+1 609 698 4380",
    "sg:postcode":"08005",
    "sg:province":"NJ",
    "wof:name":"Barnegat Bay Campground",
    "wof:placetype":"venue"
},
  "geometry": {"coordinates":[-74.217105,39.764152],"type":"Point"}
}