{
  "type": "Feature",
  "properties": {
    "addr:full":"363 Lakeview Ave Clifton NJ 07011",
    "addr:housenumber":"363",
    "addr:postcode":"07011",
    "addr:street":"Lakeview Ave",
    "iso:country":"US",
    "sg:address":"363 Lakeview Ave",
    "sg:city":"Clifton",
    "sg:classifiers":[
        {
            "category":"Restaurant",
            "type":"Food & Drink"
        }
    ],
    "sg:phone":"+1 973 772 7282",
    "sg:postcode":"07011",
    "sg:province":"NJ",
    "sg:tags":[
        "venue",
        "music"
    ],
    "wof:name":"Fitzgeralds Harp & Bard",
    "wof:placetype":"venue"
},
  "geometry": {"coordinates":[-74.138901,40.887501],"type":"Point"}
}