{
  "type": "Feature",
  "properties": {
    "iso:country":"US",
    "sg:address":"707 Main St",
    "sg:city":"Little Falls",
    "sg:classifiers":[
        {
            "category":"Building & Trades",
            "subcategory":"Construction",
            "type":"Services"
        }
    ],
    "sg:phone":"+1 973 256 5600",
    "sg:postcode":"07424",
    "sg:province":"NJ",
    "sg:tags":[
        "interior",
        "design"
    ],
    "sg:website":"www.starvingartists.biz",
    "wof:name":"Starving Artists Painting & Home Repair",
    "wof:placetype":"venue"
},
  "geometry": {"coordinates":[-74.25204100000001,40.881643],"type":"Point"}
}