{
  "type": "Feature",
  "properties": {
    "addr:full":"707 Main St Caldwell NJ 07005",
    "addr:housenumber":"707",
    "addr:postcode":"07005",
    "addr:street":"Main St",
    "iso:country":"US",
    "sg:address":"707 Main St",
    "sg:city":"Caldwell",
    "sg:classifiers":[
        {
            "category":"Retail",
            "subcategory":"Laundry & Dry Cleaning",
            "type":"Services"
        }
    ],
    "sg:phone":"+1 973 237 0099",
    "sg:postcode":"07005",
    "sg:province":"NJ",
    "sg:tags":[
        "cleaners"
    ],
    "wof:name":"Town Cleaners",
    "wof:placetype":"venue"
},
  "geometry": {"coordinates":[-74.41209499999999,40.905581],"type":"Point"}
}