{
  "type": "Feature",
  "properties": {
    "iso:country":"US",
    "sg:address":"3 Mine Ave",
    "sg:city":"Bernardsville",
    "sg:classifiers":[
        {
            "category":"Real Estate",
            "subcategory":"Real Estate Agent",
            "type":"Services"
        }
    ],
    "sg:phone":"+1   ",
    "sg:postcode":"07924",
    "sg:province":"NJ",
    "wof:name":"Foxtons Realtor",
    "wof:placetype":"venue"
},
  "geometry": {"coordinates":[-74.571642,40.714612],"type":"Point"}
}