{
  "type": "Feature",
  "properties": {
    "addr:full":"400 Morris Ave Denville NJ 07834",
    "addr:housenumber":"400",
    "addr:postcode":"07834",
    "addr:street":"Morris Ave",
    "iso:country":"US",
    "sg:address":"400 Morris Ave",
    "sg:city":"Denville",
    "sg:classifiers":[
        {
            "category":"Insurance",
            "subcategory":"Insurance Agent",
            "type":"Services"
        }
    ],
    "sg:phone":"+1   ",
    "sg:postcode":"07834",
    "sg:province":"NJ",
    "sg:website":"www.tavorcorp.com",
    "wof:name":"Tavor Corp",
    "wof:placetype":"venue"
},
  "geometry": {"coordinates":[-74.503219,40.90965],"type":"Point"}
}