{
  "type": "Feature",
  "properties": {
    "iso:country":"US",
    "sg:address":"3333 Haddonfield Rd",
    "sg:city":"Pennsauken",
    "sg:classifiers":[
        {
            "category":"Food & Beverages",
            "subcategory":"Liquor & Beverages",
            "type":"Retail Goods"
        }
    ],
    "sg:phone":"+1 856 662 8475",
    "sg:postcode":"08110",
    "sg:province":"NJ",
    "sg:tags":[
        "beer",
        "spirit",
        "wine"
    ],
    "wof:name":"M & M Discount Liquors",
    "wof:placetype":"venue"
},
  "geometry": {"coordinates":[-75.023903,39.965302],"type":"Point"}
}