{
  "type": "Feature",
  "properties": {
    "iso:country":"US",
    "sg:address":"135 Kero Rd",
    "sg:city":"Carlstadt",
    "sg:classifiers":[
        {
            "category":"Shopping",
            "subcategory":"Crafts & Fabrics",
            "type":"Retail Goods"
        },
        {
            "category":"Manufacturing",
            "subcategory":"Paper Products",
            "type":"Manufacturing & Wholesale Goods"
        }
    ],
    "sg:phone":"+1 201 804 3999",
    "sg:postcode":"07072",
    "sg:province":"NJ",
    "sg:tags":[
        "yarn-wholesale",
        "yarn",
        "manufacturer"
    ],
    "wof:name":"Lion Brand Yarn",
    "wof:placetype":"venue"
},
  "geometry": {"coordinates":[-74.061021,40.829319],"type":"Point"}
}