{
  "type": "Feature",
  "properties": {
    "iso:country":"US",
    "sg:address":"1 Kelly Drivers Ln",
    "sg:city":"Laurel Springs",
    "sg:classifiers":[
        {
            "category":"Professional",
            "subcategory":"Accounting & Tax Preparation",
            "type":"Services"
        }
    ],
    "sg:phone":"+1 856 435 6667",
    "sg:postcode":"08021",
    "sg:province":"NJ",
    "sg:tags":[
        "billing"
    ],
    "wof:name":"Physicians Claims Processing",
    "wof:placetype":"venue"
},
  "geometry": {"coordinates":[-75.04019,39.819556],"type":"Point"}
}