{
  "type": "Feature",
  "properties": {
    "iso:country":"US",
    "sg:address":"119 Jefferson Ave",
    "sg:city":"Jersey City",
    "sg:classifiers":[
        {
            "category":"Retail",
            "subcategory":"Auto Repair",
            "type":"Services"
        }
    ],
    "sg:phone":"+1 201 653 5900",
    "sg:postcode":"07306",
    "sg:province":"NJ",
    "sg:tags":[
        "body",
        "car",
        "rental",
        "passenger"
    ],
    "wof:name":"Metro Rent A Car",
    "wof:placetype":"venue"
},
  "geometry": {"coordinates":[-74.054311,40.738475],"type":"Point"}
}