{
  "type": "Feature",
  "properties": {
    "addr:full":"71 Beverly Beach Rd Brick NJ 08724",
    "addr:housenumber":"71",
    "addr:postcode":"08724",
    "addr:street":"Beverly Beach Rd",
    "iso:country":"US",
    "sg:address":"71 Beverly Beach Rd",
    "sg:city":"Brick",
    "sg:classifiers":[
        {
            "category":"Building & Trades",
            "subcategory":"Construction",
            "type":"Services"
        }
    ],
    "sg:phone":"+1 732 458 4455",
    "sg:postcode":"08724",
    "sg:province":"NJ",
    "sg:tags":[
        "contracting",
        "painting"
    ],
    "wof:name":"Morton Painting Co",
    "wof:placetype":"venue"
},
  "geometry": {"coordinates":[-74.10241499999999,40.104712],"type":"Point"}
}