{
  "type": "Feature",
  "properties": {
    "iso:country":"US",
    "sg:address":"1060 Clifton Ave",
    "sg:city":"Clifton",
    "sg:classifiers":[
        {
            "category":"Health Services",
            "subcategory":"Chiropractor",
            "type":"Services"
        }
    ],
    "sg:phone":"+1 973 614 0006",
    "sg:postcode":"07013",
    "sg:province":"NJ",
    "wof:name":"North Jersey Spinal Manipulation Assoc Llc",
    "wof:placetype":"venue"
},
  "geometry": {"coordinates":[-74.1657,40.861787],"type":"Point"}
}