{
  "type": "Feature",
  "properties": {
    "addr:full":"221 Palisade Ave Jersey City NJ 07306",
    "addr:housenumber":"221",
    "addr:postcode":"07306",
    "addr:street":"Palisade Ave",
    "iso:country":"US",
    "sg:address":"221 Palisade Ave",
    "sg:city":"Jersey City",
    "sg:classifiers":[
        {
            "category":"Health Services",
            "subcategory":"Doctor",
            "type":"Services"
        },
        {
            "category":"Health Services",
            "subcategory":"Hospital",
            "type":"Services"
        }
    ],
    "sg:phone":"+1 201 656 3116",
    "sg:postcode":"07306",
    "sg:province":"NJ",
    "sg:tags":[
        "mental",
        "psychiatrist",
        "medical",
        "outpatient",
        "specialty",
        "clinic"
    ],
    "wof:name":"Palisades Behavioral Care",
    "wof:placetype":"venue"
},
  "geometry": {"coordinates":[-74.04940000000001,40.736301],"type":"Point"}
}