{
  "type": "Feature",
  "properties": {
    "addr:full":"424 S Cranford Rd Cherry Hill NJ 08003",
    "addr:housenumber":"424",
    "addr:postcode":"08003",
    "addr:street":"S Cranford Rd",
    "iso:country":"US",
    "sg:address":"424 S Cranford Rd",
    "sg:city":"Cherry Hill",
    "sg:classifiers":[
        {
            "category":"Manufacturing",
            "subcategory":"Tools & Machinery",
            "type":"Manufacturing & Wholesale Goods"
        }
    ],
    "sg:phone":"+1 856 429 5111",
    "sg:postcode":"08003",
    "sg:province":"NJ",
    "sg:tags":[
        "machine",
        "embroidering"
    ],
    "wof:name":"Promotional Products Co",
    "wof:placetype":"venue"
},
  "geometry": {"coordinates":[-74.99186400000001,39.871493],"type":"Point"}
}