{
  "type": "Feature",
  "properties": {
    "addr:full":"1000 Atrium Way Mount Laurel NJ 08054",
    "addr:housenumber":"1000",
    "addr:postcode":"08054",
    "addr:street":"Atrium Way",
    "iso:country":"US",
    "sg:address":"1000 Atrium Way",
    "sg:city":"Mount Laurel",
    "sg:classifiers":[
        {
            "category":"Insurance",
            "subcategory":"Insurance Agent",
            "type":"Services"
        }
    ],
    "sg:phone":"+1   ",
    "sg:postcode":"08054",
    "sg:province":"NJ",
    "wof:name":"Lane Stanley CLU Cpcu",
    "wof:placetype":"venue"
},
  "geometry": {"coordinates":[-74.946129,39.919288],"type":"Point"}
}