{
  "type": "Feature",
  "properties": {
    "addr:full":"484 Essex St Hackensack NJ 07601",
    "addr:housenumber":"484",
    "addr:postcode":"07601",
    "addr:street":"Essex St",
    "iso:country":"US",
    "sg:address":"484 Essex St",
    "sg:city":"Hackensack",
    "sg:classifiers":[
        {
            "category":"Retail",
            "subcategory":"Auto Repair",
            "type":"Services"
        }
    ],
    "sg:phone":"+1 201 342 7791",
    "sg:postcode":"07601",
    "sg:province":"NJ",
    "sg:tags":[
        "body",
        "shop"
    ],
    "wof:name":"Barich Inc",
    "wof:placetype":"venue"
},
  "geometry": {"coordinates":[-74.06199599999999,40.885502],"type":"Point"}
}