{
  "type": "Feature",
  "properties": {
    "addr:full":"555 Roberts Ave Bellmawr NJ 08031",
    "addr:housenumber":"555",
    "addr:postcode":"08031",
    "addr:street":"Roberts Ave",
    "iso:country":"US",
    "sg:address":"555 Roberts Ave",
    "sg:city":"Bellmawr",
    "sg:classifiers":[
        {
            "category":"Professional",
            "subcategory":"Business Services",
            "type":"Services"
        }
    ],
    "sg:phone":"+1   ",
    "sg:postcode":"08031",
    "sg:province":"NJ",
    "wof:name":"Grazie Group LLC",
    "wof:placetype":"venue"
},
  "geometry": {"coordinates":[-75.061575,39.863481],"type":"Point"}
}