{
  "type": "Feature",
  "properties": {
    "addr:full":"681 Van Houten Ave Clifton NJ 07013",
    "addr:housenumber":"681",
    "addr:postcode":"07013",
    "addr:street":"Van Houten Ave",
    "iso:country":"US",
    "sg:address":"681 Van Houten Ave",
    "sg:city":"Clifton",
    "sg:classifiers":[
        {
            "category":"Manufacturing",
            "subcategory":"Paper Products",
            "type":"Manufacturing & Wholesale Goods"
        }
    ],
    "sg:phone":"+1 973 773 0077",
    "sg:postcode":"07013",
    "sg:province":"NJ",
    "sg:tags":[
        "packaging",
        "industrial",
        "mfg"
    ],
    "wof:name":"Sierra Packaging Inc",
    "wof:placetype":"venue"
},
  "geometry": {"coordinates":[-74.150521,40.859359],"type":"Point"}
}