{
  "type": "Feature",
  "properties": {
    "iso:country":"US",
    "sg:address":"835 Broadway",
    "sg:city":"West Long Branch",
    "sg:classifiers":[
        {
            "category":"Personal",
            "subcategory":"Shoe Repair & Shine",
            "type":"Services"
        }
    ],
    "sg:phone":"+1 732 229 2887",
    "sg:postcode":"07764",
    "sg:province":"NJ",
    "sg:tags":[
        "repairing",
        "boot"
    ],
    "wof:name":"Silvestre Shoe Repair",
    "wof:placetype":"venue"
},
  "geometry": {"coordinates":[-74.00885100000001,40.298726],"type":"Point"}
}