{
  "type": "Feature",
  "properties": {
    "iso:country":"US",
    "sg:address":"1438 Ringwood Ave",
    "sg:city":"Haskell",
    "sg:classifiers":[
        {
            "category":"Wholesale",
            "subcategory":"Hardware",
            "type":"Manufacturing & Wholesale Goods"
        },
        {
            "category":"Home & Garden",
            "subcategory":"Garden Supply",
            "type":"Retail Goods"
        },
        {
            "category":"Retail",
            "subcategory":"Repair Shop",
            "type":"Services"
        }
    ],
    "sg:phone":"+1 973 835 1750",
    "sg:postcode":"07420",
    "sg:province":"NJ",
    "sg:tags":[
        "renting",
        "lawn",
        "outdoor",
        "power",
        "landscaping",
        "equipment-sales",
        "equipment",
        "saw"
    ],
    "sg:website":"http://www.stihldealer.net/default-dealer-004057.aspx",
    "wof:name":"Unirents",
    "wof:placetype":"venue"
},
  "geometry": {"coordinates":[-74.29650700000001,41.019212],"type":"Point"}
}