{
  "type": "Feature",
  "properties": {
    "addr:full":"510 Sylvan St Saddle Brook NJ 07663",
    "addr:housenumber":"510",
    "addr:postcode":"07663",
    "addr:street":"Sylvan St",
    "iso:country":"US",
    "sg:address":"510 Sylvan St",
    "sg:city":"Saddle Brook",
    "sg:classifiers":[
        {
            "category":"Building & Trades",
            "subcategory":"Construction",
            "type":"Services"
        }
    ],
    "sg:phone":"+1 201 670 0505",
    "sg:postcode":"07663",
    "sg:province":"NJ",
    "sg:tags":[
        "waterproofing",
        "contractor"
    ],
    "wof:name":"All Weather Tite Waterproofing",
    "wof:placetype":"venue"
},
  "geometry": {"coordinates":[-74.10083299999999,40.896602],"type":"Point"}
}