{
  "type": "Feature",
  "properties": {
    "iso:country":"US",
    "sg:address":"14 Broad St",
    "sg:city":"Norwood",
    "sg:classifiers":[
        {
            "category":"Building & Trades",
            "subcategory":"Construction",
            "type":"Services"
        }
    ],
    "sg:phone":"+1 201 767 2272",
    "sg:postcode":"07648",
    "sg:province":"NJ",
    "sg:tags":[
        "general",
        "commercial",
        "contractor"
    ],
    "sg:website":"www.catcord.com",
    "wof:name":"Cat Cord Construction Company",
    "wof:placetype":"venue"
},
  "geometry": {"coordinates":[-73.966801,40.999737],"type":"Point"}
}