{
  "type": "Feature",
  "properties": {
    "iso:country":"US",
    "sg:address":"2640 State Rte 70",
    "sg:city":"Manasquan",
    "sg:classifiers":[
        {
            "category":"Health Services",
            "subcategory":"Health Practitioner",
            "type":"Services"
        }
    ],
    "sg:phone":"+1   ",
    "sg:postcode":"08736",
    "sg:province":"NJ",
    "sg:tags":[
        "hospital",
        "specialty"
    ],
    "wof:name":"Rotgers Frederick Psy D",
    "wof:placetype":"venue"
},
  "geometry": {"coordinates":[-74.074141,40.112952],"type":"Point"}
}