{
  "type": "Feature",
  "properties": {
    "addr:full":"1807 Shore Rd Northfield NJ 08225",
    "addr:housenumber":"1807",
    "addr:postcode":"08225",
    "addr:street":"Shore Rd",
    "iso:country":"US",
    "sg:address":"1807 Shore Rd",
    "sg:city":"Northfield",
    "sg:classifiers":[
        {
            "category":"Health Services",
            "subcategory":"Chiropractor",
            "type":"Services"
        }
    ],
    "sg:phone":"+1   ",
    "sg:postcode":"08225",
    "sg:province":"NJ",
    "wof:name":"Arthur J Higbee DC",
    "wof:placetype":"venue"
},
  "geometry": {"coordinates":[-74.55214599999999,39.364708],"type":"Point"}
}