{
  "type": "Feature",
  "properties": {
    "iso:country":"US",
    "sg:address":"134 New Brunswick Ave",
    "sg:city":"Perth Amboy",
    "sg:classifiers":[
        {
            "category":"Professional",
            "subcategory":"Management & Consulting",
            "type":"Services"
        }
    ],
    "sg:phone":"+1 732 324 7776",
    "sg:postcode":"08861",
    "sg:province":"NJ",
    "sg:tags":[
        "marketing",
        "program"
    ],
    "wof:name":"Trendsetter Marketing",
    "wof:placetype":"venue"
},
  "geometry": {"coordinates":[-74.295973,40.524086],"type":"Point"}
}