{
  "type": "Feature",
  "properties": {
    "iso:country":"US",
    "sg:address":"170 Broad St",
    "sg:city":"Red Bank",
    "sg:classifiers":[
        {
            "category":"Banks & Credit Unions",
            "subcategory":"Investment Brokerage",
            "type":"Services"
        }
    ],
    "sg:phone":"+1 732 936 7000",
    "sg:postcode":"07701",
    "sg:province":"NJ",
    "sg:tags":[
        "stock",
        "bond"
    ],
    "wof:name":"Red Bank Trading",
    "wof:placetype":"venue"
},
  "geometry": {"coordinates":[-74.064932,40.346435],"type":"Point"}
}