{
  "type": "Feature",
  "properties": {
    "addr:full":"900 Ocean Ave Ocean City NJ 08226",
    "addr:housenumber":"900",
    "addr:postcode":"08226",
    "addr:street":"Ocean Ave",
    "iso:country":"US",
    "sg:address":"900 Ocean Ave",
    "sg:city":"Ocean City",
    "sg:classifiers":[
        {
            "category":"Banks & Credit Unions",
            "subcategory":"Bank",
            "type":"Services"
        }
    ],
    "sg:phone":"+1 609 399 3914",
    "sg:postcode":"08226",
    "sg:province":"NJ",
    "sg:tags":[
        "loan",
        "real estate"
    ],
    "wof:name":"Colonial Home Mortgage Co",
    "wof:placetype":"venue"
},
  "geometry": {"coordinates":[-74.57550000000001,39.275876],"type":"Point"}
}