{
  "type": "Feature",
  "properties": {
    "iso:country":"US",
    "sg:address":"191 Broad Ave",
    "sg:city":"Fairview",
    "sg:classifiers":[
        {
            "category":"Retail",
            "subcategory":"Self-service Laundry",
            "type":"Services"
        }
    ],
    "sg:phone":"+1 201 941 9951",
    "sg:postcode":"07022",
    "sg:province":"NJ",
    "wof:name":"Fairview Laundromat",
    "wof:placetype":"venue"
},
  "geometry": {"coordinates":[-74.007738,40.819762],"type":"Point"}
}