{
  "type": "Feature",
  "properties": {
    "iso:country":"US",
    "sg:address":"130 Rose Morrow Rd",
    "sg:city":"Sussex",
    "sg:classifiers":[
        {
            "category":"Food & Beverages",
            "subcategory":"Fruits & Vegetables",
            "type":"Retail Goods"
        }
    ],
    "sg:phone":"+1   ",
    "sg:postcode":"07461",
    "sg:province":"NJ",
    "wof:name":"Berry Hill Farms",
    "wof:placetype":"venue"
},
  "geometry": {"coordinates":[-74.600554,41.255301],"type":"Point"}
}