{
  "type": "Feature",
  "properties": {
    "iso:country":"US",
    "sg:address":"4 E Main St",
    "sg:city":"Mendham",
    "sg:classifiers":[
        {
            "category":"Shopping",
            "subcategory":"Gifts & Souvenirs",
            "type":"Retail Goods"
        }
    ],
    "sg:phone":"+1   ",
    "sg:postcode":"07945",
    "sg:province":"NJ",
    "wof:name":"Katydids Boutique",
    "wof:placetype":"venue"
},
  "geometry": {"coordinates":[-74.5976,40.776973],"type":"Point"}
}