{
  "type": "Feature",
  "properties": {
    "iso:country":"US",
    "sg:address":"60 Dodd St",
    "sg:city":"Bloomfield",
    "sg:classifiers":[
        {
            "category":"Manufacturing",
            "subcategory":"Metals",
            "type":"Manufacturing & Wholesale Goods"
        }
    ],
    "sg:phone":"+1 973 748 5141",
    "sg:postcode":"07003",
    "sg:province":"NJ",
    "sg:tags":[
        "fitting",
        "hose",
        "coupling"
    ],
    "wof:name":"Young Hydraulics Inc",
    "wof:placetype":"venue"
},
  "geometry": {"coordinates":[-74.199962,40.782345],"type":"Point"}
}