{
  "type": "Feature",
  "properties": {
    "addr:full":"20 Stirling Rd Watchung NJ 07069",
    "addr:housenumber":"20",
    "addr:postcode":"07069",
    "addr:street":"Stirling Rd",
    "iso:country":"US",
    "sg:address":"20 Stirling Rd",
    "sg:city":"Watchung",
    "sg:classifiers":[
        {
            "category":"Home & Garden",
            "subcategory":"Furniture",
            "type":"Retail Goods"
        }
    ],
    "sg:phone":"+1 908 756 7623",
    "sg:postcode":"07069",
    "sg:province":"NJ",
    "wof:name":"Valley Furniture Shop Inc",
    "wof:placetype":"venue"
},
  "geometry": {"coordinates":[-74.451362,40.637222],"type":"Point"}
}