{
  "type": "Feature",
  "properties": {
    "addr:full":"1132 Willow Ave Hoboken NJ 07030",
    "addr:housenumber":"1132",
    "addr:postcode":"07030",
    "addr:street":"Willow Ave",
    "iso:country":"US",
    "sg:address":"1132 Willow Ave",
    "sg:city":"Hoboken",
    "sg:classifiers":[
        {
            "category":"Retail",
            "subcategory":"Repair Shop",
            "type":"Services"
        }
    ],
    "sg:phone":"+1 201 334 3561",
    "sg:postcode":"07030",
    "sg:province":"NJ",
    "sg:tags":[
        "lock",
        "locksmith"
    ],
    "wof:name":"A 24 Hour Always Available",
    "wof:placetype":"venue"
},
  "geometry": {"coordinates":[-74.03052700000001,40.751317],"type":"Point"}
}