{
  "type": "Feature",
  "properties": {
    "iso:country":"US",
    "sg:address":"875 State Rte 27",
    "sg:city":"Metuchen",
    "sg:classifiers":[
        {
            "category":"Professional",
            "type":"Services"
        }
    ],
    "sg:phone":"+1 732 548 6200",
    "sg:postcode":"08840",
    "sg:province":"NJ",
    "sg:tags":[
        "establishment"
    ],
    "wof:name":"Econo Car",
    "wof:placetype":"venue"
},
  "geometry": {"coordinates":[-74.374679,40.536546],"type":"Point"}
}