{
  "type": "Feature",
  "properties": {
    "iso:country":"US",
    "sg:address":"291 US Hwy 46",
    "sg:city":"Denville",
    "sg:classifiers":[
        {
            "category":"Shopping",
            "type":"Retail Goods"
        }
    ],
    "sg:phone":"+1   ",
    "sg:postcode":"07834",
    "sg:province":"NJ",
    "sg:tags":[
        "repair",
        "electrical",
        "merchandise"
    ],
    "wof:name":"I O E Digital Image Group",
    "wof:placetype":"venue"
},
  "geometry": {"coordinates":[-74.496207,40.897396],"type":"Point"}
}