{
  "type": "Feature",
  "properties": {
    "iso:country":"US",
    "sg:address":"25 McWilliams Pl",
    "sg:city":"Jersey City",
    "sg:classifiers":[
        {
            "category":"Health Services",
            "subcategory":"Doctor",
            "type":"Services"
        }
    ],
    "sg:phone":"+1 201 217 4227",
    "sg:postcode":"07302",
    "sg:province":"NJ",
    "sg:tags":[
        "medical"
    ],
    "wof:name":"Andrew Greenspan MD",
    "wof:placetype":"venue"
},
  "geometry": {"coordinates":[-74.044223,40.727418],"type":"Point"}
}