{
  "type": "Feature",
  "properties": {
    "addr:full":"177 Ridgedale Ave Morristown NJ 07960",
    "addr:housenumber":"177",
    "addr:postcode":"07960",
    "addr:street":"Ridgedale Ave",
    "iso:country":"US",
    "sg:address":"177 Ridgedale Ave",
    "sg:city":"Morristown",
    "sg:classifiers":[
        {
            "category":"Wholesale",
            "subcategory":"Auto Parts",
            "type":"Manufacturing & Wholesale Goods"
        }
    ],
    "sg:phone":"+1 973 539 3630",
    "sg:postcode":"07960",
    "sg:province":"NJ",
    "wof:name":"Clinton Square Of Morristown",
    "wof:placetype":"venue"
},
  "geometry": {"coordinates":[-74.465543,40.802188],"type":"Point"}
}