{
  "type": "Feature",
  "properties": {
    "addr:full":"179 Berkshire Valley Rd Kenvil NJ 07847",
    "addr:housenumber":"179",
    "addr:postcode":"07847",
    "addr:street":"Berkshire Valley Rd",
    "iso:country":"US",
    "sg:address":"179 Berkshire Valley Rd",
    "sg:city":"Kenvil",
    "sg:classifiers":[
        {
            "category":"Professional",
            "subcategory":"Computer Services",
            "type":"Services"
        }
    ],
    "sg:phone":"+1   ",
    "sg:postcode":"07847",
    "sg:province":"NJ",
    "sg:tags":[
        "related"
    ],
    "wof:name":"Gazzoli Consulting",
    "wof:placetype":"venue"
},
  "geometry": {"coordinates":[-74.60888199999999,40.897625],"type":"Point"}
}