{
  "type": "Feature",
  "properties": {
    "iso:country":"US",
    "sg:address":"50 Piermont Rd",
    "sg:city":"Cresskill",
    "sg:classifiers":[
        {
            "category":"Professional",
            "subcategory":"Advertising",
            "type":"Services"
        }
    ],
    "sg:phone":"+1   ",
    "sg:postcode":"07626",
    "sg:province":"NJ",
    "sg:tags":[
        "mail",
        "list",
        "direct",
        "brokerage"
    ],
    "sg:website":"www.nrldirect.com",
    "wof:name":"NRL Direct",
    "wof:placetype":"venue"
},
  "geometry": {"coordinates":[-73.962411,40.941284],"type":"Point"}
}