{
  "type": "Feature",
  "properties": {
    "addr:full":"5851 W Side Ave North Bergen NJ 07047",
    "addr:housenumber":"5851",
    "addr:postcode":"07047",
    "addr:street":"W Side Ave",
    "iso:country":"US",
    "sg:address":"5851 W Side Ave",
    "sg:city":"North Bergen",
    "sg:classifiers":[
        {
            "category":"Building & Trades",
            "subcategory":"Construction",
            "type":"Services"
        }
    ],
    "sg:phone":"+1 201 662 8301",
    "sg:postcode":"07047",
    "sg:province":"NJ",
    "sg:tags":[
        "contractor"
    ],
    "wof:name":"Nova Interiors Inc",
    "wof:placetype":"venue"
},
  "geometry": {"coordinates":[-74.03073999999999,40.796044],"type":"Point"}
}