{
  "type": "Feature",
  "properties": {
    "addr:full":"379 Union St Hackensack NJ 07601",
    "addr:housenumber":"379",
    "addr:postcode":"07601",
    "addr:street":"Union St",
    "iso:country":"US",
    "sg:address":"379 Union St",
    "sg:city":"Hackensack",
    "sg:classifiers":[
        {
            "category":"Health Services",
            "subcategory":"Dentist",
            "type":"Services"
        }
    ],
    "sg:phone":"+1 201 488 4777",
    "sg:postcode":"07601",
    "sg:province":"NJ",
    "wof:name":"Dr Paul W Alberg D M D P C",
    "wof:placetype":"venue"
},
  "geometry": {"coordinates":[-74.042603,40.891102],"type":"Point"}
}