{
  "type": "Feature",
  "properties": {
    "iso:country":"US",
    "sg:address":"285 Main St",
    "sg:city":"Metuchen",
    "sg:classifiers":[
        {
            "category":"Local Transit",
            "type":"Transportation"
        }
    ],
    "sg:phone":"+1 732 738 8190",
    "sg:postcode":"08840",
    "sg:province":"NJ",
    "sg:tags":[
        "limousine"
    ],
    "wof:name":"Vanessa's Limousine Co Inc",
    "wof:placetype":"venue"
},
  "geometry": {"coordinates":[-74.360266,40.537255],"type":"Point"}
}