{
  "type": "Feature",
  "properties": {
    "iso:country":"US",
    "sg:address":"15 Broadway",
    "sg:city":"Ocean Grove",
    "sg:classifiers":[
        {
            "category":"Professional",
            "subcategory":"Advertising",
            "type":"Services"
        }
    ],
    "sg:phone":"+1 908 875 0527",
    "sg:postcode":"07756",
    "sg:province":"NJ",
    "sg:website":"www.ourtownrentals.com",
    "wof:name":"OURTOWNRENTALS.COM",
    "wof:placetype":"venue"
},
  "geometry": {"coordinates":[-74.004441,40.208912],"type":"Point"}
}