{
  "type": "Feature",
  "properties": {
    "iso:country":"US",
    "sg:address":"1025 Jacksonville Rd",
    "sg:city":"Burlington",
    "sg:classifiers":[
        {
            "category":"Professional",
            "subcategory":"Accounting & Tax Preparation",
            "type":"Services"
        }
    ],
    "sg:phone":"+1 609 239 4545",
    "sg:postcode":"08016",
    "sg:province":"NJ",
    "sg:tags":[
        "accountant"
    ],
    "wof:name":"Professional Services Agency Inc",
    "wof:placetype":"venue"
},
  "geometry": {"coordinates":[-74.835503,40.0662],"type":"Point"}
}