{
  "type": "Feature",
  "properties": {
    "addr:full":"283 E Bay Ave Manahawkin NJ 08050",
    "addr:housenumber":"283",
    "addr:postcode":"08050",
    "addr:street":"E Bay Ave",
    "iso:country":"US",
    "sg:address":"283 E Bay Ave",
    "sg:city":"Manahawkin",
    "sg:classifiers":[
        {
            "category":"Personal",
            "type":"Services"
        },
        {
            "category":"Shopping",
            "subcategory":"Clothing, Apparel, & Fashions",
            "type":"Retail Goods"
        }
    ],
    "sg:phone":"+1 609 597 1226",
    "sg:postcode":"08050",
    "sg:province":"NJ",
    "sg:tags":[
        "furnishing"
    ],
    "wof:name":"Corner Formals",
    "wof:placetype":"venue"
},
  "geometry": {"coordinates":[-74.250924,39.691521],"type":"Point"}
}