{
  "type": "Feature",
  "properties": {
    "addr:full":"175 Locust Ave West Long Branch NJ 07764",
    "addr:housenumber":"175",
    "addr:postcode":"07764",
    "addr:street":"Locust Ave West",
    "iso:country":"US",
    "sg:address":"175 Locust Ave",
    "sg:city":"West Long Branch",
    "sg:classifiers":[
        {
            "category":"Building & Trades",
            "subcategory":"Construction",
            "type":"Services"
        }
    ],
    "sg:phone":"+1 908 788 4046",
    "sg:postcode":"07764",
    "sg:province":"NJ",
    "sg:tags":[
        "general",
        "contractor"
    ],
    "wof:name":"Aponte Construction",
    "wof:placetype":"venue"
},
  "geometry": {"coordinates":[-74.01741,40.286088],"type":"Point"}
}