{
  "type": "Feature",
  "properties": {
    "addr:full":"227 Franklin Ave Nutley NJ 07110",
    "addr:housenumber":"227",
    "addr:postcode":"07110",
    "addr:street":"Franklin Ave",
    "iso:country":"US",
    "sg:address":"227 Franklin Ave",
    "sg:city":"Nutley",
    "sg:classifiers":[
        {
            "category":"Restaurant",
            "type":"Food & Drink"
        }
    ],
    "sg:phone":"+1 973 284 1222",
    "sg:postcode":"07110",
    "sg:province":"NJ",
    "sg:tags":[
        "chinese"
    ],
    "wof:name":"Green Jade",
    "wof:placetype":"venue"
},
  "geometry": {"coordinates":[-74.161903,40.8162],"type":"Point"}
}