{
  "type": "Feature",
  "properties": {
    "addr:full":"300 Broadacres Dr Bloomfield NJ 07003",
    "addr:housenumber":"300",
    "addr:postcode":"07003",
    "addr:street":"Broadacres Dr",
    "iso:country":"US",
    "sg:address":"300 Broadacres Dr",
    "sg:city":"Bloomfield",
    "sg:classifiers":[
        {
            "category":"Insurance",
            "subcategory":"Insurance Agent",
            "type":"Services"
        }
    ],
    "sg:phone":"+1 973 771 1010",
    "sg:postcode":"07003",
    "sg:province":"NJ",
    "wof:name":"Dpic Co",
    "wof:placetype":"venue"
},
  "geometry": {"coordinates":[-74.181962,40.838401],"type":"Point"}
}