{
  "type": "Feature",
  "properties": {
    "iso:country":"US",
    "sg:address":"8 Woodrow St",
    "sg:city":"Oakhurst",
    "sg:classifiers":[
        {
            "category":"Arena",
            "subcategory":"Sports Club",
            "type":"Entertainment"
        }
    ],
    "sg:phone":"+1   ",
    "sg:postcode":"07755",
    "sg:province":"NJ",
    "wof:name":"Ocean Township Pop Warner",
    "wof:placetype":"venue"
},
  "geometry": {"coordinates":[-74.018809,40.270727],"type":"Point"}
}