{
  "type": "Feature",
  "properties": {
    "addr:full":"213 Atlantis Ave Manahawkin NJ 08050",
    "addr:housenumber":"213",
    "addr:postcode":"08050",
    "addr:street":"Atlantis Ave",
    "iso:country":"US",
    "sg:address":"213 Atlantis Ave",
    "sg:city":"Manahawkin",
    "sg:classifiers":[
        {
            "category":"Building & Trades",
            "subcategory":"Landscaping Services",
            "type":"Services"
        }
    ],
    "sg:phone":"+1 609 978 2919",
    "sg:postcode":"08050",
    "sg:province":"NJ",
    "wof:name":"Affordable Groundsman",
    "wof:placetype":"venue"
},
  "geometry": {"coordinates":[-74.28503499999999,39.73688],"type":"Point"}
}