{
  "type": "Feature",
  "properties": {
    "iso:country":"US",
    "sg:address":"448 S Orange Ave",
    "sg:city":"Newark",
    "sg:classifiers":[
        {
            "category":"Autos & Motor Vehicles",
            "subcategory":"Automobile Sales",
            "type":"Retail Goods"
        }
    ],
    "sg:phone":"+1 973 648 0666",
    "sg:postcode":"07103",
    "sg:province":"NJ",
    "sg:tags":[
        "car",
        "dealer"
    ],
    "wof:name":"Delox Auto Sales",
    "wof:placetype":"venue"
},
  "geometry": {"coordinates":[-74.205741,40.742308],"type":"Point"}
}