{
  "type": "Feature",
  "properties": {
    "iso:country":"US",
    "sg:address":"175 Broadway",
    "sg:city":"Paterson",
    "sg:classifiers":[
        {
            "category":"Restaurant",
            "type":"Food & Drink"
        }
    ],
    "sg:phone":"+1 973 925 2442",
    "sg:postcode":"07505",
    "sg:province":"NJ",
    "wof:name":"Walker Realty Group",
    "wof:placetype":"venue"
},
  "geometry": {"coordinates":[-74.167663,40.918917],"type":"Point"}
}