{
  "type": "Feature",
  "properties": {
    "iso:country":"US",
    "sg:address":"81 Hanover Rd",
    "sg:city":"East Hanover",
    "sg:classifiers":[
        {
            "category":"Building & Trades",
            "subcategory":"Electrical",
            "type":"Services"
        }
    ],
    "sg:phone":"+1 973 884 2137",
    "sg:postcode":"07936",
    "sg:province":"NJ",
    "sg:tags":[
        "electrical",
        "contractor"
    ],
    "wof:name":"Kemper Electric Inc",
    "wof:placetype":"venue"
},
  "geometry": {"coordinates":[-74.37426499999999,40.796347],"type":"Point"}
}