{
  "type": "Feature",
  "properties": {
    "iso:country":"US",
    "sg:address":"1807 W 7th St",
    "sg:city":"Piscataway",
    "sg:classifiers":[
        {
            "category":"Building & Trades",
            "subcategory":"Construction",
            "type":"Services"
        }
    ],
    "sg:phone":"+1 732 968 4947",
    "sg:postcode":"08854",
    "sg:province":"NJ",
    "sg:tags":[
        "hanging",
        "contractor"
    ],
    "wof:name":"Snyders Painting Plus",
    "wof:placetype":"venue"
},
  "geometry": {"coordinates":[-74.44989700000001,40.586211],"type":"Point"}
}