{
  "type": "Feature",
  "properties": {
    "iso:country":"US",
    "sg:address":"9 Washington Ave",
    "sg:city":"Tenafly",
    "sg:classifiers":[
        {
            "category":"Travel",
            "subcategory":"Travel Agent",
            "type":"Entertainment"
        }
    ],
    "sg:phone":"+1 201 568 9290",
    "sg:postcode":"07670",
    "sg:province":"NJ",
    "sg:tags":[
        "agency",
        "bureau"
    ],
    "wof:name":"Concepts In Travel Inc",
    "wof:placetype":"venue"
},
  "geometry": {"coordinates":[-73.96637200000001,40.925526],"type":"Point"}
}