{
  "type": "Feature",
  "properties": {
    "addr:full":"680 River Rd New Milford NJ 07646",
    "addr:housenumber":"680",
    "addr:postcode":"07646",
    "addr:street":"River Rd",
    "iso:country":"US",
    "sg:address":"680 River Rd",
    "sg:city":"New Milford",
    "sg:classifiers":[
        {
            "category":"Personal",
            "subcategory":"Beauty Salon",
            "type":"Services"
        }
    ],
    "sg:phone":"+1 201 265 7300",
    "sg:postcode":"07646",
    "sg:province":"NJ",
    "sg:tags":[
        "nail",
        "manicuring"
    ],
    "wof:name":"Pinky Nail Salon",
    "wof:placetype":"venue"
},
  "geometry": {"coordinates":[-74.02531399999999,40.93189],"type":"Point"}
}