{
  "type": "Feature",
  "properties": {
    "addr:full":"1825 Manor Dr Union NJ 07083",
    "addr:housenumber":"1825",
    "addr:postcode":"07083",
    "addr:street":"Manor Dr",
    "iso:country":"US",
    "sg:address":"1825 Manor Dr",
    "sg:city":"Union",
    "sg:classifiers":[
        {
            "category":"Freight",
            "type":"Transportation"
        }
    ],
    "sg:phone":"+1 908 688 4617",
    "sg:postcode":"07083",
    "sg:province":"NJ",
    "sg:tags":[
        "operator",
        "trucking"
    ],
    "wof:name":"Moralewski Marcin",
    "wof:placetype":"venue"
},
  "geometry": {"coordinates":[-74.24866400000001,40.711896],"type":"Point"}
}