{
  "type": "Feature",
  "properties": {
    "iso:country":"US",
    "sg:address":"1120 Bloomfield Ave",
    "sg:city":"West Caldwell",
    "sg:classifiers":[
        {
            "category":"Professional",
            "subcategory":"Detective & Security Services",
            "type":"Services"
        }
    ],
    "sg:phone":"+1 973 882 5556",
    "sg:postcode":"07006",
    "sg:province":"NJ",
    "sg:tags":[
        "guard",
        "patrol"
    ],
    "wof:name":"Decker Assoc",
    "wof:placetype":"venue"
},
  "geometry": {"coordinates":[-74.311717,40.855621],"type":"Point"}
}