{
  "type": "Feature",
  "properties": {
    "iso:country":"US",
    "sg:address":"112 S Ave E",
    "sg:city":"Cranford",
    "sg:classifiers":[
        {
            "category":"Bars & Pubs",
            "type":"Food & Drink"
        },
        {
            "category":"Restaurant",
            "type":"Food & Drink"
        }
    ],
    "sg:phone":"+1 908 276 3414",
    "sg:postcode":"07016",
    "sg:province":"NJ",
    "sg:tags":[
        "traditional",
        "american"
    ],
    "sg:website":"www.thekilkennyhouse.com/",
    "wof:name":"The Kilkenny House Pub and Restuarant",
    "wof:placetype":"venue"
},
  "geometry": {"coordinates":[-74.3036,40.6543],"type":"Point"}
}