{
  "type": "Feature",
  "properties": {
    "iso:country":"US",
    "sg:address":"34 Mountain Park Rd",
    "sg:city":"Clifton",
    "sg:classifiers":[
        {
            "category":"Professional",
            "subcategory":"Computer Services",
            "type":"Services"
        }
    ],
    "sg:phone":"+1   ",
    "sg:postcode":"07013",
    "sg:province":"NJ",
    "wof:name":"Argencomp Inc",
    "wof:placetype":"venue"
},
  "geometry": {"coordinates":[-74.175488,40.894304],"type":"Point"}
}