{
  "type": "Feature",
  "properties": {
    "iso:country":"US",
    "sg:address":"379 Mount Lucas Rd",
    "sg:city":"Princeton",
    "sg:classifiers":[
        {
            "category":"Real Estate",
            "subcategory":"Architect",
            "type":"Services"
        }
    ],
    "sg:phone":"+1 609 921 0421",
    "sg:postcode":"08540",
    "sg:province":"NJ",
    "wof:name":"Thomas E White Architect",
    "wof:placetype":"venue"
},
  "geometry": {"coordinates":[-74.656819,40.376316],"type":"Point"}
}