{
  "type": "Feature",
  "properties": {
    "iso:country":"US",
    "sg:address":"225 Main St",
    "sg:city":"Orange",
    "sg:classifiers":[
        {
            "category":"Shopping",
            "subcategory":"Optician",
            "type":"Retail Goods"
        }
    ],
    "sg:phone":"+1 973 678 2600",
    "sg:postcode":"07050",
    "sg:province":"NJ",
    "sg:tags":[
        "eyewear"
    ],
    "wof:name":"Optical Kare Llc",
    "wof:placetype":"venue"
},
  "geometry": {"coordinates":[-74.227307,40.771407],"type":"Point"}
}