{
  "type": "Feature",
  "properties": {
    "addr:full":"229 S Van Brunt St Englewood NJ 07631",
    "addr:housenumber":"229",
    "addr:postcode":"07631",
    "addr:street":"S Van Brunt St",
    "iso:country":"US",
    "sg:address":"229 S Van Brunt St",
    "sg:city":"Englewood",
    "sg:classifiers":[
        {
            "category":"Manufacturing",
            "subcategory":"Apparel",
            "type":"Manufacturing & Wholesale Goods"
        }
    ],
    "sg:phone":"+1 201 313 0022",
    "sg:postcode":"07631",
    "sg:province":"NJ",
    "sg:tags":[
        "mfg",
        "trimming"
    ],
    "wof:name":"A A World Class Corp",
    "wof:placetype":"venue"
},
  "geometry": {"coordinates":[-73.981104,40.88884],"type":"Point"}
}