{
  "type": "Feature",
  "properties": {
    "addr:full":"614 Mount Laurel Rd Mt Laurel NJ 08054",
    "addr:housenumber":"614",
    "addr:postcode":"08054",
    "addr:street":"Mount Laurel Rd",
    "iso:country":"US",
    "sg:address":"614 Mount Laurel Rd",
    "sg:city":"Mt Laurel",
    "sg:classifiers":[
        {
            "category":"Retail",
            "subcategory":"Car Wash",
            "type":"Services"
        }
    ],
    "sg:phone":"+1 856 234 2058",
    "sg:postcode":"08054",
    "sg:province":"NJ",
    "sg:tags":[
        "automobile",
        "detail",
        "clean"
    ],
    "wof:name":"Resurrect It",
    "wof:placetype":"venue"
},
  "geometry": {"coordinates":[-74.886296,39.928791],"type":"Point"}
}