{
  "type": "Feature",
  "properties": {
    "iso:country":"US",
    "sg:address":"23 Vreeland Rd",
    "sg:city":"Florham Park",
    "sg:classifiers":[
        {
            "category":"Professional",
            "subcategory":"Lawyer & Legal Services",
            "type":"Services"
        }
    ],
    "sg:phone":"+1 973 325 1963",
    "sg:postcode":"07932",
    "sg:province":"NJ",
    "sg:tags":[
        "attorney"
    ],
    "sg:website":"www.nj-lawyer.com",
    "wof:name":"Carchman Sochor Schwarts/Ragsd",
    "wof:placetype":"venue"
},
  "geometry": {"coordinates":[-74.375936,40.794965],"type":"Point"}
}