{
  "type": "Feature",
  "properties": {
    "addr:full":"108 Gaither Dr Mount Laurel NJ 08054",
    "addr:housenumber":"108",
    "addr:postcode":"08054",
    "addr:street":"Gaither Dr",
    "iso:country":"US",
    "sg:address":"108 Gaither Dr",
    "sg:city":"Mount Laurel",
    "sg:classifiers":[
        {
            "category":"Home & Garden",
            "subcategory":"Furniture",
            "type":"Retail Goods"
        }
    ],
    "sg:phone":"+1   ",
    "sg:postcode":"08054",
    "sg:province":"NJ",
    "wof:name":"Global Industries Inc",
    "wof:placetype":"venue"
},
  "geometry": {"coordinates":[-74.954848,39.937133],"type":"Point"}
}