{
  "type": "Feature",
  "properties": {
    "addr:full":"7001 English Creek Ave Egg Harbor Township NJ 08234",
    "addr:housenumber":"7001",
    "addr:postcode":"08234",
    "addr:street":"English Creek Ave",
    "iso:country":"US",
    "sg:address":"7001 English Creek Ave",
    "sg:city":"Egg Harbor Township",
    "sg:classifiers":[
        {
            "category":"Arts & Performance",
            "subcategory":"Theater",
            "type":"Entertainment"
        }
    ],
    "sg:phone":"+1   ",
    "sg:postcode":"08234",
    "sg:province":"NJ",
    "sg:tags":[
        "promotion"
    ],
    "wof:name":"Paul Dick Music and Entrmt",
    "wof:placetype":"venue"
},
  "geometry": {"coordinates":[-74.65134999999999,39.373337],"type":"Point"}
}