{
  "type": "Feature",
  "properties": {
    "iso:country":"US",
    "sg:address":"1402 Teaneck Rd",
    "sg:city":"Teaneck",
    "sg:classifiers":[
        {
            "category":"Health Services",
            "subcategory":"Clinic",
            "type":"Services"
        }
    ],
    "sg:phone":"+1 201 261 7038",
    "sg:postcode":"07666",
    "sg:province":"NJ",
    "sg:tags":[
        "medical"
    ],
    "wof:name":"Bonaventure Medical",
    "wof:placetype":"venue"
},
  "geometry": {"coordinates":[-73.99971499999999,40.900565],"type":"Point"}
}