{
  "type": "Feature",
  "properties": {
    "addr:full":"259 W Broadway Paterson NJ 07522",
    "addr:housenumber":"259",
    "addr:postcode":"07522",
    "addr:street":"W Broadway",
    "iso:country":"US",
    "sg:address":"259 W Broadway",
    "sg:city":"Paterson",
    "sg:classifiers":[
        {
            "category":"Building & Trades",
            "subcategory":"Construction",
            "type":"Services"
        }
    ],
    "sg:phone":"+1 973 956 9191",
    "sg:postcode":"07522",
    "sg:province":"NJ",
    "sg:tags":[
        "contractor"
    ],
    "sg:website":"www.pumaconstructioninc.com",
    "wof:name":"Puma Construction Inc",
    "wof:placetype":"venue"
},
  "geometry": {"coordinates":[-74.181826,40.924731],"type":"Point"}
}