{
  "type": "Feature",
  "properties": {
    "addr:full":"24 Prestwick Way Edison NJ 08820",
    "addr:housenumber":"24",
    "addr:postcode":"08820",
    "addr:street":"Prestwick Way",
    "iso:country":"US",
    "sg:address":"24 Prestwick Way",
    "sg:city":"Edison",
    "sg:classifiers":[
        {
            "category":"Restaurant",
            "type":"Food & Drink"
        }
    ],
    "sg:phone":"+1   ",
    "sg:postcode":"08820",
    "sg:province":"NJ",
    "sg:tags":[
        "eating"
    ],
    "wof:name":"Sunny World Inc",
    "wof:placetype":"venue"
},
  "geometry": {"coordinates":[-74.396722,40.554555],"type":"Point"}
}