{
  "type": "Feature",
  "properties": {
    "iso:country":"US",
    "sg:address":"359 State Rte 23",
    "sg:city":"Sussex",
    "sg:classifiers":[
        {
            "category":"Health Services",
            "subcategory":"Chiropractor",
            "type":"Services"
        }
    ],
    "sg:phone":"+1 973 875 8700",
    "sg:postcode":"07461",
    "sg:province":"NJ",
    "wof:name":"William Preston DC",
    "wof:placetype":"venue"
},
  "geometry": {"coordinates":[-74.592506,41.196595],"type":"Point"}
}