{
  "type": "Feature",
  "properties": {
    "iso:country":"US",
    "sg:address":"134 Leslie Ave",
    "sg:city":"Merchantville",
    "sg:classifiers":[
        {
            "category":"Building & Trades",
            "subcategory":"Plumbing",
            "type":"Services"
        }
    ],
    "sg:phone":"+1 856 662 3500",
    "sg:postcode":"08109",
    "sg:province":"NJ",
    "sg:tags":[
        "drain",
        "consultant",
        "sewer",
        "cleaning",
        "plumbing-drain"
    ],
    "sg:website":"http://www.plumbmedicinc.com",
    "wof:name":"Plumb Medic",
    "wof:placetype":"venue"
},
  "geometry": {"coordinates":[-75.05276600000001,39.954027],"type":"Point"}
}