{
  "type": "Feature",
  "properties": {
    "iso:country":"US",
    "sg:address":"1230 Cellar Ave",
    "sg:city":"Clark",
    "sg:classifiers":[
        {
            "category":"Building & Trades",
            "subcategory":"Cleaning & Sanitation",
            "type":"Services"
        }
    ],
    "sg:phone":"+1 973 583 7745",
    "sg:postcode":"07066",
    "sg:province":"NJ",
    "wof:name":"Jemmotts Cleaning Service",
    "wof:placetype":"venue"
},
  "geometry": {"coordinates":[-74.337248,40.615015],"type":"Point"}
}