{
  "type": "Feature",
  "properties": {
    "addr:full":"2417 Wainwright St Camden NJ 08104",
    "addr:housenumber":"2417",
    "addr:postcode":"08104",
    "addr:street":"Wainwright St",
    "iso:country":"US",
    "sg:address":"2417 Wainwright St",
    "sg:city":"Camden",
    "sg:classifiers":[
        {
            "category":"Sports & Exercise",
            "subcategory":"Sports Center",
            "type":"Entertainment"
        }
    ],
    "sg:phone":"+1 856 541 7567",
    "sg:postcode":"08104",
    "sg:province":"NJ",
    "sg:website":"http://www.littleleaguebaseball.net",
    "wof:name":"Little League Baseball Incorporated",
    "wof:placetype":"venue"
},
  "geometry": {"coordinates":[-75.10345,39.913075],"type":"Point"}
}