{
  "type": "Feature",
  "properties": {
    "iso:country":"US",
    "sg:address":"1703 E 2nd St",
    "sg:city":"Scotch Plains",
    "sg:classifiers":[
        {
            "category":"Professional",
            "type":"Services"
        }
    ],
    "sg:phone":"+1   ",
    "sg:postcode":"07076",
    "sg:province":"NJ",
    "wof:name":"Fermins Art Studio",
    "wof:placetype":"venue"
},
  "geometry": {"coordinates":[-74.399553,40.646159],"type":"Point"}
}