{
  "type": "Feature",
  "properties": {
    "iso:country":"US",
    "sg:address":"123 Martha Rd",
    "sg:city":"Harrington Park",
    "sg:classifiers":[
        {
            "category":"Wholesale",
            "subcategory":"Medical Equipment & Supplies",
            "type":"Manufacturing & Wholesale Goods"
        }
    ],
    "sg:phone":"+1 201 768 9311",
    "sg:postcode":"07640",
    "sg:province":"NJ",
    "sg:tags":[
        "physician",
        "surgeon"
    ],
    "wof:name":"Siemens Medical Solutions",
    "wof:placetype":"venue"
},
  "geometry": {"coordinates":[-73.985292,40.98471],"type":"Point"}
}