{
  "type": "Feature",
  "properties": {
    "addr:full":"20 Mary Ct Berkeley Heights NJ 07922",
    "addr:housenumber":"20",
    "addr:postcode":"07922",
    "addr:street":"Mary Ct",
    "iso:country":"US",
    "sg:address":"20 Mary Ct",
    "sg:city":"Berkeley Heights",
    "sg:classifiers":[
        {
            "category":"Professional",
            "subcategory":"Business Services",
            "type":"Services"
        }
    ],
    "sg:phone":"+1 908 464 0896",
    "sg:postcode":"07922",
    "sg:province":"NJ",
    "sg:tags":[
        "accessory"
    ],
    "wof:name":"Dakin Group Inc",
    "wof:placetype":"venue"
},
  "geometry": {"coordinates":[-74.413597,40.673199],"type":"Point"}
}