{
  "type": "Feature",
  "properties": {
    "iso:country":"US",
    "sg:address":"214 Sykesville Rd",
    "sg:city":"Wrightstown",
    "sg:classifiers":[
        {
            "category":"Building & Trades",
            "subcategory":"Construction",
            "type":"Services"
        }
    ],
    "sg:phone":"+1 609 324 3703",
    "sg:postcode":"08515",
    "sg:province":"NJ",
    "sg:tags":[
        "hanging",
        "contractor"
    ],
    "wof:name":"Burlington Adult Training Ctr",
    "wof:placetype":"venue"
},
  "geometry": {"coordinates":[-74.62152,40.075491],"type":"Point"}
}