{
  "type": "Feature",
  "properties": {
    "addr:full":"449 High St Burlington NJ 08016",
    "addr:housenumber":"449",
    "addr:postcode":"08016",
    "addr:street":"High St",
    "iso:country":"US",
    "sg:address":"449 High St",
    "sg:city":"Burlington",
    "sg:classifiers":[
        {
            "category":"Building & Trades",
            "subcategory":"Equipment Rental",
            "type":"Services"
        },
        {
            "category":"Shopping",
            "subcategory":"Computers & Home Electronics",
            "type":"Retail Goods"
        }
    ],
    "sg:phone":"+1 609 387 3636",
    "sg:postcode":"08016",
    "sg:province":"NJ",
    "sg:tags":[
        "stereo",
        "leasing",
        "video",
        "audio",
        "equipment-renting",
        "audio-visual"
    ],
    "wof:name":"Audio Visual Systems Rental Centres",
    "wof:placetype":"venue"
},
  "geometry": {"coordinates":[-74.857547,40.076431],"type":"Point"}
}