{
  "type": "Feature",
  "properties": {
    "iso:country":"US",
    "sg:address":"16 Country Club Rd",
    "sg:city":"Parsippany",
    "sg:classifiers":[
        {
            "category":"Sports & Exercise",
            "subcategory":"Golf",
            "type":"Entertainment"
        }
    ],
    "sg:phone":"+1 973 627 5995",
    "sg:postcode":"07054",
    "sg:province":"NJ",
    "wof:name":"Mount Tabor Country Club Pro Shop",
    "wof:placetype":"venue"
},
  "geometry": {"coordinates":[-74.40770000000001,40.867901],"type":"Point"}
}