{
  "type": "Feature",
  "properties": {
    "iso:country":"US",
    "sg:address":"506 26th St",
    "sg:city":"Union City",
    "sg:classifiers":[
        {
            "category":"Professional",
            "type":"Services"
        },
        {
            "category":"Real Estate",
            "subcategory":"Real Estate Agent",
            "type":"Services"
        }
    ],
    "sg:phone":"+1 201 863 7317",
    "sg:postcode":"07087",
    "sg:province":"NJ",
    "sg:tags":[
        "management",
        "establishment"
    ],
    "wof:name":"F E K O Management Corp",
    "wof:placetype":"venue"
},
  "geometry": {"coordinates":[-74.032661,40.769309],"type":"Point"}
}