{
  "type": "Feature",
  "properties": {
    "iso:country":"US",
    "sg:address":"114 Village Dr",
    "sg:city":"Barnegat",
    "sg:classifiers":[
        {
            "category":"Wholesale",
            "subcategory":"Hardware",
            "type":"Manufacturing & Wholesale Goods"
        }
    ],
    "sg:phone":"+1 609 698 1503",
    "sg:postcode":"08005",
    "sg:province":"NJ",
    "wof:name":"GL Tools & Equipment",
    "wof:placetype":"venue"
},
  "geometry": {"coordinates":[-74.246122,39.741429],"type":"Point"}
}