{
  "type": "Feature",
  "properties": {
    "addr:full":"340 Broadway Hillsdale NJ 07642",
    "addr:housenumber":"340",
    "addr:postcode":"07642",
    "addr:street":"Broadway",
    "iso:country":"US",
    "sg:address":"340 Broadway",
    "sg:city":"Hillsdale",
    "sg:classifiers":[
        {
            "category":"Shopping",
            "subcategory":"Bicycles & Sporting Goods",
            "type":"Retail Goods"
        }
    ],
    "sg:phone":"+1 201 664 5600",
    "sg:postcode":"07642",
    "sg:province":"NJ",
    "wof:name":"Sports Expert Inc",
    "wof:placetype":"venue"
},
  "geometry": {"coordinates":[-74.042315,41.010861],"type":"Point"}
}