{
  "type": "Feature",
  "properties": {
    "iso:country":"US",
    "sg:address":"47 E Beaver Dr",
    "sg:city":"Cape May Court House",
    "sg:classifiers":[
        {
            "category":"Shopping",
            "subcategory":"Books",
            "type":"Retail Goods"
        }
    ],
    "sg:phone":"+1   ",
    "sg:postcode":"08210",
    "sg:province":"NJ",
    "sg:tags":[
        "store"
    ],
    "wof:name":"Rck Transport Inc",
    "wof:placetype":"venue"
},
  "geometry": {"coordinates":[-74.778812,39.159592],"type":"Point"}
}