{
  "type": "Feature",
  "properties": {
    "addr:full":"1221 Middle Ave Waterford Works NJ 08089",
    "addr:housenumber":"1221",
    "addr:postcode":"08089",
    "addr:street":"Middle Ave",
    "iso:country":"US",
    "sg:address":"1221 Middle Ave",
    "sg:city":"Waterford Works",
    "sg:classifiers":[
        {
            "category":"Professional",
            "subcategory":"Business Services",
            "type":"Services"
        }
    ],
    "sg:phone":"+1   ",
    "sg:postcode":"08089",
    "sg:province":"NJ",
    "wof:name":"Westwind Stables",
    "wof:placetype":"venue"
},
  "geometry": {"coordinates":[-74.834784,39.726879],"type":"Point"}
}