{
  "type": "Feature",
  "properties": {
    "iso:country":"US",
    "sg:address":"7 Olde Greenhouse Ln",
    "sg:city":"Madison",
    "sg:classifiers":[
        {
            "category":"Retail",
            "subcategory":"Veterinary Services",
            "type":"Services"
        }
    ],
    "sg:phone":"+1 973 822 0514",
    "sg:postcode":"07940",
    "sg:province":"NJ",
    "sg:tags":[
        "veterinarian"
    ],
    "wof:name":"M Palescandolo DVM",
    "wof:placetype":"venue"
},
  "geometry": {"coordinates":[-74.419624,40.745145],"type":"Point"}
}