{
  "type": "Feature",
  "properties": {
    "iso:country":"US",
    "sg:address":"6 Malden Ct",
    "sg:city":"Bergenfield",
    "sg:classifiers":[
        {
            "category":"Professional",
            "subcategory":"Management & Consulting",
            "type":"Services"
        }
    ],
    "sg:phone":"+1 201 385 7525",
    "sg:postcode":"07621",
    "sg:province":"NJ",
    "wof:name":"Hcm Enterprises Inc",
    "wof:placetype":"venue"
},
  "geometry": {"coordinates":[-74.00377,40.914626],"type":"Point"}
}