{
  "type": "Feature",
  "properties": {
    "addr:full":"130 Old Cranbury Rd Cranbury NJ 08512",
    "addr:housenumber":"130",
    "addr:postcode":"08512",
    "addr:street":"Old Cranbury Rd",
    "iso:country":"US",
    "sg:address":"130 Old Cranbury Rd",
    "sg:city":"Cranbury",
    "sg:classifiers":[
        {
            "category":"Wholesale",
            "subcategory":"Computers",
            "type":"Manufacturing & Wholesale Goods"
        }
    ],
    "sg:phone":"+1 201 664 1050",
    "sg:postcode":"08512",
    "sg:province":"NJ",
    "sg:tags":[
        "equipment",
        "lease"
    ],
    "wof:name":"E T C",
    "wof:placetype":"venue"
},
  "geometry": {"coordinates":[-74.524734,40.287478],"type":"Point"}
}