{
  "type": "Feature",
  "properties": {
    "addr:full":"130 Ryerson Ave Wayne NJ 07470",
    "addr:housenumber":"130",
    "addr:postcode":"07470",
    "addr:street":"Ryerson Ave",
    "iso:country":"US",
    "sg:address":"130 Ryerson Ave",
    "sg:city":"Wayne",
    "sg:classifiers":[
        {
            "category":"Building & Trades",
            "subcategory":"Landscaping Services",
            "type":"Services"
        }
    ],
    "sg:phone":"+1 973 694 6545",
    "sg:postcode":"07470",
    "sg:province":"NJ",
    "sg:tags":[
        "landscape"
    ],
    "wof:name":"Landscape Perceptions",
    "wof:placetype":"venue"
},
  "geometry": {"coordinates":[-74.275994,40.925619],"type":"Point"}
}