{
  "type": "Feature",
  "properties": {
    "iso:country":"US",
    "sg:address":"101 Oak Tree Rd",
    "sg:city":"South Plainfield",
    "sg:classifiers":[
        {
            "category":"Retail",
            "subcategory":"Auto Repair",
            "type":"Services"
        }
    ],
    "sg:phone":"+1   ",
    "sg:postcode":"07080",
    "sg:province":"NJ",
    "sg:tags":[
        "automotive",
        "filling",
        "station",
        "gasoline"
    ],
    "wof:name":"Good Time Auto Repair",
    "wof:placetype":"venue"
},
  "geometry": {"coordinates":[-74.40725500000001,40.580024],"type":"Point"}
}