{
  "type": "Feature",
  "properties": {
    "addr:full":"9 Devon Rd Long Valley NJ 07853",
    "addr:housenumber":"9",
    "addr:postcode":"07853",
    "addr:street":"Devon Rd",
    "iso:country":"US",
    "sg:address":"9 Devon Rd",
    "sg:city":"Long Valley",
    "sg:classifiers":[
        {
            "category":"Real Estate",
            "subcategory":"Real Estate Agent",
            "type":"Services"
        }
    ],
    "sg:phone":"+1   ",
    "sg:postcode":"07853",
    "sg:province":"NJ",
    "wof:name":"Weichert Realtors",
    "wof:placetype":"venue"
},
  "geometry": {"coordinates":[-74.771756,40.820084],"type":"Point"}
}