{
  "type": "Feature",
  "properties": {
    "addr:full":"169 State Rte 33 Manalapan NJ 07726",
    "addr:housenumber":"169",
    "addr:postcode":"07726",
    "addr:street":"State Rte 33",
    "iso:country":"US",
    "sg:address":"169 State Rte 33",
    "sg:city":"Manalapan",
    "sg:classifiers":[
        {
            "category":"Building & Trades",
            "subcategory":"Landscaping Services",
            "type":"Services"
        }
    ],
    "sg:phone":"+1 732 845 1395",
    "sg:postcode":"07726",
    "sg:province":"NJ",
    "sg:tags":[
        "landscape",
        "contractor"
    ],
    "wof:name":"Dom's Lakeview Landscaping Inc",
    "wof:placetype":"venue"
},
  "geometry": {"coordinates":[-74.341701,40.253468],"type":"Point"}
}