{
  "type": "Feature",
  "properties": {
    "iso:country":"US",
    "sg:address":"137 Aura Rd",
    "sg:city":"Pilesgrove",
    "sg:classifiers":[
        {
            "category":"Retail",
            "subcategory":"Repair Shop",
            "type":"Services"
        },
        {
            "category":"Building & Trades",
            "subcategory":"Plumbing",
            "type":"Services"
        }
    ],
    "sg:phone":"+1 856 769 2856",
    "sg:postcode":"08028",
    "sg:province":"NJ",
    "sg:tags":[
        "refrigeration",
        "electrical",
        "heating",
        "contractor"
    ],
    "wof:name":"Elder's Services",
    "wof:placetype":"venue"
},
  "geometry": {"coordinates":[-75.16035599999999,39.718361],"type":"Point"}
}