{
  "type": "Feature",
  "properties": {
    "addr:full":"365 Carnegie Ave Kenilworth NJ 07033",
    "addr:housenumber":"365",
    "addr:postcode":"07033",
    "addr:street":"Carnegie Ave",
    "iso:country":"US",
    "sg:address":"365 Carnegie Ave",
    "sg:city":"Kenilworth",
    "sg:classifiers":[
        {
            "category":"Professional",
            "type":"Services"
        }
    ],
    "sg:phone":"+1 908 245 4500",
    "sg:postcode":"07033",
    "sg:province":"NJ",
    "sg:tags":[
        "pipe",
        "equipment",
        "line"
    ],
    "sg:website":"www.ramco-safetyshields.com",
    "wof:name":"Ramco Manufacturing Co",
    "wof:placetype":"venue"
},
  "geometry": {"coordinates":[-74.279084,40.66769],"type":"Point"}
}