{
  "type": "Feature",
  "properties": {
    "addr:full":"1020 Boardwalk Seaside Heights NJ 08751",
    "addr:housenumber":"1020",
    "addr:postcode":"08751",
    "addr:street":"Boardwalk Seaside",
    "iso:country":"US",
    "sg:address":"1020 Boardwalk",
    "sg:city":"Seaside Heights",
    "sg:classifiers":[
        {
            "category":"Recreation",
            "subcategory":"Amusement Park",
            "type":"Entertainment"
        },
        {
            "category":"Recreation",
            "subcategory":"Arcade",
            "type":"Entertainment"
        }
    ],
    "sg:phone":"+1 732 793 0600",
    "sg:postcode":"08751",
    "sg:province":"NJ",
    "wof:name":"Big Top Arcade Inc",
    "wof:placetype":"venue"
},
  "geometry": {"coordinates":[-74.06995499999999,39.943877],"type":"Point"}
}