{
  "type": "Feature",
  "properties": {
    "addr:full":"358 Kinderkamack Rd Emerson NJ 07630",
    "addr:housenumber":"358",
    "addr:postcode":"07630",
    "addr:street":"Kinderkamack Rd",
    "iso:country":"US",
    "sg:address":"358 Kinderkamack Rd",
    "sg:city":"Emerson",
    "sg:classifiers":[
        {
            "category":"Retail",
            "subcategory":"Repair Shop",
            "type":"Services"
        }
    ],
    "sg:phone":"+1   ",
    "sg:postcode":"07630",
    "sg:province":"NJ",
    "sg:tags":[
        "good",
        "art",
        "custom",
        "framing",
        "knitting",
        "gallery"
    ],
    "wof:name":"Creations N Things Inc",
    "wof:placetype":"venue"
},
  "geometry": {"coordinates":[-74.024332,40.981335],"type":"Point"}
}