{
  "type": "Feature",
  "properties": {
    "iso:country":"US",
    "sg:address":"17 Williamsburg Dr",
    "sg:city":"Neptune",
    "sg:classifiers":[
        {
            "category":"Restaurant",
            "type":"Food & Drink"
        }
    ],
    "sg:phone":"+1 732 922 2411",
    "sg:postcode":"07753",
    "sg:province":"NJ",
    "sg:tags":[
        "eating",
        "caterer"
    ],
    "wof:name":"Silk Catering",
    "wof:placetype":"venue"
},
  "geometry": {"coordinates":[-74.08537099999999,40.251461],"type":"Point"}
}