{
  "type": "Feature",
  "properties": {
    "iso:country":"US",
    "sg:address":"473 State Rte 79",
    "sg:city":"Morganville",
    "sg:classifiers":[
        {
            "category":"Banks & Credit Unions",
            "subcategory":"Bank",
            "type":"Services"
        }
    ],
    "sg:phone":"+1 732 000 1111",
    "sg:postcode":"07751",
    "sg:province":"NJ",
    "wof:name":"Synergy Bank",
    "wof:placetype":"venue"
},
  "geometry": {"coordinates":[-74.24158,40.382592],"type":"Point"}
}