{
  "type": "Feature",
  "properties": {
    "addr:full":"3 Commonwealth Ave New Providence NJ 07974",
    "addr:housenumber":"3",
    "addr:postcode":"07974",
    "addr:street":"Commonwealth Ave",
    "iso:country":"US",
    "sg:address":"3 Commonwealth Ave",
    "sg:city":"New Providence",
    "sg:classifiers":[
        {
            "category":"Building & Trades",
            "subcategory":"Construction",
            "type":"Services"
        }
    ],
    "sg:phone":"+1 908 464 9495",
    "sg:postcode":"07974",
    "sg:province":"NJ",
    "sg:tags":[
        "carpenter"
    ],
    "wof:name":"Beach Construction",
    "wof:placetype":"venue"
},
  "geometry": {"coordinates":[-74.40664700000001,40.712997],"type":"Point"}
}