{
  "type": "Feature",
  "properties": {
    "addr:full":"30 Mall Drive W Newport Centre Mall Jersey City NJ 07310",
    "addr:housenumber":"30",
    "addr:postcode":"07310",
    "addr:street":"Mall Drive W Newport Centre Mall",
    "iso:country":"US",
    "sg:address":"30 Mall Drive W Newport Centre Mall",
    "sg:city":"Jersey City",
    "sg:classifiers":[
        {
            "category":"Fast Food",
            "type":"Food & Drink"
        }
    ],
    "sg:phone":"+1 201 656 1300",
    "sg:postcode":"07310",
    "sg:province":"NJ",
    "sg:tags":[
        "chicken",
        "wing"
    ],
    "sg:website":"www.wingery.com",
    "wof:name":"Wow Cafe and Wingery",
    "wof:placetype":"venue"
},
  "geometry": {"coordinates":[-74.038285,40.726857],"type":"Point"}
}