{
  "type": "Feature",
  "properties": {
    "iso:country":"US",
    "sg:address":"194 Kinderkamack Rd",
    "sg:city":"Hillsdale",
    "sg:classifiers":[
        {
            "category":"Shopping",
            "subcategory":"Used Merchandise",
            "type":"Retail Goods"
        }
    ],
    "sg:phone":"+1 201 664 0525",
    "sg:postcode":"07642",
    "sg:province":"NJ",
    "sg:tags":[
        "antique"
    ],
    "wof:name":"D R Estate & Tag Sale Spec",
    "wof:placetype":"venue"
},
  "geometry": {"coordinates":[-74.033491,41.006454],"type":"Point"}
}