{
  "type": "Feature",
  "properties": {
    "iso:country":"US",
    "sg:address":"2439 State Rte 34",
    "sg:city":"Manasquan",
    "sg:classifiers":[
        {
            "category":"Retail",
            "subcategory":"Laundry & Dry Cleaning",
            "type":"Services"
        }
    ],
    "sg:phone":"+1 732 223 4100",
    "sg:postcode":"08736",
    "sg:province":"NJ",
    "sg:tags":[
        "cleaners"
    ],
    "wof:name":"Wall Towne Dry Cleaners",
    "wof:placetype":"venue"
},
  "geometry": {"coordinates":[-74.078929,40.121068],"type":"Point"}
}