{
  "type": "Feature",
  "properties": {
    "iso:country":"US",
    "sg:address":"570 Haddon Ave",
    "sg:city":"Collingswood",
    "sg:classifiers":[
        {
            "category":"Health Services",
            "subcategory":"Doctor",
            "type":"Services"
        }
    ],
    "sg:phone":"+1 856 854 3093",
    "sg:postcode":"08108",
    "sg:province":"NJ",
    "sg:tags":[
        "podiatrist"
    ],
    "wof:name":"Kraatz David DPM",
    "wof:placetype":"venue"
},
  "geometry": {"coordinates":[-75.072701,39.9175],"type":"Point"}
}