{
  "type": "Feature",
  "properties": {
    "iso:country":"US",
    "sg:address":"2816 Morris Ave",
    "sg:city":"Union",
    "sg:classifiers":[
        {
            "category":"Professional",
            "subcategory":"Engineering",
            "type":"Services"
        }
    ],
    "sg:phone":"+1 908 851 2621",
    "sg:postcode":"07083",
    "sg:province":"NJ",
    "sg:tags":[
        "engineer"
    ],
    "wof:name":"Harold Saperstein Pe Inc",
    "wof:placetype":"venue"
},
  "geometry": {"coordinates":[-74.299494,40.706732],"type":"Point"}
}