{
  "type": "Feature",
  "properties": {
    "addr:full":"2848 S Delsea Dr Vineland NJ 08360",
    "addr:housenumber":"2848",
    "addr:postcode":"08360",
    "addr:street":"S Delsea Dr",
    "iso:country":"US",
    "sg:address":"2848 S Delsea Dr",
    "sg:city":"Vineland",
    "sg:classifiers":[
        {
            "category":"Health Services",
            "subcategory":"Doctor",
            "type":"Services"
        }
    ],
    "sg:phone":"+1 856 794 9090",
    "sg:postcode":"08360",
    "sg:province":"NJ",
    "sg:tags":[
        "physician",
        "rheumatology",
        "arthritis",
        "surgeons",
        "orthopedics",
        "surgeon"
    ],
    "sg:website":"http://drsoloway.com",
    "wof:name":"Arthritis & Rheumatology Associates",
    "wof:placetype":"venue"
},
  "geometry": {"coordinates":[-75.041866,39.445486],"type":"Point"}
}