{
  "type": "Feature",
  "properties": {
    "iso:country":"US",
    "sg:address":"1090 Dove St",
    "sg:city":"Toms River",
    "sg:classifiers":[
        {
            "category":"Professional",
            "subcategory":"Computer Services",
            "type":"Services"
        }
    ],
    "sg:phone":"+1 732 270 6070",
    "sg:postcode":"08753",
    "sg:province":"NJ",
    "sg:tags":[
        "programing",
        "custom"
    ],
    "wof:name":"Todays Technologies",
    "wof:placetype":"venue"
},
  "geometry": {"coordinates":[-74.143975,39.971047],"type":"Point"}
}