{
  "type": "Feature",
  "properties": {
    "iso:country":"US",
    "sg:address":"39 Monmouth Pkwy",
    "sg:city":"Monmouth Beach",
    "sg:classifiers":[
        {
            "category":"Professional",
            "subcategory":"Business Services",
            "type":"Services"
        }
    ],
    "sg:phone":"+1 732 571 0010",
    "sg:postcode":"07750",
    "sg:province":"NJ",
    "sg:tags":[
        "interior",
        "consultant",
        "design",
        "decorator"
    ],
    "wof:name":"Ejeanne Costine",
    "wof:placetype":"venue"
},
  "geometry": {"coordinates":[-73.984261,40.335068],"type":"Point"}
}