{
  "type": "Feature",
  "properties": {
    "iso:country":"US",
    "sg:address":"575 Valley Rd",
    "sg:city":"Montclair",
    "sg:classifiers":[
        {
            "category":"Autos & Motor Vehicles",
            "subcategory":"Fuel & Gas Station",
            "type":"Retail Goods"
        }
    ],
    "sg:phone":"+1 973 744 9718",
    "sg:postcode":"07043",
    "sg:province":"NJ",
    "wof:name":"Kirkeby Getty Service Station",
    "wof:placetype":"venue"
},
  "geometry": {"coordinates":[-74.208,40.840099],"type":"Point"}
}