{
  "type": "Feature",
  "properties": {
    "addr:full":"1176 State Rte 23 Sussex NJ 07461",
    "addr:housenumber":"1176",
    "addr:postcode":"07461",
    "addr:street":"State Rte 23",
    "iso:country":"US",
    "sg:address":"1176 State Rte 23",
    "sg:city":"Sussex",
    "sg:classifiers":[
        {
            "category":"Restaurant",
            "type":"Food & Drink"
        }
    ],
    "sg:phone":"+1 973 875 3550",
    "sg:postcode":"07461",
    "sg:province":"NJ",
    "sg:tags":[
        "eating"
    ],
    "wof:name":"Elias Cole",
    "wof:placetype":"venue"
},
  "geometry": {"coordinates":[-74.646885,41.268788],"type":"Point"}
}