{
  "type": "Feature",
  "properties": {
    "addr:full":"254 Brick Blvd Brick NJ 08723",
    "addr:housenumber":"254",
    "addr:postcode":"08723",
    "addr:street":"Brick Blvd",
    "iso:country":"US",
    "sg:address":"254 Brick Blvd",
    "sg:city":"Brick",
    "sg:classifiers":[
        {
            "category":"Professional",
            "subcategory":"Management & Consulting",
            "type":"Services"
        }
    ],
    "sg:phone":"+1 732 477 4188",
    "sg:postcode":"08723",
    "sg:province":"NJ",
    "wof:name":"Highview Management LTD",
    "wof:placetype":"venue"
},
  "geometry": {"coordinates":[-74.142799,40.038555],"type":"Point"}
}