{
  "type": "Feature",
  "properties": {
    "addr:full":"936 US Hwy 202 Somerville NJ 08876",
    "addr:housenumber":"936",
    "addr:postcode":"08876",
    "addr:street":"Us Hwy 202",
    "iso:country":"US",
    "sg:address":"936 US Hwy 202",
    "sg:city":"Somerville",
    "sg:classifiers":[
        {
            "category":"Autos & Motor Vehicles",
            "subcategory":"Fuel & Gas Station",
            "type":"Retail Goods"
        }
    ],
    "sg:phone":"+1   ",
    "sg:postcode":"08876",
    "sg:province":"NJ",
    "sg:tags":[
        "station",
        "gasoline"
    ],
    "wof:name":"Exxon",
    "wof:placetype":"venue"
},
  "geometry": {"coordinates":[-74.68719,40.566552],"type":"Point"}
}