{
  "type": "Feature",
  "properties": {
    "iso:country":"US",
    "sg:address":"1280 Wall St W",
    "sg:city":"Lyndhurst",
    "sg:classifiers":[
        {
            "category":"Professional",
            "subcategory":"Accounting & Tax Preparation",
            "type":"Services"
        }
    ],
    "sg:phone":"+1 201 729 9756",
    "sg:postcode":"07071",
    "sg:province":"NJ",
    "sg:tags":[
        "accountant"
    ],
    "wof:name":"Mci Wan For Ernst & Young",
    "wof:placetype":"venue"
},
  "geometry": {"coordinates":[-74.100692,40.805361],"type":"Point"}
}