{
  "type": "Feature",
  "properties": {
    "iso:country":"US",
    "sg:address":"2206 Kuser Rd",
    "sg:city":"Trenton",
    "sg:classifiers":[
        {
            "category":"Recreation",
            "type":"Entertainment"
        }
    ],
    "sg:phone":"+1 609 581 4127",
    "sg:postcode":"08690",
    "sg:province":"NJ",
    "sg:tags":[
        "tennis",
        "court"
    ],
    "wof:name":"Kuser Road Tennis Courts",
    "wof:placetype":"venue"
},
  "geometry": {"coordinates":[-74.682149,40.202722],"type":"Point"}
}