{
  "type": "Feature",
  "properties": {
    "iso:country":"US",
    "sg:address":"179 Tinton Ave",
    "sg:city":"Eatontown",
    "sg:classifiers":[
        {
            "category":"Professional",
            "subcategory":"Management & Consulting",
            "type":"Services"
        }
    ],
    "sg:phone":"+1 732 389 1311",
    "sg:postcode":"07724",
    "sg:province":"NJ",
    "sg:tags":[
        "marketing",
        "consultant"
    ],
    "wof:name":"Manufacturers Svc Assoc Inc",
    "wof:placetype":"venue"
},
  "geometry": {"coordinates":[-74.07155400000001,40.304884],"type":"Point"}
}