{
  "type": "Feature",
  "properties": {
    "addr:full":"15 Broadway Passaic NJ 07055",
    "addr:housenumber":"15",
    "addr:postcode":"07055",
    "addr:street":"Broadway",
    "iso:country":"US",
    "sg:address":"15 Broadway",
    "sg:city":"Passaic",
    "sg:classifiers":[
        {
            "category":"Professional",
            "subcategory":"Lawyer & Legal Services",
            "type":"Services"
        }
    ],
    "sg:phone":"+1 973 594 8700",
    "sg:postcode":"07055",
    "sg:province":"NJ",
    "wof:name":"Bloom Jeffrey M Attorney",
    "wof:placetype":"venue"
},
  "geometry": {"coordinates":[-74.12629699999999,40.860699],"type":"Point"}
}