{
  "type": "Feature",
  "properties": {
    "iso:country":"US",
    "sg:address":"203 Hidden Valley Dr",
    "sg:city":"Edison",
    "sg:classifiers":[
        {
            "category":"Wholesale",
            "subcategory":"Apparel",
            "type":"Manufacturing & Wholesale Goods"
        }
    ],
    "sg:phone":"+1 732 632 8786",
    "sg:postcode":"08820",
    "sg:province":"NJ",
    "wof:name":"New York Fashions Inc",
    "wof:placetype":"venue"
},
  "geometry": {"coordinates":[-74.337157,40.570749],"type":"Point"}
}