{
  "type": "Feature",
  "properties": {
    "addr:full":"82 Sussex St Hackensack NJ 07601",
    "addr:housenumber":"82",
    "addr:postcode":"07601",
    "addr:street":"Sussex St",
    "iso:country":"US",
    "sg:address":"82 Sussex St",
    "sg:city":"Hackensack",
    "sg:classifiers":[
        {
            "category":"Building & Trades",
            "subcategory":"Construction",
            "type":"Services"
        }
    ],
    "sg:phone":"+1 201 996 9292",
    "sg:postcode":"07601",
    "sg:province":"NJ",
    "sg:tags":[
        "contractor"
    ],
    "wof:name":"Reyes Enterprise General Contractor",
    "wof:placetype":"venue"
},
  "geometry": {"coordinates":[-74.04789700000001,40.880299],"type":"Point"}
}