{
  "type": "Feature",
  "properties": {
    "iso:country":"US",
    "sg:address":"1513 Boardwalk",
    "sg:city":"Atlantic City",
    "sg:classifiers":[
        {
            "category":"Shopping",
            "subcategory":"Gifts & Souvenirs",
            "type":"Retail Goods"
        }
    ],
    "sg:phone":"+1   ",
    "sg:postcode":"08401",
    "sg:province":"NJ",
    "wof:name":"Santosh P Sham",
    "wof:placetype":"venue"
},
  "geometry": {"coordinates":[-74.427311,39.356611],"type":"Point"}
}