{
  "type": "Feature",
  "properties": {
    "iso:country":"US",
    "sg:address":"68 Kitchell Rd",
    "sg:city":"Denville",
    "sg:classifiers":[
        {
            "category":"Professional",
            "subcategory":"Art Services",
            "type":"Services"
        }
    ],
    "sg:phone":"+1   ",
    "sg:postcode":"07834",
    "sg:province":"NJ",
    "sg:tags":[
        "photography",
        "commercial"
    ],
    "wof:name":"M Lent Photography",
    "wof:placetype":"venue"
},
  "geometry": {"coordinates":[-74.485328,40.917001],"type":"Point"}
}