{
  "type": "Feature",
  "properties": {
    "iso:country":"US",
    "sg:address":"31 Demeter Rd",
    "sg:city":"Washington",
    "sg:classifiers":[
        {
            "category":"Farming",
            "subcategory":"Berry Farm",
            "type":"Manufacturing & Wholesale Goods"
        }
    ],
    "sg:phone":"+1 908 689 3494",
    "sg:postcode":"07882",
    "sg:province":"NJ",
    "sg:tags":[
        "crop"
    ],
    "wof:name":"George Jones",
    "wof:placetype":"venue"
},
  "geometry": {"coordinates":[-75.060121,40.773433],"type":"Point"}
}