{
  "type": "Feature",
  "properties": {
    "iso:country":"US",
    "sg:address":"167 Morristown Rd",
    "sg:city":"Bernardsville",
    "sg:classifiers":[
        {
            "category":"Food & Beverages",
            "subcategory":"Specialty",
            "type":"Retail Goods"
        }
    ],
    "sg:phone":"+1   ",
    "sg:postcode":"07924",
    "sg:province":"NJ",
    "sg:tags":[
        "gourmet",
        "liquor",
        "catering"
    ],
    "sg:website":"www.montereygourmetshops.com",
    "wof:name":"Monterey Gourmet",
    "wof:placetype":"venue"
},
  "geometry": {"coordinates":[-74.555882,40.721105],"type":"Point"}
}