{
  "type": "Feature",
  "properties": {
    "iso:country":"US",
    "sg:address":"21 Winchester Rd",
    "sg:city":"Livingston",
    "sg:classifiers":[
        {
            "category":"Shopping",
            "subcategory":"Crafts & Fabrics",
            "type":"Retail Goods"
        }
    ],
    "sg:phone":"+1   ",
    "sg:postcode":"07039",
    "sg:province":"NJ",
    "sg:tags":[
        "sewing"
    ],
    "wof:name":"Sewcraft",
    "wof:placetype":"venue"
},
  "geometry": {"coordinates":[-74.32665299999999,40.7785],"type":"Point"}
}