{
  "type": "Feature",
  "properties": {
    "iso:country":"US",
    "sg:address":"990 Inman Ave",
    "sg:city":"Edison",
    "sg:classifiers":[
        {
            "category":"Personal",
            "subcategory":"Beauty Salon",
            "type":"Services"
        }
    ],
    "sg:phone":"+1 908 755 0400",
    "sg:postcode":"08820",
    "sg:province":"NJ",
    "sg:tags":[
        "shop"
    ],
    "wof:name":"Temptation Nails & Hair",
    "wof:placetype":"venue"
},
  "geometry": {"coordinates":[-74.353483,40.59726],"type":"Point"}
}