{
  "type": "Feature",
  "properties": {
    "iso:country":"US",
    "sg:address":"520 Main St",
    "sg:city":"Boonton",
    "sg:classifiers":[
        {
            "category":"Recreation",
            "type":"Entertainment"
        }
    ],
    "sg:phone":"+1 973 263 8770",
    "sg:postcode":"07005",
    "sg:province":"NJ",
    "sg:tags":[
        "karate",
        "judo",
        "instr"
    ],
    "wof:name":"Eagle Martial Arts Ctr Inc",
    "wof:placetype":"venue"
},
  "geometry": {"coordinates":[-74.410115,40.90462],"type":"Point"}
}