{
  "type": "Feature",
  "properties": {
    "addr:full":"572 Valley Rd Wayne NJ 07470",
    "addr:housenumber":"572",
    "addr:postcode":"07470",
    "addr:street":"Valley Rd",
    "iso:country":"US",
    "sg:address":"572 Valley Rd",
    "sg:city":"Wayne",
    "sg:classifiers":[
        {
            "category":"Bakery",
            "type":"Food & Drink"
        }
    ],
    "sg:phone":"+1 973 696 3430",
    "sg:postcode":"07470",
    "sg:province":"NJ",
    "sg:website":"www.baskinrobbins.com",
    "wof:name":"Dunkin Donuts-Baskin Robbins",
    "wof:placetype":"venue"
},
  "geometry": {"coordinates":[-74.182312,40.880089],"type":"Point"}
}