{
  "type": "Feature",
  "properties": {
    "iso:country":"US",
    "sg:address":"120 County Road 519",
    "sg:city":"Belvidere",
    "sg:classifiers":[
        {
            "category":"Retail",
            "subcategory":"Auto Repair",
            "type":"Services"
        }
    ],
    "sg:phone":"+1 908 475 8555",
    "sg:postcode":"07823",
    "sg:province":"NJ",
    "sg:website":"www.2carguyz.com",
    "wof:name":"Accu-Tech Auto Care",
    "wof:placetype":"venue"
},
  "geometry": {"coordinates":[-75.078003,40.807899],"type":"Point"}
}