{
  "type": "Feature",
  "properties": {
    "addr:full":"275 W Milton Ave Rahway NJ 07065",
    "addr:housenumber":"275",
    "addr:postcode":"07065",
    "addr:street":"W Milton Ave",
    "iso:country":"US",
    "sg:address":"275 W Milton Ave",
    "sg:city":"Rahway",
    "sg:classifiers":[
        {
            "category":"Retail",
            "subcategory":"Funeral Services",
            "type":"Services"
        }
    ],
    "sg:phone":"+1 732 388 1874",
    "sg:postcode":"07065",
    "sg:province":"NJ",
    "sg:tags":[
        "home",
        "cemetery"
    ],
    "sg:website":"www.lehrergibiliscofuneral.com",
    "wof:name":"Lehrer-Gibilisco Funeral Home the",
    "wof:placetype":"venue"
},
  "geometry": {"coordinates":[-74.28510300000001,40.606701],"type":"Point"}
}