{
  "type": "Feature",
  "properties": {
    "iso:country":"US",
    "sg:address":"35 Bordeaux Dr",
    "sg:city":"Parsippany",
    "sg:classifiers":[
        {
            "category":"Building & Trades",
            "subcategory":"Construction",
            "type":"Services"
        }
    ],
    "sg:phone":"+1 973 515 8586",
    "sg:postcode":"07054",
    "sg:province":"NJ",
    "sg:tags":[
        "resurfacing",
        "laying",
        "refinishing",
        "floor"
    ],
    "wof:name":"Steve Pandolfi Flooring Co",
    "wof:placetype":"venue"
},
  "geometry": {"coordinates":[-74.41141399999999,40.841197],"type":"Point"}
}