{
  "type": "Feature",
  "properties": {
    "addr:full":"73 Bloomfield Ave Pine Brook NJ 07058",
    "addr:housenumber":"73",
    "addr:postcode":"07058",
    "addr:street":"Bloomfield Ave",
    "iso:country":"US",
    "sg:address":"73 Bloomfield Ave",
    "sg:city":"Pine Brook",
    "sg:classifiers":[
        {
            "category":"Restaurant",
            "type":"Food & Drink"
        }
    ],
    "sg:phone":"+1   ",
    "sg:postcode":"07058",
    "sg:province":"NJ",
    "sg:tags":[
        "eating"
    ],
    "wof:name":"Tiffanys Restaurant",
    "wof:placetype":"venue"
},
  "geometry": {"coordinates":[-74.32902799999999,40.859797],"type":"Point"}
}