{
  "type": "Feature",
  "properties": {
    "addr:full":"1129 E Park Ave Vineland NJ 08360",
    "addr:housenumber":"1129",
    "addr:postcode":"08360",
    "addr:street":"E Park Ave",
    "iso:country":"US",
    "sg:address":"1129 E Park Ave",
    "sg:city":"Vineland",
    "sg:classifiers":[
        {
            "category":"Professional",
            "subcategory":"Business Services",
            "type":"Services"
        }
    ],
    "sg:phone":"+1 856 696 3790",
    "sg:postcode":"08360",
    "sg:province":"NJ",
    "wof:name":"Coopers Mill Studio",
    "wof:placetype":"venue"
},
  "geometry": {"coordinates":[-75.00348200000001,39.490573],"type":"Point"}
}