{
  "type": "Feature",
  "properties": {
    "addr:full":"540 Hamilton Ave Linwood NJ 08221",
    "addr:housenumber":"540",
    "addr:postcode":"08221",
    "addr:street":"Hamilton Ave",
    "iso:country":"US",
    "sg:address":"540 Hamilton Ave",
    "sg:city":"Linwood",
    "sg:classifiers":[
        {
            "category":"Building & Trades",
            "subcategory":"Cleaning & Sanitation",
            "type":"Services"
        }
    ],
    "sg:phone":"+1   ",
    "sg:postcode":"08221",
    "sg:province":"NJ",
    "sg:tags":[
        "maintenance"
    ],
    "wof:name":"Maintained Domain",
    "wof:placetype":"venue"
},
  "geometry": {"coordinates":[-74.58544999999999,39.343071],"type":"Point"}
}