{
  "type": "Feature",
  "properties": {
    "addr:full":"332 Chestnut St Union NJ 07083",
    "addr:housenumber":"332",
    "addr:postcode":"07083",
    "addr:street":"Chestnut St",
    "iso:country":"US",
    "sg:address":"332 Chestnut St",
    "sg:city":"Union",
    "sg:classifiers":[
        {
            "category":"Personal",
            "subcategory":"Beauty Salon",
            "type":"Services"
        }
    ],
    "sg:phone":"+1   ",
    "sg:postcode":"07083",
    "sg:province":"NJ",
    "sg:tags":[
        "shop"
    ],
    "wof:name":"Nail Tech",
    "wof:placetype":"venue"
},
  "geometry": {"coordinates":[-74.26799800000001,40.677541],"type":"Point"}
}