{
  "type": "Feature",
  "properties": {
    "addr:full":"920 Merritt Dr Hillsborough NJ 08844",
    "addr:housenumber":"920",
    "addr:postcode":"08844",
    "addr:street":"Merritt Dr",
    "iso:country":"US",
    "sg:address":"920 Merritt Dr",
    "sg:city":"Hillsborough",
    "sg:classifiers":[
        {
            "category":"Wholesale",
            "subcategory":"Plants",
            "type":"Manufacturing & Wholesale Goods"
        }
    ],
    "sg:phone":"+1 908 359 1328",
    "sg:postcode":"08844",
    "sg:province":"NJ",
    "sg:tags":[
        "supply"
    ],
    "wof:name":"Nordic Supply",
    "wof:placetype":"venue"
},
  "geometry": {"coordinates":[-74.667051,40.501723],"type":"Point"}
}