{
  "type": "Feature",
  "properties": {
    "addr:full":"2 Chimney Rock Rd Bridgewater NJ 08807",
    "addr:housenumber":"2",
    "addr:postcode":"08807",
    "addr:street":"Chimney Rock Rd",
    "iso:country":"US",
    "sg:address":"2 Chimney Rock Rd",
    "sg:city":"Bridgewater",
    "sg:classifiers":[
        {
            "category":"Wholesale",
            "subcategory":"Office Equipment",
            "type":"Manufacturing & Wholesale Goods"
        },
        {
            "category":"Shopping",
            "type":"Retail Goods"
        }
    ],
    "sg:phone":"+1 732 563 0360",
    "sg:postcode":"08807",
    "sg:province":"NJ",
    "sg:tags":[
        "machine",
        "duplicating",
        "merchandise",
        "copying"
    ],
    "wof:name":"Digital Source 360 LLC",
    "wof:placetype":"venue"
},
  "geometry": {"coordinates":[-74.564857,40.562363],"type":"Point"}
}