{
  "type": "Feature",
  "properties": {
    "addr:full":"577 S Hope Chapel Rd Jackson NJ 08527",
    "addr:housenumber":"577",
    "addr:postcode":"08527",
    "addr:street":"S Hope Chapel Rd",
    "iso:country":"US",
    "sg:address":"577 S Hope Chapel Rd",
    "sg:city":"Jackson",
    "sg:classifiers":[
        {
            "category":"Building & Trades",
            "subcategory":"Construction",
            "type":"Services"
        }
    ],
    "sg:phone":"+1 732 370 9290",
    "sg:postcode":"08527",
    "sg:province":"NJ",
    "sg:tags":[
        "clearing",
        "street",
        "general",
        "highway",
        "contractor"
    ],
    "wof:name":"Jrj Properties",
    "wof:placetype":"venue"
},
  "geometry": {"coordinates":[-74.28580599999999,40.05294],"type":"Point"}
}