{
  "type": "Feature",
  "properties": {
    "iso:country":"US",
    "sg:address":"8 Buckingham Cir",
    "sg:city":"Pine Brook",
    "sg:classifiers":[
        {
            "category":"Shopping",
            "subcategory":"Catalog Store",
            "type":"Retail Goods"
        }
    ],
    "sg:phone":"+1   ",
    "sg:postcode":"07058",
    "sg:province":"NJ",
    "sg:tags":[
        "mail",
        "house"
    ],
    "wof:name":"International Medical Tech",
    "wof:placetype":"venue"
},
  "geometry": {"coordinates":[-74.35756499999999,40.870996],"type":"Point"}
}