{
  "type": "Feature",
  "properties": {
    "iso:country":"US",
    "sg:address":"10 Easton Ave",
    "sg:city":"New Brunswick",
    "sg:classifiers":[
        {
            "category":"Restaurant",
            "type":"Food & Drink"
        }
    ],
    "sg:menulink":"http://www.allmenus.com/nj/new-brunswick/20235-eleven-gourmet-deli/menu/",
    "sg:phone":"+1 732 846 1600",
    "sg:postcode":"08901",
    "sg:province":"NJ",
    "sg:tags":[
        "mexican"
    ],
    "wof:name":"Eleven Gourmet Deli",
    "wof:placetype":"venue"
},
  "geometry": {"coordinates":[-74.446816,40.49678],"type":"Point"}
}