{
  "type": "Feature",
  "properties": {
    "addr:full":"329 Drum Point Rd Brick NJ 08723",
    "addr:housenumber":"329",
    "addr:postcode":"08723",
    "addr:street":"Drum Point Rd",
    "iso:country":"US",
    "sg:address":"329 Drum Point Rd",
    "sg:city":"Brick",
    "sg:classifiers":[
        {
            "category":"Retail",
            "subcategory":"Self-service Laundry",
            "type":"Services"
        }
    ],
    "sg:phone":"+1 732 477 4404",
    "sg:postcode":"08723",
    "sg:province":"NJ",
    "wof:name":"Laundry King",
    "wof:placetype":"venue"
},
  "geometry": {"coordinates":[-74.112217,40.04112],"type":"Point"}
}