{
  "type": "Feature",
  "properties": {
    "addr:full":"211 Mallory Ave Jersey City NJ 07304",
    "addr:housenumber":"211",
    "addr:postcode":"07304",
    "addr:street":"Mallory Ave",
    "iso:country":"US",
    "sg:address":"211 Mallory Ave",
    "sg:city":"Jersey City",
    "sg:classifiers":[
        {
            "category":"Food & Beverages",
            "subcategory":"Groceries & Convenience Stores",
            "type":"Retail Goods"
        }
    ],
    "sg:phone":"+1   ",
    "sg:postcode":"07304",
    "sg:province":"NJ",
    "wof:name":"Mang Cristine Farm",
    "wof:placetype":"venue"
},
  "geometry": {"coordinates":[-74.086112,40.721842],"type":"Point"}
}