{
  "type": "Feature",
  "properties": {
    "addr:full":"1644 Saint Georges Ave Avenel NJ 07001",
    "addr:housenumber":"1644",
    "addr:postcode":"07001",
    "addr:street":"Saint Georges Ave",
    "iso:country":"US",
    "sg:address":"1644 Saint Georges Ave",
    "sg:city":"Avenel",
    "sg:classifiers":[
        {
            "category":"Professional",
            "subcategory":"Accounting & Tax Preparation",
            "type":"Services"
        }
    ],
    "sg:phone":"+1 732 396 8888",
    "sg:postcode":"07001",
    "sg:province":"NJ",
    "sg:tags":[
        "return",
        "filing"
    ],
    "wof:name":"Tax Chek",
    "wof:placetype":"venue"
},
  "geometry": {"coordinates":[-74.29073699999999,40.590857],"type":"Point"}
}