{
  "type": "Feature",
  "properties": {
    "addr:full":"178 Luddington Ave Clifton NJ 07011",
    "addr:housenumber":"178",
    "addr:postcode":"07011",
    "addr:street":"Luddington Ave",
    "iso:country":"US",
    "sg:address":"178 Luddington Ave",
    "sg:city":"Clifton",
    "sg:classifiers":[
        {
            "category":"Building & Trades",
            "subcategory":"Plumbing",
            "type":"Services"
        }
    ],
    "sg:phone":"+1 973 340 3515",
    "sg:postcode":"07011",
    "sg:province":"NJ",
    "sg:tags":[
        "contractor"
    ],
    "wof:name":"S & L Airflow Inc",
    "wof:placetype":"venue"
},
  "geometry": {"coordinates":[-74.15237999999999,40.877326],"type":"Point"}
}