{
  "type": "Feature",
  "properties": {
    "iso:country":"US",
    "sg:address":"131 Columbia Tpke",
    "sg:city":"Florham Park",
    "sg:classifiers":[
        {
            "category":"Health Services",
            "subcategory":"Doctor",
            "type":"Services"
        }
    ],
    "sg:phone":"+1 973 377 8776",
    "sg:postcode":"07932",
    "sg:province":"NJ",
    "sg:tags":[
        "physician",
        "surgeon"
    ],
    "sg:website":"www.omnimedmd.com",
    "wof:name":"Omni-Med",
    "wof:placetype":"venue"
},
  "geometry": {"coordinates":[-74.38708,40.786722],"type":"Point"}
}