{
  "type": "Feature",
  "properties": {
    "iso:country":"US",
    "sg:address":"525 Royden St",
    "sg:city":"Camden",
    "sg:classifiers":[
        {
            "category":"Organizations",
            "subcategory":"Religious Organization",
            "type":"Services"
        }
    ],
    "sg:phone":"+1 856 365 3243",
    "sg:postcode":"08103",
    "sg:province":"NJ",
    "sg:tags":[
        "place",
        "worship",
        "church"
    ],
    "wof:name":"St Augustine's Episcopal Church",
    "wof:placetype":"venue"
},
  "geometry": {"coordinates":[-75.120178,39.937832],"type":"Point"}
}