{
  "type": "Feature",
  "properties": {
    "iso:country":"US",
    "sg:address":"216 Engle St",
    "sg:city":"Englewood",
    "sg:classifiers":[
        {
            "category":"Health Services",
            "subcategory":"Doctor",
            "type":"Services"
        }
    ],
    "sg:phone":"+1   ",
    "sg:postcode":"07631",
    "sg:province":"NJ",
    "sg:tags":[
        "medical"
    ],
    "wof:name":"Barash White",
    "wof:placetype":"venue"
},
  "geometry": {"coordinates":[-73.96962000000001,40.899526],"type":"Point"}
}