{
  "type": "Feature",
  "properties": {
    "addr:full":"102 S 1st St Beach Haven NJ 08008",
    "addr:housenumber":"102",
    "addr:postcode":"08008",
    "addr:street":"S 1St St",
    "iso:country":"US",
    "sg:address":"102 S 1st St",
    "sg:city":"Beach Haven",
    "sg:classifiers":[
        {
            "category":"Food & Beverages",
            "subcategory":"Groceries & Convenience Stores",
            "type":"Retail Goods"
        }
    ],
    "sg:phone":"+1 609 494 9861",
    "sg:postcode":"08008",
    "sg:province":"NJ",
    "sg:tags":[
        "supermarket",
        "market"
    ],
    "wof:name":"Ocean Bay Super Market",
    "wof:placetype":"venue"
},
  "geometry": {"coordinates":[-74.17314,39.65461],"type":"Point"}
}