{
  "type": "Feature",
  "properties": {
    "iso:country":"US",
    "sg:address":"206 Belleville Ave",
    "sg:city":"Bloomfield",
    "sg:classifiers":[
        {
            "category":"Health Services",
            "subcategory":"Doctor",
            "type":"Services"
        }
    ],
    "sg:phone":"+1 973 259 0278",
    "sg:postcode":"07003",
    "sg:province":"NJ",
    "wof:name":"Bonomini Luigi V MD",
    "wof:placetype":"venue"
},
  "geometry": {"coordinates":[-74.188599,40.799198],"type":"Point"}
}