{
  "type": "Feature",
  "properties": {
    "iso:country":"US",
    "sg:address":"485 Williamstown New Freedom Rd",
    "sg:city":"Sicklerville",
    "sg:classifiers":[
        {
            "category":"Health Services",
            "subcategory":"Podiatrist",
            "type":"Services"
        }
    ],
    "sg:phone":"+1 856 237 8080",
    "sg:postcode":"08081",
    "sg:province":"NJ",
    "wof:name":"Steven M Grant DPM",
    "wof:placetype":"venue"
},
  "geometry": {"coordinates":[-74.96603,39.721157],"type":"Point"}
}