{
  "type": "Feature",
  "properties": {
    "addr:full":"4 Brick Yard Rd Cranbury NJ 08512",
    "addr:housenumber":"4",
    "addr:postcode":"08512",
    "addr:street":"Brick Yard Rd",
    "iso:country":"US",
    "sg:address":"4 Brick Yard Rd",
    "sg:city":"Cranbury",
    "sg:classifiers":[
        {
            "category":"Travel",
            "subcategory":"Travel Agent",
            "type":"Entertainment"
        }
    ],
    "sg:phone":"+1 609 443 8200",
    "sg:postcode":"08512",
    "sg:province":"NJ",
    "sg:tags":[
        "agency"
    ],
    "wof:name":"Seasoned Travel",
    "wof:placetype":"venue"
},
  "geometry": {"coordinates":[-74.51386100000001,40.289714],"type":"Point"}
}