{
  "type": "Feature",
  "properties": {
    "addr:full":"2 Oak Ave Cape May Ct Hse NJ 08210",
    "addr:housenumber":"2",
    "addr:postcode":"08210",
    "addr:street":"Oak Ave Cape May Ct",
    "iso:country":"US",
    "sg:address":"2 Oak Ave",
    "sg:city":"Cape May Ct Hse",
    "sg:classifiers":[
        {
            "category":"Manufacturing",
            "subcategory":"Building Materials",
            "type":"Manufacturing & Wholesale Goods"
        }
    ],
    "sg:phone":"+1 609 884 8990",
    "sg:postcode":"08210",
    "sg:province":"NJ",
    "wof:name":"Cape May Millworks",
    "wof:placetype":"venue"
},
  "geometry": {"coordinates":[-74.90844800000001,39.079243],"type":"Point"}
}