{
  "type": "Feature",
  "properties": {
    "addr:full":"44 Cooper St Woodbury NJ 08096",
    "addr:housenumber":"44",
    "addr:postcode":"08096",
    "addr:street":"Cooper St",
    "iso:country":"US",
    "sg:address":"44 Cooper St",
    "sg:city":"Woodbury",
    "sg:classifiers":[
        {
            "category":"Building & Trades",
            "subcategory":"Landscaping Services",
            "type":"Services"
        }
    ],
    "sg:phone":"+1 856 384 1075",
    "sg:postcode":"08096",
    "sg:province":"NJ",
    "sg:tags":[
        "arborist",
        "tree"
    ],
    "wof:name":"Dependable Land Maintenance",
    "wof:placetype":"venue"
},
  "geometry": {"coordinates":[-75.15120400000001,39.837259],"type":"Point"}
}