{
  "type": "Feature",
  "properties": {
    "iso:country":"US",
    "sg:address":"308 Broad St",
    "sg:city":"Riverton",
    "sg:classifiers":[
        {
            "category":"Manufacturing",
            "subcategory":"Food",
            "type":"Manufacturing & Wholesale Goods"
        },
        {
            "category":"Food & Beverages",
            "subcategory":"Bakery",
            "type":"Retail Goods"
        }
    ],
    "sg:phone":"+1 856 303 8700",
    "sg:postcode":"08077",
    "sg:province":"NJ",
    "sg:tags":[
        "baker",
        "eating",
        "product",
        "mfg"
    ],
    "wof:name":"Zenas Patisserie",
    "wof:placetype":"venue"
},
  "geometry": {"coordinates":[-75.012783,40.00938],"type":"Point"}
}