{
  "type": "Feature",
  "properties": {
    "addr:full":"744 Broad St Newark NJ 07102",
    "addr:housenumber":"744",
    "addr:postcode":"07102",
    "addr:street":"Broad St",
    "iso:country":"US",
    "sg:address":"744 Broad St",
    "sg:city":"Newark",
    "sg:classifiers":[
        {
            "category":"Professional",
            "subcategory":"Management & Consulting",
            "type":"Services"
        }
    ],
    "sg:phone":"+1 973 642 4201",
    "sg:postcode":"07102",
    "sg:province":"NJ",
    "sg:tags":[
        "counselor",
        "public",
        "relations"
    ],
    "wof:name":"Newark Counseling Center",
    "wof:placetype":"venue"
},
  "geometry": {"coordinates":[-74.171454,40.73665],"type":"Point"}
}