{
  "type": "Feature",
  "properties": {
    "addr:full":"333 Broad Ave Palisades Park NJ 07650",
    "addr:housenumber":"333",
    "addr:postcode":"07650",
    "addr:street":"Broad Ave",
    "iso:country":"US",
    "sg:address":"333 Broad Ave",
    "sg:city":"Palisades Park",
    "sg:classifiers":[
        {
            "category":"Home & Garden",
            "subcategory":"Hardware",
            "type":"Retail Goods"
        }
    ],
    "sg:phone":"+1 201 944 8143",
    "sg:postcode":"07650",
    "sg:province":"NJ",
    "sg:tags":[
        "store"
    ],
    "wof:name":"Kraut Benson Industrial Supply",
    "wof:placetype":"venue"
},
  "geometry": {"coordinates":[-73.997101,40.849201],"type":"Point"}
}