{
  "type": "Feature",
  "properties": {
    "addr:full":"206 Franklin Ave Nutley NJ 07110",
    "addr:housenumber":"206",
    "addr:postcode":"07110",
    "addr:street":"Franklin Ave",
    "iso:country":"US",
    "sg:address":"206 Franklin Ave",
    "sg:city":"Nutley",
    "sg:classifiers":[
        {
            "category":"Shopping",
            "subcategory":"Mobile Phones",
            "type":"Retail Goods"
        }
    ],
    "sg:phone":"+1 973 542 1338",
    "sg:postcode":"07110",
    "sg:province":"NJ",
    "wof:name":"Wpi Verizon Wireless",
    "wof:placetype":"venue"
},
  "geometry": {"coordinates":[-74.162413,40.814933],"type":"Point"}
}