{
  "type": "Feature",
  "properties": {
    "iso:country":"US",
    "sg:address":"18 3rd St",
    "sg:city":"Passaic",
    "sg:classifiers":[
        {
            "category":"Wholesale",
            "subcategory":"Apparel",
            "type":"Manufacturing & Wholesale Goods"
        },
        {
            "category":"Professional",
            "type":"Services"
        }
    ],
    "sg:phone":"+1 973 471 6991",
    "sg:postcode":"07055",
    "sg:province":"NJ",
    "sg:tags":[
        "establishment",
        "clothing",
        "mfg"
    ],
    "wof:name":"Susana Monaco Inc",
    "wof:placetype":"venue"
},
  "geometry": {"coordinates":[-74.115135,40.861687],"type":"Point"}
}