{
  "type": "Feature",
  "properties": {
    "addr:full":"22 Old Matawan Rd Old Bridge NJ 08857",
    "addr:housenumber":"22",
    "addr:postcode":"08857",
    "addr:street":"Old Matawan Rd",
    "iso:country":"US",
    "sg:address":"22 Old Matawan Rd",
    "sg:city":"Old Bridge",
    "sg:classifiers":[
        {
            "category":"Shopping",
            "subcategory":"Gifts & Souvenirs",
            "type":"Retail Goods"
        }
    ],
    "sg:phone":"+1   ",
    "sg:postcode":"08857",
    "sg:province":"NJ",
    "sg:tags":[
        "book"
    ],
    "wof:name":"Mc Comics",
    "wof:placetype":"venue"
},
  "geometry": {"coordinates":[-74.360035,40.4106],"type":"Point"}
}