{
  "type": "Feature",
  "properties": {
    "iso:country":"US",
    "sg:address":"1617 State Rte 38",
    "sg:city":"Lumberton",
    "sg:classifiers":[
        {
            "category":"Health Services",
            "subcategory":"Doctor",
            "type":"Services"
        }
    ],
    "sg:phone":"+1 609 261 0240",
    "sg:postcode":"08048",
    "sg:province":"NJ",
    "sg:tags":[
        "physician",
        "surgeon"
    ],
    "wof:name":"Pinelands Ob-Gyn",
    "wof:placetype":"venue"
},
  "geometry": {"coordinates":[-74.83168999999999,39.977219],"type":"Point"}
}