{
  "type": "Feature",
  "properties": {
    "iso:country":"US",
    "sg:address":"15 Riesling Ct",
    "sg:city":"Marlton",
    "sg:classifiers":[
        {
            "category":"Building & Trades",
            "subcategory":"Equipment Rental",
            "type":"Services"
        }
    ],
    "sg:phone":"+1 856 985 5642",
    "sg:postcode":"08053",
    "sg:province":"NJ",
    "wof:name":"Phase One Leasing LLC",
    "wof:placetype":"venue"
},
  "geometry": {"coordinates":[-74.92150599999999,39.908997],"type":"Point"}
}