{
  "type": "Feature",
  "properties": {
    "iso:country":"US",
    "sg:address":"928 Society Hill Blvd",
    "sg:city":"Cherry Hill",
    "sg:classifiers":[
        {
            "category":"Manufacturing",
            "subcategory":"Retail Goods",
            "type":"Manufacturing & Wholesale Goods"
        }
    ],
    "sg:phone":"+1 856 424 8205",
    "sg:postcode":"08003",
    "sg:province":"NJ",
    "sg:tags":[
        "supp",
        "pencil",
        "mfg"
    ],
    "wof:name":"Walletpen",
    "wof:placetype":"venue"
},
  "geometry": {"coordinates":[-74.969712,39.899242],"type":"Point"}
}