{
  "type": "Feature",
  "properties": {
    "iso:country":"US",
    "sg:address":"65 Willowbrook Blvd",
    "sg:city":"Wayne",
    "sg:classifiers":[
        {
            "category":"Banks & Credit Unions",
            "subcategory":"Investment Brokerage",
            "type":"Services"
        }
    ],
    "sg:phone":"+1 973 396 1900",
    "sg:postcode":"07470",
    "sg:province":"NJ",
    "sg:tags":[
        "advisory",
        "financial"
    ],
    "wof:name":"Park Avenue Securities",
    "wof:placetype":"venue"
},
  "geometry": {"coordinates":[-74.250742,40.888609],"type":"Point"}
}