{
  "type": "Feature",
  "properties": {
    "addr:full":"1001 State Rte 70 Toms River NJ 08753",
    "addr:housenumber":"1001",
    "addr:postcode":"08753",
    "addr:street":"State Rte 70",
    "iso:country":"US",
    "sg:address":"1001 State Rte 70",
    "sg:city":"Toms River",
    "sg:classifiers":[
        {
            "category":"Professional",
            "type":"Services"
        }
    ],
    "sg:phone":"+1 732 363 5144",
    "sg:postcode":"08753",
    "sg:province":"NJ",
    "wof:name":"Senior Meal Svc",
    "wof:placetype":"venue"
},
  "geometry": {"coordinates":[-74.221914,40.046746],"type":"Point"}
}