{
  "type": "Feature",
  "properties": {
    "addr:full":"113 E River Rd Rumson NJ 07760",
    "addr:housenumber":"113",
    "addr:postcode":"07760",
    "addr:street":"E River Rd",
    "iso:country":"US",
    "sg:address":"113 E River Rd",
    "sg:city":"Rumson",
    "sg:classifiers":[
        {
            "category":"Personal",
            "type":"Services"
        }
    ],
    "sg:phone":"+1 732 747 0573",
    "sg:postcode":"07760",
    "sg:province":"NJ",
    "sg:tags":[
        "consultant",
        "wedding"
    ],
    "wof:name":"Nancy Montserrat Events Inc",
    "wof:placetype":"venue"
},
  "geometry": {"coordinates":[-73.99903999999999,40.371279],"type":"Point"}
}