{
  "type": "Feature",
  "properties": {
    "addr:full":"1592 3rd Ave Phillipsburg NJ 08865",
    "addr:housenumber":"1592",
    "addr:postcode":"08865",
    "addr:street":"3Rd Ave",
    "iso:country":"US",
    "sg:address":"1592 3rd Ave",
    "sg:city":"Phillipsburg",
    "sg:classifiers":[
        {
            "category":"Personal",
            "subcategory":"Beauty Salon",
            "type":"Services"
        }
    ],
    "sg:phone":"+1 908 995 9118",
    "sg:postcode":"08865",
    "sg:province":"NJ",
    "wof:name":"Scissor Talk",
    "wof:placetype":"venue"
},
  "geometry": {"coordinates":[-75.157026,40.657934],"type":"Point"}
}