{
  "type": "Feature",
  "properties": {
    "addr:full":"495 US Highway 9 S Woodbridge NJ 07095",
    "addr:housenumber":"495",
    "addr:postcode":"07095",
    "addr:street":"Us Highway 9 S",
    "iso:country":"US",
    "sg:address":"495 US Highway 9 S",
    "sg:city":"Woodbridge",
    "sg:classifiers":[
        {
            "category":"Retail",
            "subcategory":"Auto Repair",
            "type":"Services"
        }
    ],
    "sg:phone":"+1 732 750 2444",
    "sg:postcode":"07095",
    "sg:province":"NJ",
    "wof:name":"Midas Auto Service Experts",
    "wof:placetype":"venue"
},
  "geometry": {"coordinates":[-74.2948,40.5387],"type":"Point"}
}