{
  "type": "Feature",
  "properties": {
    "addr:full":"600 Mount Pleasant Ave Dover NJ 07801",
    "addr:housenumber":"600",
    "addr:postcode":"07801",
    "addr:street":"Mount Pleasant Ave",
    "iso:country":"US",
    "sg:address":"600 Mount Pleasant Ave",
    "sg:city":"Dover",
    "sg:classifiers":[
        {
            "category":"Health Services",
            "subcategory":"Doctor",
            "type":"Services"
        }
    ],
    "sg:phone":"+1 973 989 0888",
    "sg:postcode":"07801",
    "sg:province":"NJ",
    "sg:tags":[
        "physician",
        "surgeon"
    ],
    "wof:name":"Orthopedic Associates",
    "wof:placetype":"venue"
},
  "geometry": {"coordinates":[-74.5247,40.901126],"type":"Point"}
}