{
  "type": "Feature",
  "properties": {
    "addr:full":"26 S Broadway Fair Lawn NJ 07410",
    "addr:housenumber":"26",
    "addr:postcode":"07410",
    "addr:street":"S Broadway",
    "iso:country":"US",
    "sg:address":"26 S Broadway",
    "sg:city":"Fair Lawn",
    "sg:classifiers":[
        {
            "category":"Professional",
            "subcategory":"Research",
            "type":"Services"
        }
    ],
    "sg:phone":"+1 201 703 0700",
    "sg:postcode":"07410",
    "sg:province":"NJ",
    "sg:tags":[
        "laboratory"
    ],
    "wof:name":"SAWH Lab LLC",
    "wof:placetype":"venue"
},
  "geometry": {"coordinates":[-74.092135,40.920858],"type":"Point"}
}