{
  "type": "Feature",
  "properties": {
    "iso:country":"US",
    "sg:address":"124 Clinton Pl",
    "sg:city":"Newark",
    "sg:classifiers":[
        {
            "category":"Organizations",
            "subcategory":"Religious Organization",
            "type":"Services"
        }
    ],
    "sg:phone":"+1   ",
    "sg:postcode":"07108",
    "sg:province":"NJ",
    "wof:name":"Macednia Pntecostal Church God",
    "wof:placetype":"venue"
},
  "geometry": {"coordinates":[-74.21117599999999,40.719063],"type":"Point"}
}