{
  "type": "Feature",
  "properties": {
    "addr:full":"775 Downey Ave Brick NJ 08723",
    "addr:housenumber":"775",
    "addr:postcode":"08723",
    "addr:street":"Downey Ave",
    "iso:country":"US",
    "sg:address":"775 Downey Ave",
    "sg:city":"Brick",
    "sg:classifiers":[
        {
            "category":"Banks & Credit Unions",
            "subcategory":"Investment Brokerage",
            "type":"Services"
        }
    ],
    "sg:phone":"+1 732 223 5111",
    "sg:postcode":"08723",
    "sg:province":"NJ",
    "sg:tags":[
        "consultant",
        "planning",
        "financial"
    ],
    "wof:name":"Financial Enterprise Inc",
    "wof:placetype":"venue"
},
  "geometry": {"coordinates":[-74.12373100000001,40.048339],"type":"Point"}
}