{
  "type": "Feature",
  "properties": {
    "iso:country":"US",
    "sg:address":"102 Mount Laurel Rd",
    "sg:city":"Hainesport",
    "sg:classifiers":[
        {
            "category":"Building & Trades",
            "subcategory":"Construction",
            "type":"Services"
        }
    ],
    "sg:phone":"+1 609 267 4622",
    "sg:postcode":"08036",
    "sg:province":"NJ",
    "sg:tags":[
        "painter"
    ],
    "wof:name":"Letchford Painting & Paperhng",
    "wof:placetype":"venue"
},
  "geometry": {"coordinates":[-74.841753,39.977824],"type":"Point"}
}