{
  "type": "Feature",
  "properties": {
    "iso:country":"US",
    "sg:address":"137 Summit Ave",
    "sg:city":"Summit",
    "sg:classifiers":[
        {
            "category":"Health Services",
            "subcategory":"Doctor",
            "type":"Services"
        }
    ],
    "sg:phone":"+1 908 273 0884",
    "sg:postcode":"07901",
    "sg:province":"NJ",
    "sg:tags":[
        "dentist"
    ],
    "wof:name":"Grzelak Michael W DMD",
    "wof:placetype":"venue"
},
  "geometry": {"coordinates":[-74.355904,40.720001],"type":"Point"}
}