{
  "type": "Feature",
  "properties": {
    "iso:country":"US",
    "sg:address":"461 Kingsland Ave",
    "sg:city":"Lyndhurst",
    "sg:classifiers":[
        {
            "category":"Manufacturing",
            "subcategory":"Paper Products",
            "type":"Manufacturing & Wholesale Goods"
        }
    ],
    "sg:phone":"+1 201 933 2015",
    "sg:postcode":"07071",
    "sg:province":"NJ",
    "sg:tags":[
        "printing",
        "template",
        "for",
        "digital"
    ],
    "wof:name":"Popnfold Papers Inc",
    "wof:placetype":"venue"
},
  "geometry": {"coordinates":[-74.126043,40.80468],"type":"Point"}
}