{
  "type": "Feature",
  "properties": {
    "addr:full":"655 State Rte 72 Manahawkin NJ 08050",
    "addr:housenumber":"655",
    "addr:postcode":"08050",
    "addr:street":"State Rte 72",
    "iso:country":"US",
    "sg:address":"655 State Rte 72",
    "sg:city":"Manahawkin",
    "sg:classifiers":[
        {
            "category":"Health Services",
            "subcategory":"Doctor",
            "type":"Services"
        }
    ],
    "sg:phone":"+1 609 597 9330",
    "sg:postcode":"08050",
    "sg:province":"NJ",
    "sg:tags":[
        "medical"
    ],
    "wof:name":"Morris E Antebi MD",
    "wof:placetype":"venue"
},
  "geometry": {"coordinates":[-74.238044,39.680196],"type":"Point"}
}