{
  "type": "Feature",
  "properties": {
    "iso:country":"US",
    "sg:address":"12 Orange Pl",
    "sg:city":"West Orange",
    "sg:classifiers":[
        {
            "category":"Real Estate",
            "subcategory":"Real Estate Agent",
            "type":"Services"
        }
    ],
    "sg:phone":"+1 973 761 0079",
    "sg:postcode":"07052",
    "sg:province":"NJ",
    "wof:name":"Value Max Realty",
    "wof:placetype":"venue"
},
  "geometry": {"coordinates":[-74.232136,40.792733],"type":"Point"}
}