{
  "type": "Feature",
  "properties": {
    "addr:full":"200 Buckelew Ave Monroe Township NJ 08831",
    "addr:housenumber":"200",
    "addr:postcode":"08831",
    "addr:street":"Buckelew Ave",
    "iso:country":"US",
    "sg:address":"200 Buckelew Ave",
    "sg:city":"Monroe Township",
    "sg:classifiers":[
        {
            "category":"Retail",
            "subcategory":"Repair Shop",
            "type":"Services"
        }
    ],
    "sg:phone":"+1   ",
    "sg:postcode":"08831",
    "sg:province":"NJ",
    "wof:name":"24 Hour Emergency Locksmith",
    "wof:placetype":"venue"
},
  "geometry": {"coordinates":[-74.434128,40.347125],"type":"Point"}
}