{
  "type": "Feature",
  "properties": {
    "iso:country":"US",
    "sg:address":"44 Fairview Ave",
    "sg:city":"Long Valley",
    "sg:classifiers":[
        {
            "category":"Retail",
            "subcategory":"Repair Shop",
            "type":"Services"
        }
    ],
    "sg:phone":"+1 908 876 3065",
    "sg:postcode":"07853",
    "sg:province":"NJ",
    "sg:tags":[
        "welding"
    ],
    "wof:name":"Arc Tec Welding & Fabrication",
    "wof:placetype":"venue"
},
  "geometry": {"coordinates":[-74.77915299999999,40.78752],"type":"Point"}
}