{
  "type": "Feature",
  "properties": {
    "iso:country":"US",
    "sg:address":"62 Ave C",
    "sg:city":"Lodi",
    "sg:classifiers":[
        {
            "category":"Building & Trades",
            "subcategory":"Plumbing",
            "type":"Services"
        }
    ],
    "sg:phone":"+1 973 773 0972",
    "sg:postcode":"07644",
    "sg:province":"NJ",
    "sg:tags":[
        "plumbing",
        "contractor"
    ],
    "wof:name":"Rickys Plumbing & Heating",
    "wof:placetype":"venue"
},
  "geometry": {"coordinates":[-74.07817300000001,40.88565],"type":"Point"}
}