{
  "type": "Feature",
  "properties": {
    "addr:full":"65 Sip Ave Jersey City NJ 07306",
    "addr:housenumber":"65",
    "addr:postcode":"07306",
    "addr:street":"Sip Ave",
    "iso:country":"US",
    "sg:address":"65 Sip Ave",
    "sg:city":"Jersey City",
    "sg:classifiers":[
        {
            "category":"Health Services",
            "subcategory":"Health Practitioner",
            "type":"Services"
        }
    ],
    "sg:phone":"+1 201 792 2582",
    "sg:postcode":"07306",
    "sg:province":"NJ",
    "sg:tags":[
        "therapist",
        "physical"
    ],
    "wof:name":"Hudson Physical Therapy Svc",
    "wof:placetype":"venue"
},
  "geometry": {"coordinates":[-74.063233,40.730641],"type":"Point"}
}