{
  "type": "Feature",
  "properties": {
    "iso:country":"US",
    "sg:address":"900 Main St",
    "sg:city":"Boonton",
    "sg:classifiers":[
        {
            "category":"Retail",
            "subcategory":"Animal Services",
            "type":"Services"
        }
    ],
    "sg:phone":"+1 973 335 0015",
    "sg:postcode":"07005",
    "sg:province":"NJ",
    "sg:tags":[
        "pet",
        "grooming",
        "washing"
    ],
    "wof:name":"Dog Spa",
    "wof:placetype":"venue"
},
  "geometry": {"coordinates":[-74.414126,40.906622],"type":"Point"}
}