{
  "type": "Feature",
  "properties": {
    "addr:full":"58 Martins Ln Berkeley Heights NJ 07922",
    "addr:housenumber":"58",
    "addr:postcode":"07922",
    "addr:street":"Martins Ln",
    "iso:country":"US",
    "sg:address":"58 Martins Ln",
    "sg:city":"Berkeley Heights",
    "sg:classifiers":[
        {
            "category":"Professional",
            "subcategory":"Management & Consulting",
            "type":"Services"
        }
    ],
    "sg:phone":"+1   ",
    "sg:postcode":"07922",
    "sg:province":"NJ",
    "sg:tags":[
        "business"
    ],
    "wof:name":"Keiser Associates",
    "wof:placetype":"venue"
},
  "geometry": {"coordinates":[-74.413768,40.679823],"type":"Point"}
}