{
  "type": "Feature",
  "properties": {
    "iso:country":"US",
    "sg:address":"300 Saint Davids Pl",
    "sg:city":"Ocean City",
    "sg:classifiers":[
        {
            "category":"Retail",
            "subcategory":"Repair Shop",
            "type":"Services"
        }
    ],
    "sg:phone":"+1 609 398 3663",
    "sg:postcode":"08226",
    "sg:province":"NJ",
    "sg:tags":[
        "lock",
        "locksmith"
    ],
    "wof:name":"Jim's Lock Svc",
    "wof:placetype":"venue"
},
  "geometry": {"coordinates":[-74.626671,39.23457],"type":"Point"}
}