{
  "type": "Feature",
  "properties": {
    "addr:full":"106 Lincoln Dr Asbury Park NJ 07712",
    "addr:housenumber":"106",
    "addr:postcode":"07712",
    "addr:street":"Lincoln Dr Asbury Park",
    "iso:country":"US",
    "sg:address":"106 Lincoln Dr",
    "sg:city":"Asbury Park",
    "sg:classifiers":[
        {
            "category":"Building & Trades",
            "subcategory":"Construction",
            "type":"Services"
        }
    ],
    "sg:phone":"+1 732 859 8803",
    "sg:postcode":"07712",
    "sg:province":"NJ",
    "sg:tags":[
        "hanging",
        "contractor"
    ],
    "wof:name":"Interiors By Laura",
    "wof:placetype":"venue"
},
  "geometry": {"coordinates":[-74.030778,40.227169],"type":"Point"}
}