{
  "type": "Feature",
  "properties": {
    "addr:full":"336 Hawthorne Ave Newark NJ 07112",
    "addr:housenumber":"336",
    "addr:postcode":"07112",
    "addr:street":"Hawthorne Ave",
    "iso:country":"US",
    "sg:address":"336 Hawthorne Ave",
    "sg:city":"Newark",
    "sg:classifiers":[
        {
            "category":"Food & Beverages",
            "subcategory":"Groceries & Convenience Stores",
            "type":"Retail Goods"
        }
    ],
    "sg:phone":"+1 973 372 4716",
    "sg:postcode":"07112",
    "sg:province":"NJ",
    "wof:name":"Claro Grocery",
    "wof:placetype":"venue"
},
  "geometry": {"coordinates":[-74.207497,40.717602],"type":"Point"}
}