{
  "type": "Feature",
  "properties": {
    "iso:country":"US",
    "sg:address":"1 Devore Rd",
    "sg:city":"Flemington",
    "sg:classifiers":[
        {
            "category":"Professional",
            "subcategory":"Business Services",
            "type":"Services"
        }
    ],
    "sg:phone":"+1   ",
    "sg:postcode":"08822",
    "sg:province":"NJ",
    "wof:name":"Davidson MGT Solutions LLC",
    "wof:placetype":"venue"
},
  "geometry": {"coordinates":[-74.765704,40.54908],"type":"Point"}
}