{
  "type": "Feature",
  "properties": {
    "iso:country":"US",
    "sg:address":"396 E 21st St",
    "sg:city":"Paterson",
    "sg:classifiers":[
        {
            "category":"Building & Trades",
            "subcategory":"Construction",
            "type":"Services"
        }
    ],
    "sg:phone":"+1 973 881 8080",
    "sg:postcode":"07513",
    "sg:province":"NJ",
    "sg:tags":[
        "designer"
    ],
    "wof:name":"Kanaan Design",
    "wof:placetype":"venue"
},
  "geometry": {"coordinates":[-74.15598799999999,40.905994],"type":"Point"}
}