{
  "type": "Feature",
  "properties": {
    "iso:country":"US",
    "sg:address":"69 Southbrook Dr",
    "sg:city":"Eatontown",
    "sg:classifiers":[
        {
            "category":"Retail",
            "subcategory":"Repair Shop",
            "type":"Services"
        }
    ],
    "sg:phone":"+1   ",
    "sg:postcode":"07724",
    "sg:province":"NJ",
    "sg:tags":[
        "locksmith"
    ],
    "wof:name":"Lexs Locks",
    "wof:placetype":"venue"
},
  "geometry": {"coordinates":[-74.060574,40.292888],"type":"Point"}
}