{
  "type": "Feature",
  "properties": {
    "addr:full":"4400 US Hwy 9 Freehold NJ 07728",
    "addr:housenumber":"4400",
    "addr:postcode":"07728",
    "addr:street":"Us Hwy 9",
    "iso:country":"US",
    "sg:address":"4400 US Hwy 9",
    "sg:city":"Freehold",
    "sg:classifiers":[
        {
            "category":"Banks & Credit Unions",
            "subcategory":"Bank",
            "type":"Services"
        }
    ],
    "sg:phone":"+1   ",
    "sg:postcode":"07728",
    "sg:province":"NJ",
    "sg:tags":[
        "federal",
        "savings",
        "institution"
    ],
    "wof:name":"Washington Mutual Bank",
    "wof:placetype":"venue"
},
  "geometry": {"coordinates":[-74.29470600000001,40.284816],"type":"Point"}
}