{
  "type": "Feature",
  "properties": {
    "iso:country":"US",
    "sg:address":"415 Ocean Rd",
    "sg:city":"Spring Lake",
    "sg:classifiers":[
        {
            "category":"Professional",
            "subcategory":"Business Services",
            "type":"Services"
        }
    ],
    "sg:phone":"+1 732 449 7575",
    "sg:postcode":"07762",
    "sg:province":"NJ",
    "sg:tags":[
        "interior",
        "design"
    ],
    "wof:name":"Architects Studio The",
    "wof:placetype":"venue"
},
  "geometry": {"coordinates":[-74.03447199999999,40.143015],"type":"Point"}
}