{
  "type": "Feature",
  "properties": {
    "addr:full":"261 Baldwin St New Brunswick NJ 08901",
    "addr:housenumber":"261",
    "addr:postcode":"08901",
    "addr:street":"Baldwin St",
    "iso:country":"US",
    "sg:address":"261 Baldwin St",
    "sg:city":"New Brunswick",
    "sg:classifiers":[
        {
            "category":"Autos & Motor Vehicles",
            "subcategory":"Automobile Sales",
            "type":"Retail Goods"
        }
    ],
    "sg:phone":"+1 732 246 1920",
    "sg:postcode":"08901",
    "sg:province":"NJ",
    "sg:tags":[
        "car",
        "dealer"
    ],
    "wof:name":"BMR3",
    "wof:placetype":"venue"
},
  "geometry": {"coordinates":[-74.452966,40.489553],"type":"Point"}
}