{
  "type": "Feature",
  "properties": {
    "addr:full":"455 Clifton Ave Clifton NJ 07011",
    "addr:housenumber":"455",
    "addr:postcode":"07011",
    "addr:street":"Clifton Ave",
    "iso:country":"US",
    "sg:address":"455 Clifton Ave",
    "sg:city":"Clifton",
    "sg:classifiers":[
        {
            "category":"Freight",
            "type":"Transportation"
        }
    ],
    "sg:phone":"+1 973 340 0500",
    "sg:postcode":"07011",
    "sg:province":"NJ",
    "wof:name":"Lev Agency Meest",
    "wof:placetype":"venue"
},
  "geometry": {"coordinates":[-74.14382000000001,40.874572],"type":"Point"}
}