{
  "type": "Feature",
  "properties": {
    "iso:country":"US",
    "sg:address":"201 Greenway Rd",
    "sg:city":"Ridgewood",
    "sg:classifiers":[
        {
            "category":"Real Estate",
            "subcategory":"Architect",
            "type":"Services"
        },
        {
            "category":"Professional",
            "type":"Services"
        }
    ],
    "sg:phone":"+1 201 670 7711",
    "sg:postcode":"07450",
    "sg:province":"NJ",
    "sg:tags":[
        "establishment"
    ],
    "wof:name":"Arthur M Levine LLC",
    "wof:placetype":"venue"
},
  "geometry": {"coordinates":[-74.139634,40.969217],"type":"Point"}
}