{
  "type": "Feature",
  "properties": {
    "addr:full":"485 Baxter Ave Wyckoff NJ 07481",
    "addr:housenumber":"485",
    "addr:postcode":"07481",
    "addr:street":"Baxter Ave",
    "iso:country":"US",
    "sg:address":"485 Baxter Ave",
    "sg:city":"Wyckoff",
    "sg:classifiers":[
        {
            "category":"Shopping",
            "subcategory":"Stationery & Office Supplies",
            "type":"Retail Goods"
        }
    ],
    "sg:phone":"+1   ",
    "sg:postcode":"07481",
    "sg:province":"NJ",
    "wof:name":"Letters By Lynda",
    "wof:placetype":"venue"
},
  "geometry": {"coordinates":[-74.147167,40.979018],"type":"Point"}
}