{
  "type": "Feature",
  "properties": {
    "addr:full":"97 Palmer Ave Tenafly NJ 07670",
    "addr:housenumber":"97",
    "addr:postcode":"07670",
    "addr:street":"Palmer Ave",
    "iso:country":"US",
    "sg:address":"97 Palmer Ave",
    "sg:city":"Tenafly",
    "sg:classifiers":[
        {
            "category":"Banks & Credit Unions",
            "subcategory":"Financial Services",
            "type":"Services"
        }
    ],
    "sg:phone":"+1   ",
    "sg:postcode":"07670",
    "sg:province":"NJ",
    "sg:tags":[
        "investor",
        "mortgage"
    ],
    "wof:name":"Fenco Associates",
    "wof:placetype":"venue"
},
  "geometry": {"coordinates":[-73.975054,40.916935],"type":"Point"}
}