{
  "type": "Feature",
  "properties": {
    "iso:country":"US",
    "sg:address":"11 Troast Ct",
    "sg:city":"Clifton",
    "sg:classifiers":[
        {
            "category":"Manufacturing",
            "subcategory":"Paper Products",
            "type":"Manufacturing & Wholesale Goods"
        }
    ],
    "sg:phone":"+1 973 478 4551",
    "sg:postcode":"07011",
    "sg:province":"NJ",
    "sg:tags":[
        "manufacture",
        "box",
        "book",
        "bookbinder",
        "repair"
    ],
    "wof:name":"Spink & Gabor Inc",
    "wof:placetype":"venue"
},
  "geometry": {"coordinates":[-74.146683,40.882654],"type":"Point"}
}