{
  "type": "Feature",
  "properties": {
    "addr:full":"315 Iroquois Ave Beach Haven NJ 08008",
    "addr:housenumber":"315",
    "addr:postcode":"08008",
    "addr:street":"Iroquois Ave",
    "iso:country":"US",
    "sg:address":"315 Iroquois Ave",
    "sg:city":"Beach Haven",
    "sg:classifiers":[
        {
            "category":"Sports & Exercise",
            "subcategory":"Gym",
            "type":"Entertainment"
        }
    ],
    "sg:phone":"+1 609 492 5305",
    "sg:postcode":"08008",
    "sg:province":"NJ",
    "sg:tags":[
        "fitness",
        "physical",
        "facility"
    ],
    "wof:name":"At Home Fitness",
    "wof:placetype":"venue"
},
  "geometry": {"coordinates":[-74.24901699999999,39.553817],"type":"Point"}
}