{
  "type": "Feature",
  "properties": {
    "iso:country":"US",
    "sg:address":"729 Haddon Ave",
    "sg:city":"Collingswood",
    "sg:classifiers":[
        {
            "category":"Restaurant",
            "type":"Food & Drink"
        }
    ],
    "sg:phone":"+1 856 240 1217",
    "sg:postcode":"08108",
    "sg:province":"NJ",
    "sg:tags":[
        "american",
        "latin",
        "steakhouse"
    ],
    "sg:website":"www.elsitiocollingswood.com/",
    "wof:name":"El Sitio - Grill & Caf?",
    "wof:placetype":"venue"
},
  "geometry": {"coordinates":[-75.067882,39.91617],"type":"Point"}
}