{
  "type": "Feature",
  "properties": {
    "iso:country":"US",
    "sg:address":"3 E Florida Ave",
    "sg:city":"Long Beach Twp",
    "sg:classifiers":[
        {
            "category":"Wholesale",
            "subcategory":"Jewelry",
            "type":"Manufacturing & Wholesale Goods"
        }
    ],
    "sg:phone":"+1 609 492 9092",
    "sg:postcode":"08008",
    "sg:province":"NJ",
    "sg:tags":[
        "ribbon"
    ],
    "sg:website":"www.ribbonlady.com",
    "wof:name":"Creative Touch Ribbon Dist",
    "wof:placetype":"venue"
},
  "geometry": {"coordinates":[-74.212532,39.600575],"type":"Point"}
}