{
  "type": "Feature",
  "properties": {
    "addr:full":"4 Dickens Ct Howell NJ 07731",
    "addr:housenumber":"4",
    "addr:postcode":"07731",
    "addr:street":"Dickens Ct",
    "iso:country":"US",
    "sg:address":"4 Dickens Ct",
    "sg:city":"Howell",
    "sg:classifiers":[
        {
            "category":"Building & Trades",
            "subcategory":"Construction",
            "type":"Services"
        }
    ],
    "sg:phone":"+1 732 370 8978",
    "sg:postcode":"07731",
    "sg:province":"NJ",
    "sg:tags":[
        "house"
    ],
    "wof:name":"Feiss Construction Co",
    "wof:placetype":"venue"
},
  "geometry": {"coordinates":[-74.19228,40.139798],"type":"Point"}
}