{
  "type": "Feature",
  "properties": {
    "iso:country":"US",
    "sg:address":"2387 Morse Ave",
    "sg:city":"Scotch Plains",
    "sg:classifiers":[
        {
            "category":"Organizations",
            "subcategory":"Religious Organization",
            "type":"Services"
        }
    ],
    "sg:phone":"+1 908 232 6972",
    "sg:postcode":"07076",
    "sg:province":"NJ",
    "sg:tags":[
        "church"
    ],
    "wof:name":"St John's Baptist Church",
    "wof:placetype":"venue"
},
  "geometry": {"coordinates":[-74.370115,40.654737],"type":"Point"}
}