{
  "type": "Feature",
  "properties": {
    "addr:full":"222 Main St. Hackensack NJ 07601",
    "addr:housenumber":"222",
    "addr:postcode":"07601",
    "addr:street":"Main St.",
    "iso:country":"US",
    "sg:address":"222 Main St.",
    "sg:city":"Hackensack",
    "sg:classifiers":[
        {
            "category":"Restaurant",
            "type":"Food & Drink"
        }
    ],
    "sg:phone":"+1 201 342 9222",
    "sg:postcode":"07601",
    "sg:province":"NJ",
    "sg:tags":[
        "american",
        "latin"
    ],
    "wof:name":"Galapagos Deli & Restaurant",
    "wof:placetype":"venue"
},
  "geometry": {"coordinates":[-74.041855,40.88524],"type":"Point"}
}