{
  "type": "Feature",
  "properties": {
    "addr:full":"14 Church St Ste 2 Vernon NJ 07462",
    "addr:housenumber":"14",
    "addr:postcode":"07462",
    "addr:street":"Church St Ste 2",
    "iso:country":"US",
    "sg:address":"14 Church St Ste 2",
    "sg:city":"Vernon",
    "sg:classifiers":[
        {
            "category":"Real Estate",
            "subcategory":"Real Estate Services",
            "type":"Services"
        },
        {
            "category":"Real Estate",
            "subcategory":"Real Estate Agent",
            "type":"Services"
        }
    ],
    "sg:phone":"+1 973 764 0900",
    "sg:postcode":"07462",
    "sg:province":"NJ",
    "sg:tags":[
        "buyer",
        "broker"
    ],
    "wof:name":"Real Estate Consultants",
    "wof:placetype":"venue"
},
  "geometry": {"coordinates":[-74.484177,41.20145],"type":"Point"}
}