{
  "type": "Feature",
  "properties": {
    "addr:full":"300 3rd St Ocean City NJ 08226",
    "addr:housenumber":"300",
    "addr:postcode":"08226",
    "addr:street":"3Rd St",
    "iso:country":"US",
    "sg:address":"300 3rd St",
    "sg:city":"Ocean City",
    "sg:classifiers":[
        {
            "category":"Health Services",
            "subcategory":"Chiropractor",
            "type":"Services"
        }
    ],
    "sg:phone":"+1 609 399 6000",
    "sg:postcode":"08226",
    "sg:province":"NJ",
    "wof:name":"Kemenosh Chiropractic Center",
    "wof:placetype":"venue"
},
  "geometry": {"coordinates":[-74.56827699999999,39.285702],"type":"Point"}
}