{
  "type": "Feature",
  "properties": {
    "addr:full":"215 Union Ave Bridgewater NJ 08807",
    "addr:housenumber":"215",
    "addr:postcode":"08807",
    "addr:street":"Union Ave",
    "iso:country":"US",
    "sg:address":"215 Union Ave",
    "sg:city":"Bridgewater",
    "sg:classifiers":[
        {
            "category":"Health Services",
            "subcategory":"Doctor",
            "type":"Services"
        }
    ],
    "sg:phone":"+1   ",
    "sg:postcode":"08807",
    "sg:province":"NJ",
    "sg:tags":[
        "medical"
    ],
    "wof:name":"Dr Thomas Nordstrom",
    "wof:placetype":"venue"
},
  "geometry": {"coordinates":[-74.59291,40.57107],"type":"Point"}
}