{
  "type": "Feature",
  "properties": {
    "iso:country":"US",
    "sg:address":"924 State Rte 94",
    "sg:city":"Blairstown",
    "sg:classifiers":[
        {
            "category":"Retail",
            "subcategory":"Repair Shop",
            "type":"Services"
        }
    ],
    "sg:phone":"+1 908 362 5866",
    "sg:postcode":"07825",
    "sg:province":"NJ",
    "sg:tags":[
        "lock",
        "locksmith"
    ],
    "wof:name":"Ace Locksmith Svc",
    "wof:placetype":"venue"
},
  "geometry": {"coordinates":[-74.893663,40.98748],"type":"Point"}
}