{
  "type": "Feature",
  "properties": {
    "iso:country":"US",
    "sg:address":"1465 Irving St",
    "sg:city":"Rahway",
    "sg:classifiers":[
        {
            "category":"Shopping",
            "subcategory":"Discount & Variety Stores",
            "type":"Retail Goods"
        },
        {
            "category":"Shopping",
            "subcategory":"Gifts & Souvenirs",
            "type":"Retail Goods"
        }
    ],
    "sg:phone":"+1 732 388 4955",
    "sg:postcode":"07065",
    "sg:province":"NJ",
    "sg:tags":[
        "arts",
        "african",
        "merchandise",
        "general"
    ],
    "wof:name":"Imoya Treasures Inc",
    "wof:placetype":"venue"
},
  "geometry": {"coordinates":[-74.27596,40.608208],"type":"Point"}
}