{
  "type": "Feature",
  "properties": {
    "addr:full":"5 Cebulka Dr Wrightstown NJ 08515",
    "addr:housenumber":"5",
    "addr:postcode":"08515",
    "addr:street":"Cebulka Dr",
    "iso:country":"US",
    "sg:address":"5 Cebulka Dr",
    "sg:city":"Wrightstown",
    "sg:classifiers":[
        {
            "category":"Building & Trades",
            "subcategory":"Construction",
            "type":"Services"
        }
    ],
    "sg:phone":"+1 609 306 3474",
    "sg:postcode":"08515",
    "sg:province":"NJ",
    "sg:tags":[
        "house"
    ],
    "wof:name":"Ms Construction LLC",
    "wof:placetype":"venue"
},
  "geometry": {"coordinates":[-74.63220699999999,40.062311],"type":"Point"}
}