{
  "type": "Feature",
  "properties": {
    "addr:full":"500 State Rte 17 Hasbrouck Hts NJ 07604",
    "addr:housenumber":"500",
    "addr:postcode":"07604",
    "addr:street":"State Rte 17",
    "iso:country":"US",
    "sg:address":"500 State Rte 17",
    "sg:city":"Hasbrouck Hts",
    "sg:classifiers":[
        {
            "category":"Personal",
            "subcategory":"Beauty Salon",
            "type":"Services"
        }
    ],
    "sg:phone":"+1 201 462 0480",
    "sg:postcode":"07604",
    "sg:province":"NJ",
    "sg:tags":[
        "treatment",
        "skin"
    ],
    "sg:website":"www.georgetteklinger.com",
    "wof:name":"Georgette Klinger Skin Care",
    "wof:placetype":"venue"
},
  "geometry": {"coordinates":[-74.063295,40.869569],"type":"Point"}
}