{
  "type": "Feature",
  "properties": {
    "addr:full":"136 N Haddon Ave Haddonfield NJ 08033",
    "addr:housenumber":"136",
    "addr:postcode":"08033",
    "addr:street":"N Haddon Ave",
    "iso:country":"US",
    "sg:address":"136 N Haddon Ave",
    "sg:city":"Haddonfield",
    "sg:classifiers":[
        {
            "category":"Personal",
            "subcategory":"Beauty Salon",
            "type":"Services"
        }
    ],
    "sg:phone":"+1   ",
    "sg:postcode":"08033",
    "sg:province":"NJ",
    "sg:tags":[
        "shop"
    ],
    "wof:name":"European Hair Design",
    "wof:placetype":"venue"
},
  "geometry": {"coordinates":[-75.037004,39.90094],"type":"Point"}
}