{
  "type": "Feature",
  "properties": {
    "addr:full":"283 Lakeview Ter Teaneck NJ 07666",
    "addr:housenumber":"283",
    "addr:postcode":"07666",
    "addr:street":"Lakeview Ter",
    "iso:country":"US",
    "sg:address":"283 Lakeview Ter",
    "sg:city":"Teaneck",
    "sg:classifiers":[
        {
            "category":"Professional",
            "subcategory":"Business Services",
            "type":"Services"
        }
    ],
    "sg:phone":"+1   ",
    "sg:postcode":"07666",
    "sg:province":"NJ",
    "wof:name":"Tucker & Associates",
    "wof:placetype":"venue"
},
  "geometry": {"coordinates":[-73.99539,40.884382],"type":"Point"}
}