{
  "type": "Feature",
  "properties": {
    "iso:country":"US",
    "sg:address":"3 Marshall St",
    "sg:city":"Irvington",
    "sg:classifiers":[
        {
            "category":"Social Services",
            "subcategory":"Job Training",
            "type":"Services"
        }
    ],
    "sg:phone":"+1 973 351 9900",
    "sg:postcode":"07111",
    "sg:province":"NJ",
    "wof:name":"Helping Hands & Companionship",
    "wof:placetype":"venue"
},
  "geometry": {"coordinates":[-74.22234899999999,40.72922],"type":"Point"}
}