{
  "type": "Feature",
  "properties": {
    "addr:full":"2208 Summit Ave Union City NJ 07087",
    "addr:housenumber":"2208",
    "addr:postcode":"07087",
    "addr:street":"Summit Ave",
    "iso:country":"US",
    "sg:address":"2208 Summit Ave",
    "sg:city":"Union City",
    "sg:classifiers":[
        {
            "category":"Personal",
            "subcategory":"Beauty Salon",
            "type":"Services"
        }
    ],
    "sg:phone":"+1 201 866 5535",
    "sg:postcode":"07087",
    "sg:province":"NJ",
    "sg:tags":[
        "shop"
    ],
    "wof:name":"Summit Barber & Beauty Salon",
    "wof:placetype":"venue"
},
  "geometry": {"coordinates":[-74.036632,40.768567],"type":"Point"}
}