{
  "type": "Feature",
  "properties": {
    "addr:full":"361 Hadleigh Ln North Brunswick NJ 08902",
    "addr:housenumber":"361",
    "addr:postcode":"08902",
    "addr:street":"Hadleigh Ln",
    "iso:country":"US",
    "sg:address":"361 Hadleigh Ln",
    "sg:city":"North Brunswick",
    "sg:classifiers":[
        {
            "category":"Shopping",
            "subcategory":"Computers & Home Electronics",
            "type":"Retail Goods"
        }
    ],
    "sg:phone":"+1   ",
    "sg:postcode":"08902",
    "sg:province":"NJ",
    "wof:name":"American Computer Services",
    "wof:placetype":"venue"
},
  "geometry": {"coordinates":[-74.506428,40.446042],"type":"Point"}
}