{
  "type": "Feature",
  "properties": {
    "addr:full":"184 Central Ave Old Tappan NJ 07675",
    "addr:housenumber":"184",
    "addr:postcode":"07675",
    "addr:street":"Central Ave",
    "iso:country":"US",
    "sg:address":"184 Central Ave",
    "sg:city":"Old Tappan",
    "sg:classifiers":[
        {
            "category":"Real Estate",
            "subcategory":"Real Estate Agent",
            "type":"Services"
        }
    ],
    "sg:phone":"+1 201 750 8815",
    "sg:postcode":"07675",
    "sg:province":"NJ",
    "wof:name":"My Home Town Realty Inc",
    "wof:placetype":"venue"
},
  "geometry": {"coordinates":[-73.98054,41.013478],"type":"Point"}
}