{
  "type": "Feature",
  "properties": {
    "iso:country":"US",
    "sg:address":"114 Castle Pointe Blvd",
    "sg:city":"Piscataway",
    "sg:classifiers":[
        {
            "category":"Professional",
            "type":"Services"
        }
    ],
    "sg:phone":"+1   ",
    "sg:postcode":"08854",
    "sg:province":"NJ",
    "wof:name":"Birla Horizon Sumit Gangu",
    "wof:placetype":"venue"
},
  "geometry": {"coordinates":[-74.45837400000001,40.536097],"type":"Point"}
}