{
  "type": "Feature",
  "properties": {
    "iso:country":"US",
    "sg:address":"14 Hickory Dr",
    "sg:city":"East Brunswick",
    "sg:classifiers":[
        {
            "category":"Manufacturing",
            "subcategory":"Chemicals & Compounds",
            "type":"Manufacturing & Wholesale Goods"
        }
    ],
    "sg:phone":"+1 732 821 8738",
    "sg:postcode":"08816",
    "sg:province":"NJ",
    "sg:tags":[
        "adhesive",
        "mfg"
    ],
    "wof:name":"A & P Foglia Company Inc",
    "wof:placetype":"venue"
},
  "geometry": {"coordinates":[-74.46305599999999,40.433702],"type":"Point"}
}