{
  "type": "Feature",
  "properties": {
    "addr:full":"211 3rd St Ridgefield Park NJ 07660",
    "addr:housenumber":"211",
    "addr:postcode":"07660",
    "addr:street":"3Rd St",
    "iso:country":"US",
    "sg:address":"211 3rd St",
    "sg:city":"Ridgefield Park",
    "sg:classifiers":[
        {
            "category":"Freight",
            "type":"Transportation"
        }
    ],
    "sg:phone":"+1 201 440 8861",
    "sg:postcode":"07660",
    "sg:province":"NJ",
    "sg:tags":[
        "operator",
        "local",
        "trucking"
    ],
    "wof:name":"Pappas Service",
    "wof:placetype":"venue"
},
  "geometry": {"coordinates":[-74.028937,40.865789],"type":"Point"}
}