{
  "type": "Feature",
  "properties": {
    "iso:country":"US",
    "sg:address":"17 Squire Ter",
    "sg:city":"Colts Neck",
    "sg:classifiers":[
        {
            "category":"Real Estate",
            "subcategory":"Real Estate Agent",
            "type":"Services"
        }
    ],
    "sg:phone":"+1 732 946 4541",
    "sg:postcode":"07722",
    "sg:province":"NJ",
    "sg:tags":[
        "inspection"
    ],
    "wof:name":"A-1 Association Home Inspctn",
    "wof:placetype":"venue"
},
  "geometry": {"coordinates":[-74.21197600000001,40.3351],"type":"Point"}
}