{
  "type": "Feature",
  "properties": {
    "iso:country":"US",
    "sg:address":"272 Mantoloking Rd",
    "sg:city":"Brick",
    "sg:classifiers":[
        {
            "category":"Retail",
            "subcategory":"Animal Services",
            "type":"Services"
        }
    ],
    "sg:phone":"+1 732 262 0100",
    "sg:postcode":"08723",
    "sg:province":"NJ",
    "wof:name":"Scallywags Dogs Grooming",
    "wof:placetype":"venue"
},
  "geometry": {"coordinates":[-74.079593,40.045121],"type":"Point"}
}