{
  "type": "Feature",
  "properties": {
    "addr:full":"199 Main St Matawan NJ 07747",
    "addr:housenumber":"199",
    "addr:postcode":"07747",
    "addr:street":"Main St",
    "iso:country":"US",
    "sg:address":"199 Main St",
    "sg:city":"Matawan",
    "sg:classifiers":[
        {
            "category":"Shopping",
            "subcategory":"Pharmacy",
            "type":"Retail Goods"
        }
    ],
    "sg:phone":"+1   ",
    "sg:postcode":"07747",
    "sg:province":"NJ",
    "wof:name":"Rx Concepts",
    "wof:placetype":"venue"
},
  "geometry": {"coordinates":[-74.23208200000001,40.411655],"type":"Point"}
}