{
  "type": "Feature",
  "properties": {
    "addr:full":"15 Firetower Rd Budd Lake NJ 07828",
    "addr:housenumber":"15",
    "addr:postcode":"07828",
    "addr:street":"Firetower Rd",
    "iso:country":"US",
    "sg:address":"15 Firetower Rd",
    "sg:city":"Budd Lake",
    "sg:classifiers":[
        {
            "category":"Professional",
            "type":"Services"
        }
    ],
    "sg:phone":"+1 973 691 6340",
    "sg:postcode":"07828",
    "sg:province":"NJ",
    "sg:tags":[
        "establishment"
    ],
    "wof:name":"E & V Dennerlein",
    "wof:placetype":"venue"
},
  "geometry": {"coordinates":[-74.747799,40.887038],"type":"Point"}
}