{
  "type": "Feature",
  "properties": {
    "iso:country":"US",
    "sg:address":"209 N Michigan Ave",
    "sg:city":"Kenilworth",
    "sg:classifiers":[
        {
            "category":"Wholesale",
            "subcategory":"Chemicals & Plastics",
            "type":"Manufacturing & Wholesale Goods"
        },
        {
            "category":"Manufacturing",
            "subcategory":"Chemicals & Compounds",
            "type":"Manufacturing & Wholesale Goods"
        }
    ],
    "sg:phone":"+1 908 245 2600",
    "sg:postcode":"07033",
    "sg:province":"NJ",
    "sg:tags":[
        "paint",
        "product",
        "allied",
        "resin"
    ],
    "sg:website":"www.synray.com",
    "wof:name":"Sunray Corp",
    "wof:placetype":"venue"
},
  "geometry": {"coordinates":[-74.28909299999999,40.681435],"type":"Point"}
}