{
  "type": "Feature",
  "properties": {
    "addr:full":"42 Hillcrest Ave Morristown NJ 07960",
    "addr:housenumber":"42",
    "addr:postcode":"07960",
    "addr:street":"Hillcrest Ave",
    "iso:country":"US",
    "sg:address":"42 Hillcrest Ave",
    "sg:city":"Morristown",
    "sg:classifiers":[
        {
            "category":"Communications",
            "subcategory":"Film & Video Production",
            "type":"Services"
        }
    ],
    "sg:phone":"+1   ",
    "sg:postcode":"07960",
    "sg:province":"NJ",
    "sg:tags":[
        "motion"
    ],
    "wof:name":"Postabilities Inc",
    "wof:placetype":"venue"
},
  "geometry": {"coordinates":[-74.493719,40.797694],"type":"Point"}
}