{
  "type": "Feature",
  "properties": {
    "addr:full":"38 Sylvania Ave Avon By The Sea NJ 07717",
    "addr:housenumber":"38",
    "addr:postcode":"07717",
    "addr:street":"Sylvania Ave",
    "iso:country":"US",
    "sg:address":"38 Sylvania Ave",
    "sg:city":"Avon By The Sea",
    "sg:classifiers":[
        {
            "category":"Professional",
            "type":"Services"
        }
    ],
    "sg:phone":"+1   ",
    "sg:postcode":"07717",
    "sg:province":"NJ",
    "wof:name":"Iquest 4",
    "wof:placetype":"venue"
},
  "geometry": {"coordinates":[-74.01181699999999,40.19202],"type":"Point"}
}