{
  "type": "Feature",
  "properties": {
    "iso:country":"US",
    "sg:address":"48 E Railway Ave",
    "sg:city":"Paterson",
    "sg:classifiers":[
        {
            "category":"Home & Garden",
            "subcategory":"Garden Supply",
            "type":"Retail Goods"
        },
        {
            "category":"Wholesale",
            "subcategory":"Fruits & Vegetables",
            "type":"Manufacturing & Wholesale Goods"
        }
    ],
    "sg:phone":"+1 973 357 3904",
    "sg:postcode":"07503",
    "sg:province":"NJ",
    "wof:name":"Sam's Produce Co",
    "wof:placetype":"venue"
},
  "geometry": {"coordinates":[-74.157853,40.900166],"type":"Point"}
}