{
  "type": "Feature",
  "properties": {
    "addr:full":"169 Union Blvd Ste 1A Totowa NJ 07512",
    "addr:housenumber":"169",
    "addr:postcode":"07512",
    "addr:street":"Union Blvd Ste 1A",
    "iso:country":"US",
    "sg:address":"169 Union Blvd Ste 1A",
    "sg:city":"Totowa",
    "sg:classifiers":[
        {
            "category":"Deli",
            "type":"Food & Drink"
        },
        {
            "category":"Food & Beverages",
            "subcategory":"Bakery",
            "type":"Retail Goods"
        }
    ],
    "sg:phone":"+1 973 790 6446",
    "sg:postcode":"07512",
    "sg:province":"NJ",
    "sg:tags":[
        "sandwich"
    ],
    "wof:name":"Italian Corner Deli",
    "wof:placetype":"venue"
},
  "geometry": {"coordinates":[-74.205913,40.908093],"type":"Point"}
}