{
  "type": "Feature",
  "properties": {
    "iso:country":"US",
    "sg:address":"217 Cedar Ln",
    "sg:city":"Closter",
    "sg:classifiers":[
        {
            "category":"Building & Trades",
            "subcategory":"Construction",
            "type":"Services"
        }
    ],
    "sg:phone":"+1 201 768 6888",
    "sg:postcode":"07624",
    "sg:province":"NJ",
    "sg:tags":[
        "hanging",
        "contractor"
    ],
    "wof:name":"Decor Dctg Pntg & Wall Coverin",
    "wof:placetype":"venue"
},
  "geometry": {"coordinates":[-73.970612,40.978147],"type":"Point"}
}