{
  "type": "Feature",
  "properties": {
    "iso:country":"US",
    "sg:address":"742 Clinton Ave",
    "sg:city":"Newark",
    "sg:classifiers":[
        {
            "category":"Health Services",
            "subcategory":"Doctor",
            "type":"Services"
        }
    ],
    "sg:phone":"+1 973 374 2550",
    "sg:postcode":"07108",
    "sg:province":"NJ",
    "sg:tags":[
        "physician",
        "surgeon"
    ],
    "wof:name":"Delores C Gayle MD",
    "wof:placetype":"venue"
},
  "geometry": {"coordinates":[-74.21147499999999,40.722908],"type":"Point"}
}