{
  "type": "Feature",
  "properties": {
    "iso:country":"US",
    "sg:address":"4209 New York Ave",
    "sg:city":"Union City",
    "sg:classifiers":[
        {
            "category":"Shopping",
            "subcategory":"Clothing, Apparel, & Fashions",
            "type":"Retail Goods"
        }
    ],
    "sg:phone":"+1   ",
    "sg:postcode":"07087",
    "sg:province":"NJ",
    "wof:name":"Intimates By Luisa",
    "wof:placetype":"venue"
},
  "geometry": {"coordinates":[-74.023544,40.777532],"type":"Point"}
}