{
  "type": "Feature",
  "properties": {
    "addr:full":"359 N Beverwyck Rd Parsippany NJ 07054",
    "addr:housenumber":"359",
    "addr:postcode":"07054",
    "addr:street":"N Beverwyck Rd",
    "iso:country":"US",
    "sg:address":"359 N Beverwyck Rd",
    "sg:city":"Parsippany",
    "sg:classifiers":[
        {
            "category":"Health Services",
            "subcategory":"Chiropractor",
            "type":"Services"
        },
        {
            "category":"Health Services",
            "subcategory":"Doctor",
            "type":"Services"
        }
    ],
    "sg:phone":"+1 973 334 6868",
    "sg:postcode":"07054",
    "sg:province":"NJ",
    "sg:tags":[
        "medical"
    ],
    "wof:name":"Family Chiropractic Center",
    "wof:placetype":"venue"
},
  "geometry": {"coordinates":[-74.382891,40.87206],"type":"Point"}
}