{
  "type": "Feature",
  "properties": {
    "addr:full":"75 Sunset Rd Willingboro NJ 08046",
    "addr:housenumber":"75",
    "addr:postcode":"08046",
    "addr:street":"Sunset Rd",
    "iso:country":"US",
    "sg:address":"75 Sunset Rd",
    "sg:city":"Willingboro",
    "sg:classifiers":[
        {
            "category":"Social Services",
            "subcategory":"Child Care",
            "type":"Services"
        }
    ],
    "sg:phone":"+1 609 871 5300",
    "sg:postcode":"08046",
    "sg:province":"NJ",
    "sg:tags":[
        "kindergarten",
        "academic",
        "school"
    ],
    "wof:name":"Different & Wonderful",
    "wof:placetype":"venue"
},
  "geometry": {"coordinates":[-74.89852399999999,40.046669],"type":"Point"}
}