{
  "type": "Feature",
  "properties": {
    "iso:country":"US",
    "sg:address":"75 E Blackwell St",
    "sg:city":"Dover",
    "sg:classifiers":[
        {
            "category":"Retail",
            "subcategory":"Auto Repair",
            "type":"Services"
        }
    ],
    "sg:phone":"+1 973 328 1088",
    "sg:postcode":"07801",
    "sg:province":"NJ",
    "sg:tags":[
        "repairing",
        "automobile",
        "general"
    ],
    "wof:name":"G D Auto Repair",
    "wof:placetype":"venue"
},
  "geometry": {"coordinates":[-74.553687,40.884702],"type":"Point"}
}