{
  "type": "Feature",
  "properties": {
    "addr:full":"207 Ramapo Valley Rd Oakland NJ 07436",
    "addr:housenumber":"207",
    "addr:postcode":"07436",
    "addr:street":"Ramapo Valley Rd",
    "iso:country":"US",
    "sg:address":"207 Ramapo Valley Rd",
    "sg:city":"Oakland",
    "sg:classifiers":[
        {
            "category":"Professional",
            "subcategory":"Business Services",
            "type":"Services"
        }
    ],
    "sg:phone":"+1 201 337 4446",
    "sg:postcode":"07436",
    "sg:province":"NJ",
    "sg:tags":[
        "appraiser"
    ],
    "wof:name":"Van Cline & Davenport LTD",
    "wof:placetype":"venue"
},
  "geometry": {"coordinates":[-74.24969,41.017806],"type":"Point"}
}