{
  "type": "Feature",
  "properties": {
    "addr:full":"189 Berdan Ave Wayne NJ 07470",
    "addr:housenumber":"189",
    "addr:postcode":"07470",
    "addr:street":"Berdan Ave",
    "iso:country":"US",
    "sg:address":"189 Berdan Ave",
    "sg:city":"Wayne",
    "sg:classifiers":[
        {
            "category":"Retail",
            "subcategory":"Repair Shop",
            "type":"Services"
        }
    ],
    "sg:phone":"+1 973 553 9244",
    "sg:postcode":"07470",
    "sg:province":"NJ",
    "sg:tags":[
        "lock",
        "locksmith"
    ],
    "wof:name":"Any Time Any Place Locksmith",
    "wof:placetype":"venue"
},
  "geometry": {"coordinates":[-74.243353,40.964306],"type":"Point"}
}