{
  "type": "Feature",
  "properties": {
    "iso:country":"US",
    "sg:address":"13 Orchard St",
    "sg:city":"Millburn",
    "sg:classifiers":[
        {
            "category":"Building & Trades",
            "subcategory":"Plumbing",
            "type":"Services"
        }
    ],
    "sg:phone":"+1 973 376 0508",
    "sg:postcode":"07041",
    "sg:province":"NJ",
    "sg:tags":[
        "contractor"
    ],
    "wof:name":"Marcketta Heating & Cooling",
    "wof:placetype":"venue"
},
  "geometry": {"coordinates":[-74.310778,40.716708],"type":"Point"}
}