{
  "type": "Feature",
  "properties": {
    "addr:full":"2582 US Hwy 9 Howell NJ 07731",
    "addr:housenumber":"2582",
    "addr:postcode":"07731",
    "addr:street":"Us Hwy 9",
    "iso:country":"US",
    "sg:address":"2582 US Hwy 9",
    "sg:city":"Howell",
    "sg:classifiers":[
        {
            "category":"Professional",
            "subcategory":"Employment Agencies",
            "type":"Services"
        }
    ],
    "sg:phone":"+1 732 942 9300",
    "sg:postcode":"07731",
    "sg:province":"NJ",
    "sg:tags":[
        "help",
        "contractor"
    ],
    "wof:name":"Contemporary Staffing Inc",
    "wof:placetype":"venue"
},
  "geometry": {"coordinates":[-74.24106399999999,40.17347],"type":"Point"}
}