{
  "type": "Feature",
  "properties": {
    "addr:full":"907 State Rte 70 Brick NJ 08724",
    "addr:housenumber":"907",
    "addr:postcode":"08724",
    "addr:street":"State Rte 70",
    "iso:country":"US",
    "sg:address":"907 State Rte 70",
    "sg:city":"Brick",
    "sg:classifiers":[
        {
            "category":"Home & Garden",
            "subcategory":"Furniture",
            "type":"Retail Goods"
        }
    ],
    "sg:phone":"+1   ",
    "sg:postcode":"08724",
    "sg:province":"NJ",
    "wof:name":"Sleepys Inc",
    "wof:placetype":"venue"
},
  "geometry": {"coordinates":[-74.12788500000001,40.072666],"type":"Point"}
}