{
  "type": "Feature",
  "properties": {
    "addr:full":"1200 US Hwy 130 Cinnaminson NJ 08077",
    "addr:housenumber":"1200",
    "addr:postcode":"08077",
    "addr:street":"Us Hwy 130",
    "iso:country":"US",
    "sg:address":"1200 US Hwy 130",
    "sg:city":"Cinnaminson",
    "sg:classifiers":[
        {
            "category":"Retail",
            "subcategory":"Funeral Services",
            "type":"Services"
        }
    ],
    "sg:phone":"+1 856 829 8000",
    "sg:postcode":"08077",
    "sg:province":"NJ",
    "sg:tags":[
        "director"
    ],
    "wof:name":"Givnish Family Funeral Homes",
    "wof:placetype":"venue"
},
  "geometry": {"coordinates":[-74.990719,39.997701],"type":"Point"}
}