{
  "type": "Feature",
  "properties": {
    "iso:country":"US",
    "sg:address":"1241 Hamilton Ave",
    "sg:city":"Trenton",
    "sg:classifiers":[
        {
            "category":"Retail",
            "subcategory":"Auto Repair",
            "type":"Services"
        }
    ],
    "sg:phone":"+1 609 695 2124",
    "sg:postcode":"08629",
    "sg:province":"NJ",
    "sg:tags":[
        "repairing",
        "automobile",
        "general"
    ],
    "wof:name":"Chick's Auto Repair",
    "wof:placetype":"venue"
},
  "geometry": {"coordinates":[-74.731813,40.219822],"type":"Point"}
}