{
  "type": "Feature",
  "properties": {
    "addr:full":"105 Wheatsworth Rd Hamburg NJ 07419",
    "addr:housenumber":"105",
    "addr:postcode":"07419",
    "addr:street":"Wheatsworth Rd",
    "iso:country":"US",
    "sg:address":"105 Wheatsworth Rd",
    "sg:city":"Hamburg",
    "sg:classifiers":[
        {
            "category":"Sports & Exercise",
            "subcategory":"Golf",
            "type":"Entertainment"
        }
    ],
    "sg:phone":"+1 973 827 1587",
    "sg:postcode":"07419",
    "sg:province":"NJ",
    "sg:tags":[
        "course"
    ],
    "wof:name":"Crystal Springs Resort",
    "wof:placetype":"venue"
},
  "geometry": {"coordinates":[-74.580399,41.144326],"type":"Point"}
}