{
  "type": "Feature",
  "properties": {
    "iso:country":"US",
    "sg:address":"14 W 6th St",
    "sg:city":"Barnegat Light",
    "sg:classifiers":[
        {
            "category":"Building & Trades",
            "subcategory":"Plumbing",
            "type":"Services"
        }
    ],
    "sg:phone":"+1 609 494 2236",
    "sg:postcode":"08006",
    "sg:province":"NJ",
    "sg:tags":[
        "plumbing",
        "contractor"
    ],
    "wof:name":"Wayne Johnson Plumbing & Htg",
    "wof:placetype":"venue"
},
  "geometry": {"coordinates":[-74.10886000000001,39.760327],"type":"Point"}
}