{
  "type": "Feature",
  "properties": {
    "addr:full":"109 Mount Laurel Rd Mt Laurel NJ 08054",
    "addr:housenumber":"109",
    "addr:postcode":"08054",
    "addr:street":"Mount Laurel Rd",
    "iso:country":"US",
    "sg:address":"109 Mount Laurel Rd",
    "sg:city":"Mt Laurel",
    "sg:classifiers":[
        {
            "category":"Manufacturing",
            "subcategory":"Electronics",
            "type":"Manufacturing & Wholesale Goods"
        }
    ],
    "sg:phone":"+1 856 273 8688",
    "sg:postcode":"08054",
    "sg:province":"NJ",
    "sg:tags":[
        "sound",
        "equipment",
        "system"
    ],
    "sg:website":"www.wpsworld.com",
    "wof:name":"Washington Professional Systs",
    "wof:placetype":"venue"
},
  "geometry": {"coordinates":[-74.926969,39.958325],"type":"Point"}
}