{
  "type": "Feature",
  "properties": {
    "iso:country":"US",
    "sg:address":"5114 Bergenline Pl",
    "sg:city":"West New York",
    "sg:classifiers":[
        {
            "category":"Wholesale",
            "subcategory":"Groceries",
            "type":"Manufacturing & Wholesale Goods"
        }
    ],
    "sg:phone":"+1 201 974 0008",
    "sg:postcode":"07093",
    "sg:province":"NJ",
    "wof:name":"Peru Food Imports",
    "wof:placetype":"venue"
},
  "geometry": {"coordinates":[-74.019949,40.78389],"type":"Point"}
}