{
  "type": "Feature",
  "properties": {
    "iso:country":"US",
    "sg:address":"450 Murray Hill Pkwy",
    "sg:city":"East Rutherford",
    "sg:classifiers":[
        {
            "category":"Shopping",
            "subcategory":"Clothing, Apparel, & Fashions",
            "type":"Retail Goods"
        }
    ],
    "sg:phone":"+1 201 933 1030",
    "sg:postcode":"07073",
    "sg:province":"NJ",
    "wof:name":"Dream Apparel Group LLC",
    "wof:placetype":"venue"
},
  "geometry": {"coordinates":[-74.09316099999999,40.818604],"type":"Point"}
}