{
  "type": "Feature",
  "properties": {
    "iso:country":"US",
    "sg:address":"145 English St",
    "sg:city":"Hackensack",
    "sg:classifiers":[
        {
            "category":"Manufacturing",
            "subcategory":"Printing",
            "type":"Manufacturing & Wholesale Goods"
        }
    ],
    "sg:phone":"+1 201 996 0546",
    "sg:postcode":"07601",
    "sg:province":"NJ",
    "sg:tags":[
        "printer"
    ],
    "wof:name":"A C Enevelopes",
    "wof:placetype":"venue"
},
  "geometry": {"coordinates":[-74.04939299999999,40.875529],"type":"Point"}
}