{
  "type": "Feature",
  "properties": {
    "addr:full":"16 1st St Bloomingdale NJ 07403",
    "addr:housenumber":"16",
    "addr:postcode":"07403",
    "addr:street":"1St St",
    "iso:country":"US",
    "sg:address":"16 1st St",
    "sg:city":"Bloomingdale",
    "sg:classifiers":[
        {
            "category":"Building & Trades",
            "subcategory":"Construction",
            "type":"Services"
        }
    ],
    "sg:phone":"+1 973 838 0100",
    "sg:postcode":"07403",
    "sg:province":"NJ",
    "sg:tags":[
        "house"
    ],
    "wof:name":"VWV Construction Inc",
    "wof:placetype":"venue"
},
  "geometry": {"coordinates":[-74.340716,41.007634],"type":"Point"}
}