{
  "type": "Feature",
  "properties": {
    "addr:full":"386 State Rte 37 Toms River NJ 08753",
    "addr:housenumber":"386",
    "addr:postcode":"08753",
    "addr:street":"State Rte 37",
    "iso:country":"US",
    "sg:address":"386 State Rte 37",
    "sg:city":"Toms River",
    "sg:classifiers":[
        {
            "category":"Autos & Motor Vehicles",
            "subcategory":"Automobile Sales",
            "type":"Retail Goods"
        }
    ],
    "sg:phone":"+1 732 244 8400",
    "sg:postcode":"08753",
    "sg:province":"NJ",
    "sg:tags":[
        "truck"
    ],
    "wof:name":"Ocean Motors Inc",
    "wof:placetype":"venue"
},
  "geometry": {"coordinates":[-74.170137,39.957542],"type":"Point"}
}