{
  "type": "Feature",
  "properties": {
    "iso:country":"US",
    "sg:address":"26 Springhouse Rd",
    "sg:city":"Asbury Park",
    "sg:classifiers":[
        {
            "category":"Manufacturing",
            "subcategory":"Petroleum Products",
            "type":"Manufacturing & Wholesale Goods"
        },
        {
            "category":"Utilities",
            "subcategory":"Refuse",
            "type":"Services"
        }
    ],
    "sg:phone":"+1 732 922 2626",
    "sg:postcode":"07712",
    "sg:province":"NJ",
    "sg:tags":[
        "oil",
        "recovery",
        "system"
    ],
    "wof:name":"Mercury Oil Recovery",
    "wof:placetype":"venue"
},
  "geometry": {"coordinates":[-74.062037,40.240924],"type":"Point"}
}