{
  "type": "Feature",
  "properties": {
    "iso:country":"US",
    "sg:address":"43-45 Elizabeth Ave",
    "sg:city":"Newark",
    "sg:classifiers":[
        {
            "category":"Social Services",
            "subcategory":"Child Care",
            "type":"Services"
        }
    ],
    "sg:phone":"+1 973 848 0050",
    "sg:postcode":"07108",
    "sg:province":"NJ",
    "sg:tags":[
        "day"
    ],
    "wof:name":"Abbott Daycare",
    "wof:placetype":"venue"
},
  "geometry": {"coordinates":[-74.188481,40.721685],"type":"Point"}
}