{
  "type": "Feature",
  "properties": {
    "iso:country":"US",
    "sg:address":"110 W Palisades Blvd",
    "sg:city":"Palisades Park",
    "sg:classifiers":[
        {
            "category":"Banks & Credit Unions",
            "subcategory":"Bank",
            "type":"Services"
        }
    ],
    "sg:phone":"+1 201 242 5552",
    "sg:postcode":"07650",
    "sg:province":"NJ",
    "wof:name":"St Andrew Kim Federal Credit Union Inc",
    "wof:placetype":"venue"
},
  "geometry": {"coordinates":[-74.000563,40.852007],"type":"Point"}
}