{
  "type": "Feature",
  "properties": {
    "addr:full":"11 Stephen St South River NJ 08882",
    "addr:housenumber":"11",
    "addr:postcode":"08882",
    "addr:street":"Stephen St",
    "iso:country":"US",
    "sg:address":"11 Stephen St",
    "sg:city":"South River",
    "sg:classifiers":[
        {
            "category":"Education",
            "subcategory":"Special Training",
            "type":"Public Place"
        }
    ],
    "sg:phone":"+1 732 432 8000",
    "sg:postcode":"08882",
    "sg:province":"NJ",
    "sg:tags":[
        "reading",
        "instruction",
        "improvement"
    ],
    "wof:name":"Literacy Volunteers-Middlesex",
    "wof:placetype":"venue"
},
  "geometry": {"coordinates":[-74.38214499999999,40.453075],"type":"Point"}
}