{
  "type": "Feature",
  "properties": {
    "addr:full":"416 Victoria Ave Piscataway NJ 08854",
    "addr:housenumber":"416",
    "addr:postcode":"08854",
    "addr:street":"Victoria Ave",
    "iso:country":"US",
    "sg:address":"416 Victoria Ave",
    "sg:city":"Piscataway",
    "sg:classifiers":[
        {
            "category":"Social Services",
            "type":"Services"
        }
    ],
    "sg:phone":"+1 732 968 7555",
    "sg:postcode":"08854",
    "sg:province":"NJ",
    "wof:name":"Circle Playhouse Inc",
    "wof:placetype":"venue"
},
  "geometry": {"coordinates":[-74.45756799999999,40.581371],"type":"Point"}
}