{
  "type": "Feature",
  "properties": {
    "addr:full":"81 Brunswick Woods Dr East Brunswick NJ 08816",
    "addr:housenumber":"81",
    "addr:postcode":"08816",
    "addr:street":"Brunswick Woods Dr",
    "iso:country":"US",
    "sg:address":"81 Brunswick Woods Dr",
    "sg:city":"East Brunswick",
    "sg:classifiers":[
        {
            "category":"Professional",
            "type":"Services"
        }
    ],
    "sg:phone":"+1 732 390 7188",
    "sg:postcode":"08816",
    "sg:province":"NJ",
    "sg:tags":[
        "establishment"
    ],
    "wof:name":"MSI",
    "wof:placetype":"venue"
},
  "geometry": {"coordinates":[-74.390924,40.422032],"type":"Point"}
}