{
  "type": "Feature",
  "properties": {
    "iso:country":"US",
    "sg:address":"84 S Front St",
    "sg:city":"Bergenfield",
    "sg:classifiers":[
        {
            "category":"Wholesale",
            "subcategory":"Machinery & Supplies",
            "type":"Manufacturing & Wholesale Goods"
        }
    ],
    "sg:phone":"+1 201 387 0400",
    "sg:postcode":"07621",
    "sg:province":"NJ",
    "sg:tags":[
        "industrial",
        "fastener",
        "fasteners-industrial",
        "stud",
        "distributor",
        "welding"
    ],
    "wof:name":"Spano Fastening Systems Inc",
    "wof:placetype":"venue"
},
  "geometry": {"coordinates":[-73.99901199999999,40.925026],"type":"Point"}
}