{
  "type": "Feature",
  "properties": {
    "iso:country":"US",
    "sg:address":"563 Dublin Rd",
    "sg:city":"Jackson",
    "sg:classifiers":[
        {
            "category":"Building & Trades",
            "subcategory":"Construction",
            "type":"Services"
        }
    ],
    "sg:phone":"+1 732 833 9088",
    "sg:postcode":"08527",
    "sg:province":"NJ",
    "sg:tags":[
        "house",
        "general",
        "contractor"
    ],
    "wof:name":"Muzio Home & Office Constructi",
    "wof:placetype":"venue"
},
  "geometry": {"coordinates":[-74.322729,40.149999],"type":"Point"}
}