{
  "type": "Feature",
  "properties": {
    "addr:full":"1373 Broad St Ste 300A Clifton NJ 07013",
    "addr:housenumber":"1373;300a",
    "addr:postcode":"07013",
    "addr:street":"Broad St Ste",
    "iso:country":"US",
    "sg:address":"1373 Broad St Ste 300A",
    "sg:city":"Clifton",
    "sg:classifiers":[
        {
            "category":"Professional",
            "subcategory":"Employment Agencies",
            "type":"Services"
        }
    ],
    "sg:phone":"+1 973 574 1244",
    "sg:postcode":"07013",
    "sg:province":"NJ",
    "wof:name":"Assurance Group",
    "wof:placetype":"venue"
},
  "geometry": {"coordinates":[-74.180212,40.850243],"type":"Point"}
}