{
  "type": "Feature",
  "properties": {
    "iso:country":"US",
    "sg:address":"2235 Springfield Ave",
    "sg:city":"Vauxhall",
    "sg:classifiers":[
        {
            "category":"Recreation",
            "type":"Entertainment"
        }
    ],
    "sg:phone":"+1 908 688 0977",
    "sg:postcode":"07088",
    "sg:province":"NJ",
    "sg:tags":[
        "range",
        "practice",
        "golf"
    ],
    "sg:website":"www.crescentgolfonline.com",
    "wof:name":"Crescent Fairways Inc",
    "wof:placetype":"venue"
},
  "geometry": {"coordinates":[-74.28540599999999,40.718153],"type":"Point"}
}