{
  "type": "Feature",
  "properties": {
    "addr:full":"89 Pompton Ave Cedar Grove NJ 07009",
    "addr:housenumber":"89",
    "addr:postcode":"07009",
    "addr:street":"Pompton Ave",
    "iso:country":"US",
    "sg:address":"89 Pompton Ave",
    "sg:city":"Cedar Grove",
    "sg:classifiers":[
        {
            "category":"Restaurant",
            "type":"Food & Drink"
        }
    ],
    "sg:phone":"+1 973 239 7726",
    "sg:postcode":"07009",
    "sg:province":"NJ",
    "sg:tags":[
        "eating",
        "chinese"
    ],
    "wof:name":"A New China Taste Restaurant",
    "wof:placetype":"venue"
},
  "geometry": {"coordinates":[-74.22730300000001,40.837299],"type":"Point"}
}