{
  "type": "Feature",
  "properties": {
    "addr:full":"38 Maine St Toms River NJ 08753",
    "addr:housenumber":"38",
    "addr:postcode":"08753",
    "addr:street":"Maine St",
    "iso:country":"US",
    "sg:address":"38 Maine St",
    "sg:city":"Toms River",
    "sg:classifiers":[
        {
            "category":"Shopping",
            "subcategory":"Clothing, Apparel, & Fashions",
            "type":"Retail Goods"
        }
    ],
    "sg:phone":"+1   ",
    "sg:postcode":"08753",
    "sg:province":"NJ",
    "sg:tags":[
        "family"
    ],
    "wof:name":"Levin Brothers Partnership",
    "wof:placetype":"venue"
},
  "geometry": {"coordinates":[-74.144824,40.009808],"type":"Point"}
}