{
  "type": "Feature",
  "properties": {
    "iso:country":"US",
    "sg:address":"1208 Fischer Blvd",
    "sg:city":"Toms River",
    "sg:classifiers":[
        {
            "category":"Shopping",
            "subcategory":"Bicycles & Sporting Goods",
            "type":"Retail Goods"
        }
    ],
    "sg:phone":"+1   ",
    "sg:postcode":"08753",
    "sg:province":"NJ",
    "wof:name":"Braggin Size Sport Fshing Sups",
    "wof:placetype":"venue"
},
  "geometry": {"coordinates":[-74.150671,39.995114],"type":"Point"}
}