{
  "type": "Feature",
  "properties": {
    "addr:full":"103 US Hwy 206 Branchville NJ 07826",
    "addr:housenumber":"103",
    "addr:postcode":"07826",
    "addr:street":"Us Hwy 206",
    "iso:country":"US",
    "sg:address":"103 US Hwy 206",
    "sg:city":"Branchville",
    "sg:classifiers":[
        {
            "category":"Restaurant",
            "type":"Food & Drink"
        }
    ],
    "sg:phone":"+1   ",
    "sg:postcode":"07826",
    "sg:province":"NJ",
    "sg:tags":[
        "eating"
    ],
    "wof:name":"Rosies Pizza & Italian Rest",
    "wof:placetype":"venue"
},
  "geometry": {"coordinates":[-74.80298999999999,41.200396],"type":"Point"}
}