{
  "type": "Feature",
  "properties": {
    "addr:full":"11 Spielman Rd Fairfield NJ 07004",
    "addr:housenumber":"11",
    "addr:postcode":"07004",
    "addr:street":"Spielman Rd",
    "iso:country":"US",
    "sg:address":"11 Spielman Rd",
    "sg:city":"Fairfield",
    "sg:classifiers":[
        {
            "category":"Manufacturing",
            "subcategory":"Rubber & Plastics",
            "type":"Manufacturing & Wholesale Goods"
        }
    ],
    "sg:phone":"+1 973 227 2505",
    "sg:postcode":"07004",
    "sg:province":"NJ",
    "sg:tags":[
        "product",
        "engineered",
        "mfg"
    ],
    "wof:name":"Prestige Rubber Manufacturing",
    "wof:placetype":"venue"
},
  "geometry": {"coordinates":[-74.29351200000001,40.877088],"type":"Point"}
}