{
  "type": "Feature",
  "properties": {
    "iso:country":"US",
    "sg:address":"135 Clay Ave W",
    "sg:city":"Roselle Park",
    "sg:classifiers":[
        {
            "category":"Manufacturing",
            "subcategory":"Tools & Machinery",
            "type":"Manufacturing & Wholesale Goods"
        }
    ],
    "sg:phone":"+1 908 245 5545",
    "sg:postcode":"07204",
    "sg:province":"NJ",
    "sg:tags":[
        "die",
        "maker"
    ],
    "wof:name":"Accurate Machine & Tool Co",
    "wof:placetype":"venue"
},
  "geometry": {"coordinates":[-74.270208,40.664281],"type":"Point"}
}