{
  "type": "Feature",
  "properties": {
    "iso:country":"US",
    "sg:address":"608 9th St",
    "sg:city":"Carlstadt",
    "sg:classifiers":[
        {
            "category":"Retail",
            "subcategory":"Repair Shop",
            "type":"Services"
        }
    ],
    "sg:phone":"+1 201 804 9884",
    "sg:postcode":"07072",
    "sg:province":"NJ",
    "sg:tags":[
        "electrical"
    ],
    "wof:name":"Computek Cartridge Recycling",
    "wof:placetype":"venue"
},
  "geometry": {"coordinates":[-74.084656,40.839242],"type":"Point"}
}