{
  "type": "Feature",
  "properties": {
    "addr:full":"522 Lippincott Dr Marlton NJ 08053",
    "addr:housenumber":"522",
    "addr:postcode":"08053",
    "addr:street":"Lippincott Dr",
    "iso:country":"US",
    "sg:address":"522 Lippincott Dr",
    "sg:city":"Marlton",
    "sg:classifiers":[
        {
            "category":"Health Services",
            "subcategory":"Doctor",
            "type":"Services"
        }
    ],
    "sg:phone":"+1   ",
    "sg:postcode":"08053",
    "sg:province":"NJ",
    "sg:tags":[
        "medical"
    ],
    "wof:name":"Lipschultz Todd M MD",
    "wof:placetype":"venue"
},
  "geometry": {"coordinates":[-74.925865,39.885367],"type":"Point"}
}