{
  "type": "Feature",
  "properties": {
    "iso:country":"US",
    "sg:address":"2178 Klockner Rd",
    "sg:city":"Trenton",
    "sg:classifiers":[
        {
            "category":"Retail",
            "subcategory":"Veterinary Services",
            "type":"Services"
        }
    ],
    "sg:phone":"+1 609 631 8146",
    "sg:postcode":"08690",
    "sg:province":"NJ",
    "wof:name":"Princton Eqine Vterinary Assoc",
    "wof:placetype":"venue"
},
  "geometry": {"coordinates":[-74.682643,40.223241],"type":"Point"}
}