{
  "type": "Feature",
  "properties": {
    "iso:country":"US",
    "sg:address":"3 Cardinal Rd",
    "sg:city":"Highland Lakes",
    "sg:classifiers":[
        {
            "category":"Building & Trades",
            "subcategory":"Electrical",
            "type":"Services"
        }
    ],
    "sg:phone":"+1 973 764 2955",
    "sg:postcode":"07422",
    "sg:province":"NJ",
    "sg:tags":[
        "electrical",
        "contractor"
    ],
    "wof:name":"John Butterly Electric Inc",
    "wof:placetype":"venue"
},
  "geometry": {"coordinates":[-74.426647,41.20379],"type":"Point"}
}