{
  "type": "Feature",
  "properties": {
    "iso:country":"US",
    "sg:address":"127 Rahway Ave",
    "sg:city":"Elizabeth",
    "sg:classifiers":[
        {
            "category":"Freight",
            "type":"Transportation"
        }
    ],
    "sg:phone":"+1 908 994 1900",
    "sg:postcode":"07202",
    "sg:province":"NJ",
    "wof:name":"Coast Recovery Transport",
    "wof:placetype":"venue"
},
  "geometry": {"coordinates":[-74.220489,40.660769],"type":"Point"}
}