{
  "type": "Feature",
  "properties": {
    "addr:full":"205 N Center Dr North Brunswick NJ 08902",
    "addr:housenumber":"205",
    "addr:postcode":"08902",
    "addr:street":"N Center Dr",
    "iso:country":"US",
    "sg:address":"205 N Center Dr",
    "sg:city":"North Brunswick",
    "sg:classifiers":[
        {
            "category":"Wholesale",
            "subcategory":"Computers",
            "type":"Manufacturing & Wholesale Goods"
        }
    ],
    "sg:phone":"+1 732 940 7900",
    "sg:postcode":"08902",
    "sg:province":"NJ",
    "sg:tags":[
        "web",
        "processing",
        "delivery",
        "remittance",
        "imaging",
        "software"
    ],
    "wof:name":"Image-Remit New Jersey Inc",
    "wof:placetype":"venue"
},
  "geometry": {"coordinates":[-74.500641,40.445702],"type":"Point"}
}