{
  "type": "Feature",
  "properties": {
    "addr:full":"279 New Brunswick Ave Perth Amboy NJ 08861",
    "addr:housenumber":"279",
    "addr:postcode":"08861",
    "addr:street":"New Brunswick Ave",
    "iso:country":"US",
    "sg:address":"279 New Brunswick Ave",
    "sg:city":"Perth Amboy",
    "sg:classifiers":[
        {
            "category":"Building & Trades",
            "subcategory":"Locksmith",
            "type":"Services"
        }
    ],
    "sg:phone":"+1 888 277 2960",
    "sg:postcode":"08861",
    "sg:province":"NJ",
    "sg:tags":[
        "key"
    ],
    "wof:name":"A 24 Hour Emergency Locksmith",
    "wof:placetype":"venue"
},
  "geometry": {"coordinates":[-74.27323699999999,40.513537],"type":"Point"}
}