{
  "type": "Feature",
  "properties": {
    "addr:full":"814 Willow Ave Hoboken NJ 07030",
    "addr:housenumber":"814",
    "addr:postcode":"07030",
    "addr:street":"Willow Ave",
    "iso:country":"US",
    "sg:address":"814 Willow Ave",
    "sg:city":"Hoboken",
    "sg:classifiers":[
        {
            "category":"Health Services",
            "subcategory":"Health Practitioner",
            "type":"Services"
        }
    ],
    "sg:phone":"+1 201 798 3306",
    "sg:postcode":"07030",
    "sg:province":"NJ",
    "sg:tags":[
        "pathologist",
        "speech"
    ],
    "wof:name":"Roxanne Warner",
    "wof:placetype":"venue"
},
  "geometry": {"coordinates":[-74.031634,40.747751],"type":"Point"}
}