{
  "type": "Feature",
  "properties": {
    "iso:country":"US",
    "sg:address":"235 N Central Ave",
    "sg:city":"Ramsey",
    "sg:classifiers":[
        {
            "category":"Professional",
            "subcategory":"Advertising",
            "type":"Services"
        }
    ],
    "sg:phone":"+1 201 934 4908",
    "sg:postcode":"07446",
    "sg:province":"NJ",
    "sg:tags":[
        "agency"
    ],
    "wof:name":"Cab Creative Services",
    "wof:placetype":"venue"
},
  "geometry": {"coordinates":[-74.14846300000001,41.066148],"type":"Point"}
}