{
  "type": "Feature",
  "properties": {
    "iso:country":"US",
    "sg:address":"233 New Milford Ave",
    "sg:city":"Dumont",
    "sg:classifiers":[
        {
            "category":"Building & Trades",
            "subcategory":"Construction",
            "type":"Services"
        }
    ],
    "sg:phone":"+1 201 384 3747",
    "sg:postcode":"07628",
    "sg:province":"NJ",
    "sg:tags":[
        "house"
    ],
    "wof:name":"Garrett Construction Co",
    "wof:placetype":"venue"
},
  "geometry": {"coordinates":[-74.00196800000001,40.944229],"type":"Point"}
}