{
  "type": "Feature",
  "properties": {
    "iso:country":"US",
    "sg:address":"300 South Ave",
    "sg:city":"Garwood",
    "sg:classifiers":[
        {
            "category":"Personal",
            "subcategory":"Beauty Salon",
            "type":"Services"
        }
    ],
    "sg:phone":"+1   ",
    "sg:postcode":"07027",
    "sg:province":"NJ",
    "sg:tags":[
        "shop"
    ],
    "wof:name":"Labottega",
    "wof:placetype":"venue"
},
  "geometry": {"coordinates":[-74.32487399999999,40.651463],"type":"Point"}
}