{
  "type": "Feature",
  "properties": {
    "iso:country":"US",
    "sg:address":"343 E Holly Ave",
    "sg:city":"Pitman",
    "sg:classifiers":[
        {
            "category":"Retail",
            "subcategory":"Repair Shop",
            "type":"Services"
        }
    ],
    "sg:phone":"+1 856 582 2258",
    "sg:postcode":"08071",
    "sg:province":"NJ",
    "sg:tags":[
        "lock",
        "locksmith"
    ],
    "wof:name":"B Zane's Locksmith Shop",
    "wof:placetype":"venue"
},
  "geometry": {"coordinates":[-75.122894,39.736152],"type":"Point"}
}