{
  "type": "Feature",
  "properties": {
    "iso:country":"US",
    "sg:address":"300 Atlantic Ave",
    "sg:city":"Atlantic City",
    "sg:classifiers":[
        {
            "category":"Education",
            "subcategory":"Special Training",
            "type":"Public Place"
        }
    ],
    "sg:phone":"+1 609 340 8823",
    "sg:postcode":"08401",
    "sg:province":"NJ",
    "sg:tags":[
        "center"
    ],
    "wof:name":"Alternative Learning Ctr",
    "wof:placetype":"venue"
},
  "geometry": {"coordinates":[-74.415497,39.367197],"type":"Point"}
}