{
  "type": "Feature",
  "properties": {
    "addr:full":"1001 Anderson Ave Fort Lee NJ 07024",
    "addr:housenumber":"1001",
    "addr:postcode":"07024",
    "addr:street":"Anderson Ave",
    "iso:country":"US",
    "sg:address":"1001 Anderson Ave",
    "sg:city":"Fort Lee",
    "sg:classifiers":[
        {
            "category":"Health Services",
            "subcategory":"Doctor",
            "type":"Services"
        }
    ],
    "sg:phone":"+1 201 224 5252",
    "sg:postcode":"07024",
    "sg:province":"NJ",
    "sg:tags":[
        "physician",
        "surgeon",
        "medical"
    ],
    "wof:name":"Anthony M Maggiano MD",
    "wof:placetype":"venue"
},
  "geometry": {"coordinates":[-73.984053,40.833694],"type":"Point"}
}