{
  "type": "Feature",
  "properties": {
    "addr:full":"47 Lexington Ave Bayonne NJ 07002",
    "addr:housenumber":"47",
    "addr:postcode":"07002",
    "addr:street":"Lexington Ave",
    "iso:country":"US",
    "sg:address":"47 Lexington Ave",
    "sg:city":"Bayonne",
    "sg:classifiers":[
        {
            "category":"Building & Trades",
            "subcategory":"Construction",
            "type":"Services"
        }
    ],
    "sg:phone":"+1 201 436 9427",
    "sg:postcode":"07002",
    "sg:province":"NJ",
    "sg:tags":[
        "contractor"
    ],
    "wof:name":"John A Morecraft Inc",
    "wof:placetype":"venue"
},
  "geometry": {"coordinates":[-74.125737,40.648132],"type":"Point"}
}