{
  "type": "Feature",
  "properties": {
    "iso:country":"US",
    "sg:address":"2115 Millburn Ave",
    "sg:city":"Maplewood",
    "sg:classifiers":[
        {
            "category":"Professional",
            "subcategory":"Lawyer & Legal Services",
            "type":"Services"
        }
    ],
    "sg:phone":"+1 973 762 1187",
    "sg:postcode":"07040",
    "sg:province":"NJ",
    "sg:tags":[
        "attorney"
    ],
    "wof:name":"William H Sheil",
    "wof:placetype":"venue"
},
  "geometry": {"coordinates":[-74.281087,40.721629],"type":"Point"}
}