{
  "type": "Feature",
  "properties": {
    "addr:full":"297 Barrington Dr Bridgewater NJ 08807",
    "addr:housenumber":"297",
    "addr:postcode":"08807",
    "addr:street":"Barrington Dr",
    "iso:country":"US",
    "sg:address":"297 Barrington Dr",
    "sg:city":"Bridgewater",
    "sg:classifiers":[
        {
            "category":"Professional",
            "subcategory":"Business Services",
            "type":"Services"
        }
    ],
    "sg:phone":"+1   ",
    "sg:postcode":"08807",
    "sg:province":"NJ",
    "wof:name":"Noviello Financial Group Inc",
    "wof:placetype":"venue"
},
  "geometry": {"coordinates":[-74.657842,40.608001],"type":"Point"}
}