{
  "type": "Feature",
  "properties": {
    "iso:country":"US",
    "sg:address":"69 Grove St",
    "sg:city":"Somerville",
    "sg:classifiers":[
        {
            "category":"Real Estate",
            "subcategory":"Real Estate Agent",
            "type":"Services"
        }
    ],
    "sg:phone":"+1   ",
    "sg:postcode":"08876",
    "sg:province":"NJ",
    "wof:name":"Sopko Associates LLC",
    "wof:placetype":"venue"
},
  "geometry": {"coordinates":[-74.609133,40.570248],"type":"Point"}
}