{
  "type": "Feature",
  "properties": {
    "addr:full":"456 High St Mount Holly NJ 08060",
    "addr:housenumber":"456",
    "addr:postcode":"08060",
    "addr:street":"High St",
    "iso:country":"US",
    "sg:address":"456 High St",
    "sg:city":"Mount Holly",
    "sg:classifiers":[
        {
            "category":"Real Estate",
            "subcategory":"Architect",
            "type":"Services"
        }
    ],
    "sg:phone":"+1 609 265 2652",
    "sg:postcode":"08060",
    "sg:province":"NJ",
    "sg:website":"www.ryebread.com",
    "wof:name":"Ryebread Architects",
    "wof:placetype":"venue"
},
  "geometry": {"coordinates":[-74.792711,40.002396],"type":"Point"}
}