{
  "type": "Feature",
  "properties": {
    "iso:country":"US",
    "sg:address":"229 Brynmore Rd",
    "sg:city":"New Egypt",
    "sg:classifiers":[
        {
            "category":"Manufacturing",
            "subcategory":"Apparel",
            "type":"Manufacturing & Wholesale Goods"
        }
    ],
    "sg:phone":"+1 609 758 0116",
    "sg:postcode":"08533",
    "sg:province":"NJ",
    "wof:name":"Carols Custom Creations",
    "wof:placetype":"venue"
},
  "geometry": {"coordinates":[-74.50233299999999,40.061417],"type":"Point"}
}