{
  "type": "Feature",
  "properties": {
    "iso:country":"US",
    "sg:address":"310 Ocean Ave",
    "sg:city":"Rumson",
    "sg:classifiers":[
        {
            "category":"Professional",
            "subcategory":"Management & Consulting",
            "type":"Services"
        }
    ],
    "sg:phone":"+1 732 842 3433",
    "sg:postcode":"07760",
    "sg:province":"NJ",
    "wof:name":"Tightline Destinations",
    "wof:placetype":"venue"
},
  "geometry": {"coordinates":[-73.974773,40.382098],"type":"Point"}
}