{
  "type": "Feature",
  "properties": {
    "iso:country":"US",
    "sg:address":"108 N Pennsylvania Ave",
    "sg:city":"Atlantic City",
    "sg:classifiers":[
        {
            "category":"Organizations",
            "subcategory":"Religious Organization",
            "type":"Services"
        }
    ],
    "sg:phone":"+1   ",
    "sg:postcode":"08401",
    "sg:province":"NJ",
    "wof:name":"Saint Monicas Church",
    "wof:placetype":"venue"
},
  "geometry": {"coordinates":[-74.426179,39.366351],"type":"Point"}
}