{
  "type": "Feature",
  "properties": {
    "iso:country":"US",
    "sg:address":"4 Rose Ln",
    "sg:city":"Somers Point",
    "sg:classifiers":[
        {
            "category":"Health Services",
            "subcategory":"Doctor",
            "type":"Services"
        }
    ],
    "sg:phone":"+1 609 653 0602",
    "sg:postcode":"08244",
    "sg:province":"NJ",
    "sg:tags":[
        "physician",
        "surgeon"
    ],
    "wof:name":"M Slotoroff MD",
    "wof:placetype":"venue"
},
  "geometry": {"coordinates":[-74.612717,39.317951],"type":"Point"}
}