{
  "type": "Feature",
  "properties": {
    "addr:full":"17 Creek Rd Port Monmouth NJ 07758",
    "addr:housenumber":"17",
    "addr:postcode":"07758",
    "addr:street":"Creek Rd",
    "iso:country":"US",
    "sg:address":"17 Creek Rd",
    "sg:city":"Port Monmouth",
    "sg:classifiers":[
        {
            "category":"Professional",
            "subcategory":"Management & Consulting",
            "type":"Services"
        }
    ],
    "sg:phone":"+1 732 787 2005",
    "sg:postcode":"07758",
    "sg:province":"NJ",
    "sg:tags":[
        "consultant",
        "security",
        "system"
    ],
    "wof:name":"Secure Touch Inc",
    "wof:placetype":"venue"
},
  "geometry": {"coordinates":[-74.09780000000001,40.428167],"type":"Point"}
}