{
  "type": "Feature",
  "properties": {
    "iso:country":"US",
    "sg:address":"1121 N Michigan Ave",
    "sg:city":"Atlantic City",
    "sg:classifiers":[
        {
            "category":"Building & Trades",
            "subcategory":"Plumbing",
            "type":"Services"
        }
    ],
    "sg:phone":"+1 609 348 0506",
    "sg:postcode":"08401",
    "sg:province":"NJ",
    "sg:tags":[
        "plumbing",
        "contractor"
    ],
    "wof:name":"P W Watson Plumbing & Heating",
    "wof:placetype":"venue"
},
  "geometry": {"coordinates":[-74.443313,39.370649],"type":"Point"}
}