{
  "type": "Feature",
  "properties": {
    "addr:full":"10 Garden Ln Montvale NJ 07645",
    "addr:housenumber":"10",
    "addr:postcode":"07645",
    "addr:street":"Garden Ln",
    "iso:country":"US",
    "sg:address":"10 Garden Ln",
    "sg:city":"Montvale",
    "sg:classifiers":[
        {
            "category":"Real Estate",
            "subcategory":"Real Estate Services",
            "type":"Services"
        },
        {
            "category":"Banks & Credit Unions",
            "subcategory":"Financial Services",
            "type":"Services"
        }
    ],
    "sg:phone":"+1 866 968 5555",
    "sg:postcode":"07645",
    "sg:province":"NJ",
    "sg:tags":[
        "loan",
        "mortgage"
    ],
    "sg:website":"http://www.dmacfinancial.com",
    "wof:name":"Dmac Financial",
    "wof:placetype":"venue"
},
  "geometry": {"coordinates":[-74.07858299999999,41.050269],"type":"Point"}
}