{
  "type": "Feature",
  "properties": {
    "addr:full":"165 Lees Ave Teaneck NJ 07666",
    "addr:housenumber":"165",
    "addr:postcode":"07666",
    "addr:street":"Lees Ave",
    "iso:country":"US",
    "sg:address":"165 Lees Ave",
    "sg:city":"Teaneck",
    "sg:classifiers":[
        {
            "category":"Shopping",
            "subcategory":"Computers & Home Electronics",
            "type":"Retail Goods"
        }
    ],
    "sg:phone":"+1 201 692 0005",
    "sg:postcode":"07666",
    "sg:province":"NJ",
    "sg:tags":[
        "software"
    ],
    "wof:name":"Client Server",
    "wof:placetype":"venue"
},
  "geometry": {"coordinates":[-74.01667999999999,40.869572],"type":"Point"}
}