{
  "type": "Feature",
  "properties": {
    "addr:full":"101 US Hwy 46 Pine Brook NJ 07058",
    "addr:housenumber":"101",
    "addr:postcode":"07058",
    "addr:street":"Us Hwy 46",
    "iso:country":"US",
    "sg:address":"101 US Hwy 46",
    "sg:city":"Pine Brook",
    "sg:classifiers":[
        {
            "category":"Real Estate",
            "subcategory":"Real Estate Agent",
            "type":"Services"
        }
    ],
    "sg:phone":"+1   ",
    "sg:postcode":"07058",
    "sg:province":"NJ",
    "wof:name":"Rensselear Commercial Prpts",
    "wof:placetype":"venue"
},
  "geometry": {"coordinates":[-74.32420999999999,40.85995],"type":"Point"}
}