{
  "type": "Feature",
  "properties": {
    "addr:full":"249 Straight St Ste A Paterson NJ 07501",
    "addr:housenumber":"249",
    "addr:postcode":"07501",
    "addr:street":"Straight St Ste A",
    "iso:country":"US",
    "sg:address":"249 Straight St Ste A",
    "sg:city":"Paterson",
    "sg:classifiers":[
        {
            "category":"Restaurant",
            "type":"Food & Drink"
        }
    ],
    "sg:phone":"+1 973 742 1764",
    "sg:postcode":"07501",
    "sg:province":"NJ",
    "wof:name":"El Eden Restaurant",
    "wof:placetype":"venue"
},
  "geometry": {"coordinates":[-74.166257,40.915761],"type":"Point"}
}