{
  "type": "Feature",
  "properties": {
    "iso:country":"US",
    "sg:address":"11 Tanager Run",
    "sg:city":"Kinnelon",
    "sg:classifiers":[
        {
            "category":"Building & Trades",
            "subcategory":"Construction",
            "type":"Services"
        }
    ],
    "sg:phone":"+1 973 492 5974",
    "sg:postcode":"07405",
    "sg:province":"NJ",
    "sg:tags":[
        "contractor"
    ],
    "wof:name":"Verblaauw Construction Co Inc",
    "wof:placetype":"venue"
},
  "geometry": {"coordinates":[-74.392132,40.97442],"type":"Point"}
}