{
  "type": "Feature",
  "properties": {
    "iso:country":"US",
    "sg:address":"79 Lexington Ave",
    "sg:city":"Dumont",
    "sg:classifiers":[
        {
            "category":"Professional",
            "type":"Services"
        }
    ],
    "sg:phone":"+1   ",
    "sg:postcode":"07628",
    "sg:province":"NJ",
    "wof:name":"Gangasons Inc",
    "wof:placetype":"venue"
},
  "geometry": {"coordinates":[-73.985477,40.948991],"type":"Point"}
}