{
  "type": "Feature",
  "properties": {
    "iso:country":"US",
    "sg:address":"319 W Washington Ave",
    "sg:city":"Washington",
    "sg:classifiers":[
        {
            "category":"Organizations",
            "subcategory":"Non-profit Organization",
            "type":"Services"
        }
    ],
    "sg:phone":"+1 908 689 7525",
    "sg:postcode":"07882",
    "sg:province":"NJ",
    "sg:tags":[
        "human"
    ],
    "wof:name":"Arc Warren County Chapter Inc",
    "wof:placetype":"venue"
},
  "geometry": {"coordinates":[-74.99598400000001,40.754562],"type":"Point"}
}