{
  "type": "Feature",
  "properties": {
    "addr:full":"10 1st St Hackensack NJ 07601",
    "addr:housenumber":"10",
    "addr:postcode":"07601",
    "addr:street":"1St St",
    "iso:country":"US",
    "sg:address":"10 1st St",
    "sg:city":"Hackensack",
    "sg:classifiers":[
        {
            "category":"Real Estate",
            "subcategory":"Real Estate Services",
            "type":"Services"
        }
    ],
    "sg:phone":"+1 201 343 3050",
    "sg:postcode":"07601",
    "sg:province":"NJ",
    "sg:tags":[
        "management",
        "property"
    ],
    "wof:name":"America East Real Estate",
    "wof:placetype":"venue"
},
  "geometry": {"coordinates":[-74.054147,40.881203],"type":"Point"}
}