{
  "type": "Feature",
  "properties": {
    "addr:full":"194 Jacobstown Cookstown Rd Wrightstown NJ 08562",
    "addr:housenumber":"194",
    "addr:postcode":"08562",
    "addr:street":"Jacobstown Cookstown Rd",
    "iso:country":"US",
    "sg:address":"194 Jacobstown Cookstown Rd",
    "sg:city":"Wrightstown",
    "sg:classifiers":[
        {
            "category":"Personal",
            "subcategory":"Beauty Salon",
            "type":"Services"
        }
    ],
    "sg:phone":"+1 609 758 8490",
    "sg:postcode":"08562",
    "sg:province":"NJ",
    "wof:name":"Hair Barn",
    "wof:placetype":"venue"
},
  "geometry": {"coordinates":[-74.579644,40.059523],"type":"Point"}
}