{
  "type": "Feature",
  "properties": {
    "iso:country":"US",
    "sg:address":"410 State Route 10",
    "sg:city":"East Hanover",
    "sg:classifiers":[
        {
            "category":"Shopping",
            "subcategory":"Hobbies, Toys, & Games",
            "type":"Retail Goods"
        }
    ],
    "sg:phone":"+1 973 560 1100",
    "sg:postcode":"07936",
    "sg:province":"NJ",
    "sg:tags":[
        "toy",
        "store"
    ],
    "wof:name":"Five Below",
    "wof:placetype":"venue"
},
  "geometry": {"coordinates":[-74.361937,40.802561],"type":"Point"}
}