{
  "type": "Feature",
  "properties": {
    "iso:country":"US",
    "sg:address":"63 Lilline Ln",
    "sg:city":"Saddle River",
    "sg:classifiers":[
        {
            "category":"Utilities",
            "subcategory":"Telephone",
            "type":"Services"
        }
    ],
    "sg:phone":"+1 201 825 2384",
    "sg:postcode":"07458",
    "sg:province":"NJ",
    "sg:tags":[
        "communications"
    ],
    "wof:name":"Silkjohns",
    "wof:placetype":"venue"
},
  "geometry": {"coordinates":[-74.10812900000001,41.067178],"type":"Point"}
}