{
  "type": "Feature",
  "properties": {
    "iso:country":"US",
    "sg:address":"5106 Aberdeen Dr",
    "sg:city":"Mount Laurel",
    "sg:classifiers":[
        {
            "category":"Professional",
            "subcategory":"Management & Consulting",
            "type":"Services"
        }
    ],
    "sg:phone":"+1   ",
    "sg:postcode":"08054",
    "sg:province":"NJ",
    "wof:name":"N & M Marketing",
    "wof:placetype":"venue"
},
  "geometry": {"coordinates":[-74.883498,39.972297],"type":"Point"}
}