{
  "type": "Feature",
  "properties": {
    "addr:full":"44 W Chestnut Ave Merchantville NJ 08109",
    "addr:housenumber":"44",
    "addr:postcode":"08109",
    "addr:street":"W Chestnut Ave",
    "iso:country":"US",
    "sg:address":"44 W Chestnut Ave",
    "sg:city":"Merchantville",
    "sg:classifiers":[
        {
            "category":"Social Services",
            "subcategory":"Job Training",
            "type":"Services"
        }
    ],
    "sg:phone":"+1 856 317 9300",
    "sg:postcode":"08109",
    "sg:province":"NJ",
    "sg:tags":[
        "rehabilitation"
    ],
    "wof:name":"Beechwood Center Of New Jersey",
    "wof:placetype":"venue"
},
  "geometry": {"coordinates":[-75.049008,39.952166],"type":"Point"}
}