{
  "type": "Feature",
  "properties": {
    "addr:full":"60 Brown Ave Springfield NJ 07081",
    "addr:housenumber":"60",
    "addr:postcode":"07081",
    "addr:street":"Brown Ave",
    "iso:country":"US",
    "sg:address":"60 Brown Ave",
    "sg:city":"Springfield",
    "sg:classifiers":[
        {
            "category":"Wholesale",
            "subcategory":"Machinery & Supplies",
            "type":"Manufacturing & Wholesale Goods"
        }
    ],
    "sg:phone":"+1 973 376 5877",
    "sg:postcode":"07081",
    "sg:province":"NJ",
    "sg:tags":[
        "janitor",
        "janitorial"
    ],
    "wof:name":"Gem Janitorial Supply Co Inc",
    "wof:placetype":"venue"
},
  "geometry": {"coordinates":[-74.317821,40.691238],"type":"Point"}
}