{
  "type": "Feature",
  "properties": {
    "addr:full":"288 2nd Ave W Newark NJ 07107",
    "addr:housenumber":"288",
    "addr:postcode":"07107",
    "addr:street":"2Nd Ave W",
    "iso:country":"US",
    "sg:address":"288 2nd Ave W",
    "sg:city":"Newark",
    "sg:classifiers":[
        {
            "category":"Social Services",
            "type":"Services"
        }
    ],
    "sg:phone":"+1   ",
    "sg:postcode":"07107",
    "sg:province":"NJ",
    "wof:name":"Health & Education Founda",
    "wof:placetype":"venue"
},
  "geometry": {"coordinates":[-74.182419,40.76565],"type":"Point"}
}