{
  "type": "Feature",
  "properties": {
    "addr:full":"1480 US Hwy 9 Woodbridge NJ 07095",
    "addr:housenumber":"1480",
    "addr:postcode":"07095",
    "addr:street":"Us Hwy 9",
    "iso:country":"US",
    "sg:address":"1480 US Hwy 9",
    "sg:city":"Woodbridge",
    "sg:classifiers":[
        {
            "category":"Banks & Credit Unions",
            "subcategory":"Bank",
            "type":"Services"
        }
    ],
    "sg:phone":"+1 908 241 9294",
    "sg:postcode":"07095",
    "sg:province":"NJ",
    "sg:tags":[
        "loan",
        "real estate"
    ],
    "wof:name":"A & E Mortgage Co",
    "wof:placetype":"venue"
},
  "geometry": {"coordinates":[-74.296066,40.561009],"type":"Point"}
}