{
  "type": "Feature",
  "properties": {
    "iso:country":"US",
    "sg:address":"62 Monmouth Rd",
    "sg:city":"Oakhurst",
    "sg:classifiers":[
        {
            "category":"Professional",
            "subcategory":"Lawyer & Legal Services",
            "type":"Services"
        }
    ],
    "sg:phone":"+1 732 229 7100",
    "sg:postcode":"07755",
    "sg:province":"NJ",
    "wof:name":"Sachs Jane M Public Account An",
    "wof:placetype":"venue"
},
  "geometry": {"coordinates":[-74.015743,40.270416],"type":"Point"}
}