{
  "type": "Feature",
  "properties": {
    "addr:full":"17 Belleville Ave Bloomfield NJ 07003",
    "addr:housenumber":"17",
    "addr:postcode":"07003",
    "addr:street":"Belleville Ave",
    "iso:country":"US",
    "sg:address":"17 Belleville Ave",
    "sg:city":"Bloomfield",
    "sg:classifiers":[
        {
            "category":"Shopping",
            "subcategory":"Pharmacy",
            "type":"Retail Goods"
        }
    ],
    "sg:phone":"+1   ",
    "sg:postcode":"07003",
    "sg:province":"NJ",
    "wof:name":"Walgreens",
    "wof:placetype":"venue"
},
  "geometry": {"coordinates":[-74.17986399999999,40.796633],"type":"Point"}
}