{
  "type": "Feature",
  "properties": {
    "addr:full":"361 Wayne St Jersey City NJ 07302",
    "addr:housenumber":"361",
    "addr:postcode":"07302",
    "addr:street":"Wayne St",
    "iso:country":"US",
    "sg:address":"361 Wayne St",
    "sg:city":"Jersey City",
    "sg:classifiers":[
        {
            "category":"Travel",
            "subcategory":"Travel Agent",
            "type":"Entertainment"
        }
    ],
    "sg:phone":"+1 201 434 4229",
    "sg:postcode":"07302",
    "sg:province":"NJ",
    "sg:tags":[
        "agency"
    ],
    "wof:name":"Green Flag Travel Inc",
    "wof:placetype":"venue"
},
  "geometry": {"coordinates":[-74.05694800000001,40.722897],"type":"Point"}
}