{
  "type": "Feature",
  "properties": {
    "addr:full":"964 Bergen St Newark NJ 07112",
    "addr:housenumber":"964",
    "addr:postcode":"07112",
    "addr:street":"Bergen St",
    "iso:country":"US",
    "sg:address":"964 Bergen St",
    "sg:city":"Newark",
    "sg:classifiers":[
        {
            "category":"Restaurant",
            "type":"Food & Drink"
        }
    ],
    "sg:phone":"+1 973 282 0023",
    "sg:postcode":"07112",
    "sg:province":"NJ",
    "wof:name":"Hiba Halal Grill",
    "wof:placetype":"venue"
},
  "geometry": {"coordinates":[-74.20592600000001,40.710688],"type":"Point"}
}