{
  "type": "Feature",
  "properties": {
    "iso:country":"US",
    "sg:address":"303 Midland Ave",
    "sg:city":"Garfield",
    "sg:classifiers":[
        {
            "category":"Building & Trades",
            "subcategory":"Locksmith",
            "type":"Services"
        }
    ],
    "sg:phone":"+1 888 225 2626",
    "sg:postcode":"07026",
    "sg:province":"NJ",
    "sg:tags":[
        "key"
    ],
    "wof:name":"24 Emergency Locksmith",
    "wof:placetype":"venue"
},
  "geometry": {"coordinates":[-74.103692,40.875342],"type":"Point"}
}