{
  "type": "Feature",
  "properties": {
    "iso:country":"US",
    "sg:address":"610 Station Ave",
    "sg:city":"Haddon Heights",
    "sg:classifiers":[
        {
            "category":"Building & Trades",
            "subcategory":"Plumbing",
            "type":"Services"
        }
    ],
    "sg:phone":"+1 856 547 0656",
    "sg:postcode":"08035",
    "sg:province":"NJ",
    "wof:name":"Schmidt C Len & Son Inc",
    "wof:placetype":"venue"
},
  "geometry": {"coordinates":[-75.059196,39.882099],"type":"Point"}
}