{
  "type": "Feature",
  "properties": {
    "iso:country":"US",
    "sg:address":"3608 Bergenline Ave",
    "sg:city":"Union City",
    "sg:classifiers":[
        {
            "category":"Health Services",
            "subcategory":"Clinic",
            "type":"Services"
        }
    ],
    "sg:phone":"+1 201 553 9330",
    "sg:postcode":"07087",
    "sg:province":"NJ",
    "sg:tags":[
        "home"
    ],
    "wof:name":"Excellent Home Health Care",
    "wof:placetype":"venue"
},
  "geometry": {"coordinates":[-74.027192,40.774621],"type":"Point"}
}