{
  "type": "Feature",
  "properties": {
    "iso:country":"US",
    "sg:address":"35 State Route 35",
    "sg:city":"Eatontown",
    "sg:classifiers":[
        {
            "category":"Restaurant",
            "type":"Food & Drink"
        }
    ],
    "sg:menulink":"http://www.allmenus.com/nj/eatontown/146283-subway/menu/",
    "sg:phone":"+1 732 542 4050",
    "sg:postcode":"07724",
    "sg:province":"NJ",
    "sg:tags":[
        "american",
        "sandwich"
    ],
    "wof:name":"Subway",
    "wof:placetype":"venue"
},
  "geometry": {"coordinates":[-74.05905300000001,40.30332],"type":"Point"}
}