{
  "type": "Feature",
  "properties": {
    "addr:full":"1527 John St Fort Lee NJ 07024",
    "addr:housenumber":"1527",
    "addr:postcode":"07024",
    "addr:street":"John St",
    "iso:country":"US",
    "sg:address":"1527 John St",
    "sg:city":"Fort Lee",
    "sg:classifiers":[
        {
            "category":"Professional",
            "subcategory":"Computer Services",
            "type":"Services"
        }
    ],
    "sg:phone":"+1   ",
    "sg:postcode":"07024",
    "sg:province":"NJ",
    "sg:tags":[
        "related"
    ],
    "wof:name":"Kleva Inc",
    "wof:placetype":"venue"
},
  "geometry": {"coordinates":[-73.97935200000001,40.853187],"type":"Point"}
}