{
  "type": "Feature",
  "properties": {
    "addr:full":"626 US Hwy 206 Hillsborough NJ 08844",
    "addr:housenumber":"626",
    "addr:postcode":"08844",
    "addr:street":"Us Hwy 206",
    "iso:country":"US",
    "sg:address":"626 US Hwy 206",
    "sg:city":"Hillsborough",
    "sg:classifiers":[
        {
            "category":"Personal",
            "subcategory":"Beauty Salon",
            "type":"Services"
        }
    ],
    "sg:phone":"+1 908 359 7511",
    "sg:postcode":"08844",
    "sg:province":"NJ",
    "wof:name":"Adam & Eve Hairstylists",
    "wof:placetype":"venue"
},
  "geometry": {"coordinates":[-74.64546799999999,40.500845],"type":"Point"}
}