{
  "type": "Feature",
  "properties": {
    "addr:full":"38 Maple Ave Stockholm NJ 07460",
    "addr:housenumber":"38",
    "addr:postcode":"07460",
    "addr:street":"Maple Ave",
    "iso:country":"US",
    "sg:address":"38 Maple Ave",
    "sg:city":"Stockholm",
    "sg:classifiers":[
        {
            "category":"Social Services",
            "subcategory":"Child Care",
            "type":"Services"
        }
    ],
    "sg:phone":"+1   ",
    "sg:postcode":"07460",
    "sg:province":"NJ",
    "sg:tags":[
        "day"
    ],
    "wof:name":"Creative Learning Center",
    "wof:placetype":"venue"
},
  "geometry": {"coordinates":[-74.524793,41.072317],"type":"Point"}
}