{
  "type": "Feature",
  "properties": {
    "addr:full":"18 Stanwood Ct Medford NJ 08055",
    "addr:housenumber":"18",
    "addr:postcode":"08055",
    "addr:street":"Stanwood Ct",
    "iso:country":"US",
    "sg:address":"18 Stanwood Ct",
    "sg:city":"Medford",
    "sg:classifiers":[
        {
            "category":"Professional",
            "subcategory":"Art Services",
            "type":"Services"
        }
    ],
    "sg:phone":"+1   ",
    "sg:postcode":"08055",
    "sg:province":"NJ",
    "sg:tags":[
        "commercial",
        "design"
    ],
    "wof:name":"Precision Illustration",
    "wof:placetype":"venue"
},
  "geometry": {"coordinates":[-74.842591,39.874464],"type":"Point"}
}