{
  "type": "Feature",
  "properties": {
    "iso:country":"US",
    "sg:address":"70 18th Ave",
    "sg:city":"Paterson",
    "sg:classifiers":[
        {
            "category":"Utilities",
            "subcategory":"Mobile Phone",
            "type":"Services"
        }
    ],
    "sg:phone":"+1 201 513 8000",
    "sg:postcode":"07513",
    "sg:province":"NJ",
    "sg:tags":[
        "communication",
        "radiotelephone"
    ],
    "wof:name":"Easy Wireless Inc",
    "wof:placetype":"venue"
},
  "geometry": {"coordinates":[-74.152111,40.911571],"type":"Point"}
}