{
  "type": "Feature",
  "properties": {
    "addr:full":"166 Main St Hackettstown NJ 07840",
    "addr:housenumber":"166",
    "addr:postcode":"07840",
    "addr:street":"Main St",
    "iso:country":"US",
    "sg:address":"166 Main St",
    "sg:city":"Hackettstown",
    "sg:classifiers":[
        {
            "category":"Building & Trades",
            "subcategory":"Cleaning & Sanitation",
            "type":"Services"
        }
    ],
    "sg:phone":"+1 908 852 5678",
    "sg:postcode":"07840",
    "sg:province":"NJ",
    "wof:name":"Scrubadub Of New Jersey",
    "wof:placetype":"venue"
},
  "geometry": {"coordinates":[-74.828952,40.853487],"type":"Point"}
}