{
  "type": "Feature",
  "properties": {
    "addr:full":"3 Spruce Run Rd Clinton NJ 08809",
    "addr:housenumber":"3",
    "addr:postcode":"08809",
    "addr:street":"Spruce Run Rd",
    "iso:country":"US",
    "sg:address":"3 Spruce Run Rd",
    "sg:city":"Clinton",
    "sg:classifiers":[
        {
            "category":"Professional",
            "subcategory":"Computer Services",
            "type":"Services"
        }
    ],
    "sg:phone":"+1   ",
    "sg:postcode":"08809",
    "sg:province":"NJ",
    "sg:tags":[
        "related"
    ],
    "wof:name":"A M M Consulting",
    "wof:placetype":"venue"
},
  "geometry": {"coordinates":[-74.922562,40.636922],"type":"Point"}
}