{
  "type": "Feature",
  "properties": {
    "iso:country":"US",
    "sg:address":"1020 Galloping Hill Rd",
    "sg:city":"Union",
    "sg:classifiers":[
        {
            "category":"Health Services",
            "subcategory":"Nursing And Care Facility",
            "type":"Services"
        }
    ],
    "sg:phone":"+1   ",
    "sg:postcode":"07083",
    "sg:province":"NJ",
    "sg:tags":[
        "home"
    ],
    "wof:name":"Cornell Hall Convalescent Ctr",
    "wof:placetype":"venue"
},
  "geometry": {"coordinates":[-74.26759,40.677082],"type":"Point"}
}