{
  "type": "Feature",
  "properties": {
    "iso:country":"US",
    "sg:address":"2 Llewellyn Ave",
    "sg:city":"Hawthorne",
    "sg:classifiers":[
        {
            "category":"Manufacturing",
            "subcategory":"Retail Goods",
            "type":"Manufacturing & Wholesale Goods"
        }
    ],
    "sg:phone":"+1 201 649 7412",
    "sg:postcode":"07506",
    "sg:province":"NJ",
    "sg:tags":[
        "assembly",
        "fabricating"
    ],
    "wof:name":"Jatfab Assembly Inc",
    "wof:placetype":"venue"
},
  "geometry": {"coordinates":[-74.15410799999999,40.945938],"type":"Point"}
}