{
  "type": "Feature",
  "properties": {
    "iso:country":"US",
    "sg:address":"0 State Rte 208",
    "sg:city":"Fair Lawn",
    "sg:classifiers":[
        {
            "category":"Professional",
            "subcategory":"Management & Consulting",
            "type":"Services"
        }
    ],
    "sg:phone":"+1 201 398 9870",
    "sg:postcode":"07410",
    "sg:province":"NJ",
    "sg:tags":[
        "construction"
    ],
    "wof:name":"Bethay Consultants Inc",
    "wof:placetype":"venue"
},
  "geometry": {"coordinates":[-74.132098,40.945156],"type":"Point"}
}