{
  "type": "Feature",
  "properties": {
    "iso:country":"US",
    "sg:address":"405 Broad St",
    "sg:city":"Bloomfield",
    "sg:classifiers":[
        {
            "category":"Professional",
            "subcategory":"Accounting & Tax Preparation",
            "type":"Services"
        }
    ],
    "sg:phone":"+1 973 429 9461",
    "sg:postcode":"07003",
    "sg:province":"NJ",
    "sg:tags":[
        "return",
        "filing"
    ],
    "wof:name":"Pilgrim Tax Svc Inc",
    "wof:placetype":"venue"
},
  "geometry": {"coordinates":[-74.19291699999999,40.806264],"type":"Point"}
}