{
  "type": "Feature",
  "properties": {
    "iso:country":"US",
    "sg:address":"1202 Central Ave",
    "sg:city":"Minotola",
    "sg:classifiers":[
        {
            "category":"Personal",
            "subcategory":"Beauty Salon",
            "type":"Services"
        }
    ],
    "sg:phone":"+1 856 697 8654",
    "sg:postcode":"08341",
    "sg:province":"NJ",
    "wof:name":"Lady's Choice Hair Salon",
    "wof:placetype":"venue"
},
  "geometry": {"coordinates":[-74.948735,39.515813],"type":"Point"}
}