{
  "type": "Feature",
  "properties": {
    "iso:country":"US",
    "sg:address":"19 S Livingston Ave",
    "sg:city":"Livingston",
    "sg:classifiers":[
        {
            "category":"Recreation",
            "type":"Entertainment"
        }
    ],
    "sg:phone":"+1 973 535 9642",
    "sg:postcode":"07039",
    "sg:province":"NJ",
    "sg:tags":[
        "instruction",
        "yoga"
    ],
    "wof:name":"Liv Yoga",
    "wof:placetype":"venue"
},
  "geometry": {"coordinates":[-74.315034,40.794164],"type":"Point"}
}