{
  "type": "Feature",
  "properties": {
    "addr:full":"11 Beech Dr Blackwood NJ 08012",
    "addr:housenumber":"11",
    "addr:postcode":"08012",
    "addr:street":"Beech Dr",
    "iso:country":"US",
    "sg:address":"11 Beech Dr",
    "sg:city":"Blackwood",
    "sg:classifiers":[
        {
            "category":"Retail",
            "subcategory":"Repair Shop",
            "type":"Services"
        }
    ],
    "sg:phone":"+1   ",
    "sg:postcode":"08012",
    "sg:province":"NJ",
    "wof:name":"South Jersey Refinishing",
    "wof:placetype":"venue"
},
  "geometry": {"coordinates":[-75.082178,39.81826],"type":"Point"}
}