{
  "type": "Feature",
  "properties": {
    "iso:country":"US",
    "sg:address":"340 State Rte 10",
    "sg:city":"Randolph",
    "sg:classifiers":[
        {
            "category":"Government",
            "subcategory":"Fire Station",
            "type":"Public Place"
        }
    ],
    "sg:phone":"+1 973 366 6780",
    "sg:postcode":"07869",
    "sg:province":"NJ",
    "sg:tags":[
        "department"
    ],
    "wof:name":"Millbrook Fire Co",
    "wof:placetype":"venue"
},
  "geometry": {"coordinates":[-74.550324,40.868338],"type":"Point"}
}