{
  "type": "Feature",
  "properties": {
    "addr:full":"744 Galloping Hill Rd Roselle Park NJ 07204",
    "addr:housenumber":"744",
    "addr:postcode":"07204",
    "addr:street":"Galloping Hill Rd",
    "iso:country":"US",
    "sg:address":"744 Galloping Hill Rd",
    "sg:city":"Roselle Park",
    "sg:classifiers":[
        {
            "category":"Health Services",
            "subcategory":"Doctor",
            "type":"Services"
        }
    ],
    "sg:phone":"+1 908 245 3500",
    "sg:postcode":"07204",
    "sg:province":"NJ",
    "sg:tags":[
        "dentist"
    ],
    "sg:website":"www.drwagenberg.com",
    "wof:name":"Periodontics & Implants Inc",
    "wof:placetype":"venue"
},
  "geometry": {"coordinates":[-74.257119,40.671506],"type":"Point"}
}