{
  "type": "Feature",
  "properties": {
    "iso:country":"US",
    "sg:address":"125 Main St",
    "sg:city":"Bridgeport",
    "sg:classifiers":[
        {
            "category":"Government",
            "subcategory":"Office",
            "type":"Public Place"
        }
    ],
    "sg:phone":"+1 856 467 9266",
    "sg:postcode":"08014",
    "sg:province":"NJ",
    "sg:tags":[
        "village"
    ],
    "wof:name":"City Recycling",
    "wof:placetype":"venue"
},
  "geometry": {"coordinates":[-75.34146,39.800728],"type":"Point"}
}