{
  "type": "Feature",
  "properties": {
    "iso:country":"US",
    "sg:address":"1009 Warren Pkwy",
    "sg:city":"Teaneck",
    "sg:classifiers":[
        {
            "category":"Building & Trades",
            "subcategory":"Construction",
            "type":"Services"
        }
    ],
    "sg:phone":"+1 201 233 7129",
    "sg:postcode":"07666",
    "sg:province":"NJ",
    "sg:tags":[
        "hanging",
        "contractor"
    ],
    "wof:name":"Moving In Home Restoration",
    "wof:placetype":"venue"
},
  "geometry": {"coordinates":[-73.99994599999999,40.888733],"type":"Point"}
}