{
  "type": "Feature",
  "properties": {
    "addr:full":"65 Passaic Ave Kearny NJ 07032",
    "addr:housenumber":"65",
    "addr:postcode":"07032",
    "addr:street":"Passaic Ave",
    "iso:country":"US",
    "sg:address":"65 Passaic Ave",
    "sg:city":"Kearny",
    "sg:classifiers":[
        {
            "category":"Manufacturing",
            "subcategory":"Tools & Machinery",
            "type":"Manufacturing & Wholesale Goods"
        }
    ],
    "sg:phone":"+1 201 997 1333",
    "sg:postcode":"07032",
    "sg:province":"NJ",
    "sg:tags":[
        "die",
        "maker"
    ],
    "wof:name":"Array Manufacturing Tech",
    "wof:placetype":"venue"
},
  "geometry": {"coordinates":[-74.162774,40.754473],"type":"Point"}
}