{
  "type": "Feature",
  "properties": {
    "iso:country":"US",
    "sg:address":"7 Sipley Rd",
    "sg:city":"Blairstown",
    "sg:classifiers":[
        {
            "category":"Manufacturing",
            "subcategory":"Metals",
            "type":"Manufacturing & Wholesale Goods"
        }
    ],
    "sg:phone":"+1 908 362 5637",
    "sg:postcode":"07825",
    "sg:province":"NJ",
    "sg:tags":[
        "specialty"
    ],
    "wof:name":"Quality Tools Inc",
    "wof:placetype":"venue"
},
  "geometry": {"coordinates":[-75.012788,40.966451],"type":"Point"}
}