{
  "type": "Feature",
  "properties": {
    "iso:country":"US",
    "sg:address":"22 Alta Vista Dr",
    "sg:city":"Princeton",
    "sg:classifiers":[
        {
            "category":"Building & Trades",
            "subcategory":"Construction",
            "type":"Services"
        }
    ],
    "sg:phone":"+1 609 737 4370",
    "sg:postcode":"08540",
    "sg:province":"NJ",
    "sg:tags":[
        "contractor"
    ],
    "wof:name":"Fulper Tile",
    "wof:placetype":"venue"
},
  "geometry": {"coordinates":[-74.738607,40.348889],"type":"Point"}
}