{
  "type": "Feature",
  "properties": {
    "iso:country":"US",
    "sg:address":"829 Newark Ave",
    "sg:city":"Jersey City",
    "sg:classifiers":[
        {
            "category":"Health Services",
            "subcategory":"Doctor",
            "type":"Services"
        }
    ],
    "sg:phone":"+1 201 679 0262",
    "sg:postcode":"07306",
    "sg:province":"NJ",
    "sg:tags":[
        "dentist"
    ],
    "wof:name":"Devang Modi DDS",
    "wof:placetype":"venue"
},
  "geometry": {"coordinates":[-74.066016,40.735593],"type":"Point"}
}