{
  "type": "Feature",
  "properties": {
    "addr:full":"1328 River Ave Lakewood NJ 08701",
    "addr:housenumber":"1328",
    "addr:postcode":"08701",
    "addr:street":"River Ave",
    "iso:country":"US",
    "sg:address":"1328 River Ave",
    "sg:city":"Lakewood",
    "sg:classifiers":[
        {
            "category":"Retail",
            "subcategory":"Repair Shop",
            "type":"Services"
        }
    ],
    "sg:phone":"+1   ",
    "sg:postcode":"08701",
    "sg:province":"NJ",
    "wof:name":"Emergency All Day Locksmith",
    "wof:placetype":"venue"
},
  "geometry": {"coordinates":[-74.221181,40.051901],"type":"Point"}
}