{
  "type": "Feature",
  "properties": {
    "iso:country":"US",
    "sg:address":"502 Salem St",
    "sg:city":"Paramus",
    "sg:classifiers":[
        {
            "category":"Professional",
            "subcategory":"Management & Consulting",
            "type":"Services"
        }
    ],
    "sg:phone":"+1   ",
    "sg:postcode":"07652",
    "sg:province":"NJ",
    "wof:name":"Human Rsourse Consulting Assoc",
    "wof:placetype":"venue"
},
  "geometry": {"coordinates":[-74.04486799999999,40.950002],"type":"Point"}
}