{
  "type": "Feature",
  "properties": {
    "iso:country":"US",
    "sg:address":"28 Ember Ln",
    "sg:city":"Willingboro",
    "sg:classifiers":[
        {
            "category":"Professional",
            "subcategory":"Computer Services",
            "type":"Services"
        }
    ],
    "sg:phone":"+1 609 835 4800",
    "sg:postcode":"08046",
    "sg:province":"NJ",
    "sg:tags":[
        "designer",
        "consultant",
        "telephone",
        "custom",
        "communications",
        "programing"
    ],
    "wof:name":"Odyssey Computer Service Corp",
    "wof:placetype":"venue"
},
  "geometry": {"coordinates":[-74.866094,40.017495],"type":"Point"}
}