{
  "type": "Feature",
  "properties": {
    "addr:full":"361 Market St Perth Amboy NJ 08861",
    "addr:housenumber":"361",
    "addr:postcode":"08861",
    "addr:street":"Market St",
    "iso:country":"US",
    "sg:address":"361 Market St",
    "sg:city":"Perth Amboy",
    "sg:classifiers":[
        {
            "category":"Building & Trades",
            "subcategory":"Locksmith",
            "type":"Services"
        }
    ],
    "sg:phone":"+1 888 277 5130",
    "sg:postcode":"08861",
    "sg:province":"NJ",
    "sg:tags":[
        "key"
    ],
    "wof:name":"AAA Emergency Locksmith",
    "wof:placetype":"venue"
},
  "geometry": {"coordinates":[-74.27930000000001,40.50984],"type":"Point"}
}