{
  "type": "Feature",
  "properties": {
    "addr:full":"10 Lorraine Rd Madison NJ 07940",
    "addr:housenumber":"10",
    "addr:postcode":"07940",
    "addr:street":"Lorraine Rd",
    "iso:country":"US",
    "sg:address":"10 Lorraine Rd",
    "sg:city":"Madison",
    "sg:classifiers":[
        {
            "category":"Recreation",
            "type":"Entertainment"
        }
    ],
    "sg:phone":"+1   ",
    "sg:postcode":"07940",
    "sg:province":"NJ",
    "sg:tags":[
        "consulting",
        "management"
    ],
    "wof:name":"Precision Fitness",
    "wof:placetype":"venue"
},
  "geometry": {"coordinates":[-74.403226,40.769543],"type":"Point"}
}