{
  "type": "Feature",
  "properties": {
    "iso:country":"US",
    "sg:address":"490 Brookside Ln",
    "sg:city":"Hillsborough",
    "sg:classifiers":[
        {
            "category":"Freight",
            "type":"Transportation"
        }
    ],
    "sg:phone":"+1 908 281 4000",
    "sg:postcode":"08844",
    "sg:province":"NJ",
    "sg:tags":[
        "trucking"
    ],
    "wof:name":"Joy Transport",
    "wof:placetype":"venue"
},
  "geometry": {"coordinates":[-74.634415,40.51368],"type":"Point"}
}