{
  "type": "Feature",
  "properties": {
    "iso:country":"US",
    "sg:address":"711 Clinton St",
    "sg:city":"Hoboken",
    "sg:classifiers":[
        {
            "category":"Professional",
            "type":"Services"
        }
    ],
    "sg:phone":"+1   ",
    "sg:postcode":"07030",
    "sg:province":"NJ",
    "wof:name":"Cardonet Inc",
    "wof:placetype":"venue"
},
  "geometry": {"coordinates":[-74.032786,40.746645],"type":"Point"}
}