{
  "type": "Feature",
  "properties": {
    "addr:full":"22 Green Meadow Dr Eatontown NJ 07724",
    "addr:housenumber":"22",
    "addr:postcode":"07724",
    "addr:street":"Green Meadow Dr",
    "iso:country":"US",
    "sg:address":"22 Green Meadow Dr",
    "sg:city":"Eatontown",
    "sg:classifiers":[
        {
            "category":"Banks & Credit Unions",
            "subcategory":"Bank",
            "type":"Services"
        }
    ],
    "sg:phone":"+1   ",
    "sg:postcode":"07724",
    "sg:province":"NJ",
    "sg:tags":[
        "foreign"
    ],
    "wof:name":"App International Inc",
    "wof:placetype":"venue"
},
  "geometry": {"coordinates":[-74.08396999999999,40.326232],"type":"Point"}
}