{
  "type": "Feature",
  "properties": {
    "iso:country":"US",
    "sg:address":"258 Montgomery St",
    "sg:city":"Bloomfield",
    "sg:classifiers":[
        {
            "category":"Food & Beverages",
            "subcategory":"Groceries & Convenience Stores",
            "type":"Retail Goods"
        },
        {
            "category":"Restaurant",
            "type":"Food & Drink"
        }
    ],
    "sg:phone":"+1 973 748 2355",
    "sg:postcode":"07003",
    "sg:province":"NJ",
    "sg:tags":[
        "delicatessen"
    ],
    "wof:name":"Gaetanina's Deli",
    "wof:placetype":"venue"
},
  "geometry": {"coordinates":[-74.19196700000001,40.792271],"type":"Point"}
}