{
  "type": "Feature",
  "properties": {
    "iso:country":"US",
    "sg:address":"1 Delmore Rd",
    "sg:city":"Freehold",
    "sg:classifiers":[
        {
            "category":"Professional",
            "subcategory":"Advertising",
            "type":"Services"
        }
    ],
    "sg:phone":"+1 732 863 1553",
    "sg:postcode":"07728",
    "sg:province":"NJ",
    "sg:tags":[
        "agency"
    ],
    "wof:name":"Jolis Creative LLC",
    "wof:placetype":"venue"
},
  "geometry": {"coordinates":[-74.223652,40.205985],"type":"Point"}
}