{
  "type": "Feature",
  "properties": {
    "addr:full":"30 Park St Wanaque NJ 07465",
    "addr:housenumber":"30",
    "addr:postcode":"07465",
    "addr:street":"Park St",
    "iso:country":"US",
    "sg:address":"30 Park St",
    "sg:city":"Wanaque",
    "sg:classifiers":[
        {
            "category":"Professional",
            "subcategory":"Engineering",
            "type":"Services"
        },
        {
            "category":"Professional",
            "subcategory":"Management & Consulting",
            "type":"Services"
        }
    ],
    "sg:phone":"+1 973 616 6331",
    "sg:postcode":"07465",
    "sg:province":"NJ",
    "sg:tags":[
        "accounting",
        "consultant",
        "related",
        "business",
        "research"
    ],
    "wof:name":"Minds Concepts & Solutions LLC",
    "wof:placetype":"venue"
},
  "geometry": {"coordinates":[-74.283923,41.052923],"type":"Point"}
}