{
  "type": "Feature",
  "properties": {
    "iso:country":"US",
    "sg:address":"103 Cliff St",
    "sg:city":"Haledon",
    "sg:classifiers":[
        {
            "category":"Personal",
            "type":"Services"
        }
    ],
    "sg:phone":"+1   ",
    "sg:postcode":"07508",
    "sg:province":"NJ",
    "sg:tags":[
        "pet",
        "sitting"
    ],
    "wof:name":"Pick of Litter Sitters",
    "wof:placetype":"venue"
},
  "geometry": {"coordinates":[-74.187394,40.928952],"type":"Point"}
}