{
  "type": "Feature",
  "properties": {
    "iso:country":"US",
    "sg:address":"134 Boonton Rd",
    "sg:city":"Wayne",
    "sg:classifiers":[
        {
            "category":"Personal",
            "subcategory":"Beauty Salon",
            "type":"Services"
        }
    ],
    "sg:phone":"+1 973 305 0989",
    "sg:postcode":"07470",
    "sg:province":"NJ",
    "sg:tags":[
        "shop",
        "manicuring"
    ],
    "wof:name":"Nails For You",
    "wof:placetype":"venue"
},
  "geometry": {"coordinates":[-74.26606,40.914988],"type":"Point"}
}