{
  "type": "Feature",
  "properties": {
    "addr:full":"224 New Jersey Ave Fortescue NJ 08321",
    "addr:housenumber":"224",
    "addr:postcode":"08321",
    "addr:street":"New Jersey Ave",
    "iso:country":"US",
    "sg:address":"224 New Jersey Ave",
    "sg:city":"Fortescue",
    "sg:classifiers":[
        {
            "category":"Restaurant",
            "type":"Food & Drink"
        }
    ],
    "sg:phone":"+1 856 447 4928",
    "sg:postcode":"08321",
    "sg:province":"NJ",
    "wof:name":"Charlesworth Hotel",
    "wof:placetype":"venue"
},
  "geometry": {"coordinates":[-75.172562,39.238924],"type":"Point"}
}