{
  "type": "Feature",
  "properties": {
    "iso:country":"US",
    "sg:address":"25 Bogert Pl",
    "sg:city":"Westwood",
    "sg:classifiers":[
        {
            "category":"Building & Trades",
            "subcategory":"Construction",
            "type":"Services"
        }
    ],
    "sg:phone":"+1 201 664 4023",
    "sg:postcode":"07675",
    "sg:province":"NJ",
    "sg:tags":[
        "general",
        "contractor"
    ],
    "wof:name":"Jan P Building Contractor",
    "wof:placetype":"venue"
},
  "geometry": {"coordinates":[-74.025717,40.993446],"type":"Point"}
}