{
  "type": "Feature",
  "properties": {
    "addr:full":"24 Gales Dr Apt 4 New Providence NJ 07974",
    "addr:housenumber":"24;4",
    "addr:postcode":"07974",
    "addr:street":"Gales Dr Apt",
    "iso:country":"US",
    "sg:address":"24 Gales Dr Apt 4",
    "sg:city":"New Providence",
    "sg:classifiers":[
        {
            "category":"Autos & Motor Vehicles",
            "subcategory":"Automobile Sales",
            "type":"Retail Goods"
        },
        {
            "category":"Taxi",
            "type":"Transportation"
        }
    ],
    "sg:phone":"+1 908 464 2227",
    "sg:postcode":"07974",
    "sg:province":"NJ",
    "sg:tags":[
        "limo"
    ],
    "wof:name":"New Providence Car & Limousine",
    "wof:placetype":"venue"
},
  "geometry": {"coordinates":[-74.40303299999999,40.70627],"type":"Point"}
}