{
  "type": "Feature",
  "properties": {
    "addr:full":"617 Brooklyn Blvd Sea Girt NJ 08750",
    "addr:housenumber":"617",
    "addr:postcode":"08750",
    "addr:street":"Brooklyn Blvd",
    "iso:country":"US",
    "sg:address":"617 Brooklyn Blvd",
    "sg:city":"Sea Girt",
    "sg:classifiers":[
        {
            "category":"Freight",
            "type":"Transportation"
        }
    ],
    "sg:phone":"+1 732 449 4161",
    "sg:postcode":"08750",
    "sg:province":"NJ",
    "sg:tags":[
        "operator",
        "trucking"
    ],
    "wof:name":"Shore Shipping Inc",
    "wof:placetype":"venue"
},
  "geometry": {"coordinates":[-74.04219399999999,40.136593],"type":"Point"}
}