{
  "type": "Feature",
  "properties": {
    "addr:full":"35 Broad St Keyport NJ 07735",
    "addr:housenumber":"35",
    "addr:postcode":"07735",
    "addr:street":"Broad St",
    "iso:country":"US",
    "sg:address":"35 Broad St",
    "sg:city":"Keyport",
    "sg:classifiers":[
        {
            "category":"Social Services",
            "subcategory":"Adult Care",
            "type":"Services"
        }
    ],
    "sg:phone":"+1 732 888 4149",
    "sg:postcode":"07735",
    "sg:province":"NJ",
    "sg:tags":[
        "residential"
    ],
    "wof:name":"Vna Keyport Primary Care Ctr",
    "wof:placetype":"venue"
},
  "geometry": {"coordinates":[-74.20211999999999,40.438232],"type":"Point"}
}