{
  "type": "Feature",
  "properties": {
    "iso:country":"US",
    "sg:address":"45 Walsingham Rd",
    "sg:city":"Mendham",
    "sg:classifiers":[
        {
            "category":"Professional",
            "subcategory":"Business Services",
            "type":"Services"
        }
    ],
    "sg:phone":"+1   ",
    "sg:postcode":"07945",
    "sg:province":"NJ",
    "wof:name":"Robin Brown Interiors",
    "wof:placetype":"venue"
},
  "geometry": {"coordinates":[-74.580291,40.780008],"type":"Point"}
}