{
  "type": "Feature",
  "properties": {
    "addr:full":"111 Kero Rd Carlstadt NJ 07072",
    "addr:housenumber":"111",
    "addr:postcode":"07072",
    "addr:street":"Kero Rd",
    "iso:country":"US",
    "sg:address":"111 Kero Rd",
    "sg:city":"Carlstadt",
    "sg:classifiers":[
        {
            "category":"Manufacturing",
            "subcategory":"Metals",
            "type":"Manufacturing & Wholesale Goods"
        }
    ],
    "sg:phone":"+1 201 438 6606",
    "sg:postcode":"07072",
    "sg:province":"NJ",
    "wof:name":"USA Industries",
    "wof:placetype":"venue"
},
  "geometry": {"coordinates":[-74.05941900000001,40.828295],"type":"Point"}
}