{
  "type": "Feature",
  "properties": {
    "addr:full":"85 Newfield Ave Edison NJ 08837",
    "addr:housenumber":"85",
    "addr:postcode":"08837",
    "addr:street":"Newfield Ave",
    "iso:country":"US",
    "sg:address":"85 Newfield Ave",
    "sg:city":"Edison",
    "sg:classifiers":[
        {
            "category":"Shopping",
            "subcategory":"Beauty & Cosmetics",
            "type":"Retail Goods"
        }
    ],
    "sg:phone":"+1   ",
    "sg:postcode":"08837",
    "sg:province":"NJ",
    "sg:tags":[
        "merchandise"
    ],
    "wof:name":"Majestic Perfume",
    "wof:placetype":"venue"
},
  "geometry": {"coordinates":[-74.345793,40.502861],"type":"Point"}
}