{
  "type": "Feature",
  "properties": {
    "addr:full":"52 Cayuga Way Short Hills NJ 07078",
    "addr:housenumber":"52",
    "addr:postcode":"07078",
    "addr:street":"Cayuga Way",
    "iso:country":"US",
    "sg:address":"52 Cayuga Way",
    "sg:city":"Short Hills",
    "sg:classifiers":[
        {
            "category":"Sports & Exercise",
            "subcategory":"Gym",
            "type":"Entertainment"
        }
    ],
    "sg:phone":"+1   ",
    "sg:postcode":"07078",
    "sg:province":"NJ",
    "sg:tags":[
        "fitness",
        "physical",
        "facility"
    ],
    "wof:name":"Fitness For You",
    "wof:placetype":"venue"
},
  "geometry": {"coordinates":[-74.329705,40.745324],"type":"Point"}
}