{
  "type": "Feature",
  "properties": {
    "addr:full":"24 Richboynton Rd Dover NJ 07801",
    "addr:housenumber":"24",
    "addr:postcode":"07801",
    "addr:street":"Richboynton Rd",
    "iso:country":"US",
    "sg:address":"24 Richboynton Rd",
    "sg:city":"Dover",
    "sg:classifiers":[
        {
            "category":"Manufacturing",
            "subcategory":"Rubber & Plastics",
            "type":"Manufacturing & Wholesale Goods"
        }
    ],
    "sg:phone":"+1 973 361 5000",
    "sg:postcode":"07801",
    "sg:province":"NJ",
    "sg:tags":[
        "product",
        "laminated",
        "mfg"
    ],
    "wof:name":"Andy Plastic Molding Corp",
    "wof:placetype":"venue"
},
  "geometry": {"coordinates":[-74.56786,40.894398],"type":"Point"}
}