{
  "type": "Feature",
  "properties": {
    "addr:full":"345 Chapel Heights Rd Sewell NJ 08080",
    "addr:housenumber":"345",
    "addr:postcode":"08080",
    "addr:street":"Chapel Heights Rd",
    "iso:country":"US",
    "sg:address":"345 Chapel Heights Rd",
    "sg:city":"Sewell",
    "sg:classifiers":[
        {
            "category":"Manufacturing",
            "subcategory":"Metals",
            "type":"Manufacturing & Wholesale Goods"
        }
    ],
    "sg:phone":"+1 856 589 3821",
    "sg:postcode":"08080",
    "sg:province":"NJ",
    "sg:tags":[
        "fabrication",
        "structural"
    ],
    "wof:name":"Paone Fabrication Inc",
    "wof:placetype":"venue"
},
  "geometry": {"coordinates":[-75.093294,39.736355],"type":"Point"}
}