{
  "type": "Feature",
  "properties": {
    "iso:country":"US",
    "sg:address":"40 S 5th St",
    "sg:city":"Elizabeth",
    "sg:classifiers":[
        {
            "category":"Food & Beverages",
            "subcategory":"Groceries & Convenience Stores",
            "type":"Retail Goods"
        }
    ],
    "sg:phone":"+1   ",
    "sg:postcode":"07206",
    "sg:province":"NJ",
    "wof:name":"One Stop Shop",
    "wof:placetype":"venue"
},
  "geometry": {"coordinates":[-74.20052800000001,40.652968],"type":"Point"}
}