{
  "type": "Feature",
  "properties": {
    "iso:country":"US",
    "sg:address":"319 Hackensack St",
    "sg:city":"Carlstadt",
    "sg:classifiers":[
        {
            "category":"Restaurant",
            "type":"Food & Drink"
        }
    ],
    "sg:phone":"+1   ",
    "sg:postcode":"07072",
    "sg:province":"NJ",
    "sg:tags":[
        "eating"
    ],
    "wof:name":"Cafe Fienze Restaurante",
    "wof:placetype":"venue"
},
  "geometry": {"coordinates":[-74.09262699999999,40.835679],"type":"Point"}
}