{
  "type": "Feature",
  "properties": {
    "addr:full":"10 Cherokee Trl Burlington NJ 08016",
    "addr:housenumber":"10",
    "addr:postcode":"08016",
    "addr:street":"Cherokee Trl",
    "iso:country":"US",
    "sg:address":"10 Cherokee Trl",
    "sg:city":"Burlington",
    "sg:classifiers":[
        {
            "category":"Professional",
            "subcategory":"Computer Services",
            "type":"Services"
        }
    ],
    "sg:phone":"+1 917 669 9626",
    "sg:postcode":"08016",
    "sg:province":"NJ",
    "sg:tags":[
        "consultation"
    ],
    "wof:name":"Think Tank Unlimited Corp",
    "wof:placetype":"venue"
},
  "geometry": {"coordinates":[-74.80573800000001,40.078859],"type":"Point"}
}