{
  "type": "Feature",
  "properties": {
    "iso:country":"US",
    "sg:address":"2344 Tremont Ave",
    "sg:city":"Atco",
    "sg:classifiers":[
        {
            "category":"Wholesale",
            "subcategory":"Non-durable Goods",
            "type":"Manufacturing & Wholesale Goods"
        }
    ],
    "sg:phone":"+1 856 767 4520",
    "sg:postcode":"08004",
    "sg:province":"NJ",
    "wof:name":"M&M Candle Distributors LLC",
    "wof:placetype":"venue"
},
  "geometry": {"coordinates":[-74.833416,39.768172],"type":"Point"}
}