{
  "type": "Feature",
  "properties": {
    "addr:full":"400 New Market Rd Dunellen NJ 08812",
    "addr:housenumber":"400",
    "addr:postcode":"08812",
    "addr:street":"New Market Rd",
    "iso:country":"US",
    "sg:address":"400 New Market Rd",
    "sg:city":"Dunellen",
    "sg:classifiers":[
        {
            "category":"Organizations",
            "subcategory":"Religious Organization",
            "type":"Services"
        }
    ],
    "sg:phone":"+1 732 968 6781",
    "sg:postcode":"08812",
    "sg:province":"NJ",
    "sg:tags":[
        "church"
    ],
    "wof:name":"Saint Francis Episcopal Church",
    "wof:placetype":"venue"
},
  "geometry": {"coordinates":[-74.459706,40.581556],"type":"Point"}
}