{
  "type": "Feature",
  "properties": {
    "iso:country":"US",
    "sg:address":"30 Tara Ln",
    "sg:city":"Barnegat",
    "sg:classifiers":[
        {
            "category":"Building & Trades",
            "subcategory":"Construction",
            "type":"Services"
        }
    ],
    "sg:phone":"+1 609 698 2650",
    "sg:postcode":"08005",
    "sg:province":"NJ",
    "sg:tags":[
        "house"
    ],
    "wof:name":"Acn Construction",
    "wof:placetype":"venue"
},
  "geometry": {"coordinates":[-74.252517,39.746215],"type":"Point"}
}