{
  "type": "Feature",
  "properties": {
    "addr:full":"4 Windsor Ln Newton NJ 07821",
    "addr:housenumber":"4",
    "addr:postcode":"07821",
    "addr:street":"Windsor Ln",
    "iso:country":"US",
    "sg:address":"4 Windsor Ln",
    "sg:city":"Newton",
    "sg:classifiers":[
        {
            "category":"Building & Trades",
            "subcategory":"Cleaning & Sanitation",
            "type":"Services"
        }
    ],
    "sg:phone":"+1 973 383 3439",
    "sg:postcode":"07821",
    "sg:province":"NJ",
    "sg:tags":[
        "window"
    ],
    "wof:name":"All Seasons Window Cleaning Co",
    "wof:placetype":"venue"
},
  "geometry": {"coordinates":[-74.676249,40.977549],"type":"Point"}
}