{
  "type": "Feature",
  "properties": {
    "addr:full":"36 Park Ave Rutherford NJ 07070",
    "addr:housenumber":"36",
    "addr:postcode":"07070",
    "addr:street":"Park Ave",
    "iso:country":"US",
    "sg:address":"36 Park Ave",
    "sg:city":"Rutherford",
    "sg:classifiers":[
        {
            "category":"Food & Beverages",
            "subcategory":"Bakery",
            "type":"Retail Goods"
        }
    ],
    "sg:phone":"+1 201 635 1110",
    "sg:postcode":"07070",
    "sg:province":"NJ",
    "sg:tags":[
        "baker"
    ],
    "wof:name":"Sinsatong Restaurants",
    "wof:placetype":"venue"
},
  "geometry": {"coordinates":[-74.10265200000001,40.82811],"type":"Point"}
}