{
  "type": "Feature",
  "properties": {
    "iso:country":"US",
    "sg:address":"123 Briscoe Dr",
    "sg:city":"Toms River",
    "sg:classifiers":[
        {
            "category":"Building & Trades",
            "subcategory":"Construction",
            "type":"Services"
        }
    ],
    "sg:phone":"+1 732 288 0727",
    "sg:postcode":"08753",
    "sg:province":"NJ",
    "sg:tags":[
        "contractor"
    ],
    "wof:name":"Safe T Site LLC",
    "wof:placetype":"venue"
},
  "geometry": {"coordinates":[-74.13956399999999,39.986473],"type":"Point"}
}