{
  "type": "Feature",
  "properties": {
    "addr:full":"8728 Kennedy Blvd North Bergen NJ 07047",
    "addr:housenumber":"8728",
    "addr:postcode":"07047",
    "addr:street":"Kennedy Blvd",
    "iso:country":"US",
    "sg:address":"8728 Kennedy Blvd",
    "sg:city":"North Bergen",
    "sg:classifiers":[
        {
            "category":"Restaurant",
            "type":"Food & Drink"
        }
    ],
    "sg:phone":"+1 201 868 3005",
    "sg:postcode":"07047",
    "sg:province":"NJ",
    "sg:tags":[
        "italian"
    ],
    "sg:website":"www.dorienne.com/DiPalma/Menus.htm",
    "wof:name":"Di Palma Brothers Restaurant",
    "wof:placetype":"venue"
},
  "geometry": {"coordinates":[-74.007615,40.809148],"type":"Point"}
}