{
  "type": "Feature",
  "properties": {
    "addr:full":"6 Keewadin Ave Hopatcong NJ 07843",
    "addr:housenumber":"6",
    "addr:postcode":"07843",
    "addr:street":"Keewadin Ave",
    "iso:country":"US",
    "sg:address":"6 Keewadin Ave",
    "sg:city":"Hopatcong",
    "sg:classifiers":[
        {
            "category":"Retail",
            "subcategory":"Animal Services",
            "type":"Services"
        }
    ],
    "sg:phone":"+1 973 398 0329",
    "sg:postcode":"07843",
    "sg:province":"NJ",
    "wof:name":"Dogs By Dan",
    "wof:placetype":"venue"
},
  "geometry": {"coordinates":[-74.662526,40.930906],"type":"Point"}
}