{
  "type": "Feature",
  "properties": {
    "iso:country":"US",
    "sg:address":"231 4th Ave",
    "sg:city":"Mount Ephraim",
    "sg:classifiers":[
        {
            "category":"Professional",
            "type":"Services"
        }
    ],
    "sg:phone":"+1   ",
    "sg:postcode":"08059",
    "sg:province":"NJ",
    "wof:name":"Susan Eggert",
    "wof:placetype":"venue"
},
  "geometry": {"coordinates":[-75.093485,39.885491],"type":"Point"}
}