{
  "type": "Feature",
  "properties": {
    "addr:full":"9 Livingston Ave New Brunswick NJ 08901",
    "addr:housenumber":"9",
    "addr:postcode":"08901",
    "addr:street":"Livingston Ave",
    "iso:country":"US",
    "sg:address":"9 Livingston Ave",
    "sg:city":"New Brunswick",
    "sg:classifiers":[
        {
            "category":"Organizations",
            "subcategory":"Non-profit Organization",
            "type":"Services"
        },
        {
            "category":"Arts & Performance",
            "subcategory":"Theater",
            "type":"Entertainment"
        }
    ],
    "sg:phone":"+1 732 846 2895",
    "sg:postcode":"08901",
    "sg:province":"NJ",
    "sg:tags":[
        "theatrical"
    ],
    "wof:name":"George Street Playhouse Inc",
    "wof:placetype":"venue"
},
  "geometry": {"coordinates":[-74.443619,40.494063],"type":"Point"}
}