{
  "type": "Feature",
  "properties": {
    "addr:full":"20 Nassau St Princeton NJ 08542",
    "addr:housenumber":"20",
    "addr:postcode":"08542",
    "addr:street":"Nassau St",
    "iso:country":"US",
    "sg:address":"20 Nassau St",
    "sg:city":"Princeton",
    "sg:classifiers":[
        {
            "category":"Professional",
            "subcategory":"Engineering",
            "type":"Services"
        }
    ],
    "sg:phone":"+1 609 921 2410",
    "sg:postcode":"08542",
    "sg:province":"NJ",
    "sg:tags":[
        "engineer"
    ],
    "wof:name":"Le Massena Robert F & Assoc",
    "wof:placetype":"venue"
},
  "geometry": {"coordinates":[-74.6627,40.348906],"type":"Point"}
}