{
  "type": "Feature",
  "properties": {
    "iso:country":"US",
    "sg:address":"239 Hearth Ct",
    "sg:city":"Lakewood",
    "sg:classifiers":[
        {
            "category":"Building & Trades",
            "subcategory":"Plumbing",
            "type":"Services"
        }
    ],
    "sg:phone":"+1 732 370 5959",
    "sg:postcode":"08701",
    "sg:province":"NJ",
    "sg:tags":[
        "contractor"
    ],
    "wof:name":"Superior AC & Htg",
    "wof:placetype":"venue"
},
  "geometry": {"coordinates":[-74.231335,40.081267],"type":"Point"}
}