{
  "type": "Feature",
  "properties": {
    "addr:full":"897 Aura Rd Glassboro NJ 08028",
    "addr:housenumber":"897",
    "addr:postcode":"08028",
    "addr:street":"Aura Rd",
    "iso:country":"US",
    "sg:address":"897 Aura Rd",
    "sg:city":"Glassboro",
    "sg:classifiers":[
        {
            "category":"Building & Trades",
            "subcategory":"Construction",
            "type":"Services"
        }
    ],
    "sg:phone":"+1 856 694 0236",
    "sg:postcode":"08028",
    "sg:province":"NJ",
    "sg:tags":[
        "excavating",
        "contractor"
    ],
    "wof:name":"Allivine & Raines Septic Svc",
    "wof:placetype":"venue"
},
  "geometry": {"coordinates":[-75.13968300000001,39.677598],"type":"Point"}
}