{
  "type": "Feature",
  "properties": {
    "iso:country":"US",
    "sg:address":"531 Union Mill Rd",
    "sg:city":"Mount Laurel",
    "sg:classifiers":[
        {
            "category":"Professional",
            "subcategory":"Art Services",
            "type":"Services"
        }
    ],
    "sg:phone":"+1   ",
    "sg:postcode":"08054",
    "sg:province":"NJ",
    "sg:tags":[
        "commercial",
        "design"
    ],
    "wof:name":"Morrow Design Group",
    "wof:placetype":"venue"
},
  "geometry": {"coordinates":[-74.896997,39.957287],"type":"Point"}
}