{
  "type": "Feature",
  "properties": {
    "iso:country":"US",
    "sg:address":"88 Cannonball Rd",
    "sg:city":"Pompton Lakes",
    "sg:classifiers":[
        {
            "category":"Retail",
            "subcategory":"Repair Shop",
            "type":"Services"
        }
    ],
    "sg:phone":"+1 973 839 8877",
    "sg:postcode":"07442",
    "sg:province":"NJ",
    "sg:tags":[
        "welding"
    ],
    "wof:name":"ATW",
    "wof:placetype":"venue"
},
  "geometry": {"coordinates":[-74.29141799999999,41.006674],"type":"Point"}
}