{
  "type": "Feature",
  "properties": {
    "addr:full":"427 E Pine St Lawnside NJ 08045",
    "addr:housenumber":"427",
    "addr:postcode":"08045",
    "addr:street":"E Pine St",
    "iso:country":"US",
    "sg:address":"427 E Pine St",
    "sg:city":"Lawnside",
    "sg:classifiers":[
        {
            "category":"Organizations",
            "subcategory":"Religious Organization",
            "type":"Services"
        }
    ],
    "sg:phone":"+1   ",
    "sg:postcode":"08045",
    "sg:province":"NJ",
    "wof:name":"Valley Bb Word Fith Chrch Schl",
    "wof:placetype":"venue"
},
  "geometry": {"coordinates":[-75.017015,39.860411],"type":"Point"}
}