{
  "type": "Feature",
  "properties": {
    "addr:full":"133 Crown Point Rd Westville NJ 08093",
    "addr:housenumber":"133",
    "addr:postcode":"08093",
    "addr:street":"Crown Point Rd",
    "iso:country":"US",
    "sg:address":"133 Crown Point Rd",
    "sg:city":"Westville",
    "sg:classifiers":[
        {
            "category":"Building & Trades",
            "subcategory":"Construction",
            "type":"Services"
        }
    ],
    "sg:phone":"+1 856 456 0421",
    "sg:postcode":"08093",
    "sg:province":"NJ",
    "sg:tags":[
        "painter"
    ],
    "wof:name":"Miller Painting Inc",
    "wof:placetype":"venue"
},
  "geometry": {"coordinates":[-75.126701,39.871899],"type":"Point"}
}