{
  "type": "Feature",
  "properties": {
    "iso:country":"US",
    "sg:address":"28 Stony Hill Dr",
    "sg:city":"Morganville",
    "sg:classifiers":[
        {
            "category":"Professional",
            "subcategory":"Management & Consulting",
            "type":"Services"
        }
    ],
    "sg:phone":"+1   ",
    "sg:postcode":"07751",
    "sg:province":"NJ",
    "sg:tags":[
        "business"
    ],
    "wof:name":"21st Century Consultants Inc",
    "wof:placetype":"venue"
},
  "geometry": {"coordinates":[-74.269677,40.34089],"type":"Point"}
}