{
  "type": "Feature",
  "properties": {
    "iso:country":"US",
    "sg:address":"543 Main St",
    "sg:city":"Fort Lee",
    "sg:classifiers":[
        {
            "category":"Retail",
            "subcategory":"Auto Repair",
            "type":"Services"
        }
    ],
    "sg:phone":"+1 201 461 9733",
    "sg:postcode":"07024",
    "sg:province":"NJ",
    "sg:tags":[
        "repairing",
        "automobile"
    ],
    "wof:name":"Cliff Auto Repairs",
    "wof:placetype":"venue"
},
  "geometry": {"coordinates":[-73.9776,40.85543],"type":"Point"}
}