{
  "type": "Feature",
  "properties": {
    "iso:country":"US",
    "sg:address":"7 Melanie Ln",
    "sg:city":"East Hanover",
    "sg:classifiers":[
        {
            "category":"Retail",
            "subcategory":"Auto Repair",
            "type":"Services"
        }
    ],
    "sg:phone":"+1 973 887 0230",
    "sg:postcode":"07936",
    "sg:province":"NJ",
    "wof:name":"Walter Mueller Repairing",
    "wof:placetype":"venue"
},
  "geometry": {"coordinates":[-74.387001,40.815201],"type":"Point"}
}