{
  "type": "Feature",
  "properties": {
    "iso:country":"US",
    "sg:address":"295 N Main St",
    "sg:city":"Lambertville",
    "sg:classifiers":[
        {
            "category":"Real Estate",
            "subcategory":"Real Estate Operator",
            "type":"Services"
        }
    ],
    "sg:phone":"+1 609 397 3509",
    "sg:postcode":"08530",
    "sg:province":"NJ",
    "sg:tags":[
        "building",
        "apartment"
    ],
    "wof:name":"Lambertville Village Apts",
    "wof:placetype":"venue"
},
  "geometry": {"coordinates":[-74.94566399999999,40.375373],"type":"Point"}
}