{
  "type": "Feature",
  "properties": {
    "iso:country":"US",
    "sg:address":"2113 Hidden Brook Dr",
    "sg:city":"Belmar",
    "sg:classifiers":[
        {
            "category":"Health Services",
            "subcategory":"Doctor",
            "type":"Services"
        }
    ],
    "sg:phone":"+1   ",
    "sg:postcode":"07719",
    "sg:province":"NJ",
    "sg:tags":[
        "medical"
    ],
    "wof:name":"Kul B Sethi MD",
    "wof:placetype":"venue"
},
  "geometry": {"coordinates":[-74.07779499999999,40.141707],"type":"Point"}
}