{
  "type": "Feature",
  "properties": {
    "iso:country":"US",
    "sg:address":"34 Torrington Dr",
    "sg:city":"Sicklerville",
    "sg:classifiers":[
        {
            "category":"Building & Trades",
            "subcategory":"Construction",
            "type":"Services"
        }
    ],
    "sg:phone":"+1 856 783 8389",
    "sg:postcode":"08081",
    "sg:province":"NJ",
    "sg:tags":[
        "hanging",
        "contractor"
    ],
    "wof:name":"Pride Home Decor Painting",
    "wof:placetype":"venue"
},
  "geometry": {"coordinates":[-74.998333,39.775995],"type":"Point"}
}