{
  "type": "Feature",
  "properties": {
    "addr:full":"16 Lincoln Ter Belleville NJ 07109",
    "addr:housenumber":"16",
    "addr:postcode":"07109",
    "addr:street":"Lincoln Ter",
    "iso:country":"US",
    "sg:address":"16 Lincoln Ter",
    "sg:city":"Belleville",
    "sg:classifiers":[
        {
            "category":"Professional",
            "type":"Services"
        }
    ],
    "sg:phone":"+1   ",
    "sg:postcode":"07109",
    "sg:province":"NJ",
    "wof:name":"Fernando Marillo",
    "wof:placetype":"venue"
},
  "geometry": {"coordinates":[-74.154611,40.787192],"type":"Point"}
}