{
  "type": "Feature",
  "properties": {
    "addr:full":"178 Pedricktown Woodstown Rd Pedricktown NJ 08067",
    "addr:housenumber":"178",
    "addr:postcode":"08067",
    "addr:street":"Pedricktown Woodstown Rd",
    "iso:country":"US",
    "sg:address":"178 Pedricktown Woodstown Rd",
    "sg:city":"Pedricktown",
    "sg:phone":"+1 856 299 4043",
    "sg:postcode":"08067",
    "sg:province":"NJ",
    "sg:tags":[
        "farm"
    ],
    "wof:name":"Musumeci Farms",
    "wof:placetype":"venue"
},
  "geometry": {"coordinates":[-75.38197700000001,39.726184],"type":"Point"}
}