{
  "type": "Feature",
  "properties": {
    "addr:full":"124 Cypress Ct Howell NJ 07731",
    "addr:housenumber":"124",
    "addr:postcode":"07731",
    "addr:street":"Cypress Ct",
    "iso:country":"US",
    "sg:address":"124 Cypress Ct",
    "sg:city":"Howell",
    "sg:classifiers":[
        {
            "category":"Utilities",
            "subcategory":"Telephone",
            "type":"Services"
        }
    ],
    "sg:phone":"+1 732 577 1775",
    "sg:postcode":"07731",
    "sg:province":"NJ",
    "sg:tags":[
        "company"
    ],
    "wof:name":"Teltronic Systems Inc",
    "wof:placetype":"venue"
},
  "geometry": {"coordinates":[-74.26136700000001,40.200167],"type":"Point"}
}