{
  "type": "Feature",
  "properties": {
    "addr:full":"114 Algonquin Pkwy Whippany NJ 07981",
    "addr:housenumber":"114",
    "addr:postcode":"07981",
    "addr:street":"Algonquin Pkwy",
    "iso:country":"US",
    "sg:address":"114 Algonquin Pkwy",
    "sg:city":"Whippany",
    "sg:classifiers":[
        {
            "category":"Professional",
            "subcategory":"Business Services",
            "type":"Services"
        },
        {
            "category":"Building & Trades",
            "subcategory":"Construction",
            "type":"Services"
        }
    ],
    "sg:phone":"+1 973 428 9090",
    "sg:postcode":"07981",
    "sg:province":"NJ",
    "sg:tags":[
        "industrial",
        "product",
        "designer",
        "design"
    ],
    "wof:name":"Insync Design Inc",
    "wof:placetype":"venue"
},
  "geometry": {"coordinates":[-74.396917,40.819883],"type":"Point"}
}