{
  "type": "Feature",
  "properties": {
    "iso:country":"US",
    "sg:address":"3701 US Hwy 46",
    "sg:city":"Parsippany",
    "sg:classifiers":[
        {
            "category":"Retail",
            "subcategory":"Auto Repair",
            "type":"Services"
        }
    ],
    "sg:phone":"+1 973 263 0807",
    "sg:postcode":"07054",
    "sg:province":"NJ",
    "sg:tags":[
        "machine",
        "automobile",
        "shop"
    ],
    "wof:name":"Edwin Automotive Engineering",
    "wof:placetype":"venue"
},
  "geometry": {"coordinates":[-74.444107,40.877418],"type":"Point"}
}