{
  "type": "Feature",
  "properties": {
    "iso:country":"US",
    "sg:address":"1429 14th St",
    "sg:city":"Lakewood",
    "sg:classifiers":[
        {
            "category":"Insurance",
            "subcategory":"Insurance Agent",
            "type":"Services"
        }
    ],
    "sg:phone":"+1 732 367 3342",
    "sg:postcode":"08701",
    "sg:province":"NJ",
    "wof:name":"Mordechai Rozsansky",
    "wof:placetype":"venue"
},
  "geometry": {"coordinates":[-74.23667399999999,40.104066],"type":"Point"}
}