{
  "type": "Feature",
  "properties": {
    "iso:country":"US",
    "sg:address":"5 Deer Path",
    "sg:city":"Milford",
    "sg:classifiers":[
        {
            "category":"Professional",
            "subcategory":"Management & Consulting",
            "type":"Services"
        }
    ],
    "sg:phone":"+1   ",
    "sg:postcode":"08848",
    "sg:province":"NJ",
    "wof:name":"Gerald Biuso Sr",
    "wof:placetype":"venue"
},
  "geometry": {"coordinates":[-75.071843,40.592698],"type":"Point"}
}