{
  "type": "Feature",
  "properties": {
    "addr:full":"862 S Broad St Trenton NJ 08611",
    "addr:housenumber":"862",
    "addr:postcode":"08611",
    "addr:street":"S Broad St",
    "iso:country":"US",
    "sg:address":"862 S Broad St",
    "sg:city":"Trenton",
    "sg:classifiers":[
        {
            "category":"Food & Beverages",
            "subcategory":"Groceries & Convenience Stores",
            "type":"Retail Goods"
        }
    ],
    "sg:phone":"+1 609 392 7035",
    "sg:postcode":"08611",
    "sg:province":"NJ",
    "sg:tags":[
        "grocer"
    ],
    "wof:name":"Johnny's Grocery Deli",
    "wof:placetype":"venue"
},
  "geometry": {"coordinates":[-74.750153,40.207185],"type":"Point"}
}