{
  "type": "Feature",
  "properties": {
    "iso:country":"US",
    "sg:address":"709 Kresson Rd",
    "sg:city":"Cherry Hill",
    "sg:classifiers":[
        {
            "category":"Wholesale",
            "subcategory":"Hardware",
            "type":"Manufacturing & Wholesale Goods"
        }
    ],
    "sg:phone":"+1 856 795 5770",
    "sg:postcode":"08003",
    "sg:province":"NJ",
    "wof:name":"Toms Wholesale",
    "wof:placetype":"venue"
},
  "geometry": {"coordinates":[-74.997219,39.88959],"type":"Point"}
}