{
  "type": "Feature",
  "properties": {
    "addr:full":"1 Youngs Dr Flemington NJ 08822",
    "addr:housenumber":"1",
    "addr:postcode":"08822",
    "addr:street":"Youngs Dr",
    "iso:country":"US",
    "sg:address":"1 Youngs Dr",
    "sg:city":"Flemington",
    "sg:classifiers":[
        {
            "category":"Building & Trades",
            "subcategory":"Plumbing",
            "type":"Services"
        }
    ],
    "sg:phone":"+1 908 806 7311",
    "sg:postcode":"08822",
    "sg:province":"NJ",
    "sg:tags":[
        "tank",
        "septic"
    ],
    "wof:name":"Daniel Holzli",
    "wof:placetype":"venue"
},
  "geometry": {"coordinates":[-74.8644,40.515017],"type":"Point"}
}