{
  "type": "Feature",
  "properties": {
    "addr:full":"9 Desoto Ave Villas NJ 08251",
    "addr:housenumber":"9",
    "addr:postcode":"08251",
    "addr:street":"Desoto Ave Villas",
    "iso:country":"US",
    "sg:address":"9 Desoto Ave",
    "sg:city":"Villas",
    "sg:classifiers":[
        {
            "category":"Taxi",
            "type":"Transportation"
        }
    ],
    "sg:phone":"+1 609 889 8799",
    "sg:postcode":"08251",
    "sg:province":"NJ",
    "sg:tags":[
        "taxicab"
    ],
    "wof:name":"Villas Taxi",
    "wof:placetype":"venue"
},
  "geometry": {"coordinates":[-74.933621,39.032084],"type":"Point"}
}