{
  "type": "Feature",
  "properties": {
    "addr:full":"18 Keiller Ct Haledon NJ 07508",
    "addr:housenumber":"18",
    "addr:postcode":"07508",
    "addr:street":"Keiller Ct",
    "iso:country":"US",
    "sg:address":"18 Keiller Ct",
    "sg:city":"Haledon",
    "sg:classifiers":[
        {
            "category":"Professional",
            "subcategory":"Accounting & Tax Preparation",
            "type":"Services"
        }
    ],
    "sg:phone":"+1   ",
    "sg:postcode":"07508",
    "sg:province":"NJ",
    "wof:name":"Robert Rosen CPA",
    "wof:placetype":"venue"
},
  "geometry": {"coordinates":[-74.180212,40.969893],"type":"Point"}
}