{
  "type": "Feature",
  "properties": {
    "addr:full":"83-91 Academy St Between Washington and University Newark NJ 07102",
    "addr:housenumber":"83-91",
    "addr:postcode":"07102",
    "addr:street":"Academy St",
    "iso:country":"US",
    "sg:address":"83-91 Academy St Between Washington and University",
    "sg:city":"Newark",
    "sg:classifiers":[
        {
            "category":"Parking",
            "type":"Transportation"
        }
    ],
    "sg:phone":"+1 973 623 0623",
    "sg:postcode":"07102",
    "sg:province":"NJ",
    "sg:website":"www.parkfast.com",
    "wof:name":"Edison ParkFast",
    "wof:placetype":"venue"
},
  "geometry": {"coordinates":[-74.175201,40.738264],"type":"Point"}
}