{
  "type": "Feature",
  "properties": {
    "iso:country":"US",
    "sg:address":"17 Walnut St",
    "sg:city":"Toms River",
    "sg:classifiers":[
        {
            "category":"Real Estate",
            "subcategory":"Real Estate Operator",
            "type":"Services"
        }
    ],
    "sg:phone":"+1 732 341 6003",
    "sg:postcode":"08753",
    "sg:province":"NJ",
    "sg:tags":[
        "apartment"
    ],
    "wof:name":"Paradise Club Apartments",
    "wof:placetype":"venue"
},
  "geometry": {"coordinates":[-74.200676,39.968313],"type":"Point"}
}