{
  "type": "Feature",
  "properties": {
    "addr:full":"14 Wyndham Rd Voorhees NJ 08043",
    "addr:housenumber":"14",
    "addr:postcode":"08043",
    "addr:street":"Wyndham Rd",
    "iso:country":"US",
    "sg:address":"14 Wyndham Rd",
    "sg:city":"Voorhees",
    "sg:classifiers":[
        {
            "category":"Real Estate",
            "subcategory":"Real Estate Operator",
            "type":"Services"
        }
    ],
    "sg:phone":"+1   ",
    "sg:postcode":"08043",
    "sg:province":"NJ",
    "sg:tags":[
        "property",
        "management"
    ],
    "wof:name":"National Financial Company",
    "wof:placetype":"venue"
},
  "geometry": {"coordinates":[-74.916314,39.82995],"type":"Point"}
}