{
  "type": "Feature",
  "properties": {
    "addr:full":"202 Wood St Rutherford NJ 07070",
    "addr:housenumber":"202",
    "addr:postcode":"07070",
    "addr:street":"Wood St",
    "iso:country":"US",
    "sg:address":"202 Wood St",
    "sg:city":"Rutherford",
    "sg:classifiers":[
        {
            "category":"Retail",
            "subcategory":"Auto Repair",
            "type":"Services"
        }
    ],
    "sg:phone":"+1   ",
    "sg:postcode":"07070",
    "sg:province":"NJ",
    "sg:tags":[
        "truck",
        "trailer"
    ],
    "wof:name":"Associated Auto Body & Trucks",
    "wof:placetype":"venue"
},
  "geometry": {"coordinates":[-74.110466,40.830288],"type":"Point"}
}