{
  "type": "Feature",
  "properties": {
    "addr:full":"272 Hamilton St New Brunswick NJ 08901",
    "addr:housenumber":"272",
    "addr:postcode":"08901",
    "addr:street":"Hamilton St",
    "iso:country":"US",
    "sg:address":"272 Hamilton St",
    "sg:city":"New Brunswick",
    "sg:classifiers":[
        {
            "category":"Real Estate",
            "subcategory":"Real Estate Operator",
            "type":"Services"
        }
    ],
    "sg:phone":"+1 732 828 5607",
    "sg:postcode":"08901",
    "sg:province":"NJ",
    "sg:tags":[
        "building",
        "apartment"
    ],
    "wof:name":"Birchwood Terrace Apartments",
    "wof:placetype":"venue"
},
  "geometry": {"coordinates":[-74.456417,40.496269],"type":"Point"}
}