{
  "type": "Feature",
  "properties": {
    "addr:full":"284 Mantoloking Rd Brick NJ 08723",
    "addr:housenumber":"284",
    "addr:postcode":"08723",
    "addr:street":"Mantoloking Rd",
    "iso:country":"US",
    "sg:address":"284 Mantoloking Rd",
    "sg:city":"Brick",
    "sg:classifiers":[
        {
            "category":"Professional",
            "subcategory":"Business Services",
            "type":"Services"
        }
    ],
    "sg:phone":"+1   ",
    "sg:postcode":"08723",
    "sg:province":"NJ",
    "wof:name":"NJ Legal Process Service Inc",
    "wof:placetype":"venue"
},
  "geometry": {"coordinates":[-74.08101499999999,40.044844],"type":"Point"}
}