{
  "type": "Feature",
  "properties": {
    "addr:full":"1 Palmer Sq W Princeton NJ 08542",
    "addr:housenumber":"1",
    "addr:postcode":"08542",
    "addr:street":"Palmer Sq W",
    "iso:country":"US",
    "sg:address":"1 Palmer Sq W",
    "sg:city":"Princeton",
    "sg:classifiers":[
        {
            "category":"Professional",
            "subcategory":"Lawyer & Legal Services",
            "type":"Services"
        }
    ],
    "sg:phone":"+1 609 924 9622",
    "sg:postcode":"08542",
    "sg:province":"NJ",
    "sg:tags":[
        "attorney"
    ],
    "wof:name":"David S Mulchinock",
    "wof:placetype":"venue"
},
  "geometry": {"coordinates":[-74.66151499999999,40.34983],"type":"Point"}
}