{
  "type": "Feature",
  "properties": {
    "iso:country":"US",
    "sg:address":"400 S Orange Ave",
    "sg:city":"South Orange",
    "sg:classifiers":[
        {
            "category":"Education",
            "subcategory":"College",
            "type":"Public Place"
        }
    ],
    "sg:phone":"+1   ",
    "sg:postcode":"07079",
    "sg:province":"NJ",
    "wof:name":"Educatonal Opportunity Program",
    "wof:placetype":"venue"
},
  "geometry": {"coordinates":[-74.247563,40.744631],"type":"Point"}
}