{
  "type": "Feature",
  "properties": {
    "iso:country":"US",
    "sg:address":"801 US Highway 1 S",
    "sg:city":"Iselin",
    "sg:classifiers":[
        {
            "category":"Building & Trades",
            "subcategory":"Construction",
            "type":"Services"
        }
    ],
    "sg:phone":"+1 732 634 4142",
    "sg:postcode":"08830",
    "sg:province":"NJ",
    "sg:tags":[
        "contractor"
    ],
    "wof:name":"7M's & 4V's Construction Corp",
    "wof:placetype":"venue"
},
  "geometry": {"coordinates":[-74.29879800000001,40.5648],"type":"Point"}
}