{
  "type": "Feature",
  "properties": {
    "iso:country":"US",
    "sg:address":"111 McAdoo Ave",
    "sg:city":"Jersey City",
    "sg:classifiers":[
        {
            "category":"Building & Trades",
            "subcategory":"Locksmith",
            "type":"Services"
        }
    ],
    "sg:phone":"+1 201 253 1976",
    "sg:postcode":"07305",
    "sg:province":"NJ",
    "sg:tags":[
        "key"
    ],
    "wof:name":"Locksmith AAA",
    "wof:placetype":"venue"
},
  "geometry": {"coordinates":[-74.093841,40.70319],"type":"Point"}
}