{
  "type": "Feature",
  "properties": {
    "iso:country":"US",
    "sg:address":"831 Hamilton St",
    "sg:city":"Somerset",
    "sg:classifiers":[
        {
            "category":"Personal",
            "subcategory":"Barber",
            "type":"Services"
        }
    ],
    "sg:phone":"+1   ",
    "sg:postcode":"08873",
    "sg:province":"NJ",
    "sg:tags":[
        "shop"
    ],
    "wof:name":"Franklin Township Barber Shop",
    "wof:placetype":"venue"
},
  "geometry": {"coordinates":[-74.477654,40.489616],"type":"Point"}
}