{
  "type": "Feature",
  "properties": {
    "iso:country":"US",
    "sg:address":"3586 Kennedy Rd",
    "sg:city":"South Plainfield",
    "sg:classifiers":[
        {
            "category":"Wholesale",
            "subcategory":"Photographic Equipment",
            "type":"Manufacturing & Wholesale Goods"
        },
        {
            "category":"Wholesale",
            "subcategory":"Durable Goods & Equipment",
            "type":"Manufacturing & Wholesale Goods"
        }
    ],
    "sg:phone":"+1 908 757 5400",
    "sg:postcode":"07080",
    "sg:province":"NJ",
    "sg:tags":[
        "audio",
        "video"
    ],
    "wof:name":"Custom Audio Video Dstrbtn",
    "wof:placetype":"venue"
},
  "geometry": {"coordinates":[-74.42510799999999,40.568792],"type":"Point"}
}