{
  "type": "Feature",
  "properties": {
    "iso:country":"US",
    "sg:address":"1342 Old Stagecoach Rd",
    "sg:city":"Ocean View",
    "sg:classifiers":[
        {
            "category":"Building & Trades",
            "subcategory":"Construction",
            "type":"Services"
        }
    ],
    "sg:phone":"+1 609 390 1057",
    "sg:postcode":"08230",
    "sg:province":"NJ",
    "sg:tags":[
        "house"
    ],
    "wof:name":"Hand David F Builder",
    "wof:placetype":"venue"
},
  "geometry": {"coordinates":[-74.686424,39.236997],"type":"Point"}
}