{
  "type": "Feature",
  "properties": {
    "addr:full":"609 White Horse Pike Absecon NJ 08201",
    "addr:housenumber":"609",
    "addr:postcode":"08201",
    "addr:street":"White Horse Pike",
    "iso:country":"US",
    "sg:address":"609 White Horse Pike",
    "sg:city":"Absecon",
    "sg:classifiers":[
        {
            "category":"Autos & Motor Vehicles",
            "subcategory":"Automobile Sales",
            "type":"Retail Goods"
        }
    ],
    "sg:phone":"+1 609 965 9200",
    "sg:postcode":"08201",
    "sg:province":"NJ",
    "sg:tags":[
        "truck"
    ],
    "wof:name":"Quality Truck Ctr",
    "wof:placetype":"venue"
},
  "geometry": {"coordinates":[-74.51259400000001,39.432864],"type":"Point"}
}