{
  "type": "Feature",
  "properties": {
    "iso:country":"US",
    "sg:address":"216 N Park Dr",
    "sg:city":"Woodbridge",
    "sg:classifiers":[
        {
            "category":"Health Services",
            "subcategory":"Doctor",
            "type":"Services"
        }
    ],
    "sg:phone":"+1 732 634 8277",
    "sg:postcode":"07095",
    "sg:province":"NJ",
    "sg:tags":[
        "dentist"
    ],
    "wof:name":"Edward E Zullo DDS",
    "wof:placetype":"venue"
},
  "geometry": {"coordinates":[-74.289468,40.555666],"type":"Point"}
}