{
  "type": "Feature",
  "properties": {
    "iso:country":"US",
    "sg:address":"177 N Dean St",
    "sg:city":"Englewood",
    "sg:classifiers":[
        {
            "category":"Health Services",
            "subcategory":"Doctor",
            "type":"Services"
        },
        {
            "category":"Health Services",
            "subcategory":"Medical Lab",
            "type":"Services"
        }
    ],
    "sg:phone":"+1 201 871 1950",
    "sg:postcode":"07631",
    "sg:province":"NJ",
    "sg:tags":[
        "laboratory",
        "ultrasound",
        "imaging",
        "x"
    ],
    "wof:name":"Englewood Imaging Center",
    "wof:placetype":"venue"
},
  "geometry": {"coordinates":[-73.97175799999999,40.897568],"type":"Point"}
}