{
  "type": "Feature",
  "properties": {
    "addr:full":"308 Pacific Ave Jersey City NJ 07304",
    "addr:housenumber":"308",
    "addr:postcode":"07304",
    "addr:street":"Pacific Ave",
    "iso:country":"US",
    "sg:address":"308 Pacific Ave",
    "sg:city":"Jersey City",
    "sg:classifiers":[
        {
            "category":"Restaurant",
            "type":"Food & Drink"
        }
    ],
    "sg:phone":"+1 201 985 0102",
    "sg:postcode":"07304",
    "sg:province":"NJ",
    "sg:tags":[
        "sandwich"
    ],
    "wof:name":"This Can't BA Sandwich",
    "wof:placetype":"venue"
},
  "geometry": {"coordinates":[-74.06151199999999,40.712137],"type":"Point"}
}