{
  "type": "Feature",
  "properties": {
    "iso:country":"US",
    "sg:address":"500 Morris Ave Ste 3",
    "sg:city":"Springfield",
    "sg:classifiers":[
        {
            "category":"Health Services",
            "subcategory":"Doctor",
            "type":"Services"
        },
        {
            "category":"Health Services",
            "subcategory":"Clinic",
            "type":"Services"
        }
    ],
    "sg:phone":"+1 973 912 8309",
    "sg:postcode":"07081",
    "sg:province":"NJ",
    "sg:tags":[
        "counseling",
        "mental"
    ],
    "wof:name":"Parisi Irene E Ph D",
    "wof:placetype":"venue"
},
  "geometry": {"coordinates":[-74.319603,40.714699],"type":"Point"}
}