{
  "type": "Feature",
  "properties": {
    "iso:country":"US",
    "sg:address":"280 Spring St",
    "sg:city":"Newton",
    "sg:classifiers":[
        {
            "category":"Social Services",
            "subcategory":"Child Care",
            "type":"Services"
        },
        {
            "category":"Recreation",
            "type":"Entertainment"
        }
    ],
    "sg:phone":"+1 973 383 7231",
    "sg:postcode":"07860",
    "sg:province":"NJ",
    "sg:tags":[
        "nursery",
        "day",
        "camps-recreational"
    ],
    "sg:website":"http://www.campiliff.com",
    "wof:name":"Iliff's After School Camp",
    "wof:placetype":"venue"
},
  "geometry": {"coordinates":[-74.749247,41.053858],"type":"Point"}
}