{
  "type": "Feature",
  "properties": {
    "addr:full":"160 Roseland Ave Caldwell NJ 07006",
    "addr:housenumber":"160",
    "addr:postcode":"07006",
    "addr:street":"Roseland Ave",
    "iso:country":"US",
    "sg:address":"160 Roseland Ave",
    "sg:city":"Caldwell",
    "sg:classifiers":[
        {
            "category":"Shopping",
            "subcategory":"Used Merchandise",
            "type":"Retail Goods"
        }
    ],
    "sg:phone":"+1 973 228 5164",
    "sg:postcode":"07006",
    "sg:province":"NJ",
    "sg:tags":[
        "shop",
        "thrift"
    ],
    "wof:name":"Hospice West Essex Thrift Shop",
    "wof:placetype":"venue"
},
  "geometry": {"coordinates":[-74.27937799999999,40.834801],"type":"Point"}
}