{
  "type": "Feature",
  "properties": {
    "addr:full":"240 Prospect Ave Hackensack NJ 07601",
    "addr:housenumber":"240",
    "addr:postcode":"07601",
    "addr:street":"Prospect Ave",
    "iso:country":"US",
    "sg:address":"240 Prospect Ave",
    "sg:city":"Hackensack",
    "sg:classifiers":[
        {
            "category":"Retail",
            "subcategory":"Laundry & Dry Cleaning",
            "type":"Services"
        }
    ],
    "sg:phone":"+1 201 525 5522",
    "sg:postcode":"07601",
    "sg:province":"NJ",
    "wof:name":"Julian Cleaners",
    "wof:placetype":"venue"
},
  "geometry": {"coordinates":[-74.054298,40.891102],"type":"Point"}
}