{
  "type": "Feature",
  "properties": {
    "addr:full":"305 Mount Hope Ave Rockaway NJ 07866",
    "addr:housenumber":"305",
    "addr:postcode":"07866",
    "addr:street":"Mount Hope Ave",
    "iso:country":"US",
    "sg:address":"305 Mount Hope Ave",
    "sg:city":"Rockaway",
    "sg:classifiers":[
        {
            "category":"Shopping",
            "subcategory":"Department Store",
            "type":"Retail Goods"
        }
    ],
    "sg:phone":"+1 973 361 4765",
    "sg:postcode":"07866",
    "sg:province":"NJ",
    "sg:website":"www.jcpenney.com",
    "wof:name":"J C Penney Co",
    "wof:placetype":"venue"
},
  "geometry": {"coordinates":[-74.533658,40.916699],"type":"Point"}
}