{
  "type": "Feature",
  "properties": {
    "addr:full":"133 Gaither Dr Mount Laurel NJ 08054",
    "addr:housenumber":"133",
    "addr:postcode":"08054",
    "addr:street":"Gaither Dr",
    "iso:country":"US",
    "sg:address":"133 Gaither Dr",
    "sg:city":"Mount Laurel",
    "sg:classifiers":[
        {
            "category":"Professional",
            "subcategory":"Engineering",
            "type":"Services"
        }
    ],
    "sg:phone":"+1   ",
    "sg:postcode":"08054",
    "sg:province":"NJ",
    "wof:name":"Dewberry-Goodkind Inc",
    "wof:placetype":"venue"
},
  "geometry": {"coordinates":[-74.950664,39.938163],"type":"Point"}
}