{
  "type": "Feature",
  "properties": {
    "iso:country":"US",
    "sg:address":"39 Longwood Dr",
    "sg:city":"Sicklerville",
    "sg:classifiers":[
        {
            "category":"Communications",
            "subcategory":"Film & Video Production",
            "type":"Services"
        }
    ],
    "sg:phone":"+1 856 728 3091",
    "sg:postcode":"08081",
    "sg:province":"NJ",
    "sg:tags":[
        "television",
        "medium"
    ],
    "wof:name":"Videotraxcom",
    "wof:placetype":"venue"
},
  "geometry": {"coordinates":[-75.024348,39.725177],"type":"Point"}
}