{
  "type": "Feature",
  "properties": {
    "addr:full":"5215 Wellington Ave Ventnor City NJ 08406",
    "addr:housenumber":"5215",
    "addr:postcode":"08406",
    "addr:street":"Wellington Ave",
    "iso:country":"US",
    "sg:address":"5215 Wellington Ave",
    "sg:city":"Ventnor City",
    "sg:classifiers":[
        {
            "category":"Insurance",
            "subcategory":"Insurance Agent",
            "type":"Services"
        }
    ],
    "sg:phone":"+1 609 487 1717",
    "sg:postcode":"08406",
    "sg:province":"NJ",
    "wof:name":"Lackovara Public Adjusters",
    "wof:placetype":"venue"
},
  "geometry": {"coordinates":[-74.475054,39.354265],"type":"Point"}
}