{
  "type": "Feature",
  "properties": {
    "addr:full":"877 Molde Ct Toms River NJ 08753",
    "addr:housenumber":"877",
    "addr:postcode":"08753",
    "addr:street":"Molde Ct",
    "iso:country":"US",
    "sg:address":"877 Molde Ct",
    "sg:city":"Toms River",
    "sg:classifiers":[
        {
            "category":"Professional",
            "type":"Services"
        }
    ],
    "sg:phone":"+1   ",
    "sg:postcode":"08753",
    "sg:province":"NJ",
    "wof:name":"Tardis II",
    "wof:placetype":"venue"
},
  "geometry": {"coordinates":[-74.15962399999999,39.979349],"type":"Point"}
}