{
  "type": "Feature",
  "properties": {
    "addr:full":"5 Registry Rd Trenton NJ 08648",
    "addr:housenumber":"5",
    "addr:postcode":"08648",
    "addr:street":"Registry Rd",
    "iso:country":"US",
    "sg:address":"5 Registry Rd",
    "sg:city":"Trenton",
    "sg:classifiers":[
        {
            "category":"Professional",
            "subcategory":"Business Services",
            "type":"Services"
        }
    ],
    "sg:phone":"+1 609 895 2943",
    "sg:postcode":"08648",
    "sg:province":"NJ",
    "wof:name":"Franchise Network New Jersey",
    "wof:placetype":"venue"
},
  "geometry": {"coordinates":[-74.73221100000001,40.310972],"type":"Point"}
}