{
  "type": "Feature",
  "properties": {
    "addr:full":"1 Westwood Dr Lincroft NJ 07738",
    "addr:housenumber":"1",
    "addr:postcode":"07738",
    "addr:street":"Westwood Dr",
    "iso:country":"US",
    "sg:address":"1 Westwood Dr",
    "sg:city":"Lincroft",
    "sg:classifiers":[
        {
            "category":"Freight",
            "type":"Transportation"
        }
    ],
    "sg:phone":"+1 732 530 9565",
    "sg:postcode":"07738",
    "sg:province":"NJ",
    "sg:tags":[
        "provides",
        "trucking"
    ],
    "wof:name":"Edward J August Trucking Inc",
    "wof:placetype":"venue"
},
  "geometry": {"coordinates":[-74.11534399999999,40.336569],"type":"Point"}
}