{
  "type": "Feature",
  "properties": {
    "addr:full":"3705 Quakerbridge Rd Mercerville NJ 08619",
    "addr:housenumber":"3705",
    "addr:postcode":"08619",
    "addr:street":"Quakerbridge Rd",
    "iso:country":"US",
    "sg:address":"3705 Quakerbridge Rd",
    "sg:city":"Mercerville",
    "sg:classifiers":[
        {
            "category":"Professional",
            "subcategory":"Lawyer & Legal Services",
            "type":"Services"
        }
    ],
    "sg:phone":"+1 609 890 0303",
    "sg:postcode":"08619",
    "sg:province":"NJ",
    "sg:tags":[
        "attorney"
    ],
    "wof:name":"Edward Hunter Lwyr",
    "wof:placetype":"venue"
},
  "geometry": {"coordinates":[-74.677156,40.259608],"type":"Point"}
}