{
  "type": "Feature",
  "properties": {
    "iso:country":"US",
    "sg:address":"852 S Orange Ave",
    "sg:city":"Newark",
    "sg:classifiers":[
        {
            "category":"Manufacturing",
            "subcategory":"Printing",
            "type":"Manufacturing & Wholesale Goods"
        }
    ],
    "sg:phone":"+1 973 375 4315",
    "sg:postcode":"07106",
    "sg:province":"NJ",
    "sg:tags":[
        "commercial"
    ],
    "wof:name":"Colony Press",
    "wof:placetype":"venue"
},
  "geometry": {"coordinates":[-74.223405,40.745245],"type":"Point"}
}