{
  "type": "Feature",
  "properties": {
    "iso:country":"US",
    "sg:address":"246 State Rte 10",
    "sg:city":"Randolph",
    "sg:classifiers":[
        {
            "category":"Insurance",
            "subcategory":"Insurance Agent",
            "type":"Services"
        }
    ],
    "sg:phone":"+1   ",
    "sg:postcode":"07869",
    "sg:province":"NJ",
    "wof:name":"Prudential",
    "wof:placetype":"venue"
},
  "geometry": {"coordinates":[-74.55019,40.868545],"type":"Point"}
}