{
  "type": "Feature",
  "properties": {
    "iso:country":"US",
    "sg:address":"249 Cedar Ave",
    "sg:city":"Hackensack",
    "sg:classifiers":[
        {
            "category":"Building & Trades",
            "subcategory":"Plumbing",
            "type":"Services"
        }
    ],
    "sg:phone":"+1 201 440 3322",
    "sg:postcode":"07601",
    "sg:province":"NJ",
    "sg:tags":[
        "contractor"
    ],
    "wof:name":"Muccia Plumbing & Heating Inc",
    "wof:placetype":"venue"
},
  "geometry": {"coordinates":[-74.05096899999999,40.909472],"type":"Point"}
}