{
  "type": "Feature",
  "properties": {
    "iso:country":"US",
    "sg:address":"137 Franklin St",
    "sg:city":"Secaucus",
    "sg:classifiers":[
        {
            "category":"Banks & Credit Unions",
            "subcategory":"Financial Services",
            "type":"Services"
        }
    ],
    "sg:phone":"+1   ",
    "sg:postcode":"07094",
    "sg:province":"NJ",
    "sg:tags":[
        "investor"
    ],
    "wof:name":"46 Front Riverdale LLC",
    "wof:placetype":"venue"
},
  "geometry": {"coordinates":[-74.054725,40.798375],"type":"Point"}
}