{
  "type": "Feature",
  "properties": {
    "iso:country":"US",
    "sg:address":"1484 US Hwy 206",
    "sg:city":"Tabernacle",
    "sg:classifiers":[
        {
            "category":"Banks & Credit Unions",
            "subcategory":"Bank",
            "type":"Services"
        }
    ],
    "sg:phone":"+1 609 268 5993",
    "sg:postcode":"08088",
    "sg:province":"NJ",
    "sg:website":"www.fmsbank.net",
    "wof:name":"Farmers & Mechanics Bank",
    "wof:placetype":"venue"
},
  "geometry": {"coordinates":[-74.73510899999999,39.844238],"type":"Point"}
}