{
  "type": "Feature",
  "properties": {
    "addr:full":"84 Anderson St Hackensack NJ 07601",
    "addr:housenumber":"84",
    "addr:postcode":"07601",
    "addr:street":"Anderson St",
    "iso:country":"US",
    "sg:address":"84 Anderson St",
    "sg:city":"Hackensack",
    "sg:classifiers":[
        {
            "category":"Personal",
            "subcategory":"Beauty Salon",
            "type":"Services"
        }
    ],
    "sg:phone":"+1   ",
    "sg:postcode":"07601",
    "sg:province":"NJ",
    "sg:tags":[
        "shop"
    ],
    "wof:name":"Anderson Beauty Shop",
    "wof:placetype":"venue"
},
  "geometry": {"coordinates":[-74.043741,40.893872],"type":"Point"}
}