{
  "type": "Feature",
  "properties": {
    "addr:full":"485 Tonnele Ave Jersey City NJ 07307",
    "addr:housenumber":"485",
    "addr:postcode":"07307",
    "addr:street":"Tonnele Ave",
    "iso:country":"US",
    "sg:address":"485 Tonnele Ave",
    "sg:city":"Jersey City",
    "sg:classifiers":[
        {
            "category":"Retail",
            "subcategory":"Auto Repair",
            "type":"Services"
        }
    ],
    "sg:phone":"+1 201 792 4971",
    "sg:postcode":"07307",
    "sg:province":"NJ",
    "sg:tags":[
        "body",
        "shop"
    ],
    "wof:name":"Eddy's Auto Body Inc",
    "wof:placetype":"venue"
},
  "geometry": {"coordinates":[-74.061699,40.747601],"type":"Point"}
}