{
  "type": "Feature",
  "properties": {
    "addr:full":"39 Boyd Ave Fair Lawn NJ 07410",
    "addr:housenumber":"39",
    "addr:postcode":"07410",
    "addr:street":"Boyd Ave",
    "iso:country":"US",
    "sg:address":"39 Boyd Ave",
    "sg:city":"Fair Lawn",
    "sg:classifiers":[
        {
            "category":"Retail",
            "subcategory":"Repair Shop",
            "type":"Services"
        }
    ],
    "sg:phone":"+1 201 703 0696",
    "sg:postcode":"07410",
    "sg:province":"NJ",
    "sg:tags":[
        "appliance"
    ],
    "wof:name":"A-1 Appliance Repair Svc Inc",
    "wof:placetype":"venue"
},
  "geometry": {"coordinates":[-74.117464,40.926849],"type":"Point"}
}