{
  "type": "Feature",
  "properties": {
    "addr:full":"780 Old Raritan Rd Edison NJ 08820",
    "addr:housenumber":"780",
    "addr:postcode":"08820",
    "addr:street":"Old Raritan Rd",
    "iso:country":"US",
    "sg:address":"780 Old Raritan Rd",
    "sg:city":"Edison",
    "sg:classifiers":[
        {
            "category":"Building & Trades",
            "subcategory":"Landscaping Services",
            "type":"Services"
        }
    ],
    "sg:phone":"+1 908 561 3479",
    "sg:postcode":"08820",
    "sg:province":"NJ",
    "sg:tags":[
        "landscape",
        "contractor"
    ],
    "wof:name":"Bolesta Landscaping",
    "wof:placetype":"venue"
},
  "geometry": {"coordinates":[-74.38675499999999,40.600156],"type":"Point"}
}