{
  "type": "Feature",
  "properties": {
    "iso:country":"US",
    "sg:address":"7 Lincoln St",
    "sg:city":"Hawthorne",
    "sg:classifiers":[
        {
            "category":"Building & Trades",
            "subcategory":"Construction",
            "type":"Services"
        }
    ],
    "sg:phone":"+1 973 445 9848",
    "sg:postcode":"07506",
    "sg:province":"NJ",
    "sg:tags":[
        "concrete",
        "contractor"
    ],
    "wof:name":"Flortec Hardwood Design Inc",
    "wof:placetype":"venue"
},
  "geometry": {"coordinates":[-74.154473,40.942399],"type":"Point"}
}