{
  "type": "Feature",
  "properties": {
    "addr:full":"165 Easton Ave New Brunswick NJ 08901",
    "addr:housenumber":"165",
    "addr:postcode":"08901",
    "addr:street":"Easton Ave",
    "iso:country":"US",
    "sg:address":"165 Easton Ave",
    "sg:city":"New Brunswick",
    "sg:classifiers":[
        {
            "category":"Restaurant",
            "type":"Food & Drink"
        }
    ],
    "sg:menulink":"http://www.allmenus.com/nj/new-brunswick/23972-sahara-restaurant/menu/",
    "sg:phone":"+1 732 246 3020",
    "sg:postcode":"08901",
    "sg:province":"NJ",
    "sg:tags":[
        "middle",
        "eastern"
    ],
    "wof:name":"Sahara Restaurant",
    "wof:placetype":"venue"
},
  "geometry": {"coordinates":[-74.45432,40.499966],"type":"Point"}
}