{
  "type": "Feature",
  "properties": {
    "addr:full":"709 Black Horse Pike Haddon Heights NJ 08035",
    "addr:housenumber":"709",
    "addr:postcode":"08035",
    "addr:street":"Black Horse Pike",
    "iso:country":"US",
    "sg:address":"709 Black Horse Pike",
    "sg:city":"Haddon Heights",
    "sg:classifiers":[
        {
            "category":"Restaurant",
            "type":"Food & Drink"
        }
    ],
    "sg:menulink":"http://www.allmenus.com/nj/haddon-heights/208272-taco-bell/menu/",
    "sg:phone":"+1 856 547 0394",
    "sg:postcode":"08035",
    "sg:province":"NJ",
    "sg:tags":[
        "mexican"
    ],
    "wof:name":"Taco Bell",
    "wof:placetype":"venue"
},
  "geometry": {"coordinates":[-75.08248500000001,39.873985],"type":"Point"}
}