{
  "type": "Feature",
  "properties": {
    "addr:full":"6150 Mill Rd Egg Harbor Twp NJ 08234",
    "addr:housenumber":"6150",
    "addr:postcode":"08234",
    "addr:street":"Mill Rd",
    "iso:country":"US",
    "sg:address":"6150 Mill Rd",
    "sg:city":"Egg Harbor Twp",
    "sg:classifiers":[
        {
            "category":"Building & Trades",
            "subcategory":"Construction",
            "type":"Services"
        },
        {
            "category":"Wholesale",
            "subcategory":"Scrap",
            "type":"Manufacturing & Wholesale Goods"
        }
    ],
    "sg:phone":"+1 609 926 6991",
    "sg:postcode":"08234",
    "sg:province":"NJ",
    "sg:tags":[
        "excavation",
        "recycling",
        "center",
        "contractor"
    ],
    "wof:name":"A J Puggi Class B Recycling",
    "wof:placetype":"venue"
},
  "geometry": {"coordinates":[-74.631827,39.387761],"type":"Point"}
}