{
  "type": "Feature",
  "properties": {
    "iso:country":"US",
    "sg:address":"77 Liberty St",
    "sg:city":"Little Ferry",
    "sg:classifiers":[
        {
            "category":"Shopping",
            "type":"Retail Goods"
        }
    ],
    "sg:phone":"+1 201 814 0110",
    "sg:postcode":"07643",
    "sg:province":"NJ",
    "sg:tags":[
        "chemical"
    ],
    "wof:name":"Applied Chemical Tech Inc",
    "wof:placetype":"venue"
},
  "geometry": {"coordinates":[-74.042644,40.84563],"type":"Point"}
}