{
  "type": "Feature",
  "properties": {
    "addr:full":"50 E State St Trenton NJ 08608",
    "addr:housenumber":"50",
    "addr:postcode":"08608",
    "addr:street":"E State St",
    "iso:country":"US",
    "sg:address":"50 E State St",
    "sg:city":"Trenton",
    "sg:classifiers":[
        {
            "category":"Restaurant",
            "type":"Food & Drink"
        }
    ],
    "sg:phone":"+1 609 394 2004",
    "sg:postcode":"08608",
    "sg:province":"NJ",
    "sg:tags":[
        "eating"
    ],
    "wof:name":"Two Brother's Pizza",
    "wof:placetype":"venue"
},
  "geometry": {"coordinates":[-74.764844,40.2203],"type":"Point"}
}