{
  "type": "Feature",
  "properties": {
    "addr:full":"3 Sussex Rd Holmdel NJ 07733",
    "addr:housenumber":"3",
    "addr:postcode":"07733",
    "addr:street":"Sussex Rd",
    "iso:country":"US",
    "sg:address":"3 Sussex Rd",
    "sg:city":"Holmdel",
    "sg:classifiers":[
        {
            "category":"Professional",
            "subcategory":"Management & Consulting",
            "type":"Services"
        }
    ],
    "sg:phone":"+1   ",
    "sg:postcode":"07733",
    "sg:province":"NJ",
    "sg:tags":[
        "telecommunication"
    ],
    "wof:name":"Ip Telecom Inc",
    "wof:placetype":"venue"
},
  "geometry": {"coordinates":[-74.19656500000001,40.368372],"type":"Point"}
}