{
  "type": "Feature",
  "properties": {
    "iso:country":"US",
    "sg:address":"299 Whitford Ave",
    "sg:city":"Nutley",
    "sg:classifiers":[
        {
            "category":"Arts & Performance",
            "subcategory":"Theater",
            "type":"Entertainment"
        }
    ],
    "sg:phone":"+1   ",
    "sg:postcode":"07110",
    "sg:province":"NJ",
    "sg:tags":[
        "theatrical"
    ],
    "wof:name":"Baudelaire Productions Inc",
    "wof:placetype":"venue"
},
  "geometry": {"coordinates":[-74.14834999999999,40.823253],"type":"Point"}
}