{
  "type": "Feature",
  "properties": {
    "iso:country":"US",
    "sg:address":"1190 Stelton Rd",
    "sg:city":"Piscataway",
    "sg:classifiers":[
        {
            "category":"Building & Trades",
            "subcategory":"Electrical",
            "type":"Services"
        }
    ],
    "sg:phone":"+1 732 985 0219",
    "sg:postcode":"08854",
    "sg:province":"NJ",
    "sg:tags":[
        "electrical",
        "contractor"
    ],
    "wof:name":"Kare More Electric Co Inc",
    "wof:placetype":"venue"
},
  "geometry": {"coordinates":[-74.427233,40.546272],"type":"Point"}
}