{
  "type": "Feature",
  "properties": {
    "addr:full":"15 Linda Ter Randolph NJ 07869",
    "addr:housenumber":"15",
    "addr:postcode":"07869",
    "addr:street":"Linda Ter",
    "iso:country":"US",
    "sg:address":"15 Linda Ter",
    "sg:city":"Randolph",
    "sg:classifiers":[
        {
            "category":"Building & Trades",
            "subcategory":"Construction",
            "type":"Services"
        }
    ],
    "sg:phone":"+1 973 584 5634",
    "sg:postcode":"07869",
    "sg:province":"NJ",
    "sg:tags":[
        "house"
    ],
    "wof:name":"Capstone Construction",
    "wof:placetype":"venue"
},
  "geometry": {"coordinates":[-74.61986400000001,40.822478],"type":"Point"}
}