{
  "type": "Feature",
  "properties": {
    "iso:country":"US",
    "sg:address":"268 Main St",
    "sg:city":"Gladstone",
    "sg:classifiers":[
        {
            "category":"Recreation",
            "type":"Entertainment"
        }
    ],
    "sg:phone":"+1 908 781 9900",
    "sg:postcode":"07931",
    "sg:province":"NJ",
    "sg:tags":[
        "historical"
    ],
    "sg:website":"www.saveellisisland.org",
    "wof:name":"Save Ellis Island Foundation",
    "wof:placetype":"venue"
},
  "geometry": {"coordinates":[-74.667131,40.721316],"type":"Point"}
}