{
  "type": "Feature",
  "properties": {
    "iso:country":"US",
    "sg:address":"1801 Greenwood Lake Tpke",
    "sg:city":"Hewitt",
    "sg:classifiers":[
        {
            "category":"Health Services",
            "subcategory":"Hospital",
            "type":"Services"
        }
    ],
    "sg:phone":"+1 973 728 3938",
    "sg:postcode":"07421",
    "sg:province":"NJ",
    "sg:tags":[
        "mental"
    ],
    "wof:name":"New Bridge Svc",
    "wof:placetype":"venue"
},
  "geometry": {"coordinates":[-74.344579,41.139329],"type":"Point"}
}