{
  "type": "Feature",
  "properties": {
    "addr:full":"Levitt Parkway & Meribrook Cir Willingboro NJ 08046",
    "addr:postcode":"08046",
    "addr:street":"Levitt Parkway & Meribrook Cir",
    "iso:country":"US",
    "sg:address":"Levitt Parkway & Meribrook Cir",
    "sg:city":"Willingboro",
    "sg:classifiers":[
        {
            "category":"Health Services",
            "subcategory":"Doctor",
            "type":"Services"
        }
    ],
    "sg:phone":"+1 609 871 7488",
    "sg:postcode":"08046",
    "sg:province":"NJ",
    "sg:tags":[
        "practice",
        "family"
    ],
    "wof:name":"South Jersey Family Practice",
    "wof:placetype":"venue"
},
  "geometry": {"coordinates":[-74.886875,40.030449],"type":"Point"}
}