{
  "type": "Feature",
  "properties": {
    "addr:full":"25 Powell Ln Barnegat NJ 08005",
    "addr:housenumber":"25",
    "addr:postcode":"08005",
    "addr:street":"Powell Ln",
    "iso:country":"US",
    "sg:address":"25 Powell Ln",
    "sg:city":"Barnegat",
    "sg:classifiers":[
        {
            "category":"Building & Trades",
            "subcategory":"Construction",
            "type":"Services"
        }
    ],
    "sg:phone":"+1 609 698 3881",
    "sg:postcode":"08005",
    "sg:province":"NJ",
    "sg:tags":[
        "roofing",
        "contractor"
    ],
    "wof:name":"J Rapp Roofing",
    "wof:placetype":"venue"
},
  "geometry": {"coordinates":[-74.210578,39.747699],"type":"Point"}
}