{
  "type": "Feature",
  "properties": {
    "addr:full":"3 Country Meadow Rd Hackettstown NJ 07840",
    "addr:housenumber":"3",
    "addr:postcode":"07840",
    "addr:street":"Country Meadow Rd",
    "iso:country":"US",
    "sg:address":"3 Country Meadow Rd",
    "sg:city":"Hackettstown",
    "sg:classifiers":[
        {
            "category":"Building & Trades",
            "subcategory":"Plumbing",
            "type":"Services"
        }
    ],
    "sg:phone":"+1 908 813 9525",
    "sg:postcode":"07840",
    "sg:province":"NJ",
    "sg:tags":[
        "conditioning",
        "air",
        "system",
        "contractor"
    ],
    "wof:name":"Conti's Air Conditioning",
    "wof:placetype":"venue"
},
  "geometry": {"coordinates":[-74.871515,40.810605],"type":"Point"}
}