{
  "type": "Feature",
  "properties": {
    "addr:full":"16 Jersey Ave New Brunswick NJ 08901",
    "addr:housenumber":"16",
    "addr:postcode":"08901",
    "addr:street":"Jersey Ave",
    "iso:country":"US",
    "sg:address":"16 Jersey Ave",
    "sg:city":"New Brunswick",
    "sg:classifiers":[
        {
            "category":"Manufacturing",
            "subcategory":"Retail Goods",
            "type":"Manufacturing & Wholesale Goods"
        }
    ],
    "sg:phone":"+1 732 545 1630",
    "sg:postcode":"08901",
    "sg:province":"NJ",
    "sg:tags":[
        "bucket",
        "manufacturer"
    ],
    "wof:name":"Shelton Ware Inc",
    "wof:placetype":"venue"
},
  "geometry": {"coordinates":[-74.454133,40.491876],"type":"Point"}
}