{
  "type": "Feature",
  "properties": {
    "addr:full":"187 Frederick Pl Bergenfield NJ 07621",
    "addr:housenumber":"187",
    "addr:postcode":"07621",
    "addr:street":"Frederick Pl",
    "iso:country":"US",
    "sg:address":"187 Frederick Pl",
    "sg:city":"Bergenfield",
    "sg:classifiers":[
        {
            "category":"Shopping",
            "subcategory":"Gifts & Souvenirs",
            "type":"Retail Goods"
        }
    ],
    "sg:phone":"+1   ",
    "sg:postcode":"07621",
    "sg:province":"NJ",
    "wof:name":"Eloquent Gifts & Supplies",
    "wof:placetype":"venue"
},
  "geometry": {"coordinates":[-74.005156,40.9092],"type":"Point"}
}