{
  "type": "Feature",
  "properties": {
    "iso:country":"US",
    "sg:address":"751 Kennedy Blvd",
    "sg:city":"Bayonne",
    "sg:classifiers":[
        {
            "category":"Food & Beverages",
            "subcategory":"Groceries & Convenience Stores",
            "type":"Retail Goods"
        }
    ],
    "sg:phone":"+1   ",
    "sg:postcode":"07002",
    "sg:province":"NJ",
    "wof:name":"Famous Deli & Grocery",
    "wof:placetype":"venue"
},
  "geometry": {"coordinates":[-74.119018,40.670806],"type":"Point"}
}