{
  "type": "Feature",
  "properties": {
    "iso:country":"US",
    "sg:address":"2111 Columbus Rd",
    "sg:city":"Florence",
    "sg:classifiers":[
        {
            "category":"Real Estate",
            "subcategory":"Real Estate Operator",
            "type":"Services"
        }
    ],
    "sg:phone":"+1   ",
    "sg:postcode":"08505",
    "sg:province":"NJ",
    "sg:tags":[
        "property",
        "lessor"
    ],
    "wof:name":"Hathaway Farm",
    "wof:placetype":"venue"
},
  "geometry": {"coordinates":[-74.768259,40.079384],"type":"Point"}
}