{
  "type": "Feature",
  "properties": {
    "iso:country":"US",
    "sg:address":"303 State Rte 36",
    "sg:city":"Hazlet",
    "sg:classifiers":[
        {
            "category":"Food & Beverages",
            "subcategory":"Fruits & Vegetables",
            "type":"Retail Goods"
        }
    ],
    "sg:phone":"+1 732 787 8832",
    "sg:postcode":"07730",
    "sg:province":"NJ",
    "sg:tags":[
        "produce"
    ],
    "wof:name":"Tony's Farm Market",
    "wof:placetype":"venue"
},
  "geometry": {"coordinates":[-74.1442,40.437877],"type":"Point"}
}