{
  "type": "Feature",
  "properties": {
    "addr:full":"239 US Hwy 22 Dunellen NJ 08812",
    "addr:housenumber":"239",
    "addr:postcode":"08812",
    "addr:street":"Us Hwy 22",
    "iso:country":"US",
    "sg:address":"239 US Hwy 22",
    "sg:city":"Dunellen",
    "sg:classifiers":[
        {
            "category":"Professional",
            "subcategory":"Management & Consulting",
            "type":"Services"
        }
    ],
    "sg:phone":"+1   ",
    "sg:postcode":"08812",
    "sg:province":"NJ",
    "wof:name":"TEKWOOD ASSOCIATES",
    "wof:placetype":"venue"
},
  "geometry": {"coordinates":[-74.48531800000001,40.598987],"type":"Point"}
}