{
  "type": "Feature",
  "properties": {
    "iso:country":"US",
    "sg:address":"6506 Park Ave",
    "sg:city":"West New York",
    "sg:classifiers":[
        {
            "category":"Building & Trades",
            "subcategory":"Locksmith",
            "type":"Services"
        }
    ],
    "sg:phone":"+1 201 520 1420",
    "sg:postcode":"07093",
    "sg:province":"NJ",
    "sg:tags":[
        "key"
    ],
    "wof:name":"Available Locksmith 24 7",
    "wof:placetype":"venue"
},
  "geometry": {"coordinates":[-74.00555799999999,40.789434],"type":"Point"}
}