{
  "type": "Feature",
  "properties": {
    "addr:full":"292 Main St West Orange NJ 07052",
    "addr:housenumber":"292",
    "addr:postcode":"07052",
    "addr:street":"Main St",
    "iso:country":"US",
    "sg:address":"292 Main St",
    "sg:city":"West Orange",
    "sg:classifiers":[
        {
            "category":"Restaurant",
            "type":"Food & Drink"
        }
    ],
    "sg:menulink":"http://www.allmenus.com/nj/west-orange/16177-el-centro-americano-restaurant/menu/",
    "sg:phone":"+1 973 324 0656",
    "sg:postcode":"07052",
    "sg:province":"NJ",
    "sg:tags":[
        "italian"
    ],
    "wof:name":"El Centro Americano Restaurant",
    "wof:placetype":"venue"
},
  "geometry": {"coordinates":[-74.231179,40.787667],"type":"Point"}
}