{
  "type": "Feature",
  "properties": {
    "addr:full":"625 Westfield Ave Elizabeth NJ 07208",
    "addr:housenumber":"625",
    "addr:postcode":"07208",
    "addr:street":"Westfield Ave",
    "iso:country":"US",
    "sg:address":"625 Westfield Ave",
    "sg:city":"Elizabeth",
    "sg:classifiers":[
        {
            "category":"Retail",
            "subcategory":"Repair Shop",
            "type":"Services"
        }
    ],
    "sg:phone":"+1 908 372 6769",
    "sg:postcode":"07208",
    "sg:province":"NJ",
    "sg:tags":[
        "lock",
        "locksmith"
    ],
    "wof:name":"USA Locksmith",
    "wof:placetype":"venue"
},
  "geometry": {"coordinates":[-74.236823,40.665427],"type":"Point"}
}