{
  "type": "Feature",
  "properties": {
    "iso:country":"US",
    "sg:address":"430 Industrial Ave",
    "sg:city":"Teterboro",
    "sg:classifiers":[
        {
            "category":"Autos & Motor Vehicles",
            "subcategory":"Automobile Sales",
            "type":"Retail Goods"
        }
    ],
    "sg:phone":"+1 201 288 8420",
    "sg:postcode":"07608",
    "sg:province":"NJ",
    "sg:tags":[
        "car",
        "used",
        "dealer"
    ],
    "wof:name":"Perera Auto Sales Inc",
    "wof:placetype":"venue"
},
  "geometry": {"coordinates":[-74.059673,40.86067],"type":"Point"}
}