{
  "type": "Feature",
  "properties": {
    "iso:country":"US",
    "sg:address":"199 Schraalenburgh Rd",
    "sg:city":"Closter",
    "sg:classifiers":[
        {
            "category":"Shopping",
            "subcategory":"Computers & Home Electronics",
            "type":"Retail Goods"
        }
    ],
    "sg:phone":"+1 201 750 7038",
    "sg:postcode":"07624",
    "sg:province":"NJ",
    "sg:tags":[
        "equipment",
        "dealer"
    ],
    "wof:name":"Won Tek Inc",
    "wof:placetype":"venue"
},
  "geometry": {"coordinates":[-73.98247499999999,40.972392],"type":"Point"}
}