{
  "type": "Feature",
  "properties": {
    "iso:country":"US",
    "sg:address":"554 Chestnut St",
    "sg:city":"Ridgefield",
    "sg:classifiers":[
        {
            "category":"Food & Beverages",
            "subcategory":"Specialty",
            "type":"Retail Goods"
        }
    ],
    "sg:phone":"+1   ",
    "sg:postcode":"07657",
    "sg:province":"NJ",
    "wof:name":"Bee Healthy",
    "wof:placetype":"venue"
},
  "geometry": {"coordinates":[-73.998121,40.830491],"type":"Point"}
}