{
  "type": "Feature",
  "properties": {
    "iso:country":"US",
    "sg:address":"63 W Pleasant Ave",
    "sg:city":"Maywood",
    "sg:classifiers":[
        {
            "category":"Shopping",
            "subcategory":"Gifts & Souvenirs",
            "type":"Retail Goods"
        }
    ],
    "sg:phone":"+1 201 342 9330",
    "sg:postcode":"07607",
    "sg:province":"NJ",
    "sg:tags":[
        "florist",
        "basket",
        "parcel"
    ],
    "sg:website":"www.maywoodflorist.com",
    "wof:name":"Maywood Florist",
    "wof:placetype":"venue"
},
  "geometry": {"coordinates":[-74.063301,40.9048],"type":"Point"}
}