{
  "type": "Feature",
  "properties": {
    "iso:country":"US",
    "sg:address":"46 W 26th St",
    "sg:city":"Bayonne",
    "sg:classifiers":[
        {
            "category":"Building & Trades",
            "subcategory":"Construction",
            "type":"Services"
        }
    ],
    "sg:phone":"+1 201 436 1494",
    "sg:postcode":"07002",
    "sg:province":"NJ",
    "sg:tags":[
        "house"
    ],
    "wof:name":"El San Diego Const Inc",
    "wof:placetype":"venue"
},
  "geometry": {"coordinates":[-74.116998,40.666564],"type":"Point"}
}