{
  "type": "Feature",
  "properties": {
    "addr:full":"1621 Main St Belmar NJ 07719",
    "addr:housenumber":"1621",
    "addr:postcode":"07719",
    "addr:street":"Main St",
    "iso:country":"US",
    "sg:address":"1621 Main St",
    "sg:city":"Belmar",
    "sg:classifiers":[
        {
            "category":"Restaurant",
            "type":"Food & Drink"
        }
    ],
    "sg:phone":"+1 732 681 2813",
    "sg:postcode":"07719",
    "sg:province":"NJ",
    "wof:name":"Antonio's Trattoria",
    "wof:placetype":"venue"
},
  "geometry": {"coordinates":[-74.027411,40.173702],"type":"Point"}
}