{
  "type": "Feature",
  "properties": {
    "addr:full":"655 Georges Rd North Brunswick NJ 08902",
    "addr:housenumber":"655",
    "addr:postcode":"08902",
    "addr:street":"Georges Rd",
    "iso:country":"US",
    "sg:address":"655 Georges Rd",
    "sg:city":"North Brunswick",
    "sg:classifiers":[
        {
            "category":"Building & Trades",
            "subcategory":"Construction",
            "type":"Services"
        }
    ],
    "sg:phone":"+1 732 846 5580",
    "sg:postcode":"08902",
    "sg:province":"NJ",
    "sg:tags":[
        "general",
        "contractor"
    ],
    "wof:name":"Vuk Contracting",
    "wof:placetype":"venue"
},
  "geometry": {"coordinates":[-74.45214,40.469206],"type":"Point"}
}