{
  "type": "Feature",
  "properties": {
    "iso:country":"US",
    "sg:address":"11 Dey Pl",
    "sg:city":"Edison",
    "sg:classifiers":[
        {
            "category":"Home & Garden",
            "subcategory":"Building Materials",
            "type":"Retail Goods"
        }
    ],
    "sg:phone":"+1   ",
    "sg:postcode":"08817",
    "sg:province":"NJ",
    "wof:name":"K F R Fencing",
    "wof:placetype":"venue"
},
  "geometry": {"coordinates":[-74.39824,40.508279],"type":"Point"}
}