{
  "type": "Feature",
  "properties": {
    "iso:country":"US",
    "sg:address":"3974 US Hwy 1",
    "sg:city":"Monmouth Jct",
    "sg:classifiers":[
        {
            "category":"Retail",
            "subcategory":"Car Wash",
            "type":"Services"
        }
    ],
    "sg:phone":"+1 732 821 0747",
    "sg:postcode":"08852",
    "sg:province":"NJ",
    "sg:tags":[
        "automobile",
        "detail",
        "clean"
    ],
    "wof:name":"Carsmedix Detailing",
    "wof:placetype":"venue"
},
  "geometry": {"coordinates":[-74.55003499999999,40.404356],"type":"Point"}
}