{
  "type": "Feature",
  "properties": {
    "addr:full":"400 Simons Ave Hackensack NJ 07601",
    "addr:housenumber":"400",
    "addr:postcode":"07601",
    "addr:street":"Simons Ave",
    "iso:country":"US",
    "sg:address":"400 Simons Ave",
    "sg:city":"Hackensack",
    "sg:classifiers":[
        {
            "category":"Shopping",
            "subcategory":"Hobbies, Toys, & Games",
            "type":"Retail Goods"
        }
    ],
    "sg:phone":"+1 201 342 6969",
    "sg:postcode":"07601",
    "sg:province":"NJ",
    "sg:tags":[
        "supply"
    ],
    "wof:name":"Gamers Dream",
    "wof:placetype":"venue"
},
  "geometry": {"coordinates":[-74.06278399999999,40.883297],"type":"Point"}
}