{
  "type": "Feature",
  "properties": {
    "addr:full":"1347 Stelton Rd Ste 8 Piscataway NJ 08854",
    "addr:housenumber":"1347",
    "addr:postcode":"08854",
    "addr:street":"Stelton Rd Ste 8",
    "iso:country":"US",
    "sg:address":"1347 Stelton Rd Ste 8",
    "sg:city":"Piscataway",
    "sg:phone":"+1 732 777 9595",
    "sg:postcode":"08854",
    "sg:province":"NJ",
    "wof:name":"Sukh Sagar Indian Cuisine Inc",
    "wof:placetype":"venue"
},
  "geometry": {"coordinates":[-74.423368,40.540549],"type":"Point"}
}