{
  "type": "Feature",
  "properties": {
    "addr:full":"1 Ironside Ct Willingboro NJ 08046",
    "addr:housenumber":"1",
    "addr:postcode":"08046",
    "addr:street":"Ironside Ct",
    "iso:country":"US",
    "sg:address":"1 Ironside Ct",
    "sg:city":"Willingboro",
    "sg:classifiers":[
        {
            "category":"Wholesale",
            "subcategory":"Construction Materials",
            "type":"Manufacturing & Wholesale Goods"
        }
    ],
    "sg:phone":"+1 609 877 1008",
    "sg:postcode":"08046",
    "sg:province":"NJ",
    "sg:tags":[
        "granite"
    ],
    "wof:name":"American Silestone & Granite",
    "wof:placetype":"venue"
},
  "geometry": {"coordinates":[-74.918792,40.029759],"type":"Point"}
}