{
  "type": "Feature",
  "properties": {
    "addr:full":"91 Ruckman Rd Closter NJ 07624",
    "addr:housenumber":"91",
    "addr:postcode":"07624",
    "addr:street":"Ruckman Rd",
    "iso:country":"US",
    "sg:address":"91 Ruckman Rd",
    "sg:city":"Closter",
    "sg:classifiers":[
        {
            "category":"Communications",
            "subcategory":"Film & Video Production",
            "type":"Services"
        }
    ],
    "sg:phone":"+1 201 768 5005",
    "sg:postcode":"07624",
    "sg:province":"NJ",
    "sg:tags":[
        "duplication",
        "tape"
    ],
    "sg:website":"www.duplicationservices.com",
    "wof:name":"Duplication Services",
    "wof:placetype":"venue"
},
  "geometry": {"coordinates":[-73.958809,40.973493],"type":"Point"}
}