{
  "type": "Feature",
  "properties": {
    "addr:full":"680 Promenade Blvd Bridgewater NJ 08807",
    "addr:housenumber":"680",
    "addr:postcode":"08807",
    "addr:street":"Promenade Blvd",
    "iso:country":"US",
    "sg:address":"680 Promenade Blvd",
    "sg:city":"Bridgewater",
    "sg:classifiers":[
        {
            "category":"Restaurant",
            "type":"Food & Drink"
        }
    ],
    "sg:phone":"+1 732 627 9230",
    "sg:postcode":"08807",
    "sg:province":"NJ",
    "sg:website":"www.mcdonalds.com",
    "wof:name":"Mc Donald's",
    "wof:placetype":"venue"
},
  "geometry": {"coordinates":[-74.55984599999999,40.567434],"type":"Point"}
}