{
  "type": "Feature",
  "properties": {
    "addr:full":"16 Chapel Pl Wayne NJ 07470",
    "addr:housenumber":"16",
    "addr:postcode":"07470",
    "addr:street":"Chapel Pl",
    "iso:country":"US",
    "sg:address":"16 Chapel Pl",
    "sg:city":"Wayne",
    "sg:classifiers":[
        {
            "category":"Building & Trades",
            "subcategory":"Construction",
            "type":"Services"
        }
    ],
    "sg:phone":"+1 973 956 7617",
    "sg:postcode":"07470",
    "sg:province":"NJ",
    "sg:tags":[
        "contractor"
    ],
    "wof:name":"Ckr Construction",
    "wof:placetype":"venue"
},
  "geometry": {"coordinates":[-74.22140899999999,40.929998],"type":"Point"}
}