{
  "type": "Feature",
  "properties": {
    "iso:country":"US",
    "sg:address":"23 Laurel St",
    "sg:city":"Hawthorne",
    "sg:classifiers":[
        {
            "category":"Building & Trades",
            "subcategory":"Plumbing",
            "type":"Services"
        }
    ],
    "sg:phone":"+1 973 423 5104",
    "sg:postcode":"07506",
    "sg:province":"NJ",
    "sg:tags":[
        "contractor"
    ],
    "wof:name":"Campomizzi Plumbing",
    "wof:placetype":"venue"
},
  "geometry": {"coordinates":[-74.15758099999999,40.968792],"type":"Point"}
}