{
  "type": "Feature",
  "properties": {
    "addr:full":"16 Vannoy Ave Pennington NJ 08534",
    "addr:housenumber":"16",
    "addr:postcode":"08534",
    "addr:street":"Vannoy Ave",
    "iso:country":"US",
    "sg:address":"16 Vannoy Ave",
    "sg:city":"Pennington",
    "sg:classifiers":[
        {
            "category":"Professional",
            "subcategory":"Business Services",
            "type":"Services"
        }
    ],
    "sg:phone":"+1   ",
    "sg:postcode":"08534",
    "sg:province":"NJ",
    "wof:name":"Levandowski Design",
    "wof:placetype":"venue"
},
  "geometry": {"coordinates":[-74.79178400000001,40.315446],"type":"Point"}
}