{
  "type": "Feature",
  "properties": {
    "iso:country":"US",
    "sg:address":"19 S Main St",
    "sg:city":"Marlboro",
    "sg:classifiers":[
        {
            "category":"Arts & Performance",
            "subcategory":"Theater",
            "type":"Entertainment"
        }
    ],
    "sg:phone":"+1   ",
    "sg:postcode":"07746",
    "sg:province":"NJ",
    "sg:tags":[
        "group"
    ],
    "wof:name":"Granian LLC",
    "wof:placetype":"venue"
},
  "geometry": {"coordinates":[-74.25036799999999,40.309909],"type":"Point"}
}