{
  "type": "Feature",
  "properties": {
    "iso:country":"US",
    "sg:address":"352 Clifton Ave",
    "sg:city":"Clifton",
    "sg:classifiers":[
        {
            "category":"Social Services",
            "type":"Services"
        }
    ],
    "sg:phone":"+1 973 365 2125",
    "sg:postcode":"07011",
    "sg:province":"NJ",
    "sg:tags":[
        "counselor",
        "marriage",
        "family"
    ],
    "wof:name":"Christian Counseling Center",
    "wof:placetype":"venue"
},
  "geometry": {"coordinates":[-74.14012200000001,40.875339],"type":"Point"}
}