{
  "type": "Feature",
  "properties": {
    "iso:country":"US",
    "sg:address":"339 State Rte 73",
    "sg:city":"Berlin",
    "sg:classifiers":[
        {
            "category":"Wholesale",
            "subcategory":"Office Equipment",
            "type":"Manufacturing & Wholesale Goods"
        }
    ],
    "sg:phone":"+1 856 753 8600",
    "sg:postcode":"08009",
    "sg:province":"NJ",
    "sg:tags":[
        "machine",
        "addressing",
        "mailing",
        "supply"
    ],
    "wof:name":"Addressing & Mailing Systems",
    "wof:placetype":"venue"
},
  "geometry": {"coordinates":[-74.90955099999999,39.741762],"type":"Point"}
}