{
  "type": "Feature",
  "properties": {
    "iso:country":"US",
    "sg:address":"6 High St",
    "sg:city":"Lebanon",
    "sg:classifiers":[
        {
            "category":"Government",
            "subcategory":"Office",
            "type":"Public Place"
        }
    ],
    "sg:phone":"+1 908 236 2425",
    "sg:postcode":"08833",
    "sg:province":"NJ",
    "sg:tags":[
        "village"
    ],
    "wof:name":"Lebanon Borough Municipal Ofc",
    "wof:placetype":"venue"
},
  "geometry": {"coordinates":[-74.837441,40.641235],"type":"Point"}
}