{
  "type": "Feature",
  "properties": {
    "iso:country":"US",
    "sg:address":"190 North Ave E",
    "sg:city":"Cranford",
    "sg:classifiers":[
        {
            "category":"Health Services",
            "subcategory":"Podiatrist",
            "type":"Services"
        }
    ],
    "sg:phone":"+1 908 272 1991",
    "sg:postcode":"07016",
    "sg:province":"NJ",
    "wof:name":"Marshall Cooper DPM",
    "wof:placetype":"venue"
},
  "geometry": {"coordinates":[-74.298979,40.65673],"type":"Point"}
}