{
  "type": "Feature",
  "properties": {
    "addr:full":"299 Paramus Rd Paramus NJ 07652",
    "addr:housenumber":"299",
    "addr:postcode":"07652",
    "addr:street":"Paramus Rd",
    "iso:country":"US",
    "sg:address":"299 Paramus Rd",
    "sg:city":"Paramus",
    "sg:classifiers":[
        {
            "category":"Retail",
            "subcategory":"Repair Shop",
            "type":"Services"
        }
    ],
    "sg:phone":"+1 201 334 3978",
    "sg:postcode":"07652",
    "sg:province":"NJ",
    "sg:tags":[
        "lock",
        "locksmith"
    ],
    "wof:name":"24 Hour Locksmith",
    "wof:placetype":"venue"
},
  "geometry": {"coordinates":[-74.09289099999999,40.943034],"type":"Point"}
}