{
  "type": "Feature",
  "properties": {
    "addr:full":"51 Newark Ave Bloomfield NJ 07003",
    "addr:housenumber":"51",
    "addr:postcode":"07003",
    "addr:street":"Newark Ave",
    "iso:country":"US",
    "sg:address":"51 Newark Ave",
    "sg:city":"Bloomfield",
    "sg:classifiers":[
        {
            "category":"Home & Garden",
            "subcategory":"Building Materials",
            "type":"Retail Goods"
        }
    ],
    "sg:phone":"+1 973 429 0017",
    "sg:postcode":"07003",
    "sg:province":"NJ",
    "sg:tags":[
        "windows"
    ],
    "wof:name":"Salinas Home Improvements Inc",
    "wof:placetype":"venue"
},
  "geometry": {"coordinates":[-74.18335500000001,40.787335],"type":"Point"}
}