{
  "type": "Feature",
  "properties": {
    "addr:full":"124 E Annapolis Dr Sicklerville NJ 08081",
    "addr:housenumber":"124",
    "addr:postcode":"08081",
    "addr:street":"E Annapolis Dr",
    "iso:country":"US",
    "sg:address":"124 E Annapolis Dr",
    "sg:city":"Sicklerville",
    "sg:classifiers":[
        {
            "category":"Travel",
            "subcategory":"Travel Agent",
            "type":"Entertainment"
        }
    ],
    "sg:phone":"+1 888 642 5398",
    "sg:postcode":"08081",
    "sg:province":"NJ",
    "sg:website":"www.dreamcometruevacations.com",
    "wof:name":"Dream Come True Vacations",
    "wof:placetype":"venue"
},
  "geometry": {"coordinates":[-74.99615,39.753698],"type":"Point"}
}