{
  "type": "Feature",
  "properties": {
    "iso:country":"US",
    "sg:address":"36 Summit Ave",
    "sg:city":"Fairfield",
    "sg:classifiers":[
        {
            "category":"Banks & Credit Unions",
            "subcategory":"Financial Services",
            "type":"Services"
        }
    ],
    "sg:phone":"+1   ",
    "sg:postcode":"07004",
    "sg:province":"NJ",
    "sg:tags":[
        "investor"
    ],
    "wof:name":"Jag Investment Group Liabi",
    "wof:placetype":"venue"
},
  "geometry": {"coordinates":[-74.262303,40.881815],"type":"Point"}
}