{
  "type": "Feature",
  "properties": {
    "addr:full":"629 Chester Ave Moorestown NJ 08057",
    "addr:housenumber":"629",
    "addr:postcode":"08057",
    "addr:street":"Chester Ave",
    "iso:country":"US",
    "sg:address":"629 Chester Ave",
    "sg:city":"Moorestown",
    "sg:classifiers":[
        {
            "category":"Restaurant",
            "type":"Food & Drink"
        }
    ],
    "sg:phone":"+1   ",
    "sg:postcode":"08057",
    "sg:province":"NJ",
    "sg:tags":[
        "catering"
    ],
    "wof:name":"ODonnells Caterings",
    "wof:placetype":"venue"
},
  "geometry": {"coordinates":[-74.94847799999999,39.975036],"type":"Point"}
}