{
  "type": "Feature",
  "properties": {
    "iso:country":"US",
    "sg:address":"212 Caroline Ave",
    "sg:city":"Villas",
    "sg:classifiers":[
        {
            "category":"Retail",
            "subcategory":"Repair Shop",
            "type":"Services"
        }
    ],
    "sg:phone":"+1   ",
    "sg:postcode":"08251",
    "sg:province":"NJ",
    "sg:tags":[
        "mail",
        "house"
    ],
    "wof:name":"Owens Telecom",
    "wof:placetype":"venue"
},
  "geometry": {"coordinates":[-74.927233,39.024766],"type":"Point"}
}