{
  "type": "Feature",
  "properties": {
    "addr:full":"905 Murray St Avenel NJ 07001",
    "addr:housenumber":"905",
    "addr:postcode":"07001",
    "addr:street":"Murray St",
    "iso:country":"US",
    "sg:address":"905 Murray St",
    "sg:city":"Avenel",
    "sg:classifiers":[
        {
            "category":"Professional",
            "type":"Services"
        }
    ],
    "sg:phone":"+1   ",
    "sg:postcode":"07001",
    "sg:province":"NJ",
    "wof:name":"Van Patel Inc",
    "wof:placetype":"venue"
},
  "geometry": {"coordinates":[-74.281087,40.588334],"type":"Point"}
}