{
  "type": "Feature",
  "properties": {
    "addr:full":"1111 McConnell Dr Pleasantville NJ 08232",
    "addr:housenumber":"1111",
    "addr:postcode":"08232",
    "addr:street":"Mcconnell Dr",
    "iso:country":"US",
    "sg:address":"1111 McConnell Dr",
    "sg:city":"Pleasantville",
    "sg:classifiers":[
        {
            "category":"Professional",
            "subcategory":"Business Services",
            "type":"Services"
        }
    ],
    "sg:phone":"+1 609 641 5472",
    "sg:postcode":"08232",
    "sg:province":"NJ",
    "sg:tags":[
        "painting",
        "sign"
    ],
    "wof:name":"Mosetti Signs By Moe",
    "wof:placetype":"venue"
},
  "geometry": {"coordinates":[-74.504974,39.407186],"type":"Point"}
}