{
  "type": "Feature",
  "properties": {
    "addr:full":"49 Wall St Oxford NJ 07863",
    "addr:housenumber":"49",
    "addr:postcode":"07863",
    "addr:street":"Wall St",
    "iso:country":"US",
    "sg:address":"49 Wall St",
    "sg:city":"Oxford",
    "sg:classifiers":[
        {
            "category":"Personal",
            "subcategory":"Tanning Parlor",
            "type":"Services"
        }
    ],
    "sg:phone":"+1 908 453 4040",
    "sg:postcode":"07863",
    "sg:province":"NJ",
    "sg:tags":[
        "salon"
    ],
    "wof:name":"Finish Line Tanning",
    "wof:placetype":"venue"
},
  "geometry": {"coordinates":[-74.99645099999999,40.804097],"type":"Point"}
}