{
  "type": "Feature",
  "properties": {
    "addr:full":"182 State Route 10 East Hanover NJ 07936",
    "addr:housenumber":"182",
    "addr:postcode":"07936",
    "addr:street":"State Route 10",
    "iso:country":"US",
    "sg:address":"182 State Route 10",
    "sg:city":"East Hanover",
    "sg:classifiers":[
        {
            "category":"Recreation",
            "subcategory":"Amusement Park",
            "type":"Entertainment"
        },
        {
            "category":"Personal",
            "type":"Services"
        }
    ],
    "sg:phone":"+1 973 428 1166",
    "sg:postcode":"07936",
    "sg:province":"NJ",
    "sg:tags":[
        "party",
        "planning",
        "event"
    ],
    "sg:website":"www.thefunplex.com/east_hanover/...",
    "wof:name":"Sports'n'games Funplex",
    "wof:placetype":"venue"
},
  "geometry": {"coordinates":[-74.381897,40.809799],"type":"Point"}
}