{
  "type": "Feature",
  "properties": {
    "addr:full":"482 Notch Rd Little Falls NJ 07424",
    "addr:housenumber":"482",
    "addr:postcode":"07424",
    "addr:street":"Notch Rd",
    "iso:country":"US",
    "sg:address":"482 Notch Rd",
    "sg:city":"Little Falls",
    "sg:classifiers":[
        {
            "category":"Travel",
            "subcategory":"Travel Agent",
            "type":"Entertainment"
        }
    ],
    "sg:phone":"+1 973 812 4949",
    "sg:postcode":"07424",
    "sg:province":"NJ",
    "sg:tags":[
        "agency"
    ],
    "wof:name":"Travel Four Inc",
    "wof:placetype":"venue"
},
  "geometry": {"coordinates":[-74.201415,40.876087],"type":"Point"}
}