{
  "type": "Feature",
  "properties": {
    "addr:full":"143 Bay Pkwy Waretown NJ 08758",
    "addr:housenumber":"143",
    "addr:postcode":"08758",
    "addr:street":"Bay Pkwy",
    "iso:country":"US",
    "sg:address":"143 Bay Pkwy",
    "sg:city":"Waretown",
    "sg:classifiers":[
        {
            "category":"Professional",
            "type":"Services"
        }
    ],
    "sg:phone":"+1   ",
    "sg:postcode":"08758",
    "sg:province":"NJ",
    "wof:name":"Miranda Trinidad Energy",
    "wof:placetype":"venue"
},
  "geometry": {"coordinates":[-74.18103000000001,39.806297],"type":"Point"}
}