{
  "type": "Feature",
  "properties": {
    "addr:full":"31 Wilburtha Rd Trenton NJ 08628",
    "addr:housenumber":"31",
    "addr:postcode":"08628",
    "addr:street":"Wilburtha Rd",
    "iso:country":"US",
    "sg:address":"31 Wilburtha Rd",
    "sg:city":"Trenton",
    "sg:classifiers":[
        {
            "category":"Home & Garden",
            "subcategory":"Building Materials",
            "type":"Retail Goods"
        }
    ],
    "sg:phone":"+1 609 882 2449",
    "sg:postcode":"08628",
    "sg:province":"NJ",
    "wof:name":"Trenton Stone Co Inc",
    "wof:placetype":"venue"
},
  "geometry": {"coordinates":[-74.83259700000001,40.251681],"type":"Point"}
}