{
  "type": "Feature",
  "properties": {
    "iso:country":"US",
    "sg:address":"135 Asbury Rd",
    "sg:city":"Farmingdale",
    "sg:classifiers":[
        {
            "category":"Building & Trades",
            "subcategory":"Construction",
            "type":"Services"
        }
    ],
    "sg:phone":"+1 732 938 2048",
    "sg:postcode":"07727",
    "sg:province":"NJ",
    "sg:tags":[
        "contracting"
    ],
    "wof:name":"Ira B Matthew III Bldg Contr",
    "wof:placetype":"venue"
},
  "geometry": {"coordinates":[-74.15837399999999,40.205668],"type":"Point"}
}