{
  "type": "Feature",
  "properties": {
    "iso:country":"US",
    "sg:address":"624 Collings Ave",
    "sg:city":"Oaklyn",
    "sg:classifiers":[
        {
            "category":"Restaurant",
            "type":"Food & Drink"
        }
    ],
    "sg:phone":"+1 856 854 6888",
    "sg:postcode":"08107",
    "sg:province":"NJ",
    "sg:tags":[
        "chinese"
    ],
    "wof:name":"New China Star Chinese Food",
    "wof:placetype":"venue"
},
  "geometry": {"coordinates":[-75.085098,39.910801],"type":"Point"}
}