{
  "type": "Feature",
  "properties": {
    "addr:full":"98 Market St Passaic NJ 07055",
    "addr:housenumber":"98",
    "addr:postcode":"07055",
    "addr:street":"Market St",
    "iso:country":"US",
    "sg:address":"98 Market St",
    "sg:city":"Passaic",
    "sg:classifiers":[
        {
            "category":"Restaurant",
            "type":"Food & Drink"
        }
    ],
    "sg:phone":"+1 973 779 3389",
    "sg:postcode":"07055",
    "sg:province":"NJ",
    "sg:tags":[
        "eating"
    ],
    "wof:name":"Sing Hing Restaurant",
    "wof:placetype":"venue"
},
  "geometry": {"coordinates":[-74.116699,40.8657],"type":"Point"}
}