{
  "type": "Feature",
  "properties": {
    "addr:full":"851 W Park Ave Asbury Park NJ 07712",
    "addr:housenumber":"851",
    "addr:postcode":"07712",
    "addr:street":"W Park Ave Asbury",
    "iso:country":"US",
    "sg:address":"851 W Park Ave",
    "sg:city":"Asbury Park",
    "sg:classifiers":[
        {
            "category":"Shopping",
            "subcategory":"Pharmacy",
            "type":"Retail Goods"
        }
    ],
    "sg:phone":"+1 732 695 0277",
    "sg:postcode":"07712",
    "sg:province":"NJ",
    "wof:name":"Natural Pharmacy",
    "wof:placetype":"venue"
},
  "geometry": {"coordinates":[-74.04572899999999,40.263461],"type":"Point"}
}