{
  "type": "Feature",
  "properties": {
    "addr:full":"4 Dehart St Ste 1 Morristown NJ 07960",
    "addr:housenumber":"4",
    "addr:postcode":"07960",
    "addr:street":"Dehart St Ste 1",
    "iso:country":"US",
    "sg:address":"4 Dehart St Ste 1",
    "sg:city":"Morristown",
    "sg:classifiers":[
        {
            "category":"Bars & Pubs",
            "subcategory":"Nightclub",
            "type":"Food & Drink"
        }
    ],
    "sg:phone":"+1 973 455 0200",
    "sg:postcode":"07960",
    "sg:province":"NJ",
    "sg:tags":[
        "nightlife"
    ],
    "wof:name":"Dark Horse Lounge",
    "wof:placetype":"venue"
},
  "geometry": {"coordinates":[-74.480377,40.795459],"type":"Point"}
}