{
  "type": "Feature",
  "properties": {
    "addr:full":"629 Grove St Ridgewood NJ 07450",
    "addr:housenumber":"629",
    "addr:postcode":"07450",
    "addr:street":"Grove St",
    "iso:country":"US",
    "sg:address":"629 Grove St",
    "sg:city":"Ridgewood",
    "sg:classifiers":[
        {
            "category":"Banks & Credit Unions",
            "subcategory":"Investment Brokerage",
            "type":"Services"
        }
    ],
    "sg:phone":"+1 201 652 8529",
    "sg:postcode":"07450",
    "sg:province":"NJ",
    "sg:tags":[
        "security",
        "management",
        "consulting"
    ],
    "wof:name":"Stanford Investment Group Inc",
    "wof:placetype":"venue"
},
  "geometry": {"coordinates":[-74.101797,40.966792],"type":"Point"}
}