{
  "type": "Feature",
  "properties": {
    "iso:country":"US",
    "sg:address":"12 Knightswood Dr",
    "sg:city":"Marlton",
    "sg:classifiers":[
        {
            "category":"Building & Trades",
            "subcategory":"Construction",
            "type":"Services"
        }
    ],
    "sg:phone":"+1 856 985 5855",
    "sg:postcode":"08053",
    "sg:province":"NJ",
    "sg:tags":[
        "house"
    ],
    "wof:name":"Handy Husband",
    "wof:placetype":"venue"
},
  "geometry": {"coordinates":[-74.903357,39.881414],"type":"Point"}
}