{
  "type": "Feature",
  "properties": {
    "addr:full":"1 Chopin Ct Jersey City NJ 07302",
    "addr:housenumber":"1",
    "addr:postcode":"07302",
    "addr:street":"Chopin Ct",
    "iso:country":"US",
    "sg:address":"1 Chopin Ct",
    "sg:city":"Jersey City",
    "sg:classifiers":[
        {
            "category":"Health Services",
            "subcategory":"Doctor",
            "type":"Services"
        }
    ],
    "sg:phone":"+1 201 200 0318",
    "sg:postcode":"07302",
    "sg:province":"NJ",
    "sg:tags":[
        "physician",
        "surgeon"
    ],
    "wof:name":"Cardiovascular Associates",
    "wof:placetype":"venue"
},
  "geometry": {"coordinates":[-74.05637900000001,40.72135],"type":"Point"}
}