{
  "type": "Feature",
  "properties": {
    "addr:full":"232 Morris Ave Springfield NJ 07081",
    "addr:housenumber":"232",
    "addr:postcode":"07081",
    "addr:street":"Morris Ave",
    "iso:country":"US",
    "sg:address":"232 Morris Ave",
    "sg:city":"Springfield",
    "sg:classifiers":[
        {
            "category":"Professional",
            "type":"Services"
        }
    ],
    "sg:phone":"+1 973 467 9171",
    "sg:postcode":"07081",
    "sg:province":"NJ",
    "sg:tags":[
        "establishment"
    ],
    "wof:name":"Lasting Impressions",
    "wof:placetype":"venue"
},
  "geometry": {"coordinates":[-74.312279,40.711325],"type":"Point"}
}