{
  "type": "Feature",
  "properties": {
    "iso:country":"US",
    "sg:address":"726 Anderson Ave",
    "sg:city":"Cliffside Park",
    "sg:classifiers":[
        {
            "category":"Personal",
            "subcategory":"Beauty Salon",
            "type":"Services"
        }
    ],
    "sg:phone":"+1 201 945 9115",
    "sg:postcode":"07010",
    "sg:province":"NJ",
    "sg:tags":[
        "nail",
        "shop"
    ],
    "wof:name":"Finger Fitness Nail Salon",
    "wof:placetype":"venue"
},
  "geometry": {"coordinates":[-73.985985,40.829529],"type":"Point"}
}