{
  "type": "Feature",
  "properties": {
    "addr:full":"7 Woodside Rd Springfield NJ 07081",
    "addr:housenumber":"7",
    "addr:postcode":"07081",
    "addr:street":"Woodside Rd",
    "iso:country":"US",
    "sg:address":"7 Woodside Rd",
    "sg:city":"Springfield",
    "sg:classifiers":[
        {
            "category":"Professional",
            "subcategory":"Business Services",
            "type":"Services"
        }
    ],
    "sg:phone":"+1 973 258 4040",
    "sg:postcode":"07081",
    "sg:province":"NJ",
    "sg:tags":[
        "process",
        "server"
    ],
    "sg:website":"www.professionalprocessservice.com",
    "wof:name":"Consolidated Legal Support Svc",
    "wof:placetype":"venue"
},
  "geometry": {"coordinates":[-74.314943,40.695597],"type":"Point"}
}