{
  "type": "Feature",
  "properties": {
    "addr:full":"131 Seaview Dr Secaucus NJ 07094",
    "addr:housenumber":"131",
    "addr:postcode":"07094",
    "addr:street":"Seaview Dr",
    "iso:country":"US",
    "sg:address":"131 Seaview Dr",
    "sg:city":"Secaucus",
    "sg:classifiers":[
        {
            "category":"Freight",
            "type":"Transportation"
        }
    ],
    "sg:phone":"+1 201 319 0860",
    "sg:postcode":"07094",
    "sg:province":"NJ",
    "sg:tags":[
        "operator",
        "local",
        "trucking"
    ],
    "wof:name":"Fedex",
    "wof:placetype":"venue"
},
  "geometry": {"coordinates":[-74.078086,40.77198],"type":"Point"}
}