{
  "type": "Feature",
  "properties": {
    "iso:country":"US",
    "sg:address":"23 Stanwood Ct",
    "sg:city":"Medford",
    "sg:classifiers":[
        {
            "category":"Professional",
            "subcategory":"Computer Services",
            "type":"Services"
        }
    ],
    "sg:phone":"+1 609 654 2641",
    "sg:postcode":"08055",
    "sg:province":"NJ",
    "wof:name":"Netimetry LLC",
    "wof:placetype":"venue"
},
  "geometry": {"coordinates":[-74.842703,39.875018],"type":"Point"}
}