{
  "type": "Feature",
  "properties": {
    "iso:country":"US",
    "sg:address":"203 Main St",
    "sg:city":"New Milford",
    "sg:classifiers":[
        {
            "category":"Restaurant",
            "type":"Food & Drink"
        }
    ],
    "sg:phone":"+1 201 265 0515",
    "sg:postcode":"07646",
    "sg:province":"NJ",
    "wof:name":"Lieto Italia Ristorante",
    "wof:placetype":"venue"
},
  "geometry": {"coordinates":[-74.01951,40.94573],"type":"Point"}
}