{
  "type": "Feature",
  "properties": {
    "addr:full":"1209 Omaha Rd North Brunswick NJ 08902",
    "addr:housenumber":"1209",
    "addr:postcode":"08902",
    "addr:street":"Omaha Rd",
    "iso:country":"US",
    "sg:address":"1209 Omaha Rd",
    "sg:city":"North Brunswick",
    "sg:classifiers":[
        {
            "category":"Building & Trades",
            "subcategory":"Construction",
            "type":"Services"
        }
    ],
    "sg:phone":"+1 732 846 7764",
    "sg:postcode":"08902",
    "sg:province":"NJ",
    "sg:tags":[
        "hanging",
        "contractor"
    ],
    "wof:name":"T Maggio Painting",
    "wof:placetype":"venue"
},
  "geometry": {"coordinates":[-74.48596000000001,40.46496],"type":"Point"}
}