{
  "type": "Feature",
  "properties": {
    "addr:full":"305 Pompton Ave Pompton Lakes NJ 07442",
    "addr:housenumber":"305",
    "addr:postcode":"07442",
    "addr:street":"Pompton Ave",
    "iso:country":"US",
    "sg:address":"305 Pompton Ave",
    "sg:city":"Pompton Lakes",
    "sg:classifiers":[
        {
            "category":"Banks & Credit Unions",
            "subcategory":"Financial Services",
            "type":"Services"
        }
    ],
    "sg:phone":"+1 973 835 3660",
    "sg:postcode":"07442",
    "sg:province":"NJ",
    "sg:tags":[
        "broker",
        "mortgage"
    ],
    "wof:name":"Lindsay Mortgage Temps",
    "wof:placetype":"venue"
},
  "geometry": {"coordinates":[-74.284401,41.002602],"type":"Point"}
}