{
  "type": "Feature",
  "properties": {
    "addr:full":"1 Cypress Ave North Brunswick NJ 08902",
    "addr:housenumber":"1",
    "addr:postcode":"08902",
    "addr:street":"Cypress Ave",
    "iso:country":"US",
    "sg:address":"1 Cypress Ave",
    "sg:city":"North Brunswick",
    "sg:classifiers":[
        {
            "category":"Building & Trades",
            "subcategory":"Cleaning & Sanitation",
            "type":"Services"
        }
    ],
    "sg:phone":"+1   ",
    "sg:postcode":"08902",
    "sg:province":"NJ",
    "sg:tags":[
        "maintenance"
    ],
    "wof:name":"Dmb Building Services Inc",
    "wof:placetype":"venue"
},
  "geometry": {"coordinates":[-74.45737099999999,40.469637],"type":"Point"}
}