{
  "type": "Feature",
  "properties": {
    "addr:full":"8 Bartha Ave Edison NJ 08817",
    "addr:housenumber":"8",
    "addr:postcode":"08817",
    "addr:street":"Bartha Ave",
    "iso:country":"US",
    "sg:address":"8 Bartha Ave",
    "sg:city":"Edison",
    "sg:classifiers":[
        {
            "category":"Manufacturing",
            "subcategory":"Food",
            "type":"Manufacturing & Wholesale Goods"
        }
    ],
    "sg:phone":"+1 732 317 2298",
    "sg:postcode":"08817",
    "sg:province":"NJ",
    "sg:tags":[
        "product",
        "dairy",
        "mfg"
    ],
    "wof:name":"Metabev Inc",
    "wof:placetype":"venue"
},
  "geometry": {"coordinates":[-74.42215,40.515647],"type":"Point"}
}