{
  "type": "Feature",
  "properties": {
    "addr:full":"5756 Berkshire Valley Rd Oak Ridge NJ 07438",
    "addr:housenumber":"5756",
    "addr:postcode":"07438",
    "addr:street":"Berkshire Valley Rd",
    "iso:country":"US",
    "sg:address":"5756 Berkshire Valley Rd",
    "sg:city":"Oak Ridge",
    "sg:classifiers":[
        {
            "category":"Restaurant",
            "type":"Food & Drink"
        }
    ],
    "sg:menulink":"http://www.allmenus.com/nj/jefferson/146170-subway/menu/",
    "sg:phone":"+1 973 208 3331",
    "sg:postcode":"07438",
    "sg:province":"NJ",
    "sg:tags":[
        "american",
        "sandwich"
    ],
    "wof:name":"Subway",
    "wof:placetype":"venue"
},
  "geometry": {"coordinates":[-74.503608,41.038228],"type":"Point"}
}