{
  "type": "Feature",
  "properties": {
    "iso:country":"US",
    "sg:address":"144 E Spicer Ave",
    "sg:city":"Wildwood",
    "sg:classifiers":[
        {
            "category":"Manufacturing",
            "subcategory":"Tools & Machinery",
            "type":"Manufacturing & Wholesale Goods"
        }
    ],
    "sg:phone":"+1 609 729 8225",
    "sg:postcode":"08260",
    "sg:province":"NJ",
    "sg:tags":[
        "protection",
        "system",
        "power"
    ],
    "wof:name":"Deltech Electronics Inc",
    "wof:placetype":"venue"
},
  "geometry": {"coordinates":[-74.817488,38.988302],"type":"Point"}
}