{
  "type": "Feature",
  "properties": {
    "iso:country":"US",
    "sg:address":"221 Madison Ave",
    "sg:city":"Morristown",
    "sg:classifiers":[
        {
            "category":"Banks & Credit Unions",
            "subcategory":"Bank",
            "type":"Services"
        }
    ],
    "sg:phone":"+1 973 984 3250",
    "sg:postcode":"07960",
    "sg:province":"NJ",
    "wof:name":"T D Bank North",
    "wof:placetype":"venue"
},
  "geometry": {"coordinates":[-74.453784,40.785729],"type":"Point"}
}