{
  "type": "Feature",
  "properties": {
    "iso:country":"US",
    "sg:address":"87 Hibernia Ave",
    "sg:city":"Rockaway",
    "sg:classifiers":[
        {
            "category":"Professional",
            "subcategory":"Business Services",
            "type":"Services"
        }
    ],
    "sg:phone":"+1 973 625 8900",
    "sg:postcode":"07866",
    "sg:province":"NJ",
    "sg:tags":[
        "drafting"
    ],
    "wof:name":"Spartan Design",
    "wof:placetype":"venue"
},
  "geometry": {"coordinates":[-74.505385,40.907217],"type":"Point"}
}