{
  "type": "Feature",
  "properties": {
    "addr:full":"128 Station St Berkeley Heights NJ 07922",
    "addr:housenumber":"128",
    "addr:postcode":"07922",
    "addr:street":"Station St",
    "iso:country":"US",
    "sg:address":"128 Station St",
    "sg:city":"Berkeley Heights",
    "sg:classifiers":[
        {
            "category":"Building & Trades",
            "subcategory":"Locksmith",
            "type":"Services"
        }
    ],
    "sg:phone":"+1 888 277 6174",
    "sg:postcode":"07922",
    "sg:province":"NJ",
    "sg:tags":[
        "key"
    ],
    "wof:name":"7 Day 24 Hour Emergency Locksmith",
    "wof:placetype":"venue"
},
  "geometry": {"coordinates":[-74.443725,40.682803],"type":"Point"}
}