{
  "type": "Feature",
  "properties": {
    "addr:full":"1241 Clinton Pl Elizabeth NJ 07208",
    "addr:housenumber":"1241",
    "addr:postcode":"07208",
    "addr:street":"Clinton Pl",
    "iso:country":"US",
    "sg:address":"1241 Clinton Pl",
    "sg:city":"Elizabeth",
    "sg:classifiers":[
        {
            "category":"Banks & Credit Unions",
            "subcategory":"Financial Services",
            "type":"Services"
        }
    ],
    "sg:phone":"+1 908 469 0725",
    "sg:postcode":"07208",
    "sg:province":"NJ",
    "sg:tags":[
        "broker",
        "mortgage"
    ],
    "wof:name":"Sunshine Mngmt and Consl",
    "wof:placetype":"venue"
},
  "geometry": {"coordinates":[-74.210556,40.680292],"type":"Point"}
}