{
  "type": "Feature",
  "properties": {
    "iso:country":"US",
    "sg:address":"80 Fox Hollow Rd",
    "sg:city":"Sparta",
    "sg:classifiers":[
        {
            "category":"Professional",
            "subcategory":"Business Services",
            "type":"Services"
        }
    ],
    "sg:phone":"+1   ",
    "sg:postcode":"07871",
    "sg:province":"NJ",
    "wof:name":"Dragonfly Enterprises",
    "wof:placetype":"venue"
},
  "geometry": {"coordinates":[-74.66628900000001,41.042984],"type":"Point"}
}