{
  "type": "Feature",
  "properties": {
    "addr:full":"23 Anderson St Trenton NJ 08611",
    "addr:housenumber":"23",
    "addr:postcode":"08611",
    "addr:street":"Anderson St",
    "iso:country":"US",
    "sg:address":"23 Anderson St",
    "sg:city":"Trenton",
    "sg:classifiers":[
        {
            "category":"Restaurant",
            "type":"Food & Drink"
        }
    ],
    "sg:phone":"+1 609 989 1242",
    "sg:postcode":"08611",
    "sg:province":"NJ",
    "sg:tags":[
        "eating"
    ],
    "wof:name":"Jeppy's Pizzeria",
    "wof:placetype":"venue"
},
  "geometry": {"coordinates":[-74.744522,40.215847],"type":"Point"}
}