{
  "type": "Feature",
  "properties": {
    "iso:country":"US",
    "sg:address":"760 Ringwood Ave",
    "sg:city":"Pompton Lakes",
    "sg:classifiers":[
        {
            "category":"Wholesale",
            "subcategory":"Computers",
            "type":"Manufacturing & Wholesale Goods"
        },
        {
            "category":"Professional",
            "subcategory":"Computer Services",
            "type":"Services"
        }
    ],
    "sg:phone":"+1 973 616 8264",
    "sg:postcode":"07442",
    "sg:province":"NJ",
    "sg:tags":[
        "repair"
    ],
    "wof:name":"Pompton Lakes It Grp",
    "wof:placetype":"venue"
},
  "geometry": {"coordinates":[-74.29499800000001,40.999401],"type":"Point"}
}