{
  "type": "Feature",
  "properties": {
    "addr:full":"1411 Blackwood Clementon Rd Clementon NJ 08021",
    "addr:housenumber":"1411",
    "addr:postcode":"08021",
    "addr:street":"Blackwood Clementon Rd",
    "iso:country":"US",
    "sg:address":"1411 Blackwood Clementon Rd",
    "sg:city":"Clementon",
    "sg:classifiers":[
        {
            "category":"Retail",
            "subcategory":"Laundry & Dry Cleaning",
            "type":"Services"
        }
    ],
    "sg:phone":"+1 856 782 9660",
    "sg:postcode":"08021",
    "sg:province":"NJ",
    "sg:tags":[
        "cleaners"
    ],
    "wof:name":"4-H Dry Cleaners",
    "wof:placetype":"venue"
},
  "geometry": {"coordinates":[-75.041524,39.803385],"type":"Point"}
}