{
  "type": "Feature",
  "properties": {
    "iso:country":"US",
    "sg:address":"355 Varick St",
    "sg:city":"Jersey City",
    "sg:classifiers":[
        {
            "category":"Food & Beverages",
            "subcategory":"Liquor & Beverages",
            "type":"Retail Goods"
        }
    ],
    "sg:phone":"+1 201 451 3336",
    "sg:postcode":"07302",
    "sg:province":"NJ",
    "sg:tags":[
        "beer",
        "spirit",
        "wine"
    ],
    "wof:name":"Manna Liquor Corporation",
    "wof:placetype":"venue"
},
  "geometry": {"coordinates":[-74.0485,40.721001],"type":"Point"}
}