{
  "type": "Feature",
  "properties": {
    "iso:country":"US",
    "sg:address":"107 Forman Ave",
    "sg:city":"Pt Pleasant Bch",
    "sg:classifiers":[
        {
            "category":"Building & Trades",
            "subcategory":"Construction",
            "type":"Services"
        }
    ],
    "sg:phone":"+1 732 295 3408",
    "sg:postcode":"08742",
    "sg:province":"NJ",
    "sg:tags":[
        "designer",
        "marine",
        "contractor"
    ],
    "wof:name":"Ocean Marine Svc",
    "wof:placetype":"venue"
},
  "geometry": {"coordinates":[-74.04164,40.089503],"type":"Point"}
}