{
  "type": "Feature",
  "properties": {
    "addr:full":"121 Paris Ave Northvale NJ 07647",
    "addr:housenumber":"121",
    "addr:postcode":"07647",
    "addr:street":"Paris Ave",
    "iso:country":"US",
    "sg:address":"121 Paris Ave",
    "sg:city":"Northvale",
    "sg:classifiers":[
        {
            "category":"Personal",
            "subcategory":"Beauty Salon",
            "type":"Services"
        }
    ],
    "sg:phone":"+1 201 768 8969",
    "sg:postcode":"07647",
    "sg:province":"NJ",
    "sg:tags":[
        "nail",
        "shop",
        "manicuring"
    ],
    "wof:name":"Paris Nails",
    "wof:placetype":"venue"
},
  "geometry": {"coordinates":[-73.95143899999999,41.007599],"type":"Point"}
}