{
  "type": "Feature",
  "properties": {
    "iso:country":"US",
    "sg:address":"113 Woodside Ave",
    "sg:city":"Rockaway",
    "sg:classifiers":[
        {
            "category":"Home & Garden",
            "subcategory":"Furniture",
            "type":"Retail Goods"
        }
    ],
    "sg:phone":"+1 908 850 6060",
    "sg:postcode":"07866",
    "sg:province":"NJ",
    "wof:name":"Summer Styles Outdoor Furn",
    "wof:placetype":"venue"
},
  "geometry": {"coordinates":[-74.51146,40.909845],"type":"Point"}
}