{
  "type": "Feature",
  "properties": {
    "iso:country":"US",
    "sg:address":"215 Wilson Ave",
    "sg:city":"Newark",
    "sg:classifiers":[
        {
            "category":"Travel",
            "subcategory":"Travel Agent",
            "type":"Entertainment"
        }
    ],
    "sg:phone":"+1 973 344 6191",
    "sg:postcode":"07105",
    "sg:province":"NJ",
    "sg:tags":[
        "agency",
        "bureau"
    ],
    "wof:name":"Imex Tours Inc",
    "wof:placetype":"venue"
},
  "geometry": {"coordinates":[-74.148055,40.720924],"type":"Point"}
}