{
  "type": "Feature",
  "properties": {
    "addr:full":"82 Fort Dix St Wrightstown NJ 08562",
    "addr:housenumber":"82",
    "addr:postcode":"08562",
    "addr:street":"Fort Dix St",
    "iso:country":"US",
    "sg:address":"82 Fort Dix St",
    "sg:city":"Wrightstown",
    "sg:classifiers":[
        {
            "category":"Building & Trades",
            "subcategory":"Plumbing",
            "type":"Services"
        }
    ],
    "sg:phone":"+1 609 723 3663",
    "sg:postcode":"08562",
    "sg:province":"NJ",
    "sg:tags":[
        "mechanical",
        "contractor"
    ],
    "wof:name":"K B Mechanical",
    "wof:placetype":"venue"
},
  "geometry": {"coordinates":[-74.61790999999999,40.037212],"type":"Point"}
}