{
  "type": "Feature",
  "properties": {
    "iso:country":"US",
    "sg:address":"230 Hamilton St",
    "sg:city":"Bound Brook",
    "sg:classifiers":[
        {
            "category":"Manufacturing",
            "subcategory":"Lumber",
            "type":"Manufacturing & Wholesale Goods"
        }
    ],
    "sg:phone":"+1 732 356 3732",
    "sg:postcode":"08805",
    "sg:province":"NJ",
    "sg:tags":[
        "forestry"
    ],
    "wof:name":"Brook Bound Fire Dept",
    "wof:placetype":"venue"
},
  "geometry": {"coordinates":[-74.529667,40.56441],"type":"Point"}
}