{
  "type": "Feature",
  "properties": {
    "addr:full":"11 Jacobus Ave Wayne NJ 07470",
    "addr:housenumber":"11",
    "addr:postcode":"07470",
    "addr:street":"Jacobus Ave",
    "iso:country":"US",
    "sg:address":"11 Jacobus Ave",
    "sg:city":"Wayne",
    "sg:classifiers":[
        {
            "category":"Building & Trades",
            "subcategory":"Electrical",
            "type":"Services"
        }
    ],
    "sg:phone":"+1 973 628 6001",
    "sg:postcode":"07470",
    "sg:province":"NJ",
    "sg:tags":[
        "electrical",
        "contractor"
    ],
    "wof:name":"Windward Contracting Corp",
    "wof:placetype":"venue"
},
  "geometry": {"coordinates":[-74.251909,40.919196],"type":"Point"}
}