{
  "type": "Feature",
  "properties": {
    "addr:full":"1324 South Ave Plainfield NJ 07062",
    "addr:housenumber":"1324",
    "addr:postcode":"07062",
    "addr:street":"South Ave",
    "iso:country":"US",
    "sg:address":"1324 South Ave",
    "sg:city":"Plainfield",
    "sg:classifiers":[
        {
            "category":"Restaurant",
            "type":"Food & Drink"
        }
    ],
    "sg:phone":"+1 908 756 7900",
    "sg:postcode":"07062",
    "sg:province":"NJ",
    "wof:name":"Rena's Diner",
    "wof:placetype":"venue"
},
  "geometry": {"coordinates":[-74.39979599999999,40.630257],"type":"Point"}
}