{
  "type": "Feature",
  "properties": {
    "addr:full":"1 Main St Eatontown NJ 07724",
    "addr:housenumber":"1",
    "addr:postcode":"07724",
    "addr:street":"Main St",
    "iso:country":"US",
    "sg:address":"1 Main St",
    "sg:city":"Eatontown",
    "sg:classifiers":[
        {
            "category":"Wholesale",
            "subcategory":"Non-durable Goods",
            "type":"Manufacturing & Wholesale Goods"
        }
    ],
    "sg:phone":"+1 732 544 8083",
    "sg:postcode":"07724",
    "sg:province":"NJ",
    "sg:tags":[
        "sell",
        "buy",
        "inventory"
    ],
    "wof:name":"Dealco Inc",
    "wof:placetype":"venue"
},
  "geometry": {"coordinates":[-74.059321,40.303801],"type":"Point"}
}