{
  "type": "Feature",
  "properties": {
    "iso:country":"US",
    "sg:address":"1 Church St",
    "sg:city":"Raritan",
    "sg:classifiers":[
        {
            "category":"Retail",
            "subcategory":"Repair Shop",
            "type":"Services"
        }
    ],
    "sg:phone":"+1   ",
    "sg:postcode":"08869",
    "sg:province":"NJ",
    "wof:name":"24 Hour Emergency Locksmith",
    "wof:placetype":"venue"
},
  "geometry": {"coordinates":[-74.63708699999999,40.56881],"type":"Point"}
}