{
  "type": "Feature",
  "properties": {
    "iso:country":"US",
    "sg:address":"20 Jersey Ave",
    "sg:city":"New Brunswick",
    "sg:classifiers":[
        {
            "category":"Shopping",
            "subcategory":"Pharmacy",
            "type":"Retail Goods"
        }
    ],
    "sg:phone":"+1 732 846 9338",
    "sg:postcode":"08901",
    "sg:province":"NJ",
    "wof:name":"Walgreens",
    "wof:placetype":"venue"
},
  "geometry": {"coordinates":[-74.45494600000001,40.491061],"type":"Point"}
}