{
  "type": "Feature",
  "properties": {
    "iso:country":"US",
    "sg:address":"588 Shiloh Pike",
    "sg:city":"Bridgeton",
    "sg:classifiers":[
        {
            "category":"Autos & Motor Vehicles",
            "subcategory":"Recreational Vehicle Sales",
            "type":"Retail Goods"
        }
    ],
    "sg:phone":"+1 856 455 9474",
    "sg:postcode":"08302",
    "sg:province":"NJ",
    "wof:name":"Cruise America",
    "wof:placetype":"venue"
},
  "geometry": {"coordinates":[-75.26463,39.439825],"type":"Point"}
}