{
  "type": "Feature",
  "properties": {
    "iso:country":"US",
    "sg:address":"86 Steiner Ave",
    "sg:city":"Neptune City",
    "sg:classifiers":[
        {
            "category":"Building & Trades",
            "subcategory":"Pest Control",
            "type":"Services"
        }
    ],
    "sg:phone":"+1 732 775 1456",
    "sg:postcode":"07753",
    "sg:province":"NJ",
    "wof:name":"Formulated Pest Control Svc",
    "wof:placetype":"venue"
},
  "geometry": {"coordinates":[-74.023881,40.197131],"type":"Point"}
}