{
  "type": "Feature",
  "properties": {
    "addr:full":"166 Newark Pompton Tpke Ste 2 Pequannock NJ 07440",
    "addr:housenumber":"166",
    "addr:postcode":"07440",
    "addr:street":"Newark Pompton Tpke Ste 2",
    "iso:country":"US",
    "sg:address":"166 Newark Pompton Tpke Ste 2",
    "sg:city":"Pequannock",
    "sg:classifiers":[
        {
            "category":"Restaurant",
            "type":"Food & Drink"
        }
    ],
    "sg:phone":"+1 973 696 4900",
    "sg:postcode":"07440",
    "sg:province":"NJ",
    "sg:tags":[
        "pizza",
        "italian"
    ],
    "wof:name":"Ameti's Gourmet Pizza",
    "wof:placetype":"venue"
},
  "geometry": {"coordinates":[-74.287695,40.946967],"type":"Point"}
}