{
  "type": "Feature",
  "properties": {
    "iso:country":"US",
    "sg:address":"6 Walnut St W",
    "sg:city":"Mahwah",
    "sg:classifiers":[
        {
            "category":"Health Services",
            "subcategory":"Doctor",
            "type":"Services"
        }
    ],
    "sg:phone":"+1   ",
    "sg:postcode":"07430",
    "sg:province":"NJ",
    "sg:tags":[
        "medical"
    ],
    "wof:name":"Shanti Dhupar MD",
    "wof:placetype":"venue"
},
  "geometry": {"coordinates":[-74.16559100000001,41.034749],"type":"Point"}
}