{
  "type": "Feature",
  "properties": {
    "iso:country":"US",
    "sg:address":"1806 Park Ave",
    "sg:city":"Weehawken",
    "sg:classifiers":[
        {
            "category":"Education",
            "subcategory":"Music School",
            "type":"Public Place"
        }
    ],
    "sg:phone":"+1 201 864 5666",
    "sg:postcode":"07086",
    "sg:province":"NJ",
    "sg:tags":[
        "instrument",
        "teacher",
        "musical"
    ],
    "wof:name":"Supersonic Transport Inc",
    "wof:placetype":"venue"
},
  "geometry": {"coordinates":[-74.02330000000001,40.7686],"type":"Point"}
}