{
  "type": "Feature",
  "properties": {
    "iso:country":"US",
    "sg:address":"317 1st St",
    "sg:city":"Middlesex",
    "sg:classifiers":[
        {
            "category":"Building & Trades",
            "subcategory":"Construction",
            "type":"Services"
        }
    ],
    "sg:phone":"+1 732 752 3261",
    "sg:postcode":"08846",
    "sg:province":"NJ",
    "sg:tags":[
        "general",
        "contractor"
    ],
    "wof:name":"D'Ambrosia Home Improvements",
    "wof:placetype":"venue"
},
  "geometry": {"coordinates":[-74.491854,40.584315],"type":"Point"}
}