{
  "type": "Feature",
  "properties": {
    "addr:full":"70 Sunrise Dr Gillette NJ 07933",
    "addr:housenumber":"70",
    "addr:postcode":"07933",
    "addr:street":"Sunrise Dr",
    "iso:country":"US",
    "sg:address":"70 Sunrise Dr",
    "sg:city":"Gillette",
    "sg:classifiers":[
        {
            "category":"Professional",
            "subcategory":"Lawyer & Legal Services",
            "type":"Services"
        }
    ],
    "sg:phone":"+1 908 604 0039",
    "sg:postcode":"07933",
    "sg:province":"NJ",
    "wof:name":"George L Mahr II Llc of Councel Mahr and Mahr Llc",
    "wof:placetype":"venue"
},
  "geometry": {"coordinates":[-74.46872999999999,40.671847],"type":"Point"}
}