{
  "type": "Feature",
  "properties": {
    "addr:full":"60 Kingsbridge Rd Piscataway NJ 08854",
    "addr:housenumber":"60",
    "addr:postcode":"08854",
    "addr:street":"Kingsbridge Rd",
    "iso:country":"US",
    "sg:address":"60 Kingsbridge Rd",
    "sg:city":"Piscataway",
    "sg:classifiers":[
        {
            "category":"Wholesale",
            "subcategory":"Electrical",
            "type":"Manufacturing & Wholesale Goods"
        }
    ],
    "sg:phone":"+1 732 381 0500",
    "sg:postcode":"08854",
    "sg:province":"NJ",
    "sg:tags":[
        "supply"
    ],
    "wof:name":"Gaffney-Kroese Elec Sup Corp",
    "wof:placetype":"venue"
},
  "geometry": {"coordinates":[-74.49573100000001,40.546338],"type":"Point"}
}