{
  "type": "Feature",
  "properties": {
    "iso:country":"US",
    "sg:address":"72 Sofia Dr",
    "sg:city":"Blackwood",
    "sg:classifiers":[
        {
            "category":"Wholesale",
            "subcategory":"Fruits & Vegetables",
            "type":"Manufacturing & Wholesale Goods"
        }
    ],
    "sg:phone":"+1 856 566 1615",
    "sg:postcode":"08012",
    "sg:province":"NJ",
    "wof:name":"M & R Produce Distributors Inc",
    "wof:placetype":"venue"
},
  "geometry": {"coordinates":[-75.039051,39.844722],"type":"Point"}
}