{
  "type": "Feature",
  "properties": {
    "addr:full":"6 Wichita Path Oakland NJ 07436",
    "addr:housenumber":"6",
    "addr:postcode":"07436",
    "addr:street":"Wichita Path",
    "iso:country":"US",
    "sg:address":"6 Wichita Path",
    "sg:city":"Oakland",
    "sg:classifiers":[
        {
            "category":"Manufacturing",
            "subcategory":"Rubber & Plastics",
            "type":"Manufacturing & Wholesale Goods"
        }
    ],
    "sg:phone":"+1 201 337 5699",
    "sg:postcode":"07436",
    "sg:province":"NJ",
    "sg:tags":[
        "product",
        "mfg"
    ],
    "wof:name":"Masterpiece Molding LLC",
    "wof:placetype":"venue"
},
  "geometry": {"coordinates":[-74.208907,41.04055],"type":"Point"}
}