{
  "type": "Feature",
  "properties": {
    "addr:full":"1212 Royal Sire Ct Toms River NJ 08755",
    "addr:housenumber":"1212",
    "addr:postcode":"08755",
    "addr:street":"Royal Sire Ct",
    "iso:country":"US",
    "sg:address":"1212 Royal Sire Ct",
    "sg:city":"Toms River",
    "sg:classifiers":[
        {
            "category":"Professional",
            "type":"Services"
        }
    ],
    "sg:phone":"+1   ",
    "sg:postcode":"08755",
    "sg:province":"NJ",
    "wof:name":"Tsunami Inc",
    "wof:placetype":"venue"
},
  "geometry": {"coordinates":[-74.208973,40.042804],"type":"Point"}
}