{
  "type": "Feature",
  "properties": {
    "iso:country":"US",
    "sg:address":"76 Tuckahoe Rd",
    "sg:city":"Dorothy",
    "sg:classifiers":[
        {
            "category":"Professional",
            "subcategory":"Management & Consulting",
            "type":"Services"
        }
    ],
    "sg:phone":"+1   ",
    "sg:postcode":"08317",
    "sg:province":"NJ",
    "sg:tags":[
        "business"
    ],
    "wof:name":"Santana Enterprises",
    "wof:placetype":"venue"
},
  "geometry": {"coordinates":[-74.82373,39.400013],"type":"Point"}
}