{
  "type": "Feature",
  "properties": {
    "addr:full":"237 Hanson Ave Piscataway NJ 08854",
    "addr:housenumber":"237",
    "addr:postcode":"08854",
    "addr:street":"Hanson Ave",
    "iso:country":"US",
    "sg:address":"237 Hanson Ave",
    "sg:city":"Piscataway",
    "sg:classifiers":[
        {
            "category":"Real Estate",
            "subcategory":"Real Estate Agent",
            "type":"Services"
        }
    ],
    "sg:phone":"+1 732 235 0300",
    "sg:postcode":"08854",
    "sg:province":"NJ",
    "wof:name":"Umex International Co Inc",
    "wof:placetype":"venue"
},
  "geometry": {"coordinates":[-74.48188399999999,40.528341],"type":"Point"}
}