{
  "type": "Feature",
  "properties": {
    "addr:full":"1500 State Rte 47 Rio Grande NJ 08242",
    "addr:housenumber":"1500",
    "addr:postcode":"08242",
    "addr:street":"State Rte 47",
    "iso:country":"US",
    "sg:address":"1500 State Rte 47",
    "sg:city":"Rio Grande",
    "sg:classifiers":[
        {
            "category":"Shopping",
            "subcategory":"Discount & Variety Stores",
            "type":"Retail Goods"
        }
    ],
    "sg:phone":"+1   ",
    "sg:postcode":"08242",
    "sg:province":"NJ",
    "sg:website":"www.dollartree.com",
    "wof:name":"Dollar Tree",
    "wof:placetype":"venue"
},
  "geometry": {"coordinates":[-74.872782,39.012609],"type":"Point"}
}