{
  "type": "Feature",
  "properties": {
    "addr:full":"409 Minnisink Rd Totowa NJ 07512",
    "addr:housenumber":"409",
    "addr:postcode":"07512",
    "addr:street":"Minnisink Rd",
    "iso:country":"US",
    "sg:address":"409 Minnisink Rd",
    "sg:city":"Totowa",
    "sg:classifiers":[
        {
            "category":"Building & Trades",
            "subcategory":"Construction",
            "type":"Services"
        }
    ],
    "sg:phone":"+1 973 785 0422",
    "sg:postcode":"07512",
    "sg:province":"NJ",
    "sg:tags":[
        "general",
        "contractor"
    ],
    "wof:name":"Data Site Constructors",
    "wof:placetype":"venue"
},
  "geometry": {"coordinates":[-74.236456,40.8956],"type":"Point"}
}