{
  "type": "Feature",
  "properties": {
    "addr:full":"311 Queen Anne Rd Teaneck NJ 07666",
    "addr:housenumber":"311",
    "addr:postcode":"07666",
    "addr:street":"Queen Anne Rd",
    "iso:country":"US",
    "sg:address":"311 Queen Anne Rd",
    "sg:city":"Teaneck",
    "sg:classifiers":[
        {
            "category":"Building & Trades",
            "subcategory":"Construction",
            "type":"Services"
        }
    ],
    "sg:phone":"+1 212 873 9687",
    "sg:postcode":"07666",
    "sg:province":"NJ",
    "sg:tags":[
        "hanging",
        "contractor"
    ],
    "wof:name":"Theodore Pedell",
    "wof:placetype":"venue"
},
  "geometry": {"coordinates":[-74.020955,40.873914],"type":"Point"}
}