{
  "type": "Feature",
  "properties": {
    "addr:full":"12 State Rte 34 Matawan NJ 07747",
    "addr:housenumber":"12",
    "addr:postcode":"07747",
    "addr:street":"State Rte 34",
    "iso:country":"US",
    "sg:address":"12 State Rte 34",
    "sg:city":"Matawan",
    "sg:classifiers":[
        {
            "category":"Building & Trades",
            "subcategory":"Construction",
            "type":"Services"
        }
    ],
    "sg:phone":"+1 732 583 5544",
    "sg:postcode":"07747",
    "sg:province":"NJ",
    "sg:tags":[
        "demolition",
        "contractor"
    ],
    "wof:name":"Bob's Green Acre",
    "wof:placetype":"venue"
},
  "geometry": {"coordinates":[-74.24879900000001,40.416497],"type":"Point"}
}