{
  "type": "Feature",
  "properties": {
    "addr:full":"270 Fairmount Ave Jersey City NJ 07306",
    "addr:housenumber":"270",
    "addr:postcode":"07306",
    "addr:street":"Fairmount Ave",
    "iso:country":"US",
    "sg:address":"270 Fairmount Ave",
    "sg:city":"Jersey City",
    "sg:classifiers":[
        {
            "category":"Organizations",
            "subcategory":"Community Association",
            "type":"Services"
        }
    ],
    "sg:phone":"+1   ",
    "sg:postcode":"07306",
    "sg:province":"NJ",
    "sg:tags":[
        "shelter",
        "battered"
    ],
    "wof:name":"Womenrising Inc",
    "wof:placetype":"venue"
},
  "geometry": {"coordinates":[-74.069259,40.723885],"type":"Point"}
}