{
  "type": "Feature",
  "properties": {
    "addr:full":"1 Colony Dr Long Branch NJ 07748",
    "addr:housenumber":"1",
    "addr:postcode":"07748",
    "addr:street":"Colony Dr",
    "iso:country":"US",
    "sg:address":"1 Colony Dr",
    "sg:city":"Long Branch",
    "sg:classifiers":[
        {
            "category":"Building & Trades",
            "subcategory":"Landscaping Services",
            "type":"Services"
        }
    ],
    "sg:phone":"+1 732 229 5939",
    "sg:postcode":"07748",
    "sg:province":"NJ",
    "wof:name":"Quality Tree Services",
    "wof:placetype":"venue"
},
  "geometry": {"coordinates":[-74.08828,40.390965],"type":"Point"}
}