{
  "type": "Feature",
  "properties": {
    "iso:country":"US",
    "sg:address":"122 Wall St",
    "sg:city":"West Long Branch",
    "sg:classifiers":[
        {
            "category":"Organizations",
            "subcategory":"Community Association",
            "type":"Services"
        }
    ],
    "sg:phone":"+1 732 229 4773",
    "sg:postcode":"07764",
    "sg:province":"NJ",
    "wof:name":"Jr Order of United Americ",
    "wof:placetype":"venue"
},
  "geometry": {"coordinates":[-74.009654,40.287796],"type":"Point"}
}