{
  "type": "Feature",
  "properties": {
    "iso:country":"US",
    "sg:address":"310 Cedar Ln",
    "sg:city":"Teaneck",
    "sg:classifiers":[
        {
            "category":"Professional",
            "subcategory":"Accounting & Tax Preparation",
            "type":"Services"
        }
    ],
    "sg:phone":"+1 201 692 0300",
    "sg:postcode":"07666",
    "sg:province":"NJ",
    "sg:tags":[
        "accountant"
    ],
    "wof:name":"Stratis Elia CPA",
    "wof:placetype":"venue"
},
  "geometry": {"coordinates":[-74.0159,40.887001],"type":"Point"}
}