{
  "type": "Feature",
  "properties": {
    "addr:full":"10 Grove St Cherry Hill NJ 08002",
    "addr:housenumber":"10",
    "addr:postcode":"08002",
    "addr:street":"Grove St",
    "iso:country":"US",
    "sg:address":"10 Grove St",
    "sg:city":"Cherry Hill",
    "sg:classifiers":[
        {
            "category":"Real Estate",
            "subcategory":"Real Estate Agent",
            "type":"Services"
        }
    ],
    "sg:phone":"+1   ",
    "sg:postcode":"08002",
    "sg:province":"NJ",
    "sg:tags":[
        "commercial",
        "broker"
    ],
    "sg:website":"www.tannaalok.com",
    "wof:name":"Tannenbaum & Aalok",
    "wof:placetype":"venue"
},
  "geometry": {"coordinates":[-75.034308,39.91859],"type":"Point"}
}