{
  "type": "Feature",
  "properties": {
    "iso:country":"US",
    "sg:address":"672 Grant Ave",
    "sg:city":"Maywood",
    "sg:classifiers":[
        {
            "category":"Building & Trades",
            "subcategory":"Construction",
            "type":"Services"
        }
    ],
    "sg:phone":"+1 201 587 9555",
    "sg:postcode":"07607",
    "sg:province":"NJ",
    "sg:tags":[
        "house"
    ],
    "wof:name":"Ron Chin Home Improvements",
    "wof:placetype":"venue"
},
  "geometry": {"coordinates":[-74.063016,40.90862],"type":"Point"}
}