{
  "type": "Feature",
  "properties": {
    "iso:country":"US",
    "sg:address":"58 W Main St",
    "sg:city":"Maple Shade",
    "sg:classifiers":[
        {
            "category":"Education",
            "subcategory":"Special Training",
            "type":"Public Place"
        }
    ],
    "sg:phone":"+1   ",
    "sg:postcode":"08052",
    "sg:province":"NJ",
    "wof:name":"Institute Of Media Arts LLC",
    "wof:placetype":"venue"
},
  "geometry": {"coordinates":[-75.00386399999999,39.955086],"type":"Point"}
}