{
  "type": "Feature",
  "properties": {
    "iso:country":"US",
    "sg:address":"14 Cedar Ridge Rd N",
    "sg:city":"Sussex",
    "sg:classifiers":[
        {
            "category":"Building & Trades",
            "subcategory":"Electrical",
            "type":"Services"
        }
    ],
    "sg:phone":"+1 973 702 3103",
    "sg:postcode":"07461",
    "sg:province":"NJ",
    "sg:tags":[
        "electrical",
        "contractor"
    ],
    "wof:name":"Todd Electric",
    "wof:placetype":"venue"
},
  "geometry": {"coordinates":[-74.523309,41.211021],"type":"Point"}
}