{
  "type": "Feature",
  "properties": {
    "addr:full":"3 Killington Ct Sicklerville NJ 08081",
    "addr:housenumber":"3",
    "addr:postcode":"08081",
    "addr:street":"Killington Ct",
    "iso:country":"US",
    "sg:address":"3 Killington Ct",
    "sg:city":"Sicklerville",
    "sg:classifiers":[
        {
            "category":"Wholesale",
            "subcategory":"Petroleum",
            "type":"Manufacturing & Wholesale Goods"
        }
    ],
    "sg:phone":"+1 856 782 8663",
    "sg:postcode":"08081",
    "sg:province":"NJ",
    "sg:tags":[
        "products-wholesale",
        "manufacturer"
    ],
    "wof:name":"New Jersey Siding And Windows",
    "wof:placetype":"venue"
},
  "geometry": {"coordinates":[-74.991207,39.762723],"type":"Point"}
}