{
  "type": "Feature",
  "properties": {
    "iso:country":"US",
    "sg:address":"228 Willow Ave",
    "sg:city":"Hoboken",
    "sg:classifiers":[
        {
            "category":"Restaurant",
            "type":"Food & Drink"
        }
    ],
    "sg:phone":"+1 201 222 9337",
    "sg:postcode":"07030",
    "sg:province":"NJ",
    "sg:tags":[
        "delicatessen",
        "sandwich"
    ],
    "wof:name":"Willow Deli Plus",
    "wof:placetype":"venue"
},
  "geometry": {"coordinates":[-74.034133,40.73975],"type":"Point"}
}