{
  "type": "Feature",
  "properties": {
    "addr:full":"526 State Rte 73 West Berlin NJ 08091",
    "addr:housenumber":"526",
    "addr:postcode":"08091",
    "addr:street":"State Rte 73",
    "iso:country":"US",
    "sg:address":"526 State Rte 73",
    "sg:city":"West Berlin",
    "sg:classifiers":[
        {
            "category":"Autos & Motor Vehicles",
            "subcategory":"Automobile Sales",
            "type":"Retail Goods"
        }
    ],
    "sg:phone":"+1 856 768 9005",
    "sg:postcode":"08091",
    "sg:province":"NJ",
    "sg:tags":[
        "car",
        "dealer"
    ],
    "wof:name":"Auto Toy Store",
    "wof:placetype":"venue"
},
  "geometry": {"coordinates":[-74.93025799999999,39.813925],"type":"Point"}
}