{
  "type": "Feature",
  "properties": {
    "iso:country":"US",
    "sg:address":"37 Parker Dr",
    "sg:city":"Morris Plains",
    "sg:classifiers":[
        {
            "category":"Building & Trades",
            "subcategory":"Construction",
            "type":"Services"
        }
    ],
    "sg:phone":"+1 973 631 1303",
    "sg:postcode":"07950",
    "sg:province":"NJ",
    "sg:tags":[
        "painter"
    ],
    "wof:name":"Bill Terhune Quality House",
    "wof:placetype":"venue"
},
  "geometry": {"coordinates":[-74.46969799999999,40.830774],"type":"Point"}
}