{
  "type": "Feature",
  "properties": {
    "iso:country":"US",
    "sg:address":"633 N Maple Ave",
    "sg:city":"Maple Shade",
    "sg:classifiers":[
        {
            "category":"Communications",
            "subcategory":"Film & Video Production",
            "type":"Services"
        }
    ],
    "sg:phone":"+1 856 667 6723",
    "sg:postcode":"08052",
    "sg:province":"NJ",
    "sg:tags":[
        "motion"
    ],
    "wof:name":"Flash Productions",
    "wof:placetype":"venue"
},
  "geometry": {"coordinates":[-75.004152,39.963481],"type":"Point"}
}