{
  "type": "Feature",
  "properties": {
    "iso:country":"US",
    "sg:address":"344 Clifton Ave",
    "sg:city":"Clifton",
    "sg:classifiers":[
        {
            "category":"Health Services",
            "subcategory":"Doctor",
            "type":"Services"
        }
    ],
    "sg:phone":"+1 973 472 0776",
    "sg:postcode":"07011",
    "sg:province":"NJ",
    "sg:tags":[
        "medical"
    ],
    "wof:name":"Almora Medical",
    "wof:placetype":"venue"
},
  "geometry": {"coordinates":[-74.14041899999999,40.875269],"type":"Point"}
}