{
  "type": "Feature",
  "properties": {
    "addr:full":"19 W Front St Red Bank NJ 07701",
    "addr:housenumber":"19",
    "addr:postcode":"07701",
    "addr:street":"W Front St",
    "iso:country":"US",
    "sg:address":"19 W Front St",
    "sg:city":"Red Bank",
    "sg:classifiers":[
        {
            "category":"Professional",
            "type":"Services"
        }
    ],
    "sg:phone":"+1 732 747 9744",
    "sg:postcode":"07701",
    "sg:province":"NJ",
    "sg:tags":[
        "establishment"
    ],
    "wof:name":"Paw Palace",
    "wof:placetype":"venue"
},
  "geometry": {"coordinates":[-74.065681,40.352102],"type":"Point"}
}