{
  "type": "Feature",
  "properties": {
    "iso:country":"US",
    "sg:address":"526 State Rte 17",
    "sg:city":"Ramsey",
    "sg:classifiers":[
        {
            "category":"Retail",
            "subcategory":"Auto Repair",
            "type":"Services"
        }
    ],
    "sg:phone":"+1 201 825 4550",
    "sg:postcode":"07446",
    "sg:province":"NJ",
    "sg:tags":[
        "repairing",
        "automobile"
    ],
    "wof:name":"Midas Auto Svc Experts",
    "wof:placetype":"venue"
},
  "geometry": {"coordinates":[-74.12116,41.057195],"type":"Point"}
}