{
  "type": "Feature",
  "properties": {
    "iso:country":"US",
    "sg:address":"327 US Hwy 206",
    "sg:city":"Bridgewater",
    "sg:classifiers":[
        {
            "category":"Restaurant",
            "type":"Food & Drink"
        }
    ],
    "sg:phone":"+1 908 722 8983",
    "sg:postcode":"08807",
    "sg:province":"NJ",
    "wof:name":"Thai Kitchen II",
    "wof:placetype":"venue"
},
  "geometry": {"coordinates":[-74.62206,40.582515],"type":"Point"}
}