{
  "type": "Feature",
  "properties": {
    "addr:full":"500 State Rte 23 Pompton Plains NJ 07444",
    "addr:housenumber":"500",
    "addr:postcode":"07444",
    "addr:street":"State Rte 23",
    "iso:country":"US",
    "sg:address":"500 State Rte 23",
    "sg:city":"Pompton Plains",
    "sg:classifiers":[
        {
            "category":"Shopping",
            "subcategory":"Computers & Home Electronics",
            "type":"Retail Goods"
        }
    ],
    "sg:phone":"+1   ",
    "sg:postcode":"07444",
    "sg:province":"NJ",
    "wof:name":"Radio Shack",
    "wof:placetype":"venue"
},
  "geometry": {"coordinates":[-74.285844,40.9689],"type":"Point"}
}