{
  "type": "Feature",
  "properties": {
    "iso:country":"US",
    "sg:address":"319 N Main St",
    "sg:city":"Glassboro",
    "sg:classifiers":[
        {
            "category":"Building & Trades",
            "subcategory":"Construction",
            "type":"Services"
        }
    ],
    "sg:phone":"+1 856 881 1177",
    "sg:postcode":"08028",
    "sg:province":"NJ",
    "sg:tags":[
        "windows",
        "door",
        "storm"
    ],
    "wof:name":"Window Shop",
    "wof:placetype":"venue"
},
  "geometry": {"coordinates":[-75.111062,39.710418],"type":"Point"}
}