{
  "type": "Feature",
  "properties": {
    "addr:full":"217 Bergen Ave Kearny NJ 07032",
    "addr:housenumber":"217",
    "addr:postcode":"07032",
    "addr:street":"Bergen Ave",
    "iso:country":"US",
    "sg:address":"217 Bergen Ave",
    "sg:city":"Kearny",
    "sg:classifiers":[
        {
            "category":"Professional",
            "type":"Services"
        }
    ],
    "sg:phone":"+1   ",
    "sg:postcode":"07032",
    "sg:province":"NJ",
    "wof:name":"Treasures of Heart",
    "wof:placetype":"venue"
},
  "geometry": {"coordinates":[-74.149179,40.758457],"type":"Point"}
}