{
  "type": "Feature",
  "properties": {
    "addr:full":"11 Leuning St South Hackensack NJ 07606",
    "addr:housenumber":"11",
    "addr:postcode":"07606",
    "addr:street":"Leuning St",
    "iso:country":"US",
    "sg:address":"11 Leuning St",
    "sg:city":"South Hackensack",
    "sg:classifiers":[
        {
            "category":"Wholesale",
            "subcategory":"Electrical",
            "type":"Manufacturing & Wholesale Goods"
        }
    ],
    "sg:phone":"+1 201 343 0055",
    "sg:postcode":"07606",
    "sg:province":"NJ",
    "sg:tags":[
        "light",
        "tube",
        "bulb"
    ],
    "wof:name":"Epic Assoc Inc",
    "wof:placetype":"venue"
},
  "geometry": {"coordinates":[-74.049156,40.871918],"type":"Point"}
}