{
  "type": "Feature",
  "properties": {
    "addr:full":"5 Shore Rd Edgewater NJ 07020",
    "addr:housenumber":"5",
    "addr:postcode":"07020",
    "addr:street":"Shore Rd",
    "iso:country":"US",
    "sg:address":"5 Shore Rd",
    "sg:city":"Edgewater",
    "sg:classifiers":[
        {
            "category":"Building & Trades",
            "subcategory":"Construction",
            "type":"Services"
        }
    ],
    "sg:phone":"+1 212 308 5080",
    "sg:postcode":"07020",
    "sg:province":"NJ",
    "sg:tags":[
        "interior",
        "design"
    ],
    "wof:name":"Lyons Steve",
    "wof:placetype":"venue"
},
  "geometry": {"coordinates":[-73.966086,40.843269],"type":"Point"}
}