{
  "type": "Feature",
  "properties": {
    "iso:country":"US",
    "sg:address":"58 Troy Dr",
    "sg:city":"Springfield",
    "sg:classifiers":[
        {
            "category":"Professional",
            "subcategory":"Advertising",
            "type":"Services"
        }
    ],
    "sg:phone":"+1   ",
    "sg:postcode":"07081",
    "sg:province":"NJ",
    "sg:tags":[
        "consulting",
        "management",
        "agency"
    ],
    "wof:name":"Lipkin & Associates",
    "wof:placetype":"venue"
},
  "geometry": {"coordinates":[-74.329105,40.712599],"type":"Point"}
}