{
  "type": "Feature",
  "properties": {
    "iso:country":"US",
    "sg:address":"360 Adamic Hill Rd",
    "sg:city":"Milford",
    "sg:classifiers":[
        {
            "category":"Manufacturing",
            "subcategory":"Tools & Machinery",
            "type":"Manufacturing & Wholesale Goods"
        }
    ],
    "sg:phone":"+1 908 995 9038",
    "sg:postcode":"08848",
    "sg:province":"NJ",
    "sg:tags":[
        "industrial",
        "mfg"
    ],
    "wof:name":"Adamic Hill Machine",
    "wof:placetype":"venue"
},
  "geometry": {"coordinates":[-75.153561,40.597845],"type":"Point"}
}