{
  "type": "Feature",
  "properties": {
    "iso:country":"US",
    "sg:address":"541 W 4th St",
    "sg:city":"Plainfield",
    "sg:classifiers":[
        {
            "category":"Organizations",
            "subcategory":"Non-profit Organization",
            "type":"Services"
        }
    ],
    "sg:phone":"+1 908 757 4992",
    "sg:postcode":"07060",
    "sg:province":"NJ",
    "sg:tags":[
        "group",
        "social"
    ],
    "wof:name":"Caring Hearts Foundation of Pl",
    "wof:placetype":"venue"
},
  "geometry": {"coordinates":[-74.426625,40.611672],"type":"Point"}
}