{
  "type": "Feature",
  "properties": {
    "addr:full":"132 French St New Brunswick NJ 08901",
    "addr:housenumber":"132",
    "addr:postcode":"08901",
    "addr:street":"French St",
    "iso:country":"US",
    "sg:address":"132 French St",
    "sg:city":"New Brunswick",
    "sg:classifiers":[
        {
            "category":"Shopping",
            "subcategory":"Shoes",
            "type":"Retail Goods"
        }
    ],
    "sg:phone":"+1 732 214 1355",
    "sg:postcode":"08901",
    "sg:province":"NJ",
    "wof:name":"Zapateria Dos Hermanos",
    "wof:placetype":"venue"
},
  "geometry": {"coordinates":[-74.452384,40.492968],"type":"Point"}
}