{
  "type": "Feature",
  "properties": {
    "addr:full":"116 N New Jersey Ave Atlantic City NJ 08401",
    "addr:housenumber":"116",
    "addr:postcode":"08401",
    "addr:street":"N New Jersey Ave",
    "iso:country":"US",
    "sg:address":"116 N New Jersey Ave",
    "sg:city":"Atlantic City",
    "sg:classifiers":[
        {
            "category":"Organizations",
            "subcategory":"Religious Organization",
            "type":"Services"
        }
    ],
    "sg:phone":"+1   ",
    "sg:postcode":"08401",
    "sg:province":"NJ",
    "wof:name":"Bethel Baptist Church",
    "wof:placetype":"venue"
},
  "geometry": {"coordinates":[-74.42111,39.36827],"type":"Point"}
}