{
  "type": "Feature",
  "properties": {
    "iso:country":"US",
    "sg:address":"780 Paterson Ave",
    "sg:city":"East Rutherford",
    "sg:classifiers":[
        {
            "category":"Autos & Motor Vehicles",
            "subcategory":"Automobile Sales",
            "type":"Retail Goods"
        }
    ],
    "sg:phone":"+1 973 614 0090",
    "sg:postcode":"07073",
    "sg:province":"NJ",
    "sg:tags":[
        "car",
        "dealer"
    ],
    "wof:name":"D & S Motors LLC",
    "wof:placetype":"venue"
},
  "geometry": {"coordinates":[-74.112685,40.848185],"type":"Point"}
}