{
  "type": "Feature",
  "properties": {
    "addr:full":"80 Essex Ave E Avenel NJ 07001",
    "addr:housenumber":"80",
    "addr:postcode":"07001",
    "addr:street":"Essex Ave E",
    "iso:country":"US",
    "sg:address":"80 Essex Ave E",
    "sg:city":"Avenel",
    "sg:classifiers":[
        {
            "category":"Shopping",
            "subcategory":"Clothing, Apparel, & Fashions",
            "type":"Retail Goods"
        }
    ],
    "sg:phone":"+1 732 636 1221",
    "sg:postcode":"07001",
    "sg:province":"NJ",
    "sg:tags":[
        "children's",
        "clothing"
    ],
    "wof:name":"Celebrity International",
    "wof:placetype":"venue"
},
  "geometry": {"coordinates":[-74.268303,40.580002],"type":"Point"}
}