{
  "type": "Feature",
  "properties": {
    "addr:full":"390 21st Ave Paterson NJ 07513",
    "addr:housenumber":"390",
    "addr:postcode":"07513",
    "addr:street":"21St Ave",
    "iso:country":"US",
    "sg:address":"390 21st Ave",
    "sg:city":"Paterson",
    "sg:classifiers":[
        {
            "category":"Restaurant",
            "type":"Food & Drink"
        }
    ],
    "sg:phone":"+1 973 742 8777",
    "sg:postcode":"07513",
    "sg:province":"NJ",
    "wof:name":"Banana King",
    "wof:placetype":"venue"
},
  "geometry": {"coordinates":[-74.148499,40.906601],"type":"Point"}
}