{
  "type": "Feature",
  "properties": {
    "iso:country":"US",
    "sg:address":"5200 Shawcrest Rd",
    "sg:city":"Wildwood",
    "sg:classifiers":[
        {
            "category":"Real Estate",
            "subcategory":"Developer",
            "type":"Services"
        }
    ],
    "sg:phone":"+1 609 522 2541",
    "sg:postcode":"08260",
    "sg:province":"NJ",
    "sg:tags":[
        "mobile",
        "home"
    ],
    "wof:name":"Shawcrest Mobile Home Park",
    "wof:placetype":"venue"
},
  "geometry": {"coordinates":[-74.837058,38.991294],"type":"Point"}
}