{
  "type": "Feature",
  "properties": {
    "iso:country":"US",
    "sg:address":"50 Cherry Hill Rd",
    "sg:city":"Parsippany",
    "sg:classifiers":[
        {
            "category":"Health Services",
            "subcategory":"Doctor",
            "type":"Services"
        }
    ],
    "sg:phone":"+1 973 299 1400",
    "sg:postcode":"07054",
    "sg:province":"NJ",
    "sg:tags":[
        "clinic",
        "medical"
    ],
    "wof:name":"Parsippany Medical Group Inc",
    "wof:placetype":"venue"
},
  "geometry": {"coordinates":[-74.43800400000001,40.873439],"type":"Point"}
}