{
  "type": "Feature",
  "properties": {
    "addr:full":"14 Merry Ln East Hanover NJ 07936",
    "addr:housenumber":"14",
    "addr:postcode":"07936",
    "addr:street":"Merry Ln",
    "iso:country":"US",
    "sg:address":"14 Merry Ln",
    "sg:city":"East Hanover",
    "sg:classifiers":[
        {
            "category":"Manufacturing",
            "subcategory":"Tools & Machinery",
            "type":"Manufacturing & Wholesale Goods"
        }
    ],
    "sg:phone":"+1 973 515 8540",
    "sg:postcode":"07936",
    "sg:province":"NJ",
    "sg:tags":[
        "industrial",
        "mfg"
    ],
    "wof:name":"Julius Machine & Tool",
    "wof:placetype":"venue"
},
  "geometry": {"coordinates":[-74.345304,40.818864],"type":"Point"}
}