{
  "type": "Feature",
  "properties": {
    "iso:country":"US",
    "sg:address":"6 Devonshire Dr",
    "sg:city":"Egg Harbor Twp",
    "sg:classifiers":[
        {
            "category":"Retail",
            "subcategory":"Repair Shop",
            "type":"Services"
        }
    ],
    "sg:phone":"+1 609 927 5539",
    "sg:postcode":"08234",
    "sg:province":"NJ",
    "sg:tags":[
        "lock",
        "locksmith"
    ],
    "wof:name":"Key's Locksmithing",
    "wof:placetype":"venue"
},
  "geometry": {"coordinates":[-74.68232999999999,39.379719],"type":"Point"}
}