{
  "type": "Feature",
  "properties": {
    "addr:full":"1 E Broad St Palmyra NJ 08065",
    "addr:housenumber":"1",
    "addr:postcode":"08065",
    "addr:street":"E Broad St",
    "iso:country":"US",
    "sg:address":"1 E Broad St",
    "sg:city":"Palmyra",
    "sg:classifiers":[
        {
            "category":"Shopping",
            "subcategory":"Pharmacy",
            "type":"Retail Goods"
        }
    ],
    "sg:phone":"+1 856 829 1597",
    "sg:postcode":"08065",
    "sg:province":"NJ",
    "sg:tags":[
        "drugstore"
    ],
    "wof:name":"Palmyra Pharmacy",
    "wof:placetype":"venue"
},
  "geometry": {"coordinates":[-75.028999,40.004101],"type":"Point"}
}