{
  "type": "Feature",
  "properties": {
    "addr:full":"60 Roseland Ave Caldwell NJ 07006",
    "addr:housenumber":"60",
    "addr:postcode":"07006",
    "addr:street":"Roseland Ave",
    "iso:country":"US",
    "sg:address":"60 Roseland Ave",
    "sg:city":"Caldwell",
    "sg:classifiers":[
        {
            "category":"Taxi",
            "type":"Transportation"
        }
    ],
    "sg:phone":"+1 973 226 0884",
    "sg:postcode":"07006",
    "sg:province":"NJ",
    "wof:name":"Yellow Cab of Caldwell",
    "wof:placetype":"venue"
},
  "geometry": {"coordinates":[-74.277603,40.8363],"type":"Point"}
}