{
  "type": "Feature",
  "properties": {
    "addr:full":"169 Sheridan Ave Ho Ho Kus NJ 07423",
    "addr:housenumber":"169",
    "addr:postcode":"07423",
    "addr:street":"Sheridan Ave",
    "iso:country":"US",
    "sg:address":"169 Sheridan Ave",
    "sg:city":"Ho Ho Kus",
    "sg:classifiers":[
        {
            "category":"Professional",
            "subcategory":"Computer Services",
            "type":"Services"
        }
    ],
    "sg:phone":"+1   ",
    "sg:postcode":"07423",
    "sg:province":"NJ",
    "sg:tags":[
        "management",
        "facility"
    ],
    "wof:name":"Nick Milianes",
    "wof:placetype":"venue"
},
  "geometry": {"coordinates":[-74.108093,41.003357],"type":"Point"}
}