{
  "type": "Feature",
  "properties": {
    "addr:full":"7000 Hadley Rd South Plainfield NJ 07080",
    "addr:housenumber":"7000",
    "addr:postcode":"07080",
    "addr:street":"Hadley Rd",
    "iso:country":"US",
    "sg:address":"7000 Hadley Rd",
    "sg:city":"South Plainfield",
    "sg:classifiers":[
        {
            "category":"Home & Garden",
            "subcategory":"Furniture",
            "type":"Retail Goods"
        }
    ],
    "sg:phone":"+1 908 756 7830",
    "sg:postcode":"07080",
    "sg:province":"NJ",
    "sg:tags":[
        "bedding"
    ],
    "sg:website":"www.rockawaybedding.com",
    "wof:name":"Rockaway Bedding",
    "wof:placetype":"venue"
},
  "geometry": {"coordinates":[-74.424603,40.553719],"type":"Point"}
}