{
  "type": "Feature",
  "properties": {
    "addr:full":"9 Shadowbrook Way Mendham NJ 07945",
    "addr:housenumber":"9",
    "addr:postcode":"07945",
    "addr:street":"Shadowbrook Way",
    "iso:country":"US",
    "sg:address":"9 Shadowbrook Way",
    "sg:city":"Mendham",
    "sg:classifiers":[
        {
            "category":"Shopping",
            "subcategory":"Gifts & Souvenirs",
            "type":"Retail Goods"
        }
    ],
    "sg:phone":"+1   ",
    "sg:postcode":"07945",
    "sg:province":"NJ",
    "wof:name":"Alizas Treasures",
    "wof:placetype":"venue"
},
  "geometry": {"coordinates":[-74.61488300000001,40.810219],"type":"Point"}
}