{
  "type": "Feature",
  "properties": {
    "addr:full":"45 Lower Oak Grove Rd Frenchtown NJ 08825",
    "addr:housenumber":"45",
    "addr:postcode":"08825",
    "addr:street":"Lower Oak Grove Rd",
    "iso:country":"US",
    "sg:address":"45 Lower Oak Grove Rd",
    "sg:city":"Frenchtown",
    "sg:classifiers":[
        {
            "category":"Building & Trades",
            "subcategory":"Plumbing",
            "type":"Services"
        }
    ],
    "sg:phone":"+1 908 996 5129",
    "sg:postcode":"08825",
    "sg:province":"NJ",
    "sg:tags":[
        "conditioning",
        "air",
        "system",
        "contractor"
    ],
    "wof:name":"Ultimate Air LLC",
    "wof:placetype":"venue"
},
  "geometry": {"coordinates":[-74.990793,40.522146],"type":"Point"}
}