{
  "type": "Feature",
  "properties": {
    "addr:full":"1400 Texas Ave Cape May NJ 08204",
    "addr:housenumber":"1400",
    "addr:postcode":"08204",
    "addr:street":"Texas Ave",
    "iso:country":"US",
    "sg:address":"1400 Texas Ave",
    "sg:city":"Cape May",
    "sg:classifiers":[
        {
            "category":"Real Estate",
            "subcategory":"Real Estate Services",
            "type":"Services"
        }
    ],
    "sg:phone":"+1 609 884 5005",
    "sg:postcode":"08204",
    "sg:province":"NJ",
    "wof:name":"Coastline Realty",
    "wof:placetype":"venue"
},
  "geometry": {"coordinates":[-74.909785,38.946658],"type":"Point"}
}