{
  "type": "Feature",
  "properties": {
    "addr:full":"28 Harrison Ave Englishtown NJ 07726",
    "addr:housenumber":"28",
    "addr:postcode":"07726",
    "addr:street":"Harrison Ave",
    "iso:country":"US",
    "sg:address":"28 Harrison Ave",
    "sg:city":"Englishtown",
    "sg:classifiers":[
        {
            "category":"Banks & Credit Unions",
            "subcategory":"Investment Brokerage",
            "type":"Services"
        }
    ],
    "sg:phone":"+1   ",
    "sg:postcode":"07726",
    "sg:province":"NJ",
    "sg:tags":[
        "advisory"
    ],
    "wof:name":"Englishtown Industrial PA",
    "wof:placetype":"venue"
},
  "geometry": {"coordinates":[-74.355662,40.297006],"type":"Point"}
}