{
  "type": "Feature",
  "properties": {
    "addr:full":"461 Patten Ave Long Branch NJ 07740",
    "addr:housenumber":"461",
    "addr:postcode":"07740",
    "addr:street":"Patten Ave",
    "iso:country":"US",
    "sg:address":"461 Patten Ave",
    "sg:city":"Long Branch",
    "sg:classifiers":[
        {
            "category":"Building & Trades",
            "subcategory":"Landscaping Services",
            "type":"Services"
        }
    ],
    "sg:phone":"+1 732 229 5573",
    "sg:postcode":"07740",
    "sg:province":"NJ",
    "wof:name":"Henry Lewis Gardener",
    "wof:placetype":"venue"
},
  "geometry": {"coordinates":[-73.992142,40.320009],"type":"Point"}
}