{
  "type": "Feature",
  "properties": {
    "addr:full":"1910 Marlton Pike E Cherry Hill NJ 08003",
    "addr:housenumber":"1910",
    "addr:postcode":"08003",
    "addr:street":"Marlton Pike E",
    "iso:country":"US",
    "sg:address":"1910 Marlton Pike E",
    "sg:city":"Cherry Hill",
    "sg:classifiers":[
        {
            "category":"Health Services",
            "subcategory":"Doctor",
            "type":"Services"
        }
    ],
    "sg:phone":"+1   ",
    "sg:postcode":"08003",
    "sg:province":"NJ",
    "wof:name":"Dr Gregory Shupik",
    "wof:placetype":"venue"
},
  "geometry": {"coordinates":[-74.96673800000001,39.90297],"type":"Point"}
}