{
  "type": "Feature",
  "properties": {
    "addr:full":"16 Chestnut St Emerson NJ 07630",
    "addr:housenumber":"16",
    "addr:postcode":"07630",
    "addr:street":"Chestnut St",
    "iso:country":"US",
    "sg:address":"16 Chestnut St",
    "sg:city":"Emerson",
    "sg:classifiers":[
        {
            "category":"Building & Trades",
            "subcategory":"Construction",
            "type":"Services"
        }
    ],
    "sg:phone":"+1 201 894 8484",
    "sg:postcode":"07630",
    "sg:province":"NJ",
    "sg:tags":[
        "general",
        "contractor"
    ],
    "wof:name":"Remodeling Direct",
    "wof:placetype":"venue"
},
  "geometry": {"coordinates":[-74.027053,40.979727],"type":"Point"}
}