{
  "type": "Feature",
  "properties": {
    "addr:full":"133 Cedar Ln Teaneck NJ 07666",
    "addr:housenumber":"133",
    "addr:postcode":"07666",
    "addr:street":"Cedar Ln",
    "iso:country":"US",
    "sg:address":"133 Cedar Ln",
    "sg:city":"Teaneck",
    "sg:classifiers":[
        {
            "category":"Professional",
            "subcategory":"Business Services",
            "type":"Services"
        }
    ],
    "sg:phone":"+1 201 836 0372",
    "sg:postcode":"07666",
    "sg:province":"NJ",
    "sg:tags":[
        "packaging"
    ],
    "wof:name":"Oakwood Packaging",
    "wof:placetype":"venue"
},
  "geometry": {"coordinates":[-74.011911,40.885818],"type":"Point"}
}