{
  "type": "Feature",
  "properties": {
    "addr:full":"817 8th St Keyport NJ 07735",
    "addr:housenumber":"817",
    "addr:postcode":"07735",
    "addr:street":"8Th St",
    "iso:country":"US",
    "sg:address":"817 8th St",
    "sg:city":"Keyport",
    "sg:classifiers":[
        {
            "category":"Wholesale",
            "subcategory":"Construction Materials",
            "type":"Manufacturing & Wholesale Goods"
        }
    ],
    "sg:phone":"+1 732 264 2123",
    "sg:postcode":"07735",
    "sg:province":"NJ",
    "wof:name":"A Gem Overhead Door Service",
    "wof:placetype":"venue"
},
  "geometry": {"coordinates":[-74.174879,40.44727],"type":"Point"}
}