{
  "type": "Feature",
  "properties": {
    "addr:full":"14 Kovach St Franklin NJ 07416",
    "addr:housenumber":"14",
    "addr:postcode":"07416",
    "addr:street":"Kovach St",
    "iso:country":"US",
    "sg:address":"14 Kovach St",
    "sg:city":"Franklin",
    "sg:classifiers":[
        {
            "category":"Real Estate",
            "subcategory":"Real Estate Operator",
            "type":"Services"
        }
    ],
    "sg:phone":"+1   ",
    "sg:postcode":"07416",
    "sg:province":"NJ",
    "sg:tags":[
        "building",
        "nonresidential"
    ],
    "wof:name":"S J R Properties",
    "wof:placetype":"venue"
},
  "geometry": {"coordinates":[-74.577234,41.123969],"type":"Point"}
}