{
  "type": "Feature",
  "properties": {
    "iso:country":"US",
    "sg:address":"290 Route 37 W",
    "sg:city":"Toms River",
    "sg:classifiers":[
        {
            "category":"Restaurant",
            "type":"Food & Drink"
        }
    ],
    "sg:menulink":"http://www.allmenus.com/nj/toms-river/33261-the-palms/menu/",
    "sg:phone":"+1 732 244 4000",
    "sg:postcode":"08753",
    "sg:province":"NJ",
    "sg:tags":[
        "american"
    ],
    "wof:name":"The Palms",
    "wof:placetype":"venue"
},
  "geometry": {"coordinates":[-74.177092,39.960489],"type":"Point"}
}