{
  "type": "Feature",
  "properties": {
    "iso:country":"US",
    "sg:address":"31 Plaza Rd",
    "sg:city":"Fair Lawn",
    "sg:classifiers":[
        {
            "category":"Recreation",
            "type":"Entertainment"
        }
    ],
    "sg:phone":"+1 201 791 7500",
    "sg:postcode":"07410",
    "sg:province":"NJ",
    "sg:tags":[
        "karate",
        "judo",
        "instr"
    ],
    "wof:name":"Fairlawn Taw KWON Co",
    "wof:placetype":"venue"
},
  "geometry": {"coordinates":[-74.113739,40.929612],"type":"Point"}
}