{
  "type": "Feature",
  "properties": {
    "addr:full":"28 Harrison St Woodbury NJ 08096",
    "addr:housenumber":"28",
    "addr:postcode":"08096",
    "addr:street":"Harrison St",
    "iso:country":"US",
    "sg:address":"28 Harrison St",
    "sg:city":"Woodbury",
    "sg:classifiers":[
        {
            "category":"Professional",
            "subcategory":"Business Services",
            "type":"Services"
        }
    ],
    "sg:phone":"+1 856 853 5160",
    "sg:postcode":"08096",
    "sg:province":"NJ",
    "sg:tags":[
        "special"
    ],
    "wof:name":"Docuvault",
    "wof:placetype":"venue"
},
  "geometry": {"coordinates":[-75.15518899999999,39.838959],"type":"Point"}
}