{
  "type": "Feature",
  "properties": {
    "iso:country":"US",
    "sg:address":"314 Broadwell Ave",
    "sg:city":"Union",
    "sg:classifiers":[
        {
            "category":"Social Services",
            "type":"Services"
        }
    ],
    "sg:phone":"+1   ",
    "sg:postcode":"07083",
    "sg:province":"NJ",
    "sg:tags":[
        "health"
    ],
    "wof:name":"Psyhologist",
    "wof:placetype":"venue"
},
  "geometry": {"coordinates":[-74.24891700000001,40.683838],"type":"Point"}
}