{
  "type": "Feature",
  "properties": {
    "addr:full":"309 E 2nd St Bound Brook NJ 08805",
    "addr:housenumber":"309",
    "addr:postcode":"08805",
    "addr:street":"E 2Nd St",
    "iso:country":"US",
    "sg:address":"309 E 2nd St",
    "sg:city":"Bound Brook",
    "sg:classifiers":[
        {
            "category":"Health Services",
            "subcategory":"Medical Lab",
            "type":"Services"
        }
    ],
    "sg:phone":"+1 732 356 5482",
    "sg:postcode":"08805",
    "sg:province":"NJ",
    "sg:tags":[
        "laboratory"
    ],
    "wof:name":"Bradley Orthodontic",
    "wof:placetype":"venue"
},
  "geometry": {"coordinates":[-74.530737,40.562629],"type":"Point"}
}