{
  "type": "Feature",
  "properties": {
    "addr:full":"606 Helena Ave Cherry Hill NJ 08002",
    "addr:housenumber":"606",
    "addr:postcode":"08002",
    "addr:street":"Helena Ave",
    "iso:country":"US",
    "sg:address":"606 Helena Ave",
    "sg:city":"Cherry Hill",
    "sg:classifiers":[
        {
            "category":"Professional",
            "subcategory":"Lawyer & Legal Services",
            "type":"Services"
        }
    ],
    "sg:phone":"+1 856 354 9799",
    "sg:postcode":"08002",
    "sg:province":"NJ",
    "sg:tags":[
        "attorney"
    ],
    "wof:name":"Joseph G Dilks",
    "wof:placetype":"venue"
},
  "geometry": {"coordinates":[-75.043978,39.939145],"type":"Point"}
}