{
  "type": "Feature",
  "properties": {
    "iso:country":"US",
    "sg:address":"194 Livingston St",
    "sg:city":"Northvale",
    "sg:classifiers":[
        {
            "category":"Building & Trades",
            "subcategory":"Construction",
            "type":"Services"
        }
    ],
    "sg:phone":"+1 201 768 0671",
    "sg:postcode":"07647",
    "sg:province":"NJ",
    "sg:tags":[
        "movers-commercial",
        "pipe",
        "industrial",
        "cleaning",
        "contractor"
    ],
    "wof:name":"Fmi",
    "wof:placetype":"venue"
},
  "geometry": {"coordinates":[-73.94942899999999,41.00614],"type":"Point"}
}