{
  "type": "Feature",
  "properties": {
    "iso:country":"US",
    "sg:address":"1808 State Route 23",
    "sg:city":"Wayne",
    "sg:classifiers":[
        {
            "category":"Restaurant",
            "type":"Food & Drink"
        }
    ],
    "sg:phone":"+1 973 696 4282",
    "sg:postcode":"07470",
    "sg:province":"NJ",
    "sg:tags":[
        "pizza"
    ],
    "wof:name":"Bradlee Pizzeria",
    "wof:placetype":"venue"
},
  "geometry": {"coordinates":[-74.27449799999999,40.946999],"type":"Point"}
}