{
  "type": "Feature",
  "properties": {
    "addr:full":"147 Broadway Elmwood Park NJ 07407",
    "addr:housenumber":"147",
    "addr:postcode":"07407",
    "addr:street":"Broadway",
    "iso:country":"US",
    "sg:address":"147 Broadway",
    "sg:city":"Elmwood Park",
    "sg:classifiers":[
        {
            "category":"Shopping",
            "subcategory":"Gifts & Souvenirs",
            "type":"Retail Goods"
        }
    ],
    "sg:phone":"+1   ",
    "sg:postcode":"07407",
    "sg:province":"NJ",
    "wof:name":"Adelaide Inc A New Jersey Corp",
    "wof:placetype":"venue"
},
  "geometry": {"coordinates":[-74.12204199999999,40.91999],"type":"Point"}
}