{
  "type": "Feature",
  "properties": {
    "addr:full":"514 Palmer Ave Maywood NJ 07607",
    "addr:housenumber":"514",
    "addr:postcode":"07607",
    "addr:street":"Palmer Ave",
    "iso:country":"US",
    "sg:address":"514 Palmer Ave",
    "sg:city":"Maywood",
    "sg:classifiers":[
        {
            "category":"Banks & Credit Unions",
            "subcategory":"Bank",
            "type":"Services"
        }
    ],
    "sg:phone":"+1   ",
    "sg:postcode":"07607",
    "sg:province":"NJ",
    "sg:tags":[
        "mortgage"
    ],
    "wof:name":"PHH US Mortgage",
    "wof:placetype":"venue"
},
  "geometry": {"coordinates":[-74.063742,40.905083],"type":"Point"}
}