{
  "type": "Feature",
  "properties": {
    "addr:full":"507 Summer St Paterson NJ 07501",
    "addr:housenumber":"507",
    "addr:postcode":"07501",
    "addr:street":"Summer St",
    "iso:country":"US",
    "sg:address":"507 Summer St",
    "sg:city":"Paterson",
    "sg:classifiers":[
        {
            "category":"Food & Beverages",
            "subcategory":"Liquor & Beverages",
            "type":"Retail Goods"
        }
    ],
    "sg:phone":"+1 973 684 9144",
    "sg:postcode":"07501",
    "sg:province":"NJ",
    "sg:tags":[
        "beer",
        "spirit",
        "wine"
    ],
    "wof:name":"Diamond Liquors",
    "wof:placetype":"venue"
},
  "geometry": {"coordinates":[-74.163498,40.910099],"type":"Point"}
}