{
  "type": "Feature",
  "properties": {
    "iso:country":"US",
    "sg:address":"51 Northrup Dr",
    "sg:city":"Brick",
    "sg:classifiers":[
        {
            "category":"Wholesale",
            "subcategory":"Vending Machines",
            "type":"Manufacturing & Wholesale Goods"
        }
    ],
    "sg:phone":"+1   ",
    "sg:postcode":"08724",
    "sg:province":"NJ",
    "sg:tags":[
        "operator",
        "automatic",
        "merchandising"
    ],
    "wof:name":"Rubenn Vending",
    "wof:placetype":"venue"
},
  "geometry": {"coordinates":[-74.12151900000001,40.087174],"type":"Point"}
}