{
  "type": "Feature",
  "properties": {
    "addr:full":"1700 Atlantic Ave Manasquan NJ 08736",
    "addr:housenumber":"1700",
    "addr:postcode":"08736",
    "addr:street":"Atlantic Ave",
    "iso:country":"US",
    "sg:address":"1700 Atlantic Ave",
    "sg:city":"Manasquan",
    "sg:classifiers":[
        {
            "category":"Building & Trades",
            "subcategory":"Construction",
            "type":"Services"
        }
    ],
    "sg:phone":"+1 732 223 3030",
    "sg:postcode":"08736",
    "sg:province":"NJ",
    "sg:tags":[
        "demolition",
        "contractor"
    ],
    "wof:name":"Mark Woszczak Mechanical Contr",
    "wof:placetype":"venue"
},
  "geometry": {"coordinates":[-74.074151,40.134668],"type":"Point"}
}