{
  "type": "Feature",
  "properties": {
    "addr:full":"29 Weaver St Little Falls NJ 07424",
    "addr:housenumber":"29",
    "addr:postcode":"07424",
    "addr:street":"Weaver St",
    "iso:country":"US",
    "sg:address":"29 Weaver St",
    "sg:city":"Little Falls",
    "sg:classifiers":[
        {
            "category":"Education",
            "subcategory":"Preschool",
            "type":"Public Place"
        },
        {
            "category":"Education",
            "subcategory":"School",
            "type":"Public Place"
        }
    ],
    "sg:phone":"+1 973 256 9584",
    "sg:postcode":"07424",
    "sg:province":"NJ",
    "sg:tags":[
        "elementary"
    ],
    "wof:name":"St John's Church",
    "wof:placetype":"venue"
},
  "geometry": {"coordinates":[-74.2444,40.881599],"type":"Point"}
}