{
  "type": "Feature",
  "properties": {
    "iso:country":"US",
    "sg:address":"58 Morse St",
    "sg:city":"Cranford",
    "sg:classifiers":[
        {
            "category":"Travel",
            "subcategory":"Travel Agent",
            "type":"Entertainment"
        }
    ],
    "sg:phone":"+1 908 276 0417",
    "sg:postcode":"07016",
    "sg:province":"NJ",
    "sg:tags":[
        "agency"
    ],
    "wof:name":"Berkie Travel",
    "wof:placetype":"venue"
},
  "geometry": {"coordinates":[-74.30988600000001,40.63974],"type":"Point"}
}