{
  "type": "Feature",
  "properties": {
    "iso:country":"US",
    "sg:address":"20 Carrell Rd",
    "sg:city":"Randolph",
    "sg:classifiers":[
        {
            "category":"Building & Trades",
            "subcategory":"Construction",
            "type":"Services"
        }
    ],
    "sg:phone":"+1 973 895 1663",
    "sg:postcode":"07869",
    "sg:province":"NJ",
    "sg:tags":[
        "paving",
        "contractor"
    ],
    "wof:name":"Nick Recchia Paving Co",
    "wof:placetype":"venue"
},
  "geometry": {"coordinates":[-74.59193,40.843339],"type":"Point"}
}