{
  "type": "Feature",
  "properties": {
    "addr:full":"127 Paterson Ave Little Falls NJ 07424",
    "addr:housenumber":"127",
    "addr:postcode":"07424",
    "addr:street":"Paterson Ave",
    "iso:country":"US",
    "sg:address":"127 Paterson Ave",
    "sg:city":"Little Falls",
    "sg:classifiers":[
        {
            "category":"Home & Garden",
            "subcategory":"Building Materials",
            "type":"Retail Goods"
        }
    ],
    "sg:phone":"+1 973 256 7751",
    "sg:postcode":"07424",
    "sg:province":"NJ",
    "sg:tags":[
        "s",
        "mfg"
    ],
    "wof:name":"Aluminrs-Vnylers Siding Contrs",
    "wof:placetype":"venue"
},
  "geometry": {"coordinates":[-74.22304699999999,40.884921],"type":"Point"}
}