{
  "type": "Feature",
  "properties": {
    "addr:full":"18 N High St Millville NJ 08332",
    "addr:housenumber":"18",
    "addr:postcode":"08332",
    "addr:street":"N High St",
    "iso:country":"US",
    "sg:address":"18 N High St",
    "sg:city":"Millville",
    "sg:classifiers":[
        {
            "category":"Shopping",
            "subcategory":"Clothing, Apparel, & Fashions",
            "type":"Retail Goods"
        }
    ],
    "sg:phone":"+1   ",
    "sg:postcode":"08332",
    "sg:province":"NJ",
    "sg:tags":[
        "sneaker",
        "lady",
        "man"
    ],
    "wof:name":"Franks Mens & Boys Shop",
    "wof:placetype":"venue"
},
  "geometry": {"coordinates":[-75.03853599999999,39.396095],"type":"Point"}
}