{
  "type": "Feature",
  "properties": {
    "iso:country":"US",
    "sg:address":"245 Water St",
    "sg:city":"Belvidere",
    "sg:classifiers":[
        {
            "category":"Professional",
            "subcategory":"Art Services",
            "type":"Services"
        }
    ],
    "sg:phone":"+1 908 475 1374",
    "sg:postcode":"07823",
    "sg:province":"NJ",
    "sg:tags":[
        "graphic",
        "design"
    ],
    "sg:website":"www.swiftprintsolutions.com",
    "wof:name":"Swift Print Solutions, LLC",
    "wof:placetype":"venue"
},
  "geometry": {"coordinates":[-75.07969199999999,40.829745],"type":"Point"}
}