{
  "type": "Feature",
  "properties": {
    "addr:full":"3132 State Rte 27 Kendall Park NJ 08824",
    "addr:housenumber":"3132",
    "addr:postcode":"08824",
    "addr:street":"State Rte 27",
    "iso:country":"US",
    "sg:address":"3132 State Rte 27",
    "sg:city":"Kendall Park",
    "sg:classifiers":[
        {
            "category":"Shopping",
            "subcategory":"Computers & Home Electronics",
            "type":"Retail Goods"
        }
    ],
    "sg:phone":"+1 732 398 9642",
    "sg:postcode":"08824",
    "sg:province":"NJ",
    "sg:tags":[
        "equipment",
        "electronic",
        "supply"
    ],
    "wof:name":"Radio Shack",
    "wof:placetype":"venue"
},
  "geometry": {"coordinates":[-74.56196,40.427417],"type":"Point"}
}