{
  "type": "Feature",
  "properties": {
    "addr:full":"104 Harbor Dr Jersey City NJ 07305",
    "addr:housenumber":"104",
    "addr:postcode":"07305",
    "addr:street":"Harbor Dr",
    "iso:country":"US",
    "sg:address":"104 Harbor Dr",
    "sg:city":"Jersey City",
    "sg:classifiers":[
        {
            "category":"Freight",
            "type":"Transportation"
        }
    ],
    "sg:phone":"+1 201 332 4115",
    "sg:postcode":"07305",
    "sg:province":"NJ",
    "sg:tags":[
        "operator",
        "trucking"
    ],
    "wof:name":"Eagle Rock Trucking Co Inc",
    "wof:placetype":"venue"
},
  "geometry": {"coordinates":[-74.09357799999999,40.683174],"type":"Point"}
}