{
  "type": "Feature",
  "properties": {
    "addr:full":"43 Hurleys Ln Lincroft NJ 07738",
    "addr:housenumber":"43",
    "addr:postcode":"07738",
    "addr:street":"Hurleys Ln",
    "iso:country":"US",
    "sg:address":"43 Hurleys Ln",
    "sg:city":"Lincroft",
    "sg:classifiers":[
        {
            "category":"Restaurant",
            "type":"Food & Drink"
        }
    ],
    "sg:phone":"+1 732 530 3511",
    "sg:postcode":"07738",
    "sg:province":"NJ",
    "sg:tags":[
        "caterer"
    ],
    "wof:name":"Gourmet Picnic",
    "wof:placetype":"venue"
},
  "geometry": {"coordinates":[-74.117664,40.331816],"type":"Point"}
}