{
  "type": "Feature",
  "properties": {
    "addr:full":"90 Essex St Jersey City NJ 07302",
    "addr:housenumber":"90",
    "addr:postcode":"07302",
    "addr:street":"Essex St",
    "iso:country":"US",
    "sg:address":"90 Essex St",
    "sg:city":"Jersey City",
    "sg:classifiers":[
        {
            "category":"Real Estate",
            "subcategory":"Real Estate Agent",
            "type":"Services"
        }
    ],
    "sg:phone":"+1 201 435 8470",
    "sg:postcode":"07302",
    "sg:province":"NJ",
    "sg:tags":[
        "desk",
        "space"
    ],
    "wof:name":"Quality Housing Development",
    "wof:placetype":"venue"
},
  "geometry": {"coordinates":[-74.03644799999999,40.712916],"type":"Point"}
}