{
  "type": "Feature",
  "properties": {
    "addr:full":"4 Broadway Fair Lawn NJ 07410",
    "addr:housenumber":"4",
    "addr:postcode":"07410",
    "addr:street":"Broadway",
    "iso:country":"US",
    "sg:address":"4 Broadway",
    "sg:city":"Fair Lawn",
    "sg:classifiers":[
        {
            "category":"Restaurant",
            "type":"Food & Drink"
        }
    ],
    "sg:phone":"+1   ",
    "sg:postcode":"07410",
    "sg:province":"NJ",
    "sg:tags":[
        "eating"
    ],
    "wof:name":"TCBY",
    "wof:placetype":"venue"
},
  "geometry": {"coordinates":[-74.107733,40.923634],"type":"Point"}
}