{
  "type": "Feature",
  "properties": {
    "addr:full":"22 Brennan Ct Fair Lawn NJ 07410",
    "addr:housenumber":"22",
    "addr:postcode":"07410",
    "addr:street":"Brennan Ct",
    "iso:country":"US",
    "sg:address":"22 Brennan Ct",
    "sg:city":"Fair Lawn",
    "sg:classifiers":[
        {
            "category":"Professional",
            "subcategory":"Business Services",
            "type":"Services"
        }
    ],
    "sg:phone":"+1   ",
    "sg:postcode":"07410",
    "sg:province":"NJ",
    "sg:tags":[
        "arbitration",
        "conciliation"
    ],
    "wof:name":"Mediation In NY & NJ",
    "wof:placetype":"venue"
},
  "geometry": {"coordinates":[-74.095485,40.935411],"type":"Point"}
}