{
  "type": "Feature",
  "properties": {
    "iso:country":"US",
    "sg:address":"552 High Mountain Rd",
    "sg:city":"Haledon",
    "sg:classifiers":[
        {
            "category":"Professional",
            "subcategory":"Accounting & Tax Preparation",
            "type":"Services"
        }
    ],
    "sg:phone":"+1 973 427 7500",
    "sg:postcode":"07508",
    "sg:province":"NJ",
    "wof:name":"Raymond Van Grouw CPA",
    "wof:placetype":"venue"
},
  "geometry": {"coordinates":[-74.181359,40.955225],"type":"Point"}
}