{
  "type": "Feature",
  "properties": {
    "iso:country":"US",
    "sg:address":"2668 Morris Ave",
    "sg:city":"Union",
    "sg:classifiers":[
        {
            "category":"Health Services",
            "subcategory":"Doctor",
            "type":"Services"
        }
    ],
    "sg:phone":"+1 908 686 2552",
    "sg:postcode":"07083",
    "sg:province":"NJ",
    "wof:name":"Demczuk Eugene MD",
    "wof:placetype":"venue"
},
  "geometry": {"coordinates":[-74.294296,40.704399],"type":"Point"}
}