{
  "type": "Feature",
  "properties": {
    "addr:full":"1117 Mount Kemble Ave Morristown NJ 07960",
    "addr:housenumber":"1117",
    "addr:postcode":"07960",
    "addr:street":"Mount Kemble Ave",
    "iso:country":"US",
    "sg:address":"1117 Mount Kemble Ave",
    "sg:city":"Morristown",
    "sg:classifiers":[
        {
            "category":"Shopping",
            "subcategory":"Clothing, Apparel, & Fashions",
            "type":"Retail Goods"
        }
    ],
    "sg:phone":"+1   ",
    "sg:postcode":"07960",
    "sg:province":"NJ",
    "sg:tags":[
        "sport",
        "fur",
        "gift",
        "accessory"
    ],
    "wof:name":"Giorgios Pappas Furrier",
    "wof:placetype":"venue"
},
  "geometry": {"coordinates":[-74.532945,40.745228],"type":"Point"}
}