{
  "type": "Feature",
  "properties": {
    "iso:country":"US",
    "sg:address":"445 Stockton St",
    "sg:city":"Hightstown",
    "sg:classifiers":[
        {
            "category":"Shopping",
            "subcategory":"Crafts & Fabrics",
            "type":"Retail Goods"
        }
    ],
    "sg:phone":"+1   ",
    "sg:postcode":"08520",
    "sg:province":"NJ",
    "sg:tags":[
        "embroidery",
        "custom"
    ],
    "wof:name":"Rkm Enterprises Inc",
    "wof:placetype":"venue"
},
  "geometry": {"coordinates":[-74.535741,40.271818],"type":"Point"}
}