{
  "type": "Feature",
  "properties": {
    "iso:country":"US",
    "sg:address":"1151 State Rte 33",
    "sg:city":"Farmingdale",
    "sg:classifiers":[
        {
            "category":"Recreation",
            "type":"Entertainment"
        }
    ],
    "sg:phone":"+1 732 938 5215",
    "sg:postcode":"07727",
    "sg:province":"NJ",
    "sg:tags":[
        "car",
        "model",
        "racing",
        "center"
    ],
    "wof:name":"J & J Model Car Race Place",
    "wof:placetype":"venue"
},
  "geometry": {"coordinates":[-74.19274799999999,40.226977],"type":"Point"}
}