{
  "type": "Feature",
  "properties": {
    "addr:full":"2317 US Hwy 22 Union NJ 07083",
    "addr:housenumber":"2317",
    "addr:postcode":"07083",
    "addr:street":"Us Hwy 22",
    "iso:country":"US",
    "sg:address":"2317 US Hwy 22",
    "sg:city":"Union",
    "sg:classifiers":[
        {
            "category":"Shopping",
            "subcategory":"Music",
            "type":"Retail Goods"
        }
    ],
    "sg:phone":"+1   ",
    "sg:postcode":"07083",
    "sg:province":"NJ",
    "sg:tags":[
        "compact",
        "disc"
    ],
    "wof:name":"Compact Disc World & Tape Ctr",
    "wof:placetype":"venue"
},
  "geometry": {"coordinates":[-74.291543,40.690939],"type":"Point"}
}