{
  "type": "Feature",
  "properties": {
    "iso:country":"US",
    "sg:address":"995 Lakehurst Ave",
    "sg:city":"Jackson",
    "sg:classifiers":[
        {
            "category":"Social Services",
            "subcategory":"Child Care",
            "type":"Services"
        }
    ],
    "sg:phone":"+1   ",
    "sg:postcode":"08527",
    "sg:province":"NJ",
    "sg:tags":[
        "day"
    ],
    "wof:name":"Kiddie Cabin Daycare",
    "wof:placetype":"venue"
},
  "geometry": {"coordinates":[-74.345314,40.057203],"type":"Point"}
}