{
  "type": "Feature",
  "properties": {
    "addr:full":"46 York St Lambertville NJ 08530",
    "addr:housenumber":"46",
    "addr:postcode":"08530",
    "addr:street":"York St",
    "iso:country":"US",
    "sg:address":"46 York St",
    "sg:city":"Lambertville",
    "sg:classifiers":[
        {
            "category":"Professional",
            "subcategory":"Lawyer & Legal Services",
            "type":"Services"
        }
    ],
    "sg:phone":"+1 609 773 0112",
    "sg:postcode":"08530",
    "sg:province":"NJ",
    "sg:tags":[
        "attorney"
    ],
    "wof:name":"Covey & Assoc",
    "wof:placetype":"venue"
},
  "geometry": {"coordinates":[-74.944362,40.368561],"type":"Point"}
}