{
  "type": "Feature",
  "properties": {
    "iso:country":"US",
    "sg:address":"325 Totowa Ave",
    "sg:city":"Paterson",
    "sg:classifiers":[
        {
            "category":"Restaurant",
            "type":"Food & Drink"
        }
    ],
    "sg:phone":"+1 973 595 1919",
    "sg:postcode":"07502",
    "sg:province":"NJ",
    "wof:name":"Belton's Cafe",
    "wof:placetype":"venue"
},
  "geometry": {"coordinates":[-74.186302,40.917099],"type":"Point"}
}