{
  "type": "Feature",
  "properties": {
    "iso:country":"US",
    "sg:address":"2198 Stanley Ter",
    "sg:city":"Union",
    "sg:classifiers":[
        {
            "category":"Manufacturing",
            "subcategory":"Metals",
            "type":"Manufacturing & Wholesale Goods"
        }
    ],
    "sg:phone":"+1 908 686 0930",
    "sg:postcode":"07083",
    "sg:province":"NJ",
    "sg:tags":[
        "fabricator",
        "metalwork",
        "sheet",
        "mfg"
    ],
    "wof:name":"Coronation Sheet Metal Co Inc",
    "wof:placetype":"venue"
},
  "geometry": {"coordinates":[-74.26750199999999,40.713976],"type":"Point"}
}