{
  "type": "Feature",
  "properties": {
    "addr:full":"90 County Rd Tenafly NJ 07670",
    "addr:housenumber":"90",
    "addr:postcode":"07670",
    "addr:street":"County Rd",
    "iso:country":"US",
    "sg:address":"90 County Rd",
    "sg:city":"Tenafly",
    "sg:classifiers":[
        {
            "category":"Autos & Motor Vehicles",
            "subcategory":"Automobile Sales",
            "type":"Retail Goods"
        }
    ],
    "sg:phone":"+1   ",
    "sg:postcode":"07670",
    "sg:province":"NJ",
    "wof:name":"Tenafly Peugeot",
    "wof:placetype":"venue"
},
  "geometry": {"coordinates":[-73.96180699999999,40.928125],"type":"Point"}
}