{
  "type": "Feature",
  "properties": {
    "addr:full":"502 Boulevard Kenilworth NJ 07033",
    "addr:housenumber":"502",
    "addr:postcode":"07033",
    "addr:street":"Boulevard",
    "iso:country":"US",
    "sg:address":"502 Boulevard",
    "sg:city":"Kenilworth",
    "sg:classifiers":[
        {
            "category":"Restaurant",
            "type":"Food & Drink"
        }
    ],
    "sg:phone":"+1   ",
    "sg:postcode":"07033",
    "sg:province":"NJ",
    "sg:tags":[
        "eating"
    ],
    "wof:name":"Pergup Inc",
    "wof:placetype":"venue"
},
  "geometry": {"coordinates":[-74.291522,40.67612],"type":"Point"}
}