{
  "type": "Feature",
  "properties": {
    "addr:full":"199 State Rte 10 Randolph NJ 07869",
    "addr:housenumber":"199",
    "addr:postcode":"07869",
    "addr:street":"State Rte 10",
    "iso:country":"US",
    "sg:address":"199 State Rte 10",
    "sg:city":"Randolph",
    "sg:classifiers":[
        {
            "category":"Professional",
            "type":"Services"
        }
    ],
    "sg:phone":"+1 973 601 0700",
    "sg:postcode":"07869",
    "sg:province":"NJ",
    "wof:name":"RMS One",
    "wof:placetype":"venue"
},
  "geometry": {"coordinates":[-74.543216,40.872351],"type":"Point"}
}