{
  "type": "Feature",
  "properties": {
    "iso:country":"US",
    "sg:address":"387 Tylers Mill Rd",
    "sg:city":"Sewell",
    "sg:classifiers":[
        {
            "category":"Retail",
            "subcategory":"Auto Repair",
            "type":"Services"
        }
    ],
    "sg:phone":"+1 856 589 4333",
    "sg:postcode":"08080",
    "sg:province":"NJ",
    "sg:tags":[
        "body",
        "automotive",
        "sanitary"
    ],
    "wof:name":"Tyler Mill Towing",
    "wof:placetype":"venue"
},
  "geometry": {"coordinates":[-75.133072,39.751307],"type":"Point"}
}