{
  "type": "Feature",
  "properties": {
    "addr:full":"19 Franklin Pl Ste 105 Rutherford NJ 07070",
    "addr:housenumber":"19",
    "addr:postcode":"07070",
    "addr:street":"Franklin Pl Ste 105",
    "iso:country":"US",
    "sg:address":"19 Franklin Pl Ste 105",
    "sg:city":"Rutherford",
    "sg:classifiers":[
        {
            "category":"Professional",
            "subcategory":"Lawyer & Legal Services",
            "type":"Services"
        }
    ],
    "sg:phone":"+1 201 933 3240",
    "sg:postcode":"07070",
    "sg:province":"NJ",
    "wof:name":"Mark Yampaglia Law PC",
    "wof:placetype":"venue"
},
  "geometry": {"coordinates":[-74.104786,40.827902],"type":"Point"}
}