{
  "type": "Feature",
  "properties": {
    "addr:full":"100 Springfield Ave Summit NJ 07901",
    "addr:housenumber":"100",
    "addr:postcode":"07901",
    "addr:street":"Springfield Ave",
    "iso:country":"US",
    "sg:address":"100 Springfield Ave",
    "sg:city":"Summit",
    "sg:classifiers":[
        {
            "category":"Autos & Motor Vehicles",
            "subcategory":"Automobile Sales",
            "type":"Retail Goods"
        }
    ],
    "sg:phone":"+1   ",
    "sg:postcode":"07901",
    "sg:province":"NJ",
    "sg:tags":[
        "used"
    ],
    "wof:name":"Rolfs",
    "wof:placetype":"venue"
},
  "geometry": {"coordinates":[-74.339484,40.715887],"type":"Point"}
}