{
  "type": "Feature",
  "properties": {
    "iso:country":"US",
    "sg:address":"41 Big Spring Rd",
    "sg:city":"Franklin",
    "sg:classifiers":[
        {
            "category":"Professional",
            "subcategory":"Business Services",
            "type":"Services"
        }
    ],
    "sg:phone":"+1   ",
    "sg:postcode":"07416",
    "sg:province":"NJ",
    "wof:name":"Bill Pierce and Sons",
    "wof:placetype":"venue"
},
  "geometry": {"coordinates":[-74.622075,41.128069],"type":"Point"}
}