{
  "type": "Feature",
  "properties": {
    "iso:country":"US",
    "sg:address":"24 Franklin Ave",
    "sg:city":"Nutley",
    "sg:classifiers":[
        {
            "category":"Professional",
            "subcategory":"Business Services",
            "type":"Services"
        }
    ],
    "sg:phone":"+1 973 667 7122",
    "sg:postcode":"07110",
    "sg:province":"NJ",
    "sg:tags":[
        "broker"
    ],
    "wof:name":"Discount Family Meds Of Canada",
    "wof:placetype":"venue"
},
  "geometry": {"coordinates":[-74.165525,40.810349],"type":"Point"}
}