{
  "type": "Feature",
  "properties": {
    "addr:full":"115 Forest Rd Brick NJ 08724",
    "addr:housenumber":"115",
    "addr:postcode":"08724",
    "addr:street":"Forest Rd",
    "iso:country":"US",
    "sg:address":"115 Forest Rd",
    "sg:city":"Brick",
    "sg:classifiers":[
        {
            "category":"Building & Trades",
            "subcategory":"Construction",
            "type":"Services"
        }
    ],
    "sg:phone":"+1 732 202 1000",
    "sg:postcode":"08724",
    "sg:province":"NJ",
    "sg:tags":[
        "house"
    ],
    "wof:name":"Palsco LLC",
    "wof:placetype":"venue"
},
  "geometry": {"coordinates":[-74.118275,40.06768],"type":"Point"}
}