{
  "type": "Feature",
  "properties": {
    "iso:country":"US",
    "sg:address":"800 South Ave",
    "sg:city":"Plainfield",
    "sg:classifiers":[
        {
            "category":"Wholesale",
            "subcategory":"Electrical",
            "type":"Manufacturing & Wholesale Goods"
        }
    ],
    "sg:phone":"+1 908 757 4245",
    "sg:postcode":"07062",
    "sg:province":"NJ",
    "sg:tags":[
        "parts",
        "appliance"
    ],
    "sg:website":"www.apwagner.com",
    "wof:name":"A P Wagner Inc",
    "wof:placetype":"venue"
},
  "geometry": {"coordinates":[-74.405992,40.626546],"type":"Point"}
}