{
  "type": "Feature",
  "properties": {
    "iso:country":"US",
    "sg:address":"256 Broad St",
    "sg:city":"Keyport",
    "sg:classifiers":[
        {
            "category":"Professional",
            "subcategory":"Detective & Security Services",
            "type":"Services"
        }
    ],
    "sg:phone":"+1   ",
    "sg:postcode":"07735",
    "sg:province":"NJ",
    "sg:tags":[
        "system"
    ],
    "wof:name":"Safe Kids Cards",
    "wof:placetype":"venue"
},
  "geometry": {"coordinates":[-74.197641,40.428745],"type":"Point"}
}