{
  "type": "Feature",
  "properties": {
    "addr:full":"146 N 1st St Paterson NJ 07522",
    "addr:housenumber":"146",
    "addr:postcode":"07522",
    "addr:street":"N 1St St",
    "iso:country":"US",
    "sg:address":"146 N 1st St",
    "sg:city":"Paterson",
    "sg:classifiers":[
        {
            "category":"Manufacturing",
            "subcategory":"Chemicals & Compounds",
            "type":"Manufacturing & Wholesale Goods"
        }
    ],
    "sg:phone":"+1 973 650 2191",
    "sg:postcode":"07522",
    "sg:province":"NJ",
    "wof:name":"Ahart Chemical Co",
    "wof:placetype":"venue"
},
  "geometry": {"coordinates":[-74.16978899999999,40.927651],"type":"Point"}
}