{
  "type": "Feature",
  "properties": {
    "addr:full":"365 E 22nd St Paterson NJ 07514",
    "addr:housenumber":"365",
    "addr:postcode":"07514",
    "addr:street":"E 22Nd St",
    "iso:country":"US",
    "sg:address":"365 E 22nd St",
    "sg:city":"Paterson",
    "sg:classifiers":[
        {
            "category":"Manufacturing",
            "subcategory":"Tools & Machinery",
            "type":"Manufacturing & Wholesale Goods"
        }
    ],
    "sg:phone":"+1 973 523 8610",
    "sg:postcode":"07514",
    "sg:province":"NJ",
    "sg:tags":[
        "foot",
        "appliance"
    ],
    "sg:website":"www.performlab.com",
    "wof:name":"Performance Laboratories",
    "wof:placetype":"venue"
},
  "geometry": {"coordinates":[-74.149974,40.92736],"type":"Point"}
}