{
  "type": "Feature",
  "properties": {
    "iso:country":"US",
    "sg:address":"306 Harding Hwy",
    "sg:city":"Carneys Point",
    "sg:classifiers":[
        {
            "category":"Retail",
            "subcategory":"Repair Shop",
            "type":"Services"
        },
        {
            "category":"Manufacturing",
            "subcategory":"Tools & Machinery",
            "type":"Manufacturing & Wholesale Goods"
        }
    ],
    "sg:phone":"+1 856 299 0485",
    "sg:postcode":"08069",
    "sg:province":"NJ",
    "sg:tags":[
        "television",
        "printer",
        "laser",
        "cartridge",
        "mfg",
        "ton",
        "toner",
        "radio"
    ],
    "wof:name":"Baron Laser Concepts Inc",
    "wof:placetype":"venue"
},
  "geometry": {"coordinates":[-75.452996,39.715094],"type":"Point"}
}