{
  "type": "Feature",
  "properties": {
    "iso:country":"US",
    "sg:address":"2 Toronto Dr",
    "sg:city":"Brick",
    "sg:classifiers":[
        {
            "category":"Professional",
            "type":"Services"
        }
    ],
    "sg:phone":"+1 732 657 5677",
    "sg:postcode":"08723",
    "sg:province":"NJ",
    "sg:tags":[
        "establishment"
    ],
    "wof:name":"Dirienzo & Dirienzo",
    "wof:placetype":"venue"
},
  "geometry": {"coordinates":[-74.08721199999999,40.014123],"type":"Point"}
}