{
  "type": "Feature",
  "properties": {
    "iso:country":"US",
    "sg:address":"975 W Park Ave",
    "sg:city":"Vineland",
    "sg:classifiers":[
        {
            "category":"Shopping",
            "type":"Retail Goods"
        }
    ],
    "sg:phone":"+1   ",
    "sg:postcode":"08360",
    "sg:province":"NJ",
    "sg:tags":[
        "merchandise"
    ],
    "wof:name":"Fugawe Motor Sports",
    "wof:placetype":"venue"
},
  "geometry": {"coordinates":[-75.04389500000001,39.492469],"type":"Point"}
}