{
  "type": "Feature",
  "properties": {
    "iso:country":"US",
    "sg:address":"400 N Bridge St",
    "sg:city":"Bridgewater",
    "sg:classifiers":[
        {
            "category":"Recreation",
            "type":"Entertainment"
        }
    ],
    "sg:phone":"+1   ",
    "sg:postcode":"08807",
    "sg:province":"NJ",
    "wof:name":"E T & Embroidery Technology",
    "wof:placetype":"venue"
},
  "geometry": {"coordinates":[-74.608228,40.58139],"type":"Point"}
}