{
  "type": "Feature",
  "properties": {
    "iso:country":"US",
    "sg:address":"50 Lorton Rd",
    "sg:city":"Old Bridge",
    "sg:classifiers":[
        {
            "category":"Building & Trades",
            "subcategory":"Construction",
            "type":"Services"
        }
    ],
    "sg:phone":"+1 732 416 1650",
    "sg:postcode":"08857",
    "sg:province":"NJ",
    "sg:tags":[
        "house"
    ],
    "wof:name":"Distinctive Builders LLC",
    "wof:placetype":"venue"
},
  "geometry": {"coordinates":[-74.366792,40.392383],"type":"Point"}
}