{
  "type": "Feature",
  "properties": {
    "iso:country":"US",
    "sg:address":"904 Seagull Dr",
    "sg:city":"Lanoka Harbor",
    "sg:classifiers":[
        {
            "category":"Building & Trades",
            "subcategory":"Pest Control",
            "type":"Services"
        }
    ],
    "sg:phone":"+1 609 693 2757",
    "sg:postcode":"08734",
    "sg:province":"NJ",
    "wof:name":"Advanced Pest Control Services",
    "wof:placetype":"venue"
},
  "geometry": {"coordinates":[-74.147764,39.867544],"type":"Point"}
}