{
  "type": "Feature",
  "properties": {
    "addr:full":"10 Parsonage Rd Edison NJ 08837",
    "addr:housenumber":"10",
    "addr:postcode":"08837",
    "addr:street":"Parsonage Rd",
    "iso:country":"US",
    "sg:address":"10 Parsonage Rd",
    "sg:city":"Edison",
    "sg:classifiers":[
        {
            "category":"Professional",
            "subcategory":"Computer Services",
            "type":"Services"
        }
    ],
    "sg:phone":"+1   ",
    "sg:postcode":"08837",
    "sg:province":"NJ",
    "sg:tags":[
        "related"
    ],
    "wof:name":"Cornell Computer Corp",
    "wof:placetype":"venue"
},
  "geometry": {"coordinates":[-74.33131,40.545216],"type":"Point"}
}