{
  "type": "Feature",
  "properties": {
    "addr:full":"979 US Hwy 1 North Brunswick NJ 08902",
    "addr:housenumber":"979",
    "addr:postcode":"08902",
    "addr:street":"Us Hwy 1",
    "iso:country":"US",
    "sg:address":"979 US Hwy 1",
    "sg:city":"North Brunswick",
    "sg:classifiers":[
        {
            "category":"Professional",
            "subcategory":"Accounting & Tax Preparation",
            "type":"Services"
        }
    ],
    "sg:phone":"+1 732 448 1040",
    "sg:postcode":"08902",
    "sg:province":"NJ",
    "sg:tags":[
        "return",
        "filing"
    ],
    "wof:name":"Jackson Hewitt Tax Svc",
    "wof:placetype":"venue"
},
  "geometry": {"coordinates":[-74.470412,40.458748],"type":"Point"}
}