{
  "type": "Feature",
  "properties": {
    "iso:country":"US",
    "sg:address":"162 Merritt Ave",
    "sg:city":"Bergenfield",
    "sg:classifiers":[
        {
            "category":"Building & Trades",
            "subcategory":"Landscaping Services",
            "type":"Services"
        }
    ],
    "sg:phone":"+1 201 387 6183",
    "sg:postcode":"07621",
    "sg:province":"NJ",
    "sg:tags":[
        "landscape"
    ],
    "wof:name":"Standish Landscaping Inc",
    "wof:placetype":"venue"
},
  "geometry": {"coordinates":[-73.988317,40.93478],"type":"Point"}
}