{
  "type": "Feature",
  "properties": {
    "addr:full":"587 Carroll St Orange NJ 07050",
    "addr:housenumber":"587",
    "addr:postcode":"07050",
    "addr:street":"Carroll St",
    "iso:country":"US",
    "sg:address":"587 Carroll St",
    "sg:city":"Orange",
    "sg:classifiers":[
        {
            "category":"Real Estate",
            "subcategory":"Real Estate Operator",
            "type":"Services"
        }
    ],
    "sg:phone":"+1 973 674 0303",
    "sg:postcode":"07050",
    "sg:province":"NJ",
    "sg:tags":[
        "apartment"
    ],
    "sg:website":"www.cjapts.com",
    "wof:name":"Washington-Dodd Apartments",
    "wof:placetype":"venue"
},
  "geometry": {"coordinates":[-74.220398,40.786499],"type":"Point"}
}