{
  "type": "Feature",
  "properties": {
    "addr:full":"786 Saint Georges Ave Rahway NJ 07065",
    "addr:housenumber":"786",
    "addr:postcode":"07065",
    "addr:street":"Saint Georges Ave",
    "iso:country":"US",
    "sg:address":"786 Saint Georges Ave",
    "sg:city":"Rahway",
    "sg:classifiers":[
        {
            "category":"Shopping",
            "subcategory":"Pharmacy",
            "type":"Retail Goods"
        }
    ],
    "sg:phone":"+1 732 499 4582",
    "sg:postcode":"07065",
    "sg:province":"NJ",
    "sg:tags":[
        "drugstore"
    ],
    "sg:website":"www.walgreens.com",
    "wof:name":"Walgreen Drug Store",
    "wof:placetype":"venue"
},
  "geometry": {"coordinates":[-74.282402,40.6087],"type":"Point"}
}