{
  "type": "Feature",
  "properties": {
    "addr:full":"765 14th Ave Paterson NJ 07504",
    "addr:housenumber":"765",
    "addr:postcode":"07504",
    "addr:street":"14Th Ave",
    "iso:country":"US",
    "sg:address":"765 14th Ave",
    "sg:city":"Paterson",
    "sg:classifiers":[
        {
            "category":"Education",
            "subcategory":"School",
            "type":"Public Place"
        }
    ],
    "sg:phone":"+1 973 278 4135",
    "sg:postcode":"07504",
    "sg:province":"NJ",
    "sg:tags":[
        "elementary",
        "religious"
    ],
    "wof:name":"St Therese's School",
    "wof:placetype":"venue"
},
  "geometry": {"coordinates":[-74.1409,40.915901],"type":"Point"}
}