{
  "type": "Feature",
  "properties": {
    "iso:country":"US",
    "sg:address":"111 Mulberry St",
    "sg:city":"Newark",
    "sg:classifiers":[
        {
            "category":"Banks & Credit Unions",
            "subcategory":"Investment Brokerage",
            "type":"Services"
        }
    ],
    "sg:phone":"+1 973 624 1000",
    "sg:postcode":"07102",
    "sg:province":"NJ",
    "sg:tags":[
        "advisory",
        "financial"
    ],
    "wof:name":"Elite Financial Solutions",
    "wof:placetype":"venue"
},
  "geometry": {"coordinates":[-74.169123,40.735247],"type":"Point"}
}