{
  "type": "Feature",
  "properties": {
    "iso:country":"US",
    "sg:address":"15 Willow Ln",
    "sg:city":"Milford",
    "sg:classifiers":[
        {
            "category":"Building & Trades",
            "subcategory":"Construction",
            "type":"Services"
        }
    ],
    "sg:phone":"+1 908 995 4679",
    "sg:postcode":"08848",
    "sg:province":"NJ",
    "sg:tags":[
        "woodworker"
    ],
    "wof:name":"J Raymond E Co",
    "wof:placetype":"venue"
},
  "geometry": {"coordinates":[-75.156736,40.619467],"type":"Point"}
}