{
  "type": "Feature",
  "properties": {
    "addr:full":"224 Lancaster Ct Belle Mead NJ 08502",
    "addr:housenumber":"224",
    "addr:postcode":"08502",
    "addr:street":"Lancaster Ct Belle Mead",
    "iso:country":"US",
    "sg:address":"224 Lancaster Ct",
    "sg:city":"Belle Mead",
    "sg:classifiers":[
        {
            "category":"Professional",
            "subcategory":"Advertising",
            "type":"Services"
        }
    ],
    "sg:phone":"+1 908 874 3859",
    "sg:postcode":"08502",
    "sg:province":"NJ",
    "sg:tags":[
        "mail",
        "direct"
    ],
    "wof:name":"Direct Project Management",
    "wof:placetype":"venue"
},
  "geometry": {"coordinates":[-74.65857200000001,40.463156],"type":"Point"}
}