{
  "type": "Feature",
  "properties": {
    "addr:full":"1751 Good Intent Rd Woodbury NJ 08096",
    "addr:housenumber":"1751",
    "addr:postcode":"08096",
    "addr:street":"Good Intent Rd",
    "iso:country":"US",
    "sg:address":"1751 Good Intent Rd",
    "sg:city":"Woodbury",
    "sg:classifiers":[
        {
            "category":"Wholesale",
            "subcategory":"Plants",
            "type":"Manufacturing & Wholesale Goods"
        }
    ],
    "sg:phone":"+1 856 232 1200",
    "sg:postcode":"08096",
    "sg:province":"NJ",
    "sg:tags":[
        "florist"
    ],
    "wof:name":"Falls Wholesale Florist LLC",
    "wof:placetype":"venue"
},
  "geometry": {"coordinates":[-75.10071000000001,39.810656],"type":"Point"}
}