{
  "type": "Feature",
  "properties": {
    "addr:full":"15 Chadwick Rd Livingston NJ 07039",
    "addr:housenumber":"15",
    "addr:postcode":"07039",
    "addr:street":"Chadwick Rd",
    "iso:country":"US",
    "sg:address":"15 Chadwick Rd",
    "sg:city":"Livingston",
    "sg:classifiers":[
        {
            "category":"Social Services",
            "type":"Services"
        }
    ],
    "sg:phone":"+1 973 994 4924",
    "sg:postcode":"07039",
    "sg:province":"NJ",
    "sg:tags":[
        "organization",
        "welfare"
    ],
    "wof:name":"New Jersey Assn Of School",
    "wof:placetype":"venue"
},
  "geometry": {"coordinates":[-74.328699,40.800788],"type":"Point"}
}