{
  "type": "Feature",
  "properties": {
    "iso:country":"US",
    "sg:address":"26 Chestnut Ridge Rd",
    "sg:city":"Montvale",
    "sg:classifiers":[
        {
            "category":"Professional",
            "subcategory":"Printing & Photocopies",
            "type":"Services"
        }
    ],
    "sg:phone":"+1 201 307 1033",
    "sg:postcode":"07645",
    "sg:province":"NJ",
    "sg:tags":[
        "duplicating",
        "copying"
    ],
    "wof:name":"Postnet",
    "wof:placetype":"venue"
},
  "geometry": {"coordinates":[-74.069596,41.050895],"type":"Point"}
}