{
  "type": "Feature",
  "properties": {
    "iso:country":"US",
    "sg:address":"215 Ridge Rd",
    "sg:city":"North Arlington",
    "sg:classifiers":[
        {
            "category":"Building & Trades",
            "subcategory":"Locksmith",
            "type":"Services"
        }
    ],
    "sg:phone":"+1 888 293 2495",
    "sg:postcode":"07031",
    "sg:province":"NJ",
    "sg:tags":[
        "key"
    ],
    "wof:name":"Anytime Anywhere Emergency Locksmith",
    "wof:placetype":"venue"
},
  "geometry": {"coordinates":[-74.13330000000001,40.788847],"type":"Point"}
}