{
  "type": "Feature",
  "properties": {
    "iso:country":"US",
    "sg:address":"157 Mansfield Blvd N",
    "sg:city":"Cherry Hill",
    "sg:classifiers":[
        {
            "category":"Communications",
            "subcategory":"Radio Station",
            "type":"Services"
        }
    ],
    "sg:phone":"+1 856 354 2190",
    "sg:postcode":"08034",
    "sg:province":"NJ",
    "sg:tags":[
        "education",
        "prevention"
    ],
    "wof:name":"Karen Fox",
    "wof:placetype":"venue"
},
  "geometry": {"coordinates":[-75.013324,39.888719],"type":"Point"}
}