{
  "type": "Feature",
  "properties": {
    "iso:country":"US",
    "sg:address":"91 Woodside Rd",
    "sg:city":"Maplewood",
    "sg:classifiers":[
        {
            "category":"Professional",
            "subcategory":"Computer Services",
            "type":"Services"
        }
    ],
    "sg:phone":"+1   ",
    "sg:postcode":"07040",
    "sg:province":"NJ",
    "sg:tags":[
        "design",
        "system",
        "analysis"
    ],
    "wof:name":"Shorebird Enterprises Inc",
    "wof:placetype":"venue"
},
  "geometry": {"coordinates":[-74.245508,40.728881],"type":"Point"}
}