{
  "type": "Feature",
  "properties": {
    "addr:full":"293 Eisenhower Pkwy Livingston NJ 07039",
    "addr:housenumber":"293",
    "addr:postcode":"07039",
    "addr:street":"Eisenhower Pkwy",
    "iso:country":"US",
    "sg:address":"293 Eisenhower Pkwy",
    "sg:city":"Livingston",
    "sg:classifiers":[
        {
            "category":"Professional",
            "subcategory":"Accounting & Tax Preparation",
            "type":"Services"
        }
    ],
    "sg:phone":"+1 973 994 9494",
    "sg:postcode":"07039",
    "sg:province":"NJ",
    "sg:tags":[
        "accountant"
    ],
    "sg:website":"www.sobel-cpa.com",
    "wof:name":"Sobel & Co",
    "wof:placetype":"venue"
},
  "geometry": {"coordinates":[-74.34140499999999,40.798795],"type":"Point"}
}