{
  "type": "Feature",
  "properties": {
    "addr:full":"11 Karena Ln Lawrenceville NJ 08648",
    "addr:housenumber":"11",
    "addr:postcode":"08648",
    "addr:street":"Karena Ln",
    "iso:country":"US",
    "sg:address":"11 Karena Ln",
    "sg:city":"Lawrenceville",
    "sg:classifiers":[
        {
            "category":"Building & Trades",
            "subcategory":"Plumbing",
            "type":"Services"
        }
    ],
    "sg:phone":"+1 609 895 2673",
    "sg:postcode":"08648",
    "sg:province":"NJ",
    "sg:tags":[
        "conditioning",
        "air",
        "system",
        "contractor"
    ],
    "wof:name":"Steeleco Inc",
    "wof:placetype":"venue"
},
  "geometry": {"coordinates":[-74.761337,40.28393],"type":"Point"}
}