{
  "type": "Feature",
  "properties": {
    "iso:country":"US",
    "sg:address":"185 State Rte 17",
    "sg:city":"Paramus",
    "sg:classifiers":[
        {
            "category":"Professional",
            "type":"Services"
        }
    ],
    "sg:phone":"+1 201 967 5104",
    "sg:postcode":"07652",
    "sg:province":"NJ",
    "sg:tags":[
        "establishment"
    ],
    "wof:name":"South 17 Assoc",
    "wof:placetype":"venue"
},
  "geometry": {"coordinates":[-74.07083900000001,40.90987],"type":"Point"}
}