{
  "type": "Feature",
  "properties": {
    "iso:country":"US",
    "sg:address":"1 Commerce Dr",
    "sg:city":"Cranford",
    "sg:classifiers":[
        {
            "category":"Professional",
            "subcategory":"Advertising",
            "type":"Services"
        }
    ],
    "sg:phone":"+1   ",
    "sg:postcode":"07016",
    "sg:province":"NJ",
    "sg:tags":[
        "consultant",
        "agency"
    ],
    "wof:name":"B/R Advertising Corp",
    "wof:placetype":"venue"
},
  "geometry": {"coordinates":[-74.284792,40.648419],"type":"Point"}
}