{
  "type": "Feature",
  "properties": {
    "iso:country":"US",
    "sg:address":"535 41st St",
    "sg:city":"Union City",
    "sg:classifiers":[
        {
            "category":"Social Services",
            "type":"Services"
        }
    ],
    "sg:phone":"+1   ",
    "sg:postcode":"07087",
    "sg:province":"NJ",
    "sg:tags":[
        "child",
        "day",
        "care"
    ],
    "wof:name":"Head Start North Hudson Comm",
    "wof:placetype":"venue"
},
  "geometry": {"coordinates":[-74.027289,40.777593],"type":"Point"}
}