{
  "type": "Feature",
  "properties": {
    "iso:country":"US",
    "sg:address":"505 Ringwood Ave",
    "sg:city":"Pompton Lakes",
    "sg:classifiers":[
        {
            "category":"Shopping",
            "subcategory":"Discount & Variety Stores",
            "type":"Retail Goods"
        }
    ],
    "sg:phone":"+1 973 835 9515",
    "sg:postcode":"07442",
    "sg:province":"NJ",
    "sg:tags":[
        "wholesale"
    ],
    "sg:website":"www.northeastjanitorial.com",
    "wof:name":"Northeast Janitorial Supply",
    "wof:placetype":"venue"
},
  "geometry": {"coordinates":[-74.295249,41.005957],"type":"Point"}
}