{
  "type": "Feature",
  "properties": {
    "addr:full":"221 E 23rd Ave North Wildwood NJ 08260",
    "addr:housenumber":"221",
    "addr:postcode":"08260",
    "addr:street":"E 23Rd Ave North",
    "iso:country":"US",
    "sg:address":"221 E 23rd Ave",
    "sg:city":"North Wildwood",
    "sg:classifiers":[
        {
            "category":"Travel",
            "subcategory":"Hotels & Motels",
            "type":"Entertainment"
        }
    ],
    "sg:phone":"+1 609 522 5553",
    "sg:postcode":"08260",
    "sg:province":"NJ",
    "sg:tags":[
        "operation"
    ],
    "wof:name":"San's Motel",
    "wof:placetype":"venue"
},
  "geometry": {"coordinates":[-74.805356,38.994041],"type":"Point"}
}