{
  "type": "Feature",
  "properties": {
    "addr:full":"1551 US Hwy 46 Ledgewood NJ 07852",
    "addr:housenumber":"1551",
    "addr:postcode":"07852",
    "addr:street":"Us Hwy 46",
    "iso:country":"US",
    "sg:address":"1551 US Hwy 46",
    "sg:city":"Ledgewood",
    "sg:classifiers":[
        {
            "category":"Retail",
            "subcategory":"Auto Repair",
            "type":"Services"
        }
    ],
    "sg:phone":"+1 973 927 0066",
    "sg:postcode":"07852",
    "sg:province":"NJ",
    "sg:tags":[
        "general"
    ],
    "wof:name":"Approved Auto Electric",
    "wof:placetype":"venue"
},
  "geometry": {"coordinates":[-74.66678400000001,40.890328],"type":"Point"}
}