{
  "type": "Feature",
  "properties": {
    "iso:country":"US",
    "sg:address":"33 Union St",
    "sg:city":"Mt Holly",
    "sg:classifiers":[
        {
            "category":"Professional",
            "subcategory":"Lawyer & Legal Services",
            "type":"Services"
        }
    ],
    "sg:phone":"+1 609 261 9103",
    "sg:postcode":"08060",
    "sg:province":"NJ",
    "sg:tags":[
        "attorney"
    ],
    "wof:name":"Mohanty & Rothmel",
    "wof:placetype":"venue"
},
  "geometry": {"coordinates":[-74.787471,39.997437],"type":"Point"}
}