{
  "type": "Feature",
  "properties": {
    "iso:country":"US",
    "sg:address":"58 Heights Rd",
    "sg:city":"Wayne",
    "sg:classifiers":[
        {
            "category":"Building & Trades",
            "subcategory":"Plumbing",
            "type":"Services"
        }
    ],
    "sg:phone":"+1 973 696 2285",
    "sg:postcode":"07470",
    "sg:province":"NJ",
    "wof:name":"Markowski Plumbing & Heating",
    "wof:placetype":"venue"
},
  "geometry": {"coordinates":[-74.247101,40.9203],"type":"Point"}
}