{
  "type": "Feature",
  "properties": {
    "addr:full":"201 Washington St Newark NJ 07102",
    "addr:housenumber":"201",
    "addr:postcode":"07102",
    "addr:street":"Washington St",
    "iso:country":"US",
    "sg:address":"201 Washington St",
    "sg:city":"Newark",
    "sg:classifiers":[
        {
            "category":"Professional",
            "subcategory":"Lawyer & Legal Services",
            "type":"Services"
        }
    ],
    "sg:phone":"+1 973 642 7005",
    "sg:postcode":"07102",
    "sg:province":"NJ",
    "sg:tags":[
        "attorney"
    ],
    "wof:name":"Sinins & Bross PA",
    "wof:placetype":"venue"
},
  "geometry": {"coordinates":[-74.174042,40.738191],"type":"Point"}
}