{
  "type": "Feature",
  "properties": {
    "addr:full":"4 Sandys Rd Andover NJ 07821",
    "addr:housenumber":"4",
    "addr:postcode":"07821",
    "addr:street":"Sandys Rd",
    "iso:country":"US",
    "sg:address":"4 Sandys Rd",
    "sg:city":"Andover",
    "sg:classifiers":[
        {
            "category":"Building & Trades",
            "subcategory":"Construction",
            "type":"Services"
        }
    ],
    "sg:phone":"+1 973 277 3436",
    "sg:postcode":"07821",
    "sg:province":"NJ",
    "sg:tags":[
        "carpentry",
        "contractor"
    ],
    "wof:name":"TNT Windows",
    "wof:placetype":"venue"
},
  "geometry": {"coordinates":[-74.71844900000001,40.973347],"type":"Point"}
}