{
  "type": "Feature",
  "properties": {
    "iso:country":"US",
    "sg:address":"909 Belmont Ave",
    "sg:city":"Haledon",
    "sg:classifiers":[
        {
            "category":"Shopping",
            "subcategory":"Florist",
            "type":"Retail Goods"
        }
    ],
    "sg:phone":"+1   ",
    "sg:postcode":"07508",
    "sg:province":"NJ",
    "wof:name":"Plaza Florist",
    "wof:placetype":"venue"
},
  "geometry": {"coordinates":[-74.18909499999999,40.952125],"type":"Point"}
}