{
  "type": "Feature",
  "properties": {
    "iso:country":"US",
    "sg:address":"219 Chestnut St",
    "sg:city":"Newark",
    "sg:classifiers":[
        {
            "category":"Health Services",
            "subcategory":"Hospital",
            "type":"Services"
        }
    ],
    "sg:phone":"+1   ",
    "sg:postcode":"07105",
    "sg:province":"NJ",
    "wof:name":"St Michaels Medical Center",
    "wof:placetype":"venue"
},
  "geometry": {"coordinates":[-74.166072,40.723549],"type":"Point"}
}