{
  "type": "Feature",
  "properties": {
    "addr:full":"689 Harmony Rd Middletown NJ 07748",
    "addr:housenumber":"689",
    "addr:postcode":"07748",
    "addr:street":"Harmony Rd",
    "iso:country":"US",
    "sg:address":"689 Harmony Rd",
    "sg:city":"Middletown",
    "sg:classifiers":[
        {
            "category":"Building & Trades",
            "subcategory":"Electrical",
            "type":"Services"
        }
    ],
    "sg:phone":"+1 732 495 2255",
    "sg:postcode":"07748",
    "sg:province":"NJ",
    "sg:tags":[
        "electrical",
        "electric",
        "contractor"
    ],
    "wof:name":"Fleetwood Electric Inc",
    "wof:placetype":"venue"
},
  "geometry": {"coordinates":[-74.121814,40.429376],"type":"Point"}
}