{
  "type": "Feature",
  "properties": {
    "iso:country":"US",
    "sg:address":"739 E Landis Ave",
    "sg:city":"Vineland",
    "sg:classifiers":[
        {
            "category":"Professional",
            "subcategory":"Accounting & Tax Preparation",
            "type":"Services"
        }
    ],
    "sg:phone":"+1 856 692 4422",
    "sg:postcode":"08360",
    "sg:province":"NJ",
    "sg:tags":[
        "return",
        "filing"
    ],
    "wof:name":"R V Financial Svc",
    "wof:placetype":"venue"
},
  "geometry": {"coordinates":[-75.01956199999999,39.48581],"type":"Point"}
}