{
  "type": "Feature",
  "properties": {
    "addr:full":"71 Sherman Pl # 73 Garfield NJ 07026",
    "addr:housenumber":"71",
    "addr:postcode":"07026",
    "addr:street":"Sherman Pl # 73",
    "iso:country":"US",
    "sg:address":"71 Sherman Pl # 73",
    "sg:city":"Garfield",
    "sg:classifiers":[
        {
            "category":"Retail",
            "subcategory":"Auto Repair",
            "type":"Services"
        }
    ],
    "sg:phone":"+1 973 772 9155",
    "sg:postcode":"07026",
    "sg:province":"NJ",
    "wof:name":"Expert Auto Service",
    "wof:placetype":"venue"
},
  "geometry": {"coordinates":[-74.102501,40.871498],"type":"Point"}
}