{
  "type": "Feature",
  "properties": {
    "addr:full":"233 Dickinson St Ewing NJ 08638",
    "addr:housenumber":"233",
    "addr:postcode":"08638",
    "addr:street":"Dickinson St",
    "iso:country":"US",
    "sg:address":"233 Dickinson St",
    "sg:city":"Ewing",
    "sg:classifiers":[
        {
            "category":"Manufacturing",
            "subcategory":"Metals",
            "type":"Manufacturing & Wholesale Goods"
        }
    ],
    "sg:phone":"+1 609 394 6700",
    "sg:postcode":"08638",
    "sg:province":"NJ",
    "sg:tags":[
        "coating",
        "powder"
    ],
    "wof:name":"Powtek Powder Coating",
    "wof:placetype":"venue"
},
  "geometry": {"coordinates":[-74.743511,40.231411],"type":"Point"}
}