{
  "type": "Feature",
  "properties": {
    "addr:full":"27 Lakeside Blvd Hopatcong NJ 07843",
    "addr:housenumber":"27",
    "addr:postcode":"07843",
    "addr:street":"Lakeside Blvd",
    "iso:country":"US",
    "sg:address":"27 Lakeside Blvd",
    "sg:city":"Hopatcong",
    "sg:classifiers":[
        {
            "category":"Retail",
            "subcategory":"Auto Repair",
            "type":"Services"
        }
    ],
    "sg:phone":"+1 973 398 0070",
    "sg:postcode":"07843",
    "sg:province":"NJ",
    "sg:tags":[
        "repairing",
        "automobile"
    ],
    "wof:name":"Geller's Automotive",
    "wof:placetype":"venue"
},
  "geometry": {"coordinates":[-74.66610300000001,40.920686],"type":"Point"}
}