{
  "type": "Feature",
  "properties": {
    "iso:country":"US",
    "sg:address":"65 Leuning St",
    "sg:city":"South Hackensack",
    "sg:classifiers":[
        {
            "category":"Wholesale",
            "subcategory":"Machinery & Supplies",
            "type":"Manufacturing & Wholesale Goods"
        }
    ],
    "sg:phone":"+1 201 487 2565",
    "sg:postcode":"07606",
    "sg:province":"NJ",
    "sg:tags":[
        "truck"
    ],
    "wof:name":"Maintainco Inc",
    "wof:placetype":"venue"
},
  "geometry": {"coordinates":[-74.054728,40.872616],"type":"Point"}
}