{
  "type": "Feature",
  "properties": {
    "addr:full":"2001 State Rte 33 Trenton NJ 08690",
    "addr:housenumber":"2001",
    "addr:postcode":"08690",
    "addr:street":"State Rte 33",
    "iso:country":"US",
    "sg:address":"2001 State Rte 33",
    "sg:city":"Trenton",
    "sg:classifiers":[
        {
            "category":"Food & Beverages",
            "subcategory":"Groceries & Convenience Stores",
            "type":"Retail Goods"
        }
    ],
    "sg:phone":"+1 609 890 7653",
    "sg:postcode":"08690",
    "sg:province":"NJ",
    "sg:website":"www.wawa.com",
    "wof:name":"Wawa Food Market",
    "wof:placetype":"venue"
},
  "geometry": {"coordinates":[-74.645533,40.222792],"type":"Point"}
}