{
  "type": "Feature",
  "properties": {
    "iso:country":"US",
    "sg:address":"40 Sherri Way",
    "sg:city":"Clementon",
    "sg:classifiers":[
        {
            "category":"Manufacturing",
            "subcategory":"Tools & Machinery",
            "type":"Manufacturing & Wholesale Goods"
        }
    ],
    "sg:phone":"+1 856 783 6313",
    "sg:postcode":"08021",
    "sg:province":"NJ",
    "sg:tags":[
        "control",
        "environmental",
        "mfg"
    ],
    "wof:name":"Forney Corporation",
    "wof:placetype":"venue"
},
  "geometry": {"coordinates":[-75.009417,39.796531],"type":"Point"}
}