{
  "type": "Feature",
  "properties": {
    "addr:full":"65 E Main St Mendham NJ 07945",
    "addr:housenumber":"65",
    "addr:postcode":"07945",
    "addr:street":"E Main St",
    "iso:country":"US",
    "sg:address":"65 E Main St",
    "sg:city":"Mendham",
    "sg:classifiers":[
        {
            "category":"Organizations",
            "subcategory":"Religious Organization",
            "type":"Services"
        }
    ],
    "sg:phone":"+1 973 543 7595",
    "sg:postcode":"07945",
    "sg:province":"NJ",
    "sg:website":"www.gracemendham.org",
    "wof:name":"Grace Lutheran Church",
    "wof:placetype":"venue"
},
  "geometry": {"coordinates":[-74.5932,40.77923],"type":"Point"}
}