{
  "type": "Feature",
  "properties": {
    "iso:country":"US",
    "sg:address":"953 Stillwater Rd",
    "sg:city":"Newton",
    "sg:classifiers":[
        {
            "category":"Building & Trades",
            "subcategory":"Electrical",
            "type":"Services"
        }
    ],
    "sg:phone":"+1 973 300 0111",
    "sg:postcode":"07860",
    "sg:province":"NJ",
    "sg:tags":[
        "electrician"
    ],
    "wof:name":"De Lade Brothers Electric Inc",
    "wof:placetype":"venue"
},
  "geometry": {"coordinates":[-74.864372,41.054204],"type":"Point"}
}