{
  "type": "Feature",
  "properties": {
    "addr:full":"165 Union Ave Middlesex NJ 08846",
    "addr:housenumber":"165",
    "addr:postcode":"08846",
    "addr:street":"Union Ave",
    "iso:country":"US",
    "sg:address":"165 Union Ave",
    "sg:city":"Middlesex",
    "sg:classifiers":[
        {
            "category":"Building & Trades",
            "subcategory":"Landscaping Services",
            "type":"Services"
        }
    ],
    "sg:phone":"+1 732 627 0089",
    "sg:postcode":"08846",
    "sg:province":"NJ",
    "sg:tags":[
        "landscape"
    ],
    "wof:name":"Genesis Landscape Contractors",
    "wof:placetype":"venue"
},
  "geometry": {"coordinates":[-74.521834,40.567294],"type":"Point"}
}