{
  "type": "Feature",
  "properties": {
    "addr:full":"256 Wall St Princeton NJ 08540",
    "addr:housenumber":"256",
    "addr:postcode":"08540",
    "addr:street":"Wall St",
    "iso:country":"US",
    "sg:address":"256 Wall St",
    "sg:city":"Princeton",
    "sg:classifiers":[
        {
            "category":"Social Services",
            "type":"Services"
        }
    ],
    "sg:phone":"+1   ",
    "sg:postcode":"08540",
    "sg:province":"NJ",
    "wof:name":"Montgmery Bhvral Healthcare PC",
    "wof:placetype":"venue"
},
  "geometry": {"coordinates":[-74.65096,40.396719],"type":"Point"}
}