{
  "type": "Feature",
  "properties": {
    "iso:country":"US",
    "sg:address":"147 S Main St",
    "sg:city":"Hackensack",
    "sg:classifiers":[
        {
            "category":"Manufacturing",
            "subcategory":"Chemicals & Compounds",
            "type":"Manufacturing & Wholesale Goods"
        }
    ],
    "sg:phone":"+1 973 777 7255",
    "sg:postcode":"07601",
    "sg:province":"NJ",
    "sg:tags":[
        "concrete"
    ],
    "wof:name":"L M Scofield Company",
    "wof:placetype":"venue"
},
  "geometry": {"coordinates":[-74.04572400000001,40.872647],"type":"Point"}
}