{
  "type": "Feature",
  "properties": {
    "iso:country":"US",
    "sg:address":"318 Cranbury Rd",
    "sg:city":"East Brunswick",
    "sg:classifiers":[
        {
            "category":"Social Services",
            "type":"Services"
        }
    ],
    "sg:phone":"+1 732 613 1309",
    "sg:postcode":"08816",
    "sg:province":"NJ",
    "wof:name":"Joseph Balint",
    "wof:placetype":"venue"
},
  "geometry": {"coordinates":[-74.392011,40.439288],"type":"Point"}
}