{
  "type": "Feature",
  "properties": {
    "iso:country":"US",
    "sg:address":"73 Millburn Ave",
    "sg:city":"Millburn",
    "sg:classifiers":[
        {
            "category":"Retail",
            "subcategory":"Auto Repair",
            "type":"Services"
        }
    ],
    "sg:phone":"+1   ",
    "sg:postcode":"07041",
    "sg:province":"NJ",
    "sg:tags":[
        "center",
        "tire"
    ],
    "wof:name":"Bernies Tire & Auto",
    "wof:placetype":"venue"
},
  "geometry": {"coordinates":[-74.28621800000001,40.722867],"type":"Point"}
}