{
  "type": "Feature",
  "properties": {
    "iso:country":"US",
    "sg:address":"218 Mountainview Rd",
    "sg:city":"Warren",
    "sg:classifiers":[
        {
            "category":"Wholesale",
            "subcategory":"Meat",
            "type":"Manufacturing & Wholesale Goods"
        }
    ],
    "sg:phone":"+1 908 647 5533",
    "sg:postcode":"07059",
    "sg:province":"NJ",
    "sg:tags":[
        "packer"
    ],
    "wof:name":"Dealaman Enterprises",
    "wof:placetype":"venue"
},
  "geometry": {"coordinates":[-74.523689,40.639531],"type":"Point"}
}