{
  "type": "Feature",
  "properties": {
    "iso:country":"US",
    "sg:address":"84 Broadway",
    "sg:city":"Woodcliff Lake",
    "sg:classifiers":[
        {
            "category":"Personal",
            "subcategory":"Beauty Salon",
            "type":"Services"
        }
    ],
    "sg:phone":"+1   ",
    "sg:postcode":"07677",
    "sg:province":"NJ",
    "sg:tags":[
        "shop"
    ],
    "wof:name":"Hair Garden",
    "wof:placetype":"venue"
},
  "geometry": {"coordinates":[-74.04087699999999,41.018108],"type":"Point"}
}