{
  "type": "Feature",
  "properties": {
    "addr:full":"10 Geronimo Way Oakland NJ 07436",
    "addr:housenumber":"10",
    "addr:postcode":"07436",
    "addr:street":"Geronimo Way",
    "iso:country":"US",
    "sg:address":"10 Geronimo Way",
    "sg:city":"Oakland",
    "sg:classifiers":[
        {
            "category":"Building & Trades",
            "subcategory":"Construction",
            "type":"Services"
        }
    ],
    "sg:phone":"+1 201 337 9286",
    "sg:postcode":"07436",
    "sg:province":"NJ",
    "sg:tags":[
        "residential"
    ],
    "wof:name":"Napolitano Contracting LL",
    "wof:placetype":"venue"
},
  "geometry": {"coordinates":[-74.214414,41.032139],"type":"Point"}
}