{
  "type": "Feature",
  "properties": {
    "iso:country":"US",
    "sg:address":"1003 Birchfield Dr",
    "sg:city":"Mount Laurel",
    "sg:classifiers":[
        {
            "category":"Professional",
            "subcategory":"Accounting & Tax Preparation",
            "type":"Services"
        }
    ],
    "sg:phone":"+1   ",
    "sg:postcode":"08054",
    "sg:province":"NJ",
    "sg:tags":[
        "consulting",
        "management",
        "s"
    ],
    "wof:name":"Manage Business Services",
    "wof:placetype":"venue"
},
  "geometry": {"coordinates":[-74.933933,39.93519],"type":"Point"}
}