{
  "type": "Feature",
  "properties": {
    "iso:country":"US",
    "sg:address":"35 Harding Ave",
    "sg:city":"Clifton",
    "sg:classifiers":[
        {
            "category":"Professional",
            "subcategory":"Business Services",
            "type":"Services"
        }
    ],
    "sg:phone":"+1   ",
    "sg:postcode":"07011",
    "sg:province":"NJ",
    "wof:name":"Mc Productions Inc",
    "wof:placetype":"venue"
},
  "geometry": {"coordinates":[-74.138711,40.876325],"type":"Point"}
}