{
  "type": "Feature",
  "properties": {
    "iso:country":"US",
    "sg:address":"112 State Rte 50",
    "sg:city":"Corbin City",
    "sg:classifiers":[
        {
            "category":"Professional",
            "type":"Services"
        }
    ],
    "sg:phone":"+1 609 628 1070",
    "sg:postcode":"08270",
    "sg:province":"NJ",
    "sg:tags":[
        "establishment"
    ],
    "wof:name":"Mulford's Deer Done Right",
    "wof:placetype":"venue"
},
  "geometry": {"coordinates":[-74.751593,39.297776],"type":"Point"}
}