{
  "type": "Feature",
  "properties": {
    "addr:full":"6415 Black Horse Pike Egg Harbor Twp NJ 08234",
    "addr:housenumber":"6415",
    "addr:postcode":"08234",
    "addr:street":"Black Horse Pike",
    "iso:country":"US",
    "sg:address":"6415 Black Horse Pike",
    "sg:city":"Egg Harbor Twp",
    "sg:classifiers":[
        {
            "category":"Travel",
            "subcategory":"Campground",
            "type":"Entertainment"
        },
        {
            "category":"Recreation",
            "type":"Entertainment"
        },
        {
            "category":"Recreation",
            "subcategory":"Amusement Park",
            "type":"Entertainment"
        }
    ],
    "sg:phone":"+1 609 641 7847",
    "sg:postcode":"08234",
    "sg:province":"NJ",
    "sg:tags":[
        "camp"
    ],
    "wof:name":"Story Book Land",
    "wof:placetype":"venue"
},
  "geometry": {"coordinates":[-74.59138900000001,39.423589],"type":"Point"}
}