{
  "type": "Feature",
  "properties": {
    "iso:country":"US",
    "sg:address":"48 E Front St",
    "sg:city":"Red Bank",
    "sg:classifiers":[
        {
            "category":"Professional",
            "type":"Services"
        }
    ],
    "sg:phone":"+1 732 345 0423",
    "sg:postcode":"07701",
    "sg:province":"NJ",
    "sg:tags":[
        "establishment"
    ],
    "wof:name":"Redwood Toxicology",
    "wof:placetype":"venue"
},
  "geometry": {"coordinates":[-74.063413,40.352675],"type":"Point"}
}