{
  "type": "Feature",
  "properties": {
    "iso:country":"US",
    "sg:address":"6110 Bergenline Pl",
    "sg:city":"West New York",
    "sg:classifiers":[
        {
            "category":"Shopping",
            "subcategory":"Optical Goods",
            "type":"Retail Goods"
        }
    ],
    "sg:phone":"+1 201 861 1234",
    "sg:postcode":"07093",
    "sg:province":"NJ",
    "sg:tags":[
        "optician"
    ],
    "wof:name":"Optivision",
    "wof:placetype":"venue"
},
  "geometry": {"coordinates":[-74.015333,40.790045],"type":"Point"}
}