{
  "type": "Feature",
  "properties": {
    "addr:full":"1712 Hancock Ln Burlington NJ 08016",
    "addr:housenumber":"1712",
    "addr:postcode":"08016",
    "addr:street":"Hancock Ln",
    "iso:country":"US",
    "sg:address":"1712 Hancock Ln",
    "sg:city":"Burlington",
    "sg:classifiers":[
        {
            "category":"Building & Trades",
            "subcategory":"Construction",
            "type":"Services"
        }
    ],
    "sg:phone":"+1 609 747 7758",
    "sg:postcode":"08016",
    "sg:province":"NJ",
    "sg:tags":[
        "contractor"
    ],
    "wof:name":"Inc Blue Rock Construction",
    "wof:placetype":"venue"
},
  "geometry": {"coordinates":[-74.814156,40.039273],"type":"Point"}
}