{
  "type": "Feature",
  "properties": {
    "addr:full":"20 W Chestnut Ave Merchantville NJ 08109",
    "addr:housenumber":"20",
    "addr:postcode":"08109",
    "addr:street":"W Chestnut Ave",
    "iso:country":"US",
    "sg:address":"20 W Chestnut Ave",
    "sg:city":"Merchantville",
    "sg:classifiers":[
        {
            "category":"Building & Trades",
            "subcategory":"Electrical",
            "type":"Services"
        }
    ],
    "sg:phone":"+1 856 662 0233",
    "sg:postcode":"08109",
    "sg:province":"NJ",
    "sg:tags":[
        "electrician"
    ],
    "wof:name":"Meade John F Inc",
    "wof:placetype":"venue"
},
  "geometry": {"coordinates":[-75.050102,39.952],"type":"Point"}
}