{
  "type": "Feature",
  "properties": {
    "addr:full":"44 State Rte 37 Toms River NJ 08753",
    "addr:housenumber":"44",
    "addr:postcode":"08753",
    "addr:street":"State Rte 37",
    "iso:country":"US",
    "sg:address":"44 State Rte 37",
    "sg:city":"Toms River",
    "sg:classifiers":[
        {
            "category":"Restaurant",
            "type":"Food & Drink"
        }
    ],
    "sg:phone":"+1 732 244 9588",
    "sg:postcode":"08753",
    "sg:province":"NJ",
    "sg:tags":[
        "eating"
    ],
    "wof:name":"Burger King",
    "wof:placetype":"venue"
},
  "geometry": {"coordinates":[-74.195679,39.963916],"type":"Point"}
}