{
  "type": "Feature",
  "properties": {
    "iso:country":"US",
    "sg:address":"8 Maple Ave",
    "sg:city":"Fair Lawn",
    "sg:classifiers":[
        {
            "category":"Health Services",
            "subcategory":"Doctor",
            "type":"Services"
        }
    ],
    "sg:phone":"+1   ",
    "sg:postcode":"07410",
    "sg:province":"NJ",
    "wof:name":"Amoruso Robert C MD",
    "wof:placetype":"venue"
},
  "geometry": {"coordinates":[-74.14022900000001,40.945142],"type":"Point"}
}