{
  "type": "Feature",
  "properties": {
    "iso:country":"US",
    "sg:address":"1202 Laurel Oak Rd",
    "sg:city":"Voorhees",
    "sg:classifiers":[
        {
            "category":"Education",
            "subcategory":"School",
            "type":"Public Place"
        }
    ],
    "sg:phone":"+1 856 346 6740",
    "sg:postcode":"08043",
    "sg:province":"NJ",
    "sg:website":"www.eastern.k12.nj.us",
    "wof:name":"Eastern Camden School District",
    "wof:placetype":"venue"
},
  "geometry": {"coordinates":[-74.971008,39.848005],"type":"Point"}
}