{
  "type": "Feature",
  "properties": {
    "addr:full":"64 Franklin Ave Fairview NJ 07022",
    "addr:housenumber":"64",
    "addr:postcode":"07022",
    "addr:street":"Franklin Ave",
    "iso:country":"US",
    "sg:address":"64 Franklin Ave",
    "sg:city":"Fairview",
    "sg:classifiers":[
        {
            "category":"Building & Trades",
            "subcategory":"Electrical",
            "type":"Services"
        }
    ],
    "sg:phone":"+1 201 945 3365",
    "sg:postcode":"07022",
    "sg:province":"NJ",
    "sg:tags":[
        "electrical",
        "contractor"
    ],
    "wof:name":"Top Electric Inc",
    "wof:placetype":"venue"
},
  "geometry": {"coordinates":[-74.004611,40.824525],"type":"Point"}
}