{
  "type": "Feature",
  "properties": {
    "iso:country":"US",
    "sg:address":"3809 Park Ave",
    "sg:city":"Union City",
    "sg:classifiers":[
        {
            "category":"Education",
            "subcategory":"Special Training",
            "type":"Public Place"
        }
    ],
    "sg:phone":"+1 201 864 5517",
    "sg:postcode":"07087",
    "sg:province":"NJ",
    "sg:tags":[
        "dance",
        "performing",
        "art"
    ],
    "sg:website":"www.yolandasacademy.com",
    "wof:name":"Yolanda's Academy of Music & Dance",
    "wof:placetype":"venue"
},
  "geometry": {"coordinates":[-74.02159899999999,40.7729],"type":"Point"}
}