{
  "type": "Feature",
  "properties": {
    "iso:country":"US",
    "sg:address":"2905 Bergenline Ave",
    "sg:city":"Union City",
    "sg:classifiers":[
        {
            "category":"Food & Beverages",
            "subcategory":"Meat & Fish",
            "type":"Retail Goods"
        }
    ],
    "sg:phone":"+1 201 864 6647",
    "sg:postcode":"07087",
    "sg:province":"NJ",
    "sg:tags":[
        "seafood",
        "market"
    ],
    "wof:name":"World Fish Market",
    "wof:placetype":"venue"
},
  "geometry": {"coordinates":[-74.03029600000001,40.770901],"type":"Point"}
}