{
  "type": "Feature",
  "properties": {
    "iso:country":"US",
    "sg:address":"257 Abbey Dr",
    "sg:city":"Somerset",
    "sg:classifiers":[
        {
            "category":"Organizations",
            "subcategory":"Religious Organization",
            "type":"Services"
        }
    ],
    "sg:phone":"+1   ",
    "sg:postcode":"08873",
    "sg:province":"NJ",
    "wof:name":"Calvary Chapel of Somerset",
    "wof:placetype":"venue"
},
  "geometry": {"coordinates":[-74.515895,40.52158],"type":"Point"}
}