{
  "type": "Feature",
  "properties": {
    "iso:country":"US",
    "sg:address":"30 Canfield Ave",
    "sg:city":"Randolph",
    "sg:classifiers":[
        {
            "category":"Utilities",
            "subcategory":"Cable",
            "type":"Services"
        }
    ],
    "sg:phone":"+1 973 328 7557",
    "sg:postcode":"07869",
    "sg:province":"NJ",
    "sg:tags":[
        "television"
    ],
    "wof:name":"Satellite Innovations LLC",
    "wof:placetype":"venue"
},
  "geometry": {"coordinates":[-74.61215,40.852323],"type":"Point"}
}