{
  "type": "Feature",
  "properties": {
    "iso:country":"US",
    "sg:address":"430 US Hwy 206",
    "sg:city":"Hillsborough",
    "sg:classifiers":[
        {
            "category":"Restaurant",
            "type":"Food & Drink"
        }
    ],
    "sg:phone":"+1 908 359 7770",
    "sg:postcode":"08844",
    "sg:province":"NJ",
    "wof:name":"Hillsborough Texas Wiener",
    "wof:placetype":"venue"
},
  "geometry": {"coordinates":[-74.64145499999999,40.506775],"type":"Point"}
}