{
  "type": "Feature",
  "properties": {
    "iso:country":"US",
    "sg:address":"3227 Valley Rd",
    "sg:city":"Basking Ridge",
    "sg:classifiers":[
        {
            "category":"Building & Trades",
            "subcategory":"Construction",
            "type":"Services"
        }
    ],
    "sg:phone":"+1 908 647 3376",
    "sg:postcode":"07920",
    "sg:province":"NJ",
    "sg:tags":[
        "residential"
    ],
    "wof:name":"Paul Carola Constr Co",
    "wof:placetype":"venue"
},
  "geometry": {"coordinates":[-74.54637099999999,40.665488],"type":"Point"}
}