{
  "type": "Feature",
  "properties": {
    "addr:full":"12 Country Club Ln Marlboro NJ 07746",
    "addr:housenumber":"12",
    "addr:postcode":"07746",
    "addr:street":"Country Club Ln",
    "iso:country":"US",
    "sg:address":"12 Country Club Ln",
    "sg:city":"Marlboro",
    "sg:classifiers":[
        {
            "category":"Wholesale",
            "subcategory":"Groceries",
            "type":"Manufacturing & Wholesale Goods"
        }
    ],
    "sg:phone":"+1 732 462 6004",
    "sg:postcode":"07746",
    "sg:province":"NJ",
    "sg:tags":[
        "candy"
    ],
    "wof:name":"Golden Sales Associates Ltd",
    "wof:placetype":"venue"
},
  "geometry": {"coordinates":[-74.228369,40.305789],"type":"Point"}
}