{
  "type": "Feature",
  "properties": {
    "addr:full":"530 Powell Rd Mount Holly NJ 08060",
    "addr:housenumber":"530",
    "addr:postcode":"08060",
    "addr:street":"Powell Rd",
    "iso:country":"US",
    "sg:address":"530 Powell Rd",
    "sg:city":"Mount Holly",
    "sg:classifiers":[
        {
            "category":"Building & Trades",
            "subcategory":"Construction",
            "type":"Services"
        }
    ],
    "sg:phone":"+1 609 267 0711",
    "sg:postcode":"08060",
    "sg:province":"NJ",
    "sg:tags":[
        "development",
        "utility",
        "site",
        "contractor"
    ],
    "wof:name":"Robert T Pondish & Sons Inc",
    "wof:placetype":"venue"
},
  "geometry": {"coordinates":[-74.77026499999999,39.993177],"type":"Point"}
}