{
  "type": "Feature",
  "properties": {
    "addr:full":"501 Division St Boonton NJ 07005",
    "addr:housenumber":"501",
    "addr:postcode":"07005",
    "addr:street":"Division St",
    "iso:country":"US",
    "sg:address":"501 Division St",
    "sg:city":"Boonton",
    "sg:classifiers":[
        {
            "category":"Building & Trades",
            "subcategory":"Landscaping Services",
            "type":"Services"
        }
    ],
    "sg:phone":"+1 973 299 1356",
    "sg:postcode":"07005",
    "sg:province":"NJ",
    "sg:tags":[
        "landscape",
        "contractor"
    ],
    "wof:name":"Bednar Landscape Svc",
    "wof:placetype":"venue"
},
  "geometry": {"coordinates":[-74.402145,40.907528],"type":"Point"}
}