{
  "type": "Feature",
  "properties": {
    "iso:country":"US",
    "sg:address":"1151 Woodbridge Rd",
    "sg:city":"Rahway",
    "sg:classifiers":[
        {
            "category":"Food & Beverages",
            "subcategory":"Groceries & Convenience Stores",
            "type":"Retail Goods"
        }
    ],
    "sg:phone":"+1 732 815 1403",
    "sg:postcode":"07065",
    "sg:province":"NJ",
    "wof:name":"Quick-Chek Stores",
    "wof:placetype":"venue"
},
  "geometry": {"coordinates":[-74.268204,40.597198],"type":"Point"}
}