{
  "type": "Feature",
  "properties": {
    "iso:country":"US",
    "sg:address":"6 Dudiak Ct",
    "sg:city":"Matawan",
    "sg:classifiers":[
        {
            "category":"Wholesale",
            "subcategory":"Seafood",
            "type":"Manufacturing & Wholesale Goods"
        }
    ],
    "sg:phone":"+1 732 269 3304",
    "sg:postcode":"07747",
    "sg:province":"NJ",
    "sg:tags":[
        "broker"
    ],
    "wof:name":"H & D Seafood Inc",
    "wof:placetype":"venue"
},
  "geometry": {"coordinates":[-74.275955,40.410565],"type":"Point"}
}