{
  "type": "Feature",
  "properties": {
    "addr:full":"260 Casino Dr Farmingdale NJ 07727",
    "addr:housenumber":"260",
    "addr:postcode":"07727",
    "addr:street":"Casino Dr",
    "iso:country":"US",
    "sg:address":"260 Casino Dr",
    "sg:city":"Farmingdale",
    "sg:classifiers":[
        {
            "category":"Farming",
            "subcategory":"Farm",
            "type":"Manufacturing & Wholesale Goods"
        }
    ],
    "sg:phone":"+1 732 751 8518",
    "sg:postcode":"07727",
    "sg:province":"NJ",
    "sg:tags":[
        "crop",
        "general"
    ],
    "wof:name":"Regans Hollow Farm LLC",
    "wof:placetype":"venue"
},
  "geometry": {"coordinates":[-74.209625,40.19856],"type":"Point"}
}