{
  "type": "Feature",
  "properties": {
    "addr:full":"128 S Broadway St South Amboy NJ 08879",
    "addr:housenumber":"128",
    "addr:postcode":"08879",
    "addr:street":"S Broadway St",
    "iso:country":"US",
    "sg:address":"128 S Broadway St",
    "sg:city":"South Amboy",
    "sg:classifiers":[
        {
            "category":"Personal",
            "subcategory":"Barber",
            "type":"Services"
        }
    ],
    "sg:phone":"+1 732 727 3990",
    "sg:postcode":"08879",
    "sg:province":"NJ",
    "wof:name":"Broadway Barbers",
    "wof:placetype":"venue"
},
  "geometry": {"coordinates":[-74.279355,40.482427],"type":"Point"}
}