{
  "type": "Feature",
  "properties": {
    "addr:full":"750 RT-18 East Brunswick NJ 08816",
    "addr:housenumber":"750",
    "addr:postcode":"08816",
    "addr:street":"Rt-18",
    "iso:country":"US",
    "sg:address":"750 RT-18",
    "sg:city":"East Brunswick",
    "sg:classifiers":[
        {
            "category":"Restaurant",
            "type":"Food & Drink"
        }
    ],
    "sg:menulink":"http://www.allmenus.com/nj/east-brunswick/127904-red-lobster/menu/",
    "sg:phone":"+1 732 238 4810",
    "sg:postcode":"08816",
    "sg:province":"NJ",
    "sg:tags":[
        "seafood",
        "american"
    ],
    "wof:name":"Red Lobster",
    "wof:placetype":"venue"
},
  "geometry": {"coordinates":[-74.381287,40.426373],"type":"Point"}
}