{
  "type": "Feature",
  "properties": {
    "iso:country":"US",
    "sg:address":"49 Debbie Pl",
    "sg:city":"Berkeley Heights",
    "sg:classifiers":[
        {
            "category":"Professional",
            "subcategory":"Business Services",
            "type":"Services"
        }
    ],
    "sg:phone":"+1   ",
    "sg:postcode":"07922",
    "sg:province":"NJ",
    "wof:name":"Ronner & Co",
    "wof:placetype":"venue"
},
  "geometry": {"coordinates":[-74.41619300000001,40.680073],"type":"Point"}
}