{
  "type": "Feature",
  "properties": {
    "iso:country":"US",
    "sg:address":"9 Parmley Pl",
    "sg:city":"Summit",
    "sg:classifiers":[
        {
            "category":"Retail",
            "subcategory":"Auto Repair",
            "type":"Services"
        }
    ],
    "sg:phone":"+1 908 273 5669",
    "sg:postcode":"07901",
    "sg:province":"NJ",
    "sg:tags":[
        "cleaning"
    ],
    "wof:name":"Concourse Detailing",
    "wof:placetype":"venue"
},
  "geometry": {"coordinates":[-74.357027,40.720416],"type":"Point"}
}