{
  "type": "Feature",
  "properties": {
    "addr:full":"85 2nd St Elizabeth NJ 07206",
    "addr:housenumber":"85",
    "addr:postcode":"07206",
    "addr:street":"2Nd St",
    "iso:country":"US",
    "sg:address":"85 2nd St",
    "sg:city":"Elizabeth",
    "sg:classifiers":[
        {
            "category":"Food & Beverages",
            "subcategory":"Bakery",
            "type":"Retail Goods"
        }
    ],
    "sg:phone":"+1 908 354 6984",
    "sg:postcode":"07206",
    "sg:province":"NJ",
    "sg:tags":[
        "baker"
    ],
    "wof:name":"Maciel Bakery Inc",
    "wof:placetype":"venue"
},
  "geometry": {"coordinates":[-74.189666,40.649826],"type":"Point"}
}