{
  "type": "Feature",
  "properties": {
    "addr:full":"18 Front St Hammonton NJ 08037",
    "addr:housenumber":"18",
    "addr:postcode":"08037",
    "addr:street":"Front St",
    "iso:country":"US",
    "sg:address":"18 Front St",
    "sg:city":"Hammonton",
    "sg:classifiers":[
        {
            "category":"Organizations",
            "subcategory":"Religious Organization",
            "type":"Services"
        }
    ],
    "sg:phone":"+1 609 704 8778",
    "sg:postcode":"08037",
    "sg:province":"NJ",
    "sg:tags":[
        "church"
    ],
    "wof:name":"Calvary Chapel Of Hammonton",
    "wof:placetype":"venue"
},
  "geometry": {"coordinates":[-74.80325999999999,39.633741],"type":"Point"}
}