{
  "type": "Feature",
  "properties": {
    "addr:full":"5012 Landis Ave Vineland NJ 08360",
    "addr:housenumber":"5012",
    "addr:postcode":"08360",
    "addr:street":"Landis Ave",
    "iso:country":"US",
    "sg:address":"5012 Landis Ave",
    "sg:city":"Vineland",
    "sg:classifiers":[
        {
            "category":"Farming",
            "subcategory":"Farm & Veterinary Services",
            "type":"Manufacturing & Wholesale Goods"
        }
    ],
    "sg:phone":"+1 856 696 5869",
    "sg:postcode":"08360",
    "sg:province":"NJ",
    "sg:tags":[
        "crop",
        "general"
    ],
    "wof:name":"K and G Levari Farms",
    "wof:placetype":"venue"
},
  "geometry": {"coordinates":[-74.920087,39.481192],"type":"Point"}
}