{
  "type": "Feature",
  "properties": {
    "addr:full":"338 E Homestead Ave Palisades Park NJ 07650",
    "addr:housenumber":"338",
    "addr:postcode":"07650",
    "addr:street":"E Homestead Ave",
    "iso:country":"US",
    "sg:address":"338 E Homestead Ave",
    "sg:city":"Palisades Park",
    "sg:classifiers":[
        {
            "category":"Building & Trades",
            "subcategory":"Construction",
            "type":"Services"
        }
    ],
    "sg:phone":"+1 201 461 9060",
    "sg:postcode":"07650",
    "sg:province":"NJ",
    "sg:tags":[
        "house",
        "c",
        "contractor",
        "painter",
        "hanging"
    ],
    "wof:name":"My Three Sons",
    "wof:placetype":"venue"
},
  "geometry": {"coordinates":[-73.99140199999999,40.840599],"type":"Point"}
}