{
  "type": "Feature",
  "properties": {
    "iso:country":"US",
    "sg:address":"391 Littleton Ave",
    "sg:city":"Newark",
    "sg:classifiers":[
        {
            "category":"Real Estate",
            "subcategory":"Real Estate Agent",
            "type":"Services"
        }
    ],
    "sg:phone":"+1 973 624 8466",
    "sg:postcode":"07103",
    "sg:province":"NJ",
    "wof:name":"Littleton Avenue Community Vlg",
    "wof:placetype":"venue"
},
  "geometry": {"coordinates":[-74.198369,40.734101],"type":"Point"}
}