{
  "type": "Feature",
  "properties": {
    "iso:country":"US",
    "sg:address":"2900 New York Ave",
    "sg:city":"Wildwood",
    "sg:classifiers":[
        {
            "category":"Education",
            "subcategory":"School",
            "type":"Public Place"
        }
    ],
    "sg:phone":"+1 609 729 5243",
    "sg:postcode":"08260",
    "sg:province":"NJ",
    "sg:tags":[
        "high",
        "middle",
        "elementary"
    ],
    "wof:name":"Glenwood Schools",
    "wof:placetype":"venue"
},
  "geometry": {"coordinates":[-74.813146,38.994293],"type":"Point"}
}