{
  "type": "Feature",
  "properties": {
    "addr:full":"21 Coddington Ave Perth Amboy NJ 08861",
    "addr:housenumber":"21",
    "addr:postcode":"08861",
    "addr:street":"Coddington Ave",
    "iso:country":"US",
    "sg:address":"21 Coddington Ave",
    "sg:city":"Perth Amboy",
    "sg:classifiers":[
        {
            "category":"Building & Trades",
            "subcategory":"Cleaning & Sanitation",
            "type":"Services"
        }
    ],
    "sg:phone":"+1 732 324 8445",
    "sg:postcode":"08861",
    "sg:province":"NJ",
    "sg:tags":[
        "janitor"
    ],
    "wof:name":"Unison",
    "wof:placetype":"venue"
},
  "geometry": {"coordinates":[-74.292145,40.536525],"type":"Point"}
}