{
  "type": "Feature",
  "properties": {
    "addr:full":"7800 River Rd North Bergen NJ 07047",
    "addr:housenumber":"7800",
    "addr:postcode":"07047",
    "addr:street":"River Rd",
    "iso:country":"US",
    "sg:address":"7800 River Rd",
    "sg:city":"North Bergen",
    "sg:classifiers":[
        {
            "category":"Real Estate",
            "subcategory":"Real Estate Operator",
            "type":"Services"
        }
    ],
    "sg:phone":"+1   ",
    "sg:postcode":"07047",
    "sg:province":"NJ",
    "sg:tags":[
        "building",
        "apartment"
    ],
    "wof:name":"Briarwood Manor",
    "wof:placetype":"venue"
},
  "geometry": {"coordinates":[-73.995836,40.797644],"type":"Point"}
}