{
  "type": "Feature",
  "properties": {
    "iso:country":"US",
    "sg:address":"989 Jessup Rd",
    "sg:city":"Thorofare",
    "sg:classifiers":[
        {
            "category":"Organizations",
            "subcategory":"Community Association",
            "type":"Services"
        }
    ],
    "sg:phone":"+1 856 845 2057",
    "sg:postcode":"08086",
    "sg:province":"NJ",
    "sg:tags":[
        "club"
    ],
    "wof:name":"Green Fields Swimming Club Inc",
    "wof:placetype":"venue"
},
  "geometry": {"coordinates":[-75.175085,39.824111],"type":"Point"}
}