{
  "type": "Feature",
  "properties": {
    "addr:full":"1405 Saint Georges Ave Colonia NJ 07067",
    "addr:housenumber":"1405",
    "addr:postcode":"07067",
    "addr:street":"Saint Georges Ave",
    "iso:country":"US",
    "sg:address":"1405 Saint Georges Ave",
    "sg:city":"Colonia",
    "sg:classifiers":[
        {
            "category":"Retail",
            "subcategory":"Auto Repair",
            "type":"Services"
        }
    ],
    "sg:phone":"+1 732 382 9600",
    "sg:postcode":"07067",
    "sg:province":"NJ",
    "sg:tags":[
        "repairing",
        "automobile"
    ],
    "wof:name":"Quality Auto Center",
    "wof:placetype":"venue"
},
  "geometry": {"coordinates":[-74.29239699999999,40.5854],"type":"Point"}
}