{
  "type": "Feature",
  "properties": {
    "iso:country":"US",
    "sg:address":"9600 Ventnor Ave",
    "sg:city":"Margate City",
    "sg:classifiers":[
        {
            "category":"Shopping",
            "subcategory":"Gifts & Souvenirs",
            "type":"Retail Goods"
        }
    ],
    "sg:phone":"+1   ",
    "sg:postcode":"08402",
    "sg:province":"NJ",
    "wof:name":"Awesome Baskets",
    "wof:placetype":"venue"
},
  "geometry": {"coordinates":[-74.517307,39.320411],"type":"Point"}
}