{
  "type": "Feature",
  "properties": {
    "addr:full":"193 Bellevue Ave Montclair NJ 07043",
    "addr:housenumber":"193",
    "addr:postcode":"07043",
    "addr:street":"Bellevue Ave",
    "iso:country":"US",
    "sg:address":"193 Bellevue Ave",
    "sg:city":"Montclair",
    "sg:classifiers":[
        {
            "category":"Shopping",
            "subcategory":"Computers & Home Electronics",
            "type":"Retail Goods"
        }
    ],
    "sg:phone":"+1 973 744 0600",
    "sg:postcode":"07043",
    "sg:province":"NJ",
    "sg:tags":[
        "equipment",
        "electronic",
        "supply"
    ],
    "sg:website":"www.csaaudiodesign.com",
    "wof:name":"Csa Audio",
    "wof:placetype":"venue"
},
  "geometry": {"coordinates":[-74.2052,40.840401],"type":"Point"}
}