{
  "type": "Feature",
  "properties": {
    "addr:full":"34 Link Pl Clinton NJ 08820",
    "addr:housenumber":"34",
    "addr:postcode":"08820",
    "addr:street":"Link Pl",
    "iso:country":"US",
    "sg:address":"34 Link Pl",
    "sg:city":"Clinton",
    "sg:classifiers":[
        {
            "category":"Shopping",
            "subcategory":"Department Store",
            "type":"Retail Goods"
        }
    ],
    "sg:phone":"+1   ",
    "sg:postcode":"08820",
    "sg:province":"NJ",
    "wof:name":"Wal-Mart",
    "wof:placetype":"venue"
},
  "geometry": {"coordinates":[-74.364088,40.589054],"type":"Point"}
}