{
  "type": "Feature",
  "properties": {
    "iso:country":"US",
    "sg:address":"5 Maple Ter",
    "sg:city":"Hillsborough",
    "sg:classifiers":[
        {
            "category":"Professional",
            "subcategory":"Business Services",
            "type":"Services"
        }
    ],
    "sg:phone":"+1   ",
    "sg:postcode":"08844",
    "sg:province":"NJ",
    "wof:name":"Ckj Assoc",
    "wof:placetype":"venue"
},
  "geometry": {"coordinates":[-74.586928,40.505925],"type":"Point"}
}