{
  "type": "Feature",
  "properties": {
    "addr:full":"20 Chapin Rd Pine Brook NJ 07058",
    "addr:housenumber":"20",
    "addr:postcode":"07058",
    "addr:street":"Chapin Rd",
    "iso:country":"US",
    "sg:address":"20 Chapin Rd",
    "sg:city":"Pine Brook",
    "sg:classifiers":[
        {
            "category":"Manufacturing",
            "subcategory":"Tools & Machinery",
            "type":"Manufacturing & Wholesale Goods"
        }
    ],
    "sg:phone":"+1 973 227 1551",
    "sg:postcode":"07058",
    "sg:province":"NJ",
    "sg:tags":[
        "instrument",
        "optical",
        "lense"
    ],
    "sg:website":"www.ii-vi.com",
    "wof:name":"II Vi Inc",
    "wof:placetype":"venue"
},
  "geometry": {"coordinates":[-74.33934600000001,40.857055],"type":"Point"}
}