{
  "type": "Feature",
  "properties": {
    "iso:country":"US",
    "sg:address":"101 US Highway 22",
    "sg:city":"Springfield",
    "sg:classifiers":[
        {
            "category":"Building & Trades",
            "subcategory":"Locksmith",
            "type":"Services"
        }
    ],
    "sg:phone":"+1 973 679 0833",
    "sg:postcode":"07081",
    "sg:province":"NJ",
    "sg:tags":[
        "key"
    ],
    "wof:name":"0 1 Emerge A Locksmith",
    "wof:placetype":"venue"
},
  "geometry": {"coordinates":[-74.31521100000001,40.686835],"type":"Point"}
}