{
  "type": "Feature",
  "properties": {
    "iso:country":"US",
    "sg:address":"429 Elizabeth Ave",
    "sg:city":"Elizabeth",
    "sg:classifiers":[
        {
            "category":"Food & Beverages",
            "subcategory":"Candy",
            "type":"Retail Goods"
        }
    ],
    "sg:phone":"+1 908 355 6248",
    "sg:postcode":"07206",
    "sg:province":"NJ",
    "sg:tags":[
        "confectionery"
    ],
    "wof:name":"Confecciones Vicky's",
    "wof:placetype":"venue"
},
  "geometry": {"coordinates":[-74.197631,40.653578],"type":"Point"}
}