{
  "type": "Feature",
  "properties": {
    "addr:full":"694 Dunedin St Toms River NJ 08753",
    "addr:housenumber":"694",
    "addr:postcode":"08753",
    "addr:street":"Dunedin St",
    "iso:country":"US",
    "sg:address":"694 Dunedin St",
    "sg:city":"Toms River",
    "sg:classifiers":[
        {
            "category":"Building & Trades",
            "subcategory":"Equipment Rental",
            "type":"Services"
        }
    ],
    "sg:phone":"+1 732 929 0071",
    "sg:postcode":"08753",
    "sg:province":"NJ",
    "wof:name":"G&G Rental Assoc",
    "wof:placetype":"venue"
},
  "geometry": {"coordinates":[-74.14501799999999,39.962694],"type":"Point"}
}