{
  "type": "Feature",
  "properties": {
    "iso:country":"US",
    "sg:address":"895 US Hwy 9",
    "sg:city":"Bayville",
    "sg:classifiers":[
        {
            "category":"Personal",
            "subcategory":"Barber",
            "type":"Services"
        }
    ],
    "sg:phone":"+1 732 269 6410",
    "sg:postcode":"08721",
    "sg:province":"NJ",
    "sg:tags":[
        "shop"
    ],
    "wof:name":"Seabreeze Barber Shop",
    "wof:placetype":"venue"
},
  "geometry": {"coordinates":[-74.16398100000001,39.883392],"type":"Point"}
}