{
  "type": "Feature",
  "properties": {
    "addr:full":"1452 Main Rd Newfield NJ 08344",
    "addr:housenumber":"1452",
    "addr:postcode":"08344",
    "addr:street":"Main Rd",
    "iso:country":"US",
    "sg:address":"1452 Main Rd",
    "sg:city":"Newfield",
    "sg:classifiers":[
        {
            "category":"Education",
            "subcategory":"School",
            "type":"Public Place"
        }
    ],
    "sg:phone":"+1 856 697 0220",
    "sg:postcode":"08344",
    "sg:province":"NJ",
    "sg:website":"www.franklintwpschools.org",
    "wof:name":"Main Road School",
    "wof:placetype":"venue"
},
  "geometry": {"coordinates":[-74.998786,39.556402],"type":"Point"}
}