{
  "type": "Feature",
  "properties": {
    "addr:full":"112 Hoover Ave Trenton NJ 08619",
    "addr:housenumber":"112",
    "addr:postcode":"08619",
    "addr:street":"Hoover Ave",
    "iso:country":"US",
    "sg:address":"112 Hoover Ave",
    "sg:city":"Trenton",
    "sg:classifiers":[
        {
            "category":"Professional",
            "subcategory":"Advertising",
            "type":"Services"
        }
    ],
    "sg:phone":"+1 609 890 1550",
    "sg:postcode":"08619",
    "sg:province":"NJ",
    "sg:tags":[
        "counselor"
    ],
    "wof:name":"Miramar Productions Inc",
    "wof:placetype":"venue"
},
  "geometry": {"coordinates":[-74.68147999999999,40.235587],"type":"Point"}
}