{
  "type": "Feature",
  "properties": {
    "addr:full":"87 S Farview Ave Paramus NJ 07652",
    "addr:housenumber":"87",
    "addr:postcode":"07652",
    "addr:street":"S Farview Ave",
    "iso:country":"US",
    "sg:address":"87 S Farview Ave",
    "sg:city":"Paramus",
    "sg:classifiers":[
        {
            "category":"Professional",
            "subcategory":"Lawyer & Legal Services",
            "type":"Services"
        }
    ],
    "sg:phone":"+1 201 587 1414",
    "sg:postcode":"07652",
    "sg:province":"NJ",
    "wof:name":"Houghton Katherine G Attorney At Law",
    "wof:placetype":"venue"
},
  "geometry": {"coordinates":[-74.06999999999999,40.916801],"type":"Point"}
}