{
  "type": "Feature",
  "properties": {
    "addr:full":"619 W Edgar Rd Linden NJ 07036",
    "addr:housenumber":"619",
    "addr:postcode":"07036",
    "addr:street":"W Edgar Rd",
    "iso:country":"US",
    "sg:address":"619 W Edgar Rd",
    "sg:city":"Linden",
    "sg:classifiers":[
        {
            "category":"Banks & Credit Unions",
            "subcategory":"Bank",
            "type":"Services"
        }
    ],
    "sg:phone":"+1 908 862 6448",
    "sg:postcode":"07036",
    "sg:province":"NJ",
    "wof:name":"Polish & Slovak Fed Cu",
    "wof:placetype":"venue"
},
  "geometry": {"coordinates":[-74.2521,40.61737],"type":"Point"}
}