{
  "type": "Feature",
  "properties": {
    "iso:country":"US",
    "sg:address":"4818 Park Ave",
    "sg:city":"Weehawken",
    "sg:classifiers":[
        {
            "category":"Home & Garden",
            "subcategory":"Building Materials",
            "type":"Retail Goods"
        }
    ],
    "sg:phone":"+1 201 863 1770",
    "sg:postcode":"07086",
    "sg:province":"NJ",
    "sg:tags":[
        "plumbing",
        "fixture",
        "supply"
    ],
    "wof:name":"E W Berger & Bro",
    "wof:placetype":"venue"
},
  "geometry": {"coordinates":[-74.01578000000001,40.77883],"type":"Point"}
}