{
  "type": "Feature",
  "properties": {
    "iso:country":"US",
    "sg:address":"3 Louise Ln",
    "sg:city":"Gladstone",
    "sg:classifiers":[
        {
            "category":"Professional",
            "subcategory":"Management & Consulting",
            "type":"Services"
        }
    ],
    "sg:phone":"+1   ",
    "sg:postcode":"07934",
    "sg:province":"NJ",
    "wof:name":"Soluble Solutions",
    "wof:placetype":"venue"
},
  "geometry": {"coordinates":[-74.660011,40.72261],"type":"Point"}
}