{
  "type": "Feature",
  "properties": {
    "iso:country":"US",
    "sg:address":"14 Paterson Ave",
    "sg:city":"Hoboken",
    "sg:classifiers":[
        {
            "category":"Shopping",
            "subcategory":"Florist",
            "type":"Retail Goods"
        }
    ],
    "sg:phone":"+1 201 798 4661",
    "sg:postcode":"07030",
    "sg:province":"NJ",
    "sg:tags":[
        "basket",
        "gift"
    ],
    "sg:website":"http://www.verasflorist.com",
    "wof:name":"Vera's Florist",
    "wof:placetype":"venue"
},
  "geometry": {"coordinates":[-74.040913,40.737315],"type":"Point"}
}