{
  "type": "Feature",
  "properties": {
    "addr:full":"288 Wyckoff Rd Eatontown NJ 07724",
    "addr:housenumber":"288",
    "addr:postcode":"07724",
    "addr:street":"Wyckoff Rd",
    "iso:country":"US",
    "sg:address":"288 Wyckoff Rd",
    "sg:city":"Eatontown",
    "sg:classifiers":[
        {
            "category":"Building & Trades",
            "subcategory":"Plumbing",
            "type":"Services"
        }
    ],
    "sg:phone":"+1 732 578 0379",
    "sg:postcode":"07724",
    "sg:province":"NJ",
    "sg:tags":[
        "conditioning",
        "air",
        "system",
        "contractor"
    ],
    "wof:name":"A-1 Comfort Heating & Cooling",
    "wof:placetype":"venue"
},
  "geometry": {"coordinates":[-74.06917900000001,40.279709],"type":"Point"}
}