{
  "type": "Feature",
  "properties": {
    "addr:full":"655 Palisade Ave Cliffside Park NJ 07010",
    "addr:housenumber":"655",
    "addr:postcode":"07010",
    "addr:street":"Palisade Ave",
    "iso:country":"US",
    "sg:address":"655 Palisade Ave",
    "sg:city":"Cliffside Park",
    "sg:classifiers":[
        {
            "category":"Food & Beverages",
            "subcategory":"Bakery",
            "type":"Retail Goods"
        }
    ],
    "sg:phone":"+1 201 840 8818",
    "sg:postcode":"07010",
    "sg:province":"NJ",
    "sg:tags":[
        "baker"
    ],
    "wof:name":"Anatolia Bakery",
    "wof:placetype":"venue"
},
  "geometry": {"coordinates":[-73.983999,40.824712],"type":"Point"}
}