{
  "type": "Feature",
  "properties": {
    "addr:full":"991 Inman Ave Edison NJ 08820",
    "addr:housenumber":"991",
    "addr:postcode":"08820",
    "addr:street":"Inman Ave",
    "iso:country":"US",
    "sg:address":"991 Inman Ave",
    "sg:city":"Edison",
    "sg:classifiers":[
        {
            "category":"Professional",
            "type":"Services"
        }
    ],
    "sg:phone":"+1   ",
    "sg:postcode":"08820",
    "sg:province":"NJ",
    "wof:name":"Bunting William Fine Art",
    "wof:placetype":"venue"
},
  "geometry": {"coordinates":[-74.353483,40.59726],"type":"Point"}
}