{
  "type": "Feature",
  "properties": {
    "iso:country":"US",
    "sg:address":"206 N 4th St",
    "sg:city":"Pleasantville",
    "sg:classifiers":[
        {
            "category":"Organizations",
            "subcategory":"Religious Organization",
            "type":"Services"
        }
    ],
    "sg:phone":"+1   ",
    "sg:postcode":"08232",
    "sg:province":"NJ",
    "wof:name":"Trinity Tabernacle Church",
    "wof:placetype":"venue"
},
  "geometry": {"coordinates":[-74.52543300000001,39.397749],"type":"Point"}
}