{
  "type": "Feature",
  "properties": {
    "iso:country":"US",
    "sg:address":"869 Rivervale Rd",
    "sg:city":"Westwood",
    "sg:classifiers":[
        {
            "category":"Professional",
            "subcategory":"Computer Services",
            "type":"Services"
        }
    ],
    "sg:phone":"+1   ",
    "sg:postcode":"07675",
    "sg:province":"NJ",
    "sg:tags":[
        "programing",
        "custom"
    ],
    "wof:name":"Lrx Systems Inc",
    "wof:placetype":"venue"
},
  "geometry": {"coordinates":[-74.012474,41.038431],"type":"Point"}
}