{
  "type": "Feature",
  "properties": {
    "addr:full":"19 Division Ave Summit NJ 07901",
    "addr:housenumber":"19",
    "addr:postcode":"07901",
    "addr:street":"Division Ave",
    "iso:country":"US",
    "sg:address":"19 Division Ave",
    "sg:city":"Summit",
    "sg:classifiers":[
        {
            "category":"Building & Trades",
            "subcategory":"Construction",
            "type":"Services"
        }
    ],
    "sg:phone":"+1 908 508 9348",
    "sg:postcode":"07901",
    "sg:province":"NJ",
    "sg:tags":[
        "hanging",
        "painter",
        "contractor"
    ],
    "wof:name":"Mike's Painting",
    "wof:placetype":"venue"
},
  "geometry": {"coordinates":[-74.385085,40.711177],"type":"Point"}
}