{
  "type": "Feature",
  "properties": {
    "addr:full":"58 Georgetown Rd Columbus NJ 08022",
    "addr:housenumber":"58",
    "addr:postcode":"08022",
    "addr:street":"Georgetown Rd",
    "iso:country":"US",
    "sg:address":"58 Georgetown Rd",
    "sg:city":"Columbus",
    "sg:classifiers":[
        {
            "category":"Professional",
            "subcategory":"Computer Services",
            "type":"Services"
        }
    ],
    "sg:phone":"+1 609 298 8338",
    "sg:postcode":"08022",
    "sg:province":"NJ",
    "sg:tags":[
        "prepackaged",
        "software"
    ],
    "wof:name":"English Computer Services",
    "wof:placetype":"venue"
},
  "geometry": {"coordinates":[-74.664207,40.080568],"type":"Point"}
}