{
  "type": "Feature",
  "properties": {
    "addr:full":"249 Route 10 E East Hanover NJ 07936",
    "addr:housenumber":"249;e",
    "addr:postcode":"07936",
    "addr:street":"Route 10",
    "iso:country":"US",
    "sg:address":"249 Route 10 E",
    "sg:city":"East Hanover",
    "sg:classifiers":[
        {
            "category":"Restaurant",
            "type":"Food & Drink"
        }
    ],
    "sg:phone":"+1 973 599 0700",
    "sg:postcode":"07936",
    "sg:province":"NJ",
    "sg:tags":[
        "indian"
    ],
    "sg:website":"www.saffronnj.com",
    "wof:name":"Saffron Indian Cuisine",
    "wof:placetype":"venue"
},
  "geometry": {"coordinates":[-74.372077,40.806956],"type":"Point"}
}