{
  "type": "Feature",
  "properties": {
    "iso:country":"US",
    "sg:address":"40 Fela Dr",
    "sg:city":"Parlin",
    "sg:classifiers":[
        {
            "category":"Professional",
            "subcategory":"Management & Consulting",
            "type":"Services"
        }
    ],
    "sg:phone":"+1 732 525 2033",
    "sg:postcode":"08859",
    "sg:province":"NJ",
    "wof:name":"American Management Co LLC",
    "wof:placetype":"venue"
},
  "geometry": {"coordinates":[-74.28375,40.453158],"type":"Point"}
}