{
  "type": "Feature",
  "properties": {
    "iso:country":"US",
    "sg:address":"11 Lexington Ave",
    "sg:city":"Jersey City",
    "sg:classifiers":[
        {
            "category":"Real Estate",
            "subcategory":"Real Estate Operator",
            "type":"Services"
        }
    ],
    "sg:phone":"+1 201 451 8055",
    "sg:postcode":"07304",
    "sg:province":"NJ",
    "sg:tags":[
        "apartment"
    ],
    "wof:name":"Lexington Manor Apartments",
    "wof:placetype":"venue"
},
  "geometry": {"coordinates":[-74.077866,40.717137],"type":"Point"}
}