{
  "type": "Feature",
  "properties": {
    "addr:full":"1460 US Hwy 22 E Annandale NJ 08801",
    "addr:housenumber":"1460",
    "addr:postcode":"08801",
    "addr:street":"Us Hwy 22 E",
    "iso:country":"US",
    "sg:address":"1460 US Hwy 22 E",
    "sg:city":"Annandale",
    "sg:classifiers":[
        {
            "category":"Bus Charters",
            "type":"Transportation"
        }
    ],
    "sg:phone":"+1 908 236 8887",
    "sg:postcode":"08801",
    "sg:province":"NJ",
    "sg:tags":[
        "school"
    ],
    "wof:name":"Laidlaw Transit Inc",
    "wof:placetype":"venue"
},
  "geometry": {"coordinates":[-74.856803,40.642851],"type":"Point"}
}