{
  "type": "Feature",
  "properties": {
    "addr:full":"315 Broadway Passaic NJ 07055",
    "addr:housenumber":"315",
    "addr:postcode":"07055",
    "addr:street":"Broadway",
    "iso:country":"US",
    "sg:address":"315 Broadway",
    "sg:city":"Passaic",
    "sg:classifiers":[
        {
            "category":"Food & Beverages",
            "subcategory":"Groceries & Convenience Stores",
            "type":"Retail Goods"
        }
    ],
    "sg:phone":"+1 973 773 5398",
    "sg:postcode":"07055",
    "sg:province":"NJ",
    "wof:name":"Mejia Grocery II",
    "wof:placetype":"venue"
},
  "geometry": {"coordinates":[-74.13611299999999,40.855637],"type":"Point"}
}