{
  "type": "Feature",
  "properties": {
    "addr:full":"401 S Pitney Rd Galloway NJ 08205",
    "addr:housenumber":"401",
    "addr:postcode":"08205",
    "addr:street":"S Pitney Rd",
    "iso:country":"US",
    "sg:address":"401 S Pitney Rd",
    "sg:city":"Galloway",
    "sg:classifiers":[
        {
            "category":"Food & Beverages",
            "subcategory":"Groceries & Convenience Stores",
            "type":"Retail Goods"
        }
    ],
    "sg:phone":"+1 609 404 4160",
    "sg:postcode":"08205",
    "sg:province":"NJ",
    "sg:tags":[
        "grocer"
    ],
    "sg:website":"www.stopandshop.com",
    "wof:name":"Stop & Shop",
    "wof:placetype":"venue"
},
  "geometry": {"coordinates":[-74.494041,39.463291],"type":"Point"}
}