{
  "type": "Feature",
  "properties": {
    "iso:country":"US",
    "sg:address":"58 Palfrey Ln",
    "sg:city":"Willingboro",
    "sg:classifiers":[
        {
            "category":"Utilities",
            "subcategory":"Electric",
            "type":"Services"
        }
    ],
    "sg:phone":"+1 609 835 0435",
    "sg:postcode":"08046",
    "sg:province":"NJ",
    "sg:tags":[
        "equipment",
        "supplies-repair",
        "electronic",
        "equipment-repair"
    ],
    "wof:name":"Cb Service",
    "wof:placetype":"venue"
},
  "geometry": {"coordinates":[-74.899349,40.034913],"type":"Point"}
}