{
  "type": "Feature",
  "properties": {
    "addr:full":"596 Edinburg Rd Trenton NJ 08619",
    "addr:housenumber":"596",
    "addr:postcode":"08619",
    "addr:street":"Edinburg Rd",
    "iso:country":"US",
    "sg:address":"596 Edinburg Rd",
    "sg:city":"Trenton",
    "sg:classifiers":[
        {
            "category":"Professional",
            "subcategory":"Engineering",
            "type":"Services"
        }
    ],
    "sg:phone":"+1 609 371 7990",
    "sg:postcode":"08619",
    "sg:province":"NJ",
    "sg:tags":[
        "engineer"
    ],
    "wof:name":"Wang Engineering Svc",
    "wof:placetype":"venue"
},
  "geometry": {"coordinates":[-74.676209,40.243438],"type":"Point"}
}