{
  "type": "Feature",
  "properties": {
    "addr:full":"297 Central Ave Jersey City NJ 07307",
    "addr:housenumber":"297",
    "addr:postcode":"07307",
    "addr:street":"Central Ave",
    "iso:country":"US",
    "sg:address":"297 Central Ave",
    "sg:city":"Jersey City",
    "sg:classifiers":[
        {
            "category":"Health Services",
            "subcategory":"Doctor",
            "type":"Services"
        }
    ],
    "sg:phone":"+1   ",
    "sg:postcode":"07307",
    "sg:province":"NJ",
    "sg:tags":[
        "medical"
    ],
    "wof:name":"Hemant R Shah MD PC",
    "wof:placetype":"venue"
},
  "geometry": {"coordinates":[-74.050096,40.744908],"type":"Point"}
}