{
  "type": "Feature",
  "properties": {
    "iso:country":"US",
    "sg:address":"17000 Commerce Pkwy",
    "sg:city":"Mount Laurel",
    "sg:classifiers":[
        {
            "category":"Professional",
            "subcategory":"Research",
            "type":"Services"
        }
    ],
    "sg:phone":"+1   ",
    "sg:postcode":"08054",
    "sg:province":"NJ",
    "sg:tags":[
        "association"
    ],
    "wof:name":"Ashi",
    "wof:placetype":"venue"
},
  "geometry": {"coordinates":[-74.939781,39.915856],"type":"Point"}
}