{
  "type": "Feature",
  "properties": {
    "addr:full":"2283 South Ave Scotch Plains NJ 07076",
    "addr:housenumber":"2283",
    "addr:postcode":"07076",
    "addr:street":"South Ave",
    "iso:country":"US",
    "sg:address":"2283 South Ave",
    "sg:city":"Scotch Plains",
    "sg:classifiers":[
        {
            "category":"Personal",
            "subcategory":"Beauty Salon",
            "type":"Services"
        }
    ],
    "sg:phone":"+1 908 518 1660",
    "sg:postcode":"07076",
    "sg:province":"NJ",
    "sg:tags":[
        "shop"
    ],
    "wof:name":"Classique Hair Salon Inc",
    "wof:placetype":"venue"
},
  "geometry": {"coordinates":[-74.369964,40.645584],"type":"Point"}
}