{
  "type": "Feature",
  "properties": {
    "iso:country":"US",
    "sg:address":"150 US Hwy 46",
    "sg:city":"Hackettstown",
    "sg:classifiers":[
        {
            "category":"Autos & Motor Vehicles",
            "subcategory":"Fuel & Gas Station",
            "type":"Retail Goods"
        }
    ],
    "sg:phone":"+1 908 813 8700",
    "sg:postcode":"07840",
    "sg:province":"NJ",
    "sg:tags":[
        "oil"
    ],
    "wof:name":"Hackettstown Exxon Inc",
    "wof:placetype":"venue"
},
  "geometry": {"coordinates":[-74.830168,40.854153],"type":"Point"}
}