{
  "type": "Feature",
  "properties": {
    "addr:full":"28 Harrison Ave Englishtown NJ 07726",
    "addr:housenumber":"28",
    "addr:postcode":"07726",
    "addr:street":"Harrison Ave",
    "iso:country":"US",
    "sg:address":"28 Harrison Ave",
    "sg:city":"Englishtown",
    "sg:classifiers":[
        {
            "category":"Manufacturing",
            "subcategory":"Electronics",
            "type":"Manufacturing & Wholesale Goods"
        },
        {
            "category":"Shopping",
            "subcategory":"Computers & Home Electronics",
            "type":"Retail Goods"
        }
    ],
    "sg:phone":"+1 732 792 1234",
    "sg:postcode":"07726",
    "sg:province":"NJ",
    "sg:tags":[
        "assembly",
        "cable",
        "for",
        "supply",
        "mfg",
        "parts",
        "interface",
        "display"
    ],
    "wof:name":"Quadrangle Products Inc",
    "wof:placetype":"venue"
},
  "geometry": {"coordinates":[-74.355662,40.297006],"type":"Point"}
}