{
  "type": "Feature",
  "properties": {
    "iso:country":"US",
    "sg:address":"405 South St",
    "sg:city":"Newark",
    "sg:classifiers":[
        {
            "category":"Retail",
            "subcategory":"Auto Repair",
            "type":"Services"
        }
    ],
    "sg:phone":"+1 973 344 4583",
    "sg:postcode":"07105",
    "sg:province":"NJ",
    "sg:tags":[
        "repairing",
        "automobile"
    ],
    "wof:name":"Lucimar Auto Repair",
    "wof:placetype":"venue"
},
  "geometry": {"coordinates":[-74.16178499999999,40.718727],"type":"Point"}
}