{
  "type": "Feature",
  "properties": {
    "iso:country":"US",
    "sg:address":"641 Shunpike Rd",
    "sg:city":"Chatham",
    "sg:classifiers":[
        {
            "category":"Cinema",
            "subcategory":"Movie Theater",
            "type":"Entertainment"
        }
    ],
    "sg:phone":"+1 973 822 1550",
    "sg:postcode":"07928",
    "sg:province":"NJ",
    "sg:website":"www.robertstheatres.com",
    "wof:name":"Roberts Chatham Cinema",
    "wof:placetype":"venue"
},
  "geometry": {"coordinates":[-74.430678,40.745241],"type":"Point"}
}