{
  "type": "Feature",
  "properties": {
    "iso:country":"US",
    "sg:address":"1330 State Rte 36",
    "sg:city":"Hazlet",
    "sg:classifiers":[
        {
            "category":"Wholesale",
            "subcategory":"Drugs",
            "type":"Manufacturing & Wholesale Goods"
        }
    ],
    "sg:phone":"+1 732 264 4100",
    "sg:postcode":"07730",
    "sg:province":"NJ",
    "sg:tags":[
        "perfume"
    ],
    "wof:name":"Fragrance Plus",
    "wof:placetype":"venue"
},
  "geometry": {"coordinates":[-74.18681599999999,40.430071],"type":"Point"}
}