{
  "type": "Feature",
  "properties": {
    "iso:country":"US",
    "sg:address":"8 Sailors Way",
    "sg:city":"Monmouth Beach",
    "sg:classifiers":[
        {
            "category":"Shopping",
            "subcategory":"Gifts & Souvenirs",
            "type":"Retail Goods"
        }
    ],
    "sg:phone":"+1   ",
    "sg:postcode":"07750",
    "sg:province":"NJ",
    "wof:name":"Purple Crayon",
    "wof:placetype":"venue"
},
  "geometry": {"coordinates":[-73.976884,40.335297],"type":"Point"}
}