{
  "type": "Feature",
  "properties": {
    "addr:full":"14 Rolling Hill Rd Clinton NJ 08809",
    "addr:housenumber":"14",
    "addr:postcode":"08809",
    "addr:street":"Rolling Hill Rd",
    "iso:country":"US",
    "sg:address":"14 Rolling Hill Rd",
    "sg:city":"Clinton",
    "sg:classifiers":[
        {
            "category":"Professional",
            "subcategory":"Accounting & Tax Preparation",
            "type":"Services"
        }
    ],
    "sg:phone":"+1 908 835 8810",
    "sg:postcode":"08809",
    "sg:province":"NJ",
    "sg:tags":[
        "accountant"
    ],
    "wof:name":"Charles Ferns CPA",
    "wof:placetype":"venue"
},
  "geometry": {"coordinates":[-74.90181800000001,40.634644],"type":"Point"}
}