{
  "type": "Feature",
  "properties": {
    "iso:country":"US",
    "sg:address":"11 Labakan Pl",
    "sg:city":"Highland Park",
    "sg:classifiers":[
        {
            "category":"Professional",
            "type":"Services"
        }
    ],
    "sg:phone":"+1   ",
    "sg:postcode":"08904",
    "sg:province":"NJ",
    "wof:name":"Walter Urteil",
    "wof:placetype":"venue"
},
  "geometry": {"coordinates":[-74.413929,40.500316],"type":"Point"}
}