{
  "type": "Feature",
  "properties": {
    "addr:full":"278 Lyons Ave Newark NJ 07112",
    "addr:housenumber":"278",
    "addr:postcode":"07112",
    "addr:street":"Lyons Ave",
    "iso:country":"US",
    "sg:address":"278 Lyons Ave",
    "sg:city":"Newark",
    "sg:classifiers":[
        {
            "category":"Retail",
            "subcategory":"Laundry & Dry Cleaning",
            "type":"Services"
        }
    ],
    "sg:phone":"+1   ",
    "sg:postcode":"07112",
    "sg:province":"NJ",
    "sg:tags":[
        "drycleaning",
        "plant"
    ],
    "wof:name":"Kgp Corporation",
    "wof:placetype":"venue"
},
  "geometry": {"coordinates":[-74.216735,40.711463],"type":"Point"}
}