{
  "type": "Feature",
  "properties": {
    "addr:full":"66 Washington Ave Nutley NJ 07110",
    "addr:housenumber":"66",
    "addr:postcode":"07110",
    "addr:street":"Washington Ave",
    "iso:country":"US",
    "sg:address":"66 Washington Ave",
    "sg:city":"Nutley",
    "sg:classifiers":[
        {
            "category":"Health Services",
            "subcategory":"Optometrist",
            "type":"Services"
        }
    ],
    "sg:phone":"+1 973 667 0600",
    "sg:postcode":"07110",
    "sg:province":"NJ",
    "wof:name":"Buick Agency In Nutley",
    "wof:placetype":"venue"
},
  "geometry": {"coordinates":[-74.146896,40.807999],"type":"Point"}
}