{
  "type": "Feature",
  "properties": {
    "iso:country":"US",
    "sg:address":"470 Mclean Blvd",
    "sg:city":"Paterson",
    "sg:classifiers":[
        {
            "category":"Retail",
            "subcategory":"Veterinary Services",
            "type":"Services"
        }
    ],
    "sg:postcode":"07513",
    "sg:province":"NJ",
    "sg:tags":[
        "veterinarian"
    ],
    "wof:name":"Blue Cross Animal Hospital",
    "wof:placetype":"venue"
},
  "geometry": {"coordinates":[-74.13511200000001,40.902933],"type":"Point"}
}