{
  "type": "Feature",
  "properties": {
    "addr:full":"110 S Broadway St South Amboy NJ 08879",
    "addr:housenumber":"110",
    "addr:postcode":"08879",
    "addr:street":"S Broadway St",
    "iso:country":"US",
    "sg:address":"110 S Broadway St",
    "sg:city":"South Amboy",
    "sg:classifiers":[
        {
            "category":"Professional",
            "subcategory":"Lawyer & Legal Services",
            "type":"Services"
        }
    ],
    "sg:phone":"+1 732 727 7100",
    "sg:postcode":"08879",
    "sg:province":"NJ",
    "wof:name":"McDonnell William J",
    "wof:placetype":"venue"
},
  "geometry": {"coordinates":[-74.28026199999999,40.483397],"type":"Point"}
}