{
  "type": "Feature",
  "properties": {
    "addr:full":"300 Scotch Rd Trenton NJ 08628",
    "addr:housenumber":"300",
    "addr:postcode":"08628",
    "addr:street":"Scotch Rd",
    "iso:country":"US",
    "sg:address":"300 Scotch Rd",
    "sg:city":"Trenton",
    "sg:classifiers":[
        {
            "category":"Government",
            "subcategory":"Office",
            "type":"Public Place"
        }
    ],
    "sg:phone":"+1   ",
    "sg:postcode":"08628",
    "sg:province":"NJ",
    "sg:tags":[
        "county",
        "highway"
    ],
    "wof:name":"Department of Transportaion",
    "wof:placetype":"venue"
},
  "geometry": {"coordinates":[-74.811036,40.285418],"type":"Point"}
}