{
  "type": "Feature",
  "properties": {
    "addr:full":"35 Love Ln Netcong NJ 07857",
    "addr:housenumber":"35",
    "addr:postcode":"07857",
    "addr:street":"Love Ln",
    "iso:country":"US",
    "sg:address":"35 Love Ln",
    "sg:city":"Netcong",
    "sg:classifiers":[
        {
            "category":"Professional",
            "type":"Services"
        }
    ],
    "sg:phone":"+1 973 691 5515",
    "sg:postcode":"07857",
    "sg:province":"NJ",
    "sg:tags":[
        "establishment"
    ],
    "wof:name":"A & M Worldwide",
    "wof:placetype":"venue"
},
  "geometry": {"coordinates":[-74.714726,40.894044],"type":"Point"}
}