{
  "type": "Feature",
  "properties": {
    "iso:country":"US",
    "sg:address":"277 US Hwy 46",
    "sg:city":"Great Meadows",
    "sg:classifiers":[
        {
            "category":"Banks & Credit Unions",
            "subcategory":"Bank",
            "type":"Services"
        }
    ],
    "sg:phone":"+1 908 459 4121",
    "sg:postcode":"07838",
    "sg:province":"NJ",
    "sg:website":"www.firsthope.com",
    "wof:name":"First Hope Bank",
    "wof:placetype":"venue"
},
  "geometry": {"coordinates":[-74.900835,40.873514],"type":"Point"}
}