{
  "type": "Feature",
  "properties": {
    "iso:country":"US",
    "sg:address":"211 Dayton St",
    "sg:city":"Ridgewood",
    "sg:classifiers":[
        {
            "category":"Professional",
            "subcategory":"Accounting & Tax Preparation",
            "type":"Services"
        }
    ],
    "sg:phone":"+1 201 445 5400",
    "sg:postcode":"07450",
    "sg:province":"NJ",
    "sg:tags":[
        "accountant"
    ],
    "wof:name":"Giambalvo & Co",
    "wof:placetype":"venue"
},
  "geometry": {"coordinates":[-74.11386899999999,40.977685],"type":"Point"}
}