{
  "type": "Feature",
  "properties": {
    "iso:country":"US",
    "sg:address":"311 Amboy Ave",
    "sg:city":"Woodbridge",
    "sg:classifiers":[
        {
            "category":"Wholesale",
            "subcategory":"Electrical",
            "type":"Manufacturing & Wholesale Goods"
        }
    ],
    "sg:phone":"+1 732 636 8600",
    "sg:postcode":"07095",
    "sg:province":"NJ",
    "sg:tags":[
        "control",
        "security",
        "system"
    ],
    "wof:name":"Honeywell International",
    "wof:placetype":"venue"
},
  "geometry": {"coordinates":[-74.280663,40.550984],"type":"Point"}
}