{
  "type": "Feature",
  "properties": {
    "iso:country":"US",
    "sg:address":"124 N Beverwyck Rd",
    "sg:city":"Parsippany",
    "sg:classifiers":[
        {
            "category":"Shopping",
            "subcategory":"Computers & Home Electronics",
            "type":"Retail Goods"
        }
    ],
    "sg:phone":"+1   ",
    "sg:postcode":"07054",
    "sg:province":"NJ",
    "wof:name":"Mystic Arts Software",
    "wof:placetype":"venue"
},
  "geometry": {"coordinates":[-74.38327099999999,40.867561],"type":"Point"}
}