{
  "type": "Feature",
  "properties": {
    "iso:country":"US",
    "sg:address":"520 State Rte 70",
    "sg:city":"Brick",
    "sg:classifiers":[
        {
            "category":"Home & Garden",
            "subcategory":"Building Materials",
            "type":"Retail Goods"
        }
    ],
    "sg:phone":"+1   ",
    "sg:postcode":"08723",
    "sg:province":"NJ",
    "wof:name":"Lowes",
    "wof:placetype":"venue"
},
  "geometry": {"coordinates":[-74.14978000000001,40.057331],"type":"Point"}
}