{
  "type": "Feature",
  "properties": {
    "iso:country":"US",
    "sg:address":"27 Dartmouth Rd",
    "sg:city":"Mountain Lakes",
    "sg:classifiers":[
        {
            "category":"Shopping",
            "subcategory":"Computers & Home Electronics",
            "type":"Retail Goods"
        }
    ],
    "sg:phone":"+1 973 257 1666",
    "sg:postcode":"07046",
    "sg:province":"NJ",
    "sg:tags":[
        "software"
    ],
    "wof:name":"Emax Solutions Inc",
    "wof:placetype":"venue"
},
  "geometry": {"coordinates":[-74.43338300000001,40.891353],"type":"Point"}
}