{
  "type": "Feature",
  "properties": {
    "addr:full":"424 E Main St Millville NJ 08332",
    "addr:housenumber":"424",
    "addr:postcode":"08332",
    "addr:street":"E Main St",
    "iso:country":"US",
    "sg:address":"424 E Main St",
    "sg:city":"Millville",
    "sg:classifiers":[
        {
            "category":"Professional",
            "subcategory":"Computer Services",
            "type":"Services"
        }
    ],
    "sg:phone":"+1   ",
    "sg:postcode":"08332",
    "sg:province":"NJ",
    "sg:tags":[
        "repair",
        "consulting"
    ],
    "wof:name":"Jims Computer Service",
    "wof:placetype":"venue"
},
  "geometry": {"coordinates":[-75.03307,39.395439],"type":"Point"}
}