{
  "type": "Feature",
  "properties": {
    "iso:country":"US",
    "sg:address":"176 Park Ave",
    "sg:city":"Rutherford",
    "sg:classifiers":[
        {
            "category":"Education",
            "subcategory":"School",
            "type":"Public Place"
        }
    ],
    "sg:phone":"+1 201 939 1717",
    "sg:postcode":"07070",
    "sg:province":"NJ",
    "wof:name":"Rutherford Superintendent-Schl",
    "wof:placetype":"venue"
},
  "geometry": {"coordinates":[-74.107136,40.826204],"type":"Point"}
}