{
  "type": "Feature",
  "properties": {
    "iso:country":"US",
    "sg:address":"616 Newark Pompton Tpke",
    "sg:city":"Pompton Plains",
    "sg:classifiers":[
        {
            "category":"Food & Beverages",
            "subcategory":"Candy",
            "type":"Retail Goods"
        },
        {
            "category":"Restaurant",
            "type":"Food & Drink"
        }
    ],
    "sg:phone":"+1 973 835 9613",
    "sg:postcode":"07444",
    "sg:province":"NJ",
    "sg:tags":[
        "confectionery",
        "eating"
    ],
    "wof:name":"Annie's Sweet Shop",
    "wof:placetype":"venue"
},
  "geometry": {"coordinates":[-74.295923,40.968696],"type":"Point"}
}