{
  "type": "Feature",
  "properties": {
    "addr:full":"329 Sycamore Ave Shrewsbury NJ 07702",
    "addr:housenumber":"329",
    "addr:postcode":"07702",
    "addr:street":"Sycamore Ave",
    "iso:country":"US",
    "sg:address":"329 Sycamore Ave",
    "sg:city":"Shrewsbury",
    "sg:classifiers":[
        {
            "category":"Organizations",
            "subcategory":"Religious Organization",
            "type":"Services"
        }
    ],
    "sg:phone":"+1 732 747 5728",
    "sg:postcode":"07702",
    "sg:province":"NJ",
    "sg:tags":[
        "clergy"
    ],
    "wof:name":"James E La Sage",
    "wof:placetype":"venue"
},
  "geometry": {"coordinates":[-74.060012,40.324302],"type":"Point"}
}