{
  "type": "Feature",
  "properties": {
    "addr:full":"48 S New York Rd Galloway NJ 08205",
    "addr:housenumber":"48",
    "addr:postcode":"08205",
    "addr:street":"S New York Rd",
    "iso:country":"US",
    "sg:address":"48 S New York Rd",
    "sg:city":"Galloway",
    "sg:classifiers":[
        {
            "category":"Health Services",
            "subcategory":"Health Practitioner",
            "type":"Services"
        }
    ],
    "sg:phone":"+1 609 965 4766",
    "sg:postcode":"08205",
    "sg:province":"NJ",
    "sg:tags":[
        "nutritionist"
    ],
    "wof:name":"Consultants For Better Living",
    "wof:placetype":"venue"
},
  "geometry": {"coordinates":[-74.458578,39.488248],"type":"Point"}
}