{
  "type": "Feature",
  "properties": {
    "iso:country":"US",
    "sg:address":"150 W End Ave",
    "sg:city":"Somerville",
    "sg:classifiers":[
        {
            "category":"Wholesale",
            "subcategory":"Medical Equipment & Supplies",
            "type":"Manufacturing & Wholesale Goods"
        }
    ],
    "sg:phone":"+1 908 575 1976",
    "sg:postcode":"08807",
    "sg:province":"NJ",
    "sg:tags":[
        "dental"
    ],
    "wof:name":"E & D Dental Products Inc",
    "wof:placetype":"venue"
},
  "geometry": {"coordinates":[-74.624684,40.573496],"type":"Point"}
}