{
  "type": "Feature",
  "properties": {
    "iso:country":"US",
    "sg:address":"40 E Milton Ave",
    "sg:city":"Rahway",
    "sg:classifiers":[
        {
            "category":"Restaurant",
            "type":"Food & Drink"
        }
    ],
    "sg:phone":"+1   ",
    "sg:postcode":"07065",
    "sg:province":"NJ",
    "sg:tags":[
        "eating"
    ],
    "wof:name":"Moca Motion Cafe",
    "wof:placetype":"venue"
},
  "geometry": {"coordinates":[-74.276704,40.606003],"type":"Point"}
}