{
  "type": "Feature",
  "properties": {
    "addr:full":"80 Embury Ave Ocean Grove NJ 07756",
    "addr:housenumber":"80",
    "addr:postcode":"07756",
    "addr:street":"Embury Ave",
    "iso:country":"US",
    "sg:address":"80 Embury Ave",
    "sg:city":"Ocean Grove",
    "sg:classifiers":[
        {
            "category":"Organizations",
            "subcategory":"Religious Organization",
            "type":"Services"
        }
    ],
    "sg:phone":"+1 732 775 1125",
    "sg:postcode":"07756",
    "sg:province":"NJ",
    "sg:tags":[
        "church"
    ],
    "wof:name":"St Paul's United Methodist Chr",
    "wof:placetype":"venue"
},
  "geometry": {"coordinates":[-74.008291,40.211199],"type":"Point"}
}