{
  "type": "Feature",
  "properties": {
    "addr:full":"430 S Main St Phillipsburg NJ 08865",
    "addr:housenumber":"430",
    "addr:postcode":"08865",
    "addr:street":"S Main St",
    "iso:country":"US",
    "sg:address":"430 S Main St",
    "sg:city":"Phillipsburg",
    "sg:classifiers":[
        {
            "category":"Organizations",
            "subcategory":"Religious Organization",
            "type":"Services"
        }
    ],
    "sg:phone":"+1 908 454 7620",
    "sg:postcode":"08865",
    "sg:province":"NJ",
    "sg:tags":[
        "church"
    ],
    "wof:name":"St Philips & Saint James",
    "wof:placetype":"venue"
},
  "geometry": {"coordinates":[-75.18859999999999,40.684849],"type":"Point"}
}