{
  "type": "Feature",
  "properties": {
    "iso:country":"US",
    "sg:address":"35 Farley Ave",
    "sg:city":"Newark",
    "sg:classifiers":[
        {
            "category":"Restaurant",
            "type":"Food & Drink"
        }
    ],
    "sg:phone":"+1   ",
    "sg:postcode":"07108",
    "sg:province":"NJ",
    "sg:tags":[
        "eating"
    ],
    "wof:name":"Star Deli Sub",
    "wof:placetype":"venue"
},
  "geometry": {"coordinates":[-74.20207000000001,40.725274],"type":"Point"}
}