{
  "type": "Feature",
  "properties": {
    "addr:full":"2 State Rte 31 Pennington NJ 08534",
    "addr:housenumber":"2",
    "addr:postcode":"08534",
    "addr:street":"State Rte 31",
    "iso:country":"US",
    "sg:address":"2 State Rte 31",
    "sg:city":"Pennington",
    "sg:classifiers":[
        {
            "category":"Banks & Credit Unions",
            "subcategory":"Bank",
            "type":"Services"
        }
    ],
    "sg:phone":"+1 609 737 0079",
    "sg:postcode":"08534",
    "sg:province":"NJ",
    "sg:website":"www.wachovia.com",
    "wof:name":"Wachovia Bank",
    "wof:placetype":"venue"
},
  "geometry": {"coordinates":[-74.79905599999999,40.326688],"type":"Point"}
}