{
  "type": "Feature",
  "properties": {
    "addr:full":"150 Rifle Camp Rd West Paterson NJ 07424",
    "addr:housenumber":"150",
    "addr:postcode":"07424",
    "addr:street":"Rifle Camp Rd West",
    "iso:country":"US",
    "sg:address":"150 Rifle Camp Rd",
    "sg:city":"West Paterson",
    "sg:classifiers":[
        {
            "category":"Deli",
            "type":"Food & Drink"
        }
    ],
    "sg:phone":"+1 973 684 7500",
    "sg:postcode":"07424",
    "sg:province":"NJ",
    "wof:name":"My Sisters Gourmet Deli",
    "wof:placetype":"venue"
},
  "geometry": {"coordinates":[-74.206497,40.883801],"type":"Point"}
}