{
  "type": "Feature",
  "properties": {
    "iso:country":"US",
    "sg:address":"402 Atlantic Ave",
    "sg:city":"Long Branch",
    "sg:classifiers":[
        {
            "category":"Professional",
            "subcategory":"Computer Services",
            "type":"Services"
        }
    ],
    "sg:phone":"+1   ",
    "sg:postcode":"07740",
    "sg:province":"NJ",
    "sg:tags":[
        "on",
        "sales",
        "internet"
    ],
    "wof:name":"Watching Your Security",
    "wof:placetype":"venue"
},
  "geometry": {"coordinates":[-73.999348,40.311902],"type":"Point"}
}