{
  "type": "Feature",
  "properties": {
    "addr:full":"225 Broad Ave Ste 102 Palisades Park NJ 07650",
    "addr:housenumber":"225",
    "addr:postcode":"07650",
    "addr:street":"Broad Ave Ste 102",
    "iso:country":"US",
    "sg:address":"225 Broad Ave Ste 102",
    "sg:city":"Palisades Park",
    "sg:classifiers":[
        {
            "category":"Health Services",
            "subcategory":"Doctor",
            "type":"Services"
        }
    ],
    "sg:phone":"+1 201 461 5580",
    "sg:postcode":"07650",
    "sg:province":"NJ",
    "sg:tags":[
        "surgeon",
        "oral"
    ],
    "wof:name":"Junj Richard DDS",
    "wof:placetype":"venue"
},
  "geometry": {"coordinates":[-73.99900100000001,40.846298],"type":"Point"}
}