{
  "type": "Feature",
  "properties": {
    "iso:country":"US",
    "sg:address":"1 Executive Dr",
    "sg:city":"Red Bank",
    "sg:classifiers":[
        {
            "category":"Professional",
            "subcategory":"Lawyer & Legal Services",
            "type":"Services"
        }
    ],
    "sg:phone":"+1 732 842 4777",
    "sg:postcode":"07701",
    "sg:province":"NJ",
    "sg:tags":[
        "attorney"
    ],
    "wof:name":"Goldring & Edwards LLC",
    "wof:placetype":"venue"
},
  "geometry": {"coordinates":[-74.075884,40.329105],"type":"Point"}
}