{
  "type": "Feature",
  "properties": {
    "iso:country":"US",
    "sg:address":"140 S Riverside Dr",
    "sg:city":"Neptune",
    "sg:classifiers":[
        {
            "category":"Restaurant",
            "type":"Food & Drink"
        }
    ],
    "sg:phone":"+1   ",
    "sg:postcode":"07753",
    "sg:province":"NJ",
    "sg:tags":[
        "eating"
    ],
    "wof:name":"Bistro - By - The - Sea Inc",
    "wof:placetype":"venue"
},
  "geometry": {"coordinates":[-74.03904300000001,40.193021],"type":"Point"}
}