{
  "type": "Feature",
  "properties": {
    "iso:country":"US",
    "sg:address":"2523 Nottingham Way",
    "sg:city":"Mercerville",
    "sg:classifiers":[
        {
            "category":"Insurance",
            "subcategory":"Insurance Agent",
            "type":"Services"
        }
    ],
    "sg:phone":"+1 609 584 2501",
    "sg:postcode":"08619",
    "sg:province":"NJ",
    "wof:name":"Frances Martillotti",
    "wof:placetype":"venue"
},
  "geometry": {"coordinates":[-74.69499999999999,40.234386],"type":"Point"}
}