{
  "type": "Feature",
  "properties": {
    "iso:country":"US",
    "sg:address":"52 Tomahawk Trl",
    "sg:city":"Denville",
    "sg:classifiers":[
        {
            "category":"Building & Trades",
            "subcategory":"Construction",
            "type":"Services"
        }
    ],
    "sg:phone":"+1 973 627 5444",
    "sg:postcode":"07834",
    "sg:province":"NJ",
    "sg:tags":[
        "carpentry",
        "contractor"
    ],
    "wof:name":"Deter Carpentry",
    "wof:placetype":"venue"
},
  "geometry": {"coordinates":[-74.49388399999999,40.896046],"type":"Point"}
}