{
  "type": "Feature",
  "properties": {
    "addr:full":"326 E Harriet Ave Palisades Park NJ 07650",
    "addr:housenumber":"326",
    "addr:postcode":"07650",
    "addr:street":"E Harriet Ave",
    "iso:country":"US",
    "sg:address":"326 E Harriet Ave",
    "sg:city":"Palisades Park",
    "sg:classifiers":[
        {
            "category":"Banks & Credit Unions",
            "subcategory":"Financial Services",
            "type":"Services"
        }
    ],
    "sg:phone":"+1   ",
    "sg:postcode":"07650",
    "sg:province":"NJ",
    "sg:tags":[
        "company",
        "holding"
    ],
    "wof:name":"B&M Property Holdings LLC",
    "wof:placetype":"venue"
},
  "geometry": {"coordinates":[-73.9952,40.838291],"type":"Point"}
}