{
  "type": "Feature",
  "properties": {
    "addr:full":"4 Deerwood Dr Clinton NJ 08809",
    "addr:housenumber":"4",
    "addr:postcode":"08809",
    "addr:street":"Deerwood Dr",
    "iso:country":"US",
    "sg:address":"4 Deerwood Dr",
    "sg:city":"Clinton",
    "sg:classifiers":[
        {
            "category":"Building & Trades",
            "subcategory":"Landscaping Services",
            "type":"Services"
        }
    ],
    "sg:phone":"+1 908 638 5484",
    "sg:postcode":"08809",
    "sg:province":"NJ",
    "sg:tags":[
        "landscape",
        "contractor"
    ],
    "wof:name":"Budding Earth Garden Svc",
    "wof:placetype":"venue"
},
  "geometry": {"coordinates":[-74.929789,40.671247],"type":"Point"}
}