{
  "type": "Feature",
  "properties": {
    "addr:full":"701 State Rte 73 Marlton NJ 08053",
    "addr:housenumber":"701",
    "addr:postcode":"08053",
    "addr:street":"State Rte 73",
    "iso:country":"US",
    "sg:address":"701 State Rte 73",
    "sg:city":"Marlton",
    "sg:classifiers":[
        {
            "category":"Banks & Credit Unions",
            "subcategory":"Investment Brokerage",
            "type":"Services"
        }
    ],
    "sg:phone":"+1   ",
    "sg:postcode":"08053",
    "sg:province":"NJ",
    "sg:tags":[
        "security"
    ],
    "wof:name":"UBS Financial Services Inc",
    "wof:placetype":"venue"
},
  "geometry": {"coordinates":[-74.921978,39.87103],"type":"Point"}
}