{
  "type": "Feature",
  "properties": {
    "iso:country":"US",
    "sg:address":"138 Chews Landing Rd",
    "sg:city":"Laurel Springs",
    "sg:classifiers":[
        {
            "category":"Social Services",
            "subcategory":"Child Care",
            "type":"Services"
        }
    ],
    "sg:phone":"+1 856 228 1186",
    "sg:postcode":"08021",
    "sg:province":"NJ",
    "wof:name":"My Special Place",
    "wof:placetype":"venue"
},
  "geometry": {"coordinates":[-75.003421,39.807414],"type":"Point"}
}