{
  "type": "Feature",
  "properties": {
    "addr:full":"817 Hudson Ave Secaucus NJ 07094",
    "addr:housenumber":"817",
    "addr:postcode":"07094",
    "addr:street":"Hudson Ave",
    "iso:country":"US",
    "sg:address":"817 Hudson Ave",
    "sg:city":"Secaucus",
    "sg:classifiers":[
        {
            "category":"Professional",
            "subcategory":"Business Services",
            "type":"Services"
        }
    ],
    "sg:phone":"+1 201 863 8881",
    "sg:postcode":"07094",
    "sg:province":"NJ",
    "sg:tags":[
        "record",
        "medical"
    ],
    "wof:name":"Daluma Incorp",
    "wof:placetype":"venue"
},
  "geometry": {"coordinates":[-74.064339,40.79484],"type":"Point"}
}