{
  "type": "Feature",
  "properties": {
    "addr:full":"25 Mariner Pl Brick NJ 08723",
    "addr:housenumber":"25",
    "addr:postcode":"08723",
    "addr:street":"Mariner Pl",
    "iso:country":"US",
    "sg:address":"25 Mariner Pl",
    "sg:city":"Brick",
    "sg:classifiers":[
        {
            "category":"Autos & Motor Vehicles",
            "subcategory":"Boat Sales",
            "type":"Retail Goods"
        }
    ],
    "sg:phone":"+1 732 477 1929",
    "sg:postcode":"08723",
    "sg:province":"NJ",
    "sg:tags":[
        "equipment",
        "marine",
        "supply"
    ],
    "wof:name":"Cherry V Marine Construction",
    "wof:placetype":"venue"
},
  "geometry": {"coordinates":[-74.136633,40.027588],"type":"Point"}
}