{
  "type": "Feature",
  "properties": {
    "addr:full":"127 Jacobs Rd Newfoundland NJ 07435",
    "addr:housenumber":"127",
    "addr:postcode":"07435",
    "addr:street":"Jacobs Rd",
    "iso:country":"US",
    "sg:address":"127 Jacobs Rd",
    "sg:city":"Newfoundland",
    "sg:classifiers":[
        {
            "category":"Restaurant",
            "type":"Food & Drink"
        }
    ],
    "sg:phone":"+1   ",
    "sg:postcode":"07435",
    "sg:province":"NJ",
    "sg:tags":[
        "chef",
        "semi"
    ],
    "wof:name":"Lets Talk Food",
    "wof:placetype":"venue"
},
  "geometry": {"coordinates":[-74.46063700000001,41.016623],"type":"Point"}
}