{
  "type": "Feature",
  "properties": {
    "iso:country":"US",
    "sg:address":"831 Parkway Ave",
    "sg:city":"Trenton",
    "sg:classifiers":[
        {
            "category":"Autos & Motor Vehicles",
            "subcategory":"Auto Supplies",
            "type":"Retail Goods"
        }
    ],
    "sg:phone":"+1 609 883 1934",
    "sg:postcode":"08618",
    "sg:province":"NJ",
    "sg:tags":[
        "repair",
        "stereo",
        "radio",
        "automotive",
        "automobile"
    ],
    "wof:name":"Gordon Auto Radio",
    "wof:placetype":"venue"
},
  "geometry": {"coordinates":[-74.791262,40.253698],"type":"Point"}
}