{
  "type": "Feature",
  "properties": {
    "iso:country":"US",
    "sg:address":"3 Crossman Rd S",
    "sg:city":"Sayreville",
    "sg:classifiers":[
        {
            "category":"Professional",
            "subcategory":"Research",
            "type":"Services"
        }
    ],
    "sg:phone":"+1 732 721 4700",
    "sg:postcode":"08872",
    "sg:province":"NJ",
    "sg:tags":[
        "development",
        "pharmaceutical",
        "mfg",
        "commercial",
        "laboratory",
        "physical"
    ],
    "sg:website":"www.chemodynamics.com",
    "wof:name":"Chemo Dynamics Inc",
    "wof:placetype":"venue"
},
  "geometry": {"coordinates":[-74.31913400000001,40.475348],"type":"Point"}
}