{
  "type": "Feature",
  "properties": {
    "iso:country":"US",
    "sg:address":"225 May St Ste F",
    "sg:city":"Edison",
    "sg:classifiers":[
        {
            "category":"Health Services",
            "subcategory":"Doctor",
            "type":"Services"
        }
    ],
    "sg:phone":"+1 732 738 8855",
    "sg:postcode":"08837",
    "sg:province":"NJ",
    "sg:tags":[
        "cardiologist"
    ],
    "wof:name":"Raritan Bay Cardiology Group PA",
    "wof:placetype":"venue"
},
  "geometry": {"coordinates":[-74.324203,40.528198],"type":"Point"}
}