{
  "type": "Feature",
  "properties": {
    "iso:country":"US",
    "sg:address":"143 Raymond Ave",
    "sg:city":"Marlton",
    "sg:classifiers":[
        {
            "category":"Building & Trades",
            "subcategory":"Plumbing",
            "type":"Services"
        }
    ],
    "sg:phone":"+1 856 753 9871",
    "sg:postcode":"08053",
    "sg:province":"NJ",
    "sg:tags":[
        "contractor"
    ],
    "wof:name":"George R Coulter Plumbing & He",
    "wof:placetype":"venue"
},
  "geometry": {"coordinates":[-74.898279,39.793219],"type":"Point"}
}