{
  "type": "Feature",
  "properties": {
    "addr:full":"2107 Herbertsville Rd Pt Pleasant Boro NJ 08742",
    "addr:housenumber":"2107",
    "addr:postcode":"08742",
    "addr:street":"Herbertsville Rd Pt",
    "iso:country":"US",
    "sg:address":"2107 Herbertsville Rd",
    "sg:city":"Pt Pleasant Boro",
    "sg:classifiers":[
        {
            "category":"Wholesale",
            "subcategory":"Construction Materials",
            "type":"Manufacturing & Wholesale Goods"
        },
        {
            "category":"Home & Garden",
            "subcategory":"Furniture",
            "type":"Retail Goods"
        }
    ],
    "sg:phone":"+1 732 892 1121",
    "sg:postcode":"08742",
    "sg:province":"NJ",
    "sg:tags":[
        "wooden",
        "equipment",
        "kitchen",
        "cabinet"
    ],
    "wof:name":"Finest Kitchens & Stairs",
    "wof:placetype":"venue"
},
  "geometry": {"coordinates":[-74.068983,40.083326],"type":"Point"}
}