{
  "type": "Feature",
  "properties": {
    "addr:full":"40 Kiceniuk Rd Annandale NJ 08801",
    "addr:housenumber":"40",
    "addr:postcode":"08801",
    "addr:street":"Kiceniuk Rd",
    "iso:country":"US",
    "sg:address":"40 Kiceniuk Rd",
    "sg:city":"Annandale",
    "sg:classifiers":[
        {
            "category":"Wholesale",
            "subcategory":"Farm Supplies",
            "type":"Manufacturing & Wholesale Goods"
        }
    ],
    "sg:phone":"+1 908 782 0007",
    "sg:postcode":"08801",
    "sg:province":"NJ",
    "sg:tags":[
        "horse",
        "dealer"
    ],
    "wof:name":"Four Seasons Farm",
    "wof:placetype":"venue"
},
  "geometry": {"coordinates":[-74.881649,40.580204],"type":"Point"}
}