{
  "type": "Feature",
  "properties": {
    "iso:country":"US",
    "sg:address":"576 Casino Dr",
    "sg:city":"Howell",
    "sg:classifiers":[
        {
            "category":"Manufacturing",
            "subcategory":"Signs",
            "type":"Manufacturing & Wholesale Goods"
        }
    ],
    "sg:phone":"+1 732 625 0101",
    "sg:postcode":"07731",
    "sg:province":"NJ",
    "sg:tags":[
        "specialty",
        "mfg"
    ],
    "wof:name":"Superior Graphics & Signs Inc",
    "wof:placetype":"venue"
},
  "geometry": {"coordinates":[-74.235749,40.201434],"type":"Point"}
}