{
  "type": "Feature",
  "properties": {
    "addr:full":"160 Broadway Hillsdale NJ 07642",
    "addr:housenumber":"160",
    "addr:postcode":"07642",
    "addr:street":"Broadway",
    "iso:country":"US",
    "sg:address":"160 Broadway",
    "sg:city":"Hillsdale",
    "sg:classifiers":[
        {
            "category":"Retail",
            "subcategory":"Laundry & Dry Cleaning",
            "type":"Services"
        }
    ],
    "sg:phone":"+1 201 664 5998",
    "sg:postcode":"07642",
    "sg:province":"NJ",
    "sg:tags":[
        "drycleaning",
        "plant",
        "cleaners"
    ],
    "wof:name":"Hillsdale Dry Cleaning Inc",
    "wof:placetype":"venue"
},
  "geometry": {"coordinates":[-74.04101799999999,41.005576],"type":"Point"}
}