{
  "type": "Feature",
  "properties": {
    "addr:full":"599 River Rd North Arlington NJ 07031",
    "addr:housenumber":"599",
    "addr:postcode":"07031",
    "addr:street":"River Rd North",
    "iso:country":"US",
    "sg:address":"599 River Rd",
    "sg:city":"North Arlington",
    "sg:classifiers":[
        {
            "category":"Restaurant",
            "type":"Food & Drink"
        }
    ],
    "sg:menulink":"http://www.allmenus.com/nj/north-arlington/5940-bensi-of-north-arlington-inc/menu/",
    "sg:phone":"+1 201 246 0100",
    "sg:postcode":"07031",
    "sg:province":"NJ",
    "sg:tags":[
        "italian"
    ],
    "wof:name":"Bensi Of North Arlington Inc.",
    "wof:placetype":"venue"
},
  "geometry": {"coordinates":[-74.134034,40.802126],"type":"Point"}
}