{
  "type": "Feature",
  "properties": {
    "addr:full":"331 Main St West Orange NJ 07052",
    "addr:housenumber":"331",
    "addr:postcode":"07052",
    "addr:street":"Main St",
    "iso:country":"US",
    "sg:address":"331 Main St",
    "sg:city":"West Orange",
    "sg:classifiers":[
        {
            "category":"Professional",
            "subcategory":"Accounting & Tax Preparation",
            "type":"Services"
        }
    ],
    "sg:phone":"+1 973 324 0790",
    "sg:postcode":"07052",
    "sg:province":"NJ",
    "sg:tags":[
        "accountant"
    ],
    "wof:name":"Louis L Dinnerstein CPA",
    "wof:placetype":"venue"
},
  "geometry": {"coordinates":[-74.23194700000001,40.789458],"type":"Point"}
}