{
  "type": "Feature",
  "properties": {
    "addr:full":"5 Washington St Rocky Hill NJ 08525",
    "addr:housenumber":"5",
    "addr:postcode":"08525",
    "addr:street":"Washington St",
    "iso:country":"US",
    "sg:address":"5 Washington St",
    "sg:city":"Rocky Hill",
    "sg:classifiers":[
        {
            "category":"Professional",
            "subcategory":"Accounting & Tax Preparation",
            "type":"Services"
        }
    ],
    "sg:phone":"+1 609 497 0110",
    "sg:postcode":"08525",
    "sg:province":"NJ",
    "sg:tags":[
        "accountant"
    ],
    "wof:name":"Hy Appelbaum CPA",
    "wof:placetype":"venue"
},
  "geometry": {"coordinates":[-74.762944,40.395325],"type":"Point"}
}