{
  "type": "Feature",
  "properties": {
    "addr:full":"14 Madison Rd Fairfield NJ 07004",
    "addr:housenumber":"14",
    "addr:postcode":"07004",
    "addr:street":"Madison Rd",
    "iso:country":"US",
    "sg:address":"14 Madison Rd",
    "sg:city":"Fairfield",
    "sg:classifiers":[
        {
            "category":"Manufacturing",
            "subcategory":"Electronics",
            "type":"Manufacturing & Wholesale Goods"
        }
    ],
    "sg:phone":"+1 973 227 9400",
    "sg:postcode":"07004",
    "sg:province":"NJ",
    "sg:tags":[
        "communications",
        "equipment"
    ],
    "wof:name":"Executone Information System",
    "wof:placetype":"venue"
},
  "geometry": {"coordinates":[-74.31028499999999,40.871643],"type":"Point"}
}