{
  "type": "Feature",
  "properties": {
    "iso:country":"US",
    "sg:address":"Suite 200 1940 Route 70 East",
    "sg:city":"Cherry Hill",
    "sg:classifiers":[
        {
            "category":"Professional",
            "subcategory":"Lawyer & Legal Services",
            "type":"Services"
        }
    ],
    "sg:phone":"+1 215 979 1000",
    "sg:postcode":"08003",
    "sg:province":"NJ",
    "sg:website":"http://www.duanemorris.com",
    "wof:name":"Duane Morris LLP",
    "wof:placetype":"venue"
},
  "geometry": {"coordinates":[-74.979764,39.907417],"type":"Point"}
}