{
  "type": "Feature",
  "properties": {
    "addr:full":"195 Belgrove Dr Kearny NJ 07032",
    "addr:housenumber":"195",
    "addr:postcode":"07032",
    "addr:street":"Belgrove Dr",
    "iso:country":"US",
    "sg:address":"195 Belgrove Dr",
    "sg:city":"Kearny",
    "sg:classifiers":[
        {
            "category":"Health Services",
            "subcategory":"Nursing And Care Facility",
            "type":"Services"
        }
    ],
    "sg:phone":"+1 973 844 4800",
    "sg:postcode":"07032",
    "sg:province":"NJ",
    "sg:tags":[
        "home",
        "convalescent"
    ],
    "wof:name":"Clara Maass Continuing Care",
    "wof:placetype":"venue"
},
  "geometry": {"coordinates":[-74.158158,40.758094],"type":"Point"}
}