{
  "type": "Feature",
  "properties": {
    "addr:full":"15 Fieldmere Ave Glen Rock NJ 07452",
    "addr:housenumber":"15",
    "addr:postcode":"07452",
    "addr:street":"Fieldmere Ave",
    "iso:country":"US",
    "sg:address":"15 Fieldmere Ave",
    "sg:city":"Glen Rock",
    "sg:classifiers":[
        {
            "category":"Education",
            "subcategory":"Special Training",
            "type":"Public Place"
        }
    ],
    "sg:phone":"+1 201 447 0499",
    "sg:postcode":"07452",
    "sg:province":"NJ",
    "sg:tags":[
        "tutoring"
    ],
    "wof:name":"K & L Tutoring",
    "wof:placetype":"venue"
},
  "geometry": {"coordinates":[-74.109312,40.953324],"type":"Point"}
}