{
  "type": "Feature",
  "properties": {
    "iso:country":"US",
    "sg:address":"500 Harbor Blvd",
    "sg:city":"Weehawken",
    "sg:classifiers":[
        {
            "category":"Shopping",
            "subcategory":"Gifts & Souvenirs",
            "type":"Retail Goods"
        }
    ],
    "sg:phone":"+1   ",
    "sg:postcode":"07086",
    "sg:province":"NJ",
    "sg:tags":[
        "shop"
    ],
    "wof:name":"Gift-O-Rama",
    "wof:placetype":"venue"
},
  "geometry": {"coordinates":[-74.021041,40.764069],"type":"Point"}
}