{
  "type": "Feature",
  "properties": {
    "iso:country":"US",
    "sg:address":"1571 Grandview Ave",
    "sg:city":"Paulsboro",
    "sg:classifiers":[
        {
            "category":"Shopping",
            "subcategory":"Party Supplies",
            "type":"Retail Goods"
        }
    ],
    "sg:phone":"+1 856 579 1421",
    "sg:postcode":"08066",
    "sg:province":"NJ",
    "sg:tags":[
        "favors"
    ],
    "sg:website":"http://www.samsonind.com",
    "wof:name":"Philadelphia Division",
    "wof:placetype":"venue"
},
  "geometry": {"coordinates":[-75.205262,39.831641],"type":"Point"}
}