{
  "type": "Feature",
  "properties": {
    "addr:full":"32 Rivington Ave West Long Branch NJ 07764",
    "addr:housenumber":"32",
    "addr:postcode":"07764",
    "addr:street":"Rivington Ave West",
    "iso:country":"US",
    "sg:address":"32 Rivington Ave",
    "sg:city":"West Long Branch",
    "sg:classifiers":[
        {
            "category":"Building & Trades",
            "subcategory":"Plumbing",
            "type":"Services"
        }
    ],
    "sg:phone":"+1 732 923 0222",
    "sg:postcode":"07764",
    "sg:province":"NJ",
    "sg:tags":[
        "contractor"
    ],
    "wof:name":"Kelton Service",
    "wof:placetype":"venue"
},
  "geometry": {"coordinates":[-74.01399600000001,40.30127],"type":"Point"}
}