{
  "type": "Feature",
  "properties": {
    "addr:full":"2055 Hamburg Tpke Wayne NJ 07470",
    "addr:housenumber":"2055",
    "addr:postcode":"07470",
    "addr:street":"Hamburg Tpke",
    "iso:country":"US",
    "sg:address":"2055 Hamburg Tpke",
    "sg:city":"Wayne",
    "sg:classifiers":[
        {
            "category":"Banks & Credit Unions",
            "subcategory":"Bank",
            "type":"Services"
        }
    ],
    "sg:phone":"+1   ",
    "sg:postcode":"07470",
    "sg:province":"NJ",
    "sg:tags":[
        "state",
        "commercial"
    ],
    "wof:name":"Hudson United Bank",
    "wof:placetype":"venue"
},
  "geometry": {"coordinates":[-74.26404599999999,40.972484],"type":"Point"}
}