{
  "type": "Feature",
  "properties": {
    "iso:country":"US",
    "sg:address":"320 Evesboro Medford Rd",
    "sg:city":"Marlton",
    "sg:classifiers":[
        {
            "category":"Restaurant",
            "type":"Food & Drink"
        }
    ],
    "sg:phone":"+1 856 596 3030",
    "sg:postcode":"08053",
    "sg:province":"NJ",
    "wof:name":"Mulan Chinese Restaurant",
    "wof:placetype":"venue"
},
  "geometry": {"coordinates":[-74.897218,39.902361],"type":"Point"}
}