{
  "type": "Feature",
  "properties": {
    "iso:country":"US",
    "sg:address":"19 Hilliard Dr",
    "sg:city":"Manahawkin",
    "sg:classifiers":[
        {
            "category":"Food & Beverages",
            "subcategory":"Specialty",
            "type":"Retail Goods"
        }
    ],
    "sg:phone":"+1   ",
    "sg:postcode":"08050",
    "sg:province":"NJ",
    "sg:tags":[
        "health"
    ],
    "wof:name":"Natures Nest",
    "wof:placetype":"venue"
},
  "geometry": {"coordinates":[-74.256739,39.697622],"type":"Point"}
}