{
  "type": "Feature",
  "properties": {
    "iso:country":"US",
    "sg:address":"6 Archer Dr",
    "sg:city":"Boonton",
    "sg:classifiers":[
        {
            "category":"Building & Trades",
            "subcategory":"Plumbing",
            "type":"Services"
        }
    ],
    "sg:phone":"+1 973 334 5103",
    "sg:postcode":"07005",
    "sg:province":"NJ",
    "sg:tags":[
        "contractor"
    ],
    "wof:name":"Archer Plumbing & Heating LLC",
    "wof:placetype":"venue"
},
  "geometry": {"coordinates":[-74.45678700000001,40.940715],"type":"Point"}
}