{
  "type": "Feature",
  "properties": {
    "addr:full":"16 Peake Rd Edison NJ 08837",
    "addr:housenumber":"16",
    "addr:postcode":"08837",
    "addr:street":"Peake Rd",
    "iso:country":"US",
    "sg:address":"16 Peake Rd",
    "sg:city":"Edison",
    "sg:classifiers":[
        {
            "category":"Personal",
            "type":"Services"
        }
    ],
    "sg:phone":"+1   ",
    "sg:postcode":"08837",
    "sg:province":"NJ",
    "wof:name":"Randi Rae Entertainm",
    "wof:placetype":"venue"
},
  "geometry": {"coordinates":[-74.324876,40.540469],"type":"Point"}
}