{
  "type": "Feature",
  "properties": {
    "addr:full":"3731 Herbert Ave Pennsauken NJ 08109",
    "addr:housenumber":"3731",
    "addr:postcode":"08109",
    "addr:street":"Herbert Ave",
    "iso:country":"US",
    "sg:address":"3731 Herbert Ave",
    "sg:city":"Pennsauken",
    "sg:classifiers":[
        {
            "category":"Real Estate",
            "subcategory":"Real Estate Operator",
            "type":"Services"
        }
    ],
    "sg:phone":"+1 856 662 0274",
    "sg:postcode":"08109",
    "sg:province":"NJ",
    "sg:tags":[
        "apartment"
    ],
    "wof:name":"Sycamore Ridge",
    "wof:placetype":"venue"
},
  "geometry": {"coordinates":[-75.030602,39.955601],"type":"Point"}
}