{
  "type": "Feature",
  "properties": {
    "addr:full":"39 Normandy Dr Parsippany NJ 07054",
    "addr:housenumber":"39",
    "addr:postcode":"07054",
    "addr:street":"Normandy Dr",
    "iso:country":"US",
    "sg:address":"39 Normandy Dr",
    "sg:city":"Parsippany",
    "sg:classifiers":[
        {
            "category":"Shopping",
            "type":"Retail Goods"
        }
    ],
    "sg:phone":"+1 973 560 1515",
    "sg:postcode":"07054",
    "sg:province":"NJ",
    "sg:tags":[
        "enforcement",
        "law",
        "supply"
    ],
    "wof:name":"Badge Co Of NJ",
    "wof:placetype":"venue"
},
  "geometry": {"coordinates":[-74.412026,40.843965],"type":"Point"}
}