{
  "type": "Feature",
  "properties": {
    "addr:full":"450 Getty Ave Clifton NJ 07011",
    "addr:housenumber":"450",
    "addr:postcode":"07011",
    "addr:street":"Getty Ave",
    "iso:country":"US",
    "sg:address":"450 Getty Ave",
    "sg:city":"Clifton",
    "sg:classifiers":[
        {
            "category":"Freight",
            "type":"Transportation"
        }
    ],
    "sg:phone":"+1 973 253 2222",
    "sg:postcode":"07011",
    "sg:province":"NJ",
    "sg:tags":[
        "warehouse"
    ],
    "wof:name":"Clifton Childrens Wear Center",
    "wof:placetype":"venue"
},
  "geometry": {"coordinates":[-74.14922,40.886807],"type":"Point"}
}