{
  "type": "Feature",
  "properties": {
    "addr:full":"21 Sycamore Dr Burlington NJ 08016",
    "addr:housenumber":"21",
    "addr:postcode":"08016",
    "addr:street":"Sycamore Dr",
    "iso:country":"US",
    "sg:address":"21 Sycamore Dr",
    "sg:city":"Burlington",
    "sg:classifiers":[
        {
            "category":"Freight",
            "type":"Transportation"
        }
    ],
    "sg:phone":"+1 609 386 1385",
    "sg:postcode":"08016",
    "sg:province":"NJ",
    "sg:tags":[
        "operator",
        "trucking"
    ],
    "wof:name":"Centre Carriers Acquisition Co",
    "wof:placetype":"venue"
},
  "geometry": {"coordinates":[-74.861048,40.056869],"type":"Point"}
}