{
  "type": "Feature",
  "properties": {
    "iso:country":"US",
    "sg:address":"564 S Broad St",
    "sg:city":"Elizabeth",
    "sg:classifiers":[
        {
            "category":"Restaurant",
            "type":"Food & Drink"
        }
    ],
    "sg:phone":"+1 908 351 4959",
    "sg:postcode":"07202",
    "sg:province":"NJ",
    "wof:name":"Number One Kitchen",
    "wof:placetype":"venue"
},
  "geometry": {"coordinates":[-74.216202,40.6507],"type":"Point"}
}