{
  "type": "Feature",
  "properties": {
    "iso:country":"US",
    "sg:address":"209 1st Ter",
    "sg:city":"Egg Harbor City",
    "sg:classifiers":[
        {
            "category":"Retail",
            "subcategory":"Animal Services",
            "type":"Services"
        }
    ],
    "sg:phone":"+1 609 965 1283",
    "sg:postcode":"08215",
    "sg:province":"NJ",
    "wof:name":"Dapper Dog Grooming Salon",
    "wof:placetype":"venue"
},
  "geometry": {"coordinates":[-74.64944,39.534719],"type":"Point"}
}