{
  "type": "Feature",
  "properties": {
    "iso:country":"US",
    "sg:address":"1 Old Hwy 22",
    "sg:city":"Clinton",
    "sg:classifiers":[
        {
            "category":"Food & Beverages",
            "subcategory":"Bakery",
            "type":"Retail Goods"
        }
    ],
    "sg:phone":"+1 908 730 9070",
    "sg:postcode":"08809",
    "sg:province":"NJ",
    "sg:tags":[
        "bagel"
    ],
    "wof:name":"Bagels & More",
    "wof:placetype":"venue"
},
  "geometry": {"coordinates":[-74.90970299999999,40.636448],"type":"Point"}
}