{
  "type": "Feature",
  "properties": {
    "addr:full":"570 River Rd Fair Haven NJ 07704",
    "addr:housenumber":"570",
    "addr:postcode":"07704",
    "addr:street":"River Rd",
    "iso:country":"US",
    "sg:address":"570 River Rd",
    "sg:city":"Fair Haven",
    "sg:classifiers":[
        {
            "category":"Food & Beverages",
            "subcategory":"Liquor & Beverages",
            "type":"Retail Goods"
        }
    ],
    "sg:phone":"+1   ",
    "sg:postcode":"07704",
    "sg:province":"NJ",
    "sg:tags":[
        "packaged"
    ],
    "wof:name":"Cellar Liquors",
    "wof:placetype":"venue"
},
  "geometry": {"coordinates":[-74.042986,40.360817],"type":"Point"}
}