{
  "type": "Feature",
  "properties": {
    "iso:country":"US",
    "sg:address":"11 Saddle Rd",
    "sg:city":"Cedar Knolls",
    "sg:classifiers":[
        {
            "category":"Health Services",
            "subcategory":"Doctor",
            "type":"Services"
        }
    ],
    "sg:phone":"+1 973 267 2122",
    "sg:postcode":"07927",
    "sg:province":"NJ",
    "sg:tags":[
        "physician",
        "surgeon",
        "cardiologist"
    ],
    "wof:name":"Medical Institute of Nj PC the",
    "wof:placetype":"venue"
},
  "geometry": {"coordinates":[-74.465698,40.816299],"type":"Point"}
}