{
  "type": "Feature",
  "properties": {
    "addr:full":"1401 7th Ave Neptune NJ 07753",
    "addr:housenumber":"1401",
    "addr:postcode":"07753",
    "addr:street":"7Th Ave",
    "iso:country":"US",
    "sg:address":"1401 7th Ave",
    "sg:city":"Neptune",
    "sg:classifiers":[
        {
            "category":"Social Services",
            "type":"Services"
        }
    ],
    "sg:phone":"+1 732 775 1140",
    "sg:postcode":"07753",
    "sg:province":"NJ",
    "sg:tags":[
        "organization",
        "welfare"
    ],
    "wof:name":"Madonna House",
    "wof:placetype":"venue"
},
  "geometry": {"coordinates":[-74.029259,40.205937],"type":"Point"}
}