{
  "type": "Feature",
  "properties": {
    "addr:full":"901 Long Beach Blvd Surf City NJ 08008",
    "addr:housenumber":"901",
    "addr:postcode":"08008",
    "addr:street":"Long Beach Blvd",
    "iso:country":"US",
    "sg:address":"901 Long Beach Blvd",
    "sg:city":"Surf City",
    "sg:classifiers":[
        {
            "category":"Retail",
            "subcategory":"Auto Repair",
            "type":"Services"
        }
    ],
    "sg:phone":"+1 609 494 2520",
    "sg:postcode":"08008",
    "sg:province":"NJ",
    "sg:tags":[
        "muffler",
        "exhaust",
        "system"
    ],
    "wof:name":"Odell's Service Ctr",
    "wof:placetype":"venue"
},
  "geometry": {"coordinates":[-74.17595799999999,39.64926],"type":"Point"}
}