{
  "type": "Feature",
  "properties": {
    "iso:country":"US",
    "sg:address":"223 S Evergreen Ave",
    "sg:city":"Woodbury",
    "sg:classifiers":[
        {
            "category":"Health Services",
            "subcategory":"Doctor",
            "type":"Services"
        }
    ],
    "sg:phone":"+1   ",
    "sg:postcode":"08096",
    "sg:province":"NJ",
    "sg:tags":[
        "medical"
    ],
    "wof:name":"Gerald Vernon Do",
    "wof:placetype":"venue"
},
  "geometry": {"coordinates":[-75.14681299999999,39.830852],"type":"Point"}
}