{
  "type": "Feature",
  "properties": {
    "addr:full":"222 Haddon Ave West Berlin NJ 08091",
    "addr:housenumber":"222",
    "addr:postcode":"08091",
    "addr:street":"Haddon Ave",
    "iso:country":"US",
    "sg:address":"222 Haddon Ave",
    "sg:city":"West Berlin",
    "sg:classifiers":[
        {
            "category":"Restaurant",
            "type":"Food & Drink"
        }
    ],
    "sg:phone":"+1   ",
    "sg:postcode":"08091",
    "sg:province":"NJ",
    "sg:tags":[
        "eating"
    ],
    "wof:name":"Oceanos Restaurant",
    "wof:placetype":"venue"
},
  "geometry": {"coordinates":[-74.944239,39.812777],"type":"Point"}
}