{
  "type": "Feature",
  "properties": {
    "addr:full":"51 Linden St Hackensack NJ 07601",
    "addr:housenumber":"51",
    "addr:postcode":"07601",
    "addr:street":"Linden St",
    "iso:country":"US",
    "sg:address":"51 Linden St",
    "sg:city":"Hackensack",
    "sg:classifiers":[
        {
            "category":"Building & Trades",
            "subcategory":"Locksmith",
            "type":"Services"
        }
    ],
    "sg:phone":"+1 888 287 0988",
    "sg:postcode":"07601",
    "sg:province":"NJ",
    "sg:tags":[
        "key"
    ],
    "wof:name":"A 1 Emergency Locksmith",
    "wof:placetype":"venue"
},
  "geometry": {"coordinates":[-74.044566,40.894689],"type":"Point"}
}