{
  "type": "Feature",
  "properties": {
    "addr:full":"827 Asbury Ave Ocean City NJ 08226",
    "addr:housenumber":"827",
    "addr:postcode":"08226",
    "addr:street":"Asbury Ave",
    "iso:country":"US",
    "sg:address":"827 Asbury Ave",
    "sg:city":"Ocean City",
    "sg:classifiers":[
        {
            "category":"Shopping",
            "subcategory":"Department Store",
            "type":"Retail Goods"
        }
    ],
    "sg:phone":"+1 609 391 0046",
    "sg:postcode":"08226",
    "sg:province":"NJ",
    "wof:name":"B & B Department Stores Inc",
    "wof:placetype":"venue"
},
  "geometry": {"coordinates":[-74.575096,39.279596],"type":"Point"}
}