{
  "type": "Feature",
  "properties": {
    "addr:full":"960 Bergen St Newark NJ 07112",
    "addr:housenumber":"960",
    "addr:postcode":"07112",
    "addr:street":"Bergen St",
    "iso:country":"US",
    "sg:address":"960 Bergen St",
    "sg:city":"Newark",
    "sg:classifiers":[
        {
            "category":"Personal",
            "type":"Services"
        }
    ],
    "sg:phone":"+1 973 923 0028",
    "sg:postcode":"07112",
    "sg:province":"NJ",
    "sg:tags":[
        "miscellaneous"
    ],
    "wof:name":"Personal Beepers",
    "wof:placetype":"venue"
},
  "geometry": {"coordinates":[-74.206097,40.710552],"type":"Point"}
}