{
  "type": "Feature",
  "properties": {
    "addr:full":"26 Fords Rd Randolph NJ 07869",
    "addr:housenumber":"26",
    "addr:postcode":"07869",
    "addr:street":"Fords Rd",
    "iso:country":"US",
    "sg:address":"26 Fords Rd",
    "sg:city":"Randolph",
    "sg:classifiers":[
        {
            "category":"Wholesale",
            "subcategory":"Computers",
            "type":"Manufacturing & Wholesale Goods"
        }
    ],
    "sg:phone":"+1 973 328 7151",
    "sg:postcode":"07869",
    "sg:province":"NJ",
    "sg:tags":[
        "software"
    ],
    "wof:name":"QED Microgroup Inc",
    "wof:placetype":"venue"
},
  "geometry": {"coordinates":[-74.57099599999999,40.860353],"type":"Point"}
}