{
  "type": "Feature",
  "properties": {
    "addr:full":"1781 Springfield Ave Maplewood NJ 07040",
    "addr:housenumber":"1781",
    "addr:postcode":"07040",
    "addr:street":"Springfield Ave",
    "iso:country":"US",
    "sg:address":"1781 Springfield Ave",
    "sg:city":"Maplewood",
    "sg:classifiers":[
        {
            "category":"Real Estate",
            "subcategory":"Real Estate Agent",
            "type":"Services"
        }
    ],
    "sg:phone":"+1 973 761 6022",
    "sg:postcode":"07040",
    "sg:province":"NJ",
    "sg:tags":[
        "management"
    ],
    "wof:name":"Yellow Rose Management LLC",
    "wof:placetype":"venue"
},
  "geometry": {"coordinates":[-74.261771,40.721796],"type":"Point"}
}