{
  "type": "Feature",
  "properties": {
    "addr:full":"1 Katherine St Little Ferry NJ 07643",
    "addr:housenumber":"1",
    "addr:postcode":"07643",
    "addr:street":"Katherine St",
    "iso:country":"US",
    "sg:address":"1 Katherine St",
    "sg:city":"Little Ferry",
    "sg:classifiers":[
        {
            "category":"Professional",
            "subcategory":"Management & Consulting",
            "type":"Services"
        }
    ],
    "sg:phone":"+1 201 641 1299",
    "sg:postcode":"07643",
    "sg:province":"NJ",
    "sg:tags":[
        "construction"
    ],
    "wof:name":"ATICM Group LLC",
    "wof:placetype":"venue"
},
  "geometry": {"coordinates":[-74.040605,40.847952],"type":"Point"}
}