{
  "type": "Feature",
  "properties": {
    "addr:full":"255 E Pearl St Burlington NJ 08016",
    "addr:housenumber":"255",
    "addr:postcode":"08016",
    "addr:street":"E Pearl St",
    "iso:country":"US",
    "sg:address":"255 E Pearl St",
    "sg:city":"Burlington",
    "sg:classifiers":[
        {
            "category":"Real Estate",
            "subcategory":"Real Estate Operator",
            "type":"Services"
        }
    ],
    "sg:phone":"+1 609 387 3184",
    "sg:postcode":"08016",
    "sg:province":"NJ",
    "sg:tags":[
        "building",
        "apartment"
    ],
    "wof:name":"Burlington Manor Apartments",
    "wof:placetype":"venue"
},
  "geometry": {"coordinates":[-74.854401,40.081402],"type":"Point"}
}