{
  "type": "Feature",
  "properties": {
    "addr:full":"7 Haven Hill Rise Flemington NJ 08822",
    "addr:housenumber":"7",
    "addr:postcode":"08822",
    "addr:street":"Haven Hill Rise",
    "iso:country":"US",
    "sg:address":"7 Haven Hill Rise",
    "sg:city":"Flemington",
    "sg:classifiers":[
        {
            "category":"Professional",
            "type":"Services"
        }
    ],
    "sg:phone":"+1 908 788 2820",
    "sg:postcode":"08822",
    "sg:province":"NJ",
    "sg:tags":[
        "establishment"
    ],
    "wof:name":"Res",
    "wof:placetype":"venue"
},
  "geometry": {"coordinates":[-74.888902,40.528613],"type":"Point"}
}