{
  "type": "Feature",
  "properties": {
    "addr:full":"306 Lincoln St Phillipsburg NJ 08865",
    "addr:housenumber":"306",
    "addr:postcode":"08865",
    "addr:street":"Lincoln St",
    "iso:country":"US",
    "sg:address":"306 Lincoln St",
    "sg:city":"Phillipsburg",
    "sg:classifiers":[
        {
            "category":"Professional",
            "subcategory":"Business Services",
            "type":"Services"
        }
    ],
    "sg:phone":"+1   ",
    "sg:postcode":"08865",
    "sg:province":"NJ",
    "sg:tags":[
        "printing",
        "copying"
    ],
    "wof:name":"Emmanuels Variety Store",
    "wof:placetype":"venue"
},
  "geometry": {"coordinates":[-75.185846,40.695405],"type":"Point"}
}