{
  "type": "Feature",
  "properties": {
    "addr:full":"385 Lakeview Ave Clifton NJ 07011",
    "addr:housenumber":"385",
    "addr:postcode":"07011",
    "addr:street":"Lakeview Ave",
    "iso:country":"US",
    "sg:address":"385 Lakeview Ave",
    "sg:city":"Clifton",
    "sg:classifiers":[
        {
            "category":"Banks & Credit Unions",
            "subcategory":"Bank",
            "type":"Services"
        }
    ],
    "sg:phone":"+1 973 772 3838",
    "sg:postcode":"07011",
    "sg:province":"NJ",
    "sg:tags":[
        "cashing",
        "check"
    ],
    "wof:name":"C Check Cashing",
    "wof:placetype":"venue"
},
  "geometry": {"coordinates":[-74.138897,40.888541],"type":"Point"}
}