{
  "type": "Feature",
  "properties": {
    "addr:full":"77 W 24th St Bayonne NJ 07002",
    "addr:housenumber":"77",
    "addr:postcode":"07002",
    "addr:street":"W 24Th St",
    "iso:country":"US",
    "sg:address":"77 W 24th St",
    "sg:city":"Bayonne",
    "sg:classifiers":[
        {
            "category":"Building & Trades",
            "subcategory":"Locksmith",
            "type":"Services"
        }
    ],
    "sg:phone":"+1 201 215 6811",
    "sg:postcode":"07002",
    "sg:province":"NJ",
    "sg:tags":[
        "key"
    ],
    "wof:name":"24 Hour Locksmith",
    "wof:placetype":"venue"
},
  "geometry": {"coordinates":[-74.120907,40.666595],"type":"Point"}
}