{
  "type": "Feature",
  "properties": {
    "addr:full":"620 Pavonia Ave Jersey City NJ 07306",
    "addr:housenumber":"620",
    "addr:postcode":"07306",
    "addr:street":"Pavonia Ave",
    "iso:country":"US",
    "sg:address":"620 Pavonia Ave",
    "sg:city":"Jersey City",
    "sg:classifiers":[
        {
            "category":"Communications",
            "subcategory":"News Services",
            "type":"Services"
        }
    ],
    "sg:phone":"+1 201 418 0462",
    "sg:postcode":"07306",
    "sg:province":"NJ",
    "sg:tags":[
        "newspaper",
        "photo",
        "agency",
        "for"
    ],
    "wof:name":"Snaps India Inc",
    "wof:placetype":"venue"
},
  "geometry": {"coordinates":[-74.062831,40.73305],"type":"Point"}
}