{
  "type": "Feature",
  "properties": {
    "addr:full":"133 Bridgeton Dr Parsippany NJ 07054",
    "addr:housenumber":"133",
    "addr:postcode":"07054",
    "addr:street":"Bridgeton Dr",
    "iso:country":"US",
    "sg:address":"133 Bridgeton Dr",
    "sg:city":"Parsippany",
    "sg:classifiers":[
        {
            "category":"Restaurant",
            "type":"Food & Drink"
        }
    ],
    "sg:phone":"+1 856 223 8633",
    "sg:postcode":"07054",
    "sg:province":"NJ",
    "sg:website":"www.mcdonalds.com",
    "wof:name":"Mc Donald's",
    "wof:placetype":"venue"
},
  "geometry": {"coordinates":[-74.440963,40.856177],"type":"Point"}
}