{
  "type": "Feature",
  "properties": {
    "iso:country":"US",
    "sg:address":"11 Lloyd Rd",
    "sg:city":"Ho Ho Kus",
    "sg:classifiers":[
        {
            "category":"Manufacturing",
            "subcategory":"Printing",
            "type":"Manufacturing & Wholesale Goods"
        }
    ],
    "sg:phone":"+1 201 251 9122",
    "sg:postcode":"07423",
    "sg:province":"NJ",
    "sg:tags":[
        "advertising",
        "sales",
        "publishing"
    ],
    "wof:name":"Moran Media Group LLC",
    "wof:placetype":"venue"
},
  "geometry": {"coordinates":[-74.103942,41.00134],"type":"Point"}
}