{
  "type": "Feature",
  "properties": {
    "iso:country":"US",
    "sg:address":"101 Mount Ephraim Ave",
    "sg:city":"Mt Ephraim",
    "sg:classifiers":[
        {
            "category":"Restaurant",
            "type":"Food & Drink"
        }
    ],
    "sg:phone":"+1 856 933 5220",
    "sg:postcode":"08059",
    "sg:province":"NJ",
    "sg:tags":[
        "delicatessen"
    ],
    "wof:name":"Codi's Corner LLC",
    "wof:placetype":"venue"
},
  "geometry": {"coordinates":[-75.088855,39.880319],"type":"Point"}
}