{
  "type": "Feature",
  "properties": {
    "iso:country":"US",
    "sg:address":"68 Alexander Ave",
    "sg:city":"Trenton",
    "sg:classifiers":[
        {
            "category":"Professional",
            "type":"Services"
        }
    ],
    "sg:phone":"+1 609 586 6841",
    "sg:postcode":"08619",
    "sg:province":"NJ",
    "sg:tags":[
        "establishment"
    ],
    "wof:name":"Tender Hearts",
    "wof:placetype":"venue"
},
  "geometry": {"coordinates":[-74.688962,40.250616],"type":"Point"}
}