{
  "type": "Feature",
  "properties": {
    "iso:country":"US",
    "sg:address":"2 Broad St",
    "sg:city":"Freehold",
    "sg:classifiers":[
        {
            "category":"Insurance",
            "subcategory":"Hazard Insurance",
            "type":"Services"
        },
        {
            "category":"Professional",
            "subcategory":"Business Services",
            "type":"Services"
        }
    ],
    "sg:phone":"+1 732 761 2297",
    "sg:postcode":"07728",
    "sg:province":"NJ",
    "sg:tags":[
        "bond"
    ],
    "wof:name":"You'Re Out Bail Bonds",
    "wof:placetype":"venue"
},
  "geometry": {"coordinates":[-74.277384,40.260282],"type":"Point"}
}