{
  "type": "Feature",
  "properties": {
    "iso:country":"US",
    "sg:address":"6 6th St",
    "sg:city":"Englewood Cliffs",
    "sg:classifiers":[
        {
            "category":"Professional",
            "subcategory":"Business Services",
            "type":"Services"
        }
    ],
    "sg:phone":"+1   ",
    "sg:postcode":"07632",
    "sg:province":"NJ",
    "wof:name":"Insite Media Group",
    "wof:placetype":"venue"
},
  "geometry": {"coordinates":[-73.957745,40.866193],"type":"Point"}
}