{
  "type": "Feature",
  "properties": {
    "addr:full":"593 Ocean Ave Jersey City NJ 07305",
    "addr:housenumber":"593",
    "addr:postcode":"07305",
    "addr:street":"Ocean Ave",
    "iso:country":"US",
    "sg:address":"593 Ocean Ave",
    "sg:city":"Jersey City",
    "sg:classifiers":[
        {
            "category":"Professional",
            "type":"Services"
        }
    ],
    "sg:phone":"+1 201 200 9881",
    "sg:postcode":"07305",
    "sg:province":"NJ",
    "sg:tags":[
        "establishment"
    ],
    "wof:name":"Pigott Stuartlyn",
    "wof:placetype":"venue"
},
  "geometry": {"coordinates":[-74.07791,40.706944],"type":"Point"}
}