{
  "type": "Feature",
  "properties": {
    "iso:country":"US",
    "sg:address":"530 E 6th Ave",
    "sg:city":"Roselle",
    "sg:classifiers":[
        {
            "category":"Building & Trades",
            "subcategory":"Cleaning & Sanitation",
            "type":"Services"
        }
    ],
    "sg:phone":"+1   ",
    "sg:postcode":"07203",
    "sg:province":"NJ",
    "sg:tags":[
        "maintenance"
    ],
    "wof:name":"FA Cleaning Services",
    "wof:placetype":"venue"
},
  "geometry": {"coordinates":[-74.248966,40.655561],"type":"Point"}
}