{
  "type": "Feature",
  "properties": {
    "addr:full":"2110 Surf Ave North Wildwood NJ 08260",
    "addr:housenumber":"2110",
    "addr:postcode":"08260",
    "addr:street":"Surf Ave North",
    "iso:country":"US",
    "sg:address":"2110 Surf Ave",
    "sg:city":"North Wildwood",
    "sg:classifiers":[
        {
            "category":"Travel",
            "subcategory":"Hotels & Motels",
            "type":"Entertainment"
        }
    ],
    "sg:phone":"+1 609 522 0295",
    "sg:postcode":"08260",
    "sg:province":"NJ",
    "wof:name":"Lisa's Family Motel",
    "wof:placetype":"venue"
},
  "geometry": {"coordinates":[-74.802325,38.993628],"type":"Point"}
}