{
  "type": "Feature",
  "properties": {
    "iso:country":"US",
    "sg:address":"151 Park Ave",
    "sg:city":"Rutherford",
    "sg:classifiers":[
        {
            "category":"Retail",
            "subcategory":"Portrait Studio",
            "type":"Services"
        }
    ],
    "sg:phone":"+1 201 935 8096",
    "sg:postcode":"07070",
    "sg:province":"NJ",
    "sg:tags":[
        "photography",
        "store"
    ],
    "wof:name":"Captured Moments & Design Studio",
    "wof:placetype":"venue"
},
  "geometry": {"coordinates":[-74.108987,40.825169],"type":"Point"}
}