{
  "type": "Feature",
  "properties": {
    "iso:country":"US",
    "sg:address":"1944 Broadway Tpke",
    "sg:city":"Camden",
    "sg:classifiers":[
        {
            "category":"Organizations",
            "subcategory":"Community Association",
            "type":"Services"
        }
    ],
    "sg:phone":"+1 856 365 1533",
    "sg:postcode":"08104",
    "sg:province":"NJ",
    "sg:tags":[
        "military"
    ],
    "wof:name":"American Legion",
    "wof:placetype":"venue"
},
  "geometry": {"coordinates":[-75.11966700000001,39.919757],"type":"Point"}
}