{
  "type": "Feature",
  "properties": {
    "iso:country":"US",
    "sg:address":"93 Paulin Blvd",
    "sg:city":"Leonia",
    "sg:classifiers":[
        {
            "category":"Professional",
            "type":"Services"
        }
    ],
    "sg:phone":"+1   ",
    "sg:postcode":"07605",
    "sg:province":"NJ",
    "sg:website":"www.divacommunications.com",
    "wof:name":"Diva Communications Inc",
    "wof:placetype":"venue"
},
  "geometry": {"coordinates":[-73.98648300000001,40.857289],"type":"Point"}
}