{
  "type": "Feature",
  "properties": {
    "addr:full":"6 Park Ave Rutherford NJ 07070",
    "addr:housenumber":"6",
    "addr:postcode":"07070",
    "addr:street":"Park Ave",
    "iso:country":"US",
    "sg:address":"6 Park Ave",
    "sg:city":"Rutherford",
    "sg:classifiers":[
        {
            "category":"Communications",
            "subcategory":"Newspaper",
            "type":"Services"
        }
    ],
    "sg:phone":"+1 201 935 0759",
    "sg:postcode":"07070",
    "sg:province":"NJ",
    "sg:tags":[
        "magazine"
    ],
    "wof:name":"Leprechaun News",
    "wof:placetype":"venue"
},
  "geometry": {"coordinates":[-74.10140199999999,40.828499],"type":"Point"}
}