{
  "type": "Feature",
  "properties": {
    "addr:full":"850 Newark Tpke Kearny NJ 07032",
    "addr:housenumber":"850",
    "addr:postcode":"07032",
    "addr:street":"Newark Tpke",
    "iso:country":"US",
    "sg:address":"850 Newark Tpke",
    "sg:city":"Kearny",
    "sg:classifiers":[
        {
            "category":"Government",
            "subcategory":"Post Office",
            "type":"Public Place"
        }
    ],
    "sg:phone":"+1 201 955 9798",
    "sg:postcode":"07032",
    "sg:province":"NJ",
    "sg:tags":[
        "postal",
        "us"
    ],
    "wof:name":"US Post Office",
    "wof:placetype":"venue"
},
  "geometry": {"coordinates":[-74.12577400000001,40.750395],"type":"Point"}
}