{
  "type": "Feature",
  "properties": {
    "iso:country":"US",
    "sg:address":"136 Robinson Pl",
    "sg:city":"Shrewsbury",
    "sg:classifiers":[
        {
            "category":"Banks & Credit Unions",
            "subcategory":"Bank",
            "type":"Services"
        }
    ],
    "sg:phone":"+1 732 758 1200",
    "sg:postcode":"07702",
    "sg:province":"NJ",
    "sg:tags":[
        "loan",
        "real estate"
    ],
    "wof:name":"Superior Mortgage",
    "wof:placetype":"venue"
},
  "geometry": {"coordinates":[-74.056383,40.330609],"type":"Point"}
}