{
  "type": "Feature",
  "properties": {
    "addr:full":"4 Wayside Ln Lebanon NJ 08833",
    "addr:housenumber":"4",
    "addr:postcode":"08833",
    "addr:street":"Wayside Ln",
    "iso:country":"US",
    "sg:address":"4 Wayside Ln",
    "sg:city":"Lebanon",
    "sg:classifiers":[
        {
            "category":"Professional",
            "type":"Services"
        }
    ],
    "sg:phone":"+1   ",
    "sg:postcode":"08833",
    "sg:province":"NJ",
    "wof:name":"Venice Avenue Community",
    "wof:placetype":"venue"
},
  "geometry": {"coordinates":[-74.798982,40.647118],"type":"Point"}
}