{
  "type": "Feature",
  "properties": {
    "iso:country":"US",
    "sg:address":"4 S Main St",
    "sg:city":"Woodstown",
    "sg:classifiers":[
        {
            "category":"Food & Beverages",
            "subcategory":"Specialty",
            "type":"Retail Goods"
        }
    ],
    "sg:phone":"+1 856 769 4429",
    "sg:postcode":"08098",
    "sg:province":"NJ",
    "sg:tags":[
        "tea",
        "coffee"
    ],
    "wof:name":"White Rabbit Tea Co",
    "wof:placetype":"venue"
},
  "geometry": {"coordinates":[-75.32803199999999,39.651383],"type":"Point"}
}