{
  "type": "Feature",
  "properties": {
    "iso:country":"US",
    "sg:address":"3 Webster Ave",
    "sg:city":"Jersey City",
    "sg:classifiers":[
        {
            "category":"Health Services",
            "subcategory":"Doctor",
            "type":"Services"
        }
    ],
    "sg:phone":"+1 201 216 1505",
    "sg:postcode":"07307",
    "sg:province":"NJ",
    "sg:tags":[
        "physician",
        "surgeon"
    ],
    "wof:name":"James G Sanderson DO",
    "wof:placetype":"venue"
},
  "geometry": {"coordinates":[-74.050077,40.738981],"type":"Point"}
}