{
  "type": "Feature",
  "properties": {
    "addr:full":"57 Broadway Newark NJ 07104",
    "addr:housenumber":"57",
    "addr:postcode":"07104",
    "addr:street":"Broadway",
    "iso:country":"US",
    "sg:address":"57 Broadway",
    "sg:city":"Newark",
    "sg:classifiers":[
        {
            "category":"Health Services",
            "subcategory":"Optometrist",
            "type":"Services"
        }
    ],
    "sg:phone":"+1 973 268 2565",
    "sg:postcode":"07104",
    "sg:province":"NJ",
    "wof:name":"Broadway Vision Services Inc",
    "wof:placetype":"venue"
},
  "geometry": {"coordinates":[-74.17064999999999,40.752058],"type":"Point"}
}