{
  "type": "Feature",
  "properties": {
    "iso:country":"US",
    "sg:address":"761 Palmer Ave",
    "sg:city":"Holmdel",
    "sg:classifiers":[
        {
            "category":"Restaurant",
            "type":"Food & Drink"
        }
    ],
    "sg:phone":"+1   ",
    "sg:postcode":"07733",
    "sg:province":"NJ",
    "sg:tags":[
        "eating"
    ],
    "wof:name":"Eating Behavior Consultants",
    "wof:placetype":"venue"
},
  "geometry": {"coordinates":[-74.13393499999999,40.42319],"type":"Point"}
}