{
  "type": "Feature",
  "properties": {
    "iso:country":"US",
    "sg:address":"584 Quinton Rd",
    "sg:city":"Salem",
    "sg:classifiers":[
        {
            "category":"Shopping",
            "subcategory":"Clothing, Apparel, & Fashions",
            "type":"Retail Goods"
        }
    ],
    "sg:phone":"+1 856 935 0926",
    "sg:postcode":"08079",
    "sg:province":"NJ",
    "sg:tags":[
        "work",
        "footwear",
        "clothes"
    ],
    "wof:name":"C and L Work Clothes",
    "wof:placetype":"venue"
},
  "geometry": {"coordinates":[-75.44757,39.559866],"type":"Point"}
}