{
  "type": "Feature",
  "properties": {
    "addr:full":"141 Union St Newark NJ 07105",
    "addr:housenumber":"141",
    "addr:postcode":"07105",
    "addr:street":"Union St",
    "iso:country":"US",
    "sg:address":"141 Union St",
    "sg:city":"Newark",
    "sg:classifiers":[
        {
            "category":"Organizations",
            "subcategory":"Religious Organization",
            "type":"Services"
        }
    ],
    "sg:phone":"+1   ",
    "sg:postcode":"07105",
    "sg:province":"NJ",
    "wof:name":"Providnce Mssnary Bptst Church",
    "wof:placetype":"venue"
},
  "geometry": {"coordinates":[-74.166062,40.728652],"type":"Point"}
}