{
  "type": "Feature",
  "properties": {
    "iso:country":"US",
    "sg:address":"10 Leigh St",
    "sg:city":"Clinton",
    "sg:classifiers":[
        {
            "category":"Food & Beverages",
            "subcategory":"Bakery",
            "type":"Retail Goods"
        }
    ],
    "sg:phone":"+1   ",
    "sg:postcode":"08809",
    "sg:province":"NJ",
    "wof:name":"Clinton Bakery",
    "wof:placetype":"venue"
},
  "geometry": {"coordinates":[-74.910631,40.637418],"type":"Point"}
}