{
  "type": "Feature",
  "properties": {
    "addr:full":"7 Smith Paterson NJ 07510",
    "addr:housenumber":"7",
    "addr:postcode":"07510",
    "addr:street":"Smith",
    "iso:country":"US",
    "sg:address":"7 Smith",
    "sg:city":"Paterson",
    "sg:classifiers":[
        {
            "category":"Bakery",
            "type":"Food & Drink"
        }
    ],
    "sg:phone":"+1 973 279 5629",
    "sg:postcode":"07510",
    "sg:province":"NJ",
    "sg:website":"www.dunkindonuts.com",
    "wof:name":"Dunkin Donuts",
    "wof:placetype":"venue"
},
  "geometry": {"coordinates":[-74.167603,40.9147],"type":"Point"}
}