{
  "type": "Feature",
  "properties": {
    "addr:full":"301 79th St North Bergen NJ 07047",
    "addr:housenumber":"301",
    "addr:postcode":"07047",
    "addr:street":"79Th St",
    "iso:country":"US",
    "sg:address":"301 79th St",
    "sg:city":"North Bergen",
    "sg:classifiers":[
        {
            "category":"Building & Trades",
            "subcategory":"Cleaning & Sanitation",
            "type":"Services"
        }
    ],
    "sg:phone":"+1 201 868 0990",
    "sg:postcode":"07047",
    "sg:province":"NJ",
    "sg:tags":[
        "janitor"
    ],
    "wof:name":"Clean Tech Inc",
    "wof:placetype":"venue"
},
  "geometry": {"coordinates":[-74.004721,40.800568],"type":"Point"}
}