{
  "type": "Feature",
  "properties": {
    "addr:full":"25 Ocean Pathway Ocean Grove NJ 07756",
    "addr:housenumber":"25",
    "addr:postcode":"07756",
    "addr:street":"Ocean Pathway",
    "iso:country":"US",
    "sg:address":"25 Ocean Pathway",
    "sg:city":"Ocean Grove",
    "sg:classifiers":[
        {
            "category":"Restaurant",
            "type":"Food & Drink"
        }
    ],
    "sg:phone":"+1   ",
    "sg:postcode":"07756",
    "sg:province":"NJ",
    "sg:tags":[
        "eating"
    ],
    "wof:name":"Secret Garden Restaurant",
    "wof:placetype":"venue"
},
  "geometry": {"coordinates":[-74.00510199999999,40.213665],"type":"Point"}
}