{
  "type": "Feature",
  "properties": {
    "addr:full":"7815 Bergenline Ave North Bergen NJ 07047",
    "addr:housenumber":"7815",
    "addr:postcode":"07047",
    "addr:street":"Bergenline Ave",
    "iso:country":"US",
    "sg:address":"7815 Bergenline Ave",
    "sg:city":"North Bergen",
    "sg:classifiers":[
        {
            "category":"Building & Trades",
            "subcategory":"Locksmith",
            "type":"Services"
        }
    ],
    "sg:phone":"+1 888 350 1472",
    "sg:postcode":"07047",
    "sg:province":"NJ",
    "sg:tags":[
        "key"
    ],
    "wof:name":"A 1 Emergency Locksmith",
    "wof:placetype":"venue"
},
  "geometry": {"coordinates":[-74.007099,40.801342],"type":"Point"}
}