{
  "type": "Feature",
  "properties": {
    "addr:full":"570 Kemah Lake Rd Newton NJ 07860",
    "addr:housenumber":"570",
    "addr:postcode":"07860",
    "addr:street":"Kemah Lake Rd",
    "iso:country":"US",
    "sg:address":"570 Kemah Lake Rd",
    "sg:city":"Newton",
    "sg:classifiers":[
        {
            "category":"Wholesale",
            "subcategory":"Machinery & Supplies",
            "type":"Manufacturing & Wholesale Goods"
        }
    ],
    "sg:phone":"+1 973 948 5155",
    "sg:postcode":"07860",
    "sg:province":"NJ",
    "sg:tags":[
        "industrial"
    ],
    "wof:name":"Special Diamond Products",
    "wof:placetype":"venue"
},
  "geometry": {"coordinates":[-74.77198,41.137943],"type":"Point"}
}