{
  "type": "Feature",
  "properties": {
    "addr:full":"2801 John F Kennedy Blvd Jersey City NJ 07306",
    "addr:housenumber":"2801",
    "addr:postcode":"07306",
    "addr:street":"John F Kennedy Blvd",
    "iso:country":"US",
    "sg:address":"2801 John F Kennedy Blvd",
    "sg:city":"Jersey City",
    "sg:classifiers":[
        {
            "category":"Food & Beverages",
            "subcategory":"Bakery",
            "type":"Retail Goods"
        }
    ],
    "sg:phone":"+1 201 656 4888",
    "sg:postcode":"07306",
    "sg:province":"NJ",
    "sg:tags":[
        "baker"
    ],
    "wof:name":"Karen Bakery",
    "wof:placetype":"venue"
},
  "geometry": {"coordinates":[-74.067802,40.731499],"type":"Point"}
}