{
  "type": "Feature",
  "properties": {
    "addr:full":"372 Park Ave Weehawken NJ 07086",
    "addr:housenumber":"372",
    "addr:postcode":"07086",
    "addr:street":"Park Ave",
    "iso:country":"US",
    "sg:address":"372 Park Ave",
    "sg:city":"Weehawken",
    "sg:classifiers":[
        {
            "category":"Home & Garden",
            "subcategory":"Kitchen Supply",
            "type":"Retail Goods"
        }
    ],
    "sg:phone":"+1 201 348 9232",
    "sg:postcode":"07086",
    "sg:province":"NJ",
    "sg:tags":[
        "concession",
        "concessionaire"
    ],
    "wof:name":"Weehawken Stadium Concession S",
    "wof:placetype":"venue"
},
  "geometry": {"coordinates":[-74.024232,40.765193],"type":"Point"}
}