{
  "type": "Feature",
  "properties": {
    "addr:full":"588 Morrow St Orange NJ 07050",
    "addr:housenumber":"588",
    "addr:postcode":"07050",
    "addr:street":"Morrow St",
    "iso:country":"US",
    "sg:address":"588 Morrow St",
    "sg:city":"Orange",
    "sg:classifiers":[
        {
            "category":"Building & Trades",
            "subcategory":"Construction",
            "type":"Services"
        }
    ],
    "sg:phone":"+1 973 672 9100",
    "sg:postcode":"07050",
    "sg:province":"NJ",
    "wof:name":"V Viola General Contracting",
    "wof:placetype":"venue"
},
  "geometry": {"coordinates":[-74.24813,40.764083],"type":"Point"}
}