{
  "type": "Feature",
  "properties": {
    "iso:country":"US",
    "sg:address":"73 Eagle Rock Ave",
    "sg:city":"East Hanover",
    "sg:classifiers":[
        {
            "category":"Personal",
            "type":"Services"
        }
    ],
    "sg:phone":"+1 973 386 9866",
    "sg:postcode":"07936",
    "sg:province":"NJ",
    "sg:tags":[
        "towing"
    ],
    "wof:name":"C & L Auto Body",
    "wof:placetype":"venue"
},
  "geometry": {"coordinates":[-74.34079699999999,40.832001],"type":"Point"}
}