{
  "type": "Feature",
  "properties": {
    "addr:full":"238 Delaware St Woodbury NJ 08096",
    "addr:housenumber":"238",
    "addr:postcode":"08096",
    "addr:street":"Delaware St",
    "iso:country":"US",
    "sg:address":"238 Delaware St",
    "sg:city":"Woodbury",
    "sg:classifiers":[
        {
            "category":"Professional",
            "subcategory":"Business Services",
            "type":"Services"
        }
    ],
    "sg:phone":"+1   ",
    "sg:postcode":"08096",
    "sg:province":"NJ",
    "wof:name":"LInteriors",
    "wof:placetype":"venue"
},
  "geometry": {"coordinates":[-75.16100299999999,39.840459],"type":"Point"}
}