{
  "type": "Feature",
  "properties": {
    "iso:country":"US",
    "sg:address":"422 Allen Ave",
    "sg:city":"Gibbstown",
    "sg:classifiers":[
        {
            "category":"Wholesale",
            "subcategory":"Home Furnishings",
            "type":"Manufacturing & Wholesale Goods"
        }
    ],
    "sg:phone":"+1 856 423 0666",
    "sg:postcode":"08027",
    "sg:province":"NJ",
    "sg:tags":[
        "draperies",
        "shades-wholesale",
        "curtain",
        "manufacturer"
    ],
    "wof:name":"Curtainrod Store",
    "wof:placetype":"venue"
},
  "geometry": {"coordinates":[-75.28873400000001,39.824705],"type":"Point"}
}