{
  "type": "Feature",
  "properties": {
    "addr:full":"33 Mount Vernon Rd Columbia NJ 07832",
    "addr:housenumber":"33",
    "addr:postcode":"07832",
    "addr:street":"Mount Vernon Rd",
    "iso:country":"US",
    "sg:address":"33 Mount Vernon Rd",
    "sg:city":"Columbia",
    "sg:classifiers":[
        {
            "category":"Building & Trades",
            "subcategory":"Construction",
            "type":"Services"
        }
    ],
    "sg:phone":"+1 908 362 5978",
    "sg:postcode":"07832",
    "sg:province":"NJ",
    "sg:tags":[
        "hanging",
        "contractor"
    ],
    "wof:name":"Welsh Painting & Designs Co",
    "wof:placetype":"venue"
},
  "geometry": {"coordinates":[-75.01033099999999,40.987393],"type":"Point"}
}