{
  "type": "Feature",
  "properties": {
    "addr:full":"402 E State St Trenton NJ 08608",
    "addr:housenumber":"402",
    "addr:postcode":"08608",
    "addr:street":"E State St",
    "iso:country":"US",
    "sg:address":"402 E State St",
    "sg:city":"Trenton",
    "sg:classifiers":[
        {
            "category":"Professional",
            "subcategory":"Secretarial Services",
            "type":"Services"
        }
    ],
    "sg:phone":"+1 609 695 0535",
    "sg:postcode":"08608",
    "sg:province":"NJ",
    "sg:tags":[
        "convention",
        "court",
        "reporter"
    ],
    "wof:name":"Lynne Johnson",
    "wof:placetype":"venue"
},
  "geometry": {"coordinates":[-74.757103,40.220974],"type":"Point"}
}