{
  "type": "Feature",
  "properties": {
    "addr:full":"865 Boulevard E Weehawken NJ 07086",
    "addr:housenumber":"865;e",
    "addr:postcode":"07086",
    "addr:street":"Boulevard",
    "iso:country":"US",
    "sg:address":"865 Boulevard E",
    "sg:city":"Weehawken",
    "sg:classifiers":[
        {
            "category":"Health Services",
            "subcategory":"Doctor",
            "type":"Services"
        }
    ],
    "sg:phone":"+1 201 865 4487",
    "sg:postcode":"07086",
    "sg:province":"NJ",
    "wof:name":"Massa Thos P PA",
    "wof:placetype":"venue"
},
  "geometry": {"coordinates":[-74.015198,40.774101],"type":"Point"}
}