{
  "type": "Feature",
  "properties": {
    "addr:full":"511 W Oak Ave North Wildwood NJ 08260",
    "addr:housenumber":"511",
    "addr:postcode":"08260",
    "addr:street":"W Oak Ave North",
    "iso:country":"US",
    "sg:address":"511 W Oak Ave",
    "sg:city":"North Wildwood",
    "sg:classifiers":[
        {
            "category":"Building & Trades",
            "subcategory":"Construction",
            "type":"Services"
        }
    ],
    "sg:phone":"+1 609 522 4646",
    "sg:postcode":"08260",
    "sg:province":"NJ",
    "sg:tags":[
        "marking",
        "maintenance",
        "parking"
    ],
    "wof:name":"North Wildwood Public Works",
    "wof:placetype":"venue"
},
  "geometry": {"coordinates":[-74.820514,38.994969],"type":"Point"}
}