{
  "type": "Feature",
  "properties": {
    "iso:country":"US",
    "sg:address":"822 US-22",
    "sg:city":"Somerville",
    "sg:classifiers":[
        {
            "category":"Ice Cream",
            "type":"Food & Drink"
        }
    ],
    "sg:menulink":"http://www.allmenus.com/nj/somerville/99246-friendlys/menu/",
    "sg:phone":"+1 908 203 1006",
    "sg:postcode":"08876",
    "sg:province":"NJ",
    "sg:tags":[
        "burger",
        "american"
    ],
    "wof:name":"Friendly's",
    "wof:placetype":"venue"
},
  "geometry": {"coordinates":[-74.61464100000001,40.581147],"type":"Point"}
}