{
  "type": "Feature",
  "properties": {
    "iso:country":"US",
    "sg:address":"380 North St",
    "sg:city":"Teterboro",
    "sg:classifiers":[
        {
            "category":"Real Estate",
            "subcategory":"Real Estate Operator",
            "type":"Services"
        }
    ],
    "sg:phone":"+1   ",
    "sg:postcode":"07608",
    "sg:province":"NJ",
    "sg:tags":[
        "manager",
        "property",
        "commercial"
    ],
    "wof:name":"Alta Industries",
    "wof:placetype":"venue"
},
  "geometry": {"coordinates":[-74.057722,40.867306],"type":"Point"}
}