{
  "type": "Feature",
  "properties": {
    "iso:country":"US",
    "sg:address":"45 Central Ave",
    "sg:city":"Tenafly",
    "sg:classifiers":[
        {
            "category":"Real Estate",
            "subcategory":"Real Estate Agent",
            "type":"Services"
        }
    ],
    "sg:phone":"+1 201 871 1444",
    "sg:postcode":"07670",
    "sg:province":"NJ",
    "wof:name":"Keystone Realty",
    "wof:placetype":"venue"
},
  "geometry": {"coordinates":[-73.964392,40.928771],"type":"Point"}
}