{
  "type": "Feature",
  "properties": {
    "addr:full":"50 Elmwood Ave Irvington NJ 07111",
    "addr:housenumber":"50",
    "addr:postcode":"07111",
    "addr:street":"Elmwood Ave",
    "iso:country":"US",
    "sg:address":"50 Elmwood Ave",
    "sg:city":"Irvington",
    "sg:classifiers":[
        {
            "category":"Professional",
            "subcategory":"Accounting & Tax Preparation",
            "type":"Services"
        }
    ],
    "sg:phone":"+1 973 373 8990",
    "sg:postcode":"07111",
    "sg:province":"NJ",
    "sg:tags":[
        "return",
        "filing"
    ],
    "wof:name":"Williams Refund & Recovery",
    "wof:placetype":"venue"
},
  "geometry": {"coordinates":[-74.239632,40.72556],"type":"Point"}
}