{
  "type": "Feature",
  "properties": {
    "iso:country":"US",
    "sg:address":"151 E 33rd St",
    "sg:city":"Paterson",
    "sg:classifiers":[
        {
            "category":"Organizations",
            "subcategory":"Religious Organization",
            "type":"Services"
        }
    ],
    "sg:phone":"+1 973 684 5565",
    "sg:postcode":"07514",
    "sg:province":"NJ",
    "sg:tags":[
        "synagogue"
    ],
    "sg:website":"www.templeemanuelnj.org",
    "wof:name":"Temple Emanuel of North Jersey",
    "wof:placetype":"venue"
},
  "geometry": {"coordinates":[-74.14160200000001,40.918598],"type":"Point"}
}