{
  "type": "Feature",
  "properties": {
    "iso:country":"US",
    "sg:address":"84 E Ridgewood Ave",
    "sg:city":"Ridgewood",
    "sg:classifiers":[
        {
            "category":"Banks & Credit Unions",
            "subcategory":"Bank",
            "type":"Services"
        }
    ],
    "sg:phone":"+1 201 652 3905",
    "sg:postcode":"07450",
    "sg:province":"NJ",
    "wof:name":"Chemical Private Banking",
    "wof:placetype":"venue"
},
  "geometry": {"coordinates":[-74.11874,40.979534],"type":"Point"}
}