{
  "type": "Feature",
  "properties": {
    "addr:full":"834 Beaver Dam Rd Point Pleasant Beach NJ 08742",
    "addr:housenumber":"834",
    "addr:postcode":"08742",
    "addr:street":"Beaver Dam Rd",
    "iso:country":"US",
    "sg:address":"834 Beaver Dam Rd",
    "sg:city":"Point Pleasant Beach",
    "sg:classifiers":[
        {
            "category":"Education",
            "subcategory":"Library",
            "type":"Public Place"
        }
    ],
    "sg:phone":"+1   ",
    "sg:postcode":"08742",
    "sg:province":"NJ",
    "wof:name":"County of Ocean",
    "wof:placetype":"venue"
},
  "geometry": {"coordinates":[-74.068821,40.078597],"type":"Point"}
}