{
  "type": "Feature",
  "properties": {
    "iso:country":"US",
    "sg:address":"11 Kristi Dr",
    "sg:city":"East Hanover",
    "sg:classifiers":[
        {
            "category":"Banks & Credit Unions",
            "subcategory":"Investment Brokerage",
            "type":"Services"
        }
    ],
    "sg:phone":"+1 973 428 9887",
    "sg:postcode":"07936",
    "sg:province":"NJ",
    "sg:tags":[
        "consultant",
        "financing"
    ],
    "wof:name":"V S Intl",
    "wof:placetype":"venue"
},
  "geometry": {"coordinates":[-74.39210799999999,40.799742],"type":"Point"}
}