{
  "type": "Feature",
  "properties": {
    "addr:full":"202 Broad Ave Palisades Park NJ 07650",
    "addr:housenumber":"202",
    "addr:postcode":"07650",
    "addr:street":"Broad Ave",
    "iso:country":"US",
    "sg:address":"202 Broad Ave",
    "sg:city":"Palisades Park",
    "sg:classifiers":[
        {
            "category":"Restaurant",
            "type":"Food & Drink"
        }
    ],
    "sg:phone":"+1 201 947 1454",
    "sg:postcode":"07650",
    "sg:province":"NJ",
    "sg:tags":[
        "greek",
        "eating"
    ],
    "wof:name":"Picnic Cafe",
    "wof:placetype":"venue"
},
  "geometry": {"coordinates":[-73.999246,40.845793],"type":"Point"}
}