{
  "type": "Feature",
  "properties": {
    "iso:country":"US",
    "sg:address":"139 Hamburg Tpke",
    "sg:city":"Butler",
    "sg:classifiers":[
        {
            "category":"Retail",
            "subcategory":"Auto Repair",
            "type":"Services"
        }
    ],
    "sg:phone":"+1 973 492 5840",
    "sg:postcode":"07405",
    "sg:province":"NJ",
    "sg:tags":[
        "automotive"
    ],
    "wof:name":"Northway",
    "wof:placetype":"venue"
},
  "geometry": {"coordinates":[-74.355875,41.013058],"type":"Point"}
}