{
  "type": "Feature",
  "properties": {
    "iso:country":"US",
    "sg:address":"46 1st Ave",
    "sg:city":"Atlantic Hghlnds",
    "sg:classifiers":[
        {
            "category":"Shopping",
            "subcategory":"Bicycles & Sporting Goods",
            "type":"Retail Goods"
        }
    ],
    "sg:phone":"+1 732 291 8822",
    "sg:postcode":"07716",
    "sg:province":"NJ",
    "wof:name":"Mikes Bikes",
    "wof:placetype":"venue"
},
  "geometry": {"coordinates":[-74.037454,40.414509],"type":"Point"}
}