{
  "type": "Feature",
  "properties": {
    "addr:full":"1263 Ringwood Ave Haskell NJ 07420",
    "addr:housenumber":"1263",
    "addr:postcode":"07420",
    "addr:street":"Ringwood Ave",
    "iso:country":"US",
    "sg:address":"1263 Ringwood Ave",
    "sg:city":"Haskell",
    "sg:classifiers":[
        {
            "category":"Manufacturing",
            "subcategory":"Tools & Machinery",
            "type":"Manufacturing & Wholesale Goods"
        }
    ],
    "sg:phone":"+1 973 831 9110",
    "sg:postcode":"07420",
    "sg:province":"NJ",
    "sg:tags":[
        "control"
    ],
    "wof:name":"Sico Systems Control Inc",
    "wof:placetype":"venue"
},
  "geometry": {"coordinates":[-74.296336,41.02174],"type":"Point"}
}