{
  "type": "Feature",
  "properties": {
    "addr:full":"448 Hamilton Ave Trenton NJ 08609",
    "addr:housenumber":"448",
    "addr:postcode":"08609",
    "addr:street":"Hamilton Ave",
    "iso:country":"US",
    "sg:address":"448 Hamilton Ave",
    "sg:city":"Trenton",
    "sg:classifiers":[
        {
            "category":"Professional",
            "subcategory":"Lawyer & Legal Services",
            "type":"Services"
        }
    ],
    "sg:phone":"+1 609 587 7550",
    "sg:postcode":"08609",
    "sg:province":"NJ",
    "sg:tags":[
        "attorney"
    ],
    "wof:name":"Donini & Ramsey",
    "wof:placetype":"venue"
},
  "geometry": {"coordinates":[-74.744764,40.216635],"type":"Point"}
}