{
  "type": "Feature",
  "properties": {
    "iso:country":"US",
    "sg:address":"20 Ridge Rd",
    "sg:city":"North Arlington",
    "sg:classifiers":[
        {
            "category":"Building & Trades",
            "subcategory":"Locksmith",
            "type":"Services"
        }
    ],
    "sg:phone":"+1 201 252 3218",
    "sg:postcode":"07031",
    "sg:province":"NJ",
    "sg:tags":[
        "key"
    ],
    "wof:name":"0 & 0 & 0 1 Emergency A 24 Hour A Locksmith",
    "wof:placetype":"venue"
},
  "geometry": {"coordinates":[-74.137885,40.782295],"type":"Point"}
}