{
  "type": "Feature",
  "properties": {
    "addr:full":"301 Madison Ave Lakewood NJ 08701",
    "addr:housenumber":"301",
    "addr:postcode":"08701",
    "addr:street":"Madison Ave",
    "iso:country":"US",
    "sg:address":"301 Madison Ave",
    "sg:city":"Lakewood",
    "sg:classifiers":[
        {
            "category":"Health Services",
            "subcategory":"Health Practitioner",
            "type":"Services"
        }
    ],
    "sg:phone":"+1 732 886 5010",
    "sg:postcode":"08701",
    "sg:province":"NJ",
    "sg:tags":[
        "psychotherapist"
    ],
    "wof:name":"Epstein Meshulem Lcsw",
    "wof:placetype":"venue"
},
  "geometry": {"coordinates":[-74.216792,40.092907],"type":"Point"}
}