{
  "type": "Feature",
  "properties": {
    "addr:full":"7 Shore Rd Edgewater NJ 07020",
    "addr:housenumber":"7",
    "addr:postcode":"07020",
    "addr:street":"Shore Rd",
    "iso:country":"US",
    "sg:address":"7 Shore Rd",
    "sg:city":"Edgewater",
    "sg:classifiers":[
        {
            "category":"Building & Trades",
            "subcategory":"Construction",
            "type":"Services"
        }
    ],
    "sg:phone":"+1   ",
    "sg:postcode":"07020",
    "sg:province":"NJ",
    "sg:tags":[
        "remodeling",
        "business",
        "contractor"
    ],
    "wof:name":"Giamptro Rnee Intr Renovations",
    "wof:placetype":"venue"
},
  "geometry": {"coordinates":[-73.964388,40.845962],"type":"Point"}
}