{
  "type": "Feature",
  "properties": {
    "addr:full":"14 Prospect St Madison NJ 07940",
    "addr:housenumber":"14",
    "addr:postcode":"07940",
    "addr:street":"Prospect St",
    "iso:country":"US",
    "sg:address":"14 Prospect St",
    "sg:city":"Madison",
    "sg:classifiers":[
        {
            "category":"Shopping",
            "subcategory":"Jewelry",
            "type":"Retail Goods"
        }
    ],
    "sg:phone":"+1   ",
    "sg:postcode":"07940",
    "sg:province":"NJ",
    "sg:tags":[
        "book",
        "music",
        "gift"
    ],
    "sg:website":"www.theblueturtle.com",
    "wof:name":"Blue Turtle Inc",
    "wof:placetype":"venue"
},
  "geometry": {"coordinates":[-74.41316500000001,40.757202],"type":"Point"}
}