{
  "type": "Feature",
  "properties": {
    "iso:country":"US",
    "sg:address":"40 Conger St",
    "sg:city":"Bloomfield",
    "sg:classifiers":[
        {
            "category":"Health Services",
            "subcategory":"Doctor",
            "type":"Services"
        }
    ],
    "sg:phone":"+1   ",
    "sg:postcode":"07003",
    "sg:province":"NJ",
    "sg:tags":[
        "medical"
    ],
    "wof:name":"Dmytriw Kevin R MD",
    "wof:placetype":"venue"
},
  "geometry": {"coordinates":[-74.196952,40.792215],"type":"Point"}
}