{
  "type": "Feature",
  "properties": {
    "addr:full":"1219 Kay Dr W Cherry Hill NJ 08034",
    "addr:housenumber":"1219",
    "addr:postcode":"08034",
    "addr:street":"Kay Dr W",
    "iso:country":"US",
    "sg:address":"1219 Kay Dr W",
    "sg:city":"Cherry Hill",
    "sg:classifiers":[
        {
            "category":"Manufacturing",
            "subcategory":"Retail Goods",
            "type":"Manufacturing & Wholesale Goods"
        }
    ],
    "sg:phone":"+1 856 795 8365",
    "sg:postcode":"08034",
    "sg:province":"NJ",
    "sg:tags":[
        "product",
        "mfg"
    ],
    "wof:name":"Metra Industries Inc",
    "wof:placetype":"venue"
},
  "geometry": {"coordinates":[-75.007997,39.902896],"type":"Point"}
}