{
  "type": "Feature",
  "properties": {
    "addr:full":"701 Mill Rd Pleasantville NJ 08232",
    "addr:housenumber":"701",
    "addr:postcode":"08232",
    "addr:street":"Mill Rd",
    "iso:country":"US",
    "sg:address":"701 Mill Rd",
    "sg:city":"Pleasantville",
    "sg:classifiers":[
        {
            "category":"Professional",
            "subcategory":"Business Services",
            "type":"Services"
        }
    ],
    "sg:phone":"+1 609 876 4999",
    "sg:postcode":"08232",
    "sg:province":"NJ",
    "sg:tags":[
        "event"
    ],
    "wof:name":"Prime Events",
    "wof:placetype":"venue"
},
  "geometry": {"coordinates":[-74.526224,39.406135],"type":"Point"}
}