{
  "type": "Feature",
  "properties": {
    "addr:full":"463 Oak Rd Bridgeton NJ 08302",
    "addr:housenumber":"463",
    "addr:postcode":"08302",
    "addr:street":"Oak Rd",
    "iso:country":"US",
    "sg:address":"463 Oak Rd",
    "sg:city":"Bridgeton",
    "sg:phone":"+1 856 451 7988",
    "sg:postcode":"08302",
    "sg:province":"NJ",
    "sg:tags":[
        "farm",
        "soybean"
    ],
    "wof:name":"Allen W Davis",
    "wof:placetype":"venue"
},
  "geometry": {"coordinates":[-75.31138,39.463662],"type":"Point"}
}