{
  "type": "Feature",
  "properties": {
    "iso:country":"US",
    "sg:address":"35 Journal Square 4th Fl, Suite 415",
    "sg:city":"Jersey City",
    "sg:classifiers":[
        {
            "category":"Real Estate",
            "subcategory":"Real Estate Services",
            "type":"Services"
        }
    ],
    "sg:phone":"+1 800 637 9124",
    "sg:postcode":"07306",
    "sg:province":"NJ",
    "sg:tags":[
        "management",
        "property"
    ],
    "sg:website":"www.tuscanypropertygroup.com",
    "wof:name":"Tuscany Property Management Group",
    "wof:placetype":"venue"
},
  "geometry": {"coordinates":[-74.06407299999999,40.731539],"type":"Point"}
}