{
  "type": "Feature",
  "properties": {
    "addr:full":"476 21st Ave Paterson NJ 07513",
    "addr:housenumber":"476",
    "addr:postcode":"07513",
    "addr:street":"21St Ave",
    "iso:country":"US",
    "sg:address":"476 21st Ave",
    "sg:city":"Paterson",
    "sg:classifiers":[
        {
            "category":"Restaurant",
            "type":"Food & Drink"
        }
    ],
    "sg:phone":"+1 973 278 0089",
    "sg:postcode":"07513",
    "sg:province":"NJ",
    "wof:name":"El Encanto Restaurant",
    "wof:placetype":"venue"
},
  "geometry": {"coordinates":[-74.15329699999999,40.906101],"type":"Point"}
}