{
  "type": "Feature",
  "properties": {
    "iso:country":"US",
    "sg:address":"59 E Shore Culvert Rd",
    "sg:city":"Branchville",
    "sg:classifiers":[
        {
            "category":"Building & Trades",
            "subcategory":"Construction",
            "type":"Services"
        }
    ],
    "sg:phone":"+1 973 948 2022",
    "sg:postcode":"07826",
    "sg:province":"NJ",
    "sg:tags":[
        "general",
        "contractor"
    ],
    "wof:name":"Hoffmann Construction Inc",
    "wof:placetype":"venue"
},
  "geometry": {"coordinates":[-74.78183300000001,41.156841],"type":"Point"}
}