{
  "type": "Feature",
  "properties": {
    "iso:country":"US",
    "sg:address":"55 Moonachie Ave",
    "sg:city":"Moonachie",
    "sg:classifiers":[
        {
            "category":"Building & Trades",
            "subcategory":"Locksmith",
            "type":"Services"
        }
    ],
    "sg:phone":"+1 201 403 9410",
    "sg:postcode":"07074",
    "sg:province":"NJ",
    "sg:tags":[
        "key"
    ],
    "wof:name":"24 Hr Locksmith & Auto Repair",
    "wof:placetype":"venue"
},
  "geometry": {"coordinates":[-74.075231,40.842186],"type":"Point"}
}