{
  "type": "Feature",
  "properties": {
    "iso:country":"US",
    "sg:address":"1418 Springfield Ave",
    "sg:city":"Irvington",
    "sg:classifiers":[
        {
            "category":"Shopping",
            "subcategory":"Music",
            "type":"Retail Goods"
        }
    ],
    "sg:phone":"+1 973 416 3362",
    "sg:postcode":"07111",
    "sg:province":"NJ",
    "sg:tags":[
        "compact",
        "record",
        "disc",
        "tape"
    ],
    "wof:name":"Porton Musical No 2",
    "wof:placetype":"venue"
},
  "geometry": {"coordinates":[-74.248324,40.723767],"type":"Point"}
}