{
  "type": "Feature",
  "properties": {
    "addr:full":"805 S Orange Ave Newark NJ 07106",
    "addr:housenumber":"805",
    "addr:postcode":"07106",
    "addr:street":"S Orange Ave",
    "iso:country":"US",
    "sg:address":"805 S Orange Ave",
    "sg:city":"Newark",
    "sg:classifiers":[
        {
            "category":"Organizations",
            "subcategory":"Religious Organization",
            "type":"Services"
        }
    ],
    "sg:phone":"+1   ",
    "sg:postcode":"07106",
    "sg:province":"NJ",
    "sg:website":"www.praisetemplecog.com",
    "wof:name":"Church Of God",
    "wof:placetype":"venue"
},
  "geometry": {"coordinates":[-74.22128600000001,40.745128],"type":"Point"}
}