{
  "type": "Feature",
  "properties": {
    "iso:country":"US",
    "sg:address":"58 Park Pl",
    "sg:city":"Newark",
    "sg:classifiers":[
        {
            "category":"Organizations",
            "subcategory":"Community Association",
            "type":"Services"
        }
    ],
    "sg:phone":"+1 973 622 6440",
    "sg:postcode":"07102",
    "sg:province":"NJ",
    "sg:tags":[
        "club"
    ],
    "wof:name":"Key Club",
    "wof:placetype":"venue"
},
  "geometry": {"coordinates":[-74.168511,40.739218],"type":"Point"}
}