{
  "type": "Feature",
  "properties": {
    "iso:country":"US",
    "sg:address":"36 Edgeboro Rd",
    "sg:city":"East Brunswick",
    "sg:classifiers":[
        {
            "category":"Retail",
            "subcategory":"Auto Rental",
            "type":"Services"
        }
    ],
    "sg:phone":"+1   ",
    "sg:postcode":"08816",
    "sg:province":"NJ",
    "sg:tags":[
        "truck"
    ],
    "wof:name":"Mid State Truck Sales",
    "wof:placetype":"venue"
},
  "geometry": {"coordinates":[-74.395471,40.475389],"type":"Point"}
}