{
  "type": "Feature",
  "properties": {
    "iso:country":"US",
    "sg:address":"Washington & Cherrix",
    "sg:city":"Beverly",
    "sg:classifiers":[
        {
            "category":"Education",
            "subcategory":"School",
            "type":"Public Place"
        }
    ],
    "sg:phone":"+1 609 877 1430",
    "sg:postcode":"08010",
    "sg:province":"NJ",
    "sg:tags":[
        "high",
        "middle",
        "elementary"
    ],
    "wof:name":"Edgewater Park Township of",
    "wof:placetype":"venue"
},
  "geometry": {"coordinates":[-74.907702,40.057514],"type":"Point"}
}