{
  "type": "Feature",
  "properties": {
    "addr:full":"507 S Shore Rd Marmora NJ 08223",
    "addr:housenumber":"507",
    "addr:postcode":"08223",
    "addr:street":"S Shore Rd",
    "iso:country":"US",
    "sg:address":"507 S Shore Rd",
    "sg:city":"Marmora",
    "sg:classifiers":[
        {
            "category":"Health Services",
            "subcategory":"Health Practitioner",
            "type":"Services"
        }
    ],
    "sg:phone":"+1 609 390 4895",
    "sg:postcode":"08223",
    "sg:province":"NJ",
    "wof:name":"Community Rehab Centers",
    "wof:placetype":"venue"
},
  "geometry": {"coordinates":[-74.660808,39.252626],"type":"Point"}
}