{
  "type": "Feature",
  "properties": {
    "iso:country":"US",
    "sg:address":"238 W Delaware Ave",
    "sg:city":"Pennington",
    "sg:classifiers":[
        {
            "category":"Education",
            "subcategory":"Vocational School",
            "type":"Public Place"
        }
    ],
    "sg:phone":"+1 609 737 1525",
    "sg:postcode":"08534",
    "sg:province":"NJ",
    "sg:tags":[
        "real estate"
    ],
    "wof:name":"Princeton School-Real Estate",
    "wof:placetype":"venue"
},
  "geometry": {"coordinates":[-74.799718,40.327106],"type":"Point"}
}