{
  "type": "Feature",
  "properties": {
    "iso:country":"US",
    "sg:address":"182 Quakertown Rd",
    "sg:city":"Pittstown",
    "sg:classifiers":[
        {
            "category":"Wholesale",
            "subcategory":"Vending Machines",
            "type":"Manufacturing & Wholesale Goods"
        }
    ],
    "sg:phone":"+1   ",
    "sg:postcode":"08867",
    "sg:province":"NJ",
    "sg:tags":[
        "operator"
    ],
    "wof:name":"Hunterdon Vending & Wholesale",
    "wof:placetype":"venue"
},
  "geometry": {"coordinates":[-74.95089900000001,40.569468],"type":"Point"}
}