{
  "type": "Feature",
  "properties": {
    "iso:country":"US",
    "sg:address":"119 S Olden Ave",
    "sg:city":"Trenton",
    "sg:classifiers":[
        {
            "category":"Home & Garden",
            "subcategory":"Building Materials",
            "type":"Retail Goods"
        },
        {
            "category":"Building & Trades",
            "subcategory":"Construction",
            "type":"Services"
        }
    ],
    "sg:phone":"+1 609 924 1295",
    "sg:postcode":"08609",
    "sg:province":"NJ",
    "sg:tags":[
        "windows",
        "siding",
        "contractor"
    ],
    "wof:name":"J & S Improvements",
    "wof:placetype":"venue"
},
  "geometry": {"coordinates":[-74.737889,40.224757],"type":"Point"}
}