{
  "type": "Feature",
  "properties": {
    "addr:full":"600 Arnold Ave Pt Pleasant Bch NJ 08742",
    "addr:housenumber":"600",
    "addr:postcode":"08742",
    "addr:street":"Arnold Ave Pt",
    "iso:country":"US",
    "sg:address":"600 Arnold Ave",
    "sg:city":"Pt Pleasant Bch",
    "sg:classifiers":[
        {
            "category":"Food & Beverages",
            "subcategory":"Bakery",
            "type":"Retail Goods"
        },
        {
            "category":"Restaurant",
            "type":"Food & Drink"
        }
    ],
    "sg:phone":"+1 732 295 5484",
    "sg:postcode":"08742",
    "sg:province":"NJ",
    "sg:tags":[
        "bagel",
        "eating"
    ],
    "wof:name":"Corner Bagelry Inc",
    "wof:placetype":"venue"
},
  "geometry": {"coordinates":[-74.051198,40.091631],"type":"Point"}
}