{
  "type": "Feature",
  "properties": {
    "iso:country":"US",
    "sg:address":"5 Ferrous Ct",
    "sg:city":"Chester",
    "sg:classifiers":[
        {
            "category":"Building & Trades",
            "subcategory":"Landscaping Services",
            "type":"Services"
        }
    ],
    "sg:phone":"+1 908 879 7811",
    "sg:postcode":"07930",
    "sg:province":"NJ",
    "sg:tags":[
        "landscape"
    ],
    "wof:name":"Lbd Landscaping LLC",
    "wof:placetype":"venue"
},
  "geometry": {"coordinates":[-74.684003,40.794167],"type":"Point"}
}