{
  "type": "Feature",
  "properties": {
    "addr:full":"132 State Rte 34 Holmdel NJ 07733",
    "addr:housenumber":"132",
    "addr:postcode":"07733",
    "addr:street":"State Rte 34",
    "iso:country":"US",
    "sg:address":"132 State Rte 34",
    "sg:city":"Holmdel",
    "sg:classifiers":[
        {
            "category":"Organizations",
            "subcategory":"Religious Organization",
            "type":"Services"
        }
    ],
    "sg:phone":"+1 732 332 1052",
    "sg:postcode":"07733",
    "sg:province":"NJ",
    "sg:tags":[
        "church"
    ],
    "wof:name":"St Mina Coptic Orthodox Chr",
    "wof:placetype":"venue"
},
  "geometry": {"coordinates":[-74.197565,40.36669],"type":"Point"}
}