{
  "type": "Feature",
  "properties": {
    "addr:full":"144 Rumson Rd Rumson NJ 07760",
    "addr:housenumber":"144",
    "addr:postcode":"07760",
    "addr:street":"Rumson Rd",
    "iso:country":"US",
    "sg:address":"144 Rumson Rd",
    "sg:city":"Rumson",
    "sg:classifiers":[
        {
            "category":"Organizations",
            "subcategory":"Community Association",
            "type":"Services"
        }
    ],
    "sg:phone":"+1 732 842 8817",
    "sg:postcode":"07760",
    "sg:province":"NJ",
    "sg:tags":[
        "club"
    ],
    "wof:name":"Surfrider Beach Club",
    "wof:placetype":"venue"
},
  "geometry": {"coordinates":[-74.015925,40.353691],"type":"Point"}
}