{
  "type": "Feature",
  "properties": {
    "iso:country":"US",
    "sg:address":"508 S 2nd Ave",
    "sg:city":"Galloway",
    "sg:classifiers":[
        {
            "category":"Organizations",
            "subcategory":"Religious Organization",
            "type":"Services"
        }
    ],
    "sg:phone":"+1 609 748 8888",
    "sg:postcode":"08205",
    "sg:province":"NJ",
    "sg:tags":[
        "church"
    ],
    "wof:name":"World Of Life Christian",
    "wof:placetype":"venue"
},
  "geometry": {"coordinates":[-74.516953,39.466105],"type":"Point"}
}