{
  "type": "Feature",
  "properties": {
    "iso:country":"US",
    "sg:address":"191 State Rte 34",
    "sg:city":"Matawan",
    "sg:classifiers":[
        {
            "category":"Food & Beverages",
            "subcategory":"Fruits & Vegetables",
            "type":"Retail Goods"
        }
    ],
    "sg:phone":"+1 732 583 6780",
    "sg:postcode":"07747",
    "sg:province":"NJ",
    "sg:tags":[
        "wheat",
        "farm",
        "corn",
        "soy",
        "rice",
        "market"
    ],
    "wof:name":"Cheesequake Farms",
    "wof:placetype":"venue"
},
  "geometry": {"coordinates":[-74.284864,40.42468],"type":"Point"}
}