{
  "type": "Feature",
  "properties": {
    "addr:full":"41 Main St South River NJ 08882",
    "addr:housenumber":"41",
    "addr:postcode":"08882",
    "addr:street":"Main St",
    "iso:country":"US",
    "sg:address":"41 Main St",
    "sg:city":"South River",
    "sg:classifiers":[
        {
            "category":"Banks & Credit Unions",
            "subcategory":"Bank",
            "type":"Services"
        }
    ],
    "sg:phone":"+1 732 257 8667",
    "sg:postcode":"08882",
    "sg:province":"NJ",
    "sg:tags":[
        "money",
        "order"
    ],
    "wof:name":"G & I Amigos Travel",
    "wof:placetype":"venue"
},
  "geometry": {"coordinates":[-74.380227,40.451566],"type":"Point"}
}