{
  "type": "Feature",
  "properties": {
    "iso:country":"US",
    "sg:address":"125 Turtleback Rd",
    "sg:city":"Califon",
    "sg:classifiers":[
        {
            "category":"Professional",
            "subcategory":"Research",
            "type":"Services"
        }
    ],
    "sg:phone":"+1 908 832 7722",
    "sg:postcode":"07830",
    "sg:province":"NJ",
    "sg:tags":[
        "consulting",
        "market"
    ],
    "wof:name":"Walton Research",
    "wof:placetype":"venue"
},
  "geometry": {"coordinates":[-74.80852400000001,40.748829],"type":"Point"}
}