{
  "type": "Feature",
  "properties": {
    "iso:country":"US",
    "sg:address":"1024 Shunpike Rd",
    "sg:city":"Cape May",
    "sg:classifiers":[
        {
            "category":"Autos & Motor Vehicles",
            "subcategory":"Auto Supplies",
            "type":"Retail Goods"
        },
        {
            "category":"Wholesale",
            "subcategory":"Auto Parts",
            "type":"Manufacturing & Wholesale Goods"
        }
    ],
    "sg:phone":"+1 609 884 4258",
    "sg:postcode":"08204",
    "sg:province":"NJ",
    "sg:tags":[
        "automobile",
        "used",
        "wrecking",
        "accessory"
    ],
    "wof:name":"Cape May Used Auto Parts",
    "wof:placetype":"venue"
},
  "geometry": {"coordinates":[-74.93279800000001,38.958549],"type":"Point"}
}