{
  "type": "Feature",
  "properties": {
    "iso:country":"US",
    "sg:address":"2500 Pennington Rd",
    "sg:city":"Pennington",
    "sg:classifiers":[
        {
            "category":"Building & Trades",
            "subcategory":"Construction",
            "type":"Services"
        }
    ],
    "sg:phone":"+1 609 737 1015",
    "sg:postcode":"08534",
    "sg:province":"NJ",
    "sg:tags":[
        "new",
        "commercial",
        "renovation"
    ],
    "wof:name":"Geo Matrix Construction Corp",
    "wof:placetype":"venue"
},
  "geometry": {"coordinates":[-74.784476,40.304387],"type":"Point"}
}