{
  "type": "Feature",
  "properties": {
    "addr:full":"260 Ottawa Ave Hasbrouck Heights NJ 07604",
    "addr:housenumber":"260",
    "addr:postcode":"07604",
    "addr:street":"Ottawa Ave",
    "iso:country":"US",
    "sg:address":"260 Ottawa Ave",
    "sg:city":"Hasbrouck Heights",
    "sg:classifiers":[
        {
            "category":"Travel",
            "subcategory":"Campground",
            "type":"Entertainment"
        }
    ],
    "sg:phone":"+1   ",
    "sg:postcode":"07604",
    "sg:province":"NJ",
    "sg:tags":[
        "camp"
    ],
    "wof:name":"Camp Marcella",
    "wof:placetype":"venue"
},
  "geometry": {"coordinates":[-74.071893,40.866021],"type":"Point"}
}