{
  "type": "Feature",
  "properties": {
    "addr:full":"230 Melrose Ave Middlesex NJ 08846",
    "addr:housenumber":"230",
    "addr:postcode":"08846",
    "addr:street":"Melrose Ave",
    "iso:country":"US",
    "sg:address":"230 Melrose Ave",
    "sg:city":"Middlesex",
    "sg:classifiers":[
        {
            "category":"Building & Trades",
            "subcategory":"Landscaping Services",
            "type":"Services"
        }
    ],
    "sg:phone":"+1 732 271 8727",
    "sg:postcode":"08846",
    "sg:province":"NJ",
    "wof:name":"Mountain View Landscaping",
    "wof:placetype":"venue"
},
  "geometry": {"coordinates":[-74.51265100000001,40.568201],"type":"Point"}
}