{
  "type": "Feature",
  "properties": {
    "iso:country":"US",
    "sg:address":"100 Steiner Ave",
    "sg:city":"Neptune",
    "sg:classifiers":[
        {
            "category":"Building & Trades",
            "subcategory":"Construction",
            "type":"Services"
        }
    ],
    "sg:phone":"+1 732 774 5444",
    "sg:postcode":"07753",
    "sg:province":"NJ",
    "sg:tags":[
        "general",
        "public",
        "contractor"
    ],
    "wof:name":"G & M Eastern Contracting Co",
    "wof:placetype":"venue"
},
  "geometry": {"coordinates":[-74.02358,40.198316],"type":"Point"}
}