{
  "type": "Feature",
  "properties": {
    "addr:full":"77 18th St Weehawken NJ 07086",
    "addr:housenumber":"77",
    "addr:postcode":"07086",
    "addr:street":"18Th St",
    "iso:country":"US",
    "sg:address":"77 18th St",
    "sg:city":"Weehawken",
    "sg:classifiers":[
        {
            "category":"Building & Trades",
            "subcategory":"Equipment Rental",
            "type":"Services"
        }
    ],
    "sg:phone":"+1 201 863 4100",
    "sg:postcode":"07086",
    "sg:province":"NJ",
    "sg:tags":[
        "scaffolding"
    ],
    "wof:name":"Machal Service Systems Corp",
    "wof:placetype":"venue"
},
  "geometry": {"coordinates":[-74.031356,40.758732],"type":"Point"}
}