{
  "type": "Feature",
  "properties": {
    "iso:country":"US",
    "sg:address":"60 River Rd",
    "sg:city":"Montague",
    "sg:classifiers":[
        {
            "category":"Recreation",
            "type":"Entertainment"
        }
    ],
    "sg:phone":"+1   ",
    "sg:postcode":"07827",
    "sg:province":"NJ",
    "sg:tags":[
        "course",
        "golf"
    ],
    "wof:name":"Rockview Golf Club",
    "wof:placetype":"venue"
},
  "geometry": {"coordinates":[-74.699822,41.350671],"type":"Point"}
}