{
  "type": "Feature",
  "properties": {
    "addr:full":"102 Thomas Dr Clark NJ 07066",
    "addr:housenumber":"102",
    "addr:postcode":"07066",
    "addr:street":"Thomas Dr",
    "iso:country":"US",
    "sg:address":"102 Thomas Dr",
    "sg:city":"Clark",
    "sg:classifiers":[
        {
            "category":"Building & Trades",
            "subcategory":"Construction",
            "type":"Services"
        }
    ],
    "sg:phone":"+1 732 499 4429",
    "sg:postcode":"07066",
    "sg:province":"NJ",
    "sg:tags":[
        "contractor"
    ],
    "wof:name":"Rmr Contractors LLC",
    "wof:placetype":"venue"
},
  "geometry": {"coordinates":[-74.322568,40.615937],"type":"Point"}
}