{
  "type": "Feature",
  "properties": {
    "iso:country":"US",
    "sg:address":"15 Weldon Rd",
    "sg:city":"Lake Hopatcong",
    "sg:classifiers":[
        {
            "category":"Retail",
            "subcategory":"Auto Repair",
            "type":"Services"
        }
    ],
    "sg:phone":"+1 973 663 1600",
    "sg:postcode":"07849",
    "sg:province":"NJ",
    "sg:tags":[
        "truck"
    ],
    "wof:name":"Dover Brake & Clutch Co",
    "wof:placetype":"venue"
},
  "geometry": {"coordinates":[-74.599413,40.974202],"type":"Point"}
}