{
  "type": "Feature",
  "properties": {
    "addr:full":"254 W Bigelow St Newark NJ 07108",
    "addr:housenumber":"254",
    "addr:postcode":"07108",
    "addr:street":"W Bigelow St",
    "iso:country":"US",
    "sg:address":"254 W Bigelow St",
    "sg:city":"Newark",
    "sg:classifiers":[
        {
            "category":"Government",
            "subcategory":"Police Station",
            "type":"Public Place"
        }
    ],
    "sg:phone":"+1 973 733 6270",
    "sg:postcode":"07108",
    "sg:province":"NJ",
    "sg:tags":[
        "department",
        "protection"
    ],
    "wof:name":"Newark Police Department",
    "wof:placetype":"venue"
},
  "geometry": {"coordinates":[-74.199945,40.719138],"type":"Point"}
}