{
  "type": "Feature",
  "properties": {
    "addr:full":"1025 State Rte 35 Ocean NJ 07712",
    "addr:housenumber":"1025",
    "addr:postcode":"07712",
    "addr:street":"State Rte 35",
    "iso:country":"US",
    "sg:address":"1025 State Rte 35",
    "sg:city":"Ocean",
    "sg:classifiers":[
        {
            "category":"Health Services",
            "subcategory":"Doctor",
            "type":"Services"
        }
    ],
    "sg:phone":"+1 732 531 8200",
    "sg:postcode":"07712",
    "sg:province":"NJ",
    "sg:tags":[
        "physician",
        "surgeon"
    ],
    "wof:name":"Aesthetic Facial Plastic Surg",
    "wof:placetype":"venue"
},
  "geometry": {"coordinates":[-74.03720199999999,40.239725],"type":"Point"}
}