{
  "type": "Feature",
  "properties": {
    "addr:full":"447 Garfield Ave Jersey City NJ 07305",
    "addr:housenumber":"447",
    "addr:postcode":"07305",
    "addr:street":"Garfield Ave",
    "iso:country":"US",
    "sg:address":"447 Garfield Ave",
    "sg:city":"Jersey City",
    "sg:classifiers":[
        {
            "category":"Building & Trades",
            "subcategory":"Construction",
            "type":"Services"
        }
    ],
    "sg:phone":"+1 201 434 4084",
    "sg:postcode":"07305",
    "sg:province":"NJ",
    "sg:tags":[
        "contractor"
    ],
    "wof:name":"Kingdom Builders Inc",
    "wof:placetype":"venue"
},
  "geometry": {"coordinates":[-74.082747,40.69819],"type":"Point"}
}