{
  "type": "Feature",
  "properties": {
    "iso:country":"US",
    "sg:address":"175 Smith St",
    "sg:city":"Perth Amboy",
    "sg:classifiers":[
        {
            "category":"Travel",
            "subcategory":"Travel Agent",
            "type":"Entertainment"
        }
    ],
    "sg:phone":"+1 732 442 0606",
    "sg:postcode":"08861",
    "sg:province":"NJ",
    "sg:tags":[
        "agency"
    ],
    "wof:name":"Nick Lugo Travel",
    "wof:placetype":"venue"
},
  "geometry": {"coordinates":[-74.27090099999999,40.509307],"type":"Point"}
}