{
  "type": "Feature",
  "properties": {
    "iso:country":"US",
    "sg:address":"25 Parsons Rd",
    "sg:city":"Lincoln Park",
    "sg:classifiers":[
        {
            "category":"Building & Trades",
            "subcategory":"Construction",
            "type":"Services"
        }
    ],
    "sg:phone":"+1 973 696 0038",
    "sg:postcode":"07035",
    "sg:province":"NJ",
    "sg:tags":[
        "downspouts",
        "gutter"
    ],
    "wof:name":"Metro Seamless Gutters",
    "wof:placetype":"venue"
},
  "geometry": {"coordinates":[-74.300082,40.937521],"type":"Point"}
}