{
  "type": "Feature",
  "properties": {
    "iso:country":"US",
    "sg:address":"75 Main St",
    "sg:city":"Millburn",
    "sg:classifiers":[
        {
            "category":"Health Services",
            "subcategory":"Doctor",
            "type":"Services"
        }
    ],
    "sg:phone":"+1 973 467 9744",
    "sg:postcode":"07041",
    "sg:province":"NJ",
    "sg:tags":[
        "surgeon",
        "cosmetic"
    ],
    "wof:name":"Bulan Erwin J MD",
    "wof:placetype":"venue"
},
  "geometry": {"coordinates":[-74.3069,40.722801],"type":"Point"}
}