{
  "type": "Feature",
  "properties": {
    "addr:full":"10 Barclay Dr Blackwood NJ 08012",
    "addr:housenumber":"10",
    "addr:postcode":"08012",
    "addr:street":"Barclay Dr",
    "iso:country":"US",
    "sg:address":"10 Barclay Dr",
    "sg:city":"Blackwood",
    "sg:classifiers":[
        {
            "category":"Shopping",
            "type":"Retail Goods"
        }
    ],
    "sg:phone":"+1 856 429 1699",
    "sg:postcode":"08012",
    "sg:province":"NJ",
    "sg:tags":[
        "pet",
        "food",
        "supply"
    ],
    "wof:name":"Cutter's Mill Pet Food & Supl",
    "wof:placetype":"venue"
},
  "geometry": {"coordinates":[-75.049813,39.758763],"type":"Point"}
}