{
  "type": "Feature",
  "properties": {
    "addr:full":"1200 State Rte 27 Rahway NJ 07065",
    "addr:housenumber":"1200",
    "addr:postcode":"07065",
    "addr:street":"State Rte 27",
    "iso:country":"US",
    "sg:address":"1200 State Rte 27",
    "sg:city":"Rahway",
    "sg:classifiers":[
        {
            "category":"Autos & Motor Vehicles",
            "subcategory":"Automobile Sales",
            "type":"Retail Goods"
        }
    ],
    "sg:phone":"+1   ",
    "sg:postcode":"07065",
    "sg:province":"NJ",
    "wof:name":"Bell Ford",
    "wof:placetype":"venue"
},
  "geometry": {"coordinates":[-74.286523,40.610364],"type":"Point"}
}