{
  "type": "Feature",
  "properties": {
    "iso:country":"US",
    "sg:address":"25 Mallard Dr",
    "sg:city":"Mount Laurel",
    "sg:classifiers":[
        {
            "category":"Building & Trades",
            "subcategory":"Construction",
            "type":"Services"
        }
    ],
    "sg:phone":"+1 856 234 6808",
    "sg:postcode":"08054",
    "sg:province":"NJ",
    "sg:tags":[
        "carpentry",
        "contractor"
    ],
    "wof:name":"Excel Contractors",
    "wof:placetype":"venue"
},
  "geometry": {"coordinates":[-74.908625,39.93209],"type":"Point"}
}