{
  "type": "Feature",
  "properties": {
    "iso:country":"US",
    "sg:address":"5 Sunridge Dr",
    "sg:city":"Flemington",
    "sg:classifiers":[
        {
            "category":"Organizations",
            "subcategory":"Professional Association",
            "type":"Services"
        },
        {
            "category":"Organizations",
            "subcategory":"Community Association",
            "type":"Services"
        }
    ],
    "sg:phone":"+1 908 237 0994",
    "sg:postcode":"08822",
    "sg:province":"NJ",
    "wof:name":"Sun Ridge Home Owners Assoc",
    "wof:placetype":"venue"
},
  "geometry": {"coordinates":[-74.838099,40.495442],"type":"Point"}
}