{
  "type": "Feature",
  "properties": {
    "iso:country":"US",
    "sg:address":"620 Broadway",
    "sg:city":"Bayonne",
    "sg:classifiers":[
        {
            "category":"Insurance",
            "subcategory":"Insurance Agent",
            "type":"Services"
        }
    ],
    "sg:phone":"+1 201 437 3900",
    "sg:postcode":"07002",
    "sg:province":"NJ",
    "sg:tags":[
        "motorcycle"
    ],
    "sg:website":"http://WWW.BAYONNETRANSOCEANIC.COM",
    "wof:name":"Bayonne Transoceanic",
    "wof:placetype":"venue"
},
  "geometry": {"coordinates":[-74.11464599999999,40.6682],"type":"Point"}
}