{
  "type": "Feature",
  "properties": {
    "iso:country":"US",
    "sg:address":"104 Westwood Ave",
    "sg:city":"Westwood",
    "sg:classifiers":[
        {
            "category":"Shopping",
            "subcategory":"Clothing, Apparel, & Fashions",
            "type":"Retail Goods"
        }
    ],
    "sg:phone":"+1 201 664 3111",
    "sg:postcode":"07675",
    "sg:province":"NJ",
    "sg:website":"www.hartly.net",
    "wof:name":"Hartly Fashions",
    "wof:placetype":"venue"
},
  "geometry": {"coordinates":[-74.031747,40.991923],"type":"Point"}
}