{
  "type": "Feature",
  "properties": {
    "addr:full":"1857 Winding Brook Way Scotch Plains NJ 07076",
    "addr:housenumber":"1857",
    "addr:postcode":"07076",
    "addr:street":"Winding Brook Way",
    "iso:country":"US",
    "sg:address":"1857 Winding Brook Way",
    "sg:city":"Scotch Plains",
    "sg:classifiers":[
        {
            "category":"Professional",
            "type":"Services"
        }
    ],
    "sg:phone":"+1   ",
    "sg:postcode":"07076",
    "sg:province":"NJ",
    "wof:name":"Gordon Appraisal Services LLC",
    "wof:placetype":"venue"
},
  "geometry": {"coordinates":[-74.34324700000001,40.625255],"type":"Point"}
}