{
  "type": "Feature",
  "properties": {
    "iso:country":"US",
    "sg:address":"1 Boundary Rd",
    "sg:city":"Somerville",
    "sg:classifiers":[
        {
            "category":"Building & Trades",
            "subcategory":"Electrical",
            "type":"Services"
        }
    ],
    "sg:phone":"+1 908 534 3435",
    "sg:postcode":"08876",
    "sg:province":"NJ",
    "sg:tags":[
        "electric",
        "contractor"
    ],
    "wof:name":"Phoenix Electrical Dynamics",
    "wof:placetype":"venue"
},
  "geometry": {"coordinates":[-74.72462899999999,40.606038],"type":"Point"}
}