{
  "type": "Feature",
  "properties": {
    "iso:country":"US",
    "sg:address":"315 Closter Dock Rd",
    "sg:city":"Closter",
    "sg:classifiers":[
        {
            "category":"Professional",
            "subcategory":"Accounting & Tax Preparation",
            "type":"Services"
        }
    ],
    "sg:phone":"+1 201 767 5552",
    "sg:postcode":"07624",
    "sg:province":"NJ",
    "sg:tags":[
        "accountant"
    ],
    "wof:name":"A B Gorga Construction Co",
    "wof:placetype":"venue"
},
  "geometry": {"coordinates":[-73.959479,40.970205],"type":"Point"}
}