{
  "type": "Feature",
  "properties": {
    "iso:country":"US",
    "sg:address":"3710 E State St Exd",
    "sg:city":"Trenton",
    "sg:classifiers":[
        {
            "category":"Social Services",
            "subcategory":"Child Care",
            "type":"Services"
        }
    ],
    "sg:phone":"+1 609 586 1422",
    "sg:postcode":"08619",
    "sg:province":"NJ",
    "sg:tags":[
        "kindergarten",
        "academic",
        "school",
        "day"
    ],
    "wof:name":"Our Lady Of Sorrows Pre-School",
    "wof:placetype":"venue"
},
  "geometry": {"coordinates":[-74.693916,40.238103],"type":"Point"}
}