{
  "type": "Feature",
  "properties": {
    "iso:country":"US",
    "sg:address":"20 E Main St",
    "sg:city":"Mendham",
    "sg:classifiers":[
        {
            "category":"Professional",
            "type":"Services"
        }
    ],
    "sg:phone":"+1 973 885 1775",
    "sg:postcode":"07945",
    "sg:province":"NJ",
    "sg:tags":[
        "establishment"
    ],
    "wof:name":"Fred T Fell Lpc",
    "wof:placetype":"venue"
},
  "geometry": {"coordinates":[-74.59982100000001,40.776218],"type":"Point"}
}