{
  "type": "Feature",
  "properties": {
    "addr:full":"319 N High St Millville NJ 08332",
    "addr:housenumber":"319",
    "addr:postcode":"08332",
    "addr:street":"N High St",
    "iso:country":"US",
    "sg:address":"319 N High St",
    "sg:city":"Millville",
    "sg:classifiers":[
        {
            "category":"Professional",
            "subcategory":"Business Services",
            "type":"Services"
        }
    ],
    "sg:phone":"+1 856 691 7070",
    "sg:postcode":"08332",
    "sg:province":"NJ",
    "sg:tags":[
        "notary"
    ],
    "wof:name":"Pladeck Assoc",
    "wof:placetype":"venue"
},
  "geometry": {"coordinates":[-75.038499,39.39931],"type":"Point"}
}