{
  "type": "Feature",
  "properties": {
    "iso:country":"US",
    "sg:address":"1843 Springfield Ave",
    "sg:city":"Maplewood",
    "sg:classifiers":[
        {
            "category":"Personal",
            "subcategory":"Beauty Salon",
            "type":"Services"
        }
    ],
    "sg:phone":"+1 973 763 4300",
    "sg:postcode":"07040",
    "sg:province":"NJ",
    "wof:name":"Strandz",
    "wof:placetype":"venue"
},
  "geometry": {"coordinates":[-74.26815499999999,40.720909],"type":"Point"}
}