{
  "type": "Feature",
  "properties": {
    "iso:country":"US",
    "sg:address":"275 E State Rt 4",
    "sg:city":"Paramus",
    "sg:classifiers":[
        {
            "category":"Shopping",
            "subcategory":"Jewelry",
            "type":"Retail Goods"
        }
    ],
    "sg:phone":"+1 201 342 7114",
    "sg:postcode":"07652",
    "sg:province":"NJ",
    "wof:name":"Julianna Jewelery II",
    "wof:placetype":"venue"
},
  "geometry": {"coordinates":[-74.049435,40.914799],"type":"Point"}
}