{
  "type": "Feature",
  "properties": {
    "iso:country":"US",
    "sg:address":"309 E Bay Ave",
    "sg:city":"Manahawkin",
    "sg:classifiers":[
        {
            "category":"Retail",
            "subcategory":"Auto Rental",
            "type":"Services"
        }
    ],
    "sg:phone":"+1 609 489 0966",
    "sg:postcode":"08050",
    "sg:province":"NJ",
    "sg:tags":[
        "renting",
        "truck",
        "leasing"
    ],
    "wof:name":"Avis Rent A Car",
    "wof:placetype":"venue"
},
  "geometry": {"coordinates":[-74.25038000000001,39.691387],"type":"Point"}
}