{
  "type": "Feature",
  "properties": {
    "iso:country":"US",
    "sg:address":"13 Pleasant Ave",
    "sg:city":"Montclair",
    "sg:classifiers":[
        {
            "category":"Social Services",
            "subcategory":"Child Care",
            "type":"Services"
        }
    ],
    "sg:phone":"+1   ",
    "sg:postcode":"07042",
    "sg:province":"NJ",
    "sg:tags":[
        "group",
        "day"
    ],
    "wof:name":"Hugs N Care",
    "wof:placetype":"venue"
},
  "geometry": {"coordinates":[-74.221374,40.793863],"type":"Point"}
}