{
  "type": "Feature",
  "properties": {
    "addr:full":"14 Trenton Pl Hewitt NJ 07460",
    "addr:housenumber":"14",
    "addr:postcode":"07460",
    "addr:street":"Trenton Pl",
    "iso:country":"US",
    "sg:address":"14 Trenton Pl",
    "sg:city":"Hewitt",
    "sg:classifiers":[
        {
            "category":"Retail",
            "subcategory":"Laundry & Dry Cleaning",
            "type":"Services"
        }
    ],
    "sg:phone":"+1   ",
    "sg:postcode":"07460",
    "sg:province":"NJ",
    "wof:name":"Maintenance King",
    "wof:placetype":"venue"
},
  "geometry": {"coordinates":[-74.750721,41.043908],"type":"Point"}
}