{
  "type": "Feature",
  "properties": {
    "iso:country":"US",
    "sg:address":"224 Broughton Ave",
    "sg:city":"Bloomfield",
    "sg:classifiers":[
        {
            "category":"Manufacturing",
            "subcategory":"Printing",
            "type":"Manufacturing & Wholesale Goods"
        }
    ],
    "sg:phone":"+1 973 338 8243",
    "sg:postcode":"07003",
    "sg:province":"NJ",
    "sg:tags":[
        "lithographic",
        "commercial"
    ],
    "wof:name":"Accent Press Inc",
    "wof:placetype":"venue"
},
  "geometry": {"coordinates":[-74.183483,40.817537],"type":"Point"}
}