{
  "type": "Feature",
  "properties": {
    "addr:full":"242 Market St Elmwood Park NJ 07407",
    "addr:housenumber":"242",
    "addr:postcode":"07407",
    "addr:street":"Market St",
    "iso:country":"US",
    "sg:address":"242 Market St",
    "sg:city":"Elmwood Park",
    "sg:classifiers":[
        {
            "category":"Food & Beverages",
            "subcategory":"Groceries & Convenience Stores",
            "type":"Retail Goods"
        }
    ],
    "sg:phone":"+1   ",
    "sg:postcode":"07407",
    "sg:province":"NJ",
    "wof:name":"Cucina Di Mamma",
    "wof:placetype":"venue"
},
  "geometry": {"coordinates":[-74.121128,40.900403],"type":"Point"}
}