{
  "type": "Feature",
  "properties": {
    "addr:full":"3109 Boardwalk Atlantic City NJ 08401",
    "addr:housenumber":"3109",
    "addr:postcode":"08401",
    "addr:street":"Boardwalk",
    "iso:country":"US",
    "sg:address":"3109 Boardwalk",
    "sg:city":"Atlantic City",
    "sg:classifiers":[
        {
            "category":"Real Estate",
            "subcategory":"Real Estate Agent",
            "type":"Services"
        }
    ],
    "sg:phone":"+1 609 441 1115",
    "sg:postcode":"08401",
    "sg:province":"NJ",
    "wof:name":"Leisure International",
    "wof:placetype":"venue"
},
  "geometry": {"coordinates":[-74.448097,39.350683],"type":"Point"}
}