{
  "type": "Feature",
  "properties": {
    "iso:country":"US",
    "sg:address":"2010 Marlton Pike West - Rt.70 Ste. C",
    "sg:city":"Cherry Hill",
    "sg:classifiers":[
        {
            "category":"Health Services",
            "subcategory":"Optometrist",
            "type":"Services"
        },
        {
            "category":"Shopping",
            "subcategory":"Optician",
            "type":"Retail Goods"
        }
    ],
    "sg:phone":"+1 856 663 5544",
    "sg:postcode":"08002",
    "sg:province":"NJ",
    "sg:tags":[
        "eyewear"
    ],
    "sg:website":"www.foreyes.com/",
    "wof:name":"For Eyes Optical",
    "wof:placetype":"venue"
},
  "geometry": {"coordinates":[-75.035432,39.920097],"type":"Point"}
}