{
  "type": "Feature",
  "properties": {
    "addr:full":"1304 Berwyck Ct Sicklerville NJ 08081",
    "addr:housenumber":"1304",
    "addr:postcode":"08081",
    "addr:street":"Berwyck Ct",
    "iso:country":"US",
    "sg:address":"1304 Berwyck Ct",
    "sg:city":"Sicklerville",
    "sg:classifiers":[
        {
            "category":"Professional",
            "subcategory":"Business Services",
            "type":"Services"
        }
    ],
    "sg:phone":"+1   ",
    "sg:postcode":"08081",
    "sg:province":"NJ",
    "wof:name":"Robin D Sneddon",
    "wof:placetype":"venue"
},
  "geometry": {"coordinates":[-75.03442699999999,39.760003],"type":"Point"}
}