{
  "type": "Feature",
  "properties": {
    "iso:country":"US",
    "sg:address":"15 Maple St",
    "sg:city":"Norwood",
    "sg:classifiers":[
        {
            "category":"Professional",
            "subcategory":"Management & Consulting",
            "type":"Services"
        }
    ],
    "sg:phone":"+1 201 767 9100",
    "sg:postcode":"07648",
    "sg:province":"NJ",
    "sg:tags":[
        "consultant",
        "business"
    ],
    "sg:website":"www.cusc.com",
    "wof:name":"Consumers Utilities Svc",
    "wof:placetype":"venue"
},
  "geometry": {"coordinates":[-73.95202399999999,40.992155],"type":"Point"}
}