{
  "type": "Feature",
  "properties": {
    "addr:full":"735 Anderson Ave Cliffside Park NJ 07010",
    "addr:housenumber":"735",
    "addr:postcode":"07010",
    "addr:street":"Anderson Ave",
    "iso:country":"US",
    "sg:address":"735 Anderson Ave",
    "sg:city":"Cliffside Park",
    "sg:classifiers":[
        {
            "category":"Shopping",
            "subcategory":"Shoes",
            "type":"Retail Goods"
        }
    ],
    "sg:phone":"+1 201 943 8805",
    "sg:postcode":"07010",
    "sg:province":"NJ",
    "wof:name":"Joe's Shoe Clinic",
    "wof:placetype":"venue"
},
  "geometry": {"coordinates":[-73.985705,40.830271],"type":"Point"}
}