{
  "type": "Feature",
  "properties": {
    "iso:country":"US",
    "sg:address":"26 Jefferson Plz",
    "sg:city":"Princeton",
    "sg:classifiers":[
        {
            "category":"Health Services",
            "subcategory":"Health Practitioner",
            "type":"Services"
        }
    ],
    "sg:phone":"+1 732 274 9333",
    "sg:postcode":"08540",
    "sg:province":"NJ",
    "sg:tags":[
        "psychologist"
    ],
    "wof:name":"Robert N Eckardt Jr PHD",
    "wof:placetype":"venue"
},
  "geometry": {"coordinates":[-74.58640800000001,40.381331],"type":"Point"}
}