{
  "type": "Feature",
  "properties": {
    "addr:full":"4160 Church Rd Mount Laurel NJ 08054",
    "addr:housenumber":"4160",
    "addr:postcode":"08054",
    "addr:street":"Church Rd",
    "iso:country":"US",
    "sg:address":"4160 Church Rd",
    "sg:city":"Mount Laurel",
    "sg:classifiers":[
        {
            "category":"Restaurant",
            "type":"Food & Drink"
        }
    ],
    "sg:menulink":"http://www.allmenus.com/nj/mount-laurel/106702-on-the-border/menu/",
    "sg:phone":"+1 856 787 0698",
    "sg:postcode":"08054",
    "sg:province":"NJ",
    "sg:tags":[
        "mexican"
    ],
    "wof:name":"On The Border",
    "wof:placetype":"venue"
},
  "geometry": {"coordinates":[-74.95249200000001,39.924219],"type":"Point"}
}