{
  "type": "Feature",
  "properties": {
    "iso:country":"US",
    "sg:address":"934 S Elmora Ave",
    "sg:city":"Elizabeth",
    "sg:classifiers":[
        {
            "category":"Retail",
            "subcategory":"Self-service Laundry",
            "type":"Services"
        }
    ],
    "sg:phone":"+1 908 355 5308",
    "sg:postcode":"07202",
    "sg:province":"NJ",
    "wof:name":"Laundry Shack",
    "wof:placetype":"venue"
},
  "geometry": {"coordinates":[-74.222989,40.651699],"type":"Point"}
}