{
  "type": "Feature",
  "properties": {
    "iso:country":"US",
    "sg:address":"2040 Morris Ave",
    "sg:city":"Union",
    "sg:classifiers":[
        {
            "category":"Professional",
            "type":"Services"
        }
    ],
    "sg:phone":"+1 908 686 8513",
    "sg:postcode":"07083",
    "sg:province":"NJ",
    "sg:tags":[
        "establishment"
    ],
    "wof:name":"2840 Morris Avenue Assocs",
    "wof:placetype":"venue"
},
  "geometry": {"coordinates":[-74.27133499999999,40.696756],"type":"Point"}
}