{
  "type": "Feature",
  "properties": {
    "iso:country":"US",
    "sg:address":"12 Vail St",
    "sg:city":"Newark",
    "sg:classifiers":[
        {
            "category":"Building & Trades",
            "subcategory":"Construction",
            "type":"Services"
        }
    ],
    "sg:phone":"+1 973 373 4293",
    "sg:postcode":"07106",
    "sg:province":"NJ",
    "sg:tags":[
        "contractor"
    ],
    "wof:name":"Robinson Inc",
    "wof:placetype":"venue"
},
  "geometry": {"coordinates":[-74.233664,40.748766],"type":"Point"}
}