{
  "type": "Feature",
  "properties": {
    "addr:full":"140 Amherst Dr Bayville NJ 08721",
    "addr:housenumber":"140",
    "addr:postcode":"08721",
    "addr:street":"Amherst Dr",
    "iso:country":"US",
    "sg:address":"140 Amherst Dr",
    "sg:city":"Bayville",
    "sg:classifiers":[
        {
            "category":"Building & Trades",
            "subcategory":"Construction",
            "type":"Services"
        }
    ],
    "sg:phone":"+1 732 606 9196",
    "sg:postcode":"08721",
    "sg:province":"NJ",
    "sg:tags":[
        "concrete",
        "contractor"
    ],
    "wof:name":"New Jersey Hard Surface",
    "wof:placetype":"venue"
},
  "geometry": {"coordinates":[-74.128857,39.910739],"type":"Point"}
}