{
  "type": "Feature",
  "properties": {
    "iso:country":"US",
    "sg:address":"400 Mount Laurel Rd",
    "sg:city":"Mt Laurel",
    "sg:classifiers":[
        {
            "category":"Professional",
            "subcategory":"Lawyer & Legal Services",
            "type":"Services"
        }
    ],
    "sg:phone":"+1 856 235 8020",
    "sg:postcode":"08054",
    "sg:province":"NJ",
    "sg:tags":[
        "attorney"
    ],
    "wof:name":"Duncan & Hendershot",
    "wof:placetype":"venue"
},
  "geometry": {"coordinates":[-74.900592,39.940774],"type":"Point"}
}