{
  "type": "Feature",
  "properties": {
    "addr:full":"290 Market St Elmwood Park NJ 07407",
    "addr:housenumber":"290",
    "addr:postcode":"07407",
    "addr:street":"Market St",
    "iso:country":"US",
    "sg:address":"290 Market St",
    "sg:city":"Elmwood Park",
    "sg:classifiers":[
        {
            "category":"Insurance",
            "subcategory":"Insurance Agent",
            "type":"Services"
        }
    ],
    "sg:phone":"+1 201 797 3131",
    "sg:postcode":"07407",
    "sg:province":"NJ",
    "wof:name":"State Farm Insurance",
    "wof:placetype":"venue"
},
  "geometry": {"coordinates":[-74.11861,40.899976],"type":"Point"}
}