{
  "type": "Feature",
  "properties": {
    "addr:full":"141 Mountain Ave Somerville NJ 08876",
    "addr:housenumber":"141",
    "addr:postcode":"08876",
    "addr:street":"Mountain Ave",
    "iso:country":"US",
    "sg:address":"141 Mountain Ave",
    "sg:city":"Somerville",
    "sg:classifiers":[
        {
            "category":"Building & Trades",
            "subcategory":"Construction",
            "type":"Services"
        }
    ],
    "sg:phone":"+1 908 722 7671",
    "sg:postcode":"08876",
    "sg:province":"NJ",
    "sg:tags":[
        "house"
    ],
    "wof:name":"Pernini Construction",
    "wof:placetype":"venue"
},
  "geometry": {"coordinates":[-74.61947499999999,40.576124],"type":"Point"}
}