{
  "type": "Feature",
  "properties": {
    "iso:country":"US",
    "sg:address":"24 New St",
    "sg:city":"Metuchen",
    "sg:classifiers":[
        {
            "category":"Retail",
            "subcategory":"Laundry & Dry Cleaning",
            "type":"Services"
        }
    ],
    "sg:phone":"+1   ",
    "sg:postcode":"08840",
    "sg:province":"NJ",
    "sg:tags":[
        "drycleaning",
        "plant"
    ],
    "wof:name":"New Pearl Cleaners",
    "wof:placetype":"venue"
},
  "geometry": {"coordinates":[-74.361625,40.541906],"type":"Point"}
}