{
  "type": "Feature",
  "properties": {
    "iso:country":"US",
    "sg:address":"51 New Brunswick Ave",
    "sg:city":"Perth Amboy",
    "sg:classifiers":[
        {
            "category":"Building & Trades",
            "subcategory":"Electrical",
            "type":"Services"
        }
    ],
    "sg:phone":"+1 732 826 6811",
    "sg:postcode":"08861",
    "sg:province":"NJ",
    "sg:tags":[
        "electrician"
    ],
    "wof:name":"M-P Electrical Contractors Inc",
    "wof:placetype":"venue"
},
  "geometry": {"coordinates":[-74.292,40.522999],"type":"Point"}
}