{
  "type": "Feature",
  "properties": {
    "addr:full":"311 Ocean Ave Jersey City NJ 07305",
    "addr:housenumber":"311",
    "addr:postcode":"07305",
    "addr:street":"Ocean Ave",
    "iso:country":"US",
    "sg:address":"311 Ocean Ave",
    "sg:city":"Jersey City",
    "sg:classifiers":[
        {
            "category":"Shopping",
            "subcategory":"Florist",
            "type":"Retail Goods"
        }
    ],
    "sg:phone":"+1 201 433 0205",
    "sg:postcode":"07305",
    "sg:province":"NJ",
    "sg:website":"www.entenmannsflorist.com",
    "wof:name":"Entenmann's Florist",
    "wof:placetype":"venue"
},
  "geometry": {"coordinates":[-74.086871,40.698111],"type":"Point"}
}