{
  "type": "Feature",
  "properties": {
    "addr:full":"268 S Finley Ave Basking Ridge NJ 07920",
    "addr:housenumber":"268",
    "addr:postcode":"07920",
    "addr:street":"S Finley Ave",
    "iso:country":"US",
    "sg:address":"268 S Finley Ave",
    "sg:city":"Basking Ridge",
    "sg:classifiers":[
        {
            "category":"Government",
            "subcategory":"Office",
            "type":"Public Place"
        }
    ],
    "sg:phone":"+1 908 696 9556",
    "sg:postcode":"07920",
    "sg:province":"NJ",
    "sg:tags":[
        "village"
    ],
    "wof:name":"Bernards Township Educ Assoc",
    "wof:placetype":"venue"
},
  "geometry": {"coordinates":[-74.54931500000001,40.694261],"type":"Point"}
}