{
  "type": "Feature",
  "properties": {
    "addr:full":"222 Clements Bridge Rd Barrington NJ 08007",
    "addr:housenumber":"222",
    "addr:postcode":"08007",
    "addr:street":"Clements Bridge Rd",
    "iso:country":"US",
    "sg:address":"222 Clements Bridge Rd",
    "sg:city":"Barrington",
    "sg:classifiers":[
        {
            "category":"Professional",
            "type":"Services"
        }
    ],
    "sg:phone":"+1   ",
    "sg:postcode":"08007",
    "sg:province":"NJ",
    "wof:name":"United Bioscience",
    "wof:placetype":"venue"
},
  "geometry": {"coordinates":[-75.05175199999999,39.87129],"type":"Point"}
}