{
  "type": "Feature",
  "properties": {
    "addr:full":"1438 Dunn Pkwy Mountainside NJ 07092",
    "addr:housenumber":"1438",
    "addr:postcode":"07092",
    "addr:street":"Dunn Pkwy",
    "iso:country":"US",
    "sg:address":"1438 Dunn Pkwy",
    "sg:city":"Mountainside",
    "sg:classifiers":[
        {
            "category":"Professional",
            "subcategory":"Business Services",
            "type":"Services"
        }
    ],
    "sg:phone":"+1   ",
    "sg:postcode":"07092",
    "sg:province":"NJ",
    "wof:name":"K4 Enterprises LLC",
    "wof:placetype":"venue"
},
  "geometry": {"coordinates":[-74.358031,40.670175],"type":"Point"}
}