{
  "type": "Feature",
  "properties": {
    "iso:country":"US",
    "sg:address":"33 Passaic St",
    "sg:city":"Garfield",
    "sg:classifiers":[
        {
            "category":"Autos & Motor Vehicles",
            "subcategory":"Fuel & Gas Station",
            "type":"Retail Goods"
        }
    ],
    "sg:phone":"+1   ",
    "sg:postcode":"07026",
    "sg:province":"NJ",
    "sg:tags":[
        "station"
    ],
    "wof:name":"Mazzo Oil Co Inc",
    "wof:placetype":"venue"
},
  "geometry": {"coordinates":[-74.107564,40.86582],"type":"Point"}
}