{
  "type": "Feature",
  "properties": {
    "iso:country":"US",
    "sg:address":"111 Elizabeth Ave",
    "sg:city":"Toms River",
    "sg:classifiers":[
        {
            "category":"Building & Trades",
            "subcategory":"Construction",
            "type":"Services"
        }
    ],
    "sg:phone":"+1 732 288 9634",
    "sg:postcode":"08753",
    "sg:province":"NJ",
    "sg:tags":[
        "hanging",
        "contractor"
    ],
    "wof:name":"Different Strokes Inc",
    "wof:placetype":"venue"
},
  "geometry": {"coordinates":[-74.14591900000001,39.947719],"type":"Point"}
}