{
  "type": "Feature",
  "properties": {
    "addr:full":"201 Laurel Rd Voorhees NJ 08043",
    "addr:housenumber":"201",
    "addr:postcode":"08043",
    "addr:street":"Laurel Rd",
    "iso:country":"US",
    "sg:address":"201 Laurel Rd",
    "sg:city":"Voorhees",
    "sg:classifiers":[
        {
            "category":"Shopping",
            "subcategory":"Jewelry",
            "type":"Retail Goods"
        }
    ],
    "sg:phone":"+1   ",
    "sg:postcode":"08043",
    "sg:province":"NJ",
    "wof:name":"Zales Jewelers",
    "wof:placetype":"venue"
},
  "geometry": {"coordinates":[-75.001893,39.848307],"type":"Point"}
}