{
  "type": "Feature",
  "properties": {
    "addr:full":"550 New York Ave Lyndhurst NJ 07071",
    "addr:housenumber":"550",
    "addr:postcode":"07071",
    "addr:street":"New York Ave",
    "iso:country":"US",
    "sg:address":"550 New York Ave",
    "sg:city":"Lyndhurst",
    "sg:classifiers":[
        {
            "category":"Personal",
            "subcategory":"Beauty Salon",
            "type":"Services"
        }
    ],
    "sg:phone":"+1 201 372 0078",
    "sg:postcode":"07071",
    "sg:province":"NJ",
    "sg:tags":[
        "nail",
        "shop"
    ],
    "wof:name":"Garden Nails One",
    "wof:placetype":"venue"
},
  "geometry": {"coordinates":[-74.118797,40.813],"type":"Point"}
}