{
  "type": "Feature",
  "properties": {
    "addr:full":"110 16th Ave Newark NJ 07103",
    "addr:housenumber":"110",
    "addr:postcode":"07103",
    "addr:street":"16Th Ave",
    "iso:country":"US",
    "sg:address":"110 16th Ave",
    "sg:city":"Newark",
    "sg:classifiers":[
        {
            "category":"Organizations",
            "subcategory":"Non-profit Organization",
            "type":"Services"
        }
    ],
    "sg:phone":"+1 973 642 4018",
    "sg:postcode":"07103",
    "sg:province":"NJ",
    "wof:name":"St Ann's Comm Day Care Ctr",
    "wof:placetype":"venue"
},
  "geometry": {"coordinates":[-74.199136,40.734797],"type":"Point"}
}