{
  "type": "Feature",
  "properties": {
    "iso:country":"US",
    "sg:address":"170 Ridgedale Ave",
    "sg:city":"Madison",
    "sg:classifiers":[
        {
            "category":"Education",
            "subcategory":"School",
            "type":"Public Place"
        }
    ],
    "sg:phone":"+1 973 593 3117",
    "sg:postcode":"07940",
    "sg:province":"NJ",
    "sg:tags":[
        "high",
        "middle",
        "elementary"
    ],
    "wof:name":"Madison Borough of",
    "wof:placetype":"venue"
},
  "geometry": {"coordinates":[-74.40707399999999,40.769607],"type":"Point"}
}