{
  "type": "Feature",
  "properties": {
    "addr:full":"860 US Hwy 1 Edison NJ 08817",
    "addr:housenumber":"860",
    "addr:postcode":"08817",
    "addr:street":"Us Hwy 1",
    "iso:country":"US",
    "sg:address":"860 US Hwy 1",
    "sg:city":"Edison",
    "sg:classifiers":[
        {
            "category":"Banks & Credit Unions",
            "subcategory":"Bank",
            "type":"Services"
        }
    ],
    "sg:phone":"+1 732 287 8797",
    "sg:postcode":"08817",
    "sg:province":"NJ",
    "sg:tags":[
        "loan",
        "real estate"
    ],
    "wof:name":"DJM Home Lending Group",
    "wof:placetype":"venue"
},
  "geometry": {"coordinates":[-74.375823,40.514663],"type":"Point"}
}