{
  "type": "Feature",
  "properties": {
    "addr:full":"2120 McCarter Hwy Newark NJ 07104",
    "addr:housenumber":"2120",
    "addr:postcode":"07104",
    "addr:street":"Mccarter Hwy",
    "iso:country":"US",
    "sg:address":"2120 McCarter Hwy",
    "sg:city":"Newark",
    "sg:classifiers":[
        {
            "category":"Building & Trades",
            "subcategory":"Locksmith",
            "type":"Services"
        }
    ],
    "sg:phone":"+1 973 854 4799",
    "sg:postcode":"07104",
    "sg:province":"NJ",
    "sg:tags":[
        "key"
    ],
    "wof:name":"0 24 Hour 7 A Day Emerg Locksmith",
    "wof:placetype":"venue"
},
  "geometry": {"coordinates":[-74.151543,40.778466],"type":"Point"}
}