{
  "type": "Feature",
  "properties": {
    "iso:country":"US",
    "sg:address":"6011 Bergenline Pl",
    "sg:city":"West New York",
    "sg:classifiers":[
        {
            "category":"Shopping",
            "type":"Retail Goods"
        }
    ],
    "sg:phone":"+1   ",
    "sg:postcode":"07093",
    "sg:province":"NJ",
    "sg:tags":[
        "merchandise"
    ],
    "wof:name":"Bergen Wireless Corp",
    "wof:placetype":"venue"
},
  "geometry": {"coordinates":[-74.01577899999999,40.789679],"type":"Point"}
}