{
  "type": "Feature",
  "properties": {
    "addr:full":"8 Fieldstone Way Moorestown NJ 08057",
    "addr:housenumber":"8",
    "addr:postcode":"08057",
    "addr:street":"Fieldstone Way",
    "iso:country":"US",
    "sg:address":"8 Fieldstone Way",
    "sg:city":"Moorestown",
    "sg:classifiers":[
        {
            "category":"Professional",
            "type":"Services"
        }
    ],
    "sg:phone":"+1   ",
    "sg:postcode":"08057",
    "sg:province":"NJ",
    "wof:name":"Fieldstone Paralegal Services",
    "wof:placetype":"venue"
},
  "geometry": {"coordinates":[-74.91663800000001,39.986937],"type":"Point"}
}