{
  "type": "Feature",
  "properties": {
    "iso:country":"US",
    "sg:address":"1575 W Wheat Rd",
    "sg:city":"Vineland",
    "sg:classifiers":[
        {
            "category":"Retail",
            "subcategory":"Repair Shop",
            "type":"Services"
        }
    ],
    "sg:phone":"+1   ",
    "sg:postcode":"08360",
    "sg:province":"NJ",
    "wof:name":"Advanced Polymer Repairs Corp",
    "wof:placetype":"venue"
},
  "geometry": {"coordinates":[-75.05229,39.511052],"type":"Point"}
}