{
  "type": "Feature",
  "properties": {
    "iso:country":"US",
    "sg:address":"187 Washington Ave",
    "sg:city":"Fort Lee",
    "sg:classifiers":[
        {
            "category":"Recreation",
            "type":"Entertainment"
        }
    ],
    "sg:phone":"+1 201 944 0612",
    "sg:postcode":"07024",
    "sg:province":"NJ",
    "wof:name":"Applied Martial Art Concepts",
    "wof:placetype":"venue"
},
  "geometry": {"coordinates":[-73.961637,40.864019],"type":"Point"}
}