{
  "type": "Feature",
  "properties": {
    "addr:full":"652 Hyson Rd Jackson NJ 08527",
    "addr:housenumber":"652",
    "addr:postcode":"08527",
    "addr:street":"Hyson Rd",
    "iso:country":"US",
    "sg:address":"652 Hyson Rd",
    "sg:city":"Jackson",
    "sg:classifiers":[
        {
            "category":"Food & Beverages",
            "subcategory":"Specialty",
            "type":"Retail Goods"
        }
    ],
    "sg:phone":"+1   ",
    "sg:postcode":"08527",
    "sg:province":"NJ",
    "wof:name":"All Ways For Health",
    "wof:placetype":"venue"
},
  "geometry": {"coordinates":[-74.297731,40.151731],"type":"Point"}
}