{
  "type": "Feature",
  "properties": {
    "iso:country":"US",
    "sg:address":"702 Main St",
    "sg:city":"Bradley Beach",
    "sg:classifiers":[
        {
            "category":"Food & Beverages",
            "subcategory":"Groceries & Convenience Stores",
            "type":"Retail Goods"
        }
    ],
    "sg:phone":"+1 732 869 9898",
    "sg:postcode":"07720",
    "sg:province":"NJ",
    "sg:tags":[
        "market"
    ],
    "wof:name":"Gonzalez Grocery III",
    "wof:placetype":"venue"
},
  "geometry": {"coordinates":[-74.01717600000001,40.205042],"type":"Point"}
}