{
  "type": "Feature",
  "properties": {
    "iso:country":"US",
    "sg:address":"8 Northridge Rd",
    "sg:city":"Flemington",
    "sg:classifiers":[
        {
            "category":"Building & Trades",
            "subcategory":"Construction",
            "type":"Services"
        }
    ],
    "sg:phone":"+1 908 284 1896",
    "sg:postcode":"08822",
    "sg:province":"NJ",
    "sg:tags":[
        "contractor"
    ],
    "wof:name":"Custom Window Treatments Inc",
    "wof:placetype":"venue"
},
  "geometry": {"coordinates":[-74.864127,40.539997],"type":"Point"}
}