{
  "type": "Feature",
  "properties": {
    "addr:full":"130 Morristown Rd Bernardsville NJ 07924",
    "addr:housenumber":"130",
    "addr:postcode":"07924",
    "addr:street":"Morristown Rd",
    "iso:country":"US",
    "sg:address":"130 Morristown Rd",
    "sg:city":"Bernardsville",
    "sg:classifiers":[
        {
            "category":"Retail",
            "subcategory":"Self-service Laundry",
            "type":"Services"
        },
        {
            "category":"Retail",
            "subcategory":"Laundry & Dry Cleaning",
            "type":"Services"
        }
    ],
    "sg:phone":"+1 908 766 6404",
    "sg:postcode":"07924",
    "sg:province":"NJ",
    "sg:tags":[
        "cleaners"
    ],
    "wof:name":"Linder's French Cleaners",
    "wof:placetype":"venue"
},
  "geometry": {"coordinates":[-74.560462,40.719944],"type":"Point"}
}