{
  "type": "Feature",
  "properties": {
    "addr:full":"575 Kingsland St Nutley NJ 07110",
    "addr:housenumber":"575",
    "addr:postcode":"07110",
    "addr:street":"Kingsland St",
    "iso:country":"US",
    "sg:address":"575 Kingsland St",
    "sg:city":"Nutley",
    "sg:classifiers":[
        {
            "category":"Professional",
            "subcategory":"Lawyer & Legal Services",
            "type":"Services"
        }
    ],
    "sg:phone":"+1 973 680 9900",
    "sg:postcode":"07110",
    "sg:province":"NJ",
    "wof:name":"Bianchi Angelo R Attorney",
    "wof:placetype":"venue"
},
  "geometry": {"coordinates":[-74.16280399999999,40.836399],"type":"Point"}
}