{
  "type": "Feature",
  "properties": {
    "iso:country":"US",
    "sg:address":"675 Hudson Ave",
    "sg:city":"Secaucus",
    "sg:classifiers":[
        {
            "category":"Building & Trades",
            "subcategory":"Cleaning & Sanitation",
            "type":"Services"
        },
        {
            "category":"Wholesale",
            "subcategory":"Construction Materials",
            "type":"Manufacturing & Wholesale Goods"
        },
        {
            "category":"Home & Garden",
            "subcategory":"Building Materials",
            "type":"Retail Goods"
        },
        {
            "category":"Building & Trades",
            "subcategory":"Construction",
            "type":"Services"
        }
    ],
    "sg:phone":"+1 201 866 0488",
    "sg:postcode":"07094",
    "sg:province":"NJ",
    "sg:tags":[
        "terrazzo",
        "supply",
        "top",
        "counter",
        "tile-cleaning",
        "contractor",
        "equipment",
        "cleaning-industrial",
        "janitorial",
        "sealing",
        "mason",
        "masonry",
        "marble",
        "refinishing"
    ],
    "sg:website":"http://www.marblerenewalofnj.com",
    "wof:name":"Marble Renewal",
    "wof:placetype":"venue"
},
  "geometry": {"coordinates":[-74.067853,40.791421],"type":"Point"}
}