{
  "type": "Feature",
  "properties": {
    "addr:full":"53 Povershon Rd Nutley NJ 07110",
    "addr:housenumber":"53",
    "addr:postcode":"07110",
    "addr:street":"Povershon Rd",
    "iso:country":"US",
    "sg:address":"53 Povershon Rd",
    "sg:city":"Nutley",
    "sg:classifiers":[
        {
            "category":"Building & Trades",
            "subcategory":"Locksmith",
            "type":"Services"
        }
    ],
    "sg:phone":"+1 973 847 6123",
    "sg:postcode":"07110",
    "sg:province":"NJ",
    "sg:tags":[
        "key"
    ],
    "wof:name":"Nutley 24 Hour An Emergency A Locksmith",
    "wof:placetype":"venue"
},
  "geometry": {"coordinates":[-74.170067,40.820995],"type":"Point"}
}