{
  "type": "Feature",
  "properties": {
    "iso:country":"US",
    "sg:address":"966 US Hwy 22",
    "sg:city":"Bridgewater",
    "sg:classifiers":[
        {
            "category":"Restaurant",
            "type":"Food & Drink"
        }
    ],
    "sg:phone":"+1   ",
    "sg:postcode":"08807",
    "sg:province":"NJ",
    "sg:tags":[
        "eating"
    ],
    "wof:name":"La Catena Restaurant Inc",
    "wof:placetype":"venue"
},
  "geometry": {"coordinates":[-74.606737,40.580352],"type":"Point"}
}