{
  "type": "Feature",
  "properties": {
    "addr:full":"118 Washington St Toms River NJ 08753",
    "addr:housenumber":"118",
    "addr:postcode":"08753",
    "addr:street":"Washington St",
    "iso:country":"US",
    "sg:address":"118 Washington St",
    "sg:city":"Toms River",
    "sg:classifiers":[
        {
            "category":"Education",
            "subcategory":"Library",
            "type":"Public Place"
        }
    ],
    "sg:phone":"+1 732 506 5026",
    "sg:postcode":"08753",
    "sg:province":"NJ",
    "sg:tags":[
        "special",
        "interest"
    ],
    "wof:name":"Ocean County Law Library",
    "wof:placetype":"venue"
},
  "geometry": {"coordinates":[-74.19491600000001,39.952698],"type":"Point"}
}