{
  "type": "Feature",
  "properties": {
    "iso:country":"US",
    "sg:address":"64 Broad St",
    "sg:city":"Elizabeth",
    "sg:classifiers":[
        {
            "category":"Personal",
            "subcategory":"Beauty Salon",
            "type":"Services"
        }
    ],
    "sg:phone":"+1   ",
    "sg:postcode":"07201",
    "sg:province":"NJ",
    "sg:tags":[
        "shop"
    ],
    "wof:name":"Hair Braiding Salon",
    "wof:placetype":"venue"
},
  "geometry": {"coordinates":[-74.21484,40.664773],"type":"Point"}
}