{
  "type": "Feature",
  "properties": {
    "iso:country":"US",
    "sg:address":"51 Wehrli Rd",
    "sg:city":"Long Valley",
    "sg:classifiers":[
        {
            "category":"Building & Trades",
            "subcategory":"Construction",
            "type":"Services"
        }
    ],
    "sg:phone":"+1 908 876 4373",
    "sg:postcode":"07853",
    "sg:province":"NJ",
    "sg:tags":[
        "contractor"
    ],
    "wof:name":"Turick Contractors",
    "wof:placetype":"venue"
},
  "geometry": {"coordinates":[-74.814572,40.790452],"type":"Point"}
}