{
  "type": "Feature",
  "properties": {
    "addr:full":"66 E Main St Little Falls NJ 07424",
    "addr:housenumber":"66",
    "addr:postcode":"07424",
    "addr:street":"E Main St",
    "iso:country":"US",
    "sg:address":"66 E Main St",
    "sg:city":"Little Falls",
    "sg:classifiers":[
        {
            "category":"Food & Beverages",
            "subcategory":"Groceries & Convenience Stores",
            "type":"Retail Goods"
        }
    ],
    "sg:phone":"+1 973 785 0957",
    "sg:postcode":"07424",
    "sg:province":"NJ",
    "sg:tags":[
        "product"
    ],
    "wof:name":"VMK Ices Inc",
    "wof:placetype":"venue"
},
  "geometry": {"coordinates":[-74.21969199999999,40.878277],"type":"Point"}
}