{
  "type": "Feature",
  "properties": {
    "iso:country":"US",
    "sg:address":"725 S Main St",
    "sg:city":"Forked River",
    "sg:classifiers":[
        {
            "category":"Personal",
            "subcategory":"Beauty Salon",
            "type":"Services"
        }
    ],
    "sg:phone":"+1 609 693 4418",
    "sg:postcode":"08731",
    "sg:province":"NJ",
    "wof:name":"Jade Hair & Nail",
    "wof:placetype":"venue"
},
  "geometry": {"coordinates":[-74.20244099999999,39.823011],"type":"Point"}
}