{
  "type": "Feature",
  "properties": {
    "addr:full":"1300 Middle Ave Waterford Works NJ 08089",
    "addr:housenumber":"1300",
    "addr:postcode":"08089",
    "addr:street":"Middle Ave",
    "iso:country":"US",
    "sg:address":"1300 Middle Ave",
    "sg:city":"Waterford Works",
    "sg:classifiers":[
        {
            "category":"Building & Trades",
            "subcategory":"Construction",
            "type":"Services"
        }
    ],
    "sg:phone":"+1 856 767 2555",
    "sg:postcode":"08089",
    "sg:province":"NJ",
    "sg:tags":[
        "carpentry",
        "contractor"
    ],
    "wof:name":"J M Megnin Inc",
    "wof:placetype":"venue"
},
  "geometry": {"coordinates":[-74.82768900000001,39.72491],"type":"Point"}
}