{
  "type": "Feature",
  "properties": {
    "addr:full":"136 Steuben St Jersey City NJ 07302",
    "addr:housenumber":"136",
    "addr:postcode":"07302",
    "addr:street":"Steuben St",
    "iso:country":"US",
    "sg:address":"136 Steuben St",
    "sg:city":"Jersey City",
    "sg:classifiers":[
        {
            "category":"Wholesale",
            "subcategory":"Books, Periodicals, & Newspapers",
            "type":"Manufacturing & Wholesale Goods"
        }
    ],
    "sg:phone":"+1 201 432 1293",
    "sg:postcode":"07302",
    "sg:province":"NJ",
    "sg:tags":[
        "mainland",
        "china"
    ],
    "wof:name":"Waymont Book Company",
    "wof:placetype":"venue"
},
  "geometry": {"coordinates":[-74.040998,40.719784],"type":"Point"}
}