{
  "type": "Feature",
  "properties": {
    "iso:country":"US",
    "sg:address":"800 N Massachusetts Ave",
    "sg:city":"Atlantic City",
    "sg:classifiers":[
        {
            "category":"Bars & Pubs",
            "type":"Food & Drink"
        }
    ],
    "sg:phone":"+1   ",
    "sg:postcode":"08401",
    "sg:province":"NJ",
    "sg:tags":[
        "tavern"
    ],
    "wof:name":"Moving & Storage",
    "wof:placetype":"venue"
},
  "geometry": {"coordinates":[-74.42336899999999,39.375938],"type":"Point"}
}