{
  "type": "Feature",
  "properties": {
    "addr:full":"53 Woodland Ave Rochelle Park NJ 07662",
    "addr:housenumber":"53",
    "addr:postcode":"07662",
    "addr:street":"Woodland Ave",
    "iso:country":"US",
    "sg:address":"53 Woodland Ave",
    "sg:city":"Rochelle Park",
    "sg:classifiers":[
        {
            "category":"Personal",
            "type":"Services"
        }
    ],
    "sg:phone":"+1 201 368 0058",
    "sg:postcode":"07662",
    "sg:province":"NJ",
    "sg:tags":[
        "massage"
    ],
    "wof:name":"Fuji Salon",
    "wof:placetype":"venue"
},
  "geometry": {"coordinates":[-74.072197,40.901402],"type":"Point"}
}