{
  "type": "Feature",
  "properties": {
    "iso:country":"US",
    "sg:address":"447 State Rte 10",
    "sg:city":"Randolph",
    "sg:classifiers":[
        {
            "category":"Professional",
            "subcategory":"Business Services",
            "type":"Services"
        },
        {
            "category":"Professional",
            "subcategory":"Accounting & Tax Preparation",
            "type":"Services"
        }
    ],
    "sg:phone":"+1 973 328 9001",
    "sg:postcode":"07869",
    "sg:province":"NJ",
    "sg:tags":[
        "accountant"
    ],
    "wof:name":"Yachmetz & Yachmetz",
    "wof:placetype":"venue"
},
  "geometry": {"coordinates":[-74.564685,40.862825],"type":"Point"}
}