{
  "type": "Feature",
  "properties": {
    "addr:full":"462 3rd Ave Elizabeth NJ 07206",
    "addr:housenumber":"462",
    "addr:postcode":"07206",
    "addr:street":"3Rd Ave",
    "iso:country":"US",
    "sg:address":"462 3rd Ave",
    "sg:city":"Elizabeth",
    "sg:classifiers":[
        {
            "category":"Autos & Motor Vehicles",
            "subcategory":"Auto Supplies",
            "type":"Retail Goods"
        }
    ],
    "sg:phone":"+1 908 352 6355",
    "sg:postcode":"07206",
    "sg:province":"NJ",
    "sg:tags":[
        "tire"
    ],
    "wof:name":"Firestone Tires of Elizabeth",
    "wof:placetype":"venue"
},
  "geometry": {"coordinates":[-74.20259900000001,40.651699],"type":"Point"}
}