{
  "type": "Feature",
  "properties": {
    "addr:full":"409 Martin Luther King Dr Lakewood NJ 08701",
    "addr:housenumber":"409",
    "addr:postcode":"08701",
    "addr:street":"Martin Luther King Dr",
    "iso:country":"US",
    "sg:address":"409 Martin Luther King Dr",
    "sg:city":"Lakewood",
    "sg:classifiers":[
        {
            "category":"Professional",
            "type":"Services"
        }
    ],
    "sg:phone":"+1 732 905 0500",
    "sg:postcode":"08701",
    "sg:province":"NJ",
    "sg:tags":[
        "establishment"
    ],
    "wof:name":"Oxford Coverage",
    "wof:placetype":"venue"
},
  "geometry": {"coordinates":[-74.211376,40.079545],"type":"Point"}
}