{
  "type": "Feature",
  "properties": {
    "iso:country":"US",
    "sg:address":"90 Hudson St",
    "sg:city":"Jersey City",
    "sg:classifiers":[
        {
            "category":"Banks & Credit Unions",
            "subcategory":"Investment Brokerage",
            "type":"Services"
        }
    ],
    "sg:phone":"+1 201 209 7000",
    "sg:postcode":"07302",
    "sg:province":"NJ",
    "sg:tags":[
        "security"
    ],
    "wof:name":"National Discount Brokers",
    "wof:placetype":"venue"
},
  "geometry": {"coordinates":[-74.034176,40.715203],"type":"Point"}
}