{
  "type": "Feature",
  "properties": {
    "addr:full":"246 S Main St Pennington NJ 08534",
    "addr:housenumber":"246",
    "addr:postcode":"08534",
    "addr:street":"S Main St",
    "iso:country":"US",
    "sg:address":"246 S Main St",
    "sg:city":"Pennington",
    "sg:classifiers":[
        {
            "category":"Organizations",
            "subcategory":"Religious Organization",
            "type":"Services"
        }
    ],
    "sg:phone":"+1 609 737 0922",
    "sg:postcode":"08534",
    "sg:province":"NJ",
    "wof:name":"Bethel AME Church",
    "wof:placetype":"venue"
},
  "geometry": {"coordinates":[-74.790526,40.322444],"type":"Point"}
}