{
  "type": "Feature",
  "properties": {
    "iso:country":"US",
    "sg:address":"557 Clinton Ave",
    "sg:city":"Newark",
    "sg:classifiers":[
        {
            "category":"Restaurant",
            "type":"Food & Drink"
        }
    ],
    "sg:phone":"+1   ",
    "sg:postcode":"07108",
    "sg:province":"NJ",
    "sg:tags":[
        "eating"
    ],
    "wof:name":"Shakey Hut LLC",
    "wof:placetype":"venue"
},
  "geometry": {"coordinates":[-74.204182,40.722302],"type":"Point"}
}