{
  "type": "Feature",
  "properties": {
    "iso:country":"US",
    "sg:address":"525 Gregory Ave",
    "sg:city":"Weehawken",
    "sg:classifiers":[
        {
            "category":"Social Services",
            "subcategory":"Adult Care",
            "type":"Services"
        }
    ],
    "sg:phone":"+1 201 330 7634",
    "sg:postcode":"07086",
    "sg:province":"NJ",
    "sg:tags":[
        "organization",
        "senior",
        "citizen"
    ],
    "wof:name":"Senior Nutritional Program",
    "wof:placetype":"venue"
},
  "geometry": {"coordinates":[-74.025412,40.766454],"type":"Point"}
}