{
  "type": "Feature",
  "properties": {
    "iso:country":"US",
    "sg:address":"556 US Hwy 22",
    "sg:city":"Hillside",
    "sg:classifiers":[
        {
            "category":"Shopping",
            "subcategory":"Clothing, Apparel, & Fashions",
            "type":"Retail Goods"
        }
    ],
    "sg:phone":"+1 908 964 5800",
    "sg:postcode":"07205",
    "sg:province":"NJ",
    "sg:tags":[
        "uniform"
    ],
    "wof:name":"Fit Rite Uniform Co",
    "wof:placetype":"venue"
},
  "geometry": {"coordinates":[-74.242091,40.698478],"type":"Point"}
}