{
  "type": "Feature",
  "properties": {
    "iso:country":"US",
    "sg:address":"150 Main Rd",
    "sg:city":"Montville",
    "sg:classifiers":[
        {
            "category":"Autos & Motor Vehicles",
            "subcategory":"Automobile Sales",
            "type":"Retail Goods"
        }
    ],
    "sg:phone":"+1 973 299 0078",
    "sg:postcode":"07045",
    "sg:province":"NJ",
    "sg:tags":[
        "performance",
        "race",
        "dealer"
    ],
    "wof:name":"Applied Force",
    "wof:placetype":"venue"
},
  "geometry": {"coordinates":[-74.37963999999999,40.915276],"type":"Point"}
}