{
  "type": "Feature",
  "properties": {
    "addr:full":"125 Lefante Way Bayonne NJ 07002",
    "addr:housenumber":"125",
    "addr:postcode":"07002",
    "addr:street":"Lefante Way",
    "iso:country":"US",
    "sg:address":"125 Lefante Way",
    "sg:city":"Bayonne",
    "sg:classifiers":[
        {
            "category":"Bars & Pubs",
            "subcategory":"Lounge",
            "type":"Food & Drink"
        },
        {
            "category":"Restaurant",
            "type":"Food & Drink"
        }
    ],
    "sg:phone":"+1 201 437 1212",
    "sg:postcode":"07002",
    "sg:province":"NJ",
    "sg:tags":[
        "fusion",
        "asian",
        "japanese"
    ],
    "sg:website":"www.teneastdining.com",
    "wof:name":"TenEast",
    "wof:placetype":"venue"
},
  "geometry": {"coordinates":[-74.09971,40.662164],"type":"Point"}
}