{
  "type": "Feature",
  "properties": {
    "iso:country":"US",
    "sg:address":"193 Monroe Ave",
    "sg:city":"Edison",
    "sg:classifiers":[
        {
            "category":"Health Services",
            "subcategory":"Hospital",
            "type":"Services"
        }
    ],
    "sg:phone":"+1   ",
    "sg:postcode":"08820",
    "sg:province":"NJ",
    "sg:tags":[
        "general"
    ],
    "wof:name":"American Osteopathic College",
    "wof:placetype":"venue"
},
  "geometry": {"coordinates":[-74.34747900000001,40.563382],"type":"Point"}
}