{
  "type": "Feature",
  "properties": {
    "addr:full":"909 Cranford Ave Westfield NJ 07090",
    "addr:housenumber":"909",
    "addr:postcode":"07090",
    "addr:street":"Cranford Ave",
    "iso:country":"US",
    "sg:address":"909 Cranford Ave",
    "sg:city":"Westfield",
    "sg:classifiers":[
        {
            "category":"Freight",
            "type":"Transportation"
        }
    ],
    "sg:phone":"+1 908 303 1947",
    "sg:postcode":"07090",
    "sg:province":"NJ",
    "sg:tags":[
        "general"
    ],
    "wof:name":"Total Storage Concepts LLC",
    "wof:placetype":"venue"
},
  "geometry": {"coordinates":[-74.327203,40.660838],"type":"Point"}
}