{
  "type": "Feature",
  "properties": {
    "addr:full":"11 Dinallo St South Hackensack NJ 07606",
    "addr:housenumber":"11",
    "addr:postcode":"07606",
    "addr:street":"Dinallo St",
    "iso:country":"US",
    "sg:address":"11 Dinallo St",
    "sg:city":"South Hackensack",
    "sg:classifiers":[
        {
            "category":"Professional",
            "subcategory":"Lawyer & Legal Services",
            "type":"Services"
        }
    ],
    "sg:phone":"+1 201 488 1669",
    "sg:postcode":"07606",
    "sg:province":"NJ",
    "wof:name":"Andrew Nachamie Attorney",
    "wof:placetype":"venue"
},
  "geometry": {"coordinates":[-74.048818,40.870001],"type":"Point"}
}