{
  "type": "Feature",
  "properties": {
    "iso:country":"US",
    "sg:address":"532 Summit Ave",
    "sg:city":"Jersey City",
    "sg:classifiers":[
        {
            "category":"Health Services",
            "subcategory":"Doctor",
            "type":"Services"
        }
    ],
    "sg:phone":"+1 201 653 2288",
    "sg:postcode":"07306",
    "sg:province":"NJ",
    "sg:tags":[
        "dentist"
    ],
    "wof:name":"Perfect Dental Cares",
    "wof:placetype":"venue"
},
  "geometry": {"coordinates":[-74.060902,40.730834],"type":"Point"}
}