{
  "type": "Feature",
  "properties": {
    "iso:country":"US",
    "sg:address":"454 River Styx Rd",
    "sg:city":"Hopatcong",
    "sg:classifiers":[
        {
            "category":"Restaurant",
            "type":"Food & Drink"
        }
    ],
    "sg:phone":"+1 973 398 2037",
    "sg:postcode":"07843",
    "sg:province":"NJ",
    "sg:tags":[
        "eating"
    ],
    "wof:name":"Grotto Restaurante",
    "wof:placetype":"venue"
},
  "geometry": {"coordinates":[-74.655519,40.941948],"type":"Point"}
}