{
  "type": "Feature",
  "properties": {
    "iso:country":"US",
    "sg:address":"420 Boulevard",
    "sg:city":"Mountain Lakes",
    "sg:classifiers":[
        {
            "category":"Shopping",
            "subcategory":"Computers & Home Electronics",
            "type":"Retail Goods"
        }
    ],
    "sg:phone":"+1 973 263 3400",
    "sg:postcode":"07046",
    "sg:province":"NJ",
    "sg:tags":[
        "software"
    ],
    "wof:name":"Blue Chips Systems Solutions",
    "wof:placetype":"venue"
},
  "geometry": {"coordinates":[-74.457346,40.884575],"type":"Point"}
}