{
  "type": "Feature",
  "properties": {
    "addr:full":"390 Broad St Newark NJ 07104",
    "addr:housenumber":"390",
    "addr:postcode":"07104",
    "addr:street":"Broad St",
    "iso:country":"US",
    "sg:address":"390 Broad St",
    "sg:city":"Newark",
    "sg:classifiers":[
        {
            "category":"Education",
            "subcategory":"Special Training",
            "type":"Public Place"
        },
        {
            "category":"Organizations",
            "subcategory":"Non-profit Organization",
            "type":"Services"
        }
    ],
    "sg:phone":"+1 973 484 7097",
    "sg:postcode":"07104",
    "sg:province":"NJ",
    "sg:tags":[
        "educational",
        "service/non-profit",
        "community",
        "center"
    ],
    "sg:website":"www.aspira.org",
    "wof:name":"Aspira Inc of New Jersey",
    "wof:placetype":"venue"
},
  "geometry": {"coordinates":[-74.170286,40.748477],"type":"Point"}
}