{
  "type": "Feature",
  "properties": {
    "iso:country":"US",
    "sg:address":"145 Millbrook Rd",
    "sg:city":"Washington",
    "sg:classifiers":[
        {
            "category":"Building & Trades",
            "subcategory":"Plumbing",
            "type":"Services"
        }
    ],
    "sg:phone":"+1 908 689 2730",
    "sg:postcode":"07882",
    "sg:province":"NJ",
    "sg:tags":[
        "pipe",
        "line",
        "contractor"
    ],
    "wof:name":"Industrial Fiberglass Services Inc",
    "wof:placetype":"venue"
},
  "geometry": {"coordinates":[-75.061133,40.743134],"type":"Point"}
}