{
  "type": "Feature",
  "properties": {
    "iso:country":"US",
    "sg:address":"12 Stokes Rd",
    "sg:city":"Medford",
    "sg:classifiers":[
        {
            "category":"Government",
            "subcategory":"Office",
            "type":"Public Place"
        },
        {
            "category":"Government",
            "subcategory":"Fire Station",
            "type":"Public Place"
        }
    ],
    "sg:phone":"+1   ",
    "sg:postcode":"08055",
    "sg:province":"NJ",
    "sg:tags":[
        "department",
        "volunteer",
        "general"
    ],
    "wof:name":"Medford Lakes Vlntr Fire Dept",
    "wof:placetype":"venue"
},
  "geometry": {"coordinates":[-74.820257,39.883482],"type":"Point"}
}