{
  "type": "Feature",
  "properties": {
    "addr:full":"1618 Mount Ephraim Ave Camden NJ 08104",
    "addr:housenumber":"1618",
    "addr:postcode":"08104",
    "addr:street":"Mount Ephraim Ave",
    "iso:country":"US",
    "sg:address":"1618 Mount Ephraim Ave",
    "sg:city":"Camden",
    "sg:classifiers":[
        {
            "category":"Shopping",
            "subcategory":"Shoes",
            "type":"Retail Goods"
        }
    ],
    "sg:phone":"+1 856 964 2121",
    "sg:postcode":"08104",
    "sg:province":"NJ",
    "sg:tags":[
        "store"
    ],
    "wof:name":"Extreme II",
    "wof:placetype":"venue"
},
  "geometry": {"coordinates":[-75.105301,39.9245],"type":"Point"}
}