{
  "type": "Feature",
  "properties": {
    "addr:full":"15 Garden View Ter Fair Lawn NJ 07410",
    "addr:housenumber":"15",
    "addr:postcode":"07410",
    "addr:street":"Garden View Ter",
    "iso:country":"US",
    "sg:address":"15 Garden View Ter",
    "sg:city":"Fair Lawn",
    "sg:classifiers":[
        {
            "category":"Freight",
            "type":"Transportation"
        }
    ],
    "sg:phone":"+1 201 797 0329",
    "sg:postcode":"07410",
    "sg:province":"NJ",
    "sg:tags":[
        "arrangement"
    ],
    "wof:name":"Hawk International Shipping",
    "wof:placetype":"venue"
},
  "geometry": {"coordinates":[-74.105947,40.94213],"type":"Point"}
}