{
  "type": "Feature",
  "properties": {
    "addr:full":"9 Hale Pl Fair Lawn NJ 07410",
    "addr:housenumber":"9",
    "addr:postcode":"07410",
    "addr:street":"Hale Pl",
    "iso:country":"US",
    "sg:address":"9 Hale Pl",
    "sg:city":"Fair Lawn",
    "sg:classifiers":[
        {
            "category":"Building & Trades",
            "subcategory":"Electrical",
            "type":"Services"
        }
    ],
    "sg:phone":"+1 201 791 4428",
    "sg:postcode":"07410",
    "sg:province":"NJ",
    "sg:tags":[
        "electric",
        "contractor"
    ],
    "wof:name":"Bison Electric Inc",
    "wof:placetype":"venue"
},
  "geometry": {"coordinates":[-74.104837,40.941129],"type":"Point"}
}