{
  "type": "Feature",
  "properties": {
    "iso:country":"US",
    "sg:address":"1224 Shipyard Ln",
    "sg:city":"Hoboken",
    "sg:classifiers":[
        {
            "category":"Food & Beverages",
            "subcategory":"Liquor & Beverages",
            "type":"Retail Goods"
        }
    ],
    "sg:phone":"+1 201 659 1501",
    "sg:postcode":"07030",
    "sg:province":"NJ",
    "sg:tags":[
        "beer",
        "spirit",
        "wine"
    ],
    "sg:website":"www.sparrowine.com",
    "wof:name":"Sparrow Wines & Liquiors",
    "wof:placetype":"venue"
},
  "geometry": {"coordinates":[-74.024992,40.75106],"type":"Point"}
}