{
  "type": "Feature",
  "properties": {
    "addr:full":"2176 State Rte 35 Sea Girt NJ 08750",
    "addr:housenumber":"2176",
    "addr:postcode":"08750",
    "addr:street":"State Rte 35",
    "iso:country":"US",
    "sg:address":"2176 State Rte 35",
    "sg:city":"Sea Girt",
    "sg:classifiers":[
        {
            "category":"Shopping",
            "subcategory":"Computers & Home Electronics",
            "type":"Retail Goods"
        }
    ],
    "sg:phone":"+1 732 223 3339",
    "sg:postcode":"08750",
    "sg:province":"NJ",
    "sg:tags":[
        "equipment",
        "electronic",
        "supply"
    ],
    "sg:website":"www.radioshack.com",
    "wof:name":"Radio Shack",
    "wof:placetype":"venue"
},
  "geometry": {"coordinates":[-74.0635,40.135928],"type":"Point"}
}