{
  "type": "Feature",
  "properties": {
    "addr:full":"121 Red Twig Trl Bloomingdale NJ 07403",
    "addr:housenumber":"121",
    "addr:postcode":"07403",
    "addr:street":"Red Twig Trl",
    "iso:country":"US",
    "sg:address":"121 Red Twig Trl",
    "sg:city":"Bloomingdale",
    "sg:classifiers":[
        {
            "category":"Retail",
            "subcategory":"Photofinishing",
            "type":"Services"
        }
    ],
    "sg:phone":"+1   ",
    "sg:postcode":"07403",
    "sg:province":"NJ",
    "sg:tags":[
        "laboratory"
    ],
    "wof:name":"Photo Life Inc",
    "wof:placetype":"venue"
},
  "geometry": {"coordinates":[-74.340699,41.021526],"type":"Point"}
}