{
  "type": "Feature",
  "properties": {
    "addr:full":"32 Olmstead Rd Morristown NJ 07960",
    "addr:housenumber":"32",
    "addr:postcode":"07960",
    "addr:street":"Olmstead Rd",
    "iso:country":"US",
    "sg:address":"32 Olmstead Rd",
    "sg:city":"Morristown",
    "sg:classifiers":[
        {
            "category":"Professional",
            "subcategory":"Employment Agencies",
            "type":"Services"
        }
    ],
    "sg:phone":"+1 973 734 0650",
    "sg:postcode":"07960",
    "sg:province":"NJ",
    "sg:tags":[
        "consultant",
        "search",
        "executive"
    ],
    "wof:name":"Integrated Employment Svc",
    "wof:placetype":"venue"
},
  "geometry": {"coordinates":[-74.457655,40.794464],"type":"Point"}
}