{
  "type": "Feature",
  "properties": {
    "iso:country":"US",
    "sg:address":"760 Fairfield Ave",
    "sg:city":"Kenilworth",
    "sg:classifiers":[
        {
            "category":"Building & Trades",
            "subcategory":"Electrical",
            "type":"Services"
        }
    ],
    "sg:phone":"+1   ",
    "sg:postcode":"07033",
    "sg:province":"NJ",
    "sg:tags":[
        "security",
        "electrical",
        "system",
        "contractor"
    ],
    "wof:name":"Firemaster",
    "wof:placetype":"venue"
},
  "geometry": {"coordinates":[-74.280141,40.669466],"type":"Point"}
}