{
  "type": "Feature",
  "properties": {
    "addr:full":"23 Lake Wallkill Rd Sussex NJ 07461",
    "addr:housenumber":"23",
    "addr:postcode":"07461",
    "addr:street":"Lake Wallkill Rd",
    "iso:country":"US",
    "sg:address":"23 Lake Wallkill Rd",
    "sg:city":"Sussex",
    "sg:classifiers":[
        {
            "category":"Building & Trades",
            "subcategory":"Construction",
            "type":"Services"
        }
    ],
    "sg:phone":"+1 973 875 8910",
    "sg:postcode":"07461",
    "sg:province":"NJ",
    "sg:tags":[
        "house"
    ],
    "wof:name":"Wallkill Ridge Construction Co",
    "wof:placetype":"venue"
},
  "geometry": {"coordinates":[-74.550169,41.216397],"type":"Point"}
}