{
  "type": "Feature",
  "properties": {
    "iso:country":"US",
    "sg:address":"477 Amwell Rd",
    "sg:city":"Hillsborough",
    "sg:classifiers":[
        {
            "category":"Professional",
            "type":"Services"
        }
    ],
    "sg:phone":"+1   ",
    "sg:postcode":"08844",
    "sg:province":"NJ",
    "wof:name":"Karen L Drewes",
    "wof:placetype":"venue"
},
  "geometry": {"coordinates":[-74.658137,40.497837],"type":"Point"}
}