{
  "type": "Feature",
  "properties": {
    "addr:full":"629 Green Grove Rd Asbury Park NJ 07712",
    "addr:housenumber":"629",
    "addr:postcode":"07712",
    "addr:street":"Green Grove Rd",
    "iso:country":"US",
    "sg:address":"629 Green Grove Rd",
    "sg:city":"Asbury Park",
    "sg:classifiers":[
        {
            "category":"Building & Trades",
            "subcategory":"Landscaping Services",
            "type":"Services"
        }
    ],
    "sg:phone":"+1 732 493 3179",
    "sg:postcode":"07712",
    "sg:province":"NJ",
    "wof:name":"Ralph Gundel",
    "wof:placetype":"venue"
},
  "geometry": {"coordinates":[-74.074811,40.251554],"type":"Point"}
}