{
  "type": "Feature",
  "properties": {
    "addr:full":"31 Mountain Ave North Plainfield NJ 07060",
    "addr:housenumber":"31",
    "addr:postcode":"07060",
    "addr:street":"Mountain Ave",
    "iso:country":"US",
    "sg:address":"31 Mountain Ave",
    "sg:city":"North Plainfield",
    "sg:classifiers":[
        {
            "category":"Wholesale",
            "subcategory":"Durable Goods & Equipment",
            "type":"Manufacturing & Wholesale Goods"
        }
    ],
    "sg:phone":"+1 908 769 9859",
    "sg:postcode":"07060",
    "sg:province":"NJ",
    "sg:tags":[
        "importer"
    ],
    "wof:name":"Sherry International Inc",
    "wof:placetype":"venue"
},
  "geometry": {"coordinates":[-74.433792,40.624883],"type":"Point"}
}