{
  "type": "Feature",
  "properties": {
    "addr:full":"703 N Main St Glassboro NJ 08028",
    "addr:housenumber":"703",
    "addr:postcode":"08028",
    "addr:street":"N Main St",
    "iso:country":"US",
    "sg:address":"703 N Main St",
    "sg:city":"Glassboro",
    "sg:classifiers":[
        {
            "category":"Organizations",
            "subcategory":"Political Organization",
            "type":"Services"
        }
    ],
    "sg:phone":"+1 856 863 5892",
    "sg:postcode":"08028",
    "sg:province":"NJ",
    "wof:name":"Glassboro Democratic Campaign",
    "wof:placetype":"venue"
},
  "geometry": {"coordinates":[-75.117227,39.718155],"type":"Point"}
}