{
  "type": "Feature",
  "properties": {
    "addr:full":"18 Industrial Ave Mahwah NJ 07430",
    "addr:housenumber":"18",
    "addr:postcode":"07430",
    "addr:street":"Industrial Ave",
    "iso:country":"US",
    "sg:address":"18 Industrial Ave",
    "sg:city":"Mahwah",
    "sg:classifiers":[
        {
            "category":"Utilities",
            "subcategory":"Refuse",
            "type":"Services"
        }
    ],
    "sg:phone":"+1 201 529 8170",
    "sg:postcode":"07430",
    "sg:province":"NJ",
    "sg:tags":[
        "garbage",
        "system",
        "collection"
    ],
    "wof:name":"Automated Waste Services Inc",
    "wof:placetype":"venue"
},
  "geometry": {"coordinates":[-74.142043,41.081524],"type":"Point"}
}