{
  "type": "Feature",
  "properties": {
    "addr:full":"1167 State Rt 23 Ste 17 Butler NJ 07405",
    "addr:housenumber":"1167;17",
    "addr:postcode":"07405",
    "addr:street":"State Rt 23 Ste",
    "iso:country":"US",
    "sg:address":"1167 State Rt 23 Ste 17",
    "sg:city":"Butler",
    "sg:classifiers":[
        {
            "category":"Personal",
            "type":"Services"
        },
        {
            "category":"Professional",
            "subcategory":"Detective & Security Services",
            "type":"Services"
        }
    ],
    "sg:phone":"+1 973 283 8777",
    "sg:postcode":"07405",
    "sg:province":"NJ",
    "sg:tags":[
        "control",
        "alarm",
        "medical",
        "monitoring",
        "system"
    ],
    "wof:name":"Ultimate Audio Inc",
    "wof:placetype":"venue"
},
  "geometry": {"coordinates":[-74.33512899999999,40.989759],"type":"Point"}
}