{
  "type": "Feature",
  "properties": {
    "iso:country":"US",
    "sg:address":"34 Timber Rd",
    "sg:city":"East Brunswick",
    "sg:classifiers":[
        {
            "category":"Social Services",
            "type":"Services"
        }
    ],
    "sg:phone":"+1 732 390 5940",
    "sg:postcode":"08816",
    "sg:province":"NJ",
    "wof:name":"Lora L Speiser",
    "wof:placetype":"venue"
},
  "geometry": {"coordinates":[-74.40981600000001,40.427602],"type":"Point"}
}