{
  "type": "Feature",
  "properties": {
    "iso:country":"US",
    "sg:address":"327 Adams Ct",
    "sg:city":"Manalapan",
    "sg:classifiers":[
        {
            "category":"Professional",
            "subcategory":"Management & Consulting",
            "type":"Services"
        }
    ],
    "sg:phone":"+1 732 208 3636",
    "sg:postcode":"07726",
    "sg:province":"NJ",
    "sg:tags":[
        "consultant"
    ],
    "wof:name":"Sparks Consulting Svc",
    "wof:placetype":"venue"
},
  "geometry": {"coordinates":[-74.314881,40.283922],"type":"Point"}
}