{
  "type": "Feature",
  "properties": {
    "addr:full":"520 Cooper St Camden NJ 08102",
    "addr:housenumber":"520",
    "addr:postcode":"08102",
    "addr:street":"Cooper St",
    "iso:country":"US",
    "sg:address":"520 Cooper St",
    "sg:city":"Camden",
    "sg:classifiers":[
        {
            "category":"Health Services",
            "subcategory":"Doctor",
            "type":"Services"
        }
    ],
    "sg:phone":"+1 856 757 9797",
    "sg:postcode":"08102",
    "sg:province":"NJ",
    "wof:name":"Sleep Center-Cooper Pediatrics",
    "wof:placetype":"venue"
},
  "geometry": {"coordinates":[-75.120074,39.946337],"type":"Point"}
}