{
  "type": "Feature",
  "properties": {
    "addr:full":"288 Cross Keys Rd Berlin NJ 08009",
    "addr:housenumber":"288",
    "addr:postcode":"08009",
    "addr:street":"Cross Keys Rd",
    "iso:country":"US",
    "sg:address":"288 Cross Keys Rd",
    "sg:city":"Berlin",
    "sg:classifiers":[
        {
            "category":"Building & Trades",
            "subcategory":"Construction",
            "type":"Services"
        }
    ],
    "sg:phone":"+1 856 753 8720",
    "sg:postcode":"08009",
    "sg:province":"NJ",
    "sg:tags":[
        "repair",
        "carpentry",
        "contractor"
    ],
    "wof:name":"A 1 Overhead Doors",
    "wof:placetype":"venue"
},
  "geometry": {"coordinates":[-74.95229,39.780862],"type":"Point"}
}