{
  "type": "Feature",
  "properties": {
    "addr:full":"4 Paulinskill Lake Rd Newton NJ 07860",
    "addr:housenumber":"4",
    "addr:postcode":"07860",
    "addr:street":"Paulinskill Lake Rd",
    "iso:country":"US",
    "sg:address":"4 Paulinskill Lake Rd",
    "sg:city":"Newton",
    "sg:classifiers":[
        {
            "category":"Farming",
            "subcategory":"Livestock Farm",
            "type":"Manufacturing & Wholesale Goods"
        }
    ],
    "sg:phone":"+1 973 300 9881",
    "sg:postcode":"07860",
    "sg:province":"NJ",
    "sg:tags":[
        "specialty",
        "animal"
    ],
    "wof:name":"R World Enterprises",
    "wof:placetype":"venue"
},
  "geometry": {"coordinates":[-74.815427,41.049548],"type":"Point"}
}