{
  "type": "Feature",
  "properties": {
    "iso:country":"US",
    "sg:address":"504 Grove St",
    "sg:city":"New Milford",
    "sg:classifiers":[
        {
            "category":"Manufacturing",
            "subcategory":"Metals",
            "type":"Manufacturing & Wholesale Goods"
        },
        {
            "category":"Building & Trades",
            "subcategory":"Construction",
            "type":"Services"
        }
    ],
    "sg:phone":"+1 201 385 7906",
    "sg:postcode":"07646",
    "sg:province":"NJ",
    "sg:tags":[
        "steel",
        "contractor"
    ],
    "wof:name":"Fav's Welding & Fabrication",
    "wof:placetype":"venue"
},
  "geometry": {"coordinates":[-74.017988,40.935781],"type":"Point"}
}