{
  "type": "Feature",
  "properties": {
    "iso:country":"US",
    "sg:address":"196 Anthony Pl",
    "sg:city":"Wyckoff",
    "sg:classifiers":[
        {
            "category":"Professional",
            "subcategory":"Research",
            "type":"Services"
        }
    ],
    "sg:phone":"+1 201 848 7400",
    "sg:postcode":"07481",
    "sg:province":"NJ",
    "sg:tags":[
        "development",
        "marketing",
        "product"
    ],
    "wof:name":"ISC",
    "wof:placetype":"venue"
},
  "geometry": {"coordinates":[-74.149951,41.013501],"type":"Point"}
}