{
  "type": "Feature",
  "properties": {
    "iso:country":"US",
    "sg:address":"186 Bloomfield Ave",
    "sg:city":"Newark",
    "sg:classifiers":[
        {
            "category":"Insurance",
            "subcategory":"Insurance Agent",
            "type":"Services"
        }
    ],
    "sg:phone":"+1 973 482 4184",
    "sg:postcode":"07104",
    "sg:province":"NJ",
    "wof:name":"Sanabria Insurance",
    "wof:placetype":"venue"
},
  "geometry": {"coordinates":[-74.176759,40.760713],"type":"Point"}
}