{
  "type": "Feature",
  "properties": {
    "iso:country":"US",
    "sg:address":"600 Meadowlands Pkwy",
    "sg:city":"Secaucus",
    "sg:classifiers":[
        {
            "category":"Professional",
            "subcategory":"Computer Services",
            "type":"Services"
        }
    ],
    "sg:phone":"+1 201 422 9200",
    "sg:postcode":"07094",
    "sg:province":"NJ",
    "sg:tags":[
        "consultant",
        "designer",
        "programing",
        "custom"
    ],
    "sg:website":"www.eclipsemicro.com",
    "wof:name":"Eclipse Micro Computer Inc",
    "wof:placetype":"venue"
},
  "geometry": {"coordinates":[-74.081641,40.779007],"type":"Point"}
}