{
  "type": "Feature",
  "properties": {
    "addr:full":"35 Robbinsville Allentown Rd Robbinsville NJ 08691",
    "addr:housenumber":"35",
    "addr:postcode":"08691",
    "addr:street":"Allentown Rd",
    "iso:country":"US",
    "sg:address":"35 Robbinsville Allentown Rd",
    "sg:city":"Robbinsville",
    "sg:classifiers":[
        {
            "category":"Building & Trades",
            "subcategory":"Construction",
            "type":"Services"
        }
    ],
    "sg:phone":"+1 609 259 8204",
    "sg:postcode":"08691",
    "sg:province":"NJ",
    "sg:tags":[
        "general",
        "contractor"
    ],
    "sg:website":"www.jgconstruction.net",
    "wof:name":"J & G Construction",
    "wof:placetype":"venue"
},
  "geometry": {"coordinates":[-74.623401,40.216004],"type":"Point"}
}