{
  "type": "Feature",
  "properties": {
    "iso:country":"US",
    "sg:address":"3445 US Hwy 9",
    "sg:city":"Freehold",
    "sg:classifiers":[
        {
            "category":"Restaurant",
            "type":"Food & Drink"
        }
    ],
    "sg:phone":"+1   ",
    "sg:postcode":"07728",
    "sg:province":"NJ",
    "sg:tags":[
        "eating"
    ],
    "wof:name":"Perkins Family Restaurant",
    "wof:placetype":"venue"
},
  "geometry": {"coordinates":[-74.272227,40.230028],"type":"Point"}
}