{
  "type": "Feature",
  "properties": {
    "iso:country":"US",
    "sg:address":"201 Stelton Rd",
    "sg:city":"Piscataway",
    "sg:classifiers":[
        {
            "category":"Real Estate",
            "subcategory":"Real Estate Operator",
            "type":"Services"
        }
    ],
    "sg:phone":"+1   ",
    "sg:postcode":"08854",
    "sg:province":"NJ",
    "sg:tags":[
        "building",
        "nonresidential"
    ],
    "wof:name":"Jjr Property Inc",
    "wof:placetype":"venue"
},
  "geometry": {"coordinates":[-74.456638,40.569098],"type":"Point"}
}