{
  "type": "Feature",
  "properties": {
    "addr:full":"2225 Boardwalk Atlantic City NJ 08401",
    "addr:housenumber":"2225",
    "addr:postcode":"08401",
    "addr:street":"Boardwalk",
    "iso:country":"US",
    "sg:address":"2225 Boardwalk",
    "sg:city":"Atlantic City",
    "sg:classifiers":[
        {
            "category":"Restaurant",
            "type":"Food & Drink"
        }
    ],
    "sg:phone":"+1 609 572 0866",
    "sg:postcode":"08401",
    "sg:province":"NJ",
    "wof:name":"China Cafe & Sushi Chef",
    "wof:placetype":"venue"
},
  "geometry": {"coordinates":[-74.43708700000001,39.354297],"type":"Point"}
}