{
  "type": "Feature",
  "properties": {
    "iso:country":"US",
    "sg:address":"110 Franklin Dr",
    "sg:city":"Mullica Hill",
    "sg:classifiers":[
        {
            "category":"Organizations",
            "subcategory":"Community Association",
            "type":"Services"
        }
    ],
    "sg:phone":"+1 856 478 6706",
    "sg:postcode":"08062",
    "sg:province":"NJ",
    "wof:name":"VFW Post 10886",
    "wof:placetype":"venue"
},
  "geometry": {"coordinates":[-75.212841,39.73196],"type":"Point"}
}