{
  "type": "Feature",
  "properties": {
    "addr:full":"107 E 1st Ave Roselle NJ 07203",
    "addr:housenumber":"107",
    "addr:postcode":"07203",
    "addr:street":"E 1St Ave",
    "iso:country":"US",
    "sg:address":"107 E 1st Ave",
    "sg:city":"Roselle",
    "sg:classifiers":[
        {
            "category":"Shopping",
            "subcategory":"Pharmacy",
            "type":"Retail Goods"
        }
    ],
    "sg:phone":"+1   ",
    "sg:postcode":"07203",
    "sg:province":"NJ",
    "sg:tags":[
        "drug",
        "store"
    ],
    "wof:name":"CVS",
    "wof:placetype":"venue"
},
  "geometry": {"coordinates":[-74.260655,40.660563],"type":"Point"}
}