{
  "type": "Feature",
  "properties": {
    "addr:full":"600 Main St Bradley Beach NJ 07720",
    "addr:housenumber":"600",
    "addr:postcode":"07720",
    "addr:street":"Main St",
    "iso:country":"US",
    "sg:address":"600 Main St",
    "sg:city":"Bradley Beach",
    "sg:classifiers":[
        {
            "category":"Restaurant",
            "type":"Food & Drink"
        }
    ],
    "sg:phone":"+1   ",
    "sg:postcode":"07720",
    "sg:province":"NJ",
    "sg:tags":[
        "eating"
    ],
    "wof:name":"Bella Sogno",
    "wof:placetype":"venue"
},
  "geometry": {"coordinates":[-74.01759800000001,40.204094],"type":"Point"}
}