{
  "type": "Feature",
  "properties": {
    "addr:full":"1552 Maple Ave Hillside NJ 07205",
    "addr:housenumber":"1552",
    "addr:postcode":"07205",
    "addr:street":"Maple Ave",
    "iso:country":"US",
    "sg:address":"1552 Maple Ave",
    "sg:city":"Hillside",
    "sg:classifiers":[
        {
            "category":"Shopping",
            "subcategory":"Florist",
            "type":"Retail Goods"
        }
    ],
    "sg:phone":"+1 973 926 1773",
    "sg:postcode":"07205",
    "sg:province":"NJ",
    "wof:name":"Fresh & Pretty Plus",
    "wof:placetype":"venue"
},
  "geometry": {"coordinates":[-74.21977699999999,40.703467],"type":"Point"}
}