{
  "type": "Feature",
  "properties": {
    "addr:full":"486 Central Avenue Jersey City NJ 07306",
    "addr:housenumber":"486",
    "addr:postcode":"07306",
    "addr:street":"Central Avenue",
    "iso:country":"US",
    "sg:address":"486 Central Avenue",
    "sg:city":"Jersey City",
    "sg:classifiers":[
        {
            "category":"Bars & Pubs",
            "type":"Food & Drink"
        }
    ],
    "sg:phone":"+1 201 656 8785",
    "sg:postcode":"07306",
    "sg:province":"NJ",
    "wof:name":"Ralph's Tavern",
    "wof:placetype":"venue"
},
  "geometry": {"coordinates":[-74.045678,40.751257],"type":"Point"}
}