{
  "type": "Feature",
  "properties": {
    "addr:full":"400 State St Hackensack NJ 07601",
    "addr:housenumber":"400",
    "addr:postcode":"07601",
    "addr:street":"State St",
    "iso:country":"US",
    "sg:address":"400 State St",
    "sg:city":"Hackensack",
    "sg:classifiers":[
        {
            "category":"Real Estate",
            "subcategory":"Real Estate Agent",
            "type":"Services"
        }
    ],
    "sg:phone":"+1 201 488 5848",
    "sg:postcode":"07601",
    "sg:province":"NJ",
    "sg:tags":[
        "apartment",
        "management"
    ],
    "wof:name":"James E Hanson Management Co",
    "wof:placetype":"venue"
},
  "geometry": {"coordinates":[-74.041,40.890202],"type":"Point"}
}