{
  "type": "Feature",
  "properties": {
    "addr:full":"180 Avenel Blvd Long Branch NJ 07740",
    "addr:housenumber":"180",
    "addr:postcode":"07740",
    "addr:street":"Avenel Blvd",
    "iso:country":"US",
    "sg:address":"180 Avenel Blvd",
    "sg:city":"Long Branch",
    "sg:classifiers":[
        {
            "category":"Building & Trades",
            "subcategory":"Construction",
            "type":"Services"
        }
    ],
    "sg:phone":"+1 732 229 8759",
    "sg:postcode":"07740",
    "sg:province":"NJ",
    "sg:tags":[
        "handyman"
    ],
    "wof:name":"All American Handyman",
    "wof:placetype":"venue"
},
  "geometry": {"coordinates":[-73.989242,40.316699],"type":"Point"}
}