{
  "type": "Feature",
  "properties": {
    "addr:full":"1201 Co Rd 539 Little Egg Hbr NJ 08087",
    "addr:housenumber":"1201;539",
    "addr:postcode":"08087",
    "addr:street":"Co Rd;Little",
    "iso:country":"US",
    "sg:address":"1201 Co Rd 539",
    "sg:city":"Little Egg Hbr",
    "sg:classifiers":[
        {
            "category":"Food & Beverages",
            "subcategory":"Groceries & Convenience Stores",
            "type":"Retail Goods"
        }
    ],
    "sg:phone":"+1 609 296 8573",
    "sg:postcode":"08087",
    "sg:province":"NJ",
    "wof:name":"Wawa Food Markets",
    "wof:placetype":"venue"
},
  "geometry": {"coordinates":[-74.331614,39.578145],"type":"Point"}
}