{
  "type": "Feature",
  "properties": {
    "iso:country":"US",
    "sg:address":"511 Main St",
    "sg:city":"Avon By The Sea",
    "sg:classifiers":[
        {
            "category":"Manufacturing",
            "subcategory":"Printing",
            "type":"Manufacturing & Wholesale Goods"
        }
    ],
    "sg:phone":"+1 732 774 8000",
    "sg:postcode":"07717",
    "sg:province":"NJ",
    "sg:tags":[
        "commercial"
    ],
    "wof:name":"Kirms Printing Co",
    "wof:placetype":"venue"
},
  "geometry": {"coordinates":[-74.021393,40.193653],"type":"Point"}
}