{
  "type": "Feature",
  "properties": {
    "iso:country":"US",
    "sg:address":"1588 Saint Georges Ave",
    "sg:city":"Avenel",
    "sg:classifiers":[
        {
            "category":"Retail",
            "subcategory":"Portrait Studio",
            "type":"Services"
        }
    ],
    "sg:phone":"+1 732 499 7199",
    "sg:postcode":"07001",
    "sg:province":"NJ",
    "sg:tags":[
        "photography",
        "store"
    ],
    "sg:website":"www.phototimeusa.com",
    "wof:name":"Photo Time Inc",
    "wof:placetype":"venue"
},
  "geometry": {"coordinates":[-74.29070299999999,40.5909],"type":"Point"}
}