{
  "type": "Feature",
  "properties": {
    "iso:country":"US",
    "sg:address":"19 E Lakewood Ave",
    "sg:city":"Milltown",
    "sg:classifiers":[
        {
            "category":"Building & Trades",
            "subcategory":"Construction",
            "type":"Services"
        }
    ],
    "sg:phone":"+1 732 545 1189",
    "sg:postcode":"08850",
    "sg:province":"NJ",
    "sg:tags":[
        "contractor"
    ],
    "wof:name":"J D P & Sons",
    "wof:placetype":"venue"
},
  "geometry": {"coordinates":[-74.434111,40.449498],"type":"Point"}
}