{
  "type": "Feature",
  "properties": {
    "addr:full":"145 Sand Hills Rd Monmouth Junction NJ 08852",
    "addr:housenumber":"145",
    "addr:postcode":"08852",
    "addr:street":"Sand Hills Rd",
    "iso:country":"US",
    "sg:address":"145 Sand Hills Rd",
    "sg:city":"Monmouth Junction",
    "sg:classifiers":[
        {
            "category":"Farming",
            "subcategory":"Farm",
            "type":"Manufacturing & Wholesale Goods"
        }
    ],
    "sg:phone":"+1 732 297 8022",
    "sg:postcode":"08852",
    "sg:province":"NJ",
    "sg:tags":[
        "crop",
        "general"
    ],
    "wof:name":"South Brunswick Contractor",
    "wof:placetype":"venue"
},
  "geometry": {"coordinates":[-74.548232,40.409262],"type":"Point"}
}