{
  "type": "Feature",
  "properties": {
    "iso:country":"US",
    "sg:address":"36 Clifton Ave",
    "sg:city":"Lakewood",
    "sg:classifiers":[
        {
            "category":"Shopping",
            "subcategory":"Jewelry",
            "type":"Retail Goods"
        }
    ],
    "sg:phone":"+1   ",
    "sg:postcode":"08701",
    "sg:province":"NJ",
    "sg:tags":[
        "repair"
    ],
    "sg:website":"www.twincityjewelers.com",
    "wof:name":"Twin City Jewelers",
    "wof:placetype":"venue"
},
  "geometry": {"coordinates":[-74.21444099999999,40.090754],"type":"Point"}
}