{
  "type": "Feature",
  "properties": {
    "addr:full":"514 Anderson Ave Cliffside Park NJ 07010",
    "addr:housenumber":"514",
    "addr:postcode":"07010",
    "addr:street":"Anderson Ave",
    "iso:country":"US",
    "sg:address":"514 Anderson Ave",
    "sg:city":"Cliffside Park",
    "sg:classifiers":[
        {
            "category":"Shopping",
            "subcategory":"Pharmacy",
            "type":"Retail Goods"
        }
    ],
    "sg:phone":"+1 201 941 9090",
    "sg:postcode":"07010",
    "sg:province":"NJ",
    "wof:name":"Compounding Apothecary",
    "wof:placetype":"venue"
},
  "geometry": {"coordinates":[-73.990253,40.821866],"type":"Point"}
}