{
  "type": "Feature",
  "properties": {
    "addr:full":"1518 Bond St Hillside NJ 07205",
    "addr:housenumber":"1518",
    "addr:postcode":"07205",
    "addr:street":"Bond St",
    "iso:country":"US",
    "sg:address":"1518 Bond St",
    "sg:city":"Hillside",
    "sg:classifiers":[
        {
            "category":"Personal",
            "subcategory":"Beauty Salon",
            "type":"Services"
        }
    ],
    "sg:phone":"+1 973 923 0177",
    "sg:postcode":"07205",
    "sg:province":"NJ",
    "sg:tags":[
        "make",
        "studio"
    ],
    "wof:name":"Mary Kay Cosmetics",
    "wof:placetype":"venue"
},
  "geometry": {"coordinates":[-74.219257,40.701565],"type":"Point"}
}