{
  "type": "Feature",
  "properties": {
    "addr:full":"1275 Bloomfield Ave Ste 20 Fairfield NJ 07004",
    "addr:housenumber":"1275;20",
    "addr:postcode":"07004",
    "addr:street":"Bloomfield Ave Ste",
    "iso:country":"US",
    "sg:address":"1275 Bloomfield Ave Ste 20",
    "sg:city":"Fairfield",
    "sg:classifiers":[
        {
            "category":"Education",
            "subcategory":"Special Training",
            "type":"Public Place"
        }
    ],
    "sg:phone":"+1 973 227 0321",
    "sg:postcode":"07004",
    "sg:province":"NJ",
    "sg:tags":[
        "tutoring"
    ],
    "wof:name":"The Academy Baseball-Softball Inc",
    "wof:placetype":"venue"
},
  "geometry": {"coordinates":[-74.31819900000001,40.8582],"type":"Point"}
}