{
  "type": "Feature",
  "properties": {
    "addr:full":"48 Woodmere Dr Parlin NJ 08859",
    "addr:housenumber":"48",
    "addr:postcode":"08859",
    "addr:street":"Woodmere Dr",
    "iso:country":"US",
    "sg:address":"48 Woodmere Dr",
    "sg:city":"Parlin",
    "sg:classifiers":[
        {
            "category":"Professional",
            "subcategory":"Detective & Security Services",
            "type":"Services"
        }
    ],
    "sg:phone":"+1 732 553 0481",
    "sg:postcode":"08859",
    "sg:province":"NJ",
    "sg:tags":[
        "guard",
        "investigator"
    ],
    "wof:name":"Mansfield Detective Agency LLC",
    "wof:placetype":"venue"
},
  "geometry": {"coordinates":[-74.28572200000001,40.456119],"type":"Point"}
}