{
  "type": "Feature",
  "properties": {
    "iso:country":"US",
    "sg:address":"924 Brunswick Ave",
    "sg:city":"Trenton",
    "sg:classifiers":[
        {
            "category":"Restaurant",
            "type":"Food & Drink"
        }
    ],
    "sg:phone":"+1 609 989 9888",
    "sg:postcode":"08638",
    "sg:province":"NJ",
    "sg:tags":[
        "eating"
    ],
    "wof:name":"Yu King Chinese Restaurant",
    "wof:placetype":"venue"
},
  "geometry": {"coordinates":[-74.749557,40.23938],"type":"Point"}
}