{
  "type": "Feature",
  "properties": {
    "iso:country":"US",
    "sg:address":"50 Branford Pl",
    "sg:city":"Newark",
    "sg:classifiers":[
        {
            "category":"Professional",
            "type":"Services"
        }
    ],
    "sg:phone":"+1 973 639 9500",
    "sg:postcode":"07102",
    "sg:province":"NJ",
    "sg:tags":[
        "establishment"
    ],
    "wof:name":"Branford Manor",
    "wof:placetype":"venue"
},
  "geometry": {"coordinates":[-74.175119,40.735266],"type":"Point"}
}