{
  "type": "Feature",
  "properties": {
    "addr:full":"208 Saint Mary St Burlington NJ 08016",
    "addr:housenumber":"208",
    "addr:postcode":"08016",
    "addr:street":"Saint Mary St",
    "iso:country":"US",
    "sg:address":"208 Saint Mary St",
    "sg:city":"Burlington",
    "sg:classifiers":[
        {
            "category":"Building & Trades",
            "subcategory":"Plumbing",
            "type":"Services"
        }
    ],
    "sg:phone":"+1 609 386 3097",
    "sg:postcode":"08016",
    "sg:province":"NJ",
    "wof:name":"Fox David A & Son",
    "wof:placetype":"venue"
},
  "geometry": {"coordinates":[-74.853798,40.0812],"type":"Point"}
}