{
  "type": "Feature",
  "properties": {
    "iso:country":"US",
    "sg:address":"186 Columbia Ave",
    "sg:city":"Jersey City",
    "sg:classifiers":[
        {
            "category":"Arts & Performance",
            "subcategory":"Theater",
            "type":"Entertainment"
        }
    ],
    "sg:phone":"+1   ",
    "sg:postcode":"07307",
    "sg:province":"NJ",
    "sg:tags":[
        "group"
    ],
    "wof:name":"Elwood Entertainment Inc",
    "wof:placetype":"venue"
},
  "geometry": {"coordinates":[-74.05303000000001,40.753481],"type":"Point"}
}