{
  "type": "Feature",
  "properties": {
    "iso:country":"US",
    "sg:address":"1 S Gold Dr",
    "sg:city":"Trenton",
    "sg:classifiers":[
        {
            "category":"Wholesale",
            "subcategory":"Electrical",
            "type":"Manufacturing & Wholesale Goods"
        }
    ],
    "sg:phone":"+1 609 890 7200",
    "sg:postcode":"08691",
    "sg:province":"NJ",
    "sg:tags":[
        "generator"
    ],
    "sg:website":"www.powertechserv.com",
    "wof:name":"Power Tech Svs",
    "wof:placetype":"venue"
},
  "geometry": {"coordinates":[-74.62723699999999,40.205573],"type":"Point"}
}