{
  "type": "Feature",
  "properties": {
    "iso:country":"US",
    "sg:address":"461 Frelinghuysen Ave",
    "sg:city":"Newark",
    "sg:classifiers":[
        {
            "category":"Manufacturing",
            "subcategory":"Textiles",
            "type":"Manufacturing & Wholesale Goods"
        }
    ],
    "sg:phone":"+1 973 621 6000",
    "sg:postcode":"07114",
    "sg:province":"NJ",
    "sg:tags":[
        "finishing"
    ],
    "wof:name":"J-Mar Textile",
    "wof:placetype":"venue"
},
  "geometry": {"coordinates":[-74.19374500000001,40.704977],"type":"Point"}
}