{
  "type": "Feature",
  "properties": {
    "addr:full":"237 W Chestnut Ave Vineland NJ 08360",
    "addr:housenumber":"237",
    "addr:postcode":"08360",
    "addr:street":"W Chestnut Ave",
    "iso:country":"US",
    "sg:address":"237 W Chestnut Ave",
    "sg:city":"Vineland",
    "sg:classifiers":[
        {
            "category":"Social Services",
            "subcategory":"Child Care",
            "type":"Services"
        }
    ],
    "sg:phone":"+1   ",
    "sg:postcode":"08360",
    "sg:province":"NJ",
    "sg:tags":[
        "day"
    ],
    "wof:name":"Test City Head Start",
    "wof:placetype":"venue"
},
  "geometry": {"coordinates":[-75.032616,39.479227],"type":"Point"}
}