{
  "type": "Feature",
  "properties": {
    "addr:full":"1 Compton Ct Basking Ridge NJ 07920",
    "addr:housenumber":"1",
    "addr:postcode":"07920",
    "addr:street":"Compton Ct",
    "iso:country":"US",
    "sg:address":"1 Compton Ct",
    "sg:city":"Basking Ridge",
    "sg:classifiers":[
        {
            "category":"Insurance",
            "subcategory":"Insurance Agent",
            "type":"Services"
        }
    ],
    "sg:phone":"+1   ",
    "sg:postcode":"07920",
    "sg:province":"NJ",
    "sg:tags":[
        "agency"
    ],
    "wof:name":"Mas Auto Insurance Services",
    "wof:placetype":"venue"
},
  "geometry": {"coordinates":[-74.56643099999999,40.659521],"type":"Point"}
}