{
  "type": "Feature",
  "properties": {
    "iso:country":"US",
    "sg:address":"683 Georges Rd",
    "sg:city":"North Brunswick",
    "sg:classifiers":[
        {
            "category":"Restaurant",
            "type":"Food & Drink"
        }
    ],
    "sg:phone":"+1 732 545 7777",
    "sg:postcode":"08902",
    "sg:province":"NJ",
    "sg:tags":[
        "cafe"
    ],
    "wof:name":"Cafe Biscotti",
    "wof:placetype":"venue"
},
  "geometry": {"coordinates":[-74.453333,40.46795],"type":"Point"}
}