{
  "type": "Feature",
  "properties": {
    "addr:full":"35 Sea Girt Ave Sea Girt NJ 08736",
    "addr:housenumber":"35",
    "addr:postcode":"08736",
    "addr:street":"Sea Girt Ave",
    "iso:country":"US",
    "sg:address":"35 Sea Girt Ave",
    "sg:city":"Sea Girt",
    "sg:classifiers":[
        {
            "category":"Shopping",
            "subcategory":"Computers & Home Electronics",
            "type":"Retail Goods"
        }
    ],
    "sg:phone":"+1   ",
    "sg:postcode":"08736",
    "sg:province":"NJ",
    "wof:name":"Radio Shack",
    "wof:placetype":"venue"
},
  "geometry": {"coordinates":[-74.04876899999999,40.131764],"type":"Point"}
}