{
  "type": "Feature",
  "properties": {
    "addr:full":"6415 Mill Rd Egg Harbor Township NJ 08234",
    "addr:housenumber":"6415",
    "addr:postcode":"08234",
    "addr:street":"Mill Rd;Harbor",
    "iso:country":"US",
    "sg:address":"6415 Mill Rd",
    "sg:city":"Egg Harbor Township",
    "sg:classifiers":[
        {
            "category":"Food & Beverages",
            "subcategory":"Groceries & Convenience Stores",
            "type":"Retail Goods"
        }
    ],
    "sg:phone":"+1   ",
    "sg:postcode":"08234",
    "sg:province":"NJ",
    "wof:name":"Millrose Subs & Market",
    "wof:placetype":"venue"
},
  "geometry": {"coordinates":[-74.613395,39.383772],"type":"Point"}
}