{
  "type": "Feature",
  "properties": {
    "iso:country":"US",
    "sg:address":"11 Pottersville Rd",
    "sg:city":"Oldwick",
    "sg:classifiers":[
        {
            "category":"Banks & Credit Unions",
            "subcategory":"Bank",
            "type":"Services"
        }
    ],
    "sg:phone":"+1 908 439 2265",
    "sg:postcode":"08858",
    "sg:province":"NJ",
    "sg:website":"www.pgbank.com",
    "wof:name":"Peapack-Gladstone Bank",
    "wof:placetype":"venue"
},
  "geometry": {"coordinates":[-74.749397,40.6721],"type":"Point"}
}