{
  "type": "Feature",
  "properties": {
    "addr:full":"5 Casa Ct Brigantine NJ 08203",
    "addr:housenumber":"5",
    "addr:postcode":"08203",
    "addr:street":"Casa Ct",
    "iso:country":"US",
    "sg:address":"5 Casa Ct",
    "sg:city":"Brigantine",
    "sg:classifiers":[
        {
            "category":"Building & Trades",
            "subcategory":"Construction",
            "type":"Services"
        }
    ],
    "sg:phone":"+1 609 266 1131",
    "sg:postcode":"08203",
    "sg:province":"NJ",
    "sg:tags":[
        "general",
        "contractor"
    ],
    "wof:name":"M G General Cntrctng & Rmdlng",
    "wof:placetype":"venue"
},
  "geometry": {"coordinates":[-74.40278600000001,39.386309],"type":"Point"}
}