{
  "type": "Feature",
  "properties": {
    "addr:full":"503 Monroeville Rd Swedesboro NJ 08085",
    "addr:housenumber":"503",
    "addr:postcode":"08085",
    "addr:street":"Monroeville Rd",
    "iso:country":"US",
    "sg:address":"503 Monroeville Rd",
    "sg:city":"Swedesboro",
    "sg:classifiers":[
        {
            "category":"Government",
            "subcategory":"Office",
            "type":"Public Place"
        }
    ],
    "sg:phone":"+1 856 478 6045",
    "sg:postcode":"08085",
    "sg:province":"NJ",
    "sg:tags":[
        "county",
        "program"
    ],
    "sg:website":"www.gcianj.com",
    "wof:name":"Gloucester County Solid Waste",
    "wof:placetype":"venue"
},
  "geometry": {"coordinates":[-75.29827299999999,39.740197],"type":"Point"}
}