{
  "type": "Feature",
  "properties": {
    "iso:country":"US",
    "sg:address":"1 Clubhouse Rd",
    "sg:city":"Hamburg",
    "sg:classifiers":[
        {
            "category":"Professional",
            "subcategory":"Research",
            "type":"Services"
        }
    ],
    "sg:phone":"+1   ",
    "sg:postcode":"07419",
    "sg:province":"NJ",
    "sg:tags":[
        "nonphysical",
        "commercial"
    ],
    "wof:name":"McBride Marketing Resources",
    "wof:placetype":"venue"
},
  "geometry": {"coordinates":[-74.55476899999999,41.155567],"type":"Point"}
}