{
  "type": "Feature",
  "properties": {
    "addr:full":"568 Prospect Ave Spring Lake NJ 07762",
    "addr:housenumber":"568",
    "addr:postcode":"07762",
    "addr:street":"Prospect Ave",
    "iso:country":"US",
    "sg:address":"568 Prospect Ave",
    "sg:city":"Spring Lake",
    "sg:classifiers":[
        {
            "category":"Professional",
            "subcategory":"Business Services",
            "type":"Services"
        }
    ],
    "sg:phone":"+1 732 449 8703",
    "sg:postcode":"07762",
    "sg:province":"NJ",
    "wof:name":"American Express",
    "wof:placetype":"venue"
},
  "geometry": {"coordinates":[-74.038675,40.144534],"type":"Point"}
}