{
  "type": "Feature",
  "properties": {
    "iso:country":"US",
    "sg:address":"75 Hobart Pl",
    "sg:city":"Totowa",
    "sg:classifiers":[
        {
            "category":"Building & Trades",
            "subcategory":"Plumbing",
            "type":"Services"
        }
    ],
    "sg:phone":"+1 973 595 5222",
    "sg:postcode":"07512",
    "sg:province":"NJ",
    "wof:name":"All Days & Nights Plumbing Contractor",
    "wof:placetype":"venue"
},
  "geometry": {"coordinates":[-74.21075,40.908094],"type":"Point"}
}