{
  "type": "Feature",
  "properties": {
    "addr:full":"44 High St Mt. Holly NJ 08060",
    "addr:housenumber":"44",
    "addr:postcode":"08060",
    "addr:street":"High St",
    "iso:country":"US",
    "sg:address":"44 High St",
    "sg:city":"Mt. Holly",
    "sg:classifiers":[
        {
            "category":"Organizations",
            "subcategory":"Community Association",
            "type":"Services"
        }
    ],
    "sg:phone":"+1 609 261 6900",
    "sg:postcode":"08060",
    "sg:province":"NJ",
    "sg:tags":[
        "pub"
    ],
    "wof:name":"The Bridgetown Pub",
    "wof:placetype":"venue"
},
  "geometry": {"coordinates":[-74.787958,39.994395],"type":"Point"}
}