{
  "type": "Feature",
  "properties": {
    "addr:full":"253 Broadway Paterson NJ 07501",
    "addr:housenumber":"253",
    "addr:postcode":"07501",
    "addr:street":"Broadway",
    "iso:country":"US",
    "sg:address":"253 Broadway",
    "sg:city":"Paterson",
    "sg:classifiers":[
        {
            "category":"Building & Trades",
            "subcategory":"Locksmith",
            "type":"Services"
        }
    ],
    "sg:phone":"+1 973 413 1328",
    "sg:postcode":"07501",
    "sg:province":"NJ",
    "sg:tags":[
        "key"
    ],
    "wof:name":"AA Always Available Locksmith",
    "wof:placetype":"venue"
},
  "geometry": {"coordinates":[-74.164064,40.918862],"type":"Point"}
}