{
  "type": "Feature",
  "properties": {
    "addr:full":"3 Bentwood Dr Bordentown NJ 08505",
    "addr:housenumber":"3",
    "addr:postcode":"08505",
    "addr:street":"Bentwood Dr",
    "iso:country":"US",
    "sg:address":"3 Bentwood Dr",
    "sg:city":"Bordentown",
    "sg:classifiers":[
        {
            "category":"Professional",
            "subcategory":"Computer Services",
            "type":"Services"
        }
    ],
    "sg:phone":"+1   ",
    "sg:postcode":"08505",
    "sg:province":"NJ",
    "sg:tags":[
        "related"
    ],
    "wof:name":"Jam Technology Consulting Svcs",
    "wof:placetype":"venue"
},
  "geometry": {"coordinates":[-74.681634,40.128027],"type":"Point"}
}