{
  "type": "Feature",
  "properties": {
    "iso:country":"US",
    "sg:address":"4 Reidar Dr",
    "sg:city":"Succasunna",
    "sg:classifiers":[
        {
            "category":"Building & Trades",
            "subcategory":"Landscaping Services",
            "type":"Services"
        }
    ],
    "sg:phone":"+1 973 584 0280",
    "sg:postcode":"07876",
    "sg:province":"NJ",
    "wof:name":"Poggi Lanscaping Co",
    "wof:placetype":"venue"
},
  "geometry": {"coordinates":[-74.652404,40.855054],"type":"Point"}
}