{
  "type": "Feature",
  "properties": {
    "iso:country":"US",
    "sg:address":"2028 Chapel Ave W",
    "sg:city":"Cherry Hill",
    "sg:classifiers":[
        {
            "category":"Health Services",
            "subcategory":"Chiropractor",
            "type":"Services"
        }
    ],
    "sg:phone":"+1 856 662 4848",
    "sg:postcode":"08002",
    "sg:province":"NJ",
    "sg:website":"www.drdeaninsana.com",
    "wof:name":"Dr Insana's Wellness Center Llc",
    "wof:placetype":"venue"
},
  "geometry": {"coordinates":[-75.024542,39.93098],"type":"Point"}
}