{
  "type": "Feature",
  "properties": {
    "iso:country":"US",
    "sg:address":"201 State Rte 34",
    "sg:city":"Matawan",
    "sg:classifiers":[
        {
            "category":"Social Services",
            "type":"Services"
        }
    ],
    "sg:phone":"+1 732 721 5760",
    "sg:postcode":"07747",
    "sg:province":"NJ",
    "wof:name":"Center For Mrrage Fmly Cnsling",
    "wof:placetype":"venue"
},
  "geometry": {"coordinates":[-74.24677800000001,40.41577],"type":"Point"}
}