{
  "type": "Feature",
  "properties": {
    "iso:country":"US",
    "sg:address":"40 Conger St",
    "sg:city":"Bloomfield",
    "sg:classifiers":[
        {
            "category":"Shopping",
            "type":"Retail Goods"
        }
    ],
    "sg:phone":"+1 973 743 1944",
    "sg:postcode":"07003",
    "sg:province":"NJ",
    "sg:tags":[
        "hearing",
        "equipment",
        "supply",
        "impaired"
    ],
    "wof:name":"I Appeal Opticians",
    "wof:placetype":"venue"
},
  "geometry": {"coordinates":[-74.196952,40.792215],"type":"Point"}
}