{
  "type": "Feature",
  "properties": {
    "iso:country":"US",
    "sg:address":"883 Julia St",
    "sg:city":"Elizabeth",
    "sg:classifiers":[
        {
            "category":"Manufacturing",
            "subcategory":"Metals",
            "type":"Manufacturing & Wholesale Goods"
        }
    ],
    "sg:phone":"+1 908 351 1147",
    "sg:postcode":"07201",
    "sg:province":"NJ",
    "sg:tags":[
        "fire",
        "escape"
    ],
    "wof:name":"Tri State Metal & Welding Corp",
    "wof:placetype":"venue"
},
  "geometry": {"coordinates":[-74.19877,40.669943],"type":"Point"}
}