{
  "type": "Feature",
  "properties": {
    "iso:country":"US",
    "sg:address":"242 E State St",
    "sg:city":"Trenton",
    "sg:classifiers":[
        {
            "category":"Restaurant",
            "type":"Food & Drink"
        }
    ],
    "sg:phone":"+1 609 989 0106",
    "sg:postcode":"08608",
    "sg:province":"NJ",
    "wof:name":"New York Fried Chicken",
    "wof:placetype":"venue"
},
  "geometry": {"coordinates":[-74.759784,40.220652],"type":"Point"}
}