{
  "type": "Feature",
  "properties": {
    "addr:full":"24 Albert St Moonachie NJ 07074",
    "addr:housenumber":"24",
    "addr:postcode":"07074",
    "addr:street":"Albert St",
    "iso:country":"US",
    "sg:address":"24 Albert St",
    "sg:city":"Moonachie",
    "sg:classifiers":[
        {
            "category":"Professional",
            "type":"Services"
        }
    ],
    "sg:phone":"+1   ",
    "sg:postcode":"07074",
    "sg:province":"NJ",
    "wof:name":"Manuel Martinez",
    "wof:placetype":"venue"
},
  "geometry": {"coordinates":[-74.04956,40.841849],"type":"Point"}
}