{
  "type": "Feature",
  "properties": {
    "iso:country":"US",
    "sg:address":"212 White Horse Pike",
    "sg:city":"W Colls",
    "sg:classifiers":[
        {
            "category":"Education",
            "subcategory":"Kindergarten",
            "type":"Public Place"
        }
    ],
    "sg:phone":"+1 856 854 2300",
    "sg:postcode":"08107",
    "sg:province":"NJ",
    "sg:tags":[
        "school",
        "driving"
    ],
    "wof:name":"Azure Driving Academy",
    "wof:placetype":"venue"
},
  "geometry": {"coordinates":[-75.087402,39.9165],"type":"Point"}
}