{
  "type": "Feature",
  "properties": {
    "addr:full":"1 Lloyd Ave Florham Park NJ 07932",
    "addr:housenumber":"1",
    "addr:postcode":"07932",
    "addr:street":"Lloyd Ave",
    "iso:country":"US",
    "sg:address":"1 Lloyd Ave",
    "sg:city":"Florham Park",
    "sg:classifiers":[
        {
            "category":"Organizations",
            "subcategory":"Religious Organization",
            "type":"Services"
        }
    ],
    "sg:phone":"+1 973 377 1817",
    "sg:postcode":"07932",
    "sg:province":"NJ",
    "sg:tags":[
        "church"
    ],
    "wof:name":"Holy Family Church",
    "wof:placetype":"venue"
},
  "geometry": {"coordinates":[-74.39142,40.778335],"type":"Point"}
}