{
  "type": "Feature",
  "properties": {
    "iso:country":"US",
    "sg:address":"609 Morris Ave",
    "sg:city":"Elizabeth",
    "sg:classifiers":[
        {
            "category":"Health Services",
            "subcategory":"Doctor",
            "type":"Services"
        }
    ],
    "sg:phone":"+1 908 351 1700",
    "sg:postcode":"07208",
    "sg:province":"NJ",
    "sg:tags":[
        "physician",
        "medical",
        "surgeon"
    ],
    "wof:name":"Morris Family Medical Center",
    "wof:placetype":"venue"
},
  "geometry": {"coordinates":[-74.22602999999999,40.67516],"type":"Point"}
}