{
  "type": "Feature",
  "properties": {
    "iso:country":"US",
    "sg:address":"17 Frances Ave",
    "sg:city":"Linwood",
    "sg:classifiers":[
        {
            "category":"Building & Trades",
            "subcategory":"Construction",
            "type":"Services"
        }
    ],
    "sg:phone":"+1 609 926 2005",
    "sg:postcode":"08221",
    "sg:province":"NJ",
    "sg:tags":[
        "contractor"
    ],
    "wof:name":"Donohoe Brothers Builders",
    "wof:placetype":"venue"
},
  "geometry": {"coordinates":[-74.58523599999999,39.331282],"type":"Point"}
}