{
  "type": "Feature",
  "properties": {
    "addr:full":"96 Montclair Ave Newark NJ 07104",
    "addr:housenumber":"96",
    "addr:postcode":"07104",
    "addr:street":"Montclair Ave",
    "iso:country":"US",
    "sg:address":"96 Montclair Ave",
    "sg:city":"Newark",
    "sg:classifiers":[
        {
            "category":"Building & Trades",
            "subcategory":"Cleaning & Sanitation",
            "type":"Services"
        }
    ],
    "sg:phone":"+1 973 412 7552",
    "sg:postcode":"07104",
    "sg:province":"NJ",
    "sg:tags":[
        "janitor"
    ],
    "wof:name":"Magic Touch Cleaning Svc",
    "wof:placetype":"venue"
},
  "geometry": {"coordinates":[-74.16029399999999,40.7779],"type":"Point"}
}