{
  "type": "Feature",
  "properties": {
    "addr:full":"230 Neptune Ave Jersey City NJ 07305",
    "addr:housenumber":"230",
    "addr:postcode":"07305",
    "addr:street":"Neptune Ave",
    "iso:country":"US",
    "sg:address":"230 Neptune Ave",
    "sg:city":"Jersey City",
    "sg:classifiers":[
        {
            "category":"Wholesale",
            "subcategory":"Construction Materials",
            "type":"Manufacturing & Wholesale Goods"
        }
    ],
    "sg:phone":"+1 201 319 0452",
    "sg:postcode":"07305",
    "sg:province":"NJ",
    "sg:tags":[
        "fence"
    ],
    "wof:name":"Hudson County Fence",
    "wof:placetype":"venue"
},
  "geometry": {"coordinates":[-74.09655100000001,40.693531],"type":"Point"}
}