{
  "type": "Feature",
  "properties": {
    "addr:full":"1711 W Elizabeth Ave Linden NJ 07036",
    "addr:housenumber":"1711",
    "addr:postcode":"07036",
    "addr:street":"W Elizabeth Ave",
    "iso:country":"US",
    "sg:address":"1711 W Elizabeth Ave",
    "sg:city":"Linden",
    "sg:classifiers":[
        {
            "category":"Wholesale",
            "subcategory":"Chemicals & Plastics",
            "type":"Manufacturing & Wholesale Goods"
        }
    ],
    "sg:phone":"+1 908 862 7726",
    "sg:postcode":"07036",
    "sg:province":"NJ",
    "wof:name":"Chemical Services Inc",
    "wof:placetype":"venue"
},
  "geometry": {"coordinates":[-74.256603,40.626789],"type":"Point"}
}