{
  "type": "Feature",
  "properties": {
    "iso:country":"US",
    "sg:address":"526 Sycamore St",
    "sg:city":"Rahway",
    "sg:classifiers":[
        {
            "category":"Professional",
            "subcategory":"Business Services",
            "type":"Services"
        }
    ],
    "sg:phone":"+1   ",
    "sg:postcode":"07065",
    "sg:province":"NJ",
    "wof:name":"Food Fashions LLC",
    "wof:placetype":"venue"
},
  "geometry": {"coordinates":[-74.293994,40.601858],"type":"Point"}
}