{
  "type": "Feature",
  "properties": {
    "iso:country":"US",
    "sg:address":"79 Pleasant Valley Rd",
    "sg:city":"Mendham",
    "sg:classifiers":[
        {
            "category":"Professional",
            "subcategory":"Business Services",
            "type":"Services"
        }
    ],
    "sg:phone":"+1 973 543 6988",
    "sg:postcode":"07945",
    "sg:province":"NJ",
    "wof:name":"Degregori Design LLC",
    "wof:placetype":"venue"
},
  "geometry": {"coordinates":[-74.61578900000001,40.751287],"type":"Point"}
}