{
  "type": "Feature",
  "properties": {
    "addr:full":"41 Larchwood Ave West Long Branch NJ 07764",
    "addr:housenumber":"41",
    "addr:postcode":"07764",
    "addr:street":"Larchwood Ave West",
    "iso:country":"US",
    "sg:address":"41 Larchwood Ave",
    "sg:city":"West Long Branch",
    "sg:classifiers":[
        {
            "category":"Manufacturing",
            "subcategory":"Printing",
            "type":"Manufacturing & Wholesale Goods"
        }
    ],
    "sg:phone":"+1 732 222 7934",
    "sg:postcode":"07764",
    "sg:province":"NJ",
    "sg:tags":[
        "publisher",
        "music"
    ],
    "wof:name":"Super Penetrator Publishing",
    "wof:placetype":"venue"
},
  "geometry": {"coordinates":[-74.011571,40.283607],"type":"Point"}
}