{
  "type": "Feature",
  "properties": {
    "addr:full":"117 E Main St Bound Brook NJ 08805",
    "addr:housenumber":"117",
    "addr:postcode":"08805",
    "addr:street":"E Main St",
    "iso:country":"US",
    "sg:address":"117 E Main St",
    "sg:city":"Bound Brook",
    "sg:classifiers":[
        {
            "category":"Retail",
            "subcategory":"Repair Shop",
            "type":"Services"
        }
    ],
    "sg:phone":"+1   ",
    "sg:postcode":"08805",
    "sg:province":"NJ",
    "wof:name":"24 Hour Emergency Locksmith",
    "wof:placetype":"venue"
},
  "geometry": {"coordinates":[-74.53235599999999,40.561668],"type":"Point"}
}