{
  "type": "Feature",
  "properties": {
    "addr:full":"201 North Ave Dunellen NJ 08812",
    "addr:housenumber":"201",
    "addr:postcode":"08812",
    "addr:street":"North Ave",
    "iso:country":"US",
    "sg:address":"201 North Ave",
    "sg:city":"Dunellen",
    "sg:classifiers":[
        {
            "category":"Retail",
            "subcategory":"Auto Rental",
            "type":"Services"
        }
    ],
    "sg:phone":"+1 732 752 6126",
    "sg:postcode":"08812",
    "sg:province":"NJ",
    "sg:tags":[
        "renting",
        "truck",
        "leasing"
    ],
    "wof:name":"U-Haul Co",
    "wof:placetype":"venue"
},
  "geometry": {"coordinates":[-74.463002,40.591895],"type":"Point"}
}