{
  "type": "Feature",
  "properties": {
    "iso:country":"US",
    "sg:address":"375 Brook Ave",
    "sg:city":"Passaic",
    "sg:classifiers":[
        {
            "category":"Professional",
            "subcategory":"Research",
            "type":"Services"
        }
    ],
    "sg:phone":"+1 973 472 3203",
    "sg:postcode":"07055",
    "sg:province":"NJ",
    "sg:tags":[
        "religious",
        "noncommercial"
    ],
    "wof:name":"Singer Shlomo Cantor",
    "wof:placetype":"venue"
},
  "geometry": {"coordinates":[-74.1409,40.846199],"type":"Point"}
}