{
  "type": "Feature",
  "properties": {
    "addr:full":"111 Tonnelle Ave Jersey City NJ 07306",
    "addr:housenumber":"111",
    "addr:postcode":"07306",
    "addr:street":"Tonnelle Ave",
    "iso:country":"US",
    "sg:address":"111 Tonnelle Ave",
    "sg:city":"Jersey City",
    "sg:classifiers":[
        {
            "category":"Autos & Motor Vehicles",
            "subcategory":"Automobile Sales",
            "type":"Retail Goods"
        }
    ],
    "sg:phone":"+1   ",
    "sg:postcode":"07306",
    "sg:province":"NJ",
    "sg:tags":[
        "used"
    ],
    "wof:name":"Metro Motors",
    "wof:placetype":"venue"
},
  "geometry": {"coordinates":[-74.066914,40.735398],"type":"Point"}
}