{
  "type": "Feature",
  "properties": {
    "addr:full":"2770 State Rte 23 Stockholm NJ 07460",
    "addr:housenumber":"2770",
    "addr:postcode":"07460",
    "addr:street":"State Rte 23",
    "iso:country":"US",
    "sg:address":"2770 State Rte 23",
    "sg:city":"Stockholm",
    "sg:classifiers":[
        {
            "category":"Autos & Motor Vehicles",
            "subcategory":"Fuel & Gas Station",
            "type":"Retail Goods"
        }
    ],
    "sg:phone":"+1 973 208 3100",
    "sg:postcode":"07460",
    "sg:province":"NJ",
    "sg:tags":[
        "oil"
    ],
    "wof:name":"Stockholm Gas Inc",
    "wof:placetype":"venue"
},
  "geometry": {"coordinates":[-74.52197200000001,41.090436],"type":"Point"}
}