{
  "type": "Feature",
  "properties": {
    "addr:full":"5 Winant Ave Ridgefield Park NJ 07660",
    "addr:housenumber":"5",
    "addr:postcode":"07660",
    "addr:street":"Winant Ave",
    "iso:country":"US",
    "sg:address":"5 Winant Ave",
    "sg:city":"Ridgefield Park",
    "sg:classifiers":[
        {
            "category":"Autos & Motor Vehicles",
            "subcategory":"Fuel & Gas Station",
            "type":"Retail Goods"
        }
    ],
    "sg:phone":"+1 201 229 0994",
    "sg:postcode":"07660",
    "sg:province":"NJ",
    "sg:tags":[
        "oil"
    ],
    "sg:website":"www.citgo.com",
    "wof:name":"Super Value-Citgo",
    "wof:placetype":"venue"
},
  "geometry": {"coordinates":[-74.025803,40.8503],"type":"Point"}
}