{
  "type": "Feature",
  "properties": {
    "addr:full":"809 Main St Belmar NJ 07719",
    "addr:housenumber":"809",
    "addr:postcode":"07719",
    "addr:street":"Main St",
    "iso:country":"US",
    "sg:address":"809 Main St",
    "sg:city":"Belmar",
    "sg:classifiers":[
        {
            "category":"Shopping",
            "subcategory":"Clothing, Apparel, & Fashions",
            "type":"Retail Goods"
        }
    ],
    "sg:phone":"+1 732 681 5550",
    "sg:postcode":"07719",
    "sg:province":"NJ",
    "sg:tags":[
        "item",
        "boutique"
    ],
    "wof:name":"Chix Boutique",
    "wof:placetype":"venue"
},
  "geometry": {"coordinates":[-74.02497200000001,40.181321],"type":"Point"}
}