{
  "type": "Feature",
  "properties": {
    "addr:full":"355 W Saint Georges Ave Linden NJ 07036",
    "addr:housenumber":"355",
    "addr:postcode":"07036",
    "addr:street":"W Saint Georges Ave",
    "iso:country":"US",
    "sg:address":"355 W Saint Georges Ave",
    "sg:city":"Linden",
    "sg:classifiers":[
        {
            "category":"Food & Beverages",
            "subcategory":"Liquor & Beverages",
            "type":"Retail Goods"
        }
    ],
    "sg:phone":"+1 908 290 3255",
    "sg:postcode":"07036",
    "sg:province":"NJ",
    "sg:tags":[
        "beer",
        "spirit",
        "wine"
    ],
    "wof:name":"Ks Liquor",
    "wof:placetype":"venue"
},
  "geometry": {"coordinates":[-74.268191,40.633004],"type":"Point"}
}