{
  "type": "Feature",
  "properties": {
    "addr:full":"910 Berlin Rd Voorhees NJ 08034",
    "addr:housenumber":"910",
    "addr:postcode":"08034",
    "addr:street":"Berlin Rd",
    "iso:country":"US",
    "sg:address":"910 Berlin Rd",
    "sg:city":"Voorhees",
    "sg:classifiers":[
        {
            "category":"Shopping",
            "subcategory":"Clothing, Apparel, & Fashions",
            "type":"Retail Goods"
        }
    ],
    "sg:phone":"+1   ",
    "sg:postcode":"08034",
    "sg:province":"NJ",
    "sg:tags":[
        "handbag"
    ],
    "wof:name":"Z Bag Shoppe",
    "wof:placetype":"venue"
},
  "geometry": {"coordinates":[-75.01720899999999,39.888194],"type":"Point"}
}