{
  "type": "Feature",
  "properties": {
    "addr:full":"3819 Bergenline Ave Union City NJ 07087",
    "addr:housenumber":"3819",
    "addr:postcode":"07087",
    "addr:street":"Bergenline Ave",
    "iso:country":"US",
    "sg:address":"3819 Bergenline Ave",
    "sg:city":"Union City",
    "sg:classifiers":[
        {
            "category":"Food & Beverages",
            "subcategory":"Liquor & Beverages",
            "type":"Retail Goods"
        }
    ],
    "sg:phone":"+1 201 348 1515",
    "sg:postcode":"07087",
    "sg:province":"NJ",
    "sg:tags":[
        "beer",
        "spirit",
        "wine"
    ],
    "wof:name":"Bergenline Wine and Liquors",
    "wof:placetype":"venue"
},
  "geometry": {"coordinates":[-74.02660400000001,40.7757],"type":"Point"}
}