{
  "type": "Feature",
  "properties": {
    "addr:full":"9 Fairview Pl Bloomfield NJ 07003",
    "addr:housenumber":"9",
    "addr:postcode":"07003",
    "addr:street":"Fairview Pl",
    "iso:country":"US",
    "sg:address":"9 Fairview Pl",
    "sg:city":"Bloomfield",
    "sg:classifiers":[
        {
            "category":"Building & Trades",
            "subcategory":"Construction",
            "type":"Services"
        }
    ],
    "sg:phone":"+1 973 743 9998",
    "sg:postcode":"07003",
    "sg:province":"NJ",
    "sg:tags":[
        "bathroom",
        "remodeling"
    ],
    "wof:name":"All In One",
    "wof:placetype":"venue"
},
  "geometry": {"coordinates":[-74.187521,40.790033],"type":"Point"}
}