{
  "type": "Feature",
  "properties": {
    "addr:full":"3501 Route 42 Blackwood NJ 08012",
    "addr:housenumber":"3501",
    "addr:postcode":"08012",
    "addr:street":"Route 42",
    "iso:country":"US",
    "sg:address":"3501 Route 42",
    "sg:city":"Blackwood",
    "sg:classifiers":[
        {
            "category":"Personal",
            "subcategory":"Beauty Salon",
            "type":"Services"
        },
        {
            "category":"Personal",
            "subcategory":"Barber",
            "type":"Services"
        }
    ],
    "sg:phone":"+1 856 875 7660",
    "sg:postcode":"08012",
    "sg:province":"NJ",
    "sg:tags":[
        "hair",
        "accessory",
        "stylist",
        "supply"
    ],
    "sg:website":"http://www.haircuttery.com/",
    "wof:name":"Hair Cuttery",
    "wof:placetype":"venue"
},
  "geometry": {"coordinates":[-75.033936,39.73048],"type":"Point"}
}