{
  "type": "Feature",
  "properties": {
    "iso:country":"US",
    "sg:address":"80 Eisenhower Dr",
    "sg:city":"Paramus",
    "sg:classifiers":[
        {
            "category":"Health Services",
            "subcategory":"Doctor",
            "type":"Services"
        }
    ],
    "sg:phone":"+1 201 368 6999",
    "sg:postcode":"07652",
    "sg:province":"NJ",
    "sg:tags":[
        "physician",
        "surgeon"
    ],
    "wof:name":"Pinnacle Medical Group Pharm",
    "wof:placetype":"venue"
},
  "geometry": {"coordinates":[-74.080375,40.931678],"type":"Point"}
}