{
  "type": "Feature",
  "properties": {
    "addr:full":"78 Longwood Ave Red Bank NJ 07701",
    "addr:housenumber":"78",
    "addr:postcode":"07701",
    "addr:street":"Longwood Ave",
    "iso:country":"US",
    "sg:address":"78 Longwood Ave",
    "sg:city":"Red Bank",
    "sg:classifiers":[
        {
            "category":"Shopping",
            "subcategory":"Gifts & Souvenirs",
            "type":"Retail Goods"
        }
    ],
    "sg:phone":"+1 732 758 9144",
    "sg:postcode":"07701",
    "sg:province":"NJ",
    "sg:tags":[
        "collectible"
    ],
    "wof:name":"Renaissance Gallery",
    "wof:placetype":"venue"
},
  "geometry": {"coordinates":[-74.088206,40.368647],"type":"Point"}
}