{
  "type": "Feature",
  "properties": {
    "addr:full":"97 Main St Newton NJ 07840",
    "addr:housenumber":"97",
    "addr:postcode":"07840",
    "addr:street":"Main St",
    "iso:country":"US",
    "sg:address":"97 Main St",
    "sg:city":"Newton",
    "sg:classifiers":[
        {
            "category":"Real Estate",
            "subcategory":"Real Estate Agent",
            "type":"Services"
        }
    ],
    "sg:phone":"+1 973 383 7300",
    "sg:postcode":"07840",
    "sg:province":"NJ",
    "wof:name":"Heritage Real Estate",
    "wof:placetype":"venue"
},
  "geometry": {"coordinates":[-74.831208,40.85477],"type":"Point"}
}