{
  "type": "Feature",
  "properties": {
    "addr:full":"42 Branford Pl Newark NJ 07102",
    "addr:housenumber":"42",
    "addr:postcode":"07102",
    "addr:street":"Branford Pl",
    "iso:country":"US",
    "sg:address":"42 Branford Pl",
    "sg:city":"Newark",
    "sg:classifiers":[
        {
            "category":"Shopping",
            "subcategory":"Clothing, Apparel, & Fashions",
            "type":"Retail Goods"
        }
    ],
    "sg:phone":"+1 973 621 9146",
    "sg:postcode":"07102",
    "sg:province":"NJ",
    "sg:tags":[
        "tailor",
        "alteration",
        "sewing"
    ],
    "wof:name":"Leo Cleaners",
    "wof:placetype":"venue"
},
  "geometry": {"coordinates":[-74.175301,40.7356],"type":"Point"}
}