{
  "type": "Feature",
  "properties": {
    "addr:full":"77 Ellis St Haddonfield NJ 08033",
    "addr:housenumber":"77",
    "addr:postcode":"08033",
    "addr:street":"Ellis St",
    "iso:country":"US",
    "sg:address":"77 Ellis St",
    "sg:city":"Haddonfield",
    "sg:classifiers":[
        {
            "category":"Building & Trades",
            "subcategory":"Cleaning & Sanitation",
            "type":"Services"
        }
    ],
    "sg:phone":"+1 856 795 0032",
    "sg:postcode":"08033",
    "sg:province":"NJ",
    "sg:tags":[
        "janitor"
    ],
    "wof:name":"D & V Janitorial Svc",
    "wof:placetype":"venue"
},
  "geometry": {"coordinates":[-75.029045,39.896637],"type":"Point"}
}