{
  "type": "Feature",
  "properties": {
    "iso:country":"US",
    "sg:address":"10 South St",
    "sg:city":"New Providence",
    "sg:classifiers":[
        {
            "category":"Personal",
            "subcategory":"Beauty Salon",
            "type":"Services"
        }
    ],
    "sg:phone":"+1   ",
    "sg:postcode":"07974",
    "sg:province":"NJ",
    "sg:tags":[
        "shop"
    ],
    "wof:name":"Hair & Beyond",
    "wof:placetype":"venue"
},
  "geometry": {"coordinates":[-74.405528,40.703438],"type":"Point"}
}