{
  "type": "Feature",
  "properties": {
    "iso:country":"US",
    "sg:address":"651 Kapkowski Rd",
    "sg:city":"Elizabeth",
    "sg:classifiers":[
        {
            "category":"Shopping",
            "subcategory":"Clothing, Apparel, & Fashions",
            "type":"Retail Goods"
        }
    ],
    "sg:phone":"+1 908 659 1657",
    "sg:postcode":"07201",
    "sg:province":"NJ",
    "sg:tags":[
        "shop",
        "specialty"
    ],
    "wof:name":"Icing By Claire's",
    "wof:placetype":"venue"
},
  "geometry": {"coordinates":[-74.174531,40.662922],"type":"Point"}
}