{
  "type": "Feature",
  "properties": {
    "addr:full":"43 Charles St Jersey City NJ 07307",
    "addr:housenumber":"43",
    "addr:postcode":"07307",
    "addr:street":"Charles St",
    "iso:country":"US",
    "sg:address":"43 Charles St",
    "sg:city":"Jersey City",
    "sg:classifiers":[
        {
            "category":"Education",
            "subcategory":"Special Training",
            "type":"Public Place"
        }
    ],
    "sg:phone":"+1 201 798 9438",
    "sg:postcode":"07307",
    "sg:province":"NJ",
    "sg:tags":[
        "school",
        "art"
    ],
    "wof:name":"Hope Center the",
    "wof:placetype":"venue"
},
  "geometry": {"coordinates":[-74.050301,40.748699],"type":"Point"}
}