{
  "type": "Feature",
  "properties": {
    "addr:full":"880 Harding Hwy Buena NJ 08310",
    "addr:housenumber":"880",
    "addr:postcode":"08310",
    "addr:street":"Harding Hwy",
    "iso:country":"US",
    "sg:address":"880 Harding Hwy",
    "sg:city":"Buena",
    "sg:classifiers":[
        {
            "category":"Education",
            "subcategory":"School",
            "type":"Public Place"
        }
    ],
    "sg:phone":"+1   ",
    "sg:postcode":"08310",
    "sg:province":"NJ",
    "wof:name":"John C Mlanesi Elementary Schl",
    "wof:placetype":"venue"
},
  "geometry": {"coordinates":[-74.906604,39.505833],"type":"Point"}
}