{
  "type": "Feature",
  "properties": {
    "iso:country":"US",
    "sg:address":"578 Pompton Ave",
    "sg:city":"Cedar Grove",
    "sg:classifiers":[
        {
            "category":"Professional",
            "type":"Services"
        },
        {
            "category":"Deli",
            "type":"Food & Drink"
        }
    ],
    "sg:phone":"+1 973 239 4180",
    "sg:postcode":"07009",
    "sg:province":"NJ",
    "sg:tags":[
        "caterer"
    ],
    "wof:name":"Cedar Grove Deli & Caterers",
    "wof:placetype":"venue"
},
  "geometry": {"coordinates":[-74.229698,40.852501],"type":"Point"}
}