{
  "type": "Feature",
  "properties": {
    "iso:country":"US",
    "sg:address":"136 Broadway",
    "sg:city":"Woodcliff Lake",
    "sg:classifiers":[
        {
            "category":"Health Services",
            "subcategory":"Chiropractor",
            "type":"Services"
        }
    ],
    "sg:phone":"+1 201 476 0555",
    "sg:postcode":"07677",
    "sg:province":"NJ",
    "wof:name":"Al Salvatore Dc",
    "wof:placetype":"venue"
},
  "geometry": {"coordinates":[-74.04074199999999,41.018283],"type":"Point"}
}