{
  "type": "Feature",
  "properties": {
    "addr:full":"295 Monmouth St Hightstown NJ 08520",
    "addr:housenumber":"295",
    "addr:postcode":"08520",
    "addr:street":"Monmouth St",
    "iso:country":"US",
    "sg:address":"295 Monmouth St",
    "sg:city":"Hightstown",
    "sg:classifiers":[
        {
            "category":"Professional",
            "subcategory":"Management & Consulting",
            "type":"Services"
        }
    ],
    "sg:phone":"+1   ",
    "sg:postcode":"08520",
    "sg:province":"NJ",
    "wof:name":"Time Save Communications Inc",
    "wof:placetype":"venue"
},
  "geometry": {"coordinates":[-74.515917,40.271851],"type":"Point"}
}