{
  "type": "Feature",
  "properties": {
    "addr:full":"942 Aberdeen Dr Lakewood NJ 08701",
    "addr:housenumber":"942",
    "addr:postcode":"08701",
    "addr:street":"Aberdeen Dr",
    "iso:country":"US",
    "sg:address":"942 Aberdeen Dr",
    "sg:city":"Lakewood",
    "sg:classifiers":[
        {
            "category":"Insurance",
            "subcategory":"Insurance Agent",
            "type":"Services"
        }
    ],
    "sg:phone":"+1   ",
    "sg:postcode":"08701",
    "sg:province":"NJ",
    "wof:name":"Troise Insurance Agency",
    "wof:placetype":"venue"
},
  "geometry": {"coordinates":[-74.16677300000001,40.031477],"type":"Point"}
}