{
  "type": "Feature",
  "properties": {
    "iso:country":"US",
    "sg:address":"7900 Long Beach Blvd",
    "sg:city":"Long Beach Twp",
    "sg:classifiers":[
        {
            "category":"Real Estate",
            "subcategory":"Real Estate Agent",
            "type":"Services"
        }
    ],
    "sg:phone":"+1 609 494 6666",
    "sg:postcode":"08008",
    "sg:province":"NJ",
    "sg:website":"www.lbirealestate.com",
    "wof:name":"Crest Realty",
    "wof:placetype":"venue"
},
  "geometry": {"coordinates":[-74.20465799999999,39.610999],"type":"Point"}
}