{
  "type": "Feature",
  "properties": {
    "addr:full":"2 Warren St Paterson NJ 07524",
    "addr:housenumber":"2",
    "addr:postcode":"07524",
    "addr:street":"Warren St",
    "iso:country":"US",
    "sg:address":"2 Warren St",
    "sg:city":"Paterson",
    "sg:classifiers":[
        {
            "category":"Wholesale",
            "subcategory":"Meat",
            "type":"Manufacturing & Wholesale Goods"
        }
    ],
    "sg:phone":"+1 973 345 7600",
    "sg:postcode":"07524",
    "sg:province":"NJ",
    "sg:tags":[
        "broker"
    ],
    "wof:name":"Pasha Quality Meat Inc",
    "wof:placetype":"venue"
},
  "geometry": {"coordinates":[-74.16412699999999,40.927873],"type":"Point"}
}