{
  "type": "Feature",
  "properties": {
    "iso:country":"US",
    "sg:address":"97 East 2nd St",
    "sg:city":"Bayonne",
    "sg:classifiers":[
        {
            "category":"Personal",
            "type":"Services"
        }
    ],
    "sg:phone":"+1 973 581 7111",
    "sg:postcode":"07002",
    "sg:province":"NJ",
    "sg:tags":[
        "mover"
    ],
    "wof:name":"Security Moving and Storage",
    "wof:placetype":"venue"
},
  "geometry": {"coordinates":[-74.124081,40.64715],"type":"Point"}
}