{
  "type": "Feature",
  "properties": {
    "addr:full":"434 Harrison Ave Harrison NJ 07029",
    "addr:housenumber":"434",
    "addr:postcode":"07029",
    "addr:street":"Harrison Ave",
    "iso:country":"US",
    "sg:address":"434 Harrison Ave",
    "sg:city":"Harrison",
    "sg:classifiers":[
        {
            "category":"Building & Trades",
            "subcategory":"Construction",
            "type":"Services"
        },
        {
            "category":"Retail",
            "subcategory":"Auto Repair",
            "type":"Services"
        }
    ],
    "sg:phone":"+1 973 484 5552",
    "sg:postcode":"07029",
    "sg:province":"NJ",
    "sg:tags":[
        "glass",
        "coating",
        "tinting",
        "contractor"
    ],
    "wof:name":"5 Star Window Tint Inc",
    "wof:placetype":"venue"
},
  "geometry": {"coordinates":[-74.154188,40.74688],"type":"Point"}
}