{
  "type": "Feature",
  "properties": {
    "addr:full":"17 Division St South River NJ 08882",
    "addr:housenumber":"17",
    "addr:postcode":"08882",
    "addr:street":"Division St",
    "iso:country":"US",
    "sg:address":"17 Division St",
    "sg:city":"South River",
    "sg:classifiers":[
        {
            "category":"Food & Beverages",
            "subcategory":"Groceries & Convenience Stores",
            "type":"Retail Goods"
        }
    ],
    "sg:phone":"+1 732 390 1422",
    "sg:postcode":"08882",
    "sg:province":"NJ",
    "wof:name":"Wawa Food Market",
    "wof:placetype":"venue"
},
  "geometry": {"coordinates":[-74.378336,40.444962],"type":"Point"}
}