{
  "type": "Feature",
  "properties": {
    "iso:country":"US",
    "sg:address":"445 Main St",
    "sg:city":"Metuchen",
    "sg:classifiers":[
        {
            "category":"Banks & Credit Unions",
            "subcategory":"Bank",
            "type":"Services"
        }
    ],
    "sg:phone":"+1 732 548 5885",
    "sg:postcode":"08840",
    "sg:province":"NJ",
    "sg:tags":[
        "money",
        "transfer"
    ],
    "wof:name":"Western Union",
    "wof:placetype":"venue"
},
  "geometry": {"coordinates":[-74.36205,40.542261],"type":"Point"}
}