{
  "type": "Feature",
  "properties": {
    "iso:country":"US",
    "sg:address":"152 Broad St",
    "sg:city":"Hightstown",
    "sg:classifiers":[
        {
            "category":"Farming",
            "subcategory":"Livestock Farm",
            "type":"Manufacturing & Wholesale Goods"
        }
    ],
    "sg:phone":"+1 609 443 1835",
    "sg:postcode":"08520",
    "sg:province":"NJ",
    "sg:tags":[
        "grocery",
        "specialty",
        "animal"
    ],
    "wof:name":"Bountiful Bees Broad Street",
    "wof:placetype":"venue"
},
  "geometry": {"coordinates":[-74.52026499999999,40.271233],"type":"Point"}
}