{
  "type": "Feature",
  "properties": {
    "addr:full":"134 Page Dr Oakland NJ 07436",
    "addr:housenumber":"134",
    "addr:postcode":"07436",
    "addr:street":"Page Dr",
    "iso:country":"US",
    "sg:address":"134 Page Dr",
    "sg:city":"Oakland",
    "sg:classifiers":[
        {
            "category":"Professional",
            "subcategory":"Management & Consulting",
            "type":"Services"
        }
    ],
    "sg:phone":"+1   ",
    "sg:postcode":"07436",
    "sg:province":"NJ",
    "sg:tags":[
        "business"
    ],
    "wof:name":"Fz Consulting Inc",
    "wof:placetype":"venue"
},
  "geometry": {"coordinates":[-74.24101400000001,41.013076],"type":"Point"}
}