{
  "type": "Feature",
  "properties": {
    "iso:country":"US",
    "sg:address":"116 Oldwick Rd",
    "sg:city":"Whitehouse Station",
    "sg:classifiers":[
        {
            "category":"Professional",
            "type":"Services"
        }
    ],
    "sg:phone":"+1 908 669 1229",
    "sg:postcode":"08889",
    "sg:province":"NJ",
    "wof:name":"Truscribe Transcription Services",
    "wof:placetype":"venue"
},
  "geometry": {"coordinates":[-74.75474699999999,40.650226],"type":"Point"}
}