{
  "type": "Feature",
  "properties": {
    "iso:country":"US",
    "sg:address":"59 Franklin St",
    "sg:city":"Morristown",
    "sg:classifiers":[
        {
            "category":"Health Services",
            "subcategory":"Doctor",
            "type":"Services"
        }
    ],
    "sg:phone":"+1 973 538 1515",
    "sg:postcode":"07960",
    "sg:province":"NJ",
    "sg:tags":[
        "obstetrician",
        "gynecologist"
    ],
    "sg:website":"www.lma-llc.com",
    "wof:name":"Obstetrical & Gynecological Associates of Morrs PA",
    "wof:placetype":"venue"
},
  "geometry": {"coordinates":[-74.471807,40.791262],"type":"Point"}
}