{
  "type": "Feature",
  "properties": {
    "addr:full":"205 Broadway Tpke Camden NJ 08103",
    "addr:housenumber":"205",
    "addr:postcode":"08103",
    "addr:street":"Broadway Tpke",
    "iso:country":"US",
    "sg:address":"205 Broadway Tpke",
    "sg:city":"Camden",
    "sg:classifiers":[
        {
            "category":"Shopping",
            "subcategory":"Discount & Variety Stores",
            "type":"Retail Goods"
        }
    ],
    "sg:phone":"+1 856 966 1459",
    "sg:postcode":"08103",
    "sg:province":"NJ",
    "wof:name":"99 Cent Store",
    "wof:placetype":"venue"
},
  "geometry": {"coordinates":[-75.119347,39.941581],"type":"Point"}
}