{
  "type": "Feature",
  "properties": {
    "iso:country":"US",
    "sg:address":"75 Elizabeth Ave",
    "sg:city":"Elizabeth",
    "sg:classifiers":[
        {
            "category":"Professional",
            "subcategory":"Lawyer & Legal Services",
            "type":"Services"
        }
    ],
    "sg:phone":"+1 908 353 6764",
    "sg:postcode":"07206",
    "sg:province":"NJ",
    "wof:name":"Mandelbaum Salsburg Gold Lazris Discenza & Stenbrg",
    "wof:placetype":"venue"
},
  "geometry": {"coordinates":[-74.190399,40.645699],"type":"Point"}
}