{
  "type": "Feature",
  "properties": {
    "iso:country":"US",
    "sg:address":"48 Wyker Rd",
    "sg:city":"Franklin",
    "sg:classifiers":[
        {
            "category":"Social Services",
            "subcategory":"Adult Care",
            "type":"Services"
        }
    ],
    "sg:phone":"+1 973 209 0123",
    "sg:postcode":"07416",
    "sg:province":"NJ",
    "sg:tags":[
        "organization",
        "senior",
        "citizen"
    ],
    "wof:name":"Catholic Family/Community Svc",
    "wof:placetype":"venue"
},
  "geometry": {"coordinates":[-74.588337,41.119848],"type":"Point"}
}