{
  "type": "Feature",
  "properties": {
    "iso:country":"US",
    "sg:address":"12 Emerson Ter",
    "sg:city":"Bloomfield",
    "sg:classifiers":[
        {
            "category":"Taxi",
            "type":"Transportation"
        }
    ],
    "sg:phone":"+1 973 893 8033",
    "sg:postcode":"07003",
    "sg:province":"NJ",
    "sg:tags":[
        "taxicab"
    ],
    "wof:name":"Kids Cab",
    "wof:placetype":"venue"
},
  "geometry": {"coordinates":[-74.189486,40.829611],"type":"Point"}
}