{
  "type": "Feature",
  "properties": {
    "iso:country":"US",
    "sg:address":"358 Broadway",
    "sg:city":"Newark",
    "sg:classifiers":[
        {
            "category":"Building & Trades",
            "subcategory":"Locksmith",
            "type":"Services"
        }
    ],
    "sg:phone":"+1 973 484 4501",
    "sg:postcode":"07104",
    "sg:province":"NJ",
    "sg:tags":[
        "key"
    ],
    "wof:name":"V Nole Glass & Lock Co",
    "wof:placetype":"venue"
},
  "geometry": {"coordinates":[-74.167,40.762901],"type":"Point"}
}