{
  "type": "Feature",
  "properties": {
    "addr:full":"78 Market St Passaic NJ 07055",
    "addr:housenumber":"78",
    "addr:postcode":"07055",
    "addr:street":"Market St",
    "iso:country":"US",
    "sg:address":"78 Market St",
    "sg:city":"Passaic",
    "sg:classifiers":[
        {
            "category":"Building & Trades",
            "subcategory":"Pest Control",
            "type":"Services"
        }
    ],
    "sg:phone":"+1 973 956 1987",
    "sg:postcode":"07055",
    "sg:province":"NJ",
    "wof:name":"All Garden Pest Control",
    "wof:placetype":"venue"
},
  "geometry": {"coordinates":[-74.116479,40.864037],"type":"Point"}
}