{
  "type": "Feature",
  "properties": {
    "iso:country":"US",
    "sg:address":"909 Liberty St",
    "sg:city":"Trenton",
    "sg:classifiers":[
        {
            "category":"Building & Trades",
            "subcategory":"Construction",
            "type":"Services"
        }
    ],
    "sg:phone":"+1 609 393 7700",
    "sg:postcode":"08611",
    "sg:province":"NJ",
    "sg:tags":[
        "general",
        "contractor"
    ],
    "wof:name":"Fence Tech Corp",
    "wof:placetype":"venue"
},
  "geometry": {"coordinates":[-74.738722,40.208236],"type":"Point"}
}