{
  "type": "Feature",
  "properties": {
    "addr:full":"272 US Hwy 46 Totowa NJ 07512",
    "addr:housenumber":"272",
    "addr:postcode":"07512",
    "addr:street":"Us Hwy 46",
    "iso:country":"US",
    "sg:address":"272 US Hwy 46",
    "sg:city":"Totowa",
    "sg:classifiers":[
        {
            "category":"Autos & Motor Vehicles",
            "subcategory":"Fuel & Gas Station",
            "type":"Retail Goods"
        }
    ],
    "sg:phone":"+1   ",
    "sg:postcode":"07512",
    "sg:province":"NJ",
    "sg:tags":[
        "station",
        "gasoline"
    ],
    "wof:name":"Amoco",
    "wof:placetype":"venue"
},
  "geometry": {"coordinates":[-74.23485100000001,40.894563],"type":"Point"}
}