{
  "type": "Feature",
  "properties": {
    "iso:country":"US",
    "sg:address":"875 US Hwy 9",
    "sg:city":"Manahawkin",
    "sg:classifiers":[
        {
            "category":"Retail",
            "subcategory":"Auto Repair",
            "type":"Services"
        }
    ],
    "sg:phone":"+1 609 597 8811",
    "sg:postcode":"08050",
    "sg:province":"NJ",
    "sg:tags":[
        "repairing",
        "automobile"
    ],
    "sg:website":"www.meineke.com",
    "wof:name":"Meineke Car Care Ctr",
    "wof:placetype":"venue"
},
  "geometry": {"coordinates":[-74.24683899999999,39.717124],"type":"Point"}
}