{
  "type": "Feature",
  "properties": {
    "addr:full":"216 Broad St Florence NJ 08518",
    "addr:housenumber":"216",
    "addr:postcode":"08518",
    "addr:street":"Broad St",
    "iso:country":"US",
    "sg:address":"216 Broad St",
    "sg:city":"Florence",
    "sg:classifiers":[
        {
            "category":"Health Services",
            "subcategory":"Optometrist",
            "type":"Services"
        }
    ],
    "sg:phone":"+1 609 499 1300",
    "sg:postcode":"08518",
    "sg:province":"NJ",
    "wof:name":"Brobst James OD",
    "wof:placetype":"venue"
},
  "geometry": {"coordinates":[-74.805199,40.120499],"type":"Point"}
}