{
  "type": "Feature",
  "properties": {
    "iso:country":"US",
    "sg:address":"126 Samuel Ct",
    "sg:city":"Lincroft",
    "sg:classifiers":[
        {
            "category":"Home & Garden",
            "subcategory":"Carpets & Floor Coverings",
            "type":"Retail Goods"
        }
    ],
    "sg:phone":"+1 732 747 0770",
    "sg:postcode":"07738",
    "sg:province":"NJ",
    "sg:tags":[
        "material",
        "contractor"
    ],
    "wof:name":"Lou's Ceramic Tile",
    "wof:placetype":"venue"
},
  "geometry": {"coordinates":[-74.119507,40.333876],"type":"Point"}
}