{
  "type": "Feature",
  "properties": {
    "addr:full":"166 Tooker Ave Springfield NJ 07081",
    "addr:housenumber":"166",
    "addr:postcode":"07081",
    "addr:street":"Tooker Ave",
    "iso:country":"US",
    "sg:address":"166 Tooker Ave",
    "sg:city":"Springfield",
    "sg:classifiers":[
        {
            "category":"Shopping",
            "subcategory":"Computers & Home Electronics",
            "type":"Retail Goods"
        }
    ],
    "sg:phone":"+1   ",
    "sg:postcode":"07081",
    "sg:province":"NJ",
    "sg:tags":[
        "repair"
    ],
    "wof:name":"Ehrhardt Television",
    "wof:placetype":"venue"
},
  "geometry": {"coordinates":[-74.321996,40.709479],"type":"Point"}
}