{
  "type": "Feature",
  "properties": {
    "addr:full":"221 Millstone Rd Englishtown NJ 08535",
    "addr:housenumber":"221",
    "addr:postcode":"08535",
    "addr:street":"Millstone Rd",
    "iso:country":"US",
    "sg:address":"221 Millstone Rd",
    "sg:city":"Englishtown",
    "sg:classifiers":[
        {
            "category":"Building & Trades",
            "subcategory":"Cleaning & Sanitation",
            "type":"Services"
        }
    ],
    "sg:phone":"+1 732 446 1919",
    "sg:postcode":"08535",
    "sg:province":"NJ",
    "sg:tags":[
        "janitor"
    ],
    "wof:name":"Rick's Betty Brite Cleaners",
    "wof:placetype":"venue"
},
  "geometry": {"coordinates":[-74.429401,40.222818],"type":"Point"}
}