{
  "type": "Feature",
  "properties": {
    "addr:full":"45 Lehigh St Dover NJ 07801",
    "addr:housenumber":"45",
    "addr:postcode":"07801",
    "addr:street":"Lehigh St",
    "iso:country":"US",
    "sg:address":"45 Lehigh St",
    "sg:city":"Dover",
    "sg:classifiers":[
        {
            "category":"Professional",
            "type":"Services"
        }
    ],
    "sg:phone":"+1 973 328 9438",
    "sg:postcode":"07801",
    "sg:province":"NJ",
    "sg:tags":[
        "establishment"
    ],
    "wof:name":"Joe Kubert Sch-Cartoon",
    "wof:placetype":"venue"
},
  "geometry": {"coordinates":[-74.57301099999999,40.888959],"type":"Point"}
}