{
  "type": "Feature",
  "properties": {
    "addr:full":"29 Kendal Ave Maplewood NJ 07040",
    "addr:housenumber":"29",
    "addr:postcode":"07040",
    "addr:street":"Kendal Ave",
    "iso:country":"US",
    "sg:address":"29 Kendal Ave",
    "sg:city":"Maplewood",
    "sg:classifiers":[
        {
            "category":"Professional",
            "subcategory":"Advertising",
            "type":"Services"
        }
    ],
    "sg:phone":"+1   ",
    "sg:postcode":"07040",
    "sg:province":"NJ",
    "sg:tags":[
        "agency"
    ],
    "wof:name":"New Ideas",
    "wof:placetype":"venue"
},
  "geometry": {"coordinates":[-74.273515,40.737971],"type":"Point"}
}