{
  "type": "Feature",
  "properties": {
    "iso:country":"US",
    "sg:address":"506 Main St",
    "sg:city":"Bradley Beach",
    "sg:classifiers":[
        {
            "category":"Health Services",
            "subcategory":"Chiropractor",
            "type":"Services"
        }
    ],
    "sg:phone":"+1 732 775 4448",
    "sg:postcode":"07720",
    "sg:province":"NJ",
    "wof:name":"Family Chiropractic Center",
    "wof:placetype":"venue"
},
  "geometry": {"coordinates":[-74.017916,40.202997],"type":"Point"}
}