{
  "type": "Feature",
  "properties": {
    "addr:full":"5 Chilton Rd Chester NJ 07930",
    "addr:housenumber":"5",
    "addr:postcode":"07930",
    "addr:street":"Chilton Rd",
    "iso:country":"US",
    "sg:address":"5 Chilton Rd",
    "sg:city":"Chester",
    "sg:classifiers":[
        {
            "category":"Professional",
            "subcategory":"Management & Consulting",
            "type":"Services"
        }
    ],
    "sg:phone":"+1 908 879 5966",
    "sg:postcode":"07930",
    "sg:province":"NJ",
    "sg:tags":[
        "consultant",
        "business"
    ],
    "wof:name":"Jack E Crouch & Assoc",
    "wof:placetype":"venue"
},
  "geometry": {"coordinates":[-74.68686,40.756505],"type":"Point"}
}