{
  "type": "Feature",
  "properties": {
    "iso:country":"US",
    "sg:address":"1 Monroe St",
    "sg:city":"Keyport",
    "sg:classifiers":[
        {
            "category":"Retail",
            "subcategory":"Auto Rental",
            "type":"Services"
        }
    ],
    "sg:phone":"+1   ",
    "sg:postcode":"07735",
    "sg:province":"NJ",
    "wof:name":"Bayshore Auto Rentals",
    "wof:placetype":"venue"
},
  "geometry": {"coordinates":[-74.20228299999999,40.426126],"type":"Point"}
}