{
  "type": "Feature",
  "properties": {
    "iso:country":"US",
    "sg:address":"45 Townsend Dr",
    "sg:city":"Florham Park",
    "sg:classifiers":[
        {
            "category":"Professional",
            "type":"Services"
        }
    ],
    "sg:phone":"+1 973 822 1966",
    "sg:postcode":"07932",
    "sg:province":"NJ",
    "sg:tags":[
        "establishment"
    ],
    "wof:name":"Endeavour Associates",
    "wof:placetype":"venue"
},
  "geometry": {"coordinates":[-74.405694,40.777647],"type":"Point"}
}