{
  "type": "Feature",
  "properties": {
    "iso:country":"US",
    "sg:address":"2206 Kuser Rd",
    "sg:city":"Trenton",
    "sg:classifiers":[
        {
            "category":"Social Services",
            "type":"Services"
        }
    ],
    "sg:phone":"+1 609 581 1619",
    "sg:postcode":"08690",
    "sg:province":"NJ",
    "sg:tags":[
        "youth",
        "organization",
        "center"
    ],
    "wof:name":"Nottingham Babe Ruth",
    "wof:placetype":"venue"
},
  "geometry": {"coordinates":[-74.682149,40.202722],"type":"Point"}
}