{
  "type": "Feature",
  "properties": {
    "iso:country":"US",
    "sg:address":"2114 Grier Ave",
    "sg:city":"Linden",
    "sg:classifiers":[
        {
            "category":"Building & Trades",
            "subcategory":"Locksmith",
            "type":"Services"
        }
    ],
    "sg:phone":"+1 908 986 5540",
    "sg:postcode":"07036",
    "sg:province":"NJ",
    "sg:tags":[
        "key"
    ],
    "wof:name":"Linden Locksmith",
    "wof:placetype":"venue"
},
  "geometry": {"coordinates":[-74.22380699999999,40.644667],"type":"Point"}
}