{
  "type": "Feature",
  "properties": {
    "addr:full":"50 E 17th St Paterson NJ 07524",
    "addr:housenumber":"50",
    "addr:postcode":"07524",
    "addr:street":"E 17Th St",
    "iso:country":"US",
    "sg:address":"50 E 17th St",
    "sg:city":"Paterson",
    "sg:classifiers":[
        {
            "category":"Wholesale",
            "subcategory":"Machinery & Supplies",
            "type":"Manufacturing & Wholesale Goods"
        }
    ],
    "sg:phone":"+1 973 569 9277",
    "sg:postcode":"07524",
    "sg:province":"NJ",
    "sg:tags":[
        "heat",
        "exchanger"
    ],
    "wof:name":"Spirec North America Inc",
    "wof:placetype":"venue"
},
  "geometry": {"coordinates":[-74.15093899999999,40.937079],"type":"Point"}
}