{
  "type": "Feature",
  "properties": {
    "iso:country":"US",
    "sg:address":"1193 Ridge Dr",
    "sg:city":"Mountainside",
    "sg:classifiers":[
        {
            "category":"Building & Trades",
            "subcategory":"Construction",
            "type":"Services"
        }
    ],
    "sg:phone":"+1 908 233 8585",
    "sg:postcode":"07092",
    "sg:province":"NJ",
    "sg:tags":[
        "home",
        "improvement"
    ],
    "wof:name":"Accents Restorations",
    "wof:placetype":"venue"
},
  "geometry": {"coordinates":[-74.356255,40.685737],"type":"Point"}
}