{
  "type": "Feature",
  "properties": {
    "iso:country":"US",
    "sg:address":"118 Broad Ave",
    "sg:city":"Palisades Park",
    "sg:classifiers":[
        {
            "category":"Personal",
            "subcategory":"Massage",
            "type":"Services"
        }
    ],
    "sg:phone":"+1 201 941 9111",
    "sg:postcode":"07650",
    "sg:province":"NJ",
    "wof:name":"Angel Health Spa & Skincare",
    "wof:placetype":"venue"
},
  "geometry": {"coordinates":[-74.00009900000001,40.8447],"type":"Point"}
}