{
  "type": "Feature",
  "properties": {
    "addr:full":"710 Main St Bradley Beach NJ 07720",
    "addr:housenumber":"710",
    "addr:postcode":"07720",
    "addr:street":"Main St",
    "iso:country":"US",
    "sg:address":"710 Main St",
    "sg:city":"Bradley Beach",
    "sg:classifiers":[
        {
            "category":"Food & Beverages",
            "subcategory":"Bakery",
            "type":"Retail Goods"
        }
    ],
    "sg:phone":"+1 732 776 7301",
    "sg:postcode":"07720",
    "sg:province":"NJ",
    "sg:tags":[
        "baker"
    ],
    "wof:name":"Bakery Sinai III",
    "wof:placetype":"venue"
},
  "geometry": {"coordinates":[-74.01719799999999,40.204961],"type":"Point"}
}