{
  "type": "Feature",
  "properties": {
    "addr:full":"221 Park Ave Rutherford NJ 07070",
    "addr:housenumber":"221",
    "addr:postcode":"07070",
    "addr:street":"Park Ave",
    "iso:country":"US",
    "sg:address":"221 Park Ave",
    "sg:city":"Rutherford",
    "sg:classifiers":[
        {
            "category":"Health Services",
            "subcategory":"Dentist",
            "type":"Services"
        }
    ],
    "sg:phone":"+1 201 939 0225",
    "sg:postcode":"07070",
    "sg:province":"NJ",
    "wof:name":"Rutherford Dental P.C",
    "wof:placetype":"venue"
},
  "geometry": {"coordinates":[-74.111386,40.824402],"type":"Point"}
}