{
  "type": "Feature",
  "properties": {
    "iso:country":"US",
    "sg:address":"251 Verona Ave",
    "sg:city":"Newark",
    "sg:classifiers":[
        {
            "category":"Manufacturing",
            "subcategory":"Electronics",
            "type":"Manufacturing & Wholesale Goods"
        }
    ],
    "sg:phone":"+1 973 485 9394",
    "sg:postcode":"07104",
    "sg:province":"NJ",
    "sg:tags":[
        "equipment",
        "mfg",
        "home"
    ],
    "wof:name":"Epic Audio Video Installation",
    "wof:placetype":"venue"
},
  "geometry": {"coordinates":[-74.164013,40.782311],"type":"Point"}
}