{
  "type": "Feature",
  "properties": {
    "addr:full":"506 W Side Ave Jersey City NJ 07304",
    "addr:housenumber":"506",
    "addr:postcode":"07304",
    "addr:street":"W Side Ave",
    "iso:country":"US",
    "sg:address":"506 W Side Ave",
    "sg:city":"Jersey City",
    "sg:classifiers":[
        {
            "category":"Cinema",
            "subcategory":"Movie Rental",
            "type":"Entertainment"
        }
    ],
    "sg:phone":"+1 201 434 3392",
    "sg:postcode":"07304",
    "sg:province":"NJ",
    "sg:tags":[
        "leasing",
        "video",
        "disc",
        "tape"
    ],
    "wof:name":"R G Video Ctr",
    "wof:placetype":"venue"
},
  "geometry": {"coordinates":[-74.083963,40.717864],"type":"Point"}
}