{
  "type": "Feature",
  "properties": {
    "addr:full":"1890 US Hwy 1 North Brunswick NJ 08902",
    "addr:housenumber":"1890",
    "addr:postcode":"08902",
    "addr:street":"Us Hwy 1",
    "iso:country":"US",
    "sg:address":"1890 US Hwy 1",
    "sg:city":"North Brunswick",
    "sg:classifiers":[
        {
            "category":"Autos & Motor Vehicles",
            "subcategory":"Fuel & Gas Station",
            "type":"Retail Goods"
        }
    ],
    "sg:phone":"+1 732 398 9740",
    "sg:postcode":"08902",
    "sg:province":"NJ",
    "sg:tags":[
        "oil"
    ],
    "wof:name":"BP",
    "wof:placetype":"venue"
},
  "geometry": {"coordinates":[-74.49234800000001,40.45108],"type":"Point"}
}