{
  "type": "Feature",
  "properties": {
    "iso:country":"US",
    "sg:address":"5906 Main St",
    "sg:city":"Mays Landing",
    "sg:classifiers":[
        {
            "category":"Professional",
            "subcategory":"Lawyer & Legal Services",
            "type":"Services"
        }
    ],
    "sg:phone":"+1 609 625 1352",
    "sg:postcode":"08330",
    "sg:province":"NJ",
    "sg:tags":[
        "attorney"
    ],
    "wof:name":"Leland A Stanford",
    "wof:placetype":"venue"
},
  "geometry": {"coordinates":[-74.727147,39.451899],"type":"Point"}
}