{
  "type": "Feature",
  "properties": {
    "addr:full":"125 Cedar St Stirling NJ 07980",
    "addr:housenumber":"125",
    "addr:postcode":"07980",
    "addr:street":"Cedar St",
    "iso:country":"US",
    "sg:address":"125 Cedar St",
    "sg:city":"Stirling",
    "sg:classifiers":[
        {
            "category":"Building & Trades",
            "subcategory":"Construction",
            "type":"Services"
        }
    ],
    "sg:phone":"+1 908 604 2767",
    "sg:postcode":"07980",
    "sg:province":"NJ",
    "sg:tags":[
        "general",
        "contractor"
    ],
    "wof:name":"Perrco",
    "wof:placetype":"venue"
},
  "geometry": {"coordinates":[-74.486788,40.664743],"type":"Point"}
}