{
  "type": "Feature",
  "properties": {
    "iso:country":"US",
    "sg:address":"1370 Teaneck Rd",
    "sg:city":"Teaneck",
    "sg:classifiers":[
        {
            "category":"Wholesale",
            "subcategory":"Machinery & Supplies",
            "type":"Manufacturing & Wholesale Goods"
        },
        {
            "category":"Personal",
            "subcategory":"Beauty Salon",
            "type":"Services"
        }
    ],
    "sg:phone":"+1 201 833 2271",
    "sg:postcode":"07666",
    "sg:province":"NJ",
    "sg:tags":[
        "equipment",
        "establishment"
    ],
    "wof:name":"Kay-Cee's Beauty Salon",
    "wof:placetype":"venue"
},
  "geometry": {"coordinates":[-74.00012,40.899169],"type":"Point"}
}