{
  "type": "Feature",
  "properties": {
    "iso:country":"US",
    "sg:address":"274 Elm Ave",
    "sg:city":"Teaneck",
    "sg:classifiers":[
        {
            "category":"Professional",
            "subcategory":"Accounting & Tax Preparation",
            "type":"Services"
        }
    ],
    "sg:phone":"+1 201 801 0085",
    "sg:postcode":"07666",
    "sg:province":"NJ",
    "sg:tags":[
        "accountant"
    ],
    "wof:name":"Emich Philip CPA",
    "wof:placetype":"venue"
},
  "geometry": {"coordinates":[-74.02449799999999,40.8895],"type":"Point"}
}