{
  "type": "Feature",
  "properties": {
    "addr:full":"1301 Ocean Ave Pt Pleasant Bch NJ 08742",
    "addr:housenumber":"1301",
    "addr:postcode":"08742",
    "addr:street":"Ocean Ave Pt",
    "iso:country":"US",
    "sg:address":"1301 Ocean Ave",
    "sg:city":"Pt Pleasant Bch",
    "sg:classifiers":[
        {
            "category":"Travel",
            "subcategory":"Bed & Breakfast",
            "type":"Entertainment"
        }
    ],
    "sg:phone":"+1 732 892 5415",
    "sg:postcode":"08742",
    "sg:province":"NJ",
    "sg:tags":[
        "home",
        "tourist"
    ],
    "wof:name":"Carousel Inn LLC",
    "wof:placetype":"venue"
},
  "geometry": {"coordinates":[-74.03999899999999,40.084194],"type":"Point"}
}