{
  "type": "Feature",
  "properties": {
    "addr:full":"82 N James St Woodbridge NJ 07095",
    "addr:housenumber":"82",
    "addr:postcode":"07095",
    "addr:street":"N James St",
    "iso:country":"US",
    "sg:address":"82 N James St",
    "sg:city":"Woodbridge",
    "sg:classifiers":[
        {
            "category":"Health Services",
            "subcategory":"Medical Lab",
            "type":"Services"
        }
    ],
    "sg:phone":"+1 732 634 5605",
    "sg:postcode":"07095",
    "sg:province":"NJ",
    "sg:tags":[
        "laboratory",
        "dental"
    ],
    "wof:name":"Bert Dental Lab",
    "wof:placetype":"venue"
},
  "geometry": {"coordinates":[-74.280804,40.554667],"type":"Point"}
}