{
  "type": "Feature",
  "properties": {
    "iso:country":"US",
    "sg:address":"1403 State Rte 23",
    "sg:city":"Kinnelon",
    "sg:classifiers":[
        {
            "category":"Wholesale",
            "subcategory":"Non-durable Goods",
            "type":"Manufacturing & Wholesale Goods"
        }
    ],
    "sg:phone":"+1 973 838 3400",
    "sg:postcode":"07405",
    "sg:province":"NJ",
    "sg:tags":[
        "advertising"
    ],
    "wof:name":"JMJ Printing & Promotions",
    "wof:placetype":"venue"
},
  "geometry": {"coordinates":[-74.354187,40.998345],"type":"Point"}
}