{
  "type": "Feature",
  "properties": {
    "iso:country":"US",
    "sg:address":"128 Railroad Ave",
    "sg:city":"Hackensack",
    "sg:classifiers":[
        {
            "category":"Manufacturing",
            "subcategory":"Metals",
            "type":"Manufacturing & Wholesale Goods"
        }
    ],
    "sg:phone":"+1 201 487 1033",
    "sg:postcode":"07601",
    "sg:province":"NJ",
    "sg:tags":[
        "fabricator",
        "sheet"
    ],
    "wof:name":"Hutcheon & Simon Inc",
    "wof:placetype":"venue"
},
  "geometry": {"coordinates":[-74.049621,40.883471],"type":"Point"}
}