{
  "type": "Feature",
  "properties": {
    "addr:full":"875 Kings Hwy Woodbury NJ 08096",
    "addr:housenumber":"875",
    "addr:postcode":"08096",
    "addr:street":"Kings Hwy",
    "iso:country":"US",
    "sg:address":"875 Kings Hwy",
    "sg:city":"Woodbury",
    "sg:classifiers":[
        {
            "category":"Professional",
            "subcategory":"Engineering",
            "type":"Services"
        }
    ],
    "sg:phone":"+1 856 845 0529",
    "sg:postcode":"08096",
    "sg:province":"NJ",
    "sg:tags":[
        "engineer"
    ],
    "wof:name":"Arora & Assoc",
    "wof:placetype":"venue"
},
  "geometry": {"coordinates":[-75.170626,39.826913],"type":"Point"}
}