{
  "type": "Feature",
  "properties": {
    "addr:full":"242 State Rte 156 Trenton NJ 08620",
    "addr:housenumber":"242",
    "addr:postcode":"08620",
    "addr:street":"State Rte 156",
    "iso:country":"US",
    "sg:address":"242 State Rte 156",
    "sg:city":"Trenton",
    "sg:classifiers":[
        {
            "category":"Retail",
            "subcategory":"Repair Shop",
            "type":"Services"
        }
    ],
    "sg:phone":"+1   ",
    "sg:postcode":"08620",
    "sg:province":"NJ",
    "sg:tags":[
        "equipment",
        "medical",
        "emergency"
    ],
    "wof:name":"Equipment Maintenance",
    "wof:placetype":"venue"
},
  "geometry": {"coordinates":[-74.66632300000001,40.180835],"type":"Point"}
}