{
  "type": "Feature",
  "properties": {
    "addr:full":"268 US Hwy 206 Flanders NJ 07836",
    "addr:housenumber":"268",
    "addr:postcode":"07836",
    "addr:street":"Us Hwy 206",
    "iso:country":"US",
    "sg:address":"268 US Hwy 206",
    "sg:city":"Flanders",
    "sg:classifiers":[
        {
            "category":"Government",
            "subcategory":"Office",
            "type":"Public Place"
        }
    ],
    "sg:phone":"+1   ",
    "sg:postcode":"07836",
    "sg:province":"NJ",
    "sg:tags":[
        "member",
        "state",
        "assembly",
        "district",
        "general"
    ],
    "wof:name":"District 24",
    "wof:placetype":"venue"
},
  "geometry": {"coordinates":[-74.709816,40.834541],"type":"Point"}
}