{
  "type": "Feature",
  "properties": {
    "addr:full":"52 W Front St Keyport NJ 07735",
    "addr:housenumber":"52",
    "addr:postcode":"07735",
    "addr:street":"W Front St",
    "iso:country":"US",
    "sg:address":"52 W Front St",
    "sg:city":"Keyport",
    "sg:classifiers":[
        {
            "category":"Wholesale",
            "subcategory":"Machinery & Supplies",
            "type":"Manufacturing & Wholesale Goods"
        }
    ],
    "sg:phone":"+1 732 739 1574",
    "sg:postcode":"07735",
    "sg:province":"NJ",
    "sg:tags":[
        "sweeper"
    ],
    "wof:name":"Bayshore Power Sweeping Inc",
    "wof:placetype":"venue"
},
  "geometry": {"coordinates":[-74.204038,40.436801],"type":"Point"}
}