{
  "type": "Feature",
  "properties": {
    "addr:full":"25 Dickerson Mine Rd Dover NJ 07803",
    "addr:housenumber":"25",
    "addr:postcode":"07803",
    "addr:street":"Dickerson Mine Rd",
    "iso:country":"US",
    "sg:address":"25 Dickerson Mine Rd",
    "sg:city":"Dover",
    "sg:classifiers":[
        {
            "category":"Health Services",
            "subcategory":"Doctor",
            "type":"Services"
        }
    ],
    "sg:phone":"+1   ",
    "sg:postcode":"07803",
    "sg:province":"NJ",
    "wof:name":"Anthony T Chin DDS",
    "wof:placetype":"venue"
},
  "geometry": {"coordinates":[-74.613792,40.87463],"type":"Point"}
}