{
  "type": "Feature",
  "properties": {
    "addr:full":"5600 State Rte 42 Blackwood NJ 08012",
    "addr:housenumber":"5600",
    "addr:postcode":"08012",
    "addr:street":"State Rte 42",
    "iso:country":"US",
    "sg:address":"5600 State Rte 42",
    "sg:city":"Blackwood",
    "sg:classifiers":[
        {
            "category":"Retail",
            "subcategory":"Laundry & Dry Cleaning",
            "type":"Services"
        }
    ],
    "sg:phone":"+1   ",
    "sg:postcode":"08012",
    "sg:province":"NJ",
    "sg:tags":[
        "drycleaning",
        "plant"
    ],
    "wof:name":"Whitman One Hour Cleaners",
    "wof:placetype":"venue"
},
  "geometry": {"coordinates":[-75.047196,39.758218],"type":"Point"}
}