{
  "type": "Feature",
  "properties": {
    "addr:full":"127 Halsey Ave Rockaway NJ 07866",
    "addr:housenumber":"127",
    "addr:postcode":"07866",
    "addr:street":"Halsey Ave",
    "iso:country":"US",
    "sg:address":"127 Halsey Ave",
    "sg:city":"Rockaway",
    "sg:classifiers":[
        {
            "category":"Wholesale",
            "subcategory":"Durable Goods & Equipment",
            "type":"Manufacturing & Wholesale Goods"
        }
    ],
    "sg:phone":"+1 973 625 2130",
    "sg:postcode":"07866",
    "sg:province":"NJ",
    "sg:tags":[
        "importer"
    ],
    "wof:name":"Linne International Inc",
    "wof:placetype":"venue"
},
  "geometry": {"coordinates":[-74.509333,40.905585],"type":"Point"}
}