{
  "type": "Feature",
  "properties": {
    "addr:full":"565 Bloomfield Ave Bloomfield NJ 07003",
    "addr:housenumber":"565",
    "addr:postcode":"07003",
    "addr:street":"Bloomfield Ave",
    "iso:country":"US",
    "sg:address":"565 Bloomfield Ave",
    "sg:city":"Bloomfield",
    "sg:classifiers":[
        {
            "category":"Shopping",
            "subcategory":"Discount & Variety Stores",
            "type":"Retail Goods"
        }
    ],
    "sg:phone":"+1   ",
    "sg:postcode":"07003",
    "sg:province":"NJ",
    "wof:name":"Super Value Center Inc",
    "wof:placetype":"venue"
},
  "geometry": {"coordinates":[-74.197198,40.792565],"type":"Point"}
}