{
  "type": "Feature",
  "properties": {
    "addr:full":"12 Canterbury Ln Hackettstown NJ 07840",
    "addr:housenumber":"12",
    "addr:postcode":"07840",
    "addr:street":"Canterbury Ln",
    "iso:country":"US",
    "sg:address":"12 Canterbury Ln",
    "sg:city":"Hackettstown",
    "sg:classifiers":[
        {
            "category":"Shopping",
            "subcategory":"Catalog Store",
            "type":"Retail Goods"
        }
    ],
    "sg:phone":"+1   ",
    "sg:postcode":"07840",
    "sg:province":"NJ",
    "sg:tags":[
        "mail",
        "house"
    ],
    "wof:name":"Discovery Toys of Hackettstown",
    "wof:placetype":"venue"
},
  "geometry": {"coordinates":[-74.843735,40.822651],"type":"Point"}
}