{
  "type": "Feature",
  "properties": {
    "addr:full":"84 Tidewater Ln Willingboro NJ 08046",
    "addr:housenumber":"84",
    "addr:postcode":"08046",
    "addr:street":"Tidewater Ln",
    "iso:country":"US",
    "sg:address":"84 Tidewater Ln",
    "sg:city":"Willingboro",
    "sg:classifiers":[
        {
            "category":"Real Estate",
            "subcategory":"Real Estate Agent",
            "type":"Services"
        }
    ],
    "sg:phone":"+1 609 877 3900",
    "sg:postcode":"08046",
    "sg:province":"NJ",
    "sg:website":"www.remax-unlimited.net",
    "wof:name":"Re/Max",
    "wof:placetype":"venue"
},
  "geometry": {"coordinates":[-74.87728199999999,40.007324],"type":"Point"}
}