{
  "type": "Feature",
  "properties": {
    "addr:full":"2687 US Hwy 130 Cranbury NJ 08512",
    "addr:housenumber":"2687",
    "addr:postcode":"08512",
    "addr:street":"Us Hwy 130",
    "iso:country":"US",
    "sg:address":"2687 US Hwy 130",
    "sg:city":"Cranbury",
    "sg:classifiers":[
        {
            "category":"Freight",
            "type":"Transportation"
        }
    ],
    "sg:phone":"+1 609 860 6685",
    "sg:postcode":"08512",
    "sg:province":"NJ",
    "sg:tags":[
        "cartage",
        "trucking"
    ],
    "wof:name":"Vic & Sons Transport",
    "wof:placetype":"venue"
},
  "geometry": {"coordinates":[-74.508252,40.318818],"type":"Point"}
}