{
  "type": "Feature",
  "properties": {
    "iso:country":"US",
    "sg:address":"7 Macculloch Ave",
    "sg:city":"Morristown",
    "sg:classifiers":[
        {
            "category":"Banks & Credit Unions",
            "subcategory":"Bank",
            "type":"Services"
        }
    ],
    "sg:phone":"+1 973 267 5066",
    "sg:postcode":"07960",
    "sg:province":"NJ",
    "sg:tags":[
        "loan",
        "real estate"
    ],
    "wof:name":"Us Mortgage Corp",
    "wof:placetype":"venue"
},
  "geometry": {"coordinates":[-74.48351099999999,40.793933],"type":"Point"}
}