{
  "type": "Feature",
  "properties": {
    "iso:country":"US",
    "sg:address":"2 Sheridan Ave",
    "sg:city":"Ho Ho Kus",
    "sg:classifiers":[
        {
            "category":"Autos & Motor Vehicles",
            "subcategory":"Fuel & Gas Station",
            "type":"Retail Goods"
        }
    ],
    "sg:phone":"+1   ",
    "sg:postcode":"07423",
    "sg:province":"NJ",
    "sg:tags":[
        "repair",
        "station",
        "gasoline",
        "general"
    ],
    "wof:name":"Denchs Auto Repair Inc",
    "wof:placetype":"venue"
},
  "geometry": {"coordinates":[-74.11023299999999,40.997989],"type":"Point"}
}