{
  "type": "Feature",
  "properties": {
    "addr:full":"304 Central Ave Linwood NJ 08221",
    "addr:housenumber":"304",
    "addr:postcode":"08221",
    "addr:street":"Central Ave",
    "iso:country":"US",
    "sg:address":"304 Central Ave",
    "sg:city":"Linwood",
    "sg:classifiers":[
        {
            "category":"Building & Trades",
            "subcategory":"Construction",
            "type":"Services"
        }
    ],
    "sg:phone":"+1 609 645 1271",
    "sg:postcode":"08221",
    "sg:province":"NJ",
    "sg:tags":[
        "handyman"
    ],
    "wof:name":"Dan The Handyman",
    "wof:placetype":"venue"
},
  "geometry": {"coordinates":[-74.568083,39.358724],"type":"Point"}
}