{
  "type": "Feature",
  "properties": {
    "addr:full":"675 Corliss Ave Phillipsburg NJ 08865",
    "addr:housenumber":"675",
    "addr:postcode":"08865",
    "addr:street":"Corliss Ave",
    "iso:country":"US",
    "sg:address":"675 Corliss Ave",
    "sg:city":"Phillipsburg",
    "sg:classifiers":[
        {
            "category":"Government",
            "subcategory":"Police Station",
            "type":"Public Place"
        }
    ],
    "sg:phone":"+1 908 454 1121",
    "sg:postcode":"08865",
    "sg:province":"NJ",
    "sg:tags":[
        "department"
    ],
    "wof:name":"Phillipsburg Police Dept",
    "wof:placetype":"venue"
},
  "geometry": {"coordinates":[-75.18026,40.698724],"type":"Point"}
}