{
  "type": "Feature",
  "properties": {
    "iso:country":"US",
    "sg:address":"556 Anderson Ave",
    "sg:city":"Cliffside Park",
    "sg:classifiers":[
        {
            "category":"Food & Beverages",
            "subcategory":"Bakery",
            "type":"Retail Goods"
        }
    ],
    "sg:phone":"+1 201 943 1111",
    "sg:postcode":"07010",
    "sg:province":"NJ",
    "sg:tags":[
        "baker"
    ],
    "wof:name":"Prime Food Market",
    "wof:placetype":"venue"
},
  "geometry": {"coordinates":[-73.98905499999999,40.823389],"type":"Point"}
}