{
  "type": "Feature",
  "properties": {
    "iso:country":"US",
    "sg:address":"257 N Odessa Ave",
    "sg:city":"Egg Harbor City",
    "sg:classifiers":[
        {
            "category":"Wholesale",
            "subcategory":"Seafood",
            "type":"Manufacturing & Wholesale Goods"
        }
    ],
    "sg:phone":"+1 609 432 2553",
    "sg:postcode":"08215",
    "sg:province":"NJ",
    "wof:name":"J Brooke Commercial Fishing",
    "wof:placetype":"venue"
},
  "geometry": {"coordinates":[-74.538738,39.525232],"type":"Point"}
}