{
  "type": "Feature",
  "properties": {
    "addr:full":"3 Overhill Rd Wayne NJ 07470",
    "addr:housenumber":"3",
    "addr:postcode":"07470",
    "addr:street":"Overhill Rd",
    "iso:country":"US",
    "sg:address":"3 Overhill Rd",
    "sg:city":"Wayne",
    "sg:classifiers":[
        {
            "category":"Professional",
            "type":"Services"
        }
    ],
    "sg:phone":"+1   ",
    "sg:postcode":"07470",
    "sg:province":"NJ",
    "wof:name":"Pt Trader Inc",
    "wof:placetype":"venue"
},
  "geometry": {"coordinates":[-74.27007999999999,40.985662],"type":"Point"}
}