{
  "type": "Feature",
  "properties": {
    "iso:country":"US",
    "sg:address":"13 Blatherwick Dr",
    "sg:city":"Berlin",
    "sg:classifiers":[
        {
            "category":"Communications",
            "subcategory":"Television Station",
            "type":"Services"
        }
    ],
    "sg:phone":"+1 856 768 0606",
    "sg:postcode":"08009",
    "sg:province":"NJ",
    "sg:tags":[
        "satellite",
        "antenna",
        "cable",
        "tv",
        "system",
        "equipment"
    ],
    "wof:name":"Advanced Satellite Systems Inc",
    "wof:placetype":"venue"
},
  "geometry": {"coordinates":[-74.930183,39.7817],"type":"Point"}
}