{
  "type": "Feature",
  "properties": {
    "iso:country":"US",
    "sg:address":"14 Marie Ct",
    "sg:city":"Fair Lawn",
    "sg:classifiers":[
        {
            "category":"Professional",
            "subcategory":"Business Services",
            "type":"Services"
        }
    ],
    "sg:phone":"+1   ",
    "sg:postcode":"07410",
    "sg:province":"NJ",
    "wof:name":"Mark Kannry Family Partnership",
    "wof:placetype":"venue"
},
  "geometry": {"coordinates":[-74.099688,40.941455],"type":"Point"}
}