{
  "type": "Feature",
  "properties": {
    "iso:country":"US",
    "sg:address":"165 Hillside Dr",
    "sg:city":"Haledon",
    "sg:classifiers":[
        {
            "category":"Building & Trades",
            "subcategory":"Construction",
            "type":"Services"
        }
    ],
    "sg:phone":"+1 973 427 1449",
    "sg:postcode":"07508",
    "sg:province":"NJ",
    "sg:tags":[
        "contractor"
    ],
    "wof:name":"NVR Custom Contractors Inc",
    "wof:placetype":"venue"
},
  "geometry": {"coordinates":[-74.194292,40.973074],"type":"Point"}
}