{
  "type": "Feature",
  "properties": {
    "iso:country":"US",
    "sg:address":"6 Oak Tree Rd",
    "sg:city":"Newton",
    "sg:classifiers":[
        {
            "category":"Home & Garden",
            "subcategory":"Home Furnishings",
            "type":"Retail Goods"
        }
    ],
    "sg:phone":"+1   ",
    "sg:postcode":"07860",
    "sg:province":"NJ",
    "wof:name":"That Special Touch",
    "wof:placetype":"venue"
},
  "geometry": {"coordinates":[-74.798024,41.02584],"type":"Point"}
}