{
  "type": "Feature",
  "properties": {
    "addr:full":"5 Briar Dr Sussex NJ 07461",
    "addr:housenumber":"5",
    "addr:postcode":"07461",
    "addr:street":"Briar Dr",
    "iso:country":"US",
    "sg:address":"5 Briar Dr",
    "sg:city":"Sussex",
    "sg:classifiers":[
        {
            "category":"Communications",
            "subcategory":"Film & Video Production",
            "type":"Services"
        }
    ],
    "sg:phone":"+1 973 875 0558",
    "sg:postcode":"07461",
    "sg:province":"NJ",
    "sg:tags":[
        "motion"
    ],
    "wof:name":"Vernon Productions LLC",
    "wof:placetype":"venue"
},
  "geometry": {"coordinates":[-74.559246,41.202531],"type":"Point"}
}