{
  "type": "Feature",
  "properties": {
    "addr:full":"288 Commissioners Pike Woodstown NJ 08098",
    "addr:housenumber":"288",
    "addr:postcode":"08098",
    "addr:street":"Commissioners Pike",
    "iso:country":"US",
    "sg:address":"288 Commissioners Pike",
    "sg:city":"Woodstown",
    "sg:classifiers":[
        {
            "category":"Real Estate",
            "subcategory":"Real Estate Operator",
            "type":"Services"
        }
    ],
    "sg:phone":"+1   ",
    "sg:postcode":"08098",
    "sg:province":"NJ",
    "sg:tags":[
        "property",
        "lessor"
    ],
    "wof:name":"Stanley Cross Farm",
    "wof:placetype":"venue"
},
  "geometry": {"coordinates":[-75.256061,39.637749],"type":"Point"}
}