{
  "type": "Feature",
  "properties": {
    "addr:full":"201 N Coolidge Ave Margate City NJ 08402",
    "addr:housenumber":"201",
    "addr:postcode":"08402",
    "addr:street":"N Coolidge Ave Margate",
    "iso:country":"US",
    "sg:address":"201 N Coolidge Ave",
    "sg:city":"Margate City",
    "sg:classifiers":[
        {
            "category":"Building & Trades",
            "subcategory":"Construction",
            "type":"Services"
        }
    ],
    "sg:phone":"+1 609 823 6266",
    "sg:postcode":"08402",
    "sg:province":"NJ",
    "sg:tags":[
        "house"
    ],
    "wof:name":"South Jrsey Remodeling",
    "wof:placetype":"venue"
},
  "geometry": {"coordinates":[-74.52139699999999,39.323298],"type":"Point"}
}