{
  "type": "Feature",
  "properties": {
    "iso:country":"US",
    "sg:address":"63 Hook Rd",
    "sg:city":"Bayonne",
    "sg:classifiers":[
        {
            "category":"Real Estate",
            "subcategory":"Real Estate Services",
            "type":"Services"
        }
    ],
    "sg:phone":"+1 201 436 7788",
    "sg:postcode":"07002",
    "sg:province":"NJ",
    "sg:tags":[
        "management",
        "property"
    ],
    "wof:name":"Trucking Ontime",
    "wof:placetype":"venue"
},
  "geometry": {"coordinates":[-74.096236,40.652289],"type":"Point"}
}