{
  "type": "Feature",
  "properties": {
    "iso:country":"US",
    "sg:address":"159 Asbury Rd",
    "sg:city":"Farmingdale",
    "sg:classifiers":[
        {
            "category":"Building & Trades",
            "subcategory":"Construction",
            "type":"Services"
        }
    ],
    "sg:phone":"+1 732 938 4207",
    "sg:postcode":"07727",
    "sg:province":"NJ",
    "wof:name":"Rite Way Paving",
    "wof:placetype":"venue"
},
  "geometry": {"coordinates":[-74.15738399999999,40.207574],"type":"Point"}
}