{
  "type": "Feature",
  "properties": {
    "addr:full":"292 Main St Hackensack NJ 07601",
    "addr:housenumber":"292",
    "addr:postcode":"07601",
    "addr:street":"Main St",
    "iso:country":"US",
    "sg:address":"292 Main St",
    "sg:city":"Hackensack",
    "sg:classifiers":[
        {
            "category":"Professional",
            "subcategory":"Lawyer & Legal Services",
            "type":"Services"
        }
    ],
    "sg:phone":"+1 201 488 8177",
    "sg:postcode":"07601",
    "sg:province":"NJ",
    "sg:tags":[
        "consulting",
        "naturalization",
        "immigration"
    ],
    "wof:name":"Immigration Consultant Svcs",
    "wof:placetype":"venue"
},
  "geometry": {"coordinates":[-74.04057400000001,40.888076],"type":"Point"}
}