{
  "type": "Feature",
  "properties": {
    "iso:country":"US",
    "sg:address":"56 Kostenbader Rd",
    "sg:city":"Blairstown",
    "sg:classifiers":[
        {
            "category":"Shopping",
            "subcategory":"Bicycles & Sporting Goods",
            "type":"Retail Goods"
        }
    ],
    "sg:phone":"+1   ",
    "sg:postcode":"07825",
    "sg:province":"NJ",
    "wof:name":"Budget Arms Ammo",
    "wof:placetype":"venue"
},
  "geometry": {"coordinates":[-74.994135,40.896434],"type":"Point"}
}