{
  "type": "Feature",
  "properties": {
    "addr:full":"1331 Springfield Ave Irvington NJ 07111",
    "addr:housenumber":"1331",
    "addr:postcode":"07111",
    "addr:street":"Springfield Ave",
    "iso:country":"US",
    "sg:address":"1331 Springfield Ave",
    "sg:city":"Irvington",
    "sg:classifiers":[
        {
            "category":"Banks & Credit Unions",
            "subcategory":"Bank",
            "type":"Services"
        }
    ],
    "sg:phone":"+1 973 374 8200",
    "sg:postcode":"07111",
    "sg:province":"NJ",
    "sg:website":"www.isbnj.com",
    "wof:name":"Investors Savings Bank",
    "wof:placetype":"venue"
},
  "geometry": {"coordinates":[-74.244697,40.724132],"type":"Point"}
}