{
  "type": "Feature",
  "properties": {
    "iso:country":"US",
    "sg:address":"25 Craig Rd",
    "sg:city":"Neshanic Station",
    "sg:classifiers":[
        {
            "category":"Shopping",
            "type":"Retail Goods"
        }
    ],
    "sg:phone":"+1   ",
    "sg:postcode":"08853",
    "sg:province":"NJ",
    "sg:tags":[
        "merchandise"
    ],
    "wof:name":"Lindas Tiger Mart",
    "wof:placetype":"venue"
},
  "geometry": {"coordinates":[-74.746683,40.547468],"type":"Point"}
}