{
  "type": "Feature",
  "properties": {
    "addr:full":"460 Penn St Perth Amboy NJ 08861",
    "addr:housenumber":"460",
    "addr:postcode":"08861",
    "addr:street":"Penn St",
    "iso:country":"US",
    "sg:address":"460 Penn St",
    "sg:city":"Perth Amboy",
    "sg:classifiers":[
        {
            "category":"Building & Trades",
            "subcategory":"Locksmith",
            "type":"Services"
        }
    ],
    "sg:phone":"+1 888 277 6684",
    "sg:postcode":"08861",
    "sg:province":"NJ",
    "sg:tags":[
        "key"
    ],
    "wof:name":"Always Available 24 Hour Emergency Locksmith",
    "wof:placetype":"venue"
},
  "geometry": {"coordinates":[-74.271783,40.516241],"type":"Point"}
}