{
  "type": "Feature",
  "properties": {
    "iso:country":"US",
    "sg:address":"4 Highland Rd",
    "sg:city":"Oak Ridge",
    "sg:classifiers":[
        {
            "category":"Building & Trades",
            "subcategory":"Construction",
            "type":"Services"
        }
    ],
    "sg:phone":"+1 973 208 1380",
    "sg:postcode":"07438",
    "sg:province":"NJ",
    "sg:tags":[
        "carpentry",
        "contractor"
    ],
    "wof:name":"Hoekstra Carpentry",
    "wof:placetype":"venue"
},
  "geometry": {"coordinates":[-74.518907,41.034582],"type":"Point"}
}