{
  "type": "Feature",
  "properties": {
    "iso:country":"US",
    "sg:address":"86 Co Rd 526",
    "sg:city":"Allentown",
    "sg:classifiers":[
        {
            "category":"Building & Trades",
            "subcategory":"Electrical",
            "type":"Services"
        },
        {
            "category":"Building & Trades",
            "subcategory":"Construction",
            "type":"Services"
        }
    ],
    "sg:phone":"+1 609 259 5480",
    "sg:postcode":"08501",
    "sg:province":"NJ",
    "sg:tags":[
        "utility",
        "communication",
        "general",
        "contractor"
    ],
    "wof:name":"Comm Corp Inc",
    "wof:placetype":"venue"
},
  "geometry": {"coordinates":[-74.588605,40.180731],"type":"Point"}
}