{
  "type": "Feature",
  "properties": {
    "addr:full":"50 Kinderkamack Rd Oradell NJ 07649",
    "addr:housenumber":"50",
    "addr:postcode":"07649",
    "addr:street":"Kinderkamack Rd",
    "iso:country":"US",
    "sg:address":"50 Kinderkamack Rd",
    "sg:city":"Oradell",
    "sg:classifiers":[
        {
            "category":"Shopping",
            "subcategory":"Optical Goods",
            "type":"Retail Goods"
        }
    ],
    "sg:phone":"+1   ",
    "sg:postcode":"07649",
    "sg:province":"NJ",
    "wof:name":"Sagah Optical Corp",
    "wof:placetype":"venue"
},
  "geometry": {"coordinates":[-74.029453,40.942845],"type":"Point"}
}