{
  "type": "Feature",
  "properties": {
    "addr:full":"759 Main Ave Passaic NJ 07055",
    "addr:housenumber":"759",
    "addr:postcode":"07055",
    "addr:street":"Main Ave",
    "iso:country":"US",
    "sg:address":"759 Main Ave",
    "sg:city":"Passaic",
    "sg:classifiers":[
        {
            "category":"Shopping",
            "type":"Retail Goods"
        }
    ],
    "sg:phone":"+1 973 471 0434",
    "sg:postcode":"07055",
    "sg:province":"NJ",
    "sg:tags":[
        "religious"
    ],
    "wof:name":"St Barbara Botanica",
    "wof:placetype":"venue"
},
  "geometry": {"coordinates":[-74.12840799999999,40.863104],"type":"Point"}
}