{
  "type": "Feature",
  "properties": {
    "addr:full":"438 High St Burlington NJ 08016",
    "addr:housenumber":"438",
    "addr:postcode":"08016",
    "addr:street":"High St",
    "iso:country":"US",
    "sg:address":"438 High St",
    "sg:city":"Burlington",
    "sg:classifiers":[
        {
            "category":"Professional",
            "subcategory":"Management & Consulting",
            "type":"Services"
        }
    ],
    "sg:phone":"+1   ",
    "sg:postcode":"08016",
    "sg:province":"NJ",
    "sg:tags":[
        "business"
    ],
    "wof:name":"Bandwave Systems LLC",
    "wof:placetype":"venue"
},
  "geometry": {"coordinates":[-74.85791999999999,40.077137],"type":"Point"}
}