{
  "type": "Feature",
  "properties": {
    "iso:country":"US",
    "sg:address":"142 Hanover Rd",
    "sg:city":"East Hanover",
    "sg:classifiers":[
        {
            "category":"Shopping",
            "subcategory":"Stationery & Office Supplies",
            "type":"Retail Goods"
        }
    ],
    "sg:phone":"+1 973 515 9797",
    "sg:postcode":"07936",
    "sg:province":"NJ",
    "wof:name":"Office Max",
    "wof:placetype":"venue"
},
  "geometry": {"coordinates":[-74.372986,40.797744],"type":"Point"}
}