{
  "type": "Feature",
  "properties": {
    "iso:country":"US",
    "sg:address":"240 Hayes Mill Rd",
    "sg:city":"Atco",
    "sg:classifiers":[
        {
            "category":"Building & Trades",
            "subcategory":"Pest Control",
            "type":"Services"
        }
    ],
    "sg:phone":"+1 856 767 9402",
    "sg:postcode":"08004",
    "sg:province":"NJ",
    "wof:name":"A Frames Pest Control",
    "wof:placetype":"venue"
},
  "geometry": {"coordinates":[-74.88806700000001,39.761594],"type":"Point"}
}