{
  "type": "Feature",
  "properties": {
    "addr:full":"3 Riverside Dr Phillipsburg NJ 08809",
    "addr:housenumber":"3",
    "addr:postcode":"08809",
    "addr:street":"Riverside Dr",
    "iso:country":"US",
    "sg:address":"3 Riverside Dr",
    "sg:city":"Phillipsburg",
    "sg:classifiers":[
        {
            "category":"Government",
            "subcategory":"Office",
            "type":"Public Place"
        }
    ],
    "sg:phone":"+1 908 213 0967",
    "sg:postcode":"08809",
    "sg:province":"NJ",
    "wof:name":"Us Water Inc",
    "wof:placetype":"venue"
},
  "geometry": {"coordinates":[-74.908565,40.63466],"type":"Point"}
}