{
  "type": "Feature",
  "properties": {
    "iso:country":"US",
    "sg:address":"3821 Panther Rd",
    "sg:city":"Vineland",
    "sg:classifiers":[
        {
            "category":"Retail",
            "subcategory":"Animal Services",
            "type":"Services"
        }
    ],
    "sg:phone":"+1 856 691 6449",
    "sg:postcode":"08361",
    "sg:province":"NJ",
    "wof:name":"Pink Poodle",
    "wof:placetype":"venue"
},
  "geometry": {"coordinates":[-74.948431,39.426621],"type":"Point"}
}