{
  "type": "Feature",
  "properties": {
    "iso:country":"US",
    "sg:address":"1939 Belvidere Rd",
    "sg:city":"Phillipsburg",
    "sg:classifiers":[
        {
            "category":"Organizations",
            "subcategory":"Religious Organization",
            "type":"Services"
        }
    ],
    "sg:phone":"+1   ",
    "sg:postcode":"08865",
    "sg:province":"NJ",
    "wof:name":"Richard B Gibbins Rev",
    "wof:placetype":"venue"
},
  "geometry": {"coordinates":[-75.15544,40.726625],"type":"Point"}
}