{
  "type": "Feature",
  "properties": {
    "addr:full":"62 Meeker Dr Florham Park NJ 07932",
    "addr:housenumber":"62",
    "addr:postcode":"07932",
    "addr:street":"Meeker Dr",
    "iso:country":"US",
    "sg:address":"62 Meeker Dr",
    "sg:city":"Florham Park",
    "sg:classifiers":[
        {
            "category":"Wholesale",
            "subcategory":"Non-durable Goods",
            "type":"Manufacturing & Wholesale Goods"
        }
    ],
    "sg:phone":"+1 973 564 7515",
    "sg:postcode":"07932",
    "sg:province":"NJ",
    "sg:tags":[
        "export",
        "company",
        "trading",
        "consultant"
    ],
    "wof:name":"Belko Inc",
    "wof:placetype":"venue"
},
  "geometry": {"coordinates":[-74.378314,40.784816],"type":"Point"}
}