{
  "type": "Feature",
  "properties": {
    "addr:full":"30 Neshanic Dr Ringoes NJ 08551",
    "addr:housenumber":"30",
    "addr:postcode":"08551",
    "addr:street":"Neshanic Dr",
    "iso:country":"US",
    "sg:address":"30 Neshanic Dr",
    "sg:city":"Ringoes",
    "sg:classifiers":[
        {
            "category":"Building & Trades",
            "subcategory":"Landscaping Services",
            "type":"Services"
        }
    ],
    "sg:phone":"+1 908 237 1380",
    "sg:postcode":"08551",
    "sg:province":"NJ",
    "sg:tags":[
        "landscape",
        "contractor"
    ],
    "wof:name":"Precise Landscape Svc",
    "wof:placetype":"venue"
},
  "geometry": {"coordinates":[-74.837953,40.458389],"type":"Point"}
}