{
  "type": "Feature",
  "properties": {
    "addr:full":"19 Stone River Rd Clementon NJ 08021",
    "addr:housenumber":"19",
    "addr:postcode":"08021",
    "addr:street":"Stone River Rd",
    "iso:country":"US",
    "sg:address":"19 Stone River Rd",
    "sg:city":"Clementon",
    "sg:classifiers":[
        {
            "category":"Retail",
            "subcategory":"Car Wash",
            "type":"Services"
        }
    ],
    "sg:phone":"+1   ",
    "sg:postcode":"08021",
    "sg:province":"NJ",
    "sg:tags":[
        "carwash"
    ],
    "wof:name":"Ultra Wash",
    "wof:placetype":"venue"
},
  "geometry": {"coordinates":[-75.033497,39.825456],"type":"Point"}
}