{
  "type": "Feature",
  "properties": {
    "iso:country":"US",
    "sg:address":"51 Winchester Rd",
    "sg:city":"Livingston",
    "sg:classifiers":[
        {
            "category":"Professional",
            "subcategory":"Business Services",
            "type":"Services"
        }
    ],
    "sg:phone":"+1   ",
    "sg:postcode":"07039",
    "sg:province":"NJ",
    "wof:name":"Rebolo & Afonso A Partnership",
    "wof:placetype":"venue"
},
  "geometry": {"coordinates":[-74.323278,40.783571],"type":"Point"}
}