{
  "type": "Feature",
  "properties": {
    "iso:country":"US",
    "sg:address":"3 Broadway",
    "sg:city":"Fair Lawn",
    "sg:classifiers":[
        {
            "category":"Banks & Credit Unions",
            "subcategory":"Bank",
            "type":"Services"
        }
    ],
    "sg:phone":"+1   ",
    "sg:postcode":"07410",
    "sg:province":"NJ",
    "sg:tags":[
        "mortgage"
    ],
    "wof:name":"1st 2nd Mortgage of NJ Inc",
    "wof:placetype":"venue"
},
  "geometry": {"coordinates":[-74.107726,40.923636],"type":"Point"}
}