{
  "type": "Feature",
  "properties": {
    "addr:full":"115 School House Rd Oak Ridge NJ 07438",
    "addr:housenumber":"115",
    "addr:postcode":"07438",
    "addr:street":"School House Rd",
    "iso:country":"US",
    "sg:address":"115 School House Rd",
    "sg:city":"Oak Ridge",
    "sg:classifiers":[
        {
            "category":"Retail",
            "subcategory":"Animal Services",
            "type":"Services"
        }
    ],
    "sg:phone":"+1 973 697 3008",
    "sg:postcode":"07438",
    "sg:province":"NJ",
    "wof:name":"Clip Shoppe Pet Grooming",
    "wof:placetype":"venue"
},
  "geometry": {"coordinates":[-74.52314800000001,41.037907],"type":"Point"}
}