{
  "type": "Feature",
  "properties": {
    "addr:full":"301 N Harrison St Princeton NJ 08540",
    "addr:housenumber":"301",
    "addr:postcode":"08540",
    "addr:street":"N Harrison St",
    "iso:country":"US",
    "sg:address":"301 N Harrison St",
    "sg:city":"Princeton",
    "sg:classifiers":[
        {
            "category":"Shopping",
            "subcategory":"Catalog Store",
            "type":"Retail Goods"
        }
    ],
    "sg:phone":"+1 609 924 4162",
    "sg:postcode":"08540",
    "sg:province":"NJ",
    "sg:tags":[
        "mail",
        "order",
        "internet"
    ],
    "wof:name":"J C Penney Catalog Ctr",
    "wof:placetype":"venue"
},
  "geometry": {"coordinates":[-74.654293,40.365845],"type":"Point"}
}