{
  "type": "Feature",
  "properties": {
    "iso:country":"US",
    "sg:address":"615 North Ave",
    "sg:city":"Plainfield",
    "sg:classifiers":[
        {
            "category":"Retail",
            "subcategory":"Auto Repair",
            "type":"Services"
        }
    ],
    "sg:phone":"+1   ",
    "sg:postcode":"07060",
    "sg:province":"NJ",
    "sg:tags":[
        "shop",
        "specializing",
        "medium",
        "automobile",
        "general",
        "t"
    ],
    "wof:name":"Truck Tech Inc",
    "wof:placetype":"venue"
},
  "geometry": {"coordinates":[-74.41127899999999,40.625227],"type":"Point"}
}