{
  "type": "Feature",
  "properties": {
    "iso:country":"US",
    "sg:address":"28 Port Imperial Blvd",
    "sg:city":"West New York",
    "sg:classifiers":[
        {
            "category":"Shopping",
            "subcategory":"Clothing, Apparel, & Fashions",
            "type":"Retail Goods"
        }
    ],
    "sg:phone":"+1 201 866 7773",
    "sg:postcode":"07093",
    "sg:province":"NJ",
    "sg:tags":[
        "baby",
        "accessory"
    ],
    "wof:name":"Baby Jade",
    "wof:placetype":"venue"
},
  "geometry": {"coordinates":[-74.010114,40.782889],"type":"Point"}
}