{
  "type": "Feature",
  "properties": {
    "iso:country":"US",
    "sg:address":"26 Knollwood Dr",
    "sg:city":"Short Hills",
    "sg:classifiers":[
        {
            "category":"Professional",
            "subcategory":"Management & Consulting",
            "type":"Services"
        }
    ],
    "sg:phone":"+1 973 467 2237",
    "sg:postcode":"07078",
    "sg:province":"NJ",
    "sg:tags":[
        "business"
    ],
    "wof:name":"Etf Consulting LLC",
    "wof:placetype":"venue"
},
  "geometry": {"coordinates":[-74.325647,40.727807],"type":"Point"}
}