{
  "type": "Feature",
  "properties": {
    "iso:country":"US",
    "sg:address":"1 Deer Park Drive Suite G",
    "sg:city":"Monmouth Junction",
    "sg:classifiers":[
        {
            "category":"Professional",
            "subcategory":"Research",
            "type":"Services"
        }
    ],
    "sg:phone":"+1 732 246 8676",
    "sg:postcode":"08852",
    "sg:province":"NJ",
    "sg:website":"http://www.tyrx.com/",
    "wof:name":"TyRx Pharma",
    "wof:placetype":"venue"
},
  "geometry": {"coordinates":[-74.583637,40.379059],"type":"Point"}
}