{
  "type": "Feature",
  "properties": {
    "iso:country":"US",
    "sg:address":"18 Elm St",
    "sg:city":"Morristown",
    "sg:classifiers":[
        {
            "category":"Personal",
            "subcategory":"Beauty Salon",
            "type":"Services"
        }
    ],
    "sg:phone":"+1 973 540 0764",
    "sg:postcode":"07960",
    "sg:province":"NJ",
    "sg:tags":[
        "shop",
        "treatment",
        "skin"
    ],
    "sg:website":"www.bellezzasi.com",
    "wof:name":"Bellezza Si Esthetics European",
    "wof:placetype":"venue"
},
  "geometry": {"coordinates":[-74.475661,40.792944],"type":"Point"}
}