{
  "type": "Feature",
  "properties": {
    "addr:full":"15 Lewis St Eatontown NJ 07724",
    "addr:housenumber":"15",
    "addr:postcode":"07724",
    "addr:street":"Lewis St",
    "iso:country":"US",
    "sg:address":"15 Lewis St",
    "sg:city":"Eatontown",
    "sg:classifiers":[
        {
            "category":"Building & Trades",
            "subcategory":"Construction",
            "type":"Services"
        }
    ],
    "sg:phone":"+1 732 935 0033",
    "sg:postcode":"07724",
    "sg:province":"NJ",
    "sg:tags":[
        "boring",
        "drilling",
        "contractor"
    ],
    "wof:name":"Shore Drilling Inc",
    "wof:placetype":"venue"
},
  "geometry": {"coordinates":[-74.060698,40.305073],"type":"Point"}
}