{
  "type": "Feature",
  "properties": {
    "iso:country":"US",
    "sg:address":"10 Twin Brook Rd",
    "sg:city":"West Caldwell",
    "sg:classifiers":[
        {
            "category":"Shopping",
            "subcategory":"Bicycles & Sporting Goods",
            "type":"Retail Goods"
        }
    ],
    "sg:phone":"+1 973 746 1230",
    "sg:postcode":"07006",
    "sg:province":"NJ",
    "sg:tags":[
        "equipment",
        "tennis",
        "supply"
    ],
    "wof:name":"Di Milia Tennis Court Access",
    "wof:placetype":"venue"
},
  "geometry": {"coordinates":[-74.27977,40.857123],"type":"Point"}
}