{
  "type": "Feature",
  "properties": {
    "iso:country":"US",
    "sg:address":"918 New Brunswick Ave",
    "sg:city":"Phillipsburg",
    "sg:classifiers":[
        {
            "category":"Manufacturing",
            "subcategory":"Buildings",
            "type":"Manufacturing & Wholesale Goods"
        },
        {
            "category":"Home & Garden",
            "subcategory":"Building Materials",
            "type":"Retail Goods"
        },
        {
            "category":"Building & Trades",
            "subcategory":"Construction",
            "type":"Services"
        }
    ],
    "sg:phone":"+1 908 454 7852",
    "sg:postcode":"08865",
    "sg:province":"NJ",
    "sg:tags":[
        "builder",
        "contractor",
        "concrete",
        "staining",
        "gazebo",
        "patio"
    ],
    "wof:name":"Pride Construction Co",
    "wof:placetype":"venue"
},
  "geometry": {"coordinates":[-75.137753,40.673981],"type":"Point"}
}