{
  "type": "Feature",
  "properties": {
    "addr:full":"201 42nd St S Brigantine NJ 08203",
    "addr:housenumber":"201",
    "addr:postcode":"08203",
    "addr:street":"42Nd St S",
    "iso:country":"US",
    "sg:address":"201 42nd St S",
    "sg:city":"Brigantine",
    "sg:classifiers":[
        {
            "category":"Education",
            "subcategory":"Special Training",
            "type":"Public Place"
        }
    ],
    "sg:phone":"+1   ",
    "sg:postcode":"08203",
    "sg:province":"NJ",
    "sg:tags":[
        "school"
    ],
    "wof:name":"Apoctla Academy",
    "wof:placetype":"venue"
},
  "geometry": {"coordinates":[-74.39217499999999,39.389049],"type":"Point"}
}