{
  "type": "Feature",
  "properties": {
    "iso:country":"US",
    "sg:address":"35 Clyde Rd",
    "sg:city":"Somerset",
    "sg:classifiers":[
        {
            "category":"Real Estate",
            "subcategory":"Real Estate Agent",
            "type":"Services"
        }
    ],
    "sg:phone":"+1 732 873 1258",
    "sg:postcode":"08873",
    "sg:province":"NJ",
    "sg:tags":[
        "management"
    ],
    "wof:name":"Preferred Property Management",
    "wof:placetype":"venue"
},
  "geometry": {"coordinates":[-74.510386,40.486656],"type":"Point"}
}