{
  "type": "Feature",
  "properties": {
    "addr:full":"974 Boulevard E Weehawken NJ 07086",
    "addr:housenumber":"974;e",
    "addr:postcode":"07086",
    "addr:street":"Boulevard",
    "iso:country":"US",
    "sg:address":"974 Boulevard E",
    "sg:city":"Weehawken",
    "sg:classifiers":[
        {
            "category":"Professional",
            "type":"Services"
        }
    ],
    "sg:phone":"+1 201 867 1325",
    "sg:postcode":"07086",
    "sg:province":"NJ",
    "sg:tags":[
        "establishment"
    ],
    "wof:name":"Sangil Co Inc",
    "wof:placetype":"venue"
},
  "geometry": {"coordinates":[-74.01358,40.777802],"type":"Point"}
}