{
  "type": "Feature",
  "properties": {
    "addr:full":"869 Fischer Blvd Toms River NJ 08753",
    "addr:housenumber":"869",
    "addr:postcode":"08753",
    "addr:street":"Fischer Blvd",
    "iso:country":"US",
    "sg:address":"869 Fischer Blvd",
    "sg:city":"Toms River",
    "sg:classifiers":[
        {
            "category":"Autos & Motor Vehicles",
            "subcategory":"Fuel & Gas Station",
            "type":"Retail Goods"
        }
    ],
    "sg:phone":"+1 732 270 8001",
    "sg:postcode":"08753",
    "sg:province":"NJ",
    "sg:tags":[
        "oil"
    ],
    "wof:name":"Fischer Boulevard Shell",
    "wof:placetype":"venue"
},
  "geometry": {"coordinates":[-74.135006,39.972225],"type":"Point"}
}