{
  "type": "Feature",
  "properties": {
    "addr:full":"12 Brattleboro Rd Medford NJ 08085",
    "addr:housenumber":"12",
    "addr:postcode":"08085",
    "addr:street":"Brattleboro Rd",
    "iso:country":"US",
    "sg:address":"12 Brattleboro Rd",
    "sg:city":"Medford",
    "sg:classifiers":[
        {
            "category":"Building & Trades",
            "subcategory":"Construction",
            "type":"Services"
        }
    ],
    "sg:phone":"+1 609 714 2981",
    "sg:postcode":"08085",
    "sg:province":"NJ",
    "sg:tags":[
        "builder",
        "operative"
    ],
    "wof:name":"Pulte",
    "wof:placetype":"venue"
},
  "geometry": {"coordinates":[-75.34818,39.743067],"type":"Point"}
}