{
  "type": "Feature",
  "properties": {
    "addr:full":"73 Park St Montclair NJ 07042",
    "addr:housenumber":"73",
    "addr:postcode":"07042",
    "addr:street":"Park St",
    "iso:country":"US",
    "sg:address":"73 Park St",
    "sg:city":"Montclair",
    "sg:classifiers":[
        {
            "category":"Health Services",
            "subcategory":"Doctor",
            "type":"Services"
        }
    ],
    "sg:phone":"+1 973 746 7375",
    "sg:postcode":"07042",
    "sg:province":"NJ",
    "wof:name":"Prakash Kalpana MD",
    "wof:placetype":"venue"
},
  "geometry": {"coordinates":[-74.215698,40.818802],"type":"Point"}
}