{
  "type": "Feature",
  "properties": {
    "addr:full":"76 Audrey Zapp Dr Jersey City NJ 07305",
    "addr:housenumber":"76",
    "addr:postcode":"07305",
    "addr:street":"Audrey Zapp Dr",
    "iso:country":"US",
    "sg:address":"76 Audrey Zapp Dr",
    "sg:city":"Jersey City",
    "sg:classifiers":[
        {
            "category":"Restaurant",
            "type":"Food & Drink"
        }
    ],
    "sg:menulink":"http://www.allmenus.com/nj/jersey-city/267431-liberty-house-restaurant/menu/",
    "sg:phone":"+1 201 395 0300",
    "sg:postcode":"07305",
    "sg:province":"NJ",
    "sg:tags":[
        "seafood",
        "american"
    ],
    "wof:name":"Liberty House Restaurant",
    "wof:placetype":"venue"
},
  "geometry": {"coordinates":[-74.041978,40.708963],"type":"Point"}
}