{
  "type": "Feature",
  "properties": {
    "addr:full":"Bloomfield Pompton Lakes NJ 07442",
    "addr:postcode":"07442",
    "iso:country":"US",
    "sg:address":"Bloomfield",
    "sg:city":"Pompton Lakes",
    "sg:classifiers":[
        {
            "category":"Social Services",
            "subcategory":"Child Care",
            "type":"Services"
        },
        {
            "category":"Education",
            "subcategory":"Preschool",
            "type":"Public Place"
        },
        {
            "category":"Education",
            "subcategory":"School",
            "type":"Public Place"
        }
    ],
    "sg:phone":"+1 973 835 1848",
    "sg:postcode":"07442",
    "sg:province":"NJ",
    "sg:tags":[
        "elementary",
        "day"
    ],
    "wof:name":"Rainbow Montessori",
    "wof:placetype":"venue"
},
  "geometry": {"coordinates":[-74.284897,41.000099],"type":"Point"}
}