{
  "type": "Feature",
  "properties": {
    "addr:full":"11101 1st Ave Stone Harbor NJ 08247",
    "addr:housenumber":"11101",
    "addr:postcode":"08247",
    "addr:street":"1St Ave",
    "iso:country":"US",
    "sg:address":"11101 1st Ave",
    "sg:city":"Stone Harbor",
    "sg:classifiers":[
        {
            "category":"Organizations",
            "subcategory":"Religious Organization",
            "type":"Services"
        }
    ],
    "sg:phone":"+1 609 368 4761",
    "sg:postcode":"08247",
    "sg:province":"NJ",
    "wof:name":"Sisters of I H M",
    "wof:placetype":"venue"
},
  "geometry": {"coordinates":[-74.76442400000001,39.042589],"type":"Point"}
}