{
  "type": "Feature",
  "properties": {
    "addr:full":"15 Clark Ave Edison NJ 08817",
    "addr:housenumber":"15",
    "addr:postcode":"08817",
    "addr:street":"Clark Ave",
    "iso:country":"US",
    "sg:address":"15 Clark Ave",
    "sg:city":"Edison",
    "sg:classifiers":[
        {
            "category":"Professional",
            "subcategory":"Management & Consulting",
            "type":"Services"
        }
    ],
    "sg:phone":"+1 732 572 8723",
    "sg:postcode":"08817",
    "sg:province":"NJ",
    "sg:tags":[
        "business"
    ],
    "wof:name":"Shiv Oam Inc",
    "wof:placetype":"venue"
},
  "geometry": {"coordinates":[-74.409353,40.511653],"type":"Point"}
}