{
  "type": "Feature",
  "properties": {
    "addr:full":"555 Old Bridge Tpke East Brunswick NJ 08816",
    "addr:housenumber":"555",
    "addr:postcode":"08816",
    "addr:street":"Old Bridge Tpke",
    "iso:country":"US",
    "sg:address":"555 Old Bridge Tpke",
    "sg:city":"East Brunswick",
    "sg:classifiers":[
        {
            "category":"Restaurant",
            "type":"Food & Drink"
        }
    ],
    "sg:menulink":"http://www.allmenus.com/nj/south-river/98443-carrabbas/menu/",
    "sg:phone":"+1 732 432 8054",
    "sg:postcode":"08816",
    "sg:province":"NJ",
    "sg:tags":[
        "italian"
    ],
    "wof:name":"Carrabba's",
    "wof:placetype":"venue"
},
  "geometry": {"coordinates":[-74.395685,40.459277],"type":"Point"}
}