{
  "type": "Feature",
  "properties": {
    "addr:full":"32 North Ave Cedarville NJ 08311",
    "addr:housenumber":"32",
    "addr:postcode":"08311",
    "addr:street":"North Ave",
    "iso:country":"US",
    "sg:address":"32 North Ave",
    "sg:city":"Cedarville",
    "sg:classifiers":[
        {
            "category":"Retail",
            "subcategory":"Auto Repair",
            "type":"Services"
        }
    ],
    "sg:phone":"+1 856 447 5090",
    "sg:postcode":"08311",
    "sg:province":"NJ",
    "sg:tags":[
        "glass",
        "coating",
        "tinting"
    ],
    "wof:name":"J & M Enterprises",
    "wof:placetype":"venue"
},
  "geometry": {"coordinates":[-75.20261600000001,39.345362],"type":"Point"}
}