{
  "type": "Feature",
  "properties": {
    "iso:country":"US",
    "sg:address":"1200 River Ave",
    "sg:city":"Lakewood",
    "sg:classifiers":[
        {
            "category":"Real Estate",
            "subcategory":"Real Estate Operator",
            "type":"Services"
        }
    ],
    "sg:phone":"+1 732 370 5650",
    "sg:postcode":"08701",
    "sg:province":"NJ",
    "sg:tags":[
        "owner",
        "commercial",
        "mall",
        "shopping",
        "center"
    ],
    "wof:name":"Cross Mill Village",
    "wof:placetype":"venue"
},
  "geometry": {"coordinates":[-74.220671,40.054314],"type":"Point"}
}