{
  "type": "Feature",
  "properties": {
    "iso:country":"US",
    "sg:address":"217 Stites Ave",
    "sg:city":"Cape May Court House",
    "sg:classifiers":[
        {
            "category":"Building & Trades",
            "subcategory":"Construction",
            "type":"Services"
        }
    ],
    "sg:phone":"+1 609 465 9774",
    "sg:postcode":"08210",
    "sg:province":"NJ",
    "sg:tags":[
        "concrete",
        "asphalt",
        "contractor"
    ],
    "wof:name":"Precision Paving & Concrete",
    "wof:placetype":"venue"
},
  "geometry": {"coordinates":[-74.83121199999999,39.0827],"type":"Point"}
}