{
  "type": "Feature",
  "properties": {
    "iso:country":"US",
    "sg:address":"163 Sylvan St",
    "sg:city":"Rutherford",
    "sg:classifiers":[
        {
            "category":"Retail",
            "subcategory":"Self-service Laundry",
            "type":"Services"
        }
    ],
    "sg:phone":"+1 201 933 3672",
    "sg:postcode":"07070",
    "sg:province":"NJ",
    "sg:tags":[
        "coin"
    ],
    "wof:name":"Jt Coin Inc",
    "wof:placetype":"venue"
},
  "geometry": {"coordinates":[-74.107652,40.821622],"type":"Point"}
}