{
  "type": "Feature",
  "properties": {
    "addr:full":"100 US Hwy 9 Englishtown NJ 07726",
    "addr:housenumber":"100",
    "addr:postcode":"07726",
    "addr:street":"Us Hwy 9",
    "iso:country":"US",
    "sg:address":"100 US Hwy 9",
    "sg:city":"Englishtown",
    "sg:classifiers":[
        {
            "category":"Professional",
            "subcategory":"Management & Consulting",
            "type":"Services"
        }
    ],
    "sg:phone":"+1 732 308 9166",
    "sg:postcode":"07726",
    "sg:province":"NJ",
    "sg:tags":[
        "consultant",
        "lighting"
    ],
    "wof:name":"Lights On 9",
    "wof:placetype":"venue"
},
  "geometry": {"coordinates":[-74.30705399999999,40.352197],"type":"Point"}
}