{
  "type": "Feature",
  "properties": {
    "addr:full":"44 Lincoln Shire Dr Englishtown NJ 07726",
    "addr:housenumber":"44",
    "addr:postcode":"07726",
    "addr:street":"Lincoln Shire Dr",
    "iso:country":"US",
    "sg:address":"44 Lincoln Shire Dr",
    "sg:city":"Englishtown",
    "sg:classifiers":[
        {
            "category":"Restaurant",
            "type":"Food & Drink"
        }
    ],
    "sg:phone":"+1   ",
    "sg:postcode":"07726",
    "sg:province":"NJ",
    "sg:tags":[
        "eating"
    ],
    "wof:name":"Cooking With Suzanne",
    "wof:placetype":"venue"
},
  "geometry": {"coordinates":[-74.31158000000001,40.291925],"type":"Point"}
}