{
  "type": "Feature",
  "properties": {
    "addr:full":"115 E 17th Ave Wildwood NJ 08260",
    "addr:housenumber":"115",
    "addr:postcode":"08260",
    "addr:street":"E 17Th Ave",
    "iso:country":"US",
    "sg:address":"115 E 17th Ave",
    "sg:city":"Wildwood",
    "sg:classifiers":[
        {
            "category":"Restaurant",
            "type":"Food & Drink"
        }
    ],
    "sg:phone":"+1 609 729 6110",
    "sg:postcode":"08260",
    "sg:province":"NJ",
    "sg:tags":[
        "pizza"
    ],
    "sg:website":"www.santuccis.com",
    "wof:name":"Santucci Square Pizza",
    "wof:placetype":"venue"
},
  "geometry": {"coordinates":[-74.80392000000001,38.999177],"type":"Point"}
}