{
  "type": "Feature",
  "properties": {
    "iso:country":"US",
    "sg:address":"80 James St",
    "sg:city":"Edison",
    "sg:classifiers":[
        {
            "category":"Organizations",
            "subcategory":"Non-profit Organization",
            "type":"Services"
        }
    ],
    "sg:phone":"+1 732 632 1540",
    "sg:postcode":"08820",
    "sg:province":"NJ",
    "sg:tags":[
        "social"
    ],
    "wof:name":"Kennedy John F Med Ctr Fndtion",
    "wof:placetype":"venue"
},
  "geometry": {"coordinates":[-74.346569,40.557055],"type":"Point"}
}