{
  "type": "Feature",
  "properties": {
    "addr:full":"3 Bauer Dr West Orange NJ 07052",
    "addr:housenumber":"3",
    "addr:postcode":"07052",
    "addr:street":"Bauer Dr",
    "iso:country":"US",
    "sg:address":"3 Bauer Dr",
    "sg:city":"West Orange",
    "sg:classifiers":[
        {
            "category":"Professional",
            "type":"Services"
        }
    ],
    "sg:phone":"+1   ",
    "sg:postcode":"07052",
    "sg:province":"NJ",
    "wof:name":"Elies Boutique LLC",
    "wof:placetype":"venue"
},
  "geometry": {"coordinates":[-74.26003,40.80236],"type":"Point"}
}