{
  "type": "Feature",
  "properties": {
    "addr:full":"211 N Main St Cape May Ct Hse NJ 08210",
    "addr:housenumber":"211",
    "addr:postcode":"08210",
    "addr:street":"N Main St Cape May Ct",
    "iso:country":"US",
    "sg:address":"211 N Main St",
    "sg:city":"Cape May Ct Hse",
    "sg:classifiers":[
        {
            "category":"Banks & Credit Unions",
            "subcategory":"Investment Brokerage",
            "type":"Services"
        }
    ],
    "sg:phone":"+1 609 465 1500",
    "sg:postcode":"08210",
    "sg:province":"NJ",
    "sg:tags":[
        "stock",
        "commodity",
        "contract",
        "bond"
    ],
    "wof:name":"Merrill Lynch",
    "wof:placetype":"venue"
},
  "geometry": {"coordinates":[-74.819855,39.086422],"type":"Point"}
}