{
  "type": "Feature",
  "properties": {
    "iso:country":"US",
    "sg:address":"40 N Kentucky Ave",
    "sg:city":"Atlantic City",
    "sg:classifiers":[
        {
            "category":"Personal",
            "subcategory":"Barber",
            "type":"Services"
        }
    ],
    "sg:phone":"+1 609 348 4430",
    "sg:postcode":"08401",
    "sg:province":"NJ",
    "sg:tags":[
        "shop"
    ],
    "wof:name":"Sonny's 40 Ntn Barber Co",
    "wof:placetype":"venue"
},
  "geometry": {"coordinates":[-74.43134499999999,39.362005],"type":"Point"}
}