{
  "type": "Feature",
  "properties": {
    "iso:country":"US",
    "sg:address":"847 Sampson Ave",
    "sg:city":"Phillipsburg",
    "sg:classifiers":[
        {
            "category":"Professional",
            "subcategory":"Business Services",
            "type":"Services"
        }
    ],
    "sg:phone":"+1   ",
    "sg:postcode":"08865",
    "sg:province":"NJ",
    "wof:name":"Crystal Pig Recording Studio",
    "wof:placetype":"venue"
},
  "geometry": {"coordinates":[-75.164349,40.663141],"type":"Point"}
}