{
  "type": "Feature",
  "properties": {
    "iso:country":"US",
    "sg:address":"71 Union Ave Ste 112",
    "sg:city":"Rutherford",
    "sg:classifiers":[
        {
            "category":"Banks & Credit Unions",
            "subcategory":"Financial Services",
            "type":"Services"
        }
    ],
    "sg:phone":"+1 201 935 7777",
    "sg:postcode":"07070",
    "sg:province":"NJ",
    "sg:tags":[
        "broker",
        "mortgage"
    ],
    "wof:name":"Apex Lending Inc",
    "wof:placetype":"venue"
},
  "geometry": {"coordinates":[-74.10401400000001,40.830607],"type":"Point"}
}