{
  "type": "Feature",
  "properties": {
    "addr:full":"220 W Pkwy Pompton Plains NJ 07444",
    "addr:housenumber":"220",
    "addr:postcode":"07444",
    "addr:street":"W Pkwy",
    "iso:country":"US",
    "sg:address":"220 W Pkwy",
    "sg:city":"Pompton Plains",
    "sg:classifiers":[
        {
            "category":"Wholesale",
            "subcategory":"Non-durable Goods",
            "type":"Manufacturing & Wholesale Goods"
        }
    ],
    "sg:phone":"+1 973 616 8877",
    "sg:postcode":"07444",
    "sg:province":"NJ",
    "sg:tags":[
        "fund",
        "raising",
        "merchandise"
    ],
    "sg:website":"www.ashleyfarmsinc.com",
    "wof:name":"Ashley Farms Inc",
    "wof:placetype":"venue"
},
  "geometry": {"coordinates":[-74.311955,40.978109],"type":"Point"}
}