{
  "type": "Feature",
  "properties": {
    "addr:full":"1322 State Rte 83 Cape May Court House NJ 08210",
    "addr:housenumber":"1322",
    "addr:postcode":"08210",
    "addr:street":"State Rte 83 Cape May",
    "iso:country":"US",
    "sg:address":"1322 State Rte 83",
    "sg:city":"Cape May Court House",
    "sg:classifiers":[
        {
            "category":"Building & Trades",
            "subcategory":"Electrical",
            "type":"Services"
        }
    ],
    "sg:phone":"+1 609 861 3321",
    "sg:postcode":"08210",
    "sg:province":"NJ",
    "sg:tags":[
        "electrical",
        "contractor"
    ],
    "wof:name":"Edmunds Electric",
    "wof:placetype":"venue"
},
  "geometry": {"coordinates":[-74.783641,39.163624],"type":"Point"}
}