{
  "type": "Feature",
  "properties": {
    "addr:full":"6 Appleby St Helmetta NJ 08857",
    "addr:housenumber":"6",
    "addr:postcode":"08857",
    "addr:street":"Appleby St",
    "iso:country":"US",
    "sg:address":"6 Appleby St",
    "sg:city":"Helmetta",
    "sg:classifiers":[
        {
            "category":"Manufacturing",
            "subcategory":"Retail Goods",
            "type":"Manufacturing & Wholesale Goods"
        }
    ],
    "sg:phone":"+1 732 605 2780",
    "sg:postcode":"08857",
    "sg:province":"NJ",
    "sg:tags":[
        "product",
        "mfg"
    ],
    "wof:name":"Locomotive Workshop",
    "wof:placetype":"venue"
},
  "geometry": {"coordinates":[-74.365172,40.410043],"type":"Point"}
}