{
  "type": "Feature",
  "properties": {
    "iso:country":"US",
    "sg:address":"6 Growney St",
    "sg:city":"Edison",
    "sg:classifiers":[
        {
            "category":"Professional",
            "subcategory":"Computer Services",
            "type":"Services"
        }
    ],
    "sg:phone":"+1   ",
    "sg:postcode":"08817",
    "sg:province":"NJ",
    "sg:tags":[
        "prepackaged",
        "software"
    ],
    "wof:name":"Sterling Commerce America",
    "wof:placetype":"venue"
},
  "geometry": {"coordinates":[-74.38699699999999,40.543228],"type":"Point"}
}