{
  "type": "Feature",
  "properties": {
    "addr:full":"21 W Delaware Ave Pennington NJ 08534",
    "addr:housenumber":"21",
    "addr:postcode":"08534",
    "addr:street":"W Delaware Ave",
    "iso:country":"US",
    "sg:address":"21 W Delaware Ave",
    "sg:city":"Pennington",
    "sg:classifiers":[
        {
            "category":"Retail",
            "subcategory":"Repair Shop",
            "type":"Services"
        }
    ],
    "sg:phone":"+1   ",
    "sg:postcode":"08534",
    "sg:province":"NJ",
    "wof:name":"Pennington Clock Shop",
    "wof:placetype":"venue"
},
  "geometry": {"coordinates":[-74.79222300000001,40.327998],"type":"Point"}
}