{
  "type": "Feature",
  "properties": {
    "addr:full":"39 Irving Pl Red Bank NJ 07701",
    "addr:housenumber":"39",
    "addr:postcode":"07701",
    "addr:street":"Irving Pl",
    "iso:country":"US",
    "sg:address":"39 Irving Pl",
    "sg:city":"Red Bank",
    "sg:classifiers":[
        {
            "category":"Insurance",
            "subcategory":"Insurance Agent",
            "type":"Services"
        }
    ],
    "sg:phone":"+1   ",
    "sg:postcode":"07701",
    "sg:province":"NJ",
    "wof:name":"John Hancock",
    "wof:placetype":"venue"
},
  "geometry": {"coordinates":[-74.065169,40.344229],"type":"Point"}
}