{
  "type": "Feature",
  "properties": {
    "addr:full":"625 Evans St Elizabeth NJ 07201",
    "addr:housenumber":"625",
    "addr:postcode":"07201",
    "addr:street":"Evans St",
    "iso:country":"US",
    "sg:address":"625 Evans St",
    "sg:city":"Elizabeth",
    "sg:classifiers":[
        {
            "category":"Professional",
            "subcategory":"Management & Consulting",
            "type":"Services"
        }
    ],
    "sg:phone":"+1 908 352 3776",
    "sg:postcode":"07201",
    "sg:province":"NJ",
    "sg:tags":[
        "correctional",
        "institution"
    ],
    "sg:website":"www.correctionalservices.com",
    "wof:name":"Correctional Services Corp",
    "wof:placetype":"venue"
},
  "geometry": {"coordinates":[-74.188006,40.667642],"type":"Point"}
}