{
  "type": "Feature",
  "properties": {
    "iso:country":"US",
    "sg:address":"301 Beach Ave",
    "sg:city":"Cape May",
    "sg:classifiers":[
        {
            "category":"Restaurant",
            "type":"Food & Drink"
        }
    ],
    "sg:phone":"+1 609 884 6088",
    "sg:postcode":"08204",
    "sg:province":"NJ",
    "wof:name":"George's Place",
    "wof:placetype":"venue"
},
  "geometry": {"coordinates":[-74.923012,38.930503],"type":"Point"}
}