{
  "type": "Feature",
  "properties": {
    "iso:country":"US",
    "sg:address":"24 E Broad St",
    "sg:city":"Gibbstown",
    "sg:classifiers":[
        {
            "category":"Health Services",
            "subcategory":"Optometrist",
            "type":"Services"
        }
    ],
    "sg:phone":"+1   ",
    "sg:postcode":"08027",
    "sg:province":"NJ",
    "wof:name":"Vincent L Gattuso OD",
    "wof:placetype":"venue"
},
  "geometry": {"coordinates":[-75.27716100000001,39.826166],"type":"Point"}
}