{
  "type": "Feature",
  "properties": {
    "iso:country":"US",
    "sg:address":"524 State Rte 73",
    "sg:city":"Hammonton",
    "sg:classifiers":[
        {
            "category":"Travel",
            "subcategory":"Hotels & Motels",
            "type":"Entertainment"
        }
    ],
    "sg:phone":"+1 609 561 6200",
    "sg:postcode":"08037",
    "sg:province":"NJ",
    "wof:name":"Winslow Inn & Suites",
    "wof:placetype":"venue"
},
  "geometry": {"coordinates":[-74.87955100000001,39.660795],"type":"Point"}
}