{
  "type": "Feature",
  "properties": {
    "addr:full":"1 Main St Sparta NJ 07871",
    "addr:housenumber":"1",
    "addr:postcode":"07871",
    "addr:street":"Main St",
    "iso:country":"US",
    "sg:address":"1 Main St",
    "sg:city":"Sparta",
    "sg:classifiers":[
        {
            "category":"Professional",
            "subcategory":"Lawyer & Legal Services",
            "type":"Services"
        }
    ],
    "sg:phone":"+1   ",
    "sg:postcode":"07871",
    "sg:province":"NJ",
    "wof:name":"Sweeny George F Atty At Law",
    "wof:placetype":"venue"
},
  "geometry": {"coordinates":[-74.636572,41.036125],"type":"Point"}
}