{
  "type": "Feature",
  "properties": {
    "iso:country":"US",
    "sg:address":"230 Woodland Ave",
    "sg:city":"River Edge",
    "sg:classifiers":[
        {
            "category":"Education",
            "subcategory":"School",
            "type":"Public Place"
        }
    ],
    "sg:phone":"+1 201 599 7250",
    "sg:postcode":"07661",
    "sg:province":"NJ",
    "wof:name":"River Dell Middle School",
    "wof:placetype":"venue"
},
  "geometry": {"coordinates":[-74.036345,40.939165],"type":"Point"}
}