{
  "type": "Feature",
  "properties": {
    "iso:country":"US",
    "sg:address":"7 Whitehall Ave",
    "sg:city":"Edison",
    "sg:classifiers":[
        {
            "category":"Wholesale",
            "subcategory":"Machinery & Supplies",
            "type":"Manufacturing & Wholesale Goods"
        }
    ],
    "sg:phone":"+1 732 767 0395",
    "sg:postcode":"08820",
    "sg:province":"NJ",
    "sg:tags":[
        "green",
        "product",
        "industrial",
        "com",
        "coffee"
    ],
    "wof:name":"Network Solutions",
    "wof:placetype":"venue"
},
  "geometry": {"coordinates":[-74.37259899999999,40.573963],"type":"Point"}
}