{
  "type": "Feature",
  "properties": {
    "iso:country":"US",
    "sg:address":"406 Euclid Ave",
    "sg:city":"Manasquan",
    "sg:classifiers":[
        {
            "category":"Building & Trades",
            "subcategory":"Construction",
            "type":"Services"
        }
    ],
    "sg:phone":"+1 732 223 6684",
    "sg:postcode":"08736",
    "sg:province":"NJ",
    "sg:tags":[
        "house"
    ],
    "wof:name":"Mark Herrmann Construction",
    "wof:placetype":"venue"
},
  "geometry": {"coordinates":[-74.04166600000001,40.116419],"type":"Point"}
}