{
  "type": "Feature",
  "properties": {
    "addr:full":"354 Monroe Ave Kenilworth NJ 07033",
    "addr:housenumber":"354",
    "addr:postcode":"07033",
    "addr:street":"Monroe Ave",
    "iso:country":"US",
    "sg:address":"354 Monroe Ave",
    "sg:city":"Kenilworth",
    "sg:classifiers":[
        {
            "category":"Autos & Motor Vehicles",
            "subcategory":"Fuel & Gas Station",
            "type":"Retail Goods"
        }
    ],
    "sg:phone":"+1   ",
    "sg:postcode":"07033",
    "sg:province":"NJ",
    "sg:tags":[
        "station",
        "gasoline"
    ],
    "wof:name":"BP",
    "wof:placetype":"venue"
},
  "geometry": {"coordinates":[-74.29846999999999,40.67949],"type":"Point"}
}