{
  "type": "Feature",
  "properties": {
    "iso:country":"US",
    "sg:address":"920 Main St",
    "sg:city":"Hackensack",
    "sg:classifiers":[
        {
            "category":"Health Services",
            "subcategory":"Doctor",
            "type":"Services"
        }
    ],
    "sg:phone":"+1 201 342 7733",
    "sg:postcode":"07601",
    "sg:province":"NJ",
    "wof:name":"Steven Kanarek MD",
    "wof:placetype":"venue"
},
  "geometry": {"coordinates":[-74.041178,40.908448],"type":"Point"}
}