{
  "type": "Feature",
  "properties": {
    "iso:country":"US",
    "sg:address":"2214 Buttonwood Ln",
    "sg:city":"Millville",
    "sg:classifiers":[
        {
            "category":"Building & Trades",
            "subcategory":"Plumbing",
            "type":"Services"
        }
    ],
    "sg:phone":"+1 856 825 3191",
    "sg:postcode":"08332",
    "sg:province":"NJ",
    "sg:tags":[
        "contractor"
    ],
    "wof:name":"Genco Heating & AC",
    "wof:placetype":"venue"
},
  "geometry": {"coordinates":[-75.00470799999999,39.386642],"type":"Point"}
}