{
  "type": "Feature",
  "properties": {
    "iso:country":"US",
    "sg:address":"446 Jersey Ave",
    "sg:city":"Jersey City",
    "sg:classifiers":[
        {
            "category":"Retail",
            "subcategory":"Animal Services",
            "type":"Services"
        }
    ],
    "sg:phone":"+1 201 433 9118",
    "sg:postcode":"07302",
    "sg:province":"NJ",
    "sg:tags":[
        "pet",
        "boarding",
        "sitting"
    ],
    "wof:name":"Happy Hounds & Cozy Cats",
    "wof:placetype":"venue"
},
  "geometry": {"coordinates":[-74.04821699999999,40.717628],"type":"Point"}
}