{
  "type": "Feature",
  "properties": {
    "addr:full":"48 Mill Brook Rd Broadway NJ 08822",
    "addr:housenumber":"48",
    "addr:postcode":"08822",
    "addr:street":"Mill Brook Rd",
    "iso:country":"US",
    "sg:address":"48 Mill Brook Rd",
    "sg:city":"Broadway",
    "sg:classifiers":[
        {
            "category":"Recreation",
            "type":"Entertainment"
        }
    ],
    "sg:phone":"+1 908 689 9869",
    "sg:postcode":"08822",
    "sg:province":"NJ",
    "wof:name":"Christi",
    "wof:placetype":"venue"
},
  "geometry": {"coordinates":[-74.830094,40.514304],"type":"Point"}
}