{
  "type": "Feature",
  "properties": {
    "addr:full":"1529 Route 206 Vincentown NJ 08088",
    "addr:housenumber":"1529",
    "addr:postcode":"08088",
    "addr:street":"Route 206",
    "iso:country":"US",
    "sg:address":"1529 Route 206",
    "sg:city":"Vincentown",
    "sg:classifiers":[
        {
            "category":"Restaurant",
            "type":"Food & Drink"
        }
    ],
    "sg:menulink":"http://www.allmenus.com/nj/tabernacle/146443-subway/menu/",
    "sg:phone":"+1 609 268 6363",
    "sg:postcode":"08088",
    "sg:province":"NJ",
    "sg:tags":[
        "american",
        "sandwich"
    ],
    "wof:name":"Subway",
    "wof:placetype":"venue"
},
  "geometry": {"coordinates":[-74.73446800000001,39.853288],"type":"Point"}
}