{
  "type": "Feature",
  "properties": {
    "iso:country":"US",
    "sg:address":"5006 Marshall Rd",
    "sg:city":"Farmingdale",
    "sg:classifiers":[
        {
            "category":"Organizations",
            "subcategory":"Religious Organization",
            "type":"Services"
        }
    ],
    "sg:phone":"+1   ",
    "sg:postcode":"07727",
    "sg:province":"NJ",
    "wof:name":"Hope Chpel First Baptst Church",
    "wof:placetype":"venue"
},
  "geometry": {"coordinates":[-74.12773300000001,40.220321],"type":"Point"}
}