{
  "type": "Feature",
  "properties": {
    "iso:country":"US",
    "sg:address":"163 Passaic St",
    "sg:city":"Garfield",
    "sg:classifiers":[
        {
            "category":"Building & Trades",
            "subcategory":"Locksmith",
            "type":"Services"
        }
    ],
    "sg:phone":"+1 877 906 7861",
    "sg:postcode":"07026",
    "sg:province":"NJ",
    "sg:tags":[
        "key"
    ],
    "wof:name":"Anytime Anywhere Emergency Locksmith",
    "wof:placetype":"venue"
},
  "geometry": {"coordinates":[-74.102278,40.867675],"type":"Point"}
}