{
  "type": "Feature",
  "properties": {
    "addr:full":"172 Boonton Ave Butler NJ 07405",
    "addr:housenumber":"172",
    "addr:postcode":"07405",
    "addr:street":"Boonton Ave",
    "iso:country":"US",
    "sg:address":"172 Boonton Ave",
    "sg:city":"Butler",
    "sg:classifiers":[
        {
            "category":"Health Services",
            "subcategory":"Chiropractor",
            "type":"Services"
        }
    ],
    "sg:phone":"+1 973 492 8811",
    "sg:postcode":"07405",
    "sg:province":"NJ",
    "wof:name":"Kinnelon Chiropractic Center",
    "wof:placetype":"venue"
},
  "geometry": {"coordinates":[-74.343498,40.993301],"type":"Point"}
}