{
  "type": "Feature",
  "properties": {
    "addr:full":"173 Morris St Morristown NJ 07960",
    "addr:housenumber":"173",
    "addr:postcode":"07960",
    "addr:street":"Morris St",
    "iso:country":"US",
    "sg:address":"173 Morris St",
    "sg:city":"Morristown",
    "sg:classifiers":[
        {
            "category":"Professional",
            "subcategory":"Management & Consulting",
            "type":"Services"
        }
    ],
    "sg:phone":"+1 973 267 3443",
    "sg:postcode":"07960",
    "sg:province":"NJ",
    "sg:tags":[
        "consultant",
        "business"
    ],
    "wof:name":"Frankway Associates Corp",
    "wof:placetype":"venue"
},
  "geometry": {"coordinates":[-74.469081,40.795343],"type":"Point"}
}