{
  "type": "Feature",
  "properties": {
    "addr:full":"1098 Mantua Pike Wenonah NJ 08090",
    "addr:housenumber":"1098",
    "addr:postcode":"08090",
    "addr:street":"Mantua Pike",
    "iso:country":"US",
    "sg:address":"1098 Mantua Pike",
    "sg:city":"Wenonah",
    "sg:classifiers":[
        {
            "category":"Ice Cream",
            "type":"Food & Drink"
        }
    ],
    "sg:menulink":"http://www.allmenus.com/nj/west-deptford/99257-friendlys/menu/",
    "sg:phone":"+1 856 464 0596",
    "sg:postcode":"08090",
    "sg:province":"NJ",
    "sg:tags":[
        "burger",
        "american"
    ],
    "wof:name":"Friendly's",
    "wof:placetype":"venue"
},
  "geometry": {"coordinates":[-75.168773,39.8032],"type":"Point"}
}