{
  "type": "Feature",
  "properties": {
    "addr:full":"525 E Front St Plainfield NJ 07060",
    "addr:housenumber":"525",
    "addr:postcode":"07060",
    "addr:street":"E Front St",
    "iso:country":"US",
    "sg:address":"525 E Front St",
    "sg:city":"Plainfield",
    "sg:classifiers":[
        {
            "category":"Professional",
            "type":"Services"
        }
    ],
    "sg:phone":"+1 908 753 7774",
    "sg:postcode":"07060",
    "sg:province":"NJ",
    "sg:tags":[
        "establishment"
    ],
    "wof:name":"Prebytery Of Elizabeth Rsrc",
    "wof:placetype":"venue"
},
  "geometry": {"coordinates":[-74.417136,40.625546],"type":"Point"}
}