{
  "type": "Feature",
  "properties": {
    "addr:full":"513 Stetson St Orange NJ 07050",
    "addr:housenumber":"513",
    "addr:postcode":"07050",
    "addr:street":"Stetson St",
    "iso:country":"US",
    "sg:address":"513 Stetson St",
    "sg:city":"Orange",
    "sg:classifiers":[
        {
            "category":"Retail",
            "subcategory":"Auto Repair",
            "type":"Services"
        }
    ],
    "sg:phone":"+1 973 676 2400",
    "sg:postcode":"07050",
    "sg:province":"NJ",
    "sg:tags":[
        "automotive"
    ],
    "wof:name":"Stetson Automotive Machine",
    "wof:placetype":"venue"
},
  "geometry": {"coordinates":[-74.24396,40.767715],"type":"Point"}
}