{
  "type": "Feature",
  "properties": {
    "iso:country":"US",
    "sg:address":"89 E Broad St",
    "sg:city":"Hopewell",
    "sg:classifiers":[
        {
            "category":"Building & Trades",
            "subcategory":"Construction",
            "type":"Services"
        }
    ],
    "sg:phone":"+1 609 466 5470",
    "sg:postcode":"08525",
    "sg:province":"NJ",
    "sg:tags":[
        "residential"
    ],
    "wof:name":"Dkm Residential Properties",
    "wof:placetype":"venue"
},
  "geometry": {"coordinates":[-74.755126,40.390835],"type":"Point"}
}