{
  "type": "Feature",
  "properties": {
    "iso:country":"US",
    "sg:address":"136 S Orange Ave",
    "sg:city":"South Orange",
    "sg:classifiers":[
        {
            "category":"Organizations",
            "subcategory":"Community Association",
            "type":"Services"
        }
    ],
    "sg:phone":"+1 973 763 4800",
    "sg:postcode":"07079",
    "sg:province":"NJ",
    "sg:tags":[
        "club"
    ],
    "wof:name":"AAA New Jersey Automobile Club",
    "wof:placetype":"venue"
},
  "geometry": {"coordinates":[-74.256308,40.745375],"type":"Point"}
}