{
  "type": "Feature",
  "properties": {
    "addr:full":"272 US Hwy 22 Springfield NJ 07081",
    "addr:housenumber":"272",
    "addr:postcode":"07081",
    "addr:street":"Us Hwy 22",
    "iso:country":"US",
    "sg:address":"272 US Hwy 22",
    "sg:city":"Springfield",
    "sg:classifiers":[
        {
            "category":"Restaurant",
            "type":"Food & Drink"
        }
    ],
    "sg:phone":"+1   ",
    "sg:postcode":"07081",
    "sg:province":"NJ",
    "sg:tags":[
        "drinking",
        "eating"
    ],
    "wof:name":"Bennigans",
    "wof:placetype":"venue"
},
  "geometry": {"coordinates":[-74.32821199999999,40.685014],"type":"Point"}
}