{
  "type": "Feature",
  "properties": {
    "iso:country":"US",
    "sg:address":"135 Summer St",
    "sg:city":"Passaic",
    "sg:classifiers":[
        {
            "category":"Organizations",
            "subcategory":"Professional Association",
            "type":"Services"
        }
    ],
    "sg:phone":"+1 973 473 0364",
    "sg:postcode":"07055",
    "sg:province":"NJ",
    "wof:name":"Albert Lawson Memorial Post",
    "wof:placetype":"venue"
},
  "geometry": {"coordinates":[-74.13416599999999,40.86875],"type":"Point"}
}