{
  "type": "Feature",
  "properties": {
    "addr:full":"137 George St South Amboy NJ 08879",
    "addr:housenumber":"137",
    "addr:postcode":"08879",
    "addr:street":"George St",
    "iso:country":"US",
    "sg:address":"137 George St",
    "sg:city":"South Amboy",
    "sg:classifiers":[
        {
            "category":"Organizations",
            "subcategory":"Community Association",
            "type":"Services"
        }
    ],
    "sg:phone":"+1 732 721 2661",
    "sg:postcode":"08879",
    "sg:province":"NJ",
    "wof:name":"First Catholic Slovak Union",
    "wof:placetype":"venue"
},
  "geometry": {"coordinates":[-74.27665500000001,40.482228],"type":"Point"}
}