{
  "type": "Feature",
  "properties": {
    "addr:full":"502 Seashore Rd Cape May NJ 08204",
    "addr:housenumber":"502",
    "addr:postcode":"08204",
    "addr:street":"Seashore Rd",
    "iso:country":"US",
    "sg:address":"502 Seashore Rd",
    "sg:city":"Cape May",
    "sg:classifiers":[
        {
            "category":"Retail",
            "subcategory":"Auto Repair",
            "type":"Services"
        }
    ],
    "sg:phone":"+1 609 884 3997",
    "sg:postcode":"08204",
    "sg:province":"NJ",
    "wof:name":"Trimble's Auto Tune Up",
    "wof:placetype":"venue"
},
  "geometry": {"coordinates":[-74.901901,38.990002],"type":"Point"}
}