{
  "type": "Feature",
  "properties": {
    "iso:country":"US",
    "sg:address":"123 Egg Harbor Rd",
    "sg:city":"Sewell",
    "sg:classifiers":[
        {
            "category":"Shopping",
            "subcategory":"Computers & Home Electronics",
            "type":"Retail Goods"
        },
        {
            "category":"Wholesale",
            "subcategory":"Computers",
            "type":"Manufacturing & Wholesale Goods"
        }
    ],
    "sg:phone":"+1 856 401 0550",
    "sg:postcode":"08080",
    "sg:province":"NJ",
    "sg:tags":[
        "hardware",
        "equipment",
        "supply"
    ],
    "wof:name":"T V One Productions",
    "wof:placetype":"venue"
},
  "geometry": {"coordinates":[-75.099503,39.78156],"type":"Point"}
}