{
  "type": "Feature",
  "properties": {
    "addr:full":"230 High St E Glassboro NJ 08028",
    "addr:housenumber":"230",
    "addr:postcode":"08028",
    "addr:street":"High St E",
    "iso:country":"US",
    "sg:address":"230 High St E",
    "sg:city":"Glassboro",
    "sg:classifiers":[
        {
            "category":"Professional",
            "subcategory":"Advertising",
            "type":"Services"
        }
    ],
    "sg:phone":"+1 856 881 4300",
    "sg:postcode":"08028",
    "sg:province":"NJ",
    "sg:tags":[
        "outdoor",
        "spec",
        "mfg"
    ],
    "wof:name":"Astro Sign Co",
    "wof:placetype":"venue"
},
  "geometry": {"coordinates":[-75.10373800000001,39.701305],"type":"Point"}
}