{
  "type": "Feature",
  "properties": {
    "addr:full":"3909 Marlton Pike Pennsauken NJ 08110",
    "addr:housenumber":"3909",
    "addr:postcode":"08110",
    "addr:street":"Marlton Pike",
    "iso:country":"US",
    "sg:address":"3909 Marlton Pike",
    "sg:city":"Pennsauken",
    "sg:classifiers":[
        {
            "category":"Restaurant",
            "type":"Food & Drink"
        }
    ],
    "sg:menulink":"http://www.allmenus.com/nj/pennsauken/15814-francello-pizzeria/menu/",
    "sg:phone":"+1 856 665 7045",
    "sg:postcode":"08110",
    "sg:province":"NJ",
    "sg:tags":[
        "italian"
    ],
    "wof:name":"Francello Pizzeria",
    "wof:placetype":"venue"
},
  "geometry": {"coordinates":[-75.077388,39.938028],"type":"Point"}
}