{
  "type": "Feature",
  "properties": {
    "addr:full":"140 Westwood Blvd Westwood NJ 07675",
    "addr:housenumber":"140",
    "addr:postcode":"07675",
    "addr:street":"Westwood Blvd",
    "iso:country":"US",
    "sg:address":"140 Westwood Blvd",
    "sg:city":"Westwood",
    "sg:classifiers":[
        {
            "category":"Retail",
            "subcategory":"Auto Repair",
            "type":"Services"
        }
    ],
    "sg:phone":"+1 201 343 7744",
    "sg:postcode":"07675",
    "sg:province":"NJ",
    "sg:tags":[
        "repairing",
        "automobile"
    ],
    "wof:name":"Citizen Automotive & Towing",
    "wof:placetype":"venue"
},
  "geometry": {"coordinates":[-74.012261,40.9862],"type":"Point"}
}