{
  "type": "Feature",
  "properties": {
    "iso:country":"US",
    "sg:address":"509 Co Rd 523",
    "sg:city":"Whitehouse Sta",
    "sg:classifiers":[
        {
            "category":"Government",
            "subcategory":"Office",
            "type":"Public Place"
        }
    ],
    "sg:phone":"+1 908 534 6786",
    "sg:postcode":"08889",
    "sg:province":"NJ",
    "sg:tags":[
        "village"
    ],
    "wof:name":"Readington Twp Offices",
    "wof:placetype":"venue"
},
  "geometry": {"coordinates":[-74.779715,40.602418],"type":"Point"}
}