{
  "type": "Feature",
  "properties": {
    "addr:full":"62 Toronto Dr Brick NJ 08723",
    "addr:housenumber":"62",
    "addr:postcode":"08723",
    "addr:street":"Toronto Dr",
    "iso:country":"US",
    "sg:address":"62 Toronto Dr",
    "sg:city":"Brick",
    "sg:classifiers":[
        {
            "category":"Professional",
            "subcategory":"Management & Consulting",
            "type":"Services"
        }
    ],
    "sg:phone":"+1   ",
    "sg:postcode":"08723",
    "sg:province":"NJ",
    "sg:tags":[
        "business"
    ],
    "wof:name":"Ckj Consulting LLC",
    "wof:placetype":"venue"
},
  "geometry": {"coordinates":[-74.086681,40.014255],"type":"Point"}
}