{
  "type": "Feature",
  "properties": {
    "addr:full":"56 Collins Ave Closter NJ 07624",
    "addr:housenumber":"56",
    "addr:postcode":"07624",
    "addr:street":"Collins Ave",
    "iso:country":"US",
    "sg:address":"56 Collins Ave",
    "sg:city":"Closter",
    "sg:classifiers":[
        {
            "category":"Professional",
            "type":"Services"
        }
    ],
    "sg:phone":"+1 201 750 4986",
    "sg:postcode":"07624",
    "sg:province":"NJ",
    "sg:tags":[
        "establishment"
    ],
    "wof:name":"R&T International",
    "wof:placetype":"venue"
},
  "geometry": {"coordinates":[-73.944653,40.97224],"type":"Point"}
}