{
  "type": "Feature",
  "properties": {
    "iso:country":"US",
    "sg:address":"435 59th St Fl 1",
    "sg:city":"West New York",
    "sg:classifiers":[
        {
            "category":"Health Services",
            "subcategory":"Doctor",
            "type":"Services"
        }
    ],
    "sg:phone":"+1 201 295 1456",
    "sg:postcode":"07093",
    "sg:province":"NJ",
    "wof:name":"Gibilisco Raffaele MD",
    "wof:placetype":"venue"
},
  "geometry": {"coordinates":[-74.0168,40.787998],"type":"Point"}
}