{
  "type": "Feature",
  "properties": {
    "iso:country":"US",
    "sg:address":"417 W Broad St",
    "sg:city":"Westfield",
    "sg:classifiers":[
        {
            "category":"Health Services",
            "subcategory":"Doctor",
            "type":"Services"
        }
    ],
    "sg:phone":"+1   ",
    "sg:postcode":"07090",
    "sg:province":"NJ",
    "sg:tags":[
        "medical"
    ],
    "wof:name":"Baez Juan MD",
    "wof:placetype":"venue"
},
  "geometry": {"coordinates":[-74.353874,40.646114],"type":"Point"}
}