{
  "type": "Feature",
  "properties": {
    "iso:country":"US",
    "sg:address":"181 Wert Ave",
    "sg:city":"Trenton",
    "sg:classifiers":[
        {
            "category":"Professional",
            "type":"Services"
        }
    ],
    "sg:phone":"+1 609 888 1059",
    "sg:postcode":"08610",
    "sg:province":"NJ",
    "sg:tags":[
        "establishment"
    ],
    "wof:name":"Allies Inc",
    "wof:placetype":"venue"
},
  "geometry": {"coordinates":[-74.71710299999999,40.209019],"type":"Point"}
}