{
  "type": "Feature",
  "properties": {
    "addr:full":"110 Valley Station Rd Asbury NJ 08802",
    "addr:housenumber":"110",
    "addr:postcode":"08802",
    "addr:street":"Valley Station Rd",
    "iso:country":"US",
    "sg:address":"110 Valley Station Rd",
    "sg:city":"Asbury",
    "sg:classifiers":[
        {
            "category":"Professional",
            "subcategory":"Accounting & Tax Preparation",
            "type":"Services"
        }
    ],
    "sg:phone":"+1 908 479 6070",
    "sg:postcode":"08802",
    "sg:province":"NJ",
    "sg:tags":[
        "accountant"
    ],
    "wof:name":"Weiner Associates",
    "wof:placetype":"venue"
},
  "geometry": {"coordinates":[-75.03743900000001,40.677764],"type":"Point"}
}