{
  "type": "Feature",
  "properties": {
    "iso:country":"US",
    "sg:address":"20 Wall St",
    "sg:city":"Rockaway",
    "sg:classifiers":[
        {
            "category":"Shopping",
            "subcategory":"Used Merchandise",
            "type":"Retail Goods"
        }
    ],
    "sg:phone":"+1   ",
    "sg:postcode":"07866",
    "sg:province":"NJ",
    "wof:name":"Wall Street Home & Garden",
    "wof:placetype":"venue"
},
  "geometry": {"coordinates":[-74.51386100000001,40.901286],"type":"Point"}
}