{
  "type": "Feature",
  "properties": {
    "iso:country":"US",
    "sg:address":"331 Mitchell Ave",
    "sg:city":"Linden",
    "sg:classifiers":[
        {
            "category":"Organizations",
            "subcategory":"Religious Organization",
            "type":"Services"
        }
    ],
    "sg:phone":"+1 908 862 2169",
    "sg:postcode":"07036",
    "sg:province":"NJ",
    "sg:tags":[
        "clergy"
    ],
    "wof:name":"O K Kwon",
    "wof:placetype":"venue"
},
  "geometry": {"coordinates":[-74.246275,40.627185],"type":"Point"}
}