{
  "type": "Feature",
  "properties": {
    "addr:full":"2011 Lemoine Ave Fort Lee NJ 07024",
    "addr:housenumber":"2011",
    "addr:postcode":"07024",
    "addr:street":"Lemoine Ave",
    "iso:country":"US",
    "sg:address":"2011 Lemoine Ave",
    "sg:city":"Fort Lee",
    "sg:classifiers":[
        {
            "category":"Real Estate",
            "subcategory":"Real Estate Agent",
            "type":"Services"
        }
    ],
    "sg:phone":"+1 201 363 9000",
    "sg:postcode":"07024",
    "sg:province":"NJ",
    "sg:tags":[
        "agency",
        "rental"
    ],
    "wof:name":"E Z Rent A Phone Inc",
    "wof:placetype":"venue"
},
  "geometry": {"coordinates":[-73.969932,40.851674],"type":"Point"}
}