{
  "type": "Feature",
  "properties": {
    "iso:country":"US",
    "sg:address":"1613 Union Ave",
    "sg:city":"Union",
    "sg:classifiers":[
        {
            "category":"Professional",
            "type":"Services"
        }
    ],
    "sg:phone":"+1 908 687 3790",
    "sg:postcode":"07083",
    "sg:province":"NJ",
    "sg:tags":[
        "establishment"
    ],
    "wof:name":"Joint Meeting",
    "wof:placetype":"venue"
},
  "geometry": {"coordinates":[-74.24978400000001,40.705917],"type":"Point"}
}