{
  "type": "Feature",
  "properties": {
    "addr:full":"1130 Lincoln Ave Fanwood NJ 07076",
    "addr:housenumber":"1130",
    "addr:postcode":"07076",
    "addr:street":"Lincoln Ave",
    "iso:country":"US",
    "sg:address":"1130 Lincoln Ave",
    "sg:city":"Fanwood",
    "sg:classifiers":[
        {
            "category":"Organizations",
            "subcategory":"Religious Organization",
            "type":"Services"
        }
    ],
    "sg:phone":"+1   ",
    "sg:postcode":"07076",
    "sg:province":"NJ",
    "wof:name":"Emanuel Baptist Church",
    "wof:placetype":"venue"
},
  "geometry": {"coordinates":[-74.374004,40.637964],"type":"Point"}
}