{
  "type": "Feature",
  "properties": {
    "addr:full":"683 Jackson Rd Mullica Hill NJ 08062",
    "addr:housenumber":"683",
    "addr:postcode":"08062",
    "addr:street":"Jackson Rd",
    "iso:country":"US",
    "sg:address":"683 Jackson Rd",
    "sg:city":"Mullica Hill",
    "sg:classifiers":[
        {
            "category":"Building & Trades",
            "subcategory":"Construction",
            "type":"Services"
        }
    ],
    "sg:phone":"+1 856 478 4255",
    "sg:postcode":"08062",
    "sg:province":"NJ",
    "sg:tags":[
        "excavation",
        "contractor"
    ],
    "wof:name":"Azzante Excavating",
    "wof:placetype":"venue"
},
  "geometry": {"coordinates":[-75.18489599999999,39.750354],"type":"Point"}
}