{
  "type": "Feature",
  "properties": {
    "iso:country":"US",
    "sg:address":"2117 State Rte 70",
    "sg:city":"Cherry Hill",
    "sg:classifiers":[
        {
            "category":"Restaurant",
            "type":"Food & Drink"
        }
    ],
    "sg:phone":"+1   ",
    "sg:postcode":"08002",
    "sg:province":"NJ",
    "sg:tags":[
        "eating"
    ],
    "wof:name":"Siris Thai French Cuisine",
    "wof:placetype":"venue"
},
  "geometry": {"coordinates":[-75.036868,39.920293],"type":"Point"}
}