{
  "type": "Feature",
  "properties": {
    "addr:full":"3 Doering Way Cranford NJ 07016",
    "addr:housenumber":"3",
    "addr:postcode":"07016",
    "addr:street":"Doering Way",
    "iso:country":"US",
    "sg:address":"3 Doering Way",
    "sg:city":"Cranford",
    "sg:classifiers":[
        {
            "category":"Building & Trades",
            "subcategory":"Construction",
            "type":"Services"
        }
    ],
    "sg:phone":"+1 908 497 9618",
    "sg:postcode":"07016",
    "sg:province":"NJ",
    "sg:tags":[
        "contractor"
    ],
    "wof:name":"Spackle Magician",
    "wof:placetype":"venue"
},
  "geometry": {"coordinates":[-74.31310499999999,40.665303],"type":"Point"}
}