{
  "type": "Feature",
  "properties": {
    "iso:country":"US",
    "sg:address":"175 State Hwy 45",
    "sg:city":"Salem",
    "sg:classifiers":[
        {
            "category":"Government",
            "subcategory":"Fire Station",
            "type":"Public Place"
        }
    ],
    "sg:phone":"+1 856 935 1313",
    "sg:postcode":"08079",
    "sg:province":"NJ",
    "sg:tags":[
        "department"
    ],
    "wof:name":"Manningtown Township Fire Co",
    "wof:placetype":"venue"
},
  "geometry": {"coordinates":[-75.454122,39.587744],"type":"Point"}
}