{
  "type": "Feature",
  "properties": {
    "addr:full":"14 Madison St Newark NJ 07105",
    "addr:housenumber":"14",
    "addr:postcode":"07105",
    "addr:street":"Madison St",
    "iso:country":"US",
    "sg:address":"14 Madison St",
    "sg:city":"Newark",
    "sg:classifiers":[
        {
            "category":"Building & Trades",
            "subcategory":"Construction",
            "type":"Services"
        }
    ],
    "sg:phone":"+1 973 578 2622",
    "sg:postcode":"07105",
    "sg:province":"NJ",
    "sg:tags":[
        "house"
    ],
    "wof:name":"J & J Carpentry and Gen Cnstr",
    "wof:placetype":"venue"
},
  "geometry": {"coordinates":[-74.158509,40.731723],"type":"Point"}
}