{
  "type": "Feature",
  "properties": {
    "iso:country":"US",
    "sg:address":"1157 Barley Sheaf Rd",
    "sg:city":"Flemington",
    "sg:classifiers":[
        {
            "category":"Shopping",
            "subcategory":"Clothing, Apparel, & Fashions",
            "type":"Retail Goods"
        }
    ],
    "sg:phone":"+1   ",
    "sg:postcode":"08822",
    "sg:province":"NJ",
    "sg:tags":[
        "sporting"
    ],
    "wof:name":"Montys Sport About",
    "wof:placetype":"venue"
},
  "geometry": {"coordinates":[-74.797032,40.555478],"type":"Point"}
}