{
  "type": "Feature",
  "properties": {
    "iso:country":"US",
    "sg:address":"400 State Rte 73",
    "sg:city":"Marlton",
    "sg:classifiers":[
        {
            "category":"Education",
            "subcategory":"School",
            "type":"Public Place"
        }
    ],
    "sg:phone":"+1 856 988 0675",
    "sg:postcode":"08053",
    "sg:province":"NJ",
    "wof:name":"Evans School",
    "wof:placetype":"venue"
},
  "geometry": {"coordinates":[-74.933976,39.901689],"type":"Point"}
}