{
  "type": "Feature",
  "properties": {
    "addr:full":"917 N Wood Ave Linden NJ 07036",
    "addr:housenumber":"917",
    "addr:postcode":"07036",
    "addr:street":"N Wood Ave",
    "iso:country":"US",
    "sg:address":"917 N Wood Ave",
    "sg:city":"Linden",
    "sg:classifiers":[
        {
            "category":"Health Services",
            "subcategory":"Doctor",
            "type":"Services"
        }
    ],
    "sg:phone":"+1 908 486 5732",
    "sg:postcode":"07036",
    "sg:province":"NJ",
    "sg:tags":[
        "medical"
    ],
    "wof:name":"Thomas Bejgrowicz MD",
    "wof:placetype":"venue"
},
  "geometry": {"coordinates":[-74.26415799999999,40.636998],"type":"Point"}
}