{
  "type": "Feature",
  "properties": {
    "iso:country":"US",
    "sg:address":"289 S Main St",
    "sg:city":"Manville",
    "sg:classifiers":[
        {
            "category":"Food & Beverages",
            "subcategory":"Groceries & Convenience Stores",
            "type":"Retail Goods"
        }
    ],
    "sg:phone":"+1   ",
    "sg:postcode":"08835",
    "sg:province":"NJ",
    "wof:name":"Stop & Go Food Store",
    "wof:placetype":"venue"
},
  "geometry": {"coordinates":[-74.58873199999999,40.538589],"type":"Point"}
}