{
  "type": "Feature",
  "properties": {
    "addr:full":"25 US Hwy 46 Columbia NJ 07832",
    "addr:housenumber":"25",
    "addr:postcode":"07832",
    "addr:street":"Us Hwy 46",
    "iso:country":"US",
    "sg:address":"25 US Hwy 46",
    "sg:city":"Columbia",
    "sg:classifiers":[
        {
            "category":"Autos & Motor Vehicles",
            "subcategory":"Fuel & Gas Station",
            "type":"Retail Goods"
        }
    ],
    "sg:phone":"+1   ",
    "sg:postcode":"07832",
    "sg:province":"NJ",
    "sg:tags":[
        "station",
        "gasoline"
    ],
    "wof:name":"Texaco",
    "wof:placetype":"venue"
},
  "geometry": {"coordinates":[-75.077563,40.913278],"type":"Point"}
}