{
  "type": "Feature",
  "properties": {
    "iso:country":"US",
    "sg:address":"201 Cedar Ln",
    "sg:city":"Teaneck",
    "sg:classifiers":[
        {
            "category":"Building & Trades",
            "subcategory":"Locksmith",
            "type":"Services"
        }
    ],
    "sg:phone":"+1 201 379 3327",
    "sg:postcode":"07666",
    "sg:province":"NJ",
    "sg:tags":[
        "key"
    ],
    "wof:name":"# # 0 0 24 Hour Lock & Locksmith",
    "wof:placetype":"venue"
},
  "geometry": {"coordinates":[-74.01378,40.886474],"type":"Point"}
}