{
  "type": "Feature",
  "properties": {
    "addr:full":"19 Percypenny Ln Parsippany NJ 07054",
    "addr:housenumber":"19",
    "addr:postcode":"07054",
    "addr:street":"Percypenny Ln",
    "iso:country":"US",
    "sg:address":"19 Percypenny Ln",
    "sg:city":"Parsippany",
    "sg:classifiers":[
        {
            "category":"Professional",
            "subcategory":"Computer Services",
            "type":"Services"
        }
    ],
    "sg:phone":"+1 201 400 2286",
    "sg:postcode":"07054",
    "sg:province":"NJ",
    "sg:tags":[
        "consultant",
        "designer"
    ],
    "wof:name":"Alpha Business Solutions Inc",
    "wof:placetype":"venue"
},
  "geometry": {"coordinates":[-74.35863500000001,40.863146],"type":"Point"}
}