{
  "type": "Feature",
  "properties": {
    "iso:country":"US",
    "sg:address":"5100 State Rte 42",
    "sg:city":"Turnersville",
    "sg:classifiers":[
        {
            "category":"Personal",
            "subcategory":"Beauty Salon",
            "type":"Services"
        }
    ],
    "sg:phone":"+1 856 228 4470",
    "sg:postcode":"08012",
    "sg:province":"NJ",
    "sg:tags":[
        "manicuring"
    ],
    "wof:name":"Top Nails Salon",
    "wof:placetype":"venue"
},
  "geometry": {"coordinates":[-75.045796,39.751053],"type":"Point"}
}