{
  "type": "Feature",
  "properties": {
    "addr:full":"47 Symmes Rd Englishtown NJ 07726",
    "addr:housenumber":"47",
    "addr:postcode":"07726",
    "addr:street":"Symmes Rd",
    "iso:country":"US",
    "sg:address":"47 Symmes Rd",
    "sg:city":"Englishtown",
    "sg:classifiers":[
        {
            "category":"Communications",
            "type":"Services"
        }
    ],
    "sg:phone":"+1 732 431 5512",
    "sg:postcode":"07726",
    "sg:province":"NJ",
    "sg:tags":[
        "communication"
    ],
    "wof:name":"Small World Communication",
    "wof:placetype":"venue"
},
  "geometry": {"coordinates":[-74.32016299999999,40.288751],"type":"Point"}
}