{
  "type": "Feature",
  "properties": {
    "iso:country":"US",
    "sg:address":"288 Herbert Ave",
    "sg:city":"Closter",
    "sg:classifiers":[
        {
            "category":"Building & Trades",
            "subcategory":"Plumbing",
            "type":"Services"
        }
    ],
    "sg:phone":"+1 201 768 2523",
    "sg:postcode":"07624",
    "sg:province":"NJ",
    "sg:tags":[
        "contractor"
    ],
    "wof:name":"B & M Plumbing & Heating",
    "wof:placetype":"venue"
},
  "geometry": {"coordinates":[-73.96099700000001,40.97289],"type":"Point"}
}