{
  "type": "Feature",
  "properties": {
    "iso:country":"US",
    "sg:address":"86 Lackawanna Ave",
    "sg:city":"Little Falls",
    "sg:classifiers":[
        {
            "category":"Retail",
            "subcategory":"Repair Shop",
            "type":"Services"
        }
    ],
    "sg:phone":"+1 973 278 5570",
    "sg:postcode":"07424",
    "sg:province":"NJ",
    "wof:name":"Cestaro Furniture Finishing",
    "wof:placetype":"venue"
},
  "geometry": {"coordinates":[-74.213843,40.889525],"type":"Point"}
}