{
  "type": "Feature",
  "properties": {
    "addr:full":"131 W Main St Moorestown NJ 08057",
    "addr:housenumber":"131",
    "addr:postcode":"08057",
    "addr:street":"W Main St",
    "iso:country":"US",
    "sg:address":"131 W Main St",
    "sg:city":"Moorestown",
    "sg:classifiers":[
        {
            "category":"Wholesale",
            "subcategory":"Groceries",
            "type":"Manufacturing & Wholesale Goods"
        }
    ],
    "sg:phone":"+1 856 642 1135",
    "sg:postcode":"08057",
    "sg:province":"NJ",
    "sg:tags":[
        "pretzel",
        "restaurant"
    ],
    "wof:name":"Philly Pretzel Factory",
    "wof:placetype":"venue"
},
  "geometry": {"coordinates":[-74.948875,39.962929],"type":"Point"}
}