{
  "type": "Feature",
  "properties": {
    "addr:full":"10 Aron Ct Asbury Park NJ 07712",
    "addr:housenumber":"10",
    "addr:postcode":"07712",
    "addr:street":"Aron Ct Asbury",
    "iso:country":"US",
    "sg:address":"10 Aron Ct",
    "sg:city":"Asbury Park",
    "sg:classifiers":[
        {
            "category":"Professional",
            "type":"Services"
        }
    ],
    "sg:phone":"+1   ",
    "sg:postcode":"07712",
    "sg:province":"NJ",
    "wof:name":"Celjo LLC Joan & Maria Bezerra",
    "wof:placetype":"venue"
},
  "geometry": {"coordinates":[-74.065485,40.235443],"type":"Point"}
}