{
  "type": "Feature",
  "properties": {
    "iso:country":"US",
    "sg:address":"114 Mill Creek Dr",
    "sg:city":"Secaucus",
    "sg:classifiers":[
        {
            "category":"Wholesale",
            "subcategory":"Drugs",
            "type":"Manufacturing & Wholesale Goods"
        }
    ],
    "sg:phone":"+1 201 392 1060",
    "sg:postcode":"07094",
    "sg:province":"NJ",
    "sg:tags":[
        "perfume"
    ],
    "wof:name":"Perfume Romance",
    "wof:placetype":"venue"
},
  "geometry": {"coordinates":[-74.05149400000001,40.790562],"type":"Point"}
}