{
  "type": "Feature",
  "properties": {
    "addr:full":"330 South St Morristown NJ 07960",
    "addr:housenumber":"330",
    "addr:postcode":"07960",
    "addr:street":"South St",
    "iso:country":"US",
    "sg:address":"330 South St",
    "sg:city":"Morristown",
    "sg:classifiers":[
        {
            "category":"Professional",
            "subcategory":"Management & Consulting",
            "type":"Services"
        }
    ],
    "sg:phone":"+1 973 540 0968",
    "sg:postcode":"07960",
    "sg:province":"NJ",
    "sg:tags":[
        "consultant",
        "business"
    ],
    "wof:name":"Van Beuren Management Inc",
    "wof:placetype":"venue"
},
  "geometry": {"coordinates":[-74.468293,40.783972],"type":"Point"}
}