{
  "type": "Feature",
  "properties": {
    "iso:country":"US",
    "sg:address":"220 N 27th St",
    "sg:city":"Camden",
    "sg:classifiers":[
        {
            "category":"Organizations",
            "subcategory":"Religious Organization",
            "type":"Services"
        }
    ],
    "sg:phone":"+1 856 541 9689",
    "sg:postcode":"08105",
    "sg:province":"NJ",
    "wof:name":"St John's Born Again Church of Jesus Christ",
    "wof:placetype":"venue"
},
  "geometry": {"coordinates":[-75.08820299999999,39.948601],"type":"Point"}
}