{
  "type": "Feature",
  "properties": {
    "iso:country":"US",
    "sg:address":"56 Van Riper Ave",
    "sg:city":"Elmwood Park",
    "sg:classifiers":[
        {
            "category":"Building & Trades",
            "subcategory":"Construction",
            "type":"Services"
        }
    ],
    "sg:phone":"+1 201 791 9694",
    "sg:postcode":"07407",
    "sg:province":"NJ",
    "sg:tags":[
        "general",
        "contractor"
    ],
    "wof:name":"Marini Builders & Remodelers",
    "wof:placetype":"venue"
},
  "geometry": {"coordinates":[-74.12002200000001,40.901969],"type":"Point"}
}