{
  "type": "Feature",
  "properties": {
    "addr:full":"20 Fredon Marksboro Rd Newton NJ 07860",
    "addr:housenumber":"20",
    "addr:postcode":"07860",
    "addr:street":"Fredon Marksboro Rd",
    "iso:country":"US",
    "sg:address":"20 Fredon Marksboro Rd",
    "sg:city":"Newton",
    "sg:classifiers":[
        {
            "category":"Food & Beverages",
            "subcategory":"Supermarket",
            "type":"Retail Goods"
        }
    ],
    "sg:phone":"+1 973 579 4914",
    "sg:postcode":"07860",
    "sg:province":"NJ",
    "sg:tags":[
        "super",
        "store"
    ],
    "wof:name":"Exotic Foods, Inc.",
    "wof:placetype":"venue"
},
  "geometry": {"coordinates":[-74.831619,41.036652],"type":"Point"}
}