{
  "type": "Feature",
  "properties": {
    "iso:country":"US",
    "sg:address":"443 Grand Ave",
    "sg:city":"Trenton",
    "sg:classifiers":[
        {
            "category":"Autos & Motor Vehicles",
            "subcategory":"Auto Supplies",
            "type":"Retail Goods"
        }
    ],
    "sg:phone":"+1 609 883 0220",
    "sg:postcode":"08610",
    "sg:province":"NJ",
    "sg:tags":[
        "automobile",
        "parts"
    ],
    "wof:name":"Motor Parts Of W Trenton",
    "wof:placetype":"venue"
},
  "geometry": {"coordinates":[-74.725357,40.200327],"type":"Point"}
}