{
  "type": "Feature",
  "properties": {
    "addr:full":"315 Elmora Ave Elizabeth NJ 07208",
    "addr:housenumber":"315",
    "addr:postcode":"07208",
    "addr:street":"Elmora Ave",
    "iso:country":"US",
    "sg:address":"315 Elmora Ave",
    "sg:city":"Elizabeth",
    "sg:classifiers":[
        {
            "category":"Health Services",
            "subcategory":"Medical Lab",
            "type":"Services"
        }
    ],
    "sg:phone":"+1 908 354 3322",
    "sg:postcode":"07208",
    "sg:province":"NJ",
    "sg:tags":[
        "laboratory"
    ],
    "wof:name":"Laboratory Corporation America",
    "wof:placetype":"venue"
},
  "geometry": {"coordinates":[-74.23424,40.665992],"type":"Point"}
}