{
  "type": "Feature",
  "properties": {
    "iso:country":"US",
    "sg:address":"300 Greenbrook Rd",
    "sg:city":"Plainfield",
    "sg:classifiers":[
        {
            "category":"Building & Trades",
            "subcategory":"Construction",
            "type":"Services"
        }
    ],
    "sg:phone":"+1 908 754 6042",
    "sg:postcode":"07060",
    "sg:province":"NJ",
    "sg:tags":[
        "house"
    ],
    "wof:name":"J BS Home Imprv & Intr Design",
    "wof:placetype":"venue"
},
  "geometry": {"coordinates":[-74.446562,40.617262],"type":"Point"}
}