{
  "type": "Feature",
  "properties": {
    "iso:country":"US",
    "sg:address":"205 Smith St",
    "sg:city":"Perth Amboy",
    "sg:classifiers":[
        {
            "category":"Shopping",
            "type":"Retail Goods"
        }
    ],
    "sg:phone":"+1   ",
    "sg:postcode":"08861",
    "sg:province":"NJ",
    "sg:tags":[
        "merchandise"
    ],
    "wof:name":"No Other Name Book Store",
    "wof:placetype":"venue"
},
  "geometry": {"coordinates":[-74.27142499999999,40.509419],"type":"Point"}
}