{
  "type": "Feature",
  "properties": {
    "addr:full":"38 Ave C Newark NJ 07114",
    "addr:postcode":"07114",
    "addr:street":"38 Ave C",
    "iso:country":"US",
    "sg:address":"38 Ave C",
    "sg:city":"Newark",
    "sg:classifiers":[
        {
            "category":"Building & Trades",
            "subcategory":"Construction",
            "type":"Services"
        }
    ],
    "sg:phone":"+1 973 297 4333",
    "sg:postcode":"07114",
    "sg:province":"NJ",
    "sg:tags":[
        "masonry",
        "contractor"
    ],
    "wof:name":"Bastos Builders Corp",
    "wof:placetype":"venue"
},
  "geometry": {"coordinates":[-74.172771,40.71863],"type":"Point"}
}