{
  "type": "Feature",
  "properties": {
    "iso:country":"US",
    "sg:address":"248 Green St",
    "sg:city":"Woodbridge",
    "sg:classifiers":[
        {
            "category":"Personal",
            "type":"Services"
        }
    ],
    "sg:phone":"+1 732 414 7404",
    "sg:postcode":"07095",
    "sg:province":"NJ",
    "sg:tags":[
        "mover"
    ],
    "sg:website":"www.woodbridge-nj-movers.com",
    "wof:name":"Woodbridge NJ Movers",
    "wof:placetype":"venue"
},
  "geometry": {"coordinates":[-74.288774,40.557033],"type":"Point"}
}