{
  "type": "Feature",
  "properties": {
    "addr:full":"147 Washington Ave Little Ferry NJ 07643",
    "addr:housenumber":"147",
    "addr:postcode":"07643",
    "addr:street":"Washington Ave",
    "iso:country":"US",
    "sg:address":"147 Washington Ave",
    "sg:city":"Little Ferry",
    "sg:classifiers":[
        {
            "category":"Restaurant",
            "type":"Food & Drink"
        }
    ],
    "sg:phone":"+1 201 296 0400",
    "sg:postcode":"07643",
    "sg:province":"NJ",
    "sg:tags":[
        "deli",
        "delicatessen"
    ],
    "wof:name":"Himenez Deli",
    "wof:placetype":"venue"
},
  "geometry": {"coordinates":[-74.038696,40.8466],"type":"Point"}
}