{
  "type": "Feature",
  "properties": {
    "iso:country":"US",
    "sg:address":"210 Sussex St",
    "sg:city":"Hackensack",
    "sg:classifiers":[
        {
            "category":"Building & Trades",
            "subcategory":"Construction",
            "type":"Services"
        }
    ],
    "sg:phone":"+1 201 489 3969",
    "sg:postcode":"07601",
    "sg:province":"NJ",
    "sg:tags":[
        "hanging",
        "contractor"
    ],
    "wof:name":"Maynes Painting & Decorating",
    "wof:placetype":"venue"
},
  "geometry": {"coordinates":[-74.05401500000001,40.88178],"type":"Point"}
}