{
  "type": "Feature",
  "properties": {
    "iso:country":"US",
    "sg:address":"11 Leifried Ln",
    "sg:city":"Little Egg Hbr",
    "sg:classifiers":[
        {
            "category":"Professional",
            "subcategory":"Engineering",
            "type":"Services"
        }
    ],
    "sg:phone":"+1 609 296 8100",
    "sg:postcode":"08087",
    "sg:province":"NJ",
    "sg:tags":[
        "engineer"
    ],
    "wof:name":"Nelke Constantine & Assoc Inc",
    "wof:placetype":"venue"
},
  "geometry": {"coordinates":[-74.345817,39.60039],"type":"Point"}
}