{
  "type": "Feature",
  "properties": {
    "addr:full":"199 Main St Woodbridge NJ 07095",
    "addr:housenumber":"199",
    "addr:postcode":"07095",
    "addr:street":"Main St",
    "iso:country":"US",
    "sg:address":"199 Main St",
    "sg:city":"Woodbridge",
    "sg:classifiers":[
        {
            "category":"Freight",
            "type":"Transportation"
        }
    ],
    "sg:phone":"+1 732 750 9480",
    "sg:postcode":"07095",
    "sg:province":"NJ",
    "sg:tags":[
        "arrangement"
    ],
    "wof:name":"American Cargo Shipping Lines",
    "wof:placetype":"venue"
},
  "geometry": {"coordinates":[-74.28477599999999,40.552735],"type":"Point"}
}