{
  "type": "Feature",
  "properties": {
    "iso:country":"US",
    "sg:address":"1662 Beaver Dam Rd",
    "sg:city":"Pt Pleasant Bch",
    "sg:classifiers":[
        {
            "category":"Shopping",
            "subcategory":"Bicycles & Sporting Goods",
            "type":"Retail Goods"
        }
    ],
    "sg:phone":"+1 732 295 9322",
    "sg:postcode":"08742",
    "sg:province":"NJ",
    "wof:name":"Manasquan River Clothin Co",
    "wof:placetype":"venue"
},
  "geometry": {"coordinates":[-74.072294,40.062466],"type":"Point"}
}