{
  "type": "Feature",
  "properties": {
    "addr:full":"9 E Jimmie Leeds Rd Absecon NJ 08205",
    "addr:housenumber":"9",
    "addr:postcode":"08205",
    "addr:street":"E Jimmie Leeds Rd",
    "iso:country":"US",
    "sg:address":"9 E Jimmie Leeds Rd",
    "sg:city":"Absecon",
    "sg:classifiers":[
        {
            "category":"Health Services",
            "subcategory":"Optometrist",
            "type":"Services"
        }
    ],
    "sg:phone":"+1 609 652 1111",
    "sg:postcode":"08205",
    "sg:province":"NJ",
    "wof:name":"Louis J Fornasier OD",
    "wof:placetype":"venue"
},
  "geometry": {"coordinates":[-74.526202,39.474259],"type":"Point"}
}