{
  "type": "Feature",
  "properties": {
    "addr:full":"51 Jamaica St Edison NJ 08820",
    "addr:housenumber":"51",
    "addr:postcode":"08820",
    "addr:street":"Jamaica St",
    "iso:country":"US",
    "sg:address":"51 Jamaica St",
    "sg:city":"Edison",
    "sg:classifiers":[
        {
            "category":"Professional",
            "subcategory":"Lawyer & Legal Services",
            "type":"Services"
        }
    ],
    "sg:phone":"+1 732 906 5654",
    "sg:postcode":"08820",
    "sg:province":"NJ",
    "wof:name":"Edward M Fink Attorney",
    "wof:placetype":"venue"
},
  "geometry": {"coordinates":[-74.35389499999999,40.561467],"type":"Point"}
}