{
  "type": "Feature",
  "properties": {
    "addr:full":"49 Veronica Ave Somerset NJ 08873",
    "addr:housenumber":"49",
    "addr:postcode":"08873",
    "addr:street":"Veronica Ave",
    "iso:country":"US",
    "sg:address":"49 Veronica Ave",
    "sg:city":"Somerset",
    "sg:classifiers":[
        {
            "category":"Health Services",
            "subcategory":"Doctor",
            "type":"Services"
        }
    ],
    "sg:phone":"+1 732 565 1500",
    "sg:postcode":"08873",
    "sg:province":"NJ",
    "sg:tags":[
        "physician",
        "surgeon"
    ],
    "wof:name":"Somerset Ophthalmology Assoc",
    "wof:placetype":"venue"
},
  "geometry": {"coordinates":[-74.501401,40.480357],"type":"Point"}
}