{
  "type": "Feature",
  "properties": {
    "iso:country":"US",
    "sg:address":"331 Sandford St",
    "sg:city":"New Brunswick",
    "sg:classifiers":[
        {
            "category":"Wholesale",
            "subcategory":"Auto Parts",
            "type":"Manufacturing & Wholesale Goods"
        }
    ],
    "sg:phone":"+1 732 514 9800",
    "sg:postcode":"08901",
    "sg:province":"NJ",
    "wof:name":"A & R Body Auto Sales",
    "wof:placetype":"venue"
},
  "geometry": {"coordinates":[-74.45755699999999,40.488665],"type":"Point"}
}