{
  "type": "Feature",
  "properties": {
    "addr:full":"49 Madisonville Rd Basking Ridge NJ 07920",
    "addr:housenumber":"49",
    "addr:postcode":"07920",
    "addr:street":"Madisonville Rd",
    "iso:country":"US",
    "sg:address":"49 Madisonville Rd",
    "sg:city":"Basking Ridge",
    "sg:classifiers":[
        {
            "category":"Building & Trades",
            "subcategory":"Cleaning & Sanitation",
            "type":"Services"
        }
    ],
    "sg:phone":"+1 908 221 0102",
    "sg:postcode":"07920",
    "sg:province":"NJ",
    "sg:tags":[
        "janitor"
    ],
    "wof:name":"Celtic Maintenance Co",
    "wof:placetype":"venue"
},
  "geometry": {"coordinates":[-74.550325,40.721546],"type":"Point"}
}