{
  "type": "Feature",
  "properties": {
    "iso:country":"US",
    "sg:address":"200 Main Ave",
    "sg:city":"Passaic",
    "sg:classifiers":[
        {
            "category":"Professional",
            "subcategory":"Business Services",
            "type":"Services"
        }
    ],
    "sg:phone":"+1 626 274 4345",
    "sg:postcode":"07055",
    "sg:province":"NJ",
    "wof:name":"Atles Express Badala",
    "wof:placetype":"venue"
},
  "geometry": {"coordinates":[-74.127134,40.846263],"type":"Point"}
}