{
  "type": "Feature",
  "properties": {
    "addr:full":"1924 State Rte 35 Belmar NJ 07719",
    "addr:housenumber":"1924",
    "addr:postcode":"07719",
    "addr:street":"State Rte 35",
    "iso:country":"US",
    "sg:address":"1924 State Rte 35",
    "sg:city":"Belmar",
    "sg:classifiers":[
        {
            "category":"Personal",
            "subcategory":"Beauty Salon",
            "type":"Services"
        }
    ],
    "sg:phone":"+1   ",
    "sg:postcode":"07719",
    "sg:province":"NJ",
    "sg:tags":[
        "shop"
    ],
    "wof:name":"Image Group Salon and Spa",
    "wof:placetype":"venue"
},
  "geometry": {"coordinates":[-74.05219099999999,40.159985],"type":"Point"}
}