{
  "type": "Feature",
  "properties": {
    "addr:full":"392 Hoover Ave Bloomfield NJ 07003",
    "addr:housenumber":"392",
    "addr:postcode":"07003",
    "addr:street":"Hoover Ave",
    "iso:country":"US",
    "sg:address":"392 Hoover Ave",
    "sg:city":"Bloomfield",
    "sg:classifiers":[
        {
            "category":"Real Estate",
            "subcategory":"Real Estate Agent",
            "type":"Services"
        }
    ],
    "sg:phone":"+1 973 429 7675",
    "sg:postcode":"07003",
    "sg:province":"NJ",
    "sg:tags":[
        "condominium"
    ],
    "wof:name":"White Stone Condominiums",
    "wof:placetype":"venue"
},
  "geometry": {"coordinates":[-74.191382,40.809426],"type":"Point"}
}