{
  "type": "Feature",
  "properties": {
    "addr:full":"421 3rd Ave Lyndhurst NJ 07071",
    "addr:housenumber":"421",
    "addr:postcode":"07071",
    "addr:street":"3Rd Ave",
    "iso:country":"US",
    "sg:address":"421 3rd Ave",
    "sg:city":"Lyndhurst",
    "sg:classifiers":[
        {
            "category":"Wholesale",
            "subcategory":"Machinery & Supplies",
            "type":"Manufacturing & Wholesale Goods"
        }
    ],
    "sg:phone":"+1 201 939 0237",
    "sg:postcode":"07071",
    "sg:province":"NJ",
    "sg:tags":[
        "equipment",
        "establishment"
    ],
    "wof:name":"Essex Funeral Supplies",
    "wof:placetype":"venue"
},
  "geometry": {"coordinates":[-74.119581,40.815816],"type":"Point"}
}