{
  "type": "Feature",
  "properties": {
    "iso:country":"US",
    "sg:address":"5 Huntley Way",
    "sg:city":"Bridgewater",
    "sg:classifiers":[
        {
            "category":"Professional",
            "subcategory":"Management & Consulting",
            "type":"Services"
        }
    ],
    "sg:phone":"+1   ",
    "sg:postcode":"08807",
    "sg:province":"NJ",
    "sg:tags":[
        "business"
    ],
    "wof:name":"Forward Curve Consulting",
    "wof:placetype":"venue"
},
  "geometry": {"coordinates":[-74.668851,40.584962],"type":"Point"}
}