{
  "type": "Feature",
  "properties": {
    "addr:full":"302 Broad St Florence NJ 08518",
    "addr:housenumber":"302",
    "addr:postcode":"08518",
    "addr:street":"Broad St",
    "iso:country":"US",
    "sg:address":"302 Broad St",
    "sg:city":"Florence",
    "sg:classifiers":[
        {
            "category":"Food & Beverages",
            "subcategory":"Liquor & Beverages",
            "type":"Retail Goods"
        }
    ],
    "sg:phone":"+1   ",
    "sg:postcode":"08518",
    "sg:province":"NJ",
    "sg:tags":[
        "store"
    ],
    "wof:name":"Red White & Brew",
    "wof:placetype":"venue"
},
  "geometry": {"coordinates":[-74.805324,40.119659],"type":"Point"}
}