{
  "type": "Feature",
  "properties": {
    "addr:full":"700 Arndt Ave Apt A32 Riverside NJ 08075",
    "addr:housenumber":"700",
    "addr:postcode":"08075",
    "addr:street":"Arndt Ave Apt A32",
    "iso:country":"US",
    "sg:address":"700 Arndt Ave Apt A32",
    "sg:city":"Riverside",
    "sg:classifiers":[
        {
            "category":"Real Estate",
            "subcategory":"Real Estate Operator",
            "type":"Services"
        }
    ],
    "sg:phone":"+1 856 764 0252",
    "sg:postcode":"08075",
    "sg:province":"NJ",
    "sg:tags":[
        "apartment"
    ],
    "wof:name":"River Terrace Apartments",
    "wof:placetype":"venue"
},
  "geometry": {"coordinates":[-74.95590199999999,40.029999],"type":"Point"}
}