{
  "type": "Feature",
  "properties": {
    "iso:country":"US",
    "sg:address":"229 Newman Springs Rd",
    "sg:city":"Tinton Falls",
    "sg:classifiers":[
        {
            "category":"Professional",
            "subcategory":"Lawyer & Legal Services",
            "type":"Services"
        }
    ],
    "sg:phone":"+1 732 450 9555",
    "sg:postcode":"07724",
    "sg:province":"NJ",
    "sg:tags":[
        "attorney"
    ],
    "wof:name":"Francis E Wilton Law Office",
    "wof:placetype":"venue"
},
  "geometry": {"coordinates":[-74.085803,40.336431],"type":"Point"}
}