{
  "type": "Feature",
  "properties": {
    "addr:full":"13 Franklin School Way Metuchen NJ 08840",
    "addr:housenumber":"13",
    "addr:postcode":"08840",
    "addr:street":"School Way",
    "iso:country":"US",
    "sg:address":"13 Franklin School Way",
    "sg:city":"Metuchen",
    "sg:classifiers":[
        {
            "category":"Professional",
            "subcategory":"Lawyer & Legal Services",
            "type":"Services"
        }
    ],
    "sg:phone":"+1 732 321 1731",
    "sg:postcode":"08840",
    "sg:province":"NJ",
    "sg:tags":[
        "plan"
    ],
    "wof:name":"Exhibit ALLC",
    "wof:placetype":"venue"
},
  "geometry": {"coordinates":[-74.36618799999999,40.541396],"type":"Point"}
}