{
  "type": "Feature",
  "properties": {
    "iso:country":"US",
    "sg:address":"415 N Main St",
    "sg:city":"Lanoka Harbor",
    "sg:classifiers":[
        {
            "category":"Personal",
            "subcategory":"Beauty Salon",
            "type":"Services"
        }
    ],
    "sg:phone":"+1 609 971 7700",
    "sg:postcode":"08734",
    "sg:province":"NJ",
    "wof:name":"Tres Chic Salon & Day Spa",
    "wof:placetype":"venue"
},
  "geometry": {"coordinates":[-74.180346,39.854763],"type":"Point"}
}