{
  "type": "Feature",
  "properties": {
    "iso:country":"US",
    "sg:address":"1115 US Hwy 1",
    "sg:city":"Edison",
    "sg:classifiers":[
        {
            "category":"Wholesale",
            "subcategory":"Auto Parts",
            "type":"Manufacturing & Wholesale Goods"
        }
    ],
    "sg:phone":"+1 732 494 5655",
    "sg:postcode":"08837",
    "sg:province":"NJ",
    "sg:tags":[
        "used"
    ],
    "wof:name":"Ultimate Auto Accessories",
    "wof:placetype":"venue"
},
  "geometry": {"coordinates":[-74.357826,40.525793],"type":"Point"}
}