{
  "type": "Feature",
  "properties": {
    "iso:country":"US",
    "sg:address":"376 Railroad Ave",
    "sg:city":"Hackensack",
    "sg:classifiers":[
        {
            "category":"Wholesale",
            "subcategory":"Apparel",
            "type":"Manufacturing & Wholesale Goods"
        }
    ],
    "sg:phone":"+1 201 525 0110",
    "sg:postcode":"07601",
    "sg:province":"NJ",
    "sg:tags":[
        "textile",
        "woven"
    ],
    "wof:name":"Alaska Textile Co Inc",
    "wof:placetype":"venue"
},
  "geometry": {"coordinates":[-74.04546499999999,40.891334],"type":"Point"}
}