{
  "type": "Feature",
  "properties": {
    "addr:full":"939 Harding Hwy Buena NJ 08310",
    "addr:housenumber":"939",
    "addr:postcode":"08310",
    "addr:street":"Harding Hwy",
    "iso:country":"US",
    "sg:address":"939 Harding Hwy",
    "sg:city":"Buena",
    "sg:classifiers":[
        {
            "category":"Building & Trades",
            "subcategory":"Plumbing",
            "type":"Services"
        }
    ],
    "sg:phone":"+1 856 697 0700",
    "sg:postcode":"08310",
    "sg:province":"NJ",
    "sg:tags":[
        "plumbing",
        "contractor"
    ],
    "wof:name":"Buena Plumbing Inc",
    "wof:placetype":"venue"
},
  "geometry": {"coordinates":[-74.902402,39.503974],"type":"Point"}
}