{
  "type": "Feature",
  "properties": {
    "iso:country":"US",
    "sg:address":"1230 E Elizabeth Ave",
    "sg:city":"Linden",
    "sg:classifiers":[
        {
            "category":"Retail",
            "subcategory":"Auto Repair",
            "type":"Services"
        }
    ],
    "sg:phone":"+1 908 925 8700",
    "sg:postcode":"07036",
    "sg:province":"NJ",
    "wof:name":"Ivey Technologies Llc",
    "wof:placetype":"venue"
},
  "geometry": {"coordinates":[-74.23957900000001,40.642591],"type":"Point"}
}