{
  "type": "Feature",
  "properties": {
    "iso:country":"US",
    "sg:address":"1433 Oak Tree Rd",
    "sg:city":"Iselin",
    "sg:classifiers":[
        {
            "category":"Professional",
            "subcategory":"Business Services",
            "type":"Services"
        }
    ],
    "sg:phone":"+1   ",
    "sg:postcode":"08830",
    "sg:province":"NJ",
    "wof:name":"Moneydart",
    "wof:placetype":"venue"
},
  "geometry": {"coordinates":[-74.327749,40.573487],"type":"Point"}
}