{
  "type": "Feature",
  "properties": {
    "iso:country":"US",
    "sg:address":"11 Maywood Ct",
    "sg:city":"Caldwell",
    "sg:classifiers":[
        {
            "category":"Professional",
            "subcategory":"Business Services",
            "type":"Services"
        }
    ],
    "sg:phone":"+1   ",
    "sg:postcode":"07006",
    "sg:province":"NJ",
    "sg:tags":[
        "jewelry"
    ],
    "wof:name":"C R S Designs",
    "wof:placetype":"venue"
},
  "geometry": {"coordinates":[-74.26257099999999,40.864784],"type":"Point"}
}