{
  "type": "Feature",
  "properties": {
    "iso:country":"US",
    "sg:address":"6 Osborne Terrace",
    "sg:city":"Pequannock Township",
    "sg:classifiers":[
        {
            "category":"Building & Trades",
            "subcategory":"Electrical",
            "type":"Services"
        }
    ],
    "sg:phone":"+1 201 650 5600",
    "sg:postcode":"07444",
    "sg:province":"NJ",
    "sg:tags":[
        "electrician"
    ],
    "wof:name":"Kristy Electric",
    "wof:placetype":"venue"
},
  "geometry": {"coordinates":[-74.303787,40.972236],"type":"Point"}
}