{
  "type": "Feature",
  "properties": {
    "iso:country":"US",
    "sg:address":"1911 Bergenline Ave",
    "sg:city":"Union City",
    "sg:classifiers":[
        {
            "category":"Food & Beverages",
            "subcategory":"Groceries & Convenience Stores",
            "type":"Retail Goods"
        }
    ],
    "sg:phone":"+1 201 863 0125",
    "sg:postcode":"07087",
    "sg:province":"NJ",
    "wof:name":"Associated Supermarket",
    "wof:placetype":"venue"
},
  "geometry": {"coordinates":[-74.034668,40.764268],"type":"Point"}
}