{
  "type": "Feature",
  "properties": {
    "addr:full":"3408 Sunset Ave Asbury Park NJ 07712",
    "addr:housenumber":"3408",
    "addr:postcode":"07712",
    "addr:street":"Sunset Ave Asbury",
    "iso:country":"US",
    "sg:address":"3408 Sunset Ave",
    "sg:city":"Asbury Park",
    "sg:classifiers":[
        {
            "category":"Building & Trades",
            "subcategory":"Construction",
            "type":"Services"
        }
    ],
    "sg:phone":"+1 732 922 1275",
    "sg:postcode":"07712",
    "sg:province":"NJ",
    "sg:tags":[
        "heavy"
    ],
    "wof:name":"3404 Sunset Associates LLC",
    "wof:placetype":"venue"
},
  "geometry": {"coordinates":[-74.040933,40.236593],"type":"Point"}
}