{
  "type": "Feature",
  "properties": {
    "iso:country":"US",
    "sg:address":"324 Main St",
    "sg:city":"Hackensack",
    "sg:classifiers":[
        {
            "category":"Food & Beverages",
            "subcategory":"Meat & Fish",
            "type":"Retail Goods"
        }
    ],
    "sg:phone":"+1 201 498 0488",
    "sg:postcode":"07601",
    "sg:province":"NJ",
    "sg:tags":[
        "seafood",
        "market"
    ],
    "wof:name":"Great Ocean Seafood Inc",
    "wof:placetype":"venue"
},
  "geometry": {"coordinates":[-74.04029800000001,40.8885],"type":"Point"}
}