{
  "type": "Feature",
  "properties": {
    "iso:country":"US",
    "sg:address":"204 Passaic Ave",
    "sg:city":"Fairfield",
    "sg:classifiers":[
        {
            "category":"Recreation",
            "subcategory":"Playground",
            "type":"Entertainment"
        }
    ],
    "sg:phone":"+1 973 808 1700",
    "sg:postcode":"07004",
    "sg:province":"NJ",
    "sg:website":"www.jumpnasiumparty.com",
    "wof:name":"JUMPnasium Kids' Parties & More",
    "wof:placetype":"venue"
},
  "geometry": {"coordinates":[-74.27368800000001,40.876825],"type":"Point"}
}