{
  "type": "Feature",
  "properties": {
    "iso:country":"US",
    "sg:address":"102 Taft Ter",
    "sg:city":"Washington",
    "sg:classifiers":[
        {
            "category":"Home & Garden",
            "subcategory":"Building Materials",
            "type":"Retail Goods"
        }
    ],
    "sg:phone":"+1   ",
    "sg:postcode":"07882",
    "sg:province":"NJ",
    "wof:name":"A & L Overhead Doors",
    "wof:placetype":"venue"
},
  "geometry": {"coordinates":[-74.96889,40.763992],"type":"Point"}
}