{
  "type": "Feature",
  "properties": {
    "iso:country":"US",
    "sg:address":"5716 Berkshire Valley Rd",
    "sg:city":"Oak Ridge",
    "sg:classifiers":[
        {
            "category":"Food & Beverages",
            "subcategory":"Bakery",
            "type":"Retail Goods"
        }
    ],
    "sg:phone":"+1 973 208 2500",
    "sg:postcode":"07438",
    "sg:province":"NJ",
    "sg:tags":[
        "bagel"
    ],
    "wof:name":"Lox Stocked & Bageled Inc",
    "wof:placetype":"venue"
},
  "geometry": {"coordinates":[-74.507087,41.034846],"type":"Point"}
}