{
  "type": "Feature",
  "properties": {
    "addr:full":"936 10th St Gloucester City NJ 08030",
    "addr:housenumber":"936",
    "addr:postcode":"08030",
    "addr:street":"10Th St",
    "iso:country":"US",
    "sg:address":"936 10th St",
    "sg:city":"Gloucester City",
    "sg:classifiers":[
        {
            "category":"Building & Trades",
            "subcategory":"Landscaping Services",
            "type":"Services"
        }
    ],
    "sg:phone":"+1 856 456 1052",
    "sg:postcode":"08030",
    "sg:province":"NJ",
    "sg:tags":[
        "construction",
        "general",
        "contractor"
    ],
    "wof:name":"Rjm Construction Services",
    "wof:placetype":"venue"
},
  "geometry": {"coordinates":[-75.120564,39.885564],"type":"Point"}
}