{
  "type": "Feature",
  "properties": {
    "iso:country":"US",
    "sg:address":"2750 18th Ave",
    "sg:city":"Wall Township",
    "sg:classifiers":[
        {
            "category":"Professional",
            "subcategory":"Lawyer & Legal Services",
            "type":"Services"
        }
    ],
    "sg:phone":"+1 732 681 8111",
    "sg:postcode":"07719",
    "sg:province":"NJ",
    "sg:tags":[
        "attorney"
    ],
    "wof:name":"Lynn A Kenneally",
    "wof:placetype":"venue"
},
  "geometry": {"coordinates":[-74.082088,40.164104],"type":"Point"}
}