{
  "type": "Feature",
  "properties": {
    "addr:full":"4 E Clements Bridge Rd Runnemede NJ 08078",
    "addr:housenumber":"4",
    "addr:postcode":"08078",
    "addr:street":"E Clements Bridge Rd",
    "iso:country":"US",
    "sg:address":"4 E Clements Bridge Rd",
    "sg:city":"Runnemede",
    "sg:classifiers":[
        {
            "category":"Personal",
            "subcategory":"Barber",
            "type":"Services"
        },
        {
            "category":"Personal",
            "subcategory":"Nail Salon",
            "type":"Services"
        }
    ],
    "sg:phone":"+1 856 939 1175",
    "sg:postcode":"08078",
    "sg:province":"NJ",
    "wof:name":"Hair Hut the",
    "wof:placetype":"venue"
},
  "geometry": {"coordinates":[-75.072502,39.849201],"type":"Point"}
}