{
  "type": "Feature",
  "properties": {
    "iso:country":"US",
    "sg:address":"50 Memorial Pkwy",
    "sg:city":"Long Branch",
    "sg:classifiers":[
        {
            "category":"Real Estate",
            "subcategory":"Real Estate Agent",
            "type":"Services"
        }
    ],
    "sg:phone":"+1 732 222 8897",
    "sg:postcode":"07740",
    "sg:province":"NJ",
    "wof:name":"Hilbe Management Co",
    "wof:placetype":"venue"
},
  "geometry": {"coordinates":[-73.985282,40.303066],"type":"Point"}
}