{
  "type": "Feature",
  "properties": {
    "addr:full":"1937 Westfield Ave Scotch Plains NJ 07076",
    "addr:housenumber":"1937",
    "addr:postcode":"07076",
    "addr:street":"Westfield Ave",
    "iso:country":"US",
    "sg:address":"1937 Westfield Ave",
    "sg:city":"Scotch Plains",
    "sg:classifiers":[
        {
            "category":"Retail",
            "subcategory":"Funeral Services",
            "type":"Services"
        }
    ],
    "sg:phone":"+1 908 322 8038",
    "sg:postcode":"07076",
    "sg:province":"NJ",
    "sg:tags":[
        "director"
    ],
    "wof:name":"Rossi Funeral Home Inc",
    "wof:placetype":"venue"
},
  "geometry": {"coordinates":[-74.396636,40.649525],"type":"Point"}
}