{
  "type": "Feature",
  "properties": {
    "iso:country":"US",
    "sg:address":"518 Summit Ave",
    "sg:city":"Jersey City",
    "sg:classifiers":[
        {
            "category":"Taxi",
            "type":"Transportation"
        }
    ],
    "sg:phone":"+1 201 432 1111",
    "sg:postcode":"07306",
    "sg:province":"NJ",
    "wof:name":"Bergen City Grove Taxi",
    "wof:placetype":"venue"
},
  "geometry": {"coordinates":[-74.05988499999999,40.731708],"type":"Point"}
}