{
  "type": "Feature",
  "properties": {
    "iso:country":"US",
    "sg:address":"51 S Ashby Ave",
    "sg:city":"Livingston",
    "sg:classifiers":[
        {
            "category":"Wholesale",
            "subcategory":"Non-durable Goods",
            "type":"Manufacturing & Wholesale Goods"
        }
    ],
    "sg:phone":"+1 973 992 6689",
    "sg:postcode":"07039",
    "sg:province":"NJ",
    "wof:name":"E Way International Trading In",
    "wof:placetype":"venue"
},
  "geometry": {"coordinates":[-74.322684,40.792274],"type":"Point"}
}