{
  "type": "Feature",
  "properties": {
    "iso:country":"US",
    "sg:address":"501 Plainsboro Rd",
    "sg:city":"Plainsboro",
    "sg:classifiers":[
        {
            "category":"Professional",
            "type":"Services"
        }
    ],
    "sg:phone":"+1   ",
    "sg:postcode":"08536",
    "sg:province":"NJ",
    "wof:name":"Heptronik Corp",
    "wof:placetype":"venue"
},
  "geometry": {"coordinates":[-74.59145599999999,40.333217],"type":"Point"}
}