{
  "type": "Feature",
  "properties": {
    "iso:country":"US",
    "sg:address":"3 Victoria Ln",
    "sg:city":"Morristown",
    "sg:classifiers":[
        {
            "category":"Health Services",
            "subcategory":"Doctor",
            "type":"Services"
        }
    ],
    "sg:phone":"+1 973 898 0996",
    "sg:postcode":"07960",
    "sg:province":"NJ",
    "sg:tags":[
        "physician",
        "surgeon"
    ],
    "wof:name":"Allan L Gardner MD",
    "wof:placetype":"venue"
},
  "geometry": {"coordinates":[-74.48179399999999,40.768093],"type":"Point"}
}