{
  "type": "Feature",
  "properties": {
    "addr:full":"115 W Century Rd Paramus NJ 07652",
    "addr:housenumber":"115",
    "addr:postcode":"07652",
    "addr:street":"W Century Rd",
    "iso:country":"US",
    "sg:address":"115 W Century Rd",
    "sg:city":"Paramus",
    "sg:classifiers":[
        {
            "category":"Professional",
            "subcategory":"Advertising",
            "type":"Services"
        }
    ],
    "sg:phone":"+1   ",
    "sg:postcode":"07652",
    "sg:province":"NJ",
    "wof:name":"Innovative Medical Education",
    "wof:placetype":"venue"
},
  "geometry": {"coordinates":[-74.082421,40.935519],"type":"Point"}
}