{
  "type": "Feature",
  "properties": {
    "iso:country":"US",
    "sg:address":"4 Interhaven Ave",
    "sg:city":"Plainfield",
    "sg:classifiers":[
        {
            "category":"Shopping",
            "subcategory":"Musical Instruments",
            "type":"Retail Goods"
        }
    ],
    "sg:phone":"+1   ",
    "sg:postcode":"07060",
    "sg:province":"NJ",
    "sg:tags":[
        "recording",
        "music"
    ],
    "wof:name":"Kalinka Recordings",
    "wof:placetype":"venue"
},
  "geometry": {"coordinates":[-74.44215699999999,40.628944],"type":"Point"}
}