{
  "type": "Feature",
  "properties": {
    "iso:country":"US",
    "sg:address":"19 Valley Rd",
    "sg:city":"Boonton",
    "sg:classifiers":[
        {
            "category":"Building & Trades",
            "subcategory":"Electrical",
            "type":"Services"
        }
    ],
    "sg:phone":"+1 973 334 9155",
    "sg:postcode":"07005",
    "sg:province":"NJ",
    "sg:tags":[
        "electric",
        "contractor"
    ],
    "wof:name":"Van Riper Electric Co Inc",
    "wof:placetype":"venue"
},
  "geometry": {"coordinates":[-74.432547,40.926398],"type":"Point"}
}