{
  "type": "Feature",
  "properties": {
    "iso:country":"US",
    "sg:address":"400 Pointers Auburn Rd",
    "sg:city":"Salem",
    "sg:phone":"+1 856 935 2018",
    "sg:postcode":"08079",
    "sg:province":"NJ",
    "sg:tags":[
        "farm"
    ],
    "wof:name":"Frank J Fichera",
    "wof:placetype":"venue"
},
  "geometry": {"coordinates":[-75.42959999999999,39.642073],"type":"Point"}
}