{
  "type": "Feature",
  "properties": {
    "addr:full":"1378 Morris Ave Union NJ 07083",
    "addr:housenumber":"1378",
    "addr:postcode":"07083",
    "addr:street":"Morris Ave",
    "iso:country":"US",
    "sg:address":"1378 Morris Ave",
    "sg:city":"Union",
    "sg:classifiers":[
        {
            "category":"Personal",
            "subcategory":"Beauty Salon",
            "type":"Services"
        }
    ],
    "sg:phone":"+1 908 964 0424",
    "sg:postcode":"07083",
    "sg:province":"NJ",
    "sg:tags":[
        "shop"
    ],
    "wof:name":"Cut Above",
    "wof:placetype":"venue"
},
  "geometry": {"coordinates":[-74.245615,40.68863],"type":"Point"}
}