{
  "type": "Feature",
  "properties": {
    "addr:full":"10 Warren Dr Marlboro NJ 07746",
    "addr:housenumber":"10",
    "addr:postcode":"07746",
    "addr:street":"Warren Dr",
    "iso:country":"US",
    "sg:address":"10 Warren Dr",
    "sg:city":"Marlboro",
    "sg:classifiers":[
        {
            "category":"Building & Trades",
            "subcategory":"Cleaning & Sanitation",
            "type":"Services"
        }
    ],
    "sg:phone":"+1   ",
    "sg:postcode":"07746",
    "sg:province":"NJ",
    "sg:tags":[
        "maintenance"
    ],
    "wof:name":"Consumer Floor Maintance",
    "wof:placetype":"venue"
},
  "geometry": {"coordinates":[-74.225521,40.285772],"type":"Point"}
}