{
  "type": "Feature",
  "properties": {
    "addr:full":"22 N Bridge Ave Red Bank NJ 07701",
    "addr:housenumber":"22",
    "addr:postcode":"07701",
    "addr:street":"N Bridge Ave",
    "iso:country":"US",
    "sg:address":"22 N Bridge Ave",
    "sg:city":"Red Bank",
    "sg:classifiers":[
        {
            "category":"Restaurant",
            "type":"Food & Drink"
        }
    ],
    "sg:phone":"+1   ",
    "sg:postcode":"07701",
    "sg:province":"NJ",
    "sg:tags":[
        "eating"
    ],
    "wof:name":"China Moon",
    "wof:placetype":"venue"
},
  "geometry": {"coordinates":[-74.07545399999999,40.351193],"type":"Point"}
}