{
  "type": "Feature",
  "properties": {
    "iso:country":"US",
    "sg:address":"9 Washington St",
    "sg:city":"Morristown",
    "sg:classifiers":[
        {
            "category":"Professional",
            "subcategory":"Lawyer & Legal Services",
            "type":"Services"
        }
    ],
    "sg:phone":"+1 973 290 9666",
    "sg:postcode":"07960",
    "sg:province":"NJ",
    "sg:tags":[
        "attorney"
    ],
    "wof:name":"Bernard Weiss",
    "wof:placetype":"venue"
},
  "geometry": {"coordinates":[-74.482477,40.797312],"type":"Point"}
}