{
  "type": "Feature",
  "properties": {
    "iso:country":"US",
    "sg:address":"160 Hamilton Ave",
    "sg:city":"Fairview",
    "sg:classifiers":[
        {
            "category":"Building & Trades",
            "subcategory":"Construction",
            "type":"Services"
        }
    ],
    "sg:phone":"+1 201 313 3389",
    "sg:postcode":"07022",
    "sg:province":"NJ",
    "sg:tags":[
        "hanging",
        "contractor"
    ],
    "wof:name":"Roger & Sons Painting Inc",
    "wof:placetype":"venue"
},
  "geometry": {"coordinates":[-73.99631599999999,40.813874],"type":"Point"}
}