{
  "type": "Feature",
  "properties": {
    "iso:country":"US",
    "sg:address":"39 Spring Valley Rd",
    "sg:city":"Park Ridge",
    "sg:classifiers":[
        {
            "category":"Real Estate",
            "subcategory":"Real Estate Agent",
            "type":"Services"
        }
    ],
    "sg:phone":"+1 201 391 9225",
    "sg:postcode":"07656",
    "sg:province":"NJ",
    "sg:tags":[
        "agency",
        "rental"
    ],
    "wof:name":"Auto Body Express LLC",
    "wof:placetype":"venue"
},
  "geometry": {"coordinates":[-74.06164800000001,41.036349],"type":"Point"}
}