{
  "type": "Feature",
  "properties": {
    "addr:full":"2 Hemlock Ln Marlboro NJ 07746",
    "addr:housenumber":"2",
    "addr:postcode":"07746",
    "addr:street":"Hemlock Ln",
    "iso:country":"US",
    "sg:address":"2 Hemlock Ln",
    "sg:city":"Marlboro",
    "sg:classifiers":[
        {
            "category":"Professional",
            "subcategory":"Management & Consulting",
            "type":"Services"
        }
    ],
    "sg:phone":"+1   ",
    "sg:postcode":"07746",
    "sg:province":"NJ",
    "wof:name":"Investible Marketing Inc",
    "wof:placetype":"venue"
},
  "geometry": {"coordinates":[-74.288169,40.324382],"type":"Point"}
}