{
  "type": "Feature",
  "properties": {
    "iso:country":"US",
    "sg:address":"4609 Landis Ave",
    "sg:city":"Sea Isle City",
    "sg:classifiers":[
        {
            "category":"Shopping",
            "subcategory":"Florist",
            "type":"Retail Goods"
        }
    ],
    "sg:phone":"+1 609 263 6300",
    "sg:postcode":"08243",
    "sg:province":"NJ",
    "wof:name":"Creative Designs",
    "wof:placetype":"venue"
},
  "geometry": {"coordinates":[-74.69396500000001,39.152043],"type":"Point"}
}