{
  "type": "Feature",
  "properties": {
    "addr:full":"356 Lafayette Rd Sparta NJ 07871",
    "addr:housenumber":"356",
    "addr:postcode":"07871",
    "iso:country":"US",
    "sg:address":"356 Lafayette Rd",
    "sg:city":"Sparta",
    "sg:classifiers":[
        {
            "category":"Manufacturing",
            "subcategory":"Metals",
            "type":"Manufacturing & Wholesale Goods"
        }
    ],
    "sg:phone":"+1 973 729 4777",
    "sg:postcode":"07871",
    "sg:province":"NJ",
    "sg:tags":[
        "oil",
        "burner"
    ],
    "wof:name":"Fredericks Fuel & Heating Svc",
    "wof:placetype":"venue"
},
  "geometry": {"coordinates":[-74.65199699999999,41.066517],"type":"Point"}
}