{
  "type": "Feature",
  "properties": {
    "iso:country":"US",
    "sg:address":"345 State Rte 17",
    "sg:city":"Upper Saddle Rvr",
    "sg:classifiers":[
        {
            "category":"Banks & Credit Unions",
            "subcategory":"Bank",
            "type":"Services"
        }
    ],
    "sg:phone":"+1 201 934 4222",
    "sg:postcode":"07458",
    "sg:province":"NJ",
    "sg:tags":[
        "loan",
        "real estate"
    ],
    "sg:website":"www.americanhm.com",
    "wof:name":"American Home Mortgage",
    "wof:placetype":"venue"
},
  "geometry": {"coordinates":[-74.11976199999999,41.053948],"type":"Point"}
}