{
  "type": "Feature",
  "properties": {
    "iso:country":"US",
    "sg:address":"162 2nd St",
    "sg:city":"Keyport",
    "sg:classifiers":[
        {
            "category":"Wholesale",
            "subcategory":"Apparel",
            "type":"Manufacturing & Wholesale Goods"
        }
    ],
    "sg:phone":"+1 732 335 0533",
    "sg:postcode":"07735",
    "sg:province":"NJ",
    "wof:name":"Galinda Wang Inc",
    "wof:placetype":"venue"
},
  "geometry": {"coordinates":[-74.193225,40.438233],"type":"Point"}
}