{
  "type": "Feature",
  "properties": {
    "addr:full":"119 Walnut St Montclair NJ 07042",
    "addr:housenumber":"119",
    "addr:postcode":"07042",
    "addr:street":"Walnut St",
    "iso:country":"US",
    "sg:address":"119 Walnut St",
    "sg:city":"Montclair",
    "sg:classifiers":[
        {
            "category":"Professional",
            "subcategory":"Advertising",
            "type":"Services"
        }
    ],
    "sg:phone":"+1 973 655 9239",
    "sg:postcode":"07042",
    "sg:province":"NJ",
    "sg:tags":[
        "agency"
    ],
    "wof:name":"Custom Information Image",
    "wof:placetype":"venue"
},
  "geometry": {"coordinates":[-74.212084,40.817645],"type":"Point"}
}