{
  "type": "Feature",
  "properties": {
    "iso:country":"US",
    "sg:address":"80 Edward Ave",
    "sg:city":"Bridgeton",
    "sg:classifiers":[
        {
            "category":"Farming",
            "subcategory":"Dairy Farm",
            "type":"Manufacturing & Wholesale Goods"
        }
    ],
    "sg:phone":"+1 856 451 1300",
    "sg:postcode":"08302",
    "sg:province":"NJ",
    "wof:name":"Cumberland Dairy Inc",
    "wof:placetype":"venue"
},
  "geometry": {"coordinates":[-75.221334,39.445348],"type":"Point"}
}