{
  "type": "Feature",
  "properties": {
    "addr:full":"178 Bauer Dr Oakland NJ 07436",
    "addr:housenumber":"178",
    "addr:postcode":"07436",
    "addr:street":"Bauer Dr",
    "iso:country":"US",
    "sg:address":"178 Bauer Dr",
    "sg:city":"Oakland",
    "sg:classifiers":[
        {
            "category":"Professional",
            "type":"Services"
        }
    ],
    "sg:phone":"+1 201 337 1352",
    "sg:postcode":"07436",
    "sg:province":"NJ",
    "sg:tags":[
        "establishment"
    ],
    "wof:name":"Shiseido America Inc",
    "wof:placetype":"venue"
},
  "geometry": {"coordinates":[-74.236265,41.01019],"type":"Point"}
}