{
  "type": "Feature",
  "properties": {
    "addr:full":"642 Eagle Rock Ave Ste 9 West Orange NJ 07052",
    "addr:housenumber":"642",
    "addr:postcode":"07052",
    "addr:street":"Eagle Rock Ave Ste 9",
    "iso:country":"US",
    "sg:address":"642 Eagle Rock Ave Ste 9",
    "sg:city":"West Orange",
    "sg:classifiers":[
        {
            "category":"Bagels",
            "subcategory":"None",
            "type":"Food & Drink"
        }
    ],
    "sg:phone":"+1 973 731 4985",
    "sg:postcode":"07052",
    "sg:province":"NJ",
    "wof:name":"Bagel Box the",
    "wof:placetype":"venue"
},
  "geometry": {"coordinates":[-74.2593,40.810001],"type":"Point"}
}