{
  "type": "Feature",
  "properties": {
    "addr:full":"231 N Black Horse Pike Williamstown NJ 08094",
    "addr:housenumber":"231",
    "addr:postcode":"08094",
    "addr:street":"N Black Horse Pike",
    "iso:country":"US",
    "sg:address":"231 N Black Horse Pike",
    "sg:city":"Williamstown",
    "sg:classifiers":[
        {
            "category":"Home & Garden",
            "subcategory":"Garden Supply",
            "type":"Retail Goods"
        }
    ],
    "sg:phone":"+1 856 629 4931",
    "sg:postcode":"08094",
    "sg:province":"NJ",
    "sg:tags":[
        "equipment",
        "lawn",
        "mower"
    ],
    "wof:name":"Ormsby's Lawn Equipment",
    "wof:placetype":"venue"
},
  "geometry": {"coordinates":[-74.995302,39.691592],"type":"Point"}
}