{
  "type": "Feature",
  "properties": {
    "iso:country":"US",
    "sg:address":"561 Heritage Rd",
    "sg:city":"Millington",
    "sg:classifiers":[
        {
            "category":"Building & Trades",
            "subcategory":"Landscaping Services",
            "type":"Services"
        }
    ],
    "sg:phone":"+1 908 647 4587",
    "sg:postcode":"07946",
    "sg:province":"NJ",
    "sg:tags":[
        "landscape"
    ],
    "wof:name":"Serina Joseph Landscaping",
    "wof:placetype":"venue"
},
  "geometry": {"coordinates":[-74.506012,40.664646],"type":"Point"}
}