{
  "type": "Feature",
  "properties": {
    "addr:full":"54 Parkview Ter Lincroft NJ 07738",
    "addr:housenumber":"54",
    "addr:postcode":"07738",
    "addr:street":"Parkview Ter",
    "iso:country":"US",
    "sg:address":"54 Parkview Ter",
    "sg:city":"Lincroft",
    "sg:classifiers":[
        {
            "category":"Building & Trades",
            "subcategory":"Construction",
            "type":"Services"
        }
    ],
    "sg:phone":"+1 732 643 0760",
    "sg:postcode":"07738",
    "sg:province":"NJ",
    "sg:tags":[
        "excavation",
        "contractor"
    ],
    "wof:name":"General Groundworks",
    "wof:placetype":"venue"
},
  "geometry": {"coordinates":[-74.101793,40.33158],"type":"Point"}
}