{
  "type": "Feature",
  "properties": {
    "iso:country":"US",
    "sg:address":"123 King's Hwy",
    "sg:city":"Haddonfield",
    "sg:classifiers":[
        {
            "category":"Coffee & Tea",
            "type":"Food & Drink"
        }
    ],
    "sg:phone":"+1 856 795 8400",
    "sg:postcode":"08033",
    "sg:province":"NJ",
    "wof:name":"The Grind House",
    "wof:placetype":"venue"
},
  "geometry": {"coordinates":[-75.032977,39.897871],"type":"Point"}
}