{
  "type": "Feature",
  "properties": {
    "iso:country":"US",
    "sg:address":"510 25th St Ste 102",
    "sg:city":"Union City",
    "sg:classifiers":[
        {
            "category":"Retail",
            "subcategory":"Auto Repair",
            "type":"Services"
        }
    ],
    "sg:phone":"+1 201 590 8600",
    "sg:postcode":"07087",
    "sg:province":"NJ",
    "wof:name":"Best Auto Tech",
    "wof:placetype":"venue"
},
  "geometry": {"coordinates":[-74.03216999999999,40.768417],"type":"Point"}
}