{
  "type": "Feature",
  "properties": {
    "addr:full":"1305 State Rte 33 Farmingdale NJ 07727",
    "addr:housenumber":"1305",
    "addr:postcode":"07727",
    "addr:street":"State Rte 33",
    "iso:country":"US",
    "sg:address":"1305 State Rte 33",
    "sg:city":"Farmingdale",
    "sg:classifiers":[
        {
            "category":"Home & Garden",
            "subcategory":"Home Furnishings",
            "type":"Retail Goods"
        }
    ],
    "sg:phone":"+1 732 938 4027",
    "sg:postcode":"07727",
    "sg:province":"NJ",
    "sg:tags":[
        "lamp",
        "shades"
    ],
    "wof:name":"Etelco Lighting",
    "wof:placetype":"venue"
},
  "geometry": {"coordinates":[-74.163023,40.22547],"type":"Point"}
}