{
  "type": "Feature",
  "properties": {
    "addr:full":"4555 US Hwy 9 Howell NJ 07731",
    "addr:housenumber":"4555",
    "addr:postcode":"07731",
    "addr:street":"Us Hwy 9",
    "iso:country":"US",
    "sg:address":"4555 US Hwy 9",
    "sg:city":"Howell",
    "sg:classifiers":[
        {
            "category":"Insurance",
            "subcategory":"Insurance Agent",
            "type":"Services"
        }
    ],
    "sg:phone":"+1   ",
    "sg:postcode":"07731",
    "sg:province":"NJ",
    "wof:name":"Allstate New Jersey Insur Co",
    "wof:placetype":"venue"
},
  "geometry": {"coordinates":[-74.22506,40.140694],"type":"Point"}
}