{
  "type": "Feature",
  "properties": {
    "addr:full":"56A W Pleasant Ave Maywood NJ 07607",
    "addr:housenumber":"56a",
    "addr:postcode":"07607",
    "addr:street":"W Pleasant Ave",
    "iso:country":"US",
    "sg:address":"56A W Pleasant Ave",
    "sg:city":"Maywood",
    "sg:classifiers":[
        {
            "category":"Bagels",
            "subcategory":"None",
            "type":"Food & Drink"
        }
    ],
    "sg:phone":"+1 201 843 9480",
    "sg:postcode":"07607",
    "sg:province":"NJ",
    "wof:name":"Bakin Bagels Inc",
    "wof:placetype":"venue"
},
  "geometry": {"coordinates":[-74.06283999999999,40.904554],"type":"Point"}
}