{
  "type": "Feature",
  "properties": {
    "addr:full":"360 State Rte 17 Paramus NJ 07652",
    "addr:housenumber":"360",
    "addr:postcode":"07652",
    "addr:street":"State Rte 17",
    "iso:country":"US",
    "sg:address":"360 State Rte 17",
    "sg:city":"Paramus",
    "sg:classifiers":[
        {
            "category":"Restaurant",
            "type":"Food & Drink"
        }
    ],
    "sg:phone":"+1 201 262 9202",
    "sg:postcode":"07652",
    "sg:province":"NJ",
    "sg:tags":[
        "shop",
        "coffee"
    ],
    "wof:name":"Starbucks",
    "wof:placetype":"venue"
},
  "geometry": {"coordinates":[-74.070677,40.910582],"type":"Point"}
}