{
  "type": "Feature",
  "properties": {
    "iso:country":"US",
    "sg:address":"25 Easton Ave",
    "sg:city":"New Brunswick",
    "sg:classifiers":[
        {
            "category":"Retail",
            "subcategory":"Repair Shop",
            "type":"Services"
        }
    ],
    "sg:phone":"+1   ",
    "sg:postcode":"08901",
    "sg:province":"NJ",
    "wof:name":"024 Hour 7 A Day Emerg Locksmi",
    "wof:placetype":"venue"
},
  "geometry": {"coordinates":[-74.44917100000001,40.497918],"type":"Point"}
}