{
  "type": "Feature",
  "properties": {
    "addr:full":"1901 E Linden Ave Linden NJ 07036",
    "addr:housenumber":"1901",
    "addr:postcode":"07036",
    "addr:street":"E Linden Ave",
    "iso:country":"US",
    "sg:address":"1901 E Linden Ave",
    "sg:city":"Linden",
    "sg:classifiers":[
        {
            "category":"Manufacturing",
            "subcategory":"Electronics",
            "type":"Manufacturing & Wholesale Goods"
        },
        {
            "category":"Shopping",
            "subcategory":"Computers & Home Electronics",
            "type":"Retail Goods"
        }
    ],
    "sg:phone":"+1 908 474 9595",
    "sg:postcode":"07036",
    "sg:province":"NJ",
    "sg:tags":[
        "equipment",
        "supply",
        "component",
        "electronic",
        "mfg"
    ],
    "wof:name":"Advanced Orientation Systs Inc",
    "wof:placetype":"venue"
},
  "geometry": {"coordinates":[-74.23581799999999,40.642306],"type":"Point"}
}