{
  "type": "Feature",
  "properties": {
    "iso:country":"US",
    "sg:address":"88 Brooklake Rd",
    "sg:city":"Florham Park",
    "sg:classifiers":[
        {
            "category":"Social Services",
            "subcategory":"Child Care",
            "type":"Services"
        }
    ],
    "sg:phone":"+1 973 966 9762",
    "sg:postcode":"07932",
    "sg:province":"NJ",
    "sg:tags":[
        "day"
    ],
    "wof:name":"Vocationist Sisters",
    "wof:placetype":"venue"
},
  "geometry": {"coordinates":[-74.385803,40.759499],"type":"Point"}
}