{
  "type": "Feature",
  "properties": {
    "iso:country":"US",
    "sg:address":"20 29th St",
    "sg:city":"Fair Lawn",
    "sg:classifiers":[
        {
            "category":"Social Services",
            "subcategory":"Adult Care",
            "type":"Services"
        }
    ],
    "sg:phone":"+1 201 796 5522",
    "sg:postcode":"07410",
    "sg:province":"NJ",
    "sg:tags":[
        "home",
        "group"
    ],
    "wof:name":"UJA Add",
    "wof:placetype":"venue"
},
  "geometry": {"coordinates":[-74.10516200000001,40.920224],"type":"Point"}
}