{
  "type": "Feature",
  "properties": {
    "iso:country":"US",
    "sg:address":"831 Ramah Rd",
    "sg:city":"Millville",
    "sg:classifiers":[
        {
            "category":"Organizations",
            "subcategory":"Religious Organization",
            "type":"Services"
        }
    ],
    "sg:phone":"+1 856 447 5336",
    "sg:postcode":"08332",
    "sg:province":"NJ",
    "wof:name":"Raymond J Elberson Rev",
    "wof:placetype":"venue"
},
  "geometry": {"coordinates":[-75.134102,39.367586],"type":"Point"}
}