{
  "type": "Feature",
  "properties": {
    "addr:full":"36 Union Ave Little Falls NJ 07424",
    "addr:housenumber":"36",
    "addr:postcode":"07424",
    "addr:street":"Union Ave",
    "iso:country":"US",
    "sg:address":"36 Union Ave",
    "sg:city":"Little Falls",
    "sg:classifiers":[
        {
            "category":"Real Estate",
            "subcategory":"Real Estate Operator",
            "type":"Services"
        }
    ],
    "sg:phone":"+1   ",
    "sg:postcode":"07424",
    "sg:province":"NJ",
    "sg:tags":[
        "building",
        "apartment"
    ],
    "wof:name":"Bankers Financial Corp",
    "wof:placetype":"venue"
},
  "geometry": {"coordinates":[-74.234404,40.881833],"type":"Point"}
}