{
  "type": "Feature",
  "properties": {
    "iso:country":"US",
    "sg:address":"83 Burlews Ct",
    "sg:city":"Hackensack",
    "sg:classifiers":[
        {
            "category":"Building & Trades",
            "subcategory":"Locksmith",
            "type":"Services"
        }
    ],
    "sg:phone":"+1 201 334 3960",
    "sg:postcode":"07601",
    "sg:province":"NJ",
    "sg:tags":[
        "key"
    ],
    "wof:name":"A-1 24 Hour 7 Day Emerg A Locksmith",
    "wof:placetype":"venue"
},
  "geometry": {"coordinates":[-74.040221,40.902695],"type":"Point"}
}