{
  "type": "Feature",
  "properties": {
    "iso:country":"US",
    "sg:address":"158 N Academy St",
    "sg:city":"Hightstown",
    "sg:classifiers":[
        {
            "category":"Shopping",
            "subcategory":"Used Merchandise",
            "type":"Retail Goods"
        }
    ],
    "sg:phone":"+1 609 443 5793",
    "sg:postcode":"08520",
    "sg:province":"NJ",
    "sg:tags":[
        "antique"
    ],
    "wof:name":"Locke Manor Collections",
    "wof:placetype":"venue"
},
  "geometry": {"coordinates":[-74.526403,40.272847],"type":"Point"}
}