{
  "type": "Feature",
  "properties": {
    "addr:full":"500 Anderson Ave Cliffside Park NJ 07010",
    "addr:housenumber":"500",
    "addr:postcode":"07010",
    "addr:street":"Anderson Ave",
    "iso:country":"US",
    "sg:address":"500 Anderson Ave",
    "sg:city":"Cliffside Park",
    "sg:classifiers":[
        {
            "category":"Building & Trades",
            "subcategory":"Construction",
            "type":"Services"
        }
    ],
    "sg:phone":"+1 201 945 5946",
    "sg:postcode":"07010",
    "sg:province":"NJ",
    "sg:tags":[
        "contractor"
    ],
    "wof:name":"Anderson Avenue Llc",
    "wof:placetype":"venue"
},
  "geometry": {"coordinates":[-73.99024300000001,40.821873],"type":"Point"}
}