{
  "type": "Feature",
  "properties": {
    "addr:full":"641 Ocean Ave Lakewood NJ 08701",
    "addr:housenumber":"641",
    "addr:postcode":"08701",
    "addr:street":"Ocean Ave",
    "iso:country":"US",
    "sg:address":"641 Ocean Ave",
    "sg:city":"Lakewood",
    "sg:classifiers":[
        {
            "category":"Building & Trades",
            "subcategory":"Construction",
            "type":"Services"
        }
    ],
    "sg:phone":"+1 732 367 6396",
    "sg:postcode":"08701",
    "sg:province":"NJ",
    "sg:tags":[
        "house"
    ],
    "wof:name":"James D Chopp Construction",
    "wof:placetype":"venue"
},
  "geometry": {"coordinates":[-74.191018,40.090475],"type":"Point"}
}