{
  "type": "Feature",
  "properties": {
    "addr:full":"225 Fred Wehran Dr Teterboro NJ 07608",
    "addr:housenumber":"225",
    "addr:postcode":"07608",
    "addr:street":"Fred Wehran Dr",
    "iso:country":"US",
    "sg:address":"225 Fred Wehran Dr",
    "sg:city":"Teterboro",
    "sg:classifiers":[
        {
            "category":"Government",
            "subcategory":"Office",
            "type":"Public Place"
        }
    ],
    "sg:phone":"+1   ",
    "sg:postcode":"07608",
    "sg:province":"NJ",
    "sg:tags":[
        "transportation"
    ],
    "wof:name":"Airport Traffic Control Tower",
    "wof:placetype":"venue"
},
  "geometry": {"coordinates":[-74.05980700000001,40.860772],"type":"Point"}
}