{
  "type": "Feature",
  "properties": {
    "addr:full":"4005 Ventnor Ave Atlantic City NJ 08401",
    "addr:housenumber":"4005",
    "addr:postcode":"08401",
    "addr:street":"Ventnor Ave",
    "iso:country":"US",
    "sg:address":"4005 Ventnor Ave",
    "sg:city":"Atlantic City",
    "sg:classifiers":[
        {
            "category":"Professional",
            "subcategory":"Business Services",
            "type":"Services"
        }
    ],
    "sg:phone":"+1   ",
    "sg:postcode":"08401",
    "sg:province":"NJ",
    "wof:name":"Quell Technologies",
    "wof:placetype":"venue"
},
  "geometry": {"coordinates":[-74.45914,39.349461],"type":"Point"}
}