{
  "type": "Feature",
  "properties": {
    "iso:country":"US",
    "sg:address":"1377 Paterson Plank Rd",
    "sg:city":"Secaucus",
    "sg:classifiers":[
        {
            "category":"Retail",
            "subcategory":"Auto Rental",
            "type":"Services"
        }
    ],
    "sg:phone":"+1 201 864 3637",
    "sg:postcode":"07094",
    "sg:province":"NJ",
    "sg:tags":[
        "truck",
        "trailer",
        "utility"
    ],
    "wof:name":"U-Haul",
    "wof:placetype":"venue"
},
  "geometry": {"coordinates":[-74.058409,40.79383],"type":"Point"}
}