{
  "type": "Feature",
  "properties": {
    "addr:full":"1581 Mountain Top Rd Bridgewater NJ 08807",
    "addr:housenumber":"1581",
    "addr:postcode":"08807",
    "addr:street":"Mountain Top Rd",
    "iso:country":"US",
    "sg:address":"1581 Mountain Top Rd",
    "sg:city":"Bridgewater",
    "sg:classifiers":[
        {
            "category":"Building & Trades",
            "subcategory":"Plumbing",
            "type":"Services"
        }
    ],
    "sg:phone":"+1 908 526 4164",
    "sg:postcode":"08807",
    "sg:province":"NJ",
    "sg:tags":[
        "plumbing",
        "contractor"
    ],
    "wof:name":"Crim Associates",
    "wof:placetype":"venue"
},
  "geometry": {"coordinates":[-74.600768,40.603956],"type":"Point"}
}