{
  "type": "Feature",
  "properties": {
    "iso:country":"US",
    "sg:address":"PO Box 26",
    "sg:city":"Belleville",
    "sg:classifiers":[
        {
            "category":"Personal",
            "subcategory":"Tanning Parlor",
            "type":"Services"
        },
        {
            "category":"Personal",
            "subcategory":"Day Spa",
            "type":"Services"
        },
        {
            "category":"Personal",
            "subcategory":"Nail Salon",
            "type":"Services"
        }
    ],
    "sg:phone":"+1 201 460 9082",
    "sg:postcode":"07109",
    "sg:province":"NJ",
    "wof:name":"Superior Sun Centers",
    "wof:placetype":"venue"
},
  "geometry": {"coordinates":[-74.16390199999999,40.7953],"type":"Point"}
}