{
  "type": "Feature",
  "properties": {
    "iso:country":"US",
    "sg:address":"4602 Bergenline Ave",
    "sg:city":"Union City",
    "sg:classifiers":[
        {
            "category":"Restaurant",
            "type":"Food & Drink"
        }
    ],
    "sg:phone":"+1 201 348 4822",
    "sg:postcode":"07087",
    "sg:province":"NJ",
    "sg:tags":[
        "eating"
    ],
    "wof:name":"El Carretero",
    "wof:placetype":"venue"
},
  "geometry": {"coordinates":[-74.022598,40.780499],"type":"Point"}
}