{
  "type": "Feature",
  "properties": {
    "iso:country":"US",
    "sg:address":"540 Franklinville Rd",
    "sg:city":"Mullica Hill",
    "sg:classifiers":[
        {
            "category":"Wholesale",
            "subcategory":"Durable Goods & Equipment",
            "type":"Manufacturing & Wholesale Goods"
        }
    ],
    "sg:phone":"+1 856 478 9660",
    "sg:postcode":"08062",
    "sg:province":"NJ",
    "sg:tags":[
        "importer"
    ],
    "wof:name":"Vanguard Trading Svc",
    "wof:placetype":"venue"
},
  "geometry": {"coordinates":[-75.259294,39.722357],"type":"Point"}
}