{
  "type": "Feature",
  "properties": {
    "iso:country":"US",
    "sg:address":"1436 E Elizabeth Ave",
    "sg:city":"Linden",
    "sg:classifiers":[
        {
            "category":"Building & Trades",
            "subcategory":"Construction",
            "type":"Services"
        }
    ],
    "sg:phone":"+1 908 925 1123",
    "sg:postcode":"07036",
    "sg:province":"NJ",
    "sg:tags":[
        "industrial",
        "commercial",
        "contractor"
    ],
    "wof:name":"Gordon M Construction Co",
    "wof:placetype":"venue"
},
  "geometry": {"coordinates":[-74.237503,40.6446],"type":"Point"}
}