{
  "type": "Feature",
  "properties": {
    "addr:full":"175 Hendel Ave North Arlington NJ 07031",
    "addr:housenumber":"175",
    "addr:postcode":"07031",
    "addr:street":"Hendel Ave North",
    "iso:country":"US",
    "sg:address":"175 Hendel Ave",
    "sg:city":"North Arlington",
    "sg:classifiers":[
        {
            "category":"Building & Trades",
            "subcategory":"Construction",
            "type":"Services"
        }
    ],
    "sg:phone":"+1 201 955 0418",
    "sg:postcode":"07031",
    "sg:province":"NJ",
    "sg:tags":[
        "home",
        "contractor"
    ],
    "wof:name":"Mendez Construction Co Inc",
    "wof:placetype":"venue"
},
  "geometry": {"coordinates":[-74.142647,40.789773],"type":"Point"}
}