{
  "type": "Feature",
  "properties": {
    "iso:country":"US",
    "sg:address":"74 Ramapo Valley Rd",
    "sg:city":"Mahwah",
    "sg:classifiers":[
        {
            "category":"Shopping",
            "subcategory":"Used Merchandise",
            "type":"Retail Goods"
        }
    ],
    "sg:phone":"+1 201 529 3633",
    "sg:postcode":"07430",
    "sg:province":"NJ",
    "sg:tags":[
        "antique"
    ],
    "wof:name":"My Sister's Cottage",
    "wof:placetype":"venue"
},
  "geometry": {"coordinates":[-74.151155,41.102988],"type":"Point"}
}