{
  "type": "Feature",
  "properties": {
    "addr:full":"2042 Norris Ave Atco NJ 08004",
    "addr:housenumber":"2042",
    "addr:postcode":"08004",
    "addr:street":"Norris Ave",
    "iso:country":"US",
    "sg:address":"2042 Norris Ave",
    "sg:city":"Atco",
    "sg:classifiers":[
        {
            "category":"Building & Trades",
            "subcategory":"Construction",
            "type":"Services"
        }
    ],
    "sg:phone":"+1 856 768 0927",
    "sg:postcode":"08004",
    "sg:province":"NJ",
    "sg:tags":[
        "house"
    ],
    "wof:name":"Beck Design Co",
    "wof:placetype":"venue"
},
  "geometry": {"coordinates":[-74.87536900000001,39.746979],"type":"Point"}
}