{
  "type": "Feature",
  "properties": {
    "iso:country":"US",
    "sg:address":"600 N Albany Ave",
    "sg:city":"Atlantic City",
    "sg:classifiers":[
        {
            "category":"Professional",
            "type":"Services"
        }
    ],
    "sg:phone":"+1 609 348 1537",
    "sg:postcode":"08401",
    "sg:province":"NJ",
    "sg:tags":[
        "establishment"
    ],
    "wof:name":"Perseco",
    "wof:placetype":"venue"
},
  "geometry": {"coordinates":[-74.462153,39.360341],"type":"Point"}
}