{
  "type": "Feature",
  "properties": {
    "addr:full":"1800 State Rte 33 Trenton NJ 08690",
    "addr:housenumber":"1800",
    "addr:postcode":"08690",
    "addr:street":"State Rte 33",
    "iso:country":"US",
    "sg:address":"1800 State Rte 33",
    "sg:city":"Trenton",
    "sg:classifiers":[
        {
            "category":"Education",
            "subcategory":"Special Training",
            "type":"Public Place"
        }
    ],
    "sg:phone":"+1 609 689 0333",
    "sg:postcode":"08690",
    "sg:province":"NJ",
    "sg:tags":[
        "tutoring"
    ],
    "sg:website":"www.kumon.com",
    "wof:name":"Kumon Math & Reading Ctr",
    "wof:placetype":"venue"
},
  "geometry": {"coordinates":[-74.650693,40.224289],"type":"Point"}
}