{
  "type": "Feature",
  "properties": {
    "iso:country":"US",
    "sg:address":"319 13th St",
    "sg:city":"Carlstadt",
    "sg:classifiers":[
        {
            "category":"Building & Trades",
            "subcategory":"Equipment Rental",
            "type":"Services"
        }
    ],
    "sg:phone":"+1 201 842 0550",
    "sg:postcode":"07072",
    "sg:province":"NJ",
    "sg:tags":[
        "leasing"
    ],
    "wof:name":"Budget Fleet Lease",
    "wof:placetype":"venue"
},
  "geometry": {"coordinates":[-74.086962,40.832452],"type":"Point"}
}