{
  "type": "Feature",
  "properties": {
    "iso:country":"US",
    "sg:address":"270 Davidson Ave",
    "sg:city":"Somerset",
    "sg:classifiers":[
        {
            "category":"Professional",
            "subcategory":"Engineering",
            "type":"Services"
        }
    ],
    "sg:phone":"+1   ",
    "sg:postcode":"08873",
    "sg:province":"NJ",
    "wof:name":"Lge (old Co) Inc",
    "wof:placetype":"venue"
},
  "geometry": {"coordinates":[-74.527371,40.533721],"type":"Point"}
}