{
  "type": "Feature",
  "properties": {
    "addr:full":"33 Outwater Ln Garfield NJ 07026",
    "addr:housenumber":"33",
    "addr:postcode":"07026",
    "addr:street":"Outwater Ln",
    "iso:country":"US",
    "sg:address":"33 Outwater Ln",
    "sg:city":"Garfield",
    "sg:classifiers":[
        {
            "category":"Organizations",
            "subcategory":"Community Association",
            "type":"Services"
        }
    ],
    "sg:phone":"+1   ",
    "sg:postcode":"07026",
    "sg:province":"NJ",
    "wof:name":"Y M C A",
    "wof:placetype":"venue"
},
  "geometry": {"coordinates":[-74.117699,40.880365],"type":"Point"}
}