{
  "type": "Feature",
  "properties": {
    "addr:full":"900 Lakewood Ave Lakewood NJ 08701",
    "addr:housenumber":"900",
    "addr:postcode":"08701",
    "addr:street":"Lakewood Ave",
    "iso:country":"US",
    "sg:address":"900 Lakewood Ave",
    "sg:city":"Lakewood",
    "sg:classifiers":[
        {
            "category":"Professional",
            "type":"Services"
        }
    ],
    "sg:phone":"+1 732 364 2181",
    "sg:postcode":"08701",
    "sg:province":"NJ",
    "sg:tags":[
        "establishment"
    ],
    "wof:name":"Academic Dean",
    "wof:placetype":"venue"
},
  "geometry": {"coordinates":[-74.226125,40.096834],"type":"Point"}
}