{
  "type": "Feature",
  "properties": {
    "iso:country":"US",
    "sg:address":"369 N Main St",
    "sg:city":"Barnegat",
    "sg:classifiers":[
        {
            "category":"Health Services",
            "subcategory":"Doctor",
            "type":"Services"
        }
    ],
    "sg:phone":"+1 609 698 8030",
    "sg:postcode":"08005",
    "sg:province":"NJ",
    "sg:tags":[
        "clinic"
    ],
    "wof:name":"Excel Medical Solutions Inc",
    "wof:placetype":"venue"
},
  "geometry": {"coordinates":[-74.222971,39.753375],"type":"Point"}
}