{
  "type": "Feature",
  "properties": {
    "addr:full":"167 W Fort Lee Rd Bogota NJ 07603",
    "addr:housenumber":"167",
    "addr:postcode":"07603",
    "addr:street":"W Fort Lee Rd",
    "iso:country":"US",
    "sg:address":"167 W Fort Lee Rd",
    "sg:city":"Bogota",
    "sg:classifiers":[
        {
            "category":"Building & Trades",
            "subcategory":"Construction",
            "type":"Services"
        }
    ],
    "sg:phone":"+1 201 996 9302",
    "sg:postcode":"07603",
    "sg:province":"NJ",
    "sg:tags":[
        "equipment",
        "repair",
        "site",
        "on"
    ],
    "wof:name":"On Site Equipment Rentals",
    "wof:placetype":"venue"
},
  "geometry": {"coordinates":[-74.03892999999999,40.879189],"type":"Point"}
}