{
  "type": "Feature",
  "properties": {
    "iso:country":"US",
    "sg:address":"389 E Main St",
    "sg:city":"Somerville",
    "sg:classifiers":[
        {
            "category":"Real Estate",
            "subcategory":"Real Estate Agent",
            "type":"Services"
        }
    ],
    "sg:phone":"+1   ",
    "sg:postcode":"08876",
    "sg:province":"NJ",
    "wof:name":"Appraisal C Hoberman",
    "wof:placetype":"venue"
},
  "geometry": {"coordinates":[-74.595294,40.565175],"type":"Point"}
}