{
  "type": "Feature",
  "properties": {
    "addr:full":"77 Lake Rd Basking Ridge NJ 07920",
    "addr:housenumber":"77",
    "addr:postcode":"07920",
    "addr:street":"Lake Rd",
    "iso:country":"US",
    "sg:address":"77 Lake Rd",
    "sg:city":"Basking Ridge",
    "sg:classifiers":[
        {
            "category":"Professional",
            "subcategory":"Lawyer & Legal Services",
            "type":"Services"
        }
    ],
    "sg:phone":"+1   ",
    "sg:postcode":"07920",
    "sg:province":"NJ",
    "wof:name":"Kopacz Thmas Berryman Attorney",
    "wof:placetype":"venue"
},
  "geometry": {"coordinates":[-74.556872,40.693738],"type":"Point"}
}