{
  "type": "Feature",
  "properties": {
    "iso:country":"US",
    "sg:address":"51 Gifford Ave",
    "sg:city":"Jersey City",
    "sg:classifiers":[
        {
            "category":"Organizations",
            "subcategory":"Religious Organization",
            "type":"Services"
        }
    ],
    "sg:phone":"+1 201 433 7793",
    "sg:postcode":"07304",
    "sg:province":"NJ",
    "sg:tags":[
        "clergy"
    ],
    "wof:name":"Gladys G Moore Rev",
    "wof:placetype":"venue"
},
  "geometry": {"coordinates":[-74.074617,40.720525],"type":"Point"}
}