{
  "type": "Feature",
  "properties": {
    "addr:full":"601 Main St Metuchen NJ 08840",
    "addr:housenumber":"601",
    "addr:postcode":"08840",
    "addr:street":"Main St",
    "iso:country":"US",
    "sg:address":"601 Main St",
    "sg:city":"Metuchen",
    "sg:classifiers":[
        {
            "category":"Health Services",
            "subcategory":"Doctor",
            "type":"Services"
        }
    ],
    "sg:phone":"+1   ",
    "sg:postcode":"08840",
    "sg:province":"NJ",
    "wof:name":"George E Ludwig DDS",
    "wof:placetype":"venue"
},
  "geometry": {"coordinates":[-74.36542300000001,40.547917],"type":"Point"}
}