{
  "type": "Feature",
  "properties": {
    "addr:full":"2 Maple Pl Fairfield NJ 07004",
    "addr:housenumber":"2",
    "addr:postcode":"07004",
    "addr:street":"Maple Pl",
    "iso:country":"US",
    "sg:address":"2 Maple Pl",
    "sg:city":"Fairfield",
    "sg:classifiers":[
        {
            "category":"Building & Trades",
            "subcategory":"Construction",
            "type":"Services"
        }
    ],
    "sg:phone":"+1 973 882 9519",
    "sg:postcode":"07004",
    "sg:province":"NJ",
    "sg:tags":[
        "house",
        "improvement",
        "home"
    ],
    "wof:name":"J & V Improvements",
    "wof:placetype":"venue"
},
  "geometry": {"coordinates":[-74.306325,40.869139],"type":"Point"}
}