{
  "type": "Feature",
  "properties": {
    "addr:full":"29 W Main St Morristown NJ 07960",
    "addr:housenumber":"29",
    "addr:postcode":"07960",
    "addr:street":"W Main St",
    "iso:country":"US",
    "sg:address":"29 W Main St",
    "sg:city":"Morristown",
    "sg:classifiers":[
        {
            "category":"Education",
            "subcategory":"Special Training",
            "type":"Public Place"
        }
    ],
    "sg:phone":"+1   ",
    "sg:postcode":"07960",
    "sg:province":"NJ",
    "sg:tags":[
        "a",
        "ctr",
        "for",
        "multimedia",
        "operates",
        "manages",
        "child"
    ],
    "wof:name":"Imagine Tomorrow",
    "wof:placetype":"venue"
},
  "geometry": {"coordinates":[-74.576607,40.793736],"type":"Point"}
}