{
  "type": "Feature",
  "properties": {
    "addr:full":"10 Charles St Cape May NJ 08204",
    "addr:housenumber":"10",
    "addr:postcode":"08204",
    "addr:street":"Charles St",
    "iso:country":"US",
    "sg:address":"10 Charles St",
    "sg:city":"Cape May",
    "sg:classifiers":[
        {
            "category":"Freight",
            "type":"Transportation"
        }
    ],
    "sg:phone":"+1 609 889 0553",
    "sg:postcode":"08204",
    "sg:province":"NJ",
    "sg:tags":[
        "operator",
        "trucking"
    ],
    "wof:name":"Cape Interstate Transport Inc",
    "wof:placetype":"venue"
},
  "geometry": {"coordinates":[-74.934138,38.99826],"type":"Point"}
}