{
  "type": "Feature",
  "properties": {
    "iso:country":"US",
    "sg:address":"214 Brick Blvd",
    "sg:city":"Brick",
    "sg:classifiers":[
        {
            "category":"Retail",
            "subcategory":"Auto Repair",
            "type":"Services"
        }
    ],
    "sg:phone":"+1 732 262 9300",
    "sg:postcode":"08723",
    "sg:province":"NJ",
    "sg:tags":[
        "repairing",
        "automobile"
    ],
    "wof:name":"Del Cap Automotive",
    "wof:placetype":"venue"
},
  "geometry": {"coordinates":[-74.143231,40.034294],"type":"Point"}
}