{
  "type": "Feature",
  "properties": {
    "addr:full":"2 Quakerbridge Plz Trenton NJ 08619",
    "addr:housenumber":"2",
    "addr:postcode":"08619",
    "addr:street":"Quakerbridge Plz",
    "iso:country":"US",
    "sg:address":"2 Quakerbridge Plz",
    "sg:city":"Trenton",
    "sg:classifiers":[
        {
            "category":"Organizations",
            "subcategory":"Professional Association",
            "type":"Services"
        }
    ],
    "sg:phone":"+1 609 584 5686",
    "sg:postcode":"08619",
    "sg:province":"NJ",
    "wof:name":"National Assn Social Wkrs I",
    "wof:placetype":"venue"
},
  "geometry": {"coordinates":[-74.681859,40.253488],"type":"Point"}
}