{
  "type": "Feature",
  "properties": {
    "iso:country":"US",
    "sg:address":"604 Bartholomew Rd",
    "sg:city":"Piscataway",
    "sg:classifiers":[
        {
            "category":"Restaurant",
            "type":"Food & Drink"
        }
    ],
    "sg:phone":"+1 732 463 1616",
    "sg:postcode":"08854",
    "sg:province":"NJ",
    "sg:tags":[
        "eating",
        "pizza"
    ],
    "sg:website":"http://www.wheatzzacorp.com",
    "wof:name":"Gerlandas Pizza",
    "wof:placetype":"venue"
},
  "geometry": {"coordinates":[-74.457359,40.520641],"type":"Point"}
}