{
  "type": "Feature",
  "properties": {
    "iso:country":"US",
    "sg:address":"180 Monmouth St",
    "sg:city":"Red Bank",
    "sg:classifiers":[
        {
            "category":"Bars & Pubs",
            "type":"Food & Drink"
        }
    ],
    "sg:menulink":"http://www.allmenus.com/nj/red-bank/282086-walt-street-pub/menu/",
    "sg:phone":"+1 732 741 5936",
    "sg:postcode":"07701",
    "sg:province":"NJ",
    "sg:tags":[
        "food",
        "american",
        "pub"
    ],
    "wof:name":"Walt Street Pub",
    "wof:placetype":"venue"
},
  "geometry": {"coordinates":[-74.074411,40.348939],"type":"Point"}
}