{
  "type": "Feature",
  "properties": {
    "addr:full":"2 Mitchell Ave Piscataway NJ 08854",
    "addr:housenumber":"2",
    "addr:postcode":"08854",
    "addr:street":"Mitchell Ave",
    "iso:country":"US",
    "sg:address":"2 Mitchell Ave",
    "sg:city":"Piscataway",
    "sg:classifiers":[
        {
            "category":"Health Services",
            "subcategory":"Doctor",
            "type":"Services"
        },
        {
            "category":"Health Services",
            "subcategory":"Podiatrist",
            "type":"Services"
        }
    ],
    "sg:phone":"+1 732 645 8144",
    "sg:postcode":"08854",
    "sg:province":"NJ",
    "sg:tags":[
        "physician",
        "surgeon",
        "pediatrics-orthopedics",
        "pediatrics",
        "surgeons"
    ],
    "sg:website":"http://www.yext.com/p/superpages/brandon-m-zuklie-dpm-piscataway-new-jersey.html",
    "wof:name":"Dr. Brandon M Zuklie DPM",
    "wof:placetype":"venue"
},
  "geometry": {"coordinates":[-74.48885300000001,40.52396],"type":"Point"}
}