{
  "type": "Feature",
  "properties": {
    "addr:full":"91 Baker Ave Bergenfield NJ 07621",
    "addr:housenumber":"91",
    "addr:postcode":"07621",
    "addr:street":"Baker Ave",
    "iso:country":"US",
    "sg:address":"91 Baker Ave",
    "sg:city":"Bergenfield",
    "sg:classifiers":[
        {
            "category":"Home & Garden",
            "subcategory":"Building Materials",
            "type":"Retail Goods"
        }
    ],
    "sg:phone":"+1   ",
    "sg:postcode":"07621",
    "sg:province":"NJ",
    "wof:name":"Mc Garry Ron Handy Home Guy",
    "wof:placetype":"venue"
},
  "geometry": {"coordinates":[-74.010497,40.91495],"type":"Point"}
}