{
  "type": "Feature",
  "properties": {
    "iso:country":"US",
    "sg:address":"1325 US Hwy 206",
    "sg:city":"Skillman",
    "sg:classifiers":[
        {
            "category":"Personal",
            "subcategory":"Barber",
            "type":"Services"
        }
    ],
    "sg:phone":"+1 609 921 8221",
    "sg:postcode":"08558",
    "sg:province":"NJ",
    "wof:name":"Colonial Barber Shop",
    "wof:placetype":"venue"
},
  "geometry": {"coordinates":[-74.649308,40.404101],"type":"Point"}
}