{
  "type": "Feature",
  "properties": {
    "addr:full":"114 W Main St Clinton NJ 08809",
    "addr:housenumber":"114",
    "addr:postcode":"08809",
    "addr:street":"W Main St",
    "iso:country":"US",
    "sg:address":"114 W Main St",
    "sg:city":"Clinton",
    "sg:classifiers":[
        {
            "category":"Professional",
            "subcategory":"Accounting & Tax Preparation",
            "type":"Services"
        }
    ],
    "sg:phone":"+1 908 735 0722",
    "sg:postcode":"08809",
    "sg:province":"NJ",
    "sg:tags":[
        "accountant"
    ],
    "wof:name":"Tanis & Co",
    "wof:placetype":"venue"
},
  "geometry": {"coordinates":[-74.920531,40.632726],"type":"Point"}
}