{
  "type": "Feature",
  "properties": {
    "addr:full":"22 Wall St West Long Branch NJ 07764",
    "addr:housenumber":"22",
    "addr:postcode":"07764",
    "addr:street":"Wall St",
    "iso:country":"US",
    "sg:address":"22 Wall St",
    "sg:city":"West Long Branch",
    "sg:classifiers":[
        {
            "category":"Food & Beverages",
            "subcategory":"Groceries & Convenience Stores",
            "type":"Retail Goods"
        }
    ],
    "sg:phone":"+1   ",
    "sg:postcode":"07764",
    "sg:province":"NJ",
    "wof:name":"Fairview Farms",
    "wof:placetype":"venue"
},
  "geometry": {"coordinates":[-74.001716,40.292819],"type":"Point"}
}