{
  "type": "Feature",
  "properties": {
    "addr:full":"3 Harbeson Ct Montville NJ 07045",
    "addr:housenumber":"3",
    "addr:postcode":"07045",
    "addr:street":"Harbeson Ct",
    "iso:country":"US",
    "sg:address":"3 Harbeson Ct",
    "sg:city":"Montville",
    "sg:classifiers":[
        {
            "category":"Real Estate",
            "subcategory":"Real Estate Agent",
            "type":"Services"
        },
        {
            "category":"Real Estate",
            "subcategory":"Real Estate Operator",
            "type":"Services"
        }
    ],
    "sg:phone":"+1 973 335 2135",
    "sg:postcode":"07045",
    "sg:province":"NJ",
    "sg:tags":[
        "building",
        "communication",
        "apartment",
        "management",
        "mfg"
    ],
    "wof:name":"Green Brook Plaza Inc",
    "wof:placetype":"venue"
},
  "geometry": {"coordinates":[-74.36100399999999,40.90432],"type":"Point"}
}