{
  "type": "Feature",
  "properties": {
    "iso:country":"US",
    "sg:address":"348 Union Ave",
    "sg:city":"Paterson",
    "sg:classifiers":[
        {
            "category":"Restaurant",
            "type":"Food & Drink"
        }
    ],
    "sg:phone":"+1 973 595 6969",
    "sg:postcode":"07502",
    "sg:province":"NJ",
    "sg:tags":[
        "eating",
        "chinese"
    ],
    "wof:name":"Yee Kee Chinese Restaurant",
    "wof:placetype":"venue"
},
  "geometry": {"coordinates":[-74.18759900000001,40.919498],"type":"Point"}
}