{
  "type": "Feature",
  "properties": {
    "addr:full":"20 Old Salem Rd Woodstown NJ 08098",
    "addr:housenumber":"20",
    "addr:postcode":"08098",
    "addr:street":"Old Salem Rd",
    "iso:country":"US",
    "sg:address":"20 Old Salem Rd",
    "sg:city":"Woodstown",
    "sg:classifiers":[
        {
            "category":"Home & Garden",
            "subcategory":"Building Materials",
            "type":"Retail Goods"
        },
        {
            "category":"Home & Garden",
            "subcategory":"Furniture",
            "type":"Retail Goods"
        }
    ],
    "sg:phone":"+1 856 769 2539",
    "sg:postcode":"08098",
    "sg:province":"NJ",
    "sg:tags":[
        "item",
        "appliance",
        "cabinetry",
        "bath",
        "equipment",
        "related",
        "cabinet",
        "kitchen"
    ],
    "sg:website":"www.matteokitchens.com",
    "wof:name":"Matteo Family Kitchens & Flrg",
    "wof:placetype":"venue"
},
  "geometry": {"coordinates":[-75.33179,39.641952],"type":"Point"}
}