{
  "type": "Feature",
  "properties": {
    "addr:full":"1 Leigh Ave Princeton NJ 08542",
    "addr:housenumber":"1",
    "addr:postcode":"08542",
    "addr:street":"Leigh Ave",
    "iso:country":"US",
    "sg:address":"1 Leigh Ave",
    "sg:city":"Princeton",
    "sg:classifiers":[
        {
            "category":"Professional",
            "subcategory":"Business Services",
            "type":"Services"
        }
    ],
    "sg:phone":"+1 609 924 8188",
    "sg:postcode":"08542",
    "sg:province":"NJ",
    "sg:tags":[
        "broker"
    ],
    "sg:website":"www.cfaw.com",
    "wof:name":"Corporate Finance Assoc",
    "wof:placetype":"venue"
},
  "geometry": {"coordinates":[-74.664866,40.356097],"type":"Point"}
}