{
  "type": "Feature",
  "properties": {
    "addr:full":"18 S Talmadge St New Brunswick NJ 08901",
    "addr:housenumber":"18",
    "addr:postcode":"08901",
    "addr:street":"S Talmadge St",
    "iso:country":"US",
    "sg:address":"18 S Talmadge St",
    "sg:city":"New Brunswick",
    "sg:classifiers":[
        {
            "category":"Building & Trades",
            "subcategory":"Pest Control",
            "type":"Services"
        }
    ],
    "sg:phone":"+1 732 249 6357",
    "sg:postcode":"08901",
    "sg:province":"NJ",
    "wof:name":"East Coast Exterminators",
    "wof:placetype":"venue"
},
  "geometry": {"coordinates":[-74.444945,40.478062],"type":"Point"}
}