{
  "type": "Feature",
  "properties": {
    "iso:country":"US",
    "sg:address":"21 Grayson Pl",
    "sg:city":"Burlington",
    "sg:classifiers":[
        {
            "category":"Building & Trades",
            "subcategory":"Landscaping Services",
            "type":"Services"
        }
    ],
    "sg:phone":"+1 609 386 6153",
    "sg:postcode":"08016",
    "sg:province":"NJ",
    "sg:tags":[
        "landscape"
    ],
    "wof:name":"Vandenberg Landscaping",
    "wof:placetype":"venue"
},
  "geometry": {"coordinates":[-74.88381699999999,40.066058],"type":"Point"}
}