{
  "type": "Feature",
  "properties": {
    "addr:full":"111 Terrill Rd Plainfield NJ 07062",
    "addr:housenumber":"111",
    "addr:postcode":"07062",
    "addr:street":"Terrill Rd",
    "iso:country":"US",
    "sg:address":"111 Terrill Rd",
    "sg:city":"Plainfield",
    "sg:classifiers":[
        {
            "category":"Retail",
            "subcategory":"Repair Shop",
            "type":"Services"
        }
    ],
    "sg:phone":"+1 908 372 6963",
    "sg:postcode":"07062",
    "sg:province":"NJ",
    "sg:tags":[
        "lock",
        "locksmith"
    ],
    "wof:name":"USA Locksmith",
    "wof:placetype":"venue"
},
  "geometry": {"coordinates":[-74.408264,40.644185],"type":"Point"}
}