{
  "type": "Feature",
  "properties": {
    "addr:full":"453 Closter Dock Rd Closter NJ 07624",
    "addr:housenumber":"453",
    "addr:postcode":"07624",
    "addr:street":"Closter Dock Rd",
    "iso:country":"US",
    "sg:address":"453 Closter Dock Rd",
    "sg:city":"Closter",
    "sg:classifiers":[
        {
            "category":"Retail",
            "subcategory":"Self-service Laundry",
            "type":"Services"
        }
    ],
    "sg:phone":"+1 201 261 9608",
    "sg:postcode":"07624",
    "sg:province":"NJ",
    "sg:tags":[
        "coin"
    ],
    "wof:name":"Emerson Speed Wash",
    "wof:placetype":"venue"
},
  "geometry": {"coordinates":[-73.956318,40.966527],"type":"Point"}
}