{
  "type": "Feature",
  "properties": {
    "addr:full":"301 Arrowhead Park Dr Brick NJ 08724",
    "addr:housenumber":"301",
    "addr:postcode":"08724",
    "addr:street":"Arrowhead Park Dr",
    "iso:country":"US",
    "sg:address":"301 Arrowhead Park Dr",
    "sg:city":"Brick",
    "sg:classifiers":[
        {
            "category":"Professional",
            "type":"Services"
        }
    ],
    "sg:phone":"+1   ",
    "sg:postcode":"08724",
    "sg:province":"NJ",
    "wof:name":"Albert Lonzak",
    "wof:placetype":"venue"
},
  "geometry": {"coordinates":[-74.09942599999999,40.069511],"type":"Point"}
}