{
  "type": "Feature",
  "properties": {
    "iso:country":"US",
    "sg:address":"763 Ramsey Ave",
    "sg:city":"Hillside",
    "sg:classifiers":[
        {
            "category":"Manufacturing",
            "subcategory":"Printing",
            "type":"Manufacturing & Wholesale Goods"
        }
    ],
    "sg:phone":"+1 908 686 1479",
    "sg:postcode":"07205",
    "sg:province":"NJ",
    "sg:tags":[
        "engraver"
    ],
    "wof:name":"All American Graphic Art Co",
    "wof:placetype":"venue"
},
  "geometry": {"coordinates":[-74.233048,40.708546],"type":"Point"}
}