{
  "type": "Feature",
  "properties": {
    "iso:country":"US",
    "sg:address":"264 Washington Ave",
    "sg:city":"Kenilworth",
    "sg:classifiers":[
        {
            "category":"Retail",
            "subcategory":"Repair Shop",
            "type":"Services"
        }
    ],
    "sg:phone":"+1   ",
    "sg:postcode":"07033",
    "sg:province":"NJ",
    "wof:name":"Phillips Piano Service",
    "wof:placetype":"venue"
},
  "geometry": {"coordinates":[-74.30340099999999,40.677037],"type":"Point"}
}