{
  "type": "Feature",
  "properties": {
    "addr:full":"1 N Union St Lambertville NJ 08530",
    "addr:housenumber":"1",
    "addr:postcode":"08530",
    "addr:street":"N Union St",
    "iso:country":"US",
    "sg:address":"1 N Union St",
    "sg:city":"Lambertville",
    "sg:classifiers":[
        {
            "category":"Food & Beverages",
            "subcategory":"Liquor & Beverages",
            "type":"Retail Goods"
        }
    ],
    "sg:phone":"+1 609 397 5577",
    "sg:postcode":"08530",
    "sg:province":"NJ",
    "sg:tags":[
        "alcoholic",
        "mfg"
    ],
    "wof:name":"Tomasello Winery Inc",
    "wof:placetype":"venue"
},
  "geometry": {"coordinates":[-74.945167,40.366713],"type":"Point"}
}