{
  "type": "Feature",
  "properties": {
    "addr:full":"2210 Kerrigan Ave Union City NJ 07087",
    "addr:housenumber":"2210",
    "addr:postcode":"07087",
    "addr:street":"Kerrigan Ave",
    "iso:country":"US",
    "sg:address":"2210 Kerrigan Ave",
    "sg:city":"Union City",
    "sg:classifiers":[
        {
            "category":"Restaurant",
            "type":"Food & Drink"
        }
    ],
    "sg:phone":"+1   ",
    "sg:postcode":"07087",
    "sg:province":"NJ",
    "sg:tags":[
        "drinking",
        "eating"
    ],
    "wof:name":"Louis Restaurant Inc",
    "wof:placetype":"venue"
},
  "geometry": {"coordinates":[-74.03783900000001,40.769144],"type":"Point"}
}