{
  "type": "Feature",
  "properties": {
    "iso:country":"US",
    "sg:address":"109 Washington Valley Rd",
    "sg:city":"Warren",
    "sg:classifiers":[
        {
            "category":"Social Services",
            "subcategory":"Child Care",
            "type":"Services"
        }
    ],
    "sg:phone":"+1 732 560 5610",
    "sg:postcode":"07059",
    "sg:province":"NJ",
    "sg:tags":[
        "kindergarten",
        "academic",
        "school"
    ],
    "wof:name":"P & P Pumpkin Patch",
    "wof:placetype":"venue"
},
  "geometry": {"coordinates":[-74.516862,40.604681],"type":"Point"}
}