{
  "type": "Feature",
  "properties": {
    "addr:full":"90 Monmouth St Red Bank NJ 07701",
    "addr:housenumber":"90",
    "addr:postcode":"07701",
    "addr:street":"Monmouth St",
    "iso:country":"US",
    "sg:address":"90 Monmouth St",
    "sg:city":"Red Bank",
    "sg:classifiers":[
        {
            "category":"Government",
            "subcategory":"Office",
            "type":"Public Place"
        }
    ],
    "sg:phone":"+1 732 530 2769",
    "sg:postcode":"07701",
    "sg:province":"NJ",
    "sg:tags":[
        "city",
        "resource",
        "human"
    ],
    "wof:name":"Red Bank Welfare Dept",
    "wof:placetype":"venue"
},
  "geometry": {"coordinates":[-74.070973,40.349125],"type":"Point"}
}