{
  "type": "Feature",
  "properties": {
    "addr:full":"927 Boulevard Westfield NJ 07090",
    "addr:housenumber":"927",
    "addr:postcode":"07090",
    "addr:street":"Boulevard",
    "iso:country":"US",
    "sg:address":"927 Boulevard",
    "sg:city":"Westfield",
    "sg:classifiers":[
        {
            "category":"Wholesale",
            "subcategory":"Chemicals & Plastics",
            "type":"Manufacturing & Wholesale Goods"
        }
    ],
    "sg:phone":"+1 908 233 2521",
    "sg:postcode":"07090",
    "sg:province":"NJ",
    "wof:name":"Robert J Trout and Associates",
    "wof:placetype":"venue"
},
  "geometry": {"coordinates":[-74.333136,40.64052],"type":"Point"}
}