{
  "type": "Feature",
  "properties": {
    "addr:full":"92 Albany St New Brunswick NJ 08901",
    "addr:housenumber":"92",
    "addr:postcode":"08901",
    "addr:street":"Albany St",
    "iso:country":"US",
    "sg:address":"92 Albany St",
    "sg:city":"New Brunswick",
    "sg:classifiers":[
        {
            "category":"Shopping",
            "subcategory":"Jewelry",
            "type":"Retail Goods"
        }
    ],
    "sg:phone":"+1   ",
    "sg:postcode":"08901",
    "sg:province":"NJ",
    "wof:name":"Daddario Fine Jwlers Gmlogists",
    "wof:placetype":"venue"
},
  "geometry": {"coordinates":[-74.443667,40.496831],"type":"Point"}
}