{
  "type": "Feature",
  "properties": {
    "iso:country":"US",
    "sg:address":"723 N Beers St",
    "sg:city":"Holmdel",
    "sg:classifiers":[
        {
            "category":"Health Services",
            "subcategory":"Doctor",
            "type":"Services"
        }
    ],
    "sg:phone":"+1 732 577 1999",
    "sg:postcode":"07733",
    "sg:province":"NJ",
    "sg:tags":[
        "physician",
        "surgeon"
    ],
    "wof:name":"Middlesex-Monmouth Gstrntrlgy",
    "wof:placetype":"venue"
},
  "geometry": {"coordinates":[-74.19517399999999,40.410514],"type":"Point"}
}