{
  "type": "Feature",
  "properties": {
    "addr:full":"294 N Church Rd Sparta NJ 07871",
    "addr:housenumber":"294",
    "addr:postcode":"07871",
    "addr:street":"N Church Rd",
    "iso:country":"US",
    "sg:address":"294 N Church Rd",
    "sg:city":"Sparta",
    "sg:classifiers":[
        {
            "category":"Restaurant",
            "type":"Food & Drink"
        }
    ],
    "sg:phone":"+1   ",
    "sg:postcode":"07871",
    "sg:province":"NJ",
    "sg:tags":[
        "eating"
    ],
    "wof:name":"Homestead Rest",
    "wof:placetype":"venue"
},
  "geometry": {"coordinates":[-74.642737,41.106389],"type":"Point"}
}