{
  "type": "Feature",
  "properties": {
    "addr:full":"3919 Bergenline Ave Union City NJ 07087",
    "addr:housenumber":"3919",
    "addr:postcode":"07087",
    "addr:street":"Bergenline Ave",
    "iso:country":"US",
    "sg:address":"3919 Bergenline Ave",
    "sg:city":"Union City",
    "sg:classifiers":[
        {
            "category":"Shopping",
            "subcategory":"Music",
            "type":"Retail Goods"
        }
    ],
    "sg:phone":"+1 201 865 8606",
    "sg:postcode":"07087",
    "sg:province":"NJ",
    "sg:tags":[
        "compact",
        "record",
        "disc",
        "tape"
    ],
    "wof:name":"Natalie Records Inc",
    "wof:placetype":"venue"
},
  "geometry": {"coordinates":[-74.02606299999999,40.776273],"type":"Point"}
}