{
  "type": "Feature",
  "properties": {
    "addr:full":"9 Pleasant Ave Upper Saddle Rvr NJ 07458",
    "addr:housenumber":"9",
    "addr:postcode":"07458",
    "addr:street":"Pleasant Ave Upper Saddle Rvr",
    "iso:country":"US",
    "sg:address":"9 Pleasant Ave",
    "sg:city":"Upper Saddle Rvr",
    "sg:classifiers":[
        {
            "category":"Professional",
            "subcategory":"Management & Consulting",
            "type":"Services"
        }
    ],
    "sg:phone":"+1 201 934 6058",
    "sg:postcode":"07458",
    "sg:province":"NJ",
    "sg:tags":[
        "marketing",
        "consultant"
    ],
    "wof:name":"Roger S Denu & Assoc Inc",
    "wof:placetype":"venue"
},
  "geometry": {"coordinates":[-74.103522,41.048769],"type":"Point"}
}