{
  "type": "Feature",
  "properties": {
    "addr:full":"41 Smith St Englewood NJ 07631",
    "addr:housenumber":"41",
    "addr:postcode":"07631",
    "addr:street":"Smith St",
    "iso:country":"US",
    "sg:address":"41 Smith St",
    "sg:city":"Englewood",
    "sg:classifiers":[
        {
            "category":"Professional",
            "subcategory":"Management & Consulting",
            "type":"Services"
        }
    ],
    "sg:phone":"+1 201 296 0913",
    "sg:postcode":"07631",
    "sg:province":"NJ",
    "sg:tags":[
        "marketing",
        "consultant"
    ],
    "wof:name":"Komax International Inc",
    "wof:placetype":"venue"
},
  "geometry": {"coordinates":[-73.98245199999999,40.884965],"type":"Point"}
}