{
  "type": "Feature",
  "properties": {
    "addr:full":"6 Furler St Totowa NJ 07512",
    "addr:housenumber":"6",
    "addr:postcode":"07512",
    "addr:street":"Furler St",
    "iso:country":"US",
    "sg:address":"6 Furler St",
    "sg:city":"Totowa",
    "sg:classifiers":[
        {
            "category":"Professional",
            "subcategory":"Accounting & Tax Preparation",
            "type":"Services"
        }
    ],
    "sg:phone":"+1 973 785 4088",
    "sg:postcode":"07512",
    "sg:province":"NJ",
    "sg:tags":[
        "accountant"
    ],
    "wof:name":"R J Iuso & Co",
    "wof:placetype":"venue"
},
  "geometry": {"coordinates":[-74.225601,40.895302],"type":"Point"}
}