{
  "type": "Feature",
  "properties": {
    "iso:country":"US",
    "sg:address":"490 State Route 27",
    "sg:city":"Iselin",
    "sg:classifiers":[
        {
            "category":"Building & Trades",
            "subcategory":"Locksmith",
            "type":"Services"
        }
    ],
    "sg:phone":"+1 732 839 2858",
    "sg:postcode":"08830",
    "sg:province":"NJ",
    "sg:tags":[
        "key"
    ],
    "wof:name":"1 24 Hour 7 Day Emerg A Lock A Locksmith",
    "wof:placetype":"venue"
},
  "geometry": {"coordinates":[-74.318568,40.575102],"type":"Point"}
}