{
  "type": "Feature",
  "properties": {
    "iso:country":"US",
    "sg:address":"11 Sunnydale Dr",
    "sg:city":"Brick",
    "sg:classifiers":[
        {
            "category":"Retail",
            "subcategory":"Animal Services",
            "type":"Services"
        }
    ],
    "sg:phone":"+1 732 864 0888",
    "sg:postcode":"08723",
    "sg:province":"NJ",
    "wof:name":"Doggie Treats Mobile Grooming",
    "wof:placetype":"venue"
},
  "geometry": {"coordinates":[-74.133179,40.019943],"type":"Point"}
}