{
  "type": "Feature",
  "properties": {
    "iso:country":"US",
    "sg:address":"26 Van Brackle Rd",
    "sg:city":"Holmdel",
    "sg:classifiers":[
        {
            "category":"Professional",
            "subcategory":"Business Services",
            "type":"Services"
        }
    ],
    "sg:phone":"+1 732 264 6532",
    "sg:postcode":"07733",
    "sg:province":"NJ",
    "sg:tags":[
        "auctioneer"
    ],
    "wof:name":"B & M Auctioneers",
    "wof:placetype":"venue"
},
  "geometry": {"coordinates":[-74.200379,40.389689],"type":"Point"}
}