{
  "type": "Feature",
  "properties": {
    "iso:country":"US",
    "sg:address":"116 Old Post Rd",
    "sg:city":"Freehold",
    "sg:classifiers":[
        {
            "category":"Wholesale",
            "subcategory":"Stationery",
            "type":"Manufacturing & Wholesale Goods"
        }
    ],
    "sg:phone":"+1 732 780 5872",
    "sg:postcode":"07728",
    "sg:province":"NJ",
    "sg:tags":[
        "paper"
    ],
    "wof:name":"Edlo Sales Corp",
    "wof:placetype":"venue"
},
  "geometry": {"coordinates":[-74.278521,40.227935],"type":"Point"}
}