{
  "type": "Feature",
  "properties": {
    "iso:country":"US",
    "sg:address":"466 Bloomfield Ave",
    "sg:city":"Newark",
    "sg:classifiers":[
        {
            "category":"Real Estate",
            "subcategory":"Real Estate Agent",
            "type":"Services"
        }
    ],
    "sg:phone":"+1 973 412 9110",
    "sg:postcode":"07107",
    "sg:province":"NJ",
    "sg:website":"www.remax.com",
    "wof:name":"Re/Max Reliable",
    "wof:placetype":"venue"
},
  "geometry": {"coordinates":[-74.184363,40.771736],"type":"Point"}
}