{
  "type": "Feature",
  "properties": {
    "iso:country":"US",
    "sg:address":"111 Elm Ave",
    "sg:city":"Newton",
    "sg:classifiers":[
        {
            "category":"Communications",
            "subcategory":"Film & Video Production",
            "type":"Services"
        }
    ],
    "sg:phone":"+1 973 786 5191",
    "sg:postcode":"07860",
    "sg:province":"NJ",
    "sg:tags":[
        "motion"
    ],
    "wof:name":"Micki Sellers Productions",
    "wof:placetype":"venue"
},
  "geometry": {"coordinates":[-74.725582,41.008235],"type":"Point"}
}