{
  "type": "Feature",
  "properties": {
    "iso:country":"US",
    "sg:address":"36 Church Rd",
    "sg:city":"Maple Shade",
    "sg:classifiers":[
        {
            "category":"Retail",
            "subcategory":"Auto Rental",
            "type":"Services"
        }
    ],
    "sg:phone":"+1   ",
    "sg:postcode":"08054",
    "sg:province":"NJ",
    "sg:tags":[
        "passenger",
        "leasing",
        "car"
    ],
    "wof:name":"G&G Auto Leasing Inc",
    "wof:placetype":"venue"
},
  "geometry": {"coordinates":[-74.980206,39.930922],"type":"Point"}
}