{
  "type": "Feature",
  "properties": {
    "addr:full":"151 E Crescent Ave Allendale NJ 07401",
    "addr:housenumber":"151",
    "addr:postcode":"07401",
    "addr:street":"E Crescent Ave",
    "iso:country":"US",
    "sg:address":"151 E Crescent Ave",
    "sg:city":"Allendale",
    "sg:classifiers":[
        {
            "category":"Manufacturing",
            "subcategory":"Paper Products",
            "type":"Manufacturing & Wholesale Goods"
        }
    ],
    "sg:phone":"+1 201 327 2083",
    "sg:postcode":"07401",
    "sg:province":"NJ",
    "sg:tags":[
        "box"
    ],
    "wof:name":"Mod Pak Inc",
    "wof:placetype":"venue"
},
  "geometry": {"coordinates":[-74.126718,41.0448],"type":"Point"}
}