{
  "type": "Feature",
  "properties": {
    "iso:country":"US",
    "sg:address":"135 County Rd",
    "sg:city":"Cresskill",
    "sg:classifiers":[
        {
            "category":"Health Services",
            "subcategory":"Doctor",
            "type":"Services"
        }
    ],
    "sg:phone":"+1 201 568 9393",
    "sg:postcode":"07626",
    "sg:province":"NJ",
    "sg:tags":[
        "dentist"
    ],
    "wof:name":"Rudolph J Streemke DDS",
    "wof:placetype":"venue"
},
  "geometry": {"coordinates":[-73.95746,40.939193],"type":"Point"}
}