{
  "type": "Feature",
  "properties": {
    "iso:country":"US",
    "sg:address":"39 Kitchell Ave",
    "sg:city":"Wharton",
    "sg:classifiers":[
        {
            "category":"Shopping",
            "subcategory":"Catalog Store",
            "type":"Retail Goods"
        }
    ],
    "sg:phone":"+1   ",
    "sg:postcode":"07885",
    "sg:province":"NJ",
    "sg:tags":[
        "house",
        "mail"
    ],
    "wof:name":"Wharton Business",
    "wof:placetype":"venue"
},
  "geometry": {"coordinates":[-74.576853,40.887454],"type":"Point"}
}