{
  "type": "Feature",
  "properties": {
    "addr:full":"369 Ege Ave Jersey City NJ 07304",
    "addr:housenumber":"369",
    "addr:postcode":"07304",
    "addr:street":"Ege Ave",
    "iso:country":"US",
    "sg:address":"369 Ege Ave",
    "sg:city":"Jersey City",
    "sg:classifiers":[
        {
            "category":"Building & Trades",
            "subcategory":"Cleaning & Sanitation",
            "type":"Services"
        }
    ],
    "sg:phone":"+1 201 432 7328",
    "sg:postcode":"07304",
    "sg:province":"NJ",
    "sg:tags":[
        "maintenance"
    ],
    "wof:name":"Cleaning Solutions Inc",
    "wof:placetype":"venue"
},
  "geometry": {"coordinates":[-74.091604,40.719004],"type":"Point"}
}