{
  "type": "Feature",
  "properties": {
    "addr:full":"734 Haddon Ave Collingswood NJ 08108",
    "addr:housenumber":"734",
    "addr:postcode":"08108",
    "addr:street":"Haddon Ave",
    "iso:country":"US",
    "sg:address":"734 Haddon Ave",
    "sg:city":"Collingswood",
    "sg:classifiers":[
        {
            "category":"Personal",
            "subcategory":"Nail Salon",
            "type":"Services"
        }
    ],
    "sg:phone":"+1 856 858 0150",
    "sg:postcode":"08108",
    "sg:province":"NJ",
    "wof:name":"Pampered Nail & Spa",
    "wof:placetype":"venue"
},
  "geometry": {"coordinates":[-75.067939,39.915797],"type":"Point"}
}