{
  "type": "Feature",
  "properties": {
    "iso:country":"US",
    "sg:address":"34 Eagle Ave",
    "sg:city":"Paterson",
    "sg:classifiers":[
        {
            "category":"Local Transit",
            "type":"Transportation"
        }
    ],
    "sg:phone":"+1 973 977 8528",
    "sg:postcode":"07503",
    "sg:province":"NJ",
    "sg:tags":[
        "limousine"
    ],
    "wof:name":"Signature Rental Limo Svc",
    "wof:placetype":"venue"
},
  "geometry": {"coordinates":[-74.15536299999999,40.889454],"type":"Point"}
}