{
  "type": "Feature",
  "properties": {
    "addr:full":"54 Fairview Ave Woodcliff Lake NJ 07675",
    "addr:housenumber":"54",
    "addr:postcode":"07675",
    "addr:street":"Fairview Ave",
    "iso:country":"US",
    "sg:address":"54 Fairview Ave",
    "sg:city":"Woodcliff Lake",
    "sg:classifiers":[
        {
            "category":"Health Services",
            "subcategory":"Doctor",
            "type":"Services"
        }
    ],
    "sg:phone":"+1 201 391 8866",
    "sg:postcode":"07675",
    "sg:province":"NJ",
    "sg:tags":[
        "physician",
        "surgeon"
    ],
    "wof:name":"Leonard S Rosen MD",
    "wof:placetype":"venue"
},
  "geometry": {"coordinates":[-74.029391,40.990361],"type":"Point"}
}