{
  "type": "Feature",
  "properties": {
    "iso:country":"US",
    "sg:address":"208 Dickens Dr",
    "sg:city":"Delran",
    "sg:classifiers":[
        {
            "category":"Wholesale",
            "subcategory":"Machinery & Supplies",
            "type":"Manufacturing & Wholesale Goods"
        }
    ],
    "sg:phone":"+1 856 764 7050",
    "sg:postcode":"08075",
    "sg:province":"NJ",
    "sg:tags":[
        "packaging",
        "equipment",
        "industrial"
    ],
    "wof:name":"Cal-Pak Inc",
    "wof:placetype":"venue"
},
  "geometry": {"coordinates":[-74.967001,40.004754],"type":"Point"}
}