{
  "type": "Feature",
  "properties": {
    "iso:country":"US",
    "sg:address":"200 Mathis Dr",
    "sg:city":"Tuckerton",
    "sg:classifiers":[
        {
            "category":"Cinema",
            "subcategory":"Movie Rental",
            "type":"Entertainment"
        }
    ],
    "sg:phone":"+1   ",
    "sg:postcode":"08087",
    "sg:province":"NJ",
    "sg:tags":[
        "video",
        "tape"
    ],
    "wof:name":"Hometown Video Inc",
    "wof:placetype":"venue"
},
  "geometry": {"coordinates":[-74.35052399999999,39.603597],"type":"Point"}
}