{
  "type": "Feature",
  "properties": {
    "addr:full":"101 Carnie Blvd Voorhees NJ 08043",
    "addr:housenumber":"101",
    "addr:postcode":"08043",
    "addr:street":"Carnie Blvd",
    "iso:country":"US",
    "sg:address":"101 Carnie Blvd",
    "sg:city":"Voorhees",
    "sg:classifiers":[
        {
            "category":"Restaurant",
            "type":"Food & Drink"
        }
    ],
    "sg:phone":"+1   ",
    "sg:postcode":"08043",
    "sg:province":"NJ",
    "sg:tags":[
        "contract"
    ],
    "wof:name":"Sodexho Inc",
    "wof:placetype":"venue"
},
  "geometry": {"coordinates":[-74.958595,39.863678],"type":"Point"}
}