{
  "type": "Feature",
  "properties": {
    "iso:country":"US",
    "sg:address":"304 Glenwood Ave",
    "sg:city":"Leonia",
    "sg:classifiers":[
        {
            "category":"Organizations",
            "subcategory":"Religious Organization",
            "type":"Services"
        }
    ],
    "sg:phone":"+1 201 947 0422",
    "sg:postcode":"07605",
    "sg:province":"NJ",
    "sg:website":"www.truelight.net",
    "wof:name":"True Light Presbyterian Church",
    "wof:placetype":"venue"
},
  "geometry": {"coordinates":[-73.98248700000001,40.864724],"type":"Point"}
}