{
  "type": "Feature",
  "properties": {
    "addr:full":"5315 Atlantic Ave Ventnor City NJ 08406",
    "addr:housenumber":"5315",
    "addr:postcode":"08406",
    "addr:street":"Atlantic Ave",
    "iso:country":"US",
    "sg:address":"5315 Atlantic Ave",
    "sg:city":"Ventnor City",
    "sg:classifiers":[
        {
            "category":"Banks & Credit Unions",
            "subcategory":"Bank",
            "type":"Services"
        }
    ],
    "sg:phone":"+1 609 487 6300",
    "sg:postcode":"08406",
    "sg:province":"NJ",
    "sg:tags":[
        "loan",
        "real estate"
    ],
    "wof:name":"Liberty Mortgage Svc Inc",
    "wof:placetype":"venue"
},
  "geometry": {"coordinates":[-74.471684,39.341501],"type":"Point"}
}