{
  "type": "Feature",
  "properties": {
    "iso:country":"US",
    "sg:address":"1400 Willowbrook Mall",
    "sg:city":"Wayne",
    "sg:classifiers":[
        {
            "category":"Shopping",
            "subcategory":"Shoes",
            "type":"Retail Goods"
        }
    ],
    "sg:phone":"+1 973 890 8771",
    "sg:postcode":"07470",
    "sg:province":"NJ",
    "sg:tags":[
        "store"
    ],
    "wof:name":"Crocs",
    "wof:placetype":"venue"
},
  "geometry": {"coordinates":[-74.26127700000001,40.890664],"type":"Point"}
}