{
  "type": "Feature",
  "properties": {
    "iso:country":"US",
    "sg:address":"201 Ward St",
    "sg:city":"New Brunswick",
    "sg:classifiers":[
        {
            "category":"Manufacturing",
            "subcategory":"Chemicals & Compounds",
            "type":"Manufacturing & Wholesale Goods"
        }
    ],
    "sg:phone":"+1 732 247 8969",
    "sg:postcode":"08901",
    "sg:province":"NJ",
    "sg:tags":[
        "agricultural",
        "product"
    ],
    "wof:name":"Ralph D Pittman",
    "wof:placetype":"venue"
},
  "geometry": {"coordinates":[-74.454409,40.483112],"type":"Point"}
}