{
  "type": "Feature",
  "properties": {
    "iso:country":"US",
    "sg:address":"1633 State Rte 27",
    "sg:city":"Edison",
    "sg:classifiers":[
        {
            "category":"Personal",
            "subcategory":"Beauty Salon",
            "type":"Services"
        }
    ],
    "sg:phone":"+1 732 985 6768",
    "sg:postcode":"08817",
    "sg:province":"NJ",
    "wof:name":"Sabrina's Hair & Nail",
    "wof:placetype":"venue"
},
  "geometry": {"coordinates":[-74.41027699999999,40.50964],"type":"Point"}
}