{
  "type": "Feature",
  "properties": {
    "addr:full":"130 State Rte 73 West Berlin NJ 08091",
    "addr:housenumber":"130",
    "addr:postcode":"08091",
    "addr:street":"State Rte 73",
    "iso:country":"US",
    "sg:address":"130 State Rte 73",
    "sg:city":"West Berlin",
    "sg:classifiers":[
        {
            "category":"Autos & Motor Vehicles",
            "subcategory":"Auto Supplies",
            "type":"Retail Goods"
        }
    ],
    "sg:phone":"+1   ",
    "sg:postcode":"08091",
    "sg:province":"NJ",
    "sg:tags":[
        "tire"
    ],
    "wof:name":"Morgan Tire & Auto Inc",
    "wof:placetype":"venue"
},
  "geometry": {"coordinates":[-74.930802,39.809422],"type":"Point"}
}