{
  "type": "Feature",
  "properties": {
    "addr:full":"261 Shrewsbury Ave Red Bank NJ 07701",
    "addr:housenumber":"261",
    "addr:postcode":"07701",
    "addr:street":"Shrewsbury Ave",
    "iso:country":"US",
    "sg:address":"261 Shrewsbury Ave",
    "sg:city":"Red Bank",
    "sg:classifiers":[
        {
            "category":"Organizations",
            "subcategory":"Religious Organization",
            "type":"Services"
        }
    ],
    "sg:phone":"+1 732 933 5558",
    "sg:postcode":"07701",
    "sg:province":"NJ",
    "sg:tags":[
        "spiritualist"
    ],
    "wof:name":"Botanica Cachita",
    "wof:placetype":"venue"
},
  "geometry": {"coordinates":[-74.075457,40.341446],"type":"Point"}
}