{
  "type": "Feature",
  "properties": {
    "addr:full":"171 Main St South River NJ 08882",
    "addr:housenumber":"171",
    "addr:postcode":"08882",
    "addr:street":"Main St",
    "iso:country":"US",
    "sg:address":"171 Main St",
    "sg:city":"South River",
    "sg:classifiers":[
        {
            "category":"Local Transit",
            "type":"Transportation"
        }
    ],
    "sg:phone":"+1 732 257 6252",
    "sg:postcode":"08882",
    "sg:province":"NJ",
    "sg:tags":[
        "ambulance"
    ],
    "wof:name":"Ace Ambulance Svc",
    "wof:placetype":"venue"
},
  "geometry": {"coordinates":[-74.384856,40.44762],"type":"Point"}
}