{
  "type": "Feature",
  "properties": {
    "addr:full":"111 Riptide Ave Manahawkin NJ 08050",
    "addr:housenumber":"111",
    "addr:postcode":"08050",
    "addr:street":"Riptide Ave",
    "iso:country":"US",
    "sg:address":"111 Riptide Ave",
    "sg:city":"Manahawkin",
    "sg:classifiers":[
        {
            "category":"Personal",
            "type":"Services"
        }
    ],
    "sg:phone":"+1   ",
    "sg:postcode":"08050",
    "sg:province":"NJ",
    "wof:name":"Rons Handyman Service",
    "wof:placetype":"venue"
},
  "geometry": {"coordinates":[-74.280158,39.722193],"type":"Point"}
}