{
  "type": "Feature",
  "properties": {
    "iso:country":"US",
    "sg:address":"8001 US Hwy 130",
    "sg:city":"Delran",
    "sg:classifiers":[
        {
            "category":"Wholesale",
            "subcategory":"Electrical",
            "type":"Manufacturing & Wholesale Goods"
        }
    ],
    "sg:phone":"+1 856 764 1042",
    "sg:postcode":"08075",
    "sg:province":"NJ",
    "sg:tags":[
        "equipment",
        "electric",
        "supply"
    ],
    "wof:name":"Fox Electric Supply Co",
    "wof:placetype":"venue"
},
  "geometry": {"coordinates":[-74.937252,40.02512],"type":"Point"}
}