{
  "type": "Feature",
  "properties": {
    "addr:full":"166 Changewater Rd Long Valley NJ 07853",
    "addr:housenumber":"166",
    "addr:postcode":"07853",
    "addr:street":"Changewater Rd",
    "iso:country":"US",
    "sg:address":"166 Changewater Rd",
    "sg:city":"Long Valley",
    "sg:classifiers":[
        {
            "category":"Home & Garden",
            "subcategory":"Garden Supply",
            "type":"Retail Goods"
        }
    ],
    "sg:phone":"+1 908 689 0793",
    "sg:postcode":"07853",
    "sg:province":"NJ",
    "sg:tags":[
        "nursery",
        "gardening"
    ],
    "sg:website":"www.dutchvalleytreefarm.com",
    "wof:name":"Dutch Valley Tree Farm",
    "wof:placetype":"venue"
},
  "geometry": {"coordinates":[-74.804199,40.786201],"type":"Point"}
}