{
  "type": "Feature",
  "properties": {
    "addr:full":"7 Glenwood Pl Pennsville NJ 08070",
    "addr:housenumber":"7",
    "addr:postcode":"08070",
    "addr:street":"Glenwood Pl",
    "iso:country":"US",
    "sg:address":"7 Glenwood Pl",
    "sg:city":"Pennsville",
    "sg:classifiers":[
        {
            "category":"Health Services",
            "subcategory":"Podiatrist",
            "type":"Services"
        }
    ],
    "sg:phone":"+1 856 678 4550",
    "sg:postcode":"08070",
    "sg:province":"NJ",
    "wof:name":"Raymond A Rivell DPM",
    "wof:placetype":"venue"
},
  "geometry": {"coordinates":[-75.516768,39.657632],"type":"Point"}
}