{
  "type": "Feature",
  "properties": {
    "addr:full":"6 Heron Ct Plainsboro NJ 08536",
    "addr:housenumber":"6",
    "addr:postcode":"08536",
    "addr:street":"Heron Ct",
    "iso:country":"US",
    "sg:address":"6 Heron Ct",
    "sg:city":"Plainsboro",
    "sg:classifiers":[
        {
            "category":"Professional",
            "subcategory":"Management & Consulting",
            "type":"Services"
        }
    ],
    "sg:phone":"+1 609 716 1827",
    "sg:postcode":"08536",
    "sg:province":"NJ",
    "sg:tags":[
        "business"
    ],
    "wof:name":"Trinity Information Solutions",
    "wof:placetype":"venue"
},
  "geometry": {"coordinates":[-74.61090900000001,40.331964],"type":"Point"}
}