{
  "type": "Feature",
  "properties": {
    "addr:full":"28 Woodstone Rd Basking Ridge NJ 07920",
    "addr:housenumber":"28",
    "addr:postcode":"07920",
    "addr:street":"Woodstone Rd",
    "iso:country":"US",
    "sg:address":"28 Woodstone Rd",
    "sg:city":"Basking Ridge",
    "sg:classifiers":[
        {
            "category":"Building & Trades",
            "subcategory":"Construction",
            "type":"Services"
        },
        {
            "category":"Professional",
            "subcategory":"Art Services",
            "type":"Services"
        }
    ],
    "sg:phone":"+1 908 204 9020",
    "sg:postcode":"07920",
    "sg:province":"NJ",
    "sg:tags":[
        "hanging",
        "graphic",
        "designer",
        "contractor"
    ],
    "wof:name":"Woodstone Graphics Inc",
    "wof:placetype":"venue"
},
  "geometry": {"coordinates":[-74.542215,40.689333],"type":"Point"}
}