{
  "type": "Feature",
  "properties": {
    "iso:country":"US",
    "sg:address":"1386 Liberty Ave",
    "sg:city":"Hillside",
    "sg:classifiers":[
        {
            "category":"Restaurant",
            "type":"Food & Drink"
        }
    ],
    "sg:phone":"+1   ",
    "sg:postcode":"07205",
    "sg:province":"NJ",
    "sg:tags":[
        "eating"
    ],
    "wof:name":"Old Manhattan",
    "wof:placetype":"venue"
},
  "geometry": {"coordinates":[-74.23071299999999,40.700109],"type":"Point"}
}