{
  "type": "Feature",
  "properties": {
    "iso:country":"US",
    "sg:address":"2405 Pacific Ave",
    "sg:city":"Atlantic City",
    "sg:classifiers":[
        {
            "category":"Bars & Pubs",
            "type":"Food & Drink"
        }
    ],
    "sg:phone":"+1 609 347 1234",
    "sg:postcode":"08401",
    "sg:province":"NJ",
    "sg:tags":[
        "lounge",
        "cocktail"
    ],
    "wof:name":"Playground Lounge",
    "wof:placetype":"venue"
},
  "geometry": {"coordinates":[-74.440828,39.355094],"type":"Point"}
}