{
  "type": "Feature",
  "properties": {
    "addr:full":"22 Hummel Rd Bridgeton NJ 08302",
    "addr:housenumber":"22",
    "addr:postcode":"08302",
    "addr:street":"Hummel Rd",
    "iso:country":"US",
    "sg:address":"22 Hummel Rd",
    "sg:city":"Bridgeton",
    "sg:classifiers":[
        {
            "category":"Wholesale",
            "subcategory":"Machinery & Supplies",
            "type":"Manufacturing & Wholesale Goods"
        }
    ],
    "sg:phone":"+1 856 451 2971",
    "sg:postcode":"08302",
    "sg:province":"NJ",
    "sg:tags":[
        "distributor",
        "equipment",
        "hydraulic"
    ],
    "wof:name":"Ka Cee Enterprises LTD",
    "wof:placetype":"venue"
},
  "geometry": {"coordinates":[-75.327316,39.496394],"type":"Point"}
}