{
  "type": "Feature",
  "properties": {
    "iso:country":"US",
    "sg:address":"333 Broad St",
    "sg:city":"Red Bank",
    "sg:classifiers":[
        {
            "category":"Insurance",
            "subcategory":"Insurance Agent",
            "type":"Services"
        }
    ],
    "sg:phone":"+1   ",
    "sg:postcode":"07701",
    "sg:province":"NJ",
    "sg:tags":[
        "firm",
        "brokerage",
        "administrator",
        "third",
        "party"
    ],
    "wof:name":"Robert F Reynolds Associates",
    "wof:placetype":"venue"
},
  "geometry": {"coordinates":[-74.064044,40.341701],"type":"Point"}
}