{
  "type": "Feature",
  "properties": {
    "addr:full":"413 Locust Ave Burlington NJ 08016",
    "addr:housenumber":"413",
    "addr:postcode":"08016",
    "addr:street":"Locust Ave",
    "iso:country":"US",
    "sg:address":"413 Locust Ave",
    "sg:city":"Burlington",
    "sg:classifiers":[
        {
            "category":"Building & Trades",
            "subcategory":"Construction",
            "type":"Services"
        }
    ],
    "sg:phone":"+1 609 239 1875",
    "sg:postcode":"08016",
    "sg:province":"NJ",
    "sg:tags":[
        "work",
        "laying",
        "floor"
    ],
    "wof:name":"Floors-R-Us",
    "wof:placetype":"venue"
},
  "geometry": {"coordinates":[-74.858924,40.076104],"type":"Point"}
}