{
  "type": "Feature",
  "properties": {
    "iso:country":"US",
    "sg:address":"3 Monticello Ct",
    "sg:city":"Morganville",
    "sg:classifiers":[
        {
            "category":"Shopping",
            "subcategory":"Computers & Home Electronics",
            "type":"Retail Goods"
        }
    ],
    "sg:phone":"+1 732 591 8571",
    "sg:postcode":"07722",
    "sg:province":"NJ",
    "sg:tags":[
        "software"
    ],
    "sg:website":"www.sclab.com",
    "wof:name":"SCLAB",
    "wof:placetype":"venue"
},
  "geometry": {"coordinates":[-74.220754,40.33886],"type":"Point"}
}