{
  "type": "Feature",
  "properties": {
    "addr:full":"24 E Merion Ave Pleasantville NJ 08232",
    "addr:housenumber":"24",
    "addr:postcode":"08232",
    "addr:street":"E Merion Ave",
    "iso:country":"US",
    "sg:address":"24 E Merion Ave",
    "sg:city":"Pleasantville",
    "sg:classifiers":[
        {
            "category":"Professional",
            "subcategory":"Secretarial Services",
            "type":"Services"
        }
    ],
    "sg:phone":"+1 609 646 5322",
    "sg:postcode":"08232",
    "sg:province":"NJ",
    "sg:tags":[
        "reporting",
        "court"
    ],
    "wof:name":"Unique Secretarial Services",
    "wof:placetype":"venue"
},
  "geometry": {"coordinates":[-74.51596600000001,39.396458],"type":"Point"}
}