{
  "type": "Feature",
  "properties": {
    "iso:country":"US",
    "sg:address":"61 S Summit Ave",
    "sg:city":"Hackensack",
    "sg:classifiers":[
        {
            "category":"Social Services",
            "subcategory":"Child Care",
            "type":"Services"
        }
    ],
    "sg:phone":"+1 201 488 0588",
    "sg:postcode":"07601",
    "sg:province":"NJ",
    "wof:name":"Angie's Little Angels Day Care",
    "wof:placetype":"venue"
},
  "geometry": {"coordinates":[-74.06202500000001,40.882022],"type":"Point"}
}