{
  "type": "Feature",
  "properties": {
    "addr:full":"1167 State Rt 23 Butler NJ 07405",
    "addr:housenumber":"1167",
    "addr:postcode":"07405",
    "addr:street":"State Rt 23",
    "iso:country":"US",
    "sg:address":"1167 State Rt 23",
    "sg:city":"Butler",
    "sg:classifiers":[
        {
            "category":"Retail",
            "subcategory":"Car Wash",
            "type":"Services"
        }
    ],
    "sg:phone":"+1 973 492 1951",
    "sg:postcode":"07405",
    "sg:province":"NJ",
    "wof:name":"Route 23 Auto Care Mall",
    "wof:placetype":"venue"
},
  "geometry": {"coordinates":[-74.33869900000001,40.990601],"type":"Point"}
}