{
  "type": "Feature",
  "properties": {
    "iso:country":"US",
    "sg:address":"151 E 2nd Ave",
    "sg:city":"Roselle",
    "sg:classifiers":[
        {
            "category":"Retail",
            "subcategory":"Veterinary Services",
            "type":"Services"
        }
    ],
    "sg:phone":"+1 908 245 7853",
    "sg:postcode":"07203",
    "sg:province":"NJ",
    "sg:tags":[
        "veterinarian"
    ],
    "wof:name":"Elizabeth Veterinary Clinic",
    "wof:placetype":"venue"
},
  "geometry": {"coordinates":[-74.26142,40.659114],"type":"Point"}
}