{
  "type": "Feature",
  "properties": {
    "addr:full":"5552 State Rte 70 Merchantville NJ 08109",
    "addr:housenumber":"5552",
    "addr:postcode":"08109",
    "addr:street":"State Rte 70",
    "iso:country":"US",
    "sg:address":"5552 State Rte 70",
    "sg:city":"Merchantville",
    "sg:classifiers":[
        {
            "category":"Organizations",
            "subcategory":"Community Association",
            "type":"Services"
        }
    ],
    "sg:phone":"+1   ",
    "sg:postcode":"08109",
    "sg:province":"NJ",
    "sg:tags":[
        "society",
        "christian"
    ],
    "wof:name":"Society of Catholic Apostalate",
    "wof:placetype":"venue"
},
  "geometry": {"coordinates":[-75.058942,39.929182],"type":"Point"}
}