{
  "type": "Feature",
  "properties": {
    "addr:full":"111 S Chelsea Ave Atlantic City NJ 08401",
    "addr:housenumber":"111",
    "addr:postcode":"08401",
    "addr:street":"S Chelsea Ave",
    "iso:country":"US",
    "sg:address":"111 S Chelsea Ave",
    "sg:city":"Atlantic City",
    "sg:classifiers":[
        {
            "category":"Arts & Performance",
            "subcategory":"Theater",
            "type":"Entertainment"
        }
    ],
    "sg:phone":"+1 609 344 1989",
    "sg:postcode":"08401",
    "sg:province":"NJ",
    "sg:tags":[
        "bureau"
    ],
    "wof:name":"Lodgenet Entertainment Corp",
    "wof:placetype":"venue"
},
  "geometry": {"coordinates":[-74.447176,39.351279],"type":"Point"}
}