{
  "type": "Feature",
  "properties": {
    "iso:country":"US",
    "sg:address":"515 Heron Dr",
    "sg:city":"Swedesboro",
    "sg:classifiers":[
        {
            "category":"Building & Trades",
            "subcategory":"Cleaning & Sanitation",
            "type":"Services"
        }
    ],
    "sg:phone":"+1 856 467 1732",
    "sg:postcode":"08085",
    "sg:province":"NJ",
    "sg:tags":[
        "fireplace",
        "chimney"
    ],
    "wof:name":"Copperfield Chimney Supply",
    "wof:placetype":"venue"
},
  "geometry": {"coordinates":[-75.362897,39.76496],"type":"Point"}
}