{
  "type": "Feature",
  "properties": {
    "iso:country":"US",
    "sg:address":"13 Fontaine Bleau Dr",
    "sg:city":"Brick",
    "sg:classifiers":[
        {
            "category":"Professional",
            "subcategory":"Business Services",
            "type":"Services"
        }
    ],
    "sg:phone":"+1   ",
    "sg:postcode":"08723",
    "sg:province":"NJ",
    "wof:name":"Delis Home Inspections",
    "wof:placetype":"venue"
},
  "geometry": {"coordinates":[-74.134441,40.020255],"type":"Point"}
}