{
  "type": "Feature",
  "properties": {
    "iso:country":"US",
    "sg:address":"30 Ardmaer Dr",
    "sg:city":"Bridgewater",
    "sg:classifiers":[
        {
            "category":"Personal",
            "type":"Services"
        }
    ],
    "sg:phone":"+1   ",
    "sg:postcode":"08807",
    "sg:province":"NJ",
    "wof:name":"Still Waters Massage",
    "wof:placetype":"venue"
},
  "geometry": {"coordinates":[-74.652601,40.561],"type":"Point"}
}