{
  "type": "Feature",
  "properties": {
    "addr:full":"52 E Cherry St Rahway NJ 07065",
    "addr:housenumber":"52",
    "addr:postcode":"07065",
    "addr:street":"E Cherry St",
    "iso:country":"US",
    "sg:address":"52 E Cherry St",
    "sg:city":"Rahway",
    "sg:classifiers":[
        {
            "category":"Food & Beverages",
            "subcategory":"Liquor & Beverages",
            "type":"Retail Goods"
        }
    ],
    "sg:phone":"+1 732 388 2299",
    "sg:postcode":"07065",
    "sg:province":"NJ",
    "sg:tags":[
        "ticket",
        "lottery"
    ],
    "wof:name":"Beverage Shop The",
    "wof:placetype":"venue"
},
  "geometry": {"coordinates":[-74.274207,40.607012],"type":"Point"}
}