{
  "type": "Feature",
  "properties": {
    "iso:country":"US",
    "sg:address":"1000 Bergen St",
    "sg:city":"Newark",
    "sg:classifiers":[
        {
            "category":"Restaurant",
            "type":"Food & Drink"
        }
    ],
    "sg:phone":"+1 973 923 0316",
    "sg:postcode":"07112",
    "sg:province":"NJ",
    "wof:name":"Number One Chinese Kitchen",
    "wof:placetype":"venue"
},
  "geometry": {"coordinates":[-74.206582,40.709951],"type":"Point"}
}