{
  "type": "Feature",
  "properties": {
    "addr:full":"257 Broad Ave Palisades Park NJ 07650",
    "addr:housenumber":"257",
    "addr:postcode":"07650",
    "addr:street":"Broad Ave",
    "iso:country":"US",
    "sg:address":"257 Broad Ave",
    "sg:city":"Palisades Park",
    "sg:classifiers":[
        {
            "category":"Education",
            "subcategory":"Special Training",
            "type":"Public Place"
        }
    ],
    "sg:phone":"+1 201 944 1995",
    "sg:postcode":"07650",
    "sg:province":"NJ",
    "sg:tags":[
        "instruction",
        "driving"
    ],
    "wof:name":"Best Driving School",
    "wof:placetype":"venue"
},
  "geometry": {"coordinates":[-73.99839799999999,40.847201],"type":"Point"}
}