{
  "type": "Feature",
  "properties": {
    "iso:country":"US",
    "sg:address":"308 Washington St",
    "sg:city":"Hoboken",
    "sg:classifiers":[
        {
            "category":"Professional",
            "type":"Services"
        }
    ],
    "sg:phone":"+1 201 659 4335",
    "sg:postcode":"07030",
    "sg:province":"NJ",
    "sg:tags":[
        "establishment"
    ],
    "wof:name":"Mccrory's 5 10",
    "wof:placetype":"venue"
},
  "geometry": {"coordinates":[-74.02983999999999,40.741161],"type":"Point"}
}