{
  "type": "Feature",
  "properties": {
    "iso:country":"US",
    "sg:address":"410 N Broadway Suite #3",
    "sg:city":"Pitman",
    "sg:classifiers":[
        {
            "category":"Health Services",
            "subcategory":"Dentist",
            "type":"Services"
        }
    ],
    "sg:phone":"+1 856 589 0584",
    "sg:postcode":"08071",
    "sg:province":"NJ",
    "sg:tags":[
        "product",
        "dentistry",
        "whitening",
        "dentists-cosmetic",
        "teeth"
    ],
    "sg:website":"http://www.dentalassociatesatpitman.com/default.asp",
    "wof:name":"Dental Associates at Pitman",
    "wof:placetype":"venue"
},
  "geometry": {"coordinates":[-75.13474100000001,39.736523],"type":"Point"}
}