{
  "type": "Feature",
  "properties": {
    "addr:full":"3221 US Hwy 1 Lawrenceville NJ 08648",
    "addr:housenumber":"3221",
    "addr:postcode":"08648",
    "addr:street":"Us Hwy 1",
    "iso:country":"US",
    "sg:address":"3221 US Hwy 1",
    "sg:city":"Lawrenceville",
    "sg:classifiers":[
        {
            "category":"Retail",
            "subcategory":"Auto Repair",
            "type":"Services"
        }
    ],
    "sg:phone":"+1 609 896 1515",
    "sg:postcode":"08648",
    "sg:province":"NJ",
    "sg:tags":[
        "repairing",
        "automobile"
    ],
    "wof:name":"Midas Auto Svc Experts",
    "wof:placetype":"venue"
},
  "geometry": {"coordinates":[-74.68599399999999,40.291903],"type":"Point"}
}