{
  "type": "Feature",
  "properties": {
    "addr:full":"646 Anderson Ave Cliffside Park NJ 07010",
    "addr:housenumber":"646",
    "addr:postcode":"07010",
    "addr:street":"Anderson Ave",
    "iso:country":"US",
    "sg:address":"646 Anderson Ave",
    "sg:city":"Cliffside Park",
    "sg:classifiers":[
        {
            "category":"Professional",
            "subcategory":"Accounting & Tax Preparation",
            "type":"Services"
        }
    ],
    "sg:phone":"+1   ",
    "sg:postcode":"07010",
    "sg:province":"NJ",
    "wof:name":"Perlman & Kopel CPA",
    "wof:placetype":"venue"
},
  "geometry": {"coordinates":[-73.98703500000001,40.826778],"type":"Point"}
}