{
  "type": "Feature",
  "properties": {
    "addr:full":"26 Rosemary Ln Lebanon NJ 08833",
    "addr:housenumber":"26",
    "addr:postcode":"08833",
    "addr:street":"Rosemary Ln",
    "iso:country":"US",
    "sg:address":"26 Rosemary Ln",
    "sg:city":"Lebanon",
    "sg:classifiers":[
        {
            "category":"Building & Trades",
            "subcategory":"Construction",
            "type":"Services"
        }
    ],
    "sg:phone":"+1 908 236 9514",
    "sg:postcode":"08833",
    "sg:province":"NJ",
    "sg:tags":[
        "house"
    ],
    "wof:name":"Zamco Home Improvements",
    "wof:placetype":"venue"
},
  "geometry": {"coordinates":[-74.799491,40.653246],"type":"Point"}
}