{
  "type": "Feature",
  "properties": {
    "iso:country":"US",
    "sg:address":"101 68th St",
    "sg:city":"Sea Isle City",
    "sg:classifiers":[
        {
            "category":"Building & Trades",
            "subcategory":"Cleaning & Sanitation",
            "type":"Services"
        }
    ],
    "sg:phone":"+1 609 263 0606",
    "sg:postcode":"08243",
    "sg:province":"NJ",
    "sg:tags":[
        "house"
    ],
    "wof:name":"Beach Home Svc",
    "wof:placetype":"venue"
},
  "geometry": {"coordinates":[-74.707166,39.138393],"type":"Point"}
}