{
  "type": "Feature",
  "properties": {
    "iso:country":"US",
    "sg:address":"47 Kennedy Dr",
    "sg:city":"Lodi",
    "sg:classifiers":[
        {
            "category":"Building & Trades",
            "subcategory":"Cleaning & Sanitation",
            "type":"Services"
        },
        {
            "category":"Professional",
            "subcategory":"Employment Agencies",
            "type":"Services"
        }
    ],
    "sg:phone":"+1 973 773 2682",
    "sg:postcode":"07644",
    "sg:province":"NJ",
    "sg:tags":[
        "house",
        "help",
        "supply"
    ],
    "wof:name":"G & M Pressure Washing Inc",
    "wof:placetype":"venue"
},
  "geometry": {"coordinates":[-74.0809,40.883555],"type":"Point"}
}