{
  "type": "Feature",
  "properties": {
    "addr:full":"35 Maryland Ave Sewell NJ 08080",
    "addr:housenumber":"35",
    "addr:postcode":"08080",
    "addr:street":"Maryland Ave",
    "iso:country":"US",
    "sg:address":"35 Maryland Ave",
    "sg:city":"Sewell",
    "sg:classifiers":[
        {
            "category":"Building & Trades",
            "subcategory":"Construction",
            "type":"Services"
        }
    ],
    "sg:phone":"+1 856 468 6479",
    "sg:postcode":"08080",
    "sg:province":"NJ",
    "sg:tags":[
        "house"
    ],
    "wof:name":"M Lawn Home Maint",
    "wof:placetype":"venue"
},
  "geometry": {"coordinates":[-75.160256,39.786724],"type":"Point"}
}