{
  "type": "Feature",
  "properties": {
    "iso:country":"US",
    "sg:address":"1400 Beach Ave",
    "sg:city":"Atlantic City",
    "sg:classifiers":[
        {
            "category":"Shopping",
            "subcategory":"Music",
            "type":"Retail Goods"
        }
    ],
    "sg:phone":"+1   ",
    "sg:postcode":"08401",
    "sg:province":"NJ",
    "wof:name":"Nubian Records",
    "wof:placetype":"venue"
},
  "geometry": {"coordinates":[-74.447936,39.371694],"type":"Point"}
}