{
  "type": "Feature",
  "properties": {
    "addr:full":"355 Janet Ave Paramus NJ 07652",
    "addr:housenumber":"355",
    "addr:postcode":"07652",
    "addr:street":"Janet Ave",
    "iso:country":"US",
    "sg:address":"355 Janet Ave",
    "sg:city":"Paramus",
    "sg:classifiers":[
        {
            "category":"Professional",
            "subcategory":"Management & Consulting",
            "type":"Services"
        },
        {
            "category":"Professional",
            "subcategory":"Employment Agencies",
            "type":"Services"
        }
    ],
    "sg:phone":"+1 201 967 1616",
    "sg:postcode":"07652",
    "sg:province":"NJ",
    "sg:tags":[
        "consultant",
        "search",
        "executive"
    ],
    "wof:name":"Mensch & Co Inc",
    "wof:placetype":"venue"
},
  "geometry": {"coordinates":[-74.04569600000001,40.937242],"type":"Point"}
}