{
  "type": "Feature",
  "properties": {
    "addr:full":"446 Main Ave Wallington NJ 07057",
    "addr:housenumber":"446",
    "addr:postcode":"07057",
    "addr:street":"Main Ave",
    "iso:country":"US",
    "sg:address":"446 Main Ave",
    "sg:city":"Wallington",
    "sg:classifiers":[
        {
            "category":"Food & Beverages",
            "subcategory":"Bakery",
            "type":"Retail Goods"
        }
    ],
    "sg:phone":"+1 973 773 8223",
    "sg:postcode":"07057",
    "sg:province":"NJ",
    "sg:tags":[
        "bagel"
    ],
    "wof:name":"Wallington Hot Bagels & Sweets",
    "wof:placetype":"venue"
},
  "geometry": {"coordinates":[-74.099802,40.859954],"type":"Point"}
}