{
  "type": "Feature",
  "properties": {
    "addr:full":"30 Kershner Pl Fair Lawn NJ 07410",
    "addr:housenumber":"30",
    "addr:postcode":"07410",
    "addr:street":"Kershner Pl",
    "iso:country":"US",
    "sg:address":"30 Kershner Pl",
    "sg:city":"Fair Lawn",
    "sg:classifiers":[
        {
            "category":"Health Services",
            "subcategory":"Doctor",
            "type":"Services"
        },
        {
            "category":"Social Services",
            "type":"Services"
        }
    ],
    "sg:phone":"+1 201 791 3863",
    "sg:postcode":"07410",
    "sg:province":"NJ",
    "sg:tags":[
        "medical",
        "counselor",
        "marriage",
        "family"
    ],
    "wof:name":"Milton Deutsch PHD",
    "wof:placetype":"venue"
},
  "geometry": {"coordinates":[-74.108249,40.948467],"type":"Point"}
}