{
  "type": "Feature",
  "properties": {
    "addr:full":"73 Co Rd 645 Branchville NJ 07826",
    "addr:housenumber":"73",
    "addr:postcode":"645;07826",
    "addr:street":"Co Rd",
    "iso:country":"US",
    "sg:address":"73 Co Rd 645",
    "sg:city":"Branchville",
    "sg:classifiers":[
        {
            "category":"Professional",
            "subcategory":"Art Services",
            "type":"Services"
        }
    ],
    "sg:phone":"+1 973 948 0502",
    "sg:postcode":"07826",
    "sg:province":"NJ",
    "sg:tags":[
        "commercial",
        "design"
    ],
    "wof:name":"Trimps Ice Art",
    "wof:placetype":"venue"
},
  "geometry": {"coordinates":[-74.82047799999999,41.221135],"type":"Point"}
}