{
  "type": "Feature",
  "properties": {
    "iso:country":"US",
    "sg:address":"8366 Crofton Ln",
    "sg:city":"Merchantville",
    "sg:classifiers":[
        {
            "category":"Professional",
            "type":"Services"
        }
    ],
    "sg:phone":"+1   ",
    "sg:postcode":"08109",
    "sg:province":"NJ",
    "wof:name":"Mario J Trinidad Inc",
    "wof:placetype":"venue"
},
  "geometry": {"coordinates":[-75.02789900000001,39.969337],"type":"Point"}
}