{
  "type": "Feature",
  "properties": {
    "addr:full":"29 Garfield Ave Keansburg NJ 07734",
    "addr:housenumber":"29",
    "addr:postcode":"07734",
    "addr:street":"Garfield Ave",
    "iso:country":"US",
    "sg:address":"29 Garfield Ave",
    "sg:city":"Keansburg",
    "sg:classifiers":[
        {
            "category":"Shopping",
            "subcategory":"Gifts & Souvenirs",
            "type":"Retail Goods"
        }
    ],
    "sg:phone":"+1   ",
    "sg:postcode":"07734",
    "sg:province":"NJ",
    "wof:name":"Cardsorcery",
    "wof:placetype":"venue"
},
  "geometry": {"coordinates":[-74.13550499999999,40.44838],"type":"Point"}
}