{
  "type": "Feature",
  "properties": {
    "iso:country":"US",
    "sg:address":"288 US Hwy 22",
    "sg:city":"Dunellen",
    "sg:classifiers":[
        {
            "category":"Shopping",
            "subcategory":"Computers & Home Electronics",
            "type":"Retail Goods"
        }
    ],
    "sg:phone":"+1   ",
    "sg:postcode":"08812",
    "sg:province":"NJ",
    "wof:name":"Computer Integration Center",
    "wof:placetype":"venue"
},
  "geometry": {"coordinates":[-74.49793,40.591581],"type":"Point"}
}