{
  "type": "Feature",
  "properties": {
    "addr:full":"76 Lincoln St Berkeley Heights NJ 07922",
    "addr:housenumber":"76",
    "addr:postcode":"07922",
    "addr:street":"Lincoln St",
    "iso:country":"US",
    "sg:address":"76 Lincoln St",
    "sg:city":"Berkeley Heights",
    "sg:classifiers":[
        {
            "category":"Professional",
            "subcategory":"Management & Consulting",
            "type":"Services"
        }
    ],
    "sg:phone":"+1 908 464 7466",
    "sg:postcode":"07922",
    "sg:province":"NJ",
    "wof:name":"Sinictech Consulting Inc",
    "wof:placetype":"venue"
},
  "geometry": {"coordinates":[-74.449381,40.682754],"type":"Point"}
}