{
  "type": "Feature",
  "properties": {
    "addr:full":"96 Rutledge Dr Red Bank NJ 07701",
    "addr:housenumber":"96",
    "addr:postcode":"07701",
    "addr:street":"Rutledge Dr",
    "iso:country":"US",
    "sg:address":"96 Rutledge Dr",
    "sg:city":"Red Bank",
    "sg:classifiers":[
        {
            "category":"Professional",
            "subcategory":"Computer Services",
            "type":"Services"
        }
    ],
    "sg:phone":"+1 732 758 0800",
    "sg:postcode":"07701",
    "sg:province":"NJ",
    "sg:tags":[
        "internet"
    ],
    "wof:name":"Great Numbers",
    "wof:placetype":"venue"
},
  "geometry": {"coordinates":[-74.10213,40.376979],"type":"Point"}
}