{
  "type": "Feature",
  "properties": {
    "addr:full":"1344 State Rte 35 Middletown NJ 07748",
    "addr:housenumber":"1344",
    "addr:postcode":"07748",
    "addr:street":"State Rte 35",
    "iso:country":"US",
    "sg:address":"1344 State Rte 35",
    "sg:city":"Middletown",
    "sg:classifiers":[
        {
            "category":"Home & Garden",
            "subcategory":"Furniture",
            "type":"Retail Goods"
        }
    ],
    "sg:phone":"+1   ",
    "sg:postcode":"07748",
    "sg:province":"NJ",
    "sg:tags":[
        "mattress"
    ],
    "wof:name":"Sleepys Inc",
    "wof:placetype":"venue"
},
  "geometry": {"coordinates":[-74.12097900000001,40.400732],"type":"Point"}
}