{
  "type": "Feature",
  "properties": {
    "iso:country":"US",
    "sg:address":"920 Harrison Ave",
    "sg:city":"Roselle",
    "sg:classifiers":[
        {
            "category":"Shopping",
            "subcategory":"Beauty & Cosmetics",
            "type":"Retail Goods"
        }
    ],
    "sg:phone":"+1   ",
    "sg:postcode":"07203",
    "sg:province":"NJ",
    "sg:tags":[
        "merchandise"
    ],
    "wof:name":"Gayle Cosmetics",
    "wof:placetype":"venue"
},
  "geometry": {"coordinates":[-74.24874,40.650433],"type":"Point"}
}