{
  "type": "Feature",
  "properties": {
    "iso:country":"US",
    "sg:address":"800 Riverview Dr",
    "sg:city":"Brielle",
    "sg:classifiers":[
        {
            "category":"Professional",
            "subcategory":"Lawyer & Legal Services",
            "type":"Services"
        }
    ],
    "sg:phone":"+1 732 292 1775",
    "sg:postcode":"08730",
    "sg:province":"NJ",
    "sg:tags":[
        "attorney"
    ],
    "wof:name":"Joseph A Deckhut",
    "wof:placetype":"venue"
},
  "geometry": {"coordinates":[-74.05870899999999,40.106629],"type":"Point"}
}