{
  "type": "Feature",
  "properties": {
    "iso:country":"US",
    "sg:address":"87 Line Rd",
    "sg:city":"Trenton",
    "sg:classifiers":[
        {
            "category":"Professional",
            "subcategory":"Accounting & Tax Preparation",
            "type":"Services"
        }
    ],
    "sg:phone":"+1 609 448 4002",
    "sg:postcode":"08690",
    "sg:province":"NJ",
    "wof:name":"Zak Victorial",
    "wof:placetype":"venue"
},
  "geometry": {"coordinates":[-74.64495599999999,40.242929],"type":"Point"}
}