{
  "type": "Feature",
  "properties": {
    "iso:country":"US",
    "sg:address":"1146 S Olden Ave",
    "sg:city":"Trenton",
    "sg:classifiers":[
        {
            "category":"Retail",
            "subcategory":"Portrait Studio",
            "type":"Services"
        }
    ],
    "sg:phone":"+1 609 586 8020",
    "sg:postcode":"08610",
    "sg:province":"NJ",
    "sg:tags":[
        "photographer",
        "photo"
    ],
    "wof:name":"All Sport Photos",
    "wof:placetype":"venue"
},
  "geometry": {"coordinates":[-74.72377299999999,40.21164],"type":"Point"}
}