{
  "type": "Feature",
  "properties": {
    "iso:country":"US",
    "sg:address":"186 Columbia Tpke",
    "sg:city":"Florham Park",
    "sg:classifiers":[
        {
            "category":"Deli",
            "type":"Food & Drink"
        },
        {
            "category":"Bagels",
            "subcategory":"None",
            "type":"Food & Drink"
        }
    ],
    "sg:phone":"+1 973 443 0636",
    "sg:postcode":"07932",
    "sg:province":"NJ",
    "sg:website":"www.florhamparkbagels.com",
    "wof:name":"Florham Park Bagel & Deli Inc",
    "wof:placetype":"venue"
},
  "geometry": {"coordinates":[-74.393693,40.788599],"type":"Point"}
}