{
  "type": "Feature",
  "properties": {
    "addr:full":"54 Broadway Passaic NJ 07055",
    "addr:housenumber":"54",
    "addr:postcode":"07055",
    "addr:street":"Broadway",
    "iso:country":"US",
    "sg:address":"54 Broadway",
    "sg:city":"Passaic",
    "sg:classifiers":[
        {
            "category":"Restaurant",
            "type":"Food & Drink"
        }
    ],
    "sg:phone":"+1 973 249 0060",
    "sg:postcode":"07055",
    "sg:province":"NJ",
    "wof:name":"LA Resaca Restaurant",
    "wof:placetype":"venue"
},
  "geometry": {"coordinates":[-74.127199,40.860525],"type":"Point"}
}