{
  "type": "Feature",
  "properties": {
    "addr:full":"20 Monroe St Union NJ 07083",
    "addr:housenumber":"20",
    "addr:postcode":"07083",
    "addr:street":"Monroe St",
    "iso:country":"US",
    "sg:address":"20 Monroe St",
    "sg:city":"Union",
    "sg:classifiers":[
        {
            "category":"Manufacturing",
            "subcategory":"Tools & Machinery",
            "type":"Manufacturing & Wholesale Goods"
        }
    ],
    "sg:phone":"+1 908 686 2910",
    "sg:postcode":"07083",
    "sg:province":"NJ",
    "sg:tags":[
        "machine",
        "die",
        "parts",
        "special"
    ],
    "wof:name":"Philip Creter Inc",
    "wof:placetype":"venue"
},
  "geometry": {"coordinates":[-74.30112099999999,40.68716],"type":"Point"}
}