{
  "type": "Feature",
  "properties": {
    "iso:country":"US",
    "sg:address":"22 James Dr",
    "sg:city":"Ringwood",
    "sg:classifiers":[
        {
            "category":"Shopping",
            "subcategory":"Gifts & Souvenirs",
            "type":"Retail Goods"
        }
    ],
    "sg:phone":"+1   ",
    "sg:postcode":"07456",
    "sg:province":"NJ",
    "wof:name":"Smac Greetings",
    "wof:placetype":"venue"
},
  "geometry": {"coordinates":[-74.25805800000001,41.079917],"type":"Point"}
}