{
  "type": "Feature",
  "properties": {
    "addr:full":"250 Broad Ave Leonia NJ 07605",
    "addr:housenumber":"250",
    "addr:postcode":"07605",
    "addr:street":"Broad Ave",
    "iso:country":"US",
    "sg:address":"250 Broad Ave",
    "sg:city":"Leonia",
    "sg:classifiers":[
        {
            "category":"Professional",
            "type":"Services"
        }
    ],
    "sg:phone":"+1   ",
    "sg:postcode":"07605",
    "sg:province":"NJ",
    "wof:name":"Medbilling Services",
    "wof:placetype":"venue"
},
  "geometry": {"coordinates":[-73.990138,40.858661],"type":"Point"}
}