{
  "type": "Feature",
  "properties": {
    "iso:country":"US",
    "sg:address":"3401 Bridge Ave",
    "sg:city":"Pt Pleasant Boro",
    "sg:classifiers":[
        {
            "category":"Building & Trades",
            "subcategory":"Construction",
            "type":"Services"
        }
    ],
    "sg:phone":"+1 732 892 5454",
    "sg:postcode":"08742",
    "sg:province":"NJ",
    "sg:tags":[
        "roofing",
        "contractor"
    ],
    "wof:name":"American Monarch Roofing Inc",
    "wof:placetype":"venue"
},
  "geometry": {"coordinates":[-74.088368,40.081027],"type":"Point"}
}