{
  "type": "Feature",
  "properties": {
    "addr:full":"26 Columbia Tpke Florham Park NJ 07932",
    "addr:housenumber":"26",
    "addr:postcode":"07932",
    "addr:street":"Columbia Tpke",
    "iso:country":"US",
    "sg:address":"26 Columbia Tpke",
    "sg:city":"Florham Park",
    "sg:classifiers":[
        {
            "category":"Insurance",
            "subcategory":"Insurance Agent",
            "type":"Services"
        }
    ],
    "sg:phone":"+1 973 549 1868",
    "sg:postcode":"07932",
    "sg:province":"NJ",
    "sg:website":"www.kushnercompanies.com",
    "wof:name":"Statfeld Wantage Insurance Grp",
    "wof:placetype":"venue"
},
  "geometry": {"coordinates":[-74.37195199999999,40.780497],"type":"Point"}
}