{
  "type": "Feature",
  "properties": {
    "addr:full":"197 Ferry St Newark NJ 07105",
    "addr:housenumber":"197",
    "addr:postcode":"07105",
    "addr:street":"Ferry St",
    "iso:country":"US",
    "sg:address":"197 Ferry St",
    "sg:city":"Newark",
    "sg:classifiers":[
        {
            "category":"Shopping",
            "subcategory":"Jewelry",
            "type":"Retail Goods"
        }
    ],
    "sg:phone":"+1 973 344 9260",
    "sg:postcode":"07105",
    "sg:province":"NJ",
    "sg:tags":[
        "store",
        "jeweler"
    ],
    "sg:website":"www.vinhas.com",
    "wof:name":"Vinhas Jewelers Inc",
    "wof:placetype":"venue"
},
  "geometry": {"coordinates":[-74.15682700000001,40.728499],"type":"Point"}
}