{
  "type": "Feature",
  "properties": {
    "iso:country":"US",
    "sg:address":"129 N Wood Ave Fl 1",
    "sg:city":"Linden",
    "sg:classifiers":[
        {
            "category":"Retail",
            "subcategory":"Laundry & Dry Cleaning",
            "type":"Services"
        }
    ],
    "sg:phone":"+1 908 486 9876",
    "sg:postcode":"07036",
    "sg:province":"NJ",
    "wof:name":"Chang's Cleaners",
    "wof:placetype":"venue"
},
  "geometry": {"coordinates":[-74.25340300000001,40.631001],"type":"Point"}
}