{
  "type": "Feature",
  "properties": {
    "addr:full":"53 Osborn Ave Manasquan NJ 08736",
    "addr:housenumber":"53",
    "addr:postcode":"08736",
    "addr:street":"Osborn Ave",
    "iso:country":"US",
    "sg:address":"53 Osborn Ave",
    "sg:city":"Manasquan",
    "sg:classifiers":[
        {
            "category":"Building & Trades",
            "subcategory":"Plumbing",
            "type":"Services"
        }
    ],
    "sg:phone":"+1 732 223 6337",
    "sg:postcode":"08736",
    "sg:province":"NJ",
    "sg:tags":[
        "air",
        "heating",
        "conditioning",
        "contractor"
    ],
    "wof:name":"Ron Lamo Heating & Cooling",
    "wof:placetype":"venue"
},
  "geometry": {"coordinates":[-74.051433,40.127738],"type":"Point"}
}