{
  "type": "Feature",
  "properties": {
    "addr:full":"426 Franklin Ave Belleville NJ 07109",
    "addr:housenumber":"426",
    "addr:postcode":"07109",
    "addr:street":"Franklin Ave",
    "iso:country":"US",
    "sg:address":"426 Franklin Ave",
    "sg:city":"Belleville",
    "sg:classifiers":[
        {
            "category":"Retail",
            "subcategory":"Animal Services",
            "type":"Services"
        }
    ],
    "sg:phone":"+1 973 879 9133",
    "sg:postcode":"07109",
    "sg:province":"NJ",
    "wof:name":"Alpha K9 LLC",
    "wof:placetype":"venue"
},
  "geometry": {"coordinates":[-74.16962100000001,40.803121],"type":"Point"}
}