{
  "type": "Feature",
  "properties": {
    "addr:full":"13 Bartholdi Ave Jersey City NJ 07305",
    "addr:housenumber":"13",
    "addr:postcode":"07305",
    "addr:street":"Bartholdi Ave",
    "iso:country":"US",
    "sg:address":"13 Bartholdi Ave",
    "sg:city":"Jersey City",
    "sg:classifiers":[
        {
            "category":"Banks & Credit Unions",
            "subcategory":"Financial Services",
            "type":"Services"
        }
    ],
    "sg:phone":"+1   ",
    "sg:postcode":"07305",
    "sg:province":"NJ",
    "sg:tags":[
        "investor"
    ],
    "wof:name":"D&A Investors Inc",
    "wof:placetype":"venue"
},
  "geometry": {"coordinates":[-74.094675,40.694169],"type":"Point"}
}