{
  "type": "Feature",
  "properties": {
    "iso:country":"US",
    "sg:address":"200 Wright St",
    "sg:city":"Newark",
    "sg:classifiers":[
        {
            "category":"Manufacturing",
            "subcategory":"Apparel",
            "type":"Manufacturing & Wholesale Goods"
        }
    ],
    "sg:phone":"+1 973 622 1144",
    "sg:postcode":"07114",
    "sg:province":"NJ",
    "sg:tags":[
        "mfg"
    ],
    "wof:name":"Headwear Creations Inc",
    "wof:placetype":"venue"
},
  "geometry": {"coordinates":[-74.176632,40.718427],"type":"Point"}
}