{
  "type": "Feature",
  "properties": {
    "addr:full":"2176 State Rte 35 Sea Girt NJ 08750",
    "addr:housenumber":"2176",
    "addr:postcode":"08750",
    "addr:street":"State Rte 35",
    "iso:country":"US",
    "sg:address":"2176 State Rte 35",
    "sg:city":"Sea Girt",
    "sg:classifiers":[
        {
            "category":"Home & Garden",
            "subcategory":"Building Materials",
            "type":"Retail Goods"
        }
    ],
    "sg:phone":"+1 732 292 0032",
    "sg:postcode":"08750",
    "sg:province":"NJ",
    "sg:tags":[
        "paint"
    ],
    "wof:name":"Sherwin-Williams Paints",
    "wof:placetype":"venue"
},
  "geometry": {"coordinates":[-74.0635,40.135928],"type":"Point"}
}