{
  "type": "Feature",
  "properties": {
    "addr:full":"1090 US Hwy 202 Branchburg NJ 08876",
    "addr:housenumber":"1090",
    "addr:postcode":"08876",
    "addr:street":"Us Hwy 202",
    "iso:country":"US",
    "sg:address":"1090 US Hwy 202",
    "sg:city":"Branchburg",
    "sg:classifiers":[
        {
            "category":"Banks & Credit Unions",
            "subcategory":"Bank",
            "type":"Services"
        }
    ],
    "sg:phone":"+1 908 000 1111",
    "sg:postcode":"08876",
    "sg:province":"NJ",
    "sg:website":"www.fleet.com",
    "wof:name":"Bank Of America",
    "wof:placetype":"venue"
},
  "geometry": {"coordinates":[-74.700293,40.561824],"type":"Point"}
}