{
  "type": "Feature",
  "properties": {
    "addr:full":"324 Wayland Rd Cherry Hill NJ 08034",
    "addr:housenumber":"324",
    "addr:postcode":"08034",
    "addr:street":"Wayland Rd",
    "iso:country":"US",
    "sg:address":"324 Wayland Rd",
    "sg:city":"Cherry Hill",
    "sg:classifiers":[
        {
            "category":"Professional",
            "subcategory":"Management & Consulting",
            "type":"Services"
        }
    ],
    "sg:phone":"+1   ",
    "sg:postcode":"08034",
    "sg:province":"NJ",
    "sg:tags":[
        "consultant"
    ],
    "wof:name":"Ebbert Company",
    "wof:placetype":"venue"
},
  "geometry": {"coordinates":[-75.00431,39.911315],"type":"Point"}
}