{
  "type": "Feature",
  "properties": {
    "iso:country":"US",
    "sg:address":"32 Hillside Ave",
    "sg:city":"Saddle River",
    "sg:classifiers":[
        {
            "category":"Building & Trades",
            "subcategory":"Construction",
            "type":"Services"
        }
    ],
    "sg:phone":"+1 201 825 2351",
    "sg:postcode":"07458",
    "sg:province":"NJ",
    "sg:tags":[
        "developer",
        "condominium",
        "general",
        "contractor"
    ],
    "wof:name":"Rotonda Construction Co",
    "wof:placetype":"venue"
},
  "geometry": {"coordinates":[-74.094044,41.082107],"type":"Point"}
}