{
  "type": "Feature",
  "properties": {
    "addr:full":"453 Amboy Ave Woodbridge NJ 07095",
    "addr:housenumber":"453",
    "addr:postcode":"07095",
    "addr:street":"Amboy Ave",
    "iso:country":"US",
    "sg:address":"453 Amboy Ave",
    "sg:city":"Woodbridge",
    "sg:classifiers":[
        {
            "category":"Health Services",
            "subcategory":"Doctor",
            "type":"Services"
        }
    ],
    "sg:phone":"+1 732 636 6612",
    "sg:postcode":"07095",
    "sg:province":"NJ",
    "wof:name":"Park Primary Care Assoc",
    "wof:placetype":"venue"
},
  "geometry": {"coordinates":[-74.283401,40.555801],"type":"Point"}
}