{
  "type": "Feature",
  "properties": {
    "addr:full":"90 Market St Clifton NJ 07012",
    "addr:housenumber":"90",
    "addr:postcode":"07012",
    "addr:street":"Market St",
    "iso:country":"US",
    "sg:address":"90 Market St",
    "sg:city":"Clifton",
    "sg:classifiers":[
        {
            "category":"Food & Beverages",
            "subcategory":"Groceries & Convenience Stores",
            "type":"Retail Goods"
        }
    ],
    "sg:phone":"+1 973 341 6511",
    "sg:postcode":"07012",
    "sg:province":"NJ",
    "wof:name":"Puebla Foods",
    "wof:placetype":"venue"
},
  "geometry": {"coordinates":[-74.162086,40.845867],"type":"Point"}
}