{
  "type": "Feature",
  "properties": {
    "iso:country":"US",
    "sg:address":"73 Lomond Rd",
    "sg:city":"Williamstown",
    "sg:classifiers":[
        {
            "category":"Shopping",
            "subcategory":"Computers & Home Electronics",
            "type":"Retail Goods"
        }
    ],
    "sg:phone":"+1   ",
    "sg:postcode":"08094",
    "sg:province":"NJ",
    "sg:tags":[
        "consulting",
        "management"
    ],
    "wof:name":"Richdor Ent Inc",
    "wof:placetype":"venue"
},
  "geometry": {"coordinates":[-75.017976,39.699901],"type":"Point"}
}