{
  "type": "Feature",
  "properties": {
    "addr:full":"632 2nd Ave Long Branch NJ 07740",
    "addr:housenumber":"632",
    "addr:postcode":"07740",
    "addr:street":"2Nd Ave",
    "iso:country":"US",
    "sg:address":"632 2nd Ave",
    "sg:city":"Long Branch",
    "sg:classifiers":[
        {
            "category":"Autos & Motor Vehicles",
            "subcategory":"Fuel & Gas Station",
            "type":"Retail Goods"
        }
    ],
    "sg:phone":"+1 732 571 9191",
    "sg:postcode":"07740",
    "sg:province":"NJ",
    "sg:tags":[
        "oil"
    ],
    "wof:name":"Long Branch Exxon",
    "wof:placetype":"venue"
},
  "geometry": {"coordinates":[-73.98654500000001,40.283991],"type":"Point"}
}