{
  "type": "Feature",
  "properties": {
    "addr:full":"2444 Morris Ave Union NJ 07083",
    "addr:housenumber":"2444",
    "addr:postcode":"07083",
    "addr:street":"Morris Ave",
    "iso:country":"US",
    "sg:address":"2444 Morris Ave",
    "sg:city":"Union",
    "sg:classifiers":[
        {
            "category":"Insurance",
            "subcategory":"Insurance Agent",
            "type":"Services"
        }
    ],
    "sg:phone":"+1 908 688 0204",
    "sg:postcode":"07083",
    "sg:province":"NJ",
    "sg:website":"www.bpsinc-online.com",
    "wof:name":"Benefit Program Svc",
    "wof:placetype":"venue"
},
  "geometry": {"coordinates":[-74.28722399999999,40.701432],"type":"Point"}
}