{
  "type": "Feature",
  "properties": {
    "addr:full":"23 Iris Ct Eatontown NJ 07724",
    "addr:housenumber":"23",
    "addr:postcode":"07724",
    "addr:street":"Iris Ct",
    "iso:country":"US",
    "sg:address":"23 Iris Ct",
    "sg:city":"Eatontown",
    "sg:classifiers":[
        {
            "category":"Social Services",
            "type":"Services"
        }
    ],
    "sg:phone":"+1 732 530 3940",
    "sg:postcode":"07724",
    "sg:province":"NJ",
    "sg:tags":[
        "counselor",
        "marriage",
        "family"
    ],
    "wof:name":"Herbert Feldman MA",
    "wof:placetype":"venue"
},
  "geometry": {"coordinates":[-74.076335,40.317193],"type":"Point"}
}