{
  "type": "Feature",
  "properties": {
    "iso:country":"US",
    "sg:address":"1522 Route 38 Ste 202",
    "sg:city":"Cherry Hill",
    "sg:classifiers":[
        {
            "category":"Professional",
            "subcategory":"Lawyer & Legal Services",
            "type":"Services"
        }
    ],
    "sg:phone":"+1 856 665 7140",
    "sg:postcode":"08002",
    "sg:province":"NJ",
    "wof:name":"Talbot Richard J Esquire",
    "wof:placetype":"venue"
},
  "geometry": {"coordinates":[-75.031623,39.938343],"type":"Point"}
}