{
  "type": "Feature",
  "properties": {
    "iso:country":"US",
    "sg:address":"98 Village Way",
    "sg:city":"Budd Lake",
    "sg:classifiers":[
        {
            "category":"Banks & Credit Unions",
            "subcategory":"Bank",
            "type":"Services"
        }
    ],
    "sg:phone":"+1 973 691 1411",
    "sg:postcode":"07828",
    "sg:province":"NJ",
    "sg:tags":[
        "financing"
    ],
    "sg:website":"www.hfc.com",
    "wof:name":"Household Finance",
    "wof:placetype":"venue"
},
  "geometry": {"coordinates":[-74.727265,40.887498],"type":"Point"}
}