{
  "type": "Feature",
  "properties": {
    "addr:full":"5042 Industrial Rd Belmar NJ 07727",
    "addr:housenumber":"5042",
    "addr:postcode":"07727",
    "addr:street":"Industrial Rd",
    "iso:country":"US",
    "sg:address":"5042 Industrial Rd",
    "sg:city":"Belmar",
    "sg:classifiers":[
        {
            "category":"Building & Trades",
            "subcategory":"Construction",
            "type":"Services"
        }
    ],
    "sg:phone":"+1 732 919 2700",
    "sg:postcode":"07727",
    "sg:province":"NJ",
    "sg:tags":[
        "painter"
    ],
    "wof:name":"Spectrum Painting",
    "wof:placetype":"venue"
},
  "geometry": {"coordinates":[-74.124859,40.191016],"type":"Point"}
}