{
  "type": "Feature",
  "properties": {
    "iso:country":"US",
    "sg:address":"522 4th St",
    "sg:city":"Atco",
    "sg:classifiers":[
        {
            "category":"Banks & Credit Unions",
            "subcategory":"Bank",
            "type":"Services"
        }
    ],
    "sg:phone":"+1   ",
    "sg:postcode":"08004",
    "sg:province":"NJ",
    "sg:tags":[
        "depository",
        "banking"
    ],
    "wof:name":"Atm Reps Inc",
    "wof:placetype":"venue"
},
  "geometry": {"coordinates":[-74.87823299999999,39.774282],"type":"Point"}
}