{
  "type": "Feature",
  "properties": {
    "iso:country":"US",
    "sg:address":"60 Main Ave",
    "sg:city":"Ocean Grove",
    "sg:classifiers":[
        {
            "category":"Restaurant",
            "type":"Food & Drink"
        }
    ],
    "sg:phone":"+1   ",
    "sg:postcode":"07756",
    "sg:province":"NJ",
    "sg:tags":[
        "eating"
    ],
    "wof:name":"Pizza Shoppe",
    "wof:placetype":"venue"
},
  "geometry": {"coordinates":[-74.00620000000001,40.211938],"type":"Point"}
}