{
  "type": "Feature",
  "properties": {
    "iso:country":"US",
    "sg:address":"559 E Holly Ave",
    "sg:city":"Pitman",
    "sg:classifiers":[
        {
            "category":"Professional",
            "subcategory":"Business Services",
            "type":"Services"
        }
    ],
    "sg:phone":"+1   ",
    "sg:postcode":"08071",
    "sg:province":"NJ",
    "sg:tags":[
        "security"
    ],
    "wof:name":"S Chip Doughty Co",
    "wof:placetype":"venue"
},
  "geometry": {"coordinates":[-75.117457,39.737912],"type":"Point"}
}