{
  "type": "Feature",
  "properties": {
    "addr:full":"139 US Hwy 46 Hackettstown NJ 07840",
    "addr:housenumber":"139",
    "addr:postcode":"07840",
    "addr:street":"Us Hwy 46",
    "iso:country":"US",
    "sg:address":"139 US Hwy 46",
    "sg:city":"Hackettstown",
    "sg:classifiers":[
        {
            "category":"Freight",
            "type":"Transportation"
        }
    ],
    "sg:phone":"+1 908 852 9190",
    "sg:postcode":"07840",
    "sg:province":"NJ",
    "sg:tags":[
        "distance",
        "hauling",
        "long",
        "trucking"
    ],
    "wof:name":"Mid Atlantic Express Inc",
    "wof:placetype":"venue"
},
  "geometry": {"coordinates":[-74.829842,40.85413],"type":"Point"}
}