{
  "type": "Feature",
  "properties": {
    "addr:full":"623 E Landis Ave Vineland NJ 08360",
    "addr:housenumber":"623",
    "addr:postcode":"08360",
    "addr:street":"E Landis Ave",
    "iso:country":"US",
    "sg:address":"623 E Landis Ave",
    "sg:city":"Vineland",
    "sg:classifiers":[
        {
            "category":"Manufacturing",
            "subcategory":"Food",
            "type":"Manufacturing & Wholesale Goods"
        }
    ],
    "sg:phone":"+1 856 563 0229",
    "sg:postcode":"08360",
    "sg:province":"NJ",
    "sg:tags":[
        "flavor",
        "mfg"
    ],
    "wof:name":"Nujeru Records",
    "wof:placetype":"venue"
},
  "geometry": {"coordinates":[-75.021586,39.485909],"type":"Point"}
}