{
  "type": "Feature",
  "properties": {
    "addr:full":"585 Winters Ave Paramus NJ 07652",
    "addr:housenumber":"585",
    "addr:postcode":"07652",
    "addr:street":"Winters Ave",
    "iso:country":"US",
    "sg:address":"585 Winters Ave",
    "sg:city":"Paramus",
    "sg:classifiers":[
        {
            "category":"Health Services",
            "subcategory":"Doctor",
            "type":"Services"
        }
    ],
    "sg:phone":"+1 201 262 3636",
    "sg:postcode":"07652",
    "sg:province":"NJ",
    "sg:tags":[
        "dentist"
    ],
    "wof:name":"Endodontic Associates",
    "wof:placetype":"venue"
},
  "geometry": {"coordinates":[-74.07199799999999,40.959641],"type":"Point"}
}