{
  "type": "Feature",
  "properties": {
    "iso:country":"US",
    "sg:address":"8 Horizon Dr",
    "sg:city":"Mendham",
    "sg:classifiers":[
        {
            "category":"Wholesale",
            "subcategory":"Non-durable Goods",
            "type":"Manufacturing & Wholesale Goods"
        }
    ],
    "sg:phone":"+1 732 899 5283",
    "sg:postcode":"07945",
    "sg:province":"NJ",
    "wof:name":"JMG Designs Inc",
    "wof:placetype":"venue"
},
  "geometry": {"coordinates":[-74.60057500000001,40.792994],"type":"Point"}
}