{
  "type": "Feature",
  "properties": {
    "addr:full":"14 Parmly St Rumson NJ 07760",
    "addr:housenumber":"14",
    "addr:postcode":"07760",
    "addr:street":"Parmly St",
    "iso:country":"US",
    "sg:address":"14 Parmly St",
    "sg:city":"Rumson",
    "sg:classifiers":[
        {
            "category":"Wholesale",
            "subcategory":"Electrical",
            "type":"Manufacturing & Wholesale Goods"
        }
    ],
    "sg:phone":"+1 732 842 2087",
    "sg:postcode":"07760",
    "sg:province":"NJ",
    "sg:tags":[
        "equipment"
    ],
    "wof:name":"Monmouth Alarm Services",
    "wof:placetype":"venue"
},
  "geometry": {"coordinates":[-73.998243,40.373675],"type":"Point"}
}