{
  "type": "Feature",
  "properties": {
    "addr:full":"808 Marlborough Ave Blackwood NJ 08012",
    "addr:housenumber":"808",
    "addr:postcode":"08012",
    "addr:street":"Marlborough Ave",
    "iso:country":"US",
    "sg:address":"808 Marlborough Ave",
    "sg:city":"Blackwood",
    "sg:classifiers":[
        {
            "category":"Shopping",
            "subcategory":"Clothing, Apparel, & Fashions",
            "type":"Retail Goods"
        }
    ],
    "sg:phone":"+1   ",
    "sg:postcode":"08012",
    "sg:province":"NJ",
    "wof:name":"Bridal Invitations By Joann",
    "wof:placetype":"venue"
},
  "geometry": {"coordinates":[-75.03416199999999,39.744806],"type":"Point"}
}