{
  "type": "Feature",
  "properties": {
    "addr:full":"1540 Kuser Rd Trenton NJ 08619",
    "addr:housenumber":"1540",
    "addr:postcode":"08619",
    "addr:street":"Kuser Rd",
    "iso:country":"US",
    "sg:address":"1540 Kuser Rd",
    "sg:city":"Trenton",
    "sg:classifiers":[
        {
            "category":"Professional",
            "subcategory":"Accounting & Tax Preparation",
            "type":"Services"
        }
    ],
    "sg:phone":"+1 609 581 0300",
    "sg:postcode":"08619",
    "sg:province":"NJ",
    "sg:tags":[
        "public",
        "accountants-certified"
    ],
    "wof:name":"Civale Silvestri Alfieri Martin & Higgins",
    "wof:placetype":"venue"
},
  "geometry": {"coordinates":[-74.696938,40.208154],"type":"Point"}
}