{
  "type": "Feature",
  "properties": {
    "iso:country":"US",
    "sg:address":"33 Ramsey St",
    "sg:city":"Bridgewater",
    "sg:classifiers":[
        {
            "category":"Professional",
            "subcategory":"Art Services",
            "type":"Services"
        }
    ],
    "sg:phone":"+1   ",
    "sg:postcode":"08807",
    "sg:province":"NJ",
    "sg:tags":[
        "commercial",
        "design"
    ],
    "wof:name":"Summer Days Camp Marketing",
    "wof:placetype":"venue"
},
  "geometry": {"coordinates":[-74.575552,40.559872],"type":"Point"}
}