{
  "type": "Feature",
  "properties": {
    "addr:full":"100 Marin Blvd Jersey City NJ 07302",
    "addr:housenumber":"100",
    "addr:postcode":"07302",
    "addr:street":"Marin Blvd",
    "iso:country":"US",
    "sg:address":"100 Marin Blvd",
    "sg:city":"Jersey City",
    "sg:classifiers":[
        {
            "category":"Building & Trades",
            "subcategory":"Pest Control",
            "type":"Services"
        }
    ],
    "sg:phone":"+1 212 571 5805",
    "sg:postcode":"07302",
    "sg:province":"NJ",
    "wof:name":"Western Pest Services",
    "wof:placetype":"venue"
},
  "geometry": {"coordinates":[-74.04303299999999,40.713103],"type":"Point"}
}