{
  "type": "Feature",
  "properties": {
    "addr:full":"231 Wanaque Ave Pompton Lakes NJ 07442",
    "addr:housenumber":"231",
    "addr:postcode":"07442",
    "addr:street":"Wanaque Ave",
    "iso:country":"US",
    "sg:address":"231 Wanaque Ave",
    "sg:city":"Pompton Lakes",
    "sg:classifiers":[
        {
            "category":"Food & Beverages",
            "subcategory":"Candy",
            "type":"Retail Goods"
        }
    ],
    "sg:phone":"+1 973 839 3303",
    "sg:postcode":"07442",
    "sg:province":"NJ",
    "sg:tags":[
        "confectionery"
    ],
    "wof:name":"Candy Bouquet",
    "wof:placetype":"venue"
},
  "geometry": {"coordinates":[-74.291568,41.00514],"type":"Point"}
}