{
  "type": "Feature",
  "properties": {
    "iso:country":"US",
    "sg:address":"312 Middlesex St",
    "sg:city":"Toms River",
    "sg:classifiers":[
        {
            "category":"Recreation",
            "type":"Entertainment"
        }
    ],
    "sg:phone":"+1 732 818 0271",
    "sg:postcode":"08757",
    "sg:province":"NJ",
    "sg:tags":[
        "amusement"
    ],
    "wof:name":"Magic Sports Complex Inc",
    "wof:placetype":"venue"
},
  "geometry": {"coordinates":[-74.262235,39.995348],"type":"Point"}
}