{
  "type": "Feature",
  "properties": {
    "addr:full":"9204 Collins Ave Pennsauken NJ 08110",
    "addr:housenumber":"9204",
    "addr:postcode":"08110",
    "addr:street":"Collins Ave",
    "iso:country":"US",
    "sg:address":"9204 Collins Ave",
    "sg:city":"Pennsauken",
    "sg:classifiers":[
        {
            "category":"Manufacturing",
            "subcategory":"Tools & Machinery",
            "type":"Manufacturing & Wholesale Goods"
        },
        {
            "category":"Home & Garden",
            "subcategory":"Hardware",
            "type":"Retail Goods"
        }
    ],
    "sg:phone":"+1 856 662 1700",
    "sg:postcode":"08110",
    "sg:province":"NJ",
    "sg:tags":[
        "nut",
        "fasteners-industrial",
        "bolt"
    ],
    "sg:website":"http://www.3dbolt.com",
    "wof:name":"3d Bolt",
    "wof:placetype":"venue"
},
  "geometry": {"coordinates":[-75.02041800000001,39.971949],"type":"Point"}
}