{
  "type": "Feature",
  "properties": {
    "iso:country":"US",
    "sg:address":"395 E 18th St",
    "sg:city":"Paterson",
    "sg:classifiers":[
        {
            "category":"Autos & Motor Vehicles",
            "subcategory":"Auto Supplies",
            "type":"Retail Goods"
        },
        {
            "category":"Retail",
            "subcategory":"Auto Repair",
            "type":"Services"
        },
        {
            "category":"Sports & Exercise",
            "subcategory":"Race Track",
            "type":"Entertainment"
        }
    ],
    "sg:phone":"+1 973 742 4972",
    "sg:postcode":"07524",
    "sg:province":"NJ",
    "sg:tags":[
        "shop",
        "automobile",
        "accessory",
        "machine",
        "equipment",
        "part",
        "car",
        "performance",
        "racing"
    ],
    "wof:name":"Ceralli Competition Engines Inc",
    "wof:placetype":"venue"
},
  "geometry": {"coordinates":[-74.15316,40.92672],"type":"Point"}
}