{
  "type": "Feature",
  "properties": {
    "iso:country":"US",
    "sg:address":"54 Brunswick Woods Dr",
    "sg:city":"East Brunswick",
    "sg:classifiers":[
        {
            "category":"Professional",
            "subcategory":"Business Services",
            "type":"Services"
        }
    ],
    "sg:phone":"+1   ",
    "sg:postcode":"08816",
    "sg:province":"NJ",
    "wof:name":"SMR Associates",
    "wof:placetype":"venue"
},
  "geometry": {"coordinates":[-74.392081,40.421628],"type":"Point"}
}