{
  "type": "Feature",
  "properties": {
    "addr:full":"174 S Leswing Ave Saddle Brook NJ 07663",
    "addr:housenumber":"174",
    "addr:postcode":"07663",
    "addr:street":"S Leswing Ave",
    "iso:country":"US",
    "sg:address":"174 S Leswing Ave",
    "sg:city":"Saddle Brook",
    "sg:classifiers":[
        {
            "category":"Building & Trades",
            "subcategory":"Construction",
            "type":"Services"
        }
    ],
    "sg:phone":"+1 201 226 1414",
    "sg:postcode":"07663",
    "sg:province":"NJ",
    "sg:tags":[
        "contractor"
    ],
    "wof:name":"Vision Contracting & Development",
    "wof:placetype":"venue"
},
  "geometry": {"coordinates":[-74.09787799999999,40.90436],"type":"Point"}
}