{
  "type": "Feature",
  "properties": {
    "addr:full":"1023 S Olden Ave Trenton NJ 08610",
    "addr:housenumber":"1023",
    "addr:postcode":"08610",
    "addr:street":"S Olden Ave",
    "iso:country":"US",
    "sg:address":"1023 S Olden Ave",
    "sg:city":"Trenton",
    "sg:classifiers":[
        {
            "category":"Autos & Motor Vehicles",
            "subcategory":"Auto Supplies",
            "type":"Retail Goods"
        }
    ],
    "sg:phone":"+1   ",
    "sg:postcode":"08610",
    "sg:province":"NJ",
    "sg:tags":[
        "automotive",
        "tire",
        "accessory"
    ],
    "wof:name":"Garden State Tire & Automotive",
    "wof:placetype":"venue"
},
  "geometry": {"coordinates":[-74.725233,40.212087],"type":"Point"}
}