{
  "type": "Feature",
  "properties": {
    "iso:country":"US",
    "sg:address":"497 US Hwy 22",
    "sg:city":"North Plainfield",
    "sg:classifiers":[
        {
            "category":"Autos & Motor Vehicles",
            "subcategory":"Fuel & Gas Station",
            "type":"Retail Goods"
        }
    ],
    "sg:phone":"+1 908 755 9304",
    "sg:postcode":"07060",
    "sg:province":"NJ",
    "sg:tags":[
        "oil"
    ],
    "wof:name":"North Plainfield Amoco",
    "wof:placetype":"venue"
},
  "geometry": {"coordinates":[-74.430483,40.631654],"type":"Point"}
}