{
  "type": "Feature",
  "properties": {
    "addr:full":"1164 Manor Dr Lakewood NJ 08701",
    "addr:housenumber":"1164",
    "addr:postcode":"08701",
    "addr:street":"Manor Dr",
    "iso:country":"US",
    "sg:address":"1164 Manor Dr",
    "sg:city":"Lakewood",
    "sg:classifiers":[
        {
            "category":"Retail",
            "subcategory":"Repair Shop",
            "type":"Services"
        }
    ],
    "sg:phone":"+1   ",
    "sg:postcode":"08701",
    "sg:province":"NJ",
    "wof:name":"Ebonebor Cleaning Servives",
    "wof:placetype":"venue"
},
  "geometry": {"coordinates":[-74.211878,40.053892],"type":"Point"}
}