{
  "type": "Feature",
  "properties": {
    "addr:full":"206 Walnut Dr Brick NJ 08724",
    "addr:housenumber":"206",
    "addr:postcode":"08724",
    "addr:street":"Walnut Dr",
    "iso:country":"US",
    "sg:address":"206 Walnut Dr",
    "sg:city":"Brick",
    "sg:classifiers":[
        {
            "category":"Building & Trades",
            "subcategory":"Construction",
            "type":"Services"
        }
    ],
    "sg:phone":"+1 732 206 0008",
    "sg:postcode":"08724",
    "sg:province":"NJ",
    "sg:tags":[
        "nonresidential"
    ],
    "wof:name":"Grq Building Inc",
    "wof:placetype":"venue"
},
  "geometry": {"coordinates":[-74.10119899999999,40.100373],"type":"Point"}
}