{
  "type": "Feature",
  "properties": {
    "addr:full":"275 Linden St Moorestown NJ 08057",
    "addr:housenumber":"275",
    "addr:postcode":"08057",
    "addr:street":"Linden St",
    "iso:country":"US",
    "sg:address":"275 Linden St",
    "sg:city":"Moorestown",
    "sg:classifiers":[
        {
            "category":"Professional",
            "subcategory":"Art Services",
            "type":"Services"
        }
    ],
    "sg:phone":"+1 856 727 8447",
    "sg:postcode":"08057",
    "sg:province":"NJ",
    "sg:tags":[
        "commercial",
        "design"
    ],
    "wof:name":"Working Designs",
    "wof:placetype":"venue"
},
  "geometry": {"coordinates":[-74.93738500000001,39.971624],"type":"Point"}
}