{
  "type": "Feature",
  "properties": {
    "iso:country":"US",
    "sg:address":"31 Junard Dr",
    "sg:city":"Morristown",
    "sg:classifiers":[
        {
            "category":"Communications",
            "subcategory":"Film & Video Production",
            "type":"Services"
        }
    ],
    "sg:phone":"+1 973 267 7331",
    "sg:postcode":"07960",
    "sg:province":"NJ",
    "sg:tags":[
        "editing",
        "tape"
    ],
    "wof:name":"Cromm Video Svc",
    "wof:placetype":"venue"
},
  "geometry": {"coordinates":[-74.53408899999999,40.827748],"type":"Point"}
}