{
  "type": "Feature",
  "properties": {
    "iso:country":"US",
    "sg:address":"7 N Maple Ave",
    "sg:city":"Irvington",
    "sg:classifiers":[
        {
            "category":"Personal",
            "subcategory":"Beauty Salon",
            "type":"Services"
        }
    ],
    "sg:phone":"+1 973 375 4120",
    "sg:postcode":"07111",
    "sg:province":"NJ",
    "sg:tags":[
        "shop"
    ],
    "wof:name":"Geneva",
    "wof:placetype":"venue"
},
  "geometry": {"coordinates":[-74.222138,40.728232],"type":"Point"}
}