{
  "type": "Feature",
  "properties": {
    "iso:country":"US",
    "sg:address":"103 28th Ave",
    "sg:city":"Monroeville",
    "sg:classifiers":[
        {
            "category":"Organizations",
            "subcategory":"Community Association",
            "type":"Services"
        }
    ],
    "sg:phone":"+1 856 881 7132",
    "sg:postcode":"08343",
    "sg:province":"NJ",
    "wof:name":"First Love Inc",
    "wof:placetype":"venue"
},
  "geometry": {"coordinates":[-75.117037,39.653355],"type":"Point"}
}