{
  "type": "Feature",
  "properties": {
    "iso:country":"US",
    "sg:address":"440 West St",
    "sg:city":"Fort Lee",
    "sg:classifiers":[
        {
            "category":"Real Estate",
            "subcategory":"Real Estate Agent",
            "type":"Services"
        }
    ],
    "sg:phone":"+1   ",
    "sg:postcode":"07024",
    "sg:province":"NJ",
    "sg:tags":[
        "manager"
    ],
    "wof:name":"Matthews Group The",
    "wof:placetype":"venue"
},
  "geometry": {"coordinates":[-73.971442,40.858754],"type":"Point"}
}