{
  "type": "Feature",
  "properties": {
    "addr:full":"257 Depue St Belvidere NJ 07823",
    "addr:housenumber":"257",
    "addr:postcode":"07823",
    "addr:street":"Depue St",
    "iso:country":"US",
    "sg:address":"257 Depue St",
    "sg:city":"Belvidere",
    "sg:classifiers":[
        {
            "category":"Professional",
            "type":"Services"
        }
    ],
    "sg:phone":"+1   ",
    "sg:postcode":"07823",
    "sg:province":"NJ",
    "wof:name":"Tedi S Sera",
    "wof:placetype":"venue"
},
  "geometry": {"coordinates":[-75.08183200000001,40.824695],"type":"Point"}
}