{
  "type": "Feature",
  "properties": {
    "iso:country":"US",
    "sg:address":"260 N Broadway",
    "sg:city":"Pennsville",
    "sg:classifiers":[
        {
            "category":"Banks & Credit Unions",
            "subcategory":"Bank",
            "type":"Services"
        }
    ],
    "sg:phone":"+1 856 678 5911",
    "sg:postcode":"08070",
    "sg:province":"NJ",
    "sg:website":"www.franklinsavingsbank.com",
    "wof:name":"Franklin Savings Bank SLA",
    "wof:placetype":"venue"
},
  "geometry": {"coordinates":[-75.505925,39.668629],"type":"Point"}
}