{
  "type": "Feature",
  "properties": {
    "iso:country":"US",
    "sg:address":"11 Fair Lawn Ave",
    "sg:city":"Fair Lawn",
    "sg:classifiers":[
        {
            "category":"Banks & Credit Unions",
            "subcategory":"Investment Brokerage",
            "type":"Services"
        }
    ],
    "sg:phone":"+1 201 791 5252",
    "sg:postcode":"07410",
    "sg:province":"NJ",
    "sg:tags":[
        "stock",
        "bond"
    ],
    "wof:name":"Spencer-Winston Securities",
    "wof:placetype":"venue"
},
  "geometry": {"coordinates":[-74.130425,40.936495],"type":"Point"}
}