{
  "type": "Feature",
  "properties": {
    "addr:full":"75 Garden St Hoboken NJ 07030",
    "addr:housenumber":"75",
    "addr:postcode":"07030",
    "addr:street":"Garden St",
    "iso:country":"US",
    "sg:address":"75 Garden St",
    "sg:city":"Hoboken",
    "sg:classifiers":[
        {
            "category":"Professional",
            "subcategory":"Computer Services",
            "type":"Services"
        }
    ],
    "sg:phone":"+1   ",
    "sg:postcode":"07030",
    "sg:province":"NJ",
    "sg:tags":[
        "design",
        "system"
    ],
    "wof:name":"Skypin Systems Inc",
    "wof:placetype":"venue"
},
  "geometry": {"coordinates":[-74.03307599999999,40.735933],"type":"Point"}
}