{
  "type": "Feature",
  "properties": {
    "iso:country":"US",
    "sg:address":"155 Ferry St",
    "sg:city":"Newark",
    "sg:classifiers":[
        {
            "category":"Personal",
            "subcategory":"Beauty Salon",
            "type":"Services"
        }
    ],
    "sg:phone":"+1 973 578 8168",
    "sg:postcode":"07105",
    "sg:province":"NJ",
    "sg:tags":[
        "shop"
    ],
    "wof:name":"Nails Galery",
    "wof:placetype":"venue"
},
  "geometry": {"coordinates":[-74.158084,40.728979],"type":"Point"}
}