{
  "type": "Feature",
  "properties": {
    "addr:full":"53 Windsor St Kearny NJ 07032",
    "addr:housenumber":"53",
    "addr:postcode":"07032",
    "addr:street":"Windsor St",
    "iso:country":"US",
    "sg:address":"53 Windsor St",
    "sg:city":"Kearny",
    "sg:classifiers":[
        {
            "category":"Restaurant",
            "type":"Food & Drink"
        }
    ],
    "sg:phone":"+1   ",
    "sg:postcode":"07032",
    "sg:province":"NJ",
    "sg:tags":[
        "eating"
    ],
    "wof:name":"Johnnys Grill LLC",
    "wof:placetype":"venue"
},
  "geometry": {"coordinates":[-74.15433400000001,40.758334],"type":"Point"}
}