{
  "type": "Feature",
  "properties": {
    "iso:country":"US",
    "sg:address":"225 Millburn Ave",
    "sg:city":"Millburn",
    "sg:classifiers":[
        {
            "category":"Health Services",
            "subcategory":"Doctor",
            "type":"Services"
        }
    ],
    "sg:phone":"+1 973 218 1511",
    "sg:postcode":"07041",
    "sg:province":"NJ",
    "sg:tags":[
        "psychiatrist"
    ],
    "wof:name":"Frederikse Melissa E. MD",
    "wof:placetype":"venue"
},
  "geometry": {"coordinates":[-74.298742,40.723462],"type":"Point"}
}