{
  "type": "Feature",
  "properties": {
    "addr:full":"42 Faner Rd Midland Park NJ 07432",
    "addr:housenumber":"42",
    "addr:postcode":"07432",
    "addr:street":"Faner Rd",
    "iso:country":"US",
    "sg:address":"42 Faner Rd",
    "sg:city":"Midland Park",
    "sg:classifiers":[
        {
            "category":"Retail",
            "subcategory":"Car Wash",
            "type":"Services"
        }
    ],
    "sg:phone":"+1   ",
    "sg:postcode":"07432",
    "sg:province":"NJ",
    "sg:tags":[
        "carwash"
    ],
    "wof:name":"Best Auto Detailing Inc",
    "wof:placetype":"venue"
},
  "geometry": {"coordinates":[-74.145354,40.987798],"type":"Point"}
}