{
  "type": "Feature",
  "properties": {
    "addr:full":"16 Whitesville Rd Toms River NJ 08753",
    "addr:housenumber":"16",
    "addr:postcode":"08753",
    "addr:street":"Whitesville Rd",
    "iso:country":"US",
    "sg:address":"16 Whitesville Rd",
    "sg:city":"Toms River",
    "sg:classifiers":[
        {
            "category":"Professional",
            "subcategory":"Management & Consulting",
            "type":"Services"
        }
    ],
    "sg:phone":"+1 732 341 1600",
    "sg:postcode":"08753",
    "sg:province":"NJ",
    "wof:name":"Country Health Nursing Home",
    "wof:placetype":"venue"
},
  "geometry": {"coordinates":[-74.210143,39.982309],"type":"Point"}
}