{
  "type": "Feature",
  "properties": {
    "addr:full":"563 61st St West New York NJ 07093",
    "addr:housenumber":"563",
    "addr:postcode":"nj 07093",
    "addr:street":"61St St West",
    "iso:country":"US",
    "sg:address":"563 61st St",
    "sg:city":"West New York",
    "sg:classifiers":[
        {
            "category":"Personal",
            "subcategory":"Beauty Salon",
            "type":"Services"
        }
    ],
    "sg:phone":"+1   ",
    "sg:postcode":"07093",
    "sg:province":"NJ",
    "sg:tags":[
        "shop"
    ],
    "wof:name":"Touch of Beauty Inc",
    "wof:placetype":"venue"
},
  "geometry": {"coordinates":[-74.018219,40.791016],"type":"Point"}
}