{
  "type": "Feature",
  "properties": {
    "addr:full":"166 Maple Ave Red Bank NJ 07701",
    "addr:housenumber":"166",
    "addr:postcode":"07701",
    "addr:street":"Maple Ave",
    "iso:country":"US",
    "sg:address":"166 Maple Ave",
    "sg:city":"Red Bank",
    "sg:classifiers":[
        {
            "category":"Organizations",
            "subcategory":"Community Association",
            "type":"Services"
        }
    ],
    "sg:phone":"+1   ",
    "sg:postcode":"07701",
    "sg:province":"NJ",
    "sg:tags":[
        "library"
    ],
    "wof:name":"Camp Zehnder",
    "wof:placetype":"venue"
},
  "geometry": {"coordinates":[-74.068389,40.345698],"type":"Point"}
}