{
  "type": "Feature",
  "properties": {
    "addr:full":"268 Martin Luther King Jr Blvd Newark NJ 07102",
    "addr:housenumber":"268",
    "addr:postcode":"07102",
    "addr:street":"Martin Luther King Jr Blvd",
    "iso:country":"US",
    "sg:address":"268 Martin Luther King Jr Blvd",
    "sg:city":"Newark",
    "sg:classifiers":[
        {
            "category":"Coffee & Tea",
            "type":"Food & Drink"
        },
        {
            "category":"Restaurant",
            "type":"Food & Drink"
        }
    ],
    "sg:phone":"+1 973 877 5637",
    "sg:postcode":"07102",
    "sg:province":"NJ",
    "sg:tags":[
        "espresso"
    ],
    "wof:name":"L & H Tom Fish Inc",
    "wof:placetype":"venue"
},
  "geometry": {"coordinates":[-74.17504700000001,40.745166],"type":"Point"}
}