{
  "type": "Feature",
  "properties": {
    "iso:country":"US",
    "sg:address":"238 Pennypacker Dr",
    "sg:city":"Willingboro",
    "sg:classifiers":[
        {
            "category":"Recreation",
            "type":"Entertainment"
        }
    ],
    "sg:phone":"+1 609 877 6812",
    "sg:postcode":"08046",
    "sg:province":"NJ",
    "sg:tags":[
        "club",
        "baseball"
    ],
    "wof:name":"Willingboro Baseball American",
    "wof:placetype":"venue"
},
  "geometry": {"coordinates":[-74.905447,40.041058],"type":"Point"}
}