{
  "type": "Feature",
  "properties": {
    "iso:country":"US",
    "sg:address":"2421 Nottingham Way",
    "sg:city":"Trenton",
    "sg:classifiers":[
        {
            "category":"Shopping",
            "subcategory":"Jewelry",
            "type":"Retail Goods"
        }
    ],
    "sg:phone":"+1 609 588 0604",
    "sg:postcode":"08619",
    "sg:province":"NJ",
    "sg:tags":[
        "jeweler"
    ],
    "wof:name":"Big Oak Jeweler Inc",
    "wof:placetype":"venue"
},
  "geometry": {"coordinates":[-74.696412,40.234069],"type":"Point"}
}