{
  "type": "Feature",
  "properties": {
    "iso:country":"US",
    "sg:address":"91 Vincent Dr",
    "sg:city":"Burlington",
    "sg:classifiers":[
        {
            "category":"Building & Trades",
            "subcategory":"Construction",
            "type":"Services"
        }
    ],
    "sg:phone":"+1 609 387 4507",
    "sg:postcode":"08016",
    "sg:province":"NJ",
    "sg:tags":[
        "hanging",
        "contractor"
    ],
    "wof:name":"Gudul Painting Co",
    "wof:placetype":"venue"
},
  "geometry": {"coordinates":[-74.824386,40.066791],"type":"Point"}
}