{
  "type": "Feature",
  "properties": {
    "addr:full":"10 Commerce St Newark NJ 07102",
    "addr:housenumber":"10",
    "addr:postcode":"07102",
    "addr:street":"Commerce St",
    "iso:country":"US",
    "sg:address":"10 Commerce St",
    "sg:city":"Newark",
    "sg:classifiers":[
        {
            "category":"Travel",
            "subcategory":"Travel Agent",
            "type":"Entertainment"
        }
    ],
    "sg:phone":"+1 973 623 8430",
    "sg:postcode":"07102",
    "sg:province":"NJ",
    "sg:tags":[
        "agency",
        "bureau"
    ],
    "wof:name":"Essex Travel Svc",
    "wof:placetype":"venue"
},
  "geometry": {"coordinates":[-74.170484,40.73682],"type":"Point"}
}