{
  "type": "Feature",
  "properties": {
    "iso:country":"US",
    "sg:address":"76 Carlisle Ave",
    "sg:city":"Trenton",
    "sg:classifiers":[
        {
            "category":"Manufacturing",
            "subcategory":"Furniture",
            "type":"Manufacturing & Wholesale Goods"
        }
    ],
    "sg:phone":"+1 609 581 2651",
    "sg:postcode":"08620",
    "sg:province":"NJ",
    "sg:tags":[
        "upholstered",
        "wood"
    ],
    "wof:name":"Italian Wood Working",
    "wof:placetype":"venue"
},
  "geometry": {"coordinates":[-74.66158299999999,40.177254],"type":"Point"}
}