{
  "type": "Feature",
  "properties": {
    "addr:full":"2903 Atlantic Ave Atlantic City NJ 08401",
    "addr:housenumber":"2903",
    "addr:postcode":"08401",
    "addr:street":"Atlantic Ave",
    "iso:country":"US",
    "sg:address":"2903 Atlantic Ave",
    "sg:city":"Atlantic City",
    "sg:classifiers":[
        {
            "category":"Retail",
            "subcategory":"Laundry & Dry Cleaning",
            "type":"Services"
        }
    ],
    "sg:phone":"+1   ",
    "sg:postcode":"08401",
    "sg:province":"NJ",
    "wof:name":"Brighton Cleaners",
    "wof:placetype":"venue"
},
  "geometry": {"coordinates":[-74.447963,39.354071],"type":"Point"}
}