{
  "type": "Feature",
  "properties": {
    "iso:country":"US",
    "sg:address":"754 New Brunswick Ave",
    "sg:city":"Rahway",
    "sg:classifiers":[
        {
            "category":"Restaurant",
            "type":"Food & Drink"
        }
    ],
    "sg:phone":"+1 732 610 7088",
    "sg:postcode":"07065",
    "sg:province":"NJ",
    "wof:name":"Nishi Enterprise Inc",
    "wof:placetype":"venue"
},
  "geometry": {"coordinates":[-74.28229,40.599363],"type":"Point"}
}