{
  "type": "Feature",
  "properties": {
    "addr:full":"934 Potters Rd Newton NJ 07860",
    "addr:housenumber":"934",
    "addr:postcode":"07860",
    "addr:street":"Potters Rd",
    "iso:country":"US",
    "sg:address":"934 Potters Rd",
    "sg:city":"Newton",
    "sg:classifiers":[
        {
            "category":"Building & Trades",
            "subcategory":"Cleaning & Sanitation",
            "type":"Services"
        }
    ],
    "sg:phone":"+1 973 579 1115",
    "sg:postcode":"07860",
    "sg:province":"NJ",
    "sg:tags":[
        "polishing",
        "waxing",
        "floor"
    ],
    "wof:name":"Center Interior Svc",
    "wof:placetype":"venue"
},
  "geometry": {"coordinates":[-74.856686,41.044181],"type":"Point"}
}