{
  "type": "Feature",
  "properties": {
    "addr:full":"1745 State Rte 37 Toms River NJ 08757",
    "addr:housenumber":"1745",
    "addr:postcode":"08757",
    "addr:street":"State Rte 37",
    "iso:country":"US",
    "sg:address":"1745 State Rte 37",
    "sg:city":"Toms River",
    "sg:classifiers":[
        {
            "category":"Professional",
            "subcategory":"Art Services",
            "type":"Services"
        }
    ],
    "sg:phone":"+1   ",
    "sg:postcode":"08757",
    "sg:province":"NJ",
    "sg:tags":[
        "graphic",
        "design",
        "sign"
    ],
    "wof:name":"Air Graphix Inc",
    "wof:placetype":"venue"
},
  "geometry": {"coordinates":[-74.271079,39.992179],"type":"Point"}
}