{
  "type": "Feature",
  "properties": {
    "addr:full":"14 Stonehenge Dr Lumberton NJ 08048",
    "addr:housenumber":"14",
    "addr:postcode":"08048",
    "addr:street":"Stonehenge Dr",
    "iso:country":"US",
    "sg:address":"14 Stonehenge Dr",
    "sg:city":"Lumberton",
    "sg:classifiers":[
        {
            "category":"Insurance",
            "subcategory":"Insurance Agent",
            "type":"Services"
        }
    ],
    "sg:phone":"+1 609 702 1037",
    "sg:postcode":"08048",
    "sg:province":"NJ",
    "sg:tags":[
        "adjuster"
    ],
    "wof:name":"Dallmer Adjusters Inc",
    "wof:placetype":"venue"
},
  "geometry": {"coordinates":[-74.79024699999999,39.970181],"type":"Point"}
}