{
  "type": "Feature",
  "properties": {
    "iso:country":"US",
    "sg:address":"19 W St",
    "sg:city":"Woodbury",
    "sg:classifiers":[
        {
            "category":"Manufacturing",
            "subcategory":"Printing",
            "type":"Manufacturing & Wholesale Goods"
        }
    ],
    "sg:phone":"+1 856 845 4563",
    "sg:postcode":"08096",
    "sg:province":"NJ",
    "sg:tags":[
        "screen"
    ],
    "sg:website":"www.cappyprint.com",
    "wof:name":"Cappy's Silk Screen Printing",
    "wof:placetype":"venue"
},
  "geometry": {"coordinates":[-75.15714199999999,39.834549],"type":"Point"}
}