{
  "type": "Feature",
  "properties": {
    "addr:full":"428 E State St Trenton NJ 08608",
    "addr:housenumber":"428",
    "addr:postcode":"08608",
    "addr:street":"E State St",
    "iso:country":"US",
    "sg:address":"428 E State St",
    "sg:city":"Trenton",
    "sg:classifiers":[
        {
            "category":"Government",
            "subcategory":"Office",
            "type":"Public Place"
        }
    ],
    "sg:phone":"+1 609 292 3294",
    "sg:postcode":"08608",
    "sg:province":"NJ",
    "sg:tags":[
        "state",
        "program"
    ],
    "wof:name":"Nj Dept-Environmental Protctn",
    "wof:placetype":"venue"
},
  "geometry": {"coordinates":[-74.75577800000001,40.221063],"type":"Point"}
}