{
  "type": "Feature",
  "properties": {
    "addr:full":"5 Bradford Ter Middletown NJ 07748",
    "addr:housenumber":"5",
    "addr:postcode":"07748",
    "addr:street":"Bradford Ter",
    "iso:country":"US",
    "sg:address":"5 Bradford Ter",
    "sg:city":"Middletown",
    "sg:classifiers":[
        {
            "category":"Professional",
            "subcategory":"Detective & Security Services",
            "type":"Services"
        }
    ],
    "sg:phone":"+1 732 671 6004",
    "sg:postcode":"07748",
    "sg:province":"NJ",
    "sg:tags":[
        "investigator"
    ],
    "wof:name":"Dignitary Protection",
    "wof:placetype":"venue"
},
  "geometry": {"coordinates":[-74.125266,40.385055],"type":"Point"}
}