{
  "type": "Feature",
  "properties": {
    "iso:country":"US",
    "sg:address":"51 Yorktown Rd",
    "sg:city":"Monmouth Junction",
    "sg:classifiers":[
        {
            "category":"Social Services",
            "subcategory":"Child Care",
            "type":"Services"
        }
    ],
    "sg:phone":"+1   ",
    "sg:postcode":"08852",
    "sg:province":"NJ",
    "sg:tags":[
        "day"
    ],
    "wof:name":"Kiddie Academy CC Learning Ctr",
    "wof:placetype":"venue"
},
  "geometry": {"coordinates":[-74.516885,40.399938],"type":"Point"}
}