{
  "type": "Feature",
  "properties": {
    "iso:country":"US",
    "sg:address":"358 Anderson St",
    "sg:city":"Hackensack",
    "sg:classifiers":[
        {
            "category":"Organizations",
            "subcategory":"Religious Organization",
            "type":"Services"
        }
    ],
    "sg:phone":"+1 201 489 9022",
    "sg:postcode":"07601",
    "sg:province":"NJ",
    "sg:tags":[
        "clergy"
    ],
    "wof:name":"Leo B Collins III",
    "wof:placetype":"venue"
},
  "geometry": {"coordinates":[-74.05173499999999,40.898892],"type":"Point"}
}