{
  "type": "Feature",
  "properties": {
    "iso:country":"US",
    "sg:address":"4 Lakawanna Ct",
    "sg:city":"Dayton",
    "sg:classifiers":[
        {
            "category":"Professional",
            "subcategory":"Computer Services",
            "type":"Services"
        }
    ],
    "sg:phone":"+1   ",
    "sg:postcode":"08810",
    "sg:province":"NJ",
    "sg:tags":[
        "prepackaged",
        "software"
    ],
    "wof:name":"Swift River Software Inc",
    "wof:placetype":"venue"
},
  "geometry": {"coordinates":[-74.512478,40.371576],"type":"Point"}
}