{
  "type": "Feature",
  "properties": {
    "addr:full":"415 Hamburg Tpke Ste G Wayne NJ 07470",
    "addr:housenumber":"415",
    "addr:postcode":"07470",
    "addr:street":"Hamburg Tpke Ste G",
    "iso:country":"US",
    "sg:address":"415 Hamburg Tpke Ste G",
    "sg:city":"Wayne",
    "sg:classifiers":[
        {
            "category":"Shopping",
            "subcategory":"Gifts & Souvenirs",
            "type":"Retail Goods"
        },
        {
            "category":"Professional",
            "subcategory":"Business Services",
            "type":"Services"
        }
    ],
    "sg:phone":"+1 973 790 0990",
    "sg:postcode":"07470",
    "sg:province":"NJ",
    "sg:tags":[
        "material",
        "wrapping",
        "labeling"
    ],
    "wof:name":"Swan Packaging Fulfillment Co Inc",
    "wof:placetype":"venue"
},
  "geometry": {"coordinates":[-74.210213,40.951674],"type":"Point"}
}