{
  "type": "Feature",
  "properties": {
    "addr:full":"6 Hampshire Rd Berkeley Heights NJ 07922",
    "addr:housenumber":"6",
    "addr:postcode":"07922",
    "addr:street":"Hampshire Rd",
    "iso:country":"US",
    "sg:address":"6 Hampshire Rd",
    "sg:city":"Berkeley Heights",
    "sg:classifiers":[
        {
            "category":"Professional",
            "subcategory":"Detective & Security Services",
            "type":"Services"
        }
    ],
    "sg:phone":"+1 908 665 0749",
    "sg:postcode":"07922",
    "sg:province":"NJ",
    "sg:tags":[
        "business"
    ],
    "wof:name":"Vaughn Cardwell",
    "wof:placetype":"venue"
},
  "geometry": {"coordinates":[-74.415706,40.684019],"type":"Point"}
}