{
  "type": "Feature",
  "properties": {
    "addr:full":"363 Davis Ave Kearny NJ 07032",
    "addr:housenumber":"363",
    "addr:postcode":"07032",
    "addr:street":"Davis Ave",
    "iso:country":"US",
    "sg:address":"363 Davis Ave",
    "sg:city":"Kearny",
    "sg:classifiers":[
        {
            "category":"Professional",
            "subcategory":"Advertising",
            "type":"Services"
        }
    ],
    "sg:phone":"+1 201 997 6902",
    "sg:postcode":"07032",
    "sg:province":"NJ",
    "sg:tags":[
        "mail",
        "direct"
    ],
    "wof:name":"Money Mailer of NW Essex",
    "wof:placetype":"venue"
},
  "geometry": {"coordinates":[-74.142341,40.765226],"type":"Point"}
}