{
  "type": "Feature",
  "properties": {
    "iso:country":"US",
    "sg:address":"549 Carleton Rd",
    "sg:city":"Westfield",
    "sg:classifiers":[
        {
            "category":"Home & Garden",
            "subcategory":"Home Furnishings",
            "type":"Retail Goods"
        }
    ],
    "sg:phone":"+1 973 579 1825",
    "sg:postcode":"07090",
    "sg:province":"NJ",
    "sg:tags":[
        "pottery"
    ],
    "wof:name":"Peter's Pottery",
    "wof:placetype":"venue"
},
  "geometry": {"coordinates":[-74.342817,40.647702],"type":"Point"}
}