{
  "type": "Feature",
  "properties": {
    "addr:full":"646 Hermann Rd North Brunswick NJ 08902",
    "addr:housenumber":"646",
    "addr:postcode":"08902",
    "addr:street":"Hermann Rd",
    "iso:country":"US",
    "sg:address":"646 Hermann Rd",
    "sg:city":"North Brunswick",
    "sg:classifiers":[
        {
            "category":"Professional",
            "subcategory":"Accounting & Tax Preparation",
            "type":"Services"
        }
    ],
    "sg:phone":"+1 201 863 2616",
    "sg:postcode":"08902",
    "sg:province":"NJ",
    "sg:tags":[
        "accountant"
    ],
    "wof:name":"Chetan Shah CPA",
    "wof:placetype":"venue"
},
  "geometry": {"coordinates":[-74.45485499999999,40.466632],"type":"Point"}
}