{
  "type": "Feature",
  "properties": {
    "addr:full":"188 Thatchers Hill Rd Flemington NJ 08822",
    "addr:housenumber":"188",
    "addr:postcode":"08822",
    "addr:street":"Thatchers Hill Rd",
    "iso:country":"US",
    "sg:address":"188 Thatchers Hill Rd",
    "sg:city":"Flemington",
    "sg:classifiers":[
        {
            "category":"Building & Trades",
            "subcategory":"Construction",
            "type":"Services"
        }
    ],
    "sg:phone":"+1 908 782 2115",
    "sg:postcode":"08822",
    "sg:province":"NJ",
    "sg:tags":[
        "mason",
        "general",
        "contractor"
    ],
    "wof:name":"Baker General Contracting Inc",
    "wof:placetype":"venue"
},
  "geometry": {"coordinates":[-74.879902,40.53503],"type":"Point"}
}