{
  "type": "Feature",
  "properties": {
    "addr:full":"667 Shunpike Rd Chatham NJ 07928",
    "addr:housenumber":"667",
    "addr:postcode":"07928",
    "addr:street":"Shunpike Rd",
    "iso:country":"US",
    "sg:address":"667 Shunpike Rd",
    "sg:city":"Chatham",
    "sg:classifiers":[
        {
            "category":"Building & Trades",
            "subcategory":"Construction",
            "type":"Services"
        }
    ],
    "sg:phone":"+1 973 377 5424",
    "sg:postcode":"07928",
    "sg:province":"NJ",
    "sg:tags":[
        "contractor"
    ],
    "wof:name":"Esposito A J",
    "wof:placetype":"venue"
},
  "geometry": {"coordinates":[-74.43356,40.746951],"type":"Point"}
}