{
  "type": "Feature",
  "properties": {
    "iso:country":"US",
    "sg:address":"595 County Ave",
    "sg:city":"Secaucus",
    "sg:classifiers":[
        {
            "category":"Health Services",
            "subcategory":"Nursing And Care Facility",
            "type":"Services"
        }
    ],
    "sg:phone":"+1 201 863 8866",
    "sg:postcode":"07094",
    "sg:province":"NJ",
    "sg:tags":[
        "home",
        "convalescent"
    ],
    "wof:name":"Hudson Manor",
    "wof:placetype":"venue"
},
  "geometry": {"coordinates":[-74.061702,40.776036],"type":"Point"}
}