{
  "type": "Feature",
  "properties": {
    "addr:full":"159 Liberty St Metuchen NJ 08840",
    "addr:housenumber":"159",
    "addr:postcode":"08840",
    "addr:street":"Liberty St",
    "iso:country":"US",
    "sg:address":"159 Liberty St",
    "sg:city":"Metuchen",
    "sg:classifiers":[
        {
            "category":"Manufacturing",
            "subcategory":"Rubber & Plastics",
            "type":"Manufacturing & Wholesale Goods"
        }
    ],
    "sg:phone":"+1 732 549 7100",
    "sg:postcode":"08840",
    "sg:province":"NJ",
    "sg:tags":[
        "product",
        "mfg"
    ],
    "sg:website":"www.valley-extrusions.com",
    "wof:name":"Valley Extrusions",
    "wof:placetype":"venue"
},
  "geometry": {"coordinates":[-74.37187299999999,40.547612],"type":"Point"}
}