{
  "type": "Feature",
  "properties": {
    "iso:country":"US",
    "sg:address":"52 Maplewood Ave",
    "sg:city":"Maplewood",
    "sg:classifiers":[
        {
            "category":"Professional",
            "subcategory":"Computer Services",
            "type":"Services"
        }
    ],
    "sg:phone":"+1 973 761 5417",
    "sg:postcode":"07040",
    "sg:province":"NJ",
    "sg:tags":[
        "related"
    ],
    "wof:name":"Sunrise Assocation",
    "wof:placetype":"venue"
},
  "geometry": {"coordinates":[-74.271681,40.736028],"type":"Point"}
}