{
  "type": "Feature",
  "properties": {
    "addr:full":"511 Ocean Ave Lakewood NJ 08701",
    "addr:housenumber":"511",
    "addr:postcode":"08701",
    "addr:street":"Ocean Ave",
    "iso:country":"US",
    "sg:address":"511 Ocean Ave",
    "sg:city":"Lakewood",
    "sg:classifiers":[
        {
            "category":"Real Estate",
            "subcategory":"Real Estate Agent",
            "type":"Services"
        }
    ],
    "sg:phone":"+1 732 961 9991",
    "sg:postcode":"08701",
    "sg:province":"NJ",
    "wof:name":"First New Jersey Real Property",
    "wof:placetype":"venue"
},
  "geometry": {"coordinates":[-74.19639599999999,40.090683],"type":"Point"}
}