{
  "type": "Feature",
  "properties": {
    "addr:full":"2 Hospital Dr Toms River NJ 08755",
    "addr:housenumber":"2",
    "addr:postcode":"08755",
    "addr:street":"Hospital Dr",
    "iso:country":"US",
    "sg:address":"2 Hospital Dr",
    "sg:city":"Toms River",
    "sg:classifiers":[
        {
            "category":"Professional",
            "subcategory":"Accounting & Tax Preparation",
            "type":"Services"
        }
    ],
    "sg:phone":"+1 732 244 6225",
    "sg:postcode":"08755",
    "sg:province":"NJ",
    "wof:name":"Healthsouth",
    "wof:placetype":"venue"
},
  "geometry": {"coordinates":[-74.21836999999999,39.961191],"type":"Point"}
}