{
  "type": "Feature",
  "properties": {
    "addr:full":"51 US Hwy 1 New Brunswick NJ 08901",
    "addr:housenumber":"51",
    "addr:postcode":"08901",
    "addr:street":"Us Hwy 1",
    "iso:country":"US",
    "sg:address":"51 US Hwy 1",
    "sg:city":"New Brunswick",
    "sg:classifiers":[
        {
            "category":"Shopping",
            "type":"Retail Goods"
        }
    ],
    "sg:phone":"+1 732 937 4664",
    "sg:postcode":"08901",
    "sg:province":"NJ",
    "sg:tags":[
        "hearing",
        "equipment",
        "supply",
        "impaired"
    ],
    "wof:name":"Centers For Hearing Inc",
    "wof:placetype":"venue"
},
  "geometry": {"coordinates":[-74.417281,40.484453],"type":"Point"}
}