{
  "type": "Feature",
  "properties": {
    "iso:country":"US",
    "sg:address":"3646 Central Ave",
    "sg:city":"Ocean City",
    "sg:classifiers":[
        {
            "category":"Professional",
            "subcategory":"Management & Consulting",
            "type":"Services"
        }
    ],
    "sg:phone":"+1   ",
    "sg:postcode":"08226",
    "sg:province":"NJ",
    "sg:tags":[
        "consultant",
        "business"
    ],
    "wof:name":"Ralph E Parkin",
    "wof:placetype":"venue"
},
  "geometry": {"coordinates":[-74.613569,39.247658],"type":"Point"}
}