{
  "type": "Feature",
  "properties": {
    "addr:full":"1774 E 2nd St Scotch Plains NJ 07076",
    "addr:housenumber":"1774",
    "addr:postcode":"07076",
    "addr:street":"E 2Nd St",
    "iso:country":"US",
    "sg:address":"1774 E 2nd St",
    "sg:city":"Scotch Plains",
    "sg:classifiers":[
        {
            "category":"Real Estate",
            "subcategory":"Real Estate Agent",
            "type":"Services"
        }
    ],
    "sg:phone":"+1 908 322 7717",
    "sg:postcode":"07076",
    "sg:province":"NJ",
    "wof:name":"Marks Miler Levy Real Estate",
    "wof:placetype":"venue"
},
  "geometry": {"coordinates":[-74.39777100000001,40.648035],"type":"Point"}
}