{
  "type": "Feature",
  "properties": {
    "addr:full":"107 4th St Elmer NJ 08318",
    "addr:housenumber":"107",
    "addr:postcode":"08318",
    "addr:street":"4Th St",
    "iso:country":"US",
    "sg:address":"107 4th St",
    "sg:city":"Elmer",
    "sg:classifiers":[
        {
            "category":"Building & Trades",
            "subcategory":"Plumbing",
            "type":"Services"
        }
    ],
    "sg:phone":"+1 856 358 3608",
    "sg:postcode":"08318",
    "sg:province":"NJ",
    "sg:tags":[
        "plumbing",
        "contractor"
    ],
    "wof:name":"Robert H Johnson Plumbing",
    "wof:placetype":"venue"
},
  "geometry": {"coordinates":[-75.175608,39.597603],"type":"Point"}
}