{
  "type": "Feature",
  "properties": {
    "addr:full":"39 Maida Ln Howell NJ 07731",
    "addr:housenumber":"39",
    "addr:postcode":"07731",
    "addr:street":"Maida Ln",
    "iso:country":"US",
    "sg:address":"39 Maida Ln",
    "sg:city":"Howell",
    "sg:classifiers":[
        {
            "category":"Building & Trades",
            "subcategory":"Construction",
            "type":"Services"
        }
    ],
    "sg:phone":"+1 732 961 0113",
    "sg:postcode":"07731",
    "sg:province":"NJ",
    "sg:tags":[
        "pond",
        "supply"
    ],
    "wof:name":"Ground Breaking Landscapes",
    "wof:placetype":"venue"
},
  "geometry": {"coordinates":[-74.18662500000001,40.128034],"type":"Point"}
}