{
  "type": "Feature",
  "properties": {
    "iso:country":"US",
    "sg:address":"1027 Erial Rd",
    "sg:city":"Blackwood",
    "sg:classifiers":[
        {
            "category":"Autos & Motor Vehicles",
            "subcategory":"Fuel & Gas Station",
            "type":"Retail Goods"
        }
    ],
    "sg:phone":"+1 856 228 8388",
    "sg:postcode":"08012",
    "sg:province":"NJ",
    "sg:tags":[
        "oil"
    ],
    "wof:name":"H & H Auto Inc",
    "wof:placetype":"venue"
},
  "geometry": {"coordinates":[-75.039919,39.795495],"type":"Point"}
}