{
  "type": "Feature",
  "properties": {
    "addr:full":"347 Van Buren St Newark NJ 07105",
    "addr:housenumber":"347",
    "addr:postcode":"07105",
    "addr:street":"Van Buren St",
    "iso:country":"US",
    "sg:address":"347 Van Buren St",
    "sg:city":"Newark",
    "sg:classifiers":[
        {
            "category":"Restaurant",
            "type":"Food & Drink"
        }
    ],
    "sg:phone":"+1 973 344 8999",
    "sg:postcode":"07105",
    "sg:province":"NJ",
    "sg:tags":[
        "eating"
    ],
    "wof:name":"Little Dinner the",
    "wof:placetype":"venue"
},
  "geometry": {"coordinates":[-74.162003,40.719601],"type":"Point"}
}