{
  "type": "Feature",
  "properties": {
    "iso:country":"US",
    "sg:address":"White Horse Pike & K",
    "sg:city":"Atco",
    "sg:classifiers":[
        {
            "category":"Food & Beverages",
            "subcategory":"Liquor & Beverages",
            "type":"Retail Goods"
        }
    ],
    "sg:phone":"+1 856 767 0483",
    "sg:postcode":"08004",
    "sg:province":"NJ",
    "sg:tags":[
        "beer",
        "spirit",
        "wine"
    ],
    "wof:name":"Best Liquor of Atco",
    "wof:placetype":"venue"
},
  "geometry": {"coordinates":[-74.877098,39.754398],"type":"Point"}
}