{
  "type": "Feature",
  "properties": {
    "iso:country":"US",
    "sg:address":"139 South Mail St",
    "sg:city":"Hackensack",
    "sg:classifiers":[
        {
            "category":"Personal",
            "type":"Services"
        }
    ],
    "sg:phone":"+1 866 766 0500",
    "sg:postcode":"07601",
    "sg:province":"NJ",
    "sg:tags":[
        "mover"
    ],
    "sg:website":"www.usexpressmoving.com",
    "wof:name":"US Express Moving System",
    "wof:placetype":"venue"
},
  "geometry": {"coordinates":[-74.04571300000001,40.873365],"type":"Point"}
}