{
  "type": "Feature",
  "properties": {
    "addr:full":"14 Viburnum Ct Trenton NJ 08648",
    "addr:housenumber":"14",
    "addr:postcode":"08648",
    "addr:street":"Viburnum Ct",
    "iso:country":"US",
    "sg:address":"14 Viburnum Ct",
    "sg:city":"Trenton",
    "sg:classifiers":[
        {
            "category":"Professional",
            "subcategory":"Management & Consulting",
            "type":"Services"
        }
    ],
    "sg:phone":"+1   ",
    "sg:postcode":"08648",
    "sg:province":"NJ",
    "sg:tags":[
        "business"
    ],
    "wof:name":"Linktank LLC",
    "wof:placetype":"venue"
},
  "geometry": {"coordinates":[-74.73670799999999,40.308198],"type":"Point"}
}