{
  "type": "Feature",
  "properties": {
    "addr:full":"3611 Bergen Ct North Bergen NJ 07047",
    "addr:housenumber":"3611",
    "addr:postcode":"07047",
    "addr:street":"Bergen Ct",
    "iso:country":"US",
    "sg:address":"3611 Bergen Ct",
    "sg:city":"North Bergen",
    "sg:classifiers":[
        {
            "category":"Shopping",
            "subcategory":"Catalog Store",
            "type":"Retail Goods"
        }
    ],
    "sg:phone":"+1   ",
    "sg:postcode":"07047",
    "sg:province":"NJ",
    "sg:tags":[
        "mail",
        "house"
    ],
    "wof:name":"V Max",
    "wof:placetype":"venue"
},
  "geometry": {"coordinates":[-74.032644,40.776819],"type":"Point"}
}