{
  "type": "Feature",
  "properties": {
    "addr:full":"407 Ege Ave Jersey City NJ 07304",
    "addr:housenumber":"407",
    "addr:postcode":"07304",
    "addr:street":"Ege Ave",
    "iso:country":"US",
    "sg:address":"407 Ege Ave",
    "sg:city":"Jersey City",
    "sg:classifiers":[
        {
            "category":"Manufacturing",
            "subcategory":"Chemicals & Compounds",
            "type":"Manufacturing & Wholesale Goods"
        }
    ],
    "sg:phone":"+1 201 333 5256",
    "sg:postcode":"07304",
    "sg:province":"NJ",
    "sg:tags":[
        "synthetic",
        "dyestuff",
        "mfg"
    ],
    "wof:name":"Dye Specialties Inc",
    "wof:placetype":"venue"
},
  "geometry": {"coordinates":[-74.090456,40.718201],"type":"Point"}
}