{
  "type": "Feature",
  "properties": {
    "addr:full":"7731 Bergenline Ave # 1 North Bergen NJ 07047",
    "addr:housenumber":"7731",
    "addr:postcode":"07047",
    "addr:street":"Bergenline Ave # 1",
    "iso:country":"US",
    "sg:address":"7731 Bergenline Ave # 1",
    "sg:city":"North Bergen",
    "sg:classifiers":[
        {
            "category":"Wholesale",
            "subcategory":"Home Furnishings",
            "type":"Manufacturing & Wholesale Goods"
        }
    ],
    "sg:phone":"+1 201 869 1120",
    "sg:postcode":"07047",
    "sg:province":"NJ",
    "sg:tags":[
        "blind",
        "shade"
    ],
    "wof:name":"Sosower J & Son",
    "wof:placetype":"venue"
},
  "geometry": {"coordinates":[-74.00749999999999,40.8009],"type":"Point"}
}