{
  "type": "Feature",
  "properties": {
    "addr:full":"204 Monmouth Rd Oakhurst NJ 07755",
    "addr:housenumber":"204",
    "addr:postcode":"07755",
    "addr:street":"Monmouth Rd",
    "iso:country":"US",
    "sg:address":"204 Monmouth Rd",
    "sg:city":"Oakhurst",
    "sg:classifiers":[
        {
            "category":"Personal",
            "subcategory":"Barber",
            "type":"Services"
        }
    ],
    "sg:phone":"+1 732 663 1010",
    "sg:postcode":"07755",
    "sg:province":"NJ",
    "sg:tags":[
        "shop"
    ],
    "wof:name":"Universal Barber Stylist",
    "wof:placetype":"venue"
},
  "geometry": {"coordinates":[-74.012395,40.262426],"type":"Point"}
}