{
  "type": "Feature",
  "properties": {
    "addr:full":"3100 Dune Dr Avalon NJ 08202",
    "addr:housenumber":"3100",
    "addr:postcode":"08202",
    "addr:street":"Dune Dr",
    "iso:country":"US",
    "sg:address":"3100 Dune Dr",
    "sg:city":"Avalon",
    "sg:classifiers":[
        {
            "category":"Government",
            "subcategory":"Office",
            "type":"Public Place"
        }
    ],
    "sg:phone":"+1 609 967 8200",
    "sg:postcode":"08202",
    "sg:province":"NJ",
    "sg:tags":[
        "village"
    ],
    "wof:name":"Avalon Municipal Bldg General",
    "wof:placetype":"venue"
},
  "geometry": {"coordinates":[-74.723422,39.095217],"type":"Point"}
}