{
  "type": "Feature",
  "properties": {
    "iso:country":"US",
    "sg:address":"335 Oak Ave",
    "sg:city":"River Edge",
    "sg:classifiers":[
        {
            "category":"Real Estate",
            "subcategory":"Real Estate Agent",
            "type":"Services"
        }
    ],
    "sg:phone":"+1 201 265 1478",
    "sg:postcode":"07661",
    "sg:province":"NJ",
    "wof:name":"Janie Management",
    "wof:placetype":"venue"
},
  "geometry": {"coordinates":[-74.043193,40.921019],"type":"Point"}
}