{
  "type": "Feature",
  "properties": {
    "iso:country":"US",
    "sg:address":"8 Caesar Pl",
    "sg:city":"Moonachie",
    "sg:classifiers":[
        {
            "category":"Wholesale",
            "subcategory":"Furniture",
            "type":"Manufacturing & Wholesale Goods"
        },
        {
            "category":"Shopping",
            "subcategory":"Clothing, Apparel, & Fashions",
            "type":"Retail Goods"
        }
    ],
    "sg:phone":"+1 201 635 0506",
    "sg:postcode":"07074",
    "sg:province":"NJ",
    "wof:name":"Elite Home Fashion LLC",
    "wof:placetype":"venue"
},
  "geometry": {"coordinates":[-74.067498,40.836193],"type":"Point"}
}