{
  "type": "Feature",
  "properties": {
    "addr:full":"486 State Rte 12 Flemington NJ 08822",
    "addr:housenumber":"486",
    "addr:postcode":"08822",
    "addr:street":"State Rte 12",
    "iso:country":"US",
    "sg:address":"486 State Rte 12",
    "sg:city":"Flemington",
    "sg:classifiers":[
        {
            "category":"Building & Trades",
            "subcategory":"Construction",
            "type":"Services"
        }
    ],
    "sg:phone":"+1 908 284 9509",
    "sg:postcode":"08822",
    "sg:province":"NJ",
    "sg:tags":[
        "carpenter"
    ],
    "wof:name":"Steves Creative Carpentry",
    "wof:placetype":"venue"
},
  "geometry": {"coordinates":[-74.927367,40.508499],"type":"Point"}
}