{
  "type": "Feature",
  "properties": {
    "addr:full":"113 Brahma Ave Bridgewater NJ 08807",
    "addr:housenumber":"113",
    "addr:postcode":"08807",
    "addr:street":"Brahma Ave",
    "iso:country":"US",
    "sg:address":"113 Brahma Ave",
    "sg:city":"Bridgewater",
    "sg:classifiers":[
        {
            "category":"Building & Trades",
            "subcategory":"Plumbing",
            "type":"Services"
        }
    ],
    "sg:phone":"+1 908 526 0823",
    "sg:postcode":"08807",
    "sg:province":"NJ",
    "sg:tags":[
        "plumbing",
        "air",
        "heating",
        "conditioning",
        "contractor"
    ],
    "sg:website":"www.atlasplumbing.net",
    "wof:name":"Atlas Plumbing & Heating Inc",
    "wof:placetype":"venue"
},
  "geometry": {"coordinates":[-74.661075,40.56416],"type":"Point"}
}