{
  "type": "Feature",
  "properties": {
    "iso:country":"US",
    "sg:address":"315 Coles St",
    "sg:city":"Jersey City",
    "sg:classifiers":[
        {
            "category":"Freight",
            "type":"Transportation"
        }
    ],
    "sg:phone":"+1 888 313 4945",
    "sg:postcode":"07310",
    "sg:province":"NJ",
    "sg:tags":[
        "self",
        "storage"
    ],
    "sg:website":"www.americanselfstorage.com",
    "wof:name":"American Self Storage",
    "wof:placetype":"venue"
},
  "geometry": {"coordinates":[-74.04569600000001,40.734924],"type":"Point"}
}