{
  "type": "Feature",
  "properties": {
    "iso:country":"US",
    "sg:address":"1035 Hamburg Tpke",
    "sg:city":"Wayne",
    "sg:classifiers":[
        {
            "category":"Organizations",
            "subcategory":"Religious Organization",
            "type":"Services"
        }
    ],
    "sg:phone":"+1   ",
    "sg:postcode":"07470",
    "sg:province":"NJ",
    "wof:name":"Our Lady Consolation Church",
    "wof:placetype":"venue"
},
  "geometry": {"coordinates":[-74.236073,40.959656],"type":"Point"}
}