{
  "type": "Feature",
  "properties": {
    "iso:country":"US",
    "sg:address":"72 Westfield Ave",
    "sg:city":"Clark",
    "sg:classifiers":[
        {
            "category":"Restaurant",
            "type":"Food & Drink"
        }
    ],
    "sg:phone":"+1   ",
    "sg:postcode":"07066",
    "sg:province":"NJ",
    "sg:tags":[
        "eating"
    ],
    "wof:name":"Luigis Pizza",
    "wof:placetype":"venue"
},
  "geometry": {"coordinates":[-74.29760400000001,40.619096],"type":"Point"}
}