{
  "type": "Feature",
  "properties": {
    "addr:full":"50 Macarthur Ave Lodi NJ 07644",
    "addr:housenumber":"50",
    "addr:postcode":"07644",
    "addr:street":"Macarthur Ave",
    "iso:country":"US",
    "sg:address":"50 Macarthur Ave",
    "sg:city":"Lodi",
    "sg:classifiers":[
        {
            "category":"Professional",
            "type":"Services"
        }
    ],
    "sg:phone":"+1   ",
    "sg:postcode":"07644",
    "sg:province":"NJ",
    "wof:name":"Tone Works",
    "wof:placetype":"venue"
},
  "geometry": {"coordinates":[-74.071071,40.877023],"type":"Point"}
}