{
  "type": "Feature",
  "properties": {
    "addr:full":"681 Newark Ave Elizabeth NJ 07208",
    "addr:housenumber":"681",
    "addr:postcode":"07208",
    "addr:street":"Newark Ave",
    "iso:country":"US",
    "sg:address":"681 Newark Ave",
    "sg:city":"Elizabeth",
    "sg:classifiers":[
        {
            "category":"Restaurant",
            "type":"Food & Drink"
        }
    ],
    "sg:phone":"+1   ",
    "sg:postcode":"07208",
    "sg:province":"NJ",
    "sg:tags":[
        "eating"
    ],
    "wof:name":"Family Buffet",
    "wof:placetype":"venue"
},
  "geometry": {"coordinates":[-74.210382,40.678748],"type":"Point"}
}