{
  "type": "Feature",
  "properties": {
    "addr:full":"90 Bayard St New Brunswick NJ 08901",
    "addr:housenumber":"90",
    "addr:postcode":"08901",
    "addr:street":"Bayard St",
    "iso:country":"US",
    "sg:address":"90 Bayard St",
    "sg:city":"New Brunswick",
    "sg:classifiers":[
        {
            "category":"Professional",
            "subcategory":"Lawyer & Legal Services",
            "type":"Services"
        }
    ],
    "sg:phone":"+1 732 828 6200",
    "sg:postcode":"08901",
    "sg:province":"NJ",
    "sg:tags":[
        "attorney"
    ],
    "wof:name":"Jules G Kollar Esq",
    "wof:placetype":"venue"
},
  "geometry": {"coordinates":[-74.44757199999999,40.493787],"type":"Point"}
}