{
  "type": "Feature",
  "properties": {
    "iso:country":"US",
    "sg:address":"473 Broadway",
    "sg:city":"Bayonne",
    "sg:classifiers":[
        {
            "category":"Communications",
            "subcategory":"Film & Video Production",
            "type":"Services"
        }
    ],
    "sg:phone":"+1   ",
    "sg:postcode":"07002",
    "sg:province":"NJ",
    "sg:tags":[
        "motion",
        "picture"
    ],
    "wof:name":"Crystal Clear Production",
    "wof:placetype":"venue"
},
  "geometry": {"coordinates":[-74.11823099999999,40.663961],"type":"Point"}
}