{
  "type": "Feature",
  "properties": {
    "addr:full":"2355 State Rte 33 Trenton NJ 08691",
    "addr:housenumber":"2355",
    "addr:postcode":"08691",
    "addr:street":"State Rte 33",
    "iso:country":"US",
    "sg:address":"2355 State Rte 33",
    "sg:city":"Trenton",
    "sg:classifiers":[
        {
            "category":"Home & Garden",
            "subcategory":"Furniture",
            "type":"Retail Goods"
        }
    ],
    "sg:phone":"+1 609 259 5552",
    "sg:postcode":"08691",
    "sg:province":"NJ",
    "wof:name":"Transformations Interior",
    "wof:placetype":"venue"
},
  "geometry": {"coordinates":[-74.625874,40.217531],"type":"Point"}
}