{
  "type": "Feature",
  "properties": {
    "iso:country":"US",
    "sg:address":"100 Wagon Wheel Rd",
    "sg:city":"Sparta",
    "sg:classifiers":[
        {
            "category":"Health Services",
            "subcategory":"Chiropractor",
            "type":"Services"
        }
    ],
    "sg:phone":"+1 973 729 9556",
    "sg:postcode":"07871",
    "sg:province":"NJ",
    "wof:name":"Todd Massey DC",
    "wof:placetype":"venue"
},
  "geometry": {"coordinates":[-74.65215499999999,41.037937],"type":"Point"}
}