{
  "type": "Feature",
  "properties": {
    "addr:full":"126 Flocktown Rd Long Valley NJ 07853",
    "addr:housenumber":"126",
    "addr:postcode":"07853",
    "addr:street":"Flocktown Rd",
    "iso:country":"US",
    "sg:address":"126 Flocktown Rd",
    "sg:city":"Long Valley",
    "sg:classifiers":[
        {
            "category":"Building & Trades",
            "subcategory":"Construction",
            "type":"Services"
        }
    ],
    "sg:phone":"+1 908 852 9004",
    "sg:postcode":"07853",
    "sg:province":"NJ",
    "sg:tags":[
        "house"
    ],
    "wof:name":"Clearwater Construction",
    "wof:placetype":"venue"
},
  "geometry": {"coordinates":[-74.79718099999999,40.812608],"type":"Point"}
}