{
  "type": "Feature",
  "properties": {
    "iso:country":"US",
    "sg:address":"12 Ginger Rd",
    "sg:city":"Allentown",
    "sg:classifiers":[
        {
            "category":"Wholesale",
            "subcategory":"Machinery & Supplies",
            "type":"Manufacturing & Wholesale Goods"
        }
    ],
    "sg:phone":"+1 609 259 1623",
    "sg:postcode":"08515",
    "sg:province":"NJ",
    "sg:tags":[
        "industrial"
    ],
    "wof:name":"Eagle Quality Products Inc",
    "wof:placetype":"venue"
},
  "geometry": {"coordinates":[-74.60571299999999,40.122564],"type":"Point"}
}