{
  "type": "Feature",
  "properties": {
    "addr:full":"46 Nottingham Dr Old Bridge NJ 08857",
    "addr:housenumber":"46",
    "addr:postcode":"08857",
    "addr:street":"Nottingham Dr",
    "iso:country":"US",
    "sg:address":"46 Nottingham Dr",
    "sg:city":"Old Bridge",
    "sg:classifiers":[
        {
            "category":"Education",
            "subcategory":"Dance Studio",
            "type":"Public Place"
        }
    ],
    "sg:phone":"+1   ",
    "sg:postcode":"08857",
    "sg:province":"NJ",
    "wof:name":"Dance Power",
    "wof:placetype":"venue"
},
  "geometry": {"coordinates":[-74.28925700000001,40.397618],"type":"Point"}
}