{
  "type": "Feature",
  "properties": {
    "addr:full":"74 Ridge Rd Ridgewood NJ 07450",
    "addr:housenumber":"74",
    "addr:postcode":"07450",
    "addr:street":"Ridge Rd",
    "iso:country":"US",
    "sg:address":"74 Ridge Rd",
    "sg:city":"Ridgewood",
    "sg:classifiers":[
        {
            "category":"Health Services",
            "subcategory":"Doctor",
            "type":"Services"
        }
    ],
    "sg:phone":"+1 201 447 6117",
    "sg:postcode":"07450",
    "sg:province":"NJ",
    "sg:tags":[
        "medical"
    ],
    "wof:name":"Alexander Panossian MD",
    "wof:placetype":"venue"
},
  "geometry": {"coordinates":[-74.123643,40.983462],"type":"Point"}
}