{
  "type": "Feature",
  "properties": {
    "iso:country":"US",
    "sg:address":"196 Newark Ave",
    "sg:city":"Bloomfield",
    "sg:classifiers":[
        {
            "category":"Building & Trades",
            "subcategory":"Cleaning & Sanitation",
            "type":"Services"
        }
    ],
    "sg:phone":"+1 973 680 0430",
    "sg:postcode":"07003",
    "sg:province":"NJ",
    "sg:tags":[
        "maintenance"
    ],
    "wof:name":"Anas Cleaning Service",
    "wof:placetype":"venue"
},
  "geometry": {"coordinates":[-74.19029500000001,40.789516],"type":"Point"}
}