{
  "type": "Feature",
  "properties": {
    "iso:country":"US",
    "sg:address":"90 Woodbridge Ctr Dr",
    "sg:city":"Woodbridge",
    "sg:classifiers":[
        {
            "category":"Shopping",
            "subcategory":"Stationery & Office Supplies",
            "type":"Retail Goods"
        }
    ],
    "sg:phone":"+1 732 283 3647",
    "sg:postcode":"07095",
    "sg:province":"NJ",
    "sg:tags":[
        "equipment"
    ],
    "wof:name":"Arenson Office Furnishings Inc",
    "wof:placetype":"venue"
},
  "geometry": {"coordinates":[-74.298374,40.551444],"type":"Point"}
}