{
  "type": "Feature",
  "properties": {
    "addr:full":"84 W Main St Somerville NJ 08876",
    "addr:housenumber":"84",
    "addr:postcode":"08876",
    "addr:street":"W Main St",
    "iso:country":"US",
    "sg:address":"84 W Main St",
    "sg:city":"Somerville",
    "sg:classifiers":[
        {
            "category":"Shopping",
            "subcategory":"Computers & Home Electronics",
            "type":"Retail Goods"
        }
    ],
    "sg:phone":"+1 908 725 1373",
    "sg:postcode":"08876",
    "sg:province":"NJ",
    "sg:tags":[
        "parts",
        "supply"
    ],
    "sg:website":"www.csm-corp.com",
    "wof:name":"Computer Systems & Methods",
    "wof:placetype":"venue"
},
  "geometry": {"coordinates":[-74.61406100000001,40.568862],"type":"Point"}
}