{
  "type": "Feature",
  "properties": {
    "addr:full":"2814 Palisade Ave Weehawken NJ 07086",
    "addr:housenumber":"2814",
    "addr:postcode":"07086",
    "addr:street":"Palisade Ave",
    "iso:country":"US",
    "sg:address":"2814 Palisade Ave",
    "sg:city":"Weehawken",
    "sg:classifiers":[
        {
            "category":"Retail",
            "subcategory":"Auto Repair",
            "type":"Services"
        }
    ],
    "sg:phone":"+1 201 617 5700",
    "sg:postcode":"07086",
    "sg:province":"NJ",
    "sg:tags":[
        "automotive"
    ],
    "wof:name":"Top of the Line Glass Tinting Inc",
    "wof:placetype":"venue"
},
  "geometry": {"coordinates":[-74.02770700000001,40.769697],"type":"Point"}
}