{
  "type": "Feature",
  "properties": {
    "addr:full":"145 Talmadge Rd Edison NJ 08817",
    "addr:housenumber":"145",
    "addr:postcode":"08817",
    "addr:street":"Talmadge Rd",
    "iso:country":"US",
    "sg:address":"145 Talmadge Rd",
    "sg:city":"Edison",
    "sg:classifiers":[
        {
            "category":"Food & Beverages",
            "subcategory":"Groceries & Convenience Stores",
            "type":"Retail Goods"
        }
    ],
    "sg:phone":"+1 516 938 8811",
    "sg:postcode":"08817",
    "sg:province":"NJ",
    "sg:tags":[
        "grocer"
    ],
    "wof:name":"Twin County Grocers Inc",
    "wof:placetype":"venue"
},
  "geometry": {"coordinates":[-74.394756,40.53508],"type":"Point"}
}