{
  "type": "Feature",
  "properties": {
    "iso:country":"US",
    "sg:address":"106 N Main St",
    "sg:city":"Cape May Court House",
    "sg:classifiers":[
        {
            "category":"Shopping",
            "subcategory":"Beauty & Cosmetics",
            "type":"Retail Goods"
        }
    ],
    "sg:phone":"+1   ",
    "sg:postcode":"08210",
    "sg:province":"NJ",
    "sg:tags":[
        "parlor",
        "massage"
    ],
    "wof:name":"Massage Works Wellness Center",
    "wof:placetype":"venue"
},
  "geometry": {"coordinates":[-74.820834,39.085434],"type":"Point"}
}