{
  "type": "Feature",
  "properties": {
    "iso:country":"US",
    "sg:address":"223 Forest Ave",
    "sg:city":"Medford",
    "sg:classifiers":[
        {
            "category":"Restaurant",
            "type":"Food & Drink"
        }
    ],
    "sg:phone":"+1 856 983 1999",
    "sg:postcode":"08055",
    "sg:province":"NJ",
    "sg:website":"www.beau-rivage.com",
    "wof:name":"Beau Rivage French Restaurant",
    "wof:placetype":"venue"
},
  "geometry": {"coordinates":[-74.847561,39.864273],"type":"Point"}
}