{
  "type": "Feature",
  "properties": {
    "addr:full":"11 Fairfield Ave Little Falls NJ 07424",
    "addr:housenumber":"11",
    "addr:postcode":"07424",
    "addr:street":"Fairfield Ave",
    "iso:country":"US",
    "sg:address":"11 Fairfield Ave",
    "sg:city":"Little Falls",
    "sg:classifiers":[
        {
            "category":"Professional",
            "type":"Services"
        }
    ],
    "sg:phone":"+1 973 890 4057",
    "sg:postcode":"07424",
    "sg:province":"NJ",
    "sg:tags":[
        "establishment"
    ],
    "wof:name":"New Wall Systems",
    "wof:placetype":"venue"
},
  "geometry": {"coordinates":[-74.244197,40.88784],"type":"Point"}
}