{
  "type": "Feature",
  "properties": {
    "addr:full":"170 Fair St Palisades Park NJ 07650",
    "addr:housenumber":"170",
    "addr:postcode":"07650",
    "addr:street":"Fair St",
    "iso:country":"US",
    "sg:address":"170 Fair St",
    "sg:city":"Palisades Park",
    "sg:classifiers":[
        {
            "category":"Home & Garden",
            "subcategory":"Home Furnishings",
            "type":"Retail Goods"
        }
    ],
    "sg:phone":"+1 201 461 4600",
    "sg:postcode":"07650",
    "sg:province":"NJ",
    "sg:tags":[
        "bathroom",
        "fixture",
        "accessory"
    ],
    "wof:name":"Royal Crest Home Fashions Inc",
    "wof:placetype":"venue"
},
  "geometry": {"coordinates":[-74.000901,40.853931],"type":"Point"}
}