{
  "type": "Feature",
  "properties": {
    "addr:full":"613 10th Ave Belmar NJ 07719",
    "addr:housenumber":"613",
    "addr:postcode":"07719",
    "addr:street":"10Th Ave",
    "iso:country":"US",
    "sg:address":"613 10th Ave",
    "sg:city":"Belmar",
    "sg:classifiers":[
        {
            "category":"Health Services",
            "subcategory":"Optometrist",
            "type":"Services"
        }
    ],
    "sg:phone":"+1 732 681 2320",
    "sg:postcode":"07719",
    "sg:province":"NJ",
    "sg:website":"www.visrehab.com",
    "wof:name":"Center For Visual Rehab",
    "wof:placetype":"venue"
},
  "geometry": {"coordinates":[-74.025443,40.179249],"type":"Point"}
}