{
  "type": "Feature",
  "properties": {
    "iso:country":"US",
    "sg:address":"1231 E Elizabeth Ave",
    "sg:city":"Linden",
    "sg:classifiers":[
        {
            "category":"Building & Trades",
            "subcategory":"Construction",
            "type":"Services"
        }
    ],
    "sg:phone":"+1 800 734 7713",
    "sg:postcode":"07036",
    "sg:province":"NJ",
    "sg:tags":[
        "nonresidential"
    ],
    "wof:name":"Atul Construction Co",
    "wof:placetype":"venue"
},
  "geometry": {"coordinates":[-74.239642,40.64277],"type":"Point"}
}