{
  "type": "Feature",
  "properties": {
    "iso:country":"US",
    "sg:address":"711 Marshall Pl",
    "sg:city":"Plainfield",
    "sg:classifiers":[
        {
            "category":"Professional",
            "subcategory":"Business Services",
            "type":"Services"
        }
    ],
    "sg:phone":"+1   ",
    "sg:postcode":"07062",
    "sg:province":"NJ",
    "wof:name":"Thorpe Assoc",
    "wof:placetype":"venue"
},
  "geometry": {"coordinates":[-74.396621,40.630657],"type":"Point"}
}