{
  "type": "Feature",
  "properties": {
    "iso:country":"US",
    "sg:address":"60 Oxford Rd",
    "sg:city":"Holmdel",
    "sg:classifiers":[
        {
            "category":"Wholesale",
            "subcategory":"Home Furnishings",
            "type":"Manufacturing & Wholesale Goods"
        }
    ],
    "sg:phone":"+1 732 706 5404",
    "sg:postcode":"07733",
    "sg:province":"NJ",
    "wof:name":"Aysegul Enterprises",
    "wof:placetype":"venue"
},
  "geometry": {"coordinates":[-74.14376799999999,40.417828],"type":"Point"}
}