{
  "type": "Feature",
  "properties": {
    "addr:full":"90 Michigan Ave Paterson NJ 07503",
    "addr:housenumber":"90",
    "addr:postcode":"07503",
    "addr:street":"Michigan Ave",
    "iso:country":"US",
    "sg:address":"90 Michigan Ave",
    "sg:city":"Paterson",
    "sg:classifiers":[
        {
            "category":"Wholesale",
            "subcategory":"Fruits & Vegetables",
            "type":"Manufacturing & Wholesale Goods"
        }
    ],
    "sg:phone":"+1 973 881 8701",
    "sg:postcode":"07503",
    "sg:province":"NJ",
    "sg:tags":[
        "banana"
    ],
    "wof:name":"Mac Car Intl Trading",
    "wof:placetype":"venue"
},
  "geometry": {"coordinates":[-74.154652,40.893677],"type":"Point"}
}