{
  "type": "Feature",
  "properties": {
    "iso:country":"US",
    "sg:address":"133 Park Ave",
    "sg:city":"East Orange",
    "sg:classifiers":[
        {
            "category":"Education",
            "subcategory":"Preschool",
            "type":"Public Place"
        },
        {
            "category":"Education",
            "subcategory":"School",
            "type":"Public Place"
        }
    ],
    "sg:phone":"+1 973 678 2966",
    "sg:postcode":"07017",
    "sg:province":"NJ",
    "sg:tags":[
        "elementary"
    ],
    "wof:name":"Little Philosopher School of Learning the",
    "wof:placetype":"venue"
},
  "geometry": {"coordinates":[-74.198402,40.763302],"type":"Point"}
}