{
  "type": "Feature",
  "properties": {
    "addr:full":"2 Executive Dr Somerset NJ 08873",
    "addr:housenumber":"2",
    "addr:postcode":"08873",
    "addr:street":"Executive Dr",
    "iso:country":"US",
    "sg:address":"2 Executive Dr",
    "sg:city":"Somerset",
    "sg:classifiers":[
        {
            "category":"Banks & Credit Unions",
            "subcategory":"Bank",
            "type":"Services"
        }
    ],
    "sg:phone":"+1 908 203 8680",
    "sg:postcode":"08873",
    "sg:province":"NJ",
    "sg:tags":[
        "loan",
        "real estate"
    ],
    "wof:name":"First Hallmark Mortgage Corp",
    "wof:placetype":"venue"
},
  "geometry": {"coordinates":[-74.521058,40.543436],"type":"Point"}
}