{
  "type": "Feature",
  "properties": {
    "addr:full":"329 Park Edison NJ 08837",
    "addr:housenumber":"329",
    "addr:postcode":"08837",
    "addr:street":"Park Edison",
    "iso:country":"US",
    "sg:address":"329 Park",
    "sg:city":"Edison",
    "sg:classifiers":[
        {
            "category":"Food & Beverages",
            "subcategory":"Specialty",
            "type":"Retail Goods"
        }
    ],
    "sg:phone":"+1 732 603 8288",
    "sg:postcode":"08837",
    "sg:province":"NJ",
    "sg:tags":[
        "health",
        "diet"
    ],
    "sg:website":"www.gnc.com",
    "wof:name":"GNC",
    "wof:placetype":"venue"
},
  "geometry": {"coordinates":[-74.338306,40.549446],"type":"Point"}
}