{
  "type": "Feature",
  "properties": {
    "iso:country":"US",
    "sg:address":"12 Roosevelt Ave",
    "sg:city":"Northfield",
    "sg:classifiers":[
        {
            "category":"Retail",
            "subcategory":"Auto Repair",
            "type":"Services"
        }
    ],
    "sg:phone":"+1 609 344 0141",
    "sg:postcode":"08225",
    "sg:province":"NJ",
    "sg:tags":[
        "general"
    ],
    "wof:name":"Panettas Auto Repair Service",
    "wof:placetype":"venue"
},
  "geometry": {"coordinates":[-74.545721,39.372514],"type":"Point"}
}