{
  "type": "Feature",
  "properties": {
    "addr:full":"20 Jill Ct Edison NJ 08817",
    "addr:housenumber":"20",
    "addr:postcode":"08817",
    "addr:street":"Jill Ct",
    "iso:country":"US",
    "sg:address":"20 Jill Ct",
    "sg:city":"Edison",
    "sg:classifiers":[
        {
            "category":"Home & Garden",
            "subcategory":"Household Appliances",
            "type":"Retail Goods"
        },
        {
            "category":"Retail",
            "subcategory":"Laundry & Dry Cleaning",
            "type":"Services"
        },
        {
            "category":"Building & Trades",
            "subcategory":"Cleaning & Sanitation",
            "type":"Services"
        }
    ],
    "sg:phone":"+1 732 985 5599",
    "sg:postcode":"08817",
    "sg:province":"NJ",
    "sg:tags":[
        "cleaner",
        "upholstery",
        "duct",
        "house",
        "rug",
        "air",
        "ventilation",
        "cleaning-industrial",
        "vacuum",
        "curtain",
        "drapery",
        "carpet"
    ],
    "sg:website":"http://www.servicemasterclean.com/reslf/smclean_leadform.asp?url=http://www.servicemasterclean.com/reslf/smclean_leadform.asp&partnerName=YellowPages.com&adName=yptl&HGProp=SMClean",
    "wof:name":"ServiceMaster Clean",
    "wof:placetype":"venue"
},
  "geometry": {"coordinates":[-74.396978,40.498661],"type":"Point"}
}