{
  "type": "Feature",
  "properties": {
    "iso:country":"US",
    "sg:address":"1083 High Mountain Rd",
    "sg:city":"Franklin Lakes",
    "sg:classifiers":[
        {
            "category":"Professional",
            "type":"Services"
        }
    ],
    "sg:phone":"+1   ",
    "sg:postcode":"07417",
    "sg:province":"NJ",
    "wof:name":"Rollo A Michaelle",
    "wof:placetype":"venue"
},
  "geometry": {"coordinates":[-74.220012,41.012311],"type":"Point"}
}