{
  "type": "Feature",
  "properties": {
    "iso:country":"US",
    "sg:address":"5 Vernon Crossing Rd",
    "sg:city":"Vernon",
    "sg:classifiers":[
        {
            "category":"Manufacturing",
            "subcategory":"Building Materials",
            "type":"Manufacturing & Wholesale Goods"
        },
        {
            "category":"Home & Garden",
            "subcategory":"Home Furnishings",
            "type":"Retail Goods"
        },
        {
            "category":"Manufacturing",
            "subcategory":"Glass & Minerals",
            "type":"Manufacturing & Wholesale Goods"
        },
        {
            "category":"Retail",
            "subcategory":"Auto Repair",
            "type":"Services"
        }
    ],
    "sg:phone":"+1 866 986 4252",
    "sg:postcode":"07462",
    "sg:province":"NJ",
    "sg:tags":[
        "plate",
        "window",
        "accessory",
        "glass-auto",
        "doors",
        "mirror",
        "frames",
        "windshield",
        "glass-block"
    ],
    "wof:name":"Country Glass Shop",
    "wof:placetype":"venue"
},
  "geometry": {"coordinates":[-74.486819,41.209537],"type":"Point"}
}