{
  "type": "Feature",
  "properties": {
    "addr:full":"753 Broadway Newark NJ 07104",
    "addr:housenumber":"753",
    "addr:postcode":"07104",
    "addr:street":"Broadway",
    "iso:country":"US",
    "sg:address":"753 Broadway",
    "sg:city":"Newark",
    "sg:classifiers":[
        {
            "category":"Personal",
            "subcategory":"Beauty Salon",
            "type":"Services"
        }
    ],
    "sg:phone":"+1 973 484 2266",
    "sg:postcode":"07104",
    "sg:province":"NJ",
    "sg:tags":[
        "shop"
    ],
    "wof:name":"Dons & Divas Hair Salon",
    "wof:placetype":"venue"
},
  "geometry": {"coordinates":[-74.158953,40.775177],"type":"Point"}
}