{
  "type": "Feature",
  "properties": {
    "addr:full":"29 Eastern Ct Willingboro NJ 08046",
    "addr:housenumber":"29",
    "addr:postcode":"08046",
    "addr:street":"Eastern Ct",
    "iso:country":"US",
    "sg:address":"29 Eastern Ct",
    "sg:city":"Willingboro",
    "sg:classifiers":[
        {
            "category":"Building & Trades",
            "subcategory":"Construction",
            "type":"Services"
        }
    ],
    "sg:phone":"+1 609 877 0563",
    "sg:postcode":"08046",
    "sg:province":"NJ",
    "sg:tags":[
        "house"
    ],
    "wof:name":"Bell Home Improvement",
    "wof:placetype":"venue"
},
  "geometry": {"coordinates":[-74.86269299999999,40.025043],"type":"Point"}
}