{
  "type": "Feature",
  "properties": {
    "addr:full":"11 N Dean St Englewood NJ 07631",
    "addr:housenumber":"11",
    "addr:postcode":"07631",
    "addr:street":"N Dean St",
    "iso:country":"US",
    "sg:address":"11 N Dean St",
    "sg:city":"Englewood",
    "sg:classifiers":[
        {
            "category":"Health Services",
            "subcategory":"Clinic",
            "type":"Services"
        }
    ],
    "sg:phone":"+1 201 541 7601",
    "sg:postcode":"07631",
    "sg:province":"NJ",
    "wof:name":"Mind Body & Nutrition Fitness",
    "wof:placetype":"venue"
},
  "geometry": {"coordinates":[-73.974209,40.893698],"type":"Point"}
}