{
  "type": "Feature",
  "properties": {
    "addr:full":"33 Pagoda Ct Trenton NJ 08648",
    "addr:housenumber":"33",
    "addr:postcode":"08648",
    "addr:street":"Pagoda Ct",
    "iso:country":"US",
    "sg:address":"33 Pagoda Ct",
    "sg:city":"Trenton",
    "sg:classifiers":[
        {
            "category":"Manufacturing",
            "subcategory":"Tools & Machinery",
            "type":"Manufacturing & Wholesale Goods"
        }
    ],
    "sg:phone":"+1 609 912 0508",
    "sg:postcode":"08648",
    "sg:province":"NJ",
    "sg:tags":[
        "photographic",
        "mfg"
    ],
    "wof:name":"Photo Medium Ltd",
    "wof:placetype":"venue"
},
  "geometry": {"coordinates":[-74.735829,40.302382],"type":"Point"}
}