{
  "type": "Feature",
  "properties": {
    "iso:country":"US",
    "sg:address":"997 Lenox Dr",
    "sg:city":"Lawrenceville",
    "sg:classifiers":[
        {
            "category":"Professional",
            "subcategory":"Lawyer & Legal Services",
            "type":"Services"
        }
    ],
    "sg:phone":"+1 609 896 7655",
    "sg:postcode":"08648",
    "sg:province":"NJ",
    "sg:tags":[
        "attorney"
    ],
    "wof:name":"Peter F Kelly",
    "wof:placetype":"venue"
},
  "geometry": {"coordinates":[-74.705158,40.287796],"type":"Point"}
}