{
  "type": "Feature",
  "properties": {
    "iso:country":"US",
    "sg:address":"53 Bentwood Dr",
    "sg:city":"Westampton",
    "sg:classifiers":[
        {
            "category":"Organizations",
            "subcategory":"Professional Association",
            "type":"Services"
        }
    ],
    "sg:phone":"+1 609 871 7437",
    "sg:postcode":"08060",
    "sg:province":"NJ",
    "sg:tags":[
        "agency",
        "bureau",
        "entertainment"
    ],
    "wof:name":"Doe Foe Lo Managment",
    "wof:placetype":"venue"
},
  "geometry": {"coordinates":[-74.850967,40.020851],"type":"Point"}
}