{
  "type": "Feature",
  "properties": {
    "addr:full":"148 Myer St Hackensack NJ 07601",
    "addr:housenumber":"148",
    "addr:postcode":"07601",
    "addr:street":"Myer St",
    "iso:country":"US",
    "sg:address":"148 Myer St",
    "sg:city":"Hackensack",
    "sg:classifiers":[
        {
            "category":"Building & Trades",
            "subcategory":"Plumbing",
            "type":"Services"
        }
    ],
    "sg:phone":"+1 201 261 5113",
    "sg:postcode":"07601",
    "sg:province":"NJ",
    "sg:tags":[
        "plumbing",
        "contractor"
    ],
    "wof:name":"All Clear Inc",
    "wof:placetype":"venue"
},
  "geometry": {"coordinates":[-74.049449,40.881693],"type":"Point"}
}