{
  "type": "Feature",
  "properties": {
    "addr:full":"105 E Main St Moorestown NJ 08057",
    "addr:housenumber":"105",
    "addr:postcode":"08057",
    "addr:street":"E Main St",
    "iso:country":"US",
    "sg:address":"105 E Main St",
    "sg:city":"Moorestown",
    "sg:classifiers":[
        {
            "category":"Utilities",
            "subcategory":"Telephone",
            "type":"Services"
        }
    ],
    "sg:phone":"+1 856 772 9950",
    "sg:postcode":"08057",
    "sg:province":"NJ",
    "sg:tags":[
        "communication"
    ],
    "wof:name":"Verizon",
    "wof:placetype":"venue"
},
  "geometry": {"coordinates":[-74.940727,39.965869],"type":"Point"}
}