{
  "type": "Feature",
  "properties": {
    "addr:full":"26 Hopewell Ave Flemington NJ 08822",
    "addr:housenumber":"26",
    "addr:postcode":"08822",
    "addr:street":"Hopewell Ave",
    "iso:country":"US",
    "sg:address":"26 Hopewell Ave",
    "sg:city":"Flemington",
    "sg:classifiers":[
        {
            "category":"Home & Garden",
            "subcategory":"Garden Supply",
            "type":"Retail Goods"
        }
    ],
    "sg:phone":"+1 908 782 1996",
    "sg:postcode":"08822",
    "sg:province":"NJ",
    "sg:tags":[
        "lawn",
        "mower"
    ],
    "wof:name":"Agway",
    "wof:placetype":"venue"
},
  "geometry": {"coordinates":[-74.857311,40.516013],"type":"Point"}
}