{
  "type": "Feature",
  "properties": {
    "addr:full":"900 Route 168 Blackwood NJ 08012",
    "addr:housenumber":"900",
    "addr:postcode":"08012",
    "addr:street":"Route 168",
    "iso:country":"US",
    "sg:address":"900 Route 168",
    "sg:city":"Blackwood",
    "sg:classifiers":[
        {
            "category":"Health Services",
            "subcategory":"Doctor",
            "type":"Services"
        }
    ],
    "sg:phone":"+1 856 227 7488",
    "sg:postcode":"08012",
    "sg:province":"NJ",
    "sg:tags":[
        "physician",
        "surgeons",
        "hematology",
        "blood",
        "dermatology",
        "surgeon"
    ],
    "sg:website":"http://sjdermatology.com",
    "wof:name":"South Jersey Dermatology Associates",
    "wof:placetype":"venue"
},
  "geometry": {"coordinates":[-75.05275,39.777746],"type":"Point"}
}