{
  "type": "Feature",
  "properties": {
    "iso:country":"US",
    "sg:address":"557 Main St",
    "sg:city":"Orange",
    "sg:classifiers":[
        {
            "category":"Sports & Exercise",
            "subcategory":"Gym",
            "type":"Entertainment"
        }
    ],
    "sg:phone":"+1 973 416 9595",
    "sg:postcode":"07050",
    "sg:province":"NJ",
    "sg:website":"www.boxzing.com/",
    "wof:name":"Gladiators Boxing Gym",
    "wof:placetype":"venue"
},
  "geometry": {"coordinates":[-74.23799699999999,40.776114],"type":"Point"}
}