{
  "type": "Feature",
  "properties": {
    "addr:full":"601 Berkley St Camden NJ 08103",
    "addr:housenumber":"601",
    "addr:postcode":"08103",
    "addr:street":"Berkley St",
    "iso:country":"US",
    "sg:address":"601 Berkley St",
    "sg:city":"Camden",
    "sg:classifiers":[
        {
            "category":"Professional",
            "subcategory":"Computer Services",
            "type":"Services"
        }
    ],
    "sg:phone":"+1 856 365 0600",
    "sg:postcode":"08103",
    "sg:province":"NJ",
    "sg:tags":[
        "information",
        "technology"
    ],
    "wof:name":"Stenstrom Scientific",
    "wof:placetype":"venue"
},
  "geometry": {"coordinates":[-75.11686,39.939192],"type":"Point"}
}