{
  "type": "Feature",
  "properties": {
    "iso:country":"US",
    "sg:address":"1857 Oak Tree Rd",
    "sg:city":"Edison",
    "sg:classifiers":[
        {
            "category":"Professional",
            "subcategory":"Business Services",
            "type":"Services"
        }
    ],
    "sg:phone":"+1   ",
    "sg:postcode":"08820",
    "sg:province":"NJ",
    "wof:name":"John Alo Enterprises",
    "wof:placetype":"venue"
},
  "geometry": {"coordinates":[-74.357298,40.571719],"type":"Point"}
}