{
  "type": "Feature",
  "properties": {
    "addr:full":"434 Ridgedale Ave East Hanover NJ 07936",
    "addr:housenumber":"434",
    "addr:postcode":"07936",
    "addr:street":"Ridgedale Ave",
    "iso:country":"US",
    "sg:address":"434 Ridgedale Ave",
    "sg:city":"East Hanover",
    "sg:classifiers":[
        {
            "category":"Building & Trades",
            "subcategory":"Locksmith",
            "type":"Services"
        }
    ],
    "sg:phone":"+1 888 528 9075",
    "sg:postcode":"07936",
    "sg:province":"NJ",
    "sg:tags":[
        "key"
    ],
    "wof:name":"1 24 Hour Emergency Locksmith",
    "wof:placetype":"venue"
},
  "geometry": {"coordinates":[-74.359278,40.826781],"type":"Point"}
}