{
  "type": "Feature",
  "properties": {
    "addr:full":"248 Columbia Tpke Florham Park NJ 07932",
    "addr:housenumber":"248",
    "addr:postcode":"07932",
    "addr:street":"Columbia Tpke",
    "iso:country":"US",
    "sg:address":"248 Columbia Tpke",
    "sg:city":"Florham Park",
    "sg:classifiers":[
        {
            "category":"Shopping",
            "subcategory":"Computers & Home Electronics",
            "type":"Retail Goods"
        }
    ],
    "sg:phone":"+1 973 360 0750",
    "sg:postcode":"07932",
    "sg:province":"NJ",
    "sg:tags":[
        "towing",
        "software"
    ],
    "sg:website":"www.accessig.com",
    "wof:name":"Access International Group Inc",
    "wof:placetype":"venue"
},
  "geometry": {"coordinates":[-74.397903,40.789101],"type":"Point"}
}