{
  "type": "Feature",
  "properties": {
    "addr:full":"570 Rahway Ave Woodbridge NJ 07095",
    "addr:housenumber":"570",
    "addr:postcode":"07095",
    "addr:street":"Rahway Ave",
    "iso:country":"US",
    "sg:address":"570 Rahway Ave",
    "sg:city":"Woodbridge",
    "sg:classifiers":[
        {
            "category":"Professional",
            "subcategory":"Lawyer & Legal Services",
            "type":"Services"
        }
    ],
    "sg:phone":"+1 732 634 1770",
    "sg:postcode":"07095",
    "sg:province":"NJ",
    "wof:name":"Russo Alfred & Casey Timothy",
    "wof:placetype":"venue"
},
  "geometry": {"coordinates":[-74.274101,40.5606],"type":"Point"}
}