{
  "type": "Feature",
  "properties": {
    "iso:country":"US",
    "sg:address":"205 Main St",
    "sg:city":"South Amboy",
    "sg:classifiers":[
        {
            "category":"Shopping",
            "subcategory":"Used Merchandise",
            "type":"Retail Goods"
        }
    ],
    "sg:phone":"+1   ",
    "sg:postcode":"08879",
    "sg:province":"NJ",
    "wof:name":"Tin Lizzie Antiques",
    "wof:placetype":"venue"
},
  "geometry": {"coordinates":[-74.284656,40.485535],"type":"Point"}
}