{
  "type": "Feature",
  "properties": {
    "iso:country":"US",
    "sg:address":"63 Sip Ave",
    "sg:city":"Jersey City",
    "sg:classifiers":[
        {
            "category":"Health Services",
            "subcategory":"Doctor",
            "type":"Services"
        }
    ],
    "sg:phone":"+1 201 239 9200",
    "sg:postcode":"07306",
    "sg:province":"NJ",
    "sg:tags":[
        "physician",
        "surgeon"
    ],
    "wof:name":"Hudson Primary Care Pro",
    "wof:placetype":"venue"
},
  "geometry": {"coordinates":[-74.061257,40.730422],"type":"Point"}
}