{
  "type": "Feature",
  "properties": {
    "addr:full":"370 E Main St Somerville NJ 08876",
    "addr:housenumber":"370",
    "addr:postcode":"08876",
    "addr:street":"E Main St",
    "iso:country":"US",
    "sg:address":"370 E Main St",
    "sg:city":"Somerville",
    "sg:classifiers":[
        {
            "category":"Professional",
            "subcategory":"Engineering",
            "type":"Services"
        }
    ],
    "sg:phone":"+1   ",
    "sg:postcode":"08876",
    "sg:province":"NJ",
    "sg:tags":[
        "civil",
        "surveying"
    ],
    "wof:name":"Parker Engrg & Surveying PC",
    "wof:placetype":"venue"
},
  "geometry": {"coordinates":[-74.596881,40.565359],"type":"Point"}
}