{
  "type": "Feature",
  "properties": {
    "iso:country":"US",
    "sg:address":"3 Hoagland Rd",
    "sg:city":"Flemington",
    "sg:classifiers":[
        {
            "category":"Professional",
            "type":"Services"
        }
    ],
    "sg:phone":"+1 908 788 7030",
    "sg:postcode":"08822",
    "sg:province":"NJ",
    "sg:tags":[
        "establishment"
    ],
    "wof:name":"James Hager Jr Inc",
    "wof:placetype":"venue"
},
  "geometry": {"coordinates":[-74.772059,40.548935],"type":"Point"}
}