{
  "type": "Feature",
  "properties": {
    "iso:country":"US",
    "sg:address":"137 S Main St",
    "sg:city":"Glassboro",
    "sg:classifiers":[
        {
            "category":"Organizations",
            "subcategory":"Religious Organization",
            "type":"Services"
        }
    ],
    "sg:phone":"+1 856 881 2257",
    "sg:postcode":"08028",
    "sg:province":"NJ",
    "sg:tags":[
        "church"
    ],
    "wof:name":"Bethlehem United Church Christ",
    "wof:placetype":"venue"
},
  "geometry": {"coordinates":[-75.113016,39.69871],"type":"Point"}
}