{
  "type": "Feature",
  "properties": {
    "addr:full":"50 May St Hawthorne NJ 07506",
    "addr:housenumber":"50",
    "addr:postcode":"07506",
    "addr:street":"May St",
    "iso:country":"US",
    "sg:address":"50 May St",
    "sg:city":"Hawthorne",
    "sg:classifiers":[
        {
            "category":"Home & Garden",
            "subcategory":"Building Materials",
            "type":"Retail Goods"
        },
        {
            "category":"Building & Trades",
            "subcategory":"Construction",
            "type":"Services"
        }
    ],
    "sg:phone":"+1 973 636 9696",
    "sg:postcode":"07506",
    "sg:province":"NJ",
    "sg:tags":[
        "improvement"
    ],
    "wof:name":"Integrity Home Improvements",
    "wof:placetype":"venue"
},
  "geometry": {"coordinates":[-74.157754,40.942515],"type":"Point"}
}