{
  "type": "Feature",
  "properties": {
    "iso:country":"US",
    "sg:address":"879 State Rte 10",
    "sg:city":"Randolph",
    "sg:classifiers":[
        {
            "category":"Real Estate",
            "subcategory":"Real Estate Agent",
            "type":"Services"
        }
    ],
    "sg:phone":"+1   ",
    "sg:postcode":"07869",
    "sg:province":"NJ",
    "wof:name":"Campo and Campo",
    "wof:placetype":"venue"
},
  "geometry": {"coordinates":[-74.59392800000001,40.859323],"type":"Point"}
}