{
  "type": "Feature",
  "properties": {
    "addr:full":"524 N West Blvd Vineland NJ 08360",
    "addr:housenumber":"524",
    "addr:postcode":"08360",
    "addr:street":"N West Blvd",
    "iso:country":"US",
    "sg:address":"524 N West Blvd",
    "sg:city":"Vineland",
    "sg:classifiers":[
        {
            "category":"Shopping",
            "subcategory":"Pharmacy",
            "type":"Retail Goods"
        }
    ],
    "sg:phone":"+1 856 563 0444",
    "sg:postcode":"08360",
    "sg:province":"NJ",
    "wof:name":"Compu PHARM-Aps Corp",
    "wof:placetype":"venue"
},
  "geometry": {"coordinates":[-75.02543,39.496545],"type":"Point"}
}