{
  "type": "Feature",
  "properties": {
    "addr:full":"617 State Rte 37 Toms River NJ 08755",
    "addr:housenumber":"617",
    "addr:postcode":"08755",
    "addr:street":"State Rte 37",
    "iso:country":"US",
    "sg:address":"617 State Rte 37",
    "sg:city":"Toms River",
    "sg:classifiers":[
        {
            "category":"Insurance",
            "subcategory":"Insurance Agent",
            "type":"Services"
        }
    ],
    "sg:phone":"+1 732 473 0100",
    "sg:postcode":"08755",
    "sg:province":"NJ",
    "wof:name":"State Farm Insurance",
    "wof:placetype":"venue"
},
  "geometry": {"coordinates":[-74.230424,39.968316],"type":"Point"}
}