{
  "type": "Feature",
  "properties": {
    "addr:full":"238 Ramtown-Greenville Rd Howell NJ 07731",
    "addr:housenumber":"238",
    "addr:postcode":"07731",
    "addr:street":"Ramtown-Greenville Rd",
    "iso:country":"US",
    "sg:address":"238 Ramtown-Greenville Rd",
    "sg:city":"Howell",
    "sg:classifiers":[
        {
            "category":"Autos & Motor Vehicles",
            "subcategory":"Auto Supplies",
            "type":"Retail Goods"
        }
    ],
    "sg:phone":"+1 732 458 3966",
    "sg:postcode":"07731",
    "sg:province":"NJ",
    "sg:tags":[
        "automobile",
        "parts"
    ],
    "wof:name":"Jeepster Man Inc",
    "wof:placetype":"venue"
},
  "geometry": {"coordinates":[-74.152541,40.11307],"type":"Point"}
}