{
  "type": "Feature",
  "properties": {
    "iso:country":"US",
    "sg:address":"6010 Black Horse Pike",
    "sg:city":"Egg Harbor Township",
    "sg:classifiers":[
        {
            "category":"Health Services",
            "subcategory":"Hospital",
            "type":"Services"
        }
    ],
    "sg:phone":"+1 609 646 5143",
    "sg:postcode":"08234",
    "sg:province":"NJ",
    "sg:tags":[
        "specialty"
    ],
    "wof:name":"Alcohol & Drug Abuse Unit",
    "wof:placetype":"venue"
},
  "geometry": {"coordinates":[-74.61912100000001,39.439751],"type":"Point"}
}