{
  "type": "Feature",
  "properties": {
    "iso:country":"US",
    "sg:address":"21 Zev Ct",
    "sg:city":"Monmouth Junction",
    "sg:classifiers":[
        {
            "category":"Professional",
            "subcategory":"Management & Consulting",
            "type":"Services"
        }
    ],
    "sg:phone":"+1   ",
    "sg:postcode":"08852",
    "sg:province":"NJ",
    "sg:tags":[
        "business"
    ],
    "wof:name":"Axxom Consulting Inc",
    "wof:placetype":"venue"
},
  "geometry": {"coordinates":[-74.557366,40.410158],"type":"Point"}
}