{
  "type": "Feature",
  "properties": {
    "addr:full":"628 3rd Ave Elizabeth NJ 07202",
    "addr:housenumber":"628",
    "addr:postcode":"07202",
    "addr:street":"3Rd Ave",
    "iso:country":"US",
    "sg:address":"628 3rd Ave",
    "sg:city":"Elizabeth",
    "sg:classifiers":[
        {
            "category":"Health Services",
            "subcategory":"Medical Lab",
            "type":"Services"
        }
    ],
    "sg:phone":"+1 908 558 1143",
    "sg:postcode":"07202",
    "sg:province":"NJ",
    "sg:tags":[
        "laboratory",
        "dentist",
        "dental"
    ],
    "wof:name":"Supreme Dental Lab",
    "wof:placetype":"venue"
},
  "geometry": {"coordinates":[-74.2052,40.655602],"type":"Point"}
}