{
  "type": "Feature",
  "properties": {
    "iso:country":"US",
    "sg:address":"114 Ashmore Ave",
    "sg:city":"Trenton",
    "sg:classifiers":[
        {
            "category":"Building & Trades",
            "subcategory":"Construction",
            "type":"Services"
        }
    ],
    "sg:phone":"+1 609 278 5167",
    "sg:postcode":"08611",
    "sg:province":"NJ",
    "sg:tags":[
        "roofing",
        "contractor"
    ],
    "wof:name":"Improvements By George Inc",
    "wof:placetype":"venue"
},
  "geometry": {"coordinates":[-74.74236000000001,40.209592],"type":"Point"}
}