{
  "type": "Feature",
  "properties": {
    "addr:full":"2891 State Rte 73 Maple Shade NJ 08052",
    "addr:housenumber":"2891",
    "addr:postcode":"08052",
    "addr:street":"State Rte 73 Maple",
    "iso:country":"US",
    "sg:address":"2891 State Rte 73",
    "sg:city":"Maple Shade",
    "sg:classifiers":[
        {
            "category":"Retail",
            "subcategory":"Self-service Laundry",
            "type":"Services"
        }
    ],
    "sg:phone":"+1 856 667 6653",
    "sg:postcode":"08052",
    "sg:province":"NJ",
    "sg:tags":[
        "coin",
        "cleaning"
    ],
    "wof:name":"Maytag Equipped Laundromat",
    "wof:placetype":"venue"
},
  "geometry": {"coordinates":[-74.985013,39.947397],"type":"Point"}
}