{
  "type": "Feature",
  "properties": {
    "addr:full":"532 Old Marlton Pike W Marlton NJ 08053",
    "addr:housenumber":"532",
    "addr:postcode":"08053",
    "addr:street":"Old Marlton Pike W Marlton",
    "iso:country":"US",
    "sg:address":"532 Old Marlton Pike W",
    "sg:city":"Marlton",
    "sg:classifiers":[
        {
            "category":"Wholesale",
            "subcategory":"Non-durable Goods",
            "type":"Manufacturing & Wholesale Goods"
        }
    ],
    "sg:phone":"+1 856 751 8917",
    "sg:postcode":"08053",
    "sg:province":"NJ",
    "sg:tags":[
        "merchandise",
        "general"
    ],
    "wof:name":"David Cooper Sales",
    "wof:placetype":"venue"
},
  "geometry": {"coordinates":[-74.93251600000001,39.893161],"type":"Point"}
}