{
  "type": "Feature",
  "properties": {
    "iso:country":"US",
    "sg:address":"124 S White Horse Pike",
    "sg:city":"Berlin",
    "sg:classifiers":[
        {
            "category":"Health Services",
            "subcategory":"Doctor",
            "type":"Services"
        }
    ],
    "sg:phone":"+1 856 767 2500",
    "sg:postcode":"08009",
    "sg:province":"NJ",
    "sg:tags":[
        "medical"
    ],
    "wof:name":"Advanced Eye Care Laser Ctr PC",
    "wof:placetype":"venue"
},
  "geometry": {"coordinates":[-74.930542,39.792943],"type":"Point"}
}