{
  "type": "Feature",
  "properties": {
    "addr:full":"116 E Main St Ramsey NJ 07446",
    "addr:housenumber":"116",
    "addr:postcode":"07446",
    "addr:street":"E Main St",
    "iso:country":"US",
    "sg:address":"116 E Main St",
    "sg:city":"Ramsey",
    "sg:classifiers":[
        {
            "category":"Restaurant",
            "type":"Food & Drink"
        }
    ],
    "sg:phone":"+1 201 825 1638",
    "sg:postcode":"07446",
    "sg:province":"NJ",
    "sg:tags":[
        "parlor",
        "ice",
        "cream"
    ],
    "wof:name":"Carvel Ice Cream & Bakery",
    "wof:placetype":"venue"
},
  "geometry": {"coordinates":[-74.138734,41.057475],"type":"Point"}
}