{
  "type": "Feature",
  "properties": {
    "iso:country":"US",
    "sg:address":"352 Applegarth Rd",
    "sg:city":"Monroe Twp",
    "sg:classifiers":[
        {
            "category":"Shopping",
            "subcategory":"Used Merchandise",
            "type":"Retail Goods"
        }
    ],
    "sg:phone":"+1 609 655 0042",
    "sg:postcode":"08831",
    "sg:province":"NJ",
    "sg:tags":[
        "shop",
        "consignment"
    ],
    "wof:name":"Century 21 Ryan Grp",
    "wof:placetype":"venue"
},
  "geometry": {"coordinates":[-74.470658,40.324106],"type":"Point"}
}