{
  "type": "Feature",
  "properties": {
    "addr:full":"63 Bartholdi Ave Butler NJ 07405",
    "addr:housenumber":"63",
    "addr:postcode":"07405",
    "addr:street":"Bartholdi Ave",
    "iso:country":"US",
    "sg:address":"63 Bartholdi Ave",
    "sg:city":"Butler",
    "sg:classifiers":[
        {
            "category":"Organizations",
            "subcategory":"Religious Organization",
            "type":"Services"
        }
    ],
    "sg:phone":"+1 973 778 1915",
    "sg:postcode":"07405",
    "sg:province":"NJ",
    "wof:name":"Sacred Heart Friary",
    "wof:placetype":"venue"
},
  "geometry": {"coordinates":[-74.341103,40.995602],"type":"Point"}
}