{
  "type": "Feature",
  "properties": {
    "addr:full":"516 Hamburg Tpke Wayne NJ 07470",
    "addr:housenumber":"516",
    "addr:postcode":"07470",
    "addr:street":"Hamburg Tpke",
    "iso:country":"US",
    "sg:address":"516 Hamburg Tpke",
    "sg:city":"Wayne",
    "sg:classifiers":[
        {
            "category":"Health Services",
            "subcategory":"Doctor",
            "type":"Services"
        }
    ],
    "sg:phone":"+1 973 595 7922",
    "sg:postcode":"07470",
    "sg:province":"NJ",
    "sg:tags":[
        "physician",
        "surgeon",
        "medical"
    ],
    "wof:name":"Robert Fernand MD PA",
    "wof:placetype":"venue"
},
  "geometry": {"coordinates":[-74.21522899999999,40.954416],"type":"Point"}
}