{
  "type": "Feature",
  "properties": {
    "addr:full":"100 Meadow Rd Clark NJ 07066",
    "addr:housenumber":"100",
    "addr:postcode":"07066",
    "addr:street":"Meadow Rd",
    "iso:country":"US",
    "sg:address":"100 Meadow Rd",
    "sg:city":"Clark",
    "sg:classifiers":[
        {
            "category":"Building & Trades",
            "subcategory":"Construction",
            "type":"Services"
        }
    ],
    "sg:phone":"+1 732 882 0056",
    "sg:postcode":"07066",
    "sg:province":"NJ",
    "sg:tags":[
        "contractor"
    ],
    "wof:name":"M L Builders",
    "wof:placetype":"venue"
},
  "geometry": {"coordinates":[-74.329882,40.614754],"type":"Point"}
}