{
  "type": "Feature",
  "properties": {
    "iso:country":"US",
    "sg:address":"468 Paterson Ave",
    "sg:city":"East Rutherford",
    "sg:classifiers":[
        {
            "category":"Wholesale",
            "subcategory":"Machinery & Supplies",
            "type":"Manufacturing & Wholesale Goods"
        }
    ],
    "sg:phone":"+1 201 933 5115",
    "sg:postcode":"07073",
    "sg:province":"NJ",
    "sg:tags":[
        "heavy",
        "duty",
        "truck",
        "equipment"
    ],
    "wof:name":"Im-Ex Trading",
    "wof:placetype":"venue"
},
  "geometry": {"coordinates":[-74.102769,40.841477],"type":"Point"}
}