{
  "type": "Feature",
  "properties": {
    "addr:full":"31 Plaza Rd Fair Lawn NJ 07410",
    "addr:housenumber":"31",
    "addr:postcode":"07410",
    "addr:street":"Plaza Rd",
    "iso:country":"US",
    "sg:address":"31 Plaza Rd",
    "sg:city":"Fair Lawn",
    "sg:classifiers":[
        {
            "category":"Restaurant",
            "type":"Food & Drink"
        }
    ],
    "sg:phone":"+1 201 794 0004",
    "sg:postcode":"07410",
    "sg:province":"NJ",
    "wof:name":"Quiznos Sub",
    "wof:placetype":"venue"
},
  "geometry": {"coordinates":[-74.113739,40.929612],"type":"Point"}
}