{
  "type": "Feature",
  "properties": {
    "addr:full":"101 Cooper St Woodbury NJ 08096",
    "addr:housenumber":"101",
    "addr:postcode":"08096",
    "addr:street":"Cooper St",
    "iso:country":"US",
    "sg:address":"101 Cooper St",
    "sg:city":"Woodbury",
    "sg:classifiers":[
        {
            "category":"Restaurant",
            "type":"Food & Drink"
        }
    ],
    "sg:phone":"+1   ",
    "sg:postcode":"08096",
    "sg:province":"NJ",
    "sg:tags":[
        "eating"
    ],
    "wof:name":"Cooper Express",
    "wof:placetype":"venue"
},
  "geometry": {"coordinates":[-75.14877799999999,39.836088],"type":"Point"}
}