{
  "type": "Feature",
  "properties": {
    "iso:country":"US",
    "sg:address":"351 State Rte 35",
    "sg:city":"Eatontown",
    "sg:classifiers":[
        {
            "category":"Home & Garden",
            "subcategory":"Furniture",
            "type":"Retail Goods"
        }
    ],
    "sg:phone":"+1 732 389 2055",
    "sg:postcode":"07724",
    "sg:province":"NJ",
    "wof:name":"Walt's Furniture & Sleep Shop",
    "wof:placetype":"venue"
},
  "geometry": {"coordinates":[-74.047219,40.280421],"type":"Point"}
}