{
  "type": "Feature",
  "properties": {
    "addr:full":"36 Adamsville Rd S Bridgewater NJ 08807",
    "addr:housenumber":"36",
    "addr:postcode":"08807",
    "addr:street":"Adamsville Rd S",
    "iso:country":"US",
    "sg:address":"36 Adamsville Rd S",
    "sg:city":"Bridgewater",
    "sg:classifiers":[
        {
            "category":"Wholesale",
            "subcategory":"Machinery & Supplies",
            "type":"Manufacturing & Wholesale Goods"
        }
    ],
    "sg:phone":"+1 908 722 6000",
    "sg:postcode":"08807",
    "sg:province":"NJ",
    "sg:tags":[
        "equipment",
        "plastic"
    ],
    "sg:website":"www.davis-standard.com",
    "wof:name":"Egan Davis Standard",
    "wof:placetype":"venue"
},
  "geometry": {"coordinates":[-74.590099,40.56148],"type":"Point"}
}