{
  "type": "Feature",
  "properties": {
    "addr:full":"2641 Boardwalk Atlantic City NJ 08401",
    "addr:housenumber":"2641",
    "addr:postcode":"08401",
    "addr:street":"Boardwalk",
    "iso:country":"US",
    "sg:address":"2641 Boardwalk",
    "sg:city":"Atlantic City",
    "sg:classifiers":[
        {
            "category":"Restaurant",
            "type":"Food & Drink"
        }
    ],
    "sg:phone":"+1 609 344 7774",
    "sg:postcode":"08401",
    "sg:province":"NJ",
    "wof:name":"Mediterranean Flames",
    "wof:placetype":"venue"
},
  "geometry": {"coordinates":[-74.441638,39.352879],"type":"Point"}
}