{
  "type": "Feature",
  "properties": {
    "iso:country":"US",
    "sg:address":"10 Oxford Dr",
    "sg:city":"Moonachie",
    "sg:classifiers":[
        {
            "category":"Wholesale",
            "subcategory":"Electrical",
            "type":"Manufacturing & Wholesale Goods"
        }
    ],
    "sg:phone":"+1 201 373 9800",
    "sg:postcode":"07074",
    "sg:province":"NJ",
    "sg:tags":[
        "battery"
    ],
    "wof:name":"B & B Battery USA INC",
    "wof:placetype":"venue"
},
  "geometry": {"coordinates":[-74.05064900000001,40.844776],"type":"Point"}
}