{
  "type": "Feature",
  "properties": {
    "addr:full":"43 US Hwy 206 Augusta NJ 07822",
    "addr:housenumber":"43",
    "addr:postcode":"07822",
    "addr:street":"Us Hwy 206",
    "iso:country":"US",
    "sg:address":"43 US Hwy 206",
    "sg:city":"Augusta",
    "sg:classifiers":[
        {
            "category":"Building & Trades",
            "subcategory":"Construction",
            "type":"Services"
        }
    ],
    "sg:phone":"+1 973 300 2037",
    "sg:postcode":"07822",
    "sg:province":"NJ",
    "sg:tags":[
        "remodeling",
        "contractor"
    ],
    "wof:name":"Berlin Construction Inc",
    "wof:placetype":"venue"
},
  "geometry": {"coordinates":[-74.71745199999999,41.123348],"type":"Point"}
}