{
  "type": "Feature",
  "properties": {
    "iso:country":"US",
    "sg:address":"34 Exchange Pl",
    "sg:city":"Jersey City",
    "sg:classifiers":[
        {
            "category":"Banks & Credit Unions",
            "subcategory":"Bank",
            "type":"Services"
        }
    ],
    "sg:phone":"+1 201 432 7285",
    "sg:postcode":"07302",
    "sg:province":"NJ",
    "wof:name":"Deutsch Bank",
    "wof:placetype":"venue"
},
  "geometry": {"coordinates":[-74.045799,40.721901],"type":"Point"}
}