{
  "type": "Feature",
  "properties": {
    "iso:country":"US",
    "sg:address":"59 N Broad St",
    "sg:city":"Ridgewood",
    "sg:classifiers":[
        {
            "category":"Professional",
            "subcategory":"Business Services",
            "type":"Services"
        }
    ],
    "sg:phone":"+1 201 670 4887",
    "sg:postcode":"07450",
    "sg:province":"NJ",
    "sg:tags":[
        "interior",
        "consultant",
        "design",
        "decorator"
    ],
    "wof:name":"Norellen Stokley Interiors Inc",
    "wof:placetype":"venue"
},
  "geometry": {"coordinates":[-74.12031500000001,40.98018],"type":"Point"}
}