{
  "type": "Feature",
  "properties": {
    "iso:country":"US",
    "sg:address":"900 Federal Blvd",
    "sg:city":"Carteret",
    "sg:classifiers":[
        {
            "category":"Wholesale",
            "subcategory":"Motor Vehicles",
            "type":"Manufacturing & Wholesale Goods"
        }
    ],
    "sg:phone":"+1 732 750 5100",
    "sg:postcode":"07008",
    "sg:province":"NJ",
    "sg:tags":[
        "auction",
        "automobile"
    ],
    "wof:name":"Sterling Auction Limited Inc",
    "wof:placetype":"venue"
},
  "geometry": {"coordinates":[-74.24527500000001,40.583515],"type":"Point"}
}