{
  "type": "Feature",
  "properties": {
    "iso:country":"US",
    "sg:address":"1 Corporate Dr",
    "sg:city":"Wayne",
    "sg:classifiers":[
        {
            "category":"Banks & Credit Unions",
            "subcategory":"Bank",
            "type":"Services"
        }
    ],
    "sg:phone":"+1 973 305 8889",
    "sg:postcode":"07470",
    "sg:province":"NJ",
    "sg:website":"www.firstjerseycu.com",
    "wof:name":"First Jersey Credit Union",
    "wof:placetype":"venue"
},
  "geometry": {"coordinates":[-74.241963,40.912417],"type":"Point"}
}