{
  "type": "Feature",
  "properties": {
    "addr:full":"3 Chelsea Ct Marlton NJ 08053",
    "addr:housenumber":"3",
    "addr:postcode":"08053",
    "addr:street":"Chelsea Ct",
    "iso:country":"US",
    "sg:address":"3 Chelsea Ct",
    "sg:city":"Marlton",
    "sg:classifiers":[
        {
            "category":"Professional",
            "subcategory":"Business Services",
            "type":"Services"
        }
    ],
    "sg:phone":"+1   ",
    "sg:postcode":"08053",
    "sg:province":"NJ",
    "wof:name":"Ss Marketing Solutions LLC",
    "wof:placetype":"venue"
},
  "geometry": {"coordinates":[-74.88109900000001,39.859067],"type":"Point"}
}