{
  "type": "Feature",
  "properties": {
    "addr:full":"40 Crestmont Rd Little Falls NJ 07424",
    "addr:housenumber":"40",
    "addr:postcode":"07424",
    "addr:street":"Crestmont Rd",
    "iso:country":"US",
    "sg:address":"40 Crestmont Rd",
    "sg:city":"Little Falls",
    "sg:classifiers":[
        {
            "category":"Professional",
            "subcategory":"Business Services",
            "type":"Services"
        }
    ],
    "sg:phone":"+1   ",
    "sg:postcode":"07424",
    "sg:province":"NJ",
    "wof:name":"George Stavrou Associates",
    "wof:placetype":"venue"
},
  "geometry": {"coordinates":[-74.204673,40.877687],"type":"Point"}
}