{
  "type": "Feature",
  "properties": {
    "addr:full":"5 William St Newark NJ 07102",
    "addr:housenumber":"5",
    "addr:postcode":"07102",
    "addr:street":"William St",
    "iso:country":"US",
    "sg:address":"5 William St",
    "sg:city":"Newark",
    "sg:classifiers":[
        {
            "category":"Professional",
            "subcategory":"Business Services",
            "type":"Services"
        }
    ],
    "sg:phone":"+1   ",
    "sg:postcode":"07102",
    "sg:province":"NJ",
    "wof:name":"Ghanam Textile",
    "wof:placetype":"venue"
},
  "geometry": {"coordinates":[-74.174164,40.733457],"type":"Point"}
}