{
  "type": "Feature",
  "properties": {
    "iso:country":"US",
    "sg:address":"149 Franklin Tpke",
    "sg:city":"Waldwick",
    "sg:classifiers":[
        {
            "category":"Building & Trades",
            "subcategory":"Construction",
            "type":"Services"
        }
    ],
    "sg:phone":"+1 201 327 3813",
    "sg:postcode":"07463",
    "sg:province":"NJ",
    "sg:tags":[
        "material",
        "fence",
        "contractor"
    ],
    "wof:name":"Vanderbeck Fence Co Inc",
    "wof:placetype":"venue"
},
  "geometry": {"coordinates":[-74.12222199999999,41.018258],"type":"Point"}
}