{
  "type": "Feature",
  "properties": {
    "iso:country":"US",
    "sg:address":"711 Beach Dr",
    "sg:city":"Cape May",
    "sg:classifiers":[
        {
            "category":"Food & Beverages",
            "subcategory":"Dairy",
            "type":"Retail Goods"
        }
    ],
    "sg:phone":"+1   ",
    "sg:postcode":"08204",
    "sg:province":"NJ",
    "sg:tags":[
        "ice",
        "cream"
    ],
    "wof:name":"Cape Creamery",
    "wof:placetype":"venue"
},
  "geometry": {"coordinates":[-74.91774700000001,38.930654],"type":"Point"}
}