{
  "type": "Feature",
  "properties": {
    "addr:full":"103 Moonachie Ave Moonachie NJ 07074",
    "addr:housenumber":"103",
    "addr:postcode":"07074",
    "addr:street":"Moonachie Ave",
    "iso:country":"US",
    "sg:address":"103 Moonachie Ave",
    "sg:city":"Moonachie",
    "sg:classifiers":[
        {
            "category":"Autos & Motor Vehicles",
            "subcategory":"Recreational Vehicle Sales",
            "type":"Retail Goods"
        }
    ],
    "sg:phone":"+1   ",
    "sg:postcode":"07074",
    "sg:province":"NJ",
    "sg:tags":[
        "mobile",
        "home",
        "sales"
    ],
    "wof:name":"Metropolitan Associates Ltd",
    "wof:placetype":"venue"
},
  "geometry": {"coordinates":[-74.070511,40.839981],"type":"Point"}
}