{
  "type": "Feature",
  "properties": {
    "addr:full":"84 Big Piece Road. Fairfield NJ 07004",
    "addr:housenumber":"84",
    "addr:postcode":"07004",
    "addr:street":"Big Piece Road.",
    "iso:country":"US",
    "sg:address":"84 Big Piece Road.",
    "sg:city":"Fairfield",
    "sg:classifiers":[
        {
            "category":"Personal",
            "type":"Services"
        }
    ],
    "sg:phone":"+1 973 862 0552",
    "sg:postcode":"07004",
    "sg:province":"NJ",
    "sg:tags":[
        "party",
        "planning",
        "event"
    ],
    "sg:website":"www.rozanz.com",
    "wof:name":"RoZanZ",
    "wof:placetype":"venue"
},
  "geometry": {"coordinates":[-74.320571,40.881188],"type":"Point"}
}