{
  "type": "Feature",
  "properties": {
    "iso:country":"US",
    "sg:address":"66 E Main St",
    "sg:city":"Rockaway",
    "sg:classifiers":[
        {
            "category":"Health Services",
            "subcategory":"Doctor",
            "type":"Services"
        }
    ],
    "sg:phone":"+1 973 627 4499",
    "sg:postcode":"07866",
    "sg:province":"NJ",
    "sg:tags":[
        "physician",
        "surgeon"
    ],
    "wof:name":"Skyland Medical Group",
    "wof:placetype":"venue"
},
  "geometry": {"coordinates":[-74.51059100000001,40.899658],"type":"Point"}
}