{
  "type": "Feature",
  "properties": {
    "iso:country":"US",
    "sg:address":"831 W Browning Rd",
    "sg:city":"Bellmawr",
    "sg:classifiers":[
        {
            "category":"Shopping",
            "subcategory":"Pharmacy",
            "type":"Retail Goods"
        }
    ],
    "sg:phone":"+1   ",
    "sg:postcode":"08031",
    "sg:province":"NJ",
    "sg:tags":[
        "drug",
        "store"
    ],
    "wof:name":"Rite Aid",
    "wof:placetype":"venue"
},
  "geometry": {"coordinates":[-75.104786,39.873522],"type":"Point"}
}