{
  "type": "Feature",
  "properties": {
    "iso:country":"US",
    "sg:address":"69 State Rte 35",
    "sg:city":"Neptune City",
    "sg:classifiers":[
        {
            "category":"Home & Garden",
            "subcategory":"Household Appliances",
            "type":"Retail Goods"
        }
    ],
    "sg:phone":"+1 732 775 8062",
    "sg:postcode":"07753",
    "sg:province":"NJ",
    "wof:name":"Ace TV & Appliance Co",
    "wof:placetype":"venue"
},
  "geometry": {"coordinates":[-74.02841600000001,40.199085],"type":"Point"}
}