{
  "type": "Feature",
  "properties": {
    "iso:country":"US",
    "sg:address":"706 Alexander Rd",
    "sg:city":"Princeton",
    "sg:classifiers":[
        {
            "category":"Health Services",
            "subcategory":"Doctor",
            "type":"Services"
        }
    ],
    "sg:phone":"+1 609 243 0100",
    "sg:postcode":"08540",
    "sg:province":"NJ",
    "sg:tags":[
        "physician",
        "surgeon"
    ],
    "wof:name":"Center For Asthma & Allergy",
    "wof:placetype":"venue"
},
  "geometry": {"coordinates":[-74.637171,40.321417],"type":"Point"}
}