{
  "type": "Feature",
  "properties": {
    "iso:country":"US",
    "sg:address":"107 Hutton St",
    "sg:city":"Jersey City",
    "sg:classifiers":[
        {
            "category":"Shopping",
            "type":"Retail Goods"
        }
    ],
    "sg:phone":"+1   ",
    "sg:postcode":"07307",
    "sg:province":"NJ",
    "sg:tags":[
        "merchandise"
    ],
    "wof:name":"Botanica Tres Virtudes",
    "wof:placetype":"venue"
},
  "geometry": {"coordinates":[-74.052482,40.745458],"type":"Point"}
}