{
  "type": "Feature",
  "properties": {
    "addr:full":"970 State Route 36 Atlantic Highlands NJ 07716",
    "addr:housenumber":"970",
    "addr:postcode":"07716",
    "addr:street":"State Route 36",
    "iso:country":"US",
    "sg:address":"970 State Route 36",
    "sg:city":"Atlantic Highlands",
    "sg:classifiers":[
        {
            "category":"Restaurant",
            "type":"Food & Drink"
        }
    ],
    "sg:menulink":"http://www.allmenus.com/nj/middletown/194757-mcdonalds/menu/",
    "sg:phone":"+1 732 291 7474",
    "sg:postcode":"07716",
    "sg:province":"NJ",
    "sg:tags":[
        "burger",
        "american"
    ],
    "wof:name":"McDonald's",
    "wof:placetype":"venue"
},
  "geometry": {"coordinates":[-74.02060899999999,40.404758],"type":"Point"}
}