{
  "type": "Feature",
  "properties": {
    "addr:full":"12 Southfork Dr Jackson NJ 08527",
    "addr:housenumber":"12",
    "addr:postcode":"08527",
    "addr:street":"Southfork Dr",
    "iso:country":"US",
    "sg:address":"12 Southfork Dr",
    "sg:city":"Jackson",
    "sg:classifiers":[
        {
            "category":"Professional",
            "type":"Services"
        },
        {
            "category":"Professional",
            "subcategory":"Employment Agencies",
            "type":"Services"
        }
    ],
    "sg:phone":"+1 732 928 8455",
    "sg:postcode":"08527",
    "sg:province":"NJ",
    "sg:tags":[
        "establishment"
    ],
    "wof:name":"William Bell Associates Inc",
    "wof:placetype":"venue"
},
  "geometry": {"coordinates":[-74.322818,40.136898],"type":"Point"}
}