{
  "type": "Feature",
  "properties": {
    "iso:country":"US",
    "sg:address":"585 McCarter Hwy",
    "sg:city":"Newark",
    "sg:classifiers":[
        {
            "category":"Building & Trades",
            "subcategory":"Locksmith",
            "type":"Services"
        }
    ],
    "sg:phone":"+1 888 277 2895",
    "sg:postcode":"07102",
    "sg:province":"NJ",
    "sg:tags":[
        "key"
    ],
    "wof:name":"Anytime Anywhere Emergency Locksmith",
    "wof:placetype":"venue"
},
  "geometry": {"coordinates":[-74.172206,40.727249],"type":"Point"}
}