{
  "type": "Feature",
  "properties": {
    "iso:country":"US",
    "sg:address":"1776 Glendola Rd",
    "sg:city":"Belmar",
    "sg:classifiers":[
        {
            "category":"Real Estate",
            "subcategory":"Real Estate Agent",
            "type":"Services"
        }
    ],
    "sg:phone":"+1   ",
    "sg:postcode":"07719",
    "sg:province":"NJ",
    "wof:name":"100 Broadway Inc",
    "wof:placetype":"venue"
},
  "geometry": {"coordinates":[-74.074151,40.176197],"type":"Point"}
}