{
  "type": "Feature",
  "properties": {
    "iso:country":"US",
    "sg:address":"400 Morris Ave",
    "sg:city":"Denville",
    "sg:classifiers":[
        {
            "category":"Organizations",
            "subcategory":"Professional Association",
            "type":"Services"
        }
    ],
    "sg:phone":"+1 973 586 4300",
    "sg:postcode":"07834",
    "sg:province":"NJ",
    "sg:website":"www.alz.org",
    "wof:name":"Alzheimer's Association",
    "wof:placetype":"venue"
},
  "geometry": {"coordinates":[-74.503219,40.90965],"type":"Point"}
}