{
  "type": "Feature",
  "properties": {
    "addr:full":"79 S White Horse Pike Ste B Hammonton NJ 08037",
    "addr:housenumber":"79",
    "addr:postcode":"08037",
    "addr:street":"S White Horse Pike Ste B",
    "iso:country":"US",
    "sg:address":"79 S White Horse Pike Ste B",
    "sg:city":"Hammonton",
    "sg:classifiers":[
        {
            "category":"Personal",
            "subcategory":"Beauty Salon",
            "type":"Services"
        },
        {
            "category":"Personal",
            "subcategory":"Barber",
            "type":"Services"
        }
    ],
    "sg:phone":"+1 609 567 9199",
    "sg:postcode":"08037",
    "sg:province":"NJ",
    "sg:tags":[
        "hair",
        "accessory",
        "stylist",
        "supply"
    ],
    "sg:website":"http://www.haircuttery.com/",
    "wof:name":"Hair Cuttery",
    "wof:placetype":"venue"
},
  "geometry": {"coordinates":[-74.785634,39.645537],"type":"Point"}
}