{
  "type": "Feature",
  "properties": {
    "iso:country":"US",
    "sg:address":"419 Dover Rd",
    "sg:city":"Toms River",
    "sg:classifiers":[
        {
            "category":"Education",
            "subcategory":"School",
            "type":"Public Place"
        }
    ],
    "sg:phone":"+1 732 505 5890",
    "sg:postcode":"08757",
    "sg:province":"NJ",
    "sg:website":"www.trschools.com",
    "wof:name":"South Toms River Elem School",
    "wof:placetype":"venue"
},
  "geometry": {"coordinates":[-74.21593,39.94004],"type":"Point"}
}