{
  "type": "Feature",
  "properties": {
    "addr:full":"178 River St Paterson NJ 07501",
    "addr:housenumber":"178",
    "addr:postcode":"07501",
    "addr:street":"River St",
    "iso:country":"US",
    "sg:address":"178 River St",
    "sg:city":"Paterson",
    "sg:classifiers":[
        {
            "category":"Utilities",
            "subcategory":"Refuse",
            "type":"Services"
        }
    ],
    "sg:phone":"+1 973 684 6661",
    "sg:postcode":"07501",
    "sg:province":"NJ",
    "sg:tags":[
        "system"
    ],
    "wof:name":"Onyx Waste Services Inc (wi)",
    "wof:placetype":"venue"
},
  "geometry": {"coordinates":[-74.168177,40.923698],"type":"Point"}
}