{
  "type": "Feature",
  "properties": {
    "addr:full":"151 Lydia Dr West New York NJ 07093",
    "addr:housenumber":"151",
    "addr:postcode":"07093",
    "addr:street":"Lydia Dr West",
    "iso:country":"US",
    "sg:address":"151 Lydia Dr",
    "sg:city":"West New York",
    "sg:classifiers":[
        {
            "category":"Professional",
            "type":"Services"
        }
    ],
    "sg:phone":"+1 212 366 9696",
    "sg:postcode":"07093",
    "sg:province":"NJ",
    "sg:tags":[
        "caterer"
    ],
    "wof:name":"De Lux Food Productions Inc",
    "wof:placetype":"venue"
},
  "geometry": {"coordinates":[-73.99909599999999,40.789124],"type":"Point"}
}