{
  "type": "Feature",
  "properties": {
    "iso:country":"US",
    "sg:address":"942 US Hwy 22",
    "sg:city":"Phillipsburg",
    "sg:classifiers":[
        {
            "category":"Utilities",
            "subcategory":"Mobile Phone",
            "type":"Services"
        }
    ],
    "sg:phone":"+1 908 454 7120",
    "sg:postcode":"08865",
    "sg:province":"NJ",
    "sg:tags":[
        "telephone",
        "cellular"
    ],
    "wof:name":"Cell Dex",
    "wof:placetype":"venue"
},
  "geometry": {"coordinates":[-75.168842,40.698384],"type":"Point"}
}