{
  "type": "Feature",
  "properties": {
    "iso:country":"US",
    "sg:address":"626 Bound Brook Rd",
    "sg:city":"Dunellen",
    "sg:classifiers":[
        {
            "category":"Communications",
            "subcategory":"Film & Video Production",
            "type":"Services"
        },
        {
            "category":"Shopping",
            "subcategory":"Computers & Home Electronics",
            "type":"Retail Goods"
        }
    ],
    "sg:phone":"+1 732 926 0220",
    "sg:postcode":"08812",
    "sg:province":"NJ",
    "sg:tags":[
        "audio"
    ],
    "wof:name":"Pohara Inc",
    "wof:placetype":"venue"
},
  "geometry": {"coordinates":[-74.47195000000001,40.587831],"type":"Point"}
}