{
  "type": "Feature",
  "properties": {
    "addr:full":"22 Kent Ct Passaic NJ 07055",
    "addr:housenumber":"22",
    "addr:postcode":"07055",
    "addr:street":"Kent Ct",
    "iso:country":"US",
    "sg:address":"22 Kent Ct",
    "sg:city":"Passaic",
    "sg:classifiers":[
        {
            "category":"Recreation",
            "type":"Entertainment"
        }
    ],
    "sg:phone":"+1 973 779 6662",
    "sg:postcode":"07055",
    "sg:province":"NJ",
    "sg:tags":[
        "concessionaire"
    ],
    "wof:name":"Dolores' Cafeteria",
    "wof:placetype":"venue"
},
  "geometry": {"coordinates":[-74.13255700000001,40.852753],"type":"Point"}
}