{
  "type": "Feature",
  "properties": {
    "iso:country":"US",
    "sg:address":"1297 Main Ave",
    "sg:city":"Clifton",
    "sg:classifiers":[
        {
            "category":"Real Estate",
            "subcategory":"Real Estate Agent",
            "type":"Services"
        }
    ],
    "sg:phone":"+1   ",
    "sg:postcode":"07011",
    "sg:province":"NJ",
    "sg:tags":[
        "insurance"
    ],
    "wof:name":"Ernest T Scheidemann Agency",
    "wof:placetype":"venue"
},
  "geometry": {"coordinates":[-74.141057,40.876768],"type":"Point"}
}