{
  "type": "Feature",
  "properties": {
    "addr:full":"1600 Boardwalk North Wildwood NJ 08260",
    "addr:housenumber":"1600",
    "addr:postcode":"08260",
    "addr:street":"Boardwalk North",
    "iso:country":"US",
    "sg:address":"1600 Boardwalk",
    "sg:city":"North Wildwood",
    "sg:classifiers":[
        {
            "category":"Restaurant",
            "type":"Food & Drink"
        }
    ],
    "sg:phone":"+1 609 522 7545",
    "sg:postcode":"08260",
    "sg:province":"NJ",
    "wof:name":"Miss Abby's",
    "wof:placetype":"venue"
},
  "geometry": {"coordinates":[-74.796589,38.994583],"type":"Point"}
}