{
  "type": "Feature",
  "properties": {
    "addr:full":"39 Keasler Ave Lodi NJ 07644",
    "addr:housenumber":"39",
    "addr:postcode":"07644",
    "addr:street":"Keasler Ave",
    "iso:country":"US",
    "sg:address":"39 Keasler Ave",
    "sg:city":"Lodi",
    "sg:classifiers":[
        {
            "category":"Professional",
            "subcategory":"Business Services",
            "type":"Services"
        }
    ],
    "sg:phone":"+1   ",
    "sg:postcode":"07644",
    "sg:province":"NJ",
    "wof:name":"Djk Enterprises",
    "wof:placetype":"venue"
},
  "geometry": {"coordinates":[-74.086806,40.884604],"type":"Point"}
}