{
  "type": "Feature",
  "properties": {
    "iso:country":"US",
    "sg:address":"116 Main St",
    "sg:city":"Mt Ephraim",
    "sg:classifiers":[
        {
            "category":"Building & Trades",
            "subcategory":"Construction",
            "type":"Services"
        }
    ],
    "sg:phone":"+1 856 456 5409",
    "sg:postcode":"08059",
    "sg:province":"NJ",
    "sg:tags":[
        "product",
        "asphalt"
    ],
    "wof:name":"American Asphalt Co",
    "wof:placetype":"venue"
},
  "geometry": {"coordinates":[-75.092568,39.890025],"type":"Point"}
}