{
  "type": "Feature",
  "properties": {
    "addr:full":"1534 Redondo Ln Lakewood NJ 08701",
    "addr:housenumber":"1534",
    "addr:postcode":"08701",
    "addr:street":"Redondo Ln",
    "iso:country":"US",
    "sg:address":"1534 Redondo Ln",
    "sg:city":"Lakewood",
    "sg:classifiers":[
        {
            "category":"Building & Trades",
            "subcategory":"Construction",
            "type":"Services"
        }
    ],
    "sg:phone":"+1 732 886 6269",
    "sg:postcode":"08701",
    "sg:province":"NJ",
    "sg:tags":[
        "contractor"
    ],
    "wof:name":"South Coast Drywall",
    "wof:placetype":"venue"
},
  "geometry": {"coordinates":[-74.15848,40.097053],"type":"Point"}
}