{
  "type": "Feature",
  "properties": {
    "iso:country":"US",
    "sg:address":"1860 Willowbrook Mall",
    "sg:city":"Wayne",
    "sg:classifiers":[
        {
            "category":"Recreation",
            "type":"Entertainment"
        }
    ],
    "sg:phone":"+1 973 785 0830",
    "sg:postcode":"07470",
    "sg:province":"NJ",
    "sg:tags":[
        "amusement"
    ],
    "wof:name":"Fun-N-Games",
    "wof:placetype":"venue"
},
  "geometry": {"coordinates":[-74.25505800000001,40.889533],"type":"Point"}
}