{
  "type": "Feature",
  "properties": {
    "addr:full":"316 Riverside Dr Bayville NJ 08721",
    "addr:housenumber":"316",
    "addr:postcode":"08721",
    "addr:street":"Riverside Dr",
    "iso:country":"US",
    "sg:address":"316 Riverside Dr",
    "sg:city":"Bayville",
    "sg:classifiers":[
        {
            "category":"Building & Trades",
            "subcategory":"Construction",
            "type":"Services"
        }
    ],
    "sg:phone":"+1 732 269 3420",
    "sg:postcode":"08721",
    "sg:province":"NJ",
    "sg:tags":[
        "general",
        "contractor"
    ],
    "wof:name":"Tru-Design Construction",
    "wof:placetype":"venue"
},
  "geometry": {"coordinates":[-74.14981299999999,39.896351],"type":"Point"}
}