{
  "type": "Feature",
  "properties": {
    "iso:country":"US",
    "sg:address":"202 Garden Ter",
    "sg:city":"Runnemede",
    "sg:classifiers":[
        {
            "category":"Restaurant",
            "type":"Food & Drink"
        }
    ],
    "sg:phone":"+1   ",
    "sg:postcode":"08078",
    "sg:province":"NJ",
    "sg:tags":[
        "eating"
    ],
    "wof:name":"Break Away Grill Inc",
    "wof:placetype":"venue"
},
  "geometry": {"coordinates":[-75.070162,39.855069],"type":"Point"}
}