{
  "type": "Feature",
  "properties": {
    "iso:country":"US",
    "sg:address":"70 Main St",
    "sg:city":"Garfield",
    "sg:classifiers":[
        {
            "category":"Building & Trades",
            "subcategory":"Construction",
            "type":"Services"
        }
    ],
    "sg:phone":"+1 973 772 6914",
    "sg:postcode":"07026",
    "sg:province":"NJ",
    "sg:tags":[
        "general",
        "contractor"
    ],
    "wof:name":"DNP Trebenista Construction",
    "wof:placetype":"venue"
},
  "geometry": {"coordinates":[-74.110601,40.884291],"type":"Point"}
}