{
  "type": "Feature",
  "properties": {
    "addr:full":"171 Pickford Ave Phillipsburg NJ 08865",
    "addr:housenumber":"171",
    "addr:postcode":"08865",
    "addr:street":"Pickford Ave",
    "iso:country":"US",
    "sg:address":"171 Pickford Ave",
    "sg:city":"Phillipsburg",
    "sg:classifiers":[
        {
            "category":"Building & Trades",
            "subcategory":"Construction",
            "type":"Services"
        }
    ],
    "sg:phone":"+1 908 213 1794",
    "sg:postcode":"08865",
    "sg:province":"NJ",
    "sg:tags":[
        "interior",
        "residential",
        "painting",
        "contractor"
    ],
    "wof:name":"Custon Works",
    "wof:placetype":"venue"
},
  "geometry": {"coordinates":[-75.18243699999999,40.700344],"type":"Point"}
}