{
  "type": "Feature",
  "properties": {
    "addr:full":"280 Main St Little Falls NJ 07424",
    "addr:housenumber":"280",
    "addr:postcode":"07424",
    "addr:street":"Main St",
    "iso:country":"US",
    "sg:address":"280 Main St",
    "sg:city":"Little Falls",
    "sg:classifiers":[
        {
            "category":"Building & Trades",
            "subcategory":"Landscaping Services",
            "type":"Services"
        }
    ],
    "sg:phone":"+1 973 256 6224",
    "sg:postcode":"07424",
    "sg:province":"NJ",
    "sg:tags":[
        "landscape",
        "contractor"
    ],
    "wof:name":"Great Notch Landscape Co Inc",
    "wof:placetype":"venue"
},
  "geometry": {"coordinates":[-74.23387099999999,40.882895],"type":"Point"}
}