{
  "type": "Feature",
  "properties": {
    "addr:full":"324 Broad Ave Leonia NJ 07605",
    "addr:housenumber":"324",
    "addr:postcode":"07605",
    "addr:street":"Broad Ave",
    "iso:country":"US",
    "sg:address":"324 Broad Ave",
    "sg:city":"Leonia",
    "sg:classifiers":[
        {
            "category":"Food & Beverages",
            "subcategory":"Liquor & Beverages",
            "type":"Retail Goods"
        }
    ],
    "sg:phone":"+1 201 592 8191",
    "sg:postcode":"07605",
    "sg:province":"NJ",
    "wof:name":"Princer's Wines & Spirits",
    "wof:placetype":"venue"
},
  "geometry": {"coordinates":[-73.98768200000001,40.862205],"type":"Point"}
}