{
  "type": "Feature",
  "properties": {
    "addr:full":"431 Danforth Ave Jersey City NJ 07305",
    "addr:housenumber":"431",
    "addr:postcode":"07305",
    "addr:street":"Danforth Ave",
    "iso:country":"US",
    "sg:address":"431 Danforth Ave",
    "sg:city":"Jersey City",
    "sg:classifiers":[
        {
            "category":"Food & Beverages",
            "subcategory":"Bakery",
            "type":"Retail Goods"
        },
        {
            "category":"Bagels",
            "type":"Food & Drink"
        }
    ],
    "sg:menulink":"http://www.allmenus.com/nj/jersey-city/258639-wonder-bagels/menu/",
    "sg:phone":"+1 201 324 1540",
    "sg:postcode":"07305",
    "sg:province":"NJ",
    "sg:tags":[
        "bagel",
        "american"
    ],
    "wof:name":"Wonder Bagels",
    "wof:placetype":"venue"
},
  "geometry": {"coordinates":[-74.09777800000001,40.703869],"type":"Point"}
}