{
  "type": "Feature",
  "properties": {
    "addr:full":"10 3rd St Ocean City NJ 08226",
    "addr:housenumber":"10",
    "addr:postcode":"08226",
    "addr:street":"3Rd St",
    "iso:country":"US",
    "sg:address":"10 3rd St",
    "sg:city":"Ocean City",
    "sg:classifiers":[
        {
            "category":"Building & Trades",
            "subcategory":"Construction",
            "type":"Services"
        }
    ],
    "sg:phone":"+1 609 391 2156",
    "sg:postcode":"08226",
    "sg:province":"NJ",
    "sg:tags":[
        "house"
    ],
    "wof:name":"Naegele Construction",
    "wof:placetype":"venue"
},
  "geometry": {"coordinates":[-74.570707,39.287481],"type":"Point"}
}