{
  "type": "Feature",
  "properties": {
    "addr:full":"1029 Edwards Rd Parsippany NJ 07054",
    "addr:housenumber":"1029",
    "addr:postcode":"07054",
    "addr:street":"Edwards Rd",
    "iso:country":"US",
    "sg:address":"1029 Edwards Rd",
    "sg:city":"Parsippany",
    "sg:classifiers":[
        {
            "category":"Wholesale",
            "subcategory":"Electrical",
            "type":"Manufacturing & Wholesale Goods"
        }
    ],
    "sg:phone":"+1 973 244 6347",
    "sg:postcode":"07054",
    "sg:province":"NJ",
    "sg:tags":[
        "equipment"
    ],
    "wof:name":"Nabco Lighting Solutions",
    "wof:placetype":"venue"
},
  "geometry": {"coordinates":[-74.347352,40.84529],"type":"Point"}
}