{
  "type": "Feature",
  "properties": {
    "addr:full":"19 Arlington St Paterson NJ 07522",
    "addr:housenumber":"19",
    "addr:postcode":"07522",
    "addr:street":"Arlington St",
    "iso:country":"US",
    "sg:address":"19 Arlington St",
    "sg:city":"Paterson",
    "sg:classifiers":[
        {
            "category":"Restaurant",
            "type":"Food & Drink"
        }
    ],
    "sg:phone":"+1 973 595 8721",
    "sg:postcode":"07522",
    "sg:province":"NJ",
    "sg:tags":[
        "caterer"
    ],
    "wof:name":"C & C Food Svc-Posh Island",
    "wof:placetype":"venue"
},
  "geometry": {"coordinates":[-74.17801799999999,40.924823],"type":"Point"}
}