{
  "type": "Feature",
  "properties": {
    "addr:full":"218 Madison Pl Ridgewood NJ 07450",
    "addr:housenumber":"218",
    "addr:postcode":"07450",
    "addr:street":"Madison Pl",
    "iso:country":"US",
    "sg:address":"218 Madison Pl",
    "sg:city":"Ridgewood",
    "sg:classifiers":[
        {
            "category":"Shopping",
            "type":"Retail Goods"
        },
        {
            "category":"Organizations",
            "subcategory":"Non-profit Organization",
            "type":"Services"
        }
    ],
    "sg:phone":"+1 201 445 2159",
    "sg:postcode":"07450",
    "sg:province":"NJ",
    "sg:tags":[
        "fund",
        "games",
        "raising",
        "merchandise",
        "supply"
    ],
    "wof:name":"Christine Oreilly Childrens Foundation",
    "wof:placetype":"venue"
},
  "geometry": {"coordinates":[-74.12696200000001,40.983433],"type":"Point"}
}