{
  "type": "Feature",
  "properties": {
    "iso:country":"US",
    "sg:address":"1130 McBride Ave",
    "sg:city":"Little Falls",
    "sg:classifiers":[
        {
            "category":"Health Services",
            "subcategory":"Doctor",
            "type":"Services"
        }
    ],
    "sg:phone":"+1   ",
    "sg:postcode":"07424",
    "sg:province":"NJ",
    "sg:tags":[
        "medical"
    ],
    "wof:name":"Gambetta Louis DPM",
    "wof:placetype":"venue"
},
  "geometry": {"coordinates":[-74.212772,40.891699],"type":"Point"}
}