{
  "type": "Feature",
  "properties": {
    "iso:country":"US",
    "sg:address":"17 Lake Louise Rd",
    "sg:city":"Morganville",
    "sg:classifiers":[
        {
            "category":"Professional",
            "subcategory":"Business Services",
            "type":"Services"
        }
    ],
    "sg:phone":"+1   ",
    "sg:postcode":"07751",
    "sg:province":"NJ",
    "wof:name":"Lsmg",
    "wof:placetype":"venue"
},
  "geometry": {"coordinates":[-74.285838,40.331089],"type":"Point"}
}