{
  "type": "Feature",
  "properties": {
    "addr:full":"38 Laura Ln Morristown NJ 07960",
    "addr:housenumber":"38",
    "addr:postcode":"07960",
    "addr:street":"Laura Ln",
    "iso:country":"US",
    "sg:address":"38 Laura Ln",
    "sg:city":"Morristown",
    "sg:classifiers":[
        {
            "category":"Banks & Credit Unions",
            "subcategory":"Investment Brokerage",
            "type":"Services"
        }
    ],
    "sg:phone":"+1 973 605 1045",
    "sg:postcode":"07960",
    "sg:province":"NJ",
    "sg:tags":[
        "investing"
    ],
    "wof:name":"Jg Advisors Llc",
    "wof:placetype":"venue"
},
  "geometry": {"coordinates":[-74.476293,40.766898],"type":"Point"}
}