{
  "type": "Feature",
  "properties": {
    "addr:full":"85 Berkshire Ave Paterson NJ 07502",
    "addr:housenumber":"85",
    "addr:postcode":"07502",
    "addr:street":"Berkshire Ave",
    "iso:country":"US",
    "sg:address":"85 Berkshire Ave",
    "sg:city":"Paterson",
    "sg:classifiers":[
        {
            "category":"Health Services",
            "subcategory":"Podiatrist",
            "type":"Services"
        }
    ],
    "sg:phone":"+1 973 942 4545",
    "sg:postcode":"07502",
    "sg:province":"NJ",
    "wof:name":"Zisa John J DPM",
    "wof:placetype":"venue"
},
  "geometry": {"coordinates":[-74.19409899999999,40.9161],"type":"Point"}
}