{
  "type": "Feature",
  "properties": {
    "addr:full":"717 New Rd Somers Point NJ 08244",
    "addr:housenumber":"717",
    "addr:postcode":"08244",
    "addr:street":"New Rd",
    "iso:country":"US",
    "sg:address":"717 New Rd",
    "sg:city":"Somers Point",
    "sg:classifiers":[
        {
            "category":"Autos & Motor Vehicles",
            "subcategory":"Automobile Sales",
            "type":"Retail Goods"
        }
    ],
    "sg:phone":"+1 609 927 2300",
    "sg:postcode":"08244",
    "sg:province":"NJ",
    "sg:tags":[
        "car",
        "dealer"
    ],
    "wof:name":"Tommy D's Classic Cars",
    "wof:placetype":"venue"
},
  "geometry": {"coordinates":[-74.60486899999999,39.317589],"type":"Point"}
}