{
  "type": "Feature",
  "properties": {
    "addr:full":"59 5th St Saddle Brook NJ 07663",
    "addr:housenumber":"59",
    "addr:postcode":"07663",
    "addr:street":"5Th St",
    "iso:country":"US",
    "sg:address":"59 5th St",
    "sg:city":"Saddle Brook",
    "sg:classifiers":[
        {
            "category":"Manufacturing",
            "subcategory":"Tools & Machinery",
            "type":"Manufacturing & Wholesale Goods"
        }
    ],
    "sg:phone":"+1 201 712 1266",
    "sg:postcode":"07663",
    "sg:province":"NJ",
    "sg:tags":[
        "home",
        "mfg",
        "lighting",
        "equipment"
    ],
    "sg:website":"www.unilux.com",
    "wof:name":"Unilux Inc",
    "wof:placetype":"venue"
},
  "geometry": {"coordinates":[-74.099597,40.893465],"type":"Point"}
}