{
  "type": "Feature",
  "properties": {
    "addr:full":"901 W 3rd St Plainfield NJ 07063",
    "addr:housenumber":"901",
    "addr:postcode":"07063",
    "addr:street":"W 3Rd St",
    "iso:country":"US",
    "sg:address":"901 W 3rd St",
    "sg:city":"Plainfield",
    "sg:classifiers":[
        {
            "category":"Retail",
            "subcategory":"Repair Shop",
            "type":"Services"
        }
    ],
    "sg:phone":"+1   ",
    "sg:postcode":"07063",
    "sg:province":"NJ",
    "wof:name":"A24 All Day Emergency A Locksm",
    "wof:placetype":"venue"
},
  "geometry": {"coordinates":[-74.43593,40.605658],"type":"Point"}
}