{
  "type": "Feature",
  "properties": {
    "iso:country":"US",
    "sg:address":"113 Lenox Ave",
    "sg:city":"Paterson",
    "sg:classifiers":[
        {
            "category":"Education",
            "subcategory":"Special Training",
            "type":"Public Place"
        }
    ],
    "sg:phone":"+1   ",
    "sg:postcode":"07502",
    "sg:province":"NJ",
    "sg:tags":[
        "lesson",
        "voice",
        "rehabilitation"
    ],
    "wof:name":"Vocal Behavior Training",
    "wof:placetype":"venue"
},
  "geometry": {"coordinates":[-74.196382,40.915668],"type":"Point"}
}