{
  "type": "Feature",
  "properties": {
    "iso:country":"US",
    "sg:address":"125 Paterson Plank Rd",
    "sg:city":"Carlstadt",
    "sg:classifiers":[
        {
            "category":"Retail",
            "subcategory":"Photofinishing",
            "type":"Services"
        }
    ],
    "sg:phone":"+1 201 896 0700",
    "sg:postcode":"07072",
    "sg:province":"NJ",
    "sg:tags":[
        "photo",
        "finishing"
    ],
    "wof:name":"Alaten Co",
    "wof:placetype":"venue"
},
  "geometry": {"coordinates":[-74.084416,40.830711],"type":"Point"}
}