{
  "type": "Feature",
  "properties": {
    "addr:full":"11 Lakeview Dr Butler NJ 07405",
    "addr:housenumber":"11",
    "addr:postcode":"07405",
    "addr:street":"Lakeview Dr",
    "iso:country":"US",
    "sg:address":"11 Lakeview Dr",
    "sg:city":"Butler",
    "sg:classifiers":[
        {
            "category":"Shopping",
            "subcategory":"Gifts & Souvenirs",
            "type":"Retail Goods"
        }
    ],
    "sg:phone":"+1   ",
    "sg:postcode":"07405",
    "sg:province":"NJ",
    "wof:name":"Hot Gifts & Gags",
    "wof:placetype":"venue"
},
  "geometry": {"coordinates":[-74.374943,40.971317],"type":"Point"}
}