{
  "type": "Feature",
  "properties": {
    "iso:country":"US",
    "sg:address":"272 Van Buren St",
    "sg:city":"Newark",
    "sg:classifiers":[
        {
            "category":"Food & Beverages",
            "subcategory":"Bakery",
            "type":"Retail Goods"
        }
    ],
    "sg:phone":"+1 973 491 0004",
    "sg:postcode":"07105",
    "sg:province":"NJ",
    "sg:tags":[
        "baker"
    ],
    "wof:name":"Veneza Bakery & Deli",
    "wof:placetype":"venue"
},
  "geometry": {"coordinates":[-74.1605,40.722801],"type":"Point"}
}