{
  "type": "Feature",
  "properties": {
    "addr:full":"100 State St Teaneck NJ 07666",
    "addr:housenumber":"100",
    "addr:postcode":"07666",
    "addr:street":"State St",
    "iso:country":"US",
    "sg:address":"100 State St",
    "sg:city":"Teaneck",
    "sg:classifiers":[
        {
            "category":"Health Services",
            "subcategory":"Health Practitioner",
            "type":"Services"
        }
    ],
    "sg:phone":"+1   ",
    "sg:postcode":"07666",
    "sg:province":"NJ",
    "wof:name":"Abner Strauss PHD",
    "wof:placetype":"venue"
},
  "geometry": {"coordinates":[-74.00394,40.902733],"type":"Point"}
}