{
  "type": "Feature",
  "properties": {
    "iso:country":"US",
    "sg:address":"336 Franklin Ave",
    "sg:city":"Belleville",
    "sg:classifiers":[
        {
            "category":"Personal",
            "type":"Services"
        }
    ],
    "sg:phone":"+1 973 751 5330",
    "sg:postcode":"07109",
    "sg:province":"NJ",
    "sg:tags":[
        "hair",
        "replacement"
    ],
    "wof:name":"Maria Roberts Hair Replacement",
    "wof:placetype":"venue"
},
  "geometry": {"coordinates":[-74.16957499999999,40.803039],"type":"Point"}
}