{
  "type": "Feature",
  "properties": {
    "iso:country":"US",
    "sg:address":"410 W Delilah Rd",
    "sg:city":"Pleasantville",
    "sg:classifiers":[
        {
            "category":"Real Estate",
            "subcategory":"Real Estate Agent",
            "type":"Services"
        }
    ],
    "sg:phone":"+1 609 272 0540",
    "sg:postcode":"08232",
    "sg:province":"NJ",
    "sg:tags":[
        "management"
    ],
    "wof:name":"Atlantic County Mortgage Co",
    "wof:placetype":"venue"
},
  "geometry": {"coordinates":[-74.51978200000001,39.407723],"type":"Point"}
}