{
  "type": "Feature",
  "properties": {
    "addr:full":"60 Hillside Dr Trenton NJ 08691",
    "addr:housenumber":"60",
    "addr:postcode":"08691",
    "addr:street":"Hillside Dr",
    "iso:country":"US",
    "sg:address":"60 Hillside Dr",
    "sg:city":"Trenton",
    "sg:classifiers":[
        {
            "category":"Personal",
            "subcategory":"Beauty Salon",
            "type":"Services"
        }
    ],
    "sg:phone":"+1 609 259 7234",
    "sg:postcode":"08691",
    "sg:province":"NJ",
    "wof:name":"Extreme Cuts",
    "wof:placetype":"venue"
},
  "geometry": {"coordinates":[-74.604034,40.206716],"type":"Point"}
}