{
  "type": "Feature",
  "properties": {
    "iso:country":"US",
    "sg:address":"519 W Rio Grande Ave",
    "sg:city":"Wildwood",
    "sg:classifiers":[
        {
            "category":"Autos & Motor Vehicles",
            "subcategory":"Boat Sales",
            "type":"Retail Goods"
        }
    ],
    "sg:phone":"+1 609 729 6661",
    "sg:postcode":"08260",
    "sg:province":"NJ",
    "sg:tags":[
        "dealer",
        "sales"
    ],
    "wof:name":"Cape Island Yacht Sales",
    "wof:placetype":"venue"
},
  "geometry": {"coordinates":[-74.830494,38.988976],"type":"Point"}
}