{
  "type": "Feature",
  "properties": {
    "addr:full":"251 Wheatsworth Rd Hamburg NJ 07419",
    "addr:housenumber":"251",
    "addr:postcode":"07419",
    "addr:street":"Wheatsworth Rd",
    "iso:country":"US",
    "sg:address":"251 Wheatsworth Rd",
    "sg:city":"Hamburg",
    "sg:classifiers":[
        {
            "category":"Organizations",
            "subcategory":"Religious Organization",
            "type":"Services"
        }
    ],
    "sg:phone":"+1 973 827 7437",
    "sg:postcode":"07419",
    "sg:province":"NJ",
    "sg:tags":[
        "clergy"
    ],
    "wof:name":"Stephen Vogt",
    "wof:placetype":"venue"
},
  "geometry": {"coordinates":[-74.603481,41.136499],"type":"Point"}
}