{
  "type": "Feature",
  "properties": {
    "addr:full":"490 US Hwy 46 Fairfield NJ 07004",
    "addr:housenumber":"490",
    "addr:postcode":"07004",
    "addr:street":"Us Hwy 46",
    "iso:country":"US",
    "sg:address":"490 US Hwy 46",
    "sg:city":"Fairfield",
    "sg:classifiers":[
        {
            "category":"Shopping",
            "subcategory":"Catalog Store",
            "type":"Retail Goods"
        }
    ],
    "sg:phone":"+1   ",
    "sg:postcode":"07004",
    "sg:province":"NJ",
    "sg:tags":[
        "mail",
        "house"
    ],
    "wof:name":"Complete Collegiate",
    "wof:placetype":"venue"
},
  "geometry": {"coordinates":[-74.285945,40.884518],"type":"Point"}
}