{
  "type": "Feature",
  "properties": {
    "addr:full":"324 Central Ave Jersey City NJ 07307",
    "addr:housenumber":"324",
    "addr:postcode":"07307",
    "addr:street":"Central Ave",
    "iso:country":"US",
    "sg:address":"324 Central Ave",
    "sg:city":"Jersey City",
    "sg:classifiers":[
        {
            "category":"Wholesale",
            "subcategory":"Drugs",
            "type":"Manufacturing & Wholesale Goods"
        }
    ],
    "sg:phone":"+1 201 386 9595",
    "sg:postcode":"07307",
    "sg:province":"NJ",
    "wof:name":"World of Perfume",
    "wof:placetype":"venue"
},
  "geometry": {"coordinates":[-74.048897,40.746469],"type":"Point"}
}