{
  "type": "Feature",
  "properties": {
    "iso:country":"US",
    "sg:address":"222 Bergen Tpke",
    "sg:city":"Ridgefield Park",
    "sg:classifiers":[
        {
            "category":"Wholesale",
            "subcategory":"Machinery & Supplies",
            "type":"Manufacturing & Wholesale Goods"
        }
    ],
    "sg:phone":"+1 201 440 6002",
    "sg:postcode":"07660",
    "sg:province":"NJ",
    "sg:tags":[
        "platform",
        "aerial",
        "rent"
    ],
    "sg:website":"www.unitedrentals.com",
    "wof:name":"United Rentals",
    "wof:placetype":"venue"
},
  "geometry": {"coordinates":[-74.02184099999999,40.842149],"type":"Point"}
}