{
  "type": "Feature",
  "properties": {
    "addr:full":"24 Yorkshire Dr Voorhees NJ 08043",
    "addr:housenumber":"24",
    "addr:postcode":"08043",
    "addr:street":"Yorkshire Dr",
    "iso:country":"US",
    "sg:address":"24 Yorkshire Dr",
    "sg:city":"Voorhees",
    "sg:classifiers":[
        {
            "category":"Professional",
            "type":"Services"
        }
    ],
    "sg:phone":"+1   ",
    "sg:postcode":"08043",
    "sg:province":"NJ",
    "wof:name":"Sydria Klein Schaffer PC",
    "wof:placetype":"venue"
},
  "geometry": {"coordinates":[-74.970815,39.853291],"type":"Point"}
}