{
  "type": "Feature",
  "properties": {
    "addr:full":"193 Westwood Ave Long Branch NJ 07740",
    "addr:housenumber":"193",
    "addr:postcode":"07740",
    "addr:street":"Westwood Ave",
    "iso:country":"US",
    "sg:address":"193 Westwood Ave",
    "sg:city":"Long Branch",
    "sg:classifiers":[
        {
            "category":"Wholesale",
            "subcategory":"Vending Machines",
            "type":"Manufacturing & Wholesale Goods"
        }
    ],
    "sg:phone":"+1 732 870 8787",
    "sg:postcode":"07740",
    "sg:province":"NJ",
    "wof:name":"Refreshman Vending LLC",
    "wof:placetype":"venue"
},
  "geometry": {"coordinates":[-73.98885300000001,40.298021],"type":"Point"}
}