{
  "type": "Feature",
  "properties": {
    "addr:full":"24 Brookridge Dr Basking Ridge NJ 07920",
    "addr:housenumber":"24",
    "addr:postcode":"07920",
    "addr:street":"Brookridge Dr",
    "iso:country":"US",
    "sg:address":"24 Brookridge Dr",
    "sg:city":"Basking Ridge",
    "sg:classifiers":[
        {
            "category":"Professional",
            "subcategory":"Management & Consulting",
            "type":"Services"
        }
    ],
    "sg:phone":"+1   ",
    "sg:postcode":"07920",
    "sg:province":"NJ",
    "sg:tags":[
        "business"
    ],
    "wof:name":"Infusion Pharma Consulting LLC",
    "wof:placetype":"venue"
},
  "geometry": {"coordinates":[-74.55440400000001,40.692173],"type":"Point"}
}