{
  "type": "Feature",
  "properties": {
    "addr:full":"440 US Hwy 22 Bridgewater NJ 08807",
    "addr:housenumber":"440",
    "addr:postcode":"08807",
    "addr:street":"Us Hwy 22",
    "iso:country":"US",
    "sg:address":"440 US Hwy 22",
    "sg:city":"Bridgewater",
    "sg:classifiers":[
        {
            "category":"Manufacturing",
            "subcategory":"Chemicals & Compounds",
            "type":"Manufacturing & Wholesale Goods"
        }
    ],
    "sg:phone":"+1 908 218 7300",
    "sg:postcode":"08807",
    "sg:province":"NJ",
    "sg:tags":[
        "preparation",
        "pharmaceutical",
        "mfg"
    ],
    "wof:name":"Johnson & Johnson",
    "wof:placetype":"venue"
},
  "geometry": {"coordinates":[-74.651893,40.592149],"type":"Point"}
}