{
  "type": "Feature",
  "properties": {
    "iso:country":"US",
    "sg:address":"35 Lincoln Park Rd",
    "sg:city":"Pequannock",
    "sg:classifiers":[
        {
            "category":"Shopping",
            "subcategory":"Hobbies, Toys, & Games",
            "type":"Retail Goods"
        }
    ],
    "sg:phone":"+1   ",
    "sg:postcode":"07440",
    "sg:province":"NJ",
    "wof:name":"Race Games Inc",
    "wof:placetype":"venue"
},
  "geometry": {"coordinates":[-74.29686,40.941963],"type":"Point"}
}