{
  "type": "Feature",
  "properties": {
    "iso:country":"US",
    "sg:address":"63 Park St",
    "sg:city":"Tenafly",
    "sg:classifiers":[
        {
            "category":"Health Services",
            "subcategory":"Doctor",
            "type":"Services"
        }
    ],
    "sg:phone":"+1 201 567 1676",
    "sg:postcode":"07670",
    "sg:province":"NJ",
    "sg:tags":[
        "physician",
        "surgeon"
    ],
    "wof:name":"Martin Gardy MD",
    "wof:placetype":"venue"
},
  "geometry": {"coordinates":[-73.95519299999999,40.926528],"type":"Point"}
}