{
  "type": "Feature",
  "properties": {
    "addr:full":"11 Valley Rd Boonton NJ 07005",
    "addr:housenumber":"11",
    "addr:postcode":"07005",
    "addr:street":"Valley Rd",
    "iso:country":"US",
    "sg:address":"11 Valley Rd",
    "sg:city":"Boonton",
    "sg:classifiers":[
        {
            "category":"Education",
            "subcategory":"School",
            "type":"Public Place"
        }
    ],
    "sg:phone":"+1   ",
    "sg:postcode":"07005",
    "sg:province":"NJ",
    "wof:name":"Boonton Township School Dst",
    "wof:placetype":"venue"
},
  "geometry": {"coordinates":[-74.43066,40.925584],"type":"Point"}
}