{
  "type": "Feature",
  "properties": {
    "iso:country":"US",
    "sg:address":"275 Morgan Ave",
    "sg:city":"Pennsauken",
    "sg:classifiers":[
        {
            "category":"Freight",
            "type":"Transportation"
        }
    ],
    "sg:phone":"+1 856 665 7790",
    "sg:postcode":"08110",
    "sg:province":"NJ",
    "sg:tags":[
        "storage"
    ],
    "wof:name":"Product Storage Inc",
    "wof:placetype":"venue"
},
  "geometry": {"coordinates":[-75.06168599999999,39.979698],"type":"Point"}
}