{
  "type": "Feature",
  "properties": {
    "iso:country":"US",
    "sg:address":"68 Kelly Dr",
    "sg:city":"Edison",
    "sg:classifiers":[
        {
            "category":"Professional",
            "subcategory":"Computer Services",
            "type":"Services"
        }
    ],
    "sg:phone":"+1 732 321 5367",
    "sg:postcode":"08820",
    "sg:province":"NJ",
    "sg:tags":[
        "system",
        "integration"
    ],
    "wof:name":"Bridgelogix Corporation",
    "wof:placetype":"venue"
},
  "geometry": {"coordinates":[-74.398399,40.54977],"type":"Point"}
}