{
  "type": "Feature",
  "properties": {
    "addr:full":"5 Chopin Ct Jersey City NJ 07302",
    "addr:housenumber":"5",
    "addr:postcode":"07302",
    "addr:street":"Chopin Ct",
    "iso:country":"US",
    "sg:address":"5 Chopin Ct",
    "sg:city":"Jersey City",
    "sg:classifiers":[
        {
            "category":"Professional",
            "subcategory":"Research",
            "type":"Services"
        }
    ],
    "sg:phone":"+1 201 736 7243",
    "sg:postcode":"07302",
    "sg:province":"NJ",
    "sg:tags":[
        "commercial",
        "physical"
    ],
    "wof:name":"Tipu Communications",
    "wof:placetype":"venue"
},
  "geometry": {"coordinates":[-74.056359,40.721596],"type":"Point"}
}