{
  "type": "Feature",
  "properties": {
    "addr:full":"97 Blauvelt Ave Bergenfield NJ 07621",
    "addr:housenumber":"97",
    "addr:postcode":"07621",
    "addr:street":"Blauvelt Ave",
    "iso:country":"US",
    "sg:address":"97 Blauvelt Ave",
    "sg:city":"Bergenfield",
    "sg:classifiers":[
        {
            "category":"Shopping",
            "subcategory":"Gifts & Souvenirs",
            "type":"Retail Goods"
        }
    ],
    "sg:phone":"+1   ",
    "sg:postcode":"07621",
    "sg:province":"NJ",
    "wof:name":"Jubels Thrift Shop",
    "wof:placetype":"venue"
},
  "geometry": {"coordinates":[-74.001897,40.934765],"type":"Point"}
}