{
  "type": "Feature",
  "properties": {
    "addr:full":"420 Union Ave Irvington NJ 07111",
    "addr:housenumber":"420",
    "addr:postcode":"07111",
    "addr:street":"Union Ave",
    "iso:country":"US",
    "sg:address":"420 Union Ave",
    "sg:city":"Irvington",
    "sg:classifiers":[
        {
            "category":"Retail",
            "subcategory":"Auto Repair",
            "type":"Services"
        }
    ],
    "sg:phone":"+1 973 399 0117",
    "sg:postcode":"07111",
    "sg:province":"NJ",
    "sg:tags":[
        "repairing",
        "automobile"
    ],
    "wof:name":"Union Auto Ctr",
    "wof:placetype":"venue"
},
  "geometry": {"coordinates":[-74.239541,40.714214],"type":"Point"}
}