{
  "type": "Feature",
  "properties": {
    "iso:country":"US",
    "sg:address":"4 Fairfield Rd",
    "sg:city":"Fairfield",
    "sg:classifiers":[
        {
            "category":"Restaurant",
            "type":"Food & Drink"
        }
    ],
    "sg:phone":"+1   ",
    "sg:postcode":"07004",
    "sg:province":"NJ",
    "sg:tags":[
        "eating"
    ],
    "wof:name":"Osaka Restaurant",
    "wof:placetype":"venue"
},
  "geometry": {"coordinates":[-74.30449400000001,40.871431],"type":"Point"}
}