{
  "type": "Feature",
  "properties": {
    "addr:full":"631 Wright Debow Rd Jackson NJ 08527",
    "addr:housenumber":"631",
    "addr:postcode":"08527",
    "addr:street":"Wright Debow Rd",
    "iso:country":"US",
    "sg:address":"631 Wright Debow Rd",
    "sg:city":"Jackson",
    "sg:classifiers":[
        {
            "category":"Building & Trades",
            "subcategory":"Construction",
            "type":"Services"
        }
    ],
    "sg:phone":"+1 732 928 0600",
    "sg:postcode":"08527",
    "sg:province":"NJ",
    "sg:tags":[
        "course",
        "golf"
    ],
    "sg:website":"www.thedawsoncorp.com",
    "wof:name":"Dawson Corp",
    "wof:placetype":"venue"
},
  "geometry": {"coordinates":[-74.389141,40.165354],"type":"Point"}
}