{
  "type": "Feature",
  "properties": {
    "addr:full":"2 Roberts Rd Montvale NJ 07645",
    "addr:housenumber":"2",
    "addr:postcode":"07645",
    "addr:street":"Roberts Rd",
    "iso:country":"US",
    "sg:address":"2 Roberts Rd",
    "sg:city":"Montvale",
    "sg:classifiers":[
        {
            "category":"Manufacturing",
            "subcategory":"Chemicals & Compounds",
            "type":"Manufacturing & Wholesale Goods"
        }
    ],
    "sg:phone":"+1 201 782 1661",
    "sg:postcode":"07645",
    "sg:province":"NJ",
    "sg:tags":[
        "mfg"
    ],
    "wof:name":"Creative Pavers",
    "wof:placetype":"venue"
},
  "geometry": {"coordinates":[-74.01934199999999,41.043181],"type":"Point"}
}