{
  "type": "Feature",
  "properties": {
    "addr:full":"16 Tamwood Ln Sewell NJ 08080",
    "addr:housenumber":"16",
    "addr:postcode":"08080",
    "addr:street":"Tamwood Ln",
    "iso:country":"US",
    "sg:address":"16 Tamwood Ln",
    "sg:city":"Sewell",
    "sg:classifiers":[
        {
            "category":"Autos & Motor Vehicles",
            "subcategory":"Fuel & Gas Station",
            "type":"Retail Goods"
        }
    ],
    "sg:phone":"+1   ",
    "sg:postcode":"08080",
    "sg:province":"NJ",
    "sg:tags":[
        "station",
        "gasoline"
    ],
    "wof:name":"Amoco Petroleum Products",
    "wof:placetype":"venue"
},
  "geometry": {"coordinates":[-75.105572,39.764123],"type":"Point"}
}