{
  "type": "Feature",
  "properties": {
    "addr:full":"234 Windsor Cmns East Windsor NJ 08512",
    "addr:housenumber":"234",
    "addr:postcode":"08512",
    "addr:street":"Windsor Cmns East",
    "iso:country":"US",
    "sg:address":"234 Windsor Cmns",
    "sg:city":"East Windsor",
    "sg:classifiers":[
        {
            "category":"Food & Beverages",
            "subcategory":"Groceries & Convenience Stores",
            "type":"Retail Goods"
        }
    ],
    "sg:phone":"+1 609 448 0815",
    "sg:postcode":"08512",
    "sg:province":"NJ",
    "sg:tags":[
        "market"
    ],
    "wof:name":"Krauszer's",
    "wof:placetype":"venue"
},
  "geometry": {"coordinates":[-74.546299,40.286961],"type":"Point"}
}