{
  "type": "Feature",
  "properties": {
    "addr:full":"15 Riverside Dr Pine Brook NJ 07058",
    "addr:housenumber":"15",
    "addr:postcode":"07058",
    "addr:street":"Riverside Dr Pine",
    "iso:country":"US",
    "sg:address":"15 Riverside Dr",
    "sg:city":"Pine Brook",
    "sg:classifiers":[
        {
            "category":"Wholesale",
            "subcategory":"Electrical",
            "type":"Manufacturing & Wholesale Goods"
        }
    ],
    "sg:phone":"+1 973 439 0961",
    "sg:postcode":"07058",
    "sg:province":"NJ",
    "sg:tags":[
        "equipment",
        "electric",
        "supply"
    ],
    "wof:name":"Barnett Inc",
    "wof:placetype":"venue"
},
  "geometry": {"coordinates":[-74.34082100000001,40.853878],"type":"Point"}
}