{
  "type": "Feature",
  "properties": {
    "addr:full":"6 Molter Pl Bloomfield NJ 07003",
    "addr:housenumber":"6",
    "addr:postcode":"07003",
    "addr:street":"Molter Pl",
    "iso:country":"US",
    "sg:address":"6 Molter Pl",
    "sg:city":"Bloomfield",
    "sg:classifiers":[
        {
            "category":"Cinema",
            "subcategory":"Movie Rental",
            "type":"Entertainment"
        }
    ],
    "sg:phone":"+1 973 429 0492",
    "sg:postcode":"07003",
    "sg:province":"NJ",
    "sg:tags":[
        "video",
        "tape"
    ],
    "wof:name":"Motion Photo Video Studio",
    "wof:placetype":"venue"
},
  "geometry": {"coordinates":[-74.198588,40.783754],"type":"Point"}
}