{
  "type": "Feature",
  "properties": {
    "addr:full":"47 Distler Ave Caldwell NJ 07006",
    "addr:housenumber":"47",
    "addr:postcode":"07006",
    "addr:street":"Distler Ave",
    "iso:country":"US",
    "sg:address":"47 Distler Ave",
    "sg:city":"Caldwell",
    "sg:classifiers":[
        {
            "category":"Real Estate",
            "subcategory":"Real Estate Agent",
            "type":"Services"
        }
    ],
    "sg:phone":"+1   ",
    "sg:postcode":"07006",
    "sg:province":"NJ",
    "sg:tags":[
        "appraiser"
    ],
    "wof:name":"Appraisal Group",
    "wof:placetype":"venue"
},
  "geometry": {"coordinates":[-74.306856,40.850451],"type":"Point"}
}