{
  "type": "Feature",
  "properties": {
    "iso:country":"US",
    "sg:address":"201 W Passaic St",
    "sg:city":"Rochelle Park",
    "sg:classifiers":[
        {
            "category":"Health Services",
            "subcategory":"Doctor",
            "type":"Services"
        }
    ],
    "sg:phone":"+1 201 556 9430",
    "sg:postcode":"07662",
    "sg:province":"NJ",
    "sg:tags":[
        "development",
        "management",
        "for",
        "medical",
        "it",
        "software"
    ],
    "wof:name":"Palm Lake Enterprises Inc",
    "wof:placetype":"venue"
},
  "geometry": {"coordinates":[-74.082438,40.914961],"type":"Point"}
}