{
  "type": "Feature",
  "properties": {
    "iso:country":"US",
    "sg:address":"1187 Main Ave",
    "sg:city":"Clifton",
    "sg:classifiers":[
        {
            "category":"Health Services",
            "subcategory":"Optometrist",
            "type":"Services"
        }
    ],
    "sg:phone":"+1 973 546 6161",
    "sg:postcode":"07011",
    "sg:province":"NJ",
    "sg:tags":[
        "ophthalmologist"
    ],
    "wof:name":"Mund Michael L MD Facs",
    "wof:placetype":"venue"
},
  "geometry": {"coordinates":[-74.140404,40.876099],"type":"Point"}
}