{
  "type": "Feature",
  "properties": {
    "addr:full":"426 E Ridgewood Ave Absecon NJ 08201",
    "addr:housenumber":"426",
    "addr:postcode":"08201",
    "addr:street":"E Ridgewood Ave",
    "iso:country":"US",
    "sg:address":"426 E Ridgewood Ave",
    "sg:city":"Absecon",
    "sg:classifiers":[
        {
            "category":"Professional",
            "subcategory":"Business Services",
            "type":"Services"
        }
    ],
    "sg:phone":"+1   ",
    "sg:postcode":"08201",
    "sg:province":"NJ",
    "wof:name":"Hartman Intriors Fine Cabinets",
    "wof:placetype":"venue"
},
  "geometry": {"coordinates":[-74.490236,39.452798],"type":"Point"}
}