{
  "type": "Feature",
  "properties": {
    "iso:country":"US",
    "sg:address":"211 Main St",
    "sg:city":"Orange",
    "sg:classifiers":[
        {
            "category":"Shopping",
            "subcategory":"Shoes",
            "type":"Retail Goods"
        }
    ],
    "sg:phone":"+1 973 677 1260",
    "sg:postcode":"07050",
    "sg:province":"NJ",
    "sg:tags":[
        "store"
    ],
    "wof:name":"Hip Hop Sneakers",
    "wof:placetype":"venue"
},
  "geometry": {"coordinates":[-74.22689699999999,40.771237],"type":"Point"}
}