{
  "type": "Feature",
  "properties": {
    "addr:full":"2 Emerson Ln Secaucus NJ 07094",
    "addr:housenumber":"2",
    "addr:postcode":"07094",
    "addr:street":"Emerson Ln",
    "iso:country":"US",
    "sg:address":"2 Emerson Ln",
    "sg:city":"Secaucus",
    "sg:classifiers":[
        {
            "category":"Shopping",
            "type":"Retail Goods"
        }
    ],
    "sg:phone":"+1 201 319 8411",
    "sg:postcode":"07094",
    "sg:province":"NJ",
    "sg:tags":[
        "factory",
        "outlet"
    ],
    "wof:name":"Liz Claiborne Outlet Store",
    "wof:placetype":"venue"
},
  "geometry": {"coordinates":[-74.06561499999999,40.785374],"type":"Point"}
}