{
  "type": "Feature",
  "properties": {
    "addr:full":"246 Seaview Ave Jersey City NJ 07305",
    "addr:housenumber":"246",
    "addr:postcode":"07305",
    "addr:street":"Seaview Ave",
    "iso:country":"US",
    "sg:address":"246 Seaview Ave",
    "sg:city":"Jersey City",
    "sg:classifiers":[
        {
            "category":"Retail",
            "subcategory":"Auto Repair",
            "type":"Services"
        }
    ],
    "sg:phone":"+1 201 521 0987",
    "sg:postcode":"07305",
    "sg:province":"NJ",
    "wof:name":"E R Auto Service",
    "wof:placetype":"venue"
},
  "geometry": {"coordinates":[-74.099299,40.696182],"type":"Point"}
}