{
  "type": "Feature",
  "properties": {
    "addr:full":"115 Belmont Ave Belleville NJ 07109",
    "addr:housenumber":"115",
    "addr:postcode":"07109",
    "addr:street":"Belmont Ave",
    "iso:country":"US",
    "sg:address":"115 Belmont Ave",
    "sg:city":"Belleville",
    "sg:classifiers":[
        {
            "category":"Retail",
            "subcategory":"Self-service Laundry",
            "type":"Services"
        },
        {
            "category":"Retail",
            "subcategory":"Laundry & Dry Cleaning",
            "type":"Services"
        }
    ],
    "sg:phone":"+1 973 751 0571",
    "sg:postcode":"07109",
    "sg:province":"NJ",
    "sg:tags":[
        "drycleaning",
        "plant",
        "coin"
    ],
    "wof:name":"Tri-City Laundromat & Dry Clnr",
    "wof:placetype":"venue"
},
  "geometry": {"coordinates":[-74.18180700000001,40.779973],"type":"Point"}
}