{
  "type": "Feature",
  "properties": {
    "iso:country":"US",
    "sg:address":"613 Paramus Rd",
    "sg:city":"Paramus",
    "sg:classifiers":[
        {
            "category":"Wholesale",
            "subcategory":"Home Furnishings",
            "type":"Manufacturing & Wholesale Goods"
        }
    ],
    "sg:phone":"+1 201 652 8009",
    "sg:postcode":"07652",
    "sg:province":"NJ",
    "sg:tags":[
        "rug",
        "area"
    ],
    "wof:name":"Synovia Rugs Inc",
    "wof:placetype":"venue"
},
  "geometry": {"coordinates":[-74.092062,40.967616],"type":"Point"}
}