{
  "type": "Feature",
  "properties": {
    "addr:full":"2401 Arctic Ave Atlantic City NJ 08401",
    "addr:housenumber":"2401",
    "addr:postcode":"08401",
    "addr:street":"Arctic Ave",
    "iso:country":"US",
    "sg:address":"2401 Arctic Ave",
    "sg:city":"Atlantic City",
    "sg:classifiers":[
        {
            "category":"Retail",
            "subcategory":"Auto Repair",
            "type":"Services"
        }
    ],
    "sg:phone":"+1   ",
    "sg:postcode":"08401",
    "sg:province":"NJ",
    "sg:tags":[
        "automotive",
        "station",
        "gasoline",
        "general"
    ],
    "wof:name":"BP",
    "wof:placetype":"venue"
},
  "geometry": {"coordinates":[-74.442902,39.358067],"type":"Point"}
}