{
  "type": "Feature",
  "properties": {
    "iso:country":"US",
    "sg:address":"90 US Hwy 206",
    "sg:city":"Stanhope",
    "sg:classifiers":[
        {
            "category":"Cinema",
            "subcategory":"Movie Rental",
            "type":"Entertainment"
        }
    ],
    "sg:phone":"+1   ",
    "sg:postcode":"07874",
    "sg:province":"NJ",
    "sg:tags":[
        "video",
        "tape"
    ],
    "sg:website":"www.hollywoodvideo.com",
    "wof:name":"Hollywood Video",
    "wof:placetype":"venue"
},
  "geometry": {"coordinates":[-74.720759,40.934813],"type":"Point"}
}