{
  "type": "Feature",
  "properties": {
    "addr:full":"1675 Whitehorse Mercerville Rd Trenton NJ 08619",
    "addr:housenumber":"1675",
    "addr:postcode":"08619",
    "addr:street":"Whitehorse Mercerville Rd",
    "iso:country":"US",
    "sg:address":"1675 Whitehorse Mercerville Rd",
    "sg:city":"Trenton",
    "sg:classifiers":[
        {
            "category":"Health Services",
            "subcategory":"Doctor",
            "type":"Services"
        }
    ],
    "sg:phone":"+1 609 890 1606",
    "sg:postcode":"08619",
    "sg:province":"NJ",
    "sg:tags":[
        "physician",
        "surgeon"
    ],
    "wof:name":"Carl J Chiappetta MD",
    "wof:placetype":"venue"
},
  "geometry": {"coordinates":[-74.687693,40.222485],"type":"Point"}
}