{
  "type": "Feature",
  "properties": {
    "addr:full":"39 Hines Ave Mahwah NJ 07430",
    "addr:housenumber":"39",
    "addr:postcode":"07430",
    "addr:street":"Hines Ave",
    "iso:country":"US",
    "sg:address":"39 Hines Ave",
    "sg:city":"Mahwah",
    "sg:classifiers":[
        {
            "category":"Building & Trades",
            "subcategory":"Plumbing",
            "type":"Services"
        }
    ],
    "sg:phone":"+1 201 529 1230",
    "sg:postcode":"07430",
    "sg:province":"NJ",
    "sg:tags":[
        "conditioning",
        "air",
        "system",
        "contractor"
    ],
    "wof:name":"Nelsons HVAC Corp",
    "wof:placetype":"venue"
},
  "geometry": {"coordinates":[-74.15693899999999,41.100614],"type":"Point"}
}