{
  "type": "Feature",
  "properties": {
    "addr:full":"125 Kensington Ave Jersey City NJ 07304",
    "addr:housenumber":"125",
    "addr:postcode":"07304",
    "addr:street":"Kensington Ave",
    "iso:country":"US",
    "sg:address":"125 Kensington Ave",
    "sg:city":"Jersey City",
    "sg:classifiers":[
        {
            "category":"Real Estate",
            "subcategory":"Architect",
            "type":"Services"
        }
    ],
    "sg:phone":"+1 201 432 8906",
    "sg:postcode":"07304",
    "sg:province":"NJ",
    "sg:tags":[
        "marketing",
        "consulting",
        "design",
        "architectural"
    ],
    "wof:name":"Elizabeth R Thomson AIA",
    "wof:placetype":"venue"
},
  "geometry": {"coordinates":[-74.076853,40.723519],"type":"Point"}
}