{
  "type": "Feature",
  "properties": {
    "iso:country":"US",
    "sg:address":"10 Belmont Ave",
    "sg:city":"Madison",
    "sg:classifiers":[
        {
            "category":"Retail",
            "subcategory":"Auto Repair",
            "type":"Services"
        }
    ],
    "sg:phone":"+1 973 593 0445",
    "sg:postcode":"07940",
    "sg:province":"NJ",
    "sg:tags":[
        "towing"
    ],
    "wof:name":"MO-Tow-Auto",
    "wof:placetype":"venue"
},
  "geometry": {"coordinates":[-74.414034,40.752806],"type":"Point"}
}