{
  "type": "Feature",
  "properties": {
    "addr:full":"509 Monmouth Ave Spring Lake NJ 07762",
    "addr:housenumber":"509",
    "addr:postcode":"07762",
    "addr:street":"Monmouth Ave",
    "iso:country":"US",
    "sg:address":"509 Monmouth Ave",
    "sg:city":"Spring Lake",
    "sg:classifiers":[
        {
            "category":"Government",
            "subcategory":"Office",
            "type":"Public Place"
        }
    ],
    "sg:phone":"+1 732 449 7930",
    "sg:postcode":"07762",
    "sg:province":"NJ",
    "sg:tags":[
        "govt",
        "city"
    ],
    "wof:name":"Spring Lake Water Works",
    "wof:placetype":"venue"
},
  "geometry": {"coordinates":[-74.035865,40.147285],"type":"Point"}
}