{
  "type": "Feature",
  "properties": {
    "addr:full":"587 Fayette St Perth Amboy NJ 08861",
    "addr:housenumber":"587",
    "addr:postcode":"08861",
    "addr:street":"Fayette St",
    "iso:country":"US",
    "sg:address":"587 Fayette St",
    "sg:city":"Perth Amboy",
    "sg:classifiers":[
        {
            "category":"Restaurant",
            "type":"Food & Drink"
        }
    ],
    "sg:phone":"+1   ",
    "sg:postcode":"08861",
    "sg:province":"NJ",
    "sg:tags":[
        "eating"
    ],
    "wof:name":"Blimpie",
    "wof:placetype":"venue"
},
  "geometry": {"coordinates":[-74.28622799999999,40.515587],"type":"Point"}
}