{
  "type": "Feature",
  "properties": {
    "addr:full":"18 Mill Run Dr Hammonton NJ 08037",
    "addr:housenumber":"18",
    "addr:postcode":"08037",
    "addr:street":"Mill Run Dr",
    "iso:country":"US",
    "sg:address":"18 Mill Run Dr",
    "sg:city":"Hammonton",
    "sg:classifiers":[
        {
            "category":"Freight",
            "type":"Transportation"
        }
    ],
    "sg:phone":"+1 609 567 2648",
    "sg:postcode":"08037",
    "sg:province":"NJ",
    "sg:tags":[
        "operator",
        "local",
        "trucking"
    ],
    "wof:name":"L M R Trucking Inc",
    "wof:placetype":"venue"
},
  "geometry": {"coordinates":[-74.77626600000001,39.621006],"type":"Point"}
}