{
  "type": "Feature",
  "properties": {
    "iso:country":"US",
    "sg:address":"390 Hurffville Crosskeys Rd",
    "sg:city":"Sewell",
    "sg:classifiers":[
        {
            "category":"Shopping",
            "subcategory":"Pharmacy",
            "type":"Retail Goods"
        }
    ],
    "sg:phone":"+1 856 589 8466",
    "sg:postcode":"08080",
    "sg:province":"NJ",
    "wof:name":"Rite Aid",
    "wof:placetype":"venue"
},
  "geometry": {"coordinates":[-75.05802799999999,39.72928],"type":"Point"}
}