{
  "type": "Feature",
  "properties": {
    "iso:country":"US",
    "sg:address":"237 N Black Horse Pike",
    "sg:city":"Bellmawr",
    "sg:classifiers":[
        {
            "category":"Professional",
            "subcategory":"Business Services",
            "type":"Services"
        }
    ],
    "sg:phone":"+1 856 232 0001",
    "sg:postcode":"08031",
    "sg:province":"NJ",
    "sg:tags":[
        "pool",
        "swimming"
    ],
    "wof:name":"Glacier Blue Pool Svc",
    "wof:placetype":"venue"
},
  "geometry": {"coordinates":[-75.081993,39.872224],"type":"Point"}
}