{
  "type": "Feature",
  "properties": {
    "addr:full":"30 N Broadway Pitman NJ 08071",
    "addr:housenumber":"30",
    "addr:postcode":"08071",
    "addr:street":"N Broadway",
    "iso:country":"US",
    "sg:address":"30 N Broadway",
    "sg:city":"Pitman",
    "sg:classifiers":[
        {
            "category":"Organizations",
            "subcategory":"Religious Organization",
            "type":"Services"
        }
    ],
    "sg:phone":"+1   ",
    "sg:postcode":"08071",
    "sg:province":"NJ",
    "wof:name":"First Baptist Church",
    "wof:placetype":"venue"
},
  "geometry": {"coordinates":[-75.13183100000001,39.733345],"type":"Point"}
}