{
  "type": "Feature",
  "properties": {
    "addr:full":"28 Valley Forge Ln Morris Plains NJ 07950",
    "addr:housenumber":"28",
    "addr:postcode":"07950",
    "addr:street":"Valley Forge Ln",
    "iso:country":"US",
    "sg:address":"28 Valley Forge Ln",
    "sg:city":"Morris Plains",
    "sg:classifiers":[
        {
            "category":"Wholesale",
            "subcategory":"Apparel",
            "type":"Manufacturing & Wholesale Goods"
        }
    ],
    "sg:phone":"+1 973 216 2023",
    "sg:postcode":"07950",
    "sg:province":"NJ",
    "sg:tags":[
        "clothing"
    ],
    "wof:name":"Babyragz",
    "wof:placetype":"venue"
},
  "geometry": {"coordinates":[-74.48860999999999,40.853594],"type":"Point"}
}