{
  "type": "Feature",
  "properties": {
    "addr:full":"6 Healey Ter Kearny NJ 07032",
    "addr:housenumber":"6",
    "addr:postcode":"07032",
    "addr:street":"Healey Ter",
    "iso:country":"US",
    "sg:address":"6 Healey Ter",
    "sg:city":"Kearny",
    "sg:classifiers":[
        {
            "category":"Retail",
            "subcategory":"Self-service Laundry",
            "type":"Services"
        }
    ],
    "sg:phone":"+1 201 997 5296",
    "sg:postcode":"07032",
    "sg:province":"NJ",
    "sg:tags":[
        "coin"
    ],
    "wof:name":"En Central Laundry Inc",
    "wof:placetype":"venue"
},
  "geometry": {"coordinates":[-74.15286,40.770913],"type":"Point"}
}