{
  "type": "Feature",
  "properties": {
    "addr:full":"460 Totowa Ave Paterson NJ 07522",
    "addr:housenumber":"460",
    "addr:postcode":"07522",
    "addr:street":"Totowa Ave",
    "iso:country":"US",
    "sg:address":"460 Totowa Ave",
    "sg:city":"Paterson",
    "sg:classifiers":[
        {
            "category":"Manufacturing",
            "subcategory":"Electronics",
            "type":"Manufacturing & Wholesale Goods"
        }
    ],
    "sg:phone":"+1 973 942 2222",
    "sg:postcode":"07522",
    "sg:province":"NJ",
    "sg:tags":[
        "coil",
        "transformer",
        "electronic"
    ],
    "wof:name":"Electronic Transformer Corp",
    "wof:placetype":"venue"
},
  "geometry": {"coordinates":[-74.181656,40.920009],"type":"Point"}
}