{
  "type": "Feature",
  "properties": {
    "iso:country":"US",
    "sg:address":"250 Moonachie Rd Ste 4",
    "sg:city":"Moonachie",
    "sg:classifiers":[
        {
            "category":"Professional",
            "subcategory":"Accounting & Tax Preparation",
            "type":"Services"
        }
    ],
    "sg:phone":"+1 201 488 9188",
    "sg:postcode":"07074",
    "sg:province":"NJ",
    "sg:tags":[
        "accountant"
    ],
    "wof:name":"Liebgold Wuensch & Assoc Llp Cpa's",
    "wof:placetype":"venue"
},
  "geometry": {"coordinates":[-74.051919,40.834124],"type":"Point"}
}