{
  "type": "Feature",
  "properties": {
    "addr:full":"212 Vanderpool St Newark NJ 07114",
    "addr:housenumber":"212",
    "addr:postcode":"07114",
    "addr:street":"Vanderpool St",
    "iso:country":"US",
    "sg:address":"212 Vanderpool St",
    "sg:city":"Newark",
    "sg:classifiers":[
        {
            "category":"Wholesale",
            "subcategory":"Chemicals & Plastics",
            "type":"Manufacturing & Wholesale Goods"
        }
    ],
    "sg:phone":"+1 973 622 8666",
    "sg:postcode":"07114",
    "sg:province":"NJ",
    "wof:name":"A-1 Productions",
    "wof:placetype":"venue"
},
  "geometry": {"coordinates":[-74.178039,40.717257],"type":"Point"}
}