{
  "type": "Feature",
  "properties": {
    "addr:full":"2 Freedom Ln Marlboro NJ 07746",
    "addr:housenumber":"2",
    "addr:postcode":"07746",
    "addr:street":"Freedom Ln",
    "iso:country":"US",
    "sg:address":"2 Freedom Ln",
    "sg:city":"Marlboro",
    "sg:classifiers":[
        {
            "category":"Health Services",
            "subcategory":"Health Practitioner",
            "type":"Services"
        }
    ],
    "sg:phone":"+1 732 536 8858",
    "sg:postcode":"07746",
    "sg:province":"NJ",
    "wof:name":"Occupational Services",
    "wof:placetype":"venue"
},
  "geometry": {"coordinates":[-74.26088799999999,40.326634],"type":"Point"}
}