{
  "type": "Feature",
  "properties": {
    "iso:country":"US",
    "sg:address":"111 Broad St",
    "sg:city":"Eatontown",
    "sg:classifiers":[
        {
            "category":"Professional",
            "subcategory":"Lawyer & Legal Services",
            "type":"Services"
        }
    ],
    "sg:phone":"+1 732 389 7555",
    "sg:postcode":"07724",
    "sg:province":"NJ",
    "sg:tags":[
        "attorney"
    ],
    "wof:name":"Leon J Gaylord Jr Esq",
    "wof:placetype":"venue"
},
  "geometry": {"coordinates":[-74.060244,40.305378],"type":"Point"}
}