{
  "type": "Feature",
  "properties": {
    "iso:country":"US",
    "sg:address":"321 Broad Ave",
    "sg:city":"Ridgefield",
    "sg:classifiers":[
        {
            "category":"Shopping",
            "subcategory":"Department Store",
            "type":"Retail Goods"
        }
    ],
    "sg:phone":"+1 201 840 1110",
    "sg:postcode":"07657",
    "sg:province":"NJ",
    "wof:name":"Anh Broadcasting Corporation",
    "wof:placetype":"venue"
},
  "geometry": {"coordinates":[-74.00915999999999,40.82496],"type":"Point"}
}