{
  "type": "Feature",
  "properties": {
    "iso:country":"US",
    "sg:address":"230 N Main Rd",
    "sg:city":"Vineland",
    "sg:classifiers":[
        {
            "category":"Real Estate",
            "subcategory":"Real Estate Agent",
            "type":"Services"
        }
    ],
    "sg:phone":"+1 856 691 4664",
    "sg:postcode":"08360",
    "sg:province":"NJ",
    "sg:tags":[
        "management"
    ],
    "wof:name":"Eve Ackerman Real Estate",
    "wof:placetype":"venue"
},
  "geometry": {"coordinates":[-74.998442,39.487934],"type":"Point"}
}