{
  "type": "Feature",
  "properties": {
    "iso:country":"US",
    "sg:address":"65 Cambridge Dr",
    "sg:city":"Jackson",
    "sg:classifiers":[
        {
            "category":"Building & Trades",
            "subcategory":"Construction",
            "type":"Services"
        }
    ],
    "sg:phone":"+1 732 942 9032",
    "sg:postcode":"08527",
    "sg:province":"NJ",
    "sg:tags":[
        "contractor"
    ],
    "wof:name":"Komitski Contracting",
    "wof:placetype":"venue"
},
  "geometry": {"coordinates":[-74.279848,40.111127],"type":"Point"}
}