{
  "type": "Feature",
  "properties": {
    "iso:country":"US",
    "sg:address":"270 Walker St",
    "sg:city":"Fairview",
    "sg:classifiers":[
        {
            "category":"Professional",
            "type":"Services"
        }
    ],
    "sg:phone":"+1   ",
    "sg:postcode":"07022",
    "sg:province":"NJ",
    "wof:name":"Klapa S Susak",
    "wof:placetype":"venue"
},
  "geometry": {"coordinates":[-73.994758,40.816435],"type":"Point"}
}