{
  "type": "Feature",
  "properties": {
    "addr:full":"184 19th St Union City NJ 07087",
    "addr:housenumber":"184",
    "addr:postcode":"07087",
    "addr:street":"19Th St",
    "iso:country":"US",
    "sg:address":"184 19th St",
    "sg:city":"Union City",
    "sg:classifiers":[
        {
            "category":"Manufacturing",
            "subcategory":"Signs",
            "type":"Manufacturing & Wholesale Goods"
        }
    ],
    "sg:phone":"+1 201 902 9299",
    "sg:postcode":"07087",
    "sg:province":"NJ",
    "sg:tags":[
        "specialty",
        "mfg"
    ],
    "wof:name":"A G I",
    "wof:placetype":"venue"
},
  "geometry": {"coordinates":[-74.030461,40.762208],"type":"Point"}
}