{
  "type": "Feature",
  "properties": {
    "addr:full":"210 Carlton Ave Collingswood NJ 08108",
    "addr:housenumber":"210",
    "addr:postcode":"08108",
    "addr:street":"Carlton Ave",
    "iso:country":"US",
    "sg:address":"210 Carlton Ave",
    "sg:city":"Collingswood",
    "sg:classifiers":[
        {
            "category":"Professional",
            "subcategory":"Detective & Security Services",
            "type":"Services"
        }
    ],
    "sg:phone":"+1   ",
    "sg:postcode":"08108",
    "sg:province":"NJ",
    "sg:tags":[
        "car"
    ],
    "wof:name":"Aarons Investigations",
    "wof:placetype":"venue"
},
  "geometry": {"coordinates":[-75.04742,39.904657],"type":"Point"}
}