{
  "type": "Feature",
  "properties": {
    "addr:full":"703 E Front St Plainfield NJ 07060",
    "addr:housenumber":"703",
    "addr:postcode":"07060",
    "addr:street":"E Front St",
    "iso:country":"US",
    "sg:address":"703 E Front St",
    "sg:city":"Plainfield",
    "sg:classifiers":[
        {
            "category":"Building & Trades",
            "subcategory":"Construction",
            "type":"Services"
        }
    ],
    "sg:phone":"+1 908 561 7555",
    "sg:postcode":"07060",
    "sg:province":"NJ",
    "sg:tags":[
        "resurfacing",
        "laying",
        "refinishing",
        "floor"
    ],
    "wof:name":"Eagle Floors",
    "wof:placetype":"venue"
},
  "geometry": {"coordinates":[-74.41490899999999,40.628755],"type":"Point"}
}