{
  "type": "Feature",
  "properties": {
    "addr:full":"89 Main St South Bound Brook NJ 08880",
    "addr:housenumber":"89",
    "addr:postcode":"08880",
    "addr:street":"Main St",
    "iso:country":"US",
    "sg:address":"89 Main St",
    "sg:city":"South Bound Brook",
    "sg:classifiers":[
        {
            "category":"Restaurant",
            "type":"Food & Drink"
        }
    ],
    "sg:menulink":"http://www.allmenus.com/nj/south-bound-brook/23870-wasabi-wok/menu/",
    "sg:phone":"+1 732 805 3998",
    "sg:postcode":"08880",
    "sg:province":"NJ",
    "sg:tags":[
        "asian",
        "chinese"
    ],
    "wof:name":"Wasabi Wok",
    "wof:placetype":"venue"
},
  "geometry": {"coordinates":[-74.52486,40.553789],"type":"Point"}
}