{
  "type": "Feature",
  "properties": {
    "addr:full":"80 Cherryville Stanton Rd Flemington NJ 08822",
    "addr:housenumber":"80",
    "addr:postcode":"08822",
    "addr:street":"Cherryville Stanton Rd",
    "iso:country":"US",
    "sg:address":"80 Cherryville Stanton Rd",
    "sg:city":"Flemington",
    "sg:classifiers":[
        {
            "category":"Manufacturing",
            "subcategory":"Tools & Machinery",
            "type":"Manufacturing & Wholesale Goods"
        }
    ],
    "sg:phone":"+1 908 782 6781",
    "sg:postcode":"08822",
    "sg:province":"NJ",
    "sg:tags":[
        "machine",
        "shop",
        "industrial",
        "mfg"
    ],
    "wof:name":"C M C Machine Co",
    "wof:placetype":"venue"
},
  "geometry": {"coordinates":[-74.896068,40.561244],"type":"Point"}
}