{
  "type": "Feature",
  "properties": {
    "addr:full":"251 Main Ave Passaic NJ 07055",
    "addr:housenumber":"251",
    "addr:postcode":"07055",
    "addr:street":"Main Ave",
    "iso:country":"US",
    "sg:address":"251 Main Ave",
    "sg:city":"Passaic",
    "sg:classifiers":[
        {
            "category":"Shopping",
            "subcategory":"Clothing, Apparel, & Fashions",
            "type":"Retail Goods"
        }
    ],
    "sg:phone":"+1   ",
    "sg:postcode":"07055",
    "sg:province":"NJ",
    "sg:tags":[
        "woman"
    ],
    "wof:name":"Two-Tone",
    "wof:placetype":"venue"
},
  "geometry": {"coordinates":[-74.124944,40.848668],"type":"Point"}
}