{
  "type": "Feature",
  "properties": {
    "addr:full":"357 N Main St Glassboro NJ 08028",
    "addr:housenumber":"357",
    "addr:postcode":"08028",
    "addr:street":"N Main St",
    "iso:country":"US",
    "sg:address":"357 N Main St",
    "sg:city":"Glassboro",
    "sg:classifiers":[
        {
            "category":"Personal",
            "type":"Services"
        }
    ],
    "sg:phone":"+1   ",
    "sg:postcode":"08028",
    "sg:province":"NJ",
    "wof:name":"Rae M R S",
    "wof:placetype":"venue"
},
  "geometry": {"coordinates":[-75.111065,39.70907],"type":"Point"}
}