{
  "type": "Feature",
  "properties": {
    "addr:full":"181 Co Rd 539 Creamridge NJ 08514",
    "addr:housenumber":"181",
    "addr:postcode":"08514",
    "addr:street":"Co Rd 539",
    "iso:country":"US",
    "sg:address":"181 Co Rd 539",
    "sg:city":"Creamridge",
    "sg:classifiers":[
        {
            "category":"Recreation",
            "type":"Entertainment"
        }
    ],
    "sg:phone":"+1 609 259 2849",
    "sg:postcode":"08514",
    "sg:province":"NJ",
    "sg:tags":[
        "golf",
        "leasing",
        "cart"
    ],
    "wof:name":"Creemwich Golf Club",
    "wof:placetype":"venue"
},
  "geometry": {"coordinates":[-74.537171,40.146747],"type":"Point"}
}