{
  "type": "Feature",
  "properties": {
    "iso:country":"US",
    "sg:address":"89 Chestnut St",
    "sg:city":"Ridgewood",
    "sg:classifiers":[
        {
            "category":"Professional",
            "subcategory":"Lawyer & Legal Services",
            "type":"Services"
        }
    ],
    "sg:phone":"+1 201 251 2636",
    "sg:postcode":"07450",
    "sg:province":"NJ",
    "wof:name":"Edward Teitelbaum PC",
    "wof:placetype":"venue"
},
  "geometry": {"coordinates":[-74.11794,40.983506],"type":"Point"}
}