{
  "type": "Feature",
  "properties": {
    "addr:full":"100 Adams Dr Totowa NJ 07512",
    "addr:housenumber":"100",
    "addr:postcode":"07512",
    "addr:street":"Adams Dr",
    "iso:country":"US",
    "sg:address":"100 Adams Dr",
    "sg:city":"Totowa",
    "sg:classifiers":[
        {
            "category":"Manufacturing",
            "subcategory":"Pet Food",
            "type":"Manufacturing & Wholesale Goods"
        }
    ],
    "sg:phone":"+1 973 256 8886",
    "sg:postcode":"07512",
    "sg:province":"NJ",
    "sg:tags":[
        "flour",
        "prepared",
        "dough",
        "mix"
    ],
    "sg:website":"www.caravanproducts.com",
    "wof:name":"Caravan Products Co Inc",
    "wof:placetype":"venue"
},
  "geometry": {"coordinates":[-74.22675599999999,40.885392],"type":"Point"}
}