{
  "type": "Feature",
  "properties": {
    "iso:country":"US",
    "sg:address":"6 Thistle Ln",
    "sg:city":"Flemington",
    "sg:classifiers":[
        {
            "category":"Banks & Credit Unions",
            "subcategory":"Investment Brokerage",
            "type":"Services"
        }
    ],
    "sg:phone":"+1 908 788 1014",
    "sg:postcode":"08822",
    "sg:province":"NJ",
    "sg:tags":[
        "consultant",
        "planning",
        "financial"
    ],
    "sg:website":"www.pmc-management.com",
    "wof:name":"PMC Management Consultants",
    "wof:placetype":"venue"
},
  "geometry": {"coordinates":[-74.795019,40.53961],"type":"Point"}
}