{
  "type": "Feature",
  "properties": {
    "addr:full":"363 Janes Chapel Rd Oxford NJ 07863",
    "addr:housenumber":"363",
    "addr:postcode":"07863",
    "addr:street":"Janes Chapel Rd",
    "iso:country":"US",
    "sg:address":"363 Janes Chapel Rd",
    "sg:city":"Oxford",
    "sg:classifiers":[
        {
            "category":"Sports & Exercise",
            "subcategory":"Sports Center",
            "type":"Entertainment"
        },
        {
            "category":"Arena",
            "subcategory":"Sports Club",
            "type":"Entertainment"
        }
    ],
    "sg:phone":"+1 908 637 9813",
    "sg:postcode":"07863",
    "sg:province":"NJ",
    "sg:tags":[
        "professional",
        "amateur",
        "team"
    ],
    "wof:name":"Shongum Sportsmens Association",
    "wof:placetype":"venue"
},
  "geometry": {"coordinates":[-74.923599,40.839199],"type":"Point"}
}