{
  "type": "Feature",
  "properties": {
    "addr:full":"400 W Broadway Haledon NJ 07508",
    "addr:housenumber":"400",
    "addr:postcode":"07508",
    "addr:street":"W Broadway",
    "iso:country":"US",
    "sg:address":"400 W Broadway",
    "sg:city":"Haledon",
    "sg:classifiers":[
        {
            "category":"Retail",
            "subcategory":"Storage",
            "type":"Services"
        }
    ],
    "sg:phone":"+1 973 904 0599",
    "sg:postcode":"07508",
    "sg:province":"NJ",
    "sg:tags":[
        "self"
    ],
    "sg:website":"www.aselfstorage.com",
    "wof:name":"A Self Storage of Haledon",
    "wof:placetype":"venue"
},
  "geometry": {"coordinates":[-74.186798,40.927502],"type":"Point"}
}