{
  "type": "Feature",
  "properties": {
    "addr:full":"65 William St Old Bridge NJ 08857",
    "addr:housenumber":"65",
    "addr:postcode":"08857",
    "addr:street":"William St",
    "iso:country":"US",
    "sg:address":"65 William St",
    "sg:city":"Old Bridge",
    "sg:classifiers":[
        {
            "category":"Professional",
            "type":"Services"
        }
    ],
    "sg:phone":"+1   ",
    "sg:postcode":"08857",
    "sg:province":"NJ",
    "wof:name":"G Mills Teresa",
    "wof:placetype":"venue"
},
  "geometry": {"coordinates":[-74.360805,40.419256],"type":"Point"}
}