{
  "type": "Feature",
  "properties": {
    "iso:country":"US",
    "sg:address":"184 S Broad St",
    "sg:city":"Trenton",
    "sg:classifiers":[
        {
            "category":"Professional",
            "subcategory":"Lawyer & Legal Services",
            "type":"Services"
        }
    ],
    "sg:phone":"+1 609 656 9100",
    "sg:postcode":"08608",
    "sg:province":"NJ",
    "sg:tags":[
        "attorney",
        "criminal",
        "duo",
        "personal",
        "worker",
        "compensation",
        "benefit",
        "employee",
        "injury",
        "dwi",
        "law"
    ],
    "sg:website":"http://www.davisfirmllc.com",
    "wof:name":"Davis Law Firm, LLC",
    "wof:placetype":"venue"
},
  "geometry": {"coordinates":[-74.763115,40.21684],"type":"Point"}
}