{
  "type": "Feature",
  "properties": {
    "iso:country":"US",
    "sg:address":"203 Elm St",
    "sg:city":"Westfield",
    "sg:classifiers":[
        {
            "category":"Travel",
            "subcategory":"Travel Agent",
            "type":"Entertainment"
        }
    ],
    "sg:phone":"+1 908 789 5445",
    "sg:postcode":"07090",
    "sg:province":"NJ",
    "sg:tags":[
        "operator",
        "tour"
    ],
    "wof:name":"Trading Places International",
    "wof:placetype":"venue"
},
  "geometry": {"coordinates":[-74.352073,40.653764],"type":"Point"}
}