{
  "type": "Feature",
  "properties": {
    "iso:country":"US",
    "sg:address":"18 Ellis Rd",
    "sg:city":"Caldwell",
    "sg:classifiers":[
        {
            "category":"Banks & Credit Unions",
            "subcategory":"Bank",
            "type":"Services"
        }
    ],
    "sg:phone":"+1   ",
    "sg:postcode":"07006",
    "sg:province":"NJ",
    "sg:tags":[
        "mortgage"
    ],
    "wof:name":"Cendant Mortgage Corporation",
    "wof:placetype":"venue"
},
  "geometry": {"coordinates":[-74.30612499999999,40.833609],"type":"Point"}
}