{
  "type": "Feature",
  "properties": {
    "iso:country":"US",
    "sg:address":"1563 Parker Ave",
    "sg:city":"Fort Lee",
    "sg:classifiers":[
        {
            "category":"Health Services",
            "subcategory":"Doctor",
            "type":"Services"
        }
    ],
    "sg:phone":"+1   ",
    "sg:postcode":"07024",
    "sg:province":"NJ",
    "wof:name":"Cory Wanatick Dmb",
    "wof:placetype":"venue"
},
  "geometry": {"coordinates":[-73.968537,40.84864],"type":"Point"}
}