{
  "type": "Feature",
  "properties": {
    "iso:country":"US",
    "sg:address":"50 Whitehouse Ave",
    "sg:city":"Whitehouse Sta",
    "sg:classifiers":[
        {
            "category":"Recreation",
            "type":"Entertainment"
        }
    ],
    "sg:phone":"+1 908 534 8420",
    "sg:postcode":"08889",
    "sg:province":"NJ",
    "sg:tags":[
        "parks"
    ],
    "wof:name":"Readington Township Recreation",
    "wof:placetype":"venue"
},
  "geometry": {"coordinates":[-74.759129,40.614328],"type":"Point"}
}