{
  "type": "Feature",
  "properties": {
    "addr:full":"121 Railroad Ave Ridgefield Park NJ 07660",
    "addr:housenumber":"121",
    "addr:postcode":"07660",
    "addr:street":"Railroad Ave",
    "iso:country":"US",
    "sg:address":"121 Railroad Ave",
    "sg:city":"Ridgefield Park",
    "sg:classifiers":[
        {
            "category":"Building & Trades",
            "subcategory":"Locksmith",
            "type":"Services"
        }
    ],
    "sg:phone":"+1 201 403 9654",
    "sg:postcode":"07660",
    "sg:province":"NJ",
    "sg:tags":[
        "key"
    ],
    "wof:name":"121 Towing & Locksmith",
    "wof:placetype":"venue"
},
  "geometry": {"coordinates":[-74.03055000000001,40.863263],"type":"Point"}
}