{
  "type": "Feature",
  "properties": {
    "iso:country":"US",
    "sg:address":"1271 US Highway 22",
    "sg:city":"Lebanon",
    "sg:classifiers":[
        {
            "category":"Shopping",
            "subcategory":"Crafts & Fabrics",
            "type":"Retail Goods"
        }
    ],
    "sg:phone":"+1 908 236 7676",
    "sg:postcode":"08833",
    "sg:province":"NJ",
    "sg:tags":[
        "store"
    ],
    "sg:website":"www.buddingstarquilts.com",
    "wof:name":"Budding Star Quilts",
    "wof:placetype":"venue"
},
  "geometry": {"coordinates":[-74.830399,40.6437],"type":"Point"}
}