{
  "type": "Feature",
  "properties": {
    "addr:full":"105 Porchtown Rd Elmer NJ 08318",
    "addr:housenumber":"105",
    "addr:postcode":"08318",
    "addr:street":"Porchtown Rd",
    "iso:country":"US",
    "sg:address":"105 Porchtown Rd",
    "sg:city":"Elmer",
    "sg:classifiers":[
        {
            "category":"Wholesale",
            "subcategory":"Groceries",
            "type":"Manufacturing & Wholesale Goods"
        }
    ],
    "sg:phone":"+1 856 358 6493",
    "sg:postcode":"08318",
    "sg:province":"NJ",
    "sg:tags":[
        "sauce"
    ],
    "wof:name":"Cedar Run Farms LLC",
    "wof:placetype":"venue"
},
  "geometry": {"coordinates":[-75.094196,39.57731],"type":"Point"}
}