{
  "type": "Feature",
  "properties": {
    "addr:full":"240 Bacon Ave Trenton NJ 08610",
    "addr:housenumber":"240",
    "addr:postcode":"08610",
    "addr:street":"Bacon Ave",
    "iso:country":"US",
    "sg:address":"240 Bacon Ave",
    "sg:city":"Trenton",
    "sg:classifiers":[
        {
            "category":"Health Services",
            "subcategory":"Chiropractor",
            "type":"Services"
        }
    ],
    "sg:phone":"+1 609 530 9080",
    "sg:postcode":"08610",
    "sg:province":"NJ",
    "wof:name":"Orlando Fmly Chiropractic Ctr",
    "wof:placetype":"venue"
},
  "geometry": {"coordinates":[-74.71797100000001,40.211786],"type":"Point"}
}