{
  "type": "Feature",
  "properties": {
    "addr:full":"142 Ralph St Belleville NJ 07109",
    "addr:housenumber":"142",
    "addr:postcode":"07109",
    "addr:street":"Ralph St",
    "iso:country":"US",
    "sg:address":"142 Ralph St",
    "sg:city":"Belleville",
    "sg:classifiers":[
        {
            "category":"Retail",
            "subcategory":"Auto Repair",
            "type":"Services"
        }
    ],
    "sg:phone":"+1   ",
    "sg:postcode":"07109",
    "sg:province":"NJ",
    "sg:tags":[
        "general"
    ],
    "wof:name":"Hometown Autocare",
    "wof:placetype":"venue"
},
  "geometry": {"coordinates":[-74.147307,40.790489],"type":"Point"}
}