{
  "type": "Feature",
  "properties": {
    "iso:country":"US",
    "sg:address":"440 Westfield Ave E",
    "sg:city":"Roselle Park",
    "sg:classifiers":[
        {
            "category":"Manufacturing",
            "subcategory":"Signs",
            "type":"Manufacturing & Wholesale Goods"
        }
    ],
    "sg:phone":"+1 908 245 7993",
    "sg:postcode":"07204",
    "sg:province":"NJ",
    "sg:tags":[
        "mfg"
    ],
    "wof:name":"Sign-It Signs & Service",
    "wof:placetype":"venue"
},
  "geometry": {"coordinates":[-74.247191,40.663856],"type":"Point"}
}