{
  "type": "Feature",
  "properties": {
    "iso:country":"US",
    "sg:address":"5301 Black Horse Pike",
    "sg:city":"Turnersville",
    "sg:classifiers":[
        {
            "category":"Home & Garden",
            "subcategory":"Furniture",
            "type":"Retail Goods"
        }
    ],
    "sg:phone":"+1 856 228 7720",
    "sg:postcode":"08012",
    "sg:province":"NJ",
    "sg:tags":[
        "mattress"
    ],
    "wof:name":"Sleepy's The Mattress Pros",
    "wof:placetype":"venue"
},
  "geometry": {"coordinates":[-75.04710300000001,39.756016],"type":"Point"}
}