{
  "type": "Feature",
  "properties": {
    "iso:country":"US",
    "sg:address":"63 Woodland Ave",
    "sg:city":"Westwood",
    "sg:classifiers":[
        {
            "category":"Professional",
            "type":"Services"
        }
    ],
    "sg:phone":"+1 201 664 3749",
    "sg:postcode":"07675",
    "sg:province":"NJ",
    "sg:tags":[
        "establishment"
    ],
    "wof:name":"Dial-A-Rosary-Padre Pio's",
    "wof:placetype":"venue"
},
  "geometry": {"coordinates":[-74.01406,40.981933],"type":"Point"}
}