{
  "type": "Feature",
  "properties": {
    "addr:full":"19 Old Mine Rd Lebanon NJ 08833",
    "addr:housenumber":"19",
    "addr:postcode":"08833",
    "addr:street":"Old Mine Rd",
    "iso:country":"US",
    "sg:address":"19 Old Mine Rd",
    "sg:city":"Lebanon",
    "sg:classifiers":[
        {
            "category":"Shopping",
            "subcategory":"Clothing, Apparel, & Fashions",
            "type":"Retail Goods"
        }
    ],
    "sg:phone":"+1   ",
    "sg:postcode":"08833",
    "sg:province":"NJ",
    "wof:name":"Friends For Fashion LLC",
    "wof:placetype":"venue"
},
  "geometry": {"coordinates":[-74.834799,40.68152],"type":"Point"}
}