{
  "type": "Feature",
  "properties": {
    "addr:full":"261 James St Ste 3F Morristown NJ 07960",
    "addr:housenumber":"261",
    "addr:postcode":"07960",
    "addr:street":"James St Ste 3F",
    "iso:country":"US",
    "sg:address":"261 James St Ste 3F",
    "sg:city":"Morristown",
    "sg:classifiers":[
        {
            "category":"Health Services",
            "subcategory":"Doctor",
            "type":"Services"
        }
    ],
    "sg:phone":"+1 973 538 0029",
    "sg:postcode":"07960",
    "sg:province":"NJ",
    "sg:tags":[
        "medicine",
        "sport",
        "orthopedist"
    ],
    "sg:website":"www.orthogrouponline.com",
    "wof:name":"Orthopedic Group PA the",
    "wof:placetype":"venue"
},
  "geometry": {"coordinates":[-74.48139999999999,40.770199],"type":"Point"}
}