{
  "type": "Feature",
  "properties": {
    "addr:full":"82 Moonachie Rd Moonachie NJ 07074",
    "addr:housenumber":"82",
    "addr:postcode":"07074",
    "addr:street":"Moonachie Rd",
    "iso:country":"US",
    "sg:address":"82 Moonachie Rd",
    "sg:city":"Moonachie",
    "sg:classifiers":[
        {
            "category":"Shopping",
            "subcategory":"Jewelry",
            "type":"Retail Goods"
        }
    ],
    "sg:phone":"+1 201 641 7622",
    "sg:postcode":"07074",
    "sg:province":"NJ",
    "sg:tags":[
        "jeweler"
    ],
    "wof:name":"Rita's",
    "wof:placetype":"venue"
},
  "geometry": {"coordinates":[-74.047461,40.840503],"type":"Point"}
}