{
  "type": "Feature",
  "properties": {
    "iso:country":"US",
    "sg:address":"6 Gate Ct",
    "sg:city":"Burlington",
    "sg:classifiers":[
        {
            "category":"Shopping",
            "subcategory":"Used Merchandise",
            "type":"Retail Goods"
        }
    ],
    "sg:phone":"+1   ",
    "sg:postcode":"08016",
    "sg:province":"NJ",
    "sg:tags":[
        "group"
    ],
    "wof:name":"All Jazz LLC",
    "wof:placetype":"venue"
},
  "geometry": {"coordinates":[-74.80953,40.082392],"type":"Point"}
}