{
  "type": "Feature",
  "properties": {
    "iso:country":"US",
    "sg:address":"65 Willowbrook Blvd",
    "sg:city":"Wayne",
    "sg:classifiers":[
        {
            "category":"Insurance",
            "subcategory":"Life Insurance",
            "type":"Services"
        }
    ],
    "sg:phone":"+1   ",
    "sg:postcode":"07470",
    "sg:province":"NJ",
    "sg:tags":[
        "agency"
    ],
    "wof:name":"Guardian Life Insur Co of Amer",
    "wof:placetype":"venue"
},
  "geometry": {"coordinates":[-74.250742,40.888609],"type":"Point"}
}