{
  "type": "Feature",
  "properties": {
    "addr:full":"10 Anderson Rd Bernardsville NJ 07924",
    "addr:housenumber":"10",
    "addr:postcode":"07924",
    "addr:street":"Anderson Rd",
    "iso:country":"US",
    "sg:address":"10 Anderson Rd",
    "sg:city":"Bernardsville",
    "sg:classifiers":[
        {
            "category":"Health Services",
            "subcategory":"Chiropractor",
            "type":"Services"
        }
    ],
    "sg:phone":"+1 908 766 3943",
    "sg:postcode":"07924",
    "sg:province":"NJ",
    "wof:name":"Mastrobattista Chiropractic",
    "wof:placetype":"venue"
},
  "geometry": {"coordinates":[-74.56950500000001,40.71963],"type":"Point"}
}