{
  "type": "Feature",
  "properties": {
    "iso:country":"US",
    "sg:address":"387 Ridge St",
    "sg:city":"Newark",
    "sg:classifiers":[
        {
            "category":"Social Services",
            "type":"Services"
        }
    ],
    "sg:phone":"+1 973 497 9978",
    "sg:postcode":"07104",
    "sg:province":"NJ",
    "sg:tags":[
        "organization",
        "welfare"
    ],
    "wof:name":"Devereaux Foundation",
    "wof:placetype":"venue"
},
  "geometry": {"coordinates":[-74.173345,40.764846],"type":"Point"}
}