{
  "type": "Feature",
  "properties": {
    "iso:country":"US",
    "sg:address":"91 New England Ave",
    "sg:city":"Piscataway",
    "sg:classifiers":[
        {
            "category":"Wholesale",
            "subcategory":"Furniture",
            "type":"Manufacturing & Wholesale Goods"
        }
    ],
    "sg:phone":"+1 732 562 0119",
    "sg:postcode":"08854",
    "sg:province":"NJ",
    "wof:name":"Coaster Co Of America Inc",
    "wof:placetype":"venue"
},
  "geometry": {"coordinates":[-74.470152,40.554651],"type":"Point"}
}