{
  "type": "Feature",
  "properties": {
    "addr:full":"2000 Rt 38 Cherry Hill NJ 08002",
    "addr:housenumber":"2000",
    "addr:postcode":"08002",
    "addr:street":"Rt 38",
    "iso:country":"US",
    "sg:address":"2000 Rt 38",
    "sg:city":"Cherry Hill",
    "sg:classifiers":[
        {
            "category":"Shopping",
            "subcategory":"Clothing, Apparel, & Fashions",
            "type":"Retail Goods"
        },
        {
            "category":"Shopping",
            "subcategory":"Bridal",
            "type":"Retail Goods"
        }
    ],
    "sg:postcode":"08002",
    "sg:province":"NJ",
    "sg:tags":[
        "clothing",
        "women's"
    ],
    "sg:website":"www.jcrew.com",
    "wof:name":"J. Crew",
    "wof:placetype":"venue"
},
  "geometry": {"coordinates":[-75.025747,39.940745],"type":"Point"}
}