{
  "type": "Feature",
  "properties": {
    "addr:full":"560 Morris Ave Summit NJ 07901",
    "addr:housenumber":"560",
    "addr:postcode":"07901",
    "addr:street":"Morris Ave",
    "iso:country":"US",
    "sg:address":"560 Morris Ave",
    "sg:city":"Summit",
    "sg:classifiers":[
        {
            "category":"Health Services",
            "subcategory":"Clinic",
            "type":"Services"
        }
    ],
    "sg:phone":"+1 908 598 7800",
    "sg:postcode":"07901",
    "sg:province":"NJ",
    "wof:name":"Novartis Consumer Health Inc",
    "wof:placetype":"venue"
},
  "geometry": {"coordinates":[-74.376295,40.728546],"type":"Point"}
}