{
  "type": "Feature",
  "properties": {
    "iso:country":"US",
    "sg:address":"62 Broadman Pkwy",
    "sg:city":"Jersey City",
    "sg:classifiers":[
        {
            "category":"Personal",
            "subcategory":"Beauty Salon",
            "type":"Services"
        }
    ],
    "sg:phone":"+1 201 798 6444",
    "sg:postcode":"07305",
    "sg:province":"NJ",
    "wof:name":"Carmen Salon & Spa",
    "wof:placetype":"venue"
},
  "geometry": {"coordinates":[-74.08789400000001,40.712553],"type":"Point"}
}