{
  "type": "Feature",
  "properties": {
    "iso:country":"US",
    "sg:address":"155 Ridge Rd",
    "sg:city":"North Arlington",
    "sg:classifiers":[
        {
            "category":"Food & Beverages",
            "subcategory":"Groceries & Convenience Stores",
            "type":"Retail Goods"
        }
    ],
    "sg:phone":"+1 201 246 7766",
    "sg:postcode":"07031",
    "sg:province":"NJ",
    "wof:name":"Stonehill Market Corp",
    "wof:placetype":"venue"
},
  "geometry": {"coordinates":[-74.134321,40.787129],"type":"Point"}
}