{
  "type": "Feature",
  "properties": {
    "addr:full":"18 Commerce Rd Fairfield NJ 07004",
    "addr:housenumber":"18",
    "addr:postcode":"07004",
    "addr:street":"Commerce Rd",
    "iso:country":"US",
    "sg:address":"18 Commerce Rd",
    "sg:city":"Fairfield",
    "sg:classifiers":[
        {
            "category":"Building & Trades",
            "subcategory":"Locksmith",
            "type":"Services"
        }
    ],
    "sg:phone":"+1 888 458 8637",
    "sg:postcode":"07004",
    "sg:province":"NJ",
    "sg:tags":[
        "key"
    ],
    "wof:name":"AAA Emergency Locksmith",
    "wof:placetype":"venue"
},
  "geometry": {"coordinates":[-74.318011,40.871957],"type":"Point"}
}