{
  "type": "Feature",
  "properties": {
    "addr:full":"1608 Media Rd Cherry Hill NJ 08002",
    "addr:housenumber":"1608",
    "addr:postcode":"08002",
    "addr:street":"Media Rd",
    "iso:country":"US",
    "sg:address":"1608 Media Rd",
    "sg:city":"Cherry Hill",
    "sg:classifiers":[
        {
            "category":"Building & Trades",
            "subcategory":"Construction",
            "type":"Services"
        }
    ],
    "sg:phone":"+1 856 665 1131",
    "sg:postcode":"08002",
    "sg:province":"NJ",
    "sg:tags":[
        "hanging",
        "contractor"
    ],
    "wof:name":"Ahern Painting",
    "wof:placetype":"venue"
},
  "geometry": {"coordinates":[-75.01872899999999,39.951473],"type":"Point"}
}