{
  "type": "Feature",
  "properties": {
    "addr:full":"115 Locust Ave Wallington NJ 07057",
    "addr:housenumber":"115",
    "addr:postcode":"07057",
    "addr:street":"Locust Ave",
    "iso:country":"US",
    "sg:address":"115 Locust Ave",
    "sg:city":"Wallington",
    "sg:classifiers":[
        {
            "category":"Retail",
            "subcategory":"Animal Services",
            "type":"Services"
        }
    ],
    "sg:phone":"+1 973 458 0707",
    "sg:postcode":"07057",
    "sg:province":"NJ",
    "sg:tags":[
        "pet",
        "farm",
        "sitting",
        "boarding/pet",
        "supply"
    ],
    "sg:website":"www.absolutelydogz.com",
    "wof:name":"Animal Feeds & Needs",
    "wof:placetype":"venue"
},
  "geometry": {"coordinates":[-74.110603,40.853699],"type":"Point"}
}