{
  "type": "Feature",
  "properties": {
    "addr:full":"8 Empire Blvd Moonachie NJ 07074",
    "addr:housenumber":"8",
    "addr:postcode":"07074",
    "addr:street":"Empire Blvd",
    "iso:country":"US",
    "sg:address":"8 Empire Blvd",
    "sg:city":"Moonachie",
    "sg:classifiers":[
        {
            "category":"Building & Trades",
            "subcategory":"Locksmith",
            "type":"Services"
        }
    ],
    "sg:phone":"+1 888 523 5269",
    "sg:postcode":"07074",
    "sg:province":"NJ",
    "sg:tags":[
        "key"
    ],
    "wof:name":"Emergency 24 Hour 7 Day Locksmith",
    "wof:placetype":"venue"
},
  "geometry": {"coordinates":[-74.047634,40.83264],"type":"Point"}
}