{
  "type": "Feature",
  "properties": {
    "addr:full":"215 North Ave E Westfield NJ 07090",
    "addr:housenumber":"215",
    "addr:postcode":"07090",
    "addr:street":"North Ave E",
    "iso:country":"US",
    "sg:address":"215 North Ave E",
    "sg:city":"Westfield",
    "sg:classifiers":[
        {
            "category":"Personal",
            "type":"Services"
        }
    ],
    "sg:phone":"+1 908 233 9198",
    "sg:postcode":"07090",
    "sg:province":"NJ",
    "sg:tags":[
        "consultant",
        "program",
        "health",
        "fitness"
    ],
    "wof:name":"Rowdell's Fitness",
    "wof:placetype":"venue"
},
  "geometry": {"coordinates":[-74.343605,40.650822],"type":"Point"}
}