{
  "type": "Feature",
  "properties": {
    "addr:full":"6109 Bergenline Pl West New York NJ 07093",
    "addr:housenumber":"6109",
    "addr:postcode":"07093",
    "addr:street":"Bergenline Pl West",
    "iso:country":"US",
    "sg:address":"6109 Bergenline Pl",
    "sg:city":"West New York",
    "sg:classifiers":[
        {
            "category":"Shopping",
            "subcategory":"Computers & Home Electronics",
            "type":"Retail Goods"
        }
    ],
    "sg:phone":"+1 201 854 0812",
    "sg:postcode":"07093",
    "sg:province":"NJ",
    "sg:tags":[
        "equipment",
        "electronic",
        "supply"
    ],
    "wof:name":"New Discovery Electronics LLC",
    "wof:placetype":"venue"
},
  "geometry": {"coordinates":[-74.014696,40.791151],"type":"Point"}
}