{
  "type": "Feature",
  "properties": {
    "iso:country":"US",
    "sg:address":"145 Lambertville Hq Rd",
    "sg:city":"Stockton",
    "sg:classifiers":[
        {
            "category":"Communications",
            "subcategory":"Film & Video Production",
            "type":"Services"
        }
    ],
    "sg:phone":"+1   ",
    "sg:postcode":"08559",
    "sg:province":"NJ",
    "sg:tags":[
        "motion",
        "picture"
    ],
    "wof:name":"Jcm Productions Inc",
    "wof:placetype":"venue"
},
  "geometry": {"coordinates":[-74.934408,40.413241],"type":"Point"}
}