{
  "type": "Feature",
  "properties": {
    "iso:country":"US",
    "sg:address":"295 Princeton Ave",
    "sg:city":"Bayville",
    "sg:classifiers":[
        {
            "category":"Retail",
            "subcategory":"Car Wash",
            "type":"Services"
        }
    ],
    "sg:phone":"+1 732 269 6134",
    "sg:postcode":"08721",
    "sg:province":"NJ",
    "sg:tags":[
        "automobile",
        "detail",
        "clean"
    ],
    "wof:name":"Car Brite Mobile Auto Detail",
    "wof:placetype":"venue"
},
  "geometry": {"coordinates":[-74.175691,39.901957],"type":"Point"}
}