{
  "type": "Feature",
  "properties": {
    "iso:country":"US",
    "sg:address":"5 Sugarmaple Ln",
    "sg:city":"Sicklerville",
    "sg:classifiers":[
        {
            "category":"Shopping",
            "subcategory":"Gifts & Souvenirs",
            "type":"Retail Goods"
        }
    ],
    "sg:phone":"+1   ",
    "sg:postcode":"08081",
    "sg:province":"NJ",
    "wof:name":"Tara Treasures",
    "wof:placetype":"venue"
},
  "geometry": {"coordinates":[-75.00131399999999,39.73475],"type":"Point"}
}