{
  "type": "Feature",
  "properties": {
    "addr:full":"391 Bogert Rd River Edge NJ 07661",
    "addr:housenumber":"391",
    "addr:postcode":"07661",
    "addr:street":"Bogert Rd",
    "iso:country":"US",
    "sg:address":"391 Bogert Rd",
    "sg:city":"River Edge",
    "sg:classifiers":[
        {
            "category":"Health Services",
            "subcategory":"Doctor",
            "type":"Services"
        }
    ],
    "sg:phone":"+1 201 599 2828",
    "sg:postcode":"07661",
    "sg:province":"NJ",
    "sg:tags":[
        "medical"
    ],
    "wof:name":"Andrew J Tashjian MD",
    "wof:placetype":"venue"
},
  "geometry": {"coordinates":[-74.036845,40.920216],"type":"Point"}
}