{
  "type": "Feature",
  "properties": {
    "iso:country":"US",
    "sg:address":"144 Gates Ave",
    "sg:city":"Montclair",
    "sg:classifiers":[
        {
            "category":"Professional",
            "subcategory":"Accounting & Tax Preparation",
            "type":"Services"
        }
    ],
    "sg:phone":"+1 973 746 7255",
    "sg:postcode":"07042",
    "sg:province":"NJ",
    "sg:tags":[
        "accountant"
    ],
    "wof:name":"Haynesworth Andrew Jr CPA",
    "wof:placetype":"venue"
},
  "geometry": {"coordinates":[-74.224403,40.8074],"type":"Point"}
}