{
  "type": "Feature",
  "properties": {
    "iso:country":"US",
    "sg:address":"160 Circle Dr N",
    "sg:city":"Piscataway",
    "sg:classifiers":[
        {
            "category":"Freight",
            "type":"Transportation"
        }
    ],
    "sg:phone":"+1 732 748 7222",
    "sg:postcode":"08854",
    "sg:province":"NJ",
    "sg:tags":[
        "general"
    ],
    "wof:name":"Hilton",
    "wof:placetype":"venue"
},
  "geometry": {"coordinates":[-74.47945199999999,40.55911],"type":"Point"}
}