{
  "type": "Feature",
  "properties": {
    "iso:country":"US",
    "sg:address":"602 Evesham Ave E",
    "sg:city":"Magnolia",
    "sg:classifiers":[
        {
            "category":"Organizations",
            "subcategory":"Religious Organization",
            "type":"Services"
        }
    ],
    "sg:phone":"+1   ",
    "sg:postcode":"08049",
    "sg:province":"NJ",
    "wof:name":"Mt Olive Baptist Church",
    "wof:placetype":"venue"
},
  "geometry": {"coordinates":[-75.02216799999999,39.857644],"type":"Point"}
}