{
  "type": "Feature",
  "properties": {
    "iso:country":"US",
    "sg:address":"50 Clearview Rd",
    "sg:city":"Edison",
    "sg:classifiers":[
        {
            "category":"Local Transit",
            "type":"Transportation"
        }
    ],
    "sg:phone":"+1 732 225 1145",
    "sg:postcode":"08837",
    "sg:province":"NJ",
    "sg:tags":[
        "bus",
        "line"
    ],
    "wof:name":"Pleasant Company",
    "wof:placetype":"venue"
},
  "geometry": {"coordinates":[-74.33001299999999,40.522912],"type":"Point"}
}