{
  "type": "Feature",
  "properties": {
    "iso:country":"US",
    "sg:address":"29 Lexington Ave",
    "sg:city":"Trenton",
    "sg:classifiers":[
        {
            "category":"Home & Garden",
            "subcategory":"Building Materials",
            "type":"Retail Goods"
        }
    ],
    "sg:phone":"+1 609 882 4900",
    "sg:postcode":"08618",
    "sg:province":"NJ",
    "sg:tags":[
        "door"
    ],
    "wof:name":"Wherry Doors & Hardware Co",
    "wof:placetype":"venue"
},
  "geometry": {"coordinates":[-74.792022,40.250858],"type":"Point"}
}