{
  "type": "Feature",
  "properties": {
    "addr:full":"1 Corporate Way Mine Hill NJ 07803",
    "addr:housenumber":"1",
    "addr:postcode":"07803",
    "addr:street":"Corporate Way",
    "iso:country":"US",
    "sg:address":"1 Corporate Way",
    "sg:city":"Mine Hill",
    "sg:classifiers":[
        {
            "category":"Retail",
            "subcategory":"Auto Rental",
            "type":"Services"
        }
    ],
    "sg:phone":"+1 973 361 0250",
    "sg:postcode":"07803",
    "sg:province":"NJ",
    "sg:tags":[
        "renting",
        "automobile"
    ],
    "wof:name":"Avis Rent A Car",
    "wof:placetype":"venue"
},
  "geometry": {"coordinates":[-74.593924,40.879622],"type":"Point"}
}