{
  "type": "Feature",
  "properties": {
    "addr:full":"52 Deforest Ave Summit NJ 07901",
    "addr:housenumber":"52",
    "addr:postcode":"07901",
    "addr:street":"Deforest Ave",
    "iso:country":"US",
    "sg:address":"52 Deforest Ave",
    "sg:city":"Summit",
    "sg:classifiers":[
        {
            "category":"Health Services",
            "subcategory":"Doctor",
            "type":"Services"
        }
    ],
    "sg:phone":"+1 908 273 3873",
    "sg:postcode":"07901",
    "sg:province":"NJ",
    "wof:name":"Jeffrey Plancey DMD",
    "wof:placetype":"venue"
},
  "geometry": {"coordinates":[-74.361092,40.718751],"type":"Point"}
}