{
  "type": "Feature",
  "properties": {
    "iso:country":"US",
    "sg:address":"235 Cedar Ln",
    "sg:city":"River Vale",
    "sg:classifiers":[
        {
            "category":"Professional",
            "subcategory":"Art Services",
            "type":"Services"
        }
    ],
    "sg:phone":"+1 201 368 2744",
    "sg:postcode":"07675",
    "sg:province":"NJ",
    "sg:tags":[
        "photographer"
    ],
    "wof:name":"Wolf Productions",
    "wof:placetype":"venue"
},
  "geometry": {"coordinates":[-74.01995700000001,40.995215],"type":"Point"}
}