{
  "type": "Feature",
  "properties": {
    "addr:full":"447 Union Ave Paterson NJ 07522",
    "addr:housenumber":"447",
    "addr:postcode":"07522",
    "addr:street":"Union Ave",
    "iso:country":"US",
    "sg:address":"447 Union Ave",
    "sg:city":"Paterson",
    "sg:classifiers":[
        {
            "category":"Health Services",
            "subcategory":"Optometrist",
            "type":"Services"
        }
    ],
    "sg:phone":"+1 973 942 4221",
    "sg:postcode":"07522",
    "sg:province":"NJ",
    "wof:name":"Ehrenworth Steven L OD",
    "wof:placetype":"venue"
},
  "geometry": {"coordinates":[-74.18422099999999,40.922058],"type":"Point"}
}