{
  "type": "Feature",
  "properties": {
    "addr:full":"62 Hillairy Ave Morristown NJ 07960",
    "addr:housenumber":"62",
    "addr:postcode":"07960",
    "addr:street":"Hillairy Ave",
    "iso:country":"US",
    "sg:address":"62 Hillairy Ave",
    "sg:city":"Morristown",
    "sg:classifiers":[
        {
            "category":"Professional",
            "type":"Services"
        }
    ],
    "sg:phone":"+1   ",
    "sg:postcode":"07960",
    "sg:province":"NJ",
    "wof:name":"Eric G Brown",
    "wof:placetype":"venue"
},
  "geometry": {"coordinates":[-74.477113,40.810755],"type":"Point"}
}