{
  "type": "Feature",
  "properties": {
    "iso:country":"US",
    "sg:address":"256 Columbia Tpke",
    "sg:city":"Florham Park",
    "sg:classifiers":[
        {
            "category":"Retail",
            "subcategory":"Repair Shop",
            "type":"Services"
        }
    ],
    "sg:phone":"+1 973 360 1700",
    "sg:postcode":"07932",
    "sg:province":"NJ",
    "sg:tags":[
        "equipment",
        "telephone",
        "system"
    ],
    "wof:name":"Novacom Telephone Co",
    "wof:placetype":"venue"
},
  "geometry": {"coordinates":[-74.404185,40.789803],"type":"Point"}
}