{
  "type": "Feature",
  "properties": {
    "iso:country":"US",
    "sg:address":"740 Brewers Bridge Rd",
    "sg:city":"Jackson",
    "sg:classifiers":[
        {
            "category":"Food & Beverages",
            "subcategory":"Groceries & Convenience Stores",
            "type":"Retail Goods"
        }
    ],
    "sg:phone":"+1 732 730 8800",
    "sg:postcode":"08527",
    "sg:province":"NJ",
    "sg:tags":[
        "market"
    ],
    "wof:name":"Krauzers Food Store",
    "wof:placetype":"venue"
},
  "geometry": {"coordinates":[-74.25942499999999,40.122401],"type":"Point"}
}