{
  "type": "Feature",
  "properties": {
    "iso:country":"US",
    "sg:address":"338 Chestnut St Ste 1",
    "sg:city":"Passaic",
    "sg:classifiers":[
        {
            "category":"Health Services",
            "subcategory":"Doctor",
            "type":"Services"
        }
    ],
    "sg:phone":"+1 973 471 9494",
    "sg:postcode":"07055",
    "sg:province":"NJ",
    "wof:name":"Demuro Paul DO",
    "wof:placetype":"venue"
},
  "geometry": {"coordinates":[-74.13526299999999,40.864976],"type":"Point"}
}