{
  "type": "Feature",
  "properties": {
    "iso:country":"US",
    "sg:address":"77 Colfax Rd",
    "sg:city":"Wayne",
    "sg:classifiers":[
        {
            "category":"Professional",
            "subcategory":"Business Services",
            "type":"Services"
        }
    ],
    "sg:phone":"+1   ",
    "sg:postcode":"07470",
    "sg:province":"NJ",
    "wof:name":"Robert Mirrer",
    "wof:placetype":"venue"
},
  "geometry": {"coordinates":[-74.266496,40.981568],"type":"Point"}
}