{
  "type": "Feature",
  "properties": {
    "iso:country":"US",
    "sg:address":"585 Newark Ave",
    "sg:city":"Elizabeth",
    "sg:classifiers":[
        {
            "category":"Arts & Performance",
            "subcategory":"Theater",
            "type":"Entertainment"
        }
    ],
    "sg:phone":"+1 908 436 3779",
    "sg:postcode":"07208",
    "sg:province":"NJ",
    "wof:name":"Three2rockaway Entertainment",
    "wof:placetype":"venue"
},
  "geometry": {"coordinates":[-74.21280299999999,40.675387],"type":"Point"}
}