{
  "type": "Feature",
  "properties": {
    "addr:full":"727 Joralemon St Belleville NJ 07109",
    "addr:housenumber":"727",
    "addr:postcode":"07109",
    "addr:street":"Joralemon St",
    "iso:country":"US",
    "sg:address":"727 Joralemon St",
    "sg:city":"Belleville",
    "sg:classifiers":[
        {
            "category":"Professional",
            "subcategory":"Management & Consulting",
            "type":"Services"
        }
    ],
    "sg:phone":"+1 973 751 0960",
    "sg:postcode":"07109",
    "sg:province":"NJ",
    "sg:tags":[
        "consultant",
        "educational",
        "business"
    ],
    "wof:name":"Preserving Americas Four Free",
    "wof:placetype":"venue"
},
  "geometry": {"coordinates":[-74.17182699999999,40.803929],"type":"Point"}
}