{
  "type": "Feature",
  "properties": {
    "iso:country":"US",
    "sg:address":"226 Main St",
    "sg:city":"Butler",
    "sg:classifiers":[
        {
            "category":"Shopping",
            "subcategory":"Clothing, Apparel, & Fashions",
            "type":"Retail Goods"
        },
        {
            "category":"Retail",
            "subcategory":"Laundry & Dry Cleaning",
            "type":"Services"
        },
        {
            "category":"Building & Trades",
            "subcategory":"Equipment Rental",
            "type":"Services"
        }
    ],
    "sg:phone":"+1 973 335 1488",
    "sg:postcode":"07405",
    "sg:province":"NJ",
    "sg:tags":[
        "yard",
        "costumes-renting",
        "store",
        "costume"
    ],
    "wof:name":"Costume Depot",
    "wof:placetype":"venue"
},
  "geometry": {"coordinates":[-74.34144499999999,41.003802],"type":"Point"}
}