{
  "type": "Feature",
  "properties": {
    "iso:country":"US",
    "sg:address":"7100 W Buckshutem Rd",
    "sg:city":"Millville",
    "sg:classifiers":[
        {
            "category":"Manufacturing",
            "subcategory":"Metals",
            "type":"Manufacturing & Wholesale Goods"
        }
    ],
    "sg:phone":"+1 856 327 0605",
    "sg:postcode":"08332",
    "sg:province":"NJ",
    "sg:tags":[
        "carpentry",
        "structural",
        "work",
        "fabrication",
        "contractor"
    ],
    "wof:name":"Ronald Kruysman Co",
    "wof:placetype":"venue"
},
  "geometry": {"coordinates":[-75.09042700000001,39.367741],"type":"Point"}
}