{
  "type": "Feature",
  "properties": {
    "iso:country":"US",
    "sg:address":"601 Lees Ave",
    "sg:city":"Collingswood",
    "sg:classifiers":[
        {
            "category":"Manufacturing",
            "subcategory":"Apparel",
            "type":"Manufacturing & Wholesale Goods"
        }
    ],
    "sg:phone":"+1 856 858 0131",
    "sg:postcode":"08108",
    "sg:province":"NJ",
    "sg:tags":[
        "outerwear",
        "mfg"
    ],
    "wof:name":"Two Cherubs",
    "wof:placetype":"venue"
},
  "geometry": {"coordinates":[-75.069002,39.908108],"type":"Point"}
}