{
  "type": "Feature",
  "properties": {
    "addr:full":"41 Elm St Morristown NJ 07960",
    "addr:housenumber":"41",
    "addr:postcode":"07960",
    "addr:street":"Elm St",
    "iso:country":"US",
    "sg:address":"41 Elm St",
    "sg:city":"Morristown",
    "sg:classifiers":[
        {
            "category":"Health Services",
            "subcategory":"Doctor",
            "type":"Services"
        }
    ],
    "sg:phone":"+1 973 540 1311",
    "sg:postcode":"07960",
    "sg:province":"NJ",
    "sg:tags":[
        "surgeon",
        "oral"
    ],
    "wof:name":"Appelbaum Marc B DDS",
    "wof:placetype":"venue"
},
  "geometry": {"coordinates":[-74.474701,40.794498],"type":"Point"}
}