{
  "type": "Feature",
  "properties": {
    "iso:country":"US",
    "sg:address":"12 Gully Rd",
    "sg:city":"Neptune",
    "sg:classifiers":[
        {
            "category":"Building & Trades",
            "subcategory":"Electrical",
            "type":"Services"
        }
    ],
    "sg:phone":"+1 732 922 5832",
    "sg:postcode":"07753",
    "sg:province":"NJ",
    "sg:tags":[
        "electrical",
        "contractor"
    ],
    "wof:name":"Berndt Dereck",
    "wof:placetype":"venue"
},
  "geometry": {"coordinates":[-74.08143,40.20702],"type":"Point"}
}