{
  "type": "Feature",
  "properties": {
    "iso:country":"US",
    "sg:address":"145 Co Rd 539",
    "sg:city":"Cream Ridge",
    "sg:classifiers":[
        {
            "category":"Manufacturing",
            "subcategory":"Food",
            "type":"Manufacturing & Wholesale Goods"
        }
    ],
    "sg:phone":"+1 609 259 9797",
    "sg:postcode":"08514",
    "sg:province":"NJ",
    "sg:tags":[
        "winery"
    ],
    "sg:website":"www.creamridgewinery.com",
    "wof:name":"Cream Ridge Winery",
    "wof:placetype":"venue"
},
  "geometry": {"coordinates":[-74.540694,40.149909],"type":"Point"}
}