{
  "type": "Feature",
  "properties": {
    "iso:country":"US",
    "sg:address":"58 Cold Indian Springs Rd",
    "sg:city":"Asbury Park",
    "sg:classifiers":[
        {
            "category":"Shopping",
            "subcategory":"Musical Instruments",
            "type":"Retail Goods"
        }
    ],
    "sg:phone":"+1   ",
    "sg:postcode":"07712",
    "sg:province":"NJ",
    "wof:name":"Mack Percussion",
    "wof:placetype":"venue"
},
  "geometry": {"coordinates":[-74.059444,40.246698],"type":"Point"}
}