{
  "type": "Feature",
  "properties": {
    "iso:country":"US",
    "sg:address":"68 Easton Ave",
    "sg:city":"New Brunswick",
    "sg:classifiers":[
        {
            "category":"Restaurant",
            "type":"Food & Drink"
        }
    ],
    "sg:menulink":"http://www.allmenus.com/nj/new-brunswick/20226-edo-japanese-restaurant/menu/",
    "sg:phone":"+1 732 514 0700",
    "sg:postcode":"08901",
    "sg:province":"NJ",
    "sg:tags":[
        "japanese",
        "asian"
    ],
    "wof:name":"Edo Japanese Restaurant",
    "wof:placetype":"venue"
},
  "geometry": {"coordinates":[-74.449574,40.498118],"type":"Point"}
}