{
  "type": "Feature",
  "properties": {
    "iso:country":"US",
    "sg:address":"71 4th Ave",
    "sg:city":"East Orange",
    "sg:classifiers":[
        {
            "category":"Banks & Credit Unions",
            "subcategory":"Investment Brokerage",
            "type":"Services"
        }
    ],
    "sg:phone":"+1 973 673 2892",
    "sg:postcode":"07017",
    "sg:province":"NJ",
    "sg:tags":[
        "advisory",
        "financial"
    ],
    "wof:name":"Mina Financial Svc",
    "wof:placetype":"venue"
},
  "geometry": {"coordinates":[-74.196658,40.765241],"type":"Point"}
}