{
  "type": "Feature",
  "properties": {
    "iso:country":"US",
    "sg:address":"901 E Linden Ave",
    "sg:city":"Linden",
    "sg:classifiers":[
        {
            "category":"Wholesale",
            "subcategory":"Construction Materials",
            "type":"Manufacturing & Wholesale Goods"
        }
    ],
    "sg:phone":"+1 908 406 1569",
    "sg:postcode":"07036",
    "sg:province":"NJ",
    "sg:tags":[
        "pallet",
        "skid"
    ],
    "wof:name":"Bless Pallets",
    "wof:placetype":"venue"
},
  "geometry": {"coordinates":[-74.244392,40.634086],"type":"Point"}
}