{
  "type": "Feature",
  "properties": {
    "addr:full":"214 Sykesville Rd Wrightstown NJ 08515",
    "addr:housenumber":"214",
    "addr:postcode":"08515",
    "addr:street":"Sykesville Rd",
    "iso:country":"US",
    "sg:address":"214 Sykesville Rd",
    "sg:city":"Wrightstown",
    "sg:classifiers":[
        {
            "category":"Wholesale",
            "subcategory":"Machinery & Supplies",
            "type":"Manufacturing & Wholesale Goods"
        }
    ],
    "sg:phone":"+1 609 324 9024",
    "sg:postcode":"08515",
    "sg:province":"NJ",
    "sg:tags":[
        "environmental",
        "screen",
        "mfg",
        "well",
        "equipment",
        "drilling"
    ],
    "wof:name":"Acqua Bella Mfg and Supply",
    "wof:placetype":"venue"
},
  "geometry": {"coordinates":[-74.62152,40.075491],"type":"Point"}
}