{
  "type": "Feature",
  "properties": {
    "addr:full":"8 N Elk Ave Dover NJ 07801",
    "addr:housenumber":"8",
    "addr:postcode":"07801",
    "addr:street":"N Elk Ave",
    "iso:country":"US",
    "sg:address":"8 N Elk Ave",
    "sg:city":"Dover",
    "sg:classifiers":[
        {
            "category":"Professional",
            "subcategory":"Business Services",
            "type":"Services"
        }
    ],
    "sg:phone":"+1 973 989 1166",
    "sg:postcode":"07801",
    "sg:province":"NJ",
    "wof:name":"Hartmark Enterprises",
    "wof:placetype":"venue"
},
  "geometry": {"coordinates":[-74.575023,40.886993],"type":"Point"}
}