{
  "type": "Feature",
  "properties": {
    "addr:full":"1630 Tilton Rd Northfield NJ 08225",
    "addr:housenumber":"1630",
    "addr:postcode":"08225",
    "addr:street":"Tilton Rd",
    "iso:country":"US",
    "sg:address":"1630 Tilton Rd",
    "sg:city":"Northfield",
    "sg:classifiers":[
        {
            "category":"Retail",
            "subcategory":"Laundry & Dry Cleaning",
            "type":"Services"
        }
    ],
    "sg:phone":"+1   ",
    "sg:postcode":"08225",
    "sg:province":"NJ",
    "wof:name":"Hattbit Cleaners",
    "wof:placetype":"venue"
},
  "geometry": {"coordinates":[-74.552612,39.368701],"type":"Point"}
}