{
  "type": "Feature",
  "properties": {
    "iso:country":"US",
    "sg:address":"666 S Springfield Ave",
    "sg:city":"Springfield",
    "sg:classifiers":[
        {
            "category":"Education",
            "subcategory":"School",
            "type":"Public Place"
        }
    ],
    "sg:phone":"+1   ",
    "sg:postcode":"07081",
    "sg:province":"NJ",
    "wof:name":"Thelma L Sndmier Elmntary Schl",
    "wof:placetype":"venue"
},
  "geometry": {"coordinates":[-74.323292,40.690846],"type":"Point"}
}