{
  "type": "Feature",
  "properties": {
    "iso:country":"US",
    "sg:address":"448 Roberts Ave",
    "sg:city":"Bellmawr",
    "sg:classifiers":[
        {
            "category":"Building & Trades",
            "subcategory":"Construction",
            "type":"Services"
        }
    ],
    "sg:phone":"+1 856 933 2030",
    "sg:postcode":"08031",
    "sg:province":"NJ",
    "sg:tags":[
        "house",
        "contractor"
    ],
    "wof:name":"Crosswind Construction",
    "wof:placetype":"venue"
},
  "geometry": {"coordinates":[-75.06427600000001,39.862698],"type":"Point"}
}