{
  "type": "Feature",
  "properties": {
    "addr:full":"142 S 9th St Newark NJ 07107",
    "addr:housenumber":"142",
    "addr:postcode":"07107",
    "addr:street":"S 9Th St",
    "iso:country":"US",
    "sg:address":"142 S 9th St",
    "sg:city":"Newark",
    "sg:classifiers":[
        {
            "category":"Manufacturing",
            "subcategory":"Printing",
            "type":"Manufacturing & Wholesale Goods"
        }
    ],
    "sg:phone":"+1 973 623 0819",
    "sg:postcode":"07107",
    "sg:province":"NJ",
    "sg:tags":[
        "printer",
        "offset"
    ],
    "wof:name":"Printers Elite",
    "wof:placetype":"venue"
},
  "geometry": {"coordinates":[-74.19577,40.748574],"type":"Point"}
}