{
  "type": "Feature",
  "properties": {
    "addr:full":"18 W Prospect St Waldwick NJ 07463",
    "addr:housenumber":"18",
    "addr:postcode":"07463",
    "addr:street":"W Prospect St",
    "iso:country":"US",
    "sg:address":"18 W Prospect St",
    "sg:city":"Waldwick",
    "sg:classifiers":[
        {
            "category":"Bars & Pubs",
            "type":"Food & Drink"
        }
    ],
    "sg:phone":"+1 201 652 9819",
    "sg:postcode":"07463",
    "sg:province":"NJ",
    "wof:name":"Amster",
    "wof:placetype":"venue"
},
  "geometry": {"coordinates":[-74.12141200000001,41.011354],"type":"Point"}
}