{
  "type": "Feature",
  "properties": {
    "iso:country":"US",
    "sg:address":"148 E Main St",
    "sg:city":"Rockaway",
    "sg:classifiers":[
        {
            "category":"Personal",
            "type":"Services"
        }
    ],
    "sg:phone":"+1   ",
    "sg:postcode":"07866",
    "sg:province":"NJ",
    "wof:name":"Psychic Shop",
    "wof:placetype":"venue"
},
  "geometry": {"coordinates":[-74.505747,40.897555],"type":"Point"}
}