{
  "type": "Feature",
  "properties": {
    "iso:country":"US",
    "sg:address":"10 Charles St",
    "sg:city":"New Brunswick",
    "sg:classifiers":[
        {
            "category":"Food & Beverages",
            "subcategory":"Bakery",
            "type":"Retail Goods"
        }
    ],
    "sg:phone":"+1 732 247 2095",
    "sg:postcode":"08901",
    "sg:province":"NJ",
    "sg:tags":[
        "baker"
    ],
    "wof:name":"Scala Pastry Shop",
    "wof:placetype":"venue"
},
  "geometry": {"coordinates":[-74.46107600000001,40.479571],"type":"Point"}
}