{
  "type": "Feature",
  "properties": {
    "iso:country":"US",
    "sg:address":"32 Marcshire Dr",
    "sg:city":"Middletown",
    "sg:classifiers":[
        {
            "category":"Professional",
            "subcategory":"Management & Consulting",
            "type":"Services"
        }
    ],
    "sg:phone":"+1   ",
    "sg:postcode":"07748",
    "sg:province":"NJ",
    "wof:name":"Navesink Logistics Inc",
    "wof:placetype":"venue"
},
  "geometry": {"coordinates":[-74.123434,40.362049],"type":"Point"}
}