{
  "type": "Feature",
  "properties": {
    "addr:full":"84 Orange Rd Montclair NJ 07042",
    "addr:housenumber":"84",
    "addr:postcode":"07042",
    "addr:street":"Orange Rd",
    "iso:country":"US",
    "sg:address":"84 Orange Rd",
    "sg:city":"Montclair",
    "sg:classifiers":[
        {
            "category":"Organizations",
            "subcategory":"Religious Organization",
            "type":"Services"
        }
    ],
    "sg:phone":"+1 973 746 8417",
    "sg:postcode":"07042",
    "sg:province":"NJ",
    "wof:name":"Montclair Unity Church",
    "wof:placetype":"venue"
},
  "geometry": {"coordinates":[-74.22286099999999,40.812692],"type":"Point"}
}