{
  "type": "Feature",
  "properties": {
    "iso:country":"US",
    "sg:address":"1720 Old Trenton Rd",
    "sg:city":"Princeton Junction",
    "sg:classifiers":[
        {
            "category":"Food & Beverages",
            "subcategory":"Groceries & Convenience Stores",
            "type":"Retail Goods"
        }
    ],
    "sg:phone":"+1   ",
    "sg:postcode":"08550",
    "sg:province":"NJ",
    "sg:tags":[
        "delicatessen"
    ],
    "wof:name":"Village Pantry Deli",
    "wof:placetype":"venue"
},
  "geometry": {"coordinates":[-74.60918100000001,40.261992],"type":"Point"}
}