{
  "type": "Feature",
  "properties": {
    "addr:full":"57 Rock Hill Rd Old Bridge NJ 08857",
    "addr:housenumber":"57",
    "addr:postcode":"08857",
    "addr:street":"Rock Hill Rd",
    "iso:country":"US",
    "sg:address":"57 Rock Hill Rd",
    "sg:city":"Old Bridge",
    "sg:classifiers":[
        {
            "category":"Communications",
            "subcategory":"Film & Video Production",
            "type":"Services"
        }
    ],
    "sg:phone":"+1 732 591 5400",
    "sg:postcode":"08857",
    "sg:province":"NJ",
    "sg:tags":[
        "graphic",
        "graphics"
    ],
    "wof:name":"Corbitt Design Inc",
    "wof:placetype":"venue"
},
  "geometry": {"coordinates":[-74.301165,40.404911],"type":"Point"}
}