{
  "type": "Feature",
  "properties": {
    "addr:full":"79 E Milton Ave Rahway NJ 07065",
    "addr:housenumber":"79",
    "addr:postcode":"07065",
    "addr:street":"E Milton Ave",
    "iso:country":"US",
    "sg:address":"79 E Milton Ave",
    "sg:city":"Rahway",
    "sg:classifiers":[
        {
            "category":"Restaurant",
            "type":"Food & Drink"
        }
    ],
    "sg:phone":"+1   ",
    "sg:postcode":"07065",
    "sg:province":"NJ",
    "sg:tags":[
        "eating"
    ],
    "wof:name":"Michelinos Pizzeria",
    "wof:placetype":"venue"
},
  "geometry": {"coordinates":[-74.276044,40.605762],"type":"Point"}
}