{
  "type": "Feature",
  "properties": {
    "iso:country":"US",
    "sg:address":"1225 Westfield Ave",
    "sg:city":"Clark",
    "sg:classifiers":[
        {
            "category":"Building & Trades",
            "subcategory":"Plumbing",
            "type":"Services"
        }
    ],
    "sg:phone":"+1 732 382 4433",
    "sg:postcode":"07066",
    "sg:province":"NJ",
    "sg:tags":[
        "contractor"
    ],
    "wof:name":"American Specialty Plumbing Heating & Air",
    "wof:placetype":"venue"
},
  "geometry": {"coordinates":[-74.321297,40.626801],"type":"Point"}
}