{
  "type": "Feature",
  "properties": {
    "iso:country":"US",
    "sg:address":"525 Bloomfield Ave",
    "sg:city":"West Caldwell",
    "sg:classifiers":[
        {
            "category":"Real Estate",
            "subcategory":"Real Estate Agent",
            "type":"Services"
        }
    ],
    "sg:phone":"+1 973 226 0822",
    "sg:postcode":"07006",
    "sg:province":"NJ",
    "wof:name":"IRC Assoc",
    "wof:placetype":"venue"
},
  "geometry": {"coordinates":[-74.28617,40.84556],"type":"Point"}
}