{
  "type": "Feature",
  "properties": {
    "addr:full":"440 Rochelle Avenue Rochelle Park NJ 07662",
    "addr:housenumber":"440",
    "addr:postcode":"07662",
    "addr:street":"Rochelle Avenue",
    "iso:country":"US",
    "sg:address":"440 Rochelle Avenue",
    "sg:city":"Rochelle Park",
    "sg:classifiers":[
        {
            "category":"Coffee & Tea",
            "type":"Food & Drink"
        }
    ],
    "sg:phone":"+1 201 368 2050",
    "sg:postcode":"07662",
    "sg:province":"NJ",
    "sg:website":"www.dunkindonuts.com",
    "wof:name":"Dunkin Donuts",
    "wof:placetype":"venue"
},
  "geometry": {"coordinates":[-74.07300499999999,40.910026],"type":"Point"}
}