{
  "type": "Feature",
  "properties": {
    "iso:country":"US",
    "sg:address":"71 W Front St",
    "sg:city":"Keyport",
    "sg:classifiers":[
        {
            "category":"Government",
            "subcategory":"Office",
            "type":"Public Place"
        }
    ],
    "sg:phone":"+1 732 739 4658",
    "sg:postcode":"07735",
    "sg:province":"NJ",
    "sg:tags":[
        "city",
        "program",
        "health"
    ],
    "wof:name":"Keyport Board Of Health",
    "wof:placetype":"venue"
},
  "geometry": {"coordinates":[-74.205208,40.436398],"type":"Point"}
}