{
  "type": "Feature",
  "properties": {
    "addr:full":"557 Elizabeth Ave Elizabeth NJ 07206",
    "addr:housenumber":"557",
    "addr:postcode":"07206",
    "addr:street":"Elizabeth Ave",
    "iso:country":"US",
    "sg:address":"557 Elizabeth Ave",
    "sg:city":"Elizabeth",
    "sg:classifiers":[
        {
            "category":"Professional",
            "subcategory":"Computer Services",
            "type":"Services"
        }
    ],
    "sg:phone":"+1 908 353 3008",
    "sg:postcode":"07206",
    "sg:province":"NJ",
    "sg:tags":[
        "stereo",
        "installation"
    ],
    "wof:name":"Rodriguez Car & Audio Accesories",
    "wof:placetype":"venue"
},
  "geometry": {"coordinates":[-74.199799,40.655701],"type":"Point"}
}