{
  "type": "Feature",
  "properties": {
    "iso:country":"US",
    "sg:address":"142 State Rte 35",
    "sg:city":"Eatontown",
    "sg:classifiers":[
        {
            "category":"Health Services",
            "subcategory":"Doctor",
            "type":"Services"
        }
    ],
    "sg:phone":"+1 732 389 5004",
    "sg:postcode":"07724",
    "sg:province":"NJ",
    "sg:tags":[
        "physician",
        "surgeon",
        "medical"
    ],
    "wof:name":"Monmouth Gastroenterology LLC",
    "wof:placetype":"venue"
},
  "geometry": {"coordinates":[-74.051429,40.289289],"type":"Point"}
}