{
  "type": "Feature",
  "properties": {
    "iso:country":"US",
    "sg:address":"5 Summit Ave",
    "sg:city":"Hackensack",
    "sg:classifiers":[
        {
            "category":"Health Services",
            "subcategory":"Doctor",
            "type":"Services"
        }
    ],
    "sg:phone":"+1 201 343 9368",
    "sg:postcode":"07601",
    "sg:province":"NJ",
    "sg:tags":[
        "throat",
        "ear",
        "nose"
    ],
    "wof:name":"Lesserson Jonathan MD",
    "wof:placetype":"venue"
},
  "geometry": {"coordinates":[-74.059601,40.8843],"type":"Point"}
}