{
  "type": "Feature",
  "properties": {
    "iso:country":"US",
    "sg:address":"18 Columbia Tpke",
    "sg:city":"Florham Park",
    "sg:classifiers":[
        {
            "category":"Building & Trades",
            "subcategory":"Construction",
            "type":"Services"
        }
    ],
    "sg:phone":"+1 973 822 0050",
    "sg:postcode":"07932",
    "sg:province":"NJ",
    "sg:tags":[
        "contractor"
    ],
    "wof:name":"West Minster Communities",
    "wof:placetype":"venue"
},
  "geometry": {"coordinates":[-74.374442,40.781661],"type":"Point"}
}