{
  "type": "Feature",
  "properties": {
    "addr:full":"503 Raritan Ave Highland Park NJ 08904",
    "addr:housenumber":"503",
    "addr:postcode":"08904",
    "addr:street":"Raritan Ave",
    "iso:country":"US",
    "sg:address":"503 Raritan Ave",
    "sg:city":"Highland Park",
    "sg:classifiers":[
        {
            "category":"Health Services",
            "subcategory":"Podiatrist",
            "type":"Services"
        },
        {
            "category":"Health Services",
            "subcategory":"Doctor",
            "type":"Services"
        }
    ],
    "sg:phone":"+1 732 572 0020",
    "sg:postcode":"08904",
    "sg:province":"NJ",
    "sg:tags":[
        "medical"
    ],
    "wof:name":"Dribbon Steven M DPM",
    "wof:placetype":"venue"
},
  "geometry": {"coordinates":[-74.423383,40.500903],"type":"Point"}
}