{
  "type": "Feature",
  "properties": {
    "iso:country":"US",
    "sg:address":"341 S Fairview St",
    "sg:city":"Riverside",
    "sg:classifiers":[
        {
            "category":"Manufacturing",
            "subcategory":"Petroleum Products",
            "type":"Manufacturing & Wholesale Goods"
        }
    ],
    "sg:phone":"+1 856 461 4161",
    "sg:postcode":"08075",
    "sg:province":"NJ",
    "wof:name":"Mat Petroleum Corp",
    "wof:placetype":"venue"
},
  "geometry": {"coordinates":[-74.958302,40.033007],"type":"Point"}
}