{
  "type": "Feature",
  "properties": {
    "addr:full":"116 N Union St Lambertville NJ 08530",
    "addr:housenumber":"116",
    "addr:postcode":"08530",
    "addr:street":"N Union St",
    "iso:country":"US",
    "sg:address":"116 N Union St",
    "sg:city":"Lambertville",
    "sg:classifiers":[
        {
            "category":"Personal",
            "subcategory":"Beauty Salon",
            "type":"Services"
        }
    ],
    "sg:phone":"+1 609 397 4044",
    "sg:postcode":"08530",
    "sg:province":"NJ",
    "sg:tags":[
        "shop"
    ],
    "wof:name":"Garden Artistry LLC",
    "wof:placetype":"venue"
},
  "geometry": {"coordinates":[-74.946303,40.370343],"type":"Point"}
}