{
  "type": "Feature",
  "properties": {
    "addr:full":"85 Horse Hill Rd Cedar Knolls NJ 07927",
    "addr:housenumber":"85",
    "addr:postcode":"07927",
    "addr:street":"Horse Hill Rd",
    "iso:country":"US",
    "sg:address":"85 Horse Hill Rd",
    "sg:city":"Cedar Knolls",
    "sg:classifiers":[
        {
            "category":"Manufacturing",
            "subcategory":"Electronics",
            "type":"Manufacturing & Wholesale Goods"
        }
    ],
    "sg:phone":"+1 973 267 1900",
    "sg:postcode":"07927",
    "sg:province":"NJ",
    "sg:tags":[
        "equipment",
        "electronic",
        "supply"
    ],
    "sg:website":"www.tdipower.com",
    "wof:name":"Transistor Devices Inc",
    "wof:placetype":"venue"
},
  "geometry": {"coordinates":[-74.46601200000001,40.81302],"type":"Point"}
}