{
  "type": "Feature",
  "properties": {
    "addr:full":"50 Cutler Ave Westville NJ 08093",
    "addr:housenumber":"50",
    "addr:postcode":"08093",
    "addr:street":"Cutler Ave",
    "iso:country":"US",
    "sg:address":"50 Cutler Ave",
    "sg:city":"Westville",
    "sg:classifiers":[
        {
            "category":"Manufacturing",
            "subcategory":"Printing",
            "type":"Manufacturing & Wholesale Goods"
        }
    ],
    "sg:phone":"+1 856 384 7773",
    "sg:postcode":"08093",
    "sg:province":"NJ",
    "sg:tags":[
        "printer"
    ],
    "wof:name":"Kiva Printing & Graphics",
    "wof:placetype":"venue"
},
  "geometry": {"coordinates":[-75.12411299999999,39.858382],"type":"Point"}
}