{
  "type": "Feature",
  "properties": {
    "iso:country":"US",
    "sg:address":"2821 Bergenline Ave",
    "sg:city":"Union City",
    "sg:classifiers":[
        {
            "category":"Local Transit",
            "type":"Transportation"
        }
    ],
    "sg:phone":"+1 201 864 6800",
    "sg:postcode":"07087",
    "sg:province":"NJ",
    "sg:tags":[
        "bus",
        "line"
    ],
    "wof:name":"Omnibus LA Cubana",
    "wof:placetype":"venue"
},
  "geometry": {"coordinates":[-74.030497,40.770488],"type":"Point"}
}