{
  "type": "Feature",
  "properties": {
    "addr:full":"744 Bergen Ave Jersey City NJ 07306",
    "addr:housenumber":"744",
    "addr:postcode":"07306",
    "addr:street":"Bergen Ave",
    "iso:country":"US",
    "sg:address":"744 Bergen Ave",
    "sg:city":"Jersey City",
    "sg:classifiers":[
        {
            "category":"Shopping",
            "subcategory":"Used Merchandise",
            "type":"Retail Goods"
        }
    ],
    "sg:phone":"+1 201 333 8991",
    "sg:postcode":"07306",
    "sg:province":"NJ",
    "sg:tags":[
        "pawnbroker"
    ],
    "wof:name":"H Schoenberg",
    "wof:placetype":"venue"
},
  "geometry": {"coordinates":[-74.06809199999999,40.725157],"type":"Point"}
}