{
  "type": "Feature",
  "properties": {
    "addr:full":"433 W Farms Rd Farmingdale NJ 07727",
    "addr:housenumber":"433",
    "addr:postcode":"07727",
    "addr:street":"W Farms Rd",
    "iso:country":"US",
    "sg:address":"433 W Farms Rd",
    "sg:city":"Farmingdale",
    "sg:classifiers":[
        {
            "category":"Building & Trades",
            "subcategory":"Construction",
            "type":"Services"
        }
    ],
    "sg:phone":"+1 732 919 0065",
    "sg:postcode":"07727",
    "sg:province":"NJ",
    "sg:tags":[
        "house"
    ],
    "wof:name":"Jamison Construction Co",
    "wof:placetype":"venue"
},
  "geometry": {"coordinates":[-74.22084599999999,40.189268],"type":"Point"}
}