{
  "type": "Feature",
  "properties": {
    "addr:full":"21 Industrial Pl Summit NJ 07901",
    "addr:housenumber":"21",
    "addr:postcode":"07901",
    "addr:street":"Industrial Pl",
    "iso:country":"US",
    "sg:address":"21 Industrial Pl",
    "sg:city":"Summit",
    "sg:classifiers":[
        {
            "category":"Building & Trades",
            "subcategory":"Construction",
            "type":"Services"
        }
    ],
    "sg:phone":"+1 908 277 4199",
    "sg:postcode":"07901",
    "sg:province":"NJ",
    "sg:tags":[
        "residential"
    ],
    "wof:name":"William F OBrien Builder",
    "wof:placetype":"venue"
},
  "geometry": {"coordinates":[-74.355287,40.714812],"type":"Point"}
}