{
  "type": "Feature",
  "properties": {
    "iso:country":"US",
    "sg:address":"55 Harristown Rd",
    "sg:city":"Glen Rock",
    "sg:classifiers":[
        {
            "category":"Professional",
            "subcategory":"Lawyer & Legal Services",
            "type":"Services"
        }
    ],
    "sg:phone":"+1 201 612 6974",
    "sg:postcode":"07452",
    "sg:province":"NJ",
    "sg:tags":[
        "attorney"
    ],
    "wof:name":"C Boyd Cote Legal Svc",
    "wof:placetype":"venue"
},
  "geometry": {"coordinates":[-74.14415099999999,40.948705],"type":"Point"}
}