{
  "type": "Feature",
  "properties": {
    "addr:full":"144 W State St Trenton NJ 08608",
    "addr:housenumber":"144",
    "addr:postcode":"08608",
    "addr:street":"W State St",
    "iso:country":"US",
    "sg:address":"144 W State St",
    "sg:city":"Trenton",
    "sg:classifiers":[
        {
            "category":"Professional",
            "subcategory":"Accounting & Tax Preparation",
            "type":"Services"
        }
    ],
    "sg:phone":"+1 609 394 0130",
    "sg:postcode":"08608",
    "sg:province":"NJ",
    "wof:name":"Deloitte & Touche",
    "wof:placetype":"venue"
},
  "geometry": {"coordinates":[-74.768096,40.220516],"type":"Point"}
}