{
  "type": "Feature",
  "properties": {
    "addr:full":"61 Karen Pl Budd Lake NJ 07828",
    "addr:housenumber":"61",
    "addr:postcode":"07828",
    "addr:street":"Karen Pl",
    "iso:country":"US",
    "sg:address":"61 Karen Pl",
    "sg:city":"Budd Lake",
    "sg:classifiers":[
        {
            "category":"Professional",
            "type":"Services"
        }
    ],
    "sg:phone":"+1   ",
    "sg:postcode":"07828",
    "sg:province":"NJ",
    "wof:name":"Daniel Fuller",
    "wof:placetype":"venue"
},
  "geometry": {"coordinates":[-74.777861,40.877333],"type":"Point"}
}