{
  "type": "Feature",
  "properties": {
    "addr:full":"100 Essex Ave Bellmawr NJ 08031",
    "addr:housenumber":"100",
    "addr:postcode":"08031",
    "addr:street":"Essex Ave",
    "iso:country":"US",
    "sg:address":"100 Essex Ave",
    "sg:city":"Bellmawr",
    "sg:classifiers":[
        {
            "category":"Organizations",
            "subcategory":"Membership Organization",
            "type":"Services"
        }
    ],
    "sg:phone":"+1 856 933 9500",
    "sg:postcode":"08031",
    "sg:province":"NJ",
    "sg:website":"www.acsnj.org",
    "wof:name":"AIDS Coalition",
    "wof:placetype":"venue"
},
  "geometry": {"coordinates":[-75.10428,39.868483],"type":"Point"}
}