{
  "type": "Feature",
  "properties": {
    "iso:country":"US",
    "sg:address":"186 Coolidge Ter",
    "sg:city":"Wyckoff",
    "sg:classifiers":[
        {
            "category":"Professional",
            "subcategory":"Management & Consulting",
            "type":"Services"
        }
    ],
    "sg:phone":"+1 201 670 1093",
    "sg:postcode":"07481",
    "sg:province":"NJ",
    "sg:tags":[
        "business"
    ],
    "wof:name":"Rational Sap Consulting Inc",
    "wof:placetype":"venue"
},
  "geometry": {"coordinates":[-74.15748000000001,40.984553],"type":"Point"}
}