{
  "type": "Feature",
  "properties": {
    "iso:country":"US",
    "sg:address":"402 Park St",
    "sg:city":"Hackensack",
    "sg:classifiers":[
        {
            "category":"Retail",
            "subcategory":"Funeral Services",
            "type":"Services"
        }
    ],
    "sg:phone":"+1 201 489 2728",
    "sg:postcode":"07601",
    "sg:province":"NJ",
    "sg:tags":[
        "cemetery"
    ],
    "sg:website":"www.dignitymemorial.com",
    "wof:name":"Riverside Memorial Chapel of New Jersey",
    "wof:placetype":"venue"
},
  "geometry": {"coordinates":[-74.044296,40.890598],"type":"Point"}
}