{
  "type": "Feature",
  "properties": {
    "iso:country":"US",
    "sg:address":"350 Center Ave",
    "sg:city":"Westwood",
    "sg:classifiers":[
        {
            "category":"Shopping",
            "subcategory":"Clothing, Apparel, & Fashions",
            "type":"Retail Goods"
        }
    ],
    "sg:phone":"+1 201 664 9299",
    "sg:postcode":"07675",
    "sg:province":"NJ",
    "sg:tags":[
        "infant",
        "accessory",
        "girl",
        "wear"
    ],
    "wof:name":"Daisy & Lilly LLC",
    "wof:placetype":"venue"
},
  "geometry": {"coordinates":[-74.03245,40.992443],"type":"Point"}
}