{
  "type": "Feature",
  "properties": {
    "iso:country":"US",
    "sg:address":"133 Cedar Ln",
    "sg:city":"Teaneck",
    "sg:classifiers":[
        {
            "category":"Manufacturing",
            "subcategory":"Paper Products",
            "type":"Manufacturing & Wholesale Goods"
        }
    ],
    "sg:phone":"+1 201 836 5060",
    "sg:postcode":"07666",
    "sg:province":"NJ",
    "sg:tags":[
        "bag"
    ],
    "wof:name":"J A Heilferty & Co",
    "wof:placetype":"venue"
},
  "geometry": {"coordinates":[-74.011911,40.885818],"type":"Point"}
}