{
  "type": "Feature",
  "properties": {
    "iso:country":"US",
    "sg:address":"100 N California Ave",
    "sg:city":"Atlantic City",
    "sg:classifiers":[
        {
            "category":"Building & Trades",
            "subcategory":"Electrical",
            "type":"Services"
        }
    ],
    "sg:phone":"+1 609 340 0081",
    "sg:postcode":"08401",
    "sg:province":"NJ",
    "sg:tags":[
        "electrician"
    ],
    "wof:name":"Michael Zingarelli",
    "wof:placetype":"venue"
},
  "geometry": {"coordinates":[-74.445819,39.357634],"type":"Point"}
}