{
  "type": "Feature",
  "properties": {
    "iso:country":"US",
    "sg:address":"771 Shrewsbury Ave",
    "sg:city":"Shrewsbury",
    "sg:classifiers":[
        {
            "category":"Manufacturing",
            "subcategory":"Printing",
            "type":"Manufacturing & Wholesale Goods"
        }
    ],
    "sg:phone":"+1 732 741 1445",
    "sg:postcode":"07701",
    "sg:province":"NJ",
    "sg:tags":[
        "printer",
        "offset"
    ],
    "wof:name":"Big Red Q",
    "wof:placetype":"venue"
},
  "geometry": {"coordinates":[-74.07257799999999,40.320077],"type":"Point"}
}