{
  "type": "Feature",
  "properties": {
    "iso:country":"US",
    "sg:address":"600 Mount Prospect Ave",
    "sg:city":"Newark",
    "sg:classifiers":[
        {
            "category":"Professional",
            "subcategory":"Management & Consulting",
            "type":"Services"
        }
    ],
    "sg:phone":"+1   ",
    "sg:postcode":"07104",
    "sg:province":"NJ",
    "wof:name":"US Neurology",
    "wof:placetype":"venue"
},
  "geometry": {"coordinates":[-74.166763,40.773711],"type":"Point"}
}