{
  "type": "Feature",
  "properties": {
    "addr:full":"334 S Broadway Pitman NJ 08071",
    "addr:housenumber":"334",
    "addr:postcode":"08071",
    "addr:street":"S Broadway",
    "iso:country":"US",
    "sg:address":"334 S Broadway",
    "sg:city":"Pitman",
    "sg:classifiers":[
        {
            "category":"Professional",
            "subcategory":"Management & Consulting",
            "type":"Services"
        }
    ],
    "sg:phone":"+1 856 582 7845",
    "sg:postcode":"08071",
    "sg:province":"NJ",
    "sg:tags":[
        "business"
    ],
    "wof:name":"Elissa Eystad",
    "wof:placetype":"venue"
},
  "geometry": {"coordinates":[-75.128047,39.729497],"type":"Point"}
}