{
  "type": "Feature",
  "properties": {
    "iso:country":"US",
    "sg:address":"739 Rahway Ave",
    "sg:city":"Woodbridge",
    "sg:classifiers":[
        {
            "category":"Restaurant",
            "type":"Food & Drink"
        }
    ],
    "sg:phone":"+1 732 634 4699",
    "sg:postcode":"07095",
    "sg:province":"NJ",
    "sg:website":"www.mulberry-street.com",
    "wof:name":"Mulberry Restaurant and Bar",
    "wof:placetype":"venue"
},
  "geometry": {"coordinates":[-74.27269699999999,40.566601],"type":"Point"}
}