{
  "type": "Feature",
  "properties": {
    "iso:country":"US",
    "sg:address":"214 Willow Ave",
    "sg:city":"Hoboken",
    "sg:classifiers":[
        {
            "category":"Communications",
            "type":"Services"
        }
    ],
    "sg:phone":"+1 201 222 1309",
    "sg:postcode":"07030",
    "sg:province":"NJ",
    "sg:tags":[
        "communication"
    ],
    "wof:name":"Ijm Communications",
    "wof:placetype":"venue"
},
  "geometry": {"coordinates":[-74.033845,40.74044],"type":"Point"}
}