{
  "type": "Feature",
  "properties": {
    "addr:full":"39 Glenridge Ave Ste A Montclair NJ 07042",
    "addr:housenumber":"39",
    "addr:postcode":"07042",
    "addr:street":"Glenridge Ave Ste A",
    "iso:country":"US",
    "sg:address":"39 Glenridge Ave Ste A",
    "sg:city":"Montclair",
    "sg:classifiers":[
        {
            "category":"Restaurant",
            "type":"Food & Drink"
        }
    ],
    "sg:phone":"+1 973 746 5600",
    "sg:postcode":"07042",
    "sg:province":"NJ",
    "wof:name":"Madear's Southern Cuisine & Catering Llc",
    "wof:placetype":"venue"
},
  "geometry": {"coordinates":[-74.207703,40.809101],"type":"Point"}
}