{
  "type": "Feature",
  "properties": {
    "iso:country":"US",
    "sg:address":"238 Rutgers Pl",
    "sg:city":"Nutley",
    "sg:classifiers":[
        {
            "category":"Professional",
            "subcategory":"Computer Services",
            "type":"Services"
        }
    ],
    "sg:phone":"+1 973 661 0220",
    "sg:postcode":"07110",
    "sg:province":"NJ",
    "sg:tags":[
        "related"
    ],
    "wof:name":"Hargrave Consulting",
    "wof:placetype":"venue"
},
  "geometry": {"coordinates":[-74.14765199999999,40.823724],"type":"Point"}
}