{
  "type": "Feature",
  "properties": {
    "addr:full":"83 Hiawatha Blvd Lake Hiawatha NJ 07034",
    "addr:housenumber":"83",
    "addr:postcode":"07034",
    "addr:street":"Hiawatha Blvd",
    "iso:country":"US",
    "sg:address":"83 Hiawatha Blvd",
    "sg:city":"Lake Hiawatha",
    "sg:classifiers":[
        {
            "category":"Building & Trades",
            "subcategory":"Landscaping Services",
            "type":"Services"
        }
    ],
    "sg:phone":"+1 973 299 8777",
    "sg:postcode":"07034",
    "sg:province":"NJ",
    "wof:name":"Coes Tree Services",
    "wof:placetype":"venue"
},
  "geometry": {"coordinates":[-74.375535,40.882089],"type":"Point"}
}