{
  "type": "Feature",
  "properties": {
    "iso:country":"US",
    "sg:address":"8 Donna Dr",
    "sg:city":"East Hanover",
    "sg:classifiers":[
        {
            "category":"Organizations",
            "subcategory":"Membership Organization",
            "type":"Services"
        }
    ],
    "sg:phone":"+1 973 428 1190",
    "sg:postcode":"07936",
    "sg:province":"NJ",
    "wof:name":"William F Grupe Foundation Inc",
    "wof:placetype":"venue"
},
  "geometry": {"coordinates":[-74.364192,40.808092],"type":"Point"}
}