{
  "type": "Feature",
  "properties": {
    "addr:full":"845 Broad Ave Ridgefield NJ 07657",
    "addr:housenumber":"845",
    "addr:postcode":"07657",
    "addr:street":"Broad Ave",
    "iso:country":"US",
    "sg:address":"845 Broad Ave",
    "sg:city":"Ridgefield",
    "sg:classifiers":[
        {
            "category":"Autos & Motor Vehicles",
            "subcategory":"Automobile Sales",
            "type":"Retail Goods"
        }
    ],
    "sg:phone":"+1 201 945 1212",
    "sg:postcode":"07657",
    "sg:province":"NJ",
    "sg:tags":[
        "limo"
    ],
    "wof:name":"Smile Limousine Enterprise",
    "wof:placetype":"venue"
},
  "geometry": {"coordinates":[-74.002995,40.841119],"type":"Point"}
}