{
  "type": "Feature",
  "properties": {
    "iso:country":"US",
    "sg:address":"248 Warren St",
    "sg:city":"Newark",
    "sg:classifiers":[
        {
            "category":"Banks & Credit Unions",
            "subcategory":"Bank",
            "type":"Services"
        }
    ],
    "sg:phone":"+1   ",
    "sg:postcode":"07103",
    "sg:province":"NJ",
    "sg:tags":[
        "mortgage"
    ],
    "wof:name":"Mortgage Finder Center LLC",
    "wof:placetype":"venue"
},
  "geometry": {"coordinates":[-74.184202,40.742819],"type":"Point"}
}