{
  "type": "Feature",
  "properties": {
    "iso:country":"US",
    "sg:address":"49 Fleming Ave",
    "sg:city":"Newark",
    "sg:classifiers":[
        {
            "category":"Restaurant",
            "type":"Food & Drink"
        }
    ],
    "sg:phone":"+1   ",
    "sg:postcode":"07105",
    "sg:province":"NJ",
    "sg:tags":[
        "luncheonette"
    ],
    "wof:name":"El Negocio",
    "wof:placetype":"venue"
},
  "geometry": {"coordinates":[-74.145551,40.731252],"type":"Point"}
}