{
  "type": "Feature",
  "properties": {
    "addr:full":"125 Georges Rd New Brunswick NJ 08901",
    "addr:housenumber":"125",
    "addr:postcode":"08901",
    "addr:street":"Georges Rd",
    "iso:country":"US",
    "sg:address":"125 Georges Rd",
    "sg:city":"New Brunswick",
    "sg:classifiers":[
        {
            "category":"Retail",
            "subcategory":"Auto Repair",
            "type":"Services"
        }
    ],
    "sg:phone":"+1 732 220 1577",
    "sg:postcode":"08901",
    "sg:province":"NJ",
    "sg:tags":[
        "repairing",
        "automobile",
        "general"
    ],
    "wof:name":"Guelo's Auto Repair",
    "wof:placetype":"venue"
},
  "geometry": {"coordinates":[-74.447801,40.476642],"type":"Point"}
}