{
  "type": "Feature",
  "properties": {
    "iso:country":"US",
    "sg:address":"237 Mill St",
    "sg:city":"Westwood",
    "sg:classifiers":[
        {
            "category":"Personal",
            "type":"Services"
        }
    ],
    "sg:phone":"+1   ",
    "sg:postcode":"07675",
    "sg:province":"NJ",
    "wof:name":"Brobson",
    "wof:placetype":"venue"
},
  "geometry": {"coordinates":[-74.04470499999999,40.987763],"type":"Point"}
}