{
  "type": "Feature",
  "properties": {
    "addr:full":"1330 Union Rd Vineland NJ 08361",
    "addr:housenumber":"1330",
    "addr:postcode":"08361",
    "addr:street":"Union Rd",
    "iso:country":"US",
    "sg:address":"1330 Union Rd",
    "sg:city":"Vineland",
    "sg:classifiers":[
        {
            "category":"Farming",
            "subcategory":"Farm",
            "type":"Manufacturing & Wholesale Goods"
        }
    ],
    "sg:phone":"+1 856 692 3187",
    "sg:postcode":"08361",
    "sg:province":"NJ",
    "sg:tags":[
        "crop",
        "general"
    ],
    "wof:name":"S and R Farms",
    "wof:placetype":"venue"
},
  "geometry": {"coordinates":[-74.924651,39.432302],"type":"Point"}
}