{
  "type": "Feature",
  "properties": {
    "addr:full":"54 South St Morristown NJ 07960",
    "addr:housenumber":"54",
    "addr:postcode":"07960",
    "addr:street":"South St",
    "iso:country":"US",
    "sg:address":"54 South St",
    "sg:city":"Morristown",
    "sg:classifiers":[
        {
            "category":"Food & Beverages",
            "subcategory":"Candy",
            "type":"Retail Goods"
        }
    ],
    "sg:phone":"+1 973 644 9400",
    "sg:postcode":"07960",
    "sg:province":"NJ",
    "sg:tags":[
        "confectionery"
    ],
    "wof:name":"Jerry Madaio",
    "wof:placetype":"venue"
},
  "geometry": {"coordinates":[-74.481005,40.796352],"type":"Point"}
}