{
  "type": "Feature",
  "properties": {
    "addr:full":"8 Magnolia Ave New Egypt NJ 08533",
    "addr:housenumber":"8",
    "addr:postcode":"08533",
    "addr:street":"Magnolia Ave",
    "iso:country":"US",
    "sg:address":"8 Magnolia Ave",
    "sg:city":"New Egypt",
    "sg:classifiers":[
        {
            "category":"Organizations",
            "subcategory":"Religious Organization",
            "type":"Services"
        }
    ],
    "sg:phone":"+1   ",
    "sg:postcode":"08533",
    "sg:province":"NJ",
    "sg:tags":[
        "baptist",
        "church"
    ],
    "wof:name":"Bible Baptist Church",
    "wof:placetype":"venue"
},
  "geometry": {"coordinates":[-74.52825,40.067108],"type":"Point"}
}