{
  "type": "Feature",
  "properties": {
    "iso:country":"US",
    "sg:address":"30 Carletondale Rd",
    "sg:city":"Ringwood",
    "sg:classifiers":[
        {
            "category":"Organizations",
            "subcategory":"Religious Organization",
            "type":"Services"
        }
    ],
    "sg:phone":"+1 973 962 7083",
    "sg:postcode":"07456",
    "sg:province":"NJ",
    "sg:tags":[
        "elementary",
        "secondary",
        "church"
    ],
    "sg:website":"www.ringwoodbaptist.org",
    "wof:name":"Ringwood Baptist Church Inc",
    "wof:placetype":"venue"
},
  "geometry": {"coordinates":[-74.25441600000001,41.112017],"type":"Point"}
}