{
  "type": "Feature",
  "properties": {
    "iso:country":"US",
    "sg:address":"300 State Rte 73",
    "sg:city":"Marlton",
    "sg:classifiers":[
        {
            "category":"Shopping",
            "subcategory":"Stationery & Office Supplies",
            "type":"Retail Goods"
        }
    ],
    "sg:phone":"+1 856 985 1776",
    "sg:postcode":"08053",
    "sg:province":"NJ",
    "sg:tags":[
        "stationer",
        "printing",
        "commercial"
    ],
    "sg:website":"www.paperyofmarlton.com",
    "wof:name":"Papery Of Marlton",
    "wof:placetype":"venue"
},
  "geometry": {"coordinates":[-74.922944,39.887091],"type":"Point"}
}