{
  "type": "Feature",
  "properties": {
    "addr:full":"1064 Commerce Ave Union NJ 07083",
    "addr:housenumber":"1064",
    "addr:postcode":"07083",
    "addr:street":"Commerce Ave",
    "iso:country":"US",
    "sg:address":"1064 Commerce Ave",
    "sg:city":"Union",
    "sg:classifiers":[
        {
            "category":"Manufacturing",
            "subcategory":"Tools & Machinery",
            "type":"Manufacturing & Wholesale Goods"
        }
    ],
    "sg:phone":"+1 908 964 0504",
    "sg:postcode":"07083",
    "sg:province":"NJ",
    "sg:tags":[
        "jig",
        "special",
        "maker",
        "die",
        "mfg"
    ],
    "wof:name":"Saturn Tool & Die Inc",
    "wof:placetype":"venue"
},
  "geometry": {"coordinates":[-74.279757,40.701098],"type":"Point"}
}