{
  "type": "Feature",
  "properties": {
    "addr:full":"4 Art St Dover NJ 07801",
    "addr:housenumber":"4",
    "addr:postcode":"07801",
    "addr:street":"Art St",
    "iso:country":"US",
    "sg:address":"4 Art St",
    "sg:city":"Dover",
    "sg:classifiers":[
        {
            "category":"Government",
            "subcategory":"Fire Station",
            "type":"Public Place"
        }
    ],
    "sg:phone":"+1   ",
    "sg:postcode":"07801",
    "sg:province":"NJ",
    "sg:tags":[
        "protection"
    ],
    "wof:name":"Birchwood Fire Dept",
    "wof:placetype":"venue"
},
  "geometry": {"coordinates":[-74.537482,40.901363],"type":"Point"}
}