{
  "type": "Feature",
  "properties": {
    "addr:full":"10 Hereford Dr Princeton Jct NJ 08550",
    "addr:housenumber":"10",
    "addr:postcode":"08550",
    "addr:street":"Hereford Dr",
    "iso:country":"US",
    "sg:address":"10 Hereford Dr",
    "sg:city":"Princeton Jct",
    "sg:classifiers":[
        {
            "category":"Professional",
            "subcategory":"Accounting & Tax Preparation",
            "type":"Services"
        }
    ],
    "sg:phone":"+1 609 497 2929",
    "sg:postcode":"08550",
    "sg:province":"NJ",
    "sg:tags":[
        "prepackaged",
        "accountant",
        "se",
        "software"
    ],
    "wof:name":"Henry B Murphy Jr CPA",
    "wof:placetype":"venue"
},
  "geometry": {"coordinates":[-74.623617,40.305484],"type":"Point"}
}