{
  "type": "Feature",
  "properties": {
    "iso:country":"US",
    "sg:address":"617 Union Ave",
    "sg:city":"Brielle",
    "sg:classifiers":[
        {
            "category":"Professional",
            "subcategory":"Employment Agencies",
            "type":"Services"
        }
    ],
    "sg:phone":"+1 732 223 7114",
    "sg:postcode":"08730",
    "sg:province":"NJ",
    "sg:tags":[
        "consultant",
        "search",
        "executive"
    ],
    "sg:website":"www.commonagenda.com",
    "wof:name":"Common Agenda",
    "wof:placetype":"venue"
},
  "geometry": {"coordinates":[-74.058188,40.111219],"type":"Point"}
}