{
  "type": "Feature",
  "properties": {
    "iso:country":"US",
    "sg:address":"675 Valley Brook Ave",
    "sg:city":"Lyndhurst",
    "sg:classifiers":[
        {
            "category":"Retail",
            "subcategory":"Auto Repair",
            "type":"Services"
        }
    ],
    "sg:phone":"+1 201 438 0879",
    "sg:postcode":"07071",
    "sg:province":"NJ",
    "wof:name":"Automotive Transport",
    "wof:placetype":"venue"
},
  "geometry": {"coordinates":[-74.11534399999999,40.806736],"type":"Point"}
}