{
  "type": "Feature",
  "properties": {
    "iso:country":"US",
    "sg:address":"757 Undercliff Ave",
    "sg:city":"Edgewater",
    "sg:classifiers":[
        {
            "category":"Local Transit",
            "type":"Transportation"
        }
    ],
    "sg:phone":"+1 201 886 1404",
    "sg:postcode":"07020",
    "sg:province":"NJ",
    "sg:tags":[
        "passenger"
    ],
    "wof:name":"E-Z Way Limousine",
    "wof:placetype":"venue"
},
  "geometry": {"coordinates":[-73.970799,40.841067],"type":"Point"}
}