{
  "type": "Feature",
  "properties": {
    "addr:full":"12 Church St Montclair NJ 07042",
    "addr:housenumber":"12",
    "addr:postcode":"07042",
    "addr:street":"Church St",
    "iso:country":"US",
    "sg:address":"12 Church St",
    "sg:city":"Montclair",
    "sg:classifiers":[
        {
            "category":"Restaurant",
            "type":"Food & Drink"
        }
    ],
    "sg:phone":"+1 973 744 2244",
    "sg:postcode":"07042",
    "sg:province":"NJ",
    "sg:tags":[
        "new",
        "american"
    ],
    "sg:website":"www.marketmontclair.com/",
    "wof:name":"Market Restaurant",
    "wof:placetype":"venue"
},
  "geometry": {"coordinates":[-74.218102,40.813742],"type":"Point"}
}