{
  "type": "Feature",
  "properties": {
    "addr:full":"32 Passaic St Paterson NJ 07501",
    "addr:housenumber":"32",
    "addr:postcode":"07501",
    "addr:street":"Passaic St",
    "iso:country":"US",
    "sg:address":"32 Passaic St",
    "sg:city":"Paterson",
    "sg:classifiers":[
        {
            "category":"Building & Trades",
            "subcategory":"Plumbing",
            "type":"Services"
        }
    ],
    "sg:phone":"+1 973 742 2950",
    "sg:postcode":"07501",
    "sg:province":"NJ",
    "wof:name":"Bianco R & Sons",
    "wof:placetype":"venue"
},
  "geometry": {"coordinates":[-74.17577300000001,40.91605],"type":"Point"}
}