{
  "type": "Feature",
  "properties": {
    "addr:full":"329 Delaware Ave Delanco NJ 08075",
    "addr:housenumber":"329",
    "addr:postcode":"08075",
    "addr:street":"Delaware Ave",
    "iso:country":"US",
    "sg:address":"329 Delaware Ave",
    "sg:city":"Delanco",
    "sg:classifiers":[
        {
            "category":"Professional",
            "subcategory":"Lawyer & Legal Services",
            "type":"Services"
        }
    ],
    "sg:phone":"+1 856 461 3306",
    "sg:postcode":"08075",
    "sg:province":"NJ",
    "wof:name":"Snow Jeffrey E",
    "wof:placetype":"venue"
},
  "geometry": {"coordinates":[-74.950897,40.027199],"type":"Point"}
}