{
  "type": "Feature",
  "properties": {
    "addr:full":"15 Center St Sussex NJ 07461",
    "addr:housenumber":"15",
    "addr:postcode":"07461",
    "addr:street":"Center St",
    "iso:country":"US",
    "sg:address":"15 Center St",
    "sg:city":"Sussex",
    "sg:classifiers":[
        {
            "category":"Retail",
            "subcategory":"Car Wash",
            "type":"Services"
        }
    ],
    "sg:phone":"+1   ",
    "sg:postcode":"07461",
    "sg:province":"NJ",
    "sg:tags":[
        "carwash"
    ],
    "wof:name":"Classic Detail",
    "wof:placetype":"venue"
},
  "geometry": {"coordinates":[-74.602273,41.212936],"type":"Point"}
}