{
  "type": "Feature",
  "properties": {
    "iso:country":"US",
    "sg:address":"20 Nassau St",
    "sg:city":"Princeton",
    "sg:classifiers":[
        {
            "category":"Banks & Credit Unions",
            "subcategory":"Investment Brokerage",
            "type":"Services"
        }
    ],
    "sg:phone":"+1   ",
    "sg:postcode":"08542",
    "sg:province":"NJ",
    "wof:name":"Quick & Reilly 221",
    "wof:placetype":"venue"
},
  "geometry": {"coordinates":[-74.6627,40.348906],"type":"Point"}
}