{
  "type": "Feature",
  "properties": {
    "iso:country":"US",
    "sg:address":"677 Bergen St",
    "sg:city":"Newark",
    "sg:classifiers":[
        {
            "category":"Restaurant",
            "type":"Food & Drink"
        }
    ],
    "sg:phone":"+1 973 824 1166",
    "sg:postcode":"07108",
    "sg:province":"NJ",
    "sg:tags":[
        "eating"
    ],
    "wof:name":"Dick & Judy's Luncheonette",
    "wof:placetype":"venue"
},
  "geometry": {"coordinates":[-74.200872,40.72018],"type":"Point"}
}