{
  "type": "Feature",
  "properties": {
    "iso:country":"US",
    "sg:address":"9 Old Milford Ln",
    "sg:city":"West Milford",
    "sg:classifiers":[
        {
            "category":"Professional",
            "subcategory":"Management & Consulting",
            "type":"Services"
        }
    ],
    "sg:phone":"+1 973 657 1142",
    "sg:postcode":"07480",
    "sg:province":"NJ",
    "sg:tags":[
        "construction"
    ],
    "wof:name":"RRAZ Design",
    "wof:placetype":"venue"
},
  "geometry": {"coordinates":[-74.405755,41.102464],"type":"Point"}
}