{
  "type": "Feature",
  "properties": {
    "addr:full":"2 Executive Dr Moorestown NJ 08057",
    "addr:housenumber":"2",
    "addr:postcode":"08057",
    "addr:street":"Executive Dr",
    "iso:country":"US",
    "sg:address":"2 Executive Dr",
    "sg:city":"Moorestown",
    "sg:classifiers":[
        {
            "category":"Building & Trades",
            "subcategory":"Construction",
            "type":"Services"
        }
    ],
    "sg:phone":"+1 856 727 0916",
    "sg:postcode":"08057",
    "sg:province":"NJ",
    "sg:tags":[
        "house"
    ],
    "wof:name":"McGarvey Development Co",
    "wof:placetype":"venue"
},
  "geometry": {"coordinates":[-74.988405,39.971413],"type":"Point"}
}