{
  "type": "Feature",
  "properties": {
    "addr:full":"7 Garfield Ave Clementon NJ 08021",
    "addr:housenumber":"7",
    "addr:postcode":"08021",
    "addr:street":"Garfield Ave",
    "iso:country":"US",
    "sg:address":"7 Garfield Ave",
    "sg:city":"Clementon",
    "sg:classifiers":[
        {
            "category":"Government",
            "subcategory":"Post Office",
            "type":"Public Place"
        }
    ],
    "sg:phone":"+1 856 783 4861",
    "sg:postcode":"08021",
    "sg:province":"NJ",
    "sg:tags":[
        "postal",
        "us"
    ],
    "wof:name":"US Post Office",
    "wof:placetype":"venue"
},
  "geometry": {"coordinates":[-74.98844699999999,39.806034],"type":"Point"}
}