{
  "type": "Feature",
  "properties": {
    "addr:full":"11 Piermont Rd Closter NJ 07624",
    "addr:housenumber":"11",
    "addr:postcode":"07624",
    "addr:street":"Piermont Rd",
    "iso:country":"US",
    "sg:address":"11 Piermont Rd",
    "sg:city":"Closter",
    "sg:classifiers":[
        {
            "category":"Building & Trades",
            "subcategory":"Construction",
            "type":"Services"
        }
    ],
    "sg:phone":"+1 201 768 0047",
    "sg:postcode":"07624",
    "sg:province":"NJ",
    "sg:tags":[
        "house"
    ],
    "wof:name":"Polynetics Inc",
    "wof:placetype":"venue"
},
  "geometry": {"coordinates":[-73.94295099999999,40.980761],"type":"Point"}
}