{
  "type": "Feature",
  "properties": {
    "iso:country":"US",
    "sg:address":"401 Narberth Ave",
    "sg:city":"Haddonfield",
    "sg:classifiers":[
        {
            "category":"Health Services",
            "subcategory":"Doctor",
            "type":"Services"
        }
    ],
    "sg:phone":"+1 800 433 3243",
    "sg:postcode":"08033",
    "sg:province":"NJ",
    "sg:tags":[
        "physician",
        "surgeons",
        "manipulative",
        "osteopathic",
        "treatment",
        "psychiatry",
        "surgeon"
    ],
    "wof:name":"University of Medicine of NJ",
    "wof:placetype":"venue"
},
  "geometry": {"coordinates":[-75.028419,39.906502],"type":"Point"}
}