{
  "type": "Feature",
  "properties": {
    "addr:full":"101 Stephen Dr Riverton NJ 08077",
    "addr:housenumber":"101",
    "addr:postcode":"08077",
    "addr:street":"Stephen Dr",
    "iso:country":"US",
    "sg:address":"101 Stephen Dr",
    "sg:city":"Riverton",
    "sg:classifiers":[
        {
            "category":"Wholesale",
            "subcategory":"Fruits & Vegetables",
            "type":"Manufacturing & Wholesale Goods"
        }
    ],
    "sg:phone":"+1 856 786 1085",
    "sg:postcode":"08077",
    "sg:province":"NJ",
    "wof:name":"George Katsikis",
    "wof:placetype":"venue"
},
  "geometry": {"coordinates":[-75.003309,39.984663],"type":"Point"}
}