{
  "type": "Feature",
  "properties": {
    "iso:country":"US",
    "sg:address":"3200 Long Beach Blvd",
    "sg:city":"Beach Haven",
    "sg:classifiers":[
        {
            "category":"Restaurant",
            "type":"Food & Drink"
        }
    ],
    "sg:phone":"+1 609 494 4917",
    "sg:postcode":"08008",
    "sg:province":"NJ",
    "wof:name":"Gino's Italian Riviera",
    "wof:placetype":"venue"
},
  "geometry": {"coordinates":[-74.186804,39.635715],"type":"Point"}
}