{
  "type": "Feature",
  "properties": {
    "addr:full":"552 Lakehurst Rd Toms River NJ 08755",
    "addr:housenumber":"552",
    "addr:postcode":"08755",
    "addr:street":"Lakehurst Rd",
    "iso:country":"US",
    "sg:address":"552 Lakehurst Rd",
    "sg:city":"Toms River",
    "sg:classifiers":[
        {
            "category":"Food & Beverages",
            "subcategory":"Meat & Fish",
            "type":"Retail Goods"
        }
    ],
    "sg:phone":"+1 732 505 1951",
    "sg:postcode":"08755",
    "sg:province":"NJ",
    "wof:name":"Abondanza",
    "wof:placetype":"venue"
},
  "geometry": {"coordinates":[-74.226287,39.965921],"type":"Point"}
}