{
  "type": "Feature",
  "properties": {
    "iso:country":"US",
    "sg:address":"6 E Washington Ave",
    "sg:city":"Pleasantville",
    "sg:classifiers":[
        {
            "category":"Personal",
            "subcategory":"Beauty Salon",
            "type":"Services"
        }
    ],
    "sg:phone":"+1   ",
    "sg:postcode":"08232",
    "sg:province":"NJ",
    "sg:tags":[
        "shop"
    ],
    "wof:name":"Shear Beauty",
    "wof:placetype":"venue"
},
  "geometry": {"coordinates":[-74.521168,39.391399],"type":"Point"}
}