{
  "type": "Feature",
  "properties": {
    "iso:country":"US",
    "sg:address":"487 Goffle Rd",
    "sg:city":"Ridgewood",
    "sg:classifiers":[
        {
            "category":"Professional",
            "subcategory":"Computer Services",
            "type":"Services"
        }
    ],
    "sg:phone":"+1 201 652 2727",
    "sg:postcode":"07450",
    "sg:province":"NJ",
    "sg:tags":[
        "programming"
    ],
    "wof:name":"Cogent Data",
    "wof:placetype":"venue"
},
  "geometry": {"coordinates":[-74.146238,40.976143],"type":"Point"}
}