{
  "type": "Feature",
  "properties": {
    "addr:full":"10 1st St Lodi NJ 07644",
    "addr:housenumber":"10",
    "addr:postcode":"07644",
    "addr:street":"1St St",
    "iso:country":"US",
    "sg:address":"10 1st St",
    "sg:city":"Lodi",
    "sg:classifiers":[
        {
            "category":"Building & Trades",
            "subcategory":"Construction",
            "type":"Services"
        }
    ],
    "sg:phone":"+1 973 546 9900",
    "sg:postcode":"07644",
    "sg:province":"NJ",
    "sg:tags":[
        "institutional",
        "municipal",
        "contractor"
    ],
    "wof:name":"Stone Creek Inc",
    "wof:placetype":"venue"
},
  "geometry": {"coordinates":[-74.08989699999999,40.873699],"type":"Point"}
}