{
  "type": "Feature",
  "properties": {
    "iso:country":"US",
    "sg:address":"317 E Trenton Ave",
    "sg:city":"Trenton",
    "sg:classifiers":[
        {
            "category":"Professional",
            "type":"Services"
        }
    ],
    "sg:phone":"+1 609 393 2162",
    "sg:postcode":"08638",
    "sg:province":"NJ",
    "sg:tags":[
        "establishment"
    ],
    "wof:name":"Upper East Trenton Ctr",
    "wof:placetype":"venue"
},
  "geometry": {"coordinates":[-74.74159400000001,40.236957],"type":"Point"}
}