{
  "type": "Feature",
  "properties": {
    "iso:country":"US",
    "sg:address":"46 Center St",
    "sg:city":"Cresskill",
    "sg:classifiers":[
        {
            "category":"Professional",
            "type":"Services"
        }
    ],
    "sg:phone":"+1   ",
    "sg:postcode":"07626",
    "sg:province":"NJ",
    "wof:name":"Jeffrey Herwitt",
    "wof:placetype":"venue"
},
  "geometry": {"coordinates":[-73.95454599999999,40.938283],"type":"Point"}
}