{
  "type": "Feature",
  "properties": {
    "addr:full":"294 Us Highway 46 Fairfield NJ 07004",
    "addr:housenumber":"294",
    "addr:postcode":"07004",
    "addr:street":"Us Highway 46",
    "iso:country":"US",
    "sg:address":"294 Us Highway 46",
    "sg:city":"Fairfield",
    "sg:classifiers":[
        {
            "category":"Ice Cream",
            "type":"Food & Drink"
        }
    ],
    "sg:menulink":"http://www.allmenus.com/nj/fairfield/243385-baskin-robbins/menu/",
    "sg:phone":"+1 973 227 3444",
    "sg:postcode":"07004",
    "sg:province":"NJ",
    "sg:tags":[
        "american"
    ],
    "wof:name":"Baskin-Robbins",
    "wof:placetype":"venue"
},
  "geometry": {"coordinates":[-74.299224,40.876837],"type":"Point"}
}