{
  "type": "Feature",
  "properties": {
    "addr:full":"2333 Whitehorse Mercerville Rd Trenton NJ 08619",
    "addr:housenumber":"2333",
    "addr:postcode":"08619",
    "addr:street":"Whitehorse Mercerville Rd",
    "iso:country":"US",
    "sg:address":"2333 Whitehorse Mercerville Rd",
    "sg:city":"Trenton",
    "sg:classifiers":[
        {
            "category":"Social Services",
            "type":"Services"
        }
    ],
    "sg:phone":"+1   ",
    "sg:postcode":"08619",
    "sg:province":"NJ",
    "sg:tags":[
        "information",
        "substance",
        "abuse"
    ],
    "wof:name":"National Council of Alcohol &",
    "wof:placetype":"venue"
},
  "geometry": {"coordinates":[-74.687128,40.229638],"type":"Point"}
}