{
  "type": "Feature",
  "properties": {
    "iso:country":"US",
    "sg:address":"11 Linden Ave",
    "sg:city":"Belleville",
    "sg:classifiers":[
        {
            "category":"Home & Garden",
            "subcategory":"Carpets & Floor Coverings",
            "type":"Retail Goods"
        }
    ],
    "sg:phone":"+1   ",
    "sg:postcode":"07109",
    "sg:province":"NJ",
    "sg:tags":[
        "install"
    ],
    "wof:name":"D L Carpets LLC",
    "wof:placetype":"venue"
},
  "geometry": {"coordinates":[-74.152497,40.794722],"type":"Point"}
}