{
  "type": "Feature",
  "properties": {
    "iso:country":"US",
    "sg:address":"433 Trinity Pl",
    "sg:city":"Elizabeth",
    "sg:classifiers":[
        {
            "category":"Retail",
            "subcategory":"Auto Rental",
            "type":"Services"
        }
    ],
    "sg:phone":"+1 908 355 3255",
    "sg:postcode":"07201",
    "sg:province":"NJ",
    "sg:tags":[
        "renting",
        "automobile"
    ],
    "wof:name":"Altra Auto Rental",
    "wof:placetype":"venue"
},
  "geometry": {"coordinates":[-74.212868,40.671784],"type":"Point"}
}