{
  "type": "Feature",
  "properties": {
    "iso:country":"US",
    "sg:address":"4 Meadow Rd",
    "sg:city":"Rutherford",
    "sg:classifiers":[
        {
            "category":"Food & Beverages",
            "subcategory":"Groceries & Convenience Stores",
            "type":"Retail Goods"
        }
    ],
    "sg:phone":"+1   ",
    "sg:postcode":"07070",
    "sg:province":"NJ",
    "sg:tags":[
        "eating"
    ],
    "wof:name":"Tutto Italiano Deli",
    "wof:placetype":"venue"
},
  "geometry": {"coordinates":[-74.100067,40.824157],"type":"Point"}
}