{
  "type": "Feature",
  "properties": {
    "iso:country":"US",
    "sg:address":"4527 Harrison Pl",
    "sg:city":"Union City",
    "sg:classifiers":[
        {
            "category":"Building & Trades",
            "subcategory":"Cleaning & Sanitation",
            "type":"Services"
        }
    ],
    "sg:phone":"+1   ",
    "sg:postcode":"07087",
    "sg:province":"NJ",
    "sg:tags":[
        "maintenance"
    ],
    "wof:name":"Select Janitorial Service",
    "wof:placetype":"venue"
},
  "geometry": {"coordinates":[-74.024197,40.780746],"type":"Point"}
}