{
  "type": "Feature",
  "properties": {
    "addr:full":"251 North Ave W Westfield NJ 07090",
    "addr:housenumber":"251",
    "addr:postcode":"07090",
    "addr:street":"North Ave W",
    "iso:country":"US",
    "sg:address":"251 North Ave W",
    "sg:city":"Westfield",
    "sg:classifiers":[
        {
            "category":"Retail",
            "subcategory":"Portrait Studio",
            "type":"Services"
        }
    ],
    "sg:phone":"+1 908 654 7171",
    "sg:postcode":"07090",
    "sg:province":"NJ",
    "sg:tags":[
        "photographer"
    ],
    "wof:name":"Moto Photo",
    "wof:placetype":"venue"
},
  "geometry": {"coordinates":[-74.347279,40.650352],"type":"Point"}
}