{
  "type": "Feature",
  "properties": {
    "iso:country":"US",
    "sg:address":"542 Birch Ave",
    "sg:city":"Westfield",
    "sg:classifiers":[
        {
            "category":"Manufacturing",
            "subcategory":"Paper Products",
            "type":"Manufacturing & Wholesale Goods"
        }
    ],
    "sg:phone":"+1 908 654 9316",
    "sg:postcode":"07090",
    "sg:province":"NJ",
    "sg:tags":[
        "mill"
    ],
    "wof:name":"Partners In Paper",
    "wof:placetype":"venue"
},
  "geometry": {"coordinates":[-74.354499,40.663437],"type":"Point"}
}