{
  "type": "Feature",
  "properties": {
    "addr:full":"35 S Dupont Rd Penns Grove NJ 08069",
    "addr:housenumber":"35",
    "addr:postcode":"08069",
    "addr:street":"S Dupont Rd",
    "iso:country":"US",
    "sg:address":"35 S Dupont Rd",
    "sg:city":"Penns Grove",
    "sg:classifiers":[
        {
            "category":"Organizations",
            "subcategory":"Community Association",
            "type":"Services"
        }
    ],
    "sg:phone":"+1   ",
    "sg:postcode":"08069",
    "sg:province":"NJ",
    "sg:tags":[
        "drinking"
    ],
    "wof:name":"Servicemens Memorial Home",
    "wof:placetype":"venue"
},
  "geometry": {"coordinates":[-75.458634,39.718811],"type":"Point"}
}