{
  "type": "Feature",
  "properties": {
    "iso:country":"US",
    "sg:address":"9 Summit St",
    "sg:city":"Newark",
    "sg:classifiers":[
        {
            "category":"Health Services",
            "subcategory":"Doctor",
            "type":"Services"
        }
    ],
    "sg:phone":"+1 973 824 0990",
    "sg:postcode":"07103",
    "sg:province":"NJ",
    "sg:tags":[
        "physician",
        "surgeon"
    ],
    "wof:name":"S Mehta MD",
    "wof:placetype":"venue"
},
  "geometry": {"coordinates":[-74.176762,40.744445],"type":"Point"}
}