{
  "type": "Feature",
  "properties": {
    "iso:country":"US",
    "sg:address":"334 6th St",
    "sg:city":"Avalon",
    "sg:classifiers":[
        {
            "category":"Professional",
            "subcategory":"Engineering",
            "type":"Services"
        }
    ],
    "sg:phone":"+1 609 967 7038",
    "sg:postcode":"08202",
    "sg:province":"NJ",
    "sg:tags":[
        "engineer"
    ],
    "wof:name":"Joseph B Callaghan Inc",
    "wof:placetype":"venue"
},
  "geometry": {"coordinates":[-74.71267899999999,39.112581],"type":"Point"}
}