{
  "type": "Feature",
  "properties": {
    "iso:country":"US",
    "sg:address":"37 Sofia Dr",
    "sg:city":"Blackwood",
    "sg:classifiers":[
        {
            "category":"Professional",
            "type":"Services"
        }
    ],
    "sg:phone":"+1   ",
    "sg:postcode":"08012",
    "sg:province":"NJ",
    "wof:name":"American Dream Develpmnt",
    "wof:placetype":"venue"
},
  "geometry": {"coordinates":[-75.039109,39.843279],"type":"Point"}
}