{
  "type": "Feature",
  "properties": {
    "iso:country":"US",
    "sg:address":"71 Joyce Ln",
    "sg:city":"Wayne",
    "sg:classifiers":[
        {
            "category":"Professional",
            "subcategory":"Management & Consulting",
            "type":"Services"
        }
    ],
    "sg:phone":"+1   ",
    "sg:postcode":"07470",
    "sg:province":"NJ",
    "sg:tags":[
        "manufacturer",
        "sales",
        "representative"
    ],
    "wof:name":"Asb Sales Co",
    "wof:placetype":"venue"
},
  "geometry": {"coordinates":[-74.243178,40.955516],"type":"Point"}
}