{
  "type": "Feature",
  "properties": {
    "addr:full":"634 Rosewood Ave Roselle NJ 07203",
    "addr:housenumber":"634",
    "addr:postcode":"07203",
    "addr:street":"Rosewood Ave",
    "iso:country":"US",
    "sg:address":"634 Rosewood Ave",
    "sg:city":"Roselle",
    "sg:classifiers":[
        {
            "category":"Arts & Performance",
            "subcategory":"Theater",
            "type":"Entertainment"
        }
    ],
    "sg:phone":"+1   ",
    "sg:postcode":"07203",
    "sg:province":"NJ",
    "sg:tags":[
        "group"
    ],
    "wof:name":"Gq Entertainment & Productions",
    "wof:placetype":"venue"
},
  "geometry": {"coordinates":[-74.245795,40.657725],"type":"Point"}
}