{
  "type": "Feature",
  "properties": {
    "addr:full":"2630 E Chestnut Ave Vineland NJ 08361",
    "addr:housenumber":"2630",
    "addr:postcode":"08361",
    "addr:street":"E Chestnut Ave",
    "iso:country":"US",
    "sg:address":"2630 E Chestnut Ave",
    "sg:city":"Vineland",
    "sg:classifiers":[
        {
            "category":"Banks & Credit Unions",
            "subcategory":"Investment Brokerage",
            "type":"Services"
        }
    ],
    "sg:phone":"+1 856 696 7300",
    "sg:postcode":"08361",
    "sg:province":"NJ",
    "sg:tags":[
        "consultant",
        "planning",
        "financial"
    ],
    "sg:website":"www.ameriprise.com",
    "wof:name":"Ameriprise Financial",
    "wof:placetype":"venue"
},
  "geometry": {"coordinates":[-74.97960399999999,39.476833],"type":"Point"}
}