{
  "type": "Feature",
  "properties": {
    "iso:country":"US",
    "sg:address":"5 Braxton Dr",
    "sg:city":"Belle Mead",
    "sg:classifiers":[
        {
            "category":"Building & Trades",
            "subcategory":"Equipment Rental",
            "type":"Services"
        }
    ],
    "sg:phone":"+1 908 359 2495",
    "sg:postcode":"08502",
    "sg:province":"NJ",
    "sg:tags":[
        "machine",
        "vending"
    ],
    "wof:name":"Health-Vend of New Jersey",
    "wof:placetype":"venue"
},
  "geometry": {"coordinates":[-74.614614,40.458676],"type":"Point"}
}