{
  "type": "Feature",
  "properties": {
    "addr:full":"36 Bartha Ave Edison NJ 08817",
    "addr:housenumber":"36",
    "addr:postcode":"08817",
    "addr:street":"Bartha Ave",
    "iso:country":"US",
    "sg:address":"36 Bartha Ave",
    "sg:city":"Edison",
    "sg:classifiers":[
        {
            "category":"Restaurant",
            "type":"Food & Drink"
        }
    ],
    "sg:phone":"+1   ",
    "sg:postcode":"08817",
    "sg:province":"NJ",
    "sg:tags":[
        "eating"
    ],
    "wof:name":"Mismillah Restaurant",
    "wof:placetype":"venue"
},
  "geometry": {"coordinates":[-74.42552000000001,40.513741],"type":"Point"}
}