{
  "type": "Feature",
  "properties": {
    "addr:full":"605 Sherwood Pkwy Mountainside NJ 07092",
    "addr:housenumber":"605",
    "addr:postcode":"07092",
    "addr:street":"Sherwood Pkwy",
    "iso:country":"US",
    "sg:address":"605 Sherwood Pkwy",
    "sg:city":"Mountainside",
    "sg:classifiers":[
        {
            "category":"Health Services",
            "subcategory":"Chiropractor",
            "type":"Services"
        }
    ],
    "sg:phone":"+1 908 233 5144",
    "sg:postcode":"07092",
    "sg:province":"NJ",
    "wof:name":"Biniaris Theodore DC",
    "wof:placetype":"venue"
},
  "geometry": {"coordinates":[-74.349098,40.666302],"type":"Point"}
}