{
  "type": "Feature",
  "properties": {
    "iso:country":"US",
    "sg:address":"4 Obert Ct",
    "sg:city":"East Brunswick",
    "sg:classifiers":[
        {
            "category":"Freight",
            "type":"Transportation"
        }
    ],
    "sg:phone":"+1 732 967 9069",
    "sg:postcode":"08816",
    "sg:province":"NJ",
    "sg:tags":[
        "operator",
        "local",
        "trucking"
    ],
    "wof:name":"Hass Trucking Corp",
    "wof:placetype":"venue"
},
  "geometry": {"coordinates":[-74.411422,40.423826],"type":"Point"}
}