{
  "type": "Feature",
  "properties": {
    "addr:full":"14 Holmes St Belleville NJ 07109",
    "addr:housenumber":"14",
    "addr:postcode":"07109",
    "addr:street":"Holmes St",
    "iso:country":"US",
    "sg:address":"14 Holmes St",
    "sg:city":"Belleville",
    "sg:classifiers":[
        {
            "category":"Retail",
            "subcategory":"Repair Shop",
            "type":"Services"
        }
    ],
    "sg:phone":"+1 973 854 5706",
    "sg:postcode":"07109",
    "sg:province":"NJ",
    "sg:tags":[
        "lock",
        "key",
        "locksmith"
    ],
    "wof:name":"0 & 0 24 Hour Locksmith",
    "wof:placetype":"venue"
},
  "geometry": {"coordinates":[-74.147065,40.790018],"type":"Point"}
}