{
  "type": "Feature",
  "properties": {
    "iso:country":"US",
    "sg:address":"99 Union Ave",
    "sg:city":"Clifton",
    "sg:classifiers":[
        {
            "category":"Building & Trades",
            "subcategory":"Cleaning & Sanitation",
            "type":"Services"
        }
    ],
    "sg:phone":"+1 973 772 4732",
    "sg:postcode":"07011",
    "sg:province":"NJ",
    "sg:tags":[
        "carpet"
    ],
    "sg:website":"www.a-1masterservice.com",
    "wof:name":"A 1 Master Svc",
    "wof:placetype":"venue"
},
  "geometry": {"coordinates":[-74.14309299999999,40.876217],"type":"Point"}
}