{
  "type": "Feature",
  "properties": {
    "addr:full":"342 Main St Paterson NJ 07505",
    "addr:housenumber":"342",
    "addr:postcode":"07505",
    "addr:street":"Main St",
    "iso:country":"US",
    "sg:address":"342 Main St",
    "sg:city":"Paterson",
    "sg:classifiers":[
        {
            "category":"Shopping",
            "subcategory":"Discount & Variety Stores",
            "type":"Retail Goods"
        }
    ],
    "sg:phone":"+1 732 271 4900",
    "sg:postcode":"07505",
    "sg:province":"NJ",
    "sg:tags":[
        "merchandise",
        "general"
    ],
    "wof:name":"Record A Call Sales & Svc",
    "wof:placetype":"venue"
},
  "geometry": {"coordinates":[-74.173096,40.913266],"type":"Point"}
}