{
  "type": "Feature",
  "properties": {
    "iso:country":"US",
    "sg:address":"80 Bergen Tpke",
    "sg:city":"Little Ferry",
    "sg:classifiers":[
        {
            "category":"Manufacturing",
            "subcategory":"Tools & Machinery",
            "type":"Manufacturing & Wholesale Goods"
        }
    ],
    "sg:phone":"+1 201 373 0088",
    "sg:postcode":"07643",
    "sg:province":"NJ",
    "sg:tags":[
        "drycleaning",
        "installation",
        "equipment"
    ],
    "wof:name":"New York Machinery Inc",
    "wof:placetype":"venue"
},
  "geometry": {"coordinates":[-74.03347599999999,40.851551],"type":"Point"}
}