{
  "type": "Feature",
  "properties": {
    "addr:full":"1004 Clinton Ave Irvington NJ 07111",
    "addr:housenumber":"1004",
    "addr:postcode":"07111",
    "addr:street":"Clinton Ave",
    "iso:country":"US",
    "sg:address":"1004 Clinton Ave",
    "sg:city":"Irvington",
    "sg:classifiers":[
        {
            "category":"Food & Beverages",
            "subcategory":"Groceries & Convenience Stores",
            "type":"Retail Goods"
        }
    ],
    "sg:phone":"+1   ",
    "sg:postcode":"07111",
    "sg:province":"NJ",
    "wof:name":"Milogros Grocery",
    "wof:placetype":"venue"
},
  "geometry": {"coordinates":[-74.22284399999999,40.724621],"type":"Point"}
}