{
  "type": "Feature",
  "properties": {
    "addr:full":"75 North St Bloomsbury NJ 08804",
    "addr:housenumber":"75",
    "addr:postcode":"08804",
    "addr:street":"North St",
    "iso:country":"US",
    "sg:address":"75 North St",
    "sg:city":"Bloomsbury",
    "sg:classifiers":[
        {
            "category":"Wholesale",
            "subcategory":"Scrap",
            "type":"Manufacturing & Wholesale Goods"
        }
    ],
    "sg:phone":"+1 908 479 1331",
    "sg:postcode":"08804",
    "sg:province":"NJ",
    "sg:tags":[
        "plastic"
    ],
    "wof:name":"CVM Inc",
    "wof:placetype":"venue"
},
  "geometry": {"coordinates":[-75.082409,40.654517],"type":"Point"}
}