{
  "type": "Feature",
  "properties": {
    "iso:country":"US",
    "sg:address":"2014 US Hwy 22",
    "sg:city":"Scotch Plains",
    "sg:classifiers":[
        {
            "category":"Restaurant",
            "type":"Food & Drink"
        }
    ],
    "sg:phone":"+1   ",
    "sg:postcode":"07076",
    "sg:province":"NJ",
    "sg:tags":[
        "stand",
        "ice",
        "cream"
    ],
    "wof:name":"Scoops Ice Creamery",
    "wof:placetype":"venue"
},
  "geometry": {"coordinates":[-74.401507,40.655643],"type":"Point"}
}