{
  "type": "Feature",
  "properties": {
    "addr:full":"7805 Ventnor Ave Margate City NJ 08402",
    "addr:housenumber":"7805",
    "addr:postcode":"08402",
    "addr:street":"Ventnor Ave Margate",
    "iso:country":"US",
    "sg:address":"7805 Ventnor Ave",
    "sg:city":"Margate City",
    "sg:classifiers":[
        {
            "category":"Restaurant",
            "type":"Food & Drink"
        }
    ],
    "sg:phone":"+1 609 487 2323",
    "sg:postcode":"08402",
    "sg:province":"NJ",
    "wof:name":"Stumpo's Italian Grill & Bar",
    "wof:placetype":"venue"
},
  "geometry": {"coordinates":[-74.497642,39.330771],"type":"Point"}
}