{
  "type": "Feature",
  "properties": {
    "iso:country":"US",
    "sg:address":"142 State Rte 17",
    "sg:city":"Mahwah",
    "sg:classifiers":[
        {
            "category":"Autos & Motor Vehicles",
            "subcategory":"Fuel & Gas Station",
            "type":"Retail Goods"
        }
    ],
    "sg:phone":"+1   ",
    "sg:postcode":"07430",
    "sg:province":"NJ",
    "sg:tags":[
        "station",
        "gasoline"
    ],
    "wof:name":"Dean Service Station",
    "wof:placetype":"venue"
},
  "geometry": {"coordinates":[-74.16092399999999,41.098467],"type":"Point"}
}