{
  "type": "Feature",
  "properties": {
    "addr:full":"901 3rd Ave Phillipsburg NJ 08865",
    "addr:housenumber":"901",
    "addr:postcode":"08865",
    "addr:street":"3Rd Ave",
    "iso:country":"US",
    "sg:address":"901 3rd Ave",
    "sg:city":"Phillipsburg",
    "sg:classifiers":[
        {
            "category":"Health Services",
            "subcategory":"Optometrist",
            "type":"Services"
        }
    ],
    "sg:phone":"+1 908 859 4433",
    "sg:postcode":"08865",
    "sg:province":"NJ",
    "wof:name":"Frederick C Mariani Dr",
    "wof:placetype":"venue"
},
  "geometry": {"coordinates":[-75.15659599999999,40.664783],"type":"Point"}
}