{
  "type": "Feature",
  "properties": {
    "addr:full":"310 Main St Asbury Park NJ 07712",
    "addr:housenumber":"310",
    "addr:postcode":"07712",
    "addr:street":"Main St Asbury",
    "iso:country":"US",
    "sg:address":"310 Main St",
    "sg:city":"Asbury Park",
    "sg:classifiers":[
        {
            "category":"Banks & Credit Unions",
            "subcategory":"Bank",
            "type":"Services"
        }
    ],
    "sg:phone":"+1 732 774 5509",
    "sg:postcode":"07712",
    "sg:province":"NJ",
    "sg:tags":[
        "loan",
        "real estate"
    ],
    "wof:name":"CFIC Home Morgage",
    "wof:placetype":"venue"
},
  "geometry": {"coordinates":[-74.012817,40.217336],"type":"Point"}
}