{
  "type": "Feature",
  "properties": {
    "iso:country":"US",
    "sg:address":"60 Karen Ln",
    "sg:city":"Emerson",
    "sg:classifiers":[
        {
            "category":"Professional",
            "subcategory":"Accounting & Tax Preparation",
            "type":"Services"
        }
    ],
    "sg:phone":"+1   ",
    "sg:postcode":"07630",
    "sg:province":"NJ",
    "wof:name":"William Obolsky",
    "wof:placetype":"venue"
},
  "geometry": {"coordinates":[-74.043181,40.971562],"type":"Point"}
}