{
  "type": "Feature",
  "properties": {
    "iso:country":"US",
    "sg:address":"1140 Burnt Tavern Rd",
    "sg:city":"Brick",
    "sg:classifiers":[
        {
            "category":"Professional",
            "subcategory":"Management & Consulting",
            "type":"Services"
        }
    ],
    "sg:phone":"+1   ",
    "sg:postcode":"08724",
    "sg:province":"NJ",
    "sg:tags":[
        "insurance"
    ],
    "wof:name":"Financial Dimensions",
    "wof:placetype":"venue"
},
  "geometry": {"coordinates":[-74.139224,40.096674],"type":"Point"}
}