{
  "type": "Feature",
  "properties": {
    "addr:full":"30 Berkshire Pl Irvington NJ 07111",
    "addr:housenumber":"30",
    "addr:postcode":"07111",
    "addr:street":"Berkshire Pl",
    "iso:country":"US",
    "sg:address":"30 Berkshire Pl",
    "sg:city":"Irvington",
    "sg:classifiers":[
        {
            "category":"Shopping",
            "subcategory":"Gifts & Souvenirs",
            "type":"Retail Goods"
        }
    ],
    "sg:phone":"+1   ",
    "sg:postcode":"07111",
    "sg:province":"NJ",
    "wof:name":"Elegantly Crated Gifts Designs",
    "wof:placetype":"venue"
},
  "geometry": {"coordinates":[-74.22963300000001,40.715921],"type":"Point"}
}