{
  "type": "Feature",
  "properties": {
    "addr:full":"30 E Main St Somerville NJ 08876",
    "addr:housenumber":"30",
    "addr:postcode":"08876",
    "addr:street":"E Main St",
    "iso:country":"US",
    "sg:address":"30 E Main St",
    "sg:city":"Somerville",
    "sg:classifiers":[
        {
            "category":"Restaurant",
            "type":"Food & Drink"
        }
    ],
    "sg:phone":"+1   ",
    "sg:postcode":"08876",
    "sg:province":"NJ",
    "sg:tags":[
        "eating"
    ],
    "wof:name":"Agra Palace Inc",
    "wof:placetype":"venue"
},
  "geometry": {"coordinates":[-74.61115599999999,40.567992],"type":"Point"}
}