{
  "type": "Feature",
  "properties": {
    "iso:country":"US",
    "sg:address":"219 W Camden Ave",
    "sg:city":"Moorestown",
    "sg:classifiers":[
        {
            "category":"Professional",
            "type":"Services"
        }
    ],
    "sg:phone":"+1   ",
    "sg:postcode":"08057",
    "sg:province":"NJ",
    "wof:name":"M and M Endeavors LLC",
    "wof:placetype":"venue"
},
  "geometry": {"coordinates":[-74.986159,39.957053],"type":"Point"}
}