{
  "type": "Feature",
  "properties": {
    "addr:full":"248 Lakeview Ave Clifton NJ 07011",
    "addr:housenumber":"248",
    "addr:postcode":"07011",
    "addr:street":"Lakeview Ave",
    "iso:country":"US",
    "sg:address":"248 Lakeview Ave",
    "sg:city":"Clifton",
    "sg:classifiers":[
        {
            "category":"Shopping",
            "subcategory":"Department Store",
            "type":"Retail Goods"
        }
    ],
    "sg:phone":"+1 973 253 8999",
    "sg:postcode":"07011",
    "sg:province":"NJ",
    "sg:tags":[
        "shop"
    ],
    "wof:name":"99 Cent Store & Up",
    "wof:placetype":"venue"
},
  "geometry": {"coordinates":[-74.137946,40.883786],"type":"Point"}
}