{
  "type": "Feature",
  "properties": {
    "addr:full":"245 US Hwy 22 Bridgewater NJ 08807",
    "addr:housenumber":"245",
    "addr:postcode":"08807",
    "addr:street":"Us Hwy 22",
    "iso:country":"US",
    "sg:address":"245 US Hwy 22",
    "sg:city":"Bridgewater",
    "sg:classifiers":[
        {
            "category":"Wholesale",
            "subcategory":"Durable Goods & Equipment",
            "type":"Manufacturing & Wholesale Goods"
        },
        {
            "category":"Shopping",
            "subcategory":"Clothing, Apparel, & Fashions",
            "type":"Retail Goods"
        }
    ],
    "sg:phone":"+1 908 429 8889",
    "sg:postcode":"08807",
    "sg:province":"NJ",
    "sg:tags":[
        "importer",
        "designer"
    ],
    "wof:name":"Harriett Studio",
    "wof:placetype":"venue"
},
  "geometry": {"coordinates":[-74.674036,40.596879],"type":"Point"}
}