{
  "type": "Feature",
  "properties": {
    "iso:country":"US",
    "sg:address":"146 Camber Ln",
    "sg:city":"Mt Laurel",
    "sg:classifiers":[
        {
            "category":"Utilities",
            "subcategory":"Telephone",
            "type":"Services"
        }
    ],
    "sg:phone":"+1 856 866 1506",
    "sg:postcode":"08054",
    "sg:province":"NJ",
    "sg:tags":[
        "telecommunication"
    ],
    "wof:name":"CTI Communication",
    "wof:placetype":"venue"
},
  "geometry": {"coordinates":[-74.87037100000001,39.958659],"type":"Point"}
}