{
  "type": "Feature",
  "properties": {
    "addr:full":"419 Prospect Ave Hackensack NJ 07601",
    "addr:housenumber":"419",
    "addr:postcode":"07601",
    "addr:street":"Prospect Ave",
    "iso:country":"US",
    "sg:address":"419 Prospect Ave",
    "sg:city":"Hackensack",
    "sg:classifiers":[
        {
            "category":"Health Services",
            "subcategory":"Doctor",
            "type":"Services"
        }
    ],
    "sg:phone":"+1 201 342 8964",
    "sg:postcode":"07601",
    "sg:province":"NJ",
    "sg:tags":[
        "surgeon",
        "oral"
    ],
    "wof:name":"Conrad A Bocksel DDS",
    "wof:placetype":"venue"
},
  "geometry": {"coordinates":[-74.051903,40.896301],"type":"Point"}
}