{
  "type": "Feature",
  "properties": {
    "iso:country":"US",
    "sg:address":"1054 Delsea Dr",
    "sg:city":"Westville",
    "sg:classifiers":[
        {
            "category":"Food & Beverages",
            "subcategory":"Groceries & Convenience Stores",
            "type":"Retail Goods"
        }
    ],
    "sg:phone":"+1 856 848 8844",
    "sg:postcode":"08093",
    "sg:province":"NJ",
    "wof:name":"8 12 Mini Market",
    "wof:placetype":"venue"
},
  "geometry": {"coordinates":[-75.125298,39.8545],"type":"Point"}
}