{
  "type": "Feature",
  "properties": {
    "iso:country":"US",
    "sg:address":"999 Cranbury South River Rd",
    "sg:city":"Jamesburg",
    "sg:classifiers":[
        {
            "category":"Utilities",
            "subcategory":"Refuse",
            "type":"Services"
        }
    ],
    "sg:phone":"+1 732 521 0910",
    "sg:postcode":"08831",
    "sg:province":"NJ",
    "sg:tags":[
        "garbage",
        "collection"
    ],
    "wof:name":"JONES Industrial Svc",
    "wof:placetype":"venue"
},
  "geometry": {"coordinates":[-74.458032,40.371618],"type":"Point"}
}