{
  "type": "Feature",
  "properties": {
    "addr:full":"1226 Haddonfield Berlin Rd Voorhees NJ 08043",
    "addr:housenumber":"1226",
    "addr:postcode":"08043",
    "addr:street":"Haddonfield Berlin Rd",
    "iso:country":"US",
    "sg:address":"1226 Haddonfield Berlin Rd",
    "sg:city":"Voorhees",
    "sg:classifiers":[
        {
            "category":"Building & Trades",
            "subcategory":"Equipment Rental",
            "type":"Services"
        }
    ],
    "sg:phone":"+1 856 767 8385",
    "sg:postcode":"08043",
    "sg:province":"NJ",
    "sg:tags":[
        "yard"
    ],
    "wof:name":"Garden State Rental Ctr",
    "wof:placetype":"venue"
},
  "geometry": {"coordinates":[-74.948612,39.819353],"type":"Point"}
}