{
  "type": "Feature",
  "properties": {
    "addr:full":"9 Edgehill Ave Chatham NJ 07928",
    "addr:housenumber":"9",
    "addr:postcode":"07928",
    "addr:street":"Edgehill Ave",
    "iso:country":"US",
    "sg:address":"9 Edgehill Ave",
    "sg:city":"Chatham",
    "sg:classifiers":[
        {
            "category":"Restaurant",
            "type":"Food & Drink"
        }
    ],
    "sg:phone":"+1   ",
    "sg:postcode":"07928",
    "sg:province":"NJ",
    "sg:tags":[
        "eating"
    ],
    "wof:name":"Tucows Inc",
    "wof:placetype":"venue"
},
  "geometry": {"coordinates":[-74.38590499999999,40.733536],"type":"Point"}
}