{
  "type": "Feature",
  "properties": {
    "iso:country":"US",
    "sg:address":"12 S Indiana Ave",
    "sg:city":"Atlantic City",
    "sg:classifiers":[
        {
            "category":"Organizations",
            "subcategory":"Community Association",
            "type":"Services"
        }
    ],
    "sg:phone":"+1 609 345 4899",
    "sg:postcode":"08401",
    "sg:province":"NJ",
    "sg:tags":[
        "club"
    ],
    "wof:name":"Caligula",
    "wof:placetype":"venue"
},
  "geometry": {"coordinates":[-74.43307299999999,39.360107],"type":"Point"}
}