{
  "type": "Feature",
  "properties": {
    "addr:full":"105 Linden Ave Kearny NJ 07032",
    "addr:housenumber":"105",
    "addr:postcode":"07032",
    "addr:street":"Linden Ave",
    "iso:country":"US",
    "sg:address":"105 Linden Ave",
    "sg:city":"Kearny",
    "sg:classifiers":[
        {
            "category":"Building & Trades",
            "subcategory":"Construction",
            "type":"Services"
        }
    ],
    "sg:phone":"+1 201 991 0689",
    "sg:postcode":"07032",
    "sg:province":"NJ",
    "sg:tags":[
        "house"
    ],
    "wof:name":"D J S Builders Inc",
    "wof:placetype":"venue"
},
  "geometry": {"coordinates":[-74.143283,40.775733],"type":"Point"}
}