{
  "type": "Feature",
  "properties": {
    "addr:full":"289 Broad St Bloomfield NJ 07003",
    "addr:housenumber":"289",
    "addr:postcode":"07003",
    "addr:street":"Broad St",
    "iso:country":"US",
    "sg:address":"289 Broad St",
    "sg:city":"Bloomfield",
    "sg:classifiers":[
        {
            "category":"Communications",
            "type":"Services"
        }
    ],
    "sg:phone":"+1 212 233 1304",
    "sg:postcode":"07003",
    "sg:province":"NJ",
    "sg:tags":[
        "web",
        "design"
    ],
    "wof:name":"White Mop Ringer Co",
    "wof:placetype":"venue"
},
  "geometry": {"coordinates":[-74.194298,40.804199],"type":"Point"}
}