{
  "type": "Feature",
  "properties": {
    "addr:full":"244 E Central Ave Hammonton NJ 08037",
    "addr:housenumber":"244",
    "addr:postcode":"08037",
    "addr:street":"E Central Ave",
    "iso:country":"US",
    "sg:address":"244 E Central Ave",
    "sg:city":"Hammonton",
    "sg:classifiers":[
        {
            "category":"Wholesale",
            "subcategory":"Machinery & Supplies",
            "type":"Manufacturing & Wholesale Goods"
        }
    ],
    "sg:phone":"+1 609 567 1157",
    "sg:postcode":"08037",
    "sg:province":"NJ",
    "sg:tags":[
        "equipment",
        "construction",
        "rent",
        "repair"
    ],
    "wof:name":"Costas Contrs Eqp & Sup Co",
    "wof:placetype":"venue"
},
  "geometry": {"coordinates":[-74.798855,39.636037],"type":"Point"}
}