{
  "type": "Feature",
  "properties": {
    "iso:country":"US",
    "sg:address":"216 Short Hills Ave",
    "sg:city":"Springfield",
    "sg:classifiers":[
        {
            "category":"Health Services",
            "subcategory":"Doctor",
            "type":"Services"
        }
    ],
    "sg:phone":"+1 973 376 7838",
    "sg:postcode":"07081",
    "sg:province":"NJ",
    "wof:name":"De Fronzo Stephen MD",
    "wof:placetype":"venue"
},
  "geometry": {"coordinates":[-74.320801,40.715],"type":"Point"}
}