{
  "type": "Feature",
  "properties": {
    "addr:full":"215 Middle Rd Hazlet NJ 07730",
    "addr:housenumber":"215",
    "addr:postcode":"07730",
    "addr:street":"Middle Rd",
    "iso:country":"US",
    "sg:address":"215 Middle Rd",
    "sg:city":"Hazlet",
    "sg:classifiers":[
        {
            "category":"Social Services",
            "subcategory":"Child Care",
            "type":"Services"
        }
    ],
    "sg:phone":"+1   ",
    "sg:postcode":"07730",
    "sg:province":"NJ",
    "sg:tags":[
        "school",
        "nursery"
    ],
    "wof:name":"Creative Campus Nursery School",
    "wof:placetype":"venue"
},
  "geometry": {"coordinates":[-74.181597,40.428152],"type":"Point"}
}