{
  "type": "Feature",
  "properties": {
    "iso:country":"US",
    "sg:address":"232 Palisade Ave",
    "sg:city":"Garfield",
    "sg:classifiers":[
        {
            "category":"Manufacturing",
            "subcategory":"Tools & Machinery",
            "type":"Manufacturing & Wholesale Goods"
        }
    ],
    "sg:phone":"+1 973 478 9041",
    "sg:postcode":"07026",
    "sg:province":"NJ",
    "sg:tags":[
        "equipment",
        "printers-equipment",
        "printing",
        "supply"
    ],
    "wof:name":"Algene Marking Equipment Co Inc",
    "wof:placetype":"venue"
},
  "geometry": {"coordinates":[-74.109278,40.872328],"type":"Point"}
}