{
  "type": "Feature",
  "properties": {
    "addr:full":"65 Illinois Rd Pennsville NJ 08070",
    "addr:housenumber":"65",
    "addr:postcode":"08070",
    "addr:street":"Illinois Rd",
    "iso:country":"US",
    "sg:address":"65 Illinois Rd",
    "sg:city":"Pennsville",
    "sg:classifiers":[
        {
            "category":"Organizations",
            "subcategory":"Labor Organization",
            "type":"Services"
        }
    ],
    "sg:phone":"+1 856 678 2303",
    "sg:postcode":"08070",
    "sg:province":"NJ",
    "wof:name":"United Steelworkers of Am",
    "wof:placetype":"venue"
},
  "geometry": {"coordinates":[-75.524795,39.639488],"type":"Point"}
}