{
  "type": "Feature",
  "properties": {
    "addr:full":"1000 E Elizabeth Ave Linden NJ 07036",
    "addr:housenumber":"1000",
    "addr:postcode":"07036",
    "addr:street":"E Elizabeth Ave",
    "iso:country":"US",
    "sg:address":"1000 E Elizabeth Ave",
    "sg:city":"Linden",
    "sg:classifiers":[
        {
            "category":"Manufacturing",
            "subcategory":"Metals",
            "type":"Manufacturing & Wholesale Goods"
        },
        {
            "category":"Building & Trades",
            "subcategory":"Plumbing",
            "type":"Services"
        }
    ],
    "sg:phone":"+1 908 486 5756",
    "sg:postcode":"07036",
    "sg:province":"NJ",
    "sg:tags":[
        "mfg",
        "work",
        "sheet",
        "contractor"
    ],
    "wof:name":"Miller Paul Sheet Metal Works",
    "wof:placetype":"venue"
},
  "geometry": {"coordinates":[-74.240984,40.641439],"type":"Point"}
}