{
  "type": "Feature",
  "properties": {
    "addr:full":"2 Salem Ln Englishtown NJ 07726",
    "addr:housenumber":"2",
    "addr:postcode":"07726",
    "addr:street":"Salem Ln",
    "iso:country":"US",
    "sg:address":"2 Salem Ln",
    "sg:city":"Englishtown",
    "sg:classifiers":[
        {
            "category":"Building & Trades",
            "subcategory":"Construction",
            "type":"Services"
        }
    ],
    "sg:phone":"+1 732 683 0120",
    "sg:postcode":"07726",
    "sg:province":"NJ",
    "sg:tags":[
        "carpentry",
        "contractor"
    ],
    "wof:name":"Salem Carpentry",
    "wof:placetype":"venue"
},
  "geometry": {"coordinates":[-74.31994899999999,40.292725],"type":"Point"}
}