{
  "type": "Feature",
  "properties": {
    "addr:full":"275 State Highway 4 N Paramus NJ 07652",
    "addr:housenumber":"275",
    "addr:postcode":"07652",
    "addr:street":"State Highway 4 N",
    "iso:country":"US",
    "sg:address":"275 State Highway 4 N",
    "sg:city":"Paramus",
    "sg:classifiers":[
        {
            "category":"Health Services",
            "subcategory":"Optometrist",
            "type":"Services"
        }
    ],
    "sg:phone":"+1 201 489 6161",
    "sg:postcode":"07652",
    "sg:province":"NJ",
    "wof:name":"Eskow Kenneth OD",
    "wof:placetype":"venue"
},
  "geometry": {"coordinates":[-74.05030499999999,40.915103],"type":"Point"}
}