{
  "type": "Feature",
  "properties": {
    "addr:full":"542 Newman Springs Rd Lincroft NJ 07738",
    "addr:housenumber":"542",
    "addr:postcode":"07738",
    "addr:street":"Newman Springs Rd",
    "iso:country":"US",
    "sg:address":"542 Newman Springs Rd",
    "sg:city":"Lincroft",
    "sg:classifiers":[
        {
            "category":"Retail",
            "subcategory":"Laundry & Dry Cleaning",
            "type":"Services"
        }
    ],
    "sg:phone":"+1 732 530 7575",
    "sg:postcode":"07738",
    "sg:province":"NJ",
    "sg:tags":[
        "cleaners"
    ],
    "wof:name":"New Lincroft Cleaners",
    "wof:placetype":"venue"
},
  "geometry": {"coordinates":[-74.116563,40.331917],"type":"Point"}
}