{
  "type": "Feature",
  "properties": {
    "addr:full":"1036 Grove St North Brunswick NJ 08902",
    "addr:housenumber":"1036",
    "addr:postcode":"08902",
    "addr:street":"Grove St",
    "iso:country":"US",
    "sg:address":"1036 Grove St",
    "sg:city":"North Brunswick",
    "sg:classifiers":[
        {
            "category":"Building & Trades",
            "subcategory":"Construction",
            "type":"Services"
        }
    ],
    "sg:phone":"+1 732 422 7901",
    "sg:postcode":"08902",
    "sg:province":"NJ",
    "sg:tags":[
        "contractor"
    ],
    "wof:name":"3d Contractors Inc",
    "wof:placetype":"venue"
},
  "geometry": {"coordinates":[-74.491945,40.452331],"type":"Point"}
}