{
  "type": "Feature",
  "properties": {
    "iso:country":"US",
    "sg:address":"600 E Palisade Ave",
    "sg:city":"Englewood Cliffs",
    "sg:classifiers":[
        {
            "category":"Travel",
            "subcategory":"Travel Agent",
            "type":"Entertainment"
        }
    ],
    "sg:phone":"+1 201 569 7711",
    "sg:postcode":"07632",
    "sg:province":"NJ",
    "sg:tags":[
        "agency"
    ],
    "wof:name":"Travel Alliance Inc",
    "wof:placetype":"venue"
},
  "geometry": {"coordinates":[-73.954881,40.882639],"type":"Point"}
}