{
  "type": "Feature",
  "properties": {
    "iso:country":"US",
    "sg:address":"1016 Long Beach Blvd",
    "sg:city":"Beach Haven",
    "sg:classifiers":[
        {
            "category":"Restaurant",
            "type":"Food & Drink"
        }
    ],
    "sg:menulink":"http://www.allmenus.com/nj/long-beach/291661-sandpiper-restaurant/menu/",
    "sg:phone":"+1 609 494 4949",
    "sg:postcode":"08008",
    "sg:province":"NJ",
    "sg:tags":[
        "american"
    ],
    "wof:name":"Sandpiper Restaurant",
    "wof:placetype":"venue"
},
  "geometry": {"coordinates":[-74.18731099999999,39.634899],"type":"Point"}
}