{
  "type": "Feature",
  "properties": {
    "iso:country":"US",
    "sg:address":"175 Peregrine Dr",
    "sg:city":"Voorhees",
    "sg:classifiers":[
        {
            "category":"Professional",
            "type":"Services"
        }
    ],
    "sg:phone":"+1   ",
    "sg:postcode":"08043",
    "sg:province":"NJ",
    "wof:name":"Vic Wiedeman",
    "wof:placetype":"venue"
},
  "geometry": {"coordinates":[-74.926919,39.86344],"type":"Point"}
}