{
  "type": "Feature",
  "properties": {
    "addr:full":"705 10th Ave Belmar NJ 07719",
    "addr:housenumber":"705",
    "addr:postcode":"07719",
    "addr:street":"10Th Ave",
    "iso:country":"US",
    "sg:address":"705 10th Ave",
    "sg:city":"Belmar",
    "sg:classifiers":[
        {
            "category":"Restaurant",
            "type":"Food & Drink"
        }
    ],
    "sg:phone":"+1   ",
    "sg:postcode":"07719",
    "sg:province":"NJ",
    "sg:tags":[
        "eating"
    ],
    "wof:name":"Vesuvio Restaurant",
    "wof:placetype":"venue"
},
  "geometry": {"coordinates":[-74.02571500000001,40.179239],"type":"Point"}
}