{
  "type": "Feature",
  "properties": {
    "iso:country":"US",
    "sg:address":"1 Farragut Ln",
    "sg:city":"Old Bridge",
    "sg:classifiers":[
        {
            "category":"Building & Trades",
            "subcategory":"Construction",
            "type":"Services"
        }
    ],
    "sg:phone":"+1 732 521 2469",
    "sg:postcode":"08857",
    "sg:province":"NJ",
    "sg:tags":[
        "contractor"
    ],
    "wof:name":"Matchaponix Hills",
    "wof:placetype":"venue"
},
  "geometry": {"coordinates":[-74.363782,40.358311],"type":"Point"}
}