{
  "type": "Feature",
  "properties": {
    "iso:country":"US",
    "sg:address":"200 Ellen Ter",
    "sg:city":"Hackensack",
    "sg:classifiers":[
        {
            "category":"Building & Trades",
            "subcategory":"Construction",
            "type":"Services"
        }
    ],
    "sg:phone":"+1 201 525 1901",
    "sg:postcode":"07601",
    "sg:province":"NJ",
    "sg:tags":[
        "roofing",
        "contractor"
    ],
    "wof:name":"Mile Square Roofing Co Inc",
    "wof:placetype":"venue"
},
  "geometry": {"coordinates":[-74.0599,40.874652],"type":"Point"}
}