{
  "type": "Feature",
  "properties": {
    "iso:country":"US",
    "sg:address":"2802 S Broad St",
    "sg:city":"Trenton",
    "sg:classifiers":[
        {
            "category":"Real Estate",
            "subcategory":"Real Estate Agent",
            "type":"Services"
        }
    ],
    "sg:phone":"+1 609 888 3700",
    "sg:postcode":"08610",
    "sg:province":"NJ",
    "wof:name":"Home Locators",
    "wof:placetype":"venue"
},
  "geometry": {"coordinates":[-74.709508,40.190229],"type":"Point"}
}