{
  "type": "Feature",
  "properties": {
    "addr:full":"23 Austin St Ridgefield Park NJ 07660",
    "addr:housenumber":"23",
    "addr:postcode":"07660",
    "addr:street":"Austin St",
    "iso:country":"US",
    "sg:address":"23 Austin St",
    "sg:city":"Ridgefield Park",
    "sg:classifiers":[
        {
            "category":"Building & Trades",
            "subcategory":"Construction",
            "type":"Services"
        }
    ],
    "sg:phone":"+1 201 931 1222",
    "sg:postcode":"07660",
    "sg:province":"NJ",
    "sg:tags":[
        "builder",
        "repairer",
        "chimney"
    ],
    "wof:name":"Countryside Chimney Svc",
    "wof:placetype":"venue"
},
  "geometry": {"coordinates":[-74.02672099999999,40.861639],"type":"Point"}
}