{
  "type": "Feature",
  "properties": {
    "iso:country":"US",
    "sg:address":"502 Hillside Ter",
    "sg:city":"Pennsauken",
    "sg:classifiers":[
        {
            "category":"Health Services",
            "subcategory":"Doctor",
            "type":"Services"
        }
    ],
    "sg:phone":"+1 856 663 7874",
    "sg:postcode":"08110",
    "sg:province":"NJ",
    "sg:tags":[
        "practice",
        "family"
    ],
    "wof:name":"Style Daniel J DO",
    "wof:placetype":"venue"
},
  "geometry": {"coordinates":[-75.076599,39.9631],"type":"Point"}
}