{
  "type": "Feature",
  "properties": {
    "iso:country":"US",
    "sg:address":"1102 Boardwalk",
    "sg:city":"Ocean City",
    "sg:classifiers":[
        {
            "category":"Restaurant",
            "type":"Food & Drink"
        }
    ],
    "sg:phone":"+1   ",
    "sg:postcode":"08226",
    "sg:province":"NJ",
    "sg:tags":[
        "eating"
    ],
    "wof:name":"Primavera Pizza & Pasta",
    "wof:placetype":"venue"
},
  "geometry": {"coordinates":[-74.57772,39.273305],"type":"Point"}
}