{
  "type": "Feature",
  "properties": {
    "addr:full":"14 Ridgedale Ave Cedar Knolls NJ 07927",
    "addr:postcode":"07927",
    "addr:street":"Ridgedale Ave",
    "iso:country":"US",
    "sg:address":"14 Ridgedale Ave",
    "sg:city":"Cedar Knolls",
    "sg:classifiers":[
        {
            "category":"Wholesale",
            "subcategory":"Durable Goods & Equipment",
            "type":"Manufacturing & Wholesale Goods"
        },
        {
            "category":"Manufacturing",
            "subcategory":"Tools & Machinery",
            "type":"Manufacturing & Wholesale Goods"
        }
    ],
    "sg:phone":"+1 973 605 1144",
    "sg:postcode":"07927",
    "sg:province":"NJ",
    "sg:tags":[
        "industrial",
        "apparatus",
        "mfg",
        "electrical",
        "representative",
        "manufacturer"
    ],
    "wof:name":"Willgold Sales Corp",
    "wof:placetype":"venue"
},
  "geometry": {"coordinates":[-74.44508399999999,40.831748],"type":"Point"}
}