{
  "type": "Feature",
  "properties": {
    "addr:full":"3507 John F Kennedy Blvd Jersey City NJ 07307",
    "addr:housenumber":"3507",
    "addr:postcode":"07307",
    "addr:street":"John F Kennedy Blvd",
    "iso:country":"US",
    "sg:address":"3507 John F Kennedy Blvd",
    "sg:city":"Jersey City",
    "sg:classifiers":[
        {
            "category":"Travel",
            "subcategory":"Travel Agent",
            "type":"Entertainment"
        }
    ],
    "sg:phone":"+1 201 386 0333",
    "sg:postcode":"07307",
    "sg:province":"NJ",
    "sg:tags":[
        "agency",
        "bureau"
    ],
    "wof:name":"Air Budget Travel Inc",
    "wof:placetype":"venue"
},
  "geometry": {"coordinates":[-74.053274,40.752173],"type":"Point"}
}