{
  "type": "Feature",
  "properties": {
    "addr:full":"1130 Spring St Elizabeth NJ 07201",
    "addr:housenumber":"1130",
    "addr:postcode":"07201",
    "addr:street":"Spring St",
    "iso:country":"US",
    "sg:address":"1130 Spring St",
    "sg:city":"Elizabeth",
    "sg:classifiers":[
        {
            "category":"Freight",
            "type":"Transportation"
        }
    ],
    "sg:phone":"+1 212 267 3211",
    "sg:postcode":"07201",
    "sg:province":"NJ",
    "wof:name":"Mccullough Transportation",
    "wof:placetype":"venue"
},
  "geometry": {"coordinates":[-74.193749,40.683407],"type":"Point"}
}