{
  "type": "Feature",
  "properties": {
    "iso:country":"US",
    "sg:address":"589 Englishtown Rd",
    "sg:city":"Monroe Township",
    "sg:classifiers":[
        {
            "category":"Food & Beverages",
            "subcategory":"Fruits & Vegetables",
            "type":"Retail Goods"
        }
    ],
    "sg:phone":"+1   ",
    "sg:postcode":"08831",
    "sg:province":"NJ",
    "wof:name":"Forman Salter & Sons",
    "wof:placetype":"venue"
},
  "geometry": {"coordinates":[-74.361386,40.327006],"type":"Point"}
}