{
  "type": "Feature",
  "properties": {
    "iso:country":"US",
    "sg:address":"115 River Rd",
    "sg:city":"Edgewater",
    "sg:classifiers":[
        {
            "category":"Shopping",
            "subcategory":"Computers & Home Electronics",
            "type":"Retail Goods"
        }
    ],
    "sg:phone":"+1 201 941 1000",
    "sg:postcode":"07020",
    "sg:province":"NJ",
    "sg:tags":[
        "equipment",
        "dealer"
    ],
    "wof:name":"Investec Corp",
    "wof:placetype":"venue"
},
  "geometry": {"coordinates":[-73.991339,40.806422],"type":"Point"}
}