{
  "type": "Feature",
  "properties": {
    "addr:full":"55 University Ave Newark NJ 07102",
    "addr:housenumber":"55",
    "addr:postcode":"07102",
    "addr:street":"University Ave",
    "iso:country":"US",
    "sg:address":"55 University Ave",
    "sg:city":"Newark",
    "sg:classifiers":[
        {
            "category":"Food & Beverages",
            "subcategory":"Meat & Fish",
            "type":"Retail Goods"
        },
        {
            "category":"Wholesale",
            "subcategory":"Meat",
            "type":"Manufacturing & Wholesale Goods"
        }
    ],
    "sg:phone":"+1 973 621 7444",
    "sg:postcode":"07102",
    "sg:province":"NJ",
    "sg:tags":[
        "provisions"
    ],
    "wof:name":"U S Beef Co",
    "wof:placetype":"venue"
},
  "geometry": {"coordinates":[-74.172397,40.744939],"type":"Point"}
}