{
  "type": "Feature",
  "properties": {
    "iso:country":"US",
    "sg:address":"1980 State Rte 27",
    "sg:city":"Edison",
    "sg:classifiers":[
        {
            "category":"Personal",
            "type":"Services"
        }
    ],
    "sg:phone":"+1 732 287 3780",
    "sg:postcode":"08817",
    "sg:province":"NJ",
    "sg:tags":[
        "therapist",
        "massage"
    ],
    "wof:name":"New Health Facial & Massage",
    "wof:placetype":"venue"
},
  "geometry": {"coordinates":[-74.393745,40.521451],"type":"Point"}
}