{
  "type": "Feature",
  "properties": {
    "addr:full":"18 Matthew Dr Trenton NJ 08690",
    "addr:housenumber":"18",
    "addr:postcode":"08690",
    "addr:street":"Matthew Dr",
    "iso:country":"US",
    "sg:address":"18 Matthew Dr",
    "sg:city":"Trenton",
    "sg:classifiers":[
        {
            "category":"Retail",
            "subcategory":"Laundry & Dry Cleaning",
            "type":"Services"
        }
    ],
    "sg:phone":"+1   ",
    "sg:postcode":"08690",
    "sg:province":"NJ",
    "wof:name":"Custom Cleaning Service",
    "wof:placetype":"venue"
},
  "geometry": {"coordinates":[-74.64998300000001,40.229223],"type":"Point"}
}