{
  "type": "Feature",
  "properties": {
    "addr:full":"99 Viburnum Ter Red Bank NJ 07701",
    "addr:housenumber":"99",
    "addr:postcode":"07701",
    "addr:street":"Viburnum Ter",
    "iso:country":"US",
    "sg:address":"99 Viburnum Ter",
    "sg:city":"Red Bank",
    "sg:classifiers":[
        {
            "category":"Personal",
            "type":"Services"
        }
    ],
    "sg:phone":"+1   ",
    "sg:postcode":"07701",
    "sg:province":"NJ",
    "wof:name":"Laugh-Inc",
    "wof:placetype":"venue"
},
  "geometry": {"coordinates":[-74.111048,40.351397],"type":"Point"}
}