{
  "type": "Feature",
  "properties": {
    "addr:full":"7703 Maple Ave Pennsauken NJ 08109",
    "addr:housenumber":"7703",
    "addr:postcode":"08109",
    "addr:street":"Maple Ave",
    "iso:country":"US",
    "sg:address":"7703 Maple Ave",
    "sg:city":"Pennsauken",
    "sg:classifiers":[
        {
            "category":"Professional",
            "subcategory":"Accounting & Tax Preparation",
            "type":"Services"
        }
    ],
    "sg:phone":"+1 856 273 5883",
    "sg:postcode":"08109",
    "sg:province":"NJ",
    "sg:tags":[
        "accountant"
    ],
    "wof:name":"Gene Crawford CPA",
    "wof:placetype":"venue"
},
  "geometry": {"coordinates":[-75.026944,39.952862],"type":"Point"}
}