{
  "type": "Feature",
  "properties": {
    "addr:full":"317 Franklin Ave Ridgewood NJ 07450",
    "addr:housenumber":"317",
    "addr:postcode":"07450",
    "addr:street":"Franklin Ave",
    "iso:country":"US",
    "sg:address":"317 Franklin Ave",
    "sg:city":"Ridgewood",
    "sg:classifiers":[
        {
            "category":"Health Services",
            "subcategory":"Doctor",
            "type":"Services"
        }
    ],
    "sg:phone":"+1 201 447 1620",
    "sg:postcode":"07450",
    "sg:province":"NJ",
    "sg:tags":[
        "medical"
    ],
    "wof:name":"Ridgewood Gynecologic Assoc",
    "wof:placetype":"venue"
},
  "geometry": {"coordinates":[-74.110758,40.979319],"type":"Point"}
}