{
  "type": "Feature",
  "properties": {
    "iso:country":"US",
    "sg:address":"10 N California Ave",
    "sg:city":"Atlantic City",
    "sg:classifiers":[
        {
            "category":"Real Estate",
            "subcategory":"Real Estate Agent",
            "type":"Services"
        }
    ],
    "sg:phone":"+1 609 348 0909",
    "sg:postcode":"08401",
    "sg:province":"NJ",
    "sg:tags":[
        "broker"
    ],
    "wof:name":"Rafferty Real Estate Inc",
    "wof:placetype":"venue"
},
  "geometry": {"coordinates":[-74.44541700000001,39.356894],"type":"Point"}
}