{
  "type": "Feature",
  "properties": {
    "iso:country":"US",
    "sg:address":"247 N Washington Ave",
    "sg:city":"Bergenfield",
    "sg:classifiers":[
        {
            "category":"Autos & Motor Vehicles",
            "subcategory":"Automobile Sales",
            "type":"Retail Goods"
        }
    ],
    "sg:phone":"+1 201 385 6505",
    "sg:postcode":"07621",
    "sg:province":"NJ",
    "sg:tags":[
        "car",
        "dealer"
    ],
    "sg:website":"www.mullane-ford.com",
    "wof:name":"Mullane Ford",
    "wof:placetype":"venue"
},
  "geometry": {"coordinates":[-73.99502699999999,40.935747],"type":"Point"}
}