{
  "type": "Feature",
  "properties": {
    "iso:country":"US",
    "sg:address":"436 E Lakeshore Dr",
    "sg:city":"Highland Lakes",
    "sg:classifiers":[
        {
            "category":"Building & Trades",
            "subcategory":"Construction",
            "type":"Services"
        }
    ],
    "sg:phone":"+1 973 764 7304",
    "sg:postcode":"07422",
    "sg:province":"NJ",
    "sg:tags":[
        "paving",
        "asphalt"
    ],
    "wof:name":"Smith Brothers Paving",
    "wof:placetype":"venue"
},
  "geometry": {"coordinates":[-74.453052,41.164491],"type":"Point"}
}