{
  "type": "Feature",
  "properties": {
    "addr:full":"115 Humphrey St Englewood NJ 07631",
    "addr:housenumber":"115",
    "addr:postcode":"07631",
    "addr:street":"Humphrey St",
    "iso:country":"US",
    "sg:address":"115 Humphrey St",
    "sg:city":"Englewood",
    "sg:classifiers":[
        {
            "category":"Government",
            "subcategory":"Office",
            "type":"Public Place"
        }
    ],
    "sg:phone":"+1   ",
    "sg:postcode":"07631",
    "sg:province":"NJ",
    "sg:tags":[
        "housing",
        "program"
    ],
    "wof:name":"Housing Authority of City",
    "wof:placetype":"venue"
},
  "geometry": {"coordinates":[-73.981353,40.890063],"type":"Point"}
}