{
  "type": "Feature",
  "properties": {
    "addr:full":"201 Washington Crossing Pennington Rd Titusville NJ 08560",
    "addr:housenumber":"201",
    "addr:postcode":"08560",
    "addr:street":"Washington Crossing Pennington Rd",
    "iso:country":"US",
    "sg:address":"201 Washington Crossing Pennington Rd",
    "sg:city":"Titusville",
    "sg:classifiers":[
        {
            "category":"Professional",
            "subcategory":"Management & Consulting",
            "type":"Services"
        }
    ],
    "sg:phone":"+1 609 737 3100",
    "sg:postcode":"08560",
    "sg:province":"NJ",
    "sg:tags":[
        "fuel"
    ],
    "wof:name":"Emergency Management",
    "wof:placetype":"venue"
},
  "geometry": {"coordinates":[-74.81396599999999,40.308867],"type":"Point"}
}