{
  "type": "Feature",
  "properties": {
    "addr:full":"15 Worth St South Hackensack NJ 07606",
    "addr:housenumber":"15",
    "addr:postcode":"07606",
    "addr:street":"Worth St",
    "iso:country":"US",
    "sg:address":"15 Worth St",
    "sg:city":"South Hackensack",
    "sg:classifiers":[
        {
            "category":"Wholesale",
            "subcategory":"Electrical",
            "type":"Manufacturing & Wholesale Goods"
        }
    ],
    "sg:phone":"+1 201 488 9066",
    "sg:postcode":"07606",
    "sg:province":"NJ",
    "sg:tags":[
        "communication",
        "radio",
        "system"
    ],
    "wof:name":"On Site Communication",
    "wof:placetype":"venue"
},
  "geometry": {"coordinates":[-74.049683,40.872497],"type":"Point"}
}