{
  "type": "Feature",
  "properties": {
    "iso:country":"US",
    "sg:address":"1080 Garden State Rd",
    "sg:city":"Union",
    "sg:classifiers":[
        {
            "category":"Personal",
            "subcategory":"Adult",
            "type":"Services"
        }
    ],
    "sg:phone":"+1   ",
    "sg:postcode":"07083",
    "sg:province":"NJ",
    "wof:name":"Tele-Dating",
    "wof:placetype":"venue"
},
  "geometry": {"coordinates":[-74.303937,40.69162],"type":"Point"}
}