{
  "type": "Feature",
  "properties": {
    "addr:full":"12 Stirrup Ln Eatontown NJ 07724",
    "addr:housenumber":"12",
    "addr:postcode":"07724",
    "addr:street":"Stirrup Ln",
    "iso:country":"US",
    "sg:address":"12 Stirrup Ln",
    "sg:city":"Eatontown",
    "sg:classifiers":[
        {
            "category":"Wholesale",
            "subcategory":"Non-durable Goods",
            "type":"Manufacturing & Wholesale Goods"
        }
    ],
    "sg:phone":"+1 732 542 9305",
    "sg:postcode":"07724",
    "sg:province":"NJ",
    "wof:name":"Geroni Distribution Inc",
    "wof:placetype":"venue"
},
  "geometry": {"coordinates":[-74.040595,40.299155],"type":"Point"}
}