{
  "type": "Feature",
  "properties": {
    "addr:full":"263 Shell Rd Carneys Point NJ 08069",
    "addr:housenumber":"263",
    "addr:postcode":"08069",
    "addr:street":"Shell Rd",
    "iso:country":"US",
    "sg:address":"263 Shell Rd",
    "sg:city":"Carneys Point",
    "sg:classifiers":[
        {
            "category":"Autos & Motor Vehicles",
            "subcategory":"Automobile Sales",
            "type":"Retail Goods"
        }
    ],
    "sg:phone":"+1 856 351 0013",
    "sg:postcode":"08069",
    "sg:province":"NJ",
    "sg:tags":[
        "car",
        "dealer"
    ],
    "wof:name":"Troy Spencer Select Automobile",
    "wof:placetype":"venue"
},
  "geometry": {"coordinates":[-75.470697,39.71312],"type":"Point"}
}