{
  "type": "Feature",
  "properties": {
    "iso:country":"US",
    "sg:address":"2700 Allaire Rd",
    "sg:city":"Belmar",
    "sg:classifiers":[
        {
            "category":"Government",
            "subcategory":"Office",
            "type":"Public Place"
        }
    ],
    "sg:phone":"+1   ",
    "sg:postcode":"07719",
    "sg:province":"NJ",
    "sg:tags":[
        "general"
    ],
    "wof:name":"Pupil Personnel Svcs",
    "wof:placetype":"venue"
},
  "geometry": {"coordinates":[-74.065235,40.15278],"type":"Point"}
}