{
  "type": "Feature",
  "properties": {
    "iso:country":"US",
    "sg:address":"104 Continental Ave",
    "sg:city":"Belleville",
    "sg:classifiers":[
        {
            "category":"Wholesale",
            "subcategory":"Auto Parts",
            "type":"Manufacturing & Wholesale Goods"
        }
    ],
    "sg:phone":"+1 973 751 2404",
    "sg:postcode":"07109",
    "sg:province":"NJ",
    "wof:name":"Snap-On Tools",
    "wof:placetype":"venue"
},
  "geometry": {"coordinates":[-74.174654,40.800422],"type":"Point"}
}