{
  "type": "Feature",
  "properties": {
    "iso:country":"US",
    "sg:address":"219 Market St",
    "sg:city":"Perth Amboy",
    "sg:classifiers":[
        {
            "category":"Shopping",
            "subcategory":"Musical Instruments",
            "type":"Retail Goods"
        }
    ],
    "sg:phone":"+1 732 442 1532",
    "sg:postcode":"08861",
    "sg:province":"NJ",
    "sg:tags":[
        "music",
        "dealer"
    ],
    "wof:name":"King Music Store",
    "wof:placetype":"venue"
},
  "geometry": {"coordinates":[-74.273152,40.508167],"type":"Point"}
}