{
  "type": "Feature",
  "properties": {
    "iso:country":"US",
    "sg:address":"22 Grove St",
    "sg:city":"Somerville",
    "sg:classifiers":[
        {
            "category":"Government",
            "subcategory":"Police Station",
            "type":"Public Place"
        }
    ],
    "sg:phone":"+1   ",
    "sg:postcode":"08876",
    "sg:province":"NJ",
    "sg:tags":[
        "protection"
    ],
    "wof:name":"Somerset Co Sheriff",
    "wof:placetype":"venue"
},
  "geometry": {"coordinates":[-74.60963,40.568435],"type":"Point"}
}