{
  "type": "Feature",
  "properties": {
    "iso:country":"US",
    "sg:address":"224 S Orange Ave",
    "sg:city":"Newark",
    "sg:classifiers":[
        {
            "category":"Restaurant",
            "type":"Food & Drink"
        }
    ],
    "sg:phone":"+1   ",
    "sg:postcode":"07103",
    "sg:province":"NJ",
    "sg:tags":[
        "eating"
    ],
    "wof:name":"Berts Speedy Takeout",
    "wof:placetype":"venue"
},
  "geometry": {"coordinates":[-74.193085,40.738926],"type":"Point"}
}