{
  "type": "Feature",
  "properties": {
    "iso:country":"US",
    "sg:address":"10 S Monroe Ave",
    "sg:city":"Wenonah",
    "sg:classifiers":[
        {
            "category":"Building & Trades",
            "subcategory":"Plumbing",
            "type":"Services"
        }
    ],
    "sg:phone":"+1 856 468 6247",
    "sg:postcode":"08090",
    "sg:province":"NJ",
    "sg:tags":[
        "contractor"
    ],
    "wof:name":"Ed Ryan Heating & AC",
    "wof:placetype":"venue"
},
  "geometry": {"coordinates":[-75.152142,39.790562],"type":"Point"}
}