{
  "type": "Feature",
  "properties": {
    "iso:country":"US",
    "sg:address":"41 King Pl",
    "sg:city":"Closter",
    "sg:classifiers":[
        {
            "category":"Manufacturing",
            "subcategory":"Printing",
            "type":"Manufacturing & Wholesale Goods"
        }
    ],
    "sg:phone":"+1 201 784 1235",
    "sg:postcode":"07624",
    "sg:province":"NJ",
    "sg:tags":[
        "publisher"
    ],
    "wof:name":"Commodex",
    "wof:placetype":"venue"
},
  "geometry": {"coordinates":[-73.94776299999999,40.968097],"type":"Point"}
}