{
  "type": "Feature",
  "properties": {
    "addr:full":"167 Gould Ave Caldwell NJ 07006",
    "addr:housenumber":"167",
    "addr:postcode":"07006",
    "addr:street":"Gould Ave",
    "iso:country":"US",
    "sg:address":"167 Gould Ave",
    "sg:city":"Caldwell",
    "sg:classifiers":[
        {
            "category":"Travel",
            "subcategory":"Travel Agent",
            "type":"Entertainment"
        }
    ],
    "sg:phone":"+1 973 226 3661",
    "sg:postcode":"07006",
    "sg:province":"NJ",
    "sg:tags":[
        "consultant"
    ],
    "wof:name":"Ruth Asher Inc",
    "wof:placetype":"venue"
},
  "geometry": {"coordinates":[-74.265612,40.863488],"type":"Point"}
}