{
  "type": "Feature",
  "properties": {
    "addr:full":"8 S Union St Lambertville NJ 08530",
    "addr:housenumber":"8",
    "addr:postcode":"s;08530",
    "addr:street":"Union St",
    "iso:country":"US",
    "sg:address":"8 S Union St",
    "sg:city":"Lambertville",
    "sg:classifiers":[
        {
            "category":"Food & Beverages",
            "subcategory":"Liquor & Beverages",
            "type":"Retail Goods"
        }
    ],
    "sg:phone":"+1 609 397 0273",
    "sg:postcode":"08530",
    "sg:province":"NJ",
    "sg:tags":[
        "alcoholic",
        "wine"
    ],
    "wof:name":"Welsh's Liquor Store",
    "wof:placetype":"venue"
},
  "geometry": {"coordinates":[-74.944334,40.364283],"type":"Point"}
}