{
  "type": "Feature",
  "properties": {
    "iso:country":"US",
    "sg:address":"1500 Madrone Ave",
    "sg:city":"Williamstown",
    "sg:classifiers":[
        {
            "category":"Professional",
            "subcategory":"Management & Consulting",
            "type":"Services"
        }
    ],
    "sg:phone":"+1   ",
    "sg:postcode":"08094",
    "sg:province":"NJ",
    "sg:tags":[
        "business"
    ],
    "wof:name":"Olson Consulting LLC",
    "wof:placetype":"venue"
},
  "geometry": {"coordinates":[-74.964398,39.673764],"type":"Point"}
}