{
  "type": "Feature",
  "properties": {
    "addr:full":"583 Mc Keon St Perth Amboy NJ 08861",
    "addr:housenumber":"583",
    "addr:postcode":"08861",
    "addr:street":"Mc Keon St",
    "iso:country":"US",
    "sg:address":"583 Mc Keon St",
    "sg:city":"Perth Amboy",
    "sg:classifiers":[
        {
            "category":"Education",
            "subcategory":"School",
            "type":"Public Place"
        }
    ],
    "sg:phone":"+1 732 442 9533",
    "sg:postcode":"08861",
    "sg:province":"NJ",
    "wof:name":"Perth Amboy Catholic School",
    "wof:placetype":"venue"
},
  "geometry": {"coordinates":[-74.28784899999999,40.524028],"type":"Point"}
}