{
  "type": "Feature",
  "properties": {
    "iso:country":"US",
    "sg:address":"17 Lancaster Dr",
    "sg:city":"Asbury Park",
    "sg:classifiers":[
        {
            "category":"Professional",
            "subcategory":"Business Services",
            "type":"Services"
        }
    ],
    "sg:phone":"+1   ",
    "sg:postcode":"07712",
    "sg:province":"NJ",
    "wof:name":"Medical Savers Group",
    "wof:placetype":"venue"
},
  "geometry": {"coordinates":[-74.057633,40.24432],"type":"Point"}
}