{
  "type": "Feature",
  "properties": {
    "addr:full":"921 E Gibbsboro Rd Lindenwold NJ 08021",
    "addr:housenumber":"921",
    "addr:postcode":"08021",
    "addr:street":"E Gibbsboro Rd",
    "iso:country":"US",
    "sg:address":"921 E Gibbsboro Rd",
    "sg:city":"Lindenwold",
    "sg:classifiers":[
        {
            "category":"Retail",
            "subcategory":"Car Wash",
            "type":"Services"
        }
    ],
    "sg:phone":"+1 856 784 4418",
    "sg:postcode":"08021",
    "sg:province":"NJ",
    "sg:tags":[
        "polishing",
        "washing"
    ],
    "wof:name":"J K Wash Systems By J Kolinsky",
    "wof:placetype":"venue"
},
  "geometry": {"coordinates":[-74.976016,39.823672],"type":"Point"}
}