{
  "type": "Feature",
  "properties": {
    "addr:full":"268 Broadway Elmwood Park NJ 07407",
    "addr:housenumber":"268",
    "addr:postcode":"07407",
    "addr:street":"Broadway",
    "iso:country":"US",
    "sg:address":"268 Broadway",
    "sg:city":"Elmwood Park",
    "sg:classifiers":[
        {
            "category":"Retail",
            "subcategory":"Veterinary Services",
            "type":"Services"
        }
    ],
    "sg:phone":"+1 201 797 5300",
    "sg:postcode":"07407",
    "sg:province":"NJ",
    "sg:tags":[
        "hospital",
        "veterinarian",
        "animal"
    ],
    "wof:name":"Moldoff Douglas L Dvm",
    "wof:placetype":"venue"
},
  "geometry": {"coordinates":[-74.119232,40.920658],"type":"Point"}
}