{
  "type": "Feature",
  "properties": {
    "addr:full":"292 N Haledon Ave Haledon NJ 07508",
    "addr:housenumber":"292",
    "addr:postcode":"07508",
    "addr:street":"N Haledon Ave",
    "iso:country":"US",
    "sg:address":"292 N Haledon Ave",
    "sg:city":"Haledon",
    "sg:classifiers":[
        {
            "category":"Building & Trades",
            "subcategory":"Construction",
            "type":"Services"
        }
    ],
    "sg:phone":"+1 973 238 9225",
    "sg:postcode":"07508",
    "sg:province":"NJ",
    "sg:tags":[
        "asbestos",
        "specializing",
        "removal",
        "or",
        "contractor"
    ],
    "wof:name":"A Tech Restoration Inc",
    "wof:placetype":"venue"
},
  "geometry": {"coordinates":[-74.17246400000001,40.962648],"type":"Point"}
}