{
  "type": "Feature",
  "properties": {
    "addr:full":"213 E Ridgewood Ave Ridgewood NJ 07450",
    "addr:housenumber":"213",
    "addr:postcode":"07450",
    "addr:street":"E Ridgewood Ave",
    "iso:country":"US",
    "sg:address":"213 E Ridgewood Ave",
    "sg:city":"Ridgewood",
    "sg:classifiers":[
        {
            "category":"Real Estate",
            "subcategory":"Real Estate Agent",
            "type":"Services"
        }
    ],
    "sg:phone":"+1 201 445 1600",
    "sg:postcode":"07450",
    "sg:province":"NJ",
    "wof:name":"Gilsenan Real Estate Aprsrs",
    "wof:placetype":"venue"
},
  "geometry": {"coordinates":[-74.113439,40.978718],"type":"Point"}
}