{
  "type": "Feature",
  "properties": {
    "addr:full":"87 Mill St Bloomfield NJ 07003",
    "addr:housenumber":"87",
    "addr:postcode":"07003",
    "addr:street":"Mill St",
    "iso:country":"US",
    "sg:address":"87 Mill St",
    "sg:city":"Bloomfield",
    "sg:classifiers":[
        {
            "category":"Professional",
            "subcategory":"Research",
            "type":"Services"
        }
    ],
    "sg:phone":"+1   ",
    "sg:postcode":"07003",
    "sg:province":"NJ",
    "sg:tags":[
        "nonphysical",
        "commercial"
    ],
    "wof:name":"James M Sears Assoc",
    "wof:placetype":"venue"
},
  "geometry": {"coordinates":[-74.18976499999999,40.813552],"type":"Point"}
}