{
  "type": "Feature",
  "properties": {
    "addr:full":"11 Baylor St Toms River NJ 08757",
    "addr:housenumber":"11",
    "addr:postcode":"08757",
    "addr:street":"Baylor St",
    "iso:country":"US",
    "sg:address":"11 Baylor St",
    "sg:city":"Toms River",
    "sg:classifiers":[
        {
            "category":"Professional",
            "type":"Services"
        }
    ],
    "sg:phone":"+1 732 341 4532",
    "sg:postcode":"08757",
    "sg:province":"NJ",
    "sg:tags":[
        "establishment"
    ],
    "wof:name":"Emcon Associates Inc",
    "wof:placetype":"venue"
},
  "geometry": {"coordinates":[-74.21782399999999,39.935996],"type":"Point"}
}