{
  "type": "Feature",
  "properties": {
    "iso:country":"US",
    "sg:address":"25 Hemlock St",
    "sg:city":"Paterson",
    "sg:classifiers":[
        {
            "category":"Building & Trades",
            "subcategory":"Plumbing",
            "type":"Services"
        }
    ],
    "sg:phone":"+1 973 247 9444",
    "sg:postcode":"07503",
    "sg:province":"NJ",
    "sg:tags":[
        "contractor"
    ],
    "wof:name":"U-Save AC Rfrgn &",
    "wof:placetype":"venue"
},
  "geometry": {"coordinates":[-74.162733,40.900458],"type":"Point"}
}