{
  "type": "Feature",
  "properties": {
    "addr:full":"683 Iszard Ct Woodbury NJ 08096",
    "addr:housenumber":"683",
    "addr:postcode":"08096",
    "addr:street":"Iszard Ct",
    "iso:country":"US",
    "sg:address":"683 Iszard Ct",
    "sg:city":"Woodbury",
    "sg:classifiers":[
        {
            "category":"Building & Trades",
            "subcategory":"Construction",
            "type":"Services"
        }
    ],
    "sg:phone":"+1 856 251 2788",
    "sg:postcode":"08096",
    "sg:province":"NJ",
    "sg:tags":[
        "residential",
        "contracting"
    ],
    "wof:name":"T & P Energy Conservation Inc",
    "wof:placetype":"venue"
},
  "geometry": {"coordinates":[-75.14380800000001,39.823159],"type":"Point"}
}