{
  "type": "Feature",
  "properties": {
    "addr:full":"1081 Dove St Toms River NJ 08753",
    "addr:housenumber":"1081",
    "addr:postcode":"08753",
    "addr:street":"Dove St",
    "iso:country":"US",
    "sg:address":"1081 Dove St",
    "sg:city":"Toms River",
    "sg:classifiers":[
        {
            "category":"Professional",
            "type":"Services"
        }
    ],
    "sg:phone":"+1   ",
    "sg:postcode":"08753",
    "sg:province":"NJ",
    "wof:name":"Don Simone",
    "wof:placetype":"venue"
},
  "geometry": {"coordinates":[-74.14493899999999,39.970779],"type":"Point"}
}