{
  "type": "Feature",
  "properties": {
    "iso:country":"US",
    "sg:address":"47 Patton Dr",
    "sg:city":"East Brunswick",
    "sg:classifiers":[
        {
            "category":"Real Estate",
            "subcategory":"Real Estate Operator",
            "type":"Services"
        }
    ],
    "sg:phone":"+1   ",
    "sg:postcode":"08816",
    "sg:province":"NJ",
    "sg:tags":[
        "property",
        "lessor"
    ],
    "wof:name":"Enjay Associates",
    "wof:placetype":"venue"
},
  "geometry": {"coordinates":[-74.412842,40.479812],"type":"Point"}
}