{
  "type": "Feature",
  "properties": {
    "iso:country":"US",
    "sg:address":"42 Buchanan Rd",
    "sg:city":"Metuchen",
    "sg:classifiers":[
        {
            "category":"Shopping",
            "subcategory":"Bicycles & Sporting Goods",
            "type":"Retail Goods"
        }
    ],
    "sg:phone":"+1   ",
    "sg:postcode":"08840",
    "sg:province":"NJ",
    "wof:name":"All City Play Equipment Inc",
    "wof:placetype":"venue"
},
  "geometry": {"coordinates":[-74.36526000000001,40.552024],"type":"Point"}
}