{
  "type": "Feature",
  "properties": {
    "addr:full":"99 Academy St Piscataway NJ 08854",
    "addr:housenumber":"99",
    "addr:postcode":"08854",
    "addr:street":"Academy St",
    "iso:country":"US",
    "sg:address":"99 Academy St",
    "sg:city":"Piscataway",
    "sg:classifiers":[
        {
            "category":"Education",
            "subcategory":"School",
            "type":"Public Place"
        }
    ],
    "sg:phone":"+1   ",
    "sg:postcode":"08854",
    "sg:province":"NJ",
    "wof:name":"Quibbletown Middle School",
    "wof:placetype":"venue"
},
  "geometry": {"coordinates":[-74.45194100000001,40.574194],"type":"Point"}
}