{
  "type": "Feature",
  "properties": {
    "addr:full":"221 W Passaic St Rochelle Park NJ 07662",
    "addr:housenumber":"221",
    "addr:postcode":"07662",
    "addr:street":"W Passaic St",
    "iso:country":"US",
    "sg:address":"221 W Passaic St",
    "sg:city":"Rochelle Park",
    "sg:classifiers":[
        {
            "category":"Health Services",
            "subcategory":"Dentist",
            "type":"Services"
        }
    ],
    "sg:phone":"+1 201 843 2278",
    "sg:postcode":"07662",
    "sg:province":"NJ",
    "wof:name":"Rubin Alan L DMD",
    "wof:placetype":"venue"
},
  "geometry": {"coordinates":[-74.081074,40.913988],"type":"Point"}
}