{
  "type": "Feature",
  "properties": {
    "addr:full":"606 Valley Rd Chatham NJ 07928",
    "addr:housenumber":"606",
    "addr:postcode":"07928",
    "addr:street":"Valley Rd",
    "iso:country":"US",
    "sg:address":"606 Valley Rd",
    "sg:city":"Chatham",
    "sg:classifiers":[
        {
            "category":"Deli",
            "type":"Food & Drink"
        }
    ],
    "sg:phone":"+1 908 903 1818",
    "sg:postcode":"07928",
    "sg:province":"NJ",
    "wof:name":"America On Rye",
    "wof:placetype":"venue"
},
  "geometry": {"coordinates":[-74.40280199999999,40.724899],"type":"Point"}
}