{
  "type": "Feature",
  "properties": {
    "iso:country":"US",
    "sg:address":"89 Fostertown Rd",
    "sg:city":"Lumberton",
    "sg:classifiers":[
        {
            "category":"Recreation",
            "type":"Entertainment"
        }
    ],
    "sg:phone":"+1 609 261 2292",
    "sg:postcode":"08048",
    "sg:province":"NJ",
    "sg:tags":[
        "riding",
        "academy"
    ],
    "wof:name":"Fox Hunt Farm",
    "wof:placetype":"venue"
},
  "geometry": {"coordinates":[-74.80977,39.935058],"type":"Point"}
}