{
  "type": "Feature",
  "properties": {
    "addr:full":"705 Winslow Ave Cape May NJ 08204",
    "addr:housenumber":"705",
    "addr:postcode":"08204",
    "addr:street":"Winslow Ave",
    "iso:country":"US",
    "sg:address":"705 Winslow Ave",
    "sg:city":"Cape May",
    "sg:classifiers":[
        {
            "category":"Professional",
            "subcategory":"Accounting & Tax Preparation",
            "type":"Services"
        }
    ],
    "sg:phone":"+1 609 886 6958",
    "sg:postcode":"08204",
    "sg:province":"NJ",
    "sg:tags":[
        "accountant"
    ],
    "wof:name":"Mc Kinley C T Accountant",
    "wof:placetype":"venue"
},
  "geometry": {"coordinates":[-74.949799,38.974701],"type":"Point"}
}