{
  "type": "Feature",
  "properties": {
    "iso:country":"US",
    "sg:address":"417 7th St",
    "sg:city":"Carlstadt",
    "sg:classifiers":[
        {
            "category":"Building & Trades",
            "subcategory":"Construction",
            "type":"Services"
        }
    ],
    "sg:phone":"+1 201 460 3626",
    "sg:postcode":"07072",
    "sg:province":"NJ",
    "sg:tags":[
        "house"
    ],
    "wof:name":"Jrj Management & Construction",
    "wof:placetype":"venue"
},
  "geometry": {"coordinates":[-74.088697,40.837272],"type":"Point"}
}