{
  "type": "Feature",
  "properties": {
    "addr:full":"21 Black Horse Pike Pleasantville NJ 08232",
    "addr:housenumber":"21",
    "addr:postcode":"08232",
    "addr:street":"Black Horse Pike",
    "iso:country":"US",
    "sg:address":"21 Black Horse Pike",
    "sg:city":"Pleasantville",
    "sg:classifiers":[
        {
            "category":"Manufacturing",
            "subcategory":"Signs",
            "type":"Manufacturing & Wholesale Goods"
        }
    ],
    "sg:phone":"+1 609 383 2550",
    "sg:postcode":"08232",
    "sg:province":"NJ",
    "sg:tags":[
        "advertising",
        "specialty"
    ],
    "wof:name":"Signs Of Sobriety",
    "wof:placetype":"venue"
},
  "geometry": {"coordinates":[-74.521418,39.388914],"type":"Point"}
}