{
  "type": "Feature",
  "properties": {
    "addr:full":"1701 US Hwy 22 Watchung NJ 07069",
    "addr:housenumber":"1701",
    "addr:postcode":"07069",
    "addr:street":"Us Hwy 22",
    "iso:country":"US",
    "sg:address":"1701 US Hwy 22",
    "sg:city":"Watchung",
    "sg:classifiers":[
        {
            "category":"Food & Beverages",
            "subcategory":"Groceries & Convenience Stores",
            "type":"Retail Goods"
        }
    ],
    "sg:phone":"+1   ",
    "sg:postcode":"07069",
    "sg:province":"NJ",
    "wof:name":"Village Shop Rite 473",
    "wof:placetype":"venue"
},
  "geometry": {"coordinates":[-74.409927,40.646056],"type":"Point"}
}