{
  "type": "Feature",
  "properties": {
    "addr:full":"806 Shunpike Rd Cape May NJ 08204",
    "addr:housenumber":"806",
    "addr:postcode":"08204",
    "addr:street":"Shunpike Rd",
    "iso:country":"US",
    "sg:address":"806 Shunpike Rd",
    "sg:city":"Cape May",
    "sg:classifiers":[
        {
            "category":"Organizations",
            "subcategory":"Religious Organization",
            "type":"Services"
        }
    ],
    "sg:phone":"+1 609 884 8495",
    "sg:postcode":"08204",
    "sg:province":"NJ",
    "sg:tags":[
        "church"
    ],
    "wof:name":"Shore Points Presbyterian",
    "wof:placetype":"venue"
},
  "geometry": {"coordinates":[-74.923113,38.976722],"type":"Point"}
}