{
  "type": "Feature",
  "properties": {
    "iso:country":"US",
    "sg:address":"201 State Rte 17",
    "sg:city":"Paramus",
    "sg:classifiers":[
        {
            "category":"Home & Garden",
            "subcategory":"Building Materials",
            "type":"Retail Goods"
        },
        {
            "category":"Shopping",
            "type":"Retail Goods"
        }
    ],
    "sg:phone":"+1 201 262 1407",
    "sg:postcode":"07652",
    "sg:province":"NJ",
    "sg:tags":[
        "plumbing",
        "fixture",
        "business",
        "supply"
    ],
    "sg:website":"www.davidsons.com",
    "wof:name":"Davidson Plumbing Supply Inc",
    "wof:placetype":"venue"
},
  "geometry": {"coordinates":[-74.070837,40.909936],"type":"Point"}
}