{
  "type": "Feature",
  "properties": {
    "addr:full":"72 Canoe Brook Pkwy Summit NJ 07901",
    "addr:housenumber":"72",
    "addr:postcode":"07901",
    "addr:street":"Canoe Brook Pkwy",
    "iso:country":"US",
    "sg:address":"72 Canoe Brook Pkwy",
    "sg:city":"Summit",
    "sg:classifiers":[
        {
            "category":"Professional",
            "subcategory":"Management & Consulting",
            "type":"Services"
        }
    ],
    "sg:phone":"+1   ",
    "sg:postcode":"07901",
    "sg:province":"NJ",
    "sg:tags":[
        "business"
    ],
    "wof:name":"Lorna Gordon Design Consultant",
    "wof:placetype":"venue"
},
  "geometry": {"coordinates":[-74.368042,40.733703],"type":"Point"}
}