{
  "type": "Feature",
  "properties": {
    "addr:full":"30 Riveredge Rd Tenafly NJ 07670",
    "addr:housenumber":"30",
    "addr:postcode":"07670",
    "addr:street":"Riveredge Rd",
    "iso:country":"US",
    "sg:address":"30 Riveredge Rd",
    "sg:city":"Tenafly",
    "sg:classifiers":[
        {
            "category":"Banks & Credit Unions",
            "subcategory":"Bank",
            "type":"Services"
        }
    ],
    "sg:phone":"+1 201 568 7788",
    "sg:postcode":"07670",
    "sg:province":"NJ",
    "sg:tags":[
        "loan",
        "real estate"
    ],
    "wof:name":"First Metropolitan Mortgage",
    "wof:placetype":"venue"
},
  "geometry": {"coordinates":[-73.966261,40.926736],"type":"Point"}
}