{
  "type": "Feature",
  "properties": {
    "iso:country":"US",
    "sg:address":"157 Thompson Bridge Rd",
    "sg:city":"Jackson",
    "sg:classifiers":[
        {
            "category":"Building & Trades",
            "subcategory":"Landscaping Services",
            "type":"Services"
        }
    ],
    "sg:phone":"+1 732 928 5710",
    "sg:postcode":"08527",
    "sg:province":"NJ",
    "wof:name":"Lawn Boss Landscaping",
    "wof:placetype":"venue"
},
  "geometry": {"coordinates":[-74.381097,40.112445],"type":"Point"}
}