{
  "type": "Feature",
  "properties": {
    "iso:country":"US",
    "sg:address":"206 Chestnut St",
    "sg:city":"Roselle",
    "sg:classifiers":[
        {
            "category":"Personal",
            "subcategory":"Beauty Salon",
            "type":"Services"
        }
    ],
    "sg:phone":"+1 908 298 8007",
    "sg:postcode":"07203",
    "sg:province":"NJ",
    "sg:tags":[
        "shop"
    ],
    "wof:name":"All Eyes On Me",
    "wof:placetype":"venue"
},
  "geometry": {"coordinates":[-74.263103,40.657655],"type":"Point"}
}