{
  "type": "Feature",
  "properties": {
    "addr:full":"437 Atlantic City Blvd Bayville NJ 08721",
    "addr:housenumber":"437",
    "addr:postcode":"08721",
    "addr:street":"Atlantic City Blvd",
    "iso:country":"US",
    "sg:address":"437 Atlantic City Blvd",
    "sg:city":"Bayville",
    "sg:classifiers":[
        {
            "category":"Food & Beverages",
            "subcategory":"Liquor & Beverages",
            "type":"Retail Goods"
        }
    ],
    "sg:phone":"+1 732 269 6666",
    "sg:postcode":"08721",
    "sg:province":"NJ",
    "wof:name":"Friendly's Bar & Grill",
    "wof:placetype":"venue"
},
  "geometry": {"coordinates":[-74.15440599999999,39.914594],"type":"Point"}
}