{
  "type": "Feature",
  "properties": {
    "addr:full":"1973 State Rte 34 Wall NJ 07719",
    "addr:housenumber":"1973",
    "addr:postcode":"07719",
    "addr:street":"State Rte 34",
    "iso:country":"US",
    "sg:address":"1973 State Rte 34",
    "sg:city":"Wall",
    "sg:classifiers":[
        {
            "category":"Professional",
            "subcategory":"Accounting & Tax Preparation",
            "type":"Services"
        }
    ],
    "sg:phone":"+1 732 974 8717",
    "sg:postcode":"07719",
    "sg:province":"NJ",
    "sg:tags":[
        "accountant"
    ],
    "wof:name":"Mc Guigan Tombs & Co",
    "wof:placetype":"venue"
},
  "geometry": {"coordinates":[-74.098406,40.154223],"type":"Point"}
}