{
  "type": "Feature",
  "properties": {
    "addr:full":"47 Intervale Rd Boonton NJ 07005",
    "addr:housenumber":"47",
    "addr:postcode":"07005",
    "addr:street":"Intervale Rd",
    "iso:country":"US",
    "sg:address":"47 Intervale Rd",
    "sg:city":"Boonton",
    "sg:classifiers":[
        {
            "category":"Travel",
            "subcategory":"Hotels & Motels",
            "type":"Entertainment"
        }
    ],
    "sg:phone":"+1 973 335 1555",
    "sg:postcode":"07005",
    "sg:province":"NJ",
    "wof:name":"Saand.Com",
    "wof:placetype":"venue"
},
  "geometry": {"coordinates":[-74.41977199999999,40.892086],"type":"Point"}
}