{
  "type": "Feature",
  "properties": {
    "addr:full":"218 Schanck Rd Freehold NJ 07728",
    "addr:housenumber":"218",
    "addr:postcode":"07728",
    "addr:street":"Schanck Rd",
    "iso:country":"US",
    "sg:address":"218 Schanck Rd",
    "sg:city":"Freehold",
    "sg:classifiers":[
        {
            "category":"Real Estate",
            "subcategory":"Real Estate Agent",
            "type":"Services"
        }
    ],
    "sg:phone":"+1 732 308 1770",
    "sg:postcode":"07728",
    "sg:province":"NJ",
    "wof:name":"A K Property Management",
    "wof:placetype":"venue"
},
  "geometry": {"coordinates":[-74.286675,40.237838],"type":"Point"}
}