{
  "type": "Feature",
  "properties": {
    "addr:full":"313 E Glenwood Ave Wildwood NJ 08260",
    "addr:housenumber":"313",
    "addr:postcode":"08260",
    "addr:street":"E Glenwood Ave",
    "iso:country":"US",
    "sg:address":"313 E Glenwood Ave",
    "sg:city":"Wildwood",
    "sg:classifiers":[
        {
            "category":"Real Estate",
            "subcategory":"Real Estate Operator",
            "type":"Services"
        }
    ],
    "sg:phone":"+1 609 522 8241",
    "sg:postcode":"08260",
    "sg:province":"NJ",
    "sg:tags":[
        "motel",
        "apartment",
        "rental",
        "hotel"
    ],
    "sg:website":"www.sunflowermotel.com",
    "wof:name":"Sunflower Motel",
    "wof:placetype":"venue"
},
  "geometry": {"coordinates":[-74.808601,38.990299],"type":"Point"}
}