{
  "type": "Feature",
  "properties": {
    "addr:full":"1358 Stelton Rd Piscataway NJ 08854",
    "addr:housenumber":"1358",
    "addr:postcode":"08854",
    "addr:street":"Stelton Rd",
    "iso:country":"US",
    "sg:address":"1358 Stelton Rd",
    "sg:city":"Piscataway",
    "sg:classifiers":[
        {
            "category":"Home & Garden",
            "subcategory":"Building Materials",
            "type":"Retail Goods"
        }
    ],
    "sg:phone":"+1   ",
    "sg:postcode":"08854",
    "sg:province":"NJ",
    "sg:tags":[
        "custom",
        "vanity",
        "kitchen",
        "bathroom",
        "cabinet"
    ],
    "wof:name":"Stelton Cabinet & Supply Co",
    "wof:placetype":"venue"
},
  "geometry": {"coordinates":[-74.422012,40.538159],"type":"Point"}
}