{
  "type": "Feature",
  "properties": {
    "addr:full":"472 Tomlinson Ave Clementon NJ 08021",
    "addr:housenumber":"472",
    "addr:postcode":"08021",
    "addr:street":"Tomlinson Ave",
    "iso:country":"US",
    "sg:address":"472 Tomlinson Ave",
    "sg:city":"Clementon",
    "sg:classifiers":[
        {
            "category":"Shopping",
            "subcategory":"Clothing, Apparel, & Fashions",
            "type":"Retail Goods"
        }
    ],
    "sg:phone":"+1   ",
    "sg:postcode":"08021",
    "sg:province":"NJ",
    "sg:tags":[
        "family"
    ],
    "wof:name":"Approach Outfitters",
    "wof:placetype":"venue"
},
  "geometry": {"coordinates":[-75.00592399999999,39.821387],"type":"Point"}
}