{
  "type": "Feature",
  "properties": {
    "iso:country":"US",
    "sg:address":"66 Fadem Rd",
    "sg:city":"Springfield",
    "sg:classifiers":[
        {
            "category":"Wholesale",
            "subcategory":"Groceries",
            "type":"Manufacturing & Wholesale Goods"
        }
    ],
    "sg:phone":"+1 973 467 9400",
    "sg:postcode":"07081",
    "sg:province":"NJ",
    "sg:tags":[
        "food",
        "product"
    ],
    "sg:website":"www.walkerfoods.com",
    "wof:name":"Blue Grass Farms Inc",
    "wof:placetype":"venue"
},
  "geometry": {"coordinates":[-74.313419,40.682546],"type":"Point"}
}