{
  "type": "Feature",
  "properties": {
    "iso:country":"US",
    "sg:address":"90 Millburn Ave",
    "sg:city":"Millburn",
    "sg:classifiers":[
        {
            "category":"Health Services",
            "subcategory":"Doctor",
            "type":"Services"
        }
    ],
    "sg:phone":"+1 973 378 7990",
    "sg:postcode":"07041",
    "sg:province":"NJ",
    "sg:tags":[
        "physician",
        "surgeon"
    ],
    "wof:name":"Lubin LA Conti & Gruenwald",
    "wof:placetype":"venue"
},
  "geometry": {"coordinates":[-74.28598100000001,40.72271],"type":"Point"}
}