{
  "type": "Feature",
  "properties": {
    "iso:country":"US",
    "sg:address":"100 Chews Landing Rd",
    "sg:city":"Haddonfield",
    "sg:classifiers":[
        {
            "category":"Health Services",
            "subcategory":"Doctor",
            "type":"Services"
        }
    ],
    "sg:phone":"+1 856 354 8101",
    "sg:postcode":"08033",
    "sg:province":"NJ",
    "sg:tags":[
        "surgeon",
        "oral"
    ],
    "wof:name":"Colalillo Alex Jr DDS",
    "wof:placetype":"venue"
},
  "geometry": {"coordinates":[-75.041397,39.892601],"type":"Point"}
}