{
  "type": "Feature",
  "properties": {
    "iso:country":"US",
    "sg:address":"101 Woodport Rd",
    "sg:city":"Sparta",
    "sg:classifiers":[
        {
            "category":"Banks & Credit Unions",
            "subcategory":"Investment Brokerage",
            "type":"Services"
        }
    ],
    "sg:phone":"+1   ",
    "sg:postcode":"07871",
    "sg:province":"NJ",
    "sg:tags":[
        "security"
    ],
    "wof:name":"Baytree Investors Inc",
    "wof:placetype":"venue"
},
  "geometry": {"coordinates":[-74.63511099999999,41.029987],"type":"Point"}
}