{
  "type": "Feature",
  "properties": {
    "iso:country":"US",
    "sg:address":"49 Orchard St",
    "sg:city":"Hackensack",
    "sg:classifiers":[
        {
            "category":"Building & Trades",
            "subcategory":"Construction",
            "type":"Services"
        }
    ],
    "sg:phone":"+1 201 488 2277",
    "sg:postcode":"07601",
    "sg:province":"NJ",
    "sg:tags":[
        "down",
        "spout",
        "gutter",
        "contractor"
    ],
    "wof:name":"AC Maintenance Contractors",
    "wof:placetype":"venue"
},
  "geometry": {"coordinates":[-74.039147,40.904989],"type":"Point"}
}