{
  "type": "Feature",
  "properties": {
    "iso:country":"US",
    "sg:address":"947 State Rd",
    "sg:city":"Princeton",
    "sg:classifiers":[
        {
            "category":"Personal",
            "type":"Services"
        }
    ],
    "sg:phone":"+1 609 279 1679",
    "sg:postcode":"08540",
    "sg:province":"NJ",
    "sg:tags":[
        "miscellaneous"
    ],
    "wof:name":"J Parnett",
    "wof:placetype":"venue"
},
  "geometry": {"coordinates":[-74.650243,40.401716],"type":"Point"}
}