{
  "type": "Feature",
  "properties": {
    "iso:country":"US",
    "sg:address":"115 Leslie St",
    "sg:city":"Newark",
    "sg:classifiers":[
        {
            "category":"Social Services",
            "subcategory":"Child Care",
            "type":"Services"
        }
    ],
    "sg:phone":"+1 973 375 7359",
    "sg:postcode":"07112",
    "sg:province":"NJ",
    "sg:tags":[
        "day"
    ],
    "wof:name":"First Zion Hill Preschool",
    "wof:placetype":"venue"
},
  "geometry": {"coordinates":[-74.21563399999999,40.7187],"type":"Point"}
}