{
  "type": "Feature",
  "properties": {
    "addr:full":"64 Main St Madison NJ 07940",
    "addr:housenumber":"64",
    "addr:postcode":"07940",
    "addr:street":"Main St",
    "iso:country":"US",
    "sg:address":"64 Main St",
    "sg:city":"Madison",
    "sg:classifiers":[
        {
            "category":"Professional",
            "subcategory":"Business Services",
            "type":"Services"
        }
    ],
    "sg:phone":"+1 973 377 7536",
    "sg:postcode":"07940",
    "sg:province":"NJ",
    "sg:tags":[
        "interior",
        "consultant",
        "design",
        "decorator"
    ],
    "wof:name":"Garo Interiors Inc",
    "wof:placetype":"venue"
},
  "geometry": {"coordinates":[-74.415305,40.759071],"type":"Point"}
}