{
  "type": "Feature",
  "properties": {
    "addr:full":"70 Hudson St Hoboken NJ 07030",
    "addr:housenumber":"70",
    "addr:postcode":"07030",
    "addr:street":"Hudson St",
    "iso:country":"US",
    "sg:address":"70 Hudson St",
    "sg:city":"Hoboken",
    "sg:classifiers":[
        {
            "category":"Banks & Credit Unions",
            "subcategory":"Investment Brokerage",
            "type":"Services"
        }
    ],
    "sg:phone":"+1 201 610 0429",
    "sg:postcode":"07030",
    "sg:province":"NJ",
    "sg:tags":[
        "advisory",
        "financial"
    ],
    "wof:name":"Wall Street Financial Corp",
    "wof:placetype":"venue"
},
  "geometry": {"coordinates":[-74.03009400000001,40.736539],"type":"Point"}
}