{
  "type": "Feature",
  "properties": {
    "addr:full":"42 Gesner St Linden NJ 07036",
    "addr:housenumber":"42",
    "addr:postcode":"07036",
    "addr:street":"Gesner St",
    "iso:country":"US",
    "sg:address":"42 Gesner St",
    "sg:city":"Linden",
    "sg:classifiers":[
        {
            "category":"Professional",
            "subcategory":"Lawyer & Legal Services",
            "type":"Services"
        }
    ],
    "sg:phone":"+1 908 486 3181",
    "sg:postcode":"07036",
    "sg:province":"NJ",
    "sg:tags":[
        "attorney"
    ],
    "wof:name":"Mears Law Firm",
    "wof:placetype":"venue"
},
  "geometry": {"coordinates":[-74.263953,40.634822],"type":"Point"}
}