{
  "type": "Feature",
  "properties": {
    "addr:full":"73 Main St South Amboy NJ 08879",
    "addr:housenumber":"73",
    "addr:postcode":"08879",
    "addr:street":"Main St",
    "iso:country":"US",
    "sg:address":"73 Main St",
    "sg:city":"South Amboy",
    "sg:classifiers":[
        {
            "category":"Restaurant",
            "type":"Food & Drink"
        }
    ],
    "sg:phone":"+1 732 721 0033",
    "sg:postcode":"08879",
    "sg:province":"NJ",
    "sg:tags":[
        "caterer"
    ],
    "wof:name":"Mr Mom's",
    "wof:placetype":"venue"
},
  "geometry": {"coordinates":[-74.289089,40.492538],"type":"Point"}
}