{
  "type": "Feature",
  "properties": {
    "addr:full":"970 Main St Fords NJ 08863",
    "addr:housenumber":"970",
    "addr:postcode":"08863",
    "addr:street":"Main St",
    "iso:country":"US",
    "sg:address":"970 Main St",
    "sg:city":"Fords",
    "sg:classifiers":[
        {
            "category":"Food & Beverages",
            "subcategory":"Groceries & Convenience Stores",
            "type":"Retail Goods"
        }
    ],
    "sg:phone":"+1 732 738 5595",
    "sg:postcode":"08863",
    "sg:province":"NJ",
    "wof:name":"Neighborhood Convenience Store",
    "wof:placetype":"venue"
},
  "geometry": {"coordinates":[-74.317014,40.536468],"type":"Point"}
}