{
  "type": "Feature",
  "properties": {
    "addr:full":"16 All Saints Rd Princeton NJ 08540",
    "addr:housenumber":"16",
    "addr:postcode":"08540",
    "addr:street":"All Saints Rd",
    "iso:country":"US",
    "sg:address":"16 All Saints Rd",
    "sg:city":"Princeton",
    "sg:classifiers":[
        {
            "category":"Organizations",
            "subcategory":"Religious Organization",
            "type":"Services"
        }
    ],
    "sg:phone":"+1 609 921 2420",
    "sg:postcode":"08540",
    "sg:province":"NJ",
    "sg:tags":[
        "cemetery",
        "church"
    ],
    "sg:website":"www.allsaint.org",
    "wof:name":"All Saints Church",
    "wof:placetype":"venue"
},
  "geometry": {"coordinates":[-74.643466,40.374538],"type":"Point"}
}