{
  "type": "Feature",
  "properties": {
    "addr:full":"292 Main St Ste 2 Hackensack NJ 07601",
    "addr:housenumber":"292",
    "addr:postcode":"07601",
    "addr:street":"Main St Ste 2",
    "iso:country":"US",
    "sg:address":"292 Main St Ste 2",
    "sg:city":"Hackensack",
    "sg:classifiers":[
        {
            "category":"Professional",
            "subcategory":"Lawyer & Legal Services",
            "type":"Services"
        }
    ],
    "sg:phone":"+1 201 488 2211",
    "sg:postcode":"07601",
    "sg:province":"NJ",
    "wof:name":"Meyers Joseph V Attorney",
    "wof:placetype":"venue"
},
  "geometry": {"coordinates":[-74.041,40.887501],"type":"Point"}
}