{
  "type": "Feature",
  "properties": {
    "addr:full":"254 Mountain Ave Hackettstown NJ 07840",
    "addr:housenumber":"254",
    "addr:postcode":"07840",
    "addr:street":"Mountain Ave",
    "iso:country":"US",
    "sg:address":"254 Mountain Ave",
    "sg:city":"Hackettstown",
    "sg:classifiers":[
        {
            "category":"Health Services",
            "subcategory":"Doctor",
            "type":"Services"
        }
    ],
    "sg:phone":"+1 908 850 5505",
    "sg:postcode":"07840",
    "sg:province":"NJ",
    "sg:tags":[
        "physician",
        "surgeon"
    ],
    "wof:name":"Neuro Specialist-Morris Sussex",
    "wof:placetype":"venue"
},
  "geometry": {"coordinates":[-74.82343299999999,40.838502],"type":"Point"}
}