{
  "type": "Feature",
  "properties": {
    "iso:country":"US",
    "sg:address":"256 Barrington Dr",
    "sg:city":"Bridgewater",
    "sg:classifiers":[
        {
            "category":"Professional",
            "subcategory":"Business Services",
            "type":"Services"
        }
    ],
    "sg:phone":"+1   ",
    "sg:postcode":"08807",
    "sg:province":"NJ",
    "wof:name":"Ataya Enterprises Inc",
    "wof:placetype":"venue"
},
  "geometry": {"coordinates":[-74.659171,40.607725],"type":"Point"}
}