{
  "type": "Feature",
  "properties": {
    "iso:country":"US",
    "sg:address":"300 2nd Ave",
    "sg:city":"Long Branch",
    "sg:classifiers":[
        {
            "category":"Health Services",
            "subcategory":"Doctor",
            "type":"Services"
        }
    ],
    "sg:phone":"+1 732 923 7830",
    "sg:postcode":"07740",
    "sg:province":"NJ",
    "sg:tags":[
        "physician",
        "surgeon"
    ],
    "wof:name":"Cranmer Ambulatory Surgery Ctr",
    "wof:placetype":"venue"
},
  "geometry": {"coordinates":[-73.98378599999999,40.294379],"type":"Point"}
}