{
  "type": "Feature",
  "properties": {
    "iso:country":"US",
    "sg:address":"561 Hillcrest Ave",
    "sg:city":"Westfield",
    "sg:classifiers":[
        {
            "category":"Professional",
            "subcategory":"Business Services",
            "type":"Services"
        }
    ],
    "sg:phone":"+1   ",
    "sg:postcode":"07090",
    "sg:province":"NJ",
    "sg:tags":[
        "recording",
        "studio"
    ],
    "sg:website":"www.sharpnine.com",
    "wof:name":"Sharp Nine Records Inc",
    "wof:placetype":"venue"
},
  "geometry": {"coordinates":[-74.337227,40.652227],"type":"Point"}
}