{
  "type": "Feature",
  "properties": {
    "addr:full":"235 Edwards Ave Long Branch NJ 07740",
    "addr:housenumber":"235",
    "addr:postcode":"07740",
    "addr:street":"Edwards Ave",
    "iso:country":"US",
    "sg:address":"235 Edwards Ave",
    "sg:city":"Long Branch",
    "sg:classifiers":[
        {
            "category":"Professional",
            "subcategory":"Advertising",
            "type":"Services"
        }
    ],
    "sg:phone":"+1 732 571 2331",
    "sg:postcode":"07740",
    "sg:province":"NJ",
    "sg:tags":[
        "counselor",
        "agency"
    ],
    "wof:name":"Lee Bennett Assoc",
    "wof:placetype":"venue"
},
  "geometry": {"coordinates":[-74.002009,40.309984],"type":"Point"}
}