{
  "type": "Feature",
  "properties": {
    "iso:country":"US",
    "sg:address":"601 Atlantic Ave",
    "sg:city":"Atlantic City",
    "sg:classifiers":[
        {
            "category":"Professional",
            "subcategory":"Testing Lab",
            "type":"Services"
        }
    ],
    "sg:phone":"+1 609 348 3520",
    "sg:postcode":"08401",
    "sg:province":"NJ",
    "sg:tags":[
        "laboratory"
    ],
    "wof:name":"US Engineering Laboratories",
    "wof:placetype":"venue"
},
  "geometry": {"coordinates":[-74.41925999999999,39.365673],"type":"Point"}
}