{
  "type": "Feature",
  "properties": {
    "addr:full":"151 Passaic St Passaic NJ 07055",
    "addr:housenumber":"151",
    "addr:postcode":"07055",
    "addr:street":"Passaic St",
    "iso:country":"US",
    "sg:address":"151 Passaic St",
    "sg:city":"Passaic",
    "sg:classifiers":[
        {
            "category":"Travel",
            "subcategory":"Travel Agent",
            "type":"Entertainment"
        }
    ],
    "sg:phone":"+1 973 458 9955",
    "sg:postcode":"07055",
    "sg:province":"NJ",
    "sg:tags":[
        "agency"
    ],
    "wof:name":"G Q Multi Service",
    "wof:placetype":"venue"
},
  "geometry": {"coordinates":[-74.114999,40.862186],"type":"Point"}
}