{
  "type": "Feature",
  "properties": {
    "addr:full":"128 Sooy Place Rd Tabernacle NJ 08088",
    "addr:housenumber":"128",
    "addr:postcode":"08088",
    "addr:street":"Sooy Place Rd",
    "iso:country":"US",
    "sg:address":"128 Sooy Place Rd",
    "sg:city":"Tabernacle",
    "sg:classifiers":[
        {
            "category":"Home & Garden",
            "subcategory":"Garden Supply",
            "type":"Retail Goods"
        }
    ],
    "sg:phone":"+1 609 859 2004",
    "sg:postcode":"08088",
    "sg:province":"NJ",
    "sg:tags":[
        "nurseryman"
    ],
    "wof:name":"Greenwood Nursery",
    "wof:placetype":"venue"
},
  "geometry": {"coordinates":[-74.662289,39.873885],"type":"Point"}
}