{
  "type": "Feature",
  "properties": {
    "iso:country":"US",
    "sg:address":"25 Rosedale Ave",
    "sg:city":"Morris Plains",
    "sg:classifiers":[
        {
            "category":"Health Services",
            "subcategory":"Health Practitioner",
            "type":"Services"
        }
    ],
    "sg:phone":"+1 973 539 0543",
    "sg:postcode":"07950",
    "sg:province":"NJ",
    "sg:tags":[
        "nurse",
        "registry"
    ],
    "wof:name":"James Ketch Jr",
    "wof:placetype":"venue"
},
  "geometry": {"coordinates":[-74.481762,40.823872],"type":"Point"}
}