{
  "type": "Feature",
  "properties": {
    "iso:country":"US",
    "sg:address":"30 Montgomery",
    "sg:city":"Jersey City",
    "sg:classifiers":[
        {
            "category":"Banks & Credit Unions",
            "subcategory":"Investment Brokerage",
            "type":"Services"
        }
    ],
    "sg:phone":"+1 201 433 3500",
    "sg:postcode":"07302",
    "sg:province":"NJ",
    "sg:tags":[
        "investing"
    ],
    "sg:website":"www.guzman.com",
    "wof:name":"Guzman & Company",
    "wof:placetype":"venue"
},
  "geometry": {"coordinates":[-74.058161,40.720754],"type":"Point"}
}