{
  "type": "Feature",
  "properties": {
    "addr:full":"15 Springhill Rd Mantua NJ 08051",
    "addr:housenumber":"15",
    "addr:postcode":"08051",
    "addr:street":"Springhill Rd",
    "iso:country":"US",
    "sg:address":"15 Springhill Rd",
    "sg:city":"Mantua",
    "sg:classifiers":[
        {
            "category":"Science Facility",
            "type":"Public Place"
        }
    ],
    "sg:phone":"+1 609 352 7066",
    "sg:postcode":"08051",
    "sg:province":"NJ",
    "sg:tags":[
        "development",
        "laboratories-research"
    ],
    "wof:name":"Suncatcher Clean Energy",
    "wof:placetype":"venue"
},
  "geometry": {"coordinates":[-75.187152,39.794983],"type":"Point"}
}