{
  "type": "Feature",
  "properties": {
    "iso:country":"US",
    "sg:address":"663 Prospect St",
    "sg:city":"Glen Rock",
    "sg:classifiers":[
        {
            "category":"Wholesale",
            "subcategory":"Medical Equipment & Supplies",
            "type":"Manufacturing & Wholesale Goods"
        }
    ],
    "sg:phone":"+1 201 652 7052",
    "sg:postcode":"07452",
    "sg:province":"NJ",
    "wof:name":"High Quality Medical LLC",
    "wof:placetype":"venue"
},
  "geometry": {"coordinates":[-74.11148900000001,40.959869],"type":"Point"}
}