{
  "type": "Feature",
  "properties": {
    "addr:full":"426 32nd St Union City NJ 07087",
    "addr:housenumber":"426",
    "addr:postcode":"07087",
    "addr:street":"32Nd St",
    "iso:country":"US",
    "sg:address":"426 32nd St",
    "sg:city":"Union City",
    "sg:classifiers":[
        {
            "category":"Deli",
            "type":"Food & Drink"
        }
    ],
    "sg:menulink":"http://www.allmenus.com/nj/union-city/285300-viva-la-mamma/menu/",
    "sg:phone":"+1 201 392 3898",
    "sg:postcode":"07087",
    "sg:province":"NJ",
    "sg:tags":[
        "american",
        "italian"
    ],
    "wof:name":"Viva la Mamma",
    "wof:placetype":"venue"
},
  "geometry": {"coordinates":[-74.028972,40.772074],"type":"Point"}
}