{
  "type": "Feature",
  "properties": {
    "addr:full":"261 2nd St Elizabeth NJ 07206",
    "addr:housenumber":"261",
    "addr:postcode":"07206",
    "addr:street":"2Nd St",
    "iso:country":"US",
    "sg:address":"261 2nd St",
    "sg:city":"Elizabeth",
    "sg:classifiers":[
        {
            "category":"Food & Beverages",
            "subcategory":"Liquor & Beverages",
            "type":"Retail Goods"
        }
    ],
    "sg:phone":"+1 908 351 5566",
    "sg:postcode":"07206",
    "sg:province":"NJ",
    "sg:tags":[
        "beer",
        "spirit",
        "wine"
    ],
    "wof:name":"Second Street Liquors",
    "wof:placetype":"venue"
},
  "geometry": {"coordinates":[-74.1828,40.653801],"type":"Point"}
}