{
  "type": "Feature",
  "properties": {
    "addr:full":"252 State Rte 31 Washington NJ 07882",
    "addr:housenumber":"252",
    "addr:postcode":"07882",
    "addr:street":"State Rte 31",
    "iso:country":"US",
    "sg:address":"252 State Rte 31",
    "sg:city":"Washington",
    "sg:classifiers":[
        {
            "category":"Building & Trades",
            "subcategory":"Plumbing",
            "type":"Services"
        }
    ],
    "sg:phone":"+1 908 689 4690",
    "sg:postcode":"07882",
    "sg:province":"NJ",
    "sg:tags":[
        "plumbing",
        "contractor"
    ],
    "sg:website":"www.mrrooter.com",
    "wof:name":"Mr Rooter",
    "wof:placetype":"venue"
},
  "geometry": {"coordinates":[-74.98006599999999,40.770067],"type":"Point"}
}