{
  "type": "Feature",
  "properties": {
    "addr:full":"130 Old Denville Rd Boonton NJ 07005",
    "addr:housenumber":"130",
    "addr:postcode":"07005",
    "addr:street":"Old Denville Rd",
    "iso:country":"US",
    "sg:address":"130 Old Denville Rd",
    "sg:city":"Boonton",
    "sg:classifiers":[
        {
            "category":"Shopping",
            "subcategory":"Florist",
            "type":"Retail Goods"
        },
        {
            "category":"Farming",
            "subcategory":"Nursery",
            "type":"Manufacturing & Wholesale Goods"
        }
    ],
    "sg:phone":"+1 973 334 6528",
    "sg:postcode":"07005",
    "sg:province":"NJ",
    "sg:tags":[
        "farm",
        "food",
        "greenhouse",
        "crop",
        "covered"
    ],
    "sg:website":"www.hamiltonfarms.com",
    "wof:name":"Hamilton Farms",
    "wof:placetype":"venue"
},
  "geometry": {"coordinates":[-74.44328,40.914949],"type":"Point"}
}