{
  "type": "Feature",
  "properties": {
    "addr:full":"97 Church St Keyport NJ 07735",
    "addr:housenumber":"97",
    "addr:postcode":"07735",
    "addr:street":"Church St",
    "iso:country":"US",
    "sg:address":"97 Church St",
    "sg:city":"Keyport",
    "sg:classifiers":[
        {
            "category":"Retail",
            "subcategory":"Repair Shop",
            "type":"Services"
        }
    ],
    "sg:phone":"+1 732 264 2124",
    "sg:postcode":"07735",
    "sg:province":"NJ",
    "sg:tags":[
        "appliance"
    ],
    "wof:name":"Hoffer's Washer & Dryer Repair",
    "wof:placetype":"venue"
},
  "geometry": {"coordinates":[-74.198382,40.436408],"type":"Point"}
}