{
  "type": "Feature",
  "properties": {
    "addr:full":"84 E 20th St Paterson NJ 07513",
    "addr:housenumber":"84",
    "addr:postcode":"07513",
    "addr:street":"E 20Th St",
    "iso:country":"US",
    "sg:address":"84 E 20th St",
    "sg:city":"Paterson",
    "sg:classifiers":[
        {
            "category":"Travel",
            "subcategory":"Travel Agent",
            "type":"Entertainment"
        }
    ],
    "sg:phone":"+1 973 684 8503",
    "sg:postcode":"07513",
    "sg:province":"NJ",
    "sg:tags":[
        "operator",
        "tour"
    ],
    "wof:name":"Citywide Tours Inc",
    "wof:placetype":"venue"
},
  "geometry": {"coordinates":[-74.156916,40.905626],"type":"Point"}
}