{
  "type": "Feature",
  "properties": {
    "iso:country":"US",
    "sg:address":"51 Wick Dr",
    "sg:city":"Fords",
    "sg:classifiers":[
        {
            "category":"Professional",
            "subcategory":"Computer Services",
            "type":"Services"
        }
    ],
    "sg:phone":"+1 732 855 1699",
    "sg:postcode":"08863",
    "sg:province":"NJ",
    "sg:tags":[
        "related"
    ],
    "wof:name":"Bon Information Technology",
    "wof:placetype":"venue"
},
  "geometry": {"coordinates":[-74.30447100000001,40.549943],"type":"Point"}
}