{
  "type": "Feature",
  "properties": {
    "addr:full":"805 Highland Ave Paramus NJ 07652",
    "addr:housenumber":"805",
    "addr:postcode":"07652",
    "addr:street":"Highland Ave",
    "iso:country":"US",
    "sg:address":"805 Highland Ave",
    "sg:city":"Paramus",
    "sg:classifiers":[
        {
            "category":"Manufacturing",
            "subcategory":"Printing",
            "type":"Manufacturing & Wholesale Goods"
        }
    ],
    "sg:phone":"+1 201 261 9193",
    "sg:postcode":"07652",
    "sg:province":"NJ",
    "sg:tags":[
        "book"
    ],
    "wof:name":"Management Services",
    "wof:placetype":"venue"
},
  "geometry": {"coordinates":[-74.071918,40.975499],"type":"Point"}
}