{
  "type": "Feature",
  "properties": {
    "addr:full":"22 Florence St South Hackensack NJ 07606",
    "addr:housenumber":"22",
    "addr:postcode":"07606",
    "addr:street":"Florence St",
    "iso:country":"US",
    "sg:address":"22 Florence St",
    "sg:city":"South Hackensack",
    "sg:classifiers":[
        {
            "category":"Wholesale",
            "subcategory":"Non-durable Goods",
            "type":"Manufacturing & Wholesale Goods"
        }
    ],
    "sg:phone":"+1 201 489 1600",
    "sg:postcode":"07606",
    "sg:province":"NJ",
    "sg:website":"www.wascoonline.com",
    "wof:name":"Wholesale Auto Supply Co",
    "wof:placetype":"venue"
},
  "geometry": {"coordinates":[-74.046345,40.867634],"type":"Point"}
}