{
  "type": "Feature",
  "properties": {
    "addr:full":"411 Pompton Ave Cedar Grove NJ 07009",
    "addr:housenumber":"411",
    "addr:postcode":"07009",
    "addr:street":"Pompton Ave",
    "iso:country":"US",
    "sg:address":"411 Pompton Ave",
    "sg:city":"Cedar Grove",
    "sg:classifiers":[
        {
            "category":"Building & Trades",
            "subcategory":"Construction",
            "type":"Services"
        }
    ],
    "sg:phone":"+1 973 857 5244",
    "sg:postcode":"07009",
    "sg:province":"NJ",
    "sg:tags":[
        "contractor"
    ],
    "wof:name":"Drywall Intr Systems Contrs A",
    "wof:placetype":"venue"
},
  "geometry": {"coordinates":[-74.228616,40.846457],"type":"Point"}
}