{
  "type": "Feature",
  "properties": {
    "iso:country":"US",
    "sg:address":"809 Centre St",
    "sg:city":"Somers Point",
    "sg:classifiers":[
        {
            "category":"Home & Garden",
            "subcategory":"Building Materials",
            "type":"Retail Goods"
        }
    ],
    "sg:phone":"+1   ",
    "sg:postcode":"08244",
    "sg:province":"NJ",
    "sg:tags":[
        "door"
    ],
    "wof:name":"Door Store",
    "wof:placetype":"venue"
},
  "geometry": {"coordinates":[-74.597675,39.311484],"type":"Point"}
}