{
  "type": "Feature",
  "properties": {
    "iso:country":"US",
    "sg:address":"3 Penn Plz E",
    "sg:city":"Newark",
    "sg:classifiers":[
        {
            "category":"Communications",
            "subcategory":"Newspaper",
            "type":"Services"
        }
    ],
    "sg:phone":"+1 973 817 7566",
    "sg:postcode":"07105",
    "sg:province":"NJ",
    "sg:tags":[
        "print",
        "medium"
    ],
    "wof:name":"Soft Touch Newstand",
    "wof:placetype":"venue"
},
  "geometry": {"coordinates":[-74.159302,40.732101],"type":"Point"}
}