{
  "type": "Feature",
  "properties": {
    "addr:full":"439 Convery Blvd Perth Amboy NJ 08861",
    "addr:housenumber":"439",
    "addr:postcode":"08861",
    "addr:street":"Convery Blvd",
    "iso:country":"US",
    "sg:address":"439 Convery Blvd",
    "sg:city":"Perth Amboy",
    "sg:classifiers":[
        {
            "category":"Food & Beverages",
            "subcategory":"Liquor & Beverages",
            "type":"Retail Goods"
        }
    ],
    "sg:phone":"+1 732 324 2900",
    "sg:postcode":"08861",
    "sg:province":"NJ",
    "sg:tags":[
        "beer",
        "spirit",
        "wine"
    ],
    "wof:name":"Liquor T & A",
    "wof:placetype":"venue"
},
  "geometry": {"coordinates":[-74.28382499999999,40.518831],"type":"Point"}
}