{
  "type": "Feature",
  "properties": {
    "iso:country":"US",
    "sg:address":"211 Westfield Ave E",
    "sg:city":"Roselle Park",
    "sg:classifiers":[
        {
            "category":"Personal",
            "subcategory":"Beauty Salon",
            "type":"Services"
        }
    ],
    "sg:phone":"+1 908 245 9477",
    "sg:postcode":"07204",
    "sg:province":"NJ",
    "sg:tags":[
        "manicuring"
    ],
    "wof:name":"Changes Hair Studio",
    "wof:placetype":"venue"
},
  "geometry": {"coordinates":[-74.257577,40.662599],"type":"Point"}
}