{
  "type": "Feature",
  "properties": {
    "iso:country":"US",
    "sg:address":"178 Milkweed Ct",
    "sg:city":"Three Bridges",
    "sg:classifiers":[
        {
            "category":"Local Transit",
            "type":"Transportation"
        }
    ],
    "sg:phone":"+1 908 996 9030",
    "sg:postcode":"08887",
    "sg:province":"NJ",
    "sg:tags":[
        "passenger"
    ],
    "wof:name":"West Limousine",
    "wof:placetype":"venue"
},
  "geometry": {"coordinates":[-74.783455,40.528298],"type":"Point"}
}