{
  "type": "Feature",
  "properties": {
    "iso:country":"US",
    "sg:address":"47 Kinnaman Ave",
    "sg:city":"Washington",
    "sg:classifiers":[
        {
            "category":"Retail",
            "subcategory":"Portrait Studio",
            "type":"Services"
        }
    ],
    "sg:phone":"+1 908 689 2021",
    "sg:postcode":"07882",
    "sg:province":"NJ",
    "sg:tags":[
        "photo",
        "photography",
        "store"
    ],
    "wof:name":"Rimi Photography",
    "wof:placetype":"venue"
},
  "geometry": {"coordinates":[-74.991203,40.7673],"type":"Point"}
}