{
  "type": "Feature",
  "properties": {
    "addr:full":"104 White Horse Rd E Voorhees NJ 08043",
    "addr:housenumber":"104",
    "addr:postcode":"08043",
    "addr:street":"White Horse Rd E Voorhees",
    "iso:country":"US",
    "sg:address":"104 White Horse Rd E",
    "sg:city":"Voorhees",
    "sg:classifiers":[
        {
            "category":"Personal",
            "subcategory":"Beauty Salon",
            "type":"Services"
        }
    ],
    "sg:phone":"+1 856 309 2220",
    "sg:postcode":"08043",
    "sg:province":"NJ",
    "sg:tags":[
        "shop"
    ],
    "wof:name":"2000 Nails",
    "wof:placetype":"venue"
},
  "geometry": {"coordinates":[-74.99571,39.841845],"type":"Point"}
}