{
  "type": "Feature",
  "properties": {
    "addr:full":"10 E Black Horse Pike Williamstown NJ 08094",
    "addr:housenumber":"10",
    "addr:postcode":"08094",
    "addr:street":"E Black Horse Pike",
    "iso:country":"US",
    "sg:address":"10 E Black Horse Pike",
    "sg:city":"Williamstown",
    "sg:classifiers":[
        {
            "category":"Banks & Credit Unions",
            "subcategory":"Bank",
            "type":"Services"
        }
    ],
    "sg:phone":"+1 609 567 3945",
    "sg:postcode":"08094",
    "sg:province":"NJ",
    "wof:name":"South Jersey Gas Employees Cu",
    "wof:placetype":"venue"
},
  "geometry": {"coordinates":[-74.87979,39.603176],"type":"Point"}
}