{
  "type": "Feature",
  "properties": {
    "iso:country":"US",
    "sg:address":"533 Tilton Rd",
    "sg:city":"Northfield",
    "sg:classifiers":[
        {
            "category":"Government",
            "subcategory":"Office",
            "type":"Public Place"
        }
    ],
    "sg:phone":"+1   ",
    "sg:postcode":"08225",
    "sg:province":"NJ",
    "sg:tags":[
        "legislative",
        "body"
    ],
    "wof:name":"District 2",
    "wof:placetype":"venue"
},
  "geometry": {"coordinates":[-74.60301800000001,39.487416],"type":"Point"}
}