{
  "type": "Feature",
  "properties": {
    "iso:country":"US",
    "sg:address":"65 N Maple Ave",
    "sg:city":"Ridgewood",
    "sg:classifiers":[
        {
            "category":"Social Services",
            "type":"Services"
        }
    ],
    "sg:phone":"+1 201 493 0305",
    "sg:postcode":"07450",
    "sg:province":"NJ",
    "wof:name":"Reilly Judy A Lcsw",
    "wof:placetype":"venue"
},
  "geometry": {"coordinates":[-74.112664,40.980529],"type":"Point"}
}