{
  "type": "Feature",
  "properties": {
    "iso:country":"US",
    "sg:address":"344 Nye Ave",
    "sg:city":"Irvington",
    "sg:classifiers":[
        {
            "category":"Wholesale",
            "subcategory":"Chemicals & Plastics",
            "type":"Manufacturing & Wholesale Goods"
        }
    ],
    "sg:phone":"+1 973 375 7644",
    "sg:postcode":"07111",
    "sg:province":"NJ",
    "sg:tags":[
        "p",
        "bag",
        "mfg"
    ],
    "wof:name":"Industrial Poly Mfg Inc-Plant",
    "wof:placetype":"venue"
},
  "geometry": {"coordinates":[-74.221695,40.721558],"type":"Point"}
}