{
  "type": "Feature",
  "properties": {
    "iso:country":"US",
    "sg:address":"130 Matthews Farm Rd",
    "sg:city":"Belle Mead",
    "sg:classifiers":[
        {
            "category":"Organizations",
            "subcategory":"Membership Organization",
            "type":"Services"
        }
    ],
    "sg:phone":"+1 908 281 0662",
    "sg:postcode":"08502",
    "sg:province":"NJ",
    "sg:tags":[
        "personal",
        "interest",
        "association"
    ],
    "wof:name":"Mid Atlantic Flat Coat Retriev",
    "wof:placetype":"venue"
},
  "geometry": {"coordinates":[-74.652221,40.4417],"type":"Point"}
}