{
  "type": "Feature",
  "properties": {
    "iso:country":"US",
    "sg:address":"10 Roe-Ri Rd",
    "sg:city":"Pine Brook",
    "sg:classifiers":[
        {
            "category":"Wholesale",
            "subcategory":"Durable Goods & Equipment",
            "type":"Manufacturing & Wholesale Goods"
        }
    ],
    "sg:phone":"+1 973 227 2277",
    "sg:postcode":"07058",
    "sg:province":"NJ",
    "sg:tags":[
        "fire",
        "extinguisher"
    ],
    "wof:name":"Cain & Sons Fire Equipment Inc",
    "wof:placetype":"venue"
},
  "geometry": {"coordinates":[-74.33520300000001,40.866146],"type":"Point"}
}