{
  "type": "Feature",
  "properties": {
    "iso:country":"US",
    "sg:address":"86 Toby Dr",
    "sg:city":"Succasunna",
    "sg:classifiers":[
        {
            "category":"Wholesale",
            "subcategory":"Vending Machines",
            "type":"Manufacturing & Wholesale Goods"
        }
    ],
    "sg:phone":"+1   ",
    "sg:postcode":"07876",
    "sg:province":"NJ",
    "sg:tags":[
        "snack",
        "soda"
    ],
    "wof:name":"Best Vending",
    "wof:placetype":"venue"
},
  "geometry": {"coordinates":[-74.66658099999999,40.839667],"type":"Point"}
}