{
  "type": "Feature",
  "properties": {
    "iso:country":"US",
    "sg:address":"207 Summer Ave",
    "sg:city":"Newark",
    "sg:classifiers":[
        {
            "category":"Personal",
            "subcategory":"Beauty Salon",
            "type":"Services"
        }
    ],
    "sg:phone":"+1 973 482 0333",
    "sg:postcode":"07104",
    "sg:province":"NJ",
    "wof:name":"Fabulous Cuts Unisex",
    "wof:placetype":"venue"
},
  "geometry": {"coordinates":[-74.172212,40.758075],"type":"Point"}
}