{
  "type": "Feature",
  "properties": {
    "addr:full":"522 Halsey Rd North Brunswick NJ 08902",
    "addr:housenumber":"522",
    "addr:postcode":"08902",
    "addr:street":"Halsey Rd",
    "iso:country":"US",
    "sg:address":"522 Halsey Rd",
    "sg:city":"North Brunswick",
    "sg:classifiers":[
        {
            "category":"Social Services",
            "type":"Services"
        }
    ],
    "sg:phone":"+1   ",
    "sg:postcode":"08902",
    "sg:province":"NJ",
    "wof:name":"Selectively Seniors",
    "wof:placetype":"venue"
},
  "geometry": {"coordinates":[-74.472122,40.448446],"type":"Point"}
}