{
  "type": "Feature",
  "properties": {
    "addr:full":"2357 Auburn Ave Atco NJ 08004",
    "addr:housenumber":"2357",
    "addr:postcode":"08004",
    "addr:street":"Auburn Ave",
    "iso:country":"US",
    "sg:address":"2357 Auburn Ave",
    "sg:city":"Atco",
    "sg:classifiers":[
        {
            "category":"Professional",
            "type":"Services"
        }
    ],
    "sg:phone":"+1   ",
    "sg:postcode":"08004",
    "sg:province":"NJ",
    "wof:name":"William B Turner",
    "wof:placetype":"venue"
},
  "geometry": {"coordinates":[-74.87639799999999,39.773031],"type":"Point"}
}