{
  "type": "Feature",
  "properties": {
    "addr:full":"1 Glimpsewood Ln Morristown NJ 07960",
    "addr:housenumber":"1",
    "addr:postcode":"07960",
    "addr:street":"Glimpsewood Ln",
    "iso:country":"US",
    "sg:address":"1 Glimpsewood Ln",
    "sg:city":"Morristown",
    "sg:classifiers":[
        {
            "category":"Professional",
            "subcategory":"Computer Services",
            "type":"Services"
        }
    ],
    "sg:phone":"+1 973 292 3200",
    "sg:postcode":"07960",
    "sg:province":"NJ",
    "sg:tags":[
        "repair"
    ],
    "wof:name":"Rac Systems Corp",
    "wof:placetype":"venue"
},
  "geometry": {"coordinates":[-74.495018,40.804885],"type":"Point"}
}