{
  "type": "Feature",
  "properties": {
    "addr:full":"391 Hudson St Hackensack NJ 07601",
    "addr:housenumber":"391",
    "addr:postcode":"07601",
    "addr:street":"Hudson St",
    "iso:country":"US",
    "sg:address":"391 Hudson St",
    "sg:city":"Hackensack",
    "sg:classifiers":[
        {
            "category":"Social Services",
            "subcategory":"Child Care",
            "type":"Services"
        }
    ],
    "sg:phone":"+1   ",
    "sg:postcode":"07601",
    "sg:province":"NJ",
    "sg:tags":[
        "day"
    ],
    "wof:name":"Marites Desilva",
    "wof:placetype":"venue"
},
  "geometry": {"coordinates":[-74.039052,40.865649],"type":"Point"}
}