{
  "type": "Feature",
  "properties": {
    "addr:full":"16 Cranmer Rd Bayville NJ 08721",
    "addr:housenumber":"16",
    "addr:postcode":"08721",
    "addr:street":"Cranmer Rd",
    "iso:country":"US",
    "sg:address":"16 Cranmer Rd",
    "sg:city":"Bayville",
    "sg:classifiers":[
        {
            "category":"Manufacturing",
            "subcategory":"Apparel",
            "type":"Manufacturing & Wholesale Goods"
        }
    ],
    "sg:phone":"+1 732 269 0056",
    "sg:postcode":"08721",
    "sg:province":"NJ",
    "wof:name":"Kopka",
    "wof:placetype":"venue"
},
  "geometry": {"coordinates":[-74.159683,39.917292],"type":"Point"}
}