{
  "type": "Feature",
  "properties": {
    "addr:full":"1019 Westwood Ave Westwood NJ 07675",
    "addr:housenumber":"1019",
    "addr:postcode":"07675",
    "addr:street":"Westwood Ave",
    "iso:country":"US",
    "sg:address":"1019 Westwood Ave",
    "sg:city":"Westwood",
    "sg:classifiers":[
        {
            "category":"Arts & Performance",
            "subcategory":"Theater",
            "type":"Entertainment"
        }
    ],
    "sg:phone":"+1   ",
    "sg:postcode":"07675",
    "sg:province":"NJ",
    "sg:tags":[
        "group"
    ],
    "wof:name":"Adelphi Chamber Orchestra",
    "wof:placetype":"venue"
},
  "geometry": {"coordinates":[-73.988816,41.001399],"type":"Point"}
}