{
  "type": "Feature",
  "properties": {
    "addr:full":"980 Warren Dr Vineland NJ 08360",
    "addr:housenumber":"980",
    "addr:postcode":"08360",
    "addr:street":"Warren Dr",
    "iso:country":"US",
    "sg:address":"980 Warren Dr",
    "sg:city":"Vineland",
    "sg:classifiers":[
        {
            "category":"Retail",
            "subcategory":"Auto Repair",
            "type":"Services"
        }
    ],
    "sg:phone":"+1 856 696 7616",
    "sg:postcode":"08360",
    "sg:province":"NJ",
    "sg:tags":[
        "transmission"
    ],
    "wof:name":"Colon Engine & Transmission",
    "wof:placetype":"venue"
},
  "geometry": {"coordinates":[-75.04673099999999,39.498288],"type":"Point"}
}