{
  "type": "Feature",
  "properties": {
    "iso:country":"US",
    "sg:address":"28 Brant Ave",
    "sg:city":"Clark",
    "sg:classifiers":[
        {
            "category":"Professional",
            "type":"Services"
        }
    ],
    "sg:phone":"+1 908 226 0990",
    "sg:postcode":"07066",
    "sg:province":"NJ",
    "sg:tags":[
        "establishment"
    ],
    "wof:name":"Micro Analysts Assoc Inc",
    "wof:placetype":"venue"
},
  "geometry": {"coordinates":[-74.304215,40.623733],"type":"Point"}
}