{
  "type": "Feature",
  "properties": {
    "iso:country":"US",
    "sg:address":"894 John F Kennedy Blvd",
    "sg:city":"Bayonne",
    "sg:classifiers":[
        {
            "category":"Local Transit",
            "type":"Transportation"
        }
    ],
    "sg:phone":"+1 201 533 9333",
    "sg:postcode":"07002",
    "sg:province":"NJ",
    "sg:tags":[
        "limousine"
    ],
    "wof:name":"R & C Limo",
    "wof:placetype":"venue"
},
  "geometry": {"coordinates":[-74.114482,40.67612],"type":"Point"}
}