{
  "type": "Feature",
  "properties": {
    "iso:country":"US",
    "sg:address":"212 Arrow Ln",
    "sg:city":"Franklin Lakes",
    "sg:classifiers":[
        {
            "category":"Travel",
            "subcategory":"Travel Agent",
            "type":"Entertainment"
        }
    ],
    "sg:phone":"+1 201 848 4113",
    "sg:postcode":"07417",
    "sg:province":"NJ",
    "sg:tags":[
        "consultant",
        "agency"
    ],
    "wof:name":"Travel Artistry LLC",
    "wof:placetype":"venue"
},
  "geometry": {"coordinates":[-74.21797599999999,40.994196],"type":"Point"}
}