{
  "type": "Feature",
  "properties": {
    "addr:full":"542 Tremont Ave Westfield NJ 07090",
    "addr:housenumber":"542",
    "addr:postcode":"07090",
    "addr:street":"Tremont Ave",
    "iso:country":"US",
    "sg:address":"542 Tremont Ave",
    "sg:city":"Westfield",
    "sg:classifiers":[
        {
            "category":"Professional",
            "subcategory":"Business Services",
            "type":"Services"
        }
    ],
    "sg:phone":"+1   ",
    "sg:postcode":"07090",
    "sg:province":"NJ",
    "wof:name":"Wanfried Enterprising",
    "wof:placetype":"venue"
},
  "geometry": {"coordinates":[-74.33888899999999,40.653744],"type":"Point"}
}