{
  "type": "Feature",
  "properties": {
    "addr:full":"50 Park Ave Rutherford NJ 07070",
    "addr:housenumber":"50",
    "addr:postcode":"07070",
    "addr:street":"Park Ave",
    "iso:country":"US",
    "sg:address":"50 Park Ave",
    "sg:city":"Rutherford",
    "sg:classifiers":[
        {
            "category":"Professional",
            "subcategory":"Research",
            "type":"Services"
        }
    ],
    "sg:phone":"+1 201 935 3410",
    "sg:postcode":"07070",
    "sg:province":"NJ",
    "wof:name":"Child Research Svc",
    "wof:placetype":"venue"
},
  "geometry": {"coordinates":[-74.102313,40.828283],"type":"Point"}
}