{
  "type": "Feature",
  "properties": {
    "addr:full":"755 Hamburg Tpke Wayne NJ 07470",
    "addr:housenumber":"755",
    "addr:postcode":"07470",
    "addr:street":"Hamburg Tpke",
    "iso:country":"US",
    "sg:address":"755 Hamburg Tpke",
    "sg:city":"Wayne",
    "sg:classifiers":[
        {
            "category":"Retail",
            "subcategory":"Car Wash",
            "type":"Services"
        }
    ],
    "sg:phone":"+1   ",
    "sg:postcode":"07470",
    "sg:province":"NJ",
    "sg:tags":[
        "carwash"
    ],
    "wof:name":"Wayne Car Wash",
    "wof:placetype":"venue"
},
  "geometry": {"coordinates":[-74.222964,40.957177],"type":"Point"}
}