{
  "type": "Feature",
  "properties": {
    "addr:full":"166 Quakerbridge Mall Trenton NJ 08648",
    "addr:housenumber":"166",
    "addr:postcode":"08648",
    "addr:street":"Quakerbridge Mall",
    "iso:country":"US",
    "sg:address":"166 Quakerbridge Mall",
    "sg:city":"Trenton",
    "sg:classifiers":[
        {
            "category":"Shopping",
            "subcategory":"Shoes",
            "type":"Retail Goods"
        }
    ],
    "sg:phone":"+1   ",
    "sg:postcode":"08648",
    "sg:province":"NJ",
    "wof:name":"Kids Foot Locker",
    "wof:placetype":"venue"
},
  "geometry": {"coordinates":[-74.68522,40.290563],"type":"Point"}
}