{
  "type": "Feature",
  "properties": {
    "iso:country":"US",
    "sg:address":"45 N Century Rd",
    "sg:city":"Paramus",
    "sg:classifiers":[
        {
            "category":"Retail",
            "subcategory":"Car Wash",
            "type":"Services"
        }
    ],
    "sg:phone":"+1 201 914 4926",
    "sg:postcode":"07652",
    "sg:province":"NJ",
    "sg:tags":[
        "carwash"
    ],
    "wof:name":"Abella Wash Inc",
    "wof:placetype":"venue"
},
  "geometry": {"coordinates":[-74.06654399999999,40.928513],"type":"Point"}
}