{
  "type": "Feature",
  "properties": {
    "addr:full":"65 Kearny Ave Kearny NJ 07032",
    "addr:housenumber":"65",
    "addr:postcode":"07032",
    "addr:street":"Kearny Ave",
    "iso:country":"US",
    "sg:address":"65 Kearny Ave",
    "sg:city":"Kearny",
    "sg:classifiers":[
        {
            "category":"Professional",
            "type":"Services"
        }
    ],
    "sg:phone":"+1   ",
    "sg:postcode":"07032",
    "sg:province":"NJ",
    "wof:name":"Dotcom",
    "wof:placetype":"venue"
},
  "geometry": {"coordinates":[-74.156237,40.754647],"type":"Point"}
}