{
  "type": "Feature",
  "properties": {
    "addr:full":"120 Larrison Rd Wrightstown NJ 08562",
    "addr:housenumber":"120",
    "addr:postcode":"08562",
    "addr:street":"Larrison Rd",
    "iso:country":"US",
    "sg:address":"120 Larrison Rd",
    "sg:city":"Wrightstown",
    "sg:classifiers":[
        {
            "category":"Building & Trades",
            "subcategory":"Construction",
            "type":"Services"
        }
    ],
    "sg:phone":"+1 609 758 3658",
    "sg:postcode":"08562",
    "sg:province":"NJ",
    "sg:tags":[
        "house",
        "improvement",
        "home"
    ],
    "wof:name":"T & J Repairs & Remodeling",
    "wof:placetype":"venue"
},
  "geometry": {"coordinates":[-74.567217,40.082858],"type":"Point"}
}