{
  "type": "Feature",
  "properties": {
    "addr:full":"47 Camden Rd Hillsborough NJ 08844",
    "addr:housenumber":"47",
    "addr:postcode":"08844",
    "addr:street":"Camden Rd",
    "iso:country":"US",
    "sg:address":"47 Camden Rd",
    "sg:city":"Hillsborough",
    "sg:classifiers":[
        {
            "category":"Home & Garden",
            "subcategory":"Carpets & Floor Coverings",
            "type":"Retail Goods"
        }
    ],
    "sg:phone":"+1   ",
    "sg:postcode":"08844",
    "sg:province":"NJ",
    "wof:name":"Garret S Carpet Service",
    "wof:placetype":"venue"
},
  "geometry": {"coordinates":[-74.614277,40.462753],"type":"Point"}
}