{
  "type": "Feature",
  "properties": {
    "addr:full":"30 Spring Hill Rd Matawan NJ 07747",
    "addr:housenumber":"30",
    "addr:postcode":"07747",
    "addr:street":"Spring Hill Rd",
    "iso:country":"US",
    "sg:address":"30 Spring Hill Rd",
    "sg:city":"Matawan",
    "sg:classifiers":[
        {
            "category":"Freight",
            "type":"Transportation"
        }
    ],
    "sg:phone":"+1 732 566 7844",
    "sg:postcode":"07747",
    "sg:province":"NJ",
    "sg:tags":[
        "operator",
        "local",
        "trucking"
    ],
    "wof:name":"Zahn Trucking Inc",
    "wof:placetype":"venue"
},
  "geometry": {"coordinates":[-74.295686,40.429051],"type":"Point"}
}