{
  "type": "Feature",
  "properties": {
    "addr:full":"124 Park Ave Madison NJ 07940",
    "addr:housenumber":"124",
    "addr:postcode":"07940",
    "addr:street":"Park Ave",
    "iso:country":"US",
    "sg:address":"124 Park Ave",
    "sg:city":"Madison",
    "sg:classifiers":[
        {
            "category":"Autos & Motor Vehicles",
            "subcategory":"Fuel & Gas Station",
            "type":"Retail Goods"
        }
    ],
    "sg:phone":"+1 973 377 0041",
    "sg:postcode":"07940",
    "sg:province":"NJ",
    "sg:tags":[
        "repair",
        "gasoline"
    ],
    "wof:name":"Damiano's Service Center",
    "wof:placetype":"venue"
},
  "geometry": {"coordinates":[-74.4216,40.768002],"type":"Point"}
}