{
  "type": "Feature",
  "properties": {
    "addr:full":"252 Academy Ln Manahawkin NJ 08050",
    "addr:housenumber":"252",
    "addr:postcode":"08050",
    "addr:street":"Academy Ln",
    "iso:country":"US",
    "sg:address":"252 Academy Ln",
    "sg:city":"Manahawkin",
    "sg:classifiers":[
        {
            "category":"Travel",
            "subcategory":"Travel Agent",
            "type":"Entertainment"
        }
    ],
    "sg:phone":"+1 609 978 0740",
    "sg:postcode":"08050",
    "sg:province":"NJ",
    "wof:name":"Academy Travel",
    "wof:placetype":"venue"
},
  "geometry": {"coordinates":[-74.273208,39.738386],"type":"Point"}
}