{
  "type": "Feature",
  "properties": {
    "iso:country":"US",
    "sg:address":"546 Ave C",
    "sg:city":"Bayonne",
    "sg:classifiers":[
        {
            "category":"Retail",
            "subcategory":"Repair Shop",
            "type":"Services"
        }
    ],
    "sg:phone":"+1 201 334 3195",
    "sg:postcode":"07002",
    "sg:province":"NJ",
    "sg:tags":[
        "lock",
        "locksmith"
    ],
    "wof:name":"24 7 Emergency Locksmith",
    "wof:placetype":"venue"
},
  "geometry": {"coordinates":[-74.11917800000001,40.666613],"type":"Point"}
}