{
  "type": "Feature",
  "properties": {
    "iso:country":"US",
    "sg:address":"5802 Hudson Ave",
    "sg:city":"West New York",
    "sg:classifiers":[
        {
            "category":"Banks & Credit Unions",
            "subcategory":"Financial Services",
            "type":"Services"
        }
    ],
    "sg:phone":"+1 201 868 6180",
    "sg:postcode":"07093",
    "sg:province":"NJ",
    "sg:tags":[
        "company",
        "holding"
    ],
    "wof:name":"Lee & Lee Holdings Inc",
    "wof:placetype":"venue"
},
  "geometry": {"coordinates":[-74.013017,40.786397],"type":"Point"}
}