{
  "type": "Feature",
  "properties": {
    "addr:full":"200 E Ridgewood Ave Ridgewood NJ 07450",
    "addr:housenumber":"200",
    "addr:postcode":"07450",
    "addr:street":"E Ridgewood Ave",
    "iso:country":"US",
    "sg:address":"200 E Ridgewood Ave",
    "sg:city":"Ridgewood",
    "sg:classifiers":[
        {
            "category":"Shopping",
            "subcategory":"Jewelry",
            "type":"Retail Goods"
        }
    ],
    "sg:phone":"+1 201 445 7550",
    "sg:postcode":"07450",
    "sg:province":"NJ",
    "sg:tags":[
        "jeweler"
    ],
    "wof:name":"Pierre's Fine Jewelry LLC",
    "wof:placetype":"venue"
},
  "geometry": {"coordinates":[-74.116443,40.979238],"type":"Point"}
}