{
  "type": "Feature",
  "properties": {
    "iso:country":"US",
    "sg:address":"201 E Ridgewood Ave",
    "sg:city":"Ridgewood",
    "sg:classifiers":[
        {
            "category":"Real Estate",
            "subcategory":"Real Estate Agent",
            "type":"Services"
        }
    ],
    "sg:phone":"+1 201 447 2988",
    "sg:postcode":"07450",
    "sg:province":"NJ",
    "sg:website":"www.boehmerealestate.com",
    "wof:name":"Boehme Real Estate",
    "wof:placetype":"venue"
},
  "geometry": {"coordinates":[-74.113253,40.978591],"type":"Point"}
}