{
  "type": "Feature",
  "properties": {
    "addr:full":"13 Kelly Aly Trenton NJ 08618",
    "addr:housenumber":"13",
    "addr:postcode":"08618",
    "addr:street":"Kelly Aly",
    "iso:country":"US",
    "sg:address":"13 Kelly Aly",
    "sg:city":"Trenton",
    "sg:classifiers":[
        {
            "category":"Real Estate",
            "subcategory":"Real Estate Agent",
            "type":"Services"
        }
    ],
    "sg:phone":"+1 609 406 1381",
    "sg:postcode":"08618",
    "sg:province":"NJ",
    "wof:name":"American Properties Realty Inc",
    "wof:placetype":"venue"
},
  "geometry": {"coordinates":[-74.76945600000001,40.225654],"type":"Point"}
}