{
  "type": "Feature",
  "properties": {
    "iso:country":"US",
    "sg:address":"626 State Rte 94",
    "sg:city":"Newton",
    "sg:classifiers":[
        {
            "category":"Recreation",
            "type":"Entertainment"
        }
    ],
    "sg:phone":"+1 973 579 2727",
    "sg:postcode":"07860",
    "sg:province":"NJ",
    "wof:name":"Breezy View Farm",
    "wof:placetype":"venue"
},
  "geometry": {"coordinates":[-74.860765,40.997006],"type":"Point"}
}