{
  "type": "Feature",
  "properties": {
    "addr:full":"961 State St Perth Amboy NJ 08861",
    "addr:housenumber":"961",
    "addr:postcode":"08861",
    "addr:street":"State St",
    "iso:country":"US",
    "sg:address":"961 State St",
    "sg:city":"Perth Amboy",
    "sg:classifiers":[
        {
            "category":"Retail",
            "subcategory":"Auto Repair",
            "type":"Services"
        }
    ],
    "sg:phone":"+1 732 442 0047",
    "sg:postcode":"08861",
    "sg:province":"NJ",
    "wof:name":"Ceasar's Auto Body",
    "wof:placetype":"venue"
},
  "geometry": {"coordinates":[-74.264397,40.530102],"type":"Point"}
}