{
  "type": "Feature",
  "properties": {
    "iso:country":"US",
    "sg:address":"1 Harmon Plz Ste 104",
    "sg:city":"Secaucus",
    "sg:classifiers":[
        {
            "category":"Banks & Credit Unions",
            "subcategory":"Bank",
            "type":"Services"
        }
    ],
    "sg:phone":"+1 201 866 2746",
    "sg:postcode":"07094",
    "sg:province":"NJ",
    "sg:website":"www.bankofny.com",
    "wof:name":"Bank of New York",
    "wof:placetype":"venue"
},
  "geometry": {"coordinates":[-74.068905,40.793821],"type":"Point"}
}