{
  "type": "Feature",
  "properties": {
    "addr:full":"431 Main St Metuchen NJ 08840",
    "addr:housenumber":"431",
    "addr:postcode":"08840",
    "addr:street":"Main St",
    "iso:country":"US",
    "sg:address":"431 Main St",
    "sg:city":"Metuchen",
    "sg:classifiers":[
        {
            "category":"Professional",
            "type":"Services"
        }
    ],
    "sg:phone":"+1   ",
    "sg:postcode":"08840",
    "sg:province":"NJ",
    "wof:name":"Raconteur LLC",
    "wof:placetype":"venue"
},
  "geometry": {"coordinates":[-74.362193,40.542562],"type":"Point"}
}