{
  "type": "Feature",
  "properties": {
    "addr:full":"6701 Black Horse Pike Egg Harbor Twp NJ 08234",
    "addr:housenumber":"6701",
    "addr:postcode":"08234",
    "addr:street":"Black Horse Pike",
    "iso:country":"US",
    "sg:address":"6701 Black Horse Pike",
    "sg:city":"Egg Harbor Twp",
    "sg:classifiers":[
        {
            "category":"Education",
            "subcategory":"Special Training",
            "type":"Public Place"
        }
    ],
    "sg:phone":"+1 609 383 3832",
    "sg:postcode":"08234",
    "sg:province":"NJ",
    "sg:tags":[
        "instruction",
        "music"
    ],
    "wof:name":"DMG Music",
    "wof:placetype":"venue"
},
  "geometry": {"coordinates":[-74.563385,39.406887],"type":"Point"}
}