{
  "type": "Feature",
  "properties": {
    "iso:country":"US",
    "sg:address":"1701 Main St",
    "sg:city":"Belmar",
    "sg:classifiers":[
        {
            "category":"Home & Garden",
            "subcategory":"Building Materials",
            "type":"Retail Goods"
        }
    ],
    "sg:phone":"+1 732 988 3636",
    "sg:postcode":"07719",
    "sg:province":"NJ",
    "sg:tags":[
        "glass",
        "window",
        "plate"
    ],
    "wof:name":"Diamond Auto Glass",
    "wof:placetype":"venue"
},
  "geometry": {"coordinates":[-74.027406,40.171673],"type":"Point"}
}