{
  "type": "Feature",
  "properties": {
    "iso:country":"US",
    "sg:address":"108 Hammonton Rd",
    "sg:city":"Hammonton",
    "sg:classifiers":[
        {
            "category":"Communications",
            "type":"Services"
        }
    ],
    "sg:phone":"+1 856 697 6556",
    "sg:postcode":"08037",
    "sg:province":"NJ",
    "wof:name":"Connective Communications",
    "wof:placetype":"venue"
},
  "geometry": {"coordinates":[-74.855654,39.658134],"type":"Point"}
}