{
  "type": "Feature",
  "properties": {
    "addr:full":"77 Taylor Ave Manasquan NJ 08736",
    "addr:housenumber":"77",
    "addr:postcode":"08736",
    "addr:street":"Taylor Ave",
    "iso:country":"US",
    "sg:address":"77 Taylor Ave",
    "sg:city":"Manasquan",
    "sg:classifiers":[
        {
            "category":"Personal",
            "subcategory":"Barber",
            "type":"Services"
        }
    ],
    "sg:phone":"+1   ",
    "sg:postcode":"08736",
    "sg:province":"NJ",
    "sg:tags":[
        "shop"
    ],
    "wof:name":"Mug The",
    "wof:placetype":"venue"
},
  "geometry": {"coordinates":[-74.04740700000001,40.123147],"type":"Point"}
}