{
  "type": "Feature",
  "properties": {
    "iso:country":"US",
    "sg:address":"1 Hampton Rd",
    "sg:city":"Flanders",
    "sg:classifiers":[
        {
            "category":"Professional",
            "subcategory":"Management & Consulting",
            "type":"Services"
        }
    ],
    "sg:phone":"+1 973 584 9329",
    "sg:postcode":"07836",
    "sg:province":"NJ",
    "sg:tags":[
        "business"
    ],
    "sg:website":"www.complaninc.com",
    "wof:name":"Complan Inc",
    "wof:placetype":"venue"
},
  "geometry": {"coordinates":[-74.70500800000001,40.82863],"type":"Point"}
}