{
  "type": "Feature",
  "properties": {
    "addr:full":"67 Jefferson Ave Short Hills NJ 07078",
    "addr:housenumber":"67",
    "addr:postcode":"07078",
    "addr:street":"Jefferson Ave",
    "iso:country":"US",
    "sg:address":"67 Jefferson Ave",
    "sg:city":"Short Hills",
    "sg:classifiers":[
        {
            "category":"Professional",
            "type":"Services"
        }
    ],
    "sg:phone":"+1   ",
    "sg:postcode":"07078",
    "sg:province":"NJ",
    "wof:name":"Lejj Inc",
    "wof:placetype":"venue"
},
  "geometry": {"coordinates":[-74.319373,40.732701],"type":"Point"}
}