{
  "type": "Feature",
  "properties": {
    "iso:country":"US",
    "sg:address":"1177 Park Ave",
    "sg:city":"Plainfield",
    "sg:classifiers":[
        {
            "category":"Health Services",
            "subcategory":"Doctor",
            "type":"Services"
        }
    ],
    "sg:phone":"+1 908 222 0600",
    "sg:postcode":"07060",
    "sg:province":"NJ",
    "sg:tags":[
        "physician",
        "medical",
        "surgeon"
    ],
    "wof:name":"Edward A Alder MD",
    "wof:placetype":"venue"
},
  "geometry": {"coordinates":[-74.405625,40.607489],"type":"Point"}
}