{
  "type": "Feature",
  "properties": {
    "addr:full":"3406 Bergenline Ave Union City NJ 07087",
    "addr:housenumber":"3406",
    "addr:postcode":"07087",
    "addr:street":"Bergenline Ave",
    "iso:country":"US",
    "sg:address":"3406 Bergenline Ave",
    "sg:city":"Union City",
    "sg:classifiers":[
        {
            "category":"Shopping",
            "subcategory":"Clothing, Apparel, & Fashions",
            "type":"Retail Goods"
        }
    ],
    "sg:phone":"+1 201 520 0008",
    "sg:postcode":"07087",
    "sg:province":"NJ",
    "wof:name":"M J Sportswear",
    "wof:placetype":"venue"
},
  "geometry": {"coordinates":[-74.02811,40.773438],"type":"Point"}
}