{
  "type": "Feature",
  "properties": {
    "iso:country":"US",
    "sg:address":"49 W Somerset St",
    "sg:city":"Raritan",
    "sg:classifiers":[
        {
            "category":"Bakery",
            "type":"Food & Drink"
        }
    ],
    "sg:phone":"+1 908 725 2196",
    "sg:postcode":"08869",
    "sg:province":"NJ",
    "sg:website":"http://www.theraritanpastryshop.com/",
    "wof:name":"Raritan Pastry Shop",
    "wof:placetype":"venue"
},
  "geometry": {"coordinates":[-74.62969200000001,40.56892],"type":"Point"}
}