{
  "type": "Feature",
  "properties": {
    "iso:country":"US",
    "sg:address":"790 Haddon Ave",
    "sg:city":"Collingswood",
    "sg:classifiers":[
        {
            "category":"Bars & Pubs",
            "type":"Food & Drink"
        }
    ],
    "sg:phone":"+1 856 854 4501",
    "sg:postcode":"08108",
    "sg:province":"NJ",
    "sg:tags":[
        "drinking",
        "fraternal"
    ],
    "wof:name":"Collingswood Cloud Masonic Lod",
    "wof:placetype":"venue"
},
  "geometry": {"coordinates":[-75.06662,39.915588],"type":"Point"}
}