{
  "type": "Feature",
  "properties": {
    "addr:full":"201 Oakdene Pl Cliffside Park NJ 07010",
    "addr:housenumber":"201",
    "addr:postcode":"07010",
    "addr:street":"Oakdene Pl",
    "iso:country":"US",
    "sg:address":"201 Oakdene Pl",
    "sg:city":"Cliffside Park",
    "sg:classifiers":[
        {
            "category":"Wholesale",
            "subcategory":"Non-durable Goods",
            "type":"Manufacturing & Wholesale Goods"
        }
    ],
    "sg:phone":"+1 201 840 5587",
    "sg:postcode":"07010",
    "sg:province":"NJ",
    "wof:name":"Andes International Trading",
    "wof:placetype":"venue"
},
  "geometry": {"coordinates":[-73.98642,40.822909],"type":"Point"}
}