{
  "type": "Feature",
  "properties": {
    "addr:full":"38 N Haddon Ave Haddonfield NJ 08033",
    "addr:housenumber":"38",
    "addr:postcode":"08033",
    "addr:street":"N Haddon Ave",
    "iso:country":"US",
    "sg:address":"38 N Haddon Ave",
    "sg:city":"Haddonfield",
    "sg:classifiers":[
        {
            "category":"Professional",
            "subcategory":"Lawyer & Legal Services",
            "type":"Services"
        }
    ],
    "sg:phone":"+1 856 428 7000",
    "sg:postcode":"08033",
    "sg:province":"NJ",
    "wof:name":"Rubin Kenneth Attorney-At Law",
    "wof:placetype":"venue"
},
  "geometry": {"coordinates":[-75.03360000000001,39.898998],"type":"Point"}
}