{
  "type": "Feature",
  "properties": {
    "addr:full":"70 Tiffany Pl Irvington NJ 07111",
    "addr:housenumber":"70",
    "addr:postcode":"07111",
    "addr:street":"Tiffany Pl",
    "iso:country":"US",
    "sg:address":"70 Tiffany Pl",
    "sg:city":"Irvington",
    "sg:classifiers":[
        {
            "category":"Banks & Credit Unions",
            "subcategory":"Financial Services",
            "type":"Services"
        }
    ],
    "sg:phone":"+1   ",
    "sg:postcode":"07111",
    "sg:province":"NJ",
    "sg:tags":[
        "trust",
        "investment",
        "real estate"
    ],
    "wof:name":"Faster Home Buyers",
    "wof:placetype":"venue"
},
  "geometry": {"coordinates":[-74.245816,40.727627],"type":"Point"}
}