{
  "type": "Feature",
  "properties": {
    "addr:full":"35 Windsor Dr Princeton Junction NJ 08550",
    "addr:housenumber":"35",
    "addr:postcode":"08550",
    "addr:street":"Windsor Dr",
    "iso:country":"US",
    "sg:address":"35 Windsor Dr",
    "sg:city":"Princeton Junction",
    "sg:classifiers":[
        {
            "category":"Building & Trades",
            "subcategory":"Construction",
            "type":"Services"
        }
    ],
    "sg:phone":"+1 609 799 2891",
    "sg:postcode":"08550",
    "sg:province":"NJ",
    "sg:tags":[
        "excavating",
        "contractor"
    ],
    "wof:name":"Leshetz Construction Co Inc",
    "wof:placetype":"venue"
},
  "geometry": {"coordinates":[-74.615494,40.300622],"type":"Point"}
}