{
  "type": "Feature",
  "properties": {
    "addr:full":"600 Sylvan Ave Englewood Cliffs NJ 07632",
    "addr:housenumber":"600",
    "addr:postcode":"07632",
    "addr:street":"Sylvan Ave",
    "iso:country":"US",
    "sg:address":"600 Sylvan Ave",
    "sg:city":"Englewood Cliffs",
    "sg:classifiers":[
        {
            "category":"Freight",
            "type":"Transportation"
        }
    ],
    "sg:phone":"+1 201 399 8888",
    "sg:postcode":"07632",
    "sg:province":"NJ",
    "sg:tags":[
        "consultant"
    ],
    "wof:name":"Consolidated Transportation",
    "wof:placetype":"venue"
},
  "geometry": {"coordinates":[-73.945227,40.888307],"type":"Point"}
}