{
  "type": "Feature",
  "properties": {
    "iso:country":"US",
    "sg:address":"94 Keller Ave",
    "sg:city":"Cookstown",
    "sg:classifiers":[
        {
            "category":"Building & Trades",
            "subcategory":"Construction",
            "type":"Services"
        }
    ],
    "sg:phone":"+1 609 625 4181",
    "sg:postcode":"08511",
    "sg:province":"NJ",
    "sg:tags":[
        "home",
        "builder"
    ],
    "wof:name":"KARA Homes",
    "wof:placetype":"venue"
},
  "geometry": {"coordinates":[-74.575416,40.045886],"type":"Point"}
}