{
  "type": "Feature",
  "properties": {
    "addr:full":"23 Halsey St Newark NJ 07102",
    "addr:housenumber":"23",
    "addr:postcode":"07102",
    "addr:street":"Halsey St",
    "iso:country":"US",
    "sg:address":"23 Halsey St",
    "sg:city":"Newark",
    "sg:classifiers":[
        {
            "category":"Building & Trades",
            "subcategory":"Locksmith",
            "type":"Services"
        }
    ],
    "sg:phone":"+1 973 735 2785",
    "sg:postcode":"07102",
    "sg:province":"NJ",
    "sg:tags":[
        "key"
    ],
    "wof:name":"Able Emergency Locksmith",
    "wof:placetype":"venue"
},
  "geometry": {"coordinates":[-74.170872,40.741697],"type":"Point"}
}