{
  "type": "Feature",
  "properties": {
    "iso:country":"US",
    "sg:address":"56 Stockton St",
    "sg:city":"Newark",
    "sg:classifiers":[
        {
            "category":"Banks & Credit Unions",
            "subcategory":"Bank",
            "type":"Services"
        }
    ],
    "sg:phone":"+1 973 274 1113",
    "sg:postcode":"07105",
    "sg:province":"NJ",
    "sg:tags":[
        "cashing",
        "check"
    ],
    "wof:name":"Wilson Check Cashing",
    "wof:placetype":"venue"
},
  "geometry": {"coordinates":[-74.15163099999999,40.718345],"type":"Point"}
}