{
  "type": "Feature",
  "properties": {
    "addr:full":"335 E Front St Plainfield NJ 07060",
    "addr:housenumber":"335",
    "addr:postcode":"07060",
    "addr:street":"E Front St",
    "iso:country":"US",
    "sg:address":"335 E Front St",
    "sg:city":"Plainfield",
    "sg:classifiers":[
        {
            "category":"Banks & Credit Unions",
            "subcategory":"Bank",
            "type":"Services"
        }
    ],
    "sg:phone":"+1   ",
    "sg:postcode":"07060",
    "sg:province":"NJ",
    "sg:tags":[
        "state",
        "commercial"
    ],
    "wof:name":"Fleet",
    "wof:placetype":"venue"
},
  "geometry": {"coordinates":[-74.41918800000001,40.623227],"type":"Point"}
}