{
  "type": "Feature",
  "properties": {
    "addr:full":"318 Stockton St Perth Amboy NJ 08861",
    "addr:housenumber":"318",
    "addr:postcode":"08861",
    "addr:street":"Stockton St",
    "iso:country":"US",
    "sg:address":"318 Stockton St",
    "sg:city":"Perth Amboy",
    "sg:classifiers":[
        {
            "category":"Organizations",
            "subcategory":"Non-profit Organization",
            "type":"Services"
        }
    ],
    "sg:phone":"+1 732 442 1231",
    "sg:postcode":"08861",
    "sg:province":"NJ",
    "sg:tags":[
        "charitable",
        "institution"
    ],
    "wof:name":"Catholic Charities",
    "wof:placetype":"venue"
},
  "geometry": {"coordinates":[-74.27758300000001,40.51327],"type":"Point"}
}