{
  "type": "Feature",
  "properties": {
    "addr:full":"84 State Rte 31 Flemington NJ 08822",
    "addr:housenumber":"84",
    "addr:postcode":"08822",
    "addr:street":"State Rte 31",
    "iso:country":"US",
    "sg:address":"84 State Rte 31",
    "sg:city":"Flemington",
    "sg:classifiers":[
        {
            "category":"Professional",
            "subcategory":"Business Services",
            "type":"Services"
        }
    ],
    "sg:phone":"+1 908 284 7128",
    "sg:postcode":"08822",
    "sg:province":"NJ",
    "wof:name":"Wcvh FM",
    "wof:placetype":"venue"
},
  "geometry": {"coordinates":[-74.859679,40.457531],"type":"Point"}
}