{
  "type": "Feature",
  "properties": {
    "iso:country":"US",
    "sg:address":"135 E 4th Ave",
    "sg:city":"Roselle",
    "sg:classifiers":[
        {
            "category":"Organizations",
            "subcategory":"Religious Organization",
            "type":"Services"
        }
    ],
    "sg:phone":"+1   ",
    "sg:postcode":"07203",
    "sg:province":"NJ",
    "wof:name":"St Joseph Convent",
    "wof:placetype":"venue"
},
  "geometry": {"coordinates":[-74.261927,40.656583],"type":"Point"}
}