{
  "type": "Feature",
  "properties": {
    "iso:country":"US",
    "sg:address":"4722 8th Ave",
    "sg:city":"Brooklyn",
    "sg:classifiers":[
        {
            "category":"Food & Beverages",
            "subcategory":"Groceries & Convenience Stores",
            "type":"Retail Goods"
        }
    ],
    "sg:phone":"+1 718 851 0568",
    "sg:postcode":"11220",
    "sg:province":"NY",
    "wof:name":"Jinsen Grocery Inc",
    "wof:placetype":"venue"
},
  "geometry": {"coordinates":[-74.20801899999999,40.64278],"type":"Point"}
}