{
  "type": "Feature",
  "properties": {
    "addr:full":"288 N 12th Pl Haledon NJ 07508",
    "addr:housenumber":"288",
    "addr:postcode":"07508",
    "addr:street":"N 12Th Pl",
    "iso:country":"US",
    "sg:address":"288 N 12th Pl",
    "sg:city":"Haledon",
    "sg:classifiers":[
        {
            "category":"Building & Trades",
            "subcategory":"Cleaning & Sanitation",
            "type":"Services"
        }
    ],
    "sg:phone":"+1   ",
    "sg:postcode":"07508",
    "sg:province":"NJ",
    "sg:tags":[
        "maintenance"
    ],
    "wof:name":"Cleaning Service Mh",
    "wof:placetype":"venue"
},
  "geometry": {"coordinates":[-74.170113,40.938722],"type":"Point"}
}