{
  "type": "Feature",
  "properties": {
    "iso:country":"US",
    "sg:address":"10 Inverness Dr",
    "sg:city":"Marlboro",
    "sg:classifiers":[
        {
            "category":"Insurance",
            "subcategory":"Hazard Insurance",
            "type":"Services"
        }
    ],
    "sg:phone":"+1   ",
    "sg:postcode":"07726",
    "sg:province":"NJ",
    "sg:tags":[
        "carrier",
        "surety"
    ],
    "wof:name":"Discount Dental USA Liabililty",
    "wof:placetype":"venue"
},
  "geometry": {"coordinates":[-74.37869499999999,40.25866],"type":"Point"}
}