{
  "type": "Feature",
  "properties": {
    "addr:full":"383 Anderson Ave Fairview NJ 07022",
    "addr:housenumber":"383",
    "addr:postcode":"07022",
    "addr:street":"Anderson Ave",
    "iso:country":"US",
    "sg:address":"383 Anderson Ave",
    "sg:city":"Fairview",
    "sg:classifiers":[
        {
            "category":"Communications",
            "subcategory":"Film & Video Production",
            "type":"Services"
        }
    ],
    "sg:phone":"+1 201 840 8129",
    "sg:postcode":"07022",
    "sg:province":"NJ",
    "sg:tags":[
        "motion"
    ],
    "wof:name":"Giddy Productions LLC",
    "wof:placetype":"venue"
},
  "geometry": {"coordinates":[-73.99283800000001,40.818977],"type":"Point"}
}