{
  "type": "Feature",
  "properties": {
    "addr:full":"427 N Haddon Ave Haddonfield NJ 08033",
    "addr:housenumber":"427",
    "addr:postcode":"08033",
    "addr:street":"N Haddon Ave",
    "iso:country":"US",
    "sg:address":"427 N Haddon Ave",
    "sg:city":"Haddonfield",
    "sg:classifiers":[
        {
            "category":"Manufacturing",
            "subcategory":"Food",
            "type":"Manufacturing & Wholesale Goods"
        }
    ],
    "sg:phone":"+1 856 428 1655",
    "sg:postcode":"08033",
    "sg:province":"NJ",
    "sg:tags":[
        "bakery",
        "product",
        "mfg"
    ],
    "wof:name":"Sweetie Pie of Haddonfield",
    "wof:placetype":"venue"
},
  "geometry": {"coordinates":[-75.039597,39.903],"type":"Point"}
}