{
  "type": "Feature",
  "properties": {
    "iso:country":"US",
    "sg:address":"199 Baldwin Rd",
    "sg:city":"Parsippany",
    "sg:classifiers":[
        {
            "category":"Health Services",
            "subcategory":"Doctor",
            "type":"Services"
        }
    ],
    "sg:phone":"+1 973 334 8010",
    "sg:postcode":"07054",
    "sg:province":"NJ",
    "sg:tags":[
        "physician",
        "surgeon"
    ],
    "wof:name":"Gilbert Poon MD",
    "wof:placetype":"venue"
},
  "geometry": {"coordinates":[-74.395416,40.86445],"type":"Point"}
}