{
  "type": "Feature",
  "properties": {
    "iso:country":"US",
    "sg:address":"1214 S Bright St",
    "sg:city":"Hillside",
    "sg:classifiers":[
        {
            "category":"Professional",
            "subcategory":"Management & Consulting",
            "type":"Services"
        }
    ],
    "sg:phone":"+1 908 282 6661",
    "sg:postcode":"07205",
    "sg:province":"NJ",
    "wof:name":"Santana Management Inc",
    "wof:placetype":"venue"
},
  "geometry": {"coordinates":[-74.229705,40.693431],"type":"Point"}
}