{
  "type": "Feature",
  "properties": {
    "iso:country":"US",
    "sg:address":"281 Ferry St",
    "sg:city":"Newark",
    "sg:classifiers":[
        {
            "category":"Professional",
            "subcategory":"Management & Consulting",
            "type":"Services"
        }
    ],
    "sg:phone":"+1 973 465 1127",
    "sg:postcode":"07105",
    "sg:province":"NJ",
    "sg:tags":[
        "marketing",
        "consultant"
    ],
    "wof:name":"Catalina Marketing Corp",
    "wof:placetype":"venue"
},
  "geometry": {"coordinates":[-74.15078699999999,40.728867],"type":"Point"}
}