{
  "type": "Feature",
  "properties": {
    "addr:full":"40 Galesi Dr Wayne NJ 07470",
    "addr:housenumber":"40",
    "addr:postcode":"07470",
    "addr:street":"Galesi Dr",
    "iso:country":"US",
    "sg:address":"40 Galesi Dr",
    "sg:city":"Wayne",
    "sg:classifiers":[
        {
            "category":"Banks & Credit Unions",
            "subcategory":"Bank",
            "type":"Services"
        }
    ],
    "sg:phone":"+1 973 785 8636",
    "sg:postcode":"07470",
    "sg:province":"NJ",
    "wof:name":"First Centurion Bancorp",
    "wof:placetype":"venue"
},
  "geometry": {"coordinates":[-74.244499,40.896301],"type":"Point"}
}