{
  "type": "Feature",
  "properties": {
    "iso:country":"US",
    "sg:address":"46 Myers Ave",
    "sg:city":"Denville",
    "sg:classifiers":[
        {
            "category":"Autos & Motor Vehicles",
            "subcategory":"Auto Supplies",
            "type":"Retail Goods"
        }
    ],
    "sg:phone":"+1 973 625 0213",
    "sg:postcode":"07834",
    "sg:province":"NJ",
    "sg:tags":[
        "tire"
    ],
    "sg:website":"www.apollotire.com",
    "wof:name":"Apollo Tire & Automotive Center",
    "wof:placetype":"venue"
},
  "geometry": {"coordinates":[-74.480417,40.897495],"type":"Point"}
}