{
  "type": "Feature",
  "properties": {
    "iso:country":"US",
    "sg:address":"93 1st St",
    "sg:city":"Hackensack",
    "sg:classifiers":[
        {
            "category":"Professional",
            "subcategory":"Management & Consulting",
            "type":"Services"
        }
    ],
    "sg:phone":"+1 973 684 2400",
    "sg:postcode":"07601",
    "sg:province":"NJ",
    "sg:tags":[
        "marketing",
        "program"
    ],
    "wof:name":"ESP Intl Marketing",
    "wof:placetype":"venue"
},
  "geometry": {"coordinates":[-74.052233,40.884998],"type":"Point"}
}