{
  "type": "Feature",
  "properties": {
    "addr:full":"8 W Side Ave Jersey City NJ 07305",
    "addr:housenumber":"8",
    "addr:postcode":"07305",
    "addr:street":"W Side Ave",
    "iso:country":"US",
    "sg:address":"8 W Side Ave",
    "sg:city":"Jersey City",
    "sg:classifiers":[
        {
            "category":"Personal",
            "subcategory":"Beauty Salon",
            "type":"Services"
        }
    ],
    "sg:phone":"+1 201 451 1562",
    "sg:postcode":"07305",
    "sg:province":"NJ",
    "sg:tags":[
        "shop"
    ],
    "wof:name":"Star Nails",
    "wof:placetype":"venue"
},
  "geometry": {"coordinates":[-74.09813,40.704891],"type":"Point"}
}