{
  "type": "Feature",
  "properties": {
    "addr:full":"3110 Belvidere Rd Phillipsburg NJ 08865",
    "addr:housenumber":"3110",
    "addr:postcode":"08865",
    "addr:street":"Belvidere Rd",
    "iso:country":"US",
    "sg:address":"3110 Belvidere Rd",
    "sg:city":"Phillipsburg",
    "sg:classifiers":[
        {
            "category":"Professional",
            "subcategory":"Art Services",
            "type":"Services"
        }
    ],
    "sg:phone":"+1 908 475 8331",
    "sg:postcode":"08865",
    "sg:province":"NJ",
    "sg:tags":[
        "photography",
        "commercial"
    ],
    "wof:name":"Richards British Gun Shop",
    "wof:placetype":"venue"
},
  "geometry": {"coordinates":[-75.11208499999999,40.772119],"type":"Point"}
}