{
  "type": "Feature",
  "properties": {
    "addr:full":"8 Parkway Pl Holmdel NJ 07733",
    "addr:housenumber":"8",
    "addr:postcode":"07733",
    "addr:street":"Parkway Pl",
    "iso:country":"US",
    "sg:address":"8 Parkway Pl",
    "sg:city":"Holmdel",
    "sg:classifiers":[
        {
            "category":"Recreation",
            "type":"Entertainment"
        }
    ],
    "sg:phone":"+1 732 946 1601",
    "sg:postcode":"07733",
    "sg:province":"NJ",
    "sg:tags":[
        "rubber",
        "pro",
        "fabricated",
        "mfg"
    ],
    "wof:name":"Balloon Flight Inc",
    "wof:placetype":"venue"
},
  "geometry": {"coordinates":[-74.162142,40.380176],"type":"Point"}
}