{
  "type": "Feature",
  "properties": {
    "iso:country":"US",
    "sg:address":"793 Mayhew Ave",
    "sg:city":"Swedesboro",
    "sg:classifiers":[
        {
            "category":"Professional",
            "subcategory":"Lawyer & Legal Services",
            "type":"Services"
        }
    ],
    "sg:phone":"+1 856 467 0857",
    "sg:postcode":"08085",
    "sg:province":"NJ",
    "sg:tags":[
        "attorney"
    ],
    "wof:name":"Daniel L De Mora",
    "wof:placetype":"venue"
},
  "geometry": {"coordinates":[-75.318123,39.740599],"type":"Point"}
}