{
  "type": "Feature",
  "properties": {
    "iso:country":"US",
    "sg:address":"287 W 8th St",
    "sg:city":"Ship Bottom",
    "sg:classifiers":[
        {
            "category":"Real Estate",
            "subcategory":"Architect",
            "type":"Services"
        }
    ],
    "sg:phone":"+1 609 494 8429",
    "sg:postcode":"08008",
    "sg:province":"NJ",
    "wof:name":"Robert Stack LLC",
    "wof:placetype":"venue"
},
  "geometry": {"coordinates":[-74.177632,39.650654],"type":"Point"}
}