{
  "type": "Feature",
  "properties": {
    "addr:full":"53 Paterson St New Brunswick NJ 08901",
    "addr:housenumber":"53",
    "addr:postcode":"08901",
    "addr:street":"Paterson St",
    "iso:country":"US",
    "sg:address":"53 Paterson St",
    "sg:city":"New Brunswick",
    "sg:classifiers":[
        {
            "category":"Real Estate",
            "subcategory":"Real Estate Services",
            "type":"Services"
        }
    ],
    "sg:phone":"+1 732 249 9696",
    "sg:postcode":"08901",
    "sg:province":"NJ",
    "sg:tags":[
        "company",
        "abstract",
        "title"
    ],
    "wof:name":"Middlesex Abstract Co",
    "wof:placetype":"venue"
},
  "geometry": {"coordinates":[-74.44452099999999,40.495187],"type":"Point"}
}