{
  "type": "Feature",
  "properties": {
    "iso:country":"US",
    "sg:address":"2219 Morris Ave",
    "sg:city":"Union",
    "sg:classifiers":[
        {
            "category":"Shopping",
            "subcategory":"Crafts & Fabrics",
            "type":"Retail Goods"
        },
        {
            "category":"Retail",
            "subcategory":"Auto Repair",
            "type":"Services"
        }
    ],
    "sg:phone":"+1 908 686 5985",
    "sg:postcode":"07083",
    "sg:province":"NJ",
    "sg:tags":[
        "shop",
        "automobile",
        "upholstery",
        "sewing"
    ],
    "wof:name":"Great Buffalo Car Upholstery",
    "wof:placetype":"venue"
},
  "geometry": {"coordinates":[-74.281516,40.699089],"type":"Point"}
}