{
  "type": "Feature",
  "properties": {
    "addr:full":"29 51st St Weehawken NJ 07086",
    "addr:housenumber":"29",
    "addr:postcode":"07086",
    "addr:street":"51St St",
    "iso:country":"US",
    "sg:address":"29 51st St",
    "sg:city":"Weehawken",
    "sg:classifiers":[
        {
            "category":"Professional",
            "subcategory":"Business Services",
            "type":"Services"
        }
    ],
    "sg:phone":"+1   ",
    "sg:postcode":"07086",
    "sg:province":"NJ",
    "sg:tags":[
        "consultant",
        "chain",
        "supply"
    ],
    "wof:name":"New Age Consulting",
    "wof:placetype":"venue"
},
  "geometry": {"coordinates":[-74.011832,40.779744],"type":"Point"}
}