{
  "type": "Feature",
  "properties": {
    "addr:full":"400 W Decatur Ave Pleasantville NJ 08232",
    "addr:housenumber":"400",
    "addr:postcode":"08232",
    "addr:street":"W Decatur Ave",
    "iso:country":"US",
    "sg:address":"400 W Decatur Ave",
    "sg:city":"Pleasantville",
    "sg:classifiers":[
        {
            "category":"Wholesale",
            "subcategory":"Machinery & Supplies",
            "type":"Manufacturing & Wholesale Goods"
        }
    ],
    "sg:phone":"+1 609 484 1700",
    "sg:postcode":"08232",
    "sg:province":"NJ",
    "sg:tags":[
        "salon",
        "beauty"
    ],
    "wof:name":"Atlantic City Beauty Supply",
    "wof:placetype":"venue"
},
  "geometry": {"coordinates":[-74.529265,39.39073],"type":"Point"}
}