{
  "type": "Feature",
  "properties": {
    "addr:full":"2263 N 2nd St Millville NJ 08332",
    "addr:housenumber":"2263",
    "addr:postcode":"08332",
    "addr:street":"N 2Nd St",
    "iso:country":"US",
    "sg:address":"2263 N 2nd St",
    "sg:city":"Millville",
    "sg:classifiers":[
        {
            "category":"Utilities",
            "subcategory":"Mobile Phone",
            "type":"Services"
        }
    ],
    "sg:phone":"+1 856 293 0700",
    "sg:postcode":"08332",
    "sg:province":"NJ",
    "sg:tags":[
        "communication",
        "radiotelephone"
    ],
    "wof:name":"Primo Jewelers Inc",
    "wof:placetype":"venue"
},
  "geometry": {"coordinates":[-75.03989,39.42666],"type":"Point"}
}