{
  "type": "Feature",
  "properties": {
    "iso:country":"US",
    "sg:address":"101 Olde New Jersey Ave",
    "sg:city":"Wildwood",
    "sg:classifiers":[
        {
            "category":"Bars & Pubs",
            "type":"Food & Drink"
        }
    ],
    "sg:phone":"+1   ",
    "sg:postcode":"08260",
    "sg:province":"NJ",
    "sg:tags":[
        "drinking"
    ],
    "wof:name":"Flukes Irish Pub",
    "wof:placetype":"venue"
},
  "geometry": {"coordinates":[-74.793188,39.008373],"type":"Point"}
}