{
  "type": "Feature",
  "properties": {
    "iso:country":"US",
    "sg:address":"110 Greentree Rd # D",
    "sg:city":"Blackwood",
    "sg:classifiers":[
        {
            "category":"Personal",
            "type":"Services"
        }
    ],
    "sg:phone":"+1 856 232 2529",
    "sg:postcode":"08012",
    "sg:province":"NJ",
    "sg:tags":[
        "party",
        "planning",
        "event"
    ],
    "wof:name":"Family Clay Time",
    "wof:placetype":"venue"
},
  "geometry": {"coordinates":[-75.04935999999999,39.75969],"type":"Point"}
}