{
  "type": "Feature",
  "properties": {
    "addr:full":"206 Sanhican Dr Trenton NJ 08618",
    "addr:housenumber":"206",
    "addr:postcode":"08618",
    "addr:street":"Sanhican Dr",
    "iso:country":"US",
    "sg:address":"206 Sanhican Dr",
    "sg:city":"Trenton",
    "sg:classifiers":[
        {
            "category":"Restaurant",
            "type":"Food & Drink"
        }
    ],
    "sg:menulink":"http://www.allmenus.com/nj/trenton/292055-dominicks-pizzeria--italian-restaurant/menu/",
    "sg:phone":"+1 609 656 4300",
    "sg:postcode":"08618",
    "sg:province":"NJ",
    "sg:tags":[
        "pizza"
    ],
    "wof:name":"Dominick's Pizzeria & Italian Restaurant",
    "wof:placetype":"venue"
},
  "geometry": {"coordinates":[-74.80622,40.23839],"type":"Point"}
}