{
  "type": "Feature",
  "properties": {
    "addr:full":"425 Washington Ave Dover NJ 07801",
    "addr:housenumber":"425",
    "addr:postcode":"07801",
    "addr:street":"Washington Ave",
    "iso:country":"US",
    "sg:address":"425 Washington Ave",
    "sg:city":"Dover",
    "sg:classifiers":[
        {
            "category":"Government",
            "subcategory":"Office",
            "type":"Public Place"
        }
    ],
    "sg:phone":"+1 973 366 5312",
    "sg:postcode":"07801",
    "sg:province":"NJ",
    "sg:tags":[
        "village"
    ],
    "wof:name":"Victory Gardens Violations Clk",
    "wof:placetype":"venue"
},
  "geometry": {"coordinates":[-74.54288,40.875363],"type":"Point"}
}