{
  "type": "Feature",
  "properties": {
    "iso:country":"US",
    "sg:address":"1025 Detwiler Ave",
    "sg:city":"Beverly",
    "sg:classifiers":[
        {
            "category":"Education",
            "subcategory":"Library",
            "type":"Public Place"
        }
    ],
    "sg:phone":"+1 609 387 1259",
    "sg:postcode":"08010",
    "sg:province":"NJ",
    "wof:name":"Beverly Free Library",
    "wof:placetype":"venue"
},
  "geometry": {"coordinates":[-74.928772,40.063107],"type":"Point"}
}