{
  "type": "Feature",
  "properties": {
    "iso:country":"US",
    "sg:address":"1121 W Aloe St",
    "sg:city":"Egg Harbor City",
    "sg:classifiers":[
        {
            "category":"Wholesale",
            "subcategory":"Plants",
            "type":"Manufacturing & Wholesale Goods"
        }
    ],
    "sg:phone":"+1 609 965 2071",
    "sg:postcode":"08215",
    "sg:province":"NJ",
    "sg:tags":[
        "supply"
    ],
    "sg:website":"www.gallowaynursery.com",
    "wof:name":"Galloway Nursery",
    "wof:placetype":"venue"
},
  "geometry": {"coordinates":[-74.63747499999999,39.516254],"type":"Point"}
}