{
  "type": "Feature",
  "properties": {
    "iso:country":"US",
    "sg:address":"9 Cross Hill Rd",
    "sg:city":"Sicklerville",
    "sg:classifiers":[
        {
            "category":"Restaurant",
            "type":"Food & Drink"
        }
    ],
    "sg:phone":"+1   ",
    "sg:postcode":"08081",
    "sg:province":"NJ",
    "sg:tags":[
        "eating"
    ],
    "wof:name":"Kings Wok",
    "wof:placetype":"venue"
},
  "geometry": {"coordinates":[-74.977661,39.745494],"type":"Point"}
}