{
  "type": "Feature",
  "properties": {
    "addr:full":"719 Creek Rd Bellmawr NJ 08031",
    "addr:housenumber":"719",
    "addr:postcode":"08031",
    "addr:street":"Creek Rd",
    "iso:country":"US",
    "sg:address":"719 Creek Rd",
    "sg:city":"Bellmawr",
    "sg:classifiers":[
        {
            "category":"Transit Center",
            "subcategory":"Freight",
            "type":"Transportation"
        }
    ],
    "sg:phone":"+1 856 933 9902",
    "sg:postcode":"08031",
    "sg:province":"NJ",
    "sg:tags":[
        "trucking-heavy",
        "hauling"
    ],
    "sg:website":"http://www.liedtka.com",
    "wof:name":"Liedtka Trucking, Inc.",
    "wof:placetype":"venue"
},
  "geometry": {"coordinates":[-75.104251,39.865307],"type":"Point"}
}