{
  "type": "Feature",
  "properties": {
    "iso:country":"US",
    "sg:address":"599 S Livingston Ave",
    "sg:city":"Livingston",
    "sg:classifiers":[
        {
            "category":"Social Services",
            "type":"Services"
        }
    ],
    "sg:phone":"+1   ",
    "sg:postcode":"07039",
    "sg:province":"NJ",
    "wof:name":"Abbey Aborn Lcsw",
    "wof:placetype":"venue"
},
  "geometry": {"coordinates":[-74.326913,40.772656],"type":"Point"}
}