{
  "type": "Feature",
  "properties": {
    "addr:full":"702 Arnold Ave Pt Pleasant Bch NJ 08742",
    "addr:housenumber":"702",
    "addr:postcode":"08742",
    "addr:street":"Arnold Ave Pt",
    "iso:country":"US",
    "sg:address":"702 Arnold Ave",
    "sg:city":"Pt Pleasant Bch",
    "sg:classifiers":[
        {
            "category":"Shopping",
            "subcategory":"Computers & Home Electronics",
            "type":"Retail Goods"
        }
    ],
    "sg:phone":"+1 732 295 7550",
    "sg:postcode":"08742",
    "sg:province":"NJ",
    "sg:tags":[
        "audio"
    ],
    "wof:name":"Audio Visions",
    "wof:placetype":"venue"
},
  "geometry": {"coordinates":[-74.053635,40.091338],"type":"Point"}
}