{
  "type": "Feature",
  "properties": {
    "addr:full":"115 Bergerville Rd Freehold NJ 07728",
    "addr:housenumber":"115",
    "addr:postcode":"07728",
    "addr:street":"Bergerville Rd",
    "iso:country":"US",
    "sg:address":"115 Bergerville Rd",
    "sg:city":"Freehold",
    "sg:classifiers":[
        {
            "category":"Wholesale",
            "subcategory":"Machinery & Supplies",
            "type":"Manufacturing & Wholesale Goods"
        }
    ],
    "sg:phone":"+1 732 625 9960",
    "sg:postcode":"07728",
    "sg:province":"NJ",
    "sg:tags":[
        "equipment",
        "repair",
        "printing",
        "an"
    ],
    "wof:name":"East Coast Printing Press Repa",
    "wof:placetype":"venue"
},
  "geometry": {"coordinates":[-74.268027,40.202772],"type":"Point"}
}