{
  "type": "Feature",
  "properties": {
    "addr:full":"48 Kimball St Woodbridge NJ 07095",
    "addr:housenumber":"48",
    "addr:postcode":"07095",
    "addr:street":"Kimball St",
    "iso:country":"US",
    "sg:address":"48 Kimball St",
    "sg:city":"Woodbridge",
    "sg:classifiers":[
        {
            "category":"Building & Trades",
            "subcategory":"Construction",
            "type":"Services"
        }
    ],
    "sg:phone":"+1 732 382 4641",
    "sg:postcode":"07095",
    "sg:province":"NJ",
    "sg:tags":[
        "paving",
        "contractor"
    ],
    "wof:name":"J W Contractors Inc",
    "wof:placetype":"venue"
},
  "geometry": {"coordinates":[-74.296565,40.564892],"type":"Point"}
}