{
  "type": "Feature",
  "properties": {
    "addr:full":"101 Ocean St Cape May NJ 08204",
    "addr:housenumber":"101",
    "addr:postcode":"08204",
    "addr:street":"Ocean St",
    "iso:country":"US",
    "sg:address":"101 Ocean St",
    "sg:city":"Cape May",
    "sg:classifiers":[
        {
            "category":"Shopping",
            "subcategory":"Clothing, Apparel, & Fashions",
            "type":"Retail Goods"
        }
    ],
    "sg:phone":"+1 609 884 8484",
    "sg:postcode":"08204",
    "sg:province":"NJ",
    "sg:tags":[
        "ready",
        "wear",
        "accessory"
    ],
    "wof:name":"Cheeks Apparel",
    "wof:placetype":"venue"
},
  "geometry": {"coordinates":[-74.920197,38.931198],"type":"Point"}
}