{
  "type": "Feature",
  "properties": {
    "addr:full":"330 William St South River NJ 08882",
    "addr:housenumber":"330",
    "addr:postcode":"08882",
    "addr:street":"William St",
    "iso:country":"US",
    "sg:address":"330 William St",
    "sg:city":"South River",
    "sg:classifiers":[
        {
            "category":"Manufacturing",
            "subcategory":"Metals",
            "type":"Manufacturing & Wholesale Goods"
        }
    ],
    "sg:phone":"+1 732 651 7700",
    "sg:postcode":"08882",
    "sg:province":"NJ",
    "sg:tags":[
        "equipment",
        "heating"
    ],
    "sg:website":"www.westwoodproducts.com",
    "wof:name":"Westwood Products Inc",
    "wof:placetype":"venue"
},
  "geometry": {"coordinates":[-74.385632,40.457695],"type":"Point"}
}