{
  "type": "Feature",
  "properties": {
    "addr:full":"900 N Lenola Rd Moorestown NJ 08057",
    "addr:housenumber":"900",
    "addr:postcode":"08057",
    "addr:street":"N Lenola Rd",
    "iso:country":"US",
    "sg:address":"900 N Lenola Rd",
    "sg:city":"Moorestown",
    "sg:classifiers":[
        {
            "category":"Manufacturing",
            "subcategory":"Metals",
            "type":"Manufacturing & Wholesale Goods"
        }
    ],
    "sg:phone":"+1 856 722 0222",
    "sg:postcode":"08057",
    "sg:province":"NJ",
    "sg:tags":[
        "stampings",
        "mfg"
    ],
    "wof:name":"Vector Precision",
    "wof:placetype":"venue"
},
  "geometry": {"coordinates":[-74.997697,39.975905],"type":"Point"}
}