{
  "type": "Feature",
  "properties": {
    "iso:country":"US",
    "sg:address":"91 Craig Rd",
    "sg:city":"Hillsdale",
    "sg:classifiers":[
        {
            "category":"Organizations",
            "subcategory":"Membership Organization",
            "type":"Services"
        }
    ],
    "sg:phone":"+1   ",
    "sg:postcode":"07642",
    "sg:province":"NJ",
    "wof:name":"Hadassah Womens Zionist Orgn",
    "wof:placetype":"venue"
},
  "geometry": {"coordinates":[-74.07442899999999,41.011475],"type":"Point"}
}