{
  "type": "Feature",
  "properties": {
    "iso:country":"US",
    "sg:address":"305 E Bennett Ave",
    "sg:city":"Wildwood",
    "sg:classifiers":[
        {
            "category":"Travel",
            "subcategory":"Hotels & Motels",
            "type":"Entertainment"
        }
    ],
    "sg:phone":"+1   ",
    "sg:postcode":"08260",
    "sg:province":"NJ",
    "wof:name":"Tally-Ho Motel",
    "wof:placetype":"venue"
},
  "geometry": {"coordinates":[-74.823331,38.979898],"type":"Point"}
}