{
  "type": "Feature",
  "properties": {
    "iso:country":"US",
    "sg:address":"318 McLean Blvd",
    "sg:city":"Paterson",
    "sg:classifiers":[
        {
            "category":"Home & Garden",
            "subcategory":"Building Materials",
            "type":"Retail Goods"
        }
    ],
    "sg:phone":"+1 973 754 9444",
    "sg:postcode":"07504",
    "sg:province":"NJ",
    "sg:tags":[
        "supply"
    ],
    "wof:name":"Taylor Door",
    "wof:placetype":"venue"
},
  "geometry": {"coordinates":[-74.134972,40.906363],"type":"Point"}
}