{
  "type": "Feature",
  "properties": {
    "addr:full":"511 Pacific Ave Atlantic City NJ 08401",
    "addr:housenumber":"511",
    "addr:postcode":"08401",
    "addr:street":"Pacific Ave",
    "iso:country":"US",
    "sg:address":"511 Pacific Ave",
    "sg:city":"Atlantic City",
    "sg:classifiers":[
        {
            "category":"Shopping",
            "subcategory":"Used Merchandise",
            "type":"Retail Goods"
        }
    ],
    "sg:phone":"+1 609 347 9667",
    "sg:postcode":"08401",
    "sg:province":"NJ",
    "sg:tags":[
        "shop",
        "thrift"
    ],
    "wof:name":"Figueroa Record Shop",
    "wof:placetype":"venue"
},
  "geometry": {"coordinates":[-74.416961,39.36465],"type":"Point"}
}