{
  "type": "Feature",
  "properties": {
    "iso:country":"US",
    "sg:address":"52 O St",
    "sg:city":"Seaside Park",
    "sg:classifiers":[
        {
            "category":"Insurance",
            "subcategory":"Insurance Agent",
            "type":"Services"
        }
    ],
    "sg:phone":"+1   ",
    "sg:postcode":"08752",
    "sg:province":"NJ",
    "wof:name":"Healthcare Risk Specialists LL",
    "wof:placetype":"venue"
},
  "geometry": {"coordinates":[-74.07501000000001,39.933761],"type":"Point"}
}