{
  "type": "Feature",
  "properties": {
    "addr:full":"173 Stuart St Paramus NJ 07652",
    "addr:housenumber":"173",
    "addr:postcode":"07652",
    "addr:street":"Stuart St",
    "iso:country":"US",
    "sg:address":"173 Stuart St",
    "sg:city":"Paramus",
    "sg:classifiers":[
        {
            "category":"Professional",
            "subcategory":"Business Services",
            "type":"Services"
        }
    ],
    "sg:phone":"+1   ",
    "sg:postcode":"07652",
    "sg:province":"NJ",
    "wof:name":"Parabolic Solutions",
    "wof:placetype":"venue"
},
  "geometry": {"coordinates":[-74.05779200000001,40.937592],"type":"Point"}
}