{
  "type": "Feature",
  "properties": {
    "iso:country":"US",
    "sg:address":"1221 Middlesex St",
    "sg:city":"Linden",
    "sg:classifiers":[
        {
            "category":"Real Estate",
            "subcategory":"Real Estate Agent",
            "type":"Services"
        }
    ],
    "sg:phone":"+1   ",
    "sg:postcode":"07036",
    "sg:province":"NJ",
    "wof:name":"Dreamz Property Management",
    "wof:placetype":"venue"
},
  "geometry": {"coordinates":[-74.246082,40.646828],"type":"Point"}
}