{
  "type": "Feature",
  "properties": {
    "addr:full":"88 Lenox Rd Wayne NJ 07470",
    "addr:housenumber":"88",
    "addr:postcode":"07470",
    "addr:street":"Lenox Rd",
    "iso:country":"US",
    "sg:address":"88 Lenox Rd",
    "sg:city":"Wayne",
    "sg:classifiers":[
        {
            "category":"Professional",
            "type":"Services"
        }
    ],
    "sg:phone":"+1 212 268 8524",
    "sg:postcode":"07470",
    "sg:province":"NJ",
    "sg:tags":[
        "establishment"
    ],
    "wof:name":"New York Intl Group",
    "wof:placetype":"venue"
},
  "geometry": {"coordinates":[-74.264799,40.941277],"type":"Point"}
}