{
  "type": "Feature",
  "properties": {
    "iso:country":"US",
    "sg:address":"126 Almond Rd",
    "sg:city":"Elmer",
    "sg:classifiers":[
        {
            "category":"Wholesale",
            "subcategory":"Furniture",
            "type":"Manufacturing & Wholesale Goods"
        }
    ],
    "sg:phone":"+1 856 507 9996",
    "sg:postcode":"08347",
    "sg:province":"NJ",
    "wof:name":"Almond Road Office Supplies",
    "wof:placetype":"venue"
},
  "geometry": {"coordinates":[-75.076345,39.495622],"type":"Point"}
}