{
  "type": "Feature",
  "properties": {
    "addr:full":"801 Ocean Ave Sea Bright NJ 07760",
    "addr:housenumber":"801",
    "addr:postcode":"07760",
    "addr:street":"Ocean Ave",
    "iso:country":"US",
    "sg:address":"801 Ocean Ave",
    "sg:city":"Sea Bright",
    "sg:classifiers":[
        {
            "category":"Organizations",
            "subcategory":"Community Association",
            "type":"Services"
        }
    ],
    "sg:phone":"+1 732 842 0061",
    "sg:postcode":"07760",
    "sg:province":"NJ",
    "sg:tags":[
        "club"
    ],
    "wof:name":"Ship Ahoy Beach Club",
    "wof:placetype":"venue"
},
  "geometry": {"coordinates":[-73.974321,40.376075],"type":"Point"}
}