{
  "type": "Feature",
  "properties": {
    "addr:full":"18 Indian Ln Hackettstown NJ 07840",
    "addr:housenumber":"18",
    "addr:postcode":"07840",
    "addr:street":"Indian Ln",
    "iso:country":"US",
    "sg:address":"18 Indian Ln",
    "sg:city":"Hackettstown",
    "sg:classifiers":[
        {
            "category":"Building & Trades",
            "subcategory":"Landscaping Services",
            "type":"Services"
        }
    ],
    "sg:phone":"+1 908 979 0009",
    "sg:postcode":"07840",
    "sg:province":"NJ",
    "sg:tags":[
        "landscape"
    ],
    "wof:name":"Reda Brothers Landscaping",
    "wof:placetype":"venue"
},
  "geometry": {"coordinates":[-74.807695,40.854389],"type":"Point"}
}