{
  "type": "Feature",
  "properties": {
    "iso:country":"US",
    "sg:address":"54 Hibernia Ave",
    "sg:city":"Rockaway",
    "sg:classifiers":[
        {
            "category":"Home & Garden",
            "subcategory":"Carpets & Floor Coverings",
            "type":"Retail Goods"
        }
    ],
    "sg:phone":"+1 973 627 0251",
    "sg:postcode":"07866",
    "sg:province":"NJ",
    "sg:tags":[
        "dealer",
        "rug"
    ],
    "wof:name":"Chuck's Wall To Wall",
    "wof:placetype":"venue"
},
  "geometry": {"coordinates":[-74.506134,40.906917],"type":"Point"}
}