{
  "type": "Feature",
  "properties": {
    "addr:full":"408 Lyons Ave Newark NJ 07112",
    "addr:housenumber":"408",
    "addr:postcode":"07112",
    "addr:street":"Lyons Ave",
    "iso:country":"US",
    "sg:address":"408 Lyons Ave",
    "sg:city":"Newark",
    "sg:classifiers":[
        {
            "category":"Real Estate",
            "subcategory":"Developer",
            "type":"Services"
        }
    ],
    "sg:phone":"+1 973 923 5006",
    "sg:postcode":"07112",
    "sg:province":"NJ",
    "wof:name":"MGQ Investments & Dev",
    "wof:placetype":"venue"
},
  "geometry": {"coordinates":[-74.22204499999999,40.714005],"type":"Point"}
}