{
  "type": "Feature",
  "properties": {
    "addr:full":"2175 West Marlton Pike Cherry Hill NJ 08002",
    "addr:housenumber":"2175",
    "addr:postcode":"08002",
    "addr:street":"West Marlton Pike",
    "iso:country":"US",
    "sg:address":"2175 West Marlton Pike",
    "sg:city":"Cherry Hill",
    "sg:classifiers":[
        {
            "category":"Travel",
            "subcategory":"Hotels & Motels",
            "type":"Entertainment"
        },
        {
            "category":"Retail",
            "subcategory":"Event Space",
            "type":"Services"
        }
    ],
    "sg:phone":"+1 856 663 5300",
    "sg:postcode":"08002",
    "sg:province":"NJ",
    "sg:tags":[
        "venue"
    ],
    "sg:website":"www.holidaycherryhill.com",
    "wof:name":"Holiday Inn Cherry Hill",
    "wof:placetype":"venue"
},
  "geometry": {"coordinates":[-75.040897,39.921836],"type":"Point"}
}