{
  "type": "Feature",
  "properties": {
    "addr:full":"313 Broad St Newark NJ 07104",
    "addr:housenumber":"313",
    "addr:postcode":"07104",
    "addr:street":"Broad St",
    "iso:country":"US",
    "sg:address":"313 Broad St",
    "sg:city":"Newark",
    "sg:classifiers":[
        {
            "category":"Autos & Motor Vehicles",
            "subcategory":"Auto Supplies",
            "type":"Retail Goods"
        }
    ],
    "sg:phone":"+1 973 484 2188",
    "sg:postcode":"07104",
    "sg:province":"NJ",
    "sg:tags":[
        "tire"
    ],
    "wof:name":"Omero Auto Center",
    "wof:placetype":"venue"
},
  "geometry": {"coordinates":[-74.169695,40.75111],"type":"Point"}
}