{
  "type": "Feature",
  "properties": {
    "iso:country":"US",
    "sg:address":"120 McGaw Dr",
    "sg:city":"Edison",
    "sg:classifiers":[
        {
            "category":"Professional",
            "subcategory":"Computer Services",
            "type":"Services"
        }
    ],
    "sg:phone":"+1 732 225 6464",
    "sg:postcode":"08837",
    "sg:province":"NJ",
    "sg:tags":[
        "internet"
    ],
    "wof:name":"XTREMESHOPPER.COM",
    "wof:placetype":"venue"
},
  "geometry": {"coordinates":[-74.33475900000001,40.519194],"type":"Point"}
}