{
  "type": "Feature",
  "properties": {
    "addr:full":"408 Bloomfield Dr West Berlin NJ 08091",
    "addr:housenumber":"408",
    "addr:postcode":"08091",
    "addr:street":"Bloomfield Dr",
    "iso:country":"US",
    "sg:address":"408 Bloomfield Dr",
    "sg:city":"West Berlin",
    "sg:classifiers":[
        {
            "category":"Wholesale",
            "subcategory":"Machinery & Supplies",
            "type":"Manufacturing & Wholesale Goods"
        }
    ],
    "sg:phone":"+1 856 768 7575",
    "sg:postcode":"08091",
    "sg:province":"NJ",
    "sg:tags":[
        "equipment",
        "industrial"
    ],
    "wof:name":"Interntnal Surfc Prep Group TX",
    "wof:placetype":"venue"
},
  "geometry": {"coordinates":[-74.926633,39.814627],"type":"Point"}
}