{
  "type": "Feature",
  "properties": {
    "addr:full":"84 Kymer Rd Branchville NJ 07826",
    "addr:housenumber":"84",
    "addr:postcode":"07826",
    "addr:street":"Kymer Rd",
    "iso:country":"US",
    "sg:address":"84 Kymer Rd",
    "sg:city":"Branchville",
    "sg:classifiers":[
        {
            "category":"Insurance",
            "subcategory":"Insurance Agent",
            "type":"Services"
        }
    ],
    "sg:phone":"+1 973 875 1399",
    "sg:postcode":"07826",
    "sg:province":"NJ",
    "wof:name":"Tracey M Frey",
    "wof:placetype":"venue"
},
  "geometry": {"coordinates":[-74.718335,41.198111],"type":"Point"}
}