{
  "type": "Feature",
  "properties": {
    "iso:country":"US",
    "sg:address":"867 Stuyvesant Ave",
    "sg:city":"Irvington",
    "sg:classifiers":[
        {
            "category":"Wholesale",
            "subcategory":"Meat",
            "type":"Manufacturing & Wholesale Goods"
        }
    ],
    "sg:phone":"+1 973 416 0233",
    "sg:postcode":"07111",
    "sg:province":"NJ",
    "wof:name":"Hermanos Dajer Inc",
    "wof:placetype":"venue"
},
  "geometry": {"coordinates":[-74.243313,40.720301],"type":"Point"}
}