{
  "type": "Feature",
  "properties": {
    "iso:country":"US",
    "sg:address":"2207 Milford Warren Glen Rd",
    "sg:city":"Bloomsbury",
    "sg:classifiers":[
        {
            "category":"Wholesale",
            "subcategory":"Non-durable Goods",
            "type":"Manufacturing & Wholesale Goods"
        }
    ],
    "sg:phone":"+1 908 235 1146",
    "sg:postcode":"08804",
    "sg:province":"NJ",
    "sg:tags":[
        "biological",
        "product"
    ],
    "wof:name":"Critical Biologics Corporation",
    "wof:placetype":"venue"
},
  "geometry": {"coordinates":[-75.140614,40.622312],"type":"Point"}
}