{
  "type": "Feature",
  "properties": {
    "iso:country":"US",
    "sg:address":"378 US Hwy 22 E",
    "sg:city":"Whitehouse Sta",
    "sg:classifiers":[
        {
            "category":"Autos & Motor Vehicles",
            "subcategory":"Fuel & Gas Station",
            "type":"Retail Goods"
        }
    ],
    "sg:phone":"+1 908 534 4495",
    "sg:postcode":"08889",
    "sg:province":"NJ",
    "sg:tags":[
        "oil"
    ],
    "wof:name":"Whitehouse Auto Svc",
    "wof:placetype":"venue"
},
  "geometry": {"coordinates":[-74.763749,40.621347],"type":"Point"}
}