{
  "type": "Feature",
  "properties": {
    "addr:full":"20 E Main St Denville NJ 07834",
    "addr:housenumber":"20",
    "addr:postcode":"07834",
    "addr:street":"E Main St",
    "iso:country":"US",
    "sg:address":"20 E Main St",
    "sg:city":"Denville",
    "sg:classifiers":[
        {
            "category":"Manufacturing",
            "subcategory":"Tools & Machinery",
            "type":"Manufacturing & Wholesale Goods"
        }
    ],
    "sg:phone":"+1 973 335 7074",
    "sg:postcode":"07834",
    "sg:province":"NJ",
    "sg:tags":[
        "machine",
        "mfg",
        "accessory"
    ],
    "wof:name":"Fill Gauges Inc",
    "wof:placetype":"venue"
},
  "geometry": {"coordinates":[-74.478516,40.892192],"type":"Point"}
}