{
  "type": "Feature",
  "properties": {
    "addr:full":"8 W Bayview Ave Englewood Cliffs NJ 07632",
    "addr:housenumber":"8",
    "addr:postcode":"07632",
    "addr:street":"W Bayview Ave",
    "iso:country":"US",
    "sg:address":"8 W Bayview Ave",
    "sg:city":"Englewood Cliffs",
    "sg:classifiers":[
        {
            "category":"Social Services",
            "subcategory":"Child Care",
            "type":"Services"
        }
    ],
    "sg:phone":"+1 201 947 4832",
    "sg:postcode":"07632",
    "sg:province":"NJ",
    "sg:tags":[
        "elementary",
        "kindergarten",
        "school",
        "academic"
    ],
    "sg:website":"www.japaneseschool.org",
    "wof:name":"Japanese Children's Society",
    "wof:placetype":"venue"
},
  "geometry": {"coordinates":[-73.960098,40.867802],"type":"Point"}
}