{
  "type": "Feature",
  "properties": {
    "addr:full":"1 Strong Ln Montague NJ 07827",
    "addr:housenumber":"1",
    "addr:postcode":"07827",
    "addr:street":"Strong Ln",
    "iso:country":"US",
    "sg:address":"1 Strong Ln",
    "sg:city":"Montague",
    "sg:classifiers":[
        {
            "category":"Building & Trades",
            "subcategory":"Electrical",
            "type":"Services"
        }
    ],
    "sg:phone":"+1 973 827 4046",
    "sg:postcode":"07827",
    "sg:province":"NJ",
    "sg:tags":[
        "electrical",
        "electric",
        "contractor"
    ],
    "wof:name":"Veres Electrical Service Inc",
    "wof:placetype":"venue"
},
  "geometry": {"coordinates":[-74.815528,41.26322],"type":"Point"}
}