{
  "type": "Feature",
  "properties": {
    "iso:country":"US",
    "sg:address":"49 Long Bow Dr",
    "sg:city":"Sewell",
    "sg:classifiers":[
        {
            "category":"Shopping",
            "subcategory":"Hobbies, Toys, & Games",
            "type":"Retail Goods"
        }
    ],
    "sg:phone":"+1   ",
    "sg:postcode":"08080",
    "sg:province":"NJ",
    "wof:name":"Memory Quilts & Accessories",
    "wof:placetype":"venue"
},
  "geometry": {"coordinates":[-75.09746199999999,39.768229],"type":"Point"}
}