{
  "type": "Feature",
  "properties": {
    "iso:country":"US",
    "sg:address":"266 Washington St",
    "sg:city":"Newark",
    "sg:classifiers":[
        {
            "category":"Banks & Credit Unions",
            "subcategory":"Bank",
            "type":"Services"
        }
    ],
    "sg:phone":"+1   ",
    "sg:postcode":"07102",
    "sg:province":"NJ",
    "sg:tags":[
        "depository",
        "banking"
    ],
    "wof:name":"Garden State Check Cashing Svc",
    "wof:placetype":"venue"
},
  "geometry": {"coordinates":[-74.175633,40.735755],"type":"Point"}
}