{
  "type": "Feature",
  "properties": {
    "iso:country":"US",
    "sg:address":"611 Haddon Ave",
    "sg:city":"Collingswood",
    "sg:classifiers":[
        {
            "category":"Retail",
            "subcategory":"Repair Shop",
            "type":"Services"
        }
    ],
    "sg:phone":"+1 856 854 6168",
    "sg:postcode":"08108",
    "sg:province":"NJ",
    "sg:tags":[
        "taxidermist"
    ],
    "wof:name":"Baratta's Taxidermy",
    "wof:placetype":"venue"
},
  "geometry": {"coordinates":[-75.070871,39.916971],"type":"Point"}
}