{
  "type": "Feature",
  "properties": {
    "iso:country":"US",
    "sg:address":"280 Bloomfield Ave",
    "sg:city":"Verona",
    "sg:classifiers":[
        {
            "category":"Social Services",
            "type":"Services"
        }
    ],
    "sg:phone":"+1 973 239 7300",
    "sg:postcode":"07044",
    "sg:province":"NJ",
    "sg:tags":[
        "worker"
    ],
    "wof:name":"Debra A Polizzano",
    "wof:placetype":"venue"
},
  "geometry": {"coordinates":[-74.238984,40.827988],"type":"Point"}
}