{
  "type": "Feature",
  "properties": {
    "iso:country":"US",
    "sg:address":"270 Stanhope Sparta Rd",
    "sg:city":"Andover",
    "sg:classifiers":[
        {
            "category":"Social Services",
            "type":"Services"
        }
    ],
    "sg:phone":"+1   ",
    "sg:postcode":"07821",
    "sg:province":"NJ",
    "wof:name":"Andover Center",
    "wof:placetype":"venue"
},
  "geometry": {"coordinates":[-74.679187,40.95239],"type":"Point"}
}