{
  "type": "Feature",
  "properties": {
    "iso:country":"US",
    "sg:address":"22 State Rte 57",
    "sg:city":"Hackettstown",
    "sg:classifiers":[
        {
            "category":"Restaurant",
            "type":"Food & Drink"
        }
    ],
    "sg:phone":"+1   ",
    "sg:postcode":"07840",
    "sg:province":"NJ",
    "sg:tags":[
        "eating"
    ],
    "wof:name":"Dairy Queen",
    "wof:placetype":"venue"
},
  "geometry": {"coordinates":[-74.82355800000001,40.834516],"type":"Point"}
}