{
  "type": "Feature",
  "properties": {
    "iso:country":"US",
    "sg:address":"61 Mountainview Blvd",
    "sg:city":"Wayne",
    "sg:classifiers":[
        {
            "category":"Retail",
            "subcategory":"Laundry & Dry Cleaning",
            "type":"Services"
        }
    ],
    "sg:phone":"+1 973 633 8469",
    "sg:postcode":"07470",
    "sg:province":"NJ",
    "wof:name":"Gavy's Cleaning",
    "wof:placetype":"venue"
},
  "geometry": {"coordinates":[-74.265198,40.910099],"type":"Point"}
}