{
  "type": "Feature",
  "properties": {
    "iso:country":"US",
    "sg:address":"200 Bowers Ave",
    "sg:city":"Runnemede",
    "sg:classifiers":[
        {
            "category":"Home & Garden",
            "subcategory":"Household Appliances",
            "type":"Retail Goods"
        },
        {
            "category":"Building & Trades",
            "subcategory":"Plumbing",
            "type":"Services"
        },
        {
            "category":"Home & Garden",
            "subcategory":"Building Materials",
            "type":"Retail Goods"
        },
        {
            "category":"Building & Trades",
            "subcategory":"Construction",
            "type":"Services"
        }
    ],
    "sg:phone":"+1 856 939 2477",
    "sg:postcode":"08078",
    "sg:province":"NJ",
    "sg:tags":[
        "plumber",
        "industrial",
        "dishwashing",
        "specialty",
        "altering",
        "system",
        "machine",
        "heating",
        "ventilating",
        "improvement",
        "contractor",
        "remodeling",
        "air conditioning",
        "contractors-commercial"
    ],
    "sg:website":"http://www.midlanticplumbing.com",
    "wof:name":"Midlantic Plumbing Heating & Cooling",
    "wof:placetype":"venue"
},
  "geometry": {"coordinates":[-75.076218,39.850262],"type":"Point"}
}