{
  "type": "Feature",
  "properties": {
    "addr:full":"43 S White Horse Pike Stratford NJ 08084",
    "addr:housenumber":"43",
    "addr:postcode":"08084",
    "addr:street":"S White Horse Pike",
    "iso:country":"US",
    "sg:address":"43 S White Horse Pike",
    "sg:city":"Stratford",
    "sg:classifiers":[
        {
            "category":"Social Services",
            "subcategory":"Job Training",
            "type":"Services"
        },
        {
            "category":"Education",
            "subcategory":"Special Training",
            "type":"Public Place"
        },
        {
            "category":"Education",
            "subcategory":"Vocational School",
            "type":"Public Place"
        },
        {
            "category":"Education",
            "subcategory":"School",
            "type":"Public Place"
        },
        {
            "category":"Education",
            "subcategory":"University",
            "type":"Public Place"
        }
    ],
    "sg:phone":"+1 866 957 2670",
    "sg:postcode":"08084",
    "sg:province":"NJ",
    "sg:tags":[
        "industrial",
        "business",
        "technical",
        "consultant",
        "dental",
        "trade",
        "computer",
        "college",
        "assistant",
        "technician",
        "technology",
        "medical",
        "massage"
    ],
    "sg:website":"http://www.harrisschool-us.com/?source=bt-Yellowpages.com-Stratford-0-0",
    "wof:name":"Harris School of Business",
    "wof:placetype":"venue"
},
  "geometry": {"coordinates":[-75.00265899999999,39.831283],"type":"Point"}
}