{
  "type": "Feature",
  "properties": {
    "addr:full":"421 Essex St Millburn NJ 07041",
    "addr:housenumber":"421",
    "addr:postcode":"07041",
    "addr:street":"Essex St",
    "iso:country":"US",
    "sg:address":"421 Essex St",
    "sg:city":"Millburn",
    "sg:classifiers":[
        {
            "category":"Professional",
            "subcategory":"Lawyer & Legal Services",
            "type":"Services"
        }
    ],
    "sg:phone":"+1 973 258 0444",
    "sg:postcode":"07041",
    "sg:province":"NJ",
    "wof:name":"Law Offices of Rothstein",
    "wof:placetype":"venue"
},
  "geometry": {"coordinates":[-74.311758,40.723782],"type":"Point"}
}