{
  "type": "Feature",
  "properties": {
    "iso:country":"US",
    "sg:address":"99 Leonardville Rd",
    "sg:city":"Belford",
    "sg:classifiers":[
        {
            "category":"Restaurant",
            "type":"Food & Drink"
        }
    ],
    "sg:phone":"+1   ",
    "sg:postcode":"07718",
    "sg:province":"NJ",
    "sg:tags":[
        "eating"
    ],
    "wof:name":"Valentinos Rest & Pizzeria",
    "wof:placetype":"venue"
},
  "geometry": {"coordinates":[-74.098703,40.413539],"type":"Point"}
}