{
  "type": "Feature",
  "properties": {
    "addr:full":"500 Frank W. Burr Blvd. Floor 1, Suite 29 Teaneck NJ 07666",
    "addr:housenumber":"500;1",
    "addr:postcode":"07666",
    "addr:street":"Frank W. Burr Blvd. Floor;Suite 29",
    "iso:country":"US",
    "sg:address":"500 Frank W. Burr Blvd. Floor 1, Suite 29",
    "sg:city":"Teaneck",
    "sg:classifiers":[
        {
            "category":"Manufacturing",
            "subcategory":"Electronics",
            "type":"Manufacturing & Wholesale Goods"
        }
    ],
    "sg:phone":"+1 201 928 2400",
    "sg:postcode":"07666",
    "sg:province":"NJ",
    "sg:website":"http://www.encelium.com/",
    "wof:name":"Encelium Technologies",
    "wof:placetype":"venue"
},
  "geometry": {"coordinates":[-74.02011899999999,40.899806],"type":"Point"}
}