{
  "type": "Feature",
  "properties": {
    "addr:full":"47 Village Ct Hazlet NJ 07730",
    "addr:housenumber":"47",
    "addr:postcode":"07730",
    "addr:street":"Village Ct",
    "iso:country":"US",
    "sg:address":"47 Village Ct",
    "sg:city":"Hazlet",
    "sg:classifiers":[
        {
            "category":"Real Estate",
            "subcategory":"Developer",
            "type":"Services"
        }
    ],
    "sg:phone":"+1   ",
    "sg:postcode":"07730",
    "sg:province":"NJ",
    "sg:tags":[
        "land"
    ],
    "wof:name":"American Developers NJ LLC",
    "wof:placetype":"venue"
},
  "geometry": {"coordinates":[-74.174657,40.415221],"type":"Point"}
}