{
  "type": "Feature",
  "properties": {
    "addr:full":"445 Keim Blvd Burlington NJ 08016",
    "addr:housenumber":"445",
    "addr:postcode":"08016",
    "addr:street":"Keim Blvd",
    "iso:country":"US",
    "sg:address":"445 Keim Blvd",
    "sg:city":"Burlington",
    "sg:classifiers":[
        {
            "category":"Autos & Motor Vehicles",
            "subcategory":"Automobile Sales",
            "type":"Retail Goods"
        },
        {
            "category":"Wholesale",
            "subcategory":"Motor Vehicles",
            "type":"Manufacturing & Wholesale Goods"
        }
    ],
    "sg:phone":"+1 609 387 3335",
    "sg:postcode":"08016",
    "sg:province":"NJ",
    "sg:tags":[
        "car",
        "used",
        "dealer"
    ],
    "wof:name":"Cousin Motors Inc",
    "wof:placetype":"venue"
},
  "geometry": {"coordinates":[-74.866011,40.073868],"type":"Point"}
}