{
  "type": "Feature",
  "properties": {
    "iso:country":"US",
    "sg:address":"4005 Aberdeen Ln",
    "sg:city":"Blackwood",
    "sg:classifiers":[
        {
            "category":"Professional",
            "type":"Services"
        }
    ],
    "sg:phone":"+1 856 232 8728",
    "sg:postcode":"08012",
    "sg:province":"NJ",
    "sg:tags":[
        "establishment"
    ],
    "wof:name":"Intelli Mark Inc",
    "wof:placetype":"venue"
},
  "geometry": {"coordinates":[-75.05072,39.815955],"type":"Point"}
}