{
  "type": "Feature",
  "properties": {
    "addr:full":"10 S River Rd Cranbury NJ 08535",
    "addr:housenumber":"10",
    "addr:postcode":"08535",
    "addr:street":"S River Rd",
    "iso:country":"US",
    "sg:address":"10 S River Rd",
    "sg:city":"Cranbury",
    "sg:classifiers":[
        {
            "category":"Building & Trades",
            "subcategory":"Plumbing",
            "type":"Services"
        }
    ],
    "sg:phone":"+1 609 655 0200",
    "sg:postcode":"08535",
    "sg:province":"NJ",
    "sg:tags":[
        "conditioning",
        "air",
        "system",
        "contractor"
    ],
    "wof:name":"Cranbury Comfort Systems",
    "wof:placetype":"venue"
},
  "geometry": {"coordinates":[-74.443918,40.225698],"type":"Point"}
}