{
  "type": "Feature",
  "properties": {
    "addr:full":"776 William St Middlesex NJ 08846",
    "addr:housenumber":"776",
    "addr:postcode":"08846",
    "addr:street":"William St",
    "iso:country":"US",
    "sg:address":"776 William St",
    "sg:city":"Middlesex",
    "sg:classifiers":[
        {
            "category":"Organizations",
            "subcategory":"Religious Organization",
            "type":"Services"
        }
    ],
    "sg:phone":"+1 732 356 4605",
    "sg:postcode":"08846",
    "sg:province":"NJ",
    "sg:tags":[
        "church"
    ],
    "wof:name":"Jehovah's Witnesses",
    "wof:placetype":"venue"
},
  "geometry": {"coordinates":[-74.486093,40.571594],"type":"Point"}
}