{
  "type": "Feature",
  "properties": {
    "iso:country":"US",
    "sg:address":"532 Gambocz Ct",
    "sg:city":"Monmouth Junction",
    "sg:classifiers":[
        {
            "category":"Real Estate",
            "subcategory":"Real Estate Agent",
            "type":"Services"
        }
    ],
    "sg:phone":"+1   ",
    "sg:postcode":"08852",
    "sg:province":"NJ",
    "wof:name":"Homeworx",
    "wof:placetype":"venue"
},
  "geometry": {"coordinates":[-74.555903,40.391939],"type":"Point"}
}