{
  "type": "Feature",
  "properties": {
    "iso:country":"US",
    "sg:address":"29 Church St",
    "sg:city":"Paterson",
    "sg:classifiers":[
        {
            "category":"Real Estate",
            "subcategory":"Real Estate Agent",
            "type":"Services"
        }
    ],
    "sg:phone":"+1 973 278 0808",
    "sg:postcode":"07505",
    "sg:province":"NJ",
    "wof:name":"Citizen Realty",
    "wof:placetype":"venue"
},
  "geometry": {"coordinates":[-74.170436,40.918217],"type":"Point"}
}