{
  "type": "Feature",
  "properties": {
    "iso:country":"US",
    "sg:address":"199 Columbus Dr",
    "sg:city":"Franklin Park",
    "sg:classifiers":[
        {
            "category":"Banks & Credit Unions",
            "subcategory":"Financial Services",
            "type":"Services"
        }
    ],
    "sg:phone":"+1   ",
    "sg:postcode":"08823",
    "sg:province":"NJ",
    "sg:tags":[
        "investor"
    ],
    "wof:name":"Island Family Investment",
    "wof:placetype":"venue"
},
  "geometry": {"coordinates":[-74.557036,40.431881],"type":"Point"}
}