{
  "type": "Feature",
  "properties": {
    "addr:full":"64 South St New Providence NJ 07974",
    "addr:housenumber":"64",
    "addr:postcode":"07974",
    "addr:street":"South St",
    "iso:country":"US",
    "sg:address":"64 South St",
    "sg:city":"New Providence",
    "sg:classifiers":[
        {
            "category":"Building & Trades",
            "subcategory":"Locksmith",
            "type":"Services"
        }
    ],
    "sg:phone":"+1 888 225 2626",
    "sg:postcode":"07974",
    "sg:province":"NJ",
    "sg:tags":[
        "key"
    ],
    "wof:name":"Emergency 24 Hour 7 Day Locksmith",
    "wof:placetype":"venue"
},
  "geometry": {"coordinates":[-74.405512,40.703758],"type":"Point"}
}