{
  "type": "Feature",
  "properties": {
    "addr:full":"23 Candlewood Dr Mantua NJ 08051",
    "addr:housenumber":"23",
    "addr:postcode":"08051",
    "addr:street":"Candlewood Dr",
    "iso:country":"US",
    "sg:address":"23 Candlewood Dr",
    "sg:city":"Mantua",
    "sg:classifiers":[
        {
            "category":"Retail",
            "subcategory":"Auto Repair",
            "type":"Services"
        }
    ],
    "sg:phone":"+1 856 464 0800",
    "sg:postcode":"08051",
    "sg:province":"NJ",
    "sg:tags":[
        "body",
        "lettering",
        "truck"
    ],
    "wof:name":"Walsh Truck Lettering & Sign",
    "wof:placetype":"venue"
},
  "geometry": {"coordinates":[-75.170162,39.769456],"type":"Point"}
}