{
  "type": "Feature",
  "properties": {
    "addr:full":"215 S 15th Ave Manville NJ 08835",
    "addr:housenumber":"215",
    "addr:postcode":"08835",
    "addr:street":"S 15Th Ave",
    "iso:country":"US",
    "sg:address":"215 S 15th Ave",
    "sg:city":"Manville",
    "sg:classifiers":[
        {
            "category":"Banks & Credit Unions",
            "subcategory":"Investment Brokerage",
            "type":"Services"
        }
    ],
    "sg:phone":"+1   ",
    "sg:postcode":"08835",
    "sg:province":"NJ",
    "sg:tags":[
        "advisory"
    ],
    "wof:name":"Summit Financial Svc",
    "wof:placetype":"venue"
},
  "geometry": {"coordinates":[-74.597832,40.536958],"type":"Point"}
}