{
  "type": "Feature",
  "properties": {
    "addr:full":"7 Cook Rd East Brunswick NJ 08816",
    "addr:housenumber":"7",
    "addr:postcode":"08816",
    "addr:street":"Cook Rd",
    "iso:country":"US",
    "sg:address":"7 Cook Rd",
    "sg:city":"East Brunswick",
    "sg:classifiers":[
        {
            "category":"Home & Garden",
            "subcategory":"Household Appliances",
            "type":"Retail Goods"
        }
    ],
    "sg:phone":"+1   ",
    "sg:postcode":"08816",
    "sg:province":"NJ",
    "sg:tags":[
        "machine",
        "sewing"
    ],
    "wof:name":"Niru Machine Co",
    "wof:placetype":"venue"
},
  "geometry": {"coordinates":[-74.417354,40.42855],"type":"Point"}
}