{
  "type": "Feature",
  "properties": {
    "addr:full":"1685 Amwell Rd Somerset NJ 08873",
    "addr:housenumber":"1685",
    "addr:postcode":"08873",
    "addr:street":"Amwell Rd",
    "iso:country":"US",
    "sg:address":"1685 Amwell Rd",
    "sg:city":"Somerset",
    "sg:classifiers":[
        {
            "category":"Personal",
            "subcategory":"Beauty Salon",
            "type":"Services"
        }
    ],
    "sg:phone":"+1   ",
    "sg:postcode":"08873",
    "sg:province":"NJ",
    "sg:tags":[
        "hair"
    ],
    "wof:name":"Mark Raymond & Co",
    "wof:placetype":"venue"
},
  "geometry": {"coordinates":[-74.52301199999999,40.494294],"type":"Point"}
}