{
  "type": "Feature",
  "properties": {
    "addr:full":"236 Dayton Rd Jamesburg NJ 08831",
    "addr:housenumber":"236",
    "addr:postcode":"08831",
    "addr:street":"Dayton Rd",
    "iso:country":"US",
    "sg:address":"236 Dayton Rd",
    "sg:city":"Jamesburg",
    "sg:classifiers":[
        {
            "category":"Wholesale",
            "subcategory":"Hardware",
            "type":"Manufacturing & Wholesale Goods"
        },
        {
            "category":"Building & Trades",
            "subcategory":"Plumbing",
            "type":"Services"
        }
    ],
    "sg:phone":"+1 732 521 0566",
    "sg:postcode":"08831",
    "sg:province":"NJ",
    "sg:tags":[
        "system",
        "equipment",
        "heating",
        "contractor"
    ],
    "wof:name":"Jafco Air Conditioning Inc",
    "wof:placetype":"venue"
},
  "geometry": {"coordinates":[-74.45052200000001,40.359548],"type":"Point"}
}