{
  "type": "Feature",
  "properties": {
    "addr:full":"2775 Mount Ephraim Ave Camden NJ 08104",
    "addr:housenumber":"2775",
    "addr:postcode":"08104",
    "addr:street":"Mount Ephraim Ave",
    "iso:country":"US",
    "sg:address":"2775 Mount Ephraim Ave",
    "sg:city":"Camden",
    "sg:classifiers":[
        {
            "category":"Organizations",
            "subcategory":"Religious Organization",
            "type":"Services"
        }
    ],
    "sg:phone":"+1   ",
    "sg:postcode":"08104",
    "sg:province":"NJ",
    "wof:name":"Joy of Lord",
    "wof:placetype":"venue"
},
  "geometry": {"coordinates":[-75.09741200000001,39.907649],"type":"Point"}
}