{
  "type": "Feature",
  "properties": {
    "iso:country":"US",
    "sg:address":"96 Linwood Plz",
    "sg:city":"Fort Lee",
    "sg:classifiers":[
        {
            "category":"Professional",
            "subcategory":"Management & Consulting",
            "type":"Services"
        }
    ],
    "sg:phone":"+1 201 585 8100",
    "sg:postcode":"07024",
    "sg:province":"NJ",
    "sg:tags":[
        "marketing",
        "program"
    ],
    "wof:name":"American Audio Svc Bureau",
    "wof:placetype":"venue"
},
  "geometry": {"coordinates":[-73.967997,40.861236],"type":"Point"}
}