{
  "type": "Feature",
  "properties": {
    "addr:full":"13 5th Ave Avenel NJ 07001",
    "addr:housenumber":"13",
    "addr:postcode":"07001",
    "addr:street":"5Th Ave",
    "iso:country":"US",
    "sg:address":"13 5th Ave",
    "sg:city":"Avenel",
    "sg:classifiers":[
        {
            "category":"Marine",
            "type":"Transportation"
        }
    ],
    "sg:phone":"+1 732 634 4423",
    "sg:postcode":"07001",
    "sg:province":"NJ",
    "sg:tags":[
        "water",
        "transport"
    ],
    "wof:name":"Reckord Maritime Inc",
    "wof:placetype":"venue"
},
  "geometry": {"coordinates":[-74.280016,40.577531],"type":"Point"}
}