{
  "type": "Feature",
  "properties": {
    "iso:country":"US",
    "sg:address":"361 Union Ave",
    "sg:city":"Bridgewater",
    "sg:classifiers":[
        {
            "category":"Professional",
            "subcategory":"Business Services",
            "type":"Services"
        }
    ],
    "sg:phone":"+1 908 231 1119",
    "sg:postcode":"08807",
    "sg:province":"NJ",
    "sg:tags":[
        "notary"
    ],
    "wof:name":"Mosselle Notary Public",
    "wof:placetype":"venue"
},
  "geometry": {"coordinates":[-74.585223,40.570515],"type":"Point"}
}