{
  "type": "Feature",
  "properties": {
    "addr:full":"1017 Virgil Ave Ridgefield NJ 07657",
    "addr:housenumber":"1017",
    "addr:postcode":"07657",
    "addr:street":"Virgil Ave",
    "iso:country":"US",
    "sg:address":"1017 Virgil Ave",
    "sg:city":"Ridgefield",
    "sg:classifiers":[
        {
            "category":"Retail",
            "subcategory":"Auto Repair",
            "type":"Services"
        }
    ],
    "sg:phone":"+1 201 941 8288",
    "sg:postcode":"07657",
    "sg:province":"NJ",
    "wof:name":"C & C Auto Repair",
    "wof:placetype":"venue"
},
  "geometry": {"coordinates":[-74.006897,40.840401],"type":"Point"}
}