{
  "type": "Feature",
  "properties": {
    "iso:country":"US",
    "sg:address":"51 Fox Trail Rd",
    "sg:city":"Sparta",
    "sg:classifiers":[
        {
            "category":"Manufacturing",
            "subcategory":"Textiles",
            "type":"Manufacturing & Wholesale Goods"
        }
    ],
    "sg:phone":"+1 973 729 9997",
    "sg:postcode":"07871",
    "sg:province":"NJ",
    "wof:name":"A Rifkin Co",
    "wof:placetype":"venue"
},
  "geometry": {"coordinates":[-74.56156,41.040716],"type":"Point"}
}