{
  "type": "Feature",
  "properties": {
    "iso:country":"US",
    "sg:address":"17 Parker Ave",
    "sg:city":"Maplewood",
    "sg:classifiers":[
        {
            "category":"Education",
            "subcategory":"School",
            "type":"Public Place"
        }
    ],
    "sg:phone":"+1 973 762 5600",
    "sg:postcode":"07040",
    "sg:province":"NJ",
    "wof:name":"Columbia Senior High School",
    "wof:placetype":"venue"
},
  "geometry": {"coordinates":[-74.267877,40.735481],"type":"Point"}
}