{
  "type": "Feature",
  "properties": {
    "addr:full":"3 2nd St Jersey City NJ 07302",
    "addr:housenumber":"3",
    "addr:postcode":"07302",
    "addr:street":"2Nd St",
    "iso:country":"US",
    "sg:address":"3 2nd St",
    "sg:city":"Jersey City",
    "sg:classifiers":[
        {
            "category":"Professional",
            "subcategory":"Research",
            "type":"Services"
        }
    ],
    "sg:phone":"+1 201 792 4797",
    "sg:postcode":"07302",
    "sg:province":"NJ",
    "sg:tags":[
        "laboratory"
    ],
    "wof:name":"Lab Co",
    "wof:placetype":"venue"
},
  "geometry": {"coordinates":[-74.036496,40.72164],"type":"Point"}
}