{
  "type": "Feature",
  "properties": {
    "iso:country":"US",
    "sg:address":"7 Terminal B",
    "sg:city":"Newark",
    "sg:classifiers":[
        {
            "category":"Airline",
            "type":"Transportation"
        }
    ],
    "sg:phone":"+1 973 643 3042",
    "sg:postcode":"07114",
    "sg:province":"NJ",
    "sg:tags":[
        "company"
    ],
    "wof:name":"El Al Israel Airlines",
    "wof:placetype":"venue"
},
  "geometry": {"coordinates":[-74.176872,40.690912],"type":"Point"}
}