{
  "type": "Feature",
  "properties": {
    "addr:full":"222 Wanaque Ave Pompton Lakes NJ 07442",
    "addr:housenumber":"222",
    "addr:postcode":"07442",
    "addr:street":"Wanaque Ave",
    "iso:country":"US",
    "sg:address":"222 Wanaque Ave",
    "sg:city":"Pompton Lakes",
    "sg:classifiers":[
        {
            "category":"Home & Garden",
            "subcategory":"Carpets & Floor Coverings",
            "type":"Retail Goods"
        }
    ],
    "sg:phone":"+1 973 839 4919",
    "sg:postcode":"07442",
    "sg:province":"NJ",
    "sg:tags":[
        "carpeting"
    ],
    "wof:name":"Rug Liquidators",
    "wof:placetype":"venue"
},
  "geometry": {"coordinates":[-74.291702,41.004799],"type":"Point"}
}