{
  "type": "Feature",
  "properties": {
    "iso:country":"US",
    "sg:address":"301 N Raleigh Ave",
    "sg:city":"Atlantic City",
    "sg:classifiers":[
        {
            "category":"Manufacturing",
            "subcategory":"Printing",
            "type":"Manufacturing & Wholesale Goods"
        }
    ],
    "sg:phone":"+1 609 348 1555",
    "sg:postcode":"08401",
    "sg:province":"NJ",
    "sg:tags":[
        "commercial"
    ],
    "wof:name":"Pasttimes ATL Cy Postcards",
    "wof:placetype":"venue"
},
  "geometry": {"coordinates":[-74.463965,39.352098],"type":"Point"}
}