{
  "type": "Feature",
  "properties": {
    "iso:country":"US",
    "sg:address":"18 Fox Dr",
    "sg:city":"Jackson",
    "sg:classifiers":[
        {
            "category":"Professional",
            "type":"Services"
        }
    ],
    "sg:phone":"+1 732 928 6059",
    "sg:postcode":"08527",
    "sg:province":"NJ",
    "sg:tags":[
        "establishment"
    ],
    "wof:name":"Premier At Fox Hollow",
    "wof:placetype":"venue"
},
  "geometry": {"coordinates":[-74.269884,40.143355],"type":"Point"}
}