{
  "type": "Feature",
  "properties": {
    "iso:country":"US",
    "sg:address":"4 S 3rd Ave",
    "sg:city":"Highland Park",
    "sg:classifiers":[
        {
            "category":"Taxi",
            "type":"Transportation"
        }
    ],
    "sg:phone":"+1 732 545 2300",
    "sg:postcode":"08904",
    "sg:province":"NJ",
    "sg:tags":[
        "taxicab"
    ],
    "wof:name":"A-A Checker Cab Brunswick Cab",
    "wof:placetype":"venue"
},
  "geometry": {"coordinates":[-74.427487,40.497751],"type":"Point"}
}