{
  "type": "Feature",
  "properties": {
    "addr:full":"75 Apple Ave North Middletown NJ 07748",
    "addr:housenumber":"75",
    "addr:postcode":"07748",
    "addr:street":"Apple Ave North",
    "iso:country":"US",
    "sg:address":"75 Apple Ave",
    "sg:city":"North Middletown",
    "sg:classifiers":[
        {
            "category":"Professional",
            "type":"Services"
        }
    ],
    "sg:phone":"+1 732 872 8412",
    "sg:postcode":"07748",
    "sg:province":"NJ",
    "sg:tags":[
        "establishment"
    ],
    "wof:name":"SDDS Inc",
    "wof:placetype":"venue"
},
  "geometry": {"coordinates":[-74.12015100000001,40.432115],"type":"Point"}
}