{
  "type": "Feature",
  "properties": {
    "addr:full":"19 Rider Ct Newark NJ 07103",
    "addr:housenumber":"19",
    "addr:postcode":"07103",
    "addr:street":"Rider Ct",
    "iso:country":"US",
    "sg:address":"19 Rider Ct",
    "sg:city":"Newark",
    "sg:classifiers":[
        {
            "category":"Shopping",
            "subcategory":"Catalog Store",
            "type":"Retail Goods"
        }
    ],
    "sg:phone":"+1   ",
    "sg:postcode":"07103",
    "sg:province":"NJ",
    "sg:tags":[
        "house",
        "mail"
    ],
    "wof:name":"Wealth Builders Only",
    "wof:placetype":"venue"
},
  "geometry": {"coordinates":[-74.182726,40.736566],"type":"Point"}
}