{
  "type": "Feature",
  "properties": {
    "addr:full":"348 Lanza Ave Garfield NJ 07026",
    "addr:housenumber":"348",
    "addr:postcode":"07026",
    "addr:street":"Lanza Ave",
    "iso:country":"US",
    "sg:address":"348 Lanza Ave",
    "sg:city":"Garfield",
    "sg:classifiers":[
        {
            "category":"Restaurant",
            "type":"Food & Drink"
        }
    ],
    "sg:phone":"+1   ",
    "sg:postcode":"07026",
    "sg:province":"NJ",
    "sg:tags":[
        "eating"
    ],
    "wof:name":"Jumbos Luncheonette",
    "wof:placetype":"venue"
},
  "geometry": {"coordinates":[-74.11033999999999,40.889027],"type":"Point"}
}