{
  "type": "Feature",
  "properties": {
    "iso:country":"US",
    "sg:address":"2201 Federal St",
    "sg:city":"Camden",
    "sg:classifiers":[
        {
            "category":"Retail",
            "subcategory":"Self-service Laundry",
            "type":"Services"
        }
    ],
    "sg:phone":"+1 609 471 8390",
    "sg:postcode":"08105",
    "sg:province":"NJ",
    "wof:name":"Camden Cleaning Ctr",
    "wof:placetype":"venue"
},
  "geometry": {"coordinates":[-75.09151799999999,39.945789],"type":"Point"}
}