{
  "type": "Feature",
  "properties": {
    "iso:country":"US",
    "sg:address":"1700 State Rte 37",
    "sg:city":"Toms River",
    "sg:classifiers":[
        {
            "category":"Professional",
            "type":"Services"
        }
    ],
    "sg:phone":"+1 732 341 1644",
    "sg:postcode":"08757",
    "sg:province":"NJ",
    "sg:tags":[
        "establishment"
    ],
    "wof:name":"S & J Platkin",
    "wof:placetype":"venue"
},
  "geometry": {"coordinates":[-74.26998399999999,39.991685],"type":"Point"}
}