{
  "type": "Feature",
  "properties": {
    "addr:full":"468 Harrison Ave Lodi NJ 07644",
    "addr:housenumber":"468",
    "addr:postcode":"07644",
    "addr:street":"Harrison Ave",
    "iso:country":"US",
    "sg:address":"468 Harrison Ave",
    "sg:city":"Lodi",
    "sg:classifiers":[
        {
            "category":"Real Estate",
            "subcategory":"Real Estate Agent",
            "type":"Services"
        }
    ],
    "sg:phone":"+1   ",
    "sg:postcode":"07644",
    "sg:province":"NJ",
    "wof:name":"David M Tarallo",
    "wof:placetype":"venue"
},
  "geometry": {"coordinates":[-74.09290900000001,40.882449],"type":"Point"}
}