{
  "type": "Feature",
  "properties": {
    "addr:full":"116 Saint Lawrence Blvd Brick NJ 08723",
    "addr:housenumber":"116",
    "addr:postcode":"08723",
    "addr:street":"Saint Lawrence Blvd",
    "iso:country":"US",
    "sg:address":"116 Saint Lawrence Blvd",
    "sg:city":"Brick",
    "sg:classifiers":[
        {
            "category":"Building & Trades",
            "subcategory":"Plumbing",
            "type":"Services"
        }
    ],
    "sg:phone":"+1 732 920 9124",
    "sg:postcode":"08723",
    "sg:province":"NJ",
    "sg:tags":[
        "contractor"
    ],
    "wof:name":"Spontak Steven G Plumbing & H",
    "wof:placetype":"venue"
},
  "geometry": {"coordinates":[-74.085171,40.018879],"type":"Point"}
}