{
  "type": "Feature",
  "properties": {
    "addr:full":"40 Stella Dr Bridgewater NJ 08807",
    "addr:housenumber":"40",
    "addr:postcode":"08807",
    "addr:street":"Stella Dr",
    "iso:country":"US",
    "sg:address":"40 Stella Dr",
    "sg:city":"Bridgewater",
    "sg:classifiers":[
        {
            "category":"Manufacturing",
            "subcategory":"Tools & Machinery",
            "type":"Manufacturing & Wholesale Goods"
        }
    ],
    "sg:phone":"+1 908 526 8526",
    "sg:postcode":"08807",
    "sg:province":"NJ",
    "sg:tags":[
        "photographic",
        "mfg"
    ],
    "wof:name":"East 33 Productions",
    "wof:placetype":"venue"
},
  "geometry": {"coordinates":[-74.617879,40.613403],"type":"Point"}
}