{
  "type": "Feature",
  "properties": {
    "addr:full":"16 Hanover Rd East Hanover NJ 07936",
    "addr:housenumber":"16",
    "addr:postcode":"07936",
    "addr:street":"Hanover Rd",
    "iso:country":"US",
    "sg:address":"16 Hanover Rd",
    "sg:city":"East Hanover",
    "sg:classifiers":[
        {
            "category":"Restaurant",
            "type":"Food & Drink"
        }
    ],
    "sg:phone":"+1   ",
    "sg:postcode":"07936",
    "sg:province":"NJ",
    "sg:tags":[
        "eating"
    ],
    "wof:name":"Hanover Manor",
    "wof:placetype":"venue"
},
  "geometry": {"coordinates":[-74.37096,40.800678],"type":"Point"}
}