{
  "type": "Feature",
  "properties": {
    "addr:full":"3477 Us Highway 1 Princeton NJ 08540",
    "addr:housenumber":"3477",
    "addr:postcode":"08540",
    "addr:street":"Us Highway 1",
    "iso:country":"US",
    "sg:address":"3477 Us Highway 1",
    "sg:city":"Princeton",
    "sg:classifiers":[
        {
            "category":"Restaurant",
            "type":"Food & Drink"
        }
    ],
    "sg:menulink":"http://www.allmenus.com/nj/west-windsor/181747-wendys/menu/",
    "sg:phone":"+1 609 514 8790",
    "sg:postcode":"08540",
    "sg:province":"NJ",
    "sg:tags":[
        "burger",
        "american",
        "soup"
    ],
    "wof:name":"Wendy's",
    "wof:placetype":"venue"
},
  "geometry": {"coordinates":[-74.667305,40.307357],"type":"Point"}
}