{
  "type": "Feature",
  "properties": {
    "iso:country":"US",
    "sg:address":"195 Lee Ln",
    "sg:city":"Cape May Court House",
    "sg:classifiers":[
        {
            "category":"Building & Trades",
            "subcategory":"Construction",
            "type":"Services"
        }
    ],
    "sg:phone":"+1 609 465 0650",
    "sg:postcode":"08210",
    "sg:province":"NJ",
    "sg:tags":[
        "house"
    ],
    "wof:name":"LWM Builders",
    "wof:placetype":"venue"
},
  "geometry": {"coordinates":[-74.82999100000001,39.07292],"type":"Point"}
}