{
  "type": "Feature",
  "properties": {
    "addr:full":"23 Ocean St Cape May NJ 08204",
    "addr:housenumber":"23",
    "addr:postcode":"08204",
    "addr:street":"Ocean St",
    "iso:country":"US",
    "sg:address":"23 Ocean St",
    "sg:city":"Cape May",
    "sg:classifiers":[
        {
            "category":"Professional",
            "type":"Services"
        }
    ],
    "sg:phone":"+1   ",
    "sg:postcode":"08204",
    "sg:province":"NJ",
    "wof:name":"23 Ocean LLC A New Jersey Ltd",
    "wof:placetype":"venue"
},
  "geometry": {"coordinates":[-74.919611,38.93078],"type":"Point"}
}