{
  "type": "Feature",
  "properties": {
    "addr:full":"232 Clayton Ave Monroeville NJ 08343",
    "addr:housenumber":"232",
    "addr:postcode":"08343",
    "addr:street":"Clayton Ave",
    "iso:country":"US",
    "sg:address":"232 Clayton Ave",
    "sg:city":"Monroeville",
    "sg:classifiers":[
        {
            "category":"Shopping",
            "type":"Retail Goods"
        },
        {
            "category":"Building & Trades",
            "subcategory":"Pest Control",
            "type":"Services"
        }
    ],
    "sg:phone":"+1 856 863 4168",
    "sg:postcode":"08343",
    "sg:province":"NJ",
    "sg:tags":[
        "product",
        "animal"
    ],
    "wof:name":"Acp Animal Control Products",
    "wof:placetype":"venue"
},
  "geometry": {"coordinates":[-75.12017400000001,39.655582],"type":"Point"}
}