{
  "type": "Feature",
  "properties": {
    "iso:country":"US",
    "sg:address":"50 Dey St",
    "sg:city":"Jersey City",
    "sg:classifiers":[
        {
            "category":"Manufacturing",
            "subcategory":"Printing",
            "type":"Manufacturing & Wholesale Goods"
        }
    ],
    "sg:phone":"+1 201 653 3030",
    "sg:postcode":"07306",
    "sg:province":"NJ",
    "sg:tags":[
        "commercial"
    ],
    "wof:name":"Quick Service Manuel Inc",
    "wof:placetype":"venue"
},
  "geometry": {"coordinates":[-74.06705100000001,40.737658],"type":"Point"}
}