{
  "type": "Feature",
  "properties": {
    "iso:country":"US",
    "sg:address":"720 King Georges Post Rd",
    "sg:city":"Fords",
    "sg:classifiers":[
        {
            "category":"Shopping",
            "subcategory":"Catalog Store",
            "type":"Retail Goods"
        }
    ],
    "sg:phone":"+1   ",
    "sg:postcode":"08863",
    "sg:province":"NJ",
    "sg:tags":[
        "cake",
        "mail",
        "order",
        "for",
        "rum"
    ],
    "wof:name":"Caribbean Cake Connoisseurs",
    "wof:placetype":"venue"
},
  "geometry": {"coordinates":[-74.30928299999999,40.531481],"type":"Point"}
}