{
  "type": "Feature",
  "properties": {
    "iso:country":"US",
    "sg:address":"6515 Kennedy Blvd",
    "sg:city":"West New York",
    "sg:classifiers":[
        {
            "category":"Freight",
            "type":"Transportation"
        }
    ],
    "sg:phone":"+1 201 869 6915",
    "sg:postcode":"07047",
    "sg:province":"NJ",
    "wof:name":"Metrofreight International",
    "wof:placetype":"venue"
},
  "geometry": {"coordinates":[-73.996934,40.80723],"type":"Point"}
}