{
  "type": "Feature",
  "properties": {
    "iso:country":"US",
    "sg:address":"22 N Central Ave",
    "sg:city":"Sicklerville",
    "sg:classifiers":[
        {
            "category":"Arts & Performance",
            "subcategory":"Theater",
            "type":"Entertainment"
        }
    ],
    "sg:phone":"+1 856 728 8112",
    "sg:postcode":"08081",
    "sg:province":"NJ",
    "sg:tags":[
        "live",
        "music"
    ],
    "wof:name":"Soundtracts Entertainment",
    "wof:placetype":"venue"
},
  "geometry": {"coordinates":[-74.91988499999999,39.711926],"type":"Point"}
}