{
  "type": "Feature",
  "properties": {
    "addr:full":"446 Washington St Rahway NJ 07065",
    "addr:housenumber":"446",
    "addr:postcode":"07065",
    "addr:street":"Washington St",
    "iso:country":"US",
    "sg:address":"446 Washington St",
    "sg:city":"Rahway",
    "sg:classifiers":[
        {
            "category":"Wholesale",
            "subcategory":"Non-durable Goods",
            "type":"Manufacturing & Wholesale Goods"
        }
    ],
    "sg:phone":"+1 732 382 2226",
    "sg:postcode":"07065",
    "sg:province":"NJ",
    "wof:name":"E R M Enterprise Inc",
    "wof:placetype":"venue"
},
  "geometry": {"coordinates":[-74.265344,40.606976],"type":"Point"}
}