{
  "type": "Feature",
  "properties": {
    "addr:full":"1548 Atlantic Ave Atlantic City NJ 08401",
    "addr:housenumber":"1548",
    "addr:postcode":"08401",
    "addr:street":"Atlantic Ave",
    "iso:country":"US",
    "sg:address":"1548 Atlantic Ave",
    "sg:city":"Atlantic City",
    "sg:classifiers":[
        {
            "category":"Government",
            "subcategory":"Office",
            "type":"Public Place"
        }
    ],
    "sg:phone":"+1 609 441 3500",
    "sg:postcode":"08401",
    "sg:province":"NJ",
    "sg:tags":[
        "state",
        "resource"
    ],
    "wof:name":"Human Service Dept",
    "wof:placetype":"venue"
},
  "geometry": {"coordinates":[-74.43007900000001,39.361285],"type":"Point"}
}