{
  "type": "Feature",
  "properties": {
    "iso:country":"US",
    "sg:address":"151 Parkway",
    "sg:city":"Mountainside",
    "sg:classifiers":[
        {
            "category":"Professional",
            "subcategory":"Detective & Security Services",
            "type":"Services"
        }
    ],
    "sg:phone":"+1 908 232 7582",
    "sg:postcode":"07092",
    "sg:province":"NJ",
    "sg:tags":[
        "investigator"
    ],
    "wof:name":"Betyeman Detective Agency",
    "wof:placetype":"venue"
},
  "geometry": {"coordinates":[-74.35077099999999,40.672143],"type":"Point"}
}