{
  "type": "Feature",
  "properties": {
    "iso:country":"US",
    "sg:address":"100 1st St Ste 302",
    "sg:city":"Hackensack",
    "sg:classifiers":[
        {
            "category":"Health Services",
            "subcategory":"Hospital",
            "type":"Services"
        },
        {
            "category":"Community Center",
            "type":"Public Place"
        }
    ],
    "sg:phone":"+1 201 489 1349",
    "sg:postcode":"07601",
    "sg:province":"NJ",
    "sg:tags":[
        "medical"
    ],
    "wof:name":"Hackensack Medical Center",
    "wof:placetype":"venue"
},
  "geometry": {"coordinates":[-74.051963,40.884971],"type":"Point"}
}