{
  "type": "Feature",
  "properties": {
    "iso:country":"US",
    "sg:address":"1842 Merrimac Dr",
    "sg:city":"Toms River",
    "sg:classifiers":[
        {
            "category":"Personal",
            "subcategory":"Beauty Salon",
            "type":"Services"
        }
    ],
    "sg:phone":"+1 732 506 0556",
    "sg:postcode":"08753",
    "sg:province":"NJ",
    "sg:tags":[
        "shop"
    ],
    "wof:name":"Triple Eights Hairdressers LLC",
    "wof:placetype":"venue"
},
  "geometry": {"coordinates":[-74.145979,39.989976],"type":"Point"}
}