{
  "type": "Feature",
  "properties": {
    "addr:full":"32 Haddon Ave Haddon Twp NJ 08108",
    "addr:housenumber":"32",
    "addr:postcode":"08108",
    "addr:street":"Haddon Ave",
    "iso:country":"US",
    "sg:address":"32 Haddon Ave",
    "sg:city":"Haddon Twp",
    "sg:classifiers":[
        {
            "category":"Personal",
            "subcategory":"Beauty Salon",
            "type":"Services"
        }
    ],
    "sg:phone":"+1 856 854 9600",
    "sg:postcode":"08108",
    "sg:province":"NJ",
    "sg:website":"www.haircuttery.com",
    "wof:name":"Haddon Shops Hair Cuttery",
    "wof:placetype":"venue"
},
  "geometry": {"coordinates":[-75.05469600000001,39.912309],"type":"Point"}
}