{
  "type": "Feature",
  "properties": {
    "iso:country":"US",
    "sg:address":"34 Chapin Rd",
    "sg:city":"Pine Brook",
    "sg:classifiers":[
        {
            "category":"Freight",
            "type":"Transportation"
        }
    ],
    "sg:phone":"+1 973 808 7200",
    "sg:postcode":"07058",
    "sg:province":"NJ",
    "sg:tags":[
        "trucking"
    ],
    "wof:name":"Yellow Freight System Inc",
    "wof:placetype":"venue"
},
  "geometry": {"coordinates":[-74.33740400000001,40.855971],"type":"Point"}
}