{
  "type": "Feature",
  "properties": {
    "iso:country":"US",
    "sg:address":"169 Frelinghuysen Ave",
    "sg:city":"Newark",
    "sg:classifiers":[
        {
            "category":"Professional",
            "subcategory":"Business Services",
            "type":"Services"
        }
    ],
    "sg:phone":"+1 973 824 2333",
    "sg:postcode":"07114",
    "sg:province":"NJ",
    "sg:tags":[
        "delivery",
        "courier"
    ],
    "wof:name":"International Shipping Co USA Inc",
    "wof:placetype":"venue"
},
  "geometry": {"coordinates":[-74.18740099999999,40.715801],"type":"Point"}
}