{
  "type": "Feature",
  "properties": {
    "iso:country":"US",
    "sg:address":"1470 State Rte 36",
    "sg:city":"Hazlet",
    "sg:classifiers":[
        {
            "category":"Shopping",
            "type":"Retail Goods"
        }
    ],
    "sg:phone":"+1   ",
    "sg:postcode":"07730",
    "sg:province":"NJ",
    "sg:tags":[
        "merchandise"
    ],
    "wof:name":"Leslies Swimming Pool Supplies",
    "wof:placetype":"venue"
},
  "geometry": {"coordinates":[-74.189071,40.429375],"type":"Point"}
}