{
  "type": "Feature",
  "properties": {
    "iso:country":"US",
    "sg:address":"12 N Providence Ave",
    "sg:city":"Atlantic City",
    "sg:classifiers":[
        {
            "category":"Health Services",
            "subcategory":"Clinic",
            "type":"Services"
        }
    ],
    "sg:phone":"+1   ",
    "sg:postcode":"08401",
    "sg:province":"NJ",
    "sg:tags":[
        "specialty",
        "outpatient"
    ],
    "wof:name":"Providence House",
    "wof:placetype":"venue"
},
  "geometry": {"coordinates":[-74.45370200000001,39.353623],"type":"Point"}
}