{
  "type": "Feature",
  "properties": {
    "addr:full":"3200 Pacific Ave Atlantic City NJ 08401",
    "addr:housenumber":"3200",
    "addr:postcode":"08401",
    "addr:street":"Pacific Ave",
    "iso:country":"US",
    "sg:address":"3200 Pacific Ave",
    "sg:city":"Atlantic City",
    "sg:classifiers":[
        {
            "category":"Travel",
            "subcategory":"Hotels & Motels",
            "type":"Entertainment"
        }
    ],
    "sg:phone":"+1   ",
    "sg:postcode":"08401",
    "sg:province":"NJ",
    "sg:tags":[
        "building",
        "operator",
        "operation",
        "apartment"
    ],
    "wof:name":"El Greco Motel",
    "wof:placetype":"venue"
},
  "geometry": {"coordinates":[-74.44964899999999,39.351424],"type":"Point"}
}