{
  "type": "Feature",
  "properties": {
    "iso:country":"US",
    "sg:address":"365 Gilbert St",
    "sg:city":"Ridgewood",
    "sg:classifiers":[
        {
            "category":"Professional",
            "subcategory":"Detective & Security Services",
            "type":"Services"
        }
    ],
    "sg:phone":"+1 201 493 4963",
    "sg:postcode":"07450",
    "sg:province":"NJ",
    "sg:tags":[
        "system"
    ],
    "wof:name":"Cleverguard LLC",
    "wof:placetype":"venue"
},
  "geometry": {"coordinates":[-74.112346,40.972602],"type":"Point"}
}