{
  "type": "Feature",
  "properties": {
    "addr:full":"480 Broadway Newark NJ 07104",
    "addr:housenumber":"480",
    "addr:postcode":"07104",
    "addr:street":"Broadway",
    "iso:country":"US",
    "sg:address":"480 Broadway",
    "sg:city":"Newark",
    "sg:classifiers":[
        {
            "category":"Shopping",
            "subcategory":"Music",
            "type":"Retail Goods"
        }
    ],
    "sg:phone":"+1   ",
    "sg:postcode":"07104",
    "sg:province":"NJ",
    "wof:name":"City Sounds Record Shop",
    "wof:placetype":"venue"
},
  "geometry": {"coordinates":[-74.164106,40.767362],"type":"Point"}
}