{
  "type": "Feature",
  "properties": {
    "iso:country":"US",
    "sg:address":"347 Market St",
    "sg:city":"Paterson",
    "sg:classifiers":[
        {
            "category":"Restaurant",
            "type":"Food & Drink"
        }
    ],
    "sg:phone":"+1 973 925 8488",
    "sg:postcode":"07501",
    "sg:province":"NJ",
    "sg:tags":[
        "eating"
    ],
    "wof:name":"Ruby Garden",
    "wof:placetype":"venue"
},
  "geometry": {"coordinates":[-74.16406000000001,40.914617],"type":"Point"}
}