{
  "type": "Feature",
  "properties": {
    "iso:country":"US",
    "sg:address":"12 Leo Pl",
    "sg:city":"Wayne",
    "sg:classifiers":[
        {
            "category":"Retail",
            "subcategory":"Auto Repair",
            "type":"Services"
        }
    ],
    "sg:phone":"+1 973 305 1572",
    "sg:postcode":"07470",
    "sg:province":"NJ",
    "sg:tags":[
        "truck"
    ],
    "wof:name":"Dob's Truck Repair",
    "wof:placetype":"venue"
},
  "geometry": {"coordinates":[-74.277366,40.928225],"type":"Point"}
}