{
  "type": "Feature",
  "properties": {
    "addr:full":"351 Evelyn St Paramus NJ 07652",
    "addr:housenumber":"351",
    "addr:postcode":"07652",
    "addr:street":"Evelyn St",
    "iso:country":"US",
    "sg:address":"351 Evelyn St",
    "sg:city":"Paramus",
    "sg:classifiers":[
        {
            "category":"Health Services",
            "subcategory":"Health Practitioner",
            "type":"Services"
        }
    ],
    "sg:phone":"+1 201 986 1430",
    "sg:postcode":"07652",
    "sg:province":"NJ",
    "sg:tags":[
        "therapist",
        "physical"
    ],
    "sg:website":"www.healthsouth.com",
    "wof:name":"Healthsouth Rehabilitation Ctr",
    "wof:placetype":"venue"
},
  "geometry": {"coordinates":[-74.0702,40.944678],"type":"Point"}
}