{
  "type": "Feature",
  "properties": {
    "iso:country":"US",
    "sg:address":"130 Madison Ave",
    "sg:city":"Hasbrouck Heights",
    "sg:classifiers":[
        {
            "category":"Manufacturing",
            "subcategory":"Printing",
            "type":"Manufacturing & Wholesale Goods"
        }
    ],
    "sg:phone":"+1 201 288 1298",
    "sg:postcode":"07604",
    "sg:province":"NJ",
    "sg:tags":[
        "commercial"
    ],
    "wof:name":"Tyco Tees",
    "wof:placetype":"venue"
},
  "geometry": {"coordinates":[-74.075289,40.865929],"type":"Point"}
}