{
  "type": "Feature",
  "properties": {
    "addr:full":"5 Mockingbird Ln Dayton NJ 08810",
    "addr:housenumber":"5",
    "addr:postcode":"08810",
    "addr:street":"Mockingbird Ln",
    "iso:country":"US",
    "sg:address":"5 Mockingbird Ln",
    "sg:city":"Dayton",
    "sg:classifiers":[
        {
            "category":"Building & Trades",
            "subcategory":"Plumbing",
            "type":"Services"
        }
    ],
    "sg:phone":"+1 732 329 0815",
    "sg:postcode":"08810",
    "sg:province":"NJ",
    "sg:tags":[
        "contractor"
    ],
    "wof:name":"Medina Hvac Services",
    "wof:placetype":"venue"
},
  "geometry": {"coordinates":[-74.51720899999999,40.387582],"type":"Point"}
}