{
  "type": "Feature",
  "properties": {
    "iso:country":"US",
    "sg:address":"26 S Pennsylvania Ave",
    "sg:city":"Atlantic City",
    "sg:classifiers":[
        {
            "category":"Government",
            "subcategory":"Office",
            "type":"Public Place"
        }
    ],
    "sg:phone":"+1 609 441 3100",
    "sg:postcode":"08401",
    "sg:province":"NJ",
    "sg:tags":[
        "state"
    ],
    "wof:name":"Civil Rights Div",
    "wof:placetype":"venue"
},
  "geometry": {"coordinates":[-74.423519,39.362465],"type":"Point"}
}