{
  "type": "Feature",
  "properties": {
    "addr:full":"136 Rifle Camp Rd West Paterson NJ 07424",
    "addr:housenumber":"136",
    "addr:postcode":"07424",
    "addr:street":"Rifle Camp Rd West",
    "iso:country":"US",
    "sg:address":"136 Rifle Camp Rd",
    "sg:city":"West Paterson",
    "sg:classifiers":[
        {
            "category":"Building & Trades",
            "subcategory":"Locksmith",
            "type":"Services"
        }
    ],
    "sg:phone":"+1 888 348 3852",
    "sg:postcode":"07424",
    "sg:province":"NJ",
    "sg:tags":[
        "key"
    ],
    "wof:name":"24 Emergency Locksmith",
    "wof:placetype":"venue"
},
  "geometry": {"coordinates":[-74.186871,40.900232],"type":"Point"}
}