{
  "type": "Feature",
  "properties": {
    "addr:full":"28 Waterside Dr Little Ferry NJ 07643",
    "addr:housenumber":"28",
    "addr:postcode":"07643",
    "addr:street":"Waterside Dr",
    "iso:country":"US",
    "sg:address":"28 Waterside Dr",
    "sg:city":"Little Ferry",
    "sg:classifiers":[
        {
            "category":"Autos & Motor Vehicles",
            "subcategory":"Automobile Sales",
            "type":"Retail Goods"
        }
    ],
    "sg:phone":"+1 201 440 4333",
    "sg:postcode":"07643",
    "sg:province":"NJ",
    "sg:tags":[
        "limo"
    ],
    "wof:name":"Ams Limousine",
    "wof:placetype":"venue"
},
  "geometry": {"coordinates":[-74.03468100000001,40.838421],"type":"Point"}
}