{
  "type": "Feature",
  "properties": {
    "addr:full":"900 US Hwy 22 North Plainfield NJ 07060",
    "addr:housenumber":"900",
    "addr:postcode":"07060",
    "addr:street":"Us Hwy 22",
    "iso:country":"US",
    "sg:address":"900 US Hwy 22",
    "sg:city":"North Plainfield",
    "sg:classifiers":[
        {
            "category":"Retail",
            "subcategory":"Auto Repair",
            "type":"Services"
        }
    ],
    "sg:phone":"+1 908 754 0450",
    "sg:postcode":"07060",
    "sg:province":"NJ",
    "sg:tags":[
        "repairing",
        "automobile"
    ],
    "wof:name":"Pit Stop",
    "wof:placetype":"venue"
},
  "geometry": {"coordinates":[-74.445268,40.622853],"type":"Point"}
}