{
  "type": "Feature",
  "properties": {
    "iso:country":"US",
    "sg:address":"12 4th Ave",
    "sg:city":"Long Branch",
    "sg:classifiers":[
        {
            "category":"Bars & Pubs",
            "type":"Food & Drink"
        }
    ],
    "sg:phone":"+1   ",
    "sg:postcode":"07740",
    "sg:province":"NJ",
    "sg:tags":[
        "club",
        "night"
    ],
    "wof:name":"Off Broadway Cocktail Lounge",
    "wof:placetype":"venue"
},
  "geometry": {"coordinates":[-73.98940899999999,40.303286],"type":"Point"}
}