{
  "type": "Feature",
  "properties": {
    "iso:country":"US",
    "sg:address":"1114 Tanyard Rd",
    "sg:city":"Sewell",
    "sg:classifiers":[
        {
            "category":"Organizations",
            "subcategory":"Religious Organization",
            "type":"Services"
        }
    ],
    "sg:phone":"+1 856 468 9436",
    "sg:postcode":"08080",
    "sg:province":"NJ",
    "sg:tags":[
        "church"
    ],
    "wof:name":"John Three-Sixteen Assembly",
    "wof:placetype":"venue"
},
  "geometry": {"coordinates":[-75.124332,39.801775],"type":"Point"}
}