{
  "type": "Feature",
  "properties": {
    "iso:country":"US",
    "sg:address":"209 Main St",
    "sg:city":"Boonton",
    "sg:classifiers":[
        {
            "category":"Restaurant",
            "type":"Food & Drink"
        }
    ],
    "sg:phone":"+1   ",
    "sg:postcode":"07005",
    "sg:province":"NJ",
    "sg:tags":[
        "eating"
    ],
    "wof:name":"Boonton West Indian Restaurant",
    "wof:placetype":"venue"
},
  "geometry": {"coordinates":[-74.407943,40.903278],"type":"Point"}
}