{
  "type": "Feature",
  "properties": {
    "iso:country":"US",
    "sg:address":"764 Broadway",
    "sg:city":"Bayonne",
    "sg:classifiers":[
        {
            "category":"Manufacturing",
            "subcategory":"Metals",
            "type":"Manufacturing & Wholesale Goods"
        }
    ],
    "sg:phone":"+1 201 437 1871",
    "sg:postcode":"07002",
    "sg:province":"NJ",
    "sg:tags":[
        "product",
        "fabricated",
        "mfg"
    ],
    "wof:name":"Artistic Trophy & Awards",
    "wof:placetype":"venue"
},
  "geometry": {"coordinates":[-74.111351,40.672112],"type":"Point"}
}