{
  "type": "Feature",
  "properties": {
    "iso:country":"US",
    "sg:address":"80 Newfield Ave",
    "sg:city":"Edison",
    "sg:classifiers":[
        {
            "category":"Freight",
            "type":"Transportation"
        }
    ],
    "sg:phone":"+1 732 346 7171",
    "sg:postcode":"08837",
    "sg:province":"NJ",
    "wof:name":"Paramount Trnsp Systems Inc",
    "wof:placetype":"venue"
},
  "geometry": {"coordinates":[-74.345741,40.503086],"type":"Point"}
}