{
  "type": "Feature",
  "properties": {
    "iso:country":"US",
    "sg:address":"204 Bellevue Ave",
    "sg:city":"Montclair",
    "sg:classifiers":[
        {
            "category":"Health Services",
            "subcategory":"Dentist",
            "type":"Services"
        }
    ],
    "sg:phone":"+1 973 783 4491",
    "sg:postcode":"07043",
    "sg:province":"NJ",
    "sg:tags":[
        "pediatric"
    ],
    "wof:name":"Levi Mannie DDS Pedodontics",
    "wof:placetype":"venue"
},
  "geometry": {"coordinates":[-74.20610000000001,40.840698],"type":"Point"}
}