{
  "type": "Feature",
  "properties": {
    "iso:country":"US",
    "sg:address":"57 Weinmanns Blvd",
    "sg:city":"Wayne",
    "sg:classifiers":[
        {
            "category":"Building & Trades",
            "subcategory":"Construction",
            "type":"Services"
        }
    ],
    "sg:phone":"+1 973 595 5170",
    "sg:postcode":"07470",
    "sg:province":"NJ",
    "sg:tags":[
        "floor",
        "laying",
        "contractor"
    ],
    "wof:name":"Verrone Flooring LLC",
    "wof:placetype":"venue"
},
  "geometry": {"coordinates":[-74.220411,40.927],"type":"Point"}
}