{
  "type": "Feature",
  "properties": {
    "addr:full":"831 Carl Miller Blvd Camden NJ 08104",
    "addr:housenumber":"831",
    "addr:postcode":"08104",
    "addr:street":"Carl Miller Blvd",
    "iso:country":"US",
    "sg:address":"831 Carl Miller Blvd",
    "sg:city":"Camden",
    "sg:classifiers":[
        {
            "category":"Retail",
            "subcategory":"Funeral Services",
            "type":"Services"
        }
    ],
    "sg:phone":"+1 856 365 2966",
    "sg:postcode":"08104",
    "sg:province":"NJ",
    "sg:tags":[
        "cemetery"
    ],
    "wof:name":"Miller Carl Funeral Home",
    "wof:placetype":"venue"
},
  "geometry": {"coordinates":[-75.111589,39.923603],"type":"Point"}
}