{
  "type": "Feature",
  "properties": {
    "iso:country":"US",
    "sg:address":"150 Fred Wehran Dr",
    "sg:city":"Teterboro",
    "sg:classifiers":[
        {
            "category":"Retail",
            "subcategory":"Laundry & Dry Cleaning",
            "type":"Services"
        },
        {
            "category":"Airport",
            "type":"Transportation"
        }
    ],
    "sg:phone":"+1 201 288 5758",
    "sg:postcode":"07608",
    "sg:province":"NJ",
    "sg:tags":[
        "drycleaning",
        "plant",
        "aircraft",
        "maintenance"
    ],
    "wof:name":"Jets Cleaners Inc",
    "wof:placetype":"venue"
},
  "geometry": {"coordinates":[-74.061899,40.862411],"type":"Point"}
}