{
  "type": "Feature",
  "properties": {
    "addr:full":"132 W End Ave Long Branch NJ 07740",
    "addr:housenumber":"132",
    "addr:postcode":"07740",
    "addr:street":"W End Ave",
    "iso:country":"US",
    "sg:address":"132 W End Ave",
    "sg:city":"Long Branch",
    "sg:classifiers":[
        {
            "category":"Social Services",
            "type":"Services"
        }
    ],
    "sg:phone":"+1 732 728 1950",
    "sg:postcode":"07740",
    "sg:province":"NJ",
    "sg:tags":[
        "organization",
        "welfare"
    ],
    "wof:name":"YMCA",
    "wof:placetype":"venue"
},
  "geometry": {"coordinates":[-73.985969,40.285591],"type":"Point"}
}