{
  "type": "Feature",
  "properties": {
    "addr:full":"329 S Main St Barnegat NJ 08005",
    "addr:housenumber":"329",
    "addr:postcode":"08005",
    "addr:street":"S Main St",
    "iso:country":"US",
    "sg:address":"329 S Main St",
    "sg:city":"Barnegat",
    "sg:classifiers":[
        {
            "category":"Manufacturing",
            "subcategory":"Glass & Minerals",
            "type":"Manufacturing & Wholesale Goods"
        }
    ],
    "sg:phone":"+1 609 698 4441",
    "sg:postcode":"08005",
    "sg:province":"NJ",
    "sg:tags":[
        "item",
        "stained",
        "mfg"
    ],
    "wof:name":"Stained Glass Light House",
    "wof:placetype":"venue"
},
  "geometry": {"coordinates":[-74.22319899999999,39.753067],"type":"Point"}
}