{
  "type": "Feature",
  "properties": {
    "addr:full":"174 Ferry St Newark NJ 07105",
    "addr:housenumber":"174",
    "addr:postcode":"07105",
    "addr:street":"Ferry St",
    "iso:country":"US",
    "sg:address":"174 Ferry St",
    "sg:city":"Newark",
    "sg:classifiers":[
        {
            "category":"Banks & Credit Unions",
            "subcategory":"Bank",
            "type":"Services"
        }
    ],
    "sg:phone":"+1 973 344 1400",
    "sg:postcode":"07105",
    "sg:province":"NJ",
    "sg:website":"www.crownbankonline.com",
    "wof:name":"Crown Bank National",
    "wof:placetype":"venue"
},
  "geometry": {"coordinates":[-74.15770000000001,40.728802],"type":"Point"}
}