{
  "type": "Feature",
  "properties": {
    "iso:country":"US",
    "sg:address":"1685 N Olden Ave Exd",
    "sg:city":"Trenton",
    "sg:classifiers":[
        {
            "category":"Restaurant",
            "type":"Food & Drink"
        }
    ],
    "sg:phone":"+1 609 912 0355",
    "sg:postcode":"08638",
    "sg:province":"NJ",
    "wof:name":"Prince Fried Chicken",
    "wof:placetype":"venue"
},
  "geometry": {"coordinates":[-74.764779,40.246037],"type":"Point"}
}