{
  "type": "Feature",
  "properties": {
    "iso:country":"US",
    "sg:address":"1235 W Chestnut St",
    "sg:city":"Union",
    "sg:classifiers":[
        {
            "category":"Shopping",
            "subcategory":"Department Store",
            "type":"Retail Goods"
        }
    ],
    "sg:phone":"+1   ",
    "sg:postcode":"07083",
    "sg:province":"NJ",
    "wof:name":"Sears Roebuck and Co Inc",
    "wof:placetype":"venue"
},
  "geometry": {"coordinates":[-74.28910500000001,40.69116],"type":"Point"}
}