{
  "type": "Feature",
  "properties": {
    "iso:country":"US",
    "sg:address":"1126 Middletown Lincroft Rd",
    "sg:city":"Middletown",
    "sg:classifiers":[
        {
            "category":"Building & Trades",
            "subcategory":"Construction",
            "type":"Services"
        }
    ],
    "sg:phone":"+1 732 796 0749",
    "sg:postcode":"07748",
    "sg:province":"NJ",
    "sg:tags":[
        "home",
        "residential",
        "improvement"
    ],
    "wof:name":"Charlie Croce Construction",
    "wof:placetype":"venue"
},
  "geometry": {"coordinates":[-74.115607,40.369899],"type":"Point"}
}