{
  "type": "Feature",
  "properties": {
    "iso:country":"US",
    "sg:address":"16 Riverdale Ave",
    "sg:city":"Old Bridge",
    "sg:classifiers":[
        {
            "category":"Shopping",
            "subcategory":"Bicycles & Sporting Goods",
            "type":"Retail Goods"
        }
    ],
    "sg:phone":"+1 732 251 2456",
    "sg:postcode":"08857",
    "sg:province":"NJ",
    "sg:tags":[
        "bait",
        "fishing"
    ],
    "wof:name":"Bob & Troy's Bait & Tackle Shp",
    "wof:placetype":"venue"
},
  "geometry": {"coordinates":[-74.37484499999999,40.396931],"type":"Point"}
}