{
  "type": "Feature",
  "properties": {
    "iso:country":"US",
    "sg:address":"725 River Rd Ste 3",
    "sg:city":"Edgewater",
    "sg:classifiers":[
        {
            "category":"Retail",
            "subcategory":"Veterinary Services",
            "type":"Services"
        }
    ],
    "sg:phone":"+1 201 313 7000",
    "sg:postcode":"07020",
    "sg:province":"NJ",
    "sg:tags":[
        "veterinarian"
    ],
    "wof:name":"Freedman William K DVM",
    "wof:placetype":"venue"
},
  "geometry": {"coordinates":[-73.977501,40.820301],"type":"Point"}
}