{
  "type": "Feature",
  "properties": {
    "iso:country":"US",
    "sg:address":"148 Trinity Ave",
    "sg:city":"Blackwood",
    "sg:classifiers":[
        {
            "category":"Professional",
            "type":"Services"
        }
    ],
    "sg:phone":"+1   ",
    "sg:postcode":"08012",
    "sg:province":"NJ",
    "wof:name":"Behan Craft",
    "wof:placetype":"venue"
},
  "geometry": {"coordinates":[-75.059121,39.798141],"type":"Point"}
}