{
  "type": "Feature",
  "properties": {
    "iso:country":"US",
    "sg:address":"3014 Pacific Ave",
    "sg:city":"Wildwood",
    "sg:classifiers":[
        {
            "category":"Professional",
            "subcategory":"Accounting & Tax Preparation",
            "type":"Services"
        }
    ],
    "sg:phone":"+1 609 729 7634",
    "sg:postcode":"08260",
    "sg:province":"NJ",
    "sg:tags":[
        "accountant"
    ],
    "wof:name":"Mattera Dominick CPA Ea",
    "wof:placetype":"venue"
},
  "geometry": {"coordinates":[-74.81150100000001,38.9916],"type":"Point"}
}