{
  "type": "Feature",
  "properties": {
    "addr:full":"289 Main St Hackensack NJ 07601",
    "addr:housenumber":"289",
    "addr:postcode":"07601",
    "addr:street":"Main St",
    "iso:country":"US",
    "sg:address":"289 Main St",
    "sg:city":"Hackensack",
    "sg:classifiers":[
        {
            "category":"Communications",
            "type":"Services"
        }
    ],
    "sg:phone":"+1 201 996 0044",
    "sg:postcode":"07601",
    "sg:province":"NJ",
    "sg:tags":[
        "carrier",
        "radiotelephone",
        "communications-common"
    ],
    "wof:name":"Woletz, David",
    "wof:placetype":"venue"
},
  "geometry": {"coordinates":[-74.04111899999999,40.887354],"type":"Point"}
}