{
  "type": "Feature",
  "properties": {
    "iso:country":"US",
    "sg:address":"24 Washington St",
    "sg:city":"Mount Holly",
    "sg:classifiers":[
        {
            "category":"Taxi",
            "type":"Transportation"
        },
        {
            "category":"Airline",
            "type":"Transportation"
        }
    ],
    "sg:phone":"+1 609 267 4984",
    "sg:postcode":"08060",
    "sg:province":"NJ",
    "sg:tags":[
        "shuttle",
        "airport"
    ],
    "wof:name":"Mount Holly Taxi",
    "wof:placetype":"venue"
},
  "geometry": {"coordinates":[-74.78885699999999,39.992725],"type":"Point"}
}