{
  "type": "Feature",
  "properties": {
    "iso:country":"US",
    "sg:address":"2740 Kuser Rd",
    "sg:city":"Trenton",
    "sg:classifiers":[
        {
            "category":"Food & Beverages",
            "subcategory":"Meat & Fish",
            "type":"Retail Goods"
        }
    ],
    "sg:phone":"+1 609 588 8208",
    "sg:postcode":"08691",
    "sg:province":"NJ",
    "sg:tags":[
        "frozen"
    ],
    "sg:website":"www.schwans.com",
    "wof:name":"Schwan's Sales Enterprises",
    "wof:placetype":"venue"
},
  "geometry": {"coordinates":[-74.63911400000001,40.206932],"type":"Point"}
}