{
  "type": "Feature",
  "properties": {
    "iso:country":"US",
    "sg:address":"1100 State Rte 70",
    "sg:city":"Whiting",
    "sg:classifiers":[
        {
            "category":"Health Services",
            "subcategory":"Chiropractor",
            "type":"Services"
        }
    ],
    "sg:phone":"+1 732 716 1500",
    "sg:postcode":"08759",
    "sg:province":"NJ",
    "wof:name":"Nautilus Chiropractic",
    "wof:placetype":"venue"
},
  "geometry": {"coordinates":[-74.386369,39.964466],"type":"Point"}
}