{
  "type": "Feature",
  "properties": {
    "addr:full":"1451 State Rte 37 Toms River NJ 08755",
    "addr:housenumber":"1451",
    "addr:postcode":"08755",
    "addr:street":"State Rte 37",
    "iso:country":"US",
    "sg:address":"1451 State Rte 37",
    "sg:city":"Toms River",
    "sg:classifiers":[
        {
            "category":"Banks & Credit Unions",
            "subcategory":"Investment Brokerage",
            "type":"Services"
        }
    ],
    "sg:phone":"+1 732 473 1000",
    "sg:postcode":"08755",
    "sg:province":"NJ",
    "sg:tags":[
        "consultant",
        "planning",
        "financial"
    ],
    "wof:name":"Raymond James Financial Svc",
    "wof:placetype":"venue"
},
  "geometry": {"coordinates":[-74.25573199999999,39.983612],"type":"Point"}
}