{
  "type": "Feature",
  "properties": {
    "iso:country":"US",
    "sg:address":"358 Park Ave",
    "sg:city":"Scotch Plains",
    "sg:classifiers":[
        {
            "category":"Health Services",
            "subcategory":"Doctor",
            "type":"Services"
        }
    ],
    "sg:phone":"+1 908 322 9030",
    "sg:postcode":"07076",
    "sg:province":"NJ",
    "wof:name":"Bernard H Layton DDS",
    "wof:placetype":"venue"
},
  "geometry": {"coordinates":[-74.39870000000001,40.650993],"type":"Point"}
}