{
  "type": "Feature",
  "properties": {
    "addr:full":"88 Hillcrest Ave Hawthorne NJ 07506",
    "addr:housenumber":"88",
    "addr:postcode":"07506",
    "addr:street":"Hillcrest Ave",
    "iso:country":"US",
    "sg:address":"88 Hillcrest Ave",
    "sg:city":"Hawthorne",
    "sg:classifiers":[
        {
            "category":"Professional",
            "subcategory":"Business Services",
            "type":"Services"
        }
    ],
    "sg:phone":"+1   ",
    "sg:postcode":"07506",
    "sg:province":"NJ",
    "wof:name":"Dunn Sales & Marketing Lia",
    "wof:placetype":"venue"
},
  "geometry": {"coordinates":[-74.168217,40.972759],"type":"Point"}
}