{
  "type": "Feature",
  "properties": {
    "iso:country":"US",
    "sg:address":"700 S Black Horse Pike",
    "sg:city":"Blackwood",
    "sg:classifiers":[
        {
            "category":"Autos & Motor Vehicles",
            "subcategory":"Automobile Sales",
            "type":"Retail Goods"
        }
    ],
    "sg:phone":"+1   ",
    "sg:postcode":"08012",
    "sg:province":"NJ",
    "sg:tags":[
        "used"
    ],
    "wof:name":"Wholesale Outlet Inc",
    "wof:placetype":"venue"
},
  "geometry": {"coordinates":[-75.059124,39.790093],"type":"Point"}
}