{
  "type": "Feature",
  "properties": {
    "iso:country":"US",
    "sg:address":"4 Meeting House Ln",
    "sg:city":"Linwood",
    "sg:classifiers":[
        {
            "category":"Building & Trades",
            "subcategory":"Construction",
            "type":"Services"
        }
    ],
    "sg:phone":"+1 609 927 7208",
    "sg:postcode":"08221",
    "sg:province":"NJ",
    "sg:tags":[
        "general",
        "contractor"
    ],
    "wof:name":"Ferrin Builders",
    "wof:placetype":"venue"
},
  "geometry": {"coordinates":[-74.57436199999999,39.361726],"type":"Point"}
}