{
  "type": "Feature",
  "properties": {
    "iso:country":"US",
    "sg:address":"326 Wanaque Ave",
    "sg:city":"Pompton Lakes",
    "sg:classifiers":[
        {
            "category":"Shopping",
            "subcategory":"Gifts & Souvenirs",
            "type":"Retail Goods"
        }
    ],
    "sg:phone":"+1   ",
    "sg:postcode":"07442",
    "sg:province":"NJ",
    "wof:name":"A Pocket Full of Posies",
    "wof:placetype":"venue"
},
  "geometry": {"coordinates":[-74.290297,41.000926],"type":"Point"}
}