{
  "type": "Feature",
  "properties": {
    "addr:full":"95 Newfield Ave Edison NJ 08837",
    "addr:housenumber":"95",
    "addr:postcode":"08837",
    "addr:street":"Newfield Ave",
    "iso:country":"US",
    "sg:address":"95 Newfield Ave",
    "sg:city":"Edison",
    "sg:classifiers":[
        {
            "category":"Manufacturing",
            "subcategory":"Signs",
            "type":"Manufacturing & Wholesale Goods"
        }
    ],
    "sg:phone":"+1 732 512 9500",
    "sg:postcode":"08837",
    "sg:province":"NJ",
    "sg:tags":[
        "advertising",
        "specialty"
    ],
    "wof:name":"A2Z Signs LLC",
    "wof:placetype":"venue"
},
  "geometry": {"coordinates":[-74.346147,40.502599],"type":"Point"}
}