{
  "type": "Feature",
  "properties": {
    "addr:full":"480 Harding Rd Fair Haven NJ 07704",
    "addr:housenumber":"480",
    "addr:postcode":"07704",
    "addr:street":"Harding Rd",
    "iso:country":"US",
    "sg:address":"480 Harding Rd",
    "sg:city":"Fair Haven",
    "sg:classifiers":[
        {
            "category":"Professional",
            "subcategory":"Lawyer & Legal Services",
            "type":"Services"
        }
    ],
    "sg:phone":"+1 732 450 1770",
    "sg:postcode":"07704",
    "sg:province":"NJ",
    "sg:tags":[
        "attorney"
    ],
    "wof:name":"Patricia M Quigley",
    "wof:placetype":"venue"
},
  "geometry": {"coordinates":[-74.050817,40.348103],"type":"Point"}
}