{
  "type": "Feature",
  "properties": {
    "addr:full":"30 Berlin Rd Clementon NJ 08021",
    "addr:housenumber":"30",
    "addr:postcode":"08021",
    "addr:street":"Berlin Rd",
    "iso:country":"US",
    "sg:address":"30 Berlin Rd",
    "sg:city":"Clementon",
    "sg:classifiers":[
        {
            "category":"Building & Trades",
            "subcategory":"Equipment Rental",
            "type":"Services"
        }
    ],
    "sg:phone":"+1   ",
    "sg:postcode":"08021",
    "sg:province":"NJ",
    "wof:name":"Rent-A-Center",
    "wof:placetype":"venue"
},
  "geometry": {"coordinates":[-74.98983699999999,39.805497],"type":"Point"}
}