{
  "type": "Feature",
  "properties": {
    "addr:full":"1620 Beaver Dam Rd Point Pleasant Beach NJ 08742",
    "addr:housenumber":"1620",
    "addr:postcode":"08742",
    "addr:street":"Beaver Dam Rd",
    "iso:country":"US",
    "sg:address":"1620 Beaver Dam Rd",
    "sg:city":"Point Pleasant Beach",
    "sg:classifiers":[
        {
            "category":"Shopping",
            "subcategory":"Jewelry",
            "type":"Retail Goods"
        }
    ],
    "sg:phone":"+1   ",
    "sg:postcode":"08742",
    "sg:province":"NJ",
    "sg:tags":[
        "co"
    ],
    "wof:name":"Sunshine Daydream",
    "wof:placetype":"venue"
},
  "geometry": {"coordinates":[-74.072389,40.064237],"type":"Point"}
}