{
  "type": "Feature",
  "properties": {
    "iso:country":"US",
    "sg:address":"1475 Bergen Blvd",
    "sg:city":"Fort Lee",
    "sg:classifiers":[
        {
            "category":"Shopping",
            "subcategory":"Pharmacy",
            "type":"Retail Goods"
        }
    ],
    "sg:phone":"+1 201 947 4840",
    "sg:postcode":"07024",
    "sg:province":"NJ",
    "wof:name":"CVS Pharmacy",
    "wof:placetype":"venue"
},
  "geometry": {"coordinates":[-73.984865,40.85086],"type":"Point"}
}