{
  "type": "Feature",
  "properties": {
    "addr:full":"532 Glassboro Rd Woodbury Heights NJ 08097",
    "addr:housenumber":"532",
    "addr:postcode":"08097",
    "addr:street":"Glassboro Rd",
    "iso:country":"US",
    "sg:address":"532 Glassboro Rd",
    "sg:city":"Woodbury Heights",
    "sg:classifiers":[
        {
            "category":"Shopping",
            "subcategory":"Discount & Variety Stores",
            "type":"Retail Goods"
        }
    ],
    "sg:phone":"+1   ",
    "sg:postcode":"08097",
    "sg:province":"NJ",
    "wof:name":"Dollar Dream",
    "wof:placetype":"venue"
},
  "geometry": {"coordinates":[-75.15213300000001,39.827789],"type":"Point"}
}