{
  "type": "Feature",
  "properties": {
    "addr:full":"2670 US Hwy 206 Mt Holly NJ 08060",
    "addr:housenumber":"2670",
    "addr:postcode":"08060",
    "addr:street":"Us Hwy 206",
    "iso:country":"US",
    "sg:address":"2670 US Hwy 206",
    "sg:city":"Mt Holly",
    "sg:classifiers":[
        {
            "category":"Restaurant",
            "type":"Food & Drink"
        }
    ],
    "sg:phone":"+1 609 265 8801",
    "sg:postcode":"08060",
    "sg:province":"NJ",
    "wof:name":"Pizza Barn",
    "wof:placetype":"venue"
},
  "geometry": {"coordinates":[-74.80839400000001,39.988257],"type":"Point"}
}