{
  "type": "Feature",
  "properties": {
    "iso:country":"US",
    "sg:address":"427 Tiller Ave",
    "sg:city":"Beachwood",
    "sg:classifiers":[
        {
            "category":"Manufacturing",
            "subcategory":"Signs",
            "type":"Manufacturing & Wholesale Goods"
        }
    ],
    "sg:phone":"+1 732 240 4738",
    "sg:postcode":"08722",
    "sg:province":"NJ",
    "sg:tags":[
        "specialty",
        "mfg"
    ],
    "wof:name":"Plaza Graphics Signs",
    "wof:placetype":"venue"
},
  "geometry": {"coordinates":[-74.19643000000001,39.937466],"type":"Point"}
}