{
  "type": "Feature",
  "properties": {
    "iso:country":"US",
    "sg:address":"500 N Black Horse Pike",
    "sg:city":"Glendora",
    "sg:classifiers":[
        {
            "category":"Food & Beverages",
            "subcategory":"Bakery",
            "type":"Retail Goods"
        }
    ],
    "sg:phone":"+1 856 939 6030",
    "sg:postcode":"08029",
    "sg:province":"NJ",
    "sg:tags":[
        "baker"
    ],
    "wof:name":"Boaggio's Bakery",
    "wof:placetype":"venue"
},
  "geometry": {"coordinates":[-75.08833199999999,39.886694],"type":"Point"}
}