{
  "type": "Feature",
  "properties": {
    "addr:full":"350 Hawthorne Ave Newark NJ 07112",
    "addr:housenumber":"350",
    "addr:postcode":"07112",
    "addr:street":"Hawthorne Ave",
    "iso:country":"US",
    "sg:address":"350 Hawthorne Ave",
    "sg:city":"Newark",
    "sg:classifiers":[
        {
            "category":"Taxi",
            "type":"Transportation"
        }
    ],
    "sg:phone":"+1 973 371 1434",
    "sg:postcode":"07112",
    "sg:province":"NJ",
    "sg:tags":[
        "taxicab"
    ],
    "wof:name":"Mylea's Limo & Auto Cabs",
    "wof:placetype":"venue"
},
  "geometry": {"coordinates":[-74.207392,40.717487],"type":"Point"}
}