{
  "type": "Feature",
  "properties": {
    "iso:country":"US",
    "sg:address":"320 W Hanover St",
    "sg:city":"Trenton",
    "sg:classifiers":[
        {
            "category":"Food & Beverages",
            "subcategory":"Groceries & Convenience Stores",
            "type":"Retail Goods"
        }
    ],
    "sg:phone":"+1   ",
    "sg:postcode":"08618",
    "sg:province":"NJ",
    "wof:name":"Caribe Deli Market",
    "wof:placetype":"venue"
},
  "geometry": {"coordinates":[-74.773995,40.223385],"type":"Point"}
}