{
  "type": "Feature",
  "properties": {
    "iso:country":"US",
    "sg:address":"One Cedar Lane",
    "sg:city":"Englewood",
    "sg:classifiers":[
        {
            "category":"Professional",
            "subcategory":"Computer Services",
            "type":"Services"
        }
    ],
    "sg:phone":"+1 800 767 4444",
    "sg:postcode":"07631",
    "sg:province":"NJ",
    "sg:website":"http://www.daleandthomaspopcorn.com/",
    "wof:name":"Dale and Thomas Popcorn",
    "wof:placetype":"venue"
},
  "geometry": {"coordinates":[-73.987134,40.876354],"type":"Point"}
}