{
  "type": "Feature",
  "properties": {
    "addr:full":"8 Delavan Pl Belleville NJ 07109",
    "addr:housenumber":"8",
    "addr:postcode":"07109",
    "addr:street":"Delavan Pl",
    "iso:country":"US",
    "sg:address":"8 Delavan Pl",
    "sg:city":"Belleville",
    "sg:classifiers":[
        {
            "category":"Retail",
            "subcategory":"Auto Repair",
            "type":"Services"
        }
    ],
    "sg:phone":"+1 973 759 3796",
    "sg:postcode":"07109",
    "sg:province":"NJ",
    "sg:tags":[
        "body",
        "shop"
    ],
    "wof:name":"Delavan Auto Body Service",
    "wof:placetype":"venue"
},
  "geometry": {"coordinates":[-74.1819,40.779099],"type":"Point"}
}