{
  "type": "Feature",
  "properties": {
    "iso:country":"US",
    "sg:address":"888 Bay Way",
    "sg:city":"Lanoka Harbor",
    "sg:classifiers":[
        {
            "category":"Recreation",
            "subcategory":"Marina",
            "type":"Entertainment"
        }
    ],
    "sg:phone":"+1 609 693 2674",
    "sg:postcode":"08734",
    "sg:province":"NJ",
    "wof:name":"Lanoka Harbor Marina Inc",
    "wof:placetype":"venue"
},
  "geometry": {"coordinates":[-74.15464799999999,39.868576],"type":"Point"}
}