{
  "type": "Feature",
  "properties": {
    "iso:country":"US",
    "sg:address":"6956 Walnut Ave",
    "sg:city":"Pennsauken",
    "sg:classifiers":[
        {
            "category":"Wholesale",
            "subcategory":"Computers",
            "type":"Manufacturing & Wholesale Goods"
        }
    ],
    "sg:phone":"+1 856 662 3534",
    "sg:postcode":"08109",
    "sg:province":"NJ",
    "sg:tags":[
        "equipment"
    ],
    "wof:name":"Quotidian Computer Service",
    "wof:placetype":"venue"
},
  "geometry": {"coordinates":[-75.04186300000001,39.956857],"type":"Point"}
}