{
  "type": "Feature",
  "properties": {
    "iso:country":"US",
    "sg:address":"21 W Washington Ave",
    "sg:city":"Washington",
    "sg:classifiers":[
        {
            "category":"Bars & Pubs",
            "subcategory":"Nightclub",
            "type":"Food & Drink"
        }
    ],
    "sg:phone":"+1 908 835 1180",
    "sg:postcode":"07882",
    "sg:province":"NJ",
    "sg:tags":[
        "nightlife"
    ],
    "wof:name":"The Social Club",
    "wof:placetype":"venue"
},
  "geometry": {"coordinates":[-74.982399,40.757702],"type":"Point"}
}