{
  "type": "Feature",
  "properties": {
    "iso:country":"US",
    "sg:address":"44 Elmwood Ave",
    "sg:city":"Carteret",
    "sg:classifiers":[
        {
            "category":"Wholesale",
            "subcategory":"Apparel",
            "type":"Manufacturing & Wholesale Goods"
        }
    ],
    "sg:phone":"+1 732 969 3888",
    "sg:postcode":"07008",
    "sg:province":"NJ",
    "sg:tags":[
        "clothing"
    ],
    "wof:name":"Savanna Impex",
    "wof:placetype":"venue"
},
  "geometry": {"coordinates":[-74.230757,40.581793],"type":"Point"}
}