{
  "type": "Feature",
  "properties": {
    "addr:full":"330 Fairfield Rd Fairfield NJ 07004",
    "addr:housenumber":"330",
    "addr:postcode":"07004",
    "addr:street":"Fairfield Rd",
    "iso:country":"US",
    "sg:address":"330 Fairfield Rd",
    "sg:city":"Fairfield",
    "sg:classifiers":[
        {
            "category":"Food & Beverages",
            "subcategory":"Cheese",
            "type":"Retail Goods"
        }
    ],
    "sg:phone":"+1 973 227 0002",
    "sg:postcode":"07004",
    "sg:province":"NJ",
    "sg:tags":[
        "shop"
    ],
    "wof:name":"Empire Specialty Cheese Company",
    "wof:placetype":"venue"
},
  "geometry": {"coordinates":[-74.28442099999999,40.883167],"type":"Point"}
}