{
  "type": "Feature",
  "properties": {
    "addr:full":"41 Walton Ave Oakland NJ 07436",
    "addr:housenumber":"41",
    "addr:postcode":"07436",
    "addr:street":"Walton Ave",
    "iso:country":"US",
    "sg:address":"41 Walton Ave",
    "sg:city":"Oakland",
    "sg:classifiers":[
        {
            "category":"Professional",
            "type":"Services"
        }
    ],
    "sg:phone":"+1 212 544 7402",
    "sg:postcode":"07436",
    "sg:province":"NJ",
    "sg:tags":[
        "establishment"
    ],
    "wof:name":"CBT Systems USA LTD",
    "wof:placetype":"venue"
},
  "geometry": {"coordinates":[-74.241675,41.018522],"type":"Point"}
}