{
  "type": "Feature",
  "properties": {
    "iso:country":"US",
    "sg:address":"21 Louise Dr",
    "sg:city":"Milltown",
    "sg:classifiers":[
        {
            "category":"Wholesale",
            "subcategory":"Electrical",
            "type":"Manufacturing & Wholesale Goods"
        }
    ],
    "sg:phone":"+1 732 422 7056",
    "sg:postcode":"08850",
    "sg:province":"NJ",
    "sg:tags":[
        "sound",
        "equipment",
        "system"
    ],
    "sg:website":"www.dimensionssoundandlighting.com",
    "wof:name":"Dimensions Sound & Lighting",
    "wof:placetype":"venue"
},
  "geometry": {"coordinates":[-74.45598200000001,40.438463],"type":"Point"}
}