{
  "type": "Feature",
  "properties": {
    "iso:country":"US",
    "sg:address":"18 Heather Ln",
    "sg:city":"Warren",
    "sg:classifiers":[
        {
            "category":"Professional",
            "subcategory":"Business Services",
            "type":"Services"
        }
    ],
    "sg:phone":"+1   ",
    "sg:postcode":"07059",
    "sg:province":"NJ",
    "wof:name":"Seewave Technologies LLC",
    "wof:placetype":"venue"
},
  "geometry": {"coordinates":[-74.48823299999999,40.651069],"type":"Point"}
}