{
  "type": "Feature",
  "properties": {
    "addr:full":"412 Sicklerville Rd Williamstown NJ 08094",
    "addr:housenumber":"412",
    "addr:postcode":"08094",
    "addr:street":"Sicklerville Rd",
    "iso:country":"US",
    "sg:address":"412 Sicklerville Rd",
    "sg:city":"Williamstown",
    "sg:classifiers":[
        {
            "category":"Personal",
            "type":"Services"
        }
    ],
    "sg:phone":"+1 856 875 6669",
    "sg:postcode":"08094",
    "sg:province":"NJ",
    "sg:tags":[
        "program",
        "physical",
        "exercise",
        "fitness"
    ],
    "wof:name":"Curves For Women",
    "wof:placetype":"venue"
},
  "geometry": {"coordinates":[-74.990296,39.692738],"type":"Point"}
}