{
  "type": "Feature",
  "properties": {
    "addr:full":"594 Valley Rd Gillette NJ 07933",
    "addr:housenumber":"594",
    "addr:postcode":"07933",
    "addr:street":"Valley Rd",
    "iso:country":"US",
    "sg:address":"594 Valley Rd",
    "sg:city":"Gillette",
    "sg:classifiers":[
        {
            "category":"Government",
            "subcategory":"Post Office",
            "type":"Public Place"
        }
    ],
    "sg:phone":"+1 908 647 3135",
    "sg:postcode":"07933",
    "sg:province":"NJ",
    "sg:tags":[
        "postal",
        "us"
    ],
    "wof:name":"US Post Office",
    "wof:placetype":"venue"
},
  "geometry": {"coordinates":[-74.458624,40.677145],"type":"Point"}
}