{
  "type": "Feature",
  "properties": {
    "iso:country":"US",
    "sg:address":"24 Hydrangea St",
    "sg:city":"Browns Mills",
    "sg:classifiers":[
        {
            "category":"Building & Trades",
            "subcategory":"Construction",
            "type":"Services"
        }
    ],
    "sg:phone":"+1 609 893 7347",
    "sg:postcode":"08015",
    "sg:province":"NJ",
    "sg:tags":[
        "contractor"
    ],
    "wof:name":"Lucas Drywall",
    "wof:placetype":"venue"
},
  "geometry": {"coordinates":[-74.55835999999999,39.977439],"type":"Point"}
}