{
  "type": "Feature",
  "properties": {
    "addr:full":"203 Glen Crest Dr Branchburg NJ 08853",
    "addr:housenumber":"203",
    "addr:postcode":"08853",
    "addr:street":"Glen Crest Dr",
    "iso:country":"US",
    "sg:address":"203 Glen Crest Dr",
    "sg:city":"Branchburg",
    "sg:classifiers":[
        {
            "category":"Personal",
            "subcategory":"Beauty Salon",
            "type":"Services"
        },
        {
            "category":"Building & Trades",
            "subcategory":"Landscaping Services",
            "type":"Services"
        }
    ],
    "sg:phone":"+1 908 369 0037",
    "sg:postcode":"08853",
    "sg:province":"NJ",
    "sg:tags":[
        "shop",
        "landscape",
        "contractor"
    ],
    "wof:name":"Prime Design Landscapes L",
    "wof:placetype":"venue"
},
  "geometry": {"coordinates":[-74.73747299999999,40.552032],"type":"Point"}
}