{
  "type": "Feature",
  "properties": {
    "addr:full":"28 Prestwick Way Edison NJ 08820",
    "addr:housenumber":"28",
    "addr:postcode":"08820",
    "addr:street":"Prestwick Way",
    "iso:country":"US",
    "sg:address":"28 Prestwick Way",
    "sg:city":"Edison",
    "sg:classifiers":[
        {
            "category":"Personal",
            "subcategory":"Beauty Salon",
            "type":"Services"
        }
    ],
    "sg:phone":"+1 732 549 9831",
    "sg:postcode":"08820",
    "sg:province":"NJ",
    "sg:tags":[
        "shop"
    ],
    "wof:name":"Opi Nails Salon Inc",
    "wof:placetype":"venue"
},
  "geometry": {"coordinates":[-74.398122,40.554728],"type":"Point"}
}