{
  "type": "Feature",
  "properties": {
    "addr:full":"1019 E Landis Ave Vineland NJ 08360",
    "addr:housenumber":"1019",
    "addr:postcode":"08360",
    "addr:street":"E Landis Ave",
    "iso:country":"US",
    "sg:address":"1019 E Landis Ave",
    "sg:city":"Vineland",
    "sg:classifiers":[
        {
            "category":"Retail",
            "subcategory":"Funeral Services",
            "type":"Services"
        }
    ],
    "sg:phone":"+1 856 691 0929",
    "sg:postcode":"08360",
    "sg:province":"NJ",
    "sg:tags":[
        "home"
    ],
    "wof:name":"De Marco Luisi",
    "wof:placetype":"venue"
},
  "geometry": {"coordinates":[-75.014561,39.485584],"type":"Point"}
}