{
  "type": "Feature",
  "properties": {
    "addr:full":"117 Hedden Ter North Arlington NJ 07031",
    "addr:housenumber":"117",
    "addr:postcode":"07031",
    "addr:street":"Hedden Ter North",
    "iso:country":"US",
    "sg:address":"117 Hedden Ter",
    "sg:city":"North Arlington",
    "sg:classifiers":[
        {
            "category":"Insurance",
            "subcategory":"Life Insurance",
            "type":"Services"
        }
    ],
    "sg:phone":"+1   ",
    "sg:postcode":"07031",
    "sg:province":"NJ",
    "sg:tags":[
        "carrier"
    ],
    "wof:name":"Queen Elizabeth Society",
    "wof:placetype":"venue"
},
  "geometry": {"coordinates":[-74.14250699999999,40.788092],"type":"Point"}
}