{
  "type": "Feature",
  "properties": {
    "addr:full":"150 Edison Rd Lake Hopatcong NJ 07849",
    "addr:housenumber":"150",
    "addr:postcode":"07849",
    "addr:street":"Edison Rd",
    "iso:country":"US",
    "sg:address":"150 Edison Rd",
    "sg:city":"Lake Hopatcong",
    "sg:classifiers":[
        {
            "category":"Building & Trades",
            "subcategory":"Construction",
            "type":"Services"
        }
    ],
    "sg:phone":"+1 973 663 5800",
    "sg:postcode":"07849",
    "sg:province":"NJ",
    "sg:tags":[
        "roofing",
        "contractor"
    ],
    "sg:website":"www.nutekroofing.com",
    "wof:name":"Nu-Tek Roof Systems Inc",
    "wof:placetype":"venue"
},
  "geometry": {"coordinates":[-74.599002,40.958394],"type":"Point"}
}