{
  "type": "Feature",
  "properties": {
    "iso:country":"US",
    "sg:address":"60 Canfield Ave",
    "sg:city":"Randolph",
    "sg:classifiers":[
        {
            "category":"Wholesale",
            "subcategory":"Sporting Goods",
            "type":"Manufacturing & Wholesale Goods"
        }
    ],
    "sg:phone":"+1 973 584 9356",
    "sg:postcode":"07869",
    "sg:province":"NJ",
    "wof:name":"J & A Reloaders Inc",
    "wof:placetype":"venue"
},
  "geometry": {"coordinates":[-74.611801,40.853539],"type":"Point"}
}