{
  "type": "Feature",
  "properties": {
    "addr:full":"293 US Hwy 206 Flanders NJ 07836",
    "addr:housenumber":"293",
    "addr:postcode":"07836",
    "addr:street":"Us Hwy 206",
    "iso:country":"US",
    "sg:address":"293 US Hwy 206",
    "sg:city":"Flanders",
    "sg:classifiers":[
        {
            "category":"Food & Beverages",
            "subcategory":"Liquor & Beverages",
            "type":"Retail Goods"
        }
    ],
    "sg:phone":"+1 973 584 0333",
    "sg:postcode":"07836",
    "sg:province":"NJ",
    "wof:name":"Wine Rack",
    "wof:placetype":"venue"
},
  "geometry": {"coordinates":[-74.708293,40.825996],"type":"Point"}
}