{
  "type": "Feature",
  "properties": {
    "addr:full":"797 Broad St Newark NJ 07102",
    "addr:housenumber":"797",
    "addr:postcode":"07102",
    "addr:street":"Broad St",
    "iso:country":"US",
    "sg:address":"797 Broad St",
    "sg:city":"Newark",
    "sg:classifiers":[
        {
            "category":"Shopping",
            "type":"Retail Goods"
        }
    ],
    "sg:phone":"+1   ",
    "sg:postcode":"07102",
    "sg:province":"NJ",
    "sg:tags":[
        "parts",
        "electronic"
    ],
    "wof:name":"Zacks Music Center Inc",
    "wof:placetype":"venue"
},
  "geometry": {"coordinates":[-74.172526,40.735155],"type":"Point"}
}