{
  "type": "Feature",
  "properties": {
    "iso:country":"US",
    "sg:address":"385 Prospect Ave",
    "sg:city":"Hackensack",
    "sg:classifiers":[
        {
            "category":"Banks & Credit Unions",
            "subcategory":"Investment Brokerage",
            "type":"Services"
        }
    ],
    "sg:phone":"+1   ",
    "sg:postcode":"07601",
    "sg:province":"NJ",
    "sg:tags":[
        "mutual",
        "selling",
        "funds",
        "stocks",
        "insurance",
        "bond"
    ],
    "wof:name":"Cadaret Grant & Co",
    "wof:placetype":"venue"
},
  "geometry": {"coordinates":[-74.051824,40.896106],"type":"Point"}
}