{
  "type": "Feature",
  "properties": {
    "iso:country":"US",
    "sg:address":"401 Blossom Cir",
    "sg:city":"Dayton",
    "sg:classifiers":[
        {
            "category":"Professional",
            "type":"Services"
        }
    ],
    "sg:phone":"+1 732 329 0238",
    "sg:postcode":"08810",
    "sg:province":"NJ",
    "sg:tags":[
        "establishment"
    ],
    "wof:name":"Village At Summerfield",
    "wof:placetype":"venue"
},
  "geometry": {"coordinates":[-74.50682500000001,40.379646],"type":"Point"}
}