{
  "type": "Feature",
  "properties": {
    "addr:full":"216 Broad Ave Palisades Park NJ 07650",
    "addr:housenumber":"216",
    "addr:postcode":"07650",
    "addr:street":"Broad Ave",
    "iso:country":"US",
    "sg:address":"216 Broad Ave",
    "sg:city":"Palisades Park",
    "sg:classifiers":[
        {
            "category":"Food & Beverages",
            "subcategory":"Meat & Fish",
            "type":"Retail Goods"
        }
    ],
    "sg:phone":"+1 201 461 4642",
    "sg:postcode":"07650",
    "sg:province":"NJ",
    "sg:tags":[
        "shop"
    ],
    "wof:name":"Yun Ok Meats Ins",
    "wof:placetype":"venue"
},
  "geometry": {"coordinates":[-73.9991,40.8461],"type":"Point"}
}