{
  "type": "Feature",
  "properties": {
    "addr:full":"1420 Admiral Wilson Blvd Pennsauken NJ 08109",
    "addr:housenumber":"1420",
    "addr:postcode":"08109",
    "addr:street":"Admiral Wilson Blvd",
    "iso:country":"US",
    "sg:address":"1420 Admiral Wilson Blvd",
    "sg:city":"Pennsauken",
    "sg:classifiers":[
        {
            "category":"Building & Trades",
            "subcategory":"Locksmith",
            "type":"Services"
        }
    ],
    "sg:phone":"+1 856 532 0377",
    "sg:postcode":"08109",
    "sg:province":"NJ",
    "sg:tags":[
        "key"
    ],
    "wof:name":"1 Locksmith 24 Hr 7 Day",
    "wof:placetype":"venue"
},
  "geometry": {"coordinates":[-75.10318100000001,39.940843],"type":"Point"}
}