{
  "type": "Feature",
  "properties": {
    "addr:full":"1 Industrial Way W Eatontown NJ 07724",
    "addr:housenumber":"1",
    "addr:postcode":"07724",
    "addr:street":"Industrial Way W",
    "iso:country":"US",
    "sg:address":"1 Industrial Way W",
    "sg:city":"Eatontown",
    "sg:classifiers":[
        {
            "category":"Professional",
            "subcategory":"Accounting & Tax Preparation",
            "type":"Services"
        }
    ],
    "sg:phone":"+1 732 935 9808",
    "sg:postcode":"07724",
    "sg:province":"NJ",
    "wof:name":"Maggio Sharyn Inc",
    "wof:placetype":"venue"
},
  "geometry": {"coordinates":[-74.04516599999999,40.276551],"type":"Point"}
}