{
  "type": "Feature",
  "properties": {
    "addr:full":"111 Maple Stream Rd Hightstown NJ 08520",
    "addr:housenumber":"111",
    "addr:postcode":"08520",
    "addr:street":"Maple Stream Rd",
    "iso:country":"US",
    "sg:address":"111 Maple Stream Rd",
    "sg:city":"Hightstown",
    "sg:classifiers":[
        {
            "category":"Restaurant",
            "type":"Food & Drink"
        }
    ],
    "sg:phone":"+1   ",
    "sg:postcode":"08520",
    "sg:province":"NJ",
    "sg:tags":[
        "eating"
    ],
    "wof:name":"Chicken Holiday",
    "wof:placetype":"venue"
},
  "geometry": {"coordinates":[-74.546757,40.264893],"type":"Point"}
}