{
  "type": "Feature",
  "properties": {
    "addr:full":"48 Terrace Ave Jersey City NJ 07307",
    "addr:housenumber":"48",
    "addr:postcode":"07307",
    "addr:street":"Terrace Ave",
    "iso:country":"US",
    "sg:address":"48 Terrace Ave",
    "sg:city":"Jersey City",
    "sg:classifiers":[
        {
            "category":"Professional",
            "subcategory":"Business Services",
            "type":"Services"
        }
    ],
    "sg:phone":"+1   ",
    "sg:postcode":"07307",
    "sg:province":"NJ",
    "wof:name":"Express Personnel Services",
    "wof:placetype":"venue"
},
  "geometry": {"coordinates":[-74.059101,40.748098],"type":"Point"}
}