{
  "type": "Feature",
  "properties": {
    "iso:country":"US",
    "sg:address":"115 Franklin Tpke",
    "sg:city":"Mahwah",
    "sg:classifiers":[
        {
            "category":"Professional",
            "subcategory":"Engineering",
            "type":"Services"
        },
        {
            "category":"Shopping",
            "subcategory":"Computers & Home Electronics",
            "type":"Retail Goods"
        },
        {
            "category":"Professional",
            "subcategory":"Computer Services",
            "type":"Services"
        }
    ],
    "sg:phone":"+1 201 825 0609",
    "sg:postcode":"07430",
    "sg:province":"NJ",
    "sg:tags":[
        "repair",
        "sales"
    ],
    "wof:name":"Computer Junction USA",
    "wof:placetype":"venue"
},
  "geometry": {"coordinates":[-74.146354,41.097737],"type":"Point"}
}