{
  "type": "Feature",
  "properties": {
    "iso:country":"US",
    "sg:address":"4 Ramapo Valley Rd",
    "sg:city":"Oakland",
    "sg:classifiers":[
        {
            "category":"Professional",
            "subcategory":"Lawyer & Legal Services",
            "type":"Services"
        }
    ],
    "sg:phone":"+1 201 337 4104",
    "sg:postcode":"07436",
    "sg:province":"NJ",
    "wof:name":"Tiernan William J Attorney",
    "wof:placetype":"venue"
},
  "geometry": {"coordinates":[-74.26419799999999,41.012299],"type":"Point"}
}