{
  "type": "Feature",
  "properties": {
    "iso:country":"US",
    "sg:address":"2388 N East Ave",
    "sg:city":"Vineland",
    "sg:classifiers":[
        {
            "category":"Education",
            "subcategory":"Dance Studio",
            "type":"Public Place"
        }
    ],
    "sg:phone":"+1   ",
    "sg:postcode":"08360",
    "sg:province":"NJ",
    "wof:name":"Chapman Maxine Studio of Dance",
    "wof:placetype":"venue"
},
  "geometry": {"coordinates":[-75.013398,39.52697],"type":"Point"}
}