{
  "type": "Feature",
  "properties": {
    "addr:full":"175 Fay St Edison NJ 08837",
    "addr:housenumber":"175",
    "addr:postcode":"08837",
    "addr:street":"Fay St",
    "iso:country":"US",
    "sg:address":"175 Fay St",
    "sg:city":"Edison",
    "sg:classifiers":[
        {
            "category":"Freight",
            "type":"Transportation"
        }
    ],
    "sg:phone":"+1 732 661 0158",
    "sg:postcode":"08837",
    "sg:province":"NJ",
    "sg:tags":[
        "operator",
        "local",
        "trucking"
    ],
    "wof:name":"James Stio",
    "wof:placetype":"venue"
},
  "geometry": {"coordinates":[-74.320869,40.532205],"type":"Point"}
}