{
  "type": "Feature",
  "properties": {
    "iso:country":"US",
    "sg:address":"144 S Maple Ave",
    "sg:city":"Ridgewood",
    "sg:classifiers":[
        {
            "category":"Professional",
            "subcategory":"Management & Consulting",
            "type":"Services"
        }
    ],
    "sg:phone":"+1 201 612 1080",
    "sg:postcode":"07450",
    "sg:province":"NJ",
    "sg:tags":[
        "consultant",
        "business"
    ],
    "wof:name":"Corporate Growth Concepts Inc",
    "wof:placetype":"venue"
},
  "geometry": {"coordinates":[-74.11504600000001,40.976012],"type":"Point"}
}