{
  "type": "Feature",
  "properties": {
    "addr:full":"303 Mount Hope Ave Rockaway NJ 07866",
    "addr:housenumber":"303",
    "addr:postcode":"07866",
    "addr:street":"Mount Hope Ave",
    "iso:country":"US",
    "sg:address":"303 Mount Hope Ave",
    "sg:city":"Rockaway",
    "sg:classifiers":[
        {
            "category":"Shopping",
            "subcategory":"Department Store",
            "type":"Retail Goods"
        }
    ],
    "sg:phone":"+1 973 328 1234",
    "sg:postcode":"07866",
    "sg:province":"NJ",
    "wof:name":"Macy's",
    "wof:placetype":"venue"
},
  "geometry": {"coordinates":[-74.533674,40.916705],"type":"Point"}
}