{
  "type": "Feature",
  "properties": {
    "addr:full":"296 Pershing Ave Carteret NJ 07008",
    "addr:housenumber":"296",
    "addr:postcode":"07008",
    "addr:street":"Pershing Ave",
    "iso:country":"US",
    "sg:address":"296 Pershing Ave",
    "sg:city":"Carteret",
    "sg:classifiers":[
        {
            "category":"Wholesale",
            "subcategory":"Non-durable Goods",
            "type":"Manufacturing & Wholesale Goods"
        }
    ],
    "sg:phone":"+1 732 541 2807",
    "sg:postcode":"07008",
    "sg:province":"NJ",
    "sg:tags":[
        "pet",
        "store",
        "supply"
    ],
    "wof:name":"Mid Jersey Pet Supply - PRO Salt",
    "wof:placetype":"venue"
},
  "geometry": {"coordinates":[-74.21850999999999,40.581625],"type":"Point"}
}