{
  "type": "Feature",
  "properties": {
    "addr:full":"61 Hudson St Hackensack NJ 07601",
    "addr:housenumber":"61",
    "addr:postcode":"07601",
    "addr:street":"Hudson St",
    "iso:country":"US",
    "sg:address":"61 Hudson St",
    "sg:city":"Hackensack",
    "sg:classifiers":[
        {
            "category":"Professional",
            "subcategory":"Lawyer & Legal Services",
            "type":"Services"
        }
    ],
    "sg:phone":"+1 201 457 9098",
    "sg:postcode":"07601",
    "sg:province":"NJ",
    "wof:name":"Merijanian Seda Lawyer",
    "wof:placetype":"venue"
},
  "geometry": {"coordinates":[-74.047997,40.888802],"type":"Point"}
}