{
  "type": "Feature",
  "properties": {
    "addr:full":"1324 Lakeshore Dr Camden NJ 08104",
    "addr:housenumber":"1324",
    "addr:postcode":"08104",
    "addr:street":"Lakeshore Dr",
    "iso:country":"US",
    "sg:address":"1324 Lakeshore Dr",
    "sg:city":"Camden",
    "sg:classifiers":[
        {
            "category":"Professional",
            "type":"Services"
        }
    ],
    "sg:phone":"+1   ",
    "sg:postcode":"08104",
    "sg:province":"NJ",
    "wof:name":"Darnell Shambrie",
    "wof:placetype":"venue"
},
  "geometry": {"coordinates":[-75.101225,39.913468],"type":"Point"}
}