{
  "type": "Feature",
  "properties": {
    "iso:country":"US",
    "sg:address":"244 Broad Ave",
    "sg:city":"Palisades Park",
    "sg:classifiers":[
        {
            "category":"Personal",
            "subcategory":"Beauty Salon",
            "type":"Services"
        }
    ],
    "sg:phone":"+1 201 592 0021",
    "sg:postcode":"07650",
    "sg:province":"NJ",
    "wof:name":"Hair Bank",
    "wof:placetype":"venue"
},
  "geometry": {"coordinates":[-73.99809999999999,40.847601],"type":"Point"}
}