{
  "type": "Feature",
  "properties": {
    "iso:country":"US",
    "sg:address":"534 Openaki Rd",
    "sg:city":"Denville",
    "sg:classifiers":[
        {
            "category":"Professional",
            "subcategory":"Accounting & Tax Preparation",
            "type":"Services"
        }
    ],
    "sg:phone":"+1 973 989 7735",
    "sg:postcode":"07834",
    "sg:province":"NJ",
    "sg:tags":[
        "bookkeeping",
        "general"
    ],
    "wof:name":"K Clark Accounting & Bkpng",
    "wof:placetype":"venue"
},
  "geometry": {"coordinates":[-74.52643399999999,40.864267],"type":"Point"}
}