{
  "type": "Feature",
  "properties": {
    "addr:full":"124 Topaz Dr Franklin Park NJ 08823",
    "addr:housenumber":"124",
    "addr:postcode":"08823",
    "addr:street":"Topaz Dr",
    "iso:country":"US",
    "sg:address":"124 Topaz Dr",
    "sg:city":"Franklin Park",
    "sg:classifiers":[
        {
            "category":"Professional",
            "subcategory":"Advertising",
            "type":"Services"
        }
    ],
    "sg:phone":"+1   ",
    "sg:postcode":"08823",
    "sg:province":"NJ",
    "sg:tags":[
        "communications"
    ],
    "wof:name":"York Communications",
    "wof:placetype":"venue"
},
  "geometry": {"coordinates":[-74.55479,40.435763],"type":"Point"}
}