{
  "type": "Feature",
  "properties": {
    "iso:country":"US",
    "sg:address":"354 Plaza Rd N",
    "sg:city":"Fair Lawn",
    "sg:classifiers":[
        {
            "category":"Government",
            "subcategory":"Office",
            "type":"Public Place"
        }
    ],
    "sg:phone":"+1 201 398 9800",
    "sg:postcode":"07410",
    "sg:province":"NJ",
    "sg:tags":[
        "planning",
        "disaster",
        "emergency"
    ],
    "sg:website":"www.emergencyadvisors.com",
    "wof:name":"Emergency Management Advisors",
    "wof:placetype":"venue"
},
  "geometry": {"coordinates":[-74.12280199999999,40.945548],"type":"Point"}
}