{
  "type": "Feature",
  "properties": {
    "addr:full":"1750 US Hwy 46 Little Falls NJ 07424",
    "addr:housenumber":"1750",
    "addr:postcode":"07424",
    "addr:street":"Us Hwy 46",
    "iso:country":"US",
    "sg:address":"1750 US Hwy 46",
    "sg:city":"Little Falls",
    "sg:classifiers":[
        {
            "category":"Shopping",
            "type":"Retail Goods"
        }
    ],
    "sg:phone":"+1   ",
    "sg:postcode":"07424",
    "sg:province":"NJ",
    "sg:tags":[
        "product",
        "related",
        "dec",
        "christmas",
        "pool",
        "swimming"
    ],
    "wof:name":"Harrow Stores Inc",
    "wof:placetype":"venue"
},
  "geometry": {"coordinates":[-74.217305,40.887665],"type":"Point"}
}