{
  "type": "Feature",
  "properties": {
    "iso:country":"US",
    "sg:address":"700 Haddonfield Berlin Rd",
    "sg:city":"Voorhees",
    "sg:classifiers":[
        {
            "category":"Banks & Credit Unions",
            "subcategory":"Bank",
            "type":"Services"
        }
    ],
    "sg:phone":"+1 856 782 2699",
    "sg:postcode":"08043",
    "sg:province":"NJ",
    "wof:name":"Citizens Bank",
    "wof:placetype":"venue"
},
  "geometry": {"coordinates":[-74.98238000000001,39.853669],"type":"Point"}
}