{
  "type": "Feature",
  "properties": {
    "iso:country":"US",
    "sg:address":"398 Carhart Ct",
    "sg:city":"East Brunswick",
    "sg:classifiers":[
        {
            "category":"Professional",
            "subcategory":"Management & Consulting",
            "type":"Services"
        }
    ],
    "sg:phone":"+1   ",
    "sg:postcode":"08816",
    "sg:province":"NJ",
    "wof:name":"Constance Mehesy",
    "wof:placetype":"venue"
},
  "geometry": {"coordinates":[-74.402579,40.457133],"type":"Point"}
}