{
  "type": "Feature",
  "properties": {
    "addr:full":"24 October Hill Rd Oak Ridge NJ 07438",
    "addr:housenumber":"24",
    "addr:postcode":"07438",
    "addr:street":"October Hill Rd",
    "iso:country":"US",
    "sg:address":"24 October Hill Rd",
    "sg:city":"Oak Ridge",
    "sg:classifiers":[
        {
            "category":"Professional",
            "type":"Services"
        }
    ],
    "sg:phone":"+1   ",
    "sg:postcode":"07438",
    "sg:province":"NJ",
    "wof:name":"Red Top Services",
    "wof:placetype":"venue"
},
  "geometry": {"coordinates":[-74.465406,41.032734],"type":"Point"}
}