{
  "type": "Feature",
  "properties": {
    "addr:full":"690 Prospect St Maplewood NJ 07040",
    "addr:housenumber":"690",
    "addr:postcode":"07040",
    "addr:street":"Prospect St",
    "iso:country":"US",
    "sg:address":"690 Prospect St",
    "sg:city":"Maplewood",
    "sg:classifiers":[
        {
            "category":"Health Services",
            "subcategory":"Doctor",
            "type":"Services"
        }
    ],
    "sg:phone":"+1   ",
    "sg:postcode":"07040",
    "sg:province":"NJ",
    "sg:tags":[
        "surgeon",
        "oral",
        "facial"
    ],
    "wof:name":"Najjar DMD Mds PHD Galib",
    "wof:placetype":"venue"
},
  "geometry": {"coordinates":[-74.271614,40.72288],"type":"Point"}
}