{
  "type": "Feature",
  "properties": {
    "iso:country":"US",
    "sg:address":"45 Burkhardt Ln",
    "sg:city":"Harrington Park",
    "sg:classifiers":[
        {
            "category":"Professional",
            "subcategory":"Business Services",
            "type":"Services"
        }
    ],
    "sg:phone":"+1 201 768 1707",
    "sg:postcode":"07640",
    "sg:province":"NJ",
    "sg:tags":[
        "interior",
        "designer"
    ],
    "wof:name":"Carlo & Company Inc",
    "wof:placetype":"venue"
},
  "geometry": {"coordinates":[-73.98042,41.004147],"type":"Point"}
}