{
  "type": "Feature",
  "properties": {
    "addr:full":"505 Marlboro Rd Wood-Ridge NJ 07075",
    "addr:housenumber":"505",
    "addr:postcode":"07075",
    "addr:street":"Marlboro Rd",
    "iso:country":"US",
    "sg:address":"505 Marlboro Rd",
    "sg:city":"Wood-Ridge",
    "sg:classifiers":[
        {
            "category":"Building & Trades",
            "subcategory":"Cleaning & Sanitation",
            "type":"Services"
        }
    ],
    "sg:phone":"+1   ",
    "sg:postcode":"07075",
    "sg:province":"NJ",
    "sg:tags":[
        "maintenance"
    ],
    "wof:name":"Fish Window Cleaning",
    "wof:placetype":"venue"
},
  "geometry": {"coordinates":[-74.08241099999999,40.849476],"type":"Point"}
}