{
  "type": "Feature",
  "properties": {
    "iso:country":"US",
    "sg:address":"8 Airmont Ave",
    "sg:city":"Mahwah",
    "sg:classifiers":[
        {
            "category":"Manufacturing",
            "subcategory":"Metals",
            "type":"Manufacturing & Wholesale Goods"
        }
    ],
    "sg:phone":"+1 201 512 9475",
    "sg:postcode":"07430",
    "sg:province":"NJ",
    "sg:tags":[
        "tool",
        "mfg",
        "hand"
    ],
    "wof:name":"Rlf Mfg Inc",
    "wof:placetype":"venue"
},
  "geometry": {"coordinates":[-74.12102899999999,41.094218],"type":"Point"}
}