{
  "type": "Feature",
  "properties": {
    "iso:country":"US",
    "sg:address":"327 Main St",
    "sg:city":"Orange",
    "sg:classifiers":[
        {
            "category":"Real Estate",
            "subcategory":"Real Estate Operator",
            "type":"Services"
        }
    ],
    "sg:phone":"+1   ",
    "sg:postcode":"07050",
    "sg:province":"NJ",
    "sg:tags":[
        "building",
        "nonresidential"
    ],
    "wof:name":"Lee Hyanz Enterprise Inc",
    "wof:placetype":"venue"
},
  "geometry": {"coordinates":[-74.229862,40.772352],"type":"Point"}
}