{
  "type": "Feature",
  "properties": {
    "iso:country":"US",
    "sg:address":"5 Mount Dr",
    "sg:city":"Holmdel",
    "sg:classifiers":[
        {
            "category":"Professional",
            "subcategory":"Business Services",
            "type":"Services"
        }
    ],
    "sg:phone":"+1 732 335 9306",
    "sg:postcode":"07733",
    "sg:province":"NJ",
    "sg:tags":[
        "consulting",
        "software"
    ],
    "wof:name":"Db Solutions",
    "wof:placetype":"venue"
},
  "geometry": {"coordinates":[-74.16845499999999,40.396678],"type":"Point"}
}