{
  "type": "Feature",
  "properties": {
    "iso:country":"US",
    "sg:address":"16 Falls Rd",
    "sg:city":"Medford",
    "sg:classifiers":[
        {
            "category":"Sports & Exercise",
            "subcategory":"Sports Center",
            "type":"Entertainment"
        }
    ],
    "sg:phone":"+1 856 983 5715",
    "sg:postcode":"08055",
    "sg:province":"NJ",
    "sg:tags":[
        "athletic"
    ],
    "wof:name":"South Jersey Boys Lacrosse Inc",
    "wof:placetype":"venue"
},
  "geometry": {"coordinates":[-74.846474,39.865292],"type":"Point"}
}