{
  "type": "Feature",
  "properties": {
    "iso:country":"US",
    "sg:address":"36 Wantage Ave",
    "sg:city":"Branchville",
    "sg:classifiers":[
        {
            "category":"Freight",
            "type":"Transportation"
        }
    ],
    "sg:phone":"+1 973 948 7070",
    "sg:postcode":"07826",
    "sg:province":"NJ",
    "sg:tags":[
        "cartage",
        "trucking"
    ],
    "wof:name":"Dry Brook Transportation Inc",
    "wof:placetype":"venue"
},
  "geometry": {"coordinates":[-74.74705299999999,41.150988],"type":"Point"}
}