{
  "type": "Feature",
  "properties": {
    "addr:full":"360 Scotch Rd Trenton NJ 08628",
    "addr:housenumber":"360",
    "addr:postcode":"08628",
    "addr:street":"Scotch Rd",
    "iso:country":"US",
    "sg:address":"360 Scotch Rd",
    "sg:city":"Trenton",
    "sg:classifiers":[
        {
            "category":"Travel",
            "subcategory":"Hotels & Motels",
            "type":"Entertainment"
        }
    ],
    "sg:phone":"+1 609 771 1464",
    "sg:postcode":"08628",
    "sg:province":"NJ",
    "wof:name":"Inn America Hospitality",
    "wof:placetype":"venue"
},
  "geometry": {"coordinates":[-74.811138,40.286546],"type":"Point"}
}