{
  "type": "Feature",
  "properties": {
    "iso:country":"US",
    "sg:address":"3161 Kennedy Blvd",
    "sg:city":"North Bergen",
    "sg:classifiers":[
        {
            "category":"Social Services",
            "subcategory":"Retirement Home",
            "type":"Services"
        }
    ],
    "sg:phone":"+1 201 867 3585",
    "sg:postcode":"07047",
    "sg:province":"NJ",
    "sg:website":"www.fritzreuter.com/",
    "wof:name":"Fritz Reuter Retirement Community",
    "wof:placetype":"venue"
},
  "geometry": {"coordinates":[-74.033401,40.7752],"type":"Point"}
}