{
  "type": "Feature",
  "properties": {
    "iso:country":"US",
    "sg:address":"16 Port au Peck Ave",
    "sg:city":"Long Branch",
    "sg:classifiers":[
        {
            "category":"Professional",
            "type":"Services"
        }
    ],
    "sg:phone":"+1   ",
    "sg:postcode":"07740",
    "sg:province":"NJ",
    "wof:name":"Nautical Bar Inc",
    "wof:placetype":"venue"
},
  "geometry": {"coordinates":[-73.994484,40.320069],"type":"Point"}
}