{
  "type": "Feature",
  "properties": {
    "iso:country":"US",
    "sg:address":"36 Madison Ave",
    "sg:city":"Madison",
    "sg:classifiers":[
        {
            "category":"Education",
            "subcategory":"Library",
            "type":"Public Place"
        }
    ],
    "sg:phone":"+1 973 408 3590",
    "sg:postcode":"07940",
    "sg:province":"NJ",
    "sg:tags":[
        "special",
        "interest"
    ],
    "wof:name":"Methodist Library",
    "wof:placetype":"venue"
},
  "geometry": {"coordinates":[-74.422585,40.763184],"type":"Point"}
}