{
  "type": "Feature",
  "properties": {
    "addr:full":"10 Shady Ln Budd Lake NJ 07828",
    "addr:housenumber":"10",
    "addr:postcode":"07828",
    "addr:street":"Shady Ln",
    "iso:country":"US",
    "sg:address":"10 Shady Ln",
    "sg:city":"Budd Lake",
    "sg:classifiers":[
        {
            "category":"Building & Trades",
            "subcategory":"Construction",
            "type":"Services"
        }
    ],
    "sg:phone":"+1 973 989 1104",
    "sg:postcode":"07828",
    "sg:province":"NJ",
    "sg:tags":[
        "contractor"
    ],
    "wof:name":"WD Oglesby Roofing",
    "wof:placetype":"venue"
},
  "geometry": {"coordinates":[-74.742655,40.880559],"type":"Point"}
}