{
  "type": "Feature",
  "properties": {
    "addr:full":"15 Pollock Ave Jersey City NJ 07305",
    "addr:housenumber":"15",
    "addr:postcode":"07305",
    "addr:street":"Pollock Ave",
    "iso:country":"US",
    "sg:address":"15 Pollock Ave",
    "sg:city":"Jersey City",
    "sg:classifiers":[
        {
            "category":"Building & Trades",
            "subcategory":"Construction",
            "type":"Services"
        }
    ],
    "sg:phone":"+1 201 451 3911",
    "sg:postcode":"07305",
    "sg:province":"NJ",
    "sg:tags":[
        "maker",
        "cabinet"
    ],
    "wof:name":"Keats Waugh Inc",
    "wof:placetype":"venue"
},
  "geometry": {"coordinates":[-74.09003300000001,40.713962],"type":"Point"}
}