{
  "type": "Feature",
  "properties": {
    "addr:full":"339 Mountain Way Rutherford NJ 07070",
    "addr:housenumber":"339",
    "addr:postcode":"07070",
    "addr:street":"Mountain Way",
    "iso:country":"US",
    "sg:address":"339 Mountain Way",
    "sg:city":"Rutherford",
    "sg:classifiers":[
        {
            "category":"Wholesale",
            "subcategory":"Office Equipment",
            "type":"Manufacturing & Wholesale Goods"
        }
    ],
    "sg:phone":"+1 201 538 8016",
    "sg:postcode":"07070",
    "sg:province":"NJ",
    "wof:name":"C A S Copies Incorporate",
    "wof:placetype":"venue"
},
  "geometry": {"coordinates":[-74.108965,40.816614],"type":"Point"}
}