{
  "type": "Feature",
  "properties": {
    "addr:full":"959 Iron Bridge Rd Asbury NJ 08802",
    "addr:housenumber":"959",
    "addr:postcode":"08802",
    "addr:street":"Iron Bridge Rd",
    "iso:country":"US",
    "sg:address":"959 Iron Bridge Rd",
    "sg:city":"Asbury",
    "sg:classifiers":[
        {
            "category":"Organizations",
            "subcategory":"Membership Organization",
            "type":"Services"
        }
    ],
    "sg:phone":"+1 908 537 7297",
    "sg:postcode":"08802",
    "sg:province":"NJ",
    "wof:name":"Pyle Foundation",
    "wof:placetype":"venue"
},
  "geometry": {"coordinates":[-74.993236,40.682004],"type":"Point"}
}