{
  "type": "Feature",
  "properties": {
    "iso:country":"US",
    "sg:address":"72 Holly Ct",
    "sg:city":"Tabernacle",
    "sg:classifiers":[
        {
            "category":"Government",
            "subcategory":"Fire Station",
            "type":"Public Place"
        }
    ],
    "sg:phone":"+1 609 859 2600",
    "sg:postcode":"08088",
    "sg:province":"NJ",
    "sg:tags":[
        "department",
        "protection"
    ],
    "wof:name":"Lakes Volunteer Fire Company",
    "wof:placetype":"venue"
},
  "geometry": {"coordinates":[-74.712816,39.895616],"type":"Point"}
}