{
  "type": "Feature",
  "properties": {
    "addr:full":"2 Grant Ct Flanders NJ 07836",
    "addr:housenumber":"2",
    "addr:postcode":"07836",
    "addr:street":"Grant Ct",
    "iso:country":"US",
    "sg:address":"2 Grant Ct",
    "sg:city":"Flanders",
    "sg:classifiers":[
        {
            "category":"Professional",
            "type":"Services"
        }
    ],
    "sg:phone":"+1 973 584 6846",
    "sg:postcode":"07836",
    "sg:province":"NJ",
    "sg:tags":[
        "establishment"
    ],
    "wof:name":"L Howard & Co Inc",
    "wof:placetype":"venue"
},
  "geometry": {"coordinates":[-74.706467,40.823661],"type":"Point"}
}