{
  "type": "Feature",
  "properties": {
    "addr:full":"231 Crosswicks Rd Bordentown NJ 08505",
    "addr:housenumber":"231",
    "addr:postcode":"08505",
    "addr:street":"Crosswicks Rd",
    "iso:country":"US",
    "sg:address":"231 Crosswicks Rd",
    "sg:city":"Bordentown",
    "sg:classifiers":[
        {
            "category":"Insurance",
            "subcategory":"Insurance Agent",
            "type":"Services"
        }
    ],
    "sg:phone":"+1 609 324 2992",
    "sg:postcode":"08505",
    "sg:province":"NJ",
    "sg:tags":[
        "consultant"
    ],
    "wof:name":"Celtic Financial Group",
    "wof:placetype":"venue"
},
  "geometry": {"coordinates":[-74.691987,40.143714],"type":"Point"}
}