{
  "type": "Feature",
  "properties": {
    "addr:full":"365 E Main St Tuckerton NJ 08087",
    "addr:housenumber":"365",
    "addr:postcode":"08087",
    "addr:street":"E Main St",
    "iso:country":"US",
    "sg:address":"365 E Main St",
    "sg:city":"Tuckerton",
    "sg:classifiers":[
        {
            "category":"Social Services",
            "subcategory":"Job Training",
            "type":"Services"
        }
    ],
    "sg:phone":"+1 609 296 9698",
    "sg:postcode":"08087",
    "sg:province":"NJ",
    "sg:tags":[
        "retardation",
        "disabled",
        "mental",
        "dev"
    ],
    "wof:name":"Ocean County ARC",
    "wof:placetype":"venue"
},
  "geometry": {"coordinates":[-74.328253,39.608048],"type":"Point"}
}