{
  "type": "Feature",
  "properties": {
    "iso:country":"US",
    "sg:address":"21 3rd St",
    "sg:city":"Ridgefield Park",
    "sg:classifiers":[
        {
            "category":"Wholesale",
            "subcategory":"Stationery",
            "type":"Manufacturing & Wholesale Goods"
        }
    ],
    "sg:phone":"+1 201 296 0200",
    "sg:postcode":"07660",
    "sg:province":"NJ",
    "sg:tags":[
        "envelope"
    ],
    "wof:name":"Equitable Envelope & Paper Co",
    "wof:placetype":"venue"
},
  "geometry": {"coordinates":[-74.030075,40.863043],"type":"Point"}
}