{
  "type": "Feature",
  "properties": {
    "addr:full":"50 Louis St South Hackensack NJ 07606",
    "addr:housenumber":"50",
    "addr:postcode":"07606",
    "addr:street":"Louis St South",
    "iso:country":"US",
    "sg:address":"50 Louis St",
    "sg:city":"South Hackensack",
    "sg:classifiers":[
        {
            "category":"Shopping",
            "subcategory":"Crafts & Fabrics",
            "type":"Retail Goods"
        }
    ],
    "sg:phone":"+1 201 229 0100",
    "sg:postcode":"07606",
    "sg:province":"NJ",
    "sg:tags":[
        "art"
    ],
    "wof:name":"Cabin Crafters",
    "wof:placetype":"venue"
},
  "geometry": {"coordinates":[-74.046987,40.857815],"type":"Point"}
}