{
  "type": "Feature",
  "properties": {
    "iso:country":"US",
    "sg:address":"3312 W Brigantine Ave",
    "sg:city":"Brigantine",
    "sg:classifiers":[
        {
            "category":"Food & Beverages",
            "subcategory":"Meat & Fish",
            "type":"Retail Goods"
        }
    ],
    "sg:phone":"+1   ",
    "sg:postcode":"08203",
    "sg:province":"NJ",
    "sg:tags":[
        "seafood",
        "market"
    ],
    "wof:name":"Brigantine Seafood",
    "wof:placetype":"venue"
},
  "geometry": {"coordinates":[-74.386768,39.393274],"type":"Point"}
}