{
  "type": "Feature",
  "properties": {
    "iso:country":"US",
    "sg:address":"24 Schuyler Pl",
    "sg:city":"Morristown",
    "sg:classifiers":[
        {
            "category":"Personal",
            "subcategory":"Barber",
            "type":"Services"
        }
    ],
    "sg:phone":"+1 973 539 0136",
    "sg:postcode":"07960",
    "sg:province":"NJ",
    "sg:tags":[
        "shop"
    ],
    "wof:name":"Washington Barber Shop",
    "wof:placetype":"venue"
},
  "geometry": {"coordinates":[-74.483299,40.7971],"type":"Point"}
}