{
  "type": "Feature",
  "properties": {
    "addr:full":"2409 Pennington Rd Pennington NJ 08534",
    "addr:housenumber":"2409",
    "addr:postcode":"08534",
    "addr:street":"Pennington Rd",
    "iso:country":"US",
    "sg:address":"2409 Pennington Rd",
    "sg:city":"Pennington",
    "sg:classifiers":[
        {
            "category":"Professional",
            "subcategory":"Management & Consulting",
            "type":"Services"
        }
    ],
    "sg:phone":"+1 609 818 0229",
    "sg:postcode":"08534",
    "sg:province":"NJ",
    "sg:tags":[
        "consultant",
        "business"
    ],
    "wof:name":"Equity Value Advisors",
    "wof:placetype":"venue"
},
  "geometry": {"coordinates":[-74.78337999999999,40.29836],"type":"Point"}
}