{
  "type": "Feature",
  "properties": {
    "iso:country":"US",
    "sg:address":"610 N Bay Ave",
    "sg:city":"Beach Haven",
    "sg:classifiers":[
        {
            "category":"Restaurant",
            "type":"Food & Drink"
        }
    ],
    "sg:phone":"+1   ",
    "sg:postcode":"08008",
    "sg:province":"NJ",
    "sg:tags":[
        "eating"
    ],
    "wof:name":"Slice Of Heaven",
    "wof:placetype":"venue"
},
  "geometry": {"coordinates":[-74.23732699999999,39.567667],"type":"Point"}
}