{
  "type": "Feature",
  "properties": {
    "addr:full":"1210 White Horse Pike Oaklyn NJ 08107",
    "addr:housenumber":"1210",
    "addr:postcode":"08107",
    "addr:street":"White Horse Pike",
    "iso:country":"US",
    "sg:address":"1210 White Horse Pike",
    "sg:city":"Oaklyn",
    "sg:classifiers":[
        {
            "category":"Mining & Drilling",
            "type":"Manufacturing & Wholesale Goods"
        }
    ],
    "sg:phone":"+1   ",
    "sg:postcode":"08107",
    "sg:province":"NJ",
    "sg:tags":[
        "carwash",
        "nonmetallic",
        "mineral"
    ],
    "wof:name":"Diamond Detailing",
    "wof:placetype":"venue"
},
  "geometry": {"coordinates":[-75.073452,39.898393],"type":"Point"}
}