{
  "type": "Feature",
  "properties": {
    "iso:country":"US",
    "sg:address":"3100 Quakerbridge Rd",
    "sg:city":"Trenton",
    "sg:classifiers":[
        {
            "category":"Personal",
            "subcategory":"Beauty Salon",
            "type":"Services"
        }
    ],
    "sg:phone":"+1 609 890 4511",
    "sg:postcode":"08619",
    "sg:province":"NJ",
    "wof:name":"Jeanne Michel Salon & Spa",
    "wof:placetype":"venue"
},
  "geometry": {"coordinates":[-74.686177,40.247602],"type":"Point"}
}