{
  "type": "Feature",
  "properties": {
    "addr:full":"1 Anderson Hill Rd Bernardsville NJ 07924",
    "addr:housenumber":"1",
    "addr:postcode":"07924",
    "addr:street":"Anderson Hill Rd",
    "iso:country":"US",
    "sg:address":"1 Anderson Hill Rd",
    "sg:city":"Bernardsville",
    "sg:classifiers":[
        {
            "category":"Restaurant",
            "type":"Food & Drink"
        }
    ],
    "sg:phone":"+1   ",
    "sg:postcode":"07924",
    "sg:province":"NJ",
    "sg:tags":[
        "eating"
    ],
    "wof:name":"Aramark",
    "wof:placetype":"venue"
},
  "geometry": {"coordinates":[-74.56945,40.720377],"type":"Point"}
}