{
  "type": "Feature",
  "properties": {
    "iso:country":"US",
    "sg:address":"1183 Englishtown Rd",
    "sg:city":"Old Bridge",
    "sg:classifiers":[
        {
            "category":"Shopping",
            "type":"Retail Goods"
        }
    ],
    "sg:phone":"+1 732 251 8000",
    "sg:postcode":"08857",
    "sg:province":"NJ",
    "sg:tags":[
        "equipment",
        "durable",
        "medical",
        "supply"
    ],
    "wof:name":"Allcare Medical",
    "wof:placetype":"venue"
},
  "geometry": {"coordinates":[-74.36057099999999,40.400813],"type":"Point"}
}