{
  "type": "Feature",
  "properties": {
    "iso:country":"US",
    "sg:address":"101 Memorial Ln",
    "sg:city":"Mount Laurel",
    "sg:classifiers":[
        {
            "category":"Organizations",
            "subcategory":"Religious Organization",
            "type":"Services"
        }
    ],
    "sg:phone":"+1   ",
    "sg:postcode":"08054",
    "sg:province":"NJ",
    "wof:name":"Michael J Tambussi Rev",
    "wof:placetype":"venue"
},
  "geometry": {"coordinates":[-74.87426499999999,39.986018],"type":"Point"}
}