{
  "type": "Feature",
  "properties": {
    "iso:country":"US",
    "sg:address":"175 Rock Rd",
    "sg:city":"Glen Rock",
    "sg:classifiers":[
        {
            "category":"Communications",
            "type":"Services"
        }
    ],
    "sg:phone":"+1 201 447 1505",
    "sg:postcode":"07452",
    "sg:province":"NJ",
    "sg:tags":[
        "satellite"
    ],
    "wof:name":"M V S",
    "wof:placetype":"venue"
},
  "geometry": {"coordinates":[-74.13445,40.962844],"type":"Point"}
}