{
  "type": "Feature",
  "properties": {
    "addr:full":"4 Perilli Dr Trenton NJ 08610",
    "addr:housenumber":"4",
    "addr:postcode":"08610",
    "addr:street":"Perilli Dr",
    "iso:country":"US",
    "sg:address":"4 Perilli Dr",
    "sg:city":"Trenton",
    "sg:classifiers":[
        {
            "category":"Retail",
            "subcategory":"Repair Shop",
            "type":"Services"
        }
    ],
    "sg:phone":"+1 609 585 1872",
    "sg:postcode":"08610",
    "sg:province":"NJ",
    "wof:name":"Trent Meter Engineering",
    "wof:placetype":"venue"
},
  "geometry": {"coordinates":[-74.700823,40.207907],"type":"Point"}
}