{
  "type": "Feature",
  "properties": {
    "addr:full":"330 Elizabeth Ave Somerset NJ 08873",
    "addr:housenumber":"330",
    "addr:postcode":"08873",
    "addr:street":"Elizabeth Ave",
    "iso:country":"US",
    "sg:address":"330 Elizabeth Ave",
    "sg:city":"Somerset",
    "sg:classifiers":[
        {
            "category":"Manufacturing",
            "subcategory":"Tools & Machinery",
            "type":"Manufacturing & Wholesale Goods"
        }
    ],
    "sg:phone":"+1 732 469 5551",
    "sg:postcode":"08873",
    "sg:province":"NJ",
    "sg:tags":[
        "control",
        "mfg"
    ],
    "wof:name":"Matrix Controls Company Inc",
    "wof:placetype":"venue"
},
  "geometry": {"coordinates":[-74.532313,40.550173],"type":"Point"}
}