{
  "type": "Feature",
  "properties": {
    "addr:full":"266 Talmadge Rd Edison NJ 08817",
    "addr:housenumber":"266",
    "addr:postcode":"08817",
    "addr:street":"Talmadge Rd",
    "iso:country":"US",
    "sg:address":"266 Talmadge Rd",
    "sg:city":"Edison",
    "sg:classifiers":[
        {
            "category":"Personal",
            "subcategory":"Beauty Salon",
            "type":"Services"
        }
    ],
    "sg:phone":"+1 732 248 3444",
    "sg:postcode":"08817",
    "sg:province":"NJ",
    "sg:tags":[
        "shop"
    ],
    "wof:name":"Elite Nails",
    "wof:placetype":"venue"
},
  "geometry": {"coordinates":[-74.397869,40.540781],"type":"Point"}
}