{
  "type": "Feature",
  "properties": {
    "addr:full":"11 Patterson Ct Holmdel NJ 07733",
    "addr:housenumber":"11",
    "addr:postcode":"07733",
    "addr:street":"Patterson Ct",
    "iso:country":"US",
    "sg:address":"11 Patterson Ct",
    "sg:city":"Holmdel",
    "sg:classifiers":[
        {
            "category":"Professional",
            "subcategory":"Computer Services",
            "type":"Services"
        }
    ],
    "sg:phone":"+1 732 946 7121",
    "sg:postcode":"07733",
    "sg:province":"NJ",
    "sg:tags":[
        "related"
    ],
    "wof:name":"AK Assoc Inc",
    "wof:placetype":"venue"
},
  "geometry": {"coordinates":[-74.15002800000001,40.419631],"type":"Point"}
}