{
  "type": "Feature",
  "properties": {
    "addr:full":"514 Georges Rd North Brunswick NJ 08902",
    "addr:housenumber":"514",
    "addr:postcode":"08902",
    "addr:street":"Georges Rd",
    "iso:country":"US",
    "sg:address":"514 Georges Rd",
    "sg:city":"North Brunswick",
    "sg:classifiers":[
        {
            "category":"Shopping",
            "subcategory":"Used Merchandise",
            "type":"Retail Goods"
        }
    ],
    "sg:phone":"+1 732 828 0123",
    "sg:postcode":"08902",
    "sg:province":"NJ",
    "sg:tags":[
        "book",
        "rare",
        "dealer"
    ],
    "wof:name":"Book Swap Ctr",
    "wof:placetype":"venue"
},
  "geometry": {"coordinates":[-74.449862,40.471388],"type":"Point"}
}