{
  "type": "Feature",
  "properties": {
    "addr:full":"660 Ave C Bayonne NJ 07002",
    "addr:housenumber":"660",
    "addr:postcode":"07002",
    "addr:street":"Ave C",
    "iso:country":"US",
    "sg:address":"660 Ave C",
    "sg:city":"Bayonne",
    "sg:classifiers":[
        {
            "category":"Social Services",
            "subcategory":"Child Care",
            "type":"Services"
        }
    ],
    "sg:phone":"+1 201 339 0496",
    "sg:postcode":"07002",
    "sg:province":"NJ",
    "sg:tags":[
        "day"
    ],
    "wof:name":"Dee's Child Care",
    "wof:placetype":"venue"
},
  "geometry": {"coordinates":[-74.11633399999999,40.669895],"type":"Point"}
}