{
  "type": "Feature",
  "properties": {
    "addr:full":"15 Comly Rd Lincoln Park NJ 07035",
    "addr:housenumber":"15",
    "addr:postcode":"07035",
    "addr:street":"Comly Rd",
    "iso:country":"US",
    "sg:address":"15 Comly Rd",
    "sg:city":"Lincoln Park",
    "sg:classifiers":[
        {
            "category":"Building & Trades",
            "subcategory":"Electrical",
            "type":"Services"
        }
    ],
    "sg:phone":"+1 973 633 0444",
    "sg:postcode":"07035",
    "sg:province":"NJ",
    "sg:tags":[
        "electrician",
        "electric",
        "contractor"
    ],
    "wof:name":"Douglas Bell Electrical Contractors",
    "wof:placetype":"venue"
},
  "geometry": {"coordinates":[-74.299103,40.9375],"type":"Point"}
}