{
  "type": "Feature",
  "properties": {
    "iso:country":"US",
    "sg:address":"107 W Side Ave",
    "sg:city":"Jersey City",
    "sg:classifiers":[
        {
            "category":"Freight",
            "type":"Transportation"
        }
    ],
    "sg:phone":"+1 201 451 0880",
    "sg:postcode":"07305",
    "sg:province":"NJ",
    "sg:website":"www.general-transportation.com",
    "wof:name":"General Transportation Svc Inc",
    "wof:placetype":"venue"
},
  "geometry": {"coordinates":[-74.097131,40.707612],"type":"Point"}
}