{
  "type": "Feature",
  "properties": {
    "iso:country":"US",
    "sg:address":"2 Poplar Pl",
    "sg:city":"Neptune City",
    "sg:classifiers":[
        {
            "category":"Building & Trades",
            "subcategory":"Electrical",
            "type":"Services"
        }
    ],
    "sg:phone":"+1 732 988 0068",
    "sg:postcode":"07753",
    "sg:province":"NJ",
    "sg:tags":[
        "electric",
        "contractor"
    ],
    "wof:name":"Electrician Inc",
    "wof:placetype":"venue"
},
  "geometry": {"coordinates":[-74.02291700000001,40.198747],"type":"Point"}
}