{
  "type": "Feature",
  "properties": {
    "addr:full":"902 State Rte 35 Lavallette NJ 08735",
    "addr:housenumber":"902",
    "addr:postcode":"08735",
    "addr:street":"State Rte 35",
    "iso:country":"US",
    "sg:address":"902 State Rte 35",
    "sg:city":"Lavallette",
    "sg:classifiers":[
        {
            "category":"Manufacturing",
            "subcategory":"Retail Goods",
            "type":"Manufacturing & Wholesale Goods"
        }
    ],
    "sg:phone":"+1 732 830 7777",
    "sg:postcode":"08735",
    "sg:province":"NJ",
    "sg:tags":[
        "product",
        "mfg"
    ],
    "wof:name":"Mark Caramanna",
    "wof:placetype":"venue"
},
  "geometry": {"coordinates":[-74.06885699999999,39.971149],"type":"Point"}
}