{
  "type": "Feature",
  "properties": {
    "iso:country":"US",
    "sg:address":"725 Millbrook Rd",
    "sg:city":"Brick",
    "sg:classifiers":[
        {
            "category":"Building & Trades",
            "subcategory":"Construction",
            "type":"Services"
        }
    ],
    "sg:phone":"+1 732 836 0345",
    "sg:postcode":"08724",
    "sg:province":"NJ",
    "sg:tags":[
        "house"
    ],
    "wof:name":"Grandfathers Legacy Inc",
    "wof:placetype":"venue"
},
  "geometry": {"coordinates":[-74.119235,40.114264],"type":"Point"}
}