{
  "type": "Feature",
  "properties": {
    "iso:country":"US",
    "sg:address":"5 Willowbrook Ln",
    "sg:city":"Egg Harbor Twp",
    "sg:classifiers":[
        {
            "category":"Building & Trades",
            "subcategory":"Plumbing",
            "type":"Services"
        }
    ],
    "sg:phone":"+1 609 653 2027",
    "sg:postcode":"08234",
    "sg:province":"NJ",
    "sg:tags":[
        "conditioning",
        "air",
        "system",
        "contractor"
    ],
    "sg:website":"www.bartholomewheatingandcooling.com",
    "wof:name":"Bartholomew Heating & Cooling",
    "wof:placetype":"venue"
},
  "geometry": {"coordinates":[-74.581289,39.356867],"type":"Point"}
}