{
  "type": "Feature",
  "properties": {
    "addr:full":"173 Old Cranbury Rd Cranbury NJ 08512",
    "addr:housenumber":"173",
    "addr:postcode":"08512",
    "addr:street":"Old Cranbury Rd",
    "iso:country":"US",
    "sg:address":"173 Old Cranbury Rd",
    "sg:city":"Cranbury",
    "sg:classifiers":[
        {
            "category":"Building & Trades",
            "subcategory":"Construction",
            "type":"Services"
        }
    ],
    "sg:phone":"+1 609 443 8081",
    "sg:postcode":"08512",
    "sg:province":"NJ",
    "sg:tags":[
        "carpentry",
        "contractor"
    ],
    "wof:name":"Wiseman Built Construction",
    "wof:placetype":"venue"
},
  "geometry": {"coordinates":[-74.525701,40.289069],"type":"Point"}
}