{
  "type": "Feature",
  "properties": {
    "addr:full":"95 Christopher Columbus Dr Jersey City NJ 07302",
    "addr:housenumber":"95",
    "addr:postcode":"07302",
    "addr:street":"Christopher Columbus Dr",
    "iso:country":"US",
    "sg:address":"95 Christopher Columbus Dr",
    "sg:city":"Jersey City",
    "sg:classifiers":[
        {
            "category":"Building & Trades",
            "subcategory":"Locksmith",
            "type":"Services"
        }
    ],
    "sg:phone":"+1 201 253 1978",
    "sg:postcode":"07302",
    "sg:province":"NJ",
    "sg:tags":[
        "key"
    ],
    "wof:name":"Locksmith AAA",
    "wof:placetype":"venue"
},
  "geometry": {"coordinates":[-74.042384,40.719163],"type":"Point"}
}