{
  "type": "Feature",
  "properties": {
    "iso:country":"US",
    "sg:address":"33 US Hwy 206",
    "sg:city":"Augusta",
    "sg:classifiers":[
        {
            "category":"Personal",
            "subcategory":"Barber",
            "type":"Services"
        }
    ],
    "sg:phone":"+1 973 300 1116",
    "sg:postcode":"07822",
    "sg:province":"NJ",
    "wof:name":"Augusta Barber Shop",
    "wof:placetype":"venue"
},
  "geometry": {"coordinates":[-74.71745199999999,41.123348],"type":"Point"}
}