{
  "type": "Feature",
  "properties": {
    "iso:country":"US",
    "sg:address":"705 Whildam Ave",
    "sg:city":"Cape May",
    "sg:classifiers":[
        {
            "category":"Building & Trades",
            "subcategory":"Construction",
            "type":"Services"
        }
    ],
    "sg:phone":"+1 609 886 2823",
    "sg:postcode":"08204",
    "sg:province":"NJ",
    "sg:tags":[
        "residential"
    ],
    "wof:name":"Simonsens Custom Carpent",
    "wof:placetype":"venue"
},
  "geometry": {"coordinates":[-74.945438,38.975331],"type":"Point"}
}