{
  "type": "Feature",
  "properties": {
    "addr:full":"145 Cedar Ln Teaneck NJ 07666",
    "addr:housenumber":"145",
    "addr:postcode":"07666",
    "addr:street":"Cedar Ln",
    "iso:country":"US",
    "sg:address":"145 Cedar Ln",
    "sg:city":"Teaneck",
    "sg:classifiers":[
        {
            "category":"Restaurant",
            "type":"Food & Drink"
        }
    ],
    "sg:menulink":"http://www.allmenus.com/nj/teaneck/58909-best-wok/menu/",
    "sg:phone":"+1 201 836 6369",
    "sg:postcode":"07666",
    "sg:province":"NJ",
    "sg:tags":[
        "asian",
        "chinese"
    ],
    "wof:name":"Best Wok",
    "wof:placetype":"venue"
},
  "geometry": {"coordinates":[-74.01168699999999,40.885717],"type":"Point"}
}