{
  "type": "Feature",
  "properties": {
    "iso:country":"US",
    "sg:address":"1014 S Elmora Ave",
    "sg:city":"Elizabeth",
    "sg:classifiers":[
        {
            "category":"Education",
            "subcategory":"School",
            "type":"Public Place"
        }
    ],
    "sg:phone":"+1 908 436 4860",
    "sg:postcode":"07202",
    "sg:province":"NJ",
    "sg:tags":[
        "high",
        "middle",
        "elementary"
    ],
    "wof:name":"Elizabeth City of",
    "wof:placetype":"venue"
},
  "geometry": {"coordinates":[-74.226055,40.65387],"type":"Point"}
}