{
  "type": "Feature",
  "properties": {
    "iso:country":"US",
    "sg:address":"528 Market St",
    "sg:city":"Newark",
    "sg:classifiers":[
        {
            "category":"Local Transit",
            "type":"Transportation"
        }
    ],
    "sg:phone":"+1 973 344 6001",
    "sg:postcode":"07105",
    "sg:province":"NJ",
    "sg:tags":[
        "limousine"
    ],
    "wof:name":"Friends Limousine",
    "wof:placetype":"venue"
},
  "geometry": {"coordinates":[-74.155922,40.731923],"type":"Point"}
}