{
  "type": "Feature",
  "properties": {
    "addr:full":"1252 US Hwy 22 Phillipsburg NJ 08865",
    "addr:housenumber":"1252",
    "addr:postcode":"08865",
    "addr:street":"Us Hwy 22",
    "iso:country":"US",
    "sg:address":"1252 US Hwy 22",
    "sg:city":"Phillipsburg",
    "sg:classifiers":[
        {
            "category":"Shopping",
            "subcategory":"Gifts & Souvenirs",
            "type":"Retail Goods"
        }
    ],
    "sg:phone":"+1   ",
    "sg:postcode":"08865",
    "sg:province":"NJ",
    "wof:name":"Country Cottage",
    "wof:placetype":"venue"
},
  "geometry": {"coordinates":[-75.14756,40.681241],"type":"Point"}
}