{
  "type": "Feature",
  "properties": {
    "iso:country":"US",
    "sg:address":"1103 River Rd",
    "sg:city":"Hillsborough",
    "sg:classifiers":[
        {
            "category":"Professional",
            "type":"Services"
        }
    ],
    "sg:phone":"+1   ",
    "sg:postcode":"08844",
    "sg:province":"NJ",
    "wof:name":"William Barrett",
    "wof:placetype":"venue"
},
  "geometry": {"coordinates":[-74.72913699999999,40.515391],"type":"Point"}
}