{
  "type": "Feature",
  "properties": {
    "addr:full":"411 W Main St Boonton NJ 07005",
    "addr:housenumber":"411",
    "addr:postcode":"07005",
    "addr:street":"W Main St",
    "iso:country":"US",
    "sg:address":"411 W Main St",
    "sg:city":"Boonton",
    "sg:classifiers":[
        {
            "category":"Autos & Motor Vehicles",
            "subcategory":"Fuel & Gas Station",
            "type":"Retail Goods"
        }
    ],
    "sg:phone":"+1 973 263 9813",
    "sg:postcode":"07005",
    "sg:province":"NJ",
    "sg:tags":[
        "oil"
    ],
    "wof:name":"Shell",
    "wof:placetype":"venue"
},
  "geometry": {"coordinates":[-74.42564,40.905377],"type":"Point"}
}