{
  "type": "Feature",
  "properties": {
    "iso:country":"US",
    "sg:address":"107 State Rte 23",
    "sg:city":"Franklin",
    "sg:classifiers":[
        {
            "category":"Recreation",
            "type":"Entertainment"
        }
    ],
    "sg:phone":"+1 973 209 6129",
    "sg:postcode":"07416",
    "sg:province":"NJ",
    "sg:tags":[
        "martial",
        "arts",
        "instruction"
    ],
    "wof:name":"Chosun Tae KWON Do",
    "wof:placetype":"venue"
},
  "geometry": {"coordinates":[-74.58085199999999,41.102864],"type":"Point"}
}