{
  "type": "Feature",
  "properties": {
    "addr:full":"108 Industrial Dr Jersey City NJ 07305",
    "addr:housenumber":"108",
    "addr:postcode":"07305",
    "addr:street":"Industrial Dr",
    "iso:country":"US",
    "sg:address":"108 Industrial Dr",
    "sg:city":"Jersey City",
    "sg:classifiers":[
        {
            "category":"Professional",
            "type":"Services"
        }
    ],
    "sg:phone":"+1 212 432 1990",
    "sg:postcode":"07305",
    "sg:province":"NJ",
    "sg:tags":[
        "establishment"
    ],
    "wof:name":"Gtk Duplicating Inc",
    "wof:placetype":"venue"
},
  "geometry": {"coordinates":[-74.090092,40.679248],"type":"Point"}
}