{
  "type": "Feature",
  "properties": {
    "iso:country":"US",
    "sg:address":"15 Grand Ave",
    "sg:city":"Hackensack",
    "sg:classifiers":[
        {
            "category":"Retail",
            "subcategory":"Repair Shop",
            "type":"Services"
        }
    ],
    "sg:phone":"+1 201 334 3753",
    "sg:postcode":"07601",
    "sg:province":"NJ",
    "sg:tags":[
        "lock",
        "locksmith"
    ],
    "wof:name":"A 24 Hour Always Avualable",
    "wof:placetype":"venue"
},
  "geometry": {"coordinates":[-74.04405800000001,40.897251],"type":"Point"}
}