{
  "type": "Feature",
  "properties": {
    "addr:full":"390 George St New Brunswick NJ 08901",
    "addr:housenumber":"390",
    "addr:postcode":"08901",
    "addr:street":"George St",
    "iso:country":"US",
    "sg:address":"390 George St",
    "sg:city":"New Brunswick",
    "sg:classifiers":[
        {
            "category":"Professional",
            "subcategory":"Art Services",
            "type":"Services"
        }
    ],
    "sg:phone":"+1 732 565 0318",
    "sg:postcode":"08901",
    "sg:province":"NJ",
    "sg:tags":[
        "graphic",
        "design",
        "designer"
    ],
    "wof:name":"Hodge Graphic Design",
    "wof:placetype":"venue"
},
  "geometry": {"coordinates":[-74.44424100000001,40.496537],"type":"Point"}
}