{
  "type": "Feature",
  "properties": {
    "addr:full":"284 Whitehead Ave South River NJ 08882",
    "addr:housenumber":"284",
    "addr:postcode":"08882",
    "addr:street":"Whitehead Ave",
    "iso:country":"US",
    "sg:address":"284 Whitehead Ave",
    "sg:city":"South River",
    "sg:classifiers":[
        {
            "category":"Organizations",
            "subcategory":"Religious Organization",
            "type":"Services"
        }
    ],
    "sg:phone":"+1   ",
    "sg:postcode":"08882",
    "sg:province":"NJ",
    "wof:name":"Saint Ephrsynia Pltsk Blrusian",
    "wof:placetype":"venue"
},
  "geometry": {"coordinates":[-74.37721500000001,40.449553],"type":"Point"}
}