{
  "type": "Feature",
  "properties": {
    "addr:full":"10 Stuyvesant Ave Lyndhurst NJ 07071",
    "addr:housenumber":"10",
    "addr:postcode":"07071",
    "addr:street":"Stuyvesant Ave",
    "iso:country":"US",
    "sg:address":"10 Stuyvesant Ave",
    "sg:city":"Lyndhurst",
    "sg:classifiers":[
        {
            "category":"Professional",
            "subcategory":"Lawyer & Legal Services",
            "type":"Services"
        }
    ],
    "sg:phone":"+1 201 896 9825",
    "sg:postcode":"07071",
    "sg:province":"NJ",
    "sg:tags":[
        "attorney"
    ],
    "wof:name":"Talarico Anthony G Attrny Law",
    "wof:placetype":"venue"
},
  "geometry": {"coordinates":[-74.12216100000001,40.818401],"type":"Point"}
}