{
  "type": "Feature",
  "properties": {
    "iso:country":"US",
    "sg:address":"34 Copley Ave",
    "sg:city":"Teaneck",
    "sg:classifiers":[
        {
            "category":"Professional",
            "subcategory":"Business Services",
            "type":"Services"
        }
    ],
    "sg:phone":"+1   ",
    "sg:postcode":"07666",
    "sg:province":"NJ",
    "wof:name":"K Rrm Enterprises Inc",
    "wof:placetype":"venue"
},
  "geometry": {"coordinates":[-74.018826,40.878578],"type":"Point"}
}