{
  "type": "Feature",
  "properties": {
    "iso:country":"US",
    "sg:address":"271 Fort Lee Rd",
    "sg:city":"Leonia",
    "sg:classifiers":[
        {
            "category":"Professional",
            "subcategory":"Lawyer & Legal Services",
            "type":"Services"
        }
    ],
    "sg:phone":"+1 201 592 1862",
    "sg:postcode":"07605",
    "sg:province":"NJ",
    "wof:name":"David S Zapp",
    "wof:placetype":"venue"
},
  "geometry": {"coordinates":[-73.98797399999999,40.861852],"type":"Point"}
}