{
  "type": "Feature",
  "properties": {
    "iso:country":"US",
    "sg:address":"301 Birch Hollow Dr",
    "sg:city":"Bordentown",
    "sg:classifiers":[
        {
            "category":"Real Estate",
            "subcategory":"Real Estate Agent",
            "type":"Services"
        }
    ],
    "sg:phone":"+1   ",
    "sg:postcode":"08505",
    "sg:province":"NJ",
    "wof:name":"Birch Hollow Condominium Assn",
    "wof:placetype":"venue"
},
  "geometry": {"coordinates":[-74.781965,40.104642],"type":"Point"}
}