{
  "type": "Feature",
  "properties": {
    "iso:country":"US",
    "sg:address":"330 Indiana St",
    "sg:city":"Union",
    "sg:classifiers":[
        {
            "category":"Professional",
            "subcategory":"Printing & Photocopies",
            "type":"Services"
        }
    ],
    "sg:phone":"+1 908 206 1421",
    "sg:postcode":"07083",
    "sg:province":"NJ",
    "sg:tags":[
        "photocopying"
    ],
    "wof:name":"Nikkybell Inc",
    "wof:placetype":"venue"
},
  "geometry": {"coordinates":[-74.27301799999999,40.71677],"type":"Point"}
}