{
  "type": "Feature",
  "properties": {
    "addr:full":"839 Broad St Newark NJ 07102",
    "addr:housenumber":"839",
    "addr:postcode":"07102",
    "addr:street":"Broad St",
    "iso:country":"US",
    "sg:address":"839 Broad St",
    "sg:city":"Newark",
    "sg:classifiers":[
        {
            "category":"Retail",
            "subcategory":"Photofinishing",
            "type":"Services"
        }
    ],
    "sg:phone":"+1 973 648 0520",
    "sg:postcode":"07102",
    "sg:province":"NJ",
    "sg:tags":[
        "laboratory"
    ],
    "wof:name":"Downtown Photo",
    "wof:placetype":"venue"
},
  "geometry": {"coordinates":[-74.173233,40.733967],"type":"Point"}
}