{
  "type": "Feature",
  "properties": {
    "addr:full":"375 Blanch Ave Closter NJ 07624",
    "addr:housenumber":"375",
    "addr:postcode":"07624",
    "addr:street":"Blanch Ave",
    "iso:country":"US",
    "sg:address":"375 Blanch Ave",
    "sg:city":"Closter",
    "sg:classifiers":[
        {
            "category":"Building & Trades",
            "subcategory":"Construction",
            "type":"Services"
        }
    ],
    "sg:phone":"+1 201 767 9374",
    "sg:postcode":"07624",
    "sg:province":"NJ",
    "sg:tags":[
        "house"
    ],
    "wof:name":"Galcik Construction",
    "wof:placetype":"venue"
},
  "geometry": {"coordinates":[-73.942891,40.981978],"type":"Point"}
}