{
  "type": "Feature",
  "properties": {
    "iso:country":"US",
    "sg:address":"500 Dobranski Dr",
    "sg:city":"Perth Amboy",
    "sg:classifiers":[
        {
            "category":"Organizations",
            "subcategory":"Non-profit Organization",
            "type":"Services"
        }
    ],
    "sg:phone":"+1 732 826 0701",
    "sg:postcode":"08861",
    "sg:province":"NJ",
    "sg:tags":[
        "service/non-profit",
        "community"
    ],
    "wof:name":"Delaney-Dunlap Resident Council Inc",
    "wof:placetype":"venue"
},
  "geometry": {"coordinates":[-74.279297,40.530899],"type":"Point"}
}