{
  "type": "Feature",
  "properties": {
    "iso:country":"US",
    "sg:address":"4 Baker Rd",
    "sg:city":"Livingston",
    "sg:classifiers":[
        {
            "category":"Real Estate",
            "subcategory":"Real Estate Agent",
            "type":"Services"
        }
    ],
    "sg:phone":"+1   ",
    "sg:postcode":"07039",
    "sg:province":"NJ",
    "wof:name":"One Independence Corp",
    "wof:placetype":"venue"
},
  "geometry": {"coordinates":[-74.35112599999999,40.789321],"type":"Point"}
}