{
  "type": "Feature",
  "properties": {
    "iso:country":"US",
    "sg:address":"135 Lafayette St",
    "sg:city":"Newark",
    "sg:classifiers":[
        {
            "category":"Home & Garden",
            "subcategory":"Hardware",
            "type":"Retail Goods"
        }
    ],
    "sg:phone":"+1   ",
    "sg:postcode":"07105",
    "sg:province":"NJ",
    "wof:name":"Lafayette Supply LLC",
    "wof:placetype":"venue"
},
  "geometry": {"coordinates":[-74.16656399999999,40.730785],"type":"Point"}
}