{
  "type": "Feature",
  "properties": {
    "addr:full":"208 Undercliff Ave Edgewater NJ 07020",
    "addr:housenumber":"208",
    "addr:postcode":"07020",
    "addr:street":"Undercliff Ave",
    "iso:country":"US",
    "sg:address":"208 Undercliff Ave",
    "sg:city":"Edgewater",
    "sg:classifiers":[
        {
            "category":"Professional",
            "type":"Services"
        }
    ],
    "sg:phone":"+1 201 313 9783",
    "sg:postcode":"07020",
    "sg:province":"NJ",
    "sg:tags":[
        "establishment"
    ],
    "wof:name":"Hobbiecom Pr Inc",
    "wof:placetype":"venue"
},
  "geometry": {"coordinates":[-73.979478,40.821232],"type":"Point"}
}