{
  "type": "Feature",
  "properties": {
    "addr:full":"682 Lyons Ave Irvington NJ 07111",
    "addr:housenumber":"682",
    "addr:postcode":"07111",
    "addr:street":"Lyons Ave",
    "iso:country":"US",
    "sg:address":"682 Lyons Ave",
    "sg:city":"Irvington",
    "sg:classifiers":[
        {
            "category":"Building & Trades",
            "subcategory":"Construction",
            "type":"Services"
        }
    ],
    "sg:phone":"+1 973 375 8355",
    "sg:postcode":"07111",
    "sg:province":"NJ",
    "sg:tags":[
        "general",
        "contractor"
    ],
    "wof:name":"LCK Construction Inc",
    "wof:placetype":"venue"
},
  "geometry": {"coordinates":[-74.231562,40.72065],"type":"Point"}
}