{
  "type": "Feature",
  "properties": {
    "addr:full":"5 Bergen Hill Rd Rockaway NJ 07866",
    "addr:housenumber":"5",
    "addr:postcode":"07866",
    "addr:street":"Bergen Hill Rd",
    "iso:country":"US",
    "sg:address":"5 Bergen Hill Rd",
    "sg:city":"Rockaway",
    "sg:classifiers":[
        {
            "category":"Building & Trades",
            "subcategory":"Landscaping Services",
            "type":"Services"
        }
    ],
    "sg:phone":"+1 973 586 0474",
    "sg:postcode":"07866",
    "sg:province":"NJ",
    "sg:tags":[
        "landscape",
        "contractor"
    ],
    "wof:name":"Brau's Landscapes Plus Inc",
    "wof:placetype":"venue"
},
  "geometry": {"coordinates":[-74.499404,40.952512],"type":"Point"}
}