{
  "type": "Feature",
  "properties": {
    "addr:full":"349 Hazel St Clifton NJ 07011",
    "addr:housenumber":"349",
    "addr:postcode":"07011",
    "addr:street":"Hazel St",
    "iso:country":"US",
    "sg:address":"349 Hazel St",
    "sg:city":"Clifton",
    "sg:classifiers":[
        {
            "category":"Bars & Pubs",
            "type":"Food & Drink"
        }
    ],
    "sg:phone":"+1 973 772 9730",
    "sg:postcode":"07011",
    "sg:province":"NJ",
    "sg:tags":[
        "drinking",
        "restaurant"
    ],
    "wof:name":"Hazel Street Pub",
    "wof:placetype":"venue"
},
  "geometry": {"coordinates":[-74.160202,40.889702],"type":"Point"}
}