{
  "type": "Feature",
  "properties": {
    "addr:full":"1114 Sussex Tpke Randolph NJ 07869",
    "addr:housenumber":"1114",
    "addr:postcode":"07869",
    "addr:street":"Sussex Tpke",
    "iso:country":"US",
    "sg:address":"1114 Sussex Tpke",
    "sg:city":"Randolph",
    "sg:classifiers":[
        {
            "category":"Shopping",
            "subcategory":"Computers & Home Electronics",
            "type":"Retail Goods"
        }
    ],
    "sg:phone":"+1   ",
    "sg:postcode":"07869",
    "sg:province":"NJ",
    "wof:name":"Onsite Computer Services",
    "wof:placetype":"venue"
},
  "geometry": {"coordinates":[-74.559709,40.825013],"type":"Point"}
}