{
  "type": "Feature",
  "properties": {
    "addr:full":"215 Elm Ave Rahway NJ 07065",
    "addr:housenumber":"215",
    "addr:postcode":"07065",
    "addr:street":"Elm Ave",
    "iso:country":"US",
    "sg:address":"215 Elm Ave",
    "sg:city":"Rahway",
    "sg:classifiers":[
        {
            "category":"Organizations",
            "subcategory":"Religious Organization",
            "type":"Services"
        }
    ],
    "sg:phone":"+1 732 388 1815",
    "sg:postcode":"07065",
    "sg:province":"NJ",
    "sg:website":"www.zionlutherannj.org",
    "wof:name":"Zion Lutheran Church",
    "wof:placetype":"venue"
},
  "geometry": {"coordinates":[-74.28111699999999,40.607993],"type":"Point"}
}