{
  "type": "Feature",
  "properties": {
    "addr:full":"212 Boston Ave Egg Harbor Township NJ 08234",
    "addr:housenumber":"212",
    "addr:postcode":"08234",
    "addr:street":"Boston Ave",
    "iso:country":"US",
    "sg:address":"212 Boston Ave",
    "sg:city":"Egg Harbor Township",
    "sg:classifiers":[
        {
            "category":"Communications",
            "subcategory":"Film & Video Production",
            "type":"Services"
        }
    ],
    "sg:phone":"+1   ",
    "sg:postcode":"08234",
    "sg:province":"NJ",
    "sg:tags":[
        "motion"
    ],
    "wof:name":"G V A Video Productions",
    "wof:placetype":"venue"
},
  "geometry": {"coordinates":[-74.626312,39.356184],"type":"Point"}
}