{
  "type": "Feature",
  "properties": {
    "addr:full":"70 Jackson Dr Cranford NJ 07016",
    "addr:housenumber":"70",
    "addr:postcode":"07016",
    "addr:street":"Jackson Dr",
    "iso:country":"US",
    "sg:address":"70 Jackson Dr",
    "sg:city":"Cranford",
    "sg:classifiers":[
        {
            "category":"Professional",
            "subcategory":"Business Services",
            "type":"Services"
        }
    ],
    "sg:phone":"+1   ",
    "sg:postcode":"07016",
    "sg:province":"NJ",
    "sg:tags":[
        "for",
        "equipment",
        "medical",
        "medic",
        "linen",
        "wholesaler"
    ],
    "wof:name":"Rosgal Ltd",
    "wof:placetype":"venue"
},
  "geometry": {"coordinates":[-74.283107,40.647903],"type":"Point"}
}