{
  "type": "Feature",
  "properties": {
    "iso:country":"US",
    "sg:address":"14 Trimble St",
    "sg:city":"Medford",
    "sg:classifiers":[
        {
            "category":"Building & Trades",
            "subcategory":"Construction",
            "type":"Services"
        }
    ],
    "sg:phone":"+1 609 654 4663",
    "sg:postcode":"08055",
    "sg:province":"NJ",
    "sg:tags":[
        "contractor"
    ],
    "wof:name":"Integrity Tile",
    "wof:placetype":"venue"
},
  "geometry": {"coordinates":[-74.825419,39.892329],"type":"Point"}
}