{
  "type": "Feature",
  "properties": {
    "iso:country":"US",
    "sg:address":"405 South St",
    "sg:city":"Brielle",
    "sg:classifiers":[
        {
            "category":"Building & Trades",
            "subcategory":"Construction",
            "type":"Services"
        }
    ],
    "sg:phone":"+1 732 223 6146",
    "sg:postcode":"08730",
    "sg:province":"NJ",
    "sg:tags":[
        "residential"
    ],
    "wof:name":"Evron Corp",
    "wof:placetype":"venue"
},
  "geometry": {"coordinates":[-74.061502,40.115886],"type":"Point"}
}