{
  "type": "Feature",
  "properties": {
    "addr:full":"133 S Main St Milltown NJ 08850",
    "addr:housenumber":"133",
    "addr:postcode":"08850",
    "addr:street":"S Main St",
    "iso:country":"US",
    "sg:address":"133 S Main St",
    "sg:city":"Milltown",
    "sg:classifiers":[
        {
            "category":"Health Services",
            "subcategory":"Doctor",
            "type":"Services"
        }
    ],
    "sg:phone":"+1 732 545 9009",
    "sg:postcode":"08850",
    "sg:province":"NJ",
    "sg:tags":[
        "dentist"
    ],
    "wof:name":"All Smiles Family Dental LLC",
    "wof:placetype":"venue"
},
  "geometry": {"coordinates":[-74.43413099999999,40.448205],"type":"Point"}
}