{
  "type": "Feature",
  "properties": {
    "addr:full":"34 Astor Ct Sayreville NJ 08872",
    "addr:housenumber":"34",
    "addr:postcode":"08872",
    "addr:street":"Astor Ct",
    "iso:country":"US",
    "sg:address":"34 Astor Ct",
    "sg:city":"Sayreville",
    "sg:classifiers":[
        {
            "category":"Building & Trades",
            "subcategory":"Electrical",
            "type":"Services"
        }
    ],
    "sg:phone":"+1 732 254 4246",
    "sg:postcode":"08872",
    "sg:province":"NJ",
    "sg:tags":[
        "electrical",
        "contractor"
    ],
    "wof:name":"Acoustech Inc",
    "wof:placetype":"venue"
},
  "geometry": {"coordinates":[-74.333985,40.47208],"type":"Point"}
}