{
  "type": "Feature",
  "properties": {
    "addr:full":"378 Lakehurst Rd Browns Mills NJ 08015",
    "addr:housenumber":"378",
    "addr:postcode":"08015",
    "addr:street":"Lakehurst Rd",
    "iso:country":"US",
    "sg:address":"378 Lakehurst Rd",
    "sg:city":"Browns Mills",
    "sg:classifiers":[
        {
            "category":"Restaurant",
            "type":"Food & Drink"
        }
    ],
    "sg:phone":"+1   ",
    "sg:postcode":"08015",
    "sg:province":"NJ",
    "sg:tags":[
        "eating"
    ],
    "wof:name":"China Kitchen",
    "wof:placetype":"venue"
},
  "geometry": {"coordinates":[-74.574247,39.964221],"type":"Point"}
}