{
  "type": "Feature",
  "properties": {
    "addr:full":"5 Laurel Dr Flanders NJ 07836",
    "addr:housenumber":"5",
    "addr:postcode":"07836",
    "addr:street":"Laurel Dr",
    "iso:country":"US",
    "sg:address":"5 Laurel Dr",
    "sg:city":"Flanders",
    "sg:classifiers":[
        {
            "category":"Home & Garden",
            "subcategory":"Home Furnishings",
            "type":"Retail Goods"
        }
    ],
    "sg:phone":"+1 973 927 0020",
    "sg:postcode":"07836",
    "sg:province":"NJ",
    "sg:tags":[
        "mirror"
    ],
    "wof:name":"Reflections Custom Mirror",
    "wof:placetype":"venue"
},
  "geometry": {"coordinates":[-74.701588,40.843925],"type":"Point"}
}