{
  "type": "Feature",
  "properties": {
    "addr:full":"641 Shunpike Rd Chatham NJ 07928",
    "addr:housenumber":"641",
    "addr:postcode":"07928",
    "addr:street":"Shunpike Rd",
    "iso:country":"US",
    "sg:address":"641 Shunpike Rd",
    "sg:city":"Chatham",
    "sg:classifiers":[
        {
            "category":"Food & Beverages",
            "subcategory":"Groceries & Convenience Stores",
            "type":"Retail Goods"
        }
    ],
    "sg:phone":"+1 973 377 4788",
    "sg:postcode":"07928",
    "sg:province":"NJ",
    "sg:tags":[
        "grocer"
    ],
    "sg:website":"www.shoprite.com",
    "wof:name":"Shop Rite Supermarket",
    "wof:placetype":"venue"
},
  "geometry": {"coordinates":[-74.43215499999999,40.746447],"type":"Point"}
}