{
  "type": "Feature",
  "properties": {
    "iso:country":"US",
    "sg:address":"155 Gaither Dr",
    "sg:city":"Mount Laurel",
    "sg:classifiers":[
        {
            "category":"Banks & Credit Unions",
            "subcategory":"Financial Services",
            "type":"Services"
        }
    ],
    "sg:phone":"+1   ",
    "sg:postcode":"08054",
    "sg:province":"NJ",
    "sg:tags":[
        "patent",
        "public",
        "relations"
    ],
    "wof:name":"Thomas Boyd Communication",
    "wof:placetype":"venue"
},
  "geometry": {"coordinates":[-74.946848,39.938674],"type":"Point"}
}