{
  "type": "Feature",
  "properties": {
    "addr:full":"82 Boothby Dr Mount Laurel NJ 08054",
    "addr:housenumber":"82",
    "addr:postcode":"08054",
    "addr:street":"Boothby Dr",
    "iso:country":"US",
    "sg:address":"82 Boothby Dr",
    "sg:city":"Mount Laurel",
    "sg:classifiers":[
        {
            "category":"Shopping",
            "subcategory":"Gifts & Souvenirs",
            "type":"Retail Goods"
        }
    ],
    "sg:phone":"+1   ",
    "sg:postcode":"08054",
    "sg:province":"NJ",
    "wof:name":"Jest Notes",
    "wof:placetype":"venue"
},
  "geometry": {"coordinates":[-74.874899,39.982479],"type":"Point"}
}