{
  "type": "Feature",
  "properties": {
    "iso:country":"US",
    "sg:address":"84 Oceanport Ave",
    "sg:city":"Little Silver",
    "sg:classifiers":[
        {
            "category":"Shopping",
            "subcategory":"Clothing, Apparel, & Fashions",
            "type":"Retail Goods"
        }
    ],
    "sg:phone":"+1 732 530 5443",
    "sg:postcode":"07739",
    "sg:province":"NJ",
    "sg:tags":[
        "item",
        "boutique"
    ],
    "wof:name":"Lynne's Fashion Boutique Inc",
    "wof:placetype":"venue"
},
  "geometry": {"coordinates":[-74.037502,40.323483],"type":"Point"}
}