{
  "type": "Feature",
  "properties": {
    "iso:country":"US",
    "sg:address":"424 Bergen Ave",
    "sg:city":"Jersey City",
    "sg:classifiers":[
        {
            "category":"Organizations",
            "subcategory":"Religious Organization",
            "type":"Services"
        }
    ],
    "sg:phone":"+1   ",
    "sg:postcode":"07304",
    "sg:province":"NJ",
    "wof:name":"E F Webb Rev",
    "wof:placetype":"venue"
},
  "geometry": {"coordinates":[-74.078689,40.715899],"type":"Point"}
}