{
  "type": "Feature",
  "properties": {
    "iso:country":"US",
    "sg:address":"106 N Barrow Pl",
    "sg:city":"Princeton",
    "sg:classifiers":[
        {
            "category":"Health Services",
            "subcategory":"Doctor",
            "type":"Services"
        }
    ],
    "sg:phone":"+1 609 919 0680",
    "sg:postcode":"08540",
    "sg:province":"NJ",
    "wof:name":"Dental Illuminations Inc",
    "wof:placetype":"venue"
},
  "geometry": {"coordinates":[-74.63822999999999,40.315379],"type":"Point"}
}