{
  "type": "Feature",
  "properties": {
    "addr:full":"260 Nassau St Princeton NJ 08542",
    "addr:housenumber":"260",
    "addr:postcode":"08542",
    "addr:street":"Nassau St",
    "iso:country":"US",
    "sg:address":"260 Nassau St",
    "sg:city":"Princeton",
    "sg:classifiers":[
        {
            "category":"Restaurant",
            "type":"Food & Drink"
        }
    ],
    "sg:menulink":"http://www.allmenus.com/nj/princeton/18765-tiger-noodles/menu/",
    "sg:phone":"+1 609 252 0663",
    "sg:postcode":"08542",
    "sg:province":"NJ",
    "sg:tags":[
        "asian",
        "chinese"
    ],
    "wof:name":"Tiger Noodles",
    "wof:placetype":"venue"
},
  "geometry": {"coordinates":[-74.650648,40.352387],"type":"Point"}
}