{
  "type": "Feature",
  "properties": {
    "iso:country":"US",
    "sg:address":"5 Manor Dr",
    "sg:city":"Newark",
    "sg:classifiers":[
        {
            "category":"Health Services",
            "subcategory":"Doctor",
            "type":"Services"
        }
    ],
    "sg:phone":"+1 973 375 3355",
    "sg:postcode":"07106",
    "sg:province":"NJ",
    "sg:tags":[
        "physician",
        "surgeon",
        "medical"
    ],
    "wof:name":"Sisina Greco MD",
    "wof:placetype":"venue"
},
  "geometry": {"coordinates":[-74.246697,40.737202],"type":"Point"}
}