{
  "type": "Feature",
  "properties": {
    "iso:country":"US",
    "sg:address":"537 Monmouth Rd",
    "sg:city":"Jackson",
    "sg:classifiers":[
        {
            "category":"Shopping",
            "subcategory":"Shoes",
            "type":"Retail Goods"
        }
    ],
    "sg:phone":"+1   ",
    "sg:postcode":"08527",
    "sg:province":"NJ",
    "wof:name":"Reebok",
    "wof:placetype":"venue"
},
  "geometry": {"coordinates":[-74.42093199999999,40.16242],"type":"Point"}
}