{
  "type": "Feature",
  "properties": {
    "addr:full":"1228 Morton St Camden NJ 08104",
    "addr:housenumber":"1228",
    "addr:postcode":"08104",
    "addr:street":"Morton St",
    "iso:country":"US",
    "sg:address":"1228 Morton St",
    "sg:city":"Camden",
    "sg:classifiers":[
        {
            "category":"Shopping",
            "subcategory":"Gifts & Souvenirs",
            "type":"Retail Goods"
        }
    ],
    "sg:phone":"+1   ",
    "sg:postcode":"08104",
    "sg:province":"NJ",
    "sg:tags":[
        "merchandise"
    ],
    "wof:name":"Calendars Galour Etc Etc",
    "wof:placetype":"venue"
},
  "geometry": {"coordinates":[-75.102152,39.926441],"type":"Point"}
}