{
  "type": "Feature",
  "properties": {
    "addr:full":"1197 Haddon Ave Camden NJ 08103",
    "addr:housenumber":"1197",
    "addr:postcode":"08103",
    "addr:street":"Haddon Ave",
    "iso:country":"US",
    "sg:address":"1197 Haddon Ave",
    "sg:city":"Camden",
    "sg:classifiers":[
        {
            "category":"Personal",
            "subcategory":"Nail Salon",
            "type":"Services"
        }
    ],
    "sg:phone":"+1 856 541 3570",
    "sg:postcode":"08103",
    "sg:province":"NJ",
    "wof:name":"Jenny Nails",
    "wof:placetype":"venue"
},
  "geometry": {"coordinates":[-75.102898,39.9324],"type":"Point"}
}