{
  "type": "Feature",
  "properties": {
    "addr:full":"400 Broadway Rd Freehold NJ 07728",
    "addr:housenumber":"400",
    "addr:postcode":"07728",
    "addr:street":"Broadway Rd",
    "iso:country":"US",
    "sg:address":"400 Broadway Rd",
    "sg:city":"Freehold",
    "sg:classifiers":[
        {
            "category":"Home & Garden",
            "subcategory":"Garden Supply",
            "type":"Retail Goods"
        }
    ],
    "sg:phone":"+1   ",
    "sg:postcode":"07728",
    "sg:province":"NJ",
    "wof:name":"Lawrence J Lapide Inc",
    "wof:placetype":"venue"
},
  "geometry": {"coordinates":[-74.260577,40.284971],"type":"Point"}
}