{
  "type": "Feature",
  "properties": {
    "addr:full":"174 Greentree Rd Blackwood NJ 08012",
    "addr:housenumber":"174",
    "addr:postcode":"08012",
    "addr:street":"Greentree Rd",
    "iso:country":"US",
    "sg:address":"174 Greentree Rd",
    "sg:city":"Blackwood",
    "sg:classifiers":[
        {
            "category":"Health Services",
            "subcategory":"Doctor",
            "type":"Services"
        }
    ],
    "sg:phone":"+1 856 374 9992",
    "sg:postcode":"08012",
    "sg:province":"NJ",
    "sg:tags":[
        "medical"
    ],
    "wof:name":"Myopia Family Study",
    "wof:placetype":"venue"
},
  "geometry": {"coordinates":[-75.05500000000001,39.756565],"type":"Point"}
}