{
  "type": "Feature",
  "properties": {
    "addr:full":"172 Broadway Woodcliff Lake NJ 07677",
    "addr:housenumber":"172",
    "addr:postcode":"07677",
    "addr:street":"Broadway",
    "iso:country":"US",
    "sg:address":"172 Broadway",
    "sg:city":"Woodcliff Lake",
    "sg:classifiers":[
        {
            "category":"Restaurant",
            "type":"Food & Drink"
        }
    ],
    "sg:phone":"+1 201 505 9111",
    "sg:postcode":"07677",
    "sg:province":"NJ",
    "sg:tags":[
        "delivery"
    ],
    "wof:name":"Dine In Restaurant Delivery",
    "wof:placetype":"venue"
},
  "geometry": {"coordinates":[-74.04061299999999,41.021066],"type":"Point"}
}