{
  "type": "Feature",
  "properties": {
    "iso:country":"US",
    "sg:address":"3 Waterford Ct",
    "sg:city":"Ringwood",
    "sg:classifiers":[
        {
            "category":"Wholesale",
            "subcategory":"Computers",
            "type":"Manufacturing & Wholesale Goods"
        }
    ],
    "sg:phone":"+1 973 962 6703",
    "sg:postcode":"07456",
    "sg:province":"NJ",
    "wof:name":"IB Online LLC",
    "wof:placetype":"venue"
},
  "geometry": {"coordinates":[-74.248514,41.087681],"type":"Point"}
}