{
  "type": "Feature",
  "properties": {
    "iso:country":"US",
    "sg:address":"60 Hickory Dr",
    "sg:city":"Basking Ridge",
    "sg:classifiers":[
        {
            "category":"Utilities",
            "subcategory":"Telephone",
            "type":"Services"
        }
    ],
    "sg:phone":"+1 908 580 0572",
    "sg:postcode":"07920",
    "sg:province":"NJ",
    "sg:tags":[
        "communications",
        "computer",
        "related"
    ],
    "wof:name":"Hellas Systems Services L",
    "wof:placetype":"venue"
},
  "geometry": {"coordinates":[-74.54741799999999,40.677599],"type":"Point"}
}