{
  "type": "Feature",
  "properties": {
    "iso:country":"US",
    "sg:address":"385 Hillside Ave",
    "sg:city":"Hillside",
    "sg:classifiers":[
        {
            "category":"Manufacturing",
            "subcategory":"Metals",
            "type":"Manufacturing & Wholesale Goods"
        }
    ],
    "sg:phone":"+1 973 926 0900",
    "sg:postcode":"07205",
    "sg:province":"NJ",
    "sg:tags":[
        "steel",
        "spring",
        "mfg"
    ],
    "wof:name":"Rolex",
    "wof:placetype":"venue"
},
  "geometry": {"coordinates":[-74.233902,40.70371],"type":"Point"}
}