{
  "type": "Feature",
  "properties": {
    "addr:full":"489 Riverview Dr Totowa NJ 07512",
    "addr:housenumber":"489",
    "addr:postcode":"07512",
    "addr:street":"Riverview Dr",
    "iso:country":"US",
    "sg:address":"489 Riverview Dr",
    "sg:city":"Totowa",
    "sg:classifiers":[
        {
            "category":"Real Estate",
            "subcategory":"Real Estate Agent",
            "type":"Services"
        },
        {
            "category":"Banks & Credit Unions",
            "subcategory":"Financial Services",
            "type":"Services"
        }
    ],
    "sg:phone":"+1 973 812 4495",
    "sg:postcode":"07512",
    "sg:province":"NJ",
    "sg:tags":[
        "trust",
        "investment"
    ],
    "wof:name":"Crimson Capital LLC",
    "wof:placetype":"venue"
},
  "geometry": {"coordinates":[-74.21978300000001,40.89197],"type":"Point"}
}