{
  "type": "Feature",
  "properties": {
    "addr:full":"237 Centre St Nutley NJ 07110",
    "addr:housenumber":"237",
    "addr:postcode":"07110",
    "addr:street":"Centre St",
    "iso:country":"US",
    "sg:address":"237 Centre St",
    "sg:city":"Nutley",
    "sg:classifiers":[
        {
            "category":"Recreation",
            "type":"Entertainment"
        }
    ],
    "sg:phone":"+1   ",
    "sg:postcode":"07110",
    "sg:province":"NJ",
    "sg:tags":[
        "fitness"
    ],
    "wof:name":"Private Lessons Inc",
    "wof:placetype":"venue"
},
  "geometry": {"coordinates":[-74.158036,40.813233],"type":"Point"}
}