{
  "type": "Feature",
  "properties": {
    "iso:country":"US",
    "sg:address":"7 Orange Pl",
    "sg:city":"West Orange",
    "sg:classifiers":[
        {
            "category":"Real Estate",
            "subcategory":"Real Estate Agent",
            "type":"Services"
        }
    ],
    "sg:phone":"+1 973 736 3886",
    "sg:postcode":"07052",
    "sg:province":"NJ",
    "sg:tags":[
        "appraiser"
    ],
    "wof:name":"Hendricks Appraisal Co",
    "wof:placetype":"venue"
},
  "geometry": {"coordinates":[-74.232258,40.792554],"type":"Point"}
}