{
  "type": "Feature",
  "properties": {
    "addr:full":"14 Beaverson Blvd Brick NJ 08723",
    "addr:housenumber":"14",
    "addr:postcode":"08723",
    "addr:street":"Beaverson Blvd",
    "iso:country":"US",
    "sg:address":"14 Beaverson Blvd",
    "sg:city":"Brick",
    "sg:classifiers":[
        {
            "category":"Personal",
            "subcategory":"Beauty Salon",
            "type":"Services"
        }
    ],
    "sg:phone":"+1 732 477 2834",
    "sg:postcode":"08723",
    "sg:province":"NJ",
    "wof:name":"New Beginnings Hair Care Ctr",
    "wof:placetype":"venue"
},
  "geometry": {"coordinates":[-74.14468100000001,40.032569],"type":"Point"}
}