{
  "type": "Feature",
  "properties": {
    "iso:country":"US",
    "sg:address":"830 State Rte 35",
    "sg:city":"Shrewsbury",
    "sg:classifiers":[
        {
            "category":"Health Services",
            "subcategory":"Health Practitioner",
            "type":"Services"
        }
    ],
    "sg:phone":"+1 732 345 6422",
    "sg:postcode":"07702",
    "sg:province":"NJ",
    "sg:tags":[
        "nurse",
        "registry"
    ],
    "wof:name":"Jackeline Biddle",
    "wof:placetype":"venue"
},
  "geometry": {"coordinates":[-74.061775,40.325714],"type":"Point"}
}