{
  "type": "Feature",
  "properties": {
    "iso:country":"US",
    "sg:address":"26 College Rd",
    "sg:city":"Netcong",
    "sg:classifiers":[
        {
            "category":"Education",
            "subcategory":"School",
            "type":"Public Place"
        }
    ],
    "sg:phone":"+1 973 347 0020",
    "sg:postcode":"07857",
    "sg:province":"NJ",
    "sg:website":"www.netcongschool.org",
    "wof:name":"Netcong Elementary School",
    "wof:placetype":"venue"
},
  "geometry": {"coordinates":[-74.697076,40.901617],"type":"Point"}
}