{
  "type": "Feature",
  "properties": {
    "addr:full":"4047 Ocean Heights Ave Egg Harbor Twp NJ 08234",
    "addr:housenumber":"4047",
    "addr:postcode":"08234",
    "addr:street":"Ocean Heights Ave",
    "iso:country":"US",
    "sg:address":"4047 Ocean Heights Ave",
    "sg:city":"Egg Harbor Twp",
    "sg:classifiers":[
        {
            "category":"Local Transit",
            "type":"Transportation"
        }
    ],
    "sg:phone":"+1 609 601 9855",
    "sg:postcode":"08234",
    "sg:province":"NJ",
    "sg:tags":[
        "limousine"
    ],
    "wof:name":"Shamrock Limo",
    "wof:placetype":"venue"
},
  "geometry": {"coordinates":[-74.60069799999999,39.341049],"type":"Point"}
}