{
  "type": "Feature",
  "properties": {
    "addr:full":"1055 Parsippany Blvd Parsippany NJ 07054",
    "addr:housenumber":"1055",
    "addr:postcode":"07054",
    "addr:street":"Parsippany Blvd",
    "iso:country":"US",
    "sg:address":"1055 Parsippany Blvd",
    "sg:city":"Parsippany",
    "sg:classifiers":[
        {
            "category":"Insurance",
            "subcategory":"Insurance Agent",
            "type":"Services"
        }
    ],
    "sg:phone":"+1 973 316 8585",
    "sg:postcode":"07054",
    "sg:province":"NJ",
    "wof:name":"AFLAC",
    "wof:placetype":"venue"
},
  "geometry": {"coordinates":[-74.421369,40.870653],"type":"Point"}
}