{
  "type": "Feature",
  "properties": {
    "addr:full":"773 Summit Ave Jersey City NJ 07307",
    "addr:housenumber":"773",
    "addr:postcode":"07307",
    "addr:street":"Summit Ave",
    "iso:country":"US",
    "sg:address":"773 Summit Ave",
    "sg:city":"Jersey City",
    "sg:classifiers":[
        {
            "category":"Professional",
            "type":"Services"
        }
    ],
    "sg:phone":"+1 201 420 8003",
    "sg:postcode":"07307",
    "sg:province":"NJ",
    "sg:tags":[
        "establishment"
    ],
    "wof:name":"Prismz Colur Group",
    "wof:placetype":"venue"
},
  "geometry": {"coordinates":[-74.05752,40.739471],"type":"Point"}
}