{
  "type": "Feature",
  "properties": {
    "addr:full":"28 Brunswick Woods Dr East Brunswick NJ 08816",
    "addr:housenumber":"28",
    "addr:postcode":"08816",
    "addr:street":"Brunswick Woods Dr",
    "iso:country":"US",
    "sg:address":"28 Brunswick Woods Dr",
    "sg:city":"East Brunswick",
    "sg:classifiers":[
        {
            "category":"Wholesale",
            "subcategory":"Computers",
            "type":"Manufacturing & Wholesale Goods"
        },
        {
            "category":"Shopping",
            "subcategory":"Computers & Home Electronics",
            "type":"Retail Goods"
        }
    ],
    "sg:phone":"+1 732 568 1988",
    "sg:postcode":"08816",
    "sg:province":"NJ",
    "sg:tags":[
        "industrial",
        "network",
        "solution",
        "equipment",
        "distributor",
        "dealer"
    ],
    "wof:name":"Neteon Technologies Inc",
    "wof:placetype":"venue"
},
  "geometry": {"coordinates":[-74.39073399999999,40.420773],"type":"Point"}
}