{
  "type": "Feature",
  "properties": {
    "addr:full":"361 Speedwell Avenue Morris Plains NJ 07950",
    "addr:housenumber":"361",
    "addr:postcode":"07950",
    "addr:street":"Speedwell Avenue",
    "iso:country":"US",
    "sg:address":"361 Speedwell Avenue",
    "sg:city":"Morris Plains",
    "sg:classifiers":[
        {
            "category":"Professional",
            "type":"Services"
        },
        {
            "category":"Retail",
            "subcategory":"Event Space",
            "type":"Services"
        }
    ],
    "sg:phone":"+1 973 538 9000",
    "sg:postcode":"07950",
    "sg:province":"NJ",
    "sg:tags":[
        "venue",
        "caterer"
    ],
    "sg:website":"www.brettonwoods.net",
    "wof:name":"Bretton Woods Inn",
    "wof:placetype":"venue"
},
  "geometry": {"coordinates":[-74.48026,40.822926],"type":"Point"}
}