{
  "type": "Feature",
  "properties": {
    "addr:full":"7 Dalby Pl Middletown NJ 07748",
    "addr:housenumber":"7",
    "addr:postcode":"07748",
    "addr:street":"Dalby Pl",
    "iso:country":"US",
    "sg:address":"7 Dalby Pl",
    "sg:city":"Middletown",
    "sg:classifiers":[
        {
            "category":"Building & Trades",
            "subcategory":"Construction",
            "type":"Services"
        }
    ],
    "sg:phone":"+1 732 495 1390",
    "sg:postcode":"07748",
    "sg:province":"NJ",
    "sg:tags":[
        "hanging",
        "wallpaper",
        "contractor"
    ],
    "wof:name":"Cecere Wall Covering",
    "wof:placetype":"venue"
},
  "geometry": {"coordinates":[-74.121038,40.44093],"type":"Point"}
}