{
  "type": "Feature",
  "properties": {
    "addr:full":"1905 Kenyon Ave South Plainfield NJ 07080",
    "addr:housenumber":"1905",
    "addr:postcode":"07080",
    "addr:street":"Kenyon Ave",
    "iso:country":"US",
    "sg:address":"1905 Kenyon Ave",
    "sg:city":"South Plainfield",
    "sg:classifiers":[
        {
            "category":"Retail",
            "subcategory":"Repair Shop",
            "type":"Services"
        }
    ],
    "sg:phone":"+1   ",
    "sg:postcode":"07080",
    "sg:province":"NJ",
    "sg:tags":[
        "refrigeration",
        "s",
        "electrical"
    ],
    "wof:name":"Affordable Appliance Service",
    "wof:placetype":"venue"
},
  "geometry": {"coordinates":[-74.411466,40.592457],"type":"Point"}
}