{
  "type": "Feature",
  "properties": {
    "addr:full":"102 Lanza Ave Garfield NJ 07026",
    "addr:housenumber":"102",
    "addr:postcode":"07026",
    "addr:street":"Lanza Ave",
    "iso:country":"US",
    "sg:address":"102 Lanza Ave",
    "sg:city":"Garfield",
    "sg:classifiers":[
        {
            "category":"Freight",
            "type":"Transportation"
        }
    ],
    "sg:phone":"+1 973 772 3864",
    "sg:postcode":"07026",
    "sg:province":"NJ",
    "sg:tags":[
        "operator",
        "trucking"
    ],
    "wof:name":"T&M Transport LLC",
    "wof:placetype":"venue"
},
  "geometry": {"coordinates":[-74.122006,40.885962],"type":"Point"}
}