{
  "type": "Feature",
  "properties": {
    "addr:full":"463 S Orange Ave South Orange NJ 07079",
    "addr:housenumber":"463",
    "addr:postcode":"07079",
    "addr:street":"S Orange Ave",
    "iso:country":"US",
    "sg:address":"463 S Orange Ave",
    "sg:city":"South Orange",
    "sg:classifiers":[
        {
            "category":"Social Services",
            "type":"Services"
        }
    ],
    "sg:phone":"+1   ",
    "sg:postcode":"07079",
    "sg:province":"NJ",
    "wof:name":"Mars Venus Counseling Ctr",
    "wof:placetype":"venue"
},
  "geometry": {"coordinates":[-74.244603,40.745215],"type":"Point"}
}