{
  "type": "Feature",
  "properties": {
    "iso:country":"US",
    "sg:address":"125 W Saddle River Rd",
    "sg:city":"Saddle River",
    "sg:classifiers":[
        {
            "category":"Wholesale",
            "subcategory":"Electrical",
            "type":"Manufacturing & Wholesale Goods"
        }
    ],
    "sg:phone":"+1 201 327 8567",
    "sg:postcode":"07458",
    "sg:province":"NJ",
    "sg:tags":[
        "equipment"
    ],
    "wof:name":"Town & Country Lighting",
    "wof:placetype":"venue"
},
  "geometry": {"coordinates":[-74.10246100000001,41.028593],"type":"Point"}
}