{
  "type": "Feature",
  "properties": {
    "addr:full":"2421 West St Union City NJ 07087",
    "addr:housenumber":"2421",
    "addr:postcode":"07087",
    "addr:street":"West St",
    "iso:country":"US",
    "sg:address":"2421 West St",
    "sg:city":"Union City",
    "sg:classifiers":[
        {
            "category":"Restaurant",
            "type":"Food & Drink"
        }
    ],
    "sg:phone":"+1 201 866 5200",
    "sg:postcode":"07087",
    "sg:province":"NJ",
    "wof:name":"Las Estrellas De Mexico",
    "wof:placetype":"venue"
},
  "geometry": {"coordinates":[-74.033677,40.768226],"type":"Point"}
}