{
  "type": "Feature",
  "properties": {
    "addr:full":"53 Regan Ln Voorhees NJ 08043",
    "addr:housenumber":"53",
    "addr:postcode":"08043",
    "addr:street":"Regan Ln",
    "iso:country":"US",
    "sg:address":"53 Regan Ln",
    "sg:city":"Voorhees",
    "sg:classifiers":[
        {
            "category":"Shopping",
            "subcategory":"Clothing, Apparel, & Fashions",
            "type":"Retail Goods"
        }
    ],
    "sg:phone":"+1   ",
    "sg:postcode":"08043",
    "sg:province":"NJ",
    "wof:name":"Lagarto Clothing Co",
    "wof:placetype":"venue"
},
  "geometry": {"coordinates":[-74.946208,39.852232],"type":"Point"}
}