{
  "type": "Feature",
  "properties": {
    "addr:full":"26 Kearney St Bridgewater NJ 08807",
    "addr:housenumber":"26",
    "addr:postcode":"08807",
    "addr:street":"Kearney St",
    "iso:country":"US",
    "sg:address":"26 Kearney St",
    "sg:city":"Bridgewater",
    "sg:classifiers":[
        {
            "category":"Retail",
            "subcategory":"Auto Repair",
            "type":"Services"
        }
    ],
    "sg:phone":"+1 732 469 6210",
    "sg:postcode":"08807",
    "sg:province":"NJ",
    "sg:tags":[
        "repairing",
        "automobile"
    ],
    "sg:website":"www.motor-works.com",
    "wof:name":"Motorworks Inc",
    "wof:placetype":"venue"
},
  "geometry": {"coordinates":[-74.561538,40.563037],"type":"Point"}
}