{
  "type": "Feature",
  "properties": {
    "iso:country":"US",
    "sg:address":"542 Somerset St",
    "sg:city":"North Plainfield",
    "sg:classifiers":[
        {
            "category":"Autos & Motor Vehicles",
            "subcategory":"Automobile Sales",
            "type":"Retail Goods"
        }
    ],
    "sg:phone":"+1 908 753 6071",
    "sg:postcode":"07060",
    "sg:province":"NJ",
    "sg:tags":[
        "car",
        "dealer"
    ],
    "wof:name":"VIP Honda Honda Automobiles",
    "wof:placetype":"venue"
},
  "geometry": {"coordinates":[-74.436853,40.626437],"type":"Point"}
}