{
  "type": "Feature",
  "properties": {
    "addr:full":"30 Prospect St Lodi NJ 07644",
    "addr:housenumber":"30",
    "addr:postcode":"07644",
    "addr:street":"Prospect St",
    "iso:country":"US",
    "sg:address":"30 Prospect St",
    "sg:city":"Lodi",
    "sg:classifiers":[
        {
            "category":"Professional",
            "type":"Services"
        }
    ],
    "sg:phone":"+1   ",
    "sg:postcode":"07644",
    "sg:province":"NJ",
    "wof:name":"Potros Corporation",
    "wof:placetype":"venue"
},
  "geometry": {"coordinates":[-74.082639,40.874878],"type":"Point"}
}