{
  "type": "Feature",
  "properties": {
    "addr:full":"2418 Federal St Camden NJ 08105",
    "addr:housenumber":"2418",
    "addr:postcode":"08105",
    "addr:street":"Federal St",
    "iso:country":"US",
    "sg:address":"2418 Federal St",
    "sg:city":"Camden",
    "sg:classifiers":[
        {
            "category":"Professional",
            "subcategory":"Advertising",
            "type":"Services"
        }
    ],
    "sg:phone":"+1 856 691 0912",
    "sg:postcode":"08105",
    "sg:province":"NJ",
    "sg:tags":[
        "guide"
    ],
    "wof:name":"Baldy Bail Bonds",
    "wof:placetype":"venue"
},
  "geometry": {"coordinates":[-75.089826,39.945926],"type":"Point"}
}