{
  "type": "Feature",
  "properties": {
    "addr:full":"125 Clinton Rd Fairfield NJ 07004",
    "addr:housenumber":"125",
    "addr:postcode":"07004",
    "addr:street":"Clinton Rd",
    "iso:country":"US",
    "sg:address":"125 Clinton Rd",
    "sg:city":"Fairfield",
    "sg:classifiers":[
        {
            "category":"Professional",
            "type":"Services"
        }
    ],
    "sg:phone":"+1 973 575 7775",
    "sg:postcode":"07004",
    "sg:province":"NJ",
    "sg:tags":[
        "caterer"
    ],
    "wof:name":"Utopia Wedding and Event Center",
    "wof:placetype":"venue"
},
  "geometry": {"coordinates":[-74.31424699999999,40.865692],"type":"Point"}
}