{
  "type": "Feature",
  "properties": {
    "addr:full":"5 Mountain Ave North Plainfield NJ 07060",
    "addr:housenumber":"5",
    "addr:postcode":"07060",
    "addr:street":"Mountain Ave",
    "iso:country":"US",
    "sg:address":"5 Mountain Ave",
    "sg:city":"North Plainfield",
    "sg:classifiers":[
        {
            "category":"Real Estate",
            "subcategory":"Real Estate Services",
            "type":"Services"
        }
    ],
    "sg:phone":"+1 908 791 9970",
    "sg:postcode":"07060",
    "sg:province":"NJ",
    "sg:tags":[
        "company",
        "title"
    ],
    "wof:name":"Title Consulting Svc LLC",
    "wof:placetype":"venue"
},
  "geometry": {"coordinates":[-74.43267899999999,40.6259],"type":"Point"}
}