{
  "type": "Feature",
  "properties": {
    "iso:country":"US",
    "sg:address":"3107 Willowbrook Mall",
    "sg:city":"Little Falls",
    "sg:classifiers":[
        {
            "category":"Fast Food",
            "type":"Food & Drink"
        }
    ],
    "sg:phone":"+1 973 785 0841",
    "sg:postcode":"07424",
    "sg:province":"NJ",
    "sg:tags":[
        "burger"
    ],
    "sg:website":"www.wendys.com",
    "wof:name":"Wendy's",
    "wof:placetype":"venue"
},
  "geometry": {"coordinates":[-74.259817,40.890498],"type":"Point"}
}