{
  "type": "Feature",
  "properties": {
    "iso:country":"US",
    "sg:address":"39 Orchard St",
    "sg:city":"Dover",
    "sg:classifiers":[
        {
            "category":"Organizations",
            "subcategory":"Religious Organization",
            "type":"Services"
        }
    ],
    "sg:phone":"+1 973 361 7783",
    "sg:postcode":"07801",
    "sg:province":"NJ",
    "sg:tags":[
        "church"
    ],
    "wof:name":"Founders Baptist Church Dover",
    "wof:placetype":"venue"
},
  "geometry": {"coordinates":[-74.56044900000001,40.882029],"type":"Point"}
}