{
  "type": "Feature",
  "properties": {
    "addr:full":"319 E Jimmie Leeds Rd Absecon NJ 08205",
    "addr:housenumber":"319",
    "addr:postcode":"08205",
    "addr:street":"E Jimmie Leeds Rd",
    "iso:country":"US",
    "sg:address":"319 E Jimmie Leeds Rd",
    "sg:city":"Absecon",
    "sg:classifiers":[
        {
            "category":"Food & Beverages",
            "subcategory":"Groceries & Convenience Stores",
            "type":"Retail Goods"
        }
    ],
    "sg:phone":"+1 609 748 0009",
    "sg:postcode":"08205",
    "sg:province":"NJ",
    "sg:tags":[
        "grocer"
    ],
    "wof:name":"Pitney Italian Market",
    "wof:placetype":"venue"
},
  "geometry": {"coordinates":[-74.496314,39.464661],"type":"Point"}
}