{
  "type": "Feature",
  "properties": {
    "iso:country":"US",
    "sg:address":"103 Plum Dr",
    "sg:city":"Beverly",
    "sg:classifiers":[
        {
            "category":"Freight",
            "type":"Transportation"
        }
    ],
    "sg:phone":"+1 215 332 2883",
    "sg:postcode":"08010",
    "sg:province":"NJ",
    "sg:tags":[
        "haulage",
        "truck",
        "dump"
    ],
    "wof:name":"Real Transportation Inc",
    "wof:placetype":"venue"
},
  "geometry": {"coordinates":[-74.92215899999999,40.04211],"type":"Point"}
}