{
  "type": "Feature",
  "properties": {
    "addr:full":"2705 Morris Ave Union NJ 07083",
    "addr:housenumber":"2705",
    "addr:postcode":"07083",
    "addr:street":"Morris Ave",
    "iso:country":"US",
    "sg:address":"2705 Morris Ave",
    "sg:city":"Union",
    "sg:classifiers":[
        {
            "category":"Personal",
            "subcategory":"Beauty Salon",
            "type":"Services"
        }
    ],
    "sg:phone":"+1 908 964 8683",
    "sg:postcode":"07083",
    "sg:province":"NJ",
    "sg:tags":[
        "shop"
    ],
    "wof:name":"Style & Smile",
    "wof:placetype":"venue"
},
  "geometry": {"coordinates":[-74.295647,40.704977],"type":"Point"}
}