{
  "type": "Feature",
  "properties": {
    "addr:full":"5901 State Rte 42 Blackwood NJ 08012",
    "addr:housenumber":"5901",
    "addr:postcode":"08012",
    "addr:street":"State Rte 42",
    "iso:country":"US",
    "sg:address":"5901 State Rte 42",
    "sg:city":"Blackwood",
    "sg:classifiers":[
        {
            "category":"Sports & Exercise",
            "subcategory":"Gym",
            "type":"Entertainment"
        }
    ],
    "sg:phone":"+1 856 401 9688",
    "sg:postcode":"08012",
    "sg:province":"NJ",
    "sg:tags":[
        "fitness",
        "physical",
        "facility"
    ],
    "sg:website":"www.lafitness.com",
    "wof:name":"L A Fitness Sports Club",
    "wof:placetype":"venue"
},
  "geometry": {"coordinates":[-75.04851499999999,39.765029],"type":"Point"}
}