{
  "type": "Feature",
  "properties": {
    "addr:full":"263 Franklin Ave Wyckoff NJ 07481",
    "addr:housenumber":"263",
    "addr:postcode":"07481",
    "addr:street":"Franklin Ave",
    "iso:country":"US",
    "sg:address":"263 Franklin Ave",
    "sg:city":"Wyckoff",
    "sg:classifiers":[
        {
            "category":"Organizations",
            "subcategory":"Religious Organization",
            "type":"Services"
        }
    ],
    "sg:phone":"+1 201 891 1737",
    "sg:postcode":"07481",
    "sg:province":"NJ",
    "sg:tags":[
        "clergy"
    ],
    "wof:name":"Richard Perry",
    "wof:placetype":"venue"
},
  "geometry": {"coordinates":[-74.162273,41.011599],"type":"Point"}
}