{
  "type": "Feature",
  "properties": {
    "iso:country":"US",
    "sg:address":"185 W Madison Ave",
    "sg:city":"Dumont",
    "sg:classifiers":[
        {
            "category":"Organizations",
            "subcategory":"Religious Organization",
            "type":"Services"
        }
    ],
    "sg:phone":"+1 201 384 3630",
    "sg:postcode":"07628",
    "sg:province":"NJ",
    "sg:tags":[
        "church"
    ],
    "wof:name":"Calvary United Methodist",
    "wof:placetype":"venue"
},
  "geometry": {"coordinates":[-74.002562,40.940056],"type":"Point"}
}