{
  "type": "Feature",
  "properties": {
    "addr:full":"177 Bridge Plz N Fort Lee NJ 07024",
    "addr:housenumber":"177",
    "addr:postcode":"07024",
    "addr:street":"Bridge Plz N",
    "iso:country":"US",
    "sg:address":"177 Bridge Plz N",
    "sg:city":"Fort Lee",
    "sg:classifiers":[
        {
            "category":"Bars & Pubs",
            "type":"Food & Drink"
        }
    ],
    "sg:phone":"+1 201 592 6969",
    "sg:postcode":"07024",
    "sg:province":"NJ",
    "wof:name":"Siggy's",
    "wof:placetype":"venue"
},
  "geometry": {"coordinates":[-73.96749,40.855238],"type":"Point"}
}