{
  "type": "Feature",
  "properties": {
    "addr:full":"241 Clendenny Ave Jersey City NJ 07304",
    "addr:housenumber":"241",
    "addr:postcode":"07304",
    "addr:street":"Clendenny Ave",
    "iso:country":"US",
    "sg:address":"241 Clendenny Ave",
    "sg:city":"Jersey City",
    "sg:classifiers":[
        {
            "category":"Manufacturing",
            "subcategory":"Apparel",
            "type":"Manufacturing & Wholesale Goods"
        }
    ],
    "sg:phone":"+1 201 333 8485",
    "sg:postcode":"07304",
    "sg:province":"NJ",
    "sg:tags":[
        "textile",
        "manufacturer"
    ],
    "wof:name":"Hassan International",
    "wof:placetype":"venue"
},
  "geometry": {"coordinates":[-74.088509,40.721379],"type":"Point"}
}