{
  "type": "Feature",
  "properties": {
    "iso:country":"US",
    "sg:address":"150 Dawson Ave",
    "sg:city":"Clifton",
    "sg:classifiers":[
        {
            "category":"Building & Trades",
            "subcategory":"Construction",
            "type":"Services"
        }
    ],
    "sg:phone":"+1 973 614 1683",
    "sg:postcode":"07012",
    "sg:province":"NJ",
    "sg:tags":[
        "contractor"
    ],
    "wof:name":"R Wright Drywall Inc",
    "wof:placetype":"venue"
},
  "geometry": {"coordinates":[-74.150013,40.852668],"type":"Point"}
}