{
  "type": "Feature",
  "properties": {
    "addr:full":"142 Myrtle Ave Belford NJ 07740",
    "addr:housenumber":"142",
    "addr:postcode":"07740",
    "addr:street":"Myrtle Ave",
    "iso:country":"US",
    "sg:address":"142 Myrtle Ave",
    "sg:city":"Belford",
    "sg:classifiers":[
        {
            "category":"Farming",
            "subcategory":"Fish & Marine Products",
            "type":"Manufacturing & Wholesale Goods"
        }
    ],
    "sg:phone":"+1 732 787 2246",
    "sg:postcode":"07740",
    "sg:province":"NJ",
    "sg:tags":[
        "fishing"
    ],
    "wof:name":"Rule Fish Corp",
    "wof:placetype":"venue"
},
  "geometry": {"coordinates":[-74.00984,40.304211],"type":"Point"}
}