{
  "type": "Feature",
  "properties": {
    "addr:full":"47 Park Ave Rutherford NJ 07070",
    "addr:housenumber":"47",
    "addr:postcode":"07070",
    "addr:street":"Park Ave",
    "iso:country":"US",
    "sg:address":"47 Park Ave",
    "sg:city":"Rutherford",
    "sg:classifiers":[
        {
            "category":"Ice Cream",
            "type":"Food & Drink"
        }
    ],
    "sg:phone":"+1 201 406 1740",
    "sg:postcode":"07070",
    "sg:province":"NJ",
    "sg:tags":[
        "frozen",
        "yogurt"
    ],
    "wof:name":"Pazzo Gelato",
    "wof:placetype":"venue"
},
  "geometry": {"coordinates":[-74.103651,40.827389],"type":"Point"}
}