{
  "type": "Feature",
  "properties": {
    "addr:full":"14 Linden St Lodi NJ 07644",
    "addr:housenumber":"14",
    "addr:postcode":"07644",
    "addr:street":"Linden St",
    "iso:country":"US",
    "sg:address":"14 Linden St",
    "sg:city":"Lodi",
    "sg:classifiers":[
        {
            "category":"Professional",
            "subcategory":"Secretarial Services",
            "type":"Services"
        }
    ],
    "sg:phone":"+1   ",
    "sg:postcode":"07644",
    "sg:province":"NJ",
    "sg:tags":[
        "reporting"
    ],
    "wof:name":"Bebes Secretarial Service",
    "wof:placetype":"venue"
},
  "geometry": {"coordinates":[-74.083963,40.888107],"type":"Point"}
}