{
  "type": "Feature",
  "properties": {
    "addr:full":"22 Black Watch Trl Morristown NJ 07960",
    "addr:housenumber":"22",
    "addr:postcode":"07960",
    "addr:street":"Black Watch Trl",
    "iso:country":"US",
    "sg:address":"22 Black Watch Trl",
    "sg:city":"Morristown",
    "sg:classifiers":[
        {
            "category":"Organizations",
            "subcategory":"Religious Organization",
            "type":"Services"
        }
    ],
    "sg:phone":"+1 973 267 0911",
    "sg:postcode":"07960",
    "sg:province":"NJ",
    "wof:name":"Wolff E Rabbi",
    "wof:placetype":"venue"
},
  "geometry": {"coordinates":[-74.502403,40.806599],"type":"Point"}
}