{
  "type": "Feature",
  "properties": {
    "iso:country":"US",
    "sg:address":"116 S Warren St",
    "sg:city":"Trenton",
    "sg:classifiers":[
        {
            "category":"Personal",
            "subcategory":"Barber",
            "type":"Services"
        }
    ],
    "sg:phone":"+1   ",
    "sg:postcode":"08608",
    "sg:province":"NJ",
    "sg:tags":[
        "shop",
        "beauty"
    ],
    "wof:name":"State Barber Shop",
    "wof:placetype":"venue"
},
  "geometry": {"coordinates":[-74.76590299999999,40.218583],"type":"Point"}
}