{
  "type": "Feature",
  "properties": {
    "addr:full":"52 Coleman Ave Chatham NJ 07928",
    "addr:housenumber":"52",
    "addr:postcode":"07928",
    "addr:street":"Coleman Ave",
    "iso:country":"US",
    "sg:address":"52 Coleman Ave",
    "sg:city":"Chatham",
    "sg:classifiers":[
        {
            "category":"Real Estate",
            "subcategory":"Real Estate Agent",
            "type":"Services"
        }
    ],
    "sg:phone":"+1   ",
    "sg:postcode":"07928",
    "sg:province":"NJ",
    "wof:name":"Hillcrest Property Management",
    "wof:placetype":"venue"
},
  "geometry": {"coordinates":[-74.383562,40.746764],"type":"Point"}
}