{
  "type": "Feature",
  "properties": {
    "iso:country":"US",
    "sg:address":"4 Faber Rd",
    "sg:city":"Parsippany",
    "sg:classifiers":[
        {
            "category":"Professional",
            "subcategory":"Business Services",
            "type":"Services"
        }
    ],
    "sg:phone":"+1   ",
    "sg:postcode":"07054",
    "sg:province":"NJ",
    "wof:name":"AMR Healthcare Solutions",
    "wof:placetype":"venue"
},
  "geometry": {"coordinates":[-74.395549,40.845507],"type":"Point"}
}