{
  "type": "Feature",
  "properties": {
    "iso:country":"US",
    "sg:address":"1230 Parkway Ave",
    "sg:city":"Trenton",
    "sg:classifiers":[
        {
            "category":"Professional",
            "subcategory":"Lawyer & Legal Services",
            "type":"Services"
        }
    ],
    "sg:phone":"+1 609 771 8611",
    "sg:postcode":"08628",
    "sg:province":"NJ",
    "sg:tags":[
        "attorney"
    ],
    "wof:name":"Gaylord & Yuska Atty At Law",
    "wof:placetype":"venue"
},
  "geometry": {"coordinates":[-74.80184199999999,40.263508],"type":"Point"}
}