{
  "type": "Feature",
  "properties": {
    "addr:full":"15 US Hwy 9 Englishtown NJ 07726",
    "addr:housenumber":"15",
    "addr:postcode":"07726",
    "addr:street":"Us Hwy 9",
    "iso:country":"US",
    "sg:address":"15 US Hwy 9",
    "sg:city":"Englishtown",
    "sg:classifiers":[
        {
            "category":"Shopping",
            "subcategory":"Computers & Home Electronics",
            "type":"Retail Goods"
        }
    ],
    "sg:phone":"+1 732 761 8445",
    "sg:postcode":"07726",
    "sg:province":"NJ",
    "sg:tags":[
        "equipment",
        "dealer"
    ],
    "wof:name":"Best Buy",
    "wof:placetype":"venue"
},
  "geometry": {"coordinates":[-74.295384,40.28849],"type":"Point"}
}