{
  "type": "Feature",
  "properties": {
    "iso:country":"US",
    "sg:address":"627 N White Horse Pike",
    "sg:city":"Somerdale",
    "sg:classifiers":[
        {
            "category":"Shopping",
            "subcategory":"Hobbies, Toys, & Games",
            "type":"Retail Goods"
        }
    ],
    "sg:phone":"+1 856 783 1739",
    "sg:postcode":"08083",
    "sg:province":"NJ",
    "sg:tags":[
        "toy",
        "store"
    ],
    "wof:name":"P K Wholesale Toys",
    "wof:placetype":"venue"
},
  "geometry": {"coordinates":[-75.024399,39.851501],"type":"Point"}
}