{
  "type": "Feature",
  "properties": {
    "addr:full":"50 Pine St Montclair NJ 07042",
    "addr:housenumber":"50",
    "addr:postcode":"07042",
    "addr:street":"Pine St",
    "iso:country":"US",
    "sg:address":"50 Pine St",
    "sg:city":"Montclair",
    "sg:classifiers":[
        {
            "category":"Professional",
            "subcategory":"Computer Services",
            "type":"Services"
        }
    ],
    "sg:phone":"+1 201 920 4451",
    "sg:postcode":"07042",
    "sg:province":"NJ",
    "sg:tags":[
        "consulting"
    ],
    "wof:name":"Netcorrect Technologies",
    "wof:placetype":"venue"
},
  "geometry": {"coordinates":[-74.208906,40.810084],"type":"Point"}
}