{
  "type": "Feature",
  "properties": {
    "iso:country":"US",
    "sg:address":"71 Monroe St",
    "sg:city":"Hoboken",
    "sg:classifiers":[
        {
            "category":"Food & Beverages",
            "subcategory":"Liquor & Beverages",
            "type":"Retail Goods"
        }
    ],
    "sg:phone":"+1   ",
    "sg:postcode":"07030",
    "sg:province":"NJ",
    "sg:tags":[
        "drinking",
        "alcoholic"
    ],
    "wof:name":"Columbus House Wine & Lq Str",
    "wof:placetype":"venue"
},
  "geometry": {"coordinates":[-74.040226,40.738267],"type":"Point"}
}