{
  "type": "Feature",
  "properties": {
    "addr:full":"152 Momar Dr Ramsey NJ 07446",
    "addr:housenumber":"152",
    "addr:postcode":"07446",
    "addr:street":"Momar Dr",
    "iso:country":"US",
    "sg:address":"152 Momar Dr",
    "sg:city":"Ramsey",
    "sg:classifiers":[
        {
            "category":"Education",
            "subcategory":"Special Training",
            "type":"Public Place"
        }
    ],
    "sg:phone":"+1 201 934 4060",
    "sg:postcode":"07446",
    "sg:province":"NJ",
    "sg:tags":[
        "school",
        "instruction",
        "art"
    ],
    "wof:name":"Painting With Natalie",
    "wof:placetype":"venue"
},
  "geometry": {"coordinates":[-74.148786,41.046673],"type":"Point"}
}