{
  "type": "Feature",
  "properties": {
    "iso:country":"US",
    "sg:address":"1720 Bergenline Ave",
    "sg:city":"Union City",
    "sg:classifiers":[
        {
            "category":"Shopping",
            "subcategory":"Jewelry",
            "type":"Retail Goods"
        }
    ],
    "sg:phone":"+1 201 866 7473",
    "sg:postcode":"07087",
    "sg:province":"NJ",
    "sg:tags":[
        "jeweler"
    ],
    "wof:name":"Fernandez Jewelery",
    "wof:placetype":"venue"
},
  "geometry": {"coordinates":[-74.0354,40.7631],"type":"Point"}
}