{
  "type": "Feature",
  "properties": {
    "iso:country":"US",
    "sg:address":"2409 Nottingham Way",
    "sg:city":"Trenton",
    "sg:classifiers":[
        {
            "category":"Autos & Motor Vehicles",
            "subcategory":"Fuel & Gas Station",
            "type":"Retail Goods"
        }
    ],
    "sg:phone":"+1   ",
    "sg:postcode":"08619",
    "sg:province":"NJ",
    "sg:tags":[
        "station",
        "gasoline"
    ],
    "wof:name":"Somal Business",
    "wof:placetype":"venue"
},
  "geometry": {"coordinates":[-74.69752,40.233865],"type":"Point"}
}