{
  "type": "Feature",
  "properties": {
    "iso:country":"US",
    "sg:address":"402 Co Rd 519",
    "sg:city":"Phillipsburg",
    "sg:classifiers":[
        {
            "category":"Freight",
            "type":"Transportation"
        }
    ],
    "sg:phone":"+1 908 454 4272",
    "sg:postcode":"08865",
    "sg:province":"NJ",
    "sg:tags":[
        "over",
        "road",
        "trucking"
    ],
    "wof:name":"S M P Inc",
    "wof:placetype":"venue"
},
  "geometry": {"coordinates":[-75.157847,40.667732],"type":"Point"}
}