{
  "type": "Feature",
  "properties": {
    "iso:country":"US",
    "sg:address":"110 Rehill Ave",
    "sg:city":"Somerville",
    "sg:classifiers":[
        {
            "category":"Social Services",
            "subcategory":"Child Care",
            "type":"Services"
        }
    ],
    "sg:phone":"+1 908 685 2988",
    "sg:postcode":"08876",
    "sg:province":"NJ",
    "sg:tags":[
        "day"
    ],
    "wof:name":"Sunshine Ste Sick Child Dycare",
    "wof:placetype":"venue"
},
  "geometry": {"coordinates":[-74.595979,40.567603],"type":"Point"}
}