{
  "type": "Feature",
  "properties": {
    "addr:full":"65 Railroad Ave Ridgefield Park NJ 07660",
    "addr:housenumber":"65",
    "addr:postcode":"07660",
    "addr:street":"Railroad",
    "iso:country":"US",
    "sg:address":"65 Railroad Ave",
    "sg:city":"Ridgefield Park",
    "sg:classifiers":[
        {
            "category":"Building & Trades",
            "subcategory":"Construction",
            "type":"Services"
        }
    ],
    "sg:phone":"+1 201 440 3596",
    "sg:postcode":"07660",
    "sg:province":"NJ",
    "sg:tags":[
        "contractor"
    ],
    "wof:name":"Vercelli Construction Inc",
    "wof:placetype":"venue"
},
  "geometry": {"coordinates":[-74.02939499999999,40.860349],"type":"Point"}
}