{
  "type": "Feature",
  "properties": {
    "iso:country":"US",
    "sg:address":"42 School St",
    "sg:city":"Clark",
    "sg:classifiers":[
        {
            "category":"Retail",
            "subcategory":"Auto Repair",
            "type":"Services"
        }
    ],
    "sg:phone":"+1   ",
    "sg:postcode":"07066",
    "sg:province":"NJ",
    "sg:tags":[
        "general"
    ],
    "wof:name":"Al Auto & Truck Repair",
    "wof:placetype":"venue"
},
  "geometry": {"coordinates":[-74.30832700000001,40.629337],"type":"Point"}
}