{
  "type": "Feature",
  "properties": {
    "addr:full":"191 Mill Creek Rd Bayville NJ 08721",
    "addr:housenumber":"191",
    "addr:postcode":"08721",
    "addr:street":"Mill Creek Rd",
    "iso:country":"US",
    "sg:address":"191 Mill Creek Rd",
    "sg:city":"Bayville",
    "sg:classifiers":[
        {
            "category":"Professional",
            "subcategory":"Management & Consulting",
            "type":"Services"
        }
    ],
    "sg:phone":"+1   ",
    "sg:postcode":"08721",
    "sg:province":"NJ",
    "wof:name":"Ocean UCP Housing",
    "wof:placetype":"venue"
},
  "geometry": {"coordinates":[-74.153792,39.921674],"type":"Point"}
}