{
  "type": "Feature",
  "properties": {
    "addr:full":"2 Mercer St Lodi NJ 07644",
    "addr:housenumber":"2",
    "addr:postcode":"07644",
    "addr:street":"Mercer St",
    "iso:country":"US",
    "sg:address":"2 Mercer St",
    "sg:city":"Lodi",
    "sg:classifiers":[
        {
            "category":"Professional",
            "type":"Services"
        }
    ],
    "sg:phone":"+1   ",
    "sg:postcode":"07644",
    "sg:province":"NJ",
    "wof:name":"Bomgos",
    "wof:placetype":"venue"
},
  "geometry": {"coordinates":[-74.086704,40.876902],"type":"Point"}
}