{
  "type": "Feature",
  "properties": {
    "iso:country":"US",
    "sg:address":"727 Beach Dr",
    "sg:city":"Cape May",
    "sg:classifiers":[
        {
            "category":"Shopping",
            "type":"Retail Goods"
        }
    ],
    "sg:phone":"+1 609 898 1889",
    "sg:postcode":"08204",
    "sg:province":"NJ",
    "sg:tags":[
        "art",
        "gallery",
        "dealer"
    ],
    "wof:name":"Sue Walden Photography",
    "wof:placetype":"venue"
},
  "geometry": {"coordinates":[-74.91655900000001,38.930804],"type":"Point"}
}