{
  "type": "Feature",
  "properties": {
    "iso:country":"US",
    "sg:address":"633 Morris Ave",
    "sg:city":"Springfield",
    "sg:classifiers":[
        {
            "category":"Professional",
            "subcategory":"Lawyer & Legal Services",
            "type":"Services"
        }
    ],
    "sg:phone":"+1 973 564 9252",
    "sg:postcode":"07081",
    "sg:province":"NJ",
    "wof:name":"Rubin & Rothman",
    "wof:placetype":"venue"
},
  "geometry": {"coordinates":[-74.32975999999999,40.717651],"type":"Point"}
}