{
  "type": "Feature",
  "properties": {
    "iso:country":"US",
    "sg:address":"41 State Rte 12",
    "sg:city":"Flemington",
    "sg:classifiers":[
        {
            "category":"Restaurant",
            "type":"Food & Drink"
        }
    ],
    "sg:phone":"+1 908 806 2125",
    "sg:postcode":"08822",
    "sg:province":"NJ",
    "wof:name":"China Buffet",
    "wof:placetype":"venue"
},
  "geometry": {"coordinates":[-74.860899,40.501657],"type":"Point"}
}