{
  "type": "Feature",
  "properties": {
    "iso:country":"US",
    "sg:address":"51 New England Ave",
    "sg:city":"Piscataway",
    "sg:classifiers":[
        {
            "category":"Shopping",
            "subcategory":"Clothing, Apparel, & Fashions",
            "type":"Retail Goods"
        }
    ],
    "sg:phone":"+1   ",
    "sg:postcode":"08854",
    "sg:province":"NJ",
    "wof:name":"New Jersey F S 120",
    "wof:placetype":"venue"
},
  "geometry": {"coordinates":[-74.46745199999999,40.552321],"type":"Point"}
}