{
  "type": "Feature",
  "properties": {
    "iso:country":"US",
    "sg:address":"11 Chambers St",
    "sg:city":"Princeton",
    "sg:classifiers":[
        {
            "category":"Restaurant",
            "type":"Food & Drink"
        }
    ],
    "sg:phone":"+1 609 252 1158",
    "sg:postcode":"08542",
    "sg:province":"NJ",
    "sg:tags":[
        "asian",
        "pan",
        "japanese"
    ],
    "wof:name":"Ajihei",
    "wof:placetype":"venue"
},
  "geometry": {"coordinates":[-74.662595,40.349263],"type":"Point"}
}