{
  "type": "Feature",
  "properties": {
    "addr:full":"1379 Morris Ave Union NJ 07083",
    "addr:housenumber":"1379",
    "addr:postcode":"07083",
    "addr:street":"Morris Ave",
    "iso:country":"US",
    "sg:address":"1379 Morris Ave",
    "sg:city":"Union",
    "sg:classifiers":[
        {
            "category":"Professional",
            "subcategory":"Lawyer & Legal Services",
            "type":"Services"
        }
    ],
    "sg:phone":"+1 908 964 8310",
    "sg:postcode":"07083",
    "sg:province":"NJ",
    "sg:tags":[
        "attorney"
    ],
    "wof:name":"Jeffrey M Gechtman",
    "wof:placetype":"venue"
},
  "geometry": {"coordinates":[-74.245296,40.688617],"type":"Point"}
}