{
  "type": "Feature",
  "properties": {
    "addr:full":"14 Fairmount Ave Chatham NJ 07928",
    "addr:housenumber":"14",
    "addr:postcode":"07928",
    "addr:street":"Fairmount Ave",
    "iso:country":"US",
    "sg:address":"14 Fairmount Ave",
    "sg:city":"Chatham",
    "sg:classifiers":[
        {
            "category":"Real Estate",
            "subcategory":"Real Estate Agent",
            "type":"Services"
        }
    ],
    "sg:phone":"+1 973 635 4488",
    "sg:postcode":"07928",
    "sg:province":"NJ",
    "wof:name":"Stronoway Co",
    "wof:placetype":"venue"
},
  "geometry": {"coordinates":[-74.383426,40.740874],"type":"Point"}
}