{
  "type": "Feature",
  "properties": {
    "addr:full":"334 Union Ave Rutherford NJ 07070",
    "addr:housenumber":"334",
    "addr:postcode":"07070",
    "addr:street":"Union Ave",
    "iso:country":"US",
    "sg:address":"334 Union Ave",
    "sg:city":"Rutherford",
    "sg:classifiers":[
        {
            "category":"Restaurant",
            "type":"Food & Drink"
        }
    ],
    "sg:phone":"+1 201 933 8766",
    "sg:postcode":"07070",
    "sg:province":"NJ",
    "wof:name":"Chop Sticks",
    "wof:placetype":"venue"
},
  "geometry": {"coordinates":[-74.11512999999999,40.837095],"type":"Point"}
}