{
  "type": "Feature",
  "properties": {
    "iso:country":"US",
    "sg:address":"1283 State Rte 27",
    "sg:city":"Somerset",
    "sg:classifiers":[
        {
            "category":"Organizations",
            "subcategory":"Religious Organization",
            "type":"Services"
        }
    ],
    "sg:phone":"+1 732 545 8833",
    "sg:postcode":"08873",
    "sg:province":"NJ",
    "wof:name":"Muslim Women Coalition",
    "wof:placetype":"venue"
},
  "geometry": {"coordinates":[-74.491286,40.472878],"type":"Point"}
}