{
  "type": "Feature",
  "properties": {
    "iso:country":"US",
    "sg:address":"468 Industrial Way W",
    "sg:city":"Eatontown",
    "sg:classifiers":[
        {
            "category":"Banks & Credit Unions",
            "subcategory":"Bank",
            "type":"Services"
        }
    ],
    "sg:phone":"+1 732 380 3600",
    "sg:postcode":"07724",
    "sg:province":"NJ",
    "sg:tags":[
        "federal"
    ],
    "wof:name":"First Atlantic Federal Cr Un",
    "wof:placetype":"venue"
},
  "geometry": {"coordinates":[-74.05637,40.275623],"type":"Point"}
}