{
  "type": "Feature",
  "properties": {
    "addr:full":"37 Hart St Hazlet NJ 07734",
    "addr:housenumber":"37",
    "addr:postcode":"07734",
    "addr:street":"Hart St",
    "iso:country":"US",
    "sg:address":"37 Hart St",
    "sg:city":"Hazlet",
    "sg:classifiers":[
        {
            "category":"Building & Trades",
            "subcategory":"Electrical",
            "type":"Services"
        }
    ],
    "sg:phone":"+1 732 495 9167",
    "sg:postcode":"07734",
    "sg:province":"NJ",
    "sg:tags":[
        "house",
        "electrical",
        "electric",
        "contractor"
    ],
    "wof:name":"Martins Electrical Contractors",
    "wof:placetype":"venue"
},
  "geometry": {"coordinates":[-74.133194,40.434071],"type":"Point"}
}