{
  "type": "Feature",
  "properties": {
    "iso:country":"US",
    "sg:address":"1315 Barnegat Ave",
    "sg:city":"Beach Haven",
    "sg:classifiers":[
        {
            "category":"Restaurant",
            "type":"Food & Drink"
        }
    ],
    "sg:phone":"+1   ",
    "sg:postcode":"08008",
    "sg:province":"NJ",
    "sg:tags":[
        "eating"
    ],
    "wof:name":"Debut Restaurant Consulting",
    "wof:placetype":"venue"
},
  "geometry": {"coordinates":[-74.182669,39.648674],"type":"Point"}
}