{
  "type": "Feature",
  "properties": {
    "iso:country":"US",
    "sg:address":"102 S Pelham Ave",
    "sg:city":"Longport",
    "sg:classifiers":[
        {
            "category":"Health Services",
            "subcategory":"Doctor",
            "type":"Services"
        }
    ],
    "sg:phone":"+1 609 823 7104",
    "sg:postcode":"08403",
    "sg:province":"NJ",
    "sg:tags":[
        "medical"
    ],
    "wof:name":"H Moheimani MD",
    "wof:placetype":"venue"
},
  "geometry": {"coordinates":[-74.52243799999999,39.313743],"type":"Point"}
}