{
  "type": "Feature",
  "properties": {
    "addr:full":"252 N 1st St Beach Haven NJ 08008",
    "addr:housenumber":"252",
    "addr:postcode":"08008",
    "addr:street":"N 1St St",
    "iso:country":"US",
    "sg:address":"252 N 1st St",
    "sg:city":"Beach Haven",
    "sg:classifiers":[
        {
            "category":"Restaurant",
            "type":"Food & Drink"
        }
    ],
    "sg:phone":"+1   ",
    "sg:postcode":"08008",
    "sg:province":"NJ",
    "sg:tags":[
        "eating"
    ],
    "wof:name":"Island Catering LLC",
    "wof:placetype":"venue"
},
  "geometry": {"coordinates":[-74.174781,39.657045],"type":"Point"}
}