{
  "type": "Feature",
  "properties": {
    "addr:full":"48 N Broadway Pennsville NJ 08070",
    "addr:housenumber":"48",
    "addr:postcode":"08070",
    "addr:street":"N Broadway",
    "iso:country":"US",
    "sg:address":"48 N Broadway",
    "sg:city":"Pennsville",
    "sg:classifiers":[
        {
            "category":"Health Services",
            "subcategory":"Doctor",
            "type":"Services"
        }
    ],
    "sg:phone":"+1 856 678 5252",
    "sg:postcode":"08070",
    "sg:province":"NJ",
    "sg:tags":[
        "physician",
        "surgeon",
        "osteopathic"
    ],
    "wof:name":"Daniel Shufler MD",
    "wof:placetype":"venue"
},
  "geometry": {"coordinates":[-75.51800900000001,39.657449],"type":"Point"}
}