{
  "type": "Feature",
  "properties": {
    "addr:full":"155 Sinvalco Rd Secaucus NJ 07094",
    "addr:housenumber":"155",
    "addr:postcode":"07094",
    "addr:street":"Sinvalco Rd",
    "iso:country":"US",
    "sg:address":"155 Sinvalco Rd",
    "sg:city":"Secaucus",
    "sg:classifiers":[
        {
            "category":"Shopping",
            "type":"Retail Goods"
        },
        {
            "category":"Home & Garden",
            "subcategory":"Home Furnishings",
            "type":"Retail Goods"
        }
    ],
    "sg:phone":"+1 201 867 0944",
    "sg:postcode":"07094",
    "sg:province":"NJ",
    "sg:tags":[
        "factory",
        "outlet"
    ],
    "wof:name":"Mikasa Lifestyle Factory Store",
    "wof:placetype":"venue"
},
  "geometry": {"coordinates":[-74.064691,40.780086],"type":"Point"}
}