{
  "type": "Feature",
  "properties": {
    "iso:country":"US",
    "sg:address":"207 2nd St",
    "sg:city":"Lakewood",
    "sg:classifiers":[
        {
            "category":"Manufacturing",
            "subcategory":"Textiles",
            "type":"Manufacturing & Wholesale Goods"
        }
    ],
    "sg:phone":"+1 732 367 1707",
    "sg:postcode":"08701",
    "sg:province":"NJ",
    "sg:tags":[
        "hosiery"
    ],
    "sg:website":"www.babyjay.com",
    "wof:name":"Growing Feet",
    "wof:placetype":"venue"
},
  "geometry": {"coordinates":[-74.21231400000001,40.09246],"type":"Point"}
}