{
  "type": "Feature",
  "properties": {
    "addr:full":"1622 Lakewood Rd Toms River NJ 08755",
    "addr:housenumber":"1622",
    "addr:postcode":"08755",
    "addr:street":"Lakewood Rd",
    "iso:country":"US",
    "sg:address":"1622 Lakewood Rd",
    "sg:city":"Toms River",
    "sg:classifiers":[
        {
            "category":"Professional",
            "type":"Services"
        }
    ],
    "sg:phone":"+1   ",
    "sg:postcode":"08755",
    "sg:province":"NJ",
    "wof:name":"Johnson Gary",
    "wof:placetype":"venue"
},
  "geometry": {"coordinates":[-74.215734,40.008895],"type":"Point"}
}