{
  "type": "Feature",
  "properties": {
    "iso:country":"US",
    "sg:address":"320 14th St",
    "sg:city":"Union City",
    "sg:classifiers":[
        {
            "category":"Building & Trades",
            "subcategory":"Construction",
            "type":"Services"
        }
    ],
    "sg:phone":"+1 201 852 0876",
    "sg:postcode":"07087",
    "sg:province":"NJ",
    "sg:tags":[
        "industrial"
    ],
    "wof:name":"Guzman General Construction",
    "wof:placetype":"venue"
},
  "geometry": {"coordinates":[-74.03518699999999,40.760469],"type":"Point"}
}