{
  "type": "Feature",
  "properties": {
    "addr:full":"40 Vernon Ave Somerset NJ 08873",
    "addr:housenumber":"40",
    "addr:postcode":"08873",
    "addr:street":"Vernon Ave",
    "iso:country":"US",
    "sg:address":"40 Vernon Ave",
    "sg:city":"Somerset",
    "sg:classifiers":[
        {
            "category":"Professional",
            "subcategory":"Art Services",
            "type":"Services"
        }
    ],
    "sg:phone":"+1   ",
    "sg:postcode":"08873",
    "sg:province":"NJ",
    "sg:tags":[
        "photography"
    ],
    "wof:name":"Expressions Portrait Studio",
    "wof:placetype":"venue"
},
  "geometry": {"coordinates":[-74.47543400000001,40.500824],"type":"Point"}
}