{
  "type": "Feature",
  "properties": {
    "addr:full":"108 Hobart St Hackensack NJ 07601",
    "addr:housenumber":"108",
    "addr:postcode":"07601",
    "addr:street":"Hobart St",
    "iso:country":"US",
    "sg:address":"108 Hobart St",
    "sg:city":"Hackensack",
    "sg:classifiers":[
        {
            "category":"Wholesale",
            "subcategory":"Apparel",
            "type":"Manufacturing & Wholesale Goods"
        }
    ],
    "sg:phone":"+1 201 678 0011",
    "sg:postcode":"07601",
    "sg:province":"NJ",
    "sg:tags":[
        "import",
        "hat"
    ],
    "wof:name":"Topwear International Inc",
    "wof:placetype":"venue"
},
  "geometry": {"coordinates":[-74.050543,40.875859],"type":"Point"}
}