{
  "type": "Feature",
  "properties": {
    "addr:full":"261 Clinton Ave Jersey City NJ 07304",
    "addr:housenumber":"261",
    "addr:postcode":"07304",
    "addr:street":"Clinton Ave",
    "iso:country":"US",
    "sg:address":"261 Clinton Ave",
    "sg:city":"Jersey City",
    "sg:classifiers":[
        {
            "category":"Professional",
            "type":"Services"
        }
    ],
    "sg:phone":"+1   ",
    "sg:postcode":"07304",
    "sg:province":"NJ",
    "wof:name":"Marcel F Aime",
    "wof:placetype":"venue"
},
  "geometry": {"coordinates":[-74.079396,40.719061],"type":"Point"}
}