{
  "type": "Feature",
  "properties": {
    "iso:country":"US",
    "sg:address":"421 Mountain Blvd",
    "sg:city":"Watchung",
    "sg:classifiers":[
        {
            "category":"Building & Trades",
            "subcategory":"Landscaping Services",
            "type":"Services"
        }
    ],
    "sg:phone":"+1 908 561 6310",
    "sg:postcode":"07069",
    "sg:province":"NJ",
    "wof:name":"Prominent Landscaping",
    "wof:placetype":"venue"
},
  "geometry": {"coordinates":[-74.46695699999999,40.627607],"type":"Point"}
}