{
  "type": "Feature",
  "properties": {
    "iso:country":"US",
    "sg:address":"206 Homestead Rd",
    "sg:city":"Brielle",
    "sg:classifiers":[
        {
            "category":"Building & Trades",
            "subcategory":"Construction",
            "type":"Services"
        }
    ],
    "sg:phone":"+1 732 528 4656",
    "sg:postcode":"08730",
    "sg:province":"NJ",
    "sg:tags":[
        "contractor"
    ],
    "wof:name":"Homestead Contractors Corp",
    "wof:placetype":"venue"
},
  "geometry": {"coordinates":[-74.051737,40.10813],"type":"Point"}
}