{
  "type": "Feature",
  "properties": {
    "addr:full":"182 Smith St Perth Amboy NJ 08861",
    "addr:housenumber":"182",
    "addr:postcode":"08861",
    "addr:street":"Smith St",
    "iso:country":"US",
    "sg:address":"182 Smith St",
    "sg:city":"Perth Amboy",
    "sg:classifiers":[
        {
            "category":"Shopping",
            "subcategory":"Mobile Phones",
            "type":"Retail Goods"
        }
    ],
    "sg:phone":"+1 732 293 0220",
    "sg:postcode":"08861",
    "sg:province":"NJ",
    "wof:name":"T-Mobile",
    "wof:placetype":"venue"
},
  "geometry": {"coordinates":[-74.27058700000001,40.509361],"type":"Point"}
}