{
  "type": "Feature",
  "properties": {
    "addr:full":"17 W Browning Rd Bellmawr NJ 08031",
    "addr:housenumber":"17",
    "addr:postcode":"08031",
    "addr:street":"W Browning Rd",
    "iso:country":"US",
    "sg:address":"17 W Browning Rd",
    "sg:city":"Bellmawr",
    "sg:classifiers":[
        {
            "category":"Building & Trades",
            "subcategory":"Construction",
            "type":"Services"
        }
    ],
    "sg:phone":"+1 856 278 5989",
    "sg:postcode":"08031",
    "sg:province":"NJ",
    "sg:tags":[
        "painter",
        "contractor"
    ],
    "wof:name":"Design Paint Paper",
    "wof:placetype":"venue"
},
  "geometry": {"coordinates":[-75.08040200000001,39.866579],"type":"Point"}
}