{
  "type": "Feature",
  "properties": {
    "iso:country":"US",
    "sg:address":"2 Conestoga Trl",
    "sg:city":"Sparta",
    "sg:classifiers":[
        {
            "category":"Shopping",
            "subcategory":"Florist",
            "type":"Retail Goods"
        }
    ],
    "sg:phone":"+1 973 729 5300",
    "sg:postcode":"07871",
    "sg:province":"NJ",
    "wof:name":"Redshaw's Flower Shop",
    "wof:placetype":"venue"
},
  "geometry": {"coordinates":[-74.630061,41.020835],"type":"Point"}
}