{
  "type": "Feature",
  "properties": {
    "addr:full":"38 Main St High Bridge NJ 08829",
    "addr:housenumber":"38",
    "addr:postcode":"08829",
    "addr:street":"Main St",
    "iso:country":"US",
    "sg:address":"38 Main St",
    "sg:city":"High Bridge",
    "sg:classifiers":[
        {
            "category":"Shopping",
            "subcategory":"Hobbies, Toys, & Games",
            "type":"Retail Goods"
        }
    ],
    "sg:phone":"+1   ",
    "sg:postcode":"08829",
    "sg:province":"NJ",
    "wof:name":"Cherished Friends Too",
    "wof:placetype":"venue"
},
  "geometry": {"coordinates":[-74.895584,40.668818],"type":"Point"}
}