{
  "type": "Feature",
  "properties": {
    "addr:full":"183 Ballantine Pkwy Newark NJ 07104",
    "addr:housenumber":"183",
    "addr:postcode":"07104",
    "addr:street":"Ballantine Pkwy",
    "iso:country":"US",
    "sg:address":"183 Ballantine Pkwy",
    "sg:city":"Newark",
    "sg:classifiers":[
        {
            "category":"Health Services",
            "subcategory":"Nursing And Care Facility",
            "type":"Services"
        }
    ],
    "sg:phone":"+1 973 485 9752",
    "sg:postcode":"07104",
    "sg:province":"NJ",
    "sg:tags":[
        "home",
        "retirement"
    ],
    "wof:name":"Serenity House",
    "wof:placetype":"venue"
},
  "geometry": {"coordinates":[-74.169197,40.769699],"type":"Point"}
}