{
  "type": "Feature",
  "properties": {
    "iso:country":"US",
    "sg:address":"23 Ferncliff Ter",
    "sg:city":"Short Hills",
    "sg:classifiers":[
        {
            "category":"Professional",
            "subcategory":"Management & Consulting",
            "type":"Services"
        }
    ],
    "sg:phone":"+1 973 273 1368",
    "sg:postcode":"07078",
    "sg:province":"NJ",
    "sg:tags":[
        "conference",
        "consultant",
        "meeting"
    ],
    "wof:name":"Coghan & Fuller",
    "wof:placetype":"venue"
},
  "geometry": {"coordinates":[-74.323639,40.722405],"type":"Point"}
}