{
  "type": "Feature",
  "properties": {
    "iso:country":"US",
    "sg:address":"734 Morgan St",
    "sg:city":"Camden",
    "sg:classifiers":[
        {
            "category":"Personal",
            "subcategory":"Barber",
            "type":"Services"
        }
    ],
    "sg:phone":"+1 856 541 0044",
    "sg:postcode":"08104",
    "sg:province":"NJ",
    "wof:name":"Expressions",
    "wof:placetype":"venue"
},
  "geometry": {"coordinates":[-75.11302999999999,39.912452],"type":"Point"}
}