{
  "type": "Feature",
  "properties": {
    "addr:full":"18 Mill Run W Hightstown NJ 08520",
    "addr:housenumber":"18",
    "addr:postcode":"08520",
    "addr:street":"Mill Run W",
    "iso:country":"US",
    "sg:address":"18 Mill Run W",
    "sg:city":"Hightstown",
    "sg:classifiers":[
        {
            "category":"Professional",
            "subcategory":"Computer Services",
            "type":"Services"
        }
    ],
    "sg:phone":"+1   ",
    "sg:postcode":"08520",
    "sg:province":"NJ",
    "sg:tags":[
        "related"
    ],
    "wof:name":"Ajg Consultants Service Inc",
    "wof:placetype":"venue"
},
  "geometry": {"coordinates":[-74.517816,40.275887],"type":"Point"}
}