{
  "type": "Feature",
  "properties": {
    "iso:country":"US",
    "sg:address":"410 Monmouth Ave",
    "sg:city":"Lakewood",
    "sg:classifiers":[
        {
            "category":"Food & Beverages",
            "subcategory":"Groceries & Convenience Stores",
            "type":"Retail Goods"
        }
    ],
    "sg:phone":"+1   ",
    "sg:postcode":"08701",
    "sg:province":"NJ",
    "wof:name":"Center Deli Food Market",
    "wof:placetype":"venue"
},
  "geometry": {"coordinates":[-74.210808,40.095435],"type":"Point"}
}