{
  "type": "Feature",
  "properties": {
    "addr:full":"2459 Terrill Rd Union NJ 07083",
    "addr:housenumber":"2459",
    "addr:postcode":"07083",
    "addr:street":"Terrill Rd",
    "iso:country":"US",
    "sg:address":"2459 Terrill Rd",
    "sg:city":"Union",
    "sg:classifiers":[
        {
            "category":"Real Estate",
            "subcategory":"Real Estate Agent",
            "type":"Services"
        }
    ],
    "sg:phone":"+1   ",
    "sg:postcode":"07083",
    "sg:province":"NJ",
    "wof:name":"Ctc Realty Group",
    "wof:placetype":"venue"
},
  "geometry": {"coordinates":[-74.293633,40.697067],"type":"Point"}
}