{
  "type": "Feature",
  "properties": {
    "addr:full":"230 Livingston St Northvale NJ 07647",
    "addr:housenumber":"230",
    "addr:postcode":"07647",
    "addr:street":"Livingston St",
    "iso:country":"US",
    "sg:address":"230 Livingston St",
    "sg:city":"Northvale",
    "sg:classifiers":[
        {
            "category":"Manufacturing",
            "subcategory":"Printing",
            "type":"Manufacturing & Wholesale Goods"
        }
    ],
    "sg:phone":"+1 201 767 4093",
    "sg:postcode":"07647",
    "sg:province":"NJ",
    "sg:tags":[
        "publisher",
        "book"
    ],
    "wof:name":"Psychotherapy Book Club",
    "wof:placetype":"venue"
},
  "geometry": {"coordinates":[-73.94717799999999,41.010149],"type":"Point"}
}