{
  "type": "Feature",
  "properties": {
    "addr:full":"2 Marshall Dr Flemington NJ 08822",
    "addr:housenumber":"2",
    "addr:postcode":"08822",
    "addr:street":"Marshall Dr",
    "iso:country":"US",
    "sg:address":"2 Marshall Dr",
    "sg:city":"Flemington",
    "sg:classifiers":[
        {
            "category":"Wholesale",
            "subcategory":"Electrical",
            "type":"Manufacturing & Wholesale Goods"
        }
    ],
    "sg:phone":"+1 908 788 9605",
    "sg:postcode":"08822",
    "sg:province":"NJ",
    "sg:tags":[
        "alarm",
        "burglar",
        "system"
    ],
    "sg:website":"www.wire-x.com",
    "wof:name":"Wire Excellence",
    "wof:placetype":"venue"
},
  "geometry": {"coordinates":[-74.825791,40.50523],"type":"Point"}
}