{
  "type": "Feature",
  "properties": {
    "addr:full":"18 W Cedar St Livingston NJ 07039",
    "addr:housenumber":"18",
    "addr:postcode":"07039",
    "addr:street":"W Cedar St",
    "iso:country":"US",
    "sg:address":"18 W Cedar St",
    "sg:city":"Livingston",
    "sg:classifiers":[
        {
            "category":"Retail",
            "subcategory":"Auto Repair",
            "type":"Services"
        }
    ],
    "sg:phone":"+1 973 992 5669",
    "sg:postcode":"07039",
    "sg:province":"NJ",
    "sg:tags":[
        "general"
    ],
    "wof:name":"Pomeroys Garage Rear",
    "wof:placetype":"venue"
},
  "geometry": {"coordinates":[-74.316885,40.790824],"type":"Point"}
}