{
  "type": "Feature",
  "properties": {
    "iso:country":"US",
    "sg:address":"128 Mallory Ave",
    "sg:city":"Jersey City",
    "sg:classifiers":[
        {
            "category":"Shopping",
            "subcategory":"Gifts & Souvenirs",
            "type":"Retail Goods"
        }
    ],
    "sg:phone":"+1   ",
    "sg:postcode":"07304",
    "sg:province":"NJ",
    "wof:name":"Dugout",
    "wof:placetype":"venue"
},
  "geometry": {"coordinates":[-74.08923,40.718117],"type":"Point"}
}