{
  "type": "Feature",
  "properties": {
    "addr:full":"167 2nd St Keyport NJ 07735",
    "addr:housenumber":"167",
    "addr:postcode":"07735",
    "addr:street":"2Nd St",
    "iso:country":"US",
    "sg:address":"167 2nd St",
    "sg:city":"Keyport",
    "sg:classifiers":[
        {
            "category":"Autos & Motor Vehicles",
            "subcategory":"Automobile Sales",
            "type":"Retail Goods"
        }
    ],
    "sg:phone":"+1   ",
    "sg:postcode":"07735",
    "sg:province":"NJ",
    "wof:name":"Cadillac Construction",
    "wof:placetype":"venue"
},
  "geometry": {"coordinates":[-74.193502,40.43836],"type":"Point"}
}