{
  "type": "Feature",
  "properties": {
    "iso:country":"US",
    "sg:address":"2016 State Rte 88",
    "sg:city":"Brick",
    "sg:classifiers":[
        {
            "category":"Banks & Credit Unions",
            "subcategory":"Bank",
            "type":"Services"
        }
    ],
    "sg:phone":"+1 732 785 1188",
    "sg:postcode":"08724",
    "sg:province":"NJ",
    "sg:tags":[
        "loan",
        "real estate"
    ],
    "wof:name":"CFIC Home Mortgage",
    "wof:placetype":"venue"
},
  "geometry": {"coordinates":[-74.11246800000001,40.074275],"type":"Point"}
}