{
  "type": "Feature",
  "properties": {
    "iso:country":"US",
    "sg:address":"1310 W State St",
    "sg:city":"Trenton",
    "sg:classifiers":[
        {
            "category":"Professional",
            "subcategory":"Business Services",
            "type":"Services"
        }
    ],
    "sg:phone":"+1 609 396 1919",
    "sg:postcode":"08618",
    "sg:province":"NJ",
    "sg:tags":[
        "music"
    ],
    "wof:name":"CMR Music",
    "wof:placetype":"venue"
},
  "geometry": {"coordinates":[-74.795974,40.234739],"type":"Point"}
}