{
  "type": "Feature",
  "properties": {
    "addr:full":"123 Lehigh Dr Fairfield NJ 07004",
    "addr:housenumber":"123",
    "addr:postcode":"07004",
    "addr:street":"Lehigh Dr",
    "iso:country":"US",
    "sg:address":"123 Lehigh Dr",
    "sg:city":"Fairfield",
    "sg:classifiers":[
        {
            "category":"Manufacturing",
            "subcategory":"Printing",
            "type":"Manufacturing & Wholesale Goods"
        }
    ],
    "sg:phone":"+1 973 575 7550",
    "sg:postcode":"07004",
    "sg:province":"NJ",
    "sg:tags":[
        "lithographer"
    ],
    "wof:name":"Fairfield Litho II Corp",
    "wof:placetype":"venue"
},
  "geometry": {"coordinates":[-74.30962599999999,40.863189],"type":"Point"}
}