{
  "type": "Feature",
  "properties": {
    "iso:country":"US",
    "sg:address":"3196 Kennedy Blvd",
    "sg:city":"Union City",
    "sg:classifiers":[
        {
            "category":"Health Services",
            "subcategory":"Health Practitioner",
            "type":"Services"
        }
    ],
    "sg:phone":"+1 201 223 4949",
    "sg:postcode":"07087",
    "sg:province":"NJ",
    "sg:tags":[
        "therapy",
        "physical"
    ],
    "wof:name":"Sportscare Physical Therapy",
    "wof:placetype":"venue"
},
  "geometry": {"coordinates":[-74.031942,40.77505],"type":"Point"}
}