{
  "type": "Feature",
  "properties": {
    "addr:full":"104 Applegarth Rd Monroe Township NJ 08831",
    "addr:housenumber":"104",
    "addr:postcode":"08831",
    "addr:street":"Applegarth Rd",
    "iso:country":"US",
    "sg:address":"104 Applegarth Rd",
    "sg:city":"Monroe Township",
    "sg:classifiers":[
        {
            "category":"Personal",
            "subcategory":"Beauty Salon",
            "type":"Services"
        }
    ],
    "sg:phone":"+1   ",
    "sg:postcode":"08831",
    "sg:province":"NJ",
    "sg:tags":[
        "shop"
    ],
    "wof:name":"Michele Szezepanik",
    "wof:placetype":"venue"
},
  "geometry": {"coordinates":[-74.470904,40.268591],"type":"Point"}
}