{
  "type": "Feature",
  "properties": {
    "iso:country":"US",
    "sg:address":"163 Semel Ave",
    "sg:city":"Garfield",
    "sg:classifiers":[
        {
            "category":"Real Estate",
            "subcategory":"Real Estate Operator",
            "type":"Services"
        }
    ],
    "sg:phone":"+1   ",
    "sg:postcode":"07026",
    "sg:province":"NJ",
    "sg:tags":[
        "property",
        "management"
    ],
    "wof:name":"Lagattuta Partners LP",
    "wof:placetype":"venue"
},
  "geometry": {"coordinates":[-74.116179,40.884426],"type":"Point"}
}