{
  "type": "Feature",
  "properties": {
    "addr:full":"17 Crow Hill Rd Freehold NJ 07728",
    "addr:housenumber":"17",
    "addr:postcode":"07728",
    "addr:street":"Crow Hill Rd",
    "iso:country":"US",
    "sg:address":"17 Crow Hill Rd",
    "sg:city":"Freehold",
    "sg:classifiers":[
        {
            "category":"Professional",
            "subcategory":"Management & Consulting",
            "type":"Services"
        }
    ],
    "sg:phone":"+1 732 252 6214",
    "sg:postcode":"07728",
    "sg:province":"NJ",
    "wof:name":"ASAP Management",
    "wof:placetype":"venue"
},
  "geometry": {"coordinates":[-74.223895,40.252936],"type":"Point"}
}