{
  "type": "Feature",
  "properties": {
    "addr:full":"245 Hurffville Cross Keys Blackwood NJ 08012",
    "addr:housenumber":"245",
    "addr:postcode":"08012",
    "addr:street":"Hurffville",
    "iso:country":"US",
    "sg:address":"245 Hurffville Cross Keys",
    "sg:city":"Blackwood",
    "sg:classifiers":[
        {
            "category":"Restaurant",
            "type":"Food & Drink"
        }
    ],
    "sg:menulink":"http://www.allmenus.com/nj/washington/5470-angelos-pizza/menu/",
    "sg:phone":"+1 856 374 1600",
    "sg:postcode":"08012",
    "sg:province":"NJ",
    "sg:tags":[
        "italian"
    ],
    "wof:name":"Angelo's Pizza",
    "wof:placetype":"venue"
},
  "geometry": {"coordinates":[-75.049952,39.724709],"type":"Point"}
}