{
  "type": "Feature",
  "properties": {
    "addr:full":"3 Chukka Way Far Hills NJ 07931",
    "addr:housenumber":"3",
    "addr:postcode":"07931",
    "addr:street":"Chukka Way",
    "iso:country":"US",
    "sg:address":"3 Chukka Way",
    "sg:city":"Far Hills",
    "sg:classifiers":[
        {
            "category":"Shopping",
            "subcategory":"Bicycles & Sporting Goods",
            "type":"Retail Goods"
        }
    ],
    "sg:phone":"+1   ",
    "sg:postcode":"07931",
    "sg:province":"NJ",
    "wof:name":"Home Sweat Home Inc",
    "wof:placetype":"venue"
},
  "geometry": {"coordinates":[-74.635294,40.686277],"type":"Point"}
}