{
  "type": "Feature",
  "properties": {
    "iso:country":"US",
    "sg:address":"13 Hendrick Rd",
    "sg:city":"Flemington",
    "sg:classifiers":[
        {
            "category":"Shopping",
            "subcategory":"Used Merchandise",
            "type":"Retail Goods"
        }
    ],
    "sg:phone":"+1   ",
    "sg:postcode":"08822",
    "sg:province":"NJ",
    "wof:name":"Tomorrows Treasures",
    "wof:placetype":"venue"
},
  "geometry": {"coordinates":[-74.77834300000001,40.558073],"type":"Point"}
}