{
  "type": "Feature",
  "properties": {
    "addr:full":"970 New Brunswick Ave Rahway NJ 07065",
    "addr:housenumber":"970",
    "addr:postcode":"07065",
    "addr:street":"New Brunswick Ave",
    "iso:country":"US",
    "sg:address":"970 New Brunswick Ave",
    "sg:city":"Rahway",
    "sg:classifiers":[
        {
            "category":"Professional",
            "type":"Services"
        },
        {
            "category":"Manufacturing",
            "subcategory":"Tools & Machinery",
            "type":"Manufacturing & Wholesale Goods"
        }
    ],
    "sg:phone":"+1 732 382 5701",
    "sg:postcode":"07065",
    "sg:province":"NJ",
    "sg:tags":[
        "touch",
        "screen",
        "establishment",
        "monitor",
        "mfg"
    ],
    "wof:name":"Touch Dynamic Inc",
    "wof:placetype":"venue"
},
  "geometry": {"coordinates":[-74.279629,40.601051],"type":"Point"}
}