{
  "type": "Feature",
  "properties": {
    "addr:full":"20 Lakeside Ave Cherry Hill NJ 08003",
    "addr:housenumber":"20",
    "addr:postcode":"08003",
    "addr:street":"Lakeside Ave",
    "iso:country":"US",
    "sg:address":"20 Lakeside Ave",
    "sg:city":"Cherry Hill",
    "sg:classifiers":[
        {
            "category":"Wholesale",
            "subcategory":"Machinery & Supplies",
            "type":"Manufacturing & Wholesale Goods"
        }
    ],
    "sg:phone":"+1 856 429 2580",
    "sg:postcode":"08003",
    "sg:province":"NJ",
    "sg:tags":[
        "pump"
    ],
    "wof:name":"EDI Distrubutors Inc",
    "wof:placetype":"venue"
},
  "geometry": {"coordinates":[-75.01491300000001,39.872356],"type":"Point"}
}