{
  "type": "Feature",
  "properties": {
    "iso:country":"US",
    "sg:address":"165 Smith St",
    "sg:city":"Perth Amboy",
    "sg:classifiers":[
        {
            "category":"Shopping",
            "subcategory":"Clothing, Apparel, & Fashions",
            "type":"Retail Goods"
        }
    ],
    "sg:phone":"+1   ",
    "sg:postcode":"08861",
    "sg:province":"NJ",
    "sg:tags":[
        "sport"
    ],
    "wof:name":"U S World",
    "wof:placetype":"venue"
},
  "geometry": {"coordinates":[-74.269606,40.508914],"type":"Point"}
}