{
  "type": "Feature",
  "properties": {
    "addr:full":"19 Brookside Ave Fair Lawn NJ 07410",
    "addr:housenumber":"19",
    "addr:postcode":"07410",
    "addr:street":"Brookside Ave",
    "iso:country":"US",
    "sg:address":"19 Brookside Ave",
    "sg:city":"Fair Lawn",
    "sg:classifiers":[
        {
            "category":"Organizations",
            "subcategory":"Religious Organization",
            "type":"Services"
        }
    ],
    "sg:phone":"+1 201 794 0819",
    "sg:postcode":"07410",
    "sg:province":"NJ",
    "sg:tags":[
        "clergy"
    ],
    "wof:name":"Sam Josephson",
    "wof:placetype":"venue"
},
  "geometry": {"coordinates":[-74.0996,40.930558],"type":"Point"}
}