{
  "type": "Feature",
  "properties": {
    "addr:full":"200 Red Hill Rd Middletown NJ 07748",
    "addr:housenumber":"200",
    "addr:postcode":"07748",
    "addr:street":"Red Hill Rd",
    "iso:country":"US",
    "sg:address":"200 Red Hill Rd",
    "sg:city":"Middletown",
    "sg:classifiers":[
        {
            "category":"Professional",
            "subcategory":"Business Services",
            "type":"Services"
        }
    ],
    "sg:phone":"+1 732 671 1065",
    "sg:postcode":"07748",
    "sg:province":"NJ",
    "sg:tags":[
        "inspection"
    ],
    "wof:name":"Nj Inspection Svc",
    "wof:placetype":"venue"
},
  "geometry": {"coordinates":[-74.13359800000001,40.383101],"type":"Point"}
}