{
  "type": "Feature",
  "properties": {
    "iso:country":"US",
    "sg:address":"119 Somerset St",
    "sg:city":"New Brunswick",
    "sg:classifiers":[
        {
            "category":"Organizations",
            "subcategory":"Political Organization",
            "type":"Services"
        }
    ],
    "sg:phone":"+1 732 247 4606",
    "sg:postcode":"08901",
    "sg:province":"NJ",
    "wof:name":"N J Public Interest Research",
    "wof:placetype":"venue"
},
  "geometry": {"coordinates":[-74.44905799999999,40.496796],"type":"Point"}
}