{
  "type": "Feature",
  "properties": {
    "iso:country":"US",
    "sg:address":"186 W Madison Ave",
    "sg:city":"Dumont",
    "sg:classifiers":[
        {
            "category":"Shopping",
            "subcategory":"Clothing, Apparel, & Fashions",
            "type":"Retail Goods"
        }
    ],
    "sg:phone":"+1   ",
    "sg:postcode":"07628",
    "sg:province":"NJ",
    "wof:name":"OH My Buy",
    "wof:placetype":"venue"
},
  "geometry": {"coordinates":[-74.00494,40.94024],"type":"Point"}
}