{
  "type": "Feature",
  "properties": {
    "addr:full":"500 S Main St Pleasantville NJ 08232",
    "addr:housenumber":"500",
    "addr:postcode":"08232",
    "addr:street":"S Main St",
    "iso:country":"US",
    "sg:address":"500 S Main St",
    "sg:city":"Pleasantville",
    "sg:classifiers":[
        {
            "category":"Food & Beverages",
            "subcategory":"Groceries & Convenience Stores",
            "type":"Retail Goods"
        }
    ],
    "sg:phone":"+1 609 646 5267",
    "sg:postcode":"08232",
    "sg:province":"NJ",
    "sg:tags":[
        "market"
    ],
    "wof:name":"Cedar Food Market No 3",
    "wof:placetype":"venue"
},
  "geometry": {"coordinates":[-74.527642,39.386002],"type":"Point"}
}