{
  "type": "Feature",
  "properties": {
    "iso:country":"US",
    "sg:address":"248 Madison Ave",
    "sg:city":"Cresskill",
    "sg:classifiers":[
        {
            "category":"Health Services",
            "subcategory":"Nursing And Care Facility",
            "type":"Services"
        }
    ],
    "sg:phone":"+1 201 569 2660",
    "sg:postcode":"07626",
    "sg:province":"NJ",
    "sg:tags":[
        "home",
        "skilled",
        "convalescent"
    ],
    "sg:website":"www.potomacgrouphomes.com",
    "wof:name":"N J Potomac Homes",
    "wof:placetype":"venue"
},
  "geometry": {"coordinates":[-73.973651,40.941296],"type":"Point"}
}