{
  "type": "Feature",
  "properties": {
    "addr:full":"500 Chicago Ave Pt Pleasant Bch NJ 08742",
    "addr:housenumber":"500",
    "addr:postcode":"08742",
    "addr:street":"Chicago Ave Pt",
    "iso:country":"US",
    "sg:address":"500 Chicago Ave",
    "sg:city":"Pt Pleasant Bch",
    "sg:classifiers":[
        {
            "category":"Home & Garden",
            "subcategory":"Furniture",
            "type":"Retail Goods"
        }
    ],
    "sg:phone":"+1 732 206 0024",
    "sg:postcode":"08742",
    "sg:province":"NJ",
    "sg:tags":[
        "mattress"
    ],
    "wof:name":"America Mattress",
    "wof:placetype":"venue"
},
  "geometry": {"coordinates":[-74.04411,40.092168],"type":"Point"}
}