{
  "type": "Feature",
  "properties": {
    "addr:full":"60 E Main St Marlton NJ 08053",
    "addr:housenumber":"60",
    "addr:postcode":"08053",
    "addr:street":"E Main St",
    "iso:country":"US",
    "sg:address":"60 E Main St",
    "sg:city":"Marlton",
    "sg:classifiers":[
        {
            "category":"Banks & Credit Unions",
            "subcategory":"Financial Services",
            "type":"Services"
        }
    ],
    "sg:phone":"+1 856 797 9870",
    "sg:postcode":"08053",
    "sg:province":"NJ",
    "sg:tags":[
        "company",
        "holding"
    ],
    "wof:name":"Earle Enterprises",
    "wof:placetype":"venue"
},
  "geometry": {"coordinates":[-74.91655799999999,39.890439],"type":"Point"}
}