{
  "type": "Feature",
  "properties": {
    "addr:full":"150 S Main St Woodstown NJ 08098",
    "addr:housenumber":"150",
    "addr:postcode":"08098",
    "addr:street":"S Main St",
    "iso:country":"US",
    "sg:address":"150 S Main St",
    "sg:city":"Woodstown",
    "sg:classifiers":[
        {
            "category":"Building & Trades",
            "subcategory":"Construction",
            "type":"Services"
        }
    ],
    "sg:phone":"+1 856 769 4106",
    "sg:postcode":"08098",
    "sg:province":"NJ",
    "sg:tags":[
        "carpentry",
        "contractor"
    ],
    "wof:name":"Quinnette Custom Carpentry",
    "wof:placetype":"venue"
},
  "geometry": {"coordinates":[-75.327772,39.647517],"type":"Point"}
}