{
  "type": "Feature",
  "properties": {
    "iso:country":"US",
    "sg:address":"343 Millburn Ave Ste 105",
    "sg:city":"Millburn",
    "sg:classifiers":[
        {
            "category":"Restaurant",
            "type":"Food & Drink"
        }
    ],
    "sg:phone":"+1 973 379 6700",
    "sg:postcode":"07041",
    "sg:province":"NJ",
    "wof:name":"The Brick Oven Trattoria",
    "wof:placetype":"venue"
},
  "geometry": {"coordinates":[-74.307198,40.7239],"type":"Point"}
}