{
  "type": "Feature",
  "properties": {
    "addr:full":"842 Clifton Ave Ste 5 Clifton NJ 07013",
    "addr:housenumber":"842",
    "addr:postcode":"07013",
    "addr:street":"Clifton Ave Ste 5",
    "iso:country":"US",
    "sg:address":"842 Clifton Ave Ste 5",
    "sg:city":"Clifton",
    "sg:classifiers":[
        {
            "category":"Health Services",
            "subcategory":"Doctor",
            "type":"Services"
        }
    ],
    "sg:phone":"+1 973 777 2440",
    "sg:postcode":"07013",
    "sg:province":"NJ",
    "sg:tags":[
        "cardiologist"
    ],
    "wof:name":"Cardiacare Center PC",
    "wof:placetype":"venue"
},
  "geometry": {"coordinates":[-74.157898,40.866501],"type":"Point"}
}