{
  "type": "Feature",
  "properties": {
    "iso:country":"US",
    "sg:address":"363 Centre St Ste 4",
    "sg:city":"Nutley",
    "sg:classifiers":[
        {
            "category":"Autos & Motor Vehicles",
            "subcategory":"Automobile Sales",
            "type":"Retail Goods"
        }
    ],
    "sg:phone":"+1 973 661 1329",
    "sg:postcode":"07110",
    "sg:province":"NJ",
    "sg:tags":[
        "limo"
    ],
    "wof:name":"Bob Cassie Limousine Service",
    "wof:placetype":"venue"
},
  "geometry": {"coordinates":[-74.161777,40.814465],"type":"Point"}
}