{
  "type": "Feature",
  "properties": {
    "iso:country":"US",
    "sg:address":"900 State Highway 168",
    "sg:city":"Washington",
    "sg:classifiers":[
        {
            "category":"Banks & Credit Unions",
            "subcategory":"Atm",
            "type":"Services"
        }
    ],
    "sg:phone":"+1 856 228 7964",
    "sg:postcode":"07882",
    "sg:province":"NJ",
    "sg:tags":[
        "bankruptcy"
    ],
    "wof:name":"Joseph J Rogers ESQ",
    "wof:placetype":"venue"
},
  "geometry": {"coordinates":[-74.981201,40.759102],"type":"Point"}
}