{
  "type": "Feature",
  "properties": {
    "iso:country":"US",
    "sg:address":"208 Greene Ave",
    "sg:city":"Middlesex",
    "sg:classifiers":[
        {
            "category":"Building & Trades",
            "subcategory":"Cleaning & Sanitation",
            "type":"Services"
        }
    ],
    "sg:phone":"+1 732 469 2566",
    "sg:postcode":"08846",
    "sg:province":"NJ",
    "sg:tags":[
        "janitor"
    ],
    "wof:name":"Zuniga Cleaning Svc",
    "wof:placetype":"venue"
},
  "geometry": {"coordinates":[-74.51282500000001,40.567423],"type":"Point"}
}