{
  "type": "Feature",
  "properties": {
    "addr:full":"21 Old Farm Rd Oakhurst NJ 07755",
    "addr:housenumber":"21",
    "addr:postcode":"07755",
    "addr:street":"Old Farm Rd",
    "iso:country":"US",
    "sg:address":"21 Old Farm Rd",
    "sg:city":"Oakhurst",
    "sg:classifiers":[
        {
            "category":"Airline",
            "type":"Transportation"
        }
    ],
    "sg:phone":"+1 732 870 3218",
    "sg:postcode":"07755",
    "sg:province":"NJ",
    "sg:tags":[
        "executive",
        "jet"
    ],
    "wof:name":"Exchange Air Partners LLC",
    "wof:placetype":"venue"
},
  "geometry": {"coordinates":[-74.013262,40.270429],"type":"Point"}
}