{
  "type": "Feature",
  "properties": {
    "addr:full":"147 Bloomfield Ave Montclair NJ 07042",
    "addr:housenumber":"147",
    "addr:postcode":"07042",
    "addr:street":"Bloomfield Ave",
    "iso:country":"US",
    "sg:address":"147 Bloomfield Ave",
    "sg:city":"Montclair",
    "sg:classifiers":[
        {
            "category":"Organizations",
            "subcategory":"Religious Organization",
            "type":"Services"
        }
    ],
    "sg:phone":"+1 973 746 7616",
    "sg:postcode":"07042",
    "sg:province":"NJ",
    "wof:name":"Mount Carmel Holy Church",
    "wof:placetype":"venue"
},
  "geometry": {"coordinates":[-74.210899,40.807899],"type":"Point"}
}