{
  "type": "Feature",
  "properties": {
    "iso:country":"US",
    "sg:address":"155 River Rd",
    "sg:city":"North Arlington",
    "sg:classifiers":[
        {
            "category":"Building & Trades",
            "subcategory":"Electrical",
            "type":"Services"
        }
    ],
    "sg:phone":"+1 201 997 7400",
    "sg:postcode":"07031",
    "sg:province":"NJ",
    "sg:tags":[
        "electrical",
        "contractor"
    ],
    "wof:name":"SJS Electric",
    "wof:placetype":"venue"
},
  "geometry": {"coordinates":[-74.142489,40.79057],"type":"Point"}
}