{
  "type": "Feature",
  "properties": {
    "iso:country":"US",
    "sg:address":"570 Pompton Ave",
    "sg:city":"Cedar Grove",
    "sg:classifiers":[
        {
            "category":"Banks & Credit Unions",
            "subcategory":"Bank",
            "type":"Services"
        }
    ],
    "sg:phone":"+1 888 762 2265",
    "sg:postcode":"07009",
    "sg:province":"NJ",
    "wof:name":"Pnc Bank",
    "wof:placetype":"venue"
},
  "geometry": {"coordinates":[-74.22978500000001,40.852652],"type":"Point"}
}