{
  "type": "Feature",
  "properties": {
    "addr:full":"27 Hanover Rd East Hanover NJ 07936",
    "addr:housenumber":"27",
    "addr:postcode":"07936",
    "addr:street":"Hanover Rd",
    "iso:country":"US",
    "sg:address":"27 Hanover Rd",
    "sg:city":"East Hanover",
    "sg:classifiers":[
        {
            "category":"Wholesale",
            "subcategory":"Chemicals & Plastics",
            "type":"Manufacturing & Wholesale Goods"
        }
    ],
    "sg:phone":"+1 973 428 3399",
    "sg:postcode":"07936",
    "sg:province":"NJ",
    "wof:name":"Ames Chemical",
    "wof:placetype":"venue"
},
  "geometry": {"coordinates":[-74.371764,40.799751],"type":"Point"}
}