{
  "type": "Feature",
  "properties": {
    "iso:country":"US",
    "sg:address":"928 W Sherman Ave",
    "sg:city":"Vineland",
    "sg:classifiers":[
        {
            "category":"Social Services",
            "subcategory":"Adult Care",
            "type":"Services"
        }
    ],
    "sg:phone":"+1 856 696 6830",
    "sg:postcode":"08360",
    "sg:province":"NJ",
    "sg:tags":[
        "residential"
    ],
    "wof:name":"Department of Human Services",
    "wof:placetype":"venue"
},
  "geometry": {"coordinates":[-75.04979400000001,39.446985],"type":"Point"}
}