{
  "type": "Feature",
  "properties": {
    "iso:country":"US",
    "sg:address":"632 N Pearl St",
    "sg:city":"Bridgeton",
    "sg:classifiers":[
        {
            "category":"Food & Beverages",
            "subcategory":"Bakery",
            "type":"Retail Goods"
        }
    ],
    "sg:phone":"+1 856 451 6368",
    "sg:postcode":"08302",
    "sg:province":"NJ",
    "sg:tags":[
        "baker"
    ],
    "wof:name":"Terrigno's Bakery",
    "wof:placetype":"venue"
},
  "geometry": {"coordinates":[-75.221462,39.444614],"type":"Point"}
}