{
  "type": "Feature",
  "properties": {
    "iso:country":"US",
    "sg:address":"293 Passaic St",
    "sg:city":"Passaic",
    "sg:classifiers":[
        {
            "category":"Health Services",
            "subcategory":"Doctor",
            "type":"Services"
        }
    ],
    "sg:phone":"+1 973 365 1377",
    "sg:postcode":"07055",
    "sg:province":"NJ",
    "sg:tags":[
        "medical"
    ],
    "wof:name":"Castilla William MD",
    "wof:placetype":"venue"
},
  "geometry": {"coordinates":[-74.121696,40.861198],"type":"Point"}
}