{
  "type": "Feature",
  "properties": {
    "iso:country":"US",
    "sg:address":"942 Memorial Pkwy",
    "sg:city":"Phillipsburg",
    "sg:classifiers":[
        {
            "category":"Wholesale",
            "subcategory":"Machinery & Supplies",
            "type":"Manufacturing & Wholesale Goods"
        }
    ],
    "sg:phone":"+1 908 859 8000",
    "sg:postcode":"08865",
    "sg:province":"NJ",
    "sg:tags":[
        "pump"
    ],
    "wof:name":"Ingersoll Dresser Pump",
    "wof:placetype":"venue"
},
  "geometry": {"coordinates":[-75.168842,40.698384],"type":"Point"}
}