{
  "type": "Feature",
  "properties": {
    "addr:full":"4 Countryside Ln Ringwood NJ 07456",
    "addr:housenumber":"4",
    "addr:postcode":"07456",
    "addr:street":"Countryside Ln",
    "iso:country":"US",
    "sg:address":"4 Countryside Ln",
    "sg:city":"Ringwood",
    "sg:classifiers":[
        {
            "category":"Personal",
            "subcategory":"Day Spa",
            "type":"Services"
        }
    ],
    "sg:phone":"+1 973 962 8600",
    "sg:postcode":"07456",
    "sg:province":"NJ",
    "wof:name":"Magic Touch Day Spa",
    "wof:placetype":"venue"
},
  "geometry": {"coordinates":[-74.26442400000001,41.079221],"type":"Point"}
}