{
  "type": "Feature",
  "properties": {
    "addr:full":"4324 Route 130 Willingboro NJ 08046",
    "addr:housenumber":"4324",
    "addr:postcode":"08046",
    "addr:street":"Route 130",
    "iso:country":"US",
    "sg:address":"4324 Route 130",
    "sg:city":"Willingboro",
    "sg:classifiers":[
        {
            "category":"Personal",
            "subcategory":"Nail Salon",
            "type":"Services"
        }
    ],
    "sg:phone":"+1 609 871 7370",
    "sg:postcode":"08046",
    "sg:province":"NJ",
    "wof:name":"Et Nail Salon",
    "wof:placetype":"venue"
},
  "geometry": {"coordinates":[-74.906898,40.0443],"type":"Point"}
}