{
  "type": "Feature",
  "properties": {
    "addr:full":"9 Zink Pl Fair Lawn NJ 07410",
    "addr:housenumber":"9",
    "addr:postcode":"07410",
    "addr:street":"Zink Pl",
    "iso:country":"US",
    "sg:address":"9 Zink Pl",
    "sg:city":"Fair Lawn",
    "sg:classifiers":[
        {
            "category":"Freight",
            "type":"Transportation"
        }
    ],
    "sg:phone":"+1 201 797 4328",
    "sg:postcode":"07410",
    "sg:province":"NJ",
    "sg:tags":[
        "distribution",
        "cosmetic",
        "warehousing"
    ],
    "wof:name":"Darling Corporation",
    "wof:placetype":"venue"
},
  "geometry": {"coordinates":[-74.117634,40.922094],"type":"Point"}
}