{
  "type": "Feature",
  "properties": {
    "iso:country":"US",
    "sg:address":"88 Llewellyn Ave",
    "sg:city":"Bloomfield",
    "sg:classifiers":[
        {
            "category":"Shopping",
            "subcategory":"Discount & Variety Stores",
            "type":"Retail Goods"
        }
    ],
    "sg:phone":"+1 973 743 6083",
    "sg:postcode":"07003",
    "sg:province":"NJ",
    "sg:tags":[
        "merchandise",
        "general"
    ],
    "wof:name":"Ethical Products Inc",
    "wof:placetype":"venue"
},
  "geometry": {"coordinates":[-74.207832,40.788285],"type":"Point"}
}