{
  "type": "Feature",
  "properties": {
    "iso:country":"US",
    "sg:address":"201 E 5th St",
    "sg:city":"Plainfield",
    "sg:classifiers":[
        {
            "category":"Organizations",
            "subcategory":"Religious Organization",
            "type":"Services"
        }
    ],
    "sg:phone":"+1 908 822 1991",
    "sg:postcode":"07060",
    "sg:province":"NJ",
    "sg:tags":[
        "church"
    ],
    "wof:name":"House of Prayer Holy Mission",
    "wof:placetype":"venue"
},
  "geometry": {"coordinates":[-74.41609099999999,40.619282],"type":"Point"}
}