{
  "type": "Feature",
  "properties": {
    "iso:country":"US",
    "sg:address":"5 Powhataton Way",
    "sg:city":"Hackettstown",
    "sg:classifiers":[
        {
            "category":"Wholesale",
            "subcategory":"Vending Machines",
            "type":"Manufacturing & Wholesale Goods"
        }
    ],
    "sg:phone":"+1   ",
    "sg:postcode":"07840",
    "sg:province":"NJ",
    "wof:name":"AAA Vending",
    "wof:placetype":"venue"
},
  "geometry": {"coordinates":[-74.803969,40.854437],"type":"Point"}
}