{
  "type": "Feature",
  "properties": {
    "addr:full":"160 Mercer St Lawrenceville NJ 08690",
    "addr:housenumber":"160",
    "addr:postcode":"08690",
    "addr:street":"Mercer St",
    "iso:country":"US",
    "sg:address":"160 Mercer St",
    "sg:city":"Lawrenceville",
    "sg:classifiers":[
        {
            "category":"Travel",
            "subcategory":"Travel Agent",
            "type":"Entertainment"
        }
    ],
    "sg:phone":"+1 609 987 0577",
    "sg:postcode":"08690",
    "sg:province":"NJ",
    "sg:tags":[
        "agency",
        "bureau"
    ],
    "wof:name":"Empress Travel",
    "wof:placetype":"venue"
},
  "geometry": {"coordinates":[-74.657008,40.233476],"type":"Point"}
}