{
  "type": "Feature",
  "properties": {
    "iso:country":"US",
    "sg:address":"509 Hopkins Rd ",
    "sg:city":"Haddonfield",
    "sg:classifiers":[
        {
            "category":"Restaurant",
            "type":"Food & Drink"
        }
    ],
    "sg:menulink":"http://www.allmenus.com/nj/haddon/285335-brunos-restaurant--pizza/menu/",
    "sg:phone":"+1 856 428 9505",
    "sg:postcode":"08033",
    "sg:province":"NJ",
    "sg:tags":[
        "american",
        "pizza"
    ],
    "wof:name":"Bruno's Restaurant & Pizza",
    "wof:placetype":"venue"
},
  "geometry": {"coordinates":[-75.059586,39.894042],"type":"Point"}
}