{
  "type": "Feature",
  "properties": {
    "iso:country":"US",
    "sg:address":"527 Bloomfield Ave",
    "sg:city":"Caldwell",
    "sg:classifiers":[
        {
            "category":"Shopping",
            "subcategory":"Computers & Home Electronics",
            "type":"Retail Goods"
        }
    ],
    "sg:phone":"+1   ",
    "sg:postcode":"07006",
    "sg:province":"NJ",
    "sg:tags":[
        "custom"
    ],
    "wof:name":"High Grove Software",
    "wof:placetype":"venue"
},
  "geometry": {"coordinates":[-74.28617,40.84556],"type":"Point"}
}