{
  "type": "Feature",
  "properties": {
    "iso:country":"US",
    "sg:address":"707 Holmdel Rd",
    "sg:city":"Holmdel",
    "sg:classifiers":[
        {
            "category":"Professional",
            "subcategory":"Business Services",
            "type":"Services"
        }
    ],
    "sg:phone":"+1   ",
    "sg:postcode":"07733",
    "sg:province":"NJ",
    "wof:name":"Everyday Solutions LLC",
    "wof:placetype":"venue"
},
  "geometry": {"coordinates":[-74.189318,40.403907],"type":"Point"}
}