{
  "type": "Feature",
  "properties": {
    "iso:country":"US",
    "sg:address":"16 W Front St",
    "sg:city":"Red Bank",
    "sg:classifiers":[
        {
            "category":"Professional",
            "type":"Services"
        }
    ],
    "sg:phone":"+1 732 224 8782",
    "sg:postcode":"07701",
    "sg:province":"NJ",
    "sg:tags":[
        "establishment"
    ],
    "wof:name":"Monmouth Development Co Inc",
    "wof:placetype":"venue"
},
  "geometry": {"coordinates":[-74.06588600000001,40.35219],"type":"Point"}
}