{
  "type": "Feature",
  "properties": {
    "addr:full":"10 Gates Mill Ct Trenton NJ 08690",
    "addr:housenumber":"10",
    "addr:postcode":"08690",
    "addr:street":"Gates Mill Ct",
    "iso:country":"US",
    "sg:address":"10 Gates Mill Ct",
    "sg:city":"Trenton",
    "sg:classifiers":[
        {
            "category":"Education",
            "subcategory":"College",
            "type":"Public Place"
        }
    ],
    "sg:phone":"+1 609 586 0913",
    "sg:postcode":"08690",
    "sg:province":"NJ",
    "sg:tags":[
        "academic",
        "school"
    ],
    "wof:name":"University Heights",
    "wof:placetype":"venue"
},
  "geometry": {"coordinates":[-74.663085,40.205458],"type":"Point"}
}