{
  "type": "Feature",
  "properties": {
    "addr:full":"9375 N Crescent Blvd Pennsauken NJ 08110",
    "addr:housenumber":"9375",
    "addr:postcode":"08110",
    "addr:street":"N Crescent Blvd",
    "iso:country":"US",
    "sg:address":"9375 N Crescent Blvd",
    "sg:city":"Pennsauken",
    "sg:classifiers":[
        {
            "category":"Autos & Motor Vehicles",
            "subcategory":"Fuel & Gas Station",
            "type":"Retail Goods"
        }
    ],
    "sg:phone":"+1 856 662 7954",
    "sg:postcode":"08110",
    "sg:province":"NJ",
    "sg:tags":[
        "stop",
        "truck"
    ],
    "wof:name":"Ross Betsey Truck Stop",
    "wof:placetype":"venue"
},
  "geometry": {"coordinates":[-75.02260200000001,39.9815],"type":"Point"}
}