{
  "type": "Feature",
  "properties": {
    "iso:country":"US",
    "sg:address":"27 Gleim Rd",
    "sg:city":"White House Station",
    "sg:classifiers":[
        {
            "category":"Building & Trades",
            "subcategory":"Landscaping Services",
            "type":"Services"
        }
    ],
    "sg:phone":"+1 908 534 9527",
    "sg:postcode":"08889",
    "sg:province":"NJ",
    "wof:name":"Paesano Lawn Maintenance",
    "wof:placetype":"venue"
},
  "geometry": {"coordinates":[-74.767262,40.613256],"type":"Point"}
}