{
  "type": "Feature",
  "properties": {
    "iso:country":"US",
    "sg:address":"17 Moquis Trl",
    "sg:city":"Oak Ridge",
    "sg:classifiers":[
        {
            "category":"Shopping",
            "subcategory":"Catalog Store",
            "type":"Retail Goods"
        }
    ],
    "sg:phone":"+1   ",
    "sg:postcode":"07438",
    "sg:province":"NJ",
    "sg:tags":[
        "mail",
        "book",
        "order"
    ],
    "wof:name":"Stray Books Online Book Shop",
    "wof:placetype":"venue"
},
  "geometry": {"coordinates":[-74.517365,41.012206],"type":"Point"}
}