{
  "type": "Feature",
  "properties": {
    "iso:country":"US",
    "sg:address":"1155 Liberty Ave",
    "sg:city":"Hillside",
    "sg:classifiers":[
        {
            "category":"Professional",
            "type":"Services"
        }
    ],
    "sg:phone":"+1   ",
    "sg:postcode":"07205",
    "sg:province":"NJ",
    "wof:name":"Balloon Plattoon",
    "wof:placetype":"venue"
},
  "geometry": {"coordinates":[-74.23657300000001,40.693301],"type":"Point"}
}