{
  "type": "Feature",
  "properties": {
    "iso:country":"US",
    "sg:address":"5 Independence Way",
    "sg:city":"Princeton",
    "sg:classifiers":[
        {
            "category":"Arts & Performance",
            "subcategory":"Theater",
            "type":"Entertainment"
        }
    ],
    "sg:phone":"+1 609 951 9594",
    "sg:postcode":"08540",
    "sg:province":"NJ",
    "sg:tags":[
        "music"
    ],
    "wof:name":"St Clair Entertainment Inc",
    "wof:placetype":"venue"
},
  "geometry": {"coordinates":[-74.6011,40.361429],"type":"Point"}
}