{
  "type": "Feature",
  "properties": {
    "addr:full":"186 Princeton Hightstown Rd Princeton Junction NJ 08550",
    "addr:housenumber":"186",
    "addr:postcode":"08550",
    "addr:street":"Princeton Hightstown Rd",
    "iso:country":"US",
    "sg:address":"186 Princeton Hightstown Rd",
    "sg:city":"Princeton Junction",
    "sg:classifiers":[
        {
            "category":"Professional",
            "subcategory":"Accounting & Tax Preparation",
            "type":"Services"
        }
    ],
    "sg:phone":"+1 609 799 4848",
    "sg:postcode":"08550",
    "sg:province":"NJ",
    "wof:name":"Lonny E Bassin CPA",
    "wof:placetype":"venue"
},
  "geometry": {"coordinates":[-74.60674400000001,40.301246],"type":"Point"}
}