{
  "type": "Feature",
  "properties": {
    "addr:full":"149 Butler St Trenton NJ 08611",
    "addr:housenumber":"149",
    "addr:postcode":"08611",
    "addr:street":"Butler St",
    "iso:country":"US",
    "sg:address":"149 Butler St",
    "sg:city":"Trenton",
    "sg:classifiers":[
        {
            "category":"Professional",
            "subcategory":"Advertising",
            "type":"Services"
        }
    ],
    "sg:phone":"+1 609 396 2792",
    "sg:postcode":"08611",
    "sg:province":"NJ",
    "sg:tags":[
        "mailing",
        "shipping"
    ],
    "wof:name":"Agustin Ahassen",
    "wof:placetype":"venue"
},
  "geometry": {"coordinates":[-74.749832,40.213342],"type":"Point"}
}