{
  "type": "Feature",
  "properties": {
    "addr:full":"1260 Stelton Rd Piscataway NJ 08854",
    "addr:housenumber":"1260",
    "addr:postcode":"08854",
    "addr:street":"Stelton Rd",
    "iso:country":"US",
    "sg:address":"1260 Stelton Rd",
    "sg:city":"Piscataway",
    "sg:classifiers":[
        {
            "category":"Manufacturing",
            "subcategory":"Jewelry",
            "type":"Manufacturing & Wholesale Goods"
        }
    ],
    "sg:phone":"+1 732 777 9170",
    "sg:postcode":"08854",
    "sg:province":"NJ",
    "sg:tags":[
        "import",
        "silver",
        "gold",
        "mfg"
    ],
    "wof:name":"Gold Signature Incorporated",
    "wof:placetype":"venue"
},
  "geometry": {"coordinates":[-74.422684,40.539335],"type":"Point"}
}