{
  "type": "Feature",
  "properties": {
    "addr:full":"54 W Main St Ramsey NJ 07446",
    "addr:housenumber":"54",
    "addr:postcode":"07446",
    "addr:street":"W Main St",
    "iso:country":"US",
    "sg:address":"54 W Main St",
    "sg:city":"Ramsey",
    "sg:classifiers":[
        {
            "category":"Personal",
            "subcategory":"Beauty Salon",
            "type":"Services"
        }
    ],
    "sg:phone":"+1 201 236 8263",
    "sg:postcode":"07446",
    "sg:province":"NJ",
    "sg:tags":[
        "shop"
    ],
    "wof:name":"Ramsey Nail Salon",
    "wof:placetype":"venue"
},
  "geometry": {"coordinates":[-74.14396000000001,41.057148],"type":"Point"}
}