{
  "type": "Feature",
  "properties": {
    "iso:country":"US",
    "sg:address":"2333 Whitehorse Mercerville Rd",
    "sg:city":"Mercerville",
    "sg:classifiers":[
        {
            "category":"Professional",
            "subcategory":"Lawyer & Legal Services",
            "type":"Services"
        }
    ],
    "sg:phone":"+1 609 587 7758",
    "sg:postcode":"08619",
    "sg:province":"NJ",
    "sg:tags":[
        "attorney"
    ],
    "wof:name":"Mercerville Law Ctr",
    "wof:placetype":"venue"
},
  "geometry": {"coordinates":[-74.687128,40.229638],"type":"Point"}
}