{
  "type": "Feature",
  "properties": {
    "addr:full":"8 Buxmont Ln Willingboro NJ 08046",
    "addr:housenumber":"8",
    "addr:postcode":"08046",
    "addr:street":"Buxmont Ln",
    "iso:country":"US",
    "sg:address":"8 Buxmont Ln",
    "sg:city":"Willingboro",
    "sg:classifiers":[
        {
            "category":"Professional",
            "type":"Services"
        }
    ],
    "sg:phone":"+1 609 877 2967",
    "sg:postcode":"08046",
    "sg:province":"NJ",
    "sg:tags":[
        "relocation"
    ],
    "wof:name":"Hall, Scott",
    "wof:placetype":"venue"
},
  "geometry": {"coordinates":[-74.884885,40.041841],"type":"Point"}
}