{
  "type": "Feature",
  "properties": {
    "addr:full":"347 High St Burlington NJ 08016",
    "addr:housenumber":"347",
    "addr:postcode":"08016",
    "addr:street":"High St",
    "iso:country":"US",
    "sg:address":"347 High St",
    "sg:city":"Burlington",
    "sg:classifiers":[
        {
            "category":"Shopping",
            "subcategory":"Shoes",
            "type":"Retail Goods"
        }
    ],
    "sg:phone":"+1   ",
    "sg:postcode":"08016",
    "sg:province":"NJ",
    "wof:name":"Serious Shoes Plus",
    "wof:placetype":"venue"
},
  "geometry": {"coordinates":[-74.858406,40.078261],"type":"Point"}
}