{
  "type": "Feature",
  "properties": {
    "iso:country":"US",
    "sg:address":"140 Commerce Way",
    "sg:city":"Totowa",
    "sg:classifiers":[
        {
            "category":"Shopping",
            "subcategory":"Jewelry",
            "type":"Retail Goods"
        }
    ],
    "sg:phone":"+1 973 837 8196",
    "sg:postcode":"07512",
    "sg:province":"NJ",
    "sg:tags":[
        "watch"
    ],
    "wof:name":"Next Day Watches",
    "wof:placetype":"venue"
},
  "geometry": {"coordinates":[-74.235829,40.909013],"type":"Point"}
}