{
  "type": "Feature",
  "properties": {
    "addr:full":"7503 2nd Ave North Bergen NJ 07047",
    "addr:housenumber":"7503",
    "addr:postcode":"07047",
    "addr:street":"2Nd Ave",
    "iso:country":"US",
    "sg:address":"7503 2nd Ave",
    "sg:city":"North Bergen",
    "sg:classifiers":[
        {
            "category":"Freight",
            "type":"Transportation"
        }
    ],
    "sg:phone":"+1 201 854 3126",
    "sg:postcode":"07047",
    "sg:province":"NJ",
    "wof:name":"Amcro International Shipping",
    "wof:placetype":"venue"
},
  "geometry": {"coordinates":[-74.01057299999999,40.799296],"type":"Point"}
}