{
  "type": "Feature",
  "properties": {
    "iso:country":"US",
    "sg:address":"1505 Main St",
    "sg:city":"Rahway",
    "sg:classifiers":[
        {
            "category":"Shopping",
            "subcategory":"Beauty & Cosmetics",
            "type":"Retail Goods"
        }
    ],
    "sg:phone":"+1 732 396 8566",
    "sg:postcode":"07065",
    "sg:province":"NJ",
    "sg:tags":[
        "supply"
    ],
    "wof:name":"Rahway Beauty & Barber Supply",
    "wof:placetype":"venue"
},
  "geometry": {"coordinates":[-74.273804,40.607101],"type":"Point"}
}