{
  "type": "Feature",
  "properties": {
    "iso:country":"US",
    "sg:address":"720 Lexington Ave",
    "sg:city":"Kenilworth",
    "sg:classifiers":[
        {
            "category":"Freight",
            "type":"Transportation"
        }
    ],
    "sg:phone":"+1 908 241 0080",
    "sg:postcode":"07033",
    "sg:province":"NJ",
    "sg:tags":[
        "general"
    ],
    "sg:website":"www.rotarypen.com",
    "wof:name":"Rotary Pen Corp",
    "wof:placetype":"venue"
},
  "geometry": {"coordinates":[-74.280342,40.668572],"type":"Point"}
}