{
  "type": "Feature",
  "properties": {
    "addr:full":"365 Schuyler Ave Kearny NJ 07032",
    "addr:housenumber":"365",
    "addr:postcode":"07032",
    "addr:street":"Schuyler Ave",
    "iso:country":"US",
    "sg:address":"365 Schuyler Ave",
    "sg:city":"Kearny",
    "sg:classifiers":[
        {
            "category":"Retail",
            "subcategory":"Auto Repair",
            "type":"Services"
        }
    ],
    "sg:phone":"+1 201 997 0295",
    "sg:postcode":"07032",
    "sg:province":"NJ",
    "sg:tags":[
        "body",
        "shop",
        "painting",
        "automobile"
    ],
    "wof:name":"Nelson's Auto Body",
    "wof:placetype":"venue"
},
  "geometry": {"coordinates":[-74.142197,40.7612],"type":"Point"}
}