{
  "type": "Feature",
  "properties": {
    "iso:country":"US",
    "sg:address":"22 Paterson Ave",
    "sg:city":"Paterson",
    "sg:classifiers":[
        {
            "category":"Food & Beverages",
            "subcategory":"Groceries & Convenience Stores",
            "type":"Retail Goods"
        }
    ],
    "sg:phone":"+1 973 595 7360",
    "sg:postcode":"07522",
    "sg:province":"NJ",
    "sg:tags":[
        "market"
    ],
    "wof:name":"Khushiara Mini Market",
    "wof:placetype":"venue"
},
  "geometry": {"coordinates":[-74.18409699999999,40.915199],"type":"Point"}
}