{
  "type": "Feature",
  "properties": {
    "addr:full":"6B Provost Sq Caldwell NJ 07006",
    "addr:housenumber":"6b",
    "addr:postcode":"07006",
    "addr:street":"Provost Sq",
    "iso:country":"US",
    "sg:address":"6B Provost Sq",
    "sg:city":"Caldwell",
    "sg:classifiers":[
        {
            "category":"Arena",
            "subcategory":"Sports Club",
            "type":"Entertainment"
        }
    ],
    "sg:phone":"+1 973 228 7111",
    "sg:postcode":"07006",
    "sg:province":"NJ",
    "sg:tags":[
        "martial art"
    ],
    "sg:website":"www.asianartscenter.com",
    "wof:name":"Asian Arts Center",
    "wof:placetype":"venue"
},
  "geometry": {"coordinates":[-74.274456,40.837817],"type":"Point"}
}