{
  "type": "Feature",
  "properties": {
    "iso:country":"US",
    "sg:address":"669 Millbrook Ave",
    "sg:city":"Randolph",
    "sg:classifiers":[
        {
            "category":"Health Services",
            "subcategory":"Doctor",
            "type":"Services"
        }
    ],
    "sg:phone":"+1 973 895 5636",
    "sg:postcode":"07869",
    "sg:province":"NJ",
    "sg:tags":[
        "medical"
    ],
    "wof:name":"Peter Jacelone DC",
    "wof:placetype":"venue"
},
  "geometry": {"coordinates":[-74.57470499999999,40.831181],"type":"Point"}
}