{
  "type": "Feature",
  "properties": {
    "iso:country":"US",
    "sg:address":"9 Saddle River Rd",
    "sg:city":"Fair Lawn",
    "sg:classifiers":[
        {
            "category":"Shopping",
            "subcategory":"Florist",
            "type":"Retail Goods"
        }
    ],
    "sg:phone":"+1   ",
    "sg:postcode":"07410",
    "sg:province":"NJ",
    "wof:name":"J C Young",
    "wof:placetype":"venue"
},
  "geometry": {"coordinates":[-74.091281,40.919999],"type":"Point"}
}