{
  "type": "Feature",
  "properties": {
    "addr:full":"434 Elizabeth Ave Elizabeth NJ 07206",
    "addr:housenumber":"434",
    "addr:postcode":"07206",
    "addr:street":"Elizabeth Ave",
    "iso:country":"US",
    "sg:address":"434 Elizabeth Ave",
    "sg:city":"Elizabeth",
    "sg:classifiers":[
        {
            "category":"Wholesale",
            "subcategory":"Meat",
            "type":"Manufacturing & Wholesale Goods"
        }
    ],
    "sg:phone":"+1 908 351 8888",
    "sg:postcode":"07206",
    "sg:province":"NJ",
    "sg:tags":[
        "shop"
    ],
    "wof:name":"Los Ranchos",
    "wof:placetype":"venue"
},
  "geometry": {"coordinates":[-74.197502,40.653702],"type":"Point"}
}