{
  "type": "Feature",
  "properties": {
    "addr:full":"2709 John F Kennedy Blvd Jersey City NJ 07306",
    "addr:housenumber":"2709",
    "addr:postcode":"07306",
    "addr:street":"John F Kennedy Blvd",
    "iso:country":"US",
    "sg:address":"2709 John F Kennedy Blvd",
    "sg:city":"Jersey City",
    "sg:classifiers":[
        {
            "category":"Restaurant",
            "type":"Food & Drink"
        }
    ],
    "sg:phone":"+1 201 433 7333",
    "sg:postcode":"07306",
    "sg:province":"NJ",
    "sg:tags":[
        "delicatessen"
    ],
    "wof:name":"Alexandria Deli",
    "wof:placetype":"venue"
},
  "geometry": {"coordinates":[-74.069569,40.729185],"type":"Point"}
}