{
  "type": "Feature",
  "properties": {
    "addr:full":"315 High St Burlington NJ 08016",
    "addr:housenumber":"315",
    "addr:postcode":"08016",
    "addr:street":"High St",
    "iso:country":"US",
    "sg:address":"315 High St",
    "sg:city":"Burlington",
    "sg:classifiers":[
        {
            "category":"Wholesale",
            "subcategory":"Non-durable Goods",
            "type":"Manufacturing & Wholesale Goods"
        }
    ],
    "sg:phone":"+1 609 526 4107",
    "sg:postcode":"08016",
    "sg:province":"NJ",
    "sg:tags":[
        "dry",
        "goods-wholesale"
    ],
    "wof:name":"T's House Of Beauty Supplies",
    "wof:placetype":"venue"
},
  "geometry": {"coordinates":[-74.858673,40.07885],"type":"Point"}
}