{
  "type": "Feature",
  "properties": {
    "iso:country":"US",
    "sg:address":"35 Allendale Rd",
    "sg:city":"Marmora",
    "sg:classifiers":[
        {
            "category":"Building & Trades",
            "subcategory":"Construction",
            "type":"Services"
        }
    ],
    "sg:phone":"+1 609 390 7706",
    "sg:postcode":"08223",
    "sg:province":"NJ",
    "sg:tags":[
        "contractor"
    ],
    "wof:name":"Dimeglio Masonary",
    "wof:placetype":"venue"
},
  "geometry": {"coordinates":[-74.643753,39.266693],"type":"Point"}
}