{
  "type": "Feature",
  "properties": {
    "addr:full":"21 Franklin Ave Nutley NJ 07110",
    "addr:housenumber":"21",
    "addr:postcode":"07110",
    "addr:street":"Franklin Ave",
    "iso:country":"US",
    "sg:address":"21 Franklin Ave",
    "sg:city":"Nutley",
    "sg:classifiers":[
        {
            "category":"Personal",
            "type":"Services"
        }
    ],
    "sg:phone":"+1   ",
    "sg:postcode":"07110",
    "sg:province":"NJ",
    "wof:name":"Lisa Maries Day Spa",
    "wof:placetype":"venue"
},
  "geometry": {"coordinates":[-74.166572,40.808631],"type":"Point"}
}