{
  "type": "Feature",
  "properties": {
    "iso:country":"US",
    "sg:address":"26 Willow Cir",
    "sg:city":"Hamburg",
    "sg:classifiers":[
        {
            "category":"Manufacturing",
            "subcategory":"Electronics",
            "type":"Manufacturing & Wholesale Goods"
        }
    ],
    "sg:phone":"+1 973 827 7871",
    "sg:postcode":"07419",
    "sg:province":"NJ",
    "sg:tags":[
        "equipment",
        "telephone",
        "system"
    ],
    "sg:website":"www.spectralink.com",
    "wof:name":"Spectra Link Corp",
    "wof:placetype":"venue"
},
  "geometry": {"coordinates":[-74.57737299999999,41.157467],"type":"Point"}
}