{
  "type": "Feature",
  "properties": {
    "iso:country":"US",
    "sg:address":"116 Walker Ave",
    "sg:city":"West Berlin",
    "sg:classifiers":[
        {
            "category":"Shopping",
            "subcategory":"Computers & Home Electronics",
            "type":"Retail Goods"
        }
    ],
    "sg:phone":"+1 856 719 8805",
    "sg:postcode":"08091",
    "sg:province":"NJ",
    "sg:tags":[
        "game",
        "video",
        "software"
    ],
    "wof:name":"Gamestop",
    "wof:placetype":"venue"
},
  "geometry": {"coordinates":[-74.93986700000001,39.807222],"type":"Point"}
}