{
  "type": "Feature",
  "properties": {
    "addr:full":"185 12th St Jersey City NJ 07310",
    "addr:housenumber":"185",
    "addr:postcode":"07310",
    "addr:street":"12Th St",
    "iso:country":"US",
    "sg:address":"185 12th St",
    "sg:city":"Jersey City",
    "sg:classifiers":[
        {
            "category":"Fast Food",
            "type":"Food & Drink"
        }
    ],
    "sg:phone":"+1 201 656 2354",
    "sg:postcode":"07310",
    "sg:province":"NJ",
    "sg:website":"www.burgerking.com",
    "wof:name":"Burger King",
    "wof:placetype":"venue"
},
  "geometry": {"coordinates":[-74.04100200000001,40.729685],"type":"Point"}
}