{
  "type": "Feature",
  "properties": {
    "addr:full":"85 Route 17 S Woodbridge NJ 07095",
    "addr:housenumber":"85",
    "addr:postcode":"07095",
    "addr:street":"Route 17 S",
    "iso:country":"US",
    "sg:address":"85 Route 17 S",
    "sg:city":"Woodbridge",
    "sg:classifiers":[
        {
            "category":"Autos & Motor Vehicles",
            "subcategory":"Automobile Sales",
            "type":"Retail Goods"
        }
    ],
    "sg:phone":"+1 201 939 9400",
    "sg:postcode":"07095",
    "sg:province":"NJ",
    "sg:tags":[
        "car"
    ],
    "wof:name":"East Coast Toyota Mazda",
    "wof:placetype":"venue"
},
  "geometry": {"coordinates":[-74.28780399999999,40.557999],"type":"Point"}
}