{
  "type": "Feature",
  "properties": {
    "iso:country":"US",
    "sg:address":"254 Elmwood Ave",
    "sg:city":"Union",
    "sg:classifiers":[
        {
            "category":"Manufacturing",
            "subcategory":"Tools & Machinery",
            "type":"Manufacturing & Wholesale Goods"
        }
    ],
    "sg:phone":"+1 908 687 4161",
    "sg:postcode":"07083",
    "sg:province":"NJ",
    "sg:tags":[
        "machine",
        "shop",
        "job"
    ],
    "wof:name":"Fravin Machine & Tool Co Inc",
    "wof:placetype":"venue"
},
  "geometry": {"coordinates":[-74.282741,40.699324],"type":"Point"}
}