{
  "type": "Feature",
  "properties": {
    "addr:full":"473 Barbertown Point Breeze Rd Frenchtown NJ 08825",
    "addr:housenumber":"473",
    "addr:postcode":"08825",
    "addr:street":"Barbertown Point Breeze Rd",
    "iso:country":"US",
    "sg:address":"473 Barbertown Point Breeze Rd",
    "sg:city":"Frenchtown",
    "sg:classifiers":[
        {
            "category":"Social Services",
            "type":"Services"
        }
    ],
    "sg:phone":"+1   ",
    "sg:postcode":"08825",
    "sg:province":"NJ",
    "wof:name":"ARC of Hunterdon County",
    "wof:placetype":"venue"
},
  "geometry": {"coordinates":[-74.97071800000001,40.502181],"type":"Point"}
}