{
  "type": "Feature",
  "properties": {
    "addr:full":"6501 Park Ave West New York NJ 07093",
    "addr:housenumber":"6501",
    "addr:postcode":"07093",
    "addr:street":"Park Ave West",
    "iso:country":"US",
    "sg:address":"6501 Park Ave",
    "sg:city":"West New York",
    "sg:classifiers":[
        {
            "category":"Food & Beverages",
            "subcategory":"Groceries & Convenience Stores",
            "type":"Retail Goods"
        }
    ],
    "sg:phone":"+1   ",
    "sg:postcode":"07093",
    "sg:province":"NJ",
    "wof:name":"Lucky Mini Market",
    "wof:placetype":"venue"
},
  "geometry": {"coordinates":[-74.005205,40.790081],"type":"Point"}
}