{
  "type": "Feature",
  "properties": {
    "iso:country":"US",
    "sg:address":"205 Rutgers St",
    "sg:city":"Maplewood",
    "sg:classifiers":[
        {
            "category":"Organizations",
            "subcategory":"Professional Association",
            "type":"Services"
        }
    ],
    "sg:phone":"+1 973 763 8116",
    "sg:postcode":"07040",
    "sg:province":"NJ",
    "wof:name":"Asssociation-Retarded Citizens",
    "wof:placetype":"venue"
},
  "geometry": {"coordinates":[-74.263138,40.716517],"type":"Point"}
}