{
  "type": "Feature",
  "properties": {
    "addr:full":"18 Mill St Lodi NJ 07644",
    "addr:housenumber":"18",
    "addr:postcode":"07644",
    "addr:street":"Mill St",
    "iso:country":"US",
    "sg:address":"18 Mill St",
    "sg:city":"Lodi",
    "sg:classifiers":[
        {
            "category":"Manufacturing",
            "subcategory":"Chemicals & Compounds",
            "type":"Manufacturing & Wholesale Goods"
        }
    ],
    "sg:phone":"+1 973 473 2376",
    "sg:postcode":"07644",
    "sg:province":"NJ",
    "sg:tags":[
        "paint",
        "varnish",
        "allied",
        "product"
    ],
    "wof:name":"Dux Paints & Chemicals Inc",
    "wof:placetype":"venue"
},
  "geometry": {"coordinates":[-74.075833,40.881877],"type":"Point"}
}