{
  "type": "Feature",
  "properties": {
    "iso:country":"US",
    "sg:address":"393 Baldwin Ave",
    "sg:city":"Jersey City",
    "sg:classifiers":[
        {
            "category":"Retail",
            "subcategory":"Repair Shop",
            "type":"Services"
        },
        {
            "category":"Building & Trades",
            "subcategory":"Construction",
            "type":"Services"
        }
    ],
    "sg:phone":"+1 201 332 1414",
    "sg:postcode":"07306",
    "sg:province":"NJ",
    "sg:tags":[
        "welding",
        "contractor"
    ],
    "wof:name":"Commercial Iron Company",
    "wof:placetype":"venue"
},
  "geometry": {"coordinates":[-74.053483,40.734619],"type":"Point"}
}