{
  "type": "Feature",
  "properties": {
    "addr:full":"64 E Washington Ave Pleasantville NJ 08232",
    "addr:housenumber":"64",
    "addr:postcode":"08232",
    "addr:street":"E Washington Ave",
    "iso:country":"US",
    "sg:address":"64 E Washington Ave",
    "sg:city":"Pleasantville",
    "sg:classifiers":[
        {
            "category":"Communications",
            "subcategory":"Film & Video Production",
            "type":"Services"
        }
    ],
    "sg:phone":"+1 609 641 1466",
    "sg:postcode":"08232",
    "sg:province":"NJ",
    "sg:tags":[
        "motion",
        "picture"
    ],
    "wof:name":"S Brook",
    "wof:placetype":"venue"
},
  "geometry": {"coordinates":[-74.520225,39.390985],"type":"Point"}
}