{
  "type": "Feature",
  "properties": {
    "iso:country":"US",
    "sg:address":"2101 Bridge Ave",
    "sg:city":"Point Pleasant Beach",
    "sg:classifiers":[
        {
            "category":"Retail",
            "subcategory":"Auto Repair",
            "type":"Services"
        }
    ],
    "sg:phone":"+1 732 899 3023",
    "sg:postcode":"08742",
    "sg:province":"NJ",
    "sg:tags":[
        "automotive"
    ],
    "wof:name":"Service Hollywood Corp",
    "wof:placetype":"venue"
},
  "geometry": {"coordinates":[-74.063692,40.071186],"type":"Point"}
}