{
  "type": "Feature",
  "properties": {
    "iso:country":"US",
    "sg:address":"512 E Broad St",
    "sg:city":"Westfield",
    "sg:classifiers":[
        {
            "category":"Health Services",
            "subcategory":"Doctor",
            "type":"Services"
        }
    ],
    "sg:phone":"+1   ",
    "sg:postcode":"07090",
    "sg:province":"NJ",
    "sg:tags":[
        "medical"
    ],
    "wof:name":"Richard W Oliver-Smith MD",
    "wof:placetype":"venue"
},
  "geometry": {"coordinates":[-74.343807,40.655653],"type":"Point"}
}