{
  "type": "Feature",
  "properties": {
    "addr:full":"2 Berlin Rd Clementon NJ 08021",
    "addr:housenumber":"2",
    "addr:postcode":"08021",
    "addr:street":"Berlin Rd",
    "iso:country":"US",
    "sg:address":"2 Berlin Rd",
    "sg:city":"Clementon",
    "sg:classifiers":[
        {
            "category":"Shopping",
            "subcategory":"Pharmacy",
            "type":"Retail Goods"
        }
    ],
    "sg:phone":"+1   ",
    "sg:postcode":"08021",
    "sg:province":"NJ",
    "wof:name":"CVS",
    "wof:placetype":"venue"
},
  "geometry": {"coordinates":[-74.98872799999999,39.8054],"type":"Point"}
}