{
  "type": "Feature",
  "properties": {
    "addr:full":"70 Passaic St Wood Ridge NJ 07075",
    "addr:housenumber":"70",
    "addr:postcode":"07075",
    "addr:street":"Passaic St",
    "iso:country":"US",
    "sg:address":"70 Passaic St",
    "sg:city":"Wood Ridge",
    "sg:classifiers":[
        {
            "category":"Professional",
            "type":"Services"
        }
    ],
    "sg:phone":"+1 212 532 0309",
    "sg:postcode":"07075",
    "sg:province":"NJ",
    "sg:tags":[
        "establishment"
    ],
    "wof:name":"Midwest Orient NY LTD",
    "wof:placetype":"venue"
},
  "geometry": {"coordinates":[-74.09098899999999,40.863642],"type":"Point"}
}