{
  "type": "Feature",
  "properties": {
    "addr:full":"332 Union Hill Rd Englishtown NJ 07726",
    "addr:housenumber":"332",
    "addr:postcode":"07726",
    "addr:street":"Union Hill Rd",
    "iso:country":"US",
    "sg:address":"332 Union Hill Rd",
    "sg:city":"Englishtown",
    "sg:classifiers":[
        {
            "category":"Personal",
            "subcategory":"Beauty Salon",
            "type":"Services"
        }
    ],
    "sg:phone":"+1 732 972 7766",
    "sg:postcode":"07726",
    "sg:province":"NJ",
    "wof:name":"Tangles Hair Studio",
    "wof:placetype":"venue"
},
  "geometry": {"coordinates":[-74.32269700000001,40.334717],"type":"Point"}
}