{
  "type": "Feature",
  "properties": {
    "iso:country":"US",
    "sg:address":"6028 Broadway",
    "sg:city":"West New York",
    "sg:classifiers":[
        {
            "category":"Education",
            "subcategory":"School",
            "type":"Public Place"
        }
    ],
    "sg:phone":"+1 201 330 1000",
    "sg:postcode":"07093",
    "sg:province":"NJ",
    "sg:tags":[
        "elementary",
        "secondary"
    ],
    "wof:name":"West New York Board Education",
    "wof:placetype":"venue"
},
  "geometry": {"coordinates":[-74.010133,40.787313],"type":"Point"}
}