{
  "type": "Feature",
  "properties": {
    "addr:full":"1252 State Rte 166 Toms River NJ 08753",
    "addr:housenumber":"1252",
    "addr:postcode":"08753",
    "addr:street":"State Rte 166",
    "iso:country":"US",
    "sg:address":"1252 State Rte 166",
    "sg:city":"Toms River",
    "sg:classifiers":[
        {
            "category":"Utilities",
            "subcategory":"Mobile Phone",
            "type":"Services"
        }
    ],
    "sg:phone":"+1 732 505 0081",
    "sg:postcode":"08753",
    "sg:province":"NJ",
    "sg:tags":[
        "communication",
        "radiotelephone"
    ],
    "wof:name":"Bell Wireless",
    "wof:placetype":"venue"
},
  "geometry": {"coordinates":[-74.210536,39.986145],"type":"Point"}
}