{
  "type": "Feature",
  "properties": {
    "addr:full":"346 Willow St Bordentown NJ 08505",
    "addr:housenumber":"346",
    "addr:postcode":"08505",
    "addr:street":"Willow St",
    "iso:country":"US",
    "sg:address":"346 Willow St",
    "sg:city":"Bordentown",
    "sg:classifiers":[
        {
            "category":"Building & Trades",
            "subcategory":"Construction",
            "type":"Services"
        }
    ],
    "sg:phone":"+1 609 324 8221",
    "sg:postcode":"08505",
    "sg:province":"NJ",
    "sg:tags":[
        "hanging",
        "contractor"
    ],
    "wof:name":"Willow Street Painting",
    "wof:placetype":"venue"
},
  "geometry": {"coordinates":[-74.712457,40.143763],"type":"Point"}
}