{
  "type": "Feature",
  "properties": {
    "iso:country":"US",
    "sg:address":"32 Mabey Ln",
    "sg:city":"Butler",
    "sg:classifiers":[
        {
            "category":"Building & Trades",
            "subcategory":"Landscaping Services",
            "type":"Services"
        }
    ],
    "sg:phone":"+1 973 492 3245",
    "sg:postcode":"07405",
    "sg:province":"NJ",
    "wof:name":"Akers Landscaping",
    "wof:placetype":"venue"
},
  "geometry": {"coordinates":[-74.340283,40.995686],"type":"Point"}
}