{
  "type": "Feature",
  "properties": {
    "addr:full":"493 Springfield Ave Berkeley Heights NJ 07922",
    "addr:housenumber":"493",
    "addr:postcode":"07922",
    "addr:street":"Springfield Ave",
    "iso:country":"US",
    "sg:address":"493 Springfield Ave",
    "sg:city":"Berkeley Heights",
    "sg:classifiers":[
        {
            "category":"Personal",
            "subcategory":"Barber",
            "type":"Services"
        }
    ],
    "sg:phone":"+1 908 464 1166",
    "sg:postcode":"07922",
    "sg:province":"NJ",
    "wof:name":"Berkeley Barber Shop",
    "wof:placetype":"venue"
},
  "geometry": {"coordinates":[-74.441597,40.683701],"type":"Point"}
}