{
  "type": "Feature",
  "properties": {
    "addr:full":"1500 Almonesson Rd Woodbury NJ 08096",
    "addr:housenumber":"1500",
    "addr:postcode":"08096",
    "addr:street":"Almonesson Rd",
    "iso:country":"US",
    "sg:address":"1500 Almonesson Rd",
    "sg:city":"Woodbury",
    "sg:classifiers":[
        {
            "category":"Manufacturing",
            "subcategory":"Food",
            "type":"Manufacturing & Wholesale Goods"
        },
        {
            "category":"Restaurant",
            "type":"Food & Drink"
        },
        {
            "category":"Ice Cream",
            "type":"Food & Drink"
        }
    ],
    "sg:phone":"+1 856 232 2223",
    "sg:postcode":"08096",
    "sg:province":"NJ",
    "sg:tags":[
        "frozen",
        "dessert",
        "desserts-manufacturers",
        "distributor"
    ],
    "wof:name":"Maggie Moo's",
    "wof:placetype":"venue"
},
  "geometry": {"coordinates":[-75.099602,39.8241],"type":"Point"}
}