{
  "type": "Feature",
  "properties": {
    "addr:full":"215 S Shore Rd Marmora NJ 08223",
    "addr:housenumber":"215",
    "addr:postcode":"08223",
    "addr:street":"S Shore Rd",
    "iso:country":"US",
    "sg:address":"215 S Shore Rd",
    "sg:city":"Marmora",
    "sg:classifiers":[
        {
            "category":"Professional",
            "subcategory":"Computer Services",
            "type":"Services"
        }
    ],
    "sg:phone":"+1 609 390 9775",
    "sg:postcode":"08223",
    "sg:province":"NJ",
    "sg:tags":[
        "datum"
    ],
    "wof:name":"ADP",
    "wof:placetype":"venue"
},
  "geometry": {"coordinates":[-74.654048,39.25861],"type":"Point"}
}