{
  "type": "Feature",
  "properties": {
    "addr:full":"180 Ramapo Valley Rd Oakland NJ 07436",
    "addr:housenumber":"180",
    "addr:postcode":"07436",
    "addr:street":"Ramapo Valley Rd",
    "iso:country":"US",
    "sg:address":"180 Ramapo Valley Rd",
    "sg:city":"Oakland",
    "sg:classifiers":[
        {
            "category":"Health Services",
            "subcategory":"Dentist",
            "type":"Services"
        }
    ],
    "sg:phone":"+1 201 337 3797",
    "sg:postcode":"07436",
    "sg:province":"NJ",
    "wof:name":"Bradley Sean E DMD",
    "wof:placetype":"venue"
},
  "geometry": {"coordinates":[-74.25299800000001,41.015202],"type":"Point"}
}