{
  "type": "Feature",
  "properties": {
    "iso:country":"US",
    "sg:address":"65 US Highway 46",
    "sg:city":"Pine Brook",
    "sg:classifiers":[
        {
            "category":"Autos & Motor Vehicles",
            "subcategory":"Automobile Sales",
            "type":"Retail Goods"
        }
    ],
    "sg:phone":"+1 973 227 3100",
    "sg:postcode":"07058",
    "sg:province":"NJ",
    "sg:tags":[
        "car"
    ],
    "wof:name":"Kevah Konner Inc",
    "wof:placetype":"venue"
},
  "geometry": {"coordinates":[-74.32648500000001,40.859195],"type":"Point"}
}