{
  "type": "Feature",
  "properties": {
    "iso:country":"US",
    "sg:address":"1043 Centerton Rd",
    "sg:city":"Elmer",
    "sg:classifiers":[
        {
            "category":"Wholesale",
            "subcategory":"Chemicals & Plastics",
            "type":"Manufacturing & Wholesale Goods"
        }
    ],
    "sg:phone":"+1 856 358 7258",
    "sg:postcode":"08318",
    "sg:province":"NJ",
    "wof:name":"Chem Plus",
    "wof:placetype":"venue"
},
  "geometry": {"coordinates":[-75.155417,39.551483],"type":"Point"}
}