{
  "type": "Feature",
  "properties": {
    "iso:country":"US",
    "sg:address":"34 Wagner Ave",
    "sg:city":"Wallington",
    "sg:classifiers":[
        {
            "category":"Professional",
            "subcategory":"Computer Services",
            "type":"Services"
        }
    ],
    "sg:phone":"+1 973 614 0335",
    "sg:postcode":"07057",
    "sg:province":"NJ",
    "sg:tags":[
        "programing",
        "custom"
    ],
    "wof:name":"Jamel Resources",
    "wof:placetype":"venue"
},
  "geometry": {"coordinates":[-74.100171,40.854133],"type":"Point"}
}