{
  "type": "Feature",
  "properties": {
    "addr:full":"618 Cedar St Boonton NJ 07005",
    "addr:housenumber":"618",
    "addr:postcode":"07005",
    "addr:street":"Cedar St",
    "iso:country":"US",
    "sg:address":"618 Cedar St",
    "sg:city":"Boonton",
    "sg:classifiers":[
        {
            "category":"Local Transit",
            "type":"Transportation"
        }
    ],
    "sg:phone":"+1 973 263 1315",
    "sg:postcode":"07005",
    "sg:province":"NJ",
    "sg:tags":[
        "passenger"
    ],
    "wof:name":"A1 Airport Corporate Limo",
    "wof:placetype":"venue"
},
  "geometry": {"coordinates":[-74.410211,40.907862],"type":"Point"}
}