{
  "type": "Feature",
  "properties": {
    "addr:full":"241 Warrenville Rd Dunellen NJ 08812",
    "addr:housenumber":"241",
    "addr:postcode":"08812",
    "addr:street":"Warrenville Rd",
    "iso:country":"US",
    "sg:address":"241 Warrenville Rd",
    "sg:city":"Dunellen",
    "sg:classifiers":[
        {
            "category":"Professional",
            "subcategory":"Detective & Security Services",
            "type":"Services"
        }
    ],
    "sg:phone":"+1 732 926 1224",
    "sg:postcode":"08812",
    "sg:province":"NJ",
    "sg:tags":[
        "car"
    ],
    "wof:name":"Gj Millman Inc",
    "wof:placetype":"venue"
},
  "geometry": {"coordinates":[-74.49012399999999,40.595893],"type":"Point"}
}