{
  "type": "Feature",
  "properties": {
    "addr:full":"226 North Ave W Westfield NJ 07090",
    "addr:housenumber":"226",
    "addr:postcode":"07090",
    "addr:street":"North Ave W",
    "iso:country":"US",
    "sg:address":"226 North Ave W",
    "sg:city":"Westfield",
    "sg:classifiers":[
        {
            "category":"Shopping",
            "subcategory":"Jewelry",
            "type":"Retail Goods"
        }
    ],
    "sg:phone":"+1 908 233 8811",
    "sg:postcode":"07090",
    "sg:province":"NJ",
    "sg:tags":[
        "jeweler"
    ],
    "wof:name":"Michael Kohn Jewelers",
    "wof:placetype":"venue"
},
  "geometry": {"coordinates":[-74.347522,40.650156],"type":"Point"}
}