{
  "type": "Feature",
  "properties": {
    "addr:full":"45 Campus Dr Edison NJ 08837",
    "addr:housenumber":"45",
    "addr:postcode":"08837",
    "addr:street":"Campus Dr",
    "iso:country":"US",
    "sg:address":"45 Campus Dr",
    "sg:city":"Edison",
    "sg:classifiers":[
        {
            "category":"Building & Trades",
            "subcategory":"Cleaning & Sanitation",
            "type":"Services"
        }
    ],
    "sg:phone":"+1   ",
    "sg:postcode":"08837",
    "sg:province":"NJ",
    "sg:tags":[
        "maintenance"
    ],
    "wof:name":"Environmental Cleaning Systems",
    "wof:placetype":"venue"
},
  "geometry": {"coordinates":[-74.34210899999999,40.509976],"type":"Point"}
}