{
  "type": "Feature",
  "properties": {
    "addr:full":"791 S Main Rd Vineland NJ 08360",
    "addr:housenumber":"791",
    "addr:postcode":"08360",
    "addr:street":"S Main Rd",
    "iso:country":"US",
    "sg:address":"791 S Main Rd",
    "sg:city":"Vineland",
    "sg:classifiers":[
        {
            "category":"Real Estate",
            "subcategory":"Surveying",
            "type":"Services"
        }
    ],
    "sg:phone":"+1   ",
    "sg:postcode":"08360",
    "sg:province":"NJ",
    "wof:name":"Reale Associates",
    "wof:placetype":"venue"
},
  "geometry": {"coordinates":[-75.002126,39.475041],"type":"Point"}
}