{
  "type": "Feature",
  "properties": {
    "addr:full":"38 Lakeview Dr Westwood NJ 07675",
    "addr:housenumber":"38",
    "addr:postcode":"07675",
    "addr:street":"Lakeview Dr",
    "iso:country":"US",
    "sg:address":"38 Lakeview Dr",
    "sg:city":"Westwood",
    "sg:classifiers":[
        {
            "category":"Professional",
            "subcategory":"Lawyer & Legal Services",
            "type":"Services"
        }
    ],
    "sg:phone":"+1 201 934 4204",
    "sg:postcode":"07675",
    "sg:province":"NJ",
    "wof:name":"Richard Ledingham",
    "wof:placetype":"venue"
},
  "geometry": {"coordinates":[-73.986806,41.014727],"type":"Point"}
}