{
  "type": "Feature",
  "properties": {
    "iso:country":"US",
    "sg:address":"239 Lindberg Pl",
    "sg:city":"Paterson",
    "sg:classifiers":[
        {
            "category":"Real Estate",
            "subcategory":"Real Estate Agent",
            "type":"Services"
        }
    ],
    "sg:phone":"+1   ",
    "sg:postcode":"07503",
    "sg:province":"NJ",
    "sg:tags":[
        "manager"
    ],
    "wof:name":"Madison Beckwith Maintenance",
    "wof:placetype":"venue"
},
  "geometry": {"coordinates":[-74.160253,40.904156],"type":"Point"}
}