{
  "type": "Feature",
  "properties": {
    "iso:country":"US",
    "sg:address":"18 Archertown Rd",
    "sg:city":"New Egypt",
    "sg:classifiers":[
        {
            "category":"Retail",
            "subcategory":"Animal Services",
            "type":"Services"
        }
    ],
    "sg:phone":"+1 609 758 8881",
    "sg:postcode":"08533",
    "sg:province":"NJ",
    "wof:name":"Kentuckiana Farms",
    "wof:placetype":"venue"
},
  "geometry": {"coordinates":[-74.51091599999999,40.066313],"type":"Point"}
}