{
  "type": "Feature",
  "properties": {
    "iso:country":"US",
    "sg:address":"219 Richey Ave",
    "sg:city":"Oaklyn",
    "sg:classifiers":[
        {
            "category":"Professional",
            "subcategory":"Management & Consulting",
            "type":"Services"
        }
    ],
    "sg:phone":"+1   ",
    "sg:postcode":"08107",
    "sg:province":"NJ",
    "sg:tags":[
        "retail",
        "direct",
        "sales"
    ],
    "wof:name":"Artemisia",
    "wof:placetype":"venue"
},
  "geometry": {"coordinates":[-75.087857,39.915094],"type":"Point"}
}