{
  "type": "Feature",
  "properties": {
    "iso:country":"US",
    "sg:address":"23 Ellwood Rd",
    "sg:city":"East Brunswick",
    "sg:classifiers":[
        {
            "category":"Building & Trades",
            "subcategory":"Landscaping Services",
            "type":"Services"
        }
    ],
    "sg:phone":"+1 732 613 9331",
    "sg:postcode":"08816",
    "sg:province":"NJ",
    "sg:tags":[
        "landscape",
        "contractor"
    ],
    "wof:name":"Vonch's Landscaping & Lawn Svc",
    "wof:placetype":"venue"
},
  "geometry": {"coordinates":[-74.402295,40.437663],"type":"Point"}
}