{
  "type": "Feature",
  "properties": {
    "addr:full":"97 Deerfield Rd Caldwell NJ 07006",
    "addr:housenumber":"97",
    "addr:postcode":"07006",
    "addr:street":"Deerfield Rd",
    "iso:country":"US",
    "sg:address":"97 Deerfield Rd",
    "sg:city":"Caldwell",
    "sg:classifiers":[
        {
            "category":"Professional",
            "subcategory":"Accounting & Tax Preparation",
            "type":"Services"
        }
    ],
    "sg:phone":"+1   ",
    "sg:postcode":"07006",
    "sg:province":"NJ",
    "wof:name":"Linda A Dalla Riva CPA PA",
    "wof:placetype":"venue"
},
  "geometry": {"coordinates":[-74.296639,40.834461],"type":"Point"}
}