{
  "type": "Feature",
  "properties": {
    "iso:country":"US",
    "sg:address":"821 State Rte 33",
    "sg:city":"Freehold",
    "sg:classifiers":[
        {
            "category":"Wholesale",
            "subcategory":"Durable Goods & Equipment",
            "type":"Manufacturing & Wholesale Goods"
        }
    ],
    "sg:phone":"+1 732 462 6501",
    "sg:postcode":"07728",
    "sg:province":"NJ",
    "sg:tags":[
        "instrument",
        "scientific",
        "apparatus"
    ],
    "wof:name":"Scidynamics",
    "wof:placetype":"venue"
},
  "geometry": {"coordinates":[-74.219132,40.233717],"type":"Point"}
}