{
  "type": "Feature",
  "properties": {
    "iso:country":"US",
    "sg:address":"219 Railroad Ave",
    "sg:city":"West Creek",
    "sg:classifiers":[
        {
            "category":"Health Services",
            "subcategory":"Health Practitioner",
            "type":"Services"
        }
    ],
    "sg:phone":"+1 609 296 3660",
    "sg:postcode":"08092",
    "sg:province":"NJ",
    "wof:name":"West Creek Nutrition",
    "wof:placetype":"venue"
},
  "geometry": {"coordinates":[-74.31108999999999,39.637305],"type":"Point"}
}