{
  "type": "Feature",
  "properties": {
    "addr:full":"1117 New York Ave Union City NJ 07087",
    "addr:housenumber":"1117",
    "addr:postcode":"07087",
    "addr:street":"New York Ave",
    "iso:country":"US",
    "sg:address":"1117 New York Ave",
    "sg:city":"Union City",
    "sg:classifiers":[
        {
            "category":"Travel",
            "subcategory":"Travel Agent",
            "type":"Entertainment"
        }
    ],
    "sg:phone":"+1 201 866 5339",
    "sg:postcode":"07087",
    "sg:province":"NJ",
    "sg:tags":[
        "agency",
        "bureau"
    ],
    "wof:name":"Easy Travel Inc",
    "wof:placetype":"venue"
},
  "geometry": {"coordinates":[-74.036503,40.758946],"type":"Point"}
}