{
  "type": "Feature",
  "properties": {
    "iso:country":"US",
    "sg:address":"201 N New Rd",
    "sg:city":"Pleasantville",
    "sg:classifiers":[
        {
            "category":"Building & Trades",
            "subcategory":"Construction",
            "type":"Services"
        }
    ],
    "sg:phone":"+1 609 677 8766",
    "sg:postcode":"08232",
    "sg:province":"NJ",
    "sg:tags":[
        "house"
    ],
    "wof:name":"Gonzo Construction",
    "wof:placetype":"venue"
},
  "geometry": {"coordinates":[-74.52628199999999,39.398604],"type":"Point"}
}