{
  "type": "Feature",
  "properties": {
    "iso:country":"US",
    "sg:address":"85 Custer Ave",
    "sg:city":"Newark",
    "sg:classifiers":[
        {
            "category":"Professional",
            "subcategory":"Management & Consulting",
            "type":"Services"
        }
    ],
    "sg:phone":"+1 973 623 6221",
    "sg:postcode":"07112",
    "sg:province":"NJ",
    "sg:tags":[
        "consultant",
        "educational"
    ],
    "wof:name":"International Black Women's",
    "wof:placetype":"venue"
},
  "geometry": {"coordinates":[-74.20140000000001,40.709879],"type":"Point"}
}