{
  "type": "Feature",
  "properties": {
    "iso:country":"US",
    "sg:address":"510 E Main St",
    "sg:city":"Denville",
    "sg:classifiers":[
        {
            "category":"Retail",
            "subcategory":"Laundry & Dry Cleaning",
            "type":"Services"
        }
    ],
    "sg:phone":"+1 973 664 0999",
    "sg:postcode":"07834",
    "sg:province":"NJ",
    "sg:tags":[
        "cleaners",
        "plant",
        "drycleaning"
    ],
    "wof:name":"Magic Touch Cleaners",
    "wof:placetype":"venue"
},
  "geometry": {"coordinates":[-74.479767,40.879498],"type":"Point"}
}