{
  "type": "Feature",
  "properties": {
    "addr:full":"139 E Faunce Landing Rd Absecon NJ 08201",
    "addr:housenumber":"139",
    "addr:postcode":"08201",
    "addr:street":"E Faunce Landing Rd",
    "iso:country":"US",
    "sg:address":"139 E Faunce Landing Rd",
    "sg:city":"Absecon",
    "sg:classifiers":[
        {
            "category":"Recreation",
            "subcategory":"Marina",
            "type":"Entertainment"
        }
    ],
    "sg:phone":"+1 609 272 9252",
    "sg:postcode":"08201",
    "sg:province":"NJ",
    "sg:tags":[
        "operation"
    ],
    "wof:name":"Up The Creek Marina",
    "wof:placetype":"venue"
},
  "geometry": {"coordinates":[-74.49515100000001,39.428257],"type":"Point"}
}