{
  "type": "Feature",
  "properties": {
    "iso:country":"US",
    "sg:address":"734 Willow Ave",
    "sg:city":"Hoboken",
    "sg:classifiers":[
        {
            "category":"Bars & Pubs",
            "type":"Food & Drink"
        },
        {
            "category":"Restaurant",
            "type":"Food & Drink"
        }
    ],
    "sg:menulink":"http://www.allmenus.com/nj/hoboken/273659-rogos/menu/",
    "sg:phone":"+1 201 217 1512",
    "sg:postcode":"07030",
    "sg:province":"NJ",
    "sg:tags":[
        "american"
    ],
    "wof:name":"Rogo's",
    "wof:placetype":"venue"
},
  "geometry": {"coordinates":[-74.032282,40.745882],"type":"Point"}
}