{
  "type": "Feature",
  "properties": {
    "iso:country":"US",
    "sg:address":"48 Danielle Ct",
    "sg:city":"Trenton",
    "sg:classifiers":[
        {
            "category":"Professional",
            "subcategory":"Advertising",
            "type":"Services"
        }
    ],
    "sg:phone":"+1 609 219 0800",
    "sg:postcode":"08648",
    "sg:province":"NJ",
    "sg:tags":[
        "agency"
    ],
    "wof:name":"Dre F/X",
    "wof:placetype":"venue"
},
  "geometry": {"coordinates":[-74.747749,40.30485],"type":"Point"}
}