{
  "type": "Feature",
  "properties": {
    "iso:country":"US",
    "sg:address":"844 Monmouth St",
    "sg:city":"Gloucester City",
    "sg:classifiers":[
        {
            "category":"Building & Trades",
            "subcategory":"Construction",
            "type":"Services"
        }
    ],
    "sg:phone":"+1 609 714 8673",
    "sg:postcode":"08030",
    "sg:province":"NJ",
    "sg:tags":[
        "hanging",
        "contractor"
    ],
    "wof:name":"Painting By Michael",
    "wof:placetype":"venue"
},
  "geometry": {"coordinates":[-75.117327,39.894901],"type":"Point"}
}