{
  "type": "Feature",
  "properties": {
    "iso:country":"US",
    "sg:address":"175 Kearny Ave",
    "sg:city":"Perth Amboy",
    "sg:classifiers":[
        {
            "category":"Building & Trades",
            "subcategory":"Construction",
            "type":"Services"
        }
    ],
    "sg:phone":"+1 732 376 0862",
    "sg:postcode":"08861",
    "sg:province":"NJ",
    "sg:tags":[
        "house"
    ],
    "wof:name":"Inter Framing General Cnstr",
    "wof:placetype":"venue"
},
  "geometry": {"coordinates":[-74.26836,40.504703],"type":"Point"}
}