{
  "type": "Feature",
  "properties": {
    "addr:full":"994 Rahway Ave Avenel NJ 07001",
    "addr:housenumber":"994",
    "addr:postcode":"07001",
    "addr:street":"Rahway Ave",
    "iso:country":"US",
    "sg:address":"994 Rahway Ave",
    "sg:city":"Avenel",
    "sg:classifiers":[
        {
            "category":"Shopping",
            "subcategory":"Pharmacy",
            "type":"Retail Goods"
        }
    ],
    "sg:phone":"+1 732 634 1914",
    "sg:postcode":"07001",
    "sg:province":"NJ",
    "sg:tags":[
        "drugstore",
        "store",
        "drug"
    ],
    "sg:website":"www.avenelpharmacy.com",
    "wof:name":"Avenel Pharmacy & Surgical",
    "wof:placetype":"venue"
},
  "geometry": {"coordinates":[-74.269699,40.5755],"type":"Point"}
}