{
  "type": "Feature",
  "properties": {
    "iso:country":"US",
    "sg:address":"343 Janes Chapel Rd",
    "sg:city":"Oxford",
    "sg:classifiers":[
        {
            "category":"Building & Trades",
            "subcategory":"Construction",
            "type":"Services"
        }
    ],
    "sg:phone":"+1 908 637 6396",
    "sg:postcode":"07863",
    "sg:province":"NJ",
    "sg:tags":[
        "residential",
        "contractor"
    ],
    "wof:name":"Best Trim",
    "wof:placetype":"venue"
},
  "geometry": {"coordinates":[-74.923097,40.83958],"type":"Point"}
}