{
  "type": "Feature",
  "properties": {
    "addr:full":"4054 Quakerbridge Rd Trenton NJ 08619",
    "addr:housenumber":"4054",
    "addr:postcode":"08619",
    "addr:street":"Quakerbridge Rd",
    "iso:country":"US",
    "sg:address":"4054 Quakerbridge Rd",
    "sg:city":"Trenton",
    "sg:classifiers":[
        {
            "category":"Recreation",
            "type":"Entertainment"
        }
    ],
    "sg:phone":"+1 609 587 6644",
    "sg:postcode":"08619",
    "sg:province":"NJ",
    "sg:tags":[
        "martial",
        "arts",
        "school"
    ],
    "wof:name":"Northast Acdemy of Mrtial Arts",
    "wof:placetype":"venue"
},
  "geometry": {"coordinates":[-74.669635,40.276676],"type":"Point"}
}