{
  "type": "Feature",
  "properties": {
    "iso:country":"US",
    "sg:address":"1877 Springfield Ave",
    "sg:city":"Maplewood",
    "sg:classifiers":[
        {
            "category":"Food & Beverages",
            "subcategory":"Specialty",
            "type":"Retail Goods"
        }
    ],
    "sg:phone":"+1 973 378 3663",
    "sg:postcode":"07040",
    "sg:province":"NJ",
    "sg:tags":[
        "health",
        "diet"
    ],
    "wof:name":"Spring Fields Natural Market",
    "wof:placetype":"venue"
},
  "geometry": {"coordinates":[-74.269919,40.720603],"type":"Point"}
}