{
  "type": "Feature",
  "properties": {
    "addr:full":"824 Radio Rd Little Egg Hbr NJ 08087",
    "addr:housenumber":"824",
    "addr:postcode":"08087",
    "addr:street":"Radio Rd",
    "iso:country":"US",
    "sg:address":"824 Radio Rd",
    "sg:city":"Little Egg Hbr",
    "sg:classifiers":[
        {
            "category":"Real Estate",
            "subcategory":"Real Estate Agent",
            "type":"Services"
        }
    ],
    "sg:phone":"+1 609 296 3602",
    "sg:postcode":"08087",
    "sg:province":"NJ",
    "wof:name":"Coldwell Banker",
    "wof:placetype":"venue"
},
  "geometry": {"coordinates":[-74.367738,39.574643],"type":"Point"}
}