{
  "type": "Feature",
  "properties": {
    "addr:full":"141 Bodman Pl Red Bank NJ 07701",
    "addr:housenumber":"141",
    "addr:postcode":"07701",
    "addr:street":"Bodman Pl",
    "iso:country":"US",
    "sg:address":"141 Bodman Pl",
    "sg:city":"Red Bank",
    "sg:classifiers":[
        {
            "category":"Health Services",
            "subcategory":"Clinic",
            "type":"Services"
        }
    ],
    "sg:phone":"+1   ",
    "sg:postcode":"07701",
    "sg:province":"NJ",
    "sg:tags":[
        "home",
        "care"
    ],
    "wof:name":"McOss Nursing Services Inc",
    "wof:placetype":"venue"
},
  "geometry": {"coordinates":[-74.07460399999999,40.354334],"type":"Point"}
}