{
  "type": "Feature",
  "properties": {
    "addr:full":"1986 Delsea Dr Franklinville NJ 08322",
    "addr:housenumber":"1986",
    "addr:postcode":"08322",
    "addr:street":"Delsea Dr",
    "iso:country":"US",
    "sg:address":"1986 Delsea Dr",
    "sg:city":"Franklinville",
    "sg:classifiers":[
        {
            "category":"Autos & Motor Vehicles",
            "subcategory":"Fuel & Gas Station",
            "type":"Retail Goods"
        }
    ],
    "sg:phone":"+1 856 694 9824",
    "sg:postcode":"08322",
    "sg:province":"NJ",
    "wof:name":"Gulf Gas Station",
    "wof:placetype":"venue"
},
  "geometry": {"coordinates":[-75.07009600000001,39.605358],"type":"Point"}
}