{
  "type": "Feature",
  "properties": {
    "addr:full":"706 Brunswick Ave Trenton NJ 08638",
    "addr:housenumber":"706",
    "addr:postcode":"08638",
    "addr:street":"Brunswick Ave",
    "iso:country":"US",
    "sg:address":"706 Brunswick Ave",
    "sg:city":"Trenton",
    "sg:classifiers":[
        {
            "category":"Restaurant",
            "type":"Food & Drink"
        }
    ],
    "sg:phone":"+1   ",
    "sg:postcode":"08638",
    "sg:province":"NJ",
    "sg:tags":[
        "eating"
    ],
    "wof:name":"Coconut Restaurant",
    "wof:placetype":"venue"
},
  "geometry": {"coordinates":[-74.75308,40.235219],"type":"Point"}
}