{
  "type": "Feature",
  "properties": {
    "addr:full":"420 Lantana Ave Englewood NJ 07631",
    "addr:housenumber":"420",
    "addr:postcode":"07631",
    "addr:street":"Lantana Ave",
    "iso:country":"US",
    "sg:address":"420 Lantana Ave",
    "sg:city":"Englewood",
    "sg:classifiers":[
        {
            "category":"Professional",
            "subcategory":"Business Services",
            "type":"Services"
        }
    ],
    "sg:phone":"+1 201 567 0397",
    "sg:postcode":"07631",
    "sg:province":"NJ",
    "wof:name":"Creative Products",
    "wof:placetype":"venue"
},
  "geometry": {"coordinates":[-73.987098,40.908142],"type":"Point"}
}