{
  "type": "Feature",
  "properties": {
    "iso:country":"US",
    "sg:address":"8 Ridgedale Ave",
    "sg:city":"Cedar Knolls",
    "sg:classifiers":[
        {
            "category":"Social Services",
            "type":"Services"
        }
    ],
    "sg:phone":"+1   ",
    "sg:postcode":"07927",
    "sg:province":"NJ",
    "sg:tags":[
        "organization",
        "self",
        "help"
    ],
    "wof:name":"Goen Seminars",
    "wof:placetype":"venue"
},
  "geometry": {"coordinates":[-74.446105,40.833974],"type":"Point"}
}