{
  "type": "Feature",
  "properties": {
    "addr:full":"289 Georges Rd Dayton NJ 08810",
    "addr:housenumber":"289",
    "addr:postcode":"08810",
    "addr:street":"Georges Rd",
    "iso:country":"US",
    "sg:address":"289 Georges Rd",
    "sg:city":"Dayton",
    "sg:classifiers":[
        {
            "category":"Freight",
            "type":"Transportation"
        }
    ],
    "sg:phone":"+1 732 329 4500",
    "sg:postcode":"08810",
    "sg:province":"NJ",
    "sg:tags":[
        "operator",
        "local",
        "storage",
        "trucking"
    ],
    "wof:name":"A Greater New Jersey Movers",
    "wof:placetype":"venue"
},
  "geometry": {"coordinates":[-74.508537,40.369928],"type":"Point"}
}