{
  "type": "Feature",
  "properties": {
    "addr:full":"417 Carriage Ln Wyckoff NJ 07481",
    "addr:housenumber":"417",
    "addr:postcode":"07481",
    "addr:street":"Carriage Ln",
    "iso:country":"US",
    "sg:address":"417 Carriage Ln",
    "sg:city":"Wyckoff",
    "sg:classifiers":[
        {
            "category":"Home & Garden",
            "subcategory":"Building Materials",
            "type":"Retail Goods"
        }
    ],
    "sg:phone":"+1 201 848 5488",
    "sg:postcode":"07481",
    "sg:province":"NJ",
    "sg:tags":[
        "windows"
    ],
    "wof:name":"D & D Home Remodelers LLC",
    "wof:placetype":"venue"
},
  "geometry": {"coordinates":[-74.160065,40.995278],"type":"Point"}
}