{
  "type": "Feature",
  "properties": {
    "addr:full":"3060 State Rte 73 Maple Shade NJ 08052",
    "addr:housenumber":"3060",
    "addr:postcode":"08052",
    "addr:street":"State Rte 73 Maple",
    "iso:country":"US",
    "sg:address":"3060 State Rte 73",
    "sg:city":"Maple Shade",
    "sg:classifiers":[
        {
            "category":"Personal",
            "subcategory":"Beauty Salon",
            "type":"Services"
        }
    ],
    "sg:phone":"+1 856 779 2828",
    "sg:postcode":"08052",
    "sg:province":"NJ",
    "sg:tags":[
        "shop"
    ],
    "wof:name":"Hairport The",
    "wof:placetype":"venue"
},
  "geometry": {"coordinates":[-75.00014,39.965283],"type":"Point"}
}