{
  "type": "Feature",
  "properties": {
    "iso:country":"US",
    "sg:address":"188 E Bergen Pl",
    "sg:city":"Red Bank",
    "sg:classifiers":[
        {
            "category":"Health Services",
            "subcategory":"Doctor",
            "type":"Services"
        }
    ],
    "sg:phone":"+1 732 842 7000",
    "sg:postcode":"07701",
    "sg:province":"NJ",
    "sg:tags":[
        "physician",
        "surgeon"
    ],
    "wof:name":"Dina A Mc Heffey MD",
    "wof:placetype":"venue"
},
  "geometry": {"coordinates":[-74.06576699999999,40.342235],"type":"Point"}
}