{
  "type": "Feature",
  "properties": {
    "addr:full":"The Marriott Hanover Hotel 1401 State Hwy N 10 E Whippany NJ 07983",
    "addr:housenumber":"1401;10 e",
    "addr:postcode":"07983",
    "addr:street":"State Hwy N",
    "iso:country":"US",
    "sg:address":"The Marriott Hanover Hotel 1401 State Hwy N 10 E",
    "sg:city":"Whippany",
    "sg:classifiers":[
        {
            "category":"Bars & Pubs",
            "type":"Food & Drink"
        },
        {
            "category":"Restaurant",
            "type":"Food & Drink"
        }
    ],
    "sg:phone":"+1 973 898 6454",
    "sg:postcode":"07983",
    "sg:province":"NJ",
    "sg:tags":[
        "irish"
    ],
    "sg:website":"marriottmodules.com/hanover_marr...",
    "wof:name":"The Auld Shebeen",
    "wof:placetype":"venue"
},
  "geometry": {"coordinates":[-74.44914900000001,40.836157],"type":"Point"}
}