{
  "type": "Feature",
  "properties": {
    "iso:country":"US",
    "sg:address":"78 Sussex St",
    "sg:city":"Hackensack",
    "sg:classifiers":[
        {
            "category":"Building & Trades",
            "subcategory":"Locksmith",
            "type":"Services"
        }
    ],
    "sg:phone":"+1 201 403 2009",
    "sg:postcode":"07601",
    "sg:province":"NJ",
    "sg:tags":[
        "key"
    ],
    "wof:name":"All Day 24 Hr Emergency Locksmith",
    "wof:placetype":"venue"
},
  "geometry": {"coordinates":[-74.047926,40.880376],"type":"Point"}
}