{
  "type": "Feature",
  "properties": {
    "addr:full":"2101 Branch Pike Riverton NJ 08077",
    "addr:housenumber":"2101",
    "addr:postcode":"08077",
    "addr:street":"Branch Pike",
    "iso:country":"US",
    "sg:address":"2101 Branch Pike",
    "sg:city":"Riverton",
    "sg:classifiers":[
        {
            "category":"Autos & Motor Vehicles",
            "subcategory":"Fuel & Gas Station",
            "type":"Retail Goods"
        }
    ],
    "sg:phone":"+1   ",
    "sg:postcode":"08077",
    "sg:province":"NJ",
    "sg:tags":[
        "automotive",
        "general",
        "gasoline",
        "repair"
    ],
    "wof:name":"Mobil",
    "wof:placetype":"venue"
},
  "geometry": {"coordinates":[-75.004937,39.987947],"type":"Point"}
}