{
  "type": "Feature",
  "properties": {
    "iso:country":"US",
    "sg:address":"529 S Springfield Ave",
    "sg:city":"Springfield",
    "sg:classifiers":[
        {
            "category":"Personal",
            "subcategory":"Beauty Salon",
            "type":"Services"
        }
    ],
    "sg:phone":"+1   ",
    "sg:postcode":"07081",
    "sg:province":"NJ",
    "sg:tags":[
        "shop"
    ],
    "wof:name":"Expressions Hair Design",
    "wof:placetype":"venue"
},
  "geometry": {"coordinates":[-74.32069799999999,40.693483],"type":"Point"}
}