{
  "type": "Feature",
  "properties": {
    "addr:full":"167 Meadow Rd Clark NJ 07066",
    "addr:housenumber":"167",
    "addr:postcode":"07066",
    "addr:street":"Meadow Rd",
    "iso:country":"US",
    "sg:address":"167 Meadow Rd",
    "sg:city":"Clark",
    "sg:classifiers":[
        {
            "category":"Communications",
            "subcategory":"Film & Video Production",
            "type":"Services"
        }
    ],
    "sg:phone":"+1 732 388 3952",
    "sg:postcode":"07066",
    "sg:province":"NJ",
    "sg:tags":[
        "motion"
    ],
    "wof:name":"359 Production Inc",
    "wof:placetype":"venue"
},
  "geometry": {"coordinates":[-74.327941,40.61616],"type":"Point"}
}