{
  "type": "Feature",
  "properties": {
    "iso:country":"US",
    "sg:address":"904 Meadow Ct",
    "sg:city":"Helmetta",
    "sg:classifiers":[
        {
            "category":"Professional",
            "subcategory":"Research",
            "type":"Services"
        },
        {
            "category":"Professional",
            "subcategory":"Management & Consulting",
            "type":"Services"
        }
    ],
    "sg:phone":"+1 732 521 5250",
    "sg:postcode":"08828",
    "sg:province":"NJ",
    "sg:tags":[
        "environmental",
        "ecological",
        "business"
    ],
    "wof:name":"C F Enterprises Inc",
    "wof:placetype":"venue"
},
  "geometry": {"coordinates":[-74.412299,40.382718],"type":"Point"}
}