{
  "type": "Feature",
  "properties": {
    "addr:full":"126 Midland Ave Kearny NJ 07032",
    "addr:housenumber":"126",
    "addr:postcode":"07032",
    "addr:street":"Midland Ave",
    "iso:country":"US",
    "sg:address":"126 Midland Ave",
    "sg:city":"Kearny",
    "sg:classifiers":[
        {
            "category":"Social Services",
            "subcategory":"Child Care",
            "type":"Services"
        }
    ],
    "sg:phone":"+1 201 246 1600",
    "sg:postcode":"07032",
    "sg:province":"NJ",
    "sg:tags":[
        "day"
    ],
    "wof:name":"New Beginnings Early Learning Center",
    "wof:placetype":"venue"
},
  "geometry": {"coordinates":[-74.143743,40.769931],"type":"Point"}
}