{
  "type": "Feature",
  "properties": {
    "addr:full":"147 US Hwy 130 Bordentown NJ 08505",
    "addr:housenumber":"147",
    "addr:postcode":"08505",
    "addr:street":"Us Hwy 130",
    "iso:country":"US",
    "sg:address":"147 US Hwy 130",
    "sg:city":"Bordentown",
    "sg:classifiers":[
        {
            "category":"Organizations",
            "subcategory":"Religious Organization",
            "type":"Services"
        }
    ],
    "sg:phone":"+1 609 298 2461",
    "sg:postcode":"08505",
    "sg:province":"NJ",
    "sg:tags":[
        "presbyterian",
        "church"
    ],
    "wof:name":"Korean Presbyterian Church",
    "wof:placetype":"venue"
},
  "geometry": {"coordinates":[-74.699851,40.150699],"type":"Point"}
}