{
  "type": "Feature",
  "properties": {
    "addr:full":"38 Woods Edge Ct Parlin NJ 08859",
    "addr:housenumber":"38",
    "addr:postcode":"08859",
    "addr:street":"Woods Edge Ct",
    "iso:country":"US",
    "sg:address":"38 Woods Edge Ct",
    "sg:city":"Parlin",
    "sg:classifiers":[
        {
            "category":"Professional",
            "subcategory":"Computer Services",
            "type":"Services"
        }
    ],
    "sg:phone":"+1 732 316 5435",
    "sg:postcode":"08859",
    "sg:province":"NJ",
    "sg:tags":[
        "prepackaged",
        "software"
    ],
    "wof:name":"Lid Software Design Inc",
    "wof:placetype":"venue"
},
  "geometry": {"coordinates":[-74.284217,40.457583],"type":"Point"}
}