{
  "type": "Feature",
  "properties": {
    "iso:country":"US",
    "sg:address":"138 Bloomfield Ave",
    "sg:city":"Bloomfield",
    "sg:classifiers":[
        {
            "category":"Professional",
            "subcategory":"Accounting & Tax Preparation",
            "type":"Services"
        }
    ],
    "sg:phone":"+1 973 743 5582",
    "sg:postcode":"07003",
    "sg:province":"NJ",
    "sg:tags":[
        "return"
    ],
    "wof:name":"Delson Associates",
    "wof:placetype":"venue"
},
  "geometry": {"coordinates":[-74.188894,40.778102],"type":"Point"}
}