{
  "type": "Feature",
  "properties": {
    "iso:country":"US",
    "sg:address":"90 Maple Ave",
    "sg:city":"Morristown",
    "sg:classifiers":[
        {
            "category":"Professional",
            "subcategory":"Lawyer & Legal Services",
            "type":"Services"
        }
    ],
    "sg:phone":"+1 973 540 8470",
    "sg:postcode":"07960",
    "sg:province":"NJ",
    "wof:name":"Long William C Attorney",
    "wof:placetype":"venue"
},
  "geometry": {"coordinates":[-74.477898,40.791599],"type":"Point"}
}