{
  "type": "Feature",
  "properties": {
    "iso:country":"US",
    "sg:address":"415 US Hwy 9",
    "sg:city":"Lanoka Harbor",
    "sg:classifiers":[
        {
            "category":"Building & Trades",
            "subcategory":"Construction",
            "type":"Services"
        }
    ],
    "sg:phone":"+1 609 693 9355",
    "sg:postcode":"08734",
    "sg:province":"NJ",
    "sg:tags":[
        "contractor"
    ],
    "wof:name":"Bob Lange Inc",
    "wof:placetype":"venue"
},
  "geometry": {"coordinates":[-74.180346,39.854763],"type":"Point"}
}