{
  "type": "Feature",
  "properties": {
    "iso:country":"US",
    "sg:address":"29 James St",
    "sg:city":"New Brunswick",
    "sg:classifiers":[
        {
            "category":"Professional",
            "subcategory":"Business Services",
            "type":"Services"
        }
    ],
    "sg:phone":"+1   ",
    "sg:postcode":"08901",
    "sg:province":"NJ",
    "wof:name":"Beteri Boy",
    "wof:placetype":"venue"
},
  "geometry": {"coordinates":[-74.45443,40.492379],"type":"Point"}
}