{
  "type": "Feature",
  "properties": {
    "iso:country":"US",
    "sg:address":"1218 State Rte 179",
    "sg:city":"Lambertville",
    "sg:classifiers":[
        {
            "category":"Autos & Motor Vehicles",
            "subcategory":"Auto Supplies",
            "type":"Retail Goods"
        }
    ],
    "sg:phone":"+1 609 397 4666",
    "sg:postcode":"08530",
    "sg:province":"NJ",
    "sg:tags":[
        "equipment",
        "racing",
        "car",
        "automobile"
    ],
    "wof:name":"Jay's Sales",
    "wof:placetype":"venue"
},
  "geometry": {"coordinates":[-74.88342,40.410921],"type":"Point"}
}