{
  "type": "Feature",
  "properties": {
    "iso:country":"US",
    "sg:address":"214 French St",
    "sg:city":"New Brunswick",
    "sg:classifiers":[
        {
            "category":"Retail",
            "subcategory":"Repair Shop",
            "type":"Services"
        }
    ],
    "sg:phone":"+1   ",
    "sg:postcode":"08901",
    "sg:province":"NJ",
    "wof:name":"Emergency Locksmith 24 Hour",
    "wof:placetype":"venue"
},
  "geometry": {"coordinates":[-74.458561,40.490511],"type":"Point"}
}