{
  "type": "Feature",
  "properties": {
    "addr:full":"1003 Lincoln Dr W Ste A Marlton NJ 08053",
    "addr:housenumber":"1003",
    "addr:postcode":"08053",
    "addr:street":"Lincoln Dr W Ste A Marlton",
    "iso:country":"US",
    "sg:address":"1003 Lincoln Dr W Ste A",
    "sg:city":"Marlton",
    "sg:classifiers":[
        {
            "category":"Health Services",
            "subcategory":"Health Practitioner",
            "type":"Services"
        }
    ],
    "sg:phone":"+1 856 983 3328",
    "sg:postcode":"08053",
    "sg:province":"NJ",
    "sg:tags":[
        "addiction",
        "abuse",
        "drug"
    ],
    "wof:name":"Rap Room",
    "wof:placetype":"venue"
},
  "geometry": {"coordinates":[-74.944366,39.913013],"type":"Point"}
}