{
  "type": "Feature",
  "properties": {
    "iso:country":"US",
    "sg:address":"2849 Woodbridge Ave",
    "sg:city":"Edison",
    "sg:classifiers":[
        {
            "category":"Arts & Performance",
            "subcategory":"Theater",
            "type":"Entertainment"
        }
    ],
    "sg:phone":"+1 732 548 5480",
    "sg:postcode":"08837",
    "sg:province":"NJ",
    "sg:tags":[
        "group",
        "live",
        "music"
    ],
    "wof:name":"Primetime Entertainers",
    "wof:placetype":"venue"
},
  "geometry": {"coordinates":[-74.355226,40.516088],"type":"Point"}
}