{
  "type": "Feature",
  "properties": {
    "addr:full":"1337 New Rd Northfield NJ 08225",
    "addr:housenumber":"1337",
    "addr:postcode":"08225",
    "addr:street":"New Rd",
    "iso:country":"US",
    "sg:address":"1337 New Rd",
    "sg:city":"Northfield",
    "sg:classifiers":[
        {
            "category":"Retail",
            "subcategory":"Repair Shop",
            "type":"Services"
        }
    ],
    "sg:phone":"+1   ",
    "sg:postcode":"08225",
    "sg:province":"NJ",
    "wof:name":"Atlantic Electronic Repair",
    "wof:placetype":"venue"
},
  "geometry": {"coordinates":[-74.553708,39.375211],"type":"Point"}
}