{
  "type": "Feature",
  "properties": {
    "addr:full":"60 Grange Ave Fair Haven NJ 07704",
    "addr:housenumber":"60",
    "addr:postcode":"07704",
    "addr:street":"Grange Ave",
    "iso:country":"US",
    "sg:address":"60 Grange Ave",
    "sg:city":"Fair Haven",
    "sg:classifiers":[
        {
            "category":"Professional",
            "subcategory":"Employment Agencies",
            "type":"Services"
        }
    ],
    "sg:phone":"+1 732 747 8100",
    "sg:postcode":"07704",
    "sg:province":"NJ",
    "sg:tags":[
        "executive",
        "recruiting",
        "help",
        "contractor"
    ],
    "sg:website":"www.dowdgroup.com",
    "wof:name":"Dowd Group Inc",
    "wof:placetype":"venue"
},
  "geometry": {"coordinates":[-74.04908500000001,40.360669],"type":"Point"}
}