{
  "type": "Feature",
  "properties": {
    "addr:full":"255 W Broadway Paterson NJ 07522",
    "addr:housenumber":"255",
    "addr:postcode":"07522",
    "addr:street":"W Broadway",
    "iso:country":"US",
    "sg:address":"255 W Broadway",
    "sg:city":"Paterson",
    "sg:classifiers":[
        {
            "category":"Manufacturing",
            "subcategory":"Retail Goods",
            "type":"Manufacturing & Wholesale Goods"
        },
        {
            "category":"Manufacturing",
            "subcategory":"Motor Vehicles & Parts",
            "type":"Manufacturing & Wholesale Goods"
        }
    ],
    "sg:phone":"+1 973 595 1222",
    "sg:postcode":"07522",
    "sg:province":"NJ",
    "sg:tags":[
        "screen",
        "printing",
        "manufacturer"
    ],
    "wof:name":"Bergen Screen Printing Inc",
    "wof:placetype":"venue"
},
  "geometry": {"coordinates":[-74.182007,40.924908],"type":"Point"}
}