{
  "type": "Feature",
  "properties": {
    "addr:full":"2 Standish Dr Morristown NJ 07960",
    "addr:housenumber":"2",
    "addr:postcode":"07960",
    "addr:street":"Standish Dr",
    "iso:country":"US",
    "sg:address":"2 Standish Dr",
    "sg:city":"Morristown",
    "sg:classifiers":[
        {
            "category":"Wholesale",
            "subcategory":"Stationery",
            "type":"Manufacturing & Wholesale Goods"
        }
    ],
    "sg:phone":"+1 973 605 1941",
    "sg:postcode":"07960",
    "sg:province":"NJ",
    "sg:tags":[
        "business",
        "form",
        "system"
    ],
    "wof:name":"Essential Business Systems",
    "wof:placetype":"venue"
},
  "geometry": {"coordinates":[-74.53877799999999,40.816973],"type":"Point"}
}