{
  "type": "Feature",
  "properties": {
    "addr:full":"364 Lawton Ave Cliffside Park NJ 07010",
    "addr:housenumber":"364",
    "addr:postcode":"07010",
    "addr:street":"Lawton Ave",
    "iso:country":"US",
    "sg:address":"364 Lawton Ave",
    "sg:city":"Cliffside Park",
    "sg:classifiers":[
        {
            "category":"Recreation",
            "type":"Entertainment"
        }
    ],
    "sg:phone":"+1 201 777 3540",
    "sg:postcode":"07010",
    "sg:province":"NJ",
    "sg:tags":[
        "parks"
    ],
    "wof:name":"Any Time Cliffside Park",
    "wof:placetype":"venue"
},
  "geometry": {"coordinates":[-73.987341,40.827696],"type":"Point"}
}