{
  "type": "Feature",
  "properties": {
    "iso:country":"US",
    "sg:address":"220 Russell Ave",
    "sg:city":"Rahway",
    "sg:classifiers":[
        {
            "category":"Banks & Credit Unions",
            "subcategory":"Investment Brokerage",
            "type":"Services"
        }
    ],
    "sg:phone":"+1   ",
    "sg:postcode":"07065",
    "sg:province":"NJ",
    "sg:tags":[
        "advisory"
    ],
    "wof:name":"M H Elite Portfolio of Funds",
    "wof:placetype":"venue"
},
  "geometry": {"coordinates":[-74.301334,40.602312],"type":"Point"}
}