{
  "type": "Feature",
  "properties": {
    "addr:full":"35 Taylor Rd Wayne NJ 07416",
    "addr:housenumber":"35",
    "addr:postcode":"07416",
    "addr:street":"Taylor Rd",
    "iso:country":"US",
    "sg:address":"35 Taylor Rd",
    "sg:city":"Wayne",
    "sg:classifiers":[
        {
            "category":"Government",
            "subcategory":"Post Office",
            "type":"Public Place"
        }
    ],
    "sg:phone":"+1 973 000 1111",
    "sg:postcode":"07416",
    "sg:province":"NJ",
    "wof:name":"US Post Office",
    "wof:placetype":"venue"
},
  "geometry": {"coordinates":[-74.581045,41.112589],"type":"Point"}
}