{
  "type": "Feature",
  "properties": {
    "iso:country":"US",
    "sg:address":"21 Keats Rd",
    "sg:city":"Short Hills",
    "sg:classifiers":[
        {
            "category":"Professional",
            "type":"Services"
        }
    ],
    "sg:phone":"+1   ",
    "sg:postcode":"07078",
    "sg:province":"NJ",
    "wof:name":"Fistec Inc",
    "wof:placetype":"venue"
},
  "geometry": {"coordinates":[-74.345528,40.73891],"type":"Point"}
}