{
  "type": "Feature",
  "properties": {
    "addr:full":"44 Kentucky Way Freehold NJ 07728",
    "addr:housenumber":"44",
    "addr:postcode":"07728",
    "addr:street":"Kentucky Way",
    "iso:country":"US",
    "sg:address":"44 Kentucky Way",
    "sg:city":"Freehold",
    "sg:classifiers":[
        {
            "category":"Shopping",
            "type":"Retail Goods"
        }
    ],
    "sg:phone":"+1   ",
    "sg:postcode":"07728",
    "sg:province":"NJ",
    "sg:tags":[
        "merchandise"
    ],
    "wof:name":"Everfresh International",
    "wof:placetype":"venue"
},
  "geometry": {"coordinates":[-74.260757,40.264667],"type":"Point"}
}