{
  "type": "Feature",
  "properties": {
    "iso:country":"US",
    "sg:address":"29 Riverside Ave",
    "sg:city":"Newark",
    "sg:classifiers":[
        {
            "category":"Manufacturing",
            "subcategory":"Chemicals & Compounds",
            "type":"Manufacturing & Wholesale Goods"
        }
    ],
    "sg:phone":"+1 973 350 9400",
    "sg:postcode":"07104",
    "sg:province":"NJ",
    "sg:tags":[
        "manufacture",
        "paint",
        "varnish",
        "lacquer",
        "remover"
    ],
    "wof:name":"Samax Enterprise Inc",
    "wof:placetype":"venue"
},
  "geometry": {"coordinates":[-74.15724299999999,40.770531],"type":"Point"}
}