{
  "type": "Feature",
  "properties": {
    "iso:country":"US",
    "sg:address":"1495 Pennsylvania Ave",
    "sg:city":"Franklinville",
    "sg:classifiers":[
        {
            "category":"Shopping",
            "type":"Retail Goods"
        }
    ],
    "sg:phone":"+1   ",
    "sg:postcode":"08322",
    "sg:province":"NJ",
    "sg:tags":[
        "merchandise"
    ],
    "wof:name":"Ed Allens White Pine By Pcs",
    "wof:placetype":"venue"
},
  "geometry": {"coordinates":[-75.02452599999999,39.618379],"type":"Point"}
}