{
  "type": "Feature",
  "properties": {
    "addr:full":"6 Joseph Ln Succasunna NJ 07876",
    "addr:housenumber":"6",
    "addr:postcode":"07876",
    "addr:street":"Joseph Ln",
    "iso:country":"US",
    "sg:address":"6 Joseph Ln",
    "sg:city":"Succasunna",
    "sg:classifiers":[
        {
            "category":"Building & Trades",
            "subcategory":"Electrical",
            "type":"Services"
        }
    ],
    "sg:phone":"+1 973 252 3863",
    "sg:postcode":"07876",
    "sg:province":"NJ",
    "sg:tags":[
        "electrical",
        "contractor"
    ],
    "wof:name":"Worters Electric Service",
    "wof:placetype":"venue"
},
  "geometry": {"coordinates":[-74.660786,40.842631],"type":"Point"}
}