{
  "type": "Feature",
  "properties": {
    "iso:country":"US",
    "sg:address":"905 Main St",
    "sg:city":"Paterson",
    "sg:classifiers":[
        {
            "category":"Retail",
            "subcategory":"Laundry & Dry Cleaning",
            "type":"Services"
        }
    ],
    "sg:phone":"+1 973 279 3511",
    "sg:postcode":"07503",
    "sg:province":"NJ",
    "wof:name":"Crystal Clear Dry Cleaners Inc",
    "wof:placetype":"venue"
},
  "geometry": {"coordinates":[-74.16120100000001,40.8965],"type":"Point"}
}