{
  "type": "Feature",
  "properties": {
    "addr:full":"77 Channel Dr Point Pleasant Beach NJ 08742",
    "addr:housenumber":"77",
    "addr:postcode":"08742",
    "addr:street":"Channel Dr",
    "iso:country":"US",
    "sg:address":"77 Channel Dr",
    "sg:city":"Point Pleasant Beach",
    "sg:classifiers":[
        {
            "category":"Marine",
            "type":"Transportation"
        }
    ],
    "sg:phone":"+1 732 892 1831",
    "sg:postcode":"08742",
    "sg:province":"NJ",
    "wof:name":"Budget Towing",
    "wof:placetype":"venue"
},
  "geometry": {"coordinates":[-74.039737,40.101539],"type":"Point"}
}