{
  "type": "Feature",
  "properties": {
    "addr:full":"4 Precedent Pl Manalapan NJ 07726",
    "addr:housenumber":"4",
    "addr:postcode":"07726",
    "addr:street":"Precedent Pl",
    "iso:country":"US",
    "sg:address":"4 Precedent Pl",
    "sg:city":"Manalapan",
    "sg:classifiers":[
        {
            "category":"Personal",
            "type":"Services"
        }
    ],
    "sg:phone":"+1 732 845 4774",
    "sg:postcode":"07726",
    "sg:province":"NJ",
    "sg:tags":[
        "therapist",
        "massage"
    ],
    "wof:name":"Tender Touch",
    "wof:placetype":"venue"
},
  "geometry": {"coordinates":[-74.33340200000001,40.2443],"type":"Point"}
}