{
  "type": "Feature",
  "properties": {
    "iso:country":"US",
    "sg:address":"10 Greenwood Ave Ste F",
    "sg:city":"Woodbury",
    "sg:classifiers":[
        {
            "category":"Manufacturing",
            "subcategory":"Electronics",
            "type":"Manufacturing & Wholesale Goods"
        },
        {
            "category":"Utilities",
            "subcategory":"Telephone",
            "type":"Services"
        },
        {
            "category":"Communications",
            "type":"Services"
        }
    ],
    "sg:phone":"+1 856 686 0888",
    "sg:postcode":"08096",
    "sg:province":"NJ",
    "sg:tags":[
        "equipment",
        "telecommunications-equipment",
        "system",
        "systems-repair",
        "supply"
    ],
    "sg:website":"http://www.rfpnj.com",
    "wof:name":"Rfp Solutions Inc",
    "wof:placetype":"venue"
},
  "geometry": {"coordinates":[-75.16109899999999,39.823323],"type":"Point"}
}