{
  "type": "Feature",
  "properties": {
    "iso:country":"US",
    "sg:address":"115 Belmont Dr",
    "sg:city":"Somerset",
    "sg:classifiers":[
        {
            "category":"Restaurant",
            "type":"Food & Drink"
        }
    ],
    "sg:phone":"+1   ",
    "sg:postcode":"08873",
    "sg:province":"NJ",
    "sg:tags":[
        "eating"
    ],
    "wof:name":"Belmont Drive Assoc LP",
    "wof:placetype":"venue"
},
  "geometry": {"coordinates":[-74.53755200000001,40.542573],"type":"Point"}
}