{
  "type": "Feature",
  "properties": {
    "iso:country":"US",
    "sg:address":"2590 Nottingham Way",
    "sg:city":"Trenton",
    "sg:classifiers":[
        {
            "category":"Social Services",
            "subcategory":"Job Training",
            "type":"Services"
        }
    ],
    "sg:phone":"+1 609 586 0888",
    "sg:postcode":"08619",
    "sg:province":"NJ",
    "sg:tags":[
        "rehabilitation"
    ],
    "wof:name":"Mercerville Rehab Ctr",
    "wof:placetype":"venue"
},
  "geometry": {"coordinates":[-74.693468,40.234872],"type":"Point"}
}