{
  "type": "Feature",
  "properties": {
    "addr:full":"1872 W Point Dr Cherry Hill NJ 08003",
    "addr:housenumber":"1872",
    "addr:postcode":"08003",
    "addr:street":"W Point Dr",
    "iso:country":"US",
    "sg:address":"1872 W Point Dr",
    "sg:city":"Cherry Hill",
    "sg:classifiers":[
        {
            "category":"Professional",
            "subcategory":"Research",
            "type":"Services"
        }
    ],
    "sg:phone":"+1   ",
    "sg:postcode":"08003",
    "sg:province":"NJ",
    "sg:tags":[
        "nonphysical",
        "commercial"
    ],
    "wof:name":"S K Levine",
    "wof:placetype":"venue"
},
  "geometry": {"coordinates":[-74.978275,39.880319],"type":"Point"}
}