{
  "type": "Feature",
  "properties": {
    "iso:country":"US",
    "sg:address":"75 Belcher Rd",
    "sg:city":"Blairstown",
    "sg:classifiers":[
        {
            "category":"Manufacturing",
            "subcategory":"Tools & Machinery",
            "type":"Manufacturing & Wholesale Goods"
        }
    ],
    "sg:phone":"+1 908 362 8885",
    "sg:postcode":"07825",
    "sg:province":"NJ",
    "sg:tags":[
        "machine",
        "shop"
    ],
    "wof:name":"Colinear Machine & Design",
    "wof:placetype":"venue"
},
  "geometry": {"coordinates":[-74.986582,40.95432],"type":"Point"}
}