{
  "type": "Feature",
  "properties": {
    "iso:country":"US",
    "sg:address":"534 Anderson Ave",
    "sg:city":"Wood-Ridge",
    "sg:classifiers":[
        {
            "category":"Professional",
            "subcategory":"Engineering",
            "type":"Services"
        }
    ],
    "sg:phone":"+1 201 935 0184",
    "sg:postcode":"07075",
    "sg:province":"NJ",
    "wof:name":"Ehrlich Assocs",
    "wof:placetype":"venue"
},
  "geometry": {"coordinates":[-74.083817,40.845288],"type":"Point"}
}