{
  "type": "Feature",
  "properties": {
    "addr:full":"974 Bay Ave Toms River NJ 08753",
    "addr:housenumber":"974",
    "addr:postcode":"08753",
    "addr:street":"Bay Ave",
    "iso:country":"US",
    "sg:address":"974 Bay Ave",
    "sg:city":"Toms River",
    "sg:classifiers":[
        {
            "category":"Organizations",
            "subcategory":"Religious Organization",
            "type":"Services"
        }
    ],
    "sg:phone":"+1   ",
    "sg:postcode":"08753",
    "sg:province":"NJ",
    "wof:name":"East Dover Baptist Church",
    "wof:placetype":"venue"
},
  "geometry": {"coordinates":[-74.156362,39.970471],"type":"Point"}
}