{
  "type": "Feature",
  "properties": {
    "iso:country":"US",
    "sg:address":"13 Atlantic St",
    "sg:city":"Metuchen",
    "sg:classifiers":[
        {
            "category":"Restaurant",
            "type":"Food & Drink"
        }
    ],
    "sg:phone":"+1   ",
    "sg:postcode":"08840",
    "sg:province":"NJ",
    "sg:tags":[
        "eating"
    ],
    "wof:name":"Tierras Colombianas",
    "wof:placetype":"venue"
},
  "geometry": {"coordinates":[-74.327467,40.550946],"type":"Point"}
}