{
  "type": "Feature",
  "properties": {
    "addr:full":"455 Co Rd 520 Marlboro NJ 07746",
    "addr:housenumber":"455",
    "addr:postcode":"07746",
    "addr:street":"Co Rd 520",
    "iso:country":"US",
    "sg:address":"455 Co Rd 520",
    "sg:city":"Marlboro",
    "sg:classifiers":[
        {
            "category":"Professional",
            "subcategory":"Business Services",
            "type":"Services"
        }
    ],
    "sg:phone":"+1   ",
    "sg:postcode":"07746",
    "sg:province":"NJ",
    "wof:name":"Vergeo LLC",
    "wof:placetype":"venue"
},
  "geometry": {"coordinates":[-74.247253,40.333229],"type":"Point"}
}