{
  "type": "Feature",
  "properties": {
    "addr:full":"47 U Hwy 130 South N Pennsauken NJ 08110",
    "addr:housenumber":"47",
    "addr:postcode":"08110",
    "addr:street":"U Hwy 130 South N",
    "iso:country":"US",
    "sg:address":"47 U Hwy 130 South N",
    "sg:city":"Pennsauken",
    "sg:classifiers":[
        {
            "category":"Shopping",
            "subcategory":"Stationery & Office Supplies",
            "type":"Retail Goods"
        }
    ],
    "sg:phone":"+1 856 662 7080",
    "sg:postcode":"08110",
    "sg:province":"NJ",
    "sg:tags":[
        "equipment"
    ],
    "wof:name":"Shirley Office Supply",
    "wof:placetype":"venue"
},
  "geometry": {"coordinates":[-75.086635,39.922352],"type":"Point"}
}