{
  "type": "Feature",
  "properties": {
    "addr:full":"408 Fairview Ave Colonia NJ 07067",
    "addr:housenumber":"408",
    "addr:postcode":"07067",
    "addr:street":"Fairview Ave",
    "iso:country":"US",
    "sg:address":"408 Fairview Ave",
    "sg:city":"Colonia",
    "sg:classifiers":[
        {
            "category":"Manufacturing",
            "subcategory":"Tools & Machinery",
            "type":"Manufacturing & Wholesale Goods"
        }
    ],
    "sg:phone":"+1 732 381 2780",
    "sg:postcode":"07067",
    "sg:province":"NJ",
    "sg:tags":[
        "equipment",
        "mfg"
    ],
    "wof:name":"Wt Collins Maint Lawn C",
    "wof:placetype":"venue"
},
  "geometry": {"coordinates":[-74.303079,40.583178],"type":"Point"}
}