{
  "type": "Feature",
  "properties": {
    "addr:full":"5581 State Rte 42 Turnersville NJ 08012",
    "addr:housenumber":"5581",
    "addr:postcode":"08012",
    "addr:street":"State Rte 42",
    "iso:country":"US",
    "sg:address":"5581 State Rte 42",
    "sg:city":"Turnersville",
    "sg:classifiers":[
        {
            "category":"Home & Garden",
            "subcategory":"Household Appliances",
            "type":"Retail Goods"
        }
    ],
    "sg:phone":"+1 856 228 9100",
    "sg:postcode":"08012",
    "sg:province":"NJ",
    "sg:tags":[
        "cleaners",
        "vacuum"
    ],
    "wof:name":"Oreck Floor Care Ctr",
    "wof:placetype":"venue"
},
  "geometry": {"coordinates":[-75.04710300000001,39.758174],"type":"Point"}
}