{
  "type": "Feature",
  "properties": {
    "addr:full":"602 Linda Ave Blackwood NJ 08012",
    "addr:housenumber":"602",
    "addr:postcode":"08012",
    "addr:street":"Linda Ave",
    "iso:country":"US",
    "sg:address":"602 Linda Ave",
    "sg:city":"Blackwood",
    "sg:classifiers":[
        {
            "category":"Building & Trades",
            "subcategory":"Construction",
            "type":"Services"
        }
    ],
    "sg:phone":"+1 856 227 0454",
    "sg:postcode":"08012",
    "sg:province":"NJ",
    "sg:tags":[
        "contractor"
    ],
    "wof:name":"U S Siding",
    "wof:placetype":"venue"
},
  "geometry": {"coordinates":[-75.06299,39.789954],"type":"Point"}
}