{
  "type": "Feature",
  "properties": {
    "addr:full":"133 E Ridgewood Ave Ridgewood NJ 07450",
    "addr:housenumber":"133",
    "addr:postcode":"07450",
    "addr:street":"E Ridgewood Ave",
    "iso:country":"US",
    "sg:address":"133 E Ridgewood Ave",
    "sg:city":"Ridgewood",
    "sg:classifiers":[
        {
            "category":"Home & Garden",
            "subcategory":"Hardware",
            "type":"Retail Goods"
        },
        {
            "category":"Home & Garden",
            "subcategory":"Home Furnishings",
            "type":"Retail Goods"
        },
        {
            "category":"Professional",
            "subcategory":"Art Services",
            "type":"Services"
        }
    ],
    "sg:phone":"+1 201 652 1045",
    "sg:postcode":"07450",
    "sg:province":"NJ",
    "sg:tags":[
        "designer",
        "consultant",
        "fixture",
        "system",
        "equipment",
        "lighting"
    ],
    "sg:website":"http://www.hillmannlighting.com",
    "wof:name":"Hillmann Lighting",
    "wof:placetype":"venue"
},
  "geometry": {"coordinates":[-74.11695899999999,40.97937],"type":"Point"}
}