{
  "type": "Feature",
  "properties": {
    "iso:country":"US",
    "sg:address":"520 Weeks Ave",
    "sg:city":"Riverside",
    "sg:classifiers":[
        {
            "category":"Health Services",
            "subcategory":"Chiropractor",
            "type":"Services"
        }
    ],
    "sg:phone":"+1 856 461 1431",
    "sg:postcode":"08075",
    "sg:province":"NJ",
    "wof:name":"Orfe Jas K Dr",
    "wof:placetype":"venue"
},
  "geometry": {"coordinates":[-74.95549800000001,40.0322],"type":"Point"}
}