{
  "type": "Feature",
  "properties": {
    "addr:full":"15 Mount Holly Mt Holly NJ 08060",
    "addr:housenumber":"15",
    "addr:postcode":"08060",
    "addr:street":"Mount",
    "iso:country":"US",
    "sg:address":"15 Mount Holly",
    "sg:city":"Mt Holly",
    "sg:classifiers":[
        {
            "category":"Organizations",
            "subcategory":"Community Association",
            "type":"Services"
        }
    ],
    "sg:phone":"+1 609 267 3095",
    "sg:postcode":"08060",
    "sg:province":"NJ",
    "sg:tags":[
        "fraternal"
    ],
    "wof:name":"Masonic Lodge",
    "wof:placetype":"venue"
},
  "geometry": {"coordinates":[-74.807299,39.986844],"type":"Point"}
}