{
  "type": "Feature",
  "properties": {
    "iso:country":"US",
    "sg:address":"6552 Park Ave",
    "sg:city":"Merchantville",
    "sg:classifiers":[
        {
            "category":"Building & Trades",
            "subcategory":"Construction",
            "type":"Services"
        }
    ],
    "sg:phone":"+1 856 662 0106",
    "sg:postcode":"08109",
    "sg:province":"NJ",
    "sg:tags":[
        "roofing",
        "siding",
        "contractor"
    ],
    "wof:name":"Kurk Roofing & Siding Co",
    "wof:placetype":"venue"
},
  "geometry": {"coordinates":[-75.04191299999999,39.955202],"type":"Point"}
}