{
  "type": "Feature",
  "properties": {
    "iso:country":"US",
    "sg:address":"2045 Woodbridge Ave",
    "sg:city":"Edison",
    "sg:classifiers":[
        {
            "category":"Health Services",
            "subcategory":"Medical Lab",
            "type":"Services"
        }
    ],
    "sg:phone":"+1 732 985 5669",
    "sg:postcode":"08817",
    "sg:province":"NJ",
    "sg:tags":[
        "bridge",
        "mfg",
        "dental",
        "testing",
        "crown",
        "production",
        "laboratory"
    ],
    "wof:name":"J & S Dental Lab Inc",
    "wof:placetype":"venue"
},
  "geometry": {"coordinates":[-74.400352,40.500408],"type":"Point"}
}