{
  "type": "Feature",
  "properties": {
    "addr:full":"263 State Rte 31 Washington NJ 07882",
    "addr:housenumber":"263",
    "addr:postcode":"07882",
    "addr:street":"State Rte 31",
    "iso:country":"US",
    "sg:address":"263 State Rte 31",
    "sg:city":"Washington",
    "sg:classifiers":[
        {
            "category":"Retail",
            "subcategory":"Veterinary Services",
            "type":"Services"
        }
    ],
    "sg:phone":"+1 908 689 3267",
    "sg:postcode":"07882",
    "sg:province":"NJ",
    "sg:tags":[
        "veterinarian"
    ],
    "wof:name":"Washington Animal Hospital",
    "wof:placetype":"venue"
},
  "geometry": {"coordinates":[-74.979648,40.770761],"type":"Point"}
}