{
  "type": "Feature",
  "properties": {
    "iso:country":"US",
    "sg:address":"291 Amboy Ave",
    "sg:city":"Woodbridge",
    "sg:classifiers":[
        {
            "category":"Building & Trades",
            "subcategory":"Cleaning & Sanitation",
            "type":"Services"
        }
    ],
    "sg:phone":"+1 732 634 2646",
    "sg:postcode":"07095",
    "sg:province":"NJ",
    "sg:tags":[
        "house"
    ],
    "wof:name":"Sunshine Cleaning Svc",
    "wof:placetype":"venue"
},
  "geometry": {"coordinates":[-74.27979999999999,40.550067],"type":"Point"}
}