{
  "type": "Feature",
  "properties": {
    "addr:full":"1 Old Wolfe Rd Budd Lake NJ 07828",
    "addr:housenumber":"1",
    "addr:postcode":"07828",
    "addr:street":"Old Wolfe Rd",
    "iso:country":"US",
    "sg:address":"1 Old Wolfe Rd",
    "sg:city":"Budd Lake",
    "sg:classifiers":[
        {
            "category":"Building & Trades",
            "subcategory":"Cleaning & Sanitation",
            "type":"Services"
        }
    ],
    "sg:phone":"+1 973 347 3555",
    "sg:postcode":"07828",
    "sg:province":"NJ",
    "sg:tags":[
        "house"
    ],
    "wof:name":"Cleaning Authority",
    "wof:placetype":"venue"
},
  "geometry": {"coordinates":[-74.750663,40.862527],"type":"Point"}
}