{
  "type": "Feature",
  "properties": {
    "addr:full":"2222 South Ave Scotch Plains NJ 07076",
    "addr:housenumber":"2222",
    "addr:postcode":"07076",
    "addr:street":"South Ave",
    "iso:country":"US",
    "sg:address":"2222 South Ave",
    "sg:city":"Scotch Plains",
    "sg:classifiers":[
        {
            "category":"Banks & Credit Unions",
            "subcategory":"Bank",
            "type":"Services"
        }
    ],
    "sg:phone":"+1   ",
    "sg:postcode":"07076",
    "sg:province":"NJ",
    "sg:tags":[
        "national",
        "commercial"
    ],
    "wof:name":"First Community Bank",
    "wof:placetype":"venue"
},
  "geometry": {"coordinates":[-74.37127,40.645419],"type":"Point"}
}