{
  "type": "Feature",
  "properties": {
    "addr:full":"50 Buena Vista Dr Freehold NJ 07728",
    "addr:housenumber":"50",
    "addr:postcode":"07728",
    "addr:street":"Buena Vista Dr",
    "iso:country":"US",
    "sg:address":"50 Buena Vista Dr",
    "sg:city":"Freehold",
    "sg:classifiers":[
        {
            "category":"Professional",
            "subcategory":"Management & Consulting",
            "type":"Services"
        }
    ],
    "sg:phone":"+1   ",
    "sg:postcode":"07728",
    "sg:province":"NJ",
    "sg:tags":[
        "business"
    ],
    "wof:name":"Edward J Naphor",
    "wof:placetype":"venue"
},
  "geometry": {"coordinates":[-74.221907,40.254689],"type":"Point"}
}