{
  "type": "Feature",
  "properties": {
    "addr:full":"205 Nassau St Princeton NJ 08542",
    "addr:housenumber":"205",
    "addr:postcode":"08542",
    "addr:street":"Nassau St",
    "iso:country":"US",
    "sg:address":"205 Nassau St",
    "sg:city":"Princeton",
    "sg:classifiers":[
        {
            "category":"Building & Trades",
            "subcategory":"Construction",
            "type":"Services"
        }
    ],
    "sg:phone":"+1 609 924 4897",
    "sg:postcode":"08542",
    "sg:province":"NJ",
    "sg:tags":[
        "floor",
        "laying",
        "contractor"
    ],
    "wof:name":"Best Floor Co",
    "wof:placetype":"venue"
},
  "geometry": {"coordinates":[-74.652913,40.351645],"type":"Point"}
}