{
  "type": "Feature",
  "properties": {
    "addr:full":"2309 E Evesham Rd Voorhees NJ 08043",
    "addr:housenumber":"2309",
    "addr:postcode":"08043",
    "addr:street":"E Evesham Rd",
    "iso:country":"US",
    "sg:address":"2309 E Evesham Rd",
    "sg:city":"Voorhees",
    "sg:classifiers":[
        {
            "category":"Health Services",
            "subcategory":"Doctor",
            "type":"Services"
        }
    ],
    "sg:phone":"+1   ",
    "sg:postcode":"08043",
    "sg:province":"NJ",
    "sg:tags":[
        "physician"
    ],
    "wof:name":"Arthritus & Rhuemanic Disease",
    "wof:placetype":"venue"
},
  "geometry": {"coordinates":[-74.96177299999999,39.864129],"type":"Point"}
}