{
  "type": "Feature",
  "properties": {
    "addr:full":"416 Watchung Ave Plainfield NJ 07060",
    "addr:housenumber":"416",
    "addr:postcode":"07060",
    "addr:street":"Watchung Ave",
    "iso:country":"US",
    "sg:address":"416 Watchung Ave",
    "sg:city":"Plainfield",
    "sg:classifiers":[
        {
            "category":"Food & Beverages",
            "subcategory":"Groceries & Convenience Stores",
            "type":"Retail Goods"
        }
    ],
    "sg:phone":"+1   ",
    "sg:postcode":"07060",
    "sg:province":"NJ",
    "wof:name":"Ladominican Grocery",
    "wof:placetype":"venue"
},
  "geometry": {"coordinates":[-74.418708,40.618425],"type":"Point"}
}