{
  "type": "Feature",
  "properties": {
    "addr:full":"118 9th Ave Seaside Park NJ 08752",
    "addr:housenumber":"118",
    "addr:postcode":"08752",
    "addr:street":"9Th Ave",
    "iso:country":"US",
    "sg:address":"118 9th Ave",
    "sg:city":"Seaside Park",
    "sg:classifiers":[
        {
            "category":"Professional",
            "type":"Services"
        }
    ],
    "sg:phone":"+1 732 793 6211",
    "sg:postcode":"08752",
    "sg:province":"NJ",
    "sg:tags":[
        "establishment"
    ],
    "wof:name":"T W Smith LLC",
    "wof:placetype":"venue"
},
  "geometry": {"coordinates":[-74.08019299999999,39.91687],"type":"Point"}
}