{
  "type": "Feature",
  "properties": {
    "iso:country":"US",
    "sg:address":"208 3rd Ave",
    "sg:city":"Asbury Park",
    "sg:classifiers":[
        {
            "category":"Health Services",
            "subcategory":"Health Practitioner",
            "type":"Services"
        }
    ],
    "sg:phone":"+1 732 775 7575",
    "sg:postcode":"07712",
    "sg:province":"NJ",
    "sg:tags":[
        "dietitian"
    ],
    "wof:name":"Abunda Life Medical Nutrition",
    "wof:placetype":"venue"
},
  "geometry": {"coordinates":[-74.003451,40.22193],"type":"Point"}
}