{
  "type": "Feature",
  "properties": {
    "addr:full":"503 Washington Blvd Browns Mills NJ 08015",
    "addr:housenumber":"503",
    "addr:postcode":"08015",
    "addr:street":"Washington Blvd",
    "iso:country":"US",
    "sg:address":"503 Washington Blvd",
    "sg:city":"Browns Mills",
    "sg:classifiers":[
        {
            "category":"Professional",
            "subcategory":"Art Services",
            "type":"Services"
        }
    ],
    "sg:phone":"+1   ",
    "sg:postcode":"08015",
    "sg:province":"NJ",
    "sg:tags":[
        "commercial",
        "design"
    ],
    "wof:name":"Profile Design",
    "wof:placetype":"venue"
},
  "geometry": {"coordinates":[-74.56756900000001,39.909066],"type":"Point"}
}