{
  "type": "Feature",
  "properties": {
    "addr:full":"5 Heathwood Ln Trenton NJ 08620",
    "addr:housenumber":"5",
    "addr:postcode":"08620",
    "addr:street":"Heathwood Ln",
    "iso:country":"US",
    "sg:address":"5 Heathwood Ln",
    "sg:city":"Trenton",
    "sg:classifiers":[
        {
            "category":"Building & Trades",
            "subcategory":"Plumbing",
            "type":"Services"
        }
    ],
    "sg:phone":"+1 609 208 9001",
    "sg:postcode":"08620",
    "sg:province":"NJ",
    "sg:tags":[
        "plumbing",
        "air",
        "conditioning",
        "heating"
    ],
    "wof:name":"Hvac Air Conditioning & Htg",
    "wof:placetype":"venue"
},
  "geometry": {"coordinates":[-74.603066,40.157324],"type":"Point"}
}