{
  "type": "Feature",
  "properties": {
    "addr:full":"466 W Broad St Westfield NJ 07090",
    "addr:housenumber":"466",
    "addr:postcode":"07090",
    "addr:street":"W Broad St",
    "iso:country":"US",
    "sg:address":"466 W Broad St",
    "sg:city":"Westfield",
    "sg:classifiers":[
        {
            "category":"Retail",
            "subcategory":"Repair Shop",
            "type":"Services"
        }
    ],
    "sg:phone":"+1 908 364 0186",
    "sg:postcode":"07090",
    "sg:province":"NJ",
    "sg:tags":[
        "lock",
        "locksmith"
    ],
    "wof:name":"USA Locksmith",
    "wof:placetype":"venue"
},
  "geometry": {"coordinates":[-74.35330399999999,40.647091],"type":"Point"}
}