{
  "type": "Feature",
  "properties": {
    "addr:full":"2193 Spruce St Trenton NJ 08638",
    "addr:housenumber":"2193",
    "addr:postcode":"08638",
    "addr:street":"Spruce St",
    "iso:country":"US",
    "sg:address":"2193 Spruce St",
    "sg:city":"Trenton",
    "sg:classifiers":[
        {
            "category":"Professional",
            "subcategory":"Engineering",
            "type":"Services"
        }
    ],
    "sg:phone":"+1 609 882 0616",
    "sg:postcode":"08638",
    "sg:province":"NJ",
    "sg:tags":[
        "surveying",
        "engineer"
    ],
    "wof:name":"Trenton Engineering Co Inc",
    "wof:placetype":"venue"
},
  "geometry": {"coordinates":[-74.756764,40.249206],"type":"Point"}
}