{
  "type": "Feature",
  "properties": {
    "addr:full":"1901 State Rte 27 Edison NJ 08817",
    "addr:housenumber":"1901",
    "addr:postcode":"08817",
    "addr:street":"State Rte 27",
    "iso:country":"US",
    "sg:address":"1901 State Rte 27",
    "sg:city":"Edison",
    "sg:classifiers":[
        {
            "category":"Professional",
            "subcategory":"Lawyer & Legal Services",
            "type":"Services"
        }
    ],
    "sg:phone":"+1 732 985 3800",
    "sg:postcode":"08817",
    "sg:province":"NJ",
    "sg:tags":[
        "attorney"
    ],
    "wof:name":"Anthony J Marra Jr",
    "wof:placetype":"venue"
},
  "geometry": {"coordinates":[-74.399142,40.517607],"type":"Point"}
}