{
  "type": "Feature",
  "properties": {
    "addr:full":"126 College Ave New Brunswick NJ 08901",
    "addr:housenumber":"126",
    "addr:postcode":"08901",
    "addr:street":"College Ave",
    "iso:country":"US",
    "sg:address":"126 College Ave",
    "sg:city":"New Brunswick",
    "sg:classifiers":[
        {
            "category":"Communications",
            "subcategory":"Film & Video Production",
            "type":"Services"
        }
    ],
    "sg:phone":"+1 732 937 9799",
    "sg:postcode":"08901",
    "sg:province":"NJ",
    "sg:tags":[
        "taping"
    ],
    "wof:name":"Knight Vision Productions",
    "wof:placetype":"venue"
},
  "geometry": {"coordinates":[-74.451363,40.502507],"type":"Point"}
}