{
  "type": "Feature",
  "properties": {
    "iso:country":"US",
    "sg:address":"25 E Willow St Ste 3B",
    "sg:city":"Millburn",
    "sg:classifiers":[
        {
            "category":"Health Services",
            "subcategory":"Clinic",
            "type":"Services"
        }
    ],
    "sg:phone":"+1 973 912 4448",
    "sg:postcode":"07041",
    "sg:province":"NJ",
    "sg:tags":[
        "spa",
        "medical"
    ],
    "sg:website":"www.alistwellnesscenter.com/",
    "wof:name":"Alist Wellness Center",
    "wof:placetype":"venue"
},
  "geometry": {"coordinates":[-74.305481,40.71687],"type":"Point"}
}