{
  "type": "Feature",
  "properties": {
    "addr:full":"577 New Brunswick Ave Fords NJ 08863",
    "addr:housenumber":"577",
    "addr:postcode":"08863",
    "addr:street":"New Brunswick Ave",
    "iso:country":"US",
    "sg:address":"577 New Brunswick Ave",
    "sg:city":"Fords",
    "sg:classifiers":[
        {
            "category":"Restaurant",
            "type":"Food & Drink"
        }
    ],
    "sg:phone":"+1 732 738 9770",
    "sg:postcode":"08863",
    "sg:province":"NJ",
    "sg:tags":[
        "eating"
    ],
    "wof:name":"Bamboo House & Buffet",
    "wof:placetype":"venue"
},
  "geometry": {"coordinates":[-74.315697,40.528702],"type":"Point"}
}