{
  "type": "Feature",
  "properties": {
    "addr:full":"390 Newman Springs Rd Red Bank NJ 07701",
    "addr:housenumber":"390",
    "addr:postcode":"07701",
    "addr:street":"Newman Springs Rd",
    "iso:country":"US",
    "sg:address":"390 Newman Springs Rd",
    "sg:city":"Red Bank",
    "sg:classifiers":[
        {
            "category":"Autos & Motor Vehicles",
            "subcategory":"Fuel & Gas Station",
            "type":"Retail Goods"
        }
    ],
    "sg:phone":"+1 732 219 8709",
    "sg:postcode":"07701",
    "sg:province":"NJ",
    "sg:tags":[
        "oil"
    ],
    "wof:name":"Shell",
    "wof:placetype":"venue"
},
  "geometry": {"coordinates":[-74.096752,40.336672],"type":"Point"}
}