{
  "type": "Feature",
  "properties": {
    "iso:country":"US",
    "sg:address":"623 Lafayette Ave",
    "sg:city":"Hawthorne",
    "sg:classifiers":[
        {
            "category":"Health Services",
            "subcategory":"Doctor",
            "type":"Services"
        }
    ],
    "sg:phone":"+1 973 423 3833",
    "sg:postcode":"07506",
    "sg:province":"NJ",
    "sg:tags":[
        "physician",
        "surgeon"
    ],
    "wof:name":"Michael Giglio MD PA",
    "wof:placetype":"venue"
},
  "geometry": {"coordinates":[-74.155548,40.958975],"type":"Point"}
}