{
  "type": "Feature",
  "properties": {
    "iso:country":"US",
    "sg:address":"404 E Edsall Blvd",
    "sg:city":"Palisades Park",
    "sg:classifiers":[
        {
            "category":"Personal",
            "type":"Services"
        }
    ],
    "sg:phone":"+1 201 945 1135",
    "sg:postcode":"07650",
    "sg:province":"NJ",
    "sg:tags":[
        "towing"
    ],
    "wof:name":"Tcb Towing",
    "wof:placetype":"venue"
},
  "geometry": {"coordinates":[-73.9851,40.846699],"type":"Point"}
}