{
  "type": "Feature",
  "properties": {
    "addr:full":"29 Pine St Passaic NJ 07055",
    "addr:housenumber":"29",
    "addr:postcode":"07055",
    "addr:street":"Pine St",
    "iso:country":"US",
    "sg:address":"29 Pine St",
    "sg:city":"Passaic",
    "sg:classifiers":[
        {
            "category":"Manufacturing",
            "subcategory":"Printing",
            "type":"Manufacturing & Wholesale Goods"
        }
    ],
    "sg:phone":"+1 973 574 9926",
    "sg:postcode":"07055",
    "sg:province":"NJ",
    "sg:tags":[
        "publisher",
        "software"
    ],
    "wof:name":"Saul Diaz Diasol Records",
    "wof:placetype":"venue"
},
  "geometry": {"coordinates":[-74.138318,40.867109],"type":"Point"}
}