{
  "type": "Feature",
  "properties": {
    "iso:country":"US",
    "sg:address":"1872 State Rte 35",
    "sg:city":"South Amboy",
    "sg:classifiers":[
        {
            "category":"Health Services",
            "subcategory":"Doctor",
            "type":"Services"
        }
    ],
    "sg:phone":"+1 732 727 7470",
    "sg:postcode":"08879",
    "sg:province":"NJ",
    "sg:tags":[
        "physician",
        "surgeon"
    ],
    "wof:name":"Rodolfo C Ouano MD",
    "wof:placetype":"venue"
},
  "geometry": {"coordinates":[-74.274501,40.464091],"type":"Point"}
}