{
  "type": "Feature",
  "properties": {
    "iso:country":"US",
    "sg:address":"166 Main St",
    "sg:city":"Lincoln Park",
    "sg:classifiers":[
        {
            "category":"Manufacturing",
            "subcategory":"Printing",
            "type":"Manufacturing & Wholesale Goods"
        }
    ],
    "sg:phone":"+1 973 696 8008",
    "sg:postcode":"07035",
    "sg:province":"NJ",
    "sg:tags":[
        "publisher"
    ],
    "wof:name":"Life & Leasure",
    "wof:placetype":"venue"
},
  "geometry": {"coordinates":[-74.30761800000001,40.922873],"type":"Point"}
}