{
  "type": "Feature",
  "properties": {
    "iso:country":"US",
    "sg:address":"63 Lacey Rd",
    "sg:city":"Whiting",
    "sg:classifiers":[
        {
            "category":"Health Services",
            "subcategory":"Medical Lab",
            "type":"Services"
        }
    ],
    "sg:phone":"+1 732 849 0276",
    "sg:postcode":"08759",
    "sg:province":"NJ",
    "sg:tags":[
        "laboratory"
    ],
    "wof:name":"Laboratory Corp Of America",
    "wof:placetype":"venue"
},
  "geometry": {"coordinates":[-74.36491599999999,39.947635],"type":"Point"}
}