{
  "type": "Feature",
  "properties": {
    "iso:country":"US",
    "sg:address":"150 Johnson Ave",
    "sg:city":"Dumont",
    "sg:classifiers":[
        {
            "category":"Building & Trades",
            "subcategory":"Electrical",
            "type":"Services"
        }
    ],
    "sg:phone":"+1 201 384 1944",
    "sg:postcode":"07628",
    "sg:province":"NJ",
    "sg:tags":[
        "electrical",
        "contractor"
    ],
    "wof:name":"Roberge Electric Inc",
    "wof:placetype":"venue"
},
  "geometry": {"coordinates":[-73.999281,40.941683],"type":"Point"}
}