{
  "type": "Feature",
  "properties": {
    "iso:country":"US",
    "sg:address":"800 Broad St",
    "sg:city":"Newark",
    "sg:classifiers":[
        {
            "category":"Shopping",
            "subcategory":"Pharmacy",
            "type":"Retail Goods"
        }
    ],
    "sg:phone":"+1 973 596 1800",
    "sg:postcode":"07102",
    "sg:province":"NJ",
    "sg:tags":[
        "drug",
        "store"
    ],
    "wof:name":"Nick's Drugs",
    "wof:placetype":"venue"
},
  "geometry": {"coordinates":[-74.172293,40.735322],"type":"Point"}
}