{
  "type": "Feature",
  "properties": {
    "addr:full":"85 Delanco Dr Parsippany NJ 07054",
    "addr:housenumber":"85",
    "addr:postcode":"07054",
    "addr:street":"Delanco Dr",
    "iso:country":"US",
    "sg:address":"85 Delanco Dr",
    "sg:city":"Parsippany",
    "sg:classifiers":[
        {
            "category":"Professional",
            "subcategory":"Computer Services",
            "type":"Services"
        }
    ],
    "sg:phone":"+1   ",
    "sg:postcode":"07054",
    "sg:province":"NJ",
    "sg:tags":[
        "related"
    ],
    "wof:name":"Accord Business Inc",
    "wof:placetype":"venue"
},
  "geometry": {"coordinates":[-74.445699,40.856451],"type":"Point"}
}