{
  "type": "Feature",
  "properties": {
    "addr:full":"51 Sunset Rd Belle Mead NJ 08502",
    "addr:housenumber":"51",
    "addr:postcode":"08502",
    "addr:street":"Sunset Rd",
    "iso:country":"US",
    "sg:address":"51 Sunset Rd",
    "sg:city":"Belle Mead",
    "sg:classifiers":[
        {
            "category":"Autos & Motor Vehicles",
            "subcategory":"Auto Supplies",
            "type":"Retail Goods"
        }
    ],
    "sg:phone":"+1   ",
    "sg:postcode":"08502",
    "sg:province":"NJ",
    "wof:name":"Top End Motorsports",
    "wof:placetype":"venue"
},
  "geometry": {"coordinates":[-74.66867999999999,40.43682],"type":"Point"}
}