{
  "type": "Feature",
  "properties": {
    "addr:full":"4312 New York Ave Union City NJ 07087",
    "addr:housenumber":"4312",
    "addr:postcode":"07087",
    "addr:street":"New York Ave",
    "iso:country":"US",
    "sg:address":"4312 New York Ave",
    "sg:city":"Union City",
    "sg:classifiers":[
        {
            "category":"Retail",
            "subcategory":"Repair Shop",
            "type":"Services"
        }
    ],
    "sg:phone":"+1 201 223 4334",
    "sg:postcode":"07087",
    "sg:province":"NJ",
    "sg:tags":[
        "jewelry"
    ],
    "wof:name":"Gold Metals Jewelry Repair",
    "wof:placetype":"venue"
},
  "geometry": {"coordinates":[-74.02295599999999,40.778039],"type":"Point"}
}