{
  "type": "Feature",
  "properties": {
    "iso:country":"US",
    "sg:address":"551 Broad St",
    "sg:city":"Bloomfield",
    "sg:classifiers":[
        {
            "category":"Shopping",
            "subcategory":"Florist",
            "type":"Retail Goods"
        }
    ],
    "sg:phone":"+1 973 748 0655",
    "sg:postcode":"07003",
    "sg:province":"NJ",
    "wof:name":"Brookside Garden Center",
    "wof:placetype":"venue"
},
  "geometry": {"coordinates":[-74.194298,40.812599],"type":"Point"}
}