{
  "type": "Feature",
  "properties": {
    "addr:full":"159 S Orange Ave South Orange NJ 07079",
    "addr:housenumber":"159",
    "addr:postcode":"07079",
    "addr:street":"S Orange Ave",
    "iso:country":"US",
    "sg:address":"159 S Orange Ave",
    "sg:city":"South Orange",
    "sg:classifiers":[
        {
            "category":"Autos & Motor Vehicles",
            "subcategory":"Fuel & Gas Station",
            "type":"Retail Goods"
        }
    ],
    "sg:phone":"+1 973 378 7980",
    "sg:postcode":"07079",
    "sg:province":"NJ",
    "sg:tags":[
        "oil"
    ],
    "wof:name":"A J Auto & Gas",
    "wof:placetype":"venue"
},
  "geometry": {"coordinates":[-74.25404899999999,40.745234],"type":"Point"}
}