{
  "type": "Feature",
  "properties": {
    "addr:full":"63 Sylvan Ln Willingboro NJ 08046",
    "addr:housenumber":"63",
    "addr:postcode":"08046",
    "addr:street":"Sylvan Ln",
    "iso:country":"US",
    "sg:address":"63 Sylvan Ln",
    "sg:city":"Willingboro",
    "sg:classifiers":[
        {
            "category":"Organizations",
            "subcategory":"Non-profit Organization",
            "type":"Services"
        }
    ],
    "sg:phone":"+1 609 835 7757",
    "sg:postcode":"08046",
    "sg:province":"NJ",
    "sg:tags":[
        "charity",
        "foundations-educational",
        "philanthropic",
        "research"
    ],
    "wof:name":"Society Of St Vincent De Paul Council Of The United States",
    "wof:placetype":"venue"
},
  "geometry": {"coordinates":[-74.900206,40.041108],"type":"Point"}
}