{
  "type": "Feature",
  "properties": {
    "addr:full":"133 W 24th St Bayonne NJ 07002",
    "addr:housenumber":"133",
    "addr:postcode":"07002",
    "addr:street":"W 24Th St",
    "iso:country":"US",
    "sg:address":"133 W 24th St",
    "sg:city":"Bayonne",
    "sg:classifiers":[
        {
            "category":"Organizations",
            "subcategory":"Religious Organization",
            "type":"Services"
        }
    ],
    "sg:phone":"+1 201 339 5110",
    "sg:postcode":"07002",
    "sg:province":"NJ",
    "sg:tags":[
        "church"
    ],
    "wof:name":"Christian Church Of Bayonne",
    "wof:placetype":"venue"
},
  "geometry": {"coordinates":[-74.123108,40.667447],"type":"Point"}
}