{
  "type": "Feature",
  "properties": {
    "addr:full":"19 Mechanic St Millburn NJ 07041",
    "addr:housenumber":"19",
    "addr:postcode":"07041",
    "addr:street":"Mechanic St",
    "iso:country":"US",
    "sg:address":"19 Mechanic St",
    "sg:city":"Millburn",
    "sg:classifiers":[
        {
            "category":"Professional",
            "type":"Services"
        }
    ],
    "sg:phone":"+1 973 564 5010",
    "sg:postcode":"07041",
    "sg:province":"NJ",
    "sg:tags":[
        "establishment"
    ],
    "wof:name":"Bhl Enterprises Inc",
    "wof:placetype":"venue"
},
  "geometry": {"coordinates":[-74.31028999999999,40.716252],"type":"Point"}
}