{
  "type": "Feature",
  "properties": {
    "addr:full":"10 Deer Run Blairstown NJ 07825",
    "addr:housenumber":"10",
    "addr:postcode":"07825",
    "addr:street":"Deer Run",
    "iso:country":"US",
    "sg:address":"10 Deer Run",
    "sg:city":"Blairstown",
    "sg:classifiers":[
        {
            "category":"Professional",
            "subcategory":"Business Services",
            "type":"Services"
        }
    ],
    "sg:phone":"+1   ",
    "sg:postcode":"07825",
    "sg:province":"NJ",
    "wof:name":"Elite Commercial Corporat",
    "wof:placetype":"venue"
},
  "geometry": {"coordinates":[-75.01005600000001,41.004341],"type":"Point"}
}