{
  "type": "Feature",
  "properties": {
    "iso:country":"US",
    "sg:address":"48 Green St",
    "sg:city":"Newark",
    "sg:classifiers":[
        {
            "category":"Professional",
            "subcategory":"Business Services",
            "type":"Services"
        }
    ],
    "sg:phone":"+1 973 643 7900",
    "sg:postcode":"07102",
    "sg:province":"NJ",
    "sg:tags":[
        "recording",
        "studio"
    ],
    "wof:name":"Green Street Studios",
    "wof:placetype":"venue"
},
  "geometry": {"coordinates":[-74.172967,40.732239],"type":"Point"}
}