{
  "type": "Feature",
  "properties": {
    "addr:full":"16 Pitman Ave Pitman NJ 08071",
    "addr:housenumber":"16",
    "addr:postcode":"08071",
    "addr:street":"Pitman Ave",
    "iso:country":"US",
    "sg:address":"16 Pitman Ave",
    "sg:city":"Pitman",
    "sg:classifiers":[
        {
            "category":"Building & Trades",
            "subcategory":"Landscaping Services",
            "type":"Services"
        }
    ],
    "sg:phone":"+1 856 256 7947",
    "sg:postcode":"08071",
    "sg:province":"NJ",
    "sg:tags":[
        "landscape",
        "contractor"
    ],
    "wof:name":"Weed Man",
    "wof:placetype":"venue"
},
  "geometry": {"coordinates":[-75.12949999999999,39.731855],"type":"Point"}
}