{
  "type": "Feature",
  "properties": {
    "iso:country":"US",
    "sg:address":"241 Wilder St",
    "sg:city":"Hillside",
    "sg:classifiers":[
        {
            "category":"Personal",
            "type":"Services"
        }
    ],
    "sg:phone":"+1 908 527 1747",
    "sg:postcode":"07205",
    "sg:province":"NJ",
    "sg:tags":[
        "electrolysis"
    ],
    "wof:name":"Zoe Antipatis",
    "wof:placetype":"venue"
},
  "geometry": {"coordinates":[-74.22393700000001,40.681886],"type":"Point"}
}