{
  "type": "Feature",
  "properties": {
    "addr:full":"82 Bennett Ave Neptune NJ 07753",
    "addr:housenumber":"82",
    "addr:postcode":"07753",
    "addr:street":"Bennett Ave",
    "iso:country":"US",
    "sg:address":"82 Bennett Ave",
    "sg:city":"Neptune",
    "sg:classifiers":[
        {
            "category":"Wholesale",
            "subcategory":"Machinery & Supplies",
            "type":"Manufacturing & Wholesale Goods"
        }
    ],
    "sg:phone":"+1 732 774 4000",
    "sg:postcode":"07753",
    "sg:province":"NJ",
    "sg:tags":[
        "fire",
        "department",
        "equipment"
    ],
    "wof:name":"Dependable Turnout Gear Repair",
    "wof:placetype":"venue"
},
  "geometry": {"coordinates":[-74.03577900000001,40.202208],"type":"Point"}
}