{
  "type": "Feature",
  "properties": {
    "addr:full":"106 Mansfield St Belvidere NJ 07823",
    "addr:housenumber":"106",
    "addr:postcode":"07823",
    "addr:street":"Mansfield St",
    "iso:country":"US",
    "sg:address":"106 Mansfield St",
    "sg:city":"Belvidere",
    "sg:classifiers":[
        {
            "category":"Education",
            "subcategory":"Special Training",
            "type":"Public Place"
        }
    ],
    "sg:phone":"+1 908 475 1958",
    "sg:postcode":"07823",
    "sg:province":"NJ",
    "sg:tags":[
        "instruction",
        "driving"
    ],
    "wof:name":"Formula One Driving School",
    "wof:placetype":"venue"
},
  "geometry": {"coordinates":[-75.077444,40.828233],"type":"Point"}
}