{
  "type": "Feature",
  "properties": {
    "addr:full":"40 Rustic Mall Manville NJ 08835",
    "addr:housenumber":"40",
    "addr:postcode":"08835",
    "addr:street":"Rustic Mall",
    "iso:country":"US",
    "sg:address":"40 Rustic Mall",
    "sg:city":"Manville",
    "sg:classifiers":[
        {
            "category":"Wholesale",
            "subcategory":"Sporting Goods",
            "type":"Manufacturing & Wholesale Goods"
        }
    ],
    "sg:phone":"+1 908 252 0606",
    "sg:postcode":"08835",
    "sg:province":"NJ",
    "sg:tags":[
        "equipment",
        "pool",
        "swimming"
    ],
    "wof:name":"Leslie's Swimming Pool Supply",
    "wof:placetype":"venue"
},
  "geometry": {"coordinates":[-74.585807,40.54241],"type":"Point"}
}