{
  "type": "Feature",
  "properties": {
    "iso:country":"US",
    "sg:address":"303 S Black Horse Pike",
    "sg:city":"Blackwood",
    "sg:classifiers":[
        {
            "category":"Manufacturing",
            "subcategory":"Printing",
            "type":"Manufacturing & Wholesale Goods"
        }
    ],
    "sg:phone":"+1 856 232 7200",
    "sg:postcode":"08012",
    "sg:province":"NJ",
    "sg:tags":[
        "bookbinder",
        "commercial",
        "typesetting"
    ],
    "wof:name":"Pronto Press",
    "wof:placetype":"venue"
},
  "geometry": {"coordinates":[-75.063886,39.796628],"type":"Point"}
}