{
  "type": "Feature",
  "properties": {
    "addr:full":"56 Llewellyn Rd Montclair NJ 07042",
    "addr:housenumber":"56",
    "addr:postcode":"07042",
    "addr:street":"Llewellyn Rd",
    "iso:country":"US",
    "sg:address":"56 Llewellyn Rd",
    "sg:city":"Montclair",
    "sg:classifiers":[
        {
            "category":"Retail",
            "subcategory":"Portrait Studio",
            "type":"Services"
        }
    ],
    "sg:phone":"+1 973 655 9494",
    "sg:postcode":"07042",
    "sg:province":"NJ",
    "sg:tags":[
        "photographer"
    ],
    "wof:name":"Martin Ahrens Photography",
    "wof:placetype":"venue"
},
  "geometry": {"coordinates":[-74.22374499999999,40.803519],"type":"Point"}
}