{
  "type": "Feature",
  "properties": {
    "iso:country":"US",
    "sg:address":"148 Shunpike Rd",
    "sg:city":"Springfield",
    "sg:classifiers":[
        {
            "category":"Shopping",
            "subcategory":"Clothing, Apparel, & Fashions",
            "type":"Retail Goods"
        }
    ],
    "sg:phone":"+1   ",
    "sg:postcode":"07081",
    "sg:province":"NJ",
    "sg:tags":[
        "family"
    ],
    "wof:name":"Zach Lex Inc",
    "wof:placetype":"venue"
},
  "geometry": {"coordinates":[-74.325748,40.705487],"type":"Point"}
}