{
  "type": "Feature",
  "properties": {
    "iso:country":"US",
    "sg:address":"2505 Woodbridge Ave",
    "sg:city":"Edison",
    "sg:classifiers":[
        {
            "category":"Real Estate",
            "subcategory":"Real Estate Operator",
            "type":"Services"
        }
    ],
    "sg:phone":"+1   ",
    "sg:postcode":"08817",
    "sg:province":"NJ",
    "sg:tags":[
        "mobile",
        "home",
        "site"
    ],
    "wof:name":"Genisis Associates",
    "wof:placetype":"venue"
},
  "geometry": {"coordinates":[-74.37942700000001,40.504453],"type":"Point"}
}