{
  "type": "Feature",
  "properties": {
    "iso:country":"US",
    "sg:address":"343 State Rt 17",
    "sg:city":"Hasbrouck Heights",
    "sg:classifiers":[
        {
            "category":"Donuts",
            "subcategory":"None",
            "type":"Food & Drink"
        }
    ],
    "sg:phone":"+1 201 288 9639",
    "sg:postcode":"07604",
    "sg:province":"NJ",
    "wof:name":"Dunkin Donuts",
    "wof:placetype":"venue"
},
  "geometry": {"coordinates":[-74.06572199999999,40.861787],"type":"Point"}
}