{
  "type": "Feature",
  "properties": {
    "iso:country":"US",
    "sg:address":"307 Newton Ave",
    "sg:city":"Collingswood",
    "sg:classifiers":[
        {
            "category":"Professional",
            "subcategory":"Employment Agencies",
            "type":"Services"
        }
    ],
    "sg:phone":"+1 856 858 2637",
    "sg:postcode":"08108",
    "sg:province":"NJ",
    "wof:name":"The Hyman Companies Inc",
    "wof:placetype":"venue"
},
  "geometry": {"coordinates":[-75.073275,39.912483],"type":"Point"}
}