{
  "type": "Feature",
  "properties": {
    "addr:full":"3080 Ocean Heights Ave Egg Harbor Township NJ 08234",
    "addr:housenumber":"3080",
    "addr:postcode":"08234",
    "addr:street":"Ocean Heights Ave",
    "iso:country":"US",
    "sg:address":"3080 Ocean Heights Ave",
    "sg:city":"Egg Harbor Township",
    "sg:classifiers":[
        {
            "category":"Building & Trades",
            "subcategory":"Construction",
            "type":"Services"
        }
    ],
    "sg:phone":"+1 609 927 6882",
    "sg:postcode":"08234",
    "sg:province":"NJ",
    "sg:tags":[
        "contractor"
    ],
    "wof:name":"Henry Edward Block & Con Contr",
    "wof:placetype":"venue"
},
  "geometry": {"coordinates":[-74.612388,39.354768],"type":"Point"}
}