{
  "type": "Feature",
  "properties": {
    "iso:country":"US",
    "sg:address":"30 Carmel Ct",
    "sg:city":"Old Bridge",
    "sg:classifiers":[
        {
            "category":"Professional",
            "subcategory":"Management & Consulting",
            "type":"Services"
        }
    ],
    "sg:phone":"+1 908 217 3060",
    "sg:postcode":"08857",
    "sg:province":"NJ",
    "sg:tags":[
        "business"
    ],
    "wof:name":"Trained Prof Consulting",
    "wof:placetype":"venue"
},
  "geometry": {"coordinates":[-74.328307,40.387567],"type":"Point"}
}