{
  "type": "Feature",
  "properties": {
    "addr:full":"1889 State Rte 38 Southampton NJ 08088",
    "addr:housenumber":"1889",
    "addr:postcode":"08088",
    "addr:street":"State Rte 38",
    "iso:country":"US",
    "sg:address":"1889 State Rte 38",
    "sg:city":"Southampton",
    "sg:classifiers":[
        {
            "category":"Autos & Motor Vehicles",
            "subcategory":"Automobile Sales",
            "type":"Retail Goods"
        }
    ],
    "sg:phone":"+1 609 267 6969",
    "sg:postcode":"08088",
    "sg:province":"NJ",
    "sg:tags":[
        "car",
        "dealer"
    ],
    "wof:name":"Highline Cars",
    "wof:placetype":"venue"
},
  "geometry": {"coordinates":[-74.74288,39.972092],"type":"Point"}
}