{
  "type": "Feature",
  "properties": {
    "addr:full":"131 Edward Dr Swedesboro NJ 08085",
    "addr:housenumber":"131",
    "addr:postcode":"08085",
    "addr:street":"Edward Dr",
    "iso:country":"US",
    "sg:address":"131 Edward Dr",
    "sg:city":"Swedesboro",
    "sg:classifiers":[
        {
            "category":"Shopping",
            "subcategory":"Books",
            "type":"Retail Goods"
        }
    ],
    "sg:phone":"+1   ",
    "sg:postcode":"08085",
    "sg:province":"NJ",
    "wof:name":"Reading Books Are Fun",
    "wof:placetype":"venue"
},
  "geometry": {"coordinates":[-75.35465000000001,39.747998],"type":"Point"}
}