{
  "type": "Feature",
  "properties": {
    "addr:full":"950 S Chester Ave Delran NJ 08075",
    "addr:housenumber":"950",
    "addr:postcode":"08075",
    "addr:street":"S Chester Ave",
    "iso:country":"US",
    "sg:address":"950 S Chester Ave",
    "sg:city":"Delran",
    "sg:classifiers":[
        {
            "category":"Health Services",
            "subcategory":"Doctor",
            "type":"Services"
        }
    ],
    "sg:phone":"+1 856 461 3226",
    "sg:postcode":"08075",
    "sg:province":"NJ",
    "wof:name":"Pain and Spine Treatment Center",
    "wof:placetype":"venue"
},
  "geometry": {"coordinates":[-74.959031,40.020525],"type":"Point"}
}