{
  "type": "Feature",
  "properties": {
    "iso:country":"US",
    "sg:address":"1205 State Rte 35",
    "sg:city":"Neptune City",
    "sg:classifiers":[
        {
            "category":"Home & Garden",
            "subcategory":"Furniture",
            "type":"Retail Goods"
        }
    ],
    "sg:phone":"+1 732 531 3060",
    "sg:postcode":"07753",
    "sg:province":"NJ",
    "sg:tags":[
        "equipment",
        "kitchen",
        "cabinet"
    ],
    "wof:name":"Cabinet Factory Inc",
    "wof:placetype":"venue"
},
  "geometry": {"coordinates":[-74.025246,40.190207],"type":"Point"}
}