{
  "type": "Feature",
  "properties": {
    "iso:country":"US",
    "sg:address":"296 Main St",
    "sg:city":"Hackensack",
    "sg:classifiers":[
        {
            "category":"Restaurant",
            "type":"Food & Drink"
        }
    ],
    "sg:phone":"+1   ",
    "sg:postcode":"07601",
    "sg:province":"NJ",
    "wof:name":"Vandy Cafe",
    "wof:placetype":"venue"
},
  "geometry": {"coordinates":[-74.04063600000001,40.887936],"type":"Point"}
}