{
  "type": "Feature",
  "properties": {
    "iso:country":"US",
    "sg:address":"85 Chain Blvd",
    "sg:city":"Bayville",
    "sg:classifiers":[
        {
            "category":"Wholesale",
            "subcategory":"Sporting Goods",
            "type":"Manufacturing & Wholesale Goods"
        }
    ],
    "sg:phone":"+1 732 237 3383",
    "sg:postcode":"08721",
    "sg:province":"NJ",
    "wof:name":"R J Schneider & Associates",
    "wof:placetype":"venue"
},
  "geometry": {"coordinates":[-74.16117800000001,39.919086],"type":"Point"}
}