{
  "type": "Feature",
  "properties": {
    "addr:full":"574 Skylark Dr Monroe Township NJ 08831",
    "addr:housenumber":"574",
    "addr:postcode":"08831",
    "addr:street":"Skylark Dr",
    "iso:country":"US",
    "sg:address":"574 Skylark Dr",
    "sg:city":"Monroe Township",
    "sg:classifiers":[
        {
            "category":"Professional",
            "subcategory":"Engineering",
            "type":"Services"
        }
    ],
    "sg:phone":"+1   ",
    "sg:postcode":"08831",
    "sg:province":"NJ",
    "wof:name":"Evans and Methods Consultants",
    "wof:placetype":"venue"
},
  "geometry": {"coordinates":[-74.452202,40.305146],"type":"Point"}
}