{
  "type": "Feature",
  "properties": {
    "iso:country":"US",
    "sg:address":"144 Market St",
    "sg:city":"Kenilworth",
    "sg:classifiers":[
        {
            "category":"Shopping",
            "subcategory":"Computers & Home Electronics",
            "type":"Retail Goods"
        }
    ],
    "sg:phone":"+1 908 259 9007",
    "sg:postcode":"07033",
    "sg:province":"NJ",
    "sg:tags":[
        "equipment",
        "electronic",
        "supply"
    ],
    "wof:name":"Sabag Electronics USA LTD",
    "wof:placetype":"venue"
},
  "geometry": {"coordinates":[-74.279096,40.670693],"type":"Point"}
}