{
  "type": "Feature",
  "properties": {
    "addr:full":"7 Lillie Rd Toms River NJ 08753",
    "addr:housenumber":"7",
    "addr:postcode":"08753",
    "addr:street":"Lillie Rd",
    "iso:country":"US",
    "sg:address":"7 Lillie Rd",
    "sg:city":"Toms River",
    "sg:classifiers":[
        {
            "category":"Building & Trades",
            "subcategory":"Landscaping Services",
            "type":"Services"
        }
    ],
    "sg:phone":"+1 732 270 3555",
    "sg:postcode":"08753",
    "sg:province":"NJ",
    "wof:name":"Scottys Lawn & Landscape",
    "wof:placetype":"venue"
},
  "geometry": {"coordinates":[-74.126356,39.949432],"type":"Point"}
}