{
  "type": "Feature",
  "properties": {
    "addr:full":"14 Union St Rockaway NJ 07866",
    "addr:housenumber":"14",
    "addr:postcode":"07866",
    "addr:street":"Union St",
    "iso:country":"US",
    "sg:address":"14 Union St",
    "sg:city":"Rockaway",
    "sg:classifiers":[
        {
            "category":"Restaurant",
            "type":"Food & Drink"
        }
    ],
    "sg:phone":"+1 973 627 4002",
    "sg:postcode":"07866",
    "sg:province":"NJ",
    "sg:tags":[
        "delicatessen"
    ],
    "wof:name":"Quick Mart",
    "wof:placetype":"venue"
},
  "geometry": {"coordinates":[-74.507881,40.903904],"type":"Point"}
}