{
  "type": "Feature",
  "properties": {
    "iso:country":"US",
    "sg:address":"913 Deer Creek Dr",
    "sg:city":"Plainsboro",
    "sg:classifiers":[
        {
            "category":"Manufacturing",
            "subcategory":"Petroleum Products",
            "type":"Manufacturing & Wholesale Goods"
        }
    ],
    "sg:phone":"+1 609 716 6449",
    "sg:postcode":"08536",
    "sg:province":"NJ",
    "sg:tags":[
        "lubricant"
    ],
    "wof:name":"Lubriplate Lubricants",
    "wof:placetype":"venue"
},
  "geometry": {"coordinates":[-74.57270200000001,40.327747],"type":"Point"}
}