{
  "type": "Feature",
  "properties": {
    "iso:country":"US",
    "sg:address":"1909 Woodhollow Dr",
    "sg:city":"Marlton",
    "sg:classifiers":[
        {
            "category":"Professional",
            "type":"Services"
        }
    ],
    "sg:phone":"+1   ",
    "sg:postcode":"08053",
    "sg:province":"NJ",
    "wof:name":"Labor Zionist Alliance 25",
    "wof:placetype":"venue"
},
  "geometry": {"coordinates":[-74.94478100000001,39.913276],"type":"Point"}
}