{
  "type": "Feature",
  "properties": {
    "addr:full":"186 Inman Ave Colonia NJ 07067",
    "addr:housenumber":"186",
    "addr:postcode":"07067",
    "addr:street":"Inman Ave",
    "iso:country":"US",
    "sg:address":"186 Inman Ave",
    "sg:city":"Colonia",
    "sg:classifiers":[
        {
            "category":"Sports & Exercise",
            "subcategory":"Gym",
            "type":"Entertainment"
        }
    ],
    "sg:phone":"+1 732 382 4224",
    "sg:postcode":"07067",
    "sg:province":"NJ",
    "sg:tags":[
        "fitness",
        "physical",
        "facility"
    ],
    "wof:name":"Baby Power",
    "wof:placetype":"venue"
},
  "geometry": {"coordinates":[-74.31096100000001,40.600275],"type":"Point"}
}