{
  "type": "Feature",
  "properties": {
    "iso:country":"US",
    "sg:address":"2 William St",
    "sg:city":"Haskell",
    "sg:classifiers":[
        {
            "category":"Building & Trades",
            "subcategory":"Landscaping Services",
            "type":"Services"
        }
    ],
    "sg:phone":"+1 973 831 7799",
    "sg:postcode":"07420",
    "sg:province":"NJ",
    "wof:name":"Kodiak Landscape",
    "wof:placetype":"venue"
},
  "geometry": {"coordinates":[-74.305561,41.029276],"type":"Point"}
}