{
  "type": "Feature",
  "properties": {
    "iso:country":"US",
    "sg:address":"29 S Main St",
    "sg:city":"Woodstown",
    "sg:classifiers":[
        {
            "category":"Manufacturing",
            "subcategory":"Printing",
            "type":"Manufacturing & Wholesale Goods"
        }
    ],
    "sg:phone":"+1 856 769 1433",
    "sg:postcode":"08098",
    "sg:province":"NJ",
    "sg:tags":[
        "lithographic",
        "printer",
        "commercial"
    ],
    "wof:name":"John's Print Shoppe",
    "wof:placetype":"venue"
},
  "geometry": {"coordinates":[-75.32789099999999,39.650577],"type":"Point"}
}