{
  "type": "Feature",
  "properties": {
    "iso:country":"US",
    "sg:address":"919 State Rte 33",
    "sg:city":"Freehold",
    "sg:classifiers":[
        {
            "category":"Wholesale",
            "subcategory":"Electrical",
            "type":"Manufacturing & Wholesale Goods"
        }
    ],
    "sg:phone":"+1 732 303 9184",
    "sg:postcode":"07728",
    "sg:province":"NJ",
    "sg:tags":[
        "intercommunication"
    ],
    "wof:name":"Golden Eagle Intl",
    "wof:placetype":"venue"
},
  "geometry": {"coordinates":[-74.227346,40.238039],"type":"Point"}
}