{
  "type": "Feature",
  "properties": {
    "iso:country":"US",
    "sg:address":"427 Jackson Rd",
    "sg:city":"Atco",
    "sg:classifiers":[
        {
            "category":"Recreation",
            "type":"Entertainment"
        }
    ],
    "sg:phone":"+1 856 740 1407",
    "sg:postcode":"08004",
    "sg:province":"NJ",
    "sg:tags":[
        "amusement"
    ],
    "wof:name":"South Jersey Professional Sccr",
    "wof:placetype":"venue"
},
  "geometry": {"coordinates":[-74.877578,39.778852],"type":"Point"}
}