{
  "type": "Feature",
  "properties": {
    "addr:full":"604 N Wildwood Blvd Cape May Court House NJ 08210",
    "addr:housenumber":"604",
    "addr:postcode":"08210",
    "addr:street":"N Wildwood Blvd Cape May",
    "iso:country":"US",
    "sg:address":"604 N Wildwood Blvd",
    "sg:city":"Cape May Court House",
    "sg:classifiers":[
        {
            "category":"Home & Garden",
            "subcategory":"Furniture",
            "type":"Retail Goods"
        }
    ],
    "sg:phone":"+1 609 465 7370",
    "sg:postcode":"08210",
    "sg:province":"NJ",
    "sg:tags":[
        "store"
    ],
    "wof:name":"Totally Casual",
    "wof:placetype":"venue"
},
  "geometry": {"coordinates":[-74.84470399999999,39.042801],"type":"Point"}
}