{
  "type": "Feature",
  "properties": {
    "iso:country":"US",
    "sg:address":"1 Village Pl",
    "sg:city":"Neptune",
    "sg:classifiers":[
        {
            "category":"Shopping",
            "subcategory":"Jewelry",
            "type":"Retail Goods"
        }
    ],
    "sg:phone":"+1   ",
    "sg:postcode":"07753",
    "sg:province":"NJ",
    "sg:tags":[
        "shop",
        "beads"
    ],
    "wof:name":"Handcrafters Bead Shop",
    "wof:placetype":"venue"
},
  "geometry": {"coordinates":[-74.03224299999999,40.198457],"type":"Point"}
}