{
  "type": "Feature",
  "properties": {
    "iso:country":"US",
    "sg:address":"107 Bay Ave",
    "sg:city":"Forked River",
    "sg:classifiers":[
        {
            "category":"Professional",
            "subcategory":"Business Services",
            "type":"Services"
        }
    ],
    "sg:phone":"+1   ",
    "sg:postcode":"08731",
    "sg:province":"NJ",
    "sg:tags":[
        "marina",
        "dealer",
        "boat"
    ],
    "wof:name":"Forked River Yacht Sales",
    "wof:placetype":"venue"
},
  "geometry": {"coordinates":[-74.190629,39.834871],"type":"Point"}
}