{
  "type": "Feature",
  "properties": {
    "iso:country":"US",
    "sg:address":"55 Broad Ave",
    "sg:city":"Palisades Park",
    "sg:classifiers":[
        {
            "category":"Wholesale",
            "subcategory":"Hardware",
            "type":"Manufacturing & Wholesale Goods"
        }
    ],
    "sg:phone":"+1 201 313 0084",
    "sg:postcode":"07650",
    "sg:province":"NJ",
    "sg:tags":[
        "plumbing"
    ],
    "wof:name":"Eric Frohlich",
    "wof:placetype":"venue"
},
  "geometry": {"coordinates":[-74.000916,40.843632],"type":"Point"}
}