{
  "type": "Feature",
  "properties": {
    "iso:country":"US",
    "sg:address":"10 Saddle River Rd",
    "sg:city":"Fair Lawn",
    "sg:classifiers":[
        {
            "category":"Health Services",
            "subcategory":"Doctor",
            "type":"Services"
        }
    ],
    "sg:phone":"+1 201 797 8711",
    "sg:postcode":"07410",
    "sg:province":"NJ",
    "sg:tags":[
        "dentist"
    ],
    "wof:name":"Stahl Dental Studio",
    "wof:placetype":"venue"
},
  "geometry": {"coordinates":[-74.09094,40.920992],"type":"Point"}
}