{
  "type": "Feature",
  "properties": {
    "iso:country":"US",
    "sg:address":"262 State Rte 35",
    "sg:city":"Red Bank",
    "sg:classifiers":[
        {
            "category":"Professional",
            "subcategory":"Lawyer & Legal Services",
            "type":"Services"
        }
    ],
    "sg:phone":"+1 732 842 2070",
    "sg:postcode":"07701",
    "sg:province":"NJ",
    "sg:tags":[
        "attorney"
    ],
    "wof:name":"Carton & Assoc",
    "wof:placetype":"venue"
},
  "geometry": {"coordinates":[-74.083043,40.365364],"type":"Point"}
}