{
  "type": "Feature",
  "properties": {
    "iso:country":"US",
    "sg:address":"12 Woodland Cir",
    "sg:city":"Englishtown",
    "sg:classifiers":[
        {
            "category":"Wholesale",
            "subcategory":"Apparel",
            "type":"Manufacturing & Wholesale Goods"
        }
    ],
    "sg:phone":"+1 732 657 5021",
    "sg:postcode":"07726",
    "sg:province":"NJ",
    "sg:tags":[
        "for",
        "mfg",
        "imprinted",
        "sportswear",
        "representative"
    ],
    "wof:name":"S K Sales Inc",
    "wof:placetype":"venue"
},
  "geometry": {"coordinates":[-74.310678,40.307404],"type":"Point"}
}