{
  "type": "Feature",
  "properties": {
    "iso:country":"US",
    "sg:address":"1994 Springfield Ave",
    "sg:city":"Maplewood",
    "sg:classifiers":[
        {
            "category":"Food & Beverages",
            "subcategory":"Liquor & Beverages",
            "type":"Retail Goods"
        }
    ],
    "sg:phone":"+1 973 763 3778",
    "sg:postcode":"07040",
    "sg:province":"NJ",
    "wof:name":"Village Wine Shop",
    "wof:placetype":"venue"
},
  "geometry": {"coordinates":[-74.275633,40.719919],"type":"Point"}
}