{
  "type": "Feature",
  "properties": {
    "iso:country":"US",
    "sg:address":"1376 US Hwy 22",
    "sg:city":"Mountainside",
    "sg:classifiers":[
        {
            "category":"Manufacturing",
            "subcategory":"Printing",
            "type":"Manufacturing & Wholesale Goods"
        }
    ],
    "sg:phone":"+1 908 232 3600",
    "sg:postcode":"07092",
    "sg:province":"NJ",
    "sg:tags":[
        "printer"
    ],
    "wof:name":"Select Services",
    "wof:placetype":"venue"
},
  "geometry": {"coordinates":[-74.3567,40.672011],"type":"Point"}
}