{
  "type": "Feature",
  "properties": {
    "addr:full":"25 Tattletown Rd Trenton NJ 08620",
    "addr:housenumber":"25",
    "addr:postcode":"08620",
    "addr:street":"Tattletown Rd",
    "iso:country":"US",
    "sg:address":"25 Tattletown Rd",
    "sg:city":"Trenton",
    "sg:classifiers":[
        {
            "category":"Professional",
            "type":"Services"
        }
    ],
    "sg:phone":"+1   ",
    "sg:postcode":"08620",
    "sg:province":"NJ",
    "wof:name":"University Systems",
    "wof:placetype":"venue"
},
  "geometry": {"coordinates":[-74.62747400000001,40.163909],"type":"Point"}
}