{
  "type": "Feature",
  "properties": {
    "iso:country":"US",
    "sg:address":"1288 Sassafras Dr",
    "sg:city":"Vineland",
    "sg:classifiers":[
        {
            "category":"Restaurant",
            "type":"Food & Drink"
        }
    ],
    "sg:phone":"+1   ",
    "sg:postcode":"08360",
    "sg:province":"NJ",
    "sg:tags":[
        "eating"
    ],
    "wof:name":"Oriental Lotus",
    "wof:placetype":"venue"
},
  "geometry": {"coordinates":[-75.01183399999999,39.502697],"type":"Point"}
}