{
  "type": "Feature",
  "properties": {
    "iso:country":"US",
    "sg:address":"19 Mantua Rd",
    "sg:city":"Mt Royal",
    "sg:classifiers":[
        {
            "category":"Organizations",
            "subcategory":"Professional Association",
            "type":"Services"
        }
    ],
    "sg:phone":"+1 856 423 3629",
    "sg:postcode":"08061",
    "sg:province":"NJ",
    "sg:website":"www.aaop.org",
    "wof:name":"American Academy Of Orafacial",
    "wof:placetype":"venue"
},
  "geometry": {"coordinates":[-75.20935299999999,39.807505],"type":"Point"}
}