{
  "type": "Feature",
  "properties": {
    "iso:country":"US",
    "sg:address":"261 Central Ave",
    "sg:city":"Jersey City",
    "sg:classifiers":[
        {
            "category":"Personal",
            "subcategory":"Beauty Salon",
            "type":"Services"
        }
    ],
    "sg:phone":"+1 201 533 8558",
    "sg:postcode":"07307",
    "sg:province":"NJ",
    "sg:tags":[
        "shop"
    ],
    "wof:name":"Khoobsurat Beauty Salon",
    "wof:placetype":"venue"
},
  "geometry": {"coordinates":[-74.05024899999999,40.744678],"type":"Point"}
}