{
  "type": "Feature",
  "properties": {
    "addr:full":"9 Marlon Pond Rd Trenton NJ 08690",
    "addr:housenumber":"9",
    "addr:postcode":"08690",
    "addr:street":"Marlon Pond Rd",
    "iso:country":"US",
    "sg:address":"9 Marlon Pond Rd",
    "sg:city":"Trenton",
    "sg:classifiers":[
        {
            "category":"Home & Garden",
            "subcategory":"Carpets & Floor Coverings",
            "type":"Retail Goods"
        }
    ],
    "sg:phone":"+1   ",
    "sg:postcode":"08690",
    "sg:province":"NJ",
    "sg:tags":[
        "laying",
        "contractor"
    ],
    "wof:name":"Carpet Impressions Inc",
    "wof:placetype":"venue"
},
  "geometry": {"coordinates":[-74.649743,40.212666],"type":"Point"}
}