{
  "type": "Feature",
  "properties": {
    "iso:country":"US",
    "sg:address":"672 Sycamore St",
    "sg:city":"Paramus",
    "sg:classifiers":[
        {
            "category":"Arts & Performance",
            "subcategory":"Theater",
            "type":"Entertainment"
        }
    ],
    "sg:phone":"+1 201 652 0905",
    "sg:postcode":"07652",
    "sg:province":"NJ",
    "sg:tags":[
        "live",
        "music"
    ],
    "wof:name":"D V8 Productions",
    "wof:placetype":"venue"
},
  "geometry": {"coordinates":[-74.080327,40.969114],"type":"Point"}
}