{
  "type": "Feature",
  "properties": {
    "iso:country":"US",
    "sg:address":"30 W Mount Pleasant Ave",
    "sg:city":"Livingston",
    "sg:classifiers":[
        {
            "category":"Organizations",
            "subcategory":"Professional Association",
            "type":"Services"
        }
    ],
    "sg:phone":"+1   ",
    "sg:postcode":"07039",
    "sg:province":"NJ",
    "sg:tags":[
        "league",
        "business"
    ],
    "wof:name":"Eanj",
    "wof:placetype":"venue"
},
  "geometry": {"coordinates":[-74.318072,40.795389],"type":"Point"}
}