{
  "type": "Feature",
  "properties": {
    "iso:country":"US",
    "sg:address":"126 Osborn Ave",
    "sg:city":"Long Beach Twp",
    "sg:classifiers":[
        {
            "category":"Recreation",
            "subcategory":"Marina",
            "type":"Entertainment"
        }
    ],
    "sg:phone":"+1 609 492 2856",
    "sg:postcode":"08008",
    "sg:province":"NJ",
    "wof:name":"South Gate Marina",
    "wof:placetype":"venue"
},
  "geometry": {"coordinates":[-74.255875,39.548267],"type":"Point"}
}