{
  "type": "Feature",
  "properties": {
    "addr:full":"446 Broad Ave Leonia NJ 07605",
    "addr:housenumber":"446",
    "addr:postcode":"07605",
    "addr:street":"Broad Ave",
    "iso:country":"US",
    "sg:address":"446 Broad Ave",
    "sg:city":"Leonia",
    "sg:classifiers":[
        {
            "category":"Shopping",
            "subcategory":"Florist",
            "type":"Retail Goods"
        }
    ],
    "sg:phone":"+1 201 944 6321",
    "sg:postcode":"07605",
    "sg:province":"NJ",
    "sg:tags":[
        "tree",
        "nurseries-plants"
    ],
    "wof:name":"Harrington Eden Flowers",
    "wof:placetype":"venue"
},
  "geometry": {"coordinates":[-73.985085,40.865689],"type":"Point"}
}