{
  "type": "Feature",
  "properties": {
    "addr:full":"26 Maine St Toms River NJ 08753",
    "addr:housenumber":"26",
    "addr:postcode":"08753",
    "addr:street":"Maine St",
    "iso:country":"US",
    "sg:address":"26 Maine St",
    "sg:city":"Toms River",
    "sg:classifiers":[
        {
            "category":"Health Services",
            "subcategory":"Hospital",
            "type":"Services"
        }
    ],
    "sg:phone":"+1 732 797 0356",
    "sg:postcode":"08753",
    "sg:province":"NJ",
    "wof:name":"Children's Specialized Hosp",
    "wof:placetype":"venue"
},
  "geometry": {"coordinates":[-74.143935,40.010118],"type":"Point"}
}