{
  "type": "Feature",
  "properties": {
    "addr:full":"261 State Rte 17 Mahwah NJ 07430",
    "addr:housenumber":"261",
    "addr:postcode":"07430",
    "addr:street":"State Rte 17",
    "iso:country":"US",
    "sg:address":"261 State Rte 17",
    "sg:city":"Mahwah",
    "sg:classifiers":[
        {
            "category":"Autos & Motor Vehicles",
            "subcategory":"Fuel & Gas Station",
            "type":"Retail Goods"
        }
    ],
    "sg:phone":"+1 201 529 5225",
    "sg:postcode":"07430",
    "sg:province":"NJ",
    "sg:tags":[
        "oil"
    ],
    "wof:name":"TU-Way Gulf Mahwah",
    "wof:placetype":"venue"
},
  "geometry": {"coordinates":[-74.15348,41.089629],"type":"Point"}
}