{
  "type": "Feature",
  "properties": {
    "addr:full":"478 Brick Blvd Brick NJ 08723",
    "addr:housenumber":"478",
    "addr:postcode":"08723",
    "addr:street":"Brick Blvd",
    "iso:country":"US",
    "sg:address":"478 Brick Blvd",
    "sg:city":"Brick",
    "sg:classifiers":[
        {
            "category":"Real Estate",
            "subcategory":"Real Estate Agent",
            "type":"Services"
        }
    ],
    "sg:phone":"+1 732 920 9559",
    "sg:postcode":"08723",
    "sg:province":"NJ",
    "sg:website":"www.dianeturton.com",
    "wof:name":"Diane Turton Realtors",
    "wof:placetype":"venue"
},
  "geometry": {"coordinates":[-74.140992,40.052717],"type":"Point"}
}