{
  "type": "Feature",
  "properties": {
    "iso:country":"US",
    "sg:address":"9 Berry Ln",
    "sg:city":"Randolph",
    "sg:classifiers":[
        {
            "category":"Education",
            "subcategory":"Special Training",
            "type":"Public Place"
        }
    ],
    "sg:phone":"+1 973 584 6256",
    "sg:postcode":"07869",
    "sg:province":"NJ",
    "sg:tags":[
        "school",
        "language"
    ],
    "wof:name":"Accent Reduction Svc Inc",
    "wof:placetype":"venue"
},
  "geometry": {"coordinates":[-74.620278,40.825958],"type":"Point"}
}