{
  "type": "Feature",
  "properties": {
    "iso:country":"US",
    "sg:address":"695 Chancellor Ave",
    "sg:city":"Irvington",
    "sg:classifiers":[
        {
            "category":"Professional",
            "type":"Services"
        }
    ],
    "sg:phone":"+1 973 416 5515",
    "sg:postcode":"07111",
    "sg:province":"NJ",
    "sg:tags":[
        "establishment"
    ],
    "wof:name":"S S & J Enterprises Inc",
    "wof:placetype":"venue"
},
  "geometry": {"coordinates":[-74.23687700000001,40.715219],"type":"Point"}
}