{
  "type": "Feature",
  "properties": {
    "iso:country":"US",
    "sg:address":"184 William Cook Blvd",
    "sg:city":"Manahawkin",
    "sg:classifiers":[
        {
            "category":"Building & Trades",
            "subcategory":"Construction",
            "type":"Services"
        }
    ],
    "sg:phone":"+1 609 597 4172",
    "sg:postcode":"08050",
    "sg:province":"NJ",
    "sg:tags":[
        "house"
    ],
    "wof:name":"Frank Solon Bldg Contr",
    "wof:placetype":"venue"
},
  "geometry": {"coordinates":[-74.24306,39.675402],"type":"Point"}
}