{
  "type": "Feature",
  "properties": {
    "addr:full":"30 Farley Pl Short Hills NJ 07078",
    "addr:housenumber":"30",
    "addr:postcode":"07078",
    "addr:street":"Farley Pl",
    "iso:country":"US",
    "sg:address":"30 Farley Pl",
    "sg:city":"Short Hills",
    "sg:classifiers":[
        {
            "category":"Professional",
            "subcategory":"Lawyer & Legal Services",
            "type":"Services"
        }
    ],
    "sg:phone":"+1 973 467 5115",
    "sg:postcode":"07078",
    "sg:province":"NJ",
    "wof:name":"Rusignola Robert A ESQ",
    "wof:placetype":"venue"
},
  "geometry": {"coordinates":[-74.32579800000001,40.717999],"type":"Point"}
}