{
  "type": "Feature",
  "properties": {
    "iso:country":"US",
    "sg:address":"1565 6th St",
    "sg:city":"Ewing",
    "sg:classifiers":[
        {
            "category":"Manufacturing",
            "subcategory":"Metals",
            "type":"Manufacturing & Wholesale Goods"
        }
    ],
    "sg:phone":"+1 609 883 0318",
    "sg:postcode":"08638",
    "sg:province":"NJ",
    "sg:tags":[
        "refiners-precious",
        "smelter"
    ],
    "wof:name":"Century Metals",
    "wof:placetype":"venue"
},
  "geometry": {"coordinates":[-74.76227400000001,40.246338],"type":"Point"}
}