{
  "type": "Feature",
  "properties": {
    "addr:full":"24 Springfield Ave Cranford NJ 07016",
    "addr:housenumber":"24",
    "addr:postcode":"07016",
    "addr:street":"Springfield Ave",
    "iso:country":"US",
    "sg:address":"24 Springfield Ave",
    "sg:city":"Cranford",
    "sg:classifiers":[
        {
            "category":"Professional",
            "type":"Services"
        }
    ],
    "sg:phone":"+1   ",
    "sg:postcode":"07016",
    "sg:province":"NJ",
    "wof:name":"Ultimate Sealcoating Services",
    "wof:placetype":"venue"
},
  "geometry": {"coordinates":[-74.305052,40.659457],"type":"Point"}
}