{
  "type": "Feature",
  "properties": {
    "iso:country":"US",
    "sg:address":"72 Haskell Ave",
    "sg:city":"Haskell",
    "sg:classifiers":[
        {
            "category":"Arts & Performance",
            "subcategory":"Theater",
            "type":"Entertainment"
        }
    ],
    "sg:phone":"+1   ",
    "sg:postcode":"07420",
    "sg:province":"NJ",
    "sg:tags":[
        "motion",
        "pr",
        "group"
    ],
    "wof:name":"Dan Man Productions Inc",
    "wof:placetype":"venue"
},
  "geometry": {"coordinates":[-74.299363,41.018811],"type":"Point"}
}