{
  "type": "Feature",
  "properties": {
    "iso:country":"US",
    "sg:address":"112 Crescent Rd",
    "sg:city":"Ocean City",
    "sg:classifiers":[
        {
            "category":"Building & Trades",
            "subcategory":"Construction",
            "type":"Services"
        }
    ],
    "sg:phone":"+1 609 391 1641",
    "sg:postcode":"08226",
    "sg:province":"NJ",
    "sg:tags":[
        "home",
        "builder",
        "house"
    ],
    "wof:name":"J Frost Custom Builders Inc",
    "wof:placetype":"venue"
},
  "geometry": {"coordinates":[-74.561764,39.291524],"type":"Point"}
}