{
  "type": "Feature",
  "properties": {
    "iso:country":"US",
    "sg:address":"22 Jackson Ave",
    "sg:city":"Pequannock",
    "sg:classifiers":[
        {
            "category":"Real Estate",
            "subcategory":"Real Estate Agent",
            "type":"Services"
        }
    ],
    "sg:phone":"+1 973 616 6600",
    "sg:postcode":"07462",
    "sg:province":"NJ",
    "sg:tags":[
        "cooperative"
    ],
    "wof:name":"Housing Cooperative",
    "wof:placetype":"venue"
},
  "geometry": {"coordinates":[-74.533117,41.195014],"type":"Point"}
}