{
  "type": "Feature",
  "properties": {
    "addr:full":"239 Main St Woodbridge NJ 07095",
    "addr:housenumber":"239",
    "addr:postcode":"07095",
    "addr:street":"Main St",
    "iso:country":"US",
    "sg:address":"239 Main St",
    "sg:city":"Woodbridge",
    "sg:classifiers":[
        {
            "category":"Real Estate",
            "subcategory":"Real Estate Agent",
            "type":"Services"
        }
    ],
    "sg:phone":"+1   ",
    "sg:postcode":"07095",
    "sg:province":"NJ",
    "sg:tags":[
        "agency"
    ],
    "wof:name":"Century 21 Main Street Realty",
    "wof:placetype":"venue"
},
  "geometry": {"coordinates":[-74.285837,40.552426],"type":"Point"}
}