{
  "type": "Feature",
  "properties": {
    "iso:country":"US",
    "sg:address":"47 Main St",
    "sg:city":"Mantua",
    "sg:classifiers":[
        {
            "category":"Retail",
            "subcategory":"Funeral Services",
            "type":"Services"
        }
    ],
    "sg:phone":"+1 856 468 0670",
    "sg:postcode":"08051",
    "sg:province":"NJ",
    "sg:tags":[
        "home"
    ],
    "wof:name":"Smith Funeral Home",
    "wof:placetype":"venue"
},
  "geometry": {"coordinates":[-75.17208100000001,39.792521],"type":"Point"}
}