{
  "type": "Feature",
  "properties": {
    "addr:full":"77 Jacobus Ave Kearny NJ 07032",
    "addr:housenumber":"77",
    "addr:postcode":"07032",
    "addr:street":"Jacobus Ave",
    "iso:country":"US",
    "sg:address":"77 Jacobus Ave",
    "sg:city":"Kearny",
    "sg:classifiers":[
        {
            "category":"Government",
            "subcategory":"Office",
            "type":"Public Place"
        }
    ],
    "sg:phone":"+1   ",
    "sg:postcode":"07032",
    "sg:province":"NJ",
    "sg:tags":[
        "conservation"
    ],
    "wof:name":"L F R Levine Frickey",
    "wof:placetype":"venue"
},
  "geometry": {"coordinates":[-74.112021,40.73672],"type":"Point"}
}