{
  "type": "Feature",
  "properties": {
    "iso:country":"US",
    "sg:address":"509 S Lenola Rd",
    "sg:city":"Moorestown",
    "sg:classifiers":[
        {
            "category":"Health Services",
            "subcategory":"Doctor",
            "type":"Services"
        }
    ],
    "sg:phone":"+1 609 234 0222",
    "sg:postcode":"08057",
    "sg:province":"NJ",
    "sg:tags":[
        "medical"
    ],
    "wof:name":"Jurij R Bilyk MD",
    "wof:placetype":"venue"
},
  "geometry": {"coordinates":[-74.97056499999999,39.947867],"type":"Point"}
}