{
  "type": "Feature",
  "properties": {
    "addr:full":"570 Jernee Mill Rd Sayreville NJ 08872",
    "addr:housenumber":"570",
    "addr:postcode":"08872",
    "addr:street":"Jernee Mill Rd",
    "iso:country":"US",
    "sg:address":"570 Jernee Mill Rd",
    "sg:city":"Sayreville",
    "sg:classifiers":[
        {
            "category":"Bars & Pubs",
            "type":"Food & Drink"
        }
    ],
    "sg:phone":"+1 732 238 5500",
    "sg:postcode":"08872",
    "sg:province":"NJ",
    "sg:tags":[
        "club",
        "night"
    ],
    "wof:name":"Starland Ballroom",
    "wof:placetype":"venue"
},
  "geometry": {"coordinates":[-74.35096299999999,40.437791],"type":"Point"}
}