{
  "type": "Feature",
  "properties": {
    "addr:full":"132 Oakdale Rd Chester NJ 07930",
    "addr:housenumber":"132",
    "addr:postcode":"07930",
    "addr:street":"Oakdale Rd",
    "iso:country":"US",
    "sg:address":"132 Oakdale Rd",
    "sg:city":"Chester",
    "sg:classifiers":[
        {
            "category":"Building & Trades",
            "subcategory":"Landscaping Services",
            "type":"Services"
        }
    ],
    "sg:phone":"+1 908 879 5051",
    "sg:postcode":"07930",
    "sg:province":"NJ",
    "sg:tags":[
        "business"
    ],
    "wof:name":"Oakdale Landscaping",
    "wof:placetype":"venue"
},
  "geometry": {"coordinates":[-74.696111,40.796172],"type":"Point"}
}