{
  "type": "Feature",
  "properties": {
    "iso:country":"US",
    "sg:address":"56 Old Hook Rd",
    "sg:city":"Bayonne",
    "sg:classifiers":[
        {
            "category":"Manufacturing",
            "subcategory":"Tools & Machinery",
            "type":"Manufacturing & Wholesale Goods"
        }
    ],
    "sg:phone":"+1 201 436 2230",
    "sg:postcode":"07002",
    "sg:province":"NJ",
    "sg:tags":[
        "electrical",
        "apparatus"
    ],
    "sg:website":"www.airflyteelectronics.com",
    "wof:name":"Air Flyte Electronics Co",
    "wof:placetype":"venue"
},
  "geometry": {"coordinates":[-74.114867,40.659815],"type":"Point"}
}