{
  "type": "Feature",
  "properties": {
    "iso:country":"US",
    "sg:address":"64 Keen St",
    "sg:city":"Paterson",
    "sg:classifiers":[
        {
            "category":"Professional",
            "type":"Services"
        },
        {
            "category":"Social Services",
            "type":"Services"
        }
    ],
    "sg:phone":"+1 973 279 5369",
    "sg:postcode":"07524",
    "sg:province":"NJ",
    "sg:tags":[
        "organization",
        "welfare"
    ],
    "wof:name":"Catholic Family & Community",
    "wof:placetype":"venue"
},
  "geometry": {"coordinates":[-74.161361,40.926949],"type":"Point"}
}