{
  "type": "Feature",
  "properties": {
    "iso:country":"US",
    "sg:address":"17 Saxon Way",
    "sg:city":"Skillman",
    "sg:classifiers":[
        {
            "category":"Professional",
            "subcategory":"Management & Consulting",
            "type":"Services"
        }
    ],
    "sg:phone":"+1   ",
    "sg:postcode":"08558",
    "sg:province":"NJ",
    "wof:name":"Paragon Consulting Associates",
    "wof:placetype":"venue"
},
  "geometry": {"coordinates":[-74.694822,40.424541],"type":"Point"}
}