{
  "type": "Feature",
  "properties": {
    "iso:country":"US",
    "sg:address":"18 69th St",
    "sg:city":"West New York",
    "sg:classifiers":[
        {
            "category":"Professional",
            "type":"Services"
        }
    ],
    "sg:phone":"+1   ",
    "sg:postcode":"07093",
    "sg:province":"NJ",
    "wof:name":"Marc Ringlet",
    "wof:placetype":"venue"
},
  "geometry": {"coordinates":[-74.00153899999999,40.791001],"type":"Point"}
}