{
  "type": "Feature",
  "properties": {
    "iso:country":"US",
    "sg:address":"142 McCarthy Ave",
    "sg:city":"Mantua",
    "sg:classifiers":[
        {
            "category":"Professional",
            "subcategory":"Business Services",
            "type":"Services"
        }
    ],
    "sg:phone":"+1   ",
    "sg:postcode":"08051",
    "sg:province":"NJ",
    "wof:name":"Pennsylvania Assoc of Dan",
    "wof:placetype":"venue"
},
  "geometry": {"coordinates":[-75.16698,39.789781],"type":"Point"}
}