{
  "type": "Feature",
  "properties": {
    "iso:country":"US",
    "sg:address":"970 N Main Rd",
    "sg:city":"Vineland",
    "sg:classifiers":[
        {
            "category":"Shopping",
            "subcategory":"Pharmacy",
            "type":"Retail Goods"
        }
    ],
    "sg:phone":"+1   ",
    "sg:postcode":"08360",
    "sg:province":"NJ",
    "sg:tags":[
        "drug",
        "store"
    ],
    "wof:name":"Eckerd",
    "wof:placetype":"venue"
},
  "geometry": {"coordinates":[-74.995386,39.498079],"type":"Point"}
}