{
  "type": "Feature",
  "properties": {
    "addr:full":"83 Union St Medford NJ 08055",
    "addr:housenumber":"83",
    "addr:postcode":"08055",
    "addr:street":"Union St",
    "iso:country":"US",
    "sg:address":"83 Union St",
    "sg:city":"Medford",
    "sg:classifiers":[
        {
            "category":"Manufacturing",
            "subcategory":"Apparel",
            "type":"Manufacturing & Wholesale Goods"
        }
    ],
    "sg:phone":"+1 609 953 9700",
    "sg:postcode":"08055",
    "sg:province":"NJ",
    "sg:tags":[
        "product",
        "merchandise",
        "mfg"
    ],
    "wof:name":"ACS Canvas & Awnings",
    "wof:placetype":"venue"
},
  "geometry": {"coordinates":[-74.83028299999999,39.898788],"type":"Point"}
}