{
  "type": "Feature",
  "properties": {
    "iso:country":"US",
    "sg:address":"715 Delsea Dr N",
    "sg:city":"Glassboro",
    "sg:classifiers":[
        {
            "category":"Personal",
            "subcategory":"Beauty Salon",
            "type":"Services"
        }
    ],
    "sg:phone":"+1 856 307 1233",
    "sg:postcode":"08028",
    "sg:province":"NJ",
    "sg:tags":[
        "shop"
    ],
    "wof:name":"Hello Gorgeous Unisex Salon St",
    "wof:placetype":"venue"
},
  "geometry": {"coordinates":[-75.115196,39.7213],"type":"Point"}
}