{
  "type": "Feature",
  "properties": {
    "addr:full":"11 Knox Pl Nutley NJ 07110",
    "addr:housenumber":"11",
    "addr:postcode":"07110",
    "addr:street":"Knox Pl",
    "iso:country":"US",
    "sg:address":"11 Knox Pl",
    "sg:city":"Nutley",
    "sg:classifiers":[
        {
            "category":"Building & Trades",
            "subcategory":"Cleaning & Sanitation",
            "type":"Services"
        }
    ],
    "sg:phone":"+1   ",
    "sg:postcode":"07110",
    "sg:province":"NJ",
    "sg:tags":[
        "maintenance"
    ],
    "wof:name":"Somur & Sons LLC",
    "wof:placetype":"venue"
},
  "geometry": {"coordinates":[-74.169012,40.819655],"type":"Point"}
}