{
  "type": "Feature",
  "properties": {
    "iso:country":"US",
    "sg:address":"1309 3rd Ave",
    "sg:city":"Spring Lake",
    "sg:classifiers":[
        {
            "category":"Personal",
            "subcategory":"Barber",
            "type":"Services"
        }
    ],
    "sg:phone":"+1 732 449 5560",
    "sg:postcode":"07762",
    "sg:province":"NJ",
    "sg:tags":[
        "shop"
    ],
    "wof:name":"Spring Lake Barber Shop Inc",
    "wof:placetype":"venue"
},
  "geometry": {"coordinates":[-74.027764,40.154384],"type":"Point"}
}