{
  "type": "Feature",
  "properties": {
    "addr:full":"906 Main St Bradley Beach NJ 07720",
    "addr:housenumber":"906",
    "addr:postcode":"07720",
    "addr:street":"Main St",
    "iso:country":"US",
    "sg:address":"906 Main St",
    "sg:city":"Bradley Beach",
    "sg:classifiers":[
        {
            "category":"Shopping",
            "subcategory":"Clothing, Apparel, & Fashions",
            "type":"Retail Goods"
        }
    ],
    "sg:phone":"+1   ",
    "sg:postcode":"07720",
    "sg:province":"NJ",
    "sg:tags":[
        "tailor"
    ],
    "wof:name":"Oscars Tailor and Dry Cleaners",
    "wof:placetype":"venue"
},
  "geometry": {"coordinates":[-74.01666400000001,40.206445],"type":"Point"}
}