{
  "type": "Feature",
  "properties": {
    "addr:full":"396 Springfield Ave Newark NJ 07103",
    "addr:housenumber":"396",
    "addr:postcode":"07103",
    "addr:street":"Springfield Ave",
    "iso:country":"US",
    "sg:address":"396 Springfield Ave",
    "sg:city":"Newark",
    "sg:classifiers":[
        {
            "category":"Home & Garden",
            "subcategory":"Household Appliances",
            "type":"Retail Goods"
        }
    ],
    "sg:phone":"+1 973 242 0880",
    "sg:postcode":"07103",
    "sg:province":"NJ",
    "wof:name":"H & M Discount Furniture LLC",
    "wof:placetype":"venue"
},
  "geometry": {"coordinates":[-74.198714,40.73261],"type":"Point"}
}