{
  "type": "Feature",
  "properties": {
    "iso:country":"US",
    "sg:address":"60 Metro Way",
    "sg:city":"Secaucus",
    "sg:classifiers":[
        {
            "category":"Shopping",
            "subcategory":"Clothing, Apparel, & Fashions",
            "type":"Retail Goods"
        }
    ],
    "sg:phone":"+1 201 319 1955",
    "sg:postcode":"07094",
    "sg:province":"NJ",
    "wof:name":"Lawrence EM LTD",
    "wof:placetype":"venue"
},
  "geometry": {"coordinates":[-74.071096,40.772691],"type":"Point"}
}