{
  "type": "Feature",
  "properties": {
    "addr:full":"557 Broad St Bloomfield NJ 07003",
    "addr:housenumber":"557",
    "addr:postcode":"07003",
    "addr:street":"Broad St",
    "iso:country":"US",
    "sg:address":"557 Broad St",
    "sg:city":"Bloomfield",
    "sg:classifiers":[
        {
            "category":"Health Services",
            "subcategory":"Doctor",
            "type":"Services"
        }
    ],
    "sg:phone":"+1 973 680 4901",
    "sg:postcode":"07003",
    "sg:province":"NJ",
    "sg:tags":[
        "medicine",
        "sport",
        "orthopedist"
    ],
    "wof:name":"Miller Alan R MD",
    "wof:placetype":"venue"
},
  "geometry": {"coordinates":[-74.194298,40.812698],"type":"Point"}
}