{
  "type": "Feature",
  "properties": {
    "iso:country":"US",
    "sg:address":"819 Evesham Ave W",
    "sg:city":"Magnolia",
    "sg:classifiers":[
        {
            "category":"Food & Beverages",
            "subcategory":"Groceries & Convenience Stores",
            "type":"Retail Goods"
        }
    ],
    "sg:phone":"+1 856 783 2787",
    "sg:postcode":"08049",
    "sg:province":"NJ",
    "wof:name":"Brennan's Gas & Go",
    "wof:placetype":"venue"
},
  "geometry": {"coordinates":[-75.049103,39.850601],"type":"Point"}
}