{
  "type": "Feature",
  "properties": {
    "addr:full":"801 Burlington Ave Delanco NJ 08075",
    "addr:housenumber":"801",
    "addr:postcode":"08075",
    "addr:street":"Burlington Ave",
    "iso:country":"US",
    "sg:address":"801 Burlington Ave",
    "sg:city":"Delanco",
    "sg:classifiers":[
        {
            "category":"Social Services",
            "type":"Services"
        }
    ],
    "sg:phone":"+1 856 764 7083",
    "sg:postcode":"08075",
    "sg:province":"NJ",
    "wof:name":"A R C Of Burlington County",
    "wof:placetype":"venue"
},
  "geometry": {"coordinates":[-74.95375799999999,40.050659],"type":"Point"}
}