{
  "type": "Feature",
  "properties": {
    "addr:full":"1680 John F Kennedy Blvd Jersey City NJ 07305",
    "addr:housenumber":"1680",
    "addr:postcode":"07305",
    "addr:street":"John F Kennedy Blvd",
    "iso:country":"US",
    "sg:address":"1680 John F Kennedy Blvd",
    "sg:city":"Jersey City",
    "sg:classifiers":[
        {
            "category":"Autos & Motor Vehicles",
            "subcategory":"Automobile Sales",
            "type":"Retail Goods"
        }
    ],
    "sg:phone":"+1 201 434 3368",
    "sg:postcode":"07305",
    "sg:province":"NJ",
    "sg:tags":[
        "car",
        "dealer"
    ],
    "wof:name":"Trans USA Corp",
    "wof:placetype":"venue"
},
  "geometry": {"coordinates":[-74.095974,40.698589],"type":"Point"}
}