{
  "type": "Feature",
  "properties": {
    "iso:country":"US",
    "sg:address":"309 2nd St",
    "sg:city":"Hackensack",
    "sg:classifiers":[
        {
            "category":"Professional",
            "subcategory":"Business Services",
            "type":"Services"
        }
    ],
    "sg:phone":"+1   ",
    "sg:postcode":"07601",
    "sg:province":"NJ",
    "wof:name":"Godsuns Music Group",
    "wof:placetype":"venue"
},
  "geometry": {"coordinates":[-74.050241,40.891175],"type":"Point"}
}