{
  "type": "Feature",
  "properties": {
    "iso:country":"US",
    "sg:address":"410 Eugenia Dr",
    "sg:city":"Medford",
    "sg:classifiers":[
        {
            "category":"Health Services",
            "subcategory":"Doctor",
            "type":"Services"
        },
        {
            "category":"Health Services",
            "subcategory":"Clinic",
            "type":"Services"
        }
    ],
    "sg:phone":"+1 609 714 1340",
    "sg:postcode":"08055",
    "sg:province":"NJ",
    "sg:tags":[
        "psychological",
        "psychologist"
    ],
    "wof:name":"Henry, Vincent Depaul Psyd",
    "wof:placetype":"venue"
},
  "geometry": {"coordinates":[-74.841148,39.903],"type":"Point"}
}