{
  "type": "Feature",
  "properties": {
    "iso:country":"US",
    "sg:address":"288 State Rte 10",
    "sg:city":"Succasunna",
    "sg:classifiers":[
        {
            "category":"Shopping",
            "subcategory":"Clothing, Apparel, & Fashions",
            "type":"Retail Goods"
        }
    ],
    "sg:phone":"+1   ",
    "sg:postcode":"07876",
    "sg:province":"NJ",
    "wof:name":"Casual Male Big Tall The 9458",
    "wof:placetype":"venue"
},
  "geometry": {"coordinates":[-74.642804,40.869878],"type":"Point"}
}