{
  "type": "Feature",
  "properties": {
    "addr:full":"1400 Metropolitan Ave Paulsboro NJ 08066",
    "addr:housenumber":"1400",
    "addr:postcode":"08066",
    "addr:street":"Metropolitan Ave",
    "iso:country":"US",
    "sg:address":"1400 Metropolitan Ave",
    "sg:city":"Paulsboro",
    "sg:classifiers":[
        {
            "category":"Wholesale",
            "subcategory":"Fruits & Vegetables",
            "type":"Manufacturing & Wholesale Goods"
        }
    ],
    "sg:phone":"+1 856 845 0377",
    "sg:postcode":"08066",
    "sg:province":"NJ",
    "wof:name":"J Ambrogi Food Distributors",
    "wof:placetype":"venue"
},
  "geometry": {"coordinates":[-75.197757,39.829992],"type":"Point"}
}