{
  "type": "Feature",
  "properties": {
    "addr:full":"904 3rd St Keyport NJ 07735",
    "addr:housenumber":"904",
    "addr:postcode":"07735",
    "addr:street":"3Rd St",
    "iso:country":"US",
    "sg:address":"904 3rd St",
    "sg:city":"Keyport",
    "sg:classifiers":[
        {
            "category":"Wholesale",
            "subcategory":"Non-durable Goods",
            "type":"Manufacturing & Wholesale Goods"
        }
    ],
    "sg:phone":"+1 732 739 1074",
    "sg:postcode":"07735",
    "sg:province":"NJ",
    "wof:name":"A To Z Distributors",
    "wof:placetype":"venue"
},
  "geometry": {"coordinates":[-74.17095500000001,40.449483],"type":"Point"}
}