{
  "type": "Feature",
  "properties": {
    "iso:country":"US",
    "sg:address":"1816 Longview Ct",
    "sg:city":"Teaneck",
    "sg:classifiers":[
        {
            "category":"Retail",
            "subcategory":"Self-service Laundry",
            "type":"Services"
        }
    ],
    "sg:phone":"+1   ",
    "sg:postcode":"07666",
    "sg:province":"NJ",
    "sg:tags":[
        "coin",
        "eating"
    ],
    "wof:name":"Queen Anne Launderette & Clrs",
    "wof:placetype":"venue"
},
  "geometry": {"coordinates":[-73.998862,40.911778],"type":"Point"}
}