{
  "type": "Feature",
  "properties": {
    "iso:country":"US",
    "sg:address":"47 Frazier St",
    "sg:city":"Trenton",
    "sg:classifiers":[
        {
            "category":"Manufacturing",
            "subcategory":"Tools & Machinery",
            "type":"Manufacturing & Wholesale Goods"
        }
    ],
    "sg:phone":"+1 609 392 8722",
    "sg:postcode":"08618",
    "sg:province":"NJ",
    "sg:tags":[
        "machine",
        "shop"
    ],
    "wof:name":"Arthur E Farmer Machinists",
    "wof:placetype":"venue"
},
  "geometry": {"coordinates":[-74.770505,40.230593],"type":"Point"}
}