{
  "type": "Feature",
  "properties": {
    "iso:country":"US",
    "sg:address":"41 Henry Rd",
    "sg:city":"Hewitt",
    "sg:classifiers":[
        {
            "category":"Social Services",
            "subcategory":"Child Care",
            "type":"Services"
        }
    ],
    "sg:phone":"+1 973 853 2020",
    "sg:postcode":"07421",
    "sg:province":"NJ",
    "sg:tags":[
        "kindergarten",
        "academic",
        "school"
    ],
    "wof:name":"Center For Family Resources",
    "wof:placetype":"venue"
},
  "geometry": {"coordinates":[-74.388212,41.18335],"type":"Point"}
}