{
  "type": "Feature",
  "properties": {
    "addr:full":"126 Joralemon St Belleville NJ 07109",
    "addr:housenumber":"126",
    "addr:postcode":"07109",
    "addr:street":"Joralemon St",
    "iso:country":"US",
    "sg:address":"126 Joralemon St",
    "sg:city":"Belleville",
    "sg:classifiers":[
        {
            "category":"Organizations",
            "subcategory":"Religious Organization",
            "type":"Services"
        }
    ],
    "sg:phone":"+1   ",
    "sg:postcode":"07109",
    "sg:province":"NJ",
    "wof:name":"Arya Samaj Temple",
    "wof:placetype":"venue"
},
  "geometry": {"coordinates":[-74.15206499999999,40.794118],"type":"Point"}
}