{
  "type": "Feature",
  "properties": {
    "addr:full":"1430 Hooper Ave Toms River NJ 08753",
    "addr:housenumber":"1430",
    "addr:postcode":"08753",
    "addr:street":"Hooper Ave",
    "iso:country":"US",
    "sg:address":"1430 Hooper Ave",
    "sg:city":"Toms River",
    "sg:classifiers":[
        {
            "category":"Health Services",
            "subcategory":"Hospital",
            "type":"Services"
        }
    ],
    "sg:phone":"+1 732 557 0700",
    "sg:postcode":"08753",
    "sg:province":"NJ",
    "wof:name":"Chd Meridian",
    "wof:placetype":"venue"
},
  "geometry": {"coordinates":[-74.173109,39.994174],"type":"Point"}
}