{
  "type": "Feature",
  "properties": {
    "iso:country":"US",
    "sg:address":"119 Eyland Ave",
    "sg:city":"Succasunna",
    "sg:classifiers":[
        {
            "category":"Health Services",
            "subcategory":"Doctor",
            "type":"Services"
        }
    ],
    "sg:phone":"+1 973 584 4361",
    "sg:postcode":"07876",
    "sg:province":"NJ",
    "sg:tags":[
        "dentist"
    ],
    "wof:name":"Ronald M Jupiter DDS P A",
    "wof:placetype":"venue"
},
  "geometry": {"coordinates":[-74.64235499999999,40.853837],"type":"Point"}
}