{
  "type": "Feature",
  "properties": {
    "addr:full":"540 Valley Rd Wayne NJ 07470",
    "addr:housenumber":"540",
    "addr:postcode":"07470",
    "addr:street":"Valley Rd",
    "iso:country":"US",
    "sg:address":"540 Valley Rd",
    "sg:city":"Wayne",
    "sg:classifiers":[
        {
            "category":"Autos & Motor Vehicles",
            "subcategory":"Fuel & Gas Station",
            "type":"Retail Goods"
        }
    ],
    "sg:phone":"+1 973 633 6655",
    "sg:postcode":"07470",
    "sg:province":"NJ",
    "sg:tags":[
        "oil"
    ],
    "wof:name":"Valley Road Exxon",
    "wof:placetype":"venue"
},
  "geometry": {"coordinates":[-74.228402,40.929696],"type":"Point"}
}