{
  "type": "Feature",
  "properties": {
    "addr:full":"175 Fairfield Ave Caldwell NJ 07006",
    "addr:housenumber":"175",
    "addr:postcode":"07006",
    "addr:street":"Fairfield Ave",
    "iso:country":"US",
    "sg:address":"175 Fairfield Ave",
    "sg:city":"Caldwell",
    "sg:classifiers":[
        {
            "category":"Wholesale",
            "subcategory":"Electrical",
            "type":"Manufacturing & Wholesale Goods"
        }
    ],
    "sg:phone":"+1 973 226 3300",
    "sg:postcode":"07006",
    "sg:province":"NJ",
    "sg:tags":[
        "component",
        "representative",
        "mfg"
    ],
    "wof:name":"Technical Marketing Group",
    "wof:placetype":"venue"
},
  "geometry": {"coordinates":[-74.284609,40.860451],"type":"Point"}
}