{
  "type": "Feature",
  "properties": {
    "iso:country":"US",
    "sg:address":"134 Main St",
    "sg:city":"Fort Lee",
    "sg:classifiers":[
        {
            "category":"Real Estate",
            "subcategory":"Real Estate Services",
            "type":"Services"
        }
    ],
    "sg:phone":"+1 201 346 9700",
    "sg:postcode":"07024",
    "sg:province":"NJ",
    "sg:tags":[
        "management",
        "property"
    ],
    "wof:name":"Bridge Realty",
    "wof:placetype":"venue"
},
  "geometry": {"coordinates":[-73.967598,40.850899],"type":"Point"}
}