{
  "type": "Feature",
  "properties": {
    "iso:country":"US",
    "sg:address":"439 Livingston Ave",
    "sg:city":"New Brunswick",
    "sg:classifiers":[
        {
            "category":"Banks & Credit Unions",
            "subcategory":"Bank",
            "type":"Services"
        }
    ],
    "sg:phone":"+1   ",
    "sg:postcode":"08901",
    "sg:province":"NJ",
    "sg:tags":[
        "state"
    ],
    "sg:website":"www.brunswickbank.com",
    "wof:name":"Brunswick Bancorp",
    "wof:placetype":"venue"
},
  "geometry": {"coordinates":[-74.459896,40.478219],"type":"Point"}
}