{
  "type": "Feature",
  "properties": {
    "addr:full":"311 Coppola Dr South Plainfield NJ 07080",
    "addr:housenumber":"311",
    "addr:postcode":"07080",
    "addr:street":"Coppola Dr",
    "iso:country":"US",
    "sg:address":"311 Coppola Dr",
    "sg:city":"South Plainfield",
    "sg:classifiers":[
        {
            "category":"Real Estate",
            "subcategory":"Real Estate Agent",
            "type":"Services"
        }
    ],
    "sg:phone":"+1 908 791 3933",
    "sg:postcode":"07080",
    "sg:province":"NJ",
    "wof:name":"Edgewood Properties",
    "wof:placetype":"venue"
},
  "geometry": {"coordinates":[-74.417164,40.546223],"type":"Point"}
}