{
  "type": "Feature",
  "properties": {
    "iso:country":"US",
    "sg:address":"501 State Rte 35",
    "sg:city":"Neptune",
    "sg:classifiers":[
        {
            "category":"Social Services",
            "type":"Services"
        }
    ],
    "sg:phone":"+1 732 775 1140",
    "sg:postcode":"07753",
    "sg:province":"NJ",
    "sg:tags":[
        "organization",
        "welfare"
    ],
    "wof:name":"Madonna House",
    "wof:placetype":"venue"
},
  "geometry": {"coordinates":[-74.02638899999999,40.205483],"type":"Point"}
}