{
  "type": "Feature",
  "properties": {
    "iso:country":"US",
    "sg:address":"5812 Palisade Ave",
    "sg:city":"West New York",
    "sg:classifiers":[
        {
            "category":"Personal",
            "subcategory":"Barber",
            "type":"Services"
        }
    ],
    "sg:phone":"+1 201 295 8500",
    "sg:postcode":"07093",
    "sg:province":"NJ",
    "wof:name":"W Rodes Barber Shop",
    "wof:placetype":"venue"
},
  "geometry": {"coordinates":[-74.01462600000001,40.787065],"type":"Point"}
}