{
  "type": "Feature",
  "properties": {
    "iso:country":"US",
    "sg:address":"2673 Lawrenceville Rd",
    "sg:city":"Lawrenceville",
    "sg:classifiers":[
        {
            "category":"Professional",
            "type":"Services"
        }
    ],
    "sg:phone":"+1 609 394 4770",
    "sg:postcode":"08648",
    "sg:province":"NJ",
    "sg:tags":[
        "establishment"
    ],
    "wof:name":"First Union Formerly First",
    "wof:placetype":"venue"
},
  "geometry": {"coordinates":[-74.729736,40.297556],"type":"Point"}
}