{
  "type": "Feature",
  "properties": {
    "addr:full":"1081 Pennsylvania Ave Franklinville NJ 08322",
    "addr:housenumber":"1081",
    "addr:postcode":"08322",
    "addr:street":"Pennsylvania Ave",
    "iso:country":"US",
    "sg:address":"1081 Pennsylvania Ave",
    "sg:city":"Franklinville",
    "sg:classifiers":[
        {
            "category":"Building & Trades",
            "subcategory":"Construction",
            "type":"Services"
        }
    ],
    "sg:phone":"+1 856 629 7905",
    "sg:postcode":"08322",
    "sg:province":"NJ",
    "sg:tags":[
        "house"
    ],
    "wof:name":"Manton Son Inc",
    "wof:placetype":"venue"
},
  "geometry": {"coordinates":[-75.03636299999999,39.61099],"type":"Point"}
}