{
  "type": "Feature",
  "properties": {
    "addr:full":"2727 State Rte 23 Newfoundland NJ 07435",
    "addr:housenumber":"2727",
    "addr:postcode":"07435",
    "addr:street":"State Rte 23",
    "iso:country":"US",
    "sg:address":"2727 State Rte 23",
    "sg:city":"Newfoundland",
    "sg:classifiers":[
        {
            "category":"Government",
            "subcategory":"Post Office",
            "type":"Public Place"
        }
    ],
    "sg:phone":"+1 973 697 5392",
    "sg:postcode":"07435",
    "sg:province":"NJ",
    "sg:tags":[
        "postal",
        "us"
    ],
    "wof:name":"US Post Office",
    "wof:placetype":"venue"
},
  "geometry": {"coordinates":[-74.440898,41.047832],"type":"Point"}
}