{
  "type": "Feature",
  "properties": {
    "addr:full":"100 Valley Way West Orange NJ 07052",
    "addr:housenumber":"100",
    "addr:postcode":"07052",
    "addr:street":"Valley Way",
    "iso:country":"US",
    "sg:address":"100 Valley Way",
    "sg:city":"West Orange",
    "sg:classifiers":[
        {
            "category":"Education",
            "subcategory":"School",
            "type":"Public Place"
        }
    ],
    "sg:phone":"+1 973 325 4400",
    "sg:postcode":"07052",
    "sg:province":"NJ",
    "sg:tags":[
        "high",
        "middle",
        "elementary"
    ],
    "wof:name":"Mount Carmel Guild Academy",
    "wof:placetype":"venue"
},
  "geometry": {"coordinates":[-74.23454,40.795428],"type":"Point"}
}