{
  "type": "Feature",
  "properties": {
    "addr:full":"375 Corporate Dr Mahwah NJ 07430",
    "addr:housenumber":"375",
    "addr:postcode":"07430",
    "addr:street":"Corporate Dr",
    "iso:country":"US",
    "sg:address":"375 Corporate Dr",
    "sg:city":"Mahwah",
    "sg:classifiers":[
        {
            "category":"Travel",
            "subcategory":"Hotels & Motels",
            "type":"Entertainment"
        }
    ],
    "sg:phone":"+1   ",
    "sg:postcode":"07430",
    "sg:province":"NJ",
    "sg:website":"www.homewoodsuitesmahwah.com",
    "wof:name":"Homewood Suites By Hilton",
    "wof:placetype":"venue"
},
  "geometry": {"coordinates":[-74.15651800000001,41.087087],"type":"Point"}
}