{
  "type": "Feature",
  "properties": {
    "iso:country":"US",
    "sg:address":"118 Bauer Dr",
    "sg:city":"Oakland",
    "sg:classifiers":[
        {
            "category":"Manufacturing",
            "subcategory":"Motor Vehicles & Parts",
            "type":"Manufacturing & Wholesale Goods"
        }
    ],
    "sg:phone":"+1 201 337 1700",
    "sg:postcode":"07436",
    "sg:province":"NJ",
    "sg:tags":[
        "fabricator",
        "bicycle"
    ],
    "sg:website":"www.fujibikes.com",
    "wof:name":"Fuji America",
    "wof:placetype":"venue"
},
  "geometry": {"coordinates":[-74.239679,41.007017],"type":"Point"}
}