{
  "type": "Feature",
  "properties": {
    "addr:full":"327 Elm Ave Bogota NJ 07603",
    "addr:housenumber":"327",
    "addr:postcode":"07603",
    "addr:street":"Elm Ave",
    "iso:country":"US",
    "sg:address":"327 Elm Ave",
    "sg:city":"Bogota",
    "sg:classifiers":[
        {
            "category":"Professional",
            "subcategory":"Management & Consulting",
            "type":"Services"
        }
    ],
    "sg:phone":"+1   ",
    "sg:postcode":"07603",
    "sg:province":"NJ",
    "sg:tags":[
        "business"
    ],
    "wof:name":"Highland Contracting",
    "wof:placetype":"venue"
},
  "geometry": {"coordinates":[-74.030057,40.876258],"type":"Point"}
}