{
  "type": "Feature",
  "properties": {
    "iso:country":"US",
    "sg:address":"492 Franklin Ave",
    "sg:city":"Nutley",
    "sg:classifiers":[
        {
            "category":"Insurance",
            "subcategory":"Insurance Agent",
            "type":"Services"
        }
    ],
    "sg:phone":"+1 973 661 4600",
    "sg:postcode":"07110",
    "sg:province":"NJ",
    "wof:name":"David Mac Gregor Co",
    "wof:placetype":"venue"
},
  "geometry": {"coordinates":[-74.155427,40.823527],"type":"Point"}
}