{
  "type": "Feature",
  "properties": {
    "iso:country":"US",
    "sg:address":"945 S Orange Ave",
    "sg:city":"East Orange",
    "sg:classifiers":[
        {
            "category":"Professional",
            "subcategory":"Lawyer & Legal Services",
            "type":"Services"
        }
    ],
    "sg:phone":"+1 973 677 9300",
    "sg:postcode":"07018",
    "sg:province":"NJ",
    "sg:tags":[
        "naturalization",
        "immigration"
    ],
    "wof:name":"ABC Divorce & Immigration",
    "wof:placetype":"venue"
},
  "geometry": {"coordinates":[-74.226935,40.74632],"type":"Point"}
}