{
  "type": "Feature",
  "properties": {
    "addr:full":"296 Amboy Ave Metuchen NJ 08840",
    "addr:housenumber":"296",
    "addr:postcode":"08840",
    "addr:street":"Amboy Ave",
    "iso:country":"US",
    "sg:address":"296 Amboy Ave",
    "sg:city":"Metuchen",
    "sg:classifiers":[
        {
            "category":"Social Services",
            "type":"Services"
        }
    ],
    "sg:phone":"+1 732 548 4145",
    "sg:postcode":"08840",
    "sg:province":"NJ",
    "sg:tags":[
        "worker"
    ],
    "wof:name":"Diana Lunt",
    "wof:placetype":"venue"
},
  "geometry": {"coordinates":[-74.36084700000001,40.537888],"type":"Point"}
}