{
  "type": "Feature",
  "properties": {
    "iso:country":"US",
    "sg:address":"585 Ringwood Ave",
    "sg:city":"Wanaque",
    "sg:classifiers":[
        {
            "category":"Health Services",
            "subcategory":"Clinic",
            "type":"Services"
        }
    ],
    "sg:phone":"+1 973 835 2100",
    "sg:postcode":"07465",
    "sg:province":"NJ",
    "sg:tags":[
        "home"
    ],
    "wof:name":"Bayada Nurses",
    "wof:placetype":"venue"
},
  "geometry": {"coordinates":[-74.289055,41.051031],"type":"Point"}
}