{
  "type": "Feature",
  "properties": {
    "addr:full":"305 Independence Blvd Sicklerville NJ 08045",
    "addr:housenumber":"305",
    "addr:postcode":"08045",
    "addr:street":"Independence Blvd",
    "iso:country":"US",
    "sg:address":"305 Independence Blvd",
    "sg:city":"Sicklerville",
    "sg:classifiers":[
        {
            "category":"Professional",
            "subcategory":"Lawyer & Legal Services",
            "type":"Services"
        }
    ],
    "sg:phone":"+1 856 740 0930",
    "sg:postcode":"08045",
    "sg:province":"NJ",
    "sg:tags":[
        "attorney"
    ],
    "wof:name":"Jeannette M Amodeo",
    "wof:placetype":"venue"
},
  "geometry": {"coordinates":[-75.031654,39.873157],"type":"Point"}
}