{
  "type": "Feature",
  "properties": {
    "iso:country":"US",
    "sg:address":"3 Ethel Rd",
    "sg:city":"Edison",
    "sg:classifiers":[
        {
            "category":"Shopping",
            "subcategory":"Computers & Home Electronics",
            "type":"Retail Goods"
        }
    ],
    "sg:phone":"+1 732 287 3622",
    "sg:postcode":"08817",
    "sg:province":"NJ",
    "sg:tags":[
        "parts",
        "supply"
    ],
    "sg:website":"www.pcage.org",
    "wof:name":"P C Age",
    "wof:placetype":"venue"
},
  "geometry": {"coordinates":[-74.402902,40.538177],"type":"Point"}
}