{
  "type": "Feature",
  "properties": {
    "iso:country":"US",
    "sg:address":"5 Wexford Way",
    "sg:city":"Somerset",
    "sg:classifiers":[
        {
            "category":"Professional",
            "subcategory":"Business Services",
            "type":"Services"
        }
    ],
    "sg:phone":"+1   ",
    "sg:postcode":"08873",
    "sg:province":"NJ",
    "wof:name":"Alta Business Tech Solution",
    "wof:placetype":"venue"
},
  "geometry": {"coordinates":[-74.523788,40.517644],"type":"Point"}
}