{
  "type": "Feature",
  "properties": {
    "iso:country":"US",
    "sg:address":"13 Tomlinson Mill Rd",
    "sg:city":"Medford",
    "sg:classifiers":[
        {
            "category":"Social Services",
            "type":"Services"
        }
    ],
    "sg:phone":"+1 609 654 2661",
    "sg:postcode":"08055",
    "sg:province":"NJ",
    "wof:name":"Medford Counciling Asscoa",
    "wof:placetype":"venue"
},
  "geometry": {"coordinates":[-74.85889899999999,39.854396],"type":"Point"}
}