{
  "type": "Feature",
  "properties": {
    "iso:country":"US",
    "sg:address":"802 Kaminski Dr",
    "sg:city":"Rahway",
    "sg:classifiers":[
        {
            "category":"Local Transit",
            "type":"Transportation"
        }
    ],
    "sg:phone":"+1 800 346 9024",
    "sg:postcode":"07065",
    "sg:province":"NJ",
    "sg:tags":[
        "passenger"
    ],
    "wof:name":"Exclusively Yours",
    "wof:placetype":"venue"
},
  "geometry": {"coordinates":[-74.28757,40.613073],"type":"Point"}
}