{
  "type": "Feature",
  "properties": {
    "iso:country":"US",
    "sg:address":"323 Garibaldi Ave",
    "sg:city":"Lodi",
    "sg:phone":"+1 973 773 8192",
    "sg:postcode":"07644",
    "sg:province":"NJ",
    "wof:name":"Luciano's Sport Shop",
    "wof:placetype":"venue"
},
  "geometry": {"coordinates":[-74.071144,40.87841],"type":"Point"}
}