{
  "type": "Feature",
  "properties": {
    "addr:full":"201 Hawthorne St Neptune NJ 07753",
    "addr:housenumber":"201",
    "addr:postcode":"07753",
    "addr:street":"Hawthorne St",
    "iso:country":"US",
    "sg:address":"201 Hawthorne St",
    "sg:city":"Neptune",
    "sg:classifiers":[
        {
            "category":"Retail",
            "subcategory":"Repair Shop",
            "type":"Services"
        }
    ],
    "sg:phone":"+1   ",
    "sg:postcode":"07753",
    "sg:province":"NJ",
    "wof:name":"Door Experts",
    "wof:placetype":"venue"
},
  "geometry": {"coordinates":[-74.06293599999999,40.207882],"type":"Point"}
}