{
  "type": "Feature",
  "properties": {
    "addr:full":"2001 US Hwy 46 Parsippany NJ 07054",
    "addr:housenumber":"2001",
    "addr:postcode":"07054",
    "addr:street":"Us Hwy 46",
    "iso:country":"US",
    "sg:address":"2001 US Hwy 46",
    "sg:city":"Parsippany",
    "sg:classifiers":[
        {
            "category":"Wholesale",
            "subcategory":"Meat",
            "type":"Manufacturing & Wholesale Goods"
        }
    ],
    "sg:phone":"+1 973 331 5498",
    "sg:postcode":"07054",
    "sg:province":"NJ",
    "sg:tags":[
        "mfg",
        "prepared"
    ],
    "wof:name":"Jk Hams",
    "wof:placetype":"venue"
},
  "geometry": {"coordinates":[-74.41468399999999,40.868471],"type":"Point"}
}