{
  "type": "Feature",
  "properties": {
    "addr:full":"111 1st Ave Atlantic Highlands NJ 07716",
    "addr:housenumber":"111",
    "addr:postcode":"07716",
    "addr:street":"1St Ave",
    "iso:country":"US",
    "sg:address":"111 1st Ave",
    "sg:city":"Atlantic Highlands",
    "sg:classifiers":[
        {
            "category":"Banks & Credit Unions",
            "subcategory":"Bank",
            "type":"Services"
        }
    ],
    "sg:phone":"+1   ",
    "sg:postcode":"07716",
    "sg:province":"NJ",
    "sg:tags":[
        "national"
    ],
    "wof:name":"Wachovia Bank National Assn",
    "wof:placetype":"venue"
},
  "geometry": {"coordinates":[-74.03810799999999,40.413091],"type":"Point"}
}