{
  "type": "Feature",
  "properties": {
    "iso:country":"US",
    "sg:address":"124 Youngs Rd",
    "sg:city":"Mercerville",
    "sg:classifiers":[
        {
            "category":"Manufacturing",
            "subcategory":"Tools & Machinery",
            "type":"Manufacturing & Wholesale Goods"
        }
    ],
    "sg:phone":"+1 609 586 3932",
    "sg:postcode":"08619",
    "sg:province":"NJ",
    "sg:tags":[
        "shop",
        "repair",
        "industrial",
        "mfg",
        "machine",
        "welding"
    ],
    "sg:website":"www.creativemachining.com",
    "wof:name":"Creative Machining Systems Inc",
    "wof:placetype":"venue"
},
  "geometry": {"coordinates":[-74.675884,40.264032],"type":"Point"}
}