{
  "type": "Feature",
  "properties": {
    "iso:country":"US",
    "sg:address":"178 W Passaic St",
    "sg:city":"Rochelle Park",
    "sg:classifiers":[
        {
            "category":"Wholesale",
            "subcategory":"Meat",
            "type":"Manufacturing & Wholesale Goods"
        }
    ],
    "sg:phone":"+1 201 843 0059",
    "sg:postcode":"07662",
    "sg:province":"NJ",
    "sg:tags":[
        "shop"
    ],
    "wof:name":"Premier Meat Market",
    "wof:placetype":"venue"
},
  "geometry": {"coordinates":[-74.079498,40.913502],"type":"Point"}
}