{
  "type": "Feature",
  "properties": {
    "addr:full":"202 N Union St Lambertville NJ 08530",
    "addr:housenumber":"202",
    "addr:postcode":"08530",
    "addr:street":"N Union St",
    "iso:country":"US",
    "sg:address":"202 N Union St",
    "sg:city":"Lambertville",
    "sg:classifiers":[
        {
            "category":"Shopping",
            "subcategory":"Used Merchandise",
            "type":"Retail Goods"
        }
    ],
    "sg:phone":"+1 609 397 4978",
    "sg:postcode":"08530",
    "sg:province":"NJ",
    "sg:tags":[
        "antique"
    ],
    "sg:website":"www.oldenglishpine.com",
    "wof:name":"Old English Pine",
    "wof:placetype":"venue"
},
  "geometry": {"coordinates":[-74.94723399999999,40.373219],"type":"Point"}
}