{
  "type": "Feature",
  "properties": {
    "iso:country":"US",
    "sg:address":"3401 New Jersey Ave",
    "sg:city":"Wildwood",
    "sg:classifiers":[
        {
            "category":"Sports & Exercise",
            "subcategory":"Bowling",
            "type":"Entertainment"
        }
    ],
    "sg:phone":"+1 609 729 0111",
    "sg:postcode":"08260",
    "sg:province":"NJ",
    "sg:tags":[
        "center",
        "cinema"
    ],
    "sg:website":"3jwildwoodbowl.com/",
    "wof:name":"3 J's Wildwood Bowl",
    "wof:placetype":"venue"
},
  "geometry": {"coordinates":[-74.815073,38.991095],"type":"Point"}
}