{
  "type": "Feature",
  "properties": {
    "iso:country":"US",
    "sg:address":"39 Tamarack Cir",
    "sg:city":"Skillman",
    "sg:classifiers":[
        {
            "category":"Social Services",
            "type":"Services"
        }
    ],
    "sg:phone":"+1 609 683 0032",
    "sg:postcode":"08558",
    "sg:province":"NJ",
    "wof:name":"Margaret Clarke MA LPC",
    "wof:placetype":"venue"
},
  "geometry": {"coordinates":[-74.648038,40.407135],"type":"Point"}
}