{
  "type": "Feature",
  "properties": {
    "addr:full":"961 Teaneck Rd Teaneck NJ 07666",
    "addr:housenumber":"961",
    "addr:postcode":"07666",
    "addr:street":"Teaneck Rd",
    "iso:country":"US",
    "sg:address":"961 Teaneck Rd",
    "sg:city":"Teaneck",
    "sg:classifiers":[
        {
            "category":"Real Estate",
            "subcategory":"Real Estate Agent",
            "type":"Services"
        }
    ],
    "sg:phone":"+1 201 833 9300",
    "sg:postcode":"07666",
    "sg:province":"NJ",
    "sg:tags":[
        "consultant"
    ],
    "sg:website":"www.realtyline.com",
    "wof:name":"Realtyline Inc",
    "wof:placetype":"venue"
},
  "geometry": {"coordinates":[-74.00509599999999,40.888199],"type":"Point"}
}