{
  "type": "Feature",
  "properties": {
    "addr:full":"52 Adams St Irvington NJ 07111",
    "addr:housenumber":"52",
    "addr:postcode":"07111",
    "addr:street":"Adams St",
    "iso:country":"US",
    "sg:address":"52 Adams St",
    "sg:city":"Irvington",
    "sg:classifiers":[
        {
            "category":"Professional",
            "subcategory":"Management & Consulting",
            "type":"Services"
        }
    ],
    "sg:phone":"+1 973 923 7977",
    "sg:postcode":"07111",
    "sg:province":"NJ",
    "sg:tags":[
        "consultant",
        "educational"
    ],
    "wof:name":"New Jersey Urban Education",
    "wof:placetype":"venue"
},
  "geometry": {"coordinates":[-74.229873,40.73398],"type":"Point"}
}