{
  "type": "Feature",
  "properties": {
    "iso:country":"US",
    "sg:address":"223 Grand St",
    "sg:city":"New Milford",
    "sg:classifiers":[
        {
            "category":"Manufacturing",
            "subcategory":"Tools & Machinery",
            "type":"Manufacturing & Wholesale Goods"
        }
    ],
    "sg:phone":"+1 201 262 1859",
    "sg:postcode":"07646",
    "sg:province":"NJ",
    "sg:tags":[
        "shop",
        "jobbing",
        "repair"
    ],
    "wof:name":"Mkr Precision Inc",
    "wof:placetype":"venue"
},
  "geometry": {"coordinates":[-74.018365,40.950289],"type":"Point"}
}