{
  "type": "Feature",
  "properties": {
    "addr:full":"217 Broadway Point Pleasant Beach NJ 08742",
    "addr:housenumber":"217",
    "addr:postcode":"08742",
    "addr:street":"Broadway",
    "iso:country":"US",
    "sg:address":"217 Broadway",
    "sg:city":"Point Pleasant Beach",
    "sg:classifiers":[
        {
            "category":"Travel",
            "subcategory":"Hotels & Motels",
            "type":"Entertainment"
        }
    ],
    "sg:phone":"+1 732 899 0108",
    "sg:postcode":"08742",
    "sg:province":"NJ",
    "sg:tags":[
        "operation"
    ],
    "wof:name":"Pauline Wanca",
    "wof:placetype":"venue"
},
  "geometry": {"coordinates":[-74.042688,40.100673],"type":"Point"}
}