{
  "type": "Feature",
  "properties": {
    "iso:country":"US",
    "sg:address":"150 S Washington Ave",
    "sg:city":"Bergenfield",
    "sg:classifiers":[
        {
            "category":"Professional",
            "subcategory":"Accounting & Tax Preparation",
            "type":"Services"
        }
    ],
    "sg:phone":"+1 201 387 1760",
    "sg:postcode":"07621",
    "sg:province":"NJ",
    "sg:tags":[
        "accountant"
    ],
    "wof:name":"Robert Friedson CPA",
    "wof:placetype":"venue"
},
  "geometry": {"coordinates":[-73.99703599999999,40.923176],"type":"Point"}
}