{
  "type": "Feature",
  "properties": {
    "addr:full":"42 High St Mount Holly NJ 08060",
    "addr:housenumber":"42",
    "addr:postcode":"08060",
    "addr:street":"High St",
    "iso:country":"US",
    "sg:address":"42 High St",
    "sg:city":"Mount Holly",
    "sg:classifiers":[
        {
            "category":"Real Estate",
            "subcategory":"Architect",
            "type":"Services"
        }
    ],
    "sg:phone":"+1 609 267 0036",
    "sg:postcode":"08060",
    "sg:province":"NJ",
    "wof:name":"Sun Architecture Llc",
    "wof:placetype":"venue"
},
  "geometry": {"coordinates":[-74.788089,39.994124],"type":"Point"}
}