{
  "type": "Feature",
  "properties": {
    "iso:country":"US",
    "sg:address":"136 Ocean Ave",
    "sg:city":"Pt Pleasant Bch",
    "sg:classifiers":[
        {
            "category":"Food & Beverages",
            "subcategory":"Bakery",
            "type":"Retail Goods"
        }
    ],
    "sg:phone":"+1 732 892 5590",
    "sg:postcode":"08742",
    "sg:province":"NJ",
    "sg:tags":[
        "baker"
    ],
    "wof:name":"Muellers Bakery",
    "wof:placetype":"venue"
},
  "geometry": {"coordinates":[-74.036265,40.0995],"type":"Point"}
}