{
  "type": "Feature",
  "properties": {
    "iso:country":"US",
    "sg:address":"128 Mechanic St",
    "sg:city":"Boonton",
    "sg:classifiers":[
        {
            "category":"Building & Trades",
            "subcategory":"Construction",
            "type":"Services"
        }
    ],
    "sg:phone":"+1 973 394 0384",
    "sg:postcode":"07005",
    "sg:province":"NJ",
    "sg:tags":[
        "house"
    ],
    "wof:name":"KCR Construction",
    "wof:placetype":"venue"
},
  "geometry": {"coordinates":[-74.407859,40.904758],"type":"Point"}
}