{
  "type": "Feature",
  "properties": {
    "addr:full":"507 S Livingston Ave Livingston NJ 07039",
    "addr:housenumber":"507",
    "addr:postcode":"07039",
    "addr:street":"S Livingston Ave",
    "iso:country":"US",
    "sg:address":"507 S Livingston Ave",
    "sg:city":"Livingston",
    "sg:classifiers":[
        {
            "category":"Banks & Credit Unions",
            "subcategory":"Bank",
            "type":"Services"
        }
    ],
    "sg:phone":"+1 973 597 1565",
    "sg:postcode":"07039",
    "sg:province":"NJ",
    "sg:website":"www.northforkbank.com",
    "wof:name":"Capital One Bank",
    "wof:placetype":"venue"
},
  "geometry": {"coordinates":[-74.322817,40.775193],"type":"Point"}
}