{
  "type": "Feature",
  "properties": {
    "addr:full":"200 Boyden Ave Maplewood NJ 07040",
    "addr:housenumber":"200",
    "addr:postcode":"07040",
    "addr:street":"Boyden Ave",
    "iso:country":"US",
    "sg:address":"200 Boyden Ave",
    "sg:city":"Maplewood",
    "sg:classifiers":[
        {
            "category":"Professional",
            "subcategory":"Business Services",
            "type":"Services"
        }
    ],
    "sg:phone":"+1   ",
    "sg:postcode":"07040",
    "sg:province":"NJ",
    "wof:name":"Maplewood Testing Service",
    "wof:placetype":"venue"
},
  "geometry": {"coordinates":[-74.251964,40.725093],"type":"Point"}
}