{
  "type": "Feature",
  "properties": {
    "iso:country":"US",
    "sg:address":"330 6th St",
    "sg:city":"Jersey City",
    "sg:classifiers":[
        {
            "category":"Organizations",
            "subcategory":"Religious Organization",
            "type":"Services"
        }
    ],
    "sg:phone":"+1 201 653 0343",
    "sg:postcode":"07302",
    "sg:province":"NJ",
    "sg:tags":[
        "church"
    ],
    "wof:name":"Saint Anthonys Rectory",
    "wof:placetype":"venue"
},
  "geometry": {"coordinates":[-74.050102,40.725962],"type":"Point"}
}