{
  "type": "Feature",
  "properties": {
    "addr:full":"4008 Fernwood Ave Egg Harbor Twp NJ 08234",
    "addr:housenumber":"4008",
    "addr:postcode":"08234",
    "addr:street":"Fernwood Ave",
    "iso:country":"US",
    "sg:address":"4008 Fernwood Ave",
    "sg:city":"Egg Harbor Twp",
    "sg:classifiers":[
        {
            "category":"Building & Trades",
            "subcategory":"Plumbing",
            "type":"Services"
        }
    ],
    "sg:phone":"+1 609 272 1086",
    "sg:postcode":"08234",
    "sg:province":"NJ",
    "sg:tags":[
        "heating",
        "contractor"
    ],
    "wof:name":"Marcelino & Son Heating Clng",
    "wof:placetype":"venue"
},
  "geometry": {"coordinates":[-74.59890300000001,39.4139],"type":"Point"}
}