{
  "type": "Feature",
  "properties": {
    "iso:country":"US",
    "sg:address":"99 Oakridge Ave",
    "sg:city":"Nutley",
    "sg:classifiers":[
        {
            "category":"Professional",
            "subcategory":"Management & Consulting",
            "type":"Services"
        }
    ],
    "sg:phone":"+1   ",
    "sg:postcode":"07110",
    "sg:province":"NJ",
    "sg:tags":[
        "consultant",
        "hospital",
        "health"
    ],
    "wof:name":"Eileen C Napolitano",
    "wof:placetype":"venue"
},
  "geometry": {"coordinates":[-74.15270700000001,40.812062],"type":"Point"}
}