{
  "type": "Feature",
  "properties": {
    "addr:full":"833 W Shore Dr Brigantine NJ 08203",
    "addr:housenumber":"833",
    "addr:postcode":"08203",
    "addr:street":"W Shore Dr",
    "iso:country":"US",
    "sg:address":"833 W Shore Dr",
    "sg:city":"Brigantine",
    "sg:classifiers":[
        {
            "category":"Retail",
            "subcategory":"Repair Shop",
            "type":"Services"
        }
    ],
    "sg:phone":"+1   ",
    "sg:postcode":"08203",
    "sg:province":"NJ",
    "sg:tags":[
        "refrigeration"
    ],
    "wof:name":"Robbys Refrigeration",
    "wof:placetype":"venue"
},
  "geometry": {"coordinates":[-74.381601,39.418155],"type":"Point"}
}