{
  "type": "Feature",
  "properties": {
    "addr:full":"4522 Camden Ave Pennsauken NJ 08110",
    "addr:housenumber":"4522",
    "addr:postcode":"08110",
    "addr:street":"Camden Ave",
    "iso:country":"US",
    "sg:address":"4522 Camden Ave",
    "sg:city":"Pennsauken",
    "sg:classifiers":[
        {
            "category":"Health Services",
            "subcategory":"Doctor",
            "type":"Services"
        }
    ],
    "sg:phone":"+1 856 663 1389",
    "sg:postcode":"08110",
    "sg:province":"NJ",
    "sg:tags":[
        "osteopathic"
    ],
    "wof:name":"Robert Dimaio Do",
    "wof:placetype":"venue"
},
  "geometry": {"coordinates":[-75.06707900000001,39.955703],"type":"Point"}
}