{
  "type": "Feature",
  "properties": {
    "iso:country":"US",
    "sg:address":"6 Park St",
    "sg:city":"Bordentown",
    "sg:classifiers":[
        {
            "category":"Banks & Credit Unions",
            "subcategory":"Investment Brokerage",
            "type":"Services"
        }
    ],
    "sg:phone":"+1   ",
    "sg:postcode":"08505",
    "sg:province":"NJ",
    "sg:tags":[
        "advisory"
    ],
    "wof:name":"Peoples Financial Services",
    "wof:placetype":"venue"
},
  "geometry": {"coordinates":[-74.712936,40.148951],"type":"Point"}
}