{
  "type": "Feature",
  "properties": {
    "addr:full":"20 Palmer Pl Leonia NJ 07605",
    "addr:housenumber":"20",
    "addr:postcode":"07605",
    "addr:street":"Palmer Pl",
    "iso:country":"US",
    "sg:address":"20 Palmer Pl",
    "sg:city":"Leonia",
    "sg:classifiers":[
        {
            "category":"Professional",
            "subcategory":"Business Services",
            "type":"Services"
        }
    ],
    "sg:phone":"+1   ",
    "sg:postcode":"07605",
    "sg:province":"NJ",
    "wof:name":"Creed Enterprises Inc",
    "wof:placetype":"venue"
},
  "geometry": {"coordinates":[-73.98886,40.854269],"type":"Point"}
}