{
  "type": "Feature",
  "properties": {
    "iso:country":"US",
    "sg:address":"Fort of Clay St Brg",
    "sg:city":"Harrison",
    "sg:classifiers":[
        {
            "category":"Home & Garden",
            "subcategory":"Building Materials",
            "type":"Retail Goods"
        }
    ],
    "sg:phone":"+1 973 483 4494",
    "sg:postcode":"07029",
    "sg:province":"NJ",
    "sg:tags":[
        "supply"
    ],
    "wof:name":"Harrison Supply Co",
    "wof:placetype":"venue"
},
  "geometry": {"coordinates":[-74.156403,40.748699],"type":"Point"}
}