{
  "type": "Feature",
  "properties": {
    "iso:country":"US",
    "sg:address":"22 W Pierrepont Ave",
    "sg:city":"Rutherford",
    "sg:classifiers":[
        {
            "category":"Education",
            "subcategory":"Special Training",
            "type":"Public Place"
        }
    ],
    "sg:phone":"+1   ",
    "sg:postcode":"07070",
    "sg:province":"NJ",
    "wof:name":"Winemaking Plus Inc",
    "wof:placetype":"venue"
},
  "geometry": {"coordinates":[-74.11555300000001,40.824422],"type":"Point"}
}