{
  "type": "Feature",
  "properties": {
    "iso:country":"US",
    "sg:address":"6535 Mill Rd",
    "sg:city":"Egg Harbor Township",
    "sg:classifiers":[
        {
            "category":"Building & Trades",
            "subcategory":"Electrical",
            "type":"Services"
        }
    ],
    "sg:phone":"+1 609 927 3513",
    "sg:postcode":"08234",
    "sg:province":"NJ",
    "sg:tags":[
        "electrical",
        "contractor"
    ],
    "wof:name":"Shore Electric Inc",
    "wof:placetype":"venue"
},
  "geometry": {"coordinates":[-74.601247,39.381751],"type":"Point"}
}