{
  "type": "Feature",
  "properties": {
    "addr:full":"155 N Broad St Trenton NJ 08608",
    "addr:housenumber":"155",
    "addr:postcode":"08608",
    "addr:street":"N Broad St",
    "iso:country":"US",
    "sg:address":"155 N Broad St",
    "sg:city":"Trenton",
    "sg:classifiers":[
        {
            "category":"Shopping",
            "subcategory":"Clothing, Apparel, & Fashions",
            "type":"Retail Goods"
        }
    ],
    "sg:phone":"+1   ",
    "sg:postcode":"08608",
    "sg:province":"NJ",
    "wof:name":"Kim Wig Shop",
    "wof:placetype":"venue"
},
  "geometry": {"coordinates":[-74.76445699999999,40.222698],"type":"Point"}
}