{
  "type": "Feature",
  "properties": {
    "addr:full":"1145 Elizabeth Ave Elizabeth NJ 07201",
    "addr:housenumber":"1145",
    "addr:postcode":"07201",
    "addr:street":"Elizabeth Ave",
    "iso:country":"US",
    "sg:address":"1145 Elizabeth Ave",
    "sg:city":"Elizabeth",
    "sg:classifiers":[
        {
            "category":"Professional",
            "subcategory":"Accounting & Tax Preparation",
            "type":"Services"
        }
    ],
    "sg:phone":"+1   ",
    "sg:postcode":"07201",
    "sg:province":"NJ",
    "wof:name":"A C Accounting Service",
    "wof:placetype":"venue"
},
  "geometry": {"coordinates":[-74.212086,40.662006],"type":"Point"}
}