{
  "type": "Feature",
  "properties": {
    "iso:country":"US",
    "sg:address":"1405 Magnolia Rd",
    "sg:city":"Vineland",
    "sg:classifiers":[
        {
            "category":"Recreation",
            "type":"Entertainment"
        }
    ],
    "sg:phone":"+1   ",
    "sg:postcode":"08361",
    "sg:province":"NJ",
    "wof:name":"New Jersey State Black Belt",
    "wof:placetype":"venue"
},
  "geometry": {"coordinates":[-74.998383,39.464451],"type":"Point"}
}