{
  "type": "Feature",
  "properties": {
    "addr:full":"259 Bedford Rd Dumont NJ 07628",
    "addr:housenumber":"259",
    "addr:postcode":"07628",
    "addr:street":"Bedford Rd",
    "iso:country":"US",
    "sg:address":"259 Bedford Rd",
    "sg:city":"Dumont",
    "sg:classifiers":[
        {
            "category":"Retail",
            "subcategory":"Auto Repair",
            "type":"Services"
        }
    ],
    "sg:phone":"+1 201 385 2475",
    "sg:postcode":"07628",
    "sg:province":"NJ",
    "sg:tags":[
        "general"
    ],
    "wof:name":"G & G Ignition Co Inc",
    "wof:placetype":"venue"
},
  "geometry": {"coordinates":[-73.993962,40.953126],"type":"Point"}
}