{
  "type": "Feature",
  "properties": {
    "addr:full":"26 Central Ave Flemington NJ 08822",
    "addr:housenumber":"26",
    "addr:postcode":"08822",
    "addr:street":"Central Ave",
    "iso:country":"US",
    "sg:address":"26 Central Ave",
    "sg:city":"Flemington",
    "sg:phone":"+1 908 782 3383",
    "sg:postcode":"08822",
    "sg:province":"NJ",
    "sg:tags":[
        "equipment",
        "supply"
    ],
    "wof:name":"POS Solutions Inc",
    "wof:placetype":"venue"
},
  "geometry": {"coordinates":[-74.86132499999999,40.505421],"type":"Point"}
}