{
  "type": "Feature",
  "properties": {
    "addr:full":"199 Russell Pl Hackensack NJ 07601",
    "addr:housenumber":"199",
    "addr:postcode":"07601",
    "addr:street":"Russell Pl",
    "iso:country":"US",
    "sg:address":"199 Russell Pl",
    "sg:city":"Hackensack",
    "sg:classifiers":[
        {
            "category":"Community Center",
            "type":"Public Place"
        }
    ],
    "sg:phone":"+1 201 678 1601",
    "sg:postcode":"07601",
    "sg:province":"NJ",
    "sg:tags":[
        "medical"
    ],
    "sg:website":"www.humed.com",
    "wof:name":"Hackensack University Medical Center",
    "wof:placetype":"venue"
},
  "geometry": {"coordinates":[-74.05267600000001,40.882014],"type":"Point"}
}