{
  "type": "Feature",
  "properties": {
    "addr:full":"12 Cemetery Rd Blairstown NJ 07825",
    "addr:housenumber":"12",
    "addr:postcode":"07825",
    "addr:street":"Cemetery Rd",
    "iso:country":"US",
    "sg:address":"12 Cemetery Rd",
    "sg:city":"Blairstown",
    "sg:classifiers":[
        {
            "category":"Real Estate",
            "subcategory":"Architect",
            "type":"Services"
        }
    ],
    "sg:phone":"+1 908 459 5588",
    "sg:postcode":"07825",
    "sg:province":"NJ",
    "sg:tags":[
        "architectural"
    ],
    "wof:name":"Links Design & Management Inc",
    "wof:placetype":"venue"
},
  "geometry": {"coordinates":[-75.014179,40.91899],"type":"Point"}
}