{
  "type": "Feature",
  "properties": {
    "addr:full":"314 Stone House Ln Mullica Hill NJ 08062",
    "addr:housenumber":"314",
    "addr:postcode":"08062",
    "addr:street":"Stone House Ln",
    "iso:country":"US",
    "sg:address":"314 Stone House Ln",
    "sg:city":"Mullica Hill",
    "sg:classifiers":[
        {
            "category":"Professional",
            "subcategory":"Business Services",
            "type":"Services"
        }
    ],
    "sg:phone":"+1   ",
    "sg:postcode":"08062",
    "sg:province":"NJ",
    "wof:name":"Global Language Solutions",
    "wof:placetype":"venue"
},
  "geometry": {"coordinates":[-75.20579600000001,39.747512],"type":"Point"}
}