{
  "type": "Feature",
  "properties": {
    "addr:full":"100 Nolans Point Rd Lake Hopatcong NJ 07849",
    "addr:housenumber":"100",
    "addr:postcode":"07849",
    "addr:street":"Nolans Point Rd",
    "iso:country":"US",
    "sg:address":"100 Nolans Point Rd",
    "sg:city":"Lake Hopatcong",
    "sg:classifiers":[
        {
            "category":"Building & Trades",
            "subcategory":"Plumbing",
            "type":"Services"
        }
    ],
    "sg:phone":"+1 973 663 8470",
    "sg:postcode":"07849",
    "sg:province":"NJ",
    "sg:tags":[
        "conditioning",
        "air",
        "system",
        "contractor"
    ],
    "wof:name":"Central Comfort",
    "wof:placetype":"venue"
},
  "geometry": {"coordinates":[-74.628411,40.94754],"type":"Point"}
}