{
  "type": "Feature",
  "properties": {
    "addr:full":"828 Main St Paterson NJ 07503",
    "addr:housenumber":"828",
    "addr:postcode":"07503",
    "addr:street":"Main St",
    "iso:country":"US",
    "sg:address":"828 Main St",
    "sg:city":"Paterson",
    "sg:classifiers":[
        {
            "category":"Autos & Motor Vehicles",
            "subcategory":"Fuel & Gas Station",
            "type":"Retail Goods"
        }
    ],
    "sg:phone":"+1 973 357 0887",
    "sg:postcode":"07503",
    "sg:province":"NJ",
    "wof:name":"Paterson B P",
    "wof:placetype":"venue"
},
  "geometry": {"coordinates":[-74.16300200000001,40.8983],"type":"Point"}
}