{
  "type": "Feature",
  "properties": {
    "addr:full":"205 Culver Rd Monmouth Jct NJ 08852",
    "addr:housenumber":"205",
    "addr:postcode":"08852",
    "addr:street":"Culver Rd",
    "iso:country":"US",
    "sg:address":"205 Culver Rd",
    "sg:city":"Monmouth Jct",
    "sg:classifiers":[
        {
            "category":"Wholesale",
            "subcategory":"Auto Parts",
            "type":"Manufacturing & Wholesale Goods"
        }
    ],
    "sg:phone":"+1 732 220 1177",
    "sg:postcode":"08852",
    "sg:province":"NJ",
    "sg:tags":[
        "automobile",
        "rebuilt"
    ],
    "wof:name":"King Parts Auto Wreckers",
    "wof:placetype":"venue"
},
  "geometry": {"coordinates":[-74.53031300000001,40.369525],"type":"Point"}
}