{
  "type": "Feature",
  "properties": {
    "iso:country":"US",
    "sg:address":"238 N 1st Ave",
    "sg:city":"Manville",
    "sg:classifiers":[
        {
            "category":"Retail",
            "subcategory":"Auto Repair",
            "type":"Services"
        }
    ],
    "sg:phone":"+1   ",
    "sg:postcode":"08835",
    "sg:province":"NJ",
    "sg:tags":[
        "general"
    ],
    "wof:name":"J & M Auto Service",
    "wof:placetype":"venue"
},
  "geometry": {"coordinates":[-74.58758400000001,40.546751],"type":"Point"}
}