{
  "type": "Feature",
  "properties": {
    "addr:full":"521 Hamden Rd Annandale NJ 08801",
    "addr:housenumber":"521",
    "addr:postcode":"08801",
    "addr:street":"Hamden Rd",
    "iso:country":"US",
    "sg:address":"521 Hamden Rd",
    "sg:city":"Annandale",
    "sg:classifiers":[
        {
            "category":"Restaurant",
            "type":"Food & Drink"
        }
    ],
    "sg:phone":"+1 908 735 4212",
    "sg:postcode":"08801",
    "sg:province":"NJ",
    "wof:name":"JTS Diner",
    "wof:placetype":"venue"
},
  "geometry": {"coordinates":[-74.90156899999999,40.600919],"type":"Point"}
}