{
  "type": "Feature",
  "properties": {
    "iso:country":"US",
    "sg:address":"120 Jackson Ave",
    "sg:city":"Rutherford",
    "sg:classifiers":[
        {
            "category":"Education",
            "subcategory":"Special Training",
            "type":"Public Place"
        }
    ],
    "sg:phone":"+1   ",
    "sg:postcode":"07070",
    "sg:province":"NJ",
    "wof:name":"Garden State Academy Of Music",
    "wof:placetype":"venue"
},
  "geometry": {"coordinates":[-74.11679100000001,40.837468],"type":"Point"}
}