{
  "type": "Feature",
  "properties": {
    "iso:country":"US",
    "sg:address":"163 S Livingston Ave",
    "sg:city":"Livingston",
    "sg:classifiers":[
        {
            "category":"Building & Trades",
            "subcategory":"Locksmith",
            "type":"Services"
        }
    ],
    "sg:phone":"+1 973 854 5189",
    "sg:postcode":"07039",
    "sg:province":"NJ",
    "sg:tags":[
        "key"
    ],
    "wof:name":"A 24 Hour Always Available Emerg 24 Locksmith",
    "wof:placetype":"venue"
},
  "geometry": {"coordinates":[-74.313399,40.790542],"type":"Point"}
}