{
  "type": "Feature",
  "properties": {
    "addr:full":"511 Chestnut St Roselle Park NJ 07204",
    "addr:housenumber":"511",
    "addr:postcode":"07204",
    "addr:street":"Chestnut St",
    "iso:country":"US",
    "sg:address":"511 Chestnut St",
    "sg:city":"Roselle Park",
    "sg:classifiers":[
        {
            "category":"Health Services",
            "subcategory":"Doctor",
            "type":"Services"
        }
    ],
    "sg:phone":"+1 908 245 1012",
    "sg:postcode":"07204",
    "sg:province":"NJ",
    "sg:tags":[
        "dentist"
    ],
    "wof:name":"Thomas G Santora DMD",
    "wof:placetype":"venue"
},
  "geometry": {"coordinates":[-74.265214,40.667256],"type":"Point"}
}