{
  "type": "Feature",
  "properties": {
    "iso:country":"US",
    "sg:address":"25 Fleetwood Pl",
    "sg:city":"Irvington",
    "sg:classifiers":[
        {
            "category":"Freight",
            "type":"Transportation"
        }
    ],
    "sg:phone":"+1 973 416 3163",
    "sg:postcode":"07111",
    "sg:province":"NJ",
    "sg:tags":[
        "trucking"
    ],
    "wof:name":"Deas Trucking Inc",
    "wof:placetype":"venue"
},
  "geometry": {"coordinates":[-74.25289600000001,40.713865],"type":"Point"}
}