{
  "type": "Feature",
  "properties": {
    "iso:country":"US",
    "sg:address":"31 Monticello Ave",
    "sg:city":"Jersey City",
    "sg:classifiers":[
        {
            "category":"Real Estate",
            "subcategory":"Real Estate Operator",
            "type":"Services"
        }
    ],
    "sg:phone":"+1 201 332 1674",
    "sg:postcode":"07304",
    "sg:province":"NJ",
    "sg:tags":[
        "apartment"
    ],
    "wof:name":"Salm Lafayette Apartments",
    "wof:placetype":"venue"
},
  "geometry": {"coordinates":[-74.07399700000001,40.7155],"type":"Point"}
}