{
  "type": "Feature",
  "properties": {
    "addr:full":"316 S Pleasant Ave Ridgewood NJ 07450",
    "addr:housenumber":"316",
    "addr:postcode":"07450",
    "addr:street":"S Pleasant Ave",
    "iso:country":"US",
    "sg:address":"316 S Pleasant Ave",
    "sg:city":"Ridgewood",
    "sg:classifiers":[
        {
            "category":"Building & Trades",
            "subcategory":"Landscaping Services",
            "type":"Services"
        }
    ],
    "sg:phone":"+1 201 444 9313",
    "sg:postcode":"07450",
    "sg:province":"NJ",
    "sg:tags":[
        "landscape"
    ],
    "wof:name":"Scott Cornell Landscaping & De",
    "wof:placetype":"venue"
},
  "geometry": {"coordinates":[-74.101866,40.967642],"type":"Point"}
}