{
  "type": "Feature",
  "properties": {
    "addr:full":"60 Washington Ave Morristown NJ 07960",
    "addr:housenumber":"60",
    "addr:postcode":"07960",
    "addr:street":"Washington Ave",
    "iso:country":"US",
    "sg:address":"60 Washington Ave",
    "sg:city":"Morristown",
    "sg:classifiers":[
        {
            "category":"Professional",
            "subcategory":"Lawyer & Legal Services",
            "type":"Services"
        }
    ],
    "sg:phone":"+1 973 656 9159",
    "sg:postcode":"07960",
    "sg:province":"NJ",
    "sg:tags":[
        "attorney"
    ],
    "wof:name":"Pringle & Quinn",
    "wof:placetype":"venue"
},
  "geometry": {"coordinates":[-74.46459900000001,40.795197],"type":"Point"}
}