{
  "type": "Feature",
  "properties": {
    "iso:country":"US",
    "sg:address":"808 Mine Rd",
    "sg:city":"Bridgewater",
    "sg:classifiers":[
        {
            "category":"Professional",
            "subcategory":"Lawyer & Legal Services",
            "type":"Services"
        }
    ],
    "sg:phone":"+1 908 541 0003",
    "sg:postcode":"08807",
    "sg:province":"NJ",
    "sg:tags":[
        "attorney"
    ],
    "wof:name":"Richard E Yonezuka-Brown",
    "wof:placetype":"venue"
},
  "geometry": {"coordinates":[-74.609217,40.608277],"type":"Point"}
}