{
  "type": "Feature",
  "properties": {
    "addr:full":"145 Central Ave Hackensack NJ 07601",
    "addr:housenumber":"145",
    "addr:postcode":"07601",
    "addr:street":"Central Ave",
    "iso:country":"US",
    "sg:address":"145 Central Ave",
    "sg:city":"Hackensack",
    "sg:classifiers":[
        {
            "category":"Building & Trades",
            "subcategory":"Plumbing",
            "type":"Services"
        }
    ],
    "sg:phone":"+1 201 487 0046",
    "sg:postcode":"07601",
    "sg:province":"NJ",
    "sg:tags":[
        "plumbing",
        "contractor"
    ],
    "wof:name":"Frank Ackerman Inc",
    "wof:placetype":"venue"
},
  "geometry": {"coordinates":[-74.047104,40.88666],"type":"Point"}
}