{
  "type": "Feature",
  "properties": {
    "iso:country":"US",
    "sg:address":"58 Winterton Dr",
    "sg:city":"Toms River",
    "sg:classifiers":[
        {
            "category":"Recreation",
            "type":"Entertainment"
        }
    ],
    "sg:phone":"+1 732 341 4190",
    "sg:postcode":"08757",
    "sg:province":"NJ",
    "sg:tags":[
        "club",
        "membership"
    ],
    "wof:name":"Jewish Social Club",
    "wof:placetype":"venue"
},
  "geometry": {"coordinates":[-74.28093200000001,39.968214],"type":"Point"}
}