{
  "type": "Feature",
  "properties": {
    "iso:country":"US",
    "sg:address":"48 Barchester Way",
    "sg:city":"Westfield",
    "sg:classifiers":[
        {
            "category":"Health Services",
            "subcategory":"Doctor",
            "type":"Services"
        }
    ],
    "sg:phone":"+1 908 233 6523",
    "sg:postcode":"07090",
    "sg:province":"NJ",
    "wof:name":"Lavy Norman W",
    "wof:placetype":"venue"
},
  "geometry": {"coordinates":[-74.370126,40.665176],"type":"Point"}
}