{
  "type": "Feature",
  "properties": {
    "iso:country":"US",
    "sg:address":"700 S Lakeshore Dr",
    "sg:city":"Browns Mills",
    "sg:classifiers":[
        {
            "category":"Building & Trades",
            "subcategory":"Construction",
            "type":"Services"
        }
    ],
    "sg:phone":"+1 609 893 5943",
    "sg:postcode":"08015",
    "sg:province":"NJ",
    "sg:tags":[
        "contractor"
    ],
    "wof:name":"David L Jost Jr Contracting",
    "wof:placetype":"venue"
},
  "geometry": {"coordinates":[-74.567651,39.971027],"type":"Point"}
}