{
  "type": "Feature",
  "properties": {
    "iso:country":"US",
    "sg:address":"574 Newark Ave",
    "sg:city":"Jersey City",
    "sg:classifiers":[
        {
            "category":"Professional",
            "subcategory":"Lawyer & Legal Services",
            "type":"Services"
        }
    ],
    "sg:phone":"+1 201 792 6363",
    "sg:postcode":"07306",
    "sg:province":"NJ",
    "sg:tags":[
        "attorney"
    ],
    "wof:name":"Northeast New Jersey Legal Svc",
    "wof:placetype":"venue"
},
  "geometry": {"coordinates":[-74.057142,40.732212],"type":"Point"}
}