{
  "type": "Feature",
  "properties": {
    "addr:full":"59 Halsey St Newark NJ 07102",
    "addr:housenumber":"59",
    "addr:postcode":"07102",
    "addr:street":"Halsey St",
    "iso:country":"US",
    "sg:address":"59 Halsey St",
    "sg:city":"Newark",
    "sg:classifiers":[
        {
            "category":"Building & Trades",
            "subcategory":"Locksmith",
            "type":"Services"
        }
    ],
    "sg:phone":"+1 973 854 5105",
    "sg:postcode":"07102",
    "sg:province":"NJ",
    "sg:tags":[
        "key"
    ],
    "wof:name":"A 24 Hour Always Available Emerg 24 Locksmith",
    "wof:placetype":"venue"
},
  "geometry": {"coordinates":[-74.171421,40.740482],"type":"Point"}
}