{
  "type": "Feature",
  "properties": {
    "iso:country":"US",
    "sg:address":"111 Orion Rd",
    "sg:city":"Berkeley Heights",
    "sg:classifiers":[
        {
            "category":"Professional",
            "subcategory":"Management & Consulting",
            "type":"Services"
        }
    ],
    "sg:phone":"+1 908 464 5117",
    "sg:postcode":"07922",
    "sg:province":"NJ",
    "sg:tags":[
        "business"
    ],
    "wof:name":"Valid Solutions Inc",
    "wof:placetype":"venue"
},
  "geometry": {"coordinates":[-74.421108,40.67057],"type":"Point"}
}