{
  "type": "Feature",
  "properties": {
    "iso:country":"US",
    "sg:address":"865 S Fork Landing Rd",
    "sg:city":"Cinnaminson",
    "sg:classifiers":[
        {
            "category":"Building & Trades",
            "subcategory":"Landscaping Services",
            "type":"Services"
        }
    ],
    "sg:phone":"+1 856 722 0556",
    "sg:postcode":"08077",
    "sg:province":"NJ",
    "sg:tags":[
        "tree"
    ],
    "wof:name":"Hudson Tree Service",
    "wof:placetype":"venue"
},
  "geometry": {"coordinates":[-75.01318999999999,39.971985],"type":"Point"}
}