{
  "type": "Feature",
  "properties": {
    "addr:full":"509 2nd Ave Asbury Park NJ 07712",
    "addr:housenumber":"509",
    "addr:postcode":"07712",
    "addr:street":"2Nd Ave Asbury",
    "iso:country":"US",
    "sg:address":"509 2nd Ave",
    "sg:city":"Asbury Park",
    "sg:classifiers":[
        {
            "category":"Retail",
            "subcategory":"Funeral Services",
            "type":"Services"
        }
    ],
    "sg:phone":"+1 732 775 2455",
    "sg:postcode":"07712",
    "sg:province":"NJ",
    "sg:tags":[
        "director",
        "parlor"
    ],
    "wof:name":"Buckley Funeral Homes",
    "wof:placetype":"venue"
},
  "geometry": {"coordinates":[-74.008132,40.22194],"type":"Point"}
}