{
  "type": "Feature",
  "properties": {
    "iso:country":"US",
    "sg:address":"424 Portsmouth Rd",
    "sg:city":"Cape May",
    "sg:classifiers":[
        {
            "category":"Professional",
            "subcategory":"Computer Services",
            "type":"Services"
        }
    ],
    "sg:phone":"+1   ",
    "sg:postcode":"08204",
    "sg:province":"NJ",
    "sg:tags":[
        "design",
        "system"
    ],
    "wof:name":"Fishing Rod Enterprises",
    "wof:placetype":"venue"
},
  "geometry": {"coordinates":[-74.913704,38.960567],"type":"Point"}
}