{
  "type": "Feature",
  "properties": {
    "addr:full":"501 High St Norwood NJ 07648",
    "addr:housenumber":"501",
    "addr:postcode":"07648",
    "addr:street":"High St",
    "iso:country":"US",
    "sg:address":"501 High St",
    "sg:city":"Norwood",
    "sg:classifiers":[
        {
            "category":"Building & Trades",
            "subcategory":"Landscaping Services",
            "type":"Services"
        }
    ],
    "sg:phone":"+1 201 768 1577",
    "sg:postcode":"07648",
    "sg:province":"NJ",
    "sg:tags":[
        "landscape"
    ],
    "wof:name":"Irish Landscape Designs",
    "wof:placetype":"venue"
},
  "geometry": {"coordinates":[-73.955642,40.999656],"type":"Point"}
}