{
  "type": "Feature",
  "properties": {
    "addr:full":"100 Bauer Dr Oakland NJ 07436",
    "addr:housenumber":"100",
    "addr:postcode":"07436",
    "addr:street":"Bauer Dr",
    "iso:country":"US",
    "sg:address":"100 Bauer Dr",
    "sg:city":"Oakland",
    "sg:classifiers":[
        {
            "category":"Professional",
            "subcategory":"Research",
            "type":"Services"
        }
    ],
    "sg:phone":"+1   ",
    "sg:postcode":"07436",
    "sg:province":"NJ",
    "sg:tags":[
        "commercial",
        "physical"
    ],
    "wof:name":"Crompton Corporation",
    "wof:placetype":"venue"
},
  "geometry": {"coordinates":[-74.237312,41.009201],"type":"Point"}
}