{
  "type": "Feature",
  "properties": {
    "iso:country":"US",
    "sg:address":"1427 Boardwalk",
    "sg:city":"Atlantic City",
    "sg:classifiers":[
        {
            "category":"Shopping",
            "subcategory":"Clothing, Apparel, & Fashions",
            "type":"Retail Goods"
        }
    ],
    "sg:phone":"+1 609 347 0050",
    "sg:postcode":"08401",
    "sg:province":"NJ",
    "sg:tags":[
        "sportswear"
    ],
    "wof:name":"Seaside Sportswear",
    "wof:placetype":"venue"
},
  "geometry": {"coordinates":[-74.425022,39.357056],"type":"Point"}
}