{
  "type": "Feature",
  "properties": {
    "addr:full":"1 Jefferson Dr Lake Hopatcong NJ 07849",
    "addr:housenumber":"1",
    "addr:postcode":"07849",
    "addr:street":"Jefferson Dr",
    "iso:country":"US",
    "sg:address":"1 Jefferson Dr",
    "sg:city":"Lake Hopatcong",
    "sg:classifiers":[
        {
            "category":"Education",
            "subcategory":"School",
            "type":"Public Place"
        }
    ],
    "sg:phone":"+1   ",
    "sg:postcode":"07849",
    "sg:province":"NJ",
    "sg:website":"www.jefftwp.org",
    "wof:name":"Ellen T Briggs Elementary Schl",
    "wof:placetype":"venue"
},
  "geometry": {"coordinates":[-74.612916,40.951505],"type":"Point"}
}