{
  "type": "Feature",
  "properties": {
    "iso:country":"US",
    "sg:address":"115 Plaza Ctr",
    "sg:city":"Secaucus",
    "sg:classifiers":[
        {
            "category":"Food & Beverages",
            "subcategory":"Liquor & Beverages",
            "type":"Retail Goods"
        }
    ],
    "sg:phone":"+1 201 867 7428",
    "sg:postcode":"07094",
    "sg:province":"NJ",
    "sg:tags":[
        "beer",
        "spirit",
        "wine"
    ],
    "wof:name":"Secaucus Liquor Shop Inc",
    "wof:placetype":"venue"
},
  "geometry": {"coordinates":[-74.05639600000001,40.791401],"type":"Point"}
}