{
  "type": "Feature",
  "properties": {
    "addr:full":"570 Chesterfield Arneytown Rd Wrightstown NJ 08562",
    "addr:housenumber":"570",
    "addr:postcode":"08562",
    "addr:street":"Chesterfield Arneytown Rd",
    "iso:country":"US",
    "sg:address":"570 Chesterfield Arneytown Rd",
    "sg:city":"Wrightstown",
    "sg:classifiers":[
        {
            "category":"Building & Trades",
            "subcategory":"Construction",
            "type":"Services"
        }
    ],
    "sg:phone":"+1 609 259 7521",
    "sg:postcode":"08562",
    "sg:province":"NJ",
    "sg:tags":[
        "interior",
        "residential",
        "painting",
        "exterior"
    ],
    "wof:name":"Daves Minor Changes Inc",
    "wof:placetype":"venue"
},
  "geometry": {"coordinates":[-74.61133100000001,40.107782],"type":"Point"}
}