{
  "type": "Feature",
  "properties": {
    "addr:full":"115 E Grove St Westfield NJ 07090",
    "addr:housenumber":"115",
    "addr:postcode":"07090",
    "addr:street":"E Grove St",
    "iso:country":"US",
    "sg:address":"115 E Grove St",
    "sg:city":"Westfield",
    "sg:classifiers":[
        {
            "category":"Retail",
            "subcategory":"Repair Shop",
            "type":"Services"
        }
    ],
    "sg:phone":"+1 908 232 7661",
    "sg:postcode":"07090",
    "sg:province":"NJ",
    "sg:tags":[
        "lock",
        "locksmith"
    ],
    "wof:name":"A 24 Hour Locksmith",
    "wof:placetype":"venue"
},
  "geometry": {"coordinates":[-74.33418500000001,40.64596],"type":"Point"}
}