{
  "type": "Feature",
  "properties": {
    "addr:full":"43 Sea Drift Ave Highlands NJ 07732",
    "addr:housenumber":"43",
    "addr:postcode":"07732",
    "addr:street":"Sea Drift Ave",
    "iso:country":"US",
    "sg:address":"43 Sea Drift Ave",
    "sg:city":"Highlands",
    "sg:classifiers":[
        {
            "category":"Building & Trades",
            "subcategory":"Plumbing",
            "type":"Services"
        }
    ],
    "sg:phone":"+1 732 291 2145",
    "sg:postcode":"07732",
    "sg:province":"NJ",
    "sg:tags":[
        "contractor"
    ],
    "wof:name":"Brothers Mechanical",
    "wof:placetype":"venue"
},
  "geometry": {"coordinates":[-73.990165,40.405552],"type":"Point"}
}