{
  "type": "Feature",
  "properties": {
    "iso:country":"US",
    "sg:address":"252 State Rte 31",
    "sg:city":"Washington",
    "sg:classifiers":[
        {
            "category":"Building & Trades",
            "subcategory":"Construction",
            "type":"Services"
        }
    ],
    "sg:phone":"+1 908 689 9500",
    "sg:postcode":"07882",
    "sg:province":"NJ",
    "sg:tags":[
        "builder",
        "operative"
    ],
    "wof:name":"Production Office",
    "wof:placetype":"venue"
},
  "geometry": {"coordinates":[-74.98006599999999,40.770067],"type":"Point"}
}