{
  "type": "Feature",
  "properties": {
    "addr:full":"497 Plainsboro Rd Plainsboro NJ 08536",
    "addr:housenumber":"497",
    "addr:postcode":"08536",
    "addr:street":"Plainsboro Rd",
    "iso:country":"US",
    "sg:address":"497 Plainsboro Rd",
    "sg:city":"Plainsboro",
    "sg:classifiers":[
        {
            "category":"Banks & Credit Unions",
            "subcategory":"Bank",
            "type":"Services"
        }
    ],
    "sg:phone":"+1 609 897 1401",
    "sg:postcode":"08536",
    "sg:province":"NJ",
    "wof:name":"Pnc Bank",
    "wof:placetype":"venue"
},
  "geometry": {"coordinates":[-74.59992699999999,40.333615],"type":"Point"}
}