{
  "type": "Feature",
  "properties": {
    "addr:full":"105 Roosevelt Blvd Oakland NJ 07436",
    "addr:housenumber":"105",
    "addr:postcode":"07436",
    "addr:street":"Roosevelt Blvd",
    "iso:country":"US",
    "sg:address":"105 Roosevelt Blvd",
    "sg:city":"Oakland",
    "sg:classifiers":[
        {
            "category":"Building & Trades",
            "subcategory":"Landscaping Services",
            "type":"Services"
        }
    ],
    "sg:phone":"+1 201 337 1299",
    "sg:postcode":"07436",
    "sg:province":"NJ",
    "sg:tags":[
        "landscape"
    ],
    "wof:name":"Bill Artinger Landscaping",
    "wof:placetype":"venue"
},
  "geometry": {"coordinates":[-74.24472799999999,41.032978],"type":"Point"}
}