{
  "type": "Feature",
  "properties": {
    "addr:full":"3411 Round Hill Rd Branchburg NJ 08876",
    "addr:housenumber":"3411",
    "addr:postcode":"08876",
    "addr:street":"Round Hill Rd",
    "iso:country":"US",
    "sg:address":"3411 Round Hill Rd",
    "sg:city":"Branchburg",
    "sg:classifiers":[
        {
            "category":"Shopping",
            "type":"Retail Goods"
        }
    ],
    "sg:phone":"+1 908 526 1666",
    "sg:postcode":"08876",
    "sg:province":"NJ",
    "sg:tags":[
        "cosmetic",
        "perfume"
    ],
    "wof:name":"Mary Kay Cosmetics",
    "wof:placetype":"venue"
},
  "geometry": {"coordinates":[-74.706718,40.612185],"type":"Point"}
}