{
  "type": "Feature",
  "properties": {
    "iso:country":"US",
    "sg:address":"21 Grove St",
    "sg:city":"Kearny",
    "sg:classifiers":[
        {
            "category":"Building & Trades",
            "subcategory":"Construction",
            "type":"Services"
        }
    ],
    "sg:phone":"+1 201 927 5655",
    "sg:postcode":"07032",
    "sg:province":"NJ",
    "sg:tags":[
        "house"
    ],
    "wof:name":"A One Quality Remodeling LLC",
    "wof:placetype":"venue"
},
  "geometry": {"coordinates":[-74.149055,40.765274],"type":"Point"}
}