{
  "type": "Feature",
  "properties": {
    "iso:country":"US",
    "sg:address":"16 Van Cleve Ave",
    "sg:city":"Clifton",
    "sg:classifiers":[
        {
            "category":"Building & Trades",
            "subcategory":"Construction",
            "type":"Services"
        },
        {
            "category":"Home & Garden",
            "subcategory":"Carpets & Floor Coverings",
            "type":"Retail Goods"
        }
    ],
    "sg:phone":"+1 973 340 6214",
    "sg:postcode":"07011",
    "sg:province":"NJ",
    "sg:tags":[
        "laying",
        "contractor"
    ],
    "wof:name":"Garcia-Feliz Hardwood Flooring",
    "wof:placetype":"venue"
},
  "geometry": {"coordinates":[-74.13083899999999,40.876906],"type":"Point"}
}