{
  "type": "Feature",
  "properties": {
    "iso:country":"US",
    "sg:address":"462 Central Ave",
    "sg:city":"Jersey City",
    "sg:classifiers":[
        {
            "category":"Social Services",
            "subcategory":"Child Care",
            "type":"Services"
        }
    ],
    "sg:phone":"+1 201 798 7474",
    "sg:postcode":"07307",
    "sg:province":"NJ",
    "sg:tags":[
        "day"
    ],
    "wof:name":"Central Day Care",
    "wof:placetype":"venue"
},
  "geometry": {"coordinates":[-74.046055,40.750664],"type":"Point"}
}