{
  "type": "Feature",
  "properties": {
    "iso:country":"US",
    "sg:address":"155 Exeter St",
    "sg:city":"Highland Park",
    "sg:classifiers":[
        {
            "category":"Professional",
            "subcategory":"Business Services",
            "type":"Services"
        }
    ],
    "sg:phone":"+1   ",
    "sg:postcode":"08904",
    "sg:province":"NJ",
    "wof:name":"As You Wish Enterprises LLC",
    "wof:placetype":"venue"
},
  "geometry": {"coordinates":[-74.41271500000001,40.50392],"type":"Point"}
}