{
  "type": "Feature",
  "properties": {
    "addr:full":"20 Charlton St Newark NJ 07103",
    "addr:housenumber":"20",
    "addr:postcode":"07103",
    "addr:street":"Charlton St",
    "iso:country":"US",
    "sg:address":"20 Charlton St",
    "sg:city":"Newark",
    "sg:classifiers":[
        {
            "category":"Organizations",
            "subcategory":"Community Association",
            "type":"Services"
        }
    ],
    "sg:phone":"+1 973 589 9721",
    "sg:postcode":"07103",
    "sg:province":"NJ",
    "sg:tags":[
        "civic",
        "social"
    ],
    "wof:name":"Howard Schwartz American",
    "wof:placetype":"venue"
},
  "geometry": {"coordinates":[-74.18690700000001,40.734828],"type":"Point"}
}