{
  "type": "Feature",
  "properties": {
    "addr:full":"39 Maple Ave Pennsville NJ 08070",
    "addr:housenumber":"39",
    "addr:postcode":"08070",
    "addr:street":"Maple Ave",
    "iso:country":"US",
    "sg:address":"39 Maple Ave",
    "sg:city":"Pennsville",
    "sg:classifiers":[
        {
            "category":"Wholesale",
            "subcategory":"Construction Materials",
            "type":"Manufacturing & Wholesale Goods"
        }
    ],
    "sg:phone":"+1 856 678 7291",
    "sg:postcode":"08070",
    "sg:province":"NJ",
    "sg:tags":[
        "fence"
    ],
    "wof:name":"Kiger Fence Co",
    "wof:placetype":"venue"
},
  "geometry": {"coordinates":[-75.506094,39.662358],"type":"Point"}
}