{
  "type": "Feature",
  "properties": {
    "addr:full":"82 State Rte 15 Lafayette NJ 07848",
    "addr:housenumber":"82",
    "addr:postcode":"07848",
    "addr:street":"State Rte 15",
    "iso:country":"US",
    "sg:address":"82 State Rte 15",
    "sg:city":"Lafayette",
    "sg:classifiers":[
        {
            "category":"Health Services",
            "subcategory":"Chiropractor",
            "type":"Services"
        }
    ],
    "sg:phone":"+1 973 383 5052",
    "sg:postcode":"07848",
    "sg:province":"NJ",
    "sg:website":"www.spartahealth.org",
    "wof:name":"Takacs Chiropractic Center",
    "wof:placetype":"venue"
},
  "geometry": {"coordinates":[-74.698689,41.106199],"type":"Point"}
}