{
  "type": "Feature",
  "properties": {
    "addr:full":"86 Roxiticus Rd Far Hills NJ 07931",
    "addr:housenumber":"86",
    "addr:postcode":"07931",
    "addr:street":"Roxiticus Rd",
    "iso:country":"US",
    "sg:address":"86 Roxiticus Rd",
    "sg:city":"Far Hills",
    "sg:classifiers":[
        {
            "category":"Banks & Credit Unions",
            "subcategory":"Financial Services",
            "type":"Services"
        }
    ],
    "sg:phone":"+1   ",
    "sg:postcode":"07931",
    "sg:province":"NJ",
    "sg:tags":[
        "investor"
    ],
    "wof:name":"Roxiticus Investment Corp",
    "wof:placetype":"venue"
},
  "geometry": {"coordinates":[-74.653312,40.750318],"type":"Point"}
}