{
  "type": "Feature",
  "properties": {
    "addr:full":"93 Cedar Ave Maywood NJ 07607",
    "addr:housenumber":"93",
    "addr:postcode":"07607",
    "addr:street":"Cedar Ave",
    "iso:country":"US",
    "sg:address":"93 Cedar Ave",
    "sg:city":"Maywood",
    "sg:classifiers":[
        {
            "category":"Social Services",
            "type":"Services"
        }
    ],
    "sg:phone":"+1 201 587 0178",
    "sg:postcode":"07607",
    "sg:province":"NJ",
    "wof:name":"Schifrien E Lcsw Bcd",
    "wof:placetype":"venue"
},
  "geometry": {"coordinates":[-74.05325999999999,40.910853],"type":"Point"}
}