{
  "type": "Feature",
  "properties": {
    "addr:full":"531 US Hwy 46 Fairfield NJ 07004",
    "addr:housenumber":"531",
    "addr:postcode":"07004",
    "addr:street":"Us Hwy 46",
    "iso:country":"US",
    "sg:address":"531 US Hwy 46",
    "sg:city":"Fairfield",
    "sg:classifiers":[
        {
            "category":"Building & Trades",
            "subcategory":"Construction",
            "type":"Services"
        }
    ],
    "sg:phone":"+1 973 808 0650",
    "sg:postcode":"07004",
    "sg:province":"NJ",
    "sg:tags":[
        "resurfacing",
        "laying",
        "refinishing",
        "floor"
    ],
    "wof:name":"Pinnacle Flooring LLC",
    "wof:placetype":"venue"
},
  "geometry": {"coordinates":[-74.280051,40.887468],"type":"Point"}
}