{
  "type": "Feature",
  "properties": {
    "iso:country":"US",
    "sg:address":"2019 Greenwood Lake Tpke",
    "sg:city":"Hewitt",
    "sg:classifiers":[
        {
            "category":"Food & Beverages",
            "subcategory":"Liquor & Beverages",
            "type":"Retail Goods"
        }
    ],
    "sg:phone":"+1 973 728 8123",
    "sg:postcode":"07421",
    "sg:province":"NJ",
    "sg:tags":[
        "beer",
        "ale"
    ],
    "wof:name":"Greenwood Lake Discount Lqrs",
    "wof:placetype":"venue"
},
  "geometry": {"coordinates":[-74.35013499999999,41.152809],"type":"Point"}
}