{
  "type": "Feature",
  "properties": {
    "iso:country":"US",
    "sg:address":"99 Murray Hill Pkwy",
    "sg:city":"East Rutherford",
    "sg:classifiers":[
        {
            "category":"Wholesale",
            "subcategory":"Construction Materials",
            "type":"Manufacturing & Wholesale Goods"
        }
    ],
    "sg:phone":"+1 201 939 0663",
    "sg:postcode":"07073",
    "sg:province":"NJ",
    "sg:tags":[
        "glass"
    ],
    "sg:website":"www.oldcastleglass.com",
    "wof:name":"Oldcastle Glass",
    "wof:placetype":"venue"
},
  "geometry": {"coordinates":[-74.084981,40.827412],"type":"Point"}
}