{
  "type": "Feature",
  "properties": {
    "iso:country":"US",
    "sg:address":"51 State Rte 23",
    "sg:city":"Riverdale",
    "sg:classifiers":[
        {
            "category":"Health Services",
            "subcategory":"Doctor",
            "type":"Services"
        }
    ],
    "sg:phone":"+1 973 248 1550",
    "sg:postcode":"07457",
    "sg:province":"NJ",
    "sg:tags":[
        "physician",
        "surgeon",
        "medical"
    ],
    "wof:name":"Bharat Dasani MD",
    "wof:placetype":"venue"
},
  "geometry": {"coordinates":[-74.304979,40.986014],"type":"Point"}
}