{
  "type": "Feature",
  "properties": {
    "addr:full":"700 New Rd Linwood NJ 08221",
    "addr:housenumber":"700",
    "addr:postcode":"08221",
    "addr:street":"New Rd",
    "iso:country":"US",
    "sg:address":"700 New Rd",
    "sg:city":"Linwood",
    "sg:classifiers":[
        {
            "category":"Social Services",
            "type":"Services"
        }
    ],
    "sg:phone":"+1 609 545 0853",
    "sg:postcode":"08221",
    "sg:province":"NJ",
    "sg:tags":[
        "youth",
        "organization",
        "center"
    ],
    "wof:name":"Young Life",
    "wof:placetype":"venue"
},
  "geometry": {"coordinates":[-74.57509,39.353817],"type":"Point"}
}