{
  "type": "Feature",
  "properties": {
    "addr:full":"10 Forest Dr Bloomingdale NJ 07403",
    "addr:housenumber":"10",
    "addr:postcode":"07403",
    "addr:street":"Forest Dr",
    "iso:country":"US",
    "sg:address":"10 Forest Dr",
    "sg:city":"Bloomingdale",
    "sg:classifiers":[
        {
            "category":"Building & Trades",
            "subcategory":"Plumbing",
            "type":"Services"
        }
    ],
    "sg:phone":"+1 973 492 5535",
    "sg:postcode":"07403",
    "sg:province":"NJ",
    "sg:tags":[
        "heating",
        "contractor"
    ],
    "wof:name":"Michael Braden Plumbing and He",
    "wof:placetype":"venue"
},
  "geometry": {"coordinates":[-74.326808,41.011513],"type":"Point"}
}