{
  "type": "Feature",
  "properties": {
    "iso:country":"US",
    "sg:address":"9 Franklin St",
    "sg:city":"Morristown",
    "sg:classifiers":[
        {
            "category":"Health Services",
            "subcategory":"Doctor",
            "type":"Services"
        }
    ],
    "sg:phone":"+1 973 538 2575",
    "sg:postcode":"07960",
    "sg:province":"NJ",
    "wof:name":"Fiore Michael J MD",
    "wof:placetype":"venue"
},
  "geometry": {"coordinates":[-74.47489899999999,40.793201],"type":"Point"}
}