{
  "type": "Feature",
  "properties": {
    "iso:country":"US",
    "sg:address":"240 E Palisade Ave",
    "sg:city":"Englewood",
    "sg:classifiers":[
        {
            "category":"Professional",
            "subcategory":"Business Services",
            "type":"Services"
        }
    ],
    "sg:phone":"+1 201 567 7431",
    "sg:postcode":"07631",
    "sg:province":"NJ",
    "wof:name":"Delandry Assoc Ltd",
    "wof:placetype":"venue"
},
  "geometry": {"coordinates":[-73.96788599999999,40.889916],"type":"Point"}
}