{
  "type": "Feature",
  "properties": {
    "addr:full":"137 Prospect St Newark NJ 07105",
    "addr:housenumber":"137",
    "addr:postcode":"07105",
    "addr:street":"Prospect St",
    "iso:country":"US",
    "sg:address":"137 Prospect St",
    "sg:city":"Newark",
    "sg:classifiers":[
        {
            "category":"Health Services",
            "subcategory":"Doctor",
            "type":"Services"
        }
    ],
    "sg:phone":"+1 973 344 5379",
    "sg:postcode":"07105",
    "sg:province":"NJ",
    "sg:tags":[
        "physician",
        "surgeon",
        "medical"
    ],
    "wof:name":"Mosquera Joseph L MD",
    "wof:placetype":"venue"
},
  "geometry": {"coordinates":[-74.164524,40.729072],"type":"Point"}
}