{
  "type": "Feature",
  "properties": {
    "addr:full":"626 Ezra Boice Rd Absecon NJ 08205",
    "addr:housenumber":"626",
    "addr:postcode":"08205",
    "addr:street":"Ezra Boice Rd",
    "iso:country":"US",
    "sg:address":"626 Ezra Boice Rd",
    "sg:city":"Absecon",
    "sg:classifiers":[
        {
            "category":"Professional",
            "subcategory":"Business Services",
            "type":"Services"
        }
    ],
    "sg:phone":"+1   ",
    "sg:postcode":"08205",
    "sg:province":"NJ",
    "wof:name":"Cml Business Services",
    "wof:placetype":"venue"
},
  "geometry": {"coordinates":[-74.47240499999999,39.453192],"type":"Point"}
}