{
  "type": "Feature",
  "properties": {
    "iso:country":"US",
    "sg:address":"235 Berlin Rd",
    "sg:city":"Cherry Hill",
    "sg:classifiers":[
        {
            "category":"Retail",
            "subcategory":"Car Wash",
            "type":"Services"
        }
    ],
    "sg:phone":"+1 856 428 5777",
    "sg:postcode":"08034",
    "sg:province":"NJ",
    "wof:name":"Autosheen Express",
    "wof:placetype":"venue"
},
  "geometry": {"coordinates":[-75.019088,39.890697],"type":"Point"}
}