{
  "type": "Feature",
  "properties": {
    "addr:full":"190 Regina Ave Rahway NJ 07065",
    "addr:housenumber":"190",
    "addr:postcode":"07065",
    "addr:street":"Regina Ave",
    "iso:country":"US",
    "sg:address":"190 Regina Ave",
    "sg:city":"Rahway",
    "sg:classifiers":[
        {
            "category":"Wholesale",
            "subcategory":"Auto Parts",
            "type":"Manufacturing & Wholesale Goods"
        }
    ],
    "sg:phone":"+1 732 388 1440",
    "sg:postcode":"07065",
    "sg:province":"NJ",
    "sg:tags":[
        "automobile",
        "supply"
    ],
    "wof:name":"A To Z Automotive Company",
    "wof:placetype":"venue"
},
  "geometry": {"coordinates":[-74.282681,40.598796],"type":"Point"}
}