{
  "type": "Feature",
  "properties": {
    "iso:country":"US",
    "sg:address":"58 Berkley Blvd",
    "sg:city":"Iselin",
    "sg:classifiers":[
        {
            "category":"Building & Trades",
            "subcategory":"Landscaping Services",
            "type":"Services"
        }
    ],
    "sg:phone":"+1 732 283 3212",
    "sg:postcode":"08830",
    "sg:province":"NJ",
    "sg:tags":[
        "landscape"
    ],
    "wof:name":"D&D Landscaping & Turf Managem",
    "wof:placetype":"venue"
},
  "geometry": {"coordinates":[-74.31908300000001,40.571089],"type":"Point"}
}