{
  "type": "Feature",
  "properties": {
    "addr:full":"1533 Saint Georges Ave Rahway NJ 07065",
    "addr:housenumber":"1533",
    "addr:postcode":"07065",
    "addr:street":"Saint Georges Ave",
    "iso:country":"US",
    "sg:address":"1533 Saint Georges Ave",
    "sg:city":"Rahway",
    "sg:classifiers":[
        {
            "category":"Professional",
            "subcategory":"Lawyer & Legal Services",
            "type":"Services"
        }
    ],
    "sg:phone":"+1 732 574 2210",
    "sg:postcode":"07065",
    "sg:province":"NJ",
    "wof:name":"Murray Donald W Attorney At Law",
    "wof:placetype":"venue"
},
  "geometry": {"coordinates":[-74.28589599999999,40.615002],"type":"Point"}
}