{
  "type": "Feature",
  "properties": {
    "iso:country":"US",
    "sg:address":"19 Violet Ct",
    "sg:city":"Marlton",
    "sg:classifiers":[
        {
            "category":"Building & Trades",
            "subcategory":"Landscaping Services",
            "type":"Services"
        }
    ],
    "sg:phone":"+1 856 810 3465",
    "sg:postcode":"08053",
    "sg:province":"NJ",
    "sg:tags":[
        "lawn",
        "garden"
    ],
    "wof:name":"Dutch Nursery & Landscape Inc",
    "wof:placetype":"venue"
},
  "geometry": {"coordinates":[-74.879114,39.905182],"type":"Point"}
}