{
  "type": "Feature",
  "properties": {
    "addr:full":"62 Lake Dr Beverly NJ 08010",
    "addr:housenumber":"62",
    "addr:postcode":"08010",
    "addr:street":"Lake Dr",
    "iso:country":"US",
    "sg:address":"62 Lake Dr",
    "sg:city":"Beverly",
    "sg:classifiers":[
        {
            "category":"Travel",
            "subcategory":"Travel Agent",
            "type":"Entertainment"
        }
    ],
    "sg:phone":"+1 856 764 8278",
    "sg:postcode":"08010",
    "sg:province":"NJ",
    "sg:tags":[
        "agency"
    ],
    "wof:name":"Lees International Travel Gro",
    "wof:placetype":"venue"
},
  "geometry": {"coordinates":[-74.92488400000001,40.031343],"type":"Point"}
}