{
  "type": "Feature",
  "properties": {
    "addr:full":"108 Bright St Jersey City NJ 07302",
    "addr:housenumber":"108",
    "addr:postcode":"07302",
    "addr:street":"Bright St",
    "iso:country":"US",
    "sg:address":"108 Bright St",
    "sg:city":"Jersey City",
    "sg:classifiers":[
        {
            "category":"Food & Beverages",
            "subcategory":"Groceries & Convenience Stores",
            "type":"Retail Goods"
        }
    ],
    "sg:phone":"+1   ",
    "sg:postcode":"07302",
    "sg:province":"NJ",
    "sg:tags":[
        "delicatessen"
    ],
    "wof:name":"Vareck Deli",
    "wof:placetype":"venue"
},
  "geometry": {"coordinates":[-74.051559,40.718247],"type":"Point"}
}