{
  "type": "Feature",
  "properties": {
    "addr:full":"280 Powerville Rd Boonton NJ 07005",
    "addr:housenumber":"280",
    "addr:postcode":"07005",
    "addr:street":"Powerville Rd",
    "iso:country":"US",
    "sg:address":"280 Powerville Rd",
    "sg:city":"Boonton",
    "sg:classifiers":[
        {
            "category":"Professional",
            "subcategory":"Business Services",
            "type":"Services"
        }
    ],
    "sg:phone":"+1   ",
    "sg:postcode":"07005",
    "sg:province":"NJ",
    "wof:name":"Girouard James Design Assoc",
    "wof:placetype":"venue"
},
  "geometry": {"coordinates":[-74.427877,40.923272],"type":"Point"}
}