{
  "type": "Feature",
  "properties": {
    "addr:full":"1087 Prospect Ave Mountainside NJ 07092",
    "addr:housenumber":"1087",
    "addr:postcode":"07092",
    "addr:street":"Prospect Ave",
    "iso:country":"US",
    "sg:address":"1087 Prospect Ave",
    "sg:city":"Mountainside",
    "sg:classifiers":[
        {
            "category":"Communications",
            "subcategory":"Newspaper",
            "type":"Services"
        }
    ],
    "sg:phone":"+1 212 627 8050",
    "sg:postcode":"07092",
    "sg:province":"NJ",
    "sg:tags":[
        "print",
        "medium"
    ],
    "wof:name":"Safeway Contracting Inc",
    "wof:placetype":"venue"
},
  "geometry": {"coordinates":[-74.354698,40.691898],"type":"Point"}
}