{
  "type": "Feature",
  "properties": {
    "iso:country":"US",
    "sg:address":"239 Bloomfield Ave",
    "sg:city":"Bloomfield",
    "sg:classifiers":[
        {
            "category":"Banks & Credit Unions",
            "subcategory":"Bank",
            "type":"Services"
        }
    ],
    "sg:phone":"+1   ",
    "sg:postcode":"07003",
    "sg:province":"NJ",
    "sg:tags":[
        "cashing",
        "check"
    ],
    "wof:name":"City Financial",
    "wof:placetype":"venue"
},
  "geometry": {"coordinates":[-74.19176899999999,40.782762],"type":"Point"}
}