{
  "type": "Feature",
  "properties": {
    "iso:country":"US",
    "sg:address":"409 Adams St",
    "sg:city":"Newark",
    "sg:classifiers":[
        {
            "category":"Building & Trades",
            "subcategory":"Construction",
            "type":"Services"
        }
    ],
    "sg:phone":"+1 973 465 5227",
    "sg:postcode":"07114",
    "sg:province":"NJ",
    "sg:tags":[
        "concrete",
        "sidewalk",
        "curb",
        "contractor"
    ],
    "wof:name":"V A Construction Co Inc",
    "wof:placetype":"venue"
},
  "geometry": {"coordinates":[-74.16520199999999,40.717609],"type":"Point"}
}