{
  "type": "Feature",
  "properties": {
    "iso:country":"US",
    "sg:address":"199 Devon Ter",
    "sg:city":"Kearny",
    "sg:classifiers":[
        {
            "category":"Manufacturing",
            "subcategory":"Tools & Machinery",
            "type":"Manufacturing & Wholesale Goods"
        },
        {
            "category":"Building & Trades",
            "subcategory":"Plumbing",
            "type":"Services"
        },
        {
            "category":"Manufacturing",
            "subcategory":"Building Materials",
            "type":"Manufacturing & Wholesale Goods"
        }
    ],
    "sg:phone":"+1 201 997 0250",
    "sg:postcode":"07032",
    "sg:province":"NJ",
    "sg:tags":[
        "jig",
        "tools-electric",
        "solid",
        "die",
        "fixture",
        "surface",
        "maker"
    ],
    "sg:website":"http://www.uniteddie.com",
    "wof:name":"United Die Co Inc",
    "wof:placetype":"venue"
},
  "geometry": {"coordinates":[-74.143495,40.753684],"type":"Point"}
}