{
  "type": "Feature",
  "properties": {
    "iso:country":"US",
    "sg:address":"35 E 48th St",
    "sg:city":"Bayonne",
    "sg:classifiers":[
        {
            "category":"Building & Trades",
            "subcategory":"Construction",
            "type":"Services"
        }
    ],
    "sg:phone":"+1 201 436 8815",
    "sg:postcode":"07002",
    "sg:province":"NJ",
    "sg:tags":[
        "floor",
        "laying",
        "contractor"
    ],
    "wof:name":"Dyna Clean",
    "wof:placetype":"venue"
},
  "geometry": {"coordinates":[-74.10100799999999,40.680534],"type":"Point"}
}