{
  "type": "Feature",
  "properties": {
    "addr:full":"216 Canary Ln Mount Holly NJ 08060",
    "addr:housenumber":"216",
    "addr:postcode":"08060",
    "addr:street":"Canary Ln",
    "iso:country":"US",
    "sg:address":"216 Canary Ln",
    "sg:city":"Mount Holly",
    "sg:classifiers":[
        {
            "category":"Professional",
            "subcategory":"Business Services",
            "type":"Services"
        }
    ],
    "sg:phone":"+1   ",
    "sg:postcode":"08060",
    "sg:province":"NJ",
    "wof:name":"Notary Signing Agency NJ",
    "wof:placetype":"venue"
},
  "geometry": {"coordinates":[-74.794712,40.009815],"type":"Point"}
}