{
  "type": "Feature",
  "properties": {
    "addr:full":"1439 Springdale Rd Cherry Hill NJ 08003",
    "addr:housenumber":"1439",
    "addr:postcode":"08003",
    "addr:street":"Springdale Rd",
    "iso:country":"US",
    "sg:address":"1439 Springdale Rd",
    "sg:city":"Cherry Hill",
    "sg:classifiers":[
        {
            "category":"Organizations",
            "subcategory":"Religious Organization",
            "type":"Services"
        }
    ],
    "sg:phone":"+1 856 424 3212",
    "sg:postcode":"08003",
    "sg:province":"NJ",
    "wof:name":"St Thomas More",
    "wof:placetype":"venue"
},
  "geometry": {"coordinates":[-74.968873,39.886675],"type":"Point"}
}