{
  "type": "Feature",
  "properties": {
    "addr:full":"473 US Hwy 206 Branchville NJ 07826",
    "addr:housenumber":"473",
    "addr:postcode":"07826",
    "addr:street":"Us Hwy 206",
    "iso:country":"US",
    "sg:address":"473 US Hwy 206",
    "sg:city":"Branchville",
    "sg:classifiers":[
        {
            "category":"Professional",
            "subcategory":"Business Services",
            "type":"Services"
        }
    ],
    "sg:phone":"+1   ",
    "sg:postcode":"07826",
    "sg:province":"NJ",
    "wof:name":"Traco Embroidery",
    "wof:placetype":"venue"
},
  "geometry": {"coordinates":[-74.78838399999999,41.163188],"type":"Point"}
}