{
  "type": "Feature",
  "properties": {
    "addr:full":"3010 E Landis Ave Vineland NJ 08361",
    "addr:housenumber":"3010",
    "addr:postcode":"08361",
    "addr:street":"E Landis Ave",
    "iso:country":"US",
    "sg:address":"3010 E Landis Ave",
    "sg:city":"Vineland",
    "sg:classifiers":[
        {
            "category":"Professional",
            "subcategory":"Advertising",
            "type":"Services"
        }
    ],
    "sg:phone":"+1   ",
    "sg:postcode":"08361",
    "sg:province":"NJ",
    "sg:tags":[
        "agency"
    ],
    "wof:name":"Jack Rawlins Freelance",
    "wof:placetype":"venue"
},
  "geometry": {"coordinates":[-74.967726,39.483496],"type":"Point"}
}