{
  "type": "Feature",
  "properties": {
    "iso:country":"US",
    "sg:address":"32 Old Cranbury Rd",
    "sg:city":"Cranbury",
    "sg:classifiers":[
        {
            "category":"Shopping",
            "subcategory":"Gifts & Souvenirs",
            "type":"Retail Goods"
        }
    ],
    "sg:phone":"+1   ",
    "sg:postcode":"08512",
    "sg:province":"NJ",
    "wof:name":"Amys Hallmark",
    "wof:placetype":"venue"
},
  "geometry": {"coordinates":[-74.526651,40.293404],"type":"Point"}
}