{
  "type": "Feature",
  "properties": {
    "addr:full":"343 S Jefferson St Orange NJ 07050",
    "addr:housenumber":"343",
    "addr:postcode":"07050",
    "addr:street":"S Jefferson St",
    "iso:country":"US",
    "sg:address":"343 S Jefferson St",
    "sg:city":"Orange",
    "sg:classifiers":[
        {
            "category":"Taxi",
            "type":"Transportation"
        }
    ],
    "sg:phone":"+1 973 672 5252",
    "sg:postcode":"07050",
    "sg:province":"NJ",
    "sg:tags":[
        "taxicab"
    ],
    "wof:name":"West Orange & Orange Transport",
    "wof:placetype":"venue"
},
  "geometry": {"coordinates":[-74.243709,40.768272],"type":"Point"}
}