{
  "type": "Feature",
  "properties": {
    "addr:full":"684 Passaic Ave Nutley NJ 07110",
    "addr:housenumber":"684",
    "addr:postcode":"07110",
    "addr:street":"Passaic Ave",
    "iso:country":"US",
    "sg:address":"684 Passaic Ave",
    "sg:city":"Nutley",
    "sg:classifiers":[
        {
            "category":"Personal",
            "subcategory":"Day Spa",
            "type":"Services"
        }
    ],
    "sg:phone":"+1 973 661 0303",
    "sg:postcode":"07110",
    "sg:province":"NJ",
    "sg:website":"www.sunflowerdayspa.com",
    "wof:name":"Sunflower Day Spa",
    "wof:placetype":"venue"
},
  "geometry": {"coordinates":[-74.14522100000001,40.827874],"type":"Point"}
}