{
  "type": "Feature",
  "properties": {
    "addr:full":"274 Woodbridge Ctr Woodbridge NJ 07095",
    "addr:housenumber":"274",
    "addr:postcode":"07095",
    "addr:street":"Woodbridge Ctr",
    "iso:country":"US",
    "sg:address":"274 Woodbridge Ctr",
    "sg:city":"Woodbridge",
    "sg:classifiers":[
        {
            "category":"Shopping",
            "subcategory":"Clothing, Apparel, & Fashions",
            "type":"Retail Goods"
        }
    ],
    "sg:phone":"+1 732 636 5900",
    "sg:postcode":"07095",
    "sg:province":"NJ",
    "sg:tags":[
        "accessory"
    ],
    "sg:website":"www.lanebryant.com",
    "wof:name":"Lane Bryant Inc",
    "wof:placetype":"venue"
},
  "geometry": {"coordinates":[-74.298103,40.550701],"type":"Point"}
}