{
  "type": "Feature",
  "properties": {
    "addr:full":"440 S Main St Forked River NJ 08731",
    "addr:housenumber":"440",
    "addr:postcode":"08731",
    "addr:street":"S Main St",
    "iso:country":"US",
    "sg:address":"440 S Main St",
    "sg:city":"Forked River",
    "sg:classifiers":[
        {
            "category":"Restaurant",
            "type":"Food & Drink"
        }
    ],
    "sg:phone":"+1   ",
    "sg:postcode":"08731",
    "sg:province":"NJ",
    "sg:tags":[
        "eating"
    ],
    "wof:name":"Cafferys Restaurant",
    "wof:placetype":"venue"
},
  "geometry": {"coordinates":[-74.19727899999999,39.832658],"type":"Point"}
}