{
  "type": "Feature",
  "properties": {
    "addr:full":"358 1/2 S 19th St Newark NJ 07103",
    "addr:housenumber":"358 1 / 2",
    "addr:postcode":"07103",
    "addr:street":"S 19Th St",
    "iso:country":"US",
    "sg:address":"358 1/2 S 19th St",
    "sg:city":"Newark",
    "sg:classifiers":[
        {
            "category":"Organizations",
            "subcategory":"Religious Organization",
            "type":"Services"
        }
    ],
    "sg:phone":"+1 973 399 8414",
    "sg:postcode":"07103",
    "sg:province":"NJ",
    "wof:name":"Simmons Clifford Rev",
    "wof:placetype":"venue"
},
  "geometry": {"coordinates":[-74.207266,40.744691],"type":"Point"}
}