{
  "type": "Feature",
  "properties": {
    "addr:full":"25 Farmersville Rd Califon NJ 07830",
    "addr:housenumber":"25",
    "addr:postcode":"07830",
    "addr:street":"Farmersville Rd",
    "iso:country":"US",
    "sg:address":"25 Farmersville Rd",
    "sg:city":"Califon",
    "sg:classifiers":[
        {
            "category":"Professional",
            "type":"Services"
        }
    ],
    "sg:phone":"+1   ",
    "sg:postcode":"07830",
    "sg:province":"NJ",
    "wof:name":"Fe A Pung",
    "wof:placetype":"venue"
},
  "geometry": {"coordinates":[-74.810964,40.720411],"type":"Point"}
}