{
  "type": "Feature",
  "properties": {
    "iso:country":"US",
    "sg:address":"5 Pinecrest Ct",
    "sg:city":"Woodbury",
    "sg:classifiers":[
        {
            "category":"Banks & Credit Unions",
            "subcategory":"Financial Services",
            "type":"Services"
        }
    ],
    "sg:phone":"+1   ",
    "sg:postcode":"08096",
    "sg:province":"NJ",
    "sg:tags":[
        "investor"
    ],
    "wof:name":"Elite Enterprising Lads",
    "wof:placetype":"venue"
},
  "geometry": {"coordinates":[-75.13097,39.838131],"type":"Point"}
}