{
  "type": "Feature",
  "properties": {
    "iso:country":"US",
    "sg:address":"1262 S Broad St",
    "sg:city":"Trenton",
    "sg:classifiers":[
        {
            "category":"Utilities",
            "subcategory":"Mobile Phone",
            "type":"Services"
        }
    ],
    "sg:phone":"+1 609 278 5775",
    "sg:postcode":"08610",
    "sg:province":"NJ",
    "sg:tags":[
        "telephone",
        "cellular"
    ],
    "wof:name":"Unique Wireless & Electric Inc",
    "wof:placetype":"venue"
},
  "geometry": {"coordinates":[-74.740137,40.202931],"type":"Point"}
}