{
  "type": "Feature",
  "properties": {
    "addr:full":"112 Central Ave Jersey City NJ 07306",
    "addr:housenumber":"112",
    "addr:postcode":"07306",
    "addr:street":"Central Ave",
    "iso:country":"US",
    "sg:address":"112 Central Ave",
    "sg:city":"Jersey City",
    "sg:classifiers":[
        {
            "category":"Retail",
            "subcategory":"Auto Repair",
            "type":"Services"
        }
    ],
    "sg:phone":"+1 201 656 9191",
    "sg:postcode":"07306",
    "sg:province":"NJ",
    "sg:tags":[
        "body",
        "shop"
    ],
    "sg:website":"www.gioiaautorepair.com",
    "wof:name":"Gioia Auto Repair",
    "wof:placetype":"venue"
},
  "geometry": {"coordinates":[-74.054298,40.738499],"type":"Point"}
}