{
  "type": "Feature",
  "properties": {
    "addr:full":"1790 State Rte 70 Cherry Hill NJ 08003",
    "addr:housenumber":"1790",
    "addr:postcode":"08003",
    "addr:street":"State Rte 70",
    "iso:country":"US",
    "sg:address":"1790 State Rte 70",
    "sg:city":"Cherry Hill",
    "sg:classifiers":[
        {
            "category":"Shopping",
            "type":"Retail Goods"
        }
    ],
    "sg:phone":"+1 856 761 1000",
    "sg:postcode":"08003",
    "sg:province":"NJ",
    "sg:tags":[
        "communications",
        "merchandise",
        "telephone",
        "business"
    ],
    "wof:name":"The Phoneowners Group",
    "wof:placetype":"venue"
},
  "geometry": {"coordinates":[-74.9729,39.905214],"type":"Point"}
}