{
  "type": "Feature",
  "properties": {
    "addr:full":"1909 Village Dr Avenel NJ 07001",
    "addr:housenumber":"1909",
    "addr:postcode":"07001",
    "addr:street":"Village Dr",
    "iso:country":"US",
    "sg:address":"1909 Village Dr",
    "sg:city":"Avenel",
    "sg:classifiers":[
        {
            "category":"Food & Beverages",
            "subcategory":"Groceries & Convenience Stores",
            "type":"Retail Goods"
        }
    ],
    "sg:phone":"+1   ",
    "sg:postcode":"07001",
    "sg:province":"NJ",
    "wof:name":"Hariom Food Mart Inc",
    "wof:placetype":"venue"
},
  "geometry": {"coordinates":[-74.28406699999999,40.592172],"type":"Point"}
}