{
  "type": "Feature",
  "properties": {
    "addr:full":"798 Springfield Ave Irvington NJ 07111",
    "addr:housenumber":"798",
    "addr:postcode":"07111",
    "addr:street":"Springfield Ave",
    "iso:country":"US",
    "sg:address":"798 Springfield Ave",
    "sg:city":"Irvington",
    "sg:classifiers":[
        {
            "category":"Professional",
            "subcategory":"Business Services",
            "type":"Services"
        },
        {
            "category":"Retail",
            "subcategory":"Auto Rental",
            "type":"Services"
        }
    ],
    "sg:phone":"+1 973 416 1590",
    "sg:postcode":"07111",
    "sg:province":"NJ",
    "sg:tags":[
        "renting",
        "automobile"
    ],
    "sg:website":"www.enterprise.com",
    "wof:name":"Enterprise Rent A Car",
    "wof:placetype":"venue"
},
  "geometry": {"coordinates":[-74.220347,40.728392],"type":"Point"}
}