{
  "type": "Feature",
  "properties": {
    "iso:country":"US",
    "sg:address":"405 State Rte 35",
    "sg:city":"Neptune",
    "sg:classifiers":[
        {
            "category":"Shopping",
            "subcategory":"Clothing, Apparel, & Fashions",
            "type":"Retail Goods"
        }
    ],
    "sg:phone":"+1   ",
    "sg:postcode":"07753",
    "sg:province":"NJ",
    "sg:tags":[
        "family"
    ],
    "wof:name":"4 Play Fashions Inc",
    "wof:placetype":"venue"
},
  "geometry": {"coordinates":[-74.03183900000001,40.218038],"type":"Point"}
}