{
  "type": "Feature",
  "properties": {
    "addr:full":"323 W Washington Ave Washington NJ 07882",
    "addr:housenumber":"323",
    "addr:postcode":"07882",
    "addr:street":"W Washington Ave",
    "iso:country":"US",
    "sg:address":"323 W Washington Ave",
    "sg:city":"Washington",
    "sg:classifiers":[
        {
            "category":"Retail",
            "subcategory":"Repair Shop",
            "type":"Services"
        },
        {
            "category":"Building & Trades",
            "subcategory":"Construction",
            "type":"Services"
        }
    ],
    "sg:phone":"+1 484 894 2344",
    "sg:postcode":"07882",
    "sg:province":"NJ",
    "sg:tags":[
        "major",
        "refinishing",
        "appliance",
        "system",
        "air conditioning",
        "small",
        "contractor",
        "freezers-repair",
        "refrigerator"
    ],
    "wof:name":"MAS Michaels Appliance Service",
    "wof:placetype":"venue"
},
  "geometry": {"coordinates":[-74.996196,40.754484],"type":"Point"}
}