{
  "type": "Feature",
  "properties": {
    "addr:full":"681 Lawlins Rd Ste 160 Wyckoff NJ 07481",
    "addr:housenumber":"681",
    "addr:postcode":"07481",
    "addr:street":"Lawlins Rd Ste 160",
    "iso:country":"US",
    "sg:address":"681 Lawlins Rd Ste 160",
    "sg:city":"Wyckoff",
    "sg:classifiers":[
        {
            "category":"Professional",
            "type":"Services"
        },
        {
            "category":"Shopping",
            "subcategory":"Party Supplies",
            "type":"Retail Goods"
        },
        {
            "category":"Building & Trades",
            "subcategory":"Equipment Rental",
            "type":"Services"
        },
        {
            "category":"Shopping",
            "subcategory":"Bicycles & Sporting Goods",
            "type":"Retail Goods"
        },
        {
            "category":"Home & Garden",
            "subcategory":"Furniture",
            "type":"Retail Goods"
        }
    ],
    "sg:phone":"+1 201 847 1700",
    "sg:postcode":"07481",
    "sg:province":"NJ",
    "sg:tags":[
        "renting",
        "leasing",
        "favors",
        "decoration",
        "caterer",
        "chair",
        "tent"
    ],
    "sg:website":"http://www.dancopartyrentals.com",
    "wof:name":"Danco Rentals & Services",
    "wof:placetype":"venue"
},
  "geometry": {"coordinates":[-74.18575199999999,41.015301],"type":"Point"}
}