{
  "type": "Feature",
  "properties": {
    "iso:country":"US",
    "sg:address":"561 Ocean Ave",
    "sg:city":"Jersey City",
    "sg:classifiers":[
        {
            "category":"Restaurant",
            "type":"Food & Drink"
        }
    ],
    "sg:phone":"+1   ",
    "sg:postcode":"07305",
    "sg:province":"NJ",
    "sg:tags":[
        "eating"
    ],
    "wof:name":"Victory Pizzeria & Clam Bar",
    "wof:placetype":"venue"
},
  "geometry": {"coordinates":[-74.078817,40.705367],"type":"Point"}
}