{
  "type": "Feature",
  "properties": {
    "iso:country":"US",
    "sg:address":"486 W Shore Dr",
    "sg:city":"Brigantine",
    "sg:classifiers":[
        {
            "category":"Autos & Motor Vehicles",
            "subcategory":"Boat Sales",
            "type":"Retail Goods"
        }
    ],
    "sg:phone":"+1 609 266 7764",
    "sg:postcode":"08203",
    "sg:province":"NJ",
    "sg:tags":[
        "marina",
        "sales",
        "dealer"
    ],
    "wof:name":"Bobs Outboard Marine Inc",
    "wof:placetype":"venue"
},
  "geometry": {"coordinates":[-74.372579,39.409587],"type":"Point"}
}