{
  "type": "Feature",
  "properties": {
    "iso:country":"US",
    "sg:address":"8 Dogwood Dr",
    "sg:city":"Chester",
    "sg:classifiers":[
        {
            "category":"Social Services",
            "subcategory":"Child Care",
            "type":"Services"
        }
    ],
    "sg:phone":"+1   ",
    "sg:postcode":"07930",
    "sg:province":"NJ",
    "sg:tags":[
        "day"
    ],
    "wof:name":"Dogwood School",
    "wof:placetype":"venue"
},
  "geometry": {"coordinates":[-74.63704199999999,40.806813],"type":"Point"}
}