{
  "type": "Feature",
  "properties": {
    "iso:country":"US",
    "sg:address":"31 Dehart St",
    "sg:city":"Morristown",
    "sg:classifiers":[
        {
            "category":"Retail",
            "subcategory":"Auto Rental",
            "type":"Services"
        }
    ],
    "sg:phone":"+1 973 644 2627",
    "sg:postcode":"07960",
    "sg:province":"NJ",
    "sg:tags":[
        "car"
    ],
    "wof:name":"Corporate Fleet Leasing Inc",
    "wof:placetype":"venue"
},
  "geometry": {"coordinates":[-74.48187900000001,40.7947],"type":"Point"}
}