{
  "type": "Feature",
  "properties": {
    "iso:country":"US",
    "sg:address":"272 Hobart St",
    "sg:city":"Perth Amboy",
    "sg:classifiers":[
        {
            "category":"Health Services",
            "subcategory":"Clinic",
            "type":"Services"
        }
    ],
    "sg:phone":"+1 732 376 9333",
    "sg:postcode":"08861",
    "sg:province":"NJ",
    "sg:tags":[
        "organization",
        "medical",
        "surgical"
    ],
    "wof:name":"Jewish Renaissance Medical Ctr",
    "wof:placetype":"venue"
},
  "geometry": {"coordinates":[-74.269392,40.508244],"type":"Point"}
}