{
  "type": "Feature",
  "properties": {
    "iso:country":"US",
    "sg:address":"6 Witmer Way",
    "sg:city":"Trenton",
    "sg:classifiers":[
        {
            "category":"Home & Garden",
            "subcategory":"Hardware",
            "type":"Retail Goods"
        }
    ],
    "sg:phone":"+1   ",
    "sg:postcode":"08691",
    "sg:province":"NJ",
    "wof:name":"Value Pharma",
    "wof:placetype":"venue"
},
  "geometry": {"coordinates":[-74.60265,40.238679],"type":"Point"}
}