{
  "type": "Feature",
  "properties": {
    "iso:country":"US",
    "sg:address":"1135 Broad St",
    "sg:city":"Clifton",
    "sg:classifiers":[
        {
            "category":"Health Services",
            "subcategory":"Chiropractor",
            "type":"Services"
        }
    ],
    "sg:phone":"+1 973 471 2890",
    "sg:postcode":"07013",
    "sg:province":"NJ",
    "wof:name":"Anson Family Chiropractic Center",
    "wof:placetype":"venue"
},
  "geometry": {"coordinates":[-74.17600299999999,40.858101],"type":"Point"}
}