{
  "type": "Feature",
  "properties": {
    "iso:country":"US",
    "sg:address":"20 Banta Pl",
    "sg:city":"Hackensack",
    "sg:classifiers":[
        {
            "category":"Government",
            "subcategory":"Office",
            "type":"Public Place"
        }
    ],
    "sg:phone":"+1   ",
    "sg:postcode":"07601",
    "sg:province":"NJ",
    "sg:tags":[
        "recruiting"
    ],
    "wof:name":"Navy Recruiting",
    "wof:placetype":"venue"
},
  "geometry": {"coordinates":[-74.043389,40.885246],"type":"Point"}
}