{
  "type": "Feature",
  "properties": {
    "iso:country":"US",
    "sg:address":"400 Broad St",
    "sg:city":"Bloomfield",
    "sg:classifiers":[
        {
            "category":"Professional",
            "subcategory":"Business Services",
            "type":"Services"
        }
    ],
    "sg:phone":"+1 973 680 8193",
    "sg:postcode":"07003",
    "sg:province":"NJ",
    "sg:tags":[
        "messenger"
    ],
    "wof:name":"Citi-Beeper",
    "wof:placetype":"venue"
},
  "geometry": {"coordinates":[-74.192888,40.80643],"type":"Point"}
}