{
  "type": "Feature",
  "properties": {
    "iso:country":"US",
    "sg:address":"175 Sussex Ave",
    "sg:city":"Newark",
    "sg:classifiers":[
        {
            "category":"Retail",
            "subcategory":"Auto Repair",
            "type":"Services"
        }
    ],
    "sg:phone":"+1 973 482 6648",
    "sg:postcode":"07103",
    "sg:province":"NJ",
    "sg:tags":[
        "wrecker"
    ],
    "wof:name":"Raul's Towing Svc",
    "wof:placetype":"venue"
},
  "geometry": {"coordinates":[-74.18370899999999,40.747971],"type":"Point"}
}