{
  "type": "Feature",
  "properties": {
    "addr:full":"202 Downer Ave Mantoloking NJ 08738",
    "addr:housenumber":"202",
    "addr:postcode":"08738",
    "addr:street":"Downer Ave",
    "iso:country":"US",
    "sg:address":"202 Downer Ave",
    "sg:city":"Mantoloking",
    "sg:classifiers":[
        {
            "category":"Government",
            "subcategory":"Office",
            "type":"Public Place"
        }
    ],
    "sg:phone":"+1 732 899 6600",
    "sg:postcode":"08738",
    "sg:province":"NJ",
    "sg:tags":[
        "city",
        "taxation"
    ],
    "wof:name":"Mantoloking Tax Collector",
    "wof:placetype":"venue"
},
  "geometry": {"coordinates":[-74.052385,40.037118],"type":"Point"}
}