{
  "type": "Feature",
  "properties": {
    "iso:country":"US",
    "sg:address":"25 Lincoln Rd",
    "sg:city":"Elmer",
    "sg:classifiers":[
        {
            "category":"Professional",
            "subcategory":"Business Services",
            "type":"Services"
        }
    ],
    "sg:phone":"+1   ",
    "sg:postcode":"08318",
    "sg:province":"NJ",
    "wof:name":"Quality Testing Svcs",
    "wof:placetype":"venue"
},
  "geometry": {"coordinates":[-75.13637799999999,39.591291],"type":"Point"}
}