{
  "type": "Feature",
  "properties": {
    "addr:full":"24 Fairview Ave Little Silver NJ 07739",
    "addr:housenumber":"24",
    "addr:postcode":"07739",
    "addr:street":"Fairview Ave",
    "iso:country":"US",
    "sg:address":"24 Fairview Ave",
    "sg:city":"Little Silver",
    "sg:classifiers":[
        {
            "category":"Retail",
            "subcategory":"Auto Repair",
            "type":"Services"
        }
    ],
    "sg:phone":"+1 732 741 7979",
    "sg:postcode":"07739",
    "sg:province":"NJ",
    "sg:tags":[
        "body",
        "automobile",
        "painting"
    ],
    "wof:name":"Epic Collision",
    "wof:placetype":"venue"
},
  "geometry": {"coordinates":[-74.03743299999999,40.324688],"type":"Point"}
}