{
  "type": "Feature",
  "properties": {
    "iso:country":"US",
    "sg:address":"177 Millburn Ave",
    "sg:city":"Millburn",
    "sg:classifiers":[
        {
            "category":"Personal",
            "subcategory":"Beauty Salon",
            "type":"Services"
        }
    ],
    "sg:phone":"+1 973 379 8300",
    "sg:postcode":"07041",
    "sg:province":"NJ",
    "sg:tags":[
        "boutique"
    ],
    "wof:name":"Salon Profilo Inc",
    "wof:placetype":"venue"
},
  "geometry": {"coordinates":[-74.29456500000001,40.722162],"type":"Point"}
}