{
  "type": "Feature",
  "properties": {
    "addr:full":"18 W Maple Ave Merchantville NJ 08109",
    "addr:housenumber":"18",
    "addr:postcode":"08109",
    "addr:street":"W Maple Ave",
    "iso:country":"US",
    "sg:address":"18 W Maple Ave",
    "sg:city":"Merchantville",
    "sg:classifiers":[
        {
            "category":"Shopping",
            "subcategory":"Pharmacy",
            "type":"Retail Goods"
        }
    ],
    "sg:phone":"+1 856 375 8094",
    "sg:postcode":"08109",
    "sg:province":"NJ",
    "sg:tags":[
        "drugstore"
    ],
    "wof:name":"CVS/pharmacy",
    "wof:placetype":"venue"
},
  "geometry": {"coordinates":[-75.049851,39.949909],"type":"Point"}
}