{
  "type": "Feature",
  "properties": {
    "addr:full":"180 Tamarack Cir Skillman NJ 08558",
    "addr:housenumber":"180",
    "addr:postcode":"08558",
    "addr:street":"Tamarack Cir",
    "iso:country":"US",
    "sg:address":"180 Tamarack Cir",
    "sg:city":"Skillman",
    "sg:classifiers":[
        {
            "category":"Manufacturing",
            "subcategory":"Furniture",
            "type":"Manufacturing & Wholesale Goods"
        }
    ],
    "sg:phone":"+1 609 430 2114",
    "sg:postcode":"08558",
    "sg:province":"NJ",
    "sg:tags":[
        "marketing",
        "develop",
        "platform"
    ],
    "wof:name":"Lifestream Network LLC",
    "wof:placetype":"venue"
},
  "geometry": {"coordinates":[-74.64902499999999,40.408531],"type":"Point"}
}