{
  "type": "Feature",
  "properties": {
    "addr:full":"436 Morris Ave Springfield NJ 07081",
    "addr:housenumber":"436",
    "addr:postcode":"07081",
    "addr:street":"Morris Ave",
    "iso:country":"US",
    "sg:address":"436 Morris Ave",
    "sg:city":"Springfield",
    "sg:classifiers":[
        {
            "category":"Personal",
            "subcategory":"Beauty Salon",
            "type":"Services"
        }
    ],
    "sg:phone":"+1 973 376 6153",
    "sg:postcode":"07081",
    "sg:province":"NJ",
    "sg:tags":[
        "shop"
    ],
    "wof:name":"Marion's Beauty Salon",
    "wof:placetype":"venue"
},
  "geometry": {"coordinates":[-74.31885,40.714507],"type":"Point"}
}