{
  "type": "Feature",
  "properties": {
    "iso:country":"US",
    "sg:address":"175 Essex Ave",
    "sg:city":"Metuchen",
    "sg:classifiers":[
        {
            "category":"Retail",
            "subcategory":"Car Wash",
            "type":"Services"
        }
    ],
    "sg:phone":"+1 732 906 5475",
    "sg:postcode":"08840",
    "sg:province":"NJ",
    "sg:tags":[
        "polishing",
        "washing"
    ],
    "wof:name":"Premier Car Care Ctr",
    "wof:placetype":"venue"
},
  "geometry": {"coordinates":[-74.372046,40.536627],"type":"Point"}
}