{
  "type": "Feature",
  "properties": {
    "iso:country":"US",
    "sg:address":"4 Rockport Rd",
    "sg:city":"Sussex",
    "sg:classifiers":[
        {
            "category":"Building & Trades",
            "subcategory":"Construction",
            "type":"Services"
        }
    ],
    "sg:phone":"+1 973 702 8123",
    "sg:postcode":"07461",
    "sg:province":"NJ",
    "sg:tags":[
        "nonresidential"
    ],
    "wof:name":"Crown Builders Inc",
    "wof:placetype":"venue"
},
  "geometry": {"coordinates":[-74.596791,41.308481],"type":"Point"}
}