{
  "type": "Feature",
  "properties": {
    "addr:full":"1 E State St Trenton NJ 08608",
    "addr:housenumber":"1",
    "addr:postcode":"08608",
    "addr:street":"E State St",
    "iso:country":"US",
    "sg:address":"1 E State St",
    "sg:city":"Trenton",
    "sg:classifiers":[
        {
            "category":"Professional",
            "subcategory":"Accounting & Tax Preparation",
            "type":"Services"
        }
    ],
    "sg:phone":"+1 609 396 6509",
    "sg:postcode":"08608",
    "sg:province":"NJ",
    "sg:tags":[
        "return"
    ],
    "wof:name":"H & R Block",
    "wof:placetype":"venue"
},
  "geometry": {"coordinates":[-74.76420899999999,40.22015],"type":"Point"}
}