{
  "type": "Feature",
  "properties": {
    "iso:country":"US",
    "sg:address":"154 Pine St",
    "sg:city":"Jersey City",
    "sg:classifiers":[
        {
            "category":"Taxi",
            "type":"Transportation"
        }
    ],
    "sg:phone":"+1 201 222 6633",
    "sg:postcode":"07304",
    "sg:province":"NJ",
    "sg:tags":[
        "taxicab"
    ],
    "wof:name":"Action Cab Inc",
    "wof:placetype":"venue"
},
  "geometry": {"coordinates":[-74.063034,40.709055],"type":"Point"}
}