{
  "type": "Feature",
  "properties": {
    "addr:full":"526 Bloomfield Ave Caldwell NJ 07006",
    "addr:housenumber":"526",
    "addr:postcode":"07006",
    "addr:street":"Bloomfield Ave",
    "iso:country":"US",
    "sg:address":"526 Bloomfield Ave",
    "sg:city":"Caldwell",
    "sg:classifiers":[
        {
            "category":"Health Services",
            "subcategory":"Doctor",
            "type":"Services"
        }
    ],
    "sg:phone":"+1 973 736 7616",
    "sg:postcode":"07006",
    "sg:province":"NJ",
    "sg:tags":[
        "dentist"
    ],
    "wof:name":"Metropolitan Craniofacial",
    "wof:placetype":"venue"
},
  "geometry": {"coordinates":[-74.283872,40.845075],"type":"Point"}
}