{
  "type": "Feature",
  "properties": {
    "addr:full":"28 Concordia Shopping Ctr Dr Monroe Township NJ 08831",
    "addr:housenumber":"28",
    "addr:postcode":"08831",
    "addr:street":"Concordia Shopping Ctr Dr",
    "iso:country":"US",
    "sg:address":"28 Concordia Shopping Ctr Dr",
    "sg:city":"Monroe Township",
    "sg:classifiers":[
        {
            "category":"Banks & Credit Unions",
            "subcategory":"Bank",
            "type":"Services"
        }
    ],
    "sg:phone":"+1   ",
    "sg:postcode":"08831",
    "sg:province":"NJ",
    "sg:tags":[
        "national",
        "commercial"
    ],
    "wof:name":"New Jersey Nat Bankcore State",
    "wof:placetype":"venue"
},
  "geometry": {"coordinates":[-74.43903299999999,40.31649],"type":"Point"}
}