{
  "type": "Feature",
  "properties": {
    "iso:country":"US",
    "sg:address":"22 Prospect St",
    "sg:city":"Madison",
    "sg:classifiers":[
        {
            "category":"Retail",
            "subcategory":"Animal Services",
            "type":"Services"
        }
    ],
    "sg:phone":"+1 973 377 0116",
    "sg:postcode":"07940",
    "sg:province":"NJ",
    "sg:tags":[
        "pet",
        "training",
        "store"
    ],
    "sg:website":"www.sthuberts.org",
    "wof:name":"St Hubert's Dog Training School",
    "wof:placetype":"venue"
},
  "geometry": {"coordinates":[-74.414101,40.756199],"type":"Point"}
}