{
  "type": "Feature",
  "properties": {
    "addr:full":"537 Windsor Rd Bergenfield NJ 07621",
    "addr:housenumber":"537",
    "addr:postcode":"07621",
    "addr:street":"Windsor Rd",
    "iso:country":"US",
    "sg:address":"537 Windsor Rd",
    "sg:city":"Bergenfield",
    "sg:classifiers":[
        {
            "category":"Organizations",
            "subcategory":"Professional Association",
            "type":"Services"
        }
    ],
    "sg:phone":"+1 201 385 1269",
    "sg:postcode":"07621",
    "sg:province":"NJ",
    "wof:name":"Masonic Lodge",
    "wof:placetype":"venue"
},
  "geometry": {"coordinates":[-74.002678,40.911629],"type":"Point"}
}