{
  "type": "Feature",
  "properties": {
    "addr:full":"338 Main St South Amboy NJ 08879",
    "addr:housenumber":"338",
    "addr:postcode":"08879",
    "addr:street":"Main St",
    "iso:country":"US",
    "sg:address":"338 Main St",
    "sg:city":"South Amboy",
    "sg:classifiers":[
        {
            "category":"Retail",
            "subcategory":"Funeral Services",
            "type":"Services"
        }
    ],
    "sg:phone":"+1 732 721 0475",
    "sg:postcode":"08879",
    "sg:province":"NJ",
    "sg:tags":[
        "director"
    ],
    "wof:name":"Kurzawa Funeral Home Inc",
    "wof:placetype":"venue"
},
  "geometry": {"coordinates":[-74.287751,40.481655],"type":"Point"}
}