{
  "type": "Feature",
  "properties": {
    "iso:country":"US",
    "sg:address":"376 Hollywood Ave",
    "sg:city":"Fairfield",
    "sg:classifiers":[
        {
            "category":"Restaurant",
            "type":"Food & Drink"
        }
    ],
    "sg:menulink":"http://www.allmenus.com/nj/fairfield/15073-hollywood-pizzeria/menu/",
    "sg:phone":"+1 973 808 0123",
    "sg:postcode":"07004",
    "sg:province":"NJ",
    "sg:tags":[
        "italian"
    ],
    "wof:name":"Hollywood Pizzeria",
    "wof:placetype":"venue"
},
  "geometry": {"coordinates":[-74.29254299999999,40.883628],"type":"Point"}
}