{
  "type": "Feature",
  "properties": {
    "iso:country":"US",
    "sg:address":"25 Washington St",
    "sg:city":"Morristown",
    "sg:classifiers":[
        {
            "category":"Professional",
            "subcategory":"Management & Consulting",
            "type":"Services"
        }
    ],
    "sg:phone":"+1   ",
    "sg:postcode":"07960",
    "sg:province":"NJ",
    "sg:tags":[
        "retail",
        "direct",
        "sales"
    ],
    "wof:name":"Deanna Torrieri & Assoc Inc",
    "wof:placetype":"venue"
},
  "geometry": {"coordinates":[-74.48199099999999,40.796932],"type":"Point"}
}