{
  "type": "Feature",
  "properties": {
    "iso:country":"US",
    "sg:address":"201 W Passaic St",
    "sg:city":"Rochelle Park",
    "sg:classifiers":[
        {
            "category":"Professional",
            "subcategory":"Research",
            "type":"Services"
        }
    ],
    "sg:phone":"+1 201 226 0240",
    "sg:postcode":"07662",
    "sg:province":"NJ",
    "sg:tags":[
        "laboratory"
    ],
    "wof:name":"Unichem Laboratories",
    "wof:placetype":"venue"
},
  "geometry": {"coordinates":[-74.082438,40.914961],"type":"Point"}
}