{
  "type": "Feature",
  "properties": {
    "addr:full":"263 Changebridge Rd Montville NJ 07045",
    "addr:housenumber":"263",
    "addr:postcode":"07045",
    "addr:street":"Changebridge Rd",
    "iso:country":"US",
    "sg:address":"263 Changebridge Rd",
    "sg:city":"Montville",
    "sg:classifiers":[
        {
            "category":"Food & Beverages",
            "subcategory":"Meat & Fish",
            "type":"Retail Goods"
        }
    ],
    "sg:phone":"+1 973 575 8557",
    "sg:postcode":"07045",
    "sg:province":"NJ",
    "sg:tags":[
        "shop"
    ],
    "wof:name":"Montville Meats & Deli",
    "wof:placetype":"venue"
},
  "geometry": {"coordinates":[-74.360298,40.8727],"type":"Point"}
}