{
  "type": "Feature",
  "properties": {
    "addr:full":"107 US Hwy 22 North Plainfield NJ 07060",
    "addr:housenumber":"107",
    "addr:postcode":"07060",
    "addr:street":"Us Hwy 22",
    "iso:country":"US",
    "sg:address":"107 US Hwy 22",
    "sg:city":"North Plainfield",
    "sg:classifiers":[
        {
            "category":"Shopping",
            "subcategory":"Department Store",
            "type":"Retail Goods"
        }
    ],
    "sg:phone":"+1 908 490 1107",
    "sg:postcode":"07060",
    "sg:province":"NJ",
    "sg:website":"www.kohls.com",
    "wof:name":"Kohl's Department Store",
    "wof:placetype":"venue"
},
  "geometry": {"coordinates":[-74.417841,40.64014],"type":"Point"}
}