{
  "type": "Feature",
  "properties": {
    "addr:full":"228 Lackawanna Ave Little Falls NJ 07424",
    "addr:housenumber":"228",
    "addr:postcode":"07424",
    "addr:street":"Lackawanna Ave",
    "iso:country":"US",
    "sg:address":"228 Lackawanna Ave",
    "sg:city":"Little Falls",
    "sg:classifiers":[
        {
            "category":"Arena",
            "subcategory":"Sports Club",
            "type":"Entertainment"
        }
    ],
    "sg:phone":"+1 973 237 0999",
    "sg:postcode":"07424",
    "sg:province":"NJ",
    "wof:name":"Duva Boxing",
    "wof:placetype":"venue"
},
  "geometry": {"coordinates":[-74.20969700000001,40.888546],"type":"Point"}
}