{
  "type": "Feature",
  "properties": {
    "addr:full":"1953 Westfield Ave Scotch Plains NJ 07076",
    "addr:housenumber":"1953",
    "addr:postcode":"07076",
    "addr:street":"Westfield Ave",
    "iso:country":"US",
    "sg:address":"1953 Westfield Ave",
    "sg:city":"Scotch Plains",
    "sg:classifiers":[
        {
            "category":"Professional",
            "subcategory":"Lawyer & Legal Services",
            "type":"Services"
        }
    ],
    "sg:phone":"+1 908 322 9191",
    "sg:postcode":"07076",
    "sg:province":"NJ",
    "sg:tags":[
        "attorney"
    ],
    "wof:name":"Jeney & Jeney",
    "wof:placetype":"venue"
},
  "geometry": {"coordinates":[-74.395134,40.650856],"type":"Point"}
}