{
  "type": "Feature",
  "properties": {
    "addr:full":"1703 Taylors Ln Cinnaminson NJ 08077",
    "addr:housenumber":"1703",
    "addr:postcode":"08077",
    "addr:street":"Taylors Ln",
    "iso:country":"US",
    "sg:address":"1703 Taylors Ln",
    "sg:city":"Cinnaminson",
    "sg:classifiers":[
        {
            "category":"Building & Trades",
            "subcategory":"Plumbing",
            "type":"Services"
        }
    ],
    "sg:phone":"+1 856 786 5470",
    "sg:postcode":"08077",
    "sg:province":"NJ",
    "sg:tags":[
        "conditioning",
        "air",
        "system",
        "contractor"
    ],
    "sg:website":"www.amsmechanical.com",
    "wof:name":"AMS Mechanical Systems",
    "wof:placetype":"venue"
},
  "geometry": {"coordinates":[-74.980063,40.018774],"type":"Point"}
}