{
  "type": "Feature",
  "properties": {
    "iso:country":"US",
    "sg:address":"54 Princeton Pl",
    "sg:city":"Princeton Jct",
    "sg:classifiers":[
        {
            "category":"Manufacturing",
            "subcategory":"Printing",
            "type":"Manufacturing & Wholesale Goods"
        }
    ],
    "sg:phone":"+1 609 799 4200",
    "sg:postcode":"08550",
    "sg:province":"NJ",
    "sg:tags":[
        "screen"
    ],
    "sg:website":"www.screenprintingusainc.com",
    "wof:name":"Screen Printing USA",
    "wof:placetype":"venue"
},
  "geometry": {"coordinates":[-74.62076399999999,40.300929],"type":"Point"}
}