{
  "type": "Feature",
  "properties": {
    "iso:country":"US",
    "sg:address":"41 Daugherty Ave",
    "sg:city":"Gillette",
    "sg:classifiers":[
        {
            "category":"Wholesale",
            "subcategory":"Machinery & Supplies",
            "type":"Manufacturing & Wholesale Goods"
        }
    ],
    "sg:phone":"+1 908 647 3336",
    "sg:postcode":"07933",
    "sg:province":"NJ",
    "sg:tags":[
        "industrial"
    ],
    "wof:name":"Independent Fuller Brush Distr",
    "wof:placetype":"venue"
},
  "geometry": {"coordinates":[-74.45547000000001,40.686997],"type":"Point"}
}