{
  "type": "Feature",
  "properties": {
    "addr:full":"1849 State Rte 27 Edison NJ 08817",
    "addr:housenumber":"1849",
    "addr:postcode":"08817",
    "addr:street":"State Rte 27",
    "iso:country":"US",
    "sg:address":"1849 State Rte 27",
    "sg:city":"Edison",
    "sg:classifiers":[
        {
            "category":"Personal",
            "subcategory":"Beauty Salon",
            "type":"Services"
        }
    ],
    "sg:phone":"+1 732 650 9644",
    "sg:postcode":"08817",
    "sg:province":"NJ",
    "sg:tags":[
        "shop",
        "manicuring"
    ],
    "wof:name":"La Belle Nail & Skin Beauty Sp",
    "wof:placetype":"venue"
},
  "geometry": {"coordinates":[-74.403802,40.514283],"type":"Point"}
}