{
  "type": "Feature",
  "properties": {
    "addr:full":"1 Brunswick Woods Dr East Brunswick NJ 08816",
    "addr:housenumber":"1",
    "addr:postcode":"08816",
    "addr:street":"Brunswick Woods Dr",
    "iso:country":"US",
    "sg:address":"1 Brunswick Woods Dr",
    "sg:city":"East Brunswick",
    "sg:classifiers":[
        {
            "category":"Government",
            "subcategory":"Office",
            "type":"Public Place"
        },
        {
            "category":"Utilities",
            "subcategory":"Water",
            "type":"Services"
        }
    ],
    "sg:phone":"+1 732 390 6826",
    "sg:postcode":"08816",
    "sg:province":"NJ",
    "sg:tags":[
        "dept",
        "company",
        "executive",
        "sewage"
    ],
    "wof:name":"East Brunswick Water Dept",
    "wof:placetype":"venue"
},
  "geometry": {"coordinates":[-74.389532,40.421004],"type":"Point"}
}