{
  "type": "Feature",
  "properties": {
    "iso:country":"US",
    "sg:address":"3691 US Hwy 9",
    "sg:city":"Old Bridge",
    "sg:classifiers":[
        {
            "category":"Autos & Motor Vehicles",
            "subcategory":"Auto Supplies",
            "type":"Retail Goods"
        }
    ],
    "sg:phone":"+1 732 591 2050",
    "sg:postcode":"08857",
    "sg:province":"NJ",
    "sg:tags":[
        "tire"
    ],
    "wof:name":"STS Tire & Auto Ctr",
    "wof:placetype":"venue"
},
  "geometry": {"coordinates":[-74.307698,40.381263],"type":"Point"}
}