{
  "type": "Feature",
  "properties": {
    "addr:full":"88 Polifly Rd Hackensack NJ 07601",
    "addr:housenumber":"88",
    "addr:postcode":"07601",
    "addr:street":"Polifly Rd",
    "iso:country":"US",
    "sg:address":"88 Polifly Rd",
    "sg:city":"Hackensack",
    "sg:classifiers":[
        {
            "category":"Retail",
            "subcategory":"Auto Rental",
            "type":"Services"
        }
    ],
    "sg:phone":"+1   ",
    "sg:postcode":"07601",
    "sg:province":"NJ",
    "sg:tags":[
        "truck"
    ],
    "wof:name":"Hackensack Leasing Corp",
    "wof:placetype":"venue"
},
  "geometry": {"coordinates":[-74.056487,40.878249],"type":"Point"}
}