{
  "type": "Feature",
  "properties": {
    "iso:country":"US",
    "sg:address":"715 State Rte 70",
    "sg:city":"Brick",
    "sg:classifiers":[
        {
            "category":"Banks & Credit Unions",
            "subcategory":"Bank",
            "type":"Services"
        }
    ],
    "sg:phone":"+1 732 451 9000",
    "sg:postcode":"08723",
    "sg:province":"NJ",
    "sg:tags":[
        "commercial"
    ],
    "sg:website":"www.crownbank.net",
    "wof:name":"Crown Bank National Assn",
    "wof:placetype":"venue"
},
  "geometry": {"coordinates":[-74.137878,40.062453],"type":"Point"}
}