{
  "type": "Feature",
  "properties": {
    "iso:country":"US",
    "sg:address":"809 Hylton Rd Ste 8",
    "sg:city":"Pennsauken",
    "sg:classifiers":[
        {
            "category":"Building & Trades",
            "subcategory":"Cleaning & Sanitation",
            "type":"Services"
        },
        {
            "category":"Wholesale",
            "subcategory":"Construction Materials",
            "type":"Manufacturing & Wholesale Goods"
        },
        {
            "category":"Building & Trades",
            "subcategory":"Construction",
            "type":"Services"
        }
    ],
    "sg:phone":"+1 856 324 0683",
    "sg:postcode":"08110",
    "sg:province":"NJ",
    "sg:tags":[
        "elevator-consultants",
        "elevators-repairing",
        "elevator",
        "cars-refinishing",
        "inspector"
    ],
    "wof:name":"Castlehale Consulting Limited Liability Company",
    "wof:placetype":"venue"
},
  "geometry": {"coordinates":[-75.02894999999999,39.987383],"type":"Point"}
}