{
  "type": "Feature",
  "properties": {
    "iso:country":"US",
    "sg:address":"2015 Lakeview Dr",
    "sg:city":"Parlin",
    "sg:classifiers":[
        {
            "category":"Restaurant",
            "type":"Food & Drink"
        }
    ],
    "sg:phone":"+1   ",
    "sg:postcode":"08859",
    "sg:province":"NJ",
    "sg:tags":[
        "eating"
    ],
    "wof:name":"Quimbys Place",
    "wof:placetype":"venue"
},
  "geometry": {"coordinates":[-74.325717,40.465993],"type":"Point"}
}