{
  "type": "Feature",
  "properties": {
    "addr:full":"35 Paducah Rd Mount Holly NJ 08060",
    "addr:housenumber":"35",
    "addr:postcode":"08060",
    "addr:street":"Paducah Rd",
    "iso:country":"US",
    "sg:address":"35 Paducah Rd",
    "sg:city":"Mount Holly",
    "sg:classifiers":[
        {
            "category":"Building & Trades",
            "subcategory":"Cleaning & Sanitation",
            "type":"Services"
        }
    ],
    "sg:phone":"+1 609 267 9695",
    "sg:postcode":"08060",
    "sg:province":"NJ",
    "wof:name":"Gold Cross",
    "wof:placetype":"venue"
},
  "geometry": {"coordinates":[-74.766362,39.987379],"type":"Point"}
}