{
  "type": "Feature",
  "properties": {
    "addr:full":"300 Corporate Dr Mahwah NJ 07430",
    "addr:housenumber":"300",
    "addr:postcode":"07430",
    "addr:street":"Corporate Dr",
    "iso:country":"US",
    "sg:address":"300 Corporate Dr",
    "sg:city":"Mahwah",
    "sg:classifiers":[
        {
            "category":"Freight",
            "type":"Transportation"
        }
    ],
    "sg:phone":"+1 201 529 1308",
    "sg:postcode":"07430",
    "sg:province":"NJ",
    "sg:tags":[
        "general"
    ],
    "wof:name":"Jessica Mc Clintock Inc",
    "wof:placetype":"venue"
},
  "geometry": {"coordinates":[-74.15630299999999,41.088044],"type":"Point"}
}