{
  "type": "Feature",
  "properties": {
    "iso:country":"US",
    "sg:address":"318 Danielle Dr",
    "sg:city":"Asbury Park",
    "sg:classifiers":[
        {
            "category":"Wholesale",
            "subcategory":"Apparel",
            "type":"Manufacturing & Wholesale Goods"
        }
    ],
    "sg:phone":"+1 732 493 1017",
    "sg:postcode":"07712",
    "sg:province":"NJ",
    "wof:name":"H T Holly Co",
    "wof:placetype":"venue"
},
  "geometry": {"coordinates":[-74.058436,40.265706],"type":"Point"}
}