{
  "type": "Feature",
  "properties": {
    "addr:full":"2409 Central Ave Wildwood NJ 08260",
    "addr:housenumber":"2409",
    "addr:postcode":"08260",
    "addr:street":"Central Ave",
    "iso:country":"US",
    "sg:address":"2409 Central Ave",
    "sg:city":"Wildwood",
    "sg:classifiers":[
        {
            "category":"Building & Trades",
            "subcategory":"Cleaning & Sanitation",
            "type":"Services"
        }
    ],
    "sg:phone":"+1 609 522 5833",
    "sg:postcode":"08260",
    "sg:province":"NJ",
    "sg:tags":[
        "home"
    ],
    "wof:name":"American Classy Cleaning Co",
    "wof:placetype":"venue"
},
  "geometry": {"coordinates":[-74.807503,38.9939],"type":"Point"}
}