{
  "type": "Feature",
  "properties": {
    "addr:full":"191 Broadway Bayonne NJ 07002",
    "addr:housenumber":"191",
    "addr:postcode":"07002",
    "addr:street":"Broadway",
    "iso:country":"US",
    "sg:address":"191 Broadway",
    "sg:city":"Bayonne",
    "sg:classifiers":[
        {
            "category":"Retail",
            "subcategory":"Repair Shop",
            "type":"Services"
        }
    ],
    "sg:phone":"+1 201 334 3145",
    "sg:postcode":"07002",
    "sg:province":"NJ",
    "sg:tags":[
        "lock",
        "locksmith"
    ],
    "wof:name":"All Day Emergency Locksmith",
    "wof:placetype":"venue"
},
  "geometry": {"coordinates":[-74.127602,40.6529],"type":"Point"}
}