{
  "type": "Feature",
  "properties": {
    "iso:country":"US",
    "sg:address":"165 Long Swamp Rd",
    "sg:city":"New Egypt",
    "sg:classifiers":[
        {
            "category":"Manufacturing",
            "subcategory":"Signs",
            "type":"Manufacturing & Wholesale Goods"
        }
    ],
    "sg:phone":"+1 609 758 3181",
    "sg:postcode":"08533",
    "sg:province":"NJ",
    "sg:tags":[
        "specialty",
        "mfg"
    ],
    "wof:name":"Conway Signs",
    "wof:placetype":"venue"
},
  "geometry": {"coordinates":[-74.494285,40.049394],"type":"Point"}
}