{
  "type": "Feature",
  "properties": {
    "addr:full":"35 Walnut Ave Clark NJ 07066",
    "addr:housenumber":"35",
    "addr:postcode":"07066",
    "addr:street":"Walnut Ave",
    "iso:country":"US",
    "sg:address":"35 Walnut Ave",
    "sg:city":"Clark",
    "sg:classifiers":[
        {
            "category":"Government",
            "subcategory":"Police Station",
            "type":"Public Place"
        }
    ],
    "sg:phone":"+1   ",
    "sg:postcode":"07066",
    "sg:province":"NJ",
    "sg:tags":[
        "protection"
    ],
    "wof:name":"Union County Police Department",
    "wof:placetype":"venue"
},
  "geometry": {"coordinates":[-74.301812,40.630121],"type":"Point"}
}