{
  "type": "Feature",
  "properties": {
    "iso:country":"US",
    "sg:address":"10 Broadview Ave",
    "sg:city":"Maplewood",
    "sg:classifiers":[
        {
            "category":"Professional",
            "type":"Services"
        }
    ],
    "sg:phone":"+1 973 313 9202",
    "sg:postcode":"07040",
    "sg:province":"NJ",
    "sg:tags":[
        "establishment"
    ],
    "wof:name":"Plaza Curtis",
    "wof:placetype":"venue"
},
  "geometry": {"coordinates":[-74.277378,40.722157],"type":"Point"}
}