{
  "type": "Feature",
  "properties": {
    "addr:full":"88 Juliette St Perth Amboy NJ 08861",
    "addr:housenumber":"88",
    "addr:postcode":"08861",
    "addr:street":"Juliette St",
    "iso:country":"US",
    "sg:address":"88 Juliette St",
    "sg:city":"Perth Amboy",
    "sg:classifiers":[
        {
            "category":"Building & Trades",
            "subcategory":"Landscaping Services",
            "type":"Services"
        }
    ],
    "sg:phone":"+1 732 826 4680",
    "sg:postcode":"08861",
    "sg:province":"NJ",
    "sg:tags":[
        "landscape"
    ],
    "wof:name":"Ed Fowler & Sons",
    "wof:placetype":"venue"
},
  "geometry": {"coordinates":[-74.294673,40.524515],"type":"Point"}
}