{
  "type": "Feature",
  "properties": {
    "addr:full":"1373 Broad St Clifton NJ 07013",
    "addr:housenumber":"1373",
    "addr:postcode":"07013",
    "addr:street":"Broad St",
    "iso:country":"US",
    "sg:address":"1373 Broad St",
    "sg:city":"Clifton",
    "sg:classifiers":[
        {
            "category":"Professional",
            "subcategory":"Management & Consulting",
            "type":"Services"
        }
    ],
    "sg:phone":"+1 973 614 9100",
    "sg:postcode":"07013",
    "sg:province":"NJ",
    "sg:tags":[
        "consultant",
        "hospital"
    ],
    "sg:website":"www.armds.com",
    "wof:name":"ARMDS Inc",
    "wof:placetype":"venue"
},
  "geometry": {"coordinates":[-74.181095,40.848172],"type":"Point"}
}