{
  "type": "Feature",
  "properties": {
    "addr:full":"64 Lexington Ave Passaic NJ 07055",
    "addr:housenumber":"64",
    "addr:postcode":"07055",
    "addr:street":"Lexington Ave",
    "iso:country":"US",
    "sg:address":"64 Lexington Ave",
    "sg:city":"Passaic",
    "sg:classifiers":[
        {
            "category":"Home & Garden",
            "subcategory":"Home Furnishings",
            "type":"Retail Goods"
        }
    ],
    "sg:phone":"+1 973 471 7181",
    "sg:postcode":"07055",
    "sg:province":"NJ",
    "sg:tags":[
        "linen"
    ],
    "wof:name":"Big Bargain",
    "wof:placetype":"venue"
},
  "geometry": {"coordinates":[-74.12713100000001,40.863425],"type":"Point"}
}