{
  "type": "Feature",
  "properties": {
    "iso:country":"US",
    "sg:address":"132 45th St",
    "sg:city":"Union City",
    "sg:classifiers":[
        {
            "category":"Food & Beverages",
            "subcategory":"Groceries & Convenience Stores",
            "type":"Retail Goods"
        }
    ],
    "sg:phone":"+1 201 863 9444",
    "sg:postcode":"07087",
    "sg:province":"NJ",
    "wof:name":"Diaz Grocery II",
    "wof:placetype":"venue"
},
  "geometry": {"coordinates":[-74.01950100000001,40.7775],"type":"Point"}
}