{
  "type": "Feature",
  "properties": {
    "iso:country":"US",
    "sg:address":"273 Summer St",
    "sg:city":"Passaic",
    "sg:classifiers":[
        {
            "category":"Shopping",
            "type":"Retail Goods"
        }
    ],
    "sg:phone":"+1 973 591 0456",
    "sg:postcode":"07055",
    "sg:province":"NJ",
    "sg:tags":[
        "cosmetic",
        "perfume"
    ],
    "wof:name":"Asime",
    "wof:placetype":"venue"
},
  "geometry": {"coordinates":[-74.140569,40.867035],"type":"Point"}
}