{
  "type": "Feature",
  "properties": {
    "addr:full":"1959 Englishtown Rd Jamesburg NJ 08831",
    "addr:housenumber":"1959",
    "addr:postcode":"08831",
    "addr:street":"Englishtown Rd",
    "iso:country":"US",
    "sg:address":"1959 Englishtown Rd",
    "sg:city":"Jamesburg",
    "sg:classifiers":[
        {
            "category":"Home & Garden",
            "subcategory":"Garden Supply",
            "type":"Retail Goods"
        },
        {
            "category":"Building & Trades",
            "subcategory":"Landscaping Services",
            "type":"Services"
        }
    ],
    "sg:phone":"+1 732 521 1979",
    "sg:postcode":"08831",
    "sg:province":"NJ",
    "sg:tags":[
        "nurseryman"
    ],
    "wof:name":"Stasi Landscaping Co Inc",
    "wof:placetype":"venue"
},
  "geometry": {"coordinates":[-74.357139,40.34833],"type":"Point"}
}