{
  "type": "Feature",
  "properties": {
    "addr:full":"842 State Rd Princeton NJ 08540",
    "addr:housenumber":"842",
    "addr:postcode":"08540",
    "addr:street":"State Rd",
    "iso:country":"US",
    "sg:address":"842 State Rd",
    "sg:city":"Princeton",
    "sg:classifiers":[
        {
            "category":"Health Services",
            "subcategory":"Health Practitioner",
            "type":"Services"
        }
    ],
    "sg:phone":"+1   ",
    "sg:postcode":"08540",
    "sg:province":"NJ",
    "wof:name":"Antoinette Goodwin PHD",
    "wof:placetype":"venue"
},
  "geometry": {"coordinates":[-74.65501500000001,40.390236],"type":"Point"}
}