{
  "type": "Feature",
  "properties": {
    "iso:country":"US",
    "sg:address":"3 Great Meadow Ln",
    "sg:city":"East Hanover",
    "sg:classifiers":[
        {
            "category":"Real Estate",
            "subcategory":"Real Estate Services",
            "type":"Services"
        }
    ],
    "sg:phone":"+1 973 887 0900",
    "sg:postcode":"07936",
    "sg:province":"NJ",
    "sg:tags":[
        "management",
        "property"
    ],
    "wof:name":"S Marron Services Llc",
    "wof:placetype":"venue"
},
  "geometry": {"coordinates":[-74.39425900000001,40.80222],"type":"Point"}
}