{
  "type": "Feature",
  "properties": {
    "iso:country":"US",
    "sg:address":"345 Monmouth Ave",
    "sg:city":"New Milford",
    "sg:classifiers":[
        {
            "category":"Organizations",
            "subcategory":"Religious Organization",
            "type":"Services"
        }
    ],
    "sg:phone":"+1   ",
    "sg:postcode":"07646",
    "sg:province":"NJ",
    "wof:name":"First Bptst Church New Milford",
    "wof:placetype":"venue"
},
  "geometry": {"coordinates":[-74.01938800000001,40.932721],"type":"Point"}
}