{
  "type": "Feature",
  "properties": {
    "addr:full":"75 Orchard St Ramsey NJ 07446",
    "addr:housenumber":"75",
    "addr:postcode":"07446",
    "addr:street":"Orchard St",
    "iso:country":"US",
    "sg:address":"75 Orchard St",
    "sg:city":"Ramsey",
    "sg:classifiers":[
        {
            "category":"Home & Garden",
            "subcategory":"Carpets & Floor Coverings",
            "type":"Retail Goods"
        }
    ],
    "sg:phone":"+1 201 825 8821",
    "sg:postcode":"07446",
    "sg:province":"NJ",
    "sg:tags":[
        "dealer",
        "rug"
    ],
    "wof:name":"Modern Floors Co",
    "wof:placetype":"venue"
},
  "geometry": {"coordinates":[-74.13991,41.077015],"type":"Point"}
}