{
  "type": "Feature",
  "properties": {
    "iso:country":"US",
    "sg:address":"722 Sheridan Ave",
    "sg:city":"Vineland",
    "sg:classifiers":[
        {
            "category":"Professional",
            "subcategory":"Computer Services",
            "type":"Services"
        }
    ],
    "sg:phone":"+1 856 825 4232",
    "sg:postcode":"08361",
    "sg:province":"NJ",
    "sg:tags":[
        "management",
        "facility"
    ],
    "wof:name":"Garcia & Assoc Inc",
    "wof:placetype":"venue"
},
  "geometry": {"coordinates":[-75.016634,39.432239],"type":"Point"}
}