{
  "type": "Feature",
  "properties": {
    "addr:full":"216 Sunset Rd Willingboro NJ 08046",
    "addr:housenumber":"216",
    "addr:postcode":"08046",
    "addr:street":"Sunset Rd",
    "iso:country":"US",
    "sg:address":"216 Sunset Rd",
    "sg:city":"Willingboro",
    "sg:classifiers":[
        {
            "category":"Organizations",
            "subcategory":"Religious Organization",
            "type":"Services"
        }
    ],
    "sg:phone":"+1 609 871 2015",
    "sg:postcode":"08046",
    "sg:province":"NJ",
    "sg:tags":[
        "church"
    ],
    "sg:website":"www.fbcwillingboro.org",
    "wof:name":"First Baptist Church",
    "wof:placetype":"venue"
},
  "geometry": {"coordinates":[-74.882801,40.048477],"type":"Point"}
}