{
  "type": "Feature",
  "properties": {
    "addr:full":"111 Ave A Bayonne NJ 07002",
    "addr:postcode":"07002",
    "addr:street":"111 Ave A",
    "iso:country":"US",
    "sg:address":"111 Ave A",
    "sg:city":"Bayonne",
    "sg:classifiers":[
        {
            "category":"Freight",
            "type":"Transportation"
        }
    ],
    "sg:phone":"+1 201 436 6708",
    "sg:postcode":"07002",
    "sg:province":"NJ",
    "sg:tags":[
        "operator",
        "trucking"
    ],
    "wof:name":"Bay Leasing",
    "wof:placetype":"venue"
},
  "geometry": {"coordinates":[-74.137815,40.651776],"type":"Point"}
}