{
  "type": "Feature",
  "properties": {
    "iso:country":"US",
    "sg:address":"2 Corporate Dr",
    "sg:city":"Cranbury",
    "sg:classifiers":[
        {
            "category":"Professional",
            "subcategory":"Employment Agencies",
            "type":"Services"
        }
    ],
    "sg:phone":"+1 609 860 0400",
    "sg:postcode":"08512",
    "sg:province":"NJ",
    "sg:tags":[
        "leasing"
    ],
    "sg:website":"www.abel-leasing.com",
    "wof:name":"Abel",
    "wof:placetype":"venue"
},
  "geometry": {"coordinates":[-74.48321,40.33349],"type":"Point"}
}