{
  "type": "Feature",
  "properties": {
    "addr:full":"23 Manor Blvd Monroe Township NJ 08831",
    "addr:housenumber":"23",
    "addr:postcode":"08831",
    "addr:street":"Manor Blvd",
    "iso:country":"US",
    "sg:address":"23 Manor Blvd",
    "sg:city":"Monroe Township",
    "sg:classifiers":[
        {
            "category":"Professional",
            "type":"Services"
        }
    ],
    "sg:phone":"+1   ",
    "sg:postcode":"08831",
    "sg:province":"NJ",
    "wof:name":"Eileen Steinhart",
    "wof:placetype":"venue"
},
  "geometry": {"coordinates":[-74.384917,40.371125],"type":"Point"}
}