{
  "type": "Feature",
  "properties": {
    "addr:full":"211 Hickory Tavern Rd Gillette NJ 07933",
    "addr:housenumber":"211",
    "addr:postcode":"07933",
    "addr:street":"Hickory Tavern Rd",
    "iso:country":"US",
    "sg:address":"211 Hickory Tavern Rd",
    "sg:city":"Gillette",
    "sg:classifiers":[
        {
            "category":"Shopping",
            "subcategory":"Used Merchandise",
            "type":"Retail Goods"
        }
    ],
    "sg:phone":"+1 908 647 1959",
    "sg:postcode":"07933",
    "sg:province":"NJ",
    "sg:tags":[
        "antique"
    ],
    "wof:name":"Trading Post Antiques the",
    "wof:placetype":"venue"
},
  "geometry": {"coordinates":[-74.469902,40.689701],"type":"Point"}
}