{
  "type": "Feature",
  "properties": {
    "iso:country":"US",
    "sg:address":"2388 Crisfield Cir",
    "sg:city":"Toms River",
    "sg:classifiers":[
        {
            "category":"Professional",
            "subcategory":"Research",
            "type":"Services"
        }
    ],
    "sg:phone":"+1   ",
    "sg:postcode":"08755",
    "sg:province":"NJ",
    "sg:tags":[
        "organization",
        "noncommercial"
    ],
    "wof:name":"University of Chicago",
    "wof:placetype":"venue"
},
  "geometry": {"coordinates":[-74.23706,40.04761],"type":"Point"}
}