{
  "type": "Feature",
  "properties": {
    "iso:country":"US",
    "sg:address":"59 Courtland St",
    "sg:city":"Paterson",
    "sg:classifiers":[
        {
            "category":"Home & Garden",
            "subcategory":"Building Materials",
            "type":"Retail Goods"
        }
    ],
    "sg:phone":"+1   ",
    "sg:postcode":"07503",
    "sg:province":"NJ",
    "wof:name":"Luther Studios",
    "wof:placetype":"venue"
},
  "geometry": {"coordinates":[-74.1658,40.900531],"type":"Point"}
}