{
  "type": "Feature",
  "properties": {
    "iso:country":"US",
    "sg:address":"150 S Johnston Ave",
    "sg:city":"Trenton",
    "sg:classifiers":[
        {
            "category":"Organizations",
            "subcategory":"Religious Organization",
            "type":"Services"
        }
    ],
    "sg:phone":"+1 609 587 0268",
    "sg:postcode":"08609",
    "sg:province":"NJ",
    "sg:website":"www.bethelofhamilton.org",
    "wof:name":"Bethel Lutheran Church",
    "wof:placetype":"venue"
},
  "geometry": {"coordinates":[-74.730412,40.230546],"type":"Point"}
}