{
  "type": "Feature",
  "properties": {
    "iso:country":"US",
    "sg:address":"373 US Hwy 46",
    "sg:city":"Fairfield",
    "sg:classifiers":[
        {
            "category":"Manufacturing",
            "subcategory":"Metals",
            "type":"Manufacturing & Wholesale Goods"
        }
    ],
    "sg:phone":"+1 973 575 8350",
    "sg:postcode":"07004",
    "sg:province":"NJ",
    "sg:tags":[
        "pipe",
        "fitting",
        "valve"
    ],
    "wof:name":"Amsco Sales Corp",
    "wof:placetype":"venue"
},
  "geometry": {"coordinates":[-74.29883599999999,40.877242],"type":"Point"}
}