{
  "type": "Feature",
  "properties": {
    "addr:full":"515 Bay Ave Pt Pleasant Bch NJ 08742",
    "addr:housenumber":"515",
    "addr:postcode":"08742",
    "addr:street":"Bay Ave Pt",
    "iso:country":"US",
    "sg:address":"515 Bay Ave",
    "sg:city":"Pt Pleasant Bch",
    "sg:classifiers":[
        {
            "category":"Shopping",
            "subcategory":"Discount & Variety Stores",
            "type":"Retail Goods"
        },
        {
            "category":"Shopping",
            "subcategory":"Gifts & Souvenirs",
            "type":"Retail Goods"
        }
    ],
    "sg:phone":"+1 732 892 5757",
    "sg:postcode":"08742",
    "sg:province":"NJ",
    "sg:tags":[
        "shop",
        "general"
    ],
    "wof:name":"Everybody's General Store",
    "wof:placetype":"venue"
},
  "geometry": {"coordinates":[-74.051896,40.091411],"type":"Point"}
}