{
  "type": "Feature",
  "properties": {
    "iso:country":"US",
    "sg:address":"17 Dogwood Ter",
    "sg:city":"Livingston",
    "sg:classifiers":[
        {
            "category":"Wholesale",
            "subcategory":"Groceries",
            "type":"Manufacturing & Wholesale Goods"
        }
    ],
    "sg:phone":"+1 973 422 1165",
    "sg:postcode":"07039",
    "sg:province":"NJ",
    "sg:tags":[
        "food",
        "broker"
    ],
    "wof:name":"Frank & Maria Food Brokers",
    "wof:placetype":"venue"
},
  "geometry": {"coordinates":[-74.33339700000001,40.784925],"type":"Point"}
}