{
  "type": "Feature",
  "properties": {
    "iso:country":"US",
    "sg:address":"10 Ellis Rd",
    "sg:city":"Caldwell",
    "sg:classifiers":[
        {
            "category":"Building & Trades",
            "subcategory":"Construction",
            "type":"Services"
        }
    ],
    "sg:phone":"+1 973 226 6572",
    "sg:postcode":"07006",
    "sg:province":"NJ",
    "sg:tags":[
        "contractor",
        "nonresidential"
    ],
    "wof:name":"TNT Homes Inc",
    "wof:placetype":"venue"
},
  "geometry": {"coordinates":[-74.308098,40.83517],"type":"Point"}
}