{
  "type": "Feature",
  "properties": {
    "addr:full":"8290 National Hwy Pennsauken NJ 08110",
    "addr:housenumber":"8290",
    "addr:postcode":"08110",
    "addr:street":"National Hwy",
    "iso:country":"US",
    "sg:address":"8290 National Hwy",
    "sg:city":"Pennsauken",
    "sg:classifiers":[
        {
            "category":"Freight",
            "type":"Transportation"
        }
    ],
    "sg:phone":"+1 856 486 1689",
    "sg:postcode":"08110",
    "sg:province":"NJ",
    "sg:tags":[
        "operator",
        "trucking"
    ],
    "wof:name":"Hartt Transportation Systems",
    "wof:placetype":"venue"
},
  "geometry": {"coordinates":[-75.033744,39.981815],"type":"Point"}
}