{
  "type": "Feature",
  "properties": {
    "iso:country":"US",
    "sg:address":"491 Darlington Ave",
    "sg:city":"Ramsey",
    "sg:classifiers":[
        {
            "category":"Building & Trades",
            "subcategory":"Construction",
            "type":"Services"
        }
    ],
    "sg:phone":"+1 201 825 0420",
    "sg:postcode":"07446",
    "sg:province":"NJ",
    "sg:tags":[
        "contractor"
    ],
    "wof:name":"Craftsman Guild Ltd",
    "wof:placetype":"venue"
},
  "geometry": {"coordinates":[-74.16493199999999,41.062433],"type":"Point"}
}