{
  "type": "Feature",
  "properties": {
    "iso:country":"US",
    "sg:address":"22 Mountainside Dr",
    "sg:city":"Colts Neck",
    "sg:classifiers":[
        {
            "category":"Professional",
            "subcategory":"Computer Services",
            "type":"Services"
        }
    ],
    "sg:phone":"+1   ",
    "sg:postcode":"07722",
    "sg:province":"NJ",
    "sg:tags":[
        "related"
    ],
    "wof:name":"Orriss Consulting LLC",
    "wof:placetype":"venue"
},
  "geometry": {"coordinates":[-74.205974,40.340509],"type":"Point"}
}