{
  "type": "Feature",
  "properties": {
    "iso:country":"US",
    "sg:address":"18 Newell Pass",
    "sg:city":"Willingboro",
    "sg:classifiers":[
        {
            "category":"Home & Garden",
            "subcategory":"Hardware",
            "type":"Retail Goods"
        }
    ],
    "sg:phone":"+1   ",
    "sg:postcode":"08046",
    "sg:province":"NJ",
    "wof:name":"Iron Man Tools",
    "wof:placetype":"venue"
},
  "geometry": {"coordinates":[-74.856572,40.035492],"type":"Point"}
}