{
  "type": "Feature",
  "properties": {
    "addr:full":"32 William St Metuchen NJ 08840",
    "addr:housenumber":"32",
    "addr:postcode":"08840",
    "addr:street":"William St",
    "iso:country":"US",
    "sg:address":"32 William St",
    "sg:city":"Metuchen",
    "sg:classifiers":[
        {
            "category":"Professional",
            "subcategory":"Management & Consulting",
            "type":"Services"
        }
    ],
    "sg:phone":"+1   ",
    "sg:postcode":"08840",
    "sg:province":"NJ",
    "sg:tags":[
        "business"
    ],
    "wof:name":"Batton Consulting",
    "wof:placetype":"venue"
},
  "geometry": {"coordinates":[-74.364952,40.543315],"type":"Point"}
}