{
  "type": "Feature",
  "properties": {
    "iso:country":"US",
    "sg:address":"303 Cedar Ct",
    "sg:city":"Norwood",
    "sg:classifiers":[
        {
            "category":"Professional",
            "subcategory":"Computer Services",
            "type":"Services"
        }
    ],
    "sg:phone":"+1   ",
    "sg:postcode":"07648",
    "sg:province":"NJ",
    "sg:tags":[
        "related"
    ],
    "wof:name":"Keem Network",
    "wof:placetype":"venue"
},
  "geometry": {"coordinates":[-73.950428,40.986606],"type":"Point"}
}