{
  "type": "Feature",
  "properties": {
    "iso:country":"US",
    "sg:address":"169 Maplewood Ave",
    "sg:city":"Maplewood",
    "sg:classifiers":[
        {
            "category":"Professional",
            "subcategory":"Lawyer & Legal Services",
            "type":"Services"
        }
    ],
    "sg:phone":"+1 973 275 5010",
    "sg:postcode":"07040",
    "sg:province":"NJ",
    "sg:tags":[
        "attorney"
    ],
    "wof:name":"Stephen Skollar Law Offices",
    "wof:placetype":"venue"
},
  "geometry": {"coordinates":[-74.277259,40.73108],"type":"Point"}
}