{
  "type": "Feature",
  "properties": {
    "addr:full":"95 Maryland Pl Orange NJ 07050",
    "addr:housenumber":"95",
    "addr:postcode":"07050",
    "addr:street":"Maryland Pl",
    "iso:country":"US",
    "sg:address":"95 Maryland Pl",
    "sg:city":"Orange",
    "sg:classifiers":[
        {
            "category":"Wholesale",
            "subcategory":"Scrap",
            "type":"Manufacturing & Wholesale Goods"
        }
    ],
    "sg:phone":"+1 973 674 9494",
    "sg:postcode":"07050",
    "sg:province":"NJ",
    "sg:tags":[
        "recycling",
        "center"
    ],
    "wof:name":"Eastern Recycling Inc",
    "wof:placetype":"venue"
},
  "geometry": {"coordinates":[-74.236279,40.772259],"type":"Point"}
}