{
  "type": "Feature",
  "properties": {
    "iso:country":"US",
    "sg:address":"6 Augusta Ct",
    "sg:city":"Neptune",
    "sg:classifiers":[
        {
            "category":"Building & Trades",
            "subcategory":"Construction",
            "type":"Services"
        }
    ],
    "sg:phone":"+1 732 918 0092",
    "sg:postcode":"07701",
    "sg:province":"NJ",
    "sg:tags":[
        "business",
        "well",
        "water",
        "s",
        "drilling",
        "plumbing"
    ],
    "wof:name":"Tilton Pump Service Inc",
    "wof:placetype":"venue"
},
  "geometry": {"coordinates":[-74.093773,40.351857],"type":"Point"}
}