{
  "type": "Feature",
  "properties": {
    "iso:country":"US",
    "sg:address":"412 Washington St",
    "sg:city":"Orange",
    "sg:classifiers":[
        {
            "category":"Personal",
            "subcategory":"Beauty Salon",
            "type":"Services"
        }
    ],
    "sg:phone":"+1   ",
    "sg:postcode":"07050",
    "sg:province":"NJ",
    "sg:tags":[
        "shop"
    ],
    "wof:name":"Fabs Faboulas Buty & Barbr Sp",
    "wof:placetype":"venue"
},
  "geometry": {"coordinates":[-74.225943,40.78366],"type":"Point"}
}