{
  "type": "Feature",
  "properties": {
    "iso:country":"US",
    "sg:address":"430 Radcliffe St",
    "sg:city":"Wyckoff",
    "sg:classifiers":[
        {
            "category":"Banks & Credit Unions",
            "subcategory":"Bank",
            "type":"Services"
        }
    ],
    "sg:phone":"+1 201 444 1486",
    "sg:postcode":"07481",
    "sg:province":"NJ",
    "wof:name":"Paragon Fed Credit Union",
    "wof:placetype":"venue"
},
  "geometry": {"coordinates":[-74.14737599999999,40.982115],"type":"Point"}
}