{
  "type": "Feature",
  "properties": {
    "addr:full":"118 Mott Ave Burlington NJ 08016",
    "addr:housenumber":"118",
    "addr:postcode":"08016",
    "addr:street":"Mott Ave",
    "iso:country":"US",
    "sg:address":"118 Mott Ave",
    "sg:city":"Burlington",
    "sg:classifiers":[
        {
            "category":"Building & Trades",
            "subcategory":"Construction",
            "type":"Services"
        }
    ],
    "sg:phone":"+1 609 387 4400",
    "sg:postcode":"08016",
    "sg:province":"NJ",
    "sg:tags":[
        "excavation",
        "contractor"
    ],
    "wof:name":"Ground Pounders Excavating LLC",
    "wof:placetype":"venue"
},
  "geometry": {"coordinates":[-74.85983299999999,40.069035],"type":"Point"}
}