{
  "type": "Feature",
  "properties": {
    "iso:country":"US",
    "sg:address":"800 Newton Ave",
    "sg:city":"Oaklyn",
    "sg:classifiers":[
        {
            "category":"Building & Trades",
            "subcategory":"Construction",
            "type":"Services"
        }
    ],
    "sg:phone":"+1 856 858 7771",
    "sg:postcode":"08107",
    "sg:province":"NJ",
    "sg:tags":[
        "design",
        "window",
        "installation",
        "contractor"
    ],
    "wof:name":"Westco",
    "wof:placetype":"venue"
},
  "geometry": {"coordinates":[-75.077347,39.899408],"type":"Point"}
}