{
  "type": "Feature",
  "properties": {
    "iso:country":"US",
    "sg:address":"525 Cinnaminson St",
    "sg:city":"Riverton",
    "sg:classifiers":[
        {
            "category":"Professional",
            "subcategory":"Business Services",
            "type":"Services"
        }
    ],
    "sg:phone":"+1 856 303 9188",
    "sg:postcode":"08077",
    "sg:province":"NJ",
    "sg:tags":[
        "information",
        "referral"
    ],
    "wof:name":"MPR Information Svc",
    "wof:placetype":"venue"
},
  "geometry": {"coordinates":[-75.011509,40.010488],"type":"Point"}
}