{
  "type": "Feature",
  "properties": {
    "iso:country":"US",
    "sg:address":"27 Hudson Pl",
    "sg:city":"Weehawken",
    "sg:classifiers":[
        {
            "category":"Professional",
            "subcategory":"Management & Consulting",
            "type":"Services"
        }
    ],
    "sg:phone":"+1   ",
    "sg:postcode":"07086",
    "sg:province":"NJ",
    "sg:tags":[
        "public",
        "relations"
    ],
    "wof:name":"Ford Pub Relations Micheal A",
    "wof:placetype":"venue"
},
  "geometry": {"coordinates":[-74.018351,40.772723],"type":"Point"}
}