{
  "type": "Feature",
  "properties": {
    "iso:country":"US",
    "sg:address":"1514 Woodland Ave",
    "sg:city":"South Plainfield",
    "sg:classifiers":[
        {
            "category":"Communications",
            "subcategory":"Film & Video Production",
            "type":"Services"
        }
    ],
    "sg:phone":"+1 908 769 6599",
    "sg:postcode":"07080",
    "sg:province":"NJ",
    "sg:tags":[
        "motion",
        "editing",
        "tape"
    ],
    "wof:name":"G Man Pictures",
    "wof:placetype":"venue"
},
  "geometry": {"coordinates":[-74.39455100000001,40.600217],"type":"Point"}
}