{
  "type": "Feature",
  "properties": {
    "iso:country":"US",
    "sg:address":"801 US Hwy 130",
    "sg:city":"Burlington",
    "sg:classifiers":[
        {
            "category":"Restaurant",
            "type":"Food & Drink"
        }
    ],
    "sg:phone":"+1 609 386 0106",
    "sg:postcode":"08016",
    "sg:province":"NJ",
    "sg:tags":[
        "sandwich"
    ],
    "wof:name":"Stewart's Drive-In Tray Svc",
    "wof:placetype":"venue"
},
  "geometry": {"coordinates":[-74.84374099999999,40.077115],"type":"Point"}
}