{
  "type": "Feature",
  "properties": {
    "iso:country":"US",
    "sg:address":"26 Linden Ave",
    "sg:city":"Springfield",
    "sg:classifiers":[
        {
            "category":"Social Services",
            "type":"Services"
        }
    ],
    "sg:phone":"+1   ",
    "sg:postcode":"07081",
    "sg:province":"NJ",
    "wof:name":"Robin Shimel Lcsw",
    "wof:placetype":"venue"
},
  "geometry": {"coordinates":[-74.30943600000001,40.709246],"type":"Point"}
}