{
  "type": "Feature",
  "properties": {
    "addr:full":"1718 Bay Isle Dr Point Pleasant Beach NJ 08742",
    "addr:housenumber":"1718",
    "addr:postcode":"08742",
    "addr:street":"Bay Isle Dr",
    "iso:country":"US",
    "sg:address":"1718 Bay Isle Dr",
    "sg:city":"Point Pleasant Beach",
    "sg:classifiers":[
        {
            "category":"Wholesale",
            "subcategory":"Machinery & Supplies",
            "type":"Manufacturing & Wholesale Goods"
        }
    ],
    "sg:phone":"+1 732 899 6840",
    "sg:postcode":"08742",
    "sg:province":"NJ",
    "sg:tags":[
        "equipment",
        "transportation"
    ],
    "wof:name":"United States Power Squad",
    "wof:placetype":"venue"
},
  "geometry": {"coordinates":[-74.058032,40.062462],"type":"Point"}
}