{
  "type": "Feature",
  "properties": {
    "iso:country":"US",
    "sg:address":"389 Princeton Ave",
    "sg:city":"Bayville",
    "sg:classifiers":[
        {
            "category":"Building & Trades",
            "subcategory":"Construction",
            "type":"Services"
        }
    ],
    "sg:phone":"+1 732 237 0247",
    "sg:postcode":"08721",
    "sg:province":"NJ",
    "sg:tags":[
        "paving",
        "contractor"
    ],
    "wof:name":"Just Paving & Trucking Inc",
    "wof:placetype":"venue"
},
  "geometry": {"coordinates":[-74.17473099999999,39.896132],"type":"Point"}
}