{
  "type": "Feature",
  "properties": {
    "iso:country":"US",
    "sg:address":"328 Saint Georges Ave",
    "sg:city":"Rahway",
    "sg:classifiers":[
        {
            "category":"Restaurant",
            "type":"Food & Drink"
        }
    ],
    "sg:phone":"+1 732 388 8848",
    "sg:postcode":"07065",
    "sg:province":"NJ",
    "sg:tags":[
        "eating"
    ],
    "wof:name":"New Great Wall",
    "wof:placetype":"venue"
},
  "geometry": {"coordinates":[-74.29029800000001,40.5965],"type":"Point"}
}