{
  "type": "Feature",
  "properties": {
    "iso:country":"US",
    "sg:address":"24 Cokesbury Rd",
    "sg:city":"Lebanon",
    "sg:classifiers":[
        {
            "category":"Building & Trades",
            "subcategory":"Construction",
            "type":"Services"
        }
    ],
    "sg:phone":"+1 908 781 6889",
    "sg:postcode":"08833",
    "sg:province":"NJ",
    "sg:tags":[
        "downspouts",
        "gutter",
        "contractor"
    ],
    "wof:name":"R H Teed Seamless Gutters Inc",
    "wof:placetype":"venue"
},
  "geometry": {"coordinates":[-74.834484,40.646684],"type":"Point"}
}