{
  "type": "Feature",
  "properties": {
    "addr:full":"16 Waverly Pl Madison NJ 07940",
    "addr:housenumber":"16",
    "addr:postcode":"07940",
    "addr:street":"Waverly Pl",
    "iso:country":"US",
    "sg:address":"16 Waverly Pl",
    "sg:city":"Madison",
    "sg:classifiers":[
        {
            "category":"Banks & Credit Unions",
            "subcategory":"Bank",
            "type":"Services"
        }
    ],
    "sg:phone":"+1   ",
    "sg:postcode":"07940",
    "sg:province":"NJ",
    "sg:tags":[
        "national",
        "commercial"
    ],
    "wof:name":"Fleet",
    "wof:placetype":"venue"
},
  "geometry": {"coordinates":[-74.415352,40.758104],"type":"Point"}
}