{
  "type": "Feature",
  "properties": {
    "iso:country":"US",
    "sg:address":"2 Delwood Ln",
    "sg:city":"Berlin",
    "sg:classifiers":[
        {
            "category":"Building & Trades",
            "subcategory":"Construction",
            "type":"Services"
        }
    ],
    "sg:phone":"+1 856 767 6892",
    "sg:postcode":"08009",
    "sg:province":"NJ",
    "sg:tags":[
        "painter"
    ],
    "wof:name":"Monico Custom Painting",
    "wof:placetype":"venue"
},
  "geometry": {"coordinates":[-74.93064099999999,39.778942],"type":"Point"}
}