{
  "type": "Feature",
  "properties": {
    "addr:full":"12 State Rte 17 Paramus NJ 07652",
    "addr:housenumber":"12",
    "addr:postcode":"07652",
    "addr:street":"State Rte 17",
    "iso:country":"US",
    "sg:address":"12 State Rte 17",
    "sg:city":"Paramus",
    "sg:classifiers":[
        {
            "category":"Banks & Credit Unions",
            "subcategory":"Investment Brokerage",
            "type":"Services"
        }
    ],
    "sg:phone":"+1 201 291 1628",
    "sg:postcode":"07652",
    "sg:province":"NJ",
    "sg:tags":[
        "advisory",
        "financial"
    ],
    "wof:name":"Raymond James Financial Svc",
    "wof:placetype":"venue"
},
  "geometry": {"coordinates":[-74.07250999999999,40.916049],"type":"Point"}
}