{
  "type": "Feature",
  "properties": {
    "addr:full":"301 Hay Rd Manahawkin NJ 08050",
    "addr:housenumber":"301",
    "addr:postcode":"08050",
    "addr:street":"Hay Rd",
    "iso:country":"US",
    "sg:address":"301 Hay Rd",
    "sg:city":"Manahawkin",
    "sg:classifiers":[
        {
            "category":"Government",
            "subcategory":"Office",
            "type":"Public Place"
        }
    ],
    "sg:phone":"+1   ",
    "sg:postcode":"08050",
    "sg:province":"NJ",
    "sg:tags":[
        "executive"
    ],
    "wof:name":"Ocean County Road Department",
    "wof:placetype":"venue"
},
  "geometry": {"coordinates":[-74.290761,39.713898],"type":"Point"}
}