{
  "type": "Feature",
  "properties": {
    "iso:country":"US",
    "sg:address":"135 S Center St",
    "sg:city":"Orange",
    "sg:classifiers":[
        {
            "category":"Health Services",
            "subcategory":"Doctor",
            "type":"Services"
        }
    ],
    "sg:phone":"+1 973 672 0121",
    "sg:postcode":"07050",
    "sg:province":"NJ",
    "wof:name":"Cooper Joseph MD P A",
    "wof:placetype":"venue"
},
  "geometry": {"coordinates":[-74.23014999999999,40.768489],"type":"Point"}
}