{
  "type": "Feature",
  "properties": {
    "addr:full":"254 College Dr Edison NJ 08817",
    "addr:housenumber":"254",
    "addr:postcode":"08817",
    "addr:street":"College Dr",
    "iso:country":"US",
    "sg:address":"254 College Dr",
    "sg:city":"Edison",
    "sg:classifiers":[
        {
            "category":"Professional",
            "type":"Services"
        }
    ],
    "sg:phone":"+1 732 348 8819",
    "sg:postcode":"08817",
    "sg:province":"NJ",
    "sg:tags":[
        "transportation"
    ],
    "wof:name":"Agrawal Transport Inc",
    "wof:placetype":"venue"
},
  "geometry": {"coordinates":[-74.37382599999999,40.501786],"type":"Point"}
}