{
  "type": "Feature",
  "properties": {
    "iso:country":"US",
    "sg:address":"25 Harwood Rd",
    "sg:city":"Marlton",
    "sg:classifiers":[
        {
            "category":"Manufacturing",
            "subcategory":"Printing",
            "type":"Manufacturing & Wholesale Goods"
        }
    ],
    "sg:phone":"+1 856 988 9858",
    "sg:postcode":"08053",
    "sg:province":"NJ",
    "sg:tags":[
        "newspaper"
    ],
    "wof:name":"Landon Media Group Inc",
    "wof:placetype":"venue"
},
  "geometry": {"coordinates":[-74.899801,39.902649],"type":"Point"}
}