{
  "type": "Feature",
  "properties": {
    "iso:country":"US",
    "sg:address":"520 Chestnut Ave",
    "sg:city":"Trenton",
    "sg:classifiers":[
        {
            "category":"Education",
            "subcategory":"School",
            "type":"Public Place"
        }
    ],
    "sg:phone":"+1   ",
    "sg:postcode":"08611",
    "sg:province":"NJ",
    "sg:tags":[
        "organization",
        "religious"
    ],
    "wof:name":"Immaculate Conception School",
    "wof:placetype":"venue"
},
  "geometry": {"coordinates":[-74.747136,40.213191],"type":"Point"}
}