{
  "type": "Feature",
  "properties": {
    "addr:full":"92 Johnston Ave Kearny NJ 07032",
    "addr:housenumber":"92",
    "addr:postcode":"07032",
    "addr:street":"Johnston Ave",
    "iso:country":"US",
    "sg:address":"92 Johnston Ave",
    "sg:city":"Kearny",
    "sg:classifiers":[
        {
            "category":"Personal",
            "subcategory":"Beauty Salon",
            "type":"Services"
        }
    ],
    "sg:phone":"+1 201 998 0126",
    "sg:postcode":"07032",
    "sg:province":"NJ",
    "wof:name":"Ray's Hairdressers",
    "wof:placetype":"venue"
},
  "geometry": {"coordinates":[-74.15849300000001,40.752902],"type":"Point"}
}