{
  "type": "Feature",
  "properties": {
    "iso:country":"US",
    "sg:address":"100 Highland Ave",
    "sg:city":"Newark",
    "sg:classifiers":[
        {
            "category":"Building & Trades",
            "subcategory":"Construction",
            "type":"Services"
        }
    ],
    "sg:phone":"+1 973 481 6374",
    "sg:postcode":"07104",
    "sg:province":"NJ",
    "sg:tags":[
        "house"
    ],
    "wof:name":"Asencio Home Improvement",
    "wof:placetype":"venue"
},
  "geometry": {"coordinates":[-74.178614,40.758854],"type":"Point"}
}