{
  "type": "Feature",
  "properties": {
    "iso:country":"US",
    "sg:address":"2 Hillcrest Ave",
    "sg:city":"Millville",
    "sg:classifiers":[
        {
            "category":"Organizations",
            "subcategory":"Religious Organization",
            "type":"Services"
        }
    ],
    "sg:phone":"+1 856 825 1513",
    "sg:postcode":"08332",
    "sg:province":"NJ",
    "sg:tags":[
        "church"
    ],
    "wof:name":"St John Bosco C C D Office",
    "wof:placetype":"venue"
},
  "geometry": {"coordinates":[-75.07065799999999,39.396577],"type":"Point"}
}