{
  "type": "Feature",
  "properties": {
    "iso:country":"US",
    "sg:address":"683 Eayrestown Rd",
    "sg:city":"Lumberton",
    "sg:classifiers":[
        {
            "category":"Manufacturing",
            "subcategory":"Glass & Minerals",
            "type":"Manufacturing & Wholesale Goods"
        }
    ],
    "sg:phone":"+1 609 261 5448",
    "sg:postcode":"08048",
    "sg:province":"NJ",
    "sg:tags":[
        "refractory"
    ],
    "wof:name":"Milich Furnace Svc Inc",
    "wof:placetype":"venue"
},
  "geometry": {"coordinates":[-74.780778,39.968518],"type":"Point"}
}