{
  "type": "Feature",
  "properties": {
    "addr:full":"811 New Brunswick Ave Rahway NJ 07065",
    "addr:housenumber":"811",
    "addr:postcode":"07065",
    "addr:street":"New Brunswick Ave",
    "iso:country":"US",
    "sg:address":"811 New Brunswick Ave",
    "sg:city":"Rahway",
    "sg:classifiers":[
        {
            "category":"Retail",
            "subcategory":"Auto Repair",
            "type":"Services"
        }
    ],
    "sg:phone":"+1 732 388 2400",
    "sg:postcode":"07065",
    "sg:province":"NJ",
    "sg:tags":[
        "body",
        "shop",
        "automobile"
    ],
    "sg:website":"www.qualityautobody.net",
    "wof:name":"Quality Auto Body",
    "wof:placetype":"venue"
},
  "geometry": {"coordinates":[-74.2826,40.599098],"type":"Point"}
}