{
  "type": "Feature",
  "properties": {
    "addr:full":"40 E Main St Moorestown NJ 08057",
    "addr:housenumber":"40",
    "addr:postcode":"08057",
    "addr:street":"E Main St",
    "iso:country":"US",
    "sg:address":"40 E Main St",
    "sg:city":"Moorestown",
    "sg:classifiers":[
        {
            "category":"Professional",
            "subcategory":"Lawyer & Legal Services",
            "type":"Services"
        }
    ],
    "sg:phone":"+1 856 235 9433",
    "sg:postcode":"08057",
    "sg:province":"NJ",
    "sg:tags":[
        "attorney"
    ],
    "wof:name":"Begley & Gaskill",
    "wof:placetype":"venue"
},
  "geometry": {"coordinates":[-74.94431899999999,39.964738],"type":"Point"}
}