{
  "type": "Feature",
  "properties": {
    "iso:country":"US",
    "sg:address":"391 Central Ave",
    "sg:city":"Haledon",
    "sg:classifiers":[
        {
            "category":"Building & Trades",
            "subcategory":"Construction",
            "type":"Services"
        }
    ],
    "sg:phone":"+1 973 790 7457",
    "sg:postcode":"07508",
    "sg:province":"NJ",
    "sg:tags":[
        "residential"
    ],
    "wof:name":"Tom Terrific Residential Htg",
    "wof:placetype":"venue"
},
  "geometry": {"coordinates":[-74.19111100000001,40.93532],"type":"Point"}
}