{
  "type": "Feature",
  "properties": {
    "iso:country":"US",
    "sg:address":"26 Millburn Ave Ste 4",
    "sg:city":"Springfield",
    "sg:classifiers":[
        {
            "category":"Health Services",
            "subcategory":"Doctor",
            "type":"Services"
        }
    ],
    "sg:phone":"+1 973 258 1776",
    "sg:postcode":"07081",
    "sg:province":"NJ",
    "wof:name":"Morris Mark DO",
    "wof:placetype":"venue"
},
  "geometry": {"coordinates":[-74.324287,40.717504],"type":"Point"}
}