{
  "type": "Feature",
  "properties": {
    "addr:full":"2 Skyline Lake Dr Ringwood NJ 07456",
    "addr:housenumber":"2",
    "addr:postcode":"07456",
    "addr:street":"Skyline Lake Dr",
    "iso:country":"US",
    "sg:address":"2 Skyline Lake Dr",
    "sg:city":"Ringwood",
    "sg:classifiers":[
        {
            "category":"Restaurant",
            "type":"Food & Drink"
        }
    ],
    "sg:menulink":"http://www.allmenus.com/nj/ringwood/15739-luigis-pizza/menu/",
    "sg:phone":"+1 973 839 0268",
    "sg:postcode":"07456",
    "sg:province":"NJ",
    "sg:tags":[
        "italian"
    ],
    "wof:name":"Luigi's Pizza",
    "wof:placetype":"venue"
},
  "geometry": {"coordinates":[-74.282014,41.069665],"type":"Point"}
}