{
  "type": "Feature",
  "properties": {
    "iso:country":"US",
    "sg:address":"1236 Haddon Ave",
    "sg:city":"Camden",
    "sg:classifiers":[
        {
            "category":"Professional",
            "subcategory":"Employment Agencies",
            "type":"Services"
        }
    ],
    "sg:phone":"+1 856 541 5300",
    "sg:postcode":"08103",
    "sg:province":"NJ",
    "wof:name":"Problem Solvers Employment Service",
    "wof:placetype":"venue"
},
  "geometry": {"coordinates":[-75.10279800000001,39.931999],"type":"Point"}
}