{
  "type": "Feature",
  "properties": {
    "addr:full":"570 W Mount Pleasant Ave Livingston NJ 07039",
    "addr:housenumber":"570",
    "addr:postcode":"07039",
    "addr:street":"W Mount Pleasant Ave",
    "iso:country":"US",
    "sg:address":"570 W Mount Pleasant Ave",
    "sg:city":"Livingston",
    "sg:classifiers":[
        {
            "category":"Professional",
            "subcategory":"Lawyer & Legal Services",
            "type":"Services"
        }
    ],
    "sg:phone":"+1 973 994 6677",
    "sg:postcode":"07039",
    "sg:province":"NJ",
    "wof:name":"Hopkins Steven Lawyer",
    "wof:placetype":"venue"
},
  "geometry": {"coordinates":[-74.35169999999999,40.797501],"type":"Point"}
}