{
  "type": "Feature",
  "properties": {
    "addr:full":"6 E 20th St Paterson NJ 07513",
    "addr:housenumber":"6",
    "addr:postcode":"07513",
    "addr:street":"E 20Th St",
    "iso:country":"US",
    "sg:address":"6 E 20th St",
    "sg:city":"Paterson",
    "sg:classifiers":[
        {
            "category":"Organizations",
            "subcategory":"Religious Organization",
            "type":"Services"
        }
    ],
    "sg:phone":"+1   ",
    "sg:postcode":"07513",
    "sg:province":"NJ",
    "wof:name":"Central Baptist Church",
    "wof:placetype":"venue"
},
  "geometry": {"coordinates":[-74.156524,40.906739],"type":"Point"}
}