{
  "type": "Feature",
  "properties": {
    "addr:full":"251 Godwin Ave Midland Park NJ 07432",
    "addr:housenumber":"251",
    "addr:postcode":"07432",
    "addr:street":"Godwin Ave",
    "iso:country":"US",
    "sg:address":"251 Godwin Ave",
    "sg:city":"Midland Park",
    "sg:classifiers":[
        {
            "category":"Professional",
            "subcategory":"Business Services",
            "type":"Services"
        }
    ],
    "sg:phone":"+1 201 689 0700",
    "sg:postcode":"07432",
    "sg:province":"NJ",
    "sg:tags":[
        "embroidery"
    ],
    "wof:name":"Branding Time",
    "wof:placetype":"venue"
},
  "geometry": {"coordinates":[-74.141689,40.991183],"type":"Point"}
}