{
  "type": "Feature",
  "properties": {
    "addr:full":"19 Berkeley Sq Berkeley Heights NJ 07922",
    "addr:housenumber":"19",
    "addr:postcode":"07922",
    "addr:street":"Berkeley Sq",
    "iso:country":"US",
    "sg:address":"19 Berkeley Sq",
    "sg:city":"Berkeley Heights",
    "sg:classifiers":[
        {
            "category":"Insurance",
            "subcategory":"Insurance Agent",
            "type":"Services"
        }
    ],
    "sg:phone":"+1   ",
    "sg:postcode":"07922",
    "sg:province":"NJ",
    "wof:name":"Dorchester Assocs",
    "wof:placetype":"venue"
},
  "geometry": {"coordinates":[-74.420354,40.67239],"type":"Point"}
}