{
  "type": "Feature",
  "properties": {
    "addr:full":"379 Highland St Cresskill NJ 07626",
    "addr:housenumber":"379",
    "addr:postcode":"07626",
    "addr:street":"Highland St",
    "iso:country":"US",
    "sg:address":"379 Highland St",
    "sg:city":"Cresskill",
    "sg:classifiers":[
        {
            "category":"Building & Trades",
            "subcategory":"Construction",
            "type":"Services"
        }
    ],
    "sg:phone":"+1 201 568 8577",
    "sg:postcode":"07626",
    "sg:province":"NJ",
    "sg:tags":[
        "house"
    ],
    "wof:name":"Twl Home Improvement Resources",
    "wof:placetype":"venue"
},
  "geometry": {"coordinates":[-73.972497,40.947254],"type":"Point"}
}