{
  "type": "Feature",
  "properties": {
    "iso:country":"US",
    "sg:address":"288 N Broad St",
    "sg:city":"Elizabeth",
    "sg:classifiers":[
        {
            "category":"Building & Trades",
            "subcategory":"Equipment Rental",
            "type":"Services"
        }
    ],
    "sg:phone":"+1 908 354 3600",
    "sg:postcode":"07208",
    "sg:province":"NJ",
    "sg:tags":[
        "leasing"
    ],
    "wof:name":"Bovis Lend Lease Inc",
    "wof:placetype":"venue"
},
  "geometry": {"coordinates":[-74.215401,40.667786],"type":"Point"}
}