{
  "type": "Feature",
  "properties": {
    "addr:full":"227 US Hwy 206 Flanders NJ 07836",
    "addr:housenumber":"227",
    "addr:postcode":"07836",
    "addr:street":"Us Hwy 206",
    "iso:country":"US",
    "sg:address":"227 US Hwy 206",
    "sg:city":"Flanders",
    "sg:classifiers":[
        {
            "category":"Manufacturing",
            "subcategory":"Tools & Machinery",
            "type":"Manufacturing & Wholesale Goods"
        }
    ],
    "sg:phone":"+1 973 927 5592",
    "sg:postcode":"07836",
    "sg:province":"NJ",
    "sg:tags":[
        "instrument",
        "surgical"
    ],
    "wof:name":"Karl Storz Endoscopy Inc",
    "wof:placetype":"venue"
},
  "geometry": {"coordinates":[-74.709311,40.837044],"type":"Point"}
}