{
  "type": "Feature",
  "properties": {
    "iso:country":"US",
    "sg:address":"10 Molly Stark Dr",
    "sg:city":"Morristown",
    "sg:classifiers":[
        {
            "category":"Professional",
            "type":"Services"
        }
    ],
    "sg:phone":"+1 973 455 1004",
    "sg:postcode":"07960",
    "sg:province":"NJ",
    "sg:tags":[
        "writer"
    ],
    "wof:name":"Prose Pro's",
    "wof:placetype":"venue"
},
  "geometry": {"coordinates":[-74.49209500000001,40.791779],"type":"Point"}
}