{
  "type": "Feature",
  "properties": {
    "iso:country":"US",
    "sg:address":"3729 Bayshore Rd",
    "sg:city":"Cape May",
    "sg:classifiers":[
        {
            "category":"Food & Beverages",
            "subcategory":"Groceries & Convenience Stores",
            "type":"Retail Goods"
        }
    ],
    "sg:phone":"+1   ",
    "sg:postcode":"08204",
    "sg:province":"NJ",
    "wof:name":"Wawa 483",
    "wof:placetype":"venue"
},
  "geometry": {"coordinates":[-74.942037,38.982802],"type":"Point"}
}