{
  "type": "Feature",
  "properties": {
    "iso:country":"US",
    "sg:address":"161 Heywood Ave",
    "sg:city":"Orange",
    "sg:classifiers":[
        {
            "category":"Professional",
            "subcategory":"Printing & Photocopies",
            "type":"Services"
        }
    ],
    "sg:phone":"+1 973 673 9411",
    "sg:postcode":"07050",
    "sg:province":"NJ",
    "sg:tags":[
        "duplicating",
        "copying"
    ],
    "wof:name":"Mt Olive Hour Of Power",
    "wof:placetype":"venue"
},
  "geometry": {"coordinates":[-74.239745,40.754043],"type":"Point"}
}