{
  "type": "Feature",
  "properties": {
    "iso:country":"US",
    "sg:address":"3649 Reading Ave",
    "sg:city":"Hammonton",
    "sg:classifiers":[
        {
            "category":"Wholesale",
            "subcategory":"Computers",
            "type":"Manufacturing & Wholesale Goods"
        }
    ],
    "sg:phone":"+1 609 567 0565",
    "sg:postcode":"08037",
    "sg:province":"NJ",
    "wof:name":"A&M Services",
    "wof:placetype":"venue"
},
  "geometry": {"coordinates":[-74.749157,39.59385],"type":"Point"}
}