{
  "type": "Feature",
  "properties": {
    "iso:country":"US",
    "sg:address":"29 Carlow Way",
    "sg:city":"Hazlet",
    "sg:classifiers":[
        {
            "category":"Real Estate",
            "subcategory":"Developer",
            "type":"Services"
        }
    ],
    "sg:phone":"+1   ",
    "sg:postcode":"07730",
    "sg:province":"NJ",
    "wof:name":"Stone Development Inc",
    "wof:placetype":"venue"
},
  "geometry": {"coordinates":[-74.206608,40.415749],"type":"Point"}
}