{
  "type": "Feature",
  "properties": {
    "iso:country":"US",
    "sg:address":"6000 US Hwy 130",
    "sg:city":"Delran",
    "sg:classifiers":[
        {
            "category":"Wholesale",
            "subcategory":"Electrical",
            "type":"Manufacturing & Wholesale Goods"
        }
    ],
    "sg:phone":"+1 856 461 5076",
    "sg:postcode":"08075",
    "sg:province":"NJ",
    "sg:tags":[
        "telecommunication"
    ],
    "wof:name":"CTS Telecommunication",
    "wof:placetype":"venue"
},
  "geometry": {"coordinates":[-74.94609199999999,40.019901],"type":"Point"}
}