{
  "type": "Feature",
  "properties": {
    "iso:country":"US",
    "sg:address":"265 Park Ave",
    "sg:city":"Nutley",
    "sg:classifiers":[
        {
            "category":"Building & Trades",
            "subcategory":"Construction",
            "type":"Services"
        }
    ],
    "sg:phone":"+1 973 667 0584",
    "sg:postcode":"07110",
    "sg:province":"NJ",
    "sg:tags":[
        "masonry",
        "contractor"
    ],
    "wof:name":"Carmen Micciche Construction",
    "wof:placetype":"venue"
},
  "geometry": {"coordinates":[-74.150751,40.813024],"type":"Point"}
}