{
  "type": "Feature",
  "properties": {
    "addr:full":"189 New Brunswick Ave Perth Amboy NJ 08861",
    "addr:housenumber":"189",
    "addr:postcode":"08861",
    "addr:street":"New Brunswick Ave",
    "iso:country":"US",
    "sg:address":"189 New Brunswick Ave",
    "sg:city":"Perth Amboy",
    "sg:classifiers":[
        {
            "category":"Autos & Motor Vehicles",
            "subcategory":"Auto Supplies",
            "type":"Retail Goods"
        }
    ],
    "sg:phone":"+1 732 324 2244",
    "sg:postcode":"08861",
    "sg:province":"NJ",
    "sg:tags":[
        "automobile",
        "accessory"
    ],
    "wof:name":"Cars Glow",
    "wof:placetype":"venue"
},
  "geometry": {"coordinates":[-74.269347,40.511147],"type":"Point"}
}