{
  "type": "Feature",
  "properties": {
    "iso:country":"US",
    "sg:address":"160 Lawrenceville Pennington Rd",
    "sg:city":"Lawrenceville",
    "sg:classifiers":[
        {
            "category":"Shopping",
            "subcategory":"Pharmacy",
            "type":"Retail Goods"
        },
        {
            "category":"Shopping",
            "subcategory":"Gifts & Souvenirs",
            "type":"Retail Goods"
        }
    ],
    "sg:phone":"+1 609 895 0444",
    "sg:postcode":"08648",
    "sg:province":"NJ",
    "sg:tags":[
        "cards",
        "greeting"
    ],
    "wof:name":"Penlar Pharmacy",
    "wof:placetype":"venue"
},
  "geometry": {"coordinates":[-74.74875400000001,40.301548],"type":"Point"}
}