{
  "type": "Feature",
  "properties": {
    "iso:country":"US",
    "sg:address":"127 Passaic Ave",
    "sg:city":"Passaic",
    "sg:classifiers":[
        {
            "category":"Deli",
            "type":"Food & Drink"
        }
    ],
    "sg:phone":"+1 973 779 6581",
    "sg:postcode":"07055",
    "sg:province":"NJ",
    "wof:name":"Win City Mini Mart",
    "wof:placetype":"venue"
},
  "geometry": {"coordinates":[-74.129099,40.856304],"type":"Point"}
}