{
  "type": "Feature",
  "properties": {
    "iso:country":"US",
    "sg:address":"324 Duncan Ave",
    "sg:city":"Jersey City",
    "sg:classifiers":[
        {
            "category":"Government",
            "subcategory":"Office",
            "type":"Public Place"
        }
    ],
    "sg:phone":"+1   ",
    "sg:postcode":"07306",
    "sg:province":"NJ",
    "sg:tags":[
        "housing",
        "program"
    ],
    "wof:name":"A Harry Moore APT",
    "wof:placetype":"venue"
},
  "geometry": {"coordinates":[-74.083534,40.729766],"type":"Point"}
}