{
  "type": "Feature",
  "properties": {
    "addr:full":"118 Watchung Ave Montclair NJ 07043",
    "addr:housenumber":"118",
    "addr:postcode":"07043",
    "addr:street":"Watchung Ave",
    "iso:country":"US",
    "sg:address":"118 Watchung Ave",
    "sg:city":"Montclair",
    "sg:classifiers":[
        {
            "category":"Parking",
            "type":"Transportation"
        },
        {
            "category":"Personal",
            "type":"Services"
        },
        {
            "category":"Retail",
            "subcategory":"Auto Repair",
            "type":"Services"
        }
    ],
    "sg:phone":"+1 973 744 5200",
    "sg:postcode":"07043",
    "sg:province":"NJ",
    "sg:tags":[
        "towing"
    ],
    "wof:name":"Covello Sam Garage",
    "wof:placetype":"venue"
},
  "geometry": {"coordinates":[-74.206001,40.830601],"type":"Point"}
}