{
  "type": "Feature",
  "properties": {
    "addr:full":"145 Copper Hill Rd Ringoes NJ 08551",
    "addr:housenumber":"145",
    "addr:postcode":"08551",
    "addr:street":"Copper Hill Rd",
    "iso:country":"US",
    "sg:address":"145 Copper Hill Rd",
    "sg:city":"Ringoes",
    "sg:classifiers":[
        {
            "category":"Professional",
            "type":"Services"
        }
    ],
    "sg:phone":"+1 908 284 9462",
    "sg:postcode":"08551",
    "sg:province":"NJ",
    "sg:tags":[
        "establishment"
    ],
    "wof:name":"Neshanic Technologies Inc",
    "wof:placetype":"venue"
},
  "geometry": {"coordinates":[-74.867413,40.467725],"type":"Point"}
}