{
  "type": "Feature",
  "properties": {
    "addr:full":"821 Riverview Dr Brielle NJ 08730",
    "addr:housenumber":"821",
    "addr:postcode":"08730",
    "addr:street":"Riverview Dr",
    "iso:country":"US",
    "sg:address":"821 Riverview Dr",
    "sg:city":"Brielle",
    "sg:classifiers":[
        {
            "category":"Social Services",
            "subcategory":"Child Care",
            "type":"Services"
        }
    ],
    "sg:phone":"+1 732 528 6404",
    "sg:postcode":"08730",
    "sg:province":"NJ",
    "sg:tags":[
        "kindergarten",
        "academic",
        "school"
    ],
    "wof:name":"School In Brielle",
    "wof:placetype":"venue"
},
  "geometry": {"coordinates":[-74.060502,40.104724],"type":"Point"}
}