{
  "type": "Feature",
  "properties": {
    "iso:country":"US",
    "sg:address":"39 Central Ave",
    "sg:city":"Linwood",
    "sg:classifiers":[
        {
            "category":"Real Estate",
            "subcategory":"Real Estate Agent",
            "type":"Services"
        }
    ],
    "sg:phone":"+1 609 653 6969",
    "sg:postcode":"08221",
    "sg:province":"NJ",
    "sg:tags":[
        "appraiser"
    ],
    "wof:name":"Brian Musto & Co",
    "wof:placetype":"venue"
},
  "geometry": {"coordinates":[-74.562693,39.357573],"type":"Point"}
}