{
  "type": "Feature",
  "properties": {
    "addr:full":"7 Sylvan Way Caldwell NJ 07006",
    "addr:housenumber":"7",
    "addr:postcode":"07006",
    "addr:street":"Sylvan Way",
    "iso:country":"US",
    "sg:address":"7 Sylvan Way",
    "sg:city":"Caldwell",
    "sg:classifiers":[
        {
            "category":"Building & Trades",
            "subcategory":"Plumbing",
            "type":"Services"
        }
    ],
    "sg:phone":"+1 973 403 7557",
    "sg:postcode":"07006",
    "sg:province":"NJ",
    "sg:tags":[
        "contractor"
    ],
    "wof:name":"EMR Plumbing LLC",
    "wof:placetype":"venue"
},
  "geometry": {"coordinates":[-74.27320899999999,40.855144],"type":"Point"}
}