{
  "type": "Feature",
  "properties": {
    "addr:full":"796 Court St Franklin Lakes NJ 07417",
    "addr:housenumber":"796",
    "addr:postcode":"07417",
    "addr:street":"Court St",
    "iso:country":"US",
    "sg:address":"796 Court St",
    "sg:city":"Franklin Lakes",
    "sg:classifiers":[
        {
            "category":"Professional",
            "type":"Services"
        }
    ],
    "sg:phone":"+1 201 847 9994",
    "sg:postcode":"07417",
    "sg:province":"NJ",
    "sg:tags":[
        "establishment"
    ],
    "wof:name":"B & D Development Inc",
    "wof:placetype":"venue"
},
  "geometry": {"coordinates":[-74.207284,41.022109],"type":"Point"}
}