{
  "type": "Feature",
  "properties": {
    "iso:country":"US",
    "sg:address":"8 Quakerbridge Plz",
    "sg:city":"Trenton",
    "sg:classifiers":[
        {
            "category":"Shopping",
            "type":"Retail Goods"
        }
    ],
    "sg:phone":"+1 609 890 1726",
    "sg:postcode":"08619",
    "sg:province":"NJ",
    "sg:tags":[
        "hearing",
        "equipment",
        "supply",
        "merchandise",
        "impaired"
    ],
    "wof:name":"Bucks Mercer Hearing Centers",
    "wof:placetype":"venue"
},
  "geometry": {"coordinates":[-74.682203,40.25365],"type":"Point"}
}