{
  "type": "Feature",
  "properties": {
    "iso:country":"US",
    "sg:address":"125 Prospect Ave",
    "sg:city":"Hackensack",
    "sg:classifiers":[
        {
            "category":"Professional",
            "subcategory":"Lawyer & Legal Services",
            "type":"Services"
        }
    ],
    "sg:phone":"+1 201 488 3830",
    "sg:postcode":"07601",
    "sg:province":"NJ",
    "wof:name":"Youderian John A Jr Attorney",
    "wof:placetype":"venue"
},
  "geometry": {"coordinates":[-74.056297,40.887299],"type":"Point"}
}