{
  "type": "Feature",
  "properties": {
    "iso:country":"US",
    "sg:address":"200 Emerald Ave",
    "sg:city":"Haddon Township",
    "sg:classifiers":[
        {
            "category":"Social Services",
            "subcategory":"Child Care",
            "type":"Services"
        },
        {
            "category":"Education",
            "subcategory":"Preschool",
            "type":"Public Place"
        },
        {
            "category":"Education",
            "subcategory":"School",
            "type":"Public Place"
        }
    ],
    "sg:phone":"+1 856 858 2300",
    "sg:postcode":"08108",
    "sg:province":"NJ",
    "sg:tags":[
        "elementary",
        "day"
    ],
    "wof:name":"Little People Learning Center",
    "wof:placetype":"venue"
},
  "geometry": {"coordinates":[-75.056602,39.917999],"type":"Point"}
}