{
  "type": "Feature",
  "properties": {
    "iso:country":"US",
    "sg:address":"1 Elmwood Ln",
    "sg:city":"Washington",
    "sg:classifiers":[
        {
            "category":"Wholesale",
            "subcategory":"Chemicals & Plastics",
            "type":"Manufacturing & Wholesale Goods"
        }
    ],
    "sg:phone":"+1 908 689 3885",
    "sg:postcode":"07882",
    "sg:province":"NJ",
    "sg:tags":[
        "textile",
        "dyer"
    ],
    "wof:name":"World Wide Dyeworks Inc",
    "wof:placetype":"venue"
},
  "geometry": {"coordinates":[-74.96032,40.739724],"type":"Point"}
}