{
  "type": "Feature",
  "properties": {
    "addr:full":"2 Heritage Ct Long Valley NJ 07853",
    "addr:housenumber":"2",
    "addr:postcode":"07853",
    "addr:street":"Heritage Ct",
    "iso:country":"US",
    "sg:address":"2 Heritage Ct",
    "sg:city":"Long Valley",
    "sg:classifiers":[
        {
            "category":"Personal",
            "type":"Services"
        }
    ],
    "sg:phone":"+1   ",
    "sg:postcode":"07853",
    "sg:province":"NJ",
    "wof:name":"Hometown Handyman",
    "wof:placetype":"venue"
},
  "geometry": {"coordinates":[-74.78233,40.820364],"type":"Point"}
}