{
  "type": "Feature",
  "properties": {
    "addr:full":"235 River Rd New Milford NJ 07646",
    "addr:housenumber":"235",
    "addr:postcode":"07646",
    "addr:street":"River Rd",
    "iso:country":"US",
    "sg:address":"235 River Rd",
    "sg:city":"New Milford",
    "sg:classifiers":[
        {
            "category":"Retail",
            "subcategory":"Auto Repair",
            "type":"Services"
        }
    ],
    "sg:phone":"+1 201 261 9499",
    "sg:postcode":"07646",
    "sg:province":"NJ",
    "sg:tags":[
        "repairing",
        "automobile",
        "general"
    ],
    "wof:name":"B & E Auto",
    "wof:placetype":"venue"
},
  "geometry": {"coordinates":[-74.020201,40.943925],"type":"Point"}
}