{
  "type": "Feature",
  "properties": {
    "iso:country":"US",
    "sg:address":"1445 Seminole Rd",
    "sg:city":"North Brunswick",
    "sg:classifiers":[
        {
            "category":"Professional",
            "subcategory":"Computer Services",
            "type":"Services"
        }
    ],
    "sg:phone":"+1   ",
    "sg:postcode":"08902",
    "sg:province":"NJ",
    "sg:tags":[
        "related"
    ],
    "wof:name":"Cathleen Whalen",
    "wof:placetype":"venue"
},
  "geometry": {"coordinates":[-74.494204,40.46663],"type":"Point"}
}