{
  "type": "Feature",
  "properties": {
    "iso:country":"US",
    "sg:address":"87 S Main St",
    "sg:city":"Marlboro",
    "sg:classifiers":[
        {
            "category":"Restaurant",
            "type":"Food & Drink"
        }
    ],
    "sg:phone":"+1 732 761 1999",
    "sg:postcode":"07746",
    "sg:province":"NJ",
    "sg:tags":[
        "delicatessen"
    ],
    "wof:name":"Symphony Cafe & Deli",
    "wof:placetype":"venue"
},
  "geometry": {"coordinates":[-74.254508,40.299997],"type":"Point"}
}