{
  "type": "Feature",
  "properties": {
    "addr:full":"360 Somerset St Stirling NJ 07980",
    "addr:housenumber":"360",
    "addr:postcode":"07980",
    "addr:street":"Somerset St",
    "iso:country":"US",
    "sg:address":"360 Somerset St",
    "sg:city":"Stirling",
    "sg:classifiers":[
        {
            "category":"Utilities",
            "subcategory":"Telephone",
            "type":"Services"
        }
    ],
    "sg:phone":"+1 908 647 0374",
    "sg:postcode":"07980",
    "sg:province":"NJ",
    "sg:tags":[
        "communications"
    ],
    "wof:name":"Tronics",
    "wof:placetype":"venue"
},
  "geometry": {"coordinates":[-74.496734,40.673027],"type":"Point"}
}