{
  "type": "Feature",
  "properties": {
    "iso:country":"US",
    "sg:address":"227 Grant Ave",
    "sg:city":"Eatontown",
    "sg:classifiers":[
        {
            "category":"Professional",
            "subcategory":"Business Services",
            "type":"Services"
        }
    ],
    "sg:phone":"+1   ",
    "sg:postcode":"07724",
    "sg:province":"NJ",
    "wof:name":"Hire Precision Partners",
    "wof:placetype":"venue"
},
  "geometry": {"coordinates":[-74.06542,40.28634],"type":"Point"}
}