{
  "type": "Feature",
  "properties": {
    "addr:full":"377 Mechlin Corner Rd Pittstown NJ 08867",
    "addr:housenumber":"377",
    "addr:postcode":"08867",
    "addr:street":"Mechlin Corner Rd",
    "iso:country":"US",
    "sg:address":"377 Mechlin Corner Rd",
    "sg:city":"Pittstown",
    "sg:classifiers":[
        {
            "category":"Home & Garden",
            "subcategory":"Garden Supply",
            "type":"Retail Goods"
        }
    ],
    "sg:phone":"+1   ",
    "sg:postcode":"08867",
    "sg:province":"NJ",
    "sg:tags":[
        "plant",
        "related"
    ],
    "wof:name":"Stony Brook Nursery & Grdn Ctr",
    "wof:placetype":"venue"
},
  "geometry": {"coordinates":[-75.008145,40.583396],"type":"Point"}
}