{
  "type": "Feature",
  "properties": {
    "addr:full":"769 W Bay Ave Barnegat NJ 08005",
    "addr:housenumber":"769",
    "addr:postcode":"08005",
    "addr:street":"W Bay Ave",
    "iso:country":"US",
    "sg:address":"769 W Bay Ave",
    "sg:city":"Barnegat",
    "sg:classifiers":[
        {
            "category":"Building & Trades",
            "subcategory":"Electrical",
            "type":"Services"
        }
    ],
    "sg:phone":"+1 609 698 8631",
    "sg:postcode":"08005",
    "sg:province":"NJ",
    "sg:tags":[
        "electrical",
        "contractor"
    ],
    "wof:name":"Zips Electric LLC",
    "wof:placetype":"venue"
},
  "geometry": {"coordinates":[-74.229551,39.754528],"type":"Point"}
}