{
  "type": "Feature",
  "properties": {
    "addr:full":"1510 Park Ave South Plainfield NJ 07080",
    "addr:housenumber":"1510",
    "addr:postcode":"07080",
    "addr:street":"Park Ave",
    "iso:country":"US",
    "sg:address":"1510 Park Ave",
    "sg:city":"South Plainfield",
    "sg:classifiers":[
        {
            "category":"Banks & Credit Unions",
            "subcategory":"Bank",
            "type":"Services"
        }
    ],
    "sg:phone":"+1 908 754 2500",
    "sg:postcode":"07080",
    "sg:province":"NJ",
    "sg:tags":[
        "loan"
    ],
    "sg:website":"www.p-f-s.com",
    "wof:name":"PFS Patient Financing Inc",
    "wof:placetype":"venue"
},
  "geometry": {"coordinates":[-74.402067,40.599602],"type":"Point"}
}