{
  "type": "Feature",
  "properties": {
    "iso:country":"US",
    "sg:address":"118 Creek Rd",
    "sg:city":"Mount Laurel",
    "sg:classifiers":[
        {
            "category":"Home & Garden",
            "subcategory":"Furniture",
            "type":"Retail Goods"
        }
    ],
    "sg:phone":"+1 856 235 1830",
    "sg:postcode":"08054",
    "sg:province":"NJ",
    "sg:tags":[
        "lighting",
        "fixture",
        "mfg"
    ],
    "wof:name":"Spencers",
    "wof:placetype":"venue"
},
  "geometry": {"coordinates":[-74.860018,39.981881],"type":"Point"}
}