{
  "type": "Feature",
  "properties": {
    "addr:full":"408 Berkeley Ave Beachwood NJ 08722",
    "addr:housenumber":"408",
    "addr:postcode":"08722",
    "addr:street":"Berkeley Ave",
    "iso:country":"US",
    "sg:address":"408 Berkeley Ave",
    "sg:city":"Beachwood",
    "sg:classifiers":[
        {
            "category":"Arts & Performance",
            "subcategory":"Theater",
            "type":"Entertainment"
        }
    ],
    "sg:phone":"+1   ",
    "sg:postcode":"08722",
    "sg:province":"NJ",
    "sg:tags":[
        "group"
    ],
    "wof:name":"Matthew Dwinells",
    "wof:placetype":"venue"
},
  "geometry": {"coordinates":[-74.18705199999999,39.929538],"type":"Point"}
}