{
  "type": "Feature",
  "properties": {
    "iso:country":"US",
    "sg:address":"625 Lafayette Ave",
    "sg:city":"Hawthorne",
    "sg:classifiers":[
        {
            "category":"Health Services",
            "subcategory":"Doctor",
            "type":"Services"
        }
    ],
    "sg:phone":"+1 973 238 0055",
    "sg:postcode":"07506",
    "sg:province":"NJ",
    "sg:tags":[
        "medical"
    ],
    "wof:name":"Joseph W Montagnino MD",
    "wof:placetype":"venue"
},
  "geometry": {"coordinates":[-74.155535,40.958903],"type":"Point"}
}