{
  "type": "Feature",
  "properties": {
    "iso:country":"US",
    "sg:address":"120 McGaw Dr",
    "sg:city":"Edison",
    "sg:classifiers":[
        {
            "category":"Personal",
            "subcategory":"Beauty Salon",
            "type":"Services"
        }
    ],
    "sg:phone":"+1   ",
    "sg:postcode":"08837",
    "sg:province":"NJ",
    "sg:tags":[
        "shop"
    ],
    "wof:name":"Mario Badescu Skin Care Inc",
    "wof:placetype":"venue"
},
  "geometry": {"coordinates":[-74.33475900000001,40.519194],"type":"Point"}
}