{
  "type": "Feature",
  "properties": {
    "addr:full":"1624 Shady Ln Toms River NJ 08753",
    "addr:housenumber":"1624",
    "addr:postcode":"08753",
    "addr:street":"Shady Ln",
    "iso:country":"US",
    "sg:address":"1624 Shady Ln",
    "sg:city":"Toms River",
    "sg:classifiers":[
        {
            "category":"Building & Trades",
            "subcategory":"Construction",
            "type":"Services"
        }
    ],
    "sg:phone":"+1 732 270 3302",
    "sg:postcode":"08753",
    "sg:province":"NJ",
    "sg:tags":[
        "house"
    ],
    "wof:name":"Mel Cain Building Contractors",
    "wof:placetype":"venue"
},
  "geometry": {"coordinates":[-74.151568,39.957479],"type":"Point"}
}