{
  "type": "Feature",
  "properties": {
    "iso:country":"US",
    "sg:address":"880 Delsea Dr N",
    "sg:city":"Glassboro",
    "sg:classifiers":[
        {
            "category":"Restaurant",
            "type":"Food & Drink"
        }
    ],
    "sg:phone":"+1 856 881 6612",
    "sg:postcode":"08028",
    "sg:province":"NJ",
    "wof:name":"Golden Dragon Chinese Rstrnt",
    "wof:placetype":"venue"
},
  "geometry": {"coordinates":[-75.11582,39.723995],"type":"Point"}
}