{
  "type": "Feature",
  "properties": {
    "addr:full":"1115 US Hwy 46 Ledgewood NJ 07852",
    "addr:housenumber":"1115",
    "addr:postcode":"07852",
    "addr:street":"Us Hwy 46",
    "iso:country":"US",
    "sg:address":"1115 US Hwy 46",
    "sg:city":"Ledgewood",
    "sg:classifiers":[
        {
            "category":"Freight",
            "type":"Transportation"
        }
    ],
    "sg:phone":"+1 973 584 3555",
    "sg:postcode":"07852",
    "sg:province":"NJ",
    "sg:tags":[
        "commercial",
        "storage"
    ],
    "wof:name":"A-1 Self Storage Systems",
    "wof:placetype":"venue"
},
  "geometry": {"coordinates":[-74.64292,40.879236],"type":"Point"}
}