{
  "type": "Feature",
  "properties": {
    "addr:full":"495 Union Ave Middlesex NJ 08846",
    "addr:housenumber":"495",
    "addr:postcode":"08846",
    "addr:street":"Union Ave",
    "iso:country":"US",
    "sg:address":"495 Union Ave",
    "sg:city":"Middlesex",
    "sg:classifiers":[
        {
            "category":"Professional",
            "subcategory":"Accounting & Tax Preparation",
            "type":"Services"
        }
    ],
    "sg:phone":"+1 732 302 9800",
    "sg:postcode":"08846",
    "sg:province":"NJ",
    "sg:tags":[
        "accountant"
    ],
    "wof:name":"Sharon L Roma CPA",
    "wof:placetype":"venue"
},
  "geometry": {"coordinates":[-74.510198,40.573399],"type":"Point"}
}