{
  "type": "Feature",
  "properties": {
    "iso:country":"US",
    "sg:address":"376 Hollywood Ave",
    "sg:city":"Fairfield",
    "sg:classifiers":[
        {
            "category":"Juice Bar",
            "subcategory":"None",
            "type":"Food & Drink"
        },
        {
            "category":"Professional",
            "type":"Services"
        }
    ],
    "sg:phone":"+1 973 226 0080",
    "sg:postcode":"07004",
    "sg:province":"NJ",
    "sg:tags":[
        "smoothy",
        "caterer"
    ],
    "wof:name":"Soup To Nuts Catering",
    "wof:placetype":"venue"
},
  "geometry": {"coordinates":[-74.292603,40.8839],"type":"Point"}
}