{
  "type": "Feature",
  "properties": {
    "iso:country":"US",
    "sg:address":"291 Martin Luther King Jr Dr",
    "sg:city":"Jersey City",
    "sg:classifiers":[
        {
            "category":"Education",
            "subcategory":"Library",
            "type":"Public Place"
        }
    ],
    "sg:phone":"+1 201 547 4555",
    "sg:postcode":"07305",
    "sg:province":"NJ",
    "wof:name":"Claremont Library",
    "wof:placetype":"venue"
},
  "geometry": {"coordinates":[-74.08102599999999,40.709226],"type":"Point"}
}