{
  "type": "Feature",
  "properties": {
    "addr:full":"342 Garden St Hoboken NJ 07030",
    "addr:housenumber":"342",
    "addr:postcode":"07030",
    "addr:street":"Garden St",
    "iso:country":"US",
    "sg:address":"342 Garden St",
    "sg:city":"Hoboken",
    "sg:classifiers":[
        {
            "category":"Restaurant",
            "type":"Food & Drink"
        }
    ],
    "sg:menulink":"http://www.allmenus.com/nj/hoboken/247614-7-stars-pizzeria/menu/",
    "sg:phone":"+1 201 653 7204",
    "sg:postcode":"07030",
    "sg:province":"NJ",
    "sg:tags":[
        "american",
        "wing",
        "pizza"
    ],
    "wof:name":"7 Stars Pizzeria",
    "wof:placetype":"venue"
},
  "geometry": {"coordinates":[-74.031785,40.74153],"type":"Point"}
}