{
  "type": "Feature",
  "properties": {
    "addr:full":"500 49th St Pennsauken NJ 08110",
    "addr:housenumber":"500",
    "addr:postcode":"08110",
    "addr:street":"49Th St",
    "iso:country":"US",
    "sg:address":"500 49th St",
    "sg:city":"Pennsauken",
    "sg:classifiers":[
        {
            "category":"Retail",
            "subcategory":"Auto Repair",
            "type":"Services"
        }
    ],
    "sg:phone":"+1 856 665 8135",
    "sg:postcode":"08110",
    "sg:province":"NJ",
    "sg:tags":[
        "repairing",
        "automobile",
        "automotive"
    ],
    "wof:name":"Mark's Automotive",
    "wof:placetype":"venue"
},
  "geometry": {"coordinates":[-75.070801,39.964802],"type":"Point"}
}