{
  "type": "Feature",
  "properties": {
    "addr:full":"145 Fairfield Rd Fairfield NJ 07004",
    "addr:housenumber":"145",
    "addr:postcode":"07004",
    "addr:street":"Fairfield Rd",
    "iso:country":"US",
    "sg:address":"145 Fairfield Rd",
    "sg:city":"Fairfield",
    "sg:classifiers":[
        {
            "category":"Professional",
            "type":"Services"
        }
    ],
    "sg:phone":"+1 212 267 4524",
    "sg:postcode":"07004",
    "sg:province":"NJ",
    "sg:tags":[
        "establishment"
    ],
    "wof:name":"Hydro Air Inc",
    "wof:placetype":"venue"
},
  "geometry": {"coordinates":[-74.297275,40.875138],"type":"Point"}
}