{
  "type": "Feature",
  "properties": {
    "iso:country":"US",
    "sg:address":"27 Horseneck Rd",
    "sg:city":"Fairfield",
    "sg:classifiers":[
        {
            "category":"Arts & Performance",
            "subcategory":"Theater",
            "type":"Entertainment"
        },
        {
            "category":"Banks & Credit Unions",
            "subcategory":"Financial Services",
            "type":"Services"
        }
    ],
    "sg:phone":"+1 973 575 6570",
    "sg:postcode":"07004",
    "sg:province":"NJ",
    "sg:tags":[
        "entertainer",
        "company",
        "holding"
    ],
    "wof:name":"Platinum Ventures Group LLC",
    "wof:placetype":"venue"
},
  "geometry": {"coordinates":[-74.297264,40.87697],"type":"Point"}
}