{
  "type": "Feature",
  "properties": {
    "iso:country":"US",
    "sg:address":"2300 N Route 9",
    "sg:city":"Cape May Court House",
    "sg:classifiers":[
        {
            "category":"Home & Garden",
            "subcategory":"Furniture",
            "type":"Retail Goods"
        }
    ],
    "sg:phone":"+1 609 624 3988",
    "sg:postcode":"08210",
    "sg:province":"NJ",
    "sg:tags":[
        "store"
    ],
    "sg:website":"www.charlesharveyfurniture.com",
    "wof:name":"Charles Harvey Home Furnishings",
    "wof:placetype":"venue"
},
  "geometry": {"coordinates":[-74.750759,39.159808],"type":"Point"}
}