{
  "type": "Feature",
  "properties": {
    "addr:full":"2106 State Rte 35 Sea Girt NJ 08750",
    "addr:housenumber":"2106",
    "addr:postcode":"08750",
    "addr:street":"State Rte 35",
    "iso:country":"US",
    "sg:address":"2106 State Rte 35",
    "sg:city":"Sea Girt",
    "sg:classifiers":[
        {
            "category":"Professional",
            "subcategory":"Lawyer & Legal Services",
            "type":"Services"
        }
    ],
    "sg:phone":"+1 732 449 5764",
    "sg:postcode":"08750",
    "sg:province":"NJ",
    "sg:tags":[
        "attorney"
    ],
    "wof:name":"Access To Money",
    "wof:placetype":"venue"
},
  "geometry": {"coordinates":[-74.061081,40.141066],"type":"Point"}
}