{
  "type": "Feature",
  "properties": {
    "addr:full":"641 15th Ave Newark NJ 07103",
    "addr:housenumber":"641",
    "addr:postcode":"07103",
    "addr:street":"15Th Ave",
    "iso:country":"US",
    "sg:address":"641 15th Ave",
    "sg:city":"Newark",
    "sg:classifiers":[
        {
            "category":"Retail",
            "subcategory":"Auto Repair",
            "type":"Services"
        }
    ],
    "sg:phone":"+1 973 373 6354",
    "sg:postcode":"07103",
    "sg:province":"NJ",
    "sg:tags":[
        "wrecker"
    ],
    "wof:name":"Dapper Dan Towing",
    "wof:placetype":"venue"
},
  "geometry": {"coordinates":[-74.210581,40.739336],"type":"Point"}
}