{
  "type": "Feature",
  "properties": {
    "addr:full":"37 Cedar Ave Newark NJ 07106",
    "addr:housenumber":"37",
    "addr:postcode":"07106",
    "addr:street":"Cedar Ave",
    "iso:country":"US",
    "sg:address":"37 Cedar Ave",
    "sg:city":"Newark",
    "sg:classifiers":[
        {
            "category":"Wholesale",
            "subcategory":"Machinery & Supplies",
            "type":"Manufacturing & Wholesale Goods"
        },
        {
            "category":"Wholesale",
            "subcategory":"Durable Goods & Equipment",
            "type":"Manufacturing & Wholesale Goods"
        }
    ],
    "sg:phone":"+1 973 416 1329",
    "sg:postcode":"07106",
    "sg:province":"NJ",
    "sg:tags":[
        "industrial",
        "representative",
        "con",
        "manufacturer"
    ],
    "wof:name":"New Jersey Pump Inc",
    "wof:placetype":"venue"
},
  "geometry": {"coordinates":[-74.21998499999999,40.745048],"type":"Point"}
}