{
  "type": "Feature",
  "properties": {
    "iso:country":"US",
    "sg:address":"530 Chestnut St",
    "sg:city":"Union",
    "sg:classifiers":[
        {
            "category":"Shopping",
            "subcategory":"Tobacco",
            "type":"Retail Goods"
        }
    ],
    "sg:phone":"+1 908 687 6422",
    "sg:postcode":"07083",
    "sg:province":"NJ",
    "sg:tags":[
        "cigarette",
        "cigar",
        "dealer"
    ],
    "wof:name":"B & C Assoc",
    "wof:placetype":"venue"
},
  "geometry": {"coordinates":[-74.269248,40.684745],"type":"Point"}
}