{
  "type": "Feature",
  "properties": {
    "iso:country":"US",
    "sg:address":"125 Paterson St",
    "sg:city":"New Brunswick",
    "sg:classifiers":[
        {
            "category":"Health Services",
            "subcategory":"Doctor",
            "type":"Services"
        }
    ],
    "sg:phone":"+1 732 235 7122",
    "sg:postcode":"08901",
    "sg:province":"NJ",
    "sg:tags":[
        "physician",
        "surgeon"
    ],
    "wof:name":"University Medicine Dentistry",
    "wof:placetype":"venue"
},
  "geometry": {"coordinates":[-74.44796100000001,40.494561],"type":"Point"}
}