{
  "type": "Feature",
  "properties": {
    "addr:full":"1588 US Hwy 130 North Brunswick NJ 08902",
    "addr:housenumber":"1588",
    "addr:postcode":"08902",
    "addr:street":"Us Hwy 130",
    "iso:country":"US",
    "sg:address":"1588 US Hwy 130",
    "sg:city":"North Brunswick",
    "sg:classifiers":[
        {
            "category":"Health Services",
            "subcategory":"Medical Lab",
            "type":"Services"
        }
    ],
    "sg:phone":"+1   ",
    "sg:postcode":"08902",
    "sg:province":"NJ",
    "sg:tags":[
        "laboratory"
    ],
    "wof:name":"Bradstreet Clincl Rsrch Assoc",
    "wof:placetype":"venue"
},
  "geometry": {"coordinates":[-74.467113,40.445634],"type":"Point"}
}