{
  "type": "Feature",
  "properties": {
    "iso:country":"US",
    "sg:address":"35 Woodland Ave",
    "sg:city":"Westwood",
    "sg:classifiers":[
        {
            "category":"Freight",
            "type":"Transportation"
        }
    ],
    "sg:phone":"+1 201 664 4096",
    "sg:postcode":"07675",
    "sg:province":"NJ",
    "sg:tags":[
        "general"
    ],
    "wof:name":"Record The",
    "wof:placetype":"venue"
},
  "geometry": {"coordinates":[-74.01586500000001,40.9823],"type":"Point"}
}