{
  "type": "Feature",
  "properties": {
    "addr:full":"132 E Olive St Westville NJ 08093",
    "addr:housenumber":"132",
    "addr:postcode":"08093",
    "addr:street":"E Olive St",
    "iso:country":"US",
    "sg:address":"132 E Olive St",
    "sg:city":"Westville",
    "sg:classifiers":[
        {
            "category":"Professional",
            "type":"Services"
        }
    ],
    "sg:phone":"+1   ",
    "sg:postcode":"08093",
    "sg:province":"NJ",
    "wof:name":"Hewitts",
    "wof:placetype":"venue"
},
  "geometry": {"coordinates":[-75.12962400000001,39.86251],"type":"Point"}
}