{
  "type": "Feature",
  "properties": {
    "addr:full":"20 River Rd North Arlington NJ 07031",
    "addr:housenumber":"20",
    "addr:postcode":"07031",
    "addr:street":"River Rd North",
    "iso:country":"US",
    "sg:address":"20 River Rd",
    "sg:city":"North Arlington",
    "sg:classifiers":[
        {
            "category":"Manufacturing",
            "subcategory":"Signs",
            "type":"Manufacturing & Wholesale Goods"
        }
    ],
    "sg:phone":"+1 973 680 1461",
    "sg:postcode":"07031",
    "sg:province":"NJ",
    "sg:tags":[
        "advertising",
        "specialty"
    ],
    "wof:name":"Garden State Flag Co Inc",
    "wof:placetype":"venue"
},
  "geometry": {"coordinates":[-74.14529899999999,40.786482],"type":"Point"}
}