{
  "type": "Feature",
  "properties": {
    "iso:country":"US",
    "sg:address":"6210 Bergenline Pl",
    "sg:city":"West New York",
    "sg:classifiers":[
        {
            "category":"Food & Beverages",
            "subcategory":"Groceries & Convenience Stores",
            "type":"Retail Goods"
        }
    ],
    "sg:phone":"+1 201 868 3716",
    "sg:postcode":"07093",
    "sg:province":"NJ",
    "sg:tags":[
        "grocer"
    ],
    "wof:name":"Fine Fare Supermarket",
    "wof:placetype":"venue"
},
  "geometry": {"coordinates":[-74.01407399999999,40.791731],"type":"Point"}
}