{
  "type": "Feature",
  "properties": {
    "iso:country":"US",
    "sg:address":"19 Gloria Ln",
    "sg:city":"Fairfield",
    "sg:classifiers":[
        {
            "category":"Shopping",
            "subcategory":"Stationery & Office Supplies",
            "type":"Retail Goods"
        }
    ],
    "sg:phone":"+1 973 227 5272",
    "sg:postcode":"07004",
    "sg:province":"NJ",
    "sg:tags":[
        "equipment"
    ],
    "sg:website":"www.completedocumentsolutions.com",
    "wof:name":"Complete Document Solutions",
    "wof:placetype":"venue"
},
  "geometry": {"coordinates":[-74.295723,40.87547],"type":"Point"}
}