{
  "type": "Feature",
  "properties": {
    "addr:full":"511 Market St Camden NJ 08102",
    "addr:housenumber":"511",
    "addr:postcode":"08102",
    "addr:street":"Market St",
    "iso:country":"US",
    "sg:address":"511 Market St",
    "sg:city":"Camden",
    "sg:classifiers":[
        {
            "category":"Professional",
            "subcategory":"Detective & Security Services",
            "type":"Services"
        }
    ],
    "sg:phone":"+1 856 964 5700",
    "sg:postcode":"08102",
    "sg:province":"NJ",
    "sg:tags":[
        "investigator"
    ],
    "wof:name":"Phyllis Krichev Assoc",
    "wof:placetype":"venue"
},
  "geometry": {"coordinates":[-75.12007199999999,39.945471],"type":"Point"}
}