{
  "type": "Feature",
  "properties": {
    "addr:full":"672 Somerset St North Plainfield NJ 07060",
    "addr:housenumber":"672",
    "addr:postcode":"07060",
    "addr:street":"Somerset St",
    "iso:country":"US",
    "sg:address":"672 Somerset St",
    "sg:city":"North Plainfield",
    "sg:classifiers":[
        {
            "category":"Banks & Credit Unions",
            "subcategory":"Bank",
            "type":"Services"
        }
    ],
    "sg:phone":"+1 908 561 4144",
    "sg:postcode":"07060",
    "sg:province":"NJ",
    "sg:website":"www.valleynationalbank.com",
    "wof:name":"Valley National Bancorp",
    "wof:placetype":"venue"
},
  "geometry": {"coordinates":[-74.439868,40.627943],"type":"Point"}
}