{
  "type": "Feature",
  "properties": {
    "addr:full":"3 Karen Ter Westfield NJ 07090",
    "addr:housenumber":"3",
    "addr:postcode":"07090",
    "addr:street":"Karen Ter",
    "iso:country":"US",
    "sg:address":"3 Karen Ter",
    "sg:city":"Westfield",
    "sg:classifiers":[
        {
            "category":"Building & Trades",
            "subcategory":"Electrical",
            "type":"Services"
        }
    ],
    "sg:phone":"+1 908 233 3478",
    "sg:postcode":"07090",
    "sg:province":"NJ",
    "sg:tags":[
        "electrical",
        "contractor"
    ],
    "wof:name":"Gene Zivny Electric Inc",
    "wof:placetype":"venue"
},
  "geometry": {"coordinates":[-74.335491,40.667065],"type":"Point"}
}