{
  "type": "Feature",
  "properties": {
    "iso:country":"US",
    "sg:address":"110 Meadowlands Pkwy",
    "sg:city":"Secaucus",
    "sg:classifiers":[
        {
            "category":"Professional",
            "subcategory":"Lawyer & Legal Services",
            "type":"Services"
        }
    ],
    "sg:phone":"+1 201 617 9100",
    "sg:postcode":"07094",
    "sg:province":"NJ",
    "wof:name":"Mausner Richard M Attorney At Law",
    "wof:placetype":"venue"
},
  "geometry": {"coordinates":[-74.06909899999999,40.7952],"type":"Point"}
}