{
  "type": "Feature",
  "properties": {
    "addr:full":"2 S Centre St Merchantville NJ 08109",
    "addr:housenumber":"2",
    "addr:postcode":"08109",
    "addr:street":"S Centre St",
    "iso:country":"US",
    "sg:address":"2 S Centre St",
    "sg:city":"Merchantville",
    "sg:classifiers":[
        {
            "category":"Shopping",
            "subcategory":"Used Merchandise",
            "type":"Retail Goods"
        }
    ],
    "sg:phone":"+1   ",
    "sg:postcode":"08109",
    "sg:province":"NJ",
    "wof:name":"Angels Attic",
    "wof:placetype":"venue"
},
  "geometry": {"coordinates":[-75.04902800000001,39.952279],"type":"Point"}
}