{
  "type": "Feature",
  "properties": {
    "addr:full":"10 S Portland Ave Ventnor City NJ 08406",
    "addr:housenumber":"10",
    "addr:postcode":"08406",
    "addr:street":"S Portland Ave",
    "iso:country":"US",
    "sg:address":"10 S Portland Ave",
    "sg:city":"Ventnor City",
    "sg:classifiers":[
        {
            "category":"Utilities",
            "subcategory":"Telephone",
            "type":"Services"
        }
    ],
    "sg:phone":"+1 609 641 9900",
    "sg:postcode":"08406",
    "sg:province":"NJ",
    "sg:tags":[
        "communications"
    ],
    "wof:name":"Verizon",
    "wof:placetype":"venue"
},
  "geometry": {"coordinates":[-74.482129,39.338023],"type":"Point"}
}