{
  "type": "Feature",
  "properties": {
    "addr:full":"809 N Wood Ave Linden NJ 07036",
    "addr:housenumber":"809",
    "addr:postcode":"07036",
    "addr:street":"N Wood Ave",
    "iso:country":"US",
    "sg:address":"809 N Wood Ave",
    "sg:city":"Linden",
    "sg:classifiers":[
        {
            "category":"Health Services",
            "subcategory":"Doctor",
            "type":"Services"
        }
    ],
    "sg:phone":"+1 908 486 0400",
    "sg:postcode":"07036",
    "sg:province":"NJ",
    "wof:name":"Center For Pain Relief",
    "wof:placetype":"venue"
},
  "geometry": {"coordinates":[-74.261606,40.635412],"type":"Point"}
}