{
  "type": "Feature",
  "properties": {
    "addr:full":"2800 State Rte 35 Hazlet NJ 07730",
    "addr:housenumber":"2800",
    "addr:postcode":"07730",
    "addr:street":"State Rte 35",
    "iso:country":"US",
    "sg:address":"2800 State Rte 35",
    "sg:city":"Hazlet",
    "sg:classifiers":[
        {
            "category":"Retail",
            "subcategory":"Car Wash",
            "type":"Services"
        }
    ],
    "sg:phone":"+1 732 264 4660",
    "sg:postcode":"07730",
    "sg:province":"NJ",
    "sg:tags":[
        "polishing",
        "carwash",
        "washing"
    ],
    "wof:name":"Crown Car Wash Inc",
    "wof:placetype":"venue"
},
  "geometry": {"coordinates":[-74.16978899999999,40.416962],"type":"Point"}
}