{
  "type": "Feature",
  "properties": {
    "iso:country":"US",
    "sg:address":"141 N County Line Rd",
    "sg:city":"Jackson",
    "sg:classifiers":[
        {
            "category":"Building & Trades",
            "subcategory":"Construction",
            "type":"Services"
        }
    ],
    "sg:phone":"+1 732 431 1012",
    "sg:postcode":"08527",
    "sg:province":"NJ",
    "sg:tags":[
        "insulation",
        "heat",
        "contractor"
    ],
    "sg:website":"www.gabrielspry.com",
    "wof:name":"Gabriel Spry Svc",
    "wof:placetype":"venue"
},
  "geometry": {"coordinates":[-74.28498,40.134817],"type":"Point"}
}