{
  "type": "Feature",
  "properties": {
    "iso:country":"US",
    "sg:address":"37 Schaal St",
    "sg:city":"Bridgewater",
    "sg:classifiers":[
        {
            "category":"Professional",
            "subcategory":"Computer Services",
            "type":"Services"
        }
    ],
    "sg:phone":"+1 908 707 8418",
    "sg:postcode":"08807",
    "sg:province":"NJ",
    "sg:tags":[
        "related"
    ],
    "wof:name":"Clover Soft",
    "wof:placetype":"venue"
},
  "geometry": {"coordinates":[-74.667067,40.590486],"type":"Point"}
}