{
  "type": "Feature",
  "properties": {
    "iso:country":"US",
    "sg:address":"63 E Ridgewood Ave",
    "sg:city":"Paramus",
    "sg:classifiers":[
        {
            "category":"Restaurant",
            "type":"Food & Drink"
        }
    ],
    "sg:menulink":"http://www.allmenus.com/nj/paramus/19052-king-pizza/menu/",
    "sg:phone":"+1 201 265 6370",
    "sg:postcode":"07652",
    "sg:province":"NJ",
    "sg:tags":[
        "italian"
    ],
    "wof:name":"King Pizza",
    "wof:placetype":"venue"
},
  "geometry": {"coordinates":[-74.084889,40.970173],"type":"Point"}
}