{
  "type": "Feature",
  "properties": {
    "iso:country":"US",
    "sg:address":"566 Ringwood Ave",
    "sg:city":"Wanaque",
    "sg:classifiers":[
        {
            "category":"Professional",
            "subcategory":"Accounting & Tax Preparation",
            "type":"Services"
        }
    ],
    "sg:phone":"+1   ",
    "sg:postcode":"07465",
    "sg:province":"NJ",
    "sg:tags":[
        "return"
    ],
    "wof:name":"EFA-Electronic Filing Assoc",
    "wof:placetype":"venue"
},
  "geometry": {"coordinates":[-74.288641,41.051837],"type":"Point"}
}