{
  "type": "Feature",
  "properties": {
    "iso:country":"US",
    "sg:address":"528 Raymond Blvd",
    "sg:city":"Newark",
    "sg:classifiers":[
        {
            "category":"Retail",
            "subcategory":"Laundry & Dry Cleaning",
            "type":"Services"
        }
    ],
    "sg:phone":"+1 973 589 0566",
    "sg:postcode":"07105",
    "sg:province":"NJ",
    "wof:name":"Laundry World",
    "wof:placetype":"venue"
},
  "geometry": {"coordinates":[-74.143001,40.733692],"type":"Point"}
}