{
  "type": "Feature",
  "properties": {
    "iso:country":"US",
    "sg:address":"603 River St",
    "sg:city":"Paterson",
    "sg:classifiers":[
        {
            "category":"Restaurant",
            "type":"Food & Drink"
        }
    ],
    "sg:phone":"+1   ",
    "sg:postcode":"07524",
    "sg:province":"NJ",
    "sg:tags":[
        "eating"
    ],
    "wof:name":"Rincon Del Sabor",
    "wof:placetype":"venue"
},
  "geometry": {"coordinates":[-74.156074,40.933955],"type":"Point"}
}