{
  "type": "Feature",
  "properties": {
    "iso:country":"US",
    "sg:address":"333 3rd Ave",
    "sg:city":"Clementon",
    "sg:classifiers":[
        {
            "category":"Health Services",
            "subcategory":"Chiropractor",
            "type":"Services"
        }
    ],
    "sg:phone":"+1 856 857 9500",
    "sg:postcode":"08021",
    "sg:province":"NJ",
    "wof:name":"Back To Hlth Chiropractic Ctr",
    "wof:placetype":"venue"
},
  "geometry": {"coordinates":[-75.007305,39.814592],"type":"Point"}
}