{
  "type": "Feature",
  "properties": {
    "iso:country":"US",
    "sg:address":"441 Minnisink Rd",
    "sg:city":"Totowa",
    "sg:classifiers":[
        {
            "category":"Restaurant",
            "type":"Food & Drink"
        }
    ],
    "sg:phone":"+1   ",
    "sg:postcode":"07512",
    "sg:province":"NJ",
    "sg:tags":[
        "eating"
    ],
    "wof:name":"Wendys",
    "wof:placetype":"venue"
},
  "geometry": {"coordinates":[-74.236208,40.895674],"type":"Point"}
}