{
  "type": "Feature",
  "properties": {
    "iso:country":"US",
    "sg:address":"500 Washington Blvd",
    "sg:city":"Sea Girt",
    "sg:classifiers":[
        {
            "category":"Shopping",
            "subcategory":"Gifts & Souvenirs",
            "type":"Retail Goods"
        }
    ],
    "sg:phone":"+1 732 974 0079",
    "sg:postcode":"08750",
    "sg:province":"NJ",
    "sg:tags":[
        "shop"
    ],
    "wof:name":"Down The Shore Gifts",
    "wof:placetype":"venue"
},
  "geometry": {"coordinates":[-74.041933,40.130064],"type":"Point"}
}