{
  "type": "Feature",
  "properties": {
    "iso:country":"US",
    "sg:address":"15 Columbia St",
    "sg:city":"Elmwood Park",
    "sg:classifiers":[
        {
            "category":"Food & Beverages",
            "subcategory":"Bakery",
            "type":"Retail Goods"
        }
    ],
    "sg:phone":"+1   ",
    "sg:postcode":"07407",
    "sg:province":"NJ",
    "wof:name":"Sue Sweets",
    "wof:placetype":"venue"
},
  "geometry": {"coordinates":[-74.12835099999999,40.921678],"type":"Point"}
}