{
  "type": "Feature",
  "properties": {
    "iso:country":"US",
    "sg:address":"29 Ashton Dr",
    "sg:city":"Voorhees",
    "sg:classifiers":[
        {
            "category":"Professional",
            "subcategory":"Engineering",
            "type":"Services"
        }
    ],
    "sg:phone":"+1   ",
    "sg:postcode":"08043",
    "sg:province":"NJ",
    "wof:name":"Tesco Inc",
    "wof:placetype":"venue"
},
  "geometry": {"coordinates":[-74.91879900000001,39.820325],"type":"Point"}
}