{
  "type": "Feature",
  "properties": {
    "addr:full":"15 Costill Ave Clayton NJ 08312",
    "addr:housenumber":"15",
    "addr:postcode":"08312",
    "addr:street":"Costill Ave",
    "iso:country":"US",
    "sg:address":"15 Costill Ave",
    "sg:city":"Clayton",
    "sg:classifiers":[
        {
            "category":"Real Estate",
            "subcategory":"Real Estate Operator",
            "type":"Services"
        }
    ],
    "sg:phone":"+1   ",
    "sg:postcode":"08312",
    "sg:province":"NJ",
    "sg:tags":[
        "building",
        "apartment"
    ],
    "wof:name":"Delsea View Apartments",
    "wof:placetype":"venue"
},
  "geometry": {"coordinates":[-75.091399,39.665386],"type":"Point"}
}