{
  "type": "Feature",
  "properties": {
    "addr:full":"12 Chambers St Princeton NJ 08542",
    "addr:housenumber":"12",
    "addr:postcode":"08542",
    "addr:street":"Chambers St",
    "iso:country":"US",
    "sg:address":"12 Chambers St",
    "sg:city":"Princeton",
    "sg:classifiers":[
        {
            "category":"Retail",
            "subcategory":"Auto Repair",
            "type":"Services"
        }
    ],
    "sg:phone":"+1 609 683 4361",
    "sg:postcode":"08542",
    "sg:province":"NJ",
    "sg:tags":[
        "repairing",
        "automobile",
        "radiator"
    ],
    "wof:name":"Capital Radiator & Tires",
    "wof:placetype":"venue"
},
  "geometry": {"coordinates":[-74.66297299999999,40.349966],"type":"Point"}
}