{
  "type": "Feature",
  "properties": {
    "iso:country":"US",
    "sg:address":"77 Everdell Ave",
    "sg:city":"Hillsdale",
    "sg:classifiers":[
        {
            "category":"Professional",
            "subcategory":"Testing Lab",
            "type":"Services"
        }
    ],
    "sg:phone":"+1 201 666 5519",
    "sg:postcode":"07642",
    "sg:province":"NJ",
    "sg:tags":[
        "device",
        "flow",
        "back"
    ],
    "wof:name":"Hydro Technology Backflow",
    "wof:placetype":"venue"
},
  "geometry": {"coordinates":[-74.025976,41.001125],"type":"Point"}
}