{
  "type": "Feature",
  "properties": {
    "iso:country":"US",
    "sg:address":"1 W Blackwell St",
    "sg:city":"Dover",
    "sg:classifiers":[
        {
            "category":"Travel",
            "subcategory":"Travel Agent",
            "type":"Entertainment"
        }
    ],
    "sg:phone":"+1 973 989 8669",
    "sg:postcode":"07801",
    "sg:province":"NJ",
    "sg:tags":[
        "agency"
    ],
    "wof:name":"Super Rapido Express Inc",
    "wof:placetype":"venue"
},
  "geometry": {"coordinates":[-74.55942400000001,40.884091],"type":"Point"}
}