{
  "type": "Feature",
  "properties": {
    "addr:full":"14 Nassau St Princeton NJ 08542",
    "addr:housenumber":"14",
    "addr:postcode":"08542",
    "addr:street":"Nassau St",
    "iso:country":"US",
    "sg:address":"14 Nassau St",
    "sg:city":"Princeton",
    "sg:classifiers":[
        {
            "category":"Shopping",
            "subcategory":"Books",
            "type":"Retail Goods"
        }
    ],
    "sg:phone":"+1 609 921 2268",
    "sg:postcode":"08542",
    "sg:province":"NJ",
    "sg:tags":[
        "dealer"
    ],
    "wof:name":"Glen Echo Books",
    "wof:placetype":"venue"
},
  "geometry": {"coordinates":[-74.662521,40.348973],"type":"Point"}
}