{
  "type": "Feature",
  "properties": {
    "iso:country":"US",
    "sg:address":"1435 51st St",
    "sg:city":"North Bergen",
    "sg:classifiers":[
        {
            "category":"Wholesale",
            "subcategory":"Apparel",
            "type":"Manufacturing & Wholesale Goods"
        }
    ],
    "sg:phone":"+1 201 867 7007",
    "sg:postcode":"07047",
    "sg:province":"NJ",
    "sg:tags":[
        "importer"
    ],
    "wof:name":"Toofan Inc",
    "wof:placetype":"venue"
},
  "geometry": {"coordinates":[-74.028978,40.786871],"type":"Point"}
}