{
  "type": "Feature",
  "properties": {
    "addr:full":"3501 State Rte 42 Blackwood NJ 08012",
    "addr:housenumber":"3501",
    "addr:postcode":"08012",
    "addr:street":"State Rte 42",
    "iso:country":"US",
    "sg:address":"3501 State Rte 42",
    "sg:city":"Blackwood",
    "sg:classifiers":[
        {
            "category":"Shopping",
            "subcategory":"Clothing, Apparel, & Fashions",
            "type":"Retail Goods"
        }
    ],
    "sg:phone":"+1   ",
    "sg:postcode":"08012",
    "sg:province":"NJ",
    "wof:name":"Dots Inc",
    "wof:placetype":"venue"
},
  "geometry": {"coordinates":[-75.03357099999999,39.73012],"type":"Point"}
}