{
  "type": "Feature",
  "properties": {
    "iso:country":"US",
    "sg:address":"35 W Broadway",
    "sg:city":"Salem",
    "sg:classifiers":[
        {
            "category":"Manufacturing",
            "subcategory":"Retail Goods",
            "type":"Manufacturing & Wholesale Goods"
        }
    ],
    "sg:phone":"+1 856 339 4004",
    "sg:postcode":"08079",
    "sg:province":"NJ",
    "sg:tags":[
        "assembly",
        "fabricating"
    ],
    "wof:name":"G E Fabricators Inc",
    "wof:placetype":"venue"
},
  "geometry": {"coordinates":[-75.477412,39.574499],"type":"Point"}
}