{
  "type": "Feature",
  "properties": {
    "iso:country":"US",
    "sg:address":"1020 Arlington Rd",
    "sg:city":"New Milford",
    "sg:classifiers":[
        {
            "category":"Professional",
            "subcategory":"Business Services",
            "type":"Services"
        }
    ],
    "sg:phone":"+1 201 261 8803",
    "sg:postcode":"07646",
    "sg:province":"NJ",
    "sg:tags":[
        "collectible",
        "promotion",
        "show"
    ],
    "wof:name":"K & S Promotions",
    "wof:placetype":"venue"
},
  "geometry": {"coordinates":[-74.028003,40.920422],"type":"Point"}
}