{
  "type": "Feature",
  "properties": {
    "addr:full":"169 Hobart Ave Short Hills NJ 07078",
    "addr:housenumber":"169",
    "addr:postcode":"07078",
    "addr:street":"Hobart Ave",
    "iso:country":"US",
    "sg:address":"169 Hobart Ave",
    "sg:city":"Short Hills",
    "sg:classifiers":[
        {
            "category":"Health Services",
            "subcategory":"Doctor",
            "type":"Services"
        }
    ],
    "sg:phone":"+1 973 376 5781",
    "sg:postcode":"07078",
    "sg:province":"NJ",
    "sg:tags":[
        "surgeon",
        "oral",
        "dentist"
    ],
    "wof:name":"Busby Stephen T DDS",
    "wof:placetype":"venue"
},
  "geometry": {"coordinates":[-74.324501,40.7258],"type":"Point"}
}