{
  "type": "Feature",
  "properties": {
    "addr:full":"450 Howard Blvd Mt Arlington NJ 07856",
    "addr:housenumber":"450",
    "addr:postcode":"07856",
    "addr:street":"Howard Blvd Mt",
    "iso:country":"US",
    "sg:address":"450 Howard Blvd",
    "sg:city":"Mt Arlington",
    "sg:classifiers":[
        {
            "category":"Restaurant",
            "type":"Food & Drink"
        }
    ],
    "sg:phone":"+1 973 663 6000",
    "sg:postcode":"07856",
    "sg:province":"NJ",
    "sg:tags":[
        "caterer"
    ],
    "sg:website":"www.arlingtoncaterers.com",
    "wof:name":"Arlington",
    "wof:placetype":"venue"
},
  "geometry": {"coordinates":[-74.629829,40.934878],"type":"Point"}
}