{
  "type": "Feature",
  "properties": {
    "addr:full":"798 US Hwy 202 Flemington NJ 08822",
    "addr:housenumber":"798",
    "addr:postcode":"08822",
    "addr:street":"Us Hwy 202",
    "iso:country":"US",
    "sg:address":"798 US Hwy 202",
    "sg:city":"Flemington",
    "sg:classifiers":[
        {
            "category":"Building & Trades",
            "subcategory":"Construction",
            "type":"Services"
        }
    ],
    "sg:phone":"+1 908 782 2737",
    "sg:postcode":"08822",
    "sg:province":"NJ",
    "sg:tags":[
        "general",
        "contractor"
    ],
    "wof:name":"Jayeff Construction",
    "wof:placetype":"venue"
},
  "geometry": {"coordinates":[-74.778425,40.532613],"type":"Point"}
}