{
  "type": "Feature",
  "properties": {
    "addr:full":"1046 Springfield Ave Irvington NJ 07111",
    "addr:housenumber":"1046",
    "addr:postcode":"07111",
    "addr:street":"Springfield Ave",
    "iso:country":"US",
    "sg:address":"1046 Springfield Ave",
    "sg:city":"Irvington",
    "sg:classifiers":[
        {
            "category":"Shopping",
            "subcategory":"Discount & Variety Stores",
            "type":"Retail Goods"
        }
    ],
    "sg:phone":"+1 973 351 7900",
    "sg:postcode":"07111",
    "sg:province":"NJ",
    "sg:tags":[
        "merchandise",
        "general"
    ],
    "wof:name":"99 Cents Plus",
    "wof:placetype":"venue"
},
  "geometry": {"coordinates":[-74.23087099999999,40.726212],"type":"Point"}
}