{
  "type": "Feature",
  "properties": {
    "addr:full":"619 Amboy Ave Edison NJ 08837",
    "addr:housenumber":"619",
    "addr:postcode":"08837",
    "addr:street":"Amboy Ave",
    "iso:country":"US",
    "sg:address":"619 Amboy Ave",
    "sg:city":"Edison",
    "sg:classifiers":[
        {
            "category":"Health Services",
            "subcategory":"Doctor",
            "type":"Services"
        }
    ],
    "sg:phone":"+1   ",
    "sg:postcode":"08837",
    "sg:province":"NJ",
    "wof:name":"Raritan Vlly Oral/Maxillofcl",
    "wof:placetype":"venue"
},
  "geometry": {"coordinates":[-74.31740499999999,40.529232],"type":"Point"}
}