{
  "type": "Feature",
  "properties": {
    "iso:country":"US",
    "sg:address":"341 Westwind Ct",
    "sg:city":"Norwood",
    "sg:classifiers":[
        {
            "category":"Shopping",
            "subcategory":"Musical Instruments",
            "type":"Retail Goods"
        }
    ],
    "sg:phone":"+1   ",
    "sg:postcode":"07648",
    "sg:province":"NJ",
    "wof:name":"HI Nose Tubes",
    "wof:placetype":"venue"
},
  "geometry": {"coordinates":[-73.943457,40.986699],"type":"Point"}
}