{
  "type": "Feature",
  "properties": {
    "addr:full":"719 Main St Lumberton NJ 08048",
    "addr:housenumber":"719",
    "addr:postcode":"08048",
    "addr:street":"Main St",
    "iso:country":"US",
    "sg:address":"719 Main St",
    "sg:city":"Lumberton",
    "sg:classifiers":[
        {
            "category":"Freight",
            "type":"Transportation"
        }
    ],
    "sg:phone":"+1 609 261 8646",
    "sg:postcode":"08048",
    "sg:province":"NJ",
    "sg:tags":[
        "operator",
        "local",
        "trucking"
    ],
    "wof:name":"Hometown Moving & Storage",
    "wof:placetype":"venue"
},
  "geometry": {"coordinates":[-74.79925299999999,39.978452],"type":"Point"}
}