{
  "type": "Feature",
  "properties": {
    "iso:country":"US",
    "sg:address":"95 Central Ave",
    "sg:city":"Metuchen",
    "sg:classifiers":[
        {
            "category":"Building & Trades",
            "subcategory":"Equipment Rental",
            "type":"Services"
        }
    ],
    "sg:phone":"+1 732 548 6260",
    "sg:postcode":"08840",
    "sg:province":"NJ",
    "sg:tags":[
        "leasing"
    ],
    "wof:name":"Dodge Renting & Leasing",
    "wof:placetype":"venue"
},
  "geometry": {"coordinates":[-74.368537,40.542452],"type":"Point"}
}