{
  "type": "Feature",
  "properties": {
    "addr:full":"325 State Rte 36 Hazlet NJ 07730",
    "addr:housenumber":"325",
    "addr:postcode":"07730",
    "addr:street":"State Rte 36",
    "iso:country":"US",
    "sg:address":"325 State Rte 36",
    "sg:city":"Hazlet",
    "sg:classifiers":[
        {
            "category":"Autos & Motor Vehicles",
            "subcategory":"Fuel & Gas Station",
            "type":"Retail Goods"
        }
    ],
    "sg:phone":"+1 732 787 3322",
    "sg:postcode":"07730",
    "sg:province":"NJ",
    "sg:tags":[
        "oil"
    ],
    "wof:name":"Hazlet Oil",
    "wof:placetype":"venue"
},
  "geometry": {"coordinates":[-74.14444899999999,40.437861],"type":"Point"}
}