{
  "type": "Feature",
  "properties": {
    "iso:country":"US",
    "sg:address":"55 Margaret Dr",
    "sg:city":"Somerset",
    "sg:classifiers":[
        {
            "category":"Professional",
            "subcategory":"Management & Consulting",
            "type":"Services"
        }
    ],
    "sg:phone":"+1   ",
    "sg:postcode":"08873",
    "sg:province":"NJ",
    "wof:name":"Janusreach Inc",
    "wof:placetype":"venue"
},
  "geometry": {"coordinates":[-74.52442600000001,40.490357],"type":"Point"}
}