{
  "type": "Feature",
  "properties": {
    "addr:full":"30 Ginger Dr Edison NJ 08837",
    "addr:housenumber":"30",
    "addr:postcode":"08837",
    "addr:street":"Ginger Dr",
    "iso:country":"US",
    "sg:address":"30 Ginger Dr",
    "sg:city":"Edison",
    "sg:classifiers":[
        {
            "category":"Shopping",
            "subcategory":"Computers & Home Electronics",
            "type":"Retail Goods"
        }
    ],
    "sg:phone":"+1 732 356 6700",
    "sg:postcode":"08837",
    "sg:province":"NJ",
    "sg:tags":[
        "software"
    ],
    "wof:name":"Sierra Technologies LTD",
    "wof:placetype":"venue"
},
  "geometry": {"coordinates":[-74.347128,40.528091],"type":"Point"}
}