{
  "type": "Feature",
  "properties": {
    "iso:country":"US",
    "sg:address":"355 Murray Hill Pkwy",
    "sg:city":"East Rutherford",
    "sg:classifiers":[
        {
            "category":"Organizations",
            "subcategory":"Labor Organization",
            "type":"Services"
        }
    ],
    "sg:phone":"+1 201 933 9494",
    "sg:postcode":"07073",
    "sg:province":"NJ",
    "wof:name":"International Union-Elect",
    "wof:placetype":"venue"
},
  "geometry": {"coordinates":[-74.09287,40.819063],"type":"Point"}
}