{
  "type": "Feature",
  "properties": {
    "iso:country":"US",
    "sg:address":"81 Two Bridges Rd Ste 211",
    "sg:city":"Fairfield",
    "sg:classifiers":[
        {
            "category":"Professional",
            "subcategory":"Lawyer & Legal Services",
            "type":"Services"
        }
    ],
    "sg:phone":"+1 973 787 0299",
    "sg:postcode":"07004",
    "sg:province":"NJ",
    "sg:website":"www.scclegal.com",
    "wof:name":"Sedita Campisano & Campisano",
    "wof:placetype":"venue"
},
  "geometry": {"coordinates":[-74.273037,40.89594],"type":"Point"}
}