{
  "type": "Feature",
  "properties": {
    "iso:country":"US",
    "sg:address":"462 Broad Ave",
    "sg:city":"Palisades Park",
    "sg:classifiers":[
        {
            "category":"Retail",
            "subcategory":"Laundry & Dry Cleaning",
            "type":"Services"
        }
    ],
    "sg:phone":"+1 201 944 6068",
    "sg:postcode":"07650",
    "sg:province":"NJ",
    "wof:name":"Young S Kim",
    "wof:placetype":"venue"
},
  "geometry": {"coordinates":[-73.995124,40.85142],"type":"Point"}
}