{
  "type": "Feature",
  "properties": {
    "addr:full":"56 Hanover Rd East Hanover NJ 07936",
    "addr:housenumber":"56",
    "addr:postcode":"07936",
    "addr:street":"Hanover Rd",
    "iso:country":"US",
    "sg:address":"56 Hanover Rd",
    "sg:city":"East Hanover",
    "sg:classifiers":[
        {
            "category":"Manufacturing",
            "subcategory":"Electronics",
            "type":"Manufacturing & Wholesale Goods"
        }
    ],
    "sg:phone":"+1 973 887 0571",
    "sg:postcode":"07936",
    "sg:province":"NJ",
    "sg:tags":[
        "connector",
        "electronic"
    ],
    "sg:website":"www.jettron.com",
    "wof:name":"Jettron Products Inc",
    "wof:placetype":"venue"
},
  "geometry": {"coordinates":[-74.37426499999999,40.796347],"type":"Point"}
}