{
  "type": "Feature",
  "properties": {
    "addr:full":"1217 Central Ave Hillside NJ 07205",
    "addr:housenumber":"1217",
    "addr:postcode":"07205",
    "addr:street":"Central Ave",
    "iso:country":"US",
    "sg:address":"1217 Central Ave",
    "sg:city":"Hillside",
    "sg:classifiers":[
        {
            "category":"Building & Trades",
            "subcategory":"Construction",
            "type":"Services"
        }
    ],
    "sg:phone":"+1 908 282 4487",
    "sg:postcode":"07205",
    "sg:province":"NJ",
    "sg:tags":[
        "planning",
        "remodeling",
        "kitchen"
    ],
    "wof:name":"Finekraft Kitchens",
    "wof:placetype":"venue"
},
  "geometry": {"coordinates":[-74.229525,40.689696],"type":"Point"}
}