{
  "type": "Feature",
  "properties": {
    "iso:country":"US",
    "sg:address":"4 State Rte 34",
    "sg:city":"Matawan",
    "sg:classifiers":[
        {
            "category":"Professional",
            "subcategory":"Management & Consulting",
            "type":"Services"
        }
    ],
    "sg:phone":"+1 732 566 6106",
    "sg:postcode":"07747",
    "sg:province":"NJ",
    "sg:tags":[
        "health",
        "care"
    ],
    "wof:name":"Genesis Health Ventures",
    "wof:placetype":"venue"
},
  "geometry": {"coordinates":[-74.248042,40.416233],"type":"Point"}
}