{
  "type": "Feature",
  "properties": {
    "iso:country":"US",
    "sg:address":"102 W Front St",
    "sg:city":"Red Bank",
    "sg:classifiers":[
        {
            "category":"Personal",
            "subcategory":"Beauty Salon",
            "type":"Services"
        }
    ],
    "sg:phone":"+1 732 530 7373",
    "sg:postcode":"07701",
    "sg:province":"NJ",
    "wof:name":"White Studio",
    "wof:placetype":"venue"
},
  "geometry": {"coordinates":[-74.069339,40.351211],"type":"Point"}
}