{
  "type": "Feature",
  "properties": {
    "addr:full":"820 Main St Toms River NJ 08753",
    "addr:housenumber":"820",
    "addr:postcode":"08753",
    "addr:street":"Main St",
    "iso:country":"US",
    "sg:address":"820 Main St",
    "sg:city":"Toms River",
    "sg:classifiers":[
        {
            "category":"Bars & Pubs",
            "subcategory":"Lounge",
            "type":"Food & Drink"
        }
    ],
    "sg:menulink":"http://www.allmenus.com/nj/toms-river/29378-the-office-restaurant--lounge/menu/",
    "sg:phone":"+1 732 349 0800",
    "sg:postcode":"08753",
    "sg:province":"NJ",
    "sg:tags":[
        "american"
    ],
    "wof:name":"The Office Restaurant & Lounge",
    "wof:placetype":"venue"
},
  "geometry": {"coordinates":[-74.200363,39.961953],"type":"Point"}
}