{
  "type": "Feature",
  "properties": {
    "addr:full":"35 Red School House Rd Lebanon NJ 08833",
    "addr:housenumber":"35",
    "addr:postcode":"08833",
    "addr:street":"Red School House Rd",
    "iso:country":"US",
    "sg:address":"35 Red School House Rd",
    "sg:city":"Lebanon",
    "sg:classifiers":[
        {
            "category":"Building & Trades",
            "subcategory":"Construction",
            "type":"Services"
        }
    ],
    "sg:phone":"+1 908 735 8222",
    "sg:postcode":"08833",
    "sg:province":"NJ",
    "sg:tags":[
        "excavation",
        "contractor"
    ],
    "wof:name":"Bundt Excavating",
    "wof:placetype":"venue"
},
  "geometry": {"coordinates":[-74.88087400000001,40.601217],"type":"Point"}
}