{
  "type": "Feature",
  "properties": {
    "iso:country":"US",
    "sg:address":"2900 Fire Rd",
    "sg:city":"Egg Harbor Twp",
    "sg:classifiers":[
        {
            "category":"Professional",
            "subcategory":"Lawyer & Legal Services",
            "type":"Services"
        }
    ],
    "sg:phone":"+1 609 645 1881",
    "sg:postcode":"08234",
    "sg:province":"NJ",
    "sg:tags":[
        "attorney"
    ],
    "sg:website":"www.flastergreenberg.com",
    "wof:name":"Flaster Greenberg",
    "wof:placetype":"venue"
},
  "geometry": {"coordinates":[-74.552403,39.399933],"type":"Point"}
}