{
  "type": "Feature",
  "properties": {
    "iso:country":"US",
    "sg:address":"RT. 130 & BROWNING ROAD",
    "sg:city":"Brooklawn",
    "sg:classifiers":[
        {
            "category":"Fast Food",
            "type":"Food & Drink"
        },
        {
            "category":"Restaurant",
            "type":"Food & Drink"
        }
    ],
    "sg:phone":"+1 856 742 1819",
    "sg:postcode":"08030",
    "sg:province":"NJ",
    "sg:tags":[
        "shop",
        "hamburger",
        "dog",
        "hot",
        "fountain",
        "soda",
        "american"
    ],
    "sg:website":"http://www.awrestaurants.com/",
    "wof:name":"A&W - KFC",
    "wof:placetype":"venue"
},
  "geometry": {"coordinates":[-75.115143,39.888222],"type":"Point"}
}