{
  "type": "Feature",
  "properties": {
    "addr:full":"131 Main Rd Hammonton NJ 08037",
    "addr:housenumber":"131",
    "addr:postcode":"08037",
    "addr:street":"Main Rd",
    "iso:country":"US",
    "sg:address":"131 Main Rd",
    "sg:city":"Hammonton",
    "sg:classifiers":[
        {
            "category":"Banks & Credit Unions",
            "subcategory":"Bank",
            "type":"Services"
        }
    ],
    "sg:phone":"+1   ",
    "sg:postcode":"08037",
    "sg:province":"NJ",
    "sg:tags":[
        "mortgage"
    ],
    "wof:name":"Gabriel Mortgage Services LLC",
    "wof:placetype":"venue"
},
  "geometry": {"coordinates":[-74.772035,39.636957],"type":"Point"}
}