{
  "type": "Feature",
  "properties": {
    "iso:country":"US",
    "sg:address":"243 Co Rd 537",
    "sg:city":"Colts Neck",
    "sg:classifiers":[
        {
            "category":"Retail",
            "subcategory":"Animal Services",
            "type":"Services"
        }
    ],
    "sg:phone":"+1 732 389 8018",
    "sg:postcode":"07722",
    "sg:province":"NJ",
    "wof:name":"Barney Barney",
    "wof:placetype":"venue"
},
  "geometry": {"coordinates":[-74.123502,40.3014],"type":"Point"}
}