{
  "type": "Feature",
  "properties": {
    "iso:country":"US",
    "sg:address":"409 Madison Ave",
    "sg:city":"New Milford",
    "sg:classifiers":[
        {
            "category":"Retail",
            "subcategory":"Auto Repair",
            "type":"Services"
        }
    ],
    "sg:phone":"+1 201 261 9271",
    "sg:postcode":"07646",
    "sg:province":"NJ",
    "sg:tags":[
        "repairing",
        "automobile"
    ],
    "wof:name":"D & R Auto Svc",
    "wof:placetype":"venue"
},
  "geometry": {"coordinates":[-74.012157,40.940275],"type":"Point"}
}