{
  "type": "Feature",
  "properties": {
    "iso:country":"US",
    "sg:address":"270 Valley Blvd",
    "sg:city":"Wood Ridge",
    "sg:classifiers":[
        {
            "category":"Home & Garden",
            "subcategory":"Hardware",
            "type":"Retail Goods"
        }
    ],
    "sg:phone":"+1 201 438 2024",
    "sg:postcode":"07075",
    "sg:province":"NJ",
    "sg:tags":[
        "store"
    ],
    "wof:name":"Siegel's Hardware & Paints",
    "wof:placetype":"venue"
},
  "geometry": {"coordinates":[-74.084801,40.851299],"type":"Point"}
}