{
  "type": "Feature",
  "properties": {
    "addr:full":"712 Hartwell St Teaneck NJ 07666",
    "addr:housenumber":"712",
    "addr:postcode":"07666",
    "addr:street":"Hartwell St",
    "iso:country":"US",
    "sg:address":"712 Hartwell St",
    "sg:city":"Teaneck",
    "sg:classifiers":[
        {
            "category":"Social Services",
            "type":"Services"
        }
    ],
    "sg:phone":"+1 201 836 0883",
    "sg:postcode":"07666",
    "sg:province":"NJ",
    "sg:tags":[
        "counselor",
        "marriage",
        "family"
    ],
    "wof:name":"Jim Gilbert PHD",
    "wof:placetype":"venue"
},
  "geometry": {"coordinates":[-74.00804100000001,40.881206],"type":"Point"}
}