{
  "type": "Feature",
  "properties": {
    "addr:full":"87 Berdan Ave Wayne NJ 07470",
    "addr:housenumber":"87",
    "addr:postcode":"07470",
    "addr:street":"Berdan Ave",
    "iso:country":"US",
    "sg:address":"87 Berdan Ave",
    "sg:city":"Wayne",
    "sg:classifiers":[
        {
            "category":"Recreation",
            "type":"Entertainment"
        }
    ],
    "sg:phone":"+1 973 692 1991",
    "sg:postcode":"07470",
    "sg:province":"NJ",
    "sg:tags":[
        "judo",
        "facility",
        "martial art",
        "instr",
        "karate",
        "fitness",
        "physical"
    ],
    "sg:website":"www.sernackskarate.com",
    "wof:name":"Sernack's Karate & Fitness",
    "wof:placetype":"venue"
},
  "geometry": {"coordinates":[-74.242401,40.963001],"type":"Point"}
}