{
  "type": "Feature",
  "properties": {
    "addr:full":"414 N Wood Ave Linden NJ 07036",
    "addr:housenumber":"414",
    "addr:postcode":"07036",
    "addr:street":"N Wood Ave",
    "iso:country":"US",
    "sg:address":"414 N Wood Ave",
    "sg:city":"Linden",
    "sg:classifiers":[
        {
            "category":"Shopping",
            "subcategory":"Clothing, Apparel, & Fashions",
            "type":"Retail Goods"
        }
    ],
    "sg:phone":"+1 908 486 4808",
    "sg:postcode":"07036",
    "sg:province":"NJ",
    "sg:website":"www.abcsuperstore.com",
    "wof:name":"ABC Bargain Stores",
    "wof:placetype":"venue"
},
  "geometry": {"coordinates":[-74.25722399999999,40.633],"type":"Point"}
}