{
  "type": "Feature",
  "properties": {
    "iso:country":"US",
    "sg:address":"680 Stokes Rd",
    "sg:city":"Medford Lakes",
    "sg:classifiers":[
        {
            "category":"Personal",
            "type":"Services"
        }
    ],
    "sg:phone":"+1 609 953 1785",
    "sg:postcode":"08055",
    "sg:province":"NJ",
    "sg:tags":[
        "wear",
        "formal"
    ],
    "wof:name":"Queen Cleaners",
    "wof:placetype":"venue"
},
  "geometry": {"coordinates":[-74.808864,39.866671],"type":"Point"}
}