{
  "type": "Feature",
  "properties": {
    "addr:full":"215 Highland Ave Haddon Twp NJ 08108",
    "addr:housenumber":"215",
    "addr:postcode":"08108",
    "addr:street":"Highland Ave",
    "iso:country":"US",
    "sg:address":"215 Highland Ave",
    "sg:city":"Haddon Twp",
    "sg:classifiers":[
        {
            "category":"Professional",
            "subcategory":"Accounting & Tax Preparation",
            "type":"Services"
        }
    ],
    "sg:phone":"+1 856 858 5212",
    "sg:postcode":"08108",
    "sg:province":"NJ",
    "sg:tags":[
        "billing"
    ],
    "wof:name":"Medical Consultants Of America",
    "wof:placetype":"venue"
},
  "geometry": {"coordinates":[-75.047572,39.910736],"type":"Point"}
}