{
  "type": "Feature",
  "properties": {
    "addr:full":"144 Black Horse Pike Mount Ephraim NJ 08059",
    "addr:housenumber":"144",
    "addr:postcode":"08059",
    "addr:street":"Black Horse Pike",
    "iso:country":"US",
    "sg:address":"144 Black Horse Pike",
    "sg:city":"Mount Ephraim",
    "sg:classifiers":[
        {
            "category":"Wholesale",
            "subcategory":"Groceries",
            "type":"Manufacturing & Wholesale Goods"
        }
    ],
    "sg:phone":"+1 856 456 8612",
    "sg:postcode":"08059",
    "sg:province":"NJ",
    "sg:tags":[
        "food"
    ],
    "wof:name":"Dimar Foods",
    "wof:placetype":"venue"
},
  "geometry": {"coordinates":[-75.093334,39.898214],"type":"Point"}
}