{
  "type": "Feature",
  "properties": {
    "addr:full":"499 Division St Boonton NJ 07005",
    "addr:housenumber":"499",
    "addr:postcode":"07005",
    "addr:street":"Division St",
    "iso:country":"US",
    "sg:address":"499 Division St",
    "sg:city":"Boonton",
    "sg:classifiers":[
        {
            "category":"Building & Trades",
            "subcategory":"Electrical",
            "type":"Services"
        }
    ],
    "sg:phone":"+1 973 263 3144",
    "sg:postcode":"07005",
    "sg:province":"NJ",
    "sg:tags":[
        "electrical",
        "contractor"
    ],
    "wof:name":"Glander Electric Company Inc",
    "wof:placetype":"venue"
},
  "geometry": {"coordinates":[-74.402106,40.907542],"type":"Point"}
}