{
  "type": "Feature",
  "properties": {
    "iso:country":"US",
    "sg:address":"1605 Grand Central Ave",
    "sg:city":"Lavallette",
    "sg:classifiers":[
        {
            "category":"Real Estate",
            "subcategory":"Real Estate Agent",
            "type":"Services"
        }
    ],
    "sg:phone":"+1 732 830 1108",
    "sg:postcode":"08735",
    "sg:province":"NJ",
    "wof:name":"D B Realty",
    "wof:placetype":"venue"
},
  "geometry": {"coordinates":[-74.06952,39.966285],"type":"Point"}
}