{
  "type": "Feature",
  "properties": {
    "addr:full":"1358 Morris Ave Union NJ 07083",
    "addr:housenumber":"1358",
    "addr:postcode":"07083",
    "addr:street":"Morris Ave",
    "iso:country":"US",
    "sg:address":"1358 Morris Ave",
    "sg:city":"Union",
    "sg:classifiers":[
        {
            "category":"Professional",
            "subcategory":"Lawyer & Legal Services",
            "type":"Services"
        }
    ],
    "sg:phone":"+1 908 687 3555",
    "sg:postcode":"07083",
    "sg:province":"NJ",
    "wof:name":"Pearson & Shapiro",
    "wof:placetype":"venue"
},
  "geometry": {"coordinates":[-74.24467300000001,40.688204],"type":"Point"}
}