{
  "type": "Feature",
  "properties": {
    "addr:full":"269 Central Ave Mountainside NJ 07092",
    "addr:housenumber":"269",
    "addr:postcode":"07092",
    "addr:street":"Central Ave",
    "iso:country":"US",
    "sg:address":"269 Central Ave",
    "sg:city":"Mountainside",
    "sg:classifiers":[
        {
            "category":"Building & Trades",
            "subcategory":"Construction",
            "type":"Services"
        }
    ],
    "sg:phone":"+1 908 233 5253",
    "sg:postcode":"07092",
    "sg:province":"NJ",
    "sg:tags":[
        "excavation",
        "contractor"
    ],
    "wof:name":"Mountainside Equipment Co Inc",
    "wof:placetype":"venue"
},
  "geometry": {"coordinates":[-74.35005099999999,40.679247],"type":"Point"}
}