{
  "type": "Feature",
  "properties": {
    "iso:country":"US",
    "sg:address":"146 W 30th St",
    "sg:city":"Bayonne",
    "sg:classifiers":[
        {
            "category":"Building & Trades",
            "subcategory":"Construction",
            "type":"Services"
        }
    ],
    "sg:phone":"+1 201 436 8815",
    "sg:postcode":"07002",
    "sg:province":"NJ",
    "sg:tags":[
        "layer",
        "carpet"
    ],
    "wof:name":"Dyna Clean",
    "wof:placetype":"venue"
},
  "geometry": {"coordinates":[-74.119423,40.671616],"type":"Point"}
}