{
  "type": "Feature",
  "properties": {
    "addr:full":"16 Sunset Ter Maplewood NJ 07040",
    "addr:housenumber":"16",
    "addr:postcode":"07040",
    "addr:street":"Sunset Ter",
    "iso:country":"US",
    "sg:address":"16 Sunset Ter",
    "sg:city":"Maplewood",
    "sg:classifiers":[
        {
            "category":"Shopping",
            "subcategory":"Gifts & Souvenirs",
            "type":"Retail Goods"
        }
    ],
    "sg:phone":"+1   ",
    "sg:postcode":"07040",
    "sg:province":"NJ",
    "sg:tags":[
        "comic",
        "promotion",
        "format"
    ],
    "wof:name":"Navigator Comics",
    "wof:placetype":"venue"
},
  "geometry": {"coordinates":[-74.279116,40.740522],"type":"Point"}
}