{
  "type": "Feature",
  "properties": {
    "iso:country":"US",
    "sg:address":"714 Coolidge Ave",
    "sg:city":"Toms River",
    "sg:classifiers":[
        {
            "category":"Professional",
            "subcategory":"Management & Consulting",
            "type":"Services"
        }
    ],
    "sg:phone":"+1 732 573 1246",
    "sg:postcode":"08753",
    "sg:province":"NJ",
    "sg:tags":[
        "party",
        "planning"
    ],
    "wof:name":"Party Time Blessings",
    "wof:placetype":"venue"
},
  "geometry": {"coordinates":[-74.138817,39.962578],"type":"Point"}
}