{
  "type": "Feature",
  "properties": {
    "addr:full":"20 Ashton Ave Swedesboro NJ 08085",
    "addr:housenumber":"20",
    "addr:postcode":"08085",
    "addr:street":"Ashton Ave",
    "iso:country":"US",
    "sg:address":"20 Ashton Ave",
    "sg:city":"Swedesboro",
    "sg:classifiers":[
        {
            "category":"Manufacturing",
            "subcategory":"Rubber & Plastics",
            "type":"Manufacturing & Wholesale Goods"
        }
    ],
    "sg:phone":"+1 856 467 0485",
    "sg:postcode":"08085",
    "sg:province":"NJ",
    "sg:tags":[
        "paper",
        "lamination"
    ],
    "wof:name":"Ccl Container",
    "wof:placetype":"venue"
},
  "geometry": {"coordinates":[-75.308545,39.749362],"type":"Point"}
}