{
  "type": "Feature",
  "properties": {
    "iso:country":"US",
    "sg:address":"87 Jersey St",
    "sg:city":"Paterson",
    "sg:classifiers":[
        {
            "category":"Retail",
            "subcategory":"Auto Repair",
            "type":"Services"
        }
    ],
    "sg:phone":"+1 973 742 9330",
    "sg:postcode":"07501",
    "sg:province":"NJ",
    "wof:name":"R A Auto Service",
    "wof:placetype":"venue"
},
  "geometry": {"coordinates":[-74.175791,40.911738],"type":"Point"}
}