{
  "type": "Feature",
  "properties": {
    "iso:country":"US",
    "sg:address":"6 Sommers Ave",
    "sg:city":"Somers Point",
    "sg:classifiers":[
        {
            "category":"Insurance",
            "subcategory":"Insurance Agent",
            "type":"Services"
        }
    ],
    "sg:phone":"+1   ",
    "sg:postcode":"08244",
    "sg:province":"NJ",
    "wof:name":"Nagle & Associates",
    "wof:placetype":"venue"
},
  "geometry": {"coordinates":[-74.59576,39.309801],"type":"Point"}
}