{
  "type": "Feature",
  "properties": {
    "addr:full":"7 Homestead Dr Columbus NJ 08022",
    "addr:housenumber":"7",
    "addr:postcode":"08022",
    "addr:street":"Homestead Dr",
    "iso:country":"US",
    "sg:address":"7 Homestead Dr",
    "sg:city":"Columbus",
    "sg:classifiers":[
        {
            "category":"Social Services",
            "subcategory":"Adult Care",
            "type":"Services"
        },
        {
            "category":"Health Services",
            "subcategory":"Nursing And Care Facility",
            "type":"Services"
        }
    ],
    "sg:phone":"+1 609 298 8080",
    "sg:postcode":"08022",
    "sg:province":"NJ",
    "sg:tags":[
        "residential"
    ],
    "wof:name":"Homestead At Mansfield Inc",
    "wof:placetype":"venue"
},
  "geometry": {"coordinates":[-74.74711600000001,40.072098],"type":"Point"}
}