{
  "type": "Feature",
  "properties": {
    "addr:full":"375 Euclid Ave Manasquan NJ 08736",
    "addr:housenumber":"375",
    "addr:postcode":"08736",
    "addr:street":"Euclid Ave",
    "iso:country":"US",
    "sg:address":"375 Euclid Ave",
    "sg:city":"Manasquan",
    "sg:classifiers":[
        {
            "category":"Retail",
            "subcategory":"Repair Shop",
            "type":"Services"
        }
    ],
    "sg:phone":"+1   ",
    "sg:postcode":"08736",
    "sg:province":"NJ",
    "wof:name":"Toms TV Service",
    "wof:placetype":"venue"
},
  "geometry": {"coordinates":[-74.043329,40.117274],"type":"Point"}
}