{
  "type": "Feature",
  "properties": {
    "addr:full":"369 Monroe Ave Kenilworth NJ 07033",
    "addr:housenumber":"369",
    "addr:postcode":"07033",
    "addr:street":"Monroe Ave",
    "iso:country":"US",
    "sg:address":"369 Monroe Ave",
    "sg:city":"Kenilworth",
    "sg:classifiers":[
        {
            "category":"Organizations",
            "subcategory":"Religious Organization",
            "type":"Services"
        }
    ],
    "sg:phone":"+1 908 276 8057",
    "sg:postcode":"07033",
    "sg:province":"NJ",
    "wof:name":"St Paul A M E Church",
    "wof:placetype":"venue"
},
  "geometry": {"coordinates":[-74.298599,40.679501],"type":"Point"}
}