{
  "type": "Feature",
  "properties": {
    "addr:full":"390 Communipaw Ave Jersey City NJ 07304",
    "addr:housenumber":"390",
    "addr:postcode":"07304",
    "addr:street":"Communipaw Ave",
    "iso:country":"US",
    "sg:address":"390 Communipaw Ave",
    "sg:city":"Jersey City",
    "sg:classifiers":[
        {
            "category":"Restaurant",
            "type":"Food & Drink"
        }
    ],
    "sg:phone":"+1   ",
    "sg:postcode":"07304",
    "sg:province":"NJ",
    "sg:tags":[
        "eating"
    ],
    "wof:name":"Aguilar Rosalio",
    "wof:placetype":"venue"
},
  "geometry": {"coordinates":[-74.06447199999999,40.712988],"type":"Point"}
}