{
  "type": "Feature",
  "properties": {
    "addr:full":"270 Broad St Bloomfield NJ 07003",
    "addr:housenumber":"270",
    "addr:postcode":"07003",
    "addr:street":"Broad St",
    "iso:country":"US",
    "sg:address":"270 Broad St",
    "sg:city":"Bloomfield",
    "sg:classifiers":[
        {
            "category":"Wholesale",
            "subcategory":"Machinery & Supplies",
            "type":"Manufacturing & Wholesale Goods"
        }
    ],
    "sg:phone":"+1 973 748 5885",
    "sg:postcode":"07003",
    "sg:province":"NJ",
    "sg:tags":[
        "equipment",
        "railroad"
    ],
    "sg:website":"www.atlantictrack.com",
    "wof:name":"Atlantic Track & Turnout Co",
    "wof:placetype":"venue"
},
  "geometry": {"coordinates":[-74.19568700000001,40.802566],"type":"Point"}
}