{
  "type": "Feature",
  "properties": {
    "addr:full":"97 Clifton Ter Weehawken NJ 07086",
    "addr:housenumber":"97",
    "addr:postcode":"07086",
    "addr:street":"Clifton Ter",
    "iso:country":"US",
    "sg:address":"97 Clifton Ter",
    "sg:city":"Weehawken",
    "sg:classifiers":[
        {
            "category":"Professional",
            "subcategory":"Lawyer & Legal Services",
            "type":"Services"
        }
    ],
    "sg:phone":"+1 201 487 7430",
    "sg:postcode":"07086",
    "sg:province":"NJ",
    "sg:tags":[
        "attorney"
    ],
    "wof:name":"Catherine T Calabria",
    "wof:placetype":"venue"
},
  "geometry": {"coordinates":[-74.019015,40.775343],"type":"Point"}
}