{
  "type": "Feature",
  "properties": {
    "addr:full":"775 Newark Ave Jersey City NJ 07306",
    "addr:housenumber":"775",
    "addr:postcode":"07306",
    "addr:street":"Newark Ave",
    "iso:country":"US",
    "sg:address":"775 Newark Ave",
    "sg:city":"Jersey City",
    "sg:classifiers":[
        {
            "category":"Food & Beverages",
            "subcategory":"Groceries & Convenience Stores",
            "type":"Retail Goods"
        }
    ],
    "sg:phone":"+1 201 963 6400",
    "sg:postcode":"07306",
    "sg:province":"NJ",
    "wof:name":"Nadi Halal Meat & Grocery Store",
    "wof:placetype":"venue"
},
  "geometry": {"coordinates":[-74.06379699999999,40.735401],"type":"Point"}
}