{
  "type": "Feature",
  "properties": {
    "addr:full":"127 Pine St Montclair NJ 07042",
    "addr:housenumber":"127",
    "addr:postcode":"07042",
    "addr:street":"Pine St",
    "iso:country":"US",
    "sg:address":"127 Pine St",
    "sg:city":"Montclair",
    "sg:classifiers":[
        {
            "category":"Personal",
            "subcategory":"Beauty Salon",
            "type":"Services"
        }
    ],
    "sg:phone":"+1 973 509 9557",
    "sg:postcode":"07042",
    "sg:province":"NJ",
    "sg:tags":[
        "shop",
        "massage"
    ],
    "wof:name":"Exhale Day Spa of Montclair",
    "wof:placetype":"venue"
},
  "geometry": {"coordinates":[-74.207296,40.811804],"type":"Point"}
}