{
  "type": "Feature",
  "properties": {
    "addr:full":"28 Woods Rd Jackson NJ 08533",
    "addr:housenumber":"28",
    "addr:postcode":"08533",
    "addr:street":"Woods Rd",
    "iso:country":"US",
    "sg:address":"28 Woods Rd",
    "sg:city":"Jackson",
    "sg:classifiers":[
        {
            "category":"Wholesale",
            "subcategory":"Motor Vehicles",
            "type":"Manufacturing & Wholesale Goods"
        }
    ],
    "sg:phone":"+1 732 833 6299",
    "sg:postcode":"08533",
    "sg:province":"NJ",
    "wof:name":"Wholesale Motorsports Co",
    "wof:placetype":"venue"
},
  "geometry": {"coordinates":[-74.48056699999999,40.095529],"type":"Point"}
}