{
  "type": "Feature",
  "properties": {
    "addr:full":"330 State Park Rd Hope NJ 07825",
    "addr:housenumber":"330",
    "addr:postcode":"07825",
    "addr:street":"State Park Rd",
    "iso:country":"US",
    "sg:address":"330 State Park Rd",
    "sg:city":"Hope",
    "sg:classifiers":[
        {
            "category":"Government",
            "subcategory":"Office",
            "type":"Public Place"
        }
    ],
    "sg:phone":"+1   ",
    "sg:postcode":"07825",
    "sg:province":"NJ",
    "sg:tags":[
        "state",
        "park"
    ],
    "wof:name":"Jenny Jump State Forest",
    "wof:placetype":"venue"
},
  "geometry": {"coordinates":[-74.924091,40.913105],"type":"Point"}
}