{
  "type": "Feature",
  "properties": {
    "iso:country":"US",
    "sg:address":"1600 Saint Georges Ave",
    "sg:city":"Rahway",
    "sg:classifiers":[
        {
            "category":"Professional",
            "type":"Services"
        }
    ],
    "sg:phone":"+1 732 388 2340",
    "sg:postcode":"07065",
    "sg:province":"NJ",
    "sg:tags":[
        "establishment"
    ],
    "wof:name":"Advanced Network Inc",
    "wof:placetype":"venue"
},
  "geometry": {"coordinates":[-74.285357,40.61577],"type":"Point"}
}