{
  "type": "Feature",
  "properties": {
    "iso:country":"US",
    "sg:address":"215 Quakertown Rd",
    "sg:city":"Pittstown",
    "sg:classifiers":[
        {
            "category":"Home & Garden",
            "subcategory":"Garden Supply",
            "type":"Retail Goods"
        }
    ],
    "sg:phone":"+1 908 730 7123",
    "sg:postcode":"08867",
    "sg:province":"NJ",
    "sg:tags":[
        "farm",
        "nurseryman",
        "crop",
        "general"
    ],
    "wof:name":"Chia Sin Farms Inc",
    "wof:placetype":"venue"
},
  "geometry": {"coordinates":[-74.947639,40.567807],"type":"Point"}
}