{
  "type": "Feature",
  "properties": {
    "addr:full":"82 Park Ave Paterson NJ 07501",
    "addr:housenumber":"82",
    "addr:postcode":"07501",
    "addr:street":"Park Ave",
    "iso:country":"US",
    "sg:address":"82 Park Ave",
    "sg:city":"Paterson",
    "sg:classifiers":[
        {
            "category":"Health Services",
            "subcategory":"Doctor",
            "type":"Services"
        }
    ],
    "sg:phone":"+1 973 881 8568",
    "sg:postcode":"07501",
    "sg:province":"NJ",
    "sg:tags":[
        "surgeon",
        "oral"
    ],
    "wof:name":"Mayer David M DDS",
    "wof:placetype":"venue"
},
  "geometry": {"coordinates":[-74.162598,40.915199],"type":"Point"}
}