{
  "type": "Feature",
  "properties": {
    "addr:full":"25 S Main St Neptune NJ 07753",
    "addr:housenumber":"25",
    "addr:postcode":"07753",
    "addr:street":"S Main St",
    "iso:country":"US",
    "sg:address":"25 S Main St",
    "sg:city":"Neptune",
    "sg:classifiers":[
        {
            "category":"Retail",
            "subcategory":"Photofinishing",
            "type":"Services"
        }
    ],
    "sg:phone":"+1 732 775 9083",
    "sg:postcode":"07753",
    "sg:province":"NJ",
    "sg:tags":[
        "photo",
        "finishing"
    ],
    "wof:name":"Eckerd",
    "wof:placetype":"venue"
},
  "geometry": {"coordinates":[-74.01501,40.211556],"type":"Point"}
}