{
  "type": "Feature",
  "properties": {
    "iso:country":"US",
    "sg:address":"21 Crisfield Rd",
    "sg:city":"Sicklerville",
    "sg:classifiers":[
        {
            "category":"Professional",
            "subcategory":"Business Services",
            "type":"Services"
        },
        {
            "category":"Building & Trades",
            "subcategory":"Construction",
            "type":"Services"
        }
    ],
    "sg:phone":"+1 856 782 7437",
    "sg:postcode":"08081",
    "sg:province":"NJ",
    "sg:tags":[
        "plastering",
        "coping",
        "water",
        "treatment",
        "tiling",
        "pool",
        "swimming"
    ],
    "wof:name":"R H Technologies",
    "wof:placetype":"venue"
},
  "geometry": {"coordinates":[-74.989154,39.75289],"type":"Point"}
}