{
  "type": "Feature",
  "properties": {
    "addr:full":"18 W Olive St Westville NJ 08093",
    "addr:housenumber":"18",
    "addr:postcode":"08093",
    "addr:street":"W Olive St",
    "iso:country":"US",
    "sg:address":"18 W Olive St",
    "sg:city":"Westville",
    "sg:classifiers":[
        {
            "category":"Real Estate",
            "subcategory":"Real Estate Services",
            "type":"Services"
        }
    ],
    "sg:phone":"+1 856 742 8400",
    "sg:postcode":"08093",
    "sg:province":"NJ",
    "sg:tags":[
        "management",
        "property"
    ],
    "wof:name":"Pinnacle Hospitality Group Llc",
    "wof:placetype":"venue"
},
  "geometry": {"coordinates":[-75.132786,39.863945],"type":"Point"}
}