{
  "type": "Feature",
  "properties": {
    "addr:full":"9616 Amherst Ave Margate City NJ 08402",
    "addr:housenumber":"9616",
    "addr:postcode":"08402",
    "addr:street":"Amherst Ave Margate",
    "iso:country":"US",
    "sg:address":"9616 Amherst Ave",
    "sg:city":"Margate City",
    "sg:classifiers":[
        {
            "category":"Building & Trades",
            "subcategory":"Construction",
            "type":"Services"
        }
    ],
    "sg:phone":"+1 609 823 6344",
    "sg:postcode":"08402",
    "sg:province":"NJ",
    "sg:tags":[
        "house"
    ],
    "wof:name":"Cedarwood Builders",
    "wof:placetype":"venue"
},
  "geometry": {"coordinates":[-74.520388,39.323817],"type":"Point"}
}