{
  "type": "Feature",
  "properties": {
    "addr:full":"16 New St Bloomfield NJ 07003",
    "addr:housenumber":"16",
    "addr:postcode":"07003",
    "addr:street":"New St",
    "iso:country":"US",
    "sg:address":"16 New St",
    "sg:city":"Bloomfield",
    "sg:classifiers":[
        {
            "category":"Building & Trades",
            "subcategory":"Construction",
            "type":"Services"
        }
    ],
    "sg:phone":"+1 973 748 2488",
    "sg:postcode":"07003",
    "sg:province":"NJ",
    "sg:tags":[
        "painter"
    ],
    "wof:name":"All Hart Painting",
    "wof:placetype":"venue"
},
  "geometry": {"coordinates":[-74.192398,40.801102],"type":"Point"}
}