{
  "type": "Feature",
  "properties": {
    "iso:country":"US",
    "sg:address":"48 Newton Ave",
    "sg:city":"Woodbury",
    "sg:classifiers":[
        {
            "category":"Building & Trades",
            "subcategory":"Construction",
            "type":"Services"
        },
        {
            "category":"Professional",
            "subcategory":"Management & Consulting",
            "type":"Services"
        }
    ],
    "sg:phone":"+1 856 848 0919",
    "sg:postcode":"08096",
    "sg:province":"NJ",
    "sg:tags":[
        "house",
        "nonresidential"
    ],
    "wof:name":"Puente Construction Enterprise",
    "wof:placetype":"venue"
},
  "geometry": {"coordinates":[-75.151205,39.838412],"type":"Point"}
}