{
  "type": "Feature",
  "properties": {
    "addr:full":"1111 Parvin Mill Rd Elmer NJ 08318",
    "addr:housenumber":"1111",
    "addr:postcode":"08318",
    "addr:street":"Parvin Mill Rd",
    "iso:country":"US",
    "sg:address":"1111 Parvin Mill Rd",
    "sg:city":"Elmer",
    "sg:classifiers":[
        {
            "category":"Retail",
            "subcategory":"Event Space",
            "type":"Services"
        },
        {
            "category":"Sports & Exercise",
            "subcategory":"Golf",
            "type":"Entertainment"
        }
    ],
    "sg:phone":"+1 856 521 4163",
    "sg:postcode":"08318",
    "sg:province":"NJ",
    "sg:tags":[
        "facility",
        "hall",
        "course",
        "location",
        "reception",
        "wedding",
        "banquet"
    ],
    "sg:website":"http://www.runningdeergc.com/",
    "wof:name":"Running Deer Golf Club",
    "wof:placetype":"venue"
},
  "geometry": {"coordinates":[-75.123924,39.51712],"type":"Point"}
}