{
  "type": "Feature",
  "properties": {
    "iso:country":"US",
    "sg:address":"160 Morris St",
    "sg:city":"Morristown",
    "sg:classifiers":[
        {
            "category":"Banks & Credit Unions",
            "subcategory":"Financial Services",
            "type":"Services"
        },
        {
            "category":"Real Estate",
            "subcategory":"Real Estate Agent",
            "type":"Services"
        }
    ],
    "sg:phone":"+1 800 245 2272",
    "sg:postcode":"07960",
    "sg:province":"NJ",
    "sg:tags":[
        "broker",
        "mortgage"
    ],
    "sg:website":"www.century21atlantic.com",
    "wof:name":"Century 21 Atlantic Realtors",
    "wof:placetype":"venue"
},
  "geometry": {"coordinates":[-74.47214099999999,40.796254],"type":"Point"}
}