{
  "type": "Feature",
  "properties": {
    "addr:full":"1485 Ocean Ave Sea Bright NJ 07760",
    "addr:housenumber":"1485",
    "addr:postcode":"07760",
    "addr:street":"Ocean Ave",
    "iso:country":"US",
    "sg:address":"1485 Ocean Ave",
    "sg:city":"Sea Bright",
    "sg:classifiers":[
        {
            "category":"Recreation",
            "type":"Entertainment"
        }
    ],
    "sg:phone":"+1 732 842 2273",
    "sg:postcode":"07760",
    "sg:province":"NJ",
    "sg:tags":[
        "club",
        "beach",
        "cabana"
    ],
    "wof:name":"Driftwood Beach Club Inc",
    "wof:placetype":"venue"
},
  "geometry": {"coordinates":[-73.97386899999999,40.349732],"type":"Point"}
}