{
  "type": "Feature",
  "properties": {
    "iso:country":"US",
    "sg:address":"14 Jenks Rd",
    "sg:city":"Morristown",
    "sg:classifiers":[
        {
            "category":"Professional",
            "type":"Services"
        }
    ],
    "sg:phone":"+1 973 605 1954",
    "sg:postcode":"07960",
    "sg:province":"NJ",
    "sg:tags":[
        "establishment"
    ],
    "wof:name":"Simple Cooking",
    "wof:placetype":"venue"
},
  "geometry": {"coordinates":[-74.505912,40.765907],"type":"Point"}
}