{
  "type": "Feature",
  "properties": {
    "addr:full":"615 Co Rd 524 Allentown NJ 08501",
    "addr:housenumber":"615",
    "addr:postcode":"08501",
    "addr:street":"Co Rd 524",
    "iso:country":"US",
    "sg:address":"615 Co Rd 524",
    "sg:city":"Allentown",
    "sg:classifiers":[
        {
            "category":"Farming",
            "subcategory":"Livestock Farm",
            "type":"Manufacturing & Wholesale Goods"
        }
    ],
    "sg:phone":"+1 609 259 7673",
    "sg:postcode":"08501",
    "sg:province":"NJ",
    "sg:tags":[
        "equine"
    ],
    "wof:name":"Red Gate Farm",
    "wof:placetype":"venue"
},
  "geometry": {"coordinates":[-74.475264,40.188705],"type":"Point"}
}