{
  "type": "Feature",
  "properties": {
    "iso:country":"US",
    "sg:address":"69 Hillcrest Rd",
    "sg:city":"West Caldwell",
    "sg:classifiers":[
        {
            "category":"Building & Trades",
            "subcategory":"Plumbing",
            "type":"Services"
        }
    ],
    "sg:phone":"+1 973 226 4899",
    "sg:postcode":"07006",
    "sg:province":"NJ",
    "wof:name":"Atkul Company",
    "wof:placetype":"venue"
},
  "geometry": {"coordinates":[-74.279301,40.849717],"type":"Point"}
}