{
  "type": "Feature",
  "properties": {
    "iso:country":"US",
    "sg:address":"26 N Morris St",
    "sg:city":"Dover",
    "sg:classifiers":[
        {
            "category":"Home & Garden",
            "subcategory":"Furniture",
            "type":"Retail Goods"
        }
    ],
    "sg:phone":"+1 973 366 0174",
    "sg:postcode":"07801",
    "sg:province":"NJ",
    "wof:name":"Dover Furniture Corp",
    "wof:placetype":"venue"
},
  "geometry": {"coordinates":[-74.557636,40.885701],"type":"Point"}
}