{
  "type": "Feature",
  "properties": {
    "addr:full":"1634 Springfield Ave Maplewood NJ 07040",
    "addr:housenumber":"1634",
    "addr:postcode":"07040",
    "addr:street":"Springfield Ave",
    "iso:country":"US",
    "sg:address":"1634 Springfield Ave",
    "sg:city":"Maplewood",
    "sg:classifiers":[
        {
            "category":"Education",
            "subcategory":"Dance Studio",
            "type":"Public Place"
        }
    ],
    "sg:phone":"+1 973 761 7236",
    "sg:postcode":"07040",
    "sg:province":"NJ",
    "sg:tags":[
        "instruction",
        "dancing"
    ],
    "wof:name":"Bette White Dance Center",
    "wof:placetype":"venue"
},
  "geometry": {"coordinates":[-74.25806300000001,40.722399],"type":"Point"}
}