{
  "type": "Feature",
  "properties": {
    "addr:full":"2411 Oak Ave Northfield NJ 08225",
    "addr:housenumber":"2411",
    "addr:postcode":"08225",
    "addr:street":"Oak Ave",
    "iso:country":"US",
    "sg:address":"2411 Oak Ave",
    "sg:city":"Northfield",
    "sg:classifiers":[
        {
            "category":"Building & Trades",
            "subcategory":"Electrical",
            "type":"Services"
        }
    ],
    "sg:phone":"+1 609 641 8484",
    "sg:postcode":"08225",
    "sg:province":"NJ",
    "sg:tags":[
        "electrical",
        "contractor"
    ],
    "wof:name":"Conover Conklin Electric Corp",
    "wof:placetype":"venue"
},
  "geometry": {"coordinates":[-74.57048899999999,39.365951],"type":"Point"}
}