{
  "type": "Feature",
  "properties": {
    "addr:full":"142 E Bay Ave Manahawkin NJ 08050",
    "addr:housenumber":"142",
    "addr:postcode":"08050",
    "addr:street":"E Bay Ave",
    "iso:country":"US",
    "sg:address":"142 E Bay Ave",
    "sg:city":"Manahawkin",
    "sg:phone":"+1 609 978 9009",
    "sg:postcode":"08050",
    "sg:province":"NJ",
    "sg:website":"http://www.homealliancerealty.com",
    "wof:name":"Home Alliance Realty",
    "wof:placetype":"venue"
},
  "geometry": {"coordinates":[-74.254352,39.693076],"type":"Point"}
}