{
  "type": "Feature",
  "properties": {
    "addr:full":"1 University Plz Hackensack NJ 07601",
    "addr:housenumber":"1",
    "addr:postcode":"07601",
    "addr:street":"University Plz",
    "iso:country":"US",
    "sg:address":"1 University Plz",
    "sg:city":"Hackensack",
    "sg:classifiers":[
        {
            "category":"Professional",
            "subcategory":"Lawyer & Legal Services",
            "type":"Services"
        }
    ],
    "sg:phone":"+1 212 643 0044",
    "sg:postcode":"07601",
    "sg:province":"NJ",
    "wof:name":"Eisbrouch Antoniewicz & Marsh P C",
    "wof:placetype":"venue"
},
  "geometry": {"coordinates":[-74.03296,40.89843],"type":"Point"}
}