{
  "type": "Feature",
  "properties": {
    "addr:full":"26 Sorrel Run Mount Laurel NJ 08054",
    "addr:housenumber":"26",
    "addr:postcode":"08054",
    "addr:street":"Sorrel Run",
    "iso:country":"US",
    "sg:address":"26 Sorrel Run",
    "sg:city":"Mount Laurel",
    "sg:classifiers":[
        {
            "category":"Professional",
            "subcategory":"Computer Services",
            "type":"Services"
        }
    ],
    "sg:phone":"+1   ",
    "sg:postcode":"08054",
    "sg:province":"NJ",
    "sg:tags":[
        "prepackaged",
        "software"
    ],
    "wof:name":"Akwins Software Inc",
    "wof:placetype":"venue"
},
  "geometry": {"coordinates":[-74.880027,39.934879],"type":"Point"}
}