{
  "type": "Feature",
  "properties": {
    "iso:country":"US",
    "sg:address":"33 Maida Ter",
    "sg:city":"Red Bank",
    "sg:classifiers":[
        {
            "category":"Freight",
            "type":"Transportation"
        }
    ],
    "sg:phone":"+1 732 219 0071",
    "sg:postcode":"07701",
    "sg:province":"NJ",
    "sg:tags":[
        "courier"
    ],
    "wof:name":"Apostle Courier Svc",
    "wof:placetype":"venue"
},
  "geometry": {"coordinates":[-74.080119,40.372657],"type":"Point"}
}