{
  "type": "Feature",
  "properties": {
    "addr:full":"59 E Mill Rd Unit 102 Long Valley NJ 07853",
    "addr:housenumber":"59;102",
    "addr:postcode":"07853",
    "addr:street":"E Mill Rd Unit",
    "iso:country":"US",
    "sg:address":"59 E Mill Rd Unit 102",
    "sg:city":"Long Valley",
    "sg:classifiers":[
        {
            "category":"Health Services",
            "subcategory":"Chiropractor",
            "type":"Services"
        }
    ],
    "sg:phone":"+1 908 876 9188",
    "sg:postcode":"07853",
    "sg:province":"NJ",
    "wof:name":"Genesis Chiropractic Center Office Hours Mon-Sat",
    "wof:placetype":"venue"
},
  "geometry": {"coordinates":[-74.77387,40.784123],"type":"Point"}
}