{
  "type": "Feature",
  "properties": {
    "addr:full":"315 Main St Paterson NJ 07505",
    "addr:housenumber":"315",
    "addr:postcode":"07505",
    "addr:street":"Main St",
    "iso:country":"US",
    "sg:address":"315 Main St",
    "sg:city":"Paterson",
    "sg:classifiers":[
        {
            "category":"Retail",
            "subcategory":"Repair Shop",
            "type":"Services"
        }
    ],
    "sg:phone":"+1 973 279 6353",
    "sg:postcode":"07505",
    "sg:province":"NJ",
    "wof:name":"Altron TV Service Incorporated",
    "wof:placetype":"venue"
},
  "geometry": {"coordinates":[-74.17330800000001,40.914061],"type":"Point"}
}