{
  "type": "Feature",
  "properties": {
    "iso:country":"US",
    "sg:address":"20 Coronet Ave",
    "sg:city":"Lincroft",
    "sg:classifiers":[
        {
            "category":"Building & Trades",
            "subcategory":"Construction",
            "type":"Services"
        }
    ],
    "sg:phone":"+1 732 747 5141",
    "sg:postcode":"07738",
    "sg:province":"NJ",
    "sg:tags":[
        "nonresidential",
        "general",
        "contractor"
    ],
    "wof:name":"Marco Ciriani Inc",
    "wof:placetype":"venue"
},
  "geometry": {"coordinates":[-74.11517499999999,40.327826],"type":"Point"}
}