{
  "type": "Feature",
  "properties": {
    "addr:full":"167 Union St Lodi NJ 07644",
    "addr:housenumber":"167",
    "addr:postcode":"07644",
    "addr:street":"Union St",
    "iso:country":"US",
    "sg:address":"167 Union St",
    "sg:city":"Lodi",
    "sg:classifiers":[
        {
            "category":"Recreation",
            "type":"Entertainment"
        }
    ],
    "sg:phone":"+1   ",
    "sg:postcode":"07644",
    "sg:province":"NJ",
    "sg:tags":[
        "club",
        "membership"
    ],
    "wof:name":"Veterans Fgn Wars Post No 5082",
    "wof:placetype":"venue"
},
  "geometry": {"coordinates":[-74.080585,40.87539],"type":"Point"}
}