{
  "type": "Feature",
  "properties": {
    "iso:country":"US",
    "sg:address":"545 Georges Rd",
    "sg:city":"North Brunswick",
    "sg:classifiers":[
        {
            "category":"Retail",
            "subcategory":"Auto Repair",
            "type":"Services"
        }
    ],
    "sg:phone":"+1   ",
    "sg:postcode":"08902",
    "sg:province":"NJ",
    "sg:tags":[
        "automotive"
    ],
    "wof:name":"Volvo Car Srvc-Prgressive Auto",
    "wof:placetype":"venue"
},
  "geometry": {"coordinates":[-74.44999799999999,40.471278],"type":"Point"}
}