{
  "type": "Feature",
  "properties": {
    "addr:full":"110 Hickory Corner Rd Hightstown NJ 08520",
    "addr:housenumber":"110",
    "addr:postcode":"08520",
    "addr:street":"Hickory Corner Rd",
    "iso:country":"US",
    "sg:address":"110 Hickory Corner Rd",
    "sg:city":"Hightstown",
    "sg:classifiers":[
        {
            "category":"Organizations",
            "subcategory":"Community Association",
            "type":"Services"
        }
    ],
    "sg:phone":"+1 609 448 9794",
    "sg:postcode":"08520",
    "sg:province":"NJ",
    "sg:tags":[
        "membership",
        "fraternal",
        "civic"
    ],
    "wof:name":"Bpoe 1955",
    "wof:placetype":"venue"
},
  "geometry": {"coordinates":[-74.55483099999999,40.262459],"type":"Point"}
}