{
  "type": "Feature",
  "properties": {
    "addr:full":"908 Main St Asbury Park NJ 07712",
    "addr:housenumber":"908",
    "addr:postcode":"07712",
    "addr:street":"Main St Asbury",
    "iso:country":"US",
    "sg:address":"908 Main St",
    "sg:city":"Asbury Park",
    "sg:classifiers":[
        {
            "category":"Health Services",
            "subcategory":"Clinic",
            "type":"Services"
        }
    ],
    "sg:phone":"+1 732 774 5451",
    "sg:postcode":"07712",
    "sg:province":"NJ",
    "wof:name":"Health Point",
    "wof:placetype":"venue"
},
  "geometry": {"coordinates":[-74.010993,40.222378],"type":"Point"}
}