{
  "type": "Feature",
  "properties": {
    "iso:country":"US",
    "sg:address":"8 Old Bridge Tpke",
    "sg:city":"South River",
    "sg:classifiers":[
        {
            "category":"Health Services",
            "subcategory":"Doctor",
            "type":"Services"
        }
    ],
    "sg:phone":"+1 732 390 4888",
    "sg:postcode":"08882",
    "sg:province":"NJ",
    "sg:tags":[
        "physician",
        "surgeon"
    ],
    "wof:name":"Nilesh S Mhaskar MD",
    "wof:placetype":"venue"
},
  "geometry": {"coordinates":[-74.380298,40.430163],"type":"Point"}
}