{
  "type": "Feature",
  "properties": {
    "iso:country":"US",
    "sg:address":"127 Pine St",
    "sg:city":"Montclair",
    "sg:classifiers":[
        {
            "category":"Professional",
            "type":"Services"
        }
    ],
    "sg:phone":"+1 973 744 4404",
    "sg:postcode":"07042",
    "sg:province":"NJ",
    "sg:tags":[
        "establishment"
    ],
    "wof:name":"Healing Hands By Nina Corp",
    "wof:placetype":"venue"
},
  "geometry": {"coordinates":[-74.20716899999999,40.812129],"type":"Point"}
}