{
  "type": "Feature",
  "properties": {
    "addr:full":"52 Harbourton Woodsville Rd Pennington NJ 08534",
    "addr:housenumber":"52",
    "addr:postcode":"08534",
    "addr:street":"Harbourton Woodsville Rd",
    "iso:country":"US",
    "sg:address":"52 Harbourton Woodsville Rd",
    "sg:city":"Pennington",
    "sg:classifiers":[
        {
            "category":"Professional",
            "type":"Services"
        }
    ],
    "sg:phone":"+1 609 737 0790",
    "sg:postcode":"08534",
    "sg:province":"NJ",
    "sg:tags":[
        "arts",
        "artist"
    ],
    "wof:name":"Morris Docktor",
    "wof:placetype":"venue"
},
  "geometry": {"coordinates":[-74.824654,40.363081],"type":"Point"}
}