{
  "type": "Feature",
  "properties": {
    "iso:country":"US",
    "sg:address":"2208 Stanley Ter",
    "sg:city":"Union",
    "sg:classifiers":[
        {
            "category":"Organizations",
            "subcategory":"Religious Organization",
            "type":"Services"
        }
    ],
    "sg:phone":"+1 908 686 8171",
    "sg:postcode":"07083",
    "sg:province":"NJ",
    "sg:tags":[
        "church"
    ],
    "wof:name":"Ukrainian Evangelical Church",
    "wof:placetype":"venue"
},
  "geometry": {"coordinates":[-74.267354,40.713854],"type":"Point"}
}