{
  "type": "Feature",
  "properties": {
    "addr:full":"19 Main St High Bridge NJ 08829",
    "addr:housenumber":"19",
    "addr:postcode":"08829",
    "addr:street":"Main St",
    "iso:country":"US",
    "sg:address":"19 Main St",
    "sg:city":"High Bridge",
    "sg:classifiers":[
        {
            "category":"Shopping",
            "subcategory":"Gifts & Souvenirs",
            "type":"Retail Goods"
        }
    ],
    "sg:phone":"+1 908 638 6644",
    "sg:postcode":"08829",
    "sg:province":"NJ",
    "sg:tags":[
        "shop"
    ],
    "wof:name":"Eggsotic Events",
    "wof:placetype":"venue"
},
  "geometry": {"coordinates":[-74.895673,40.667494],"type":"Point"}
}