{
  "type": "Feature",
  "properties": {
    "addr:full":"302 E 21st Ave Wildwood NJ 08260",
    "addr:housenumber":"302",
    "addr:postcode":"08260",
    "addr:street":"E 21St Ave",
    "iso:country":"US",
    "sg:address":"302 E 21st Ave",
    "sg:city":"Wildwood",
    "sg:classifiers":[
        {
            "category":"Real Estate",
            "subcategory":"Architect",
            "type":"Services"
        }
    ],
    "sg:phone":"+1 609 523 6666",
    "sg:postcode":"08260",
    "sg:province":"NJ",
    "wof:name":"Thomson Robert F",
    "wof:placetype":"venue"
},
  "geometry": {"coordinates":[-74.803912,38.994715],"type":"Point"}
}