{
  "type": "Feature",
  "properties": {
    "addr:full":"1801 W Edgar Rd Linden NJ 07036",
    "addr:housenumber":"1801",
    "addr:postcode":"07036",
    "addr:street":"W Edgar Rd",
    "iso:country":"US",
    "sg:address":"1801 W Edgar Rd",
    "sg:city":"Linden",
    "sg:classifiers":[
        {
            "category":"Home & Garden",
            "subcategory":"Carpets & Floor Coverings",
            "type":"Retail Goods"
        }
    ],
    "sg:phone":"+1 908 862 3100",
    "sg:postcode":"07036",
    "sg:province":"NJ",
    "sg:tags":[
        "carpeting"
    ],
    "wof:name":"Affordable Floors Inc",
    "wof:placetype":"venue"
},
  "geometry": {"coordinates":[-74.257301,40.611099],"type":"Point"}
}