{
  "type": "Feature",
  "properties": {
    "iso:country":"US",
    "sg:address":"5 Rosewood Dr",
    "sg:city":"Spring Lake",
    "sg:classifiers":[
        {
            "category":"Wholesale",
            "subcategory":"Machinery & Supplies",
            "type":"Manufacturing & Wholesale Goods"
        }
    ],
    "sg:phone":"+1 732 974 2081",
    "sg:postcode":"07762",
    "sg:province":"NJ",
    "sg:tags":[
        "commercial",
        "fan"
    ],
    "wof:name":"S J Savoia Assoc Inc",
    "wof:placetype":"venue"
},
  "geometry": {"coordinates":[-74.046806,40.152813],"type":"Point"}
}