{
  "type": "Feature",
  "properties": {
    "iso:country":"US",
    "sg:address":"17 11th St",
    "sg:city":"Fair Lawn",
    "sg:classifiers":[
        {
            "category":"Professional",
            "subcategory":"Business Services",
            "type":"Services"
        }
    ],
    "sg:phone":"+1   ",
    "sg:postcode":"07410",
    "sg:province":"NJ",
    "wof:name":"Bernhardt Ruth Fund Raising",
    "wof:placetype":"venue"
},
  "geometry": {"coordinates":[-74.130038,40.936577],"type":"Point"}
}