{
  "type": "Feature",
  "properties": {
    "iso:country":"US",
    "sg:address":"118 Broad Ave Ste N4",
    "sg:city":"Palisades Park",
    "sg:classifiers":[
        {
            "category":"Shopping",
            "subcategory":"Pharmacy",
            "type":"Retail Goods"
        }
    ],
    "sg:phone":"+1 201 945 7222",
    "sg:postcode":"07650",
    "sg:province":"NJ",
    "sg:tags":[
        "drugstore"
    ],
    "wof:name":"Benjamins Pharmacy",
    "wof:placetype":"venue"
},
  "geometry": {"coordinates":[-74.00009900000001,40.8447],"type":"Point"}
}