{
  "type": "Feature",
  "properties": {
    "addr:full":"86 Oneida Ave North Plainfield NJ 07060",
    "addr:housenumber":"86",
    "addr:postcode":"07060",
    "addr:street":"Oneida Ave",
    "iso:country":"US",
    "sg:address":"86 Oneida Ave",
    "sg:city":"North Plainfield",
    "sg:classifiers":[
        {
            "category":"Professional",
            "subcategory":"Management & Consulting",
            "type":"Services"
        }
    ],
    "sg:phone":"+1 908 788 4944",
    "sg:postcode":"07060",
    "sg:province":"NJ",
    "sg:tags":[
        "fuel"
    ],
    "wof:name":"JMT Real Estate Svc Inc",
    "wof:placetype":"venue"
},
  "geometry": {"coordinates":[-74.4196,40.628533],"type":"Point"}
}