{
  "type": "Feature",
  "properties": {
    "addr:full":"8 Greensprings Dr Lakewood NJ 08701",
    "addr:housenumber":"8",
    "addr:postcode":"08701",
    "addr:street":"Greensprings Dr",
    "iso:country":"US",
    "sg:address":"8 Greensprings Dr",
    "sg:city":"Lakewood",
    "sg:classifiers":[
        {
            "category":"Professional",
            "type":"Services"
        }
    ],
    "sg:phone":"+1   ",
    "sg:postcode":"08701",
    "sg:province":"NJ",
    "wof:name":"Mask",
    "wof:placetype":"venue"
},
  "geometry": {"coordinates":[-74.175347,40.038118],"type":"Point"}
}