{
  "type": "Feature",
  "properties": {
    "addr:full":"10 Bonnie Ln Willingboro NJ 08046",
    "addr:housenumber":"10",
    "addr:postcode":"08046",
    "addr:street":"Bonnie Ln",
    "iso:country":"US",
    "sg:address":"10 Bonnie Ln",
    "sg:city":"Willingboro",
    "sg:classifiers":[
        {
            "category":"Professional",
            "subcategory":"Management & Consulting",
            "type":"Services"
        }
    ],
    "sg:phone":"+1 609 871 0765",
    "sg:postcode":"08046",
    "sg:province":"NJ",
    "wof:name":"Sinclair McMullin",
    "wof:placetype":"venue"
},
  "geometry": {"coordinates":[-74.892561,40.036968],"type":"Point"}
}