{
  "type": "Feature",
  "properties": {
    "addr:full":"7804 Amherst Ave Margate City NJ 08402",
    "addr:housenumber":"7804",
    "addr:postcode":"08402",
    "addr:street":"Amherst Ave Margate",
    "iso:country":"US",
    "sg:address":"7804 Amherst Ave",
    "sg:city":"Margate City",
    "sg:classifiers":[
        {
            "category":"Education",
            "subcategory":"School",
            "type":"Public Place"
        }
    ],
    "sg:phone":"+1   ",
    "sg:postcode":"08402",
    "sg:province":"NJ",
    "sg:website":"www.margateschools.org",
    "wof:name":"EUGENE A Tighe Middle School",
    "wof:placetype":"venue"
},
  "geometry": {"coordinates":[-74.502831,39.33391],"type":"Point"}
}