{
  "type": "Feature",
  "properties": {
    "iso:country":"US",
    "sg:address":"571 Walnut St",
    "sg:city":"Elizabeth",
    "sg:classifiers":[
        {
            "category":"Building & Trades",
            "subcategory":"Construction",
            "type":"Services"
        }
    ],
    "sg:phone":"+1 908 351 6784",
    "sg:postcode":"07201",
    "sg:province":"NJ",
    "sg:tags":[
        "general",
        "contractor"
    ],
    "wof:name":"Santa Rosa Constr & Contractor",
    "wof:placetype":"venue"
},
  "geometry": {"coordinates":[-74.208444,40.67601],"type":"Point"}
}