{
  "type": "Feature",
  "properties": {
    "iso:country":"US",
    "sg:address":"1931 Long Hill Rd",
    "sg:city":"Millington",
    "sg:classifiers":[
        {
            "category":"Restaurant",
            "type":"Food & Drink"
        }
    ],
    "sg:phone":"+1 908 647 7558",
    "sg:postcode":"07946",
    "sg:province":"NJ",
    "wof:name":"Millington Station Cafe",
    "wof:placetype":"venue"
},
  "geometry": {"coordinates":[-74.523961,40.673874],"type":"Point"}
}