{
  "type": "Feature",
  "properties": {
    "addr:full":"44 Hawthorne Ln Willingboro NJ 08046",
    "addr:housenumber":"44",
    "addr:postcode":"08046",
    "addr:street":"Hawthorne Ln",
    "iso:country":"US",
    "sg:address":"44 Hawthorne Ln",
    "sg:city":"Willingboro",
    "sg:classifiers":[
        {
            "category":"Building & Trades",
            "subcategory":"Cleaning & Sanitation",
            "type":"Services"
        }
    ],
    "sg:phone":"+1 609 871 7440",
    "sg:postcode":"08046",
    "sg:province":"NJ",
    "wof:name":"Dash Property Mntnc & Cleaning",
    "wof:placetype":"venue"
},
  "geometry": {"coordinates":[-74.873876,40.038242],"type":"Point"}
}