{
  "type": "Feature",
  "properties": {
    "iso:country":"US",
    "sg:address":"83 Dewolf Rd",
    "sg:city":"Old Tappan",
    "sg:classifiers":[
        {
            "category":"Restaurant",
            "type":"Food & Drink"
        }
    ],
    "sg:phone":"+1 201 767 4311",
    "sg:postcode":"07675",
    "sg:province":"NJ",
    "wof:name":"Club At Old Tappan",
    "wof:placetype":"venue"
},
  "geometry": {"coordinates":[-73.97783200000001,41.02276],"type":"Point"}
}