{
  "type": "Feature",
  "properties": {
    "iso:country":"US",
    "sg:address":"22 Allerton Rd",
    "sg:city":"Lebanon",
    "sg:classifiers":[
        {
            "category":"Social Services",
            "subcategory":"Child Care",
            "type":"Services"
        }
    ],
    "sg:phone":"+1   ",
    "sg:postcode":"08833",
    "sg:province":"NJ",
    "sg:tags":[
        "day"
    ],
    "wof:name":"ABC Academy",
    "wof:placetype":"venue"
},
  "geometry": {"coordinates":[-74.863269,40.615428],"type":"Point"}
}