{
  "type": "Feature",
  "properties": {
    "addr:full":"10 Oxford St Montclair NJ 07042",
    "addr:housenumber":"10",
    "addr:postcode":"07042",
    "addr:street":"Oxford St",
    "iso:country":"US",
    "sg:address":"10 Oxford St",
    "sg:city":"Montclair",
    "sg:classifiers":[
        {
            "category":"Banks & Credit Unions",
            "subcategory":"Financial Services",
            "type":"Services"
        }
    ],
    "sg:phone":"+1   ",
    "sg:postcode":"07042",
    "sg:province":"NJ",
    "sg:tags":[
        "investor"
    ],
    "wof:name":"Bill Louisanna Investments LLC",
    "wof:placetype":"venue"
},
  "geometry": {"coordinates":[-74.205933,40.816155],"type":"Point"}
}