{
  "type": "Feature",
  "properties": {
    "addr:full":"533 New Brunswick Ave Perth Amboy NJ 08861",
    "addr:housenumber":"533",
    "addr:postcode":"08861",
    "addr:street":"New Brunswick Ave",
    "iso:country":"US",
    "sg:address":"533 New Brunswick Ave",
    "sg:city":"Perth Amboy",
    "sg:classifiers":[
        {
            "category":"Health Services",
            "subcategory":"Health Practitioner",
            "type":"Services"
        }
    ],
    "sg:phone":"+1 732 697 1063",
    "sg:postcode":"08861",
    "sg:province":"NJ",
    "sg:tags":[
        "therapy",
        "physical"
    ],
    "wof:name":"Twin Boro Physical Therapy",
    "wof:placetype":"venue"
},
  "geometry": {"coordinates":[-74.281716,40.518792],"type":"Point"}
}