{
  "type": "Feature",
  "properties": {
    "iso:country":"US",
    "sg:address":"46 Prospect St",
    "sg:city":"Midland Park",
    "sg:classifiers":[
        {
            "category":"Professional",
            "subcategory":"Engineering",
            "type":"Services"
        }
    ],
    "sg:phone":"+1 201 447 3035",
    "sg:postcode":"07432",
    "sg:province":"NJ",
    "wof:name":"Douglas Hill Consulting",
    "wof:placetype":"venue"
},
  "geometry": {"coordinates":[-74.14118999999999,40.993099],"type":"Point"}
}