{
  "type": "Feature",
  "properties": {
    "addr:full":"4200 Sylon Blvd Unit 4202 Hainesport NJ 08036",
    "addr:housenumber":"4200",
    "addr:postcode":"4202;08036",
    "addr:street":"Sylon Blvd Unit",
    "iso:country":"US",
    "sg:address":"4200 Sylon Blvd Unit 4202",
    "sg:city":"Hainesport",
    "sg:classifiers":[
        {
            "category":"Professional",
            "subcategory":"Detective & Security Services",
            "type":"Services"
        }
    ],
    "sg:phone":"+1 609 265 7661",
    "sg:postcode":"08036",
    "sg:province":"NJ",
    "sg:tags":[
        "equipment",
        "system",
        "consultant"
    ],
    "wof:name":"Heron Enterprises",
    "wof:placetype":"venue"
},
  "geometry": {"coordinates":[-74.849665,39.979299],"type":"Point"}
}