{
  "type": "Feature",
  "properties": {
    "addr:full":"1000 Arctic Ave Atlantic City NJ 08401",
    "addr:housenumber":"1000",
    "addr:postcode":"08401",
    "addr:street":"Arctic Ave",
    "iso:country":"US",
    "sg:address":"1000 Arctic Ave",
    "sg:city":"Atlantic City",
    "sg:classifiers":[
        {
            "category":"Banks & Credit Unions",
            "subcategory":"Bank",
            "type":"Services"
        }
    ],
    "sg:phone":"+1   ",
    "sg:postcode":"08401",
    "sg:province":"NJ",
    "sg:tags":[
        "national",
        "commercial"
    ],
    "wof:name":"Fleet",
    "wof:placetype":"venue"
},
  "geometry": {"coordinates":[-74.42465,39.365451],"type":"Point"}
}