{
  "type": "Feature",
  "properties": {
    "iso:country":"US",
    "sg:address":"523 Stuyvesant Ave",
    "sg:city":"Irvington",
    "sg:classifiers":[
        {
            "category":"Food & Beverages",
            "subcategory":"Groceries & Convenience Stores",
            "type":"Retail Goods"
        }
    ],
    "sg:phone":"+1   ",
    "sg:postcode":"07111",
    "sg:province":"NJ",
    "wof:name":"Zarzuela Grocery & Deli",
    "wof:placetype":"venue"
},
  "geometry": {"coordinates":[-74.235472,40.73192],"type":"Point"}
}