{
  "type": "Feature",
  "properties": {
    "addr:full":"322 S Main St Lodi NJ 07644",
    "addr:housenumber":"322",
    "addr:postcode":"07644",
    "addr:street":"S Main St",
    "iso:country":"US",
    "sg:address":"322 S Main St",
    "sg:city":"Lodi",
    "sg:classifiers":[
        {
            "category":"Restaurant",
            "type":"Food & Drink"
        }
    ],
    "sg:phone":"+1 973 473 8555",
    "sg:postcode":"07644",
    "sg:province":"NJ",
    "wof:name":"Grill At Lodi",
    "wof:placetype":"venue"
},
  "geometry": {"coordinates":[-74.093593,40.865569],"type":"Point"}
}