{
  "type": "Feature",
  "properties": {
    "iso:country":"US",
    "sg:address":"569 Millburn Ave",
    "sg:city":"Short Hills",
    "sg:classifiers":[
        {
            "category":"Building & Trades",
            "subcategory":"Locksmith",
            "type":"Services"
        }
    ],
    "sg:phone":"+1 888 546 4340",
    "sg:postcode":"07078",
    "sg:province":"NJ",
    "sg:tags":[
        "key"
    ],
    "wof:name":"A 24 Hour Emergency Locksmith",
    "wof:placetype":"venue"
},
  "geometry": {"coordinates":[-74.32402500000001,40.717949],"type":"Point"}
}