{
  "type": "Feature",
  "properties": {
    "addr:full":"8 Mountainside Park Tr Montclair NJ 07043",
    "addr:housenumber":"8",
    "addr:postcode":"07043",
    "addr:street":"Mountainside Park Tr",
    "iso:country":"US",
    "sg:address":"8 Mountainside Park Tr",
    "sg:city":"Montclair",
    "sg:classifiers":[
        {
            "category":"Health Services",
            "subcategory":"Clinic",
            "type":"Services"
        },
        {
            "category":"Sports & Exercise",
            "subcategory":"Gym",
            "type":"Entertainment"
        },
        {
            "category":"Health Services",
            "subcategory":"Health Practitioner",
            "type":"Services"
        }
    ],
    "sg:phone":"+1 973 509 8879",
    "sg:postcode":"07043",
    "sg:province":"NJ",
    "sg:tags":[
        "trainer",
        "nutritionist",
        "mental",
        "counseling"
    ],
    "wof:name":"Youths Eating Smart Program",
    "wof:placetype":"venue"
},
  "geometry": {"coordinates":[-74.2062,40.8559],"type":"Point"}
}