{
  "type": "Feature",
  "properties": {
    "iso:country":"US",
    "sg:address":"298 Kinderkamack Rd",
    "sg:city":"Oradell",
    "sg:classifiers":[
        {
            "category":"Arts & Performance",
            "subcategory":"Theater",
            "type":"Entertainment"
        }
    ],
    "sg:phone":"+1 201 261 4200",
    "sg:postcode":"07649",
    "sg:province":"NJ",
    "sg:tags":[
        "theatrical"
    ],
    "wof:name":"Bergen County Players Inc",
    "wof:placetype":"venue"
},
  "geometry": {"coordinates":[-74.03218200000001,40.950535],"type":"Point"}
}