{
  "type": "Feature",
  "properties": {
    "addr:full":"527 Cinnaminson Ave Palmyra NJ 08065",
    "addr:housenumber":"527",
    "addr:postcode":"08065",
    "addr:street":"Cinnaminson Ave",
    "iso:country":"US",
    "sg:address":"527 Cinnaminson Ave",
    "sg:city":"Palmyra",
    "sg:classifiers":[
        {
            "category":"Organizations",
            "subcategory":"Community Association",
            "type":"Services"
        }
    ],
    "sg:phone":"+1   ",
    "sg:postcode":"08065",
    "sg:province":"NJ",
    "wof:name":"Single Parents Society",
    "wof:placetype":"venue"
},
  "geometry": {"coordinates":[-75.022132,40.004356],"type":"Point"}
}