{
  "type": "Feature",
  "properties": {
    "addr:full":"1561 US Hwy 9 Toms River NJ 08755",
    "addr:housenumber":"1561",
    "addr:postcode":"08755",
    "addr:street":"Us Hwy 9",
    "iso:country":"US",
    "sg:address":"1561 US Hwy 9",
    "sg:city":"Toms River",
    "sg:classifiers":[
        {
            "category":"Home & Garden",
            "subcategory":"Building Materials",
            "type":"Retail Goods"
        },
        {
            "category":"Home & Garden",
            "subcategory":"Furniture",
            "type":"Retail Goods"
        }
    ],
    "sg:phone":"+1 732 349 7626",
    "sg:postcode":"08755",
    "sg:province":"NJ",
    "sg:tags":[
        "top",
        "counter"
    ],
    "wof:name":"Counter Connection",
    "wof:placetype":"venue"
},
  "geometry": {"coordinates":[-74.21444099999999,40.005851],"type":"Point"}
}