{
  "type": "Feature",
  "properties": {
    "iso:country":"US",
    "sg:address":"200 S Orange Ave",
    "sg:city":"Newark",
    "sg:classifiers":[
        {
            "category":"Wholesale",
            "subcategory":"Apparel",
            "type":"Manufacturing & Wholesale Goods"
        }
    ],
    "sg:phone":"+1 973 623 8016",
    "sg:postcode":"07103",
    "sg:province":"NJ",
    "wof:name":"Babyland Family Svc",
    "wof:placetype":"venue"
},
  "geometry": {"coordinates":[-74.190713,40.738641],"type":"Point"}
}