{
  "type": "Feature",
  "properties": {
    "iso:country":"US",
    "sg:address":"2010 Kennedy Blvd",
    "sg:city":"Union City",
    "sg:classifiers":[
        {
            "category":"Retail",
            "subcategory":"Laundry & Dry Cleaning",
            "type":"Services"
        }
    ],
    "sg:phone":"+1 201 863 1410",
    "sg:postcode":"07087",
    "sg:province":"NJ",
    "wof:name":"Union City Speedwash",
    "wof:placetype":"venue"
},
  "geometry": {"coordinates":[-74.040599,40.76854],"type":"Point"}
}