{
  "type": "Feature",
  "properties": {
    "addr:full":"16 Elm St Morristown NJ 07960",
    "addr:housenumber":"16",
    "addr:postcode":"07960",
    "addr:street":"Elm St",
    "iso:country":"US",
    "sg:address":"16 Elm St",
    "sg:city":"Morristown",
    "sg:classifiers":[
        {
            "category":"Professional",
            "subcategory":"Business Services",
            "type":"Services"
        }
    ],
    "sg:phone":"+1 973 984 5262",
    "sg:postcode":"07960",
    "sg:province":"NJ",
    "sg:tags":[
        "appraiser"
    ],
    "wof:name":"Gallery",
    "wof:placetype":"venue"
},
  "geometry": {"coordinates":[-74.475616,40.793044],"type":"Point"}
}