{
  "type": "Feature",
  "properties": {
    "addr:full":"1 Berlin Rd Cherry Hill NJ 08034",
    "addr:housenumber":"1",
    "addr:postcode":"08034",
    "addr:street":"Berlin Rd",
    "iso:country":"US",
    "sg:address":"1 Berlin Rd",
    "sg:city":"Cherry Hill",
    "sg:classifiers":[
        {
            "category":"Food & Beverages",
            "subcategory":"Liquor & Beverages",
            "type":"Retail Goods"
        }
    ],
    "sg:phone":"+1 856 428 5200",
    "sg:postcode":"08034",
    "sg:province":"NJ",
    "sg:tags":[
        "beer",
        "spirit",
        "wine"
    ],
    "sg:website":"www.kresswine.com",
    "wof:name":"Kress Wine",
    "wof:placetype":"venue"
},
  "geometry": {"coordinates":[-75.02419999999999,39.895],"type":"Point"}
}