{
  "type": "Feature",
  "properties": {
    "iso:country":"US",
    "sg:address":"78 Grove St",
    "sg:city":"Somerville",
    "sg:classifiers":[
        {
            "category":"Professional",
            "subcategory":"Lawyer & Legal Services",
            "type":"Services"
        }
    ],
    "sg:phone":"+1 908 725 3322",
    "sg:postcode":"08876",
    "sg:province":"NJ",
    "sg:tags":[
        "attorney"
    ],
    "wof:name":"Stanley Powers & Matyola",
    "wof:placetype":"venue"
},
  "geometry": {"coordinates":[-74.609111,40.569751],"type":"Point"}
}