{
  "type": "Feature",
  "properties": {
    "addr:full":"400 Co Rd 530 Whiting NJ 08759",
    "addr:housenumber":"400",
    "addr:postcode":"08759",
    "addr:street":"Co Rd 530",
    "iso:country":"US",
    "sg:address":"400 Co Rd 530",
    "sg:city":"Whiting",
    "sg:classifiers":[
        {
            "category":"Health Services",
            "subcategory":"Health Practitioner",
            "type":"Services"
        }
    ],
    "sg:phone":"+1 732 849 0700",
    "sg:postcode":"08759",
    "sg:province":"NJ",
    "sg:tags":[
        "therapist",
        "physical"
    ],
    "wof:name":"All Care Physical Therapy Ctr",
    "wof:placetype":"venue"
},
  "geometry": {"coordinates":[-74.35707499999999,39.946555],"type":"Point"}
}