{
  "type": "Feature",
  "properties": {
    "addr:full":"307 N High St Millville NJ 08332",
    "addr:housenumber":"307",
    "addr:postcode":"08332",
    "addr:street":"N High St",
    "iso:country":"US",
    "sg:address":"307 N High St",
    "sg:city":"Millville",
    "sg:classifiers":[
        {
            "category":"Utilities",
            "subcategory":"Mobile Phone",
            "type":"Services"
        }
    ],
    "sg:phone":"+1 856 293 1414",
    "sg:postcode":"08332",
    "sg:province":"NJ",
    "sg:tags":[
        "telephone",
        "cellular"
    ],
    "wof:name":"Go Wireless",
    "wof:placetype":"venue"
},
  "geometry": {"coordinates":[-75.03851,39.399445],"type":"Point"}
}