{
  "type": "Feature",
  "properties": {
    "addr:full":"503 Market St Newark NJ 07105",
    "addr:housenumber":"503",
    "addr:postcode":"07105",
    "addr:street":"Market St",
    "iso:country":"US",
    "sg:address":"503 Market St",
    "sg:city":"Newark",
    "sg:classifiers":[
        {
            "category":"Manufacturing",
            "subcategory":"Signs",
            "type":"Manufacturing & Wholesale Goods"
        }
    ],
    "sg:phone":"+1 973 589 7553",
    "sg:postcode":"07105",
    "sg:province":"NJ",
    "sg:tags":[
        "specialty",
        "mfg"
    ],
    "wof:name":"Awning & Signs By Sign Studio",
    "wof:placetype":"venue"
},
  "geometry": {"coordinates":[-74.156212,40.732032],"type":"Point"}
}