{
  "type": "Feature",
  "properties": {
    "addr:full":"228 Garden Rd Elmer NJ 08318",
    "addr:housenumber":"228",
    "addr:postcode":"08318",
    "addr:street":"Garden Rd",
    "iso:country":"US",
    "sg:address":"228 Garden Rd",
    "sg:city":"Elmer",
    "sg:classifiers":[
        {
            "category":"Freight",
            "type":"Transportation"
        }
    ],
    "sg:phone":"+1 856 358 7555",
    "sg:postcode":"08318",
    "sg:province":"NJ",
    "sg:tags":[
        "dry",
        "bulk",
        "trucking"
    ],
    "wof:name":"Lee Transport Inc",
    "wof:placetype":"venue"
},
  "geometry": {"coordinates":[-75.14072899999999,39.538238],"type":"Point"}
}