{
  "type": "Feature",
  "properties": {
    "addr:full":"1624 Bedford St Rahway NJ 07065",
    "addr:housenumber":"1624",
    "addr:postcode":"07065",
    "addr:street":"Bedford St",
    "iso:country":"US",
    "sg:address":"1624 Bedford St",
    "sg:city":"Rahway",
    "sg:classifiers":[
        {
            "category":"Professional",
            "subcategory":"Business Services",
            "type":"Services"
        }
    ],
    "sg:phone":"+1 732 574 0570",
    "sg:postcode":"07065",
    "sg:province":"NJ",
    "sg:tags":[
        "appraiser"
    ],
    "wof:name":"C & C Appraisal Svc Inc",
    "wof:placetype":"venue"
},
  "geometry": {"coordinates":[-74.291518,40.618871],"type":"Point"}
}