{
  "type": "Feature",
  "properties": {
    "addr:full":"210 Harcourt Dr Trenton NJ 08610",
    "addr:housenumber":"210",
    "addr:postcode":"08610",
    "addr:street":"Harcourt Dr",
    "iso:country":"US",
    "sg:address":"210 Harcourt Dr",
    "sg:city":"Trenton",
    "sg:classifiers":[
        {
            "category":"Building & Trades",
            "subcategory":"Construction",
            "type":"Services"
        }
    ],
    "sg:phone":"+1 609 888 0110",
    "sg:postcode":"08610",
    "sg:province":"NJ",
    "sg:tags":[
        "general",
        "contractor"
    ],
    "wof:name":"Ryba General Construction",
    "wof:placetype":"venue"
},
  "geometry": {"coordinates":[-74.71562900000001,40.186868],"type":"Point"}
}