{
  "type": "Feature",
  "properties": {
    "addr:full":"6570 Collins Ave Pennsauken NJ 08109",
    "addr:housenumber":"6570",
    "addr:postcode":"08109",
    "addr:street":"Collins Ave",
    "iso:country":"US",
    "sg:address":"6570 Collins Ave",
    "sg:city":"Pennsauken",
    "sg:classifiers":[
        {
            "category":"Health Services",
            "subcategory":"Doctor",
            "type":"Services"
        }
    ],
    "sg:phone":"+1 856 662 6055",
    "sg:postcode":"08109",
    "sg:province":"NJ",
    "sg:tags":[
        "dentist"
    ],
    "wof:name":"Adams Robt L Jr DMD",
    "wof:placetype":"venue"
},
  "geometry": {"coordinates":[-75.04920199999999,39.959499],"type":"Point"}
}