{
  "type": "Feature",
  "properties": {
    "addr:full":"292 Janine Way Bridgewater NJ 08807",
    "addr:housenumber":"292",
    "addr:postcode":"08807",
    "addr:street":"Janine Way",
    "iso:country":"US",
    "sg:address":"292 Janine Way",
    "sg:city":"Bridgewater",
    "sg:classifiers":[
        {
            "category":"Professional",
            "subcategory":"Management & Consulting",
            "type":"Services"
        }
    ],
    "sg:phone":"+1   ",
    "sg:postcode":"08807",
    "sg:province":"NJ",
    "sg:tags":[
        "communications",
        "agency",
        "public",
        "advertising"
    ],
    "wof:name":"Communications Plus Four LLC",
    "wof:placetype":"venue"
},
  "geometry": {"coordinates":[-74.667042,40.593547],"type":"Point"}
}