{
  "type": "Feature",
  "properties": {
    "iso:country":"US",
    "sg:address":"500 E Landis Ave",
    "sg:city":"Vineland",
    "sg:classifiers":[
        {
            "category":"Government",
            "subcategory":"Office",
            "type":"Public Place"
        }
    ],
    "sg:phone":"+1   ",
    "sg:postcode":"08360",
    "sg:province":"NJ",
    "sg:tags":[
        "station",
        "recruiting"
    ],
    "wof:name":"Nrs Vineland",
    "wof:placetype":"venue"
},
  "geometry": {"coordinates":[-75.023449,39.486061],"type":"Point"}
}