{
  "type": "Feature",
  "properties": {
    "iso:country":"US",
    "sg:address":"1505 Palmyra Bridge Rd",
    "sg:city":"Pennsauken",
    "sg:classifiers":[
        {
            "category":"Food & Beverages",
            "subcategory":"Groceries & Convenience Stores",
            "type":"Retail Goods"
        }
    ],
    "sg:phone":"+1 856 663 2251",
    "sg:postcode":"08110",
    "sg:province":"NJ",
    "wof:name":"Wawa Food Market",
    "wof:placetype":"venue"
},
  "geometry": {"coordinates":[-75.02113300000001,39.98739],"type":"Point"}
}