{
  "type": "Feature",
  "properties": {
    "addr:full":"311 Beach Dr Cape May NJ 08204",
    "addr:housenumber":"311",
    "addr:postcode":"08204",
    "addr:street":"Beach Dr",
    "iso:country":"US",
    "sg:address":"311 Beach Dr",
    "sg:city":"Cape May",
    "sg:classifiers":[
        {
            "category":"Recreation",
            "type":"Entertainment"
        },
        {
            "category":"Shopping",
            "subcategory":"Bicycles & Sporting Goods",
            "type":"Retail Goods"
        }
    ],
    "sg:phone":"+1 609 898 0988",
    "sg:postcode":"08204",
    "sg:province":"NJ",
    "sg:tags":[
        "club",
        "beach",
        "cabana"
    ],
    "wof:name":"Southend Surf Shop",
    "wof:placetype":"venue"
},
  "geometry": {"coordinates":[-74.923036,38.93031],"type":"Point"}
}