{
  "type": "Feature",
  "properties": {
    "addr:full":"414 S Broad St Elizabeth NJ 07202",
    "addr:housenumber":"414",
    "addr:postcode":"07202",
    "addr:street":"S Broad St",
    "iso:country":"US",
    "sg:address":"414 S Broad St",
    "sg:city":"Elizabeth",
    "sg:classifiers":[
        {
            "category":"Professional",
            "subcategory":"Management & Consulting",
            "type":"Services"
        }
    ],
    "sg:phone":"+1   ",
    "sg:postcode":"07202",
    "sg:province":"NJ",
    "sg:tags":[
        "retail",
        "direct",
        "sales"
    ],
    "wof:name":"La Milla Milk",
    "wof:placetype":"venue"
},
  "geometry": {"coordinates":[-74.21581,40.653194],"type":"Point"}
}