{
  "type": "Feature",
  "properties": {
    "iso:country":"US",
    "sg:address":"47 S Park St",
    "sg:city":"Montclair",
    "sg:classifiers":[
        {
            "category":"Shopping",
            "subcategory":"Clothing, Apparel, & Fashions",
            "type":"Retail Goods"
        }
    ],
    "sg:phone":"+1 973 744 8070",
    "sg:postcode":"07042",
    "sg:province":"NJ",
    "sg:tags":[
        "lingerie"
    ],
    "sg:website":"www.joharionline.com",
    "wof:name":"Johari",
    "wof:placetype":"venue"
},
  "geometry": {"coordinates":[-74.217697,40.811401],"type":"Point"}
}