{
  "type": "Feature",
  "properties": {
    "addr:full":"10 E Buckingham Ave Mount Ephraim NJ 08059",
    "addr:housenumber":"10",
    "addr:postcode":"08059",
    "addr:street":"E Buckingham Ave",
    "iso:country":"US",
    "sg:address":"10 E Buckingham Ave",
    "sg:city":"Mount Ephraim",
    "sg:classifiers":[
        {
            "category":"Insurance",
            "subcategory":"Insurance Agent",
            "type":"Services"
        }
    ],
    "sg:phone":"+1   ",
    "sg:postcode":"08059",
    "sg:province":"NJ",
    "wof:name":"Insurance & Financial Services",
    "wof:placetype":"venue"
},
  "geometry": {"coordinates":[-75.082745,39.882449],"type":"Point"}
}