{
  "type": "Feature",
  "properties": {
    "iso:country":"US",
    "sg:address":"520 N 9th St",
    "sg:city":"Camden",
    "sg:classifiers":[
        {
            "category":"Government",
            "subcategory":"Office",
            "type":"Public Place"
        }
    ],
    "sg:phone":"+1 856 225 5369",
    "sg:postcode":"08102",
    "sg:province":"NJ",
    "wof:name":"Camden County Div-Insurance",
    "wof:placetype":"venue"
},
  "geometry": {"coordinates":[-75.11327199999999,39.949766],"type":"Point"}
}