{
  "type": "Feature",
  "properties": {
    "iso:country":"US",
    "sg:address":"74 W Main St",
    "sg:city":"Mendham",
    "sg:classifiers":[
        {
            "category":"Professional",
            "type":"Services"
        }
    ],
    "sg:phone":"+1 973 543 4008",
    "sg:postcode":"07945",
    "sg:province":"NJ",
    "sg:tags":[
        "establishment"
    ],
    "wof:name":"ADH Sales Support Inc",
    "wof:placetype":"venue"
},
  "geometry": {"coordinates":[-74.615222,40.773864],"type":"Point"}
}