{
  "type": "Feature",
  "properties": {
    "iso:country":"US",
    "sg:address":"1700 Pacific Ave",
    "sg:city":"Atlantic City",
    "sg:classifiers":[
        {
            "category":"Restaurant",
            "type":"Food & Drink"
        },
        {
            "category":"Bars & Pubs",
            "type":"Food & Drink"
        }
    ],
    "sg:phone":"+1 609 345 3071",
    "sg:postcode":"08401",
    "sg:province":"NJ",
    "sg:tags":[
        "lounge",
        "drinking",
        "eating",
        "cocktail"
    ],
    "wof:name":"Poseidon Restaurant Inc",
    "wof:placetype":"venue"
},
  "geometry": {"coordinates":[-74.43203099999999,39.35856],"type":"Point"}
}