{
  "type": "Feature",
  "properties": {
    "addr:full":"9 Nina Dr East Hanover NJ 07936",
    "addr:housenumber":"9",
    "addr:postcode":"07936",
    "addr:street":"Nina Dr",
    "iso:country":"US",
    "sg:address":"9 Nina Dr",
    "sg:city":"East Hanover",
    "sg:classifiers":[
        {
            "category":"Professional",
            "subcategory":"Computer Services",
            "type":"Services"
        }
    ],
    "sg:phone":"+1 973 560 9118",
    "sg:postcode":"07936",
    "sg:province":"NJ",
    "sg:tags":[
        "prepackaged",
        "software"
    ],
    "wof:name":"Gem Software Inc",
    "wof:placetype":"venue"
},
  "geometry": {"coordinates":[-74.391457,40.801089],"type":"Point"}
}