{
  "type": "Feature",
  "properties": {
    "iso:country":"US",
    "sg:address":"33 Adalist Ave",
    "sg:city":"Butler",
    "sg:classifiers":[
        {
            "category":"Professional",
            "subcategory":"Computer Services",
            "type":"Services"
        }
    ],
    "sg:phone":"+1 973 838 3888",
    "sg:postcode":"07405",
    "sg:province":"NJ",
    "sg:tags":[
        "internet"
    ],
    "sg:website":"www.thetopwebsite.com",
    "wof:name":"Lyrix Inc",
    "wof:placetype":"venue"
},
  "geometry": {"coordinates":[-74.349203,40.995878],"type":"Point"}
}