{
  "type": "Feature",
  "properties": {
    "addr:full":"1046 Riverton St North Brunswick NJ 08902",
    "addr:housenumber":"1046",
    "addr:postcode":"08902",
    "addr:street":"Riverton St",
    "iso:country":"US",
    "sg:address":"1046 Riverton St",
    "sg:city":"North Brunswick",
    "sg:classifiers":[
        {
            "category":"Professional",
            "subcategory":"Business Services",
            "type":"Services"
        }
    ],
    "sg:phone":"+1 732 828 0385",
    "sg:postcode":"08902",
    "sg:province":"NJ",
    "wof:name":"Simkos Fleet Service",
    "wof:placetype":"venue"
},
  "geometry": {"coordinates":[-74.469346,40.467332],"type":"Point"}
}