{
  "type": "Feature",
  "properties": {
    "iso:country":"US",
    "sg:address":"3108 Pacific Ave",
    "sg:city":"Atlantic City",
    "sg:classifiers":[
        {
            "category":"Restaurant",
            "type":"Food & Drink"
        }
    ],
    "sg:menulink":"http://www.allmenus.com/nj/atlantic-city/267869-girasole-ristorante/menu/",
    "sg:phone":"+1 609 345 5554",
    "sg:postcode":"08401",
    "sg:province":"NJ",
    "sg:tags":[
        "italian"
    ],
    "wof:name":"Girasole Ristorante",
    "wof:placetype":"venue"
},
  "geometry": {"coordinates":[-74.447999,39.352104],"type":"Point"}
}