{
  "type": "Feature",
  "properties": {
    "addr:full":"1039 Lyndale Ave Trenton NJ 08629",
    "addr:housenumber":"1039",
    "addr:postcode":"08629",
    "addr:street":"Lyndale Ave",
    "iso:country":"US",
    "sg:address":"1039 Lyndale Ave",
    "sg:city":"Trenton",
    "sg:classifiers":[
        {
            "category":"Professional",
            "type":"Services"
        }
    ],
    "sg:phone":"+1   ",
    "sg:postcode":"08629",
    "sg:province":"NJ",
    "wof:name":"Royal Prestige Marjurie LLC",
    "wof:placetype":"venue"
},
  "geometry": {"coordinates":[-74.734041,40.214974],"type":"Point"}
}