{
  "type": "Feature",
  "properties": {
    "addr:full":"240 Rockland Ave Westwood NJ 07675",
    "addr:housenumber":"240",
    "addr:postcode":"07675",
    "addr:street":"Rockland Ave",
    "iso:country":"US",
    "sg:address":"240 Rockland Ave",
    "sg:city":"Westwood",
    "sg:classifiers":[
        {
            "category":"Building & Trades",
            "subcategory":"Construction",
            "type":"Services"
        }
    ],
    "sg:phone":"+1 201 664 7604",
    "sg:postcode":"07675",
    "sg:province":"NJ",
    "sg:tags":[
        "both",
        "general",
        "contractor"
    ],
    "wof:name":"J V T Construction Inc",
    "wof:placetype":"venue"
},
  "geometry": {"coordinates":[-74.013099,40.997564],"type":"Point"}
}