{
  "type": "Feature",
  "properties": {
    "addr:full":"515 White Horse Pike Atco NJ 08004",
    "addr:housenumber":"515",
    "addr:postcode":"08004",
    "addr:street":"White Horse Pike",
    "iso:country":"US",
    "sg:address":"515 White Horse Pike",
    "sg:city":"Atco",
    "sg:classifiers":[
        {
            "category":"Building & Trades",
            "subcategory":"Construction",
            "type":"Services"
        }
    ],
    "sg:phone":"+1 856 719 9996",
    "sg:postcode":"08004",
    "sg:province":"NJ",
    "sg:tags":[
        "hanging",
        "painter",
        "contractor"
    ],
    "sg:website":"www.pclpainting.com",
    "wof:name":"PCL Painting Contractors Inc",
    "wof:placetype":"venue"
},
  "geometry": {"coordinates":[-74.88601199999999,39.761412],"type":"Point"}
}