{
  "type": "Feature",
  "properties": {
    "addr:full":"21 Trojan Ave Parsippany NJ 07054",
    "addr:housenumber":"21",
    "addr:postcode":"07054",
    "addr:street":"Trojan Ave",
    "iso:country":"US",
    "sg:address":"21 Trojan Ave",
    "sg:city":"Parsippany",
    "sg:classifiers":[
        {
            "category":"Professional",
            "subcategory":"Accounting & Tax Preparation",
            "type":"Services"
        }
    ],
    "sg:phone":"+1 973 335 6207",
    "sg:postcode":"07054",
    "sg:province":"NJ",
    "wof:name":"Grace R Salvatore",
    "wof:placetype":"venue"
},
  "geometry": {"coordinates":[-74.43566199999999,40.867989],"type":"Point"}
}