{
  "type": "Feature",
  "properties": {
    "addr:full":"238 14th St Jersey City NJ 07310",
    "addr:housenumber":"238",
    "addr:postcode":"07310",
    "addr:street":"14Th St",
    "iso:country":"US",
    "sg:address":"238 14th St",
    "sg:city":"Jersey City",
    "sg:classifiers":[
        {
            "category":"Retail",
            "subcategory":"Repair Shop",
            "type":"Services"
        }
    ],
    "sg:phone":"+1 201 334 3478",
    "sg:postcode":"07310",
    "sg:province":"NJ",
    "sg:tags":[
        "lock",
        "locksmith"
    ],
    "wof:name":"24 Hour Locksmith",
    "wof:placetype":"venue"
},
  "geometry": {"coordinates":[-74.04553900000001,40.732149],"type":"Point"}
}