{
  "type": "Feature",
  "properties": {
    "addr:full":"629 White Horse Pike Haddon Twp NJ 08107",
    "addr:housenumber":"629",
    "addr:postcode":"08107",
    "addr:street":"White Horse Pike",
    "iso:country":"US",
    "sg:address":"629 White Horse Pike",
    "sg:city":"Haddon Twp",
    "sg:classifiers":[
        {
            "category":"Retail",
            "subcategory":"Repair Shop",
            "type":"Services"
        }
    ],
    "sg:phone":"+1 856 854 1152",
    "sg:postcode":"08107",
    "sg:province":"NJ",
    "sg:tags":[
        "bicycle"
    ],
    "wof:name":"Esher's Bike Shop",
    "wof:placetype":"venue"
},
  "geometry": {"coordinates":[-75.077394,39.902865],"type":"Point"}
}