{
  "type": "Feature",
  "properties": {
    "iso:country":"US",
    "sg:address":"6505 Hudson Ave",
    "sg:city":"West New York",
    "sg:classifiers":[
        {
            "category":"Building & Trades",
            "subcategory":"Equipment Rental",
            "type":"Services"
        }
    ],
    "sg:phone":"+1 201 854 6447",
    "sg:postcode":"07093",
    "sg:province":"NJ",
    "wof:name":"U&L Amusement",
    "wof:placetype":"venue"
},
  "geometry": {"coordinates":[-74.0089,40.791782],"type":"Point"}
}