{
  "type": "Feature",
  "properties": {
    "addr:full":"11 Garret Dr Little Falls NJ 07424",
    "addr:housenumber":"11",
    "addr:postcode":"07424",
    "addr:street":"Garret Dr",
    "iso:country":"US",
    "sg:address":"11 Garret Dr",
    "sg:city":"Little Falls",
    "sg:classifiers":[
        {
            "category":"Professional",
            "type":"Services"
        }
    ],
    "sg:phone":"+1   ",
    "sg:postcode":"07424",
    "sg:province":"NJ",
    "wof:name":"United States Masters Swi",
    "wof:placetype":"venue"
},
  "geometry": {"coordinates":[-74.184037,40.892501],"type":"Point"}
}