{
  "type": "Feature",
  "properties": {
    "iso:country":"US",
    "sg:address":"352 Stokes Rd",
    "sg:city":"Medford",
    "sg:classifiers":[
        {
            "category":"Education",
            "subcategory":"Vocational School",
            "type":"Public Place"
        },
        {
            "category":"Professional",
            "subcategory":"Computer Services",
            "type":"Services"
        }
    ],
    "sg:phone":"+1 609 953 0044",
    "sg:postcode":"08055",
    "sg:province":"NJ",
    "sg:tags":[
        "information",
        "training",
        "management",
        "technology",
        "software"
    ],
    "sg:website":"www.canterburyconsultinggroup.com",
    "wof:name":"Canterbury Consulting Group",
    "wof:placetype":"venue"
},
  "geometry": {"coordinates":[-74.819081,39.881077],"type":"Point"}
}