{
  "type": "Feature",
  "properties": {
    "addr:full":"1191 Co Rd 547 Howell NJ 07731",
    "addr:housenumber":"1191",
    "addr:postcode":"07731",
    "addr:street":"Co Rd 547",
    "iso:country":"US",
    "sg:address":"1191 Co Rd 547",
    "sg:city":"Howell",
    "sg:classifiers":[
        {
            "category":"Professional",
            "subcategory":"Business Services",
            "type":"Services"
        },
        {
            "category":"Home & Garden",
            "subcategory":"Furniture",
            "type":"Retail Goods"
        }
    ],
    "sg:phone":"+1 732 901 9992",
    "sg:postcode":"07731",
    "sg:province":"NJ",
    "sg:tags":[
        "hotel",
        "auctioneer",
        "supply"
    ],
    "wof:name":"Furniture Concepts Inc",
    "wof:placetype":"venue"
},
  "geometry": {"coordinates":[-74.195419,40.115936],"type":"Point"}
}