{
  "type": "Feature",
  "properties": {
    "addr:full":"122 Lake Valley Rd Morristown NJ 07960",
    "addr:housenumber":"122",
    "addr:postcode":"07960",
    "addr:street":"Lake Valley Rd",
    "iso:country":"US",
    "sg:address":"122 Lake Valley Rd",
    "sg:city":"Morristown",
    "sg:classifiers":[
        {
            "category":"Real Estate",
            "subcategory":"Real Estate Services",
            "type":"Services"
        }
    ],
    "sg:phone":"+1   ",
    "sg:postcode":"07960",
    "sg:province":"NJ",
    "sg:tags":[
        "abstract",
        "title"
    ],
    "wof:name":"Abstract Automation Inc",
    "wof:placetype":"venue"
},
  "geometry": {"coordinates":[-74.49455399999999,40.817545],"type":"Point"}
}