{
  "type": "Feature",
  "properties": {
    "iso:country":"US",
    "sg:address":"77 Elbo Ln",
    "sg:city":"Mt Laurel",
    "sg:classifiers":[
        {
            "category":"Wholesale",
            "subcategory":"Office Equipment",
            "type":"Manufacturing & Wholesale Goods"
        },
        {
            "category":"Shopping",
            "type":"Retail Goods"
        }
    ],
    "sg:phone":"+1 856 727 8100",
    "sg:postcode":"08054",
    "sg:province":"NJ",
    "sg:tags":[
        "fax",
        "copier",
        "duplicating",
        "machine",
        "copying",
        "furniture"
    ],
    "sg:website":"www.stewartnj.com",
    "wof:name":"Stewart Industries Inc",
    "wof:placetype":"venue"
},
  "geometry": {"coordinates":[-74.93210500000001,39.942116],"type":"Point"}
}