{
  "type": "Feature",
  "properties": {
    "iso:country":"US",
    "sg:address":"133 Black Point Rd",
    "sg:city":"Rumson",
    "sg:classifiers":[
        {
            "category":"Professional",
            "subcategory":"Art Services",
            "type":"Services"
        },
        {
            "category":"Manufacturing",
            "subcategory":"Printing",
            "type":"Manufacturing & Wholesale Goods"
        }
    ],
    "sg:phone":"+1 732 741 6304",
    "sg:postcode":"07760",
    "sg:province":"NJ",
    "sg:tags":[
        "arts",
        "graphic",
        "designer"
    ],
    "wof:name":"Line By Line Designs",
    "wof:placetype":"venue"
},
  "geometry": {"coordinates":[-73.993082,40.373454],"type":"Point"}
}