{
  "type": "Feature",
  "properties": {
    "addr:full":"25 W Highland Ave Atlantic Hghlnds NJ 07716",
    "addr:housenumber":"25",
    "addr:postcode":"07716",
    "addr:street":"W Highland Ave",
    "iso:country":"US",
    "sg:address":"25 W Highland Ave",
    "sg:city":"Atlantic Hghlnds",
    "sg:classifiers":[
        {
            "category":"Building & Trades",
            "subcategory":"Electrical",
            "type":"Services"
        }
    ],
    "sg:phone":"+1 732 291 1713",
    "sg:postcode":"07716",
    "sg:province":"NJ",
    "sg:tags":[
        "electric",
        "contractor"
    ],
    "wof:name":"Sodon's Electrical Inc",
    "wof:placetype":"venue"
},
  "geometry": {"coordinates":[-74.04028099999999,40.412761],"type":"Point"}
}