{
  "type": "Feature",
  "properties": {
    "addr:full":"120 Brookside Ln Hillsborough NJ 08844",
    "addr:housenumber":"120",
    "addr:postcode":"08844",
    "addr:street":"Brookside Ln",
    "iso:country":"US",
    "sg:address":"120 Brookside Ln",
    "sg:city":"Hillsborough",
    "sg:classifiers":[
        {
            "category":"Professional",
            "type":"Services"
        }
    ],
    "sg:phone":"+1 908 874 8777",
    "sg:postcode":"08844",
    "sg:province":"NJ",
    "sg:tags":[
        "establishment"
    ],
    "wof:name":"786 Enterprises",
    "wof:placetype":"venue"
},
  "geometry": {"coordinates":[-74.637044,40.511846],"type":"Point"}
}