{
  "type": "Feature",
  "properties": {
    "iso:country":"US",
    "sg:address":"3141 US Hwy 9",
    "sg:city":"Old Bridge",
    "sg:classifiers":[
        {
            "category":"Food & Beverages",
            "subcategory":"Bakery",
            "type":"Retail Goods"
        }
    ],
    "sg:phone":"+1 732 679 5123",
    "sg:postcode":"08857",
    "sg:province":"NJ",
    "sg:tags":[
        "baker"
    ],
    "wof:name":"LA Dolce Bakery",
    "wof:placetype":"venue"
},
  "geometry": {"coordinates":[-74.308108,40.382844],"type":"Point"}
}