{
  "type": "Feature",
  "properties": {
    "addr:full":"83 Pebble Ln Blackwood NJ 08012",
    "addr:housenumber":"83",
    "addr:postcode":"08012",
    "addr:street":"Pebble Ln",
    "iso:country":"US",
    "sg:address":"83 Pebble Ln",
    "sg:city":"Blackwood",
    "sg:classifiers":[
        {
            "category":"Professional",
            "subcategory":"Engineering",
            "type":"Services"
        }
    ],
    "sg:phone":"+1   ",
    "sg:postcode":"08012",
    "sg:province":"NJ",
    "wof:name":"Gadfly Industries Facet Ent",
    "wof:placetype":"venue"
},
  "geometry": {"coordinates":[-75.051922,39.816487],"type":"Point"}
}