{
  "type": "Feature",
  "properties": {
    "iso:country":"US",
    "sg:address":"885 Bloomfield Ave",
    "sg:city":"West Caldwell",
    "sg:classifiers":[
        {
            "category":"Education",
            "subcategory":"Special Training",
            "type":"Public Place"
        }
    ],
    "sg:phone":"+1 973 882 5350",
    "sg:postcode":"07006",
    "sg:province":"NJ",
    "sg:tags":[
        "tutoring"
    ],
    "wof:name":"Score Educational Centers",
    "wof:placetype":"venue"
},
  "geometry": {"coordinates":[-74.29920199999999,40.851501],"type":"Point"}
}