{
  "type": "Feature",
  "properties": {
    "iso:country":"US",
    "sg:address":"275 Old New Brunswick Rd",
    "sg:city":"Piscataway",
    "sg:classifiers":[
        {
            "category":"Professional",
            "subcategory":"Employment Agencies",
            "type":"Services"
        }
    ],
    "sg:phone":"+1 732 981 4370",
    "sg:postcode":"08854",
    "sg:province":"NJ",
    "sg:tags":[
        "help",
        "supply"
    ],
    "wof:name":"Option One",
    "wof:placetype":"venue"
},
  "geometry": {"coordinates":[-74.47355,40.554302],"type":"Point"}
}