{
  "type": "Feature",
  "properties": {
    "iso:country":"US",
    "sg:address":"3 Birdie Ln",
    "sg:city":"Ringoes",
    "sg:classifiers":[
        {
            "category":"Professional",
            "subcategory":"Management & Consulting",
            "type":"Services"
        }
    ],
    "sg:phone":"+1   ",
    "sg:postcode":"08551",
    "sg:province":"NJ",
    "sg:tags":[
        "retail",
        "direct",
        "sales"
    ],
    "wof:name":"Lifescan Inc",
    "wof:placetype":"venue"
},
  "geometry": {"coordinates":[-74.87255999999999,40.46889],"type":"Point"}
}