{
  "type": "Feature",
  "properties": {
    "iso:country":"US",
    "sg:address":"17 Peak Pl",
    "sg:city":"Sewell",
    "sg:classifiers":[
        {
            "category":"Wholesale",
            "subcategory":"Furniture",
            "type":"Manufacturing & Wholesale Goods"
        }
    ],
    "sg:phone":"+1 856 227 3786",
    "sg:postcode":"08080",
    "sg:province":"NJ",
    "wof:name":"Longwood Forest Products",
    "wof:placetype":"venue"
},
  "geometry": {"coordinates":[-75.071721,39.769618],"type":"Point"}
}