{
  "type": "Feature",
  "properties": {
    "addr:full":"222 River Ave Lakewood NJ 08701",
    "addr:housenumber":"222",
    "addr:postcode":"08701",
    "addr:street":"River Ave",
    "iso:country":"US",
    "sg:address":"222 River Ave",
    "sg:city":"Lakewood",
    "sg:classifiers":[
        {
            "category":"Wholesale",
            "subcategory":"Stationery",
            "type":"Manufacturing & Wholesale Goods"
        },
        {
            "category":"Manufacturing",
            "subcategory":"Printing",
            "type":"Manufacturing & Wholesale Goods"
        }
    ],
    "sg:phone":"+1 732 363 5788",
    "sg:postcode":"08701",
    "sg:province":"NJ",
    "sg:tags":[
        "printer",
        "paper",
        "business",
        "form",
        "system"
    ],
    "sg:website":"www.abpprint.com",
    "wof:name":"American Business Paper Inc",
    "wof:placetype":"venue"
},
  "geometry": {"coordinates":[-74.21602,40.082526],"type":"Point"}
}