{
  "type": "Feature",
  "properties": {
    "addr:full":"11 Lancaster Ct Ramsey NJ 07446",
    "addr:housenumber":"11",
    "addr:postcode":"07446",
    "addr:street":"Lancaster Ct",
    "iso:country":"US",
    "sg:address":"11 Lancaster Ct",
    "sg:city":"Ramsey",
    "sg:classifiers":[
        {
            "category":"Building & Trades",
            "subcategory":"Construction",
            "type":"Services"
        },
        {
            "category":"Home & Garden",
            "subcategory":"Carpets & Floor Coverings",
            "type":"Retail Goods"
        }
    ],
    "sg:phone":"+1 201 818 8840",
    "sg:postcode":"07446",
    "sg:province":"NJ",
    "sg:tags":[
        "dealer",
        "laying",
        "rug",
        "contractor"
    ],
    "wof:name":"Flooring Solutions Inc",
    "wof:placetype":"venue"
},
  "geometry": {"coordinates":[-74.170365,41.050651],"type":"Point"}
}