{
  "type": "Feature",
  "properties": {
    "iso:country":"US",
    "sg:address":"1420 Scranton Ave",
    "sg:city":"Lakehurst",
    "sg:classifiers":[
        {
            "category":"Shopping",
            "subcategory":"Computers & Home Electronics",
            "type":"Retail Goods"
        }
    ],
    "sg:phone":"+1   ",
    "sg:postcode":"08759",
    "sg:province":"NJ",
    "sg:tags":[
        "related"
    ],
    "wof:name":"Computer Guy",
    "wof:placetype":"venue"
},
  "geometry": {"coordinates":[-74.383878,39.915525],"type":"Point"}
}