{
  "type": "Feature",
  "properties": {
    "addr:full":"601 Marlton Pike W Cherry Hill NJ 08002",
    "addr:housenumber":"601",
    "addr:postcode":"08002",
    "addr:street":"Marlton Pike W",
    "iso:country":"US",
    "sg:address":"601 Marlton Pike W",
    "sg:city":"Cherry Hill",
    "sg:classifiers":[
        {
            "category":"Retail",
            "subcategory":"Funeral Services",
            "type":"Services"
        }
    ],
    "sg:phone":"+1 856 429 8020",
    "sg:postcode":"08002",
    "sg:province":"NJ",
    "sg:tags":[
        "cemetery"
    ],
    "wof:name":"Digerolamo Wendy Shook Funeral Director",
    "wof:placetype":"venue"
},
  "geometry": {"coordinates":[-75.018097,39.915401],"type":"Point"}
}