{
  "type": "Feature",
  "properties": {
    "iso:country":"US",
    "sg:address":"289 Howland Ave",
    "sg:city":"River Edge",
    "sg:classifiers":[
        {
            "category":"Health Services",
            "subcategory":"Doctor",
            "type":"Services"
        }
    ],
    "sg:phone":"+1 201 281 6509",
    "sg:postcode":"07661",
    "sg:province":"NJ",
    "sg:tags":[
        "medical"
    ],
    "wof:name":"Anita Chait MD",
    "wof:placetype":"venue"
},
  "geometry": {"coordinates":[-74.045512,40.92122],"type":"Point"}
}