{
  "type": "Feature",
  "properties": {
    "addr:full":"211 N 5th St Camden NJ 08102",
    "addr:housenumber":"211",
    "addr:postcode":"08102",
    "addr:street":"N 5Th St",
    "iso:country":"US",
    "sg:address":"211 N 5th St",
    "sg:city":"Camden",
    "sg:classifiers":[
        {
            "category":"Professional",
            "subcategory":"Lawyer & Legal Services",
            "type":"Services"
        }
    ],
    "sg:phone":"+1 856 338 0888",
    "sg:postcode":"08102",
    "sg:province":"NJ",
    "sg:tags":[
        "attorney"
    ],
    "wof:name":"Palmer Biezup & Henderson",
    "wof:placetype":"venue"
},
  "geometry": {"coordinates":[-75.12076500000001,39.947001],"type":"Point"}
}