{
  "type": "Feature",
  "properties": {
    "iso:country":"US",
    "sg:address":"512 S Main St",
    "sg:city":"Forked River",
    "sg:classifiers":[
        {
            "category":"Professional",
            "subcategory":"Management & Consulting",
            "type":"Services"
        }
    ],
    "sg:phone":"+1   ",
    "sg:postcode":"08731",
    "sg:province":"NJ",
    "sg:tags":[
        "software",
        "solution",
        "provider"
    ],
    "sg:website":"www.comprotech.com",
    "wof:name":"Compro Technologies Inc",
    "wof:placetype":"venue"
},
  "geometry": {"coordinates":[-74.199106,39.830073],"type":"Point"}
}