{
  "type": "Feature",
  "properties": {
    "iso:country":"US",
    "sg:address":"5 Stockton Ave",
    "sg:city":"Jamesburg",
    "sg:classifiers":[
        {
            "category":"Professional",
            "subcategory":"Lawyer & Legal Services",
            "type":"Services"
        }
    ],
    "sg:phone":"+1 732 656 0336",
    "sg:postcode":"08831",
    "sg:province":"NJ",
    "sg:tags":[
        "attorney"
    ],
    "wof:name":"Otto J Kostbar PA",
    "wof:placetype":"venue"
},
  "geometry": {"coordinates":[-74.441789,40.354078],"type":"Point"}
}