{
  "type": "Feature",
  "properties": {
    "iso:country":"US",
    "sg:address":"681 Orangeburgh Rd",
    "sg:city":"Westwood",
    "sg:classifiers":[
        {
            "category":"Professional",
            "subcategory":"Business Services",
            "type":"Services"
        }
    ],
    "sg:phone":"+1   ",
    "sg:postcode":"07675",
    "sg:province":"NJ",
    "wof:name":"Edward Strohmeyer",
    "wof:placetype":"venue"
},
  "geometry": {"coordinates":[-74.004773,41.033118],"type":"Point"}
}