{
  "type": "Feature",
  "properties": {
    "iso:country":"US",
    "sg:address":"1008 Baywood Dr",
    "sg:city":"Williamstown",
    "sg:classifiers":[
        {
            "category":"Professional",
            "subcategory":"Computer Services",
            "type":"Services"
        }
    ],
    "sg:phone":"+1   ",
    "sg:postcode":"08094",
    "sg:province":"NJ",
    "wof:name":"Eastern Computers Inc",
    "wof:placetype":"venue"
},
  "geometry": {"coordinates":[-75.002787,39.703555],"type":"Point"}
}