{
  "type": "Feature",
  "properties": {
    "iso:country":"US",
    "sg:address":"160 W Broadway",
    "sg:city":"Paterson",
    "sg:classifiers":[
        {
            "category":"Restaurant",
            "type":"Food & Drink"
        }
    ],
    "sg:phone":"+1 973 720 1100",
    "sg:postcode":"07522",
    "sg:province":"NJ",
    "wof:name":"Captain Fish & Chips",
    "wof:placetype":"venue"
},
  "geometry": {"coordinates":[-74.177285,40.922278],"type":"Point"}
}