{
  "type": "Feature",
  "properties": {
    "iso:country":"US",
    "sg:address":"431 North Ave",
    "sg:city":"Dunellen",
    "sg:classifiers":[
        {
            "category":"Wholesale",
            "subcategory":"Electrical",
            "type":"Manufacturing & Wholesale Goods"
        }
    ],
    "sg:phone":"+1 908 272 9190",
    "sg:postcode":"08812",
    "sg:province":"NJ",
    "sg:tags":[
        "alarm",
        "burglar",
        "system"
    ],
    "wof:name":"Protection Plus",
    "wof:placetype":"venue"
},
  "geometry": {"coordinates":[-74.46689499999999,40.589408],"type":"Point"}
}