{
  "type": "Feature",
  "properties": {
    "addr:full":"107 Vose Ave South Orange NJ 07079",
    "addr:housenumber":"107",
    "addr:postcode":"07079",
    "addr:street":"Vose Ave",
    "iso:country":"US",
    "sg:address":"107 Vose Ave",
    "sg:city":"South Orange",
    "sg:classifiers":[
        {
            "category":"Real Estate",
            "subcategory":"Real Estate Operator",
            "type":"Services"
        }
    ],
    "sg:phone":"+1 973 763 4643",
    "sg:postcode":"07079",
    "sg:province":"NJ",
    "sg:tags":[
        "apartment"
    ],
    "wof:name":"Town House",
    "wof:placetype":"venue"
},
  "geometry": {"coordinates":[-74.25757299999999,40.748303],"type":"Point"}
}