{
  "type": "Feature",
  "properties": {
    "iso:country":"US",
    "sg:address":"214 Haworth Ave",
    "sg:city":"Haworth",
    "sg:classifiers":[
        {
            "category":"Shopping",
            "subcategory":"Pharmacy",
            "type":"Retail Goods"
        }
    ],
    "sg:phone":"+1   ",
    "sg:postcode":"07641",
    "sg:province":"NJ",
    "sg:tags":[
        "drugstore"
    ],
    "wof:name":"Morses Pharmacy",
    "wof:placetype":"venue"
},
  "geometry": {"coordinates":[-73.98433799999999,40.960425],"type":"Point"}
}