{
  "type": "Feature",
  "properties": {
    "addr:full":"353 Georges Rd Dayton NJ 08810",
    "addr:housenumber":"353",
    "addr:postcode":"08810",
    "addr:street":"Georges Rd",
    "iso:country":"US",
    "sg:address":"353 Georges Rd",
    "sg:city":"Dayton",
    "sg:classifiers":[
        {
            "category":"Professional",
            "subcategory":"Business Services",
            "type":"Services"
        }
    ],
    "sg:phone":"+1 732 274 9540",
    "sg:postcode":"08810",
    "sg:province":"NJ",
    "sg:tags":[
        "interior",
        "consultant",
        "design",
        "decorator"
    ],
    "sg:website":"www.gdsinc.net",
    "wof:name":"GDS",
    "wof:placetype":"venue"
},
  "geometry": {"coordinates":[-74.511482,40.374637],"type":"Point"}
}