{
  "type": "Feature",
  "properties": {
    "addr:full":"10 Maddock Dr Trenton NJ 08628",
    "addr:housenumber":"10",
    "addr:postcode":"08628",
    "addr:street":"Maddock Dr",
    "iso:country":"US",
    "sg:address":"10 Maddock Dr",
    "sg:city":"Trenton",
    "sg:classifiers":[
        {
            "category":"Health Services",
            "subcategory":"Doctor",
            "type":"Services"
        }
    ],
    "sg:phone":"+1 609 394 5251",
    "sg:postcode":"08628",
    "sg:province":"NJ",
    "sg:tags":[
        "dentist"
    ],
    "wof:name":"Thomas J Ungrady DDS",
    "wof:placetype":"venue"
},
  "geometry": {"coordinates":[-74.844168,40.265494],"type":"Point"}
}