{
  "type": "Feature",
  "properties": {
    "iso:country":"US",
    "sg:address":"20 Thomas Dr",
    "sg:city":"Englishtown",
    "sg:classifiers":[
        {
            "category":"Professional",
            "subcategory":"Management & Consulting",
            "type":"Services"
        }
    ],
    "sg:phone":"+1   ",
    "sg:postcode":"07726",
    "sg:province":"NJ",
    "wof:name":"Mpg Assoc",
    "wof:placetype":"venue"
},
  "geometry": {"coordinates":[-74.32881500000001,40.289205],"type":"Point"}
}