{
  "type": "Feature",
  "properties": {
    "addr:full":"39 E End Ave Avon By The Sea NJ 07717",
    "addr:housenumber":"39",
    "addr:postcode":"07717",
    "addr:street":"E End Ave",
    "iso:country":"US",
    "sg:address":"39 E End Ave",
    "sg:city":"Avon By The Sea",
    "sg:classifiers":[
        {
            "category":"Real Estate",
            "subcategory":"Real Estate Agent",
            "type":"Services"
        }
    ],
    "sg:phone":"+1   ",
    "sg:postcode":"07717",
    "sg:province":"NJ",
    "wof:name":"East End Enterprises LLC",
    "wof:placetype":"venue"
},
  "geometry": {"coordinates":[-74.01073,40.194456],"type":"Point"}
}