{
  "type": "Feature",
  "properties": {
    "addr:full":"4 Washingtons Advance Englishtown NJ 07726",
    "addr:housenumber":"4",
    "addr:postcode":"07726",
    "addr:street":"Washingtons Advance",
    "iso:country":"US",
    "sg:address":"4 Washingtons Advance",
    "sg:city":"Englishtown",
    "sg:classifiers":[
        {
            "category":"Professional",
            "subcategory":"Lawyer & Legal Services",
            "type":"Services"
        }
    ],
    "sg:phone":"+1 732 683 1959",
    "sg:postcode":"07726",
    "sg:province":"NJ",
    "wof:name":"Abbondante & Bava",
    "wof:placetype":"venue"
},
  "geometry": {"coordinates":[-74.30849499999999,40.290194],"type":"Point"}
}