{
  "type": "Feature",
  "properties": {
    "addr:full":"640 Pinewald Keswick Rd Whiting NJ 08759",
    "addr:housenumber":"640",
    "addr:postcode":"08759",
    "addr:street":"Pinewald Keswick Rd",
    "iso:country":"US",
    "sg:address":"640 Pinewald Keswick Rd",
    "sg:city":"Whiting",
    "sg:classifiers":[
        {
            "category":"Professional",
            "type":"Services"
        }
    ],
    "sg:phone":"+1 732 244 7485",
    "sg:postcode":"08759",
    "sg:province":"NJ",
    "sg:tags":[
        "establishment"
    ],
    "wof:name":"Berkeley Emergency Response",
    "wof:placetype":"venue"
},
  "geometry": {"coordinates":[-74.345203,39.947446],"type":"Point"}
}