{
  "type": "Feature",
  "properties": {
    "iso:country":"US",
    "sg:address":"5 Changebridge Rd",
    "sg:city":"Montville",
    "sg:classifiers":[
        {
            "category":"Professional",
            "type":"Services"
        }
    ],
    "sg:phone":"+1 973 226 2054",
    "sg:postcode":"07045",
    "sg:province":"NJ",
    "sg:tags":[
        "establishment"
    ],
    "wof:name":"Boonton Bldg Material Co Inc",
    "wof:placetype":"venue"
},
  "geometry": {"coordinates":[-74.362453,40.915553],"type":"Point"}
}