{
  "type": "Feature",
  "properties": {
    "iso:country":"US",
    "sg:address":"85 Godwin Ave",
    "sg:city":"Midland Park",
    "sg:classifiers":[
        {
            "category":"Personal",
            "type":"Services"
        },
        {
            "category":"Sports & Exercise",
            "subcategory":"Gym",
            "type":"Entertainment"
        }
    ],
    "sg:phone":"+1 201 689 7555",
    "sg:postcode":"07432",
    "sg:province":"NJ",
    "sg:tags":[
        "facility",
        "consultant",
        "program",
        "health",
        "fitness",
        "physical"
    ],
    "wof:name":"Club Womens Fitness Studio The",
    "wof:placetype":"venue"
},
  "geometry": {"coordinates":[-74.138171,40.984773],"type":"Point"}
}