{
  "type": "Feature",
  "properties": {
    "iso:country":"US",
    "sg:address":"3417 Bergenline Ave",
    "sg:city":"Union City",
    "sg:classifiers":[
        {
            "category":"Shopping",
            "type":"Retail Goods"
        }
    ],
    "sg:phone":"+1 201 861 5171",
    "sg:postcode":"07087",
    "sg:province":"NJ",
    "sg:tags":[
        "mobile",
        "phone",
        "telephone",
        "cellular"
    ],
    "wof:name":"West New York Electronics",
    "wof:placetype":"venue"
},
  "geometry": {"coordinates":[-74.028533,40.773091],"type":"Point"}
}