{
  "type": "Feature",
  "properties": {
    "iso:country":"US",
    "sg:address":"48 Baptist Church Rd",
    "sg:city":"Hampton",
    "sg:classifiers":[
        {
            "category":"Manufacturing",
            "subcategory":"Signs",
            "type":"Manufacturing & Wholesale Goods"
        }
    ],
    "sg:phone":"+1 908 713 6122",
    "sg:postcode":"08827",
    "sg:province":"NJ",
    "sg:tags":[
        "advertising"
    ],
    "wof:name":"Recognition Graphics",
    "wof:placetype":"venue"
},
  "geometry": {"coordinates":[-74.995058,40.630226],"type":"Point"}
}