{
  "type": "Feature",
  "properties": {
    "addr:full":"515 N Pearl St Bridgeton NJ 08302",
    "addr:housenumber":"515",
    "addr:postcode":"08302",
    "addr:street":"N Pearl St",
    "iso:country":"US",
    "sg:address":"515 N Pearl St",
    "sg:city":"Bridgeton",
    "sg:classifiers":[
        {
            "category":"Retail",
            "subcategory":"Self-service Laundry",
            "type":"Services"
        }
    ],
    "sg:phone":"+1   ",
    "sg:postcode":"08302",
    "sg:province":"NJ",
    "sg:tags":[
        "coin"
    ],
    "wof:name":"Menz-O-Matic Inc",
    "wof:placetype":"venue"
},
  "geometry": {"coordinates":[-75.223743,39.441683],"type":"Point"}
}