{
  "type": "Feature",
  "properties": {
    "addr:full":"189 Co Rd 526 Allentown NJ 08501",
    "addr:housenumber":"189;526",
    "addr:postcode":"08501",
    "addr:street":"Co Rd",
    "iso:country":"US",
    "sg:address":"189 Co Rd 526",
    "sg:city":"Allentown",
    "sg:classifiers":[
        {
            "category":"Manufacturing",
            "subcategory":"Glass & Minerals",
            "type":"Manufacturing & Wholesale Goods"
        }
    ],
    "sg:phone":"+1 609 259 8687",
    "sg:postcode":"08501",
    "sg:province":"NJ",
    "sg:tags":[
        "ready",
        "mixed",
        "mfg",
        "concrete"
    ],
    "wof:name":"Ralph Clayton & Sons",
    "wof:placetype":"venue"
},
  "geometry": {"coordinates":[-74.535124,40.17039],"type":"Point"}
}