{
  "type": "Feature",
  "properties": {
    "iso:country":"US",
    "sg:address":"340 Eastbrook Rd",
    "sg:city":"Ridgewood",
    "sg:classifiers":[
        {
            "category":"Professional",
            "subcategory":"Advertising",
            "type":"Services"
        }
    ],
    "sg:phone":"+1 201 612 8272",
    "sg:postcode":"07450",
    "sg:province":"NJ",
    "sg:tags":[
        "distributing",
        "sample",
        "service-circular"
    ],
    "wof:name":"Imprints",
    "wof:placetype":"venue"
},
  "geometry": {"coordinates":[-74.085279,40.985081],"type":"Point"}
}