{
  "type": "Feature",
  "properties": {
    "addr:full":"17 Monroe St Passaic NJ 07055",
    "addr:housenumber":"17",
    "addr:postcode":"07055",
    "addr:street":"Monroe St",
    "iso:country":"US",
    "sg:address":"17 Monroe St",
    "sg:city":"Passaic",
    "sg:classifiers":[
        {
            "category":"Real Estate",
            "subcategory":"Real Estate Agent",
            "type":"Services"
        }
    ],
    "sg:phone":"+1   ",
    "sg:postcode":"07055",
    "sg:province":"NJ",
    "wof:name":"Riverview Realty Assoc",
    "wof:placetype":"venue"
},
  "geometry": {"coordinates":[-74.116102,40.868319],"type":"Point"}
}