{
  "type": "Feature",
  "properties": {
    "addr:full":"7 Orange Pl West Orange NJ 07052",
    "addr:housenumber":"7",
    "addr:postcode":"07052",
    "addr:street":"Orange Pl",
    "iso:country":"US",
    "sg:address":"7 Orange Pl",
    "sg:city":"West Orange",
    "sg:classifiers":[
        {
            "category":"Food & Beverages",
            "subcategory":"Liquor & Beverages",
            "type":"Retail Goods"
        }
    ],
    "sg:phone":"+1   ",
    "sg:postcode":"07052",
    "sg:province":"NJ",
    "sg:tags":[
        "alcoholic"
    ],
    "wof:name":"Ables Liquor Inc",
    "wof:placetype":"venue"
},
  "geometry": {"coordinates":[-74.232258,40.792554],"type":"Point"}
}