{
  "type": "Feature",
  "properties": {
    "iso:country":"US",
    "sg:address":"29 Bloomfield Ave",
    "sg:city":"Newark",
    "sg:classifiers":[
        {
            "category":"Retail",
            "subcategory":"Auto Repair",
            "type":"Services"
        }
    ],
    "sg:phone":"+1 973 268 2799",
    "sg:postcode":"07104",
    "sg:province":"NJ",
    "sg:tags":[
        "general"
    ],
    "wof:name":"Hernandez Auto Repair",
    "wof:placetype":"venue"
},
  "geometry": {"coordinates":[-74.17226700000001,40.755223],"type":"Point"}
}