{
  "type": "Feature",
  "properties": {
    "iso:country":"US",
    "sg:address":"255 Jackson Pines Rd",
    "sg:city":"Jackson",
    "sg:classifiers":[
        {
            "category":"Retail",
            "subcategory":"Veterinary Services",
            "type":"Services"
        }
    ],
    "sg:phone":"+1 732 364 5557",
    "sg:postcode":"08527",
    "sg:province":"NJ",
    "sg:tags":[
        "veterinarian"
    ],
    "wof:name":"House Call Veterinary Services",
    "wof:placetype":"venue"
},
  "geometry": {"coordinates":[-74.265336,40.097549],"type":"Point"}
}