{
  "type": "Feature",
  "properties": {
    "iso:country":"US",
    "sg:address":"35 High St",
    "sg:city":"Cranford",
    "sg:classifiers":[
        {
            "category":"Building & Trades",
            "subcategory":"Construction",
            "type":"Services"
        }
    ],
    "sg:phone":"+1 908 272 7080",
    "sg:postcode":"07016",
    "sg:province":"NJ",
    "sg:tags":[
        "contractor"
    ],
    "wof:name":"Ferro Buildrs Corp",
    "wof:placetype":"venue"
},
  "geometry": {"coordinates":[-74.30259700000001,40.653883],"type":"Point"}
}