{
  "type": "Feature",
  "properties": {
    "iso:country":"US",
    "sg:address":"8 Buckingham Dr",
    "sg:city":"Ocean",
    "sg:classifiers":[
        {
            "category":"Health Services",
            "subcategory":"Chiropractor",
            "type":"Services"
        }
    ],
    "sg:phone":"+1 732 918 1236",
    "sg:postcode":"07712",
    "sg:province":"NJ",
    "wof:name":"Phillip C Agrios DC",
    "wof:placetype":"venue"
},
  "geometry": {"coordinates":[-74.067758,40.244824],"type":"Point"}
}