{
  "type": "Feature",
  "properties": {
    "addr:full":"46 4th Ave Long Branch NJ 07740",
    "addr:housenumber":"46",
    "addr:postcode":"07740",
    "addr:street":"4Th Ave",
    "iso:country":"US",
    "sg:address":"46 4th Ave",
    "sg:city":"Long Branch",
    "sg:classifiers":[
        {
            "category":"Shopping",
            "subcategory":"Department Store",
            "type":"Retail Goods"
        }
    ],
    "sg:phone":"+1 732 571 3100",
    "sg:postcode":"07740",
    "sg:province":"NJ",
    "sg:tags":[
        "club",
        "wholesale"
    ],
    "wof:name":"Royal Merchanising",
    "wof:placetype":"venue"
},
  "geometry": {"coordinates":[-73.98921,40.302248],"type":"Point"}
}