{
  "type": "Feature",
  "properties": {
    "addr:full":"422 W Pestalozzi Ave Egg Harbor City NJ 08215",
    "addr:housenumber":"422",
    "addr:postcode":"08215",
    "addr:street":"W Pestalozzi Ave",
    "iso:country":"US",
    "sg:address":"422 W Pestalozzi Ave",
    "sg:city":"Egg Harbor City",
    "sg:classifiers":[
        {
            "category":"Professional",
            "type":"Services"
        }
    ],
    "sg:phone":"+1   ",
    "sg:postcode":"08215",
    "sg:province":"NJ",
    "wof:name":"Joseph Sahl",
    "wof:placetype":"venue"
},
  "geometry": {"coordinates":[-74.542554,39.522532],"type":"Point"}
}