{
  "type": "Feature",
  "properties": {
    "addr:full":"4264 US Hwy 9 Freehold NJ 07728",
    "addr:housenumber":"4264",
    "addr:postcode":"07728",
    "addr:street":"Us Hwy 9",
    "iso:country":"US",
    "sg:address":"4264 US Hwy 9",
    "sg:city":"Freehold",
    "sg:classifiers":[
        {
            "category":"Autos & Motor Vehicles",
            "subcategory":"Automobile Sales",
            "type":"Retail Goods"
        }
    ],
    "sg:phone":"+1 732 780 0666",
    "sg:postcode":"07728",
    "sg:province":"NJ",
    "sg:tags":[
        "car",
        "dealer"
    ],
    "wof:name":"Richard's Mazda Isuzu Suzuki",
    "wof:placetype":"venue"
},
  "geometry": {"coordinates":[-74.294247,40.274885],"type":"Point"}
}