{
  "type": "Feature",
  "properties": {
    "iso:country":"US",
    "sg:address":"119 S Main St",
    "sg:city":"Milltown",
    "sg:classifiers":[
        {
            "category":"Retail",
            "subcategory":"Repair Shop",
            "type":"Services"
        }
    ],
    "sg:phone":"+1   ",
    "sg:postcode":"08850",
    "sg:province":"NJ",
    "wof:name":"Schwendeman Taxidermy Studio",
    "wof:placetype":"venue"
},
  "geometry": {"coordinates":[-74.433965,40.447802],"type":"Point"}
}