{
  "type": "Feature",
  "properties": {
    "iso:country":"US",
    "sg:address":"812 Brass Castle Rd",
    "sg:city":"Belvidere",
    "sg:classifiers":[
        {
            "category":"Manufacturing",
            "subcategory":"Furniture",
            "type":"Manufacturing & Wholesale Goods"
        }
    ],
    "sg:phone":"+1 908 475 8872",
    "sg:postcode":"07823",
    "sg:province":"NJ",
    "sg:tags":[
        "woodworking",
        "commercial",
        "mfg"
    ],
    "wof:name":"Classic Concepts Ltd Inc",
    "wof:placetype":"venue"
},
  "geometry": {"coordinates":[-75.041335,40.811915],"type":"Point"}
}