{
  "type": "Feature",
  "properties": {
    "iso:country":"US",
    "sg:address":"380 W Pleasantview Ave",
    "sg:city":"Hackensack",
    "sg:classifiers":[
        {
            "category":"Cinema",
            "subcategory":"Movie Rental",
            "type":"Entertainment"
        }
    ],
    "sg:phone":"+1 201 498 9130",
    "sg:postcode":"07601",
    "sg:province":"NJ",
    "sg:tags":[
        "game",
        "video"
    ],
    "sg:website":"www.gamestop.com",
    "wof:name":"Game Stop",
    "wof:placetype":"venue"
},
  "geometry": {"coordinates":[-74.066902,40.875999],"type":"Point"}
}