{
  "type": "Feature",
  "properties": {
    "addr:full":"70 E Fleming Pike Hammonton NJ 08037",
    "addr:housenumber":"70",
    "addr:postcode":"08037",
    "addr:street":"E Fleming Pike",
    "iso:country":"US",
    "sg:address":"70 E Fleming Pike",
    "sg:city":"Hammonton",
    "sg:classifiers":[
        {
            "category":"Arts & Performance",
            "subcategory":"Music",
            "type":"Entertainment"
        }
    ],
    "sg:phone":"+1 609 561 8891",
    "sg:postcode":"08037",
    "sg:province":"NJ",
    "sg:tags":[
        "dj"
    ],
    "wof:name":"High Rollers Casino & Dj Entertainment",
    "wof:placetype":"venue"
},
  "geometry": {"coordinates":[-74.869979,39.662425],"type":"Point"}
}