{
  "type": "Feature",
  "properties": {
    "addr:full":"2106 W Landis Ave Vineland NJ 08360",
    "addr:housenumber":"2106",
    "addr:postcode":"08360",
    "addr:street":"W Landis Ave",
    "iso:country":"US",
    "sg:address":"2106 W Landis Ave",
    "sg:city":"Vineland",
    "sg:classifiers":[
        {
            "category":"Organizations",
            "subcategory":"Religious Organization",
            "type":"Services"
        }
    ],
    "sg:phone":"+1 856 507 8888",
    "sg:postcode":"08360",
    "sg:province":"NJ",
    "sg:tags":[
        "church"
    ],
    "wof:name":"Shiloh Baptist Church",
    "wof:placetype":"venue"
},
  "geometry": {"coordinates":[-75.06527699999999,39.488059],"type":"Point"}
}