{
  "type": "Feature",
  "properties": {
    "addr:full":"3221 Bergenline Ave Ste B Union City NJ 07087",
    "addr:housenumber":"3221",
    "addr:postcode":"07087",
    "addr:street":"Bergenline Ave Ste B",
    "iso:country":"US",
    "sg:address":"3221 Bergenline Ave Ste B",
    "sg:city":"Union City",
    "sg:classifiers":[
        {
            "category":"Home & Garden",
            "subcategory":"Furniture",
            "type":"Retail Goods"
        }
    ],
    "sg:phone":"+1 201 442 0842",
    "sg:postcode":"07087",
    "sg:province":"NJ",
    "sg:tags":[
        "store"
    ],
    "wof:name":"Royal Prestige",
    "wof:placetype":"venue"
},
  "geometry": {"coordinates":[-74.028998,40.772732],"type":"Point"}
}