{
  "type": "Feature",
  "properties": {
    "addr:full":"23 S Finley Ave Basking Ridge NJ 07920",
    "addr:housenumber":"23",
    "addr:postcode":"07920",
    "addr:street":"S Finley Ave",
    "iso:country":"US",
    "sg:address":"23 S Finley Ave",
    "sg:city":"Basking Ridge",
    "sg:classifiers":[
        {
            "category":"Retail",
            "subcategory":"Animal Services",
            "type":"Services"
        }
    ],
    "sg:phone":"+1 908 221 9588",
    "sg:postcode":"07920",
    "sg:province":"NJ",
    "sg:tags":[
        "grooming"
    ],
    "wof:name":"Pawsibilities Inc",
    "wof:placetype":"venue"
},
  "geometry": {"coordinates":[-74.54907,40.70577],"type":"Point"}
}