{
  "type": "Feature",
  "properties": {
    "iso:country":"US",
    "sg:address":"601 Haddon Ave",
    "sg:city":"Collingswood",
    "sg:classifiers":[
        {
            "category":"Building & Trades",
            "subcategory":"Construction",
            "type":"Services"
        }
    ],
    "sg:phone":"+1 856 854 2858",
    "sg:postcode":"08108",
    "sg:province":"NJ",
    "sg:tags":[
        "contractor"
    ],
    "wof:name":"Orlind Construction Inc",
    "wof:placetype":"venue"
},
  "geometry": {"coordinates":[-75.070728,39.916827],"type":"Point"}
}