{
  "type": "Feature",
  "properties": {
    "addr:full":"209 Ridgedale Ave Florham Park NJ 07932",
    "addr:housenumber":"209",
    "addr:postcode":"07932",
    "addr:street":"Ridgedale Ave",
    "iso:country":"US",
    "sg:address":"209 Ridgedale Ave",
    "sg:city":"Florham Park",
    "sg:classifiers":[
        {
            "category":"Banks & Credit Unions",
            "subcategory":"Bank",
            "type":"Services"
        }
    ],
    "sg:phone":"+1 973 301 1940",
    "sg:postcode":"07932",
    "sg:province":"NJ",
    "wof:name":"Boiling Springs Savings Bank",
    "wof:placetype":"venue"
},
  "geometry": {"coordinates":[-74.38886599999999,40.789811],"type":"Point"}
}