{
  "type": "Feature",
  "properties": {
    "addr:full":"280 Ramapo Valley Rd Mahwah NJ 07430",
    "addr:housenumber":"280",
    "addr:postcode":"07430",
    "addr:street":"Ramapo Valley Rd",
    "iso:country":"US",
    "sg:address":"280 Ramapo Valley Rd",
    "sg:city":"Mahwah",
    "sg:classifiers":[
        {
            "category":"Organizations",
            "subcategory":"Religious Organization",
            "type":"Services"
        }
    ],
    "sg:phone":"+1   ",
    "sg:postcode":"07430",
    "sg:province":"NJ",
    "sg:tags":[
        "temple"
    ],
    "sg:website":"www.bethhaverim.org",
    "wof:name":"Temple Beth Haverim",
    "wof:placetype":"venue"
},
  "geometry": {"coordinates":[-74.16571999999999,41.095884],"type":"Point"}
}