{
  "type": "Feature",
  "properties": {
    "iso:country":"US",
    "sg:address":"113 Danbury Dr",
    "sg:city":"Tuckerton",
    "sg:classifiers":[
        {
            "category":"Retail",
            "subcategory":"Car Wash",
            "type":"Services"
        }
    ],
    "sg:phone":"+1 609 660 0700",
    "sg:postcode":"08087",
    "sg:province":"NJ",
    "sg:tags":[
        "carwash"
    ],
    "wof:name":"Hydro Wash",
    "wof:placetype":"venue"
},
  "geometry": {"coordinates":[-74.377038,39.58416],"type":"Point"}
}