{
  "type": "Feature",
  "properties": {
    "addr:full":"723 Washington St Apt 7 Hoboken NJ 07030",
    "addr:housenumber":"723;7",
    "addr:postcode":"07030",
    "addr:street":"Washington St Apt",
    "iso:country":"US",
    "sg:address":"723 Washington St Apt 7",
    "sg:city":"Hoboken",
    "sg:classifiers":[
        {
            "category":"Sports & Exercise",
            "subcategory":"Golf",
            "type":"Entertainment"
        }
    ],
    "sg:phone":"+1 201 653 2688",
    "sg:postcode":"07030",
    "sg:province":"NJ",
    "sg:tags":[
        "course"
    ],
    "wof:name":"Of Course Foods",
    "wof:placetype":"venue"
},
  "geometry": {"coordinates":[-74.028592,40.745027],"type":"Point"}
}