{
  "type": "Feature",
  "properties": {
    "iso:country":"US",
    "sg:address":"242 Petticoat Bridge Rd",
    "sg:city":"Columbus",
    "sg:classifiers":[
        {
            "category":"Building & Trades",
            "subcategory":"Electrical",
            "type":"Services"
        }
    ],
    "sg:phone":"+1 609 298 4714",
    "sg:postcode":"08022",
    "sg:province":"NJ",
    "sg:tags":[
        "electric",
        "contractor"
    ],
    "wof:name":"Powers Electric Co",
    "wof:placetype":"venue"
},
  "geometry": {"coordinates":[-74.73806399999999,40.064916],"type":"Point"}
}