{
  "type": "Feature",
  "properties": {
    "iso:country":"US",
    "sg:address":"59 Village Park Rd",
    "sg:city":"Cedar Grove",
    "sg:classifiers":[
        {
            "category":"Banks & Credit Unions",
            "subcategory":"Financial Services",
            "type":"Services"
        }
    ],
    "sg:phone":"+1   ",
    "sg:postcode":"07009",
    "sg:province":"NJ",
    "sg:tags":[
        "investment",
        "real estate"
    ],
    "wof:name":"Powmac Associates LP",
    "wof:placetype":"venue"
},
  "geometry": {"coordinates":[-74.22648700000001,40.866452],"type":"Point"}
}