{
  "type": "Feature",
  "properties": {
    "addr:full":"105 Evesboro Medford Rd Marlton NJ 08053",
    "addr:housenumber":"105",
    "addr:postcode":"08053",
    "addr:street":"Evesboro Medford Rd",
    "iso:country":"US",
    "sg:address":"105 Evesboro Medford Rd",
    "sg:city":"Marlton",
    "sg:classifiers":[
        {
            "category":"Professional",
            "subcategory":"Management & Consulting",
            "type":"Services"
        }
    ],
    "sg:phone":"+1 856 983 7590",
    "sg:postcode":"08053",
    "sg:province":"NJ",
    "sg:tags":[
        "consultant",
        "security",
        "system"
    ],
    "wof:name":"Innovative Security Solutions",
    "wof:placetype":"venue"
},
  "geometry": {"coordinates":[-74.921447,39.913132],"type":"Point"}
}