{
  "type": "Feature",
  "properties": {
    "iso:country":"US",
    "sg:address":"116 S North Carolina Ave",
    "sg:city":"Atlantic City",
    "sg:classifiers":[
        {
            "category":"Shopping",
            "subcategory":"Jewelry",
            "type":"Retail Goods"
        }
    ],
    "sg:phone":"+1   ",
    "sg:postcode":"08401",
    "sg:province":"NJ",
    "wof:name":"Golden Gate",
    "wof:placetype":"venue"
},
  "geometry": {"coordinates":[-74.423772,39.360483],"type":"Point"}
}