{
  "type": "Feature",
  "properties": {
    "addr:full":"661 Ridgewood Ave Montclair NJ 07043",
    "addr:housenumber":"661",
    "addr:postcode":"07043",
    "addr:street":"Ridgewood Ave",
    "iso:country":"US",
    "sg:address":"661 Ridgewood Ave",
    "sg:city":"Montclair",
    "sg:classifiers":[
        {
            "category":"Professional",
            "type":"Services"
        }
    ],
    "sg:phone":"+1   ",
    "sg:postcode":"07043",
    "sg:province":"NJ",
    "wof:name":"Smg Artists",
    "wof:placetype":"venue"
},
  "geometry": {"coordinates":[-74.193951,40.829337],"type":"Point"}
}