{
  "type": "Feature",
  "properties": {
    "addr:full":"80 Main St Woodbridge NJ 07095",
    "addr:housenumber":"80",
    "addr:postcode":"07095",
    "addr:street":"Main St",
    "iso:country":"US",
    "sg:address":"80 Main St",
    "sg:city":"Woodbridge",
    "sg:classifiers":[
        {
            "category":"Sports & Exercise",
            "subcategory":"Gym",
            "type":"Entertainment"
        }
    ],
    "sg:phone":"+1 732 582 6405",
    "sg:postcode":"07095",
    "sg:province":"NJ",
    "wof:name":"Dolphin Weight Loss",
    "wof:placetype":"venue"
},
  "geometry": {"coordinates":[-74.279792,40.554333],"type":"Point"}
}