{
  "type": "Feature",
  "properties": {
    "addr:full":"109 W Sumner Ave Beach Haven NJ 08008",
    "addr:housenumber":"109",
    "addr:postcode":"08008",
    "addr:street":"W Sumner Ave",
    "iso:country":"US",
    "sg:address":"109 W Sumner Ave",
    "sg:city":"Beach Haven",
    "sg:classifiers":[
        {
            "category":"Health Services",
            "subcategory":"Doctor",
            "type":"Services"
        }
    ],
    "sg:phone":"+1 609 494 6207",
    "sg:postcode":"08008",
    "sg:province":"NJ",
    "sg:tags":[
        "medical"
    ],
    "wof:name":"Coastal Neurology P C",
    "wof:placetype":"venue"
},
  "geometry": {"coordinates":[-74.19629399999999,39.626067],"type":"Point"}
}