{
  "type": "Feature",
  "properties": {
    "iso:country":"US",
    "sg:address":"26 W Park Pl",
    "sg:city":"Morristown",
    "sg:classifiers":[
        {
            "category":"Real Estate",
            "subcategory":"Developer",
            "type":"Services"
        }
    ],
    "sg:phone":"+1 973 984 5999",
    "sg:postcode":"07960",
    "sg:province":"NJ",
    "wof:name":"Lyons Mall Inc",
    "wof:placetype":"venue"
},
  "geometry": {"coordinates":[-74.481556,40.796644],"type":"Point"}
}