{
  "type": "Feature",
  "properties": {
    "addr:full":"346 W Burlington St Bordentown NJ 08505",
    "addr:housenumber":"346",
    "addr:postcode":"08505",
    "addr:street":"W Burlington St",
    "iso:country":"US",
    "sg:address":"346 W Burlington St",
    "sg:city":"Bordentown",
    "sg:classifiers":[
        {
            "category":"Organizations",
            "subcategory":"Religious Organization",
            "type":"Services"
        }
    ],
    "sg:phone":"+1   ",
    "sg:postcode":"08505",
    "sg:province":"NJ",
    "wof:name":"Union Baptist Church",
    "wof:placetype":"venue"
},
  "geometry": {"coordinates":[-74.714933,40.142629],"type":"Point"}
}