{
  "type": "Feature",
  "properties": {
    "addr:full":"28 Avenel St Avenel NJ 07001",
    "addr:housenumber":"28",
    "addr:postcode":"07001",
    "addr:street":"Avenel St",
    "iso:country":"US",
    "sg:address":"28 Avenel St",
    "sg:city":"Avenel",
    "sg:classifiers":[
        {
            "category":"Wholesale",
            "subcategory":"Electrical",
            "type":"Manufacturing & Wholesale Goods"
        }
    ],
    "sg:phone":"+1 732 636 2716",
    "sg:postcode":"07001",
    "sg:province":"NJ",
    "sg:tags":[
        "electronic"
    ],
    "wof:name":"Tradition Video Productions",
    "wof:placetype":"venue"
},
  "geometry": {"coordinates":[-74.27090800000001,40.575937],"type":"Point"}
}