{
  "type": "Feature",
  "properties": {
    "addr:full":"249 Madison Ave Perth Amboy NJ 08861",
    "addr:housenumber":"249",
    "addr:postcode":"08861",
    "addr:street":"Madison Ave",
    "iso:country":"US",
    "sg:address":"249 Madison Ave",
    "sg:city":"Perth Amboy",
    "sg:classifiers":[
        {
            "category":"Food & Beverages",
            "subcategory":"Meat & Fish",
            "type":"Retail Goods"
        }
    ],
    "sg:phone":"+1 732 826 8926",
    "sg:postcode":"08861",
    "sg:province":"NJ",
    "sg:tags":[
        "shop"
    ],
    "wof:name":"Quisqueya Meat Market & Grocery",
    "wof:placetype":"venue"
},
  "geometry": {"coordinates":[-74.27089700000001,40.5079],"type":"Point"}
}