{
  "type": "Feature",
  "properties": {
    "addr:full":"77 Main St Little Falls NJ 07424",
    "addr:housenumber":"77",
    "addr:postcode":"07424",
    "addr:street":"Main St",
    "iso:country":"US",
    "sg:address":"77 Main St",
    "sg:city":"Little Falls",
    "sg:classifiers":[
        {
            "category":"Home & Garden",
            "subcategory":"Household Appliances",
            "type":"Retail Goods"
        }
    ],
    "sg:phone":"+1 973 256 8223",
    "sg:postcode":"07424",
    "sg:province":"NJ",
    "sg:tags":[
        "cleaning",
        "carpet"
    ],
    "wof:name":"Little Falls Vacuum Service",
    "wof:placetype":"venue"
},
  "geometry": {"coordinates":[-74.227501,40.881199],"type":"Point"}
}