{
  "type": "Feature",
  "properties": {
    "iso:country":"US",
    "sg:address":"1591 Springtown Rd",
    "sg:city":"Alpha",
    "sg:classifiers":[
        {
            "category":"Home & Garden",
            "subcategory":"Building Materials",
            "type":"Retail Goods"
        }
    ],
    "sg:phone":"+1 908 454 6401",
    "sg:postcode":"08865",
    "sg:province":"NJ",
    "sg:tags":[
        "paint"
    ],
    "wof:name":"Alpha Paint Co",
    "wof:placetype":"venue"
},
  "geometry": {"coordinates":[-75.157831,40.66006],"type":"Point"}
}