{
  "type": "Feature",
  "properties": {
    "iso:country":"US",
    "sg:address":"970 Main Ave",
    "sg:city":"Passaic",
    "sg:classifiers":[
        {
            "category":"Retail",
            "subcategory":"Car Wash",
            "type":"Services"
        }
    ],
    "sg:phone":"+1 973 365 1322",
    "sg:postcode":"07055",
    "sg:province":"NJ",
    "sg:tags":[
        "polishing",
        "washing"
    ],
    "wof:name":"Stc Wash LLC",
    "wof:placetype":"venue"
},
  "geometry": {"coordinates":[-74.13459,40.870052],"type":"Point"}
}