{
  "type": "Feature",
  "properties": {
    "iso:country":"US",
    "sg:address":"213 N Delsea Dr",
    "sg:city":"Clayton",
    "sg:classifiers":[
        {
            "category":"Shopping",
            "subcategory":"Used Merchandise",
            "type":"Retail Goods"
        }
    ],
    "sg:phone":"+1 856 881 9910",
    "sg:postcode":"08312",
    "sg:province":"NJ",
    "sg:tags":[
        "antique"
    ],
    "wof:name":"Den Of Antiquity",
    "wof:placetype":"venue"
},
  "geometry": {"coordinates":[-75.091652,39.657862],"type":"Point"}
}