{
  "type": "Feature",
  "properties": {
    "addr:full":"78 Arlington Ave Bergenfield NJ 07621",
    "addr:housenumber":"78",
    "addr:postcode":"07621",
    "addr:street":"Arlington Ave",
    "iso:country":"US",
    "sg:address":"78 Arlington Ave",
    "sg:city":"Bergenfield",
    "sg:classifiers":[
        {
            "category":"Organizations",
            "subcategory":"Religious Organization",
            "type":"Services"
        }
    ],
    "sg:phone":"+1 201 384 0092",
    "sg:postcode":"07621",
    "sg:province":"NJ",
    "sg:tags":[
        "church"
    ],
    "wof:name":"Calvary Lutheran Church",
    "wof:placetype":"venue"
},
  "geometry": {"coordinates":[-74.000007,40.924423],"type":"Point"}
}