{
  "type": "Feature",
  "properties": {
    "addr:full":"707 Calhoun St Trenton NJ 08618",
    "addr:housenumber":"707",
    "addr:postcode":"08618",
    "addr:street":"Calhoun St",
    "iso:country":"US",
    "sg:address":"707 Calhoun St",
    "sg:city":"Trenton",
    "sg:classifiers":[
        {
            "category":"Government",
            "subcategory":"Office",
            "type":"Public Place"
        }
    ],
    "sg:phone":"+1 609 989 3175",
    "sg:postcode":"08618",
    "sg:province":"NJ",
    "sg:tags":[
        "city",
        "program"
    ],
    "wof:name":"Trenton Solid Waste Mgmt",
    "wof:placetype":"venue"
},
  "geometry": {"coordinates":[-74.766846,40.230764],"type":"Point"}
}