{
  "type": "Feature",
  "properties": {
    "addr:full":"307 66th St West New York NJ 07093",
    "addr:housenumber":"307",
    "addr:postcode":"nj 07093",
    "addr:street":"66Th St West",
    "iso:country":"US",
    "sg:address":"307 66th St",
    "sg:city":"West New York",
    "sg:classifiers":[
        {
            "category":"Building & Trades",
            "subcategory":"Construction",
            "type":"Services"
        }
    ],
    "sg:phone":"+1 201 453 0048",
    "sg:postcode":"07093",
    "sg:province":"NJ",
    "sg:tags":[
        "house"
    ],
    "wof:name":"Montufar Construction Inc",
    "wof:placetype":"venue"
},
  "geometry": {"coordinates":[-74.01037100000001,40.792388],"type":"Point"}
}