{
  "type": "Feature",
  "properties": {
    "addr:full":"202 Stockton St Hightstown NJ 08520",
    "addr:housenumber":"202",
    "addr:postcode":"08520",
    "addr:street":"Stockton St",
    "iso:country":"US",
    "sg:address":"202 Stockton St",
    "sg:city":"Hightstown",
    "sg:classifiers":[
        {
            "category":"Retail",
            "subcategory":"Funeral Services",
            "type":"Services"
        }
    ],
    "sg:phone":"+1   ",
    "sg:postcode":"08520",
    "sg:province":"NJ",
    "wof:name":"Barlow J Brent",
    "wof:placetype":"venue"
},
  "geometry": {"coordinates":[-74.52820199999999,40.270962],"type":"Point"}
}