{
  "type": "Feature",
  "properties": {
    "addr:full":"90 Main St Woodbridge NJ 07095",
    "addr:housenumber":"90",
    "addr:postcode":"07095",
    "addr:street":"Main St",
    "iso:country":"US",
    "sg:address":"90 Main St",
    "sg:city":"Woodbridge",
    "sg:classifiers":[
        {
            "category":"Building & Trades",
            "subcategory":"Cleaning & Sanitation",
            "type":"Services"
        }
    ],
    "sg:phone":"+1   ",
    "sg:postcode":"07095",
    "sg:province":"NJ",
    "sg:tags":[
        "maintenance"
    ],
    "wof:name":"Bright Ideas",
    "wof:placetype":"venue"
},
  "geometry": {"coordinates":[-74.282596,40.553668],"type":"Point"}
}