{
  "type": "Feature",
  "properties": {
    "iso:country":"US",
    "sg:address":"17 W Palisade Ave",
    "sg:city":"Englewood",
    "sg:classifiers":[
        {
            "category":"Shopping",
            "subcategory":"Music",
            "type":"Retail Goods"
        }
    ],
    "sg:phone":"+1 201 816 8117",
    "sg:postcode":"07631",
    "sg:province":"NJ",
    "sg:tags":[
        "compact",
        "record",
        "disc",
        "tape"
    ],
    "wof:name":"Your Beat",
    "wof:placetype":"venue"
},
  "geometry": {"coordinates":[-73.97556899999999,40.894381],"type":"Point"}
}