{
  "type": "Feature",
  "properties": {
    "addr:full":"11 Cayuga Ct Springfield NJ 07081",
    "addr:housenumber":"11",
    "addr:postcode":"07081",
    "addr:street":"Cayuga Ct",
    "iso:country":"US",
    "sg:address":"11 Cayuga Ct",
    "sg:city":"Springfield",
    "sg:classifiers":[
        {
            "category":"Wholesale",
            "subcategory":"Metals & Minerals",
            "type":"Manufacturing & Wholesale Goods"
        }
    ],
    "sg:phone":"+1 973 376 1269",
    "sg:postcode":"07081",
    "sg:province":"NJ",
    "sg:tags":[
        "center"
    ],
    "wof:name":"Frei Chuck",
    "wof:placetype":"venue"
},
  "geometry": {"coordinates":[-74.30998099999999,40.692935],"type":"Point"}
}