{
  "type": "Feature",
  "properties": {
    "addr:full":"3 Condron Ln Little Falls NJ 07424",
    "addr:housenumber":"3",
    "addr:postcode":"07424",
    "addr:street":"Condron Ln",
    "iso:country":"US",
    "sg:address":"3 Condron Ln",
    "sg:city":"Little Falls",
    "sg:classifiers":[
        {
            "category":"Banks & Credit Unions",
            "subcategory":"Financial Services",
            "type":"Services"
        }
    ],
    "sg:phone":"+1   ",
    "sg:postcode":"07424",
    "sg:province":"NJ",
    "sg:tags":[
        "investor"
    ],
    "wof:name":"Next World Investments LLC",
    "wof:placetype":"venue"
},
  "geometry": {"coordinates":[-74.19011999999999,40.88497],"type":"Point"}
}