{
  "type": "Feature",
  "properties": {
    "addr:full":"1 Krebs Rd Plainsboro NJ 08536",
    "addr:housenumber":"1",
    "addr:postcode":"08536",
    "addr:street":"Krebs Rd",
    "iso:country":"US",
    "sg:address":"1 Krebs Rd",
    "sg:city":"Plainsboro",
    "sg:classifiers":[
        {
            "category":"Professional",
            "subcategory":"Management & Consulting",
            "type":"Services"
        }
    ],
    "sg:phone":"+1 609 275 1424",
    "sg:postcode":"08536",
    "sg:province":"NJ",
    "sg:tags":[
        "business"
    ],
    "wof:name":"Sine Solutions Inc",
    "wof:placetype":"venue"
},
  "geometry": {"coordinates":[-74.583585,40.35677],"type":"Point"}
}