{
  "type": "Feature",
  "properties": {
    "addr:full":"7 Ardsley Ct Belle Mead NJ 08550",
    "addr:housenumber":"7",
    "addr:postcode":"08550",
    "addr:street":"Ardsley Ct Belle Mead",
    "iso:country":"US",
    "sg:address":"7 Ardsley Ct",
    "sg:city":"Belle Mead",
    "sg:classifiers":[
        {
            "category":"Professional",
            "type":"Services"
        }
    ],
    "sg:phone":"+1 908 431 9605",
    "sg:postcode":"08550",
    "sg:province":"NJ",
    "sg:tags":[
        "establishment"
    ],
    "wof:name":"Getronics",
    "wof:placetype":"venue"
},
  "geometry": {"coordinates":[-74.615835,40.28111],"type":"Point"}
}