{
  "type": "Feature",
  "properties": {
    "addr:full":"136 Lincoln Ave Hawthorne NJ 07410",
    "addr:housenumber":"136",
    "addr:postcode":"07410",
    "addr:street":"Lincoln Ave",
    "iso:country":"US",
    "sg:address":"136 Lincoln Ave",
    "sg:city":"Hawthorne",
    "sg:classifiers":[
        {
            "category":"Building & Trades",
            "subcategory":"Landscaping Services",
            "type":"Services"
        }
    ],
    "sg:phone":"+1 973 636 2889",
    "sg:postcode":"07410",
    "sg:province":"NJ",
    "sg:tags":[
        "landscape",
        "contractor"
    ],
    "wof:name":"J & O Landscaping",
    "wof:placetype":"venue"
},
  "geometry": {"coordinates":[-74.14668500000001,40.947181],"type":"Point"}
}