{
  "type": "Feature",
  "properties": {
    "addr:full":"17 Hilliard Ave Edgewater NJ 07020",
    "addr:housenumber":"17",
    "addr:postcode":"07020",
    "addr:street":"Hilliard Ave",
    "iso:country":"US",
    "sg:address":"17 Hilliard Ave",
    "sg:city":"Edgewater",
    "sg:classifiers":[
        {
            "category":"Communications",
            "subcategory":"Film & Video Production",
            "type":"Services"
        }
    ],
    "sg:phone":"+1 201 945 0844",
    "sg:postcode":"07020",
    "sg:province":"NJ",
    "sg:tags":[
        "motion",
        "taping"
    ],
    "wof:name":"Hook Mountain Productions LLC",
    "wof:placetype":"venue"
},
  "geometry": {"coordinates":[-73.97415599999999,40.826093],"type":"Point"}
}