{
  "type": "Feature",
  "properties": {
    "addr:full":"726 Wilhelm St Harrison NJ 07029",
    "addr:housenumber":"726",
    "addr:postcode":"07029",
    "addr:street":"Wilhelm St",
    "iso:country":"US",
    "sg:address":"726 Wilhelm St",
    "sg:city":"Harrison",
    "sg:classifiers":[
        {
            "category":"Bakery",
            "type":"Food & Drink"
        }
    ],
    "sg:phone":"+1 973 485 1515",
    "sg:postcode":"07029",
    "sg:province":"NJ",
    "wof:name":"Shra-Lin's Pita Bakery",
    "wof:placetype":"venue"
},
  "geometry": {"coordinates":[-74.1493,40.744598],"type":"Point"}
}