{
  "type": "Feature",
  "properties": {
    "iso:country":"US",
    "sg:address":"1610 State Rte 35",
    "sg:city":"Oakhurst",
    "sg:classifiers":[
        {
            "category":"Personal",
            "subcategory":"Tanning Parlor",
            "type":"Services"
        }
    ],
    "sg:phone":"+1 732 517 0303",
    "sg:postcode":"07755",
    "sg:province":"NJ",
    "sg:tags":[
        "salon"
    ],
    "wof:name":"Tiki Tan Of Ocean",
    "wof:placetype":"venue"
},
  "geometry": {"coordinates":[-74.041594,40.261903],"type":"Point"}
}