{
  "type": "Feature",
  "properties": {
    "addr:full":"113 Monroe Ave Pitman NJ 08071",
    "addr:housenumber":"113",
    "addr:postcode":"08071",
    "addr:street":"Monroe Ave",
    "iso:country":"US",
    "sg:address":"113 Monroe Ave",
    "sg:city":"Pitman",
    "sg:classifiers":[
        {
            "category":"Building & Trades",
            "subcategory":"Cleaning & Sanitation",
            "type":"Services"
        }
    ],
    "sg:phone":"+1 856 286 3253",
    "sg:postcode":"08071",
    "sg:province":"NJ",
    "sg:tags":[
        "fireplace",
        "chimney"
    ],
    "wof:name":"Coppertop Chimney Svc",
    "wof:placetype":"venue"
},
  "geometry": {"coordinates":[-75.116724,39.724211],"type":"Point"}
}