{
  "type": "Feature",
  "properties": {
    "iso:country":"US",
    "sg:address":"1970 Springfield Ave",
    "sg:city":"Maplewood",
    "sg:classifiers":[
        {
            "category":"Retail",
            "subcategory":"Repair Shop",
            "type":"Services"
        },
        {
            "category":"Home & Garden",
            "subcategory":"Garden Supply",
            "type":"Retail Goods"
        }
    ],
    "sg:phone":"+1 973 763 6637",
    "sg:postcode":"07040",
    "sg:province":"NJ",
    "sg:tags":[
        "lawn",
        "mower"
    ],
    "wof:name":"P & P Lawnmowers",
    "wof:placetype":"venue"
},
  "geometry": {"coordinates":[-74.274416,40.720077],"type":"Point"}
}