{
  "type": "Feature",
  "properties": {
    "addr:full":"100 W Sheffield Ave Englewood NJ 07631",
    "addr:housenumber":"100",
    "addr:postcode":"07631",
    "addr:street":"W Sheffield Ave",
    "iso:country":"US",
    "sg:address":"100 W Sheffield Ave",
    "sg:city":"Englewood",
    "sg:classifiers":[
        {
            "category":"Manufacturing",
            "subcategory":"Tools & Machinery",
            "type":"Manufacturing & Wholesale Goods"
        }
    ],
    "sg:phone":"+1 201 568 0830",
    "sg:postcode":"07631",
    "sg:province":"NJ",
    "sg:tags":[
        "appliance",
        "electric"
    ],
    "sg:website":"www.royalsovereign.com",
    "wof:name":"Royal Sovereign",
    "wof:placetype":"venue"
},
  "geometry": {"coordinates":[-73.989271,40.878881],"type":"Point"}
}