{
  "type": "Feature",
  "properties": {
    "iso:country":"US",
    "sg:address":"647 N County Line Rd",
    "sg:city":"Jackson",
    "sg:classifiers":[
        {
            "category":"Local Transit",
            "type":"Transportation"
        }
    ],
    "sg:phone":"+1 732 928 6031",
    "sg:postcode":"08527",
    "sg:province":"NJ",
    "sg:tags":[
        "limousine",
        "nationwide"
    ],
    "wof:name":"Stretch One Limousine Service",
    "wof:placetype":"venue"
},
  "geometry": {"coordinates":[-74.323454,40.147382],"type":"Point"}
}