{
  "type": "Feature",
  "properties": {
    "iso:country":"US",
    "sg:address":"3034 Marlton Pike",
    "sg:city":"Pennsauken",
    "sg:classifiers":[
        {
            "category":"Social Services",
            "subcategory":"Child Care",
            "type":"Services"
        }
    ],
    "sg:phone":"+1 856 317 2233",
    "sg:postcode":"08110",
    "sg:province":"NJ",
    "wof:name":"El Shaddai II Day Care Inc",
    "wof:placetype":"venue"
},
  "geometry": {"coordinates":[-75.08105999999999,39.939673],"type":"Point"}
}