{
  "type": "Feature",
  "properties": {
    "iso:country":"US",
    "sg:address":"281 Allwood Rd",
    "sg:city":"Clifton",
    "sg:classifiers":[
        {
            "category":"Restaurant",
            "type":"Food & Drink"
        }
    ],
    "sg:phone":"+1 973 777 0511",
    "sg:postcode":"07011",
    "sg:province":"NJ",
    "sg:tags":[
        "diner"
    ],
    "sg:website":"www.theticktockdiner.com/",
    "wof:name":"Tick-Tock Diner",
    "wof:placetype":"venue"
},
  "geometry": {"coordinates":[-74.152368,40.836851],"type":"Point"}
}