{
  "type": "Feature",
  "properties": {
    "addr:full":"504 W Rio Grande Ave Wildwood NJ 08260",
    "addr:housenumber":"504",
    "addr:postcode":"08260",
    "addr:street":"W Rio Grande Ave",
    "iso:country":"US",
    "sg:address":"504 W Rio Grande Ave",
    "sg:city":"Wildwood",
    "sg:classifiers":[
        {
            "category":"Recreation",
            "type":"Entertainment"
        },
        {
            "category":"Manufacturing",
            "subcategory":"Watercraft",
            "type":"Manufacturing & Wholesale Goods"
        }
    ],
    "sg:phone":"+1 609 729 7777",
    "sg:postcode":"08260",
    "sg:province":"NJ",
    "sg:tags":[
        "party",
        "fishing"
    ],
    "wof:name":"Adventurer Deep Sea Fishing",
    "wof:placetype":"venue"
},
  "geometry": {"coordinates":[-74.830716,38.988994],"type":"Point"}
}