{
  "type": "Feature",
  "properties": {
    "iso:country":"US",
    "sg:address":"86 Stephenville Pkwy",
    "sg:city":"Edison",
    "sg:classifiers":[
        {
            "category":"Professional",
            "subcategory":"Business Services",
            "type":"Services"
        }
    ],
    "sg:phone":"+1   ",
    "sg:postcode":"08820",
    "sg:province":"NJ",
    "wof:name":"Ifc Ventures Inc",
    "wof:placetype":"venue"
},
  "geometry": {"coordinates":[-74.366997,40.569989],"type":"Point"}
}