{
  "type": "Feature",
  "properties": {
    "iso:country":"US",
    "sg:address":"807 Franklin Ave",
    "sg:city":"Franklin Lakes",
    "sg:classifiers":[
        {
            "category":"Utilities",
            "subcategory":"Mobile Phone",
            "type":"Services"
        }
    ],
    "sg:phone":"+1 201 847 2355",
    "sg:postcode":"07417",
    "sg:province":"NJ",
    "sg:tags":[
        "telephone",
        "cellular"
    ],
    "wof:name":"Phones For You",
    "wof:placetype":"venue"
},
  "geometry": {"coordinates":[-74.209456,41.023989],"type":"Point"}
}