{
  "type": "Feature",
  "properties": {
    "iso:country":"US",
    "sg:address":"7 Park St",
    "sg:city":"Montclair",
    "sg:classifiers":[
        {
            "category":"Sports & Exercise",
            "subcategory":"Bowling",
            "type":"Entertainment"
        }
    ],
    "sg:phone":"+1   ",
    "sg:postcode":"07042",
    "sg:province":"NJ",
    "sg:tags":[
        "center"
    ],
    "wof:name":"Mary White Lanes",
    "wof:placetype":"venue"
},
  "geometry": {"coordinates":[-74.218171,40.815962],"type":"Point"}
}