{
  "type": "Feature",
  "properties": {
    "addr:full":"1582 Glassboro Rd Wenonah NJ 08090",
    "addr:housenumber":"1582",
    "addr:postcode":"08090",
    "addr:street":"Glassboro Rd",
    "iso:country":"US",
    "sg:address":"1582 Glassboro Rd",
    "sg:city":"Wenonah",
    "sg:classifiers":[
        {
            "category":"Professional",
            "subcategory":"Management & Consulting",
            "type":"Services"
        }
    ],
    "sg:phone":"+1   ",
    "sg:postcode":"08090",
    "sg:province":"NJ",
    "sg:tags":[
        "organizational"
    ],
    "wof:name":"Vortex Consulting LLC",
    "wof:placetype":"venue"
},
  "geometry": {"coordinates":[-75.14075099999999,39.790181],"type":"Point"}
}