{
  "type": "Feature",
  "properties": {
    "iso:country":"US",
    "sg:address":"26 Linden Ave",
    "sg:city":"Springfield",
    "sg:classifiers":[
        {
            "category":"Home & Garden",
            "subcategory":"Building Materials",
            "type":"Retail Goods"
        }
    ],
    "sg:phone":"+1 973 912 9565",
    "sg:postcode":"07081",
    "sg:province":"NJ",
    "sg:tags":[
        "equipment",
        "fixture",
        "lighting"
    ],
    "wof:name":"Metrolight Sales Corp",
    "wof:placetype":"venue"
},
  "geometry": {"coordinates":[-74.309303,40.7099],"type":"Point"}
}