{
  "type": "Feature",
  "properties": {
    "addr:full":"36 Fairhaven Dr Cherry Hill NJ 08003",
    "addr:housenumber":"36",
    "addr:postcode":"08003",
    "addr:street":"Fairhaven Dr",
    "iso:country":"US",
    "sg:address":"36 Fairhaven Dr",
    "sg:city":"Cherry Hill",
    "sg:classifiers":[
        {
            "category":"Communications",
            "type":"Services"
        }
    ],
    "sg:phone":"+1 856 751 9681",
    "sg:postcode":"08003",
    "sg:province":"NJ",
    "wof:name":"A T & Tcits",
    "wof:placetype":"venue"
},
  "geometry": {"coordinates":[-74.95899199999999,39.875325],"type":"Point"}
}