{
  "type": "Feature",
  "properties": {
    "addr:full":"98 Ladow Ave Millville NJ 08332",
    "addr:housenumber":"98",
    "addr:postcode":"08332",
    "addr:street":"Ladow Ave",
    "iso:country":"US",
    "sg:address":"98 Ladow Ave",
    "sg:city":"Millville",
    "sg:classifiers":[
        {
            "category":"Railroad",
            "type":"Transportation"
        }
    ],
    "sg:phone":"+1 856 765 0389",
    "sg:postcode":"08332",
    "sg:province":"NJ",
    "wof:name":"Conrail Corp",
    "wof:placetype":"venue"
},
  "geometry": {"coordinates":[-75.033895,39.418622],"type":"Point"}
}