{
  "type": "Feature",
  "properties": {
    "iso:country":"US",
    "sg:address":"509 Washington Ave",
    "sg:city":"Carlstadt",
    "sg:classifiers":[
        {
            "category":"Government",
            "subcategory":"Fire Station",
            "type":"Public Place"
        }
    ],
    "sg:phone":"+1 877 361 3187",
    "sg:postcode":"07072",
    "sg:province":"NJ",
    "sg:tags":[
        "consultant",
        "protection"
    ],
    "sg:website":"http://www.MetroFire.com",
    "wof:name":"Metro Fire & Safety Equipment Co., Inc.",
    "wof:placetype":"venue"
},
  "geometry": {"coordinates":[-74.05944100000001,40.823795],"type":"Point"}
}