{
  "type": "Feature",
  "properties": {
    "iso:country":"US",
    "sg:address":"228 E Bay Ave",
    "sg:city":"Manahawkin",
    "sg:classifiers":[
        {
            "category":"Retail",
            "subcategory":"Auto Repair",
            "type":"Services"
        }
    ],
    "sg:phone":"+1 609 597 8717",
    "sg:postcode":"08050",
    "sg:province":"NJ",
    "sg:tags":[
        "repairing",
        "automobile",
        "general"
    ],
    "wof:name":"Kevin's Auto & Truck Repair",
    "wof:placetype":"venue"
},
  "geometry": {"coordinates":[-74.252137,39.692172],"type":"Point"}
}