{
  "type": "Feature",
  "properties": {
    "addr:full":"215 Gates Rd Ste I Little Ferry NJ 07643",
    "addr:housenumber":"215",
    "addr:postcode":"07643",
    "addr:street":"Gates Rd Ste I;Ferry",
    "iso:country":"US",
    "sg:address":"215 Gates Rd Ste I",
    "sg:city":"Little Ferry",
    "sg:classifiers":[
        {
            "category":"Building & Trades",
            "subcategory":"Plumbing",
            "type":"Services"
        }
    ],
    "sg:phone":"+1 201 641 6700",
    "sg:postcode":"07643",
    "sg:province":"NJ",
    "wof:name":"Galdi Plumbing & Heating Inc",
    "wof:placetype":"venue"
},
  "geometry": {"coordinates":[-74.032291,40.843819],"type":"Point"}
}