{
  "type": "Feature",
  "properties": {
    "iso:country":"US",
    "sg:address":"163 Main St",
    "sg:city":"East Brunswick",
    "sg:classifiers":[
        {
            "category":"Autos & Motor Vehicles",
            "subcategory":"Automobile Sales",
            "type":"Retail Goods"
        }
    ],
    "sg:phone":"+1   ",
    "sg:postcode":"08816",
    "sg:province":"NJ",
    "sg:tags":[
        "used"
    ],
    "wof:name":"Deals On Wheels Auto Sales",
    "wof:placetype":"venue"
},
  "geometry": {"coordinates":[-74.366871,40.413971],"type":"Point"}
}