{
  "type": "Feature",
  "properties": {
    "iso:country":"US",
    "sg:address":"7305 Ventnor Ave",
    "sg:city":"Ventnor City",
    "sg:classifiers":[
        {
            "category":"Wholesale",
            "subcategory":"Durable Goods & Equipment",
            "type":"Manufacturing & Wholesale Goods"
        }
    ],
    "sg:phone":"+1 609 822 0351",
    "sg:postcode":"08406",
    "sg:province":"NJ",
    "sg:tags":[
        "luggage"
    ],
    "wof:name":"Dony Simon Plus",
    "wof:placetype":"venue"
},
  "geometry": {"coordinates":[-74.49207800000001,39.3335],"type":"Point"}
}