{
  "type": "Feature",
  "properties": {
    "iso:country":"US",
    "sg:address":"22 Louise St",
    "sg:city":"Garfield",
    "sg:classifiers":[
        {
            "category":"Professional",
            "subcategory":"Business Services",
            "type":"Services"
        }
    ],
    "sg:phone":"+1 973 253 2781",
    "sg:postcode":"07026",
    "sg:province":"NJ",
    "sg:tags":[
        "messenger"
    ],
    "wof:name":"Fast Messenger Svc LLC",
    "wof:placetype":"venue"
},
  "geometry": {"coordinates":[-74.11424,40.889019],"type":"Point"}
}