{
  "type": "Feature",
  "properties": {
    "iso:country":"US",
    "sg:address":"715 Park Ave",
    "sg:city":"Lakewood",
    "sg:classifiers":[
        {
            "category":"Organizations",
            "subcategory":"Religious Organization",
            "type":"Services"
        }
    ],
    "sg:phone":"+1   ",
    "sg:postcode":"08701",
    "sg:province":"NJ",
    "wof:name":"House Of True Worship",
    "wof:placetype":"venue"
},
  "geometry": {"coordinates":[-74.204313,40.099537],"type":"Point"}
}