{
  "type": "Feature",
  "properties": {
    "iso:country":"US",
    "sg:address":"37 Stout St",
    "sg:city":"Paterson",
    "sg:classifiers":[
        {
            "category":"Professional",
            "subcategory":"Business Services",
            "type":"Services"
        }
    ],
    "sg:phone":"+1   ",
    "sg:postcode":"07522",
    "sg:province":"NJ",
    "wof:name":"Bentstudios",
    "wof:placetype":"venue"
},
  "geometry": {"coordinates":[-74.169951,40.92522],"type":"Point"}
}