{
  "type": "Feature",
  "properties": {
    "addr:full":"75 Franklin Ave Ridgewood NJ 07450",
    "addr:housenumber":"75",
    "addr:postcode":"07450",
    "addr:street":"Franklin Ave",
    "iso:country":"US",
    "sg:address":"75 Franklin Ave",
    "sg:city":"Ridgewood",
    "sg:classifiers":[
        {
            "category":"Professional",
            "subcategory":"Engineering",
            "type":"Services"
        }
    ],
    "sg:phone":"+1 201 445 8685",
    "sg:postcode":"07450",
    "sg:province":"NJ",
    "sg:tags":[
        "engineer"
    ],
    "wof:name":"Van Ness Engineering",
    "wof:placetype":"venue"
},
  "geometry": {"coordinates":[-74.11852399999999,40.981237],"type":"Point"}
}