{
  "type": "Feature",
  "properties": {
    "iso:country":"US",
    "sg:address":"20 Colfax Ave",
    "sg:city":"Clifton",
    "sg:classifiers":[
        {
            "category":"Wholesale",
            "subcategory":"Electrical",
            "type":"Manufacturing & Wholesale Goods"
        }
    ],
    "sg:phone":"+1 973 472 7800",
    "sg:postcode":"07013",
    "sg:province":"NJ",
    "sg:tags":[
        "equipment",
        "or",
        "supply"
    ],
    "wof:name":"Breakers & Controls Inc",
    "wof:placetype":"venue"
},
  "geometry": {"coordinates":[-74.152362,40.865226],"type":"Point"}
}