{
  "type": "Feature",
  "properties": {
    "iso:country":"US",
    "sg:address":"85 Jackson Ave",
    "sg:city":"Rutherford",
    "sg:classifiers":[
        {
            "category":"Restaurant",
            "type":"Food & Drink"
        }
    ],
    "sg:phone":"+1   ",
    "sg:postcode":"07070",
    "sg:province":"NJ",
    "sg:tags":[
        "eating"
    ],
    "wof:name":"Lily S Cafe Inc",
    "wof:placetype":"venue"
},
  "geometry": {"coordinates":[-74.115413,40.839088],"type":"Point"}
}