{
  "type": "Feature",
  "properties": {
    "addr:full":"9 Whitewood Dr Morris Plains NJ 07950",
    "addr:housenumber":"9",
    "addr:postcode":"07950",
    "addr:street":"Whitewood Dr",
    "iso:country":"US",
    "sg:address":"9 Whitewood Dr",
    "sg:city":"Morris Plains",
    "sg:classifiers":[
        {
            "category":"Professional",
            "subcategory":"Management & Consulting",
            "type":"Services"
        }
    ],
    "sg:phone":"+1   ",
    "sg:postcode":"07950",
    "sg:province":"NJ",
    "sg:tags":[
        "electronic",
        "sales"
    ],
    "wof:name":"Latronics",
    "wof:placetype":"venue"
},
  "geometry": {"coordinates":[-74.471467,40.868225],"type":"Point"}
}