{
  "type": "Feature",
  "properties": {
    "iso:country":"US",
    "sg:address":"149 Old York Rd",
    "sg:city":"Ringoes",
    "sg:classifiers":[
        {
            "category":"Building & Trades",
            "subcategory":"Construction",
            "type":"Services"
        }
    ],
    "sg:phone":"+1 908 788 4040",
    "sg:postcode":"08551",
    "sg:province":"NJ",
    "sg:tags":[
        "house"
    ],
    "wof:name":"Clonmel Construction Corp",
    "wof:placetype":"venue"
},
  "geometry": {"coordinates":[-74.82827,40.466183],"type":"Point"}
}