{
  "type": "Feature",
  "properties": {
    "addr:full":"3 Lin Ford Ct Marlboro NJ 07746",
    "addr:housenumber":"3",
    "addr:postcode":"07746",
    "addr:street":"Lin Ford Ct",
    "iso:country":"US",
    "sg:address":"3 Lin Ford Ct",
    "sg:city":"Marlboro",
    "sg:classifiers":[
        {
            "category":"Professional",
            "subcategory":"Computer Services",
            "type":"Services"
        }
    ],
    "sg:phone":"+1   ",
    "sg:postcode":"07746",
    "sg:province":"NJ",
    "sg:tags":[
        "related"
    ],
    "wof:name":"Shoreline Systems Inc",
    "wof:placetype":"venue"
},
  "geometry": {"coordinates":[-74.22902499999999,40.320229],"type":"Point"}
}