{
  "type": "Feature",
  "properties": {
    "iso:country":"US",
    "sg:address":"601 N 5th St",
    "sg:city":"Camden",
    "sg:classifiers":[
        {
            "category":"Building & Trades",
            "subcategory":"Locksmith",
            "type":"Services"
        }
    ],
    "sg:phone":"+1 856 536 3017",
    "sg:postcode":"08102",
    "sg:province":"NJ",
    "sg:tags":[
        "key"
    ],
    "wof:name":"1&a Anytime Locksmith",
    "wof:placetype":"venue"
},
  "geometry": {"coordinates":[-75.11962,39.951013],"type":"Point"}
}