{
  "type": "Feature",
  "properties": {
    "addr:full":"111 W 50th St Bayonne NJ 07002",
    "addr:housenumber":"111",
    "addr:postcode":"07002",
    "addr:street":"W 50Th St",
    "iso:country":"US",
    "sg:address":"111 W 50th St",
    "sg:city":"Bayonne",
    "sg:classifiers":[
        {
            "category":"Retail",
            "subcategory":"Auto Repair",
            "type":"Services"
        }
    ],
    "sg:phone":"+1 201 339 7505",
    "sg:postcode":"07002",
    "sg:province":"NJ",
    "wof:name":"Richie's Auto Repair",
    "wof:placetype":"venue"
},
  "geometry": {"coordinates":[-74.10610200000001,40.684502],"type":"Point"}
}