{
  "type": "Feature",
  "properties": {
    "iso:country":"US",
    "sg:address":"52 Reading Blvd",
    "sg:city":"Belle Mead",
    "sg:classifiers":[
        {
            "category":"Social Services",
            "type":"Services"
        }
    ],
    "sg:phone":"+1 908 359 4045",
    "sg:postcode":"08502",
    "sg:province":"NJ",
    "sg:tags":[
        "youth",
        "organization",
        "center"
    ],
    "wof:name":"Montgomery Baseball League",
    "wof:placetype":"venue"
},
  "geometry": {"coordinates":[-74.667176,40.463654],"type":"Point"}
}