{
  "type": "Feature",
  "properties": {
    "iso:country":"US",
    "sg:address":"34 Industrial Way E",
    "sg:city":"Eatontown",
    "sg:classifiers":[
        {
            "category":"Utilities",
            "subcategory":"Telephone",
            "type":"Services"
        }
    ],
    "sg:phone":"+1 732 544 2310",
    "sg:postcode":"07724",
    "sg:province":"NJ",
    "sg:tags":[
        "telecommunication"
    ],
    "wof:name":"Bowthorpe Telecom Group",
    "wof:placetype":"venue"
},
  "geometry": {"coordinates":[-74.041107,40.282768],"type":"Point"}
}