{
  "type": "Feature",
  "properties": {
    "iso:country":"US",
    "sg:address":"2300 Marlton Pike W",
    "sg:city":"Cherry Hill",
    "sg:classifiers":[
        {
            "category":"Restaurant",
            "type":"Food & Drink"
        }
    ],
    "sg:phone":"+1 856 665 4824",
    "sg:postcode":"08034",
    "sg:province":"NJ",
    "sg:tags":[
        "pizza"
    ],
    "sg:website":"www.thefamouskingofpizza.com/",
    "wof:name":"King of Pizza",
    "wof:placetype":"venue"
},
  "geometry": {"coordinates":[-75.047139,39.925082],"type":"Point"}
}