{
  "type": "Feature",
  "properties": {
    "addr:full":"5 River St Exd Little Ferry NJ 07643",
    "addr:housenumber":"5",
    "addr:postcode":"07643",
    "addr:street":"River St Exd;Ferry",
    "iso:country":"US",
    "sg:address":"5 River St Exd",
    "sg:city":"Little Ferry",
    "sg:classifiers":[
        {
            "category":"Building & Trades",
            "subcategory":"Electrical",
            "type":"Services"
        }
    ],
    "sg:phone":"+1 201 229 1394",
    "sg:postcode":"07643",
    "sg:province":"NJ",
    "sg:tags":[
        "electrical",
        "contractor"
    ],
    "wof:name":"Sexton Electric",
    "wof:placetype":"venue"
},
  "geometry": {"coordinates":[-74.03529399999999,40.857609],"type":"Point"}
}