{
  "type": "Feature",
  "properties": {
    "addr:full":"300 Somerset St Gloucester City NJ 08030",
    "addr:housenumber":"300",
    "addr:postcode":"08030",
    "addr:street":"Somerset St",
    "iso:country":"US",
    "sg:address":"300 Somerset St",
    "sg:city":"Gloucester City",
    "sg:classifiers":[
        {
            "category":"Deli",
            "type":"Food & Drink"
        }
    ],
    "sg:phone":"+1 856 456 7077",
    "sg:postcode":"08030",
    "sg:province":"NJ",
    "wof:name":"Bramble's Cold Cuts",
    "wof:placetype":"venue"
},
  "geometry": {"coordinates":[-75.124199,39.897301],"type":"Point"}
}