{
  "type": "Feature",
  "properties": {
    "iso:country":"US",
    "sg:address":"26 Rockleigh Rd",
    "sg:city":"Rockleigh",
    "sg:classifiers":[
        {
            "category":"Government",
            "subcategory":"Fire Station",
            "type":"Public Place"
        }
    ],
    "sg:phone":"+1 201 768 2091",
    "sg:postcode":"07647",
    "sg:province":"NJ",
    "sg:tags":[
        "department"
    ],
    "wof:name":"Rockleigh Fire Marshall",
    "wof:placetype":"venue"
},
  "geometry": {"coordinates":[-73.926703,41.001731],"type":"Point"}
}