{
  "type": "Feature",
  "properties": {
    "iso:country":"US",
    "sg:address":"716 Dakota Trl",
    "sg:city":"Franklin Lakes",
    "sg:classifiers":[
        {
            "category":"Professional",
            "subcategory":"Management & Consulting",
            "type":"Services"
        },
        {
            "category":"Manufacturing",
            "subcategory":"Chemicals & Compounds",
            "type":"Manufacturing & Wholesale Goods"
        }
    ],
    "sg:phone":"+1 201 891 8787",
    "sg:postcode":"07417",
    "sg:province":"NJ",
    "sg:tags":[
        "preparation",
        "pharmaceutical",
        "mfg",
        "industrial",
        "consultant"
    ],
    "wof:name":"D H Gold Assoc Inc",
    "wof:placetype":"venue"
},
  "geometry": {"coordinates":[-74.233687,40.991217],"type":"Point"}
}