{
  "type": "Feature",
  "properties": {
    "iso:country":"US",
    "sg:address":"106 Wyoming St",
    "sg:city":"Westfield",
    "sg:classifiers":[
        {
            "category":"Professional",
            "subcategory":"Accounting & Tax Preparation",
            "type":"Services"
        }
    ],
    "sg:phone":"+1 908 232 4358",
    "sg:postcode":"07090",
    "sg:province":"NJ",
    "sg:tags":[
        "return",
        "filing"
    ],
    "wof:name":"Robert L Storcks Ea",
    "wof:placetype":"venue"
},
  "geometry": {"coordinates":[-74.31932999999999,40.635028],"type":"Point"}
}