{
  "type": "Feature",
  "properties": {
    "addr:full":"130 Market St Kenilworth NJ 07033",
    "addr:housenumber":"130",
    "addr:postcode":"07033",
    "addr:street":"Market St",
    "iso:country":"US",
    "sg:address":"130 Market St",
    "sg:city":"Kenilworth",
    "sg:classifiers":[
        {
            "category":"Wholesale",
            "subcategory":"Drugs",
            "type":"Manufacturing & Wholesale Goods"
        }
    ],
    "sg:phone":"+1 908 241 1818",
    "sg:postcode":"07033",
    "sg:province":"NJ",
    "wof:name":"Cardinal Health 414 Inc",
    "wof:placetype":"venue"
},
  "geometry": {"coordinates":[-74.281779,40.675008],"type":"Point"}
}