{
  "type": "Feature",
  "properties": {
    "addr:full":"210 Delancey St Newark NJ 07105",
    "addr:housenumber":"210",
    "addr:postcode":"07105",
    "addr:street":"Delancey St",
    "iso:country":"US",
    "sg:address":"210 Delancey St",
    "sg:city":"Newark",
    "sg:classifiers":[
        {
            "category":"Building & Trades",
            "subcategory":"Cleaning & Sanitation",
            "type":"Services"
        }
    ],
    "sg:phone":"+1 973 817 9459",
    "sg:postcode":"07105",
    "sg:province":"NJ",
    "sg:tags":[
        "janitor"
    ],
    "wof:name":"Vidal Professional Cleaner",
    "wof:placetype":"venue"
},
  "geometry": {"coordinates":[-74.15700200000001,40.718795],"type":"Point"}
}