{
  "type": "Feature",
  "properties": {
    "iso:country":"US",
    "sg:address":"945 Liberty St",
    "sg:city":"Trenton",
    "sg:classifiers":[
        {
            "category":"Fast Food",
            "type":"Food & Drink"
        },
        {
            "category":"Restaurant",
            "type":"Food & Drink"
        }
    ],
    "sg:phone":"+1 609 394 9698",
    "sg:postcode":"08611",
    "sg:province":"NJ",
    "sg:tags":[
        "take"
    ],
    "wof:name":"Zip's Steak House",
    "wof:placetype":"venue"
},
  "geometry": {"coordinates":[-74.73853699999999,40.208571],"type":"Point"}
}