{
  "type": "Feature",
  "properties": {
    "iso:country":"US",
    "sg:address":"1131 State Rte 36",
    "sg:city":"Hazlet",
    "sg:classifiers":[
        {
            "category":"Food & Beverages",
            "subcategory":"Bakery",
            "type":"Retail Goods"
        }
    ],
    "sg:phone":"+1 732 264 6539",
    "sg:postcode":"07730",
    "sg:province":"NJ",
    "sg:tags":[
        "specializing",
        "doughnut"
    ],
    "wof:name":"Dunkin' Donuts",
    "wof:placetype":"venue"
},
  "geometry": {"coordinates":[-74.181217,40.433488],"type":"Point"}
}