{
  "type": "Feature",
  "properties": {
    "iso:country":"US",
    "sg:address":"700 Sicklerville Rd",
    "sg:city":"Williamstown",
    "sg:classifiers":[
        {
            "category":"Shopping",
            "subcategory":"Party Supplies",
            "type":"Retail Goods"
        }
    ],
    "sg:phone":"+1 856 629 5445",
    "sg:postcode":"08094",
    "sg:province":"NJ",
    "sg:tags":[
        "toilets-portable"
    ],
    "wof:name":"Al Dennys Portable Toilets",
    "wof:placetype":"venue"
},
  "geometry": {"coordinates":[-74.986351,39.698132],"type":"Point"}
}