{
  "type": "Feature",
  "properties": {
    "iso:country":"US",
    "sg:address":"780 Passaic Ave",
    "sg:city":"West Caldwell",
    "sg:classifiers":[
        {
            "category":"Manufacturing",
            "subcategory":"Food",
            "type":"Manufacturing & Wholesale Goods"
        }
    ],
    "sg:phone":"+1 973 226 3100",
    "sg:postcode":"07006",
    "sg:province":"NJ",
    "sg:tags":[
        "frozen",
        "dessert",
        "ice",
        "cream"
    ],
    "wof:name":"Welsh Farms Ice Cream Inc",
    "wof:placetype":"venue"
},
  "geometry": {"coordinates":[-74.284245,40.863445],"type":"Point"}
}