{
  "type": "Feature",
  "properties": {
    "iso:country":"US",
    "sg:address":"59 Beaverbrook Rd Ste 303A",
    "sg:city":"Lincoln Park",
    "sg:classifiers":[
        {
            "category":"Education",
            "subcategory":"Kindergarten",
            "type":"Public Place"
        }
    ],
    "sg:phone":"+1 973 872 9199",
    "sg:postcode":"07035",
    "sg:province":"NJ",
    "sg:tags":[
        "school",
        "driving"
    ],
    "sg:website":"www.drivingschoolnj.com",
    "wof:name":"Aumm Auto Driving School",
    "wof:placetype":"venue"
},
  "geometry": {"coordinates":[-74.309843,40.924508],"type":"Point"}
}