{
  "type": "Feature",
  "properties": {
    "addr:full":"32 Sherman St Monroe Township NJ 08831",
    "addr:housenumber":"32",
    "addr:postcode":"08831",
    "addr:street":"Sherman St",
    "iso:country":"US",
    "sg:address":"32 Sherman St",
    "sg:city":"Monroe Township",
    "sg:classifiers":[
        {
            "category":"Professional",
            "type":"Services"
        }
    ],
    "sg:phone":"+1   ",
    "sg:postcode":"08831",
    "sg:province":"NJ",
    "wof:name":"United Tech Service",
    "wof:placetype":"venue"
},
  "geometry": {"coordinates":[-74.441817,40.355042],"type":"Point"}
}