{
  "type": "Feature",
  "properties": {
    "addr:full":"50 Main St Orange NJ 07050",
    "addr:housenumber":"50",
    "addr:postcode":"07050",
    "addr:street":"Main St",
    "iso:country":"US",
    "sg:address":"50 Main St",
    "sg:city":"Orange",
    "sg:classifiers":[
        {
            "category":"Food & Beverages",
            "subcategory":"Groceries & Convenience Stores",
            "type":"Retail Goods"
        }
    ],
    "sg:phone":"+1   ",
    "sg:postcode":"07050",
    "sg:province":"NJ",
    "wof:name":"Savannah Mini Market",
    "wof:placetype":"venue"
},
  "geometry": {"coordinates":[-74.22199000000001,40.768282],"type":"Point"}
}