{
  "type": "Feature",
  "properties": {
    "addr:full":"675 Paterson Plank Rd Carlstadt NJ 07072",
    "addr:housenumber":"675",
    "addr:postcode":"07072",
    "addr:street":"Paterson Plank Rd",
    "iso:country":"US",
    "sg:address":"675 Paterson Plank Rd",
    "sg:city":"Carlstadt",
    "sg:classifiers":[
        {
            "category":"Banks & Credit Unions",
            "subcategory":"Bank",
            "type":"Services"
        }
    ],
    "sg:phone":"+1 201 964 1540",
    "sg:postcode":"07072",
    "sg:province":"NJ",
    "sg:website":"www.wamu.com",
    "wof:name":"Washington Mutual",
    "wof:placetype":"venue"
},
  "geometry": {"coordinates":[-74.062589,40.811295],"type":"Point"}
}