{
  "type": "Feature",
  "properties": {
    "iso:country":"US",
    "sg:address":"344 Springfield Ave",
    "sg:city":"Newark",
    "sg:classifiers":[
        {
            "category":"Government",
            "subcategory":"Fire Station",
            "type":"Public Place"
        }
    ],
    "sg:phone":"+1 973 733 7485",
    "sg:postcode":"07103",
    "sg:province":"NJ",
    "sg:tags":[
        "department"
    ],
    "wof:name":"Fire Signal System Maintenance",
    "wof:placetype":"venue"
},
  "geometry": {"coordinates":[-74.19406600000001,40.73362],"type":"Point"}
}