{
  "type": "Feature",
  "properties": {
    "addr:full":"702 South Ave W Rear Westfield NJ 07090",
    "addr:housenumber":"702",
    "addr:postcode":"07090",
    "addr:street":"South Ave W Rear",
    "iso:country":"US",
    "sg:address":"702 South Ave W Rear",
    "sg:city":"Westfield",
    "sg:classifiers":[
        {
            "category":"Home & Garden",
            "subcategory":"Household Appliances",
            "type":"Retail Goods"
        },
        {
            "category":"Retail",
            "subcategory":"Repair Shop",
            "type":"Services"
        },
        {
            "category":"Wholesale",
            "subcategory":"Machinery & Supplies",
            "type":"Manufacturing & Wholesale Goods"
        },
        {
            "category":"Restaurant",
            "type":"Food & Drink"
        },
        {
            "category":"Building & Trades",
            "subcategory":"Construction",
            "type":"Services"
        }
    ],
    "sg:phone":"+1 908 232 5070",
    "sg:postcode":"07090",
    "sg:province":"NJ",
    "sg:tags":[
        "major",
        "equipment-commercial",
        "dishwashing",
        "supplies-refrigeration",
        "system",
        "contractor",
        "machine",
        "equipment",
        "industrial",
        "refrigeration",
        "air conditioning",
        "freezers-repair",
        "refrigerator"
    ],
    "wof:name":"Summit Rfrgn & Ac Co",
    "wof:placetype":"venue"
},
  "geometry": {"coordinates":[-74.35462200000001,40.647722],"type":"Point"}
}