{
  "type": "Feature",
  "properties": {
    "iso:country":"US",
    "sg:address":"145 Walnut St",
    "sg:city":"Englewood",
    "sg:classifiers":[
        {
            "category":"Professional",
            "subcategory":"Management & Consulting",
            "type":"Services"
        }
    ],
    "sg:phone":"+1   ",
    "sg:postcode":"07631",
    "sg:province":"NJ",
    "sg:tags":[
        "financial",
        "risk"
    ],
    "wof:name":"D N L Risk Management Assoc",
    "wof:placetype":"venue"
},
  "geometry": {"coordinates":[-73.967733,40.89426],"type":"Point"}
}