{
  "type": "Feature",
  "properties": {
    "addr:full":"74 Brick Blvd Brick NJ 08723",
    "addr:housenumber":"74",
    "addr:postcode":"08723",
    "addr:street":"Brick Blvd",
    "iso:country":"US",
    "sg:address":"74 Brick Blvd",
    "sg:city":"Brick",
    "sg:classifiers":[
        {
            "category":"Health Services",
            "subcategory":"Doctor",
            "type":"Services"
        }
    ],
    "sg:phone":"+1 732 920 8828",
    "sg:postcode":"08723",
    "sg:province":"NJ",
    "sg:tags":[
        "physician",
        "surgeon"
    ],
    "wof:name":"Alan M Tell MD",
    "wof:placetype":"venue"
},
  "geometry": {"coordinates":[-74.14410599999999,40.025462],"type":"Point"}
}