{
  "type": "Feature",
  "properties": {
    "iso:country":"US",
    "sg:address":"12 Hunters Pointe",
    "sg:city":"Middletown",
    "sg:classifiers":[
        {
            "category":"Wholesale",
            "subcategory":"Groceries",
            "type":"Manufacturing & Wholesale Goods"
        }
    ],
    "sg:phone":"+1 732 495 7735",
    "sg:postcode":"07748",
    "sg:province":"NJ",
    "sg:tags":[
        "confectionery"
    ],
    "wof:name":"B&H Snacks Inc",
    "wof:placetype":"venue"
},
  "geometry": {"coordinates":[-74.131224,40.419896],"type":"Point"}
}