{
  "type": "Feature",
  "properties": {
    "addr:full":"9 Gates Ave Montclair NJ 07042",
    "addr:housenumber":"9",
    "addr:postcode":"07042",
    "addr:street":"Gates Ave",
    "iso:country":"US",
    "sg:address":"9 Gates Ave",
    "sg:city":"Montclair",
    "sg:classifiers":[
        {
            "category":"Professional",
            "type":"Services"
        }
    ],
    "sg:phone":"+1   ",
    "sg:postcode":"07042",
    "sg:province":"NJ",
    "wof:name":"Know Frills",
    "wof:placetype":"venue"
},
  "geometry": {"coordinates":[-74.214939,40.810195],"type":"Point"}
}