{
  "type": "Feature",
  "properties": {
    "iso:country":"US",
    "sg:address":"280 N Midland Ave",
    "sg:city":"Saddle Brook",
    "sg:classifiers":[
        {
            "category":"Shopping",
            "subcategory":"Clothing, Apparel, & Fashions",
            "type":"Retail Goods"
        }
    ],
    "sg:phone":"+1   ",
    "sg:postcode":"07663",
    "sg:province":"NJ",
    "wof:name":"Q T Promotions",
    "wof:placetype":"venue"
},
  "geometry": {"coordinates":[-74.105993,40.906397],"type":"Point"}
}