{
  "type": "Feature",
  "properties": {
    "addr:full":"481 Island Rd Ramsey NJ 07446",
    "addr:housenumber":"481",
    "addr:postcode":"07446",
    "addr:street":"Island Rd",
    "iso:country":"US",
    "sg:address":"481 Island Rd",
    "sg:city":"Ramsey",
    "sg:classifiers":[
        {
            "category":"Farming",
            "subcategory":"Nursery",
            "type":"Manufacturing & Wholesale Goods"
        },
        {
            "category":"Shopping",
            "subcategory":"Crafts & Fabrics",
            "type":"Retail Goods"
        }
    ],
    "sg:phone":"+1 201 327 0722",
    "sg:postcode":"07446",
    "sg:province":"NJ",
    "sg:tags":[
        "florists'",
        "nurseries-plants",
        "supply",
        "tree",
        "nursery-wholesale",
        "florist",
        "supplies-wholesale",
        "grower",
        "manufacturer"
    ],
    "wof:name":"Skyline Greenhouses",
    "wof:placetype":"venue"
},
  "geometry": {"coordinates":[-74.142617,41.071784],"type":"Point"}
}