{
  "type": "Feature",
  "properties": {
    "addr:full":"30 Westville Ave Caldwell NJ 07006",
    "addr:housenumber":"30",
    "addr:postcode":"07006",
    "addr:street":"Westville Ave",
    "iso:country":"US",
    "sg:address":"30 Westville Ave",
    "sg:city":"Caldwell",
    "sg:classifiers":[
        {
            "category":"Health Services",
            "subcategory":"Doctor",
            "type":"Services"
        }
    ],
    "sg:phone":"+1 973 228 6866",
    "sg:postcode":"07006",
    "sg:province":"NJ",
    "sg:tags":[
        "dermatologist"
    ],
    "wof:name":"Gouterman Ira H MD",
    "wof:placetype":"venue"
},
  "geometry": {"coordinates":[-74.27780199999999,40.838699],"type":"Point"}
}