{
  "type": "Feature",
  "properties": {
    "addr:full":"378 Amboy Ave Woodbridge NJ 07095",
    "addr:housenumber":"378",
    "addr:postcode":"07095",
    "addr:street":"Amboy Ave",
    "iso:country":"US",
    "sg:address":"378 Amboy Ave",
    "sg:city":"Woodbridge",
    "sg:classifiers":[
        {
            "category":"Banks & Credit Unions",
            "subcategory":"Bank",
            "type":"Services"
        }
    ],
    "sg:phone":"+1   ",
    "sg:postcode":"07095",
    "sg:province":"NJ",
    "sg:tags":[
        "state",
        "commercial"
    ],
    "wof:name":"Fleet",
    "wof:placetype":"venue"
},
  "geometry": {"coordinates":[-74.282031,40.552855],"type":"Point"}
}