{
  "type": "Feature",
  "properties": {
    "iso:country":"US",
    "sg:address":"37 Sussex Rd",
    "sg:city":"Clifton",
    "sg:classifiers":[
        {
            "category":"Building & Trades",
            "subcategory":"Construction",
            "type":"Services"
        }
    ],
    "sg:phone":"+1 973 473 4088",
    "sg:postcode":"07012",
    "sg:province":"NJ",
    "sg:tags":[
        "house"
    ],
    "wof:name":"Flow-More",
    "wof:placetype":"venue"
},
  "geometry": {"coordinates":[-74.164542,40.844865],"type":"Point"}
}