{
  "type": "Feature",
  "properties": {
    "addr:full":"12 Roszel Rd Princeton NJ 08540",
    "addr:housenumber":"12",
    "addr:postcode":"08540",
    "addr:street":"Roszel Rd",
    "iso:country":"US",
    "sg:address":"12 Roszel Rd",
    "sg:city":"Princeton",
    "sg:classifiers":[
        {
            "category":"Organizations",
            "subcategory":"Professional Association",
            "type":"Services"
        }
    ],
    "sg:phone":"+1 609 514 1180",
    "sg:postcode":"08540",
    "sg:province":"NJ",
    "sg:website":"www.alz.org",
    "wof:name":"Alzheimer's Association",
    "wof:placetype":"venue"
},
  "geometry": {"coordinates":[-74.63752700000001,40.3214],"type":"Point"}
}