{
  "type": "Feature",
  "properties": {
    "addr:full":"19 Orange Pl West Orange NJ 07052",
    "addr:housenumber":"19",
    "addr:postcode":"07052",
    "addr:street":"Orange Pl",
    "iso:country":"US",
    "sg:address":"19 Orange Pl",
    "sg:city":"West Orange",
    "sg:classifiers":[
        {
            "category":"Arts & Performance",
            "subcategory":"Theater",
            "type":"Entertainment"
        }
    ],
    "sg:phone":"+1   ",
    "sg:postcode":"07052",
    "sg:province":"NJ",
    "sg:tags":[
        "music",
        "classical",
        "producer"
    ],
    "wof:name":"Classical Music Productions",
    "wof:placetype":"venue"
},
  "geometry": {"coordinates":[-74.231616,40.792721],"type":"Point"}
}