{
  "type": "Feature",
  "properties": {
    "addr:full":"40 Swartswood Rd Newton NJ 07860",
    "addr:housenumber":"40",
    "addr:postcode":"07860",
    "addr:street":"Swartswood Rd",
    "iso:country":"US",
    "sg:address":"40 Swartswood Rd",
    "sg:city":"Newton",
    "sg:classifiers":[
        {
            "category":"Real Estate",
            "subcategory":"Real Estate Operator",
            "type":"Services"
        }
    ],
    "sg:phone":"+1 973 383 6881",
    "sg:postcode":"07860",
    "sg:province":"NJ",
    "sg:tags":[
        "apartment"
    ],
    "wof:name":"Landmark West",
    "wof:placetype":"venue"
},
  "geometry": {"coordinates":[-74.760108,41.064206],"type":"Point"}
}