{
  "type": "Feature",
  "properties": {
    "addr:full":"28 Dutch Rd East Brunswick NJ 08816",
    "addr:housenumber":"28",
    "addr:postcode":"08816",
    "addr:street":"Dutch Rd",
    "iso:country":"US",
    "sg:address":"28 Dutch Rd",
    "sg:city":"East Brunswick",
    "sg:classifiers":[
        {
            "category":"Wholesale",
            "subcategory":"Durable Goods & Equipment",
            "type":"Manufacturing & Wholesale Goods"
        }
    ],
    "sg:phone":"+1 732 257 9010",
    "sg:postcode":"08816",
    "sg:province":"NJ",
    "sg:tags":[
        "representative",
        "manufacturer"
    ],
    "wof:name":"Allied Sales Inc",
    "wof:placetype":"venue"
},
  "geometry": {"coordinates":[-74.43211599999999,40.426167],"type":"Point"}
}