{
  "type": "Feature",
  "properties": {
    "addr:full":"US Hwy 46 & Ri NW Totowa NJ 07512",
    "addr:postcode":"07512",
    "addr:street":"Us Hwy 46 & Ri Nw",
    "iso:country":"US",
    "sg:address":"US Hwy 46 & Ri NW",
    "sg:city":"Totowa",
    "sg:classifiers":[
        {
            "category":"Shopping",
            "subcategory":"Music",
            "type":"Retail Goods"
        }
    ],
    "sg:phone":"+1 973 812 1220",
    "sg:postcode":"07512",
    "sg:province":"NJ",
    "sg:tags":[
        "dvd's"
    ],
    "wof:name":"Coconuts Music & Video",
    "wof:placetype":"venue"
},
  "geometry": {"coordinates":[-74.21410400000001,40.905998],"type":"Point"}
}