{
  "type": "Feature",
  "properties": {
    "addr:full":"79 Mainbridge Ln Willingboro NJ 08046",
    "addr:housenumber":"79",
    "addr:postcode":"08046",
    "addr:street":"Mainbridge Ln",
    "iso:country":"US",
    "sg:address":"79 Mainbridge Ln",
    "sg:city":"Willingboro",
    "sg:classifiers":[
        {
            "category":"Professional",
            "subcategory":"Lawyer & Legal Services",
            "type":"Services"
        }
    ],
    "sg:phone":"+1 609 877 5511",
    "sg:postcode":"08046",
    "sg:province":"NJ",
    "sg:tags":[
        "attorney"
    ],
    "wof:name":"Armstrong Michael Law Office",
    "wof:placetype":"venue"
},
  "geometry": {"coordinates":[-74.889503,40.032101],"type":"Point"}
}