{
  "type": "Feature",
  "properties": {
    "addr:full":"622 Boulevard Kenilworth NJ 07033",
    "addr:housenumber":"622",
    "addr:postcode":"07033",
    "addr:street":"Boulevard",
    "iso:country":"US",
    "sg:address":"622 Boulevard",
    "sg:city":"Kenilworth",
    "sg:classifiers":[
        {
            "category":"Health Services",
            "subcategory":"Doctor",
            "type":"Services"
        }
    ],
    "sg:phone":"+1 908 241 3181",
    "sg:postcode":"07033",
    "sg:province":"NJ",
    "sg:tags":[
        "dermatologist"
    ],
    "wof:name":"Pravda Douglas DO",
    "wof:placetype":"venue"
},
  "geometry": {"coordinates":[-74.287903,40.676701],"type":"Point"}
}