{
  "type": "Feature",
  "properties": {
    "iso:country":"US",
    "sg:address":"7 Evergreen Dr",
    "sg:city":"Ocean View",
    "sg:classifiers":[
        {
            "category":"Building & Trades",
            "subcategory":"Cleaning & Sanitation",
            "type":"Services"
        }
    ],
    "sg:phone":"+1 609 513 0612",
    "sg:postcode":"08230",
    "sg:province":"NJ",
    "sg:tags":[
        "butler",
        "maid"
    ],
    "wof:name":"Jet Cleaning",
    "wof:placetype":"venue"
},
  "geometry": {"coordinates":[-74.69162300000001,39.230151],"type":"Point"}
}