{
  "type": "Feature",
  "properties": {
    "addr:full":"2001 S 6th St Camden NJ 08104",
    "addr:housenumber":"2001",
    "addr:postcode":"08104",
    "addr:street":"S 6Th St",
    "iso:country":"US",
    "sg:address":"2001 S 6th St",
    "sg:city":"Camden",
    "sg:classifiers":[
        {
            "category":"Wholesale",
            "subcategory":"Poultry",
            "type":"Manufacturing & Wholesale Goods"
        }
    ],
    "sg:phone":"+1 856 963 3250",
    "sg:postcode":"08104",
    "sg:province":"NJ",
    "sg:tags":[
        "plant"
    ],
    "wof:name":"Jack Lambersky Poultry Co",
    "wof:placetype":"venue"
},
  "geometry": {"coordinates":[-75.11798899999999,39.918257],"type":"Point"}
}