{
  "type": "Feature",
  "properties": {
    "iso:country":"US",
    "sg:address":"124 Woodvale Rd",
    "sg:city":"Glen Rock",
    "sg:classifiers":[
        {
            "category":"Health Services",
            "subcategory":"Doctor",
            "type":"Services"
        }
    ],
    "sg:phone":"+1 201 445 0220",
    "sg:postcode":"07452",
    "sg:province":"NJ",
    "sg:tags":[
        "medical"
    ],
    "wof:name":"Meri Schachter MD",
    "wof:placetype":"venue"
},
  "geometry": {"coordinates":[-74.113305,40.952037],"type":"Point"}
}