{
  "type": "Feature",
  "properties": {
    "addr:full":"114 Central Ave Westfield NJ 07090",
    "addr:housenumber":"114",
    "addr:postcode":"07090",
    "addr:street":"Central Ave",
    "iso:country":"US",
    "sg:address":"114 Central Ave",
    "sg:city":"Westfield",
    "sg:classifiers":[
        {
            "category":"Real Estate",
            "subcategory":"Real Estate Agent",
            "type":"Services"
        }
    ],
    "sg:phone":"+1   ",
    "sg:postcode":"07090",
    "sg:province":"NJ",
    "wof:name":"Allen Chrone",
    "wof:placetype":"venue"
},
  "geometry": {"coordinates":[-74.347218,40.651858],"type":"Point"}
}