{
  "type": "Feature",
  "properties": {
    "iso:country":"US",
    "sg:address":"120 Albany St",
    "sg:city":"New Brunswick",
    "sg:classifiers":[
        {
            "category":"Professional",
            "subcategory":"Lawyer & Legal Services",
            "type":"Services"
        }
    ],
    "sg:phone":"+1 732 246 3822",
    "sg:postcode":"08901",
    "sg:province":"NJ",
    "sg:tags":[
        "attorney"
    ],
    "wof:name":"Nelson Mullins Riley",
    "wof:placetype":"venue"
},
  "geometry": {"coordinates":[-74.445162,40.496636],"type":"Point"}
}