{
  "type": "Feature",
  "properties": {
    "addr:full":"101 S Reeds Rd Absecon NJ 08205",
    "addr:housenumber":"101",
    "addr:postcode":"08205",
    "addr:street":"S Reeds Rd",
    "iso:country":"US",
    "sg:address":"101 S Reeds Rd",
    "sg:city":"Absecon",
    "sg:classifiers":[
        {
            "category":"Organizations",
            "subcategory":"Membership Organization",
            "type":"Services"
        }
    ],
    "sg:phone":"+1 609 652 1300",
    "sg:postcode":"08205",
    "sg:province":"NJ",
    "sg:tags":[
        "athletic"
    ],
    "wof:name":"Atlantic Cape Jr High School",
    "wof:placetype":"venue"
},
  "geometry": {"coordinates":[-74.51435499999999,39.485562],"type":"Point"}
}