{
  "type": "Feature",
  "properties": {
    "addr:full":"488 W Perry St Cape May NJ 08204",
    "addr:housenumber":"488",
    "addr:postcode":"08204",
    "addr:street":"W Perry St",
    "iso:country":"US",
    "sg:address":"488 W Perry St",
    "sg:city":"Cape May",
    "sg:classifiers":[
        {
            "category":"Building & Trades",
            "subcategory":"Construction",
            "type":"Services"
        }
    ],
    "sg:phone":"+1 609 884 4847",
    "sg:postcode":"08204",
    "sg:province":"NJ",
    "sg:tags":[
        "paving",
        "contractor"
    ],
    "wof:name":"Eastern Asphalt Maintenance",
    "wof:placetype":"venue"
},
  "geometry": {"coordinates":[-74.928755,38.934588],"type":"Point"}
}