{
  "type": "Feature",
  "properties": {
    "addr:full":"1120 Morris Ave Union NJ 07083",
    "addr:housenumber":"1120",
    "addr:postcode":"07083",
    "addr:street":"Morris Ave",
    "iso:country":"US",
    "sg:address":"1120 Morris Ave",
    "sg:city":"Union",
    "sg:classifiers":[
        {
            "category":"Professional",
            "subcategory":"Research",
            "type":"Services"
        }
    ],
    "sg:phone":"+1 908 810 0736",
    "sg:postcode":"07083",
    "sg:province":"NJ",
    "sg:tags":[
        "foundation",
        "philanthropic"
    ],
    "wof:name":"Pankarpathian Foundation",
    "wof:placetype":"venue"
},
  "geometry": {"coordinates":[-74.238035,40.684563],"type":"Point"}
}