{
  "type": "Feature",
  "properties": {
    "iso:country":"US",
    "sg:address":"48 Washington St",
    "sg:city":"Paterson",
    "sg:classifiers":[
        {
            "category":"Donuts",
            "subcategory":"None",
            "type":"Food & Drink"
        }
    ],
    "sg:phone":"+1 973 881 7100",
    "sg:postcode":"07501",
    "sg:province":"NJ",
    "wof:name":"Valenti's Bakeries Inc",
    "wof:placetype":"venue"
},
  "geometry": {"coordinates":[-74.171898,40.920399],"type":"Point"}
}