{
  "type": "Feature",
  "properties": {
    "iso:country":"US",
    "sg:address":"9 Queens Pass",
    "sg:city":"Colts Neck",
    "sg:classifiers":[
        {
            "category":"Professional",
            "subcategory":"Management & Consulting",
            "type":"Services"
        }
    ],
    "sg:phone":"+1   ",
    "sg:postcode":"07722",
    "sg:province":"NJ",
    "wof:name":"Call Center Marketing LLC",
    "wof:placetype":"venue"
},
  "geometry": {"coordinates":[-74.22166199999999,40.270771],"type":"Point"}
}