{
  "type": "Feature",
  "properties": {
    "addr:full":"536 Shields Ave Woodbury NJ 08096",
    "addr:housenumber":"536",
    "addr:postcode":"08096",
    "addr:street":"Shields Ave",
    "iso:country":"US",
    "sg:address":"536 Shields Ave",
    "sg:city":"Woodbury",
    "sg:classifiers":[
        {
            "category":"Professional",
            "subcategory":"Secretarial Services",
            "type":"Services"
        }
    ],
    "sg:phone":"+1 856 845 5580",
    "sg:postcode":"08096",
    "sg:province":"NJ",
    "sg:tags":[
        "reporting"
    ],
    "wof:name":"Shields Secretarial Servi",
    "wof:placetype":"venue"
},
  "geometry": {"coordinates":[-75.153713,39.847244],"type":"Point"}
}