{
  "type": "Feature",
  "properties": {
    "iso:country":"US",
    "sg:address":"4266 US Hwy 1",
    "sg:city":"Monmouth Jct",
    "sg:classifiers":[
        {
            "category":"Wholesale",
            "subcategory":"Chemicals & Plastics",
            "type":"Manufacturing & Wholesale Goods"
        }
    ],
    "sg:phone":"+1 732 438 0995",
    "sg:postcode":"08852",
    "sg:province":"NJ",
    "sg:website":"www.triventchemical.com",
    "wof:name":"Trivent Chemical Co",
    "wof:placetype":"venue"
},
  "geometry": {"coordinates":[-74.582724,40.377489],"type":"Point"}
}