{
  "type": "Feature",
  "properties": {
    "iso:country":"US",
    "sg:address":"11205 Long Beach Blvd",
    "sg:city":"Beach Haven",
    "sg:classifiers":[
        {
            "category":"Shopping",
            "subcategory":"Clothing, Apparel, & Fashions",
            "type":"Retail Goods"
        }
    ],
    "sg:phone":"+1   ",
    "sg:postcode":"08008",
    "sg:province":"NJ",
    "sg:tags":[
        "wear"
    ],
    "wof:name":"Sea Oats Ltd",
    "wof:placetype":"venue"
},
  "geometry": {"coordinates":[-74.216556,39.59527],"type":"Point"}
}