{
  "type": "Feature",
  "properties": {
    "iso:country":"US",
    "sg:address":"1813 State Rte 71",
    "sg:city":"Belmar",
    "sg:classifiers":[
        {
            "category":"Home & Garden",
            "subcategory":"Building Materials",
            "type":"Retail Goods"
        }
    ],
    "sg:phone":"+1 732 681 1200",
    "sg:postcode":"07719",
    "sg:province":"NJ",
    "sg:tags":[
        "plate",
        "window",
        "automotive",
        "install",
        "glass"
    ],
    "wof:name":"Atlantic Glass Company",
    "wof:placetype":"venue"
},
  "geometry": {"coordinates":[-74.033508,40.168883],"type":"Point"}
}