{
  "type": "Feature",
  "properties": {
    "iso:country":"US",
    "sg:address":"132 Beckwith Ave",
    "sg:city":"Paterson",
    "sg:classifiers":[
        {
            "category":"Professional",
            "subcategory":"Business Services",
            "type":"Services"
        }
    ],
    "sg:phone":"+1 973 279 2600",
    "sg:postcode":"07503",
    "sg:province":"NJ",
    "sg:tags":[
        "packaging"
    ],
    "wof:name":"Lightning Pack",
    "wof:placetype":"venue"
},
  "geometry": {"coordinates":[-74.161209,40.906478],"type":"Point"}
}