{
  "type": "Feature",
  "properties": {
    "iso:country":"US",
    "sg:address":"224 Leeward Rd",
    "sg:city":"Manahawkin",
    "sg:classifiers":[
        {
            "category":"Building & Trades",
            "subcategory":"Construction",
            "type":"Services"
        }
    ],
    "sg:phone":"+1 609 607 0514",
    "sg:postcode":"08050",
    "sg:province":"NJ",
    "sg:tags":[
        "hanging",
        "contractor"
    ],
    "wof:name":"Rematt Painting Co",
    "wof:placetype":"venue"
},
  "geometry": {"coordinates":[-74.296584,39.735894],"type":"Point"}
}