{
  "type": "Feature",
  "properties": {
    "addr:full":"513 Boulevard Kenilworth NJ 07033",
    "addr:housenumber":"513",
    "addr:postcode":"07033",
    "addr:street":"Boulevard",
    "iso:country":"US",
    "sg:address":"513 Boulevard",
    "sg:city":"Kenilworth",
    "sg:classifiers":[
        {
            "category":"Health Services",
            "subcategory":"Doctor",
            "type":"Services"
        }
    ],
    "sg:phone":"+1 908 276 6652",
    "sg:postcode":"07033",
    "sg:province":"NJ",
    "sg:tags":[
        "dentist"
    ],
    "wof:name":"Kenilworth Dental Associates",
    "wof:placetype":"venue"
},
  "geometry": {"coordinates":[-74.2916,40.6758],"type":"Point"}
}