{
  "type": "Feature",
  "properties": {
    "iso:country":"US",
    "sg:address":"505 Hamilton Ave",
    "sg:city":"Lumberton",
    "sg:classifiers":[
        {
            "category":"Professional",
            "subcategory":"Management & Consulting",
            "type":"Services"
        }
    ],
    "sg:phone":"+1   ",
    "sg:postcode":"08048",
    "sg:province":"NJ",
    "sg:tags":[
        "business"
    ],
    "wof:name":"Transactional Consulting",
    "wof:placetype":"venue"
},
  "geometry": {"coordinates":[-74.789074,39.974466],"type":"Point"}
}