{
  "type": "Feature",
  "properties": {
    "addr:full":"1114 State Rte 83 Cape May Court House NJ 08210",
    "addr:housenumber":"1114",
    "addr:postcode":"08210",
    "addr:street":"State Rte 83 Cape May",
    "iso:country":"US",
    "sg:address":"1114 State Rte 83",
    "sg:city":"Cape May Court House",
    "sg:classifiers":[
        {
            "category":"Arts & Performance",
            "subcategory":"Theater",
            "type":"Entertainment"
        }
    ],
    "sg:phone":"+1   ",
    "sg:postcode":"08210",
    "sg:province":"NJ",
    "sg:tags":[
        "group"
    ],
    "wof:name":"Clermont Sundevils",
    "wof:placetype":"venue"
},
  "geometry": {"coordinates":[-74.769458,39.157479],"type":"Point"}
}