{
  "type": "Feature",
  "properties": {
    "addr:full":"4 Bell Ln Burlington NJ 08016",
    "addr:housenumber":"4",
    "addr:postcode":"08016",
    "addr:street":"Bell Ln",
    "iso:country":"US",
    "sg:address":"4 Bell Ln",
    "sg:city":"Burlington",
    "sg:classifiers":[
        {
            "category":"Professional",
            "subcategory":"Employment Agencies",
            "type":"Services"
        }
    ],
    "sg:phone":"+1 609 386 0944",
    "sg:postcode":"08016",
    "sg:province":"NJ",
    "sg:tags":[
        "recruitment",
        "top",
        "placement",
        "talent",
        "hispanic"
    ],
    "wof:name":"Muchosjobscom",
    "wof:placetype":"venue"
},
  "geometry": {"coordinates":[-74.859189,40.044371],"type":"Point"}
}