{
  "type": "Feature",
  "properties": {
    "addr:full":"2110 Newark Ave Scotch Plains NJ 07076",
    "addr:housenumber":"2110",
    "addr:postcode":"07076",
    "addr:street":"Newark Ave",
    "iso:country":"US",
    "sg:address":"2110 Newark Ave",
    "sg:city":"Scotch Plains",
    "sg:classifiers":[
        {
            "category":"Professional",
            "subcategory":"Art Services",
            "type":"Services"
        }
    ],
    "sg:phone":"+1   ",
    "sg:postcode":"07076",
    "sg:province":"NJ",
    "sg:tags":[
        "commercial",
        "design"
    ],
    "wof:name":"Ablaze Communication Inc",
    "wof:placetype":"venue"
},
  "geometry": {"coordinates":[-74.36877200000001,40.640668],"type":"Point"}
}