{
  "type": "Feature",
  "properties": {
    "addr:full":"9 Lalique Dr Montville NJ 07045",
    "addr:housenumber":"9",
    "addr:postcode":"07045",
    "addr:street":"Lalique Dr",
    "iso:country":"US",
    "sg:address":"9 Lalique Dr",
    "sg:city":"Montville",
    "sg:classifiers":[
        {
            "category":"Education",
            "subcategory":"Vocational School",
            "type":"Public Place"
        }
    ],
    "sg:phone":"+1   ",
    "sg:postcode":"07045",
    "sg:province":"NJ",
    "sg:tags":[
        "processing",
        "datum"
    ],
    "wof:name":"Priority Computer Training",
    "wof:placetype":"venue"
},
  "geometry": {"coordinates":[-74.380988,40.907856],"type":"Point"}
}