{
  "type": "Feature",
  "properties": {
    "addr:full":"123 Chestnut St Roselle Park NJ 07204",
    "addr:housenumber":"123",
    "addr:postcode":"07204",
    "addr:street":"Chestnut St",
    "iso:country":"US",
    "sg:address":"123 Chestnut St",
    "sg:city":"Roselle Park",
    "sg:classifiers":[
        {
            "category":"Shopping",
            "subcategory":"Gifts & Souvenirs",
            "type":"Retail Goods"
        }
    ],
    "sg:phone":"+1 908 241 6542",
    "sg:postcode":"07204",
    "sg:province":"NJ",
    "sg:tags":[
        "party",
        "supply"
    ],
    "wof:name":"Love Letters Inc",
    "wof:placetype":"venue"
},
  "geometry": {"coordinates":[-74.264267,40.663235],"type":"Point"}
}