{
  "type": "Feature",
  "properties": {
    "iso:country":"US",
    "sg:address":"211 Essex St",
    "sg:city":"Hackensack",
    "sg:classifiers":[
        {
            "category":"Health Services",
            "subcategory":"Doctor",
            "type":"Services"
        }
    ],
    "sg:phone":"+1 201 488 1515",
    "sg:postcode":"07601",
    "sg:province":"NJ",
    "sg:tags":[
        "physician",
        "surgeon"
    ],
    "sg:website":"www.hackensackneurologygroup.com",
    "wof:name":"Neurological Professional Asso",
    "wof:placetype":"venue"
},
  "geometry": {"coordinates":[-74.054304,40.880859],"type":"Point"}
}