{
  "type": "Feature",
  "properties": {
    "addr:full":"21 E Atlantic Blvd Ocean City NJ 08226",
    "addr:housenumber":"21",
    "addr:postcode":"08226",
    "addr:street":"E Atlantic Blvd",
    "iso:country":"US",
    "sg:address":"21 E Atlantic Blvd",
    "sg:city":"Ocean City",
    "sg:classifiers":[
        {
            "category":"Professional",
            "subcategory":"Computer Services",
            "type":"Services"
        }
    ],
    "sg:phone":"+1 609 398 1275",
    "sg:postcode":"08226",
    "sg:province":"NJ",
    "sg:tags":[
        "consulting",
        "management",
        "datum"
    ],
    "wof:name":"Internet Development Group LLC",
    "wof:placetype":"venue"
},
  "geometry": {"coordinates":[-74.55981300000001,39.286612],"type":"Point"}
}