{
  "type": "Feature",
  "properties": {
    "iso:country":"US",
    "sg:address":"601 N Olden Ave",
    "sg:city":"Trenton",
    "sg:classifiers":[
        {
            "category":"Building & Trades",
            "subcategory":"Plumbing",
            "type":"Services"
        }
    ],
    "sg:phone":"+1 609 396 3665",
    "sg:postcode":"08638",
    "sg:province":"NJ",
    "sg:tags":[
        "plumber",
        "contractor"
    ],
    "wof:name":"Ted's Plumbing & Heating",
    "wof:placetype":"venue"
},
  "geometry": {"coordinates":[-74.745361,40.233292],"type":"Point"}
}