{
  "type": "Feature",
  "properties": {
    "addr:full":"22 E Railway Ave Paterson NJ 07503",
    "addr:housenumber":"22",
    "addr:postcode":"07503",
    "addr:street":"E Railway Ave",
    "iso:country":"US",
    "sg:address":"22 E Railway Ave",
    "sg:city":"Paterson",
    "sg:classifiers":[
        {
            "category":"Manufacturing",
            "subcategory":"Signs",
            "type":"Manufacturing & Wholesale Goods"
        }
    ],
    "sg:phone":"+1 973 279 4101",
    "sg:postcode":"07503",
    "sg:province":"NJ",
    "sg:tags":[
        "specialty",
        "mfg"
    ],
    "wof:name":"Rod Enterprises Signs By Fuzzy",
    "wof:placetype":"venue"
},
  "geometry": {"coordinates":[-74.159035,40.901155],"type":"Point"}
}