{
  "type": "Feature",
  "properties": {
    "iso:country":"US",
    "sg:address":"11 School St",
    "sg:city":"Clinton",
    "sg:classifiers":[
        {
            "category":"Real Estate",
            "subcategory":"Real Estate Operator",
            "type":"Services"
        }
    ],
    "sg:phone":"+1   ",
    "sg:postcode":"08809",
    "sg:province":"NJ",
    "sg:tags":[
        "building",
        "apartment"
    ],
    "wof:name":"Clinton Garden Apartments",
    "wof:placetype":"venue"
},
  "geometry": {"coordinates":[-74.907426,40.635539],"type":"Point"}
}