{
  "type": "Feature",
  "properties": {
    "iso:country":"US",
    "sg:address":"4000 Long Beach Blvd",
    "sg:city":"Long Beach Twp",
    "sg:classifiers":[
        {
            "category":"Home & Garden",
            "subcategory":"Carpets & Floor Coverings",
            "type":"Retail Goods"
        }
    ],
    "sg:phone":"+1 609 361 7476",
    "sg:postcode":"08008",
    "sg:province":"NJ",
    "sg:tags":[
        "dealer",
        "rug"
    ],
    "wof:name":"Designs By The Bay",
    "wof:placetype":"venue"
},
  "geometry": {"coordinates":[-74.189454,39.631898],"type":"Point"}
}