{
  "type": "Feature",
  "properties": {
    "addr:full":"329 Pedricktown Woodstown Rd Pedricktown NJ 08067",
    "addr:housenumber":"329",
    "addr:postcode":"08067",
    "addr:street":"Pedricktown Woodstown Rd",
    "iso:country":"US",
    "sg:address":"329 Pedricktown Woodstown Rd",
    "sg:city":"Pedricktown",
    "sg:classifiers":[
        {
            "category":"Manufacturing",
            "subcategory":"Metals",
            "type":"Manufacturing & Wholesale Goods"
        }
    ],
    "sg:phone":"+1 856 299 2462",
    "sg:postcode":"08067",
    "sg:province":"NJ",
    "wof:name":"Superior Mold Polishing",
    "wof:placetype":"venue"
},
  "geometry": {"coordinates":[-75.371003,39.70839],"type":"Point"}
}