{
  "type": "Feature",
  "properties": {
    "iso:country":"US",
    "sg:address":"259 Godwin Ave",
    "sg:city":"Midland Park",
    "sg:classifiers":[
        {
            "category":"Shopping",
            "subcategory":"Musical Instruments",
            "type":"Retail Goods"
        }
    ],
    "sg:phone":"+1   ",
    "sg:postcode":"07432",
    "sg:province":"NJ",
    "sg:tags":[
        "repair",
        "school",
        "music"
    ],
    "wof:name":"Ackermans Music Center",
    "wof:placetype":"venue"
},
  "geometry": {"coordinates":[-74.141595,40.990908],"type":"Point"}
}