{
  "type": "Feature",
  "properties": {
    "addr:full":"4716 Broadway Union City NJ 07087",
    "addr:housenumber":"4716",
    "addr:postcode":"07087",
    "addr:street":"Broadway",
    "iso:country":"US",
    "sg:address":"4716 Broadway",
    "sg:city":"Union City",
    "sg:classifiers":[
        {
            "category":"Banks & Credit Unions",
            "subcategory":"Bank",
            "type":"Services"
        }
    ],
    "sg:phone":"+1 201 348 2540",
    "sg:postcode":"07087",
    "sg:province":"NJ",
    "wof:name":"Hudson United Bank",
    "wof:placetype":"venue"
},
  "geometry": {"coordinates":[-74.01680899999999,40.779177],"type":"Point"}
}