{
  "type": "Feature",
  "properties": {
    "iso:country":"US",
    "sg:address":"1094 Jackson Ave",
    "sg:city":"Franklinville",
    "sg:classifiers":[
        {
            "category":"Shopping",
            "type":"Retail Goods"
        }
    ],
    "sg:phone":"+1 856 881 9034",
    "sg:postcode":"08322",
    "sg:province":"NJ",
    "sg:tags":[
        "collectible"
    ],
    "wof:name":"Mike's Nascar Collectibles",
    "wof:placetype":"venue"
},
  "geometry": {"coordinates":[-75.064718,39.651002],"type":"Point"}
}