{
  "type": "Feature",
  "properties": {
    "addr:full":"5 Peterson Ct Perth Amboy NJ 08861",
    "addr:housenumber":"5",
    "addr:postcode":"08861",
    "addr:street":"Peterson Ct",
    "iso:country":"US",
    "sg:address":"5 Peterson Ct",
    "sg:city":"Perth Amboy",
    "sg:classifiers":[
        {
            "category":"Professional",
            "subcategory":"Management & Consulting",
            "type":"Services"
        }
    ],
    "sg:phone":"+1   ",
    "sg:postcode":"08861",
    "sg:province":"NJ",
    "wof:name":"Disease Management",
    "wof:placetype":"venue"
},
  "geometry": {"coordinates":[-74.259304,40.521255],"type":"Point"}
}