{
  "type": "Feature",
  "properties": {
    "addr:full":"809 State Rte 70 Brick NJ 08724",
    "addr:housenumber":"809",
    "addr:postcode":"08724",
    "addr:street":"State Rte 70",
    "iso:country":"US",
    "sg:address":"809 State Rte 70",
    "sg:city":"Brick",
    "sg:classifiers":[
        {
            "category":"Recreation",
            "subcategory":"Marina",
            "type":"Entertainment"
        }
    ],
    "sg:phone":"+1 732 477 0701",
    "sg:postcode":"08724",
    "sg:province":"NJ",
    "sg:tags":[
        "operation"
    ],
    "wof:name":"Lightining Jacks Marina Inc",
    "wof:placetype":"venue"
},
  "geometry": {"coordinates":[-74.131716,40.067432],"type":"Point"}
}