{
  "type": "Feature",
  "properties": {
    "addr:full":"520 Atlantic Ave Atlantic City NJ 08401",
    "addr:housenumber":"520",
    "addr:postcode":"08401",
    "addr:street":"Atlantic Ave",
    "iso:country":"US",
    "sg:address":"520 Atlantic Ave",
    "sg:city":"Atlantic City",
    "sg:classifiers":[
        {
            "category":"Shopping",
            "subcategory":"Gifts & Souvenirs",
            "type":"Retail Goods"
        }
    ],
    "sg:phone":"+1   ",
    "sg:postcode":"08401",
    "sg:province":"NJ",
    "wof:name":"American Today Is You",
    "wof:placetype":"venue"
},
  "geometry": {"coordinates":[-74.41795500000001,39.366121],"type":"Point"}
}