{
  "type": "Feature",
  "properties": {
    "iso:country":"US",
    "sg:address":"316 Clifton Ave",
    "sg:city":"Bayville",
    "sg:classifiers":[
        {
            "category":"Wholesale",
            "subcategory":"Seafood",
            "type":"Manufacturing & Wholesale Goods"
        }
    ],
    "sg:phone":"+1 732 269 5166",
    "sg:postcode":"08721",
    "sg:province":"NJ",
    "wof:name":"Anthony Seafood Wholesale Inc",
    "wof:placetype":"venue"
},
  "geometry": {"coordinates":[-74.179468,39.901228],"type":"Point"}
}