{
  "type": "Feature",
  "properties": {
    "addr:full":"116 Calderwood Ln Mount Laurel NJ 08054",
    "addr:housenumber":"116",
    "addr:postcode":"08054",
    "addr:street":"Calderwood Ln",
    "iso:country":"US",
    "sg:address":"116 Calderwood Ln",
    "sg:city":"Mount Laurel",
    "sg:classifiers":[
        {
            "category":"Manufacturing",
            "subcategory":"Apparel",
            "type":"Manufacturing & Wholesale Goods"
        }
    ],
    "sg:phone":"+1 856 222 9423",
    "sg:postcode":"08054",
    "sg:province":"NJ",
    "sg:tags":[
        "mfg"
    ],
    "wof:name":"Top It Off",
    "wof:placetype":"venue"
},
  "geometry": {"coordinates":[-74.871098,39.96042],"type":"Point"}
}