{
  "type": "Feature",
  "properties": {
    "addr:full":"251 Main St Hackensack NJ 07601",
    "addr:housenumber":"251",
    "addr:postcode":"07601",
    "addr:street":"Main St",
    "iso:country":"US",
    "sg:address":"251 Main St",
    "sg:city":"Hackensack",
    "sg:classifiers":[
        {
            "category":"Shopping",
            "subcategory":"Photographic Equipment",
            "type":"Retail Goods"
        }
    ],
    "sg:phone":"+1 201 343 4180",
    "sg:postcode":"07601",
    "sg:province":"NJ",
    "sg:tags":[
        "supply"
    ],
    "wof:name":"Apollo Camera Inc",
    "wof:placetype":"venue"
},
  "geometry": {"coordinates":[-74.041377,40.886897],"type":"Point"}
}