{
  "type": "Feature",
  "properties": {
    "iso:country":"US",
    "sg:address":"241 Main St",
    "sg:city":"Hackensack",
    "sg:classifiers":[
        {
            "category":"Personal",
            "subcategory":"Beauty Salon",
            "type":"Services"
        }
    ],
    "sg:phone":"+1 201 996 9494",
    "sg:postcode":"07601",
    "sg:province":"NJ",
    "sg:tags":[
        "treatment",
        "skin"
    ],
    "wof:name":"Topaz Skin Care",
    "wof:placetype":"venue"
},
  "geometry": {"coordinates":[-74.041254,40.887229],"type":"Point"}
}