{
  "type": "Feature",
  "properties": {
    "iso:country":"US",
    "sg:address":"430 Madison Ave",
    "sg:city":"New Milford",
    "sg:classifiers":[
        {
            "category":"Retail",
            "subcategory":"Auto Repair",
            "type":"Services"
        }
    ],
    "sg:phone":"+1 201 265 2462",
    "sg:postcode":"07646",
    "sg:province":"NJ",
    "sg:tags":[
        "repairing",
        "automobile",
        "automotive",
        "general"
    ],
    "wof:name":"Jay's Car Care",
    "wof:placetype":"venue"
},
  "geometry": {"coordinates":[-74.01070900000001,40.940118],"type":"Point"}
}