{
  "type": "Feature",
  "properties": {
    "iso:country":"US",
    "sg:address":"24 Barbour Ave",
    "sg:city":"Passaic",
    "sg:classifiers":[
        {
            "category":"Restaurant",
            "type":"Food & Drink"
        }
    ],
    "sg:phone":"+1 973 365 0454",
    "sg:postcode":"07055",
    "sg:province":"NJ",
    "sg:tags":[
        "pizza"
    ],
    "wof:name":"Little Caesars Pizza",
    "wof:placetype":"venue"
},
  "geometry": {"coordinates":[-74.120497,40.874546],"type":"Point"}
}