{
  "type": "Feature",
  "properties": {
    "addr:full":"1875 Wynnewood Dr Vineland NJ 08361",
    "addr:housenumber":"1875",
    "addr:postcode":"08361",
    "addr:street":"Wynnewood Dr",
    "iso:country":"US",
    "sg:address":"1875 Wynnewood Dr",
    "sg:city":"Vineland",
    "sg:classifiers":[
        {
            "category":"Professional",
            "subcategory":"Lawyer & Legal Services",
            "type":"Services"
        }
    ],
    "sg:phone":"+1 856 691 2282",
    "sg:postcode":"08361",
    "sg:province":"NJ",
    "sg:tags":[
        "attorney"
    ],
    "wof:name":"Farnoly & Barse",
    "wof:placetype":"venue"
},
  "geometry": {"coordinates":[-74.972414,39.455947],"type":"Point"}
}