{
  "type": "Feature",
  "properties": {
    "addr:full":"55 Main St Millburn NJ 07041",
    "addr:housenumber":"55",
    "addr:postcode":"07041",
    "addr:street":"Main St",
    "iso:country":"US",
    "sg:address":"55 Main St",
    "sg:city":"Millburn",
    "sg:classifiers":[
        {
            "category":"Shopping",
            "subcategory":"Jewelry",
            "type":"Retail Goods"
        },
        {
            "category":"Shopping",
            "subcategory":"Antiques",
            "type":"Retail Goods"
        }
    ],
    "sg:phone":"+1 973 467 1007",
    "sg:postcode":"07041",
    "sg:province":"NJ",
    "wof:name":"Remolina George Designs",
    "wof:placetype":"venue"
},
  "geometry": {"coordinates":[-74.306999,40.723701],"type":"Point"}
}