{
  "type": "Feature",
  "properties": {
    "addr:full":"412 Walnut Street Rd Salem NJ 08079",
    "addr:housenumber":"412",
    "addr:postcode":"08079",
    "addr:street":"Walnut Street Rd",
    "iso:country":"US",
    "sg:address":"412 Walnut Street Rd",
    "sg:city":"Salem",
    "sg:classifiers":[
        {
            "category":"Retail",
            "subcategory":"Laundry & Dry Cleaning",
            "type":"Services"
        }
    ],
    "sg:phone":"+1   ",
    "sg:postcode":"08079",
    "sg:province":"NJ",
    "wof:name":"Carpet Connection",
    "wof:placetype":"venue"
},
  "geometry": {"coordinates":[-75.477012,39.538511],"type":"Point"}
}