{
  "type": "Feature",
  "properties": {
    "iso:country":"US",
    "sg:address":"30 Ryan Rd",
    "sg:city":"Englishtown",
    "sg:classifiers":[
        {
            "category":"Shopping",
            "subcategory":"Clothing, Apparel, & Fashions",
            "type":"Retail Goods"
        }
    ],
    "sg:phone":"+1 732 780 3754",
    "sg:postcode":"07726",
    "sg:province":"NJ",
    "sg:tags":[
        "salvage",
        "surplus",
        "merchandise"
    ],
    "wof:name":"Ryan Enterprises Inc",
    "wof:placetype":"venue"
},
  "geometry": {"coordinates":[-74.29701799999999,40.29378],"type":"Point"}
}