{
  "type": "Feature",
  "properties": {
    "addr:full":"386 Circle Dr Wyckoff NJ 07481",
    "addr:housenumber":"386",
    "addr:postcode":"07481",
    "addr:street":"Circle Dr",
    "iso:country":"US",
    "sg:address":"386 Circle Dr",
    "sg:city":"Wyckoff",
    "sg:classifiers":[
        {
            "category":"Building & Trades",
            "subcategory":"Plumbing",
            "type":"Services"
        }
    ],
    "sg:phone":"+1 201 652 8167",
    "sg:postcode":"07481",
    "sg:province":"NJ",
    "sg:tags":[
        "plumbing",
        "contractor"
    ],
    "wof:name":"James P Scanlon",
    "wof:placetype":"venue"
},
  "geometry": {"coordinates":[-74.15403499999999,40.984809],"type":"Point"}
}