{
  "type": "Feature",
  "properties": {
    "iso:country":"US",
    "sg:address":"33 Spring Lake Gardens Ct",
    "sg:city":"Spring Lake",
    "sg:classifiers":[
        {
            "category":"Professional",
            "subcategory":"Detective & Security Services",
            "type":"Services"
        }
    ],
    "sg:phone":"+1   ",
    "sg:postcode":"07762",
    "sg:province":"NJ",
    "sg:tags":[
        "investigator"
    ],
    "wof:name":"James L Lott",
    "wof:placetype":"venue"
},
  "geometry": {"coordinates":[-74.052026,40.152482],"type":"Point"}
}