{
  "type": "Feature",
  "properties": {
    "iso:country":"US",
    "sg:address":"67 2nd Ave",
    "sg:city":"Roebling",
    "sg:classifiers":[
        {
            "category":"Professional",
            "subcategory":"Advertising",
            "type":"Services"
        }
    ],
    "sg:phone":"+1 609 499 8899",
    "sg:postcode":"08554",
    "sg:province":"NJ",
    "sg:tags":[
        "shop",
        "letter"
    ],
    "wof:name":"FIREDIX.COM",
    "wof:placetype":"venue"
},
  "geometry": {"coordinates":[-74.773628,40.119774],"type":"Point"}
}