{
  "type": "Feature",
  "properties": {
    "iso:country":"US",
    "sg:address":"80 New Freedom Rd",
    "sg:city":"Medford",
    "sg:classifiers":[
        {
            "category":"Building & Trades",
            "subcategory":"Construction",
            "type":"Services"
        }
    ],
    "sg:phone":"+1 609 914 0444",
    "sg:postcode":"08055",
    "sg:province":"NJ",
    "sg:tags":[
        "paving",
        "contractor"
    ],
    "wof:name":"Christy Construction Inc",
    "wof:placetype":"venue"
},
  "geometry": {"coordinates":[-74.789682,39.907371],"type":"Point"}
}