{
  "type": "Feature",
  "properties": {
    "addr:full":"680 High St Burlington NJ 08016",
    "addr:housenumber":"680",
    "addr:postcode":"08016",
    "addr:street":"High St",
    "iso:country":"US",
    "sg:address":"680 High St",
    "sg:city":"Burlington",
    "sg:classifiers":[
        {
            "category":"Building & Trades",
            "subcategory":"Locksmith",
            "type":"Services"
        }
    ],
    "sg:phone":"+1 609 456 0508",
    "sg:postcode":"08016",
    "sg:province":"NJ",
    "sg:tags":[
        "key"
    ],
    "wof:name":"24 Hour Emergency Locksmith",
    "wof:placetype":"venue"
},
  "geometry": {"coordinates":[-74.85467199999999,40.069534],"type":"Point"}
}