{
  "type": "Feature",
  "properties": {
    "addr:full":"311 Roberts Rd Toms River NJ 08755",
    "addr:housenumber":"311",
    "addr:postcode":"08755",
    "addr:street":"Roberts Rd",
    "iso:country":"US",
    "sg:address":"311 Roberts Rd",
    "sg:city":"Toms River",
    "sg:classifiers":[
        {
            "category":"Wholesale",
            "subcategory":"Vending Machines",
            "type":"Manufacturing & Wholesale Goods"
        }
    ],
    "sg:phone":"+1   ",
    "sg:postcode":"08755",
    "sg:province":"NJ",
    "sg:tags":[
        "operator"
    ],
    "wof:name":"101 Vending & Amusements",
    "wof:placetype":"venue"
},
  "geometry": {"coordinates":[-74.22741600000001,40.039998],"type":"Point"}
}