{
  "type": "Feature",
  "properties": {
    "addr:full":"300 Craig Rd Manalapan NJ 07726",
    "addr:housenumber":"300",
    "addr:postcode":"07726",
    "addr:street":"Craig Rd",
    "iso:country":"US",
    "sg:address":"300 Craig Rd",
    "sg:city":"Manalapan",
    "sg:classifiers":[
        {
            "category":"Communications",
            "subcategory":"Film & Video Production",
            "type":"Services"
        }
    ],
    "sg:phone":"+1 732 780 2599",
    "sg:postcode":"07726",
    "sg:province":"NJ",
    "sg:tags":[
        "audio"
    ],
    "wof:name":"Epic Video Productions",
    "wof:placetype":"venue"
},
  "geometry": {"coordinates":[-74.298475,40.286121],"type":"Point"}
}