{
  "type": "Feature",
  "properties": {
    "iso:country":"US",
    "sg:address":"268 Main St",
    "sg:city":"Butler",
    "sg:classifiers":[
        {
            "category":"Building & Trades",
            "subcategory":"Cleaning & Sanitation",
            "type":"Services"
        }
    ],
    "sg:phone":"+1 973 283 2221",
    "sg:postcode":"07405",
    "sg:province":"NJ",
    "sg:tags":[
        "ventilating",
        "system"
    ],
    "wof:name":"Clean Air Technologies",
    "wof:placetype":"venue"
},
  "geometry": {"coordinates":[-74.342111,41.004449],"type":"Point"}
}