{
  "type": "Feature",
  "properties": {
    "iso:country":"US",
    "sg:address":"11 State St",
    "sg:city":"Hackensack",
    "sg:classifiers":[
        {
            "category":"Professional",
            "subcategory":"Lawyer & Legal Services",
            "type":"Services"
        }
    ],
    "sg:phone":"+1 201 343 2229",
    "sg:postcode":"07601",
    "sg:province":"NJ",
    "sg:tags":[
        "attorney"
    ],
    "wof:name":"Goldstein Ballen O'Rourke",
    "wof:placetype":"venue"
},
  "geometry": {"coordinates":[-74.04727,40.87879],"type":"Point"}
}