{
  "type": "Feature",
  "properties": {
    "addr:full":"90 W 55th St Ocean City NJ 08226",
    "addr:housenumber":"90",
    "addr:postcode":"08226",
    "addr:street":"W 55Th St",
    "iso:country":"US",
    "sg:address":"90 W 55th St",
    "sg:city":"Ocean City",
    "sg:classifiers":[
        {
            "category":"Restaurant",
            "type":"Food & Drink"
        }
    ],
    "sg:phone":"+1 609 391 9292",
    "sg:postcode":"08226",
    "sg:province":"NJ",
    "wof:name":"55th Street Diner",
    "wof:placetype":"venue"
},
  "geometry": {"coordinates":[-74.639374,39.226823],"type":"Point"}
}