{
  "type": "Feature",
  "properties": {
    "addr:full":"953 Frelinghuysen Ave Newark NJ 07114",
    "addr:housenumber":"953",
    "addr:postcode":"07114",
    "addr:street":"Frelinghuysen Ave",
    "iso:country":"US",
    "sg:address":"953 Frelinghuysen Ave",
    "sg:city":"Newark",
    "sg:classifiers":[
        {
            "category":"Shopping",
            "subcategory":"Pharmacy",
            "type":"Retail Goods"
        }
    ],
    "sg:phone":"+1 973 824 2627",
    "sg:postcode":"07114",
    "sg:province":"NJ",
    "wof:name":"Freedom Pharmacy Inc",
    "wof:placetype":"venue"
},
  "geometry": {"coordinates":[-74.203284,40.689419],"type":"Point"}
}