{
  "type": "Feature",
  "properties": {
    "addr:full":"63 Lacey Rd Lakehurst NJ 08759",
    "addr:housenumber":"63",
    "addr:postcode":"08759",
    "addr:street":"Lacey Rd",
    "iso:country":"US",
    "sg:address":"63 Lacey Rd",
    "sg:city":"Lakehurst",
    "sg:classifiers":[
        {
            "category":"Health Services",
            "subcategory":"Doctor",
            "type":"Services"
        }
    ],
    "sg:phone":"+1 732 849 1051",
    "sg:postcode":"08759",
    "sg:province":"NJ",
    "sg:tags":[
        "physician",
        "medical",
        "surgeon"
    ],
    "wof:name":"James F Clyde MD",
    "wof:placetype":"venue"
},
  "geometry": {"coordinates":[-74.36491599999999,39.947635],"type":"Point"}
}