{
  "type": "Feature",
  "properties": {
    "addr:full":"225 State Rte 10 Succasunna NJ 07876",
    "addr:housenumber":"225",
    "addr:postcode":"07876",
    "addr:street":"State Rte 10",
    "iso:country":"US",
    "sg:address":"225 State Rte 10",
    "sg:city":"Succasunna",
    "sg:classifiers":[
        {
            "category":"Insurance",
            "subcategory":"Insurance Agent",
            "type":"Services"
        }
    ],
    "sg:phone":"+1 973 598 8801",
    "sg:postcode":"07876",
    "sg:province":"NJ",
    "wof:name":"Mc Cormack & Flynn",
    "wof:placetype":"venue"
},
  "geometry": {"coordinates":[-74.642034,40.869411],"type":"Point"}
}