{
  "type": "Feature",
  "properties": {
    "addr:full":"810 Fairacres Ave Westfield NJ 07090",
    "addr:housenumber":"810",
    "addr:postcode":"07090",
    "addr:street":"Fairacres Ave",
    "iso:country":"US",
    "sg:address":"810 Fairacres Ave",
    "sg:city":"Westfield",
    "sg:classifiers":[
        {
            "category":"Professional",
            "subcategory":"Business Services",
            "type":"Services"
        }
    ],
    "sg:phone":"+1   ",
    "sg:postcode":"07090",
    "sg:province":"NJ",
    "wof:name":"David S Jaslow Assoc",
    "wof:placetype":"venue"
},
  "geometry": {"coordinates":[-74.334225,40.661873],"type":"Point"}
}