{
  "type": "Feature",
  "properties": {
    "addr:full":"1075 Cranbury South River Rd Jamesburg NJ 08831",
    "addr:housenumber":"1075",
    "addr:postcode":"08831",
    "addr:street":"Cranbury South River Rd",
    "iso:country":"US",
    "sg:address":"1075 Cranbury South River Rd",
    "sg:city":"Jamesburg",
    "sg:classifiers":[
        {
            "category":"Professional",
            "subcategory":"Business Services",
            "type":"Services"
        }
    ],
    "sg:phone":"+1 609 860 5239",
    "sg:postcode":"08831",
    "sg:province":"NJ",
    "sg:tags":[
        "broker"
    ],
    "wof:name":"Southland Corp",
    "wof:placetype":"venue"
},
  "geometry": {"coordinates":[-74.47120200000001,40.357498],"type":"Point"}
}