{
  "type": "Feature",
  "properties": {
    "iso:country":"US",
    "sg:address":"11 Mc Donald Rd",
    "sg:city":"Marlboro",
    "sg:classifiers":[
        {
            "category":"Building & Trades",
            "subcategory":"Construction",
            "type":"Services"
        }
    ],
    "sg:phone":"+1 732 536 1414",
    "sg:postcode":"07746",
    "sg:province":"NJ",
    "sg:tags":[
        "control",
        "industrial",
        "door",
        "enclosure",
        "noise"
    ],
    "wof:name":"Robert S Kaiser Industrials",
    "wof:placetype":"venue"
},
  "geometry": {"coordinates":[-74.257392,40.314588],"type":"Point"}
}