{
  "type": "Feature",
  "properties": {
    "addr:full":"65 Lincoln Ave Florham Park NJ 07932",
    "addr:housenumber":"65",
    "addr:postcode":"07932",
    "addr:street":"Lincoln Ave",
    "iso:country":"US",
    "sg:address":"65 Lincoln Ave",
    "sg:city":"Florham Park",
    "sg:classifiers":[
        {
            "category":"Utilities",
            "subcategory":"Water",
            "type":"Services"
        }
    ],
    "sg:phone":"+1 973 377 7585",
    "sg:postcode":"07932",
    "sg:province":"NJ",
    "sg:tags":[
        "supply"
    ],
    "wof:name":"Whitney Lake Water Co Inc",
    "wof:placetype":"venue"
},
  "geometry": {"coordinates":[-74.385879,40.774915],"type":"Point"}
}