{
  "type": "Feature",
  "properties": {
    "addr:full":"1 Suburbia Ter Jersey City NJ 07305",
    "addr:housenumber":"1",
    "addr:postcode":"07305",
    "addr:street":"Suburbia Ter",
    "iso:country":"US",
    "sg:address":"1 Suburbia Ter",
    "sg:city":"Jersey City",
    "sg:classifiers":[
        {
            "category":"Shopping",
            "subcategory":"Catalog Store",
            "type":"Retail Goods"
        }
    ],
    "sg:phone":"+1 201 985 0953",
    "sg:postcode":"07305",
    "sg:province":"NJ",
    "sg:tags":[
        "mail",
        "order"
    ],
    "wof:name":"Inspirationals",
    "wof:placetype":"venue"
},
  "geometry": {"coordinates":[-74.100578,40.703015],"type":"Point"}
}