{
  "type": "Feature",
  "properties": {
    "iso:country":"US",
    "sg:address":"200 State Rte 73",
    "sg:city":"Berlin",
    "sg:classifiers":[
        {
            "category":"Shopping",
            "subcategory":"Clothing, Apparel, & Fashions",
            "type":"Retail Goods"
        }
    ],
    "sg:phone":"+1 856 768 8350",
    "sg:postcode":"08009",
    "sg:province":"NJ",
    "sg:tags":[
        "western"
    ],
    "wof:name":"Western Atm Inc",
    "wof:placetype":"venue"
},
  "geometry": {"coordinates":[-74.92352700000001,39.795443],"type":"Point"}
}