{
  "type": "Feature",
  "properties": {
    "addr:full":"1355 State Rt 23 Sussex NJ 07461",
    "addr:housenumber":"1355",
    "addr:postcode":"07461",
    "addr:street":"State Rt 23",
    "iso:country":"US",
    "sg:address":"1355 State Rt 23",
    "sg:city":"Sussex",
    "sg:classifiers":[
        {
            "category":"Building & Trades",
            "subcategory":"Landscaping Services",
            "type":"Services"
        }
    ],
    "sg:phone":"+1 973 702 8380",
    "sg:postcode":"07461",
    "sg:province":"NJ",
    "sg:tags":[
        "landscape",
        "contractor"
    ],
    "wof:name":"Advanced Landscaping",
    "wof:placetype":"venue"
},
  "geometry": {"coordinates":[-74.664193,41.301764],"type":"Point"}
}