{
  "type": "Feature",
  "properties": {
    "addr:full":"186 Wykertown Rd Branchville NJ 07826",
    "addr:housenumber":"186",
    "addr:postcode":"07826",
    "addr:street":"Wykertown Rd",
    "iso:country":"US",
    "sg:address":"186 Wykertown Rd",
    "sg:city":"Branchville",
    "sg:classifiers":[
        {
            "category":"Building & Trades",
            "subcategory":"Construction",
            "type":"Services"
        }
    ],
    "sg:phone":"+1 973 875 2622",
    "sg:postcode":"07826",
    "sg:province":"NJ",
    "sg:tags":[
        "masonry",
        "contractor"
    ],
    "wof:name":"Kieffer Art Mason Contractor",
    "wof:placetype":"venue"
},
  "geometry": {"coordinates":[-74.70159700000001,41.178941],"type":"Point"}
}