{
  "type": "Feature",
  "properties": {
    "addr:full":"51 Watchung Plz Montclair NJ 07042",
    "addr:housenumber":"51",
    "addr:postcode":"07042",
    "addr:street":"Watchung Plz",
    "iso:country":"US",
    "sg:address":"51 Watchung Plz",
    "sg:city":"Montclair",
    "sg:classifiers":[
        {
            "category":"Shopping",
            "subcategory":"Stationery & Office Supplies",
            "type":"Retail Goods"
        }
    ],
    "sg:phone":"+1 973 783 5984",
    "sg:postcode":"07042",
    "sg:province":"NJ",
    "sg:tags":[
        "equipment"
    ],
    "wof:name":"Friendly Stationery",
    "wof:placetype":"venue"
},
  "geometry": {"coordinates":[-74.2062,40.830502],"type":"Point"}
}