{
  "type": "Feature",
  "properties": {
    "iso:country":"US",
    "sg:address":"431 Ridge Rd",
    "sg:city":"Dayton",
    "sg:classifiers":[
        {
            "category":"Wholesale",
            "subcategory":"Electrical",
            "type":"Manufacturing & Wholesale Goods"
        }
    ],
    "sg:phone":"+1 732 438 0041",
    "sg:postcode":"08810",
    "sg:province":"NJ",
    "sg:tags":[
        "radio"
    ],
    "sg:website":"www.usamobility.com",
    "wof:name":"USA Mobility Inc",
    "wof:placetype":"venue"
},
  "geometry": {"coordinates":[-74.51712000000001,40.375767],"type":"Point"}
}