{
  "type": "Feature",
  "properties": {
    "iso:country":"US",
    "sg:address":"31 Harrison Ave",
    "sg:city":"West Caldwell",
    "sg:classifiers":[
        {
            "category":"Health Services",
            "subcategory":"Dentist",
            "type":"Services"
        }
    ],
    "sg:phone":"+1 973 228 0076",
    "sg:postcode":"07006",
    "sg:province":"NJ",
    "wof:name":"Josephsen Alfred P DMD",
    "wof:placetype":"venue"
},
  "geometry": {"coordinates":[-74.26750199999999,40.841599],"type":"Point"}
}