{
  "type": "Feature",
  "properties": {
    "addr:full":"21 Union Pl Summit NJ 07901",
    "addr:housenumber":"21",
    "addr:postcode":"07901",
    "addr:street":"Union Pl",
    "iso:country":"US",
    "sg:address":"21 Union Pl",
    "sg:city":"Summit",
    "sg:classifiers":[
        {
            "category":"Restaurant",
            "type":"Food & Drink"
        }
    ],
    "sg:menulink":"http://www.allmenus.com/nj/summit/5570-summit-brick-oven-pizza/menu/",
    "sg:phone":"+1 908 598 0045",
    "sg:postcode":"07901",
    "sg:province":"NJ",
    "sg:tags":[
        "italian"
    ],
    "wof:name":"Summit Brick Oven Pizza",
    "wof:placetype":"venue"
},
  "geometry": {"coordinates":[-74.35748,40.716811],"type":"Point"}
}