{
  "type": "Feature",
  "properties": {
    "iso:country":"US",
    "sg:address":"7 Naughright Rd",
    "sg:city":"Hackettstown",
    "sg:classifiers":[
        {
            "category":"Restaurant",
            "type":"Food & Drink"
        }
    ],
    "sg:menulink":"http://www.allmenus.com/nj/mount-olive/146331-subway/menu/",
    "sg:phone":"+1 908 813 0373",
    "sg:postcode":"07840",
    "sg:province":"NJ",
    "sg:tags":[
        "american",
        "sandwich"
    ],
    "wof:name":"Subway",
    "wof:placetype":"venue"
},
  "geometry": {"coordinates":[-74.782557,40.849437],"type":"Point"}
}