{
  "type": "Feature",
  "properties": {
    "iso:country":"US",
    "sg:address":"1110 Cedarbrook Ave",
    "sg:city":"Millville",
    "sg:classifiers":[
        {
            "category":"Wholesale",
            "subcategory":"Construction Materials",
            "type":"Manufacturing & Wholesale Goods"
        }
    ],
    "sg:phone":"+1 856 696 4116",
    "sg:postcode":"08332",
    "sg:province":"NJ",
    "sg:tags":[
        "fence"
    ],
    "wof:name":"John Pangburn Fence Co",
    "wof:placetype":"venue"
},
  "geometry": {"coordinates":[-75.06206299999999,39.391075],"type":"Point"}
}