{
  "type": "Feature",
  "properties": {
    "addr:full":"321 Sip Ave Jersey City NJ 07306",
    "addr:housenumber":"321",
    "addr:postcode":"07306",
    "addr:street":"Sip Ave",
    "iso:country":"US",
    "sg:address":"321 Sip Ave",
    "sg:city":"Jersey City",
    "sg:classifiers":[
        {
            "category":"Real Estate",
            "subcategory":"Real Estate Services",
            "type":"Services"
        }
    ],
    "sg:phone":"+1 201 324 1000",
    "sg:postcode":"07306",
    "sg:province":"NJ",
    "sg:tags":[
        "management",
        "property"
    ],
    "wof:name":"Ajc Realty Exchange Llc",
    "wof:placetype":"venue"
},
  "geometry": {"coordinates":[-74.074699,40.732899],"type":"Point"}
}