{
  "type": "Feature",
  "properties": {
    "addr:full":"941 Asbury Ave Ocean City NJ 08226",
    "addr:housenumber":"941",
    "addr:postcode":"08226",
    "addr:street":"Asbury Ave",
    "iso:country":"US",
    "sg:address":"941 Asbury Ave",
    "sg:city":"Ocean City",
    "sg:classifiers":[
        {
            "category":"Freight",
            "type":"Transportation"
        }
    ],
    "sg:phone":"+1 609 398 5005",
    "sg:postcode":"08226",
    "sg:province":"NJ",
    "sg:tags":[
        "controlled",
        "storage"
    ],
    "wof:name":"Ocean City Self Storage",
    "wof:placetype":"venue"
},
  "geometry": {"coordinates":[-74.577202,39.278118],"type":"Point"}
}