{
  "type": "Feature",
  "properties": {
    "iso:country":"US",
    "sg:address":"1107 Merrick Ave",
    "sg:city":"Collingswood",
    "sg:classifiers":[
        {
            "category":"Building & Trades",
            "subcategory":"Construction",
            "type":"Services"
        }
    ],
    "sg:phone":"+1 609 313 9427",
    "sg:postcode":"08108",
    "sg:province":"NJ",
    "sg:tags":[
        "residential",
        "painting",
        "contractor"
    ],
    "wof:name":"Dave Gottardi",
    "wof:placetype":"venue"
},
  "geometry": {"coordinates":[-75.06044199999999,39.906732],"type":"Point"}
}