{
  "type": "Feature",
  "properties": {
    "addr:full":"701 Trinity St South Plainfield NJ 07080",
    "addr:housenumber":"701",
    "addr:postcode":"07080",
    "addr:street":"Trinity St",
    "iso:country":"US",
    "sg:address":"701 Trinity St",
    "sg:city":"South Plainfield",
    "sg:classifiers":[
        {
            "category":"Shopping",
            "subcategory":"Discount & Variety Stores",
            "type":"Retail Goods"
        }
    ],
    "sg:phone":"+1 908 755 6453",
    "sg:postcode":"07080",
    "sg:province":"NJ",
    "sg:tags":[
        "merchandise",
        "general"
    ],
    "wof:name":"East Coast Svc",
    "wof:placetype":"venue"
},
  "geometry": {"coordinates":[-74.437997,40.595526],"type":"Point"}
}