{
  "type": "Feature",
  "properties": {
    "iso:country":"US",
    "sg:address":"173 Dodd St",
    "sg:city":"East Orange",
    "sg:classifiers":[
        {
            "category":"Food & Beverages",
            "subcategory":"Groceries & Convenience Stores",
            "type":"Retail Goods"
        }
    ],
    "sg:phone":"+1 973 414 1151",
    "sg:postcode":"07017",
    "sg:province":"NJ",
    "wof:name":"El Divino Nino Grocery",
    "wof:placetype":"venue"
},
  "geometry": {"coordinates":[-74.209101,40.781379],"type":"Point"}
}