{
  "type": "Feature",
  "properties": {
    "iso:country":"US",
    "sg:address":"347 2nd St",
    "sg:city":"Elizabeth",
    "sg:classifiers":[
        {
            "category":"Building & Trades",
            "subcategory":"Construction",
            "type":"Services"
        }
    ],
    "sg:phone":"+1 908 787 1005",
    "sg:postcode":"07206",
    "sg:province":"NJ",
    "sg:tags":[
        "contractor"
    ],
    "wof:name":"Black Stallion Construction",
    "wof:placetype":"venue"
},
  "geometry": {"coordinates":[-74.179934,40.655098],"type":"Point"}
}