{
  "type": "Feature",
  "properties": {
    "iso:country":"US",
    "sg:address":"516 W Broad St",
    "sg:city":"Gibbstown",
    "sg:classifiers":[
        {
            "category":"Organizations",
            "subcategory":"Religious Organization",
            "type":"Services"
        }
    ],
    "sg:phone":"+1 856 423 1196",
    "sg:postcode":"08027",
    "sg:province":"NJ",
    "sg:tags":[
        "church"
    ],
    "wof:name":"Clonmell United Methodist Chr",
    "wof:placetype":"venue"
},
  "geometry": {"coordinates":[-75.29129399999999,39.824751],"type":"Point"}
}