{
  "type": "Feature",
  "properties": {
    "iso:country":"US",
    "sg:address":"1779 Belmont Ave",
    "sg:city":"Wall",
    "sg:classifiers":[
        {
            "category":"Retail",
            "subcategory":"Repair Shop",
            "type":"Services"
        }
    ],
    "sg:phone":"+1 732 280 3533",
    "sg:postcode":"07719",
    "sg:province":"NJ",
    "sg:tags":[
        "scooter",
        "motorcycle",
        "motor"
    ],
    "wof:name":"Sled Shed",
    "wof:placetype":"venue"
},
  "geometry": {"coordinates":[-74.028762,40.172141],"type":"Point"}
}