{
  "type": "Feature",
  "properties": {
    "iso:country":"US",
    "sg:address":"210 Market St",
    "sg:city":"Newark",
    "sg:classifiers":[
        {
            "category":"Professional",
            "subcategory":"Management & Consulting",
            "type":"Services"
        }
    ],
    "sg:phone":"+1 973 622 0559",
    "sg:postcode":"07102",
    "sg:province":"NJ",
    "sg:tags":[
        "fuel"
    ],
    "wof:name":"P Funk Records & Management",
    "wof:placetype":"venue"
},
  "geometry": {"coordinates":[-74.172174,40.735577],"type":"Point"}
}