{
  "type": "Feature",
  "properties": {
    "iso:country":"US",
    "sg:address":"70 S Washington Ave",
    "sg:city":"Bergenfield",
    "sg:classifiers":[
        {
            "category":"Personal",
            "subcategory":"Beauty Salon",
            "type":"Services"
        }
    ],
    "sg:phone":"+1 201 387 1869",
    "sg:postcode":"07621",
    "sg:province":"NJ",
    "sg:tags":[
        "shop"
    ],
    "wof:name":"Hair Masters North",
    "wof:placetype":"venue"
},
  "geometry": {"coordinates":[-73.996911,40.925328],"type":"Point"}
}