{
  "type": "Feature",
  "properties": {
    "iso:country":"US",
    "sg:address":"160 Mill St",
    "sg:city":"Washington Twp",
    "sg:classifiers":[
        {
            "category":"Health Services",
            "subcategory":"Clinic",
            "type":"Services"
        }
    ],
    "sg:phone":"+1 856 629 5715",
    "sg:postcode":"07675",
    "sg:province":"NJ",
    "wof:name":"Gloucester Co Health Svc",
    "wof:placetype":"venue"
},
  "geometry": {"coordinates":[-74.04098999999999,40.988015],"type":"Point"}
}