{
  "type": "Feature",
  "properties": {
    "iso:country":"US",
    "sg:address":"7 Village Rd",
    "sg:city":"Kendall Park",
    "sg:classifiers":[
        {
            "category":"Professional",
            "subcategory":"Lawyer & Legal Services",
            "type":"Services"
        }
    ],
    "sg:phone":"+1 732 821 6077",
    "sg:postcode":"08824",
    "sg:province":"NJ",
    "wof:name":"Immigration & Visas Intl",
    "wof:placetype":"venue"
},
  "geometry": {"coordinates":[-74.54513799999999,40.430271],"type":"Point"}
}