{
  "type": "Feature",
  "properties": {
    "addr:full":"320 Broad Ave Ridgefield NJ 07657",
    "addr:housenumber":"320",
    "addr:postcode":"07657",
    "addr:street":"Broad Ave",
    "iso:country":"US",
    "sg:address":"320 Broad Ave",
    "sg:city":"Ridgefield",
    "sg:classifiers":[
        {
            "category":"Restaurant",
            "type":"Food & Drink"
        }
    ],
    "sg:phone":"+1 201 943 9400",
    "sg:postcode":"07657",
    "sg:province":"NJ",
    "wof:name":"Kunson Restaurant",
    "wof:placetype":"venue"
},
  "geometry": {"coordinates":[-74.00946999999999,40.82572],"type":"Point"}
}