{
  "type": "Feature",
  "properties": {
    "iso:country":"US",
    "sg:address":"297 Morris Ave",
    "sg:city":"Springfield",
    "sg:classifiers":[
        {
            "category":"Building & Trades",
            "subcategory":"Construction",
            "type":"Services"
        }
    ],
    "sg:phone":"+1 973 564 6282",
    "sg:postcode":"07081",
    "sg:province":"NJ",
    "sg:tags":[
        "contractor"
    ],
    "wof:name":"Rodriquez Contractors",
    "wof:placetype":"venue"
},
  "geometry": {"coordinates":[-74.314137,40.711651],"type":"Point"}
}