{
  "type": "Feature",
  "properties": {
    "iso:country":"US",
    "sg:address":"32 Conklin Ave",
    "sg:city":"Morristown",
    "sg:classifiers":[
        {
            "category":"Professional",
            "subcategory":"Management & Consulting",
            "type":"Services"
        }
    ],
    "sg:phone":"+1   ",
    "sg:postcode":"07960",
    "sg:province":"NJ",
    "sg:tags":[
        "support",
        "sales"
    ],
    "wof:name":"Tmw Consulting Associates LLC",
    "wof:placetype":"venue"
},
  "geometry": {"coordinates":[-74.493409,40.80211],"type":"Point"}
}