{
  "type": "Feature",
  "properties": {
    "addr:full":"8 5th St Flagtown NJ 08857",
    "addr:housenumber":"8",
    "addr:postcode":"08857",
    "addr:street":"5Th St",
    "iso:country":"US",
    "sg:address":"8 5th St",
    "sg:city":"Flagtown",
    "sg:classifiers":[
        {
            "category":"Building & Trades",
            "subcategory":"Construction",
            "type":"Services"
        }
    ],
    "sg:phone":"+1 908 595 9019",
    "sg:postcode":"08857",
    "sg:province":"NJ",
    "sg:tags":[
        "masonry",
        "contractor"
    ],
    "sg:website":"www.concretechiropractor.com",
    "wof:name":"Concrete Chiropractor",
    "wof:placetype":"venue"
},
  "geometry": {"coordinates":[-74.361659,40.403206],"type":"Point"}
}