{
  "type": "Feature",
  "properties": {
    "iso:country":"US",
    "sg:address":"853 Monmouth Rd",
    "sg:city":"Cream Ridge",
    "sg:classifiers":[
        {
            "category":"Building & Trades",
            "subcategory":"Construction",
            "type":"Services"
        }
    ],
    "sg:phone":"+1 609 758 9484",
    "sg:postcode":"08514",
    "sg:province":"NJ",
    "sg:tags":[
        "house",
        "builder",
        "home"
    ],
    "wof:name":"Alvik Log Homes",
    "wof:placetype":"venue"
},
  "geometry": {"coordinates":[-74.51853699999999,40.096102],"type":"Point"}
}