{
  "type": "Feature",
  "properties": {
    "addr:full":"131 State Rte 23 Hamburg NJ 07419",
    "addr:housenumber":"131",
    "addr:postcode":"07419",
    "addr:street":"State Rte 23",
    "iso:country":"US",
    "sg:address":"131 State Rte 23",
    "sg:city":"Hamburg",
    "sg:classifiers":[
        {
            "category":"Building & Trades",
            "subcategory":"Construction",
            "type":"Services"
        }
    ],
    "sg:phone":"+1   ",
    "sg:postcode":"07419",
    "sg:province":"NJ",
    "sg:tags":[
        "fencing",
        "fence",
        "contractor"
    ],
    "wof:name":"Abate",
    "wof:placetype":"venue"
},
  "geometry": {"coordinates":[-74.572115,41.141463],"type":"Point"}
}