{
  "type": "Feature",
  "properties": {
    "addr:full":"6 Shifra Ct Edison NJ 08820",
    "addr:housenumber":"6",
    "addr:postcode":"08820",
    "addr:street":"Shifra Ct",
    "iso:country":"US",
    "sg:address":"6 Shifra Ct",
    "sg:city":"Edison",
    "sg:classifiers":[
        {
            "category":"Professional",
            "subcategory":"Computer Services",
            "type":"Services"
        }
    ],
    "sg:phone":"+1   ",
    "sg:postcode":"08820",
    "sg:province":"NJ",
    "sg:tags":[
        "related"
    ],
    "wof:name":"Prime Data Integrity Inc",
    "wof:placetype":"venue"
},
  "geometry": {"coordinates":[-74.395336,40.553934],"type":"Point"}
}