{
  "type": "Feature",
  "properties": {
    "iso:country":"US",
    "sg:address":"30 Leuning St",
    "sg:city":"South Hackensack",
    "sg:classifiers":[
        {
            "category":"Shopping",
            "subcategory":"Jewelry",
            "type":"Retail Goods"
        }
    ],
    "sg:phone":"+1   ",
    "sg:postcode":"07606",
    "sg:province":"NJ",
    "wof:name":"North American Watch Inc",
    "wof:placetype":"venue"
},
  "geometry": {"coordinates":[-74.050538,40.872209],"type":"Point"}
}