{
  "type": "Feature",
  "properties": {
    "iso:country":"US",
    "sg:address":"1839 Admiral Wilson Blvd",
    "sg:city":"Pennsauken",
    "sg:classifiers":[
        {
            "category":"Autos & Motor Vehicles",
            "subcategory":"Fuel & Gas Station",
            "type":"Retail Goods"
        }
    ],
    "sg:phone":"+1 856 964 8801",
    "sg:postcode":"08109",
    "sg:province":"NJ",
    "wof:name":"McNulty Exxon Station",
    "wof:placetype":"venue"
},
  "geometry": {"coordinates":[-75.09610000000001,39.940399],"type":"Point"}
}