{
  "type": "Feature",
  "properties": {
    "iso:country":"US",
    "sg:address":"129 Washington St",
    "sg:city":"Hoboken",
    "sg:classifiers":[
        {
            "category":"Health Services",
            "subcategory":"Doctor",
            "type":"Services"
        }
    ],
    "sg:phone":"+1 201 795 0501",
    "sg:postcode":"07030",
    "sg:province":"NJ",
    "sg:tags":[
        "physician",
        "surgeon"
    ],
    "wof:name":"George Mc Quilkin MD",
    "wof:placetype":"venue"
},
  "geometry": {"coordinates":[-74.030522,40.738335],"type":"Point"}
}