{
  "type": "Feature",
  "properties": {
    "addr:full":"1904 Bay Blvd Point Pleasant Beach NJ 08742",
    "addr:housenumber":"1904",
    "addr:postcode":"08742",
    "addr:street":"Bay Blvd",
    "iso:country":"US",
    "sg:address":"1904 Bay Blvd",
    "sg:city":"Point Pleasant Beach",
    "sg:classifiers":[
        {
            "category":"Shopping",
            "subcategory":"Used Merchandise",
            "type":"Retail Goods"
        }
    ],
    "sg:phone":"+1   ",
    "sg:postcode":"08742",
    "sg:province":"NJ",
    "wof:name":"Antique Alley",
    "wof:placetype":"venue"
},
  "geometry": {"coordinates":[-74.059909,40.068343],"type":"Point"}
}