{
  "type": "Feature",
  "properties": {
    "iso:country":"US",
    "sg:address":"395 Lyons Ave",
    "sg:city":"Newark",
    "sg:classifiers":[
        {
            "category":"Shopping",
            "subcategory":"Clothing, Apparel, & Fashions",
            "type":"Retail Goods"
        }
    ],
    "sg:phone":"+1 908 756 3730",
    "sg:postcode":"07112",
    "sg:province":"NJ",
    "wof:name":"Miss Ethel's Divine Wear",
    "wof:placetype":"venue"
},
  "geometry": {"coordinates":[-74.221065,40.713686],"type":"Point"}
}