{
  "type": "Feature",
  "properties": {
    "iso:country":"US",
    "sg:address":"45 Roseland Ave",
    "sg:city":"Caldwell",
    "sg:classifiers":[
        {
            "category":"Manufacturing",
            "subcategory":"Furniture",
            "type":"Manufacturing & Wholesale Goods"
        },
        {
            "category":"Home & Garden",
            "subcategory":"Home Furnishings",
            "type":"Retail Goods"
        }
    ],
    "sg:phone":"+1 973 403 9800",
    "sg:postcode":"07006",
    "sg:province":"NJ",
    "sg:tags":[
        "venetian",
        "blind",
        "drapery",
        "mfg"
    ],
    "wof:name":"Sunco Blinds & Shades",
    "wof:placetype":"venue"
},
  "geometry": {"coordinates":[-74.277818,40.836323],"type":"Point"}
}