{
  "type": "Feature",
  "properties": {
    "iso:country":"US",
    "sg:address":"42 Johnson Rd",
    "sg:city":"Gibbsboro",
    "sg:classifiers":[
        {
            "category":"Building & Trades",
            "subcategory":"Construction",
            "type":"Services"
        }
    ],
    "sg:phone":"+1 856 627 2235",
    "sg:postcode":"08026",
    "sg:province":"NJ",
    "sg:tags":[
        "contractor"
    ],
    "wof:name":"Richardson Cstm Cedar Fencing",
    "wof:placetype":"venue"
},
  "geometry": {"coordinates":[-74.975526,39.829173],"type":"Point"}
}