{
  "type": "Feature",
  "properties": {
    "iso:country":"US",
    "sg:address":"15 Buckingham Cir",
    "sg:city":"Pine Brook",
    "sg:classifiers":[
        {
            "category":"Shopping",
            "subcategory":"Clothing, Apparel, & Fashions",
            "type":"Retail Goods"
        }
    ],
    "sg:phone":"+1   ",
    "sg:postcode":"07058",
    "sg:province":"NJ",
    "wof:name":"Precious Jewels",
    "wof:placetype":"venue"
},
  "geometry": {"coordinates":[-74.35574200000001,40.872468],"type":"Point"}
}