{
  "type": "Feature",
  "properties": {
    "iso:country":"US",
    "sg:address":"230 Demarest St",
    "sg:city":"Ridgewood",
    "sg:classifiers":[
        {
            "category":"Education",
            "subcategory":"School",
            "type":"Public Place"
        }
    ],
    "sg:phone":"+1 201 670 2730",
    "sg:postcode":"07450",
    "sg:province":"NJ",
    "sg:website":"www.ridgewood.k12.nj.us",
    "wof:name":"Ridgewood Orchard Elem School",
    "wof:placetype":"venue"
},
  "geometry": {"coordinates":[-74.12768800000001,40.973683],"type":"Point"}
}