{
  "type": "Feature",
  "properties": {
    "addr:full":"152 Louis St South Hackensack NJ 07606",
    "addr:housenumber":"152",
    "addr:postcode":"07606",
    "addr:street":"Louis St South",
    "iso:country":"US",
    "sg:address":"152 Louis St",
    "sg:city":"South Hackensack",
    "sg:classifiers":[
        {
            "category":"Manufacturing",
            "subcategory":"Furniture",
            "type":"Manufacturing & Wholesale Goods"
        }
    ],
    "sg:phone":"+1 201 641 6555",
    "sg:postcode":"07606",
    "sg:province":"NJ",
    "sg:tags":[
        "household",
        "wood",
        "mfg"
    ],
    "wof:name":"Mastercrafts",
    "wof:placetype":"venue"
},
  "geometry": {"coordinates":[-74.04901099999999,40.857663],"type":"Point"}
}