{
  "type": "Feature",
  "properties": {
    "addr:full":"437 Somerset St Plainfield NJ 07060",
    "addr:housenumber":"437",
    "addr:postcode":"07060",
    "addr:street":"Somerset St",
    "iso:country":"US",
    "sg:address":"437 Somerset St",
    "sg:city":"Plainfield",
    "sg:classifiers":[
        {
            "category":"Building & Trades",
            "subcategory":"Construction",
            "type":"Services"
        }
    ],
    "sg:phone":"+1 908 561 4552",
    "sg:postcode":"07060",
    "sg:province":"NJ",
    "sg:tags":[
        "contractor"
    ],
    "wof:name":"Charles Enterprises",
    "wof:placetype":"venue"
},
  "geometry": {"coordinates":[-74.43391,40.624407],"type":"Point"}
}