{
  "type": "Feature",
  "properties": {
    "iso:country":"US",
    "sg:address":"2 Old Forge Rd",
    "sg:city":"Helmetta",
    "sg:classifiers":[
        {
            "category":"Restaurant",
            "type":"Food & Drink"
        }
    ],
    "sg:phone":"+1 732 656 3121",
    "sg:postcode":"08828",
    "sg:province":"NJ",
    "wof:name":"Cafe Mario",
    "wof:placetype":"venue"
},
  "geometry": {"coordinates":[-74.41521,40.374919],"type":"Point"}
}