{
  "type": "Feature",
  "properties": {
    "addr:full":"1035 US Highway 46 Clifton NJ 07013",
    "addr:housenumber":"1035",
    "addr:postcode":"07013",
    "addr:street":"Us Highway 46",
    "iso:country":"US",
    "sg:address":"1035 US Highway 46",
    "sg:city":"Clifton",
    "sg:classifiers":[
        {
            "category":"Professional",
            "subcategory":"Lawyer & Legal Services",
            "type":"Services"
        }
    ],
    "sg:phone":"+1 973 470 0156",
    "sg:postcode":"07013",
    "sg:province":"NJ",
    "wof:name":"Kridel J A ESQ",
    "wof:placetype":"venue"
},
  "geometry": {"coordinates":[-74.179001,40.871498],"type":"Point"}
}