{
  "type": "Feature",
  "properties": {
    "iso:country":"US",
    "sg:address":"100 Ocean Ave",
    "sg:city":"Jersey City",
    "sg:classifiers":[
        {
            "category":"Personal",
            "subcategory":"Beauty Salon",
            "type":"Services"
        }
    ],
    "sg:phone":"+1 201 432 9339",
    "sg:postcode":"07305",
    "sg:province":"NJ",
    "wof:name":"Fanta Hair Braiding",
    "wof:placetype":"venue"
},
  "geometry": {"coordinates":[-74.095562,40.691583],"type":"Point"}
}