{
  "type": "Feature",
  "properties": {
    "addr:full":"1 Upper Pond Rd Ste 4 Parsippany NJ 07054",
    "addr:housenumber":"1",
    "addr:postcode":"07054",
    "addr:street":"Upper Pond Rd Ste 4",
    "iso:country":"US",
    "sg:address":"1 Upper Pond Rd Ste 4",
    "sg:city":"Parsippany",
    "sg:classifiers":[
        {
            "category":"Shopping",
            "subcategory":"Pharmacy",
            "type":"Retail Goods"
        }
    ],
    "sg:phone":"+1 973 335 3800",
    "sg:postcode":"07054",
    "sg:province":"NJ",
    "sg:tags":[
        "drugstore"
    ],
    "wof:name":"J H P Pharmaceuticals",
    "wof:placetype":"venue"
},
  "geometry": {"coordinates":[-74.45023,40.871183],"type":"Point"}
}