{
  "type": "Feature",
  "properties": {
    "iso:country":"US",
    "sg:address":"13 Bennington Dr",
    "sg:city":"Trenton",
    "sg:classifiers":[
        {
            "category":"Health Services",
            "subcategory":"Chiropractor",
            "type":"Services"
        }
    ],
    "sg:phone":"+1 609 671 9548",
    "sg:postcode":"08648",
    "sg:province":"NJ",
    "wof:name":"Village Chiropractic",
    "wof:placetype":"venue"
},
  "geometry": {"coordinates":[-74.750379,40.297057],"type":"Point"}
}