{
  "type": "Feature",
  "properties": {
    "iso:country":"US",
    "sg:address":"3401 Tremley Point Rd",
    "sg:city":"Linden",
    "sg:classifiers":[
        {
            "category":"Freight",
            "type":"Transportation"
        }
    ],
    "sg:phone":"+1 908 474 9224",
    "sg:postcode":"07036",
    "sg:province":"NJ",
    "sg:tags":[
        "special",
        "warehousing"
    ],
    "wof:name":"International Customs Brkrg",
    "wof:placetype":"venue"
},
  "geometry": {"coordinates":[-74.225796,40.613365],"type":"Point"}
}