{
  "type": "Feature",
  "properties": {
    "addr:full":"1123 Inman Ave Edison NJ 08820",
    "addr:housenumber":"1123",
    "addr:postcode":"08820",
    "addr:street":"Inman Ave",
    "iso:country":"US",
    "sg:address":"1123 Inman Ave",
    "sg:city":"Edison",
    "sg:classifiers":[
        {
            "category":"Travel",
            "subcategory":"Travel Agent",
            "type":"Entertainment"
        }
    ],
    "sg:phone":"+1 908 755 5500",
    "sg:postcode":"08820",
    "sg:province":"NJ",
    "sg:tags":[
        "agency",
        "bureau"
    ],
    "wof:name":"Travel Network",
    "wof:placetype":"venue"
},
  "geometry": {"coordinates":[-74.36659,40.596787],"type":"Point"}
}