{
  "type": "Feature",
  "properties": {
    "iso:country":"US",
    "sg:address":"939 Maple Ave",
    "sg:city":"Atco",
    "sg:classifiers":[
        {
            "category":"Retail",
            "subcategory":"Repair Shop",
            "type":"Services"
        }
    ],
    "sg:phone":"+1 856 768 4329",
    "sg:postcode":"08004",
    "sg:province":"NJ",
    "sg:tags":[
        "good",
        "mfg"
    ],
    "wof:name":"Digitaldagger Co",
    "wof:placetype":"venue"
},
  "geometry": {"coordinates":[-74.84949,39.761388],"type":"Point"}
}