{
  "type": "Feature",
  "properties": {
    "addr:full":"251 Monroe Ave Kenilworth NJ 07033",
    "addr:housenumber":"251",
    "addr:postcode":"07033",
    "addr:street":"Monroe Ave",
    "iso:country":"US",
    "sg:address":"251 Monroe Ave",
    "sg:city":"Kenilworth",
    "sg:classifiers":[
        {
            "category":"Building & Trades",
            "subcategory":"Equipment Rental",
            "type":"Services"
        }
    ],
    "sg:phone":"+1   ",
    "sg:postcode":"07033",
    "sg:province":"NJ",
    "sg:tags":[
        "transportation",
        "lease"
    ],
    "wof:name":"Flexi-Van",
    "wof:placetype":"venue"
},
  "geometry": {"coordinates":[-74.30419500000001,40.678765],"type":"Point"}
}