{
  "type": "Feature",
  "properties": {
    "addr:full":"50 S Main St Mullica Hill NJ 08062",
    "addr:housenumber":"50",
    "addr:postcode":"08062",
    "addr:street":"S Main St",
    "iso:country":"US",
    "sg:address":"50 S Main St",
    "sg:city":"Mullica Hill",
    "sg:classifiers":[
        {
            "category":"Real Estate",
            "subcategory":"Real Estate Agent",
            "type":"Services"
        }
    ],
    "sg:phone":"+1 856 478 6960",
    "sg:postcode":"08062",
    "sg:province":"NJ",
    "wof:name":"Weichert Realtors",
    "wof:placetype":"venue"
},
  "geometry": {"coordinates":[-75.224357,39.732314],"type":"Point"}
}