{
  "type": "Feature",
  "properties": {
    "iso:country":"US",
    "sg:address":"825 Fairfield Ave",
    "sg:city":"Kenilworth",
    "sg:classifiers":[
        {
            "category":"Wholesale",
            "subcategory":"Jewelry",
            "type":"Manufacturing & Wholesale Goods"
        }
    ],
    "sg:phone":"+1 908 620 0700",
    "sg:postcode":"07033",
    "sg:province":"NJ",
    "sg:tags":[
        "stone"
    ],
    "wof:name":"Ilas Accents Inc",
    "wof:placetype":"venue"
},
  "geometry": {"coordinates":[-74.27656,40.670677],"type":"Point"}
}