{
  "type": "Feature",
  "properties": {
    "iso:country":"US",
    "sg:address":"90 Moonachie Ave",
    "sg:city":"Teterboro",
    "sg:classifiers":[
        {
            "category":"Airline",
            "type":"Transportation"
        }
    ],
    "sg:phone":"+1 201 288 5218",
    "sg:postcode":"07608",
    "sg:province":"NJ",
    "sg:tags":[
        "airport"
    ],
    "wof:name":"Avport",
    "wof:placetype":"venue"
},
  "geometry": {"coordinates":[-74.06880200000001,40.839802],"type":"Point"}
}