{
  "type": "Feature",
  "properties": {
    "iso:country":"US",
    "sg:address":"400 Morris Ave",
    "sg:city":"Denville",
    "sg:classifiers":[
        {
            "category":"Professional",
            "subcategory":"Detective & Security Services",
            "type":"Services"
        }
    ],
    "sg:phone":"+1 973 627 2877",
    "sg:postcode":"07834",
    "sg:province":"NJ",
    "sg:tags":[
        "car",
        "guard",
        "patrol"
    ],
    "sg:website":"www.securitasinc.com",
    "wof:name":"Securitas Security Svc USA Inc",
    "wof:placetype":"venue"
},
  "geometry": {"coordinates":[-74.503219,40.90965],"type":"Point"}
}