{
  "type": "Feature",
  "properties": {
    "iso:country":"US",
    "sg:address":"107 Closter Dock Rd",
    "sg:city":"Closter",
    "sg:classifiers":[
        {
            "category":"Home & Garden",
            "subcategory":"Furniture",
            "type":"Retail Goods"
        }
    ],
    "sg:phone":"+1   ",
    "sg:postcode":"07624",
    "sg:province":"NJ",
    "wof:name":"Rockaway Bedding 86",
    "wof:placetype":"venue"
},
  "geometry": {"coordinates":[-73.964369,40.97672],"type":"Point"}
}