{
  "type": "Feature",
  "properties": {
    "addr:full":"379 Kinderkamack Rd Oradell NJ 07649",
    "addr:housenumber":"379",
    "addr:postcode":"07649",
    "addr:street":"Kinderkamack Rd",
    "iso:country":"US",
    "sg:address":"379 Kinderkamack Rd",
    "sg:city":"Oradell",
    "sg:classifiers":[
        {
            "category":"Manufacturing",
            "subcategory":"Printing",
            "type":"Manufacturing & Wholesale Goods"
        }
    ],
    "sg:phone":"+1 201 265 7977",
    "sg:postcode":"07649",
    "sg:province":"NJ",
    "sg:tags":[
        "photo",
        "printer"
    ],
    "wof:name":"Emerson Speed Printing Inc",
    "wof:placetype":"venue"
},
  "geometry": {"coordinates":[-74.03173,40.953682],"type":"Point"}
}