{
  "type": "Feature",
  "properties": {
    "iso:country":"US",
    "sg:address":"80 Terrace Ave",
    "sg:city":"Maywood",
    "sg:classifiers":[
        {
            "category":"Retail",
            "subcategory":"Animal Services",
            "type":"Services"
        }
    ],
    "sg:phone":"+1 201 843 7387",
    "sg:postcode":"07607",
    "sg:province":"NJ",
    "sg:tags":[
        "pet",
        "boarding",
        "sitting"
    ],
    "wof:name":"Pets Amour Inc",
    "wof:placetype":"venue"
},
  "geometry": {"coordinates":[-74.057411,40.904368],"type":"Point"}
}