{
  "type": "Feature",
  "properties": {
    "iso:country":"US",
    "sg:address":"11 E Main St",
    "sg:city":"Tuckerton",
    "sg:classifiers":[
        {
            "category":"Professional",
            "subcategory":"Accounting & Tax Preparation",
            "type":"Services"
        }
    ],
    "sg:phone":"+1 609 296 1439",
    "sg:postcode":"08087",
    "sg:province":"NJ",
    "sg:tags":[
        "return"
    ],
    "wof:name":"H & R Block Eastern Tax Svcs",
    "wof:placetype":"venue"
},
  "geometry": {"coordinates":[-74.34028000000001,39.603339],"type":"Point"}
}