{
  "type": "Feature",
  "properties": {
    "addr:full":"5 Kimberly Dr Runnemede NJ 08029",
    "addr:housenumber":"5",
    "addr:postcode":"08029",
    "addr:street":"Kimberly Dr",
    "iso:country":"US",
    "sg:address":"5 Kimberly Dr",
    "sg:city":"Runnemede",
    "sg:classifiers":[
        {
            "category":"Personal",
            "subcategory":"Beauty Salon",
            "type":"Services"
        }
    ],
    "sg:phone":"+1 856 887 1772",
    "sg:postcode":"08029",
    "sg:province":"NJ",
    "sg:tags":[
        "spa"
    ],
    "sg:website":"www.BodicareSpa.com",
    "wof:name":"Bodicare Spa",
    "wof:placetype":"venue"
},
  "geometry": {"coordinates":[-75.05083999999999,39.850802],"type":"Point"}
}