{
  "type": "Feature",
  "properties": {
    "iso:country":"US",
    "sg:address":"353 Dover Chester Rd",
    "sg:city":"Randolph",
    "sg:classifiers":[
        {
            "category":"Health Services",
            "subcategory":"Health Practitioner",
            "type":"Services"
        }
    ],
    "sg:phone":"+1 973 366 9017",
    "sg:postcode":"07869",
    "sg:province":"NJ",
    "sg:tags":[
        "acupuncture"
    ],
    "wof:name":"Zen Acupuncture & Massage",
    "wof:placetype":"venue"
},
  "geometry": {"coordinates":[-74.61796099999999,40.826727],"type":"Point"}
}