{
  "type": "Feature",
  "properties": {
    "addr:full":"810 N Forklanding Rd Maple Shade NJ 08052",
    "addr:housenumber":"810",
    "addr:postcode":"08052",
    "addr:street":"N Forklanding Rd",
    "iso:country":"US",
    "sg:address":"810 N Forklanding Rd",
    "sg:city":"Maple Shade",
    "sg:classifiers":[
        {
            "category":"Professional",
            "subcategory":"Computer Services",
            "type":"Services"
        }
    ],
    "sg:phone":"+1   ",
    "sg:postcode":"08052",
    "sg:province":"NJ",
    "sg:tags":[
        "related"
    ],
    "wof:name":"Bravado Consulting Inc",
    "wof:placetype":"venue"
},
  "geometry": {"coordinates":[-75.01235699999999,39.970114],"type":"Point"}
}