{
  "type": "Feature",
  "properties": {
    "iso:country":"US",
    "sg:address":"1601 Central Ave",
    "sg:city":"Union City",
    "sg:classifiers":[
        {
            "category":"Education",
            "subcategory":"School",
            "type":"Public Place"
        },
        {
            "category":"Organizations",
            "subcategory":"Religious Organization",
            "type":"Services"
        }
    ],
    "sg:phone":"+1 201 863 4112",
    "sg:postcode":"07087",
    "sg:province":"NJ",
    "sg:tags":[
        "elementary"
    ],
    "sg:website":"www.stfrancisacademy.com",
    "wof:name":"Saint Francis Academy",
    "wof:placetype":"venue"
},
  "geometry": {"coordinates":[-74.038597,40.763401],"type":"Point"}
}