{
  "type": "Feature",
  "properties": {
    "iso:country":"US",
    "sg:address":"75 Morristown Rd",
    "sg:city":"Bernardsville",
    "sg:classifiers":[
        {
            "category":"Restaurant",
            "type":"Food & Drink"
        }
    ],
    "sg:phone":"+1   ",
    "sg:postcode":"07924",
    "sg:province":"NJ",
    "sg:tags":[
        "gourmet",
        "japanese"
    ],
    "wof:name":"Tokyo Delite",
    "wof:placetype":"venue"
},
  "geometry": {"coordinates":[-74.56528400000001,40.718811],"type":"Point"}
}