{
  "type": "Feature",
  "properties": {
    "iso:country":"US",
    "sg:address":"51 Darlington Dr",
    "sg:city":"Wayne",
    "sg:classifiers":[
        {
            "category":"Building & Trades",
            "subcategory":"Construction",
            "type":"Services"
        }
    ],
    "sg:phone":"+1 973 790 3101",
    "sg:postcode":"07470",
    "sg:province":"NJ",
    "sg:tags":[
        "contractor"
    ],
    "wof:name":"Totowa Tile",
    "wof:placetype":"venue"
},
  "geometry": {"coordinates":[-74.217996,40.92044],"type":"Point"}
}