{
  "type": "Feature",
  "properties": {
    "addr:full":"49 Lucille Ave Dumont NJ 07628",
    "addr:housenumber":"49",
    "addr:postcode":"07628",
    "addr:street":"Lucille Ave",
    "iso:country":"US",
    "sg:address":"49 Lucille Ave",
    "sg:city":"Dumont",
    "sg:classifiers":[
        {
            "category":"Retail",
            "subcategory":"Auto Repair",
            "type":"Services"
        }
    ],
    "sg:phone":"+1 201 387 8874",
    "sg:postcode":"07628",
    "sg:province":"NJ",
    "sg:tags":[
        "general"
    ],
    "wof:name":"Morikawa Auto Agency",
    "wof:placetype":"venue"
},
  "geometry": {"coordinates":[-73.97832699999999,40.944874],"type":"Point"}
}