{
  "type": "Feature",
  "properties": {
    "addr:full":"844 State Rte 73 West Berlin NJ 08091",
    "addr:housenumber":"844",
    "addr:postcode":"08091",
    "addr:street":"State Rte 73",
    "iso:country":"US",
    "sg:address":"844 State Rte 73",
    "sg:city":"West Berlin",
    "sg:classifiers":[
        {
            "category":"Shopping",
            "subcategory":"Musical Instruments",
            "type":"Retail Goods"
        }
    ],
    "sg:phone":"+1 856 768 2226",
    "sg:postcode":"08091",
    "sg:province":"NJ",
    "wof:name":"MUSIC Place",
    "wof:placetype":"venue"
},
  "geometry": {"coordinates":[-74.910416,39.787431],"type":"Point"}
}