{
  "type": "Feature",
  "properties": {
    "addr:full":"27 Betsy Ross Dr Freehold NJ 07728",
    "addr:housenumber":"27",
    "addr:postcode":"07728",
    "addr:street":"Betsy Ross Dr",
    "iso:country":"US",
    "sg:address":"27 Betsy Ross Dr",
    "sg:city":"Freehold",
    "sg:classifiers":[
        {
            "category":"Professional",
            "subcategory":"Accounting & Tax Preparation",
            "type":"Services"
        }
    ],
    "sg:phone":"+1 609 208 1188",
    "sg:postcode":"07728",
    "sg:province":"NJ",
    "sg:tags":[
        "bookkeeping",
        "general"
    ],
    "wof:name":"Andrea Goldberg Bookkeeping",
    "wof:placetype":"venue"
},
  "geometry": {"coordinates":[-74.28962900000001,40.284858],"type":"Point"}
}