{
  "type": "Feature",
  "properties": {
    "addr:full":"123 Hook Mountain Rd Montville NJ 07045",
    "addr:housenumber":"123",
    "addr:postcode":"07045",
    "addr:street":"Hook Mountain Rd",
    "iso:country":"US",
    "sg:address":"123 Hook Mountain Rd",
    "sg:city":"Montville",
    "sg:classifiers":[
        {
            "category":"Building & Trades",
            "subcategory":"Construction",
            "type":"Services"
        }
    ],
    "sg:phone":"+1 973 227 9905",
    "sg:postcode":"07045",
    "sg:province":"NJ",
    "sg:tags":[
        "contractor"
    ],
    "wof:name":"T&J Masonry",
    "wof:placetype":"venue"
},
  "geometry": {"coordinates":[-74.340898,40.880275],"type":"Point"}
}