{
  "type": "Feature",
  "properties": {
    "iso:country":"US",
    "sg:address":"1000 N Black Horse Pike",
    "sg:city":"Runnemede",
    "sg:classifiers":[
        {
            "category":"Building & Trades",
            "subcategory":"Construction",
            "type":"Services"
        }
    ],
    "sg:phone":"+1   ",
    "sg:postcode":"08078",
    "sg:province":"NJ",
    "sg:tags":[
        "repair",
        "merchandise",
        "contractor"
    ],
    "wof:name":"Saving Energy Today & Always",
    "wof:placetype":"venue"
},
  "geometry": {"coordinates":[-75.07598,39.857882],"type":"Point"}
}