{
  "type": "Feature",
  "properties": {
    "iso:country":"US",
    "sg:address":"589 Cedar Ave",
    "sg:city":"West Long Branch",
    "sg:classifiers":[
        {
            "category":"Shopping",
            "type":"Retail Goods"
        }
    ],
    "sg:phone":"+1   ",
    "sg:postcode":"07764",
    "sg:province":"NJ",
    "sg:tags":[
        "merchandise"
    ],
    "wof:name":"A To Z Wireless Inc",
    "wof:placetype":"venue"
},
  "geometry": {"coordinates":[-74.016716,40.283424],"type":"Point"}
}