{
  "type": "Feature",
  "properties": {
    "iso:country":"US",
    "sg:address":"190 Tyler St",
    "sg:city":"Newark",
    "sg:classifiers":[
        {
            "category":"Freight",
            "type":"Transportation"
        }
    ],
    "sg:phone":"+1 973 274 0138",
    "sg:postcode":"07114",
    "sg:province":"NJ",
    "wof:name":"New York Shipping Assn Inc",
    "wof:placetype":"venue"
},
  "geometry": {"coordinates":[-74.156728,40.69432],"type":"Point"}
}