{
  "type": "Feature",
  "properties": {
    "iso:country":"US",
    "sg:address":"45 Joans Ln",
    "sg:city":"Berlin",
    "sg:classifiers":[
        {
            "category":"Building & Trades",
            "subcategory":"Equipment Rental",
            "type":"Services"
        }
    ],
    "sg:phone":"+1 856 767 3435",
    "sg:postcode":"08009",
    "sg:province":"NJ",
    "sg:tags":[
        "machine",
        "washing"
    ],
    "wof:name":"Huber's Skinny Mini Svc",
    "wof:placetype":"venue"
},
  "geometry": {"coordinates":[-74.926069,39.776902],"type":"Point"}
}