{
  "type": "Feature",
  "properties": {
    "iso:country":"US",
    "sg:address":"8 Fletcher Dr",
    "sg:city":"Montville",
    "sg:classifiers":[
        {
            "category":"Professional",
            "subcategory":"Computer Services",
            "type":"Services"
        }
    ],
    "sg:phone":"+1 973 335 0752",
    "sg:postcode":"07045",
    "sg:province":"NJ",
    "sg:tags":[
        "datum",
        "programing",
        "custom"
    ],
    "wof:name":"AHB Systems Inc",
    "wof:placetype":"venue"
},
  "geometry": {"coordinates":[-74.356258,40.899459],"type":"Point"}
}