{
  "type": "Feature",
  "properties": {
    "addr:full":"830 S 16th St Newark NJ 07108",
    "addr:housenumber":"830",
    "addr:postcode":"07108",
    "addr:street":"S 16Th St",
    "iso:country":"US",
    "sg:address":"830 S 16th St",
    "sg:city":"Newark",
    "sg:classifiers":[
        {
            "category":"Wholesale",
            "subcategory":"Machinery & Supplies",
            "type":"Manufacturing & Wholesale Goods"
        }
    ],
    "sg:phone":"+1 973 372 6881",
    "sg:postcode":"07108",
    "sg:province":"NJ",
    "sg:tags":[
        "contractor"
    ],
    "wof:name":"LSE General Contractors",
    "wof:placetype":"venue"
},
  "geometry": {"coordinates":[-74.21157100000001,40.727319],"type":"Point"}
}