{
  "type": "Feature",
  "properties": {
    "iso:country":"US",
    "sg:address":"1147 E Jersey St",
    "sg:city":"Elizabeth",
    "sg:classifiers":[
        {
            "category":"Shopping",
            "subcategory":"Pharmacy",
            "type":"Retail Goods"
        }
    ],
    "sg:phone":"+1 908 994 1525",
    "sg:postcode":"07201",
    "sg:province":"NJ",
    "wof:name":"Elizabeth Pharmancy",
    "wof:placetype":"venue"
},
  "geometry": {"coordinates":[-74.21454,40.665364],"type":"Point"}
}