{
  "type": "Feature",
  "properties": {
    "iso:country":"US",
    "sg:address":"131 Seminole Ave",
    "sg:city":"Oakland",
    "sg:classifiers":[
        {
            "category":"Taxi",
            "type":"Transportation"
        }
    ],
    "sg:phone":"+1 201 337 6000",
    "sg:postcode":"07436",
    "sg:province":"NJ",
    "sg:tags":[
        "taxicab",
        "local"
    ],
    "wof:name":"Smiley's Taxi",
    "wof:placetype":"venue"
},
  "geometry": {"coordinates":[-74.22854,41.033154],"type":"Point"}
}