{
  "type": "Feature",
  "properties": {
    "iso:country":"US",
    "sg:address":"250 E Ridgewood Ave",
    "sg:city":"Ridgewood",
    "sg:classifiers":[
        {
            "category":"Shopping",
            "subcategory":"Clothing, Apparel, & Fashions",
            "type":"Retail Goods"
        }
    ],
    "sg:phone":"+1 201 444 1300",
    "sg:postcode":"07450",
    "sg:province":"NJ",
    "wof:name":"Leapin' Lizards",
    "wof:placetype":"venue"
},
  "geometry": {"coordinates":[-74.11413,40.978746],"type":"Point"}
}