{
  "type": "Feature",
  "properties": {
    "addr:full":"155 Park Ave Lyndhurst NJ 07071",
    "addr:housenumber":"155",
    "addr:postcode":"07071",
    "addr:street":"Park Ave",
    "iso:country":"US",
    "sg:address":"155 Park Ave",
    "sg:city":"Lyndhurst",
    "sg:classifiers":[
        {
            "category":"Real Estate",
            "subcategory":"Real Estate Operator",
            "type":"Services"
        }
    ],
    "sg:phone":"+1   ",
    "sg:postcode":"07071",
    "sg:province":"NJ",
    "sg:tags":[
        "owner",
        "building",
        "an"
    ],
    "wof:name":"Park Court Development Co",
    "wof:placetype":"venue"
},
  "geometry": {"coordinates":[-74.12740700000001,40.818428],"type":"Point"}
}