{
  "type": "Feature",
  "properties": {
    "addr:full":"10 Shilling Way Jackson NJ 08527",
    "addr:housenumber":"10",
    "addr:postcode":"08527",
    "addr:street":"Shilling Way",
    "iso:country":"US",
    "sg:address":"10 Shilling Way",
    "sg:city":"Jackson",
    "sg:classifiers":[
        {
            "category":"Building & Trades",
            "subcategory":"Construction",
            "type":"Services"
        }
    ],
    "sg:phone":"+1 732 961 1277",
    "sg:postcode":"08527",
    "sg:province":"NJ",
    "sg:tags":[
        "contractor"
    ],
    "wof:name":"Desilva Contractors",
    "wof:placetype":"venue"
},
  "geometry": {"coordinates":[-74.274055,40.131388],"type":"Point"}
}