{
  "type": "Feature",
  "properties": {
    "addr:full":"574 Amboy Ave Woodbridge NJ 07095",
    "addr:housenumber":"574",
    "addr:postcode":"07095",
    "addr:street":"Amboy Ave",
    "iso:country":"US",
    "sg:address":"574 Amboy Ave",
    "sg:city":"Woodbridge",
    "sg:classifiers":[
        {
            "category":"Autos & Motor Vehicles",
            "subcategory":"Motorcycle Sales",
            "type":"Retail Goods"
        }
    ],
    "sg:phone":"+1 732 636 2555",
    "sg:postcode":"07095",
    "sg:province":"NJ",
    "wof:name":"Action Enterprises",
    "wof:placetype":"venue"
},
  "geometry": {"coordinates":[-74.285004,40.560501],"type":"Point"}
}