{
  "type": "Feature",
  "properties": {
    "addr:full":"103 Troy Meadow Rd Parsippany NJ 07054",
    "addr:housenumber":"103",
    "addr:postcode":"07054",
    "addr:street":"Troy Meadow Rd",
    "iso:country":"US",
    "sg:address":"103 Troy Meadow Rd",
    "sg:city":"Parsippany",
    "sg:classifiers":[
        {
            "category":"Shopping",
            "subcategory":"Computers & Home Electronics",
            "type":"Retail Goods"
        }
    ],
    "sg:phone":"+1 973 599 0780",
    "sg:postcode":"07054",
    "sg:province":"NJ",
    "sg:tags":[
        "parts",
        "supply"
    ],
    "wof:name":"Reliable Resources Inc",
    "wof:placetype":"venue"
},
  "geometry": {"coordinates":[-74.387141,40.850514],"type":"Point"}
}