{
  "type": "Feature",
  "properties": {
    "iso:country":"US",
    "sg:address":"120 E Pleasant Ave",
    "sg:city":"Maywood",
    "sg:classifiers":[
        {
            "category":"Organizations",
            "subcategory":"Religious Organization",
            "type":"Services"
        }
    ],
    "sg:phone":"+1   ",
    "sg:postcode":"07607",
    "sg:province":"NJ",
    "sg:website":"www.zionmaywood.org",
    "wof:name":"Zion Lutheran Church",
    "wof:placetype":"venue"
},
  "geometry": {"coordinates":[-74.058268,40.901906],"type":"Point"}
}