{
  "type": "Feature",
  "properties": {
    "addr:full":"17 W Red Bank Ave Woodbury NJ 08096",
    "addr:housenumber":"17",
    "addr:postcode":"08096",
    "addr:street":"W Red Bank Ave",
    "iso:country":"US",
    "sg:address":"17 W Red Bank Ave",
    "sg:city":"Woodbury",
    "sg:classifiers":[
        {
            "category":"Health Services",
            "subcategory":"Health Practitioner",
            "type":"Services"
        }
    ],
    "sg:phone":"+1 856 384 1964",
    "sg:postcode":"08096",
    "sg:province":"NJ",
    "sg:tags":[
        "acupuncture"
    ],
    "wof:name":"Cooper Hospital Medical Ctr",
    "wof:placetype":"venue"
},
  "geometry": {"coordinates":[-75.15193600000001,39.844213],"type":"Point"}
}