{
  "type": "Feature",
  "properties": {
    "iso:country":"US",
    "sg:address":"897 Palisade Ave",
    "sg:city":"Fort Lee",
    "sg:classifiers":[
        {
            "category":"Insurance",
            "subcategory":"Insurance Agent",
            "type":"Services"
        }
    ],
    "sg:phone":"+1 201 224 0300",
    "sg:postcode":"07024",
    "sg:province":"NJ",
    "wof:name":"Allstate Insurance Co",
    "wof:placetype":"venue"
},
  "geometry": {"coordinates":[-73.979051,40.831612],"type":"Point"}
}