{
  "type": "Feature",
  "properties": {
    "addr:full":"100 Campus Dr Morganville NJ 07751",
    "addr:housenumber":"100",
    "addr:postcode":"07751",
    "addr:street":"Campus Dr",
    "iso:country":"US",
    "sg:address":"100 Campus Dr",
    "sg:city":"Morganville",
    "sg:classifiers":[
        {
            "category":"Professional",
            "subcategory":"Computer Services",
            "type":"Services"
        }
    ],
    "sg:phone":"+1 732 617 0202",
    "sg:postcode":"07751",
    "sg:province":"NJ",
    "sg:tags":[
        "consultant",
        "designer"
    ],
    "wof:name":"Quest Data LTD",
    "wof:placetype":"venue"
},
  "geometry": {"coordinates":[-74.289782,40.349402],"type":"Point"}
}