{
  "type": "Feature",
  "properties": {
    "addr:full":"398 Manila Ave Jersey City NJ 07302",
    "addr:housenumber":"398",
    "addr:postcode":"07302",
    "addr:street":"Manila Ave",
    "iso:country":"US",
    "sg:address":"398 Manila Ave",
    "sg:city":"Jersey City",
    "sg:classifiers":[
        {
            "category":"Organizations",
            "subcategory":"Religious Organization",
            "type":"Services"
        }
    ],
    "sg:phone":"+1 201 792 2987",
    "sg:postcode":"07302",
    "sg:province":"NJ",
    "sg:tags":[
        "church"
    ],
    "wof:name":"Puerto Rican Lutheran",
    "wof:placetype":"venue"
},
  "geometry": {"coordinates":[-74.042647,40.721653],"type":"Point"}
}