{
  "type": "Feature",
  "properties": {
    "iso:country":"US",
    "sg:address":"66 Burnt Hill Rd",
    "sg:city":"Skillman",
    "sg:classifiers":[
        {
            "category":"Building & Trades",
            "subcategory":"Construction",
            "type":"Services"
        }
    ],
    "sg:phone":"+1 609 466 1088",
    "sg:postcode":"08558",
    "sg:province":"NJ",
    "sg:tags":[
        "industrial",
        "nonresidential"
    ],
    "wof:name":"Haggan Corp",
    "wof:placetype":"venue"
},
  "geometry": {"coordinates":[-74.685175,40.409897],"type":"Point"}
}