{
  "type": "Feature",
  "properties": {
    "addr:full":"38 Carter Ln Marlton NJ 08009",
    "addr:housenumber":"38",
    "addr:postcode":"08009",
    "addr:street":"Carter Ln",
    "iso:country":"US",
    "sg:address":"38 Carter Ln",
    "sg:city":"Marlton",
    "sg:classifiers":[
        {
            "category":"Building & Trades",
            "subcategory":"Pest Control",
            "type":"Services"
        }
    ],
    "sg:phone":"+1 856 985 8077",
    "sg:postcode":"08009",
    "sg:province":"NJ",
    "wof:name":"Bio Safe Termite & Pest Ctrl",
    "wof:placetype":"venue"
},
  "geometry": {"coordinates":[-74.973696,39.772872],"type":"Point"}
}