{
  "type": "Feature",
  "properties": {
    "iso:country":"US",
    "sg:address":"117 E Main St",
    "sg:city":"Denville",
    "sg:classifiers":[
        {
            "category":"Professional",
            "subcategory":"Lawyer & Legal Services",
            "type":"Services"
        }
    ],
    "sg:phone":"+1 973 983 7783",
    "sg:postcode":"07834",
    "sg:province":"NJ",
    "wof:name":"Dattolo Angelo",
    "wof:placetype":"venue"
},
  "geometry": {"coordinates":[-74.478692,40.8892],"type":"Point"}
}