{
  "type": "Feature",
  "properties": {
    "iso:country":"US",
    "sg:address":"3600 Bergen Ct",
    "sg:city":"North Bergen",
    "sg:classifiers":[
        {
            "category":"Professional",
            "subcategory":"Management & Consulting",
            "type":"Services"
        }
    ],
    "sg:phone":"+1   ",
    "sg:postcode":"07047",
    "sg:province":"NJ",
    "wof:name":"Artech Solutions Inc",
    "wof:placetype":"venue"
},
  "geometry": {"coordinates":[-74.03240099999999,40.77675],"type":"Point"}
}