{
  "type": "Feature",
  "properties": {
    "iso:country":"US",
    "sg:address":"5926 Main St",
    "sg:city":"Mays Landing",
    "sg:classifiers":[
        {
            "category":"Shopping",
            "subcategory":"Florist",
            "type":"Retail Goods"
        },
        {
            "category":"Shopping",
            "subcategory":"Gifts & Souvenirs",
            "type":"Retail Goods"
        }
    ],
    "sg:phone":"+1 609 625 3500",
    "sg:postcode":"08330",
    "sg:province":"NJ",
    "sg:tags":[
        "balloon",
        "artist"
    ],
    "wof:name":"County Seat Florist Inc",
    "wof:placetype":"venue"
},
  "geometry": {"coordinates":[-74.726776,39.451732],"type":"Point"}
}