{
  "type": "Feature",
  "properties": {
    "iso:country":"US",
    "sg:address":"20 Marble Hill Rd",
    "sg:city":"Great Meadows",
    "sg:classifiers":[
        {
            "category":"Building & Trades",
            "subcategory":"Construction",
            "type":"Services"
        }
    ],
    "sg:phone":"+1 908 637 4028",
    "sg:postcode":"07838",
    "sg:province":"NJ",
    "sg:tags":[
        "carpentry",
        "contractor"
    ],
    "wof:name":"Cummins Buildings",
    "wof:placetype":"venue"
},
  "geometry": {"coordinates":[-74.953599,40.869981],"type":"Point"}
}