{
  "type": "Feature",
  "properties": {
    "iso:country":"US",
    "sg:address":"36 Virginia Ave",
    "sg:city":"Livingston",
    "sg:classifiers":[
        {
            "category":"Building & Trades",
            "subcategory":"Construction",
            "type":"Services"
        }
    ],
    "sg:phone":"+1 973 992 6310",
    "sg:postcode":"07039",
    "sg:province":"NJ",
    "sg:tags":[
        "house"
    ],
    "wof:name":"Nu State Remodeling",
    "wof:placetype":"venue"
},
  "geometry": {"coordinates":[-74.316795,40.795485],"type":"Point"}
}