{
  "type": "Feature",
  "properties": {
    "addr:full":"4 S 27th Ave Longport NJ 08403",
    "addr:housenumber":"4",
    "addr:postcode":"08403",
    "addr:street":"S 27Th Ave",
    "iso:country":"US",
    "sg:address":"4 S 27th Ave",
    "sg:city":"Longport",
    "sg:classifiers":[
        {
            "category":"Government",
            "subcategory":"Post Office",
            "type":"Public Place"
        }
    ],
    "sg:phone":"+1 609 823 1777",
    "sg:postcode":"08403",
    "sg:province":"NJ",
    "wof:name":"US Post Office",
    "wof:placetype":"venue"
},
  "geometry": {"coordinates":[-74.52496499999999,39.313084],"type":"Point"}
}