{
  "type": "Feature",
  "properties": {
    "addr:full":"380 Mountain Rd Apt 1213 Union City NJ 07087",
    "addr:housenumber":"380;1213",
    "addr:postcode":"07087",
    "addr:street":"Mountain Rd Apt",
    "iso:country":"US",
    "sg:address":"380 Mountain Rd Apt 1213",
    "sg:city":"Union City",
    "sg:classifiers":[
        {
            "category":"Real Estate",
            "subcategory":"Real Estate Operator",
            "type":"Services"
        }
    ],
    "sg:phone":"+1 201 865 6000",
    "sg:postcode":"07087",
    "sg:province":"NJ",
    "sg:tags":[
        "apartment"
    ],
    "sg:website":"www.troytowers.net",
    "wof:name":"Troy Towers-Union City",
    "wof:placetype":"venue"
},
  "geometry": {"coordinates":[-74.028801,40.761398],"type":"Point"}
}