{
  "type": "Feature",
  "properties": {
    "addr:full":"12 Brookview Rd Denville NJ 07834",
    "addr:housenumber":"12",
    "addr:postcode":"07834",
    "addr:street":"Brookview Rd",
    "iso:country":"US",
    "sg:address":"12 Brookview Rd",
    "sg:city":"Denville",
    "sg:classifiers":[
        {
            "category":"Manufacturing",
            "subcategory":"Retail Goods",
            "type":"Manufacturing & Wholesale Goods"
        }
    ],
    "sg:phone":"+1 973 586 8412",
    "sg:postcode":"07834",
    "sg:province":"NJ",
    "sg:tags":[
        "product",
        "mfg"
    ],
    "wof:name":"Fun On A String Pppets Mrnttes",
    "wof:placetype":"venue"
},
  "geometry": {"coordinates":[-74.461788,40.919185],"type":"Point"}
}