{
  "type": "Feature",
  "properties": {
    "addr:full":"2258 Morris Ave Union NJ 07083",
    "addr:housenumber":"2258",
    "addr:postcode":"07083",
    "addr:street":"Morris Ave",
    "iso:country":"US",
    "sg:address":"2258 Morris Ave",
    "sg:city":"Union",
    "sg:classifiers":[
        {
            "category":"Restaurant",
            "type":"Food & Drink"
        }
    ],
    "sg:phone":"+1 908 349 8411",
    "sg:postcode":"07083",
    "sg:province":"NJ",
    "sg:tags":[
        "mexican"
    ],
    "sg:website":"www.TheRedCadillacNJ.com",
    "wof:name":"The Red Cadillac",
    "wof:placetype":"venue"
},
  "geometry": {"coordinates":[-74.2814,40.6987],"type":"Point"}
}