{
  "type": "Feature",
  "properties": {
    "iso:country":"US",
    "sg:address":"2112 State Rte 70",
    "sg:city":"Manchester",
    "sg:classifiers":[
        {
            "category":"Shopping",
            "type":"Retail Goods"
        }
    ],
    "sg:phone":"+1 732 323 3000",
    "sg:postcode":"08733",
    "sg:province":"NJ",
    "sg:tags":[
        "cosmetic",
        "perfume"
    ],
    "wof:name":"Body Wrap Shoppe",
    "wof:placetype":"venue"
},
  "geometry": {"coordinates":[-74.26867300000001,40.023761],"type":"Point"}
}