{
  "type": "Feature",
  "properties": {
    "iso:country":"US",
    "sg:address":"2000 Gates Ct",
    "sg:city":"Morris Plains",
    "sg:classifiers":[
        {
            "category":"Professional",
            "type":"Services"
        }
    ],
    "sg:phone":"+1 732 797 1955",
    "sg:postcode":"07950",
    "sg:province":"NJ",
    "sg:tags":[
        "establishment"
    ],
    "wof:name":"Poly Mark Inc",
    "wof:placetype":"venue"
},
  "geometry": {"coordinates":[-74.48642700000001,40.848152],"type":"Point"}
}