{
  "type": "Feature",
  "properties": {
    "addr:full":"204 Kings Hwy S Cherry Hill NJ 08034",
    "addr:housenumber":"204",
    "addr:postcode":"08034",
    "addr:street":"Kings Hwy S",
    "iso:country":"US",
    "sg:address":"204 Kings Hwy S",
    "sg:city":"Cherry Hill",
    "sg:classifiers":[
        {
            "category":"Professional",
            "subcategory":"Detective & Security Services",
            "type":"Services"
        }
    ],
    "sg:phone":"+1 856 755 0622",
    "sg:postcode":"08034",
    "sg:province":"NJ",
    "sg:tags":[
        "investigator"
    ],
    "sg:website":"www.signalpiracy.com",
    "wof:name":"Signal Piracy Investigations",
    "wof:placetype":"venue"
},
  "geometry": {"coordinates":[-75.012035,39.91259],"type":"Point"}
}