{
  "type": "Feature",
  "properties": {
    "iso:country":"US",
    "sg:address":"56 Dorset Pl",
    "sg:city":"Somerdale",
    "sg:classifiers":[
        {
            "category":"Professional",
            "subcategory":"Computer Services",
            "type":"Services"
        }
    ],
    "sg:phone":"+1   ",
    "sg:postcode":"08083",
    "sg:province":"NJ",
    "sg:tags":[
        "datum"
    ],
    "wof:name":"Trops Web Design",
    "wof:placetype":"venue"
},
  "geometry": {"coordinates":[-75.047318,39.839373],"type":"Point"}
}