{
  "type": "Feature",
  "properties": {
    "iso:country":"US",
    "sg:address":"101 Broad St",
    "sg:city":"Elizabeth",
    "sg:classifiers":[
        {
            "category":"Wholesale",
            "subcategory":"Electrical",
            "type":"Manufacturing & Wholesale Goods"
        }
    ],
    "sg:phone":"+1 908 352 3656",
    "sg:postcode":"07201",
    "sg:province":"NJ",
    "sg:tags":[
        "electronic"
    ],
    "wof:name":"Broad Electronics",
    "wof:placetype":"venue"
},
  "geometry": {"coordinates":[-74.214989,40.666332],"type":"Point"}
}