{
  "type": "Feature",
  "properties": {
    "addr:full":"467 Marshall St Paterson NJ 07503",
    "addr:housenumber":"467",
    "addr:postcode":"07503",
    "addr:street":"Marshall St",
    "iso:country":"US",
    "sg:address":"467 Marshall St",
    "sg:city":"Paterson",
    "sg:classifiers":[
        {
            "category":"Autos & Motor Vehicles",
            "subcategory":"Automobile Sales",
            "type":"Retail Goods"
        }
    ],
    "sg:phone":"+1   ",
    "sg:postcode":"07503",
    "sg:province":"NJ",
    "sg:tags":[
        "used"
    ],
    "wof:name":"R Fierro & Sons Inc",
    "wof:placetype":"venue"
},
  "geometry": {"coordinates":[-74.167618,40.897224],"type":"Point"}
}