{
  "type": "Feature",
  "properties": {
    "addr:full":"1330 Parkway Ave Trenton NJ 08628",
    "addr:housenumber":"1330",
    "addr:postcode":"08628",
    "addr:street":"Parkway Ave",
    "iso:country":"US",
    "sg:address":"1330 Parkway Ave",
    "sg:city":"Trenton",
    "sg:classifiers":[
        {
            "category":"Health Services",
            "subcategory":"Clinic",
            "type":"Services"
        },
        {
            "category":"Social Services",
            "subcategory":"Job Training",
            "type":"Services"
        }
    ],
    "sg:phone":"+1 609 883 5541",
    "sg:postcode":"08628",
    "sg:province":"NJ",
    "sg:tags":[
        "rehabilitation",
        "outpatient",
        "specialty"
    ],
    "wof:name":"Vital Health Care LLC",
    "wof:placetype":"venue"
},
  "geometry": {"coordinates":[-74.80502199999999,40.265402],"type":"Point"}
}