{
  "type": "Feature",
  "properties": {
    "addr:full":"22 Church St Paterson NJ 07505",
    "addr:housenumber":"22",
    "addr:postcode":"07505",
    "addr:street":"Church St",
    "iso:country":"US",
    "sg:address":"22 Church St",
    "sg:city":"Paterson",
    "sg:classifiers":[
        {
            "category":"Shopping",
            "subcategory":"Gifts & Souvenirs",
            "type":"Retail Goods"
        }
    ],
    "sg:phone":"+1 973 279 0203",
    "sg:postcode":"07505",
    "sg:province":"NJ",
    "sg:tags":[
        "shop"
    ],
    "wof:name":"Gaby's Place",
    "wof:placetype":"venue"
},
  "geometry": {"coordinates":[-74.170486,40.917282],"type":"Point"}
}