{
  "type": "Feature",
  "properties": {
    "addr:full":"130 Mountain Ave Springfield NJ 07081",
    "addr:housenumber":"130",
    "addr:postcode":"07081",
    "addr:street":"Mountain Ave",
    "iso:country":"US",
    "sg:address":"130 Mountain Ave",
    "sg:city":"Springfield",
    "sg:classifiers":[
        {
            "category":"Banks & Credit Unions",
            "subcategory":"Bank",
            "type":"Services"
        }
    ],
    "sg:phone":"+1 973 564 9000",
    "sg:postcode":"07081",
    "sg:province":"NJ",
    "sg:tags":[
        "federal",
        "saving",
        "institution",
        "holding"
    ],
    "wof:name":"Pulaski Savings Bank",
    "wof:placetype":"venue"
},
  "geometry": {"coordinates":[-74.314796,40.7075],"type":"Point"}
}