{
  "type": "Feature",
  "properties": {
    "addr:full":"544 Freeman St Orange NJ 07050",
    "addr:housenumber":"544",
    "addr:postcode":"07050",
    "addr:street":"Freeman St",
    "iso:country":"US",
    "sg:address":"544 Freeman St",
    "sg:city":"Orange",
    "sg:classifiers":[
        {
            "category":"Museum",
            "type":"Entertainment"
        }
    ],
    "sg:phone":"+1 973 675 2787",
    "sg:postcode":"07050",
    "sg:province":"NJ",
    "sg:tags":[
        "information",
        "school",
        "art"
    ],
    "wof:name":"Arts Unbound Inc",
    "wof:placetype":"venue"
},
  "geometry": {"coordinates":[-74.244935,40.766222],"type":"Point"}
}