{
  "type": "Feature",
  "properties": {
    "addr:full":"325 Magnolia Pl Leonia NJ 07605",
    "addr:housenumber":"325",
    "addr:postcode":"07605",
    "addr:street":"Magnolia Pl",
    "iso:country":"US",
    "sg:address":"325 Magnolia Pl",
    "sg:city":"Leonia",
    "sg:classifiers":[
        {
            "category":"Social Services",
            "type":"Services"
        }
    ],
    "sg:phone":"+1 201 592 6628",
    "sg:postcode":"07605",
    "sg:province":"NJ",
    "sg:tags":[
        "counselor",
        "marriage",
        "family"
    ],
    "wof:name":"Marsha K Ontell",
    "wof:placetype":"venue"
},
  "geometry": {"coordinates":[-73.985463,40.862344],"type":"Point"}
}