{
  "type": "Feature",
  "properties": {
    "addr:full":"224 Broad St Bloomfield NJ 07003",
    "addr:housenumber":"224",
    "addr:postcode":"07003",
    "addr:street":"Broad St",
    "iso:country":"US",
    "sg:address":"224 Broad St",
    "sg:city":"Bloomfield",
    "sg:classifiers":[
        {
            "category":"Social Services",
            "type":"Services"
        },
        {
            "category":"Social Services",
            "subcategory":"Child Care",
            "type":"Services"
        }
    ],
    "sg:phone":"+1 973 743 6688",
    "sg:postcode":"07003",
    "sg:province":"NJ",
    "sg:tags":[
        "counseling",
        "community",
        "family",
        "day"
    ],
    "wof:name":"Family Day Nursery",
    "wof:placetype":"venue"
},
  "geometry": {"coordinates":[-74.195999,40.801701],"type":"Point"}
}