{
  "type": "Feature",
  "properties": {
    "addr:full":"14 Iroquois Ave Landing NJ 07850",
    "addr:housenumber":"14",
    "addr:postcode":"07850",
    "addr:street":"Iroquois Ave",
    "iso:country":"US",
    "sg:address":"14 Iroquois Ave",
    "sg:city":"Landing",
    "sg:classifiers":[
        {
            "category":"Professional",
            "type":"Services"
        }
    ],
    "sg:phone":"+1   ",
    "sg:postcode":"07850",
    "sg:province":"NJ",
    "wof:name":"Joy L Interior Painting",
    "wof:placetype":"venue"
},
  "geometry": {"coordinates":[-74.64476999999999,40.918017],"type":"Point"}
}