{
  "type": "Feature",
  "properties": {
    "iso:country":"US",
    "sg:address":"100 Long Branch Ave",
    "sg:city":"Long Branch",
    "sg:classifiers":[
        {
            "category":"Wholesale",
            "subcategory":"Office Equipment",
            "type":"Manufacturing & Wholesale Goods"
        }
    ],
    "sg:phone":"+1 732 222 0414",
    "sg:postcode":"07740",
    "sg:province":"NJ",
    "sg:tags":[
        "register",
        "cash",
        "supply"
    ],
    "sg:website":"www.talcopos.com",
    "wof:name":"Talco Cash Register Co",
    "wof:placetype":"venue"
},
  "geometry": {"coordinates":[-73.98275,40.306679],"type":"Point"}
}