{
  "type": "Feature",
  "properties": {
    "iso:country":"US",
    "sg:address":"1049 Broad St Ste 2",
    "sg:city":"Bloomfield",
    "sg:classifiers":[
        {
            "category":"Shopping",
            "subcategory":"Pharmacy",
            "type":"Retail Goods"
        }
    ],
    "sg:phone":"+1 973 338 7300",
    "sg:postcode":"07003",
    "sg:province":"NJ",
    "sg:tags":[
        "drugstore"
    ],
    "wof:name":"Terry Drugs",
    "wof:placetype":"venue"
},
  "geometry": {"coordinates":[-74.18699599999999,40.8284],"type":"Point"}
}