{
  "type": "Feature",
  "properties": {
    "iso:country":"US",
    "sg:address":"144 Main Rd",
    "sg:city":"Montville",
    "sg:classifiers":[
        {
            "category":"Wholesale",
            "subcategory":"Scrap",
            "type":"Manufacturing & Wholesale Goods"
        }
    ],
    "sg:phone":"+1 973 334 0073",
    "sg:postcode":"07045",
    "sg:province":"NJ",
    "sg:tags":[
        "metal",
        "iron"
    ],
    "wof:name":"V & V Recycling Inc",
    "wof:placetype":"venue"
},
  "geometry": {"coordinates":[-74.380517,40.915262],"type":"Point"}
}