{
  "type": "Feature",
  "properties": {
    "addr:full":"631 S Broad St Elizabeth NJ 07202",
    "addr:housenumber":"631",
    "addr:postcode":"07202",
    "addr:street":"S Broad St",
    "iso:country":"US",
    "sg:address":"631 S Broad St",
    "sg:city":"Elizabeth",
    "sg:classifiers":[
        {
            "category":"Professional",
            "subcategory":"Lawyer & Legal Services",
            "type":"Services"
        }
    ],
    "sg:phone":"+1 908 282 6800",
    "sg:postcode":"07202",
    "sg:province":"NJ",
    "wof:name":"Marshall Law Firm",
    "wof:placetype":"venue"
},
  "geometry": {"coordinates":[-74.21625400000001,40.649227],"type":"Point"}
}