{
  "type": "Feature",
  "properties": {
    "addr:full":"101 Heilman Ave Bridgeport NJ 08014",
    "addr:housenumber":"101",
    "addr:postcode":"08014",
    "addr:street":"Heilman Ave",
    "iso:country":"US",
    "sg:address":"101 Heilman Ave",
    "sg:city":"Bridgeport",
    "sg:classifiers":[
        {
            "category":"Utilities",
            "subcategory":"Mobile Phone",
            "type":"Services"
        }
    ],
    "sg:phone":"+1 856 467 5614",
    "sg:postcode":"08014",
    "sg:province":"NJ",
    "sg:tags":[
        "telephone",
        "cellular"
    ],
    "wof:name":"Cingular Wireless",
    "wof:placetype":"venue"
},
  "geometry": {"coordinates":[-75.343805,39.80206],"type":"Point"}
}