{
  "type": "Feature",
  "properties": {
    "iso:country":"US",
    "sg:address":"296 Main St",
    "sg:city":"West Orange",
    "sg:classifiers":[
        {
            "category":"Travel",
            "subcategory":"Travel Agent",
            "type":"Entertainment"
        }
    ],
    "sg:phone":"+1 973 325 0777",
    "sg:postcode":"07052",
    "sg:province":"NJ",
    "sg:tags":[
        "agency",
        "bureau"
    ],
    "wof:name":"Genesis Travel Svc",
    "wof:placetype":"venue"
},
  "geometry": {"coordinates":[-74.23128699999999,40.787465],"type":"Point"}
}