{
  "type": "Feature",
  "properties": {
    "iso:country":"US",
    "sg:address":"34 Marudy Dr",
    "sg:city":"Clinton",
    "sg:classifiers":[
        {
            "category":"Professional",
            "subcategory":"Secretarial Services",
            "type":"Services"
        }
    ],
    "sg:phone":"+1 908 735 8648",
    "sg:postcode":"08809",
    "sg:province":"NJ",
    "sg:tags":[
        "typing"
    ],
    "wof:name":"Final Word",
    "wof:placetype":"venue"
},
  "geometry": {"coordinates":[-74.919118,40.632979],"type":"Point"}
}