{
  "type": "Feature",
  "properties": {
    "iso:country":"US",
    "sg:address":"301 N Harrison St",
    "sg:city":"Princeton",
    "sg:classifiers":[
        {
            "category":"Professional",
            "subcategory":"Advertising",
            "type":"Services"
        }
    ],
    "sg:phone":"+1 609 514 8700",
    "sg:postcode":"08540",
    "sg:province":"NJ",
    "sg:tags":[
        "counselor"
    ],
    "wof:name":"Princeton Media Inc",
    "wof:placetype":"venue"
},
  "geometry": {"coordinates":[-74.654293,40.365845],"type":"Point"}
}