{
  "type": "Feature",
  "properties": {
    "addr:full":"300 Main St Chatham NJ 07928",
    "addr:housenumber":"300",
    "addr:postcode":"07928",
    "addr:street":"Main St",
    "iso:country":"US",
    "sg:address":"300 Main St",
    "sg:city":"Chatham",
    "sg:classifiers":[
        {
            "category":"Health Services",
            "subcategory":"Doctor",
            "type":"Services"
        }
    ],
    "sg:phone":"+1 973 635 4960",
    "sg:postcode":"07928",
    "sg:province":"NJ",
    "sg:tags":[
        "dentist"
    ],
    "wof:name":"Miller Caryn F DMD",
    "wof:placetype":"venue"
},
  "geometry": {"coordinates":[-74.383797,40.7411],"type":"Point"}
}