{
  "type": "Feature",
  "properties": {
    "iso:country":"US",
    "sg:address":"176 Mount Pleasant Ave",
    "sg:city":"Newark",
    "sg:classifiers":[
        {
            "category":"Organizations",
            "subcategory":"Religious Organization",
            "type":"Services"
        }
    ],
    "sg:phone":"+1 973 482 8544",
    "sg:postcode":"07104",
    "sg:province":"NJ",
    "wof:name":"Immanuel Love Fellowship Center",
    "wof:placetype":"venue"
},
  "geometry": {"coordinates":[-74.168198,40.755402],"type":"Point"}
}