{
  "type": "Feature",
  "properties": {
    "iso:country":"US",
    "sg:address":"96 Vones Ln",
    "sg:city":"Raritan",
    "sg:classifiers":[
        {
            "category":"Building & Trades",
            "subcategory":"Construction",
            "type":"Services"
        }
    ],
    "sg:phone":"+1 908 722 4506",
    "sg:postcode":"08869",
    "sg:province":"NJ",
    "sg:tags":[
        "house"
    ],
    "wof:name":"Tozzi Construction",
    "wof:placetype":"venue"
},
  "geometry": {"coordinates":[-74.65392300000001,40.582438],"type":"Point"}
}