{
  "type": "Feature",
  "properties": {
    "addr:full":"527 Belmont Ave Haledon NJ 07508",
    "addr:housenumber":"527",
    "addr:postcode":"07508",
    "addr:street":"Belmont Ave",
    "iso:country":"US",
    "sg:address":"527 Belmont Ave",
    "sg:city":"Haledon",
    "sg:classifiers":[
        {
            "category":"Shopping",
            "type":"Retail Goods"
        }
    ],
    "sg:phone":"+1   ",
    "sg:postcode":"07508",
    "sg:province":"NJ",
    "sg:tags":[
        "merchandise"
    ],
    "wof:name":"Fish Tank Man Aqar Discounts",
    "wof:placetype":"venue"
},
  "geometry": {"coordinates":[-74.185425,40.942685],"type":"Point"}
}