{
  "type": "Feature",
  "properties": {
    "iso:country":"US",
    "sg:address":"49 Broadway",
    "sg:city":"Newark",
    "sg:classifiers":[
        {
            "category":"Building & Trades",
            "subcategory":"Locksmith",
            "type":"Services"
        }
    ],
    "sg:phone":"+1 973 854 5369",
    "sg:postcode":"07104",
    "sg:province":"NJ",
    "sg:tags":[
        "key"
    ],
    "wof:name":"0 24 Hour 7 A Day Emerg Locksmith",
    "wof:placetype":"venue"
},
  "geometry": {"coordinates":[-74.17045899999999,40.7518],"type":"Point"}
}