{
  "type": "Feature",
  "properties": {
    "addr:full":"253 Privateer Rd Manahawkin NJ 08050",
    "addr:housenumber":"253",
    "addr:postcode":"08050",
    "addr:street":"Privateer Rd",
    "iso:country":"US",
    "sg:address":"253 Privateer Rd",
    "sg:city":"Manahawkin",
    "sg:classifiers":[
        {
            "category":"Professional",
            "subcategory":"Business Services",
            "type":"Services"
        }
    ],
    "sg:phone":"+1 609 698 0946",
    "sg:postcode":"08050",
    "sg:province":"NJ",
    "sg:tags":[
        "pool",
        "swimming"
    ],
    "wof:name":"Wasilko Pools Swimming Pools",
    "wof:placetype":"venue"
},
  "geometry": {"coordinates":[-74.29137299999999,39.736912],"type":"Point"}
}