{
  "type": "Feature",
  "properties": {
    "addr:full":"420 Kuller Rd Clifton NJ 07011",
    "addr:housenumber":"420",
    "addr:postcode":"07011",
    "addr:street":"Kuller Rd",
    "iso:country":"US",
    "sg:address":"420 Kuller Rd",
    "sg:city":"Clifton",
    "sg:classifiers":[
        {
            "category":"Health Services",
            "subcategory":"Doctor",
            "type":"Services"
        }
    ],
    "sg:phone":"+1 973 340 2500",
    "sg:postcode":"07011",
    "sg:province":"NJ",
    "wof:name":"Tri-State Orthopedic",
    "wof:placetype":"venue"
},
  "geometry": {"coordinates":[-74.163498,40.880402],"type":"Point"}
}