{
  "type": "Feature",
  "properties": {
    "iso:country":"US",
    "sg:address":"235 Bloomfield Ave",
    "sg:city":"Caldwell",
    "sg:classifiers":[
        {
            "category":"Education",
            "subcategory":"School",
            "type":"Public Place"
        }
    ],
    "sg:phone":"+1 973 226 3386",
    "sg:postcode":"07006",
    "sg:province":"NJ",
    "sg:tags":[
        "elementary"
    ],
    "wof:name":"Trinity Academy",
    "wof:placetype":"venue"
},
  "geometry": {"coordinates":[-74.27419999999999,40.838299],"type":"Point"}
}