{
  "type": "Feature",
  "properties": {
    "addr:full":"9 Edgewood Pl Flanders NJ 07836",
    "addr:housenumber":"9",
    "addr:postcode":"07836",
    "addr:street":"Edgewood Pl",
    "iso:country":"US",
    "sg:address":"9 Edgewood Pl",
    "sg:city":"Flanders",
    "sg:classifiers":[
        {
            "category":"Personal",
            "subcategory":"Beauty Salon",
            "type":"Services"
        }
    ],
    "sg:phone":"+1 973 584 1316",
    "sg:postcode":"07836",
    "sg:province":"NJ",
    "sg:tags":[
        "manicuring"
    ],
    "wof:name":"Salon Professionails",
    "wof:placetype":"venue"
},
  "geometry": {"coordinates":[-74.70274999999999,40.830411],"type":"Point"}
}