{
  "type": "Feature",
  "properties": {
    "addr:full":"7 Edgar St Summit NJ 07901",
    "addr:housenumber":"7",
    "addr:postcode":"07901",
    "addr:street":"Edgar St",
    "iso:country":"US",
    "sg:address":"7 Edgar St",
    "sg:city":"Summit",
    "sg:classifiers":[
        {
            "category":"Professional",
            "subcategory":"Testing Lab",
            "type":"Services"
        }
    ],
    "sg:phone":"+1   ",
    "sg:postcode":"07901",
    "sg:province":"NJ",
    "sg:tags":[
        "laboratory"
    ],
    "wof:name":"Harrison Trading Company",
    "wof:placetype":"venue"
},
  "geometry": {"coordinates":[-74.369523,40.72011],"type":"Point"}
}