{
  "type": "Feature",
  "properties": {
    "addr:full":"540 Hunters Rd Brick NJ 08724",
    "addr:housenumber":"540",
    "addr:postcode":"08724",
    "addr:street":"Hunters Rd",
    "iso:country":"US",
    "sg:address":"540 Hunters Rd",
    "sg:city":"Brick",
    "sg:classifiers":[
        {
            "category":"Professional",
            "subcategory":"Management & Consulting",
            "type":"Services"
        }
    ],
    "sg:phone":"+1   ",
    "sg:postcode":"08724",
    "sg:province":"NJ",
    "wof:name":"Eagle Land Services Inc",
    "wof:placetype":"venue"
},
  "geometry": {"coordinates":[-74.087735,40.062154],"type":"Point"}
}