{
  "type": "Feature",
  "properties": {
    "addr:full":"178 Rutherford Blvd Clifton NJ 07014",
    "addr:housenumber":"178",
    "addr:postcode":"07014",
    "addr:street":"Rutherford Blvd",
    "iso:country":"US",
    "sg:address":"178 Rutherford Blvd",
    "sg:city":"Clifton",
    "sg:classifiers":[
        {
            "category":"Professional",
            "subcategory":"Detective & Security Services",
            "type":"Services"
        }
    ],
    "sg:phone":"+1   ",
    "sg:postcode":"07014",
    "sg:province":"NJ",
    "sg:tags":[
        "inspection",
        "cause",
        "determination"
    ],
    "wof:name":"Fire Inspector Services",
    "wof:placetype":"venue"
},
  "geometry": {"coordinates":[-74.129046,40.836434],"type":"Point"}
}