{
  "type": "Feature",
  "properties": {
    "iso:country":"US",
    "sg:address":"150 Garrabrant Ave",
    "sg:city":"Bloomfield",
    "sg:classifiers":[
        {
            "category":"Education",
            "subcategory":"School",
            "type":"Public Place"
        }
    ],
    "sg:phone":"+1 973 680 8590",
    "sg:postcode":"07003",
    "sg:province":"NJ",
    "sg:tags":[
        "high",
        "middle",
        "elementary"
    ],
    "wof:name":"Bloomfield Township of",
    "wof:placetype":"venue"
},
  "geometry": {"coordinates":[-74.172051,40.839926],"type":"Point"}
}