{
  "type": "Feature",
  "properties": {
    "addr:full":"4 Cary Ct Egg Harbor Twp NJ 08234",
    "addr:housenumber":"4",
    "addr:postcode":"08234",
    "addr:street":"Cary Ct",
    "iso:country":"US",
    "sg:address":"4 Cary Ct",
    "sg:city":"Egg Harbor Twp",
    "sg:classifiers":[
        {
            "category":"Professional",
            "subcategory":"Art Services",
            "type":"Services"
        }
    ],
    "sg:phone":"+1 609 653 8008",
    "sg:postcode":"08234",
    "sg:province":"NJ",
    "sg:tags":[
        "graphic",
        "design",
        "designer"
    ],
    "sg:website":"www.graphicpyramid.com",
    "wof:name":"Graphic Pyramid",
    "wof:placetype":"venue"
},
  "geometry": {"coordinates":[-74.59785599999999,39.382099],"type":"Point"}
}