{
  "type": "Feature",
  "properties": {
    "iso:country":"US",
    "sg:address":"212 Bellevue Ave",
    "sg:city":"Hammonton",
    "sg:classifiers":[
        {
            "category":"Retail",
            "subcategory":"Photofinishing",
            "type":"Services"
        }
    ],
    "sg:phone":"+1   ",
    "sg:postcode":"08037",
    "sg:province":"NJ",
    "sg:tags":[
        "laboratory"
    ],
    "wof:name":"Photo Center",
    "wof:placetype":"venue"
},
  "geometry": {"coordinates":[-74.802988,39.636263],"type":"Point"}
}