{
  "type": "Feature",
  "properties": {
    "addr:full":"845 Springfield Ave Irvington NJ 07111",
    "addr:housenumber":"845",
    "addr:postcode":"07111",
    "addr:street":"Springfield Ave",
    "iso:country":"US",
    "sg:address":"845 Springfield Ave",
    "sg:city":"Irvington",
    "sg:classifiers":[
        {
            "category":"Restaurant",
            "type":"Food & Drink"
        }
    ],
    "sg:menulink":"http://www.allmenus.com/nj/irvington/146100-subway/menu/",
    "sg:phone":"+1 973 374 3500",
    "sg:postcode":"07111",
    "sg:province":"NJ",
    "sg:tags":[
        "american",
        "sandwich"
    ],
    "wof:name":"Subway",
    "wof:placetype":"venue"
},
  "geometry": {"coordinates":[-74.22070600000001,40.728168],"type":"Point"}
}