{
  "type": "Feature",
  "properties": {
    "iso:country":"US",
    "sg:address":"152 Colonial Dr",
    "sg:city":"Lakewood",
    "sg:classifiers":[
        {
            "category":"Wholesale",
            "subcategory":"Durable Goods & Equipment",
            "type":"Manufacturing & Wholesale Goods"
        }
    ],
    "sg:phone":"+1 732 363 0163",
    "sg:postcode":"08701",
    "sg:province":"NJ",
    "wof:name":"Clean TEC Supplies LLC",
    "wof:placetype":"venue"
},
  "geometry": {"coordinates":[-74.21575900000001,40.052241],"type":"Point"}
}