{
  "type": "Feature",
  "properties": {
    "addr:full":"137 Boehmhurst Ave Sayreville NJ 08872",
    "addr:housenumber":"137",
    "addr:postcode":"08872",
    "addr:street":"Boehmhurst Ave",
    "iso:country":"US",
    "sg:address":"137 Boehmhurst Ave",
    "sg:city":"Sayreville",
    "sg:classifiers":[
        {
            "category":"Building & Trades",
            "subcategory":"Construction",
            "type":"Services"
        }
    ],
    "sg:phone":"+1 732 238 3690",
    "sg:postcode":"08872",
    "sg:province":"NJ",
    "sg:tags":[
        "house"
    ],
    "wof:name":"Dennis J Coyle General Contr",
    "wof:placetype":"venue"
},
  "geometry": {"coordinates":[-74.340791,40.476563],"type":"Point"}
}