{
  "type": "Feature",
  "properties": {
    "addr:full":"519 2nd Ave Long Branch NJ 07740",
    "addr:housenumber":"519",
    "addr:postcode":"07740",
    "addr:street":"2Nd Ave",
    "iso:country":"US",
    "sg:address":"519 2nd Ave",
    "sg:city":"Long Branch",
    "sg:classifiers":[
        {
            "category":"Professional",
            "type":"Services"
        }
    ],
    "sg:phone":"+1   ",
    "sg:postcode":"07740",
    "sg:province":"NJ",
    "wof:name":"Michael A Unger",
    "wof:placetype":"venue"
},
  "geometry": {"coordinates":[-73.985325,40.287654],"type":"Point"}
}