{
  "type": "Feature",
  "properties": {
    "iso:country":"US",
    "sg:address":"12 Henley Pl",
    "sg:city":"Pennington",
    "sg:classifiers":[
        {
            "category":"Professional",
            "subcategory":"Advertising",
            "type":"Services"
        }
    ],
    "sg:phone":"+1 609 730 4104",
    "sg:postcode":"08534",
    "sg:province":"NJ",
    "sg:tags":[
        "representative"
    ],
    "wof:name":"Mark World Assoc Inc",
    "wof:placetype":"venue"
},
  "geometry": {"coordinates":[-74.763794,40.30739],"type":"Point"}
}