{
  "type": "Feature",
  "properties": {
    "iso:country":"US",
    "sg:address":"219 Gregory Ave",
    "sg:city":"Passaic",
    "sg:classifiers":[
        {
            "category":"Wholesale",
            "subcategory":"Non-durable Goods",
            "type":"Manufacturing & Wholesale Goods"
        }
    ],
    "sg:phone":"+1 973 778 4398",
    "sg:postcode":"07055",
    "sg:province":"NJ",
    "wof:name":"Keashfa Import & Export",
    "wof:placetype":"venue"
},
  "geometry": {"coordinates":[-74.129341,40.858435],"type":"Point"}
}