{
  "type": "Feature",
  "properties": {
    "iso:country":"US",
    "sg:address":"25 Division St",
    "sg:city":"Jersey City",
    "sg:classifiers":[
        {
            "category":"Retail",
            "subcategory":"Auto Repair",
            "type":"Services"
        }
    ],
    "sg:phone":"+1 201 239 0600",
    "sg:postcode":"07302",
    "sg:province":"NJ",
    "wof:name":"Punjab Auto Repair",
    "wof:placetype":"venue"
},
  "geometry": {"coordinates":[-74.051804,40.726799],"type":"Point"}
}