{
  "type": "Feature",
  "properties": {
    "iso:country":"US",
    "sg:address":"2645 Nottingham Way",
    "sg:city":"Trenton",
    "sg:classifiers":[
        {
            "category":"Personal",
            "subcategory":"Beauty Salon",
            "type":"Services"
        }
    ],
    "sg:phone":"+1 609 587 3611",
    "sg:postcode":"08619",
    "sg:province":"NJ",
    "sg:tags":[
        "nail",
        "manicuring"
    ],
    "wof:name":"Spa Nails",
    "wof:placetype":"venue"
},
  "geometry": {"coordinates":[-74.690634,40.235747],"type":"Point"}
}