{
  "type": "Feature",
  "properties": {
    "iso:country":"US",
    "sg:address":"4030 US Hwy 1",
    "sg:city":"Monmouth Jct",
    "sg:classifiers":[
        {
            "category":"Home & Garden",
            "subcategory":"Furniture",
            "type":"Retail Goods"
        }
    ],
    "sg:phone":"+1 732 951 9000",
    "sg:postcode":"08852",
    "sg:province":"NJ",
    "wof:name":"LA-Z-Boy Furntiure Galleries",
    "wof:placetype":"venue"
},
  "geometry": {"coordinates":[-74.556713,40.398342],"type":"Point"}
}