{
  "type": "Feature",
  "properties": {
    "iso:country":"US",
    "sg:address":"455 Hillsdale Ave",
    "sg:city":"Hillsdale",
    "sg:classifiers":[
        {
            "category":"Shopping",
            "subcategory":"Pets & Pet Supplies",
            "type":"Retail Goods"
        }
    ],
    "sg:phone":"+1 201 664 4000",
    "sg:postcode":"07642",
    "sg:province":"NJ",
    "sg:tags":[
        "feed"
    ],
    "wof:name":"Fornazor International, Inc.",
    "wof:placetype":"venue"
},
  "geometry": {"coordinates":[-74.04304399999999,41.002604],"type":"Point"}
}