{
  "type": "Feature",
  "properties": {
    "addr:full":"598 Central Ave New Providence NJ 07974",
    "addr:housenumber":"598",
    "addr:postcode":"07974",
    "addr:street":"Central Ave",
    "iso:country":"US",
    "sg:address":"598 Central Ave",
    "sg:city":"New Providence",
    "sg:classifiers":[
        {
            "category":"Food & Beverages",
            "subcategory":"Bakery",
            "type":"Retail Goods"
        }
    ],
    "sg:phone":"+1 908 508 0500",
    "sg:postcode":"07974",
    "sg:province":"NJ",
    "sg:tags":[
        "sandwich"
    ],
    "sg:website":"www.tables4two.com",
    "wof:name":"Tables For Two Panini Cafe",
    "wof:placetype":"venue"
},
  "geometry": {"coordinates":[-74.405084,40.697245],"type":"Point"}
}