{
  "type": "Feature",
  "properties": {
    "addr:full":"32 W Prospect St Waldwick NJ 07463",
    "addr:housenumber":"32",
    "addr:postcode":"07463",
    "addr:street":"W Prospect St",
    "iso:country":"US",
    "sg:address":"32 W Prospect St",
    "sg:city":"Waldwick",
    "sg:classifiers":[
        {
            "category":"Building & Trades",
            "subcategory":"Landscaping Services",
            "type":"Services"
        }
    ],
    "sg:phone":"+1 201 493 8360",
    "sg:postcode":"07463",
    "sg:province":"NJ",
    "sg:tags":[
        "lawn",
        "maintenance",
        "grounds"
    ],
    "wof:name":"J & O Landscaping",
    "wof:placetype":"venue"
},
  "geometry": {"coordinates":[-74.122445,41.011533],"type":"Point"}
}