{
  "type": "Feature",
  "properties": {
    "iso:country":"US",
    "sg:address":"13 S Gables Dr",
    "sg:city":"Chester",
    "sg:classifiers":[
        {
            "category":"Professional",
            "subcategory":"Management & Consulting",
            "type":"Services"
        }
    ],
    "sg:phone":"+1 908 879 9201",
    "sg:postcode":"07930",
    "sg:province":"NJ",
    "sg:tags":[
        "consultant"
    ],
    "wof:name":"B K Patnaik Assoc",
    "wof:placetype":"venue"
},
  "geometry": {"coordinates":[-74.645639,40.805185],"type":"Point"}
}