{
  "type": "Feature",
  "properties": {
    "addr:full":"56 Terrace Ave Hasbrouck Heights NJ 07604",
    "addr:housenumber":"56",
    "addr:postcode":"07604",
    "addr:street":"Terrace Ave",
    "iso:country":"US",
    "sg:address":"56 Terrace Ave",
    "sg:city":"Hasbrouck Heights",
    "sg:classifiers":[
        {
            "category":"Building & Trades",
            "subcategory":"Locksmith",
            "type":"Services"
        }
    ],
    "sg:phone":"+1 888 403 8828",
    "sg:postcode":"07604",
    "sg:province":"NJ",
    "sg:tags":[
        "key"
    ],
    "wof:name":"Always Available 24 Hour Emergency Locksmith",
    "wof:placetype":"venue"
},
  "geometry": {"coordinates":[-74.077349,40.852691],"type":"Point"}
}