{
  "type": "Feature",
  "properties": {
    "iso:country":"US",
    "sg:address":"1001 Berlin Rd N",
    "sg:city":"Lindenwold",
    "sg:classifiers":[
        {
            "category":"Restaurant",
            "type":"Food & Drink"
        }
    ],
    "sg:phone":"+1 856 783 4544",
    "sg:postcode":"08021",
    "sg:province":"NJ",
    "wof:name":"Pufferbelly",
    "wof:placetype":"venue"
},
  "geometry": {"coordinates":[-74.994624,39.828885],"type":"Point"}
}