{
  "type": "Feature",
  "properties": {
    "iso:country":"US",
    "sg:address":"12 Aspen Way",
    "sg:city":"Morristown",
    "sg:classifiers":[
        {
            "category":"Professional",
            "subcategory":"Management & Consulting",
            "type":"Services"
        }
    ],
    "sg:phone":"+1 973 267 2509",
    "sg:postcode":"07960",
    "sg:province":"NJ",
    "wof:name":"Presciens",
    "wof:placetype":"venue"
},
  "geometry": {"coordinates":[-74.49837100000001,40.776949],"type":"Point"}
}