{
  "type": "Feature",
  "properties": {
    "iso:country":"US",
    "sg:address":"829 Broad St",
    "sg:city":"Newark",
    "sg:classifiers":[
        {
            "category":"Shopping",
            "subcategory":"Bicycles & Sporting Goods",
            "type":"Retail Goods"
        }
    ],
    "sg:phone":"+1 973 622 3569",
    "sg:postcode":"07102",
    "sg:province":"NJ",
    "wof:name":"World Sneakers Inc",
    "wof:placetype":"venue"
},
  "geometry": {"coordinates":[-74.173355,40.73368],"type":"Point"}
}