{
  "type": "Feature",
  "properties": {
    "iso:country":"US",
    "sg:address":"11 John St",
    "sg:city":"Kearny",
    "sg:classifiers":[
        {
            "category":"Freight",
            "type":"Transportation"
        }
    ],
    "sg:phone":"+1 201 997 4500",
    "sg:postcode":"07032",
    "sg:province":"NJ",
    "sg:tags":[
        "general"
    ],
    "wof:name":"Mace Brothers Fine Furniture",
    "wof:placetype":"venue"
},
  "geometry": {"coordinates":[-74.159058,40.754686],"type":"Point"}
}