{
  "type": "Feature",
  "properties": {
    "iso:country":"US",
    "sg:address":"929 Main St",
    "sg:city":"Paterson",
    "sg:classifiers":[
        {
            "category":"Food & Beverages",
            "subcategory":"Liquor & Beverages",
            "type":"Retail Goods"
        }
    ],
    "sg:phone":"+1 973 523 3834",
    "sg:postcode":"07503",
    "sg:province":"NJ",
    "sg:tags":[
        "beer",
        "ale",
        "spirit",
        "wine"
    ],
    "wof:name":"Edward's Wines & Liquors Inc",
    "wof:placetype":"venue"
},
  "geometry": {"coordinates":[-74.1604,40.895802],"type":"Point"}
}