{
  "type": "Feature",
  "properties": {
    "iso:country":"US",
    "sg:address":"67 Willowbrook Blvd",
    "sg:city":"Wayne",
    "sg:classifiers":[
        {
            "category":"Cinema",
            "subcategory":"Movie Theater",
            "type":"Entertainment"
        }
    ],
    "sg:phone":"+1 973 890 0505",
    "sg:postcode":"07470",
    "sg:province":"NJ",
    "wof:name":"AMC Theaters - Loews Wayne 14",
    "wof:placetype":"venue"
},
  "geometry": {"coordinates":[-74.250603,40.888699],"type":"Point"}
}