{
  "type": "Feature",
  "properties": {
    "iso:country":"US",
    "sg:address":"404 State Rte 70",
    "sg:city":"Cherry Hill",
    "sg:classifiers":[
        {
            "category":"Food & Beverages",
            "subcategory":"Meat & Fish",
            "type":"Retail Goods"
        }
    ],
    "sg:phone":"+1 856 429 3398",
    "sg:postcode":"08002",
    "sg:province":"NJ",
    "sg:tags":[
        "seafood"
    ],
    "wof:name":"Alexs Seafood & Good Eat",
    "wof:placetype":"venue"
},
  "geometry": {"coordinates":[-75.016261,39.915204],"type":"Point"}
}