{
  "type": "Feature",
  "properties": {
    "addr:full":"1115 State Rte 35 Deal NJ 07702",
    "addr:housenumber":"1115",
    "addr:postcode":"07702",
    "addr:street":"State Rte 35",
    "iso:country":"US",
    "sg:address":"1115 State Rte 35",
    "sg:city":"Deal",
    "sg:classifiers":[
        {
            "category":"Retail",
            "subcategory":"Auto Repair",
            "type":"Services"
        }
    ],
    "sg:phone":"+1 732 531 1222",
    "sg:postcode":"07702",
    "sg:province":"NJ",
    "sg:tags":[
        "automobile",
        "lubrication"
    ],
    "wof:name":"Mr Good Lube Inc",
    "wof:placetype":"venue"
},
  "geometry": {"coordinates":[-74.06321699999999,40.314877],"type":"Point"}
}