{
  "type": "Feature",
  "properties": {
    "iso:country":"US",
    "sg:address":"728 Boonton Ave",
    "sg:city":"Boonton",
    "sg:classifiers":[
        {
            "category":"Professional",
            "subcategory":"Computer Services",
            "type":"Services"
        }
    ],
    "sg:phone":"+1   ",
    "sg:postcode":"07005",
    "sg:province":"NJ",
    "sg:tags":[
        "related"
    ],
    "wof:name":"Voytek Technology Inc",
    "wof:placetype":"venue"
},
  "geometry": {"coordinates":[-74.40460299999999,40.914736],"type":"Point"}
}