{
  "type": "Feature",
  "properties": {
    "addr:full":"50 Byrd Ave Bloomfield NJ 07003",
    "addr:housenumber":"50",
    "addr:postcode":"07003",
    "addr:street":"Byrd Ave",
    "iso:country":"US",
    "sg:address":"50 Byrd Ave",
    "sg:city":"Bloomfield",
    "sg:classifiers":[
        {
            "category":"Education",
            "subcategory":"School",
            "type":"Public Place"
        }
    ],
    "sg:phone":"+1 973 338 8505",
    "sg:postcode":"07003",
    "sg:province":"NJ",
    "sg:tags":[
        "high",
        "middle",
        "elementary"
    ],
    "wof:name":"St Thomas the Apostle Church",
    "wof:placetype":"venue"
},
  "geometry": {"coordinates":[-74.177696,40.832199],"type":"Point"}
}