{
  "type": "Feature",
  "properties": {
    "addr:full":"284 Marlton Ave Camden NJ 08105",
    "addr:housenumber":"284",
    "addr:postcode":"08105",
    "addr:street":"Marlton Ave",
    "iso:country":"US",
    "sg:address":"284 Marlton Ave",
    "sg:city":"Camden",
    "sg:classifiers":[
        {
            "category":"Food & Beverages",
            "subcategory":"Fruits & Vegetables",
            "type":"Retail Goods"
        }
    ],
    "sg:phone":"+1   ",
    "sg:postcode":"08105",
    "sg:province":"NJ",
    "wof:name":"Sconiers Produce",
    "wof:placetype":"venue"
},
  "geometry": {"coordinates":[-75.087124,39.942687],"type":"Point"}
}