{
  "type": "Feature",
  "properties": {
    "iso:country":"US",
    "sg:address":"57 Mill St",
    "sg:city":"Paterson",
    "sg:classifiers":[
        {
            "category":"Bars & Pubs",
            "type":"Food & Drink"
        }
    ],
    "sg:phone":"+1 973 345 3083",
    "sg:postcode":"07501",
    "sg:province":"NJ",
    "wof:name":"Charles Restaurant & Bar",
    "wof:placetype":"venue"
},
  "geometry": {"coordinates":[-74.176131,40.913883],"type":"Point"}
}