{
  "type": "Feature",
  "properties": {
    "addr:full":"2117 Bay Ave Ocean City NJ 08226",
    "addr:housenumber":"2117",
    "addr:postcode":"08226",
    "addr:street":"Bay Ave",
    "iso:country":"US",
    "sg:address":"2117 Bay Ave",
    "sg:city":"Ocean City",
    "sg:classifiers":[
        {
            "category":"Health Services",
            "subcategory":"Doctor",
            "type":"Services"
        }
    ],
    "sg:phone":"+1   ",
    "sg:postcode":"08226",
    "sg:province":"NJ",
    "sg:tags":[
        "medical"
    ],
    "wof:name":"Steven Fenichel MD",
    "wof:placetype":"venue"
},
  "geometry": {"coordinates":[-74.59669100000001,39.268369],"type":"Point"}
}