{
  "type": "Feature",
  "properties": {
    "iso:country":"US",
    "sg:address":"11 Everdale Rd",
    "sg:city":"Randolph",
    "sg:classifiers":[
        {
            "category":"Building & Trades",
            "subcategory":"Construction",
            "type":"Services"
        }
    ],
    "sg:phone":"+1 973 366 8870",
    "sg:postcode":"07869",
    "sg:province":"NJ",
    "sg:tags":[
        "masonry",
        "contractor"
    ],
    "wof:name":"Amjo Construction Corp",
    "wof:placetype":"venue"
},
  "geometry": {"coordinates":[-74.546969,40.852917],"type":"Point"}
}