{
  "type": "Feature",
  "properties": {
    "iso:country":"US",
    "sg:address":"4903 Lake Rd",
    "sg:city":"Newfield",
    "sg:classifiers":[
        {
            "category":"Freight",
            "type":"Transportation"
        }
    ],
    "sg:phone":"+1 856 767 9400",
    "sg:postcode":"08344",
    "sg:province":"NJ",
    "sg:tags":[
        "general",
        "supply"
    ],
    "wof:name":"New Holland Floral Inc",
    "wof:placetype":"venue"
},
  "geometry": {"coordinates":[-75.027596,39.560279],"type":"Point"}
}