{
  "type": "Feature",
  "properties": {
    "iso:country":"US",
    "sg:address":"17 Whiting Ln",
    "sg:city":"Cape May Court House",
    "sg:classifiers":[
        {
            "category":"Professional",
            "type":"Services"
        }
    ],
    "sg:phone":"+1   ",
    "sg:postcode":"08210",
    "sg:province":"NJ",
    "wof:name":"Air Bounce of Cape May",
    "wof:placetype":"venue"
},
  "geometry": {"coordinates":[-74.79990599999999,39.113675],"type":"Point"}
}