{
  "type": "Feature",
  "properties": {
    "iso:country":"US",
    "sg:address":"69 Monroe St",
    "sg:city":"Cedar Grove",
    "sg:classifiers":[
        {
            "category":"Retail",
            "subcategory":"Repair Shop",
            "type":"Services"
        }
    ],
    "sg:phone":"+1   ",
    "sg:postcode":"07009",
    "sg:province":"NJ",
    "wof:name":"Monarch General Repairs",
    "wof:placetype":"venue"
},
  "geometry": {"coordinates":[-74.22029000000001,40.855787],"type":"Point"}
}