{
  "type": "Feature",
  "properties": {
    "iso:country":"US",
    "sg:address":"21 Vail Rd",
    "sg:city":"Lake Hiawatha",
    "sg:classifiers":[
        {
            "category":"Wholesale",
            "subcategory":"Auto Parts",
            "type":"Manufacturing & Wholesale Goods"
        }
    ],
    "sg:phone":"+1 973 257 5677",
    "sg:postcode":"07034",
    "sg:province":"NJ",
    "wof:name":"Craibek & Company",
    "wof:placetype":"venue"
},
  "geometry": {"coordinates":[-74.36739900000001,40.871812],"type":"Point"}
}