{
  "type": "Feature",
  "properties": {
    "addr:full":"338 Wilson Rd Blackwood NJ 08012",
    "addr:housenumber":"338",
    "addr:postcode":"08012",
    "addr:street":"Wilson Rd",
    "iso:country":"US",
    "sg:address":"338 Wilson Rd",
    "sg:city":"Blackwood",
    "sg:classifiers":[
        {
            "category":"Building & Trades",
            "subcategory":"Construction",
            "type":"Services"
        }
    ],
    "sg:phone":"+1 856 228 8358",
    "sg:postcode":"08012",
    "sg:province":"NJ",
    "sg:tags":[
        "general",
        "contractor"
    ],
    "wof:name":"G A Craft Assoc",
    "wof:placetype":"venue"
},
  "geometry": {"coordinates":[-75.056569,39.773634],"type":"Point"}
}