{
  "type": "Feature",
  "properties": {
    "addr:full":"1243 Sussex Tpke Randolph NJ 07869",
    "addr:housenumber":"1243",
    "addr:postcode":"07869",
    "addr:street":"Sussex Tpke",
    "iso:country":"US",
    "sg:address":"1243 Sussex Tpke",
    "sg:city":"Randolph",
    "sg:classifiers":[
        {
            "category":"Recreation",
            "type":"Entertainment"
        }
    ],
    "sg:phone":"+1 973 895 5335",
    "sg:postcode":"07869",
    "sg:province":"NJ",
    "sg:tags":[
        "karate",
        "judo",
        "instr"
    ],
    "wof:name":"Black Belt Academy",
    "wof:placetype":"venue"
},
  "geometry": {"coordinates":[-74.580038,40.825644],"type":"Point"}
}