{
  "type": "Feature",
  "properties": {
    "iso:country":"US",
    "sg:address":"291 Black Oak Ridge Rd",
    "sg:city":"Wayne",
    "sg:classifiers":[
        {
            "category":"Professional",
            "subcategory":"Computer Services",
            "type":"Services"
        }
    ],
    "sg:phone":"+1   ",
    "sg:postcode":"07470",
    "sg:province":"NJ",
    "sg:tags":[
        "related"
    ],
    "sg:website":"www.candico.com",
    "wof:name":"Candico",
    "wof:placetype":"venue"
},
  "geometry": {"coordinates":[-74.27289399999999,40.950933],"type":"Point"}
}