{
  "type": "Feature",
  "properties": {
    "addr:full":"153 Sanford Ave Kearny NJ 07032",
    "addr:housenumber":"153",
    "addr:postcode":"07032",
    "addr:street":"Sanford Ave",
    "iso:country":"US",
    "sg:address":"153 Sanford Ave",
    "sg:city":"Kearny",
    "sg:classifiers":[
        {
            "category":"Retail",
            "subcategory":"Auto Repair",
            "type":"Services"
        }
    ],
    "sg:phone":"+1 201 991 2937",
    "sg:postcode":"07032",
    "sg:province":"NJ",
    "sg:tags":[
        "general"
    ],
    "wof:name":"Joe Belfiore",
    "wof:placetype":"venue"
},
  "geometry": {"coordinates":[-74.143817,40.74795],"type":"Point"}
}