{
  "type": "Feature",
  "properties": {
    "addr:full":"3020 Moss Mill Rd Hammonton NJ 08037",
    "addr:postcode":"3020;08037",
    "addr:street":"Moss Mill Rd",
    "iso:country":"US",
    "sg:address":"3020 Moss Mill Rd",
    "sg:city":"Hammonton",
    "sg:classifiers":[
        {
            "category":"Freight",
            "type":"Transportation"
        }
    ],
    "sg:phone":"+1 609 704 1958",
    "sg:postcode":"08037",
    "sg:province":"NJ",
    "sg:tags":[
        "consultant"
    ],
    "wof:name":"WLT Inc",
    "wof:placetype":"venue"
},
  "geometry": {"coordinates":[-74.76445099999999,39.613018],"type":"Point"}
}