{
  "type": "Feature",
  "properties": {
    "addr:full":"1841 Route 541 Brlngtn Mt Mount Holly NJ 08060",
    "addr:housenumber":"1841",
    "addr:postcode":"08060",
    "addr:street":"Route 541;Mt",
    "iso:country":"US",
    "sg:address":"1841 Route 541 Brlngtn Mt",
    "sg:city":"Mount Holly",
    "sg:classifiers":[
        {
            "category":"Shopping",
            "subcategory":"Florist",
            "type":"Retail Goods"
        },
        {
            "category":"Personal",
            "subcategory":"Nail Salon",
            "type":"Services"
        }
    ],
    "sg:phone":"+1 609 267 6450",
    "sg:postcode":"08060",
    "sg:province":"NJ",
    "wof:name":"Miss Flower's Unisex Salon",
    "wof:placetype":"venue"
},
  "geometry": {"coordinates":[-74.7864,39.999001],"type":"Point"}
}