{
  "type": "Feature",
  "properties": {
    "addr:full":"424 Alexander Ave Howell NJ 07731",
    "addr:housenumber":"424",
    "addr:postcode":"07731",
    "addr:street":"Alexander Ave",
    "iso:country":"US",
    "sg:address":"424 Alexander Ave",
    "sg:city":"Howell",
    "sg:classifiers":[
        {
            "category":"Building & Trades",
            "subcategory":"Construction",
            "type":"Services"
        }
    ],
    "sg:phone":"+1 732 901 0025",
    "sg:postcode":"07731",
    "sg:province":"NJ",
    "sg:tags":[
        "steam",
        "cleaning"
    ],
    "wof:name":"Dirt Busters Power Washing",
    "wof:placetype":"venue"
},
  "geometry": {"coordinates":[-74.199628,40.116332],"type":"Point"}
}