{
  "type": "Feature",
  "properties": {
    "iso:country":"US",
    "sg:address":"757 River Dr",
    "sg:city":"Passaic",
    "sg:classifiers":[
        {
            "category":"Wholesale",
            "subcategory":"Construction Materials",
            "type":"Manufacturing & Wholesale Goods"
        },
        {
            "category":"Building & Trades",
            "subcategory":"Construction",
            "type":"Services"
        }
    ],
    "sg:phone":"+1 973 299 6336",
    "sg:postcode":"07055",
    "sg:province":"NJ",
    "sg:tags":[
        "fence",
        "contractor"
    ],
    "sg:website":"www.artisticfencenj.com",
    "wof:name":"Artistic Fence Co",
    "wof:placetype":"venue"
},
  "geometry": {"coordinates":[-74.125204,40.836781],"type":"Point"}
}