{
  "type": "Feature",
  "properties": {
    "addr:full":"503 Asbury Ave Asbury Park NJ 07712",
    "addr:housenumber":"503",
    "addr:postcode":"07712",
    "addr:street":"Asbury Ave Asbury",
    "iso:country":"US",
    "sg:address":"503 Asbury Ave",
    "sg:city":"Asbury Park",
    "sg:classifiers":[
        {
            "category":"Organizations",
            "subcategory":"Religious Organization",
            "type":"Services"
        }
    ],
    "sg:phone":"+1 732 775 5084",
    "sg:postcode":"07712",
    "sg:province":"NJ",
    "sg:website":"www.trinitynj.com",
    "wof:name":"Trinity Episcopal Church",
    "wof:placetype":"venue"
},
  "geometry": {"coordinates":[-74.008968,40.219845],"type":"Point"}
}