{
  "type": "Feature",
  "properties": {
    "iso:country":"US",
    "sg:address":"412 Mount Kemble Ave",
    "sg:city":"Morristown",
    "sg:classifiers":[
        {
            "category":"Banks & Credit Unions",
            "subcategory":"Bank",
            "type":"Services"
        }
    ],
    "sg:phone":"+1   ",
    "sg:postcode":"07960",
    "sg:province":"NJ",
    "sg:tags":[
        "federal"
    ],
    "wof:name":"Skyline Federal Credit Un",
    "wof:placetype":"venue"
},
  "geometry": {"coordinates":[-74.507233,40.770705],"type":"Point"}
}