{
  "type": "Feature",
  "properties": {
    "iso:country":"US",
    "sg:address":"13 Chuckanutt Dr",
    "sg:city":"Oakland",
    "sg:classifiers":[
        {
            "category":"Professional",
            "subcategory":"Management & Consulting",
            "type":"Services"
        }
    ],
    "sg:phone":"+1 201 337 8778",
    "sg:postcode":"07436",
    "sg:province":"NJ",
    "wof:name":"International Resources Assoc",
    "wof:placetype":"venue"
},
  "geometry": {"coordinates":[-74.222713,41.045183],"type":"Point"}
}