{
  "type": "Feature",
  "properties": {
    "addr:full":"141 Chestnut Ave Irvington NJ 07111",
    "addr:housenumber":"141",
    "addr:postcode":"07111",
    "addr:street":"Chestnut Ave",
    "iso:country":"US",
    "sg:address":"141 Chestnut Ave",
    "sg:city":"Irvington",
    "sg:classifiers":[
        {
            "category":"Retail",
            "subcategory":"Auto Repair",
            "type":"Services"
        }
    ],
    "sg:phone":"+1 973 374 2330",
    "sg:postcode":"07111",
    "sg:province":"NJ",
    "sg:tags":[
        "body",
        "automobile",
        "general"
    ],
    "wof:name":"Sudden Impact Auto Body Inc",
    "wof:placetype":"venue"
},
  "geometry": {"coordinates":[-74.23248100000001,40.709755],"type":"Point"}
}