{
  "type": "Feature",
  "properties": {
    "iso:country":"US",
    "sg:address":"701 Marys Dr",
    "sg:city":"Brick",
    "sg:classifiers":[
        {
            "category":"Professional",
            "subcategory":"Business Services",
            "type":"Services"
        }
    ],
    "sg:phone":"+1   ",
    "sg:postcode":"08723",
    "sg:province":"NJ",
    "wof:name":"Inspired Technologies",
    "wof:placetype":"venue"
},
  "geometry": {"coordinates":[-74.130937,40.057113],"type":"Point"}
}