{
  "type": "Feature",
  "properties": {
    "addr:full":"860 Cross Ave Elizabeth NJ 07208",
    "addr:housenumber":"860",
    "addr:postcode":"07208",
    "addr:street":"Cross Ave",
    "iso:country":"US",
    "sg:address":"860 Cross Ave",
    "sg:city":"Elizabeth",
    "sg:classifiers":[
        {
            "category":"Education",
            "subcategory":"School",
            "type":"Public Place"
        }
    ],
    "sg:phone":"+1 908 436 6000",
    "sg:postcode":"07208",
    "sg:province":"NJ",
    "sg:tags":[
        "high",
        "middle",
        "elementary"
    ],
    "wof:name":"Elizabeth City of",
    "wof:placetype":"venue"
},
  "geometry": {"coordinates":[-74.21063700000001,40.683614],"type":"Point"}
}