{
  "type": "Feature",
  "properties": {
    "iso:country":"US",
    "sg:address":"1 Broadway",
    "sg:city":"Elmwood Park",
    "sg:classifiers":[
        {
            "category":"Health Services",
            "subcategory":"Doctor",
            "type":"Services"
        }
    ],
    "sg:phone":"+1 201 791 7005",
    "sg:postcode":"07407",
    "sg:province":"NJ",
    "sg:tags":[
        "surgeon",
        "oral"
    ],
    "wof:name":"Dubover Grigory DDS",
    "wof:placetype":"venue"
},
  "geometry": {"coordinates":[-74.129501,40.918201],"type":"Point"}
}