{
  "type": "Feature",
  "properties": {
    "addr:full":"20 Lydia Dr West New York NJ 07093",
    "addr:housenumber":"20",
    "addr:postcode":"07093",
    "addr:street":"Lydia Dr West",
    "iso:country":"US",
    "sg:address":"20 Lydia Dr",
    "sg:city":"West New York",
    "sg:classifiers":[
        {
            "category":"Professional",
            "subcategory":"Art Services",
            "type":"Services"
        }
    ],
    "sg:phone":"+1   ",
    "sg:postcode":"07093",
    "sg:province":"NJ",
    "sg:tags":[
        "commercial",
        "design"
    ],
    "wof:name":"Al Design & Consulting Inc",
    "wof:placetype":"venue"
},
  "geometry": {"coordinates":[-74.008049,40.78413],"type":"Point"}
}