{
  "type": "Feature",
  "properties": {
    "iso:country":"US",
    "sg:address":"8 Cubler Ct",
    "sg:city":"Westville",
    "sg:classifiers":[
        {
            "category":"Retail",
            "subcategory":"Repair Shop",
            "type":"Services"
        }
    ],
    "sg:phone":"+1   ",
    "sg:postcode":"08093",
    "sg:province":"NJ",
    "wof:name":"Cubler W J",
    "wof:placetype":"venue"
},
  "geometry": {"coordinates":[-75.123936,39.840328],"type":"Point"}
}