{
  "type": "Feature",
  "properties": {
    "addr:full":"401 Hackensack Ave Hackensack NJ 07601",
    "addr:housenumber":"401",
    "addr:postcode":"07601",
    "addr:street":"Hackensack Ave",
    "iso:country":"US",
    "sg:address":"401 Hackensack Ave",
    "sg:city":"Hackensack",
    "sg:classifiers":[
        {
            "category":"Professional",
            "subcategory":"Employment Agencies",
            "type":"Services"
        }
    ],
    "sg:phone":"+1 201 488 0999",
    "sg:postcode":"07601",
    "sg:province":"NJ",
    "sg:tags":[
        "opportunity",
        "contractor"
    ],
    "sg:website":"http://www.ultimatestaffing.com",
    "wof:name":"Ulimate Staffing",
    "wof:placetype":"venue"
},
  "geometry": {"coordinates":[-74.033255,40.909787],"type":"Point"}
}