{
  "type": "Feature",
  "properties": {
    "addr:full":"176 N Fullerton Ave Montclair NJ 07042",
    "addr:housenumber":"176",
    "addr:postcode":"07042",
    "addr:street":"N Fullerton Ave",
    "iso:country":"US",
    "sg:address":"176 N Fullerton Ave",
    "sg:city":"Montclair",
    "sg:classifiers":[
        {
            "category":"Social Services",
            "type":"Services"
        }
    ],
    "sg:phone":"+1 973 655 9749",
    "sg:postcode":"07042",
    "sg:province":"NJ",
    "sg:tags":[
        "organization",
        "welfare"
    ],
    "wof:name":"YMCA",
    "wof:placetype":"venue"
},
  "geometry": {"coordinates":[-74.211962,40.820421],"type":"Point"}
}