{
  "type": "Feature",
  "properties": {
    "addr:full":"130 Monticello Ave Jersey City NJ 07304",
    "addr:housenumber":"130",
    "addr:postcode":"07304",
    "addr:street":"Monticello Ave",
    "iso:country":"US",
    "sg:address":"130 Monticello Ave",
    "sg:city":"Jersey City",
    "sg:classifiers":[
        {
            "category":"Shopping",
            "subcategory":"Books",
            "type":"Retail Goods"
        }
    ],
    "sg:phone":"+1   ",
    "sg:postcode":"07304",
    "sg:province":"NJ",
    "sg:tags":[
        "merchandise"
    ],
    "wof:name":"Word Works Christn Bk Gift Str",
    "wof:placetype":"venue"
},
  "geometry": {"coordinates":[-74.07185699999999,40.718275],"type":"Point"}
}