{
  "type": "Feature",
  "properties": {
    "addr:full":"105 Ketch Rd Morristown NJ 07960",
    "addr:housenumber":"105",
    "addr:postcode":"07960",
    "addr:street":"Ketch Rd",
    "iso:country":"US",
    "sg:address":"105 Ketch Rd",
    "sg:city":"Morristown",
    "sg:classifiers":[
        {
            "category":"Government",
            "subcategory":"Office",
            "type":"Public Place"
        }
    ],
    "sg:phone":"+1 973 540 8063",
    "sg:postcode":"07960",
    "sg:province":"NJ",
    "wof:name":"Morris County Nutrition Site",
    "wof:placetype":"venue"
},
  "geometry": {"coordinates":[-74.51195,40.831166],"type":"Point"}
}