{
  "type": "Feature",
  "properties": {
    "iso:country":"US",
    "sg:address":"80 Mount Hope Rd",
    "sg:city":"Rockaway",
    "sg:classifiers":[
        {
            "category":"Shopping",
            "subcategory":"Clothing, Apparel, & Fashions",
            "type":"Retail Goods"
        }
    ],
    "sg:phone":"+1   ",
    "sg:postcode":"07866",
    "sg:province":"NJ",
    "sg:tags":[
        "woman"
    ],
    "wof:name":"Wet Seal",
    "wof:placetype":"venue"
},
  "geometry": {"coordinates":[-74.52958,40.915208],"type":"Point"}
}