{
  "type": "Feature",
  "properties": {
    "addr:full":"1001 Toms River Rd Jackson NJ 08527",
    "addr:housenumber":"1001",
    "addr:postcode":"08527",
    "addr:street":"Toms River Rd",
    "iso:country":"US",
    "sg:address":"1001 Toms River Rd",
    "sg:city":"Jackson",
    "sg:classifiers":[
        {
            "category":"Manufacturing",
            "subcategory":"Retail Goods",
            "type":"Manufacturing & Wholesale Goods"
        }
    ],
    "sg:phone":"+1 732 408 1927",
    "sg:postcode":"08527",
    "sg:province":"NJ",
    "sg:tags":[
        "product",
        "mfg"
    ],
    "wof:name":"Bradley Industries",
    "wof:placetype":"venue"
},
  "geometry": {"coordinates":[-74.342355,40.053159],"type":"Point"}
}