{
  "type": "Feature",
  "properties": {
    "addr:full":"33 Norman Ave Riverside NJ 08075",
    "addr:housenumber":"33",
    "addr:postcode":"08075",
    "addr:street":"Norman Ave",
    "iso:country":"US",
    "sg:address":"33 Norman Ave",
    "sg:city":"Riverside",
    "sg:classifiers":[
        {
            "category":"Professional",
            "type":"Services"
        }
    ],
    "sg:phone":"+1 856 824 1850",
    "sg:postcode":"08075",
    "sg:province":"NJ",
    "sg:tags":[
        "marine",
        "contractor"
    ],
    "wof:name":"A To Z Marine Performance Inc",
    "wof:placetype":"venue"
},
  "geometry": {"coordinates":[-74.973994,40.03517],"type":"Point"}
}