{
  "type": "Feature",
  "properties": {
    "iso:country":"US",
    "sg:address":"115 Kearny Ave",
    "sg:city":"Kearny",
    "sg:classifiers":[
        {
            "category":"Professional",
            "type":"Services"
        }
    ],
    "sg:phone":"+1 201 991 3399",
    "sg:postcode":"07032",
    "sg:province":"NJ",
    "sg:tags":[
        "establishment"
    ],
    "wof:name":"Maresco Int'l Inc",
    "wof:placetype":"venue"
},
  "geometry": {"coordinates":[-74.15469299999999,40.756201],"type":"Point"}
}