{
  "type": "Feature",
  "properties": {
    "iso:country":"US",
    "sg:address":"1061 Raritan Rd",
    "sg:city":"Clark",
    "sg:classifiers":[
        {
            "category":"Personal",
            "subcategory":"Beauty Salon",
            "type":"Services"
        }
    ],
    "sg:phone":"+1 732 882 0024",
    "sg:postcode":"07066",
    "sg:province":"NJ",
    "sg:tags":[
        "shop"
    ],
    "wof:name":"Russell Scott Hair Designs LLC",
    "wof:placetype":"venue"
},
  "geometry": {"coordinates":[-74.314302,40.628278],"type":"Point"}
}