{
  "type": "Feature",
  "properties": {
    "addr:full":"49 Birmingham Dr Englishtown NJ 07726",
    "addr:housenumber":"49",
    "addr:postcode":"07726",
    "addr:street":"Birmingham Dr",
    "iso:country":"US",
    "sg:address":"49 Birmingham Dr",
    "sg:city":"Englishtown",
    "sg:classifiers":[
        {
            "category":"Insurance",
            "subcategory":"Insurance Agent",
            "type":"Services"
        }
    ],
    "sg:phone":"+1   ",
    "sg:postcode":"07726",
    "sg:province":"NJ",
    "wof:name":"Jack Heir & Associates",
    "wof:placetype":"venue"
},
  "geometry": {"coordinates":[-74.33639100000001,40.316219],"type":"Point"}
}