{
  "type": "Feature",
  "properties": {
    "iso:country":"US",
    "sg:address":"300 Montgomery St",
    "sg:city":"Jersey City",
    "sg:classifiers":[
        {
            "category":"Professional",
            "subcategory":"Computer Services",
            "type":"Services"
        }
    ],
    "sg:phone":"+1 201 484 8147",
    "sg:postcode":"07302",
    "sg:province":"NJ",
    "sg:tags":[
        "repair"
    ],
    "wof:name":"Geeks Mobile - Computer Repair",
    "wof:placetype":"venue"
},
  "geometry": {"coordinates":[-74.048226,40.718915],"type":"Point"}
}