{
  "type": "Feature",
  "properties": {
    "iso:country":"US",
    "sg:address":"1320 Summit Ave",
    "sg:city":"Union City",
    "sg:classifiers":[
        {
            "category":"Shopping",
            "subcategory":"Clothing, Apparel, & Fashions",
            "type":"Retail Goods"
        }
    ],
    "sg:phone":"+1   ",
    "sg:postcode":"07087",
    "sg:province":"NJ",
    "sg:tags":[
        "family"
    ],
    "wof:name":"Chiquilladas Boutique",
    "wof:placetype":"venue"
},
  "geometry": {"coordinates":[-74.041303,40.76191],"type":"Point"}
}