{
  "type": "Feature",
  "properties": {
    "iso:country":"US",
    "sg:address":"1 Locust St",
    "sg:city":"Lakewood",
    "sg:classifiers":[
        {
            "category":"Professional",
            "type":"Services"
        }
    ],
    "sg:phone":"+1 732 367 0661",
    "sg:postcode":"08701",
    "sg:province":"NJ",
    "sg:tags":[
        "establishment"
    ],
    "wof:name":"St Mary Of The Lake",
    "wof:placetype":"venue"
},
  "geometry": {"coordinates":[-74.21977699999999,40.047793],"type":"Point"}
}