{
  "type": "Feature",
  "properties": {
    "iso:country":"US",
    "sg:address":"221 96th St",
    "sg:city":"Stone Harbor",
    "sg:classifiers":[
        {
            "category":"Shopping",
            "type":"Retail Goods"
        }
    ],
    "sg:phone":"+1 609 368 8830",
    "sg:postcode":"08247",
    "sg:province":"NJ",
    "sg:tags":[
        "art",
        "gallery",
        "merchandise",
        "dealer"
    ],
    "wof:name":"Southern California Art Co",
    "wof:placetype":"venue"
},
  "geometry": {"coordinates":[-74.760366,39.054301],"type":"Point"}
}