{
  "type": "Feature",
  "properties": {
    "iso:country":"US",
    "sg:address":"1071 Springfield Rd",
    "sg:city":"Union",
    "sg:classifiers":[
        {
            "category":"Building & Trades",
            "subcategory":"Construction",
            "type":"Services"
        }
    ],
    "sg:phone":"+1 908 688 6801",
    "sg:postcode":"07083",
    "sg:province":"NJ",
    "sg:tags":[
        "interior",
        "design"
    ],
    "wof:name":"Strategic Workplace Consulting",
    "wof:placetype":"venue"
},
  "geometry": {"coordinates":[-74.3004,40.692799],"type":"Point"}
}