{
  "type": "Feature",
  "properties": {
    "iso:country":"US",
    "sg:address":"133 Newark Ave",
    "sg:city":"Jersey City",
    "sg:classifiers":[
        {
            "category":"Shopping",
            "subcategory":"Jewelry",
            "type":"Retail Goods"
        }
    ],
    "sg:phone":"+1   ",
    "sg:postcode":"07302",
    "sg:province":"NJ",
    "wof:name":"133 Boutique",
    "wof:placetype":"venue"
},
  "geometry": {"coordinates":[-74.04401799999999,40.72038],"type":"Point"}
}