{
  "type": "Feature",
  "properties": {
    "addr:full":"1567 Palisade Ave Fort Lee NJ 07024",
    "addr:housenumber":"1567",
    "addr:postcode":"07024",
    "addr:street":"Palisade Ave",
    "iso:country":"US",
    "sg:address":"1567 Palisade Ave",
    "sg:city":"Fort Lee",
    "sg:classifiers":[
        {
            "category":"Health Services",
            "subcategory":"Doctor",
            "type":"Services"
        }
    ],
    "sg:phone":"+1 201 947 8300",
    "sg:postcode":"07024",
    "sg:province":"NJ",
    "sg:tags":[
        "dentist"
    ],
    "wof:name":"A Plus Family Dental",
    "wof:placetype":"venue"
},
  "geometry": {"coordinates":[-73.969381,40.848865],"type":"Point"}
}