{
  "type": "Feature",
  "properties": {
    "iso:country":"US",
    "sg:address":"428 Derousse Ave",
    "sg:city":"Pennsauken",
    "sg:classifiers":[
        {
            "category":"Building & Trades",
            "subcategory":"Landscaping Services",
            "type":"Services"
        }
    ],
    "sg:phone":"+1 856 662 6882",
    "sg:postcode":"08110",
    "sg:province":"NJ",
    "wof:name":"Johns Landscaping & Lawn Svc",
    "wof:placetype":"venue"
},
  "geometry": {"coordinates":[-75.059642,39.977688],"type":"Point"}
}