{
  "type": "Feature",
  "properties": {
    "addr:full":"10 Norwood Dr Gillette NJ 07933",
    "addr:housenumber":"10",
    "addr:postcode":"07933",
    "addr:street":"Norwood Dr",
    "iso:country":"US",
    "sg:address":"10 Norwood Dr",
    "sg:city":"Gillette",
    "sg:classifiers":[
        {
            "category":"Organizations",
            "subcategory":"Religious Organization",
            "type":"Services"
        }
    ],
    "sg:phone":"+1   ",
    "sg:postcode":"07933",
    "sg:province":"NJ",
    "wof:name":"Jehovahs Wtnsses Cngrtn Gllett",
    "wof:placetype":"venue"
},
  "geometry": {"coordinates":[-74.4559,40.677349],"type":"Point"}
}