{
  "type": "Feature",
  "properties": {
    "iso:country":"US",
    "sg:address":"20 Hartley Pl",
    "sg:city":"Fair Lawn",
    "sg:classifiers":[
        {
            "category":"Professional",
            "subcategory":"Advertising",
            "type":"Services"
        }
    ],
    "sg:phone":"+1 201 794 1006",
    "sg:postcode":"07410",
    "sg:province":"NJ",
    "sg:tags":[
        "guide"
    ],
    "wof:name":"Jewish Israeli Yellow Pages",
    "wof:placetype":"venue"
},
  "geometry": {"coordinates":[-74.115595,40.928955],"type":"Point"}
}