{
  "type": "Feature",
  "properties": {
    "iso:country":"US",
    "sg:address":"637 Ridge Rd",
    "sg:city":"Monmouth Jct",
    "sg:classifiers":[
        {
            "category":"Professional",
            "subcategory":"Computer Services",
            "type":"Services"
        }
    ],
    "sg:phone":"+1 732 329 0177",
    "sg:postcode":"08852",
    "sg:province":"NJ",
    "sg:tags":[
        "repair"
    ],
    "wof:name":"Aurora Electronics",
    "wof:placetype":"venue"
},
  "geometry": {"coordinates":[-74.549543,40.377453],"type":"Point"}
}