{
  "type": "Feature",
  "properties": {
    "iso:country":"US",
    "sg:address":"124 Boxwood Ln",
    "sg:city":"Cinnaminson",
    "sg:classifiers":[
        {
            "category":"Professional",
            "subcategory":"Art Services",
            "type":"Services"
        }
    ],
    "sg:phone":"+1 856 786 1399",
    "sg:postcode":"08077",
    "sg:province":"NJ",
    "sg:tags":[
        "commercial",
        "artist"
    ],
    "wof:name":"Constance Burke Schnurr",
    "wof:placetype":"venue"
},
  "geometry": {"coordinates":[-74.98912799999999,39.994292],"type":"Point"}
}