{
  "type": "Feature",
  "properties": {
    "addr:full":"154 Carlisle Ave Trenton NJ 08620",
    "addr:housenumber":"154",
    "addr:postcode":"08620",
    "addr:street":"Carlisle Ave",
    "iso:country":"US",
    "sg:address":"154 Carlisle Ave",
    "sg:city":"Trenton",
    "sg:classifiers":[
        {
            "category":"Building & Trades",
            "subcategory":"Construction",
            "type":"Services"
        }
    ],
    "sg:phone":"+1 609 585 7745",
    "sg:postcode":"08620",
    "sg:province":"NJ",
    "sg:tags":[
        "house",
        "nonresidential"
    ],
    "wof:name":"Iorio Loius J Jr General Cnstr",
    "wof:placetype":"venue"
},
  "geometry": {"coordinates":[-74.65941100000001,40.180872],"type":"Point"}
}