{
  "type": "Feature",
  "properties": {
    "iso:country":"US",
    "sg:address":"180 Manor Rd",
    "sg:city":"East Rutherford",
    "sg:classifiers":[
        {
            "category":"Professional",
            "subcategory":"Art Services",
            "type":"Services"
        }
    ],
    "sg:phone":"+1 201 488 0220",
    "sg:postcode":"07073",
    "sg:province":"NJ",
    "sg:tags":[
        "development",
        "package",
        "designing"
    ],
    "sg:website":"www.appleltd.com",
    "wof:name":"Apple Corrugated LTD",
    "wof:placetype":"venue"
},
  "geometry": {"coordinates":[-74.08626599999999,40.824338],"type":"Point"}
}