{
  "type": "Feature",
  "properties": {
    "addr:full":"38 Sycamore Dr Saddle River NJ 07458",
    "addr:housenumber":"38",
    "addr:postcode":"07458",
    "addr:street":"Sycamore Dr",
    "iso:country":"US",
    "sg:address":"38 Sycamore Dr",
    "sg:city":"Saddle River",
    "sg:classifiers":[
        {
            "category":"Real Estate",
            "subcategory":"Real Estate Agent",
            "type":"Services"
        }
    ],
    "sg:phone":"+1   ",
    "sg:postcode":"07458",
    "sg:province":"NJ",
    "sg:tags":[
        "management",
        "investment"
    ],
    "wof:name":"J P Meredith Co Inc",
    "wof:placetype":"venue"
},
  "geometry": {"coordinates":[-74.086254,41.078212],"type":"Point"}
}