{
  "type": "Feature",
  "properties": {
    "addr:full":"126 S Broadway Pitman NJ 08071",
    "addr:housenumber":"126",
    "addr:postcode":"08071",
    "addr:street":"S Broadway",
    "iso:country":"US",
    "sg:address":"126 S Broadway",
    "sg:city":"Pitman",
    "sg:classifiers":[
        {
            "category":"Wholesale",
            "subcategory":"Stationery",
            "type":"Manufacturing & Wholesale Goods"
        }
    ],
    "sg:phone":"+1 856 582 8222",
    "sg:postcode":"08071",
    "sg:province":"NJ",
    "sg:tags":[
        "school",
        "supply"
    ],
    "wof:name":"Learning Can Be Fun",
    "wof:placetype":"venue"
},
  "geometry": {"coordinates":[-75.12990000000001,39.731442],"type":"Point"}
}