{
  "type": "Feature",
  "properties": {
    "addr:full":"214 96th St Stone Harbor NJ 08247",
    "addr:housenumber":"214",
    "addr:postcode":"08247",
    "addr:street":"96Th St",
    "iso:country":"US",
    "sg:address":"214 96th St",
    "sg:city":"Stone Harbor",
    "sg:classifiers":[
        {
            "category":"Recreation",
            "subcategory":"Amusement Park",
            "type":"Entertainment"
        }
    ],
    "sg:phone":"+1 609 368 8484",
    "sg:postcode":"08247",
    "sg:province":"NJ",
    "wof:name":"Rigi's Amusement Center",
    "wof:placetype":"venue"
},
  "geometry": {"coordinates":[-74.758904,39.053799],"type":"Point"}
}