{
  "type": "Feature",
  "properties": {
    "addr:full":"12 Koster Blvd Edison NJ 08837",
    "addr:housenumber":"12",
    "addr:postcode":"08837",
    "addr:street":"Koster Blvd",
    "iso:country":"US",
    "sg:address":"12 Koster Blvd",
    "sg:city":"Edison",
    "sg:classifiers":[
        {
            "category":"Real Estate",
            "subcategory":"Real Estate Operator",
            "type":"Services"
        }
    ],
    "sg:phone":"+1 732 548 3661",
    "sg:postcode":"08837",
    "sg:province":"NJ",
    "sg:tags":[
        "building",
        "apartment"
    ],
    "wof:name":"Parkwood Gardens Inc",
    "wof:placetype":"venue"
},
  "geometry": {"coordinates":[-74.34401699999999,40.549927],"type":"Point"}
}