{
  "type": "Feature",
  "properties": {
    "addr:full":"18 Northfield Dr Sussex NJ 07461",
    "addr:housenumber":"18",
    "addr:postcode":"07461",
    "addr:street":"Northfield Dr",
    "iso:country":"US",
    "sg:address":"18 Northfield Dr",
    "sg:city":"Sussex",
    "sg:classifiers":[
        {
            "category":"Building & Trades",
            "subcategory":"Plumbing",
            "type":"Services"
        }
    ],
    "sg:phone":"+1 973 702 0018",
    "sg:postcode":"07461",
    "sg:province":"NJ",
    "sg:tags":[
        "plumber"
    ],
    "wof:name":"High Tech Utilities",
    "wof:placetype":"venue"
},
  "geometry": {"coordinates":[-74.661524,41.22037],"type":"Point"}
}