{
  "type": "Feature",
  "properties": {
    "iso:country":"US",
    "sg:address":"45 Rt 17 S",
    "sg:city":"Hasbrouck Heights",
    "sg:classifiers":[
        {
            "category":"Autos & Motor Vehicles",
            "subcategory":"Automobile Sales",
            "type":"Retail Goods"
        },
        {
            "category":"Retail",
            "subcategory":"Auto Repair",
            "type":"Services"
        }
    ],
    "sg:phone":"+1 201 796 5050",
    "sg:postcode":"07604",
    "sg:province":"NJ",
    "sg:tags":[
        "car"
    ],
    "sg:website":"www.meadowlandsnissan.com",
    "wof:name":"Meadowlands Nissan",
    "wof:placetype":"venue"
},
  "geometry": {"coordinates":[-74.073348,40.89861],"type":"Point"}
}