{
  "type": "Feature",
  "properties": {
    "iso:country":"US",
    "sg:address":"280 Jackson Rd",
    "sg:city":"Berlin",
    "sg:classifiers":[
        {
            "category":"Organizations",
            "subcategory":"Non-profit Organization",
            "type":"Services"
        }
    ],
    "sg:phone":"+1 856 767 5757",
    "sg:postcode":"08009",
    "sg:province":"NJ",
    "sg:tags":[
        "human"
    ],
    "sg:website":"www.archwayprograms.org",
    "wof:name":"Archway Programs",
    "wof:placetype":"venue"
},
  "geometry": {"coordinates":[-74.892078,39.781474],"type":"Point"}
}