{
  "type": "Feature",
  "properties": {
    "iso:country":"US",
    "sg:address":"34 Monterey Dr",
    "sg:city":"Hazlet",
    "sg:classifiers":[
        {
            "category":"Utilities",
            "subcategory":"Electric",
            "type":"Services"
        }
    ],
    "sg:phone":"+1 732 888 5518",
    "sg:postcode":"07730",
    "sg:province":"NJ",
    "wof:name":"American Standard Electric Co",
    "wof:placetype":"venue"
},
  "geometry": {"coordinates":[-74.172777,40.429853],"type":"Point"}
}