{
  "type": "Feature",
  "properties": {
    "addr:full":"92 State Rte 23 Hamburg NJ 07419",
    "addr:housenumber":"92",
    "addr:postcode":"07419",
    "addr:street":"State Rte 23",
    "iso:country":"US",
    "sg:address":"92 State Rte 23",
    "sg:city":"Hamburg",
    "sg:classifiers":[
        {
            "category":"Personal",
            "subcategory":"Beauty Salon",
            "type":"Services"
        }
    ],
    "sg:phone":"+1 973 209 0468",
    "sg:postcode":"07419",
    "sg:province":"NJ",
    "sg:tags":[
        "manicuring"
    ],
    "wof:name":"Susie Nail & Skin Care",
    "wof:placetype":"venue"
},
  "geometry": {"coordinates":[-74.579336,41.160396],"type":"Point"}
}