{
  "type": "Feature",
  "properties": {
    "addr:full":"8640 Githens Ave Pennsauken NJ 08109",
    "addr:housenumber":"8640",
    "addr:postcode":"08109",
    "addr:street":"Githens Ave",
    "iso:country":"US",
    "sg:address":"8640 Githens Ave",
    "sg:city":"Pennsauken",
    "sg:classifiers":[
        {
            "category":"Building & Trades",
            "subcategory":"Plumbing",
            "type":"Services"
        }
    ],
    "sg:phone":"+1 856 663 4936",
    "sg:postcode":"08109",
    "sg:province":"NJ",
    "sg:tags":[
        "contractor"
    ],
    "wof:name":"Palmer Enterprises Inc",
    "wof:placetype":"venue"
},
  "geometry": {"coordinates":[-75.025791,39.967737],"type":"Point"}
}