{
  "type": "Feature",
  "properties": {
    "iso:country":"US",
    "sg:address":"130 Coolidge Ave",
    "sg:city":"Englewood",
    "sg:classifiers":[
        {
            "category":"Wholesale",
            "subcategory":"Machinery & Supplies",
            "type":"Manufacturing & Wholesale Goods"
        },
        {
            "category":"Manufacturing",
            "subcategory":"Rubber & Plastics",
            "type":"Manufacturing & Wholesale Goods"
        }
    ],
    "sg:phone":"+1 201 567 6100",
    "sg:postcode":"07631",
    "sg:province":"NJ",
    "sg:tags":[
        "belting",
        "mfg"
    ],
    "sg:website":"www.siegling-us.com",
    "wof:name":"Siegling America Inc",
    "wof:placetype":"venue"
},
  "geometry": {"coordinates":[-73.989372,40.887495],"type":"Point"}
}