{
  "type": "Feature",
  "properties": {
    "addr:full":"12 Glenn Ave Glen Gardner NJ 08826",
    "addr:housenumber":"12",
    "addr:postcode":"08826",
    "addr:street":"Glenn Ave",
    "iso:country":"US",
    "sg:address":"12 Glenn Ave",
    "sg:city":"Glen Gardner",
    "sg:classifiers":[
        {
            "category":"Building & Trades",
            "subcategory":"Construction",
            "type":"Services"
        }
    ],
    "sg:phone":"+1 908 537 2159",
    "sg:postcode":"08826",
    "sg:province":"NJ",
    "sg:tags":[
        "house"
    ],
    "wof:name":"Armor Home Improvements",
    "wof:placetype":"venue"
},
  "geometry": {"coordinates":[-74.944776,40.694832],"type":"Point"}
}