{
  "type": "Feature",
  "properties": {
    "addr:full":"487 Market St Ste 10 Saddle Brook NJ 07663",
    "addr:housenumber":"487",
    "addr:postcode":"07663",
    "addr:street":"Market St Ste 10",
    "iso:country":"US",
    "sg:address":"487 Market St Ste 10",
    "sg:city":"Saddle Brook",
    "sg:classifiers":[
        {
            "category":"Food & Beverages",
            "subcategory":"Bakery",
            "type":"Retail Goods"
        }
    ],
    "sg:phone":"+1 201 843 8000",
    "sg:postcode":"07663",
    "sg:province":"NJ",
    "sg:tags":[
        "sandwich"
    ],
    "sg:website":"www.subway.com",
    "wof:name":"Subway",
    "wof:placetype":"venue"
},
  "geometry": {"coordinates":[-74.09985500000001,40.897457],"type":"Point"}
}