{
  "type": "Feature",
  "properties": {
    "addr:full":"125 S 7th St Newark NJ 07107",
    "addr:housenumber":"125",
    "addr:postcode":"07107",
    "addr:street":"S 7Th St",
    "iso:country":"US",
    "sg:address":"125 S 7th St",
    "sg:city":"Newark",
    "sg:classifiers":[
        {
            "category":"Professional",
            "subcategory":"Employment Agencies",
            "type":"Services"
        }
    ],
    "sg:phone":"+1 973 622 0016",
    "sg:postcode":"07107",
    "sg:province":"NJ",
    "sg:tags":[
        "help",
        "contractor"
    ],
    "wof:name":"Dental & Medical Staffing Agcy",
    "wof:placetype":"venue"
},
  "geometry": {"coordinates":[-74.195401,40.745411],"type":"Point"}
}