{
  "type": "Feature",
  "properties": {
    "iso:country":"US",
    "sg:address":"9 Peach Tree Hill Rd",
    "sg:city":"Livingston",
    "sg:classifiers":[
        {
            "category":"Manufacturing",
            "subcategory":"Rubber & Plastics",
            "type":"Manufacturing & Wholesale Goods"
        }
    ],
    "sg:phone":"+1 973 994 8000",
    "sg:postcode":"07039",
    "sg:province":"NJ",
    "sg:tags":[
        "sheet",
        "film",
        "mfg"
    ],
    "wof:name":"Amtopp",
    "wof:placetype":"venue"
},
  "geometry": {"coordinates":[-74.362376,40.772708],"type":"Point"}
}