{
  "type": "Feature",
  "properties": {
    "addr:full":"7 Kyle Dr Phillipsburg NJ 08865",
    "addr:housenumber":"7",
    "addr:postcode":"08865",
    "addr:street":"Kyle Dr",
    "iso:country":"US",
    "sg:address":"7 Kyle Dr",
    "sg:city":"Phillipsburg",
    "sg:classifiers":[
        {
            "category":"Professional",
            "subcategory":"Business Services",
            "type":"Services"
        }
    ],
    "sg:phone":"+1   ",
    "sg:postcode":"08865",
    "sg:province":"NJ",
    "wof:name":"Vesta Group Inc",
    "wof:placetype":"venue"
},
  "geometry": {"coordinates":[-75.16943000000001,40.714673],"type":"Point"}
}