{
  "type": "Feature",
  "properties": {
    "iso:country":"US",
    "sg:address":"51 N Main St",
    "sg:city":"Paterson",
    "sg:classifiers":[
        {
            "category":"Food & Beverages",
            "subcategory":"Groceries & Convenience Stores",
            "type":"Retail Goods"
        }
    ],
    "sg:phone":"+1 973 595 0274",
    "sg:postcode":"07522",
    "sg:province":"NJ",
    "sg:tags":[
        "ticket",
        "lottery"
    ],
    "wof:name":"Family Grocery Store",
    "wof:placetype":"venue"
},
  "geometry": {"coordinates":[-74.1717,40.924301],"type":"Point"}
}