{
  "type": "Feature",
  "properties": {
    "addr:full":"9140 Pennsauken Hwy Ste C Pennsauken NJ 08110",
    "addr:housenumber":"9140",
    "addr:postcode":"08110",
    "addr:street":"Pennsauken Hwy Ste C",
    "iso:country":"US",
    "sg:address":"9140 Pennsauken Hwy Ste C",
    "sg:city":"Pennsauken",
    "sg:classifiers":[
        {
            "category":"Animal Shelter",
            "type":"Public Place"
        },
        {
            "category":"Shopping",
            "subcategory":"Pets & Pet Supplies",
            "type":"Retail Goods"
        }
    ],
    "sg:phone":"+1 856 663 3058",
    "sg:postcode":"08110",
    "sg:province":"NJ",
    "sg:tags":[
        "store"
    ],
    "wof:name":"Almost Home Animal Shelter",
    "wof:placetype":"venue"
},
  "geometry": {"coordinates":[-75.02372200000001,39.978003],"type":"Point"}
}