{
  "type": "Feature",
  "properties": {
    "addr:full":"79 Wehrli Rd Long Valley NJ 07853",
    "addr:housenumber":"79",
    "addr:postcode":"07853",
    "addr:street":"Wehrli Rd",
    "iso:country":"US",
    "sg:address":"79 Wehrli Rd",
    "sg:city":"Long Valley",
    "sg:classifiers":[
        {
            "category":"Professional",
            "subcategory":"Business Services",
            "type":"Services"
        },
        {
            "category":"Manufacturing",
            "subcategory":"Tools & Machinery",
            "type":"Manufacturing & Wholesale Goods"
        }
    ],
    "sg:phone":"+1 908 852 0600",
    "sg:postcode":"07853",
    "sg:province":"NJ",
    "sg:tags":[
        "specializing",
        "physician",
        "consulting",
        "packaging",
        "surgeon",
        "engineer"
    ],
    "sg:website":"www.donbarindustries.com",
    "wof:name":"Donbar Industries Inc",
    "wof:placetype":"venue"
},
  "geometry": {"coordinates":[-74.82051800000001,40.790849],"type":"Point"}
}