{
  "type": "Feature",
  "properties": {
    "addr:full":"2435 State Rte 35 Manasquan NJ 08736",
    "addr:housenumber":"2435",
    "addr:postcode":"08736",
    "addr:street":"State Rte 35",
    "iso:country":"US",
    "sg:address":"2435 State Rte 35",
    "sg:city":"Manasquan",
    "sg:classifiers":[
        {
            "category":"Shopping",
            "subcategory":"Computers & Home Electronics",
            "type":"Retail Goods"
        }
    ],
    "sg:phone":"+1 732 292 9922",
    "sg:postcode":"08736",
    "sg:province":"NJ",
    "sg:tags":[
        "equipment",
        "satellite",
        "system"
    ],
    "wof:name":"Corporate Telecom",
    "wof:placetype":"venue"
},
  "geometry": {"coordinates":[-74.068033,40.126207],"type":"Point"}
}