{
  "type": "Feature",
  "properties": {
    "addr:full":"813 E Gate Dr Mt Laurel NJ 08054",
    "addr:housenumber":"813",
    "addr:postcode":"08054",
    "addr:street":"E Gate Dr",
    "iso:country":"US",
    "sg:address":"813 E Gate Dr",
    "sg:city":"Mt Laurel",
    "sg:classifiers":[
        {
            "category":"Insurance",
            "subcategory":"Health Insurance",
            "type":"Services"
        }
    ],
    "sg:phone":"+1 856 778 1196",
    "sg:postcode":"08054",
    "sg:province":"NJ",
    "sg:tags":[
        "plan"
    ],
    "wof:name":"Blue Cross & Blue Shield",
    "wof:placetype":"venue"
},
  "geometry": {"coordinates":[-74.94867000000001,39.943254],"type":"Point"}
}