{
  "type": "Feature",
  "properties": {
    "addr:full":"106 S Main Rd Vineland NJ 08360",
    "addr:housenumber":"106",
    "addr:postcode":"08360",
    "addr:street":"S Main Rd",
    "iso:country":"US",
    "sg:address":"106 S Main Rd",
    "sg:city":"Vineland",
    "sg:classifiers":[
        {
            "category":"Food & Beverages",
            "subcategory":"Liquor & Beverages",
            "type":"Retail Goods"
        }
    ],
    "sg:phone":"+1   ",
    "sg:postcode":"08360",
    "sg:province":"NJ",
    "sg:tags":[
        "alcoholic"
    ],
    "wof:name":"Main Discount Liquor & Deli",
    "wof:placetype":"venue"
},
  "geometry": {"coordinates":[-75.000112,39.482494],"type":"Point"}
}