{
  "type": "Feature",
  "properties": {
    "addr:full":"28 Meadow Ave Monmouth Beach NJ 07750",
    "addr:housenumber":"28",
    "addr:postcode":"07750",
    "addr:street":"Meadow Ave",
    "iso:country":"US",
    "sg:address":"28 Meadow Ave",
    "sg:city":"Monmouth Beach",
    "sg:classifiers":[
        {
            "category":"Building & Trades",
            "subcategory":"Construction",
            "type":"Services"
        }
    ],
    "sg:phone":"+1 732 923 1941",
    "sg:postcode":"07750",
    "sg:province":"NJ",
    "sg:tags":[
        "house"
    ],
    "wof:name":"Ned Hager",
    "wof:placetype":"venue"
},
  "geometry": {"coordinates":[-73.991198,40.333687],"type":"Point"}
}