{
  "type": "Feature",
  "properties": {
    "iso:country":"US",
    "sg:address":"155 Union Rd",
    "sg:city":"Frenchtown",
    "sg:classifiers":[
        {
            "category":"Recreation",
            "type":"Entertainment"
        }
    ],
    "sg:phone":"+1 908 996 4233",
    "sg:postcode":"08825",
    "sg:province":"NJ",
    "sg:tags":[
        "balloon"
    ],
    "wof:name":"A-Lot-A Hot Air Balloon Rides",
    "wof:placetype":"venue"
},
  "geometry": {"coordinates":[-75.002166,40.504958],"type":"Point"}
}