{
  "type": "Feature",
  "properties": {
    "iso:country":"US",
    "sg:address":"599 Franklin Ave",
    "sg:city":"Franklin Lakes",
    "sg:classifiers":[
        {
            "category":"Building & Trades",
            "subcategory":"Electrical",
            "type":"Services"
        }
    ],
    "sg:phone":"+1 201 891 6766",
    "sg:postcode":"07417",
    "sg:province":"NJ",
    "sg:tags":[
        "electrical",
        "electric",
        "contractor"
    ],
    "wof:name":"Hallmark Electrical Associates",
    "wof:placetype":"venue"
},
  "geometry": {"coordinates":[-74.194653,41.012115],"type":"Point"}
}