{
  "type": "Feature",
  "properties": {
    "iso:country":"US",
    "sg:address":"966 Rahway Ave",
    "sg:city":"Union",
    "sg:classifiers":[
        {
            "category":"Building & Trades",
            "subcategory":"Electrical",
            "type":"Services"
        }
    ],
    "sg:phone":"+1 908 964 7894",
    "sg:postcode":"07083",
    "sg:province":"NJ",
    "sg:tags":[
        "electrical",
        "contractor"
    ],
    "wof:name":"Hacks Electric",
    "wof:placetype":"venue"
},
  "geometry": {"coordinates":[-74.28547399999999,40.699669],"type":"Point"}
}