{
  "type": "Feature",
  "properties": {
    "iso:country":"US",
    "sg:address":"282 McKinley Ave",
    "sg:city":"Bayville",
    "sg:classifiers":[
        {
            "category":"Building & Trades",
            "subcategory":"Construction",
            "type":"Services"
        }
    ],
    "sg:phone":"+1 732 269 7618",
    "sg:postcode":"08721",
    "sg:province":"NJ",
    "sg:tags":[
        "house",
        "family"
    ],
    "wof:name":"Ken Garry Construction Co",
    "wof:placetype":"venue"
},
  "geometry": {"coordinates":[-74.191102,39.903509],"type":"Point"}
}