{
  "type": "Feature",
  "properties": {
    "addr:full":"314 Broad St Bloomfield NJ 07003",
    "addr:housenumber":"314",
    "addr:postcode":"07003",
    "addr:street":"Broad St",
    "iso:country":"US",
    "sg:address":"314 Broad St",
    "sg:city":"Bloomfield",
    "sg:classifiers":[
        {
            "category":"Social Services",
            "subcategory":"Child Care",
            "type":"Services"
        }
    ],
    "sg:phone":"+1 973 748 1984",
    "sg:postcode":"07003",
    "sg:province":"NJ",
    "sg:tags":[
        "kindergarten",
        "academic",
        "school",
        "day",
        "elementary"
    ],
    "wof:name":"Olive Tree Child Care Center",
    "wof:placetype":"venue"
},
  "geometry": {"coordinates":[-74.194298,40.804298],"type":"Point"}
}