{
  "type": "Feature",
  "properties": {
    "iso:country":"US",
    "sg:address":"22 Maple Ave",
    "sg:city":"North Brunswick",
    "sg:classifiers":[
        {
            "category":"Building & Trades",
            "subcategory":"Construction",
            "type":"Services"
        }
    ],
    "sg:phone":"+1 732 545 7785",
    "sg:postcode":"08902",
    "sg:province":"NJ",
    "sg:tags":[
        "hanging",
        "contractor"
    ],
    "wof:name":"Carmens Painting",
    "wof:placetype":"venue"
},
  "geometry": {"coordinates":[-74.454617,40.46778],"type":"Point"}
}