{
  "type": "Feature",
  "properties": {
    "iso:country":"US",
    "sg:address":"1025 Greeley Ave",
    "sg:city":"Union",
    "sg:classifiers":[
        {
            "category":"Organizations",
            "subcategory":"Community Association",
            "type":"Services"
        }
    ],
    "sg:phone":"+1   ",
    "sg:postcode":"07083",
    "sg:province":"NJ",
    "wof:name":"American Legion Post 440",
    "wof:placetype":"venue"
},
  "geometry": {"coordinates":[-74.30044100000001,40.690972],"type":"Point"}
}