{
  "type": "Feature",
  "properties": {
    "iso:country":"US",
    "sg:address":"771 Saint George Ave",
    "sg:city":"Woodbridge",
    "sg:classifiers":[
        {
            "category":"Retail",
            "subcategory":"Laundry & Dry Cleaning",
            "type":"Services"
        }
    ],
    "sg:phone":"+1 732 326 0100",
    "sg:postcode":"07095",
    "sg:province":"NJ",
    "wof:name":"Pride Dry Cleaners & Tailor Shop",
    "wof:placetype":"venue"
},
  "geometry": {"coordinates":[-74.287003,40.565701],"type":"Point"}
}