{
  "type": "Feature",
  "properties": {
    "addr:full":"54 Freeman St Newark NJ 07105",
    "addr:housenumber":"54",
    "addr:postcode":"07105",
    "addr:street":"Freeman St",
    "iso:country":"US",
    "sg:address":"54 Freeman St",
    "sg:city":"Newark",
    "sg:classifiers":[
        {
            "category":"Manufacturing",
            "subcategory":"Tools & Machinery",
            "type":"Manufacturing & Wholesale Goods"
        }
    ],
    "sg:phone":"+1 973 589 1391",
    "sg:postcode":"07105",
    "sg:province":"NJ",
    "sg:tags":[
        "pattern",
        "industrial",
        "maker",
        "mfg"
    ],
    "wof:name":"Creative Patterns & Mfg",
    "wof:placetype":"venue"
},
  "geometry": {"coordinates":[-74.143682,40.730437],"type":"Point"}
}