{
  "type": "Feature",
  "properties": {
    "addr:full":"2658 N West Blvd Vineland NJ 08360",
    "addr:housenumber":"2658",
    "addr:postcode":"08360",
    "addr:street":"N West Blvd",
    "iso:country":"US",
    "sg:address":"2658 N West Blvd",
    "sg:city":"Vineland",
    "sg:classifiers":[
        {
            "category":"Manufacturing",
            "subcategory":"Electronics",
            "type":"Manufacturing & Wholesale Goods"
        },
        {
            "category":"Communications",
            "subcategory":"Television Station",
            "type":"Services"
        },
        {
            "category":"Utilities",
            "subcategory":"Telephone",
            "type":"Services"
        },
        {
            "category":"Communications",
            "type":"Services"
        },
        {
            "category":"Professional",
            "subcategory":"Computer Services",
            "type":"Services"
        }
    ],
    "sg:phone":"+1 856 691 5111",
    "sg:postcode":"08360",
    "sg:province":"NJ",
    "sg:tags":[
        "satellite",
        "telecommunications-equipment",
        "telecommunication",
        "cable",
        "supply",
        "consultant"
    ],
    "sg:website":"http://www.comtecusa.net",
    "wof:name":"Comtec Systems Inc",
    "wof:placetype":"venue"
},
  "geometry": {"coordinates":[-75.02325399999999,39.524512],"type":"Point"}
}