{
  "type": "Feature",
  "properties": {
    "iso:country":"US",
    "sg:address":"1860 Trenton Ave",
    "sg:city":"Lakehurst",
    "sg:classifiers":[
        {
            "category":"Building & Trades",
            "subcategory":"Cleaning & Sanitation",
            "type":"Services"
        }
    ],
    "sg:phone":"+1   ",
    "sg:postcode":"08759",
    "sg:province":"NJ",
    "sg:tags":[
        "maintenance"
    ],
    "wof:name":"Ace Air Duct Cleaning",
    "wof:placetype":"venue"
},
  "geometry": {"coordinates":[-74.376886,39.933219],"type":"Point"}
}