{
  "type": "Feature",
  "properties": {
    "addr:full":"327 Norwood Ave Long Branch NJ 07740",
    "addr:housenumber":"327",
    "addr:postcode":"07740",
    "addr:street":"Norwood Ave",
    "iso:country":"US",
    "sg:address":"327 Norwood Ave",
    "sg:city":"Long Branch",
    "sg:classifiers":[
        {
            "category":"Home & Garden",
            "subcategory":"Furniture",
            "type":"Retail Goods"
        }
    ],
    "sg:phone":"+1   ",
    "sg:postcode":"07740",
    "sg:province":"NJ",
    "wof:name":"Flos Fine Furniture",
    "wof:placetype":"venue"
},
  "geometry": {"coordinates":[-74.002346,40.288004],"type":"Point"}
}