{
  "type": "Feature",
  "properties": {
    "iso:country":"US",
    "sg:address":"205 Pierron St",
    "sg:city":"Northvale",
    "sg:classifiers":[
        {
            "category":"Professional",
            "type":"Services"
        }
    ],
    "sg:phone":"+1   ",
    "sg:postcode":"07647",
    "sg:province":"NJ",
    "wof:name":"Nick Azilides",
    "wof:placetype":"venue"
},
  "geometry": {"coordinates":[-73.945725,41.009063],"type":"Point"}
}