{
  "type": "Feature",
  "properties": {
    "addr:full":"800 Rahway Ave Westfield NJ 07090",
    "addr:housenumber":"800",
    "addr:postcode":"07090",
    "addr:street":"Rahway Ave",
    "iso:country":"US",
    "sg:address":"800 Rahway Ave",
    "sg:city":"Westfield",
    "sg:classifiers":[
        {
            "category":"Education",
            "subcategory":"School",
            "type":"Public Place"
        }
    ],
    "sg:phone":"+1   ",
    "sg:postcode":"07090",
    "sg:province":"NJ",
    "sg:tags":[
        "intermediate"
    ],
    "wof:name":"Edison Intermediate School",
    "wof:placetype":"venue"
},
  "geometry": {"coordinates":[-74.34087,40.638207],"type":"Point"}
}