{
  "type": "Feature",
  "properties": {
    "iso:country":"US",
    "sg:address":"80 Broadway",
    "sg:city":"Elmwood Park",
    "sg:classifiers":[
        {
            "category":"Professional",
            "subcategory":"Lawyer & Legal Services",
            "type":"Services"
        }
    ],
    "sg:phone":"+1 201 791 8500",
    "sg:postcode":"07407",
    "sg:province":"NJ",
    "sg:tags":[
        "attorney"
    ],
    "wof:name":"Marcus & Levy",
    "wof:placetype":"venue"
},
  "geometry": {"coordinates":[-74.12791799999999,40.918327],"type":"Point"}
}