{
  "type": "Feature",
  "properties": {
    "iso:country":"US",
    "sg:address":"362 Central Ave",
    "sg:city":"Jersey City",
    "sg:classifiers":[
        {
            "category":"Shopping",
            "subcategory":"Clothing, Apparel, & Fashions",
            "type":"Retail Goods"
        }
    ],
    "sg:phone":"+1   ",
    "sg:postcode":"07307",
    "sg:province":"NJ",
    "sg:tags":[
        "woman",
        "accessory"
    ],
    "wof:name":"Discount Boutique",
    "wof:placetype":"venue"
},
  "geometry": {"coordinates":[-74.048664,40.74671],"type":"Point"}
}