{
  "type": "Feature",
  "properties": {
    "addr:full":"580 State Rte 35 Red Bank NJ 07701",
    "addr:housenumber":"580",
    "addr:postcode":"07701",
    "addr:street":"State Rte 35",
    "iso:country":"US",
    "sg:address":"580 State Rte 35",
    "sg:city":"Red Bank",
    "sg:classifiers":[
        {
            "category":"Personal",
            "subcategory":"Tanning Parlor",
            "type":"Services"
        }
    ],
    "sg:phone":"+1 732 842 9990",
    "sg:postcode":"07701",
    "sg:province":"NJ",
    "sg:tags":[
        "salon"
    ],
    "sg:website":"www.tantaztictan.com",
    "wof:name":"Tantaztic Tanning Ctr",
    "wof:placetype":"venue"
},
  "geometry": {"coordinates":[-74.09138400000001,40.379026],"type":"Point"}
}