{
  "type": "Feature",
  "properties": {
    "iso:country":"US",
    "sg:address":"89 Susan St",
    "sg:city":"Toms River",
    "sg:classifiers":[
        {
            "category":"Building & Trades",
            "subcategory":"Construction",
            "type":"Services"
        }
    ],
    "sg:phone":"+1 732 255 8787",
    "sg:postcode":"08753",
    "sg:province":"NJ",
    "sg:tags":[
        "contractor"
    ],
    "wof:name":"American Coring & Supply",
    "wof:placetype":"venue"
},
  "geometry": {"coordinates":[-74.13652399999999,40.017809],"type":"Point"}
}