{
  "type": "Feature",
  "properties": {
    "iso:country":"US",
    "sg:address":"30 Garfield Pl",
    "sg:city":"South Hackensack",
    "sg:classifiers":[
        {
            "category":"Retail",
            "subcategory":"Auto Repair",
            "type":"Services"
        }
    ],
    "sg:phone":"+1 973 473 0707",
    "sg:postcode":"07606",
    "sg:province":"NJ",
    "wof:name":"Pro Care Automotive",
    "wof:placetype":"venue"
},
  "geometry": {"coordinates":[-74.047302,40.869701],"type":"Point"}
}