{
  "type": "Feature",
  "properties": {
    "iso:country":"US",
    "sg:address":"120 Main St",
    "sg:city":"Sussex",
    "sg:classifiers":[
        {
            "category":"Local Transit",
            "type":"Transportation"
        }
    ],
    "sg:phone":"+1 973 875 7011",
    "sg:postcode":"07461",
    "sg:province":"NJ",
    "sg:tags":[
        "limousine"
    ],
    "wof:name":"Viking Limousine",
    "wof:placetype":"venue"
},
  "geometry": {"coordinates":[-74.60790799999999,41.211218],"type":"Point"}
}