{
  "type": "Feature",
  "properties": {
    "iso:country":"US",
    "sg:address":"9 Village Ct",
    "sg:city":"Demarest",
    "sg:classifiers":[
        {
            "category":"Professional",
            "subcategory":"Business Services",
            "type":"Services"
        }
    ],
    "sg:phone":"+1   ",
    "sg:postcode":"07627",
    "sg:province":"NJ",
    "wof:name":"Alyse Pinto Interiors LLC",
    "wof:placetype":"venue"
},
  "geometry": {"coordinates":[-73.9563,40.945528],"type":"Point"}
}