{
  "type": "Feature",
  "properties": {
    "iso:country":"US",
    "sg:address":"907 Pleasant Valley Ave",
    "sg:city":"Mount Laurel",
    "sg:classifiers":[
        {
            "category":"Manufacturing",
            "subcategory":"Tools & Machinery",
            "type":"Manufacturing & Wholesale Goods"
        }
    ],
    "sg:phone":"+1 856 222 0675",
    "sg:postcode":"08057",
    "sg:province":"NJ",
    "sg:tags":[
        "instrument",
        "mfg"
    ],
    "wof:name":"Quest Diagnostics 05",
    "wof:placetype":"venue"
},
  "geometry": {"coordinates":[-74.94118,39.944404],"type":"Point"}
}