{
  "type": "Feature",
  "properties": {
    "addr:full":"2037 Woodbridge Ave Edison NJ 08817",
    "addr:housenumber":"2037",
    "addr:postcode":"08817",
    "addr:street":"Woodbridge Ave",
    "iso:country":"US",
    "sg:address":"2037 Woodbridge Ave",
    "sg:city":"Edison",
    "sg:classifiers":[
        {
            "category":"Personal",
            "subcategory":"Beauty Salon",
            "type":"Services"
        }
    ],
    "sg:phone":"+1   ",
    "sg:postcode":"08817",
    "sg:province":"NJ",
    "sg:tags":[
        "shop"
    ],
    "wof:name":"Edison Hair & Nails",
    "wof:placetype":"venue"
},
  "geometry": {"coordinates":[-74.401089,40.500409],"type":"Point"}
}