{
  "type": "Feature",
  "properties": {
    "addr:full":"6 Lakeside Pl Sparta NJ 07871",
    "addr:housenumber":"6",
    "addr:postcode":"07871",
    "addr:street":"Lakeside Pl",
    "iso:country":"US",
    "sg:address":"6 Lakeside Pl",
    "sg:city":"Sparta",
    "sg:classifiers":[
        {
            "category":"Arts & Performance",
            "subcategory":"Theater",
            "type":"Entertainment"
        }
    ],
    "sg:phone":"+1 973 729 1231",
    "sg:postcode":"07871",
    "sg:province":"NJ",
    "sg:tags":[
        "live",
        "music"
    ],
    "wof:name":"Rikki Starr DJ Entertainment",
    "wof:placetype":"venue"
},
  "geometry": {"coordinates":[-74.621937,41.023794],"type":"Point"}
}