{
  "type": "Feature",
  "properties": {
    "addr:full":"444 Grand St Paterson NJ 07505",
    "addr:housenumber":"444",
    "addr:postcode":"07505",
    "addr:street":"Grand St",
    "iso:country":"US",
    "sg:address":"444 Grand St",
    "sg:city":"Paterson",
    "sg:classifiers":[
        {
            "category":"Professional",
            "subcategory":"Lawyer & Legal Services",
            "type":"Services"
        },
        {
            "category":"Arena",
            "subcategory":"Sports Club",
            "type":"Entertainment"
        }
    ],
    "sg:phone":"+1 973 357 0707",
    "sg:postcode":"07505",
    "sg:province":"NJ",
    "sg:tags":[
        "attorney"
    ],
    "wof:name":"V I P Personal Promotions",
    "wof:placetype":"venue"
},
  "geometry": {"coordinates":[-74.169391,40.913031],"type":"Point"}
}