{
  "type": "Feature",
  "properties": {
    "iso:country":"US",
    "sg:address":"98 Tamarack Cir",
    "sg:city":"Skillman",
    "sg:classifiers":[
        {
            "category":"Professional",
            "subcategory":"Employment Agencies",
            "type":"Services"
        }
    ],
    "sg:phone":"+1 609 921 7898",
    "sg:postcode":"08558",
    "sg:province":"NJ",
    "sg:tags":[
        "coach"
    ],
    "wof:name":"Robert Fass Counselor",
    "wof:placetype":"venue"
},
  "geometry": {"coordinates":[-74.645955,40.407259],"type":"Point"}
}