{
  "type": "Feature",
  "properties": {
    "iso:country":"US",
    "sg:address":"411 Main Ave",
    "sg:city":"Clifton",
    "sg:classifiers":[
        {
            "category":"Health Services",
            "subcategory":"Chiropractor",
            "type":"Services"
        }
    ],
    "sg:phone":"+1 973 473 8975",
    "sg:postcode":"07014",
    "sg:province":"NJ",
    "sg:website":"www.godslovechiropractic.com",
    "wof:name":"God's Love Chiropractic",
    "wof:placetype":"venue"
},
  "geometry": {"coordinates":[-74.134697,40.8396],"type":"Point"}
}