{
  "type": "Feature",
  "properties": {
    "addr:full":"926 Broadway Bayonne NJ 07002",
    "addr:housenumber":"926",
    "addr:postcode":"07002",
    "addr:street":"Broadway",
    "iso:country":"US",
    "sg:address":"926 Broadway",
    "sg:city":"Bayonne",
    "sg:classifiers":[
        {
            "category":"Retail",
            "subcategory":"Veterinary Services",
            "type":"Services"
        }
    ],
    "sg:phone":"+1 201 437 6666",
    "sg:postcode":"07002",
    "sg:province":"NJ",
    "sg:tags":[
        "veterinarian"
    ],
    "wof:name":"Animal Clinic of Bayonne",
    "wof:placetype":"venue"
},
  "geometry": {"coordinates":[-74.105103,40.679199],"type":"Point"}
}