{
  "type": "Feature",
  "properties": {
    "addr:full":"2301 Route 130 S Cinnaminson NJ 08077",
    "addr:housenumber":"2301",
    "addr:postcode":"08077",
    "addr:street":"Route 130 S",
    "iso:country":"US",
    "sg:address":"2301 Route 130 S",
    "sg:city":"Cinnaminson",
    "sg:classifiers":[
        {
            "category":"Shopping",
            "subcategory":"Department Store",
            "type":"Retail Goods"
        },
        {
            "category":"Shopping",
            "type":"Retail Goods"
        },
        {
            "category":"Shopping",
            "subcategory":"Discount & Variety Stores",
            "type":"Retail Goods"
        }
    ],
    "sg:phone":"+1 856 829 1128",
    "sg:postcode":"08077",
    "sg:province":"NJ",
    "sg:tags":[
        "merchandise"
    ],
    "sg:website":"http://www.dollartree.com/",
    "wof:name":"Dollar Tree",
    "wof:placetype":"venue"
},
  "geometry": {"coordinates":[-74.979433,40.00482],"type":"Point"}
}