{
  "type": "Feature",
  "properties": {
    "addr:full":"550 Getty Ave Clifton NJ 07011",
    "addr:housenumber":"550",
    "addr:postcode":"07011",
    "addr:street":"Getty Ave",
    "iso:country":"US",
    "sg:address":"550 Getty Ave",
    "sg:city":"Clifton",
    "sg:classifiers":[
        {
            "category":"Shopping",
            "subcategory":"Clothing, Apparel, & Fashions",
            "type":"Retail Goods"
        }
    ],
    "sg:phone":"+1   ",
    "sg:postcode":"07011",
    "sg:province":"NJ",
    "sg:tags":[
        "toy"
    ],
    "wof:name":"Childrens Wear Center",
    "wof:placetype":"venue"
},
  "geometry": {"coordinates":[-74.152153,40.889845],"type":"Point"}
}