{
  "type": "Feature",
  "properties": {
    "addr:full":"203 White Horse Pike Egg Harbor City NJ 08215",
    "addr:housenumber":"203",
    "addr:postcode":"08215",
    "addr:street":"White Horse Pike",
    "iso:country":"US",
    "sg:address":"203 White Horse Pike",
    "sg:city":"Egg Harbor City",
    "sg:classifiers":[
        {
            "category":"Home & Garden",
            "subcategory":"Furniture",
            "type":"Retail Goods"
        }
    ],
    "sg:phone":"+1   ",
    "sg:postcode":"08215",
    "sg:province":"NJ",
    "wof:name":"Ideal Furniture",
    "wof:placetype":"venue"
},
  "geometry": {"coordinates":[-74.65175499999999,39.531758],"type":"Point"}
}