{
  "type": "Feature",
  "properties": {
    "addr:full":"1547 US Hwy 9 Cape May Ct Hse NJ 08210",
    "addr:housenumber":"1547",
    "addr:postcode":"08210",
    "addr:street":"Us Hwy 9 Cape May Ct",
    "iso:country":"US",
    "sg:address":"1547 US Hwy 9",
    "sg:city":"Cape May Ct Hse",
    "sg:classifiers":[
        {
            "category":"Health Services",
            "subcategory":"Chiropractor",
            "type":"Services"
        }
    ],
    "sg:phone":"+1 609 463 4590",
    "sg:postcode":"08210",
    "sg:province":"NJ",
    "wof:name":"Farrell Chiropractic & Rehab",
    "wof:placetype":"venue"
},
  "geometry": {"coordinates":[-74.790133,39.123076],"type":"Point"}
}