{
  "type": "Feature",
  "properties": {
    "iso:country":"US",
    "sg:address":"6 Telegraph Hill Rd",
    "sg:city":"Holmdel",
    "sg:classifiers":[
        {
            "category":"Building & Trades",
            "subcategory":"Construction",
            "type":"Services"
        }
    ],
    "sg:phone":"+1 732 208 0109",
    "sg:postcode":"07733",
    "sg:province":"NJ",
    "sg:tags":[
        "contractor"
    ],
    "wof:name":"Bruno Pruscino Masonry Inc",
    "wof:placetype":"venue"
},
  "geometry": {"coordinates":[-74.18187399999999,40.409789],"type":"Point"}
}