{
  "type": "Feature",
  "properties": {
    "addr:full":"1020 Broad St Newark NJ 07102",
    "addr:housenumber":"1020",
    "addr:postcode":"07102",
    "addr:street":"Broad St",
    "iso:country":"US",
    "sg:address":"1020 Broad St",
    "sg:city":"Newark",
    "sg:classifiers":[
        {
            "category":"Organizations",
            "subcategory":"Non-profit Organization",
            "type":"Services"
        }
    ],
    "sg:phone":"+1 973 623 1033",
    "sg:postcode":"07102",
    "sg:province":"NJ",
    "sg:tags":[
        "performing",
        "art"
    ],
    "wof:name":"Garden State Ballet School",
    "wof:placetype":"venue"
},
  "geometry": {"coordinates":[-74.176399,40.728298],"type":"Point"}
}