{
  "type": "Feature",
  "properties": {
    "iso:country":"US",
    "sg:address":"125 Washington Ave Ste 7",
    "sg:city":"Dumont",
    "sg:classifiers":[
        {
            "category":"Insurance",
            "subcategory":"Insurance Agent",
            "type":"Services"
        },
        {
            "category":"Insurance",
            "subcategory":"Hazard Insurance",
            "type":"Services"
        }
    ],
    "sg:phone":"+1 201 384 4446",
    "sg:postcode":"07628",
    "sg:province":"NJ",
    "sg:tags":[
        "consultant",
        "analyst"
    ],
    "wof:name":"E Payne Susan & Associates Inc",
    "wof:placetype":"venue"
},
  "geometry": {"coordinates":[-73.993846,40.940258],"type":"Point"}
}