{
  "type": "Feature",
  "properties": {
    "iso:country":"US",
    "sg:address":"34 Black Rd",
    "sg:city":"Trenton",
    "sg:classifiers":[
        {
            "category":"Building & Trades",
            "subcategory":"Construction",
            "type":"Services"
        }
    ],
    "sg:phone":"+1 609 586 9986",
    "sg:postcode":"08648",
    "sg:province":"NJ",
    "sg:tags":[
        "concrete",
        "contractor"
    ],
    "wof:name":"Adcon Inc",
    "wof:placetype":"venue"
},
  "geometry": {"coordinates":[-74.690288,40.274026],"type":"Point"}
}