{
  "type": "Feature",
  "properties": {
    "iso:country":"US",
    "sg:address":"5 S Main St",
    "sg:city":"Englishtown",
    "sg:classifiers":[
        {
            "category":"Freight",
            "type":"Transportation"
        }
    ],
    "sg:phone":"+1 732 446 1699",
    "sg:postcode":"07726",
    "sg:province":"NJ",
    "sg:tags":[
        "delivery"
    ],
    "wof:name":"Vargas Delivery Svc Inc",
    "wof:placetype":"venue"
},
  "geometry": {"coordinates":[-74.361611,40.292036],"type":"Point"}
}