{
  "type": "Feature",
  "properties": {
    "addr:full":"171 Main St South River NJ 08882",
    "addr:housenumber":"171",
    "addr:postcode":"08882",
    "addr:street":"Main St",
    "iso:country":"US",
    "sg:address":"171 Main St",
    "sg:city":"South River",
    "sg:classifiers":[
        {
            "category":"Health Services",
            "subcategory":"Chiropractor",
            "type":"Services"
        }
    ],
    "sg:phone":"+1 732 257 0555",
    "sg:postcode":"08882",
    "sg:province":"NJ",
    "wof:name":"Daniel S Gray Dr",
    "wof:placetype":"venue"
},
  "geometry": {"coordinates":[-74.384856,40.44762],"type":"Point"}
}