{
  "type": "Feature",
  "properties": {
    "addr:full":"1816 Englishtown Rd Old Bridge NJ 08857",
    "addr:housenumber":"1816",
    "addr:postcode":"08857",
    "addr:street":"Englishtown Rd",
    "iso:country":"US",
    "sg:address":"1816 Englishtown Rd",
    "sg:city":"Old Bridge",
    "sg:classifiers":[
        {
            "category":"Building & Trades",
            "subcategory":"Construction",
            "type":"Services"
        }
    ],
    "sg:phone":"+1 732 251 2294",
    "sg:postcode":"08857",
    "sg:province":"NJ",
    "sg:tags":[
        "builder",
        "patio",
        "deck"
    ],
    "wof:name":"Powers Custo Patios & Landscpg",
    "wof:placetype":"venue"
},
  "geometry": {"coordinates":[-74.35490799999999,40.356866],"type":"Point"}
}