{
  "type": "Feature",
  "properties": {
    "addr:full":"94 Fulton St Paterson NJ 07501",
    "addr:housenumber":"94",
    "addr:postcode":"07501",
    "addr:street":"Fulton St",
    "iso:country":"US",
    "sg:address":"94 Fulton St",
    "sg:city":"Paterson",
    "sg:classifiers":[
        {
            "category":"Building & Trades",
            "subcategory":"Construction",
            "type":"Services"
        }
    ],
    "sg:phone":"+1 973 742 7008",
    "sg:postcode":"07501",
    "sg:province":"NJ",
    "sg:tags":[
        "maker",
        "cabinet"
    ],
    "wof:name":"C D C Products Inc",
    "wof:placetype":"venue"
},
  "geometry": {"coordinates":[-74.163766,40.923533],"type":"Point"}
}