{
  "type": "Feature",
  "properties": {
    "addr:full":"2115 Millburn Ave Maplewood NJ 07040",
    "addr:housenumber":"2115",
    "addr:postcode":"07040",
    "addr:street":"Millburn Ave",
    "iso:country":"US",
    "sg:address":"2115 Millburn Ave",
    "sg:city":"Maplewood",
    "sg:classifiers":[
        {
            "category":"Social Services",
            "type":"Services"
        }
    ],
    "sg:phone":"+1 973 762 5088",
    "sg:postcode":"07040",
    "sg:province":"NJ",
    "sg:tags":[
        "worker"
    ],
    "wof:name":"Denise Endress",
    "wof:placetype":"venue"
},
  "geometry": {"coordinates":[-74.281087,40.721629],"type":"Point"}
}