{
  "type": "Feature",
  "properties": {
    "addr:full":"399 Mantoloking Rd Brick NJ 08723",
    "addr:housenumber":"399",
    "addr:postcode":"08723",
    "addr:street":"Mantoloking Rd",
    "iso:country":"US",
    "sg:address":"399 Mantoloking Rd",
    "sg:city":"Brick",
    "sg:classifiers":[
        {
            "category":"Restaurant",
            "type":"Food & Drink"
        }
    ],
    "sg:phone":"+1 732 920 1221",
    "sg:postcode":"08723",
    "sg:province":"NJ",
    "sg:tags":[
        "sandwich"
    ],
    "wof:name":"That's A Wrap",
    "wof:placetype":"venue"
},
  "geometry": {"coordinates":[-74.090434,40.045352],"type":"Point"}
}