{
  "type": "Feature",
  "properties": {
    "iso:country":"US",
    "sg:address":"5 N Main St",
    "sg:city":"Manasquan",
    "sg:classifiers":[
        {
            "category":"Mining & Drilling",
            "type":"Manufacturing & Wholesale Goods"
        }
    ],
    "sg:phone":"+1 732 223 5400",
    "sg:postcode":"08736",
    "sg:province":"NJ",
    "sg:tags":[
        "oil",
        "gas",
        "producer"
    ],
    "wof:name":"Schafer Oil Co Inc",
    "wof:placetype":"venue"
},
  "geometry": {"coordinates":[-74.053178,40.127741],"type":"Point"}
}