{
  "type": "Feature",
  "properties": {
    "iso:country":"US",
    "sg:address":"144 Mount Horeb Rd",
    "sg:city":"Warren",
    "sg:classifiers":[
        {
            "category":"Building & Trades",
            "subcategory":"Electrical",
            "type":"Services"
        }
    ],
    "sg:phone":"+1 732 469 0281",
    "sg:postcode":"07059",
    "sg:province":"NJ",
    "sg:tags":[
        "electric",
        "contractor"
    ],
    "wof:name":"Cooney Electrical Svc",
    "wof:placetype":"venue"
},
  "geometry": {"coordinates":[-74.522139,40.624058],"type":"Point"}
}