{
  "type": "Feature",
  "properties": {
    "addr:full":"88 Parkhurst St Newark NJ 07114",
    "addr:housenumber":"88",
    "addr:postcode":"07114",
    "addr:street":"Parkhurst St",
    "iso:country":"US",
    "sg:address":"88 Parkhurst St",
    "sg:city":"Newark",
    "sg:classifiers":[
        {
            "category":"Professional",
            "type":"Services"
        }
    ],
    "sg:phone":"+1   ",
    "sg:postcode":"07114",
    "sg:province":"NJ",
    "wof:name":"Taylor Service Co",
    "wof:placetype":"venue"
},
  "geometry": {"coordinates":[-74.177419,40.722508],"type":"Point"}
}