{
  "type": "Feature",
  "properties": {
    "iso:country":"US",
    "sg:address":"3 Buckeye Dr",
    "sg:city":"Flemington",
    "sg:classifiers":[
        {
            "category":"Professional",
            "subcategory":"Computer Services",
            "type":"Services"
        }
    ],
    "sg:phone":"+1 908 788 8202",
    "sg:postcode":"08857",
    "sg:province":"NJ",
    "wof:name":"Computer Science Corp",
    "wof:placetype":"venue"
},
  "geometry": {"coordinates":[-74.33078399999999,40.38371],"type":"Point"}
}