{
  "type": "Feature",
  "properties": {
    "iso:country":"US",
    "sg:address":"5 Otter Hill Ct",
    "sg:city":"Sussex",
    "sg:classifiers":[
        {
            "category":"Building & Trades",
            "subcategory":"Equipment Rental",
            "type":"Services"
        }
    ],
    "sg:phone":"+1   ",
    "sg:postcode":"07461",
    "sg:province":"NJ",
    "wof:name":"Aviation Club",
    "wof:placetype":"venue"
},
  "geometry": {"coordinates":[-74.541264,41.215145],"type":"Point"}
}