{
  "type": "Feature",
  "properties": {
    "addr:full":"1 Graphics Dr Trenton NJ 08628",
    "addr:postcode":"08628",
    "addr:street":"Dr",
    "iso:country":"US",
    "sg:address":"1 Graphics Dr",
    "sg:city":"Trenton",
    "sg:classifiers":[
        {
            "category":"Manufacturing",
            "subcategory":"Printing",
            "type":"Manufacturing & Wholesale Goods"
        }
    ],
    "sg:phone":"+1 609 771 0555",
    "sg:postcode":"08628",
    "sg:province":"NJ",
    "sg:tags":[
        "bookbinder"
    ],
    "sg:website":"www.regalprinting.com",
    "wof:name":"Riegel Printing Co",
    "wof:placetype":"venue"
},
  "geometry": {"coordinates":[-74.801604,40.279044],"type":"Point"}
}