{
  "type": "Feature",
  "properties": {
    "addr:full":"198 Walnut St Northvale NJ 07647",
    "addr:housenumber":"198",
    "addr:postcode":"07647",
    "addr:street":"Walnut St",
    "iso:country":"US",
    "sg:address":"198 Walnut St",
    "sg:city":"Northvale",
    "sg:classifiers":[
        {
            "category":"Retail",
            "subcategory":"Repair Shop",
            "type":"Services"
        }
    ],
    "sg:phone":"+1 201 328 0640",
    "sg:postcode":"07647",
    "sg:province":"NJ",
    "sg:tags":[
        "lock",
        "locksmith"
    ],
    "wof:name":"24 Hour Emergency Locksmith",
    "wof:placetype":"venue"
},
  "geometry": {"coordinates":[-73.94611999999999,41.003879],"type":"Point"}
}