{
  "type": "Feature",
  "properties": {
    "addr:full":"172 E Kinney St Newark NJ 07105",
    "addr:housenumber":"172",
    "addr:postcode":"07105",
    "addr:street":"E Kinney St",
    "iso:country":"US",
    "sg:address":"172 E Kinney St",
    "sg:city":"Newark",
    "sg:classifiers":[
        {
            "category":"Social Services",
            "subcategory":"Child Care",
            "type":"Services"
        }
    ],
    "sg:phone":"+1 973 344 1835",
    "sg:postcode":"07105",
    "sg:province":"NJ",
    "sg:tags":[
        "day"
    ],
    "wof:name":"Fairy Tales Day Care Inc",
    "wof:placetype":"venue"
},
  "geometry": {"coordinates":[-74.16720599999999,40.725872],"type":"Point"}
}