{
  "type": "Feature",
  "properties": {
    "addr:full":"22 Church St Rumson NJ 07760",
    "addr:housenumber":"22",
    "addr:postcode":"07760",
    "addr:street":"Church St",
    "iso:country":"US",
    "sg:address":"22 Church St",
    "sg:city":"Rumson",
    "sg:classifiers":[
        {
            "category":"Freight",
            "type":"Transportation"
        }
    ],
    "sg:phone":"+1 732 219 5093",
    "sg:postcode":"07760",
    "sg:province":"NJ",
    "sg:tags":[
        "local",
        "trucking"
    ],
    "wof:name":"T W Stack Enterprise",
    "wof:placetype":"venue"
},
  "geometry": {"coordinates":[-73.97411099999999,40.361466],"type":"Point"}
}