{
  "type": "Feature",
  "properties": {
    "addr:full":"14 Foxwood Ct Sicklerville NJ 08081",
    "addr:housenumber":"14",
    "addr:postcode":"08081",
    "addr:street":"Foxwood Ct",
    "iso:country":"US",
    "sg:address":"14 Foxwood Ct",
    "sg:city":"Sicklerville",
    "sg:classifiers":[
        {
            "category":"Building & Trades",
            "subcategory":"Cleaning & Sanitation",
            "type":"Services"
        }
    ],
    "sg:phone":"+1   ",
    "sg:postcode":"08081",
    "sg:province":"NJ",
    "sg:tags":[
        "maintenance"
    ],
    "wof:name":"Clean Masters Janitorial Svcs",
    "wof:placetype":"venue"
},
  "geometry": {"coordinates":[-75.018652,39.751833],"type":"Point"}
}