{
  "type": "Feature",
  "properties": {
    "iso:country":"US",
    "sg:address":"1016 Montauk Dr",
    "sg:city":"Forked River",
    "sg:classifiers":[
        {
            "category":"Building & Trades",
            "subcategory":"Construction",
            "type":"Services"
        }
    ],
    "sg:phone":"+1 609 693 8998",
    "sg:postcode":"08731",
    "sg:province":"NJ",
    "sg:tags":[
        "home",
        "general",
        "contractor"
    ],
    "wof:name":"Kretzer & Sons Inc",
    "wof:placetype":"venue"
},
  "geometry": {"coordinates":[-74.156289,39.84372],"type":"Point"}
}