{
  "type": "Feature",
  "properties": {
    "iso:country":"US",
    "sg:address":"662 Peach St",
    "sg:city":"Hammonton",
    "sg:classifiers":[
        {
            "category":"Freight",
            "type":"Transportation"
        }
    ],
    "sg:phone":"+1 609 561 3432",
    "sg:postcode":"08037",
    "sg:province":"NJ",
    "wof:name":"JRK Transport",
    "wof:placetype":"venue"
},
  "geometry": {"coordinates":[-74.792215,39.64292],"type":"Point"}
}