{
  "type": "Feature",
  "properties": {
    "addr:full":"1000 Crawford Pl Mount Laurel NJ 08054",
    "addr:housenumber":"1000",
    "addr:postcode":"08054",
    "addr:street":"Crawford Pl",
    "iso:country":"US",
    "sg:address":"1000 Crawford Pl",
    "sg:city":"Mount Laurel",
    "sg:classifiers":[
        {
            "category":"Government",
            "subcategory":"Office",
            "type":"Public Place"
        }
    ],
    "sg:phone":"+1   ",
    "sg:postcode":"08054",
    "sg:province":"NJ",
    "sg:tags":[
        "explosive",
        "bureau",
        "alcohol",
        "tobacco",
        "firearm"
    ],
    "wof:name":"Alcohol Tob Firearms Expl Bur",
    "wof:placetype":"venue"
},
  "geometry": {"coordinates":[-74.947125,39.915658],"type":"Point"}
}