{
  "type": "Feature",
  "properties": {
    "addr:full":"347 Sanford Ave Newark NJ 07106",
    "addr:housenumber":"347",
    "addr:postcode":"07106",
    "addr:street":"Sanford Ave",
    "iso:country":"US",
    "sg:address":"347 Sanford Ave",
    "sg:city":"Newark",
    "sg:classifiers":[
        {
            "category":"Building & Trades",
            "subcategory":"Plumbing",
            "type":"Services"
        }
    ],
    "sg:phone":"+1 973 372 6686",
    "sg:postcode":"07106",
    "sg:province":"NJ",
    "sg:tags":[
        "plumbing",
        "contractor"
    ],
    "wof:name":"Wagner Plumbing & Heating",
    "wof:placetype":"venue"
},
  "geometry": {"coordinates":[-74.231094,40.750127],"type":"Point"}
}