{
  "type": "Feature",
  "properties": {
    "addr:full":"21 Bridge St Lambertville NJ 08530",
    "addr:housenumber":"21",
    "addr:postcode":"08530",
    "addr:street":"Bridge St",
    "iso:country":"US",
    "sg:address":"21 Bridge St",
    "sg:city":"Lambertville",
    "sg:classifiers":[
        {
            "category":"Organizations",
            "subcategory":"Non-profit Organization",
            "type":"Services"
        }
    ],
    "sg:phone":"+1 609 397 3230",
    "sg:postcode":"08530",
    "sg:province":"NJ",
    "wof:name":"Amwell Lodge F & AM",
    "wof:placetype":"venue"
},
  "geometry": {"coordinates":[-74.945618,40.365446],"type":"Point"}
}