{
  "type": "Feature",
  "properties": {
    "addr:full":"16 Broadway Fair Lawn NJ 07410",
    "addr:housenumber":"16",
    "addr:postcode":"07410",
    "addr:street":"Broadway",
    "iso:country":"US",
    "sg:address":"16 Broadway",
    "sg:city":"Fair Lawn",
    "sg:classifiers":[
        {
            "category":"Utilities",
            "subcategory":"Mobile Phone",
            "type":"Services"
        }
    ],
    "sg:phone":"+1 201 791 5115",
    "sg:postcode":"07410",
    "sg:province":"NJ",
    "sg:tags":[
        "telephone",
        "cellular"
    ],
    "wof:name":"Cingular Wireless",
    "wof:placetype":"venue"
},
  "geometry": {"coordinates":[-74.121326,40.920178],"type":"Point"}
}