{
  "type": "Feature",
  "properties": {
    "addr:full":"333 New Road Parsippany NJ 07054",
    "addr:housenumber":"333",
    "addr:postcode":"07054",
    "addr:street":"New Road",
    "iso:country":"US",
    "sg:address":"333 New Road",
    "sg:city":"Parsippany",
    "sg:classifiers":[
        {
            "category":"Home & Garden",
            "subcategory":"Building Materials",
            "type":"Retail Goods"
        }
    ],
    "sg:phone":"+1 973 575 0760",
    "sg:postcode":"07054",
    "sg:province":"NJ",
    "sg:tags":[
        "supply"
    ],
    "sg:website":"www.fluorotherm.com",
    "wof:name":"Fluorotherm Polymers Inc.",
    "wof:placetype":"venue"
},
  "geometry": {"coordinates":[-74.34878999999999,40.8538],"type":"Point"}
}