{
  "type": "Feature",
  "properties": {
    "addr:full":"903 Bergen Ave Jersey City NJ 07306",
    "addr:housenumber":"903",
    "addr:postcode":"07306",
    "addr:street":"Bergen Ave",
    "iso:country":"US",
    "sg:address":"903 Bergen Ave",
    "sg:city":"Jersey City",
    "sg:classifiers":[
        {
            "category":"Restaurant",
            "type":"Food & Drink"
        }
    ],
    "sg:phone":"+1   ",
    "sg:postcode":"07306",
    "sg:province":"NJ",
    "sg:tags":[
        "eating"
    ],
    "wof:name":"New Yorker Deli Pizza Plus",
    "wof:placetype":"venue"
},
  "geometry": {"coordinates":[-74.065421,40.729805],"type":"Point"}
}