{
  "type": "Feature",
  "properties": {
    "addr:full":"931 Fischer Blvd Toms River NJ 08753",
    "addr:housenumber":"931",
    "addr:postcode":"08753",
    "addr:street":"Fischer Blvd",
    "iso:country":"US",
    "sg:address":"931 Fischer Blvd",
    "sg:city":"Toms River",
    "sg:classifiers":[
        {
            "category":"Restaurant",
            "type":"Food & Drink"
        }
    ],
    "sg:phone":"+1   ",
    "sg:postcode":"08753",
    "sg:province":"NJ",
    "sg:tags":[
        "eating"
    ],
    "wof:name":"Burger King",
    "wof:placetype":"venue"
},
  "geometry": {"coordinates":[-74.138284,39.976424],"type":"Point"}
}