{
  "type": "Feature",
  "properties": {
    "iso:country":"US",
    "sg:address":"12 Klemm Ave",
    "sg:city":"Gloucester City",
    "sg:classifiers":[
        {
            "category":"Manufacturing",
            "subcategory":"Metals",
            "type":"Manufacturing & Wholesale Goods"
        }
    ],
    "sg:phone":"+1 856 456 9055",
    "sg:postcode":"08030",
    "sg:province":"NJ",
    "sg:tags":[
        "steel",
        "mfg",
        "contractor",
        "trade",
        "fabrication",
        "structural"
    ],
    "wof:name":"H Barron Iron Works Inc",
    "wof:placetype":"venue"
},
  "geometry": {"coordinates":[-75.108999,39.891454],"type":"Point"}
}