{
  "type": "Feature",
  "properties": {
    "iso:country":"US",
    "sg:address":"Washington Blvd & Town Square Pl",
    "sg:city":"Jersey City",
    "sg:classifiers":[
        {
            "category":"Restaurant",
            "type":"Food & Drink"
        },
        {
            "category":"Food Court",
            "type":"Food & Drink"
        }
    ],
    "sg:postcode":"07310",
    "sg:province":"NJ",
    "sg:tags":[
        "middle",
        "stand",
        "eastern"
    ],
    "wof:name":"Halal Cart",
    "wof:placetype":"venue"
},
  "geometry": {"coordinates":[-74.03474,40.726703],"type":"Point"}
}