{
  "type": "Feature",
  "properties": {
    "iso:country":"US",
    "sg:address":"2064 Winding Brook Way",
    "sg:city":"Scotch Plains",
    "sg:classifiers":[
        {
            "category":"Wholesale",
            "subcategory":"Durable Goods & Equipment",
            "type":"Manufacturing & Wholesale Goods"
        }
    ],
    "sg:phone":"+1 908 654 0908",
    "sg:postcode":"07076",
    "sg:province":"NJ",
    "sg:tags":[
        "professional",
        "r",
        "repair"
    ],
    "wof:name":"Island Laser",
    "wof:placetype":"venue"
},
  "geometry": {"coordinates":[-74.33807299999999,40.621673],"type":"Point"}
}