{
  "type": "Feature",
  "properties": {
    "iso:country":"US",
    "sg:address":"100 Warren St",
    "sg:city":"Jersey City",
    "sg:classifiers":[
        {
            "category":"Professional",
            "subcategory":"Computer Services",
            "type":"Services"
        }
    ],
    "sg:phone":"+1   ",
    "sg:postcode":"07302",
    "sg:province":"NJ",
    "sg:tags":[
        "related"
    ],
    "wof:name":"Zen Matrix Data Inc",
    "wof:placetype":"venue"
},
  "geometry": {"coordinates":[-74.03993800000001,40.712249],"type":"Point"}
}