{
  "type": "Feature",
  "properties": {
    "iso:country":"US",
    "sg:address":"525 E County Line Rd",
    "sg:city":"Lakewood",
    "sg:classifiers":[
        {
            "category":"Professional",
            "subcategory":"Management & Consulting",
            "type":"Services"
        }
    ],
    "sg:phone":"+1 732 730 9248",
    "sg:postcode":"08701",
    "sg:province":"NJ",
    "sg:tags":[
        "fuel"
    ],
    "wof:name":"Makom Management Svc",
    "wof:placetype":"venue"
},
  "geometry": {"coordinates":[-74.205592,40.105314],"type":"Point"}
}