{
  "type": "Feature",
  "properties": {
    "iso:country":"US",
    "sg:address":"909 Park Ave",
    "sg:city":"Plainfield",
    "sg:classifiers":[
        {
            "category":"Professional",
            "subcategory":"Management & Consulting",
            "type":"Services"
        }
    ],
    "sg:phone":"+1 908 757 5597",
    "sg:postcode":"07060",
    "sg:province":"NJ",
    "sg:tags":[
        "marketing",
        "program"
    ],
    "wof:name":"Milestone Marketing Inc",
    "wof:placetype":"venue"
},
  "geometry": {"coordinates":[-74.411945,40.611832],"type":"Point"}
}