{
  "type": "Feature",
  "properties": {
    "iso:country":"US",
    "sg:address":"3201 Bayshore Ave",
    "sg:city":"Brigantine",
    "sg:classifiers":[
        {
            "category":"Insurance",
            "subcategory":"Insurance Agent",
            "type":"Services"
        }
    ],
    "sg:phone":"+1 609 266 7541",
    "sg:postcode":"08203",
    "sg:province":"NJ",
    "wof:name":"LTC Horizons",
    "wof:placetype":"venue"
},
  "geometry": {"coordinates":[-74.38860200000001,39.395351],"type":"Point"}
}