{
  "type": "Feature",
  "properties": {
    "iso:country":"US",
    "sg:address":"1400 State Rte 35",
    "sg:city":"Ocean",
    "sg:classifiers":[
        {
            "category":"Professional",
            "subcategory":"Business Services",
            "type":"Services"
        }
    ],
    "sg:phone":"+1 732 660 1194",
    "sg:postcode":"07712",
    "sg:province":"NJ",
    "wof:name":"Cardiac Imaging Ctr",
    "wof:placetype":"venue"
},
  "geometry": {"coordinates":[-74.03821600000001,40.245845],"type":"Point"}
}