{
  "type": "Feature",
  "properties": {
    "addr:full":"24 S White Horse Pike Clementon NJ 08021",
    "addr:housenumber":"24",
    "addr:postcode":"08021",
    "addr:street":"S White Horse Pike",
    "iso:country":"US",
    "sg:address":"24 S White Horse Pike",
    "sg:city":"Clementon",
    "sg:classifiers":[
        {
            "category":"Insurance",
            "subcategory":"Insurance Agent",
            "type":"Services"
        }
    ],
    "sg:phone":"+1   ",
    "sg:postcode":"08021",
    "sg:province":"NJ",
    "sg:tags":[
        "business"
    ],
    "wof:name":"Farinelli Insurance Agency",
    "wof:placetype":"venue"
},
  "geometry": {"coordinates":[-74.992952,39.817534],"type":"Point"}
}