{
  "type": "Feature",
  "properties": {
    "addr:full":"122 Main St Flemington NJ 08822",
    "addr:housenumber":"122",
    "addr:postcode":"08822",
    "addr:street":"Main St",
    "iso:country":"US",
    "sg:address":"122 Main St",
    "sg:city":"Flemington",
    "sg:classifiers":[
        {
            "category":"Social Services",
            "type":"Services"
        }
    ],
    "sg:phone":"+1 908 788 6044",
    "sg:postcode":"08822",
    "sg:province":"NJ",
    "wof:name":"Bukowski Kathryn Acsw Bcd",
    "wof:placetype":"venue"
},
  "geometry": {"coordinates":[-74.858678,40.509111],"type":"Point"}
}