{
  "type": "Feature",
  "properties": {
    "addr:full":"25 Washington Pl Morristown NJ 07960",
    "addr:housenumber":"25",
    "addr:postcode":"07960",
    "addr:street":"Washington Pl",
    "iso:country":"US",
    "sg:address":"25 Washington Pl",
    "sg:city":"Morristown",
    "sg:classifiers":[
        {
            "category":"Travel",
            "subcategory":"Travel Agent",
            "type":"Entertainment"
        }
    ],
    "sg:phone":"+1 973 605 2456",
    "sg:postcode":"07960",
    "sg:province":"NJ",
    "sg:tags":[
        "cruise"
    ],
    "wof:name":"Cruise & Vacation Views",
    "wof:placetype":"venue"
},
  "geometry": {"coordinates":[-74.466019,40.797406],"type":"Point"}
}