{
  "type": "Feature",
  "properties": {
    "addr:full":"70 Longfellow St Carteret NJ 07008",
    "addr:housenumber":"70",
    "addr:postcode":"07008",
    "addr:street":"Longfellow St",
    "iso:country":"US",
    "sg:address":"70 Longfellow St",
    "sg:city":"Carteret",
    "sg:classifiers":[
        {
            "category":"Building & Trades",
            "subcategory":"Landscaping Services",
            "type":"Services"
        }
    ],
    "sg:phone":"+1 732 541 7800",
    "sg:postcode":"07008",
    "sg:province":"NJ",
    "sg:tags":[
        "landscape",
        "contractor"
    ],
    "wof:name":"C & M Landscaping Inc",
    "wof:placetype":"venue"
},
  "geometry": {"coordinates":[-74.22506,40.577147],"type":"Point"}
}