{
  "type": "Feature",
  "properties": {
    "iso:country":"US",
    "sg:address":"33 Osborne St",
    "sg:city":"Bloomfield",
    "sg:classifiers":[
        {
            "category":"Social Services",
            "subcategory":"Child Care",
            "type":"Services"
        }
    ],
    "sg:phone":"+1   ",
    "sg:postcode":"07003",
    "sg:province":"NJ",
    "sg:tags":[
        "day"
    ],
    "wof:name":"Argownauts",
    "wof:placetype":"venue"
},
  "geometry": {"coordinates":[-74.19476299999999,40.805067],"type":"Point"}
}