{
  "type": "Feature",
  "properties": {
    "iso:country":"US",
    "sg:address":"1301 Union Ave",
    "sg:city":"Pennsauken",
    "sg:classifiers":[
        {
            "category":"Professional",
            "type":"Services"
        }
    ],
    "sg:phone":"+1 856 665 1810",
    "sg:postcode":"08110",
    "sg:province":"NJ",
    "sg:tags":[
        "establishment"
    ],
    "wof:name":"Co-Packing Specialists Inc",
    "wof:placetype":"venue"
},
  "geometry": {"coordinates":[-75.043933,39.978159],"type":"Point"}
}