{
  "type": "Feature",
  "properties": {
    "iso:country":"US",
    "sg:address":"457 Bender Ave",
    "sg:city":"Iselin",
    "sg:classifiers":[
        {
            "category":"Professional",
            "type":"Services"
        }
    ],
    "sg:phone":"+1   ",
    "sg:postcode":"08830",
    "sg:province":"NJ",
    "wof:name":"Suburb Svc",
    "wof:placetype":"venue"
},
  "geometry": {"coordinates":[-74.334889,40.581265],"type":"Point"}
}