{
  "type": "Feature",
  "properties": {
    "addr:full":"16 Daisy Ct Sayreville NJ 08872",
    "addr:housenumber":"16",
    "addr:postcode":"08872",
    "addr:street":"Daisy Ct",
    "iso:country":"US",
    "sg:address":"16 Daisy Ct",
    "sg:city":"Sayreville",
    "sg:classifiers":[
        {
            "category":"Local Transit",
            "type":"Transportation"
        }
    ],
    "sg:phone":"+1 732 991 5952",
    "sg:postcode":"08872",
    "sg:province":"NJ",
    "sg:tags":[
        "passenger"
    ],
    "wof:name":"Signature Limousine",
    "wof:placetype":"venue"
},
  "geometry": {"coordinates":[-74.334138,40.470169],"type":"Point"}
}