{
  "type": "Feature",
  "properties": {
    "iso:country":"US",
    "sg:address":"488 Colonial Ter",
    "sg:city":"Hackensack",
    "sg:classifiers":[
        {
            "category":"Real Estate",
            "subcategory":"Real Estate Operator",
            "type":"Services"
        }
    ],
    "sg:phone":"+1 201 489 9187",
    "sg:postcode":"07601",
    "sg:province":"NJ",
    "sg:tags":[
        "building",
        "apartment"
    ],
    "wof:name":"Suburban Terrace Apartments",
    "wof:placetype":"venue"
},
  "geometry": {"coordinates":[-74.05625999999999,40.896642],"type":"Point"}
}