{
  "type": "Feature",
  "properties": {
    "addr:full":"504 N South Carolina Ave Atlantic City NJ 08401",
    "addr:housenumber":"504",
    "addr:postcode":"08401",
    "addr:street":"N South Carolina Ave",
    "iso:country":"US",
    "sg:address":"504 N South Carolina Ave",
    "sg:city":"Atlantic City",
    "sg:classifiers":[
        {
            "category":"Organizations",
            "subcategory":"Non-profit Organization",
            "type":"Services"
        }
    ],
    "sg:phone":"+1 609 344 2066",
    "sg:postcode":"08401",
    "sg:province":"NJ",
    "wof:name":"Multicultural Commissioners",
    "wof:placetype":"venue"
},
  "geometry": {"coordinates":[-74.432233,39.370593],"type":"Point"}
}