{
  "type": "Feature",
  "properties": {
    "addr:full":"875 State Hwy 3 Ser NE Secaucus NJ 07094",
    "addr:housenumber":"875",
    "addr:postcode":"07094",
    "addr:street":"State Hwy 3 Ser Ne",
    "iso:country":"US",
    "sg:address":"875 State Hwy 3 Ser NE",
    "sg:city":"Secaucus",
    "sg:classifiers":[
        {
            "category":"Travel",
            "subcategory":"Hotels & Motels",
            "type":"Entertainment"
        }
    ],
    "sg:phone":"+1 201 864 1400",
    "sg:postcode":"07094",
    "sg:province":"NJ",
    "wof:name":"Hilton Garden Inn-Secaucus Meadowlands",
    "wof:placetype":"venue"
},
  "geometry": {"coordinates":[-74.0625,40.7911],"type":"Point"}
}