{
  "type": "Feature",
  "properties": {
    "iso:country":"US",
    "sg:address":"201 Prospect Ave",
    "sg:city":"Dunellen",
    "sg:classifiers":[
        {
            "category":"Organizations",
            "subcategory":"Community Association",
            "type":"Services"
        }
    ],
    "sg:phone":"+1   ",
    "sg:postcode":"08812",
    "sg:province":"NJ",
    "wof:name":"Veterans Foreign Wars Tri-Boro",
    "wof:placetype":"venue"
},
  "geometry": {"coordinates":[-74.46367600000001,40.587863],"type":"Point"}
}