{
  "type": "Feature",
  "properties": {
    "iso:country":"US",
    "sg:address":"136 Main St",
    "sg:city":"Princeton",
    "sg:classifiers":[
        {
            "category":"Banks & Credit Unions",
            "subcategory":"Investment Brokerage",
            "type":"Services"
        }
    ],
    "sg:phone":"+1 609 951 0900",
    "sg:postcode":"08540",
    "sg:province":"NJ",
    "sg:tags":[
        "security"
    ],
    "sg:website":"www.agedwards.com",
    "wof:name":"A G Edwards & Sons Inc",
    "wof:placetype":"venue"
},
  "geometry": {"coordinates":[-74.606036,40.379065],"type":"Point"}
}