{
  "type": "Feature",
  "properties": {
    "iso:country":"US",
    "sg:address":"320 Washington Ave",
    "sg:city":"Haddonfield",
    "sg:classifiers":[
        {
            "category":"Professional",
            "subcategory":"Lawyer & Legal Services",
            "type":"Services"
        }
    ],
    "sg:phone":"+1 856 795 5700",
    "sg:postcode":"08033",
    "sg:province":"NJ",
    "wof:name":"Sambalino John D Attorney At Law",
    "wof:placetype":"venue"
},
  "geometry": {"coordinates":[-75.03589599999999,39.890598],"type":"Point"}
}