{
  "type": "Feature",
  "properties": {
    "iso:country":"US",
    "sg:address":"108 Hayward Pl",
    "sg:city":"Wallington",
    "sg:classifiers":[
        {
            "category":"Retail",
            "subcategory":"Auto Repair",
            "type":"Services"
        }
    ],
    "sg:phone":"+1 973 777 6320",
    "sg:postcode":"07057",
    "sg:province":"NJ",
    "sg:tags":[
        "body",
        "shop"
    ],
    "wof:name":"Hayward Place Auto Body",
    "wof:placetype":"venue"
},
  "geometry": {"coordinates":[-74.1157,40.854801],"type":"Point"}
}