{
  "type": "Feature",
  "properties": {
    "addr:full":"1353 Bound Brook Rd Middlesex NJ 08846",
    "addr:housenumber":"1353",
    "addr:postcode":"08846",
    "addr:street":"Bound Brook Rd",
    "iso:country":"US",
    "sg:address":"1353 Bound Brook Rd",
    "sg:city":"Middlesex",
    "sg:classifiers":[
        {
            "category":"Autos & Motor Vehicles",
            "subcategory":"Fuel & Gas Station",
            "type":"Retail Goods"
        }
    ],
    "sg:phone":"+1 732 356 5666",
    "sg:postcode":"08846",
    "sg:province":"NJ",
    "sg:tags":[
        "oil"
    ],
    "wof:name":"Exxon",
    "wof:placetype":"venue"
},
  "geometry": {"coordinates":[-74.50477600000001,40.578834],"type":"Point"}
}