{
  "type": "Feature",
  "properties": {
    "addr:full":"2104 The Woods Cherry Hill NJ 08003",
    "addr:housenumber":"2104",
    "addr:postcode":"08003",
    "addr:street":"The Woods",
    "iso:country":"US",
    "sg:address":"2104 The Woods",
    "sg:city":"Cherry Hill",
    "sg:classifiers":[
        {
            "category":"Freight",
            "type":"Transportation"
        }
    ],
    "sg:phone":"+1 856 424 6464",
    "sg:postcode":"08003",
    "sg:province":"NJ",
    "sg:tags":[
        "cargo",
        "haul"
    ],
    "wof:name":"Kansas City Southern Rlwy Co",
    "wof:placetype":"venue"
},
  "geometry": {"coordinates":[-74.94725099999999,39.869908],"type":"Point"}
}