{
  "type": "Feature",
  "properties": {
    "addr:full":"221 Van Horne St Jersey City NJ 07304",
    "addr:housenumber":"221",
    "addr:postcode":"07304",
    "addr:street":"Van Horne St",
    "iso:country":"US",
    "sg:address":"221 Van Horne St",
    "sg:city":"Jersey City",
    "sg:classifiers":[
        {
            "category":"Personal",
            "subcategory":"Beauty Salon",
            "type":"Services"
        }
    ],
    "sg:phone":"+1 201 536 0696",
    "sg:postcode":"07304",
    "sg:province":"NJ",
    "sg:tags":[
        "shop"
    ],
    "wof:name":"Ramsay Unisex",
    "wof:placetype":"venue"
},
  "geometry": {"coordinates":[-74.06307700000001,40.713129],"type":"Point"}
}