{
  "type": "Feature",
  "properties": {
    "iso:country":"US",
    "sg:address":"6 Executive Ct",
    "sg:city":"Cherry Hill",
    "sg:classifiers":[
        {
            "category":"Manufacturing",
            "subcategory":"Food",
            "type":"Manufacturing & Wholesale Goods"
        }
    ],
    "sg:phone":"+1 856 969 7100",
    "sg:postcode":"08046",
    "sg:province":"NJ",
    "sg:tags":[
        "mfg",
        "high",
        "convenience",
        "branded",
        "quality",
        "marketer"
    ],
    "wof:name":"Crunch Equity Holding LLC",
    "wof:placetype":"venue"
},
  "geometry": {"coordinates":[-74.864392,40.018525],"type":"Point"}
}