{
  "type": "Feature",
  "properties": {
    "iso:country":"US",
    "sg:address":"281 State Rte 79",
    "sg:city":"Morganville",
    "sg:classifiers":[
        {
            "category":"Professional",
            "subcategory":"Business Services",
            "type":"Services"
        }
    ],
    "sg:phone":"+1   ",
    "sg:postcode":"07751",
    "sg:province":"NJ",
    "wof:name":"Net Scale Technologies Inc",
    "wof:placetype":"venue"
},
  "geometry": {"coordinates":[-74.249211,40.357504],"type":"Point"}
}