{
  "type": "Feature",
  "properties": {
    "iso:country":"US",
    "sg:address":"21 17th St",
    "sg:city":"Fair Lawn",
    "sg:classifiers":[
        {
            "category":"Utilities",
            "subcategory":"Telephone",
            "type":"Services"
        }
    ],
    "sg:phone":"+1 201 796 3482",
    "sg:postcode":"07410",
    "sg:province":"NJ",
    "sg:tags":[
        "web",
        "design",
        "hosting",
        "page"
    ],
    "wof:name":"Innovative Strategic Tech LLC",
    "wof:placetype":"venue"
},
  "geometry": {"coordinates":[-74.11743199999999,40.921439],"type":"Point"}
}