{
  "type": "Feature",
  "properties": {
    "iso:country":"US",
    "sg:address":"70 Park Ave",
    "sg:city":"East Orange",
    "sg:classifiers":[
        {
            "category":"Place Of Worship",
            "subcategory":"Church",
            "type":"Public Place"
        }
    ],
    "sg:phone":"+1 973 674 4578",
    "sg:postcode":"07017",
    "sg:province":"NJ",
    "wof:name":"Park Avenue Christian Church Disciples of Christ",
    "wof:placetype":"venue"
},
  "geometry": {"coordinates":[-74.19609199999999,40.762702],"type":"Point"}
}