{
  "type": "Feature",
  "properties": {
    "addr:full":"147 Malvern St Newark NJ 07105",
    "addr:housenumber":"147",
    "addr:postcode":"07105",
    "addr:street":"Malvern St",
    "iso:country":"US",
    "sg:address":"147 Malvern St",
    "sg:city":"Newark",
    "sg:classifiers":[
        {
            "category":"Restaurant",
            "type":"Food & Drink"
        }
    ],
    "sg:phone":"+1   ",
    "sg:postcode":"07105",
    "sg:province":"NJ",
    "sg:tags":[
        "eating"
    ],
    "wof:name":"Puglieses Deli & Restaurant",
    "wof:placetype":"venue"
},
  "geometry": {"coordinates":[-74.16291,40.721562],"type":"Point"}
}