{
  "type": "Feature",
  "properties": {
    "iso:country":"US",
    "sg:address":"2345 US Hwy 206",
    "sg:city":"Southampton",
    "sg:classifiers":[
        {
            "category":"Shopping",
            "type":"Retail Goods"
        },
        {
            "category":"Autos & Motor Vehicles",
            "subcategory":"Auto Supplies",
            "type":"Retail Goods"
        }
    ],
    "sg:phone":"+1 609 267 6610",
    "sg:postcode":"08088",
    "sg:province":"NJ",
    "sg:tags":[
        "communication",
        "equipment",
        "stereo",
        "radio",
        "automobile"
    ],
    "wof:name":"White Dtte Communications Elec",
    "wof:placetype":"venue"
},
  "geometry": {"coordinates":[-74.735997,39.968362],"type":"Point"}
}