{
  "type": "Feature",
  "properties": {
    "iso:country":"US",
    "sg:address":"11 W 8th St",
    "sg:city":"Bayonne",
    "sg:classifiers":[
        {
            "category":"Real Estate",
            "subcategory":"Architect",
            "type":"Services"
        }
    ],
    "sg:phone":"+1 201 823 0779",
    "sg:postcode":"07002",
    "sg:province":"NJ",
    "wof:name":"Dal Design Group",
    "wof:placetype":"venue"
},
  "geometry": {"coordinates":[-74.12799800000001,40.654301],"type":"Point"}
}