{
  "type": "Feature",
  "properties": {
    "iso:country":"US",
    "sg:address":"4 Deerfield Dr",
    "sg:city":"Franklin",
    "sg:classifiers":[
        {
            "category":"Professional",
            "type":"Services"
        }
    ],
    "sg:phone":"+1   ",
    "sg:postcode":"07416",
    "sg:province":"NJ",
    "wof:name":"Suzanne O Neil Inc",
    "wof:placetype":"venue"
},
  "geometry": {"coordinates":[-74.617492,41.135329],"type":"Point"}
}