{
  "type": "Feature",
  "properties": {
    "iso:country":"US",
    "sg:address":"57 W Main St",
    "sg:city":"Bogota",
    "sg:classifiers":[
        {
            "category":"Bagels",
            "subcategory":"None",
            "type":"Food & Drink"
        }
    ],
    "sg:phone":"+1 201 342 2224",
    "sg:postcode":"07603",
    "sg:province":"NJ",
    "wof:name":"Bogota Bagel",
    "wof:placetype":"venue"
},
  "geometry": {"coordinates":[-74.029602,40.877899],"type":"Point"}
}