{
  "type": "Feature",
  "properties": {
    "addr:full":"79 Mountainview Rd Trenton NJ 08628",
    "addr:housenumber":"79",
    "addr:postcode":"08628",
    "addr:street":"Mountainview Rd",
    "iso:country":"US",
    "sg:address":"79 Mountainview Rd",
    "sg:city":"Trenton",
    "sg:classifiers":[
        {
            "category":"Building & Trades",
            "subcategory":"Construction",
            "type":"Services"
        }
    ],
    "sg:phone":"+1 609 882 6858",
    "sg:postcode":"08628",
    "sg:province":"NJ",
    "sg:tags":[
        "house"
    ],
    "wof:name":"James A Sparano Builders",
    "wof:placetype":"venue"
},
  "geometry": {"coordinates":[-74.83992600000001,40.281171],"type":"Point"}
}