{
  "type": "Feature",
  "properties": {
    "addr:full":"841 Allwood Rd Clifton NJ 07012",
    "addr:housenumber":"841",
    "addr:postcode":"07012",
    "addr:street":"Allwood Rd",
    "iso:country":"US",
    "sg:address":"841 Allwood Rd",
    "sg:city":"Clifton",
    "sg:classifiers":[
        {
            "category":"Real Estate",
            "subcategory":"Developer",
            "type":"Services"
        }
    ],
    "sg:phone":"+1   ",
    "sg:postcode":"07012",
    "sg:province":"NJ",
    "sg:tags":[
        "cemetery"
    ],
    "wof:name":"Jewish Cemetary Association",
    "wof:placetype":"venue"
},
  "geometry": {"coordinates":[-74.14688,40.83514],"type":"Point"}
}