{
  "type": "Feature",
  "properties": {
    "addr:full":"28 Madison Ave New Providence NJ 07974",
    "addr:housenumber":"28",
    "addr:postcode":"07974",
    "addr:street":"Madison Ave",
    "iso:country":"US",
    "sg:address":"28 Madison Ave",
    "sg:city":"New Providence",
    "sg:classifiers":[
        {
            "category":"Professional",
            "subcategory":"Business Services",
            "type":"Services"
        }
    ],
    "sg:phone":"+1   ",
    "sg:postcode":"07974",
    "sg:province":"NJ",
    "wof:name":"Gibbons Enterprises",
    "wof:placetype":"venue"
},
  "geometry": {"coordinates":[-74.39897999999999,40.709975],"type":"Point"}
}