{
  "type": "Feature",
  "properties": {
    "addr:full":"917 State Rte 36 Keyport NJ 07735",
    "addr:housenumber":"917",
    "addr:postcode":"07735",
    "addr:street":"State Rte 36",
    "iso:country":"US",
    "sg:address":"917 State Rte 36",
    "sg:city":"Keyport",
    "sg:classifiers":[
        {
            "category":"Retail",
            "subcategory":"Auto Repair",
            "type":"Services"
        }
    ],
    "sg:phone":"+1 732 739 1177",
    "sg:postcode":"07735",
    "sg:province":"NJ",
    "sg:tags":[
        "repairing",
        "automobile",
        "general"
    ],
    "wof:name":"Straight Line Automotive",
    "wof:placetype":"venue"
},
  "geometry": {"coordinates":[-74.16668300000001,40.438004],"type":"Point"}
}