{
  "type": "Feature",
  "properties": {
    "addr:full":"70 Demarest Dr Wayne NJ 07470",
    "addr:housenumber":"70",
    "addr:postcode":"07470",
    "addr:street":"Demarest Dr",
    "iso:country":"US",
    "sg:address":"70 Demarest Dr",
    "sg:city":"Wayne",
    "sg:classifiers":[
        {
            "category":"Wholesale",
            "subcategory":"Home Furnishings",
            "type":"Manufacturing & Wholesale Goods"
        }
    ],
    "sg:phone":"+1 973 694 2888",
    "sg:postcode":"07470",
    "sg:province":"NJ",
    "sg:tags":[
        "flooring"
    ],
    "wof:name":"Hoboken Floors",
    "wof:placetype":"venue"
},
  "geometry": {"coordinates":[-74.263396,40.90565],"type":"Point"}
}