{
  "type": "Feature",
  "properties": {
    "addr:full":"310 State Rte 36 Long Branch NJ 07740",
    "addr:housenumber":"310",
    "addr:postcode":"07740",
    "addr:street":"State Rte 36",
    "iso:country":"US",
    "sg:address":"310 State Rte 36",
    "sg:city":"Long Branch",
    "sg:classifiers":[
        {
            "category":"Shopping",
            "type":"Retail Goods"
        }
    ],
    "sg:phone":"+1   ",
    "sg:postcode":"07740",
    "sg:province":"NJ",
    "sg:tags":[
        "pet",
        "food",
        "supply"
    ],
    "wof:name":"Petsmart",
    "wof:placetype":"venue"
},
  "geometry": {"coordinates":[-73.97975099999999,40.315289],"type":"Point"}
}