{
  "type": "Feature",
  "properties": {
    "addr:full":"835 Sycamore Ave Eatontown NJ 07724",
    "addr:housenumber":"835",
    "addr:postcode":"07724",
    "addr:street":"Sycamore Ave",
    "iso:country":"US",
    "sg:address":"835 Sycamore Ave",
    "sg:city":"Eatontown",
    "sg:classifiers":[
        {
            "category":"Shopping",
            "subcategory":"Jewelry",
            "type":"Retail Goods"
        }
    ],
    "sg:phone":"+1   ",
    "sg:postcode":"07724",
    "sg:province":"NJ",
    "wof:name":"Bella Donna Beads Inc",
    "wof:placetype":"venue"
},
  "geometry": {"coordinates":[-74.084487,40.31912],"type":"Point"}
}