{
  "type": "Feature",
  "properties": {
    "iso:country":"US",
    "sg:address":"2 Lackawanna Ct",
    "sg:city":"Morristown",
    "sg:classifiers":[
        {
            "category":"Building & Trades",
            "subcategory":"Equipment Rental",
            "type":"Services"
        }
    ],
    "sg:phone":"+1   ",
    "sg:postcode":"07928",
    "sg:province":"NJ",
    "wof:name":"Party Shoppe",
    "wof:placetype":"venue"
},
  "geometry": {"coordinates":[-74.385001,40.727848],"type":"Point"}
}