{
  "type": "Feature",
  "properties": {
    "addr:full":"2505 Atlantic Ave Atlantic City NJ 08401",
    "addr:housenumber":"2505",
    "addr:postcode":"08401",
    "addr:street":"Atlantic Ave",
    "iso:country":"US",
    "sg:address":"2505 Atlantic Ave",
    "sg:city":"Atlantic City",
    "sg:classifiers":[
        {
            "category":"Personal",
            "subcategory":"Barber",
            "type":"Services"
        }
    ],
    "sg:phone":"+1 609 345 5492",
    "sg:postcode":"08401",
    "sg:province":"NJ",
    "wof:name":"Hollywood Barber & Hair Stylng",
    "wof:placetype":"venue"
},
  "geometry": {"coordinates":[-74.44237699999999,39.356257],"type":"Point"}
}