{
  "type": "Feature",
  "properties": {
    "addr:full":"82 Montgomery Ave Long Branch NJ 07740",
    "addr:housenumber":"82",
    "addr:postcode":"07740",
    "addr:street":"Montgomery Ave",
    "iso:country":"US",
    "sg:address":"82 Montgomery Ave",
    "sg:city":"Long Branch",
    "sg:classifiers":[
        {
            "category":"Restaurant",
            "type":"Food & Drink"
        }
    ],
    "sg:menulink":"http://www.allmenus.com/nj/long-branch/82410-dominos-pizza/menu/",
    "sg:phone":"+1 732 571 2800",
    "sg:postcode":"07740",
    "sg:province":"NJ",
    "sg:tags":[
        "american",
        "wing",
        "pizza"
    ],
    "wof:name":"Domino's Pizza",
    "wof:placetype":"venue"
},
  "geometry": {"coordinates":[-73.98577299999999,40.285099],"type":"Point"}
}