{
  "type": "Feature",
  "properties": {
    "addr:full":"481 Grove Ave Edison NJ 08820",
    "addr:housenumber":"481",
    "addr:postcode":"08820",
    "addr:street":"Grove Ave",
    "iso:country":"US",
    "sg:address":"481 Grove Ave",
    "sg:city":"Edison",
    "sg:classifiers":[
        {
            "category":"Health Services",
            "subcategory":"Doctor",
            "type":"Services"
        }
    ],
    "sg:phone":"+1 732 549 1777",
    "sg:postcode":"08820",
    "sg:province":"NJ",
    "sg:tags":[
        "medical"
    ],
    "wof:name":"Shah Bharti MD",
    "wof:placetype":"venue"
},
  "geometry": {"coordinates":[-74.35741299999999,40.556591],"type":"Point"}
}