{
  "type": "Feature",
  "properties": {
    "addr:full":"9040 Pennsauken Hwy Pennsauken NJ 08110",
    "addr:postcode":"9040;08110",
    "addr:street":"Pennsauken Hwy",
    "iso:country":"US",
    "sg:address":"9040 Pennsauken Hwy",
    "sg:city":"Pennsauken",
    "sg:classifiers":[
        {
            "category":"Manufacturing",
            "subcategory":"Printing",
            "type":"Manufacturing & Wholesale Goods"
        }
    ],
    "sg:phone":"+1 856 665 2070",
    "sg:postcode":"08110",
    "sg:province":"NJ",
    "sg:tags":[
        "printer",
        "commercial"
    ],
    "sg:website":"www.fairmountprinters.com",
    "wof:name":"Fairmount Printers LLC",
    "wof:placetype":"venue"
},
  "geometry": {"coordinates":[-75.02682799999999,39.976273],"type":"Point"}
}