{
  "type": "Feature",
  "properties": {
    "iso:country":"US",
    "sg:address":"721 Tanager Way",
    "sg:city":"Brick",
    "sg:classifiers":[
        {
            "category":"Building & Trades",
            "subcategory":"Construction",
            "type":"Services"
        }
    ],
    "sg:phone":"+1 732 458 8853",
    "sg:postcode":"08724",
    "sg:province":"NJ",
    "sg:tags":[
        "general",
        "contractor"
    ],
    "wof:name":"Mother & Son Construction",
    "wof:placetype":"venue"
},
  "geometry": {"coordinates":[-74.10320400000001,40.119966],"type":"Point"}
}