{
  "type": "Feature",
  "properties": {
    "iso:country":"US",
    "sg:address":"6 Spring St",
    "sg:city":"Jamesburg",
    "sg:classifiers":[
        {
            "category":"Retail",
            "subcategory":"Auto Repair",
            "type":"Services"
        }
    ],
    "sg:phone":"+1 732 521 2542",
    "sg:postcode":"08831",
    "sg:province":"NJ",
    "sg:tags":[
        "machine",
        "automotive",
        "shop",
        "automobile"
    ],
    "wof:name":"Steve's Machine",
    "wof:placetype":"venue"
},
  "geometry": {"coordinates":[-74.42743,40.345506],"type":"Point"}
}