{
  "type": "Feature",
  "properties": {
    "addr:full":"226 Oak Ave Toms River NJ 08753",
    "addr:housenumber":"226",
    "addr:postcode":"08753",
    "addr:street":"Oak Ave",
    "iso:country":"US",
    "sg:address":"226 Oak Ave",
    "sg:city":"Toms River",
    "sg:classifiers":[
        {
            "category":"Insurance",
            "subcategory":"Insurance Agent",
            "type":"Services"
        }
    ],
    "sg:phone":"+1   ",
    "sg:postcode":"08753",
    "sg:province":"NJ",
    "wof:name":"Allstate",
    "wof:placetype":"venue"
},
  "geometry": {"coordinates":[-74.184341,39.987973],"type":"Point"}
}