{
  "type": "Feature",
  "properties": {
    "addr:full":"180 Lafayette Ave Edison NJ 08837",
    "addr:housenumber":"180",
    "addr:postcode":"08837",
    "addr:street":"Lafayette Ave",
    "iso:country":"US",
    "sg:address":"180 Lafayette Ave",
    "sg:city":"Edison",
    "sg:classifiers":[
        {
            "category":"Recreation",
            "type":"Entertainment"
        }
    ],
    "sg:phone":"+1 732 906 8400",
    "sg:postcode":"08837",
    "sg:province":"NJ",
    "sg:tags":[
        "diving",
        "instruction"
    ],
    "wof:name":"Ocean Explorers Aquatic Center",
    "wof:placetype":"venue"
},
  "geometry": {"coordinates":[-74.33560199999999,40.542928],"type":"Point"}
}