{
  "type": "Feature",
  "properties": {
    "iso:country":"US",
    "sg:address":"30 Central Ave",
    "sg:city":"Newark",
    "sg:classifiers":[
        {
            "category":"Restaurant",
            "type":"Food & Drink"
        }
    ],
    "sg:phone":"+1 973 623 8137",
    "sg:postcode":"07102",
    "sg:province":"NJ",
    "sg:tags":[
        "diner"
    ],
    "wof:name":"Central Restaurant",
    "wof:placetype":"venue"
},
  "geometry": {"coordinates":[-74.170599,40.741542],"type":"Point"}
}