{
  "type": "Feature",
  "properties": {
    "iso:country":"US",
    "sg:address":"731 State Rte 12",
    "sg:city":"Frenchtown",
    "sg:classifiers":[
        {
            "category":"Autos & Motor Vehicles",
            "subcategory":"Automobile Sales",
            "type":"Retail Goods"
        }
    ],
    "sg:phone":"+1 908 788 2074",
    "sg:postcode":"08825",
    "sg:province":"NJ",
    "sg:tags":[
        "car",
        "dealer"
    ],
    "wof:name":"J W Auto Sales",
    "wof:placetype":"venue"
},
  "geometry": {"coordinates":[-74.964893,40.506788],"type":"Point"}
}