{
  "type": "Feature",
  "properties": {
    "iso:country":"US",
    "sg:address":"34 Engle St",
    "sg:city":"Englewood",
    "sg:classifiers":[
        {
            "category":"Travel",
            "subcategory":"Travel Agent",
            "type":"Entertainment"
        }
    ],
    "sg:phone":"+1 201 568 0370",
    "sg:postcode":"07631",
    "sg:province":"NJ",
    "sg:tags":[
        "agency",
        "bureau"
    ],
    "wof:name":"Kuoni Travel Management",
    "wof:placetype":"venue"
},
  "geometry": {"coordinates":[-73.972104,40.894762],"type":"Point"}
}