{
  "type": "Feature",
  "properties": {
    "addr:full":"Ocean Dr & Fish Dock Rd Wildwood NJ 08260",
    "addr:postcode":"08260",
    "addr:street":"Ocean Dr;Dock Rd",
    "iso:country":"US",
    "sg:address":"Ocean Dr & Fish Dock Rd",
    "sg:city":"Wildwood",
    "sg:classifiers":[
        {
            "category":"Restaurant",
            "type":"Food & Drink"
        }
    ],
    "sg:menulink":"http://www.allmenus.com/nj/lower/31076-two-mile-inn/menu/",
    "sg:phone":"+1 609 552 1341",
    "sg:postcode":"08260",
    "sg:province":"NJ",
    "sg:tags":[
        "seafood",
        "american"
    ],
    "wof:name":"Two Mile Inn",
    "wof:placetype":"venue"
},
  "geometry": {"coordinates":[-74.86246,38.95647],"type":"Point"}
}