{
  "type": "Feature",
  "properties": {
    "addr:full":"165 E Main St Denville NJ 07834",
    "addr:housenumber":"165",
    "addr:postcode":"07834",
    "addr:street":"E Main St",
    "iso:country":"US",
    "sg:address":"165 E Main St",
    "sg:city":"Denville",
    "sg:classifiers":[
        {
            "category":"Social Services",
            "type":"Services"
        }
    ],
    "sg:phone":"+1 973 625 2237",
    "sg:postcode":"07834",
    "sg:province":"NJ",
    "sg:tags":[
        "counselor",
        "marriage",
        "family"
    ],
    "wof:name":"Carolyn Harris Msw",
    "wof:placetype":"venue"
},
  "geometry": {"coordinates":[-74.47967,40.885821],"type":"Point"}
}