{
  "type": "Feature",
  "properties": {
    "iso:country":"US",
    "sg:address":"340 Scotch Rd",
    "sg:city":"Trenton",
    "sg:classifiers":[
        {
            "category":"Professional",
            "subcategory":"Management & Consulting",
            "type":"Services"
        }
    ],
    "sg:phone":"+1   ",
    "sg:postcode":"08628",
    "sg:province":"NJ",
    "wof:name":"OBrien-Kreitzberg Inc",
    "wof:placetype":"venue"
},
  "geometry": {"coordinates":[-74.81111900000001,40.28708],"type":"Point"}
}