{
  "type": "Feature",
  "properties": {
    "addr:full":"46 W Front St Keyport NJ 07735",
    "addr:housenumber":"46",
    "addr:postcode":"07735",
    "addr:street":"W Front St",
    "iso:country":"US",
    "sg:address":"46 W Front St",
    "sg:city":"Keyport",
    "sg:classifiers":[
        {
            "category":"Professional",
            "type":"Services"
        }
    ],
    "sg:phone":"+1   ",
    "sg:postcode":"07735",
    "sg:province":"NJ",
    "wof:name":"Mitchell Sanborn Gallery",
    "wof:placetype":"venue"
},
  "geometry": {"coordinates":[-74.20417500000001,40.436715],"type":"Point"}
}