{
  "type": "Feature",
  "properties": {
    "iso:country":"US",
    "sg:address":"301 E Main St",
    "sg:city":"Bergenfield",
    "sg:classifiers":[
        {
            "category":"Professional",
            "subcategory":"Accounting & Tax Preparation",
            "type":"Services"
        }
    ],
    "sg:phone":"+1   ",
    "sg:postcode":"07621",
    "sg:province":"NJ",
    "wof:name":"Leon A Levine CPA",
    "wof:placetype":"venue"
},
  "geometry": {"coordinates":[-73.984351,40.928245],"type":"Point"}
}