{
  "type": "Feature",
  "properties": {
    "iso:country":"US",
    "sg:address":"87 Oakland Ave",
    "sg:city":"Jersey City",
    "sg:classifiers":[
        {
            "category":"Banks & Credit Unions",
            "subcategory":"Financial Services",
            "type":"Services"
        }
    ],
    "sg:phone":"+1 201 533 0660",
    "sg:postcode":"07306",
    "sg:province":"NJ",
    "sg:tags":[
        "investor"
    ],
    "wof:name":"United Capital Investors",
    "wof:placetype":"venue"
},
  "geometry": {"coordinates":[-74.05525299999999,40.734787],"type":"Point"}
}