{
  "type": "Feature",
  "properties": {
    "iso:country":"US",
    "sg:address":"605 Bloomfield Ave Ste 8",
    "sg:city":"Montclair",
    "sg:classifiers":[
        {
            "category":"Real Estate",
            "subcategory":"Architect",
            "type":"Services"
        }
    ],
    "sg:phone":"+1 973 233 9355",
    "sg:postcode":"07042",
    "sg:province":"NJ",
    "wof:name":"Dassa Haines Architects",
    "wof:placetype":"venue"
},
  "geometry": {"coordinates":[-74.220299,40.816101],"type":"Point"}
}