{
  "type": "Feature",
  "properties": {
    "addr:full":"1341 Main Ave Clifton NJ 07011",
    "addr:housenumber":"1341",
    "addr:postcode":"07011",
    "addr:street":"Main Ave",
    "iso:country":"US",
    "sg:address":"1341 Main Ave",
    "sg:city":"Clifton",
    "sg:classifiers":[
        {
            "category":"Fast Food",
            "type":"Food & Drink"
        },
        {
            "category":"Restaurant",
            "type":"Food & Drink"
        }
    ],
    "sg:phone":"+1 973 772 0335",
    "sg:postcode":"07011",
    "sg:province":"NJ",
    "sg:tags":[
        "american",
        "hot",
        "hamburger",
        "dog"
    ],
    "sg:website":"www.whitecastle.com",
    "wof:name":"White Castle",
    "wof:placetype":"venue"
},
  "geometry": {"coordinates":[-74.14484,40.880413],"type":"Point"}
}