{
  "type": "Feature",
  "properties": {
    "addr:full":"211 W Commerce St Bridgeton NJ 08302",
    "addr:housenumber":"211",
    "addr:postcode":"08302",
    "addr:street":"W Commerce St",
    "iso:country":"US",
    "sg:address":"211 W Commerce St",
    "sg:city":"Bridgeton",
    "sg:classifiers":[
        {
            "category":"Building & Trades",
            "subcategory":"Electrical",
            "type":"Services"
        }
    ],
    "sg:phone":"+1 856 455 6512",
    "sg:postcode":"08302",
    "sg:province":"NJ",
    "sg:tags":[
        "electrical",
        "contractor"
    ],
    "wof:name":"G Maier Electric",
    "wof:placetype":"venue"
},
  "geometry": {"coordinates":[-75.244175,39.431278],"type":"Point"}
}