{
  "type": "Feature",
  "properties": {
    "addr:full":"16 White Bridge Rd Pittstown NJ 08867",
    "addr:housenumber":"16",
    "addr:postcode":"08867",
    "addr:street":"White Bridge Rd",
    "iso:country":"US",
    "sg:address":"16 White Bridge Rd",
    "sg:city":"Pittstown",
    "sg:classifiers":[
        {
            "category":"Manufacturing",
            "subcategory":"Retail Goods",
            "type":"Manufacturing & Wholesale Goods"
        }
    ],
    "sg:phone":"+1 908 238 0898",
    "sg:postcode":"08867",
    "sg:province":"NJ",
    "sg:tags":[
        "manufacturer"
    ],
    "wof:name":"Keopsys Inc",
    "wof:placetype":"venue"
},
  "geometry": {"coordinates":[-74.949173,40.587069],"type":"Point"}
}