{
  "type": "Feature",
  "properties": {
    "iso:country":"US",
    "sg:address":"60 Jefferson Rd",
    "sg:city":"Princeton",
    "sg:classifiers":[
        {
            "category":"Professional",
            "subcategory":"Management & Consulting",
            "type":"Services"
        }
    ],
    "sg:phone":"+1   ",
    "sg:postcode":"08540",
    "sg:province":"NJ",
    "sg:tags":[
        "business"
    ],
    "wof:name":"Western  Bruce",
    "wof:placetype":"venue"
},
  "geometry": {"coordinates":[-74.658427,40.356601],"type":"Point"}
}