{
  "type": "Feature",
  "properties": {
    "iso:country":"US",
    "sg:address":"19 Russet Ln",
    "sg:city":"Farmingdale",
    "sg:classifiers":[
        {
            "category":"Professional",
            "subcategory":"Computer Services",
            "type":"Services"
        }
    ],
    "sg:phone":"+1   ",
    "sg:postcode":"07727",
    "sg:province":"NJ",
    "sg:tags":[
        "programing",
        "custom"
    ],
    "wof:name":"Epoia Interactive Studios LLC",
    "wof:placetype":"venue"
},
  "geometry": {"coordinates":[-74.170208,40.204006],"type":"Point"}
}