{
  "type": "Feature",
  "properties": {
    "iso:country":"US",
    "sg:address":"ROUTE 41",
    "sg:city":"Deptford",
    "sg:classifiers":[
        {
            "category":"Manufacturing",
            "subcategory":"Metals",
            "type":"Manufacturing & Wholesale Goods"
        },
        {
            "category":"Manufacturing",
            "subcategory":"Printing",
            "type":"Manufacturing & Wholesale Goods"
        },
        {
            "category":"Autos & Motor Vehicles",
            "subcategory":"Auto Supplies",
            "type":"Retail Goods"
        },
        {
            "category":"Utilities",
            "subcategory":"Recycling",
            "type":"Services"
        },
        {
            "category":"Train Station",
            "subcategory":"Light Rail",
            "type":"Transportation"
        }
    ],
    "sg:phone":"+1 856 227 3600",
    "sg:postcode":"08096",
    "sg:province":"NJ",
    "sg:tags":[
        "steel",
        "rebuilt",
        "used",
        "container",
        "garbage",
        "automobile",
        "removal",
        "equipment",
        "paper",
        "supplies-used",
        "rubbish",
        "part",
        "waste",
        "accessory",
        "contractors'"
    ],
    "wof:name":"East Coast Metal Recovery",
    "wof:placetype":"venue"
},
  "geometry": {"coordinates":[-75.097775,39.83],"type":"Point"}
}