{
  "type": "Feature",
  "properties": {
    "addr:full":"593 61st St West New York NJ 07093",
    "addr:housenumber":"593",
    "addr:postcode":"nj 07093",
    "addr:street":"61St St West",
    "iso:country":"US",
    "sg:address":"593 61st St",
    "sg:city":"West New York",
    "sg:classifiers":[
        {
            "category":"Wholesale",
            "subcategory":"Home Furnishings",
            "type":"Manufacturing & Wholesale Goods"
        }
    ],
    "sg:phone":"+1 201 854 7881",
    "sg:postcode":"07093",
    "sg:province":"NJ",
    "wof:name":"Reflections Mirrors & Design",
    "wof:placetype":"venue"
},
  "geometry": {"coordinates":[-74.018647,40.791168],"type":"Point"}
}