{
  "type": "Feature",
  "properties": {
    "iso:country":"US",
    "sg:address":"108 W Broad St",
    "sg:city":"Berlin",
    "sg:classifiers":[
        {
            "category":"Organizations",
            "subcategory":"Religious Organization",
            "type":"Services"
        }
    ],
    "sg:phone":"+1 856 767 0160",
    "sg:postcode":"08009",
    "sg:province":"NJ",
    "wof:name":"Church of the Good Shepherd",
    "wof:placetype":"venue"
},
  "geometry": {"coordinates":[-74.9328,39.7929],"type":"Point"}
}