{
  "type": "Feature",
  "properties": {
    "addr:full":"205 Tuckerton Rd Ste 206 Medford NJ 08055",
    "addr:housenumber":"205",
    "addr:postcode":"08055",
    "addr:street":"Tuckerton Rd Ste 206",
    "iso:country":"US",
    "sg:address":"205 Tuckerton Rd Ste 206",
    "sg:city":"Medford",
    "sg:classifiers":[
        {
            "category":"Retail",
            "subcategory":"Driving School",
            "type":"Services"
        }
    ],
    "sg:phone":"+1 856 988 9886",
    "sg:postcode":"08055",
    "sg:province":"NJ",
    "sg:tags":[
        "instruction",
        "traffic"
    ],
    "wof:name":"Medford Driving School",
    "wof:placetype":"venue"
},
  "geometry": {"coordinates":[-74.84574600000001,39.870467],"type":"Point"}
}