{
  "type": "Feature",
  "properties": {
    "addr:full":"309 Essex Rd Neptune NJ 07753",
    "addr:housenumber":"309",
    "addr:postcode":"07753",
    "addr:street":"Essex Rd",
    "iso:country":"US",
    "sg:address":"309 Essex Rd",
    "sg:city":"Neptune",
    "sg:classifiers":[
        {
            "category":"Wholesale",
            "subcategory":"Machinery & Supplies",
            "type":"Manufacturing & Wholesale Goods"
        }
    ],
    "sg:phone":"+1 732 922 1701",
    "sg:postcode":"07753",
    "sg:province":"NJ",
    "wof:name":"Gibraltar Granite & Marble Crp",
    "wof:placetype":"venue"
},
  "geometry": {"coordinates":[-74.08990799999999,40.234702],"type":"Point"}
}