{
  "type": "Feature",
  "properties": {
    "addr:full":"21 Cambridge Ave Garfield NJ 07026",
    "addr:housenumber":"21",
    "addr:postcode":"07026",
    "addr:street":"Cambridge Ave",
    "iso:country":"US",
    "sg:address":"21 Cambridge Ave",
    "sg:city":"Garfield",
    "sg:classifiers":[
        {
            "category":"Professional",
            "subcategory":"Lawyer & Legal Services",
            "type":"Services"
        }
    ],
    "sg:phone":"+1 973 365 1030",
    "sg:postcode":"07026",
    "sg:province":"NJ",
    "sg:tags":[
        "attorney"
    ],
    "wof:name":"Nicholas P Nasarenko Law Ofcs",
    "wof:placetype":"venue"
},
  "geometry": {"coordinates":[-74.10827500000001,40.864741],"type":"Point"}
}