{
  "type": "Feature",
  "properties": {
    "iso:country":"US",
    "sg:address":"1288 State Rte 73",
    "sg:city":"Mount Laurel",
    "sg:classifiers":[
        {
            "category":"Professional",
            "subcategory":"Advertising",
            "type":"Services"
        }
    ],
    "sg:phone":"+1   ",
    "sg:postcode":"08054",
    "sg:province":"NJ",
    "sg:tags":[
        "mail",
        "insurance",
        "direct"
    ],
    "wof:name":"Seco Financial Services Inc",
    "wof:placetype":"venue"
},
  "geometry": {"coordinates":[-74.949349,39.923565],"type":"Point"}
}