{
  "type": "Feature",
  "properties": {
    "addr:full":"70 Riverside Sq Hackensack NJ 07601",
    "addr:housenumber":"70",
    "addr:postcode":"07601",
    "addr:street":"Riverside Sq",
    "iso:country":"US",
    "sg:address":"70 Riverside Sq",
    "sg:city":"Hackensack",
    "sg:classifiers":[
        {
            "category":"Restaurant",
            "type":"Food & Drink"
        }
    ],
    "sg:phone":"+1 201 221 2030",
    "sg:postcode":"07601",
    "sg:province":"NJ",
    "sg:tags":[
        "italian"
    ],
    "sg:website":"www.maggianos.com",
    "wof:name":"Maggiano's Little Italy",
    "wof:placetype":"venue"
},
  "geometry": {"coordinates":[-74.032416,40.908531],"type":"Point"}
}