{
  "type": "Feature",
  "properties": {
    "addr:full":"870 Co Rd 530 Lakehurst NJ 08759",
    "addr:housenumber":"870;530",
    "addr:postcode":"08759",
    "addr:street":"Co Rd",
    "iso:country":"US",
    "sg:address":"870 Co Rd 530",
    "sg:city":"Lakehurst",
    "sg:classifiers":[
        {
            "category":"Manufacturing",
            "subcategory":"Rubber & Plastics",
            "type":"Manufacturing & Wholesale Goods"
        }
    ],
    "sg:phone":"+1 732 349 2669",
    "sg:postcode":"08759",
    "sg:province":"NJ",
    "sg:tags":[
        "devices",
        "mfg"
    ],
    "wof:name":"Federal-Mogul Corporation",
    "wof:placetype":"venue"
},
  "geometry": {"coordinates":[-74.334146,39.946777],"type":"Point"}
}