{
  "type": "Feature",
  "properties": {
    "addr:full":"16 Jericho Dr Trenton NJ 08690",
    "addr:housenumber":"16",
    "addr:postcode":"08690",
    "addr:street":"Jericho Dr",
    "iso:country":"US",
    "sg:address":"16 Jericho Dr",
    "sg:city":"Trenton",
    "sg:classifiers":[
        {
            "category":"Professional",
            "subcategory":"Employment Agencies",
            "type":"Services"
        }
    ],
    "sg:phone":"+1 609 586 0712",
    "sg:postcode":"08690",
    "sg:province":"NJ",
    "wof:name":"Dorothy Deblasio Mrs Rn",
    "wof:placetype":"venue"
},
  "geometry": {"coordinates":[-74.66473499999999,40.235217],"type":"Point"}
}