{
  "type": "Feature",
  "properties": {
    "addr:full":"277 Olympia Dr River Edge NJ 07661",
    "addr:housenumber":"277",
    "addr:postcode":"07661",
    "addr:street":"Olympia Dr",
    "iso:country":"US",
    "sg:address":"277 Olympia Dr",
    "sg:city":"River Edge",
    "sg:classifiers":[
        {
            "category":"Shopping",
            "subcategory":"Computers & Home Electronics",
            "type":"Retail Goods"
        }
    ],
    "sg:phone":"+1 201 225 1440",
    "sg:postcode":"07661",
    "sg:province":"NJ",
    "sg:tags":[
        "equipment",
        "dealer"
    ],
    "wof:name":"EPIA Solutions LLC",
    "wof:placetype":"venue"
},
  "geometry": {"coordinates":[-74.045424,40.921999],"type":"Point"}
}