{
  "type": "Feature",
  "properties": {
    "addr:full":"6 Highland Ave Rumson NJ 07760",
    "addr:housenumber":"6",
    "addr:postcode":"07760",
    "addr:street":"Highland Ave",
    "iso:country":"US",
    "sg:address":"6 Highland Ave",
    "sg:city":"Rumson",
    "sg:classifiers":[
        {
            "category":"Shopping",
            "subcategory":"Catalog Store",
            "type":"Retail Goods"
        }
    ],
    "sg:phone":"+1   ",
    "sg:postcode":"07760",
    "sg:province":"NJ",
    "sg:tags":[
        "mail",
        "house"
    ],
    "wof:name":"Baytique LLC",
    "wof:placetype":"venue"
},
  "geometry": {"coordinates":[-73.99760000000001,40.374569],"type":"Point"}
}