{
  "type": "Feature",
  "properties": {
    "iso:country":"US",
    "sg:address":"901 3rd St",
    "sg:city":"Ocean City",
    "sg:classifiers":[
        {
            "category":"Travel",
            "subcategory":"Hotels & Motels",
            "type":"Entertainment"
        }
    ],
    "sg:phone":"+1 609 729 0555",
    "sg:postcode":"08226",
    "sg:province":"NJ",
    "wof:name":"Tuscany Motor Inn",
    "wof:placetype":"venue"
},
  "geometry": {"coordinates":[-74.560863,39.280046],"type":"Point"}
}