{
  "type": "Feature",
  "properties": {
    "addr:full":"250 Bergen Tpke Little Ferry NJ 07643",
    "addr:housenumber":"250",
    "addr:postcode":"07643",
    "addr:street":"Bergen Tpke;Ferry",
    "iso:country":"US",
    "sg:address":"250 Bergen Tpke",
    "sg:city":"Little Ferry",
    "sg:classifiers":[
        {
            "category":"Ice Cream",
            "type":"Food & Drink"
        }
    ],
    "sg:menulink":"http://www.allmenus.com/nj/little-ferry/243395-baskin-robbins/menu/",
    "sg:phone":"+1 201 373 0373",
    "sg:postcode":"07643",
    "sg:province":"NJ",
    "sg:tags":[
        "american"
    ],
    "wof:name":"Baskin-Robbins",
    "wof:placetype":"venue"
},
  "geometry": {"coordinates":[-74.035763,40.857443],"type":"Point"}
}