{
  "type": "Feature",
  "properties": {
    "iso:country":"US",
    "sg:address":"1156 Woolley Ave",
    "sg:city":"Union",
    "sg:classifiers":[
        {
            "category":"Manufacturing",
            "subcategory":"Tools & Machinery",
            "type":"Manufacturing & Wholesale Goods"
        }
    ],
    "sg:phone":"+1 908 687 1094",
    "sg:postcode":"07083",
    "sg:province":"NJ",
    "sg:tags":[
        "machine",
        "shop"
    ],
    "wof:name":"Haussler Tool Co Inc",
    "wof:placetype":"venue"
},
  "geometry": {"coordinates":[-74.276599,40.701792],"type":"Point"}
}