{
  "type": "Feature",
  "properties": {
    "addr:full":"21 Edgewood St Tenafly NJ 07670",
    "addr:housenumber":"21",
    "addr:postcode":"07670",
    "addr:street":"Edgewood St",
    "iso:country":"US",
    "sg:address":"21 Edgewood St",
    "sg:city":"Tenafly",
    "sg:classifiers":[
        {
            "category":"Professional",
            "type":"Services"
        }
    ],
    "sg:phone":"+1   ",
    "sg:postcode":"07670",
    "sg:province":"NJ",
    "wof:name":"Cosine Llc/Medivault",
    "wof:placetype":"venue"
},
  "geometry": {"coordinates":[-73.957002,40.913639],"type":"Point"}
}