{
  "type": "Feature",
  "properties": {
    "addr:full":"1609 Boardwalk Atlantic City NJ 08401",
    "addr:housenumber":"1609",
    "addr:postcode":"08401",
    "addr:street":"Boardwalk",
    "iso:country":"US",
    "sg:address":"1609 Boardwalk",
    "sg:city":"Atlantic City",
    "sg:classifiers":[
        {
            "category":"Personal",
            "subcategory":"Massage",
            "type":"Services"
        }
    ],
    "sg:phone":"+1 609 345 8886",
    "sg:postcode":"08401",
    "sg:province":"NJ",
    "wof:name":"Din Hao Back & Foot Rub",
    "wof:placetype":"venue"
},
  "geometry": {"coordinates":[-74.428718,39.356276],"type":"Point"}
}