{
  "type": "Feature",
  "properties": {
    "addr:full":"742 E 1st Ave Roselle NJ 07203",
    "addr:housenumber":"742",
    "addr:postcode":"07203",
    "addr:street":"E 1St Ave",
    "iso:country":"US",
    "sg:address":"742 E 1st Ave",
    "sg:city":"Roselle",
    "sg:classifiers":[
        {
            "category":"Autos & Motor Vehicles",
            "subcategory":"Automobile Sales",
            "type":"Retail Goods"
        }
    ],
    "sg:phone":"+1   ",
    "sg:postcode":"07203",
    "sg:province":"NJ",
    "sg:tags":[
        "used"
    ],
    "wof:name":"H&H Salvage",
    "wof:placetype":"venue"
},
  "geometry": {"coordinates":[-74.243478,40.662738],"type":"Point"}
}