{
  "type": "Feature",
  "properties": {
    "addr:full":"936 Broad St Newark NJ 07102",
    "addr:housenumber":"936",
    "addr:postcode":"07102",
    "addr:street":"Broad St",
    "iso:country":"US",
    "sg:address":"936 Broad St",
    "sg:city":"Newark",
    "sg:classifiers":[
        {
            "category":"Restaurant",
            "type":"Food & Drink"
        }
    ],
    "sg:menulink":"http://www.allmenus.com/nj/newark/146080-subway/menu/",
    "sg:phone":"+1 973 273 1588",
    "sg:postcode":"07102",
    "sg:province":"NJ",
    "sg:tags":[
        "american",
        "sandwich"
    ],
    "wof:name":"Subway",
    "wof:placetype":"venue"
},
  "geometry": {"coordinates":[-74.174398,40.731437],"type":"Point"}
}