{
  "type": "Feature",
  "properties": {
    "addr:full":"76 Regal Dr Monmouth Junction NJ 08852",
    "addr:housenumber":"76",
    "addr:postcode":"08852",
    "addr:street":"Regal Dr",
    "iso:country":"US",
    "sg:address":"76 Regal Dr",
    "sg:city":"Monmouth Junction",
    "sg:classifiers":[
        {
            "category":"Recreation",
            "type":"Entertainment"
        }
    ],
    "sg:phone":"+1 732 355 0687",
    "sg:postcode":"08852",
    "sg:province":"NJ",
    "sg:tags":[
        "club",
        "membership"
    ],
    "wof:name":"Russian Social Club Inc",
    "wof:placetype":"venue"
},
  "geometry": {"coordinates":[-74.523612,40.388338],"type":"Point"}
}