{
  "type": "Feature",
  "properties": {
    "addr:full":"1500 Hudson St Hoboken NJ 07030",
    "addr:housenumber":"1500",
    "addr:postcode":"07030",
    "addr:street":"Hudson St",
    "iso:country":"US",
    "sg:address":"1500 Hudson St",
    "sg:city":"Hoboken",
    "sg:classifiers":[
        {
            "category":"Wholesale",
            "subcategory":"Apparel",
            "type":"Manufacturing & Wholesale Goods"
        }
    ],
    "sg:phone":"+1 201 420 5993",
    "sg:postcode":"07030",
    "sg:province":"NJ",
    "sg:tags":[
        "clothing"
    ],
    "wof:name":"Nu Spirit Inc",
    "wof:placetype":"venue"
},
  "geometry": {"coordinates":[-74.025149,40.752446],"type":"Point"}
}