{
  "type": "Feature",
  "properties": {
    "iso:country":"US",
    "sg:address":"9 Riverside Dr",
    "sg:city":"Hackettstown",
    "sg:classifiers":[
        {
            "category":"Health Services",
            "subcategory":"Doctor",
            "type":"Services"
        }
    ],
    "sg:phone":"+1 908 850 5055",
    "sg:postcode":"07834",
    "sg:province":"NJ",
    "sg:tags":[
        "physician",
        "surgeon"
    ],
    "wof:name":"Riverside Medical Ctr",
    "wof:placetype":"venue"
},
  "geometry": {"coordinates":[-74.475183,40.896734],"type":"Point"}
}