{
  "type": "Feature",
  "properties": {
    "iso:country":"US",
    "sg:address":"6577 Delilah Rd",
    "sg:city":"Egg Harbor Twp",
    "sg:classifiers":[
        {
            "category":"Shopping",
            "subcategory":"Hobbies, Toys, & Games",
            "type":"Retail Goods"
        }
    ],
    "sg:phone":"+1 609 272 0744",
    "sg:postcode":"08234",
    "sg:province":"NJ",
    "sg:tags":[
        "supply"
    ],
    "wof:name":"Sigma Game Inc",
    "wof:placetype":"venue"
},
  "geometry": {"coordinates":[-74.557575,39.423874],"type":"Point"}
}