{
  "type": "Feature",
  "properties": {
    "addr:full":"545 Amboy Ave Woodbridge NJ 07095",
    "addr:housenumber":"545",
    "addr:postcode":"07095",
    "addr:street":"Amboy Ave",
    "iso:country":"US",
    "sg:address":"545 Amboy Ave",
    "sg:city":"Woodbridge",
    "sg:classifiers":[
        {
            "category":"Health Services",
            "subcategory":"Chiropractor",
            "type":"Services"
        }
    ],
    "sg:phone":"+1 732 634 3040",
    "sg:postcode":"07095",
    "sg:province":"NJ",
    "wof:name":"Kuzma Family Chiropractic",
    "wof:placetype":"venue"
},
  "geometry": {"coordinates":[-74.284897,40.5597],"type":"Point"}
}