{
  "type": "Feature",
  "properties": {
    "iso:country":"US",
    "sg:address":"31 Parkside Ct",
    "sg:city":"Wayne",
    "sg:classifiers":[
        {
            "category":"Shopping",
            "subcategory":"Clothing, Apparel, & Fashions",
            "type":"Retail Goods"
        }
    ],
    "sg:phone":"+1   ",
    "sg:postcode":"07470",
    "sg:province":"NJ",
    "wof:name":"Funny Lingerie",
    "wof:placetype":"venue"
},
  "geometry": {"coordinates":[-74.257825,40.9692],"type":"Point"}
}