{
  "type": "Feature",
  "properties": {
    "addr:full":"563 Howell Ave Trenton NJ 08628",
    "addr:housenumber":"563",
    "addr:postcode":"08628",
    "addr:street":"Howell Ave",
    "iso:country":"US",
    "sg:address":"563 Howell Ave",
    "sg:city":"Trenton",
    "sg:classifiers":[
        {
            "category":"Shopping",
            "subcategory":"Computers & Home Electronics",
            "type":"Retail Goods"
        }
    ],
    "sg:phone":"+1 609 406 0305",
    "sg:postcode":"08628",
    "sg:province":"NJ",
    "sg:tags":[
        "software"
    ],
    "wof:name":"People Soft Inc",
    "wof:placetype":"venue"
},
  "geometry": {"coordinates":[-74.817221,40.266011],"type":"Point"}
}