{
  "type": "Feature",
  "properties": {
    "addr:full":"170 Talmadge Rd Edison NJ 08817",
    "addr:housenumber":"170",
    "addr:postcode":"08817",
    "addr:street":"Talmadge Rd",
    "iso:country":"US",
    "sg:address":"170 Talmadge Rd",
    "sg:city":"Edison",
    "sg:classifiers":[
        {
            "category":"Retail",
            "subcategory":"Repair Shop",
            "type":"Services"
        }
    ],
    "sg:phone":"+1   ",
    "sg:postcode":"08817",
    "sg:province":"NJ",
    "wof:name":"Emergency Locksmith",
    "wof:placetype":"venue"
},
  "geometry": {"coordinates":[-74.396018,40.536963],"type":"Point"}
}