{
  "type": "Feature",
  "properties": {
    "addr:full":"359 Paterson Ave Wallington NJ 07057",
    "addr:housenumber":"359",
    "addr:postcode":"07057",
    "addr:street":"Paterson Ave",
    "iso:country":"US",
    "sg:address":"359 Paterson Ave",
    "sg:city":"Wallington",
    "sg:classifiers":[
        {
            "category":"Food & Beverages",
            "subcategory":"Specialty",
            "type":"Retail Goods"
        }
    ],
    "sg:phone":"+1 201 635 9666",
    "sg:postcode":"07057",
    "sg:province":"NJ",
    "sg:tags":[
        "vitamin"
    ],
    "wof:name":"General Nutrition Ctr",
    "wof:placetype":"venue"
},
  "geometry": {"coordinates":[-74.107455,40.844243],"type":"Point"}
}