{
  "type": "Feature",
  "properties": {
    "addr:full":"323 38th St Union City NJ 07087",
    "addr:housenumber":"323",
    "addr:postcode":"07087",
    "addr:street":"38Th St",
    "iso:country":"US",
    "sg:address":"323 38th St",
    "sg:city":"Union City",
    "sg:classifiers":[
        {
            "category":"Professional",
            "subcategory":"Employment Agencies",
            "type":"Services"
        }
    ],
    "sg:phone":"+1 201 770 0032",
    "sg:postcode":"07087",
    "sg:province":"NJ",
    "sg:tags":[
        "help",
        "supply"
    ],
    "wof:name":"Stratus Service Group Inc",
    "wof:placetype":"venue"
},
  "geometry": {"coordinates":[-74.025486,40.774516],"type":"Point"}
}