{
  "type": "Feature",
  "properties": {
    "addr:full":"15 Furnace Rd Chester NJ 07930",
    "addr:housenumber":"15",
    "addr:postcode":"07930",
    "addr:street":"Furnace Rd",
    "iso:country":"US",
    "sg:address":"15 Furnace Rd",
    "sg:city":"Chester",
    "sg:classifiers":[
        {
            "category":"Retail",
            "subcategory":"Funeral Services",
            "type":"Services"
        }
    ],
    "sg:phone":"+1 908 879 3090",
    "sg:postcode":"07930",
    "sg:province":"NJ",
    "sg:tags":[
        "director"
    ],
    "wof:name":"William J Leber Funeral Home",
    "wof:placetype":"venue"
},
  "geometry": {"coordinates":[-74.706474,40.793119],"type":"Point"}
}