{
  "type": "Feature",
  "properties": {
    "addr:full":"83 S Washington Ave Bergenfield NJ 07621",
    "addr:housenumber":"83",
    "addr:postcode":"07621",
    "addr:street":"S Washington Ave",
    "iso:country":"US",
    "sg:address":"83 S Washington Ave",
    "sg:city":"Bergenfield",
    "sg:classifiers":[
        {
            "category":"Personal",
            "type":"Services"
        }
    ],
    "sg:phone":"+1 201 439 0313",
    "sg:postcode":"07621",
    "sg:province":"NJ",
    "sg:tags":[
        "salon",
        "tanning"
    ],
    "wof:name":"Miami Tan",
    "wof:placetype":"venue"
},
  "geometry": {"coordinates":[-73.99686,40.924789],"type":"Point"}
}