{
  "type": "Feature",
  "properties": {
    "iso:country":"US",
    "sg:address":"3203 Atlantic Ave",
    "sg:city":"Allenwood",
    "sg:classifiers":[
        {
            "category":"Shopping",
            "subcategory":"Gifts & Souvenirs",
            "type":"Retail Goods"
        }
    ],
    "sg:phone":"+1   ",
    "sg:postcode":"08720",
    "sg:province":"NJ",
    "wof:name":"Wicked Wickery",
    "wof:placetype":"venue"
},
  "geometry": {"coordinates":[-74.100268,40.142233],"type":"Point"}
}