{
  "type": "Feature",
  "properties": {
    "iso:country":"US",
    "sg:address":"348 Brookvale Ter",
    "sg:city":"Kinnelon",
    "sg:classifiers":[
        {
            "category":"Manufacturing",
            "subcategory":"Metals",
            "type":"Manufacturing & Wholesale Goods"
        }
    ],
    "sg:phone":"+1 973 838 3966",
    "sg:postcode":"07405",
    "sg:province":"NJ",
    "sg:tags":[
        "brass"
    ],
    "wof:name":"Independent Metals Inc",
    "wof:placetype":"venue"
},
  "geometry": {"coordinates":[-74.396246,41.014206],"type":"Point"}
}