{
  "type": "Feature",
  "properties": {
    "addr:full":"512 Frank E Rodgers Blvd N Harrison NJ 07029",
    "addr:housenumber":"512",
    "addr:postcode":"07029",
    "addr:street":"Frank E Rodgers Blvd N",
    "iso:country":"US",
    "sg:address":"512 Frank E Rodgers Blvd N",
    "sg:city":"Harrison",
    "sg:classifiers":[
        {
            "category":"Professional",
            "subcategory":"Accounting & Tax Preparation",
            "type":"Services"
        }
    ],
    "sg:phone":"+1 973 484 7332",
    "sg:postcode":"07029",
    "sg:province":"NJ",
    "sg:tags":[
        "return",
        "filing"
    ],
    "wof:name":"Malqui Tax",
    "wof:placetype":"venue"
},
  "geometry": {"coordinates":[-74.157284,40.750533],"type":"Point"}
}