{
  "type": "Feature",
  "properties": {
    "iso:country":"US",
    "sg:address":"336 US Highway 46",
    "sg:city":"Great Meadows",
    "sg:classifiers":[
        {
            "category":"Building & Trades",
            "subcategory":"Plumbing",
            "type":"Services"
        }
    ],
    "sg:phone":"+1 908 637 4457",
    "sg:postcode":"07838",
    "sg:province":"NJ",
    "wof:name":"Lloyd C Grub Plumbing & Heating Ll C",
    "wof:placetype":"venue"
},
  "geometry": {"coordinates":[-74.937775,40.850415],"type":"Point"}
}