{
  "type": "Feature",
  "properties": {
    "iso:country":"US",
    "sg:address":"430 N Broad St",
    "sg:city":"Woodbury",
    "sg:classifiers":[
        {
            "category":"Food & Beverages",
            "subcategory":"Liquor & Beverages",
            "type":"Retail Goods"
        }
    ],
    "sg:phone":"+1 856 853 9616",
    "sg:postcode":"08096",
    "sg:province":"NJ",
    "sg:tags":[
        "alcoholic"
    ],
    "wof:name":"J & Ds Discount Liquor Gallery",
    "wof:placetype":"venue"
},
  "geometry": {"coordinates":[-75.14954,39.842776],"type":"Point"}
}