{
  "type": "Feature",
  "properties": {
    "addr:full":"36 Church Rd Maple Shade NJ 08054",
    "addr:housenumber":"36",
    "addr:postcode":"08054",
    "addr:street":"Church Rd",
    "iso:country":"US",
    "sg:address":"36 Church Rd",
    "sg:city":"Maple Shade",
    "sg:classifiers":[
        {
            "category":"Autos & Motor Vehicles",
            "subcategory":"Fuel & Gas Station",
            "type":"Retail Goods"
        }
    ],
    "sg:phone":"+1   ",
    "sg:postcode":"08054",
    "sg:province":"NJ",
    "sg:tags":[
        "station"
    ],
    "wof:name":"Gabes Texaco",
    "wof:placetype":"venue"
},
  "geometry": {"coordinates":[-74.980206,39.930922],"type":"Point"}
}