{
  "type": "Feature",
  "properties": {
    "iso:country":"US",
    "sg:address":"74 W Main St",
    "sg:city":"Chester",
    "sg:classifiers":[
        {
            "category":"Retail",
            "subcategory":"Veterinary Services",
            "type":"Services"
        }
    ],
    "sg:phone":"+1 908 879 5161",
    "sg:postcode":"07930",
    "sg:province":"NJ",
    "sg:tags":[
        "veterinarian"
    ],
    "wof:name":"Chester Animal Hospital",
    "wof:placetype":"venue"
},
  "geometry": {"coordinates":[-74.702917,40.781867],"type":"Point"}
}