{
  "type": "Feature",
  "properties": {
    "addr:full":"44 Swartzel Dr Middletown NJ 07748",
    "addr:housenumber":"44",
    "addr:postcode":"07748",
    "addr:street":"Swartzel Dr",
    "iso:country":"US",
    "sg:address":"44 Swartzel Dr",
    "sg:city":"Middletown",
    "sg:classifiers":[
        {
            "category":"Building & Trades",
            "subcategory":"Landscaping Services",
            "type":"Services"
        }
    ],
    "sg:phone":"+1 732 671 9554",
    "sg:postcode":"07748",
    "sg:province":"NJ",
    "wof:name":"Flynn Tree Service",
    "wof:placetype":"venue"
},
  "geometry": {"coordinates":[-74.09485100000001,40.399958],"type":"Point"}
}