{
  "type": "Feature",
  "properties": {
    "addr:full":"2519 Boardwalk Atlantic City NJ 08401",
    "addr:housenumber":"2519",
    "addr:postcode":"08401",
    "addr:street":"Boardwalk",
    "iso:country":"US",
    "sg:address":"2519 Boardwalk",
    "sg:city":"Atlantic City",
    "sg:classifiers":[
        {
            "category":"Restaurant",
            "type":"Food & Drink"
        }
    ],
    "sg:phone":"+1 609 345 3290",
    "sg:postcode":"08401",
    "sg:province":"NJ",
    "wof:name":"Food Court Express",
    "wof:placetype":"venue"
},
  "geometry": {"coordinates":[-74.441063,39.353039],"type":"Point"}
}