{
  "type": "Feature",
  "properties": {
    "addr:full":"25 Lake Park Ter Hewitt NJ 07421",
    "addr:housenumber":"25",
    "addr:postcode":"07421",
    "addr:street":"Lake Park Ter",
    "iso:country":"US",
    "sg:address":"25 Lake Park Ter",
    "sg:city":"Hewitt",
    "sg:classifiers":[
        {
            "category":"Health Services",
            "subcategory":"Clinic",
            "type":"Services"
        }
    ],
    "sg:phone":"+1 973 728 6855",
    "sg:postcode":"07421",
    "sg:province":"NJ",
    "sg:tags":[
        "promotion"
    ],
    "wof:name":"Health and Wellness Med Svc",
    "wof:placetype":"venue"
},
  "geometry": {"coordinates":[-74.331757,41.165105],"type":"Point"}
}