{
  "type": "Feature",
  "properties": {
    "iso:country":"US",
    "sg:address":"4 S Main St",
    "sg:city":"Woodstown",
    "sg:classifiers":[
        {
            "category":"Shopping",
            "subcategory":"Crafts & Fabrics",
            "type":"Retail Goods"
        }
    ],
    "sg:phone":"+1   ",
    "sg:postcode":"08098",
    "sg:province":"NJ",
    "sg:tags":[
        "sewing"
    ],
    "wof:name":"Pieceful Stitches",
    "wof:placetype":"venue"
},
  "geometry": {"coordinates":[-75.32803199999999,39.651383],"type":"Point"}
}