{
  "type": "Feature",
  "properties": {
    "iso:country":"US",
    "sg:address":"55 Madison Ave",
    "sg:city":"Morristown",
    "sg:classifiers":[
        {
            "category":"Professional",
            "subcategory":"Advertising",
            "type":"Services"
        }
    ],
    "sg:phone":"+1 973 644 2424",
    "sg:postcode":"07960",
    "sg:province":"NJ",
    "sg:tags":[
        "counselor"
    ],
    "wof:name":"Atkinson Pankow & Assoc Inc",
    "wof:placetype":"venue"
},
  "geometry": {"coordinates":[-74.472408,40.78899],"type":"Point"}
}