{
  "type": "Feature",
  "properties": {
    "iso:country":"US",
    "sg:address":"21 Main St",
    "sg:city":"Eatontown",
    "sg:classifiers":[
        {
            "category":"Real Estate",
            "subcategory":"Real Estate Services",
            "type":"Services"
        }
    ],
    "sg:phone":"+1 732 460 0061",
    "sg:postcode":"07724",
    "sg:province":"NJ",
    "sg:tags":[
        "company",
        "title"
    ],
    "wof:name":"Lakeside Title Agency LLC",
    "wof:placetype":"venue"
},
  "geometry": {"coordinates":[-74.058468,40.302622],"type":"Point"}
}