{
  "type": "Feature",
  "properties": {
    "iso:country":"US",
    "sg:address":"25 S East Ave",
    "sg:city":"Vineland",
    "sg:classifiers":[
        {
            "category":"Organizations",
            "subcategory":"Religious Organization",
            "type":"Services"
        }
    ],
    "sg:phone":"+1 856 507 9055",
    "sg:postcode":"08360",
    "sg:province":"NJ",
    "sg:tags":[
        "church"
    ],
    "wof:name":"Living Manna Ministries Inc",
    "wof:placetype":"venue"
},
  "geometry": {"coordinates":[-75.01663600000001,39.48495],"type":"Point"}
}