{
  "type": "Feature",
  "properties": {
    "iso:country":"US",
    "sg:address":"42 S Maple Ave",
    "sg:city":"Ridgewood",
    "sg:classifiers":[
        {
            "category":"Professional",
            "type":"Services"
        }
    ],
    "sg:phone":"+1   ",
    "sg:postcode":"07450",
    "sg:province":"NJ",
    "wof:name":"EPM Inc",
    "wof:placetype":"venue"
},
  "geometry": {"coordinates":[-74.113443,40.978493],"type":"Point"}
}