{
  "type": "Feature",
  "properties": {
    "addr:full":"367 Hamilton Ave Trenton NJ 08609",
    "addr:housenumber":"367",
    "addr:postcode":"08609",
    "addr:street":"Hamilton Ave",
    "iso:country":"US",
    "sg:address":"367 Hamilton Ave",
    "sg:city":"Trenton",
    "sg:classifiers":[
        {
            "category":"Professional",
            "subcategory":"Accounting & Tax Preparation",
            "type":"Services"
        }
    ],
    "sg:phone":"+1 609 396 4545",
    "sg:postcode":"08609",
    "sg:province":"NJ",
    "sg:tags":[
        "return",
        "filing"
    ],
    "wof:name":"Alicea & Roman Associates",
    "wof:placetype":"venue"
},
  "geometry": {"coordinates":[-74.748902,40.215348],"type":"Point"}
}