{
  "type": "Feature",
  "properties": {
    "addr:full":"9 Princeton Ave Brick NJ 08724",
    "addr:housenumber":"9",
    "addr:postcode":"08724",
    "addr:street":"Princeton Ave",
    "iso:country":"US",
    "sg:address":"9 Princeton Ave",
    "sg:city":"Brick",
    "sg:classifiers":[
        {
            "category":"Banks & Credit Unions",
            "subcategory":"Bank",
            "type":"Services"
        }
    ],
    "sg:phone":"+1 732 840 4477",
    "sg:postcode":"08724",
    "sg:province":"NJ",
    "sg:tags":[
        "loan",
        "real estate"
    ],
    "wof:name":"Apple Mortgage Svc",
    "wof:placetype":"venue"
},
  "geometry": {"coordinates":[-74.129881,40.068327],"type":"Point"}
}