{
  "type": "Feature",
  "properties": {
    "addr:full":"387 Somerset St North Plainfield NJ 07060",
    "addr:housenumber":"387",
    "addr:postcode":"07060",
    "addr:street":"Somerset St",
    "iso:country":"US",
    "sg:address":"387 Somerset St",
    "sg:city":"North Plainfield",
    "sg:classifiers":[
        {
            "category":"Health Services",
            "subcategory":"Health Practitioner",
            "type":"Services"
        }
    ],
    "sg:phone":"+1 908 755 9100",
    "sg:postcode":"07060",
    "sg:province":"NJ",
    "sg:tags":[
        "therapist",
        "physical"
    ],
    "wof:name":"Total Care Physical Thrpy Ctr",
    "wof:placetype":"venue"
},
  "geometry": {"coordinates":[-74.431246,40.622758],"type":"Point"}
}