{
  "type": "Feature",
  "properties": {
    "iso:country":"US",
    "sg:address":"14 Morse St",
    "sg:city":"Cranford",
    "sg:classifiers":[
        {
            "category":"Building & Trades",
            "subcategory":"Construction",
            "type":"Services"
        }
    ],
    "sg:phone":"+1 908 276 1691",
    "sg:postcode":"07016",
    "sg:province":"NJ",
    "sg:tags":[
        "house",
        "contractor",
        "residential"
    ],
    "wof:name":"Galico Contractors Inc",
    "wof:placetype":"venue"
},
  "geometry": {"coordinates":[-74.313301,40.641701],"type":"Point"}
}