{
  "type": "Feature",
  "properties": {
    "iso:country":"US",
    "sg:address":"1931 Middle Country Rd",
    "sg:city":"Centereach",
    "sg:classifiers":[
        {
            "category":"Personal",
            "subcategory":"Nail Salon",
            "type":"Services"
        }
    ],
    "sg:phone":"+1 631 580 2554",
    "sg:postcode":"11720",
    "sg:province":"NY",
    "wof:name":"Tiffany Nails & Spa",
    "wof:placetype":"venue"
},
  "geometry": {"coordinates":[-73.96482399999999,40.859043],"type":"Point"}
}