{
  "type": "Feature",
  "properties": {
    "addr:full":"71 Dodd St Nutley NJ 07110",
    "addr:housenumber":"71",
    "addr:postcode":"07110",
    "addr:street":"Dodd St",
    "iso:country":"US",
    "sg:address":"71 Dodd St",
    "sg:city":"Nutley",
    "sg:classifiers":[
        {
            "category":"Autos & Motor Vehicles",
            "subcategory":"Automobile Sales",
            "type":"Retail Goods"
        },
        {
            "category":"Retail",
            "subcategory":"Auto Repair",
            "type":"Services"
        }
    ],
    "sg:phone":"+1 973 667 2121",
    "sg:postcode":"07110",
    "sg:province":"NJ",
    "sg:tags":[
        "repairing",
        "used"
    ],
    "sg:website":"www.njinspectionservices.com",
    "wof:name":"Mulligan Ed Motors",
    "wof:placetype":"venue"
},
  "geometry": {"coordinates":[-74.15330899999999,40.824216],"type":"Point"}
}