{
  "type": "Feature",
  "properties": {
    "iso:country":"US",
    "sg:address":"16 Chapin Rd",
    "sg:city":"Pine Brook",
    "sg:classifiers":[
        {
            "category":"Home & Garden",
            "subcategory":"Building Materials",
            "type":"Retail Goods"
        }
    ],
    "sg:phone":"+1 973 575 4440",
    "sg:postcode":"07058",
    "sg:province":"NJ",
    "sg:tags":[
        "supply"
    ],
    "sg:website":"www.bencoinc.com",
    "wof:name":"Benco Inc",
    "wof:placetype":"venue"
},
  "geometry": {"coordinates":[-74.339879,40.857364],"type":"Point"}
}