{
  "type": "Feature",
  "properties": {
    "iso:country":"US",
    "sg:address":"2 Harvest Ln",
    "sg:city":"Long Valley",
    "sg:classifiers":[
        {
            "category":"Shopping",
            "subcategory":"Bicycles & Sporting Goods",
            "type":"Retail Goods"
        }
    ],
    "sg:phone":"+1   ",
    "sg:postcode":"07853",
    "sg:province":"NJ",
    "wof:name":"Passion Fore Golf LLC",
    "wof:placetype":"venue"
},
  "geometry": {"coordinates":[-74.80873699999999,40.779376],"type":"Point"}
}