{
  "type": "Feature",
  "properties": {
    "addr:full":"600 William St Piscataway NJ 08854",
    "addr:housenumber":"600",
    "addr:postcode":"08854",
    "addr:street":"William St",
    "iso:country":"US",
    "sg:address":"600 William St",
    "sg:city":"Piscataway",
    "sg:classifiers":[
        {
            "category":"Food & Beverages",
            "subcategory":"Groceries & Convenience Stores",
            "type":"Retail Goods"
        }
    ],
    "sg:phone":"+1 732 764 9813",
    "sg:postcode":"08854",
    "sg:province":"NJ",
    "sg:tags":[
        "grocer"
    ],
    "wof:name":"Quick Chek",
    "wof:placetype":"venue"
},
  "geometry": {"coordinates":[-74.49086200000001,40.5686],"type":"Point"}
}