{
  "type": "Feature",
  "properties": {
    "addr:full":"193 W Clinton Ave Tenafly NJ 07670",
    "addr:housenumber":"193",
    "addr:postcode":"07670",
    "addr:street":"W Clinton Ave",
    "iso:country":"US",
    "sg:address":"193 W Clinton Ave",
    "sg:city":"Tenafly",
    "sg:classifiers":[
        {
            "category":"Cinema",
            "subcategory":"Movie Rental",
            "type":"Entertainment"
        }
    ],
    "sg:phone":"+1 201 567 4432",
    "sg:postcode":"07670",
    "sg:province":"NJ",
    "sg:tags":[
        "leasing",
        "video",
        "disc",
        "tape"
    ],
    "wof:name":"48 Hours Sportswear Co Inc",
    "wof:placetype":"venue"
},
  "geometry": {"coordinates":[-73.973557,40.924838],"type":"Point"}
}