{
  "type": "Feature",
  "properties": {
    "addr:full":"357 Randolph Ave Jersey City NJ 07304",
    "addr:housenumber":"357",
    "addr:postcode":"07304",
    "addr:street":"Randolph Ave",
    "iso:country":"US",
    "sg:address":"357 Randolph Ave",
    "sg:city":"Jersey City",
    "sg:classifiers":[
        {
            "category":"Food & Beverages",
            "subcategory":"Groceries & Convenience Stores",
            "type":"Retail Goods"
        },
        {
            "category":"Restaurant",
            "type":"Food & Drink"
        }
    ],
    "sg:phone":"+1 201 434 2194",
    "sg:postcode":"07304",
    "sg:province":"NJ",
    "sg:tags":[
        "delicatessen"
    ],
    "wof:name":"Union Superette 2",
    "wof:placetype":"venue"
},
  "geometry": {"coordinates":[-74.068541,40.714262],"type":"Point"}
}