{
  "type": "Feature",
  "properties": {
    "addr:full":"2235 W Main St Millville NJ 08332",
    "addr:housenumber":"2235",
    "addr:postcode":"08332",
    "addr:street":"W Main St",
    "iso:country":"US",
    "sg:address":"2235 W Main St",
    "sg:city":"Millville",
    "sg:classifiers":[
        {
            "category":"Utilities",
            "subcategory":"Mobile Phone",
            "type":"Services"
        }
    ],
    "sg:phone":"+1 856 293 0938",
    "sg:postcode":"08332",
    "sg:province":"NJ",
    "sg:tags":[
        "telephone",
        "cellular"
    ],
    "wof:name":"Cingular Wireless",
    "wof:placetype":"venue"
},
  "geometry": {"coordinates":[-75.100481,39.405416],"type":"Point"}
}