{
  "type": "Feature",
  "properties": {
    "addr:full":"17 4th St Bordentown NJ 08505",
    "addr:housenumber":"17",
    "addr:postcode":"08505",
    "addr:street":"4Th St",
    "iso:country":"US",
    "sg:address":"17 4th St",
    "sg:city":"Bordentown",
    "sg:classifiers":[
        {
            "category":"Wholesale",
            "subcategory":"Auto Parts",
            "type":"Manufacturing & Wholesale Goods"
        }
    ],
    "sg:phone":"+1 609 298 0825",
    "sg:postcode":"08505",
    "sg:province":"NJ",
    "wof:name":"Wholesale Specialties",
    "wof:placetype":"venue"
},
  "geometry": {"coordinates":[-74.731005,40.13471],"type":"Point"}
}