{
  "type": "Feature",
  "properties": {
    "addr:full":"1098 Sunny Slope Dr Mountainside NJ 07092",
    "addr:housenumber":"1098",
    "addr:postcode":"07092",
    "addr:street":"Sunny Slope Dr",
    "iso:country":"US",
    "sg:address":"1098 Sunny Slope Dr",
    "sg:city":"Mountainside",
    "sg:classifiers":[
        {
            "category":"Insurance",
            "subcategory":"Insurance Agent",
            "type":"Services"
        }
    ],
    "sg:phone":"+1   ",
    "sg:postcode":"07092",
    "sg:province":"NJ",
    "wof:name":"Ukrainian National Assn I",
    "wof:placetype":"venue"
},
  "geometry": {"coordinates":[-74.34960100000001,40.688171],"type":"Point"}
}