{
  "type": "Feature",
  "properties": {
    "addr:full":"350 Cranbury Rd East Brunswick NJ 08816",
    "addr:housenumber":"350",
    "addr:postcode":"08816",
    "addr:street":"Cranbury Rd",
    "iso:country":"US",
    "sg:address":"350 Cranbury Rd",
    "sg:city":"East Brunswick",
    "sg:classifiers":[
        {
            "category":"Real Estate",
            "subcategory":"Real Estate Agent",
            "type":"Services"
        }
    ],
    "sg:phone":"+1 732 257 3000",
    "sg:postcode":"08816",
    "sg:province":"NJ",
    "wof:name":"Town & Country Realtors",
    "wof:placetype":"venue"
},
  "geometry": {"coordinates":[-74.393203,40.437081],"type":"Point"}
}