{
  "type": "Feature",
  "properties": {
    "iso:country":"US",
    "sg:address":"38 Chicopee Dr",
    "sg:city":"Wayne",
    "sg:classifiers":[
        {
            "category":"Building & Trades",
            "subcategory":"Construction",
            "type":"Services"
        }
    ],
    "sg:phone":"+1 973 694 0505",
    "sg:postcode":"07470",
    "sg:province":"NJ",
    "sg:tags":[
        "hanging",
        "contractor"
    ],
    "wof:name":"Touch Of The Brush",
    "wof:placetype":"venue"
},
  "geometry": {"coordinates":[-74.229463,40.975137],"type":"Point"}
}