{
  "type": "Feature",
  "properties": {
    "addr:full":"40 Washington Ave Ste A Belleville NJ 07109",
    "addr:housenumber":"40",
    "addr:postcode":"07109",
    "addr:street":"Washington Ave Ste A",
    "iso:country":"US",
    "sg:address":"40 Washington Ave Ste A",
    "sg:city":"Belleville",
    "sg:classifiers":[
        {
            "category":"Personal",
            "subcategory":"Barber",
            "type":"Services"
        }
    ],
    "sg:phone":"+1 973 759 0509",
    "sg:postcode":"07109",
    "sg:province":"NJ",
    "wof:name":"Figueroa Barber Shop 2",
    "wof:placetype":"venue"
},
  "geometry": {"coordinates":[-74.15384400000001,40.782557],"type":"Point"}
}