{
  "type": "Feature",
  "properties": {
    "iso:country":"US",
    "sg:address":"315 Market St",
    "sg:city":"Trenton",
    "sg:classifiers":[
        {
            "category":"Professional",
            "subcategory":"Lawyer & Legal Services",
            "type":"Services"
        }
    ],
    "sg:phone":"+1 609 599 2244",
    "sg:postcode":"08611",
    "sg:province":"NJ",
    "sg:tags":[
        "attorney"
    ],
    "wof:name":"Takace & Somers",
    "wof:placetype":"venue"
},
  "geometry": {"coordinates":[-74.762001,40.215723],"type":"Point"}
}