{
  "type": "Feature",
  "properties": {
    "addr:full":"700 Union Landing Rd Riverton NJ 08077",
    "addr:housenumber":"700",
    "addr:postcode":"08077",
    "addr:street":"Union Landing Rd",
    "iso:country":"US",
    "sg:address":"700 Union Landing Rd",
    "sg:city":"Riverton",
    "sg:classifiers":[
        {
            "category":"Manufacturing",
            "subcategory":"Glass & Minerals",
            "type":"Manufacturing & Wholesale Goods"
        }
    ],
    "sg:phone":"+1 856 829 0400",
    "sg:postcode":"08077",
    "sg:province":"NJ",
    "sg:tags":[
        "float",
        "mfg"
    ],
    "wof:name":"Afg Cinnaminson Plant",
    "wof:placetype":"venue"
},
  "geometry": {"coordinates":[-74.99331599999999,40.017305],"type":"Point"}
}