{
  "type": "Feature",
  "properties": {
    "iso:country":"US",
    "sg:address":"221 Willmont Ave",
    "sg:city":"Barrington",
    "sg:classifiers":[
        {
            "category":"Manufacturing",
            "subcategory":"Printing",
            "type":"Manufacturing & Wholesale Goods"
        }
    ],
    "sg:phone":"+1 856 547 9505",
    "sg:postcode":"08007",
    "sg:province":"NJ",
    "sg:tags":[
        "periodical"
    ],
    "wof:name":"Hometown Coupon Magazine LLC",
    "wof:placetype":"venue"
},
  "geometry": {"coordinates":[-75.05565799999999,39.866876],"type":"Point"}
}