{
  "type": "Feature",
  "properties": {
    "iso:country":"US",
    "sg:address":"2110 State Rte 35",
    "sg:city":"Sea Girt",
    "sg:classifiers":[
        {
            "category":"Autos & Motor Vehicles",
            "subcategory":"Automobile Sales",
            "type":"Retail Goods"
        }
    ],
    "sg:phone":"+1 732 974 1500",
    "sg:postcode":"08750",
    "sg:province":"NJ",
    "sg:tags":[
        "car",
        "dealer"
    ],
    "wof:name":"Ambassador Motors",
    "wof:placetype":"venue"
},
  "geometry": {"coordinates":[-74.060806,40.141823],"type":"Point"}
}