{
  "type": "Feature",
  "properties": {
    "iso:country":"US",
    "sg:address":"408 Stokes Rd",
    "sg:city":"Medford",
    "sg:classifiers":[
        {
            "category":"Restaurant",
            "type":"Food & Drink"
        }
    ],
    "sg:menulink":"http://www.allmenus.com/nj/medford/15800-femmina-italian-grill/menu/",
    "sg:phone":"+1 609 714 8800",
    "sg:postcode":"08055",
    "sg:province":"NJ",
    "sg:tags":[
        "italian"
    ],
    "wof:name":"Femmina Italian Grill",
    "wof:placetype":"venue"
},
  "geometry": {"coordinates":[-74.817474,39.878049],"type":"Point"}
}