{
  "type": "Feature",
  "properties": {
    "addr:full":"169 Washington Street Morristown NJ 07960",
    "addr:housenumber":"169",
    "addr:postcode":"07960",
    "addr:street":"Washington Street",
    "iso:country":"US",
    "sg:address":"169 Washington Street",
    "sg:city":"Morristown",
    "sg:classifiers":[
        {
            "category":"Retail",
            "subcategory":"Auto Repair",
            "type":"Services"
        }
    ],
    "sg:phone":"+1 973 229 3227",
    "sg:postcode":"07960",
    "sg:province":"NJ",
    "sg:tags":[
        "detailing"
    ],
    "sg:website":"www.allinthedetailsnj.com",
    "wof:name":"All In The Details Professional Detail Services",
    "wof:placetype":"venue"
},
  "geometry": {"coordinates":[-74.492108,40.800542],"type":"Point"}
}