{
  "type": "Feature",
  "properties": {
    "iso:country":"US",
    "sg:address":"373 Bloomfield Ave",
    "sg:city":"Montclair",
    "sg:classifiers":[
        {
            "category":"Building & Trades",
            "subcategory":"Locksmith",
            "type":"Services"
        }
    ],
    "sg:phone":"+1 973 854 5293",
    "sg:postcode":"07042",
    "sg:province":"NJ",
    "sg:tags":[
        "key"
    ],
    "wof:name":"0 1 All Day A Emergency Locksmith",
    "wof:placetype":"venue"
},
  "geometry": {"coordinates":[-74.21534699999999,40.812377],"type":"Point"}
}