{
  "type": "Feature",
  "properties": {
    "addr:full":"42 Mayfield Ave Edison NJ 08837",
    "addr:housenumber":"42",
    "addr:postcode":"08837",
    "addr:street":"Mayfield Ave",
    "iso:country":"US",
    "sg:address":"42 Mayfield Ave",
    "sg:city":"Edison",
    "sg:classifiers":[
        {
            "category":"Professional",
            "subcategory":"Detective & Security Services",
            "type":"Services"
        }
    ],
    "sg:phone":"+1   ",
    "sg:postcode":"08837",
    "sg:province":"NJ",
    "sg:tags":[
        "system"
    ],
    "wof:name":"Certified Protection Systems",
    "wof:placetype":"venue"
},
  "geometry": {"coordinates":[-74.34493000000001,40.505421],"type":"Point"}
}