{
  "type": "Feature",
  "properties": {
    "addr:full":"32 Medinah Ct Jackson NJ 08527",
    "addr:housenumber":"32",
    "addr:postcode":"08527",
    "addr:street":"Medinah Ct",
    "iso:country":"US",
    "sg:address":"32 Medinah Ct",
    "sg:city":"Jackson",
    "sg:classifiers":[
        {
            "category":"Shopping",
            "subcategory":"Discount & Variety Stores",
            "type":"Retail Goods"
        }
    ],
    "sg:phone":"+1 732 928 9300",
    "sg:postcode":"08527",
    "sg:province":"NJ",
    "sg:tags":[
        "merchandise",
        "general"
    ],
    "wof:name":"Winding Ways Sales Ctr",
    "wof:placetype":"venue"
},
  "geometry": {"coordinates":[-74.29216099999999,40.131445],"type":"Point"}
}