{
  "type": "Feature",
  "properties": {
    "addr:full":"30 Mall Dr W Jersey City NJ 07310",
    "addr:housenumber":"30",
    "addr:postcode":"07310",
    "addr:street":"Mall Dr W",
    "iso:country":"US",
    "sg:address":"30 Mall Dr W",
    "sg:city":"Jersey City",
    "sg:classifiers":[
        {
            "category":"Utilities",
            "subcategory":"Mobile Phone",
            "type":"Services"
        }
    ],
    "sg:phone":"+1 201 239 4000",
    "sg:postcode":"07310",
    "sg:province":"NJ",
    "sg:tags":[
        "communication",
        "radiotelephone"
    ],
    "wof:name":"Verizon",
    "wof:placetype":"venue"
},
  "geometry": {"coordinates":[-74.039326,40.729517],"type":"Point"}
}