{
  "type": "Feature",
  "properties": {
    "iso:country":"US",
    "sg:address":"36 Potomac Rd",
    "sg:city":"Monmouth Junction",
    "sg:classifiers":[
        {
            "category":"Health Services",
            "subcategory":"Medical Lab",
            "type":"Services"
        }
    ],
    "sg:phone":"+1   ",
    "sg:postcode":"08852",
    "sg:province":"NJ",
    "sg:tags":[
        "laboratory",
        "dental"
    ],
    "wof:name":"One Dental Ceramics Inc",
    "wof:placetype":"venue"
},
  "geometry": {"coordinates":[-74.51139000000001,40.401426],"type":"Point"}
}