{
  "type": "Feature",
  "properties": {
    "iso:country":"US",
    "sg:address":"155 Village Rd",
    "sg:city":"Toms River",
    "sg:classifiers":[
        {
            "category":"Freight",
            "type":"Transportation"
        }
    ],
    "sg:phone":"+1 732 286 5102",
    "sg:postcode":"08755",
    "sg:province":"NJ",
    "sg:tags":[
        "operator",
        "trucking"
    ],
    "wof:name":"Gibbs Traffic Systems",
    "wof:placetype":"venue"
},
  "geometry": {"coordinates":[-74.230806,40.025754],"type":"Point"}
}