{
  "type": "Feature",
  "properties": {
    "iso:country":"US",
    "sg:address":"354 Maitland Ave",
    "sg:city":"Teaneck",
    "sg:classifiers":[
        {
            "category":"Education",
            "subcategory":"Music School",
            "type":"Public Place"
        }
    ],
    "sg:phone":"+1 201 801 0083",
    "sg:postcode":"07666",
    "sg:province":"NJ",
    "sg:tags":[
        "instrument",
        "teacher",
        "musical"
    ],
    "sg:website":"teachkids.kindermusik.net",
    "wof:name":"Kindermusik with Ms K",
    "wof:placetype":"venue"
},
  "geometry": {"coordinates":[-74.010153,40.905268],"type":"Point"}
}