{
  "type": "Feature",
  "properties": {
    "iso:country":"US",
    "sg:address":"320 Warrenville Rd",
    "sg:city":"Green Brook",
    "sg:classifiers":[
        {
            "category":"Wholesale",
            "subcategory":"Electrical",
            "type":"Manufacturing & Wholesale Goods"
        }
    ],
    "sg:phone":"+1 908 757 8537",
    "sg:postcode":"08812",
    "sg:province":"NJ",
    "sg:tags":[
        "alarm",
        "burglar",
        "system"
    ],
    "wof:name":"Tri-Star Alarm Svc",
    "wof:placetype":"venue"
},
  "geometry": {"coordinates":[-74.487937,40.605756],"type":"Point"}
}