{
  "type": "Feature",
  "properties": {
    "addr:full":"33 2nd Ave Raritan NJ 08869",
    "addr:housenumber":"33",
    "addr:postcode":"08869",
    "addr:street":"2Nd Ave",
    "iso:country":"US",
    "sg:address":"33 2nd Ave",
    "sg:city":"Raritan",
    "sg:classifiers":[
        {
            "category":"Health Services",
            "subcategory":"Podiatrist",
            "type":"Services"
        },
        {
            "category":"Health Services",
            "subcategory":"Doctor",
            "type":"Services"
        }
    ],
    "sg:phone":"+1 908 685 1931",
    "sg:postcode":"08869",
    "sg:province":"NJ",
    "sg:tags":[
        "physician",
        "surgeon"
    ],
    "wof:name":"Robin Gessner DPM",
    "wof:placetype":"venue"
},
  "geometry": {"coordinates":[-74.63616399999999,40.569802],"type":"Point"}
}