{
  "type": "Feature",
  "properties": {
    "addr:full":"28 Reservoir Rd Stewartsville NJ 08886",
    "addr:housenumber":"28",
    "addr:postcode":"08886",
    "addr:street":"Reservoir Rd",
    "iso:country":"US",
    "sg:address":"28 Reservoir Rd",
    "sg:city":"Stewartsville",
    "sg:classifiers":[
        {
            "category":"Professional",
            "subcategory":"Engineering",
            "type":"Services"
        }
    ],
    "sg:phone":"+1   ",
    "sg:postcode":"08886",
    "sg:province":"NJ",
    "wof:name":"Kenneth J Ortbach Inc",
    "wof:placetype":"venue"
},
  "geometry": {"coordinates":[-75.10996900000001,40.715908],"type":"Point"}
}