{
  "type": "Feature",
  "properties": {
    "iso:country":"US",
    "sg:address":"20 Burch Dr",
    "sg:city":"Morris Plains",
    "sg:classifiers":[
        {
            "category":"Professional",
            "subcategory":"Lawyer & Legal Services",
            "type":"Services"
        }
    ],
    "sg:phone":"+1 973 292 0099",
    "sg:postcode":"07950",
    "sg:province":"NJ",
    "sg:tags":[
        "attorney"
    ],
    "wof:name":"Robert D Gardner Law Office",
    "wof:placetype":"venue"
},
  "geometry": {"coordinates":[-74.48658399999999,40.826881],"type":"Point"}
}