{
  "type": "Feature",
  "properties": {
    "addr:full":"16 Bay Ave Manahawkin NJ 08050",
    "addr:housenumber":"16",
    "addr:postcode":"08050",
    "addr:street":"Bay Ave",
    "iso:country":"US",
    "sg:address":"16 Bay Ave",
    "sg:city":"Manahawkin",
    "sg:classifiers":[
        {
            "category":"Professional",
            "subcategory":"Management & Consulting",
            "type":"Services"
        }
    ],
    "sg:phone":"+1   ",
    "sg:postcode":"08050",
    "sg:province":"NJ",
    "wof:name":"Pjm Consulting Corp",
    "wof:placetype":"venue"
},
  "geometry": {"coordinates":[-74.186187,39.65553],"type":"Point"}
}