{
  "type": "Feature",
  "properties": {
    "addr:full":"550 Crescent Blvd Gloucester City NJ 08030",
    "addr:housenumber":"550",
    "addr:postcode":"08030",
    "addr:street":"Crescent Blvd",
    "iso:country":"US",
    "sg:address":"550 Crescent Blvd",
    "sg:city":"Gloucester City",
    "sg:classifiers":[
        {
            "category":"Organizations",
            "subcategory":"Community Association",
            "type":"Services"
        }
    ],
    "sg:phone":"+1 856 742 0433",
    "sg:postcode":"08030",
    "sg:province":"NJ",
    "sg:tags":[
        "civic",
        "social"
    ],
    "wof:name":"American Legion",
    "wof:placetype":"venue"
},
  "geometry": {"coordinates":[-75.11790499999999,39.876285],"type":"Point"}
}