{
  "type": "Feature",
  "properties": {
    "iso:country":"US",
    "sg:address":"2 Hadley Dr",
    "sg:city":"Medford",
    "sg:classifiers":[
        {
            "category":"Shopping",
            "subcategory":"Gifts & Souvenirs",
            "type":"Retail Goods"
        }
    ],
    "sg:phone":"+1   ",
    "sg:postcode":"08055",
    "sg:province":"NJ",
    "wof:name":"Danas Hallmark",
    "wof:placetype":"venue"
},
  "geometry": {"coordinates":[-74.81057800000001,39.838545],"type":"Point"}
}