{
  "type": "Feature",
  "properties": {
    "addr:full":"314 Worthington Ave Spring Lake NJ 07762",
    "addr:housenumber":"314",
    "addr:postcode":"07762",
    "addr:street":"Worthington Ave",
    "iso:country":"US",
    "sg:address":"314 Worthington Ave",
    "sg:city":"Spring Lake",
    "sg:classifiers":[
        {
            "category":"Professional",
            "subcategory":"Employment Agencies",
            "type":"Services"
        }
    ],
    "sg:phone":"+1   ",
    "sg:postcode":"07762",
    "sg:province":"NJ",
    "sg:tags":[
        "information",
        "consulting",
        "technology"
    ],
    "wof:name":"Crimson Precision Inc",
    "wof:placetype":"venue"
},
  "geometry": {"coordinates":[-74.029978,40.159956],"type":"Point"}
}