{
  "type": "Feature",
  "properties": {
    "iso:country":"US",
    "sg:address":"211 Market St",
    "sg:city":"Elmwood Park",
    "sg:classifiers":[
        {
            "category":"Retail",
            "subcategory":"Auto Repair",
            "type":"Services"
        }
    ],
    "sg:phone":"+1 201 796 8113",
    "sg:postcode":"07407",
    "sg:province":"NJ",
    "sg:tags":[
        "body",
        "automobile",
        "towing",
        "painting"
    ],
    "wof:name":"Parkway Auto Body",
    "wof:placetype":"venue"
},
  "geometry": {"coordinates":[-74.122101,40.900799],"type":"Point"}
}