{
  "type": "Feature",
  "properties": {
    "addr:full":"3702 Bayshore Rd Cape May NJ 08204",
    "addr:housenumber":"3702",
    "addr:postcode":"08204",
    "addr:street":"Bayshore Rd",
    "iso:country":"US",
    "sg:address":"3702 Bayshore Rd",
    "sg:city":"Cape May",
    "sg:classifiers":[
        {
            "category":"Food & Beverages",
            "subcategory":"Specialty",
            "type":"Retail Goods"
        }
    ],
    "sg:phone":"+1 609 886 8008",
    "sg:postcode":"08204",
    "sg:province":"NJ",
    "sg:tags":[
        "health",
        "market"
    ],
    "wof:name":"Bayshore Nutrition Center",
    "wof:placetype":"venue"
},
  "geometry": {"coordinates":[-74.941597,38.984001],"type":"Point"}
}