{
  "type": "Feature",
  "properties": {
    "addr:full":"272 22nd Ave Brick NJ 08724",
    "addr:housenumber":"272",
    "addr:postcode":"08724",
    "addr:street":"22Nd Ave",
    "iso:country":"US",
    "sg:address":"272 22nd Ave",
    "sg:city":"Brick",
    "sg:classifiers":[
        {
            "category":"Building & Trades",
            "subcategory":"Landscaping Services",
            "type":"Services"
        }
    ],
    "sg:phone":"+1 732 530 0077",
    "sg:postcode":"08724",
    "sg:province":"NJ",
    "sg:tags":[
        "landscape",
        "contractor"
    ],
    "wof:name":"Amazing Beginnings",
    "wof:placetype":"venue"
},
  "geometry": {"coordinates":[-74.09801299999999,40.098022],"type":"Point"}
}