{
  "type": "Feature",
  "properties": {
    "iso:country":"US",
    "sg:address":"359 State Rt 17",
    "sg:city":"Wood Ridge",
    "sg:classifiers":[
        {
            "category":"Fast Food",
            "type":"Food & Drink"
        }
    ],
    "sg:phone":"+1 201 939 3108",
    "sg:postcode":"07075",
    "sg:province":"NJ",
    "sg:tags":[
        "burger"
    ],
    "sg:website":"www.wendys.com",
    "wof:name":"Wendy's",
    "wof:placetype":"venue"
},
  "geometry": {"coordinates":[-74.077202,40.846802],"type":"Point"}
}