{
  "type": "Feature",
  "properties": {
    "addr:full":"192 Elton Ave Trenton NJ 08620",
    "addr:housenumber":"192",
    "addr:postcode":"08620",
    "addr:street":"Elton Ave",
    "iso:country":"US",
    "sg:address":"192 Elton Ave",
    "sg:city":"Trenton",
    "sg:classifiers":[
        {
            "category":"Professional",
            "subcategory":"Accounting & Tax Preparation",
            "type":"Services"
        }
    ],
    "sg:phone":"+1 609 585 6163",
    "sg:postcode":"08620",
    "sg:province":"NJ",
    "wof:name":"Vicari Millner & Arcolesse",
    "wof:placetype":"venue"
},
  "geometry": {"coordinates":[-74.66944599999999,40.187719],"type":"Point"}
}