{
  "type": "Feature",
  "properties": {
    "addr:full":"180 Old Tappan Rd E Old Tappan NJ 07675",
    "addr:housenumber":"180",
    "addr:postcode":"07675",
    "addr:street":"Old Tappan Rd E",
    "iso:country":"US",
    "sg:address":"180 Old Tappan Rd E",
    "sg:city":"Old Tappan",
    "sg:classifiers":[
        {
            "category":"Communications",
            "subcategory":"Film & Video Production",
            "type":"Services"
        },
        {
            "category":"Arts & Performance",
            "subcategory":"Theater",
            "type":"Entertainment"
        }
    ],
    "sg:phone":"+1 201 750 9168",
    "sg:postcode":"07675",
    "sg:province":"NJ",
    "sg:tags":[
        "motion",
        "television",
        "program",
        "producer"
    ],
    "wof:name":"Sea Lion Productions Inc",
    "wof:placetype":"venue"
},
  "geometry": {"coordinates":[-73.976716,41.017337],"type":"Point"}
}