{
  "type": "Feature",
  "properties": {
    "addr:full":"3916 Boardwalk Wildwood NJ 08260",
    "addr:housenumber":"3916",
    "addr:postcode":"08260",
    "addr:street":"Boardwalk",
    "iso:country":"US",
    "sg:address":"3916 Boardwalk",
    "sg:city":"Wildwood",
    "sg:classifiers":[
        {
            "category":"Shopping",
            "subcategory":"Clothing, Apparel, & Fashions",
            "type":"Retail Goods"
        }
    ],
    "sg:phone":"+1 609 522 4650",
    "sg:postcode":"08260",
    "sg:province":"NJ",
    "sg:tags":[
        "furnishing",
        "accessory"
    ],
    "sg:website":"www.sandjamm.com/",
    "wof:name":"Sand Jamm Kingdom of the Sun",
    "wof:placetype":"venue"
},
  "geometry": {"coordinates":[-74.813599,38.984699],"type":"Point"}
}