{
  "type": "Feature",
  "properties": {
    "addr:full":"1613 State Rte 47 Rio Grande NJ 08242",
    "addr:housenumber":"1613",
    "addr:postcode":"08242",
    "addr:street":"State Rte 47",
    "iso:country":"US",
    "sg:address":"1613 State Rte 47",
    "sg:city":"Rio Grande",
    "sg:classifiers":[
        {
            "category":"Personal",
            "subcategory":"Tanning Parlor",
            "type":"Services"
        }
    ],
    "sg:phone":"+1 609 889 7400",
    "sg:postcode":"08242",
    "sg:province":"NJ",
    "sg:tags":[
        "salon"
    ],
    "wof:name":"Hollywood Tans & Nail Salon",
    "wof:placetype":"venue"
},
  "geometry": {"coordinates":[-74.87145200000001,39.011717],"type":"Point"}
}