{
  "type": "Feature",
  "properties": {
    "addr:full":"16 Brunswick Woods Dr East Brunswick NJ 08816",
    "addr:housenumber":"16",
    "addr:postcode":"08816",
    "addr:street":"Brunswick Woods Dr",
    "iso:country":"US",
    "sg:address":"16 Brunswick Woods Dr",
    "sg:city":"East Brunswick",
    "sg:classifiers":[
        {
            "category":"Retail",
            "subcategory":"Auto Repair",
            "type":"Services"
        }
    ],
    "sg:phone":"+1 732 254 1310",
    "sg:postcode":"08816",
    "sg:province":"NJ",
    "sg:tags":[
        "repairing",
        "automobile",
        "general"
    ],
    "wof:name":"Foreign Car Hospital",
    "wof:placetype":"venue"
},
  "geometry": {"coordinates":[-74.390175,40.420845],"type":"Point"}
}