{
  "type": "Feature",
  "properties": {
    "addr:full":"774 Black Horse Pike Pleasantville NJ 08232",
    "addr:housenumber":"774",
    "addr:postcode":"08232",
    "addr:street":"Black Horse Pike",
    "iso:country":"US",
    "sg:address":"774 Black Horse Pike",
    "sg:city":"Pleasantville",
    "sg:classifiers":[
        {
            "category":"Restaurant",
            "type":"Food & Drink"
        }
    ],
    "sg:menulink":"http://www.allmenus.com/nj/pleasantville/194719-mcdonalds/menu/",
    "sg:phone":"+1 609 645 1840",
    "sg:postcode":"08232",
    "sg:province":"NJ",
    "sg:tags":[
        "burger",
        "american"
    ],
    "wof:name":"McDonald's",
    "wof:placetype":"venue"
},
  "geometry": {"coordinates":[-74.536355,39.39306],"type":"Point"}
}