{
  "type": "Feature",
  "properties": {
    "addr:full":"141 Marina Dr Edison NJ 08817",
    "addr:housenumber":"141",
    "addr:postcode":"08817",
    "addr:street":"Marina Dr",
    "iso:country":"US",
    "sg:address":"141 Marina Dr",
    "sg:city":"Edison",
    "sg:classifiers":[
        {
            "category":"Real Estate",
            "subcategory":"Real Estate Operator",
            "type":"Services"
        }
    ],
    "sg:phone":"+1 732 985 0859",
    "sg:postcode":"08817",
    "sg:province":"NJ",
    "sg:tags":[
        "building",
        "apartment"
    ],
    "wof:name":"Valley Manor Apartments",
    "wof:placetype":"venue"
},
  "geometry": {"coordinates":[-74.41416099999999,40.49365],"type":"Point"}
}