{
  "type": "Feature",
  "properties": {
    "iso:country":"US",
    "sg:address":"219 Murray Hill Pkwy",
    "sg:city":"East Rutherford",
    "sg:classifiers":[
        {
            "category":"Banks & Credit Unions",
            "subcategory":"Investment Brokerage",
            "type":"Services"
        }
    ],
    "sg:phone":"+1   ",
    "sg:postcode":"07073",
    "sg:province":"NJ",
    "sg:tags":[
        "advisory"
    ],
    "wof:name":"Georgeson & Company Inc",
    "wof:placetype":"venue"
},
  "geometry": {"coordinates":[-74.088989,40.82215],"type":"Point"}
}