{
  "type": "Feature",
  "properties": {
    "addr:full":"2365 Hamburg Tpke Wayne NJ 07470",
    "addr:housenumber":"2365",
    "addr:postcode":"07470",
    "addr:street":"Hamburg Tpke",
    "iso:country":"US",
    "sg:address":"2365 Hamburg Tpke",
    "sg:city":"Wayne",
    "sg:classifiers":[
        {
            "category":"Autos & Motor Vehicles",
            "subcategory":"Automobile Sales",
            "type":"Retail Goods"
        }
    ],
    "sg:phone":"+1   ",
    "sg:postcode":"07470",
    "sg:province":"NJ",
    "sg:tags":[
        "used"
    ],
    "wof:name":"Ronnies Car & Truck Sales",
    "wof:placetype":"venue"
},
  "geometry": {"coordinates":[-74.27927800000001,40.988107],"type":"Point"}
}