{
  "type": "Feature",
  "properties": {
    "addr:full":"One Gateway Center Newark NJ 07102",
    "addr:postcode":"07102",
    "iso:country":"US",
    "sg:address":"One Gateway Center",
    "sg:city":"Newark",
    "sg:classifiers":[
        {
            "category":"Coffee & Tea",
            "type":"Food & Drink"
        },
        {
            "category":"Bagels",
            "subcategory":"None",
            "type":"Food & Drink"
        },
        {
            "category":"Donuts",
            "subcategory":"None",
            "type":"Food & Drink"
        }
    ],
    "sg:postcode":"07102",
    "sg:province":"NJ",
    "sg:website":"www.dunkindonuts.com",
    "wof:name":"Dunkin' Donuts",
    "wof:placetype":"venue"
},
  "geometry": {"coordinates":[-74.169731,40.735255],"type":"Point"}
}