{
  "type": "Feature",
  "properties": {
    "addr:full":"96 S Washington Ave Bergenfield NJ 07621",
    "addr:housenumber":"96",
    "addr:postcode":"07621",
    "addr:street":"S Washington Ave",
    "iso:country":"US",
    "sg:address":"96 S Washington Ave",
    "sg:city":"Bergenfield",
    "sg:classifiers":[
        {
            "category":"Restaurant",
            "type":"Food & Drink"
        }
    ],
    "sg:phone":"+1   ",
    "sg:postcode":"07621",
    "sg:province":"NJ",
    "sg:tags":[
        "eating"
    ],
    "wof:name":"La Tasca LLC",
    "wof:placetype":"venue"
},
  "geometry": {"coordinates":[-73.99703599999999,40.924519],"type":"Point"}
}