{
  "type": "Feature",
  "properties": {
    "iso:country":"US",
    "sg:address":"8 Peckman Rd",
    "sg:city":"Little Falls",
    "sg:classifiers":[
        {
            "category":"Professional",
            "subcategory":"Lawyer & Legal Services",
            "type":"Services"
        }
    ],
    "sg:phone":"+1 973 785 3300",
    "sg:postcode":"07424",
    "sg:province":"NJ",
    "sg:tags":[
        "attorney",
        "counselor",
        "at",
        "law"
    ],
    "wof:name":"Fishman Martin Law Office",
    "wof:placetype":"venue"
},
  "geometry": {"coordinates":[-74.21925299999999,40.884236],"type":"Point"}
}