{
  "type": "Feature",
  "properties": {
    "iso:country":"US",
    "sg:address":"740 Irvington Ave",
    "sg:city":"Maplewood",
    "sg:classifiers":[
        {
            "category":"Banks & Credit Unions",
            "subcategory":"Bank",
            "type":"Services"
        }
    ],
    "sg:phone":"+1   ",
    "sg:postcode":"07040",
    "sg:province":"NJ",
    "sg:tags":[
        "national",
        "commercial"
    ],
    "sg:website":"www.valleynationalbank.com",
    "wof:name":"Valley National Bank",
    "wof:placetype":"venue"
},
  "geometry": {"coordinates":[-74.244379,40.733069],"type":"Point"}
}