{
  "type": "Feature",
  "properties": {
    "addr:full":"123 Barclay St Paterson NJ 07503",
    "addr:housenumber":"123",
    "addr:postcode":"07503",
    "addr:street":"Barclay St",
    "iso:country":"US",
    "sg:address":"123 Barclay St",
    "sg:city":"Paterson",
    "sg:classifiers":[
        {
            "category":"Food & Beverages",
            "subcategory":"Groceries & Convenience Stores",
            "type":"Retail Goods"
        }
    ],
    "sg:phone":"+1   ",
    "sg:postcode":"07503",
    "sg:province":"NJ",
    "wof:name":"Mardoris Grocery",
    "wof:placetype":"venue"
},
  "geometry": {"coordinates":[-74.168291,40.901305],"type":"Point"}
}