{
  "type": "Feature",
  "properties": {
    "iso:country":"US",
    "sg:address":"235 Lexington Ave",
    "sg:city":"Passaic",
    "sg:classifiers":[
        {
            "category":"Social Services",
            "subcategory":"Child Care",
            "type":"Services"
        }
    ],
    "sg:phone":"+1 973 779 3990",
    "sg:postcode":"07055",
    "sg:province":"NJ",
    "sg:tags":[
        "day"
    ],
    "wof:name":"Lexington Child Care Llc",
    "wof:placetype":"venue"
},
  "geometry": {"coordinates":[-74.128095,40.869855],"type":"Point"}
}