{
  "type": "Feature",
  "properties": {
    "iso:country":"US",
    "sg:address":"16 Bloomfield Ave",
    "sg:city":"Newark",
    "sg:classifiers":[
        {
            "category":"Personal",
            "subcategory":"Beauty Salon",
            "type":"Services"
        }
    ],
    "sg:phone":"+1 973 350 0063",
    "sg:postcode":"07104",
    "sg:province":"NJ",
    "sg:tags":[
        "shop"
    ],
    "wof:name":"Karina's Beauty Salon",
    "wof:placetype":"venue"
},
  "geometry": {"coordinates":[-74.17103299999999,40.753555],"type":"Point"}
}