{
  "type": "Feature",
  "properties": {
    "iso:country":"US",
    "sg:address":"327 Greenwich St",
    "sg:city":"Belvidere",
    "sg:classifiers":[
        {
            "category":"Organizations",
            "subcategory":"Religious Organization",
            "type":"Services"
        }
    ],
    "sg:phone":"+1 908 475 4919",
    "sg:postcode":"07823",
    "sg:province":"NJ",
    "sg:tags":[
        "church"
    ],
    "wof:name":"Ccd Office",
    "wof:placetype":"venue"
},
  "geometry": {"coordinates":[-75.078898,40.825451],"type":"Point"}
}