{
  "type": "Feature",
  "properties": {
    "iso:country":"US",
    "sg:address":"237 Mount Lucas Rd",
    "sg:city":"Princeton",
    "sg:classifiers":[
        {
            "category":"Professional",
            "subcategory":"Management & Consulting",
            "type":"Services"
        }
    ],
    "sg:phone":"+1 609 688 1092",
    "sg:postcode":"08540",
    "sg:province":"NJ",
    "wof:name":"Duncan/Ellison",
    "wof:placetype":"venue"
},
  "geometry": {"coordinates":[-74.660855,40.368718],"type":"Point"}
}