{
  "type": "Feature",
  "properties": {
    "addr:full":"170 Kinnelon Rd Kinnelon NJ 07405",
    "addr:housenumber":"170",
    "addr:postcode":"07405",
    "addr:street":"Kinnelon Rd",
    "iso:country":"US",
    "sg:address":"170 Kinnelon Rd",
    "sg:city":"Kinnelon",
    "sg:classifiers":[
        {
            "category":"Wholesale",
            "subcategory":"Durable Goods & Equipment",
            "type":"Manufacturing & Wholesale Goods"
        }
    ],
    "sg:phone":"+1 973 838 0123",
    "sg:postcode":"07405",
    "sg:province":"NJ",
    "sg:tags":[
        "representative",
        "manufacturer"
    ],
    "wof:name":"Phoenix Group",
    "wof:placetype":"venue"
},
  "geometry": {"coordinates":[-74.384738,40.989068],"type":"Point"}
}