{
  "type": "Feature",
  "properties": {
    "addr:full":"26 Barkers Mill Rd Hackettstown NJ 07840",
    "addr:housenumber":"26",
    "addr:postcode":"07840",
    "addr:street":"Barkers Mill Rd",
    "iso:country":"US",
    "sg:address":"26 Barkers Mill Rd",
    "sg:city":"Hackettstown",
    "sg:classifiers":[
        {
            "category":"Building & Trades",
            "subcategory":"Pest Control",
            "type":"Services"
        }
    ],
    "sg:phone":"+1 908 637 4993",
    "sg:postcode":"07840",
    "sg:province":"NJ",
    "wof:name":"C & C Pest Control",
    "wof:placetype":"venue"
},
  "geometry": {"coordinates":[-74.891555,40.863461],"type":"Point"}
}