{
  "type": "Feature",
  "properties": {
    "addr:full":"148 N Main St Manville NJ 08835",
    "addr:housenumber":"148",
    "addr:postcode":"08835",
    "addr:street":"N Main St",
    "iso:country":"US",
    "sg:address":"148 N Main St",
    "sg:city":"Manville",
    "sg:classifiers":[
        {
            "category":"Food & Beverages",
            "subcategory":"Specialty",
            "type":"Retail Goods"
        }
    ],
    "sg:phone":"+1   ",
    "sg:postcode":"08835",
    "sg:province":"NJ",
    "wof:name":"GNC",
    "wof:placetype":"venue"
},
  "geometry": {"coordinates":[-74.586472,40.54698],"type":"Point"}
}