{
  "type": "Feature",
  "properties": {
    "iso:country":"US",
    "sg:address":"3016 US Hwy 9",
    "sg:city":"Ocean View",
    "sg:classifiers":[
        {
            "category":"Restaurant",
            "type":"Food & Drink"
        }
    ],
    "sg:phone":"+1 609 624 7555",
    "sg:postcode":"08230",
    "sg:province":"NJ",
    "sg:tags":[
        "shop",
        "coffee"
    ],
    "wof:name":"Coffee Etc",
    "wof:placetype":"venue"
},
  "geometry": {"coordinates":[-74.705527,39.206627],"type":"Point"}
}