{
  "type": "Feature",
  "properties": {
    "iso:country":"US",
    "sg:address":"1123 Millstone River Rd",
    "sg:city":"Hillsborough",
    "sg:classifiers":[
        {
            "category":"Wholesale",
            "subcategory":"Non-durable Goods",
            "type":"Manufacturing & Wholesale Goods"
        }
    ],
    "sg:phone":"+1 908 359 7114",
    "sg:postcode":"08844",
    "sg:province":"NJ",
    "wof:name":"Design Works",
    "wof:placetype":"venue"
},
  "geometry": {"coordinates":[-74.59127700000001,40.525445],"type":"Point"}
}