{
  "type": "Feature",
  "properties": {
    "iso:country":"US",
    "sg:address":"484 N Beverwyck Rd",
    "sg:city":"Lake Hiawatha",
    "sg:classifiers":[
        {
            "category":"Personal",
            "type":"Services"
        }
    ],
    "sg:phone":"+1 973 334 8551",
    "sg:postcode":"07034",
    "sg:province":"NJ",
    "sg:tags":[
        "sewing",
        "alteration"
    ],
    "wof:name":"White Stone Cleaners",
    "wof:placetype":"venue"
},
  "geometry": {"coordinates":[-74.38020299999999,40.887001],"type":"Point"}
}