{
  "type": "Feature",
  "properties": {
    "iso:country":"US",
    "sg:address":"20 Grove Ave",
    "sg:city":"Verona",
    "sg:classifiers":[
        {
            "category":"Building & Trades",
            "subcategory":"Locksmith",
            "type":"Services"
        }
    ],
    "sg:phone":"+1 877 834 6706",
    "sg:postcode":"07044",
    "sg:province":"NJ",
    "sg:tags":[
        "key"
    ],
    "wof:name":"Always Affective Available Emergency Locksmith",
    "wof:placetype":"venue"
},
  "geometry": {"coordinates":[-74.24815700000001,40.833876],"type":"Point"}
}