{
  "type": "Feature",
  "properties": {
    "addr:full":"1809 Lark Ln Cherry Hill NJ 08003",
    "addr:housenumber":"1809",
    "addr:postcode":"08003",
    "addr:street":"Lark Ln",
    "iso:country":"US",
    "sg:address":"1809 Lark Ln",
    "sg:city":"Cherry Hill",
    "sg:classifiers":[
        {
            "category":"Wholesale",
            "subcategory":"Non-durable Goods",
            "type":"Manufacturing & Wholesale Goods"
        }
    ],
    "sg:phone":"+1 856 354 2100",
    "sg:postcode":"08003",
    "sg:province":"NJ",
    "sg:tags":[
        "advertising"
    ],
    "wof:name":"Promotional Design Group Inc",
    "wof:placetype":"venue"
},
  "geometry": {"coordinates":[-74.977324,39.87412],"type":"Point"}
}