{
  "type": "Feature",
  "properties": {
    "addr:full":"902 Bayshore Rd Villas NJ 08251",
    "addr:housenumber":"902",
    "addr:postcode":"08251",
    "addr:street":"Bayshore Rd",
    "iso:country":"US",
    "sg:address":"902 Bayshore Rd",
    "sg:city":"Villas",
    "sg:classifiers":[
        {
            "category":"Restaurant",
            "type":"Food & Drink"
        }
    ],
    "sg:phone":"+1   ",
    "sg:postcode":"08251",
    "sg:province":"NJ",
    "sg:tags":[
        "eating"
    ],
    "wof:name":"Catering By Millard",
    "wof:placetype":"venue"
},
  "geometry": {"coordinates":[-74.93446900000001,39.031385],"type":"Point"}
}