{
  "type": "Feature",
  "properties": {
    "addr:full":"850 US Hwy 1 North Brunswick NJ 08902",
    "addr:housenumber":"850",
    "addr:postcode":"08902",
    "addr:street":"Us Hwy 1",
    "iso:country":"US",
    "sg:address":"850 US Hwy 1",
    "sg:city":"North Brunswick",
    "sg:classifiers":[
        {
            "category":"Food & Beverages",
            "subcategory":"Liquor & Beverages",
            "type":"Retail Goods"
        }
    ],
    "sg:phone":"+1 732 247 2523",
    "sg:postcode":"08902",
    "sg:province":"NJ",
    "sg:tags":[
        "wine"
    ],
    "wof:name":"Monarch Wine Co Of Georgia",
    "wof:placetype":"venue"
},
  "geometry": {"coordinates":[-74.471519,40.458236],"type":"Point"}
}