{
  "type": "Feature",
  "properties": {
    "addr:full":"128 Francisco Ave Rutherford NJ 07070",
    "addr:housenumber":"128",
    "addr:postcode":"07070",
    "addr:street":"Francisco Ave",
    "iso:country":"US",
    "sg:address":"128 Francisco Ave",
    "sg:city":"Rutherford",
    "sg:classifiers":[
        {
            "category":"Farming",
            "subcategory":"Livestock Farm",
            "type":"Manufacturing & Wholesale Goods"
        }
    ],
    "sg:phone":"+1 201 935 7672",
    "sg:postcode":"07070",
    "sg:province":"NJ",
    "sg:tags":[
        "breeding",
        "dog"
    ],
    "wof:name":"Regina Bichon Frisa",
    "wof:placetype":"venue"
},
  "geometry": {"coordinates":[-74.117324,40.834249],"type":"Point"}
}