{
  "type": "Feature",
  "properties": {
    "addr:full":"8 Tindall Rd Middletown NJ 07748",
    "addr:housenumber":"8",
    "addr:postcode":"07748",
    "addr:street":"Tindall Rd",
    "iso:country":"US",
    "sg:address":"8 Tindall Rd",
    "sg:city":"Middletown",
    "sg:classifiers":[
        {
            "category":"Health Services",
            "subcategory":"Doctor",
            "type":"Services"
        }
    ],
    "sg:phone":"+1 732 706 1100",
    "sg:postcode":"07748",
    "sg:province":"NJ",
    "sg:tags":[
        "dentist"
    ],
    "wof:name":"Rockwell Family Dental",
    "wof:placetype":"venue"
},
  "geometry": {"coordinates":[-74.10118199999999,40.397061],"type":"Point"}
}