{
  "type": "Feature",
  "properties": {
    "addr:full":"16 Lyford Ct Toms River NJ 08757",
    "addr:housenumber":"16",
    "addr:postcode":"08757",
    "addr:street":"Lyford Ct",
    "iso:country":"US",
    "sg:address":"16 Lyford Ct",
    "sg:city":"Toms River",
    "sg:classifiers":[
        {
            "category":"Professional",
            "type":"Services"
        }
    ],
    "sg:phone":"+1   ",
    "sg:postcode":"08757",
    "sg:province":"NJ",
    "wof:name":"G Steinbach",
    "wof:placetype":"venue"
},
  "geometry": {"coordinates":[-74.23966799999999,39.952932],"type":"Point"}
}