{
  "type": "Feature",
  "properties": {
    "addr:full":"304 Maple Pl Cranford NJ 07016",
    "addr:housenumber":"304",
    "addr:postcode":"07016",
    "addr:street":"Maple Pl",
    "iso:country":"US",
    "sg:address":"304 Maple Pl",
    "sg:city":"Cranford",
    "sg:classifiers":[
        {
            "category":"Building & Trades",
            "subcategory":"Plumbing",
            "type":"Services"
        }
    ],
    "sg:phone":"+1 908 272 3620",
    "sg:postcode":"07016",
    "sg:province":"NJ",
    "wof:name":"Cuozzo L J & Son",
    "wof:placetype":"venue"
},
  "geometry": {"coordinates":[-74.303337,40.663554],"type":"Point"}
}