{
  "type": "Feature",
  "properties": {
    "iso:country":"US",
    "sg:address":"1803 Hawthorne Ct",
    "sg:city":"Sewell",
    "sg:classifiers":[
        {
            "category":"Health Services",
            "subcategory":"Health Practitioner",
            "type":"Services"
        }
    ],
    "sg:phone":"+1 856 256 9055",
    "sg:postcode":"08080",
    "sg:province":"NJ",
    "sg:tags":[
        "nurse",
        "registry"
    ],
    "wof:name":"Quality Care Nursing",
    "wof:placetype":"venue"
},
  "geometry": {"coordinates":[-75.05377900000001,39.72188],"type":"Point"}
}