{
  "type": "Feature",
  "properties": {
    "addr:full":"116 Gainsboro Rd Trenton NJ 08648",
    "addr:housenumber":"116",
    "addr:postcode":"08648",
    "addr:street":"Gainsboro Rd",
    "iso:country":"US",
    "sg:address":"116 Gainsboro Rd",
    "sg:city":"Trenton",
    "sg:classifiers":[
        {
            "category":"Wholesale",
            "subcategory":"Durable Goods & Equipment",
            "type":"Manufacturing & Wholesale Goods"
        }
    ],
    "sg:phone":"+1 609 771 0560",
    "sg:postcode":"08648",
    "sg:province":"NJ",
    "sg:tags":[
        "sunglasses",
        "accessory"
    ],
    "wof:name":"Moore Frames Inc",
    "wof:placetype":"venue"
},
  "geometry": {"coordinates":[-74.738435,40.263666],"type":"Point"}
}