{
  "type": "Feature",
  "properties": {
    "iso:country":"US",
    "sg:address":"103 Marlton Rd",
    "sg:city":"Pilesgrove",
    "sg:classifiers":[
        {
            "category":"Manufacturing",
            "subcategory":"Tools & Machinery",
            "type":"Manufacturing & Wholesale Goods"
        }
    ],
    "sg:phone":"+1 856 769 0056",
    "sg:postcode":"08098",
    "sg:province":"NJ",
    "sg:tags":[
        "transmission",
        "power"
    ],
    "sg:website":"www.salemcompany.com",
    "wof:name":"Salem Co",
    "wof:placetype":"venue"
},
  "geometry": {"coordinates":[-75.336491,39.65538],"type":"Point"}
}