{
  "type": "Feature",
  "properties": {
    "iso:country":"US",
    "sg:address":"2 E Washington Ave",
    "sg:city":"Atlantic Highlands",
    "sg:classifiers":[
        {
            "category":"Communications",
            "subcategory":"Film & Video Production",
            "type":"Services"
        }
    ],
    "sg:phone":"+1 732 291 0219",
    "sg:postcode":"07716",
    "sg:province":"NJ",
    "sg:tags":[
        "motion"
    ],
    "wof:name":"Crazy Duck Productions Inc",
    "wof:placetype":"venue"
},
  "geometry": {"coordinates":[-74.036846,40.411282],"type":"Point"}
}