{
  "type": "Feature",
  "properties": {
    "iso:country":"US",
    "sg:address":"400 W Route 38",
    "sg:city":"Moorestown",
    "sg:classifiers":[
        {
            "category":"Bakery",
            "type":"Food & Drink"
        }
    ],
    "sg:menulink":"http://www.allmenus.com/nj/moorestown/223955-cinnabon/menu/",
    "sg:phone":"+1 856 802 0205",
    "sg:postcode":"08057",
    "sg:province":"NJ",
    "sg:tags":[
        "american",
        "pastry"
    ],
    "wof:name":"Cinnabon",
    "wof:placetype":"venue"
},
  "geometry": {"coordinates":[-74.930178,39.961458],"type":"Point"}
}