{
  "type": "Feature",
  "properties": {
    "addr:full":"48 Wynnewood Rd Livingston NJ 07039",
    "addr:housenumber":"48",
    "addr:postcode":"07039",
    "addr:street":"Wynnewood Rd",
    "iso:country":"US",
    "sg:address":"48 Wynnewood Rd",
    "sg:city":"Livingston",
    "sg:classifiers":[
        {
            "category":"Manufacturing",
            "subcategory":"Tools & Machinery",
            "type":"Manufacturing & Wholesale Goods"
        }
    ],
    "sg:phone":"+1 973 992 1423",
    "sg:postcode":"07039",
    "sg:province":"NJ",
    "sg:tags":[
        "mfg"
    ],
    "wof:name":"Camp Tool & Die Corp",
    "wof:placetype":"venue"
},
  "geometry": {"coordinates":[-74.342923,40.788002],"type":"Point"}
}