{
  "type": "Feature",
  "properties": {
    "addr:full":"850 Van Houten Ave Clifton NJ 07013",
    "addr:housenumber":"850",
    "addr:postcode":"07013",
    "addr:street":"Van Houten Ave",
    "iso:country":"US",
    "sg:address":"850 Van Houten Ave",
    "sg:city":"Clifton",
    "sg:classifiers":[
        {
            "category":"Restaurant",
            "type":"Food & Drink"
        }
    ],
    "sg:phone":"+1 973 614 8227",
    "sg:postcode":"07013",
    "sg:province":"NJ",
    "sg:tags":[
        "eating"
    ],
    "wof:name":"Clifton Chinatown Gourmet",
    "wof:placetype":"venue"
},
  "geometry": {"coordinates":[-74.156097,40.862801],"type":"Point"}
}