{
  "type": "Feature",
  "properties": {
    "iso:country":"US",
    "sg:address":"28 Lenox Ave",
    "sg:city":"Cranford",
    "sg:classifiers":[
        {
            "category":"Professional",
            "type":"Services"
        }
    ],
    "sg:phone":"+1   ",
    "sg:postcode":"07016",
    "sg:province":"NJ",
    "wof:name":"Steven Levy",
    "wof:placetype":"venue"
},
  "geometry": {"coordinates":[-74.298858,40.665744],"type":"Point"}
}