{
  "type": "Feature",
  "properties": {
    "addr:full":"902 Merrywood Dr Edison NJ 08817",
    "addr:housenumber":"902",
    "addr:postcode":"08817",
    "addr:street":"Merrywood Dr",
    "iso:country":"US",
    "sg:address":"902 Merrywood Dr",
    "sg:city":"Edison",
    "sg:classifiers":[
        {
            "category":"Wholesale",
            "subcategory":"Groceries",
            "type":"Manufacturing & Wholesale Goods"
        }
    ],
    "sg:phone":"+1 732 572 5980",
    "sg:postcode":"08817",
    "sg:province":"NJ",
    "sg:tags":[
        "cocoa",
        "chocolate"
    ],
    "wof:name":"Eckert's Gift",
    "wof:placetype":"venue"
},
  "geometry": {"coordinates":[-74.41090699999999,40.527712],"type":"Point"}
}