{
  "type": "Feature",
  "properties": {
    "addr:full":"209 Saint Georges Ave Roselle NJ 07203",
    "addr:housenumber":"209",
    "addr:postcode":"07203",
    "addr:street":"Saint Georges Ave",
    "iso:country":"US",
    "sg:address":"209 Saint Georges Ave",
    "sg:city":"Roselle",
    "sg:classifiers":[
        {
            "category":"Restaurant",
            "type":"Food & Drink"
        }
    ],
    "sg:phone":"+1 908 245 4417",
    "sg:postcode":"07203",
    "sg:province":"NJ",
    "wof:name":"Burger King",
    "wof:placetype":"venue"
},
  "geometry": {"coordinates":[-74.261202,40.640895],"type":"Point"}
}