{
  "type": "Feature",
  "properties": {
    "addr:full":"3628 Atlantic Brigantine Blvd Brigantine NJ 08203",
    "addr:housenumber":"3628",
    "addr:postcode":"08203",
    "addr:street":"Atlantic Brigantine Blvd",
    "iso:country":"US",
    "sg:address":"3628 Atlantic Brigantine Blvd",
    "sg:city":"Brigantine",
    "sg:classifiers":[
        {
            "category":"Restaurant",
            "type":"Food & Drink"
        }
    ],
    "sg:phone":"+1 609 266 7608",
    "sg:postcode":"08203",
    "sg:province":"NJ",
    "wof:name":"Yuki Hana Restaurant",
    "wof:placetype":"venue"
},
  "geometry": {"coordinates":[-74.39152,39.394734],"type":"Point"}
}