{
  "type": "Feature",
  "properties": {
    "addr:full":"1617 Prince Dr Cherry Hill NJ 08003",
    "addr:housenumber":"1617",
    "addr:postcode":"08003",
    "addr:street":"Prince Dr",
    "iso:country":"US",
    "sg:address":"1617 Prince Dr",
    "sg:city":"Cherry Hill",
    "sg:classifiers":[
        {
            "category":"Professional",
            "type":"Services"
        }
    ],
    "sg:phone":"+1 856 795 1897",
    "sg:postcode":"08003",
    "sg:province":"NJ",
    "sg:tags":[
        "establishment"
    ],
    "wof:name":"D Carroll",
    "wof:placetype":"venue"
},
  "geometry": {"coordinates":[-74.97112799999999,39.86721],"type":"Point"}
}