{
  "type": "Feature",
  "properties": {
    "addr:full":"58 Princeton Pl Wayne NJ 07470",
    "addr:housenumber":"58",
    "addr:postcode":"07470",
    "addr:street":"Princeton Pl",
    "iso:country":"US",
    "sg:address":"58 Princeton Pl",
    "sg:city":"Wayne",
    "sg:classifiers":[
        {
            "category":"Professional",
            "subcategory":"Computer Services",
            "type":"Services"
        }
    ],
    "sg:phone":"+1 973 248 8039",
    "sg:postcode":"07470",
    "sg:province":"NJ",
    "sg:tags":[
        "consulting"
    ],
    "wof:name":"Jars Computer Service Inc",
    "wof:placetype":"venue"
},
  "geometry": {"coordinates":[-74.27470700000001,40.98109],"type":"Point"}
}