{
  "type": "Feature",
  "properties": {
    "iso:country":"US",
    "sg:address":"161 Washington Valley Rd",
    "sg:city":"Warren",
    "sg:classifiers":[
        {
            "category":"Education",
            "subcategory":"Special Training",
            "type":"Public Place"
        }
    ],
    "sg:phone":"+1 732 748 2020",
    "sg:postcode":"07059",
    "sg:province":"NJ",
    "sg:tags":[
        "tutoring"
    ],
    "wof:name":"Enrichment Center",
    "wof:placetype":"venue"
},
  "geometry": {"coordinates":[-74.494822,40.615111],"type":"Point"}
}