{
  "type": "Feature",
  "properties": {
    "addr:full":"978 US Hwy 9 Bayville NJ 08721",
    "addr:housenumber":"978",
    "addr:postcode":"08721",
    "addr:street":"Us Hwy 9",
    "iso:country":"US",
    "sg:address":"978 US Hwy 9",
    "sg:city":"Bayville",
    "sg:classifiers":[
        {
            "category":"Shopping",
            "subcategory":"Discount & Variety Stores",
            "type":"Retail Goods"
        }
    ],
    "sg:phone":"+1 732 237 2900",
    "sg:postcode":"08721",
    "sg:province":"NJ",
    "sg:tags":[
        "post",
        "trading"
    ],
    "wof:name":"East-West TRADING LLC",
    "wof:placetype":"venue"
},
  "geometry": {"coordinates":[-74.166163,39.879181],"type":"Point"}
}