{
  "type": "Feature",
  "properties": {
    "iso:country":"US",
    "sg:address":"1201 S Beecham Rd",
    "sg:city":"Williamstown",
    "sg:classifiers":[
        {
            "category":"Professional",
            "subcategory":"Business Services",
            "type":"Services"
        }
    ],
    "sg:phone":"+1   ",
    "sg:postcode":"08094",
    "sg:province":"NJ",
    "wof:name":"Key Recovery",
    "wof:placetype":"venue"
},
  "geometry": {"coordinates":[-74.98317299999999,39.670436],"type":"Point"}
}