{
  "type": "Feature",
  "properties": {
    "addr:full":"483 Hollow Rd Skillman NJ 08558",
    "addr:housenumber":"483",
    "addr:postcode":"08558",
    "addr:street":"Hollow Rd",
    "iso:country":"US",
    "sg:address":"483 Hollow Rd",
    "sg:city":"Skillman",
    "sg:classifiers":[
        {
            "category":"Professional",
            "subcategory":"Art Services",
            "type":"Services"
        }
    ],
    "sg:phone":"+1   ",
    "sg:postcode":"08558",
    "sg:province":"NJ",
    "sg:tags":[
        "photo",
        "photography",
        "commercial",
        "studio",
        "portrait"
    ],
    "wof:name":"Tasha Rana Photographics",
    "wof:placetype":"venue"
},
  "geometry": {"coordinates":[-74.735698,40.435933],"type":"Point"}
}