{
  "type": "Feature",
  "properties": {
    "iso:country":"US",
    "sg:address":"855 Garfield Ave",
    "sg:city":"Jersey City",
    "sg:classifiers":[
        {
            "category":"Freight",
            "type":"Transportation"
        }
    ],
    "sg:phone":"+1 201 332 5562",
    "sg:postcode":"07305",
    "sg:province":"NJ",
    "sg:tags":[
        "general"
    ],
    "wof:name":"French Park Warehouse Co",
    "wof:placetype":"venue"
},
  "geometry": {"coordinates":[-74.072762,40.707746],"type":"Point"}
}