{
  "type": "Feature",
  "properties": {
    "addr:full":"279 Hamburg Tpke Riverdale NJ 07457",
    "addr:housenumber":"279",
    "addr:postcode":"07457",
    "addr:street":"Hamburg Tpke",
    "iso:country":"US",
    "sg:address":"279 Hamburg Tpke",
    "sg:city":"Riverdale",
    "sg:classifiers":[
        {
            "category":"Building & Trades",
            "subcategory":"Electrical",
            "type":"Services"
        }
    ],
    "sg:phone":"+1 973 838 7550",
    "sg:postcode":"07457",
    "sg:province":"NJ",
    "sg:tags":[
        "electrical",
        "electric",
        "contractor"
    ],
    "wof:name":"Q & S Electric Company",
    "wof:placetype":"venue"
},
  "geometry": {"coordinates":[-74.318952,41.00146],"type":"Point"}
}