{
  "type": "Feature",
  "properties": {
    "iso:country":"US",
    "sg:address":"438 County Road 513",
    "sg:city":"Califon",
    "sg:classifiers":[
        {
            "category":"Sports & Exercise",
            "subcategory":"Gym",
            "type":"Entertainment"
        }
    ],
    "sg:phone":"+1 908 832 7887",
    "sg:postcode":"07830",
    "sg:province":"NJ",
    "sg:tags":[
        "yoga"
    ],
    "wof:name":"Yoga Studio the",
    "wof:placetype":"venue"
},
  "geometry": {"coordinates":[-74.850403,40.721901],"type":"Point"}
}