{
  "type": "Feature",
  "properties": {
    "iso:country":"US",
    "sg:address":"41 Manners Rd",
    "sg:city":"Ringoes",
    "sg:classifiers":[
        {
            "category":"Building & Trades",
            "subcategory":"Construction",
            "type":"Services"
        }
    ],
    "sg:phone":"+1 609 466 3888",
    "sg:postcode":"08551",
    "sg:province":"NJ",
    "sg:tags":[
        "woodworker"
    ],
    "wof:name":"J Drew Foster",
    "wof:placetype":"venue"
},
  "geometry": {"coordinates":[-74.803935,40.455152],"type":"Point"}
}