{
  "type": "Feature",
  "properties": {
    "iso:country":"US",
    "sg:address":"158 French St",
    "sg:city":"New Brunswick",
    "sg:classifiers":[
        {
            "category":"Professional",
            "subcategory":"Employment Agencies",
            "type":"Services"
        }
    ],
    "sg:phone":"+1 732 846 3130",
    "sg:postcode":"08901",
    "sg:province":"NJ",
    "sg:tags":[
        "leasing"
    ],
    "wof:name":"Staffing Visions Of New Jersey",
    "wof:placetype":"venue"
},
  "geometry": {"coordinates":[-74.453158,40.492388],"type":"Point"}
}