{
  "type": "Feature",
  "properties": {
    "iso:country":"US",
    "sg:address":"29 Jefferson St",
    "sg:city":"Red Bank",
    "sg:classifiers":[
        {
            "category":"Education",
            "subcategory":"Special Training",
            "type":"Public Place"
        }
    ],
    "sg:phone":"+1   ",
    "sg:postcode":"07701",
    "sg:province":"NJ",
    "wof:name":"Craig J Page Enterprises",
    "wof:placetype":"venue"
},
  "geometry": {"coordinates":[-74.08801699999999,40.364754],"type":"Point"}
}