{
  "type": "Feature",
  "properties": {
    "addr:full":"340 Kingsland St Nutley NJ 07110",
    "addr:housenumber":"340",
    "addr:postcode":"07110",
    "addr:street":"Kingsland St",
    "iso:country":"US",
    "sg:address":"340 Kingsland St",
    "sg:city":"Nutley",
    "sg:classifiers":[
        {
            "category":"Professional",
            "subcategory":"Computer Services",
            "type":"Services"
        }
    ],
    "sg:phone":"+1 973 235 3449",
    "sg:postcode":"07110",
    "sg:province":"NJ",
    "sg:tags":[
        "building",
        "design",
        "system",
        "maintenance"
    ],
    "wof:name":"Johnson Controls",
    "wof:placetype":"venue"
},
  "geometry": {"coordinates":[-74.153598,40.829968],"type":"Point"}
}