{
  "type": "Feature",
  "properties": {
    "addr:full":"115 Longview Dr Waldwick NJ 07463",
    "addr:housenumber":"115",
    "addr:postcode":"07463",
    "addr:street":"Longview Dr",
    "iso:country":"US",
    "sg:address":"115 Longview Dr",
    "sg:city":"Waldwick",
    "sg:classifiers":[
        {
            "category":"Professional",
            "subcategory":"Engineering",
            "type":"Services"
        }
    ],
    "sg:phone":"+1   ",
    "sg:postcode":"07463",
    "sg:province":"NJ",
    "wof:name":"Berc A Kurkciyan Engineering",
    "wof:placetype":"venue"
},
  "geometry": {"coordinates":[-74.14616599999999,41.014412],"type":"Point"}
}