{
  "type": "Feature",
  "properties": {
    "iso:country":"US",
    "sg:address":"178 Franklin St",
    "sg:city":"Northvale",
    "sg:classifiers":[
        {
            "category":"Building & Trades",
            "subcategory":"Landscaping Services",
            "type":"Services"
        }
    ],
    "sg:phone":"+1 201 784 8878",
    "sg:postcode":"07647",
    "sg:province":"NJ",
    "sg:tags":[
        "landscape"
    ],
    "wof:name":"Richard Scaglione",
    "wof:placetype":"venue"
},
  "geometry": {"coordinates":[-73.947068,41.003686],"type":"Point"}
}