{
  "type": "Feature",
  "properties": {
    "addr:full":"517 Lake Ave Asbury Park NJ 07712",
    "addr:housenumber":"517",
    "addr:postcode":"07712",
    "addr:street":"Lake Ave Asbury",
    "iso:country":"US",
    "sg:address":"517 Lake Ave",
    "sg:city":"Asbury Park",
    "sg:classifiers":[
        {
            "category":"Bars & Pubs",
            "subcategory":"Lounge",
            "type":"Food & Drink"
        }
    ],
    "sg:menulink":"http://www.allmenus.com/nj/asbury-park/29883-moon-struck-restaurant--cocktail-lounge/menu/",
    "sg:phone":"+1 732 988 0123",
    "sg:postcode":"07712",
    "sg:province":"NJ",
    "sg:tags":[
        "pasta",
        "american",
        "salad"
    ],
    "wof:name":"Moon Struck Restaurant & Cocktail Lounge",
    "wof:placetype":"venue"
},
  "geometry": {"coordinates":[-74.008064,40.215959],"type":"Point"}
}