{
  "type": "Feature",
  "properties": {
    "iso:country":"US",
    "sg:address":"35 State Rte 183",
    "sg:city":"Netcong",
    "sg:classifiers":[
        {
            "category":"Wholesale",
            "subcategory":"Office Equipment",
            "type":"Manufacturing & Wholesale Goods"
        },
        {
            "category":"Shopping",
            "subcategory":"Photographic Equipment",
            "type":"Retail Goods"
        }
    ],
    "sg:phone":"+1 973 347 8600",
    "sg:postcode":"07857",
    "sg:province":"NJ",
    "sg:tags":[
        "machine",
        "copier",
        "duplicating",
        "copying",
        "supply"
    ],
    "wof:name":"Unique Image Corp",
    "wof:placetype":"venue"
},
  "geometry": {"coordinates":[-74.70372399999999,40.899708],"type":"Point"}
}