{
  "type": "Feature",
  "properties": {
    "iso:country":"US",
    "sg:address":"602 Grove St",
    "sg:city":"Dunellen",
    "sg:classifiers":[
        {
            "category":"Building & Trades",
            "subcategory":"Cleaning & Sanitation",
            "type":"Services"
        }
    ],
    "sg:phone":"+1   ",
    "sg:postcode":"08812",
    "sg:province":"NJ",
    "sg:tags":[
        "maintenance"
    ],
    "wof:name":"Clover Cleaning Svc",
    "wof:placetype":"venue"
},
  "geometry": {"coordinates":[-74.464519,40.588443],"type":"Point"}
}