{
  "type": "Feature",
  "properties": {
    "addr:full":"132 Kings Hwy Mount Royal NJ 08061",
    "addr:housenumber":"132",
    "addr:postcode":"08061",
    "addr:street":"Kings Hwy",
    "iso:country":"US",
    "sg:address":"132 Kings Hwy",
    "sg:city":"Mount Royal",
    "sg:classifiers":[
        {
            "category":"Professional",
            "subcategory":"Computer Services",
            "type":"Services"
        }
    ],
    "sg:phone":"+1 856 224 0391",
    "sg:postcode":"08061",
    "sg:province":"NJ",
    "sg:tags":[
        "programing",
        "custom"
    ],
    "wof:name":"Ruff Inc",
    "wof:placetype":"venue"
},
  "geometry": {"coordinates":[-75.20980400000001,39.81053],"type":"Point"}
}