{
  "type": "Feature",
  "properties": {
    "iso:country":"US",
    "sg:address":"132 Pine Ave",
    "sg:city":"Egg Harbor Township",
    "sg:classifiers":[
        {
            "category":"Building & Trades",
            "subcategory":"Plumbing",
            "type":"Services"
        }
    ],
    "sg:phone":"+1 609 646 5777",
    "sg:postcode":"08234",
    "sg:province":"NJ",
    "sg:tags":[
        "contractor"
    ],
    "wof:name":"William Mills Plbg Htg",
    "wof:placetype":"venue"
},
  "geometry": {"coordinates":[-74.652107,39.408702],"type":"Point"}
}