{
  "type": "Feature",
  "properties": {
    "addr:full":"200 Campus Dr Florham Park NJ 07932",
    "addr:housenumber":"200",
    "addr:postcode":"07932",
    "addr:street":"Campus Dr",
    "iso:country":"US",
    "sg:address":"200 Campus Dr",
    "sg:city":"Florham Park",
    "sg:classifiers":[
        {
            "category":"Professional",
            "type":"Services"
        },
        {
            "category":"Real Estate",
            "subcategory":"Real Estate Agent",
            "type":"Services"
        }
    ],
    "sg:phone":"+1 973 410 1009",
    "sg:postcode":"07932",
    "sg:province":"NJ",
    "sg:tags":[
        "property",
        "management",
        "establishment",
        "investment"
    ],
    "wof:name":"Gale & Wentworth Inc",
    "wof:placetype":"venue"
},
  "geometry": {"coordinates":[-74.42964000000001,40.782882],"type":"Point"}
}