{
  "type": "Feature",
  "properties": {
    "iso:country":"US",
    "sg:address":"7546 Msgr Fallon Dr",
    "sg:city":"Pennsauken",
    "sg:classifiers":[
        {
            "category":"Organizations",
            "subcategory":"Religious Organization",
            "type":"Services"
        }
    ],
    "sg:phone":"+1 856 488 8002",
    "sg:postcode":"08109",
    "sg:province":"NJ",
    "wof:name":"Hoenig John D Rev",
    "wof:placetype":"venue"
},
  "geometry": {"coordinates":[-75.03980300000001,39.969601],"type":"Point"}
}