{
  "type": "Feature",
  "properties": {
    "addr:full":"1830 Easton Ave Somerset NJ 08873",
    "addr:housenumber":"1830",
    "addr:postcode":"08873",
    "addr:street":"Easton Ave",
    "iso:country":"US",
    "sg:address":"1830 Easton Ave",
    "sg:city":"Somerset",
    "sg:classifiers":[
        {
            "category":"Food & Beverages",
            "subcategory":"Groceries & Convenience Stores",
            "type":"Retail Goods"
        }
    ],
    "sg:phone":"+1 732 271 0369",
    "sg:postcode":"08873",
    "sg:province":"NJ",
    "wof:name":"Speedy Mart",
    "wof:placetype":"venue"
},
  "geometry": {"coordinates":[-74.50889599999999,40.536661],"type":"Point"}
}