{
  "type": "Feature",
  "properties": {
    "iso:country":"US",
    "sg:address":"239 Williamstown Rd",
    "sg:city":"Berlin",
    "sg:classifiers":[
        {
            "category":"Retail",
            "subcategory":"Repair Shop",
            "type":"Services"
        }
    ],
    "sg:phone":"+1 856 753 7665",
    "sg:postcode":"08009",
    "sg:province":"NJ",
    "sg:tags":[
        "related"
    ],
    "wof:name":"Hair Repair",
    "wof:placetype":"venue"
},
  "geometry": {"coordinates":[-74.942121,39.743485],"type":"Point"}
}