{
  "type": "Feature",
  "properties": {
    "iso:country":"US",
    "sg:address":"39 Woodport Rd",
    "sg:city":"Sparta",
    "sg:classifiers":[
        {
            "category":"Shopping",
            "subcategory":"Stationery & Office Supplies",
            "type":"Retail Goods"
        }
    ],
    "sg:phone":"+1 973 729 8787",
    "sg:postcode":"07871",
    "sg:province":"NJ",
    "wof:name":"Sparta Stationery Plus Inc",
    "wof:placetype":"venue"
},
  "geometry": {"coordinates":[-74.63779700000001,41.034148],"type":"Point"}
}