{
  "type": "Feature",
  "properties": {
    "iso:country":"US",
    "sg:address":"1105 Main St",
    "sg:city":"Asbury Park",
    "sg:classifiers":[
        {
            "category":"Food & Beverages",
            "subcategory":"Bakery",
            "type":"Retail Goods"
        }
    ],
    "sg:phone":"+1 732 774 7577",
    "sg:postcode":"07712",
    "sg:province":"NJ",
    "sg:tags":[
        "baker"
    ],
    "wof:name":"Tex Bagel & Bakery Inc",
    "wof:placetype":"venue"
},
  "geometry": {"coordinates":[-74.010363,40.224579],"type":"Point"}
}