{
  "type": "Feature",
  "properties": {
    "addr:full":"25 Main St Hackensack NJ 07601",
    "addr:housenumber":"25",
    "addr:postcode":"07601",
    "addr:street":"Main St",
    "iso:country":"US",
    "sg:address":"25 Main St",
    "sg:city":"Hackensack",
    "sg:classifiers":[
        {
            "category":"Professional",
            "subcategory":"Lawyer & Legal Services",
            "type":"Services"
        }
    ],
    "sg:phone":"+1 201 342 5790",
    "sg:postcode":"07601",
    "sg:province":"NJ",
    "wof:name":"Toskos Menelaos W Attorney",
    "wof:placetype":"venue"
},
  "geometry": {"coordinates":[-74.044403,40.879002],"type":"Point"}
}