{
  "type": "Feature",
  "properties": {
    "iso:country":"US",
    "sg:address":"43 Lincoln Ave",
    "sg:city":"Mount Ephraim",
    "sg:classifiers":[
        {
            "category":"Shopping",
            "subcategory":"Books",
            "type":"Retail Goods"
        }
    ],
    "sg:phone":"+1   ",
    "sg:postcode":"08059",
    "sg:province":"NJ",
    "wof:name":"Books Are Fun",
    "wof:placetype":"venue"
},
  "geometry": {"coordinates":[-75.091112,39.878561],"type":"Point"}
}