{
  "type": "Feature",
  "properties": {
    "addr:full":"167 Kettle Run Marlton NJ 08053",
    "addr:housenumber":"167",
    "addr:postcode":"08053",
    "addr:street":"Kettle Run",
    "iso:country":"US",
    "sg:address":"167 Kettle Run",
    "sg:city":"Marlton",
    "sg:classifiers":[
        {
            "category":"Building & Trades",
            "subcategory":"Construction",
            "type":"Services"
        }
    ],
    "sg:phone":"+1 856 983 5168",
    "sg:postcode":"08053",
    "sg:province":"NJ",
    "sg:tags":[
        "carpentry",
        "contractor"
    ],
    "wof:name":"Wirth Carpentry Inc",
    "wof:placetype":"venue"
},
  "geometry": {"coordinates":[-74.89904300000001,39.848225],"type":"Point"}
}