{
  "type": "Feature",
  "properties": {
    "addr:full":"500 Van Bussum Ave Garfield NJ 07026",
    "addr:housenumber":"500",
    "addr:postcode":"07026",
    "addr:street":"Van Bussum Ave",
    "iso:country":"US",
    "sg:address":"500 Van Bussum Ave",
    "sg:city":"Garfield",
    "sg:classifiers":[
        {
            "category":"Shopping",
            "subcategory":"Jewelry",
            "type":"Retail Goods"
        }
    ],
    "sg:phone":"+1   ",
    "sg:postcode":"07026",
    "sg:province":"NJ",
    "wof:name":"Svs Jewelry By Design",
    "wof:placetype":"venue"
},
  "geometry": {"coordinates":[-74.105369,40.892401],"type":"Point"}
}