{
  "type": "Feature",
  "properties": {
    "iso:country":"US",
    "sg:address":"800 Jessup Rd",
    "sg:city":"Thorofare",
    "sg:classifiers":[
        {
            "category":"Health Services",
            "subcategory":"Doctor",
            "type":"Services"
        }
    ],
    "sg:phone":"+1 856 848 0500",
    "sg:postcode":"08086",
    "sg:province":"NJ",
    "sg:tags":[
        "medical"
    ],
    "wof:name":"Brian Gotchel DPM",
    "wof:placetype":"venue"
},
  "geometry": {"coordinates":[-75.17582299999999,39.824553],"type":"Point"}
}