{
  "type": "Feature",
  "properties": {
    "addr:full":"933 US Hwy 130 Burlington NJ 08016",
    "addr:housenumber":"933",
    "addr:postcode":"08016",
    "addr:street":"Us Hwy 130",
    "iso:country":"US",
    "sg:address":"933 US Hwy 130",
    "sg:city":"Burlington",
    "sg:classifiers":[
        {
            "category":"Retail",
            "subcategory":"Self-service Laundry",
            "type":"Services"
        }
    ],
    "sg:phone":"+1   ",
    "sg:postcode":"08016",
    "sg:province":"NJ",
    "sg:tags":[
        "operated",
        "coin"
    ],
    "wof:name":"On Go Laundromat",
    "wof:placetype":"venue"
},
  "geometry": {"coordinates":[-74.84090500000001,40.080205],"type":"Point"}
}