{
  "type": "Feature",
  "properties": {
    "iso:country":"US",
    "sg:address":"1 Ironwood Rd",
    "sg:city":"Short Hills",
    "sg:classifiers":[
        {
            "category":"Banks & Credit Unions",
            "subcategory":"Investment Brokerage",
            "type":"Services"
        }
    ],
    "sg:phone":"+1   ",
    "sg:postcode":"07078",
    "sg:province":"NJ",
    "sg:tags":[
        "advisory"
    ],
    "wof:name":"Strategic Financial Management",
    "wof:placetype":"venue"
},
  "geometry": {"coordinates":[-74.353413,40.735267],"type":"Point"}
}