{
  "type": "Feature",
  "properties": {
    "iso:country":"US",
    "sg:address":"211 Berlin Rd",
    "sg:city":"Cherry Hill",
    "sg:classifiers":[
        {
            "category":"Bars & Pubs",
            "type":"Food & Drink"
        }
    ],
    "sg:phone":"+1 856 427 4465",
    "sg:postcode":"08034",
    "sg:province":"NJ",
    "sg:tags":[
        "lounge",
        "cocktail"
    ],
    "wof:name":"Xhale",
    "wof:placetype":"venue"
},
  "geometry": {"coordinates":[-75.021045,39.892019],"type":"Point"}
}