{
  "type": "Feature",
  "properties": {
    "addr:full":"10 Beekman Rd Franklin Park NJ 08823",
    "addr:housenumber":"10",
    "addr:postcode":"08823",
    "addr:street":"Beekman Rd",
    "iso:country":"US",
    "sg:address":"10 Beekman Rd",
    "sg:city":"Franklin Park",
    "sg:classifiers":[
        {
            "category":"Professional",
            "type":"Services"
        }
    ],
    "sg:phone":"+1   ",
    "sg:postcode":"08823",
    "sg:province":"NJ",
    "wof:name":"Kashmir Air Inc",
    "wof:placetype":"venue"
},
  "geometry": {"coordinates":[-74.548723,40.434574],"type":"Point"}
}