{
  "type": "Feature",
  "properties": {
    "iso:country":"US",
    "sg:address":"223 Wyckoff Ave",
    "sg:city":"Ramsey",
    "sg:classifiers":[
        {
            "category":"Building & Trades",
            "subcategory":"Construction",
            "type":"Services"
        }
    ],
    "sg:phone":"+1 201 818 4505",
    "sg:postcode":"07446",
    "sg:province":"NJ",
    "sg:tags":[
        "general",
        "contractor"
    ],
    "wof:name":"J Z Construction Co",
    "wof:placetype":"venue"
},
  "geometry": {"coordinates":[-74.15253,41.050905],"type":"Point"}
}