{
  "type": "Feature",
  "properties": {
    "iso:country":"US",
    "sg:address":"598 Palmer Ave",
    "sg:city":"Middletown",
    "sg:classifiers":[
        {
            "category":"Communications",
            "subcategory":"Film & Video Production",
            "type":"Services"
        }
    ],
    "sg:phone":"+1 732 495 7662",
    "sg:postcode":"07748",
    "sg:province":"NJ",
    "sg:tags":[
        "editing",
        "tape"
    ],
    "wof:name":"Krystle Clear Vdeo Productions",
    "wof:placetype":"venue"
},
  "geometry": {"coordinates":[-74.132414,40.430226],"type":"Point"}
}