{
  "type": "Feature",
  "properties": {
    "iso:country":"US",
    "sg:address":"43 Bloomfield Ave",
    "sg:city":"Newark",
    "sg:classifiers":[
        {
            "category":"Personal",
            "subcategory":"Beauty Salon",
            "type":"Services"
        }
    ],
    "sg:phone":"+1 973 483 9428",
    "sg:postcode":"07104",
    "sg:province":"NJ",
    "sg:tags":[
        "shop"
    ],
    "wof:name":"Las Americas Unisex",
    "wof:placetype":"venue"
},
  "geometry": {"coordinates":[-74.17183799999999,40.75461],"type":"Point"}
}