{
  "type": "Feature",
  "properties": {
    "iso:country":"US",
    "sg:address":"1 Abbey Rd",
    "sg:city":"Jackson",
    "sg:classifiers":[
        {
            "category":"Professional",
            "subcategory":"Business Services",
            "type":"Services"
        }
    ],
    "sg:phone":"+1   ",
    "sg:postcode":"08527",
    "sg:province":"NJ",
    "wof:name":"Effective Business Solutions",
    "wof:placetype":"venue"
},
  "geometry": {"coordinates":[-74.40839200000001,40.153514],"type":"Point"}
}