{
  "type": "Feature",
  "properties": {
    "addr:full":"105 Hurffville Crosskeys Rd Sewell NJ 08080",
    "addr:housenumber":"105",
    "addr:postcode":"08080",
    "addr:street":"Hurffville Crosskeys Rd",
    "iso:country":"US",
    "sg:address":"105 Hurffville Crosskeys Rd",
    "sg:city":"Sewell",
    "sg:classifiers":[
        {
            "category":"Health Services",
            "subcategory":"Doctor",
            "type":"Services"
        }
    ],
    "sg:phone":"+1 856 848 4998",
    "sg:postcode":"08080",
    "sg:province":"NJ",
    "sg:tags":[
        "physician",
        "surgeon"
    ],
    "wof:name":"Booth Radiology Assoc",
    "wof:placetype":"venue"
},
  "geometry": {"coordinates":[-75.044049,39.721343],"type":"Point"}
}