{
  "type": "Feature",
  "properties": {
    "iso:country":"US",
    "sg:address":"196 Lakeview Ave",
    "sg:city":"Clifton",
    "sg:classifiers":[
        {
            "category":"Personal",
            "subcategory":"Beauty Salon",
            "type":"Services"
        }
    ],
    "sg:phone":"+1 973 279 5687",
    "sg:postcode":"07011",
    "sg:province":"NJ",
    "sg:tags":[
        "shop"
    ],
    "wof:name":"Marcels Prof Unisex Hair",
    "wof:placetype":"venue"
},
  "geometry": {"coordinates":[-74.13740900000001,40.881415],"type":"Point"}
}