{
  "type": "Feature",
  "properties": {
    "iso:country":"US",
    "sg:address":"545 Howard Blvd",
    "sg:city":"Lake Hopatcong",
    "sg:classifiers":[
        {
            "category":"Recreation",
            "subcategory":"Marina",
            "type":"Entertainment"
        }
    ],
    "sg:phone":"+1 973 663 1668",
    "sg:postcode":"07849",
    "sg:province":"NJ",
    "sg:tags":[
        "repairing",
        "boat"
    ],
    "sg:website":"www.sanbarmarina.com",
    "wof:name":"Lake Hopatcong Marine Corp",
    "wof:placetype":"venue"
},
  "geometry": {"coordinates":[-74.619877,40.942966],"type":"Point"}
}