{
  "type": "Feature",
  "properties": {
    "addr:full":"83 S Main St Milltown NJ 08850",
    "addr:housenumber":"83",
    "addr:postcode":"08850",
    "addr:street":"S Main St",
    "iso:country":"US",
    "sg:address":"83 S Main St",
    "sg:city":"Milltown",
    "sg:classifiers":[
        {
            "category":"Personal",
            "subcategory":"Beauty Salon",
            "type":"Services"
        }
    ],
    "sg:phone":"+1 732 545 1069",
    "sg:postcode":"08850",
    "sg:province":"NJ",
    "wof:name":"Gustavos Hair Salon",
    "wof:placetype":"venue"
},
  "geometry": {"coordinates":[-74.434141,40.448498],"type":"Point"}
}