{
  "type": "Feature",
  "properties": {
    "addr:full":"1070 Clinton Ave Irvington NJ 07111",
    "addr:housenumber":"1070",
    "addr:postcode":"07111",
    "addr:street":"Clinton Ave",
    "iso:country":"US",
    "sg:address":"1070 Clinton Ave",
    "sg:city":"Irvington",
    "sg:classifiers":[
        {
            "category":"Insurance",
            "subcategory":"Insurance Agent",
            "type":"Services"
        }
    ],
    "sg:phone":"+1   ",
    "sg:postcode":"07111",
    "sg:province":"NJ",
    "wof:name":"Eisenberg-Gollin Insur Agcy",
    "wof:placetype":"venue"
},
  "geometry": {"coordinates":[-74.22666599999999,40.725665],"type":"Point"}
}