{
  "type": "Feature",
  "properties": {
    "addr:full":"630 Springfield Ave Berkeley Heights NJ 07922",
    "addr:housenumber":"630",
    "addr:postcode":"07922",
    "addr:street":"Springfield Ave",
    "iso:country":"US",
    "sg:address":"630 Springfield Ave",
    "sg:city":"Berkeley Heights",
    "sg:classifiers":[
        {
            "category":"Banks & Credit Unions",
            "subcategory":"Investment Brokerage",
            "type":"Services"
        }
    ],
    "sg:phone":"+1 908 286 1902",
    "sg:postcode":"07922",
    "sg:province":"NJ",
    "sg:tags":[
        "investing"
    ],
    "wof:name":"Strategic Investment Advisors Llc",
    "wof:placetype":"venue"
},
  "geometry": {"coordinates":[-74.447068,40.681494],"type":"Point"}
}