{
  "type": "Feature",
  "properties": {
    "addr:full":"1818 Mount Ephraim Ave Camden NJ 08104",
    "addr:housenumber":"1818",
    "addr:postcode":"08104",
    "addr:street":"Mount Ephraim Ave",
    "iso:country":"US",
    "sg:address":"1818 Mount Ephraim Ave",
    "sg:city":"Camden",
    "sg:classifiers":[
        {
            "category":"Shopping",
            "subcategory":"Department Store",
            "type":"Retail Goods"
        }
    ],
    "sg:phone":"+1   ",
    "sg:postcode":"08104",
    "sg:province":"NJ",
    "wof:name":"Kmart",
    "wof:placetype":"venue"
},
  "geometry": {"coordinates":[-75.103965,39.922143],"type":"Point"}
}