{
  "type": "Feature",
  "properties": {
    "iso:country":"US",
    "sg:address":"18 Morris Ave",
    "sg:city":"Springfield",
    "sg:classifiers":[
        {
            "category":"Health Services",
            "subcategory":"Doctor",
            "type":"Services"
        }
    ],
    "sg:phone":"+1 973 376 2900",
    "sg:postcode":"07081",
    "sg:province":"NJ",
    "wof:name":"Lang Bridget A DMD",
    "wof:placetype":"venue"
},
  "geometry": {"coordinates":[-74.326742,40.717527],"type":"Point"}
}