{
  "type": "Feature",
  "properties": {
    "addr:full":"386 Walnut St Englewood NJ 07631",
    "addr:housenumber":"386",
    "addr:postcode":"07631",
    "addr:street":"Walnut St",
    "iso:country":"US",
    "sg:address":"386 Walnut St",
    "sg:city":"Englewood",
    "sg:classifiers":[
        {
            "category":"Health Services",
            "subcategory":"Doctor",
            "type":"Services"
        }
    ],
    "sg:phone":"+1 201 568 1234",
    "sg:postcode":"07631",
    "sg:province":"NJ",
    "sg:tags":[
        "physician",
        "medical",
        "surgeon"
    ],
    "wof:name":"Henry Haberfield MD",
    "wof:placetype":"venue"
},
  "geometry": {"coordinates":[-73.959755,40.890109],"type":"Point"}
}