{
  "type": "Feature",
  "properties": {
    "iso:country":"US",
    "sg:address":"65 Hamilton St",
    "sg:city":"Paterson",
    "sg:classifiers":[
        {
            "category":"Social Services",
            "type":"Services"
        }
    ],
    "sg:phone":"+1 973 881 4700",
    "sg:postcode":"07505",
    "sg:province":"NJ",
    "sg:tags":[
        "probation"
    ],
    "wof:name":"Passaci County Probation",
    "wof:placetype":"venue"
},
  "geometry": {"coordinates":[-74.17192900000001,40.914379],"type":"Point"}
}