{
  "type": "Feature",
  "properties": {
    "addr:full":"343 Snyder Ave Berkeley Heights NJ 07922",
    "addr:housenumber":"343",
    "addr:postcode":"07922",
    "addr:street":"Snyder Ave",
    "iso:country":"US",
    "sg:address":"343 Snyder Ave",
    "sg:city":"Berkeley Heights",
    "sg:classifiers":[
        {
            "category":"Professional",
            "subcategory":"Business Services",
            "type":"Services"
        }
    ],
    "sg:phone":"+1 908 286 1000",
    "sg:postcode":"07922",
    "sg:province":"NJ",
    "sg:tags":[
        "interior",
        "consultant",
        "design",
        "decorator"
    ],
    "wof:name":"Brass Gift & Home Decor",
    "wof:placetype":"venue"
},
  "geometry": {"coordinates":[-74.431167,40.681335],"type":"Point"}
}