{
  "type": "Feature",
  "properties": {
    "addr:full":"667 Lake Shore Dr Parsippany NJ 07054",
    "addr:housenumber":"667",
    "addr:postcode":"07054",
    "addr:street":"Lake Shore Dr",
    "iso:country":"US",
    "sg:address":"667 Lake Shore Dr",
    "sg:city":"Parsippany",
    "sg:classifiers":[
        {
            "category":"Retail",
            "subcategory":"Repair Shop",
            "type":"Services"
        }
    ],
    "sg:phone":"+1 973 887 1847",
    "sg:postcode":"07054",
    "sg:province":"NJ",
    "sg:tags":[
        "repairing",
        "lawn",
        "mower"
    ],
    "wof:name":"Charlie's Lawn Mower Repair",
    "wof:placetype":"venue"
},
  "geometry": {"coordinates":[-74.43827,40.847521],"type":"Point"}
}