{
  "type": "Feature",
  "properties": {
    "addr:full":"250 Essex St Hackensack NJ 07601",
    "addr:housenumber":"250",
    "addr:postcode":"07601",
    "addr:street":"Essex St",
    "iso:country":"US",
    "sg:address":"250 Essex St",
    "sg:city":"Hackensack",
    "sg:classifiers":[
        {
            "category":"Restaurant",
            "type":"Food & Drink"
        }
    ],
    "sg:phone":"+1 201 342 2275",
    "sg:postcode":"07601",
    "sg:province":"NJ",
    "sg:tags":[
        "bakery"
    ],
    "wof:name":"Arena Diner Restaurant",
    "wof:placetype":"venue"
},
  "geometry": {"coordinates":[-74.054703,40.881401],"type":"Point"}
}