{
  "type": "Feature",
  "properties": {
    "iso:country":"US",
    "sg:address":"175 US Hwy 1",
    "sg:city":"Metuchen",
    "sg:classifiers":[
        {
            "category":"Home & Garden",
            "subcategory":"Furniture",
            "type":"Retail Goods"
        }
    ],
    "sg:phone":"+1   ",
    "sg:postcode":"08840",
    "sg:province":"NJ",
    "wof:name":"Sleepys Mattress Professionals",
    "wof:placetype":"venue"
},
  "geometry": {"coordinates":[-74.325913,40.547751],"type":"Point"}
}