{
  "type": "Feature",
  "properties": {
    "iso:country":"US",
    "sg:address":"16 Alexandra Ct",
    "sg:city":"Tuckerton",
    "sg:classifiers":[
        {
            "category":"Shopping",
            "subcategory":"Discount & Variety Stores",
            "type":"Retail Goods"
        }
    ],
    "sg:phone":"+1 609 294 0438",
    "sg:postcode":"08053",
    "sg:province":"NJ",
    "sg:tags":[
        "merchandise",
        "general"
    ],
    "wof:name":"Sunrise Bay Sales Ctr",
    "wof:placetype":"venue"
},
  "geometry": {"coordinates":[-74.863193,39.87781],"type":"Point"}
}