{
  "type": "Feature",
  "properties": {
    "iso:country":"US",
    "sg:address":"2700 Atlantic Ave",
    "sg:city":"Wildwood",
    "sg:classifiers":[
        {
            "category":"Food & Beverages",
            "subcategory":"Groceries & Convenience Stores",
            "type":"Retail Goods"
        }
    ],
    "sg:phone":"+1 609 522 0141",
    "sg:postcode":"08260",
    "sg:province":"NJ",
    "wof:name":"Pops Deli",
    "wof:placetype":"venue"
},
  "geometry": {"coordinates":[-74.80753900000001,38.992018],"type":"Point"}
}