{
  "type": "Feature",
  "properties": {
    "iso:country":"US",
    "sg:address":"1617 Beaver Dam Rd",
    "sg:city":"Pt Pleasant Bch",
    "sg:classifiers":[
        {
            "category":"Professional",
            "subcategory":"Management & Consulting",
            "type":"Services"
        },
        {
            "category":"Education",
            "subcategory":"Special Training",
            "type":"Public Place"
        }
    ],
    "sg:phone":"+1 732 295 7323",
    "sg:postcode":"08742",
    "sg:province":"NJ",
    "sg:tags":[
        "consultant",
        "educational"
    ],
    "wof:name":"First Literacy Resource",
    "wof:placetype":"venue"
},
  "geometry": {"coordinates":[-74.072429,40.066082],"type":"Point"}
}