{
  "type": "Feature",
  "properties": {
    "iso:country":"US",
    "sg:address":"781 Chase Ave",
    "sg:city":"Lyndhurst",
    "sg:classifiers":[
        {
            "category":"Building & Trades",
            "subcategory":"Plumbing",
            "type":"Services"
        }
    ],
    "sg:phone":"+1 201 438 9277",
    "sg:postcode":"07071",
    "sg:province":"NJ",
    "sg:tags":[
        "air",
        "heating",
        "conditioning",
        "contractor"
    ],
    "wof:name":"Rite Temp AC & Htg",
    "wof:placetype":"venue"
},
  "geometry": {"coordinates":[-74.130235,40.801808],"type":"Point"}
}