{
  "type": "Feature",
  "properties": {
    "addr:full":"225 May St Edison NJ 08837",
    "addr:housenumber":"225",
    "addr:postcode":"08837",
    "addr:street":"May St",
    "iso:country":"US",
    "sg:address":"225 May St",
    "sg:city":"Edison",
    "sg:classifiers":[
        {
            "category":"Health Services",
            "subcategory":"Doctor",
            "type":"Services"
        }
    ],
    "sg:phone":"+1 732 738 4337",
    "sg:postcode":"08837",
    "sg:province":"NJ",
    "sg:tags":[
        "physician",
        "surgeon"
    ],
    "wof:name":"Abraham Meltzer MD",
    "wof:placetype":"venue"
},
  "geometry": {"coordinates":[-74.32064,40.526225],"type":"Point"}
}