{
  "type": "Feature",
  "properties": {
    "iso:country":"US",
    "sg:address":"1374 Stuyvesant Ave",
    "sg:city":"Union",
    "sg:classifiers":[
        {
            "category":"Retail",
            "subcategory":"Auto Repair",
            "type":"Services"
        }
    ],
    "sg:phone":"+1   ",
    "sg:postcode":"07083",
    "sg:province":"NJ",
    "sg:tags":[
        "automotive",
        "supply"
    ],
    "wof:name":"Vitos Auto Electric",
    "wof:placetype":"venue"
},
  "geometry": {"coordinates":[-74.26314600000001,40.703044],"type":"Point"}
}