{
  "type": "Feature",
  "properties": {
    "iso:country":"US",
    "sg:address":"214 W State St",
    "sg:city":"Trenton",
    "sg:classifiers":[
        {
            "category":"Organizations",
            "subcategory":"Professional Association",
            "type":"Services"
        }
    ],
    "sg:phone":"+1 609 392 1201",
    "sg:postcode":"08608",
    "sg:province":"NJ",
    "sg:tags":[
        "business",
        "trade"
    ],
    "wof:name":"New Jersey Academy-Opthalmolgy",
    "wof:placetype":"venue"
},
  "geometry": {"coordinates":[-74.774788,40.22235],"type":"Point"}
}