{
  "type": "Feature",
  "properties": {
    "iso:country":"US",
    "sg:address":"331 Tilton Rd",
    "sg:city":"Northfield",
    "sg:classifiers":[
        {
            "category":"Food & Beverages",
            "subcategory":"Specialty",
            "type":"Retail Goods"
        }
    ],
    "sg:phone":"+1 609 641 6524",
    "sg:postcode":"08225",
    "sg:province":"NJ",
    "sg:tags":[
        "health",
        "diet"
    ],
    "wof:name":"Honey Tree Natural Food Store",
    "wof:placetype":"venue"
},
  "geometry": {"coordinates":[-74.556411,39.38547],"type":"Point"}
}