{
  "type": "Feature",
  "properties": {
    "addr:full":"41 Liberty St Passaic NJ 07055",
    "addr:housenumber":"41",
    "addr:postcode":"07055",
    "addr:street":"Liberty St",
    "iso:country":"US",
    "sg:address":"41 Liberty St",
    "sg:city":"Passaic",
    "sg:classifiers":[
        {
            "category":"Building & Trades",
            "subcategory":"Construction",
            "type":"Services"
        }
    ],
    "sg:phone":"+1 973 472 6992",
    "sg:postcode":"07055",
    "sg:province":"NJ",
    "sg:tags":[
        "contractor"
    ],
    "wof:name":"Zdm Construction Inc",
    "wof:placetype":"venue"
},
  "geometry": {"coordinates":[-74.13870199999999,40.8568],"type":"Point"}
}