{
  "type": "Feature",
  "properties": {
    "iso:country":"US",
    "sg:address":"3498 Delaware Ct",
    "sg:city":"Merchantville",
    "sg:classifiers":[
        {
            "category":"Professional",
            "subcategory":"Business Services",
            "type":"Services"
        }
    ],
    "sg:phone":"+1   ",
    "sg:postcode":"08109",
    "sg:province":"NJ",
    "sg:tags":[
        "computer",
        "parts",
        "sales"
    ],
    "wof:name":"Memory Queen",
    "wof:placetype":"venue"
},
  "geometry": {"coordinates":[-75.023454,39.961749],"type":"Point"}
}