{
  "type": "Feature",
  "properties": {
    "addr:full":"2428 Lemoine Ave Fort Lee NJ 07024",
    "addr:housenumber":"2428",
    "addr:postcode":"07024",
    "addr:street":"Lemoine Ave",
    "iso:country":"US",
    "sg:address":"2428 Lemoine Ave",
    "sg:city":"Fort Lee",
    "sg:classifiers":[
        {
            "category":"Restaurant",
            "type":"Food & Drink"
        }
    ],
    "sg:phone":"+1 201 947 4780",
    "sg:postcode":"07024",
    "sg:province":"NJ",
    "sg:tags":[
        "mexican"
    ],
    "sg:website":"www.cincodemayoonline.com/",
    "wof:name":"Cinco De Mayo Mexican Grill & Deli",
    "wof:placetype":"venue"
},
  "geometry": {"coordinates":[-73.962086,40.863985],"type":"Point"}
}