{
  "type": "Feature",
  "properties": {
    "addr:full":"427 Colorado Trl Browns Mills NJ 08015",
    "addr:housenumber":"427",
    "addr:postcode":"08015",
    "addr:street":"Colorado Trl",
    "iso:country":"US",
    "sg:address":"427 Colorado Trl",
    "sg:city":"Browns Mills",
    "sg:classifiers":[
        {
            "category":"Arts & Performance",
            "subcategory":"Theater",
            "type":"Entertainment"
        }
    ],
    "sg:phone":"+1   ",
    "sg:postcode":"08015",
    "sg:province":"NJ",
    "sg:tags":[
        "group"
    ],
    "wof:name":"Clown A Round",
    "wof:placetype":"venue"
},
  "geometry": {"coordinates":[-74.56364499999999,39.9177],"type":"Point"}
}