{
  "type": "Feature",
  "properties": {
    "iso:country":"US",
    "sg:address":"275 Main St",
    "sg:city":"Lodi",
    "sg:classifiers":[
        {
            "category":"Food & Beverages",
            "subcategory":"Bakery",
            "type":"Retail Goods"
        }
    ],
    "sg:phone":"+1   ",
    "sg:postcode":"07644",
    "sg:province":"NJ",
    "sg:tags":[
        "real",
        "property",
        "lessor"
    ],
    "wof:name":"Shivani Estate LLC",
    "wof:placetype":"venue"
},
  "geometry": {"coordinates":[-74.083534,40.882391],"type":"Point"}
}