{
  "type": "Feature",
  "properties": {
    "iso:country":"US",
    "sg:address":"21 Buttonwood Ln",
    "sg:city":"Freehold",
    "sg:classifiers":[
        {
            "category":"Professional",
            "subcategory":"Business Services",
            "type":"Services"
        }
    ],
    "sg:phone":"+1   ",
    "sg:postcode":"07728",
    "sg:province":"NJ",
    "wof:name":"Chatrath Design Associates",
    "wof:placetype":"venue"
},
  "geometry": {"coordinates":[-74.304919,40.23617],"type":"Point"}
}