{
  "type": "Feature",
  "properties": {
    "addr:full":"633 Division St Elizabeth NJ 07201",
    "addr:housenumber":"633",
    "addr:postcode":"07201",
    "addr:street":"Division St",
    "iso:country":"US",
    "sg:address":"633 Division St",
    "sg:city":"Elizabeth",
    "sg:classifiers":[
        {
            "category":"Freight",
            "type":"Transportation"
        }
    ],
    "sg:phone":"+1 908 351 8801",
    "sg:postcode":"07201",
    "sg:province":"NJ",
    "wof:name":"Caseth Logistics Inc",
    "wof:placetype":"venue"
},
  "geometry": {"coordinates":[-74.19105399999999,40.674558],"type":"Point"}
}