{
  "type": "Feature",
  "properties": {
    "iso:country":"US",
    "sg:address":"6 Blue Star Dr",
    "sg:city":"Gillette",
    "sg:classifiers":[
        {
            "category":"Professional",
            "subcategory":"Management & Consulting",
            "type":"Services"
        }
    ],
    "sg:phone":"+1   ",
    "sg:postcode":"07933",
    "sg:province":"NJ",
    "sg:tags":[
        "business"
    ],
    "wof:name":"Stgi Inc",
    "wof:placetype":"venue"
},
  "geometry": {"coordinates":[-74.47577800000001,40.685255],"type":"Point"}
}