{
  "type": "Feature",
  "properties": {
    "addr:full":"543 Valley Rd Montclair NJ 07043",
    "addr:housenumber":"543",
    "addr:postcode":"07043",
    "addr:street":"Valley Rd",
    "iso:country":"US",
    "sg:address":"543 Valley Rd",
    "sg:city":"Montclair",
    "sg:classifiers":[
        {
            "category":"Health Services",
            "subcategory":"Doctor",
            "type":"Services"
        }
    ],
    "sg:phone":"+1 973 655 0012",
    "sg:postcode":"07043",
    "sg:province":"NJ",
    "sg:tags":[
        "psychiatrist"
    ],
    "wof:name":"Weiner Alison MD PC",
    "wof:placetype":"venue"
},
  "geometry": {"coordinates":[-74.20729799999999,40.838299],"type":"Point"}
}