{
  "type": "Feature",
  "properties": {
    "iso:country":"US",
    "sg:address":"2999 E Evesham Rd",
    "sg:city":"Voorhees",
    "sg:classifiers":[
        {
            "category":"Personal",
            "subcategory":"Beauty Salon",
            "type":"Services"
        }
    ],
    "sg:phone":"+1   ",
    "sg:postcode":"08043",
    "sg:province":"NJ",
    "sg:tags":[
        "shop",
        "merchandise"
    ],
    "wof:name":"Estectica By Dominic",
    "wof:placetype":"venue"
},
  "geometry": {"coordinates":[-74.937128,39.871001],"type":"Point"}
}