{
  "type": "Feature",
  "properties": {
    "addr:full":"829 Blackwood Clementon Rd Lindenwold NJ 08021",
    "addr:housenumber":"829",
    "addr:postcode":"08021",
    "addr:street":"Blackwood Clementon Rd",
    "iso:country":"US",
    "sg:address":"829 Blackwood Clementon Rd",
    "sg:city":"Lindenwold",
    "sg:classifiers":[
        {
            "category":"Autos & Motor Vehicles",
            "subcategory":"Fuel & Gas Station",
            "type":"Retail Goods"
        }
    ],
    "sg:phone":"+1 856 783 4330",
    "sg:postcode":"08021",
    "sg:province":"NJ",
    "sg:tags":[
        "oil"
    ],
    "wof:name":"Laurel Road Mobil",
    "wof:placetype":"venue"
},
  "geometry": {"coordinates":[-75.006934,39.805155],"type":"Point"}
}