{
  "type": "Feature",
  "properties": {
    "addr:full":"122 State Rte 34 Howell NJ 07747",
    "addr:housenumber":"122",
    "addr:postcode":"07747",
    "addr:street":"State Rte 34",
    "iso:country":"US",
    "sg:address":"122 State Rte 34",
    "sg:city":"Howell",
    "sg:classifiers":[
        {
            "category":"Wholesale",
            "subcategory":"Machinery & Supplies",
            "type":"Manufacturing & Wholesale Goods"
        }
    ],
    "sg:phone":"+1 732 938 9099",
    "sg:postcode":"07747",
    "sg:province":"NJ",
    "sg:tags":[
        "contractor"
    ],
    "wof:name":"Siteco Materials Inc",
    "wof:placetype":"venue"
},
  "geometry": {"coordinates":[-74.266212,40.422627],"type":"Point"}
}