{
  "type": "Feature",
  "properties": {
    "addr:full":"15 Fernwood Rd Milford NJ 08848",
    "addr:housenumber":"15",
    "addr:postcode":"08848",
    "addr:street":"Fernwood Rd",
    "iso:country":"US",
    "sg:address":"15 Fernwood Rd",
    "sg:city":"Milford",
    "sg:classifiers":[
        {
            "category":"Recreation",
            "type":"Entertainment"
        }
    ],
    "sg:phone":"+1   ",
    "sg:postcode":"08848",
    "sg:province":"NJ",
    "sg:tags":[
        "equipment",
        "retail",
        "golf"
    ],
    "wof:name":"Michael Knight",
    "wof:placetype":"venue"
},
  "geometry": {"coordinates":[-75.117969,40.604494],"type":"Point"}
}