{
  "type": "Feature",
  "properties": {
    "iso:country":"US",
    "sg:address":"55 Union Blvd",
    "sg:city":"Totowa",
    "sg:classifiers":[
        {
            "category":"Banks & Credit Unions",
            "subcategory":"Financial Services",
            "type":"Services"
        }
    ],
    "sg:phone":"+1 973 942 1111",
    "sg:postcode":"07512",
    "sg:province":"NJ",
    "sg:tags":[
        "company",
        "holding"
    ],
    "sg:website":"www.greatercommunitybank.com",
    "wof:name":"Greater Community Bancorp",
    "wof:placetype":"venue"
},
  "geometry": {"coordinates":[-74.203248,40.90972],"type":"Point"}
}