{
  "type": "Feature",
  "properties": {
    "iso:country":"US",
    "sg:address":"2 Clubhouse Rd",
    "sg:city":"Riverdale",
    "sg:classifiers":[
        {
            "category":"Real Estate",
            "subcategory":"Real Estate Agent",
            "type":"Services"
        }
    ],
    "sg:phone":"+1 973 492 1381",
    "sg:postcode":"07480",
    "sg:province":"NJ",
    "sg:tags":[
        "management"
    ],
    "wof:name":"Rock Creek Crossing Management",
    "wof:placetype":"venue"
},
  "geometry": {"coordinates":[-74.36761199999999,41.049493],"type":"Point"}
}