{
  "type": "Feature",
  "properties": {
    "addr:full":"51 Progress St Union NJ 07083",
    "addr:housenumber":"51",
    "addr:postcode":"07083",
    "addr:street":"Progress St",
    "iso:country":"US",
    "sg:address":"51 Progress St",
    "sg:city":"Union",
    "sg:classifiers":[
        {
            "category":"Professional",
            "type":"Services"
        }
    ],
    "sg:phone":"+1 908 851 2150",
    "sg:postcode":"07083",
    "sg:province":"NJ",
    "wof:name":"Lincoln Service & Equipment Co",
    "wof:placetype":"venue"
},
  "geometry": {"coordinates":[-74.30068199999999,40.691445],"type":"Point"}
}