{
  "type": "Feature",
  "properties": {
    "addr:full":"135 N Black Horse Pike Williamstown NJ 08094",
    "addr:housenumber":"135",
    "addr:postcode":"08094",
    "addr:street":"N Black Horse Pike",
    "iso:country":"US",
    "sg:address":"135 N Black Horse Pike",
    "sg:city":"Williamstown",
    "sg:classifiers":[
        {
            "category":"Organizations",
            "subcategory":"Professional Association",
            "type":"Services"
        }
    ],
    "sg:phone":"+1 856 629 3352",
    "sg:postcode":"08094",
    "sg:province":"NJ",
    "wof:name":"Knights Of Columbus",
    "wof:placetype":"venue"
},
  "geometry": {"coordinates":[-74.99498800000001,39.691178],"type":"Point"}
}