{
  "type": "Feature",
  "properties": {
    "addr:full":"525 Washington Blvd Fl 3300 Jersey City NJ 07310",
    "addr:housenumber":"525",
    "addr:postcode":"3300;07310",
    "addr:street":"Washington Blvd",
    "iso:country":"US",
    "sg:address":"525 Washington Blvd Fl 3300",
    "sg:city":"Jersey City",
    "sg:classifiers":[
        {
            "category":"Banks & Credit Unions",
            "subcategory":"Investment Brokerage",
            "type":"Services"
        }
    ],
    "sg:phone":"+1 201 217 3283",
    "sg:postcode":"07310",
    "sg:province":"NJ",
    "sg:tags":[
        "investing"
    ],
    "wof:name":"Axa Equitable",
    "wof:placetype":"venue"
},
  "geometry": {"coordinates":[-74.035158,40.726775],"type":"Point"}
}