{
  "type": "Feature",
  "properties": {
    "addr:full":"155 Ellison St Paterson NJ 07505",
    "addr:housenumber":"155",
    "addr:postcode":"07505",
    "addr:street":"Ellison St",
    "iso:country":"US",
    "sg:address":"155 Ellison St",
    "sg:city":"Paterson",
    "sg:classifiers":[
        {
            "category":"Social Services",
            "type":"Services"
        }
    ],
    "sg:phone":"+1   ",
    "sg:postcode":"07505",
    "sg:province":"NJ",
    "sg:tags":[
        "center"
    ],
    "wof:name":"Paterson Task Frce Cmmty Actn",
    "wof:placetype":"venue"
},
  "geometry": {"coordinates":[-74.170934,40.917375],"type":"Point"}
}