{
  "type": "Feature",
  "properties": {
    "iso:country":"US",
    "sg:address":"40 Clinton Rd",
    "sg:city":"West Caldwell",
    "sg:classifiers":[
        {
            "category":"Professional",
            "type":"Services"
        },
        {
            "category":"Restaurant",
            "type":"Food & Drink"
        }
    ],
    "sg:phone":"+1 973 228 9989",
    "sg:postcode":"07006",
    "sg:province":"NJ",
    "sg:tags":[
        "italian",
        "caterer"
    ],
    "wof:name":"Vitellas Cucina",
    "wof:placetype":"venue"
},
  "geometry": {"coordinates":[-74.29545400000001,40.85237],"type":"Point"}
}