{
  "type": "Feature",
  "properties": {
    "iso:country":"US",
    "sg:address":"34 Sunset Dr",
    "sg:city":"Clementon",
    "sg:classifiers":[
        {
            "category":"Professional",
            "subcategory":"Computer Services",
            "type":"Services"
        }
    ],
    "sg:phone":"+1 856 435 8673",
    "sg:postcode":"08021",
    "sg:province":"NJ",
    "sg:tags":[
        "processing",
        "datum"
    ],
    "wof:name":"A Tent & Associates",
    "wof:placetype":"venue"
},
  "geometry": {"coordinates":[-75.03313,39.792459],"type":"Point"}
}