{
  "type": "Feature",
  "properties": {
    "iso:country":"US",
    "sg:address":"205 Pine St",
    "sg:city":"Hackettstown",
    "sg:classifiers":[
        {
            "category":"Education",
            "subcategory":"Dance Studio",
            "type":"Public Place"
        }
    ],
    "sg:phone":"+1 908 852 7822",
    "sg:postcode":"07840",
    "sg:province":"NJ",
    "wof:name":"J&J Music & Dance",
    "wof:placetype":"venue"
},
  "geometry": {"coordinates":[-74.81491800000001,40.858999],"type":"Point"}
}