{
  "type": "Feature",
  "properties": {
    "addr:full":"116 Chestnut St Roselle NJ 07203",
    "addr:housenumber":"116",
    "addr:postcode":"07203",
    "addr:street":"Chestnut St",
    "iso:country":"US",
    "sg:address":"116 Chestnut St",
    "sg:city":"Roselle",
    "sg:classifiers":[
        {
            "category":"Professional",
            "subcategory":"Computer Services",
            "type":"Services"
        }
    ],
    "sg:phone":"+1 908 241 4996",
    "sg:postcode":"07203",
    "sg:province":"NJ",
    "sg:tags":[
        "repair"
    ],
    "wof:name":"THS Computers",
    "wof:placetype":"venue"
},
  "geometry": {"coordinates":[-74.263403,40.659027],"type":"Point"}
}