{
  "type": "Feature",
  "properties": {
    "addr:full":"130 Moonachie Ave Moonachie NJ 07074",
    "addr:housenumber":"130",
    "addr:postcode":"07074",
    "addr:street":"Moonachie Ave",
    "iso:country":"US",
    "sg:address":"130 Moonachie Ave",
    "sg:city":"Moonachie",
    "sg:classifiers":[
        {
            "category":"Freight",
            "type":"Transportation"
        }
    ],
    "sg:phone":"+1 201 935 4110",
    "sg:postcode":"07074",
    "sg:province":"NJ",
    "sg:tags":[
        "trucking"
    ],
    "sg:website":"www.hopx.com",
    "wof:name":"Howards Express Inc",
    "wof:placetype":"venue"
},
  "geometry": {"coordinates":[-74.059473,40.835618],"type":"Point"}
}