{
  "type": "Feature",
  "properties": {
    "iso:country":"US",
    "sg:address":"625 Oradell Ave",
    "sg:city":"Oradell",
    "sg:classifiers":[
        {
            "category":"Professional",
            "type":"Services"
        }
    ],
    "sg:phone":"+1   ",
    "sg:postcode":"07649",
    "sg:province":"NJ",
    "wof:name":"Audio Optics",
    "wof:placetype":"venue"
},
  "geometry": {"coordinates":[-74.030877,40.954],"type":"Point"}
}