{
  "type": "Feature",
  "properties": {
    "iso:country":"US",
    "sg:address":"35 Libra Ln",
    "sg:city":"Sewell",
    "sg:classifiers":[
        {
            "category":"Building & Trades",
            "subcategory":"Plumbing",
            "type":"Services"
        }
    ],
    "sg:phone":"+1 856 728 8803",
    "sg:postcode":"08080",
    "sg:province":"NJ",
    "sg:tags":[
        "contractor"
    ],
    "wof:name":"Daniels Heating and AC",
    "wof:placetype":"venue"
},
  "geometry": {"coordinates":[-75.06988,39.726882],"type":"Point"}
}