{
  "type": "Feature",
  "properties": {
    "addr:full":"162 Cedar Ln Teaneck NJ 07666",
    "addr:housenumber":"162",
    "addr:postcode":"07666",
    "addr:street":"Cedar Ln",
    "iso:country":"US",
    "sg:address":"162 Cedar Ln",
    "sg:city":"Teaneck",
    "sg:classifiers":[
        {
            "category":"Wholesale",
            "subcategory":"Electrical",
            "type":"Manufacturing & Wholesale Goods"
        }
    ],
    "sg:phone":"+1 201 530 1555",
    "sg:postcode":"07666",
    "sg:province":"NJ",
    "sg:tags":[
        "telecommunication"
    ],
    "wof:name":"Better Value Tlcmmnctns",
    "wof:placetype":"venue"
},
  "geometry": {"coordinates":[-74.014611,40.8865],"type":"Point"}
}