{
  "type": "Feature",
  "properties": {
    "addr:full":"600 E Clements Bridge Rd Runnemede NJ 08078",
    "addr:housenumber":"600",
    "addr:postcode":"08078",
    "addr:street":"E Clements Bridge Rd",
    "iso:country":"US",
    "sg:address":"600 E Clements Bridge Rd",
    "sg:city":"Runnemede",
    "sg:classifiers":[
        {
            "category":"Manufacturing",
            "subcategory":"Apparel",
            "type":"Manufacturing & Wholesale Goods"
        }
    ],
    "sg:phone":"+1 856 939 9599",
    "sg:postcode":"08078",
    "sg:province":"NJ",
    "sg:tags":[
        "hat"
    ],
    "wof:name":"Rasta Imposta Hats",
    "wof:placetype":"venue"
},
  "geometry": {"coordinates":[-75.06546899999999,39.854335],"type":"Point"}
}