{
  "type": "Feature",
  "properties": {
    "addr:full":"20 Heritage Dr Howell NJ 07731",
    "addr:housenumber":"20",
    "addr:postcode":"07731",
    "addr:street":"Heritage Dr",
    "iso:country":"US",
    "sg:address":"20 Heritage Dr",
    "sg:city":"Howell",
    "sg:classifiers":[
        {
            "category":"Professional",
            "subcategory":"Business Services",
            "type":"Services"
        },
        {
            "category":"Professional",
            "subcategory":"Advertising",
            "type":"Services"
        }
    ],
    "sg:phone":"+1 732 367 6145",
    "sg:postcode":"07731",
    "sg:province":"NJ",
    "sg:tags":[
        "mailing",
        "shipping"
    ],
    "wof:name":"S C Shipping Consultants",
    "wof:placetype":"venue"
},
  "geometry": {"coordinates":[-74.236214,40.140019],"type":"Point"}
}