{
  "type": "Feature",
  "properties": {
    "iso:country":"US",
    "sg:address":"PO Box 129",
    "sg:city":"Hackensack",
    "sg:classifiers":[
        {
            "category":"Real Estate",
            "subcategory":"Real Estate Operator",
            "type":"Services"
        }
    ],
    "sg:phone":"+1 908 359 3606",
    "sg:postcode":"07602",
    "sg:province":"NJ",
    "sg:tags":[
        "apartment"
    ],
    "wof:name":"Claremont Towers Apartments",
    "wof:placetype":"venue"
},
  "geometry": {"coordinates":[-74.044701,40.8839],"type":"Point"}
}