{
  "type": "Feature",
  "properties": {
    "addr:full":"113 Essex Ave Bloomfield NJ 07003",
    "addr:housenumber":"113",
    "addr:postcode":"07003",
    "addr:street":"Essex Ave",
    "iso:country":"US",
    "sg:address":"113 Essex Ave",
    "sg:city":"Bloomfield",
    "sg:classifiers":[
        {
            "category":"Building & Trades",
            "subcategory":"Construction",
            "type":"Services"
        }
    ],
    "sg:phone":"+1 973 748 0362",
    "sg:postcode":"07003",
    "sg:province":"NJ",
    "sg:tags":[
        "repairing",
        "remodeling",
        "contractor"
    ],
    "wof:name":"Michael Wujek",
    "wof:placetype":"venue"
},
  "geometry": {"coordinates":[-74.196011,40.809861],"type":"Point"}
}