{
  "type": "Feature",
  "properties": {
    "addr:full":"312 Haledon Ave Haledon NJ 07508",
    "addr:housenumber":"312",
    "addr:postcode":"07508",
    "addr:street":"Haledon Ave",
    "iso:country":"US",
    "sg:address":"312 Haledon Ave",
    "sg:city":"Haledon",
    "sg:classifiers":[
        {
            "category":"Personal",
            "subcategory":"Beauty Salon",
            "type":"Services"
        }
    ],
    "sg:phone":"+1 973 942 1966",
    "sg:postcode":"07508",
    "sg:province":"NJ",
    "sg:tags":[
        "shop"
    ],
    "wof:name":"Final Touch By Nina",
    "wof:placetype":"venue"
},
  "geometry": {"coordinates":[-74.17885099999999,40.935195],"type":"Point"}
}