{
  "type": "Feature",
  "properties": {
    "iso:country":"US",
    "sg:address":"268 Main St",
    "sg:city":"South Amboy",
    "sg:classifiers":[
        {
            "category":"Organizations",
            "subcategory":"Community Association",
            "type":"Services"
        }
    ],
    "sg:phone":"+1 732 721 0806",
    "sg:postcode":"08879",
    "sg:province":"NJ",
    "sg:tags":[
        "fraternal"
    ],
    "wof:name":"Masonic Lodge",
    "wof:placetype":"venue"
},
  "geometry": {"coordinates":[-74.285753,40.484354],"type":"Point"}
}