{
  "type": "Feature",
  "properties": {
    "addr:full":"1571 Imperial Way Paulsboro NJ 08066",
    "addr:housenumber":"1571",
    "addr:postcode":"08066",
    "addr:street":"Imperial Way",
    "iso:country":"US",
    "sg:address":"1571 Imperial Way",
    "sg:city":"Paulsboro",
    "sg:classifiers":[
        {
            "category":"Building & Trades",
            "subcategory":"Electrical",
            "type":"Services"
        }
    ],
    "sg:phone":"+1 856 848 7666",
    "sg:postcode":"08066",
    "sg:province":"NJ",
    "sg:tags":[
        "electrical",
        "contractor"
    ],
    "wof:name":"3M Co/Electrical Products Div",
    "wof:placetype":"venue"
},
  "geometry": {"coordinates":[-75.20287399999999,39.830186],"type":"Point"}
}