{
  "type": "Feature",
  "properties": {
    "addr:full":"890 Broadway Bayonne NJ 07002",
    "addr:housenumber":"890",
    "addr:postcode":"07002",
    "addr:street":"Broadway",
    "iso:country":"US",
    "sg:address":"890 Broadway",
    "sg:city":"Bayonne",
    "sg:classifiers":[
        {
            "category":"Shopping",
            "subcategory":"Bicycles & Sporting Goods",
            "type":"Retail Goods"
        }
    ],
    "sg:phone":"+1   ",
    "sg:postcode":"07002",
    "sg:province":"NJ",
    "sg:tags":[
        "repair"
    ],
    "wof:name":"Argies Bicycle Shop",
    "wof:placetype":"venue"
},
  "geometry": {"coordinates":[-74.106649,40.67742],"type":"Point"}
}