{
  "type": "Feature",
  "properties": {
    "iso:country":"US",
    "sg:address":"3 New Bridge Rd",
    "sg:city":"River Edge",
    "sg:classifiers":[
        {
            "category":"Recreation",
            "type":"Entertainment"
        }
    ],
    "sg:phone":"+1 201 525 1888",
    "sg:postcode":"07661",
    "sg:province":"NJ",
    "sg:tags":[
        "club",
        "baseball"
    ],
    "wof:name":"Bergen Batting Center",
    "wof:placetype":"venue"
},
  "geometry": {"coordinates":[-74.03112400000001,40.914854],"type":"Point"}
}