{
  "type": "Feature",
  "properties": {
    "addr:full":"475 Valley Rd Wayne NJ 07470",
    "addr:housenumber":"475",
    "addr:postcode":"07470",
    "addr:street":"Valley Rd",
    "iso:country":"US",
    "sg:address":"475 Valley Rd",
    "sg:city":"Wayne",
    "sg:classifiers":[
        {
            "category":"Professional",
            "subcategory":"Business Services",
            "type":"Services"
        }
    ],
    "sg:phone":"+1   ",
    "sg:postcode":"07470",
    "sg:province":"NJ",
    "sg:tags":[
        "building",
        "inspector"
    ],
    "wof:name":"Wayne Building Inspector",
    "wof:placetype":"venue"
},
  "geometry": {"coordinates":[-74.23040899999999,40.928037],"type":"Point"}
}