{
  "type": "Feature",
  "properties": {
    "iso:country":"US",
    "sg:address":"8 Kastor Ln",
    "sg:city":"West Long Branch",
    "sg:classifiers":[
        {
            "category":"Travel",
            "subcategory":"Travel Agent",
            "type":"Entertainment"
        }
    ],
    "sg:phone":"+1 732 870 2591",
    "sg:postcode":"07764",
    "sg:province":"NJ",
    "sg:tags":[
        "agency"
    ],
    "wof:name":"Empress Travel",
    "wof:placetype":"venue"
},
  "geometry": {"coordinates":[-74.02728999999999,40.282779],"type":"Point"}
}