{
  "type": "Feature",
  "properties": {
    "addr:full":"426 Hudson St Ste 2 Hackensack NJ 07601",
    "addr:housenumber":"426",
    "addr:postcode":"07601",
    "addr:street":"Hudson St Ste 2",
    "iso:country":"US",
    "sg:address":"426 Hudson St Ste 2",
    "sg:city":"Hackensack",
    "sg:classifiers":[
        {
            "category":"Shopping",
            "subcategory":"Jewelry",
            "type":"Retail Goods"
        }
    ],
    "sg:phone":"+1 201 373 1222",
    "sg:postcode":"07601",
    "sg:province":"NJ",
    "sg:website":"www.elimsoft.com",
    "wof:name":"Elimsoft Corp",
    "wof:placetype":"venue"
},
  "geometry": {"coordinates":[-74.03890199999999,40.865002],"type":"Point"}
}