{
  "type": "Feature",
  "properties": {
    "addr:full":"76 Knollwood Ter Clifton NJ 07012",
    "addr:housenumber":"76",
    "addr:postcode":"07012",
    "addr:street":"Knollwood Ter",
    "iso:country":"US",
    "sg:address":"76 Knollwood Ter",
    "sg:city":"Clifton",
    "sg:classifiers":[
        {
            "category":"Building & Trades",
            "subcategory":"Electrical",
            "type":"Services"
        }
    ],
    "sg:phone":"+1 973 470 8104",
    "sg:postcode":"07012",
    "sg:province":"NJ",
    "sg:tags":[
        "installation"
    ],
    "wof:name":"Alarmtronix Inc",
    "wof:placetype":"venue"
},
  "geometry": {"coordinates":[-74.16595599999999,40.839925],"type":"Point"}
}