{
  "type": "Feature",
  "properties": {
    "iso:country":"US",
    "sg:address":"6 E Main St",
    "sg:city":"Ramsey",
    "sg:classifiers":[
        {
            "category":"Banks & Credit Unions",
            "subcategory":"Investment Brokerage",
            "type":"Services"
        }
    ],
    "sg:phone":"+1 201 760 1068",
    "sg:postcode":"07446",
    "sg:province":"NJ",
    "sg:tags":[
        "advisory",
        "financial"
    ],
    "wof:name":"Sound Financial Advice LLC",
    "wof:placetype":"venue"
},
  "geometry": {"coordinates":[-74.14164599999999,41.057258],"type":"Point"}
}