{
  "type": "Feature",
  "properties": {
    "iso:country":"US",
    "sg:address":"302 South Ave",
    "sg:city":"Garwood",
    "sg:classifiers":[
        {
            "category":"Food & Beverages",
            "subcategory":"Liquor & Beverages",
            "type":"Retail Goods"
        }
    ],
    "sg:phone":"+1 908 789 1244",
    "sg:postcode":"07027",
    "sg:province":"NJ",
    "wof:name":"Little Joe's",
    "wof:placetype":"venue"
},
  "geometry": {"coordinates":[-74.32487399999999,40.651463],"type":"Point"}
}