{
  "type": "Feature",
  "properties": {
    "iso:country":"US",
    "sg:address":"777 State Rte 17",
    "sg:city":"Paramus",
    "sg:classifiers":[
        {
            "category":"Home & Garden",
            "subcategory":"Home Furnishings",
            "type":"Retail Goods"
        }
    ],
    "sg:phone":"+1   ",
    "sg:postcode":"07652",
    "sg:province":"NJ",
    "wof:name":"Blinds To Go Inc",
    "wof:placetype":"venue"
},
  "geometry": {"coordinates":[-74.081182,40.974143],"type":"Point"}
}