{
  "type": "Feature",
  "properties": {
    "addr:full":"507 E 9th St Ocean City NJ 08226",
    "addr:housenumber":"507",
    "addr:postcode":"08226",
    "addr:street":"E 9Th St",
    "iso:country":"US",
    "sg:address":"507 E 9th St",
    "sg:city":"Ocean City",
    "sg:classifiers":[
        {
            "category":"Personal",
            "subcategory":"Beauty Salon",
            "type":"Services"
        }
    ],
    "sg:phone":"+1 609 525 9900",
    "sg:postcode":"08226",
    "sg:province":"NJ",
    "wof:name":"James Lindsy Salon & Color",
    "wof:placetype":"venue"
},
  "geometry": {"coordinates":[-74.575442,39.278323],"type":"Point"}
}