{
  "type": "Feature",
  "properties": {
    "addr:full":"6603 Bergenline Pl West New York NJ 07093",
    "addr:housenumber":"6603",
    "addr:postcode":"07093",
    "addr:street":"Bergenline Pl West",
    "iso:country":"US",
    "sg:address":"6603 Bergenline Pl",
    "sg:city":"West New York",
    "sg:classifiers":[
        {
            "category":"Utilities",
            "subcategory":"Telephone",
            "type":"Services"
        }
    ],
    "sg:phone":"+1 201 271 1107",
    "sg:postcode":"07093",
    "sg:province":"NJ",
    "sg:tags":[
        "communications"
    ],
    "wof:name":"Communications Data & Internet",
    "wof:placetype":"venue"
},
  "geometry": {"coordinates":[-74.012867,40.793586],"type":"Point"}
}