{
  "type": "Feature",
  "properties": {
    "iso:country":"US",
    "sg:address":"110 Baldwin Ave",
    "sg:city":"Jersey City",
    "sg:classifiers":[
        {
            "category":"Food & Beverages",
            "subcategory":"Groceries & Convenience Stores",
            "type":"Retail Goods"
        }
    ],
    "sg:phone":"+1 201 451 0206",
    "sg:postcode":"07306",
    "sg:province":"NJ",
    "wof:name":"Bolden Fruit & Grocery",
    "wof:placetype":"venue"
},
  "geometry": {"coordinates":[-74.066498,40.7318],"type":"Point"}
}