{
  "type": "Feature",
  "properties": {
    "iso:country":"US",
    "sg:address":"270 State Rt 23 Ste C",
    "sg:city":"Franklin",
    "sg:classifiers":[
        {
            "category":"Shopping",
            "subcategory":"Pets & Pet Supplies",
            "type":"Retail Goods"
        }
    ],
    "sg:phone":"+1 973 209 3469",
    "sg:postcode":"07416",
    "sg:province":"NJ",
    "sg:tags":[
        "furnishing",
        "dog",
        "store",
        "cat"
    ],
    "wof:name":"Route 23 Pet Center",
    "wof:placetype":"venue"
},
  "geometry": {"coordinates":[-74.580552,41.112859],"type":"Point"}
}