{
  "type": "Feature",
  "properties": {
    "addr:full":"766 Shrewsbury Ave Eatontown NJ 07724",
    "addr:housenumber":"766",
    "addr:postcode":"07724",
    "addr:street":"Shrewsbury Ave",
    "iso:country":"US",
    "sg:address":"766 Shrewsbury Ave",
    "sg:city":"Eatontown",
    "sg:classifiers":[
        {
            "category":"Government",
            "subcategory":"Court House",
            "type":"Public Place"
        }
    ],
    "sg:phone":"+1   ",
    "sg:postcode":"07724",
    "sg:province":"NJ",
    "sg:tags":[
        "legal"
    ],
    "wof:name":"Hopkins Elizabeth A",
    "wof:placetype":"venue"
},
  "geometry": {"coordinates":[-74.07257799999999,40.320077],"type":"Point"}
}