{
  "type": "Feature",
  "properties": {
    "addr:full":"13 W Grand Ave Montvale NJ 07645",
    "addr:housenumber":"13",
    "addr:postcode":"07645",
    "addr:street":"W Grand Ave",
    "iso:country":"US",
    "sg:address":"13 W Grand Ave",
    "sg:city":"Montvale",
    "sg:classifiers":[
        {
            "category":"Shopping",
            "subcategory":"Florist",
            "type":"Retail Goods"
        }
    ],
    "sg:phone":"+1 201 505 1500",
    "sg:postcode":"07645",
    "sg:province":"NJ",
    "wof:name":"A New Leaf Floral Co",
    "wof:placetype":"venue"
},
  "geometry": {"coordinates":[-74.029916,41.040197],"type":"Point"}
}