{
  "type": "Feature",
  "properties": {
    "iso:country":"US",
    "sg:address":"146 Lakeview Dr S",
    "sg:city":"Gibbsboro",
    "sg:classifiers":[
        {
            "category":"Arts & Performance",
            "subcategory":"Theater",
            "type":"Entertainment"
        }
    ],
    "sg:phone":"+1 856 218 0001",
    "sg:postcode":"08026",
    "sg:province":"NJ",
    "sg:tags":[
        "musician"
    ],
    "wof:name":"Anderson Entertainment Mgmt",
    "wof:placetype":"venue"
},
  "geometry": {"coordinates":[-74.958231,39.834563],"type":"Point"}
}