{
  "type": "Feature",
  "properties": {
    "addr:full":"30 Northfield Ave Edison NJ 08837",
    "addr:housenumber":"30",
    "addr:postcode":"08837",
    "addr:street":"Northfield Ave",
    "iso:country":"US",
    "sg:address":"30 Northfield Ave",
    "sg:city":"Edison",
    "sg:classifiers":[
        {
            "category":"Shopping",
            "subcategory":"Used Merchandise",
            "type":"Retail Goods"
        }
    ],
    "sg:phone":"+1 732 225 0770",
    "sg:postcode":"08837",
    "sg:province":"NJ",
    "sg:tags":[
        "antique"
    ],
    "sg:website":"www.aaimporting.com",
    "wof:name":"A A Importing Co",
    "wof:placetype":"venue"
},
  "geometry": {"coordinates":[-74.34481599999999,40.507871],"type":"Point"}
}