{
  "type": "Feature",
  "properties": {
    "iso:country":"US",
    "sg:address":"646 Tonnelle Ave",
    "sg:city":"Jersey City",
    "sg:classifiers":[
        {
            "category":"Autos & Motor Vehicles",
            "subcategory":"Automobile Sales",
            "type":"Retail Goods"
        }
    ],
    "sg:phone":"+1   ",
    "sg:postcode":"07307",
    "sg:province":"NJ",
    "sg:tags":[
        "used"
    ],
    "wof:name":"Three Brothers Auto Sales",
    "wof:placetype":"venue"
},
  "geometry": {"coordinates":[-74.056974,40.753182],"type":"Point"}
}