{
  "type": "Feature",
  "properties": {
    "addr:full":"301 Hyslip Ave Westfield NJ 07090",
    "addr:housenumber":"301",
    "addr:postcode":"07090",
    "addr:street":"Hyslip Ave",
    "iso:country":"US",
    "sg:address":"301 Hyslip Ave",
    "sg:city":"Westfield",
    "sg:classifiers":[
        {
            "category":"Professional",
            "subcategory":"Management & Consulting",
            "type":"Services"
        }
    ],
    "sg:phone":"+1   ",
    "sg:postcode":"07090",
    "sg:province":"NJ",
    "wof:name":"Safety Maintenance Inc",
    "wof:placetype":"venue"
},
  "geometry": {"coordinates":[-74.351618,40.640128],"type":"Point"}
}