{
  "type": "Feature",
  "properties": {
    "iso:country":"US",
    "sg:address":"221 Sheridan Ave",
    "sg:city":"Roselle",
    "sg:classifiers":[
        {
            "category":"Banks & Credit Unions",
            "subcategory":"Bank",
            "type":"Services"
        }
    ],
    "sg:phone":"+1 908 298 1311",
    "sg:postcode":"07203",
    "sg:province":"NJ",
    "wof:name":"Singer Employees Credit Union",
    "wof:placetype":"venue"
},
  "geometry": {"coordinates":[-74.249725,40.66039],"type":"Point"}
}