{
  "type": "Feature",
  "properties": {
    "iso:country":"US",
    "sg:address":"900 Asbury Ave",
    "sg:city":"Ocean City",
    "sg:classifiers":[
        {
            "category":"Manufacturing",
            "subcategory":"Food",
            "type":"Manufacturing & Wholesale Goods"
        },
        {
            "category":"Restaurant",
            "type":"Food & Drink"
        }
    ],
    "sg:phone":"+1 609 399 4400",
    "sg:postcode":"08226",
    "sg:province":"NJ",
    "sg:tags":[
        "desert",
        "ice",
        "mfg"
    ],
    "wof:name":"Laureen's Cafe On Nine",
    "wof:placetype":"venue"
},
  "geometry": {"coordinates":[-74.577732,39.277721],"type":"Point"}
}