{
  "type": "Feature",
  "properties": {
    "iso:country":"US",
    "sg:address":"576 E Veterans Hwy",
    "sg:city":"Jackson",
    "sg:classifiers":[
        {
            "category":"Health Services",
            "subcategory":"Chiropractor",
            "type":"Services"
        }
    ],
    "sg:phone":"+1 732 928 9274",
    "sg:postcode":"08527",
    "sg:province":"NJ",
    "wof:name":"Cimar Chiropractic Center",
    "wof:placetype":"venue"
},
  "geometry": {"coordinates":[-74.304115,40.086254],"type":"Point"}
}