{
  "type": "Feature",
  "properties": {
    "addr:full":"284 US Hwy 206 Hillsborough NJ 08844",
    "addr:housenumber":"284",
    "addr:postcode":"08844",
    "addr:street":"Us Hwy 206",
    "iso:country":"US",
    "sg:address":"284 US Hwy 206",
    "sg:city":"Hillsborough",
    "sg:classifiers":[
        {
            "category":"Building & Trades",
            "subcategory":"Construction",
            "type":"Services"
        }
    ],
    "sg:phone":"+1 908 874 3980",
    "sg:postcode":"08844",
    "sg:province":"NJ",
    "sg:tags":[
        "contractor"
    ],
    "wof:name":"Adamsville Maintainence",
    "wof:placetype":"venue"
},
  "geometry": {"coordinates":[-74.627797,40.524479],"type":"Point"}
}