{
  "type": "Feature",
  "properties": {
    "iso:country":"US",
    "sg:address":"5 Sun Valley Way",
    "sg:city":"Long Valley",
    "sg:classifiers":[
        {
            "category":"Professional",
            "subcategory":"Management & Consulting",
            "type":"Services"
        }
    ],
    "sg:phone":"+1 908 876 3721",
    "sg:postcode":"07853",
    "sg:province":"NJ",
    "wof:name":"Beckman HCC Inc",
    "wof:placetype":"venue"
},
  "geometry": {"coordinates":[-74.765052,40.750626],"type":"Point"}
}