{
  "type": "Feature",
  "properties": {
    "addr:full":"14 Greenville Ave Jersey City NJ 07305",
    "addr:housenumber":"14",
    "addr:postcode":"07305",
    "addr:street":"Greenville",
    "iso:country":"US",
    "sg:address":"14 Greenville Ave",
    "sg:city":"Jersey City",
    "sg:classifiers":[
        {
            "category":"Organizations",
            "subcategory":"Religious Organization",
            "type":"Services"
        }
    ],
    "sg:phone":"+1 201 521 0044",
    "sg:postcode":"07305",
    "sg:province":"NJ",
    "sg:tags":[
        "monastery",
        "convent"
    ],
    "wof:name":"Dominican Sisters",
    "wof:placetype":"venue"
},
  "geometry": {"coordinates":[-74.094742,40.697698],"type":"Point"}
}