{
  "type": "Feature",
  "properties": {
    "addr:full":"195 Closter Dock Rd Closter NJ 07624",
    "addr:housenumber":"195",
    "addr:postcode":"07624",
    "addr:street":"Closter Dock Rd",
    "iso:country":"US",
    "sg:address":"195 Closter Dock Rd",
    "sg:city":"Closter",
    "sg:classifiers":[
        {
            "category":"Autos & Motor Vehicles",
            "subcategory":"Auto Supplies",
            "type":"Retail Goods"
        }
    ],
    "sg:phone":"+1   ",
    "sg:postcode":"07624",
    "sg:province":"NJ",
    "sg:tags":[
        "automotive",
        "parts"
    ],
    "wof:name":"Alpine Auto Parts",
    "wof:placetype":"venue"
},
  "geometry": {"coordinates":[-73.96252800000001,40.974372],"type":"Point"}
}