{
  "type": "Feature",
  "properties": {
    "iso:country":"US",
    "sg:address":"8 Crestwood Dr",
    "sg:city":"Randolph",
    "sg:classifiers":[
        {
            "category":"Building & Trades",
            "subcategory":"Plumbing",
            "type":"Services"
        }
    ],
    "sg:phone":"+1 973 927 0810",
    "sg:postcode":"07869",
    "sg:province":"NJ",
    "sg:tags":[
        "plumbing",
        "air",
        "heating",
        "contractor"
    ],
    "wof:name":"Competitive Welding-Boiler",
    "wof:placetype":"venue"
},
  "geometry": {"coordinates":[-74.57600600000001,40.84896],"type":"Point"}
}