{
  "type": "Feature",
  "properties": {
    "iso:country":"US",
    "sg:address":"212 Laurel Heights Dr",
    "sg:city":"Bridgeton",
    "sg:classifiers":[
        {
            "category":"Health Services",
            "subcategory":"Doctor",
            "type":"Services"
        }
    ],
    "sg:phone":"+1 856 451 4400",
    "sg:postcode":"08302",
    "sg:province":"NJ",
    "sg:tags":[
        "medical"
    ],
    "wof:name":"Gandhi Jatin MD P A",
    "wof:placetype":"venue"
},
  "geometry": {"coordinates":[-75.22894599999999,39.453552],"type":"Point"}
}