{
  "type": "Feature",
  "properties": {
    "iso:country":"US",
    "sg:address":"2 Regent Sq",
    "sg:city":"Jackson",
    "sg:classifiers":[
        {
            "category":"Professional",
            "subcategory":"Art Services",
            "type":"Services"
        }
    ],
    "sg:phone":"+1   ",
    "sg:postcode":"08527",
    "sg:province":"NJ",
    "sg:tags":[
        "commercial",
        "design"
    ],
    "wof:name":"Graphics Unlimited",
    "wof:placetype":"venue"
},
  "geometry": {"coordinates":[-74.28335,40.111171],"type":"Point"}
}