{
  "type": "Feature",
  "properties": {
    "addr:full":"1179 Chestnut St Elizabeth NJ 07201",
    "addr:housenumber":"1179",
    "addr:postcode":"07201",
    "addr:street":"Chestnut St",
    "iso:country":"US",
    "sg:address":"1179 Chestnut St",
    "sg:city":"Elizabeth",
    "sg:classifiers":[
        {
            "category":"Retail",
            "subcategory":"Auto Repair",
            "type":"Services"
        }
    ],
    "sg:phone":"+1   ",
    "sg:postcode":"07201",
    "sg:province":"NJ",
    "sg:tags":[
        "body"
    ],
    "wof:name":"Metro Auto Body",
    "wof:placetype":"venue"
},
  "geometry": {"coordinates":[-74.21376600000001,40.669285],"type":"Point"}
}