{
  "type": "Feature",
  "properties": {
    "addr:full":"123 E Park Ave Haddon Twp NJ 08107",
    "addr:housenumber":"123",
    "addr:postcode":"08107",
    "addr:street":"E Park Ave",
    "iso:country":"US",
    "sg:address":"123 E Park Ave",
    "sg:city":"Haddon Twp",
    "sg:classifiers":[
        {
            "category":"Professional",
            "type":"Services"
        },
        {
            "category":"Professional",
            "subcategory":"Business Services",
            "type":"Services"
        }
    ],
    "sg:phone":"+1 856 869 7112",
    "sg:postcode":"08107",
    "sg:province":"NJ",
    "sg:tags":[
        "establishment"
    ],
    "wof:name":"Alternative Design Concepts",
    "wof:placetype":"venue"
},
  "geometry": {"coordinates":[-75.069928,39.902138],"type":"Point"}
}