{
  "type": "Feature",
  "properties": {
    "iso:country":"US",
    "sg:address":"909 Harrison Ave",
    "sg:city":"Kearny",
    "sg:classifiers":[
        {
            "category":"Freight",
            "type":"Transportation"
        }
    ],
    "sg:phone":"+1 201 998 6006",
    "sg:postcode":"07032",
    "sg:province":"NJ",
    "wof:name":"Freeman Transportation",
    "wof:placetype":"venue"
},
  "geometry": {"coordinates":[-74.14532699999999,40.748169],"type":"Point"}
}