{
  "type": "Feature",
  "properties": {
    "iso:country":"US",
    "sg:address":"29 Hadley Ave",
    "sg:city":"Toms River",
    "sg:classifiers":[
        {
            "category":"Professional",
            "subcategory":"Lawyer & Legal Services",
            "type":"Services"
        }
    ],
    "sg:phone":"+1 732 286 9800",
    "sg:postcode":"08753",
    "sg:province":"NJ",
    "sg:tags":[
        "attorney"
    ],
    "wof:name":"Matthew J Heagen",
    "wof:placetype":"venue"
},
  "geometry": {"coordinates":[-74.190521,39.954574],"type":"Point"}
}