{
  "type": "Feature",
  "properties": {
    "iso:country":"US",
    "sg:address":"384 Fairview Ave",
    "sg:city":"Fairview",
    "sg:classifiers":[
        {
            "category":"Education",
            "subcategory":"Music School",
            "type":"Public Place"
        },
        {
            "category":"Arts & Performance",
            "subcategory":"Arts Center",
            "type":"Entertainment"
        }
    ],
    "sg:phone":"+1 201 943 3410",
    "sg:postcode":"07022",
    "sg:province":"NJ",
    "sg:tags":[
        "instrument",
        "performing",
        "musical",
        "teacher"
    ],
    "wof:name":"Fairview Piano Co",
    "wof:placetype":"venue"
},
  "geometry": {"coordinates":[-74.00140399999999,40.8111],"type":"Point"}
}