{
  "type": "Feature",
  "properties": {
    "addr:full":"1043 US Hwy 9 Old Bridge NJ 08857",
    "addr:housenumber":"1043",
    "addr:postcode":"08857",
    "addr:street":"Us Hwy 9",
    "iso:country":"US",
    "sg:address":"1043 US Hwy 9",
    "sg:city":"Old Bridge",
    "sg:classifiers":[
        {
            "category":"Banks & Credit Unions",
            "subcategory":"Bank",
            "type":"Services"
        }
    ],
    "sg:phone":"+1   ",
    "sg:postcode":"08857",
    "sg:province":"NJ",
    "sg:tags":[
        "national",
        "commercial"
    ],
    "sg:website":"www.pennfederal.com",
    "wof:name":"Penn Federal Savings Bank",
    "wof:placetype":"venue"
},
  "geometry": {"coordinates":[-74.297202,40.453441],"type":"Point"}
}