{
  "type": "Feature",
  "properties": {
    "addr:full":"38 Morris Ave Springfield NJ 07081",
    "addr:housenumber":"38",
    "addr:postcode":"07081",
    "addr:street":"Morris Ave",
    "iso:country":"US",
    "sg:address":"38 Morris Ave",
    "sg:city":"Springfield",
    "sg:classifiers":[
        {
            "category":"Building & Trades",
            "subcategory":"Electrical",
            "type":"Services"
        }
    ],
    "sg:phone":"+1 973 376 4670",
    "sg:postcode":"07081",
    "sg:province":"NJ",
    "sg:tags":[
        "electrician",
        "electric",
        "contractor"
    ],
    "wof:name":"Catullo Electric",
    "wof:placetype":"venue"
},
  "geometry": {"coordinates":[-74.303398,40.708599],"type":"Point"}
}