{
  "type": "Feature",
  "properties": {
    "iso:country":"US",
    "sg:address":"424 Lincoln Ave",
    "sg:city":"Avon By The Sea",
    "sg:classifiers":[
        {
            "category":"Organizations",
            "subcategory":"Religious Organization",
            "type":"Services"
        }
    ],
    "sg:phone":"+1 732 774 4089",
    "sg:postcode":"07717",
    "sg:province":"NJ",
    "sg:tags":[
        "church"
    ],
    "wof:name":"St Elizabeth's Church",
    "wof:placetype":"venue"
},
  "geometry": {"coordinates":[-74.020188,40.190574],"type":"Point"}
}