{
  "type": "Feature",
  "properties": {
    "addr:full":"21 Passaic St Hackensack NJ 07601",
    "addr:housenumber":"21",
    "addr:postcode":"07601",
    "addr:street":"Passaic St",
    "iso:country":"US",
    "sg:address":"21 Passaic St",
    "sg:city":"Hackensack",
    "sg:classifiers":[
        {
            "category":"Professional",
            "subcategory":"Employment Agencies",
            "type":"Services"
        }
    ],
    "sg:phone":"+1 201 487 2203",
    "sg:postcode":"07601",
    "sg:province":"NJ",
    "sg:tags":[
        "modeling",
        "school",
        "cosmetology"
    ],
    "wof:name":"Beautician & Model Agency",
    "wof:placetype":"venue"
},
  "geometry": {"coordinates":[-74.040599,40.889982],"type":"Point"}
}