{
  "type": "Feature",
  "properties": {
    "addr:full":"731 Pennsylvania Ave Elizabeth NJ 07201",
    "addr:housenumber":"731",
    "addr:postcode":"07201",
    "addr:street":"Pennsylvania Ave",
    "iso:country":"US",
    "sg:address":"731 Pennsylvania Ave",
    "sg:city":"Elizabeth",
    "sg:classifiers":[
        {
            "category":"Building & Trades",
            "subcategory":"Construction",
            "type":"Services"
        }
    ],
    "sg:phone":"+1 908 354 2330",
    "sg:postcode":"07201",
    "sg:province":"NJ",
    "sg:tags":[
        "hanging",
        "painter",
        "contractor"
    ],
    "wof:name":"Friedland D Painting Co",
    "wof:placetype":"venue"
},
  "geometry": {"coordinates":[-74.20666199999999,40.680783],"type":"Point"}
}