{
  "type": "Feature",
  "properties": {
    "addr:full":"186 6th St Harrison NJ 07029",
    "addr:housenumber":"186",
    "addr:postcode":"07029",
    "addr:street":"6Th St",
    "iso:country":"US",
    "sg:address":"186 6th St",
    "sg:city":"Harrison",
    "sg:classifiers":[
        {
            "category":"Building & Trades",
            "subcategory":"Plumbing",
            "type":"Services"
        }
    ],
    "sg:phone":"+1 973 484 7089",
    "sg:postcode":"07029",
    "sg:province":"NJ",
    "sg:tags":[
        "contractor"
    ],
    "wof:name":"Vrv Services & Heating",
    "wof:placetype":"venue"
},
  "geometry": {"coordinates":[-74.151927,40.74574],"type":"Point"}
}