{
  "type": "Feature",
  "properties": {
    "iso:country":"US",
    "sg:address":"51 Jim Fear Dr",
    "sg:city":"Morris Plains",
    "sg:classifiers":[
        {
            "category":"Sports & Exercise",
            "subcategory":"Sports Center",
            "type":"Entertainment"
        },
        {
            "category":"Arena",
            "subcategory":"Sports Club",
            "type":"Entertainment"
        }
    ],
    "sg:phone":"+1 973 267 4455",
    "sg:postcode":"07950",
    "sg:province":"NJ",
    "sg:tags":[
        "professional",
        "amateur",
        "team"
    ],
    "wof:name":"Morris Plains Little League",
    "wof:placetype":"venue"
},
  "geometry": {"coordinates":[-74.467598,40.8344],"type":"Point"}
}