{
  "type": "Feature",
  "properties": {
    "addr:full":"192 State Rte 33 Manalapan NJ 07726",
    "addr:housenumber":"192",
    "addr:postcode":"07726",
    "addr:street":"State Rte 33",
    "iso:country":"US",
    "sg:address":"192 State Rte 33",
    "sg:city":"Manalapan",
    "sg:classifiers":[
        {
            "category":"Building & Trades",
            "subcategory":"Construction",
            "type":"Services"
        }
    ],
    "sg:phone":"+1 732 308 2216",
    "sg:postcode":"07726",
    "sg:province":"NJ",
    "sg:tags":[
        "fence",
        "contractor"
    ],
    "wof:name":"Achieved Fencing",
    "wof:placetype":"venue"
},
  "geometry": {"coordinates":[-74.347663,40.253445],"type":"Point"}
}