{
  "type": "Feature",
  "properties": {
    "iso:country":"US",
    "sg:address":"400 Old Goshen Rd",
    "sg:city":"Ocean View",
    "sg:classifiers":[
        {
            "category":"Manufacturing",
            "subcategory":"Food",
            "type":"Manufacturing & Wholesale Goods"
        }
    ],
    "sg:phone":"+1 609 827 6166",
    "sg:postcode":"08230",
    "sg:province":"NJ",
    "sg:tags":[
        "preparation",
        "mfg"
    ],
    "wof:name":"Adams Awesome Salsa",
    "wof:placetype":"venue"
},
  "geometry": {"coordinates":[-74.740032,39.184563],"type":"Point"}
}