{
  "type": "Feature",
  "properties": {
    "addr:full":"45 Orchard Pl Irvington NJ 07111",
    "addr:housenumber":"45",
    "addr:postcode":"07111",
    "addr:street":"Orchard Pl",
    "iso:country":"US",
    "sg:address":"45 Orchard Pl",
    "sg:city":"Irvington",
    "sg:classifiers":[
        {
            "category":"Professional",
            "subcategory":"Management & Consulting",
            "type":"Services"
        }
    ],
    "sg:phone":"+1   ",
    "sg:postcode":"07111",
    "sg:province":"NJ",
    "sg:tags":[
        "business"
    ],
    "wof:name":"Jabb Consulting Inc",
    "wof:placetype":"venue"
},
  "geometry": {"coordinates":[-74.24608499999999,40.714456],"type":"Point"}
}