{
  "type": "Feature",
  "properties": {
    "iso:country":"US",
    "sg:address":"365 Hewitt Ave",
    "sg:city":"Trenton",
    "sg:classifiers":[
        {
            "category":"Professional",
            "subcategory":"Business Services",
            "type":"Services"
        }
    ],
    "sg:phone":"+1   ",
    "sg:postcode":"08611",
    "sg:province":"NJ",
    "wof:name":"Distinctive Design",
    "wof:placetype":"venue"
},
  "geometry": {"coordinates":[-74.750441,40.193193],"type":"Point"}
}