{
  "type": "Feature",
  "properties": {
    "iso:country":"US",
    "sg:address":"2715 E Chestnut Ave",
    "sg:city":"Vineland",
    "sg:classifiers":[
        {
            "category":"Real Estate",
            "subcategory":"Real Estate Operator",
            "type":"Services"
        }
    ],
    "sg:phone":"+1 856 692 3300",
    "sg:postcode":"08361",
    "sg:province":"NJ",
    "sg:tags":[
        "apartment"
    ],
    "wof:name":"Brewster Garden Apts",
    "wof:placetype":"venue"
},
  "geometry": {"coordinates":[-74.97457799999999,39.476415],"type":"Point"}
}