{
  "type": "Feature",
  "properties": {
    "addr:full":"1310 Dill Ave Linden NJ 07036",
    "addr:housenumber":"1310",
    "addr:postcode":"07036",
    "addr:street":"Dill Ave",
    "iso:country":"US",
    "sg:address":"1310 Dill Ave",
    "sg:city":"Linden",
    "sg:classifiers":[
        {
            "category":"Building & Trades",
            "subcategory":"Electrical",
            "type":"Services"
        }
    ],
    "sg:phone":"+1 908 925 5984",
    "sg:postcode":"07036",
    "sg:province":"NJ",
    "sg:tags":[
        "electrical",
        "contractor"
    ],
    "wof:name":"Pierre Grand Electrical Contr",
    "wof:placetype":"venue"
},
  "geometry": {"coordinates":[-74.24288300000001,40.646327],"type":"Point"}
}