{
  "type": "Feature",
  "properties": {
    "iso:country":"US",
    "sg:address":"52 W Erie Ave",
    "sg:city":"Rutherford",
    "sg:classifiers":[
        {
            "category":"Professional",
            "subcategory":"Research",
            "type":"Services"
        }
    ],
    "sg:phone":"+1   ",
    "sg:postcode":"07070",
    "sg:province":"NJ",
    "sg:tags":[
        "nonphysical",
        "commercial"
    ],
    "wof:name":"Justin Gardiner",
    "wof:placetype":"venue"
},
  "geometry": {"coordinates":[-74.10315300000001,40.832791],"type":"Point"}
}