{
  "type": "Feature",
  "properties": {
    "addr:full":"35 Abbett Ave Ste 2 Morristown NJ 07960",
    "addr:housenumber":"35",
    "addr:postcode":"07960",
    "addr:street":"Abbett Ave Ste 2",
    "iso:country":"US",
    "sg:address":"35 Abbett Ave Ste 2",
    "sg:city":"Morristown",
    "sg:classifiers":[
        {
            "category":"Home & Garden",
            "subcategory":"Furniture",
            "type":"Retail Goods"
        }
    ],
    "sg:phone":"+1 973 695 0110",
    "sg:postcode":"07960",
    "sg:province":"NJ",
    "sg:tags":[
        "store"
    ],
    "wof:name":"British Pine Emporium",
    "wof:placetype":"venue"
},
  "geometry": {"coordinates":[-74.472481,40.801581],"type":"Point"}
}