{
  "type": "Feature",
  "properties": {
    "iso:country":"US",
    "sg:address":"200 Mill Rd",
    "sg:city":"Burlington",
    "sg:classifiers":[
        {
            "category":"Autos & Motor Vehicles",
            "subcategory":"Automobile Sales",
            "type":"Retail Goods"
        }
    ],
    "sg:phone":"+1   ",
    "sg:postcode":"08016",
    "sg:province":"NJ",
    "sg:tags":[
        "car",
        "used"
    ],
    "wof:name":"Joe Dicioccios Quality U Cars",
    "wof:placetype":"venue"
},
  "geometry": {"coordinates":[-74.865731,40.063289],"type":"Point"}
}