{
  "type": "Feature",
  "properties": {
    "addr:full":"7 Whitall Dr Sicklerville NJ 08081",
    "addr:housenumber":"7",
    "addr:postcode":"08081",
    "addr:street":"Whitall Dr",
    "iso:country":"US",
    "sg:address":"7 Whitall Dr",
    "sg:city":"Sicklerville",
    "sg:classifiers":[
        {
            "category":"Professional",
            "subcategory":"Management & Consulting",
            "type":"Services"
        }
    ],
    "sg:phone":"+1 856 228 0655",
    "sg:postcode":"08081",
    "sg:province":"NJ",
    "wof:name":"Creative Insites Inc",
    "wof:placetype":"venue"
},
  "geometry": {"coordinates":[-75.036198,39.764691],"type":"Point"}
}