{
  "type": "Feature",
  "properties": {
    "addr:full":"4 Leonard St Metuchen NJ 08840",
    "addr:housenumber":"4",
    "addr:postcode":"08840",
    "addr:street":"Leonard St",
    "iso:country":"US",
    "sg:address":"4 Leonard St",
    "sg:city":"Metuchen",
    "sg:classifiers":[
        {
            "category":"Professional",
            "subcategory":"Computer Services",
            "type":"Services"
        }
    ],
    "sg:phone":"+1 732 636 0688",
    "sg:postcode":"08840",
    "sg:province":"NJ",
    "sg:tags":[
        "design",
        "system"
    ],
    "wof:name":"Netlink Consulting Inc",
    "wof:placetype":"venue"
},
  "geometry": {"coordinates":[-74.37361900000001,40.546411],"type":"Point"}
}