{
  "type": "Feature",
  "properties": {
    "addr:full":"13 W 41st St Bayonne NJ 07002",
    "addr:housenumber":"13",
    "addr:postcode":"07002",
    "addr:street":"W 41St St",
    "iso:country":"US",
    "sg:address":"13 W 41st St",
    "sg:city":"Bayonne",
    "sg:classifiers":[
        {
            "category":"Retail",
            "subcategory":"Auto Repair",
            "type":"Services"
        }
    ],
    "sg:phone":"+1 201 436 0901",
    "sg:postcode":"07002",
    "sg:province":"NJ",
    "wof:name":"Pittner Louis",
    "wof:placetype":"venue"
},
  "geometry": {"coordinates":[-74.107201,40.677399],"type":"Point"}
}