{
  "type": "Feature",
  "properties": {
    "iso:country":"US",
    "sg:address":"1781 S Spring Rd",
    "sg:city":"Vineland",
    "sg:classifiers":[
        {
            "category":"Real Estate",
            "subcategory":"Real Estate Operator",
            "type":"Services"
        }
    ],
    "sg:phone":"+1   ",
    "sg:postcode":"08361",
    "sg:province":"NJ",
    "sg:tags":[
        "building",
        "apartment"
    ],
    "wof:name":"Spring Gardens Senior Housing",
    "wof:placetype":"venue"
},
  "geometry": {"coordinates":[-74.99049100000001,39.457522],"type":"Point"}
}