{
  "type": "Feature",
  "properties": {
    "addr:full":"33 Sleepy Hollow Dr Tabernacle NJ 08088",
    "addr:housenumber":"33",
    "addr:postcode":"08088",
    "addr:street":"Sleepy Hollow Dr",
    "iso:country":"US",
    "sg:address":"33 Sleepy Hollow Dr",
    "sg:city":"Tabernacle",
    "sg:classifiers":[
        {
            "category":"Building & Trades",
            "subcategory":"Construction",
            "type":"Services"
        }
    ],
    "sg:phone":"+1 609 268 1919",
    "sg:postcode":"08088",
    "sg:province":"NJ",
    "sg:tags":[
        "house",
        "contractor"
    ],
    "wof:name":"Shawnee Builders Inc",
    "wof:placetype":"venue"
},
  "geometry": {"coordinates":[-74.741687,39.847152],"type":"Point"}
}