{
  "type": "Feature",
  "properties": {
    "addr:full":"200 US Hwy 22 Springfield NJ 07081",
    "addr:housenumber":"200",
    "addr:postcode":"07081",
    "addr:street":"Us Hwy 22",
    "iso:country":"US",
    "sg:address":"200 US Hwy 22",
    "sg:city":"Springfield",
    "sg:classifiers":[
        {
            "category":"Shopping",
            "subcategory":"Optical Goods",
            "type":"Retail Goods"
        }
    ],
    "sg:phone":"+1 973 467 2266",
    "sg:postcode":"07081",
    "sg:province":"NJ",
    "wof:name":"Lens Crafters",
    "wof:placetype":"venue"
},
  "geometry": {"coordinates":[-74.31992700000001,40.686017],"type":"Point"}
}