{
  "type": "Feature",
  "properties": {
    "iso:country":"US",
    "sg:address":"10 Ravine Ave",
    "sg:city":"Wyckoff",
    "sg:classifiers":[
        {
            "category":"Retail",
            "subcategory":"Auto Repair",
            "type":"Services"
        }
    ],
    "sg:phone":"+1 201 447 3838",
    "sg:postcode":"07481",
    "sg:province":"NJ",
    "sg:tags":[
        "lettering",
        "truck"
    ],
    "wof:name":"Denver Sign Co",
    "wof:placetype":"venue"
},
  "geometry": {"coordinates":[-74.147307,40.975616],"type":"Point"}
}