{
  "type": "Feature",
  "properties": {
    "addr:full":"20 Bellevue Ave Rumson NJ 07760",
    "addr:housenumber":"20",
    "addr:postcode":"07760",
    "addr:street":"Bellevue Ave",
    "iso:country":"US",
    "sg:address":"20 Bellevue Ave",
    "sg:city":"Rumson",
    "sg:classifiers":[
        {
            "category":"Marine",
            "type":"Transportation"
        }
    ],
    "sg:phone":"+1 732 219 8980",
    "sg:postcode":"07760",
    "sg:province":"NJ",
    "wof:name":"Bay Marine Ltd",
    "wof:placetype":"venue"
},
  "geometry": {"coordinates":[-74.01696099999999,40.367879],"type":"Point"}
}