{
  "type": "Feature",
  "properties": {
    "addr:full":"606 Commerce Rd Linden NJ 07036",
    "addr:housenumber":"606",
    "addr:postcode":"07036",
    "addr:street":"Commerce Rd",
    "iso:country":"US",
    "sg:address":"606 Commerce Rd",
    "sg:city":"Linden",
    "sg:classifiers":[
        {
            "category":"Manufacturing",
            "subcategory":"Rubber & Plastics",
            "type":"Manufacturing & Wholesale Goods"
        }
    ],
    "sg:phone":"+1 908 862 0350",
    "sg:postcode":"07036",
    "sg:province":"NJ",
    "sg:tags":[
        "custom"
    ],
    "sg:website":"www.perforatingindustries.com",
    "wof:name":"Perforating Industries Inc",
    "wof:placetype":"venue"
},
  "geometry": {"coordinates":[-74.239868,40.631964],"type":"Point"}
}