{
  "type": "Feature",
  "properties": {
    "addr:full":"226 S 5th St Elizabeth NJ 07206",
    "addr:housenumber":"226",
    "addr:postcode":"07206",
    "addr:street":"S 5Th St",
    "iso:country":"US",
    "sg:address":"226 S 5th St",
    "sg:city":"Elizabeth",
    "sg:classifiers":[
        {
            "category":"Professional",
            "type":"Services"
        }
    ],
    "sg:phone":"+1   ",
    "sg:postcode":"07206",
    "sg:province":"NJ",
    "wof:name":"Comclean Inc",
    "wof:placetype":"venue"
},
  "geometry": {"coordinates":[-74.20267699999999,40.652206],"type":"Point"}
}