{
  "type": "Feature",
  "properties": {
    "iso:country":"US",
    "sg:address":"26 Manley Ter",
    "sg:city":"Maplewood",
    "sg:classifiers":[
        {
            "category":"Professional",
            "subcategory":"Business Services",
            "type":"Services"
        }
    ],
    "sg:phone":"+1   ",
    "sg:postcode":"07040",
    "sg:province":"NJ",
    "wof:name":"Nancy Rosen Wall Art Inc",
    "wof:placetype":"venue"
},
  "geometry": {"coordinates":[-74.27866899999999,40.720335],"type":"Point"}
}