{
  "type": "Feature",
  "properties": {
    "addr:full":"333 US Hwy 46 Fairfield NJ 07004",
    "addr:housenumber":"333",
    "addr:postcode":"07004",
    "addr:street":"Us Hwy 46",
    "iso:country":"US",
    "sg:address":"333 US Hwy 46",
    "sg:city":"Fairfield",
    "sg:classifiers":[
        {
            "category":"Professional",
            "subcategory":"Management & Consulting",
            "type":"Services"
        }
    ],
    "sg:phone":"+1 973 575 6327",
    "sg:postcode":"07004",
    "sg:province":"NJ",
    "sg:tags":[
        "construction"
    ],
    "wof:name":"Avila Consultants LLC",
    "wof:placetype":"venue"
},
  "geometry": {"coordinates":[-74.296638,40.87895],"type":"Point"}
}