{
  "type": "Feature",
  "properties": {
    "addr:full":"31 Louis Dr Montville NJ 07045",
    "addr:housenumber":"31",
    "addr:postcode":"07045",
    "addr:street":"Louis Dr",
    "iso:country":"US",
    "sg:address":"31 Louis Dr",
    "sg:city":"Montville",
    "sg:classifiers":[
        {
            "category":"Real Estate",
            "subcategory":"Architect",
            "type":"Services"
        }
    ],
    "sg:phone":"+1 973 316 1241",
    "sg:postcode":"07045",
    "sg:province":"NJ",
    "sg:tags":[
        "architectural"
    ],
    "wof:name":"Tjwu Inc",
    "wof:placetype":"venue"
},
  "geometry": {"coordinates":[-74.381513,40.908743],"type":"Point"}
}