{
  "type": "Feature",
  "properties": {
    "iso:country":"US",
    "sg:address":"296 US Highway 46",
    "sg:city":"Rockaway",
    "sg:classifiers":[
        {
            "category":"Restaurant",
            "type":"Food & Drink"
        }
    ],
    "sg:phone":"+1 973 627 8400",
    "sg:postcode":"07866",
    "sg:province":"NJ",
    "sg:tags":[
        "thai"
    ],
    "sg:website":"www.Thainamphet.com",
    "wof:name":"Thai Nam Phet",
    "wof:placetype":"venue"
},
  "geometry": {"coordinates":[-74.521202,40.8909],"type":"Point"}
}