{
  "type": "Feature",
  "properties": {
    "addr:full":"2080 E State St Exd Trenton NJ 08619",
    "addr:housenumber":"2080",
    "addr:postcode":"08619",
    "addr:street":"E State St Exd",
    "iso:country":"US",
    "sg:address":"2080 E State St Exd",
    "sg:city":"Trenton",
    "sg:classifiers":[
        {
            "category":"Building & Trades",
            "subcategory":"Construction",
            "type":"Services"
        },
        {
            "category":"Wholesale",
            "subcategory":"Home Furnishings",
            "type":"Manufacturing & Wholesale Goods"
        }
    ],
    "sg:phone":"+1 609 689 0099",
    "sg:postcode":"08619",
    "sg:province":"NJ",
    "sg:tags":[
        "accessory",
        "work",
        "closet",
        "carpentry"
    ],
    "wof:name":"Closets By Design South Jersey",
    "wof:placetype":"venue"
},
  "geometry": {"coordinates":[-74.719791,40.242222],"type":"Point"}
}