{
  "type": "Feature",
  "properties": {
    "iso:country":"US",
    "sg:address":"13 Lori St",
    "sg:city":"Jamesburg",
    "sg:classifiers":[
        {
            "category":"Professional",
            "subcategory":"Engineering",
            "type":"Services"
        }
    ],
    "sg:phone":"+1 732 251 3330",
    "sg:postcode":"08831",
    "sg:province":"NJ",
    "sg:tags":[
        "engineer"
    ],
    "sg:website":"www.ram-associates.com",
    "wof:name":"RAM Assoc",
    "wof:placetype":"venue"
},
  "geometry": {"coordinates":[-74.389104,40.368729],"type":"Point"}
}