{
  "type": "Feature",
  "properties": {
    "addr:full":"301 Broadway Cape May NJ 08204",
    "addr:housenumber":"301",
    "addr:postcode":"08204",
    "addr:street":"Broadway",
    "iso:country":"US",
    "sg:address":"301 Broadway",
    "sg:city":"Cape May",
    "sg:classifiers":[
        {
            "category":"Bakery",
            "type":"Food & Drink"
        }
    ],
    "sg:phone":"+1 609 884 4007",
    "sg:postcode":"08204",
    "sg:province":"NJ",
    "wof:name":"Ellie's Bakery",
    "wof:placetype":"venue"
},
  "geometry": {"coordinates":[-74.930205,38.937172],"type":"Point"}
}