{
  "type": "Feature",
  "properties": {
    "addr:full":"596 Valley Rd Montclair NJ 07043",
    "addr:housenumber":"596",
    "addr:postcode":"07043",
    "addr:street":"Valley Rd",
    "iso:country":"US",
    "sg:address":"596 Valley Rd",
    "sg:city":"Montclair",
    "sg:classifiers":[
        {
            "category":"Restaurant",
            "type":"Food & Drink"
        }
    ],
    "sg:phone":"+1 973 744 0915",
    "sg:postcode":"07043",
    "sg:province":"NJ",
    "sg:website":"www.uptownmontclair.com",
    "wof:name":"Uptown Bistro",
    "wof:placetype":"venue"
},
  "geometry": {"coordinates":[-74.208097,40.840887],"type":"Point"}
}