{
  "type": "Feature",
  "properties": {
    "addr:full":"64 The Promenade Edgewater NJ 07020",
    "addr:housenumber":"64",
    "addr:postcode":"07020",
    "addr:street":"The Promenade",
    "iso:country":"US",
    "sg:address":"64 The Promenade",
    "sg:city":"Edgewater",
    "sg:classifiers":[
        {
            "category":"Shopping",
            "subcategory":"Clothing, Apparel, & Fashions",
            "type":"Retail Goods"
        }
    ],
    "sg:phone":"+1 201 941 1896",
    "sg:postcode":"07020",
    "sg:province":"NJ",
    "sg:tags":[
        "maternity"
    ],
    "wof:name":"Motherhood Maternity",
    "wof:placetype":"venue"
},
  "geometry": {"coordinates":[-73.940693,40.888155],"type":"Point"}
}