{
  "type": "Feature",
  "properties": {
    "iso:country":"US",
    "sg:address":"89 Hendrickson Rd",
    "sg:city":"Freehold",
    "sg:classifiers":[
        {
            "category":"Professional",
            "type":"Services"
        }
    ],
    "sg:phone":"+1   ",
    "sg:postcode":"07728",
    "sg:province":"NJ",
    "wof:name":"Lets Party",
    "wof:placetype":"venue"
},
  "geometry": {"coordinates":[-74.353072,40.197135],"type":"Point"}
}