{
  "type": "Feature",
  "properties": {
    "iso:country":"US",
    "sg:address":"80 Montgomery Ave",
    "sg:city":"Long Branch",
    "sg:classifiers":[
        {
            "category":"Restaurant",
            "type":"Food & Drink"
        }
    ],
    "sg:menulink":"http://www.allmenus.com/nj/long-branch/18101-ming-ying/menu/",
    "sg:phone":"+1 732 728 0088",
    "sg:postcode":"07740",
    "sg:province":"NJ",
    "sg:tags":[
        "asian",
        "chinese"
    ],
    "wof:name":"Ming Ying",
    "wof:placetype":"venue"
},
  "geometry": {"coordinates":[-73.98558300000001,40.284951],"type":"Point"}
}