{
  "type": "Feature",
  "properties": {
    "iso:country":"US",
    "sg:address":"3 Boyle Rd Ste 1",
    "sg:city":"Selden",
    "sg:classifiers":[
        {
            "category":"Personal",
            "subcategory":"Day Spa",
            "type":"Services"
        }
    ],
    "sg:phone":"+1 631 696 2424",
    "sg:postcode":"11784",
    "sg:province":"NY",
    "wof:name":"Spa Exotique",
    "wof:placetype":"venue"
},
  "geometry": {"coordinates":[-73.952401,40.865724],"type":"Point"}
}