{
  "type": "Feature",
  "properties": {
    "addr:full":"1701 Salem Rd Burlington NJ 08016",
    "addr:housenumber":"1701",
    "addr:postcode":"08016",
    "addr:street":"Salem Rd",
    "iso:country":"US",
    "sg:address":"1701 Salem Rd",
    "sg:city":"Burlington",
    "sg:classifiers":[
        {
            "category":"Real Estate",
            "subcategory":"Real Estate Operator",
            "type":"Services"
        }
    ],
    "sg:phone":"+1 609 387 1878",
    "sg:postcode":"08016",
    "sg:province":"NJ",
    "sg:tags":[
        "apartment"
    ],
    "wof:name":"Willow Pointe",
    "wof:placetype":"venue"
},
  "geometry": {"coordinates":[-74.869992,40.052015],"type":"Point"}
}