{
  "type": "Feature",
  "properties": {
    "addr:full":"9 Belaire Ln Englishtown NJ 07726",
    "addr:housenumber":"9",
    "addr:postcode":"07726",
    "addr:street":"Belaire Ln",
    "iso:country":"US",
    "sg:address":"9 Belaire Ln",
    "sg:city":"Englishtown",
    "sg:classifiers":[
        {
            "category":"Real Estate",
            "subcategory":"Real Estate Agent",
            "type":"Services"
        }
    ],
    "sg:phone":"+1   ",
    "sg:postcode":"07726",
    "sg:province":"NJ",
    "wof:name":"Jmp Properties Inc",
    "wof:placetype":"venue"
},
  "geometry": {"coordinates":[-74.31458600000001,40.299318],"type":"Point"}
}