{
  "type": "Feature",
  "properties": {
    "iso:country":"US",
    "sg:address":"274 Rosa Parks Blvd",
    "sg:city":"Paterson",
    "sg:classifiers":[
        {
            "category":"Food & Beverages",
            "subcategory":"Groceries & Convenience Stores",
            "type":"Retail Goods"
        }
    ],
    "sg:phone":"+1 973 881 8809",
    "sg:postcode":"07501",
    "sg:province":"NJ",
    "sg:tags":[
        "grocer"
    ],
    "wof:name":"Afr Supermarket",
    "wof:placetype":"venue"
},
  "geometry": {"coordinates":[-74.15909499999999,40.919967],"type":"Point"}
}