{
  "type": "Feature",
  "properties": {
    "iso:country":"US",
    "sg:address":"630 E Front St",
    "sg:city":"Plainfield",
    "sg:classifiers":[
        {
            "category":"Education",
            "subcategory":"School",
            "type":"Public Place"
        }
    ],
    "sg:phone":"+1   ",
    "sg:postcode":"07060",
    "sg:province":"NJ",
    "sg:tags":[
        "lutheran"
    ],
    "wof:name":"Messiah Lutheran School",
    "wof:placetype":"venue"
},
  "geometry": {"coordinates":[-74.41566400000001,40.62737],"type":"Point"}
}