{
  "type": "Feature",
  "properties": {
    "addr:full":"402 Boulevard Westfield NJ 07090",
    "addr:housenumber":"402",
    "addr:postcode":"07090",
    "addr:street":"Boulevard",
    "iso:country":"US",
    "sg:address":"402 Boulevard",
    "sg:city":"Westfield",
    "sg:classifiers":[
        {
            "category":"Health Services",
            "subcategory":"Clinic",
            "type":"Services"
        }
    ],
    "sg:phone":"+1 908 233 2110",
    "sg:postcode":"07090",
    "sg:province":"NJ",
    "sg:tags":[
        "holistic",
        "practitioner"
    ],
    "wof:name":"Westfield Nature Therapy",
    "wof:placetype":"venue"
},
  "geometry": {"coordinates":[-74.345473,40.648353],"type":"Point"}
}