{
  "type": "Feature",
  "properties": {
    "iso:country":"US",
    "sg:address":"360 Main St",
    "sg:city":"Matawan",
    "sg:classifiers":[
        {
            "category":"Home & Garden",
            "subcategory":"Building Materials",
            "type":"Retail Goods"
        }
    ],
    "sg:phone":"+1   ",
    "sg:postcode":"07747",
    "sg:province":"NJ",
    "wof:name":"Jaeger Lumber Co",
    "wof:placetype":"venue"
},
  "geometry": {"coordinates":[-74.237195,40.405141],"type":"Point"}
}