{
  "type": "Feature",
  "properties": {
    "iso:country":"US",
    "sg:address":"194 Fries Mill Rd",
    "sg:city":"Blackwood",
    "sg:classifiers":[
        {
            "category":"Restaurant",
            "type":"Food & Drink"
        }
    ],
    "sg:phone":"+1   ",
    "sg:postcode":"08012",
    "sg:province":"NJ",
    "sg:tags":[
        "personal",
        "eating"
    ],
    "wof:name":"Renaissance Catering",
    "wof:placetype":"venue"
},
  "geometry": {"coordinates":[-75.048737,39.732205],"type":"Point"}
}