{
  "type": "Feature",
  "properties": {
    "addr:full":"36 Ashbrooke Dr Voorhees NJ 08043",
    "addr:housenumber":"36",
    "addr:postcode":"08043",
    "addr:street":"Ashbrooke Dr",
    "iso:country":"US",
    "sg:address":"36 Ashbrooke Dr",
    "sg:city":"Voorhees",
    "sg:classifiers":[
        {
            "category":"Wholesale",
            "subcategory":"Seafood",
            "type":"Manufacturing & Wholesale Goods"
        }
    ],
    "sg:phone":"+1 856 435 0442",
    "sg:postcode":"08043",
    "sg:province":"NJ",
    "wof:name":"Blue Ribbon Smoked Fish Inc",
    "wof:placetype":"venue"
},
  "geometry": {"coordinates":[-74.940387,39.841545],"type":"Point"}
}