{
  "type": "Feature",
  "properties": {
    "addr:full":"12 Beech St Belleville NJ 07109",
    "addr:housenumber":"12",
    "addr:postcode":"07109",
    "addr:street":"Beech St",
    "iso:country":"US",
    "sg:address":"12 Beech St",
    "sg:city":"Belleville",
    "sg:classifiers":[
        {
            "category":"Shopping",
            "subcategory":"Gifts & Souvenirs",
            "type":"Retail Goods"
        }
    ],
    "sg:phone":"+1   ",
    "sg:postcode":"07109",
    "sg:province":"NJ",
    "wof:name":"Figurines & Things",
    "wof:placetype":"venue"
},
  "geometry": {"coordinates":[-74.149795,40.798967],"type":"Point"}
}