{
  "type": "Feature",
  "properties": {
    "iso:country":"US",
    "sg:address":"8275 N Crescent Blvd",
    "sg:city":"Pennsauken",
    "sg:classifiers":[
        {
            "category":"Professional",
            "subcategory":"Management & Consulting",
            "type":"Services"
        }
    ],
    "sg:phone":"+1   ",
    "sg:postcode":"08110",
    "sg:province":"NJ",
    "sg:tags":[
        "retail",
        "direct",
        "sales"
    ],
    "wof:name":"Vintage Spring Wter-Pepsi-Cola",
    "wof:placetype":"venue"
},
  "geometry": {"coordinates":[-75.031398,39.977014],"type":"Point"}
}