{
  "type": "Feature",
  "properties": {
    "addr:full":"23 Brier Rd Whitehouse Sta NJ 08889",
    "addr:housenumber":"23",
    "addr:postcode":"08889",
    "addr:street":"Brier Rd",
    "iso:country":"US",
    "sg:address":"23 Brier Rd",
    "sg:city":"Whitehouse Sta",
    "sg:classifiers":[
        {
            "category":"Recreation",
            "type":"Entertainment"
        }
    ],
    "sg:phone":"+1 908 534 8833",
    "sg:postcode":"08889",
    "sg:province":"NJ",
    "sg:tags":[
        "stable"
    ],
    "wof:name":"Briarwood Farm",
    "wof:placetype":"venue"
},
  "geometry": {"coordinates":[-74.790755,40.580061],"type":"Point"}
}