{
  "type": "Feature",
  "properties": {
    "addr:full":"1 Arch Ave Secaucus NJ 07094",
    "addr:housenumber":"1",
    "addr:postcode":"07094",
    "addr:street":"Arch Ave",
    "iso:country":"US",
    "sg:address":"1 Arch Ave",
    "sg:city":"Secaucus",
    "sg:classifiers":[
        {
            "category":"Freight",
            "type":"Transportation"
        }
    ],
    "sg:phone":"+1 201 319 0874",
    "sg:postcode":"07094",
    "sg:province":"NJ",
    "sg:tags":[
        "operator",
        "local",
        "trucking"
    ],
    "wof:name":"Rivera Son Trucking",
    "wof:placetype":"venue"
},
  "geometry": {"coordinates":[-74.055595,40.799684],"type":"Point"}
}