{
  "type": "Feature",
  "properties": {
    "iso:country":"US",
    "sg:address":"237 W Union Ave",
    "sg:city":"Bound Brook",
    "sg:classifiers":[
        {
            "category":"Home & Garden",
            "subcategory":"Garden Supply",
            "type":"Retail Goods"
        }
    ],
    "sg:phone":"+1   ",
    "sg:postcode":"08805",
    "sg:province":"NJ",
    "sg:tags":[
        "a",
        "lawnmowers",
        "repairer"
    ],
    "wof:name":"Lawn Mower Shop Inc",
    "wof:placetype":"venue"
},
  "geometry": {"coordinates":[-74.54066400000001,40.567454],"type":"Point"}
}