{
  "type": "Feature",
  "properties": {
    "iso:country":"US",
    "sg:address":"9 Lamont Ave",
    "sg:city":"Trenton",
    "sg:classifiers":[
        {
            "category":"Professional",
            "type":"Services"
        }
    ],
    "sg:phone":"+1 609 890 6314",
    "sg:postcode":"08619",
    "sg:province":"NJ",
    "sg:tags":[
        "establishment"
    ],
    "wof:name":"Moderate Income Management Co",
    "wof:placetype":"venue"
},
  "geometry": {"coordinates":[-74.69088600000001,40.224837],"type":"Point"}
}