{
  "type": "Feature",
  "properties": {
    "iso:country":"US",
    "sg:address":"1 Partridge Run",
    "sg:city":"Warren",
    "sg:classifiers":[
        {
            "category":"Building & Trades",
            "subcategory":"Construction",
            "type":"Services"
        }
    ],
    "sg:phone":"+1 732 469 5178",
    "sg:postcode":"07059",
    "sg:province":"NJ",
    "sg:tags":[
        "house"
    ],
    "wof:name":"Gkg Electrical Contracting",
    "wof:placetype":"venue"
},
  "geometry": {"coordinates":[-74.552887,40.616488],"type":"Point"}
}