{
  "type": "Feature",
  "properties": {
    "addr:full":"219 Broad St Elizabeth NJ 07201",
    "addr:housenumber":"219",
    "addr:postcode":"07201",
    "addr:street":"Broad St",
    "iso:country":"US",
    "sg:address":"219 Broad St",
    "sg:city":"Elizabeth",
    "sg:classifiers":[
        {
            "category":"Personal",
            "subcategory":"Beauty Salon",
            "type":"Services"
        }
    ],
    "sg:phone":"+1 908 558 9626",
    "sg:postcode":"07201",
    "sg:province":"NJ",
    "sg:tags":[
        "manicuring"
    ],
    "wof:name":"Lucky Nails",
    "wof:placetype":"venue"
},
  "geometry": {"coordinates":[-74.215098,40.666914],"type":"Point"}
}