{
  "type": "Feature",
  "properties": {
    "iso:country":"US",
    "sg:address":"116 S Harding Hwy",
    "sg:city":"Landisville",
    "sg:classifiers":[
        {
            "category":"Shopping",
            "subcategory":"Pharmacy",
            "type":"Retail Goods"
        }
    ],
    "sg:phone":"+1 856 697 1111",
    "sg:postcode":"08326",
    "sg:province":"NJ",
    "wof:name":"Matlack Pharmacy",
    "wof:placetype":"venue"
},
  "geometry": {"coordinates":[-74.93673699999999,39.523652],"type":"Point"}
}