{
  "type": "Feature",
  "properties": {
    "addr:full":"919 E Malaga Rd Williamstown NJ 08094",
    "addr:housenumber":"919",
    "addr:postcode":"08094",
    "addr:street":"E Malaga Rd",
    "iso:country":"US",
    "sg:address":"919 E Malaga Rd",
    "sg:city":"Williamstown",
    "sg:classifiers":[
        {
            "category":"Professional",
            "type":"Services"
        }
    ],
    "sg:phone":"+1   ",
    "sg:postcode":"08094",
    "sg:province":"NJ",
    "wof:name":"Ms Shirley Davis",
    "wof:placetype":"venue"
},
  "geometry": {"coordinates":[-74.952629,39.678042],"type":"Point"}
}