{
  "type": "Feature",
  "properties": {
    "addr:full":"53 Lexington Ave Passaic NJ 07055",
    "addr:housenumber":"53",
    "addr:postcode":"07055",
    "addr:street":"Lexington Ave",
    "iso:country":"US",
    "sg:address":"53 Lexington Ave",
    "sg:city":"Passaic",
    "sg:classifiers":[
        {
            "category":"Shopping",
            "subcategory":"Books",
            "type":"Retail Goods"
        }
    ],
    "sg:phone":"+1 973 777 6458",
    "sg:postcode":"07055",
    "sg:province":"NJ",
    "sg:tags":[
        "bookstore"
    ],
    "wof:name":"Best Adult Book Store",
    "wof:placetype":"venue"
},
  "geometry": {"coordinates":[-74.12750200000001,40.864498],"type":"Point"}
}