{
  "type": "Feature",
  "properties": {
    "addr:full":"302 S Black Horse Pike Blackwood NJ 08012",
    "addr:housenumber":"302",
    "addr:postcode":"08012",
    "addr:street":"S Black Horse Pike",
    "iso:country":"US",
    "sg:address":"302 S Black Horse Pike",
    "sg:city":"Blackwood",
    "sg:classifiers":[
        {
            "category":"Autos & Motor Vehicles",
            "subcategory":"Fuel & Gas Station",
            "type":"Retail Goods"
        }
    ],
    "sg:phone":"+1   ",
    "sg:postcode":"08012",
    "sg:province":"NJ",
    "sg:tags":[
        "station",
        "gasoline"
    ],
    "wof:name":"Citgo",
    "wof:placetype":"venue"
},
  "geometry": {"coordinates":[-75.064016,39.796554],"type":"Point"}
}