{
  "type": "Feature",
  "properties": {
    "iso:country":"US",
    "sg:address":"359 96th St",
    "sg:city":"Stone Harbor",
    "sg:classifiers":[
        {
            "category":"Professional",
            "subcategory":"Lawyer & Legal Services",
            "type":"Services"
        },
        {
            "category":"Professional",
            "subcategory":"Management & Consulting",
            "type":"Services"
        }
    ],
    "sg:phone":"+1 609 368 6400",
    "sg:postcode":"08247",
    "sg:province":"NJ",
    "sg:tags":[
        "planning",
        "estate"
    ],
    "wof:name":"Lane Financial & Estate P",
    "wof:placetype":"venue"
},
  "geometry": {"coordinates":[-74.763094,39.055635],"type":"Point"}
}