{
  "type": "Feature",
  "properties": {
    "addr:full":"37 Koeck Rd Columbia NJ 07832",
    "addr:housenumber":"37",
    "addr:postcode":"07832",
    "addr:street":"Koeck Rd",
    "iso:country":"US",
    "sg:address":"37 Koeck Rd",
    "sg:city":"Columbia",
    "sg:classifiers":[
        {
            "category":"Building & Trades",
            "subcategory":"Construction",
            "type":"Services"
        }
    ],
    "sg:phone":"+1 908 459 0477",
    "sg:postcode":"07832",
    "sg:province":"NJ",
    "sg:tags":[
        "residential"
    ],
    "wof:name":"Casa Country Homes Inc",
    "wof:placetype":"venue"
},
  "geometry": {"coordinates":[-75.031633,40.896633],"type":"Point"}
}