{
  "type": "Feature",
  "properties": {
    "iso:country":"US",
    "sg:address":"1260 State Rte 28",
    "sg:city":"Somerville",
    "sg:classifiers":[
        {
            "category":"Food & Beverages",
            "subcategory":"Bakery",
            "type":"Retail Goods"
        }
    ],
    "sg:phone":"+1 908 927 9988",
    "sg:postcode":"08876",
    "sg:province":"NJ",
    "sg:tags":[
        "bagel"
    ],
    "wof:name":"Bagels 4u of Lamington",
    "wof:placetype":"venue"
},
  "geometry": {"coordinates":[-74.696652,40.606589],"type":"Point"}
}