{
  "type": "Feature",
  "properties": {
    "iso:country":"US",
    "sg:address":"966 Park Blvd",
    "sg:city":"Cherry Hill",
    "sg:classifiers":[
        {
            "category":"Professional",
            "subcategory":"Computer Services",
            "type":"Services"
        }
    ],
    "sg:phone":"+1   ",
    "sg:postcode":"08002",
    "sg:province":"NJ",
    "wof:name":"Calderwood Computer Service",
    "wof:placetype":"venue"
},
  "geometry": {"coordinates":[-75.044546,39.921645],"type":"Point"}
}