{
  "type": "Feature",
  "properties": {
    "addr:full":"71 US Highway 46 Elmwood Park NJ 07407",
    "addr:housenumber":"71",
    "addr:postcode":"07407",
    "addr:street":"Us Highway 46",
    "iso:country":"US",
    "sg:address":"71 US Highway 46",
    "sg:city":"Elmwood Park",
    "sg:classifiers":[
        {
            "category":"Deli",
            "type":"Food & Drink"
        }
    ],
    "sg:phone":"+1 201 703 9696",
    "sg:postcode":"07407",
    "sg:province":"NJ",
    "wof:name":"Cuchi Deli & Pizza",
    "wof:placetype":"venue"
},
  "geometry": {"coordinates":[-74.1241,40.893398],"type":"Point"}
}