{
  "type": "Feature",
  "properties": {
    "iso:country":"US",
    "sg:address":"73 S Broad St",
    "sg:city":"Elizabeth",
    "sg:classifiers":[
        {
            "category":"Shopping",
            "subcategory":"Clothing, Apparel, & Fashions",
            "type":"Retail Goods"
        }
    ],
    "sg:phone":"+1 908 355 6866",
    "sg:postcode":"07202",
    "sg:province":"NJ",
    "wof:name":"73 Broad Clothing Corp",
    "wof:placetype":"venue"
},
  "geometry": {"coordinates":[-74.215306,40.660468],"type":"Point"}
}