{
  "type": "Feature",
  "properties": {
    "iso:country":"US",
    "sg:address":"26 Wilkins Ave",
    "sg:city":"Haddonfield",
    "sg:classifiers":[
        {
            "category":"Education",
            "subcategory":"School",
            "type":"Public Place"
        }
    ],
    "sg:phone":"+1 856 216 2918",
    "sg:postcode":"08033",
    "sg:province":"NJ",
    "wof:name":"Center For Networks and Education",
    "wof:placetype":"venue"
},
  "geometry": {"coordinates":[-75.03600299999999,39.898102],"type":"Point"}
}