{
  "type": "Feature",
  "properties": {
    "addr:full":"102 E Clements Bridge Rd Runnemede NJ 08078",
    "addr:housenumber":"102",
    "addr:postcode":"08078",
    "addr:street":"E Clements Bridge Rd",
    "iso:country":"US",
    "sg:address":"102 E Clements Bridge Rd",
    "sg:city":"Runnemede",
    "sg:classifiers":[
        {
            "category":"Shopping",
            "subcategory":"Gifts & Souvenirs",
            "type":"Retail Goods"
        }
    ],
    "sg:phone":"+1 856 312 0016",
    "sg:postcode":"08078",
    "sg:province":"NJ",
    "sg:tags":[
        "shop"
    ],
    "wof:name":"Plum Tree",
    "wof:placetype":"venue"
},
  "geometry": {"coordinates":[-75.071091,39.850029],"type":"Point"}
}