{
  "type": "Feature",
  "properties": {
    "iso:country":"US",
    "sg:address":"153 Passaic St",
    "sg:city":"Garfield",
    "sg:classifiers":[
        {
            "category":"Retail",
            "subcategory":"Repair Shop",
            "type":"Services"
        }
    ],
    "sg:phone":"+1 973 594 8200",
    "sg:postcode":"07026",
    "sg:province":"NJ",
    "sg:tags":[
        "auto",
        "rewinding",
        "armature"
    ],
    "wof:name":"Danco Motors Inc",
    "wof:placetype":"venue"
},
  "geometry": {"coordinates":[-74.1026,40.8675],"type":"Point"}
}