{
  "type": "Feature",
  "properties": {
    "iso:country":"US",
    "sg:address":"14 S 2nd Ave",
    "sg:city":"Highland Park",
    "sg:classifiers":[
        {
            "category":"Retail",
            "subcategory":"Laundry & Dry Cleaning",
            "type":"Services"
        }
    ],
    "sg:phone":"+1 732 249 7379",
    "sg:postcode":"08904",
    "sg:province":"NJ",
    "sg:tags":[
        "cleaners"
    ],
    "wof:name":"Al's Dry Cleaners",
    "wof:placetype":"venue"
},
  "geometry": {"coordinates":[-74.42986500000001,40.497339],"type":"Point"}
}