{
  "type": "Feature",
  "properties": {
    "addr:full":"436 Main St Hackensack NJ 07601",
    "addr:housenumber":"436",
    "addr:postcode":"07601",
    "addr:street":"Main St",
    "iso:country":"US",
    "sg:address":"436 Main St",
    "sg:city":"Hackensack",
    "sg:classifiers":[
        {
            "category":"Shopping",
            "subcategory":"Department Store",
            "type":"Retail Goods"
        }
    ],
    "sg:phone":"+1 201 525 5200",
    "sg:postcode":"07601",
    "sg:province":"NJ",
    "sg:website":"www.sears.com",
    "wof:name":"Sears Roebuck and Co",
    "wof:placetype":"venue"
},
  "geometry": {"coordinates":[-74.039497,40.8922],"type":"Point"}
}