{
  "type": "Feature",
  "properties": {
    "addr:full":"244 Main St Chatham NJ 07928",
    "addr:housenumber":"244",
    "addr:postcode":"07928",
    "addr:street":"Main St",
    "iso:country":"US",
    "sg:address":"244 Main St",
    "sg:city":"Chatham",
    "sg:classifiers":[
        {
            "category":"Social Services",
            "type":"Services"
        }
    ],
    "sg:phone":"+1   ",
    "sg:postcode":"07928",
    "sg:province":"NJ",
    "wof:name":"Counseling Associates",
    "wof:placetype":"venue"
},
  "geometry": {"coordinates":[-74.382766,40.740807],"type":"Point"}
}