{
  "type": "Feature",
  "properties": {
    "iso:country":"US",
    "sg:address":"32 Windsor Dr",
    "sg:city":"Pine Brook",
    "sg:classifiers":[
        {
            "category":"Communications",
            "subcategory":"Film & Video Production",
            "type":"Services"
        }
    ],
    "sg:phone":"+1 973 808 0354",
    "sg:postcode":"07058",
    "sg:province":"NJ",
    "sg:tags":[
        "motion"
    ],
    "wof:name":"Haywire Productions",
    "wof:placetype":"venue"
},
  "geometry": {"coordinates":[-74.341965,40.870689],"type":"Point"}
}