{
  "type": "Feature",
  "properties": {
    "iso:country":"US",
    "sg:address":"45 Karen Pl",
    "sg:city":"Edison",
    "sg:classifiers":[
        {
            "category":"Professional",
            "subcategory":"Computer Services",
            "type":"Services"
        }
    ],
    "sg:phone":"+1   ",
    "sg:postcode":"08817",
    "sg:province":"NJ",
    "sg:tags":[
        "development",
        "creates",
        "software",
        "page",
        "web"
    ],
    "wof:name":"Cybermatics Inc",
    "wof:placetype":"venue"
},
  "geometry": {"coordinates":[-74.38871899999999,40.543653],"type":"Point"}
}