{
  "type": "Feature",
  "properties": {
    "addr:full":"98 Gotthardt St Newark NJ 07105",
    "addr:housenumber":"98",
    "addr:postcode":"07105",
    "addr:street":"Gotthardt St",
    "iso:country":"US",
    "sg:address":"98 Gotthardt St",
    "sg:city":"Newark",
    "sg:classifiers":[
        {
            "category":"Building & Trades",
            "subcategory":"Construction",
            "type":"Services"
        }
    ],
    "sg:phone":"+1 973 344 7011",
    "sg:postcode":"07105",
    "sg:province":"NJ",
    "sg:tags":[
        "floor",
        "laying",
        "contractor"
    ],
    "wof:name":"Hardwood Floors Corp",
    "wof:placetype":"venue"
},
  "geometry": {"coordinates":[-74.15026899999999,40.722438],"type":"Point"}
}