{
  "type": "Feature",
  "properties": {
    "iso:country":"US",
    "sg:address":"614 Frank E Rodgers Blvd S",
    "sg:city":"Harrison",
    "sg:classifiers":[
        {
            "category":"Building & Trades",
            "subcategory":"Construction",
            "type":"Services"
        }
    ],
    "sg:phone":"+1 973 481 0418",
    "sg:postcode":"07029",
    "sg:province":"NJ",
    "sg:tags":[
        "house"
    ],
    "wof:name":"Construction Jimenez",
    "wof:placetype":"venue"
},
  "geometry": {"coordinates":[-74.15572899999999,40.741496],"type":"Point"}
}