{
  "type": "Feature",
  "properties": {
    "iso:country":"US",
    "sg:address":"37 School St",
    "sg:city":"Califon",
    "sg:classifiers":[
        {
            "category":"Professional",
            "subcategory":"Accounting & Tax Preparation",
            "type":"Services"
        }
    ],
    "sg:phone":"+1 908 832 5273",
    "sg:postcode":"07830",
    "sg:province":"NJ",
    "sg:tags":[
        "accountant"
    ],
    "wof:name":"Murray James M CPA",
    "wof:placetype":"venue"
},
  "geometry": {"coordinates":[-74.841499,40.7253],"type":"Point"}
}