{
  "type": "Feature",
  "properties": {
    "iso:country":"US",
    "sg:address":"302 Newark Ave",
    "sg:city":"Jersey City",
    "sg:classifiers":[
        {
            "category":"Personal",
            "subcategory":"Barber",
            "type":"Services"
        }
    ],
    "sg:phone":"+1 201 795 0440",
    "sg:postcode":"07302",
    "sg:province":"NJ",
    "wof:name":"Quisqueya Barber Shop",
    "wof:placetype":"venue"
},
  "geometry": {"coordinates":[-74.050296,40.724037],"type":"Point"}
}