{
  "type": "Feature",
  "properties": {
    "iso:country":"US",
    "sg:address":"124 Marlton Pike E",
    "sg:city":"Cherry Hill",
    "sg:classifiers":[
        {
            "category":"Retail",
            "subcategory":"Laundry & Dry Cleaning",
            "type":"Services"
        }
    ],
    "sg:phone":"+1 856 429 5191",
    "sg:postcode":"08034",
    "sg:province":"NJ",
    "sg:tags":[
        "cleaners"
    ],
    "wof:name":"Barclay Cleaners",
    "wof:placetype":"venue"
},
  "geometry": {"coordinates":[-75.009439,39.913757],"type":"Point"}
}