{
  "type": "Feature",
  "properties": {
    "addr:full":"43 Valley Trl Oak Ridge NJ 07438",
    "addr:housenumber":"43",
    "addr:postcode":"07438",
    "addr:street":"Valley Trl",
    "iso:country":"US",
    "sg:address":"43 Valley Trl",
    "sg:city":"Oak Ridge",
    "sg:classifiers":[
        {
            "category":"Manufacturing",
            "subcategory":"Tools & Machinery",
            "type":"Manufacturing & Wholesale Goods"
        }
    ],
    "sg:phone":"+1 973 697 6673",
    "sg:postcode":"07438",
    "sg:province":"NJ",
    "sg:tags":[
        "designed",
        "built"
    ],
    "wof:name":"Jay Enterprises",
    "wof:placetype":"venue"
},
  "geometry": {"coordinates":[-74.53650500000001,40.986664],"type":"Point"}
}