{
  "type": "Feature",
  "properties": {
    "addr:full":"444 Grand St Paterson NJ 07505",
    "addr:housenumber":"444",
    "addr:postcode":"07505",
    "addr:street":"Grand St",
    "iso:country":"US",
    "sg:address":"444 Grand St",
    "sg:city":"Paterson",
    "sg:classifiers":[
        {
            "category":"Professional",
            "type":"Services"
        }
    ],
    "sg:phone":"+1 973 278 1472",
    "sg:postcode":"07505",
    "sg:province":"NJ",
    "sg:tags":[
        "establishment"
    ],
    "wof:name":"RAM Mobile Data",
    "wof:placetype":"venue"
},
  "geometry": {"coordinates":[-74.169391,40.913031],"type":"Point"}
}