{
  "type": "Feature",
  "properties": {
    "iso:country":"US",
    "sg:address":"30 N Main St",
    "sg:city":"Milltown",
    "sg:classifiers":[
        {
            "category":"Restaurant",
            "type":"Food & Drink"
        }
    ],
    "sg:phone":"+1   ",
    "sg:postcode":"08850",
    "sg:province":"NJ",
    "sg:tags":[
        "eating"
    ],
    "wof:name":"Bergens Mill Cafe Inc",
    "wof:placetype":"venue"
},
  "geometry": {"coordinates":[-74.438312,40.451464],"type":"Point"}
}