{
  "type": "Feature",
  "properties": {
    "iso:country":"US",
    "sg:address":"69 Orchard St",
    "sg:city":"Ramsey",
    "sg:classifiers":[
        {
            "category":"Wholesale",
            "subcategory":"Apparel",
            "type":"Manufacturing & Wholesale Goods"
        }
    ],
    "sg:phone":"+1 201 785 9200",
    "sg:postcode":"07446",
    "sg:province":"NJ",
    "sg:tags":[
        "shoes"
    ],
    "wof:name":"Sudini Imports",
    "wof:placetype":"venue"
},
  "geometry": {"coordinates":[-74.139672,41.077062],"type":"Point"}
}