{
  "type": "Feature",
  "properties": {
    "iso:country":"US",
    "sg:address":"132 Perrineville Rd",
    "sg:city":"Jackson",
    "sg:classifiers":[
        {
            "category":"Professional",
            "subcategory":"Business Services",
            "type":"Services"
        }
    ],
    "sg:phone":"+1 732 833 7883",
    "sg:postcode":"08527",
    "sg:province":"NJ",
    "wof:name":"Vs Enterprise LLC",
    "wof:placetype":"venue"
},
  "geometry": {"coordinates":[-74.39116300000001,40.112716],"type":"Point"}
}