{
  "type": "Feature",
  "properties": {
    "iso:country":"US",
    "sg:address":"526 State Rte 17",
    "sg:city":"Ramsey",
    "sg:classifiers":[
        {
            "category":"Wholesale",
            "subcategory":"Electrical",
            "type":"Manufacturing & Wholesale Goods"
        }
    ],
    "sg:phone":"+1 201 995 0800",
    "sg:postcode":"07446",
    "sg:province":"NJ",
    "sg:tags":[
        "radio"
    ],
    "wof:name":"Paging Concepts",
    "wof:placetype":"venue"
},
  "geometry": {"coordinates":[-74.12116,41.057195],"type":"Point"}
}