{
  "type": "Feature",
  "properties": {
    "iso:country":"US",
    "sg:address":"306 N Union Ave",
    "sg:city":"Margate City",
    "sg:classifiers":[
        {
            "category":"Professional",
            "subcategory":"Accounting & Tax Preparation",
            "type":"Services"
        }
    ],
    "sg:phone":"+1 609 822 2189",
    "sg:postcode":"08402",
    "sg:province":"NJ",
    "sg:tags":[
        "bookkeeping",
        "general"
    ],
    "wof:name":"Business Outsourcing Svc",
    "wof:placetype":"venue"
},
  "geometry": {"coordinates":[-74.514627,39.328632],"type":"Point"}
}