{
  "type": "Feature",
  "properties": {
    "iso:country":"US",
    "sg:address":"132 Market St",
    "sg:city":"Perth Amboy",
    "sg:classifiers":[
        {
            "category":"Health Services",
            "subcategory":"Chiropractor",
            "type":"Services"
        }
    ],
    "sg:phone":"+1 732 826 8045",
    "sg:postcode":"08861",
    "sg:province":"NJ",
    "wof:name":"Gonzalez Chiropractic Center",
    "wof:placetype":"venue"
},
  "geometry": {"coordinates":[-74.26889799999999,40.507198],"type":"Point"}
}