{
  "type": "Feature",
  "properties": {
    "iso:country":"US",
    "sg:address":"523 Main St",
    "sg:city":"Bradley Beach",
    "sg:classifiers":[
        {
            "category":"Real Estate",
            "subcategory":"Real Estate Agent",
            "type":"Services"
        }
    ],
    "sg:phone":"+1   ",
    "sg:postcode":"07720",
    "sg:province":"NJ",
    "wof:name":"Better Homes and Gardens",
    "wof:placetype":"venue"
},
  "geometry": {"coordinates":[-74.018106,40.202878],"type":"Point"}
}