{
  "type": "Feature",
  "properties": {
    "iso:country":"US",
    "sg:address":"1763 John F Kennedy Blvd",
    "sg:city":"Jersey City",
    "sg:classifiers":[
        {
            "category":"Cinema",
            "subcategory":"Movie Rental",
            "type":"Entertainment"
        }
    ],
    "sg:phone":"+1 201 433 8866",
    "sg:postcode":"07305",
    "sg:province":"NJ",
    "sg:tags":[
        "leasing",
        "video",
        "disc",
        "tape"
    ],
    "wof:name":"Kings Video",
    "wof:placetype":"venue"
},
  "geometry": {"coordinates":[-74.093287,40.701157],"type":"Point"}
}