{
  "type": "Feature",
  "properties": {
    "addr:full":"110 Mt Vernon St Ridgefield Park NJ 07660",
    "addr:housenumber":"110",
    "addr:postcode":"07660",
    "addr:street":"Mt Vernon St",
    "iso:country":"US",
    "sg:address":"110 Mt Vernon St",
    "sg:city":"Ridgefield Park",
    "sg:classifiers":[
        {
            "category":"Education",
            "subcategory":"School",
            "type":"Public Place"
        }
    ],
    "sg:phone":"+1 201 641 9159",
    "sg:postcode":"07660",
    "sg:province":"NJ",
    "sg:tags":[
        "high",
        "middle",
        "elementary"
    ],
    "wof:name":"St Francis School",
    "wof:placetype":"venue"
},
  "geometry": {"coordinates":[-74.02330000000001,40.856098],"type":"Point"}
}