{
  "type": "Feature",
  "properties": {
    "iso:country":"US",
    "sg:address":"75 Reigate Rd",
    "sg:city":"Bloomfield",
    "sg:classifiers":[
        {
            "category":"Arena",
            "subcategory":"Sports Club",
            "type":"Entertainment"
        }
    ],
    "sg:phone":"+1 973 338 6062",
    "sg:postcode":"07003",
    "sg:province":"NJ",
    "wof:name":"Newark Bears Pro Baseball",
    "wof:placetype":"venue"
},
  "geometry": {"coordinates":[-74.170062,40.83305],"type":"Point"}
}