{
  "type": "Feature",
  "properties": {
    "iso:country":"US",
    "sg:address":"219 Changebridge Rd",
    "sg:city":"Montville",
    "sg:classifiers":[
        {
            "category":"Professional",
            "type":"Services"
        }
    ],
    "sg:phone":"+1 973 541 1815",
    "sg:postcode":"07045",
    "sg:province":"NJ",
    "sg:tags":[
        "establishment"
    ],
    "wof:name":"Anti-Aging Solutions",
    "wof:placetype":"venue"
},
  "geometry": {"coordinates":[-74.362686,40.87829],"type":"Point"}
}