{
  "type": "Feature",
  "properties": {
    "iso:country":"US",
    "sg:address":"67 Greylock Ave",
    "sg:city":"Belleville",
    "sg:classifiers":[
        {
            "category":"Manufacturing",
            "subcategory":"Tools & Machinery",
            "type":"Manufacturing & Wholesale Goods"
        }
    ],
    "sg:phone":"+1 973 751 0789",
    "sg:postcode":"07109",
    "sg:province":"NJ",
    "sg:tags":[
        "machine",
        "shop"
    ],
    "sg:website":"www.bmmachine.com",
    "wof:name":"B & M Machine Co",
    "wof:placetype":"venue"
},
  "geometry": {"coordinates":[-74.142325,40.799344],"type":"Point"}
}