{
  "type": "Feature",
  "properties": {
    "iso:country":"US",
    "sg:address":"1215 Harrison Ave",
    "sg:city":"Kearny",
    "sg:classifiers":[
        {
            "category":"Restaurant",
            "type":"Food & Drink"
        }
    ],
    "sg:menulink":"http://www.allmenus.com/nj/kearny/145973-subway/menu/",
    "sg:phone":"+1 201 998 3511",
    "sg:postcode":"07032",
    "sg:province":"NJ",
    "sg:tags":[
        "american",
        "sandwich"
    ],
    "wof:name":"Subway",
    "wof:placetype":"venue"
},
  "geometry": {"coordinates":[-74.137336,40.749299],"type":"Point"}
}