{
  "type": "Feature",
  "properties": {
    "addr:full":"1632 Route 38 Ste 1 Lumberton NJ 08048",
    "addr:housenumber":"1632",
    "addr:postcode":"08048",
    "addr:street":"Route 38 Ste 1",
    "iso:country":"US",
    "sg:address":"1632 Route 38 Ste 1",
    "sg:city":"Lumberton",
    "sg:classifiers":[
        {
            "category":"Social Services",
            "type":"Services"
        }
    ],
    "sg:phone":"+1 609 267 9595",
    "sg:postcode":"08048",
    "sg:province":"NJ",
    "sg:website":"http://www.redcross.org",
    "wof:name":"Red Cross",
    "wof:placetype":"venue"
},
  "geometry": {"coordinates":[-74.78668399999999,39.982232],"type":"Point"}
}