{
  "type": "Feature",
  "properties": {
    "addr:full":"24A Ave At Port Imperial West New York NJ 07093",
    "addr:housenumber":"24a",
    "addr:postcode":"07093",
    "addr:street":"Ave At Port Imperial West",
    "iso:country":"US",
    "sg:address":"24A Ave At Port Imperial",
    "sg:city":"West New York",
    "sg:classifiers":[
        {
            "category":"Real Estate",
            "subcategory":"Real Estate Operator",
            "type":"Services"
        }
    ],
    "sg:phone":"+1 201 863 4900",
    "sg:postcode":"07093",
    "sg:province":"NJ",
    "sg:tags":[
        "apartment"
    ],
    "wof:name":"Riverside West",
    "wof:placetype":"venue"
},
  "geometry": {"coordinates":[-74.00771,40.781023],"type":"Point"}
}