{
  "type": "Feature",
  "properties": {
    "addr:full":"19 Gould Ave Paterson NJ 07503",
    "addr:housenumber":"19",
    "addr:postcode":"07503",
    "addr:street":"Gould Ave",
    "iso:country":"US",
    "sg:address":"19 Gould Ave",
    "sg:city":"Paterson",
    "sg:classifiers":[
        {
            "category":"Food & Beverages",
            "subcategory":"Candy",
            "type":"Retail Goods"
        }
    ],
    "sg:phone":"+1 973 742 1084",
    "sg:postcode":"07503",
    "sg:province":"NJ",
    "sg:tags":[
        "confectionery"
    ],
    "wof:name":"Budget Soda Market",
    "wof:placetype":"venue"
},
  "geometry": {"coordinates":[-74.16062599999999,40.893021],"type":"Point"}
}