{
  "type": "Feature",
  "properties": {
    "iso:country":"US",
    "sg:address":"914 Amsterdam Ave",
    "sg:city":"Roselle",
    "sg:classifiers":[
        {
            "category":"Building & Trades",
            "subcategory":"Equipment Rental",
            "type":"Services"
        }
    ],
    "sg:phone":"+1 908 298 1770",
    "sg:postcode":"07203",
    "sg:province":"NJ",
    "sg:tags":[
        "crane"
    ],
    "wof:name":"Crane Builders",
    "wof:placetype":"venue"
},
  "geometry": {"coordinates":[-74.281013,40.650035],"type":"Point"}
}