{
  "type": "Feature",
  "properties": {
    "addr:full":"7447 Maple Ave Pennsauken NJ 08109",
    "addr:housenumber":"7447",
    "addr:postcode":"08109",
    "addr:street":"Maple Ave",
    "iso:country":"US",
    "sg:address":"7447 Maple Ave",
    "sg:city":"Pennsauken",
    "sg:classifiers":[
        {
            "category":"Building & Trades",
            "subcategory":"Locksmith",
            "type":"Services"
        }
    ],
    "sg:phone":"+1 856 532 0104",
    "sg:postcode":"08109",
    "sg:province":"NJ",
    "sg:tags":[
        "key"
    ],
    "wof:name":"All Day All Night Emergency Locksmith",
    "wof:placetype":"venue"
},
  "geometry": {"coordinates":[-75.032686,39.952302],"type":"Point"}
}