{
  "type": "Feature",
  "properties": {
    "iso:country":"US",
    "sg:address":"43 Maine St",
    "sg:city":"Toms River",
    "sg:classifiers":[
        {
            "category":"Arts & Performance",
            "subcategory":"Theater",
            "type":"Entertainment"
        }
    ],
    "sg:phone":"+1 732 818 9670",
    "sg:postcode":"08753",
    "sg:province":"NJ",
    "sg:tags":[
        "live",
        "music"
    ],
    "wof:name":"Majestic Entertainment",
    "wof:placetype":"venue"
},
  "geometry": {"coordinates":[-74.141831,40.010777],"type":"Point"}
}