{
  "type": "Feature",
  "properties": {
    "iso:country":"US",
    "sg:address":"555 Kemah Lake Rd",
    "sg:city":"Branchville",
    "sg:classifiers":[
        {
            "category":"Building & Trades",
            "subcategory":"Construction",
            "type":"Services"
        }
    ],
    "sg:phone":"+1 973 903 8370",
    "sg:postcode":"07826",
    "sg:province":"NJ",
    "sg:tags":[
        "house"
    ],
    "wof:name":"Kittatinny Ridge Construction",
    "wof:placetype":"venue"
},
  "geometry": {"coordinates":[-74.770518,41.138917],"type":"Point"}
}