{
  "type": "Feature",
  "properties": {
    "addr:full":"258 Main St Chatham NJ 07928",
    "addr:housenumber":"258",
    "addr:postcode":"07928",
    "addr:street":"Main St",
    "iso:country":"US",
    "sg:address":"258 Main St",
    "sg:city":"Chatham",
    "sg:classifiers":[
        {
            "category":"Shopping",
            "subcategory":"Jewelry",
            "type":"Retail Goods"
        }
    ],
    "sg:phone":"+1 973 635 0020",
    "sg:postcode":"07928",
    "sg:province":"NJ",
    "sg:tags":[
        "jeweler"
    ],
    "wof:name":"Classic Accessories",
    "wof:placetype":"venue"
},
  "geometry": {"coordinates":[-74.382698,40.740799],"type":"Point"}
}