{
  "type": "Feature",
  "properties": {
    "iso:country":"US",
    "sg:address":"22 Church St",
    "sg:city":"Ramsey",
    "sg:classifiers":[
        {
            "category":"Restaurant",
            "type":"Food & Drink"
        }
    ],
    "sg:phone":"+1 201 236 0283",
    "sg:postcode":"07446",
    "sg:province":"NJ",
    "sg:tags":[
        "chinese"
    ],
    "wof:name":"Ramsey Good Taste Restaurant",
    "wof:placetype":"venue"
},
  "geometry": {"coordinates":[-74.1417,41.058194],"type":"Point"}
}