{
  "type": "Feature",
  "properties": {
    "addr:full":"62 US Hwy 46 Lodi NJ 07644",
    "addr:housenumber":"62",
    "addr:postcode":"07644",
    "addr:street":"Us Hwy 46",
    "iso:country":"US",
    "sg:address":"62 US Hwy 46",
    "sg:city":"Lodi",
    "sg:classifiers":[
        {
            "category":"Autos & Motor Vehicles",
            "subcategory":"Automobile Sales",
            "type":"Retail Goods"
        }
    ],
    "sg:phone":"+1 973 471 0800",
    "sg:postcode":"07644",
    "sg:province":"NJ",
    "sg:tags":[
        "car",
        "dealer"
    ],
    "wof:name":"Eden Unique Auto LLC",
    "wof:placetype":"venue"
},
  "geometry": {"coordinates":[-74.079362,40.880131],"type":"Point"}
}