{
  "type": "Feature",
  "properties": {
    "iso:country":"US",
    "sg:address":"510 N Maple Ave",
    "sg:city":"Ridgewood",
    "sg:classifiers":[
        {
            "category":"Wholesale",
            "subcategory":"Medical Equipment & Supplies",
            "type":"Manufacturing & Wholesale Goods"
        }
    ],
    "sg:phone":"+1 201 670 6032",
    "sg:postcode":"07450",
    "sg:province":"NJ",
    "wof:name":"Houde Glass Co",
    "wof:placetype":"venue"
},
  "geometry": {"coordinates":[-74.111761,40.992848],"type":"Point"}
}