{
  "type": "Feature",
  "properties": {
    "iso:country":"US",
    "sg:address":"36 Rosedale Ave",
    "sg:city":"Saddle Brook",
    "sg:classifiers":[
        {
            "category":"Personal",
            "subcategory":"Beauty Salon",
            "type":"Services"
        }
    ],
    "sg:phone":"+1 201 291 9006",
    "sg:postcode":"07663",
    "sg:province":"NJ",
    "sg:tags":[
        "shop"
    ],
    "wof:name":"Alpha Electrolysis",
    "wof:placetype":"venue"
},
  "geometry": {"coordinates":[-74.08417300000001,40.893824],"type":"Point"}
}