{
  "type": "Feature",
  "properties": {
    "iso:country":"US",
    "sg:address":"11 Market St",
    "sg:city":"Somerset",
    "sg:classifiers":[
        {
            "category":"Professional",
            "subcategory":"Business Services",
            "type":"Services"
        },
        {
            "category":"Government",
            "subcategory":"Post Office",
            "type":"Public Place"
        }
    ],
    "sg:phone":"+1 800 275 8777",
    "sg:postcode":"08873",
    "sg:province":"NJ",
    "sg:tags":[
        "mail",
        "shipping"
    ],
    "sg:website":"http://www.usps.com",
    "wof:name":"USPS - United States Post Office - East Millstone Station",
    "wof:placetype":"venue"
},
  "geometry": {"coordinates":[-74.581914,40.50287],"type":"Point"}
}