{
  "type": "Feature",
  "properties": {
    "iso:country":"US",
    "sg:address":"660 Newark St",
    "sg:city":"Hoboken",
    "sg:classifiers":[
        {
            "category":"Retail",
            "subcategory":"Auto Repair",
            "type":"Services"
        }
    ],
    "sg:phone":"+1 201 420 1924",
    "sg:postcode":"07030",
    "sg:province":"NJ",
    "wof:name":"L & A Auto Body & Fender Repair",
    "wof:placetype":"venue"
},
  "geometry": {"coordinates":[-74.04239699999999,40.736301],"type":"Point"}
}