{
  "type": "Feature",
  "properties": {
    "addr:full":"8 Ward Witty Dr Montville NJ 07045",
    "addr:housenumber":"8",
    "addr:postcode":"07045",
    "addr:street":"Ward Witty Dr",
    "iso:country":"US",
    "sg:address":"8 Ward Witty Dr",
    "sg:city":"Montville",
    "sg:classifiers":[
        {
            "category":"Professional",
            "subcategory":"Lawyer & Legal Services",
            "type":"Services"
        }
    ],
    "sg:phone":"+1 973 335 4555",
    "sg:postcode":"07045",
    "sg:province":"NJ",
    "sg:tags":[
        "attorney"
    ],
    "wof:name":"Korduba George B ESQ",
    "wof:placetype":"venue"
},
  "geometry": {"coordinates":[-74.36309799999999,40.939201],"type":"Point"}
}