{
  "type": "Feature",
  "properties": {
    "addr:full":"211 N Main St Cape May Court House NJ 08210",
    "addr:housenumber":"211",
    "addr:postcode":"08210",
    "addr:street":"N Main St Cape May",
    "iso:country":"US",
    "sg:address":"211 N Main St",
    "sg:city":"Cape May Court House",
    "sg:classifiers":[
        {
            "category":"Professional",
            "subcategory":"Lawyer & Legal Services",
            "type":"Services"
        }
    ],
    "sg:phone":"+1   ",
    "sg:postcode":"08210",
    "sg:province":"NJ",
    "wof:name":"Monzo Anthony P",
    "wof:placetype":"venue"
},
  "geometry": {"coordinates":[-74.819855,39.086422],"type":"Point"}
}