{
  "type": "Feature",
  "properties": {
    "addr:full":"893 Edinburg Rd Trenton NJ 08690",
    "addr:housenumber":"893",
    "addr:postcode":"08690",
    "addr:street":"Edinburg Rd",
    "iso:country":"US",
    "sg:address":"893 Edinburg Rd",
    "sg:city":"Trenton",
    "sg:classifiers":[
        {
            "category":"Social Services",
            "subcategory":"Child Care",
            "type":"Services"
        }
    ],
    "sg:phone":"+1   ",
    "sg:postcode":"08690",
    "sg:province":"NJ",
    "sg:tags":[
        "day"
    ],
    "wof:name":"Edinburg Day School",
    "wof:placetype":"venue"
},
  "geometry": {"coordinates":[-74.667255,40.247664],"type":"Point"}
}