{
  "type": "Feature",
  "properties": {
    "addr:full":"968 Lorraine Ave Union NJ 07083",
    "addr:housenumber":"968",
    "addr:postcode":"07083",
    "addr:street":"Lorraine Ave",
    "iso:country":"US",
    "sg:address":"968 Lorraine Ave",
    "sg:city":"Union",
    "sg:classifiers":[
        {
            "category":"Building & Trades",
            "subcategory":"Cleaning & Sanitation",
            "type":"Services"
        }
    ],
    "sg:phone":"+1   ",
    "sg:postcode":"07083",
    "sg:province":"NJ",
    "sg:tags":[
        "maintenance"
    ],
    "wof:name":"Clear Cleaning Co",
    "wof:placetype":"venue"
},
  "geometry": {"coordinates":[-74.245639,40.688731],"type":"Point"}
}