{
  "type": "Feature",
  "properties": {
    "addr:full":"421 Bergen St Harrison NJ 07029",
    "addr:housenumber":"421",
    "addr:postcode":"07029",
    "addr:street":"Bergen St",
    "iso:country":"US",
    "sg:address":"421 Bergen St",
    "sg:city":"Harrison",
    "sg:classifiers":[
        {
            "category":"Banks & Credit Unions",
            "subcategory":"Bank",
            "type":"Services"
        }
    ],
    "sg:phone":"+1 973 412 1730",
    "sg:postcode":"07029",
    "sg:province":"NJ",
    "sg:tags":[
        "cashing",
        "check"
    ],
    "wof:name":"Harrison Check Cashing",
    "wof:placetype":"venue"
},
  "geometry": {"coordinates":[-74.154177,40.74319],"type":"Point"}
}