{
  "type": "Feature",
  "properties": {
    "addr:full":"10 Charles Ter Piscataway NJ 08854",
    "addr:housenumber":"10",
    "addr:postcode":"08854",
    "addr:street":"Charles Ter",
    "iso:country":"US",
    "sg:address":"10 Charles Ter",
    "sg:city":"Piscataway",
    "sg:classifiers":[
        {
            "category":"Shopping",
            "subcategory":"Discount & Variety Stores",
            "type":"Retail Goods"
        }
    ],
    "sg:phone":"+1 732 393 0098",
    "sg:postcode":"08854",
    "sg:province":"NJ",
    "sg:tags":[
        "merchandise",
        "general"
    ],
    "wof:name":"Dwanah International Trading",
    "wof:placetype":"venue"
},
  "geometry": {"coordinates":[-74.41951,40.544557],"type":"Point"}
}