{
  "type": "Feature",
  "properties": {
    "addr:full":"18 Industrial Ave Mahwah NJ 07430",
    "addr:housenumber":"18",
    "addr:postcode":"07430",
    "addr:street":"Industrial Ave",
    "iso:country":"US",
    "sg:address":"18 Industrial Ave",
    "sg:city":"Mahwah",
    "sg:classifiers":[
        {
            "category":"Wholesale",
            "subcategory":"Computers",
            "type":"Manufacturing & Wholesale Goods"
        },
        {
            "category":"Professional",
            "subcategory":"Computer Services",
            "type":"Services"
        }
    ],
    "sg:phone":"+1 201 529 5575",
    "sg:postcode":"07430",
    "sg:province":"NJ",
    "sg:tags":[
        "consultant",
        "peripheral",
        "designer",
        "software"
    ],
    "wof:name":"Odyssey Tek Nj LLC",
    "wof:placetype":"venue"
},
  "geometry": {"coordinates":[-74.142043,41.081524],"type":"Point"}
}