{
  "type": "Feature",
  "properties": {
    "iso:country":"US",
    "sg:address":"2 Northumberland Dr",
    "sg:city":"Mount Holly",
    "sg:classifiers":[
        {
            "category":"Health Services",
            "subcategory":"Chiropractor",
            "type":"Services"
        }
    ],
    "sg:phone":"+1 609 267 8040",
    "sg:postcode":"08060",
    "sg:province":"NJ",
    "sg:tags":[
        "physician"
    ],
    "wof:name":"Eastampton Chiropractic Center",
    "wof:placetype":"venue"
},
  "geometry": {"coordinates":[-74.769699,39.993801],"type":"Point"}
}