{
  "type": "Feature",
  "properties": {
    "iso:country":"US",
    "sg:address":"1039 S Orange Ave",
    "sg:city":"Newark",
    "sg:classifiers":[
        {
            "category":"Banks & Credit Unions",
            "subcategory":"Bank",
            "type":"Services"
        }
    ],
    "sg:phone":"+1   ",
    "sg:postcode":"07106",
    "sg:province":"NJ",
    "sg:tags":[
        "federal",
        "savings"
    ],
    "wof:name":"Gibraltar Savings Bank",
    "wof:placetype":"venue"
},
  "geometry": {"coordinates":[-74.23128,40.746376],"type":"Point"}
}