{
  "type": "Feature",
  "properties": {
    "iso:country":"US",
    "sg:address":"230 Hickory Ln",
    "sg:city":"Bayville",
    "sg:classifiers":[
        {
            "category":"Autos & Motor Vehicles",
            "subcategory":"Boat Sales",
            "type":"Retail Goods"
        }
    ],
    "sg:phone":"+1 732 269 2929",
    "sg:postcode":"08721",
    "sg:province":"NJ",
    "sg:tags":[
        "propeller"
    ],
    "wof:name":"J & B Marine Propeller Repair",
    "wof:placetype":"venue"
},
  "geometry": {"coordinates":[-74.168826,39.90794],"type":"Point"}
}