{
  "type": "Feature",
  "properties": {
    "addr:full":"2880 Hull Rd Camden NJ 08104",
    "addr:housenumber":"2880",
    "addr:postcode":"08104",
    "addr:street":"Hull Rd",
    "iso:country":"US",
    "sg:address":"2880 Hull Rd",
    "sg:city":"Camden",
    "sg:classifiers":[
        {
            "category":"Health Services",
            "subcategory":"Dentist",
            "type":"Services"
        }
    ],
    "sg:phone":"+1 856 966 1152",
    "sg:postcode":"08104",
    "sg:province":"NJ",
    "wof:name":"Dentist Information Service",
    "wof:placetype":"venue"
},
  "geometry": {"coordinates":[-75.101674,39.907694],"type":"Point"}
}