{
  "type": "Feature",
  "properties": {
    "addr:full":"709 E 9th St Ocean City NJ 08226",
    "addr:housenumber":"709",
    "addr:postcode":"08226",
    "addr:street":"E 9Th St",
    "iso:country":"US",
    "sg:address":"709 E 9th St",
    "sg:city":"Ocean City",
    "sg:classifiers":[
        {
            "category":"Restaurant",
            "type":"Food & Drink"
        }
    ],
    "sg:phone":"+1   ",
    "sg:postcode":"08226",
    "sg:province":"NJ",
    "sg:tags":[
        "eating"
    ],
    "wof:name":"Periwinkles",
    "wof:placetype":"venue"
},
  "geometry": {"coordinates":[-74.573809,39.277076],"type":"Point"}
}