{
  "type": "Feature",
  "properties": {
    "addr:full":"3 Chorister Pl Flemington NJ 08822",
    "addr:housenumber":"3",
    "addr:postcode":"08822",
    "addr:street":"Chorister Pl",
    "iso:country":"US",
    "sg:address":"3 Chorister Pl",
    "sg:city":"Flemington",
    "sg:classifiers":[
        {
            "category":"Government",
            "subcategory":"Office",
            "type":"Public Place"
        }
    ],
    "sg:phone":"+1 908 788 1256",
    "sg:postcode":"08822",
    "sg:province":"NJ",
    "sg:website":"www.co.hunterdon.nj.us",
    "wof:name":"Hunterdon Cultural & Heritage",
    "wof:placetype":"venue"
},
  "geometry": {"coordinates":[-74.857815,40.509843],"type":"Point"}
}