{
  "type": "Feature",
  "properties": {
    "iso:country":"US",
    "sg:address":"86 Lincoln Ter",
    "sg:city":"Harrington Park",
    "sg:classifiers":[
        {
            "category":"Real Estate",
            "subcategory":"Real Estate Agent",
            "type":"Services"
        }
    ],
    "sg:phone":"+1 201 767 3256",
    "sg:postcode":"07640",
    "sg:province":"NJ",
    "sg:tags":[
        "consultant"
    ],
    "wof:name":"Likim Enterprises",
    "wof:placetype":"venue"
},
  "geometry": {"coordinates":[-73.97878,40.994172],"type":"Point"}
}