{
  "type": "Feature",
  "properties": {
    "addr:full":"185 Industrial Pkwy Somerville NJ 08876",
    "addr:housenumber":"185",
    "addr:postcode":"08876",
    "addr:street":"Industrial Pkwy",
    "iso:country":"US",
    "sg:address":"185 Industrial Pkwy",
    "sg:city":"Somerville",
    "sg:classifiers":[
        {
            "category":"Wholesale",
            "subcategory":"Electrical",
            "type":"Manufacturing & Wholesale Goods"
        }
    ],
    "sg:phone":"+1 908 231 7777",
    "sg:postcode":"08876",
    "sg:province":"NJ",
    "sg:tags":[
        "distributor",
        "communication",
        "datum",
        "equipment"
    ],
    "wof:name":"ACR",
    "wof:placetype":"venue"
},
  "geometry": {"coordinates":[-74.708551,40.598292],"type":"Point"}
}