{
  "type": "Feature",
  "properties": {
    "iso:country":"US",
    "sg:address":"430 Mountain Ave",
    "sg:city":"Berkeley Heights",
    "sg:classifiers":[
        {
            "category":"Food & Beverages",
            "subcategory":"Groceries & Convenience Stores",
            "type":"Retail Goods"
        }
    ],
    "sg:phone":"+1   ",
    "sg:postcode":"07922",
    "sg:province":"NJ",
    "wof:name":"Montblanc Exec Sales & Mkt",
    "wof:placetype":"venue"
},
  "geometry": {"coordinates":[-74.42642600000001,40.670792],"type":"Point"}
}