{
  "type": "Feature",
  "properties": {
    "iso:country":"US",
    "sg:address":"23 Imperial Dr",
    "sg:city":"Egg Harbor Township",
    "sg:classifiers":[
        {
            "category":"Manufacturing",
            "subcategory":"Food",
            "type":"Manufacturing & Wholesale Goods"
        }
    ],
    "sg:phone":"+1 609 484 0665",
    "sg:postcode":"08234",
    "sg:province":"NJ",
    "sg:tags":[
        "desert",
        "ice",
        "mfg"
    ],
    "wof:name":"Creatacone",
    "wof:placetype":"venue"
},
  "geometry": {"coordinates":[-74.599492,39.408252],"type":"Point"}
}