{
  "type": "Feature",
  "properties": {
    "addr:full":"20 Fair Lawn Ave Fair Lawn NJ 07410",
    "addr:housenumber":"20",
    "addr:postcode":"07410",
    "addr:street":"Fair Lawn Ave",
    "iso:country":"US",
    "sg:address":"20 Fair Lawn Ave",
    "sg:city":"Fair Lawn",
    "sg:classifiers":[
        {
            "category":"Retail",
            "subcategory":"Auto Rental",
            "type":"Services"
        }
    ],
    "sg:phone":"+1 201 796 7789",
    "sg:postcode":"07410",
    "sg:province":"NJ",
    "sg:tags":[
        "renting",
        "automobile"
    ],
    "wof:name":"Hertz Rent A Car",
    "wof:placetype":"venue"
},
  "geometry": {"coordinates":[-74.12277400000001,40.938604],"type":"Point"}
}