{
  "type": "Feature",
  "properties": {
    "iso:country":"US",
    "sg:address":"132 Ferry St",
    "sg:city":"Newark",
    "sg:classifiers":[
        {
            "category":"Food & Beverages",
            "subcategory":"Groceries & Convenience Stores",
            "type":"Retail Goods"
        }
    ],
    "sg:phone":"+1   ",
    "sg:postcode":"07105",
    "sg:province":"NJ",
    "wof:name":"O & J Supermarket",
    "wof:placetype":"venue"
},
  "geometry": {"coordinates":[-74.159729,40.730014],"type":"Point"}
}