{
  "type": "Feature",
  "properties": {
    "iso:country":"US",
    "sg:address":"6028 Tyler Pl",
    "sg:city":"West New York",
    "sg:classifiers":[
        {
            "category":"Food & Beverages",
            "subcategory":"Groceries & Convenience Stores",
            "type":"Retail Goods"
        }
    ],
    "sg:phone":"+1   ",
    "sg:postcode":"07093",
    "sg:province":"NJ",
    "wof:name":"Country Farm",
    "wof:placetype":"venue"
},
  "geometry": {"coordinates":[-74.01398,40.789095],"type":"Point"}
}