{
  "type": "Feature",
  "properties": {
    "iso:country":"US",
    "sg:address":"1 W White Horse Pike",
    "sg:city":"Berlin",
    "sg:classifiers":[
        {
            "category":"Shopping",
            "subcategory":"Pharmacy",
            "type":"Retail Goods"
        }
    ],
    "sg:phone":"+1   ",
    "sg:postcode":"08009",
    "sg:province":"NJ",
    "wof:name":"CVS",
    "wof:placetype":"venue"
},
  "geometry": {"coordinates":[-74.93385499999999,39.79779],"type":"Point"}
}