{
  "type": "Feature",
  "properties": {
    "iso:country":"US",
    "sg:address":"500 Buttermere Ave",
    "sg:city":"Asbury Park",
    "sg:classifiers":[
        {
            "category":"Shopping",
            "subcategory":"Music",
            "type":"Retail Goods"
        }
    ],
    "sg:phone":"+1   ",
    "sg:postcode":"07712",
    "sg:province":"NJ",
    "wof:name":"Hdw Records LLC",
    "wof:placetype":"venue"
},
  "geometry": {"coordinates":[-74.01736699999999,40.237057],"type":"Point"}
}