{
  "type": "Feature",
  "properties": {
    "iso:country":"US",
    "sg:address":"91 Buttonwood Ln",
    "sg:city":"Freehold",
    "sg:classifiers":[
        {
            "category":"Professional",
            "subcategory":"Accounting & Tax Preparation",
            "type":"Services"
        }
    ],
    "sg:phone":"+1   ",
    "sg:postcode":"07728",
    "sg:province":"NJ",
    "sg:tags":[
        "bookkeeping"
    ],
    "wof:name":"Shah Financial Services",
    "wof:placetype":"venue"
},
  "geometry": {"coordinates":[-74.30439699999999,40.237787],"type":"Point"}
}