{
  "type": "Feature",
  "properties": {
    "addr:full":"237 Park Pl Irvington NJ 07111",
    "addr:housenumber":"237",
    "addr:postcode":"07111",
    "addr:street":"Park Pl",
    "iso:country":"US",
    "sg:address":"237 Park Pl",
    "sg:city":"Irvington",
    "sg:classifiers":[
        {
            "category":"Real Estate",
            "subcategory":"Real Estate Operator",
            "type":"Services"
        }
    ],
    "sg:phone":"+1   ",
    "sg:postcode":"07111",
    "sg:province":"NJ",
    "sg:tags":[
        "property",
        "lessor"
    ],
    "wof:name":"Brooks & Trotman",
    "wof:placetype":"venue"
},
  "geometry": {"coordinates":[-74.242487,40.718616],"type":"Point"}
}