{
  "type": "Feature",
  "properties": {
    "addr:full":"249 Wescott Dr Rahway NJ 07065",
    "addr:housenumber":"249",
    "addr:postcode":"07065",
    "addr:street":"Wescott Dr",
    "iso:country":"US",
    "sg:address":"249 Wescott Dr",
    "sg:city":"Rahway",
    "sg:classifiers":[
        {
            "category":"Building & Trades",
            "subcategory":"Locksmith",
            "type":"Services"
        }
    ],
    "sg:phone":"+1 877 768 2565",
    "sg:postcode":"07065",
    "sg:province":"NJ",
    "sg:tags":[
        "key"
    ],
    "wof:name":"24 Emergency Locksmith",
    "wof:placetype":"venue"
},
  "geometry": {"coordinates":[-74.283878,40.595401],"type":"Point"}
}