{
  "type": "Feature",
  "properties": {
    "iso:country":"US",
    "sg:address":"106 Westervelt Ave",
    "sg:city":"Tenafly",
    "sg:classifiers":[
        {
            "category":"Health Services",
            "subcategory":"Doctor",
            "type":"Services"
        }
    ],
    "sg:phone":"+1 201 568 5769",
    "sg:postcode":"07670",
    "sg:province":"NJ",
    "sg:tags":[
        "medical"
    ],
    "wof:name":"Jan Kung Ming MD",
    "wof:placetype":"venue"
},
  "geometry": {"coordinates":[-73.974086,40.921513],"type":"Point"}
}