{
  "type": "Feature",
  "properties": {
    "iso:country":"US",
    "sg:address":"159 Chestnut St",
    "sg:city":"Garfield",
    "sg:classifiers":[
        {
            "category":"Shopping",
            "type":"Retail Goods"
        },
        {
            "category":"Wholesale",
            "subcategory":"Electrical",
            "type":"Manufacturing & Wholesale Goods"
        }
    ],
    "sg:phone":"+1 973 478 9070",
    "sg:postcode":"07026",
    "sg:province":"NJ",
    "sg:tags":[
        "alarm",
        "burglar",
        "security",
        "system"
    ],
    "wof:name":"Security Control Alarm Co Inc",
    "wof:placetype":"venue"
},
  "geometry": {"coordinates":[-74.107512,40.87886],"type":"Point"}
}