{
  "type": "Feature",
  "properties": {
    "addr:full":"88 Chancellor Ave Newark NJ 07112",
    "addr:housenumber":"88",
    "addr:postcode":"07112",
    "addr:street":"Chancellor Ave",
    "iso:country":"US",
    "sg:address":"88 Chancellor Ave",
    "sg:city":"Newark",
    "sg:classifiers":[
        {
            "category":"Health Services",
            "subcategory":"Doctor",
            "type":"Services"
        }
    ],
    "sg:phone":"+1   ",
    "sg:postcode":"07112",
    "sg:province":"NJ",
    "sg:tags":[
        "medical"
    ],
    "wof:name":"Alberca Bey",
    "wof:placetype":"venue"
},
  "geometry": {"coordinates":[-74.214341,40.705181],"type":"Point"}
}