{
  "type": "Feature",
  "properties": {
    "iso:country":"US",
    "sg:address":"95 Waterview Dr",
    "sg:city":"Galloway",
    "sg:classifiers":[
        {
            "category":"Professional",
            "subcategory":"Computer Services",
            "type":"Services"
        }
    ],
    "sg:phone":"+1 609 748 6620",
    "sg:postcode":"08205",
    "sg:province":"NJ",
    "sg:tags":[
        "repair"
    ],
    "wof:name":"P C Svc",
    "wof:placetype":"venue"
},
  "geometry": {"coordinates":[-74.459042,39.492023],"type":"Point"}
}