{
  "type": "Feature",
  "properties": {
    "addr:full":"71 North Ave E Elizabeth NJ 07201",
    "addr:housenumber":"71",
    "addr:postcode":"07201",
    "addr:street":"North Ave E",
    "iso:country":"US",
    "sg:address":"71 North Ave E",
    "sg:city":"Elizabeth",
    "sg:classifiers":[
        {
            "category":"Freight",
            "type":"Transportation"
        }
    ],
    "sg:phone":"+1 908 965 0100",
    "sg:postcode":"07201",
    "sg:province":"NJ",
    "sg:tags":[
        "logistics",
        "party",
        "third"
    ],
    "wof:name":"Carrier Industries Inc",
    "wof:placetype":"venue"
},
  "geometry": {"coordinates":[-74.17104500000001,40.666935],"type":"Point"}
}