{
  "type": "Feature",
  "properties": {
    "iso:country":"US",
    "sg:address":"47 W Sunset Rd",
    "sg:city":"Pompton Plains",
    "sg:classifiers":[
        {
            "category":"Sports & Exercise",
            "subcategory":"Golf",
            "type":"Entertainment"
        }
    ],
    "sg:phone":"+1 973 839 5676",
    "sg:postcode":"07444",
    "sg:province":"NJ",
    "wof:name":"Sunset Valley Golf Course",
    "wof:placetype":"venue"
},
  "geometry": {"coordinates":[-74.325121,40.962518],"type":"Point"}
}