{
  "type": "Feature",
  "properties": {
    "iso:country":"US",
    "sg:address":"1403 Franklin Blvd",
    "sg:city":"Linwood",
    "sg:classifiers":[
        {
            "category":"Building & Trades",
            "subcategory":"Construction",
            "type":"Services"
        }
    ],
    "sg:phone":"+1 609 601 6026",
    "sg:postcode":"08221",
    "sg:province":"NJ",
    "sg:tags":[
        "designer"
    ],
    "wof:name":"JFA",
    "wof:placetype":"venue"
},
  "geometry": {"coordinates":[-74.56944300000001,39.341239],"type":"Point"}
}