{
  "type": "Feature",
  "properties": {
    "addr:full":"914 Mountainview Cir Westfield NJ 07090",
    "addr:housenumber":"914",
    "addr:postcode":"07090",
    "addr:street":"Mountainview Cir",
    "iso:country":"US",
    "sg:address":"914 Mountainview Cir",
    "sg:city":"Westfield",
    "sg:classifiers":[
        {
            "category":"Banks & Credit Unions",
            "subcategory":"Financial Services",
            "type":"Services"
        }
    ],
    "sg:phone":"+1   ",
    "sg:postcode":"07090",
    "sg:province":"NJ",
    "sg:tags":[
        "investor"
    ],
    "wof:name":"Shore Capital LLC",
    "wof:placetype":"venue"
},
  "geometry": {"coordinates":[-74.353972,40.666815],"type":"Point"}
}