{
  "type": "Feature",
  "properties": {
    "addr:full":"264 S Orange Ave South Orange NJ 07079",
    "addr:housenumber":"264",
    "addr:postcode":"07079",
    "addr:street":"S Orange Ave",
    "iso:country":"US",
    "sg:address":"264 S Orange Ave",
    "sg:city":"South Orange",
    "sg:classifiers":[
        {
            "category":"Professional",
            "subcategory":"Art Services",
            "type":"Services"
        }
    ],
    "sg:phone":"+1   ",
    "sg:postcode":"07079",
    "sg:province":"NJ",
    "sg:tags":[
        "commercial",
        "design"
    ],
    "wof:name":"Elyse Carter Design",
    "wof:placetype":"venue"
},
  "geometry": {"coordinates":[-74.250045,40.744705],"type":"Point"}
}