{
  "type": "Feature",
  "properties": {
    "iso:country":"US",
    "sg:address":"947 State Rd",
    "sg:city":"Princeton",
    "sg:classifiers":[
        {
            "category":"Professional",
            "subcategory":"Lawyer & Legal Services",
            "type":"Services"
        }
    ],
    "sg:phone":"+1 609 497 4911",
    "sg:postcode":"08540",
    "sg:province":"NJ",
    "sg:tags":[
        "attorney"
    ],
    "wof:name":"Yong H Hyon",
    "wof:placetype":"venue"
},
  "geometry": {"coordinates":[-74.650243,40.401716],"type":"Point"}
}