{
  "type": "Feature",
  "properties": {
    "addr:full":"3131 Princeton Pike Lawrenceville NJ 08648",
    "addr:housenumber":"3131",
    "addr:postcode":"08648",
    "addr:street":"Princeton Pike",
    "iso:country":"US",
    "sg:address":"3131 Princeton Pike",
    "sg:city":"Lawrenceville",
    "sg:classifiers":[
        {
            "category":"Insurance",
            "subcategory":"Insurance Agent",
            "type":"Services"
        }
    ],
    "sg:phone":"+1 609 896 7000",
    "sg:postcode":"08648",
    "sg:province":"NJ",
    "wof:name":"Sypek & Sandford",
    "wof:placetype":"venue"
},
  "geometry": {"coordinates":[-74.714203,40.284616],"type":"Point"}
}