{
  "type": "Feature",
  "properties": {
    "addr:full":"111 Madison Ave Morristown NJ 07960",
    "addr:housenumber":"111",
    "addr:postcode":"07960",
    "addr:street":"Madison Ave",
    "iso:country":"US",
    "sg:address":"111 Madison Ave",
    "sg:city":"Morristown",
    "sg:classifiers":[
        {
            "category":"Health Services",
            "subcategory":"Clinic",
            "type":"Services"
        }
    ],
    "sg:phone":"+1 973 971 6900",
    "sg:postcode":"07960",
    "sg:province":"NJ",
    "sg:tags":[
        "surgical",
        "center"
    ],
    "sg:website":"www.morristownsurgicalcenter.com",
    "wof:name":"Morristown Surgical Ctr",
    "wof:placetype":"venue"
},
  "geometry": {"coordinates":[-74.466053,40.788037],"type":"Point"}
}