{
  "type": "Feature",
  "properties": {
    "iso:country":"US",
    "sg:address":"1505 Squirrel Rd",
    "sg:city":"Marlton",
    "sg:classifiers":[
        {
            "category":"Building & Trades",
            "subcategory":"Construction",
            "type":"Services"
        }
    ],
    "sg:phone":"+1 856 489 3150",
    "sg:postcode":"08053",
    "sg:province":"NJ",
    "sg:tags":[
        "home",
        "builder"
    ],
    "wof:name":"Whitebridge Village Homes",
    "wof:placetype":"venue"
},
  "geometry": {"coordinates":[-74.866488,39.893627],"type":"Point"}
}