{
  "type": "Feature",
  "properties": {
    "addr:full":"35 Little Falls Rd Fairfield NJ 07004",
    "addr:housenumber":"35",
    "addr:postcode":"07004",
    "addr:street":"Little Falls Rd",
    "iso:country":"US",
    "sg:address":"35 Little Falls Rd",
    "sg:city":"Fairfield",
    "sg:classifiers":[
        {
            "category":"Deli",
            "type":"Food & Drink"
        }
    ],
    "sg:phone":"+1 973 882 8586",
    "sg:postcode":"07004",
    "sg:province":"NJ",
    "wof:name":"La Cocina",
    "wof:placetype":"venue"
},
  "geometry": {"coordinates":[-74.273697,40.888699],"type":"Point"}
}