{
  "type": "Feature",
  "properties": {
    "addr:full":"601 Browning Ln Brooklawn NJ 08030",
    "addr:housenumber":"601",
    "addr:postcode":"08030",
    "addr:street":"Browning Ln",
    "iso:country":"US",
    "sg:address":"601 Browning Ln",
    "sg:city":"Brooklawn",
    "sg:classifiers":[
        {
            "category":"Deli",
            "type":"Food & Drink"
        },
        {
            "category":"Restaurant",
            "type":"Food & Drink"
        },
        {
            "category":"Food & Beverages",
            "subcategory":"Bakery",
            "type":"Retail Goods"
        }
    ],
    "sg:phone":"+1 856 456 5552",
    "sg:postcode":"08030",
    "sg:province":"NJ",
    "sg:tags":[
        "delicatessen",
        "sandwich",
        "italian"
    ],
    "wof:name":"Sorrentino's Italian Deli",
    "wof:placetype":"venue"
},
  "geometry": {"coordinates":[-75.11585599999999,39.878601],"type":"Point"}
}