{
  "type": "Feature",
  "properties": {
    "addr:full":"75 Neptune Ave Neptune NJ 07753",
    "addr:housenumber":"75",
    "addr:postcode":"07753",
    "addr:street":"Neptune Ave",
    "iso:country":"US",
    "sg:address":"75 Neptune Ave",
    "sg:city":"Neptune",
    "sg:classifiers":[
        {
            "category":"Communications",
            "type":"Services"
        }
    ],
    "sg:phone":"+1 732 361 6985",
    "sg:postcode":"07753",
    "sg:province":"NJ",
    "wof:name":"All In One Communications",
    "wof:placetype":"venue"
},
  "geometry": {"coordinates":[-74.034325,40.201953],"type":"Point"}
}