{
  "type": "Feature",
  "properties": {
    "addr:full":"546 Valley Rd Montclair NJ 07043",
    "addr:housenumber":"546",
    "addr:postcode":"07043",
    "addr:street":"Valley Rd",
    "iso:country":"US",
    "sg:address":"546 Valley Rd",
    "sg:city":"Montclair",
    "sg:classifiers":[
        {
            "category":"Professional",
            "subcategory":"Accounting & Tax Preparation",
            "type":"Services"
        }
    ],
    "sg:phone":"+1   ",
    "sg:postcode":"07043",
    "sg:province":"NJ",
    "wof:name":"H & R Block",
    "wof:placetype":"venue"
},
  "geometry": {"coordinates":[-74.207376,40.83802],"type":"Point"}
}