{
  "type": "Feature",
  "properties": {
    "iso:country":"US",
    "sg:address":"26 W Passaic St",
    "sg:city":"Rochelle Park",
    "sg:classifiers":[
        {
            "category":"Home & Garden",
            "subcategory":"Building Materials",
            "type":"Retail Goods"
        }
    ],
    "sg:phone":"+1   ",
    "sg:postcode":"07662",
    "sg:province":"NJ",
    "wof:name":"Creative Wrks By Brndon Copans",
    "wof:placetype":"venue"
},
  "geometry": {"coordinates":[-74.073258,40.909535],"type":"Point"}
}