{
  "type": "Feature",
  "properties": {
    "addr:full":"3101 Shetland Way Westville NJ 08093",
    "addr:housenumber":"3101",
    "addr:postcode":"08093",
    "addr:street":"Shetland Way",
    "iso:country":"US",
    "sg:address":"3101 Shetland Way",
    "sg:city":"Westville",
    "sg:classifiers":[
        {
            "category":"Wholesale",
            "subcategory":"Durable Goods & Equipment",
            "type":"Manufacturing & Wholesale Goods"
        }
    ],
    "sg:phone":"+1 856 845 6059",
    "sg:postcode":"08093",
    "sg:province":"NJ",
    "sg:tags":[
        "professional"
    ],
    "wof:name":"Shomer Shops Co",
    "wof:placetype":"venue"
},
  "geometry": {"coordinates":[-75.120701,39.857164],"type":"Point"}
}