{
  "type": "Feature",
  "properties": {
    "iso:country":"US",
    "sg:address":"838 Vail Rd",
    "sg:city":"Monroe Township",
    "sg:classifiers":[
        {
            "category":"Organizations",
            "subcategory":"Non-profit Organization",
            "type":"Services"
        }
    ],
    "sg:phone":"+1 609 395 1106",
    "sg:postcode":"08831",
    "sg:province":"NJ",
    "sg:tags":[
        "social"
    ],
    "wof:name":"National Assoc of Retired",
    "wof:placetype":"venue"
},
  "geometry": {"coordinates":[-74.457024,40.306834],"type":"Point"}
}