{
  "type": "Feature",
  "properties": {
    "addr:full":"595 Main St Paterson NJ 07503",
    "addr:housenumber":"595",
    "addr:postcode":"07503",
    "addr:street":"Main St",
    "iso:country":"US",
    "sg:address":"595 Main St",
    "sg:city":"Paterson",
    "sg:classifiers":[
        {
            "category":"Building & Trades",
            "subcategory":"Construction",
            "type":"Services"
        }
    ],
    "sg:phone":"+1 973 742 1772",
    "sg:postcode":"07503",
    "sg:province":"NJ",
    "sg:tags":[
        "contractor"
    ],
    "wof:name":"Mundo Construction",
    "wof:placetype":"venue"
},
  "geometry": {"coordinates":[-74.169329,40.905376],"type":"Point"}
}