{
  "type": "Feature",
  "properties": {
    "addr:full":"62 Lincoln Ave Cliffside Park NJ 07010",
    "addr:housenumber":"62",
    "addr:postcode":"07010",
    "addr:street":"Lincoln Ave",
    "iso:country":"US",
    "sg:address":"62 Lincoln Ave",
    "sg:city":"Cliffside Park",
    "sg:classifiers":[
        {
            "category":"Building & Trades",
            "subcategory":"Construction",
            "type":"Services"
        }
    ],
    "sg:phone":"+1 201 941 2552",
    "sg:postcode":"07010",
    "sg:province":"NJ",
    "sg:tags":[
        "contractor"
    ],
    "wof:name":"ASAP Roofing",
    "wof:placetype":"venue"
},
  "geometry": {"coordinates":[-73.98447400000001,40.82263],"type":"Point"}
}