{
  "type": "Feature",
  "properties": {
    "addr:full":"11 Davenport St Somerville NJ 08876",
    "addr:housenumber":"11",
    "addr:postcode":"08876",
    "addr:street":"Davenport St",
    "iso:country":"US",
    "sg:address":"11 Davenport St",
    "sg:city":"Somerville",
    "sg:classifiers":[
        {
            "category":"Professional",
            "subcategory":"Lawyer & Legal Services",
            "type":"Services"
        }
    ],
    "sg:phone":"+1   ",
    "sg:postcode":"08876",
    "sg:province":"NJ",
    "wof:name":"George Goceljak",
    "wof:placetype":"venue"
},
  "geometry": {"coordinates":[-74.615691,40.570208],"type":"Point"}
}