{
  "type": "Feature",
  "properties": {
    "iso:country":"US",
    "sg:address":"11 Lawrence Rd",
    "sg:city":"Newton",
    "sg:classifiers":[
        {
            "category":"Health Services",
            "subcategory":"Optometrist",
            "type":"Services"
        }
    ],
    "sg:phone":"+1 973 579 3937",
    "sg:postcode":"07869",
    "sg:province":"NJ",
    "wof:name":"Andover Eye Care",
    "wof:placetype":"venue"
},
  "geometry": {"coordinates":[-74.576472,40.851832],"type":"Point"}
}