{
  "type": "Feature",
  "properties": {
    "iso:country":"US",
    "sg:address":"22 Kennedy Ct",
    "sg:city":"Lyndhurst",
    "sg:classifiers":[
        {
            "category":"Professional",
            "subcategory":"Management & Consulting",
            "type":"Services"
        }
    ],
    "sg:phone":"+1 201 650 2024",
    "sg:postcode":"07071",
    "sg:province":"NJ",
    "sg:tags":[
        "business"
    ],
    "wof:name":"Bedlam",
    "wof:placetype":"venue"
},
  "geometry": {"coordinates":[-74.11599099999999,40.805832],"type":"Point"}
}