{
  "type": "Feature",
  "properties": {
    "iso:country":"US",
    "sg:address":"22 N Greenwood Ave",
    "sg:city":"Hopewell",
    "sg:classifiers":[
        {
            "category":"Professional",
            "subcategory":"Management & Consulting",
            "type":"Services"
        }
    ],
    "sg:phone":"+1 609 466 4114",
    "sg:postcode":"08525",
    "sg:province":"NJ",
    "sg:tags":[
        "marketing",
        "railroad"
    ],
    "wof:name":"Rail Systems Inc",
    "wof:placetype":"venue"
},
  "geometry": {"coordinates":[-74.762925,40.390252],"type":"Point"}
}