{
  "type": "Feature",
  "properties": {
    "addr:full":"19 N Maple Ave Marlton NJ 08053",
    "addr:housenumber":"19",
    "addr:postcode":"08053",
    "addr:street":"N Maple Ave",
    "iso:country":"US",
    "sg:address":"19 N Maple Ave",
    "sg:city":"Marlton",
    "sg:classifiers":[
        {
            "category":"Retail",
            "subcategory":"Animal Services",
            "type":"Services"
        }
    ],
    "sg:phone":"+1 856 985 7086",
    "sg:postcode":"08053",
    "sg:province":"NJ",
    "sg:tags":[
        "cat",
        "dog",
        "kennel"
    ],
    "sg:website":"www.dogdaysinc.net",
    "wof:name":"Dog Days",
    "wof:placetype":"venue"
},
  "geometry": {"coordinates":[-74.92210799999999,39.893411],"type":"Point"}
}