{
  "type": "Feature",
  "properties": {
    "addr:full":"823 W Park Ave Asbury Park NJ 07712",
    "addr:housenumber":"823",
    "addr:postcode":"07712",
    "addr:street":"W Park Ave Asbury",
    "iso:country":"US",
    "sg:address":"823 W Park Ave",
    "sg:city":"Asbury Park",
    "sg:classifiers":[
        {
            "category":"Professional",
            "subcategory":"Computer Services",
            "type":"Services"
        }
    ],
    "sg:phone":"+1   ",
    "sg:postcode":"07712",
    "sg:province":"NJ",
    "sg:tags":[
        "related"
    ],
    "wof:name":"Danucom Corp",
    "wof:placetype":"venue"
},
  "geometry": {"coordinates":[-74.042946,40.264398],"type":"Point"}
}