{
  "type": "Feature",
  "properties": {
    "iso:country":"US",
    "sg:address":"100 S Jefferson Rd",
    "sg:city":"Whippany",
    "sg:classifiers":[
        {
            "category":"Mining & Drilling",
            "type":"Manufacturing & Wholesale Goods"
        }
    ],
    "sg:phone":"+1 973 887 8611",
    "sg:postcode":"07981",
    "sg:province":"NJ",
    "sg:tags":[
        "crude",
        "petroleum",
        "natural",
        "gas"
    ],
    "wof:name":"Nucoastal Trading Co",
    "wof:placetype":"venue"
},
  "geometry": {"coordinates":[-74.441599,40.818026],"type":"Point"}
}