{
  "type": "Feature",
  "properties": {
    "addr:full":"4 Dolbow Rd Salem NJ 08079",
    "addr:housenumber":"4",
    "addr:postcode":"08079",
    "addr:street":"Dolbow Rd",
    "iso:country":"US",
    "sg:address":"4 Dolbow Rd",
    "sg:city":"Salem",
    "sg:classifiers":[
        {
            "category":"Building & Trades",
            "subcategory":"Electrical",
            "type":"Services"
        }
    ],
    "sg:phone":"+1 856 339 0707",
    "sg:postcode":"08079",
    "sg:province":"NJ",
    "sg:tags":[
        "electric",
        "contractor"
    ],
    "wof:name":"Moonlighting Electric",
    "wof:placetype":"venue"
},
  "geometry": {"coordinates":[-75.40191900000001,39.578527],"type":"Point"}
}