{
  "type": "Feature",
  "properties": {
    "iso:country":"US",
    "sg:address":"76 Union St",
    "sg:city":"Hackensack",
    "sg:classifiers":[
        {
            "category":"Retail",
            "subcategory":"Auto Repair",
            "type":"Services"
        }
    ],
    "sg:phone":"+1 201 342 7383",
    "sg:postcode":"07601",
    "sg:province":"NJ",
    "wof:name":"Digas Auto Repair",
    "wof:placetype":"venue"
},
  "geometry": {"coordinates":[-74.048103,40.881199],"type":"Point"}
}