{
  "type": "Feature",
  "properties": {
    "iso:country":"US",
    "sg:address":"9 Nicole Ter",
    "sg:city":"Edison",
    "sg:classifiers":[
        {
            "category":"Restaurant",
            "type":"Food & Drink"
        }
    ],
    "sg:phone":"+1   ",
    "sg:postcode":"08820",
    "sg:province":"NJ",
    "sg:tags":[
        "eating"
    ],
    "wof:name":"Passion Food Catering LLC",
    "wof:placetype":"venue"
},
  "geometry": {"coordinates":[-74.386742,40.560115],"type":"Point"}
}