{
  "type": "Feature",
  "properties": {
    "addr:full":"114 Summit Ave Ramsey NJ 07446",
    "addr:housenumber":"114",
    "addr:postcode":"07446",
    "addr:street":"Summit Ave",
    "iso:country":"US",
    "sg:address":"114 Summit Ave",
    "sg:city":"Ramsey",
    "sg:classifiers":[
        {
            "category":"Professional",
            "subcategory":"Computer Services",
            "type":"Services"
        }
    ],
    "sg:phone":"+1 201 327 4780",
    "sg:postcode":"07446",
    "sg:province":"NJ",
    "sg:tags":[
        "programing",
        "custom"
    ],
    "wof:name":"Double Diamond Associates",
    "wof:placetype":"venue"
},
  "geometry": {"coordinates":[-74.144723,41.053674],"type":"Point"}
}