{
  "type": "Feature",
  "properties": {
    "iso:country":"US",
    "sg:address":"95-B Dell Glen Ave",
    "sg:city":"Lodi",
    "sg:classifiers":[
        {
            "category":"Arena",
            "subcategory":"Sports Club",
            "type":"Entertainment"
        }
    ],
    "sg:phone":"+1 862 591 1281",
    "sg:postcode":"07644",
    "sg:province":"NJ",
    "sg:tags":[
        "martial art"
    ],
    "sg:website":"northjerseymuaythai.net",
    "wof:name":"North Jersey Muay Thai",
    "wof:placetype":"venue"
},
  "geometry": {"coordinates":[-74.087281,40.880686],"type":"Point"}
}