{
  "type": "Feature",
  "properties": {
    "iso:country":"US",
    "sg:address":"200 Macarthur Ave",
    "sg:city":"Garfield",
    "sg:classifiers":[
        {
            "category":"Organizations",
            "subcategory":"Religious Organization",
            "type":"Services"
        }
    ],
    "sg:phone":"+1   ",
    "sg:postcode":"07026",
    "sg:province":"NJ",
    "sg:website":"www.garfieldcatholicacademy.com",
    "wof:name":"Garfield Catholic Academy",
    "wof:placetype":"venue"
},
  "geometry": {"coordinates":[-74.098698,40.873933],"type":"Point"}
}