{
  "type": "Feature",
  "properties": {
    "addr:full":"241 Division Ave Hasbrouck Heights NJ 07604",
    "addr:housenumber":"241",
    "addr:postcode":"07604",
    "addr:street":"Division Ave",
    "iso:country":"US",
    "sg:address":"241 Division Ave",
    "sg:city":"Hasbrouck Heights",
    "sg:classifiers":[
        {
            "category":"Freight",
            "type":"Transportation"
        }
    ],
    "sg:phone":"+1 201 288 5784",
    "sg:postcode":"07604",
    "sg:province":"NJ",
    "sg:tags":[
        "operator",
        "local",
        "trucking"
    ],
    "wof:name":"N&A Trucking LLC",
    "wof:placetype":"venue"
},
  "geometry": {"coordinates":[-74.078014,40.859286],"type":"Point"}
}