{
  "type": "Feature",
  "properties": {
    "iso:country":"US",
    "sg:address":"160 Old Marlton Pike",
    "sg:city":"Medford",
    "sg:classifiers":[
        {
            "category":"Shopping",
            "subcategory":"Used Merchandise",
            "type":"Retail Goods"
        }
    ],
    "sg:phone":"+1 609 953 0005",
    "sg:postcode":"08055",
    "sg:province":"NJ",
    "sg:tags":[
        "antique",
        "shop"
    ],
    "wof:name":"Toll House Antiques Inc",
    "wof:placetype":"venue"
},
  "geometry": {"coordinates":[-74.843795,39.897819],"type":"Point"}
}