{
  "type": "Feature",
  "properties": {
    "addr:full":"110 State Rte 183 Stanhope NJ 07874",
    "addr:housenumber":"110",
    "addr:postcode":"07874",
    "addr:street":"State Rte 183",
    "iso:country":"US",
    "sg:address":"110 State Rte 183",
    "sg:city":"Stanhope",
    "sg:classifiers":[
        {
            "category":"Real Estate",
            "subcategory":"Real Estate Agent",
            "type":"Services"
        }
    ],
    "sg:phone":"+1 973 347 2157",
    "sg:postcode":"07874",
    "sg:province":"NJ",
    "sg:tags":[
        "management"
    ],
    "wof:name":"Heritage Crossing LLC",
    "wof:placetype":"venue"
},
  "geometry": {"coordinates":[-74.71150799999999,40.908737],"type":"Point"}
}