{
  "type": "Feature",
  "properties": {
    "iso:country":"US",
    "sg:address":"409 Saddle River Rd",
    "sg:city":"Saddle Brook",
    "sg:classifiers":[
        {
            "category":"Professional",
            "subcategory":"Detective & Security Services",
            "type":"Services"
        }
    ],
    "sg:phone":"+1   ",
    "sg:postcode":"07663",
    "sg:province":"NJ",
    "sg:tags":[
        "investigation",
        "private"
    ],
    "wof:name":"Dm Disney & Assoc",
    "wof:placetype":"venue"
},
  "geometry": {"coordinates":[-74.087057,40.906684],"type":"Point"}
}