{
  "type": "Feature",
  "properties": {
    "iso:country":"US",
    "sg:address":"349 State Rte 31",
    "sg:city":"Flemington",
    "sg:classifiers":[
        {
            "category":"Professional",
            "subcategory":"Accounting & Tax Preparation",
            "type":"Services"
        }
    ],
    "sg:phone":"+1 908 782 4888",
    "sg:postcode":"08822",
    "sg:province":"NJ",
    "sg:tags":[
        "accountant"
    ],
    "wof:name":"Hodakowski & Hodakowski",
    "wof:placetype":"venue"
},
  "geometry": {"coordinates":[-74.857421,40.541708],"type":"Point"}
}