{
  "type": "Feature",
  "properties": {
    "iso:country":"US",
    "sg:address":"239 E Front St",
    "sg:city":"Trenton",
    "sg:classifiers":[
        {
            "category":"Social Services",
            "subcategory":"Child Care",
            "type":"Services"
        }
    ],
    "sg:phone":"+1 609 393 8888",
    "sg:postcode":"08611",
    "sg:province":"NJ",
    "wof:name":"Learning Depot",
    "wof:placetype":"venue"
},
  "geometry": {"coordinates":[-74.759422,40.21918],"type":"Point"}
}