{
  "type": "Feature",
  "properties": {
    "addr:full":"149 Northampton Dr Holmdel NJ 07733",
    "addr:housenumber":"149",
    "addr:postcode":"07733",
    "addr:street":"Northampton Dr",
    "iso:country":"US",
    "sg:address":"149 Northampton Dr",
    "sg:city":"Holmdel",
    "sg:classifiers":[
        {
            "category":"Building & Trades",
            "subcategory":"Construction",
            "type":"Services"
        }
    ],
    "sg:phone":"+1 732 264 9089",
    "sg:postcode":"07733",
    "sg:province":"NJ",
    "sg:tags":[
        "interior",
        "painting",
        "custom"
    ],
    "wof:name":"Finished Walls",
    "wof:placetype":"venue"
},
  "geometry": {"coordinates":[-74.15797499999999,40.418987],"type":"Point"}
}