{
  "type": "Feature",
  "properties": {
    "iso:country":"US",
    "sg:address":"10 Summit Ave",
    "sg:city":"Montvale",
    "sg:classifiers":[
        {
            "category":"Shopping",
            "subcategory":"Crafts & Fabrics",
            "type":"Retail Goods"
        }
    ],
    "sg:phone":"+1   ",
    "sg:postcode":"07645",
    "sg:province":"NJ",
    "sg:tags":[
        "sales"
    ],
    "wof:name":"Wwwfabricbanditcom",
    "wof:placetype":"venue"
},
  "geometry": {"coordinates":[-74.046561,41.059579],"type":"Point"}
}