{
  "type": "Feature",
  "properties": {
    "addr:full":"779 Market St Apt 1 Paterson NJ 07513",
    "addr:housenumber":"779;1",
    "addr:postcode":"07513",
    "addr:street":"Market St Apt",
    "iso:country":"US",
    "sg:address":"779 Market St Apt 1",
    "sg:city":"Paterson",
    "sg:classifiers":[
        {
            "category":"Retail",
            "subcategory":"Repair Shop",
            "type":"Services"
        }
    ],
    "sg:phone":"+1 973 684 9263",
    "sg:postcode":"07513",
    "sg:province":"NJ",
    "sg:tags":[
        "reupholstery",
        "furniture"
    ],
    "sg:website":"www.kingupholstery.com",
    "wof:name":"King Upholstery",
    "wof:placetype":"venue"
},
  "geometry": {"coordinates":[-74.147903,40.9062],"type":"Point"}
}