{
  "type": "Feature",
  "properties": {
    "addr:full":"30 Quince Ct Mt Laurel NJ 08054",
    "addr:housenumber":"30",
    "addr:postcode":"08054",
    "addr:street":"Quince Ct",
    "iso:country":"US",
    "sg:address":"30 Quince Ct",
    "sg:city":"Mt Laurel",
    "sg:classifiers":[
        {
            "category":"Professional",
            "subcategory":"Computer Services",
            "type":"Services"
        }
    ],
    "sg:phone":"+1 856 231 1755",
    "sg:postcode":"08054",
    "sg:province":"NJ",
    "sg:tags":[
        "consultant",
        "designer"
    ],
    "wof:name":"MF-2000",
    "wof:placetype":"venue"
},
  "geometry": {"coordinates":[-74.92631,39.933171],"type":"Point"}
}