{
  "type": "Feature",
  "properties": {
    "iso:country":"US",
    "sg:address":"1555 Zion Rd",
    "sg:city":"Northfield",
    "sg:classifiers":[
        {
            "category":"Shopping",
            "type":"Retail Goods"
        },
        {
            "category":"Health Services",
            "subcategory":"Doctor",
            "type":"Services"
        }
    ],
    "sg:phone":"+1 609 272 0365",
    "sg:postcode":"08225",
    "sg:province":"NJ",
    "sg:tags":[
        "physician",
        "surgeon",
        "cosmetic",
        "perfume"
    ],
    "wof:name":"Volk Center For Cosmetic",
    "wof:placetype":"venue"
},
  "geometry": {"coordinates":[-74.554154,39.370206],"type":"Point"}
}