{
  "type": "Feature",
  "properties": {
    "iso:country":"US",
    "sg:address":"82 Leonardville Rd",
    "sg:city":"Middletown",
    "sg:classifiers":[
        {
            "category":"Restaurant",
            "type":"Food & Drink"
        }
    ],
    "sg:phone":"+1 732 495 4953",
    "sg:postcode":"07748",
    "sg:province":"NJ",
    "wof:name":"Bella Cucina Cabinets Inc",
    "wof:placetype":"venue"
},
  "geometry": {"coordinates":[-74.097532,40.413844],"type":"Point"}
}