{
  "type": "Feature",
  "properties": {
    "addr:full":"300 State Rte 38 Moorestown NJ 08057",
    "addr:housenumber":"300",
    "addr:postcode":"08057",
    "addr:street":"State Rte 38",
    "iso:country":"US",
    "sg:address":"300 State Rte 38",
    "sg:city":"Moorestown",
    "sg:classifiers":[
        {
            "category":"Health Services",
            "subcategory":"Chiropractor",
            "type":"Services"
        },
        {
            "category":"Building & Trades",
            "subcategory":"Equipment Rental",
            "type":"Services"
        }
    ],
    "sg:phone":"+1 856 273 9054",
    "sg:postcode":"08057",
    "sg:province":"NJ",
    "sg:tags":[
        "leasing"
    ],
    "wof:name":"D C Leasing",
    "wof:placetype":"venue"
},
  "geometry": {"coordinates":[-74.95332999999999,39.951046],"type":"Point"}
}