{
  "type": "Feature",
  "properties": {
    "iso:country":"US",
    "sg:address":"24 Highbridge Blvd",
    "sg:city":"Medford",
    "sg:classifiers":[
        {
            "category":"Building & Trades",
            "subcategory":"Electrical",
            "type":"Services"
        }
    ],
    "sg:phone":"+1 609 953 3500",
    "sg:postcode":"08055",
    "sg:province":"NJ",
    "sg:tags":[
        "electrical",
        "contractor"
    ],
    "wof:name":"J J Moore Electric Inc",
    "wof:placetype":"venue"
},
  "geometry": {"coordinates":[-74.81479299999999,39.833337],"type":"Point"}
}