{
  "type": "Feature",
  "properties": {
    "iso:country":"US",
    "sg:address":"230 Hamilton St",
    "sg:city":"Bound Brook",
    "sg:classifiers":[
        {
            "category":"Recreation",
            "type":"Entertainment"
        }
    ],
    "sg:phone":"+1 732 469 0877",
    "sg:postcode":"08805",
    "sg:province":"NJ",
    "sg:tags":[
        "parks"
    ],
    "wof:name":"Director Of Recreation",
    "wof:placetype":"venue"
},
  "geometry": {"coordinates":[-74.529667,40.56441],"type":"Point"}
}