{
  "type": "Feature",
  "properties": {
    "addr:full":"67 Maple Ave Ste 2 Morristown NJ 07960",
    "addr:housenumber":"67",
    "addr:postcode":"07960",
    "addr:street":"Maple Ave Ste 2",
    "iso:country":"US",
    "sg:address":"67 Maple Ave Ste 2",
    "sg:city":"Morristown",
    "sg:classifiers":[
        {
            "category":"Health Services",
            "subcategory":"Doctor",
            "type":"Services"
        }
    ],
    "sg:phone":"+1 973 984 7510",
    "sg:postcode":"07960",
    "sg:province":"NJ",
    "wof:name":"Michaels Christopher S Ph D",
    "wof:placetype":"venue"
},
  "geometry": {"coordinates":[-74.479412,40.79246],"type":"Point"}
}