{
  "type": "Feature",
  "properties": {
    "addr:full":"7611 Bergenline Ave North Bergen NJ 07047",
    "addr:housenumber":"7611",
    "addr:postcode":"07047",
    "addr:street":"Bergenline Ave",
    "iso:country":"US",
    "sg:address":"7611 Bergenline Ave",
    "sg:city":"North Bergen",
    "sg:classifiers":[
        {
            "category":"Professional",
            "subcategory":"Employment Agencies",
            "type":"Services"
        }
    ],
    "sg:phone":"+1 201 453 8738",
    "sg:postcode":"07047",
    "sg:province":"NJ",
    "sg:website":"www.laborready.com",
    "wof:name":"Labor Ready",
    "wof:placetype":"venue"
},
  "geometry": {"coordinates":[-74.007896,40.800301],"type":"Point"}
}