{
  "type": "Feature",
  "properties": {
    "addr:full":"330 S Van Brunt St Englewood NJ 07631",
    "addr:housenumber":"330",
    "addr:postcode":"07631",
    "addr:street":"S Van Brunt St",
    "iso:country":"US",
    "sg:address":"330 S Van Brunt St",
    "sg:city":"Englewood",
    "sg:classifiers":[
        {
            "category":"Freight",
            "type":"Transportation"
        }
    ],
    "sg:phone":"+1 201 833 1600",
    "sg:postcode":"07631",
    "sg:province":"NJ",
    "sg:tags":[
        "special",
        "general"
    ],
    "wof:name":"Beacon Looms Inc",
    "wof:placetype":"venue"
},
  "geometry": {"coordinates":[-73.98600500000001,40.882962],"type":"Point"}
}