{
  "type": "Feature",
  "properties": {
    "iso:country":"US",
    "sg:address":"308 Valley Brook Ave",
    "sg:city":"Lyndhurst",
    "sg:classifiers":[
        {
            "category":"Shopping",
            "subcategory":"Catalog Store",
            "type":"Retail Goods"
        }
    ],
    "sg:phone":"+1   ",
    "sg:postcode":"07071",
    "sg:province":"NJ",
    "sg:tags":[
        "mail",
        "house"
    ],
    "wof:name":"Gotham Bying Slling Cllctibles",
    "wof:placetype":"venue"
},
  "geometry": {"coordinates":[-74.12644,40.813092],"type":"Point"}
}