{
  "type": "Feature",
  "properties": {
    "iso:country":"US",
    "sg:address":"7 Briarwood Rd",
    "sg:city":"Rumson",
    "sg:classifiers":[
        {
            "category":"Professional",
            "subcategory":"Business Services",
            "type":"Services"
        }
    ],
    "sg:phone":"+1   ",
    "sg:postcode":"07760",
    "sg:province":"NJ",
    "sg:tags":[
        "interior",
        "design"
    ],
    "wof:name":"Goodman Design Studio",
    "wof:placetype":"venue"
},
  "geometry": {"coordinates":[-74.008537,40.362728],"type":"Point"}
}