{
  "type": "Feature",
  "properties": {
    "iso:country":"US",
    "sg:address":"17 Pompton Ave",
    "sg:city":"Pompton Lakes",
    "sg:classifiers":[
        {
            "category":"Organizations",
            "subcategory":"Religious Organization",
            "type":"Services"
        }
    ],
    "sg:phone":"+1   ",
    "sg:postcode":"07442",
    "sg:province":"NJ",
    "sg:tags":[
        "catholic",
        "roman",
        "church"
    ],
    "wof:name":"Our Lady of The Assumption",
    "wof:placetype":"venue"
},
  "geometry": {"coordinates":[-74.287774,41.002024],"type":"Point"}
}