{
  "type": "Feature",
  "properties": {
    "iso:country":"US",
    "sg:address":"638 Shadowlawn Dr",
    "sg:city":"Westfield",
    "sg:classifiers":[
        {
            "category":"Banks & Credit Unions",
            "subcategory":"Investment Brokerage",
            "type":"Services"
        }
    ],
    "sg:phone":"+1   ",
    "sg:postcode":"07090",
    "sg:province":"NJ",
    "sg:tags":[
        "security"
    ],
    "wof:name":"Stephen Dvorak & Company",
    "wof:placetype":"venue"
},
  "geometry": {"coordinates":[-74.350041,40.64034],"type":"Point"}
}