{
  "type": "Feature",
  "properties": {
    "addr:full":"136 Mercer St Woodbury Heights NJ 08097",
    "addr:housenumber":"136",
    "addr:postcode":"08097",
    "addr:street":"Mercer St",
    "iso:country":"US",
    "sg:address":"136 Mercer St",
    "sg:city":"Woodbury Heights",
    "sg:classifiers":[
        {
            "category":"Professional",
            "subcategory":"Art Services",
            "type":"Services"
        }
    ],
    "sg:phone":"+1 856 848 9236",
    "sg:postcode":"08097",
    "sg:province":"NJ",
    "sg:tags":[
        "commercial",
        "design"
    ],
    "wof:name":"Russell Farrell Illustration",
    "wof:placetype":"venue"
},
  "geometry": {"coordinates":[-75.15110799999999,39.820819],"type":"Point"}
}