{
  "type": "Feature",
  "properties": {
    "iso:country":"US",
    "sg:address":"510 Grove Ave",
    "sg:city":"Highland Park",
    "sg:classifiers":[
        {
            "category":"Freight",
            "type":"Transportation"
        }
    ],
    "sg:phone":"+1 732 572 0391",
    "sg:postcode":"08904",
    "sg:province":"NJ",
    "sg:tags":[
        "sea",
        "foreign"
    ],
    "wof:name":"T & T Enterprise International",
    "wof:placetype":"venue"
},
  "geometry": {"coordinates":[-74.422183,40.494299],"type":"Point"}
}