{
  "type": "Feature",
  "properties": {
    "iso:country":"US",
    "sg:address":"338 N Hook Rd",
    "sg:city":"Pennsville",
    "sg:classifiers":[
        {
            "category":"Manufacturing",
            "subcategory":"Food",
            "type":"Manufacturing & Wholesale Goods"
        },
        {
            "category":"Wholesale",
            "subcategory":"Dairy",
            "type":"Manufacturing & Wholesale Goods"
        }
    ],
    "sg:phone":"+1 856 678 3607",
    "sg:postcode":"08070",
    "sg:province":"NJ",
    "sg:tags":[
        "mfg",
        "frozen",
        "dessert",
        "ice",
        "desert",
        "cream"
    ],
    "wof:name":"Uncle Teddy's Custard Stand",
    "wof:placetype":"venue"
},
  "geometry": {"coordinates":[-75.487959,39.6683],"type":"Point"}
}