{
  "type": "Feature",
  "properties": {
    "iso:country":"US",
    "sg:address":"411 Palisade Ave",
    "sg:city":"Jersey City",
    "sg:classifiers":[
        {
            "category":"Building & Trades",
            "subcategory":"Construction",
            "type":"Services"
        }
    ],
    "sg:phone":"+1 201 709 5787",
    "sg:postcode":"07307",
    "sg:province":"NJ",
    "sg:tags":[
        "industrial"
    ],
    "wof:name":"Pati LLC",
    "wof:placetype":"venue"
},
  "geometry": {"coordinates":[-74.044646,40.743551],"type":"Point"}
}