{
  "type": "Feature",
  "properties": {
    "iso:country":"US",
    "sg:address":"400 Lanidex Plz",
    "sg:city":"Parsippany",
    "sg:classifiers":[
        {
            "category":"Professional",
            "subcategory":"Lawyer & Legal Services",
            "type":"Services"
        }
    ],
    "sg:phone":"+1 973 434 8800",
    "sg:postcode":"07054",
    "sg:province":"NJ",
    "sg:tags":[
        "attorney"
    ],
    "wof:name":"Samson & Wasserman",
    "wof:placetype":"venue"
},
  "geometry": {"coordinates":[-74.420542,40.862448],"type":"Point"}
}