{
  "type": "Feature",
  "properties": {
    "iso:country":"US",
    "sg:address":"260 Secaucus Rd",
    "sg:city":"Secaucus",
    "sg:classifiers":[
        {
            "category":"Restaurant",
            "type":"Food & Drink"
        }
    ],
    "sg:phone":"+1 201 422 0009",
    "sg:postcode":"07094",
    "sg:province":"NJ",
    "sg:tags":[
        "seafood"
    ],
    "wof:name":"Scandia Seafood New York Inc",
    "wof:placetype":"venue"
},
  "geometry": {"coordinates":[-74.057503,40.77],"type":"Point"}
}