{
  "type": "Feature",
  "properties": {
    "iso:country":"US",
    "sg:address":"134 Ramblewood Pkwy",
    "sg:city":"Mount Laurel",
    "sg:classifiers":[
        {
            "category":"Building & Trades",
            "subcategory":"Equipment Rental",
            "type":"Services"
        }
    ],
    "sg:phone":"+1 856 234 5794",
    "sg:postcode":"08054",
    "sg:province":"NJ",
    "sg:tags":[
        "transcription",
        "medical"
    ],
    "wof:name":"J V Esposito Word Processing",
    "wof:placetype":"venue"
},
  "geometry": {"coordinates":[-74.947692,39.925244],"type":"Point"}
}