{
  "type": "Feature",
  "properties": {
    "addr:full":"73 Center St West Milford NJ 07480",
    "addr:housenumber":"73",
    "addr:postcode":"07480",
    "addr:street":"Center St",
    "iso:country":"US",
    "sg:address":"73 Center St",
    "sg:city":"West Milford",
    "sg:classifiers":[
        {
            "category":"Real Estate",
            "subcategory":"Surveying",
            "type":"Services"
        }
    ],
    "sg:phone":"+1 973 728 5767",
    "sg:postcode":"07480",
    "sg:province":"NJ",
    "sg:tags":[
        "surveyor"
    ],
    "wof:name":"Mapco",
    "wof:placetype":"venue"
},
  "geometry": {"coordinates":[-74.367677,41.124536],"type":"Point"}
}