{
  "type": "Feature",
  "properties": {
    "addr:full":"3515 Bergenline Ave Union City NJ 07087",
    "addr:housenumber":"3515",
    "addr:postcode":"07087",
    "addr:street":"Bergenline Ave",
    "iso:country":"US",
    "sg:address":"3515 Bergenline Ave",
    "sg:city":"Union City",
    "sg:classifiers":[
        {
            "category":"Shopping",
            "subcategory":"Shoes",
            "type":"Retail Goods"
        }
    ],
    "sg:phone":"+1   ",
    "sg:postcode":"07087",
    "sg:province":"NJ",
    "wof:name":"Fabco Shoes 34",
    "wof:placetype":"venue"
},
  "geometry": {"coordinates":[-74.027568,40.774265],"type":"Point"}
}