{
  "type": "Feature",
  "properties": {
    "iso:country":"US",
    "sg:address":"341 Central Ave",
    "sg:city":"Jersey City",
    "sg:classifiers":[
        {
            "category":"Travel",
            "subcategory":"Travel Agent",
            "type":"Entertainment"
        }
    ],
    "sg:phone":"+1 201 653 1600",
    "sg:postcode":"07307",
    "sg:province":"NJ",
    "sg:tags":[
        "agency",
        "bureau"
    ],
    "sg:website":"www.dctravel.com",
    "wof:name":"D C Travel Bureau Inc",
    "wof:placetype":"venue"
},
  "geometry": {"coordinates":[-74.048469,40.747248],"type":"Point"}
}