{
  "type": "Feature",
  "properties": {
    "iso:country":"US",
    "sg:address":"556 4th St",
    "sg:city":"Hoboken",
    "sg:classifiers":[
        {
            "category":"Professional",
            "subcategory":"Management & Consulting",
            "type":"Services"
        }
    ],
    "sg:phone":"+1   ",
    "sg:postcode":"07030",
    "sg:province":"NJ",
    "sg:tags":[
        "business"
    ],
    "wof:name":"Orpheus Consulting Inc",
    "wof:placetype":"venue"
},
  "geometry": {"coordinates":[-74.03884499999999,40.742902],"type":"Point"}
}