{
  "type": "Feature",
  "properties": {
    "iso:country":"US",
    "sg:address":"111 S Orange Ave",
    "sg:city":"South Orange",
    "sg:classifiers":[
        {
            "category":"Professional",
            "subcategory":"Lawyer & Legal Services",
            "type":"Services"
        }
    ],
    "sg:phone":"+1 973 378 8485",
    "sg:postcode":"07079",
    "sg:province":"NJ",
    "wof:name":"C M Hartwyk Esq",
    "wof:placetype":"venue"
},
  "geometry": {"coordinates":[-74.256985,40.745573],"type":"Point"}
}