{
  "type": "Feature",
  "properties": {
    "iso:country":"US",
    "sg:address":"14 Chester Ave",
    "sg:city":"Irvington",
    "sg:classifiers":[
        {
            "category":"Banks & Credit Unions",
            "subcategory":"Investment Brokerage",
            "type":"Services"
        }
    ],
    "sg:phone":"+1   ",
    "sg:postcode":"07111",
    "sg:province":"NJ",
    "sg:tags":[
        "advisory"
    ],
    "wof:name":"Universal Financial Planning",
    "wof:placetype":"venue"
},
  "geometry": {"coordinates":[-74.230304,40.718756],"type":"Point"}
}