{
  "type": "Feature",
  "properties": {
    "iso:country":"US",
    "sg:address":"499 Washington Blvd",
    "sg:city":"Jersey City",
    "sg:classifiers":[
        {
            "category":"Insurance",
            "subcategory":"Hazard Insurance",
            "type":"Services"
        }
    ],
    "sg:phone":"+1 201 533 7000",
    "sg:postcode":"07310",
    "sg:province":"NJ",
    "sg:website":"www.cigna.com",
    "wof:name":"Cigna",
    "wof:placetype":"venue"
},
  "geometry": {"coordinates":[-74.0364,40.722698],"type":"Point"}
}