{
  "type": "Feature",
  "properties": {
    "iso:country":"US",
    "sg:address":"190 Homestead Ave",
    "sg:city":"Avenel",
    "sg:classifiers":[
        {
            "category":"Retail",
            "subcategory":"Repair Shop",
            "type":"Services"
        }
    ],
    "sg:phone":"+1   ",
    "sg:postcode":"07001",
    "sg:province":"NJ",
    "wof:name":"Real Time Data Inc",
    "wof:placetype":"venue"
},
  "geometry": {"coordinates":[-74.26371,40.579361],"type":"Point"}
}