{
  "type": "Feature",
  "properties": {
    "iso:country":"US",
    "sg:address":"11 Broadway",
    "sg:city":"Fair Lawn",
    "sg:classifiers":[
        {
            "category":"Organizations",
            "subcategory":"Non-profit Organization",
            "type":"Services"
        }
    ],
    "sg:phone":"+1 201 796 4540",
    "sg:postcode":"07410",
    "sg:province":"NJ",
    "sg:tags":[
        "information",
        "alcoholism",
        "treatment"
    ],
    "wof:name":"A A Alternative Counseling",
    "wof:placetype":"venue"
},
  "geometry": {"coordinates":[-74.121326,40.920178],"type":"Point"}
}