{
  "type": "Feature",
  "properties": {
    "addr:full":"763 Ave C Bayonne NJ 07002",
    "addr:housenumber":"763",
    "addr:postcode":"07002",
    "addr:street":"Ave C",
    "iso:country":"US",
    "sg:address":"763 Ave C",
    "sg:city":"Bayonne",
    "sg:classifiers":[
        {
            "category":"Social Services",
            "subcategory":"Child Care",
            "type":"Services"
        }
    ],
    "sg:phone":"+1 201 339 2229",
    "sg:postcode":"07002",
    "sg:province":"NJ",
    "wof:name":"Learning Zone",
    "wof:placetype":"venue"
},
  "geometry": {"coordinates":[-74.113411,40.673618],"type":"Point"}
}