{
  "type": "Feature",
  "properties": {
    "iso:country":"US",
    "sg:address":"83 Polk St",
    "sg:city":"Newark",
    "sg:classifiers":[
        {
            "category":"Professional",
            "subcategory":"Lawyer & Legal Services",
            "type":"Services"
        }
    ],
    "sg:phone":"+1 973 344 5542",
    "sg:postcode":"07105",
    "sg:province":"NJ",
    "wof:name":"Simoes Fausto",
    "wof:placetype":"venue"
},
  "geometry": {"coordinates":[-74.15351,40.731451],"type":"Point"}
}