{
  "type": "Feature",
  "properties": {
    "addr:full":"160 Franklin St Paterson NJ 07524",
    "addr:housenumber":"160",
    "addr:postcode":"07524",
    "addr:street":"Franklin St",
    "iso:country":"US",
    "sg:address":"160 Franklin St",
    "sg:city":"Paterson",
    "sg:classifiers":[
        {
            "category":"Social Services",
            "subcategory":"Child Care",
            "type":"Services"
        }
    ],
    "sg:phone":"+1   ",
    "sg:postcode":"07524",
    "sg:province":"NJ",
    "sg:tags":[
        "day"
    ],
    "wof:name":"Dotts Tots",
    "wof:placetype":"venue"
},
  "geometry": {"coordinates":[-74.157494,40.926087],"type":"Point"}
}