{
  "type": "Feature",
  "properties": {
    "addr:full":"181 Maplewood Ave Maplewood NJ 07040",
    "addr:housenumber":"181",
    "addr:postcode":"07040",
    "addr:street":"Maplewood Ave",
    "iso:country":"US",
    "sg:address":"181 Maplewood Ave",
    "sg:city":"Maplewood",
    "sg:classifiers":[
        {
            "category":"Shopping",
            "subcategory":"Shoes",
            "type":"Retail Goods"
        }
    ],
    "sg:phone":"+1 973 762 4433",
    "sg:postcode":"07040",
    "sg:province":"NJ",
    "wof:name":"March Kids Shoes",
    "wof:placetype":"venue"
},
  "geometry": {"coordinates":[-74.277924,40.730871],"type":"Point"}
}