{
  "type": "Feature",
  "properties": {
    "addr:full":"370 Broadway Paterson NJ 07501",
    "addr:housenumber":"370",
    "addr:postcode":"07501",
    "addr:street":"Broadway",
    "iso:country":"US",
    "sg:address":"370 Broadway",
    "sg:city":"Paterson",
    "sg:classifiers":[
        {
            "category":"Government",
            "subcategory":"Office",
            "type":"Public Place"
        }
    ],
    "sg:phone":"+1 973 977 4530",
    "sg:postcode":"07501",
    "sg:province":"NJ",
    "sg:tags":[
        "state",
        "inspection"
    ],
    "wof:name":"Wage & Hour Bureau",
    "wof:placetype":"venue"
},
  "geometry": {"coordinates":[-74.156093,40.918349],"type":"Point"}
}