{
  "type": "Feature",
  "properties": {
    "addr:full":"510 Anderson Ave Cliffside Park NJ 07010",
    "addr:housenumber":"510",
    "addr:postcode":"07010",
    "addr:street":"Anderson Ave",
    "iso:country":"US",
    "sg:address":"510 Anderson Ave",
    "sg:city":"Cliffside Park",
    "sg:classifiers":[
        {
            "category":"Personal",
            "subcategory":"Beauty Salon",
            "type":"Services"
        }
    ],
    "sg:phone":"+1 201 840 7898",
    "sg:postcode":"07010",
    "sg:province":"NJ",
    "sg:tags":[
        "shop"
    ],
    "wof:name":"Sonia Saphire Nails",
    "wof:placetype":"venue"
},
  "geometry": {"coordinates":[-73.99018599999999,40.821982],"type":"Point"}
}