{
  "type": "Feature",
  "properties": {
    "iso:country":"US",
    "sg:address":"20 Kings Hwy E",
    "sg:city":"Haddonfield",
    "sg:classifiers":[
        {
            "category":"Professional",
            "subcategory":"Lawyer & Legal Services",
            "type":"Services"
        }
    ],
    "sg:phone":"+1 856 795 6700",
    "sg:postcode":"08033",
    "sg:province":"NJ",
    "sg:tags":[
        "divorce",
        "law",
        "family"
    ],
    "wof:name":"Gerstein Grayson Llp",
    "wof:placetype":"venue"
},
  "geometry": {"coordinates":[-75.03469800000001,39.896599],"type":"Point"}
}