{
  "type": "Feature",
  "properties": {
    "addr:full":"114 S Orange Ave South Orange NJ 07079",
    "addr:housenumber":"114",
    "addr:postcode":"07079",
    "addr:street":"S Orange Ave",
    "iso:country":"US",
    "sg:address":"114 S Orange Ave",
    "sg:city":"South Orange",
    "sg:classifiers":[
        {
            "category":"Wholesale",
            "subcategory":"Auto Parts",
            "type":"Manufacturing & Wholesale Goods"
        }
    ],
    "sg:phone":"+1 973 763 1205",
    "sg:postcode":"07079",
    "sg:province":"NJ",
    "sg:tags":[
        "supply"
    ],
    "wof:name":"NAPA Auto Parts",
    "wof:placetype":"venue"
},
  "geometry": {"coordinates":[-74.25518599999999,40.745263],"type":"Point"}
}