{
  "type": "Feature",
  "properties": {
    "iso:country":"US",
    "sg:address":"75 W Front St",
    "sg:city":"Red Bank",
    "sg:classifiers":[
        {
            "category":"Utilities",
            "subcategory":"Telephone",
            "type":"Services"
        }
    ],
    "sg:phone":"+1 732 758 0800",
    "sg:postcode":"07701",
    "sg:province":"NJ",
    "sg:tags":[
        "communications",
        "consulting",
        "management"
    ],
    "wof:name":"Great Numbers",
    "wof:placetype":"venue"
},
  "geometry": {"coordinates":[-74.068603,40.351247],"type":"Point"}
}