{
  "type": "Feature",
  "properties": {
    "addr:full":"380 Catherine St Somerville NJ 08876",
    "addr:housenumber":"380",
    "addr:postcode":"08876",
    "addr:street":"Catherine St",
    "iso:country":"US",
    "sg:address":"380 Catherine St",
    "sg:city":"Somerville",
    "sg:classifiers":[
        {
            "category":"Real Estate",
            "subcategory":"Real Estate Services",
            "type":"Services"
        }
    ],
    "sg:phone":"+1   ",
    "sg:postcode":"08876",
    "sg:province":"NJ",
    "sg:tags":[
        "abstract",
        "legal",
        "title"
    ],
    "wof:name":"C M T Abstract Inc",
    "wof:placetype":"venue"
},
  "geometry": {"coordinates":[-74.60432900000001,40.573243],"type":"Point"}
}