{
  "type": "Feature",
  "properties": {
    "addr:full":"1985 Rutgers University Blvd. Lakewood NJ 08701",
    "addr:housenumber":"1985",
    "addr:postcode":"08701",
    "addr:street":"Rutgers University Blvd.",
    "iso:country":"US",
    "sg:address":"1985 Rutgers University Blvd.",
    "sg:city":"Lakewood",
    "sg:classifiers":[
        {
            "category":"Professional",
            "subcategory":"Computer Services",
            "type":"Services"
        }
    ],
    "sg:phone":"+1 888 436 6846",
    "sg:postcode":"08701",
    "sg:province":"NJ",
    "sg:tags":[
        "rubberecycle-mulch",
        "playground-rubber-mulch",
        "playground-safety",
        "playground-surfaces",
        "rubber-playgrounds",
        "playground",
        "gardening",
        "landscaping",
        "rubber-footing",
        "environment",
        "tire-mulch",
        "recycled-tires",
        "colored-rubber-mulch",
        "crumb-rubber",
        "shredded-tires",
        "rubbe"
    ],
    "sg:website":"http://www.rubberecycle.com/",
    "wof:name":"Rubberecycle",
    "wof:placetype":"venue"
},
  "geometry": {"coordinates":[-74.164118,40.070838],"type":"Point"}
}