{
  "type": "Feature",
  "properties": {
    "iso:country":"US",
    "sg:address":"361 Maple Pl",
    "sg:city":"Keyport",
    "sg:classifiers":[
        {
            "category":"Retail",
            "subcategory":"Funeral Services",
            "type":"Services"
        }
    ],
    "sg:phone":"+1 732 264 1352",
    "sg:postcode":"07735",
    "sg:province":"NJ",
    "sg:tags":[
        "director",
        "mortician"
    ],
    "wof:name":"Day Funeral Home Inc",
    "wof:placetype":"venue"
},
  "geometry": {"coordinates":[-74.21207099999999,40.427513],"type":"Point"}
}