{
  "type": "Feature",
  "properties": {
    "addr:full":"16 Reserve Ave Jersey City NJ 07307",
    "addr:housenumber":"16",
    "addr:postcode":"07307",
    "addr:street":"Reserve Ave",
    "iso:country":"US",
    "sg:address":"16 Reserve Ave",
    "sg:city":"Jersey City",
    "sg:classifiers":[
        {
            "category":"Building & Trades",
            "subcategory":"Cleaning & Sanitation",
            "type":"Services"
        }
    ],
    "sg:phone":"+1 201 798 9602",
    "sg:postcode":"07307",
    "sg:province":"NJ",
    "sg:tags":[
        "home",
        "janitor"
    ],
    "wof:name":"Jenny's House & Office Cleaning Services",
    "wof:placetype":"venue"
},
  "geometry": {"coordinates":[-74.060416,40.747685],"type":"Point"}
}