{
  "type": "Feature",
  "properties": {
    "addr:full":"106 Anelve Ave Neptune NJ 07753",
    "addr:housenumber":"106",
    "addr:postcode":"07753",
    "addr:street":"Anelve Ave",
    "iso:country":"US",
    "sg:address":"106 Anelve Ave",
    "sg:city":"Neptune",
    "sg:classifiers":[
        {
            "category":"Building & Trades",
            "subcategory":"Construction",
            "type":"Services"
        }
    ],
    "sg:phone":"+1 732 897 1332",
    "sg:postcode":"07753",
    "sg:province":"NJ",
    "sg:tags":[
        "house"
    ],
    "wof:name":"C&B Home Repair",
    "wof:placetype":"venue"
},
  "geometry": {"coordinates":[-74.030188,40.224049],"type":"Point"}
}