{
  "type": "Feature",
  "properties": {
    "addr:full":"127 E Centre St Nutley NJ 07110",
    "addr:housenumber":"127",
    "addr:postcode":"07110",
    "addr:street":"E Centre St",
    "iso:country":"US",
    "sg:address":"127 E Centre St",
    "sg:city":"Nutley",
    "sg:classifiers":[
        {
            "category":"Retail",
            "subcategory":"Auto Repair",
            "type":"Services"
        }
    ],
    "sg:phone":"+1 973 667 5671",
    "sg:postcode":"07110",
    "sg:province":"NJ",
    "sg:tags":[
        "body",
        "shop"
    ],
    "wof:name":"Three County Volkswagen Body Shop",
    "wof:placetype":"venue"
},
  "geometry": {"coordinates":[-74.146004,40.809299],"type":"Point"}
}