{
  "type": "Feature",
  "properties": {
    "addr:full":"49 Top Sall Rd Brick NJ 08723",
    "addr:housenumber":"49",
    "addr:postcode":"08723",
    "addr:street":"Top Sall Rd",
    "iso:country":"US",
    "sg:address":"49 Top Sall Rd",
    "sg:city":"Brick",
    "sg:classifiers":[
        {
            "category":"Health Services",
            "subcategory":"Chiropractor",
            "type":"Services"
        }
    ],
    "sg:phone":"+1 732 262 0840",
    "sg:postcode":"08723",
    "sg:province":"NJ",
    "wof:name":"Anthony J Esposito Dr",
    "wof:placetype":"venue"
},
  "geometry": {"coordinates":[-74.121392,40.028528],"type":"Point"}
}