{
  "type": "Feature",
  "properties": {
    "addr:full":"705 Frelinghuysen Ave Newark NJ 07114",
    "addr:housenumber":"705",
    "addr:postcode":"07114",
    "addr:street":"Frelinghuysen Ave",
    "iso:country":"US",
    "sg:address":"705 Frelinghuysen Ave",
    "sg:city":"Newark",
    "sg:classifiers":[
        {
            "category":"Food & Beverages",
            "subcategory":"Groceries & Convenience Stores",
            "type":"Retail Goods"
        }
    ],
    "sg:phone":"+1 973 824 1700",
    "sg:postcode":"07114",
    "sg:province":"NJ",
    "wof:name":"Shop & Bag Meat Center",
    "wof:placetype":"venue"
},
  "geometry": {"coordinates":[-74.198303,40.6973],"type":"Point"}
}