{
  "type": "Feature",
  "properties": {
    "addr:full":"276 Buttonwood Dr Paramus NJ 07652",
    "addr:housenumber":"276",
    "addr:postcode":"07652",
    "addr:street":"Buttonwood Dr",
    "iso:country":"US",
    "sg:address":"276 Buttonwood Dr",
    "sg:city":"Paramus",
    "sg:classifiers":[
        {
            "category":"Building & Trades",
            "subcategory":"Landscaping Services",
            "type":"Services"
        }
    ],
    "sg:phone":"+1 201 967 8097",
    "sg:postcode":"07652",
    "sg:province":"NJ",
    "sg:tags":[
        "arborist",
        "tree"
    ],
    "wof:name":"Dickinson Tree Service",
    "wof:placetype":"venue"
},
  "geometry": {"coordinates":[-74.06663500000001,40.938791],"type":"Point"}
}