{
  "type": "Feature",
  "properties": {
    "iso:country":"US",
    "sg:address":"510 State St",
    "sg:city":"Camden",
    "sg:classifiers":[
        {
            "category":"Education",
            "subcategory":"Vocational School",
            "type":"Public Place"
        }
    ],
    "sg:phone":"+1 856 964 3205",
    "sg:postcode":"08102",
    "sg:province":"NJ",
    "sg:tags":[
        "cooking"
    ],
    "wof:name":"Respond Inc",
    "wof:placetype":"venue"
},
  "geometry": {"coordinates":[-75.118663,39.952644],"type":"Point"}
}