{
  "type": "Feature",
  "properties": {
    "iso:country":"US",
    "sg:address":"63 Garrett Ln",
    "sg:city":"Willingboro",
    "sg:classifiers":[
        {
            "category":"Health Services",
            "subcategory":"Doctor",
            "type":"Services"
        }
    ],
    "sg:phone":"+1 609 871 0900",
    "sg:postcode":"08046",
    "sg:province":"NJ",
    "sg:tags":[
        "dentist"
    ],
    "wof:name":"Dennis Center the",
    "wof:placetype":"venue"
},
  "geometry": {"coordinates":[-74.881897,40.024799],"type":"Point"}
}