{
  "type": "Feature",
  "properties": {
    "addr:full":"401 S Van Brunt St Englewood NJ 07631",
    "addr:housenumber":"401",
    "addr:postcode":"07631",
    "addr:street":"S Van Brunt St",
    "iso:country":"US",
    "sg:address":"401 S Van Brunt St",
    "sg:city":"Englewood",
    "sg:classifiers":[
        {
            "category":"Banks & Credit Unions",
            "subcategory":"Bank",
            "type":"Services"
        }
    ],
    "sg:phone":"+1 201 833 9700",
    "sg:postcode":"07631",
    "sg:province":"NJ",
    "sg:tags":[
        "cashing",
        "check"
    ],
    "sg:website":"www.commutercheck.com",
    "wof:name":"Commuter Check Svc Corp",
    "wof:placetype":"venue"
},
  "geometry": {"coordinates":[-73.984145,40.88549],"type":"Point"}
}