{
  "type": "Feature",
  "properties": {
    "addr:full":"463 N Lake Shore Dr Brick NJ 08723",
    "addr:housenumber":"463",
    "addr:postcode":"08723",
    "addr:street":"N Lake Shore Dr",
    "iso:country":"US",
    "sg:address":"463 N Lake Shore Dr",
    "sg:city":"Brick",
    "sg:classifiers":[
        {
            "category":"Communications",
            "subcategory":"Film & Video Production",
            "type":"Services"
        }
    ],
    "sg:phone":"+1 732 477 4360",
    "sg:postcode":"08723",
    "sg:province":"NJ",
    "wof:name":"Martin Healey Productions",
    "wof:placetype":"venue"
},
  "geometry": {"coordinates":[-74.145836,40.04906],"type":"Point"}
}