{
  "type": "Feature",
  "properties": {
    "addr:full":"389 Passaic Ave Ste 2 Fairfield NJ 07004",
    "addr:housenumber":"389",
    "addr:postcode":"07004",
    "addr:street":"Passaic Ave Ste 2",
    "iso:country":"US",
    "sg:address":"389 Passaic Ave Ste 2",
    "sg:city":"Fairfield",
    "sg:classifiers":[
        {
            "category":"Banks & Credit Unions",
            "subcategory":"Investment Brokerage",
            "type":"Services"
        }
    ],
    "sg:phone":"+1 973 808 0869",
    "sg:postcode":"07004",
    "sg:province":"NJ",
    "sg:tags":[
        "investing"
    ],
    "sg:website":"www.capitaladvisors.com",
    "wof:name":"Capital Advisor's Group Inc",
    "wof:placetype":"venue"
},
  "geometry": {"coordinates":[-74.273201,40.887901],"type":"Point"}
}