{
  "type": "Feature",
  "properties": {
    "addr:full":"437 1st Ave Bellmawr NJ 08031",
    "addr:housenumber":"437",
    "addr:postcode":"08031",
    "addr:street":"1St Ave",
    "iso:country":"US",
    "sg:address":"437 1st Ave",
    "sg:city":"Bellmawr",
    "sg:classifiers":[
        {
            "category":"Building & Trades",
            "subcategory":"Construction",
            "type":"Services"
        }
    ],
    "sg:phone":"+1 856 931 9671",
    "sg:postcode":"08031",
    "sg:province":"NJ",
    "sg:tags":[
        "floor",
        "laying",
        "contractor"
    ],
    "wof:name":"James E Harbinson",
    "wof:placetype":"venue"
},
  "geometry": {"coordinates":[-75.066023,39.867331],"type":"Point"}
}