{
  "type": "Feature",
  "properties": {
    "iso:country":"US",
    "sg:address":"183 Smith St",
    "sg:city":"Perth Amboy",
    "sg:classifiers":[
        {
            "category":"Restaurant",
            "type":"Food & Drink"
        }
    ],
    "sg:phone":"+1 732 442 3311",
    "sg:postcode":"08861",
    "sg:province":"NJ",
    "sg:tags":[
        "pizza"
    ],
    "wof:name":"Antonio's Catering",
    "wof:placetype":"venue"
},
  "geometry": {"coordinates":[-74.268997,40.508801],"type":"Point"}
}