{
  "type": "Feature",
  "properties": {
    "addr:full":"13 Bright Rd New Egypt NJ 08533",
    "addr:housenumber":"13",
    "addr:postcode":"08533",
    "addr:street":"Bright Rd",
    "iso:country":"US",
    "sg:address":"13 Bright Rd",
    "sg:city":"New Egypt",
    "sg:classifiers":[
        {
            "category":"Building & Trades",
            "subcategory":"Construction",
            "type":"Services"
        }
    ],
    "sg:phone":"+1 609 758 2474",
    "sg:postcode":"08533",
    "sg:province":"NJ",
    "sg:tags":[
        "home",
        "house",
        "industrial",
        "co",
        "improvement"
    ],
    "wof:name":"Valentine Home Improvements",
    "wof:placetype":"venue"
},
  "geometry": {"coordinates":[-74.52493200000001,40.075422],"type":"Point"}
}