{
  "type": "Feature",
  "properties": {
    "addr:full":"14 Roberts Rd Warren NJ 07059",
    "addr:housenumber":"14",
    "addr:postcode":"07059",
    "addr:street":"Roberts Rd",
    "iso:country":"US",
    "sg:address":"14 Roberts Rd",
    "sg:city":"Warren",
    "sg:classifiers":[
        {
            "category":"Professional",
            "type":"Services"
        }
    ],
    "sg:phone":"+1   ",
    "sg:postcode":"07059",
    "sg:province":"NJ",
    "wof:name":"Lanieve LLC",
    "wof:placetype":"venue"
},
  "geometry": {"coordinates":[-74.473125,40.656493],"type":"Point"}
}