{
  "type": "Feature",
  "properties": {
    "addr:full":"127A Queen Anne Rd Bogota NJ 07603",
    "addr:housenumber":"127a",
    "addr:postcode":"07603",
    "addr:street":"Queen Anne Rd",
    "iso:country":"US",
    "sg:address":"127A Queen Anne Rd",
    "sg:city":"Bogota",
    "sg:classifiers":[
        {
            "category":"Professional",
            "type":"Services"
        },
        {
            "category":"Food & Beverages",
            "subcategory":"Liquor & Beverages",
            "type":"Retail Goods"
        }
    ],
    "sg:phone":"+1 201 488 7448",
    "sg:postcode":"07603",
    "sg:province":"NJ",
    "sg:tags":[
        "beer",
        "wine",
        "spirit",
        "caterer"
    ],
    "wof:name":"Bruno's Delicatessen & Liquors",
    "wof:placetype":"venue"
},
  "geometry": {"coordinates":[-74.02204500000001,40.869126],"type":"Point"}
}