{
  "type": "Feature",
  "properties": {
    "iso:country":"US",
    "sg:address":"687 Frelinghuysen Ave",
    "sg:city":"Newark",
    "sg:classifiers":[
        {
            "category":"Health Services",
            "subcategory":"Clinic",
            "type":"Services"
        }
    ],
    "sg:phone":"+1 973 799 0508",
    "sg:postcode":"07114",
    "sg:province":"NJ",
    "sg:tags":[
        "specialty",
        "outpatient"
    ],
    "wof:name":"American Habitare Counseling",
    "wof:placetype":"venue"
},
  "geometry": {"coordinates":[-74.198295,40.697841],"type":"Point"}
}