{
  "type": "Feature",
  "properties": {
    "iso:country":"US",
    "sg:address":"30 Alexauken Creek Rd",
    "sg:city":"Lambertville",
    "sg:classifiers":[
        {
            "category":"Building & Trades",
            "subcategory":"Construction",
            "type":"Services"
        }
    ],
    "sg:phone":"+1 609 397 1588",
    "sg:postcode":"08530",
    "sg:province":"NJ",
    "sg:tags":[
        "contractor"
    ],
    "wof:name":"Masterson Roofing",
    "wof:placetype":"venue"
},
  "geometry": {"coordinates":[-74.943896,40.386192],"type":"Point"}
}