{
  "type": "Feature",
  "properties": {
    "iso:country":"US",
    "sg:address":"1 Riverview Plz",
    "sg:city":"Red Bank",
    "sg:classifiers":[
        {
            "category":"Health Services",
            "subcategory":"Doctor",
            "type":"Services"
        }
    ],
    "sg:phone":"+1 732 530 2296",
    "sg:postcode":"07701",
    "sg:province":"NJ",
    "sg:tags":[
        "clinic"
    ],
    "wof:name":"Family Health Ctr-Meridian",
    "wof:placetype":"venue"
},
  "geometry": {"coordinates":[-74.063631,40.35333],"type":"Point"}
}