{
  "type": "Feature",
  "properties": {
    "iso:country":"US",
    "sg:address":"54 Girard Ave",
    "sg:city":"West Long Branch",
    "sg:classifiers":[
        {
            "category":"Professional",
            "type":"Services"
        }
    ],
    "sg:phone":"+1   ",
    "sg:postcode":"07764",
    "sg:province":"NJ",
    "wof:name":"Luce Di Speranza A New Je",
    "wof:placetype":"venue"
},
  "geometry": {"coordinates":[-74.018766,40.279663],"type":"Point"}
}