{
  "type": "Feature",
  "properties": {
    "addr:full":"23 Edgewood Rd Matawan NJ 07747",
    "addr:housenumber":"23",
    "addr:postcode":"07747",
    "addr:street":"Edgewood Rd",
    "iso:country":"US",
    "sg:address":"23 Edgewood Rd",
    "sg:city":"Matawan",
    "sg:classifiers":[
        {
            "category":"Professional",
            "subcategory":"Management & Consulting",
            "type":"Services"
        }
    ],
    "sg:phone":"+1   ",
    "sg:postcode":"07747",
    "sg:province":"NJ",
    "wof:name":"James P Heary",
    "wof:placetype":"venue"
},
  "geometry": {"coordinates":[-74.255865,40.413493],"type":"Point"}
}