{
  "type": "Feature",
  "properties": {
    "iso:country":"US",
    "sg:address":"26 Mayberry Dr",
    "sg:city":"Eatontown",
    "sg:classifiers":[
        {
            "category":"Wholesale",
            "subcategory":"Machinery & Supplies",
            "type":"Manufacturing & Wholesale Goods"
        }
    ],
    "sg:phone":"+1 732 804 2663",
    "sg:postcode":"07724",
    "sg:province":"NJ",
    "sg:tags":[
        "vending"
    ],
    "wof:name":"Bottoms-Up Vending",
    "wof:placetype":"venue"
},
  "geometry": {"coordinates":[-74.105833,40.283385],"type":"Point"}
}