{
  "type": "Feature",
  "properties": {
    "addr:full":"15 N Union St Lambertville NJ 08530",
    "addr:housenumber":"15",
    "addr:postcode":"08530",
    "addr:street":"N Union St",
    "iso:country":"US",
    "sg:address":"15 N Union St",
    "sg:city":"Lambertville",
    "sg:classifiers":[
        {
            "category":"Food & Beverages",
            "subcategory":"Dairy",
            "type":"Retail Goods"
        }
    ],
    "sg:phone":"+1   ",
    "sg:postcode":"08530",
    "sg:province":"NJ",
    "sg:tags":[
        "product"
    ],
    "wof:name":"Marishka Ice Creamery",
    "wof:placetype":"venue"
},
  "geometry": {"coordinates":[-74.945083,40.36618],"type":"Point"}
}