{
  "type": "Feature",
  "properties": {
    "addr:full":"1004 Wharton Rd Mount Laurel NJ 08054",
    "addr:housenumber":"1004",
    "addr:postcode":"08054",
    "addr:street":"Wharton Rd",
    "iso:country":"US",
    "sg:address":"1004 Wharton Rd",
    "sg:city":"Mount Laurel",
    "sg:classifiers":[
        {
            "category":"Professional",
            "type":"Services"
        }
    ],
    "sg:phone":"+1   ",
    "sg:postcode":"08054",
    "sg:province":"NJ",
    "wof:name":"Gideon Softworks Inc",
    "wof:placetype":"venue"
},
  "geometry": {"coordinates":[-74.928138,39.942407],"type":"Point"}
}