{
  "type": "Feature",
  "properties": {
    "iso:country":"US",
    "sg:address":"71 S State Rte 17",
    "sg:city":"Paramus",
    "sg:classifiers":[
        {
            "category":"Restaurant",
            "type":"Food & Drink"
        }
    ],
    "sg:phone":"+1 201 368 3380",
    "sg:postcode":"07653",
    "sg:province":"NJ",
    "sg:tags":[
        "mexican"
    ],
    "sg:website":"www.ontheborder.com/",
    "wof:name":"On The Border",
    "wof:placetype":"venue"
},
  "geometry": {"coordinates":[-74.072557,40.91543],"type":"Point"}
}