{
  "type": "Feature",
  "properties": {
    "iso:country":"US",
    "sg:address":"2305 Pacific Ave",
    "sg:city":"Atlantic City",
    "sg:classifiers":[
        {
            "category":"Bars & Pubs",
            "type":"Food & Drink"
        }
    ],
    "sg:phone":"+1   ",
    "sg:postcode":"08401",
    "sg:province":"NJ",
    "sg:tags":[
        "drinking"
    ],
    "wof:name":"Bull Shots",
    "wof:placetype":"venue"
},
  "geometry": {"coordinates":[-74.439589,39.355582],"type":"Point"}
}