{
  "type": "Feature",
  "properties": {
    "addr:full":"120 Union Blvd Totowa NJ 07512",
    "addr:housenumber":"120",
    "addr:postcode":"07512",
    "addr:street":"Union Blvd",
    "iso:country":"US",
    "sg:address":"120 Union Blvd",
    "sg:city":"Totowa",
    "sg:classifiers":[
        {
            "category":"Shopping",
            "subcategory":"Pharmacy",
            "type":"Retail Goods"
        }
    ],
    "sg:phone":"+1 973 956 9101",
    "sg:postcode":"07512",
    "sg:province":"NJ",
    "sg:tags":[
        "drugstore"
    ],
    "sg:website":"www.cvs.com",
    "wof:name":"Cvs/Pharmacy",
    "wof:placetype":"venue"
},
  "geometry": {"coordinates":[-74.20410200000001,40.909302],"type":"Point"}
}