{
  "type": "Feature",
  "properties": {
    "iso:country":"US",
    "sg:address":"3528 US Hwy 9",
    "sg:city":"Howell",
    "sg:classifiers":[
        {
            "category":"Travel",
            "subcategory":"Travel Agent",
            "type":"Entertainment"
        }
    ],
    "sg:phone":"+1 732 367 3333",
    "sg:postcode":"07731",
    "sg:province":"NJ",
    "sg:tags":[
        "agency",
        "bureau"
    ],
    "wof:name":"Howell Travel Inc",
    "wof:placetype":"venue"
},
  "geometry": {"coordinates":[-74.23286400000001,40.160295],"type":"Point"}
}