{
  "type": "Feature",
  "properties": {
    "addr:full":"903 US Hwy 202 Raritan NJ 08869",
    "addr:housenumber":"903",
    "addr:postcode":"08869",
    "addr:street":"Us Hwy 202",
    "iso:country":"US",
    "sg:address":"903 US Hwy 202",
    "sg:city":"Raritan",
    "sg:classifiers":[
        {
            "category":"Real Estate",
            "subcategory":"Real Estate Agent",
            "type":"Services"
        }
    ],
    "sg:phone":"+1 908 707 9990",
    "sg:postcode":"08869",
    "sg:province":"NJ",
    "wof:name":"Re/Max Real Estate",
    "wof:placetype":"venue"
},
  "geometry": {"coordinates":[-74.64212000000001,40.574169],"type":"Point"}
}