{
  "type": "Feature",
  "properties": {
    "addr:full":"90 Airport Rd Bedminster NJ 07921",
    "addr:housenumber":"90",
    "addr:postcode":"07921",
    "addr:street":"Airport Rd",
    "iso:country":"US",
    "sg:address":"90 Airport Rd",
    "sg:city":"Bedminster",
    "sg:classifiers":[
        {
            "category":"Building & Trades",
            "subcategory":"Construction",
            "type":"Services"
        }
    ],
    "sg:phone":"+1 908 685 1115",
    "sg:postcode":"07921",
    "sg:province":"NJ",
    "sg:tags":[
        "carpentry",
        "contractor"
    ],
    "wof:name":"Universal Construction",
    "wof:placetype":"venue"
},
  "geometry": {"coordinates":[-74.664286,40.62606],"type":"Point"}
}