{
  "type": "Feature",
  "properties": {
    "addr:full":"15 Highwood Ave Tenafly NJ 07670",
    "addr:housenumber":"15",
    "addr:postcode":"07670",
    "addr:street":"Highwood Ave",
    "iso:country":"US",
    "sg:address":"15 Highwood Ave",
    "sg:city":"Tenafly",
    "sg:classifiers":[
        {
            "category":"Food & Beverages",
            "subcategory":"Specialty",
            "type":"Retail Goods"
        }
    ],
    "sg:phone":"+1 201 567 5688",
    "sg:postcode":"07670",
    "sg:province":"NJ",
    "sg:tags":[
        "gourmet",
        "shop"
    ],
    "wof:name":"Tenafly Gourmet Farm",
    "wof:placetype":"venue"
},
  "geometry": {"coordinates":[-73.962784,40.926559],"type":"Point"}
}