{
  "type": "Feature",
  "properties": {
    "addr:full":"2600 John F Kennedy Blvd Jersey City NJ 07306",
    "addr:housenumber":"2600",
    "addr:postcode":"07306",
    "addr:street":"John F Kennedy Blvd",
    "iso:country":"US",
    "sg:address":"2600 John F Kennedy Blvd",
    "sg:city":"Jersey City",
    "sg:classifiers":[
        {
            "category":"Retail",
            "subcategory":"Auto Repair",
            "type":"Services"
        }
    ],
    "sg:phone":"+1 201 451 5035",
    "sg:postcode":"07306",
    "sg:province":"NJ",
    "sg:tags":[
        "general"
    ],
    "wof:name":"East Orange Motors Inc",
    "wof:placetype":"venue"
},
  "geometry": {"coordinates":[-74.072737,40.725415],"type":"Point"}
}