{
  "type": "Feature",
  "properties": {
    "addr:full":"107 Stover Ave North Arlington NJ 07031",
    "addr:housenumber":"107",
    "addr:postcode":"07031",
    "addr:street":"Stover Ave North",
    "iso:country":"US",
    "sg:address":"107 Stover Ave",
    "sg:city":"North Arlington",
    "sg:classifiers":[
        {
            "category":"Manufacturing",
            "subcategory":"Tools & Machinery",
            "type":"Manufacturing & Wholesale Goods"
        }
    ],
    "sg:phone":"+1 201 997 5388",
    "sg:postcode":"07031",
    "sg:province":"NJ",
    "sg:tags":[
        "development",
        "network"
    ],
    "wof:name":"M C System Solutions LLC",
    "wof:placetype":"venue"
},
  "geometry": {"coordinates":[-74.13598399999999,40.793179],"type":"Point"}
}