{
  "type": "Feature",
  "properties": {
    "iso:country":"US",
    "sg:address":"257 Hillside Ave",
    "sg:city":"Leonia",
    "sg:classifiers":[
        {
            "category":"Retail",
            "subcategory":"Repair Shop",
            "type":"Services"
        }
    ],
    "sg:phone":"+1 201 399 0315",
    "sg:postcode":"07605",
    "sg:province":"NJ",
    "sg:tags":[
        "lock",
        "locksmith"
    ],
    "wof:name":"24 Hour Emergency Locksmith",
    "wof:placetype":"venue"
},
  "geometry": {"coordinates":[-73.985544,40.865494],"type":"Point"}
}