{
  "type": "Feature",
  "properties": {
    "iso:country":"US",
    "sg:address":"1230 State Rte 34",
    "sg:city":"Matawan",
    "sg:classifiers":[
        {
            "category":"Communications",
            "type":"Services"
        }
    ],
    "sg:phone":"+1 732 332 9442",
    "sg:postcode":"07747",
    "sg:province":"NJ",
    "sg:tags":[
        "business"
    ],
    "wof:name":"C 2 Connect",
    "wof:placetype":"venue"
},
  "geometry": {"coordinates":[-74.219379,40.389522],"type":"Point"}
}