{
  "type": "Feature",
  "properties": {
    "iso:country":"US",
    "sg:address":"26 Paris Ave",
    "sg:city":"Northvale",
    "sg:classifiers":[
        {
            "category":"Restaurant",
            "type":"Food & Drink"
        }
    ],
    "sg:phone":"+1 201 768 7171",
    "sg:postcode":"07647",
    "sg:province":"NJ",
    "sg:tags":[
        "catering",
        "caterer",
        "facility"
    ],
    "wof:name":"Rockleigh Country Club",
    "wof:placetype":"venue"
},
  "geometry": {"coordinates":[-73.93647,41.003631],"type":"Point"}
}