{
  "type": "Feature",
  "properties": {
    "iso:country":"US",
    "sg:address":"418 Main St",
    "sg:city":"Metuchen",
    "sg:classifiers":[
        {
            "category":"Shopping",
            "subcategory":"Clothing, Apparel, & Fashions",
            "type":"Retail Goods"
        }
    ],
    "sg:phone":"+1 732 548 2998",
    "sg:postcode":"08840",
    "sg:province":"NJ",
    "wof:name":"Mili",
    "wof:placetype":"venue"
},
  "geometry": {"coordinates":[-74.361158,40.541094],"type":"Point"}
}