{
  "type": "Feature",
  "properties": {
    "addr:full":"584 S Delsea Dr Vineland NJ 08360",
    "addr:housenumber":"584",
    "addr:postcode":"08360",
    "addr:street":"S Delsea Dr",
    "iso:country":"US",
    "sg:address":"584 S Delsea Dr",
    "sg:city":"Vineland",
    "sg:classifiers":[
        {
            "category":"Restaurant",
            "type":"Food & Drink"
        }
    ],
    "sg:phone":"+1   ",
    "sg:postcode":"08360",
    "sg:province":"NJ",
    "sg:tags":[
        "eating"
    ],
    "wof:name":"In Stewarts Drive",
    "wof:placetype":"venue"
},
  "geometry": {"coordinates":[-75.04379299999999,39.478392],"type":"Point"}
}