{
  "type": "Feature",
  "properties": {
    "addr:full":"1231 Clements Bridge Rd Woodbury NJ 08096",
    "addr:housenumber":"1231",
    "addr:postcode":"08096",
    "addr:street":"Clements Bridge Rd",
    "iso:country":"US",
    "sg:address":"1231 Clements Bridge Rd",
    "sg:city":"Woodbury",
    "sg:classifiers":[
        {
            "category":"Retail",
            "subcategory":"Repair Shop",
            "type":"Services"
        }
    ],
    "sg:phone":"+1 212 295 4505",
    "sg:postcode":"08096",
    "sg:province":"NJ",
    "sg:tags":[
        "stereo",
        "audio",
        "video",
        "equipment-service"
    ],
    "wof:name":"ARC Installations",
    "wof:placetype":"venue"
},
  "geometry": {"coordinates":[-75.114868,39.827549],"type":"Point"}
}