{
  "type": "Feature",
  "properties": {
    "iso:country":"US",
    "sg:address":"530 Morris Ave",
    "sg:city":"Springfield",
    "sg:classifiers":[
        {
            "category":"Health Services",
            "subcategory":"Doctor",
            "type":"Services"
        }
    ],
    "sg:phone":"+1 973 467 6738",
    "sg:postcode":"07081",
    "sg:province":"NJ",
    "sg:tags":[
        "physician",
        "surgeon"
    ],
    "wof:name":"Asthma Care Ctr",
    "wof:placetype":"venue"
},
  "geometry": {"coordinates":[-74.32304999999999,40.716049],"type":"Point"}
}