{
  "type": "Feature",
  "properties": {
    "iso:country":"US",
    "sg:address":"28 Old Milford Ln",
    "sg:city":"West Milford",
    "sg:classifiers":[
        {
            "category":"Professional",
            "subcategory":"Lawyer & Legal Services",
            "type":"Services"
        }
    ],
    "sg:phone":"+1   ",
    "sg:postcode":"07480",
    "sg:province":"NJ",
    "wof:name":"Affinito and Associates",
    "wof:placetype":"venue"
},
  "geometry": {"coordinates":[-74.40800900000001,41.103325],"type":"Point"}
}