{
  "type": "Feature",
  "properties": {
    "addr:full":"34 Columbia St Newark NJ 07102",
    "addr:housenumber":"34",
    "addr:postcode":"07102",
    "addr:street":"Columbia",
    "iso:country":"US",
    "sg:address":"34 Columbia St",
    "sg:city":"Newark",
    "sg:classifiers":[
        {
            "category":"Restaurant",
            "type":"Food & Drink"
        }
    ],
    "sg:phone":"+1   ",
    "sg:postcode":"07102",
    "sg:province":"NJ",
    "sg:tags":[
        "eating"
    ],
    "wof:name":"Frank G Eng Consulting In",
    "wof:placetype":"venue"
},
  "geometry": {"coordinates":[-74.169507,40.731434],"type":"Point"}
}