{
  "type": "Feature",
  "properties": {
    "addr:full":"25 Hunter Pl Fair Lawn NJ 07410",
    "addr:housenumber":"25",
    "addr:postcode":"07410",
    "addr:street":"Hunter Pl",
    "iso:country":"US",
    "sg:address":"25 Hunter Pl",
    "sg:city":"Fair Lawn",
    "sg:classifiers":[
        {
            "category":"Wholesale",
            "subcategory":"Photographic Equipment",
            "type":"Manufacturing & Wholesale Goods"
        }
    ],
    "sg:phone":"+1 201 794 7999",
    "sg:postcode":"07410",
    "sg:province":"NJ",
    "sg:tags":[
        "photo"
    ],
    "wof:name":"Novelens",
    "wof:placetype":"venue"
},
  "geometry": {"coordinates":[-74.11289499999999,40.949859],"type":"Point"}
}