{
  "type": "Feature",
  "properties": {
    "iso:country":"US",
    "sg:address":"43 Tyson Pl",
    "sg:city":"Bergenfield",
    "sg:classifiers":[
        {
            "category":"Building & Trades",
            "subcategory":"Construction",
            "type":"Services"
        }
    ],
    "sg:phone":"+1 551 486 6648",
    "sg:postcode":"07621",
    "sg:province":"NJ",
    "sg:tags":[
        "house"
    ],
    "wof:name":"Layne Builders LLC",
    "wof:placetype":"venue"
},
  "geometry": {"coordinates":[-73.999318,40.92866],"type":"Point"}
}