{
  "type": "Feature",
  "properties": {
    "iso:country":"US",
    "sg:address":"1198 State Hwy 40",
    "sg:city":"Pilesgrove",
    "sg:classifiers":[
        {
            "category":"Wholesale",
            "subcategory":"Medical Equipment & Supplies",
            "type":"Manufacturing & Wholesale Goods"
        }
    ],
    "sg:phone":"+1 856 769 5449",
    "sg:postcode":"08098",
    "sg:province":"NJ",
    "sg:tags":[
        "physician",
        "surgeon"
    ],
    "wof:name":"DBS O2 & Medical Equipment",
    "wof:placetype":"venue"
},
  "geometry": {"coordinates":[-75.30263100000001,39.647143],"type":"Point"}
}