{
  "type": "Feature",
  "properties": {
    "iso:country":"US",
    "sg:address":"203 Kresson Gibbsboro Rd",
    "sg:city":"Voorhees",
    "sg:classifiers":[
        {
            "category":"Personal",
            "subcategory":"Beauty Salon",
            "type":"Services"
        }
    ],
    "sg:phone":"+1   ",
    "sg:postcode":"08043",
    "sg:province":"NJ",
    "sg:tags":[
        "shop"
    ],
    "wof:name":"Lisa Ann",
    "wof:placetype":"venue"
},
  "geometry": {"coordinates":[-74.940217,39.845542],"type":"Point"}
}