{
  "type": "Feature",
  "properties": {
    "iso:country":"US",
    "sg:address":"733 W Side Ave",
    "sg:city":"Jersey City",
    "sg:classifiers":[
        {
            "category":"Food & Beverages",
            "subcategory":"Groceries & Convenience Stores",
            "type":"Retail Goods"
        }
    ],
    "sg:phone":"+1 201 333 0071",
    "sg:postcode":"07306",
    "sg:province":"NJ",
    "sg:tags":[
        "grocer"
    ],
    "wof:name":"Lucille's West Indian Grocery",
    "wof:placetype":"venue"
},
  "geometry": {"coordinates":[-74.077499,40.725601],"type":"Point"}
}