{
  "type": "Feature",
  "properties": {
    "addr:full":"5515 Jackson St West New York NJ 07093",
    "addr:housenumber":"5515",
    "addr:postcode":"nj 07093",
    "addr:street":"Jackson St West",
    "iso:country":"US",
    "sg:address":"5515 Jackson St",
    "sg:city":"West New York",
    "sg:classifiers":[
        {
            "category":"Organizations",
            "subcategory":"Religious Organization",
            "type":"Services"
        }
    ],
    "sg:phone":"+1   ",
    "sg:postcode":"07093",
    "sg:province":"NJ",
    "wof:name":"Kingdom Hall Jhovahs Witnesses",
    "wof:placetype":"venue"
},
  "geometry": {"coordinates":[-74.02093499999999,40.787632],"type":"Point"}
}