{
  "type": "Feature",
  "properties": {
    "addr:full":"400 Delanco Rd Beverly NJ 08010",
    "addr:housenumber":"400",
    "addr:postcode":"08010",
    "addr:street":"Delanco Rd",
    "iso:country":"US",
    "sg:address":"400 Delanco Rd",
    "sg:city":"Beverly",
    "sg:classifiers":[
        {
            "category":"Government",
            "subcategory":"Fire Station",
            "type":"Public Place"
        }
    ],
    "sg:phone":"+1   ",
    "sg:postcode":"08010",
    "sg:province":"NJ",
    "sg:tags":[
        "department"
    ],
    "wof:name":"Edgewater Pk Fire Dist",
    "wof:placetype":"venue"
},
  "geometry": {"coordinates":[-74.911558,40.044962],"type":"Point"}
}