{
  "type": "Feature",
  "properties": {
    "addr:full":"120 State Rte 156 Trenton NJ 08620",
    "addr:housenumber":"120",
    "addr:postcode":"08620",
    "addr:street":"State Rte 156",
    "iso:country":"US",
    "sg:address":"120 State Rte 156",
    "sg:city":"Trenton",
    "sg:classifiers":[
        {
            "category":"Real Estate",
            "subcategory":"Real Estate Services",
            "type":"Services"
        }
    ],
    "sg:phone":"+1 609 581 2054",
    "sg:postcode":"08620",
    "sg:province":"NJ",
    "sg:tags":[
        "company",
        "abstract",
        "title"
    ],
    "wof:name":"Empire Title & Abstract Agen",
    "wof:placetype":"venue"
},
  "geometry": {"coordinates":[-74.670891,40.178355],"type":"Point"}
}