{
  "type": "Feature",
  "properties": {
    "iso:country":"US",
    "sg:address":"565 Little Mill Rd",
    "sg:city":"Monroeville",
    "sg:classifiers":[
        {
            "category":"Building & Trades",
            "subcategory":"Electrical",
            "type":"Services"
        }
    ],
    "sg:phone":"+1 856 694 3540",
    "sg:postcode":"08343",
    "sg:province":"NJ",
    "sg:tags":[
        "electrical",
        "contractor"
    ],
    "wof:name":"Rizzuto Electric",
    "wof:placetype":"venue"
},
  "geometry": {"coordinates":[-75.10790799999999,39.631226],"type":"Point"}
}