{
  "type": "Feature",
  "properties": {
    "iso:country":"US",
    "sg:address":"15 State Highway 73 N",
    "sg:city":"Cedar Brook",
    "sg:classifiers":[
        {
            "category":"Restaurant",
            "type":"Food & Drink"
        }
    ],
    "sg:phone":"+1 609 561 1296",
    "sg:postcode":"08018",
    "sg:province":"NJ",
    "wof:name":"Francesco's",
    "wof:placetype":"venue"
},
  "geometry": {"coordinates":[-74.90300000000001,39.724602],"type":"Point"}
}