{
  "type": "Feature",
  "properties": {
    "iso:country":"US",
    "sg:address":"1232 Hooper Ave",
    "sg:city":"Toms River",
    "sg:classifiers":[
        {
            "category":"Professional",
            "type":"Services"
        }
    ],
    "sg:phone":"+1   ",
    "sg:postcode":"08753",
    "sg:province":"NJ",
    "wof:name":"A Cuttler",
    "wof:placetype":"venue"
},
  "geometry": {"coordinates":[-74.181606,39.981586],"type":"Point"}
}