{
  "type": "Feature",
  "properties": {
    "iso:country":"US",
    "sg:address":"285 Gordons Corner Rd",
    "sg:city":"Englishtown",
    "sg:classifiers":[
        {
            "category":"Restaurant",
            "type":"Food & Drink"
        }
    ],
    "sg:phone":"+1   ",
    "sg:postcode":"07726",
    "sg:province":"NJ",
    "sg:tags":[
        "eating"
    ],
    "wof:name":"Cmbc Corp",
    "wof:placetype":"venue"
},
  "geometry": {"coordinates":[-74.32207699999999,40.309053],"type":"Point"}
}