{
  "type": "Feature",
  "properties": {
    "iso:country":"US",
    "sg:address":"226 Wilson Ave",
    "sg:city":"Mount Ephraim",
    "sg:classifiers":[
        {
            "category":"Restaurant",
            "type":"Food & Drink"
        }
    ],
    "sg:phone":"+1 856 456 4535",
    "sg:postcode":"08059",
    "sg:province":"NJ",
    "sg:tags":[
        "eating"
    ],
    "wof:name":"Browns Stop In Restaurant",
    "wof:placetype":"venue"
},
  "geometry": {"coordinates":[-75.097397,39.893902],"type":"Point"}
}