{
  "type": "Feature",
  "properties": {
    "iso:country":"US",
    "sg:address":"142 Jefferson St",
    "sg:city":"Newark",
    "sg:classifiers":[
        {
            "category":"Organizations",
            "subcategory":"Religious Organization",
            "type":"Services"
        }
    ],
    "sg:phone":"+1 973 344 8322",
    "sg:postcode":"07105",
    "sg:province":"NJ",
    "wof:name":"St James Church",
    "wof:placetype":"venue"
},
  "geometry": {"coordinates":[-74.162836,40.728213],"type":"Point"}
}