{
  "type": "Feature",
  "properties": {
    "iso:country":"US",
    "sg:address":"430 Commerce Ln",
    "sg:city":"West Berlin",
    "sg:classifiers":[
        {
            "category":"Wholesale",
            "subcategory":"Meat",
            "type":"Manufacturing & Wholesale Goods"
        }
    ],
    "sg:phone":"+1 856 719 9311",
    "sg:postcode":"08091",
    "sg:province":"NJ",
    "sg:tags":[
        "product",
        "broker"
    ],
    "wof:name":"International Entrees Corp",
    "wof:placetype":"venue"
},
  "geometry": {"coordinates":[-74.92955600000001,39.81056],"type":"Point"}
}