{
  "type": "Feature",
  "properties": {
    "addr:full":"272 State Route 10 Randolph NJ 07869",
    "addr:housenumber":"272",
    "addr:postcode":"07869",
    "addr:street":"State Route 10",
    "iso:country":"US",
    "sg:address":"272 State Route 10",
    "sg:city":"Randolph",
    "sg:classifiers":[
        {
            "category":"Retail",
            "subcategory":"Funeral Services",
            "type":"Services"
        }
    ],
    "sg:phone":"+1 973 366 7400",
    "sg:postcode":"07869",
    "sg:province":"NJ",
    "sg:tags":[
        "cemetery"
    ],
    "wof:name":"Tuttle Dean T Funeral Director",
    "wof:placetype":"venue"
},
  "geometry": {"coordinates":[-74.54769899999999,40.870098],"type":"Point"}
}