{
  "type": "Feature",
  "properties": {
    "addr:full":"290 Madison Ave Ste 2 Morristown NJ 07960",
    "addr:housenumber":"290",
    "addr:postcode":"07960",
    "addr:street":"Madison Ave Ste 2",
    "iso:country":"US",
    "sg:address":"290 Madison Ave Ste 2",
    "sg:city":"Morristown",
    "sg:classifiers":[
        {
            "category":"Health Services",
            "subcategory":"Doctor",
            "type":"Services"
        }
    ],
    "sg:phone":"+1 973 538 5338",
    "sg:postcode":"07960",
    "sg:province":"NJ",
    "sg:tags":[
        "surgeon",
        "oral"
    ],
    "wof:name":"Strambi Rudolph DDS",
    "wof:placetype":"venue"
},
  "geometry": {"coordinates":[-74.451103,40.783298],"type":"Point"}
}