{
  "type": "Feature",
  "properties": {
    "iso:country":"US",
    "sg:address":"335 Trenton Ave",
    "sg:city":"Paterson",
    "sg:classifiers":[
        {
            "category":"Building & Trades",
            "subcategory":"Landscaping Services",
            "type":"Services"
        }
    ],
    "sg:phone":"+1 973 977 8910",
    "sg:postcode":"07503",
    "sg:province":"NJ",
    "wof:name":"Jcr Landscaping Design & Tree",
    "wof:placetype":"venue"
},
  "geometry": {"coordinates":[-74.14569400000001,40.894593],"type":"Point"}
}