{
  "type": "Feature",
  "properties": {
    "iso:country":"US",
    "sg:address":"2502 Honeysuckle Ln",
    "sg:city":"Point Pleasant Beach",
    "sg:classifiers":[
        {
            "category":"Professional",
            "subcategory":"Business Services",
            "type":"Services"
        }
    ],
    "sg:phone":"+1   ",
    "sg:postcode":"08742",
    "sg:province":"NJ",
    "wof:name":"Gemini Home Interiors",
    "wof:placetype":"venue"
},
  "geometry": {"coordinates":[-74.079573,40.070283],"type":"Point"}
}