{
  "type": "Feature",
  "properties": {
    "iso:country":"US",
    "sg:address":"57 Mountain Ave",
    "sg:city":"Princeton",
    "sg:classifiers":[
        {
            "category":"Museum",
            "type":"Entertainment"
        }
    ],
    "sg:phone":"+1   ",
    "sg:postcode":"08540",
    "sg:province":"NJ",
    "sg:tags":[
        "gallery"
    ],
    "wof:name":"Mountain Lakes House",
    "wof:placetype":"venue"
},
  "geometry": {"coordinates":[-74.672292,40.357087],"type":"Point"}
}