{
  "type": "Feature",
  "properties": {
    "addr:full":"513 Saint Louis Ave Pt Pleasant Bch NJ 08742",
    "addr:housenumber":"513",
    "addr:postcode":"08742",
    "addr:street":"Saint Louis Ave Pt",
    "iso:country":"US",
    "sg:address":"513 Saint Louis Ave",
    "sg:city":"Pt Pleasant Bch",
    "sg:classifiers":[
        {
            "category":"Recreation",
            "type":"Entertainment"
        },
        {
            "category":"Organizations",
            "subcategory":"Community Association",
            "type":"Services"
        }
    ],
    "sg:phone":"+1 732 899 5930",
    "sg:postcode":"08742",
    "sg:province":"NJ",
    "sg:tags":[
        "club",
        "membership"
    ],
    "wof:name":"Woman's Club Of Point Pleasant",
    "wof:placetype":"venue"
},
  "geometry": {"coordinates":[-74.046081,40.091127],"type":"Point"}
}