{
  "type": "Feature",
  "properties": {
    "addr:full":"263 Union St Lodi NJ 07644",
    "addr:housenumber":"263",
    "addr:postcode":"07644",
    "addr:street":"Union St",
    "iso:country":"US",
    "sg:address":"263 Union St",
    "sg:city":"Lodi",
    "sg:classifiers":[
        {
            "category":"Professional",
            "subcategory":"Business Services",
            "type":"Services"
        }
    ],
    "sg:phone":"+1   ",
    "sg:postcode":"07644",
    "sg:province":"NJ",
    "wof:name":"Mid Atlantic Assoc For Ed",
    "wof:placetype":"venue"
},
  "geometry": {"coordinates":[-74.075604,40.872113],"type":"Point"}
}