{
  "type": "Feature",
  "properties": {
    "addr:full":"30 Galesi Dr Wayne NJ 07470",
    "addr:housenumber":"30",
    "addr:postcode":"07470",
    "addr:street":"Galesi Dr",
    "iso:country":"US",
    "sg:address":"30 Galesi Dr",
    "sg:city":"Wayne",
    "sg:classifiers":[
        {
            "category":"Building & Trades",
            "subcategory":"Construction",
            "type":"Services"
        }
    ],
    "sg:phone":"+1 201 585 5300",
    "sg:postcode":"07470",
    "sg:province":"NJ",
    "sg:tags":[
        "excavating",
        "contractor"
    ],
    "sg:website":"www.mjpaquet.com",
    "wof:name":"M J Paquet Inc",
    "wof:placetype":"venue"
},
  "geometry": {"coordinates":[-74.24453699999999,40.896126],"type":"Point"}
}