{
  "type": "Feature",
  "properties": {
    "addr:full":"999 Airport Rd Lakewood NJ 08701",
    "addr:housenumber":"999",
    "addr:postcode":"08701",
    "addr:street":"Airport Rd",
    "iso:country":"US",
    "sg:address":"999 Airport Rd",
    "sg:city":"Lakewood",
    "sg:classifiers":[
        {
            "category":"Professional",
            "subcategory":"Research",
            "type":"Services"
        }
    ],
    "sg:phone":"+1 732 370 6636",
    "sg:postcode":"08701",
    "sg:province":"NJ",
    "sg:tags":[
        "environmental",
        "ecological"
    ],
    "wof:name":"Environmental Remediation&",
    "wof:placetype":"venue"
},
  "geometry": {"coordinates":[-74.17994299999999,40.058648],"type":"Point"}
}