{
  "type": "Feature",
  "properties": {
    "addr:full":"186 5th Ave Paterson NJ 07524",
    "addr:housenumber":"186",
    "addr:postcode":"07524",
    "addr:street":"5Th Ave",
    "iso:country":"US",
    "sg:address":"186 5th Ave",
    "sg:city":"Paterson",
    "sg:classifiers":[
        {
            "category":"Education",
            "subcategory":"Special Training",
            "type":"Public Place"
        }
    ],
    "sg:phone":"+1 973 523 0808",
    "sg:postcode":"07524",
    "sg:province":"NJ",
    "sg:tags":[
        "school",
        "language"
    ],
    "wof:name":"ESL English School",
    "wof:placetype":"venue"
},
  "geometry": {"coordinates":[-74.15358999999999,40.934743],"type":"Point"}
}