{
  "type": "Feature",
  "properties": {
    "addr:full":"15 Citadel Dr Jackson NJ 08527",
    "addr:housenumber":"15",
    "addr:postcode":"08527",
    "addr:street":"Citadel Dr",
    "iso:country":"US",
    "sg:address":"15 Citadel Dr",
    "sg:city":"Jackson",
    "sg:classifiers":[
        {
            "category":"Shopping",
            "subcategory":"Hobbies, Toys, & Games",
            "type":"Retail Goods"
        }
    ],
    "sg:phone":"+1 732 276 6308",
    "sg:postcode":"08527",
    "sg:province":"NJ",
    "sg:tags":[
        "craft"
    ],
    "wof:name":"S & S Arts & Handycrafts",
    "wof:placetype":"venue"
},
  "geometry": {"coordinates":[-74.25593600000001,40.122149],"type":"Point"}
}