{
  "type": "Feature",
  "properties": {
    "addr:full":"33 Aberdeen Rd Matawan NJ 07747",
    "addr:housenumber":"33",
    "addr:postcode":"07747",
    "addr:street":"Aberdeen Rd",
    "iso:country":"US",
    "sg:address":"33 Aberdeen Rd",
    "sg:city":"Matawan",
    "sg:classifiers":[
        {
            "category":"Real Estate",
            "subcategory":"Real Estate Operator",
            "type":"Services"
        }
    ],
    "sg:phone":"+1   ",
    "sg:postcode":"07747",
    "sg:province":"NJ",
    "sg:tags":[
        "building",
        "apartment"
    ],
    "wof:name":"Tree Haven Apartments",
    "wof:placetype":"venue"
},
  "geometry": {"coordinates":[-74.23119199999999,40.424538],"type":"Point"}
}