{
  "type": "Feature",
  "properties": {
    "iso:country":"US",
    "sg:address":"5741 Cranberry Ct",
    "sg:city":"Egg Harbor City",
    "sg:classifiers":[
        {
            "category":"Farming",
            "subcategory":"Berry Farm",
            "type":"Manufacturing & Wholesale Goods"
        }
    ],
    "sg:phone":"+1 609 965 0358",
    "sg:postcode":"08215",
    "sg:province":"NJ",
    "sg:tags":[
        "crop"
    ],
    "wof:name":"Cranberrygrower Co",
    "wof:placetype":"venue"
},
  "geometry": {"coordinates":[-74.605386,39.591051],"type":"Point"}
}