{
  "type": "Feature",
  "properties": {
    "addr:full":"450 Hackensack Ave Hackensack NJ 07601",
    "addr:housenumber":"450",
    "addr:postcode":"07601",
    "addr:street":"Hackensack Ave",
    "iso:country":"US",
    "sg:address":"450 Hackensack Ave",
    "sg:city":"Hackensack",
    "sg:classifiers":[
        {
            "category":"Restaurant",
            "type":"Food & Drink"
        }
    ],
    "sg:menulink":"http://www.allmenus.com/nj/hackensack/122847-quiznos-sub/menu/",
    "sg:phone":"+1 201 342 8737",
    "sg:postcode":"07601",
    "sg:province":"NJ",
    "sg:tags":[
        "wrap",
        "american",
        "sandwich"
    ],
    "wof:name":"Quiznos Sub",
    "wof:placetype":"venue"
},
  "geometry": {"coordinates":[-74.033141,40.910373],"type":"Point"}
}