{
  "type": "Feature",
  "properties": {
    "addr:full":"2801 Ventnor Ave Longport NJ 08403",
    "addr:housenumber":"2801",
    "addr:postcode":"08403",
    "addr:street":"Ventnor Ave",
    "iso:country":"US",
    "sg:address":"2801 Ventnor Ave",
    "sg:city":"Longport",
    "sg:classifiers":[
        {
            "category":"Organizations",
            "subcategory":"Religious Organization",
            "type":"Services"
        }
    ],
    "sg:phone":"+1 609 822 8940",
    "sg:postcode":"08403",
    "sg:province":"NJ",
    "sg:tags":[
        "church"
    ],
    "wof:name":"Church Of The Epiphany",
    "wof:placetype":"venue"
},
  "geometry": {"coordinates":[-74.524467,39.314679],"type":"Point"}
}