{
  "type": "Feature",
  "properties": {
    "addr:full":"7-45 Raymond Plz W Newark NJ 07105",
    "addr:housenumber":"7-45",
    "addr:postcode":"07105",
    "addr:street":"Raymond Plz W",
    "iso:country":"US",
    "sg:address":"7-45 Raymond Plz W",
    "sg:city":"Newark",
    "sg:classifiers":[
        {
            "category":"Sports & Exercise",
            "subcategory":"Gym",
            "type":"Entertainment"
        },
        {
            "category":"Communications",
            "type":"Services"
        }
    ],
    "sg:phone":"+1 973 642 6070",
    "sg:postcode":"07105",
    "sg:province":"NJ",
    "sg:tags":[
        "medium",
        "mass"
    ],
    "sg:website":"www.mysportsclubs.com/clubsched/...",
    "wof:name":"New York Sports Club",
    "wof:placetype":"venue"
},
  "geometry": {"coordinates":[-74.16494299999999,40.734756],"type":"Point"}
}