{
  "type": "Feature",
  "properties": {
    "iso:country":"US",
    "sg:address":"103 Wisbech Pl",
    "sg:city":"Somerset",
    "sg:classifiers":[
        {
            "category":"Local Transit",
            "type":"Transportation"
        }
    ],
    "sg:phone":"+1 732 748 3386",
    "sg:postcode":"08873",
    "sg:province":"NJ",
    "sg:tags":[
        "passenger"
    ],
    "wof:name":"Cardinal On Time Limo Inc",
    "wof:placetype":"venue"
},
  "geometry": {"coordinates":[-74.51698500000001,40.516356],"type":"Point"}
}