{
  "type": "Feature",
  "properties": {
    "iso:country":"US",
    "sg:address":"376 Somerset St",
    "sg:city":"North Plainfield",
    "sg:classifiers":[
        {
            "category":"Insurance",
            "subcategory":"Insurance Agent",
            "type":"Services"
        }
    ],
    "sg:phone":"+1 908 756 5050",
    "sg:postcode":"07060",
    "sg:province":"NJ",
    "sg:tags":[
        "consultant"
    ],
    "wof:name":"Siegel Agency",
    "wof:placetype":"venue"
},
  "geometry": {"coordinates":[-74.43156999999999,40.623118],"type":"Point"}
}