{
  "type": "Feature",
  "properties": {
    "addr:full":"1240 Whitaker Ave Millville NJ 08332",
    "addr:housenumber":"1240",
    "addr:postcode":"08332",
    "addr:street":"Whitaker Ave",
    "iso:country":"US",
    "sg:address":"1240 Whitaker Ave",
    "sg:city":"Millville",
    "sg:classifiers":[
        {
            "category":"Building & Trades",
            "subcategory":"Construction",
            "type":"Services"
        }
    ],
    "sg:phone":"+1 856 825 5132",
    "sg:postcode":"08332",
    "sg:province":"NJ",
    "sg:tags":[
        "contractor"
    ],
    "wof:name":"J Morie Building Contractors",
    "wof:placetype":"venue"
},
  "geometry": {"coordinates":[-75.014667,39.412795],"type":"Point"}
}