{
  "type": "Feature",
  "properties": {
    "addr:full":"15 Tara Way Pittstown NJ 08867",
    "addr:housenumber":"15",
    "addr:postcode":"08867",
    "addr:street":"Tara Way",
    "iso:country":"US",
    "sg:address":"15 Tara Way",
    "sg:city":"Pittstown",
    "sg:classifiers":[
        {
            "category":"Retail",
            "subcategory":"Animal Services",
            "type":"Services"
        }
    ],
    "sg:phone":"+1 908 730 8627",
    "sg:postcode":"08867",
    "sg:province":"NJ",
    "wof:name":"Fig Tree Farm",
    "wof:placetype":"venue"
},
  "geometry": {"coordinates":[-74.937434,40.601538],"type":"Point"}
}