{
  "type": "Feature",
  "properties": {
    "iso:country":"US",
    "sg:address":"237 Martin Luther King Jr Dr",
    "sg:city":"Jersey City",
    "sg:classifiers":[
        {
            "category":"Food & Beverages",
            "subcategory":"Groceries & Convenience Stores",
            "type":"Retail Goods"
        }
    ],
    "sg:phone":"+1 201 324 2810",
    "sg:postcode":"07305",
    "sg:province":"NJ",
    "wof:name":"Jaritza Supermarket",
    "wof:placetype":"venue"
},
  "geometry": {"coordinates":[-74.08313099999999,40.707385],"type":"Point"}
}