{
  "type": "Feature",
  "properties": {
    "iso:country":"US",
    "sg:address":"521 W Mount Pleasant Ave",
    "sg:city":"Livingston",
    "sg:classifiers":[
        {
            "category":"Personal",
            "type":"Services"
        },
        {
            "category":"Retail",
            "subcategory":"Auto Repair",
            "type":"Services"
        }
    ],
    "sg:phone":"+1 973 992 5274",
    "sg:postcode":"07039",
    "sg:province":"NJ",
    "sg:tags":[
        "body",
        "shop",
        "towing"
    ],
    "wof:name":"Crawford Jean",
    "wof:placetype":"venue"
},
  "geometry": {"coordinates":[-74.34290300000001,40.7962],"type":"Point"}
}