{
  "type": "Feature",
  "properties": {
    "iso:country":"US",
    "sg:address":"461 W Main St",
    "sg:city":"Wyckoff",
    "sg:classifiers":[
        {
            "category":"Manufacturing",
            "subcategory":"Rubber & Plastics",
            "type":"Manufacturing & Wholesale Goods"
        }
    ],
    "sg:phone":"+1 201 848 8081",
    "sg:postcode":"07481",
    "sg:province":"NJ",
    "sg:tags":[
        "manufacture",
        "shower",
        "tub",
        "retail"
    ],
    "sg:website":"www.duschqueenusa.com",
    "wof:name":"Duschqueen Inc",
    "wof:placetype":"venue"
},
  "geometry": {"coordinates":[-74.176688,41.014],"type":"Point"}
}