{
  "type": "Feature",
  "properties": {
    "iso:country":"US",
    "sg:address":"111 Chelsea Ave",
    "sg:city":"Long Branch",
    "sg:classifiers":[
        {
            "category":"Organizations",
            "subcategory":"Religious Organization",
            "type":"Services"
        }
    ],
    "sg:phone":"+1 732 229 0952",
    "sg:postcode":"07740",
    "sg:province":"NJ",
    "sg:tags":[
        "church"
    ],
    "wof:name":"Center For Christian Formation",
    "wof:placetype":"venue"
},
  "geometry": {"coordinates":[-73.984292,40.30135],"type":"Point"}
}