{
  "type": "Feature",
  "properties": {
    "addr:full":"832 Livingston Ave North Brunswick NJ 08902",
    "addr:housenumber":"832",
    "addr:postcode":"08902",
    "addr:street":"Livingston Ave",
    "iso:country":"US",
    "sg:address":"832 Livingston Ave",
    "sg:city":"North Brunswick",
    "sg:classifiers":[
        {
            "category":"Retail",
            "subcategory":"Veterinary Services",
            "type":"Services"
        }
    ],
    "sg:phone":"+1 732 828 8175",
    "sg:postcode":"08902",
    "sg:province":"NJ",
    "wof:name":"North Brunswick Vet Clinic",
    "wof:placetype":"venue"
},
  "geometry": {"coordinates":[-74.46642199999999,40.472307],"type":"Point"}
}