{
  "type": "Feature",
  "properties": {
    "iso:country":"US",
    "sg:address":"1565 US Highway 46",
    "sg:city":"Little Falls",
    "sg:classifiers":[
        {
            "category":"Insurance",
            "subcategory":"Health Insurance",
            "type":"Services"
        }
    ],
    "sg:phone":"+1 973 785 4700",
    "sg:postcode":"07424",
    "sg:province":"NJ",
    "sg:tags":[
        "market"
    ],
    "sg:website":"www.vitaminshoppe.com",
    "wof:name":"Vitamin Shoppe the",
    "wof:placetype":"venue"
},
  "geometry": {"coordinates":[-74.206497,40.883801],"type":"Point"}
}