{
  "type": "Feature",
  "properties": {
    "iso:country":"US",
    "sg:address":"416 Irvine Turner Blvd",
    "sg:city":"Newark",
    "sg:classifiers":[
        {
            "category":"Organizations",
            "subcategory":"Membership Organization",
            "type":"Services"
        }
    ],
    "sg:phone":"+1 973 286 0030",
    "sg:postcode":"07108",
    "sg:province":"NJ",
    "wof:name":"Sast Sisters Always Stick Toge",
    "wof:placetype":"venue"
},
  "geometry": {"coordinates":[-74.195033,40.718386],"type":"Point"}
}