{
  "type": "Feature",
  "properties": {
    "addr:full":"41 Mount Bethel Rd Port Murray NJ 07865",
    "addr:housenumber":"41",
    "addr:postcode":"07865",
    "addr:street":"Mount Bethel Rd",
    "iso:country":"US",
    "sg:address":"41 Mount Bethel Rd",
    "sg:city":"Port Murray",
    "sg:classifiers":[
        {
            "category":"Manufacturing",
            "subcategory":"Lumber",
            "type":"Manufacturing & Wholesale Goods"
        }
    ],
    "sg:phone":"+1 908 852 5811",
    "sg:postcode":"07865",
    "sg:province":"NJ",
    "sg:tags":[
        "operation",
        "timber",
        "tract"
    ],
    "wof:name":"Mt Bethel Christmas Tree Farm",
    "wof:placetype":"venue"
},
  "geometry": {"coordinates":[-74.901698,40.82653],"type":"Point"}
}