{
  "type": "Feature",
  "properties": {
    "iso:country":"US",
    "sg:address":"55 Thomas Rd N",
    "sg:city":"Hawthorne",
    "sg:classifiers":[
        {
            "category":"Wholesale",
            "subcategory":"Apparel",
            "type":"Manufacturing & Wholesale Goods"
        }
    ],
    "sg:phone":"+1 973 423 0556",
    "sg:postcode":"07506",
    "sg:province":"NJ",
    "sg:tags":[
        "knit"
    ],
    "sg:website":"www.markbilt.com",
    "wof:name":"Markbilt Inc",
    "wof:placetype":"venue"
},
  "geometry": {"coordinates":[-74.162637,40.940923],"type":"Point"}
}