{
  "type": "Feature",
  "properties": {
    "addr:full":"1502 Springwood Ave Asbury Park NJ 07712",
    "addr:housenumber":"1502",
    "addr:postcode":"07712",
    "addr:street":"Springwood Ave Asbury",
    "iso:country":"US",
    "sg:address":"1502 Springwood Ave",
    "sg:city":"Asbury Park",
    "sg:classifiers":[
        {
            "category":"Restaurant",
            "type":"Food & Drink"
        }
    ],
    "sg:phone":"+1   ",
    "sg:postcode":"07712",
    "sg:province":"NJ",
    "sg:tags":[
        "eating"
    ],
    "wof:name":"Smoke Stak Inc",
    "wof:placetype":"venue"
},
  "geometry": {"coordinates":[-74.025097,40.215305],"type":"Point"}
}