{
  "type": "Feature",
  "properties": {
    "iso:country":"US",
    "sg:address":"700 Lanidex Plz",
    "sg:city":"Parsippany",
    "sg:classifiers":[
        {
            "category":"Professional",
            "subcategory":"Employment Agencies",
            "type":"Services"
        }
    ],
    "sg:phone":"+1 973 781 1030",
    "sg:postcode":"07054",
    "sg:province":"NJ",
    "sg:tags":[
        "opportunity"
    ],
    "wof:name":"Career Blazers",
    "wof:placetype":"venue"
},
  "geometry": {"coordinates":[-74.423158,40.863097],"type":"Point"}
}