{
  "type": "Feature",
  "properties": {
    "iso:country":"US",
    "sg:address":"76 Mount Vernon Pl",
    "sg:city":"Newark",
    "sg:classifiers":[
        {
            "category":"Banks & Credit Unions",
            "subcategory":"Investment Brokerage",
            "type":"Services"
        }
    ],
    "sg:phone":"+1 973 230 9003",
    "sg:postcode":"07106",
    "sg:province":"NJ",
    "sg:tags":[
        "advisory",
        "financial"
    ],
    "wof:name":"Main St Financial",
    "wof:placetype":"venue"
},
  "geometry": {"coordinates":[-74.24126699999999,40.73658],"type":"Point"}
}