{
  "type": "Feature",
  "properties": {
    "addr:full":"25 Main St Sparta NJ 07871",
    "addr:housenumber":"25",
    "addr:postcode":"07871",
    "addr:street":"Main St",
    "iso:country":"US",
    "sg:address":"25 Main St",
    "sg:city":"Sparta",
    "sg:classifiers":[
        {
            "category":"Wholesale",
            "subcategory":"Machinery & Supplies",
            "type":"Manufacturing & Wholesale Goods"
        }
    ],
    "sg:phone":"+1 973 729 7971",
    "sg:postcode":"07871",
    "sg:province":"NJ",
    "sg:tags":[
        "equipment",
        "plastic"
    ],
    "wof:name":"Scott Process Equipment Corp",
    "wof:placetype":"venue"
},
  "geometry": {"coordinates":[-74.634683,41.038094],"type":"Point"}
}