{
  "type": "Feature",
  "properties": {
    "addr:full":"15 Hepburn Rd Clifton NJ 07012",
    "addr:housenumber":"15",
    "addr:postcode":"07012",
    "addr:street":"Hepburn Rd",
    "iso:country":"US",
    "sg:address":"15 Hepburn Rd",
    "sg:city":"Clifton",
    "sg:classifiers":[
        {
            "category":"Retail",
            "subcategory":"Auto Repair",
            "type":"Services"
        }
    ],
    "sg:phone":"+1   ",
    "sg:postcode":"07012",
    "sg:province":"NJ",
    "sg:tags":[
        "body",
        "general"
    ],
    "wof:name":"Park Auto Body",
    "wof:placetype":"venue"
},
  "geometry": {"coordinates":[-74.169714,40.849235],"type":"Point"}
}