{
  "type": "Feature",
  "properties": {
    "addr:full":"14 Georgetown Ct Linwood NJ 08221",
    "addr:housenumber":"14",
    "addr:postcode":"08221",
    "addr:street":"Georgetown Ct",
    "iso:country":"US",
    "sg:address":"14 Georgetown Ct",
    "sg:city":"Linwood",
    "sg:classifiers":[
        {
            "category":"Professional",
            "subcategory":"Management & Consulting",
            "type":"Services"
        }
    ],
    "sg:phone":"+1 609 927 2274",
    "sg:postcode":"08221",
    "sg:province":"NJ",
    "sg:tags":[
        "consultant"
    ],
    "wof:name":"Bill Blake Consultants",
    "wof:placetype":"venue"
},
  "geometry": {"coordinates":[-74.578811,39.338569],"type":"Point"}
}