{
  "type": "Feature",
  "properties": {
    "addr:full":"270 Belleville Ave Belleville NJ 07109",
    "addr:housenumber":"270",
    "addr:postcode":"07109",
    "addr:street":"Belleville Ave",
    "iso:country":"US",
    "sg:address":"270 Belleville Ave",
    "sg:city":"Belleville",
    "sg:classifiers":[
        {
            "category":"Autos & Motor Vehicles",
            "subcategory":"Auto Supplies",
            "type":"Retail Goods"
        }
    ],
    "sg:phone":"+1 973 751 0333",
    "sg:postcode":"07109",
    "sg:province":"NJ",
    "sg:tags":[
        "glass"
    ],
    "wof:name":"Route 10 Auto Glass",
    "wof:placetype":"venue"
},
  "geometry": {"coordinates":[-74.16074399999999,40.788185],"type":"Point"}
}