{
  "type": "Feature",
  "properties": {
    "iso:country":"US",
    "sg:address":"721 New England Rd",
    "sg:city":"Cape May",
    "sg:classifiers":[
        {
            "category":"Building & Trades",
            "subcategory":"Construction",
            "type":"Services"
        }
    ],
    "sg:phone":"+1 609 884 6702",
    "sg:postcode":"08204",
    "sg:province":"NJ",
    "sg:tags":[
        "carpentry",
        "contractor"
    ],
    "wof:name":"Cold Springs Carpentry LLC",
    "wof:placetype":"venue"
},
  "geometry": {"coordinates":[-74.93001700000001,38.963615],"type":"Point"}
}