{
  "type": "Feature",
  "properties": {
    "addr:full":"71 W Main St Freehold NJ 07728",
    "addr:housenumber":"71",
    "addr:postcode":"07728",
    "addr:street":"W Main St",
    "iso:country":"US",
    "sg:address":"71 W Main St",
    "sg:city":"Freehold",
    "sg:classifiers":[
        {
            "category":"Professional",
            "subcategory":"Lawyer & Legal Services",
            "type":"Services"
        }
    ],
    "sg:phone":"+1 732 431 5131",
    "sg:postcode":"07728",
    "sg:province":"NJ",
    "wof:name":"Local No 1115 Prepaid Legal",
    "wof:placetype":"venue"
},
  "geometry": {"coordinates":[-74.277344,40.257959],"type":"Point"}
}