{
  "type": "Feature",
  "properties": {
    "iso:country":"US",
    "sg:address":"48 Hope Rd",
    "sg:city":"Blairstown",
    "sg:classifiers":[
        {
            "category":"Professional",
            "type":"Services"
        }
    ],
    "sg:phone":"+1 908 362 8346",
    "sg:postcode":"07825",
    "sg:province":"NJ",
    "sg:tags":[
        "establishment"
    ],
    "wof:name":"Merco Inc",
    "wof:placetype":"venue"
},
  "geometry": {"coordinates":[-74.95507499999999,40.969247],"type":"Point"}
}