{
  "type": "Feature",
  "properties": {
    "iso:country":"US",
    "sg:address":"1099 Delsea Dr",
    "sg:city":"Westville",
    "sg:classifiers":[
        {
            "category":"Shopping",
            "type":"Retail Goods"
        }
    ],
    "sg:phone":"+1 856 848 2828",
    "sg:postcode":"08093",
    "sg:province":"NJ",
    "sg:tags":[
        "telephone",
        "cellular"
    ],
    "wof:name":"Deptford Communication",
    "wof:placetype":"venue"
},
  "geometry": {"coordinates":[-75.12511499999999,39.850942],"type":"Point"}
}