{
  "type": "Feature",
  "properties": {
    "iso:country":"US",
    "sg:address":"539 Hartung Dr",
    "sg:city":"Wyckoff",
    "sg:classifiers":[
        {
            "category":"Professional",
            "type":"Services"
        }
    ],
    "sg:phone":"+1   ",
    "sg:postcode":"07481",
    "sg:province":"NJ",
    "wof:name":"Elliot Richman",
    "wof:placetype":"venue"
},
  "geometry": {"coordinates":[-74.18321299999999,41.005768],"type":"Point"}
}