{
  "type": "Feature",
  "properties": {
    "addr:full":"81 Van Winkle Ave Hawthorne NJ 07506",
    "addr:housenumber":"81",
    "addr:postcode":"07506",
    "addr:street":"Van Winkle Ave",
    "iso:country":"US",
    "sg:address":"81 Van Winkle Ave",
    "sg:city":"Hawthorne",
    "sg:classifiers":[
        {
            "category":"Organizations",
            "subcategory":"Professional Association",
            "type":"Services"
        }
    ],
    "sg:phone":"+1 973 423 1069",
    "sg:postcode":"07506",
    "sg:province":"NJ",
    "sg:tags":[
        "business"
    ],
    "wof:name":"Hawthorne Teachers",
    "wof:placetype":"venue"
},
  "geometry": {"coordinates":[-74.157177,40.962911],"type":"Point"}
}