{
  "type": "Feature",
  "properties": {
    "iso:country":"US",
    "sg:address":"315 Alden St",
    "sg:city":"Orange",
    "sg:classifiers":[
        {
            "category":"Organizations",
            "subcategory":"Religious Organization",
            "type":"Services"
        }
    ],
    "sg:phone":"+1 973 676 1200",
    "sg:postcode":"07050",
    "sg:province":"NJ",
    "sg:tags":[
        "church"
    ],
    "wof:name":"Anointed Pentecostal Church",
    "wof:placetype":"venue"
},
  "geometry": {"coordinates":[-74.22461300000001,40.780448],"type":"Point"}
}