{
  "type": "Feature",
  "properties": {
    "addr:full":"2 Waterloo Rd Stanhope NJ 07874",
    "addr:housenumber":"2",
    "addr:postcode":"07874",
    "addr:street":"Waterloo Rd",
    "iso:country":"US",
    "sg:address":"2 Waterloo Rd",
    "sg:city":"Stanhope",
    "sg:classifiers":[
        {
            "category":"Banks & Credit Unions",
            "subcategory":"Bank",
            "type":"Services"
        }
    ],
    "sg:phone":"+1 973 347 5353",
    "sg:postcode":"07874",
    "sg:province":"NJ",
    "wof:name":"Sovereign Bank",
    "wof:placetype":"venue"
},
  "geometry": {"coordinates":[-74.79940999999999,40.889697],"type":"Point"}
}