{
  "type": "Feature",
  "properties": {
    "addr:full":"6 Telegraph Hill Rd Holmdel NJ 07733",
    "addr:housenumber":"6",
    "addr:postcode":"07733",
    "addr:street":"Telegraph Hill Rd",
    "iso:country":"US",
    "sg:address":"6 Telegraph Hill Rd",
    "sg:city":"Holmdel",
    "sg:classifiers":[
        {
            "category":"Shopping",
            "subcategory":"Optical Goods",
            "type":"Retail Goods"
        }
    ],
    "sg:phone":"+1 732 264 4986",
    "sg:postcode":"07733",
    "sg:province":"NJ",
    "sg:tags":[
        "sun",
        "goggles",
        "sunglasses"
    ],
    "wof:name":"Sunglass Hut",
    "wof:placetype":"venue"
},
  "geometry": {"coordinates":[-74.18187399999999,40.409789],"type":"Point"}
}