{
  "type": "Feature",
  "properties": {
    "iso:country":"US",
    "sg:address":"65 Mountain Trl",
    "sg:city":"Branchville",
    "sg:classifiers":[
        {
            "category":"Building & Trades",
            "subcategory":"Construction",
            "type":"Services"
        }
    ],
    "sg:phone":"+1 973 948 6160",
    "sg:postcode":"07826",
    "sg:province":"NJ",
    "sg:tags":[
        "home",
        "builder"
    ],
    "wof:name":"Mountainside Builders",
    "wof:placetype":"venue"
},
  "geometry": {"coordinates":[-74.797721,41.173378],"type":"Point"}
}