{
  "type": "Feature",
  "properties": {
    "iso:country":"US",
    "sg:address":"1903 Birchwood Park Dr N",
    "sg:city":"Cherry Hill",
    "sg:classifiers":[
        {
            "category":"Building & Trades",
            "subcategory":"Equipment Rental",
            "type":"Services"
        }
    ],
    "sg:phone":"+1 856 751 6480",
    "sg:postcode":"08003",
    "sg:province":"NJ",
    "wof:name":"Shore Summer Rentals LLC",
    "wof:placetype":"venue"
},
  "geometry": {"coordinates":[-74.96515100000001,39.912726],"type":"Point"}
}