{
  "type": "Feature",
  "properties": {
    "iso:country":"US",
    "sg:address":"107 E Mount Pleasant Ave",
    "sg:city":"Livingston",
    "sg:classifiers":[
        {
            "category":"Health Services",
            "subcategory":"Medical Lab",
            "type":"Services"
        }
    ],
    "sg:phone":"+1 973 535 3993",
    "sg:postcode":"07039",
    "sg:province":"NJ",
    "sg:tags":[
        "laboratory"
    ],
    "wof:name":"Living-Stone Dental Lab",
    "wof:placetype":"venue"
},
  "geometry": {"coordinates":[-74.31148899999999,40.796714],"type":"Point"}
}