{
  "type": "Feature",
  "properties": {
    "addr:full":"471 Cortlandt St Belleville NJ 07109",
    "addr:housenumber":"471",
    "addr:postcode":"07109",
    "addr:street":"Cortlandt St",
    "iso:country":"US",
    "sg:address":"471 Cortlandt St",
    "sg:city":"Belleville",
    "sg:classifiers":[
        {
            "category":"Manufacturing",
            "subcategory":"Retail Goods",
            "type":"Manufacturing & Wholesale Goods"
        }
    ],
    "sg:phone":"+1 973 450 8200",
    "sg:postcode":"07109",
    "sg:province":"NJ",
    "sg:tags":[
        "manufacturer"
    ],
    "wof:name":"Ericyan Industry II Inc",
    "wof:placetype":"venue"
},
  "geometry": {"coordinates":[-74.147164,40.794987],"type":"Point"}
}