{
  "type": "Feature",
  "properties": {
    "addr:full":"200 Whitehead Rd Trenton NJ 08619",
    "addr:housenumber":"200",
    "addr:postcode":"08619",
    "addr:street":"Whitehead Rd",
    "iso:country":"US",
    "sg:address":"200 Whitehead Rd",
    "sg:city":"Trenton",
    "sg:classifiers":[
        {
            "category":"Home & Garden",
            "subcategory":"Building Materials",
            "type":"Retail Goods"
        },
        {
            "category":"Professional",
            "subcategory":"Art Services",
            "type":"Services"
        },
        {
            "category":"Building & Trades",
            "subcategory":"Construction",
            "type":"Services"
        }
    ],
    "sg:phone":"+1 609 838 2938",
    "sg:postcode":"08619",
    "sg:province":"NJ",
    "sg:tags":[
        "designer",
        "installation",
        "canopies-repair",
        "altering",
        "windows-repair",
        "contractor",
        "interior",
        "siding",
        "awning",
        "improvement",
        "remodeling",
        "decorator",
        "replacement"
    ],
    "sg:website":"http://www.impact-remodeling.com",
    "wof:name":"Impact Remodeling",
    "wof:placetype":"venue"
},
  "geometry": {"coordinates":[-74.72843399999999,40.238175],"type":"Point"}
}