{
  "type": "Feature",
  "properties": {
    "addr:full":"37 Knox Ter Wayne NJ 07470",
    "addr:housenumber":"37",
    "addr:postcode":"07470",
    "addr:street":"Knox Ter",
    "iso:country":"US",
    "sg:address":"37 Knox Ter",
    "sg:city":"Wayne",
    "sg:classifiers":[
        {
            "category":"Professional",
            "subcategory":"Business Services",
            "type":"Services"
        }
    ],
    "sg:phone":"+1   ",
    "sg:postcode":"07470",
    "sg:province":"NJ",
    "wof:name":"North Jersey Business Exchange",
    "wof:placetype":"venue"
},
  "geometry": {"coordinates":[-74.224706,40.951318],"type":"Point"}
}