{
  "type": "Feature",
  "properties": {
    "addr:full":"309 Lincoln Blvd Middlesex NJ 08846",
    "addr:housenumber":"309",
    "addr:postcode":"08846",
    "addr:street":"Lincoln Blvd",
    "iso:country":"US",
    "sg:address":"309 Lincoln Blvd",
    "sg:city":"Middlesex",
    "sg:classifiers":[
        {
            "category":"Autos & Motor Vehicles",
            "subcategory":"Fuel & Gas Station",
            "type":"Retail Goods"
        }
    ],
    "sg:phone":"+1   ",
    "sg:postcode":"08846",
    "sg:province":"NJ",
    "sg:tags":[
        "station"
    ],
    "wof:name":"Gulf",
    "wof:placetype":"venue"
},
  "geometry": {"coordinates":[-74.501571,40.566977],"type":"Point"}
}