{
  "type": "Feature",
  "properties": {
    "addr:full":"55 Parsonage Rd Edison NJ 08837",
    "addr:housenumber":"55",
    "addr:postcode":"08837",
    "addr:street":"Parsonage Rd",
    "iso:country":"US",
    "sg:address":"55 Parsonage Rd",
    "sg:city":"Edison",
    "sg:classifiers":[
        {
            "category":"Banks & Credit Unions",
            "subcategory":"Investment Brokerage",
            "type":"Services"
        },
        {
            "category":"Shopping",
            "subcategory":"Music",
            "type":"Retail Goods"
        },
        {
            "category":"Shopping",
            "subcategory":"Computers & Home Electronics",
            "type":"Retail Goods"
        },
        {
            "category":"Shopping",
            "subcategory":"Gifts & Souvenirs",
            "type":"Retail Goods"
        },
        {
            "category":"Utilities",
            "subcategory":"Mobile Phone",
            "type":"Services"
        },
        {
            "category":"Communications",
            "subcategory":"Film & Video Production",
            "type":"Services"
        },
        {
            "category":"Shopping",
            "subcategory":"Books",
            "type":"Retail Goods"
        },
        {
            "category":"Wholesale",
            "subcategory":"Books, Periodicals, & Newspapers",
            "type":"Manufacturing & Wholesale Goods"
        }
    ],
    "sg:phone":"+1 732 548 4179",
    "sg:postcode":"08837",
    "sg:province":"NJ",
    "sg:tags":[
        "shop",
        "educational",
        "dvd",
        "material",
        "sale",
        "hotspot",
        "dvds-rental",
        "record",
        "magazine",
        "tapes-wholesale",
        "tape",
        "cd's",
        "wi-fi",
        "store",
        "manufacturer"
    ],
    "sg:website":"http://store-locator.barnesandnoble.com/store/2162",
    "wof:name":"Barnes & Noble Booksellers",
    "wof:placetype":"venue"
},
  "geometry": {"coordinates":[-74.33314900000001,40.547717],"type":"Point"}
}