{
  "type": "Feature",
  "properties": {
    "addr:full":"662 W Cuthbert Blvd Collingswood NJ 08108",
    "addr:housenumber":"662",
    "addr:postcode":"08108",
    "addr:street":"W Cuthbert Blvd",
    "iso:country":"US",
    "sg:address":"662 W Cuthbert Blvd",
    "sg:city":"Collingswood",
    "sg:classifiers":[
        {
            "category":"Shopping",
            "subcategory":"Discount & Variety Stores",
            "type":"Retail Goods"
        }
    ],
    "sg:phone":"+1 856 858 3600",
    "sg:postcode":"08108",
    "sg:province":"NJ",
    "wof:name":"Dollar Tree",
    "wof:placetype":"venue"
},
  "geometry": {"coordinates":[-75.064077,39.901767],"type":"Point"}
}