{
  "type": "Feature",
  "properties": {
    "iso:country":"US",
    "sg:address":"226 W Clinton Ave",
    "sg:city":"Tenafly",
    "sg:classifiers":[
        {
            "category":"Professional",
            "subcategory":"Computer Services",
            "type":"Services"
        }
    ],
    "sg:phone":"+1 201 541 0198",
    "sg:postcode":"07670",
    "sg:province":"NJ",
    "sg:tags":[
        "related"
    ],
    "wof:name":"Ideal Solutions of America",
    "wof:placetype":"venue"
},
  "geometry": {"coordinates":[-73.976331,40.924513],"type":"Point"}
}