{
  "type": "Feature",
  "properties": {
    "addr:full":"642 Ogden Ave Teaneck NJ 07666",
    "addr:housenumber":"642",
    "addr:postcode":"07666",
    "addr:street":"Ogden Ave",
    "iso:country":"US",
    "sg:address":"642 Ogden Ave",
    "sg:city":"Teaneck",
    "sg:classifiers":[
        {
            "category":"Place Of Worship",
            "subcategory":"Synagogue",
            "type":"Public Place"
        }
    ],
    "sg:phone":"+1 201 530 0222",
    "sg:postcode":"07666",
    "sg:province":"NJ",
    "wof:name":"Congregation B'nai Yeshurun",
    "wof:placetype":"venue"
},
  "geometry": {"coordinates":[-74.020798,40.907398],"type":"Point"}
}