{
  "type": "Feature",
  "properties": {
    "addr:full":"222 Ridge Rd North Arlington NJ 07031",
    "addr:housenumber":"222",
    "addr:postcode":"07031",
    "addr:street":"Ridge Rd North",
    "iso:country":"US",
    "sg:address":"222 Ridge Rd",
    "sg:city":"North Arlington",
    "sg:classifiers":[
        {
            "category":"Education",
            "subcategory":"School",
            "type":"Public Place"
        }
    ],
    "sg:phone":"+1 201 955 5216",
    "sg:postcode":"07031",
    "sg:province":"NJ",
    "sg:tags":[
        "high",
        "middle",
        "elementary"
    ],
    "wof:name":"North Arlington Borough of",
    "wof:placetype":"venue"
},
  "geometry": {"coordinates":[-74.134201,40.787102],"type":"Point"}
}