{
  "type": "Feature",
  "properties": {
    "addr:full":"366 Van Nostrand Ave Englewood NJ 07631",
    "addr:housenumber":"366",
    "addr:postcode":"07631",
    "addr:street":"Van Nostrand Ave",
    "iso:country":"US",
    "sg:address":"366 Van Nostrand Ave",
    "sg:city":"Englewood",
    "sg:classifiers":[
        {
            "category":"Health Services",
            "subcategory":"Doctor",
            "type":"Services"
        }
    ],
    "sg:phone":"+1 201 569 4144",
    "sg:postcode":"07631",
    "sg:province":"NJ",
    "sg:tags":[
        "medical"
    ],
    "wof:name":"Louis Solomon MD",
    "wof:placetype":"venue"
},
  "geometry": {"coordinates":[-73.969809,40.874131],"type":"Point"}
}