{
  "type": "Feature",
  "properties": {
    "addr:full":"33 Witherspoon St Princeton NJ 08542",
    "addr:housenumber":"33",
    "addr:postcode":"08542",
    "addr:street":"Witherspoon St",
    "iso:country":"US",
    "sg:address":"33 Witherspoon St",
    "sg:city":"Princeton",
    "sg:classifiers":[
        {
            "category":"Health Services",
            "subcategory":"Doctor",
            "type":"Services"
        }
    ],
    "sg:phone":"+1 609 924 0190",
    "sg:postcode":"08542",
    "sg:province":"NJ",
    "sg:tags":[
        "physician",
        "surgeon"
    ],
    "wof:name":"Olivia Lewis-Chang PHD",
    "wof:placetype":"venue"
},
  "geometry": {"coordinates":[-74.659814,40.349777],"type":"Point"}
}