{
  "type": "Feature",
  "properties": {
    "iso:country":"US",
    "sg:address":"327 Bridge Plz N",
    "sg:city":"Fort Lee",
    "sg:classifiers":[
        {
            "category":"Personal",
            "subcategory":"Beauty Salon",
            "type":"Services"
        }
    ],
    "sg:phone":"+1 201 944 6006",
    "sg:postcode":"07024",
    "sg:province":"NJ",
    "sg:tags":[
        "hairdresser"
    ],
    "wof:name":"Giambieri Hair Designers",
    "wof:placetype":"venue"
},
  "geometry": {"coordinates":[-73.971558,40.857104],"type":"Point"}
}