{
  "type": "Feature",
  "properties": {
    "addr:full":"79 Grand Blvd Emerson NJ 07630",
    "addr:housenumber":"79",
    "addr:postcode":"07630",
    "addr:street":"Grand Blvd",
    "iso:country":"US",
    "sg:address":"79 Grand Blvd",
    "sg:city":"Emerson",
    "sg:classifiers":[
        {
            "category":"Building & Trades",
            "subcategory":"Construction",
            "type":"Services"
        }
    ],
    "sg:phone":"+1 201 265 3170",
    "sg:postcode":"07630",
    "sg:province":"NJ",
    "sg:tags":[
        "painter"
    ],
    "wof:name":"Viglione Painting",
    "wof:placetype":"venue"
},
  "geometry": {"coordinates":[-74.030714,40.974443],"type":"Point"}
}