{
  "type": "Feature",
  "properties": {
    "addr:full":"9 Westminster Dr Annandale NJ 08801",
    "addr:housenumber":"9",
    "addr:postcode":"08801",
    "addr:street":"Westminster Dr",
    "iso:country":"US",
    "sg:address":"9 Westminster Dr",
    "sg:city":"Annandale",
    "sg:classifiers":[
        {
            "category":"Professional",
            "subcategory":"Business Services",
            "type":"Services"
        }
    ],
    "sg:phone":"+1   ",
    "sg:postcode":"08801",
    "sg:province":"NJ",
    "wof:name":"Rv Enterprises",
    "wof:placetype":"venue"
},
  "geometry": {"coordinates":[-74.89622,40.61219],"type":"Point"}
}