{
  "type": "Feature",
  "properties": {
    "iso:country":"US",
    "sg:address":"1108 Ocean Ave",
    "sg:city":"Asbury Park",
    "sg:classifiers":[
        {
            "category":"Travel",
            "subcategory":"Hotels & Motels",
            "type":"Entertainment"
        }
    ],
    "sg:phone":"+1 732 531 1007",
    "sg:postcode":"07712",
    "sg:province":"NJ",
    "wof:name":"Tower Motel",
    "wof:placetype":"venue"
},
  "geometry": {"coordinates":[-73.999514,40.22235],"type":"Point"}
}