{
  "type": "Feature",
  "properties": {
    "iso:country":"US",
    "sg:address":"185 Oberlin Ave N",
    "sg:city":"Lakewood",
    "sg:classifiers":[
        {
            "category":"Wholesale",
            "subcategory":"Chemicals & Plastics",
            "type":"Manufacturing & Wholesale Goods"
        }
    ],
    "sg:phone":"+1 732 363 5158",
    "sg:postcode":"08701",
    "sg:province":"NJ",
    "sg:tags":[
        "spec"
    ],
    "wof:name":"Total Lubes",
    "wof:placetype":"venue"
},
  "geometry": {"coordinates":[-74.175285,40.078216],"type":"Point"}
}