{
  "type": "Feature",
  "properties": {
    "iso:country":"US",
    "sg:address":"1161 Paterson Plank Rd",
    "sg:city":"Secaucus",
    "sg:classifiers":[
        {
            "category":"Professional",
            "subcategory":"Art Services",
            "type":"Services"
        }
    ],
    "sg:phone":"+1 201 438 5535",
    "sg:postcode":"07094",
    "sg:province":"NJ",
    "sg:tags":[
        "photographer",
        "photography",
        "commercial"
    ],
    "wof:name":"Studio 4",
    "wof:placetype":"venue"
},
  "geometry": {"coordinates":[-74.054086,40.787514],"type":"Point"}
}