{
  "type": "Feature",
  "properties": {
    "addr:full":"186 N Broadway Pennsville NJ 08070",
    "addr:housenumber":"186",
    "addr:postcode":"08070",
    "addr:street":"N Broadway",
    "iso:country":"US",
    "sg:address":"186 N Broadway",
    "sg:city":"Pennsville",
    "sg:classifiers":[
        {
            "category":"Travel",
            "subcategory":"Travel Agent",
            "type":"Entertainment"
        }
    ],
    "sg:phone":"+1 856 678 2067",
    "sg:postcode":"08070",
    "sg:province":"NJ",
    "sg:tags":[
        "agency",
        "general"
    ],
    "sg:website":"www.colonytravel.com",
    "wof:name":"Colony Travel",
    "wof:placetype":"venue"
},
  "geometry": {"coordinates":[-75.509376,39.66441],"type":"Point"}
}