{
  "type": "Feature",
  "properties": {
    "addr:full":"1275 Bloomfield Ave Fairfield NJ 07004",
    "addr:housenumber":"1275",
    "addr:postcode":"07004",
    "addr:street":"Bloomfield Ave",
    "iso:country":"US",
    "sg:address":"1275 Bloomfield Ave",
    "sg:city":"Fairfield",
    "sg:classifiers":[
        {
            "category":"Sports & Exercise",
            "subcategory":"Gym",
            "type":"Entertainment"
        }
    ],
    "sg:phone":"+1 973 227 8823",
    "sg:postcode":"07004",
    "sg:province":"NJ",
    "sg:tags":[
        "club",
        "studio",
        "health",
        "gymnasium"
    ],
    "wof:name":"Olympus Gym Fitness Aerobics & Tanning",
    "wof:placetype":"venue"
},
  "geometry": {"coordinates":[-74.318398,40.858299],"type":"Point"}
}