{
  "type": "Feature",
  "properties": {
    "addr:full":"981 Magie Ave Union NJ 07083",
    "addr:housenumber":"981",
    "addr:postcode":"07083",
    "addr:street":"Magie Ave",
    "iso:country":"US",
    "sg:address":"981 Magie Ave",
    "sg:city":"Union",
    "sg:classifiers":[
        {
            "category":"Real Estate",
            "subcategory":"Real Estate Agent",
            "type":"Services"
        }
    ],
    "sg:phone":"+1 908 289 5625",
    "sg:postcode":"07083",
    "sg:province":"NJ",
    "wof:name":"Vansh Realty LLC",
    "wof:placetype":"venue"
},
  "geometry": {"coordinates":[-74.244039,40.673124],"type":"Point"}
}