{
  "type": "Feature",
  "properties": {
    "addr:full":"2978 US Hwy 1 Lawrenceville NJ 08648",
    "addr:housenumber":"2978",
    "addr:postcode":"08648",
    "addr:street":"Us Hwy 1",
    "iso:country":"US",
    "sg:address":"2978 US Hwy 1",
    "sg:city":"Lawrenceville",
    "sg:classifiers":[
        {
            "category":"Shopping",
            "subcategory":"Florist",
            "type":"Retail Goods"
        }
    ],
    "sg:phone":"+1 609 219 0219",
    "sg:postcode":"08648",
    "sg:province":"NJ",
    "wof:name":"Adorn A European Flower Market",
    "wof:placetype":"venue"
},
  "geometry": {"coordinates":[-74.70389299999999,40.276922],"type":"Point"}
}