{
  "type": "Feature",
  "properties": {
    "addr:full":"95 Main St Paterson NJ 07505",
    "addr:housenumber":"95",
    "addr:postcode":"07505",
    "addr:street":"Main St",
    "iso:country":"US",
    "sg:address":"95 Main St",
    "sg:city":"Paterson",
    "sg:classifiers":[
        {
            "category":"Shopping",
            "subcategory":"Discount & Variety Stores",
            "type":"Retail Goods"
        }
    ],
    "sg:phone":"+1   ",
    "sg:postcode":"07505",
    "sg:province":"NJ",
    "wof:name":"Mannys Ladies Boutique",
    "wof:placetype":"venue"
},
  "geometry": {"coordinates":[-74.17285800000001,40.91927],"type":"Point"}
}