{
  "type": "Feature",
  "properties": {
    "iso:country":"US",
    "sg:address":"2108 Route 70",
    "sg:city":"Manchester",
    "sg:classifiers":[
        {
            "category":"Shopping",
            "subcategory":"Party Supplies",
            "type":"Retail Goods"
        },
        {
            "category":"Travel",
            "subcategory":"Travel Agent",
            "type":"Entertainment"
        },
        {
            "category":"Marine",
            "type":"Transportation"
        }
    ],
    "sg:phone":"+1 732 657 7700",
    "sg:postcode":"08759",
    "sg:province":"NJ",
    "sg:tags":[
        "wedding",
        "agency",
        "services-commercial",
        "cruise"
    ],
    "wof:name":"Travel Plaza",
    "wof:placetype":"venue"
},
  "geometry": {"coordinates":[-74.269071,40.023618],"type":"Point"}
}