{
  "type": "Feature",
  "properties": {
    "iso:country":"US",
    "sg:address":"22 Ridge Rd",
    "sg:city":"Morganville",
    "sg:classifiers":[
        {
            "category":"Building & Trades",
            "subcategory":"Construction",
            "type":"Services"
        }
    ],
    "sg:phone":"+1 732 946 0759",
    "sg:postcode":"07751",
    "sg:province":"NJ",
    "sg:tags":[
        "carpentry",
        "contractor"
    ],
    "wof:name":"Barboline Contracting",
    "wof:placetype":"venue"
},
  "geometry": {"coordinates":[-74.247364,40.352],"type":"Point"}
}