{
  "type": "Feature",
  "properties": {
    "addr:full":"148 Marsh St Newark NJ 07114",
    "addr:housenumber":"148",
    "addr:postcode":"07114",
    "addr:street":"Marsh St",
    "iso:country":"US",
    "sg:address":"148 Marsh St",
    "sg:city":"Newark",
    "sg:classifiers":[
        {
            "category":"Building & Trades",
            "subcategory":"Construction",
            "type":"Services"
        }
    ],
    "sg:phone":"+1 973 344 1670",
    "sg:postcode":"07114",
    "sg:province":"NJ",
    "sg:tags":[
        "heavy",
        "marine",
        "dredging"
    ],
    "wof:name":"M P Howlwtt",
    "wof:placetype":"venue"
},
  "geometry": {"coordinates":[-74.152041,40.695478],"type":"Point"}
}