{
  "type": "Feature",
  "properties": {
    "iso:country":"US",
    "sg:address":"36 Blueberry Dr",
    "sg:city":"Woodcliff Lake",
    "sg:classifiers":[
        {
            "category":"Restaurant",
            "type":"Food & Drink"
        }
    ],
    "sg:phone":"+1   ",
    "sg:postcode":"07677",
    "sg:province":"NJ",
    "sg:tags":[
        "eating"
    ],
    "wof:name":"Joseph D Gatti Jr",
    "wof:placetype":"venue"
},
  "geometry": {"coordinates":[-74.07487399999999,41.014716],"type":"Point"}
}