{
  "type": "Feature",
  "properties": {
    "addr:full":"360 Springfield Ave Summit NJ 07901",
    "addr:housenumber":"360",
    "addr:postcode":"07901",
    "addr:street":"Springfield Ave",
    "iso:country":"US",
    "sg:address":"360 Springfield Ave",
    "sg:city":"Summit",
    "sg:classifiers":[
        {
            "category":"Social Services",
            "type":"Services"
        }
    ],
    "sg:phone":"+1 908 273 4091",
    "sg:postcode":"07901",
    "sg:province":"NJ",
    "wof:name":"Sybil Keane LPC",
    "wof:placetype":"venue"
},
  "geometry": {"coordinates":[-74.356905,40.718043],"type":"Point"}
}