{
  "type": "Feature",
  "properties": {
    "addr:full":"501 State Rte 71 Spring Lake NJ 07762",
    "addr:housenumber":"501",
    "addr:postcode":"07762",
    "addr:street":"State Rte 71",
    "iso:country":"US",
    "sg:address":"501 State Rte 71",
    "sg:city":"Spring Lake",
    "sg:classifiers":[
        {
            "category":"Shopping",
            "type":"Retail Goods"
        }
    ],
    "sg:phone":"+1 732 449 0222",
    "sg:postcode":"07762",
    "sg:province":"NJ",
    "sg:tags":[
        "plaque"
    ],
    "wof:name":"B & B Trophy Plaque Awards Co",
    "wof:placetype":"venue"
},
  "geometry": {"coordinates":[-74.04101199999999,40.147248],"type":"Point"}
}