{
  "type": "Feature",
  "properties": {
    "iso:country":"US",
    "sg:address":"4609 Park Ave",
    "sg:city":"Union City",
    "sg:classifiers":[
        {
            "category":"Professional",
            "subcategory":"Accounting & Tax Preparation",
            "type":"Services"
        }
    ],
    "sg:phone":"+1 201 601 0901",
    "sg:postcode":"07087",
    "sg:province":"NJ",
    "sg:tags":[
        "return",
        "filing"
    ],
    "wof:name":"Malqui Tax",
    "wof:placetype":"venue"
},
  "geometry": {"coordinates":[-74.016666,40.778442],"type":"Point"}
}