{
  "type": "Feature",
  "properties": {
    "iso:country":"US",
    "sg:address":"110 Warren St",
    "sg:city":"Nutley",
    "sg:classifiers":[
        {
            "category":"Shopping",
            "subcategory":"Books",
            "type":"Retail Goods"
        }
    ],
    "sg:phone":"+1   ",
    "sg:postcode":"07110",
    "sg:province":"NJ",
    "sg:tags":[
        "textbook"
    ],
    "wof:name":"College Bookstore",
    "wof:placetype":"venue"
},
  "geometry": {"coordinates":[-74.156683,40.821351],"type":"Point"}
}