{
  "type": "Feature",
  "properties": {
    "addr:full":"1296 15th St Fort Lee NJ 07024",
    "addr:housenumber":"1296",
    "addr:postcode":"07024",
    "addr:street":"15Th St",
    "iso:country":"US",
    "sg:address":"1296 15th St",
    "sg:city":"Fort Lee",
    "sg:classifiers":[
        {
            "category":"Real Estate",
            "subcategory":"Real Estate Operator",
            "type":"Services"
        }
    ],
    "sg:phone":"+1 201 886 8360",
    "sg:postcode":"07024",
    "sg:province":"NJ",
    "sg:tags":[
        "condominium"
    ],
    "wof:name":"Terrace West Condo Assoc",
    "wof:placetype":"venue"
},
  "geometry": {"coordinates":[-73.982332,40.843503],"type":"Point"}
}