{
  "type": "Feature",
  "properties": {
    "iso:country":"US",
    "sg:address":"55 Main St",
    "sg:city":"Hackensack",
    "sg:classifiers":[
        {
            "category":"Professional",
            "subcategory":"Lawyer & Legal Services",
            "type":"Services"
        }
    ],
    "sg:phone":"+1 201 489 5500",
    "sg:postcode":"07601",
    "sg:province":"NJ",
    "wof:name":"Kopelman Michael S Attorney",
    "wof:placetype":"venue"
},
  "geometry": {"coordinates":[-74.044296,40.879902],"type":"Point"}
}