{
  "type": "Feature",
  "properties": {
    "addr:full":"86 Lackawanna Ave Little Falls NJ 07424",
    "addr:housenumber":"86",
    "addr:postcode":"07424",
    "addr:street":"Lackawanna Ave",
    "iso:country":"US",
    "sg:address":"86 Lackawanna Ave",
    "sg:city":"Little Falls",
    "sg:phone":"+1 973 237 9588",
    "sg:postcode":"07424",
    "sg:province":"NJ",
    "sg:tags":[
        "equipment",
        "commercial"
    ],
    "wof:name":"Miracle Manufacturing",
    "wof:placetype":"venue"
},
  "geometry": {"coordinates":[-74.213843,40.889525],"type":"Point"}
}