{
  "type": "Feature",
  "properties": {
    "addr:full":"324 Wall St Princeton NJ 08540",
    "addr:housenumber":"324",
    "addr:postcode":"08540",
    "addr:street":"Wall St",
    "iso:country":"US",
    "sg:address":"324 Wall St",
    "sg:city":"Princeton",
    "sg:classifiers":[
        {
            "category":"Professional",
            "subcategory":"Accounting & Tax Preparation",
            "type":"Services"
        }
    ],
    "sg:phone":"+1 609 921 6220",
    "sg:postcode":"08540",
    "sg:province":"NJ",
    "wof:name":"Robert H Geer CPA",
    "wof:placetype":"venue"
},
  "geometry": {"coordinates":[-74.65069800000001,40.396647],"type":"Point"}
}