{
  "type": "Feature",
  "properties": {
    "addr:full":"99 Market St Paterson NJ 07505",
    "addr:housenumber":"99",
    "addr:postcode":"07505",
    "addr:street":"Market St",
    "iso:country":"US",
    "sg:address":"99 Market St",
    "sg:city":"Paterson",
    "sg:classifiers":[
        {
            "category":"Shopping",
            "subcategory":"Music",
            "type":"Retail Goods"
        }
    ],
    "sg:phone":"+1 973 345 9503",
    "sg:postcode":"07505",
    "sg:province":"NJ",
    "sg:tags":[
        "dvd's"
    ],
    "wof:name":"Alta Fidelidad Records",
    "wof:placetype":"venue"
},
  "geometry": {"coordinates":[-74.174004,40.9161],"type":"Point"}
}