{
  "type": "Feature",
  "properties": {
    "iso:country":"US",
    "sg:address":"101 Prospect Ave",
    "sg:city":"Hackensack",
    "sg:classifiers":[
        {
            "category":"Professional",
            "type":"Services"
        }
    ],
    "sg:phone":"+1 201 489 1509",
    "sg:postcode":"07601",
    "sg:province":"NJ",
    "sg:tags":[
        "establishment"
    ],
    "wof:name":"Aromac Inc",
    "wof:placetype":"venue"
},
  "geometry": {"coordinates":[-74.056703,40.886475],"type":"Point"}
}