{
  "type": "Feature",
  "properties": {
    "addr:full":"16 Van Wettering Pl Hackensack NJ 07601",
    "addr:housenumber":"16",
    "addr:postcode":"07601",
    "addr:street":"Van Wettering Pl",
    "iso:country":"US",
    "sg:address":"16 Van Wettering Pl",
    "sg:city":"Hackensack",
    "sg:classifiers":[
        {
            "category":"Professional",
            "subcategory":"Advertising",
            "type":"Services"
        }
    ],
    "sg:phone":"+1   ",
    "sg:postcode":"07601",
    "sg:province":"NJ",
    "sg:tags":[
        "mail",
        "direct"
    ],
    "wof:name":"Mailathon Inc",
    "wof:placetype":"venue"
},
  "geometry": {"coordinates":[-74.042096,40.87497],"type":"Point"}
}