{
  "type": "Feature",
  "properties": {
    "iso:country":"US",
    "sg:address":"945 Sergeantsville Rd",
    "sg:city":"Stockton",
    "sg:classifiers":[
        {
            "category":"Building & Trades",
            "subcategory":"Plumbing",
            "type":"Services"
        }
    ],
    "sg:phone":"+1 609 397 5709",
    "sg:postcode":"08559",
    "sg:province":"NJ",
    "sg:tags":[
        "conditioning",
        "air",
        "system",
        "contractor"
    ],
    "wof:name":"Gary C Culbertson",
    "wof:placetype":"venue"
},
  "geometry": {"coordinates":[-74.966713,40.416092],"type":"Point"}
}