{
  "type": "Feature",
  "properties": {
    "iso:country":"US",
    "sg:address":"683 Donald Dr N",
    "sg:city":"Bridgewater",
    "sg:classifiers":[
        {
            "category":"Health Services",
            "subcategory":"Health Practitioner",
            "type":"Services"
        }
    ],
    "sg:phone":"+1   ",
    "sg:postcode":"08807",
    "sg:province":"NJ",
    "wof:name":"A New Life LLC",
    "wof:placetype":"venue"
},
  "geometry": {"coordinates":[-74.627621,40.597841],"type":"Point"}
}