{
  "type": "Feature",
  "properties": {
    "iso:country":"US",
    "sg:address":"101 Columbia Rd",
    "sg:city":"Morristown",
    "sg:classifiers":[
        {
            "category":"Professional",
            "subcategory":"Management & Consulting",
            "type":"Services"
        }
    ],
    "sg:phone":"+1 973 455 1139",
    "sg:postcode":"07960",
    "sg:province":"NJ",
    "sg:tags":[
        "food"
    ],
    "wof:name":"Flik International",
    "wof:placetype":"venue"
},
  "geometry": {"coordinates":[-74.443361,40.79419],"type":"Point"}
}