{
  "type": "Feature",
  "properties": {
    "iso:country":"US",
    "sg:address":"5309 State Rte 33",
    "sg:city":"Wall Township",
    "sg:classifiers":[
        {
            "category":"Travel",
            "subcategory":"Hotels & Motels",
            "type":"Entertainment"
        }
    ],
    "sg:phone":"+1 732 938 3110",
    "sg:postcode":"07727",
    "sg:province":"NJ",
    "wof:name":"Econo Lodge",
    "wof:placetype":"venue"
},
  "geometry": {"coordinates":[-74.137147,40.22373],"type":"Point"}
}