{
  "type": "Feature",
  "properties": {
    "addr:full":"5324 River Dr Hammonton NJ 08037",
    "addr:housenumber":"5324",
    "addr:postcode":"08037",
    "addr:street":"River Dr",
    "iso:country":"US",
    "sg:address":"5324 River Dr",
    "sg:city":"Hammonton",
    "sg:classifiers":[
        {
            "category":"Manufacturing",
            "subcategory":"Tools & Machinery",
            "type":"Manufacturing & Wholesale Goods"
        }
    ],
    "sg:phone":"+1 609 965 3461",
    "sg:postcode":"08037",
    "sg:province":"NJ",
    "sg:tags":[
        "mfg",
        "repair",
        "industrial",
        "welding"
    ],
    "wof:name":"Diehl Welding & Machine Co",
    "wof:placetype":"venue"
},
  "geometry": {"coordinates":[-74.606461,39.618183],"type":"Point"}
}