{
  "type": "Feature",
  "properties": {
    "addr:full":"413 Clements Bridge Rd Barrington NJ 08007",
    "addr:housenumber":"413",
    "addr:postcode":"08007",
    "addr:street":"Clements Bridge Rd",
    "iso:country":"US",
    "sg:address":"413 Clements Bridge Rd",
    "sg:city":"Barrington",
    "sg:classifiers":[
        {
            "category":"Professional",
            "subcategory":"Lawyer & Legal Services",
            "type":"Services"
        }
    ],
    "sg:phone":"+1 856 589 8565",
    "sg:postcode":"08007",
    "sg:province":"NJ",
    "sg:tags":[
        "personal",
        "injury"
    ],
    "wof:name":"The Law Offices of Stephen Guice P C",
    "wof:placetype":"venue"
},
  "geometry": {"coordinates":[-75.05300099999999,39.8685],"type":"Point"}
}