{
  "type": "Feature",
  "properties": {
    "iso:country":"US",
    "sg:address":"304 Smith Ln",
    "sg:city":"Runnemede",
    "sg:classifiers":[
        {
            "category":"Arts & Performance",
            "subcategory":"Theater",
            "type":"Entertainment"
        }
    ],
    "sg:phone":"+1   ",
    "sg:postcode":"08078",
    "sg:province":"NJ",
    "sg:tags":[
        "group"
    ],
    "wof:name":"Bravo Entertainment",
    "wof:placetype":"venue"
},
  "geometry": {"coordinates":[-75.08029000000001,39.85377],"type":"Point"}
}