{
  "type": "Feature",
  "properties": {
    "addr:full":"2900 Dune Dr Avalon NJ 08202",
    "addr:housenumber":"2900",
    "addr:postcode":"08202",
    "addr:street":"Dune Dr",
    "iso:country":"US",
    "sg:address":"2900 Dune Dr",
    "sg:city":"Avalon",
    "sg:classifiers":[
        {
            "category":"Ice Cream",
            "type":"Food & Drink"
        }
    ],
    "sg:phone":"+1 609 368 1121",
    "sg:postcode":"08202",
    "sg:province":"NJ",
    "sg:tags":[
        "frozen",
        "yogurt"
    ],
    "wof:name":"Sundae Best Homemade Ice Cream",
    "wof:placetype":"venue"
},
  "geometry": {"coordinates":[-74.722455,39.096553],"type":"Point"}
}