{
  "type": "Feature",
  "properties": {
    "iso:country":"US",
    "sg:address":"701 Grier Ave",
    "sg:city":"Elizabeth",
    "sg:classifiers":[
        {
            "category":"Building & Trades",
            "subcategory":"Locksmith",
            "type":"Services"
        }
    ],
    "sg:phone":"+1 888 278 0806",
    "sg:postcode":"07202",
    "sg:province":"NJ",
    "sg:tags":[
        "key"
    ],
    "wof:name":"AAA Emergency Locksmith",
    "wof:placetype":"venue"
},
  "geometry": {"coordinates":[-74.218941,40.649182],"type":"Point"}
}