{
  "type": "Feature",
  "properties": {
    "iso:country":"US",
    "sg:address":"2515 E State St Exd",
    "sg:city":"Trenton",
    "sg:classifiers":[
        {
            "category":"Professional",
            "type":"Services"
        }
    ],
    "sg:phone":"+1 609 587 9881",
    "sg:postcode":"08619",
    "sg:province":"NJ",
    "sg:tags":[
        "establishment"
    ],
    "wof:name":"Cf Motorfreight",
    "wof:placetype":"venue"
},
  "geometry": {"coordinates":[-74.711187,40.247852],"type":"Point"}
}