{
  "type": "Feature",
  "properties": {
    "iso:country":"US",
    "sg:address":"610 Agnes Ave",
    "sg:city":"Brielle",
    "sg:classifiers":[
        {
            "category":"Professional",
            "subcategory":"Management & Consulting",
            "type":"Services"
        }
    ],
    "sg:phone":"+1 917 348 1221",
    "sg:postcode":"08730",
    "sg:province":"NJ",
    "wof:name":"Leopard Creek",
    "wof:placetype":"venue"
},
  "geometry": {"coordinates":[-74.057563,40.118394],"type":"Point"}
}