{
  "type": "Feature",
  "properties": {
    "addr:full":"189 Co Rd 526 Allentown NJ 08501",
    "addr:housenumber":"189;526",
    "addr:postcode":"08501",
    "addr:street":"Co Rd",
    "iso:country":"US",
    "sg:address":"189 Co Rd 526",
    "sg:city":"Allentown",
    "sg:classifiers":[
        {
            "category":"Building & Trades",
            "subcategory":"Construction",
            "type":"Services"
        }
    ],
    "sg:phone":"+1 609 208 1944",
    "sg:postcode":"08501",
    "sg:province":"NJ",
    "sg:tags":[
        "concrete",
        "contractor"
    ],
    "wof:name":"Caledonia Concrete Corporation",
    "wof:placetype":"venue"
},
  "geometry": {"coordinates":[-74.535124,40.17039],"type":"Point"}
}