{
  "type": "Feature",
  "properties": {
    "addr:full":"642 Morford Ave Long Branch NJ 07740",
    "addr:housenumber":"642",
    "addr:postcode":"07740",
    "addr:street":"Morford Ave",
    "iso:country":"US",
    "sg:address":"642 Morford Ave",
    "sg:city":"Long Branch",
    "sg:classifiers":[
        {
            "category":"Professional",
            "subcategory":"Advertising",
            "type":"Services"
        }
    ],
    "sg:phone":"+1   ",
    "sg:postcode":"07740",
    "sg:province":"NJ",
    "sg:tags":[
        "representative"
    ],
    "wof:name":"Esex Media",
    "wof:placetype":"venue"
},
  "geometry": {"coordinates":[-74.00585700000001,40.297274],"type":"Point"}
}