{
  "type": "Feature",
  "properties": {
    "iso:country":"US",
    "sg:address":"217 S Delsea Dr",
    "sg:city":"Vineland",
    "sg:classifiers":[
        {
            "category":"Wholesale",
            "subcategory":"Groceries",
            "type":"Manufacturing & Wholesale Goods"
        }
    ],
    "sg:phone":"+1 856 690 0137",
    "sg:postcode":"08360",
    "sg:province":"NJ",
    "sg:tags":[
        "baker"
    ],
    "wof:name":"Tastykake Thrift Outlet",
    "wof:placetype":"venue"
},
  "geometry": {"coordinates":[-75.043245,39.483439],"type":"Point"}
}