{
  "type": "Feature",
  "properties": {
    "addr:full":"1007 Macarthur Blvd Mahwah NJ 07430",
    "addr:housenumber":"1007",
    "addr:postcode":"07430",
    "addr:street":"Macarthur Blvd",
    "iso:country":"US",
    "sg:address":"1007 Macarthur Blvd",
    "sg:city":"Mahwah",
    "sg:classifiers":[
        {
            "category":"Real Estate",
            "subcategory":"Developer",
            "type":"Services"
        }
    ],
    "sg:phone":"+1   ",
    "sg:postcode":"07430",
    "sg:province":"NJ",
    "wof:name":"Pinnacle Commercial Properties",
    "wof:placetype":"venue"
},
  "geometry": {"coordinates":[-74.16774599999999,41.077528],"type":"Point"}
}