{
  "type": "Feature",
  "properties": {
    "addr:full":"718 Doris Ter Neptune NJ 07753",
    "addr:housenumber":"718",
    "addr:postcode":"07753",
    "addr:street":"Doris Ter",
    "iso:country":"US",
    "sg:address":"718 Doris Ter",
    "sg:city":"Neptune",
    "sg:classifiers":[
        {
            "category":"Wholesale",
            "subcategory":"Farm Supplies",
            "type":"Manufacturing & Wholesale Goods"
        }
    ],
    "sg:phone":"+1 732 922 8299",
    "sg:postcode":"07753",
    "sg:province":"NJ",
    "sg:tags":[
        "livestock"
    ],
    "wof:name":"Stirrup Cattle Inc",
    "wof:placetype":"venue"
},
  "geometry": {"coordinates":[-74.06492900000001,40.222417],"type":"Point"}
}