{
  "type": "Feature",
  "properties": {
    "addr:full":"634 N Franklin Tpke Allendale NJ 07401",
    "addr:housenumber":"634",
    "addr:postcode":"07401",
    "addr:street":"N Franklin Tpke",
    "iso:country":"US",
    "sg:address":"634 N Franklin Tpke",
    "sg:city":"Allendale",
    "sg:classifiers":[
        {
            "category":"Real Estate",
            "subcategory":"Architect",
            "type":"Services"
        }
    ],
    "sg:phone":"+1 201 785 8855",
    "sg:postcode":"07401",
    "sg:province":"NJ",
    "wof:name":"Z Plus Architects LLC",
    "wof:placetype":"venue"
},
  "geometry": {"coordinates":[-74.12857,41.039472],"type":"Point"}
}