{
  "type": "Feature",
  "properties": {
    "iso:country":"US",
    "sg:address":"1594 3rd Ave",
    "sg:city":"Phillipsburg",
    "sg:classifiers":[
        {
            "category":"Shopping",
            "subcategory":"Bicycles & Sporting Goods",
            "type":"Retail Goods"
        },
        {
            "category":"Travel",
            "subcategory":"Travel Agent",
            "type":"Entertainment"
        },
        {
            "category":"Shopping",
            "type":"Retail Goods"
        },
        {
            "category":"Sports & Exercise",
            "subcategory":"Swimming Pool",
            "type":"Entertainment"
        }
    ],
    "sg:phone":"+1 908 454 3577",
    "sg:postcode":"08865",
    "sg:province":"NJ",
    "sg:tags":[
        "supply",
        "instruction",
        "equipment",
        "agency",
        "services-commercial",
        "divers'",
        "diving"
    ],
    "sg:website":"http://www.kunuku.com",
    "wof:name":"Kunuku Dive & Travel",
    "wof:placetype":"venue"
},
  "geometry": {"coordinates":[-75.157026,40.657933],"type":"Point"}
}