{
  "type": "Feature",
  "properties": {
    "addr:full":"228 Franklin Ave Nutley NJ 07110",
    "addr:housenumber":"228",
    "addr:postcode":"07110",
    "addr:street":"Franklin Ave",
    "iso:country":"US",
    "sg:address":"228 Franklin Ave",
    "sg:city":"Nutley",
    "sg:classifiers":[
        {
            "category":"Personal",
            "type":"Services"
        }
    ],
    "sg:phone":"+1 973 235 0285",
    "sg:postcode":"07110",
    "sg:province":"NJ",
    "sg:tags":[
        "program",
        "physical",
        "exercise",
        "fitness"
    ],
    "wof:name":"Ladies First Fitness",
    "wof:placetype":"venue"
},
  "geometry": {"coordinates":[-74.16255,40.815083],"type":"Point"}
}