{
  "type": "Feature",
  "properties": {
    "iso:country":"US",
    "sg:address":"1071 Main St",
    "sg:city":"Paterson",
    "sg:classifiers":[
        {
            "category":"Banks & Credit Unions",
            "subcategory":"Financial Services",
            "type":"Services"
        }
    ],
    "sg:phone":"+1 862 264 4068",
    "sg:postcode":"07503",
    "sg:province":"NJ",
    "sg:tags":[
        "broker",
        "mortgage"
    ],
    "wof:name":"Laridian Mortgage First",
    "wof:placetype":"venue"
},
  "geometry": {"coordinates":[-74.156558,40.891906],"type":"Point"}
}