{
  "type": "Feature",
  "properties": {
    "addr:full":"60 E State St Trenton NJ 08608",
    "addr:housenumber":"60",
    "addr:postcode":"08608",
    "addr:street":"E State St",
    "iso:country":"US",
    "sg:address":"60 E State St",
    "sg:city":"Trenton",
    "sg:classifiers":[
        {
            "category":"Shopping",
            "subcategory":"Pharmacy",
            "type":"Retail Goods"
        }
    ],
    "sg:phone":"+1   ",
    "sg:postcode":"08608",
    "sg:province":"NJ",
    "sg:tags":[
        "drug",
        "store"
    ],
    "wof:name":"Eckerd",
    "wof:placetype":"venue"
},
  "geometry": {"coordinates":[-74.764978,40.220316],"type":"Point"}
}