{
  "type": "Feature",
  "properties": {
    "addr:full":"5 Fisher St Sayreville NJ 08872",
    "addr:housenumber":"5",
    "addr:postcode":"08872",
    "addr:street":"Fisher St",
    "iso:country":"US",
    "sg:address":"5 Fisher St",
    "sg:city":"Sayreville",
    "sg:classifiers":[
        {
            "category":"Restaurant",
            "type":"Food & Drink"
        }
    ],
    "sg:phone":"+1 732 254 5096",
    "sg:postcode":"08872",
    "sg:province":"NJ",
    "wof:name":"Sayreville Family Restaurant",
    "wof:placetype":"venue"
},
  "geometry": {"coordinates":[-74.367694,40.45625],"type":"Point"}
}