{
  "type": "Feature",
  "properties": {
    "addr:full":"9370 N Crescent Blvd Pennsauken NJ 08110",
    "addr:housenumber":"9370",
    "addr:postcode":"08110",
    "addr:street":"N Crescent Blvd",
    "iso:country":"US",
    "sg:address":"9370 N Crescent Blvd",
    "sg:city":"Pennsauken",
    "sg:classifiers":[
        {
            "category":"Health Services",
            "subcategory":"Hospital",
            "type":"Services"
        },
        {
            "category":"Health Services",
            "subcategory":"Health Practitioner",
            "type":"Services"
        }
    ],
    "sg:phone":"+1 856 662 0660",
    "sg:postcode":"08110",
    "sg:province":"NJ",
    "sg:tags":[
        "acupuncture"
    ],
    "wof:name":"Cooper University Hospital",
    "wof:placetype":"venue"
},
  "geometry": {"coordinates":[-75.022598,39.9814],"type":"Point"}
}