{
  "type": "Feature",
  "properties": {
    "addr:full":"131 Horseneck Point Rd Oceanport NJ 07757",
    "addr:housenumber":"131",
    "addr:postcode":"07757",
    "addr:street":"Horseneck Point Rd",
    "iso:country":"US",
    "sg:address":"131 Horseneck Point Rd",
    "sg:city":"Oceanport",
    "sg:classifiers":[
        {
            "category":"Professional",
            "subcategory":"Business Services",
            "type":"Services"
        }
    ],
    "sg:phone":"+1   ",
    "sg:postcode":"07757",
    "sg:province":"NJ",
    "sg:tags":[
        "textile",
        "good",
        "mfg"
    ],
    "wof:name":"Grant Industries",
    "wof:placetype":"venue"
},
  "geometry": {"coordinates":[-74.026647,40.321202],"type":"Point"}
}