{
  "type": "Feature",
  "properties": {
    "iso:country":"US",
    "sg:address":"268 Cliffwood Ave",
    "sg:city":"Cliffwood",
    "sg:classifiers":[
        {
            "category":"Professional",
            "subcategory":"Detective & Security Services",
            "type":"Services"
        },
        {
            "category":"Wholesale",
            "subcategory":"Electrical",
            "type":"Manufacturing & Wholesale Goods"
        }
    ],
    "sg:phone":"+1 732 583 0006",
    "sg:postcode":"07721",
    "sg:province":"NJ",
    "sg:tags":[
        "control",
        "system"
    ],
    "sg:website":"www.integratedsystems.org",
    "wof:name":"Integrated Systems and Svcs",
    "wof:placetype":"venue"
},
  "geometry": {"coordinates":[-74.235686,40.434805],"type":"Point"}
}