{
  "type": "Feature",
  "properties": {
    "iso:country":"US",
    "sg:address":"1028 State Rte 94",
    "sg:city":"Blairstown",
    "sg:classifiers":[
        {
            "category":"Autos & Motor Vehicles",
            "subcategory":"Auto Supplies",
            "type":"Retail Goods"
        }
    ],
    "sg:phone":"+1 908 362 6269",
    "sg:postcode":"07825",
    "sg:province":"NJ",
    "sg:tags":[
        "tire"
    ],
    "wof:name":"Country Discount Tire & Pool",
    "wof:placetype":"venue"
},
  "geometry": {"coordinates":[-74.90835,40.987711],"type":"Point"}
}