{
  "type": "Feature",
  "properties": {
    "addr:full":"660 Fairmont Ave Westfield NJ 07090",
    "addr:housenumber":"660",
    "addr:postcode":"07090",
    "addr:street":"Fairmont Ave",
    "iso:country":"US",
    "sg:address":"660 Fairmont Ave",
    "sg:city":"Westfield",
    "sg:classifiers":[
        {
            "category":"Professional",
            "subcategory":"Computer Services",
            "type":"Services"
        }
    ],
    "sg:phone":"+1 908 232 4674",
    "sg:postcode":"07090",
    "sg:province":"NJ",
    "wof:name":"Eyeon Associates",
    "wof:placetype":"venue"
},
  "geometry": {"coordinates":[-74.336186,40.654544],"type":"Point"}
}