{
  "type": "Feature",
  "properties": {
    "addr:full":"600 N County Line Rd Jackson NJ 08527",
    "addr:housenumber":"600",
    "addr:postcode":"08527",
    "addr:street":"N County Line Rd",
    "iso:country":"US",
    "sg:address":"600 N County Line Rd",
    "sg:city":"Jackson",
    "sg:classifiers":[
        {
            "category":"Building & Trades",
            "subcategory":"Construction",
            "type":"Services"
        }
    ],
    "sg:phone":"+1 732 833 5005",
    "sg:postcode":"08527",
    "sg:province":"NJ",
    "sg:tags":[
        "contractor"
    ],
    "wof:name":"Einhorn Construction LLC",
    "wof:placetype":"venue"
},
  "geometry": {"coordinates":[-74.32190799999999,40.146927],"type":"Point"}
}