{
  "type": "Feature",
  "properties": {
    "addr:full":"1089 Ringwood Ave Pompton Lakes NJ 07442",
    "addr:housenumber":"1089",
    "addr:postcode":"07442",
    "addr:street":"Ringwood Ave",
    "iso:country":"US",
    "sg:address":"1089 Ringwood Ave",
    "sg:city":"Pompton Lakes",
    "sg:classifiers":[
        {
            "category":"Recreation",
            "type":"Entertainment"
        }
    ],
    "sg:phone":"+1 973 616 0429",
    "sg:postcode":"07442",
    "sg:province":"NJ",
    "sg:tags":[
        "psychic",
        "medium"
    ],
    "wof:name":"Natural Wisdom",
    "wof:placetype":"venue"
},
  "geometry": {"coordinates":[-74.294732,40.999114],"type":"Point"}
}