{
  "type": "Feature",
  "properties": {
    "iso:country":"US",
    "sg:address":"70 Hudson St Ste 4B",
    "sg:city":"Hoboken",
    "sg:classifiers":[
        {
            "category":"Communications",
            "type":"Services"
        }
    ],
    "sg:phone":"+1 201 792 3007",
    "sg:postcode":"07030",
    "sg:province":"NJ",
    "sg:tags":[
        "medium",
        "mass"
    ],
    "sg:website":"www.adforum.com/",
    "wof:name":"AdForum MayDream Inc.",
    "wof:placetype":"venue"
},
  "geometry": {"coordinates":[-74.030141,40.736153],"type":"Point"}
}