{
  "type": "Feature",
  "properties": {
    "addr:full":"1 Brookmead Dr Cherry Hill NJ 08034",
    "addr:housenumber":"1",
    "addr:postcode":"08034",
    "addr:street":"Brookmead Dr",
    "iso:country":"US",
    "sg:address":"1 Brookmead Dr",
    "sg:city":"Cherry Hill",
    "sg:classifiers":[
        {
            "category":"Health Services",
            "subcategory":"Doctor",
            "type":"Services"
        }
    ],
    "sg:phone":"+1 856 427 4001",
    "sg:postcode":"08034",
    "sg:province":"NJ",
    "sg:tags":[
        "physician",
        "surgeon"
    ],
    "wof:name":"Brookmead Medical Assoc PC",
    "wof:placetype":"venue"
},
  "geometry": {"coordinates":[-75.00665499999999,39.911617],"type":"Point"}
}