{
  "type": "Feature",
  "properties": {
    "addr:full":"395 Harding Hwy Elmer NJ 08318",
    "addr:housenumber":"395",
    "addr:postcode":"08318",
    "addr:street":"Harding Hwy",
    "iso:country":"US",
    "sg:address":"395 Harding Hwy",
    "sg:city":"Elmer",
    "sg:classifiers":[
        {
            "category":"Food & Beverages",
            "subcategory":"Fruits & Vegetables",
            "type":"Retail Goods"
        }
    ],
    "sg:phone":"+1 856 358 1370",
    "sg:postcode":"08318",
    "sg:province":"NJ",
    "sg:tags":[
        "produce"
    ],
    "wof:name":"Fox's Market Garden Ctr/Video",
    "wof:placetype":"venue"
},
  "geometry": {"coordinates":[-75.175979,39.596816],"type":"Point"}
}