{
  "type": "Feature",
  "properties": {
    "addr:full":"95 Castle Rd Secaucus NJ 07094",
    "addr:housenumber":"95",
    "addr:postcode":"07094",
    "addr:street":"Castle Rd",
    "iso:country":"US",
    "sg:address":"95 Castle Rd",
    "sg:city":"Secaucus",
    "sg:classifiers":[
        {
            "category":"Government",
            "subcategory":"Office",
            "type":"Public Place"
        }
    ],
    "sg:phone":"+1 201 865 0043",
    "sg:postcode":"07094",
    "sg:province":"NJ",
    "sg:tags":[
        "international",
        "affairs",
        "supply"
    ],
    "wof:name":"USF",
    "wof:placetype":"venue"
},
  "geometry": {"coordinates":[-74.08432999999999,40.773561],"type":"Point"}
}