{
  "type": "Feature",
  "properties": {
    "iso:country":"US",
    "sg:address":"429 White Horse Pike",
    "sg:city":"Atco",
    "sg:classifiers":[
        {
            "category":"Health Services",
            "subcategory":"Doctor",
            "type":"Services"
        }
    ],
    "sg:phone":"+1 856 767 1026",
    "sg:postcode":"08004",
    "sg:province":"NJ",
    "sg:tags":[
        "physician"
    ],
    "wof:name":"Advanced Fmly Hlth & Wellness",
    "wof:placetype":"venue"
},
  "geometry": {"coordinates":[-74.891435,39.765338],"type":"Point"}
}