{
  "type": "Feature",
  "properties": {
    "iso:country":"US",
    "sg:address":"141 Mount Laurel Rd",
    "sg:city":"Mt Laurel",
    "sg:classifiers":[
        {
            "category":"Food & Beverages",
            "subcategory":"Specialty",
            "type":"Retail Goods"
        }
    ],
    "sg:phone":"+1 856 616 1809",
    "sg:postcode":"08054",
    "sg:province":"NJ",
    "sg:tags":[
        "health",
        "diet"
    ],
    "wof:name":"Teri Chew",
    "wof:placetype":"venue"
},
  "geometry": {"coordinates":[-74.926041,39.957687],"type":"Point"}
}