{
  "type": "Feature",
  "properties": {
    "addr:full":"6115 Long Beach Blvd Beach Haven NJ 08008",
    "addr:housenumber":"6115",
    "addr:postcode":"08008",
    "addr:street":"Long Beach Blvd",
    "iso:country":"US",
    "sg:address":"6115 Long Beach Blvd",
    "sg:city":"Beach Haven",
    "sg:classifiers":[
        {
            "category":"Retail",
            "subcategory":"Laundry & Dry Cleaning",
            "type":"Services"
        }
    ],
    "sg:phone":"+1 609 494 5858",
    "sg:postcode":"08008",
    "sg:province":"NJ",
    "sg:tags":[
        "cleaners",
        "rug",
        "carpet"
    ],
    "wof:name":"Superb Carpet Cleaning",
    "wof:placetype":"venue"
},
  "geometry": {"coordinates":[-74.197256,39.620775],"type":"Point"}
}