{
  "type": "Feature",
  "properties": {
    "iso:country":"US",
    "sg:address":"17 Gerry Ln",
    "sg:city":"Sicklerville",
    "sg:classifiers":[
        {
            "category":"Home & Garden",
            "subcategory":"Hardware",
            "type":"Retail Goods"
        }
    ],
    "sg:phone":"+1   ",
    "sg:postcode":"08081",
    "sg:province":"NJ",
    "wof:name":"A&M Tool Sales",
    "wof:placetype":"venue"
},
  "geometry": {"coordinates":[-74.988648,39.738636],"type":"Point"}
}