{
  "type": "Feature",
  "properties": {
    "iso:country":"US",
    "sg:address":"50 5th Ave",
    "sg:city":"Seaside Park",
    "sg:classifiers":[
        {
            "category":"Shopping",
            "subcategory":"Pharmacy",
            "type":"Retail Goods"
        }
    ],
    "sg:phone":"+1   ",
    "sg:postcode":"08752",
    "sg:province":"NJ",
    "wof:name":"Eckerd",
    "wof:placetype":"venue"
},
  "geometry": {"coordinates":[-74.077473,39.919563],"type":"Point"}
}