{
  "type": "Feature",
  "properties": {
    "iso:country":"US",
    "sg:address":"418 Addison Pl",
    "sg:city":"Ridgewood",
    "sg:classifiers":[
        {
            "category":"Professional",
            "subcategory":"Management & Consulting",
            "type":"Services"
        }
    ],
    "sg:phone":"+1   ",
    "sg:postcode":"07450",
    "sg:province":"NJ",
    "wof:name":"Decision Processes Intl",
    "wof:placetype":"venue"
},
  "geometry": {"coordinates":[-74.109559,40.976447],"type":"Point"}
}