{
  "type": "Feature",
  "properties": {
    "iso:country":"US",
    "sg:address":"4206 Park Ave",
    "sg:city":"Weehawken",
    "sg:classifiers":[
        {
            "category":"Airline",
            "type":"Transportation"
        }
    ],
    "sg:phone":"+1 201 864 9209",
    "sg:postcode":"07086",
    "sg:province":"NJ",
    "sg:tags":[
        "courier",
        "air"
    ],
    "wof:name":"Urgente Express",
    "wof:placetype":"venue"
},
  "geometry": {"coordinates":[-74.019599,40.775728],"type":"Point"}
}