{
  "type": "Feature",
  "properties": {
    "addr:full":"1209 Main Ave Clifton NJ 07011",
    "addr:housenumber":"1209",
    "addr:postcode":"07011",
    "addr:street":"Main Ave",
    "iso:country":"US",
    "sg:address":"1209 Main Ave",
    "sg:city":"Clifton",
    "sg:classifiers":[
        {
            "category":"Food & Beverages",
            "subcategory":"Bakery",
            "type":"Retail Goods"
        }
    ],
    "sg:phone":"+1 973 340 8245",
    "sg:postcode":"07011",
    "sg:province":"NJ",
    "sg:tags":[
        "doughnut"
    ],
    "wof:name":"Dunkin Donuts",
    "wof:placetype":"venue"
},
  "geometry": {"coordinates":[-74.141403,40.8769],"type":"Point"}
}