{
  "type": "Feature",
  "properties": {
    "addr:full":"1930 State Route 57 Hackettstown NJ 07840",
    "addr:housenumber":"1930",
    "addr:postcode":"07840",
    "addr:street":"State Route 57",
    "iso:country":"US",
    "sg:address":"1930 State Route 57",
    "sg:city":"Hackettstown",
    "sg:classifiers":[
        {
            "category":"Ice Cream",
            "type":"Food & Drink"
        }
    ],
    "sg:menulink":"http://www.allmenus.com/nj/mansfield/184129-cold-stone-creamery/menu/",
    "sg:phone":"+1 908 850 9901",
    "sg:postcode":"07840",
    "sg:province":"NJ",
    "sg:tags":[
        "smoothy",
        "juice",
        "american"
    ],
    "wof:name":"Cold Stone Creamery",
    "wof:placetype":"venue"
},
  "geometry": {"coordinates":[-74.83569799999999,40.822098],"type":"Point"}
}