{
  "type": "Feature",
  "properties": {
    "iso:country":"US",
    "sg:address":"12 Main St",
    "sg:city":"Madison",
    "sg:classifiers":[
        {
            "category":"Banks & Credit Unions",
            "subcategory":"Bank",
            "type":"Services"
        }
    ],
    "sg:phone":"+1   ",
    "sg:postcode":"07940",
    "sg:province":"NJ",
    "sg:tags":[
        "state",
        "commercial"
    ],
    "wof:name":"Norcrown Bank Inc",
    "wof:placetype":"venue"
},
  "geometry": {"coordinates":[-74.416509,40.759787],"type":"Point"}
}