{
  "type": "Feature",
  "properties": {
    "addr:full":"473 Winthrop Rd Teaneck NJ 07666",
    "addr:housenumber":"473",
    "addr:postcode":"07666",
    "addr:street":"Winthrop Rd",
    "iso:country":"US",
    "sg:address":"473 Winthrop Rd",
    "sg:city":"Teaneck",
    "sg:classifiers":[
        {
            "category":"Health Services",
            "subcategory":"Health Practitioner",
            "type":"Services"
        }
    ],
    "sg:phone":"+1 201 862 0923",
    "sg:postcode":"07666",
    "sg:province":"NJ",
    "sg:tags":[
        "psychotherapist"
    ],
    "wof:name":"Sarah Goodman",
    "wof:placetype":"venue"
},
  "geometry": {"coordinates":[-74.015754,40.90972],"type":"Point"}
}