{
  "type": "Feature",
  "properties": {
    "addr:full":"547 Union Blvd Totowa NJ 07512",
    "addr:housenumber":"547",
    "addr:postcode":"07512",
    "addr:street":"Union Blvd",
    "iso:country":"US",
    "sg:address":"547 Union Blvd",
    "sg:city":"Totowa",
    "sg:classifiers":[
        {
            "category":"Health Services",
            "subcategory":"Dentist",
            "type":"Services"
        }
    ],
    "sg:phone":"+1 973 942 3233",
    "sg:postcode":"07512",
    "sg:province":"NJ",
    "sg:website":"www.dentalartsoftotowa.com",
    "wof:name":"Affordable Gentle Family Dental Care",
    "wof:placetype":"venue"
},
  "geometry": {"coordinates":[-74.2183,40.899899],"type":"Point"}
}