{
  "type": "Feature",
  "properties": {
    "addr:full":"600 Cape May St Harrison NJ 07029",
    "addr:housenumber":"600",
    "addr:postcode":"07029",
    "addr:street":"Cape May St",
    "iso:country":"US",
    "sg:address":"600 Cape May St",
    "sg:city":"Harrison",
    "sg:classifiers":[
        {
            "category":"Freight",
            "type":"Transportation"
        }
    ],
    "sg:phone":"+1 973 481 1200",
    "sg:postcode":"07029",
    "sg:province":"NJ",
    "sg:tags":[
        "general"
    ],
    "wof:name":"National Wholesale Liquidators",
    "wof:placetype":"venue"
},
  "geometry": {"coordinates":[-74.148855,40.737515],"type":"Point"}
}