{
  "type": "Feature",
  "properties": {
    "iso:country":"US",
    "sg:address":"11 Lacey Rd",
    "sg:city":"Forked River",
    "sg:classifiers":[
        {
            "category":"Shopping",
            "subcategory":"Jewelry",
            "type":"Retail Goods"
        }
    ],
    "sg:phone":"+1   ",
    "sg:postcode":"08731",
    "sg:province":"NJ",
    "wof:name":"Blase De Natale Jewelers",
    "wof:placetype":"venue"
},
  "geometry": {"coordinates":[-74.191986,39.840961],"type":"Point"}
}