{
  "type": "Feature",
  "properties": {
    "iso:country":"US",
    "sg:address":"11 W Ormond Ave",
    "sg:city":"Cherry Hill",
    "sg:classifiers":[
        {
            "category":"Health Services",
            "subcategory":"Medical Lab",
            "type":"Services"
        }
    ],
    "sg:phone":"+1 856 616 1080",
    "sg:postcode":"08002",
    "sg:province":"NJ",
    "sg:tags":[
        "x"
    ],
    "wof:name":"Womb With A View-Cherry Hill",
    "wof:placetype":"venue"
},
  "geometry": {"coordinates":[-75.007817,39.91847],"type":"Point"}
}