{
  "type": "Feature",
  "properties": {
    "addr:full":"922 Main St Asbury Park NJ 07712",
    "addr:housenumber":"922",
    "addr:postcode":"07712",
    "addr:street":"Main St Asbury",
    "iso:country":"US",
    "sg:address":"922 Main St",
    "sg:city":"Asbury Park",
    "sg:classifiers":[
        {
            "category":"Professional",
            "subcategory":"Management & Consulting",
            "type":"Services"
        }
    ],
    "sg:phone":"+1   ",
    "sg:postcode":"07712",
    "sg:province":"NJ",
    "sg:tags":[
        "loan",
        "broker"
    ],
    "wof:name":"Loan Tree Corp",
    "wof:placetype":"venue"
},
  "geometry": {"coordinates":[-74.01103500000001,40.222227],"type":"Point"}
}