{
  "type": "Feature",
  "properties": {
    "iso:country":"US",
    "sg:address":"454 Market St",
    "sg:city":"Elmwood Park",
    "sg:classifiers":[
        {
            "category":"Restaurant",
            "type":"Food & Drink"
        }
    ],
    "sg:phone":"+1 201 797 8881",
    "sg:postcode":"07407",
    "sg:province":"NJ",
    "sg:tags":[
        "chinese"
    ],
    "wof:name":"China House",
    "wof:placetype":"venue"
},
  "geometry": {"coordinates":[-74.111,40.8988],"type":"Point"}
}