{
  "type": "Feature",
  "properties": {
    "iso:country":"US",
    "sg:address":"576 Princess Ct",
    "sg:city":"Toms River",
    "sg:classifiers":[
        {
            "category":"Building & Trades",
            "subcategory":"Construction",
            "type":"Services"
        }
    ],
    "sg:phone":"+1 732 267 4444",
    "sg:postcode":"08753",
    "sg:province":"NJ",
    "sg:tags":[
        "contractor"
    ],
    "wof:name":"Jdi Contracting",
    "wof:placetype":"venue"
},
  "geometry": {"coordinates":[-74.15810399999999,39.958603],"type":"Point"}
}