{
  "type": "Feature",
  "properties": {
    "iso:country":"US",
    "sg:address":"211 US Hwy 9",
    "sg:city":"Marmora",
    "sg:classifiers":[
        {
            "category":"Professional",
            "subcategory":"Computer Services",
            "type":"Services"
        }
    ],
    "sg:phone":"+1 609 390 8383",
    "sg:postcode":"08223",
    "sg:province":"NJ",
    "sg:tags":[
        "internet"
    ],
    "wof:name":"New Jersey Broad Band",
    "wof:placetype":"venue"
},
  "geometry": {"coordinates":[-74.64286800000001,39.270675],"type":"Point"}
}