{
  "type": "Feature",
  "properties": {
    "iso:country":"US",
    "sg:address":"1320 US Hwy 22",
    "sg:city":"Lebanon",
    "sg:classifiers":[
        {
            "category":"Home & Garden",
            "subcategory":"Furniture",
            "type":"Retail Goods"
        }
    ],
    "sg:phone":"+1 908 236 9321",
    "sg:postcode":"08833",
    "sg:province":"NJ",
    "sg:tags":[
        "equipment",
        "kitchen",
        "cabinet"
    ],
    "wof:name":"CWI Kitchens & Baths",
    "wof:placetype":"venue"
},
  "geometry": {"coordinates":[-74.83944700000001,40.644155],"type":"Point"}
}