{
  "type": "Feature",
  "properties": {
    "iso:country":"US",
    "sg:address":"5311 Kennedy Blvd E Ste A",
    "sg:city":"West New York",
    "sg:classifiers":[
        {
            "category":"Health Services",
            "subcategory":"Doctor",
            "type":"Services"
        }
    ],
    "sg:phone":"+1 201 866 3422",
    "sg:postcode":"07093",
    "sg:province":"NJ",
    "wof:name":"Carluccio Chas MD",
    "wof:placetype":"venue"
},
  "geometry": {"coordinates":[-74.01156899999999,40.781068],"type":"Point"}
}