{
  "type": "Feature",
  "properties": {
    "iso:country":"US",
    "sg:address":"208 17th St S",
    "sg:city":"Brigantine",
    "sg:classifiers":[
        {
            "category":"Building & Trades",
            "subcategory":"Construction",
            "type":"Services"
        }
    ],
    "sg:phone":"+1 609 266 9750",
    "sg:postcode":"08203",
    "sg:province":"NJ",
    "sg:tags":[
        "home",
        "improvement"
    ],
    "wof:name":"Bob O'Donnell Custom Hm Imprv",
    "wof:placetype":"venue"
},
  "geometry": {"coordinates":[-74.375229,39.400726],"type":"Point"}
}