{
  "type": "Feature",
  "properties": {
    "iso:country":"US",
    "sg:address":"81 Fillmore St",
    "sg:city":"Newark",
    "sg:classifiers":[
        {
            "category":"Building & Trades",
            "subcategory":"Construction",
            "type":"Services"
        }
    ],
    "sg:phone":"+1 973 344 3125",
    "sg:postcode":"07105",
    "sg:province":"NJ",
    "sg:tags":[
        "nonresidential"
    ],
    "wof:name":"J&M Construction Inc",
    "wof:placetype":"venue"
},
  "geometry": {"coordinates":[-74.150689,40.72916],"type":"Point"}
}