{
  "type": "Feature",
  "properties": {
    "addr:full":"12 Collinson Dr Middletown NJ 07748",
    "addr:housenumber":"12",
    "addr:postcode":"07748",
    "addr:street":"Collinson Dr",
    "iso:country":"US",
    "sg:address":"12 Collinson Dr",
    "sg:city":"Middletown",
    "sg:classifiers":[
        {
            "category":"Building & Trades",
            "subcategory":"Construction",
            "type":"Services"
        }
    ],
    "sg:phone":"+1 732 671 6647",
    "sg:postcode":"07748",
    "sg:province":"NJ",
    "sg:tags":[
        "general",
        "contractor"
    ],
    "wof:name":"Riker John J General Contr",
    "wof:placetype":"venue"
},
  "geometry": {"coordinates":[-74.11039,40.418195],"type":"Point"}
}