{
  "type": "Feature",
  "properties": {
    "addr:full":"1320 State Rte 23 Sussex NJ 07461",
    "addr:housenumber":"1320",
    "addr:postcode":"07461",
    "addr:street":"State Rte 23",
    "iso:country":"US",
    "sg:address":"1320 State Rte 23",
    "sg:city":"Sussex",
    "sg:classifiers":[
        {
            "category":"Communications",
            "subcategory":"Film & Video Production",
            "type":"Services"
        }
    ],
    "sg:phone":"+1 973 633 0170",
    "sg:postcode":"07461",
    "sg:province":"NJ",
    "sg:tags":[
        "editing",
        "tape"
    ],
    "wof:name":"Multivision",
    "wof:placetype":"venue"
},
  "geometry": {"coordinates":[-74.653953,41.293201],"type":"Point"}
}