{
  "type": "Feature",
  "properties": {
    "iso:country":"US",
    "sg:address":"7 Canyon Rd",
    "sg:city":"Sussex",
    "sg:classifiers":[
        {
            "category":"Professional",
            "subcategory":"Detective & Security Services",
            "type":"Services"
        }
    ],
    "sg:phone":"+1 973 702 8058",
    "sg:postcode":"07461",
    "sg:province":"NJ",
    "sg:tags":[
        "system"
    ],
    "wof:name":"Fin Security",
    "wof:placetype":"venue"
},
  "geometry": {"coordinates":[-74.525052,41.241228],"type":"Point"}
}