{
  "type": "Feature",
  "properties": {
    "addr:full":"147 Rafkind Rd Bloomingdale NJ 07403",
    "addr:housenumber":"147",
    "addr:postcode":"07403",
    "addr:street":"Rafkind Rd",
    "iso:country":"US",
    "sg:address":"147 Rafkind Rd",
    "sg:city":"Bloomingdale",
    "sg:classifiers":[
        {
            "category":"Building & Trades",
            "subcategory":"Construction",
            "type":"Services"
        }
    ],
    "sg:phone":"+1 973 492 0450",
    "sg:postcode":"07403",
    "sg:province":"NJ",
    "sg:tags":[
        "remodeling",
        "contractor"
    ],
    "wof:name":"Can Do All",
    "wof:placetype":"venue"
},
  "geometry": {"coordinates":[-74.32565200000001,41.015805],"type":"Point"}
}