{
  "type": "Feature",
  "properties": {
    "iso:country":"US",
    "sg:address":"431 North Ave",
    "sg:city":"Dunellen",
    "sg:classifiers":[
        {
            "category":"Retail",
            "subcategory":"Auto Repair",
            "type":"Services"
        }
    ],
    "sg:phone":"+1 732 968 4400",
    "sg:postcode":"08812",
    "sg:province":"NJ",
    "sg:tags":[
        "repairing",
        "automobile"
    ],
    "wof:name":"Turlip's Garage",
    "wof:placetype":"venue"
},
  "geometry": {"coordinates":[-74.46689499999999,40.589408],"type":"Point"}
}