{
  "type": "Feature",
  "properties": {
    "iso:country":"US",
    "sg:address":"97 Westervelt Pl",
    "sg:city":"Passaic",
    "sg:classifiers":[
        {
            "category":"Shopping",
            "subcategory":"Discount & Variety Stores",
            "type":"Retail Goods"
        }
    ],
    "sg:phone":"+1 973 472 0478",
    "sg:postcode":"07055",
    "sg:province":"NJ",
    "sg:tags":[
        "merchandise",
        "general"
    ],
    "wof:name":"Weiss Enterprises",
    "wof:placetype":"venue"
},
  "geometry": {"coordinates":[-74.12522,40.848706],"type":"Point"}
}