{
  "type": "Feature",
  "properties": {
    "addr:full":"389 State Rte 17 Mahwah NJ 07430",
    "addr:housenumber":"389",
    "addr:postcode":"07430",
    "addr:street":"State Rte 17",
    "iso:country":"US",
    "sg:address":"389 State Rte 17",
    "sg:city":"Mahwah",
    "sg:phone":"+1 201 529 0012",
    "sg:postcode":"07430",
    "sg:province":"NJ",
    "sg:tags":[
        "oil"
    ],
    "wof:name":"Fuel Max Mahwah Inc",
    "wof:placetype":"venue"
},
  "geometry": {"coordinates":[-74.149492,41.079542],"type":"Point"}
}