{
  "type": "Feature",
  "properties": {
    "addr:full":"661 Anderson Ave Cliffside Park NJ 07010",
    "addr:housenumber":"661",
    "addr:postcode":"07010",
    "addr:street":"Anderson Ave",
    "iso:country":"US",
    "sg:address":"661 Anderson Ave",
    "sg:city":"Cliffside Park",
    "sg:classifiers":[
        {
            "category":"Shopping",
            "subcategory":"Optical Goods",
            "type":"Retail Goods"
        },
        {
            "category":"Health Services",
            "subcategory":"Optometrist",
            "type":"Services"
        }
    ],
    "sg:phone":"+1 201 941 3937",
    "sg:postcode":"07010",
    "sg:province":"NJ",
    "wof:name":"Eye Care Plus",
    "wof:placetype":"venue"
},
  "geometry": {"coordinates":[-73.98678,40.827591],"type":"Point"}
}