{
  "type": "Feature",
  "properties": {
    "iso:country":"US",
    "sg:address":"1301 State Rte 168",
    "sg:city":"Blackwood",
    "sg:classifiers":[
        {
            "category":"Shopping",
            "subcategory":"Florist",
            "type":"Retail Goods"
        }
    ],
    "sg:phone":"+1 856 227 6197",
    "sg:postcode":"08012",
    "sg:province":"NJ",
    "sg:tags":[
        "construction",
        "material"
    ],
    "wof:name":"Gardens At Grenloch",
    "wof:placetype":"venue"
},
  "geometry": {"coordinates":[-75.06777599999999,39.822969],"type":"Point"}
}