{
  "type": "Feature",
  "properties": {
    "addr:full":"96 Flock Rd Trenton NJ 08619",
    "addr:housenumber":"96",
    "addr:postcode":"08619",
    "addr:street":"Flock Rd",
    "iso:country":"US",
    "sg:address":"96 Flock Rd",
    "sg:city":"Trenton",
    "sg:classifiers":[
        {
            "category":"Government",
            "subcategory":"Office",
            "type":"Public Place"
        }
    ],
    "sg:phone":"+1   ",
    "sg:postcode":"08619",
    "sg:province":"NJ",
    "sg:tags":[
        "national",
        "security"
    ],
    "wof:name":"United States Marine Corps",
    "wof:placetype":"venue"
},
  "geometry": {"coordinates":[-74.683188,40.249045],"type":"Point"}
}