{
  "type": "Feature",
  "properties": {
    "addr:full":"810 S 18th St Newark NJ 07108",
    "addr:housenumber":"810",
    "addr:postcode":"07108",
    "addr:street":"S 18Th St",
    "iso:country":"US",
    "sg:address":"810 S 18th St",
    "sg:city":"Newark",
    "sg:classifiers":[
        {
            "category":"Retail",
            "subcategory":"Auto Repair",
            "type":"Services"
        }
    ],
    "sg:phone":"+1 973 416 1827",
    "sg:postcode":"07108",
    "sg:province":"NJ",
    "sg:tags":[
        "body",
        "automobile",
        "painting"
    ],
    "wof:name":"Capital Sales Auto Ctr",
    "wof:placetype":"venue"
},
  "geometry": {"coordinates":[-74.213661,40.726646],"type":"Point"}
}