{
  "type": "Feature",
  "properties": {
    "addr:full":"87 Berkshire Pl Irvington NJ 07111",
    "addr:housenumber":"87",
    "addr:postcode":"07111",
    "addr:street":"Berkshire Pl",
    "iso:country":"US",
    "sg:address":"87 Berkshire Pl",
    "sg:city":"Irvington",
    "sg:classifiers":[
        {
            "category":"Wholesale",
            "subcategory":"Electrical",
            "type":"Manufacturing & Wholesale Goods"
        }
    ],
    "sg:phone":"+1 973 373 1526",
    "sg:postcode":"07111",
    "sg:province":"NJ",
    "sg:tags":[
        "equipment"
    ],
    "wof:name":"Offline Electrical Mtc",
    "wof:placetype":"venue"
},
  "geometry": {"coordinates":[-74.231492,40.715727],"type":"Point"}
}