{
  "type": "Feature",
  "properties": {
    "iso:country":"US",
    "sg:address":"969 Belleville Tpke",
    "sg:city":"Kearny",
    "sg:classifiers":[
        {
            "category":"Freight",
            "type":"Transportation"
        }
    ],
    "sg:phone":"+1 713 673 2288",
    "sg:postcode":"07032",
    "sg:province":"NJ",
    "sg:tags":[
        "general"
    ],
    "wof:name":"Integrated Freight Houston",
    "wof:placetype":"venue"
},
  "geometry": {"coordinates":[-74.108085,40.753946],"type":"Point"}
}