{
  "type": "Feature",
  "properties": {
    "iso:country":"US",
    "sg:address":"3 Princeton Hightstown Rd",
    "sg:city":"Princeton Jct",
    "sg:classifiers":[
        {
            "category":"Banks & Credit Unions",
            "subcategory":"Investment Brokerage",
            "type":"Services"
        }
    ],
    "sg:phone":"+1 609 936 1119",
    "sg:postcode":"08550",
    "sg:province":"NJ",
    "sg:tags":[
        "banker"
    ],
    "wof:name":"Weinstock Management Group Inc",
    "wof:placetype":"venue"
},
  "geometry": {"coordinates":[-74.620627,40.302214],"type":"Point"}
}