{
  "type": "Feature",
  "properties": {
    "addr:full":"71 Holland Rd Sussex NJ 07461",
    "addr:housenumber":"71",
    "addr:postcode":"07461",
    "addr:street":"Holland Rd",
    "iso:country":"US",
    "sg:address":"71 Holland Rd",
    "sg:city":"Sussex",
    "sg:classifiers":[
        {
            "category":"Professional",
            "subcategory":"Engineering",
            "type":"Services"
        }
    ],
    "sg:phone":"+1 973 875 6408",
    "sg:postcode":"07461",
    "sg:province":"NJ",
    "sg:tags":[
        "ventilating",
        "heating",
        "engineer"
    ],
    "wof:name":"Dolan Associates",
    "wof:placetype":"venue"
},
  "geometry": {"coordinates":[-74.67165,41.211005],"type":"Point"}
}