{
  "type": "Feature",
  "properties": {
    "iso:country":"US",
    "sg:address":"245 Mounts Mills Rd",
    "sg:city":"Monroe Township",
    "sg:classifiers":[
        {
            "category":"Professional",
            "type":"Services"
        }
    ],
    "sg:phone":"+1   ",
    "sg:postcode":"08831",
    "sg:province":"NJ",
    "wof:name":"AGS Rebuilding",
    "wof:placetype":"venue"
},
  "geometry": {"coordinates":[-74.39203500000001,40.328779],"type":"Point"}
}