{
  "type": "Feature",
  "properties": {
    "iso:country":"US",
    "sg:address":"819 New Rd",
    "sg:city":"Northfield",
    "sg:classifiers":[
        {
            "category":"Professional",
            "subcategory":"Lawyer & Legal Services",
            "type":"Services"
        }
    ],
    "sg:phone":"+1 609 601 0900",
    "sg:postcode":"08225",
    "sg:province":"NJ",
    "sg:tags":[
        "attorney"
    ],
    "wof:name":"Holtzman & Mc Clain",
    "wof:placetype":"venue"
},
  "geometry": {"coordinates":[-74.550721,39.377912],"type":"Point"}
}