{
  "type": "Feature",
  "properties": {
    "iso:country":"US",
    "sg:address":"457B S Washington Ave",
    "sg:city":"Bergenfield",
    "sg:classifiers":[
        {
            "category":"Building & Trades",
            "subcategory":"Plumbing",
            "type":"Services"
        },
        {
            "category":"Home & Garden",
            "subcategory":"Hardware",
            "type":"Retail Goods"
        }
    ],
    "sg:phone":"+1 201 384 5505",
    "sg:postcode":"07621",
    "sg:province":"NJ",
    "sg:tags":[
        "filtration",
        "supply",
        "work",
        "purification",
        "water",
        "equipment"
    ],
    "wof:name":"Water People",
    "wof:placetype":"venue"
},
  "geometry": {"coordinates":[-73.99756600000001,40.91337],"type":"Point"}
}