{
  "type": "Feature",
  "properties": {
    "iso:country":"US",
    "sg:address":"207 Bellevue Ave",
    "sg:city":"Montclair",
    "sg:classifiers":[
        {
            "category":"Health Services",
            "subcategory":"Doctor",
            "type":"Services"
        },
        {
            "category":"Health Services",
            "subcategory":"Clinic",
            "type":"Services"
        }
    ],
    "sg:phone":"+1 973 746 0551",
    "sg:postcode":"07043",
    "sg:province":"NJ",
    "sg:tags":[
        "counseling",
        "mental"
    ],
    "wof:name":"Snyder Margaret T Ph D",
    "wof:placetype":"venue"
},
  "geometry": {"coordinates":[-74.206299,40.840801],"type":"Point"}
}