{
  "type": "Feature",
  "properties": {
    "addr:full":"1205 Deacon Rd Hainesport NJ 08036",
    "addr:housenumber":"1205",
    "addr:postcode":"08036",
    "addr:street":"Deacon Rd",
    "iso:country":"US",
    "sg:address":"1205 Deacon Rd",
    "sg:city":"Hainesport",
    "sg:classifiers":[
        {
            "category":"Building & Trades",
            "subcategory":"Electrical",
            "type":"Services"
        }
    ],
    "sg:phone":"+1 609 267 4200",
    "sg:postcode":"08036",
    "sg:province":"NJ",
    "sg:tags":[
        "electric",
        "contractor"
    ],
    "sg:website":"www.stevensonelectric.com",
    "wof:name":"Stevenson Electric",
    "wof:placetype":"venue"
},
  "geometry": {"coordinates":[-74.81640299999999,39.990058],"type":"Point"}
}