{
  "type": "Feature",
  "properties": {
    "iso:country":"US",
    "sg:address":"147 Woodland Ave",
    "sg:city":"Little Ferry",
    "sg:classifiers":[
        {
            "category":"Professional",
            "subcategory":"Computer Services",
            "type":"Services"
        }
    ],
    "sg:phone":"+1   ",
    "sg:postcode":"07643",
    "sg:province":"NJ",
    "sg:tags":[
        "related"
    ],
    "wof:name":"At Computer Consulting Co",
    "wof:placetype":"venue"
},
  "geometry": {"coordinates":[-74.039948,40.854756],"type":"Point"}
}