{
  "type": "Feature",
  "properties": {
    "addr:full":"240 Pearsall Ave Jersey City NJ 07305",
    "addr:housenumber":"240",
    "addr:postcode":"07305",
    "addr:street":"Pearsall Ave",
    "iso:country":"US",
    "sg:address":"240 Pearsall Ave",
    "sg:city":"Jersey City",
    "sg:classifiers":[
        {
            "category":"Professional",
            "type":"Services"
        }
    ],
    "sg:phone":"+1   ",
    "sg:postcode":"07305",
    "sg:province":"NJ",
    "wof:name":"Rascal House II",
    "wof:placetype":"venue"
},
  "geometry": {"coordinates":[-74.09495,40.695334],"type":"Point"}
}