{
  "type": "Feature",
  "properties": {
    "iso:country":"US",
    "sg:address":"618 2nd Ave",
    "sg:city":"Avon By The Sea",
    "sg:classifiers":[
        {
            "category":"Travel",
            "subcategory":"Hotels & Motels",
            "type":"Entertainment"
        }
    ],
    "sg:phone":"+1 732 775 3900",
    "sg:postcode":"07717",
    "sg:province":"NJ",
    "sg:website":"www.norwoodinn.com",
    "wof:name":"Norwood Inn",
    "wof:placetype":"venue"
},
  "geometry": {"coordinates":[-74.013616,40.194168],"type":"Point"}
}