{
  "type": "Feature",
  "properties": {
    "addr:full":"24 North Ave E Cranford NJ 07016",
    "addr:housenumber":"24",
    "addr:postcode":"07016",
    "addr:street":"North Ave E",
    "iso:country":"US",
    "sg:address":"24 North Ave E",
    "sg:city":"Cranford",
    "sg:classifiers":[
        {
            "category":"Restaurant",
            "type":"Food & Drink"
        }
    ],
    "sg:phone":"+1 908 276 3664",
    "sg:postcode":"07016",
    "sg:province":"NJ",
    "sg:tags":[
        "spanish"
    ],
    "wof:name":"Cervantes of Spain",
    "wof:placetype":"venue"
},
  "geometry": {"coordinates":[-74.302673,40.65633],"type":"Point"}
}