{
  "type": "Feature",
  "properties": {
    "iso:country":"US",
    "sg:address":"2520 Autumn Dr",
    "sg:city":"Manasquan",
    "sg:classifiers":[
        {
            "category":"Building & Trades",
            "subcategory":"Construction",
            "type":"Services"
        }
    ],
    "sg:phone":"+1 732 528 6105",
    "sg:postcode":"08736",
    "sg:province":"NJ",
    "sg:tags":[
        "new",
        "home"
    ],
    "wof:name":"DESA Corp",
    "wof:placetype":"venue"
},
  "geometry": {"coordinates":[-74.089055,40.11619],"type":"Point"}
}