{
  "type": "Feature",
  "properties": {
    "addr:full":"5102 State Rte 33 Wall Township NJ 07727",
    "addr:housenumber":"5102",
    "addr:postcode":"07727",
    "addr:street":"State Rte 33 Wall",
    "iso:country":"US",
    "sg:address":"5102 State Rte 33",
    "sg:city":"Wall Township",
    "sg:classifiers":[
        {
            "category":"Home & Garden",
            "subcategory":"Building Materials",
            "type":"Retail Goods"
        }
    ],
    "sg:phone":"+1 732 938 5005",
    "sg:postcode":"07727",
    "sg:province":"NJ",
    "sg:website":"www.marjam.com",
    "wof:name":"Marjam Supply Co",
    "wof:placetype":"venue"
},
  "geometry": {"coordinates":[-74.130996,40.220815],"type":"Point"}
}