{
  "type": "Feature",
  "properties": {
    "addr:full":"2422 Capshaw Rd Forked River NJ 08731",
    "addr:housenumber":"2422",
    "addr:postcode":"08731",
    "addr:street":"Capshaw Rd",
    "iso:country":"US",
    "sg:address":"2422 Capshaw Rd",
    "sg:city":"Forked River",
    "sg:classifiers":[
        {
            "category":"Building & Trades",
            "subcategory":"Plumbing",
            "type":"Services"
        }
    ],
    "sg:phone":"+1 609 971 8540",
    "sg:postcode":"08731",
    "sg:province":"NJ",
    "sg:tags":[
        "contractor"
    ],
    "wof:name":"Mfm Mechanical",
    "wof:placetype":"venue"
},
  "geometry": {"coordinates":[-74.31291,39.892583],"type":"Point"}
}