{
  "type": "Feature",
  "properties": {
    "addr:full":"11 Broadway Fair Lawn NJ 07410",
    "addr:housenumber":"11",
    "addr:postcode":"07410",
    "addr:street":"Broadway",
    "iso:country":"US",
    "sg:address":"11 Broadway",
    "sg:city":"Fair Lawn",
    "sg:classifiers":[
        {
            "category":"Travel",
            "subcategory":"Travel Agent",
            "type":"Entertainment"
        }
    ],
    "sg:phone":"+1 201 791 3100",
    "sg:postcode":"07410",
    "sg:province":"NJ",
    "sg:tags":[
        "agency"
    ],
    "wof:name":"Air & Sea Travel Service",
    "wof:placetype":"venue"
},
  "geometry": {"coordinates":[-74.121326,40.920178],"type":"Point"}
}