{
  "type": "Feature",
  "properties": {
    "iso:country":"US",
    "sg:address":"501 Clubhouse Ct",
    "sg:city":"Union",
    "sg:classifiers":[
        {
            "category":"Real Estate",
            "subcategory":"Real Estate Operator",
            "type":"Services"
        }
    ],
    "sg:phone":"+1 908 687 2839",
    "sg:postcode":"07083",
    "sg:province":"NJ",
    "sg:tags":[
        "condominium"
    ],
    "wof:name":"Pointe At Galloping Hill Guard",
    "wof:placetype":"venue"
},
  "geometry": {"coordinates":[-74.290638,40.688635],"type":"Point"}
}