{
  "type": "Feature",
  "properties": {
    "addr:full":"399 Cook Rd Jackson NJ 08527",
    "addr:housenumber":"399",
    "addr:postcode":"08527",
    "addr:street":"Cook Rd",
    "iso:country":"US",
    "sg:address":"399 Cook Rd",
    "sg:city":"Jackson",
    "sg:classifiers":[
        {
            "category":"Restaurant",
            "type":"Food & Drink"
        }
    ],
    "sg:phone":"+1   ",
    "sg:postcode":"08527",
    "sg:province":"NJ",
    "sg:tags":[
        "eating"
    ],
    "wof:name":"Alashara Enterprises Inc",
    "wof:placetype":"venue"
},
  "geometry": {"coordinates":[-74.296207,40.145082],"type":"Point"}
}