{
  "type": "Feature",
  "properties": {
    "addr:full":"75 Union Ave Garfield NJ 07026",
    "addr:housenumber":"75",
    "addr:postcode":"07026",
    "addr:street":"Union Ave",
    "iso:country":"US",
    "sg:address":"75 Union Ave",
    "sg:city":"Garfield",
    "sg:classifiers":[
        {
            "category":"Building & Trades",
            "subcategory":"Electrical",
            "type":"Services"
        }
    ],
    "sg:phone":"+1 973 772 7598",
    "sg:postcode":"07026",
    "sg:province":"NJ",
    "sg:tags":[
        "electric",
        "contractor"
    ],
    "wof:name":"B & W Electric Corp Inc",
    "wof:placetype":"venue"
},
  "geometry": {"coordinates":[-74.107221,40.884323],"type":"Point"}
}