{
  "type": "Feature",
  "properties": {
    "addr:full":"263 State Rte 36 Middletown NJ 07748",
    "addr:housenumber":"263",
    "addr:postcode":"07748",
    "addr:street":"State Rte 36",
    "iso:country":"US",
    "sg:address":"263 State Rte 36",
    "sg:city":"Middletown",
    "sg:classifiers":[
        {
            "category":"Professional",
            "subcategory":"Business Services",
            "type":"Services"
        }
    ],
    "sg:phone":"+1   ",
    "sg:postcode":"07748",
    "sg:province":"NJ",
    "wof:name":"Alton Associates LLC",
    "wof:placetype":"venue"
},
  "geometry": {"coordinates":[-74.11541200000001,40.433009],"type":"Point"}
}