{
  "type": "Feature",
  "properties": {
    "iso:country":"US",
    "sg:address":"651 Kapkowski Rd",
    "sg:city":"Elizabeth",
    "sg:classifiers":[
        {
            "category":"Utilities",
            "subcategory":"Mobile Phone",
            "type":"Services"
        }
    ],
    "sg:phone":"+1 908 659 1699",
    "sg:postcode":"07201",
    "sg:province":"NJ",
    "sg:tags":[
        "communication",
        "radiotelephone"
    ],
    "wof:name":"Verizon Wireless Jersey Garden",
    "wof:placetype":"venue"
},
  "geometry": {"coordinates":[-74.174531,40.662922],"type":"Point"}
}