{
  "type": "Feature",
  "properties": {
    "iso:country":"US",
    "sg:address":"510 Williamstown Rd Unit C",
    "sg:city":"Sicklerville",
    "sg:classifiers":[
        {
            "category":"Banks & Credit Unions",
            "subcategory":"Financial Services",
            "type":"Services"
        }
    ],
    "sg:phone":"+1 856 740 4912",
    "sg:postcode":"08081",
    "sg:province":"NJ",
    "sg:tags":[
        "advising"
    ],
    "sg:website":"www.taxroute.com",
    "wof:name":"TaxRoute",
    "wof:placetype":"venue"
},
  "geometry": {"coordinates":[-74.9678,39.717463],"type":"Point"}
}