{
  "type": "Feature",
  "properties": {
    "iso:country":"US",
    "sg:address":"162 Lodi St",
    "sg:city":"Hackensack",
    "sg:classifiers":[
        {
            "category":"Wholesale",
            "subcategory":"Stationery",
            "type":"Manufacturing & Wholesale Goods"
        }
    ],
    "sg:phone":"+1 201 336 3200",
    "sg:postcode":"07601",
    "sg:province":"NJ",
    "sg:tags":[
        "brochure",
        "advertising"
    ],
    "wof:name":"F M S Graphics",
    "wof:placetype":"venue"
},
  "geometry": {"coordinates":[-74.05022099999999,40.874442],"type":"Point"}
}