{
  "type": "Feature",
  "properties": {
    "iso:country":"US",
    "sg:address":"84 Winding Wood Dr",
    "sg:city":"Sayreville",
    "sg:classifiers":[
        {
            "category":"Manufacturing",
            "subcategory":"Toys & Sporting Goods",
            "type":"Manufacturing & Wholesale Goods"
        }
    ],
    "sg:phone":"+1 732 967 1709",
    "sg:postcode":"08872",
    "sg:province":"NJ",
    "sg:tags":[
        "mfg"
    ],
    "wof:name":"Royal Trading U S A Inc",
    "wof:placetype":"venue"
},
  "geometry": {"coordinates":[-74.35502,40.428269],"type":"Point"}
}