{
  "type": "Feature",
  "properties": {
    "addr:full":"513 W Mount Pleasant Ave Ste 122 Livingston NJ 07039",
    "addr:housenumber":"513",
    "addr:postcode":"07039",
    "addr:street":"W Mount Pleasant Ave Ste 122",
    "iso:country":"US",
    "sg:address":"513 W Mount Pleasant Ave Ste 122",
    "sg:city":"Livingston",
    "sg:classifiers":[
        {
            "category":"Building & Trades",
            "subcategory":"Construction",
            "type":"Services"
        }
    ],
    "sg:phone":"+1 973 535 0502",
    "sg:postcode":"07039",
    "sg:province":"NJ",
    "sg:tags":[
        "contractor"
    ],
    "wof:name":"Precision General Contractors",
    "wof:placetype":"venue"
},
  "geometry": {"coordinates":[-74.347964,40.796588],"type":"Point"}
}