{
  "type": "Feature",
  "properties": {
    "iso:country":"US",
    "sg:address":"71 Union Ave",
    "sg:city":"Rutherford",
    "sg:classifiers":[
        {
            "category":"Health Services",
            "subcategory":"Doctor",
            "type":"Services"
        }
    ],
    "sg:phone":"+1 201 460 8600",
    "sg:postcode":"07070",
    "sg:province":"NJ",
    "sg:tags":[
        "physician",
        "surgeon"
    ],
    "wof:name":"Rosenburg & Basralan",
    "wof:placetype":"venue"
},
  "geometry": {"coordinates":[-74.104321,40.830948],"type":"Point"}
}