{
  "type": "Feature",
  "properties": {
    "addr:full":"1217 7th St North Bergen NJ 07047",
    "addr:housenumber":"1217",
    "addr:postcode":"07047",
    "addr:street":"7Th St",
    "iso:country":"US",
    "sg:address":"1217 7th St",
    "sg:city":"North Bergen",
    "sg:classifiers":[
        {
            "category":"Professional",
            "subcategory":"Management & Consulting",
            "type":"Services"
        }
    ],
    "sg:phone":"+1 201 988 0178",
    "sg:postcode":"07047",
    "sg:province":"NJ",
    "sg:tags":[
        "business"
    ],
    "wof:name":"Maes & Assoc",
    "wof:placetype":"venue"
},
  "geometry": {"coordinates":[-74.046774,40.759157],"type":"Point"}
}