{
  "type": "Feature",
  "properties": {
    "iso:country":"US",
    "sg:address":"51 South St",
    "sg:city":"Morristown",
    "sg:classifiers":[
        {
            "category":"Arts & Performance",
            "subcategory":"Arts Center",
            "type":"Entertainment"
        }
    ],
    "sg:phone":"+1 973 538 6285",
    "sg:postcode":"07960",
    "sg:province":"NJ",
    "sg:tags":[
        "performing"
    ],
    "sg:website":"www.worthtyrrellstudios.com",
    "wof:name":"Worth-Tyrrell Studios School of Performing Arts",
    "wof:placetype":"venue"
},
  "geometry": {"coordinates":[-74.479401,40.794899],"type":"Point"}
}