{
  "type": "Feature",
  "properties": {
    "iso:country":"US",
    "sg:address":"11 Robin Rd",
    "sg:city":"Rumson",
    "sg:classifiers":[
        {
            "category":"Building & Trades",
            "subcategory":"Construction",
            "type":"Services"
        }
    ],
    "sg:phone":"+1 732 345 8588",
    "sg:postcode":"07760",
    "sg:province":"NJ",
    "sg:tags":[
        "resurfacing",
        "laying",
        "refinishing",
        "floor"
    ],
    "wof:name":"Clarke Wood Flooring",
    "wof:placetype":"venue"
},
  "geometry": {"coordinates":[-73.995047,40.368394],"type":"Point"}
}