{
  "type": "Feature",
  "properties": {
    "addr:full":"501 Cooper St Collingswood NJ 08108",
    "addr:housenumber":"501",
    "addr:postcode":"08108",
    "addr:street":"Cooper St",
    "iso:country":"US",
    "sg:address":"501 Cooper St",
    "sg:city":"Collingswood",
    "sg:classifiers":[
        {
            "category":"Building & Trades",
            "subcategory":"Construction",
            "type":"Services"
        }
    ],
    "sg:phone":"+1 856 854 5225",
    "sg:postcode":"08108",
    "sg:province":"NJ",
    "sg:tags":[
        "hanging",
        "wallpaper",
        "contractor"
    ],
    "wof:name":"Seidman Paperhanging",
    "wof:placetype":"venue"
},
  "geometry": {"coordinates":[-75.047411,39.916703],"type":"Point"}
}