{
  "type": "Feature",
  "properties": {
    "iso:country":"US",
    "sg:address":"17 Mandeville Ave",
    "sg:city":"Pequannock",
    "sg:classifiers":[
        {
            "category":"Building & Trades",
            "subcategory":"Plumbing",
            "type":"Services"
        }
    ],
    "sg:phone":"+1 973 872 0567",
    "sg:postcode":"07440",
    "sg:province":"NJ",
    "wof:name":"Premier Plumbing and Heating",
    "wof:placetype":"venue"
},
  "geometry": {"coordinates":[-74.29360200000001,40.945499],"type":"Point"}
}