{
  "type": "Feature",
  "properties": {
    "addr:full":"87 Fairfield Rd Fairfield NJ 07004",
    "addr:housenumber":"87",
    "addr:postcode":"07004",
    "addr:street":"Fairfield Rd",
    "iso:country":"US",
    "sg:address":"87 Fairfield Rd",
    "sg:city":"Fairfield",
    "sg:classifiers":[
        {
            "category":"Utilities",
            "subcategory":"Telephone",
            "type":"Services"
        }
    ],
    "sg:phone":"+1 973 244 9909",
    "sg:postcode":"07004",
    "sg:province":"NJ",
    "sg:tags":[
        "company"
    ],
    "wof:name":"CTCI",
    "wof:placetype":"venue"
},
  "geometry": {"coordinates":[-74.30116200000001,40.872774],"type":"Point"}
}