{
  "type": "Feature",
  "properties": {
    "iso:country":"US",
    "sg:address":"465 Court House South Dennis Rd",
    "sg:city":"Cape May Ct Hse",
    "sg:classifiers":[
        {
            "category":"Professional",
            "type":"Services"
        }
    ],
    "sg:phone":"+1 609 465 8117",
    "sg:postcode":"08210",
    "sg:province":"NJ",
    "wof:name":"Kismet Studio",
    "wof:placetype":"venue"
},
  "geometry": {"coordinates":[-74.821106,39.118555],"type":"Point"}
}