{
  "type": "Feature",
  "properties": {
    "iso:country":"US",
    "sg:address":"4 York Ave",
    "sg:city":"West Caldwell",
    "sg:phone":"+1 973 227 8882",
    "sg:postcode":"07006",
    "sg:province":"NJ",
    "sg:tags":[
        "scale"
    ],
    "wof:name":"Easy Weigh USA Inc",
    "wof:placetype":"venue"
},
  "geometry": {"coordinates":[-74.282904,40.861687],"type":"Point"}
}