{
  "type": "Feature",
  "properties": {
    "iso:country":"US",
    "sg:address":"1030 Saint Georges Ave Ste 205",
    "sg:city":"Avenel",
    "sg:classifiers":[
        {
            "category":"Government",
            "subcategory":"Office",
            "type":"Public Place"
        }
    ],
    "sg:phone":"+1 732 750 3270",
    "sg:postcode":"07001",
    "sg:province":"NJ",
    "sg:website":"http://www.dioshday.com",
    "wof:name":"Avenel Area Office",
    "wof:placetype":"venue"
},
  "geometry": {"coordinates":[-74.29402,40.574081],"type":"Point"}
}