{
  "type": "Feature",
  "properties": {
    "addr:full":"1275 Bloomfield Ave Fairfield NJ 07004",
    "addr:housenumber":"1275",
    "addr:postcode":"07004",
    "addr:street":"Bloomfield Ave",
    "iso:country":"US",
    "sg:address":"1275 Bloomfield Ave",
    "sg:city":"Fairfield",
    "sg:classifiers":[
        {
            "category":"Wholesale",
            "subcategory":"Home Furnishings",
            "type":"Manufacturing & Wholesale Goods"
        }
    ],
    "sg:phone":"+1 973 808 5577",
    "sg:postcode":"07004",
    "sg:province":"NJ",
    "sg:tags":[
        "picture",
        "frame"
    ],
    "wof:name":"Picture Framing Warehouse",
    "wof:placetype":"venue"
},
  "geometry": {"coordinates":[-74.318907,40.858492],"type":"Point"}
}