{
  "type": "Feature",
  "properties": {
    "addr:full":"106 Watchung Ave Plainfield NJ 07060",
    "addr:housenumber":"106",
    "addr:postcode":"07060",
    "addr:street":"Watchung Ave",
    "iso:country":"US",
    "sg:address":"106 Watchung Ave",
    "sg:city":"Plainfield",
    "sg:classifiers":[
        {
            "category":"Real Estate",
            "subcategory":"Real Estate Agent",
            "type":"Services"
        }
    ],
    "sg:phone":"+1   ",
    "sg:postcode":"07060",
    "sg:province":"NJ",
    "wof:name":"A-Supreme Realty",
    "wof:placetype":"venue"
},
  "geometry": {"coordinates":[-74.426328,40.622384],"type":"Point"}
}