{
  "type": "Feature",
  "properties": {
    "iso:country":"US",
    "sg:address":"10 Jennings Rd",
    "sg:city":"Medford",
    "sg:classifiers":[
        {
            "category":"Social Services",
            "subcategory":"Child Care",
            "type":"Services"
        }
    ],
    "sg:phone":"+1 609 714 8686",
    "sg:postcode":"08055",
    "sg:province":"NJ",
    "wof:name":"Goddard School",
    "wof:placetype":"venue"
},
  "geometry": {"coordinates":[-74.835855,39.902567],"type":"Point"}
}