{
  "type": "Feature",
  "properties": {
    "addr:full":"311 New Albany Rd Moorestown NJ 08057",
    "addr:housenumber":"311",
    "addr:postcode":"08057",
    "addr:street":"New Albany Rd",
    "iso:country":"US",
    "sg:address":"311 New Albany Rd",
    "sg:city":"Moorestown",
    "sg:classifiers":[
        {
            "category":"Manufacturing",
            "subcategory":"Electronics",
            "type":"Manufacturing & Wholesale Goods"
        },
        {
            "category":"Wholesale",
            "subcategory":"Electrical",
            "type":"Manufacturing & Wholesale Goods"
        }
    ],
    "sg:phone":"+1 856 234 4200",
    "sg:postcode":"08057",
    "sg:province":"NJ",
    "sg:tags":[
        "equipment",
        "parts",
        "electronic",
        "supply"
    ],
    "sg:website":"www.marlac.com",
    "wof:name":"Marlac Electronics Inc",
    "wof:placetype":"venue"
},
  "geometry": {"coordinates":[-74.974655,39.964096],"type":"Point"}
}