{
  "type": "Feature",
  "properties": {
    "iso:country":"US",
    "sg:address":"101 US Hwy 46",
    "sg:city":"Saddle Brook",
    "sg:classifiers":[
        {
            "category":"Shopping",
            "subcategory":"Bicycles & Sporting Goods",
            "type":"Retail Goods"
        }
    ],
    "sg:phone":"+1 201 843 7788",
    "sg:postcode":"07663",
    "sg:province":"NJ",
    "sg:tags":[
        "equipment",
        "archery",
        "supply"
    ],
    "wof:name":"Targeteers Sporting Goods",
    "wof:placetype":"venue"
},
  "geometry": {"coordinates":[-74.09267800000001,40.887454],"type":"Point"}
}