{
  "type": "Feature",
  "properties": {
    "addr:full":"82 E Allendale Rd Saddle River NJ 07458",
    "addr:housenumber":"82",
    "addr:postcode":"07458",
    "addr:street":"E Allendale Rd",
    "iso:country":"US",
    "sg:address":"82 E Allendale Rd",
    "sg:city":"Saddle River",
    "sg:classifiers":[
        {
            "category":"Banks & Credit Unions",
            "subcategory":"Investment Brokerage",
            "type":"Services"
        }
    ],
    "sg:phone":"+1 201 236 8045",
    "sg:postcode":"07458",
    "sg:province":"NJ",
    "sg:tags":[
        "advisory",
        "financial"
    ],
    "wof:name":"Glass Capital Management",
    "wof:placetype":"venue"
},
  "geometry": {"coordinates":[-74.095157,41.030913],"type":"Point"}
}