{
  "type": "Feature",
  "properties": {
    "addr:full":"80 Main St West Orange NJ 07052",
    "addr:housenumber":"80",
    "addr:postcode":"07052",
    "addr:street":"Main St",
    "iso:country":"US",
    "sg:address":"80 Main St",
    "sg:city":"West Orange",
    "sg:classifiers":[
        {
            "category":"Professional",
            "subcategory":"Lawyer & Legal Services",
            "type":"Services"
        }
    ],
    "sg:phone":"+1 973 669 5880",
    "sg:postcode":"07052",
    "sg:province":"NJ",
    "wof:name":"Rodner Judith E Attorney At Law",
    "wof:placetype":"venue"
},
  "geometry": {"coordinates":[-74.23870100000001,40.778702],"type":"Point"}
}