{
  "type": "Feature",
  "properties": {
    "addr:full":"66 Main St Andover NJ 07821",
    "addr:housenumber":"66",
    "addr:postcode":"07821",
    "addr:street":"Main St",
    "iso:country":"US",
    "sg:address":"66 Main St",
    "sg:city":"Andover",
    "sg:classifiers":[
        {
            "category":"Building & Trades",
            "subcategory":"Construction",
            "type":"Services"
        }
    ],
    "sg:phone":"+1 973 786 6705",
    "sg:postcode":"07821",
    "sg:province":"NJ",
    "sg:tags":[
        "contractor"
    ],
    "wof:name":"Schifano Construction",
    "wof:placetype":"venue"
},
  "geometry": {"coordinates":[-74.738681,40.978763],"type":"Point"}
}