{
  "type": "Feature",
  "properties": {
    "addr:full":"64 Main St Califon NJ 07830",
    "addr:housenumber":"64",
    "addr:postcode":"07830",
    "addr:street":"Main St",
    "iso:country":"US",
    "sg:address":"64 Main St",
    "sg:city":"Califon",
    "sg:classifiers":[
        {
            "category":"Building & Trades",
            "subcategory":"Construction",
            "type":"Services"
        }
    ],
    "sg:phone":"+1 908 832 0531",
    "sg:postcode":"07830",
    "sg:province":"NJ",
    "wof:name":"Aegis Building Systems",
    "wof:placetype":"venue"
},
  "geometry": {"coordinates":[-74.834574,40.718731],"type":"Point"}
}