{
  "type": "Feature",
  "properties": {
    "iso:country":"US",
    "sg:address":"121 Helen St",
    "sg:city":"South Plainfield",
    "sg:classifiers":[
        {
            "category":"Manufacturing",
            "subcategory":"Paper Products",
            "type":"Manufacturing & Wholesale Goods"
        }
    ],
    "sg:phone":"+1 908 412 8889",
    "sg:postcode":"07080",
    "sg:province":"NJ",
    "wof:name":"Golden West Paper Converting",
    "wof:placetype":"venue"
},
  "geometry": {"coordinates":[-74.413331,40.556601],"type":"Point"}
}