{
  "type": "Feature",
  "properties": {
    "iso:country":"US",
    "sg:address":"48 N 2nd St",
    "sg:city":"Paterson",
    "sg:classifiers":[
        {
            "category":"Home & Garden",
            "subcategory":"Building Materials",
            "type":"Retail Goods"
        }
    ],
    "sg:phone":"+1 973 720 1200",
    "sg:postcode":"07522",
    "sg:province":"NJ",
    "sg:tags":[
        "equipment",
        "fixture",
        "lighting"
    ],
    "wof:name":"Vision Lighting",
    "wof:placetype":"venue"
},
  "geometry": {"coordinates":[-74.1707,40.928001],"type":"Point"}
}