{
  "type": "Feature",
  "properties": {
    "iso:country":"US",
    "sg:address":"15 1st St",
    "sg:city":"Bloomingdale",
    "sg:classifiers":[
        {
            "category":"Retail",
            "subcategory":"Auto Repair",
            "type":"Services"
        }
    ],
    "sg:phone":"+1 973 838 9180",
    "sg:postcode":"07403",
    "sg:province":"NJ",
    "sg:tags":[
        "automotive"
    ],
    "wof:name":"Bills Service LLC",
    "wof:placetype":"venue"
},
  "geometry": {"coordinates":[-74.340816,41.007445],"type":"Point"}
}