{
  "type": "Feature",
  "properties": {
    "iso:country":"US",
    "sg:address":"2100 Summer Hill Rd",
    "sg:city":"Wayne",
    "sg:classifiers":[
        {
            "category":"Personal",
            "subcategory":"Beauty Salon",
            "type":"Services"
        }
    ],
    "sg:phone":"+1 973 628 9996",
    "sg:postcode":"07470",
    "sg:province":"NJ",
    "sg:tags":[
        "shop"
    ],
    "wof:name":"Summer Hill Salon",
    "wof:placetype":"venue"
},
  "geometry": {"coordinates":[-74.239908,40.977598],"type":"Point"}
}