{
  "type": "Feature",
  "properties": {
    "iso:country":"US",
    "sg:address":"70 Spruce Mill Ln",
    "sg:city":"Scotch Plains",
    "sg:classifiers":[
        {
            "category":"Organizations",
            "subcategory":"Religious Organization",
            "type":"Services"
        }
    ],
    "sg:phone":"+1 908 233 0363",
    "sg:postcode":"07076",
    "sg:province":"NJ",
    "sg:tags":[
        "church"
    ],
    "wof:name":"Agape Presbyterian Church",
    "wof:placetype":"venue"
},
  "geometry": {"coordinates":[-74.333737,40.623905],"type":"Point"}
}