{
  "type": "Feature",
  "properties": {
    "addr:full":"22 Elm Ridge Rd Pennington NJ 08534",
    "addr:housenumber":"22",
    "addr:postcode":"08534",
    "addr:street":"Elm Ridge Rd",
    "iso:country":"US",
    "sg:address":"22 Elm Ridge Rd",
    "sg:city":"Pennington",
    "sg:classifiers":[
        {
            "category":"Professional",
            "subcategory":"Management & Consulting",
            "type":"Services"
        }
    ],
    "sg:phone":"+1   ",
    "sg:postcode":"08534",
    "sg:province":"NJ",
    "wof:name":"Organization Change Resources",
    "wof:placetype":"venue"
},
  "geometry": {"coordinates":[-74.73801400000001,40.342249],"type":"Point"}
}