{
  "type": "Feature",
  "properties": {
    "addr:full":"311 State Rte 73 West Berlin NJ 08091",
    "addr:housenumber":"311",
    "addr:postcode":"08091",
    "addr:street":"State Rte 73",
    "iso:country":"US",
    "sg:address":"311 State Rte 73",
    "sg:city":"West Berlin",
    "sg:classifiers":[
        {
            "category":"Travel",
            "subcategory":"Hotels & Motels",
            "type":"Entertainment"
        }
    ],
    "sg:phone":"+1   ",
    "sg:postcode":"08091",
    "sg:province":"NJ",
    "sg:tags":[
        "operation"
    ],
    "wof:name":"Holiday Inn",
    "wof:placetype":"venue"
},
  "geometry": {"coordinates":[-74.930758,39.810711],"type":"Point"}
}