{
  "type": "Feature",
  "properties": {
    "addr:full":"16 Dempsey Ave Edgewater NJ 07020",
    "addr:housenumber":"16",
    "addr:postcode":"07020",
    "addr:street":"Dempsey Ave",
    "iso:country":"US",
    "sg:address":"16 Dempsey Ave",
    "sg:city":"Edgewater",
    "sg:classifiers":[
        {
            "category":"Wholesale",
            "subcategory":"Apparel",
            "type":"Manufacturing & Wholesale Goods"
        }
    ],
    "sg:phone":"+1 201 969 1941",
    "sg:postcode":"07020",
    "sg:province":"NJ",
    "sg:tags":[
        "piece"
    ],
    "wof:name":"Gufu Corp",
    "wof:placetype":"venue"
},
  "geometry": {"coordinates":[-73.974052,40.82728],"type":"Point"}
}