{
  "type": "Feature",
  "properties": {
    "addr:full":"741 Corkery Ln Williamstown NJ 08094",
    "addr:housenumber":"741",
    "addr:postcode":"08094",
    "addr:street":"Corkery Ln",
    "iso:country":"US",
    "sg:address":"741 Corkery Ln",
    "sg:city":"Williamstown",
    "sg:classifiers":[
        {
            "category":"Personal",
            "subcategory":"Tanning Parlor",
            "type":"Services"
        }
    ],
    "sg:phone":"+1 856 740 1414",
    "sg:postcode":"08094",
    "sg:province":"NJ",
    "sg:website":"www.capritans.com",
    "wof:name":"Capri Tans & Spa",
    "wof:placetype":"venue"
},
  "geometry": {"coordinates":[-74.984302,39.668773],"type":"Point"}
}