{
  "type": "Feature",
  "properties": {
    "addr:full":"229 Berger St Wood Ridge NJ 07075",
    "addr:housenumber":"229",
    "addr:postcode":"07075",
    "addr:street":"Berger St",
    "iso:country":"US",
    "sg:address":"229 Berger St",
    "sg:city":"Wood Ridge",
    "sg:classifiers":[
        {
            "category":"Freight",
            "type":"Transportation"
        },
        {
            "category":"Utilities",
            "subcategory":"Refuse",
            "type":"Services"
        }
    ],
    "sg:phone":"+1 201 507 0049",
    "sg:postcode":"07075",
    "sg:province":"NJ",
    "sg:tags":[
        "consulting",
        "business",
        "garbage",
        "collection",
        "trucking",
        "operator",
        "local"
    ],
    "wof:name":"S & L Zeppetelli Inc",
    "wof:placetype":"venue"
},
  "geometry": {"coordinates":[-74.076886,40.844166],"type":"Point"}
}