{
  "type": "Feature",
  "properties": {
    "addr:full":"65 Greens Way Blackwood NJ 08012",
    "addr:housenumber":"65",
    "addr:postcode":"08012",
    "addr:street":"Greens Way",
    "iso:country":"US",
    "sg:address":"65 Greens Way",
    "sg:city":"Blackwood",
    "sg:classifiers":[
        {
            "category":"Manufacturing",
            "subcategory":"Printing",
            "type":"Manufacturing & Wholesale Goods"
        }
    ],
    "sg:phone":"+1 856 374 1512",
    "sg:postcode":"08012",
    "sg:province":"NJ",
    "sg:tags":[
        "publishing"
    ],
    "wof:name":"Victorian Treasures",
    "wof:placetype":"venue"
},
  "geometry": {"coordinates":[-75.059516,39.820632],"type":"Point"}
}