{
  "type": "Feature",
  "properties": {
    "iso:country":"US",
    "sg:address":"216 Stonehenge Dr",
    "sg:city":"Phillipsburg",
    "sg:classifiers":[
        {
            "category":"Professional",
            "subcategory":"Computer Services",
            "type":"Services"
        }
    ],
    "sg:phone":"+1   ",
    "sg:postcode":"08865",
    "sg:province":"NJ",
    "sg:tags":[
        "related"
    ],
    "wof:name":"Celero LLC",
    "wof:placetype":"venue"
},
  "geometry": {"coordinates":[-75.161654,40.710883],"type":"Point"}
}