{
  "type": "Feature",
  "properties": {
    "addr:full":"25 Pierce Ave Jersey City NJ 07307",
    "addr:housenumber":"25",
    "addr:postcode":"07307",
    "addr:street":"Pierce Ave",
    "iso:country":"US",
    "sg:address":"25 Pierce Ave",
    "sg:city":"Jersey City",
    "sg:classifiers":[
        {
            "category":"Retail",
            "subcategory":"Car Wash",
            "type":"Services"
        }
    ],
    "sg:phone":"+1 201 792 6806",
    "sg:postcode":"07307",
    "sg:province":"NJ",
    "sg:tags":[
        "carwash"
    ],
    "wof:name":"Mobile Fleet Wash of Jers",
    "wof:placetype":"venue"
},
  "geometry": {"coordinates":[-74.05027,40.751455],"type":"Point"}
}