{
  "type": "Feature",
  "properties": {
    "addr:full":"261 River Dr Passaic NJ 07055",
    "addr:housenumber":"261",
    "addr:postcode":"07055",
    "addr:street":"River Dr",
    "iso:country":"US",
    "sg:address":"261 River Dr",
    "sg:city":"Passaic",
    "sg:classifiers":[
        {
            "category":"Wholesale",
            "subcategory":"Durable Goods & Equipment",
            "type":"Manufacturing & Wholesale Goods"
        }
    ],
    "sg:phone":"+1 973 458 0096",
    "sg:postcode":"07055",
    "sg:province":"NJ",
    "sg:tags":[
        "importer"
    ],
    "wof:name":"E & K Success Import Export",
    "wof:placetype":"venue"
},
  "geometry": {"coordinates":[-74.121138,40.851816],"type":"Point"}
}