{
  "type": "Feature",
  "properties": {
    "iso:country":"US",
    "sg:address":"170 Kinnelon Rd",
    "sg:city":"Butler",
    "sg:classifiers":[
        {
            "category":"Manufacturing",
            "subcategory":"Printing",
            "type":"Manufacturing & Wholesale Goods"
        }
    ],
    "sg:phone":"+1 973 838 6544",
    "sg:postcode":"07405",
    "sg:province":"NJ",
    "sg:tags":[
        "typesetter"
    ],
    "wof:name":"Typen Graphics Inc",
    "wof:placetype":"venue"
},
  "geometry": {"coordinates":[-74.384738,40.989068],"type":"Point"}
}