{
  "type": "Feature",
  "properties": {
    "addr:full":"1825 US Hwy 130 North Brunswick NJ 08902",
    "addr:housenumber":"1825",
    "addr:postcode":"08902",
    "addr:street":"Us Hwy 130",
    "iso:country":"US",
    "sg:address":"1825 US Hwy 130",
    "sg:city":"North Brunswick",
    "sg:classifiers":[
        {
            "category":"Sports & Exercise",
            "subcategory":"Gym",
            "type":"Entertainment"
        }
    ],
    "sg:phone":"+1 732 422 8200",
    "sg:postcode":"08902",
    "sg:province":"NJ",
    "sg:tags":[
        "club",
        "gymnasium",
        "health",
        "fitness",
        "studio",
        "physical"
    ],
    "wof:name":"Curves For Women",
    "wof:placetype":"venue"
},
  "geometry": {"coordinates":[-74.47787099999999,40.440407],"type":"Point"}
}