{
  "type": "Feature",
  "properties": {
    "addr:full":"219 Berlin Rd Cherry Hill NJ 08034",
    "addr:housenumber":"219",
    "addr:postcode":"08034",
    "addr:street":"Berlin Rd",
    "iso:country":"US",
    "sg:address":"219 Berlin Rd",
    "sg:city":"Cherry Hill",
    "sg:classifiers":[
        {
            "category":"Restaurant",
            "type":"Food & Drink"
        }
    ],
    "sg:phone":"+1 856 795 0188",
    "sg:postcode":"08034",
    "sg:province":"NJ",
    "sg:tags":[
        "chinese"
    ],
    "wof:name":"Chrysanthemum Contemporary Chinese Cuisine",
    "wof:placetype":"venue"
},
  "geometry": {"coordinates":[-75.020606,39.891679],"type":"Point"}
}