{
  "type": "Feature",
  "properties": {
    "addr:full":"2118 Windrow Dr Princeton NJ 08540",
    "addr:housenumber":"2118",
    "addr:postcode":"08540",
    "addr:street":"Windrow Dr",
    "iso:country":"US",
    "sg:address":"2118 Windrow Dr",
    "sg:city":"Princeton",
    "sg:classifiers":[
        {
            "category":"Organizations",
            "subcategory":"Religious Organization",
            "type":"Services"
        }
    ],
    "sg:phone":"+1 609 919 9459",
    "sg:postcode":"08540",
    "sg:province":"NJ",
    "sg:tags":[
        "clergy"
    ],
    "wof:name":"R S Armstrong",
    "wof:placetype":"venue"
},
  "geometry": {"coordinates":[-74.625159,40.381332],"type":"Point"}
}