{
  "type": "Feature",
  "properties": {
    "addr:full":"699 Wyckoff Ave Wyckoff NJ 07481",
    "addr:housenumber":"699",
    "addr:postcode":"07481",
    "addr:street":"Wyckoff Ave",
    "iso:country":"US",
    "sg:address":"699 Wyckoff Ave",
    "sg:city":"Wyckoff",
    "sg:classifiers":[
        {
            "category":"Shopping",
            "subcategory":"Jewelry",
            "type":"Retail Goods"
        },
        {
            "category":"Manufacturing",
            "subcategory":"Jewelry",
            "type":"Manufacturing & Wholesale Goods"
        }
    ],
    "sg:phone":"+1 201 425 4153",
    "sg:postcode":"07481",
    "sg:province":"NJ",
    "sg:tags":[
        "manufacturer",
        "watch",
        "jewelers-wholesale",
        "jeweler"
    ],
    "sg:website":"http://newyork.citysearch.com/profile/external/6692107/wyckoff_nj/hartgers_jewelers.html?publisher=yellowpages&reference_id=1&placement=ypwebsitemip",
    "wof:name":"Hartgers Jewelers",
    "wof:placetype":"venue"
},
  "geometry": {"coordinates":[-74.17134900000001,41.015541],"type":"Point"}
}