{
  "type": "Feature",
  "properties": {
    "addr:full":"14 Hatfield St Caldwell NJ 07006",
    "addr:housenumber":"14",
    "addr:postcode":"07006",
    "addr:street":"Hatfield St",
    "iso:country":"US",
    "sg:address":"14 Hatfield St",
    "sg:city":"Caldwell",
    "sg:classifiers":[
        {
            "category":"Wholesale",
            "subcategory":"Machinery & Supplies",
            "type":"Manufacturing & Wholesale Goods"
        }
    ],
    "sg:phone":"+1 973 364 1515",
    "sg:postcode":"07006",
    "sg:province":"NJ",
    "wof:name":"Viron Energy Svc",
    "wof:placetype":"venue"
},
  "geometry": {"coordinates":[-74.266808,40.838699],"type":"Point"}
}