{
  "type": "Feature",
  "properties": {
    "addr:full":"2 Garfield Ave Jersey City NJ 07305",
    "addr:housenumber":"2",
    "addr:postcode":"07305",
    "addr:street":"Garfield Ave",
    "iso:country":"US",
    "sg:address":"2 Garfield Ave",
    "sg:city":"Jersey City",
    "sg:classifiers":[
        {
            "category":"Utilities",
            "subcategory":"Mobile Phone",
            "type":"Services"
        }
    ],
    "sg:phone":"+1 201 432 8111",
    "sg:postcode":"07305",
    "sg:province":"NJ",
    "sg:tags":[
        "telephone",
        "cellular"
    ],
    "wof:name":"Page One Wireless",
    "wof:placetype":"venue"
},
  "geometry": {"coordinates":[-74.099794,40.685772],"type":"Point"}
}