{
  "type": "Feature",
  "properties": {
    "addr:full":"1208 State Rte 34 Matawan NJ 07747",
    "addr:housenumber":"1208",
    "addr:postcode":"07747",
    "addr:street":"State Rte 34",
    "iso:country":"US",
    "sg:address":"1208 State Rte 34",
    "sg:city":"Matawan",
    "sg:classifiers":[
        {
            "category":"Wholesale",
            "subcategory":"Construction Materials",
            "type":"Manufacturing & Wholesale Goods"
        }
    ],
    "sg:phone":"+1 732 441 1287",
    "sg:postcode":"07747",
    "sg:province":"NJ",
    "sg:tags":[
        "molding"
    ],
    "wof:name":"Classic Details",
    "wof:placetype":"venue"
},
  "geometry": {"coordinates":[-74.21905599999999,40.388942],"type":"Point"}
}