{
  "type": "Feature",
  "properties": {
    "iso:country":"US",
    "sg:address":"288 Egg Harbor Rd",
    "sg:city":"Sewell",
    "sg:classifiers":[
        {
            "category":"Recreation",
            "type":"Entertainment"
        }
    ],
    "sg:phone":"+1 856 256 0838",
    "sg:postcode":"08080",
    "sg:province":"NJ",
    "sg:tags":[
        "karate",
        "judo",
        "instr"
    ],
    "wof:name":"Aikido New Jersey",
    "wof:placetype":"venue"
},
  "geometry": {"coordinates":[-75.08646,39.766053],"type":"Point"}
}