{
  "type": "Feature",
  "properties": {
    "addr:full":"203 E Ruby Ave Palisades Park NJ 07650",
    "addr:housenumber":"203",
    "addr:postcode":"07650",
    "addr:street":"E Ruby Ave",
    "iso:country":"US",
    "sg:address":"203 E Ruby Ave",
    "sg:city":"Palisades Park",
    "sg:classifiers":[
        {
            "category":"Real Estate",
            "subcategory":"Real Estate Operator",
            "type":"Services"
        }
    ],
    "sg:phone":"+1   ",
    "sg:postcode":"07650",
    "sg:province":"NJ",
    "sg:tags":[
        "building",
        "apartment"
    ],
    "wof:name":"Skyline Studio Apartment",
    "wof:placetype":"venue"
},
  "geometry": {"coordinates":[-73.997257,40.841352],"type":"Point"}
}