{
  "type": "Feature",
  "properties": {
    "iso:country":"US",
    "sg:address":"4507 Hudson Ave",
    "sg:city":"Union City",
    "sg:classifiers":[
        {
            "category":"Education",
            "subcategory":"School",
            "type":"Public Place"
        }
    ],
    "sg:phone":"+1 201 348 5971",
    "sg:postcode":"07087",
    "sg:province":"NJ",
    "sg:website":"www.union-city.k12.nj.us",
    "wof:name":"Roosevelt Elementary School",
    "wof:placetype":"venue"
},
  "geometry": {"coordinates":[-74.01967999999999,40.778251],"type":"Point"}
}