{
  "type": "Feature",
  "properties": {
    "addr:full":"302 Washington Ave Spring Lake NJ 07762",
    "addr:housenumber":"302",
    "addr:postcode":"07762",
    "addr:street":"Washington Ave",
    "iso:country":"US",
    "sg:address":"302 Washington Ave",
    "sg:city":"Spring Lake",
    "sg:classifiers":[
        {
            "category":"Communications",
            "subcategory":"Film & Video Production",
            "type":"Services"
        }
    ],
    "sg:phone":"+1 732 282 1118",
    "sg:postcode":"07762",
    "sg:province":"NJ",
    "sg:tags":[
        "editing",
        "tape"
    ],
    "wof:name":"New World Video",
    "wof:placetype":"venue"
},
  "geometry": {"coordinates":[-74.02957600000001,40.154873],"type":"Point"}
}