{
  "type": "Feature",
  "properties": {
    "addr:full":"197 State Rte 18 East Brunswick NJ 08816",
    "addr:housenumber":"197",
    "addr:postcode":"08816",
    "addr:street":"State Rte 18",
    "iso:country":"US",
    "sg:address":"197 State Rte 18",
    "sg:city":"East Brunswick",
    "sg:classifiers":[
        {
            "category":"Personal",
            "type":"Services"
        }
    ],
    "sg:phone":"+1 732 247 8282",
    "sg:postcode":"08816",
    "sg:province":"NJ",
    "sg:tags":[
        "hair",
        "replacement"
    ],
    "wof:name":"Hair Club For Men & Women",
    "wof:placetype":"venue"
},
  "geometry": {"coordinates":[-74.389832,40.42218],"type":"Point"}
}