{
  "type": "Feature",
  "properties": {
    "addr:full":"163 Stockton St Hightstown NJ 08520",
    "addr:housenumber":"163",
    "addr:postcode":"08520",
    "addr:street":"Stockton St",
    "iso:country":"US",
    "sg:address":"163 Stockton St",
    "sg:city":"Hightstown",
    "sg:classifiers":[
        {
            "category":"Professional",
            "subcategory":"Management & Consulting",
            "type":"Services"
        }
    ],
    "sg:phone":"+1   ",
    "sg:postcode":"08520",
    "sg:province":"NJ",
    "sg:tags":[
        "construction",
        "administration"
    ],
    "sg:website":"www.greentreeconsulting.com",
    "wof:name":"Greentree Consulting Inc",
    "wof:placetype":"venue"
},
  "geometry": {"coordinates":[-74.525391,40.270461],"type":"Point"}
}