{
  "type": "Feature",
  "properties": {
    "iso:country":"US",
    "sg:address":"61 N Maple Ave",
    "sg:city":"Ridgewood",
    "sg:classifiers":[
        {
            "category":"Social Services",
            "subcategory":"Child Care",
            "type":"Services"
        },
        {
            "category":"Social Services",
            "type":"Services"
        }
    ],
    "sg:phone":"+1 201 444 3686",
    "sg:postcode":"07450",
    "sg:province":"NJ",
    "sg:tags":[
        "counseling",
        "day"
    ],
    "wof:name":"Stepping Stones Counseling Ctr",
    "wof:placetype":"venue"
},
  "geometry": {"coordinates":[-74.112692,40.979966],"type":"Point"}
}