{
  "type": "Feature",
  "properties": {
    "addr:full":"167 Main St Ste 3 Hackensack NJ 07601",
    "addr:housenumber":"167",
    "addr:postcode":"07601",
    "addr:street":"Main St Ste 3",
    "iso:country":"US",
    "sg:address":"167 Main St Ste 3",
    "sg:city":"Hackensack",
    "sg:classifiers":[
        {
            "category":"Professional",
            "subcategory":"Lawyer & Legal Services",
            "type":"Services"
        }
    ],
    "sg:phone":"+1 201 853 0077",
    "sg:postcode":"07601",
    "sg:province":"NJ",
    "wof:name":"Miller Donald F",
    "wof:placetype":"venue"
},
  "geometry": {"coordinates":[-74.042958,40.883979],"type":"Point"}
}