{
  "type": "Feature",
  "properties": {
    "addr:full":"1304 N Delaware St Paulsboro NJ 08066",
    "addr:housenumber":"1304",
    "addr:postcode":"08066",
    "addr:street":"N Delaware St",
    "iso:country":"US",
    "sg:address":"1304 N Delaware St",
    "sg:city":"Paulsboro",
    "sg:classifiers":[
        {
            "category":"Shopping",
            "subcategory":"Clothing, Apparel, & Fashions",
            "type":"Retail Goods"
        }
    ],
    "sg:phone":"+1 856 423 6254",
    "sg:postcode":"08066",
    "sg:province":"NJ",
    "sg:tags":[
        "sport",
        "embroidery"
    ],
    "wof:name":"Just For You",
    "wof:placetype":"venue"
},
  "geometry": {"coordinates":[-75.240512,39.83018],"type":"Point"}
}