{
  "type": "Feature",
  "properties": {
    "addr:full":"294 22nd Ave Paterson NJ 07513",
    "addr:housenumber":"294",
    "addr:postcode":"07513",
    "addr:street":"22Nd Ave",
    "iso:country":"US",
    "sg:address":"294 22nd Ave",
    "sg:city":"Paterson",
    "sg:classifiers":[
        {
            "category":"Building & Trades",
            "subcategory":"Locksmith",
            "type":"Services"
        }
    ],
    "sg:phone":"+1 973 854 4934",
    "sg:postcode":"07513",
    "sg:province":"NJ",
    "sg:tags":[
        "key"
    ],
    "wof:name":"A-1 24 Hour 7 Day Emerg A Locksmith",
    "wof:placetype":"venue"
},
  "geometry": {"coordinates":[-74.14429800000001,40.902831],"type":"Point"}
}