{
  "type": "Feature",
  "properties": {
    "iso:country":"US",
    "sg:address":"408 Plainfield Ave",
    "sg:city":"Plainfield",
    "sg:classifiers":[
        {
            "category":"Retail",
            "subcategory":"Repair Shop",
            "type":"Services"
        }
    ],
    "sg:phone":"+1 908 372 6570",
    "sg:postcode":"07060",
    "sg:province":"NJ",
    "sg:tags":[
        "lock",
        "locksmith"
    ],
    "wof:name":"USA Locksmith",
    "wof:placetype":"venue"
},
  "geometry": {"coordinates":[-74.426338,40.610418],"type":"Point"}
}