{
  "type": "Feature",
  "properties": {
    "addr:full":"1409 Wickapecko Dr Ocean NJ 07712",
    "addr:housenumber":"1409",
    "addr:postcode":"07712",
    "addr:street":"Wickapecko Dr",
    "iso:country":"US",
    "sg:address":"1409 Wickapecko Dr",
    "sg:city":"Ocean",
    "sg:classifiers":[
        {
            "category":"Wholesale",
            "subcategory":"Medical Equipment & Supplies",
            "type":"Manufacturing & Wholesale Goods"
        }
    ],
    "sg:phone":"+1 732 776 5530",
    "sg:postcode":"07712",
    "sg:province":"NJ",
    "sg:tags":[
        "physician",
        "surgeon"
    ],
    "wof:name":"Wickapecko Medical Supplies",
    "wof:placetype":"venue"
},
  "geometry": {"coordinates":[-74.025548,40.231885],"type":"Point"}
}