{
  "type": "Feature",
  "properties": {
    "iso:country":"US",
    "sg:address":"17 Woodhollow Rd",
    "sg:city":"Princeton Junction",
    "sg:classifiers":[
        {
            "category":"Real Estate",
            "subcategory":"Surveying",
            "type":"Services"
        }
    ],
    "sg:phone":"+1 609 936 8454",
    "sg:postcode":"08550",
    "sg:province":"NJ",
    "wof:name":"Accurate Locating Inc",
    "wof:placetype":"venue"
},
  "geometry": {"coordinates":[-74.640838,40.286897],"type":"Point"}
}