{
  "type": "Feature",
  "properties": {
    "addr:full":"113 Delwyn Ln Williamstown NJ 08094",
    "addr:housenumber":"113",
    "addr:postcode":"08094",
    "addr:street":"Delwyn Ln",
    "iso:country":"US",
    "sg:address":"113 Delwyn Ln",
    "sg:city":"Williamstown",
    "sg:classifiers":[
        {
            "category":"Building & Trades",
            "subcategory":"Construction",
            "type":"Services"
        }
    ],
    "sg:phone":"+1 609 561 3027",
    "sg:postcode":"08094",
    "sg:province":"NJ",
    "sg:tags":[
        "general",
        "contractor"
    ],
    "wof:name":"Al-Com Construction Inc",
    "wof:placetype":"venue"
},
  "geometry": {"coordinates":[-74.884046,39.596257],"type":"Point"}
}