{
  "type": "Feature",
  "properties": {
    "iso:country":"US",
    "sg:address":"110 W Palisades Blvd",
    "sg:city":"Palisades Park",
    "sg:classifiers":[
        {
            "category":"Social Services",
            "type":"Services"
        }
    ],
    "sg:phone":"+1 201 944 8111",
    "sg:postcode":"07650",
    "sg:province":"NJ",
    "sg:tags":[
        "organization",
        "welfare"
    ],
    "wof:name":"Meejoee Catholic Social Wrkrs",
    "wof:placetype":"venue"
},
  "geometry": {"coordinates":[-74.000868,40.852174],"type":"Point"}
}