{
  "type": "Feature",
  "properties": {
    "addr:full":"11 Meadow Pond Rd Hamburg NJ 07419",
    "addr:housenumber":"11",
    "addr:postcode":"07419",
    "addr:street":"Meadow Pond Rd",
    "iso:country":"US",
    "sg:address":"11 Meadow Pond Rd",
    "sg:city":"Hamburg",
    "sg:classifiers":[
        {
            "category":"Wholesale",
            "subcategory":"Jewelry",
            "type":"Manufacturing & Wholesale Goods"
        }
    ],
    "sg:phone":"+1 973 209 1517",
    "sg:postcode":"07419",
    "sg:province":"NJ",
    "sg:tags":[
        "stone",
        "sewing"
    ],
    "wof:name":"T W E",
    "wof:placetype":"venue"
},
  "geometry": {"coordinates":[-74.59764199999999,41.148354],"type":"Point"}
}