{
  "type": "Feature",
  "properties": {
    "iso:country":"US",
    "sg:address":"68 Mountain Lake Rd",
    "sg:city":"Belvidere",
    "sg:classifiers":[
        {
            "category":"Home & Garden",
            "subcategory":"Garden Supply",
            "type":"Retail Goods"
        }
    ],
    "sg:phone":"+1 908 475 2776",
    "sg:postcode":"07823",
    "sg:province":"NJ",
    "sg:tags":[
        "nurseryman"
    ],
    "wof:name":"Stoney Meadow Nursery",
    "wof:placetype":"venue"
},
  "geometry": {"coordinates":[-75.01015700000001,40.844053],"type":"Point"}
}