{
  "type": "Feature",
  "properties": {
    "iso:country":"US",
    "sg:address":"160 Timber Dr",
    "sg:city":"Berkeley Heights",
    "sg:classifiers":[
        {
            "category":"Wholesale",
            "subcategory":"Computers",
            "type":"Manufacturing & Wholesale Goods"
        },
        {
            "category":"Professional",
            "subcategory":"Computer Services",
            "type":"Services"
        }
    ],
    "sg:phone":"+1 908 898 0200",
    "sg:postcode":"07922",
    "sg:province":"NJ",
    "sg:tags":[
        "repair"
    ],
    "sg:website":"www.wanttlc.com",
    "wof:name":"Tlc Computer Services",
    "wof:placetype":"venue"
},
  "geometry": {"coordinates":[-74.423349,40.679707],"type":"Point"}
}