{
  "type": "Feature",
  "properties": {
    "addr:full":"562 Hickory Ave Saddle Brook NJ 07663",
    "addr:housenumber":"562",
    "addr:postcode":"07663",
    "addr:street":"Hickory Ave",
    "iso:country":"US",
    "sg:address":"562 Hickory Ave",
    "sg:city":"Saddle Brook",
    "sg:classifiers":[
        {
            "category":"Building & Trades",
            "subcategory":"Equipment Rental",
            "type":"Services"
        }
    ],
    "sg:phone":"+1 201 398 0090",
    "sg:postcode":"07663",
    "sg:province":"NJ",
    "sg:tags":[
        "visual",
        "audio",
        "installation"
    ],
    "wof:name":"Avectus LLC",
    "wof:placetype":"venue"
},
  "geometry": {"coordinates":[-74.099227,40.920596],"type":"Point"}
}