{
  "type": "Feature",
  "properties": {
    "iso:country":"US",
    "sg:address":"151 Ferry St",
    "sg:city":"Newark",
    "sg:classifiers":[
        {
            "category":"Utilities",
            "subcategory":"Mobile Phone",
            "type":"Services"
        }
    ],
    "sg:phone":"+1 973 344 9183",
    "sg:postcode":"07105",
    "sg:province":"NJ",
    "sg:tags":[
        "equipment",
        "paging",
        "signaling",
        "system"
    ],
    "wof:name":"Hi-Tech Computers",
    "wof:placetype":"venue"
},
  "geometry": {"coordinates":[-74.15943300000001,40.729728],"type":"Point"}
}