{
  "type": "Feature",
  "properties": {
    "addr:full":"14 E Prospect St Waldwick NJ 07463",
    "addr:housenumber":"14",
    "addr:postcode":"07463",
    "addr:street":"E Prospect St",
    "iso:country":"US",
    "sg:address":"14 E Prospect St",
    "sg:city":"Waldwick",
    "sg:classifiers":[
        {
            "category":"Personal",
            "subcategory":"Beauty Salon",
            "type":"Services"
        }
    ],
    "sg:phone":"+1 201 444 0290",
    "sg:postcode":"07463",
    "sg:province":"NJ",
    "wof:name":"Morning Glow Hair Stylists",
    "wof:placetype":"venue"
},
  "geometry": {"coordinates":[-74.11762299999999,41.010685],"type":"Point"}
}