{
  "type": "Feature",
  "properties": {
    "iso:country":"US",
    "sg:address":"1080 S Orange Ave",
    "sg:city":"Newark",
    "sg:classifiers":[
        {
            "category":"Professional",
            "type":"Services"
        }
    ],
    "sg:phone":"+1 973 374 9959",
    "sg:postcode":"07106",
    "sg:province":"NJ",
    "sg:tags":[
        "establishment"
    ],
    "wof:name":"Lamsuique",
    "wof:placetype":"venue"
},
  "geometry": {"coordinates":[-74.23345399999999,40.745671],"type":"Point"}
}