{
  "type": "Feature",
  "properties": {
    "iso:country":"US",
    "sg:address":"12 Brian Rd",
    "sg:city":"Edison",
    "sg:classifiers":[
        {
            "category":"Wholesale",
            "subcategory":"Durable Goods & Equipment",
            "type":"Manufacturing & Wholesale Goods"
        }
    ],
    "sg:phone":"+1 732 548 0670",
    "sg:postcode":"08817",
    "sg:province":"NJ",
    "wof:name":"A&S Supply Sales & Services",
    "wof:placetype":"venue"
},
  "geometry": {"coordinates":[-74.383404,40.543291],"type":"Point"}
}