{
  "type": "Feature",
  "properties": {
    "iso:country":"US",
    "sg:address":"1277 Puritan Ave",
    "sg:city":"Woodbury",
    "sg:classifiers":[
        {
            "category":"Manufacturing",
            "subcategory":"Signs",
            "type":"Manufacturing & Wholesale Goods"
        }
    ],
    "sg:phone":"+1 856 845 4392",
    "sg:postcode":"08096",
    "sg:province":"NJ",
    "sg:tags":[
        "specialty",
        "mfg"
    ],
    "wof:name":"Neon Crafters",
    "wof:placetype":"venue"
},
  "geometry": {"coordinates":[-75.147974,39.8582],"type":"Point"}
}