{
  "type": "Feature",
  "properties": {
    "addr:full":"349 Railroad Ave East Rutherford NJ 07073",
    "addr:housenumber":"349",
    "addr:postcode":"07073",
    "addr:street":"Railroad Ave",
    "iso:country":"US",
    "sg:address":"349 Railroad Ave",
    "sg:city":"East Rutherford",
    "sg:classifiers":[
        {
            "category":"Manufacturing",
            "subcategory":"Printing",
            "type":"Manufacturing & Wholesale Goods"
        }
    ],
    "sg:phone":"+1 201 842 1144",
    "sg:postcode":"07073",
    "sg:province":"NJ",
    "sg:tags":[
        "printer",
        "commercial"
    ],
    "wof:name":"Tri Color Graphics",
    "wof:placetype":"venue"
},
  "geometry": {"coordinates":[-74.102769,40.833775],"type":"Point"}
}