{
  "type": "Feature",
  "properties": {
    "iso:country":"US",
    "sg:address":"69 Jersey St",
    "sg:city":"Trenton",
    "sg:classifiers":[
        {
            "category":"Building & Trades",
            "subcategory":"Construction",
            "type":"Services"
        }
    ],
    "sg:phone":"+1 609 695 7111",
    "sg:postcode":"08611",
    "sg:province":"NJ",
    "sg:tags":[
        "home",
        "improvement"
    ],
    "wof:name":"Sam's Home Improvement",
    "wof:placetype":"venue"
},
  "geometry": {"coordinates":[-74.751576,40.204526],"type":"Point"}
}