{
  "type": "Feature",
  "properties": {
    "iso:country":"US",
    "sg:address":"228 Old Short Hills Rd",
    "sg:city":"Short Hills",
    "sg:classifiers":[
        {
            "category":"Shopping",
            "type":"Retail Goods"
        }
    ],
    "sg:phone":"+1 973 912 4363",
    "sg:postcode":"07078",
    "sg:province":"NJ",
    "sg:tags":[
        "cosmetic",
        "perfume"
    ],
    "sg:website":"www.usa.thebodyshop.com",
    "wof:name":"Body Shop",
    "wof:placetype":"venue"
},
  "geometry": {"coordinates":[-74.313551,40.740262],"type":"Point"}
}