{
  "type": "Feature",
  "properties": {
    "iso:country":"US",
    "sg:address":"8 Lyons Ave",
    "sg:city":"Newark",
    "sg:classifiers":[
        {
            "category":"Building & Trades",
            "subcategory":"Cleaning & Sanitation",
            "type":"Services"
        }
    ],
    "sg:phone":"+1 973 878 3625",
    "sg:postcode":"07112",
    "sg:province":"NJ",
    "sg:tags":[
        "carpet"
    ],
    "wof:name":"Golden Cleaners",
    "wof:placetype":"venue"
},
  "geometry": {"coordinates":[-74.206264,40.705648],"type":"Point"}
}