{
  "type": "Feature",
  "properties": {
    "addr:full":"634 Branch Dr Toms River NJ 08755",
    "addr:housenumber":"634",
    "addr:postcode":"08755",
    "addr:street":"Branch Dr",
    "iso:country":"US",
    "sg:address":"634 Branch Dr",
    "sg:city":"Toms River",
    "sg:classifiers":[
        {
            "category":"Building & Trades",
            "subcategory":"Landscaping Services",
            "type":"Services"
        }
    ],
    "sg:phone":"+1 732 281 2284",
    "sg:postcode":"08755",
    "sg:province":"NJ",
    "sg:tags":[
        "landscape"
    ],
    "wof:name":"BV Landscaping",
    "wof:placetype":"venue"
},
  "geometry": {"coordinates":[-74.225437,39.996157],"type":"Point"}
}