{
  "type": "Feature",
  "properties": {
    "addr:full":"1042 Pines Lake Dr W Wayne NJ 07470",
    "addr:housenumber":"1042",
    "addr:postcode":"07470",
    "addr:street":"Pines Lake Dr W",
    "iso:country":"US",
    "sg:address":"1042 Pines Lake Dr W",
    "sg:city":"Wayne",
    "sg:classifiers":[
        {
            "category":"Recreation",
            "type":"Entertainment"
        }
    ],
    "sg:phone":"+1   ",
    "sg:postcode":"07470",
    "sg:province":"NJ",
    "sg:tags":[
        "club",
        "membership"
    ],
    "wof:name":"Sunny R Beach",
    "wof:placetype":"venue"
},
  "geometry": {"coordinates":[-74.268928,40.999439],"type":"Point"}
}