{
  "type": "Feature",
  "properties": {
    "iso:country":"US",
    "sg:address":"1357 Prince Rodgers Ave",
    "sg:city":"Bridgewater",
    "sg:classifiers":[
        {
            "category":"Restaurant",
            "type":"Food & Drink"
        }
    ],
    "sg:phone":"+1 908 526 5260",
    "sg:postcode":"08807",
    "sg:province":"NJ",
    "sg:tags":[
        "eating"
    ],
    "wof:name":"Generoso's Pizza Inc",
    "wof:placetype":"venue"
},
  "geometry": {"coordinates":[-74.60870199999999,40.588893],"type":"Point"}
}