{
  "type": "Feature",
  "properties": {
    "addr:full":"443 Elizabeth Ave Newark NJ 07112",
    "addr:housenumber":"443",
    "addr:postcode":"07112",
    "addr:street":"Elizabeth Ave",
    "iso:country":"US",
    "sg:address":"443 Elizabeth Ave",
    "sg:city":"Newark",
    "sg:classifiers":[
        {
            "category":"Food & Beverages",
            "subcategory":"Liquor & Beverages",
            "type":"Retail Goods"
        }
    ],
    "sg:phone":"+1   ",
    "sg:postcode":"07112",
    "sg:province":"NJ",
    "sg:tags":[
        "alcoholic"
    ],
    "wof:name":"New All Brothers Liquors Inc",
    "wof:placetype":"venue"
},
  "geometry": {"coordinates":[-74.199832,40.709015],"type":"Point"}
}