{
  "type": "Feature",
  "properties": {
    "iso:country":"US",
    "sg:address":"23 N Main St",
    "sg:city":"Woodstown",
    "sg:classifiers":[
        {
            "category":"Shopping",
            "subcategory":"Clothing, Apparel, & Fashions",
            "type":"Retail Goods"
        }
    ],
    "sg:phone":"+1 856 769 0494",
    "sg:postcode":"08098",
    "sg:province":"NJ",
    "sg:tags":[
        "tailor"
    ],
    "wof:name":"Bell Cleaner",
    "wof:placetype":"venue"
},
  "geometry": {"coordinates":[-75.32790900000001,39.651647],"type":"Point"}
}