{
  "type": "Feature",
  "properties": {
    "iso:country":"US",
    "sg:address":"176 Ridgedale Ave",
    "sg:city":"Morristown",
    "sg:classifiers":[
        {
            "category":"Home & Garden",
            "subcategory":"Garden Supply",
            "type":"Retail Goods"
        }
    ],
    "sg:phone":"+1 973 538 3232",
    "sg:postcode":"07960",
    "sg:province":"NJ",
    "sg:tags":[
        "center"
    ],
    "wof:name":"Agway Inc Farm Home & Garden",
    "wof:placetype":"venue"
},
  "geometry": {"coordinates":[-74.464141,40.805154],"type":"Point"}
}