{
  "type": "Feature",
  "properties": {
    "iso:country":"US",
    "sg:address":"335 Franklin Ave",
    "sg:city":"Wyckoff",
    "sg:classifiers":[
        {
            "category":"Shopping",
            "subcategory":"Shoes",
            "type":"Retail Goods"
        }
    ],
    "sg:phone":"+1 201 891 8580",
    "sg:postcode":"07481",
    "sg:province":"NJ",
    "wof:name":"Stride Rite Bootery",
    "wof:placetype":"venue"
},
  "geometry": {"coordinates":[-74.167475,41.010611],"type":"Point"}
}