{
  "type": "Feature",
  "properties": {
    "iso:country":"US",
    "sg:address":"525 Ridge Rd",
    "sg:city":"Lyndhurst",
    "sg:classifiers":[
        {
            "category":"Health Services",
            "subcategory":"Doctor",
            "type":"Services"
        }
    ],
    "sg:phone":"+1 201 935 5512",
    "sg:postcode":"07071",
    "sg:province":"NJ",
    "wof:name":"Wahba Janette M MD",
    "wof:placetype":"venue"
},
  "geometry": {"coordinates":[-74.12220000000001,40.803398],"type":"Point"}
}