{
  "type": "Feature",
  "properties": {
    "addr:full":"150 Sawmill Rd Sparta NJ 07871",
    "addr:housenumber":"150",
    "addr:postcode":"07871",
    "addr:street":"Sawmill Rd",
    "iso:country":"US",
    "sg:address":"150 Sawmill Rd",
    "sg:city":"Sparta",
    "sg:classifiers":[
        {
            "category":"Professional",
            "type":"Services"
        }
    ],
    "sg:phone":"+1   ",
    "sg:postcode":"07871",
    "sg:province":"NJ",
    "wof:name":"Brian Stegman",
    "wof:placetype":"venue"
},
  "geometry": {"coordinates":[-74.62983699999999,41.009572],"type":"Point"}
}