{
  "type": "Feature",
  "properties": {
    "iso:country":"US",
    "sg:address":"2810 Morris Ave Ste 302",
    "sg:city":"Union",
    "sg:classifiers":[
        {
            "category":"Professional",
            "subcategory":"Computer Services",
            "type":"Services"
        }
    ],
    "sg:phone":"+1 908 686 8700",
    "sg:postcode":"07083",
    "sg:province":"NJ",
    "sg:tags":[
        "repair"
    ],
    "wof:name":"Enenia Biometrics Inc",
    "wof:placetype":"venue"
},
  "geometry": {"coordinates":[-74.299626,40.706679],"type":"Point"}
}