{
  "type": "Feature",
  "properties": {
    "iso:country":"US",
    "sg:address":"48 Spruce St",
    "sg:city":"Oakland",
    "sg:classifiers":[
        {
            "category":"Manufacturing",
            "subcategory":"Tools & Machinery",
            "type":"Manufacturing & Wholesale Goods"
        }
    ],
    "sg:phone":"+1 201 337 3731",
    "sg:postcode":"07436",
    "sg:province":"NJ",
    "sg:tags":[
        "designed",
        "built"
    ],
    "wof:name":"Silicon Technology Corp",
    "wof:placetype":"venue"
},
  "geometry": {"coordinates":[-74.255793,41.019243],"type":"Point"}
}