{
  "type": "Feature",
  "properties": {
    "iso:country":"US",
    "sg:address":"16 Cooks Ln",
    "sg:city":"Caldwell",
    "sg:classifiers":[
        {
            "category":"Freight",
            "type":"Transportation"
        }
    ],
    "sg:phone":"+1 973 228 6500",
    "sg:postcode":"07006",
    "sg:province":"NJ",
    "sg:tags":[
        "general"
    ],
    "wof:name":"Good Products",
    "wof:placetype":"venue"
},
  "geometry": {"coordinates":[-74.27444800000001,40.839189],"type":"Point"}
}