{
  "type": "Feature",
  "properties": {
    "addr:full":"39 Main St Farmingdale NJ 07727",
    "addr:housenumber":"39",
    "addr:postcode":"07727",
    "addr:street":"Main St",
    "iso:country":"US",
    "sg:address":"39 Main St",
    "sg:city":"Farmingdale",
    "sg:classifiers":[
        {
            "category":"Professional",
            "subcategory":"Secretarial Services",
            "type":"Services"
        }
    ],
    "sg:phone":"+1   ",
    "sg:postcode":"07727",
    "sg:province":"NJ",
    "sg:tags":[
        "reporting"
    ],
    "wof:name":"Bass Bus & Secretarial Svcs",
    "wof:placetype":"venue"
},
  "geometry": {"coordinates":[-74.167846,40.196029],"type":"Point"}
}