{
  "type": "Feature",
  "properties": {
    "iso:country":"US",
    "sg:address":"450 E Kennedy Blvd",
    "sg:city":"Lakewood",
    "sg:classifiers":[
        {
            "category":"Real Estate",
            "subcategory":"Real Estate Agent",
            "type":"Services"
        },
        {
            "category":"Professional",
            "subcategory":"Management & Consulting",
            "type":"Services"
        }
    ],
    "sg:phone":"+1 732 905 7879",
    "sg:postcode":"08701",
    "sg:province":"NJ",
    "sg:tags":[
        "consultant"
    ],
    "wof:name":"Simon Brecher & Company",
    "wof:placetype":"venue"
},
  "geometry": {"coordinates":[-74.209489,40.106127],"type":"Point"}
}