{
  "type": "Feature",
  "properties": {
    "addr:full":"120 Mizzen Ave Manahawkin NJ 08050",
    "addr:housenumber":"120",
    "addr:postcode":"08050",
    "addr:street":"Mizzen Ave",
    "iso:country":"US",
    "sg:address":"120 Mizzen Ave",
    "sg:city":"Manahawkin",
    "sg:classifiers":[
        {
            "category":"Building & Trades",
            "subcategory":"Construction",
            "type":"Services"
        }
    ],
    "sg:phone":"+1 609 978 0032",
    "sg:postcode":"08050",
    "sg:province":"NJ",
    "sg:tags":[
        "hanging",
        "contractor"
    ],
    "wof:name":"Coasling Painting & Staining",
    "wof:placetype":"venue"
},
  "geometry": {"coordinates":[-74.282212,39.735294],"type":"Point"}
}