{
  "type": "Feature",
  "properties": {
    "iso:country":"US",
    "sg:address":"74 Diamond Rd",
    "sg:city":"Springfield",
    "sg:classifiers":[
        {
            "category":"Personal",
            "type":"Services"
        }
    ],
    "sg:phone":"+1 973 467 1200",
    "sg:postcode":"07081",
    "sg:province":"NJ",
    "sg:tags":[
        "local"
    ],
    "sg:website":"www.bigelowcomponents.com/",
    "wof:name":"Bigelow Component Corp",
    "wof:placetype":"venue"
},
  "geometry": {"coordinates":[-74.318881,40.683721],"type":"Point"}
}