{
  "type": "Feature",
  "properties": {
    "iso:country":"US",
    "sg:address":"308 Washington Ave",
    "sg:city":"Haddonfield",
    "sg:classifiers":[
        {
            "category":"Professional",
            "subcategory":"Detective & Security Services",
            "type":"Services"
        }
    ],
    "sg:phone":"+1 856 795 8264",
    "sg:postcode":"08033",
    "sg:province":"NJ",
    "sg:tags":[
        "information",
        "bureau"
    ],
    "wof:name":"Htf Home Services",
    "wof:placetype":"venue"
},
  "geometry": {"coordinates":[-75.035646,39.891372],"type":"Point"}
}