{
  "type": "Feature",
  "properties": {
    "addr:full":"801 Bower St Linden NJ 07036",
    "addr:housenumber":"801",
    "addr:postcode":"07036",
    "addr:street":"Bower St",
    "iso:country":"US",
    "sg:address":"801 Bower St",
    "sg:city":"Linden",
    "sg:classifiers":[
        {
            "category":"Building & Trades",
            "subcategory":"Cleaning & Sanitation",
            "type":"Services"
        }
    ],
    "sg:phone":"+1 908 925 2537",
    "sg:postcode":"07036",
    "sg:province":"NJ",
    "sg:tags":[
        "janitorial",
        "maintenance"
    ],
    "wof:name":"Johnsons Flr Waxing Jantr Serv",
    "wof:placetype":"venue"
},
  "geometry": {"coordinates":[-74.25103799999999,40.639858],"type":"Point"}
}