{
  "type": "Feature",
  "properties": {
    "addr:full":"48 Lorton Rd Old Bridge NJ 08857",
    "addr:housenumber":"48",
    "addr:postcode":"08857",
    "addr:street":"Lorton Rd",
    "iso:country":"US",
    "sg:address":"48 Lorton Rd",
    "sg:city":"Old Bridge",
    "sg:classifiers":[
        {
            "category":"Professional",
            "subcategory":"Computer Services",
            "type":"Services"
        }
    ],
    "sg:phone":"+1   ",
    "sg:postcode":"08857",
    "sg:province":"NJ",
    "sg:tags":[
        "related"
    ],
    "wof:name":"Andy Ng",
    "wof:placetype":"venue"
},
  "geometry": {"coordinates":[-74.366964,40.392492],"type":"Point"}
}