{
  "type": "Feature",
  "properties": {
    "addr:full":"28 Fanok Rd Whippany NJ 07981",
    "addr:housenumber":"28",
    "addr:postcode":"07981",
    "addr:street":"Fanok Rd",
    "iso:country":"US",
    "sg:address":"28 Fanok Rd",
    "sg:city":"Whippany",
    "sg:classifiers":[
        {
            "category":"Retail",
            "subcategory":"Auto Repair",
            "type":"Services"
        }
    ],
    "sg:phone":"+1 973 887 1377",
    "sg:postcode":"07981",
    "sg:province":"NJ",
    "sg:tags":[
        "exchanging",
        "engine"
    ],
    "wof:name":"P & W Automotive Machining",
    "wof:placetype":"venue"
},
  "geometry": {"coordinates":[-74.430611,40.834278],"type":"Point"}
}