{
  "type": "Feature",
  "properties": {
    "iso:country":"US",
    "sg:address":"2 Barker Ct",
    "sg:city":"Park Ridge",
    "sg:classifiers":[
        {
            "category":"Professional",
            "subcategory":"Lawyer & Legal Services",
            "type":"Services"
        }
    ],
    "sg:phone":"+1 201 825 9720",
    "sg:postcode":"07656",
    "sg:province":"NJ",
    "sg:tags":[
        "attorney"
    ],
    "wof:name":"Howard K Schwartzman Law Ofcs",
    "wof:placetype":"venue"
},
  "geometry": {"coordinates":[-74.021952,41.021111],"type":"Point"}
}