{
  "type": "Feature",
  "properties": {
    "iso:country":"US",
    "sg:address":"80 Summit Cir",
    "sg:city":"Little Ferry",
    "sg:classifiers":[
        {
            "category":"Arts & Performance",
            "subcategory":"Theater",
            "type":"Entertainment"
        }
    ],
    "sg:phone":"+1   ",
    "sg:postcode":"07643",
    "sg:province":"NJ",
    "sg:tags":[
        "group"
    ],
    "wof:name":"Dynamic Sounds",
    "wof:placetype":"venue"
},
  "geometry": {"coordinates":[-74.040144,40.857515],"type":"Point"}
}