{
  "type": "Feature",
  "properties": {
    "iso:country":"US",
    "sg:address":"1433 State Rte 34",
    "sg:city":"Wall Township",
    "sg:classifiers":[
        {
            "category":"Real Estate",
            "subcategory":"Real Estate Agent",
            "type":"Services"
        }
    ],
    "sg:phone":"+1 732 919 0067",
    "sg:postcode":"07727",
    "sg:province":"NJ",
    "sg:tags":[
        "management"
    ],
    "sg:website":"www.mack-cali.com",
    "wof:name":"Mack-Cali Realty Corp",
    "wof:placetype":"venue"
},
  "geometry": {"coordinates":[-74.123693,40.207481],"type":"Point"}
}