{
  "type": "Feature",
  "properties": {
    "addr:full":"22 Cantebury Dr Piscataway NJ 08831",
    "addr:housenumber":"22",
    "addr:postcode":"08831",
    "addr:street":"Cantebury Dr",
    "iso:country":"US",
    "sg:address":"22 Cantebury Dr",
    "sg:city":"Piscataway",
    "sg:classifiers":[
        {
            "category":"Professional",
            "subcategory":"Computer Services",
            "type":"Services"
        }
    ],
    "sg:phone":"+1   ",
    "sg:postcode":"08831",
    "sg:province":"NJ",
    "sg:tags":[
        "related"
    ],
    "wof:name":"Immanuel Services LLC",
    "wof:placetype":"venue"
},
  "geometry": {"coordinates":[-74.44655299999999,40.304736],"type":"Point"}
}