{
  "type": "Feature",
  "properties": {
    "iso:country":"US",
    "sg:address":"6 Greenwich St",
    "sg:city":"Belvidere",
    "sg:classifiers":[
        {
            "category":"Health Services",
            "subcategory":"Chiropractor",
            "type":"Services"
        }
    ],
    "sg:phone":"+1 908 475 2933",
    "sg:postcode":"07823",
    "sg:province":"NJ",
    "sg:website":"www.belviderechiropractic.com",
    "wof:name":"Belvidere Chiropractic Center",
    "wof:placetype":"venue"
},
  "geometry": {"coordinates":[-75.078796,40.829201],"type":"Point"}
}