{
  "type": "Feature",
  "properties": {
    "iso:country":"US",
    "sg:address":"5 Central Schoolhouse Rd",
    "sg:city":"Penns Grove",
    "sg:classifiers":[
        {
            "category":"Retail",
            "subcategory":"Car Wash",
            "type":"Services"
        }
    ],
    "sg:phone":"+1   ",
    "sg:postcode":"08069",
    "sg:province":"NJ",
    "sg:tags":[
        "carwash"
    ],
    "wof:name":"Noodles Truck Wash",
    "wof:placetype":"venue"
},
  "geometry": {"coordinates":[-75.443765,39.70658],"type":"Point"}
}