{
  "type": "Feature",
  "properties": {
    "addr:full":"990 Cedarbridge Ave Brick NJ 08723",
    "addr:housenumber":"990",
    "addr:postcode":"08723",
    "addr:street":"Cedarbridge Ave",
    "iso:country":"US",
    "sg:address":"990 Cedarbridge Ave",
    "sg:city":"Brick",
    "sg:classifiers":[
        {
            "category":"Restaurant",
            "type":"Food & Drink"
        }
    ],
    "sg:menulink":"http://www.allmenus.com/nj/brick/36726-three-brothers-form-italy/menu/",
    "sg:phone":"+1 732 920 9293",
    "sg:postcode":"08723",
    "sg:province":"NJ",
    "sg:tags":[
        "italian"
    ],
    "wof:name":"Three Brothers Form Italy",
    "wof:placetype":"venue"
},
  "geometry": {"coordinates":[-74.138188,40.053764],"type":"Point"}
}