{
  "type": "Feature",
  "properties": {
    "iso:country":"US",
    "sg:address":"901 Old Marlton Pike W",
    "sg:city":"Marlton",
    "sg:classifiers":[
        {
            "category":"Retail",
            "subcategory":"Portrait Studio",
            "type":"Services"
        }
    ],
    "sg:phone":"+1 856 874 0080",
    "sg:postcode":"08053",
    "sg:province":"NJ",
    "sg:tags":[
        "photographer"
    ],
    "wof:name":"Michael Gould Photography",
    "wof:placetype":"venue"
},
  "geometry": {"coordinates":[-74.943405,39.894909],"type":"Point"}
}