{
  "type": "Feature",
  "properties": {
    "iso:country":"US",
    "sg:address":"47 Overlook Dr",
    "sg:city":"Woodcliff Lake",
    "sg:classifiers":[
        {
            "category":"Retail",
            "subcategory":"Self-service Laundry",
            "type":"Services"
        }
    ],
    "sg:phone":"+1 201 505 1864",
    "sg:postcode":"07677",
    "sg:province":"NJ",
    "sg:tags":[
        "coin"
    ],
    "wof:name":"Solo Laundry Service LLC",
    "wof:placetype":"venue"
},
  "geometry": {"coordinates":[-74.069698,41.01582],"type":"Point"}
}