{
  "type": "Feature",
  "properties": {
    "addr:full":"185 Ridgedale Ave Morristown NJ 07960",
    "addr:housenumber":"185",
    "addr:postcode":"07960",
    "addr:street":"Ridgedale Ave",
    "iso:country":"US",
    "sg:address":"185 Ridgedale Ave",
    "sg:city":"Morristown",
    "sg:classifiers":[
        {
            "category":"Utilities",
            "subcategory":"Mobile Phone",
            "type":"Services"
        }
    ],
    "sg:phone":"+1 973 695 9600",
    "sg:postcode":"07960",
    "sg:province":"NJ",
    "sg:tags":[
        "communication",
        "radiotelephone"
    ],
    "wof:name":"Interntional Wireless Tech LLC",
    "wof:placetype":"venue"
},
  "geometry": {"coordinates":[-74.465543,40.802188],"type":"Point"}
}