{
  "type": "Feature",
  "properties": {
    "iso:country":"US",
    "sg:address":"174 W Lake Shore Dr",
    "sg:city":"Rockaway",
    "sg:classifiers":[
        {
            "category":"Building & Trades",
            "subcategory":"Landscaping Services",
            "type":"Services"
        }
    ],
    "sg:phone":"+1 973 627 1488",
    "sg:postcode":"07866",
    "sg:province":"NJ",
    "wof:name":"Kocaj Tree & Lawn Service",
    "wof:placetype":"venue"
},
  "geometry": {"coordinates":[-74.524523,40.925519],"type":"Point"}
}