{
  "type": "Feature",
  "properties": {
    "iso:country":"US",
    "sg:address":"365 Convery Blvd",
    "sg:city":"Perth Amboy",
    "sg:classifiers":[
        {
            "category":"Building & Trades",
            "subcategory":"Locksmith",
            "type":"Services"
        }
    ],
    "sg:phone":"+1 888 277 6068",
    "sg:postcode":"08861",
    "sg:province":"NJ",
    "sg:tags":[
        "key"
    ],
    "wof:name":"Always Affective Available Emergency Locksmith",
    "wof:placetype":"venue"
},
  "geometry": {"coordinates":[-74.28583399999999,40.516418],"type":"Point"}
}