{
  "type": "Feature",
  "properties": {
    "addr:full":"211 Honeysuckle Dr Trenton NJ 08691",
    "addr:housenumber":"211",
    "addr:postcode":"08691",
    "addr:street":"Honeysuckle Dr",
    "iso:country":"US",
    "sg:address":"211 Honeysuckle Dr",
    "sg:city":"Trenton",
    "sg:classifiers":[
        {
            "category":"Food & Beverages",
            "subcategory":"Specialty",
            "type":"Retail Goods"
        }
    ],
    "sg:phone":"+1   ",
    "sg:postcode":"08691",
    "sg:province":"NJ",
    "wof:name":"Lin Ling Wang",
    "wof:placetype":"venue"
},
  "geometry": {"coordinates":[-74.61363900000001,40.206315],"type":"Point"}
}