{
  "type": "Feature",
  "properties": {
    "iso:country":"US",
    "sg:address":"500 Nordhoff Pl",
    "sg:city":"Englewood",
    "sg:classifiers":[
        {
            "category":"Building & Trades",
            "subcategory":"Construction",
            "type":"Services"
        }
    ],
    "sg:phone":"+1 201 567 7706",
    "sg:postcode":"07631",
    "sg:province":"NJ",
    "sg:tags":[
        "general",
        "contractor"
    ],
    "wof:name":"FJV Construction Co",
    "wof:placetype":"venue"
},
  "geometry": {"coordinates":[-73.98406199999999,40.88136],"type":"Point"}
}