{
  "type": "Feature",
  "properties": {
    "iso:country":"US",
    "sg:address":"4 Essex Ave",
    "sg:city":"Bernardsville",
    "sg:classifiers":[
        {
            "category":"Building & Trades",
            "subcategory":"Construction",
            "type":"Services"
        }
    ],
    "sg:phone":"+1 908 696 0433",
    "sg:postcode":"07924",
    "sg:province":"NJ",
    "sg:tags":[
        "contractor"
    ],
    "wof:name":"Essex Building",
    "wof:placetype":"venue"
},
  "geometry": {"coordinates":[-74.572428,40.717819],"type":"Point"}
}