{
  "type": "Feature",
  "properties": {
    "iso:country":"US",
    "sg:address":"61-15 97",
    "sg:city":"Ridgefield Park",
    "sg:classifiers":[
        {
            "category":"Shopping",
            "subcategory":"Jewelry",
            "type":"Retail Goods"
        }
    ],
    "sg:phone":"+1 212 391 8044",
    "sg:postcode":"07660",
    "sg:province":"NJ",
    "wof:name":"Sunshine Import Inc",
    "wof:placetype":"venue"
},
  "geometry": {"coordinates":[-74.02610300000001,40.857956],"type":"Point"}
}