{
  "type": "Feature",
  "properties": {
    "iso:country":"US",
    "sg:address":"495 Marion St",
    "sg:city":"Teaneck",
    "sg:classifiers":[
        {
            "category":"Professional",
            "type":"Services"
        }
    ],
    "sg:phone":"+1 201 996 0088",
    "sg:postcode":"07666",
    "sg:province":"NJ",
    "sg:tags":[
        "sculptor"
    ],
    "wof:name":"Bonnyworks",
    "wof:placetype":"venue"
},
  "geometry": {"coordinates":[-74.00265899999999,40.874604],"type":"Point"}
}