{
  "type": "Feature",
  "properties": {
    "addr:full":"37 Station Dr Princeton Junction NJ 08550",
    "addr:housenumber":"37",
    "addr:postcode":"08550",
    "addr:street":"Station Dr",
    "iso:country":"US",
    "sg:address":"37 Station Dr",
    "sg:city":"Princeton Junction",
    "sg:classifiers":[
        {
            "category":"Professional",
            "subcategory":"Accounting & Tax Preparation",
            "type":"Services"
        }
    ],
    "sg:phone":"+1 609 716 9766",
    "sg:postcode":"08550",
    "sg:province":"NJ",
    "wof:name":"Donald H Greenman",
    "wof:placetype":"venue"
},
  "geometry": {"coordinates":[-74.62316300000001,40.317516],"type":"Point"}
}