{
  "type": "Feature",
  "properties": {
    "addr:full":"412 Hampton Ct Englishtown NJ 07726",
    "addr:housenumber":"412",
    "addr:postcode":"07726",
    "addr:street":"Hampton Ct",
    "iso:country":"US",
    "sg:address":"412 Hampton Ct",
    "sg:city":"Englishtown",
    "sg:classifiers":[
        {
            "category":"Building & Trades",
            "subcategory":"Construction",
            "type":"Services"
        }
    ],
    "sg:phone":"+1 732 972 8776",
    "sg:postcode":"07726",
    "sg:province":"NJ",
    "sg:tags":[
        "contractor"
    ],
    "wof:name":"Ermar Contracting",
    "wof:placetype":"venue"
},
  "geometry": {"coordinates":[-74.307817,40.312871],"type":"Point"}
}