{
  "type": "Feature",
  "properties": {
    "iso:country":"US",
    "sg:address":"201 River Rd",
    "sg:city":"New Milford",
    "sg:classifiers":[
        {
            "category":"Personal",
            "subcategory":"Barber",
            "type":"Services"
        }
    ],
    "sg:phone":"+1 201 986 0250",
    "sg:postcode":"07646",
    "sg:province":"NJ",
    "sg:tags":[
        "shop"
    ],
    "wof:name":"Tris' Barber Shop",
    "wof:placetype":"venue"
},
  "geometry": {"coordinates":[-74.020203,40.945805],"type":"Point"}
}