{
  "type": "Feature",
  "properties": {
    "addr:full":"182 E Iselin Pkwy Iselin NJ 08830",
    "addr:housenumber":"182",
    "addr:postcode":"08830",
    "addr:street":"E Iselin Pkwy",
    "iso:country":"US",
    "sg:address":"182 E Iselin Pkwy",
    "sg:city":"Iselin",
    "sg:classifiers":[
        {
            "category":"Professional",
            "subcategory":"Business Services",
            "type":"Services"
        }
    ],
    "sg:phone":"+1 732 283 2026",
    "sg:postcode":"08830",
    "sg:province":"NJ",
    "wof:name":"Nocturnal Productions Inc",
    "wof:placetype":"venue"
},
  "geometry": {"coordinates":[-74.32807200000001,40.582401],"type":"Point"}
}