{
  "type": "Feature",
  "properties": {
    "iso:country":"US",
    "sg:address":"53 Edgeboro Rd",
    "sg:city":"East Brunswick",
    "sg:classifiers":[
        {
            "category":"Building & Trades",
            "subcategory":"Construction",
            "type":"Services"
        }
    ],
    "sg:phone":"+1 732 246 1014",
    "sg:postcode":"08816",
    "sg:province":"NJ",
    "sg:tags":[
        "excavating",
        "contractor"
    ],
    "wof:name":"Vollers Excavators",
    "wof:placetype":"venue"
},
  "geometry": {"coordinates":[-74.395313,40.470494],"type":"Point"}
}