{
  "type": "Feature",
  "properties": {
    "addr:full":"700 Atrium Dr Somerset NJ 08873",
    "addr:housenumber":"700",
    "addr:postcode":"08873",
    "addr:street":"Atrium Dr",
    "iso:country":"US",
    "sg:address":"700 Atrium Dr",
    "sg:city":"Somerset",
    "sg:classifiers":[
        {
            "category":"Wholesale",
            "subcategory":"Drugs",
            "type":"Manufacturing & Wholesale Goods"
        }
    ],
    "sg:phone":"+1 732 302 7277",
    "sg:postcode":"08873",
    "sg:province":"NJ",
    "wof:name":"L Avdey",
    "wof:placetype":"venue"
},
  "geometry": {"coordinates":[-74.52086,40.533744],"type":"Point"}
}