{
  "type": "Feature",
  "properties": {
    "addr:full":"903 Castle Rd Secaucus NJ 07094",
    "addr:housenumber":"903",
    "addr:postcode":"07094",
    "addr:street":"Castle Rd",
    "iso:country":"US",
    "sg:address":"903 Castle Rd",
    "sg:city":"Secaucus",
    "sg:classifiers":[
        {
            "category":"Freight",
            "type":"Transportation"
        }
    ],
    "sg:phone":"+1 201 583 1507",
    "sg:postcode":"07094",
    "sg:province":"NJ",
    "sg:tags":[
        "trucking"
    ],
    "sg:website":"www.summittrans.com",
    "wof:name":"Summit Transportation Inc",
    "wof:placetype":"venue"
},
  "geometry": {"coordinates":[-74.08528200000001,40.774058],"type":"Point"}
}