{
  "type": "Feature",
  "properties": {
    "iso:country":"US",
    "sg:address":"401 Bergen St",
    "sg:city":"Harrison",
    "sg:classifiers":[
        {
            "category":"Restaurant",
            "type":"Food & Drink"
        }
    ],
    "sg:menulink":"http://www.allmenus.com/nj/harrison/181690-wendys/menu/",
    "sg:phone":"+1 973 483 8704",
    "sg:postcode":"07029",
    "sg:province":"NJ",
    "sg:tags":[
        "burger",
        "american",
        "soup"
    ],
    "wof:name":"Wendy's",
    "wof:placetype":"venue"
},
  "geometry": {"coordinates":[-74.15568399999999,40.743085],"type":"Point"}
}