{
  "type": "Feature",
  "properties": {
    "addr:full":"2503 Pacific Ave Atlantic City NJ 08401",
    "addr:housenumber":"2503",
    "addr:postcode":"08401",
    "addr:street":"Pacific Ave",
    "iso:country":"US",
    "sg:address":"2503 Pacific Ave",
    "sg:city":"Atlantic City",
    "sg:classifiers":[
        {
            "category":"Restaurant",
            "type":"Food & Drink"
        }
    ],
    "sg:phone":"+1   ",
    "sg:postcode":"08401",
    "sg:province":"NJ",
    "sg:tags":[
        "eating"
    ],
    "wof:name":"Cancun Restaurant",
    "wof:placetype":"venue"
},
  "geometry": {"coordinates":[-74.44139199999999,39.354868],"type":"Point"}
}