{
  "type": "Feature",
  "properties": {
    "addr:full":"247 Westwood Ave Westwood NJ 07675",
    "addr:housenumber":"247",
    "addr:postcode":"07675",
    "addr:street":"Westwood Ave",
    "iso:country":"US",
    "sg:address":"247 Westwood Ave",
    "sg:city":"Westwood",
    "sg:classifiers":[
        {
            "category":"Home & Garden",
            "subcategory":"Hardware",
            "type":"Retail Goods"
        }
    ],
    "sg:phone":"+1 201 664 5016",
    "sg:postcode":"07675",
    "sg:province":"NJ",
    "wof:name":"L N Grand True Value Westwood",
    "wof:placetype":"venue"
},
  "geometry": {"coordinates":[-74.030277,40.992727],"type":"Point"}
}