{
  "type": "Feature",
  "properties": {
    "addr:full":"503 N Franklin Tpke Ramsey NJ 07446",
    "addr:housenumber":"503",
    "addr:postcode":"07446",
    "addr:street":"N Franklin Tpke",
    "iso:country":"US",
    "sg:address":"503 N Franklin Tpke",
    "sg:city":"Ramsey",
    "sg:classifiers":[
        {
            "category":"Recreation",
            "type":"Entertainment"
        }
    ],
    "sg:phone":"+1 201 825 0404",
    "sg:postcode":"07446",
    "sg:province":"NJ",
    "wof:name":"Softball Tunnel",
    "wof:placetype":"venue"
},
  "geometry": {"coordinates":[-74.137049,41.072126],"type":"Point"}
}