{
  "type": "Feature",
  "properties": {
    "iso:country":"US",
    "sg:address":"1100 N Egg Harbor Rd",
    "sg:city":"Hammonton",
    "sg:classifiers":[
        {
            "category":"Wholesale",
            "subcategory":"Durable Goods & Equipment",
            "type":"Manufacturing & Wholesale Goods"
        }
    ],
    "sg:phone":"+1 609 561 4240",
    "sg:postcode":"08037",
    "sg:province":"NJ",
    "sg:tags":[
        "fire",
        "extinguisher"
    ],
    "wof:name":"Tomasellas Fire Equipment Co",
    "wof:placetype":"venue"
},
  "geometry": {"coordinates":[-74.82952,39.64959],"type":"Point"}
}