{
  "type": "Feature",
  "properties": {
    "iso:country":"US",
    "sg:address":"307 US Hwy 9",
    "sg:city":"Englishtown",
    "sg:classifiers":[
        {
            "category":"Retail",
            "subcategory":"Laundry & Dry Cleaning",
            "type":"Services"
        }
    ],
    "sg:phone":"+1   ",
    "sg:postcode":"07726",
    "sg:province":"NJ",
    "sg:tags":[
        "drycleaning",
        "plant"
    ],
    "wof:name":"Carousel Cleaners",
    "wof:placetype":"venue"
},
  "geometry": {"coordinates":[-74.304112,40.307098],"type":"Point"}
}