{
  "type": "Feature",
  "properties": {
    "addr:full":"240 Sylvan Dell Ave Edison NJ 08817",
    "addr:housenumber":"240",
    "addr:postcode":"08817",
    "addr:street":"Sylvan Dell Ave",
    "iso:country":"US",
    "sg:address":"240 Sylvan Dell Ave",
    "sg:city":"Edison",
    "sg:classifiers":[
        {
            "category":"Freight",
            "type":"Transportation"
        }
    ],
    "sg:phone":"+1 732 572 1981",
    "sg:postcode":"08817",
    "sg:province":"NJ",
    "wof:name":"Super Dave Transportation LLC",
    "wof:placetype":"venue"
},
  "geometry": {"coordinates":[-74.402462,40.495603],"type":"Point"}
}