{
  "type": "Feature",
  "properties": {
    "iso:country":"US",
    "sg:address":"141 Cedar Ln",
    "sg:city":"Teaneck",
    "sg:classifiers":[
        {
            "category":"Personal",
            "subcategory":"Beauty Salon",
            "type":"Services"
        }
    ],
    "sg:phone":"+1 201 287 0112",
    "sg:postcode":"07666",
    "sg:province":"NJ",
    "wof:name":"Janell's Place",
    "wof:placetype":"venue"
},
  "geometry": {"coordinates":[-74.01164900000001,40.885708],"type":"Point"}
}