{
  "type": "Feature",
  "properties": {
    "addr:full":"117 Pennsylvania Ave Paterson NJ 07503",
    "addr:housenumber":"117",
    "addr:postcode":"07503",
    "addr:street":"Pennsylvania Ave",
    "iso:country":"US",
    "sg:address":"117 Pennsylvania Ave",
    "sg:city":"Paterson",
    "sg:classifiers":[
        {
            "category":"Building & Trades",
            "subcategory":"Equipment Rental",
            "type":"Services"
        }
    ],
    "sg:phone":"+1 973 742 1779",
    "sg:postcode":"07503",
    "sg:province":"NJ",
    "sg:tags":[
        "party",
        "supply"
    ],
    "sg:website":"www.somethingdifferentparty.com",
    "wof:name":"Something Different Party Rntl",
    "wof:placetype":"venue"
},
  "geometry": {"coordinates":[-74.153963,40.90116],"type":"Point"}
}