{
  "type": "Feature",
  "properties": {
    "iso:country":"US",
    "sg:address":"201 Sandford St",
    "sg:city":"New Brunswick",
    "sg:classifiers":[
        {
            "category":"Retail",
            "subcategory":"Funeral Services",
            "type":"Services"
        }
    ],
    "sg:phone":"+1 732 545 7312",
    "sg:postcode":"08901",
    "sg:province":"NJ",
    "sg:tags":[
        "director"
    ],
    "wof:name":"Anderson Funeral Svc",
    "wof:placetype":"venue"
},
  "geometry": {"coordinates":[-74.44963199999999,40.483857],"type":"Point"}
}