{
  "type": "Feature",
  "properties": {
    "addr:full":"110 Greenwich St Belvidere NJ 07823",
    "addr:housenumber":"110",
    "addr:postcode":"07823",
    "addr:street":"Greenwich St",
    "iso:country":"US",
    "sg:address":"110 Greenwich St",
    "sg:city":"Belvidere",
    "sg:classifiers":[
        {
            "category":"Building & Trades",
            "subcategory":"Locksmith",
            "type":"Services"
        }
    ],
    "sg:phone":"+1 888 271 1710",
    "sg:postcode":"07823",
    "sg:province":"NJ",
    "sg:tags":[
        "key"
    ],
    "wof:name":"Anytime Anywhere Emergency Locksmith",
    "wof:placetype":"venue"
},
  "geometry": {"coordinates":[-75.07854500000001,40.82826],"type":"Point"}
}