{
  "type": "Feature",
  "properties": {
    "addr:full":"100 Grove St Haddonfield NJ 08033",
    "addr:housenumber":"100",
    "addr:postcode":"08033",
    "addr:street":"Grove St",
    "iso:country":"US",
    "sg:address":"100 Grove St",
    "sg:city":"Haddonfield",
    "sg:classifiers":[
        {
            "category":"Professional",
            "subcategory":"Lawyer & Legal Services",
            "type":"Services"
        }
    ],
    "sg:phone":"+1 856 795 2440",
    "sg:postcode":"08033",
    "sg:province":"NJ",
    "sg:tags":[
        "attorney"
    ],
    "wof:name":"Kancher Law Firm",
    "wof:placetype":"venue"
},
  "geometry": {"coordinates":[-75.032118,39.90406],"type":"Point"}
}