{
  "type": "Feature",
  "properties": {
    "addr:full":"167 Washington Ave Little Ferry NJ 07643",
    "addr:housenumber":"167",
    "addr:postcode":"07643",
    "addr:street":"Washington Ave",
    "iso:country":"US",
    "sg:address":"167 Washington Ave",
    "sg:city":"Little Ferry",
    "sg:classifiers":[
        {
            "category":"Health Services",
            "subcategory":"Chiropractor",
            "type":"Services"
        }
    ],
    "sg:phone":"+1 201 641 1600",
    "sg:postcode":"07643",
    "sg:province":"NJ",
    "wof:name":"Terranova Charles DC",
    "wof:placetype":"venue"
},
  "geometry": {"coordinates":[-74.03948800000001,40.846137],"type":"Point"}
}