{
  "type": "Feature",
  "properties": {
    "iso:country":"US",
    "sg:address":"81 Smull Ave",
    "sg:city":"West Caldwell",
    "sg:classifiers":[
        {
            "category":"Professional",
            "subcategory":"Management & Consulting",
            "type":"Services"
        }
    ],
    "sg:phone":"+1 973 403 1200",
    "sg:postcode":"07006",
    "sg:province":"NJ",
    "sg:tags":[
        "consultant"
    ],
    "wof:name":"Keen Sense Consulting",
    "wof:placetype":"venue"
},
  "geometry": {"coordinates":[-74.270922,40.8439],"type":"Point"}
}