{
  "type": "Feature",
  "properties": {
    "iso:country":"US",
    "sg:address":"32 Deane Way",
    "sg:city":"Red Bank",
    "sg:classifiers":[
        {
            "category":"Building & Trades",
            "subcategory":"Construction",
            "type":"Services"
        }
    ],
    "sg:phone":"+1 732 530 5940",
    "sg:postcode":"07701",
    "sg:province":"NJ",
    "sg:tags":[
        "hanging",
        "contractor"
    ],
    "wof:name":"Dependable Painting",
    "wof:placetype":"venue"
},
  "geometry": {"coordinates":[-74.09143299999999,40.34383],"type":"Point"}
}