{
  "type": "Feature",
  "properties": {
    "iso:country":"US",
    "sg:address":"840 N Lenola Rd Ste 4",
    "sg:city":"Moorestown",
    "sg:classifiers":[
        {
            "category":"Professional",
            "subcategory":"Engineering",
            "type":"Services"
        },
        {
            "category":"Wholesale",
            "subcategory":"Construction Materials",
            "type":"Manufacturing & Wholesale Goods"
        },
        {
            "category":"Building & Trades",
            "subcategory":"Construction",
            "type":"Services"
        }
    ],
    "sg:phone":"+1 856 234 2220",
    "sg:postcode":"08057",
    "sg:province":"NJ",
    "sg:tags":[
        "industrial",
        "elevators-repairing",
        "elevator",
        "passenger-commercial",
        "elevators-freight"
    ],
    "sg:website":"http://www.us.schindler.com",
    "wof:name":"Schindler Elevator Corp",
    "wof:placetype":"venue"
},
  "geometry": {"coordinates":[-74.99058599999999,39.96954],"type":"Point"}
}