{
  "type": "Feature",
  "properties": {
    "iso:country":"US",
    "sg:address":"20 Gordon Way",
    "sg:city":"Princeton",
    "sg:classifiers":[
        {
            "category":"Real Estate",
            "subcategory":"Architect",
            "type":"Services"
        }
    ],
    "sg:phone":"+1 609 921 2030",
    "sg:postcode":"08540",
    "sg:province":"NJ",
    "wof:name":"Olav Pedersen Architecture",
    "wof:placetype":"venue"
},
  "geometry": {"coordinates":[-74.64572099999999,40.356455],"type":"Point"}
}