{
  "type": "Feature",
  "properties": {
    "addr:full":"5706 Bergenline Pl West New York NJ 07093",
    "addr:postcode":"5706;07093",
    "addr:street":"Bergenline Pl West",
    "iso:country":"US",
    "sg:address":"5706 Bergenline Pl",
    "sg:city":"West New York",
    "sg:classifiers":[
        {
            "category":"Shopping",
            "subcategory":"Pharmacy",
            "type":"Retail Goods"
        }
    ],
    "sg:phone":"+1 201 869 8054",
    "sg:postcode":"07093",
    "sg:province":"NJ",
    "wof:name":"Rite Aid Pharmacy",
    "wof:placetype":"venue"
},
  "geometry": {"coordinates":[-74.01722700000001,40.787532],"type":"Point"}
}