{
  "type": "Feature",
  "properties": {
    "addr:full":"841 Shrewsbury Ave Shrewsbury NJ 07701",
    "addr:housenumber":"841",
    "addr:postcode":"07701",
    "addr:street":"Shrewsbury Ave",
    "iso:country":"US",
    "sg:address":"841 Shrewsbury Ave",
    "sg:city":"Shrewsbury",
    "sg:classifiers":[
        {
            "category":"Freight",
            "type":"Transportation"
        }
    ],
    "sg:phone":"+1 732 264 6004",
    "sg:postcode":"07701",
    "sg:province":"NJ",
    "sg:tags":[
        "warehouse"
    ],
    "wof:name":"Safeguard Self Storage",
    "wof:placetype":"venue"
},
  "geometry": {"coordinates":[-74.072577,40.31952],"type":"Point"}
}