{
  "type": "Feature",
  "properties": {
    "addr:full":"103 Spruce Rd Ocean City NJ 08226",
    "addr:housenumber":"103",
    "addr:postcode":"08226",
    "addr:street":"Spruce Rd",
    "iso:country":"US",
    "sg:address":"103 Spruce Rd",
    "sg:city":"Ocean City",
    "sg:classifiers":[
        {
            "category":"Professional",
            "subcategory":"Secretarial Services",
            "type":"Services"
        }
    ],
    "sg:phone":"+1   ",
    "sg:postcode":"08226",
    "sg:province":"NJ",
    "sg:tags":[
        "reporting"
    ],
    "wof:name":"Gerald Abarno Court Reporter",
    "wof:placetype":"venue"
},
  "geometry": {"coordinates":[-74.600928,39.273846],"type":"Point"}
}