{
  "type": "Feature",
  "properties": {
    "addr:full":"12 Overbrook Rd Saddle River NJ 07458",
    "addr:housenumber":"12",
    "addr:postcode":"07458",
    "addr:street":"Overbrook Rd",
    "iso:country":"US",
    "sg:address":"12 Overbrook Rd",
    "sg:city":"Saddle River",
    "sg:classifiers":[
        {
            "category":"Sports & Exercise",
            "subcategory":"Gym",
            "type":"Entertainment"
        }
    ],
    "sg:phone":"+1 201 236 0924",
    "sg:postcode":"07458",
    "sg:province":"NJ",
    "sg:tags":[
        "spa"
    ],
    "wof:name":"Travel Tips Nail Salon LLC",
    "wof:placetype":"venue"
},
  "geometry": {"coordinates":[-74.111024,41.054272],"type":"Point"}
}