{
  "type": "Feature",
  "properties": {
    "iso:country":"US",
    "sg:address":"1627 Wyckoff Rd",
    "sg:city":"Farmingdale",
    "sg:classifiers":[
        {
            "category":"Real Estate",
            "subcategory":"Real Estate Agent",
            "type":"Services"
        }
    ],
    "sg:phone":"+1   ",
    "sg:postcode":"07727",
    "sg:province":"NJ",
    "sg:tags":[
        "management"
    ],
    "wof:name":"Fast Forward Inc",
    "wof:placetype":"venue"
},
  "geometry": {"coordinates":[-74.12393299999999,40.199393],"type":"Point"}
}