{
  "type": "Feature",
  "properties": {
    "iso:country":"US",
    "sg:address":"59 Evergreen St",
    "sg:city":"Bayonne",
    "sg:classifiers":[
        {
            "category":"Building & Trades",
            "subcategory":"Plumbing",
            "type":"Services"
        }
    ],
    "sg:phone":"+1 201 339 8912",
    "sg:postcode":"07002",
    "sg:province":"NJ",
    "wof:name":"Leahey Walter M Plumbing & Electrical",
    "wof:placetype":"venue"
},
  "geometry": {"coordinates":[-74.12509900000001,40.653702],"type":"Point"}
}