{
  "type": "Feature",
  "properties": {
    "iso:country":"US",
    "sg:address":"20 Peake Rd",
    "sg:city":"Edison",
    "sg:classifiers":[
        {
            "category":"Shopping",
            "subcategory":"Jewelry",
            "type":"Retail Goods"
        }
    ],
    "sg:phone":"+1   ",
    "sg:postcode":"08837",
    "sg:province":"NJ",
    "wof:name":"Marvelus Beaded Jewelry",
    "wof:placetype":"venue"
},
  "geometry": {"coordinates":[-74.324519,40.540055],"type":"Point"}
}