{
  "type": "Feature",
  "properties": {
    "addr:full":"41 Orchard St Ramsey NJ 07446",
    "addr:housenumber":"41",
    "addr:postcode":"07446",
    "addr:street":"Orchard St",
    "iso:country":"US",
    "sg:address":"41 Orchard St",
    "sg:city":"Ramsey",
    "sg:classifiers":[
        {
            "category":"Professional",
            "subcategory":"Business Services",
            "type":"Services"
        }
    ],
    "sg:phone":"+1 201 802 9080",
    "sg:postcode":"07446",
    "sg:province":"NJ",
    "sg:tags":[
        "information",
        "referral"
    ],
    "wof:name":"Siteline Technologies Inc",
    "wof:placetype":"venue"
},
  "geometry": {"coordinates":[-74.142984,41.07667],"type":"Point"}
}