{
  "type": "Feature",
  "properties": {
    "iso:country":"US",
    "sg:address":"42 E Main St",
    "sg:city":"Denville",
    "sg:classifiers":[
        {
            "category":"Autos & Motor Vehicles",
            "subcategory":"Fuel & Gas Station",
            "type":"Retail Goods"
        }
    ],
    "sg:phone":"+1 973 983 8440",
    "sg:postcode":"07834",
    "sg:province":"NJ",
    "sg:tags":[
        "repair",
        "oil"
    ],
    "wof:name":"Denville Getty",
    "wof:placetype":"venue"
},
  "geometry": {"coordinates":[-74.477997,40.890999],"type":"Point"}
}