{
  "type": "Feature",
  "properties": {
    "iso:country":"US",
    "sg:address":"600 Meadowlands Pkwy",
    "sg:city":"Secaucus",
    "sg:classifiers":[
        {
            "category":"Manufacturing",
            "subcategory":"Chemicals & Compounds",
            "type":"Manufacturing & Wholesale Goods"
        }
    ],
    "sg:phone":"+1 201 866 6490",
    "sg:postcode":"07094",
    "sg:province":"NJ",
    "sg:tags":[
        "mfg"
    ],
    "wof:name":"United Energies",
    "wof:placetype":"venue"
},
  "geometry": {"coordinates":[-74.081641,40.779007],"type":"Point"}
}