{
  "type": "Feature",
  "properties": {
    "iso:country":"US",
    "sg:address":"2 Jersey St",
    "sg:city":"Harrison",
    "sg:classifiers":[
        {
            "category":"Shopping",
            "subcategory":"Computers & Home Electronics",
            "type":"Retail Goods"
        }
    ],
    "sg:phone":"+1   ",
    "sg:postcode":"07029",
    "sg:province":"NJ",
    "wof:name":"Compros International",
    "wof:placetype":"venue"
},
  "geometry": {"coordinates":[-74.16104,40.745148],"type":"Point"}
}