{
  "type": "Feature",
  "properties": {
    "iso:country":"US",
    "sg:address":"117 Mountainview Ave",
    "sg:city":"Nutley",
    "sg:classifiers":[
        {
            "category":"Professional",
            "subcategory":"Management & Consulting",
            "type":"Services"
        }
    ],
    "sg:phone":"+1   ",
    "sg:postcode":"07110",
    "sg:province":"NJ",
    "sg:tags":[
        "retail",
        "direct",
        "sales"
    ],
    "wof:name":"Richies Uncle Corp",
    "wof:placetype":"venue"
},
  "geometry": {"coordinates":[-74.16341300000001,40.821318],"type":"Point"}
}