{
  "type": "Feature",
  "properties": {
    "iso:country":"US",
    "sg:address":"27 N Livingston Ave",
    "sg:city":"Livingston",
    "sg:classifiers":[
        {
            "category":"Home & Garden",
            "subcategory":"Hardware",
            "type":"Retail Goods"
        }
    ],
    "sg:phone":"+1 973 992 0022",
    "sg:postcode":"07039",
    "sg:province":"NJ",
    "sg:tags":[
        "housewares",
        "paint",
        "store"
    ],
    "wof:name":"Karig's Livingston Hardware Store Inc",
    "wof:placetype":"venue"
},
  "geometry": {"coordinates":[-74.31559799999999,40.7967],"type":"Point"}
}