{
  "type": "Feature",
  "properties": {
    "addr:full":"112 Kintzing Dr Marlton NJ 08053",
    "addr:housenumber":"112",
    "addr:postcode":"08053",
    "addr:street":"Kintzing Dr",
    "iso:country":"US",
    "sg:address":"112 Kintzing Dr",
    "sg:city":"Marlton",
    "sg:classifiers":[
        {
            "category":"Building & Trades",
            "subcategory":"Construction",
            "type":"Services"
        }
    ],
    "sg:phone":"+1   ",
    "sg:postcode":"08053",
    "sg:province":"NJ",
    "sg:tags":[
        "contractor",
        "laying",
        "floor",
        "covering"
    ],
    "wof:name":"Dana Corp",
    "wof:placetype":"venue"
},
  "geometry": {"coordinates":[-74.930131,39.909571],"type":"Point"}
}