{
  "type": "Feature",
  "properties": {
    "addr:full":"17 Rumson Rd Rumson NJ 07760",
    "addr:housenumber":"17",
    "addr:postcode":"07760",
    "addr:street":"Rumson Rd",
    "iso:country":"US",
    "sg:address":"17 Rumson Rd",
    "sg:city":"Rumson",
    "sg:classifiers":[
        {
            "category":"Professional",
            "subcategory":"Accounting & Tax Preparation",
            "type":"Services"
        }
    ],
    "sg:phone":"+1 732 842 8211",
    "sg:postcode":"07760",
    "sg:province":"NJ",
    "wof:name":"Nancy M Kegelman CPA",
    "wof:placetype":"venue"
},
  "geometry": {"coordinates":[-73.979152,40.365114],"type":"Point"}
}