{
  "type": "Feature",
  "properties": {
    "addr:full":"1 Warren St Rumson NJ 07760",
    "addr:housenumber":"1",
    "addr:postcode":"07760",
    "addr:street":"Warren St",
    "iso:country":"US",
    "sg:address":"1 Warren St",
    "sg:city":"Rumson",
    "sg:classifiers":[
        {
            "category":"Retail",
            "subcategory":"Repair Shop",
            "type":"Services"
        }
    ],
    "sg:phone":"+1 732 224 9336",
    "sg:postcode":"07760",
    "sg:province":"NJ",
    "sg:tags":[
        "appliance"
    ],
    "wof:name":"Allstate Appliance Repair",
    "wof:placetype":"venue"
},
  "geometry": {"coordinates":[-73.98142799999999,40.360298],"type":"Point"}
}