{
  "type": "Feature",
  "properties": {
    "iso:country":"US",
    "sg:address":"510 Old Short Hills Rd",
    "sg:city":"Short Hills",
    "sg:classifiers":[
        {
            "category":"Health Services",
            "subcategory":"Doctor",
            "type":"Services"
        }
    ],
    "sg:phone":"+1 973 376 8090",
    "sg:postcode":"07078",
    "sg:province":"NJ",
    "wof:name":"Aaron Joseph J MD",
    "wof:placetype":"venue"
},
  "geometry": {"coordinates":[-74.30549600000001,40.756401],"type":"Point"}
}