{
  "type": "Feature",
  "properties": {
    "iso:country":"US",
    "sg:address":"124 Old Tpke",
    "sg:city":"Pleasantville",
    "sg:classifiers":[
        {
            "category":"Wholesale",
            "subcategory":"Fruits & Vegetables",
            "type":"Manufacturing & Wholesale Goods"
        }
    ],
    "sg:phone":"+1 609 641 7122",
    "sg:postcode":"08232",
    "sg:province":"NJ",
    "wof:name":"Jersey Girls Produce",
    "wof:placetype":"venue"
},
  "geometry": {"coordinates":[-74.518863,39.392089],"type":"Point"}
}