{
  "type": "Feature",
  "properties": {
    "addr:full":"110 S Maple Ave Basking Ridge NJ 07920",
    "addr:housenumber":"110",
    "addr:postcode":"07920",
    "addr:street":"S Maple Ave",
    "iso:country":"US",
    "sg:address":"110 S Maple Ave",
    "sg:city":"Basking Ridge",
    "sg:classifiers":[
        {
            "category":"Professional",
            "type":"Services"
        }
    ],
    "sg:phone":"+1 908 766 7330",
    "sg:postcode":"07920",
    "sg:province":"NJ",
    "sg:tags":[
        "establishment"
    ],
    "wof:name":"Barons At Basking Ridge",
    "wof:placetype":"venue"
},
  "geometry": {"coordinates":[-74.547061,40.70439],"type":"Point"}
}