{
  "type": "Feature",
  "properties": {
    "addr:full":"117 Van Horne St Jersey City NJ 07304",
    "addr:housenumber":"117",
    "addr:postcode":"07304",
    "addr:street":"Van Horne St",
    "iso:country":"US",
    "sg:address":"117 Van Horne St",
    "sg:city":"Jersey City",
    "sg:classifiers":[
        {
            "category":"Banks & Credit Unions",
            "subcategory":"Financial Services",
            "type":"Services"
        }
    ],
    "sg:phone":"+1   ",
    "sg:postcode":"07304",
    "sg:province":"NJ",
    "sg:tags":[
        "business",
        "general",
        "real estate",
        "small"
    ],
    "wof:name":"P L Henry & Associates Inc",
    "wof:placetype":"venue"
},
  "geometry": {"coordinates":[-74.0671,40.710162],"type":"Point"}
}