{
  "type": "Feature",
  "properties": {
    "iso:country":"US",
    "sg:address":"605 Bloomfield Ave Ste 6",
    "sg:city":"Montclair",
    "sg:classifiers":[
        {
            "category":"Health Services",
            "subcategory":"Clinic",
            "type":"Services"
        }
    ],
    "sg:phone":"+1 973 744 6888",
    "sg:postcode":"07042",
    "sg:province":"NJ",
    "sg:tags":[
        "counseling",
        "mental"
    ],
    "wof:name":"Stone Audrey R Msw Lcsw",
    "wof:placetype":"venue"
},
  "geometry": {"coordinates":[-74.220299,40.816101],"type":"Point"}
}