{
  "type": "Feature",
  "properties": {
    "iso:country":"US",
    "sg:address":"17 N 13th St",
    "sg:city":"Kenilworth",
    "sg:classifiers":[
        {
            "category":"Restaurant",
            "type":"Food & Drink"
        }
    ],
    "sg:phone":"+1   ",
    "sg:postcode":"07033",
    "sg:province":"NJ",
    "sg:tags":[
        "eating"
    ],
    "wof:name":"Pelican Petes Fish Fry Inc",
    "wof:placetype":"venue"
},
  "geometry": {"coordinates":[-74.29881,40.677093],"type":"Point"}
}