{
  "type": "Feature",
  "properties": {
    "addr:full":"64 Ogle Rd Westwood NJ 07675",
    "addr:housenumber":"64",
    "addr:postcode":"07675",
    "addr:street":"Ogle Rd",
    "iso:country":"US",
    "sg:address":"64 Ogle Rd",
    "sg:city":"Westwood",
    "sg:classifiers":[
        {
            "category":"Professional",
            "subcategory":"Engineering",
            "type":"Services"
        }
    ],
    "sg:phone":"+1 201 767 7829",
    "sg:postcode":"07675",
    "sg:province":"NJ",
    "wof:name":"Old Tappan Road Assoc Inc",
    "wof:placetype":"venue"
},
  "geometry": {"coordinates":[-73.983518,41.026812],"type":"Point"}
}