{
  "type": "Feature",
  "properties": {
    "addr:full":"286 W 7th St Beach Haven NJ 08008",
    "addr:housenumber":"286",
    "addr:postcode":"08008",
    "addr:street":"W 7Th St",
    "iso:country":"US",
    "sg:address":"286 W 7th St",
    "sg:city":"Beach Haven",
    "sg:classifiers":[
        {
            "category":"Shopping",
            "subcategory":"Clothing, Apparel, & Fashions",
            "type":"Retail Goods"
        }
    ],
    "sg:phone":"+1   ",
    "sg:postcode":"08008",
    "sg:province":"NJ",
    "sg:tags":[
        "jewelry"
    ],
    "wof:name":"Phantasmagoria",
    "wof:placetype":"venue"
},
  "geometry": {"coordinates":[-74.17726,39.651148],"type":"Point"}
}