{
  "type": "Feature",
  "properties": {
    "iso:country":"US",
    "sg:address":"242 Elizabeth Ave",
    "sg:city":"Newark",
    "sg:classifiers":[
        {
            "category":"Retail",
            "subcategory":"Car Wash",
            "type":"Services"
        }
    ],
    "sg:phone":"+1   ",
    "sg:postcode":"07108",
    "sg:province":"NJ",
    "sg:tags":[
        "carwash"
    ],
    "wof:name":"Wow Car Wash",
    "wof:placetype":"venue"
},
  "geometry": {"coordinates":[-74.192363,40.714631],"type":"Point"}
}