{
  "type": "Feature",
  "properties": {
    "addr:full":"5 Mathews Ave Riverdale NJ 07457",
    "addr:housenumber":"5",
    "addr:postcode":"07457",
    "addr:street":"Mathews Ave",
    "iso:country":"US",
    "sg:address":"5 Mathews Ave",
    "sg:city":"Riverdale",
    "sg:classifiers":[
        {
            "category":"Wholesale",
            "subcategory":"Scrap",
            "type":"Manufacturing & Wholesale Goods"
        }
    ],
    "sg:phone":"+1 973 838 0034",
    "sg:postcode":"07457",
    "sg:province":"NJ",
    "sg:tags":[
        "recycling",
        "center"
    ],
    "wof:name":"Glass Cycle Systems Inc",
    "wof:placetype":"venue"
},
  "geometry": {"coordinates":[-74.321215,41.000591],"type":"Point"}
}