{
  "type": "Feature",
  "properties": {
    "addr:full":"680 Knollwood Rd Franklin Lakes NJ 07417",
    "addr:housenumber":"680",
    "addr:postcode":"07417",
    "addr:street":"Knollwood Rd",
    "iso:country":"US",
    "sg:address":"680 Knollwood Rd",
    "sg:city":"Franklin Lakes",
    "sg:classifiers":[
        {
            "category":"Wholesale",
            "subcategory":"Machinery & Supplies",
            "type":"Manufacturing & Wholesale Goods"
        }
    ],
    "sg:phone":"+1 201 891 4744",
    "sg:postcode":"07417",
    "sg:province":"NJ",
    "sg:tags":[
        "salon",
        "beauty"
    ],
    "wof:name":"R J Scissors Edge LLC",
    "wof:placetype":"venue"
},
  "geometry": {"coordinates":[-74.21383299999999,41.010169],"type":"Point"}
}