{
  "type": "Feature",
  "properties": {
    "iso:country":"US",
    "sg:address":"253 Newton Sparta Ave",
    "sg:city":"Newton",
    "sg:classifiers":[
        {
            "category":"Personal",
            "subcategory":"Beauty Salon",
            "type":"Services"
        }
    ],
    "sg:phone":"+1   ",
    "sg:postcode":"07860",
    "sg:province":"NJ",
    "sg:tags":[
        "shop"
    ],
    "wof:name":"Ultima Hair Designers",
    "wof:placetype":"venue"
},
  "geometry": {"coordinates":[-74.688422,41.036339],"type":"Point"}
}