{
  "type": "Feature",
  "properties": {
    "addr:full":"5617 Bergenline Ave West New York NJ 07093",
    "addr:housenumber":"5617",
    "addr:postcode":"07093",
    "addr:street":"Bergenline Ave West",
    "iso:country":"US",
    "sg:address":"5617 Bergenline Ave",
    "sg:city":"West New York",
    "sg:classifiers":[
        {
            "category":"Shopping",
            "subcategory":"Florist",
            "type":"Retail Goods"
        }
    ],
    "sg:phone":"+1 201 617 7797",
    "sg:postcode":"07093",
    "sg:province":"NJ",
    "wof:name":"The Castle Flowers",
    "wof:placetype":"venue"
},
  "geometry": {"coordinates":[-74.01799800000001,40.7869],"type":"Point"}
}