{
  "type": "Feature",
  "properties": {
    "addr:full":"35 Gilbert St N Tinton Falls NJ 07701",
    "addr:housenumber":"35",
    "addr:postcode":"07701",
    "addr:street":"Gilbert St N",
    "iso:country":"US",
    "sg:address":"35 Gilbert St N",
    "sg:city":"Tinton Falls",
    "sg:classifiers":[
        {
            "category":"Health Services",
            "subcategory":"Health Practitioner",
            "type":"Services"
        }
    ],
    "sg:phone":"+1 732 936 0444",
    "sg:postcode":"07701",
    "sg:province":"NJ",
    "sg:tags":[
        "therapist",
        "physical"
    ],
    "wof:name":"Southern Ocean Physical Thrpy",
    "wof:placetype":"venue"
},
  "geometry": {"coordinates":[-74.07675399999999,40.326511],"type":"Point"}
}