{
  "type": "Feature",
  "properties": {
    "addr:full":"693 Main St Hackensack NJ 07601",
    "addr:housenumber":"693",
    "addr:postcode":"07601",
    "addr:street":"Main St",
    "iso:country":"US",
    "sg:address":"693 Main St",
    "sg:city":"Hackensack",
    "sg:classifiers":[
        {
            "category":"Professional",
            "subcategory":"Computer Services",
            "type":"Services"
        }
    ],
    "sg:phone":"+1   ",
    "sg:postcode":"07601",
    "sg:province":"NJ",
    "sg:tags":[
        "motion",
        "production",
        "design",
        "system"
    ],
    "wof:name":"Suede Interactive Media Center",
    "wof:placetype":"venue"
},
  "geometry": {"coordinates":[-74.04114,40.900034],"type":"Point"}
}