{
  "type": "Feature",
  "properties": {
    "addr:full":"7 Ohio State Dr Riverside NJ 08075",
    "addr:housenumber":"7",
    "addr:postcode":"08075",
    "addr:street":"Ohio State Dr",
    "iso:country":"US",
    "sg:address":"7 Ohio State Dr",
    "sg:city":"Riverside",
    "sg:classifiers":[
        {
            "category":"Cinema",
            "subcategory":"Movie Rental",
            "type":"Entertainment"
        }
    ],
    "sg:phone":"+1 856 824 0781",
    "sg:postcode":"08075",
    "sg:province":"NJ",
    "sg:tags":[
        "video",
        "tape"
    ],
    "wof:name":"Mr Movies",
    "wof:placetype":"venue"
},
  "geometry": {"coordinates":[-74.949736,40.005072],"type":"Point"}
}