{
  "type": "Feature",
  "properties": {
    "addr:full":"12 Academy St N Glassboro NJ 08028",
    "addr:housenumber":"12",
    "addr:postcode":"08028",
    "addr:street":"Academy St N",
    "iso:country":"US",
    "sg:address":"12 Academy St N",
    "sg:city":"Glassboro",
    "sg:classifiers":[
        {
            "category":"Retail",
            "subcategory":"Laundry & Dry Cleaning",
            "type":"Services"
        }
    ],
    "sg:phone":"+1   ",
    "sg:postcode":"08028",
    "sg:province":"NJ",
    "sg:tags":[
        "drycleaning",
        "plant"
    ],
    "wof:name":"Capital Cleaners",
    "wof:placetype":"venue"
},
  "geometry": {"coordinates":[-75.109617,39.703077],"type":"Point"}
}