{
  "type": "Feature",
  "properties": {
    "iso:country":"US",
    "sg:address":"744 Morgan St",
    "sg:city":"Camden",
    "sg:classifiers":[
        {
            "category":"Restaurant",
            "type":"Food & Drink"
        }
    ],
    "sg:phone":"+1 856 541 1502",
    "sg:postcode":"08104",
    "sg:province":"NJ",
    "sg:tags":[
        "eating"
    ],
    "wof:name":"El Paraiso Restaurant",
    "wof:placetype":"venue"
},
  "geometry": {"coordinates":[-75.112999,39.912498],"type":"Point"}
}