{
  "type": "Feature",
  "properties": {
    "iso:country":"US",
    "sg:address":"7 Woodmere Way",
    "sg:city":"Pennington",
    "sg:classifiers":[
        {
            "category":"Professional",
            "subcategory":"Computer Services",
            "type":"Services"
        }
    ],
    "sg:phone":"+1   ",
    "sg:postcode":"08534",
    "sg:province":"NJ",
    "sg:tags":[
        "datum"
    ],
    "wof:name":"Mike McGranaghan",
    "wof:placetype":"venue"
},
  "geometry": {"coordinates":[-74.781006,40.323548],"type":"Point"}
}