{
  "type": "Feature",
  "properties": {
    "iso:country":"US",
    "sg:address":"1579 Broad St",
    "sg:city":"Bloomfield",
    "sg:classifiers":[
        {
            "category":"Manufacturing",
            "subcategory":"Electronics",
            "type":"Manufacturing & Wholesale Goods"
        }
    ],
    "sg:phone":"+1 201 933 6666",
    "sg:postcode":"07003",
    "sg:province":"NJ",
    "sg:tags":[
        "electronic",
        "component",
        "mfg"
    ],
    "wof:name":"R&M Electronics Inc",
    "wof:placetype":"venue"
},
  "geometry": {"coordinates":[-74.182917,40.842573],"type":"Point"}
}