{
  "type": "Feature",
  "properties": {
    "addr:full":"90 Oakwood Ave West Long Branch NJ 07764",
    "addr:housenumber":"90",
    "addr:postcode":"07764",
    "addr:street":"Oakwood Ave West",
    "iso:country":"US",
    "sg:address":"90 Oakwood Ave",
    "sg:city":"West Long Branch",
    "sg:classifiers":[
        {
            "category":"Retail",
            "subcategory":"Repair Shop",
            "type":"Services"
        }
    ],
    "sg:phone":"+1   ",
    "sg:postcode":"07764",
    "sg:province":"NJ",
    "sg:tags":[
        "jewelry"
    ],
    "wof:name":"Clocks Etc",
    "wof:placetype":"venue"
},
  "geometry": {"coordinates":[-74.006631,40.295207],"type":"Point"}
}