{
  "type": "Feature",
  "properties": {
    "addr:full":"10 Apache Trl Ringwood NJ 07456",
    "addr:housenumber":"10",
    "addr:postcode":"07456",
    "addr:street":"Apache Trl",
    "iso:country":"US",
    "sg:address":"10 Apache Trl",
    "sg:city":"Ringwood",
    "sg:classifiers":[
        {
            "category":"Building & Trades",
            "subcategory":"Landscaping Services",
            "type":"Services"
        }
    ],
    "sg:phone":"+1 973 962 8008",
    "sg:postcode":"07456",
    "sg:province":"NJ",
    "sg:tags":[
        "landscape",
        "contractor"
    ],
    "wof:name":"Autumn Ridge Landscp Mgmt LLC",
    "wof:placetype":"venue"
},
  "geometry": {"coordinates":[-74.253435,41.102151],"type":"Point"}
}