{
  "type": "Feature",
  "properties": {
    "addr:full":"370 Market St Saddle Brook NJ 07663",
    "addr:housenumber":"370",
    "addr:postcode":"07663",
    "addr:street":"Market St",
    "iso:country":"US",
    "sg:address":"370 Market St",
    "sg:city":"Saddle Brook",
    "sg:classifiers":[
        {
            "category":"Food & Beverages",
            "subcategory":"Candy",
            "type":"Retail Goods"
        },
        {
            "category":"Food & Beverages",
            "subcategory":"Chocolate",
            "type":"Retail Goods"
        }
    ],
    "sg:phone":"+1 201 843 4200",
    "sg:postcode":"07663",
    "sg:province":"NJ",
    "sg:tags":[
        "shop",
        "chocolatiers",
        "store"
    ],
    "wof:name":"Perugina Premium Chocolate Warehouse",
    "wof:placetype":"venue"
},
  "geometry": {"coordinates":[-74.095299,40.8969],"type":"Point"}
}