{
  "type": "Feature",
  "properties": {
    "addr:full":"56 Salem Hill Rd Howell NJ 07731",
    "addr:housenumber":"56",
    "addr:postcode":"07731",
    "addr:street":"Salem Hill Rd",
    "iso:country":"US",
    "sg:address":"56 Salem Hill Rd",
    "sg:city":"Howell",
    "sg:classifiers":[
        {
            "category":"Local Transit",
            "type":"Transportation"
        }
    ],
    "sg:phone":"+1 732 905 8777",
    "sg:postcode":"07731",
    "sg:province":"NJ",
    "sg:tags":[
        "limousine"
    ],
    "wof:name":"Luigi's Limousine Svc Inc",
    "wof:placetype":"venue"
},
  "geometry": {"coordinates":[-74.21783600000001,40.155239],"type":"Point"}
}