{
  "type": "Feature",
  "properties": {
    "addr:full":"70 Wayne St Wayne NJ 07470",
    "addr:housenumber":"70",
    "addr:postcode":"07470",
    "addr:street":"Wayne St",
    "iso:country":"US",
    "sg:address":"70 Wayne St",
    "sg:city":"Wayne",
    "sg:classifiers":[
        {
            "category":"Shopping",
            "subcategory":"Music",
            "type":"Retail Goods"
        }
    ],
    "sg:phone":"+1 973 694 5630",
    "sg:postcode":"07470",
    "sg:province":"NJ",
    "sg:tags":[
        "compact",
        "record",
        "disc",
        "tape"
    ],
    "wof:name":"Sam Goody",
    "wof:placetype":"venue"
},
  "geometry": {"coordinates":[-74.28351000000001,40.921268],"type":"Point"}
}