{
  "type": "Feature",
  "properties": {
    "addr:full":"374 Allentown Rd Parsippany NJ 07054",
    "addr:housenumber":"374",
    "addr:postcode":"07054",
    "addr:street":"Allentown Rd",
    "iso:country":"US",
    "sg:address":"374 Allentown Rd",
    "sg:city":"Parsippany",
    "sg:classifiers":[
        {
            "category":"Professional",
            "subcategory":"Management & Consulting",
            "type":"Services"
        }
    ],
    "sg:phone":"+1   ",
    "sg:postcode":"07054",
    "sg:province":"NJ",
    "wof:name":"Soul In Elder Care Planning",
    "wof:placetype":"venue"
},
  "geometry": {"coordinates":[-74.439328,40.856027],"type":"Point"}
}