{
  "type": "Feature",
  "properties": {
    "iso:country":"US",
    "sg:address":"301 N Oxford Ave",
    "sg:city":"Ventnor City",
    "sg:classifiers":[
        {
            "category":"Taxi",
            "type":"Transportation"
        }
    ],
    "sg:phone":"+1 609 823 6062",
    "sg:postcode":"08406",
    "sg:province":"NJ",
    "sg:tags":[
        "taxicab"
    ],
    "wof:name":"Stamoulis Taxi Service",
    "wof:placetype":"venue"
},
  "geometry": {"coordinates":[-74.48035299999999,39.346517],"type":"Point"}
}