{
  "type": "Feature",
  "properties": {
    "addr:full":"79 Commerce St Garfield NJ 07026",
    "addr:housenumber":"79",
    "addr:postcode":"07026",
    "addr:street":"Commerce St",
    "iso:country":"US",
    "sg:address":"79 Commerce St",
    "sg:city":"Garfield",
    "sg:classifiers":[
        {
            "category":"Wholesale",
            "subcategory":"Auto Parts",
            "type":"Manufacturing & Wholesale Goods"
        }
    ],
    "sg:phone":"+1 973 458 9500",
    "sg:postcode":"07026",
    "sg:province":"NJ",
    "sg:tags":[
        "equipment",
        "towing"
    ],
    "wof:name":"David's Towing",
    "wof:placetype":"venue"
},
  "geometry": {"coordinates":[-74.104693,40.869501],"type":"Point"}
}