{
  "type": "Feature",
  "properties": {
    "iso:country":"US",
    "sg:address":"575 US Hwy 46",
    "sg:city":"Fairfield",
    "sg:classifiers":[
        {
            "category":"Professional",
            "subcategory":"Engineering",
            "type":"Services"
        }
    ],
    "sg:phone":"+1 973 808 8779",
    "sg:postcode":"07004",
    "sg:province":"NJ",
    "sg:tags":[
        "engineer"
    ],
    "wof:name":"Matarazzo Engineering LLC",
    "wof:placetype":"venue"
},
  "geometry": {"coordinates":[-74.27691799999999,40.888852],"type":"Point"}
}