{
  "type": "Feature",
  "properties": {
    "addr:full":"44 Oliver St Newark NJ 07105",
    "addr:housenumber":"44",
    "addr:postcode":"07105",
    "addr:street":"Oliver St",
    "iso:country":"US",
    "sg:address":"44 Oliver St",
    "sg:city":"Newark",
    "sg:classifiers":[
        {
            "category":"Professional",
            "type":"Services"
        }
    ],
    "sg:phone":"+1 212 986 1120",
    "sg:postcode":"07105",
    "sg:province":"NJ",
    "sg:tags":[
        "establishment"
    ],
    "wof:name":"Day Glo Color Corp",
    "wof:placetype":"venue"
},
  "geometry": {"coordinates":[-74.16986300000001,40.726018],"type":"Point"}
}