{
  "type": "Feature",
  "properties": {
    "addr:full":"16 Ames Ave Rutherford NJ 07070",
    "addr:housenumber":"16",
    "addr:postcode":"07070",
    "addr:street":"Ames Ave",
    "iso:country":"US",
    "sg:address":"16 Ames Ave",
    "sg:city":"Rutherford",
    "sg:classifiers":[
        {
            "category":"Taxi",
            "type":"Transportation"
        },
        {
            "category":"Airline",
            "type":"Transportation"
        }
    ],
    "sg:phone":"+1 201 507 0707",
    "sg:postcode":"07070",
    "sg:province":"NJ",
    "sg:tags":[
        "shuttle",
        "airport"
    ],
    "wof:name":"Rutherford Yellow Taxi Inc",
    "wof:placetype":"venue"
},
  "geometry": {"coordinates":[-74.102402,40.8288],"type":"Point"}
}