{
  "type": "Feature",
  "properties": {
    "iso:country":"US",
    "sg:address":"71 Morris Rd",
    "sg:city":"Clifton",
    "sg:classifiers":[
        {
            "category":"Shopping",
            "subcategory":"Department Store",
            "type":"Retail Goods"
        }
    ],
    "sg:phone":"+1 973 894 3423",
    "sg:postcode":"07012",
    "sg:province":"NJ",
    "sg:website":"www.ottomantrade.com",
    "wof:name":"Ottoman Trade",
    "wof:placetype":"venue"
},
  "geometry": {"coordinates":[-74.161419,40.846347],"type":"Point"}
}