{
  "type": "Feature",
  "properties": {
    "iso:country":"US",
    "sg:address":"2 Park Ave",
    "sg:city":"Caldwell",
    "sg:classifiers":[
        {
            "category":"Building & Trades",
            "subcategory":"Electrical",
            "type":"Services"
        }
    ],
    "sg:phone":"+1 973 226 6024",
    "sg:postcode":"07006",
    "sg:province":"NJ",
    "sg:tags":[
        "electrician"
    ],
    "sg:website":"www.krugelectric.com",
    "wof:name":"Krug Electric",
    "wof:placetype":"venue"
},
  "geometry": {"coordinates":[-74.277,40.840698],"type":"Point"}
}