{
  "type": "Feature",
  "properties": {
    "addr:full":"76 E 15th St Paterson NJ 07524",
    "addr:housenumber":"76",
    "addr:postcode":"07524",
    "addr:street":"E 15Th St",
    "iso:country":"US",
    "sg:address":"76 E 15th St",
    "sg:city":"Paterson",
    "sg:classifiers":[
        {
            "category":"Food & Beverages",
            "subcategory":"Groceries & Convenience Stores",
            "type":"Retail Goods"
        }
    ],
    "sg:phone":"+1 973 881 9696",
    "sg:postcode":"07524",
    "sg:province":"NJ",
    "sg:tags":[
        "grocer"
    ],
    "wof:name":"Bravo Supermarket",
    "wof:placetype":"venue"
},
  "geometry": {"coordinates":[-74.153997,40.933879],"type":"Point"}
}