{
  "type": "Feature",
  "properties": {
    "iso:country":"US",
    "sg:address":"4612 Park Blvd",
    "sg:city":"Wildwood",
    "sg:classifiers":[
        {
            "category":"Insurance",
            "subcategory":"Insurance Agent",
            "type":"Services"
        }
    ],
    "sg:phone":"+1   ",
    "sg:postcode":"08260",
    "sg:province":"NJ",
    "wof:name":"Coastline Insurance Agency",
    "wof:placetype":"venue"
},
  "geometry": {"coordinates":[-74.825033,38.987412],"type":"Point"}
}