{
  "type": "Feature",
  "properties": {
    "addr:full":"810 Broadway Newark NJ 07104",
    "addr:housenumber":"810",
    "addr:postcode":"07104",
    "addr:street":"Broadway",
    "iso:country":"US",
    "sg:address":"810 Broadway",
    "sg:city":"Newark",
    "sg:classifiers":[
        {
            "category":"Freight",
            "type":"Transportation"
        }
    ],
    "sg:phone":"+1 973 481 0079",
    "sg:postcode":"07104",
    "sg:province":"NJ",
    "sg:tags":[
        "operator",
        "local",
        "trucking"
    ],
    "wof:name":"Cobins Delivery Man",
    "wof:placetype":"venue"
},
  "geometry": {"coordinates":[-74.15731700000001,40.777504],"type":"Point"}
}