{
  "type": "Feature",
  "properties": {
    "iso:country":"US",
    "sg:address":"7002 Kennedy Blvd",
    "sg:city":"West New York",
    "sg:classifiers":[
        {
            "category":"Wholesale",
            "subcategory":"Electrical",
            "type":"Manufacturing & Wholesale Goods"
        }
    ],
    "sg:phone":"+1 201 662 1408",
    "sg:postcode":"07093",
    "sg:province":"NJ",
    "sg:tags":[
        "electronic"
    ],
    "wof:name":"Invertech",
    "wof:placetype":"venue"
},
  "geometry": {"coordinates":[-74.01482,40.79874],"type":"Point"}
}