{
  "type": "Feature",
  "properties": {
    "addr:full":"727 Beach Dr Cape May NJ 08204",
    "addr:housenumber":"727",
    "addr:postcode":"08204",
    "addr:street":"Beach Dr",
    "iso:country":"US",
    "sg:address":"727 Beach Dr",
    "sg:city":"Cape May",
    "sg:classifiers":[
        {
            "category":"Shopping",
            "subcategory":"Gifts & Souvenirs",
            "type":"Retail Goods"
        }
    ],
    "sg:phone":"+1 609 884 3385",
    "sg:postcode":"08204",
    "sg:province":"NJ",
    "sg:tags":[
        "shop"
    ],
    "wof:name":"Mystical Mermaid",
    "wof:placetype":"venue"
},
  "geometry": {"coordinates":[-74.91655900000001,38.930804],"type":"Point"}
}