{
  "type": "Feature",
  "properties": {
    "iso:country":"US",
    "sg:address":"554 Mount Laurel Rd",
    "sg:city":"Mt Laurel",
    "sg:classifiers":[
        {
            "category":"Travel",
            "subcategory":"Hotels & Motels",
            "type":"Entertainment"
        }
    ],
    "sg:phone":"+1 856 802 2800",
    "sg:postcode":"08054",
    "sg:province":"NJ",
    "sg:website":"www.super8.com",
    "wof:name":"Super 8 Motel",
    "wof:placetype":"venue"
},
  "geometry": {"coordinates":[-74.88909700000001,39.931841],"type":"Point"}
}