{
  "type": "Feature",
  "properties": {
    "addr:full":"805 Main St Belmar NJ 07719",
    "addr:housenumber":"805",
    "addr:postcode":"07719",
    "addr:street":"Main St",
    "iso:country":"US",
    "sg:address":"805 Main St",
    "sg:city":"Belmar",
    "sg:classifiers":[
        {
            "category":"Shopping",
            "subcategory":"Gifts & Souvenirs",
            "type":"Retail Goods"
        }
    ],
    "sg:phone":"+1 732 681 7078",
    "sg:postcode":"07719",
    "sg:province":"NJ",
    "sg:tags":[
        "shop"
    ],
    "wof:name":"Carr's Hallmark",
    "wof:placetype":"venue"
},
  "geometry": {"coordinates":[-74.024962,40.181359],"type":"Point"}
}