{
  "type": "Feature",
  "properties": {
    "addr:full":"641 Asbury Ave Ocean City NJ 08226",
    "addr:housenumber":"641",
    "addr:postcode":"08226",
    "addr:street":"Asbury Ave",
    "iso:country":"US",
    "sg:address":"641 Asbury Ave",
    "sg:city":"Ocean City",
    "sg:classifiers":[
        {
            "category":"Shopping",
            "subcategory":"Clothing, Apparel, & Fashions",
            "type":"Retail Goods"
        }
    ],
    "sg:phone":"+1 609 814 0300",
    "sg:postcode":"08226",
    "sg:province":"NJ",
    "sg:tags":[
        "infant",
        "wear"
    ],
    "wof:name":"Pink & Blue Baby Boutique",
    "wof:placetype":"venue"
},
  "geometry": {"coordinates":[-74.57297699999999,39.281441],"type":"Point"}
}