{
  "type": "Feature",
  "properties": {
    "addr:full":"1104 Raritan Rd Cranford NJ 07016",
    "addr:housenumber":"1104",
    "addr:postcode":"07016",
    "addr:street":"Raritan Rd",
    "iso:country":"US",
    "sg:address":"1104 Raritan Rd",
    "sg:city":"Cranford",
    "sg:classifiers":[
        {
            "category":"Building & Trades",
            "subcategory":"Construction",
            "type":"Services"
        }
    ],
    "sg:phone":"+1 908 272 3552",
    "sg:postcode":"07016",
    "sg:province":"NJ",
    "sg:tags":[
        "home",
        "remodeling"
    ],
    "wof:name":"Norway Contracting & Repair",
    "wof:placetype":"venue"
},
  "geometry": {"coordinates":[-74.299331,40.636554],"type":"Point"}
}