{
  "type": "Feature",
  "properties": {
    "addr:full":"97 Ackerman Ave Clifton NJ 07011",
    "addr:housenumber":"97",
    "addr:postcode":"07011",
    "addr:street":"Ackerman Ave",
    "iso:country":"US",
    "sg:address":"97 Ackerman Ave",
    "sg:city":"Clifton",
    "sg:classifiers":[
        {
            "category":"Organizations",
            "subcategory":"Religious Organization",
            "type":"Services"
        }
    ],
    "sg:phone":"+1 973 478 2778",
    "sg:postcode":"07011",
    "sg:province":"NJ",
    "sg:tags":[
        "nightlife",
        "church"
    ],
    "wof:name":"Macedonia Bar & Restaurant",
    "wof:placetype":"venue"
},
  "geometry": {"coordinates":[-74.124163,40.878188],"type":"Point"}
}