{
  "type": "Feature",
  "properties": {
    "addr:full":"1409 Country Ln Trenton NJ 08628",
    "addr:housenumber":"1409",
    "addr:postcode":"08628",
    "addr:street":"Country Ln",
    "iso:country":"US",
    "sg:address":"1409 Country Ln",
    "sg:city":"Trenton",
    "sg:classifiers":[
        {
            "category":"Building & Trades",
            "subcategory":"Construction",
            "type":"Services"
        }
    ],
    "sg:phone":"+1 609 771 1199",
    "sg:postcode":"08628",
    "sg:province":"NJ",
    "sg:tags":[
        "excavating",
        "contractor"
    ],
    "wof:name":"Lawson Sons Excavating",
    "wof:placetype":"venue"
},
  "geometry": {"coordinates":[-74.832041,40.247337],"type":"Point"}
}