{
  "type": "Feature",
  "properties": {
    "addr:full":"318 Woodridge Ave Wood-Ridge NJ 07075",
    "addr:housenumber":"318",
    "addr:postcode":"07075",
    "addr:street":"Woodridge Ave",
    "iso:country":"US",
    "sg:address":"318 Woodridge Ave",
    "sg:city":"Wood-Ridge",
    "sg:classifiers":[
        {
            "category":"Professional",
            "subcategory":"Business Services",
            "type":"Services"
        }
    ],
    "sg:phone":"+1   ",
    "sg:postcode":"07075",
    "sg:province":"NJ",
    "wof:name":"Quality Business Solutions",
    "wof:placetype":"venue"
},
  "geometry": {"coordinates":[-74.08973400000001,40.850291],"type":"Point"}
}