{
  "type": "Feature",
  "properties": {
    "addr:full":"2015 Mount Holly Rd Mount Holly NJ 08060",
    "addr:housenumber":"2015",
    "addr:postcode":"08060",
    "addr:street":"Mount Holly Rd",
    "iso:country":"US",
    "sg:address":"2015 Mount Holly Rd",
    "sg:city":"Mount Holly",
    "sg:classifiers":[
        {
            "category":"Travel",
            "subcategory":"Hotels & Motels",
            "type":"Entertainment"
        }
    ],
    "sg:phone":"+1   ",
    "sg:postcode":"08060",
    "sg:province":"NJ",
    "wof:name":"Howard Johnson",
    "wof:placetype":"venue"
},
  "geometry": {"coordinates":[-74.817825,40.028243],"type":"Point"}
}