{
  "type": "Feature",
  "properties": {
    "addr:full":"3340 Us Highway 1 Trenton NJ 08648",
    "addr:housenumber":"3340",
    "addr:postcode":"08648",
    "addr:street":"Us Highway 1",
    "iso:country":"US",
    "sg:address":"3340 Us Highway 1",
    "sg:city":"Trenton",
    "sg:classifiers":[
        {
            "category":"Food & Beverages",
            "subcategory":"Bakery",
            "type":"Retail Goods"
        },
        {
            "category":"Bagels",
            "type":"Food & Drink"
        }
    ],
    "sg:menulink":"http://www.allmenus.com/nj/lawrence/149691-einstein-bros/menu/",
    "sg:phone":"+1 609 951 0663",
    "sg:postcode":"08648",
    "sg:province":"NJ",
    "sg:tags":[
        "sandwich",
        "salad",
        "bagel",
        "soup",
        "american",
        "wrap"
    ],
    "wof:name":"Einstein Bros",
    "wof:placetype":"venue"
},
  "geometry": {"coordinates":[-74.68284199999999,40.294292],"type":"Point"}
}