{
  "type": "Feature",
  "properties": {
    "iso:country":"US",
    "sg:address":"606 Dowd Ave",
    "sg:city":"Elizabeth",
    "sg:classifiers":[
        {
            "category":"Professional",
            "type":"Services"
        }
    ],
    "sg:phone":"+1 908 355 7480",
    "sg:postcode":"07201",
    "sg:province":"NJ",
    "sg:tags":[
        "establishment"
    ],
    "wof:name":"Laboratory Corp Of America",
    "wof:placetype":"venue"
},
  "geometry": {"coordinates":[-74.186032,40.662358],"type":"Point"}
}