{
  "type": "Feature",
  "properties": {
    "iso:country":"US",
    "sg:address":"108 George Hill Rd",
    "sg:city":"Branchville",
    "sg:classifiers":[
        {
            "category":"Building & Trades",
            "subcategory":"Construction",
            "type":"Services"
        }
    ],
    "sg:phone":"+1 973 293 3030",
    "sg:postcode":"07826",
    "sg:province":"NJ",
    "sg:tags":[
        "excavation",
        "contractor"
    ],
    "wof:name":"Pete Smith Excavating",
    "wof:placetype":"venue"
},
  "geometry": {"coordinates":[-74.727412,41.163329],"type":"Point"}
}