{
  "type": "Feature",
  "properties": {
    "iso:country":"US",
    "sg:address":"124 Half Mile Rd",
    "sg:city":"Red Bank",
    "sg:classifiers":[
        {
            "category":"Professional",
            "subcategory":"Lawyer & Legal Services",
            "type":"Services"
        }
    ],
    "sg:phone":"+1 732 747 6100",
    "sg:postcode":"07701",
    "sg:province":"NJ",
    "sg:tags":[
        "attorney"
    ],
    "wof:name":"Michael R Rizzuto",
    "wof:placetype":"venue"
},
  "geometry": {"coordinates":[-74.09619600000001,40.340228],"type":"Point"}
}