{
  "type": "Feature",
  "properties": {
    "iso:country":"US",
    "sg:address":"418 Palmer St",
    "sg:city":"Elizabeth",
    "sg:classifiers":[
        {
            "category":"Building & Trades",
            "subcategory":"Locksmith",
            "type":"Services"
        }
    ],
    "sg:phone":"+1 888 263 1379",
    "sg:postcode":"07202",
    "sg:province":"NJ",
    "sg:tags":[
        "key"
    ],
    "wof:name":"1 24 Hour Emergency Locksmith",
    "wof:placetype":"venue"
},
  "geometry": {"coordinates":[-74.20635299999999,40.653182],"type":"Point"}
}