{
  "type": "Feature",
  "properties": {
    "addr:full":"705 Hamburg Tpke Wayne NJ 07470",
    "addr:housenumber":"705",
    "addr:postcode":"07470",
    "addr:street":"Hamburg Tpke",
    "iso:country":"US",
    "sg:address":"705 Hamburg Tpke",
    "sg:city":"Wayne",
    "sg:classifiers":[
        {
            "category":"Health Services",
            "subcategory":"Doctor",
            "type":"Services"
        }
    ],
    "sg:phone":"+1 973 904 9898",
    "sg:postcode":"07470",
    "sg:province":"NJ",
    "sg:tags":[
        "physician",
        "surgeon"
    ],
    "wof:name":"Santangelo Medical Ctr",
    "wof:placetype":"venue"
},
  "geometry": {"coordinates":[-74.222236,40.956863],"type":"Point"}
}