{
  "type": "Feature",
  "properties": {
    "iso:country":"US",
    "sg:address":"536 Bergen Blvd",
    "sg:city":"Palisades Park",
    "sg:classifiers":[
        {
            "category":"Building & Trades",
            "subcategory":"Construction",
            "type":"Services"
        }
    ],
    "sg:phone":"+1 201 592 2000",
    "sg:postcode":"07650",
    "sg:province":"NJ",
    "sg:tags":[
        "general",
        "contractor"
    ],
    "wof:name":"Raimondo Construction Inc",
    "wof:placetype":"venue"
},
  "geometry": {"coordinates":[-73.985097,40.8471],"type":"Point"}
}