{
  "type": "Feature",
  "properties": {
    "addr:full":"32 Ashcroft Ave Ocean View NJ 08230",
    "addr:housenumber":"32",
    "addr:postcode":"08230",
    "addr:street":"Ashcroft Ave",
    "iso:country":"US",
    "sg:address":"32 Ashcroft Ave",
    "sg:city":"Ocean View",
    "sg:classifiers":[
        {
            "category":"Wholesale",
            "subcategory":"Sporting Goods",
            "type":"Manufacturing & Wholesale Goods"
        }
    ],
    "sg:phone":"+1 609 624 3811",
    "sg:postcode":"08230",
    "sg:province":"NJ",
    "wof:name":"HRF & Associates",
    "wof:placetype":"venue"
},
  "geometry": {"coordinates":[-74.71480099999999,39.210612],"type":"Point"}
}