{
  "type": "Feature",
  "properties": {
    "iso:country":"US",
    "sg:address":"250 Sussex Rd",
    "sg:city":"Wood Ridge",
    "sg:classifiers":[
        {
            "category":"Building & Trades",
            "subcategory":"Plumbing",
            "type":"Services"
        }
    ],
    "sg:phone":"+1 201 935 2259",
    "sg:postcode":"07075",
    "sg:province":"NJ",
    "wof:name":"Prior Paul Plumbing & Heating",
    "wof:placetype":"venue"
},
  "geometry": {"coordinates":[-74.08899700000001,40.855499],"type":"Point"}
}