{
  "type": "Feature",
  "properties": {
    "addr:full":"268 Truman Dr Cresskill NJ 07626",
    "addr:housenumber":"268",
    "addr:postcode":"07626",
    "addr:street":"Truman Dr",
    "iso:country":"US",
    "sg:address":"268 Truman Dr",
    "sg:city":"Cresskill",
    "sg:classifiers":[
        {
            "category":"Professional",
            "subcategory":"Engineering",
            "type":"Services"
        }
    ],
    "sg:phone":"+1   ",
    "sg:postcode":"07626",
    "sg:province":"NJ",
    "sg:tags":[
        "specializing",
        "structural",
        "engineer",
        "contractor"
    ],
    "wof:name":"Vista Engineering Corp",
    "wof:placetype":"venue"
},
  "geometry": {"coordinates":[-73.94085699999999,40.937383],"type":"Point"}
}