{
  "type": "Feature",
  "properties": {
    "addr:full":"3367 Clark Ave Cedarville NJ 08332",
    "addr:housenumber":"3367",
    "addr:postcode":"08332",
    "addr:street":"Clark Ave",
    "iso:country":"US",
    "sg:address":"3367 Clark Ave",
    "sg:city":"Cedarville",
    "sg:classifiers":[
        {
            "category":"Building & Trades",
            "subcategory":"Landscaping Services",
            "type":"Services"
        }
    ],
    "sg:phone":"+1 856 447 4171",
    "sg:postcode":"08332",
    "sg:province":"NJ",
    "sg:tags":[
        "landscape",
        "contractor"
    ],
    "wof:name":"Turf Toe Landscaping",
    "wof:placetype":"venue"
},
  "geometry": {"coordinates":[-75.137641,39.348274],"type":"Point"}
}