{
  "type": "Feature",
  "properties": {
    "addr:full":"147 US Highway 46 Rockaway NJ 07866",
    "addr:housenumber":"147",
    "addr:postcode":"07866",
    "addr:street":"Us Highway 46",
    "iso:country":"US",
    "sg:address":"147 US Highway 46",
    "sg:city":"Rockaway",
    "sg:classifiers":[
        {
            "category":"Restaurant",
            "type":"Food & Drink"
        }
    ],
    "sg:phone":"+1 973 627 1606",
    "sg:postcode":"07866",
    "sg:province":"NJ",
    "sg:tags":[
        "italian"
    ],
    "sg:website":"www.caffenavona.com",
    "wof:name":"Caffe Navona",
    "wof:placetype":"venue"
},
  "geometry": {"coordinates":[-74.508815,40.892917],"type":"Point"}
}