{
  "type": "Feature",
  "properties": {
    "iso:country":"US",
    "sg:address":"913 Gray Fox Cir",
    "sg:city":"Sewell",
    "sg:classifiers":[
        {
            "category":"Professional",
            "subcategory":"Advertising",
            "type":"Services"
        }
    ],
    "sg:phone":"+1   ",
    "sg:postcode":"08080",
    "sg:province":"NJ",
    "wof:name":"Spw Productions",
    "wof:placetype":"venue"
},
  "geometry": {"coordinates":[-75.140524,39.75997],"type":"Point"}
}