{
  "type": "Feature",
  "properties": {
    "addr:full":"128 High St Westampton NJ 08060",
    "addr:housenumber":"128",
    "addr:postcode":"08060",
    "addr:street":"High St",
    "iso:country":"US",
    "sg:address":"128 High St",
    "sg:city":"Westampton",
    "sg:classifiers":[
        {
            "category":"Museum",
            "type":"Entertainment"
        }
    ],
    "sg:phone":"+1 609 265 5858",
    "sg:postcode":"08060",
    "sg:province":"NJ",
    "wof:name":"Burlington",
    "wof:placetype":"venue"
},
  "geometry": {"coordinates":[-74.78852000000001,39.995869],"type":"Point"}
}