{
  "type": "Feature",
  "properties": {
    "addr:full":"149 N Ensign Dr Tuckerton NJ 08087",
    "addr:housenumber":"149",
    "addr:postcode":"08087",
    "addr:street":"N Ensign Dr",
    "iso:country":"US",
    "sg:address":"149 N Ensign Dr",
    "sg:city":"Tuckerton",
    "sg:classifiers":[
        {
            "category":"Retail",
            "subcategory":"Repair Shop",
            "type":"Services"
        }
    ],
    "sg:phone":"+1   ",
    "sg:postcode":"08087",
    "sg:province":"NJ",
    "sg:tags":[
        "refrigeration"
    ],
    "wof:name":"K W Mechanical",
    "wof:placetype":"venue"
},
  "geometry": {"coordinates":[-74.367935,39.561773],"type":"Point"}
}