{
  "type": "Feature",
  "properties": {
    "iso:country":"US",
    "sg:address":"357 Cleveland Ave",
    "sg:city":"West Berlin",
    "sg:classifiers":[
        {
            "category":"Retail",
            "subcategory":"Portrait Studio",
            "type":"Services"
        }
    ],
    "sg:phone":"+1   ",
    "sg:postcode":"08091",
    "sg:province":"NJ",
    "sg:tags":[
        "photo"
    ],
    "wof:name":"A Thousand Words Images",
    "wof:placetype":"venue"
},
  "geometry": {"coordinates":[-74.93343299999999,39.809619],"type":"Point"}
}