{
  "type": "Feature",
  "properties": {
    "iso:country":"US",
    "sg:address":"122 Berkeley Ave",
    "sg:city":"Bloomfield",
    "sg:classifiers":[
        {
            "category":"Health Services",
            "subcategory":"Medical Lab",
            "type":"Services"
        }
    ],
    "sg:phone":"+1   ",
    "sg:postcode":"07003",
    "sg:province":"NJ",
    "sg:tags":[
        "laboratory",
        "dental"
    ],
    "wof:name":"Far East Dental Lab",
    "wof:placetype":"venue"
},
  "geometry": {"coordinates":[-74.188543,40.785269],"type":"Point"}
}