{
  "type": "Feature",
  "properties": {
    "addr:full":"5 Myrtle Dr Montague NJ 07827",
    "addr:housenumber":"5",
    "addr:postcode":"07827",
    "addr:street":"Myrtle Dr",
    "iso:country":"US",
    "sg:address":"5 Myrtle Dr",
    "sg:city":"Montague",
    "sg:classifiers":[
        {
            "category":"Wholesale",
            "subcategory":"Construction Materials",
            "type":"Manufacturing & Wholesale Goods"
        },
        {
            "category":"Home & Garden",
            "subcategory":"Furniture",
            "type":"Retail Goods"
        }
    ],
    "sg:phone":"+1 973 293 7237",
    "sg:postcode":"07827",
    "sg:province":"NJ",
    "sg:tags":[
        "top",
        "counter"
    ],
    "wof:name":"Thompson Stone",
    "wof:placetype":"venue"
},
  "geometry": {"coordinates":[-74.79168300000001,41.285417],"type":"Point"}
}