{
  "type": "Feature",
  "properties": {
    "addr:full":"223 Hale St Pennington NJ 08534",
    "addr:housenumber":"223",
    "addr:postcode":"08534",
    "addr:street":"Hale St",
    "iso:country":"US",
    "sg:address":"223 Hale St",
    "sg:city":"Pennington",
    "sg:classifiers":[
        {
            "category":"Building & Trades",
            "subcategory":"Construction",
            "type":"Services"
        }
    ],
    "sg:phone":"+1 609 466 0852",
    "sg:postcode":"08534",
    "sg:province":"NJ",
    "sg:tags":[
        "house"
    ],
    "wof:name":"James R Bartholomew",
    "wof:placetype":"venue"
},
  "geometry": {"coordinates":[-74.79491,40.322178],"type":"Point"}
}