{
  "type": "Feature",
  "properties": {
    "iso:country":"US",
    "sg:address":"1519 Lincoln Ave",
    "sg:city":"Pompton Lakes",
    "sg:classifiers":[
        {
            "category":"Freight",
            "type":"Transportation"
        }
    ],
    "sg:phone":"+1 973 831 4031",
    "sg:postcode":"07442",
    "sg:province":"NJ",
    "sg:tags":[
        "trucking"
    ],
    "wof:name":"D & J Transport Inc",
    "wof:placetype":"venue"
},
  "geometry": {"coordinates":[-74.283028,40.984299],"type":"Point"}
}