{
  "type": "Feature",
  "properties": {
    "iso:country":"US",
    "sg:address":"31 Hoffman Rd",
    "sg:city":"Monroe Twp",
    "sg:classifiers":[
        {
            "category":"Building & Trades",
            "subcategory":"Plumbing",
            "type":"Services"
        }
    ],
    "sg:phone":"+1 732 446 3688",
    "sg:postcode":"08831",
    "sg:province":"NJ",
    "sg:tags":[
        "conditioning",
        "air",
        "system",
        "contractor"
    ],
    "wof:name":"Ultra-Tech Heating & Cooling",
    "wof:placetype":"venue"
},
  "geometry": {"coordinates":[-74.383464,40.311371],"type":"Point"}
}