{
  "type": "Feature",
  "properties": {
    "addr:full":"1075 Stone Harbor Blvd Stone Harbor NJ 08247",
    "addr:housenumber":"1075",
    "addr:postcode":"08247",
    "addr:street":"Stone Harbor Blvd",
    "iso:country":"US",
    "sg:address":"1075 Stone Harbor Blvd",
    "sg:city":"Stone Harbor",
    "sg:classifiers":[
        {
            "category":"Museum",
            "type":"Entertainment"
        }
    ],
    "sg:phone":"+1 609 368 1211",
    "sg:postcode":"08247",
    "sg:province":"NJ",
    "wof:name":"Wetlands Institute the",
    "wof:placetype":"venue"
},
  "geometry": {"coordinates":[-74.7724,39.061199],"type":"Point"}
}