{
  "type": "Feature",
  "properties": {
    "addr:full":"776 River Rd Fair Haven NJ 07704",
    "addr:housenumber":"776",
    "addr:postcode":"07704",
    "addr:street":"River Rd",
    "iso:country":"US",
    "sg:address":"776 River Rd",
    "sg:city":"Fair Haven",
    "sg:classifiers":[
        {
            "category":"Retail",
            "subcategory":"Repair Shop",
            "type":"Services"
        }
    ],
    "sg:phone":"+1 732 842 7330",
    "sg:postcode":"07704",
    "sg:province":"NJ",
    "wof:name":"Frame It Yourself",
    "wof:placetype":"venue"
},
  "geometry": {"coordinates":[-74.034683,40.364702],"type":"Point"}
}