{
  "type": "Feature",
  "properties": {
    "addr:full":"25 Elisa Ln Clark NJ 07066",
    "addr:housenumber":"25",
    "addr:postcode":"07066",
    "addr:street":"Elisa Ln",
    "iso:country":"US",
    "sg:address":"25 Elisa Ln",
    "sg:city":"Clark",
    "sg:classifiers":[
        {
            "category":"Shopping",
            "subcategory":"Clothing, Apparel, & Fashions",
            "type":"Retail Goods"
        }
    ],
    "sg:phone":"+1   ",
    "sg:postcode":"07066",
    "sg:province":"NJ",
    "wof:name":"Booth Sixty Two",
    "wof:placetype":"venue"
},
  "geometry": {"coordinates":[-74.31231099999999,40.61686],"type":"Point"}
}