{
  "type": "Feature",
  "properties": {
    "iso:country":"US",
    "sg:address":"24 Buckingham Dr",
    "sg:city":"Asbury Park",
    "sg:classifiers":[
        {
            "category":"Professional",
            "type":"Services"
        }
    ],
    "sg:phone":"+1   ",
    "sg:postcode":"07712",
    "sg:province":"NJ",
    "wof:name":"Bib Lactation Services LLC",
    "wof:placetype":"venue"
},
  "geometry": {"coordinates":[-74.070965,40.243651],"type":"Point"}
}