{
  "type": "Feature",
  "properties": {
    "addr:full":"31 N Broad St Ridgewood NJ 07450",
    "addr:housenumber":"31",
    "addr:postcode":"07450",
    "addr:street":"N Broad St",
    "iso:country":"US",
    "sg:address":"31 N Broad St",
    "sg:city":"Ridgewood",
    "sg:classifiers":[
        {
            "category":"Recreation",
            "type":"Entertainment"
        }
    ],
    "sg:phone":"+1 201 447 9595",
    "sg:postcode":"07450",
    "sg:province":"NJ",
    "wof:name":"U S Martial Arts College",
    "wof:placetype":"venue"
},
  "geometry": {"coordinates":[-74.11995400000001,40.980732],"type":"Point"}
}