{
  "type": "Feature",
  "properties": {
    "iso:country":"US",
    "sg:address":"14 Pleasant View Rd",
    "sg:city":"Lebanon",
    "sg:classifiers":[
        {
            "category":"Manufacturing",
            "subcategory":"Food",
            "type":"Manufacturing & Wholesale Goods"
        }
    ],
    "sg:phone":"+1 908 437 0299",
    "sg:postcode":"08833",
    "sg:province":"NJ",
    "sg:tags":[
        "mfg"
    ],
    "wof:name":"Pleasant View Winery LLC",
    "wof:placetype":"venue"
},
  "geometry": {"coordinates":[-74.83957700000001,40.583578],"type":"Point"}
}