{
  "type": "Feature",
  "properties": {
    "addr:full":"108 Broad St Flemington NJ 08822",
    "addr:housenumber":"108",
    "addr:postcode":"08822",
    "addr:street":"Broad St",
    "iso:country":"US",
    "sg:address":"108 Broad St",
    "sg:city":"Flemington",
    "sg:classifiers":[
        {
            "category":"Real Estate",
            "subcategory":"Real Estate Agent",
            "type":"Services"
        }
    ],
    "sg:phone":"+1 908 782 6161",
    "sg:postcode":"08822",
    "sg:province":"NJ",
    "wof:name":"X Broker Of Real Estate LLC",
    "wof:placetype":"venue"
},
  "geometry": {"coordinates":[-74.85583200000001,40.506634],"type":"Point"}
}