{
  "type": "Feature",
  "properties": {
    "iso:country":"US",
    "sg:address":"76 US Hwy 206",
    "sg:city":"Andover",
    "sg:classifiers":[
        {
            "category":"Manufacturing",
            "subcategory":"Food",
            "type":"Manufacturing & Wholesale Goods"
        }
    ],
    "sg:phone":"+1 973 786 5354",
    "sg:postcode":"07821",
    "sg:province":"NJ",
    "sg:tags":[
        "mfg",
        "raw",
        "cane",
        "sugar"
    ],
    "wof:name":"Clark Hill Inc",
    "wof:placetype":"venue"
},
  "geometry": {"coordinates":[-74.739028,40.976629],"type":"Point"}
}