{
  "type": "Feature",
  "properties": {
    "iso:country":"US",
    "sg:address":"1520 Atlantic Ave",
    "sg:city":"Atlantic City",
    "sg:classifiers":[
        {
            "category":"Professional",
            "type":"Services"
        }
    ],
    "sg:phone":"+1   ",
    "sg:postcode":"08401",
    "sg:province":"NJ",
    "wof:name":"Mohammed J Hosen",
    "wof:placetype":"venue"
},
  "geometry": {"coordinates":[-74.430368,39.361136],"type":"Point"}
}