{
  "type": "Feature",
  "properties": {
    "addr:full":"704 Kings Hwy Haddon Heights NJ 08035",
    "addr:housenumber":"704",
    "addr:postcode":"08035",
    "addr:street":"Kings Hwy",
    "iso:country":"US",
    "sg:address":"704 Kings Hwy",
    "sg:city":"Haddon Heights",
    "sg:classifiers":[
        {
            "category":"Organizations",
            "subcategory":"Religious Organization",
            "type":"Services"
        }
    ],
    "sg:phone":"+1 856 547 0564",
    "sg:postcode":"08035",
    "sg:province":"NJ",
    "wof:name":"St Rose of Lima Church",
    "wof:placetype":"venue"
},
  "geometry": {"coordinates":[-75.064206,39.884761],"type":"Point"}
}