{
  "type": "Feature",
  "properties": {
    "iso:country":"US",
    "sg:address":"401 S Clinton Ave",
    "sg:city":"Trenton",
    "sg:classifiers":[
        {
            "category":"Shopping",
            "subcategory":"Used Merchandise",
            "type":"Retail Goods"
        }
    ],
    "sg:phone":"+1   ",
    "sg:postcode":"08609",
    "sg:province":"NJ",
    "wof:name":"Sigmund Kardas Consultant",
    "wof:placetype":"venue"
},
  "geometry": {"coordinates":[-74.75412300000001,40.21438],"type":"Point"}
}