{
  "type": "Feature",
  "properties": {
    "iso:country":"US",
    "sg:address":"1329 Hurffville Rd",
    "sg:city":"Deptford",
    "sg:classifiers":[
        {
            "category":"Recreation",
            "type":"Entertainment"
        }
    ],
    "sg:phone":"+1 856 374 1144",
    "sg:postcode":"08096",
    "sg:province":"NJ",
    "sg:tags":[
        "martial",
        "arts",
        "instruction"
    ],
    "wof:name":"Katai Martial Arts Academy",
    "wof:placetype":"venue"
},
  "geometry": {"coordinates":[-75.090761,39.821251],"type":"Point"}
}