{
  "type": "Feature",
  "properties": {
    "addr:full":"35 Brunswick Woods Dr East Brunswick NJ 08816",
    "addr:housenumber":"35",
    "addr:postcode":"08816",
    "addr:street":"Brunswick Woods Dr",
    "iso:country":"US",
    "sg:address":"35 Brunswick Woods Dr",
    "sg:city":"East Brunswick",
    "sg:classifiers":[
        {
            "category":"Retail",
            "subcategory":"Self-service Laundry",
            "type":"Services"
        }
    ],
    "sg:phone":"+1 732 254 1116",
    "sg:postcode":"08816",
    "sg:province":"NJ",
    "sg:tags":[
        "coin",
        "laundromat"
    ],
    "wof:name":"One Stop Laundry",
    "wof:placetype":"venue"
},
  "geometry": {"coordinates":[-74.39151699999999,40.421039],"type":"Point"}
}