{
  "type": "Feature",
  "properties": {
    "iso:country":"US",
    "sg:address":"632 E 23rd St",
    "sg:city":"Paterson",
    "sg:classifiers":[
        {
            "category":"Autos & Motor Vehicles",
            "subcategory":"Auto Supplies",
            "type":"Retail Goods"
        }
    ],
    "sg:phone":"+1 973 204 6955",
    "sg:postcode":"07514",
    "sg:province":"NJ",
    "sg:tags":[
        "tire"
    ],
    "wof:name":"Jersey Tire & Wheel",
    "wof:placetype":"venue"
},
  "geometry": {"coordinates":[-74.151353,40.918833],"type":"Point"}
}