{
  "type": "Feature",
  "properties": {
    "addr:full":"535 Dowd Ave Elizabeth NJ 07201",
    "addr:housenumber":"535",
    "addr:postcode":"07201",
    "addr:street":"Dowd Ave",
    "iso:country":"US",
    "sg:address":"535 Dowd Ave",
    "sg:city":"Elizabeth",
    "sg:classifiers":[
        {
            "category":"Wholesale",
            "subcategory":"Groceries",
            "type":"Manufacturing & Wholesale Goods"
        }
    ],
    "sg:phone":"+1 908 787 1997",
    "sg:postcode":"07201",
    "sg:province":"NJ",
    "sg:tags":[
        "beverage"
    ],
    "wof:name":"National Beverage Distrib",
    "wof:placetype":"venue"
},
  "geometry": {"coordinates":[-74.187512,40.666419],"type":"Point"}
}