{
  "type": "Feature",
  "properties": {
    "iso:country":"US",
    "sg:address":"40 Sandhill Rd",
    "sg:city":"Blairstown",
    "sg:classifiers":[
        {
            "category":"Building & Trades",
            "subcategory":"Construction",
            "type":"Services"
        }
    ],
    "sg:phone":"+1 908 362 0155",
    "sg:postcode":"07825",
    "sg:province":"NJ",
    "sg:tags":[
        "handyman"
    ],
    "wof:name":"Community Handyman Svc",
    "wof:placetype":"venue"
},
  "geometry": {"coordinates":[-75.01342200000001,40.962349],"type":"Point"}
}