{
  "type": "Feature",
  "properties": {
    "iso:country":"US",
    "sg:address":"1635 Brunswick Ave",
    "sg:city":"Trenton",
    "sg:classifiers":[
        {
            "category":"Health Services",
            "subcategory":"Chiropractor",
            "type":"Services"
        }
    ],
    "sg:phone":"+1   ",
    "sg:postcode":"08648",
    "sg:province":"NJ",
    "wof:name":"Robert B Wittenborn DC",
    "wof:placetype":"venue"
},
  "geometry": {"coordinates":[-74.73993400000001,40.247222],"type":"Point"}
}