{
  "type": "Feature",
  "properties": {
    "iso:country":"US",
    "sg:address":"7 Hasler Ln",
    "sg:city":"Little Silver",
    "sg:classifiers":[
        {
            "category":"Health Services",
            "subcategory":"Doctor",
            "type":"Services"
        }
    ],
    "sg:phone":"+1   ",
    "sg:postcode":"07739",
    "sg:province":"NJ",
    "sg:tags":[
        "medical"
    ],
    "wof:name":"John S Greco MD Inc",
    "wof:placetype":"venue"
},
  "geometry": {"coordinates":[-74.039528,40.344615],"type":"Point"}
}