{
  "type": "Feature",
  "properties": {
    "iso:country":"US",
    "sg:address":"4546 Bergenline Ave",
    "sg:city":"Union City",
    "sg:classifiers":[
        {
            "category":"Real Estate",
            "subcategory":"Real Estate Services",
            "type":"Services"
        }
    ],
    "sg:phone":"+1 201 865 6066",
    "sg:postcode":"07087",
    "sg:province":"NJ",
    "sg:tags":[
        "management",
        "property"
    ],
    "wof:name":"C & C West New York",
    "wof:placetype":"venue"
},
  "geometry": {"coordinates":[-74.022863,40.780087],"type":"Point"}
}