{
  "type": "Feature",
  "properties": {
    "iso:country":"US",
    "sg:address":"54 2nd Ave",
    "sg:city":"Long Branch",
    "sg:classifiers":[
        {
            "category":"Building & Trades",
            "subcategory":"Construction",
            "type":"Services"
        }
    ],
    "sg:phone":"+1 732 728 9666",
    "sg:postcode":"07740",
    "sg:province":"NJ",
    "sg:tags":[
        "contractor"
    ],
    "wof:name":"Bianco Development Corp",
    "wof:placetype":"venue"
},
  "geometry": {"coordinates":[-73.98293700000001,40.303485],"type":"Point"}
}