{
  "type": "Feature",
  "properties": {
    "iso:country":"US",
    "sg:address":"84 Broad St",
    "sg:city":"Keyport",
    "sg:classifiers":[
        {
            "category":"Organizations",
            "subcategory":"Religious Organization",
            "type":"Services"
        }
    ],
    "sg:phone":"+1 732 264 6310",
    "sg:postcode":"07735",
    "sg:province":"NJ",
    "sg:tags":[
        "church"
    ],
    "wof:name":"Christian Science Society",
    "wof:placetype":"venue"
},
  "geometry": {"coordinates":[-74.20192299999999,40.437291],"type":"Point"}
}