{
  "type": "Feature",
  "properties": {
    "iso:country":"US",
    "sg:address":"69 Mackerly Rd",
    "sg:city":"Newton",
    "sg:classifiers":[
        {
            "category":"Education",
            "subcategory":"School",
            "type":"Public Place"
        }
    ],
    "sg:phone":"+1 973 383 6666",
    "sg:postcode":"07860",
    "sg:province":"NJ",
    "wof:name":"Green Twp School",
    "wof:placetype":"venue"
},
  "geometry": {"coordinates":[-74.79768300000001,40.985854],"type":"Point"}
}