{
  "type": "Feature",
  "properties": {
    "addr:full":"943 Bloomfield St Hoboken NJ 07030",
    "addr:housenumber":"943",
    "addr:postcode":"07030",
    "addr:street":"Bloomfield St",
    "iso:country":"US",
    "sg:address":"943 Bloomfield St",
    "sg:city":"Hoboken",
    "sg:classifiers":[
        {
            "category":"Banks & Credit Unions",
            "subcategory":"Financial Services",
            "type":"Services"
        }
    ],
    "sg:phone":"+1   ",
    "sg:postcode":"07030",
    "sg:province":"NJ",
    "sg:tags":[
        "investment",
        "closed"
    ],
    "wof:name":"Candlestick Capital LLC",
    "wof:placetype":"venue"
},
  "geometry": {"coordinates":[-74.02838,40.748141],"type":"Point"}
}