{
  "type": "Feature",
  "properties": {
    "iso:country":"US",
    "sg:address":"306 2nd Ave",
    "sg:city":"Elizabeth",
    "sg:classifiers":[
        {
            "category":"Real Estate",
            "subcategory":"Real Estate Agent",
            "type":"Services"
        }
    ],
    "sg:phone":"+1   ",
    "sg:postcode":"07206",
    "sg:province":"NJ",
    "wof:name":"D B F Properties LLC",
    "wof:placetype":"venue"
},
  "geometry": {"coordinates":[-74.197778,40.648674],"type":"Point"}
}