{
  "type": "Feature",
  "properties": {
    "iso:country":"US",
    "sg:address":"57 Central Pkwy",
    "sg:city":"Bayville",
    "sg:classifiers":[
        {
            "category":"Education",
            "subcategory":"School",
            "type":"Public Place"
        }
    ],
    "sg:phone":"+1   ",
    "sg:postcode":"08721",
    "sg:province":"NJ",
    "sg:website":"www.cbw.bayville.nj.us",
    "wof:name":"Clara B Worth Elementary Schl",
    "wof:placetype":"venue"
},
  "geometry": {"coordinates":[-74.16699199999999,39.891371],"type":"Point"}
}