{
  "type": "Feature",
  "properties": {
    "addr:full":"1041 State Rte 18 East Brunswick NJ 08816",
    "addr:housenumber":"1041",
    "addr:postcode":"08816",
    "addr:street":"State Rte 18",
    "iso:country":"US",
    "sg:address":"1041 State Rte 18",
    "sg:city":"East Brunswick",
    "sg:classifiers":[
        {
            "category":"Autos & Motor Vehicles",
            "subcategory":"Automobile Sales",
            "type":"Retail Goods"
        }
    ],
    "sg:phone":"+1   ",
    "sg:postcode":"08816",
    "sg:province":"NJ",
    "wof:name":"Ryan Motors of Morristown Inc",
    "wof:placetype":"venue"
},
  "geometry": {"coordinates":[-74.389832,40.42218],"type":"Point"}
}