{
  "type": "Feature",
  "properties": {
    "iso:country":"US",
    "sg:address":"27 S Kinderkamack Rd",
    "sg:city":"Montvale",
    "sg:classifiers":[
        {
            "category":"Restaurant",
            "type":"Food & Drink"
        }
    ],
    "sg:menulink":"http://www.allmenus.com/nj/montvale/208444-taco-bell/menu/",
    "sg:phone":"+1 201 722 0404",
    "sg:postcode":"07645",
    "sg:province":"NJ",
    "sg:tags":[
        "mexican"
    ],
    "wof:name":"Taco Bell",
    "wof:placetype":"venue"
},
  "geometry": {"coordinates":[-74.02876999999999,41.043294],"type":"Point"}
}