{
  "type": "Feature",
  "properties": {
    "iso:country":"US",
    "sg:address":"7 Laurelwood Dr",
    "sg:city":"Bernardsville",
    "sg:classifiers":[
        {
            "category":"Professional",
            "type":"Services"
        }
    ],
    "sg:phone":"+1   ",
    "sg:postcode":"07924",
    "sg:province":"NJ",
    "wof:name":"Kathleen Earley",
    "wof:placetype":"venue"
},
  "geometry": {"coordinates":[-74.583167,40.715772],"type":"Point"}
}