{
  "type": "Feature",
  "properties": {
    "iso:country":"US",
    "sg:address":"61 Sterling St",
    "sg:city":"Franklin",
    "sg:classifiers":[
        {
            "category":"Retail",
            "subcategory":"Repair Shop",
            "type":"Services"
        }
    ],
    "sg:phone":"+1 973 209 8677",
    "sg:postcode":"07416",
    "sg:province":"NJ",
    "wof:name":"Doctor Pete Inc",
    "wof:placetype":"venue"
},
  "geometry": {"coordinates":[-74.57897,41.127933],"type":"Point"}
}