{
  "type": "Feature",
  "properties": {
    "iso:country":"US",
    "sg:address":"3851 Boardwalk",
    "sg:city":"Atlantic City",
    "sg:classifiers":[
        {
            "category":"Real Estate",
            "subcategory":"Real Estate Operator",
            "type":"Services"
        }
    ],
    "sg:phone":"+1   ",
    "sg:postcode":"08401",
    "sg:province":"NJ",
    "sg:tags":[
        "property",
        "lessor"
    ],
    "wof:name":"L S Latz Assoc LLC",
    "wof:placetype":"venue"
},
  "geometry": {"coordinates":[-74.45399,39.348524],"type":"Point"}
}