{
  "type": "Feature",
  "properties": {
    "addr:full":"449 E 18th St Paterson NJ 07524",
    "addr:housenumber":"449",
    "addr:postcode":"07524",
    "addr:street":"E 18Th St",
    "iso:country":"US",
    "sg:address":"449 E 18th St",
    "sg:city":"Paterson",
    "sg:classifiers":[
        {
            "category":"Wholesale",
            "subcategory":"Painting Supplies",
            "type":"Manufacturing & Wholesale Goods"
        },
        {
            "category":"Home & Garden",
            "subcategory":"Garden Supply",
            "type":"Retail Goods"
        },
        {
            "category":"Wholesale",
            "subcategory":"Construction Materials",
            "type":"Manufacturing & Wholesale Goods"
        },
        {
            "category":"Home & Garden",
            "subcategory":"Hardware",
            "type":"Retail Goods"
        }
    ],
    "sg:phone":"+1 973 279 0711",
    "sg:postcode":"07524",
    "sg:province":"NJ",
    "sg:tags":[
        "lawn",
        "paint",
        "equipment",
        "part",
        "plumbing",
        "fixtures",
        "store"
    ],
    "sg:website":"http://www.truevalue.com/neilhardware",
    "wof:name":"Neil Hardware",
    "wof:placetype":"venue"
},
  "geometry": {"coordinates":[-74.153778,40.924511],"type":"Point"}
}