{
  "type": "Feature",
  "properties": {
    "addr:full":"527 Pepperidge Tree Ln Kinnelon NJ 07405",
    "addr:housenumber":"527",
    "addr:postcode":"07405",
    "addr:street":"Pepperidge Tree Ln",
    "iso:country":"US",
    "sg:address":"527 Pepperidge Tree Ln",
    "sg:city":"Kinnelon",
    "sg:classifiers":[
        {
            "category":"Bakery",
            "type":"Food & Drink"
        }
    ],
    "sg:phone":"+1 973 214 3193",
    "sg:postcode":"07405",
    "sg:province":"NJ",
    "sg:tags":[
        "cake",
        "pastry",
        "wedding"
    ],
    "wof:name":"Just Cakes And A Few Pies",
    "wof:placetype":"venue"
},
  "geometry": {"coordinates":[-74.409081,41.019391],"type":"Point"}
}