{
  "type": "Feature",
  "properties": {
    "addr:full":"1053 Chimes Ter Vineland NJ 08360",
    "addr:housenumber":"1053",
    "addr:postcode":"08360",
    "addr:street":"Chimes Ter",
    "iso:country":"US",
    "sg:address":"1053 Chimes Ter",
    "sg:city":"Vineland",
    "sg:classifiers":[
        {
            "category":"Travel",
            "subcategory":"Travel Agent",
            "type":"Entertainment"
        }
    ],
    "sg:phone":"+1 856 696 3297",
    "sg:postcode":"08360",
    "sg:province":"NJ",
    "sg:tags":[
        "operator",
        "tour"
    ],
    "wof:name":"BJ Tours & Marketing Inc",
    "wof:placetype":"venue"
},
  "geometry": {"coordinates":[-75.046493,39.477175],"type":"Point"}
}