{
  "type": "Feature",
  "properties": {
    "addr:full":"869 Madison Ave Paterson NJ 07501",
    "addr:housenumber":"869",
    "addr:postcode":"07501",
    "addr:street":"Madison Ave",
    "iso:country":"US",
    "sg:address":"869 Madison Ave",
    "sg:city":"Paterson",
    "sg:classifiers":[
        {
            "category":"Professional",
            "subcategory":"Accounting & Tax Preparation",
            "type":"Services"
        }
    ],
    "sg:phone":"+1 973 357 9997",
    "sg:postcode":"07501",
    "sg:province":"NJ",
    "sg:tags":[
        "return",
        "filing"
    ],
    "wof:name":"Kenny's Tax Svc",
    "wof:placetype":"venue"
},
  "geometry": {"coordinates":[-74.156036,40.911121],"type":"Point"}
}