{
  "type": "Feature",
  "properties": {
    "iso:country":"US",
    "sg:address":"329 Main Rd",
    "sg:city":"Montville",
    "sg:classifiers":[
        {
            "category":"Health Services",
            "subcategory":"Doctor",
            "type":"Services"
        }
    ],
    "sg:phone":"+1   ",
    "sg:postcode":"07045",
    "sg:province":"NJ",
    "sg:tags":[
        "clinic",
        "medical"
    ],
    "wof:name":"H Patrick Burns MD",
    "wof:placetype":"venue"
},
  "geometry": {"coordinates":[-74.367456,40.915196],"type":"Point"}
}