{
  "type": "Feature",
  "properties": {
    "iso:country":"US",
    "sg:address":"43 Conestoga Trl",
    "sg:city":"Sparta",
    "sg:classifiers":[
        {
            "category":"Manufacturing",
            "subcategory":"Tools & Machinery",
            "type":"Manufacturing & Wholesale Goods"
        }
    ],
    "sg:phone":"+1 973 729 8061",
    "sg:postcode":"07871",
    "sg:province":"NJ",
    "sg:tags":[
        "equipment",
        "mfg"
    ],
    "wof:name":"Nicde Corp",
    "wof:placetype":"venue"
},
  "geometry": {"coordinates":[-74.62958399999999,41.017148],"type":"Point"}
}