{
  "type": "Feature",
  "properties": {
    "addr:full":"10 Kings Hwy E Haddonfield NJ 08033",
    "addr:housenumber":"10",
    "addr:postcode":"08033",
    "addr:street":"Kings Hwy E",
    "iso:country":"US",
    "sg:address":"10 Kings Hwy E",
    "sg:city":"Haddonfield",
    "sg:classifiers":[
        {
            "category":"Personal",
            "subcategory":"Barber",
            "type":"Services"
        }
    ],
    "sg:phone":"+1 856 795 7405",
    "sg:postcode":"08033",
    "sg:province":"NJ",
    "sg:tags":[
        "shop"
    ],
    "wof:name":"Caravelli Brothers",
    "wof:placetype":"venue"
},
  "geometry": {"coordinates":[-75.03468100000001,39.896606],"type":"Point"}
}