{
  "type": "Feature",
  "properties": {
    "iso:country":"US",
    "sg:address":"108 Alden St",
    "sg:city":"Cranford",
    "sg:classifiers":[
        {
            "category":"Health Services",
            "subcategory":"Clinic",
            "type":"Services"
        },
        {
            "category":"Social Services",
            "type":"Services"
        }
    ],
    "sg:phone":"+1 908 497 3968",
    "sg:postcode":"07016",
    "sg:province":"NJ",
    "sg:tags":[
        "organization",
        "welfare",
        "specialty",
        "outpatient"
    ],
    "sg:website":"www.ccsnewark.org",
    "wof:name":"Mt Carmel Guild Mental Health",
    "wof:placetype":"venue"
},
  "geometry": {"coordinates":[-74.305964,40.657925],"type":"Point"}
}