{
  "type": "Feature",
  "properties": {
    "iso:country":"US",
    "sg:address":"2 E Side Dr",
    "sg:city":"Newton",
    "sg:classifiers":[
        {
            "category":"Building & Trades",
            "subcategory":"Construction",
            "type":"Services"
        }
    ],
    "sg:phone":"+1 973 579 6707",
    "sg:postcode":"07860",
    "sg:province":"NJ",
    "sg:tags":[
        "wallcoverings-installation",
        "wallpaper",
        "painting",
        "contractor"
    ],
    "wof:name":"Gallagher's Painting & Papering",
    "wof:placetype":"venue"
},
  "geometry": {"coordinates":[-74.812668,41.081379],"type":"Point"}
}