{
  "type": "Feature",
  "properties": {
    "addr:full":"62 Booraem Ave Jersey City NJ 07307",
    "addr:housenumber":"62",
    "addr:postcode":"07307",
    "addr:street":"Booraem Ave",
    "iso:country":"US",
    "sg:address":"62 Booraem Ave",
    "sg:city":"Jersey City",
    "sg:classifiers":[
        {
            "category":"Local Transit",
            "type":"Transportation"
        }
    ],
    "sg:phone":"+1 201 451 5298",
    "sg:postcode":"07307",
    "sg:province":"NJ",
    "sg:tags":[
        "passenger",
        "limousine"
    ],
    "wof:name":"Stratford Limousine Service",
    "wof:placetype":"venue"
},
  "geometry": {"coordinates":[-74.04778899999999,40.738732],"type":"Point"}
}