{
  "type": "Feature",
  "properties": {
    "addr:full":"712 E Bay Ave Manahawkin NJ 08050",
    "addr:housenumber":"712",
    "addr:postcode":"08050",
    "addr:street":"E Bay Ave",
    "iso:country":"US",
    "sg:address":"712 E Bay Ave",
    "sg:city":"Manahawkin",
    "sg:classifiers":[
        {
            "category":"Shopping",
            "subcategory":"Department Store",
            "type":"Retail Goods"
        }
    ],
    "sg:phone":"+1 609 597 1201",
    "sg:postcode":"08050",
    "sg:province":"NJ",
    "wof:name":"Reynolds Specialty Store",
    "wof:placetype":"venue"
},
  "geometry": {"coordinates":[-74.237351,39.685311],"type":"Point"}
}