{
  "type": "Feature",
  "properties": {
    "addr:full":"119 Centre St Metuchen NJ 08840",
    "addr:housenumber":"119",
    "addr:postcode":"08840",
    "addr:street":"Centre St",
    "iso:country":"US",
    "sg:address":"119 Centre St",
    "sg:city":"Metuchen",
    "sg:classifiers":[
        {
            "category":"Building & Trades",
            "subcategory":"Construction",
            "type":"Services"
        }
    ],
    "sg:phone":"+1 732 494 1414",
    "sg:postcode":"08840",
    "sg:province":"NJ",
    "sg:tags":[
        "house"
    ],
    "wof:name":"Joneseys Home Improvement",
    "wof:placetype":"venue"
},
  "geometry": {"coordinates":[-74.367125,40.544357],"type":"Point"}
}