{
  "type": "Feature",
  "properties": {
    "iso:country":"US",
    "sg:address":"123 W Mount Pleasant Ave",
    "sg:city":"Livingston",
    "sg:classifiers":[
        {
            "category":"Shopping",
            "subcategory":"Gifts & Souvenirs",
            "type":"Retail Goods"
        }
    ],
    "sg:phone":"+1 973 992 4033",
    "sg:postcode":"07039",
    "sg:province":"NJ",
    "sg:tags":[
        "announcement",
        "invitation"
    ],
    "sg:website":"www.allthebestinvitations.com",
    "wof:name":"All The Best Invitations",
    "wof:placetype":"venue"
},
  "geometry": {"coordinates":[-74.32082200000001,40.795064],"type":"Point"}
}