{
  "type": "Feature",
  "properties": {
    "addr:full":"66 Evergreen Dr Willingboro NJ 08046",
    "addr:housenumber":"66",
    "addr:postcode":"08046",
    "addr:street":"Evergreen Dr",
    "iso:country":"US",
    "sg:address":"66 Evergreen Dr",
    "sg:city":"Willingboro",
    "sg:classifiers":[
        {
            "category":"Organizations",
            "subcategory":"Religious Organization",
            "type":"Services"
        }
    ],
    "sg:phone":"+1 609 877 6557",
    "sg:postcode":"08046",
    "sg:province":"NJ",
    "sg:tags":[
        "clergy"
    ],
    "wof:name":"J R Bishop",
    "wof:placetype":"venue"
},
  "geometry": {"coordinates":[-74.86885100000001,40.015469],"type":"Point"}
}