{
  "type": "Feature",
  "properties": {
    "iso:country":"US",
    "sg:address":"276 Lafayette Pl",
    "sg:city":"Englewood",
    "sg:classifiers":[
        {
            "category":"Food & Beverages",
            "subcategory":"Groceries & Convenience Stores",
            "type":"Retail Goods"
        }
    ],
    "sg:phone":"+1 201 541 4066",
    "sg:postcode":"07631",
    "sg:province":"NJ",
    "wof:name":"Stop & Go Deli-Atm",
    "wof:placetype":"venue"
},
  "geometry": {"coordinates":[-73.99024,40.890286],"type":"Point"}
}