{
  "type": "Feature",
  "properties": {
    "addr:full":"680 N Beers St Holmdel NJ 07733",
    "addr:housenumber":"680",
    "addr:postcode":"07733",
    "addr:street":"N Beers St",
    "iso:country":"US",
    "sg:address":"680 N Beers St",
    "sg:city":"Holmdel",
    "sg:classifiers":[
        {
            "category":"Shopping",
            "type":"Retail Goods"
        }
    ],
    "sg:phone":"+1   ",
    "sg:postcode":"07733",
    "sg:province":"NJ",
    "sg:tags":[
        "merchandise"
    ],
    "wof:name":"Phillips Pool Supply",
    "wof:placetype":"venue"
},
  "geometry": {"coordinates":[-74.194766,40.409135],"type":"Point"}
}