{
  "type": "Feature",
  "properties": {
    "iso:country":"US",
    "sg:address":"379 Grove St",
    "sg:city":"Newark",
    "sg:classifiers":[
        {
            "category":"Deli",
            "type":"Food & Drink"
        },
        {
            "category":"Food & Beverages",
            "subcategory":"Bakery",
            "type":"Retail Goods"
        }
    ],
    "sg:phone":"+1 973 900 6017",
    "sg:postcode":"07103",
    "sg:province":"NJ",
    "sg:tags":[
        "sandwich"
    ],
    "wof:name":"American Deli Grove",
    "wof:placetype":"venue"
},
  "geometry": {"coordinates":[-74.210865,40.744215],"type":"Point"}
}