{
  "type": "Feature",
  "properties": {
    "addr:full":"124 Little Falls Rd Fairfield NJ 07004",
    "addr:housenumber":"124",
    "addr:postcode":"07004",
    "addr:street":"Little Falls Rd",
    "iso:country":"US",
    "sg:address":"124 Little Falls Rd",
    "sg:city":"Fairfield",
    "sg:classifiers":[
        {
            "category":"Professional",
            "subcategory":"Advertising",
            "type":"Services"
        }
    ],
    "sg:phone":"+1 973 439 0646",
    "sg:postcode":"07004",
    "sg:province":"NJ",
    "wof:name":"Northeast On Line",
    "wof:placetype":"venue"
},
  "geometry": {"coordinates":[-74.27196499999999,40.888787],"type":"Point"}
}