{
  "type": "Feature",
  "properties": {
    "addr:full":"11 Commerce Dr Cranford NJ 07016",
    "addr:housenumber":"11",
    "addr:postcode":"07016",
    "addr:street":"Commerce Dr",
    "iso:country":"US",
    "sg:address":"11 Commerce Dr",
    "sg:city":"Cranford",
    "sg:classifiers":[
        {
            "category":"Professional",
            "type":"Services"
        }
    ],
    "sg:phone":"+1 908 931 9499",
    "sg:postcode":"07016",
    "sg:province":"NJ",
    "sg:tags":[
        "establishment"
    ],
    "wof:name":"Lawrence & Walsh",
    "wof:placetype":"venue"
},
  "geometry": {"coordinates":[-74.28476499999999,40.647868],"type":"Point"}
}