{
  "type": "Feature",
  "properties": {
    "iso:country":"US",
    "sg:address":"19 Louise Ln",
    "sg:city":"Tenafly",
    "sg:classifiers":[
        {
            "category":"Communications",
            "subcategory":"Radio Station",
            "type":"Services"
        }
    ],
    "sg:phone":"+1 201 569 2654",
    "sg:postcode":"07670",
    "sg:province":"NJ",
    "sg:tags":[
        "broadcast"
    ],
    "wof:name":"Laska LLC",
    "wof:placetype":"venue"
},
  "geometry": {"coordinates":[-73.973393,40.918648],"type":"Point"}
}