{
  "type": "Feature",
  "properties": {
    "addr:full":"99 New Bridge Rd Bergenfield NJ 07621",
    "addr:housenumber":"99",
    "addr:postcode":"07621",
    "addr:street":"New Bridge Rd",
    "iso:country":"US",
    "sg:address":"99 New Bridge Rd",
    "sg:city":"Bergenfield",
    "sg:classifiers":[
        {
            "category":"Health Services",
            "subcategory":"Doctor",
            "type":"Services"
        }
    ],
    "sg:phone":"+1 201 384 5941",
    "sg:postcode":"07621",
    "sg:province":"NJ",
    "sg:tags":[
        "surgeon",
        "oral"
    ],
    "wof:name":"DO Young T DDS",
    "wof:placetype":"venue"
},
  "geometry": {"coordinates":[-74.001198,40.914001],"type":"Point"}
}