{
  "type": "Feature",
  "properties": {
    "addr:full":"114 W Franklin Ave Pennington NJ 08534",
    "addr:housenumber":"114",
    "addr:postcode":"08534",
    "addr:street":"W Franklin Ave",
    "iso:country":"US",
    "sg:address":"114 W Franklin Ave",
    "sg:city":"Pennington",
    "sg:classifiers":[
        {
            "category":"Personal",
            "type":"Services"
        }
    ],
    "sg:phone":"+1   ",
    "sg:postcode":"08534",
    "sg:province":"NJ",
    "wof:name":"Body Logic Massage Therapy",
    "wof:placetype":"venue"
},
  "geometry": {"coordinates":[-74.7998,40.33167],"type":"Point"}
}