{
  "type": "Feature",
  "properties": {
    "iso:country":"US",
    "sg:address":"199 Warbler Dr",
    "sg:city":"Wayne",
    "sg:classifiers":[
        {
            "category":"Home & Garden",
            "subcategory":"Garden Supply",
            "type":"Retail Goods"
        }
    ],
    "sg:phone":"+1   ",
    "sg:postcode":"07470",
    "sg:province":"NJ",
    "sg:tags":[
        "plant",
        "hydroponic"
    ],
    "wof:name":"Hyrponic Plant Gallery",
    "wof:placetype":"venue"
},
  "geometry": {"coordinates":[-74.20619499999999,40.955217],"type":"Point"}
}