{
  "type": "Feature",
  "properties": {
    "addr:full":"2 Wallace Rd Princeton Jct NJ 08550",
    "addr:housenumber":"2",
    "addr:postcode":"08550",
    "addr:street":"Wallace Rd",
    "iso:country":"US",
    "sg:address":"2 Wallace Rd",
    "sg:city":"Princeton Jct",
    "sg:classifiers":[
        {
            "category":"Restaurant",
            "type":"Food & Drink"
        }
    ],
    "sg:phone":"+1 609 799 8844",
    "sg:postcode":"08550",
    "sg:province":"NJ",
    "sg:tags":[
        "eating"
    ],
    "wof:name":"En Route",
    "wof:placetype":"venue"
},
  "geometry": {"coordinates":[-74.62308299999999,40.31541],"type":"Point"}
}