{
  "type": "Feature",
  "properties": {
    "addr:full":"207 Parker Ave Clifton NJ 07011",
    "addr:housenumber":"207",
    "addr:postcode":"07011",
    "addr:street":"Parker Ave",
    "iso:country":"US",
    "sg:address":"207 Parker Ave",
    "sg:city":"Clifton",
    "sg:classifiers":[
        {
            "category":"Utilities",
            "subcategory":"Mobile Phone",
            "type":"Services"
        }
    ],
    "sg:phone":"+1 973 246 7117",
    "sg:postcode":"07011",
    "sg:province":"NJ",
    "sg:tags":[
        "telephone",
        "cellular"
    ],
    "wof:name":"Selena Wireless",
    "wof:placetype":"venue"
},
  "geometry": {"coordinates":[-74.12335400000001,40.87481],"type":"Point"}
}