{
  "type": "Feature",
  "properties": {
    "iso:country":"US",
    "sg:address":"504 Chestnut St",
    "sg:city":"Riverside",
    "sg:classifiers":[
        {
            "category":"Building & Trades",
            "subcategory":"Electrical",
            "type":"Services"
        }
    ],
    "sg:phone":"+1 856 764 0344",
    "sg:postcode":"08075",
    "sg:province":"NJ",
    "sg:tags":[
        "electrical",
        "contractor"
    ],
    "wof:name":"Lenny Schmierer Electric",
    "wof:placetype":"venue"
},
  "geometry": {"coordinates":[-74.96734600000001,40.0252],"type":"Point"}
}