{
  "type": "Feature",
  "properties": {
    "addr:full":"321 Broad Ave Ste 9 Ridgefield NJ 07657",
    "addr:housenumber":"321",
    "addr:postcode":"07657",
    "addr:street":"Broad Ave Ste 9",
    "iso:country":"US",
    "sg:address":"321 Broad Ave Ste 9",
    "sg:city":"Ridgefield",
    "sg:classifiers":[
        {
            "category":"Home & Garden",
            "subcategory":"Carpets & Floor Coverings",
            "type":"Retail Goods"
        }
    ],
    "sg:phone":"+1 201 945 9944",
    "sg:postcode":"07657",
    "sg:province":"NJ",
    "sg:tags":[
        "mattress"
    ],
    "wof:name":"Jang Soo Furnishings",
    "wof:placetype":"venue"
},
  "geometry": {"coordinates":[-74.009309,40.825165],"type":"Point"}
}