{
  "type": "Feature",
  "properties": {
    "addr:full":"1606 Lauckson Pl Point Pleasant Beach NJ 08742",
    "addr:housenumber":"1606",
    "addr:postcode":"08742",
    "addr:street":"Lauckson Pl",
    "iso:country":"US",
    "sg:address":"1606 Lauckson Pl",
    "sg:city":"Point Pleasant Beach",
    "sg:classifiers":[
        {
            "category":"Building & Trades",
            "subcategory":"Construction",
            "type":"Services"
        }
    ],
    "sg:phone":"+1 732 714 0376",
    "sg:postcode":"08742",
    "sg:province":"NJ",
    "sg:tags":[
        "house"
    ],
    "wof:name":"J Michael Homes LLC New Jersey",
    "wof:placetype":"venue"
},
  "geometry": {"coordinates":[-74.081591,40.068528],"type":"Point"}
}