{
  "type": "Feature",
  "properties": {
    "addr:full":"301 Madison Ave Lakewood NJ 08701",
    "addr:housenumber":"301",
    "addr:postcode":"08701",
    "addr:street":"Madison Ave",
    "iso:country":"US",
    "sg:address":"301 Madison Ave",
    "sg:city":"Lakewood",
    "sg:classifiers":[
        {
            "category":"Social Services",
            "type":"Services"
        },
        {
            "category":"Organizations",
            "subcategory":"Community Association",
            "type":"Services"
        }
    ],
    "sg:phone":"+1 732 363 0530",
    "sg:postcode":"08701",
    "sg:province":"NJ",
    "sg:tags":[
        "welfare"
    ],
    "wof:name":"Jewish Federation Ocean County",
    "wof:placetype":"venue"
},
  "geometry": {"coordinates":[-74.216792,40.092907],"type":"Point"}
}