{
  "type": "Feature",
  "properties": {
    "addr:full":"4 Turkey Hill Rd Boonton NJ 07005",
    "addr:housenumber":"4",
    "addr:postcode":"07005",
    "addr:street":"Turkey Hill Rd",
    "iso:country":"US",
    "sg:address":"4 Turkey Hill Rd",
    "sg:city":"Boonton",
    "sg:classifiers":[
        {
            "category":"Professional",
            "subcategory":"Research",
            "type":"Services"
        }
    ],
    "sg:phone":"+1 973 402 9625",
    "sg:postcode":"07005",
    "sg:province":"NJ",
    "sg:tags":[
        "nonphysical",
        "commercial"
    ],
    "wof:name":"Tactical Automotive Solutions",
    "wof:placetype":"venue"
},
  "geometry": {"coordinates":[-74.389253,40.935643],"type":"Point"}
}