{
  "type": "Feature",
  "properties": {
    "iso:country":"US",
    "sg:address":"806 State Rte 17",
    "sg:city":"Ramsey",
    "sg:classifiers":[
        {
            "category":"Personal",
            "subcategory":"Beauty Salon",
            "type":"Services"
        }
    ],
    "sg:phone":"+1 201 825 3900",
    "sg:postcode":"07446",
    "sg:province":"NJ",
    "sg:tags":[
        "spa",
        "day"
    ],
    "wof:name":"Ajina Health Svc",
    "wof:placetype":"venue"
},
  "geometry": {"coordinates":[-74.12889,41.064446],"type":"Point"}
}