{
  "type": "Feature",
  "properties": {
    "addr:full":"181 Boulevard Hasbrouck Heights NJ 07604",
    "addr:housenumber":"181",
    "addr:postcode":"07604",
    "addr:street":"Boulevard",
    "iso:country":"US",
    "sg:address":"181 Boulevard",
    "sg:city":"Hasbrouck Heights",
    "sg:classifiers":[
        {
            "category":"Professional",
            "subcategory":"Accounting & Tax Preparation",
            "type":"Services"
        }
    ],
    "sg:phone":"+1 201 393 0330",
    "sg:postcode":"07604",
    "sg:province":"NJ",
    "sg:tags":[
        "accountant"
    ],
    "wof:name":"Failla Theodore CPA",
    "wof:placetype":"venue"
},
  "geometry": {"coordinates":[-74.079498,40.860699],"type":"Point"}
}