{
  "type": "Feature",
  "properties": {
    "iso:country":"US",
    "sg:address":"39 Highview Ave",
    "sg:city":"Park Ridge",
    "sg:classifiers":[
        {
            "category":"Building & Trades",
            "subcategory":"Construction",
            "type":"Services"
        }
    ],
    "sg:phone":"+1 201 391 7991",
    "sg:postcode":"07656",
    "sg:province":"NJ",
    "sg:tags":[
        "contractor"
    ],
    "wof:name":"MSC Construction Corp",
    "wof:placetype":"venue"
},
  "geometry": {"coordinates":[-74.03143,41.032811],"type":"Point"}
}