{
  "type": "Feature",
  "properties": {
    "iso:country":"US",
    "sg:address":"2240 74th St",
    "sg:city":"North Bergen",
    "sg:classifiers":[
        {
            "category":"Personal",
            "type":"Services"
        }
    ],
    "sg:phone":"+1 201 662 7900",
    "sg:postcode":"07047",
    "sg:province":"NJ",
    "sg:tags":[
        "station",
        "container",
        "freight"
    ],
    "wof:name":"Arrowpac International Inc",
    "wof:placetype":"venue"
},
  "geometry": {"coordinates":[-74.02085099999999,40.803309],"type":"Point"}
}