{
  "type": "Feature",
  "properties": {
    "addr:full":"4 Smalley Ave Middlesex NJ 08846",
    "addr:housenumber":"4",
    "addr:postcode":"08846",
    "addr:street":"Smalley Ave",
    "iso:country":"US",
    "sg:address":"4 Smalley Ave",
    "sg:city":"Middlesex",
    "sg:classifiers":[
        {
            "category":"Retail",
            "subcategory":"Laundry & Dry Cleaning",
            "type":"Services"
        }
    ],
    "sg:phone":"+1 732 752 8907",
    "sg:postcode":"08846",
    "sg:province":"NJ",
    "sg:tags":[
        "cleaners"
    ],
    "wof:name":"Cpv Drying Svc Inc",
    "wof:placetype":"venue"
},
  "geometry": {"coordinates":[-74.475008,40.586932],"type":"Point"}
}