{
  "type": "Feature",
  "properties": {
    "iso:country":"US",
    "sg:address":"455 8th St",
    "sg:city":"Gloucester City",
    "sg:classifiers":[
        {
            "category":"Building & Trades",
            "subcategory":"Electrical",
            "type":"Services"
        }
    ],
    "sg:phone":"+1 856 742 5337",
    "sg:postcode":"08030",
    "sg:province":"NJ",
    "sg:tags":[
        "electric",
        "contractor"
    ],
    "wof:name":"Matter Brothers Electric Cntr",
    "wof:placetype":"venue"
},
  "geometry": {"coordinates":[-75.124405,39.88942],"type":"Point"}
}