{
  "type": "Feature",
  "properties": {
    "addr:full":"189 Ross Ave Hackensack NJ 07601",
    "addr:housenumber":"189",
    "addr:postcode":"07601",
    "addr:street":"Ross Ave",
    "iso:country":"US",
    "sg:address":"189 Ross Ave",
    "sg:city":"Hackensack",
    "sg:classifiers":[
        {
            "category":"Building & Trades",
            "subcategory":"Construction",
            "type":"Services"
        }
    ],
    "sg:phone":"+1 201 678 9252",
    "sg:postcode":"07601",
    "sg:province":"NJ",
    "sg:tags":[
        "hanging",
        "contractor"
    ],
    "wof:name":"Regal Painting Inc",
    "wof:placetype":"venue"
},
  "geometry": {"coordinates":[-74.046964,40.900693],"type":"Point"}
}