{
  "type": "Feature",
  "properties": {
    "iso:country":"US",
    "sg:address":"376 Bloomfield Ave",
    "sg:city":"Caldwell",
    "sg:classifiers":[
        {
            "category":"Health Services",
            "subcategory":"Doctor",
            "type":"Services"
        }
    ],
    "sg:phone":"+1 973 226 2263",
    "sg:postcode":"07006",
    "sg:province":"NJ",
    "sg:tags":[
        "podiatrist"
    ],
    "wof:name":"Caldwell Podiatry Center",
    "wof:placetype":"venue"
},
  "geometry": {"coordinates":[-74.278164,40.840611],"type":"Point"}
}