{
  "type": "Feature",
  "properties": {
    "iso:country":"US",
    "sg:address":"113 Lincoln Ave",
    "sg:city":"Dunellen",
    "sg:classifiers":[
        {
            "category":"Professional",
            "subcategory":"Accounting & Tax Preparation",
            "type":"Services"
        }
    ],
    "sg:phone":"+1 732 926 9099",
    "sg:postcode":"08812",
    "sg:province":"NJ",
    "sg:tags":[
        "consultant"
    ],
    "wof:name":"Lujansa Express",
    "wof:placetype":"venue"
},
  "geometry": {"coordinates":[-74.466067,40.591051],"type":"Point"}
}