{
  "type": "Feature",
  "properties": {
    "iso:country":"US",
    "sg:address":"759 Lafayette Ave",
    "sg:city":"Hawthorne",
    "sg:classifiers":[
        {
            "category":"Personal",
            "subcategory":"Beauty Salon",
            "type":"Services"
        }
    ],
    "sg:phone":"+1 973 427 9519",
    "sg:postcode":"07506",
    "sg:province":"NJ",
    "wof:name":"Hair'n Now",
    "wof:placetype":"venue"
},
  "geometry": {"coordinates":[-74.156487,40.96442],"type":"Point"}
}