{
  "type": "Feature",
  "properties": {
    "iso:country":"US",
    "sg:address":"501 Main St",
    "sg:city":"Asbury Park",
    "sg:classifiers":[
        {
            "category":"Retail",
            "subcategory":"Self-service Laundry",
            "type":"Services"
        }
    ],
    "sg:phone":"+1 732 869 0340",
    "sg:postcode":"07712",
    "sg:province":"NJ",
    "sg:tags":[
        "coin"
    ],
    "wof:name":"Laundry Zone",
    "wof:placetype":"venue"
},
  "geometry": {"coordinates":[-74.012345,40.218883],"type":"Point"}
}