{
  "type": "Feature",
  "properties": {
    "iso:country":"US",
    "sg:address":"158 Belmont Ave",
    "sg:city":"Belleville",
    "sg:classifiers":[
        {
            "category":"Building & Trades",
            "subcategory":"Construction",
            "type":"Services"
        },
        {
            "category":"Wholesale",
            "subcategory":"Metals & Minerals",
            "type":"Manufacturing & Wholesale Goods"
        }
    ],
    "sg:phone":"+1 973 751 4338",
    "sg:postcode":"07109",
    "sg:province":"NJ",
    "sg:tags":[
        "ornamental",
        "work",
        "iron",
        "contractor"
    ],
    "wof:name":"Baldi Rocco Iron Works",
    "wof:placetype":"venue"
},
  "geometry": {"coordinates":[-74.181499,40.780114],"type":"Point"}
}