{
  "type": "Feature",
  "properties": {
    "iso:country":"US",
    "sg:address":"354 Eisenhower Pkwy",
    "sg:city":"Livingston",
    "sg:classifiers":[
        {
            "category":"Real Estate",
            "subcategory":"Real Estate Agent",
            "type":"Services"
        }
    ],
    "sg:phone":"+1   ",
    "sg:postcode":"07039",
    "sg:province":"NJ",
    "sg:tags":[
        "realtor",
        "arr",
        "mortgage",
        "broker",
        "manager",
        "property"
    ],
    "wof:name":"Punia Company LLC",
    "wof:placetype":"venue"
},
  "geometry": {"coordinates":[-74.33864199999999,40.808139],"type":"Point"}
}