{
  "type": "Feature",
  "properties": {
    "addr:full":"67 Willowbrook Blvd Wayne NJ 07470",
    "addr:housenumber":"67",
    "addr:postcode":"07470",
    "addr:street":"Willowbrook Blvd",
    "iso:country":"US",
    "sg:address":"67 Willowbrook Blvd",
    "sg:city":"Wayne",
    "sg:classifiers":[
        {
            "category":"Professional",
            "subcategory":"Advertising",
            "type":"Services"
        }
    ],
    "sg:phone":"+1 973 837 9367",
    "sg:postcode":"07470",
    "sg:province":"NJ",
    "sg:tags":[
        "counselor"
    ],
    "wof:name":"Ad Space Network",
    "wof:placetype":"venue"
},
  "geometry": {"coordinates":[-74.251058,40.88857],"type":"Point"}
}