{
  "type": "Feature",
  "properties": {
    "iso:country":"US",
    "sg:address":"7 Old Quarry Rd",
    "sg:city":"Cedar Grove",
    "sg:classifiers":[
        {
            "category":"Real Estate",
            "subcategory":"Architect",
            "type":"Services"
        }
    ],
    "sg:phone":"+1 973 746 3571",
    "sg:postcode":"07009",
    "sg:province":"NJ",
    "wof:name":"Valk Gerard Architect",
    "wof:placetype":"venue"
},
  "geometry": {"coordinates":[-74.21779600000001,40.848301],"type":"Point"}
}