{
  "type": "Feature",
  "properties": {
    "addr:full":"173 Washington Pl Hasbrouck Heights NJ 07604",
    "addr:housenumber":"173",
    "addr:postcode":"07604",
    "addr:street":"Washington Pl",
    "iso:country":"US",
    "sg:address":"173 Washington Pl",
    "sg:city":"Hasbrouck Heights",
    "sg:classifiers":[
        {
            "category":"Insurance",
            "subcategory":"Insurance Agent",
            "type":"Services"
        }
    ],
    "sg:phone":"+1   ",
    "sg:postcode":"07604",
    "sg:province":"NJ",
    "wof:name":"J R Insurance Services",
    "wof:placetype":"venue"
},
  "geometry": {"coordinates":[-74.077671,40.865202],"type":"Point"}
}