{
  "type": "Feature",
  "properties": {
    "addr:full":"85 W Palisade Ave Englewood NJ 07631",
    "addr:housenumber":"85",
    "addr:postcode":"07631",
    "addr:street":"W Palisade Ave",
    "iso:country":"US",
    "sg:address":"85 W Palisade Ave",
    "sg:city":"Englewood",
    "sg:classifiers":[
        {
            "category":"Professional",
            "subcategory":"Business Services",
            "type":"Services"
        }
    ],
    "sg:phone":"+1   ",
    "sg:postcode":"07631",
    "sg:province":"NJ",
    "wof:name":"ZAI Express",
    "wof:placetype":"venue"
},
  "geometry": {"coordinates":[-73.979378,40.896587],"type":"Point"}
}