{
  "type": "Feature",
  "properties": {
    "addr:full":"323 Sweetmans Ln Perrineville NJ 08535",
    "addr:housenumber":"323",
    "addr:postcode":"08535",
    "addr:street":"Sweetmans Ln",
    "iso:country":"US",
    "sg:address":"323 Sweetmans Ln",
    "sg:city":"Perrineville",
    "sg:classifiers":[
        {
            "category":"Farming",
            "subcategory":"Livestock Farm",
            "type":"Manufacturing & Wholesale Goods"
        }
    ],
    "sg:phone":"+1 732 446 9900",
    "sg:postcode":"08535",
    "sg:province":"NJ",
    "sg:tags":[
        "equine"
    ],
    "wof:name":"Golden Gait Farm Inc",
    "wof:placetype":"venue"
},
  "geometry": {"coordinates":[-74.42250799999999,40.223586],"type":"Point"}
}