{
  "type": "Feature",
  "properties": {
    "iso:country":"US",
    "sg:address":"943 Sergeantsville Rd",
    "sg:city":"Stockton",
    "sg:classifiers":[
        {
            "category":"Travel",
            "subcategory":"Hotels & Motels",
            "type":"Entertainment"
        }
    ],
    "sg:phone":"+1 609 397 4678",
    "sg:postcode":"08559",
    "sg:province":"NJ",
    "sg:tags":[
        "operation"
    ],
    "wof:name":"Remax Cottages Castles",
    "wof:placetype":"venue"
},
  "geometry": {"coordinates":[-74.96679,40.416022],"type":"Point"}
}