{
  "type": "Feature",
  "properties": {
    "addr:full":"52 Blaine St Passaic NJ 07055",
    "addr:housenumber":"52",
    "addr:postcode":"07055",
    "addr:street":"Blaine St",
    "iso:country":"US",
    "sg:address":"52 Blaine St",
    "sg:city":"Passaic",
    "sg:classifiers":[
        {
            "category":"Manufacturing",
            "subcategory":"Textiles",
            "type":"Manufacturing & Wholesale Goods"
        }
    ],
    "sg:phone":"+1 201 925 7767",
    "sg:postcode":"07055",
    "sg:province":"NJ",
    "sg:tags":[
        "knit"
    ],
    "wof:name":"Gold Knitting Inc",
    "wof:placetype":"venue"
},
  "geometry": {"coordinates":[-74.14118499999999,40.854506],"type":"Point"}
}