{
  "type": "Feature",
  "properties": {
    "iso:country":"US",
    "sg:address":"64 Congress St",
    "sg:city":"Newark",
    "sg:classifiers":[
        {
            "category":"Personal",
            "subcategory":"Beauty Salon",
            "type":"Services"
        }
    ],
    "sg:phone":"+1 973 690 5119",
    "sg:postcode":"07105",
    "sg:province":"NJ",
    "wof:name":"Sao Beauty Salon",
    "wof:placetype":"venue"
},
  "geometry": {"coordinates":[-74.162881,40.729491],"type":"Point"}
}