{
  "type": "Feature",
  "properties": {
    "iso:country":"US",
    "sg:address":"251 Middle Rd",
    "sg:city":"Hazlet",
    "sg:classifiers":[
        {
            "category":"Education",
            "subcategory":"Library",
            "type":"Public Place"
        }
    ],
    "sg:phone":"+1   ",
    "sg:postcode":"07730",
    "sg:province":"NJ",
    "sg:tags":[
        "executive"
    ],
    "wof:name":"Monmouth County Library",
    "wof:placetype":"venue"
},
  "geometry": {"coordinates":[-74.17596500000001,40.427248],"type":"Point"}
}