{
  "type": "Feature",
  "properties": {
    "addr:full":"142 Union Ave New Providence NJ 07974",
    "addr:housenumber":"142",
    "addr:postcode":"07974",
    "addr:street":"Union Ave",
    "iso:country":"US",
    "sg:address":"142 Union Ave",
    "sg:city":"New Providence",
    "sg:classifiers":[
        {
            "category":"Building & Trades",
            "subcategory":"Construction",
            "type":"Services"
        }
    ],
    "sg:phone":"+1 908 790 9266",
    "sg:postcode":"07974",
    "sg:province":"NJ",
    "sg:tags":[
        "house"
    ],
    "wof:name":"Augustine Construction Inc",
    "wof:placetype":"venue"
},
  "geometry": {"coordinates":[-74.418586,40.691593],"type":"Point"}
}