{
  "type": "Feature",
  "properties": {
    "iso:country":"US",
    "sg:address":"2 Chamberlin Ct",
    "sg:city":"Cranbury",
    "sg:classifiers":[
        {
            "category":"Shopping",
            "subcategory":"Clothing, Apparel, & Fashions",
            "type":"Retail Goods"
        }
    ],
    "sg:phone":"+1   ",
    "sg:postcode":"08512",
    "sg:province":"NJ",
    "wof:name":"Dorli Bridal & Tailor",
    "wof:placetype":"venue"
},
  "geometry": {"coordinates":[-74.516595,40.300656],"type":"Point"}
}