{
  "type": "Feature",
  "properties": {
    "addr:full":"360 Hurst St Linden NJ 07036",
    "addr:housenumber":"360",
    "addr:postcode":"07036",
    "addr:street":"Hurst St",
    "iso:country":"US",
    "sg:address":"360 Hurst St",
    "sg:city":"Linden",
    "sg:classifiers":[
        {
            "category":"Manufacturing",
            "subcategory":"Printing",
            "type":"Manufacturing & Wholesale Goods"
        }
    ],
    "sg:phone":"+1 908 523 0555",
    "sg:postcode":"07036",
    "sg:province":"NJ",
    "sg:tags":[
        "publisher"
    ],
    "wof:name":"Son Schein Sales Inc",
    "wof:placetype":"venue"
},
  "geometry": {"coordinates":[-74.26878600000001,40.620569],"type":"Point"}
}