{
  "type": "Feature",
  "properties": {
    "addr:full":"165 US Highway 46 Rockaway NJ 07866",
    "addr:housenumber":"165",
    "addr:postcode":"07866",
    "addr:street":"Us Highway 46",
    "iso:country":"US",
    "sg:address":"165 US Highway 46",
    "sg:city":"Rockaway",
    "sg:classifiers":[
        {
            "category":"Sports & Exercise",
            "subcategory":"Gym",
            "type":"Entertainment"
        }
    ],
    "sg:phone":"+1 973 586 7003",
    "sg:postcode":"07866",
    "sg:province":"NJ",
    "sg:tags":[
        "trainer"
    ],
    "wof:name":"A Plus Fitness Services Llc",
    "wof:placetype":"venue"
},
  "geometry": {"coordinates":[-74.506897,40.893398],"type":"Point"}
}