{
  "type": "Feature",
  "properties": {
    "iso:country":"US",
    "sg:address":"2029 Ingalls Ave",
    "sg:city":"Linden",
    "sg:classifiers":[
        {
            "category":"Local Transit",
            "type":"Transportation"
        }
    ],
    "sg:phone":"+1 908 468 7752",
    "sg:postcode":"07036",
    "sg:province":"NJ",
    "sg:tags":[
        "passenger"
    ],
    "wof:name":"Prime Time Limousine Svc",
    "wof:placetype":"venue"
},
  "geometry": {"coordinates":[-74.233873,40.653187],"type":"Point"}
}