{
  "type": "Feature",
  "properties": {
    "iso:country":"US",
    "sg:address":"57 Willard St",
    "sg:city":"Lodi",
    "sg:classifiers":[
        {
            "category":"Building & Trades",
            "subcategory":"Plumbing",
            "type":"Services"
        }
    ],
    "sg:phone":"+1 973 340 7200",
    "sg:postcode":"07644",
    "sg:province":"NJ",
    "sg:tags":[
        "plumbing",
        "heating",
        "contractor"
    ],
    "wof:name":"Acqua Pure Plumbing & Heating",
    "wof:placetype":"venue"
},
  "geometry": {"coordinates":[-74.09335,40.878144],"type":"Point"}
}