{
  "type": "Feature",
  "properties": {
    "iso:country":"US",
    "sg:address":"87 W Palisade Ave",
    "sg:city":"Englewood",
    "sg:classifiers":[
        {
            "category":"Shopping",
            "subcategory":"Party Supplies",
            "type":"Retail Goods"
        },
        {
            "category":"Personal",
            "type":"Services"
        }
    ],
    "sg:phone":"+1 201 567 2659",
    "sg:postcode":"07631",
    "sg:province":"NJ",
    "sg:tags":[
        "delivery",
        "balloon",
        "balloons-retail",
        "decorator"
    ],
    "wof:name":"Fiesta Party Supply",
    "wof:placetype":"venue"
},
  "geometry": {"coordinates":[-73.97829299999999,40.895914],"type":"Point"}
}