{
  "type": "Feature",
  "properties": {
    "iso:country":"US",
    "sg:address":"239 W Sylvania Ave",
    "sg:city":"Neptune",
    "sg:classifiers":[
        {
            "category":"Food & Beverages",
            "subcategory":"Groceries & Convenience Stores",
            "type":"Retail Goods"
        }
    ],
    "sg:phone":"+1 732 774 1749",
    "sg:postcode":"07753",
    "sg:province":"NJ",
    "sg:tags":[
        "grocer"
    ],
    "wof:name":"Pathway Market",
    "wof:placetype":"venue"
},
  "geometry": {"coordinates":[-74.044065,40.204682],"type":"Point"}
}