{
  "type": "Feature",
  "properties": {
    "addr:full":"3425 Coles Mill Rd Franklinville NJ 08322",
    "addr:housenumber":"3425",
    "addr:postcode":"08322",
    "addr:street":"Coles Mill Rd",
    "iso:country":"US",
    "sg:address":"3425 Coles Mill Rd",
    "sg:city":"Franklinville",
    "sg:classifiers":[
        {
            "category":"Professional",
            "subcategory":"Business Services",
            "type":"Services"
        }
    ],
    "sg:phone":"+1 856 629 7977",
    "sg:postcode":"08322",
    "sg:province":"NJ",
    "sg:tags":[
        "water",
        "inspection"
    ],
    "wof:name":"Toncris Mfg picture This",
    "wof:placetype":"venue"
},
  "geometry": {"coordinates":[-75.014307,39.619872],"type":"Point"}
}