{
  "type": "Feature",
  "properties": {
    "iso:country":"US",
    "sg:address":"5605 Chestnut Ave",
    "sg:city":"Vineland",
    "sg:classifiers":[
        {
            "category":"Building & Trades",
            "subcategory":"Cleaning & Sanitation",
            "type":"Services"
        }
    ],
    "sg:phone":"+1 856 507 9202",
    "sg:postcode":"08360",
    "sg:province":"NJ",
    "sg:tags":[
        "ventilating",
        "system"
    ],
    "wof:name":"Iaq Inc",
    "wof:placetype":"venue"
},
  "geometry": {"coordinates":[-74.894524,39.472506],"type":"Point"}
}