{
  "type": "Feature",
  "properties": {
    "addr:full":"38 W Joffre Ave Milltown NJ 08850",
    "addr:housenumber":"38",
    "addr:postcode":"08850",
    "addr:street":"W Joffre Ave",
    "iso:country":"US",
    "sg:address":"38 W Joffre Ave",
    "sg:city":"Milltown",
    "sg:classifiers":[
        {
            "category":"Building & Trades",
            "subcategory":"Construction",
            "type":"Services"
        }
    ],
    "sg:phone":"+1 732 846 0411",
    "sg:postcode":"08850",
    "sg:province":"NJ",
    "sg:tags":[
        "house"
    ],
    "wof:name":"J&M Construction Assoc",
    "wof:placetype":"venue"
},
  "geometry": {"coordinates":[-74.430474,40.440674],"type":"Point"}
}