{
  "type": "Feature",
  "properties": {
    "addr:full":"20 E Redman Ave Haddonfield NJ 08033",
    "addr:housenumber":"20",
    "addr:postcode":"08033",
    "addr:street":"E Redman Ave",
    "iso:country":"US",
    "sg:address":"20 E Redman Ave",
    "sg:city":"Haddonfield",
    "sg:classifiers":[
        {
            "category":"Professional",
            "subcategory":"Research",
            "type":"Services"
        }
    ],
    "sg:phone":"+1 856 216 8080",
    "sg:postcode":"08033",
    "sg:province":"NJ",
    "sg:tags":[
        "foundation",
        "philanthropic"
    ],
    "wof:name":"Knowles Science Teaching Fndtn",
    "wof:placetype":"venue"
},
  "geometry": {"coordinates":[-75.037491,39.901452],"type":"Point"}
}