{
  "type": "Feature",
  "properties": {
    "addr:full":"490 Grand Ave West Trenton NJ 08628",
    "addr:housenumber":"490",
    "addr:postcode":"08628",
    "addr:street":"Grand Ave West",
    "iso:country":"US",
    "sg:address":"490 Grand Ave",
    "sg:city":"West Trenton",
    "sg:classifiers":[
        {
            "category":"Organizations",
            "subcategory":"Religious Organization",
            "type":"Services"
        }
    ],
    "sg:phone":"+1 609 882 3629",
    "sg:postcode":"08628",
    "sg:province":"NJ",
    "sg:tags":[
        "church"
    ],
    "wof:name":"West Trenton Presbyterian Chr",
    "wof:placetype":"venue"
},
  "geometry": {"coordinates":[-74.816782,40.261696],"type":"Point"}
}