{
  "type": "Feature",
  "properties": {
    "iso:country":"US",
    "sg:address":"280 Main St",
    "sg:city":"Keyport",
    "sg:classifiers":[
        {
            "category":"Freight",
            "type":"Transportation"
        }
    ],
    "sg:phone":"+1 732 203 0687",
    "sg:postcode":"07735",
    "sg:province":"NJ",
    "sg:tags":[
        "trucking"
    ],
    "wof:name":"A & G Trucking",
    "wof:placetype":"venue"
},
  "geometry": {"coordinates":[-74.199645,40.429613],"type":"Point"}
}