{
  "type": "Feature",
  "properties": {
    "iso:country":"US",
    "sg:address":"2316 Linden Ave",
    "sg:city":"South Plainfield",
    "sg:classifiers":[
        {
            "category":"Retail",
            "subcategory":"Repair Shop",
            "type":"Services"
        }
    ],
    "sg:phone":"+1   ",
    "sg:postcode":"07080",
    "sg:province":"NJ",
    "wof:name":"Schaible Coil Cleaning Service",
    "wof:placetype":"venue"
},
  "geometry": {"coordinates":[-74.396385,40.593413],"type":"Point"}
}