{
  "type": "Feature",
  "properties": {
    "iso:country":"US",
    "sg:address":"71 S Newman St",
    "sg:city":"Hackensack",
    "sg:classifiers":[
        {
            "category":"Wholesale",
            "subcategory":"Scrap",
            "type":"Manufacturing & Wholesale Goods"
        }
    ],
    "sg:phone":"+1 201 498 0025",
    "sg:postcode":"07601",
    "sg:province":"NJ",
    "sg:tags":[
        "recycling",
        "center"
    ],
    "wof:name":"Environmental Asset Management",
    "wof:placetype":"venue"
},
  "geometry": {"coordinates":[-74.054958,40.877852],"type":"Point"}
}