{
  "type": "Feature",
  "properties": {
    "iso:country":"US",
    "sg:address":"103 Park St",
    "sg:city":"Montclair",
    "sg:classifiers":[
        {
            "category":"Health Services",
            "subcategory":"Doctor",
            "type":"Services"
        }
    ],
    "sg:phone":"+1 973 744 7900",
    "sg:postcode":"07042",
    "sg:province":"NJ",
    "wof:name":"Fischer Evan MD",
    "wof:placetype":"venue"
},
  "geometry": {"coordinates":[-74.213577,40.820824],"type":"Point"}
}