{
  "type": "Feature",
  "properties": {
    "addr:full":"476 Ocean Ave Jersey City NJ 07305",
    "addr:housenumber":"476",
    "addr:postcode":"07305",
    "addr:street":"Ocean Ave",
    "iso:country":"US",
    "sg:address":"476 Ocean Ave",
    "sg:city":"Jersey City",
    "sg:classifiers":[
        {
            "category":"Building & Trades",
            "subcategory":"Locksmith",
            "type":"Services"
        }
    ],
    "sg:phone":"+1 201 793 9089",
    "sg:postcode":"07305",
    "sg:province":"NJ",
    "sg:tags":[
        "key"
    ],
    "wof:name":"Locksmith 01 7 Day Emergency",
    "wof:placetype":"venue"
},
  "geometry": {"coordinates":[-74.081188,40.702601],"type":"Point"}
}