{
  "type": "Feature",
  "properties": {
    "addr:full":"191 Harriot Ave Harrington Park NJ 07640",
    "addr:housenumber":"191",
    "addr:postcode":"07640",
    "addr:street":"Harriot Ave",
    "iso:country":"US",
    "sg:address":"191 Harriot Ave",
    "sg:city":"Harrington Park",
    "sg:classifiers":[
        {
            "category":"Education",
            "subcategory":"School",
            "type":"Public Place"
        }
    ],
    "sg:phone":"+1 201 768 5700",
    "sg:postcode":"07640",
    "sg:province":"NJ",
    "sg:tags":[
        "educational",
        "administrative"
    ],
    "sg:website":"www.hpsd.org",
    "wof:name":"Harrington Park Public School",
    "wof:placetype":"venue"
},
  "geometry": {"coordinates":[-73.98215500000001,40.985861],"type":"Point"}
}