{
  "type": "Feature",
  "properties": {
    "iso:country":"US",
    "sg:address":"241 Monmouth Rd",
    "sg:city":"West Long Branch",
    "sg:classifiers":[
        {
            "category":"Professional",
            "subcategory":"Business Services",
            "type":"Services"
        }
    ],
    "sg:phone":"+1 732 483 0332",
    "sg:postcode":"07764",
    "sg:province":"NJ",
    "wof:name":"United Surgical Partners",
    "wof:placetype":"venue"
},
  "geometry": {"coordinates":[-74.02567500000001,40.289753],"type":"Point"}
}