{
  "type": "Feature",
  "properties": {
    "iso:country":"US",
    "sg:address":"1267 US Highway 22",
    "sg:city":"Mountainside",
    "sg:classifiers":[
        {
            "category":"Food & Beverages",
            "subcategory":"Liquor & Beverages",
            "type":"Retail Goods"
        }
    ],
    "sg:phone":"+1 908 233 1133",
    "sg:postcode":"07092",
    "sg:province":"NJ",
    "sg:tags":[
        "beer",
        "spirit",
        "wine"
    ],
    "wof:name":"Bliwise Liquors",
    "wof:placetype":"venue"
},
  "geometry": {"coordinates":[-74.34850299999999,40.675301],"type":"Point"}
}