{
  "type": "Feature",
  "properties": {
    "iso:country":"US",
    "sg:address":"523 Lincoln Ave",
    "sg:city":"Collingswood",
    "sg:classifiers":[
        {
            "category":"Professional",
            "subcategory":"Accounting & Tax Preparation",
            "type":"Services"
        }
    ],
    "sg:phone":"+1 609 744 6202",
    "sg:postcode":"08108",
    "sg:province":"NJ",
    "wof:name":"Wb Accounting",
    "wof:placetype":"venue"
},
  "geometry": {"coordinates":[-75.062504,39.92014],"type":"Point"}
}