{
  "type": "Feature",
  "properties": {
    "iso:country":"US",
    "sg:address":"60 Pitt Rd",
    "sg:city":"Parsippany",
    "sg:classifiers":[
        {
            "category":"Education",
            "subcategory":"School",
            "type":"Public Place"
        }
    ],
    "sg:phone":"+1 973 263 7075",
    "sg:postcode":"07081",
    "sg:province":"NJ",
    "wof:name":"Intervale Elementary School",
    "wof:placetype":"venue"
},
  "geometry": {"coordinates":[-74.323177,40.697185],"type":"Point"}
}