{
  "type": "Feature",
  "properties": {
    "addr:full":"300 Interpace Pkwy Parsippany NJ 07054",
    "addr:housenumber":"300",
    "addr:postcode":"07054",
    "addr:street":"Interpace Pkwy",
    "iso:country":"US",
    "sg:address":"300 Interpace Pkwy",
    "sg:city":"Parsippany",
    "sg:classifiers":[
        {
            "category":"Real Estate",
            "subcategory":"Real Estate Agent",
            "type":"Services"
        }
    ],
    "sg:phone":"+1 973 335 0311",
    "sg:postcode":"07054",
    "sg:province":"NJ",
    "wof:name":"C B Richard Ellis",
    "wof:placetype":"venue"
},
  "geometry": {"coordinates":[-74.448297,40.86845],"type":"Point"}
}