{
  "type": "Feature",
  "properties": {
    "addr:full":"1016 Kennedy Blvd Bayonne NJ 07002",
    "addr:housenumber":"1016",
    "addr:postcode":"07002",
    "addr:street":"Kennedy Blvd",
    "iso:country":"US",
    "sg:address":"1016 Kennedy Blvd",
    "sg:city":"Bayonne",
    "sg:classifiers":[
        {
            "category":"Shopping",
            "subcategory":"Clothing, Apparel, & Fashions",
            "type":"Retail Goods"
        }
    ],
    "sg:phone":"+1 201 858 2261",
    "sg:postcode":"07002",
    "sg:province":"NJ",
    "sg:tags":[
        "designer"
    ],
    "wof:name":"Birdie Design Inc",
    "wof:placetype":"venue"
},
  "geometry": {"coordinates":[-74.111999,40.681072],"type":"Point"}
}