{
  "type": "Feature",
  "properties": {
    "addr:full":"323 68th St West New York NJ 07093",
    "addr:housenumber":"323",
    "addr:postcode":"nj 07093",
    "addr:street":"68Th St West",
    "iso:country":"US",
    "sg:address":"323 68th St",
    "sg:city":"West New York",
    "sg:classifiers":[
        {
            "category":"Home & Garden",
            "subcategory":"Furniture",
            "type":"Retail Goods"
        }
    ],
    "sg:phone":"+1   ",
    "sg:postcode":"07093",
    "sg:province":"NJ",
    "wof:name":"Bianca Furniture Warehouse",
    "wof:placetype":"venue"
},
  "geometry": {"coordinates":[-74.009793,40.793709],"type":"Point"}
}