{
  "type": "Feature",
  "properties": {
    "iso:country":"US",
    "sg:address":"1934 Arbar Ct",
    "sg:city":"Toms River",
    "sg:classifiers":[
        {
            "category":"Wholesale",
            "subcategory":"Machinery & Supplies",
            "type":"Manufacturing & Wholesale Goods"
        }
    ],
    "sg:phone":"+1 732 557 0957",
    "sg:postcode":"08755",
    "sg:province":"NJ",
    "sg:tags":[
        "industrial"
    ],
    "wof:name":"Nu Tech Surface Systems Inc",
    "wof:placetype":"venue"
},
  "geometry": {"coordinates":[-74.239271,40.021233],"type":"Point"}
}