{
  "type": "Feature",
  "properties": {
    "iso:country":"US",
    "sg:address":"1 Teal Rd",
    "sg:city":"Cape May Ct Hse",
    "sg:classifiers":[
        {
            "category":"Building & Trades",
            "subcategory":"Construction",
            "type":"Services"
        }
    ],
    "sg:phone":"+1 609 465 0512",
    "sg:postcode":"08242",
    "sg:province":"NJ",
    "sg:tags":[
        "home",
        "builder"
    ],
    "wof:name":"Ryan Homes Delaware Farms",
    "wof:placetype":"venue"
},
  "geometry": {"coordinates":[-74.88029299999999,39.021426],"type":"Point"}
}