{
  "type": "Feature",
  "properties": {
    "addr:full":"449 E Main St Denville NJ 07834",
    "addr:housenumber":"449",
    "addr:postcode":"07834",
    "addr:street":"E Main St",
    "iso:country":"US",
    "sg:address":"449 E Main St",
    "sg:city":"Denville",
    "sg:classifiers":[
        {
            "category":"Home & Garden",
            "subcategory":"Furniture",
            "type":"Retail Goods"
        }
    ],
    "sg:phone":"+1   ",
    "sg:postcode":"07834",
    "sg:province":"NJ",
    "sg:tags":[
        "product",
        "woodworking"
    ],
    "wof:name":"J & R Custom Woodworking Inc",
    "wof:placetype":"venue"
},
  "geometry": {"coordinates":[-74.480492,40.877262],"type":"Point"}
}