{
  "type": "Feature",
  "properties": {
    "addr:full":"21 Glouchester Dr Somerset NJ 08873",
    "addr:housenumber":"21",
    "addr:postcode":"08873",
    "addr:street":"Glouchester Dr",
    "iso:country":"US",
    "sg:address":"21 Glouchester Dr",
    "sg:city":"Somerset",
    "sg:classifiers":[
        {
            "category":"Sports & Exercise",
            "subcategory":"Gym",
            "type":"Entertainment"
        }
    ],
    "sg:phone":"+1 732 873 9020",
    "sg:postcode":"08873",
    "sg:province":"NJ",
    "sg:tags":[
        "club",
        "health",
        "studio",
        "gymnasium"
    ],
    "wof:name":"H & A Fitness Ventures",
    "wof:placetype":"venue"
},
  "geometry": {"coordinates":[-74.519485,40.507407],"type":"Point"}
}