{
  "type": "Feature",
  "properties": {
    "addr:full":"741 Teaneck Rd Teaneck NJ 07666",
    "addr:housenumber":"741",
    "addr:postcode":"07666",
    "addr:street":"Teaneck Rd",
    "iso:country":"US",
    "sg:address":"741 Teaneck Rd",
    "sg:city":"Teaneck",
    "sg:classifiers":[
        {
            "category":"Health Services",
            "subcategory":"Doctor",
            "type":"Services"
        }
    ],
    "sg:phone":"+1   ",
    "sg:postcode":"07666",
    "sg:province":"NJ",
    "sg:tags":[
        "medical"
    ],
    "wof:name":"Ignatios Zairis MD",
    "wof:placetype":"venue"
},
  "geometry": {"coordinates":[-74.007395,40.884078],"type":"Point"}
}