{
  "type": "Feature",
  "properties": {
    "addr:full":"505 Boulevard Elmwood Park NJ 07407",
    "addr:housenumber":"505",
    "addr:postcode":"07407",
    "addr:street":"Boulevard",
    "iso:country":"US",
    "sg:address":"505 Boulevard",
    "sg:city":"Elmwood Park",
    "sg:classifiers":[
        {
            "category":"Restaurant",
            "type":"Food & Drink"
        }
    ],
    "sg:phone":"+1 201 703 8811",
    "sg:postcode":"07407",
    "sg:province":"NJ",
    "sg:website":"www.subway.com",
    "wof:name":"Subway Sandwich & Salads",
    "wof:placetype":"venue"
},
  "geometry": {"coordinates":[-74.116203,40.9006],"type":"Point"}
}