{
  "type": "Feature",
  "properties": {
    "addr:full":"9 Main St Sparta NJ 07871",
    "addr:housenumber":"9",
    "addr:postcode":"07871",
    "addr:street":"Main St",
    "iso:country":"US",
    "sg:address":"9 Main St",
    "sg:city":"Sparta",
    "sg:classifiers":[
        {
            "category":"Shopping",
            "subcategory":"Bicycles & Sporting Goods",
            "type":"Retail Goods"
        }
    ],
    "sg:phone":"+1 973 729 7775",
    "sg:postcode":"07871",
    "sg:province":"NJ",
    "wof:name":"Bike Stop",
    "wof:placetype":"venue"
},
  "geometry": {"coordinates":[-74.63599000000001,41.036768],"type":"Point"}
}