{
  "type": "Feature",
  "properties": {
    "iso:country":"US",
    "sg:address":"10 Schley St",
    "sg:city":"Garfield",
    "sg:classifiers":[
        {
            "category":"Building & Trades",
            "subcategory":"Landscaping Services",
            "type":"Services"
        }
    ],
    "sg:phone":"+1 973 546 4355",
    "sg:postcode":"07026",
    "sg:province":"NJ",
    "sg:tags":[
        "landscape",
        "contractor"
    ],
    "wof:name":"Paul's Lawn Svc Inc",
    "wof:placetype":"venue"
},
  "geometry": {"coordinates":[-74.110159,40.879782],"type":"Point"}
}