{
  "type": "Feature",
  "properties": {
    "iso:country":"US",
    "sg:address":"519 Park Ave",
    "sg:city":"Paterson",
    "sg:classifiers":[
        {
            "category":"Restaurant",
            "type":"Food & Drink"
        }
    ],
    "sg:phone":"+1 973 881 1525",
    "sg:postcode":"07504",
    "sg:province":"NJ",
    "sg:tags":[
        "eating",
        "pizza"
    ],
    "wof:name":"Frank & Joe's Pizza",
    "wof:placetype":"venue"
},
  "geometry": {"coordinates":[-74.143097,40.913601],"type":"Point"}
}