{
  "type": "Feature",
  "properties": {
    "iso:country":"US",
    "sg:address":"122 Valley Station Rd",
    "sg:city":"Asbury",
    "sg:classifiers":[
        {
            "category":"Building & Trades",
            "subcategory":"Landscaping Services",
            "type":"Services"
        }
    ],
    "sg:phone":"+1 908 479 6304",
    "sg:postcode":"08802",
    "sg:province":"NJ",
    "sg:tags":[
        "landscape"
    ],
    "wof:name":"River Valley Nursery",
    "wof:placetype":"venue"
},
  "geometry": {"coordinates":[-75.03585099999999,40.671564],"type":"Point"}
}