{
  "type": "Feature",
  "properties": {
    "addr:full":"420 Grand St Jersey City NJ 07302",
    "addr:housenumber":"420",
    "addr:postcode":"07302",
    "addr:street":"Grand St",
    "iso:country":"US",
    "sg:address":"420 Grand St",
    "sg:city":"Jersey City",
    "sg:classifiers":[
        {
            "category":"Restaurant",
            "type":"Food & Drink"
        }
    ],
    "sg:phone":"+1 201 209 0091",
    "sg:postcode":"07302",
    "sg:province":"NJ",
    "wof:name":"Princess Pizza",
    "wof:placetype":"venue"
},
  "geometry": {"coordinates":[-74.053102,40.71707],"type":"Point"}
}