{
  "type": "Feature",
  "properties": {
    "addr:full":"42 Main St Holmdel NJ 07733",
    "addr:housenumber":"42",
    "addr:postcode":"07733",
    "addr:street":"Main St",
    "iso:country":"US",
    "sg:address":"42 Main St",
    "sg:city":"Holmdel",
    "sg:classifiers":[
        {
            "category":"Real Estate",
            "subcategory":"Real Estate Agent",
            "type":"Services"
        }
    ],
    "sg:phone":"+1 732 946 4443",
    "sg:postcode":"07733",
    "sg:province":"NJ",
    "wof:name":"Zellers Agency",
    "wof:placetype":"venue"
},
  "geometry": {"coordinates":[-74.185193,40.345116],"type":"Point"}
}