{
  "type": "Feature",
  "properties": {
    "addr:full":"918 Kings Croft Cherry Hill NJ 08034",
    "addr:housenumber":"918",
    "addr:postcode":"08034",
    "addr:street":"Kings Croft",
    "iso:country":"US",
    "sg:address":"918 Kings Croft",
    "sg:city":"Cherry Hill",
    "sg:classifiers":[
        {
            "category":"Professional",
            "subcategory":"Employment Agencies",
            "type":"Services"
        }
    ],
    "sg:phone":"+1   ",
    "sg:postcode":"08034",
    "sg:province":"NJ",
    "wof:name":"R S V P Services",
    "wof:placetype":"venue"
},
  "geometry": {"coordinates":[-74.98545,39.934752],"type":"Point"}
}