{
  "type": "Feature",
  "properties": {
    "addr:full":"86 Lackawanna Ave Totowa NJ 07512",
    "addr:housenumber":"86",
    "addr:postcode":"07512",
    "addr:street":"Lackawanna Ave",
    "iso:country":"US",
    "sg:address":"86 Lackawanna Ave",
    "sg:city":"Totowa",
    "sg:classifiers":[
        {
            "category":"Building & Trades",
            "subcategory":"Construction",
            "type":"Services"
        }
    ],
    "sg:phone":"+1 973 837 1237",
    "sg:postcode":"07512",
    "sg:province":"NJ",
    "sg:tags":[
        "contractor",
        "product",
        "wood",
        "carpentry",
        "mfg"
    ],
    "wof:name":"Tannous Fine Woodworking",
    "wof:placetype":"venue"
},
  "geometry": {"coordinates":[-74.220912,40.89371],"type":"Point"}
}