{
  "type": "Feature",
  "properties": {
    "addr:full":"59 Greenwood Rd Westwood NJ 07675",
    "addr:housenumber":"59",
    "addr:postcode":"07675",
    "addr:street":"Greenwood Rd",
    "iso:country":"US",
    "sg:address":"59 Greenwood Rd",
    "sg:city":"Westwood",
    "sg:classifiers":[
        {
            "category":"Professional",
            "subcategory":"Management & Consulting",
            "type":"Services"
        }
    ],
    "sg:phone":"+1   ",
    "sg:postcode":"07675",
    "sg:province":"NJ",
    "sg:tags":[
        "business"
    ],
    "wof:name":"R M Pavesi",
    "wof:placetype":"venue"
},
  "geometry": {"coordinates":[-73.979748,41.031276],"type":"Point"}
}