{
  "type": "Feature",
  "properties": {
    "addr:full":"8505 Bergenline Ave North Bergen NJ 07047",
    "addr:housenumber":"8505",
    "addr:postcode":"07047",
    "addr:street":"Bergenline Ave",
    "iso:country":"US",
    "sg:address":"8505 Bergenline Ave",
    "sg:city":"North Bergen",
    "sg:classifiers":[
        {
            "category":"Shopping",
            "subcategory":"Bicycles & Sporting Goods",
            "type":"Retail Goods"
        },
        {
            "category":"Sports & Exercise",
            "subcategory":"Bicycle Rental",
            "type":"Entertainment"
        }
    ],
    "sg:phone":"+1 201 945 2701",
    "sg:postcode":"07047",
    "sg:province":"NJ",
    "sg:tags":[
        "bike"
    ],
    "sg:website":"www.jamesvincentbicycles.com",
    "wof:name":"James Vincent Bicycles",
    "wof:placetype":"venue"
},
  "geometry": {"coordinates":[-74.004204,40.805199],"type":"Point"}
}