{
  "type": "Feature",
  "properties": {
    "iso:country":"US",
    "sg:address":"517 E 1st Ave",
    "sg:city":"Roselle",
    "sg:classifiers":[
        {
            "category":"Retail",
            "subcategory":"Auto Repair",
            "type":"Services"
        }
    ],
    "sg:phone":"+1 908 241 2466",
    "sg:postcode":"07203",
    "sg:province":"NJ",
    "sg:tags":[
        "transmission"
    ],
    "wof:name":"Rays Automatic Transm Svc",
    "wof:placetype":"venue"
},
  "geometry": {"coordinates":[-74.25198899999999,40.661665],"type":"Point"}
}