{
  "type": "Feature",
  "properties": {
    "addr:full":"150 River Rd Montville NJ 07045",
    "addr:housenumber":"150",
    "addr:postcode":"07045",
    "addr:street":"River Rd",
    "iso:country":"US",
    "sg:address":"150 River Rd",
    "sg:city":"Montville",
    "sg:classifiers":[
        {
            "category":"Health Services",
            "subcategory":"Dentist",
            "type":"Services"
        }
    ],
    "sg:phone":"+1 973 334 4114",
    "sg:postcode":"07045",
    "sg:province":"NJ",
    "wof:name":"All Smiles Family Dentistry",
    "wof:placetype":"venue"
},
  "geometry": {"coordinates":[-74.374298,40.9007],"type":"Point"}
}