{
  "type": "Feature",
  "properties": {
    "addr:full":"87 Augusta St South Amboy NJ 08879",
    "addr:postcode":"08879",
    "addr:street":"87 Augusta St",
    "iso:country":"US",
    "sg:address":"87 Augusta St",
    "sg:city":"South Amboy",
    "sg:classifiers":[
        {
            "category":"Building & Trades",
            "subcategory":"Construction",
            "type":"Services"
        }
    ],
    "sg:phone":"+1 732 316 0611",
    "sg:postcode":"08879",
    "sg:province":"NJ",
    "sg:tags":[
        "concrete",
        "contractor"
    ],
    "wof:name":"Thomas Concrete Flooring",
    "wof:placetype":"venue"
},
  "geometry": {"coordinates":[-74.27972200000001,40.48419],"type":"Point"}
}