{
  "type": "Feature",
  "properties": {
    "iso:country":"US",
    "sg:address":"440 Benigno Blvd",
    "sg:city":"Bellmawr",
    "sg:classifiers":[
        {
            "category":"Arts & Performance",
            "subcategory":"Theater",
            "type":"Entertainment"
        }
    ],
    "sg:phone":"+1 856 933 4732",
    "sg:postcode":"08031",
    "sg:province":"NJ",
    "sg:tags":[
        "bureau"
    ],
    "wof:name":"Lodgenet Entertainment",
    "wof:placetype":"venue"
},
  "geometry": {"coordinates":[-75.096182,39.858651],"type":"Point"}
}