{
  "type": "Feature",
  "properties": {
    "addr:full":"46 Newman Springs Rd Red Bank NJ 07701",
    "addr:housenumber":"46",
    "addr:postcode":"07701",
    "addr:street":"Newman Springs Rd",
    "iso:country":"US",
    "sg:address":"46 Newman Springs Rd",
    "sg:city":"Red Bank",
    "sg:classifiers":[
        {
            "category":"Building & Trades",
            "subcategory":"Construction",
            "type":"Services"
        }
    ],
    "sg:phone":"+1 732 219 7767",
    "sg:postcode":"07701",
    "sg:province":"NJ",
    "sg:tags":[
        "general",
        "contractor"
    ],
    "wof:name":"Tomae Construction Corp",
    "wof:placetype":"venue"
},
  "geometry": {"coordinates":[-74.06520399999999,40.338245],"type":"Point"}
}