{
  "type": "Feature",
  "properties": {
    "iso:country":"US",
    "sg:address":"576 Kearny Ave",
    "sg:city":"Kearny",
    "sg:classifiers":[
        {
            "category":"Banks & Credit Unions",
            "subcategory":"Bank",
            "type":"Services"
        }
    ],
    "sg:phone":"+1 201 991 5561",
    "sg:postcode":"07032",
    "sg:province":"NJ",
    "sg:tags":[
        "loan",
        "real estate"
    ],
    "wof:name":"Acceptance Mortgage LLC",
    "wof:placetype":"venue"
},
  "geometry": {"coordinates":[-74.145432,40.769749],"type":"Point"}
}