{
  "type": "Feature",
  "properties": {
    "addr:full":"901 Railroad Ave Spring Lake NJ 07762",
    "addr:housenumber":"901",
    "addr:postcode":"07762",
    "addr:street":"Railroad Ave",
    "iso:country":"US",
    "sg:address":"901 Railroad Ave",
    "sg:city":"Spring Lake",
    "sg:classifiers":[
        {
            "category":"Banks & Credit Unions",
            "subcategory":"Bank",
            "type":"Services"
        }
    ],
    "sg:phone":"+1 732 359 6555",
    "sg:postcode":"07762",
    "sg:province":"NJ",
    "sg:tags":[
        "loan",
        "real estate"
    ],
    "wof:name":"Ben Salem Mortgage",
    "wof:placetype":"venue"
},
  "geometry": {"coordinates":[-74.03544599999999,40.151588],"type":"Point"}
}