{
  "type": "Feature",
  "properties": {
    "addr:full":"656 Anderson Ave Cliffside Park NJ 07010",
    "addr:housenumber":"656",
    "addr:postcode":"07010",
    "addr:street":"Anderson Ave",
    "iso:country":"US",
    "sg:address":"656 Anderson Ave",
    "sg:city":"Cliffside Park",
    "sg:classifiers":[
        {
            "category":"Professional",
            "type":"Services"
        },
        {
            "category":"Professional",
            "subcategory":"Computer Services",
            "type":"Services"
        }
    ],
    "sg:phone":"+1 201 941 4001",
    "sg:postcode":"07010",
    "sg:province":"NJ",
    "sg:tags":[
        "repair"
    ],
    "sg:website":"www.cynabro.com",
    "wof:name":"The Computer",
    "wof:placetype":"venue"
},
  "geometry": {"coordinates":[-73.986952,40.82645],"type":"Point"}
}