{
  "type": "Feature",
  "properties": {
    "iso:country":"US",
    "sg:address":"39 Golf Links Ave",
    "sg:city":"Piscataway",
    "sg:classifiers":[
        {
            "category":"Professional",
            "subcategory":"Engineering",
            "type":"Services"
        }
    ],
    "sg:phone":"+1   ",
    "sg:postcode":"08854",
    "sg:province":"NJ",
    "sg:tags":[
        "control",
        "mfg",
        "installs",
        "system",
        "air",
        "equipment",
        "pollution"
    ],
    "wof:name":"Ray Solv Inc",
    "wof:placetype":"venue"
},
  "geometry": {"coordinates":[-74.470097,40.513446],"type":"Point"}
}