{
  "type": "Feature",
  "properties": {
    "addr:full":"89 Park St Montclair NJ 07042",
    "addr:housenumber":"89",
    "addr:postcode":"07042",
    "addr:street":"Park St",
    "iso:country":"US",
    "sg:address":"89 Park St",
    "sg:city":"Montclair",
    "sg:classifiers":[
        {
            "category":"Utilities",
            "subcategory":"Telephone",
            "type":"Services"
        }
    ],
    "sg:phone":"+1 973 509 8100",
    "sg:postcode":"07042",
    "sg:province":"NJ",
    "sg:tags":[
        "telecommunication"
    ],
    "wof:name":"Telecom Express",
    "wof:placetype":"venue"
},
  "geometry": {"coordinates":[-74.21486299999999,40.819258],"type":"Point"}
}