{
  "type": "Feature",
  "properties": {
    "iso:country":"US",
    "sg:address":"26 W 16th St",
    "sg:city":"Linden",
    "sg:classifiers":[
        {
            "category":"Freight",
            "type":"Transportation"
        }
    ],
    "sg:phone":"+1 908 862 3416",
    "sg:postcode":"07036",
    "sg:province":"NJ",
    "wof:name":"Haeley Moving Corp",
    "wof:placetype":"venue"
},
  "geometry": {"coordinates":[-74.23965,40.622126],"type":"Point"}
}