{
  "type": "Feature",
  "properties": {
    "addr:full":"2016 Morris Ave Union NJ 07083",
    "addr:housenumber":"2016",
    "addr:postcode":"07083",
    "addr:street":"Morris Ave",
    "iso:country":"US",
    "sg:address":"2016 Morris Ave",
    "sg:city":"Union",
    "sg:classifiers":[
        {
            "category":"Food & Beverages",
            "subcategory":"Specialty",
            "type":"Retail Goods"
        }
    ],
    "sg:phone":"+1 908 851 4300",
    "sg:postcode":"07083",
    "sg:province":"NJ",
    "sg:tags":[
        "health",
        "diet"
    ],
    "sg:website":"www.brainybrawn.com",
    "wof:name":"BRAINYBRAWN.COM",
    "wof:placetype":"venue"
},
  "geometry": {"coordinates":[-74.270672,40.696482],"type":"Point"}
}