{
  "type": "Feature",
  "properties": {
    "addr:full":"325 Mechanic St Cape May Court House NJ 08210",
    "addr:housenumber":"325",
    "addr:postcode":"08210",
    "addr:street":"Mechanic St",
    "iso:country":"US",
    "sg:address":"325 Mechanic St",
    "sg:city":"Cape May Court House",
    "sg:classifiers":[
        {
            "category":"Building & Trades",
            "subcategory":"Construction",
            "type":"Services"
        }
    ],
    "sg:phone":"+1 609 465 7877",
    "sg:postcode":"08210",
    "sg:province":"NJ",
    "sg:tags":[
        "contractor"
    ],
    "wof:name":"Beacon Pools and Cnstr Co",
    "wof:placetype":"venue"
},
  "geometry": {"coordinates":[-74.831434,39.085302],"type":"Point"}
}