{
  "type": "Feature",
  "properties": {
    "addr:full":"140 Belford Ave Rutherford NJ 07070",
    "addr:housenumber":"140",
    "addr:postcode":"07070",
    "addr:street":"Belford Ave",
    "iso:country":"US",
    "sg:address":"140 Belford Ave",
    "sg:city":"Rutherford",
    "sg:classifiers":[
        {
            "category":"Professional",
            "type":"Services"
        }
    ],
    "sg:phone":"+1 212 809 5411",
    "sg:postcode":"07070",
    "sg:province":"NJ",
    "sg:tags":[
        "establishment"
    ],
    "wof:name":"Leone Production",
    "wof:placetype":"venue"
},
  "geometry": {"coordinates":[-74.116136,40.836508],"type":"Point"}
}