{
  "type": "Feature",
  "properties": {
    "iso:country":"US",
    "sg:address":"114 Jacksonville Rd",
    "sg:city":"Towaco",
    "sg:classifiers":[
        {
            "category":"Retail",
            "subcategory":"Repair Shop",
            "type":"Services"
        }
    ],
    "sg:phone":"+1   ",
    "sg:postcode":"07082",
    "sg:province":"NJ",
    "sg:tags":[
        "co",
        "marketing",
        "machine",
        "vending",
        "operator",
        "group"
    ],
    "wof:name":"North Star Vending Inc",
    "wof:placetype":"venue"
},
  "geometry": {"coordinates":[-74.336446,40.943624],"type":"Point"}
}