{
  "type": "Feature",
  "properties": {
    "iso:country":"US",
    "sg:address":"3 Campbell Dr",
    "sg:city":"Sussex",
    "sg:classifiers":[
        {
            "category":"Real Estate",
            "subcategory":"Real Estate Services",
            "type":"Services"
        },
        {
            "category":"Building & Trades",
            "subcategory":"Cleaning & Sanitation",
            "type":"Services"
        }
    ],
    "sg:phone":"+1 973 725 0480",
    "sg:postcode":"07461",
    "sg:province":"NJ",
    "sg:tags":[
        "maintenance",
        "cleaners-interior"
    ],
    "wof:name":"R L Maintenance Corp",
    "wof:placetype":"venue"
},
  "geometry": {"coordinates":[-74.531729,41.217082],"type":"Point"}
}