{
  "type": "Feature",
  "properties": {
    "addr:full":"623 Van Houten Ave Clifton NJ 07013",
    "addr:housenumber":"623",
    "addr:postcode":"07013",
    "addr:street":"Van Houten Ave",
    "iso:country":"US",
    "sg:address":"623 Van Houten Ave",
    "sg:city":"Clifton",
    "sg:classifiers":[
        {
            "category":"Retail",
            "subcategory":"Laundry & Dry Cleaning",
            "type":"Services"
        }
    ],
    "sg:phone":"+1 973 594 1120",
    "sg:postcode":"07013",
    "sg:province":"NJ",
    "sg:tags":[
        "cleaners",
        "rug",
        "carpet"
    ],
    "wof:name":"Quality Carpet Svc",
    "wof:placetype":"venue"
},
  "geometry": {"coordinates":[-74.14837900000001,40.85811],"type":"Point"}
}