{
  "type": "Feature",
  "properties": {
    "iso:country":"US",
    "sg:address":"447 Mount Prospect Ave",
    "sg:city":"Clifton",
    "sg:classifiers":[
        {
            "category":"Manufacturing",
            "subcategory":"Chemicals & Compounds",
            "type":"Manufacturing & Wholesale Goods"
        }
    ],
    "sg:phone":"+1 973 777 7829",
    "sg:postcode":"07012",
    "sg:province":"NJ",
    "sg:tags":[
        "mfg",
        "footwear",
        "cyclic"
    ],
    "wof:name":"Dynamic Industries Ltd",
    "wof:placetype":"venue"
},
  "geometry": {"coordinates":[-74.16088999999999,40.85642],"type":"Point"}
}