{
  "type": "Feature",
  "properties": {
    "iso:country":"US",
    "sg:address":"5 Buena Vista Ave",
    "sg:city":"Rumson",
    "sg:classifiers":[
        {
            "category":"Shopping",
            "subcategory":"Clothing, Apparel, & Fashions",
            "type":"Retail Goods"
        }
    ],
    "sg:phone":"+1 732 842 6942",
    "sg:postcode":"07760",
    "sg:province":"NJ",
    "sg:tags":[
        "handbag"
    ],
    "wof:name":"Carrie Valentine LLC",
    "wof:placetype":"venue"
},
  "geometry": {"coordinates":[-74.015264,40.356848],"type":"Point"}
}