{
  "type": "Feature",
  "properties": {
    "iso:country":"US",
    "sg:address":"14 Willow Rd",
    "sg:city":"Maple Shade",
    "sg:classifiers":[
        {
            "category":"Wholesale",
            "subcategory":"Fruits & Vegetables",
            "type":"Manufacturing & Wholesale Goods"
        }
    ],
    "sg:phone":"+1 856 727 0806",
    "sg:postcode":"08052",
    "sg:province":"NJ",
    "sg:tags":[
        "fresh",
        "store"
    ],
    "wof:name":"Produce Junction Inc",
    "wof:placetype":"venue"
},
  "geometry": {"coordinates":[-74.97030100000001,39.941041],"type":"Point"}
}