{
  "type": "Feature",
  "properties": {
    "iso:country":"US",
    "sg:address":"66 W Allen St",
    "sg:city":"Irvington",
    "sg:classifiers":[
        {
            "category":"Building & Trades",
            "subcategory":"Electrical",
            "type":"Services"
        }
    ],
    "sg:phone":"+1 973 372 7444",
    "sg:postcode":"07111",
    "sg:province":"NJ",
    "sg:tags":[
        "electrical",
        "electric",
        "contractor"
    ],
    "wof:name":"Olem's Electric",
    "wof:placetype":"venue"
},
  "geometry": {"coordinates":[-74.22976,40.7333],"type":"Point"}
}