{
  "type": "Feature",
  "properties": {
    "addr:full":"1320 State Rte 88 Lakewood NJ 08701",
    "addr:housenumber":"1320",
    "addr:postcode":"08701",
    "addr:street":"State Rte 88",
    "iso:country":"US",
    "sg:address":"1320 State Rte 88",
    "sg:city":"Lakewood",
    "sg:classifiers":[
        {
            "category":"Autos & Motor Vehicles",
            "subcategory":"Automobile Sales",
            "type":"Retail Goods"
        }
    ],
    "sg:phone":"+1   ",
    "sg:postcode":"08701",
    "sg:province":"NJ",
    "sg:tags":[
        "used"
    ],
    "sg:website":"www.nobullauto.com",
    "wof:name":"Auto Exchange Inc",
    "wof:placetype":"venue"
},
  "geometry": {"coordinates":[-74.15905600000001,40.081784],"type":"Point"}
}