{
  "type": "Feature",
  "properties": {
    "iso:country":"US",
    "sg:address":"240 E Pearl St Apt 301",
    "sg:city":"Burlington",
    "sg:classifiers":[
        {
            "category":"Real Estate",
            "subcategory":"Real Estate Operator",
            "type":"Services"
        }
    ],
    "sg:phone":"+1 609 386 6500",
    "sg:postcode":"08016",
    "sg:province":"NJ",
    "sg:tags":[
        "apartment"
    ],
    "wof:name":"J Frank Budd Bldg C-O Pennrose Management",
    "wof:placetype":"venue"
},
  "geometry": {"coordinates":[-74.8545,40.0812],"type":"Point"}
}