{
  "type": "Feature",
  "properties": {
    "iso:country":"US",
    "sg:address":"567 Franklin Ave",
    "sg:city":"Belleville",
    "sg:classifiers":[
        {
            "category":"Health Services",
            "subcategory":"Chiropractor",
            "type":"Services"
        }
    ],
    "sg:phone":"+1 973 450 1003",
    "sg:postcode":"07109",
    "sg:province":"NJ",
    "wof:name":"Stefanelli Paul DC",
    "wof:placetype":"venue"
},
  "geometry": {"coordinates":[-74.167,40.808201],"type":"Point"}
}