{
  "type": "Feature",
  "properties": {
    "addr:full":"304 Hackensack St Wood Ridge NJ 07075",
    "addr:housenumber":"304",
    "addr:postcode":"07075",
    "addr:street":"Hackensack St",
    "iso:country":"US",
    "sg:address":"304 Hackensack St",
    "sg:city":"Wood Ridge",
    "sg:classifiers":[
        {
            "category":"Professional",
            "subcategory":"Lawyer & Legal Services",
            "type":"Services"
        }
    ],
    "sg:phone":"+1 201 438 5522",
    "sg:postcode":"07075",
    "sg:province":"NJ",
    "wof:name":"Fraioli Ronald M Attorney",
    "wof:placetype":"venue"
},
  "geometry": {"coordinates":[-74.079697,40.8498],"type":"Point"}
}