{
  "type": "Feature",
  "properties": {
    "addr:full":"344 Kresson Rd Cherry Hill NJ 08034",
    "addr:housenumber":"344",
    "addr:postcode":"08034",
    "addr:street":"Kresson Rd",
    "iso:country":"US",
    "sg:address":"344 Kresson Rd",
    "sg:city":"Cherry Hill",
    "sg:classifiers":[
        {
            "category":"Organizations",
            "subcategory":"Religious Organization",
            "type":"Services"
        }
    ],
    "sg:phone":"+1   ",
    "sg:postcode":"08034",
    "sg:province":"NJ",
    "wof:name":"Brennan William Rev",
    "wof:placetype":"venue"
},
  "geometry": {"coordinates":[-75.015732,39.893355],"type":"Point"}
}