{
  "type": "Feature",
  "properties": {
    "addr:full":"107 1st St Hackensack NJ 07601",
    "addr:housenumber":"107",
    "addr:postcode":"07601",
    "addr:street":"1St St",
    "iso:country":"US",
    "sg:address":"107 1st St",
    "sg:city":"Hackensack",
    "sg:classifiers":[
        {
            "category":"Health Services",
            "subcategory":"Doctor",
            "type":"Services"
        }
    ],
    "sg:phone":"+1 201 342 2212",
    "sg:postcode":"07601",
    "sg:province":"NJ",
    "wof:name":"Benedet Pediatrics",
    "wof:placetype":"venue"
},
  "geometry": {"coordinates":[-74.05260800000001,40.884528],"type":"Point"}
}