{
  "type": "Feature",
  "properties": {
    "addr:full":"1571 Main Rd Newfield NJ 08344",
    "addr:housenumber":"1571",
    "addr:postcode":"08344",
    "addr:street":"Main Rd",
    "iso:country":"US",
    "sg:address":"1571 Main Rd",
    "sg:city":"Newfield",
    "sg:classifiers":[
        {
            "category":"Freight",
            "type":"Transportation"
        }
    ],
    "sg:phone":"+1 856 697 2000",
    "sg:postcode":"08344",
    "sg:province":"NJ",
    "sg:tags":[
        "trucking"
    ],
    "wof:name":"Coughlin Trucking Co",
    "wof:placetype":"venue"
},
  "geometry": {"coordinates":[-75.00016599999999,39.55943],"type":"Point"}
}