{
  "type": "Feature",
  "properties": {
    "addr:full":"149 Fillmore St Phillipsburg NJ 08865",
    "addr:housenumber":"149",
    "addr:postcode":"08865",
    "addr:street":"Fillmore St",
    "iso:country":"US",
    "sg:address":"149 Fillmore St",
    "sg:city":"Phillipsburg",
    "sg:classifiers":[
        {
            "category":"Building & Trades",
            "subcategory":"Construction",
            "type":"Services"
        }
    ],
    "sg:phone":"+1 908 454 2168",
    "sg:postcode":"08865",
    "sg:province":"NJ",
    "sg:tags":[
        "general",
        "contractor"
    ],
    "wof:name":"BDM General Contracting",
    "wof:placetype":"venue"
},
  "geometry": {"coordinates":[-75.193676,40.691374],"type":"Point"}
}