{
  "type": "Feature",
  "properties": {
    "addr:full":"329 Village Rd E Princeton Jct NJ 08550",
    "addr:housenumber":"329",
    "addr:postcode":"08550",
    "addr:street":"Village Rd E",
    "iso:country":"US",
    "sg:address":"329 Village Rd E",
    "sg:city":"Princeton Jct",
    "sg:classifiers":[
        {
            "category":"Social Services",
            "subcategory":"Child Care",
            "type":"Services"
        },
        {
            "category":"Education",
            "subcategory":"Special Training",
            "type":"Public Place"
        }
    ],
    "sg:phone":"+1 609 799 8811",
    "sg:postcode":"08550",
    "sg:province":"NJ",
    "sg:tags":[
        "kindergarten",
        "academic",
        "school",
        "synagogue"
    ],
    "sg:website":"www.bethchaim.org",
    "wof:name":"Congregation Beth Chaim Prschl",
    "wof:placetype":"venue"
},
  "geometry": {"coordinates":[-74.596604,40.272541],"type":"Point"}
}