{
  "type": "Feature",
  "properties": {
    "addr:full":"2 Risley Rd Hewitt NJ 07421",
    "addr:housenumber":"2",
    "addr:postcode":"07421",
    "addr:street":"Risley Rd",
    "iso:country":"US",
    "sg:address":"2 Risley Rd",
    "sg:city":"Hewitt",
    "sg:classifiers":[
        {
            "category":"Building & Trades",
            "subcategory":"Construction",
            "type":"Services"
        }
    ],
    "sg:phone":"+1 973 853 8697",
    "sg:postcode":"07421",
    "sg:province":"NJ",
    "sg:tags":[
        "painter"
    ],
    "wof:name":"Joe Van Go",
    "wof:placetype":"venue"
},
  "geometry": {"coordinates":[-74.384912,41.187838],"type":"Point"}
}