{
  "type": "Feature",
  "properties": {
    "addr:full":"571 N Evergreen Ave Woodbury NJ 08096",
    "addr:housenumber":"571",
    "addr:postcode":"08096",
    "addr:street":"N Evergreen Ave",
    "iso:country":"US",
    "sg:address":"571 N Evergreen Ave",
    "sg:city":"Woodbury",
    "sg:classifiers":[
        {
            "category":"Health Services",
            "subcategory":"Clinic",
            "type":"Services"
        },
        {
            "category":"Health Services",
            "subcategory":"Hospital",
            "type":"Services"
        }
    ],
    "sg:phone":"+1 856 853 8735",
    "sg:postcode":"08096",
    "sg:province":"NJ",
    "sg:tags":[
        "medical",
        "dialysis"
    ],
    "wof:name":"Fresenius Medical Care",
    "wof:placetype":"venue"
},
  "geometry": {"coordinates":[-75.14469099999999,39.843303],"type":"Point"}
}