{
  "type": "Feature",
  "properties": {
    "iso:country":"US",
    "sg:address":"308 Queen Anne Rd",
    "sg:city":"Teaneck",
    "sg:classifiers":[
        {
            "category":"Food & Beverages",
            "subcategory":"Groceries & Convenience Stores",
            "type":"Retail Goods"
        }
    ],
    "sg:phone":"+1 201 287 1245",
    "sg:postcode":"07666",
    "sg:province":"NJ",
    "wof:name":"Bobs Stationary",
    "wof:placetype":"venue"
},
  "geometry": {"coordinates":[-74.02122,40.874226],"type":"Point"}
}