{
  "type": "Feature",
  "properties": {
    "addr:full":"555 Prospect St Metuchen NJ 08840",
    "addr:housenumber":"555",
    "addr:postcode":"08840",
    "addr:street":"Prospect St",
    "iso:country":"US",
    "sg:address":"555 Prospect St",
    "sg:city":"Metuchen",
    "sg:classifiers":[
        {
            "category":"Manufacturing",
            "subcategory":"Textiles",
            "type":"Manufacturing & Wholesale Goods"
        }
    ],
    "sg:phone":"+1 732 494 0500",
    "sg:postcode":"08840",
    "sg:province":"NJ",
    "sg:tags":[
        "sewn",
        "towel",
        "mfg",
        "domestic",
        "embroidered",
        "import"
    ],
    "sg:website":"www.franco-mfg.com",
    "wof:name":"Franco Manufacturing Co Inc",
    "wof:placetype":"venue"
},
  "geometry": {"coordinates":[-74.371709,40.533216],"type":"Point"}
}