{
  "type": "Feature",
  "properties": {
    "addr:full":"1250 Liberty Ave Hillside NJ 07205",
    "addr:housenumber":"1250",
    "addr:postcode":"07205",
    "addr:street":"Liberty Ave",
    "iso:country":"US",
    "sg:address":"1250 Liberty Ave",
    "sg:city":"Hillside",
    "sg:classifiers":[
        {
            "category":"Marine",
            "type":"Transportation"
        }
    ],
    "sg:phone":"+1 908 964 8812",
    "sg:postcode":"07205",
    "sg:province":"NJ",
    "sg:tags":[
        "heavy",
        "including",
        "dredging",
        "lift",
        "salvage"
    ],
    "wof:name":"Donjon Marine Co Inc",
    "wof:placetype":"venue"
},
  "geometry": {"coordinates":[-74.23442300000001,40.695977],"type":"Point"}
}