{
  "type": "Feature",
  "properties": {
    "iso:country":"US",
    "sg:address":"2 Prospect St",
    "sg:city":"Trenton",
    "sg:classifiers":[
        {
            "category":"Real Estate",
            "subcategory":"Real Estate Operator",
            "type":"Services"
        }
    ],
    "sg:phone":"+1 609 989 8401",
    "sg:postcode":"08618",
    "sg:province":"NJ",
    "sg:tags":[
        "apartment"
    ],
    "wof:name":"Smith Court Apartments",
    "wof:placetype":"venue"
},
  "geometry": {"coordinates":[-74.77892300000001,40.22644],"type":"Point"}
}