{
  "type": "Feature",
  "properties": {
    "addr:full":"415 Henry St Fairview NJ 07022",
    "addr:housenumber":"415",
    "addr:postcode":"07022",
    "addr:street":"Henry St",
    "iso:country":"US",
    "sg:address":"415 Henry St",
    "sg:city":"Fairview",
    "sg:classifiers":[
        {
            "category":"Professional",
            "subcategory":"Business Services",
            "type":"Services"
        }
    ],
    "sg:phone":"+1 201 941 0614",
    "sg:postcode":"07022",
    "sg:province":"NJ",
    "wof:name":"Richard Schmidt Zahn Punching",
    "wof:placetype":"venue"
},
  "geometry": {"coordinates":[-74.001227,40.814241],"type":"Point"}
}