{
  "type": "Feature",
  "properties": {
    "addr:full":"32 Rancocas Blvd Mount Laurel NJ 08054",
    "addr:housenumber":"32",
    "addr:postcode":"08054",
    "addr:street":"Rancocas Blvd",
    "iso:country":"US",
    "sg:address":"32 Rancocas Blvd",
    "sg:city":"Mount Laurel",
    "sg:classifiers":[
        {
            "category":"Shopping",
            "subcategory":"Gifts & Souvenirs",
            "type":"Retail Goods"
        }
    ],
    "sg:phone":"+1   ",
    "sg:postcode":"08054",
    "sg:province":"NJ",
    "wof:name":"Ginas Creative Healing Arts",
    "wof:placetype":"venue"
},
  "geometry": {"coordinates":[-74.857264,39.982467],"type":"Point"}
}