{
  "type": "Feature",
  "properties": {
    "iso:country":"US",
    "sg:address":"2115 New Rd",
    "sg:city":"Linwood",
    "sg:classifiers":[
        {
            "category":"Organizations",
            "subcategory":"Religious Organization",
            "type":"Services"
        }
    ],
    "sg:phone":"+1 609 927 8079",
    "sg:postcode":"08221",
    "sg:province":"NJ",
    "sg:tags":[
        "school"
    ],
    "sg:website":"www.mainlandassembly.com",
    "wof:name":"Mainland Assembly Of God",
    "wof:placetype":"venue"
},
  "geometry": {"coordinates":[-74.589274,39.33389],"type":"Point"}
}