{
  "type": "Feature",
  "properties": {
    "iso:country":"US",
    "sg:address":"636 Van Houten Ave",
    "sg:city":"Clifton",
    "sg:classifiers":[
        {
            "category":"Health Services",
            "subcategory":"Optometrist",
            "type":"Services"
        }
    ],
    "sg:phone":"+1 973 777 7117",
    "sg:postcode":"07013",
    "sg:province":"NJ",
    "sg:tags":[
        "good",
        "optical",
        "optician",
        "eyewear"
    ],
    "wof:name":"Eyecare and Eyewear",
    "wof:placetype":"venue"
},
  "geometry": {"coordinates":[-74.14810199999999,40.8582],"type":"Point"}
}