{
  "type": "Feature",
  "properties": {
    "addr:full":"190 Moore St Ste 410 Hackensack NJ 07601",
    "addr:housenumber":"190",
    "addr:postcode":"07601",
    "addr:street":"Moore St Ste 410",
    "iso:country":"US",
    "sg:address":"190 Moore St Ste 410",
    "sg:city":"Hackensack",
    "sg:classifiers":[
        {
            "category":"Organizations",
            "subcategory":"Religious Organization",
            "type":"Services"
        }
    ],
    "sg:phone":"+1 201 457 0058",
    "sg:postcode":"07601",
    "sg:province":"NJ",
    "wof:name":"Jewish Association For Developmental Disabilities",
    "wof:placetype":"venue"
},
  "geometry": {"coordinates":[-74.041746,40.883692],"type":"Point"}
}