{
  "type": "Feature",
  "properties": {
    "iso:country":"US",
    "sg:address":"3253 State Rte 35",
    "sg:city":"Hazlet",
    "sg:classifiers":[
        {
            "category":"Home & Garden",
            "subcategory":"Building Materials",
            "type":"Retail Goods"
        }
    ],
    "sg:phone":"+1   ",
    "sg:postcode":"07730",
    "sg:province":"NJ",
    "wof:name":"Designer Source",
    "wof:placetype":"venue"
},
  "geometry": {"coordinates":[-74.18626399999999,40.421349],"type":"Point"}
}