{
  "type": "Feature",
  "properties": {
    "addr:full":"42 S Broadway Pennsville NJ 08070",
    "addr:housenumber":"42",
    "addr:postcode":"08070",
    "addr:street":"S Broadway",
    "iso:country":"US",
    "sg:address":"42 S Broadway",
    "sg:city":"Pennsville",
    "sg:classifiers":[
        {
            "category":"Personal",
            "type":"Services"
        }
    ],
    "sg:phone":"+1   ",
    "sg:postcode":"08070",
    "sg:province":"NJ",
    "wof:name":"Sun Country Inn",
    "wof:placetype":"venue"
},
  "geometry": {"coordinates":[-75.520315,39.652088],"type":"Point"}
}