{
  "type": "Feature",
  "properties": {
    "iso:country":"US",
    "sg:address":"301 Fern Dr",
    "sg:city":"Atco",
    "sg:classifiers":[
        {
            "category":"Real Estate",
            "subcategory":"Real Estate Services",
            "type":"Services"
        }
    ],
    "sg:phone":"+1 856 767 6888",
    "sg:postcode":"08004",
    "sg:province":"NJ",
    "sg:tags":[
        "management",
        "property"
    ],
    "wof:name":"J B Management Services",
    "wof:placetype":"venue"
},
  "geometry": {"coordinates":[-74.877098,39.754398],"type":"Point"}
}