{
  "type": "Feature",
  "properties": {
    "iso:country":"US",
    "sg:address":"14 Clifton Ave",
    "sg:city":"Lakewood",
    "sg:classifiers":[
        {
            "category":"Professional",
            "type":"Services"
        }
    ],
    "sg:phone":"+1 732 730 9040",
    "sg:postcode":"08701",
    "sg:province":"NJ",
    "sg:tags":[
        "establishment"
    ],
    "wof:name":"Magnatronix",
    "wof:placetype":"venue"
},
  "geometry": {"coordinates":[-74.214478,40.091005],"type":"Point"}
}