{
  "type": "Feature",
  "properties": {
    "addr:full":"422 Cliff St Fairview NJ 07022",
    "addr:housenumber":"422",
    "addr:postcode":"07022",
    "addr:street":"Cliff St",
    "iso:country":"US",
    "sg:address":"422 Cliff St",
    "sg:city":"Fairview",
    "sg:classifiers":[
        {
            "category":"Manufacturing",
            "subcategory":"Apparel",
            "type":"Manufacturing & Wholesale Goods"
        }
    ],
    "sg:phone":"+1 201 313 4480",
    "sg:postcode":"07022",
    "sg:province":"NJ",
    "sg:tags":[
        "mfg",
        "embroidered"
    ],
    "sg:website":"www.usabeading.com",
    "wof:name":"Faraj Inc",
    "wof:placetype":"venue"
},
  "geometry": {"coordinates":[-73.99652399999999,40.81868],"type":"Point"}
}