{
  "type": "Feature",
  "properties": {
    "iso:country":"US",
    "sg:address":"3201 Central Ave",
    "sg:city":"Union City",
    "sg:classifiers":[
        {
            "category":"Organizations",
            "subcategory":"Religious Organization",
            "type":"Services"
        }
    ],
    "sg:phone":"+1 201 422 7550",
    "sg:postcode":"07087",
    "sg:province":"NJ",
    "wof:name":"Province Of St Nicholas",
    "wof:placetype":"venue"
},
  "geometry": {"coordinates":[-74.02992999999999,40.773945],"type":"Point"}
}