{
  "type": "Feature",
  "properties": {
    "addr:full":"229 Main St Chatham NJ 07928",
    "addr:housenumber":"229",
    "addr:postcode":"07928",
    "addr:street":"Main St",
    "iso:country":"US",
    "sg:address":"229 Main St",
    "sg:city":"Chatham",
    "sg:classifiers":[
        {
            "category":"Professional",
            "subcategory":"Lawyer & Legal Services",
            "type":"Services"
        }
    ],
    "sg:phone":"+1 973 635 5200",
    "sg:postcode":"07928",
    "sg:province":"NJ",
    "wof:name":"Frahn Carl A Lawyer",
    "wof:placetype":"venue"
},
  "geometry": {"coordinates":[-74.38159899999999,40.740299],"type":"Point"}
}