{
  "type": "Feature",
  "properties": {
    "iso:country":"US",
    "sg:address":"475 Old Marlton Pike W",
    "sg:city":"Marlton",
    "sg:classifiers":[
        {
            "category":"Health Services",
            "subcategory":"Doctor",
            "type":"Services"
        }
    ],
    "sg:phone":"+1 856 596 6333",
    "sg:postcode":"08053",
    "sg:province":"NJ",
    "sg:tags":[
        "physician",
        "surgeon"
    ],
    "wof:name":"Pediatric Gastroenterology Ctr",
    "wof:placetype":"venue"
},
  "geometry": {"coordinates":[-74.931597,39.892862],"type":"Point"}
}