{
  "type": "Feature",
  "properties": {
    "iso:country":"US",
    "sg:address":"267 Main St",
    "sg:city":"Madison",
    "sg:classifiers":[
        {
            "category":"Retail",
            "subcategory":"Car Wash",
            "type":"Services"
        }
    ],
    "sg:phone":"+1 973 377 7188",
    "sg:postcode":"07940",
    "sg:province":"NJ",
    "wof:name":"Madison Car Wash & Detail Center",
    "wof:placetype":"venue"
},
  "geometry": {"coordinates":[-74.40300000000001,40.751499],"type":"Point"}
}