{
  "type": "Feature",
  "properties": {
    "addr:full":"94 Willard St Garfield NJ 07026",
    "addr:housenumber":"94",
    "addr:postcode":"07026",
    "addr:street":"Willard St",
    "iso:country":"US",
    "sg:address":"94 Willard St",
    "sg:city":"Garfield",
    "sg:classifiers":[
        {
            "category":"Building & Trades",
            "subcategory":"Construction",
            "type":"Services"
        }
    ],
    "sg:phone":"+1 973 685 9988",
    "sg:postcode":"07026",
    "sg:province":"NJ",
    "sg:tags":[
        "contractor"
    ],
    "sg:website":"www.asmconstructioncorp.com",
    "wof:name":"Asm Construction Corp",
    "wof:placetype":"venue"
},
  "geometry": {"coordinates":[-74.10826900000001,40.871345],"type":"Point"}
}