{
  "type": "Feature",
  "properties": {
    "iso:country":"US",
    "sg:address":"8 Cardinal Dr",
    "sg:city":"Egg Harbor City",
    "sg:classifiers":[
        {
            "category":"Building & Trades",
            "subcategory":"Construction",
            "type":"Services"
        }
    ],
    "sg:phone":"+1 609 804 9199",
    "sg:postcode":"08210",
    "sg:province":"NJ",
    "sg:tags":[
        "contractor"
    ],
    "wof:name":"Action Chimney & Masonary Mtc",
    "wof:placetype":"venue"
},
  "geometry": {"coordinates":[-74.859407,39.127285],"type":"Point"}
}