{
  "type": "Feature",
  "properties": {
    "addr:full":"666 N 7th St Newark NJ 07107",
    "addr:housenumber":"666",
    "addr:postcode":"07107",
    "addr:street":"N 7Th St",
    "iso:country":"US",
    "sg:address":"666 N 7th St",
    "sg:city":"Newark",
    "sg:classifiers":[
        {
            "category":"Bars & Pubs",
            "subcategory":"Nightclub",
            "type":"Food & Drink"
        }
    ],
    "sg:phone":"+1 973 485 9397",
    "sg:postcode":"07107",
    "sg:province":"NJ",
    "sg:tags":[
        "nightlife"
    ],
    "wof:name":"Esther's Place",
    "wof:placetype":"venue"
},
  "geometry": {"coordinates":[-74.180397,40.7733],"type":"Point"}
}