{
  "type": "Feature",
  "properties": {
    "iso:country":"US",
    "sg:address":"521 61st St",
    "sg:city":"West New York",
    "sg:classifiers":[
        {
            "category":"Shopping",
            "type":"Retail Goods"
        }
    ],
    "sg:phone":"+1   ",
    "sg:postcode":"07093",
    "sg:province":"NJ",
    "sg:tags":[
        "merchandise"
    ],
    "wof:name":"Botanica LA Brasabola",
    "wof:placetype":"venue"
},
  "geometry": {"coordinates":[-74.016622,40.790252],"type":"Point"}
}