{
  "type": "Feature",
  "properties": {
    "iso:country":"US",
    "sg:address":"389 E Mount Pleasant Ave",
    "sg:city":"Livingston",
    "sg:classifiers":[
        {
            "category":"Health Services",
            "subcategory":"Doctor",
            "type":"Services"
        }
    ],
    "sg:phone":"+1 973 673 4410",
    "sg:postcode":"07039",
    "sg:province":"NJ",
    "sg:tags":[
        "physician",
        "surgeon"
    ],
    "wof:name":"Rajender K Arora MD",
    "wof:placetype":"venue"
},
  "geometry": {"coordinates":[-74.291265,40.795678],"type":"Point"}
}