{
  "type": "Feature",
  "properties": {
    "addr:full":"145 South St Freehold NJ 07728",
    "addr:housenumber":"145",
    "addr:postcode":"07728",
    "addr:street":"South St",
    "iso:country":"US",
    "sg:address":"145 South St",
    "sg:city":"Freehold",
    "sg:classifiers":[
        {
            "category":"Banks & Credit Unions",
            "subcategory":"Bank",
            "type":"Services"
        }
    ],
    "sg:phone":"+1 732 303 0444",
    "sg:postcode":"07728",
    "sg:province":"NJ",
    "sg:tags":[
        "financing"
    ],
    "wof:name":"Light House Funding",
    "wof:placetype":"venue"
},
  "geometry": {"coordinates":[-74.27430699999999,40.250188],"type":"Point"}
}