{
  "type": "Feature",
  "properties": {
    "iso:country":"US",
    "sg:address":"905 Kings Hwy S",
    "sg:city":"Cherry Hill",
    "sg:classifiers":[
        {
            "category":"Professional",
            "subcategory":"Lawyer & Legal Services",
            "type":"Services"
        }
    ],
    "sg:phone":"+1 856 667 6440",
    "sg:postcode":"08034",
    "sg:province":"NJ",
    "wof:name":"Katz Ettin & Levine",
    "wof:placetype":"venue"
},
  "geometry": {"coordinates":[-75.01986100000001,39.905209],"type":"Point"}
}