{
  "type": "Feature",
  "properties": {
    "iso:country":"US",
    "sg:address":"3020 Shore Rd",
    "sg:city":"Ocean View",
    "sg:classifiers":[
        {
            "category":"Retail",
            "subcategory":"Animal Services",
            "type":"Services"
        }
    ],
    "sg:phone":"+1 609 624 7818",
    "sg:postcode":"08230",
    "sg:province":"NJ",
    "sg:tags":[
        "pet",
        "grooming",
        "washing"
    ],
    "wof:name":"Bobbi's Grooming",
    "wof:placetype":"venue"
},
  "geometry": {"coordinates":[-74.70572900000001,39.206294],"type":"Point"}
}