{
  "type": "Feature",
  "properties": {
    "iso:country":"US",
    "sg:address":"2 Old Orchard Rd",
    "sg:city":"Morristown",
    "sg:classifiers":[
        {
            "category":"Building & Trades",
            "subcategory":"Construction",
            "type":"Services"
        }
    ],
    "sg:phone":"+1 973 829 0400",
    "sg:postcode":"07960",
    "sg:province":"NJ",
    "sg:tags":[
        "masonry",
        "contractor"
    ],
    "wof:name":"Spano Masonry",
    "wof:placetype":"venue"
},
  "geometry": {"coordinates":[-74.54764299999999,40.809235],"type":"Point"}
}