{
  "type": "Feature",
  "properties": {
    "iso:country":"US",
    "sg:address":"109 Oak St",
    "sg:city":"Old Bridge",
    "sg:classifiers":[
        {
            "category":"Professional",
            "subcategory":"Business Services",
            "type":"Services"
        }
    ],
    "sg:phone":"+1 732 679 1800",
    "sg:postcode":"08857",
    "sg:province":"NJ",
    "sg:tags":[
        "electrical",
        "system",
        "power"
    ],
    "sg:website":"www.mlpower.com",
    "wof:name":"M & L Power Systems Mntnc",
    "wof:placetype":"venue"
},
  "geometry": {"coordinates":[-74.355182,40.390448],"type":"Point"}
}