{
  "type": "Feature",
  "properties": {
    "iso:country":"US",
    "sg:address":"4 Orange Pl",
    "sg:city":"West Orange",
    "sg:classifiers":[
        {
            "category":"Education",
            "subcategory":"Dance Studio",
            "type":"Public Place"
        }
    ],
    "sg:phone":"+1   ",
    "sg:postcode":"07052",
    "sg:province":"NJ",
    "wof:name":"Oskar Schindler Performing Art",
    "wof:placetype":"venue"
},
  "geometry": {"coordinates":[-74.23244200000001,40.792668],"type":"Point"}
}