{
  "type": "Feature",
  "properties": {
    "addr:full":"1302 Sussex Tpke Randolph NJ 07869",
    "addr:housenumber":"1302",
    "addr:postcode":"07869",
    "addr:street":"Sussex Tpke",
    "iso:country":"US",
    "sg:address":"1302 Sussex Tpke",
    "sg:city":"Randolph",
    "sg:classifiers":[
        {
            "category":"Building & Trades",
            "subcategory":"Landscaping Services",
            "type":"Services"
        }
    ],
    "sg:phone":"+1 862 849 0115",
    "sg:postcode":"07869",
    "sg:province":"NJ",
    "sg:tags":[
        "landscape"
    ],
    "wof:name":"Anthony Agudelo Landscaping",
    "wof:placetype":"venue"
},
  "geometry": {"coordinates":[-74.585932,40.829316],"type":"Point"}
}