{
  "type": "Feature",
  "properties": {
    "iso:country":"US",
    "sg:address":"129 Bogert St",
    "sg:city":"Teaneck",
    "sg:classifiers":[
        {
            "category":"Professional",
            "subcategory":"Research",
            "type":"Services"
        }
    ],
    "sg:phone":"+1 201 837 8091",
    "sg:postcode":"07666",
    "sg:province":"NJ",
    "wof:name":"High Impact Research Ctr",
    "wof:placetype":"venue"
},
  "geometry": {"coordinates":[-74.006119,40.899363],"type":"Point"}
}