{
  "type": "Feature",
  "properties": {
    "addr:full":"10 River Rd Bogota NJ 07603",
    "addr:housenumber":"10",
    "addr:postcode":"07603",
    "addr:street":"River Rd",
    "iso:country":"US",
    "sg:address":"10 River Rd",
    "sg:city":"Bogota",
    "sg:classifiers":[
        {
            "category":"Building & Trades",
            "subcategory":"Locksmith",
            "type":"Services"
        }
    ],
    "sg:phone":"+1 201 243 3673",
    "sg:postcode":"07603",
    "sg:province":"NJ",
    "sg:tags":[
        "key"
    ],
    "wof:name":"0 # A & & # 1 24 Hour Emergency Locksmith",
    "wof:placetype":"venue"
},
  "geometry": {"coordinates":[-74.032224,40.869627],"type":"Point"}
}