{
  "type": "Feature",
  "properties": {
    "addr:full":"35 E Front St Red Bank NJ 07701",
    "addr:housenumber":"35",
    "addr:postcode":"07701",
    "addr:street":"E Front St",
    "iso:country":"US",
    "sg:address":"35 E Front St",
    "sg:city":"Red Bank",
    "sg:classifiers":[
        {
            "category":"Shopping",
            "subcategory":"Jewelry",
            "type":"Retail Goods"
        }
    ],
    "sg:phone":"+1   ",
    "sg:postcode":"07701",
    "sg:province":"NJ",
    "wof:name":"Leonardo Jewelers",
    "wof:placetype":"venue"
},
  "geometry": {"coordinates":[-74.062804,40.353018],"type":"Point"}
}