{
  "type": "Feature",
  "properties": {
    "iso:country":"US",
    "sg:address":"1 Montauk Rd",
    "sg:city":"Cape May",
    "sg:classifiers":[
        {
            "category":"Professional",
            "subcategory":"Business Services",
            "type":"Services"
        }
    ],
    "sg:phone":"+1   ",
    "sg:postcode":"08204",
    "sg:province":"NJ",
    "wof:name":"Dbay Partners LLC",
    "wof:placetype":"venue"
},
  "geometry": {"coordinates":[-74.90881899999999,38.960158],"type":"Point"}
}