{
  "type": "Feature",
  "properties": {
    "iso:country":"US",
    "sg:address":"744 Main St",
    "sg:city":"Belford",
    "sg:classifiers":[
        {
            "category":"Wholesale",
            "subcategory":"Vending Machines",
            "type":"Manufacturing & Wholesale Goods"
        }
    ],
    "sg:phone":"+1 732 495 3550",
    "sg:postcode":"07718",
    "sg:province":"NJ",
    "wof:name":"Gateway Vending",
    "wof:placetype":"venue"
},
  "geometry": {"coordinates":[-74.090609,40.421718],"type":"Point"}
}