{
  "type": "Feature",
  "properties": {
    "addr:full":"600 Monroe Ave Asbury Park NJ 07712",
    "addr:housenumber":"600",
    "addr:postcode":"07712",
    "addr:street":"Monroe Ave Asbury",
    "iso:country":"US",
    "sg:address":"600 Monroe Ave",
    "sg:city":"Asbury Park",
    "sg:classifiers":[
        {
            "category":"Education",
            "subcategory":"School",
            "type":"Public Place"
        }
    ],
    "sg:phone":"+1 732 776 2660",
    "sg:postcode":"07712",
    "sg:province":"NJ",
    "sg:website":"www.asburypark.k12.nj.us",
    "wof:name":"Thurgood Marshall Elementary",
    "wof:placetype":"venue"
},
  "geometry": {"coordinates":[-74.01110799999999,40.21862],"type":"Point"}
}