{
  "type": "Feature",
  "properties": {
    "addr:full":"1347 Stelton Rd Piscataway NJ 08854",
    "addr:housenumber":"1347",
    "addr:postcode":"08854",
    "addr:street":"Stelton Rd",
    "iso:country":"US",
    "sg:address":"1347 Stelton Rd",
    "sg:city":"Piscataway",
    "sg:classifiers":[
        {
            "category":"Personal",
            "subcategory":"Beauty Salon",
            "type":"Services"
        }
    ],
    "sg:phone":"+1 732 572 8844",
    "sg:postcode":"08854",
    "sg:province":"NJ",
    "wof:name":"Payal Beauty Parlor",
    "wof:placetype":"venue"
},
  "geometry": {"coordinates":[-74.423,40.540378],"type":"Point"}
}