{
  "type": "Feature",
  "properties": {
    "addr:full":"50 Birmingham Dr Englishtown NJ 07726",
    "addr:housenumber":"50",
    "addr:postcode":"07726",
    "addr:street":"Birmingham Dr",
    "iso:country":"US",
    "sg:address":"50 Birmingham Dr",
    "sg:city":"Englishtown",
    "sg:classifiers":[
        {
            "category":"Professional",
            "subcategory":"Business Services",
            "type":"Services"
        }
    ],
    "sg:phone":"+1   ",
    "sg:postcode":"07726",
    "sg:province":"NJ",
    "wof:name":"Stets Express Inc",
    "wof:placetype":"venue"
},
  "geometry": {"coordinates":[-74.33596199999999,40.316313],"type":"Point"}
}