{
  "type": "Feature",
  "properties": {
    "addr:full":"617 N 2nd St Camden NJ 08102",
    "addr:housenumber":"617",
    "addr:postcode":"08102",
    "addr:street":"N 2Nd St",
    "iso:country":"US",
    "sg:address":"617 N 2nd St",
    "sg:city":"Camden",
    "sg:classifiers":[
        {
            "category":"Social Services",
            "subcategory":"Child Care",
            "type":"Services"
        }
    ],
    "sg:phone":"+1 856 541 3696",
    "sg:postcode":"08102",
    "sg:province":"NJ",
    "sg:tags":[
        "elementary",
        "kindergarten",
        "school",
        "academic"
    ],
    "wof:name":"El Centro Comunal Borincano Inc",
    "wof:placetype":"venue"
},
  "geometry": {"coordinates":[-75.12339799999999,39.9524],"type":"Point"}
}