{
  "type": "Feature",
  "properties": {
    "iso:country":"US",
    "sg:address":"2327 Linden Ave",
    "sg:city":"South Plainfield",
    "sg:classifiers":[
        {
            "category":"Building & Trades",
            "subcategory":"Construction",
            "type":"Services"
        }
    ],
    "sg:phone":"+1 973 376 5846",
    "sg:postcode":"07080",
    "sg:province":"NJ",
    "sg:tags":[
        "floor",
        "laying",
        "contractor"
    ],
    "wof:name":"R J Powell & Sons",
    "wof:placetype":"venue"
},
  "geometry": {"coordinates":[-74.396305,40.593616],"type":"Point"}
}