{
  "type": "Feature",
  "properties": {
    "addr:full":"3202 Cove Rd Merchantville NJ 08109",
    "addr:housenumber":"3202",
    "addr:postcode":"08109",
    "addr:street":"Cove Rd",
    "iso:country":"US",
    "sg:address":"3202 Cove Rd",
    "sg:city":"Merchantville",
    "sg:classifiers":[
        {
            "category":"Professional",
            "subcategory":"Business Services",
            "type":"Services"
        }
    ],
    "sg:phone":"+1   ",
    "sg:postcode":"08109",
    "sg:province":"NJ",
    "wof:name":"Charles G Bruder III B",
    "wof:placetype":"venue"
},
  "geometry": {"coordinates":[-75.04558900000001,39.955153],"type":"Point"}
}