{
  "type": "Feature",
  "properties": {
    "iso:country":"US",
    "sg:address":"829 Poole Ave",
    "sg:city":"Hazlet",
    "sg:classifiers":[
        {
            "category":"Professional",
            "subcategory":"Lawyer & Legal Services",
            "type":"Services"
        }
    ],
    "sg:phone":"+1 732 888 4785",
    "sg:postcode":"07730",
    "sg:province":"NJ",
    "wof:name":"Sahl Craig Attorney At Law",
    "wof:placetype":"venue"
},
  "geometry": {"coordinates":[-74.17804099999999,40.425653],"type":"Point"}
}