{
  "type": "Feature",
  "properties": {
    "iso:country":"US",
    "sg:address":"1700 Columbus Rd Unit 103",
    "sg:city":"Burlington",
    "sg:classifiers":[
        {
            "category":"Restaurant",
            "type":"Food & Drink"
        }
    ],
    "sg:phone":"+1 609 239 8888",
    "sg:postcode":"08016",
    "sg:province":"NJ",
    "sg:tags":[
        "pizza",
        "italian"
    ],
    "sg:website":"www.luigispizzafresca.com",
    "wof:name":"Pizza Fresca by Luigi",
    "wof:placetype":"venue"
},
  "geometry": {"coordinates":[-74.819902,40.080274],"type":"Point"}
}