{
  "type": "Feature",
  "properties": {
    "iso:country":"US",
    "sg:address":"575 Main St",
    "sg:city":"Hackensack",
    "sg:classifiers":[
        {
            "category":"Bars & Pubs",
            "subcategory":"Nightclub",
            "type":"Food & Drink"
        }
    ],
    "sg:phone":"+1 201 457 1670",
    "sg:postcode":"07601",
    "sg:province":"NJ",
    "sg:tags":[
        "nightlife"
    ],
    "sg:website":"www.gildasclubnnj.org",
    "wof:name":"Gilda's Club of Northern New Jersey",
    "wof:placetype":"venue"
},
  "geometry": {"coordinates":[-74.040001,40.896801],"type":"Point"}
}