{
  "type": "Feature",
  "properties": {
    "addr:full":"61 Harrison Ave Colonia NJ 07067",
    "addr:housenumber":"61",
    "addr:postcode":"07067",
    "addr:street":"Harrison Ave",
    "iso:country":"US",
    "sg:address":"61 Harrison Ave",
    "sg:city":"Colonia",
    "sg:classifiers":[
        {
            "category":"Professional",
            "subcategory":"Business Services",
            "type":"Services"
        }
    ],
    "sg:phone":"+1 732 396 1315",
    "sg:postcode":"07067",
    "sg:province":"NJ",
    "sg:tags":[
        "messenger"
    ],
    "wof:name":"Colonia Courier Inc",
    "wof:placetype":"venue"
},
  "geometry": {"coordinates":[-74.316005,40.595523],"type":"Point"}
}