{
  "type": "Feature",
  "properties": {
    "addr:full":"118 Thomson Ave Paulsboro NJ 08066",
    "addr:housenumber":"118",
    "addr:postcode":"08066",
    "addr:street":"Thomson Ave",
    "iso:country":"US",
    "sg:address":"118 Thomson Ave",
    "sg:city":"Paulsboro",
    "sg:classifiers":[
        {
            "category":"Freight",
            "type":"Transportation"
        }
    ],
    "sg:phone":"+1 856 423 2150",
    "sg:postcode":"08066",
    "sg:province":"NJ",
    "sg:tags":[
        "trucking"
    ],
    "wof:name":"KRW Transport",
    "wof:placetype":"venue"
},
  "geometry": {"coordinates":[-75.24267399999999,39.828488],"type":"Point"}
}