{
  "type": "Feature",
  "properties": {
    "iso:country":"US",
    "sg:address":"4 Blanche St",
    "sg:city":"Woodstown",
    "sg:classifiers":[
        {
            "category":"Organizations",
            "subcategory":"Community Association",
            "type":"Services"
        }
    ],
    "sg:phone":"+1   ",
    "sg:postcode":"08098",
    "sg:province":"NJ",
    "wof:name":"Woodstown Beautification",
    "wof:placetype":"venue"
},
  "geometry": {"coordinates":[-75.329386,39.660645],"type":"Point"}
}