{
  "type": "Feature",
  "properties": {
    "addr:full":"2437 Blue Bell Rd Williamstown NJ 08094",
    "addr:housenumber":"2437",
    "addr:postcode":"08094",
    "addr:street":"Blue Bell Rd",
    "iso:country":"US",
    "sg:address":"2437 Blue Bell Rd",
    "sg:city":"Williamstown",
    "sg:classifiers":[
        {
            "category":"Wholesale",
            "subcategory":"Auto Parts",
            "type":"Manufacturing & Wholesale Goods"
        }
    ],
    "sg:phone":"+1 856 629 7719",
    "sg:postcode":"08094",
    "sg:province":"NJ",
    "sg:tags":[
        "automobile",
        "rebuilt"
    ],
    "wof:name":"Blue Bell Auto Parts Inc",
    "wof:placetype":"venue"
},
  "geometry": {"coordinates":[-74.983626,39.630143],"type":"Point"}
}