{
  "type": "Feature",
  "properties": {
    "addr:full":"6 Roome Rd Towaco NJ 07082",
    "addr:housenumber":"6",
    "addr:postcode":"07082",
    "addr:street":"Roome Rd",
    "iso:country":"US",
    "sg:address":"6 Roome Rd",
    "sg:city":"Towaco",
    "sg:classifiers":[
        {
            "category":"Building & Trades",
            "subcategory":"Electrical",
            "type":"Services"
        }
    ],
    "sg:phone":"+1 973 299 8014",
    "sg:postcode":"07082",
    "sg:province":"NJ",
    "sg:tags":[
        "electrician"
    ],
    "wof:name":"Filippo Electric",
    "wof:placetype":"venue"
},
  "geometry": {"coordinates":[-74.33090199999999,40.921001],"type":"Point"}
}