{
  "type": "Feature",
  "properties": {
    "iso:country":"US",
    "sg:address":"17 Chestnut St",
    "sg:city":"Ridgewood",
    "sg:classifiers":[
        {
            "category":"Education",
            "subcategory":"Dance Studio",
            "type":"Public Place"
        }
    ],
    "sg:phone":"+1   ",
    "sg:postcode":"07450",
    "sg:province":"NJ",
    "wof:name":"Fred Astire Dnce Stdio Rdgwood",
    "wof:placetype":"venue"
},
  "geometry": {"coordinates":[-74.118973,40.980769],"type":"Point"}
}