{
  "type": "Feature",
  "properties": {
    "addr:full":"220 Main St Newport NJ 08345",
    "addr:housenumber":"220",
    "addr:postcode":"08345",
    "addr:street":"Main St",
    "iso:country":"US",
    "sg:address":"220 Main St",
    "sg:city":"Newport",
    "sg:classifiers":[
        {
            "category":"Education",
            "subcategory":"School",
            "type":"Public Place"
        }
    ],
    "sg:phone":"+1   ",
    "sg:postcode":"08345",
    "sg:province":"NJ",
    "sg:tags":[
        "educational",
        "administrative"
    ],
    "wof:name":"Downe Elm Sch",
    "wof:placetype":"venue"
},
  "geometry": {"coordinates":[-75.164619,39.29629],"type":"Point"}
}