{
  "type": "Feature",
  "properties": {
    "iso:country":"US",
    "sg:address":"293 Eisenhower Pkwy",
    "sg:city":"Livingston",
    "sg:classifiers":[
        {
            "category":"Professional",
            "type":"Services"
        }
    ],
    "sg:phone":"+1 973 535 1218",
    "sg:postcode":"07039",
    "sg:province":"NJ",
    "sg:tags":[
        "establishment"
    ],
    "wof:name":"Brady Mcenerney & Co",
    "wof:placetype":"venue"
},
  "geometry": {"coordinates":[-74.34140499999999,40.798795],"type":"Point"}
}