{
  "type": "Feature",
  "properties": {
    "addr:full":"179 E Main St Rockaway NJ 07866",
    "addr:housenumber":"179",
    "addr:postcode":"07866",
    "addr:street":"E Main St",
    "iso:country":"US",
    "sg:address":"179 E Main St",
    "sg:city":"Rockaway",
    "sg:classifiers":[
        {
            "category":"Professional",
            "type":"Services"
        }
    ],
    "sg:phone":"+1 973 625 0813",
    "sg:postcode":"07866",
    "sg:province":"NJ",
    "sg:tags":[
        "establishment"
    ],
    "wof:name":"KAP LLC",
    "wof:placetype":"venue"
},
  "geometry": {"coordinates":[-74.504971,40.8973],"type":"Point"}
}