{
  "type": "Feature",
  "properties": {
    "iso:country":"US",
    "sg:address":"1591 Irving St",
    "sg:city":"Rahway",
    "sg:classifiers":[
        {
            "category":"Education",
            "subcategory":"School",
            "type":"Public Place"
        }
    ],
    "sg:phone":"+1 732 396 1196",
    "sg:postcode":"07065",
    "sg:province":"NJ",
    "sg:tags":[
        "high",
        "middle",
        "elementary"
    ],
    "wof:name":"Rahway City of",
    "wof:placetype":"venue"
},
  "geometry": {"coordinates":[-74.27672800000001,40.61035],"type":"Point"}
}