{
  "type": "Feature",
  "properties": {
    "addr:full":"10 Station Pl Metuchen NJ 08840",
    "addr:housenumber":"10",
    "addr:postcode":"08840",
    "addr:street":"Station Pl",
    "iso:country":"US",
    "sg:address":"10 Station Pl",
    "sg:city":"Metuchen",
    "sg:classifiers":[
        {
            "category":"Organizations",
            "subcategory":"Labor Organization",
            "type":"Services"
        }
    ],
    "sg:phone":"+1 732 494 8827",
    "sg:postcode":"08840",
    "sg:province":"NJ",
    "sg:website":"www.ibew.org",
    "wof:name":"IBEW",
    "wof:placetype":"venue"
},
  "geometry": {"coordinates":[-74.360591,40.542023],"type":"Point"}
}