{
  "type": "Feature",
  "properties": {
    "iso:country":"US",
    "sg:address":"179 S Maple Ave",
    "sg:city":"Ridgewood",
    "sg:classifiers":[
        {
            "category":"Insurance",
            "subcategory":"Insurance Agent",
            "type":"Services"
        }
    ],
    "sg:phone":"+1   ",
    "sg:postcode":"07450",
    "sg:province":"NJ",
    "sg:tags":[
        "management",
        "risk"
    ],
    "wof:name":"Compsearch Incorporated",
    "wof:placetype":"venue"
},
  "geometry": {"coordinates":[-74.11436500000001,40.976789],"type":"Point"}
}