{
  "type": "Feature",
  "properties": {
    "addr:full":"84 1st Ave Atlantic Hghlnds NJ 07716",
    "addr:housenumber":"84",
    "addr:postcode":"07716",
    "addr:street":"1St Ave",
    "iso:country":"US",
    "sg:address":"84 1st Ave",
    "sg:city":"Atlantic Hghlnds",
    "sg:classifiers":[
        {
            "category":"Professional",
            "subcategory":"Business Services",
            "type":"Services"
        }
    ],
    "sg:phone":"+1 732 291 7991",
    "sg:postcode":"07716",
    "sg:province":"NJ",
    "sg:tags":[
        "auctioneer"
    ],
    "wof:name":"Goin' Once",
    "wof:placetype":"venue"
},
  "geometry": {"coordinates":[-74.037707,40.413797],"type":"Point"}
}