{
  "type": "Feature",
  "properties": {
    "addr:full":"300 Columbus Cir Edison NJ 08837",
    "addr:housenumber":"300",
    "addr:postcode":"08837",
    "addr:street":"Columbus Cir",
    "iso:country":"US",
    "sg:address":"300 Columbus Cir",
    "sg:city":"Edison",
    "sg:classifiers":[
        {
            "category":"Professional",
            "type":"Services"
        }
    ],
    "sg:phone":"+1 732 225 1466",
    "sg:postcode":"08837",
    "sg:province":"NJ",
    "sg:tags":[
        "establishment"
    ],
    "wof:name":"Austar Pharma",
    "wof:placetype":"venue"
},
  "geometry": {"coordinates":[-74.34178,40.504194],"type":"Point"}
}