{
  "type": "Feature",
  "properties": {
    "addr:full":"1 W Blackwell St Dover NJ 07801",
    "addr:housenumber":"1",
    "addr:postcode":"07801",
    "addr:street":"W Blackwell St",
    "iso:country":"US",
    "sg:address":"1 W Blackwell St",
    "sg:city":"Dover",
    "sg:classifiers":[
        {
            "category":"Wholesale",
            "subcategory":"Toys & Hobbies",
            "type":"Manufacturing & Wholesale Goods"
        }
    ],
    "sg:phone":"+1 973 366 8999",
    "sg:postcode":"07801",
    "sg:province":"NJ",
    "wof:name":"Helens Boardwalk Collectibles",
    "wof:placetype":"venue"
},
  "geometry": {"coordinates":[-74.55942400000001,40.884091],"type":"Point"}
}