{
  "type": "Feature",
  "properties": {
    "addr:full":"306 Anderson Ave Fairview NJ 07022",
    "addr:housenumber":"306",
    "addr:postcode":"07022",
    "addr:street":"Anderson Ave",
    "iso:country":"US",
    "sg:address":"306 Anderson Ave",
    "sg:city":"Fairview",
    "sg:classifiers":[
        {
            "category":"Food & Beverages",
            "subcategory":"Groceries & Convenience Stores",
            "type":"Retail Goods"
        },
        {
            "category":"Restaurant",
            "type":"Food & Drink"
        }
    ],
    "sg:phone":"+1 201 945 5566",
    "sg:postcode":"07022",
    "sg:province":"NJ",
    "sg:tags":[
        "caterer"
    ],
    "wof:name":"Marmara International Foods",
    "wof:placetype":"venue"
},
  "geometry": {"coordinates":[-73.993987,40.817267],"type":"Point"}
}