{
  "type": "Feature",
  "properties": {
    "addr:full":"1029 Beach Dr Keyport NJ 07735",
    "addr:housenumber":"1029",
    "addr:postcode":"07735",
    "addr:street":"Beach Dr",
    "iso:country":"US",
    "sg:address":"1029 Beach Dr",
    "sg:city":"Keyport",
    "sg:classifiers":[
        {
            "category":"Banks & Credit Unions",
            "subcategory":"Financial Services",
            "type":"Services"
        }
    ],
    "sg:phone":"+1   ",
    "sg:postcode":"07735",
    "sg:province":"NJ",
    "sg:tags":[
        "investment",
        "closed"
    ],
    "wof:name":"G Assesment Katz Management",
    "wof:placetype":"venue"
},
  "geometry": {"coordinates":[-74.20953799999999,40.446011],"type":"Point"}
}