{
  "type": "Feature",
  "properties": {
    "addr:full":"35 Benford Dr Princeton Junction NJ 08550",
    "addr:housenumber":"35",
    "addr:postcode":"08550",
    "addr:street":"Benford Dr",
    "iso:country":"US",
    "sg:address":"35 Benford Dr",
    "sg:city":"Princeton Junction",
    "sg:classifiers":[
        {
            "category":"Professional",
            "subcategory":"Computer Services",
            "type":"Services"
        }
    ],
    "sg:phone":"+1   ",
    "sg:postcode":"08550",
    "sg:province":"NJ",
    "sg:tags":[
        "related"
    ],
    "wof:name":"Maxim Software LLC",
    "wof:placetype":"venue"
},
  "geometry": {"coordinates":[-74.62728199999999,40.311546],"type":"Point"}
}