{
  "type": "Feature",
  "properties": {
    "addr:full":"11 State Rte 15 Lafayette NJ 07848",
    "addr:housenumber":"11",
    "addr:postcode":"07848",
    "addr:street":"State Rte 15",
    "iso:country":"US",
    "sg:address":"11 State Rte 15",
    "sg:city":"Lafayette",
    "sg:classifiers":[
        {
            "category":"Recreation",
            "type":"Entertainment"
        }
    ],
    "sg:phone":"+1 973 579 3220",
    "sg:postcode":"07848",
    "sg:province":"NJ",
    "sg:tags":[
        "martial",
        "arts",
        "instruction"
    ],
    "wof:name":"Universal Martial Arts",
    "wof:placetype":"venue"
},
  "geometry": {"coordinates":[-74.680318,41.090463],"type":"Point"}
}