{
  "type": "Feature",
  "properties": {
    "iso:country":"US",
    "sg:address":"500 Nordhoff Pl",
    "sg:city":"Englewood",
    "sg:classifiers":[
        {
            "category":"Wholesale",
            "subcategory":"Construction Materials",
            "type":"Manufacturing & Wholesale Goods"
        },
        {
            "category":"Home & Garden",
            "subcategory":"Building Materials",
            "type":"Retail Goods"
        }
    ],
    "sg:phone":"+1 201 503 0077",
    "sg:postcode":"07631",
    "sg:province":"NJ",
    "sg:tags":[
        "glass"
    ],
    "wof:name":"Allen Goldberg Weather All Win",
    "wof:placetype":"venue"
},
  "geometry": {"coordinates":[-73.98406199999999,40.88136],"type":"Point"}
}