{
  "type": "Feature",
  "properties": {
    "iso:country":"US",
    "sg:address":"197 Fairfield Rd",
    "sg:city":"Fairfield",
    "sg:classifiers":[
        {
            "category":"Health Services",
            "subcategory":"Chiropractor",
            "type":"Services"
        }
    ],
    "sg:phone":"+1 973 838 2106",
    "sg:postcode":"07004",
    "sg:province":"NJ",
    "wof:name":"Back Care Centers-North Jersey",
    "wof:placetype":"venue"
},
  "geometry": {"coordinates":[-74.292579,40.878422],"type":"Point"}
}