{
  "type": "Feature",
  "properties": {
    "addr:full":"75 Clifton Ave Clifton NJ 07011",
    "addr:housenumber":"75",
    "addr:postcode":"07011",
    "addr:street":"Clifton Ave",
    "iso:country":"US",
    "sg:address":"75 Clifton Ave",
    "sg:city":"Clifton",
    "sg:classifiers":[
        {
            "category":"Health Services",
            "subcategory":"Doctor",
            "type":"Services"
        }
    ],
    "sg:phone":"+1 973 546 6400",
    "sg:postcode":"07011",
    "sg:province":"NJ",
    "sg:tags":[
        "medical"
    ],
    "wof:name":"Rodulfo Moises MD",
    "wof:placetype":"venue"
},
  "geometry": {"coordinates":[-74.128304,40.878601],"type":"Point"}
}