{
  "type": "Feature",
  "properties": {
    "addr:full":"42 Riva Ave North Brunswick NJ 08902",
    "addr:housenumber":"42",
    "addr:postcode":"08902",
    "addr:street":"Riva Ave",
    "iso:country":"US",
    "sg:address":"42 Riva Ave",
    "sg:city":"North Brunswick",
    "sg:classifiers":[
        {
            "category":"Government",
            "subcategory":"Office",
            "type":"Public Place"
        }
    ],
    "sg:phone":"+1 732 745 3443",
    "sg:postcode":"08902",
    "sg:province":"NJ",
    "wof:name":"Middlesex County Agriculture",
    "wof:placetype":"venue"
},
  "geometry": {"coordinates":[-74.495012,40.414658],"type":"Point"}
}