{
  "type": "Feature",
  "properties": {
    "iso:country":"US",
    "sg:address":"108 Vail St",
    "sg:city":"Middlesex",
    "sg:classifiers":[
        {
            "category":"Health Services",
            "subcategory":"Doctor",
            "type":"Services"
        }
    ],
    "sg:phone":"+1 732 469 7282",
    "sg:postcode":"08846",
    "sg:province":"NJ",
    "wof:name":"Mark R Green DDS",
    "wof:placetype":"venue"
},
  "geometry": {"coordinates":[-74.50805,40.575116],"type":"Point"}
}