{
  "type": "Feature",
  "properties": {
    "iso:country":"US",
    "sg:address":"743 Stella Ct",
    "sg:city":"Paramus",
    "sg:classifiers":[
        {
            "category":"Restaurant",
            "type":"Food & Drink"
        }
    ],
    "sg:phone":"+1   ",
    "sg:postcode":"07652",
    "sg:province":"NJ",
    "sg:tags":[
        "eating"
    ],
    "wof:name":"Boston Market",
    "wof:placetype":"venue"
},
  "geometry": {"coordinates":[-74.072626,40.973674],"type":"Point"}
}