{
  "type": "Feature",
  "properties": {
    "iso:country":"US",
    "sg:address":"12 Edelweiss Ln",
    "sg:city":"Voorhees",
    "sg:classifiers":[
        {
            "category":"Banks & Credit Unions",
            "subcategory":"Bank",
            "type":"Services"
        }
    ],
    "sg:phone":"+1 856 768 2395",
    "sg:postcode":"08043",
    "sg:province":"NJ",
    "sg:tags":[
        "loan"
    ],
    "wof:name":"Student Loan Relief Orgnztn",
    "wof:placetype":"venue"
},
  "geometry": {"coordinates":[-74.93059599999999,39.831653],"type":"Point"}
}