{
  "type": "Feature",
  "properties": {
    "addr:full":"714 US Hwy 130 Cinnaminson NJ 08077",
    "addr:housenumber":"714",
    "addr:postcode":"08077",
    "addr:street":"Us Hwy 130",
    "iso:country":"US",
    "sg:address":"714 US Hwy 130",
    "sg:city":"Cinnaminson",
    "sg:classifiers":[
        {
            "category":"Banks & Credit Unions",
            "subcategory":"Bank",
            "type":"Services"
        }
    ],
    "sg:phone":"+1 856 000 1111",
    "sg:postcode":"08077",
    "sg:province":"NJ",
    "wof:name":"Bank Of America",
    "wof:placetype":"venue"
},
  "geometry": {"coordinates":[-74.994687,39.995772],"type":"Point"}
}