{
  "type": "Feature",
  "properties": {
    "addr:full":"7 Greenbriar Rd Marmora NJ 08223",
    "addr:housenumber":"7",
    "addr:postcode":"08223",
    "addr:street":"Greenbriar Rd",
    "iso:country":"US",
    "sg:address":"7 Greenbriar Rd",
    "sg:city":"Marmora",
    "sg:classifiers":[
        {
            "category":"Health Services",
            "subcategory":"Health Practitioner",
            "type":"Services"
        }
    ],
    "sg:phone":"+1 609 390 1325",
    "sg:postcode":"08223",
    "sg:province":"NJ",
    "sg:tags":[
        "pathologist",
        "speech"
    ],
    "wof:name":"Lauri Greenberg",
    "wof:placetype":"venue"
},
  "geometry": {"coordinates":[-74.65773,39.267834],"type":"Point"}
}