{
  "type": "Feature",
  "properties": {
    "iso:country":"US",
    "sg:address":"350 State Rte 17",
    "sg:city":"Saddle River",
    "sg:classifiers":[
        {
            "category":"Personal",
            "subcategory":"Beauty Salon",
            "type":"Services"
        }
    ],
    "sg:phone":"+1 201 785 0911",
    "sg:postcode":"07458",
    "sg:province":"NJ",
    "sg:tags":[
        "shop",
        "fitness",
        "physical",
        "manicuring",
        "facility"
    ],
    "wof:name":"Happy Nails & Spa",
    "wof:placetype":"venue"
},
  "geometry": {"coordinates":[-74.11882,41.051672],"type":"Point"}
}