{
  "type": "Feature",
  "properties": {
    "iso:country":"US",
    "sg:address":"130 Maple Ave",
    "sg:city":"Red Bank",
    "sg:classifiers":[
        {
            "category":"Building & Trades",
            "subcategory":"Construction",
            "type":"Services"
        }
    ],
    "sg:phone":"+1 732 530 1360",
    "sg:postcode":"07701",
    "sg:province":"NJ",
    "sg:tags":[
        "residential",
        "general",
        "commercial",
        "contractor"
    ],
    "wof:name":"Sharon Construction Corp",
    "wof:placetype":"venue"
},
  "geometry": {"coordinates":[-74.068528,40.346015],"type":"Point"}
}