{
  "type": "Feature",
  "properties": {
    "iso:country":"US",
    "sg:address":"7709 Park Ave",
    "sg:city":"Pennsauken",
    "sg:classifiers":[
        {
            "category":"Restaurant",
            "type":"Food & Drink"
        }
    ],
    "sg:phone":"+1 856 662 9467",
    "sg:postcode":"08109",
    "sg:province":"NJ",
    "sg:tags":[
        "pizza"
    ],
    "wof:name":"Pizza Castle",
    "wof:placetype":"venue"
},
  "geometry": {"coordinates":[-75.033203,39.959999],"type":"Point"}
}