{
  "type": "Feature",
  "properties": {
    "addr:full":"99 Northfield Ave 1st Fl West Orange NJ 07052",
    "addr:housenumber":"99",
    "addr:postcode":"07052",
    "addr:street":"Northfield Ave 1St",
    "iso:country":"US",
    "sg:address":"99 Northfield Ave 1st Fl",
    "sg:city":"West Orange",
    "sg:classifiers":[
        {
            "category":"Professional",
            "type":"Services"
        },
        {
            "category":"Personal",
            "type":"Services"
        }
    ],
    "sg:phone":"+1 973 985 4013",
    "sg:postcode":"07052",
    "sg:province":"NJ",
    "sg:tags":[
        "local"
    ],
    "wof:name":"Gabson Enterprises",
    "wof:placetype":"venue"
},
  "geometry": {"coordinates":[-74.24525300000001,40.77575],"type":"Point"}
}