{
  "type": "Feature",
  "properties": {
    "addr:full":"1 Ocean Blvd Long Branch NJ 07740",
    "addr:housenumber":"1",
    "addr:postcode":"07740",
    "addr:street":"Ocean Blvd",
    "iso:country":"US",
    "sg:address":"1 Ocean Blvd",
    "sg:city":"Long Branch",
    "sg:classifiers":[
        {
            "category":"Building & Trades",
            "subcategory":"Electrical",
            "type":"Services"
        }
    ],
    "sg:phone":"+1 732 222 2200",
    "sg:postcode":"07740",
    "sg:province":"NJ",
    "sg:tags":[
        "electric",
        "contractor"
    ],
    "wof:name":"Power Electric Co",
    "wof:placetype":"venue"
},
  "geometry": {"coordinates":[-73.98116899999999,40.303381],"type":"Point"}
}