{
  "type": "Feature",
  "properties": {
    "addr:full":"6 Continental Dr Sparta NJ 07871",
    "addr:housenumber":"6",
    "addr:postcode":"07871",
    "addr:street":"Continental Dr",
    "iso:country":"US",
    "sg:address":"6 Continental Dr",
    "sg:city":"Sparta",
    "sg:classifiers":[
        {
            "category":"Communications",
            "subcategory":"Film & Video Production",
            "type":"Services"
        }
    ],
    "sg:phone":"+1   ",
    "sg:postcode":"07871",
    "sg:province":"NJ",
    "sg:tags":[
        "motion",
        "picture"
    ],
    "wof:name":"Grade-A Media",
    "wof:placetype":"venue"
},
  "geometry": {"coordinates":[-74.63797,41.000946],"type":"Point"}
}