{
  "type": "Feature",
  "properties": {
    "addr:full":"417 N Grove St Berlin NJ 08009",
    "addr:housenumber":"417",
    "addr:postcode":"08009",
    "addr:street":"N Grove St",
    "iso:country":"US",
    "sg:address":"417 N Grove St",
    "sg:city":"Berlin",
    "sg:classifiers":[
        {
            "category":"Retail",
            "subcategory":"Auto Repair",
            "type":"Services"
        },
        {
            "category":"Manufacturing",
            "subcategory":"Tools & Machinery",
            "type":"Manufacturing & Wholesale Goods"
        }
    ],
    "sg:phone":"+1 856 767 7740",
    "sg:postcode":"08009",
    "sg:province":"NJ",
    "sg:tags":[
        "general"
    ],
    "wof:name":"D & F Performance",
    "wof:placetype":"venue"
},
  "geometry": {"coordinates":[-74.942061,39.76299],"type":"Point"}
}