{
  "type": "Feature",
  "properties": {
    "iso:country":"US",
    "sg:address":"430 Long Ave",
    "sg:city":"Hillside",
    "sg:classifiers":[
        {
            "category":"Restaurant",
            "type":"Food & Drink"
        }
    ],
    "sg:phone":"+1   ",
    "sg:postcode":"07205",
    "sg:province":"NJ",
    "sg:tags":[
        "eating"
    ],
    "wof:name":"Arcos Bar & Restaurant",
    "wof:placetype":"venue"
},
  "geometry": {"coordinates":[-74.236188,40.698728],"type":"Point"}
}