{
  "type": "Feature",
  "properties": {
    "iso:country":"US",
    "sg:address":"290 Jefferson Ave",
    "sg:city":"Cresskill",
    "sg:classifiers":[
        {
            "category":"Professional",
            "subcategory":"Management & Consulting",
            "type":"Services"
        }
    ],
    "sg:phone":"+1 201 567 0436",
    "sg:postcode":"07626",
    "sg:province":"NJ",
    "wof:name":"Creatique",
    "wof:placetype":"venue"
},
  "geometry": {"coordinates":[-73.969758,40.943827],"type":"Point"}
}