{
  "type": "Feature",
  "properties": {
    "iso:country":"US",
    "sg:address":"9 Centre Dr",
    "sg:city":"Monroe Township",
    "sg:classifiers":[
        {
            "category":"Health Services",
            "subcategory":"Doctor",
            "type":"Services"
        }
    ],
    "sg:phone":"+1 609 395 7615",
    "sg:postcode":"08831",
    "sg:province":"NJ",
    "sg:tags":[
        "medical"
    ],
    "wof:name":"Roger Behar MD",
    "wof:placetype":"venue"
},
  "geometry": {"coordinates":[-74.46316299999999,40.338672],"type":"Point"}
}