{
  "type": "Feature",
  "properties": {
    "addr:full":"Tucker Florham Park NJ 07932",
    "addr:postcode":"07932",
    "iso:country":"US",
    "sg:address":"Tucker",
    "sg:city":"Florham Park",
    "sg:classifiers":[
        {
            "category":"Retail",
            "subcategory":"Event Space",
            "type":"Services"
        }
    ],
    "sg:phone":"+1 973 377 9650",
    "sg:postcode":"07932",
    "sg:province":"NJ",
    "sg:tags":[
        "venue"
    ],
    "wof:name":"Holy Family Auditorium",
    "wof:placetype":"venue"
},
  "geometry": {"coordinates":[-74.38960299999999,40.776798],"type":"Point"}
}