{
  "type": "Feature",
  "properties": {
    "addr:full":"1044 Lacey Rd Forked River NJ 08731",
    "addr:housenumber":"1044",
    "addr:postcode":"08731",
    "addr:street":"Lacey Rd",
    "iso:country":"US",
    "sg:address":"1044 Lacey Rd",
    "sg:city":"Forked River",
    "sg:classifiers":[
        {
            "category":"Social Services",
            "type":"Services"
        }
    ],
    "sg:phone":"+1 609 971 1105",
    "sg:postcode":"08731",
    "sg:province":"NJ",
    "sg:tags":[
        "counseling"
    ],
    "wof:name":"Eileen Tangeman",
    "wof:placetype":"venue"
},
  "geometry": {"coordinates":[-74.216239,39.862633],"type":"Point"}
}