{
  "type": "Feature",
  "properties": {
    "iso:country":"US",
    "sg:address":"201 Whitehead Ave",
    "sg:city":"South River",
    "sg:classifiers":[
        {
            "category":"Organizations",
            "subcategory":"Religious Organization",
            "type":"Services"
        }
    ],
    "sg:phone":"+1 732 257 0779",
    "sg:postcode":"08882",
    "sg:province":"NJ",
    "sg:tags":[
        "church"
    ],
    "wof:name":"Igreja Batista Missionaria",
    "wof:placetype":"venue"
},
  "geometry": {"coordinates":[-74.377588,40.450224],"type":"Point"}
}