{
  "type": "Feature",
  "properties": {
    "iso:country":"US",
    "sg:address":"52 Edwina Ct",
    "sg:city":"Dayton",
    "sg:classifiers":[
        {
            "category":"Professional",
            "subcategory":"Business Services",
            "type":"Services"
        }
    ],
    "sg:phone":"+1   ",
    "sg:postcode":"08810",
    "sg:province":"NJ",
    "wof:name":"Presdon Enterprises Inc",
    "wof:placetype":"venue"
},
  "geometry": {"coordinates":[-74.521665,40.383293],"type":"Point"}
}