{
  "type": "Feature",
  "properties": {
    "iso:country":"US",
    "sg:address":"29 Schalk St",
    "sg:city":"Newark",
    "sg:classifiers":[
        {
            "category":"Professional",
            "type":"Services"
        }
    ],
    "sg:phone":"+1 212 620 0580",
    "sg:postcode":"07105",
    "sg:province":"NJ",
    "sg:tags":[
        "establishment"
    ],
    "wof:name":"Diehl M",
    "wof:placetype":"venue"
},
  "geometry": {"coordinates":[-74.14068899999999,40.733552],"type":"Point"}
}