{
  "type": "Feature",
  "properties": {
    "addr:full":"234 Main St Paterson NJ 07505",
    "addr:housenumber":"234",
    "addr:postcode":"07505",
    "addr:street":"Main St",
    "iso:country":"US",
    "sg:address":"234 Main St",
    "sg:city":"Paterson",
    "sg:classifiers":[
        {
            "category":"Shopping",
            "subcategory":"Computers & Home Electronics",
            "type":"Retail Goods"
        }
    ],
    "sg:phone":"+1   ",
    "sg:postcode":"07505",
    "sg:province":"NJ",
    "wof:name":"Audio Video International Inc",
    "wof:placetype":"venue"
},
  "geometry": {"coordinates":[-74.17325,40.917037],"type":"Point"}
}