{
  "type": "Feature",
  "properties": {
    "addr:full":"4 5th St New Brunswick NJ 08901",
    "addr:housenumber":"4",
    "addr:postcode":"08901",
    "addr:street":"5Th St",
    "iso:country":"US",
    "sg:address":"4 5th St",
    "sg:city":"New Brunswick",
    "sg:classifiers":[
        {
            "category":"Building & Trades",
            "subcategory":"Landscaping Services",
            "type":"Services"
        }
    ],
    "sg:phone":"+1 732 545 5932",
    "sg:postcode":"08901",
    "sg:province":"NJ",
    "wof:name":"Jersey Landscape Cnstr Contr",
    "wof:placetype":"venue"
},
  "geometry": {"coordinates":[-74.465059,40.475779],"type":"Point"}
}