{
  "type": "Feature",
  "properties": {
    "addr:full":"26 Franklin St Tenafly NJ 07670",
    "addr:housenumber":"26",
    "addr:postcode":"07670",
    "addr:street":"Franklin St",
    "iso:country":"US",
    "sg:address":"26 Franklin St",
    "sg:city":"Tenafly",
    "sg:classifiers":[
        {
            "category":"Professional",
            "subcategory":"Lawyer & Legal Services",
            "type":"Services"
        }
    ],
    "sg:phone":"+1   ",
    "sg:postcode":"07670",
    "sg:province":"NJ",
    "sg:tags":[
        "law",
        "general"
    ],
    "wof:name":"Bell Allen M",
    "wof:placetype":"venue"
},
  "geometry": {"coordinates":[-73.965965,40.922189],"type":"Point"}
}