{
  "type": "Feature",
  "properties": {
    "addr:full":"11 Dehart St Morristown NJ 07960",
    "addr:housenumber":"11",
    "addr:postcode":"07960",
    "addr:street":"Dehart St",
    "iso:country":"US",
    "sg:address":"11 Dehart St",
    "sg:city":"Morristown",
    "sg:classifiers":[
        {
            "category":"Personal",
            "subcategory":"Tanning Parlor",
            "type":"Services"
        }
    ],
    "sg:phone":"+1 973 889 0800",
    "sg:postcode":"07960",
    "sg:province":"NJ",
    "sg:tags":[
        "salon"
    ],
    "wof:name":"Hollywood Tans",
    "wof:placetype":"venue"
},
  "geometry": {"coordinates":[-74.481128,40.795196],"type":"Point"}
}