{
  "type": "Feature",
  "properties": {
    "iso:country":"US",
    "sg:address":"1200 State Rte 35",
    "sg:city":"Middletown",
    "sg:classifiers":[
        {
            "category":"Home & Garden",
            "subcategory":"Furniture",
            "type":"Retail Goods"
        }
    ],
    "sg:phone":"+1   ",
    "sg:postcode":"07748",
    "sg:province":"NJ",
    "wof:name":"Value City",
    "wof:placetype":"venue"
},
  "geometry": {"coordinates":[-74.112612,40.398092],"type":"Point"}
}