{
  "type": "Feature",
  "properties": {
    "iso:country":"US",
    "sg:address":"481 Valley Rd",
    "sg:city":"West Orange",
    "sg:classifiers":[
        {
            "category":"Retail",
            "subcategory":"Laundry & Dry Cleaning",
            "type":"Services"
        }
    ],
    "sg:phone":"+1 973 678 1033",
    "sg:postcode":"07052",
    "sg:province":"NJ",
    "wof:name":"Glassman Cleaners",
    "wof:placetype":"venue"
},
  "geometry": {"coordinates":[-74.243599,40.771702],"type":"Point"}
}