{
  "type": "Feature",
  "properties": {
    "iso:country":"US",
    "sg:address":"80 S Orange Ave",
    "sg:city":"South Orange",
    "sg:classifiers":[
        {
            "category":"Professional",
            "type":"Services"
        }
    ],
    "sg:phone":"+1   ",
    "sg:postcode":"07079",
    "sg:province":"NJ",
    "wof:name":"Inspired Heritage",
    "wof:placetype":"venue"
},
  "geometry": {"coordinates":[-74.257831,40.745613],"type":"Point"}
}