{
  "type": "Feature",
  "properties": {
    "addr:full":"1635 Glendola Rd Wall Township NJ 07719",
    "addr:housenumber":"1635",
    "addr:postcode":"07719",
    "addr:street":"Glendola Rd",
    "iso:country":"US",
    "sg:address":"1635 Glendola Rd",
    "sg:city":"Wall Township",
    "sg:classifiers":[
        {
            "category":"Professional",
            "subcategory":"Computer Services",
            "type":"Services"
        }
    ],
    "sg:phone":"+1 732 280 8926",
    "sg:postcode":"07719",
    "sg:province":"NJ",
    "sg:tags":[
        "internet"
    ],
    "wof:name":"Web Start Designs",
    "wof:placetype":"venue"
},
  "geometry": {"coordinates":[-74.07655200000001,40.184922],"type":"Point"}
}