{
  "type": "Feature",
  "properties": {
    "addr:full":"28 Millburn Ave Springfield NJ 07081",
    "addr:housenumber":"28",
    "addr:postcode":"07081",
    "addr:street":"Millburn Ave",
    "iso:country":"US",
    "sg:address":"28 Millburn Ave",
    "sg:city":"Springfield",
    "sg:classifiers":[
        {
            "category":"Health Services",
            "subcategory":"Dentist",
            "type":"Services"
        }
    ],
    "sg:phone":"+1 973 218 9190",
    "sg:postcode":"07081",
    "sg:province":"NJ",
    "wof:name":"Yambao Maria DDS",
    "wof:placetype":"venue"
},
  "geometry": {"coordinates":[-74.324218,40.717536],"type":"Point"}
}