{
  "type": "Feature",
  "properties": {
    "iso:country":"US",
    "sg:address":"1136 Empire Ave",
    "sg:city":"Camden",
    "sg:classifiers":[
        {
            "category":"Freight",
            "type":"Transportation"
        }
    ],
    "sg:phone":"+1 609 792 0335",
    "sg:postcode":"08103",
    "sg:province":"NJ",
    "sg:tags":[
        "local",
        "trucking"
    ],
    "wof:name":"Sob Trucking",
    "wof:placetype":"venue"
},
  "geometry": {"coordinates":[-75.103173,39.935978],"type":"Point"}
}