{
  "type": "Feature",
  "properties": {
    "iso:country":"US",
    "sg:address":"2 Hudson Pl",
    "sg:city":"Hoboken",
    "sg:classifiers":[
        {
            "category":"Utilities",
            "subcategory":"Telephone",
            "type":"Services"
        }
    ],
    "sg:phone":"+1 201 795 3883",
    "sg:postcode":"07030",
    "sg:province":"NJ",
    "sg:tags":[
        "communications",
        "telecommunication",
        "radiotelephone",
        "communication"
    ],
    "sg:website":"www.tti-telecom.com",
    "wof:name":"TTI Team Telecom Intl Inc",
    "wof:placetype":"venue"
},
  "geometry": {"coordinates":[-74.029218,40.735825],"type":"Point"}
}