{
  "type": "Feature",
  "properties": {
    "iso:country":"US",
    "sg:address":"141 Eagle Rock Ave",
    "sg:city":"Roseland",
    "sg:classifiers":[
        {
            "category":"Organizations",
            "subcategory":"Religious Organization",
            "type":"Services"
        }
    ],
    "sg:phone":"+1 973 226 8340",
    "sg:postcode":"07068",
    "sg:province":"NJ",
    "sg:tags":[
        "clergy"
    ],
    "wof:name":"Charles H Peet",
    "wof:placetype":"venue"
},
  "geometry": {"coordinates":[-74.29177799999999,40.820571],"type":"Point"}
}