{
  "type": "Feature",
  "properties": {
    "addr:full":"405 S Pitney Rd Galloway NJ 08205",
    "addr:housenumber":"405",
    "addr:postcode":"08205",
    "addr:street":"S Pitney Rd",
    "iso:country":"US",
    "sg:address":"405 S Pitney Rd",
    "sg:city":"Galloway",
    "sg:classifiers":[
        {
            "category":"Utilities",
            "subcategory":"Mobile Phone",
            "type":"Services"
        },
        {
            "category":"Coffee & Tea",
            "type":"Food & Drink"
        }
    ],
    "sg:phone":"+1 609 748 4962",
    "sg:postcode":"08205",
    "sg:province":"NJ",
    "sg:tags":[
        "shop",
        "wi-fi",
        "espresso",
        "hotspot",
        "restaurant"
    ],
    "sg:website":"http://www.starbuckscoffee.com",
    "wof:name":"Starbucks Coffee",
    "wof:placetype":"venue"
},
  "geometry": {"coordinates":[-74.49413,39.462513],"type":"Point"}
}