{
  "type": "Feature",
  "properties": {
    "addr:full":"1452 Back Line Rd Hammonton NJ 08037",
    "addr:housenumber":"1452",
    "addr:postcode":"08037",
    "addr:street":"Back Line Rd",
    "iso:country":"US",
    "sg:address":"1452 Back Line Rd",
    "sg:city":"Hammonton",
    "sg:classifiers":[
        {
            "category":"Professional",
            "subcategory":"Management & Consulting",
            "type":"Services"
        }
    ],
    "sg:phone":"+1   ",
    "sg:postcode":"08037",
    "sg:province":"NJ",
    "sg:tags":[
        "beverage",
        "direct",
        "sales"
    ],
    "wof:name":"Hammonton Beverage Inc",
    "wof:placetype":"venue"
},
  "geometry": {"coordinates":[-74.851709,39.605413],"type":"Point"}
}