{
  "type": "Feature",
  "properties": {
    "addr:full":"75 Morristown Rd Bernardsville NJ 07924",
    "addr:housenumber":"75",
    "addr:postcode":"07924",
    "addr:street":"Morristown Rd",
    "iso:country":"US",
    "sg:address":"75 Morristown Rd",
    "sg:city":"Bernardsville",
    "sg:classifiers":[
        {
            "category":"Restaurant",
            "type":"Food & Drink"
        }
    ],
    "sg:phone":"+1   ",
    "sg:postcode":"07924",
    "sg:province":"NJ",
    "sg:tags":[
        "eating"
    ],
    "wof:name":"China Palace",
    "wof:placetype":"venue"
},
  "geometry": {"coordinates":[-74.56528400000001,40.718811],"type":"Point"}
}