{
  "type": "Feature",
  "properties": {
    "iso:country":"US",
    "sg:address":"457 9th Ave",
    "sg:city":"Paterson",
    "sg:classifiers":[
        {
            "category":"Retail",
            "subcategory":"Auto Repair",
            "type":"Services"
        }
    ],
    "sg:phone":"+1 973 754 6125",
    "sg:postcode":"07514",
    "sg:province":"NJ",
    "sg:tags":[
        "automobile",
        "lubrication"
    ],
    "wof:name":"Lube Xpress Co Inc",
    "wof:placetype":"venue"
},
  "geometry": {"coordinates":[-74.142939,40.92588],"type":"Point"}
}