{
  "type": "Feature",
  "properties": {
    "iso:country":"US",
    "sg:address":"1763 John F Kennedy Blvd",
    "sg:city":"Jersey City",
    "sg:classifiers":[
        {
            "category":"Travel",
            "subcategory":"Travel Agent",
            "type":"Entertainment"
        }
    ],
    "sg:phone":"+1 201 433 1127",
    "sg:postcode":"07305",
    "sg:province":"NJ",
    "sg:tags":[
        "agency",
        "bureau"
    ],
    "wof:name":"Donia Travel",
    "wof:placetype":"venue"
},
  "geometry": {"coordinates":[-74.093287,40.701157],"type":"Point"}
}