{
  "type": "Feature",
  "properties": {
    "addr:full":"15 Cutter Ave Fords NJ 08863",
    "addr:housenumber":"15",
    "addr:postcode":"08863",
    "addr:street":"Cutter Ave",
    "iso:country":"US",
    "sg:address":"15 Cutter Ave",
    "sg:city":"Fords",
    "sg:classifiers":[
        {
            "category":"Freight",
            "type":"Transportation"
        }
    ],
    "sg:phone":"+1 732 661 2012",
    "sg:postcode":"08863",
    "sg:province":"NJ",
    "sg:tags":[
        "trucking"
    ],
    "wof:name":"Andres Trucking",
    "wof:placetype":"venue"
},
  "geometry": {"coordinates":[-74.31574000000001,40.53885],"type":"Point"}
}