{
  "type": "Feature",
  "properties": {
    "iso:country":"US",
    "sg:address":"1308 Saint Georges Ave",
    "sg:city":"Avenel",
    "sg:classifiers":[
        {
            "category":"Education",
            "subcategory":"Dance Studio",
            "type":"Public Place"
        }
    ],
    "sg:phone":"+1 732 636 4740",
    "sg:postcode":"07001",
    "sg:province":"NJ",
    "sg:tags":[
        "art",
        "performing",
        "instruction",
        "dancing"
    ],
    "wof:name":"Woodbridge School of Dance",
    "wof:placetype":"venue"
},
  "geometry": {"coordinates":[-74.2929,40.583302],"type":"Point"}
}