{
  "type": "Feature",
  "properties": {
    "addr:full":"824 Valley Rd Montclair NJ 07043",
    "addr:housenumber":"824",
    "addr:postcode":"07043",
    "addr:street":"Valley Rd",
    "iso:country":"US",
    "sg:address":"824 Valley Rd",
    "sg:city":"Montclair",
    "sg:classifiers":[
        {
            "category":"Building & Trades",
            "subcategory":"Construction",
            "type":"Services"
        }
    ],
    "sg:phone":"+1 973 746 0782",
    "sg:postcode":"07043",
    "sg:province":"NJ",
    "sg:tags":[
        "house",
        "general",
        "contractor"
    ],
    "wof:name":"Four Ms Construction & Mgmt",
    "wof:placetype":"venue"
},
  "geometry": {"coordinates":[-74.18945100000001,40.871194],"type":"Point"}
}