{
  "type": "Feature",
  "properties": {
    "addr:full":"843 Nancy Way Westfield NJ 07090",
    "addr:housenumber":"843",
    "addr:postcode":"07090",
    "addr:street":"Nancy Way",
    "iso:country":"US",
    "sg:address":"843 Nancy Way",
    "sg:city":"Westfield",
    "sg:classifiers":[
        {
            "category":"Professional",
            "subcategory":"Management & Consulting",
            "type":"Services"
        }
    ],
    "sg:phone":"+1   ",
    "sg:postcode":"07090",
    "sg:province":"NJ",
    "wof:name":"Solid Solutions",
    "wof:placetype":"venue"
},
  "geometry": {"coordinates":[-74.34658,40.63136],"type":"Point"}
}