{
  "type": "Feature",
  "properties": {
    "iso:country":"US",
    "sg:address":"1946 N Black Horse Pike",
    "sg:city":"Williamstown",
    "sg:classifiers":[
        {
            "category":"Shopping",
            "type":"Retail Goods"
        }
    ],
    "sg:phone":"+1   ",
    "sg:postcode":"08094",
    "sg:province":"NJ",
    "sg:tags":[
        "merchandise"
    ],
    "wof:name":"Discount Trailer Warehouse",
    "wof:placetype":"venue"
},
  "geometry": {"coordinates":[-75.017723,39.71443],"type":"Point"}
}