{
  "type": "Feature",
  "properties": {
    "iso:country":"US",
    "sg:address":"254 Washington St",
    "sg:city":"Newark",
    "sg:classifiers":[
        {
            "category":"Restaurant",
            "type":"Food & Drink"
        }
    ],
    "sg:menulink":"http://www.allmenus.com/nj/newark/27119-crown-fried-chicken/menu/",
    "sg:phone":"+1 973 642 8442",
    "sg:postcode":"07102",
    "sg:province":"NJ",
    "sg:tags":[
        "chicken",
        "american"
    ],
    "wof:name":"Crown Fried Chicken",
    "wof:placetype":"venue"
},
  "geometry": {"coordinates":[-74.17532799999999,40.73622],"type":"Point"}
}