{
  "type": "Feature",
  "properties": {
    "iso:country":"US",
    "sg:address":"7 Naughright Rd",
    "sg:city":"Hackettstown",
    "sg:classifiers":[
        {
            "category":"Restaurant",
            "type":"Food & Drink"
        }
    ],
    "sg:menulink":"http://www.allmenus.com/nj/mount-olive/16614-franks-pizza/menu/",
    "sg:phone":"+1 908 979 3113",
    "sg:postcode":"07840",
    "sg:province":"NJ",
    "sg:tags":[
        "italian"
    ],
    "wof:name":"Frank's Pizza",
    "wof:placetype":"venue"
},
  "geometry": {"coordinates":[-74.782746,40.851549],"type":"Point"}
}