{
  "type": "Feature",
  "properties": {
    "iso:country":"US",
    "sg:address":"25 Hoffman Ave",
    "sg:city":"Lake Hiawatha",
    "sg:classifiers":[
        {
            "category":"Autos & Motor Vehicles",
            "subcategory":"Recreational Vehicle Sales",
            "type":"Retail Goods"
        }
    ],
    "sg:phone":"+1 973 299 0290",
    "sg:postcode":"07034",
    "sg:province":"NJ",
    "wof:name":"Paul's Auto Repairs RV Svc",
    "wof:placetype":"venue"
},
  "geometry": {"coordinates":[-74.378563,40.886047],"type":"Point"}
}