{
  "type": "Feature",
  "properties": {
    "iso:country":"US",
    "sg:address":"58 Weber Ave",
    "sg:city":"Trenton",
    "sg:classifiers":[
        {
            "category":"Building & Trades",
            "subcategory":"Construction",
            "type":"Services"
        }
    ],
    "sg:phone":"+1 609 883 2201",
    "sg:postcode":"08638",
    "sg:province":"NJ",
    "sg:tags":[
        "contractor"
    ],
    "wof:name":"Edward Enourato & Sons",
    "wof:placetype":"venue"
},
  "geometry": {"coordinates":[-74.76632499999999,40.240595],"type":"Point"}
}