{
  "type": "Feature",
  "properties": {
    "addr:full":"60 Essex St Harrison NJ 07029",
    "addr:housenumber":"60",
    "addr:postcode":"07029",
    "addr:street":"Essex St",
    "iso:country":"US",
    "sg:address":"60 Essex St",
    "sg:city":"Harrison",
    "sg:classifiers":[
        {
            "category":"Building & Trades",
            "subcategory":"Construction",
            "type":"Services"
        }
    ],
    "sg:phone":"+1 973 268 2468",
    "sg:postcode":"07029",
    "sg:province":"NJ",
    "sg:tags":[
        "marking",
        "maintenance",
        "parking"
    ],
    "wof:name":"Harrison Street Dept Garage",
    "wof:placetype":"venue"
},
  "geometry": {"coordinates":[-74.16257299999999,40.742235],"type":"Point"}
}