{
  "type": "Feature",
  "properties": {
    "iso:country":"US",
    "sg:address":"340 Westfield Ave E",
    "sg:city":"Roselle Park",
    "sg:classifiers":[
        {
            "category":"Home & Garden",
            "subcategory":"Building Materials",
            "type":"Retail Goods"
        }
    ],
    "sg:phone":"+1 908 245 7831",
    "sg:postcode":"07204",
    "sg:province":"NJ",
    "sg:tags":[
        "paint"
    ],
    "wof:name":"Newark Paint II Inc",
    "wof:placetype":"venue"
},
  "geometry": {"coordinates":[-74.251829,40.663245],"type":"Point"}
}