{
  "type": "Feature",
  "properties": {
    "iso:country":"US",
    "sg:address":"123 E Main St",
    "sg:city":"Moorestown",
    "sg:classifiers":[
        {
            "category":"Professional",
            "subcategory":"Advertising",
            "type":"Services"
        }
    ],
    "sg:phone":"+1 856 234 9777",
    "sg:postcode":"08057",
    "sg:province":"NJ",
    "sg:tags":[
        "commercial",
        "agency",
        "design"
    ],
    "wof:name":"Imagine That",
    "wof:placetype":"venue"
},
  "geometry": {"coordinates":[-74.94168500000001,39.965696],"type":"Point"}
}