{
  "type": "Feature",
  "properties": {
    "iso:country":"US",
    "sg:address":"105 Mount Ln",
    "sg:city":"Manasquan",
    "sg:classifiers":[
        {
            "category":"Building & Trades",
            "subcategory":"Landscaping Services",
            "type":"Services"
        }
    ],
    "sg:phone":"+1 732 255 7806",
    "sg:postcode":"08736",
    "sg:province":"NJ",
    "sg:tags":[
        "landscape",
        "contractor"
    ],
    "wof:name":"J P & E",
    "wof:placetype":"venue"
},
  "geometry": {"coordinates":[-74.048981,40.118632],"type":"Point"}
}