{
  "type": "Feature",
  "properties": {
    "addr:full":"12 Melrose Dr Chester NJ 07930",
    "addr:housenumber":"12",
    "addr:postcode":"07930",
    "addr:street":"Melrose Dr",
    "iso:country":"US",
    "sg:address":"12 Melrose Dr",
    "sg:city":"Chester",
    "sg:classifiers":[
        {
            "category":"Organizations",
            "subcategory":"Religious Organization",
            "type":"Services"
        }
    ],
    "sg:phone":"+1 908 879 5061",
    "sg:postcode":"07930",
    "sg:province":"NJ",
    "sg:tags":[
        "church"
    ],
    "wof:name":"Grace Bible Chapel",
    "wof:placetype":"venue"
},
  "geometry": {"coordinates":[-74.68851600000001,40.795006],"type":"Point"}
}