{
  "type": "Feature",
  "properties": {
    "iso:country":"US",
    "sg:address":"975 Joyce Kilmer Ave",
    "sg:city":"North Brunswick",
    "sg:classifiers":[
        {
            "category":"Taxi",
            "type":"Transportation"
        }
    ],
    "sg:phone":"+1 732 249 6606",
    "sg:postcode":"08902",
    "sg:province":"NJ",
    "sg:tags":[
        "taxicab"
    ],
    "wof:name":"Yellow Cab Of North Brunswick",
    "wof:placetype":"venue"
},
  "geometry": {"coordinates":[-74.47111599999999,40.470527],"type":"Point"}
}