{
  "type": "Feature",
  "properties": {
    "iso:country":"US",
    "sg:address":"1306 Brielle Ave",
    "sg:city":"Ocean",
    "sg:classifiers":[
        {
            "category":"Freight",
            "type":"Transportation"
        }
    ],
    "sg:phone":"+1 732 493 8888",
    "sg:postcode":"07712",
    "sg:province":"NJ",
    "wof:name":"Seman Tov Inc",
    "wof:placetype":"venue"
},
  "geometry": {"coordinates":[-74.045483,40.240497],"type":"Point"}
}