{
  "type": "Feature",
  "properties": {
    "iso:country":"US",
    "sg:address":"311 Pequest Rd",
    "sg:city":"Andover",
    "sg:classifiers":[
        {
            "category":"Home & Garden",
            "subcategory":"Garden Supply",
            "type":"Retail Goods"
        }
    ],
    "sg:phone":"+1 973 786 5429",
    "sg:postcode":"07821",
    "sg:province":"NJ",
    "sg:tags":[
        "ornamental",
        "center",
        "orchard",
        "farm",
        "tree",
        "fruit"
    ],
    "wof:name":"Cahill's Farm",
    "wof:placetype":"venue"
},
  "geometry": {"coordinates":[-74.767043,40.982156],"type":"Point"}
}