{
  "type": "Feature",
  "properties": {
    "iso:country":"US",
    "sg:address":"130 Hancock Ln",
    "sg:city":"Mount Holly",
    "sg:classifiers":[
        {
            "category":"Wholesale",
            "subcategory":"Machinery & Supplies",
            "type":"Manufacturing & Wholesale Goods"
        }
    ],
    "sg:phone":"+1 609 267 1852",
    "sg:postcode":"08060",
    "sg:province":"NJ",
    "sg:tags":[
        "janitorial",
        "cleaning"
    ],
    "wof:name":"Evergreen Building Maint Inc",
    "wof:placetype":"venue"
},
  "geometry": {"coordinates":[-74.814094,40.029155],"type":"Point"}
}