{
  "type": "Feature",
  "properties": {
    "addr:full":"135 Sylvania Ave Avon By The Sea NJ 07717",
    "addr:housenumber":"135",
    "addr:postcode":"07717",
    "addr:street":"Sylvania Ave",
    "iso:country":"US",
    "sg:address":"135 Sylvania Ave",
    "sg:city":"Avon By The Sea",
    "sg:classifiers":[
        {
            "category":"Building & Trades",
            "subcategory":"Plumbing",
            "type":"Services"
        }
    ],
    "sg:phone":"+1 732 349 1954",
    "sg:postcode":"07717",
    "sg:province":"NJ",
    "sg:tags":[
        "plumbing",
        "contractor"
    ],
    "wof:name":"Wright H I and Son Plumbing",
    "wof:placetype":"venue"
},
  "geometry": {"coordinates":[-74.01342699999999,40.191984],"type":"Point"}
}