{
  "type": "Feature",
  "properties": {
    "iso:country":"US",
    "sg:address":"2 Mount Prospect Ave",
    "sg:city":"Dover",
    "sg:classifiers":[
        {
            "category":"Health Services",
            "subcategory":"Doctor",
            "type":"Services"
        }
    ],
    "sg:phone":"+1 973 366 0694",
    "sg:postcode":"07801",
    "sg:province":"NJ",
    "sg:tags":[
        "dentist"
    ],
    "wof:name":"David L Stevens DDS",
    "wof:placetype":"venue"
},
  "geometry": {"coordinates":[-74.53126899999999,40.887522],"type":"Point"}
}