{
  "type": "Feature",
  "properties": {
    "iso:country":"US",
    "sg:address":"7 Quail Mews",
    "sg:city":"North Brunswick",
    "sg:classifiers":[
        {
            "category":"Health Services",
            "subcategory":"Health Practitioner",
            "type":"Services"
        }
    ],
    "sg:phone":"+1 732 297 7273",
    "sg:postcode":"08902",
    "sg:province":"NJ",
    "sg:tags":[
        "pathologist",
        "speech"
    ],
    "wof:name":"Dianne Finkelstein",
    "wof:placetype":"venue"
},
  "geometry": {"coordinates":[-74.510645,40.452094],"type":"Point"}
}