{
  "type": "Feature",
  "properties": {
    "iso:country":"US",
    "sg:address":"1544 Irving St",
    "sg:city":"Rahway",
    "sg:classifiers":[
        {
            "category":"Real Estate",
            "subcategory":"Developer",
            "type":"Services"
        },
        {
            "category":"Real Estate",
            "subcategory":"Real Estate Operator",
            "type":"Services"
        }
    ],
    "sg:phone":"+1 732 574 1339",
    "sg:postcode":"07065",
    "sg:province":"NJ",
    "sg:tags":[
        "building",
        "owner",
        "commercial",
        "d"
    ],
    "wof:name":"Carol Realty & Development Co",
    "wof:placetype":"venue"
},
  "geometry": {"coordinates":[-74.27627099999999,40.608519],"type":"Point"}
}