{
  "type": "Feature",
  "properties": {
    "addr:full":"1435 46th St North Bergen NJ 07047",
    "addr:housenumber":"1435",
    "addr:postcode":"07047",
    "addr:street":"46Th St",
    "iso:country":"US",
    "sg:address":"1435 46th St",
    "sg:city":"North Bergen",
    "sg:classifiers":[
        {
            "category":"Professional",
            "subcategory":"Lawyer & Legal Services",
            "type":"Services"
        }
    ],
    "sg:phone":"+1 201 867 7609",
    "sg:postcode":"07047",
    "sg:province":"NJ",
    "wof:name":"Bal Eric J Lawyer",
    "wof:placetype":"venue"
},
  "geometry": {"coordinates":[-74.029999,40.783699],"type":"Point"}
}