{
  "type": "Feature",
  "properties": {
    "iso:country":"US",
    "sg:address":"605 Newark Pompton Tpke",
    "sg:city":"Pompton Plains",
    "sg:classifiers":[
        {
            "category":"Insurance",
            "subcategory":"Insurance Agent",
            "type":"Services"
        }
    ],
    "sg:phone":"+1 973 492 3900",
    "sg:postcode":"07444",
    "sg:province":"NJ",
    "wof:name":"R B A Benefits Group Inc",
    "wof:placetype":"venue"
},
  "geometry": {"coordinates":[-74.29598300000001,40.968209],"type":"Point"}
}