{
  "type": "Feature",
  "properties": {
    "addr:full":"1738 Bay Blvd Pt Pleasant Bch NJ 08742",
    "addr:housenumber":"1738",
    "addr:postcode":"08742",
    "addr:street":"Bay Blvd Pt",
    "iso:country":"US",
    "sg:address":"1738 Bay Blvd",
    "sg:city":"Pt Pleasant Bch",
    "sg:classifiers":[
        {
            "category":"Real Estate",
            "subcategory":"Real Estate Agent",
            "type":"Services"
        }
    ],
    "sg:phone":"+1 732 892 0147",
    "sg:postcode":"08742",
    "sg:province":"NJ",
    "wof:name":"Harbor Appraisal Company",
    "wof:placetype":"venue"
},
  "geometry": {"coordinates":[-74.054557,40.064501],"type":"Point"}
}