{
  "type": "Feature",
  "properties": {
    "addr:full":"450 7th St Hoboken NJ 07030",
    "addr:housenumber":"450",
    "addr:postcode":"07030",
    "addr:street":"7Th St",
    "iso:country":"US",
    "sg:address":"450 7th St",
    "sg:city":"Hoboken",
    "sg:classifiers":[
        {
            "category":"Education",
            "subcategory":"Special Training",
            "type":"Public Place"
        }
    ],
    "sg:phone":"+1 201 792 6696",
    "sg:postcode":"07030",
    "sg:province":"NJ",
    "sg:tags":[
        "educational"
    ],
    "wof:name":"Hoboken Education Assn",
    "wof:placetype":"venue"
},
  "geometry": {"coordinates":[-74.03591400000001,40.746053],"type":"Point"}
}