{
  "type": "Feature",
  "properties": {
    "iso:country":"US",
    "sg:address":"201 Mayfair Rd",
    "sg:city":"Paramus",
    "sg:classifiers":[
        {
            "category":"Manufacturing",
            "subcategory":"Rubber & Plastics",
            "type":"Manufacturing & Wholesale Goods"
        }
    ],
    "sg:phone":"+1 201 612 3242",
    "sg:postcode":"07652",
    "sg:province":"NJ",
    "sg:tags":[
        "producer"
    ],
    "wof:name":"Mississippi Polymers",
    "wof:placetype":"venue"
},
  "geometry": {"coordinates":[-74.091537,40.95744],"type":"Point"}
}