{
  "type": "Feature",
  "properties": {
    "iso:country":"US",
    "sg:address":"360 Grove St",
    "sg:city":"Jersey City",
    "sg:classifiers":[
        {
            "category":"Social Services",
            "subcategory":"Child Care",
            "type":"Services"
        }
    ],
    "sg:phone":"+1 201 798 0343",
    "sg:postcode":"07302",
    "sg:province":"NJ",
    "sg:tags":[
        "day"
    ],
    "wof:name":"Baby Galileo Preschool & Daycare",
    "wof:placetype":"venue"
},
  "geometry": {"coordinates":[-74.042571,40.720977],"type":"Point"}
}