{
  "type": "Feature",
  "properties": {
    "addr:full":"147 Piermont Rd Tenafly NJ 07670",
    "addr:housenumber":"147",
    "addr:postcode":"07670",
    "addr:street":"Piermont Rd",
    "iso:country":"US",
    "sg:address":"147 Piermont Rd",
    "sg:city":"Tenafly",
    "sg:classifiers":[
        {
            "category":"Retail",
            "subcategory":"Auto Repair",
            "type":"Services"
        }
    ],
    "sg:phone":"+1 201 569 1382",
    "sg:postcode":"07670",
    "sg:province":"NJ",
    "sg:tags":[
        "body",
        "wash",
        "car"
    ],
    "wof:name":"Clarke Brud Auto Body Shop",
    "wof:placetype":"venue"
},
  "geometry": {"coordinates":[-73.962332,40.93749],"type":"Point"}
}