{
  "type": "Feature",
  "properties": {
    "iso:country":"US",
    "sg:address":"3391 State Rte 27",
    "sg:city":"Franklin Park",
    "sg:classifiers":[
        {
            "category":"Shopping",
            "subcategory":"Hobbies, Toys, & Games",
            "type":"Retail Goods"
        }
    ],
    "sg:phone":"+1   ",
    "sg:postcode":"08823",
    "sg:province":"NJ",
    "wof:name":"Planet Pets",
    "wof:placetype":"venue"
},
  "geometry": {"coordinates":[-74.556304,40.429723],"type":"Point"}
}