{
  "type": "Feature",
  "properties": {
    "addr:full":"464 Ash Ave Absecon NJ 08201",
    "addr:housenumber":"464",
    "addr:postcode":"08201",
    "addr:street":"Ash Ave",
    "iso:country":"US",
    "sg:address":"464 Ash Ave",
    "sg:city":"Absecon",
    "sg:classifiers":[
        {
            "category":"Professional",
            "subcategory":"Accounting & Tax Preparation",
            "type":"Services"
        }
    ],
    "sg:phone":"+1   ",
    "sg:postcode":"08201",
    "sg:province":"NJ",
    "wof:name":"Whittles J Bookkeeping",
    "wof:placetype":"venue"
},
  "geometry": {"coordinates":[-74.534823,39.460312],"type":"Point"}
}