{
  "type": "Feature",
  "properties": {
    "iso:country":"US",
    "sg:address":"12 Charleston Rd",
    "sg:city":"Willingboro",
    "sg:classifiers":[
        {
            "category":"Food & Beverages",
            "subcategory":"Groceries & Convenience Stores",
            "type":"Retail Goods"
        }
    ],
    "sg:phone":"+1 609 871 0063",
    "sg:postcode":"08046",
    "sg:province":"NJ",
    "sg:tags":[
        "market"
    ],
    "wof:name":"Yeblo Village Intl",
    "wof:placetype":"venue"
},
  "geometry": {"coordinates":[-74.901855,40.045416],"type":"Point"}
}