{
  "type": "Feature",
  "properties": {
    "addr:full":"419 Essex St # A Hackensack NJ 07601",
    "addr:housenumber":"419",
    "addr:postcode":"07601",
    "addr:street":"Essex St # A",
    "iso:country":"US",
    "sg:address":"419 Essex St # A",
    "sg:city":"Hackensack",
    "sg:classifiers":[
        {
            "category":"Real Estate",
            "subcategory":"Real Estate Services",
            "type":"Services"
        }
    ],
    "sg:phone":"+1 201 488 7877",
    "sg:postcode":"07601",
    "sg:province":"NJ",
    "sg:tags":[
        "management",
        "property"
    ],
    "wof:name":"Howard F Koval Realty",
    "wof:placetype":"venue"
},
  "geometry": {"coordinates":[-74.06089799999999,40.884701],"type":"Point"}
}