{
  "type": "Feature",
  "properties": {
    "iso:country":"US",
    "sg:address":"140 S Morris St",
    "sg:city":"Dover",
    "sg:classifiers":[
        {
            "category":"Wholesale",
            "subcategory":"Stationery",
            "type":"Manufacturing & Wholesale Goods"
        }
    ],
    "sg:phone":"+1 973 366 8070",
    "sg:postcode":"07801",
    "sg:province":"NJ",
    "sg:tags":[
        "business",
        "form",
        "system"
    ],
    "wof:name":"Dolphin Business Forms & Syst",
    "wof:placetype":"venue"
},
  "geometry": {"coordinates":[-74.556051,40.87983],"type":"Point"}
}