{
  "type": "Feature",
  "properties": {
    "addr:full":"377 McKinley Blvd Paramus NJ 07652",
    "addr:housenumber":"377",
    "addr:postcode":"07652",
    "addr:street":"Mckinley Blvd",
    "iso:country":"US",
    "sg:address":"377 McKinley Blvd",
    "sg:city":"Paramus",
    "sg:classifiers":[
        {
            "category":"Professional",
            "type":"Services"
        }
    ],
    "sg:phone":"+1   ",
    "sg:postcode":"07652",
    "sg:province":"NJ",
    "wof:name":"Shirley Sloanfader",
    "wof:placetype":"venue"
},
  "geometry": {"coordinates":[-74.05643999999999,40.952947],"type":"Point"}
}