{
  "type": "Feature",
  "properties": {
    "iso:country":"US",
    "sg:address":"603 1st Ave",
    "sg:city":"Raritan",
    "sg:classifiers":[
        {
            "category":"Insurance",
            "subcategory":"Insurance Agent",
            "type":"Services"
        }
    ],
    "sg:phone":"+1   ",
    "sg:postcode":"08869",
    "sg:province":"NJ",
    "sg:tags":[
        "real estate"
    ],
    "wof:name":"Warren Valley Insurance",
    "wof:placetype":"venue"
},
  "geometry": {"coordinates":[-74.63884,40.57464],"type":"Point"}
}