{
  "type": "Feature",
  "properties": {
    "addr:full":"471 River Rd Fair Haven NJ 07704",
    "addr:housenumber":"471",
    "addr:postcode":"07704",
    "addr:street":"River Rd",
    "iso:country":"US",
    "sg:address":"471 River Rd",
    "sg:city":"Fair Haven",
    "sg:classifiers":[
        {
            "category":"Professional",
            "subcategory":"Management & Consulting",
            "type":"Services"
        }
    ],
    "sg:phone":"+1   ",
    "sg:postcode":"07704",
    "sg:province":"NJ",
    "wof:name":"J & J Sales & Marketing",
    "wof:placetype":"venue"
},
  "geometry": {"coordinates":[-74.046403,40.359338],"type":"Point"}
}