{
  "type": "Feature",
  "properties": {
    "addr:full":"42 E Burlington St Bordentown NJ 08505",
    "addr:housenumber":"42 e",
    "addr:postcode":"08505",
    "addr:street":"Burlington St",
    "iso:country":"US",
    "sg:address":"42 E Burlington St",
    "sg:city":"Bordentown",
    "sg:classifiers":[
        {
            "category":"Organizations",
            "subcategory":"Religious Organization",
            "type":"Services"
        }
    ],
    "sg:phone":"+1 609 298 2224",
    "sg:postcode":"08505",
    "sg:province":"NJ",
    "sg:tags":[
        "churches-interdenominational",
        "church"
    ],
    "wof:name":"Ebenezer Full Gospel Comm",
    "wof:placetype":"venue"
},
  "geometry": {"coordinates":[-74.70837,40.144846],"type":"Point"}
}