{
  "type": "Feature",
  "properties": {
    "addr:full":"318 Diamond Bridge Ave Hawthorne NJ 07506",
    "addr:housenumber":"318",
    "addr:postcode":"07506",
    "addr:street":"Diamond Bridge Ave",
    "iso:country":"US",
    "sg:address":"318 Diamond Bridge Ave",
    "sg:city":"Hawthorne",
    "sg:classifiers":[
        {
            "category":"Shopping",
            "subcategory":"Discount & Variety Stores",
            "type":"Retail Goods"
        },
        {
            "category":"Restaurant",
            "type":"Food & Drink"
        }
    ],
    "sg:phone":"+1 973 423 3923",
    "sg:postcode":"07506",
    "sg:province":"NJ",
    "sg:tags":[
        "eating",
        "merchandise",
        "general"
    ],
    "wof:name":"Adele's General Store",
    "wof:placetype":"venue"
},
  "geometry": {"coordinates":[-74.14852,40.949385],"type":"Point"}
}