{
  "type": "Feature",
  "properties": {
    "iso:country":"US",
    "sg:address":"426 Quaker Church Rd",
    "sg:city":"Randolph",
    "sg:classifiers":[
        {
            "category":"Wholesale",
            "subcategory":"Scrap",
            "type":"Manufacturing & Wholesale Goods"
        }
    ],
    "sg:phone":"+1 973 328 0829",
    "sg:postcode":"07869",
    "sg:province":"NJ",
    "sg:tags":[
        "material"
    ],
    "wof:name":"Well Scrap ME Silly",
    "wof:placetype":"venue"
},
  "geometry": {"coordinates":[-74.58363799999999,40.866793],"type":"Point"}
}