{
  "type": "Feature",
  "properties": {
    "iso:country":"US",
    "sg:address":"1845 Hooper Ave",
    "sg:city":"Toms River",
    "sg:classifiers":[
        {
            "category":"Retail",
            "subcategory":"Laundry & Dry Cleaning",
            "type":"Services"
        }
    ],
    "sg:phone":"+1 732 864 1880",
    "sg:postcode":"08753",
    "sg:province":"NJ",
    "sg:tags":[
        "drycleaning",
        "plant",
        "cleaners"
    ],
    "wof:name":"Busy Bees Laundromat & Dry Clg",
    "wof:placetype":"venue"
},
  "geometry": {"coordinates":[-74.147023,40.010321],"type":"Point"}
}