{
  "type": "Feature",
  "properties": {
    "iso:country":"US",
    "sg:address":"1745 State Rte 37",
    "sg:city":"Toms River",
    "sg:classifiers":[
        {
            "category":"Autos & Motor Vehicles",
            "subcategory":"Automobile Sales",
            "type":"Retail Goods"
        }
    ],
    "sg:phone":"+1 732 736 1110",
    "sg:postcode":"08757",
    "sg:province":"NJ",
    "sg:tags":[
        "car",
        "dealer"
    ],
    "wof:name":"Choice Cars",
    "wof:placetype":"venue"
},
  "geometry": {"coordinates":[-74.271079,39.992179],"type":"Point"}
}