{
  "type": "Feature",
  "properties": {
    "addr:full":"460 Franklin Ave Nutley NJ 07110",
    "addr:housenumber":"460",
    "addr:postcode":"07110",
    "addr:street":"Franklin Ave",
    "iso:country":"US",
    "sg:address":"460 Franklin Ave",
    "sg:city":"Nutley",
    "sg:classifiers":[
        {
            "category":"Building & Trades",
            "subcategory":"Locksmith",
            "type":"Services"
        }
    ],
    "sg:phone":"+1 973 320 9365",
    "sg:postcode":"07110",
    "sg:province":"NJ",
    "sg:tags":[
        "key"
    ],
    "wof:name":"Always Ready Locksmith",
    "wof:placetype":"venue"
},
  "geometry": {"coordinates":[-74.156892,40.822423],"type":"Point"}
}