{
  "type": "Feature",
  "properties": {
    "addr:full":"185 Madisonville Rd Basking Ridge NJ 07920",
    "addr:housenumber":"185",
    "addr:postcode":"07920",
    "addr:street":"Madisonville Rd",
    "iso:country":"US",
    "sg:address":"185 Madisonville Rd",
    "sg:city":"Basking Ridge",
    "sg:classifiers":[
        {
            "category":"Restaurant",
            "type":"Food & Drink"
        }
    ],
    "sg:phone":"+1 908 766 8200",
    "sg:postcode":"07920",
    "sg:province":"NJ",
    "sg:tags":[
        "banquet",
        "rooms"
    ],
    "sg:website":"www.baskingridgecc.com",
    "wof:name":"Basking Ridge Country Club",
    "wof:placetype":"venue"
},
  "geometry": {"coordinates":[-74.535887,40.719591],"type":"Point"}
}