{
  "type": "Feature",
  "properties": {
    "addr:full":"1280 Old Stagecoach Rd Ocean View NJ 08230",
    "addr:housenumber":"1280",
    "addr:postcode":"08230",
    "addr:street":"Old Stagecoach Rd",
    "iso:country":"US",
    "sg:address":"1280 Old Stagecoach Rd",
    "sg:city":"Ocean View",
    "sg:classifiers":[
        {
            "category":"Building & Trades",
            "subcategory":"Construction",
            "type":"Services"
        }
    ],
    "sg:phone":"+1 609 390 9100",
    "sg:postcode":"08230",
    "sg:province":"NJ",
    "sg:tags":[
        "home",
        "builder"
    ],
    "wof:name":"Palmer Development",
    "wof:placetype":"venue"
},
  "geometry": {"coordinates":[-74.68315699999999,39.239801],"type":"Point"}
}