{
  "type": "Feature",
  "properties": {
    "addr:full":"306 Clay St Woodbine NJ 08270",
    "addr:housenumber":"306",
    "addr:postcode":"08270",
    "addr:street":"Clay St",
    "iso:country":"US",
    "sg:address":"306 Clay St",
    "sg:city":"Woodbine",
    "sg:classifiers":[
        {
            "category":"Organizations",
            "subcategory":"Religious Organization",
            "type":"Services"
        }
    ],
    "sg:phone":"+1 609 861 1601",
    "sg:postcode":"08270",
    "sg:province":"NJ",
    "sg:tags":[
        "church"
    ],
    "wof:name":"St Casimir Religious Education",
    "wof:placetype":"venue"
},
  "geometry": {"coordinates":[-74.82064800000001,39.239791],"type":"Point"}
}