{
  "type": "Feature",
  "properties": {
    "iso:country":"US",
    "sg:address":"310 N Broad St",
    "sg:city":"Elizabeth",
    "sg:phone":"+1 800 275 8777",
    "sg:postcode":"07208",
    "sg:province":"NJ",
    "sg:website":"http://www.usps.com",
    "wof:name":"United States Postal Service",
    "wof:placetype":"venue"
},
  "geometry": {"coordinates":[-74.215772,40.669811],"type":"Point"}
}