{
  "type": "Feature",
  "properties": {
    "addr:full":"811 Asbury Ave Ocean City NJ 08226",
    "addr:housenumber":"811",
    "addr:postcode":"08226",
    "addr:street":"Asbury Ave",
    "iso:country":"US",
    "sg:address":"811 Asbury Ave",
    "sg:city":"Ocean City",
    "sg:classifiers":[
        {
            "category":"Personal",
            "subcategory":"Beauty Salon",
            "type":"Services"
        }
    ],
    "sg:phone":"+1 609 391 9339",
    "sg:postcode":"08226",
    "sg:province":"NJ",
    "sg:tags":[
        "shop"
    ],
    "wof:name":"Fashion Nails",
    "wof:placetype":"venue"
},
  "geometry": {"coordinates":[-74.574921,39.279774],"type":"Point"}
}