{
  "type": "Feature",
  "properties": {
    "addr:full":"34 Deforest Ave East Hanover NJ 07936",
    "addr:housenumber":"34",
    "addr:postcode":"07936",
    "addr:street":"Deforest Ave",
    "iso:country":"US",
    "sg:address":"34 Deforest Ave",
    "sg:city":"East Hanover",
    "sg:classifiers":[
        {
            "category":"Building & Trades",
            "subcategory":"Plumbing",
            "type":"Services"
        }
    ],
    "sg:phone":"+1 973 515 0705",
    "sg:postcode":"07936",
    "sg:province":"NJ",
    "wof:name":"Serpe Russell",
    "wof:placetype":"venue"
},
  "geometry": {"coordinates":[-74.365898,40.819698],"type":"Point"}
}