{
  "type": "Feature",
  "properties": {
    "iso:country":"US",
    "sg:address":"251 Beach Dr",
    "sg:city":"Cape May",
    "sg:classifiers":[
        {
            "category":"Bars & Pubs",
            "subcategory":"Nightclub",
            "type":"Food & Drink"
        }
    ],
    "sg:phone":"+1 609 884 6507",
    "sg:postcode":"08204",
    "sg:province":"NJ",
    "sg:tags":[
        "nightlife"
    ],
    "wof:name":"Boiler Room At Congress Hall",
    "wof:placetype":"venue"
},
  "geometry": {"coordinates":[-74.95970199999999,38.9823],"type":"Point"}
}