{
  "type": "Feature",
  "properties": {
    "iso:country":"US",
    "sg:address":"10 Levan Ct",
    "sg:city":"Bridgewater",
    "sg:classifiers":[
        {
            "category":"Professional",
            "subcategory":"Accounting & Tax Preparation",
            "type":"Services"
        }
    ],
    "sg:phone":"+1 908 575 0415",
    "sg:postcode":"08807",
    "sg:province":"NJ",
    "sg:tags":[
        "accountant"
    ],
    "wof:name":"Mark D Weinman CPA",
    "wof:placetype":"venue"
},
  "geometry": {"coordinates":[-74.66080599999999,40.58959],"type":"Point"}
}