{
  "type": "Feature",
  "properties": {
    "iso:country":"US",
    "sg:address":"831 Rte 10 Pine Plaza Shopping Center",
    "sg:city":"Whippany",
    "sg:classifiers":[
        {
            "category":"Food & Beverages",
            "subcategory":"Specialty",
            "type":"Retail Goods"
        }
    ],
    "sg:phone":"+1 973 428 5400",
    "sg:postcode":"07981",
    "sg:province":"NJ",
    "sg:tags":[
        "fondue"
    ],
    "sg:website":"www.meltingpot.com",
    "wof:name":"The Melting Pot",
    "wof:placetype":"venue"
},
  "geometry": {"coordinates":[-74.44443699999999,40.836955],"type":"Point"}
}