{
  "type": "Feature",
  "properties": {
    "addr:full":"18 Utah Trl Medford NJ 08055",
    "addr:housenumber":"18",
    "addr:postcode":"08055",
    "addr:street":"Utah Trl",
    "iso:country":"US",
    "sg:address":"18 Utah Trl",
    "sg:city":"Medford",
    "sg:classifiers":[
        {
            "category":"Professional",
            "subcategory":"Lawyer & Legal Services",
            "type":"Services"
        }
    ],
    "sg:phone":"+1   ",
    "sg:postcode":"08055",
    "sg:province":"NJ",
    "wof:name":"Jerry Friedman",
    "wof:placetype":"venue"
},
  "geometry": {"coordinates":[-74.853948,39.87856],"type":"Point"}
}