{
  "type": "Feature",
  "properties": {
    "iso:country":"US",
    "sg:address":"1702 Queen Anne Ln",
    "sg:city":"Toms River",
    "sg:classifiers":[
        {
            "category":"Social Services",
            "subcategory":"Child Care",
            "type":"Services"
        }
    ],
    "sg:phone":"+1   ",
    "sg:postcode":"08753",
    "sg:province":"NJ",
    "sg:tags":[
        "day"
    ],
    "wof:name":"ABC Childcare",
    "wof:placetype":"venue"
},
  "geometry": {"coordinates":[-74.173137,39.986148],"type":"Point"}
}