{
  "type": "Feature",
  "properties": {
    "iso:country":"US",
    "sg:address":"160 Adamsville Rd N",
    "sg:city":"Bridgewater",
    "sg:classifiers":[
        {
            "category":"Retail",
            "subcategory":"Self-service Laundry",
            "type":"Services"
        },
        {
            "category":"Retail",
            "subcategory":"Laundry & Dry Cleaning",
            "type":"Services"
        }
    ],
    "sg:phone":"+1 908 725 2511",
    "sg:postcode":"08807",
    "sg:province":"NJ",
    "sg:tags":[
        "coin"
    ],
    "wof:name":"Suds & Dry Laundromats Inc",
    "wof:placetype":"venue"
},
  "geometry": {"coordinates":[-74.586071,40.57067],"type":"Point"}
}