{
  "type": "Feature",
  "properties": {
    "iso:country":"US",
    "sg:address":"700 W Delilah Rd",
    "sg:city":"Pleasantville",
    "sg:classifiers":[
        {
            "category":"Retail",
            "subcategory":"Auto Repair",
            "type":"Services"
        }
    ],
    "sg:phone":"+1 609 646 2028",
    "sg:postcode":"08232",
    "sg:province":"NJ",
    "sg:tags":[
        "repairing",
        "automobile"
    ],
    "wof:name":"Walker's Automotive Svc",
    "wof:placetype":"venue"
},
  "geometry": {"coordinates":[-74.523687,39.409325],"type":"Point"}
}