{
  "type": "Feature",
  "properties": {
    "iso:country":"US",
    "sg:address":"103 Union Ave",
    "sg:city":"Union",
    "sg:classifiers":[
        {
            "category":"Restaurant",
            "type":"Food & Drink"
        }
    ],
    "sg:phone":"+1 908 688 2372",
    "sg:postcode":"07083",
    "sg:province":"NJ",
    "sg:website":"www.thephoenixbar.net",
    "wof:name":"Phoenix Bar N Grill",
    "wof:placetype":"venue"
},
  "geometry": {"coordinates":[-74.249667,40.706005],"type":"Point"}
}