{
  "type": "Feature",
  "properties": {
    "addr:full":"6204 Park Ave West New York NJ 07093",
    "addr:housenumber":"6204",
    "addr:postcode":"07093",
    "addr:street":"Park Ave West",
    "iso:country":"US",
    "sg:address":"6204 Park Ave",
    "sg:city":"West New York",
    "sg:classifiers":[
        {
            "category":"Shopping",
            "subcategory":"Pets & Pet Supplies",
            "type":"Retail Goods"
        }
    ],
    "sg:phone":"+1 201 453 3584",
    "sg:postcode":"07093",
    "sg:province":"NJ",
    "sg:tags":[
        "store"
    ],
    "wof:name":"Alexs Pet Shop",
    "wof:placetype":"venue"
},
  "geometry": {"coordinates":[-74.006979,40.787659],"type":"Point"}
}