{
  "type": "Feature",
  "properties": {
    "addr:full":"8 Morris Ave Branchville NJ 07826",
    "addr:housenumber":"8",
    "addr:postcode":"07826",
    "addr:street":"Morris Ave",
    "iso:country":"US",
    "sg:address":"8 Morris Ave",
    "sg:city":"Branchville",
    "sg:classifiers":[
        {
            "category":"Building & Trades",
            "subcategory":"Construction",
            "type":"Services"
        }
    ],
    "sg:phone":"+1 973 948 3939",
    "sg:postcode":"07826",
    "sg:province":"NJ",
    "sg:tags":[
        "system",
        "specialty",
        "heating",
        "contractor",
        "air conditioning"
    ],
    "wof:name":"Kronenberg Climate Systems",
    "wof:placetype":"venue"
},
  "geometry": {"coordinates":[-74.748289,41.143324],"type":"Point"}
}