{
  "type": "Feature",
  "properties": {
    "iso:country":"US",
    "sg:address":"100 US Highway 46 Ste A4",
    "sg:city":"Mountain Lakes",
    "sg:classifiers":[
        {
            "category":"Professional",
            "subcategory":"Accounting & Tax Preparation",
            "type":"Services"
        }
    ],
    "sg:phone":"+1 973 394 8922",
    "sg:postcode":"07046",
    "sg:province":"NJ",
    "sg:tags":[
        "accountant"
    ],
    "wof:name":"North Jersey CPA PA",
    "wof:placetype":"venue"
},
  "geometry": {"coordinates":[-74.45800800000001,40.883812],"type":"Point"}
}