{
  "type": "Feature",
  "properties": {
    "addr:full":"200 Boulevard Hasbrouck Hts NJ 07604",
    "addr:housenumber":"200",
    "addr:postcode":"07604",
    "addr:street":"Boulevard",
    "iso:country":"US",
    "sg:address":"200 Boulevard",
    "sg:city":"Hasbrouck Hts",
    "sg:classifiers":[
        {
            "category":"Professional",
            "subcategory":"Accounting & Tax Preparation",
            "type":"Services"
        }
    ],
    "sg:phone":"+1 201 393 0911",
    "sg:postcode":"07604",
    "sg:province":"NJ",
    "sg:tags":[
        "billing"
    ],
    "wof:name":"Advanced Medical Solutions",
    "wof:placetype":"venue"
},
  "geometry": {"coordinates":[-74.078211,40.86195],"type":"Point"}
}