{
  "type": "Feature",
  "properties": {
    "iso:country":"US",
    "sg:address":"4 W Haddon Ct",
    "sg:city":"Marlton",
    "sg:classifiers":[
        {
            "category":"Professional",
            "subcategory":"Business Services",
            "type":"Services"
        }
    ],
    "sg:phone":"+1   ",
    "sg:postcode":"08053",
    "sg:province":"NJ",
    "wof:name":"Lck Marketing Group LLC",
    "wof:placetype":"venue"
},
  "geometry": {"coordinates":[-74.883987,39.845837],"type":"Point"}
}