{
  "type": "Feature",
  "properties": {
    "iso:country":"US",
    "sg:address":"730 Boulevard",
    "sg:city":"Kenilworth",
    "sg:classifiers":[
        {
            "category":"Organizations",
            "subcategory":"Non-profit Organization",
            "type":"Services"
        }
    ],
    "sg:phone":"+1 908 245 8669",
    "sg:postcode":"07033",
    "sg:province":"NJ",
    "sg:tags":[
        "social"
    ],
    "wof:name":"Tony Siragusa Foundation",
    "wof:placetype":"venue"
},
  "geometry": {"coordinates":[-74.28652599999999,40.677223],"type":"Point"}
}