{
  "type": "Feature",
  "properties": {
    "addr:full":"276 Co Rd 513 Glen Gardner NJ 08826",
    "addr:housenumber":"276;513",
    "addr:postcode":"08826",
    "addr:street":"Co Rd",
    "iso:country":"US",
    "sg:address":"276 Co Rd 513",
    "sg:city":"Glen Gardner",
    "sg:classifiers":[
        {
            "category":"Autos & Motor Vehicles",
            "subcategory":"Auto Supplies",
            "type":"Retail Goods"
        }
    ],
    "sg:phone":"+1 908 638 1194",
    "sg:postcode":"08826",
    "sg:province":"NJ",
    "sg:tags":[
        "equipment",
        "racing",
        "car",
        "automobile"
    ],
    "wof:name":"Powertrip Performance Inc",
    "wof:placetype":"venue"
},
  "geometry": {"coordinates":[-74.886602,40.698407],"type":"Point"}
}