{
  "type": "Feature",
  "properties": {
    "iso:country":"US",
    "sg:address":"18 Eton Dr",
    "sg:city":"Caldwell",
    "sg:classifiers":[
        {
            "category":"Professional",
            "subcategory":"Secretarial Services",
            "type":"Services"
        }
    ],
    "sg:phone":"+1 201 906 4888",
    "sg:postcode":"07006",
    "sg:province":"NJ",
    "sg:tags":[
        "resume"
    ],
    "sg:website":"www.gotthejob.com",
    "wof:name":"About Jobs",
    "wof:placetype":"venue"
},
  "geometry": {"coordinates":[-74.266986,40.859555],"type":"Point"}
}