{
  "type": "Feature",
  "properties": {
    "addr:full":"1065 Raritan Rd Clark NJ 07066",
    "addr:housenumber":"1065",
    "addr:postcode":"07066",
    "addr:street":"Raritan Rd",
    "iso:country":"US",
    "sg:address":"1065 Raritan Rd",
    "sg:city":"Clark",
    "sg:classifiers":[
        {
            "category":"Sports & Exercise",
            "subcategory":"Gym",
            "type":"Entertainment"
        }
    ],
    "sg:phone":"+1 732 381 3000",
    "sg:postcode":"07066",
    "sg:province":"NJ",
    "sg:tags":[
        "club",
        "physical",
        "fitness"
    ],
    "wof:name":"Curves For Women",
    "wof:placetype":"venue"
},
  "geometry": {"coordinates":[-74.31434299999999,40.628229],"type":"Point"}
}