{
  "type": "Feature",
  "properties": {
    "addr:full":"2100 Boardwalk Atlantic City NJ 08401",
    "addr:housenumber":"2100",
    "addr:postcode":"08401",
    "addr:street":"Boardwalk",
    "iso:country":"US",
    "sg:address":"2100 Boardwalk",
    "sg:city":"Atlantic City",
    "sg:classifiers":[
        {
            "category":"Personal",
            "subcategory":"Beauty Salon",
            "type":"Services"
        }
    ],
    "sg:phone":"+1 609 344 0011",
    "sg:postcode":"08401",
    "sg:province":"NJ",
    "sg:tags":[
        "manicuring"
    ],
    "wof:name":"Nailery",
    "wof:placetype":"venue"
},
  "geometry": {"coordinates":[-74.43575199999999,39.35463],"type":"Point"}
}