{
  "type": "Feature",
  "properties": {
    "iso:country":"US",
    "sg:address":"413 Paul Dr",
    "sg:city":"Moorestown",
    "sg:classifiers":[
        {
            "category":"Manufacturing",
            "subcategory":"Chemicals & Compounds",
            "type":"Manufacturing & Wholesale Goods"
        }
    ],
    "sg:phone":"+1 856 235 8374",
    "sg:postcode":"08057",
    "sg:province":"NJ",
    "sg:tags":[
        "product",
        "mfg"
    ],
    "wof:name":"Rabco Incorporated",
    "wof:placetype":"venue"
},
  "geometry": {"coordinates":[-74.94095900000001,39.960918],"type":"Point"}
}