{
  "type": "Feature",
  "properties": {
    "iso:country":"US",
    "sg:address":"52 Courter Ave",
    "sg:city":"Maplewood",
    "sg:classifiers":[
        {
            "category":"Professional",
            "subcategory":"Employment Agencies",
            "type":"Services"
        }
    ],
    "sg:phone":"+1 973 313 9597",
    "sg:postcode":"07040",
    "sg:province":"NJ",
    "wof:name":"J A Niece Rush Inc",
    "wof:placetype":"venue"
},
  "geometry": {"coordinates":[-74.265964,40.726184],"type":"Point"}
}