{
  "type": "Feature",
  "properties": {
    "iso:country":"US",
    "sg:address":"88 Little Philadelphia Rd",
    "sg:city":"Washington",
    "sg:classifiers":[
        {
            "category":"Building & Trades",
            "subcategory":"Plumbing",
            "type":"Services"
        }
    ],
    "sg:phone":"+1 908 689 3960",
    "sg:postcode":"07882",
    "sg:province":"NJ",
    "sg:tags":[
        "contractor"
    ],
    "wof:name":"Whitney Plumbing & Heatin",
    "wof:placetype":"venue"
},
  "geometry": {"coordinates":[-75.023094,40.758227],"type":"Point"}
}