{
  "type": "Feature",
  "properties": {
    "iso:country":"US",
    "sg:address":"156 Polkville Rd",
    "sg:city":"Columbia",
    "sg:classifiers":[
        {
            "category":"Building & Trades",
            "subcategory":"Landscaping Services",
            "type":"Services"
        }
    ],
    "sg:phone":"+1 908 496 4755",
    "sg:postcode":"07832",
    "sg:province":"NJ",
    "sg:tags":[
        "lawn",
        "designer",
        "consultant",
        "contractor",
        "maintenance",
        "landscape"
    ],
    "wof:name":"Jb's Landscaping",
    "wof:placetype":"venue"
},
  "geometry": {"coordinates":[-75.046662,40.933389],"type":"Point"}
}