{
  "type": "Feature",
  "properties": {
    "iso:country":"US",
    "sg:address":"427 State Rte 440",
    "sg:city":"Jersey City",
    "sg:classifiers":[
        {
            "category":"Restaurant",
            "type":"Food & Drink"
        }
    ],
    "sg:phone":"+1   ",
    "sg:postcode":"07305",
    "sg:province":"NJ",
    "sg:tags":[
        "eating"
    ],
    "wof:name":"J & C Snack Bar",
    "wof:placetype":"venue"
},
  "geometry": {"coordinates":[-74.09632499999999,40.715019],"type":"Point"}
}