{
  "type": "Feature",
  "properties": {
    "iso:country":"US",
    "sg:address":"670 Bound Brook Rd",
    "sg:city":"Middlesex",
    "sg:classifiers":[
        {
            "category":"Autos & Motor Vehicles",
            "subcategory":"Auto Supplies",
            "type":"Retail Goods"
        }
    ],
    "sg:phone":"+1 732 968 0550",
    "sg:postcode":"08846",
    "sg:province":"NJ",
    "sg:tags":[
        "automobile",
        "accessory"
    ],
    "wof:name":"Car Trek",
    "wof:placetype":"venue"
},
  "geometry": {"coordinates":[-74.492542,40.581388],"type":"Point"}
}