{
  "type": "Feature",
  "properties": {
    "addr:full":"808 Bloomfield Ave West Caldwell NJ 07006",
    "addr:housenumber":"808",
    "addr:postcode":"07006",
    "addr:street":"Bloomfield Ave",
    "iso:country":"US",
    "sg:address":"808 Bloomfield Ave",
    "sg:city":"West Caldwell",
    "sg:classifiers":[
        {
            "category":"Building & Trades",
            "subcategory":"Locksmith",
            "type":"Services"
        }
    ],
    "sg:phone":"+1 973 830 1294",
    "sg:postcode":"07006",
    "sg:province":"NJ",
    "sg:tags":[
        "key"
    ],
    "wof:name":"Broadway Locksmith",
    "wof:placetype":"venue"
},
  "geometry": {"coordinates":[-74.295889,40.850166],"type":"Point"}
}