{
  "type": "Feature",
  "properties": {
    "iso:country":"US",
    "sg:address":"229 Wintergreen Ln",
    "sg:city":"Penns Grove",
    "sg:classifiers":[
        {
            "category":"Organizations",
            "subcategory":"Religious Organization",
            "type":"Services"
        }
    ],
    "sg:phone":"+1   ",
    "sg:postcode":"08069",
    "sg:province":"NJ",
    "wof:name":"Ezell Garrett Rev",
    "wof:placetype":"venue"
},
  "geometry": {"coordinates":[-75.46709300000001,39.718613],"type":"Point"}
}