{
  "type": "Feature",
  "properties": {
    "addr:full":"22 Bramble Dr Brigantine NJ 08203",
    "addr:housenumber":"22",
    "addr:postcode":"08203",
    "addr:street":"Bramble Dr",
    "iso:country":"US",
    "sg:address":"22 Bramble Dr",
    "sg:city":"Brigantine",
    "sg:classifiers":[
        {
            "category":"Real Estate",
            "subcategory":"Real Estate Agent",
            "type":"Services"
        }
    ],
    "sg:phone":"+1 609 264 1247",
    "sg:postcode":"08203",
    "sg:province":"NJ",
    "wof:name":"Thomas M Kaczor Real Estate",
    "wof:placetype":"venue"
},
  "geometry": {"coordinates":[-74.398589,39.384837],"type":"Point"}
}