{
  "type": "Feature",
  "properties": {
    "addr:full":"1811 Ocean Ave Spring Lake NJ 07762",
    "addr:housenumber":"1811",
    "addr:postcode":"07762",
    "addr:street":"Ocean Ave",
    "iso:country":"US",
    "sg:address":"1811 Ocean Ave",
    "sg:city":"Spring Lake",
    "sg:classifiers":[
        {
            "category":"Building & Trades",
            "subcategory":"Construction",
            "type":"Services"
        }
    ],
    "sg:phone":"+1 732 974 1056",
    "sg:postcode":"07762",
    "sg:province":"NJ",
    "sg:tags":[
        "house"
    ],
    "wof:name":"Doug McClave Const",
    "wof:placetype":"venue"
},
  "geometry": {"coordinates":[-74.020357,40.158782],"type":"Point"}
}