{
  "type": "Feature",
  "properties": {
    "addr:full":"16 Sheryl Dr Edison NJ 08820",
    "addr:housenumber":"16",
    "addr:postcode":"08820",
    "addr:street":"Sheryl Dr",
    "iso:country":"US",
    "sg:address":"16 Sheryl Dr",
    "sg:city":"Edison",
    "sg:classifiers":[
        {
            "category":"Professional",
            "subcategory":"Business Services",
            "type":"Services"
        }
    ],
    "sg:phone":"+1 732 340 9463",
    "sg:postcode":"08820",
    "sg:province":"NJ",
    "sg:tags":[
        "appraiser"
    ],
    "wof:name":"Detail Claims Svc",
    "wof:placetype":"venue"
},
  "geometry": {"coordinates":[-74.343352,40.604974],"type":"Point"}
}