{
  "type": "Feature",
  "properties": {
    "addr:full":"1 High Mountain Rd Ringwood NJ 07456",
    "addr:housenumber":"1",
    "addr:postcode":"07456",
    "addr:street":"High Mountain Rd",
    "iso:country":"US",
    "sg:address":"1 High Mountain Rd",
    "sg:city":"Ringwood",
    "sg:classifiers":[
        {
            "category":"Building & Trades",
            "subcategory":"Pest Control",
            "type":"Services"
        }
    ],
    "sg:phone":"+1 973 839 5507",
    "sg:postcode":"07456",
    "sg:province":"NJ",
    "wof:name":"Exterminator Pest Control Inc",
    "wof:placetype":"venue"
},
  "geometry": {"coordinates":[-74.267146,41.075413],"type":"Point"}
}