{
  "type": "Feature",
  "properties": {
    "addr:full":"295 Monticello Ave Jersey City NJ 07306",
    "addr:housenumber":"295",
    "addr:postcode":"07306",
    "addr:street":"Monticello Ave",
    "iso:country":"US",
    "sg:address":"295 Monticello Ave",
    "sg:city":"Jersey City",
    "sg:classifiers":[
        {
            "category":"Retail",
            "subcategory":"Laundry & Dry Cleaning",
            "type":"Services"
        }
    ],
    "sg:phone":"+1 201 309 9977",
    "sg:postcode":"07306",
    "sg:province":"NJ",
    "sg:tags":[
        "cleaner",
        "rug",
        "carpet"
    ],
    "wof:name":"Alltime Carpet Cleaning Inc",
    "wof:placetype":"venue"
},
  "geometry": {"coordinates":[-74.06684199999999,40.724047],"type":"Point"}
}