{
  "type": "Feature",
  "properties": {
    "iso:country":"US",
    "sg:address":"398 Kingston Ct",
    "sg:city":"West New York",
    "sg:classifiers":[
        {
            "category":"Health Services",
            "subcategory":"Medical Lab",
            "type":"Services"
        }
    ],
    "sg:phone":"+1 201 866 2799",
    "sg:postcode":"07093",
    "sg:province":"NJ",
    "sg:tags":[
        "laboratory"
    ],
    "wof:name":"Moreau Clinic",
    "wof:placetype":"venue"
},
  "geometry": {"coordinates":[-74.00985,40.782362],"type":"Point"}
}