{
  "type": "Feature",
  "properties": {
    "iso:country":"US",
    "sg:address":"4333 US Hwy 130",
    "sg:city":"Beverly",
    "sg:classifiers":[
        {
            "category":"Retail",
            "subcategory":"Auto Repair",
            "type":"Services"
        }
    ],
    "sg:phone":"+1 609 871 1900",
    "sg:postcode":"08010",
    "sg:province":"NJ",
    "sg:tags":[
        "general"
    ],
    "wof:name":"Oil Station",
    "wof:placetype":"venue"
},
  "geometry": {"coordinates":[-74.892779,40.05373],"type":"Point"}
}