{
  "type": "Feature",
  "properties": {
    "iso:country":"US",
    "sg:address":"117 John St",
    "sg:city":"Clark",
    "sg:classifiers":[
        {
            "category":"Organizations",
            "subcategory":"Religious Organization",
            "type":"Services"
        }
    ],
    "sg:phone":"+1   ",
    "sg:postcode":"07066",
    "sg:province":"NJ",
    "wof:name":"Shawn Zell Rabbi",
    "wof:placetype":"venue"
},
  "geometry": {"coordinates":[-74.298664,40.623708],"type":"Point"}
}