{
  "type": "Feature",
  "properties": {
    "addr:full":"7 Baltic St Edison NJ 08820",
    "addr:housenumber":"7",
    "addr:postcode":"08820",
    "addr:street":"Baltic St",
    "iso:country":"US",
    "sg:address":"7 Baltic St",
    "sg:city":"Edison",
    "sg:classifiers":[
        {
            "category":"Health Services",
            "subcategory":"Doctor",
            "type":"Services"
        }
    ],
    "sg:phone":"+1 732 494 2988",
    "sg:postcode":"08820",
    "sg:province":"NJ",
    "sg:tags":[
        "physician",
        "surgeon",
        "medical"
    ],
    "wof:name":"Sujai Udomsaph MD",
    "wof:placetype":"venue"
},
  "geometry": {"coordinates":[-74.35662499999999,40.571328],"type":"Point"}
}