{
  "type": "Feature",
  "properties": {
    "addr:full":"11 Pequot Rd Ringwood NJ 07456",
    "addr:housenumber":"11",
    "addr:postcode":"07456",
    "addr:street":"Pequot Rd",
    "iso:country":"US",
    "sg:address":"11 Pequot Rd",
    "sg:city":"Ringwood",
    "sg:classifiers":[
        {
            "category":"Home & Garden",
            "subcategory":"Carpets & Floor Coverings",
            "type":"Retail Goods"
        }
    ],
    "sg:phone":"+1   ",
    "sg:postcode":"07456",
    "sg:province":"NJ",
    "wof:name":"Centi Carpet & Upholstery Clg",
    "wof:placetype":"venue"
},
  "geometry": {"coordinates":[-74.248806,41.091837],"type":"Point"}
}