{
  "type": "Feature",
  "properties": {
    "addr:full":"1008 South Ave W Westfield NJ 07090",
    "addr:housenumber":"1008",
    "addr:postcode":"07090",
    "addr:street":"South Ave W",
    "iso:country":"US",
    "sg:address":"1008 South Ave W",
    "sg:city":"Westfield",
    "sg:classifiers":[
        {
            "category":"Banks & Credit Unions",
            "subcategory":"Bank",
            "type":"Services"
        }
    ],
    "sg:phone":"+1   ",
    "sg:postcode":"07090",
    "sg:province":"NJ",
    "sg:tags":[
        "mortgage"
    ],
    "wof:name":"Countrywide",
    "wof:placetype":"venue"
},
  "geometry": {"coordinates":[-74.359966,40.647093],"type":"Point"}
}