{
  "type": "Feature",
  "properties": {
    "iso:country":"US",
    "sg:address":"Hanes Dr",
    "sg:city":"Wayne",
    "sg:classifiers":[
        {
            "category":"Shopping",
            "subcategory":"Clothing, Apparel, & Fashions",
            "type":"Retail Goods"
        }
    ],
    "sg:phone":"+1 973 696 6204",
    "sg:postcode":"07470",
    "sg:province":"NJ",
    "sg:tags":[
        "accessory",
        "clothing",
        "women's"
    ],
    "wof:name":"Hanes Drive Outlet",
    "wof:placetype":"venue"
},
  "geometry": {"coordinates":[-74.2388,40.9487],"type":"Point"}
}