{
  "type": "Feature",
  "properties": {
    "addr:full":"1825 Garden Ave Cherry Hill NJ 08003",
    "addr:housenumber":"1825",
    "addr:postcode":"08003",
    "addr:street":"Garden Ave",
    "iso:country":"US",
    "sg:address":"1825 Garden Ave",
    "sg:city":"Cherry Hill",
    "sg:classifiers":[
        {
            "category":"Social Services",
            "subcategory":"Child Care",
            "type":"Services"
        }
    ],
    "sg:phone":"+1 856 751 0525",
    "sg:postcode":"08003",
    "sg:province":"NJ",
    "sg:tags":[
        "kindergarten",
        "academic",
        "school",
        "day"
    ],
    "wof:name":"Montessori Learning Center",
    "wof:placetype":"venue"
},
  "geometry": {"coordinates":[-74.973968,39.908213],"type":"Point"}
}