{
  "type": "Feature",
  "properties": {
    "iso:country":"US",
    "sg:address":"103 Kings Hwy E",
    "sg:city":"Haddonfield",
    "sg:classifiers":[
        {
            "category":"Arts & Performance",
            "subcategory":"Art Gallery",
            "type":"Entertainment"
        }
    ],
    "sg:phone":"+1 856 429 2648",
    "sg:postcode":"08033",
    "sg:province":"NJ",
    "sg:tags":[
        "fine",
        "artist"
    ],
    "wof:name":"Philip Carroll Studio",
    "wof:placetype":"venue"
},
  "geometry": {"coordinates":[-75.03354299999999,39.897241],"type":"Point"}
}