{
  "type": "Feature",
  "properties": {
    "iso:country":"US",
    "sg:address":"73 Tomahawk Trl",
    "sg:city":"Sparta",
    "sg:classifiers":[
        {
            "category":"Building & Trades",
            "subcategory":"Construction",
            "type":"Services"
        }
    ],
    "sg:phone":"+1 973 729 3545",
    "sg:postcode":"07871",
    "sg:province":"NJ",
    "sg:tags":[
        "house"
    ],
    "wof:name":"Houseworks of North Jersey",
    "wof:placetype":"venue"
},
  "geometry": {"coordinates":[-74.643911,41.001172],"type":"Point"}
}