{
  "type": "Feature",
  "properties": {
    "iso:country":"US",
    "sg:address":"45 W Front St",
    "sg:city":"Keyport",
    "sg:classifiers":[
        {
            "category":"Shopping",
            "subcategory":"Clothing, Apparel, & Fashions",
            "type":"Retail Goods"
        }
    ],
    "sg:phone":"+1   ",
    "sg:postcode":"07735",
    "sg:province":"NJ",
    "sg:tags":[
        "ready"
    ],
    "wof:name":"European Creations",
    "wof:placetype":"venue"
},
  "geometry": {"coordinates":[-74.204228,40.436859],"type":"Point"}
}