{
  "type": "Feature",
  "properties": {
    "addr:full":"4202 US Hwy 130 Willingboro NJ 08046",
    "addr:housenumber":"4202",
    "addr:postcode":"08046",
    "addr:street":"Us Hwy 130",
    "iso:country":"US",
    "sg:address":"4202 US Hwy 130",
    "sg:city":"Willingboro",
    "sg:classifiers":[
        {
            "category":"Social Services",
            "type":"Services"
        }
    ],
    "sg:phone":"+1 609 871 4442",
    "sg:postcode":"08046",
    "sg:province":"NJ",
    "sg:tags":[
        "counselor",
        "marriage",
        "family"
    ],
    "wof:name":"Connect Family Ctr",
    "wof:placetype":"venue"
},
  "geometry": {"coordinates":[-74.915941,40.038392],"type":"Point"}
}