{
  "type": "Feature",
  "properties": {
    "iso:country":"US",
    "sg:address":"33 Haddon Ave",
    "sg:city":"Collingswood",
    "sg:classifiers":[
        {
            "category":"Recreation",
            "type":"Entertainment"
        }
    ],
    "sg:phone":"+1 856 869 8499",
    "sg:postcode":"08108",
    "sg:province":"NJ",
    "sg:tags":[
        "concert",
        "for",
        "sporting",
        "sales",
        "ticket",
        "event"
    ],
    "wof:name":"Tickets Galore Inc",
    "wof:placetype":"venue"
},
  "geometry": {"coordinates":[-75.05506699999999,39.912417],"type":"Point"}
}