{
  "type": "Feature",
  "properties": {
    "iso:country":"US",
    "sg:address":"970 State Rte 36",
    "sg:city":"Leonardo",
    "sg:classifiers":[
        {
            "category":"Restaurant",
            "type":"Food & Drink"
        }
    ],
    "sg:phone":"+1   ",
    "sg:postcode":"07737",
    "sg:province":"NJ",
    "sg:tags":[
        "eating"
    ],
    "wof:name":"McDonalds",
    "wof:placetype":"venue"
},
  "geometry": {"coordinates":[-74.052544,40.413293],"type":"Point"}
}