{
  "type": "Feature",
  "properties": {
    "iso:country":"US",
    "sg:address":"311 Main St",
    "sg:city":"Orange",
    "sg:classifiers":[
        {
            "category":"Shopping",
            "subcategory":"Optical Goods",
            "type":"Retail Goods"
        }
    ],
    "sg:phone":"+1   ",
    "sg:postcode":"07050",
    "sg:province":"NJ",
    "wof:name":"C A Eyes Inc",
    "wof:placetype":"venue"
},
  "geometry": {"coordinates":[-74.230282,40.772562],"type":"Point"}
}