{
  "type": "Feature",
  "properties": {
    "addr:full":"162 Short Hills Ave Springfield NJ 07081",
    "addr:housenumber":"162",
    "addr:postcode":"07081",
    "addr:street":"Short Hills Ave",
    "iso:country":"US",
    "sg:address":"162 Short Hills Ave",
    "sg:city":"Springfield",
    "sg:classifiers":[
        {
            "category":"Professional",
            "subcategory":"Management & Consulting",
            "type":"Services"
        }
    ],
    "sg:phone":"+1   ",
    "sg:postcode":"07081",
    "sg:province":"NJ",
    "sg:tags":[
        "business"
    ],
    "wof:name":"Trade Partners Consulting",
    "wof:placetype":"venue"
},
  "geometry": {"coordinates":[-74.32185200000001,40.713386],"type":"Point"}
}