{
  "type": "Feature",
  "properties": {
    "addr:full":"101 Lehigh Dr Lincroft NJ 07738",
    "addr:housenumber":"101",
    "addr:postcode":"07738",
    "addr:street":"Lehigh Dr",
    "iso:country":"US",
    "sg:address":"101 Lehigh Dr",
    "sg:city":"Lincroft",
    "sg:classifiers":[
        {
            "category":"Bus Charters",
            "type":"Transportation"
        }
    ],
    "sg:phone":"+1 732 530 9018",
    "sg:postcode":"07738",
    "sg:province":"NJ",
    "sg:tags":[
        "van"
    ],
    "wof:name":"Cosmopolitan Transportation",
    "wof:placetype":"venue"
},
  "geometry": {"coordinates":[-74.142763,40.34098],"type":"Point"}
}