{
  "type": "Feature",
  "properties": {
    "addr:full":"626 Highland Dr Westampton NJ 08060",
    "addr:housenumber":"626",
    "addr:postcode":"08060",
    "addr:street":"Highland Dr",
    "iso:country":"US",
    "sg:address":"626 Highland Dr",
    "sg:city":"Westampton",
    "sg:classifiers":[
        {
            "category":"Food & Beverages",
            "subcategory":"Groceries & Convenience Stores",
            "type":"Retail Goods"
        }
    ],
    "sg:phone":"+1 609 265 8300",
    "sg:postcode":"08060",
    "sg:province":"NJ",
    "wof:name":"Key Food Brokerage Co",
    "wof:placetype":"venue"
},
  "geometry": {"coordinates":[-74.86100500000001,40.004781],"type":"Point"}
}