{
  "type": "Feature",
  "properties": {
    "iso:country":"US",
    "sg:address":"140 E Hanover St",
    "sg:city":"Trenton",
    "sg:classifiers":[
        {
            "category":"Professional",
            "type":"Services"
        }
    ],
    "sg:phone":"+1   ",
    "sg:postcode":"08608",
    "sg:province":"NJ",
    "wof:name":"Peoples and Stories Gentey Cue",
    "wof:placetype":"venue"
},
  "geometry": {"coordinates":[-74.76209299999999,40.221239],"type":"Point"}
}