{
  "type": "Feature",
  "properties": {
    "addr:full":"332 Bloomfield Ave Bloomfield NJ 07003",
    "addr:housenumber":"332",
    "addr:postcode":"07003",
    "addr:street":"Bloomfield Ave",
    "iso:country":"US",
    "sg:address":"332 Bloomfield Ave",
    "sg:city":"Bloomfield",
    "sg:classifiers":[
        {
            "category":"Health Services",
            "subcategory":"Doctor",
            "type":"Services"
        }
    ],
    "sg:phone":"+1 973 429 9225",
    "sg:postcode":"07003",
    "sg:province":"NJ",
    "sg:tags":[
        "medical"
    ],
    "wof:name":"Petracca Louis J MD",
    "wof:placetype":"venue"
},
  "geometry": {"coordinates":[-74.19360399999999,40.785801],"type":"Point"}
}