{
  "type": "Feature",
  "properties": {
    "iso:country":"US",
    "sg:address":"54 S Orange Ave",
    "sg:city":"South Orange",
    "sg:classifiers":[
        {
            "category":"Health Services",
            "subcategory":"Chiropractor",
            "type":"Services"
        }
    ],
    "sg:phone":"+1 973 761 0500",
    "sg:postcode":"07079",
    "sg:province":"NJ",
    "wof:name":"Jersey Trama Center",
    "wof:placetype":"venue"
},
  "geometry": {"coordinates":[-74.258285,40.745762],"type":"Point"}
}