{
  "type": "Feature",
  "properties": {
    "addr:full":"1203 Route 47 Rio Grande NJ 08242",
    "addr:housenumber":"1203",
    "addr:postcode":"08242",
    "addr:street":"Route 47",
    "iso:country":"US",
    "sg:address":"1203 Route 47",
    "sg:city":"Rio Grande",
    "sg:classifiers":[
        {
            "category":"Bakery",
            "type":"Food & Drink"
        },
        {
            "category":"Donuts",
            "subcategory":"None",
            "type":"Food & Drink"
        }
    ],
    "sg:phone":"+1 609 886 8006",
    "sg:postcode":"08242",
    "sg:province":"NJ",
    "sg:website":"www.dunkindonuts.com",
    "wof:name":"Dunkin Donuts",
    "wof:placetype":"venue"
},
  "geometry": {"coordinates":[-74.875801,39.0145],"type":"Point"}
}