{
  "type": "Feature",
  "properties": {
    "addr:full":"185 Court St Teaneck NJ 07666",
    "addr:housenumber":"185",
    "addr:postcode":"07666",
    "addr:street":"Court St",
    "iso:country":"US",
    "sg:address":"185 Court St",
    "sg:city":"Teaneck",
    "sg:classifiers":[
        {
            "category":"Education",
            "subcategory":"Special Training",
            "type":"Public Place"
        }
    ],
    "sg:phone":"+1 201 568 3896",
    "sg:postcode":"07666",
    "sg:province":"NJ",
    "sg:tags":[
        "tutoring"
    ],
    "wof:name":"Kumon Math & Reading Ctr",
    "wof:placetype":"venue"
},
  "geometry": {"coordinates":[-74.00617200000001,40.900622],"type":"Point"}
}