{
  "type": "Feature",
  "properties": {
    "iso:country":"US",
    "sg:address":"120 US Hwy 130",
    "sg:city":"Bordentown",
    "sg:classifiers":[
        {
            "category":"Wholesale",
            "subcategory":"Farm Supplies",
            "type":"Manufacturing & Wholesale Goods"
        }
    ],
    "sg:phone":"+1 609 298 4100",
    "sg:postcode":"08505",
    "sg:province":"NJ",
    "sg:tags":[
        "bean"
    ],
    "wof:name":"Perdue Farms Incorporated",
    "wof:placetype":"venue"
},
  "geometry": {"coordinates":[-74.696298,40.155996],"type":"Point"}
}