{
  "type": "Feature",
  "properties": {
    "addr:full":"329 Bergen Blvd Palisades Park NJ 07650",
    "addr:housenumber":"329",
    "addr:postcode":"07650",
    "addr:street":"Bergen Blvd",
    "iso:country":"US",
    "sg:address":"329 Bergen Blvd",
    "sg:city":"Palisades Park",
    "sg:classifiers":[
        {
            "category":"Building & Trades",
            "subcategory":"Locksmith",
            "type":"Services"
        }
    ],
    "sg:phone":"+1 201 292 1109",
    "sg:postcode":"07650",
    "sg:province":"NJ",
    "sg:tags":[
        "key"
    ],
    "wof:name":"Palisades Park Locksmith",
    "wof:placetype":"venue"
},
  "geometry": {"coordinates":[-73.988073,40.842087],"type":"Point"}
}