{
  "type": "Feature",
  "properties": {
    "iso:country":"US",
    "sg:address":"930 Bethel Church Rd",
    "sg:city":"Jackson",
    "sg:classifiers":[
        {
            "category":"Professional",
            "subcategory":"Management & Consulting",
            "type":"Services"
        }
    ],
    "sg:phone":"+1   ",
    "sg:postcode":"08527",
    "sg:province":"NJ",
    "sg:tags":[
        "business"
    ],
    "wof:name":"Silver Consulting & Design",
    "wof:placetype":"venue"
},
  "geometry": {"coordinates":[-74.248445,40.129142],"type":"Point"}
}