{
  "type": "Feature",
  "properties": {
    "iso:country":"US",
    "sg:address":"701 Harrison Ave",
    "sg:city":"Harrison",
    "sg:classifiers":[
        {
            "category":"Autos & Motor Vehicles",
            "subcategory":"Fuel & Gas Station",
            "type":"Retail Goods"
        }
    ],
    "sg:phone":"+1 973 485 8901",
    "sg:postcode":"07029",
    "sg:province":"NJ",
    "sg:website":"www.citgo.com",
    "wof:name":"Harrison Citgo",
    "wof:placetype":"venue"
},
  "geometry": {"coordinates":[-74.15070299999999,40.747501],"type":"Point"}
}