{
  "type": "Feature",
  "properties": {
    "iso:country":"US",
    "sg:address":"11 Bailey Ct",
    "sg:city":"Princeton",
    "sg:classifiers":[
        {
            "category":"Professional",
            "subcategory":"Management & Consulting",
            "type":"Services"
        }
    ],
    "sg:phone":"+1 609 333 9199",
    "sg:postcode":"08540",
    "sg:province":"NJ",
    "wof:name":"Singer Aviation Resources",
    "wof:placetype":"venue"
},
  "geometry": {"coordinates":[-74.747455,40.365899],"type":"Point"}
}