{
  "type": "Feature",
  "properties": {
    "iso:country":"US",
    "sg:address":"23 Black Horse Pike",
    "sg:city":"Pleasantville",
    "sg:classifiers":[
        {
            "category":"Professional",
            "subcategory":"Lawyer & Legal Services",
            "type":"Services"
        }
    ],
    "sg:phone":"+1 609 463 3777",
    "sg:postcode":"08232",
    "sg:province":"NJ",
    "sg:tags":[
        "attorney"
    ],
    "wof:name":"Press & Taglialatella",
    "wof:placetype":"venue"
},
  "geometry": {"coordinates":[-74.521469,39.388938],"type":"Point"}
}