{
  "type": "Feature",
  "properties": {
    "addr:full":"104 Lee Pl Teaneck NJ 07652",
    "addr:housenumber":"104",
    "addr:postcode":"07652",
    "addr:street":"Lee Pl",
    "iso:country":"US",
    "sg:address":"104 Lee Pl",
    "sg:city":"Teaneck",
    "sg:classifiers":[
        {
            "category":"Health Services",
            "subcategory":"Clinic",
            "type":"Services"
        }
    ],
    "sg:phone":"+1   ",
    "sg:postcode":"07652",
    "sg:province":"NJ",
    "sg:tags":[
        "home",
        "care"
    ],
    "wof:name":"Caring People Inc",
    "wof:placetype":"venue"
},
  "geometry": {"coordinates":[-74.063644,40.946688],"type":"Point"}
}