{
  "type": "Feature",
  "properties": {
    "addr:full":"9 Beach Rd Ocean City NJ 08226",
    "addr:housenumber":"9",
    "addr:postcode":"08226",
    "addr:street":"Beach Rd",
    "iso:country":"US",
    "sg:address":"9 Beach Rd",
    "sg:city":"Ocean City",
    "sg:classifiers":[
        {
            "category":"Restaurant",
            "type":"Food & Drink"
        }
    ],
    "sg:phone":"+1 609 399 1127",
    "sg:postcode":"08226",
    "sg:province":"NJ",
    "wof:name":"Dune's Grille",
    "wof:placetype":"venue"
},
  "geometry": {"coordinates":[-74.55659,39.284921],"type":"Point"}
}