{
  "type": "Feature",
  "properties": {
    "addr:full":"877 Valley Rd Montclair NJ 07043",
    "addr:housenumber":"877",
    "addr:postcode":"07043",
    "addr:street":"Valley Rd",
    "iso:country":"US",
    "sg:address":"877 Valley Rd",
    "sg:city":"Montclair",
    "sg:classifiers":[
        {
            "category":"Building & Trades",
            "subcategory":"Construction",
            "type":"Services"
        }
    ],
    "sg:phone":"+1 973 744 8078",
    "sg:postcode":"07043",
    "sg:province":"NJ",
    "sg:tags":[
        "general",
        "contractor"
    ],
    "wof:name":"J R POWERS Contracting LLC",
    "wof:placetype":"venue"
},
  "geometry": {"coordinates":[-74.1895,40.870934],"type":"Point"}
}