{
  "type": "Feature",
  "properties": {
    "addr:full":"358 Franklin Ave Belleville NJ 07109",
    "addr:housenumber":"358",
    "addr:postcode":"07109",
    "addr:street":"Franklin Ave",
    "iso:country":"US",
    "sg:address":"358 Franklin Ave",
    "sg:city":"Belleville",
    "sg:classifiers":[
        {
            "category":"Retail",
            "subcategory":"Repair Shop",
            "type":"Services"
        }
    ],
    "sg:phone":"+1   ",
    "sg:postcode":"07109",
    "sg:province":"NJ",
    "sg:tags":[
        "appliance"
    ],
    "wof:name":"Whirlpool",
    "wof:placetype":"venue"
},
  "geometry": {"coordinates":[-74.16964,40.802443],"type":"Point"}
}