{
  "type": "Feature",
  "properties": {
    "iso:country":"US",
    "sg:address":"6 Whitman Ave",
    "sg:city":"Stratford",
    "sg:classifiers":[
        {
            "category":"Arts & Performance",
            "subcategory":"Theater",
            "type":"Entertainment"
        }
    ],
    "sg:phone":"+1 856 784 8143",
    "sg:postcode":"08084",
    "sg:province":"NJ",
    "sg:tags":[
        "bureau"
    ],
    "sg:website":"www.nationalwrestlingsuperstars.com",
    "wof:name":"Sports Entertainment Group",
    "wof:placetype":"venue"
},
  "geometry": {"coordinates":[-75.014172,39.837619],"type":"Point"}
}