{
  "type": "Feature",
  "properties": {
    "iso:country":"US",
    "sg:address":"333 Tuscarora Ave",
    "sg:city":"Barnegat",
    "sg:classifiers":[
        {
            "category":"Professional",
            "type":"Services"
        }
    ],
    "sg:phone":"+1   ",
    "sg:postcode":"08005",
    "sg:province":"NJ",
    "wof:name":"Nabil T Khalil",
    "wof:placetype":"venue"
},
  "geometry": {"coordinates":[-74.197964,39.77097],"type":"Point"}
}