{
  "type": "Feature",
  "properties": {
    "addr:full":"70 W Passaic St Rochelle Park NJ 07662",
    "addr:housenumber":"70",
    "addr:postcode":"07662",
    "addr:street":"W Passaic St",
    "iso:country":"US",
    "sg:address":"70 W Passaic St",
    "sg:city":"Rochelle Park",
    "sg:classifiers":[
        {
            "category":"Real Estate",
            "subcategory":"Developer",
            "type":"Services"
        }
    ],
    "sg:phone":"+1   ",
    "sg:postcode":"07662",
    "sg:province":"NJ",
    "sg:tags":[
        "development",
        "property",
        "c",
        "management",
        "general"
    ],
    "wof:name":"Gatollari Enterprises Inc",
    "wof:placetype":"venue"
},
  "geometry": {"coordinates":[-74.075329,40.910665],"type":"Point"}
}