{
  "type": "Feature",
  "properties": {
    "addr:full":"533 Memorial Pkwy Phillipsburg NJ 08865",
    "addr:housenumber":"533",
    "addr:postcode":"08865",
    "addr:street":"Memorial Pkwy",
    "iso:country":"US",
    "sg:address":"533 Memorial Pkwy",
    "sg:city":"Phillipsburg",
    "sg:classifiers":[
        {
            "category":"Real Estate",
            "subcategory":"Real Estate Agent",
            "type":"Services"
        }
    ],
    "sg:phone":"+1 908 689 3810",
    "sg:postcode":"08865",
    "sg:province":"NJ",
    "wof:name":"Lapel Realty",
    "wof:placetype":"venue"
},
  "geometry": {"coordinates":[-75.185141,40.696315],"type":"Point"}
}