{
  "type": "Feature",
  "properties": {
    "iso:country":"US",
    "sg:address":"15 Ellice St",
    "sg:city":"Lincoln Park",
    "sg:classifiers":[
        {
            "category":"Building & Trades",
            "subcategory":"Construction",
            "type":"Services"
        }
    ],
    "sg:phone":"+1 973 696 2388",
    "sg:postcode":"07035",
    "sg:province":"NJ",
    "sg:tags":[
        "house"
    ],
    "wof:name":"J & K Cnstr & Estimating",
    "wof:placetype":"venue"
},
  "geometry": {"coordinates":[-74.29919599999999,40.928398],"type":"Point"}
}