{
  "type": "Feature",
  "properties": {
    "addr:full":"92 Clinton Pl Newark NJ 07108",
    "addr:housenumber":"92",
    "addr:postcode":"07108",
    "addr:street":"Clinton Pl",
    "iso:country":"US",
    "sg:address":"92 Clinton Pl",
    "sg:city":"Newark",
    "sg:classifiers":[
        {
            "category":"Real Estate",
            "subcategory":"Real Estate Agent",
            "type":"Services"
        }
    ],
    "sg:phone":"+1   ",
    "sg:postcode":"07108",
    "sg:province":"NJ",
    "wof:name":"Amron Realty",
    "wof:placetype":"venue"
},
  "geometry": {"coordinates":[-74.21096300000001,40.719408],"type":"Point"}
}