{
  "type": "Feature",
  "properties": {
    "iso:country":"US",
    "sg:address":"1043 Raymond Blvd",
    "sg:city":"Newark",
    "sg:classifiers":[
        {
            "category":"Parking",
            "type":"Transportation"
        }
    ],
    "sg:phone":"+1 973 624 2022",
    "sg:postcode":"07102",
    "sg:province":"NJ",
    "sg:website":"www.centralparkingsystem.com",
    "wof:name":"Central Parking Systems of Nj",
    "wof:placetype":"venue"
},
  "geometry": {"coordinates":[-74.164096,40.735576],"type":"Point"}
}