{
  "type": "Feature",
  "properties": {
    "iso:country":"US",
    "sg:address":"1308 Haynes Run",
    "sg:city":"Medford",
    "sg:phone":"+1 609 953 0007",
    "sg:postcode":"08055",
    "sg:province":"NJ",
    "sg:tags":[
        "food",
        "equipment",
        "processing"
    ],
    "wof:name":"Garrity Equipment Co",
    "wof:placetype":"venue"
},
  "geometry": {"coordinates":[-74.809462,39.903726],"type":"Point"}
}