{
  "type": "Feature",
  "properties": {
    "addr:full":"200 Van Horne Rd Whitehouse Sta NJ 08889",
    "addr:housenumber":"200",
    "addr:postcode":"08889",
    "addr:street":"Van Horne Rd",
    "iso:country":"US",
    "sg:address":"200 Van Horne Rd",
    "sg:city":"Whitehouse Sta",
    "sg:classifiers":[
        {
            "category":"Real Estate",
            "subcategory":"Real Estate Operator",
            "type":"Services"
        }
    ],
    "sg:phone":"+1 908 534 9300",
    "sg:postcode":"08889",
    "sg:province":"NJ",
    "sg:tags":[
        "building",
        "apartment"
    ],
    "wof:name":"Mirada Senior Residence",
    "wof:placetype":"venue"
},
  "geometry": {"coordinates":[-74.777165,40.619383],"type":"Point"}
}