{
  "type": "Feature",
  "properties": {
    "addr:full":"3 Gormley Ln Butler NJ 07405",
    "addr:housenumber":"3",
    "addr:postcode":"07405",
    "addr:street":"Gormley Ln",
    "iso:country":"US",
    "sg:address":"3 Gormley Ln",
    "sg:city":"Butler",
    "sg:classifiers":[
        {
            "category":"Building & Trades",
            "subcategory":"Construction",
            "type":"Services"
        }
    ],
    "sg:phone":"+1 973 838 0210",
    "sg:postcode":"07405",
    "sg:province":"NJ",
    "sg:tags":[
        "contractor"
    ],
    "wof:name":"Cyclone",
    "wof:placetype":"venue"
},
  "geometry": {"coordinates":[-74.351614,40.986849],"type":"Point"}
}