{
  "type": "Feature",
  "properties": {
    "addr:full":"530 S 1st Ave Absecon NJ 08205",
    "addr:housenumber":"530",
    "addr:postcode":"08205",
    "addr:street":"S 1St Ave",
    "iso:country":"US",
    "sg:address":"530 S 1st Ave",
    "sg:city":"Absecon",
    "sg:classifiers":[
        {
            "category":"Building & Trades",
            "subcategory":"Construction",
            "type":"Services"
        }
    ],
    "sg:phone":"+1 609 652 4025",
    "sg:postcode":"08205",
    "sg:province":"NJ",
    "sg:tags":[
        "painting"
    ],
    "wof:name":"Morgenweck Painting",
    "wof:placetype":"venue"
},
  "geometry": {"coordinates":[-74.52628300000001,39.465399],"type":"Point"}
}