{
  "type": "Feature",
  "properties": {
    "iso:country":"US",
    "sg:address":"108 Quimby St",
    "sg:city":"Westfield",
    "sg:classifiers":[
        {
            "category":"Shopping",
            "subcategory":"Shoes",
            "type":"Retail Goods"
        }
    ],
    "sg:phone":"+1   ",
    "sg:postcode":"07090",
    "sg:province":"NJ",
    "wof:name":"Mephisto Of Westfield",
    "wof:placetype":"venue"
},
  "geometry": {"coordinates":[-74.347804,40.650798],"type":"Point"}
}