{
  "type": "Feature",
  "properties": {
    "iso:country":"US",
    "sg:address":"668 Wyckoff Ave",
    "sg:city":"Wyckoff",
    "sg:classifiers":[
        {
            "category":"Wholesale",
            "subcategory":"Stationery",
            "type":"Manufacturing & Wholesale Goods"
        }
    ],
    "sg:phone":"+1 201 891 5454",
    "sg:postcode":"07481",
    "sg:province":"NJ",
    "sg:tags":[
        "printing",
        "broker",
        "writing",
        "paper",
        "representative",
        "mill"
    ],
    "wof:name":"Anticosti Paper Corporation",
    "wof:placetype":"venue"
},
  "geometry": {"coordinates":[-74.17197899999999,41.01308],"type":"Point"}
}