{
  "type": "Feature",
  "properties": {
    "iso:country":"US",
    "sg:address":"1375 US Hwy 9",
    "sg:city":"Ocean View",
    "sg:classifiers":[
        {
            "category":"Sports & Exercise",
            "subcategory":"Golf",
            "type":"Entertainment"
        }
    ],
    "sg:phone":"+1   ",
    "sg:postcode":"08230",
    "sg:province":"NJ",
    "sg:tags":[
        "course",
        "sporting",
        "public"
    ],
    "wof:name":"Heritage Links Golf Course",
    "wof:placetype":"venue"
},
  "geometry": {"coordinates":[-74.683104,39.234342],"type":"Point"}
}