{
  "type": "Feature",
  "properties": {
    "iso:country":"US",
    "sg:address":"88 Lafayette Ave",
    "sg:city":"Chatham",
    "sg:classifiers":[
        {
            "category":"Professional",
            "subcategory":"Business Services",
            "type":"Services"
        }
    ],
    "sg:phone":"+1   ",
    "sg:postcode":"07928",
    "sg:province":"NJ",
    "wof:name":"Ultimate Coml Liabilities",
    "wof:placetype":"venue"
},
  "geometry": {"coordinates":[-74.39169699999999,40.739826],"type":"Point"}
}