{
  "type": "Feature",
  "properties": {
    "iso:country":"US",
    "sg:address":"98 James St",
    "sg:city":"Edison",
    "sg:classifiers":[
        {
            "category":"Health Services",
            "subcategory":"Doctor",
            "type":"Services"
        }
    ],
    "sg:phone":"+1 732 548 1000",
    "sg:postcode":"08820",
    "sg:province":"NJ",
    "sg:tags":[
        "physician",
        "surgeon"
    ],
    "wof:name":"Surgical Practices Assoc",
    "wof:placetype":"venue"
},
  "geometry": {"coordinates":[-74.346514,40.557007],"type":"Point"}
}