{
  "type": "Feature",
  "properties": {
    "iso:country":"US",
    "sg:address":"28 Kings Ct",
    "sg:city":"Lakewood",
    "sg:classifiers":[
        {
            "category":"Professional",
            "subcategory":"Business Services",
            "type":"Services"
        }
    ],
    "sg:phone":"+1 732 905 4408",
    "sg:postcode":"08701",
    "sg:province":"NJ",
    "wof:name":"Welsher Enterprises LLC",
    "wof:placetype":"venue"
},
  "geometry": {"coordinates":[-74.25105499999999,40.094822],"type":"Point"}
}