{
  "type": "Feature",
  "properties": {
    "addr:full":"4302 Palisade Ave Union City NJ 07087",
    "addr:housenumber":"4302",
    "addr:postcode":"07087",
    "addr:street":"Palisade Ave",
    "iso:country":"US",
    "sg:address":"4302 Palisade Ave",
    "sg:city":"Union City",
    "sg:classifiers":[
        {
            "category":"Professional",
            "subcategory":"Lawyer & Legal Services",
            "type":"Services"
        }
    ],
    "sg:phone":"+1 201 866 9097",
    "sg:postcode":"07087",
    "sg:province":"NJ",
    "wof:name":"Cochi Stephen J ESQ Attorney At Law",
    "wof:placetype":"venue"
},
  "geometry": {"coordinates":[-74.021896,40.777199],"type":"Point"}
}