{
  "type": "Feature",
  "properties": {
    "addr:full":"500 Burton Ave Northfield NJ 08225",
    "addr:housenumber":"500",
    "addr:postcode":"08225",
    "addr:street":"Burton Ave",
    "iso:country":"US",
    "sg:address":"500 Burton Ave",
    "sg:city":"Northfield",
    "sg:classifiers":[
        {
            "category":"Professional",
            "subcategory":"Computer Services",
            "type":"Services"
        }
    ],
    "sg:phone":"+1   ",
    "sg:postcode":"08225",
    "sg:province":"NJ",
    "sg:tags":[
        "related"
    ],
    "wof:name":"Network Labs",
    "wof:placetype":"venue"
},
  "geometry": {"coordinates":[-74.55263600000001,39.384266],"type":"Point"}
}