{
  "type": "Feature",
  "properties": {
    "addr:full":"190 Lodi St Hackensack NJ 07601",
    "addr:housenumber":"190",
    "addr:postcode":"07601",
    "addr:street":"Lodi St",
    "iso:country":"US",
    "sg:address":"190 Lodi St",
    "sg:city":"Hackensack",
    "sg:classifiers":[
        {
            "category":"Food & Beverages",
            "subcategory":"Meat & Fish",
            "type":"Retail Goods"
        }
    ],
    "sg:phone":"+1 201 342 7096",
    "sg:postcode":"07601",
    "sg:province":"NJ",
    "sg:tags":[
        "shop"
    ],
    "wof:name":"Kansas Quality Meats",
    "wof:placetype":"venue"
},
  "geometry": {"coordinates":[-74.05100299999999,40.874599],"type":"Point"}
}