{
  "type": "Feature",
  "properties": {
    "iso:country":"US",
    "sg:address":"1240 Sussex Tpke",
    "sg:city":"Randolph",
    "sg:classifiers":[
        {
            "category":"Health Services",
            "subcategory":"Optometrist",
            "type":"Services"
        }
    ],
    "sg:phone":"+1 973 895 9292",
    "sg:postcode":"07869",
    "sg:province":"NJ",
    "wof:name":"Affinity Eye Care Group",
    "wof:placetype":"venue"
},
  "geometry": {"coordinates":[-74.580252,40.825577],"type":"Point"}
}