{
  "type": "Feature",
  "properties": {
    "iso:country":"US",
    "sg:address":"210 Claiborne Way",
    "sg:city":"Sewell",
    "sg:classifiers":[
        {
            "category":"Building & Trades",
            "subcategory":"Construction",
            "type":"Services"
        }
    ],
    "sg:phone":"+1 856 218 1647",
    "sg:postcode":"08080",
    "sg:province":"NJ",
    "sg:tags":[
        "general",
        "contractor"
    ],
    "wof:name":"Edemi Construction Co Inc",
    "wof:placetype":"venue"
},
  "geometry": {"coordinates":[-75.09735999999999,39.76622],"type":"Point"}
}