{
  "type": "Feature",
  "properties": {
    "iso:country":"US",
    "sg:address":"1808 Capstan Dr",
    "sg:city":"Toms River",
    "sg:classifiers":[
        {
            "category":"Professional",
            "subcategory":"Computer Services",
            "type":"Services"
        }
    ],
    "sg:phone":"+1   ",
    "sg:postcode":"08753",
    "sg:province":"NJ",
    "sg:tags":[
        "related"
    ],
    "wof:name":"Ew Consultants Inc",
    "wof:placetype":"venue"
},
  "geometry": {"coordinates":[-74.14724200000001,39.992549],"type":"Point"}
}