{
  "type": "Feature",
  "properties": {
    "iso:country":"US",
    "sg:address":"28 Millburn Ave",
    "sg:city":"Springfield",
    "sg:classifiers":[
        {
            "category":"Real Estate",
            "subcategory":"Real Estate Operator",
            "type":"Services"
        }
    ],
    "sg:phone":"+1   ",
    "sg:postcode":"07081",
    "sg:province":"NJ",
    "sg:tags":[
        "building",
        "health",
        "nonresidential"
    ],
    "wof:name":"Pointe North Assoc",
    "wof:placetype":"venue"
},
  "geometry": {"coordinates":[-74.324619,40.71754],"type":"Point"}
}