{
  "type": "Feature",
  "properties": {
    "addr:full":"201 Blew Ct East Brunswick NJ 08816",
    "addr:housenumber":"201",
    "addr:postcode":"08816",
    "addr:street":"Blew Ct",
    "iso:country":"US",
    "sg:address":"201 Blew Ct",
    "sg:city":"East Brunswick",
    "sg:classifiers":[
        {
            "category":"Building & Trades",
            "subcategory":"Construction",
            "type":"Services"
        }
    ],
    "sg:phone":"+1 732 432 7737",
    "sg:postcode":"08816",
    "sg:province":"NJ",
    "sg:tags":[
        "hanging",
        "contractor"
    ],
    "wof:name":"Edys Professional Painting",
    "wof:placetype":"venue"
},
  "geometry": {"coordinates":[-74.405008,40.45773],"type":"Point"}
}