{
  "type": "Feature",
  "properties": {
    "addr:full":"125 Country Club Dr Skillman NJ 08558",
    "addr:housenumber":"125",
    "addr:postcode":"08558",
    "addr:street":"Country Club Dr",
    "iso:country":"US",
    "sg:address":"125 Country Club Dr",
    "sg:city":"Skillman",
    "sg:classifiers":[
        {
            "category":"Social Services",
            "type":"Services"
        },
        {
            "category":"Organizations",
            "subcategory":"Membership Organization",
            "type":"Services"
        },
        {
            "category":"Professional",
            "subcategory":"Employment Agencies",
            "type":"Services"
        },
        {
            "category":"Sports & Exercise",
            "subcategory":"Golf",
            "type":"Entertainment"
        }
    ],
    "sg:phone":"+1 609 466 4464",
    "sg:postcode":"08558",
    "sg:province":"NJ",
    "sg:tags":[
        "placement",
        "club",
        "private",
        "course",
        "courses-private",
        "workers'",
        "volunteer"
    ],
    "wof:name":"Cherry Valley Country Club",
    "wof:placetype":"venue"
},
  "geometry": {"coordinates":[-74.71457599999999,40.399996],"type":"Point"}
}