{
  "type": "Feature",
  "properties": {
    "addr:full":"277 Fairfield Rd Fairfield NJ 07004",
    "addr:housenumber":"277",
    "addr:postcode":"07004",
    "addr:street":"Fairfield Rd",
    "iso:country":"US",
    "sg:address":"277 Fairfield Rd",
    "sg:city":"Fairfield",
    "sg:classifiers":[
        {
            "category":"Professional",
            "subcategory":"Business Services",
            "type":"Services"
        }
    ],
    "sg:phone":"+1   ",
    "sg:postcode":"07004",
    "sg:province":"NJ",
    "wof:name":"Webco International Group LLC",
    "wof:placetype":"venue"
},
  "geometry": {"coordinates":[-74.287761,40.88087],"type":"Point"}
}