{
  "type": "Feature",
  "properties": {
    "addr:full":"1592 John St Fort Lee NJ 07024",
    "addr:housenumber":"1592",
    "addr:postcode":"07024",
    "addr:street":"John St",
    "iso:country":"US",
    "sg:address":"1592 John St",
    "sg:city":"Fort Lee",
    "sg:classifiers":[
        {
            "category":"Freight",
            "type":"Transportation"
        }
    ],
    "sg:phone":"+1 201 944 5509",
    "sg:postcode":"07024",
    "sg:province":"NJ",
    "sg:tags":[
        "operator",
        "local",
        "trucking"
    ],
    "wof:name":"Lopez Transport",
    "wof:placetype":"venue"
},
  "geometry": {"coordinates":[-73.979675,40.852519],"type":"Point"}
}