{
  "type": "Feature",
  "properties": {
    "addr:full":"36 Brunswick Woods Dr East Brunswick NJ 08816",
    "addr:housenumber":"36",
    "addr:postcode":"08816",
    "addr:street":"Brunswick Woods Dr",
    "iso:country":"US",
    "sg:address":"36 Brunswick Woods Dr",
    "sg:city":"East Brunswick",
    "sg:classifiers":[
        {
            "category":"Professional",
            "subcategory":"Business Services",
            "type":"Services"
        }
    ],
    "sg:phone":"+1   ",
    "sg:postcode":"08816",
    "sg:province":"NJ",
    "wof:name":"Pilot International Group LLC",
    "wof:placetype":"venue"
},
  "geometry": {"coordinates":[-74.391617,40.420911],"type":"Point"}
}