{
  "type": "Feature",
  "properties": {
    "iso:country":"US",
    "sg:address":"1258 Teaneck Rd",
    "sg:city":"Teaneck",
    "sg:classifiers":[
        {
            "category":"Shopping",
            "subcategory":"Stationery & Office Supplies",
            "type":"Retail Goods"
        },
        {
            "category":"Shopping",
            "subcategory":"Gifts & Souvenirs",
            "type":"Retail Goods"
        }
    ],
    "sg:phone":"+1   ",
    "sg:postcode":"07666",
    "sg:province":"NJ",
    "wof:name":"Papier Mache",
    "wof:placetype":"venue"
},
  "geometry": {"coordinates":[-74.00142,40.894779],"type":"Point"}
}