{
  "type": "Feature",
  "properties": {
    "iso:country":"US",
    "sg:address":"65 State Rte 34",
    "sg:city":"Morganville",
    "sg:classifiers":[
        {
            "category":"Wholesale",
            "subcategory":"Durable Goods & Equipment",
            "type":"Manufacturing & Wholesale Goods"
        }
    ],
    "sg:phone":"+1 732 946 3369",
    "sg:postcode":"07751",
    "sg:province":"NJ",
    "sg:tags":[
        "exporter"
    ],
    "wof:name":"Rice Co",
    "wof:placetype":"venue"
},
  "geometry": {"coordinates":[-74.20752899999999,40.37745],"type":"Point"}
}