{
  "type": "Feature",
  "properties": {
    "iso:country":"US",
    "sg:address":"737 Howe St",
    "sg:city":"Point Pleasant Beach",
    "sg:classifiers":[
        {
            "category":"Manufacturing",
            "subcategory":"Building Materials",
            "type":"Manufacturing & Wholesale Goods"
        }
    ],
    "sg:phone":"+1 732 899 4458",
    "sg:postcode":"08742",
    "sg:province":"NJ",
    "sg:tags":[
        "custom",
        "product",
        "wood",
        "carving"
    ],
    "wof:name":"Marshalls Millwork",
    "wof:placetype":"venue"
},
  "geometry": {"coordinates":[-74.057954,40.07174],"type":"Point"}
}