{
  "type": "Feature",
  "properties": {
    "iso:country":"US",
    "sg:address":"95 Summit Ave",
    "sg:city":"Montclair",
    "sg:classifiers":[
        {
            "category":"Banks & Credit Unions",
            "subcategory":"Investment Brokerage",
            "type":"Services"
        }
    ],
    "sg:phone":"+1 973 744 7889",
    "sg:postcode":"07043",
    "sg:province":"NJ",
    "sg:tags":[
        "investing"
    ],
    "wof:name":"Montclair Asset Management",
    "wof:placetype":"venue"
},
  "geometry": {"coordinates":[-74.199994,40.836963],"type":"Point"}
}