{
  "type": "Feature",
  "properties": {
    "iso:country":"US",
    "sg:address":"721 N Beers St",
    "sg:city":"Holmdel",
    "sg:classifiers":[
        {
            "category":"Health Services",
            "subcategory":"Doctor",
            "type":"Services"
        }
    ],
    "sg:phone":"+1 732 264 7803",
    "sg:postcode":"07733",
    "sg:province":"NJ",
    "sg:tags":[
        "physician",
        "surgeon",
        "medical"
    ],
    "wof:name":"Gurbachan Varma MD",
    "wof:placetype":"venue"
},
  "geometry": {"coordinates":[-74.194954,40.410344],"type":"Point"}
}