{
  "type": "Feature",
  "properties": {
    "addr:full":"373 W Market St Newark NJ 07107",
    "addr:housenumber":"373",
    "addr:postcode":"07107",
    "addr:street":"W Market St",
    "iso:country":"US",
    "sg:address":"373 W Market St",
    "sg:city":"Newark",
    "sg:classifiers":[
        {
            "category":"Food & Beverages",
            "subcategory":"Groceries & Convenience Stores",
            "type":"Retail Goods"
        }
    ],
    "sg:phone":"+1 973 792 0980",
    "sg:postcode":"07107",
    "sg:province":"NJ",
    "wof:name":"Poppy's Grocery",
    "wof:placetype":"venue"
},
  "geometry": {"coordinates":[-74.191498,40.746498],"type":"Point"}
}