{
  "type": "Feature",
  "properties": {
    "iso:country":"US",
    "sg:address":"28 Skyline Dr",
    "sg:city":"Warren",
    "sg:classifiers":[
        {
            "category":"Professional",
            "subcategory":"Computer Services",
            "type":"Services"
        }
    ],
    "sg:phone":"+1   ",
    "sg:postcode":"07059",
    "sg:province":"NJ",
    "sg:tags":[
        "development",
        "consultant",
        "software"
    ],
    "wof:name":"Maddux Software Inc",
    "wof:placetype":"venue"
},
  "geometry": {"coordinates":[-74.55057100000001,40.628736],"type":"Point"}
}