{
  "type": "Feature",
  "properties": {
    "iso:country":"US",
    "sg:address":"4 Nicholas Dr",
    "sg:city":"Sicklerville",
    "sg:classifiers":[
        {
            "category":"Food & Beverages",
            "subcategory":"Liquor & Beverages",
            "type":"Retail Goods"
        }
    ],
    "sg:phone":"+1   ",
    "sg:postcode":"08070",
    "sg:province":"NJ",
    "sg:tags":[
        "alcoholic"
    ],
    "wof:name":"Oaklyn Discount Liquor Inc",
    "wof:placetype":"venue"
},
  "geometry": {"coordinates":[-75.50036900000001,39.668147],"type":"Point"}
}