{
  "type": "Feature",
  "properties": {
    "iso:country":"US",
    "sg:address":"109 W Federal St",
    "sg:city":"Burlington",
    "sg:classifiers":[
        {
            "category":"Building & Trades",
            "subcategory":"Construction",
            "type":"Services"
        }
    ],
    "sg:phone":"+1 609 387 8692",
    "sg:postcode":"08016",
    "sg:province":"NJ",
    "sg:tags":[
        "house"
    ],
    "wof:name":"Benchcraft Builders LLC",
    "wof:placetype":"venue"
},
  "geometry": {"coordinates":[-74.861746,40.074235],"type":"Point"}
}