{
  "type": "Feature",
  "properties": {
    "iso:country":"US",
    "sg:address":"365 Summit Ave",
    "sg:city":"Jersey City",
    "sg:classifiers":[
        {
            "category":"Government",
            "subcategory":"Court House",
            "type":"Public Place"
        }
    ],
    "sg:phone":"+1 201 209 6700",
    "sg:postcode":"07306",
    "sg:province":"NJ",
    "sg:tags":[
        "city"
    ],
    "sg:website":"www.cityofjerseycity.com/court.a...",
    "wof:name":"Jersey City Municipal Court",
    "wof:placetype":"venue"
},
  "geometry": {"coordinates":[-74.06331299999999,40.727974],"type":"Point"}
}