{
  "type": "Feature",
  "properties": {
    "addr:full":"700 Goldman Dr Cream Ridge NJ 08514",
    "addr:housenumber":"700",
    "addr:postcode":"08514",
    "addr:street":"Goldman Dr Cream Ridge",
    "iso:country":"US",
    "sg:address":"700 Goldman Dr",
    "sg:city":"Cream Ridge",
    "sg:classifiers":[
        {
            "category":"Manufacturing",
            "subcategory":"Metals",
            "type":"Manufacturing & Wholesale Goods"
        }
    ],
    "sg:phone":"+1 609 758 0800",
    "sg:postcode":"08514",
    "sg:province":"NJ",
    "sg:tags":[
        "pipe",
        "fitting"
    ],
    "sg:website":"www.sigmaco.com",
    "wof:name":"Sigma Pipefittings",
    "wof:placetype":"venue"
},
  "geometry": {"coordinates":[-74.529895,40.08892],"type":"Point"}
}