{
  "type": "Feature",
  "properties": {
    "addr:full":"5412 Madison St West New York NJ 07093",
    "addr:housenumber":"5412",
    "addr:postcode":"nj 07093",
    "addr:street":"Madison St West",
    "iso:country":"US",
    "sg:address":"5412 Madison St",
    "sg:city":"West New York",
    "sg:classifiers":[
        {
            "category":"Wholesale",
            "subcategory":"Vending Machines",
            "type":"Manufacturing & Wholesale Goods"
        }
    ],
    "sg:phone":"+1   ",
    "sg:postcode":"07093",
    "sg:province":"NJ",
    "sg:tags":[
        "operator"
    ],
    "wof:name":"Amusement Electronics",
    "wof:placetype":"venue"
},
  "geometry": {"coordinates":[-74.019964,40.786003],"type":"Point"}
}