{
  "type": "Feature",
  "properties": {
    "addr:full":"9 Quincy St Passaic NJ 07055",
    "addr:housenumber":"9",
    "addr:postcode":"07055",
    "addr:street":"Quincy St",
    "iso:country":"US",
    "sg:address":"9 Quincy St",
    "sg:city":"Passaic",
    "sg:classifiers":[
        {
            "category":"Health Services",
            "subcategory":"Clinic",
            "type":"Services"
        }
    ],
    "sg:phone":"+1 973 365 5200",
    "sg:postcode":"07055",
    "sg:province":"NJ",
    "sg:tags":[
        "home"
    ],
    "sg:website":"www.patientcare.com",
    "wof:name":"Patient Care",
    "wof:placetype":"venue"
},
  "geometry": {"coordinates":[-74.12226200000001,40.867368],"type":"Point"}
}