{
  "type": "Feature",
  "properties": {
    "iso:country":"US",
    "sg:address":"301 N Harrison St",
    "sg:city":"Princeton",
    "sg:classifiers":[
        {
            "category":"Coffee & Tea",
            "type":"Food & Drink"
        },
        {
            "category":"Donuts",
            "subcategory":"None",
            "type":"Food & Drink"
        }
    ],
    "sg:phone":"+1 609 683 8383",
    "sg:postcode":"08540",
    "sg:province":"NJ",
    "sg:tags":[
        "shop",
        "espresso",
        "restaurant"
    ],
    "sg:website":"http://www.dunkindonuts.com",
    "wof:name":"Dunkin' Donuts",
    "wof:placetype":"venue"
},
  "geometry": {"coordinates":[-74.653008,40.364243],"type":"Point"}
}