{
  "type": "Feature",
  "properties": {
    "iso:country":"US",
    "sg:address":"91 River Rd",
    "sg:city":"Stockton",
    "sg:classifiers":[
        {
            "category":"Manufacturing",
            "subcategory":"Tools & Machinery",
            "type":"Manufacturing & Wholesale Goods"
        }
    ],
    "sg:phone":"+1 609 397 9580",
    "sg:postcode":"08559",
    "sg:province":"NJ",
    "sg:tags":[
        "equipment",
        "mfg"
    ],
    "wof:name":"Heat Processor",
    "wof:placetype":"venue"
},
  "geometry": {"coordinates":[-75.056771,40.418698],"type":"Point"}
}