{
  "type": "Feature",
  "properties": {
    "iso:country":"US",
    "sg:address":"152 Alexander St",
    "sg:city":"Princeton",
    "sg:classifiers":[
        {
            "category":"Insurance",
            "subcategory":"Insurance Agent",
            "type":"Services"
        }
    ],
    "sg:phone":"+1 609 921 6880",
    "sg:postcode":"08540",
    "sg:province":"NJ",
    "wof:name":"Sturhahn Dickenson & Bernard",
    "wof:placetype":"venue"
},
  "geometry": {"coordinates":[-74.658829,40.340558],"type":"Point"}
}