{
  "type": "Feature",
  "properties": {
    "addr:full":"414 Petersburg Rd Dennisville NJ 08270",
    "addr:housenumber":"414",
    "addr:postcode":"08270",
    "addr:street":"Petersburg Rd",
    "iso:country":"US",
    "sg:address":"414 Petersburg Rd",
    "sg:city":"Dennisville",
    "sg:classifiers":[
        {
            "category":"Building & Trades",
            "subcategory":"Plumbing",
            "type":"Services"
        }
    ],
    "sg:phone":"+1 609 861 5189",
    "sg:postcode":"08270",
    "sg:province":"NJ",
    "sg:tags":[
        "plumbing",
        "contractor"
    ],
    "wof:name":"De George Plumbing Heating",
    "wof:placetype":"venue"
},
  "geometry": {"coordinates":[-74.797742,39.201701],"type":"Point"}
}