{
  "type": "Feature",
  "properties": {
    "iso:country":"US",
    "sg:address":"343 Monroe St",
    "sg:city":"Passaic",
    "sg:classifiers":[
        {
            "category":"Shopping",
            "subcategory":"Florist",
            "type":"Retail Goods"
        }
    ],
    "sg:phone":"+1 973 470 9377",
    "sg:postcode":"07055",
    "sg:province":"NJ",
    "wof:name":"Exotika Floral Designs",
    "wof:placetype":"venue"
},
  "geometry": {"coordinates":[-74.13036099999999,40.863606],"type":"Point"}
}