{
  "type": "Feature",
  "properties": {
    "addr:full":"119 Washington Ave Spring Lake NJ 07762",
    "addr:housenumber":"119",
    "addr:postcode":"07762",
    "addr:street":"Washington Ave",
    "iso:country":"US",
    "sg:address":"119 Washington Ave",
    "sg:city":"Spring Lake",
    "sg:classifiers":[
        {
            "category":"Professional",
            "subcategory":"Management & Consulting",
            "type":"Services"
        }
    ],
    "sg:phone":"+1 732 359 0244",
    "sg:postcode":"07762",
    "sg:province":"NJ",
    "sg:tags":[
        "consultant",
        "business"
    ],
    "wof:name":"RMC Consultants",
    "wof:placetype":"venue"
},
  "geometry": {"coordinates":[-74.025469,40.153953],"type":"Point"}
}