{
  "type": "Feature",
  "properties": {
    "addr:full":"2233 State Rte 57 Broadway NJ 07882",
    "addr:housenumber":"2233",
    "addr:postcode":"07882",
    "addr:street":"State Rte 57",
    "iso:country":"US",
    "sg:address":"2233 State Rte 57",
    "sg:city":"Broadway",
    "sg:classifiers":[
        {
            "category":"Organizations",
            "subcategory":"Religious Organization",
            "type":"Services"
        }
    ],
    "sg:phone":"+1 908 689 3720",
    "sg:postcode":"07882",
    "sg:province":"NJ",
    "sg:tags":[
        "church"
    ],
    "wof:name":"Broadway United Methodist Chr",
    "wof:placetype":"venue"
},
  "geometry": {"coordinates":[-75.05018800000001,40.732628],"type":"Point"}
}