{
  "type": "Feature",
  "properties": {
    "iso:country":"US",
    "sg:address":"2 Two Bridges Rd",
    "sg:city":"Fairfield",
    "sg:classifiers":[
        {
            "category":"Restaurant",
            "type":"Food & Drink"
        }
    ],
    "sg:phone":"+1 973 575 1531",
    "sg:postcode":"07004",
    "sg:province":"NJ",
    "wof:name":"Sports Authority Lounge",
    "wof:placetype":"venue"
},
  "geometry": {"coordinates":[-74.272049,40.891987],"type":"Point"}
}