{
  "type": "Feature",
  "properties": {
    "addr:full":"266 Main St Madison NJ 07940",
    "addr:housenumber":"266",
    "addr:postcode":"07940",
    "addr:street":"Main St",
    "iso:country":"US",
    "sg:address":"266 Main St",
    "sg:city":"Madison",
    "sg:classifiers":[
        {
            "category":"Real Estate",
            "subcategory":"Real Estate Agent",
            "type":"Services"
        }
    ],
    "sg:phone":"+1 973 377 3454",
    "sg:postcode":"07940",
    "sg:province":"NJ",
    "sg:website":"www.nedwardrealtors.com",
    "wof:name":"Ned Ward Realtors",
    "wof:placetype":"venue"
},
  "geometry": {"coordinates":[-74.403969,40.751974],"type":"Point"}
}