{
  "type": "Feature",
  "properties": {
    "addr:full":"140 Bloomfield Ave Newark NJ 07104",
    "addr:housenumber":"140",
    "addr:postcode":"07104",
    "addr:street":"Bloomfield Ave",
    "iso:country":"US",
    "sg:address":"140 Bloomfield Ave",
    "sg:city":"Newark",
    "sg:classifiers":[
        {
            "category":"Personal",
            "subcategory":"Beauty Salon",
            "type":"Services"
        }
    ],
    "sg:phone":"+1 973 350 0990",
    "sg:postcode":"07104",
    "sg:province":"NJ",
    "sg:tags":[
        "shop"
    ],
    "wof:name":"Norma Friend Unisex Salon",
    "wof:placetype":"venue"
},
  "geometry": {"coordinates":[-74.17496800000001,40.757996],"type":"Point"}
}