{
  "type": "Feature",
  "properties": {
    "iso:country":"US",
    "sg:address":"35 Bank St",
    "sg:city":"Sussex",
    "sg:classifiers":[
        {
            "category":"Government",
            "subcategory":"Office",
            "type":"Public Place"
        }
    ],
    "sg:phone":"+1   ",
    "sg:postcode":"07461",
    "sg:province":"NJ",
    "sg:tags":[
        "state",
        "park"
    ],
    "wof:name":"High Point State Park",
    "wof:placetype":"venue"
},
  "geometry": {"coordinates":[-74.608679,41.212462],"type":"Point"}
}