{
  "type": "Feature",
  "properties": {
    "iso:country":"US",
    "sg:address":"232 US Hwy 9",
    "sg:city":"Marmora",
    "sg:classifiers":[
        {
            "category":"Home & Garden",
            "subcategory":"Household Appliances",
            "type":"Retail Goods"
        }
    ],
    "sg:phone":"+1   ",
    "sg:postcode":"08223",
    "sg:province":"NJ",
    "sg:tags":[
        "machine",
        "cleaners",
        "vacuum",
        "sewing",
        "repair"
    ],
    "wof:name":"Bakers Sew-Vac Center",
    "wof:placetype":"venue"
},
  "geometry": {"coordinates":[-74.642754,39.271147],"type":"Point"}
}