{
  "type": "Feature",
  "properties": {
    "addr:full":"550 Rt 1 S Newark NJ 07114",
    "addr:housenumber":"550",
    "addr:postcode":"07114",
    "addr:street":"Rt 1 S",
    "iso:country":"US",
    "sg:address":"550 Rt 1 S",
    "sg:city":"Newark",
    "sg:classifiers":[
        {
            "category":"Travel",
            "subcategory":"Hotels & Motels",
            "type":"Entertainment"
        }
    ],
    "sg:phone":"+1 973 824 4000",
    "sg:postcode":"07114",
    "sg:province":"NJ",
    "sg:website":"www.wyndham.com",
    "wof:name":"Wyndham Garden Hotel",
    "wof:placetype":"venue"
},
  "geometry": {"coordinates":[-74.18426599999999,40.703666],"type":"Point"}
}