{
  "type": "Feature",
  "properties": {
    "addr:full":"6738 Black Horse Pike Egg Harbor Twp NJ 08234",
    "addr:housenumber":"6738",
    "addr:postcode":"08234",
    "addr:street":"Black Horse Pike",
    "iso:country":"US",
    "sg:address":"6738 Black Horse Pike",
    "sg:city":"Egg Harbor Twp",
    "sg:classifiers":[
        {
            "category":"Home & Garden",
            "subcategory":"Building Materials",
            "type":"Retail Goods"
        }
    ],
    "sg:phone":"+1 609 646 5784",
    "sg:postcode":"08234",
    "sg:province":"NJ",
    "sg:tags":[
        "lumber"
    ],
    "sg:website":"www.84lumber.com",
    "wof:name":"84 Lumber Co",
    "wof:placetype":"venue"
},
  "geometry": {"coordinates":[-74.56246299999999,39.403226],"type":"Point"}
}