{
  "type": "Feature",
  "properties": {
    "addr:full":"2 E Center Ave Stratford NJ 08052",
    "addr:housenumber":"2",
    "addr:postcode":"08052",
    "addr:street":"Center Ave",
    "iso:country":"US",
    "sg:address":"2 E Center Ave",
    "sg:city":"Stratford",
    "sg:classifiers":[
        {
            "category":"Health Services",
            "subcategory":"Doctor",
            "type":"Services"
        }
    ],
    "sg:phone":"+1   ",
    "sg:postcode":"08052",
    "sg:province":"NJ",
    "wof:name":"Department of Cell Biology",
    "wof:placetype":"venue"
},
  "geometry": {"coordinates":[-74.999387,39.950776],"type":"Point"}
}