{
  "type": "Feature",
  "properties": {
    "iso:country":"US",
    "sg:address":"1312 Myrtle St",
    "sg:city":"Hillside",
    "sg:classifiers":[
        {
            "category":"Building & Trades",
            "subcategory":"Plumbing",
            "type":"Services"
        }
    ],
    "sg:phone":"+1 973 923 9094",
    "sg:postcode":"07205",
    "sg:province":"NJ",
    "sg:tags":[
        "contractor"
    ],
    "wof:name":"Liberty Plumbing & Heating",
    "wof:placetype":"venue"
},
  "geometry": {"coordinates":[-74.229868,40.696121],"type":"Point"}
}