{
  "type": "Feature",
  "properties": {
    "iso:country":"US",
    "sg:address":"550 Broad St",
    "sg:city":"Newark",
    "sg:classifiers":[
        {
            "category":"Insurance",
            "subcategory":"Insurance Agent",
            "type":"Services"
        }
    ],
    "sg:phone":"+1   ",
    "sg:postcode":"07102",
    "sg:province":"NJ",
    "sg:tags":[
        "agency"
    ],
    "wof:name":"Broad & Lombardy Associates",
    "wof:placetype":"venue"
},
  "geometry": {"coordinates":[-74.16914,40.742375],"type":"Point"}
}