{
  "type": "Feature",
  "properties": {
    "addr:full":"85 Outwater Ln Ste 6 Garfield NJ 07026",
    "addr:housenumber":"85",
    "addr:postcode":"07026",
    "addr:street":"Outwater Ln Ste 6",
    "iso:country":"US",
    "sg:address":"85 Outwater Ln Ste 6",
    "sg:city":"Garfield",
    "sg:classifiers":[
        {
            "category":"Restaurant",
            "type":"Food & Drink"
        }
    ],
    "sg:phone":"+1 973 253 1118",
    "sg:postcode":"07026",
    "sg:province":"NJ",
    "sg:tags":[
        "chinese"
    ],
    "wof:name":"Prosperity Chinese Restaurant",
    "wof:placetype":"venue"
},
  "geometry": {"coordinates":[-74.115196,40.881001],"type":"Point"}
}