{
  "type": "Feature",
  "properties": {
    "addr:full":"9600 River Rd Pennsauken NJ 08110",
    "addr:housenumber":"9600",
    "addr:postcode":"08110",
    "addr:street":"River Rd",
    "iso:country":"US",
    "sg:address":"9600 River Rd",
    "sg:city":"Pennsauken",
    "sg:classifiers":[
        {
            "category":"Government",
            "subcategory":"Office",
            "type":"Public Place"
        }
    ],
    "sg:phone":"+1 856 663 2772",
    "sg:postcode":"08110",
    "sg:province":"NJ",
    "sg:tags":[
        "county",
        "program"
    ],
    "sg:website":"www.pcfacc.com",
    "wof:name":"Pollution Control Financing",
    "wof:placetype":"venue"
},
  "geometry": {"coordinates":[-75.034215,39.993477],"type":"Point"}
}