{
  "type": "Feature",
  "properties": {
    "addr:full":"759 Garden Rd Elmer NJ 08318",
    "addr:housenumber":"759",
    "addr:postcode":"08318",
    "addr:street":"Garden Rd",
    "iso:country":"US",
    "sg:address":"759 Garden Rd",
    "sg:city":"Elmer",
    "sg:classifiers":[
        {
            "category":"Food & Beverages",
            "subcategory":"Groceries & Convenience Stores",
            "type":"Retail Goods"
        }
    ],
    "sg:phone":"+1 856 641 7400",
    "sg:postcode":"08318",
    "sg:province":"NJ",
    "sg:tags":[
        "market"
    ],
    "wof:name":"Weaver's Farm Market",
    "wof:placetype":"venue"
},
  "geometry": {"coordinates":[-75.10183499999999,39.529555],"type":"Point"}
}