{
  "type": "Feature",
  "properties": {
    "iso:country":"US",
    "sg:address":"4316 Boardwalk",
    "sg:city":"Wildwood",
    "sg:classifiers":[
        {
            "category":"Shopping",
            "subcategory":"Clothing, Apparel, & Fashions",
            "type":"Retail Goods"
        }
    ],
    "sg:phone":"+1 609 523 0990",
    "sg:postcode":"08260",
    "sg:province":"NJ",
    "sg:tags":[
        "swimwear",
        "accessory"
    ],
    "wof:name":"Bargain Store Swimwear",
    "wof:placetype":"venue"
},
  "geometry": {"coordinates":[-74.816029,38.982999],"type":"Point"}
}