{
  "type": "Feature",
  "properties": {
    "addr:full":"18 Colleen St Newark NJ 07106",
    "addr:housenumber":"18",
    "addr:postcode":"07106",
    "addr:street":"Colleen St",
    "iso:country":"US",
    "sg:address":"18 Colleen St",
    "sg:city":"Newark",
    "sg:classifiers":[
        {
            "category":"Professional",
            "subcategory":"Business Services",
            "type":"Services"
        }
    ],
    "sg:phone":"+1 973 954 2600",
    "sg:postcode":"07106",
    "sg:province":"NJ",
    "sg:tags":[
        "paging",
        "answering"
    ],
    "wof:name":"Rutherford Telephone Answering",
    "wof:placetype":"venue"
},
  "geometry": {"coordinates":[-74.23098299999999,40.735368],"type":"Point"}
}