{
  "type": "Feature",
  "properties": {
    "iso:country":"US",
    "sg:address":"32 Macarthur Ave",
    "sg:city":"Bloomfield",
    "sg:classifiers":[
        {
            "category":"Shopping",
            "subcategory":"Clothing, Apparel, & Fashions",
            "type":"Retail Goods"
        }
    ],
    "sg:phone":"+1 732 446 1685",
    "sg:postcode":"07003",
    "sg:province":"NJ",
    "sg:tags":[
        "alteration"
    ],
    "wof:name":"Savi's Alteration & Dress Mkng",
    "wof:placetype":"venue"
},
  "geometry": {"coordinates":[-74.195786,40.782373],"type":"Point"}
}