{
  "type": "Feature",
  "properties": {
    "iso:country":"US",
    "sg:address":"78 N Pearl St",
    "sg:city":"Bridgeton",
    "sg:classifiers":[
        {
            "category":"Education",
            "subcategory":"College",
            "type":"Public Place"
        }
    ],
    "sg:phone":"+1 856 451 6789",
    "sg:postcode":"08302",
    "sg:province":"NJ",
    "sg:tags":[
        "academic",
        "school"
    ],
    "sg:website":"www.jeffersonhealth.org",
    "wof:name":"Thomas Jefferson Univ Hospital",
    "wof:placetype":"venue"
},
  "geometry": {"coordinates":[-75.23268299999999,39.429508],"type":"Point"}
}