{
  "type": "Feature",
  "properties": {
    "addr:full":"29 Boston Rd Neptune NJ 07753",
    "addr:housenumber":"29",
    "addr:postcode":"07753",
    "addr:street":"Boston Rd",
    "iso:country":"US",
    "sg:address":"29 Boston Rd",
    "sg:city":"Neptune",
    "sg:classifiers":[
        {
            "category":"Professional",
            "subcategory":"Research",
            "type":"Services"
        }
    ],
    "sg:phone":"+1   ",
    "sg:postcode":"07753",
    "sg:province":"NJ",
    "sg:tags":[
        "nonphysical",
        "commercial"
    ],
    "wof:name":"Victoree LLC",
    "wof:placetype":"venue"
},
  "geometry": {"coordinates":[-74.026323,40.19191],"type":"Point"}
}