{
  "type": "Feature",
  "properties": {
    "addr:full":"202 Lane Ave Gloucester City NJ 08030",
    "addr:housenumber":"202",
    "addr:postcode":"08030",
    "addr:street":"Lane Ave",
    "iso:country":"US",
    "sg:address":"202 Lane Ave",
    "sg:city":"Gloucester City",
    "sg:classifiers":[
        {
            "category":"Professional",
            "subcategory":"Computer Services",
            "type":"Services"
        }
    ],
    "sg:phone":"+1 856 456 1750",
    "sg:postcode":"08030",
    "sg:province":"NJ",
    "sg:tags":[
        "internet"
    ],
    "wof:name":"Webcentrics Inc",
    "wof:placetype":"venue"
},
  "geometry": {"coordinates":[-75.116314,39.889938],"type":"Point"}
}