{
  "type": "Feature",
  "properties": {
    "iso:country":"US",
    "sg:address":"187 Lewis St",
    "sg:city":"Phillipsburg",
    "sg:classifiers":[
        {
            "category":"Retail",
            "subcategory":"Repair Shop",
            "type":"Services"
        }
    ],
    "sg:phone":"+1   ",
    "sg:postcode":"08865",
    "sg:province":"NJ",
    "sg:tags":[
        "refrigeration"
    ],
    "wof:name":"G & S Repair Inc",
    "wof:placetype":"venue"
},
  "geometry": {"coordinates":[-75.191872,40.690065],"type":"Point"}
}