{
  "type": "Feature",
  "properties": {
    "iso:country":"US",
    "sg:address":"519 E 1st Ave",
    "sg:city":"Roselle",
    "sg:classifiers":[
        {
            "category":"Retail",
            "subcategory":"Auto Repair",
            "type":"Services"
        }
    ],
    "sg:phone":"+1   ",
    "sg:postcode":"07203",
    "sg:province":"NJ",
    "sg:tags":[
        "general"
    ],
    "wof:name":"Bill S Garage Auto Repair",
    "wof:placetype":"venue"
},
  "geometry": {"coordinates":[-74.25019399999999,40.661908],"type":"Point"}
}