{
  "type": "Feature",
  "properties": {
    "iso:country":"US",
    "sg:address":"100 Willow Brook Rd",
    "sg:city":"Freehold",
    "sg:classifiers":[
        {
            "category":"Professional",
            "subcategory":"Lawyer & Legal Services",
            "type":"Services"
        }
    ],
    "sg:phone":"+1 732 777 1444",
    "sg:postcode":"07728",
    "sg:province":"NJ",
    "wof:name":"Jules Littman Lwyr",
    "wof:placetype":"venue"
},
  "geometry": {"coordinates":[-74.258274,40.24099],"type":"Point"}
}