{
  "type": "Feature",
  "properties": {
    "iso:country":"US",
    "sg:address":"390 Lackland Ave",
    "sg:city":"Piscataway",
    "sg:classifiers":[
        {
            "category":"Building & Trades",
            "subcategory":"Construction",
            "type":"Services"
        }
    ],
    "sg:phone":"+1 732 469 4249",
    "sg:postcode":"08854",
    "sg:province":"NJ",
    "sg:tags":[
        "house"
    ],
    "wof:name":"Maple Grove Inc",
    "wof:placetype":"venue"
},
  "geometry": {"coordinates":[-74.49144,40.564195],"type":"Point"}
}