{
  "type": "Feature",
  "properties": {
    "addr:full":"765 Garfield Ave Jersey City NJ 07305",
    "addr:housenumber":"765",
    "addr:postcode":"07305",
    "addr:street":"Garfield Ave",
    "iso:country":"US",
    "sg:address":"765 Garfield Ave",
    "sg:city":"Jersey City",
    "sg:classifiers":[
        {
            "category":"Retail",
            "subcategory":"Animal Services",
            "type":"Services"
        }
    ],
    "sg:phone":"+1 201 209 9663",
    "sg:postcode":"07305",
    "sg:province":"NJ",
    "wof:name":"Art Dog",
    "wof:placetype":"venue"
},
  "geometry": {"coordinates":[-74.074011,40.705639],"type":"Point"}
}