{
  "type": "Feature",
  "properties": {
    "addr:full":"371 Lake St Newark NJ 07104",
    "addr:housenumber":"371",
    "addr:postcode":"07104",
    "addr:street":"Lake St",
    "iso:country":"US",
    "sg:address":"371 Lake St",
    "sg:city":"Newark",
    "sg:classifiers":[
        {
            "category":"Manufacturing",
            "subcategory":"Tools & Machinery",
            "type":"Manufacturing & Wholesale Goods"
        }
    ],
    "sg:phone":"+1 973 482 4156",
    "sg:postcode":"07104",
    "sg:province":"NJ",
    "sg:tags":[
        "surgical",
        "mfg"
    ],
    "wof:name":"Mtm Management & Developm",
    "wof:placetype":"venue"
},
  "geometry": {"coordinates":[-74.177623,40.762763],"type":"Point"}
}