{
  "type": "Feature",
  "properties": {
    "iso:country":"US",
    "sg:address":"960 State Rte 10",
    "sg:city":"Whippany",
    "sg:classifiers":[
        {
            "category":"Restaurant",
            "type":"Food & Drink"
        }
    ],
    "sg:phone":"+1   ",
    "sg:postcode":"07981",
    "sg:province":"NJ",
    "sg:tags":[
        "tavern"
    ],
    "wof:name":"Bogeys Food & Spirits",
    "wof:placetype":"venue"
},
  "geometry": {"coordinates":[-74.431665,40.829153],"type":"Point"}
}