{
  "type": "Feature",
  "properties": {
    "addr:full":"62 Washington Ave Dumont NJ 07628",
    "addr:housenumber":"62",
    "addr:postcode":"07628",
    "addr:street":"Washington Ave",
    "iso:country":"US",
    "sg:address":"62 Washington Ave",
    "sg:city":"Dumont",
    "sg:classifiers":[
        {
            "category":"Banks & Credit Unions",
            "subcategory":"Bank",
            "type":"Services"
        }
    ],
    "sg:phone":"+1 201 244 1154",
    "sg:postcode":"07628",
    "sg:province":"NJ",
    "sg:tags":[
        "mortgage",
        "loan",
        "broker",
        "banker",
        "real estate"
    ],
    "wof:name":"Nations Standard Mortgage",
    "wof:placetype":"venue"
},
  "geometry": {"coordinates":[-73.994518,40.937677],"type":"Point"}
}