{
  "type": "Feature",
  "properties": {
    "addr:full":"782 State St Perth Amboy NJ 08861",
    "addr:housenumber":"782",
    "addr:postcode":"08861",
    "addr:street":"State St",
    "iso:country":"US",
    "sg:address":"782 State St",
    "sg:city":"Perth Amboy",
    "sg:classifiers":[
        {
            "category":"Sports & Exercise",
            "subcategory":"Sports Center",
            "type":"Entertainment"
        },
        {
            "category":"Arena",
            "subcategory":"Sports Club",
            "type":"Entertainment"
        }
    ],
    "sg:phone":"+1 732 826 2288",
    "sg:postcode":"08861",
    "sg:province":"NJ",
    "sg:tags":[
        "professional",
        "amateur",
        "team"
    ],
    "sg:website":"www.portuguesesportingclub.com",
    "wof:name":"Portuguese Sporting Club",
    "wof:placetype":"venue"
},
  "geometry": {"coordinates":[-74.26419799999999,40.5242],"type":"Point"}
}