{
  "type": "Feature",
  "properties": {
    "addr:full":"94 Chelsea Rd Clifton NJ 07012",
    "addr:housenumber":"94",
    "addr:postcode":"07012",
    "addr:street":"Chelsea Rd",
    "iso:country":"US",
    "sg:address":"94 Chelsea Rd",
    "sg:city":"Clifton",
    "sg:classifiers":[
        {
            "category":"Social Services",
            "subcategory":"Child Care",
            "type":"Services"
        }
    ],
    "sg:phone":"+1 973 779 4844",
    "sg:postcode":"07012",
    "sg:province":"NJ",
    "sg:tags":[
        "kindergarten",
        "academic",
        "school",
        "day",
        "elementary"
    ],
    "wof:name":"Allwood Play & Learn Nursery School",
    "wof:placetype":"venue"
},
  "geometry": {"coordinates":[-74.1632,40.847698],"type":"Point"}
}