{
  "type": "Feature",
  "properties": {
    "iso:country":"US",
    "sg:address":"4600 Bergenline Ave",
    "sg:city":"Union City",
    "sg:classifiers":[
        {
            "category":"Manufacturing",
            "subcategory":"Signs",
            "type":"Manufacturing & Wholesale Goods"
        }
    ],
    "sg:phone":"+1 201 617 7862",
    "sg:postcode":"07087",
    "sg:province":"NJ",
    "sg:tags":[
        "animation",
        "mechanism"
    ],
    "wof:name":"Jennifer Pet Shop",
    "wof:placetype":"venue"
},
  "geometry": {"coordinates":[-74.022453,40.780839],"type":"Point"}
}