{
  "type": "Feature",
  "properties": {
    "addr:full":"137 Kinderkamack Rd Park Ridge NJ 07656",
    "addr:housenumber":"137",
    "addr:postcode":"07656",
    "addr:street":"Kinderkamack Rd Park",
    "iso:country":"US",
    "sg:address":"137 Kinderkamack Rd",
    "sg:city":"Park Ridge",
    "sg:classifiers":[
        {
            "category":"Social Services",
            "subcategory":"Child Care",
            "type":"Services"
        },
        {
            "category":"Professional",
            "subcategory":"Management & Consulting",
            "type":"Services"
        }
    ],
    "sg:phone":"+1 201 391 9280",
    "sg:postcode":"07656",
    "sg:province":"NJ",
    "sg:tags":[
        "kindergarten",
        "consultant",
        "school",
        "company",
        "academic"
    ],
    "wof:name":"Prime Time Child Care MGT LLC",
    "wof:placetype":"venue"
},
  "geometry": {"coordinates":[-74.033525,41.033672],"type":"Point"}
}