{
  "type": "Feature",
  "properties": {
    "addr:full":"125 Jacobstown New Egypt Rd Wrightstown NJ 08562",
    "addr:housenumber":"125",
    "addr:postcode":"08562",
    "addr:street":"Jacobstown New Egypt Rd",
    "iso:country":"US",
    "sg:address":"125 Jacobstown New Egypt Rd",
    "sg:city":"Wrightstown",
    "sg:classifiers":[
        {
            "category":"Manufacturing",
            "subcategory":"Buildings",
            "type":"Manufacturing & Wholesale Goods"
        },
        {
            "category":"Professional",
            "type":"Services"
        }
    ],
    "sg:phone":"+1 609 758 2155",
    "sg:postcode":"08562",
    "sg:province":"NJ",
    "sg:tags":[
        "movers-commercial",
        "house",
        "mover",
        "industrial",
        "raising"
    ],
    "wof:name":"Frank Myroncuk & Son Inc",
    "wof:placetype":"venue"
},
  "geometry": {"coordinates":[-74.56941999999999,40.076859],"type":"Point"}
}