{
  "type": "Feature",
  "properties": {
    "iso:country":"US",
    "sg:address":"320 Ridge Rd",
    "sg:city":"Dayton",
    "sg:classifiers":[
        {
            "category":"Social Services",
            "subcategory":"Child Care",
            "type":"Services"
        }
    ],
    "sg:phone":"+1 732 438 0863",
    "sg:postcode":"08810",
    "sg:province":"NJ",
    "wof:name":"ABC123 Inc",
    "wof:placetype":"venue"
},
  "geometry": {"coordinates":[-74.498186,40.37312],"type":"Point"}
}