{
  "type": "Feature",
  "properties": {
    "addr:full":"310 Firth St Phillipsburg NJ 08865",
    "addr:housenumber":"310",
    "addr:postcode":"08865",
    "addr:street":"Firth St",
    "iso:country":"US",
    "sg:address":"310 Firth St",
    "sg:city":"Phillipsburg",
    "sg:classifiers":[
        {
            "category":"Social Services",
            "subcategory":"Adult Care",
            "type":"Services"
        },
        {
            "category":"Social Services",
            "type":"Services"
        }
    ],
    "sg:phone":"+1 908 859 2423",
    "sg:postcode":"08865",
    "sg:province":"NJ",
    "sg:tags":[
        "organization",
        "senior",
        "citizen"
    ],
    "wof:name":"Phillipsburg Senior Center",
    "wof:placetype":"venue"
},
  "geometry": {"coordinates":[-75.187805,40.693767],"type":"Point"}
}