{
  "type": "Feature",
  "properties": {
    "addr:full":"16 Old Bloomfield Ave Pine Brook NJ 07058",
    "addr:housenumber":"16",
    "addr:postcode":"07058",
    "addr:street":"Old Bloomfield Ave",
    "iso:country":"US",
    "sg:address":"16 Old Bloomfield Ave",
    "sg:city":"Pine Brook",
    "sg:classifiers":[
        {
            "category":"Building & Trades",
            "subcategory":"Construction",
            "type":"Services"
        }
    ],
    "sg:phone":"+1 973 575 3355",
    "sg:postcode":"07058",
    "sg:province":"NJ",
    "sg:tags":[
        "contractor"
    ],
    "sg:website":"www.seifernj.com",
    "wof:name":"Seifer Kitchen",
    "wof:placetype":"venue"
},
  "geometry": {"coordinates":[-74.344115,40.859463],"type":"Point"}
}