{
  "type": "Feature",
  "properties": {
    "iso:country":"US",
    "sg:address":"5209 Bergenline Pl",
    "sg:city":"West New York",
    "sg:classifiers":[
        {
            "category":"Restaurant",
            "type":"Food & Drink"
        }
    ],
    "sg:phone":"+1   ",
    "sg:postcode":"07093",
    "sg:province":"NJ",
    "sg:tags":[
        "eating"
    ],
    "wof:name":"Angelos Pizza",
    "wof:placetype":"venue"
},
  "geometry": {"coordinates":[-74.01965800000001,40.784494],"type":"Point"}
}