{
  "type": "Feature",
  "properties": {
    "iso:country":"US",
    "sg:address":"6233 Westfield Ave",
    "sg:city":"Pennsauken",
    "sg:classifiers":[
        {
            "category":"Wholesale",
            "subcategory":"Durable Goods & Equipment",
            "type":"Manufacturing & Wholesale Goods"
        },
        {
            "category":"Manufacturing",
            "subcategory":"Tools & Machinery",
            "type":"Manufacturing & Wholesale Goods"
        }
    ],
    "sg:phone":"+1 856 486 7711",
    "sg:postcode":"08110",
    "sg:province":"NJ",
    "sg:tags":[
        "industrial",
        "representative",
        "manufacturer",
        "mfg"
    ],
    "sg:website":"www.midlanticenterprises.com",
    "wof:name":"Midlantic Enterprises Inc",
    "wof:placetype":"venue"
},
  "geometry": {"coordinates":[-75.057002,39.963957],"type":"Point"}
}