{
  "type": "Feature",
  "properties": {
    "iso:country":"US",
    "sg:address":"250 E Gibbsboro Rd",
    "sg:city":"Clementon",
    "sg:classifiers":[
        {
            "category":"Health Services",
            "subcategory":"Optometrist",
            "type":"Services"
        }
    ],
    "sg:phone":"+1 856 784 0210",
    "sg:postcode":"08021",
    "sg:province":"NJ",
    "wof:name":"Michael Karliner Od",
    "wof:placetype":"venue"
},
  "geometry": {"coordinates":[-74.981658,39.816541],"type":"Point"}
}