{
  "type": "Feature",
  "properties": {
    "addr:full":"406 Lippincott Dr Marlton NJ 08053",
    "addr:housenumber":"406",
    "addr:postcode":"08053",
    "addr:street":"Lippincott Dr",
    "iso:country":"US",
    "sg:address":"406 Lippincott Dr",
    "sg:city":"Marlton",
    "sg:classifiers":[
        {
            "category":"Professional",
            "subcategory":"Computer Services",
            "type":"Services"
        }
    ],
    "sg:phone":"+1   ",
    "sg:postcode":"08053",
    "sg:province":"NJ",
    "sg:tags":[
        "development",
        "software"
    ],
    "wof:name":"D M Data Corporation",
    "wof:placetype":"venue"
},
  "geometry": {"coordinates":[-74.925754,39.883217],"type":"Point"}
}