{
  "type": "Feature",
  "properties": {
    "addr:full":"76 E Main St Little Falls NJ 07424",
    "addr:housenumber":"76",
    "addr:postcode":"07424",
    "addr:street":"E Main St",
    "iso:country":"US",
    "sg:address":"76 E Main St",
    "sg:city":"Little Falls",
    "sg:classifiers":[
        {
            "category":"Building & Trades",
            "subcategory":"Locksmith",
            "type":"Services"
        }
    ],
    "sg:phone":"+1 973 435 9243",
    "sg:postcode":"07424",
    "sg:province":"NJ",
    "sg:tags":[
        "key"
    ],
    "wof:name":"Locksmith 01 24 Hour",
    "wof:placetype":"venue"
},
  "geometry": {"coordinates":[-74.221673,40.879251],"type":"Point"}
}