{
  "type": "Feature",
  "properties": {
    "addr:full":"439 E Shore Trl Sparta NJ 07871",
    "addr:housenumber":"439",
    "addr:postcode":"07871",
    "addr:street":"E Shore Trl",
    "iso:country":"US",
    "sg:address":"439 E Shore Trl",
    "sg:city":"Sparta",
    "sg:classifiers":[
        {
            "category":"Professional",
            "subcategory":"Management & Consulting",
            "type":"Services"
        }
    ],
    "sg:phone":"+1   ",
    "sg:postcode":"07871",
    "sg:province":"NJ",
    "wof:name":"Product Procurements",
    "wof:placetype":"venue"
},
  "geometry": {"coordinates":[-74.67297000000001,41.004974],"type":"Point"}
}