{
  "type": "Feature",
  "properties": {
    "addr:full":"26 Kroy Ct Cedar Grove NJ 07009",
    "addr:housenumber":"26",
    "addr:postcode":"07009",
    "addr:street":"Kroy Ct",
    "iso:country":"US",
    "sg:address":"26 Kroy Ct",
    "sg:city":"Cedar Grove",
    "sg:classifiers":[
        {
            "category":"Wholesale",
            "subcategory":"Vending Machines",
            "type":"Manufacturing & Wholesale Goods"
        }
    ],
    "sg:phone":"+1   ",
    "sg:postcode":"07009",
    "sg:province":"NJ",
    "sg:tags":[
        "operator",
        "eating"
    ],
    "wof:name":"Javaman Vending",
    "wof:placetype":"venue"
},
  "geometry": {"coordinates":[-74.22677400000001,40.84623],"type":"Point"}
}