{
  "type": "Feature",
  "properties": {
    "addr:full":"2051 Coolidge Ave Whiting NJ 08759",
    "addr:housenumber":"2051",
    "addr:postcode":"08759",
    "addr:street":"Coolidge Ave",
    "iso:country":"US",
    "sg:address":"2051 Coolidge Ave",
    "sg:city":"Whiting",
    "sg:classifiers":[
        {
            "category":"Manufacturing",
            "subcategory":"Printing",
            "type":"Manufacturing & Wholesale Goods"
        }
    ],
    "sg:phone":"+1 201 692 7773",
    "sg:postcode":"08759",
    "sg:province":"NJ",
    "sg:tags":[
        "printer"
    ],
    "wof:name":"Paula Graphics Inc",
    "wof:placetype":"venue"
},
  "geometry": {"coordinates":[-74.39003200000001,39.927195],"type":"Point"}
}