{
  "type": "Feature",
  "properties": {
    "addr:full":"1151 Burnt Tavern Rd Brick NJ 08724",
    "addr:housenumber":"1151",
    "addr:postcode":"08724",
    "addr:street":"Burnt Tavern Rd",
    "iso:country":"US",
    "sg:address":"1151 Burnt Tavern Rd",
    "sg:city":"Brick",
    "sg:classifiers":[
        {
            "category":"Food & Beverages",
            "subcategory":"Groceries & Convenience Stores",
            "type":"Retail Goods"
        }
    ],
    "sg:phone":"+1   ",
    "sg:postcode":"08724",
    "sg:province":"NJ",
    "sg:website":"www.7-eleven.com",
    "wof:name":"7-Eleven",
    "wof:placetype":"venue"
},
  "geometry": {"coordinates":[-74.140226,40.096811],"type":"Point"}
}