{
  "type": "Feature",
  "properties": {
    "iso:country":"US",
    "sg:address":"1835 Greenwood Ave",
    "sg:city":"Trenton",
    "sg:classifiers":[
        {
            "category":"Professional",
            "type":"Services"
        }
    ],
    "sg:phone":"+1 609 584 9001",
    "sg:postcode":"08609",
    "sg:province":"NJ",
    "sg:tags":[
        "establishment"
    ],
    "wof:name":"3l Rosario Brothers",
    "wof:placetype":"venue"
},
  "geometry": {"coordinates":[-74.728157,40.228222],"type":"Point"}
}