{
  "type": "Feature",
  "properties": {
    "addr:full":"786 Bloomfield Ave Clifton NJ 07012",
    "addr:housenumber":"786",
    "addr:postcode":"07012",
    "addr:street":"Bloomfield Ave",
    "iso:country":"US",
    "sg:address":"786 Bloomfield Ave",
    "sg:city":"Clifton",
    "sg:classifiers":[
        {
            "category":"Shopping",
            "type":"Retail Goods"
        }
    ],
    "sg:phone":"+1   ",
    "sg:postcode":"07012",
    "sg:province":"NJ",
    "sg:tags":[
        "phone",
        "cellular"
    ],
    "wof:name":"Straight & Square Wireless",
    "wof:placetype":"venue"
},
  "geometry": {"coordinates":[-74.161191,40.840521],"type":"Point"}
}