{
  "type": "Feature",
  "properties": {
    "iso:country":"US",
    "sg:address":"1351 Route 38 Ste 3",
    "sg:city":"Hainesport",
    "sg:classifiers":[
        {
            "category":"Health Services",
            "subcategory":"Clinic",
            "type":"Services"
        },
        {
            "category":"Health Services",
            "subcategory":"Medical Lab",
            "type":"Services"
        }
    ],
    "sg:phone":"+1 877 496 9809",
    "sg:postcode":"08036",
    "sg:province":"NJ",
    "sg:tags":[
        "information",
        "aid",
        "welfare"
    ],
    "sg:website":"http://national.citysearch.com/profile/external/604375262/medford_nj/std_test_express_medford.html?publisher=yellowpages&reference_id=1&placement=ypwebsitemip",
    "wof:name":"STD Test Express Hainesport",
    "wof:placetype":"venue"
},
  "geometry": {"coordinates":[-74.836737,39.975886],"type":"Point"}
}