{
  "type": "Feature",
  "properties": {
    "iso:country":"US",
    "sg:address":"601 15th St",
    "sg:city":"Ocean City",
    "sg:classifiers":[
        {
            "category":"Travel",
            "subcategory":"Hotels & Motels",
            "type":"Entertainment"
        }
    ],
    "sg:phone":"+1 609 398 4319",
    "sg:postcode":"08226",
    "sg:province":"NJ",
    "sg:tags":[
        "accommodation"
    ],
    "wof:name":"Osborne's Fairview Inn",
    "wof:placetype":"venue"
},
  "geometry": {"coordinates":[-74.583146,39.270968],"type":"Point"}
}