{
  "type": "Feature",
  "properties": {
    "addr:full":"215 State Rte 10 Randolph NJ 07869",
    "addr:housenumber":"215",
    "addr:postcode":"07869",
    "addr:street":"State Rte 10",
    "iso:country":"US",
    "sg:address":"215 State Rte 10",
    "sg:city":"Randolph",
    "sg:classifiers":[
        {
            "category":"Manufacturing",
            "subcategory":"Tools & Machinery",
            "type":"Manufacturing & Wholesale Goods"
        }
    ],
    "sg:phone":"+1 973 328 8559",
    "sg:postcode":"07869",
    "sg:province":"NJ",
    "sg:tags":[
        "machine",
        "shop",
        "industrial",
        "mfg"
    ],
    "wof:name":"CPM Co",
    "wof:placetype":"venue"
},
  "geometry": {"coordinates":[-74.544506,40.871701],"type":"Point"}
}