{
  "type": "Feature",
  "properties": {
    "iso:country":"US",
    "sg:address":"156 Eagle Rock Ave",
    "sg:city":"Roseland",
    "sg:classifiers":[
        {
            "category":"Banks & Credit Unions",
            "subcategory":"Bank",
            "type":"Services"
        }
    ],
    "sg:phone":"+1   ",
    "sg:postcode":"07068",
    "sg:province":"NJ",
    "sg:tags":[
        "federal",
        "savings"
    ],
    "wof:name":"Fleet",
    "wof:placetype":"venue"
},
  "geometry": {"coordinates":[-74.293316,40.820777],"type":"Point"}
}