{
  "type": "Feature",
  "properties": {
    "iso:country":"US",
    "sg:address":"10 Beaver Ave",
    "sg:city":"North Arlington",
    "sg:classifiers":[
        {
            "category":"Organizations",
            "subcategory":"Non-profit Organization",
            "type":"Services"
        }
    ],
    "sg:phone":"+1 201 991 9519",
    "sg:postcode":"07031",
    "sg:province":"NJ",
    "sg:tags":[
        "service/non-profit",
        "community"
    ],
    "wof:name":"Senior Citizens of North Arlington",
    "wof:placetype":"venue"
},
  "geometry": {"coordinates":[-74.133202,40.7883],"type":"Point"}
}