{
  "type": "Feature",
  "properties": {
    "addr:full":"47 Georgetown Blvd Barnegat NJ 08005",
    "addr:housenumber":"47",
    "addr:postcode":"08005",
    "addr:street":"Georgetown Blvd",
    "iso:country":"US",
    "sg:address":"47 Georgetown Blvd",
    "sg:city":"Barnegat",
    "sg:classifiers":[
        {
            "category":"Building & Trades",
            "subcategory":"Landscaping Services",
            "type":"Services"
        }
    ],
    "sg:phone":"+1 609 660 8834",
    "sg:postcode":"08005",
    "sg:province":"NJ",
    "sg:tags":[
        "landscape"
    ],
    "wof:name":"M & M Landscaping",
    "wof:placetype":"venue"
},
  "geometry": {"coordinates":[-74.243255,39.735973],"type":"Point"}
}