{
  "type": "Feature",
  "properties": {
    "addr:full":"79 John St Carteret NJ 07008",
    "addr:housenumber":"79",
    "addr:postcode":"07008",
    "addr:street":"John St",
    "iso:country":"US",
    "sg:address":"79 John St",
    "sg:city":"Carteret",
    "sg:classifiers":[
        {
            "category":"Building & Trades",
            "subcategory":"Cleaning & Sanitation",
            "type":"Services"
        }
    ],
    "sg:phone":"+1   ",
    "sg:postcode":"07008",
    "sg:province":"NJ",
    "sg:tags":[
        "maintenance"
    ],
    "wof:name":"Avalanche Maintenance Inc",
    "wof:placetype":"venue"
},
  "geometry": {"coordinates":[-74.216627,40.585951],"type":"Point"}
}