{
  "type": "Feature",
  "properties": {
    "addr:full":"167 Lincoln Ave Newark NJ 07104",
    "addr:housenumber":"167",
    "addr:postcode":"07104",
    "addr:street":"Lincoln Ave",
    "iso:country":"US",
    "sg:address":"167 Lincoln Ave",
    "sg:city":"Newark",
    "sg:classifiers":[
        {
            "category":"Arts & Performance",
            "subcategory":"Theater",
            "type":"Entertainment"
        }
    ],
    "sg:phone":"+1   ",
    "sg:postcode":"07104",
    "sg:province":"NJ",
    "sg:tags":[
        "theatrical"
    ],
    "wof:name":"Little Wings Entertainment",
    "wof:placetype":"venue"
},
  "geometry": {"coordinates":[-74.163329,40.772001],"type":"Point"}
}