{
  "type": "Feature",
  "properties": {
    "iso:country":"US",
    "sg:address":"82 Hickory Corner Rd",
    "sg:city":"Hightstown",
    "sg:classifiers":[
        {
            "category":"Building & Trades",
            "subcategory":"Construction",
            "type":"Services"
        }
    ],
    "sg:phone":"+1 609 448 1550",
    "sg:postcode":"08520",
    "sg:province":"NJ",
    "sg:tags":[
        "steel",
        "erection",
        "structural"
    ],
    "wof:name":"South Camden Iron Works Inc",
    "wof:placetype":"venue"
},
  "geometry": {"coordinates":[-74.54824600000001,40.259686],"type":"Point"}
}