{
  "type": "Feature",
  "properties": {
    "addr:full":"2200 Springfield Ave Vauxhall NJ 07088",
    "addr:housenumber":"2200",
    "addr:postcode":"07088",
    "addr:street":"Springfield Ave",
    "iso:country":"US",
    "sg:address":"2200 Springfield Ave",
    "sg:city":"Vauxhall",
    "sg:classifiers":[
        {
            "category":"Autos & Motor Vehicles",
            "subcategory":"Fuel & Gas Station",
            "type":"Retail Goods"
        }
    ],
    "sg:phone":"+1 908 686 4119",
    "sg:postcode":"07088",
    "sg:province":"NJ",
    "sg:tags":[
        "oil"
    ],
    "wof:name":"S & J Corp",
    "wof:placetype":"venue"
},
  "geometry": {"coordinates":[-74.284904,40.718388],"type":"Point"}
}