{
  "type": "Feature",
  "properties": {
    "addr:full":"46 Fisk St Jersey City NJ 07305",
    "addr:housenumber":"46",
    "addr:postcode":"07305",
    "addr:street":"Fisk St",
    "iso:country":"US",
    "sg:address":"46 Fisk St",
    "sg:city":"Jersey City",
    "sg:classifiers":[
        {
            "category":"Manufacturing",
            "subcategory":"Apparel",
            "type":"Manufacturing & Wholesale Goods"
        },
        {
            "category":"Manufacturing",
            "subcategory":"Rubber & Plastics",
            "type":"Manufacturing & Wholesale Goods"
        }
    ],
    "sg:phone":"+1 201 451 0600",
    "sg:postcode":"07305",
    "sg:province":"NJ",
    "sg:tags":[
        "product",
        "glove",
        "mfg"
    ],
    "wof:name":"Armin Poly-Version Inc",
    "wof:placetype":"venue"
},
  "geometry": {"coordinates":[-74.092427,40.713576],"type":"Point"}
}