{
  "type": "Feature",
  "properties": {
    "addr:full":"263 14th Ave Newark NJ 07103",
    "addr:housenumber":"263",
    "addr:postcode":"07103",
    "addr:street":"14Th Ave",
    "iso:country":"US",
    "sg:address":"263 14th Ave",
    "sg:city":"Newark",
    "sg:classifiers":[
        {
            "category":"Food & Beverages",
            "subcategory":"Groceries & Convenience Stores",
            "type":"Retail Goods"
        }
    ],
    "sg:phone":"+1   ",
    "sg:postcode":"07103",
    "sg:province":"NJ",
    "wof:name":"Ramon Corp Supermarket",
    "wof:placetype":"venue"
},
  "geometry": {"coordinates":[-74.203344,40.739635],"type":"Point"}
}