{
  "type": "Feature",
  "properties": {
    "iso:country":"US",
    "sg:address":"183 Upper North Shore Rd",
    "sg:city":"Branchville",
    "sg:classifiers":[
        {
            "category":"Retail",
            "subcategory":"Repair Shop",
            "type":"Services"
        }
    ],
    "sg:phone":"+1   ",
    "sg:postcode":"07826",
    "sg:province":"NJ",
    "wof:name":"Satters Furniture Restoration",
    "wof:placetype":"venue"
},
  "geometry": {"coordinates":[-74.73695600000001,41.181149],"type":"Point"}
}