{
  "type": "Feature",
  "properties": {
    "addr:full":"354 13th St Carlstadt NJ 07072",
    "addr:housenumber":"354",
    "addr:postcode":"07072",
    "addr:street":"13Th St",
    "iso:country":"US",
    "sg:address":"354 13th St",
    "sg:city":"Carlstadt",
    "sg:classifiers":[
        {
            "category":"Freight",
            "type":"Transportation"
        }
    ],
    "sg:phone":"+1 201 460 4593",
    "sg:postcode":"07072",
    "sg:province":"NJ",
    "sg:tags":[
        "terminal",
        "truck"
    ],
    "sg:website":"www.empiredistribution.com",
    "wof:name":"Empire Distribution Corp",
    "wof:placetype":"venue"
},
  "geometry": {"coordinates":[-74.086153,40.833391],"type":"Point"}
}