{
  "type": "Feature",
  "properties": {
    "addr:full":"84 Broadway Newark NJ 07104",
    "addr:housenumber":"84",
    "addr:postcode":"07104",
    "addr:street":"Broadway",
    "iso:country":"US",
    "sg:address":"84 Broadway",
    "sg:city":"Newark",
    "sg:classifiers":[
        {
            "category":"Shopping",
            "subcategory":"Beauty & Cosmetics",
            "type":"Retail Goods"
        }
    ],
    "sg:phone":"+1 973 482 8787",
    "sg:postcode":"07104",
    "sg:province":"NJ",
    "sg:tags":[
        "surgical",
        "appliance"
    ],
    "wof:name":"Main Surgical Co",
    "wof:placetype":"venue"
},
  "geometry": {"coordinates":[-74.170689,40.753047],"type":"Point"}
}