{
  "type": "Feature",
  "properties": {
    "addr:full":"1025 Orange Ave Cranford NJ 07016",
    "addr:housenumber":"1025",
    "addr:postcode":"07016",
    "addr:street":"Orange Ave",
    "iso:country":"US",
    "sg:address":"1025 Orange Ave",
    "sg:city":"Cranford",
    "sg:classifiers":[
        {
            "category":"Recreation",
            "type":"Entertainment"
        }
    ],
    "sg:phone":"+1 908 709 7270",
    "sg:postcode":"07016",
    "sg:province":"NJ",
    "sg:tags":[
        "pool",
        "swimming"
    ],
    "wof:name":"Orange Avenue Pool",
    "wof:placetype":"venue"
},
  "geometry": {"coordinates":[-74.29562799999999,40.668974],"type":"Point"}
}