{
  "type": "Feature",
  "properties": {
    "iso:country":"US",
    "sg:address":"1000 Main St",
    "sg:city":"Boonton",
    "sg:classifiers":[
        {
            "category":"Banks & Credit Unions",
            "subcategory":"Investment Brokerage",
            "type":"Services"
        }
    ],
    "sg:phone":"+1 973 402 5916",
    "sg:postcode":"07005",
    "sg:province":"NJ",
    "sg:tags":[
        "consultant",
        "planning",
        "financial"
    ],
    "wof:name":"GMP Assett Management",
    "wof:placetype":"venue"
},
  "geometry": {"coordinates":[-74.414745,40.907073],"type":"Point"}
}