{
  "type": "Feature",
  "properties": {
    "addr:full":"124 Main St Edison NJ 08837",
    "addr:housenumber":"124",
    "addr:postcode":"08837",
    "addr:street":"Main St",
    "iso:country":"US",
    "sg:address":"124 Main St",
    "sg:city":"Edison",
    "sg:classifiers":[
        {
            "category":"Building & Trades",
            "subcategory":"Plumbing",
            "type":"Services"
        }
    ],
    "sg:phone":"+1 732 549 4453",
    "sg:postcode":"08837",
    "sg:province":"NJ",
    "sg:tags":[
        "contractor"
    ],
    "wof:name":"Bens Heating/Cooling",
    "wof:placetype":"venue"
},
  "geometry": {"coordinates":[-74.35759899999999,40.521001],"type":"Point"}
}