{
  "type": "Feature",
  "properties": {
    "iso:country":"US",
    "sg:address":"3201 US Hwy 22",
    "sg:city":"Somerville",
    "sg:classifiers":[
        {
            "category":"Organizations",
            "subcategory":"Membership Organization",
            "type":"Services"
        }
    ],
    "sg:phone":"+1   ",
    "sg:postcode":"08876",
    "sg:province":"NJ",
    "wof:name":"Saint Hbrts Grlda Anmal Shlter",
    "wof:placetype":"venue"
},
  "geometry": {"coordinates":[-74.69994699999999,40.606294],"type":"Point"}
}