{
  "type": "Feature",
  "properties": {
    "iso:country":"US",
    "sg:address":"80 Distribution Blvd",
    "sg:city":"Edison",
    "sg:classifiers":[
        {
            "category":"Wholesale",
            "subcategory":"Apparel",
            "type":"Manufacturing & Wholesale Goods"
        }
    ],
    "sg:phone":"+1 732 650 9501",
    "sg:postcode":"08837",
    "sg:province":"NJ",
    "sg:tags":[
        "infant",
        "wear"
    ],
    "wof:name":"St Eve Intl",
    "wof:placetype":"venue"
},
  "geometry": {"coordinates":[-74.37919599999999,40.499032],"type":"Point"}
}