{
  "type": "Feature",
  "properties": {
    "addr:full":"117 Fort Lee Rd Ste B11 Leonia NJ 07605",
    "addr:housenumber":"117",
    "addr:postcode":"b11;07605",
    "addr:street":"Fort Lee Rd Ste",
    "iso:country":"US",
    "sg:address":"117 Fort Lee Rd Ste B11",
    "sg:city":"Leonia",
    "sg:classifiers":[
        {
            "category":"Autos & Motor Vehicles",
            "subcategory":"Automobile Sales",
            "type":"Retail Goods"
        }
    ],
    "sg:phone":"+1 201 461 3222",
    "sg:postcode":"07605",
    "sg:province":"NJ",
    "sg:tags":[
        "limo"
    ],
    "wof:name":"All Purpose Limousine Inc",
    "wof:placetype":"venue"
},
  "geometry": {"coordinates":[-73.99335000000001,40.864767],"type":"Point"}
}