{
  "type": "Feature",
  "properties": {
    "iso:country":"US",
    "sg:address":"714 E Main St",
    "sg:city":"Moorestown",
    "sg:classifiers":[
        {
            "category":"Banks & Credit Unions",
            "subcategory":"Investment Brokerage",
            "type":"Services"
        },
        {
            "category":"Professional",
            "subcategory":"Management & Consulting",
            "type":"Services"
        }
    ],
    "sg:phone":"+1 856 439 2557",
    "sg:postcode":"08057",
    "sg:province":"NJ",
    "sg:tags":[
        "consultant",
        "financing",
        "financial"
    ],
    "sg:website":"www.evergfs.com",
    "wof:name":"Evergreen Financial Services",
    "wof:placetype":"venue"
},
  "geometry": {"coordinates":[-74.918165,39.972997],"type":"Point"}
}