{
  "type": "Feature",
  "properties": {
    "addr:full":"601 Route 73 S Marlton NJ 08053",
    "addr:housenumber":"601",
    "addr:postcode":"08053",
    "addr:street":"Route 73 S",
    "iso:country":"US",
    "sg:address":"601 Route 73 S",
    "sg:city":"Marlton",
    "sg:classifiers":[
        {
            "category":"Professional",
            "subcategory":"Detective & Security Services",
            "type":"Services"
        },
        {
            "category":"Retail",
            "subcategory":"Funeral Services",
            "type":"Services"
        }
    ],
    "sg:phone":"+1 856 983 1005",
    "sg:postcode":"08053",
    "sg:province":"NJ",
    "sg:tags":[
        "information",
        "advisory",
        "supply",
        "director",
        "plans-pre-arranged",
        "embalmer"
    ],
    "sg:website":"http://bradleyfuneralhome-marlton.com/",
    "wof:name":"Bradley Funeral Homes",
    "wof:placetype":"venue"
},
  "geometry": {"coordinates":[-74.92202,39.87458],"type":"Point"}
}