{
  "type": "Feature",
  "properties": {
    "addr:full":"453 Alloway Friesburg Rd Bridgeton NJ 08302",
    "addr:housenumber":"453",
    "addr:postcode":"08302",
    "addr:street":"Alloway Friesburg Rd",
    "iso:country":"US",
    "sg:address":"453 Alloway Friesburg Rd",
    "sg:city":"Bridgeton",
    "sg:classifiers":[
        {
            "category":"Retail",
            "subcategory":"Repair Shop",
            "type":"Services"
        }
    ],
    "sg:phone":"+1 856 451 8566",
    "sg:postcode":"08302",
    "sg:province":"NJ",
    "sg:tags":[
        "heavy",
        "equipment"
    ],
    "wof:name":"Filbeys Heavy Eqp Repr LLC",
    "wof:placetype":"venue"
},
  "geometry": {"coordinates":[-75.300757,39.538377],"type":"Point"}
}