{
  "type": "Feature",
  "properties": {
    "addr:full":"53 Gerard Rd Trenton NJ 08620",
    "addr:housenumber":"53",
    "addr:postcode":"08620",
    "addr:street":"Gerard Rd",
    "iso:country":"US",
    "sg:address":"53 Gerard Rd",
    "sg:city":"Trenton",
    "sg:classifiers":[
        {
            "category":"Organizations",
            "subcategory":"Community Association",
            "type":"Services"
        }
    ],
    "sg:phone":"+1   ",
    "sg:postcode":"08620",
    "sg:province":"NJ",
    "wof:name":"Patriotic Order Sons of A",
    "wof:placetype":"venue"
},
  "geometry": {"coordinates":[-74.679682,40.190497],"type":"Point"}
}