{
  "type": "Feature",
  "properties": {
    "addr:full":"839 Meadow Rd Bridgewater NJ 08807",
    "addr:housenumber":"839",
    "addr:postcode":"08807",
    "addr:street":"Meadow Rd",
    "iso:country":"US",
    "sg:address":"839 Meadow Rd",
    "sg:city":"Bridgewater",
    "sg:classifiers":[
        {
            "category":"Building & Trades",
            "subcategory":"Construction",
            "type":"Services"
        }
    ],
    "sg:phone":"+1 908 203 9326",
    "sg:postcode":"08807",
    "sg:province":"NJ",
    "sg:tags":[
        "contractor"
    ],
    "wof:name":"TFS Contracting Inc",
    "wof:placetype":"venue"
},
  "geometry": {"coordinates":[-74.65628100000001,40.624892],"type":"Point"}
}