{
  "type": "Feature",
  "properties": {
    "addr:full":"1511 US Hwy 22 Watchung NJ 07069",
    "addr:housenumber":"1511",
    "addr:postcode":"07069",
    "addr:street":"Us Hwy 22",
    "iso:country":"US",
    "sg:address":"1511 US Hwy 22",
    "sg:city":"Watchung",
    "sg:classifiers":[
        {
            "category":"Home & Garden",
            "subcategory":"Home Furnishings",
            "type":"Retail Goods"
        }
    ],
    "sg:phone":"+1 908 822 1800",
    "sg:postcode":"07069",
    "sg:province":"NJ",
    "sg:tags":[
        "housewares"
    ],
    "wof:name":"Bed Bath & Beyond Inc",
    "wof:placetype":"venue"
},
  "geometry": {"coordinates":[-74.415795,40.641127],"type":"Point"}
}