{
  "type": "Feature",
  "properties": {
    "addr:full":"74 Lakeshore Dr Oakland NJ 07436",
    "addr:housenumber":"74",
    "addr:postcode":"07436",
    "addr:street":"Lakeshore Dr",
    "iso:country":"US",
    "sg:address":"74 Lakeshore Dr",
    "sg:city":"Oakland",
    "sg:classifiers":[
        {
            "category":"Professional",
            "type":"Services"
        }
    ],
    "sg:phone":"+1   ",
    "sg:postcode":"07436",
    "sg:province":"NJ",
    "wof:name":"M&W Ullmann Inc",
    "wof:placetype":"venue"
},
  "geometry": {"coordinates":[-74.238142,41.03409],"type":"Point"}
}