{
  "type": "Feature",
  "properties": {
    "addr:full":"1165 US Hwy 22 Plainfield NJ 07060",
    "addr:housenumber":"1165",
    "addr:postcode":"07060",
    "addr:street":"Us Hwy 22",
    "iso:country":"US",
    "sg:address":"1165 US Hwy 22",
    "sg:city":"Plainfield",
    "sg:classifiers":[
        {
            "category":"Restaurant",
            "type":"Food & Drink"
        }
    ],
    "sg:phone":"+1   ",
    "sg:postcode":"07060",
    "sg:province":"NJ",
    "sg:tags":[
        "eating"
    ],
    "wof:name":"Clear Blue Sky Inc",
    "wof:placetype":"venue"
},
  "geometry": {"coordinates":[-74.453743,40.616403],"type":"Point"}
}