{
  "type": "Feature",
  "properties": {
    "addr:full":"1214 Grant Ave Haddon Twp NJ 08107",
    "addr:housenumber":"1214",
    "addr:postcode":"08107",
    "addr:street":"Grant Ave",
    "iso:country":"US",
    "sg:address":"1214 Grant Ave",
    "sg:city":"Haddon Twp",
    "sg:classifiers":[
        {
            "category":"Shopping",
            "subcategory":"Gifts & Souvenirs",
            "type":"Retail Goods"
        }
    ],
    "sg:phone":"+1 856 854 0594",
    "sg:postcode":"08107",
    "sg:province":"NJ",
    "sg:tags":[
        "balloon",
        "artist"
    ],
    "wof:name":"Westville General Store",
    "wof:placetype":"venue"
},
  "geometry": {"coordinates":[-75.09564399999999,39.907925],"type":"Point"}
}