{
  "type": "Feature",
  "properties": {
    "iso:country":"US",
    "sg:address":"26 Park Pl",
    "sg:city":"Paramus",
    "sg:classifiers":[
        {
            "category":"Health Services",
            "subcategory":"Doctor",
            "type":"Services"
        }
    ],
    "sg:phone":"+1 201 262 1140",
    "sg:postcode":"07652",
    "sg:province":"NJ",
    "sg:tags":[
        "physician",
        "surgeon",
        "medical"
    ],
    "wof:name":"Tenafly Pediatrics PA",
    "wof:placetype":"venue"
},
  "geometry": {"coordinates":[-74.073607,40.961333],"type":"Point"}
}