{
  "type": "Feature",
  "properties": {
    "addr:full":"571 Leawood Ave Toms River NJ 08755",
    "addr:housenumber":"571",
    "addr:postcode":"08755",
    "addr:street":"Leawood Ave",
    "iso:country":"US",
    "sg:address":"571 Leawood Ave",
    "sg:city":"Toms River",
    "sg:classifiers":[
        {
            "category":"Professional",
            "subcategory":"Detective & Security Services",
            "type":"Services"
        },
        {
            "category":"Insurance",
            "subcategory":"Insurance Agent",
            "type":"Services"
        }
    ],
    "sg:phone":"+1 732 341 0437",
    "sg:postcode":"08755",
    "sg:province":"NJ",
    "sg:tags":[
        "car"
    ],
    "wof:name":"V I S Investigations",
    "wof:placetype":"venue"
},
  "geometry": {"coordinates":[-74.225464,39.994719],"type":"Point"}
}