{
  "type": "Feature",
  "properties": {
    "iso:country":"US",
    "sg:address":"201 W Walnut Ave",
    "sg:city":"Wildwood",
    "sg:classifiers":[
        {
            "category":"Restaurant",
            "type":"Food & Drink"
        }
    ],
    "sg:phone":"+1 609 729 9314",
    "sg:postcode":"08260",
    "sg:province":"NJ",
    "sg:website":"www.ninosfamilyrestaurant.com",
    "wof:name":"Nino's Family Restaurant",
    "wof:placetype":"venue"
},
  "geometry": {"coordinates":[-74.79409800000001,39.010208],"type":"Point"}
}