{
  "type": "Feature",
  "properties": {
    "iso:country":"US",
    "sg:address":"10 Water St",
    "sg:city":"Farmingdale",
    "sg:classifiers":[
        {
            "category":"Home & Garden",
            "subcategory":"Building Materials",
            "type":"Retail Goods"
        }
    ],
    "sg:phone":"+1 732 938 3060",
    "sg:postcode":"07727",
    "sg:province":"NJ",
    "sg:tags":[
        "screen",
        "window"
    ],
    "wof:name":"Eastern Screen Co",
    "wof:placetype":"venue"
},
  "geometry": {"coordinates":[-74.16797800000001,40.193711],"type":"Point"}
}