{
  "type": "Feature",
  "properties": {
    "iso:country":"US",
    "sg:address":"6 Kings Hwy",
    "sg:city":"Middletown",
    "sg:classifiers":[
        {
            "category":"Real Estate",
            "subcategory":"Real Estate Agent",
            "type":"Services"
        }
    ],
    "sg:phone":"+1 732 671 0100",
    "sg:postcode":"07748",
    "sg:province":"NJ",
    "wof:name":"Woodward Realty Group Inc",
    "wof:placetype":"venue"
},
  "geometry": {"coordinates":[-74.104623,40.393837],"type":"Point"}
}