{
  "type": "Feature",
  "properties": {
    "iso:country":"US",
    "sg:address":"4000 State Rte 66",
    "sg:city":"Eatontown",
    "sg:classifiers":[
        {
            "category":"Insurance",
            "subcategory":"Life Insurance",
            "type":"Services"
        }
    ],
    "sg:phone":"+1   ",
    "sg:postcode":"07753",
    "sg:province":"NJ",
    "sg:tags":[
        "carrier"
    ],
    "wof:name":"MetLife",
    "wof:placetype":"venue"
},
  "geometry": {"coordinates":[-74.09602099999999,40.219195],"type":"Point"}
}