{
  "type": "Feature",
  "properties": {
    "iso:country":"US",
    "sg:address":"200 Lanidex Plz",
    "sg:city":"Parsippany",
    "sg:classifiers":[
        {
            "category":"Professional",
            "subcategory":"Employment Agencies",
            "type":"Services"
        }
    ],
    "sg:phone":"+1 973 526 5113",
    "sg:postcode":"07054",
    "sg:province":"NJ",
    "wof:name":"Global Employment Solutions",
    "wof:placetype":"venue"
},
  "geometry": {"coordinates":[-74.421965,40.862746],"type":"Point"}
}