{
  "type": "Feature",
  "properties": {
    "iso:country":"US",
    "sg:address":"8 Ridgeview Ct",
    "sg:city":"Highland Lakes",
    "sg:classifiers":[
        {
            "category":"Restaurant",
            "type":"Food & Drink"
        }
    ],
    "sg:phone":"+1   ",
    "sg:postcode":"07422",
    "sg:province":"NJ",
    "sg:tags":[
        "eating"
    ],
    "wof:name":"Millside Cafe Inc",
    "wof:placetype":"venue"
},
  "geometry": {"coordinates":[-74.439279,41.190322],"type":"Point"}
}