{
  "type": "Feature",
  "properties": {
    "iso:country":"US",
    "sg:address":"394 Smith St",
    "sg:city":"Perth Amboy",
    "sg:classifiers":[
        {
            "category":"Organizations",
            "subcategory":"Religious Organization",
            "type":"Services"
        }
    ],
    "sg:phone":"+1   ",
    "sg:postcode":"08861",
    "sg:province":"NJ",
    "wof:name":"Iglesia Pentecostal Un Nuevo R",
    "wof:placetype":"venue"
},
  "geometry": {"coordinates":[-74.27974399999999,40.511899],"type":"Point"}
}