{
  "type": "Feature",
  "properties": {
    "iso:country":"US",
    "sg:address":"46 Narrowbrook Ct",
    "sg:city":"Englishtown",
    "sg:classifiers":[
        {
            "category":"Professional",
            "subcategory":"Accounting & Tax Preparation",
            "type":"Services"
        }
    ],
    "sg:phone":"+1 732 625 0839",
    "sg:postcode":"07726",
    "sg:province":"NJ",
    "sg:tags":[
        "accountant"
    ],
    "wof:name":"David A Dorffman CPA",
    "wof:placetype":"venue"
},
  "geometry": {"coordinates":[-74.298129,40.28476],"type":"Point"}
}