{
  "type": "Feature",
  "properties": {
    "iso:country":"US",
    "sg:address":"320 Main St",
    "sg:city":"West Orange",
    "sg:classifiers":[
        {
            "category":"Professional",
            "type":"Services"
        }
    ],
    "sg:phone":"+1   ",
    "sg:postcode":"07052",
    "sg:province":"NJ",
    "wof:name":"Mundo Music",
    "wof:placetype":"venue"
},
  "geometry": {"coordinates":[-74.232066,40.789365],"type":"Point"}
}