{
  "type": "Feature",
  "properties": {
    "addr:full":"535 Route 38 Cherry Hill NJ 08002",
    "addr:housenumber":"535",
    "addr:postcode":"08002",
    "addr:street":"Route 38",
    "iso:country":"US",
    "sg:address":"535 Route 38",
    "sg:city":"Cherry Hill",
    "sg:classifiers":[
        {
            "category":"Professional",
            "subcategory":"Lawyer & Legal Services",
            "type":"Services"
        }
    ],
    "sg:phone":"+1 856 663 3283",
    "sg:postcode":"08002",
    "sg:province":"NJ",
    "wof:name":"Chiumento McNally and Shockley",
    "wof:placetype":"venue"
},
  "geometry": {"coordinates":[-75.04910599999999,39.935853],"type":"Point"}
}