{
  "type": "Feature",
  "properties": {
    "addr:full":"107 Turlington Ct Livingston NJ 07039",
    "addr:housenumber":"107",
    "addr:postcode":"07039",
    "addr:street":"Turlington Ct",
    "iso:country":"US",
    "sg:address":"107 Turlington Ct",
    "sg:city":"Livingston",
    "sg:classifiers":[
        {
            "category":"Professional",
            "subcategory":"Computer Services",
            "type":"Services"
        }
    ],
    "sg:phone":"+1 973 758 0448",
    "sg:postcode":"07039",
    "sg:province":"NJ",
    "sg:tags":[
        "information",
        "technology"
    ],
    "wof:name":"Information Laboratory Inc",
    "wof:placetype":"venue"
},
  "geometry": {"coordinates":[-74.355301,40.76879],"type":"Point"}
}