{
  "type": "Feature",
  "properties": {
    "addr:full":"615 Green Grove Rd Tinton Falls NJ 07712",
    "addr:housenumber":"615",
    "addr:postcode":"07712",
    "addr:street":"Green Grove Rd",
    "iso:country":"US",
    "sg:address":"615 Green Grove Rd",
    "sg:city":"Tinton Falls",
    "sg:classifiers":[
        {
            "category":"Building & Trades",
            "subcategory":"Landscaping Services",
            "type":"Services"
        }
    ],
    "sg:phone":"+1 732 922 0405",
    "sg:postcode":"07712",
    "sg:province":"NJ",
    "sg:tags":[
        "topsoil"
    ],
    "wof:name":"Benoit Top Soil",
    "wof:placetype":"venue"
},
  "geometry": {"coordinates":[-74.07477,40.251896],"type":"Point"}
}