{
  "type": "Feature",
  "properties": {
    "addr:full":"13 Bainbridge Ln Sewell NJ 08080",
    "addr:housenumber":"13",
    "addr:postcode":"08080",
    "addr:street":"Bainbridge Ln",
    "iso:country":"US",
    "sg:address":"13 Bainbridge Ln",
    "sg:city":"Sewell",
    "sg:classifiers":[
        {
            "category":"Coffee & Tea",
            "type":"Food & Drink"
        },
        {
            "category":"Restaurant",
            "type":"Food & Drink"
        }
    ],
    "sg:phone":"+1 856 218 2979",
    "sg:postcode":"08080",
    "sg:province":"NJ",
    "sg:tags":[
        "espresso"
    ],
    "wof:name":"Jank Cafe",
    "wof:placetype":"venue"
},
  "geometry": {"coordinates":[-75.100534,39.751486],"type":"Point"}
}