{
  "type": "Feature",
  "properties": {
    "iso:country":"US",
    "sg:address":"100 Colony Cir",
    "sg:city":"Lakewood",
    "sg:classifiers":[
        {
            "category":"Retail",
            "subcategory":"Repair Shop",
            "type":"Services"
        }
    ],
    "sg:phone":"+1 732 942 7499",
    "sg:postcode":"08701",
    "sg:province":"NJ",
    "sg:tags":[
        "equipment",
        "electronic",
        "supply"
    ],
    "wof:name":"MKD United Corp",
    "wof:placetype":"venue"
},
  "geometry": {"coordinates":[-74.20988699999999,40.107163],"type":"Point"}
}