{
  "type": "Feature",
  "properties": {
    "iso:country":"US",
    "sg:address":"517 Delanco Rd",
    "sg:city":"Beverly",
    "sg:classifiers":[
        {
            "category":"Professional",
            "subcategory":"Engineering",
            "type":"Services"
        },
        {
            "category":"Home & Garden",
            "subcategory":"Building Materials",
            "type":"Retail Goods"
        },
        {
            "category":"Building & Trades",
            "subcategory":"Construction",
            "type":"Services"
        }
    ],
    "sg:phone":"+1 609 871 5850",
    "sg:postcode":"08010",
    "sg:province":"NJ",
    "sg:tags":[
        "repair",
        "system",
        "specialty",
        "heating",
        "equipment",
        "ventilating",
        "contractor",
        "air conditioning"
    ],
    "sg:website":"http://www.tedspeerandsons.com",
    "wof:name":"Speer, Ted & Sons",
    "wof:placetype":"venue"
},
  "geometry": {"coordinates":[-74.92063,40.045894],"type":"Point"}
}