{
  "type": "Feature",
  "properties": {
    "iso:country":"US",
    "sg:address":"98 Main St",
    "sg:city":"East Brunswick",
    "sg:classifiers":[
        {
            "category":"Restaurant",
            "type":"Food & Drink"
        }
    ],
    "sg:phone":"+1 732 251 6929",
    "sg:postcode":"08816",
    "sg:province":"NJ",
    "wof:name":"Linda's Diner & Restaurant",
    "wof:placetype":"venue"
},
  "geometry": {"coordinates":[-74.370566,40.411527],"type":"Point"}
}