{
  "type": "Feature",
  "properties": {
    "iso:country":"US",
    "sg:address":"298 S White Horse Pike",
    "sg:city":"Audubon",
    "sg:classifiers":[
        {
            "category":"Shopping",
            "subcategory":"Mobile Phones",
            "type":"Retail Goods"
        }
    ],
    "sg:phone":"+1 856 546 8080",
    "sg:postcode":"08106",
    "sg:province":"NJ",
    "wof:name":"Best Wireless",
    "wof:placetype":"venue"
},
  "geometry": {"coordinates":[-75.066101,39.891399],"type":"Point"}
}