{
  "type": "Feature",
  "properties": {
    "iso:country":"US",
    "sg:address":"63 Oak St",
    "sg:city":"Norwood",
    "sg:classifiers":[
        {
            "category":"Autos & Motor Vehicles",
            "subcategory":"Auto Supplies",
            "type":"Retail Goods"
        }
    ],
    "sg:phone":"+1 201 784 8848",
    "sg:postcode":"07648",
    "sg:province":"NJ",
    "sg:tags":[
        "automobile",
        "part",
        "accessory"
    ],
    "wof:name":"PIAA Direct",
    "wof:placetype":"venue"
},
  "geometry": {"coordinates":[-73.953074,40.997636],"type":"Point"}
}