{
  "type": "Feature",
  "properties": {
    "addr:full":"234 Delancey St Newark NJ 07105",
    "addr:housenumber":"234",
    "addr:postcode":"07105",
    "addr:street":"Delancey St",
    "iso:country":"US",
    "sg:address":"234 Delancey St",
    "sg:city":"Newark",
    "sg:classifiers":[
        {
            "category":"Autos & Motor Vehicles",
            "subcategory":"Auto Supplies",
            "type":"Retail Goods"
        }
    ],
    "sg:phone":"+1 973 344 4733",
    "sg:postcode":"07105",
    "sg:province":"NJ",
    "sg:tags":[
        "automobile",
        "stereo",
        "radio"
    ],
    "wof:name":"Superior Sounds",
    "wof:placetype":"venue"
},
  "geometry": {"coordinates":[-74.157355,40.718956],"type":"Point"}
}