{
  "type": "Feature",
  "properties": {
    "addr:full":"320 Grove Ave Cedar Grove NJ 07009",
    "addr:housenumber":"320",
    "addr:postcode":"07009",
    "addr:street":"Grove Ave",
    "iso:country":"US",
    "sg:address":"320 Grove Ave",
    "sg:city":"Cedar Grove",
    "sg:classifiers":[
        {
            "category":"Building & Trades",
            "subcategory":"Plumbing",
            "type":"Services"
        }
    ],
    "sg:phone":"+1 973 857 1535",
    "sg:postcode":"07009",
    "sg:province":"NJ",
    "sg:website":"www.metricplumbing.com",
    "wof:name":"Metric Plumbing & Heating Inc",
    "wof:placetype":"venue"
},
  "geometry": {"coordinates":[-74.230904,40.853802],"type":"Point"}
}