{
  "type": "Feature",
  "properties": {
    "iso:country":"US",
    "sg:address":"1275 Palisade Ave",
    "sg:city":"Fort Lee",
    "sg:classifiers":[
        {
            "category":"Professional",
            "type":"Services"
        }
    ],
    "sg:phone":"+1   ",
    "sg:postcode":"07024",
    "sg:province":"NJ",
    "wof:name":"Rdr Yachts Inc",
    "wof:placetype":"venue"
},
  "geometry": {"coordinates":[-73.97676300000001,40.83957],"type":"Point"}
}