{
  "type": "Feature",
  "properties": {
    "addr:full":"75 Flanders Rd Flanders NJ 07836",
    "addr:housenumber":"75",
    "addr:postcode":"07836",
    "addr:street":"Flanders Rd",
    "iso:country":"US",
    "sg:address":"75 Flanders Rd",
    "sg:city":"Flanders",
    "sg:classifiers":[
        {
            "category":"Professional",
            "type":"Services"
        }
    ],
    "sg:phone":"+1 973 691 1119",
    "sg:postcode":"07836",
    "sg:province":"NJ",
    "sg:tags":[
        "establishment"
    ],
    "wof:name":"KMN Development",
    "wof:placetype":"venue"
},
  "geometry": {"coordinates":[-74.713117,40.863095],"type":"Point"}
}