{
  "type": "Feature",
  "properties": {
    "iso:country":"US",
    "sg:address":"8 Coolidge Dr",
    "sg:city":"Brick",
    "sg:classifiers":[
        {
            "category":"Wholesale",
            "subcategory":"Electrical",
            "type":"Manufacturing & Wholesale Goods"
        }
    ],
    "sg:phone":"+1 732 295 1277",
    "sg:postcode":"08724",
    "sg:province":"NJ",
    "sg:tags":[
        "generator"
    ],
    "wof:name":"Dieter Franiok Electrical",
    "wof:placetype":"venue"
},
  "geometry": {"coordinates":[-74.10632099999999,40.078121],"type":"Point"}
}