{
  "type": "Feature",
  "properties": {
    "iso:country":"US",
    "sg:address":"25 W Parker Ave",
    "sg:city":"Maplewood",
    "sg:classifiers":[
        {
            "category":"Education",
            "subcategory":"Special Training",
            "type":"Public Place"
        }
    ],
    "sg:phone":"+1 973 762 1591",
    "sg:postcode":"07040",
    "sg:province":"NJ",
    "sg:tags":[
        "center"
    ],
    "wof:name":"Maplewood Township Board-Edu",
    "wof:placetype":"venue"
},
  "geometry": {"coordinates":[-74.26985500000001,40.736891],"type":"Point"}
}