{
  "type": "Feature",
  "properties": {
    "iso:country":"US",
    "sg:address":"1122 Teaneck Rd",
    "sg:city":"Teaneck",
    "sg:classifiers":[
        {
            "category":"Building & Trades",
            "subcategory":"Electrical",
            "type":"Services"
        }
    ],
    "sg:phone":"+1 201 837 0612",
    "sg:postcode":"07666",
    "sg:province":"NJ",
    "sg:tags":[
        "electrician"
    ],
    "wof:name":"Nunery Le Roy & Sons",
    "wof:placetype":"venue"
},
  "geometry": {"coordinates":[-74.002403,40.892502],"type":"Point"}
}