{
  "type": "Feature",
  "properties": {
    "addr:full":"52 Medallion Ln Willingboro NJ 08046",
    "addr:housenumber":"52",
    "addr:postcode":"08046",
    "addr:street":"Medallion Ln",
    "iso:country":"US",
    "sg:address":"52 Medallion Ln",
    "sg:city":"Willingboro",
    "sg:classifiers":[
        {
            "category":"Professional",
            "subcategory":"Business Services",
            "type":"Services"
        }
    ],
    "sg:phone":"+1   ",
    "sg:postcode":"08046",
    "sg:province":"NJ",
    "wof:name":"M & K Svcs",
    "wof:placetype":"venue"
},
  "geometry": {"coordinates":[-74.883301,40.023148],"type":"Point"}
}