{
  "type": "Feature",
  "properties": {
    "addr:full":"3 E 2nd St Clifton NJ 07011",
    "addr:housenumber":"3",
    "addr:postcode":"07011",
    "addr:street":"E 2Nd St",
    "iso:country":"US",
    "sg:address":"3 E 2nd St",
    "sg:city":"Clifton",
    "sg:classifiers":[
        {
            "category":"Building & Trades",
            "subcategory":"Locksmith",
            "type":"Services"
        }
    ],
    "sg:phone":"+1 908 372 6729",
    "sg:postcode":"07011",
    "sg:province":"NJ",
    "sg:tags":[
        "key"
    ],
    "wof:name":"1 24 Hour 7 Day A Lock A Locksmith",
    "wof:placetype":"venue"
},
  "geometry": {"coordinates":[-74.139416,40.890657],"type":"Point"}
}