{
  "type": "Feature",
  "properties": {
    "addr:full":"56 St Lawrence Way Marlboro NJ 07746",
    "addr:housenumber":"56",
    "addr:postcode":"07746",
    "addr:street":"St Lawrence Way",
    "iso:country":"US",
    "sg:address":"56 St Lawrence Way",
    "sg:city":"Marlboro",
    "sg:classifiers":[
        {
            "category":"Professional",
            "subcategory":"Management & Consulting",
            "type":"Services"
        }
    ],
    "sg:phone":"+1 732 536 6950",
    "sg:postcode":"07746",
    "sg:province":"NJ",
    "sg:tags":[
        "consultant",
        "lighting"
    ],
    "wof:name":"E & M Lighting",
    "wof:placetype":"venue"
},
  "geometry": {"coordinates":[-74.281605,40.322532],"type":"Point"}
}