{
  "type": "Feature",
  "properties": {
    "addr:full":"500 Horizon Center Trenton NJ 08691",
    "addr:housenumber":"500",
    "addr:postcode":"08691",
    "addr:street":"Horizon Center",
    "iso:country":"US",
    "sg:address":"500 Horizon Center",
    "sg:city":"Trenton",
    "sg:classifiers":[
        {
            "category":"Organizations",
            "subcategory":"Professional Association",
            "type":"Services"
        }
    ],
    "sg:phone":"+1 609 587 5577",
    "sg:postcode":"08691",
    "sg:province":"NJ",
    "wof:name":"Nj Builders Assn",
    "wof:placetype":"venue"
},
  "geometry": {"coordinates":[-74.641334,40.199483],"type":"Point"}
}