{
  "type": "Feature",
  "properties": {
    "addr:full":"1608 Elwood Rd Hammonton NJ 08037",
    "addr:housenumber":"1608",
    "addr:postcode":"08037",
    "addr:street":"Elwood Rd",
    "iso:country":"US",
    "sg:address":"1608 Elwood Rd",
    "sg:city":"Hammonton",
    "sg:classifiers":[
        {
            "category":"Building & Trades",
            "subcategory":"Cleaning & Sanitation",
            "type":"Services"
        }
    ],
    "sg:phone":"+1   ",
    "sg:postcode":"08037",
    "sg:province":"NJ",
    "sg:tags":[
        "janitorial"
    ],
    "wof:name":"J R Gandy Service Industries",
    "wof:placetype":"venue"
},
  "geometry": {"coordinates":[-74.68041100000001,39.607349],"type":"Point"}
}