{
  "type": "Feature",
  "properties": {
    "addr:full":"22 E Ridgewood Ave Ridgewood NJ 07450",
    "addr:housenumber":"22",
    "addr:postcode":"07450",
    "addr:street":"E Ridgewood Ave",
    "iso:country":"US",
    "sg:address":"22 E Ridgewood Ave",
    "sg:city":"Ridgewood",
    "sg:classifiers":[
        {
            "category":"Restaurant",
            "type":"Food & Drink"
        },
        {
            "category":"Ice Cream",
            "type":"Food & Drink"
        }
    ],
    "sg:menulink":"http://www.allmenus.com/nj/ridgewood/232627-haagen-dazs/menu/",
    "sg:phone":"+1 201 447 9840",
    "sg:postcode":"07450",
    "sg:province":"NJ",
    "sg:tags":[
        "american",
        "ice",
        "cream"
    ],
    "wof:name":"Haagen Dazs",
    "wof:placetype":"venue"
},
  "geometry": {"coordinates":[-74.12011099999999,40.979714],"type":"Point"}
}