{
  "type": "Feature",
  "properties": {
    "iso:country":"US",
    "sg:address":"4045 Woodbridge Ave",
    "sg:city":"Edison",
    "sg:classifiers":[
        {
            "category":"Professional",
            "subcategory":"Management & Consulting",
            "type":"Services"
        }
    ],
    "sg:phone":"+1 732 738 4919",
    "sg:postcode":"08837",
    "sg:province":"NJ",
    "wof:name":"Fst & Associates",
    "wof:placetype":"venue"
},
  "geometry": {"coordinates":[-74.323301,40.5326],"type":"Point"}
}