{
  "type": "Feature",
  "properties": {
    "addr:full":"30 Hamilton Ave Leonardo NJ 07737",
    "addr:housenumber":"30",
    "addr:postcode":"07737",
    "addr:street":"Hamilton Ave",
    "iso:country":"US",
    "sg:address":"30 Hamilton Ave",
    "sg:city":"Leonardo",
    "sg:classifiers":[
        {
            "category":"Building & Trades",
            "subcategory":"Construction",
            "type":"Services"
        }
    ],
    "sg:phone":"+1 732 872 2949",
    "sg:postcode":"07737",
    "sg:province":"NJ",
    "sg:tags":[
        "house"
    ],
    "wof:name":"CSP Home Improvements LLC",
    "wof:placetype":"venue"
},
  "geometry": {"coordinates":[-74.05496599999999,40.417719],"type":"Point"}
}