{
  "type": "Feature",
  "properties": {
    "iso:country":"US",
    "sg:address":"222 Ridgewood Ave",
    "sg:city":"Bloomfield",
    "sg:classifiers":[
        {
            "category":"Banks & Credit Unions",
            "subcategory":"Bank",
            "type":"Services"
        }
    ],
    "sg:phone":"+1 973 680 3073",
    "sg:postcode":"07003",
    "sg:province":"NJ",
    "sg:website":"www.pnc.com",
    "wof:name":"Pnc Bank",
    "wof:placetype":"venue"
},
  "geometry": {"coordinates":[-74.20513699999999,40.800089],"type":"Point"}
}