{
  "type": "Feature",
  "properties": {
    "iso:country":"US",
    "sg:address":"12 Calt Dr",
    "sg:city":"Hazlet",
    "sg:classifiers":[
        {
            "category":"Building & Trades",
            "subcategory":"Construction",
            "type":"Services"
        }
    ],
    "sg:phone":"+1 732 739 4928",
    "sg:postcode":"07730",
    "sg:province":"NJ",
    "sg:tags":[
        "industrial",
        "general",
        "contractor"
    ],
    "wof:name":"V V S S Co Inc",
    "wof:placetype":"venue"
},
  "geometry": {"coordinates":[-74.17608799999999,40.422937],"type":"Point"}
}