{
  "type": "Feature",
  "properties": {
    "iso:country":"US",
    "sg:address":"147 W Hampton St",
    "sg:city":"Pemberton",
    "sg:classifiers":[
        {
            "category":"Retail",
            "subcategory":"Auto Repair",
            "type":"Services"
        }
    ],
    "sg:phone":"+1   ",
    "sg:postcode":"08068",
    "sg:province":"NJ",
    "sg:tags":[
        "general",
        "supply"
    ],
    "wof:name":"Precision Automotive",
    "wof:placetype":"venue"
},
  "geometry": {"coordinates":[-74.69354199999999,39.967957],"type":"Point"}
}