{
  "type": "Feature",
  "properties": {
    "addr:full":"120 Ashwood Ave Summit NJ 07901",
    "addr:housenumber":"120",
    "addr:postcode":"07901",
    "addr:street":"Ashwood Ave",
    "iso:country":"US",
    "sg:address":"120 Ashwood Ave",
    "sg:city":"Summit",
    "sg:classifiers":[
        {
            "category":"Building & Trades",
            "subcategory":"Construction",
            "type":"Services"
        }
    ],
    "sg:phone":"+1 908 273 3611",
    "sg:postcode":"07901",
    "sg:province":"NJ",
    "sg:tags":[
        "carpentry",
        "carpenter",
        "contractor"
    ],
    "wof:name":"Complete Carpentry LLC",
    "wof:placetype":"venue"
},
  "geometry": {"coordinates":[-74.352538,40.704752],"type":"Point"}
}