{
  "type": "Feature",
  "properties": {
    "iso:country":"US",
    "sg:address":"220 2nd St",
    "sg:city":"Lakewood",
    "sg:classifiers":[
        {
            "category":"Restaurant",
            "type":"Food & Drink"
        }
    ],
    "sg:phone":"+1 732 367 6020",
    "sg:postcode":"08701",
    "sg:province":"NJ",
    "sg:tags":[
        "eating"
    ],
    "wof:name":"Taco's Mexico",
    "wof:placetype":"venue"
},
  "geometry": {"coordinates":[-74.212557,40.092273],"type":"Point"}
}