{
  "type": "Feature",
  "properties": {
    "addr:full":"378 Mercer St Trenton NJ 08690",
    "addr:housenumber":"378",
    "addr:postcode":"08690",
    "addr:street":"Mercer St",
    "iso:country":"US",
    "sg:address":"378 Mercer St",
    "sg:city":"Trenton",
    "sg:classifiers":[
        {
            "category":"Shopping",
            "subcategory":"Computers & Home Electronics",
            "type":"Retail Goods"
        }
    ],
    "sg:phone":"+1 609 631 8590",
    "sg:postcode":"08690",
    "sg:province":"NJ",
    "sg:tags":[
        "equipment",
        "satellite",
        "system"
    ],
    "wof:name":"Ameritech Installation Svc",
    "wof:placetype":"venue"
},
  "geometry": {"coordinates":[-74.652216,40.23577],"type":"Point"}
}