{
  "type": "Feature",
  "properties": {
    "iso:country":"US",
    "sg:address":"7 Anderson Ave",
    "sg:city":"Fairview",
    "sg:classifiers":[
        {
            "category":"Personal",
            "subcategory":"Barber",
            "type":"Services"
        }
    ],
    "sg:phone":"+1 201 943 2912",
    "sg:postcode":"07022",
    "sg:province":"NJ",
    "wof:name":"Tommy's Barber Shop",
    "wof:placetype":"venue"
},
  "geometry": {"coordinates":[-74.000801,40.810398],"type":"Point"}
}