{
  "type": "Feature",
  "properties": {
    "addr:full":"263 Old Army Rd Basking Ridge NJ 07920",
    "addr:housenumber":"263",
    "addr:postcode":"07920",
    "addr:street":"Old Army Rd",
    "iso:country":"US",
    "sg:address":"263 Old Army Rd",
    "sg:city":"Basking Ridge",
    "sg:classifiers":[
        {
            "category":"Professional",
            "subcategory":"Computer Services",
            "type":"Services"
        }
    ],
    "sg:phone":"+1   ",
    "sg:postcode":"07920",
    "sg:province":"NJ",
    "sg:tags":[
        "datum"
    ],
    "wof:name":"Mark Ricciardi",
    "wof:placetype":"venue"
},
  "geometry": {"coordinates":[-74.55309,40.737308],"type":"Point"}
}