{
  "type": "Feature",
  "properties": {
    "iso:country":"US",
    "sg:address":"378 Catherine St",
    "sg:city":"Somerville",
    "sg:classifiers":[
        {
            "category":"Professional",
            "subcategory":"Management & Consulting",
            "type":"Services"
        }
    ],
    "sg:phone":"+1   ",
    "sg:postcode":"08876",
    "sg:province":"NJ",
    "sg:tags":[
        "public",
        "relations"
    ],
    "wof:name":"Fox Group",
    "wof:placetype":"venue"
},
  "geometry": {"coordinates":[-74.604251,40.573215],"type":"Point"}
}