{
  "type": "Feature",
  "properties": {
    "addr:full":"132 Haddon Ave Haddon Township NJ 08108",
    "addr:housenumber":"132",
    "addr:postcode":"08108",
    "addr:street":"Haddon Ave",
    "iso:country":"US",
    "sg:address":"132 Haddon Ave",
    "sg:city":"Haddon Township",
    "sg:classifiers":[
        {
            "category":"Building & Trades",
            "subcategory":"Pest Control",
            "type":"Services"
        }
    ],
    "sg:phone":"+1 856 858 2900",
    "sg:postcode":"08108",
    "sg:province":"NJ",
    "wof:name":"Apex Exterminating Co",
    "wof:placetype":"venue"
},
  "geometry": {"coordinates":[-75.084801,39.921398],"type":"Point"}
}