{
  "type": "Feature",
  "properties": {
    "addr:full":"200 Bridgeton Pike Mantua NJ 08051",
    "addr:housenumber":"200",
    "addr:postcode":"08051",
    "addr:street":"Bridgeton Pike",
    "iso:country":"US",
    "sg:address":"200 Bridgeton Pike",
    "sg:city":"Mantua",
    "sg:classifiers":[
        {
            "category":"Shopping",
            "subcategory":"Pharmacy",
            "type":"Retail Goods"
        }
    ],
    "sg:phone":"+1   ",
    "sg:postcode":"08051",
    "sg:province":"NJ",
    "sg:tags":[
        "drug",
        "store"
    ],
    "wof:name":"Eckerd",
    "wof:placetype":"venue"
},
  "geometry": {"coordinates":[-75.17469800000001,39.791357],"type":"Point"}
}