{
  "type": "Feature",
  "properties": {
    "iso:country":"US",
    "sg:address":"20 Hanes Dr",
    "sg:city":"Wayne",
    "sg:classifiers":[
        {
            "category":"Personal",
            "type":"Services"
        }
    ],
    "sg:phone":"+1 973 696 1279",
    "sg:postcode":"07470",
    "sg:province":"NJ",
    "sg:tags":[
        "mover"
    ],
    "wof:name":"Suddeath Relocation Systems",
    "wof:placetype":"venue"
},
  "geometry": {"coordinates":[-74.245192,40.911436],"type":"Point"}
}