{
  "type": "Feature",
  "properties": {
    "iso:country":"US",
    "sg:address":"90 Sewaren Ave",
    "sg:city":"Sewaren",
    "sg:classifiers":[
        {
            "category":"Building & Trades",
            "subcategory":"Construction",
            "type":"Services"
        }
    ],
    "sg:phone":"+1 732 750 3457",
    "sg:postcode":"07077",
    "sg:province":"NJ",
    "sg:tags":[
        "house"
    ],
    "wof:name":"Titan Home Builders Inc",
    "wof:placetype":"venue"
},
  "geometry": {"coordinates":[-74.26153499999999,40.551991],"type":"Point"}
}