{
  "type": "Feature",
  "properties": {
    "addr:full":"3863 Highway 516 Old Bridge NJ 08857",
    "addr:housenumber":"3863",
    "addr:postcode":"08857",
    "addr:street":"Highway 516",
    "iso:country":"US",
    "sg:address":"3863 Highway 516",
    "sg:city":"Old Bridge",
    "sg:classifiers":[
        {
            "category":"Restaurant",
            "type":"Food & Drink"
        }
    ],
    "sg:menulink":"http://www.allmenus.com/nj/old-bridge/273571-ponte-vecchio/menu/",
    "sg:phone":"+1 732 607 1650",
    "sg:postcode":"08857",
    "sg:province":"NJ",
    "sg:tags":[
        "italian"
    ],
    "wof:name":"Ponte Vecchio",
    "wof:placetype":"venue"
},
  "geometry": {"coordinates":[-74.29687699999999,40.402846],"type":"Point"}
}