{
  "type": "Feature",
  "properties": {
    "iso:country":"US",
    "sg:address":"17 Bridge St",
    "sg:city":"Frenchtown",
    "sg:classifiers":[
        {
            "category":"Shopping",
            "subcategory":"Clothing, Apparel, & Fashions",
            "type":"Retail Goods"
        }
    ],
    "sg:phone":"+1 908 996 9000",
    "sg:postcode":"08825",
    "sg:province":"NJ",
    "sg:tags":[
        "apparel",
        "women's"
    ],
    "sg:website":"http://www.alchemyclothing.com",
    "wof:name":"Alchemy Creative Clothing",
    "wof:placetype":"venue"
},
  "geometry": {"coordinates":[-75.061909,40.526408],"type":"Point"}
}