{
  "type": "Feature",
  "properties": {
    "iso:country":"US",
    "sg:address":"93 E Bay Ave",
    "sg:city":"Manahawkin",
    "sg:classifiers":[
        {
            "category":"Food & Beverages",
            "subcategory":"Groceries & Convenience Stores",
            "type":"Retail Goods"
        }
    ],
    "sg:phone":"+1   ",
    "sg:postcode":"08050",
    "sg:province":"NJ",
    "wof:name":"Bay Avenue Farms LLC",
    "wof:placetype":"venue"
},
  "geometry": {"coordinates":[-74.256224,39.693796],"type":"Point"}
}