{
  "type": "Feature",
  "properties": {
    "addr:full":"76 Carlton Ave Marlton NJ 08053",
    "addr:housenumber":"76",
    "addr:postcode":"08053",
    "addr:street":"Carlton Ave",
    "iso:country":"US",
    "sg:address":"76 Carlton Ave",
    "sg:city":"Marlton",
    "sg:classifiers":[
        {
            "category":"Building & Trades",
            "subcategory":"Construction",
            "type":"Services"
        }
    ],
    "sg:phone":"+1 856 983 9686",
    "sg:postcode":"08053",
    "sg:province":"NJ",
    "sg:tags":[
        "hanging",
        "painter",
        "contractor"
    ],
    "wof:name":"H R Painting Contractors",
    "wof:placetype":"venue"
},
  "geometry": {"coordinates":[-74.89591799999999,39.895278],"type":"Point"}
}