{
  "type": "Feature",
  "properties": {
    "addr:full":"1198 43rd St North Bergen NJ 07047",
    "addr:housenumber":"1198",
    "addr:postcode":"07047",
    "addr:street":"43Rd St",
    "iso:country":"US",
    "sg:address":"1198 43rd St",
    "sg:city":"North Bergen",
    "sg:classifiers":[
        {
            "category":"Professional",
            "subcategory":"Management & Consulting",
            "type":"Services"
        }
    ],
    "sg:phone":"+1 201 902 9488",
    "sg:postcode":"07047",
    "sg:province":"NJ",
    "wof:name":"Alkal Management Inc",
    "wof:placetype":"venue"
},
  "geometry": {"coordinates":[-74.026808,40.779838],"type":"Point"}
}