{
  "type": "Feature",
  "properties": {
    "iso:country":"US",
    "sg:address":"122 Riverbend Dr",
    "sg:city":"North Brunswick",
    "sg:classifiers":[
        {
            "category":"Retail",
            "subcategory":"Repair Shop",
            "type":"Services"
        }
    ],
    "sg:phone":"+1 732 297 5352",
    "sg:postcode":"08902",
    "sg:province":"NJ",
    "sg:tags":[
        "welding"
    ],
    "wof:name":"Fran-Co Inc",
    "wof:placetype":"venue"
},
  "geometry": {"coordinates":[-74.506016,40.454851],"type":"Point"}
}