{
  "type": "Feature",
  "properties": {
    "addr:full":"23 Sturbridge Dr Sicklerville NJ 08081",
    "addr:housenumber":"23",
    "addr:postcode":"08081",
    "addr:street":"Sturbridge Dr",
    "iso:country":"US",
    "sg:address":"23 Sturbridge Dr",
    "sg:city":"Sicklerville",
    "sg:classifiers":[
        {
            "category":"Personal",
            "type":"Services"
        }
    ],
    "sg:phone":"+1   ",
    "sg:postcode":"08081",
    "sg:province":"NJ",
    "wof:name":"Ctcfs",
    "wof:placetype":"venue"
},
  "geometry": {"coordinates":[-74.991423,39.778358],"type":"Point"}
}