{
  "type": "Feature",
  "properties": {
    "addr:full":"395 Franklin St Bloomfield NJ 07003",
    "addr:housenumber":"395",
    "addr:postcode":"07003",
    "addr:street":"Franklin St",
    "iso:country":"US",
    "sg:address":"395 Franklin St",
    "sg:city":"Bloomfield",
    "sg:classifiers":[
        {
            "category":"Professional",
            "subcategory":"Lawyer & Legal Services",
            "type":"Services"
        }
    ],
    "sg:phone":"+1 973 743 2220",
    "sg:postcode":"07003",
    "sg:province":"NJ",
    "sg:tags":[
        "attorney"
    ],
    "wof:name":"Bellizia Law Office",
    "wof:placetype":"venue"
},
  "geometry": {"coordinates":[-74.19519,40.792251],"type":"Point"}
}