{
  "type": "Feature",
  "properties": {
    "iso:country":"US",
    "sg:address":"319 Philadelphia Ave",
    "sg:city":"Egg Harbor City",
    "sg:classifiers":[
        {
            "category":"Personal",
            "subcategory":"Barber",
            "type":"Services"
        }
    ],
    "sg:phone":"+1 609 965 1248",
    "sg:postcode":"08215",
    "sg:province":"NJ",
    "sg:tags":[
        "shop"
    ],
    "wof:name":"Lou's Barber Shop",
    "wof:placetype":"venue"
},
  "geometry": {"coordinates":[-74.64322300000001,39.532586],"type":"Point"}
}