{
  "type": "Feature",
  "properties": {
    "iso:country":"US",
    "sg:address":"16 Wynwood Rd",
    "sg:city":"Chatham",
    "sg:classifiers":[
        {
            "category":"Professional",
            "subcategory":"Management & Consulting",
            "type":"Services"
        }
    ],
    "sg:phone":"+1 973 635 2868",
    "sg:postcode":"07928",
    "sg:province":"NJ",
    "wof:name":"Spear Group The",
    "wof:placetype":"venue"
},
  "geometry": {"coordinates":[-74.407376,40.725446],"type":"Point"}
}