{
  "type": "Feature",
  "properties": {
    "addr:full":"203 Foxboro Dr Glassboro NJ 08028",
    "addr:housenumber":"203",
    "addr:postcode":"08028",
    "addr:street":"Foxboro Dr",
    "iso:country":"US",
    "sg:address":"203 Foxboro Dr",
    "sg:city":"Glassboro",
    "sg:classifiers":[
        {
            "category":"Shopping",
            "subcategory":"Hobbies, Toys, & Games",
            "type":"Retail Goods"
        }
    ],
    "sg:phone":"+1 856 863 2960",
    "sg:postcode":"08028",
    "sg:province":"NJ",
    "sg:tags":[
        "shop",
        "hobby",
        "model",
        "supply"
    ],
    "wof:name":"Box Car Hobbies",
    "wof:placetype":"venue"
},
  "geometry": {"coordinates":[-75.13739200000001,39.710501],"type":"Point"}
}