{
  "type": "Feature",
  "properties": {
    "addr:full":"665 McBride Ave Little Falls NJ 07424",
    "addr:housenumber":"665",
    "addr:postcode":"07424",
    "addr:street":"Mcbride Ave",
    "iso:country":"US",
    "sg:address":"665 McBride Ave",
    "sg:city":"Little Falls",
    "sg:classifiers":[
        {
            "category":"Education",
            "subcategory":"School",
            "type":"Public Place"
        }
    ],
    "sg:phone":"+1   ",
    "sg:postcode":"07424",
    "sg:province":"NJ",
    "sg:tags":[
        "elementary"
    ],
    "wof:name":"Community School",
    "wof:placetype":"venue"
},
  "geometry": {"coordinates":[-74.198987,40.903052],"type":"Point"}
}