{
  "type": "Feature",
  "properties": {
    "addr:full":"2239 US Hwy 9 Old Bridge NJ 08857",
    "addr:housenumber":"2239",
    "addr:postcode":"08857",
    "addr:street":"Us Hwy 9",
    "iso:country":"US",
    "sg:address":"2239 US Hwy 9",
    "sg:city":"Old Bridge",
    "sg:classifiers":[
        {
            "category":"Food & Beverages",
            "subcategory":"Groceries & Convenience Stores",
            "type":"Retail Goods"
        }
    ],
    "sg:phone":"+1 732 727 3533",
    "sg:postcode":"08857",
    "sg:province":"NJ",
    "sg:tags":[
        "grocer"
    ],
    "sg:website":"www.shoprite.com",
    "wof:name":"Shop Rite Supermarket",
    "wof:placetype":"venue"
},
  "geometry": {"coordinates":[-74.30352600000001,40.4269],"type":"Point"}
}