{
  "type": "Feature",
  "properties": {
    "addr:full":"984 Grand St S Hammonton NJ 08037",
    "addr:housenumber":"984",
    "addr:postcode":"08037",
    "addr:street":"Grand St S",
    "iso:country":"US",
    "sg:address":"984 Grand St S",
    "sg:city":"Hammonton",
    "sg:classifiers":[
        {
            "category":"Wholesale",
            "subcategory":"Construction Materials",
            "type":"Manufacturing & Wholesale Goods"
        }
    ],
    "sg:phone":"+1 609 561 4381",
    "sg:postcode":"08037",
    "sg:province":"NJ",
    "sg:tags":[
        "fence"
    ],
    "wof:name":"Jersey Fencing",
    "wof:placetype":"venue"
},
  "geometry": {"coordinates":[-74.79195,39.621521],"type":"Point"}
}