{
  "type": "Feature",
  "properties": {
    "addr:full":"1 Walnut Ave Cranford NJ 07016",
    "addr:housenumber":"1",
    "addr:postcode":"07016",
    "addr:street":"Walnut Ave",
    "iso:country":"US",
    "sg:address":"1 Walnut Ave",
    "sg:city":"Cranford",
    "sg:classifiers":[
        {
            "category":"Restaurant",
            "type":"Food & Drink"
        }
    ],
    "sg:phone":"+1 908 276 6638",
    "sg:postcode":"07016",
    "sg:province":"NJ",
    "sg:tags":[
        "chinese"
    ],
    "wof:name":"1 Walnut Ave",
    "wof:placetype":"venue"
},
  "geometry": {"coordinates":[-74.304528,40.655036],"type":"Point"}
}