{
  "type": "Feature",
  "properties": {
    "addr:full":"1028 Chestnut Ave Woodbury Heights NJ 08097",
    "addr:housenumber":"1028",
    "addr:postcode":"08097",
    "addr:street":"Chestnut Ave",
    "iso:country":"US",
    "sg:address":"1028 Chestnut Ave",
    "sg:city":"Woodbury Heights",
    "sg:classifiers":[
        {
            "category":"Professional",
            "subcategory":"Computer Services",
            "type":"Services"
        }
    ],
    "sg:phone":"+1   ",
    "sg:postcode":"08097",
    "sg:province":"NJ",
    "sg:tags":[
        "datum"
    ],
    "wof:name":"Ron Tomasetti",
    "wof:placetype":"venue"
},
  "geometry": {"coordinates":[-75.138569,39.810055],"type":"Point"}
}