{
  "type": "Feature",
  "properties": {
    "addr:full":"102 Morris Ave Linwood NJ 08221",
    "addr:housenumber":"102",
    "addr:postcode":"08221",
    "addr:street":"Morris Ave",
    "iso:country":"US",
    "sg:address":"102 Morris Ave",
    "sg:city":"Linwood",
    "sg:classifiers":[
        {
            "category":"Professional",
            "subcategory":"Accounting & Tax Preparation",
            "type":"Services"
        }
    ],
    "sg:phone":"+1   ",
    "sg:postcode":"08221",
    "sg:province":"NJ",
    "wof:name":"Richard Crimi CPA",
    "wof:placetype":"venue"
},
  "geometry": {"coordinates":[-74.577504,39.342805],"type":"Point"}
}