{
  "type": "Feature",
  "properties": {
    "iso:country":"US",
    "sg:address":"12 Penny Ln",
    "sg:city":"Bayville",
    "sg:classifiers":[
        {
            "category":"Banks & Credit Unions",
            "subcategory":"Financial Services",
            "type":"Services"
        }
    ],
    "sg:phone":"+1   ",
    "sg:postcode":"08721",
    "sg:province":"NJ",
    "sg:tags":[
        "company",
        "holding"
    ],
    "wof:name":"Nguyen Pham Holding Co LLC",
    "wof:placetype":"venue"
},
  "geometry": {"coordinates":[-74.15843099999999,39.927788],"type":"Point"}
}