{
  "type": "Feature",
  "properties": {
    "addr:full":"1733 John F Kennedy Blvd Jersey City NJ 07305",
    "addr:housenumber":"1733",
    "addr:postcode":"07305",
    "addr:street":"John F Kennedy Blvd",
    "iso:country":"US",
    "sg:address":"1733 John F Kennedy Blvd",
    "sg:city":"Jersey City",
    "sg:classifiers":[
        {
            "category":"Personal",
            "subcategory":"Beauty Salon",
            "type":"Services"
        }
    ],
    "sg:phone":"+1   ",
    "sg:postcode":"07305",
    "sg:province":"NJ",
    "sg:tags":[
        "shop",
        "merchandise"
    ],
    "wof:name":"Majestic Hair Salon",
    "wof:placetype":"venue"
},
  "geometry": {"coordinates":[-74.095184,40.699494],"type":"Point"}
}