{
  "type": "Feature",
  "properties": {
    "iso:country":"US",
    "sg:address":"9 Wildwood Ter",
    "sg:city":"Denville",
    "sg:classifiers":[
        {
            "category":"Building & Trades",
            "subcategory":"Landscaping Services",
            "type":"Services"
        }
    ],
    "sg:phone":"+1 973 625 5024",
    "sg:postcode":"07834",
    "sg:province":"NJ",
    "sg:tags":[
        "tree"
    ],
    "wof:name":"Greeene Tree Removal",
    "wof:placetype":"venue"
},
  "geometry": {"coordinates":[-74.477898,40.903849],"type":"Point"}
}