{
  "type": "Feature",
  "properties": {
    "iso:country":"US",
    "sg:address":"381 Woodside Ave",
    "sg:city":"Newark",
    "sg:classifiers":[
        {
            "category":"Education",
            "subcategory":"School",
            "type":"Public Place"
        }
    ],
    "sg:phone":"+1   ",
    "sg:postcode":"07104",
    "sg:province":"NJ",
    "wof:name":"Ridge Street Annex School",
    "wof:placetype":"venue"
},
  "geometry": {"coordinates":[-74.16201,40.779932],"type":"Point"}
}