{
  "type": "Feature",
  "properties": {
    "iso:country":"US",
    "sg:address":"231 Closter Dock Rd",
    "sg:city":"Closter",
    "sg:classifiers":[
        {
            "category":"Education",
            "subcategory":"School",
            "type":"Public Place"
        },
        {
            "category":"Education",
            "subcategory":"Special Training",
            "type":"Public Place"
        }
    ],
    "sg:phone":"+1 201 750 8510",
    "sg:postcode":"07624",
    "sg:province":"NJ",
    "sg:tags":[
        "academic"
    ],
    "wof:name":"Progress Advanced Learning Ctr",
    "wof:placetype":"venue"
},
  "geometry": {"coordinates":[-73.96184100000001,40.973211],"type":"Point"}
}