{
  "type": "Feature",
  "properties": {
    "addr:full":"19 Lafayette Ct Barnegat NJ 08005",
    "addr:housenumber":"19",
    "addr:postcode":"08005",
    "addr:street":"Lafayette Ct",
    "iso:country":"US",
    "sg:address":"19 Lafayette Ct",
    "sg:city":"Barnegat",
    "sg:classifiers":[
        {
            "category":"Professional",
            "subcategory":"Computer Services",
            "type":"Services"
        }
    ],
    "sg:phone":"+1 609 660 0083",
    "sg:postcode":"08005",
    "sg:province":"NJ",
    "sg:tags":[
        "related"
    ],
    "wof:name":"Computer Cnsltion Insul Spport",
    "wof:placetype":"venue"
},
  "geometry": {"coordinates":[-74.25164100000001,39.765881],"type":"Point"}
}