{
  "type": "Feature",
  "properties": {
    "addr:full":"100 State Rte 36 West Long Branch NJ 07764",
    "addr:housenumber":"100",
    "addr:postcode":"07764",
    "addr:street":"State Rte 36 West",
    "iso:country":"US",
    "sg:address":"100 State Rte 36",
    "sg:city":"West Long Branch",
    "sg:classifiers":[
        {
            "category":"Professional",
            "subcategory":"Management & Consulting",
            "type":"Services"
        }
    ],
    "sg:phone":"+1 732 483 0111",
    "sg:postcode":"07764",
    "sg:province":"NJ",
    "sg:tags":[
        "consultant",
        "voice",
        "datum",
        "telecommunication"
    ],
    "sg:website":"www.fortuneconsulting.com",
    "wof:name":"Fortune Consulting",
    "wof:placetype":"venue"
},
  "geometry": {"coordinates":[-74.019414,40.301504],"type":"Point"}
}