{
  "type": "Feature",
  "properties": {
    "iso:country":"US",
    "sg:address":"55 Main St",
    "sg:city":"Bloomingdale",
    "sg:classifiers":[
        {
            "category":"Retail",
            "subcategory":"Repair Shop",
            "type":"Services"
        }
    ],
    "sg:phone":"+1 973 838 4600",
    "sg:postcode":"07403",
    "sg:province":"NJ",
    "sg:tags":[
        "television",
        "radio"
    ],
    "wof:name":"Courtesy TV Sales & Svc",
    "wof:placetype":"venue"
},
  "geometry": {"coordinates":[-74.32863999999999,41.002478],"type":"Point"}
}