{
  "type": "Feature",
  "properties": {
    "addr:full":"797 State Rte 37 Toms River NJ 08755",
    "addr:housenumber":"797",
    "addr:postcode":"08755",
    "addr:street":"State Rte 37",
    "iso:country":"US",
    "sg:address":"797 State Rte 37",
    "sg:city":"Toms River",
    "sg:classifiers":[
        {
            "category":"Building & Trades",
            "subcategory":"Landscaping Services",
            "type":"Services"
        }
    ],
    "sg:phone":"+1 732 240 5592",
    "sg:postcode":"08755",
    "sg:province":"NJ",
    "wof:name":"Shore Design Ldscpg & Grdn Ctr",
    "wof:placetype":"venue"
},
  "geometry": {"coordinates":[-74.234714,39.970462],"type":"Point"}
}