{
  "type": "Feature",
  "properties": {
    "addr:full":"9 Aldon Ter Bloomfield NJ 07003",
    "addr:housenumber":"9",
    "addr:postcode":"07003",
    "addr:street":"Aldon Ter",
    "iso:country":"US",
    "sg:address":"9 Aldon Ter",
    "sg:city":"Bloomfield",
    "sg:classifiers":[
        {
            "category":"Professional",
            "subcategory":"Engineering",
            "type":"Services"
        }
    ],
    "sg:phone":"+1   ",
    "sg:postcode":"07003",
    "sg:province":"NJ",
    "wof:name":"Selinger Carl Services",
    "wof:placetype":"venue"
},
  "geometry": {"coordinates":[-74.185039,40.83115],"type":"Point"}
}