{
  "type": "Feature",
  "properties": {
    "iso:country":"US",
    "sg:address":"10 W Hanover Ave",
    "sg:city":"Randolph",
    "sg:classifiers":[
        {
            "category":"Banks & Credit Unions",
            "subcategory":"Investment Brokerage",
            "type":"Services"
        },
        {
            "category":"Professional",
            "subcategory":"Management & Consulting",
            "type":"Services"
        }
    ],
    "sg:phone":"+1 973 895 1133",
    "sg:postcode":"07869",
    "sg:province":"NJ",
    "sg:tags":[
        "consultant",
        "planning",
        "financial"
    ],
    "wof:name":"Money At Work LLC",
    "wof:placetype":"venue"
},
  "geometry": {"coordinates":[-74.56797400000001,40.826694],"type":"Point"}
}