{
  "type": "Feature",
  "properties": {
    "iso:country":"US",
    "sg:address":"578 Valley Rd",
    "sg:city":"Wayne",
    "sg:classifiers":[
        {
            "category":"Shopping",
            "subcategory":"Pharmacy",
            "type":"Retail Goods"
        }
    ],
    "sg:phone":"+1 973 694 5522",
    "sg:postcode":"07470",
    "sg:province":"NJ",
    "wof:name":"Plains Pharmacy",
    "wof:placetype":"venue"
},
  "geometry": {"coordinates":[-74.227935,40.930331],"type":"Point"}
}