{
  "type": "Feature",
  "properties": {
    "iso:country":"US",
    "sg:address":"20 Oak Dr",
    "sg:city":"Chatham",
    "sg:classifiers":[
        {
            "category":"Organizations",
            "subcategory":"Religious Organization",
            "type":"Services"
        }
    ],
    "sg:phone":"+1   ",
    "sg:postcode":"07928",
    "sg:province":"NJ",
    "wof:name":"Galen L Goodwin Rev",
    "wof:placetype":"venue"
},
  "geometry": {"coordinates":[-74.39423499999999,40.734422],"type":"Point"}
}