{
  "type": "Feature",
  "properties": {
    "iso:country":"US",
    "sg:address":"424 Park Ave",
    "sg:city":"East Orange",
    "sg:classifiers":[
        {
            "category":"Food & Beverages",
            "subcategory":"Groceries & Convenience Stores",
            "type":"Retail Goods"
        }
    ],
    "sg:phone":"+1 973 673 5720",
    "sg:postcode":"07017",
    "sg:province":"NJ",
    "sg:tags":[
        "market"
    ],
    "wof:name":"F & S Caribbean Market",
    "wof:placetype":"venue"
},
  "geometry": {"coordinates":[-74.21207099999999,40.770064],"type":"Point"}
}