{
  "type": "Feature",
  "properties": {
    "iso:country":"US",
    "sg:address":"206 Hanover St",
    "sg:city":"Pemberton",
    "sg:classifiers":[
        {
            "category":"Autos & Motor Vehicles",
            "subcategory":"Fuel & Gas Station",
            "type":"Retail Goods"
        }
    ],
    "sg:phone":"+1   ",
    "sg:postcode":"08068",
    "sg:province":"NJ",
    "sg:tags":[
        "station",
        "gasoline"
    ],
    "wof:name":"Ms Gas Station",
    "wof:placetype":"venue"
},
  "geometry": {"coordinates":[-74.68502700000001,39.967347],"type":"Point"}
}