{
  "type": "Feature",
  "properties": {
    "addr:full":"28 Ward Ave Rumson NJ 07760",
    "addr:housenumber":"28",
    "addr:postcode":"07760",
    "addr:street":"Ward Ave",
    "iso:country":"US",
    "sg:address":"28 Ward Ave",
    "sg:city":"Rumson",
    "sg:classifiers":[
        {
            "category":"Professional",
            "type":"Services"
        }
    ],
    "sg:phone":"+1 732 450 2201",
    "sg:postcode":"07760",
    "sg:province":"NJ",
    "sg:tags":[
        "establishment"
    ],
    "wof:name":"Aire-Ride Transfer Inc",
    "wof:placetype":"venue"
},
  "geometry": {"coordinates":[-73.980271,40.368178],"type":"Point"}
}