{
  "type": "Feature",
  "properties": {
    "addr:full":"263 Springfield Ave Newark NJ 07103",
    "addr:housenumber":"263",
    "addr:postcode":"07103",
    "addr:street":"Springfield Ave",
    "iso:country":"US",
    "sg:address":"263 Springfield Ave",
    "sg:city":"Newark",
    "sg:classifiers":[
        {
            "category":"Food & Beverages",
            "subcategory":"Liquor & Beverages",
            "type":"Retail Goods"
        }
    ],
    "sg:phone":"+1 973 642 8181",
    "sg:postcode":"07103",
    "sg:province":"NJ",
    "sg:tags":[
        "beer",
        "wine",
        "spirit",
        "alcoholic"
    ],
    "wof:name":"New Silver Key-Liquor No 2",
    "wof:placetype":"venue"
},
  "geometry": {"coordinates":[-74.190201,40.7341],"type":"Point"}
}