{
  "type": "Feature",
  "properties": {
    "addr:full":"1355 Lakeshore Dr Camden NJ 08104",
    "addr:housenumber":"1355",
    "addr:postcode":"08104",
    "addr:street":"Lakeshore Dr",
    "iso:country":"US",
    "sg:address":"1355 Lakeshore Dr",
    "sg:city":"Camden",
    "sg:classifiers":[
        {
            "category":"Banks & Credit Unions",
            "subcategory":"Investment Brokerage",
            "type":"Services"
        },
        {
            "category":"Banks & Credit Unions",
            "subcategory":"Financial Services",
            "type":"Services"
        }
    ],
    "sg:phone":"+1 856 757 0322",
    "sg:postcode":"08104",
    "sg:province":"NJ",
    "sg:tags":[
        "advisory",
        "management",
        "planner"
    ],
    "wof:name":"Dbg Gamma Investments",
    "wof:placetype":"venue"
},
  "geometry": {"coordinates":[-75.101131,39.913689],"type":"Point"}
}