{
  "type": "Feature",
  "properties": {
    "addr:full":"106 Baker Blvd Marlton NJ 08053",
    "addr:housenumber":"106",
    "addr:postcode":"08053",
    "addr:street":"Baker Blvd",
    "iso:country":"US",
    "sg:address":"106 Baker Blvd",
    "sg:city":"Marlton",
    "sg:classifiers":[
        {
            "category":"Building & Trades",
            "subcategory":"Construction",
            "type":"Services"
        }
    ],
    "sg:phone":"+1 856 596 7780",
    "sg:postcode":"08053",
    "sg:province":"NJ",
    "sg:tags":[
        "resurfacing",
        "laying",
        "refinishing",
        "floor"
    ],
    "wof:name":"Detailed Floor Finishing",
    "wof:placetype":"venue"
},
  "geometry": {"coordinates":[-74.926367,39.899794],"type":"Point"}
}