{
  "type": "Feature",
  "properties": {
    "addr:full":"2100 Old Marlton Pike E Marlton NJ 08053",
    "addr:housenumber":"2100",
    "addr:postcode":"08053",
    "addr:street":"Old Marlton Pike",
    "iso:country":"US",
    "sg:address":"2100 Old Marlton Pike E",
    "sg:city":"Marlton",
    "sg:classifiers":[
        {
            "category":"Shopping",
            "subcategory":"Gifts & Souvenirs",
            "type":"Retail Goods"
        }
    ],
    "sg:phone":"+1   ",
    "sg:postcode":"08053",
    "sg:province":"NJ",
    "wof:name":"Patricias Touch of Crafts",
    "wof:placetype":"venue"
},
  "geometry": {"coordinates":[-74.87163700000001,39.890513],"type":"Point"}
}