{
  "type": "Feature",
  "properties": {
    "addr:full":"24 Canterbury Ct Old Bridge NJ 08857",
    "addr:housenumber":"24",
    "addr:postcode":"08857",
    "addr:street":"Canterbury Ct",
    "iso:country":"US",
    "sg:address":"24 Canterbury Ct",
    "sg:city":"Old Bridge",
    "sg:classifiers":[
        {
            "category":"Professional",
            "subcategory":"Business Services",
            "type":"Services"
        }
    ],
    "sg:phone":"+1   ",
    "sg:postcode":"08857",
    "sg:province":"NJ",
    "wof:name":"Shree Zee Group Inc",
    "wof:placetype":"venue"
},
  "geometry": {"coordinates":[-74.295635,40.398052],"type":"Point"}
}