{
  "type": "Feature",
  "properties": {
    "iso:country":"US",
    "sg:address":"19 Willow Ter",
    "sg:city":"Verona",
    "sg:classifiers":[
        {
            "category":"Building & Trades",
            "subcategory":"Construction",
            "type":"Services"
        }
    ],
    "sg:phone":"+1 973 857 1297",
    "sg:postcode":"07044",
    "sg:province":"NJ",
    "sg:tags":[
        "contractor"
    ],
    "wof:name":"Hamilton Contracting Co",
    "wof:placetype":"venue"
},
  "geometry": {"coordinates":[-74.239378,40.839778],"type":"Point"}
}