{
  "type": "Feature",
  "properties": {
    "addr:full":"130 Ryerson Ave Wayne NJ 07470",
    "addr:housenumber":"130",
    "addr:postcode":"07470",
    "addr:street":"Ryerson Ave",
    "iso:country":"US",
    "sg:address":"130 Ryerson Ave",
    "sg:city":"Wayne",
    "sg:classifiers":[
        {
            "category":"Manufacturing",
            "subcategory":"Paper Products",
            "type":"Manufacturing & Wholesale Goods"
        },
        {
            "category":"Wholesale",
            "subcategory":"Chemicals & Plastics",
            "type":"Manufacturing & Wholesale Goods"
        }
    ],
    "sg:phone":"+1 973 872 1004",
    "sg:postcode":"07470",
    "sg:province":"NJ",
    "sg:tags":[
        "bag"
    ],
    "wof:name":"Big Apple Bag Co",
    "wof:placetype":"venue"
},
  "geometry": {"coordinates":[-74.275994,40.925619],"type":"Point"}
}