{
  "type": "Feature",
  "properties": {
    "iso:country":"US",
    "sg:address":"157 Chestnut St",
    "sg:city":"Newark",
    "sg:classifiers":[
        {
            "category":"Building & Trades",
            "subcategory":"Construction",
            "type":"Services"
        }
    ],
    "sg:phone":"+1 973 589 7647",
    "sg:postcode":"07105",
    "sg:province":"NJ",
    "sg:tags":[
        "contractor"
    ],
    "wof:name":"Smm Roofing & Siding Construct",
    "wof:placetype":"venue"
},
  "geometry": {"coordinates":[-74.16794,40.724272],"type":"Point"}
}