{
  "type": "Feature",
  "properties": {
    "iso:country":"US",
    "sg:address":"357 Broad St Ste 2",
    "sg:city":"Bloomfield",
    "sg:classifiers":[
        {
            "category":"Arts & Performance",
            "subcategory":"Arts Center",
            "type":"Entertainment"
        }
    ],
    "sg:phone":"+1 973 748 2787",
    "sg:postcode":"07003",
    "sg:province":"NJ",
    "sg:tags":[
        "performing"
    ],
    "sg:website":"www.broadwayperformingarts.net",
    "wof:name":"Broadway Performing Arts",
    "wof:placetype":"venue"
},
  "geometry": {"coordinates":[-74.193426,40.805317],"type":"Point"}
}