{
  "type": "Feature",
  "properties": {
    "iso:country":"US",
    "sg:address":"4 Ross Ave",
    "sg:city":"Edison",
    "sg:classifiers":[
        {
            "category":"Organizations",
            "subcategory":"Community Association",
            "type":"Services"
        }
    ],
    "sg:phone":"+1 732 603 0109",
    "sg:postcode":"08820",
    "sg:province":"NJ",
    "wof:name":"Kiwanis International",
    "wof:placetype":"venue"
},
  "geometry": {"coordinates":[-74.355751,40.555255],"type":"Point"}
}