{
  "type": "Feature",
  "properties": {
    "iso:country":"US",
    "sg:address":"533 Kings Hwy",
    "sg:city":"Moorestown",
    "sg:classifiers":[
        {
            "category":"Organizations",
            "subcategory":"Religious Organization",
            "type":"Services"
        }
    ],
    "sg:phone":"+1   ",
    "sg:postcode":"08057",
    "sg:province":"NJ",
    "wof:name":"First United Methodist Church",
    "wof:placetype":"venue"
},
  "geometry": {"coordinates":[-74.96451999999999,39.956317],"type":"Point"}
}