{
  "type": "Feature",
  "properties": {
    "iso:country":"US",
    "sg:address":"105 S Chelsea Ave",
    "sg:city":"Atlantic City",
    "sg:classifiers":[
        {
            "category":"Restaurant",
            "type":"Food & Drink"
        }
    ],
    "sg:phone":"+1 609 344 6053",
    "sg:postcode":"08401",
    "sg:province":"NJ",
    "sg:tags":[
        "banquet",
        "rooms"
    ],
    "sg:website":"www.hojoboardwalk.com",
    "wof:name":"Crystal Ballroom",
    "wof:placetype":"venue"
},
  "geometry": {"coordinates":[-74.447142,39.351218],"type":"Point"}
}