{
  "type": "Feature",
  "properties": {
    "addr:full":"46 E Main St Bergenfield NJ 07621",
    "addr:housenumber":"46",
    "addr:postcode":"07621",
    "addr:street":"E Main St",
    "iso:country":"US",
    "sg:address":"46 E Main St",
    "sg:city":"Bergenfield",
    "sg:classifiers":[
        {
            "category":"Personal",
            "subcategory":"Beauty Salon",
            "type":"Services"
        }
    ],
    "sg:phone":"+1 201 439 0661",
    "sg:postcode":"07621",
    "sg:province":"NJ",
    "sg:tags":[
        "shop"
    ],
    "wof:name":"Ann Unisex Salon",
    "wof:placetype":"venue"
},
  "geometry": {"coordinates":[-73.99368,40.927899],"type":"Point"}
}