{
  "type": "Feature",
  "properties": {
    "iso:country":"US",
    "sg:address":"3580 US Hwy 9",
    "sg:city":"Freehold",
    "sg:classifiers":[
        {
            "category":"Retail",
            "subcategory":"Auto Repair",
            "type":"Services"
        }
    ],
    "sg:phone":"+1 732 462 6314",
    "sg:postcode":"07728",
    "sg:province":"NJ",
    "sg:tags":[
        "repairing",
        "automobile"
    ],
    "wof:name":"Bob's Automotive",
    "wof:placetype":"venue"
},
  "geometry": {"coordinates":[-74.27474100000001,40.238314],"type":"Point"}
}