{
  "type": "Feature",
  "properties": {
    "iso:country":"US",
    "sg:address":"110 Acadia Dr",
    "sg:city":"Riverton",
    "sg:classifiers":[
        {
            "category":"Building & Trades",
            "subcategory":"Construction",
            "type":"Services"
        }
    ],
    "sg:phone":"+1 856 303 1888",
    "sg:postcode":"08077",
    "sg:province":"NJ",
    "sg:tags":[
        "contractor"
    ],
    "wof:name":"Scott Brooks",
    "wof:placetype":"venue"
},
  "geometry": {"coordinates":[-74.999628,39.977955],"type":"Point"}
}