{
  "type": "Feature",
  "properties": {
    "addr:full":"130 Cable Ave Beachwood NJ 08722",
    "addr:housenumber":"130",
    "addr:postcode":"08722",
    "addr:street":"Cable Ave",
    "iso:country":"US",
    "sg:address":"130 Cable Ave",
    "sg:city":"Beachwood",
    "sg:classifiers":[
        {
            "category":"Organizations",
            "subcategory":"Religious Organization",
            "type":"Services"
        }
    ],
    "sg:phone":"+1 732 349 0871",
    "sg:postcode":"08722",
    "sg:province":"NJ",
    "sg:website":"www.stpaul-lutheranchurch.com",
    "wof:name":"St Paul Lutheran Church",
    "wof:placetype":"venue"
},
  "geometry": {"coordinates":[-74.189059,39.93768],"type":"Point"}
}