{
  "type": "Feature",
  "properties": {
    "iso:country":"US",
    "sg:address":"65 Ocean Ave",
    "sg:city":"Long Branch",
    "sg:classifiers":[
        {
            "category":"Restaurant",
            "type":"Food & Drink"
        }
    ],
    "sg:phone":"+1 732 229 1222",
    "sg:postcode":"07740",
    "sg:province":"NJ",
    "sg:tags":[
        "parlor",
        "ice",
        "cream"
    ],
    "wof:name":"Lighthouse",
    "wof:placetype":"venue"
},
  "geometry": {"coordinates":[-73.97852,40.301973],"type":"Point"}
}