{
  "type": "Feature",
  "properties": {
    "iso:country":"US",
    "sg:address":"247 N Broadway",
    "sg:city":"Pennsville",
    "sg:classifiers":[
        {
            "category":"Cinema",
            "subcategory":"Movie Rental",
            "type":"Entertainment"
        }
    ],
    "sg:phone":"+1 856 678 4747",
    "sg:postcode":"08070",
    "sg:province":"NJ",
    "sg:tags":[
        "leasing",
        "video",
        "disc",
        "tape"
    ],
    "wof:name":"Blockbuster Video",
    "wof:placetype":"venue"
},
  "geometry": {"coordinates":[-75.50551,39.669517],"type":"Point"}
}