{
  "type": "Feature",
  "properties": {
    "addr:full":"345 High St Burlington NJ 08016",
    "addr:housenumber":"345",
    "addr:postcode":"08016",
    "addr:street":"High St",
    "iso:country":"US",
    "sg:address":"345 High St",
    "sg:city":"Burlington",
    "sg:classifiers":[
        {
            "category":"Restaurant",
            "type":"Food & Drink"
        }
    ],
    "sg:phone":"+1 609 239 0027",
    "sg:postcode":"08016",
    "sg:province":"NJ",
    "sg:tags":[
        "cajun/creole"
    ],
    "wof:name":"Taste It Creole Cuisine",
    "wof:placetype":"venue"
},
  "geometry": {"coordinates":[-74.85794300000001,40.078392],"type":"Point"}
}