{
  "type": "Feature",
  "properties": {
    "addr:full":"31 Bay Ave Atlantic Highlands NJ 07716",
    "addr:housenumber":"31",
    "addr:postcode":"07716",
    "addr:street":"Bay Ave",
    "iso:country":"US",
    "sg:address":"31 Bay Ave",
    "sg:city":"Atlantic Highlands",
    "sg:classifiers":[
        {
            "category":"Manufacturing",
            "subcategory":"Printing",
            "type":"Manufacturing & Wholesale Goods"
        }
    ],
    "sg:phone":"+1 732 872 9045",
    "sg:postcode":"07716",
    "sg:province":"NJ",
    "sg:tags":[
        "book"
    ],
    "wof:name":"John G Warho PHD",
    "wof:placetype":"venue"
},
  "geometry": {"coordinates":[-74.03771999999999,40.415059],"type":"Point"}
}