{
  "type": "Feature",
  "properties": {
    "addr:full":"1411 New York Ave Union City NJ 07087",
    "addr:housenumber":"1411",
    "addr:postcode":"07087",
    "addr:street":"New York Ave",
    "iso:country":"US",
    "sg:address":"1411 New York Ave",
    "sg:city":"Union City",
    "sg:classifiers":[
        {
            "category":"Personal",
            "subcategory":"Beauty Salon",
            "type":"Services"
        }
    ],
    "sg:phone":"+1 201 422 0838",
    "sg:postcode":"07087",
    "sg:province":"NJ",
    "sg:tags":[
        "shop"
    ],
    "wof:name":"Lupe Beauty Salon Unisex",
    "wof:placetype":"venue"
},
  "geometry": {"coordinates":[-74.035129,40.761098],"type":"Point"}
}