{
  "type": "Feature",
  "properties": {
    "iso:country":"US",
    "sg:address":"409 Main Ave",
    "sg:city":"Wood-Ridge",
    "sg:classifiers":[
        {
            "category":"Building & Trades",
            "subcategory":"Construction",
            "type":"Services"
        }
    ],
    "sg:phone":"+1 201 460 7148",
    "sg:postcode":"07075",
    "sg:province":"NJ",
    "sg:tags":[
        "contractor"
    ],
    "wof:name":"John Peck Tile",
    "wof:placetype":"venue"
},
  "geometry": {"coordinates":[-74.088554,40.847417],"type":"Point"}
}