{
  "type": "Feature",
  "properties": {
    "iso:country":"US",
    "sg:address":"151 Knollcroft Rd",
    "sg:city":"Lyons",
    "sg:classifiers":[
        {
            "category":"Sports & Exercise",
            "subcategory":"Golf",
            "type":"Entertainment"
        }
    ],
    "sg:phone":"+1   ",
    "sg:postcode":"07939",
    "sg:province":"NJ",
    "sg:tags":[
        "course"
    ],
    "wof:name":"Coakley Russo Mem Golf Crse",
    "wof:placetype":"venue"
},
  "geometry": {"coordinates":[-74.554253,40.665578],"type":"Point"}
}