{
  "type": "Feature",
  "properties": {
    "iso:country":"US",
    "sg:address":"375 Paterson Ave",
    "sg:city":"Wallington",
    "sg:classifiers":[
        {
            "category":"Building & Trades",
            "subcategory":"Locksmith",
            "type":"Services"
        }
    ],
    "sg:phone":"+1 877 898 9181",
    "sg:postcode":"07057",
    "sg:province":"NJ",
    "sg:tags":[
        "key"
    ],
    "wof:name":"Always Affective Available Emergency Locksmith",
    "wof:placetype":"venue"
},
  "geometry": {"coordinates":[-74.10750400000001,40.844447],"type":"Point"}
}