{
  "type": "Feature",
  "properties": {
    "addr:full":"3250 Dune Dr Avalon NJ 08202",
    "addr:housenumber":"3250",
    "addr:postcode":"08202",
    "addr:street":"Dune Dr",
    "iso:country":"US",
    "sg:address":"3250 Dune Dr",
    "sg:city":"Avalon",
    "sg:classifiers":[
        {
            "category":"Health Services",
            "subcategory":"Hospital",
            "type":"Services"
        }
    ],
    "sg:phone":"+1 609 967 8020",
    "sg:postcode":"08202",
    "sg:province":"NJ",
    "wof:name":"Shore Memorial Hospital",
    "wof:placetype":"venue"
},
  "geometry": {"coordinates":[-74.724238,39.094288],"type":"Point"}
}