{
  "type": "Feature",
  "properties": {
    "addr:full":"264 Billings Ave Paulsboro NJ 08066",
    "addr:housenumber":"264",
    "addr:postcode":"08066",
    "addr:street":"Billings Ave",
    "iso:country":"US",
    "sg:address":"264 Billings Ave",
    "sg:city":"Paulsboro",
    "sg:classifiers":[
        {
            "category":"Organizations",
            "subcategory":"Community Association",
            "type":"Services"
        }
    ],
    "sg:phone":"+1 856 423 0615",
    "sg:postcode":"08066",
    "sg:province":"NJ",
    "wof:name":"American Legion",
    "wof:placetype":"venue"
},
  "geometry": {"coordinates":[-75.240771,39.847386],"type":"Point"}
}