{
  "type": "Feature",
  "properties": {
    "addr:full":"402 Overlook Dr Neptune NJ 07753",
    "addr:housenumber":"402",
    "addr:postcode":"07753",
    "addr:street":"Overlook Dr",
    "iso:country":"US",
    "sg:address":"402 Overlook Dr",
    "sg:city":"Neptune",
    "sg:classifiers":[
        {
            "category":"Professional",
            "type":"Services"
        }
    ],
    "sg:phone":"+1   ",
    "sg:postcode":"07753",
    "sg:province":"NJ",
    "wof:name":"Flyfishingruven Products",
    "wof:placetype":"venue"
},
  "geometry": {"coordinates":[-74.05216299999999,40.198436],"type":"Point"}
}