{
  "type": "Feature",
  "properties": {
    "iso:country":"US",
    "sg:address":"483 State Rte 17",
    "sg:city":"Paramus",
    "sg:classifiers":[
        {
            "category":"Home & Garden",
            "subcategory":"Carpets & Floor Coverings",
            "type":"Retail Goods"
        }
    ],
    "sg:phone":"+1 201 261 8848",
    "sg:postcode":"07652",
    "sg:province":"NJ",
    "sg:tags":[
        "material"
    ],
    "wof:name":"Flooring America",
    "wof:placetype":"venue"
},
  "geometry": {"coordinates":[-74.073195,40.95405],"type":"Point"}
}