{
  "type": "Feature",
  "properties": {
    "iso:country":"US",
    "sg:address":"32 W Demarest Ave",
    "sg:city":"Englewood",
    "sg:classifiers":[
        {
            "category":"Utilities",
            "subcategory":"Mobile Phone",
            "type":"Services"
        }
    ],
    "sg:phone":"+1 201 503 0707",
    "sg:postcode":"07631",
    "sg:province":"NJ",
    "sg:tags":[
        "telephone",
        "cellular"
    ],
    "wof:name":"ONG Wireless",
    "wof:placetype":"venue"
},
  "geometry": {"coordinates":[-73.974204,40.898254],"type":"Point"}
}