{
  "type": "Feature",
  "properties": {
    "addr:full":"147 Oxford Rd Colonia NJ 07067",
    "addr:housenumber":"147",
    "addr:postcode":"07067",
    "addr:street":"Oxford Rd",
    "iso:country":"US",
    "sg:address":"147 Oxford Rd",
    "sg:city":"Colonia",
    "sg:classifiers":[
        {
            "category":"Professional",
            "subcategory":"Business Services",
            "type":"Services"
        }
    ],
    "sg:phone":"+1 732 382 1813",
    "sg:postcode":"07067",
    "sg:province":"NJ",
    "sg:tags":[
        "electrical",
        "contractor"
    ],
    "wof:name":"Pace Consult",
    "wof:placetype":"venue"
},
  "geometry": {"coordinates":[-74.33180299999999,40.605776],"type":"Point"}
}