{
  "type": "Feature",
  "properties": {
    "addr:full":"227 Grand Ave Leonia NJ 07605",
    "addr:housenumber":"227",
    "addr:postcode":"07605",
    "addr:street":"Grand Ave",
    "iso:country":"US",
    "sg:address":"227 Grand Ave",
    "sg:city":"Leonia",
    "sg:classifiers":[
        {
            "category":"Shopping",
            "subcategory":"Clothing, Apparel, & Fashions",
            "type":"Retail Goods"
        }
    ],
    "sg:phone":"+1 201 585 2522",
    "sg:postcode":"07605",
    "sg:province":"NJ",
    "sg:tags":[
        "tailor"
    ],
    "wof:name":"J M Tailoring",
    "wof:placetype":"venue"
},
  "geometry": {"coordinates":[-73.994366,40.86185],"type":"Point"}
}