{
  "type": "Feature",
  "properties": {
    "iso:country":"US",
    "sg:address":"529 Dowd Ave",
    "sg:city":"Elizabeth",
    "sg:classifiers":[
        {
            "category":"Wholesale",
            "subcategory":"Durable Goods & Equipment",
            "type":"Manufacturing & Wholesale Goods"
        }
    ],
    "sg:phone":"+1 908 756 6222",
    "sg:postcode":"07201",
    "sg:province":"NJ",
    "sg:tags":[
        "importer"
    ],
    "sg:website":"www.martecintl.com",
    "wof:name":"Martec International",
    "wof:placetype":"venue"
},
  "geometry": {"coordinates":[-74.187619,40.666753],"type":"Point"}
}