{
  "type": "Feature",
  "properties": {
    "addr:full":"503 Franklin Ave South Plainfield NJ 07080",
    "addr:housenumber":"503",
    "addr:postcode":"07080",
    "addr:street":"Franklin Ave",
    "iso:country":"US",
    "sg:address":"503 Franklin Ave",
    "sg:city":"South Plainfield",
    "sg:classifiers":[
        {
            "category":"Building & Trades",
            "subcategory":"Landscaping Services",
            "type":"Services"
        }
    ],
    "sg:phone":"+1 908 561 4416",
    "sg:postcode":"07080",
    "sg:province":"NJ",
    "sg:tags":[
        "landscape"
    ],
    "wof:name":"Right Touch Landscapes Inc",
    "wof:placetype":"venue"
},
  "geometry": {"coordinates":[-74.424722,40.591539],"type":"Point"}
}