{
  "type": "Feature",
  "properties": {
    "iso:country":"US",
    "sg:address":"5 Lee Ct",
    "sg:city":"Maplewood",
    "sg:classifiers":[
        {
            "category":"Wholesale",
            "subcategory":"Drugs",
            "type":"Manufacturing & Wholesale Goods"
        },
        {
            "category":"Personal",
            "type":"Services"
        }
    ],
    "sg:phone":"+1 973 761 5142",
    "sg:postcode":"07040",
    "sg:province":"NJ",
    "sg:tags":[
        "food",
        "control",
        "weight"
    ],
    "wof:name":"Herbalife Distributors",
    "wof:placetype":"venue"
},
  "geometry": {"coordinates":[-74.253338,40.721967],"type":"Point"}
}