{
  "type": "Feature",
  "properties": {
    "iso:country":"US",
    "sg:address":"223 Parker Ave",
    "sg:city":"Clifton",
    "sg:classifiers":[
        {
            "category":"Health Services",
            "subcategory":"Podiatrist",
            "type":"Services"
        }
    ],
    "sg:phone":"+1 973 478 9149",
    "sg:postcode":"07011",
    "sg:province":"NJ",
    "wof:name":"Frank S Rogalski DPM",
    "wof:placetype":"venue"
},
  "geometry": {"coordinates":[-74.123594,40.875367],"type":"Point"}
}