{
  "type": "Feature",
  "properties": {
    "addr:full":"1000 Morris Ave Union NJ 07083",
    "addr:housenumber":"1000",
    "addr:postcode":"07083",
    "addr:street":"Morris Ave",
    "iso:country":"US",
    "sg:address":"1000 Morris Ave",
    "sg:city":"Union",
    "sg:classifiers":[
        {
            "category":"Wholesale",
            "subcategory":"Vending Machines",
            "type":"Manufacturing & Wholesale Goods"
        }
    ],
    "sg:phone":"+1   ",
    "sg:postcode":"07083",
    "sg:province":"NJ",
    "sg:tags":[
        "operator"
    ],
    "wof:name":"C V I",
    "wof:placetype":"venue"
},
  "geometry": {"coordinates":[-74.23649399999999,40.683495],"type":"Point"}
}