{
  "type": "Feature",
  "properties": {
    "iso:country":"US",
    "sg:address":"64 New St",
    "sg:city":"Bridgeton",
    "sg:classifiers":[
        {
            "category":"Organizations",
            "subcategory":"Religious Organization",
            "type":"Services"
        }
    ],
    "sg:phone":"+1 856 455 9960",
    "sg:postcode":"08302",
    "sg:province":"NJ",
    "wof:name":"Immaculate Conception Convent",
    "wof:placetype":"venue"
},
  "geometry": {"coordinates":[-75.244826,39.424449],"type":"Point"}
}