{
  "type": "Feature",
  "properties": {
    "addr:full":"681 Kingsland Ave Ridgefield NJ 07657",
    "addr:housenumber":"681",
    "addr:postcode":"07657",
    "addr:street":"Kingsland Ave",
    "iso:country":"US",
    "sg:address":"681 Kingsland Ave",
    "sg:city":"Ridgefield",
    "sg:classifiers":[
        {
            "category":"Shopping",
            "subcategory":"Hobbies, Toys, & Games",
            "type":"Retail Goods"
        }
    ],
    "sg:phone":"+1   ",
    "sg:postcode":"07657",
    "sg:province":"NJ",
    "wof:name":"Wagners",
    "wof:placetype":"venue"
},
  "geometry": {"coordinates":[-73.991741,40.830828],"type":"Point"}
}