{
  "type": "Feature",
  "properties": {
    "iso:country":"US",
    "sg:address":"104 Parker Ave",
    "sg:city":"Deal",
    "sg:classifiers":[
        {
            "category":"Professional",
            "subcategory":"Business Services",
            "type":"Services"
        }
    ],
    "sg:phone":"+1   ",
    "sg:postcode":"07723",
    "sg:province":"NJ",
    "wof:name":"Joe Shamie & Assoc Inc",
    "wof:placetype":"venue"
},
  "geometry": {"coordinates":[-74.005494,40.251516],"type":"Point"}
}