{
  "type": "Feature",
  "properties": {
    "iso:country":"US",
    "sg:address":"1300 Admiral Wilson Blvd",
    "sg:city":"Camden",
    "sg:classifiers":[
        {
            "category":"Social Services",
            "subcategory":"Adult Care",
            "type":"Services"
        },
        {
            "category":"Social Services",
            "type":"Services"
        }
    ],
    "sg:phone":"+1 856 963 4751",
    "sg:postcode":"08109",
    "sg:province":"NJ",
    "sg:tags":[
        "foster"
    ],
    "wof:name":"Youth Consultation Services",
    "wof:placetype":"venue"
},
  "geometry": {"coordinates":[-75.10612399999999,39.942586],"type":"Point"}
}