{
  "type": "Feature",
  "properties": {
    "addr:full":"78 N Four Bridges Rd Long Valley NJ 07853",
    "addr:housenumber":"78",
    "addr:postcode":"07853",
    "addr:street":"N Four Bridges Rd",
    "iso:country":"US",
    "sg:address":"78 N Four Bridges Rd",
    "sg:city":"Long Valley",
    "sg:classifiers":[
        {
            "category":"Home & Garden",
            "subcategory":"Home Furnishings",
            "type":"Retail Goods"
        }
    ],
    "sg:phone":"+1   ",
    "sg:postcode":"07853",
    "sg:province":"NJ",
    "sg:tags":[
        "window",
        "installation",
        "treatment"
    ],
    "wof:name":"Window Vangogh",
    "wof:placetype":"venue"
},
  "geometry": {"coordinates":[-74.739121,40.812053],"type":"Point"}
}