{
  "type": "Feature",
  "properties": {
    "iso:country":"US",
    "sg:address":"100 Federal City Rd",
    "sg:city":"Trenton",
    "sg:classifiers":[
        {
            "category":"Professional",
            "type":"Services"
        }
    ],
    "sg:phone":"+1 609 620 0786",
    "sg:postcode":"08648",
    "sg:province":"NJ",
    "sg:tags":[
        "establishment"
    ],
    "wof:name":"DCLI",
    "wof:placetype":"venue"
},
  "geometry": {"coordinates":[-74.76088,40.286425],"type":"Point"}
}