{
  "type": "Feature",
  "properties": {
    "iso:country":"US",
    "sg:address":"1709 Sterling Dr",
    "sg:city":"Florham Park",
    "sg:classifiers":[
        {
            "category":"Real Estate",
            "subcategory":"Real Estate Operator",
            "type":"Services"
        }
    ],
    "sg:phone":"+1   ",
    "sg:postcode":"07932",
    "sg:province":"NJ",
    "sg:tags":[
        "building",
        "nonresidential"
    ],
    "wof:name":"SDC Properties LLC",
    "wof:placetype":"venue"
},
  "geometry": {"coordinates":[-74.369765,40.752639],"type":"Point"}
}