{
  "type": "Feature",
  "properties": {
    "iso:country":"US",
    "sg:address":"1410 Valley Rd",
    "sg:city":"Wayne",
    "sg:classifiers":[
        {
            "category":"Real Estate",
            "subcategory":"Real Estate Agent",
            "type":"Services"
        }
    ],
    "sg:phone":"+1 973 696 1500",
    "sg:postcode":"07470",
    "sg:province":"NJ",
    "wof:name":"Northland Realty Inc",
    "wof:placetype":"venue"
},
  "geometry": {"coordinates":[-74.225542,40.961873],"type":"Point"}
}