{
  "type": "Feature",
  "properties": {
    "addr:full":"10 Weaver Dr Martinsville NJ 08836",
    "addr:housenumber":"10",
    "addr:postcode":"08836",
    "addr:street":"Weaver Dr",
    "iso:country":"US",
    "sg:address":"10 Weaver Dr",
    "sg:city":"Martinsville",
    "sg:classifiers":[
        {
            "category":"Professional",
            "type":"Services"
        }
    ],
    "sg:phone":"+1   ",
    "sg:postcode":"08836",
    "sg:province":"NJ",
    "wof:name":"Khetan Sheo",
    "wof:placetype":"venue"
},
  "geometry": {"coordinates":[-74.54286399999999,40.594067],"type":"Point"}
}