{
  "type": "Feature",
  "properties": {
    "addr:full":"200 Buckelew Ave Jamesburg NJ 08831",
    "addr:housenumber":"200",
    "addr:postcode":"08831",
    "addr:street":"Buckelew Ave",
    "iso:country":"US",
    "sg:address":"200 Buckelew Ave",
    "sg:city":"Jamesburg",
    "sg:classifiers":[
        {
            "category":"Personal",
            "subcategory":"Beauty Salon",
            "type":"Services"
        }
    ],
    "sg:phone":"+1 732 605 9660",
    "sg:postcode":"08831",
    "sg:province":"NJ",
    "sg:tags":[
        "shop",
        "manicuring"
    ],
    "wof:name":"Jamesburg Nail",
    "wof:placetype":"venue"
},
  "geometry": {"coordinates":[-74.434128,40.347125],"type":"Point"}
}