{
  "type": "Feature",
  "properties": {
    "addr:full":"112 Dawn Dr Mt Holly NJ 08060",
    "addr:housenumber":"112",
    "addr:postcode":"08060",
    "addr:street":"Dawn Dr Mt",
    "iso:country":"US",
    "sg:address":"112 Dawn Dr",
    "sg:city":"Mt Holly",
    "sg:classifiers":[
        {
            "category":"Building & Trades",
            "subcategory":"Construction",
            "type":"Services"
        }
    ],
    "sg:phone":"+1 609 267 9088",
    "sg:postcode":"08060",
    "sg:province":"NJ",
    "sg:tags":[
        "painter"
    ],
    "wof:name":"Painting Etc",
    "wof:placetype":"venue"
},
  "geometry": {"coordinates":[-74.77240399999999,39.998408],"type":"Point"}
}