{
  "type": "Feature",
  "properties": {
    "addr:full":"4526 Bergenline Ave Union City NJ 07087",
    "addr:housenumber":"4526",
    "addr:postcode":"07087",
    "addr:street":"Bergenline Ave",
    "iso:country":"US",
    "sg:address":"4526 Bergenline Ave",
    "sg:city":"Union City",
    "sg:classifiers":[
        {
            "category":"Shopping",
            "subcategory":"Jewelry",
            "type":"Retail Goods"
        },
        {
            "category":"Wholesale",
            "subcategory":"Jewelry",
            "type":"Manufacturing & Wholesale Goods"
        }
    ],
    "sg:phone":"+1 201 863 1450",
    "sg:postcode":"07087",
    "sg:province":"NJ",
    "sg:tags":[
        "stone",
        "jeweler"
    ],
    "wof:name":"Earring Trading Co",
    "wof:placetype":"venue"
},
  "geometry": {"coordinates":[-74.023166,40.779738],"type":"Point"}
}