{
  "type": "Feature",
  "properties": {
    "iso:country":"US",
    "sg:address":"126 Franklin St",
    "sg:city":"Riverside",
    "sg:classifiers":[
        {
            "category":"Health Services",
            "subcategory":"Podiatrist",
            "type":"Services"
        }
    ],
    "sg:phone":"+1 856 764 4400",
    "sg:postcode":"08075",
    "sg:province":"NJ",
    "wof:name":"Stuart Jacob DPM",
    "wof:placetype":"venue"
},
  "geometry": {"coordinates":[-74.958181,40.039331],"type":"Point"}
}