{
  "type": "Feature",
  "properties": {
    "addr:full":"805 Rivendell Way Edison NJ 08817",
    "addr:housenumber":"805",
    "addr:postcode":"08817",
    "addr:street":"Rivendell Way",
    "iso:country":"US",
    "sg:address":"805 Rivendell Way",
    "sg:city":"Edison",
    "sg:classifiers":[
        {
            "category":"Professional",
            "type":"Services"
        }
    ],
    "sg:phone":"+1   ",
    "sg:postcode":"08817",
    "sg:province":"NJ",
    "wof:name":"Hexa Corp",
    "wof:placetype":"venue"
},
  "geometry": {"coordinates":[-74.41472899999999,40.52852],"type":"Point"}
}