{
  "type": "Feature",
  "properties": {
    "addr:full":"116 Badger Ave Newark NJ 07108",
    "addr:housenumber":"116",
    "addr:postcode":"07108",
    "addr:street":"Badger Ave",
    "iso:country":"US",
    "sg:address":"116 Badger Ave",
    "sg:city":"Newark",
    "sg:classifiers":[
        {
            "category":"Building & Trades",
            "subcategory":"Landscaping Services",
            "type":"Services"
        }
    ],
    "sg:phone":"+1 973 242 7116",
    "sg:postcode":"07108",
    "sg:province":"NJ",
    "sg:tags":[
        "landscape",
        "contractor"
    ],
    "wof:name":"T & J Powerwashing Landscpg",
    "wof:placetype":"venue"
},
  "geometry": {"coordinates":[-74.19512400000001,40.723525],"type":"Point"}
}