{
  "type": "Feature",
  "properties": {
    "addr:full":"23 Fairview Dr Middletown NJ 07748",
    "addr:housenumber":"23",
    "addr:postcode":"07748",
    "addr:street":"Fairview Dr",
    "iso:country":"US",
    "sg:address":"23 Fairview Dr",
    "sg:city":"Middletown",
    "sg:classifiers":[
        {
            "category":"Professional",
            "type":"Services"
        }
    ],
    "sg:phone":"+1   ",
    "sg:postcode":"07748",
    "sg:province":"NJ",
    "wof:name":"Kathy Ferejohn",
    "wof:placetype":"venue"
},
  "geometry": {"coordinates":[-74.08758400000001,40.379849],"type":"Point"}
}