{
  "type": "Feature",
  "properties": {
    "iso:country":"US",
    "sg:address":"108 Pulaski St",
    "sg:city":"Newark",
    "sg:classifiers":[
        {
            "category":"Professional",
            "type":"Services"
        }
    ],
    "sg:phone":"+1 973 344 0124",
    "sg:postcode":"07105",
    "sg:province":"NJ",
    "sg:tags":[
        "establishment"
    ],
    "wof:name":"Dias Dos Reis Neto Isac",
    "wof:placetype":"venue"
},
  "geometry": {"coordinates":[-74.158593,40.72276],"type":"Point"}
}