{
  "type": "Feature",
  "properties": {
    "iso:country":"US",
    "sg:address":"4206 Boardwalk",
    "sg:city":"Wildwood",
    "sg:classifiers":[
        {
            "category":"Restaurant",
            "type":"Food & Drink"
        }
    ],
    "sg:phone":"+1 609 522 4006",
    "sg:postcode":"08260",
    "sg:province":"NJ",
    "wof:name":"White Dolphin Restaurant",
    "wof:placetype":"venue"
},
  "geometry": {"coordinates":[-74.81559799999999,38.983299],"type":"Point"}
}