{
  "type": "Feature",
  "properties": {
    "iso:country":"US",
    "sg:address":"234 River St",
    "sg:city":"Hackensack",
    "sg:classifiers":[
        {
            "category":"Retail",
            "subcategory":"Auto Repair",
            "type":"Services"
        }
    ],
    "sg:phone":"+1 201 487 8946",
    "sg:postcode":"07601",
    "sg:province":"NJ",
    "sg:tags":[
        "body",
        "shop"
    ],
    "wof:name":"Hackensack Auto Steam & Collision Co",
    "wof:placetype":"venue"
},
  "geometry": {"coordinates":[-74.04009600000001,40.885005],"type":"Point"}
}