{
  "type": "Feature",
  "properties": {
    "addr:full":"108 Bartholdi Ave Jersey City NJ 07305",
    "addr:housenumber":"108",
    "addr:postcode":"07305",
    "addr:street":"Bartholdi Ave",
    "iso:country":"US",
    "sg:address":"108 Bartholdi Ave",
    "sg:city":"Jersey City",
    "sg:classifiers":[
        {
            "category":"Local Transit",
            "type":"Transportation"
        }
    ],
    "sg:phone":"+1 201 433 0176",
    "sg:postcode":"07305",
    "sg:province":"NJ",
    "sg:tags":[
        "passenger"
    ],
    "wof:name":"Bs Limousine Services Inc",
    "wof:placetype":"venue"
},
  "geometry": {"coordinates":[-74.09584,40.695818],"type":"Point"}
}