{
  "type": "Feature",
  "properties": {
    "iso:country":"US",
    "sg:address":"130 Broadway",
    "sg:city":"Hillsdale",
    "sg:classifiers":[
        {
            "category":"Health Services",
            "subcategory":"Nursing And Care Facility",
            "type":"Services"
        }
    ],
    "sg:phone":"+1 201 829 0005",
    "sg:postcode":"07642",
    "sg:province":"NJ",
    "wof:name":"Hopi Corp",
    "wof:placetype":"venue"
},
  "geometry": {"coordinates":[-74.040783,41.004437],"type":"Point"}
}