{
  "type": "Feature",
  "properties": {
    "addr:full":"1 Declan Ct Monmouth Junction NJ 08852",
    "addr:housenumber":"1",
    "addr:postcode":"08852",
    "addr:street":"Declan Ct",
    "iso:country":"US",
    "sg:address":"1 Declan Ct",
    "sg:city":"Monmouth Junction",
    "sg:classifiers":[
        {
            "category":"Autos & Motor Vehicles",
            "subcategory":"Fuel & Gas Station",
            "type":"Retail Goods"
        }
    ],
    "sg:phone":"+1   ",
    "sg:postcode":"08852",
    "sg:province":"NJ",
    "sg:tags":[
        "station",
        "gasoline"
    ],
    "wof:name":"Akal Inc",
    "wof:placetype":"venue"
},
  "geometry": {"coordinates":[-74.548661,40.373583],"type":"Point"}
}