{
  "type": "Feature",
  "properties": {
    "addr:full":"4701 Stelton Rd South Plainfield NJ 07080",
    "addr:housenumber":"4701",
    "addr:postcode":"07080",
    "addr:street":"Stelton Rd",
    "iso:country":"US",
    "sg:address":"4701 Stelton Rd",
    "sg:city":"South Plainfield",
    "sg:classifiers":[
        {
            "category":"Travel",
            "subcategory":"Hotels & Motels",
            "type":"Entertainment"
        }
    ],
    "sg:phone":"+1   ",
    "sg:postcode":"07080",
    "sg:province":"NJ",
    "wof:name":"Holiday Inn",
    "wof:placetype":"venue"
},
  "geometry": {"coordinates":[-74.432182,40.551207],"type":"Point"}
}