{
  "type": "Feature",
  "properties": {
    "iso:country":"US",
    "sg:address":"45 Woodland Ave",
    "sg:city":"Glen Ridge",
    "sg:classifiers":[
        {
            "category":"Organizations",
            "subcategory":"Religious Organization",
            "type":"Services"
        }
    ],
    "sg:phone":"+1 973 743 4492",
    "sg:postcode":"07028",
    "sg:province":"NJ",
    "sg:tags":[
        "clergy"
    ],
    "wof:name":"Paul Brazel Williams",
    "wof:placetype":"venue"
},
  "geometry": {"coordinates":[-74.208628,40.802259],"type":"Point"}
}