{
  "type": "Feature",
  "properties": {
    "addr:full":"7700 River Rd North Bergen NJ 07047",
    "addr:housenumber":"7700",
    "addr:postcode":"07047",
    "addr:street":"River Rd",
    "iso:country":"US",
    "sg:address":"7700 River Rd",
    "sg:city":"North Bergen",
    "sg:classifiers":[
        {
            "category":"Sports & Exercise",
            "subcategory":"Gym",
            "type":"Entertainment"
        }
    ],
    "sg:phone":"+1 201 854 6666",
    "sg:postcode":"07047",
    "sg:province":"NJ",
    "sg:tags":[
        "trainer"
    ],
    "wof:name":"Palisades Fitness & Wellness Center",
    "wof:placetype":"venue"
},
  "geometry": {"coordinates":[-73.996549,40.794946],"type":"Point"}
}