{
  "type": "Feature",
  "properties": {
    "iso:country":"US",
    "sg:address":"1 Electronics Dr",
    "sg:city":"Trenton",
    "sg:classifiers":[
        {
            "category":"Social Services",
            "type":"Services"
        }
    ],
    "sg:phone":"+1 609 584 6237",
    "sg:postcode":"08619",
    "sg:province":"NJ",
    "sg:tags":[
        "organization",
        "welfare"
    ],
    "wof:name":"Osi Support Svc Inc",
    "wof:placetype":"venue"
},
  "geometry": {"coordinates":[-74.70018899999999,40.260201],"type":"Point"}
}