{
  "type": "Feature",
  "properties": {
    "iso:country":"US",
    "sg:address":"700 Co Rd 579",
    "sg:city":"Pittstown",
    "sg:classifiers":[
        {
            "category":"Building & Trades",
            "subcategory":"Construction",
            "type":"Services"
        }
    ],
    "sg:phone":"+1 908 735 8185",
    "sg:postcode":"08867",
    "sg:province":"NJ",
    "sg:tags":[
        "general",
        "contractor"
    ],
    "wof:name":"KFS Construction",
    "wof:placetype":"venue"
},
  "geometry": {"coordinates":[-74.97742599999999,40.600049],"type":"Point"}
}