{
  "type": "Feature",
  "properties": {
    "iso:country":"US",
    "sg:address":"126 Mount Pleasant Ave",
    "sg:city":"Towaco",
    "sg:classifiers":[
        {
            "category":"Organizations",
            "subcategory":"Religious Organization",
            "type":"Services"
        }
    ],
    "sg:phone":"+1 973 334 3924",
    "sg:postcode":"07052",
    "sg:province":"NJ",
    "sg:tags":[
        "church"
    ],
    "wof:name":"Montville United Meth Church",
    "wof:placetype":"venue"
},
  "geometry": {"coordinates":[-74.244573,40.780549],"type":"Point"}
}