{
  "type": "Feature",
  "properties": {
    "iso:country":"US",
    "sg:address":"21 Union St",
    "sg:city":"Lodi",
    "sg:classifiers":[
        {
            "category":"Utilities",
            "subcategory":"Mobile Phone",
            "type":"Services"
        }
    ],
    "sg:phone":"+1 973 249 0330",
    "sg:postcode":"07644",
    "sg:province":"NJ",
    "sg:tags":[
        "communication",
        "telephone",
        "cellular",
        "radiotelephone"
    ],
    "wof:name":"Soikenn Wireless",
    "wof:placetype":"venue"
},
  "geometry": {"coordinates":[-74.08453799999999,40.877361],"type":"Point"}
}