{
  "type": "Feature",
  "properties": {
    "iso:country":"US",
    "sg:address":"1043 Raritan Rd",
    "sg:city":"Clark",
    "sg:classifiers":[
        {
            "category":"Health Services",
            "subcategory":"Chiropractor",
            "type":"Services"
        }
    ],
    "sg:phone":"+1 732 382 3300",
    "sg:postcode":"07066",
    "sg:province":"NJ",
    "wof:name":"Scoliosis Treatment Center of New Jersey",
    "wof:placetype":"venue"
},
  "geometry": {"coordinates":[-74.315804,40.627201],"type":"Point"}
}