{
  "type": "Feature",
  "properties": {
    "iso:country":"US",
    "sg:address":"165 Miami Ave",
    "sg:city":"Trenton",
    "sg:classifiers":[
        {
            "category":"Building & Trades",
            "subcategory":"Construction",
            "type":"Services"
        }
    ],
    "sg:phone":"+1 609 588 0002",
    "sg:postcode":"08610",
    "sg:province":"NJ",
    "sg:tags":[
        "roofing",
        "contractor"
    ],
    "wof:name":"John's Builder's",
    "wof:placetype":"venue"
},
  "geometry": {"coordinates":[-74.711951,40.207123],"type":"Point"}
}