{
  "type": "Feature",
  "properties": {
    "addr:full":"120 Raritan Ave Highland Park NJ 08904",
    "addr:housenumber":"120",
    "addr:postcode":"08904",
    "addr:street":"Raritan Ave",
    "iso:country":"US",
    "sg:address":"120 Raritan Ave",
    "sg:city":"Highland Park",
    "sg:classifiers":[
        {
            "category":"Real Estate",
            "subcategory":"Real Estate Agent",
            "type":"Services"
        }
    ],
    "sg:phone":"+1   ",
    "sg:postcode":"08904",
    "sg:province":"NJ",
    "wof:name":"In Between Realty",
    "wof:placetype":"venue"
},
  "geometry": {"coordinates":[-74.430632,40.498309],"type":"Point"}
}