{
  "type": "Feature",
  "properties": {
    "addr:full":"27 Vernoy Rd Califon NJ 07830",
    "addr:housenumber":"27",
    "addr:postcode":"07830",
    "addr:street":"Vernoy Rd",
    "iso:country":"US",
    "sg:address":"27 Vernoy Rd",
    "sg:city":"Califon",
    "sg:classifiers":[
        {
            "category":"Building & Trades",
            "subcategory":"Construction",
            "type":"Services"
        }
    ],
    "sg:phone":"+1 908 832 2076",
    "sg:postcode":"07830",
    "sg:province":"NJ",
    "sg:tags":[
        "masonry",
        "contractor"
    ],
    "wof:name":"Pignato Landscaping",
    "wof:placetype":"venue"
},
  "geometry": {"coordinates":[-74.829677,40.733762],"type":"Point"}
}