{
  "type": "Feature",
  "properties": {
    "iso:country":"US",
    "sg:address":"200 Haddonfield Rd ",
    "sg:city":"Cherry Hill",
    "sg:classifiers":[
        {
            "category":"Restaurant",
            "type":"Food & Drink"
        }
    ],
    "sg:menulink":"http://www.allmenus.com/nj/cherry-hill/290844-scotto-pizza/menu/",
    "sg:phone":"+1 856 662 3773",
    "sg:postcode":"08002",
    "sg:province":"NJ",
    "sg:tags":[
        "american",
        "pizza"
    ],
    "wof:name":"Scotto Pizza",
    "wof:placetype":"venue"
},
  "geometry": {"coordinates":[-75.028672,39.945364],"type":"Point"}
}