{
  "type": "Feature",
  "properties": {
    "iso:country":"US",
    "sg:address":"665 Ridge Rd",
    "sg:city":"Monmouth Jct",
    "sg:classifiers":[
        {
            "category":"Shopping",
            "subcategory":"Bicycles & Sporting Goods",
            "type":"Retail Goods"
        }
    ],
    "sg:phone":"+1 732 968 1372",
    "sg:postcode":"08852",
    "sg:province":"NJ",
    "wof:name":"Bike N Gear",
    "wof:placetype":"venue"
},
  "geometry": {"coordinates":[-74.55052000000001,40.375687],"type":"Point"}
}