{
  "type": "Feature",
  "properties": {
    "iso:country":"US",
    "sg:address":"2245 US Hwy 130",
    "sg:city":"Dayton",
    "sg:classifiers":[
        {
            "category":"Insurance",
            "subcategory":"Insurance Agent",
            "type":"Services"
        }
    ],
    "sg:phone":"+1   ",
    "sg:postcode":"08810",
    "sg:province":"NJ",
    "wof:name":"Prudential",
    "wof:placetype":"venue"
},
  "geometry": {"coordinates":[-74.50256400000001,40.382631],"type":"Point"}
}