{
  "type": "Feature",
  "properties": {
    "addr:full":"101 Hillcrest Ln Willingboro NJ 08046",
    "addr:housenumber":"101",
    "addr:postcode":"08046",
    "addr:street":"Hillcrest Ln",
    "iso:country":"US",
    "sg:address":"101 Hillcrest Ln",
    "sg:city":"Willingboro",
    "sg:classifiers":[
        {
            "category":"Education",
            "subcategory":"Library",
            "type":"Public Place"
        }
    ],
    "sg:phone":"+1 609 877 5546",
    "sg:postcode":"08046",
    "sg:province":"NJ",
    "wof:name":"Rohan Branch",
    "wof:placetype":"venue"
},
  "geometry": {"coordinates":[-74.87103,40.042976],"type":"Point"}
}