{
  "type": "Feature",
  "properties": {
    "iso:country":"US",
    "sg:address":"26 New York Rd",
    "sg:city":"Port Republic",
    "sg:classifiers":[
        {
            "category":"Professional",
            "subcategory":"Employment Agencies",
            "type":"Services"
        }
    ],
    "sg:phone":"+1 609 652 0651",
    "sg:postcode":"08241",
    "sg:province":"NJ",
    "wof:name":"N McLaverty Rn",
    "wof:placetype":"venue"
},
  "geometry": {"coordinates":[-74.4654,39.535823],"type":"Point"}
}