{
  "type": "Feature",
  "properties": {
    "addr:full":"540 Route 10 W Randolph NJ 07869",
    "addr:housenumber":"540",
    "addr:postcode":"07869",
    "addr:street":"Route 10 W",
    "iso:country":"US",
    "sg:address":"540 Route 10 W",
    "sg:city":"Randolph",
    "sg:classifiers":[
        {
            "category":"Restaurant",
            "type":"Food & Drink"
        }
    ],
    "sg:menulink":"http://www.allmenus.com/nj/randolph/292448-big-rays-pizza/menu/",
    "sg:phone":"+1 973 361 2000",
    "sg:postcode":"07869",
    "sg:province":"NJ",
    "sg:tags":[
        "pizza"
    ],
    "wof:name":"Big Ray's Pizza",
    "wof:placetype":"venue"
},
  "geometry": {"coordinates":[-74.57204900000001,40.862632],"type":"Point"}
}