{
  "type": "Feature",
  "properties": {
    "addr:full":"10 Falcon Dr Edison NJ 08820",
    "addr:housenumber":"10",
    "addr:postcode":"08820",
    "addr:street":"Falcon Dr",
    "iso:country":"US",
    "sg:address":"10 Falcon Dr",
    "sg:city":"Edison",
    "sg:classifiers":[
        {
            "category":"Professional",
            "type":"Services"
        }
    ],
    "sg:phone":"+1 732 548 0171",
    "sg:postcode":"08820",
    "sg:province":"NJ",
    "sg:tags":[
        "consulting",
        "chemist"
    ],
    "wof:name":"Chem Business Development Inc",
    "wof:placetype":"venue"
},
  "geometry": {"coordinates":[-74.354496,40.574799],"type":"Point"}
}