{
  "type": "Feature",
  "properties": {
    "iso:country":"US",
    "sg:address":"144 Fairfield Rd",
    "sg:city":"Fairfield",
    "sg:classifiers":[
        {
            "category":"Professional",
            "subcategory":"Business Services",
            "type":"Services"
        }
    ],
    "sg:phone":"+1   ",
    "sg:postcode":"07004",
    "sg:province":"NJ",
    "sg:tags":[
        "trade",
        "show"
    ],
    "wof:name":"Exposition Sales and Design",
    "wof:placetype":"venue"
},
  "geometry": {"coordinates":[-74.296663,40.875426],"type":"Point"}
}