{
  "type": "Feature",
  "properties": {
    "iso:country":"US",
    "sg:address":"50 Belcher Rd",
    "sg:city":"Blairstown",
    "sg:classifiers":[
        {
            "category":"Building & Trades",
            "subcategory":"Electrical",
            "type":"Services"
        }
    ],
    "sg:phone":"+1 908 362 5515",
    "sg:postcode":"07825",
    "sg:province":"NJ",
    "sg:tags":[
        "electrical",
        "electric",
        "contractor"
    ],
    "wof:name":"Grizzly Electric LLC",
    "wof:placetype":"venue"
},
  "geometry": {"coordinates":[-74.994125,40.95701],"type":"Point"}
}