{
  "type": "Feature",
  "properties": {
    "addr:full":"21 N Day St Orange NJ 07050",
    "addr:housenumber":"21",
    "addr:postcode":"07050",
    "addr:street":"N Day St",
    "iso:country":"US",
    "sg:address":"21 N Day St",
    "sg:city":"Orange",
    "sg:classifiers":[
        {
            "category":"Real Estate",
            "subcategory":"Real Estate Services",
            "type":"Services"
        }
    ],
    "sg:phone":"+1 973 677 0029",
    "sg:postcode":"07050",
    "sg:province":"NJ",
    "sg:tags":[
        "management",
        "property"
    ],
    "wof:name":"Tire and Auto Center",
    "wof:placetype":"venue"
},
  "geometry": {"coordinates":[-74.229308,40.772968],"type":"Point"}
}