{
  "type": "Feature",
  "properties": {
    "iso:country":"US",
    "sg:address":"460 E 16th St",
    "sg:city":"Paterson",
    "sg:classifiers":[
        {
            "category":"Recreation",
            "subcategory":"Arcade",
            "type":"Entertainment"
        },
        {
            "category":"Professional",
            "subcategory":"Management & Consulting",
            "type":"Services"
        }
    ],
    "sg:phone":"+1 973 225 0262",
    "sg:postcode":"07514",
    "sg:province":"NJ",
    "sg:tags":[
        "device",
        "planning",
        "operator",
        "party",
        "event",
        "amusement"
    ],
    "wof:name":"Trade Amusement",
    "wof:placetype":"venue"
},
  "geometry": {"coordinates":[-74.155098,40.921902],"type":"Point"}
}