{
  "type": "Feature",
  "properties": {
    "addr:full":"7 Cooper Ave Marlton NJ 08053",
    "addr:housenumber":"7",
    "addr:postcode":"08053",
    "addr:street":"Cooper Ave",
    "iso:country":"US",
    "sg:address":"7 Cooper Ave",
    "sg:city":"Marlton",
    "sg:classifiers":[
        {
            "category":"Home & Garden",
            "subcategory":"Building Materials",
            "type":"Retail Goods"
        }
    ],
    "sg:phone":"+1   ",
    "sg:postcode":"08053",
    "sg:province":"NJ",
    "sg:tags":[
        "paint",
        "wallpaper",
        "novelty",
        "gift",
        "supply"
    ],
    "wof:name":"Bear Hugs",
    "wof:placetype":"venue"
},
  "geometry": {"coordinates":[-74.918537,39.893603],"type":"Point"}
}