{
  "type": "Feature",
  "properties": {
    "iso:country":"US",
    "sg:address":"28 Orange Pl",
    "sg:city":"West Orange",
    "sg:classifiers":[
        {
            "category":"Recreation",
            "type":"Entertainment"
        }
    ],
    "sg:phone":"+1   ",
    "sg:postcode":"07052",
    "sg:province":"NJ",
    "wof:name":"Mike Sheppard Bsbll Schl",
    "wof:placetype":"venue"
},
  "geometry": {"coordinates":[-74.231306,40.792975],"type":"Point"}
}