{
  "type": "Feature",
  "properties": {
    "addr:full":"62 Ridge Rd North Arlington NJ 07031",
    "addr:housenumber":"62",
    "addr:postcode":"07031",
    "addr:street":"Ridge Rd North",
    "iso:country":"US",
    "sg:address":"62 Ridge Rd",
    "sg:city":"North Arlington",
    "sg:classifiers":[
        {
            "category":"Health Services",
            "subcategory":"Doctor",
            "type":"Services"
        }
    ],
    "sg:phone":"+1 201 991 8565",
    "sg:postcode":"07031",
    "sg:province":"NJ",
    "wof:name":"Lenchur Peter MD",
    "wof:placetype":"venue"
},
  "geometry": {"coordinates":[-74.137001,40.783401],"type":"Point"}
}