{
  "type": "Feature",
  "properties": {
    "addr:full":"1781 US Hwy 206 Southampton NJ 08088",
    "addr:housenumber":"1781",
    "addr:postcode":"08088",
    "addr:street":"Us Hwy 206",
    "iso:country":"US",
    "sg:address":"1781 US Hwy 206",
    "sg:city":"Southampton",
    "sg:classifiers":[
        {
            "category":"Banks & Credit Unions",
            "subcategory":"Bank",
            "type":"Services"
        }
    ],
    "sg:phone":"+1 609 801 3202",
    "sg:postcode":"08088",
    "sg:province":"NJ",
    "wof:name":"Pnc Bank",
    "wof:placetype":"venue"
},
  "geometry": {"coordinates":[-74.741469,39.889659],"type":"Point"}
}