{
  "type": "Feature",
  "properties": {
    "iso:country":"US",
    "sg:address":"189 US Hwy 9",
    "sg:city":"Englishtown",
    "sg:classifiers":[
        {
            "category":"Health Services",
            "subcategory":"Doctor",
            "type":"Services"
        }
    ],
    "sg:phone":"+1 732 308 1133",
    "sg:postcode":"07726",
    "sg:province":"NJ",
    "sg:tags":[
        "physician",
        "surgeon"
    ],
    "wof:name":"Eye Medical & Surgery Ctr",
    "wof:placetype":"venue"
},
  "geometry": {"coordinates":[-74.303819,40.301988],"type":"Point"}
}