{
  "type": "Feature",
  "properties": {
    "addr:full":"28 William St Newark NJ 07102",
    "addr:housenumber":"28",
    "addr:postcode":"07102",
    "addr:street":"William St",
    "iso:country":"US",
    "sg:address":"28 William St",
    "sg:city":"Newark",
    "sg:classifiers":[
        {
            "category":"Wholesale",
            "subcategory":"Auto Parts",
            "type":"Manufacturing & Wholesale Goods"
        }
    ],
    "sg:phone":"+1 973 623 0415",
    "sg:postcode":"07102",
    "sg:province":"NJ",
    "sg:tags":[
        "automobile",
        "supply"
    ],
    "wof:name":"E & L Battery & Ignition",
    "wof:placetype":"venue"
},
  "geometry": {"coordinates":[-74.174746,40.733467],"type":"Point"}
}