{
  "type": "Feature",
  "properties": {
    "addr:full":"2005 Delsea Dr Franklinville NJ 08322",
    "addr:housenumber":"2005",
    "addr:postcode":"08322",
    "addr:street":"Delsea Dr",
    "iso:country":"US",
    "sg:address":"2005 Delsea Dr",
    "sg:city":"Franklinville",
    "sg:classifiers":[
        {
            "category":"Health Services",
            "subcategory":"Dentist",
            "type":"Services"
        }
    ],
    "sg:phone":"+1 856 694 5555",
    "sg:postcode":"08322",
    "sg:province":"NJ",
    "sg:tags":[
        "dentists-orthodontists"
    ],
    "wof:name":"Franklinville Family-Cosmetic",
    "wof:placetype":"venue"
},
  "geometry": {"coordinates":[-75.07037699999999,39.605755],"type":"Point"}
}