{
  "type": "Feature",
  "properties": {
    "iso:country":"US",
    "sg:address":"17 Mahogany Dr.",
    "sg:city":"Burlington",
    "sg:classifiers":[
        {
            "category":"Communications",
            "type":"Services"
        }
    ],
    "sg:phone":"+1 888 509 6460",
    "sg:postcode":"08016",
    "sg:province":"NJ",
    "sg:tags":[
        "web",
        "design"
    ],
    "sg:website":"www.pushstar.com",
    "wof:name":"pushStar Multimedia",
    "wof:placetype":"venue"
},
  "geometry": {"coordinates":[-74.866933,40.057213],"type":"Point"}
}