{
  "type": "Feature",
  "properties": {
    "iso:country":"US",
    "sg:address":"84 E Van Ness Ave",
    "sg:city":"Rutherford",
    "sg:classifiers":[
        {
            "category":"Building & Trades",
            "subcategory":"Plumbing",
            "type":"Services"
        }
    ],
    "sg:phone":"+1 201 933 3144",
    "sg:postcode":"07070",
    "sg:province":"NJ",
    "sg:tags":[
        "contractor"
    ],
    "wof:name":"RE Graver Co",
    "wof:placetype":"venue"
},
  "geometry": {"coordinates":[-74.11265299999999,40.821324],"type":"Point"}
}