{
  "type": "Feature",
  "properties": {
    "addr:full":"1048 State Rte 35 Shrewsbury NJ 07702",
    "addr:housenumber":"1048",
    "addr:postcode":"07702",
    "addr:street":"State Rte 35",
    "iso:country":"US",
    "sg:address":"1048 State Rte 35",
    "sg:city":"Shrewsbury",
    "sg:classifiers":[
        {
            "category":"Banks & Credit Unions",
            "subcategory":"Bank",
            "type":"Services"
        }
    ],
    "sg:phone":"+1   ",
    "sg:postcode":"07702",
    "sg:province":"NJ",
    "sg:tags":[
        "banker",
        "mortgage"
    ],
    "wof:name":"Countrywide",
    "wof:placetype":"venue"
},
  "geometry": {"coordinates":[-74.063169,40.315121],"type":"Point"}
}