{
  "type": "Feature",
  "properties": {
    "iso:country":"US",
    "sg:address":"222 Millstone Rd",
    "sg:city":"Perrineville",
    "sg:classifiers":[
        {
            "category":"Real Estate",
            "subcategory":"Real Estate Agent",
            "type":"Services"
        }
    ],
    "sg:phone":"+1 732 446 4959",
    "sg:postcode":"08535",
    "sg:province":"NJ",
    "sg:website":"www.prunewjersey.com",
    "wof:name":"Prudential New Jersey Realty",
    "wof:placetype":"venue"
},
  "geometry": {"coordinates":[-74.42938100000001,40.223457],"type":"Point"}
}