{
  "type": "Feature",
  "properties": {
    "iso:country":"US",
    "sg:address":"25 N Fullerton Ave",
    "sg:city":"Montclair",
    "sg:classifiers":[
        {
            "category":"Professional",
            "subcategory":"Management & Consulting",
            "type":"Services"
        }
    ],
    "sg:phone":"+1 973 233 1663",
    "sg:postcode":"07042",
    "sg:province":"NJ",
    "sg:tags":[
        "conference",
        "consultant",
        "meeting"
    ],
    "wof:name":"Detail Management",
    "wof:placetype":"venue"
},
  "geometry": {"coordinates":[-74.21674899999999,40.814823],"type":"Point"}
}