{
  "type": "Feature",
  "properties": {
    "iso:country":"US",
    "sg:address":"4607 Bergenline Ave",
    "sg:city":"Union City",
    "sg:classifiers":[
        {
            "category":"Restaurant",
            "type":"Food & Drink"
        }
    ],
    "sg:phone":"+1 201 902 0048",
    "sg:postcode":"07087",
    "sg:province":"NJ",
    "wof:name":"Pan Con Todo Llc",
    "wof:placetype":"venue"
},
  "geometry": {"coordinates":[-74.022654,40.780669],"type":"Point"}
}