{
  "type": "Feature",
  "properties": {
    "iso:country":"US",
    "sg:address":"693 Elm St",
    "sg:city":"Kearny",
    "sg:classifiers":[
        {
            "category":"Building & Trades",
            "subcategory":"Cleaning & Sanitation",
            "type":"Services"
        }
    ],
    "sg:phone":"+1 201 991 7175",
    "sg:postcode":"07032",
    "sg:province":"NJ",
    "sg:tags":[
        "janitor",
        "maintenance"
    ],
    "wof:name":"D & J Maintenance Service Co",
    "wof:placetype":"venue"
},
  "geometry": {"coordinates":[-74.13521799999999,40.775182],"type":"Point"}
}