{
  "type": "Feature",
  "properties": {
    "iso:country":"US",
    "sg:address":"12 Redwood Ter",
    "sg:city":"Hazlet",
    "sg:classifiers":[
        {
            "category":"Professional",
            "type":"Services"
        }
    ],
    "sg:phone":"+1   ",
    "sg:postcode":"07730",
    "sg:province":"NJ",
    "wof:name":"K&P Foods Inc",
    "wof:placetype":"venue"
},
  "geometry": {"coordinates":[-74.17014399999999,40.431462],"type":"Point"}
}