{
  "type": "Feature",
  "properties": {
    "iso:country":"US",
    "sg:address":"7 Pine Ct",
    "sg:city":"New Providence",
    "sg:classifiers":[
        {
            "category":"Professional",
            "type":"Services"
        }
    ],
    "sg:phone":"+1   ",
    "sg:postcode":"07974",
    "sg:province":"NJ",
    "wof:name":"Susan Muntz",
    "wof:placetype":"venue"
},
  "geometry": {"coordinates":[-74.39484,40.71109],"type":"Point"}
}