{
  "type": "Feature",
  "properties": {
    "iso:country":"US",
    "sg:address":"200 River St",
    "sg:city":"Hackensack",
    "sg:classifiers":[
        {
            "category":"Autos & Motor Vehicles",
            "subcategory":"Auto Supplies",
            "type":"Retail Goods"
        }
    ],
    "sg:phone":"+1 201 489 7543",
    "sg:postcode":"07601",
    "sg:province":"NJ",
    "sg:tags":[
        "tire"
    ],
    "wof:name":"Circle Brake",
    "wof:placetype":"venue"
},
  "geometry": {"coordinates":[-74.04059100000001,40.883688],"type":"Point"}
}