{
  "type": "Feature",
  "properties": {
    "addr:full":"1044 State Rte 23 Wayne NJ 07470",
    "addr:housenumber":"1044",
    "addr:postcode":"07470",
    "addr:street":"State Rte 23",
    "iso:country":"US",
    "sg:address":"1044 State Rte 23",
    "sg:city":"Wayne",
    "sg:classifiers":[
        {
            "category":"Health Services",
            "subcategory":"Doctor",
            "type":"Services"
        }
    ],
    "sg:phone":"+1   ",
    "sg:postcode":"07470",
    "sg:province":"NJ",
    "sg:tags":[
        "medical"
    ],
    "wof:name":"Robert Bergen MD PA",
    "wof:placetype":"venue"
},
  "geometry": {"coordinates":[-74.26737900000001,40.920158],"type":"Point"}
}