{
  "type": "Feature",
  "properties": {
    "addr:full":"68 County Line Rd Somerville NJ 08876",
    "addr:housenumber":"68",
    "addr:postcode":"08876",
    "addr:street":"County Line Rd",
    "iso:country":"US",
    "sg:address":"68 County Line Rd",
    "sg:city":"Somerville",
    "sg:classifiers":[
        {
            "category":"Manufacturing",
            "subcategory":"Rubber & Plastics",
            "type":"Manufacturing & Wholesale Goods"
        }
    ],
    "sg:phone":"+1 908 722 5254",
    "sg:postcode":"08876",
    "sg:province":"NJ",
    "sg:tags":[
        "mfg",
        "structural",
        "foam",
        "molding"
    ],
    "wof:name":"Polycel Structural Foam Inc",
    "wof:placetype":"venue"
},
  "geometry": {"coordinates":[-74.72181999999999,40.598965],"type":"Point"}
}