{
  "type": "Feature",
  "properties": {
    "iso:country":"US",
    "sg:address":"30 3rd Ave",
    "sg:city":"Allenwood",
    "sg:classifiers":[
        {
            "category":"Wholesale",
            "subcategory":"Chemicals & Plastics",
            "type":"Manufacturing & Wholesale Goods"
        }
    ],
    "sg:phone":"+1 732 938 2272",
    "sg:postcode":"08752",
    "sg:province":"NJ",
    "wof:name":"Novartis Corporation",
    "wof:placetype":"venue"
},
  "geometry": {"coordinates":[-74.076432,39.920961],"type":"Point"}
}