{
  "type": "Feature",
  "properties": {
    "addr:full":"154 Balcourt Dr Princeton NJ 08540",
    "addr:housenumber":"154",
    "addr:postcode":"08540",
    "addr:street":"Balcourt Dr",
    "iso:country":"US",
    "sg:address":"154 Balcourt Dr",
    "sg:city":"Princeton",
    "sg:classifiers":[
        {
            "category":"Banks & Credit Unions",
            "subcategory":"Investment Brokerage",
            "type":"Services"
        }
    ],
    "sg:phone":"+1   ",
    "sg:postcode":"08540",
    "sg:province":"NJ",
    "sg:tags":[
        "security"
    ],
    "wof:name":"Zumbrunn John",
    "wof:placetype":"venue"
},
  "geometry": {"coordinates":[-74.675031,40.377491],"type":"Point"}
}