{
  "type": "Feature",
  "properties": {
    "addr:full":"3807 Ventnor Ave Atlantic City NJ 08401",
    "addr:housenumber":"3807",
    "addr:postcode":"08401",
    "addr:street":"Ventnor Ave",
    "iso:country":"US",
    "sg:address":"3807 Ventnor Ave",
    "sg:city":"Atlantic City",
    "sg:classifiers":[
        {
            "category":"Professional",
            "type":"Services"
        }
    ],
    "sg:phone":"+1 609 340 8105",
    "sg:postcode":"08401",
    "sg:province":"NJ",
    "sg:tags":[
        "establishment"
    ],
    "wof:name":"Tcs II",
    "wof:placetype":"venue"
},
  "geometry": {"coordinates":[-74.45700600000001,39.350485],"type":"Point"}
}