{
  "type": "Feature",
  "properties": {
    "iso:country":"US",
    "sg:address":"1001 Teaneck Rd",
    "sg:city":"Teaneck",
    "sg:classifiers":[
        {
            "category":"Real Estate",
            "subcategory":"Real Estate Agent",
            "type":"Services"
        }
    ],
    "sg:phone":"+1 201 833 6001",
    "sg:postcode":"07666",
    "sg:province":"NJ",
    "wof:name":"Re/Max Quality Homes",
    "wof:placetype":"venue"
},
  "geometry": {"coordinates":[-74.004475,40.889058],"type":"Point"}
}