{
  "type": "Feature",
  "properties": {
    "iso:country":"US",
    "sg:address":"1529 Springfield Ave",
    "sg:city":"Maplewood",
    "sg:classifiers":[
        {
            "category":"Social Services",
            "subcategory":"Child Care",
            "type":"Services"
        }
    ],
    "sg:phone":"+1 973 378 3500",
    "sg:postcode":"07040",
    "sg:province":"NJ",
    "wof:name":"Lepetit Academy",
    "wof:placetype":"venue"
},
  "geometry": {"coordinates":[-74.253996,40.722815],"type":"Point"}
}