{
  "type": "Feature",
  "properties": {
    "addr:full":"10 Summit Ave Ste 1 Berkeley Heights NJ 07922",
    "addr:housenumber":"10",
    "addr:postcode":"07922",
    "addr:street":"Summit Ave Ste 1",
    "iso:country":"US",
    "sg:address":"10 Summit Ave Ste 1",
    "sg:city":"Berkeley Heights",
    "sg:classifiers":[
        {
            "category":"Personal",
            "type":"Services"
        }
    ],
    "sg:phone":"+1 908 464 8220",
    "sg:postcode":"07922",
    "sg:province":"NJ",
    "sg:tags":[
        "mover"
    ],
    "sg:website":"www.harringtonmovers.com",
    "wof:name":"Harrington Movers",
    "wof:placetype":"venue"
},
  "geometry": {"coordinates":[-74.443144,40.68768],"type":"Point"}
}