{
  "type": "Feature",
  "properties": {
    "iso:country":"US",
    "sg:address":"546 N Bridge St",
    "sg:city":"Bridgewater",
    "sg:classifiers":[
        {
            "category":"Professional",
            "type":"Services"
        }
    ],
    "sg:phone":"+1   ",
    "sg:postcode":"08807",
    "sg:province":"NJ",
    "wof:name":"Stela C Vergara",
    "wof:placetype":"venue"
},
  "geometry": {"coordinates":[-74.60907899999999,40.592135],"type":"Point"}
}