{
  "type": "Feature",
  "properties": {
    "iso:country":"US",
    "sg:address":"548 Colgate Ave",
    "sg:city":"Perth Amboy",
    "sg:classifiers":[
        {
            "category":"Insurance",
            "subcategory":"Insurance Agent",
            "type":"Services"
        }
    ],
    "sg:phone":"+1 732 826 1247",
    "sg:postcode":"08861",
    "sg:province":"NJ",
    "wof:name":"Dyke Co",
    "wof:placetype":"venue"
},
  "geometry": {"coordinates":[-74.287289,40.522763],"type":"Point"}
}