{
  "type": "Feature",
  "properties": {
    "iso:country":"US",
    "sg:address":"461 Cedar Ln",
    "sg:city":"Teaneck",
    "sg:classifiers":[
        {
            "category":"Personal",
            "subcategory":"Shoe Repair & Shine",
            "type":"Services"
        },
        {
            "category":"Shopping",
            "subcategory":"Shoes",
            "type":"Retail Goods"
        }
    ],
    "sg:phone":"+1 201 836 5835",
    "sg:postcode":"07666",
    "sg:province":"NJ",
    "sg:tags":[
        "store"
    ],
    "wof:name":"Panettieri F J Shoes and Repairing",
    "wof:placetype":"venue"
},
  "geometry": {"coordinates":[-74.022102,40.889],"type":"Point"}
}