{
  "type": "Feature",
  "properties": {
    "iso:country":"US",
    "sg:address":"711 Cable Ave",
    "sg:city":"Beachwood",
    "sg:classifiers":[
        {
            "category":"Manufacturing",
            "subcategory":"Glass & Minerals",
            "type":"Manufacturing & Wholesale Goods"
        }
    ],
    "sg:phone":"+1 732 281 0167",
    "sg:postcode":"08722",
    "sg:province":"NJ",
    "sg:tags":[
        "mfg"
    ],
    "wof:name":"Stonecanvas Artworks",
    "wof:placetype":"venue"
},
  "geometry": {"coordinates":[-74.197008,39.928984],"type":"Point"}
}