{
  "type": "Feature",
  "properties": {
    "addr:full":"303 W Palisade Ave Englewood NJ 07631",
    "addr:housenumber":"303",
    "addr:postcode":"07631",
    "addr:street":"W Palisade Ave",
    "iso:country":"US",
    "sg:address":"303 W Palisade Ave",
    "sg:city":"Englewood",
    "sg:classifiers":[
        {
            "category":"Health Services",
            "subcategory":"Health Practitioner",
            "type":"Services"
        }
    ],
    "sg:phone":"+1 201 816 3050",
    "sg:postcode":"07631",
    "sg:province":"NJ",
    "wof:name":"Serenity Skincare Bdy Wellness",
    "wof:placetype":"venue"
},
  "geometry": {"coordinates":[-73.988257,40.901643],"type":"Point"}
}