{
  "type": "Feature",
  "properties": {
    "iso:country":"US",
    "sg:address":"1031 McBride Ave Ste C203",
    "sg:city":"West Paterson",
    "sg:classifiers":[
        {
            "category":"Health Services",
            "subcategory":"Doctor",
            "type":"Services"
        }
    ],
    "sg:phone":"+1 973 256 4880",
    "sg:postcode":"07424",
    "sg:province":"NJ",
    "sg:tags":[
        "cardiologist"
    ],
    "wof:name":"Majid Naweed K MD",
    "wof:placetype":"venue"
},
  "geometry": {"coordinates":[-74.2071,40.8936],"type":"Point"}
}