{
  "type": "Feature",
  "properties": {
    "iso:country":"US",
    "sg:address":"16 Deerberry Ln",
    "sg:city":"Monmouth Junction",
    "sg:classifiers":[
        {
            "category":"Professional",
            "subcategory":"Management & Consulting",
            "type":"Services"
        }
    ],
    "sg:phone":"+1   ",
    "sg:postcode":"08852",
    "sg:province":"NJ",
    "sg:tags":[
        "business"
    ],
    "wof:name":"National Business Adjusters",
    "wof:placetype":"venue"
},
  "geometry": {"coordinates":[-74.56841900000001,40.396225],"type":"Point"}
}