{
  "type": "Feature",
  "properties": {
    "addr:full":"2323 State Rte 34 Manasquan NJ 08736",
    "addr:housenumber":"2323",
    "addr:postcode":"08736",
    "addr:street":"State Rte 34",
    "iso:country":"US",
    "sg:address":"2323 State Rte 34",
    "sg:city":"Manasquan",
    "sg:classifiers":[
        {
            "category":"Professional",
            "subcategory":"Management & Consulting",
            "type":"Services"
        }
    ],
    "sg:phone":"+1   ",
    "sg:postcode":"08736",
    "sg:province":"NJ",
    "wof:name":"OConco Health Care Inc",
    "wof:placetype":"venue"
},
  "geometry": {"coordinates":[-74.09090399999999,40.13689],"type":"Point"}
}