{
  "type": "Feature",
  "properties": {
    "addr:full":"8 Chestnut Ridge Rd Montvale NJ 07645",
    "addr:housenumber":"8",
    "addr:postcode":"07645",
    "addr:street":"Chestnut Ridge Rd",
    "iso:country":"US",
    "sg:address":"8 Chestnut Ridge Rd",
    "sg:city":"Montvale",
    "sg:classifiers":[
        {
            "category":"Health Services",
            "subcategory":"Chiropractor",
            "type":"Services"
        }
    ],
    "sg:phone":"+1 201 391 8282",
    "sg:postcode":"07645",
    "sg:province":"NJ",
    "wof:name":"Montvale Rehab & Spinal Care",
    "wof:placetype":"venue"
},
  "geometry": {"coordinates":[-74.069098,41.052653],"type":"Point"}
}