{
  "type": "Feature",
  "properties": {
    "iso:country":"US",
    "sg:address":"910 Hooper Ave",
    "sg:city":"Toms River",
    "sg:classifiers":[
        {
            "category":"Shopping",
            "subcategory":"Bicycles & Sporting Goods",
            "type":"Retail Goods"
        }
    ],
    "sg:phone":"+1 732 281 0666",
    "sg:postcode":"08753",
    "sg:province":"NJ",
    "wof:name":"Fudd Lacrosse",
    "wof:placetype":"venue"
},
  "geometry": {"coordinates":[-74.187212,39.963845],"type":"Point"}
}