{
  "type": "Feature",
  "properties": {
    "addr:full":"91 E Somerset St Raritan NJ 08869",
    "addr:housenumber":"91",
    "addr:postcode":"08869",
    "addr:street":"E Somerset St",
    "iso:country":"US",
    "sg:address":"91 E Somerset St",
    "sg:city":"Raritan",
    "sg:classifiers":[
        {
            "category":"Social Services",
            "subcategory":"Job Training",
            "type":"Services"
        }
    ],
    "sg:phone":"+1 908 575 9616",
    "sg:postcode":"08869",
    "sg:province":"NJ",
    "sg:tags":[
        "employment"
    ],
    "wof:name":"Arc Of Nj Project Hire",
    "wof:placetype":"venue"
},
  "geometry": {"coordinates":[-74.625938,40.569684],"type":"Point"}
}