{
  "type": "Feature",
  "properties": {
    "addr:full":"109 Sterling Ave Jersey City NJ 07305",
    "addr:housenumber":"109",
    "addr:postcode":"07305",
    "addr:street":"Sterling Ave",
    "iso:country":"US",
    "sg:address":"109 Sterling Ave",
    "sg:city":"Jersey City",
    "sg:classifiers":[
        {
            "category":"Building & Trades",
            "subcategory":"Locksmith",
            "type":"Services"
        }
    ],
    "sg:phone":"+1 888 277 3361",
    "sg:postcode":"07305",
    "sg:province":"NJ",
    "sg:tags":[
        "key"
    ],
    "wof:name":"24 Emergency Locksmith",
    "wof:placetype":"venue"
},
  "geometry": {"coordinates":[-74.093857,40.706069],"type":"Point"}
}