{
  "type": "Feature",
  "properties": {
    "addr:full":"626 Goshen Rd Cape May Ct Hse NJ 08210",
    "addr:housenumber":"626",
    "addr:postcode":"08210",
    "addr:street":"Goshen Rd;May Ct",
    "iso:country":"US",
    "sg:address":"626 Goshen Rd",
    "sg:city":"Cape May Ct Hse",
    "sg:classifiers":[
        {
            "category":"Recreation",
            "type":"Entertainment"
        }
    ],
    "sg:phone":"+1 609 465 8743",
    "sg:postcode":"08210",
    "sg:province":"NJ",
    "sg:tags":[
        "parks"
    ],
    "wof:name":"Middle Twp Recreation Dept",
    "wof:placetype":"venue"
},
  "geometry": {"coordinates":[-74.83527100000001,39.104084],"type":"Point"}
}