{
  "type": "Feature",
  "properties": {
    "addr:full":"392 State Rte 57 Washington NJ 07882",
    "addr:housenumber":"392",
    "addr:postcode":"07882",
    "addr:street":"State Rte 57",
    "iso:country":"US",
    "sg:address":"392 State Rte 57",
    "sg:city":"Washington",
    "sg:classifiers":[
        {
            "category":"Food & Beverages",
            "subcategory":"Liquor & Beverages",
            "type":"Retail Goods"
        }
    ],
    "sg:phone":"+1 908 689 8877",
    "sg:postcode":"07882",
    "sg:province":"NJ",
    "wof:name":"Town & Country Liquor",
    "wof:placetype":"venue"
},
  "geometry": {"coordinates":[-75.003902,40.751661],"type":"Point"}
}