{
  "type": "Feature",
  "properties": {
    "iso:country":"US",
    "sg:address":"186 Princeton Hightstown Rd",
    "sg:city":"Princeton Junction",
    "sg:classifiers":[
        {
            "category":"Mining & Drilling",
            "type":"Manufacturing & Wholesale Goods"
        }
    ],
    "sg:phone":"+1 609 275 9600",
    "sg:postcode":"08550",
    "sg:province":"NJ",
    "sg:tags":[
        "management",
        "oil",
        "spill"
    ],
    "wof:name":"Oops",
    "wof:placetype":"venue"
},
  "geometry": {"coordinates":[-74.60674400000001,40.301246],"type":"Point"}
}