{
  "type": "Feature",
  "properties": {
    "iso:country":"US",
    "sg:address":"2631 State Rte 516",
    "sg:city":"Old Bridge",
    "sg:classifiers":[
        {
            "category":"Shopping",
            "subcategory":"Beauty & Cosmetics",
            "type":"Retail Goods"
        }
    ],
    "sg:phone":"+1   ",
    "sg:postcode":"08857",
    "sg:province":"NJ",
    "sg:tags":[
        "shop",
        "merchandise"
    ],
    "wof:name":"Divas Beauty & Hair Supply",
    "wof:placetype":"venue"
},
  "geometry": {"coordinates":[-74.33128499999999,40.405786],"type":"Point"}
}