{
  "type": "Feature",
  "properties": {
    "iso:country":"US",
    "sg:address":"716 Bryant St",
    "sg:city":"Paramus",
    "sg:classifiers":[
        {
            "category":"Building & Trades",
            "subcategory":"Construction",
            "type":"Services"
        },
        {
            "category":"Professional",
            "subcategory":"Art Services",
            "type":"Services"
        }
    ],
    "sg:phone":"+1 201 445 4536",
    "sg:postcode":"07652",
    "sg:province":"NJ",
    "sg:tags":[
        "commercial",
        "designer",
        "design"
    ],
    "wof:name":"Dynamic Designs Inc",
    "wof:placetype":"venue"
},
  "geometry": {"coordinates":[-74.088572,40.972495],"type":"Point"}
}