{
  "type": "Feature",
  "properties": {
    "addr:full":"628 Valley Rd Montclair NJ 07043",
    "addr:housenumber":"628",
    "addr:postcode":"07043",
    "addr:street":"Valley Rd",
    "iso:country":"US",
    "sg:address":"628 Valley Rd",
    "sg:city":"Montclair",
    "sg:classifiers":[
        {
            "category":"Shopping",
            "subcategory":"Jewelry",
            "type":"Retail Goods"
        }
    ],
    "sg:phone":"+1 973 744 4111",
    "sg:postcode":"07043",
    "sg:province":"NJ",
    "sg:website":"www.wesleyjewelers.com",
    "wof:name":"Wesley's Jewelers",
    "wof:placetype":"venue"
},
  "geometry": {"coordinates":[-74.208,40.8423],"type":"Point"}
}