{
  "type": "Feature",
  "properties": {
    "iso:country":"US",
    "sg:address":"26 Highwood Rd",
    "sg:city":"Denville",
    "sg:classifiers":[
        {
            "category":"Building & Trades",
            "subcategory":"Electrical",
            "type":"Services"
        }
    ],
    "sg:phone":"+1 973 625 9050",
    "sg:postcode":"07834",
    "sg:province":"NJ",
    "sg:tags":[
        "electrical",
        "contractor"
    ],
    "wof:name":"Deegan Electrical Contracting",
    "wof:placetype":"venue"
},
  "geometry": {"coordinates":[-74.462829,40.879505],"type":"Point"}
}