{
  "type": "Feature",
  "properties": {
    "addr:full":"3464 US Hwy 9 Freehold NJ 07728",
    "addr:housenumber":"3464",
    "addr:postcode":"07728",
    "addr:street":"Us Hwy 9",
    "iso:country":"US",
    "sg:address":"3464 US Hwy 9",
    "sg:city":"Freehold",
    "sg:classifiers":[
        {
            "category":"Freight",
            "type":"Transportation"
        }
    ],
    "sg:phone":"+1 732 761 8420",
    "sg:postcode":"07728",
    "sg:province":"NJ",
    "sg:tags":[
        "commercial",
        "storage"
    ],
    "wof:name":"United Stor-All Ctr",
    "wof:placetype":"venue"
},
  "geometry": {"coordinates":[-74.272808,40.230843],"type":"Point"}
}