{
  "type": "Feature",
  "properties": {
    "addr:full":"282 South Ave Fanwood NJ 07023",
    "addr:housenumber":"282",
    "addr:postcode":"07023",
    "addr:street":"South Ave",
    "iso:country":"US",
    "sg:address":"282 South Ave",
    "sg:city":"Fanwood",
    "sg:classifiers":[
        {
            "category":"Professional",
            "subcategory":"Accounting & Tax Preparation",
            "type":"Services"
        }
    ],
    "sg:phone":"+1 908 889 9500",
    "sg:postcode":"07023",
    "sg:province":"NJ",
    "sg:tags":[
        "accountant"
    ],
    "wof:name":"Schembre & Gannon",
    "wof:placetype":"venue"
},
  "geometry": {"coordinates":[-74.383377,40.640889],"type":"Point"}
}