{
  "type": "Feature",
  "properties": {
    "iso:country":"US",
    "sg:address":"119 William St",
    "sg:city":"Middlesex",
    "sg:classifiers":[
        {
            "category":"Building & Trades",
            "subcategory":"Electrical",
            "type":"Services"
        }
    ],
    "sg:phone":"+1 732 564 9449",
    "sg:postcode":"08846",
    "sg:province":"NJ",
    "sg:tags":[
        "electric",
        "contractor"
    ],
    "wof:name":"ALC Electrical Contractors",
    "wof:placetype":"venue"
},
  "geometry": {"coordinates":[-74.48878999999999,40.57012],"type":"Point"}
}