{
  "type": "Feature",
  "properties": {
    "iso:country":"US",
    "sg:address":"4 S West Ave",
    "sg:city":"Wenonah",
    "sg:classifiers":[
        {
            "category":"Government",
            "subcategory":"Post Office",
            "type":"Public Place"
        }
    ],
    "sg:phone":"+1 856 468 6156",
    "sg:postcode":"08090",
    "sg:province":"NJ",
    "sg:tags":[
        "postal",
        "us"
    ],
    "wof:name":"US Post Office",
    "wof:placetype":"venue"
},
  "geometry": {"coordinates":[-75.150839,39.790703],"type":"Point"}
}