{
  "type": "Feature",
  "properties": {
    "iso:country":"US",
    "sg:address":"210 Ryders Ln",
    "sg:city":"Milltown",
    "sg:classifiers":[
        {
            "category":"Restaurant",
            "type":"Food & Drink"
        }
    ],
    "sg:phone":"+1   ",
    "sg:postcode":"08850",
    "sg:province":"NJ",
    "sg:tags":[
        "eating"
    ],
    "wof:name":"Fresco",
    "wof:placetype":"venue"
},
  "geometry": {"coordinates":[-74.424553,40.453818],"type":"Point"}
}