{
  "type": "Feature",
  "properties": {
    "addr:full":"139 Harristown Rd Glen Rock NJ 07452",
    "addr:housenumber":"139",
    "addr:postcode":"07452",
    "addr:street":"Harristown Rd",
    "iso:country":"US",
    "sg:address":"139 Harristown Rd",
    "sg:city":"Glen Rock",
    "sg:classifiers":[
        {
            "category":"Professional",
            "subcategory":"Accounting & Tax Preparation",
            "type":"Services"
        }
    ],
    "sg:phone":"+1 201 447 2501",
    "sg:postcode":"07452",
    "sg:province":"NJ",
    "sg:tags":[
        "billing"
    ],
    "wof:name":"Renal Institute-Central NJ",
    "wof:placetype":"venue"
},
  "geometry": {"coordinates":[-74.139864,40.951049],"type":"Point"}
}