{
  "type": "Feature",
  "properties": {
    "addr:full":"43 Saint Andrews Dr Westampton NJ 08087",
    "addr:housenumber":"43",
    "addr:postcode":"08087",
    "addr:street":"Saint Andrews Dr",
    "iso:country":"US",
    "sg:address":"43 Saint Andrews Dr",
    "sg:city":"Westampton",
    "sg:classifiers":[
        {
            "category":"Cinema",
            "subcategory":"Movie Rental",
            "type":"Entertainment"
        }
    ],
    "sg:phone":"+1 609 265 2669",
    "sg:postcode":"08087",
    "sg:province":"NJ",
    "sg:tags":[
        "leasing",
        "video",
        "disc",
        "tape"
    ],
    "wof:name":"J & L Video Svc",
    "wof:placetype":"venue"
},
  "geometry": {"coordinates":[-74.362427,39.581429],"type":"Point"}
}