{
  "type": "Feature",
  "properties": {
    "addr:full":"84 Fair Lawn Ave Fair Lawn NJ 07410",
    "addr:housenumber":"84",
    "addr:postcode":"07410",
    "addr:street":"Fair Lawn Ave",
    "iso:country":"US",
    "sg:address":"84 Fair Lawn Ave",
    "sg:city":"Fair Lawn",
    "sg:classifiers":[
        {
            "category":"Retail",
            "subcategory":"Laundry & Dry Cleaning",
            "type":"Services"
        }
    ],
    "sg:phone":"+1 201 794 0345",
    "sg:postcode":"07410",
    "sg:province":"NJ",
    "sg:tags":[
        "cleaners",
        "rug",
        "carpet"
    ],
    "wof:name":"Al's Carpet Cleaning",
    "wof:placetype":"venue"
},
  "geometry": {"coordinates":[-74.120777,40.938989],"type":"Point"}
}