{
  "type": "Feature",
  "properties": {
    "addr:full":"599 Bloomfield Ave Bloomfield NJ 07003",
    "addr:housenumber":"599",
    "addr:postcode":"07003",
    "addr:street":"Bloomfield Ave",
    "iso:country":"US",
    "sg:address":"599 Bloomfield Ave",
    "sg:city":"Bloomfield",
    "sg:classifiers":[
        {
            "category":"Shopping",
            "subcategory":"Shoes",
            "type":"Retail Goods"
        }
    ],
    "sg:phone":"+1 973 743 2237",
    "sg:postcode":"07003",
    "sg:province":"NJ",
    "wof:name":"Lou Rocco Shoe Boutique",
    "wof:placetype":"venue"
},
  "geometry": {"coordinates":[-74.198577,40.794563],"type":"Point"}
}