{
  "type": "Feature",
  "properties": {
    "addr:full":"930 Pelican Dr Lanoka Harbor NJ 08734",
    "addr:housenumber":"930",
    "addr:postcode":"08734",
    "addr:street":"Pelican Dr Lanoka",
    "iso:country":"US",
    "sg:address":"930 Pelican Dr",
    "sg:city":"Lanoka Harbor",
    "sg:classifiers":[
        {
            "category":"Building & Trades",
            "subcategory":"Construction",
            "type":"Services"
        }
    ],
    "sg:phone":"+1 609 693 8142",
    "sg:postcode":"08734",
    "sg:province":"NJ",
    "sg:tags":[
        "contractor"
    ],
    "wof:name":"D & B Homes Inc",
    "wof:placetype":"venue"
},
  "geometry": {"coordinates":[-74.147204,39.867967],"type":"Point"}
}