{
  "type": "Feature",
  "properties": {
    "iso:country":"US",
    "sg:address":"346 Avenel St",
    "sg:city":"Woodbridge",
    "sg:classifiers":[
        {
            "category":"Government",
            "subcategory":"Office",
            "type":"Public Place"
        }
    ],
    "sg:phone":"+1   ",
    "sg:postcode":"07001",
    "sg:province":"NJ",
    "sg:tags":[
        "executive"
    ],
    "wof:name":"Board of Fire Commissioners",
    "wof:placetype":"venue"
},
  "geometry": {"coordinates":[-74.284119,40.579889],"type":"Point"}
}