{
  "type": "Feature",
  "properties": {
    "iso:country":"US",
    "sg:address":"277 Westwood Ave",
    "sg:city":"Westwood",
    "sg:classifiers":[
        {
            "category":"Shopping",
            "subcategory":"Gifts & Souvenirs",
            "type":"Retail Goods"
        }
    ],
    "sg:phone":"+1 201 666 1550",
    "sg:postcode":"07675",
    "sg:province":"NJ",
    "sg:tags":[
        "shop"
    ],
    "wof:name":"You Name It Personalized Gifts",
    "wof:placetype":"venue"
},
  "geometry": {"coordinates":[-74.030039,40.992922],"type":"Point"}
}