{
  "type": "Feature",
  "properties": {
    "iso:country":"US",
    "sg:address":"46 Karen Dr",
    "sg:city":"Mahwah",
    "sg:classifiers":[
        {
            "category":"Building & Trades",
            "subcategory":"Construction",
            "type":"Services"
        }
    ],
    "sg:phone":"+1 201 529 4092",
    "sg:postcode":"07430",
    "sg:province":"NJ",
    "sg:tags":[
        "concrete",
        "contractor"
    ],
    "wof:name":"Halka Construction Co Inc",
    "wof:placetype":"venue"
},
  "geometry": {"coordinates":[-74.149744,41.090205],"type":"Point"}
}