{
  "type": "Feature",
  "properties": {
    "addr:full":"603 E 2nd St Plainfield NJ 07060",
    "addr:housenumber":"603",
    "addr:postcode":"07060",
    "addr:street":"E 2Nd St",
    "iso:country":"US",
    "sg:address":"603 E 2nd St",
    "sg:city":"Plainfield",
    "sg:classifiers":[
        {
            "category":"Manufacturing",
            "subcategory":"Electronics",
            "type":"Manufacturing & Wholesale Goods"
        }
    ],
    "sg:phone":"+1 908 755 7038",
    "sg:postcode":"07060",
    "sg:province":"NJ",
    "sg:tags":[
        "electronic",
        "capacitor",
        "mfg"
    ],
    "wof:name":"Kemet International",
    "wof:placetype":"venue"
},
  "geometry": {"coordinates":[-74.41541100000001,40.625441],"type":"Point"}
}