{
  "type": "Feature",
  "properties": {
    "addr:full":"3268 Middletown Walk Camden NJ 08104",
    "addr:housenumber":"3268",
    "addr:postcode":"08104",
    "addr:street":"Middletown Walk",
    "iso:country":"US",
    "sg:address":"3268 Middletown Walk",
    "sg:city":"Camden",
    "sg:classifiers":[
        {
            "category":"Building & Trades",
            "subcategory":"Construction",
            "type":"Services"
        }
    ],
    "sg:phone":"+1 856 486 4522",
    "sg:postcode":"08104",
    "sg:province":"NJ",
    "sg:tags":[
        "masonry",
        "contractor"
    ],
    "wof:name":"Thompson Masonry",
    "wof:placetype":"venue"
},
  "geometry": {"coordinates":[-75.097606,39.902735],"type":"Point"}
}