{
  "type": "Feature",
  "properties": {
    "addr:full":"411 Poets Way Mahwah NJ 07430",
    "addr:housenumber":"411",
    "addr:postcode":"07430",
    "addr:street":"Poets Way",
    "iso:country":"US",
    "sg:address":"411 Poets Way",
    "sg:city":"Mahwah",
    "sg:classifiers":[
        {
            "category":"Building & Trades",
            "subcategory":"Construction",
            "type":"Services"
        }
    ],
    "sg:phone":"+1 201 532 8265",
    "sg:postcode":"07430",
    "sg:province":"NJ",
    "sg:tags":[
        "house",
        "general",
        "contractor"
    ],
    "wof:name":"D & R Construction",
    "wof:placetype":"venue"
},
  "geometry": {"coordinates":[-74.16673900000001,41.071037],"type":"Point"}
}