{
  "type": "Feature",
  "properties": {
    "iso:country":"US",
    "sg:address":"50 Chestnut Ridge Rd",
    "sg:city":"Montvale",
    "sg:classifiers":[
        {
            "category":"Real Estate",
            "subcategory":"Real Estate Operator",
            "type":"Services"
        }
    ],
    "sg:phone":"+1   ",
    "sg:postcode":"07645",
    "sg:province":"NJ",
    "sg:tags":[
        "building",
        "nonresidential"
    ],
    "wof:name":"H C B Associates",
    "wof:placetype":"venue"
},
  "geometry": {"coordinates":[-74.070284,41.048567],"type":"Point"}
}