{
  "type": "Feature",
  "properties": {
    "iso:country":"US",
    "sg:address":"230 Centre St",
    "sg:city":"Nutley",
    "sg:classifiers":[
        {
            "category":"Insurance",
            "subcategory":"Insurance Agent",
            "type":"Services"
        }
    ],
    "sg:phone":"+1 973 562 0006",
    "sg:postcode":"07110",
    "sg:province":"NJ",
    "wof:name":"Benefit Providers",
    "wof:placetype":"venue"
},
  "geometry": {"coordinates":[-74.15482,40.812024],"type":"Point"}
}