{
  "type": "Feature",
  "properties": {
    "iso:country":"US",
    "sg:address":"789 Farnsworth Ave",
    "sg:city":"Bordentown",
    "sg:classifiers":[
        {
            "category":"Real Estate",
            "subcategory":"Real Estate Services",
            "type":"Services"
        },
        {
            "category":"Banks & Credit Unions",
            "subcategory":"Investment Brokerage",
            "type":"Services"
        },
        {
            "category":"Banks & Credit Unions",
            "subcategory":"Bank",
            "type":"Services"
        },
        {
            "category":"Banks & Credit Unions",
            "subcategory":"Financial Services",
            "type":"Services"
        }
    ],
    "sg:phone":"+1 609 227 2020",
    "sg:postcode":"08505",
    "sg:province":"NJ",
    "sg:tags":[
        "commercial",
        "loan",
        "saving",
        "security",
        "mortgage"
    ],
    "sg:website":"http://www.sterlingnj.com",
    "wof:name":"Sterling Bank",
    "wof:placetype":"venue"
},
  "geometry": {"coordinates":[-74.70590199999999,40.138526],"type":"Point"}
}