{
  "type": "Feature",
  "properties": {
    "addr:full":"1 Tess Dr Lafayette NJ 07848",
    "addr:housenumber":"1",
    "addr:postcode":"07848",
    "addr:street":"Tess Dr",
    "iso:country":"US",
    "sg:address":"1 Tess Dr",
    "sg:city":"Lafayette",
    "sg:classifiers":[
        {
            "category":"Real Estate",
            "subcategory":"Real Estate Operator",
            "type":"Services"
        }
    ],
    "sg:phone":"+1   ",
    "sg:postcode":"07848",
    "sg:province":"NJ",
    "sg:tags":[
        "mobile",
        "home",
        "site"
    ],
    "wof:name":"Carriage Acres",
    "wof:placetype":"venue"
},
  "geometry": {"coordinates":[-74.720804,41.088422],"type":"Point"}
}