{
  "type": "Feature",
  "properties": {
    "addr:full":"341 Michele Pl Carlstadt NJ 07072",
    "addr:housenumber":"341",
    "addr:postcode":"07072",
    "addr:street":"Michele Pl",
    "iso:country":"US",
    "sg:address":"341 Michele Pl",
    "sg:city":"Carlstadt",
    "sg:classifiers":[
        {
            "category":"Shopping",
            "type":"Retail Goods"
        }
    ],
    "sg:phone":"+1 201 438 0404",
    "sg:postcode":"07072",
    "sg:province":"NJ",
    "sg:tags":[
        "equipment",
        "r",
        "electrical",
        "merchandise"
    ],
    "wof:name":"Shields Solutions Inc",
    "wof:placetype":"venue"
},
  "geometry": {"coordinates":[-74.06278399999999,40.816714],"type":"Point"}
}