{
  "type": "Feature",
  "properties": {
    "iso:country":"US",
    "sg:address":"162 Knickerbocker Ave",
    "sg:city":"Hillsdale",
    "sg:classifiers":[
        {
            "category":"Professional",
            "subcategory":"Art Services",
            "type":"Services"
        },
        {
            "category":"Professional",
            "subcategory":"Computer Services",
            "type":"Services"
        }
    ],
    "sg:phone":"+1 201 666 0922",
    "sg:postcode":"07642",
    "sg:province":"NJ",
    "sg:tags":[
        "graphic",
        "datum",
        "designer"
    ],
    "wof:name":"By George Creative Inc",
    "wof:placetype":"venue"
},
  "geometry": {"coordinates":[-74.038805,41.008297],"type":"Point"}
}