{
  "type": "Feature",
  "properties": {
    "iso:country":"US",
    "sg:address":"120 Massachusetts Ave",
    "sg:city":"Lakewood",
    "sg:classifiers":[
        {
            "category":"Building & Trades",
            "subcategory":"Landscaping Services",
            "type":"Services"
        }
    ],
    "sg:phone":"+1 732 367 0580",
    "sg:postcode":"08701",
    "sg:province":"NJ",
    "sg:tags":[
        "landscape",
        "contractor"
    ],
    "wof:name":"Howard Payne Landscaping Inc",
    "wof:placetype":"venue"
},
  "geometry": {"coordinates":[-74.227524,40.07207],"type":"Point"}
}