{
  "type": "Feature",
  "properties": {
    "iso:country":"US",
    "sg:address":"410 State Rte 23",
    "sg:city":"Pompton Plains",
    "sg:classifiers":[
        {
            "category":"Professional",
            "subcategory":"Accounting & Tax Preparation",
            "type":"Services"
        }
    ],
    "sg:phone":"+1 973 616 6634",
    "sg:postcode":"07444",
    "sg:province":"NJ",
    "sg:tags":[
        "return",
        "filing"
    ],
    "wof:name":"H & R Block Tax Svc",
    "wof:placetype":"venue"
},
  "geometry": {"coordinates":[-74.284713,40.965765],"type":"Point"}
}