{
  "type": "Feature",
  "properties": {
    "addr:full":"85 Stein Ave Wallington NJ 07057",
    "addr:housenumber":"85",
    "addr:postcode":"07057",
    "addr:street":"Stein Ave",
    "iso:country":"US",
    "sg:address":"85 Stein Ave",
    "sg:city":"Wallington",
    "sg:classifiers":[
        {
            "category":"Retail",
            "subcategory":"Repair Shop",
            "type":"Services"
        }
    ],
    "sg:phone":"+1   ",
    "sg:postcode":"07057",
    "sg:province":"NJ",
    "wof:name":"Emtech Services",
    "wof:placetype":"venue"
},
  "geometry": {"coordinates":[-74.102756,40.855195],"type":"Point"}
}