{
  "type": "Feature",
  "properties": {
    "addr:full":"7701 Park Ave Merchantville NJ 08109",
    "addr:housenumber":"7701",
    "addr:postcode":"08109",
    "addr:street":"Park Ave",
    "iso:country":"US",
    "sg:address":"7701 Park Ave",
    "sg:city":"Merchantville",
    "sg:classifiers":[
        {
            "category":"Building & Trades",
            "subcategory":"Cleaning & Sanitation",
            "type":"Services"
        }
    ],
    "sg:phone":"+1   ",
    "sg:postcode":"08109",
    "sg:province":"NJ",
    "sg:tags":[
        "restoration"
    ],
    "wof:name":"SERVPRO",
    "wof:placetype":"venue"
},
  "geometry": {"coordinates":[-75.032037,39.960393],"type":"Point"}
}