{
  "type": "Feature",
  "properties": {
    "iso:country":"US",
    "sg:address":"194 Jefferson St",
    "sg:city":"Passaic",
    "sg:classifiers":[
        {
            "category":"Shopping",
            "subcategory":"Shoes",
            "type":"Retail Goods"
        }
    ],
    "sg:phone":"+1 973 777 0841",
    "sg:postcode":"07055",
    "sg:province":"NJ",
    "sg:tags":[
        "store"
    ],
    "wof:name":"Roman Sandal Inc the",
    "wof:placetype":"venue"
},
  "geometry": {"coordinates":[-74.12629699999999,40.8619],"type":"Point"}
}