{
  "type": "Feature",
  "properties": {
    "iso:country":"US",
    "sg:address":"400 Frank W Burr Blvd Ste 65",
    "sg:city":"Teaneck",
    "sg:classifiers":[
        {
            "category":"Banks & Credit Unions",
            "subcategory":"Bank",
            "type":"Services"
        }
    ],
    "sg:phone":"+1 201 525 5008",
    "sg:postcode":"07666",
    "sg:province":"NJ",
    "sg:website":"www.pnc.com",
    "wof:name":"Pnc Bank",
    "wof:placetype":"venue"
},
  "geometry": {"coordinates":[-74.005624,40.873941],"type":"Point"}
}