{
  "type": "Feature",
  "properties": {
    "addr:full":"1600 Arctic Ave Atlantic City NJ 08401",
    "addr:housenumber":"1600",
    "addr:postcode":"08401",
    "addr:street":"Arctic Ave",
    "iso:country":"US",
    "sg:address":"1600 Arctic Ave",
    "sg:city":"Atlantic City",
    "sg:classifiers":[
        {
            "category":"Shopping",
            "subcategory":"Florist",
            "type":"Retail Goods"
        }
    ],
    "sg:phone":"+1 609 344 4499",
    "sg:postcode":"08401",
    "sg:province":"NJ",
    "wof:name":"Flower World Intl",
    "wof:placetype":"venue"
},
  "geometry": {"coordinates":[-74.43221699999999,39.36239],"type":"Point"}
}