{
  "type": "Feature",
  "properties": {
    "addr:full":"457 2nd St Jersey City NJ 07302",
    "addr:housenumber":"457",
    "addr:postcode":"07302",
    "addr:street":"2Nd St",
    "iso:country":"US",
    "sg:address":"457 2nd St",
    "sg:city":"Jersey City",
    "sg:classifiers":[
        {
            "category":"Wholesale",
            "subcategory":"Durable Goods & Equipment",
            "type":"Manufacturing & Wholesale Goods"
        }
    ],
    "sg:phone":"+1 201 659 8086",
    "sg:postcode":"07302",
    "sg:province":"NJ",
    "sg:tags":[
        "exporter"
    ],
    "wof:name":"Sargisoff Export Corp",
    "wof:placetype":"venue"
},
  "geometry": {"coordinates":[-74.053383,40.723645],"type":"Point"}
}