{
  "type": "Feature",
  "properties": {
    "iso:country":"US",
    "sg:address":"22 Coventry Sq",
    "sg:city":"Trenton",
    "sg:classifiers":[
        {
            "category":"Professional",
            "subcategory":"Accounting & Tax Preparation",
            "type":"Services"
        }
    ],
    "sg:phone":"+1 609 883 4614",
    "sg:postcode":"08628",
    "sg:province":"NJ",
    "wof:name":"Eng Bookkeeping",
    "wof:placetype":"venue"
},
  "geometry": {"coordinates":[-74.837779,40.270618],"type":"Point"}
}