{
  "type": "Feature",
  "properties": {
    "iso:country":"US",
    "sg:address":"19 Budd Lake Heights Rd",
    "sg:city":"Budd Lake",
    "sg:classifiers":[
        {
            "category":"Professional",
            "subcategory":"Research",
            "type":"Services"
        },
        {
            "category":"Wholesale",
            "subcategory":"Electrical",
            "type":"Manufacturing & Wholesale Goods"
        }
    ],
    "sg:phone":"+1 973 347 1500",
    "sg:postcode":"07828",
    "sg:province":"NJ",
    "sg:tags":[
        "instrument",
        "weather",
        "commercial",
        "nonphysical"
    ],
    "sg:website":"www.researchwithcor.com",
    "wof:name":"Customer Opinion Research Inc",
    "wof:placetype":"venue"
},
  "geometry": {"coordinates":[-74.755224,40.887153],"type":"Point"}
}