{
  "type": "Feature",
  "properties": {
    "iso:country":"US",
    "sg:address":"231 W 10th Ave",
    "sg:city":"Wildwood",
    "sg:classifiers":[
        {
            "category":"Recreation",
            "type":"Entertainment"
        }
    ],
    "sg:phone":"+1 609 523 2620",
    "sg:postcode":"08260",
    "sg:province":"NJ",
    "sg:tags":[
        "boating",
        "charter",
        "boat"
    ],
    "wof:name":"North Wildwood Water Sports II Inc",
    "wof:placetype":"venue"
},
  "geometry": {"coordinates":[-74.80259700000001,39.005001],"type":"Point"}
}