{
  "type": "Feature",
  "properties": {
    "addr:full":"35 E 40th St Paterson NJ 07514",
    "addr:housenumber":"35",
    "addr:postcode":"07514",
    "addr:street":"E 40Th St",
    "iso:country":"US",
    "sg:address":"35 E 40th St",
    "sg:city":"Paterson",
    "sg:classifiers":[
        {
            "category":"Retail",
            "subcategory":"Auto Repair",
            "type":"Services"
        }
    ],
    "sg:phone":"+1 973 569 3431",
    "sg:postcode":"07514",
    "sg:province":"NJ",
    "sg:tags":[
        "automotive"
    ],
    "wof:name":"Marshalls Service Center",
    "wof:placetype":"venue"
},
  "geometry": {"coordinates":[-74.134541,40.921153],"type":"Point"}
}