{
  "type": "Feature",
  "properties": {
    "addr:full":"470 State Rte 79 Morganville NJ 07751",
    "addr:housenumber":"470",
    "addr:postcode":"07751",
    "addr:street":"State Rte 79",
    "iso:country":"US",
    "sg:address":"470 State Rte 79",
    "sg:city":"Morganville",
    "sg:classifiers":[
        {
            "category":"Professional",
            "subcategory":"Research",
            "type":"Services"
        }
    ],
    "sg:phone":"+1 732 591 5450",
    "sg:postcode":"07751",
    "sg:province":"NJ",
    "sg:tags":[
        "environmental",
        "ecological"
    ],
    "wof:name":"International Bio-Solutions",
    "wof:placetype":"venue"
},
  "geometry": {"coordinates":[-74.241688,40.382101],"type":"Point"}
}