{
  "type": "Feature",
  "properties": {
    "addr:full":"255 E State Rt 4 Paramus NJ 07652",
    "addr:housenumber":"255",
    "addr:postcode":"07652",
    "addr:street":"E State Rt 4",
    "iso:country":"US",
    "sg:address":"255 E State Rt 4",
    "sg:city":"Paramus",
    "sg:classifiers":[
        {
            "category":"Personal",
            "type":"Services"
        }
    ],
    "sg:phone":"+1 201 845 8494",
    "sg:postcode":"07652",
    "sg:province":"NJ",
    "sg:tags":[
        "sewing",
        "alteration"
    ],
    "wof:name":"Heman Big & Tall Mens Shop",
    "wof:placetype":"venue"
},
  "geometry": {"coordinates":[-74.050797,40.915298],"type":"Point"}
}