{
  "type": "Feature",
  "properties": {
    "iso:country":"US",
    "sg:address":"66 New Rd",
    "sg:city":"Lambertville",
    "sg:classifiers":[
        {
            "category":"Professional",
            "subcategory":"Accounting & Tax Preparation",
            "type":"Services"
        }
    ],
    "sg:phone":"+1 609 730 0180",
    "sg:postcode":"08530",
    "sg:province":"NJ",
    "wof:name":"Kevin P Lauricella CPA",
    "wof:placetype":"venue"
},
  "geometry": {"coordinates":[-74.83201800000001,40.367194],"type":"Point"}
}