{
  "type": "Feature",
  "properties": {
    "iso:country":"US",
    "sg:address":"717 Delsea Dr N",
    "sg:city":"Glassboro",
    "sg:classifiers":[
        {
            "category":"Retail",
            "subcategory":"Laundry & Dry Cleaning",
            "type":"Services"
        }
    ],
    "sg:phone":"+1 856 589 0227",
    "sg:postcode":"08028",
    "sg:province":"NJ",
    "sg:tags":[
        "drycleaning",
        "plant"
    ],
    "wof:name":"Collegetown Cleaners",
    "wof:placetype":"venue"
},
  "geometry": {"coordinates":[-75.11516399999999,39.72122],"type":"Point"}
}