{
  "type": "Feature",
  "properties": {
    "iso:country":"US",
    "sg:address":"3 Lyons Ave",
    "sg:city":"Fair Lawn",
    "sg:classifiers":[
        {
            "category":"Building & Trades",
            "subcategory":"Construction",
            "type":"Services"
        }
    ],
    "sg:phone":"+1 201 475 1548",
    "sg:postcode":"07410",
    "sg:province":"NJ",
    "sg:tags":[
        "contractor"
    ],
    "wof:name":"Dv Drywall",
    "wof:placetype":"venue"
},
  "geometry": {"coordinates":[-74.132175,40.931799],"type":"Point"}
}