{
  "type": "Feature",
  "properties": {
    "addr:full":"648 State Rte 70 Lakehurst NJ 08733",
    "addr:housenumber":"648",
    "addr:postcode":"08733",
    "addr:street":"State Rte 70",
    "iso:country":"US",
    "sg:address":"648 State Rte 70",
    "sg:city":"Lakehurst",
    "sg:classifiers":[
        {
            "category":"Shopping",
            "subcategory":"Pharmacy",
            "type":"Retail Goods"
        }
    ],
    "sg:phone":"+1   ",
    "sg:postcode":"08733",
    "sg:province":"NJ",
    "sg:tags":[
        "drug",
        "store"
    ],
    "wof:name":"Rite Aid",
    "wof:placetype":"venue"
},
  "geometry": {"coordinates":[-74.32455299999999,40.012705],"type":"Point"}
}