{
  "type": "Feature",
  "properties": {
    "addr:full":"379 Monmouth Rd West Long Branch NJ 07764",
    "addr:housenumber":"379",
    "addr:postcode":"07764",
    "addr:street":"Monmouth Rd",
    "iso:country":"US",
    "sg:address":"379 Monmouth Rd",
    "sg:city":"West Long Branch",
    "sg:classifiers":[
        {
            "category":"Building & Trades",
            "subcategory":"Construction",
            "type":"Services"
        }
    ],
    "sg:phone":"+1 732 571 5967",
    "sg:postcode":"07764",
    "sg:province":"NJ",
    "sg:tags":[
        "marking",
        "maintenance",
        "parking"
    ],
    "wof:name":"West Long Branch Public Works",
    "wof:placetype":"venue"
},
  "geometry": {"coordinates":[-74.018462,40.282296],"type":"Point"}
}