{
  "type": "Feature",
  "properties": {
    "iso:country":"US",
    "sg:address":"90 Dayton Ave",
    "sg:city":"Passaic",
    "sg:classifiers":[
        {
            "category":"Home & Garden",
            "subcategory":"Building Materials",
            "type":"Retail Goods"
        }
    ],
    "sg:phone":"+1 973 471 2858",
    "sg:postcode":"07055",
    "sg:province":"NJ",
    "sg:tags":[
        "equipment",
        "fixture",
        "lighting"
    ],
    "sg:website":"www.yosgad.com",
    "wof:name":"Yosgad Lighting Industries",
    "wof:placetype":"venue"
},
  "geometry": {"coordinates":[-74.120003,40.872501],"type":"Point"}
}