{
  "type": "Feature",
  "properties": {
    "addr:full":"141 Market St Kenilworth NJ 07033",
    "addr:housenumber":"141",
    "addr:postcode":"07033",
    "addr:street":"Market St",
    "iso:country":"US",
    "sg:address":"141 Market St",
    "sg:city":"Kenilworth",
    "sg:classifiers":[
        {
            "category":"Manufacturing",
            "subcategory":"Food",
            "type":"Manufacturing & Wholesale Goods"
        }
    ],
    "sg:phone":"+1 732 303 0855",
    "sg:postcode":"07033",
    "sg:province":"NJ",
    "sg:tags":[
        "frozen",
        "processor"
    ],
    "wof:name":"Country Fresh Foods",
    "wof:placetype":"venue"
},
  "geometry": {"coordinates":[-74.279714,40.671478],"type":"Point"}
}