{
  "type": "Feature",
  "properties": {
    "addr:full":"357 Grand St Paterson NJ 07505",
    "addr:housenumber":"357",
    "addr:postcode":"07505",
    "addr:street":"Grand St",
    "iso:country":"US",
    "sg:address":"357 Grand St",
    "sg:city":"Paterson",
    "sg:classifiers":[
        {
            "category":"Travel",
            "subcategory":"Travel Agent",
            "type":"Entertainment"
        }
    ],
    "sg:phone":"+1 973 684 3960",
    "sg:postcode":"07505",
    "sg:province":"NJ",
    "sg:tags":[
        "agency"
    ],
    "wof:name":"Quesada Travel Corp",
    "wof:placetype":"venue"
},
  "geometry": {"coordinates":[-74.173231,40.912203],"type":"Point"}
}