{
  "type": "Feature",
  "properties": {
    "iso:country":"US",
    "sg:address":"14 Orange Pl",
    "sg:city":"West Orange",
    "sg:classifiers":[
        {
            "category":"Professional",
            "subcategory":"Business Services",
            "type":"Services"
        }
    ],
    "sg:phone":"+1 973 736 8865",
    "sg:postcode":"07052",
    "sg:province":"NJ",
    "sg:tags":[
        "messenger"
    ],
    "wof:name":"Zip Messenger Svc",
    "wof:placetype":"venue"
},
  "geometry": {"coordinates":[-74.23206,40.792749],"type":"Point"}
}