{
  "type": "Feature",
  "properties": {
    "addr:full":"170 Franklin St Swedesboro NJ 08085",
    "addr:housenumber":"170",
    "addr:postcode":"08085",
    "addr:street":"Franklin St",
    "iso:country":"US",
    "sg:address":"170 Franklin St",
    "sg:city":"Swedesboro",
    "sg:classifiers":[
        {
            "category":"Wholesale",
            "subcategory":"Plants",
            "type":"Manufacturing & Wholesale Goods"
        }
    ],
    "sg:phone":"+1 856 467 4281",
    "sg:postcode":"08085",
    "sg:province":"NJ",
    "sg:tags":[
        "wreath",
        "grass",
        "dried"
    ],
    "wof:name":"Tatters & Twigs",
    "wof:placetype":"venue"
},
  "geometry": {"coordinates":[-75.303359,39.744643],"type":"Point"}
}