{
  "type": "Feature",
  "properties": {
    "addr:full":"86 Norfolk St Newark NJ 07103",
    "addr:housenumber":"86",
    "addr:postcode":"07103",
    "addr:street":"Norfolk St",
    "iso:country":"US",
    "sg:address":"86 Norfolk St",
    "sg:city":"Newark",
    "sg:classifiers":[
        {
            "category":"Autos & Motor Vehicles",
            "subcategory":"Auto Supplies",
            "type":"Retail Goods"
        }
    ],
    "sg:phone":"+1   ",
    "sg:postcode":"07103",
    "sg:province":"NJ",
    "sg:tags":[
        "repair",
        "general"
    ],
    "wof:name":"Rosales Tire Service Inc",
    "wof:placetype":"venue"
},
  "geometry": {"coordinates":[-74.18309000000001,40.745701],"type":"Point"}
}