{
  "type": "Feature",
  "properties": {
    "addr:full":"599 Chestnut St Union NJ 07083",
    "addr:housenumber":"599",
    "addr:postcode":"07083",
    "addr:street":"Chestnut St",
    "iso:country":"US",
    "sg:address":"599 Chestnut St",
    "sg:city":"Union",
    "sg:classifiers":[
        {
            "category":"Education",
            "subcategory":"Dance Studio",
            "type":"Public Place"
        }
    ],
    "sg:phone":"+1 908 688 4664",
    "sg:postcode":"07083",
    "sg:province":"NJ",
    "wof:name":"Cherney Dance Studio",
    "wof:placetype":"venue"
},
  "geometry": {"coordinates":[-74.269201,40.68513],"type":"Point"}
}