{
  "type": "Feature",
  "properties": {
    "iso:country":"US",
    "sg:address":"2508 Federal St",
    "sg:city":"Camden",
    "sg:classifiers":[
        {
            "category":"Professional",
            "subcategory":"Employment Agencies",
            "type":"Services"
        }
    ],
    "sg:phone":"+1   ",
    "sg:postcode":"08105",
    "sg:province":"NJ",
    "sg:tags":[
        "medical",
        "help",
        "supply"
    ],
    "wof:name":"Addcare Medical Staffing Svcs",
    "wof:placetype":"venue"
},
  "geometry": {"coordinates":[-75.088936,39.946032],"type":"Point"}
}