{
  "type": "Feature",
  "properties": {
    "addr:full":"322 Midland Ct West New York NJ 07093",
    "addr:housenumber":"322",
    "addr:postcode":"07093",
    "addr:street":"Midland Ct West",
    "iso:country":"US",
    "sg:address":"322 Midland Ct",
    "sg:city":"West New York",
    "sg:classifiers":[
        {
            "category":"Freight",
            "type":"Transportation"
        }
    ],
    "sg:phone":"+1 201 223 5574",
    "sg:postcode":"07093",
    "sg:province":"NJ",
    "sg:tags":[
        "sea",
        "foreign"
    ],
    "wof:name":"Moxica LLC",
    "wof:placetype":"venue"
},
  "geometry": {"coordinates":[-74.009429,40.782831],"type":"Point"}
}