{
  "type": "Feature",
  "properties": {
    "addr:full":"48 Mohican Dr Westfield NJ 07090",
    "addr:housenumber":"48",
    "addr:postcode":"07090",
    "addr:street":"Mohican Dr",
    "iso:country":"US",
    "sg:address":"48 Mohican Dr",
    "sg:city":"Westfield",
    "sg:classifiers":[
        {
            "category":"Building & Trades",
            "subcategory":"Plumbing",
            "type":"Services"
        }
    ],
    "sg:phone":"+1 908 789 1776",
    "sg:postcode":"07090",
    "sg:province":"NJ",
    "wof:name":"Bange Plumbing",
    "wof:placetype":"venue"
},
  "geometry": {"coordinates":[-74.329904,40.674362],"type":"Point"}
}