{
  "type": "Feature",
  "properties": {
    "iso:country":"US",
    "sg:address":"40 Hanover Rd",
    "sg:city":"East Hanover",
    "sg:classifiers":[
        {
            "category":"Building & Trades",
            "subcategory":"Construction",
            "type":"Services"
        }
    ],
    "sg:phone":"+1 973 887 5104",
    "sg:postcode":"07936",
    "sg:province":"NJ",
    "sg:tags":[
        "house"
    ],
    "wof:name":"Delfar Construction",
    "wof:placetype":"venue"
},
  "geometry": {"coordinates":[-74.37075299999999,40.801012],"type":"Point"}
}