{
  "type": "Feature",
  "properties": {
    "iso:country":"US",
    "sg:address":"335 N Franklin Tpke",
    "sg:city":"Ho Ho Kus",
    "sg:classifiers":[
        {
            "category":"Recreation",
            "type":"Entertainment"
        }
    ],
    "sg:phone":"+1 201 445 8311",
    "sg:postcode":"07423",
    "sg:province":"NJ",
    "sg:tags":[
        "historical"
    ],
    "sg:website":"www.thehermitage.org",
    "wof:name":"Hermitage",
    "wof:placetype":"venue"
},
  "geometry": {"coordinates":[-74.115233,41.005468],"type":"Point"}
}