{
  "type": "Feature",
  "properties": {
    "iso:country":"US",
    "sg:address":"458 W Browning Rd",
    "sg:city":"Bellmawr",
    "sg:classifiers":[
        {
            "category":"Retail",
            "subcategory":"Auto Rental",
            "type":"Services"
        }
    ],
    "sg:phone":"+1 856 931 9665",
    "sg:postcode":"08031",
    "sg:province":"NJ",
    "sg:tags":[
        "limousine"
    ],
    "wof:name":"Ocean Eleven West Limousine Inc",
    "wof:placetype":"venue"
},
  "geometry": {"coordinates":[-75.09860999999999,39.87071],"type":"Point"}
}