{
  "type": "Feature",
  "properties": {
    "iso:country":"US",
    "sg:address":"919 Main St",
    "sg:city":"Boonton",
    "sg:classifiers":[
        {
            "category":"Shopping",
            "subcategory":"Jewelry",
            "type":"Retail Goods"
        }
    ],
    "sg:phone":"+1 973 394 0304",
    "sg:postcode":"07005",
    "sg:province":"NJ",
    "sg:tags":[
        "jeweler"
    ],
    "wof:name":"Park Jewelers",
    "wof:placetype":"venue"
},
  "geometry": {"coordinates":[-74.41392399999999,40.906532],"type":"Point"}
}