{
  "type": "Feature",
  "properties": {
    "addr:full":"10 Elm Ct Bayonne NJ 07002",
    "addr:housenumber":"10",
    "addr:postcode":"07002",
    "addr:street":"Elm Ct",
    "iso:country":"US",
    "sg:address":"10 Elm Ct",
    "sg:city":"Bayonne",
    "sg:classifiers":[
        {
            "category":"Local Transit",
            "type":"Transportation"
        }
    ],
    "sg:phone":"+1 201 339 8234",
    "sg:postcode":"07002",
    "sg:province":"NJ",
    "sg:tags":[
        "leasing"
    ],
    "wof:name":"Big Gun Intl USA",
    "wof:placetype":"venue"
},
  "geometry": {"coordinates":[-74.12177,40.654592],"type":"Point"}
}