{
  "type": "Feature",
  "properties": {
    "iso:country":"US",
    "sg:address":"117 S Washington Ave",
    "sg:city":"Bergenfield",
    "sg:classifiers":[
        {
            "category":"Professional",
            "subcategory":"Accounting & Tax Preparation",
            "type":"Services"
        }
    ],
    "sg:phone":"+1 201 384 9450",
    "sg:postcode":"07621",
    "sg:province":"NJ",
    "sg:tags":[
        "bookkeeping",
        "general"
    ],
    "wof:name":"E G Enriquez & Co",
    "wof:placetype":"venue"
},
  "geometry": {"coordinates":[-73.99691,40.924232],"type":"Point"}
}