{
  "type": "Feature",
  "properties": {
    "addr:full":"600 Lake St Ramsey NJ 07446",
    "addr:housenumber":"600",
    "addr:postcode":"07446",
    "addr:street":"Lake St",
    "iso:country":"US",
    "sg:address":"600 Lake St",
    "sg:city":"Ramsey",
    "sg:classifiers":[
        {
            "category":"Wholesale",
            "subcategory":"Machinery & Supplies",
            "type":"Manufacturing & Wholesale Goods"
        }
    ],
    "sg:phone":"+1 201 825 0600",
    "sg:postcode":"07446",
    "sg:province":"NJ",
    "sg:tags":[
        "equipment",
        "industrial"
    ],
    "wof:name":"Halliburton Company",
    "wof:placetype":"venue"
},
  "geometry": {"coordinates":[-74.125142,41.059696],"type":"Point"}
}