{
  "type": "Feature",
  "properties": {
    "addr:full":"20 Hook Mountain Rd Pine Brook NJ 07058",
    "addr:housenumber":"20",
    "addr:postcode":"07058",
    "addr:street":"Hook Mountain Rd",
    "iso:country":"US",
    "sg:address":"20 Hook Mountain Rd",
    "sg:city":"Pine Brook",
    "sg:classifiers":[
        {
            "category":"Sports & Exercise",
            "subcategory":"Gym",
            "type":"Entertainment"
        }
    ],
    "sg:phone":"+1 973 244 2400",
    "sg:postcode":"07058",
    "sg:province":"NJ",
    "sg:tags":[
        "trainer"
    ],
    "sg:website":"www.curves.com",
    "wof:name":"Curves For Women",
    "wof:placetype":"venue"
},
  "geometry": {"coordinates":[-74.340401,40.859798],"type":"Point"}
}