{
  "type": "Feature",
  "properties": {
    "iso:country":"US",
    "sg:address":"112 US Hwy 9",
    "sg:city":"Englishtown",
    "sg:classifiers":[
        {
            "category":"Retail",
            "subcategory":"Repair Shop",
            "type":"Services"
        }
    ],
    "sg:phone":"+1 732 972 2171",
    "sg:postcode":"07726",
    "sg:province":"NJ",
    "sg:tags":[
        "custom",
        "art",
        "gallery",
        "framing"
    ],
    "wof:name":"Frame Decor & Gallery Inc",
    "wof:placetype":"venue"
},
  "geometry": {"coordinates":[-74.307748,40.347685],"type":"Point"}
}