{
  "type": "Feature",
  "properties": {
    "iso:country":"US",
    "sg:address":"240 Claremont Ave",
    "sg:city":"Montclair",
    "sg:classifiers":[
        {
            "category":"Real Estate",
            "subcategory":"Real Estate Operator",
            "type":"Services"
        }
    ],
    "sg:phone":"+1   ",
    "sg:postcode":"07042",
    "sg:province":"NJ",
    "sg:tags":[
        "commercial"
    ],
    "wof:name":"Chelsea Zak Group LLC",
    "wof:placetype":"venue"
},
  "geometry": {"coordinates":[-74.216675,40.817665],"type":"Point"}
}