{
  "type": "Feature",
  "properties": {
    "addr:full":"16 Route 46 Pine Brook NJ 07058",
    "addr:housenumber":"16",
    "addr:postcode":"07058",
    "addr:street":"Route 46",
    "iso:country":"US",
    "sg:address":"16 Route 46",
    "sg:city":"Pine Brook",
    "sg:classifiers":[
        {
            "category":"Sports & Exercise",
            "subcategory":"Gym",
            "type":"Entertainment"
        }
    ],
    "sg:phone":"+1 973 575 0052",
    "sg:postcode":"07058",
    "sg:province":"NJ",
    "sg:website":"www.snapfitness.com/pinebrook",
    "wof:name":"Snap Fitness of Pine Brook",
    "wof:placetype":"venue"
},
  "geometry": {"coordinates":[-74.316368,40.865489],"type":"Point"}
}