{
  "type": "Feature",
  "properties": {
    "addr:full":"100 Long Bow Cir Sewell NJ 08080",
    "addr:housenumber":"100",
    "addr:postcode":"08080",
    "addr:street":"Long Bow Cir",
    "iso:country":"US",
    "sg:address":"100 Long Bow Cir",
    "sg:city":"Sewell",
    "sg:classifiers":[
        {
            "category":"Organizations",
            "subcategory":"Professional Association",
            "type":"Services"
        },
        {
            "category":"Organizations",
            "subcategory":"Community Association",
            "type":"Services"
        }
    ],
    "sg:phone":"+1 856 232 0003",
    "sg:postcode":"08080",
    "sg:province":"NJ",
    "sg:tags":[
        "homeowner"
    ],
    "wof:name":"Hunt Club Condominium Assn",
    "wof:placetype":"venue"
},
  "geometry": {"coordinates":[-75.090891,39.77605],"type":"Point"}
}