{
  "type": "Feature",
  "properties": {
    "iso:country":"US",
    "sg:address":"189 Baldwin Rd",
    "sg:city":"Parsippany",
    "sg:classifiers":[
        {
            "category":"Professional",
            "type":"Services"
        }
    ],
    "sg:phone":"+1 973 334 8696",
    "sg:postcode":"07054",
    "sg:province":"NJ",
    "sg:tags":[
        "establishment"
    ],
    "wof:name":"Incarnata Sister OP",
    "wof:placetype":"venue"
},
  "geometry": {"coordinates":[-74.395235,40.864467],"type":"Point"}
}