{
  "type": "Feature",
  "properties": {
    "iso:country":"US",
    "sg:address":"80 Marion Dr",
    "sg:city":"Plainsboro",
    "sg:classifiers":[
        {
            "category":"Professional",
            "type":"Services"
        }
    ],
    "sg:phone":"+1   ",
    "sg:postcode":"08536",
    "sg:province":"NJ",
    "wof:name":"Amasun",
    "wof:placetype":"venue"
},
  "geometry": {"coordinates":[-74.578537,40.332021],"type":"Point"}
}