{
  "type": "Feature",
  "properties": {
    "iso:country":"US",
    "sg:address":"49 Avenue C",
    "sg:city":"Newark",
    "sg:classifiers":[
        {
            "category":"Building & Trades",
            "subcategory":"Locksmith",
            "type":"Services"
        }
    ],
    "sg:phone":"+1 888 267 1188",
    "sg:postcode":"07114",
    "sg:province":"NJ",
    "sg:tags":[
        "key"
    ],
    "wof:name":"Always Available 24 Hour Emergency Locksmith",
    "wof:placetype":"venue"
},
  "geometry": {"coordinates":[-74.173073,40.71857],"type":"Point"}
}