{
  "type": "Feature",
  "properties": {
    "addr:full":"14 US Hwy 46 Hackettstown NJ 07840",
    "addr:housenumber":"14",
    "addr:postcode":"07840",
    "addr:street":"Us Hwy 46",
    "iso:country":"US",
    "sg:address":"14 US Hwy 46",
    "sg:city":"Hackettstown",
    "sg:classifiers":[
        {
            "category":"Retail",
            "subcategory":"Veterinary Services",
            "type":"Services"
        }
    ],
    "sg:phone":"+1 908 852 3166",
    "sg:postcode":"07840",
    "sg:province":"NJ",
    "sg:tags":[
        "veterinarian"
    ],
    "wof:name":"Hackettstown Animal Hospital",
    "wof:placetype":"venue"
},
  "geometry": {"coordinates":[-74.821597,40.848571],"type":"Point"}
}