{
  "type": "Feature",
  "properties": {
    "addr:full":"308 Wooton St Boonton NJ 07005",
    "addr:housenumber":"308",
    "addr:postcode":"07005",
    "addr:street":"Wooton St",
    "iso:country":"US",
    "sg:address":"308 Wooton St",
    "sg:city":"Boonton",
    "sg:classifiers":[
        {
            "category":"Shopping",
            "subcategory":"Shoes",
            "type":"Retail Goods"
        }
    ],
    "sg:phone":"+1 973 257 2890",
    "sg:postcode":"07005",
    "sg:province":"NJ",
    "wof:name":"Payless Shoe Source",
    "wof:placetype":"venue"
},
  "geometry": {"coordinates":[-74.40051200000001,40.909045],"type":"Point"}
}