{
  "type": "Feature",
  "properties": {
    "iso:country":"US",
    "sg:address":"401 Hackensack Ave Fl 7E",
    "sg:city":"Hackensack",
    "sg:classifiers":[
        {
            "category":"Food & Beverages",
            "subcategory":"Liquor & Beverages",
            "type":"Retail Goods"
        }
    ],
    "sg:phone":"+1 201 678 0820",
    "sg:postcode":"07601",
    "sg:province":"NJ",
    "sg:tags":[
        "beer",
        "spirit",
        "wine"
    ],
    "wof:name":"Zayat Stables Llc",
    "wof:placetype":"venue"
},
  "geometry": {"coordinates":[-74.03332899999999,40.909029],"type":"Point"}
}