{
  "type": "Feature",
  "properties": {
    "addr:full":"11 Firethorn Dr Milford NJ 08848",
    "addr:housenumber":"11",
    "addr:postcode":"08848",
    "addr:street":"Firethorn Dr",
    "iso:country":"US",
    "sg:address":"11 Firethorn Dr",
    "sg:city":"Milford",
    "sg:classifiers":[
        {
            "category":"Organizations",
            "subcategory":"Religious Organization",
            "type":"Services"
        },
        {
            "category":"Real Estate",
            "subcategory":"Real Estate Services",
            "type":"Services"
        }
    ],
    "sg:phone":"+1 908 995 1070",
    "sg:postcode":"08848",
    "sg:province":"NJ",
    "sg:tags":[
        "company",
        "title"
    ],
    "wof:name":"DOC Settlement Svc",
    "wof:placetype":"venue"
},
  "geometry": {"coordinates":[-75.120503,40.593676],"type":"Point"}
}