{
  "type": "Feature",
  "properties": {
    "iso:country":"US",
    "sg:address":"120 Millburn Ave Ste 101",
    "sg:city":"Millburn",
    "sg:classifiers":[
        {
            "category":"Health Services",
            "subcategory":"Doctor",
            "type":"Services"
        }
    ],
    "sg:phone":"+1 973 376 0900",
    "sg:postcode":"07041",
    "sg:province":"NJ",
    "wof:name":"Suarez Norka J MD",
    "wof:placetype":"venue"
},
  "geometry": {"coordinates":[-74.290001,40.721699],"type":"Point"}
}