{
  "type": "Feature",
  "properties": {
    "addr:full":"18 Microlab Rd Livingston NJ 07039",
    "addr:housenumber":"18",
    "addr:postcode":"07039",
    "addr:street":"Microlab Rd",
    "iso:country":"US",
    "sg:address":"18 Microlab Rd",
    "sg:city":"Livingston",
    "sg:classifiers":[
        {
            "category":"Real Estate",
            "subcategory":"Real Estate Agent",
            "type":"Services"
        }
    ],
    "sg:phone":"+1 973 422 1975",
    "sg:postcode":"07039",
    "sg:province":"NJ",
    "wof:name":"Gruber Properties",
    "wof:placetype":"venue"
},
  "geometry": {"coordinates":[-74.34851999999999,40.801231],"type":"Point"}
}