{
  "type": "Feature",
  "properties": {
    "iso:country":"US",
    "sg:address":"20 12th St",
    "sg:city":"Hammonton",
    "sg:classifiers":[
        {
            "category":"Food & Beverages",
            "subcategory":"Liquor & Beverages",
            "type":"Retail Goods"
        }
    ],
    "sg:phone":"+1 609 567 4809",
    "sg:postcode":"08037",
    "sg:province":"NJ",
    "wof:name":"Hammonton's Main Street Lqrs",
    "wof:placetype":"venue"
},
  "geometry": {"coordinates":[-74.805348,39.634187],"type":"Point"}
}