{
  "type": "Feature",
  "properties": {
    "iso:country":"US",
    "sg:address":"74 Brick Blvd",
    "sg:city":"Brick",
    "sg:classifiers":[
        {
            "category":"Education",
            "subcategory":"Special Training",
            "type":"Public Place"
        },
        {
            "category":"Social Services",
            "type":"Services"
        }
    ],
    "sg:phone":"+1 732 279 0600",
    "sg:postcode":"08723",
    "sg:province":"NJ",
    "sg:tags":[
        "tutoring",
        "rehabilitation",
        "pediatric"
    ],
    "wof:name":"Pediatric Rehabilitation Svcs",
    "wof:placetype":"venue"
},
  "geometry": {"coordinates":[-74.14410599999999,40.025462],"type":"Point"}
}