{
  "type": "Feature",
  "properties": {
    "addr:full":"728 Pennington St Elizabeth NJ 07202",
    "addr:housenumber":"728",
    "addr:postcode":"07202",
    "addr:street":"Pennington St",
    "iso:country":"US",
    "sg:address":"728 Pennington St",
    "sg:city":"Elizabeth",
    "sg:classifiers":[
        {
            "category":"Organizations",
            "subcategory":"Religious Organization",
            "type":"Services"
        }
    ],
    "sg:phone":"+1 908 527 6924",
    "sg:postcode":"07202",
    "sg:province":"NJ",
    "wof:name":"Iglesia De Dios Ministirial",
    "wof:placetype":"venue"
},
  "geometry": {"coordinates":[-74.235617,40.662548],"type":"Point"}
}