{
  "type": "Feature",
  "properties": {
    "iso:country":"US",
    "sg:address":"480 Co Rd 520",
    "sg:city":"Marlboro",
    "sg:classifiers":[
        {
            "category":"Retail",
            "subcategory":"Veterinary Services",
            "type":"Services"
        }
    ],
    "sg:phone":"+1 732 946 8339",
    "sg:postcode":"07746",
    "sg:province":"NJ",
    "wof:name":"Brook Meadow Veterinary Hosp",
    "wof:placetype":"venue"
},
  "geometry": {"coordinates":[-74.241252,40.334257],"type":"Point"}
}