{
  "type": "Feature",
  "properties": {
    "addr:full":"598 Easton Ave New Brunswick NJ 08901",
    "addr:housenumber":"598",
    "addr:postcode":"08901",
    "addr:street":"Easton Ave",
    "iso:country":"US",
    "sg:address":"598 Easton Ave",
    "sg:city":"New Brunswick",
    "sg:classifiers":[
        {
            "category":"Restaurant",
            "type":"Food & Drink"
        }
    ],
    "sg:menulink":"http://www.allmenus.com/nj/new-brunswick/5579-steves-pizza/menu/",
    "sg:phone":"+1 732 247 0400",
    "sg:postcode":"08901",
    "sg:province":"NJ",
    "sg:tags":[
        "italian"
    ],
    "wof:name":"Steve's Pizza",
    "wof:placetype":"venue"
},
  "geometry": {"coordinates":[-74.467248,40.504964],"type":"Point"}
}