{
  "type": "Feature",
  "properties": {
    "addr:full":"1116 Almonesson Rd Woodbury NJ 08096",
    "addr:housenumber":"1116",
    "addr:postcode":"08096",
    "addr:street":"Almonesson Rd",
    "iso:country":"US",
    "sg:address":"1116 Almonesson Rd",
    "sg:city":"Woodbury",
    "sg:classifiers":[
        {
            "category":"Sports & Exercise",
            "subcategory":"Sports Center",
            "type":"Entertainment"
        },
        {
            "category":"Organizations",
            "subcategory":"Community Association",
            "type":"Services"
        },
        {
            "category":"Arena",
            "subcategory":"Sports Club",
            "type":"Entertainment"
        }
    ],
    "sg:phone":"+1 856 848 2522",
    "sg:postcode":"08096",
    "sg:province":"NJ",
    "sg:tags":[
        "baseball",
        "manager",
        "park",
        "promoter"
    ],
    "wof:name":"Deptford Township Little League Inc",
    "wof:placetype":"venue"
},
  "geometry": {"coordinates":[-75.105979,39.846899],"type":"Point"}
}