{
  "type": "Feature",
  "properties": {
    "iso:country":"US",
    "sg:address":"437 Lexington Ave",
    "sg:city":"Cranford",
    "sg:classifiers":[
        {
            "category":"Professional",
            "type":"Services"
        }
    ],
    "sg:phone":"+1   ",
    "sg:postcode":"07016",
    "sg:province":"NJ",
    "wof:name":"K Rumzie",
    "wof:placetype":"venue"
},
  "geometry": {"coordinates":[-74.311177,40.642578],"type":"Point"}
}