{
  "type": "Feature",
  "properties": {
    "addr:full":"526 Green Village Rd Green Village NJ 07935",
    "addr:housenumber":"526",
    "addr:postcode":"07935",
    "addr:street":"Green Village Rd",
    "iso:country":"US",
    "sg:address":"526 Green Village Rd",
    "sg:city":"Green Village",
    "sg:classifiers":[
        {
            "category":"Autos & Motor Vehicles",
            "subcategory":"Fuel & Gas Station",
            "type":"Retail Goods"
        },
        {
            "category":"Retail",
            "subcategory":"Auto Repair",
            "type":"Services"
        }
    ],
    "sg:phone":"+1 973 377 1556",
    "sg:postcode":"07935",
    "sg:province":"NJ",
    "wof:name":"Green Village Garage",
    "wof:placetype":"venue"
},
  "geometry": {"coordinates":[-74.452003,40.738998],"type":"Point"}
}