{
  "type": "Feature",
  "properties": {
    "iso:country":"US",
    "sg:address":"484 E Evesham Rd Ste 3 ",
    "sg:city":"Cherry Hill",
    "sg:classifiers":[
        {
            "category":"Restaurant",
            "type":"Food & Drink"
        }
    ],
    "sg:menulink":"http://www.allmenus.com/nj/cherry-hill/292382-milanese-pizza/menu/",
    "sg:phone":"+1 856 428 0202",
    "sg:postcode":"08003",
    "sg:province":"NJ",
    "sg:tags":[
        "pizza"
    ],
    "wof:name":"Milanese Pizza",
    "wof:placetype":"venue"
},
  "geometry": {"coordinates":[-74.958743,39.865136],"type":"Point"}
}