{
  "type": "Feature",
  "properties": {
    "addr:full":"1114 Goffle Rd Ste 1 Hawthorne NJ 07506",
    "addr:housenumber":"1114",
    "addr:postcode":"07506",
    "addr:street":"Goffle Rd Ste 1",
    "iso:country":"US",
    "sg:address":"1114 Goffle Rd Ste 1",
    "sg:city":"Hawthorne",
    "sg:phone":"+1 973 423 1364",
    "sg:postcode":"07506",
    "sg:province":"NJ",
    "wof:name":"Healthnet Medical Group",
    "wof:placetype":"venue"
},
  "geometry": {"coordinates":[-74.15204799999999,40.969251],"type":"Point"}
}