{
  "type": "Feature",
  "properties": {
    "addr:full":"5009 Grand Ave North Bergen NJ 07047",
    "addr:housenumber":"5009",
    "addr:postcode":"07047",
    "addr:street":"Grand Ave",
    "iso:country":"US",
    "sg:address":"5009 Grand Ave",
    "sg:city":"North Bergen",
    "sg:classifiers":[
        {
            "category":"Building & Trades",
            "subcategory":"Locksmith",
            "type":"Services"
        }
    ],
    "sg:phone":"+1 888 313 7691",
    "sg:postcode":"07047",
    "sg:province":"NJ",
    "sg:tags":[
        "key"
    ],
    "wof:name":"AAA Emergency Locksmith",
    "wof:placetype":"venue"
},
  "geometry": {"coordinates":[-74.02884400000001,40.786862],"type":"Point"}
}