{
  "type": "Feature",
  "properties": {
    "iso:country":"US",
    "sg:address":"47 E Main St",
    "sg:city":"Flemington",
    "sg:classifiers":[
        {
            "category":"Professional",
            "type":"Services"
        }
    ],
    "sg:phone":"+1 908 782 1675",
    "sg:postcode":"08822",
    "sg:province":"NJ",
    "sg:tags":[
        "establishment"
    ],
    "wof:name":"Commerce Square",
    "wof:placetype":"venue"
},
  "geometry": {"coordinates":[-74.85683299999999,40.516689],"type":"Point"}
}