{
  "type": "Feature",
  "properties": {
    "iso:country":"US",
    "sg:address":"219 Degraw Ave",
    "sg:city":"Teaneck",
    "sg:classifiers":[
        {
            "category":"Building & Trades",
            "subcategory":"Construction",
            "type":"Services"
        }
    ],
    "sg:phone":"+1 201 836 2813",
    "sg:postcode":"07666",
    "sg:province":"NJ",
    "sg:tags":[
        "house"
    ],
    "wof:name":"In Nurminen Construction Co",
    "wof:placetype":"venue"
},
  "geometry": {"coordinates":[-74.02018200000001,40.875036],"type":"Point"}
}