{
  "type": "Feature",
  "properties": {
    "iso:country":"US",
    "sg:address":"2 Cliffside Way",
    "sg:city":"Boonton",
    "sg:classifiers":[
        {
            "category":"Professional",
            "subcategory":"Business Services",
            "type":"Services"
        }
    ],
    "sg:phone":"+1   ",
    "sg:postcode":"07005",
    "sg:province":"NJ",
    "wof:name":"Wayne Bouchard",
    "wof:placetype":"venue"
},
  "geometry": {"coordinates":[-74.421806,40.928709],"type":"Point"}
}