{
  "type": "Feature",
  "properties": {
    "addr:full":"15 Pollock Ave Jersey City NJ 07305",
    "addr:housenumber":"15",
    "addr:postcode":"07305",
    "addr:street":"Pollock Ave",
    "iso:country":"US",
    "sg:address":"15 Pollock Ave",
    "sg:city":"Jersey City",
    "sg:classifiers":[
        {
            "category":"Utilities",
            "subcategory":"Fuel Oil & Lpg",
            "type":"Services"
        }
    ],
    "sg:phone":"+1   ",
    "sg:postcode":"07305",
    "sg:province":"NJ",
    "sg:tags":[
        "dealer"
    ],
    "wof:name":"American Oil & Contg Co LLC",
    "wof:placetype":"venue"
},
  "geometry": {"coordinates":[-74.09003300000001,40.713962],"type":"Point"}
}