{
  "type": "Feature",
  "properties": {
    "iso:country":"US",
    "sg:address":"4 Juniper Ln",
    "sg:city":"Blackwood",
    "sg:classifiers":[
        {
            "category":"Building & Trades",
            "subcategory":"Construction",
            "type":"Services"
        }
    ],
    "sg:phone":"+1 856 374 9206",
    "sg:postcode":"08012",
    "sg:province":"NJ",
    "sg:tags":[
        "house"
    ],
    "wof:name":"Five CS Assoc Inc",
    "wof:placetype":"venue"
},
  "geometry": {"coordinates":[-75.053741,39.810658],"type":"Point"}
}