{
  "type": "Feature",
  "properties": {
    "addr:full":"262 Warren St Jersey City NJ 07302",
    "addr:housenumber":"262",
    "addr:postcode":"07302",
    "addr:street":"Warren St",
    "iso:country":"US",
    "sg:address":"262 Warren St",
    "sg:city":"Jersey City",
    "sg:classifiers":[
        {
            "category":"Building & Trades",
            "subcategory":"Locksmith",
            "type":"Services"
        }
    ],
    "sg:phone":"+1 888 393 2613",
    "sg:postcode":"07302",
    "sg:province":"NJ",
    "sg:tags":[
        "key"
    ],
    "wof:name":"Always Affective Available Emergency Locksmith",
    "wof:placetype":"venue"
},
  "geometry": {"coordinates":[-74.038973,40.716658],"type":"Point"}
}