{
  "type": "Feature",
  "properties": {
    "addr:full":"111 Woodbridge Ctr Woodbridge NJ 07095",
    "addr:housenumber":"111",
    "addr:postcode":"07095",
    "addr:street":"Woodbridge Ctr",
    "iso:country":"US",
    "sg:address":"111 Woodbridge Ctr",
    "sg:city":"Woodbridge",
    "sg:classifiers":[
        {
            "category":"Personal",
            "subcategory":"Nail Salon",
            "type":"Services"
        }
    ],
    "sg:phone":"+1 732 636 6055",
    "sg:postcode":"07095",
    "sg:province":"NJ",
    "wof:name":"Tangles Stephen's",
    "wof:placetype":"venue"
},
  "geometry": {"coordinates":[-74.29789700000001,40.549099],"type":"Point"}
}