{
  "type": "Feature",
  "properties": {
    "addr:full":"40 Chestnut St Lakewood NJ 08701",
    "addr:housenumber":"40",
    "addr:postcode":"08701",
    "addr:street":"Chestnut St",
    "iso:country":"US",
    "sg:address":"40 Chestnut St",
    "sg:city":"Lakewood",
    "sg:classifiers":[
        {
            "category":"Building & Trades",
            "subcategory":"Construction",
            "type":"Services"
        }
    ],
    "sg:phone":"+1 732 364 4199",
    "sg:postcode":"08701",
    "sg:province":"NJ",
    "sg:tags":[
        "roofing",
        "siding",
        "contractor"
    ],
    "wof:name":"Quality Alum Vinyl Installers",
    "wof:placetype":"venue"
},
  "geometry": {"coordinates":[-74.21817799999999,40.053149],"type":"Point"}
}