{
  "type": "Feature",
  "properties": {
    "addr:full":"74 Garden St Newark NJ 07105",
    "addr:housenumber":"74",
    "addr:postcode":"07105",
    "addr:street":"Garden St",
    "iso:country":"US",
    "sg:address":"74 Garden St",
    "sg:city":"Newark",
    "sg:classifiers":[
        {
            "category":"Building & Trades",
            "subcategory":"Construction",
            "type":"Services"
        }
    ],
    "sg:phone":"+1 973 344 3377",
    "sg:postcode":"07105",
    "sg:province":"NJ",
    "sg:tags":[
        "carpentry",
        "contractor"
    ],
    "wof:name":"Garden Woodwork",
    "wof:placetype":"venue"
},
  "geometry": {"coordinates":[-74.16834,40.727019],"type":"Point"}
}