{
  "type": "Feature",
  "properties": {
    "iso:country":"US",
    "sg:address":"20 Allens Corner Rd",
    "sg:city":"Flemington",
    "sg:classifiers":[
        {
            "category":"Building & Trades",
            "subcategory":"Construction",
            "type":"Services"
        }
    ],
    "sg:phone":"+1 908 722 9380",
    "sg:postcode":"08822",
    "sg:province":"NJ",
    "sg:tags":[
        "general",
        "contractor"
    ],
    "wof:name":"Combined Industrial Svc",
    "wof:placetype":"venue"
},
  "geometry": {"coordinates":[-74.896818,40.545328],"type":"Point"}
}