{
  "type": "Feature",
  "properties": {
    "iso:country":"US",
    "sg:address":"135 Morristown Rd",
    "sg:city":"Bernardsville",
    "sg:classifiers":[
        {
            "category":"Autos & Motor Vehicles",
            "subcategory":"Fuel & Gas Station",
            "type":"Retail Goods"
        }
    ],
    "sg:phone":"+1 908 221 9237",
    "sg:postcode":"07924",
    "sg:province":"NJ",
    "sg:tags":[
        "oil"
    ],
    "wof:name":"D & B Exxon",
    "wof:placetype":"venue"
},
  "geometry": {"coordinates":[-74.55624299999999,40.721108],"type":"Point"}
}