{
  "type": "Feature",
  "properties": {
    "addr:full":"755 Memorial Pkwy Ste 8 Phillipsburg NJ 08865",
    "addr:housenumber":"755",
    "addr:postcode":"08865",
    "addr:street":"Memorial Pkwy Ste 8",
    "iso:country":"US",
    "sg:address":"755 Memorial Pkwy Ste 8",
    "sg:city":"Phillipsburg",
    "sg:classifiers":[
        {
            "category":"Shopping",
            "subcategory":"Department Store",
            "type":"Retail Goods"
        },
        {
            "category":"Shopping",
            "subcategory":"Discount & Variety Stores",
            "type":"Retail Goods"
        },
        {
            "category":"Shopping",
            "type":"Retail Goods"
        }
    ],
    "sg:phone":"+1 908 387 1828",
    "sg:postcode":"08865",
    "sg:province":"NJ",
    "sg:tags":[
        "merchandise"
    ],
    "sg:website":"http://www.biglots.com/",
    "wof:name":"Big Lots",
    "wof:placetype":"venue"
},
  "geometry": {"coordinates":[-75.174159,40.697891],"type":"Point"}
}