{
  "type": "Feature",
  "properties": {
    "addr:full":"1770 Hurffville Rd Sewell NJ 08080",
    "addr:housenumber":"1770",
    "addr:postcode":"08080",
    "addr:street":"Hurffville Rd",
    "iso:country":"US",
    "sg:address":"1770 Hurffville Rd",
    "sg:city":"Sewell",
    "sg:classifiers":[
        {
            "category":"Building & Trades",
            "subcategory":"Equipment Rental",
            "type":"Services"
        }
    ],
    "sg:phone":"+1 856 227 5640",
    "sg:postcode":"08080",
    "sg:province":"NJ",
    "sg:tags":[
        "toilet"
    ],
    "sg:website":"www.mrjohn.com",
    "wof:name":"Mr John Portable Sanitation",
    "wof:placetype":"venue"
},
  "geometry": {"coordinates":[-75.097765,39.797093],"type":"Point"}
}