{
  "type": "Feature",
  "properties": {
    "iso:country":"US",
    "sg:address":"91 Clinton Rd",
    "sg:city":"Fairfield",
    "sg:classifiers":[
        {
            "category":"Professional",
            "subcategory":"Lawyer & Legal Services",
            "type":"Services"
        }
    ],
    "sg:phone":"+1 973 244 1199",
    "sg:postcode":"07004",
    "sg:province":"NJ",
    "wof:name":"Citron Richard M Attorney",
    "wof:placetype":"venue"
},
  "geometry": {"coordinates":[-74.295799,40.882999],"type":"Point"}
}