{
  "type": "Feature",
  "properties": {
    "addr:full":"862 Warwick Tpke Hewitt NJ 07421",
    "addr:housenumber":"862",
    "addr:postcode":"07421",
    "addr:street":"Warwick Tpke",
    "iso:country":"US",
    "sg:address":"862 Warwick Tpke",
    "sg:city":"Hewitt",
    "sg:classifiers":[
        {
            "category":"Building & Trades",
            "subcategory":"Construction",
            "type":"Services"
        }
    ],
    "sg:phone":"+1 973 853 1655",
    "sg:postcode":"07421",
    "sg:province":"NJ",
    "sg:tags":[
        "blasting",
        "demolition",
        "except",
        "contractor"
    ],
    "wof:name":"J F Mines Inc",
    "wof:placetype":"venue"
},
  "geometry": {"coordinates":[-74.384792,41.209824],"type":"Point"}
}