{
  "type": "Feature",
  "properties": {
    "addr:full":"141 Egg Harbor Rd Sewell NJ 08080",
    "addr:housenumber":"141",
    "addr:postcode":"08080",
    "addr:street":"Egg Harbor Rd",
    "iso:country":"US",
    "sg:address":"141 Egg Harbor Rd",
    "sg:city":"Sewell",
    "sg:classifiers":[
        {
            "category":"Banks & Credit Unions",
            "subcategory":"Bank",
            "type":"Services"
        }
    ],
    "sg:phone":"+1 856 227 0414",
    "sg:postcode":"08080",
    "sg:province":"NJ",
    "wof:name":"TD Banknorth",
    "wof:placetype":"venue"
},
  "geometry": {"coordinates":[-75.098747,39.78092],"type":"Point"}
}