{
  "type": "Feature",
  "properties": {
    "addr:full":"6800 Kennedy Blvd W West New York NJ 07093",
    "addr:housenumber":"6800",
    "addr:postcode":"07093",
    "addr:street":"Kennedy Blvd W West",
    "iso:country":"US",
    "sg:address":"6800 Kennedy Blvd W",
    "sg:city":"West New York",
    "sg:classifiers":[
        {
            "category":"Autos & Motor Vehicles",
            "subcategory":"Fuel & Gas Station",
            "type":"Retail Goods"
        }
    ],
    "sg:phone":"+1 201 854 6858",
    "sg:postcode":"07093",
    "sg:province":"NJ",
    "wof:name":"Shiv Shivangi Inc",
    "wof:placetype":"venue"
},
  "geometry": {"coordinates":[-74.01550899999999,40.796454],"type":"Point"}
}