{
  "type": "Feature",
  "properties": {
    "addr:full":"6 Dalton Pl Bergenfield NJ 07621",
    "addr:housenumber":"6",
    "addr:postcode":"07621",
    "addr:street":"Dalton Pl",
    "iso:country":"US",
    "sg:address":"6 Dalton Pl",
    "sg:city":"Bergenfield",
    "sg:classifiers":[
        {
            "category":"Recreation",
            "type":"Entertainment"
        }
    ],
    "sg:phone":"+1   ",
    "sg:postcode":"07621",
    "sg:province":"NJ",
    "sg:tags":[
        "club",
        "membership"
    ],
    "wof:name":"Filipino American Tennis Assn",
    "wof:placetype":"venue"
},
  "geometry": {"coordinates":[-74.006345,40.921558],"type":"Point"}
}