{
  "type": "Feature",
  "properties": {
    "addr:full":"51 Main St Sayreville NJ 08872",
    "addr:housenumber":"51",
    "addr:postcode":"08872",
    "addr:street":"Main St",
    "iso:country":"US",
    "sg:address":"51 Main St",
    "sg:city":"Sayreville",
    "sg:classifiers":[
        {
            "category":"Health Services",
            "subcategory":"Doctor",
            "type":"Services"
        }
    ],
    "sg:phone":"+1   ",
    "sg:postcode":"08872",
    "sg:province":"NJ",
    "wof:name":"Weisfeld JAS L DDS",
    "wof:placetype":"venue"
},
  "geometry": {"coordinates":[-74.360551,40.457675],"type":"Point"}
}