{
  "type": "Feature",
  "properties": {
    "iso:country":"US",
    "sg:address":"241 E 4th St",
    "sg:city":"Lakewood",
    "sg:classifiers":[
        {
            "category":"Restaurant",
            "type":"Food & Drink"
        }
    ],
    "sg:menulink":"http://www.allmenus.com/nj/lakewood/15152-pizza-plus/menu/",
    "sg:phone":"+1 732 367 0711",
    "sg:postcode":"08701",
    "sg:province":"NJ",
    "sg:tags":[
        "italian"
    ],
    "wof:name":"Pizza Plus",
    "wof:placetype":"venue"
},
  "geometry": {"coordinates":[-74.201418,40.093498],"type":"Point"}
}