{
  "type": "Feature",
  "properties": {
    "addr:full":"58 Demarest Ave Oakland NJ 07436",
    "addr:housenumber":"58",
    "addr:postcode":"07436",
    "addr:street":"Demarest Ave",
    "iso:country":"US",
    "sg:address":"58 Demarest Ave",
    "sg:city":"Oakland",
    "sg:classifiers":[
        {
            "category":"Retail",
            "subcategory":"Repair Shop",
            "type":"Services"
        }
    ],
    "sg:phone":"+1   ",
    "sg:postcode":"07436",
    "sg:province":"NJ",
    "wof:name":"All Around House Repairs",
    "wof:placetype":"venue"
},
  "geometry": {"coordinates":[-74.240981,41.020626],"type":"Point"}
}