{
  "type": "Feature",
  "properties": {
    "iso:country":"US",
    "sg:address":"9 Gates Ave",
    "sg:city":"Montclair",
    "sg:classifiers":[
        {
            "category":"Professional",
            "subcategory":"Advertising",
            "type":"Services"
        }
    ],
    "sg:phone":"+1 973 403 1200",
    "sg:postcode":"07042",
    "sg:province":"NJ",
    "sg:tags":[
        "counselor"
    ],
    "sg:website":"www.keensense.com",
    "wof:name":"Keen Sense Consulting",
    "wof:placetype":"venue"
},
  "geometry": {"coordinates":[-74.214939,40.810195],"type":"Point"}
}