{
  "type": "Feature",
  "properties": {
    "addr:full":"419 N Broadway Pennsville NJ 08070",
    "addr:housenumber":"419",
    "addr:postcode":"08070",
    "addr:street":"N Broadway",
    "iso:country":"US",
    "sg:address":"419 N Broadway",
    "sg:city":"Pennsville",
    "sg:classifiers":[
        {
            "category":"Restaurant",
            "type":"Food & Drink"
        }
    ],
    "sg:menulink":"http://www.allmenus.com/nj/pennsville/84649-applebees/menu/",
    "sg:phone":"+1 856 299 7100",
    "sg:postcode":"08070",
    "sg:province":"NJ",
    "sg:tags":[
        "burger",
        "american",
        "sandwich",
        "soup"
    ],
    "wof:name":"Applebee's",
    "wof:placetype":"venue"
},
  "geometry": {"coordinates":[-75.494432,39.677601],"type":"Point"}
}