{
  "type": "Feature",
  "properties": {
    "addr:full":"12 Orange St Pennsville NJ 08070",
    "addr:housenumber":"12",
    "addr:postcode":"08070",
    "addr:street":"Orange St",
    "iso:country":"US",
    "sg:address":"12 Orange St",
    "sg:city":"Pennsville",
    "sg:classifiers":[
        {
            "category":"Building & Trades",
            "subcategory":"Construction",
            "type":"Services"
        }
    ],
    "sg:phone":"+1 856 678 3163",
    "sg:postcode":"08070",
    "sg:province":"NJ",
    "sg:tags":[
        "house"
    ],
    "wof:name":"Bevis Construction Co",
    "wof:placetype":"venue"
},
  "geometry": {"coordinates":[-75.486622,39.667809],"type":"Point"}
}