{
  "type": "Feature",
  "properties": {
    "addr:full":"235 Main St Orange NJ 07050",
    "addr:housenumber":"235",
    "addr:postcode":"07050",
    "addr:street":"Main St",
    "iso:country":"US",
    "sg:address":"235 Main St",
    "sg:city":"Orange",
    "sg:classifiers":[
        {
            "category":"Shopping",
            "subcategory":"Shoes",
            "type":"Retail Goods"
        }
    ],
    "sg:phone":"+1 973 674 6896",
    "sg:postcode":"07050",
    "sg:province":"NJ",
    "sg:tags":[
        "sneaker",
        "family",
        "store"
    ],
    "wof:name":"Sunny Shoes",
    "wof:placetype":"venue"
},
  "geometry": {"coordinates":[-74.227501,40.771301],"type":"Point"}
}