{
  "type": "Feature",
  "properties": {
    "addr:full":"1712 Bergenline Ave Union City NJ 07087",
    "addr:housenumber":"1712",
    "addr:postcode":"07087",
    "addr:street":"Bergenline Ave",
    "iso:country":"US",
    "sg:address":"1712 Bergenline Ave",
    "sg:city":"Union City",
    "sg:classifiers":[
        {
            "category":"Communications",
            "type":"Services"
        }
    ],
    "sg:phone":"+1 201 617 4566",
    "sg:postcode":"07087",
    "sg:province":"NJ",
    "sg:tags":[
        "communication"
    ],
    "wof:name":"Ketheylsa Communications",
    "wof:placetype":"venue"
},
  "geometry": {"coordinates":[-74.035049,40.763431],"type":"Point"}
}