{
  "type": "Feature",
  "properties": {
    "addr:full":"59 Summit Dr Denville NJ 07834",
    "addr:housenumber":"59",
    "addr:postcode":"07834",
    "addr:street":"Summit Dr",
    "iso:country":"US",
    "sg:address":"59 Summit Dr",
    "sg:city":"Denville",
    "sg:classifiers":[
        {
            "category":"Manufacturing",
            "subcategory":"Textiles",
            "type":"Manufacturing & Wholesale Goods"
        }
    ],
    "sg:phone":"+1 973 625 1983",
    "sg:postcode":"07834",
    "sg:province":"NJ",
    "sg:tags":[
        "mill",
        "knit",
        "outerwear"
    ],
    "wof:name":"Christine Plato",
    "wof:placetype":"venue"
},
  "geometry": {"coordinates":[-74.45971299999999,40.91572],"type":"Point"}
}