{
  "type": "Feature",
  "properties": {
    "iso:country":"US",
    "sg:address":"411 North Ave E",
    "sg:city":"Cranford",
    "sg:classifiers":[
        {
            "category":"Professional",
            "subcategory":"Research",
            "type":"Services"
        }
    ],
    "sg:phone":"+1 908 272 2967",
    "sg:postcode":"07016",
    "sg:province":"NJ",
    "sg:tags":[
        "foundation",
        "philanthropic"
    ],
    "sg:website":"www.fimdefelice.org",
    "wof:name":"Foundation For Innovation",
    "wof:placetype":"venue"
},
  "geometry": {"coordinates":[-74.289079,40.658207],"type":"Point"}
}