{
  "type": "Feature",
  "properties": {
    "iso:country":"US",
    "sg:address":"2205 Delsea Dr",
    "sg:city":"Franklinville",
    "sg:classifiers":[
        {
            "category":"Shopping",
            "subcategory":"News",
            "type":"Retail Goods"
        }
    ],
    "sg:phone":"+1 856 694 1230",
    "sg:postcode":"08322",
    "sg:province":"NJ",
    "sg:tags":[
        "dealer"
    ],
    "wof:name":"Franklinville News & Video",
    "wof:placetype":"venue"
},
  "geometry": {"coordinates":[-75.07337800000001,39.609942],"type":"Point"}
}