{
  "type": "Feature",
  "properties": {
    "addr:full":"129 W Mount Pleasant Ave Livingston NJ 07039",
    "addr:housenumber":"129",
    "addr:postcode":"07039",
    "addr:street":"W Mount Pleasant Ave",
    "iso:country":"US",
    "sg:address":"129 W Mount Pleasant Ave",
    "sg:city":"Livingston",
    "sg:classifiers":[
        {
            "category":"Professional",
            "subcategory":"Business Services",
            "type":"Services"
        }
    ],
    "sg:phone":"+1 973 251 2102",
    "sg:postcode":"07039",
    "sg:province":"NJ",
    "sg:tags":[
        "food",
        "delivery"
    ],
    "sg:website":"www.973delivery.com/index.html",
    "wof:name":"973 Delivery",
    "wof:placetype":"venue"
},
  "geometry": {"coordinates":[-74.321191,40.795126],"type":"Point"}
}