{
  "type": "Feature",
  "properties": {
    "addr:full":"5907 Jefferson St West New York NJ 07093",
    "addr:housenumber":"5907",
    "addr:postcode":"nj 07093",
    "addr:street":"Jefferson St West",
    "iso:country":"US",
    "sg:address":"5907 Jefferson St",
    "sg:city":"West New York",
    "sg:classifiers":[
        {
            "category":"Wholesale",
            "subcategory":"Machinery & Supplies",
            "type":"Manufacturing & Wholesale Goods"
        }
    ],
    "sg:phone":"+1 201 861 7967",
    "sg:postcode":"07093",
    "sg:province":"NJ",
    "sg:tags":[
        "independent",
        "rep"
    ],
    "wof:name":"Cherokee Equipment Inc",
    "wof:placetype":"venue"
},
  "geometry": {"coordinates":[-74.020557,40.790863],"type":"Point"}
}