{
  "type": "Feature",
  "properties": {
    "iso:country":"US",
    "sg:address":"1738 State Rte 37",
    "sg:city":"Toms River",
    "sg:classifiers":[
        {
            "category":"Social Services",
            "type":"Services"
        }
    ],
    "sg:phone":"+1 732 270 8393",
    "sg:postcode":"08753",
    "sg:province":"NJ",
    "sg:tags":[
        "organization",
        "welfare"
    ],
    "wof:name":"Salvation Army Corps Comm Ctr",
    "wof:placetype":"venue"
},
  "geometry": {"coordinates":[-74.148859,39.951812],"type":"Point"}
}