{
  "type": "Feature",
  "properties": {
    "iso:country":"US",
    "sg:address":"18 Garden Pl",
    "sg:city":"Edgewater",
    "sg:classifiers":[
        {
            "category":"Professional",
            "type":"Services"
        }
    ],
    "sg:phone":"+1 201 945 3575",
    "sg:postcode":"07020",
    "sg:province":"NJ",
    "sg:tags":[
        "establishment"
    ],
    "wof:name":"Mile New York Llc",
    "wof:placetype":"venue"
},
  "geometry": {"coordinates":[-73.97667300000001,40.823131],"type":"Point"}
}