{
  "type": "Feature",
  "properties": {
    "addr:full":"33 Mandl St Trenton NJ 08619",
    "addr:housenumber":"33",
    "addr:postcode":"08619",
    "addr:street":"Mandl St",
    "iso:country":"US",
    "sg:address":"33 Mandl St",
    "sg:city":"Trenton",
    "sg:classifiers":[
        {
            "category":"Building & Trades",
            "subcategory":"Cleaning & Sanitation",
            "type":"Services"
        }
    ],
    "sg:phone":"+1   ",
    "sg:postcode":"08619",
    "sg:province":"NJ",
    "sg:tags":[
        "maintenance"
    ],
    "wof:name":"J&T Janitorial Service",
    "wof:placetype":"venue"
},
  "geometry": {"coordinates":[-74.709081,40.226215],"type":"Point"}
}