{
  "type": "Feature",
  "properties": {
    "iso:country":"US",
    "sg:address":"372 State Hwy 40",
    "sg:city":"Elmer",
    "sg:classifiers":[
        {
            "category":"Retail",
            "subcategory":"Auto Rental",
            "type":"Services"
        }
    ],
    "sg:phone":"+1 856 358 1712",
    "sg:postcode":"08318",
    "sg:province":"NJ",
    "sg:tags":[
        "truck"
    ],
    "wof:name":"Auto Specialists",
    "wof:placetype":"venue"
},
  "geometry": {"coordinates":[-75.153931,39.599162],"type":"Point"}
}