{
  "type": "Feature",
  "properties": {
    "addr:full":"310 Mount Kemble Ave Morristown NJ 07960",
    "addr:housenumber":"310",
    "addr:postcode":"07960",
    "addr:street":"Mount Kemble Ave",
    "iso:country":"US",
    "sg:address":"310 Mount Kemble Ave",
    "sg:city":"Morristown",
    "sg:classifiers":[
        {
            "category":"Building & Trades",
            "subcategory":"Construction",
            "type":"Services"
        }
    ],
    "sg:phone":"+1 973 714 2057",
    "sg:postcode":"07960",
    "sg:province":"NJ",
    "sg:tags":[
        "house"
    ],
    "wof:name":"Jasper Construction LLC",
    "wof:placetype":"venue"
},
  "geometry": {"coordinates":[-74.50005899999999,40.77829],"type":"Point"}
}