{
  "type": "Feature",
  "properties": {
    "addr:full":"1208 Raritan Rd Cranford NJ 07016",
    "addr:housenumber":"1208",
    "addr:postcode":"07016",
    "addr:street":"Raritan Rd",
    "iso:country":"US",
    "sg:address":"1208 Raritan Rd",
    "sg:city":"Cranford",
    "sg:classifiers":[
        {
            "category":"Retail",
            "subcategory":"Laundry & Dry Cleaning",
            "type":"Services"
        }
    ],
    "sg:phone":"+1   ",
    "sg:postcode":"07016",
    "sg:province":"NJ",
    "sg:tags":[
        "drycleaning",
        "plant"
    ],
    "wof:name":"Raritan Cleaners",
    "wof:placetype":"venue"
},
  "geometry": {"coordinates":[-74.300972,40.635573],"type":"Point"}
}