{
  "type": "Feature",
  "properties": {
    "iso:country":"US",
    "sg:address":"414 Amboy Ave",
    "sg:city":"Perth Amboy",
    "sg:classifiers":[
        {
            "category":"Home & Garden",
            "subcategory":"Building Materials",
            "type":"Retail Goods"
        }
    ],
    "sg:phone":"+1 732 442 5433",
    "sg:postcode":"08861",
    "sg:province":"NJ",
    "sg:tags":[
        "glass",
        "window",
        "plate"
    ],
    "wof:name":"R & S Glass & Mirror Inc",
    "wof:placetype":"venue"
},
  "geometry": {"coordinates":[-74.275488,40.516188],"type":"Point"}
}