{
  "type": "Feature",
  "properties": {
    "addr:full":"416 Raritan Ave Atco NJ 08004",
    "addr:housenumber":"416",
    "addr:postcode":"08004",
    "addr:street":"Raritan Ave",
    "iso:country":"US",
    "sg:address":"416 Raritan Ave",
    "sg:city":"Atco",
    "sg:classifiers":[
        {
            "category":"Professional",
            "subcategory":"Computer Services",
            "type":"Services"
        }
    ],
    "sg:phone":"+1 856 753 9774",
    "sg:postcode":"08004",
    "sg:province":"NJ",
    "sg:tags":[
        "related"
    ],
    "wof:name":"Stephen Rynex & Associates",
    "wof:placetype":"venue"
},
  "geometry": {"coordinates":[-74.888588,39.771009],"type":"Point"}
}