{
  "type": "Feature",
  "properties": {
    "iso:country":"US",
    "sg:address":"433 W Delilah Rd",
    "sg:city":"Pleasantville",
    "sg:classifiers":[
        {
            "category":"Professional",
            "subcategory":"Accounting & Tax Preparation",
            "type":"Services"
        },
        {
            "category":"Insurance",
            "subcategory":"Insurance Agent",
            "type":"Services"
        }
    ],
    "sg:phone":"+1 609 646 8299",
    "sg:postcode":"08232",
    "sg:province":"NJ",
    "sg:tags":[
        "bookkeeping",
        "return",
        "filing",
        "general"
    ],
    "wof:name":"Nino Calabrese & Assoc Ea",
    "wof:placetype":"venue"
},
  "geometry": {"coordinates":[-74.519396,39.407337],"type":"Point"}
}