{
  "type": "Feature",
  "properties": {
    "addr:full":"4067 Harbour Dr Palmyra NJ 08065",
    "addr:housenumber":"4067",
    "addr:postcode":"08065",
    "addr:street":"Harbour Dr",
    "iso:country":"US",
    "sg:address":"4067 Harbour Dr",
    "sg:city":"Palmyra",
    "sg:classifiers":[
        {
            "category":"Real Estate",
            "subcategory":"Real Estate Agent",
            "type":"Services"
        }
    ],
    "sg:phone":"+1   ",
    "sg:postcode":"08065",
    "sg:province":"NJ",
    "wof:name":"Korman Suites At Willow Shores",
    "wof:placetype":"venue"
},
  "geometry": {"coordinates":[-75.033834,40.009285],"type":"Point"}
}