{
  "type": "Feature",
  "properties": {
    "addr:full":"158 Paramus Rd Paramus NJ 07652",
    "addr:housenumber":"158",
    "addr:postcode":"07652",
    "addr:street":"Paramus Rd",
    "iso:country":"US",
    "sg:address":"158 Paramus Rd",
    "sg:city":"Paramus",
    "sg:classifiers":[
        {
            "category":"Recreation",
            "type":"Entertainment"
        },
        {
            "category":"Organizations",
            "subcategory":"Community Association",
            "type":"Services"
        }
    ],
    "sg:phone":"+1 201 843 9543",
    "sg:postcode":"07652",
    "sg:province":"NJ",
    "sg:tags":[
        "club",
        "membership"
    ],
    "wof:name":"Arcola Country Club Pro S",
    "wof:placetype":"venue"
},
  "geometry": {"coordinates":[-74.092332,40.938129],"type":"Point"}
}