{
  "type": "Feature",
  "properties": {
    "iso:country":"US",
    "sg:address":"6415 Park Ave",
    "sg:city":"West New York",
    "sg:classifiers":[
        {
            "category":"Restaurant",
            "type":"Food & Drink"
        }
    ],
    "sg:phone":"+1 201 861 2304",
    "sg:postcode":"07093",
    "sg:province":"NJ",
    "sg:tags":[
        "eating",
        "pizza"
    ],
    "sg:website":"www.newpizzaontheblock.com",
    "wof:name":"New Pizza On the Block",
    "wof:placetype":"venue"
},
  "geometry": {"coordinates":[-74.00599699999999,40.789398],"type":"Point"}
}