{
  "type": "Feature",
  "properties": {
    "iso:country":"US",
    "sg:address":"2 Lincoln St",
    "sg:city":"Jersey City",
    "sg:classifiers":[
        {
            "category":"Personal",
            "subcategory":"Beauty Salon",
            "type":"Services"
        }
    ],
    "sg:phone":"+1 201 653 7070",
    "sg:postcode":"07307",
    "sg:province":"NJ",
    "sg:tags":[
        "shop"
    ],
    "wof:name":"Europe Hair Salon",
    "wof:placetype":"venue"
},
  "geometry": {"coordinates":[-74.05130699999999,40.747544],"type":"Point"}
}