{
  "type": "Feature",
  "properties": {
    "iso:country":"US",
    "sg:address":"44 Old Hook Rd",
    "sg:city":"Bayonne",
    "sg:classifiers":[
        {
            "category":"Freight",
            "type":"Transportation"
        }
    ],
    "sg:phone":"+1 973 277 5218",
    "sg:postcode":"07002",
    "sg:province":"NJ",
    "sg:tags":[
        "trucking"
    ],
    "wof:name":"Rtl Transport",
    "wof:placetype":"venue"
},
  "geometry": {"coordinates":[-74.114637,40.659736],"type":"Point"}
}