{
  "type": "Feature",
  "properties": {
    "addr:full":"33 E Clinton St Newton NJ 07801",
    "addr:housenumber":"33",
    "addr:postcode":"07801",
    "addr:street":"E Clinton St",
    "iso:country":"US",
    "sg:address":"33 E Clinton St",
    "sg:city":"Newton",
    "sg:classifiers":[
        {
            "category":"Shopping",
            "subcategory":"Used Merchandise",
            "type":"Retail Goods"
        }
    ],
    "sg:phone":"+1   ",
    "sg:postcode":"07801",
    "sg:province":"NJ",
    "wof:name":"Swap N Shop LLC",
    "wof:placetype":"venue"
},
  "geometry": {"coordinates":[-74.557249,40.886669],"type":"Point"}
}