{
  "type": "Feature",
  "properties": {
    "iso:country":"US",
    "sg:address":"7 E Williams Ave",
    "sg:city":"Barrington",
    "sg:classifiers":[
        {
            "category":"Professional",
            "type":"Services"
        },
        {
            "category":"Building & Trades",
            "subcategory":"Construction",
            "type":"Services"
        },
        {
            "category":"Sports & Exercise",
            "subcategory":"Swimming Pool",
            "type":"Entertainment"
        }
    ],
    "sg:phone":"+1 856 310 9341",
    "sg:postcode":"08007",
    "sg:province":"NJ",
    "sg:tags":[
        "spa",
        "repair",
        "hot",
        "tubs-repair"
    ],
    "wof:name":"Phillips Family Pools",
    "wof:placetype":"venue"
},
  "geometry": {"coordinates":[-75.05498,39.864618],"type":"Point"}
}