{
  "type": "Feature",
  "properties": {
    "addr:full":"226 Harrison St Passaic NJ 07055",
    "addr:housenumber":"226",
    "addr:postcode":"07055",
    "addr:street":"Harrison St",
    "iso:country":"US",
    "sg:address":"226 Harrison St",
    "sg:city":"Passaic",
    "sg:classifiers":[
        {
            "category":"Organizations",
            "subcategory":"Religious Organization",
            "type":"Services"
        }
    ],
    "sg:phone":"+1 973 778 9763",
    "sg:postcode":"07055",
    "sg:province":"NJ",
    "wof:name":"Holy Trinity Rc Church",
    "wof:placetype":"venue"
},
  "geometry": {"coordinates":[-74.12509900000001,40.870098],"type":"Point"}
}