{
  "type": "Feature",
  "properties": {
    "addr:full":"47 W River Rd Rumson NJ 07760",
    "addr:housenumber":"47",
    "addr:postcode":"07760",
    "addr:street":"W River Rd",
    "iso:country":"US",
    "sg:address":"47 W River Rd",
    "sg:city":"Rumson",
    "sg:classifiers":[
        {
            "category":"Professional",
            "subcategory":"Management & Consulting",
            "type":"Services"
        }
    ],
    "sg:phone":"+1 732 842 7960",
    "sg:postcode":"07760",
    "sg:province":"NJ",
    "sg:tags":[
        "consultant"
    ],
    "wof:name":"Lionhart Advisors LLC",
    "wof:placetype":"venue"
},
  "geometry": {"coordinates":[-74.012839,40.37491],"type":"Point"}
}