{
  "type": "Feature",
  "properties": {
    "addr:full":"297 US Hwy 22 E Whitehouse Sta NJ 08889",
    "addr:housenumber":"297",
    "addr:postcode":"08889",
    "addr:street":"Us Hwy 22 E",
    "iso:country":"US",
    "sg:address":"297 US Hwy 22 E",
    "sg:city":"Whitehouse Sta",
    "sg:classifiers":[
        {
            "category":"Home & Garden",
            "subcategory":"Garden Supply",
            "type":"Retail Goods"
        }
    ],
    "sg:phone":"+1 908 534 4904",
    "sg:postcode":"08889",
    "sg:province":"NJ",
    "sg:tags":[
        "center"
    ],
    "sg:website":"www.fourseasonsgreenery.com",
    "wof:name":"Four Seasons Greenery",
    "wof:placetype":"venue"
},
  "geometry": {"coordinates":[-74.762237,40.620507],"type":"Point"}
}