{
  "type": "Feature",
  "properties": {
    "addr:full":"16 Georgetown Ct Linwood NJ 08221",
    "addr:housenumber":"16",
    "addr:postcode":"08221",
    "addr:street":"Georgetown Ct",
    "iso:country":"US",
    "sg:address":"16 Georgetown Ct",
    "sg:city":"Linwood",
    "sg:classifiers":[
        {
            "category":"Wholesale",
            "subcategory":"Vending Machines",
            "type":"Manufacturing & Wholesale Goods"
        }
    ],
    "sg:phone":"+1   ",
    "sg:postcode":"08221",
    "sg:province":"NJ",
    "sg:tags":[
        "operator"
    ],
    "wof:name":"Nicks Vending",
    "wof:placetype":"venue"
},
  "geometry": {"coordinates":[-74.57877499999999,39.33855],"type":"Point"}
}