{
  "type": "Feature",
  "properties": {
    "addr:full":"3641 Haddonfield Rd Merchantville NJ 08109",
    "addr:housenumber":"3641",
    "addr:postcode":"08109",
    "addr:street":"Haddonfield Rd",
    "iso:country":"US",
    "sg:address":"3641 Haddonfield Rd",
    "sg:city":"Merchantville",
    "sg:classifiers":[
        {
            "category":"Banks & Credit Unions",
            "subcategory":"Financial Services",
            "type":"Services"
        }
    ],
    "sg:phone":"+1   ",
    "sg:postcode":"08109",
    "sg:province":"NJ",
    "sg:tags":[
        "investor"
    ],
    "wof:name":"Investment D & J",
    "wof:placetype":"venue"
},
  "geometry": {"coordinates":[-75.025508,39.959524],"type":"Point"}
}