{
  "type": "Feature",
  "properties": {
    "addr:full":"1022 US Highway 9 N Woodbridge NJ 07095",
    "addr:housenumber":"1022",
    "addr:postcode":"07095",
    "addr:street":"Us Highway 9 N",
    "iso:country":"US",
    "sg:address":"1022 US Highway 9 N",
    "sg:city":"Woodbridge",
    "sg:classifiers":[
        {
            "category":"Insurance",
            "subcategory":"Health Insurance",
            "type":"Services"
        }
    ],
    "sg:phone":"+1 732 727 0746",
    "sg:postcode":"07095",
    "sg:province":"NJ",
    "sg:tags":[
        "market"
    ],
    "sg:website":"www.gnc.com",
    "wof:name":"General Nutrition Center",
    "wof:placetype":"venue"
},
  "geometry": {"coordinates":[-74.29095599999999,40.546077],"type":"Point"}
}