{
  "type": "Feature",
  "properties": {
    "addr:full":"192 Quakerbridge Mall Trenton NJ 08648",
    "addr:housenumber":"192",
    "addr:postcode":"08648",
    "addr:street":"Quakerbridge Mall",
    "iso:country":"US",
    "sg:address":"192 Quakerbridge Mall",
    "sg:city":"Trenton",
    "sg:classifiers":[
        {
            "category":"Shopping",
            "subcategory":"Books",
            "type":"Retail Goods"
        }
    ],
    "sg:phone":"+1   ",
    "sg:postcode":"08648",
    "sg:province":"NJ",
    "wof:name":"Barnes & Noble",
    "wof:placetype":"venue"
},
  "geometry": {"coordinates":[-74.68529599999999,40.289912],"type":"Point"}
}