{
  "type": "Feature",
  "properties": {
    "addr:full":"840 Valley Brook Ave Lyndhurst NJ 07071",
    "addr:housenumber":"840",
    "addr:postcode":"07071",
    "addr:street":"Valley Brook Ave",
    "iso:country":"US",
    "sg:address":"840 Valley Brook Ave",
    "sg:city":"Lyndhurst",
    "sg:classifiers":[
        {
            "category":"Building & Trades",
            "subcategory":"Construction",
            "type":"Services"
        }
    ],
    "sg:phone":"+1 201 438 3826",
    "sg:postcode":"07071",
    "sg:province":"NJ",
    "sg:tags":[
        "general",
        "contractor"
    ],
    "wof:name":"Garofalo Contractors",
    "wof:placetype":"venue"
},
  "geometry": {"coordinates":[-74.11184900000001,40.804893],"type":"Point"}
}