{
  "type": "Feature",
  "properties": {
    "iso:country":"US",
    "sg:address":"881 Co Rd 539",
    "sg:city":"New Egypt",
    "sg:classifiers":[
        {
            "category":"Freight",
            "type":"Transportation"
        },
        {
            "category":"Professional",
            "subcategory":"Secretarial Services",
            "type":"Services"
        }
    ],
    "sg:phone":"+1 609 758 8100",
    "sg:postcode":"08533",
    "sg:province":"NJ",
    "sg:tags":[
        "operator",
        "trucking",
        "local",
        "typing"
    ],
    "wof:name":"Smd Trucking LLC",
    "wof:placetype":"venue"
},
  "geometry": {"coordinates":[-74.45321,40.049236],"type":"Point"}
}