{
  "type": "Feature",
  "properties": {
    "iso:country":"US",
    "sg:address":"14 W Scott St",
    "sg:city":"Riverside",
    "sg:classifiers":[
        {
            "category":"Government",
            "subcategory":"Fire Station",
            "type":"Public Place"
        }
    ],
    "sg:phone":"+1 856 461 6251",
    "sg:postcode":"08075",
    "sg:province":"NJ",
    "sg:tags":[
        "department"
    ],
    "wof:name":"Riverside Fire Co No 1 Inc",
    "wof:placetype":"venue"
},
  "geometry": {"coordinates":[-74.961198,40.037822],"type":"Point"}
}