{
  "type": "Feature",
  "properties": {
    "iso:country":"US",
    "sg:address":"1416 Brace Rd",
    "sg:city":"Cherry Hill",
    "sg:classifiers":[
        {
            "category":"Health Services",
            "subcategory":"Doctor",
            "type":"Services"
        }
    ],
    "sg:phone":"+1 856 795 8020",
    "sg:postcode":"08034",
    "sg:province":"NJ",
    "sg:tags":[
        "periodontist",
        "dentist"
    ],
    "sg:website":"www.sullivanyasner.com",
    "wof:name":"Sullivan, Yasner & Kazemi",
    "wof:placetype":"venue"
},
  "geometry": {"coordinates":[-75.01821,39.892494],"type":"Point"}
}