{
  "type": "Feature",
  "properties": {
    "iso:country":"US",
    "sg:address":"9 Hoover Ave",
    "sg:city":"Passaic",
    "sg:classifiers":[
        {
            "category":"Restaurant",
            "type":"Food & Drink"
        }
    ],
    "sg:phone":"+1 201 927 9834",
    "sg:postcode":"07055",
    "sg:province":"NJ",
    "wof:name":"Dragon House",
    "wof:placetype":"venue"
},
  "geometry": {"coordinates":[-74.124802,40.86204],"type":"Point"}
}