{
  "type": "Feature",
  "properties": {
    "iso:country":"US",
    "sg:address":"8 S Essex Ave",
    "sg:city":"Margate City",
    "sg:classifiers":[
        {
            "category":"Restaurant",
            "type":"Food & Drink"
        }
    ],
    "sg:phone":"+1 609 822 6363",
    "sg:postcode":"08402",
    "sg:province":"NJ",
    "wof:name":"Cafe 8 South",
    "wof:placetype":"venue"
},
  "geometry": {"coordinates":[-74.49667100000001,39.329385],"type":"Point"}
}