{
  "type": "Feature",
  "properties": {
    "iso:country":"US",
    "sg:address":"7 Red Maple Ln",
    "sg:city":"Kenilworth",
    "sg:classifiers":[
        {
            "category":"Real Estate",
            "subcategory":"Real Estate Operator",
            "type":"Services"
        }
    ],
    "sg:phone":"+1   ",
    "sg:postcode":"07033",
    "sg:province":"NJ",
    "sg:tags":[
        "building",
        "nonresidential"
    ],
    "wof:name":"Maverick Properties LLC",
    "wof:placetype":"venue"
},
  "geometry": {"coordinates":[-74.28700600000001,40.670326],"type":"Point"}
}