{
  "type": "Feature",
  "properties": {
    "addr:full":"3770 Cedarville Rd Cedarville NJ 08311",
    "addr:housenumber":"3770",
    "addr:postcode":"08311",
    "addr:street":"Cedarville Rd",
    "iso:country":"US",
    "sg:address":"3770 Cedarville Rd",
    "sg:city":"Cedarville",
    "sg:classifiers":[
        {
            "category":"Shopping",
            "subcategory":"Gifts & Souvenirs",
            "type":"Retail Goods"
        },
        {
            "category":"Home & Garden",
            "subcategory":"Garden Supply",
            "type":"Retail Goods"
        }
    ],
    "sg:phone":"+1 856 447 4365",
    "sg:postcode":"08311",
    "sg:province":"NJ",
    "sg:tags":[
        "shop",
        "repair"
    ],
    "wof:name":"Covered Bridge Gift Shop",
    "wof:placetype":"venue"
},
  "geometry": {"coordinates":[-75.177734,39.337232],"type":"Point"}
}