{
  "type": "Feature",
  "properties": {
    "addr:full":"300 State Rte 17 Mahwah NJ 07430",
    "addr:housenumber":"300",
    "addr:postcode":"07430",
    "addr:street":"State Rte 17",
    "iso:country":"US",
    "sg:address":"300 State Rte 17",
    "sg:city":"Mahwah",
    "sg:classifiers":[
        {
            "category":"Government",
            "subcategory":"Office",
            "type":"Public Place"
        }
    ],
    "sg:phone":"+1 201 529 4130",
    "sg:postcode":"07430",
    "sg:province":"NJ",
    "sg:tags":[
        "village"
    ],
    "wof:name":"Mahwah City Planning Board",
    "wof:placetype":"venue"
},
  "geometry": {"coordinates":[-74.15334,41.088897],"type":"Point"}
}