{
  "type": "Feature",
  "properties": {
    "addr:full":"20 Gloria Ln Fairfield NJ 07004",
    "addr:housenumber":"20",
    "addr:postcode":"07004",
    "addr:street":"Gloria Ln",
    "iso:country":"US",
    "sg:address":"20 Gloria Ln",
    "sg:city":"Fairfield",
    "sg:classifiers":[
        {
            "category":"Sports & Exercise",
            "subcategory":"Bicycle Rental",
            "type":"Entertainment"
        }
    ],
    "sg:phone":"+1 973 575 7840",
    "sg:postcode":"07004",
    "sg:province":"NJ",
    "sg:tags":[
        "wear"
    ],
    "sg:website":"www.unitedsportapparel.com",
    "wof:name":"United Sport Apparel",
    "wof:placetype":"venue"
},
  "geometry": {"coordinates":[-74.295891,40.875225],"type":"Point"}
}