{
  "type": "Feature",
  "properties": {
    "iso:country":"US",
    "sg:address":"1225 Raider Way",
    "sg:city":"Toms River",
    "sg:classifiers":[
        {
            "category":"Education",
            "subcategory":"School",
            "type":"Public Place"
        }
    ],
    "sg:phone":"+1   ",
    "sg:postcode":"08753",
    "sg:province":"NJ",
    "sg:website":"www.tomsriverschools.com",
    "wof:name":"Toms River High School East",
    "wof:placetype":"venue"
},
  "geometry": {"coordinates":[-74.142785,39.967949],"type":"Point"}
}