{
  "type": "Feature",
  "properties": {
    "iso:country":"US",
    "sg:address":"87 Monmouth Ave",
    "sg:city":"Wayne",
    "sg:classifiers":[
        {
            "category":"Building & Trades",
            "subcategory":"Construction",
            "type":"Services"
        }
    ],
    "sg:phone":"+1 973 305 8187",
    "sg:postcode":"07470",
    "sg:province":"NJ",
    "sg:tags":[
        "residential"
    ],
    "wof:name":"Mark C Mileto",
    "wof:placetype":"venue"
},
  "geometry": {"coordinates":[-74.278869,40.924081],"type":"Point"}
}