{
  "type": "Feature",
  "properties": {
    "addr:full":"271 96th St Stone Harbor NJ 08247",
    "addr:housenumber":"271",
    "addr:postcode":"08247",
    "addr:street":"96Th St",
    "iso:country":"US",
    "sg:address":"271 96th St",
    "sg:city":"Stone Harbor",
    "sg:classifiers":[
        {
            "category":"Shopping",
            "subcategory":"Music",
            "type":"Retail Goods"
        }
    ],
    "sg:phone":"+1 609 967 5200",
    "sg:postcode":"08247",
    "sg:province":"NJ",
    "sg:tags":[
        "compact",
        "record",
        "disc",
        "tape"
    ],
    "wof:name":"Acrat Lii",
    "wof:placetype":"venue"
},
  "geometry": {"coordinates":[-74.759534,39.053751],"type":"Point"}
}