{
  "type": "Feature",
  "properties": {
    "iso:country":"US",
    "sg:address":"7346 Remington Ave",
    "sg:city":"Pennsauken",
    "sg:classifiers":[
        {
            "category":"Building & Trades",
            "subcategory":"Construction",
            "type":"Services"
        }
    ],
    "sg:phone":"+1 856 665 9075",
    "sg:postcode":"08110",
    "sg:province":"NJ",
    "sg:tags":[
        "interior",
        "remodeling"
    ],
    "wof:name":"PDC & Son Remodeling",
    "wof:placetype":"venue"
},
  "geometry": {"coordinates":[-75.049401,39.973521],"type":"Point"}
}