{
  "type": "Feature",
  "properties": {
    "addr:full":"479 State Rte 17 Mahwah NJ 07430",
    "addr:housenumber":"479",
    "addr:postcode":"07430",
    "addr:street":"State Rte 17",
    "iso:country":"US",
    "sg:address":"479 State Rte 17",
    "sg:city":"Mahwah",
    "sg:classifiers":[
        {
            "category":"Organizations",
            "subcategory":"Community Association",
            "type":"Services"
        }
    ],
    "sg:phone":"+1   ",
    "sg:postcode":"07430",
    "sg:province":"NJ",
    "sg:tags":[
        "condominium"
    ],
    "wof:name":"Indian Ridge Condominium Assn",
    "wof:placetype":"venue"
},
  "geometry": {"coordinates":[-74.147942,41.077431],"type":"Point"}
}