{
  "type": "Feature",
  "properties": {
    "addr:full":"7 W Hampton St Pemberton NJ 08068",
    "addr:housenumber":"7",
    "addr:postcode":"08068",
    "addr:street":"W Hampton St",
    "iso:country":"US",
    "sg:address":"7 W Hampton St",
    "sg:city":"Pemberton",
    "sg:classifiers":[
        {
            "category":"Travel",
            "subcategory":"Hotels & Motels",
            "type":"Entertainment"
        }
    ],
    "sg:phone":"+1 609 894 8155",
    "sg:postcode":"08068",
    "sg:province":"NJ",
    "sg:tags":[
        "operation"
    ],
    "wof:name":"Executive Inn",
    "wof:placetype":"venue"
},
  "geometry": {"coordinates":[-74.68556599999999,39.967571],"type":"Point"}
}