{
  "type": "Feature",
  "properties": {
    "addr:full":"339 Bridgeboro Rd Moorestown NJ 08057",
    "addr:housenumber":"339",
    "addr:postcode":"08057",
    "addr:street":"Bridgeboro Rd",
    "iso:country":"US",
    "sg:address":"339 Bridgeboro Rd",
    "sg:city":"Moorestown",
    "sg:classifiers":[
        {
            "category":"Place Of Worship",
            "subcategory":"Church",
            "type":"Public Place"
        },
        {
            "category":"Place Of Worship",
            "type":"Public Place"
        }
    ],
    "sg:phone":"+1 856 234 5197",
    "sg:postcode":"08057",
    "sg:province":"NJ",
    "sg:tags":[
        "churches-jehovah's",
        "witness"
    ],
    "sg:website":"http://www.watchtower.org",
    "wof:name":"Jehovah's Witnesses",
    "wof:placetype":"venue"
},
  "geometry": {"coordinates":[-74.944591,39.988533],"type":"Point"}
}