{
  "type": "Feature",
  "properties": {
    "addr:full":"601 US Hwy 206 Hillsborough NJ 08844",
    "addr:housenumber":"601",
    "addr:postcode":"08844",
    "addr:street":"Us Hwy 206",
    "iso:country":"US",
    "sg:address":"601 US Hwy 206",
    "sg:city":"Hillsborough",
    "sg:classifiers":[
        {
            "category":"Health Services",
            "subcategory":"Doctor",
            "type":"Services"
        }
    ],
    "sg:phone":"+1 908 359 0666",
    "sg:postcode":"08844",
    "sg:province":"NJ",
    "sg:tags":[
        "dentist"
    ],
    "wof:name":"Amwell Dental Associates",
    "wof:placetype":"venue"
},
  "geometry": {"coordinates":[-74.644903,40.502018],"type":"Point"}
}