{
  "type": "Feature",
  "properties": {
    "iso:country":"US",
    "sg:address":"159 Frazier St",
    "sg:city":"Trenton",
    "sg:classifiers":[
        {
            "category":"Food & Beverages",
            "subcategory":"Meat & Fish",
            "type":"Retail Goods"
        }
    ],
    "sg:phone":"+1 609 392 5501",
    "sg:postcode":"08618",
    "sg:province":"NJ",
    "wof:name":"Frazer Shin's Quick Stop",
    "wof:placetype":"venue"
},
  "geometry": {"coordinates":[-74.77149199999999,40.230699],"type":"Point"}
}