{
  "type": "Feature",
  "properties": {
    "addr:full":"681 Paramus Rd Paramus NJ 07652",
    "addr:housenumber":"681",
    "addr:postcode":"07652",
    "addr:street":"Paramus Rd",
    "iso:country":"US",
    "sg:address":"681 Paramus Rd",
    "sg:city":"Paramus",
    "sg:classifiers":[
        {
            "category":"Food & Beverages",
            "subcategory":"Fruits & Vegetables",
            "type":"Retail Goods"
        }
    ],
    "sg:phone":"+1 201 444 2040",
    "sg:postcode":"07652",
    "sg:province":"NJ",
    "sg:tags":[
        "florist",
        "produce"
    ],
    "wof:name":"Basket Produce Inc",
    "wof:placetype":"venue"
},
  "geometry": {"coordinates":[-74.090311,40.973065],"type":"Point"}
}