{
  "type": "Feature",
  "properties": {
    "iso:country":"US",
    "sg:address":"387 Passaic Ave",
    "sg:city":"Fairfield",
    "sg:classifiers":[
        {
            "category":"Professional",
            "subcategory":"Accounting & Tax Preparation",
            "type":"Services"
        }
    ],
    "sg:phone":"+1 973 575 2900",
    "sg:postcode":"07004",
    "sg:province":"NJ",
    "sg:tags":[
        "accountant"
    ],
    "wof:name":"De Szendeffy Stephen CPA",
    "wof:placetype":"venue"
},
  "geometry": {"coordinates":[-74.27330499999999,40.888472],"type":"Point"}
}