{
  "type": "Feature",
  "properties": {
    "iso:country":"US",
    "sg:address":"629 Palisade Ave",
    "sg:city":"Cliffside Park",
    "sg:classifiers":[
        {
            "category":"Deli",
            "type":"Food & Drink"
        },
        {
            "category":"Food & Beverages",
            "subcategory":"Bakery",
            "type":"Retail Goods"
        }
    ],
    "sg:phone":"+1 201 313 7133",
    "sg:postcode":"07010",
    "sg:province":"NJ",
    "sg:tags":[
        "sandwich"
    ],
    "wof:name":"Mishka Delicatessan",
    "wof:placetype":"venue"
},
  "geometry": {"coordinates":[-73.984635,40.824092],"type":"Point"}
}