{
  "type": "Feature",
  "properties": {
    "addr:full":"30 Fox Hill Rd Califon NJ 07830",
    "addr:housenumber":"30",
    "addr:postcode":"07830",
    "addr:street":"Fox Hill Rd",
    "iso:country":"US",
    "sg:address":"30 Fox Hill Rd",
    "sg:city":"Califon",
    "sg:classifiers":[
        {
            "category":"Farming",
            "subcategory":"Farm",
            "type":"Manufacturing & Wholesale Goods"
        }
    ],
    "sg:phone":"+1   ",
    "sg:postcode":"07830",
    "sg:province":"NJ",
    "sg:tags":[
        "camp",
        "crop",
        "general"
    ],
    "wof:name":"Applewood Farm",
    "wof:placetype":"venue"
},
  "geometry": {"coordinates":[-74.75916599999999,40.699045],"type":"Point"}
}