{
  "type": "Feature",
  "properties": {
    "iso:country":"US",
    "sg:address":"283 Barr Ave",
    "sg:city":"Teaneck",
    "sg:classifiers":[
        {
            "category":"Professional",
            "subcategory":"Management & Consulting",
            "type":"Services"
        }
    ],
    "sg:phone":"+1 201 525 4859",
    "sg:postcode":"07666",
    "sg:province":"NJ",
    "wof:name":"Paris Enterprises",
    "wof:placetype":"venue"
},
  "geometry": {"coordinates":[-74.01684400000001,40.886579],"type":"Point"}
}