{
  "type": "Feature",
  "properties": {
    "iso:country":"US",
    "sg:address":"202 Halls Mill Rd",
    "sg:city":"Oldwick",
    "sg:classifiers":[
        {
            "category":"Insurance",
            "subcategory":"Insurance Agent",
            "type":"Services"
        }
    ],
    "sg:phone":"+1 908 439 2706",
    "sg:postcode":"08833",
    "sg:province":"NJ",
    "wof:name":"Chubb Group Of Insurance Co",
    "wof:placetype":"venue"
},
  "geometry": {"coordinates":[-74.77442600000001,40.646583],"type":"Point"}
}