{
  "type": "Feature",
  "properties": {
    "iso:country":"US",
    "sg:address":"1 N New York Rd",
    "sg:city":"Absecon",
    "sg:classifiers":[
        {
            "category":"Insurance",
            "subcategory":"Insurance Agent",
            "type":"Services"
        }
    ],
    "sg:phone":"+1 609 748 2121",
    "sg:postcode":"08205",
    "sg:province":"NJ",
    "wof:name":"Richard F Marshall",
    "wof:placetype":"venue"
},
  "geometry": {"coordinates":[-74.457365,39.496624],"type":"Point"}
}