{
  "type": "Feature",
  "properties": {
    "addr:full":"401 Federal St Camden NJ 08105",
    "addr:housenumber":"401",
    "addr:postcode":"08105",
    "addr:street":"Federal St",
    "iso:country":"US",
    "sg:address":"401 Federal St",
    "sg:city":"Camden",
    "sg:classifiers":[
        {
            "category":"Insurance",
            "subcategory":"Insurance Agent",
            "type":"Services"
        }
    ],
    "sg:phone":"+1 856 662 7036",
    "sg:postcode":"08105",
    "sg:province":"NJ",
    "wof:name":"Equitable Life Health & Accidn",
    "wof:placetype":"venue"
},
  "geometry": {"coordinates":[-75.121596,39.944114],"type":"Point"}
}