{
  "type": "Feature",
  "properties": {
    "addr:full":"1235 W Chestnut St Union NJ 07083",
    "addr:housenumber":"1235",
    "addr:postcode":"07083",
    "addr:street":"W Chestnut St",
    "iso:country":"US",
    "sg:address":"1235 W Chestnut St",
    "sg:city":"Union",
    "sg:classifiers":[
        {
            "category":"Social Services",
            "subcategory":"Job Training",
            "type":"Services"
        }
    ],
    "sg:phone":"+1 908 964 4002",
    "sg:postcode":"07083",
    "sg:province":"NJ",
    "sg:tags":[
        "rehabilitation"
    ],
    "wof:name":"Optimum Rehabilitation Ctr LLC",
    "wof:placetype":"venue"
},
  "geometry": {"coordinates":[-74.28910500000001,40.69116],"type":"Point"}
}