{
  "type": "Feature",
  "properties": {
    "iso:country":"US",
    "sg:address":"345 Main Ave",
    "sg:city":"Wallington",
    "sg:classifiers":[
        {
            "category":"Home & Garden",
            "subcategory":"Household Appliances",
            "type":"Retail Goods"
        }
    ],
    "sg:phone":"+1 973 777 7654",
    "sg:postcode":"07057",
    "sg:province":"NJ",
    "wof:name":"Sudol's Used Appliances",
    "wof:placetype":"venue"
},
  "geometry": {"coordinates":[-74.105527,40.859272],"type":"Point"}
}