{
  "type": "Feature",
  "properties": {
    "addr:full":"104 12th Ave Newark NJ 07107",
    "addr:housenumber":"104",
    "addr:postcode":"07107",
    "addr:street":"12Th Ave",
    "iso:country":"US",
    "sg:address":"104 12th Ave",
    "sg:city":"Newark",
    "sg:classifiers":[
        {
            "category":"Shopping",
            "subcategory":"Pharmacy",
            "type":"Retail Goods"
        }
    ],
    "sg:phone":"+1   ",
    "sg:postcode":"07107",
    "sg:province":"NJ",
    "wof:name":"Eckerd",
    "wof:placetype":"venue"
},
  "geometry": {"coordinates":[-74.19176899999999,40.742663],"type":"Point"}
}