{
  "type": "Feature",
  "properties": {
    "addr:full":"44 Ridge Rd Ste 1 North Arlington NJ 07031",
    "addr:housenumber":"44",
    "addr:postcode":"07031",
    "addr:street":"Ridge Rd Ste 1 North",
    "iso:country":"US",
    "sg:address":"44 Ridge Rd Ste 1",
    "sg:city":"North Arlington",
    "sg:classifiers":[
        {
            "category":"Health Services",
            "subcategory":"Health Practitioner",
            "type":"Services"
        }
    ],
    "sg:phone":"+1 201 998 6300",
    "sg:postcode":"07031",
    "sg:province":"NJ",
    "sg:tags":[
        "therapy",
        "physical"
    ],
    "wof:name":"Garden State Physical Therapy",
    "wof:placetype":"venue"
},
  "geometry": {"coordinates":[-74.137209,40.783126],"type":"Point"}
}