{
  "type": "Feature",
  "properties": {
    "iso:country":"US",
    "sg:address":"5 Ave F",
    "sg:city":"Kendall Park",
    "sg:classifiers":[
        {
            "category":"Building & Trades",
            "subcategory":"Construction",
            "type":"Services"
        }
    ],
    "sg:phone":"+1 732 297 2439",
    "sg:postcode":"08824",
    "sg:province":"NJ",
    "sg:tags":[
        "general",
        "contractor"
    ],
    "wof:name":"James E O'Neill General Contr",
    "wof:placetype":"venue"
},
  "geometry": {"coordinates":[-74.522021,40.435469],"type":"Point"}
}