{
  "type": "Feature",
  "properties": {
    "addr:full":"191 County Rd Tenafly NJ 07670",
    "addr:housenumber":"191",
    "addr:postcode":"07670",
    "addr:street":"County Rd",
    "iso:country":"US",
    "sg:address":"191 County Rd",
    "sg:city":"Tenafly",
    "sg:classifiers":[
        {
            "category":"Retail",
            "subcategory":"Laundry & Dry Cleaning",
            "type":"Services"
        }
    ],
    "sg:phone":"+1 201 503 1984",
    "sg:postcode":"07670",
    "sg:province":"NJ",
    "sg:tags":[
        "cleaners"
    ],
    "wof:name":"Century Cleaners",
    "wof:placetype":"venue"
},
  "geometry": {"coordinates":[-73.960914,40.930304],"type":"Point"}
}