{
  "type": "Feature",
  "properties": {
    "iso:country":"US",
    "sg:address":"540 North Ave E",
    "sg:city":"Elizabeth",
    "sg:classifiers":[
        {
            "category":"Professional",
            "subcategory":"Lawyer & Legal Services",
            "type":"Services"
        }
    ],
    "sg:phone":"+1 908 561 5577",
    "sg:postcode":"07201",
    "sg:province":"NJ",
    "sg:tags":[
        "attorney"
    ],
    "sg:website":"www.aielloharris.com",
    "wof:name":"Aiello Harris Marth Schiffman",
    "wof:placetype":"venue"
},
  "geometry": {"coordinates":[-74.180859,40.670896],"type":"Point"}
}