{
  "type": "Feature",
  "properties": {
    "addr:full":"622 Cooper St Camden NJ 08102",
    "addr:housenumber":"622",
    "addr:postcode":"08102",
    "addr:street":"Cooper St",
    "iso:country":"US",
    "sg:address":"622 Cooper St",
    "sg:city":"Camden",
    "sg:classifiers":[
        {
            "category":"Professional",
            "subcategory":"Management & Consulting",
            "type":"Services"
        },
        {
            "category":"Professional",
            "subcategory":"Business Services",
            "type":"Services"
        }
    ],
    "sg:phone":"+1 856 966 8006",
    "sg:postcode":"08102",
    "sg:province":"NJ",
    "sg:tags":[
        "consultant",
        "organizing",
        "services-household"
    ],
    "wof:name":"Bpum Economic Development Corporation",
    "wof:placetype":"venue"
},
  "geometry": {"coordinates":[-75.11846199999999,39.946381],"type":"Point"}
}