{
  "type": "Feature",
  "properties": {
    "addr:full":"1111 S Clinton Ave Trenton NJ 08611",
    "addr:housenumber":"1111",
    "addr:postcode":"08611",
    "addr:street":"S Clinton Ave",
    "iso:country":"US",
    "sg:address":"1111 S Clinton Ave",
    "sg:city":"Trenton",
    "sg:classifiers":[
        {
            "category":"Real Estate",
            "subcategory":"Real Estate Agent",
            "type":"Services"
        }
    ],
    "sg:phone":"+1   ",
    "sg:postcode":"08611",
    "sg:province":"NJ",
    "sg:tags":[
        "consultant",
        "appraisal"
    ],
    "wof:name":"Associates Appraisal Agency",
    "wof:placetype":"venue"
},
  "geometry": {"coordinates":[-74.74543199999999,40.206863],"type":"Point"}
}