{
  "type": "Feature",
  "properties": {
    "iso:country":"US",
    "sg:address":"1708 4th Ave",
    "sg:city":"Toms River",
    "sg:classifiers":[
        {
            "category":"Professional",
            "type":"Services"
        }
    ],
    "sg:phone":"+1   ",
    "sg:postcode":"08757",
    "sg:province":"NJ",
    "wof:name":"ARS Machine Inc",
    "wof:placetype":"venue"
},
  "geometry": {"coordinates":[-74.24678400000001,39.998581],"type":"Point"}
}