{
  "type": "Feature",
  "properties": {
    "iso:country":"US",
    "sg:address":"10 Osage Ct",
    "sg:city":"Flemington",
    "sg:classifiers":[
        {
            "category":"Shopping",
            "subcategory":"Computers & Home Electronics",
            "type":"Retail Goods"
        }
    ],
    "sg:phone":"+1   ",
    "sg:postcode":"08822",
    "sg:province":"NJ",
    "wof:name":"Bgm Computer Services",
    "wof:placetype":"venue"
},
  "geometry": {"coordinates":[-74.755134,40.559081],"type":"Point"}
}