{
  "type": "Feature",
  "properties": {
    "addr:full":"546 Green Ln Union NJ 07083",
    "addr:housenumber":"546",
    "addr:postcode":"07083",
    "addr:street":"Green Ln",
    "iso:country":"US",
    "sg:address":"546 Green Ln",
    "sg:city":"Union",
    "sg:classifiers":[
        {
            "category":"Retail",
            "subcategory":"Laundry & Dry Cleaning",
            "type":"Services"
        }
    ],
    "sg:phone":"+1 973 374 5800",
    "sg:postcode":"07083",
    "sg:province":"NJ",
    "sg:tags":[
        "uniform",
        "supply"
    ],
    "wof:name":"Cintas The Uniform People",
    "wof:placetype":"venue"
},
  "geometry": {"coordinates":[-74.24633300000001,40.676637],"type":"Point"}
}