{
  "type": "Feature",
  "properties": {
    "iso:country":"US",
    "sg:address":"9 Hackberry Pl",
    "sg:city":"Flemington",
    "sg:classifiers":[
        {
            "category":"Shopping",
            "subcategory":"Optical Goods",
            "type":"Retail Goods"
        }
    ],
    "sg:phone":"+1 908 782 5101",
    "sg:postcode":"08822",
    "sg:province":"NJ",
    "sg:tags":[
        "optician"
    ],
    "wof:name":"Shiffman Guild Opticians",
    "wof:placetype":"venue"
},
  "geometry": {"coordinates":[-74.834086,40.499017],"type":"Point"}
}