{
  "type": "Feature",
  "properties": {
    "addr:full":"278 Stevens Ave Jersey City NJ 07305",
    "addr:housenumber":"278",
    "addr:postcode":"07305",
    "addr:street":"Stevens Ave",
    "iso:country":"US",
    "sg:address":"278 Stevens Ave",
    "sg:city":"Jersey City",
    "sg:classifiers":[
        {
            "category":"Retail",
            "subcategory":"Portrait Studio",
            "type":"Services"
        }
    ],
    "sg:phone":"+1   ",
    "sg:postcode":"07305",
    "sg:province":"NJ",
    "sg:tags":[
        "photo"
    ],
    "wof:name":"Ernie Paniccioli",
    "wof:placetype":"venue"
},
  "geometry": {"coordinates":[-74.09514799999999,40.706549],"type":"Point"}
}