{
  "type": "Feature",
  "properties": {
    "addr:full":"86 Caldwell Ave Paterson NJ 07501",
    "addr:housenumber":"86",
    "addr:postcode":"07501",
    "addr:street":"Caldwell Ave",
    "iso:country":"US",
    "sg:address":"86 Caldwell Ave",
    "sg:city":"Paterson",
    "sg:classifiers":[
        {
            "category":"Professional",
            "subcategory":"Detective & Security Services",
            "type":"Services"
        }
    ],
    "sg:phone":"+1 973 345 6688",
    "sg:postcode":"07501",
    "sg:province":"NJ",
    "sg:tags":[
        "car"
    ],
    "wof:name":"Pro Tech Security",
    "wof:placetype":"venue"
},
  "geometry": {"coordinates":[-74.191006,40.910017],"type":"Point"}
}