{
  "type": "Feature",
  "properties": {
    "iso:country":"US",
    "sg:address":"630 Huyler St",
    "sg:city":"South Hackensack",
    "sg:classifiers":[
        {
            "category":"Wholesale",
            "subcategory":"Drugs",
            "type":"Manufacturing & Wholesale Goods"
        }
    ],
    "sg:phone":"+1 201 440 9150",
    "sg:postcode":"07606",
    "sg:province":"NJ",
    "sg:tags":[
        "preparation",
        "product",
        "haircare"
    ],
    "sg:website":"www.europeannaturals.com",
    "wof:name":"Oradell International Corp",
    "wof:placetype":"venue"
},
  "geometry": {"coordinates":[-74.051677,40.857692],"type":"Point"}
}