{
  "type": "Feature",
  "properties": {
    "iso:country":"US",
    "sg:address":"17 Burnside Ave",
    "sg:city":"Cranford",
    "sg:classifiers":[
        {
            "category":"Communications",
            "subcategory":"Film & Video Production",
            "type":"Services"
        }
    ],
    "sg:phone":"+1 908 497 0967",
    "sg:postcode":"07016",
    "sg:province":"NJ",
    "sg:tags":[
        "taping"
    ],
    "wof:name":"Tele Promotion Video Inc",
    "wof:placetype":"venue"
},
  "geometry": {"coordinates":[-74.311061,40.652729],"type":"Point"}
}