{
  "type": "Feature",
  "properties": {
    "iso:country":"US",
    "sg:address":"31 Molly Pitcher Ln",
    "sg:city":"Freehold",
    "sg:classifiers":[
        {
            "category":"Wholesale",
            "subcategory":"Stationery",
            "type":"Manufacturing & Wholesale Goods"
        }
    ],
    "sg:phone":"+1 732 761 2051",
    "sg:postcode":"07728",
    "sg:province":"NJ",
    "sg:tags":[
        "paper",
        "transportation"
    ],
    "wof:name":"Dts",
    "wof:placetype":"venue"
},
  "geometry": {"coordinates":[-74.270009,40.289964],"type":"Point"}
}