{
  "type": "Feature",
  "properties": {
    "iso:country":"US",
    "sg:address":"16 Midland Ave",
    "sg:city":"Elmwood Park",
    "sg:classifiers":[
        {
            "category":"Professional",
            "subcategory":"Art Services",
            "type":"Services"
        }
    ],
    "sg:phone":"+1   ",
    "sg:postcode":"07407",
    "sg:province":"NJ",
    "sg:tags":[
        "photography",
        "commercial"
    ],
    "wof:name":"Medco Tools",
    "wof:placetype":"venue"
},
  "geometry": {"coordinates":[-74.10403599999999,40.898261],"type":"Point"}
}