{
  "type": "Feature",
  "properties": {
    "iso:country":"US",
    "sg:address":"505 Goffle Rd",
    "sg:city":"Ridgewood",
    "sg:classifiers":[
        {
            "category":"Professional",
            "subcategory":"Lawyer & Legal Services",
            "type":"Services"
        }
    ],
    "sg:phone":"+1 201 444 4000",
    "sg:postcode":"07450",
    "sg:province":"NJ",
    "sg:tags":[
        "attorney"
    ],
    "wof:name":"Seigel & Associates",
    "wof:placetype":"venue"
},
  "geometry": {"coordinates":[-74.14549100000001,40.977371],"type":"Point"}
}