{
  "type": "Feature",
  "properties": {
    "addr:full":"25 Meadow Green Cir Manalapan NJ 07726",
    "addr:housenumber":"25",
    "addr:postcode":"07726",
    "addr:street":"Meadow Green Cir",
    "iso:country":"US",
    "sg:address":"25 Meadow Green Cir",
    "sg:city":"Manalapan",
    "sg:classifiers":[
        {
            "category":"Wholesale",
            "subcategory":"Scrap",
            "type":"Manufacturing & Wholesale Goods"
        }
    ],
    "sg:phone":"+1 732 617 0076",
    "sg:postcode":"07726",
    "sg:province":"NJ",
    "sg:tags":[
        "recycling",
        "center"
    ],
    "wof:name":"Powertrain Recycling",
    "wof:placetype":"venue"
},
  "geometry": {"coordinates":[-74.314471,40.3333],"type":"Point"}
}