{
  "type": "Feature",
  "properties": {
    "addr:full":"2200 Mount Holly Rd Burlington NJ 08016",
    "addr:housenumber":"2200",
    "addr:postcode":"08016",
    "addr:street":"Mount Holly Rd",
    "iso:country":"US",
    "sg:address":"2200 Mount Holly Rd",
    "sg:city":"Burlington",
    "sg:classifiers":[
        {
            "category":"Building & Trades",
            "subcategory":"Locksmith",
            "type":"Services"
        }
    ],
    "sg:phone":"+1 609 479 4066",
    "sg:postcode":"08016",
    "sg:province":"NJ",
    "sg:tags":[
        "key"
    ],
    "wof:name":"A 1 Emergency Locksmith",
    "wof:placetype":"venue"
},
  "geometry": {"coordinates":[-74.840034,40.049979],"type":"Point"}
}