{
  "type": "Feature",
  "properties": {
    "iso:country":"US",
    "sg:address":"Heights Chiropractic",
    "sg:city":"Berkeley Heights",
    "sg:classifiers":[
        {
            "category":"Health Services",
            "subcategory":"Chiropractor",
            "type":"Services"
        }
    ],
    "sg:phone":"+1 908 665 0770",
    "sg:postcode":"07922",
    "sg:province":"NJ",
    "wof:name":"Grauso Joseph A DC",
    "wof:placetype":"venue"
},
  "geometry": {"coordinates":[-74.431099,40.676102],"type":"Point"}
}