{
  "type": "Feature",
  "properties": {
    "iso:country":"US",
    "sg:address":"1715 47th St",
    "sg:city":"Pennsauken",
    "sg:classifiers":[
        {
            "category":"Retail",
            "subcategory":"Laundry & Dry Cleaning",
            "type":"Services"
        }
    ],
    "sg:phone":"+1 856 910 7375",
    "sg:postcode":"08110",
    "sg:province":"NJ",
    "sg:tags":[
        "cleaners",
        "rug",
        "carpet"
    ],
    "wof:name":"A-Tnt Carpet Cleaning",
    "wof:placetype":"venue"
},
  "geometry": {"coordinates":[-75.070032,39.96006],"type":"Point"}
}