{
  "type": "Feature",
  "properties": {
    "addr:full":"685 Delsea Dr N Glassboro NJ 08028",
    "addr:housenumber":"685",
    "addr:postcode":"08028",
    "addr:street":"Delsea Dr N",
    "iso:country":"US",
    "sg:address":"685 Delsea Dr N",
    "sg:city":"Glassboro",
    "sg:classifiers":[
        {
            "category":"Restaurant",
            "type":"Food & Drink"
        }
    ],
    "sg:menulink":"http://www.allmenus.com/nj/glassboro/181683-wendys/menu/",
    "sg:phone":"+1 856 863 3980",
    "sg:postcode":"08028",
    "sg:province":"NJ",
    "sg:tags":[
        "burger",
        "american",
        "soup"
    ],
    "wof:name":"Wendy's",
    "wof:placetype":"venue"
},
  "geometry": {"coordinates":[-75.11447200000001,39.719783],"type":"Point"}
}