{
  "type": "Feature",
  "properties": {
    "addr:full":"1283 Broad St Bloomfield NJ 07003",
    "addr:housenumber":"1283",
    "addr:postcode":"07003",
    "addr:street":"Broad St",
    "iso:country":"US",
    "sg:address":"1283 Broad St",
    "sg:city":"Bloomfield",
    "sg:classifiers":[
        {
            "category":"Real Estate",
            "subcategory":"Real Estate Agent",
            "type":"Services"
        }
    ],
    "sg:phone":"+1   ",
    "sg:postcode":"07003",
    "sg:province":"NJ",
    "sg:tags":[
        "residential",
        "commercial",
        "investment"
    ],
    "wof:name":"Century 21 Gemini Inc",
    "wof:placetype":"venue"
},
  "geometry": {"coordinates":[-74.18079899999999,40.833993],"type":"Point"}
}