{
  "type": "Feature",
  "properties": {
    "addr:full":"614 S Black Horse Pike Blackwood NJ 08012",
    "addr:housenumber":"614",
    "addr:postcode":"08012",
    "addr:street":"S Black Horse Pike",
    "iso:country":"US",
    "sg:address":"614 S Black Horse Pike",
    "sg:city":"Blackwood",
    "sg:classifiers":[
        {
            "category":"Wholesale",
            "subcategory":"Non-durable Goods",
            "type":"Manufacturing & Wholesale Goods"
        }
    ],
    "sg:phone":"+1 856 227 6529",
    "sg:postcode":"08012",
    "sg:province":"NJ",
    "sg:tags":[
        "candle"
    ],
    "wof:name":"Brite Ideas Fund Raising LLC",
    "wof:placetype":"venue"
},
  "geometry": {"coordinates":[-75.059776,39.790858],"type":"Point"}
}