{
  "type": "Feature",
  "properties": {
    "addr:full":"1784 State Rte 27 Edison NJ 08817",
    "addr:housenumber":"1784",
    "addr:postcode":"08817",
    "addr:street":"State Rte 27",
    "iso:country":"US",
    "sg:address":"1784 State Rte 27",
    "sg:city":"Edison",
    "sg:classifiers":[
        {
            "category":"Food & Beverages",
            "subcategory":"Specialty",
            "type":"Retail Goods"
        }
    ],
    "sg:phone":"+1 732 339 9889",
    "sg:postcode":"08817",
    "sg:province":"NJ",
    "sg:tags":[
        "product",
        "chinese"
    ],
    "wof:name":"Igloo Tea House",
    "wof:placetype":"venue"
},
  "geometry": {"coordinates":[-74.40526199999999,40.513237],"type":"Point"}
}