{
  "type": "Feature",
  "properties": {
    "addr:full":"3350 State Rte 138 Wall Township NJ 07719",
    "addr:housenumber":"3350",
    "addr:postcode":"07719",
    "addr:street":"State Rte 138 Wall",
    "iso:country":"US",
    "sg:address":"3350 State Rte 138",
    "sg:city":"Wall Township",
    "sg:classifiers":[
        {
            "category":"Building & Trades",
            "subcategory":"Equipment Rental",
            "type":"Services"
        }
    ],
    "sg:phone":"+1 732 751 8700",
    "sg:postcode":"07719",
    "sg:province":"NJ",
    "sg:tags":[
        "leasing"
    ],
    "wof:name":"Systems Fullfillment Inc",
    "wof:placetype":"venue"
},
  "geometry": {"coordinates":[-74.09433799999999,40.170255],"type":"Point"}
}