{
  "type": "Feature",
  "properties": {
    "addr:full":"259 State Route 10 East Hanover NJ 07936",
    "addr:housenumber":"259",
    "addr:postcode":"07936",
    "addr:street":"State Route 10",
    "iso:country":"US",
    "sg:address":"259 State Route 10",
    "sg:city":"East Hanover",
    "sg:classifiers":[
        {
            "category":"Autos & Motor Vehicles",
            "subcategory":"Auto Supplies",
            "type":"Retail Goods"
        }
    ],
    "sg:phone":"+1 973 386 1900",
    "sg:postcode":"07936",
    "sg:province":"NJ",
    "sg:tags":[
        "tire"
    ],
    "sg:website":"www.ststire.com",
    "wof:name":"Sts Tire & Auto Centers",
    "wof:placetype":"venue"
},
  "geometry": {"coordinates":[-74.376701,40.808201],"type":"Point"}
}