{
  "type": "Feature",
  "properties": {
    "addr:full":"2225 US Hwy 1 North Brunswick NJ 08902",
    "addr:housenumber":"2225",
    "addr:postcode":"08902",
    "addr:street":"Us Hwy 1",
    "iso:country":"US",
    "sg:address":"2225 US Hwy 1",
    "sg:city":"North Brunswick",
    "sg:classifiers":[
        {
            "category":"Banks & Credit Unions",
            "subcategory":"Bank",
            "type":"Services"
        }
    ],
    "sg:phone":"+1 732 821 8540",
    "sg:postcode":"08902",
    "sg:province":"NJ",
    "sg:tags":[
        "financing"
    ],
    "wof:name":"Citi Financial",
    "wof:placetype":"venue"
},
  "geometry": {"coordinates":[-74.499993,40.444769],"type":"Point"}
}