{
  "type": "Feature",
  "properties": {
    "iso:country":"US",
    "sg:address":"476 Berkshire Rd",
    "sg:city":"Ridgewood",
    "sg:classifiers":[
        {
            "category":"Retail",
            "subcategory":"Repair Shop",
            "type":"Services"
        }
    ],
    "sg:phone":"+1 201 444 1900",
    "sg:postcode":"07450",
    "sg:province":"NJ",
    "sg:tags":[
        "appliance"
    ],
    "wof:name":"A & H Appliance & Svc",
    "wof:placetype":"venue"
},
  "geometry": {"coordinates":[-74.100853,40.962304],"type":"Point"}
}