{
  "type": "Feature",
  "properties": {
    "addr:full":"73 Gould St Bayonne NJ 07002",
    "addr:housenumber":"73",
    "addr:postcode":"07002",
    "addr:street":"Gould St",
    "iso:country":"US",
    "sg:address":"73 Gould St",
    "sg:city":"Bayonne",
    "sg:classifiers":[
        {
            "category":"Wholesale",
            "subcategory":"Apparel",
            "type":"Manufacturing & Wholesale Goods"
        },
        {
            "category":"Shopping",
            "subcategory":"Clothing, Apparel, & Fashions",
            "type":"Retail Goods"
        }
    ],
    "sg:phone":"+1 201 858 2884",
    "sg:postcode":"07002",
    "sg:province":"NJ",
    "sg:tags":[
        "furnishing"
    ],
    "wof:name":"Neema Clothing Ltd",
    "wof:placetype":"venue"
},
  "geometry": {"coordinates":[-74.10217799999999,40.678706],"type":"Point"}
}