{
  "type": "Feature",
  "properties": {
    "iso:country":"US",
    "sg:address":"1208 Sleepy Hollow Rd",
    "sg:city":"Point Pleasant Beach",
    "sg:classifiers":[
        {
            "category":"Shopping",
            "subcategory":"Department Store",
            "type":"Retail Goods"
        }
    ],
    "sg:phone":"+1   ",
    "sg:postcode":"08742",
    "sg:province":"NJ",
    "wof:name":"Andrew Pazienza Painting & Wal",
    "wof:placetype":"venue"
},
  "geometry": {"coordinates":[-74.08119000000001,40.077103],"type":"Point"}
}