{
  "type": "Feature",
  "properties": {
    "iso:country":"US",
    "sg:address":"1926 Greentree Rd",
    "sg:city":"Cherry Hill",
    "sg:classifiers":[
        {
            "category":"Real Estate",
            "subcategory":"Architect",
            "type":"Services"
        }
    ],
    "sg:phone":"+1 856 751 5661",
    "sg:postcode":"08003",
    "sg:province":"NJ",
    "sg:tags":[
        "civil",
        "engineer"
    ],
    "wof:name":"Notis Architect Engineers",
    "wof:placetype":"venue"
},
  "geometry": {"coordinates":[-74.96328800000001,39.90551],"type":"Point"}
}