{
  "type": "Feature",
  "properties": {
    "iso:country":"US",
    "sg:address":"716 Broadway",
    "sg:city":"Bayonne",
    "sg:classifiers":[
        {
            "category":"Health Services",
            "subcategory":"Chiropractor",
            "type":"Services"
        }
    ],
    "sg:phone":"+1   ",
    "sg:postcode":"07002",
    "sg:province":"NJ",
    "wof:name":"Back & Neck Center",
    "wof:placetype":"venue"
},
  "geometry": {"coordinates":[-74.11223099999999,40.671068],"type":"Point"}
}