{
  "type": "Feature",
  "properties": {
    "iso:country":"US",
    "sg:address":"683 Stokes Rd",
    "sg:city":"Medford",
    "sg:classifiers":[
        {
            "category":"Building & Trades",
            "subcategory":"Construction",
            "type":"Services"
        }
    ],
    "sg:phone":"+1 609 654 1050",
    "sg:postcode":"08055",
    "sg:province":"NJ",
    "sg:tags":[
        "contractor"
    ],
    "wof:name":"OConnell Screen Repair",
    "wof:placetype":"venue"
},
  "geometry": {"coordinates":[-74.811662,39.872207],"type":"Point"}
}