{
  "type": "Feature",
  "properties": {
    "iso:country":"US",
    "sg:address":"13 Shetland Dr",
    "sg:city":"Cranford",
    "sg:classifiers":[
        {
            "category":"Building & Trades",
            "subcategory":"Construction",
            "type":"Services"
        }
    ],
    "sg:phone":"+1 908 276 9363",
    "sg:postcode":"07016",
    "sg:province":"NJ",
    "sg:tags":[
        "house",
        "nonresidential"
    ],
    "wof:name":"Greenstein Enterprises",
    "wof:placetype":"venue"
},
  "geometry": {"coordinates":[-74.30880399999999,40.643654],"type":"Point"}
}