{
  "type": "Feature",
  "properties": {
    "iso:country":"US",
    "sg:address":"464 Sayre Dr",
    "sg:city":"Princeton",
    "sg:classifiers":[
        {
            "category":"Professional",
            "subcategory":"Management & Consulting",
            "type":"Services"
        }
    ],
    "sg:phone":"+1   ",
    "sg:postcode":"08540",
    "sg:province":"NJ",
    "wof:name":"Ciello Marketing & Strategy",
    "wof:placetype":"venue"
},
  "geometry": {"coordinates":[-74.61917699999999,40.350671],"type":"Point"}
}