{
  "type": "Feature",
  "properties": {
    "addr:full":"1000 Asbury Ave Ocean City NJ 08226",
    "addr:housenumber":"1000",
    "addr:postcode":"08226",
    "addr:street":"Asbury Ave",
    "iso:country":"US",
    "sg:address":"1000 Asbury Ave",
    "sg:city":"Ocean City",
    "sg:classifiers":[
        {
            "category":"Banks & Credit Unions",
            "subcategory":"Bank",
            "type":"Services"
        }
    ],
    "sg:phone":"+1   ",
    "sg:postcode":"08226",
    "sg:province":"NJ",
    "sg:tags":[
        "federal",
        "savings"
    ],
    "sg:website":"www.capebankonline2.com",
    "wof:name":"Cape Savings Bank",
    "wof:placetype":"venue"
},
  "geometry": {"coordinates":[-74.57917500000001,39.276666],"type":"Point"}
}