{
  "type": "Feature",
  "properties": {
    "addr:full":"2 Jackson Dr Cranford NJ 07016",
    "addr:housenumber":"2",
    "addr:postcode":"07016",
    "addr:street":"Jackson Dr",
    "iso:country":"US",
    "sg:address":"2 Jackson Dr",
    "sg:city":"Cranford",
    "sg:classifiers":[
        {
            "category":"Travel",
            "subcategory":"Hotels & Motels",
            "type":"Entertainment"
        }
    ],
    "sg:phone":"+1 908 709 1980",
    "sg:postcode":"07016",
    "sg:province":"NJ",
    "wof:name":"Homewood Suites by Hilton",
    "wof:placetype":"venue"
},
  "geometry": {"coordinates":[-74.287897,40.640524],"type":"Point"}
}