{
  "type": "Feature",
  "properties": {
    "addr:full":"14 Dailey Dr Trenton NJ 08620",
    "addr:housenumber":"14",
    "addr:postcode":"08620",
    "addr:street":"Dailey Dr",
    "iso:country":"US",
    "sg:address":"14 Dailey Dr",
    "sg:city":"Trenton",
    "sg:classifiers":[
        {
            "category":"Building & Trades",
            "subcategory":"Plumbing",
            "type":"Services"
        }
    ],
    "sg:phone":"+1 609 585 3309",
    "sg:postcode":"08620",
    "sg:province":"NJ",
    "sg:tags":[
        "contractor"
    ],
    "wof:name":"McVay Heating and Air Corp",
    "wof:placetype":"venue"
},
  "geometry": {"coordinates":[-74.683223,40.183971],"type":"Point"}
}