{
  "type": "Feature",
  "properties": {
    "iso:country":"US",
    "sg:address":"116 W Riding Rd",
    "sg:city":"Cherry Hill",
    "sg:classifiers":[
        {
            "category":"Organizations",
            "subcategory":"Religious Organization",
            "type":"Services"
        }
    ],
    "sg:phone":"+1 856 354 9613",
    "sg:postcode":"08003",
    "sg:province":"NJ",
    "sg:tags":[
        "clergy"
    ],
    "wof:name":"Raymond F Weigle Rev",
    "wof:placetype":"venue"
},
  "geometry": {"coordinates":[-74.99038,39.891895],"type":"Point"}
}