{
  "type": "Feature",
  "properties": {
    "addr:full":"181 US Hwy 46 Dover NJ 07803",
    "addr:housenumber":"181",
    "addr:postcode":"07803",
    "addr:street":"Us Hwy 46",
    "iso:country":"US",
    "sg:address":"181 US Hwy 46",
    "sg:city":"Dover",
    "sg:classifiers":[
        {
            "category":"Health Services",
            "subcategory":"Doctor",
            "type":"Services"
        }
    ],
    "sg:phone":"+1 973 361 1081",
    "sg:postcode":"07803",
    "sg:province":"NJ",
    "sg:tags":[
        "physician",
        "surgeon",
        "pediatrician"
    ],
    "wof:name":"Ilene M Hershman PC",
    "wof:placetype":"venue"
},
  "geometry": {"coordinates":[-74.59572199999999,40.880356],"type":"Point"}
}