{
  "type": "Feature",
  "properties": {
    "addr:full":"777 N Clinton Ave Trenton NJ 08638",
    "addr:housenumber":"777",
    "addr:postcode":"08638",
    "addr:street":"N Clinton Ave",
    "iso:country":"US",
    "sg:address":"777 N Clinton Ave",
    "sg:city":"Trenton",
    "sg:classifiers":[
        {
            "category":"Building & Trades",
            "subcategory":"Electrical",
            "type":"Services"
        }
    ],
    "sg:phone":"+1 609 392 1519",
    "sg:postcode":"08638",
    "sg:province":"NJ",
    "sg:tags":[
        "electric",
        "contractor"
    ],
    "wof:name":"East Coast Electric",
    "wof:placetype":"venue"
},
  "geometry": {"coordinates":[-74.7414,40.23319],"type":"Point"}
}