{
  "type": "Feature",
  "properties": {
    "iso:country":"US",
    "sg:address":"44 High St",
    "sg:city":"Mullica Hill",
    "sg:classifiers":[
        {
            "category":"Organizations",
            "subcategory":"Religious Organization",
            "type":"Services"
        }
    ],
    "sg:phone":"+1 856 478 2511",
    "sg:postcode":"08062",
    "sg:province":"NJ",
    "sg:tags":[
        "church"
    ],
    "wof:name":"Mount Calvary Baptist Church",
    "wof:placetype":"venue"
},
  "geometry": {"coordinates":[-75.232056,39.731951],"type":"Point"}
}