{
  "type": "Feature",
  "properties": {
    "iso:country":"US",
    "sg:address":"221 Morris Ave",
    "sg:city":"Springfield",
    "sg:classifiers":[
        {
            "category":"Personal",
            "subcategory":"Beauty Salon",
            "type":"Services"
        }
    ],
    "sg:phone":"+1 973 376 4373",
    "sg:postcode":"07081",
    "sg:province":"NJ",
    "sg:tags":[
        "shop"
    ],
    "wof:name":"Norma's Salon",
    "wof:placetype":"venue"
},
  "geometry": {"coordinates":[-74.310852,40.710953],"type":"Point"}
}