{
  "type": "Feature",
  "properties": {
    "iso:country":"US",
    "sg:address":"200 E Park Dr",
    "sg:city":"Mt Laurel",
    "sg:classifiers":[
        {
            "category":"Professional",
            "subcategory":"Credit Reporting & Collection",
            "type":"Services"
        }
    ],
    "sg:phone":"+1 856 779 8160",
    "sg:postcode":"08054",
    "sg:province":"NJ",
    "sg:tags":[
        "agency"
    ],
    "wof:name":"Financial Recoveries",
    "wof:placetype":"venue"
},
  "geometry": {"coordinates":[-74.95142800000001,39.934549],"type":"Point"}
}