{
  "type": "Feature",
  "properties": {
    "iso:country":"US",
    "sg:address":"221 Lafayette St",
    "sg:city":"Roselle",
    "sg:classifiers":[
        {
            "category":"Education",
            "subcategory":"School",
            "type":"Public Place"
        }
    ],
    "sg:phone":"+1 908 241 7650",
    "sg:postcode":"07203",
    "sg:province":"NJ",
    "wof:name":"Josephs School of Tomorrow In",
    "wof:placetype":"venue"
},
  "geometry": {"coordinates":[-74.280491,40.655382],"type":"Point"}
}