{
  "type": "Feature",
  "properties": {
    "addr:full":"368 S Tuckahoe Rd Williamstown NJ 08094",
    "addr:housenumber":"368",
    "addr:postcode":"08094",
    "addr:street":"S Tuckahoe Rd",
    "iso:country":"US",
    "sg:address":"368 S Tuckahoe Rd",
    "sg:city":"Williamstown",
    "sg:classifiers":[
        {
            "category":"Social Services",
            "subcategory":"Child Care",
            "type":"Services"
        }
    ],
    "sg:phone":"+1 856 262 0861",
    "sg:postcode":"08094",
    "sg:province":"NJ",
    "sg:tags":[
        "day"
    ],
    "wof:name":"E-Z Start",
    "wof:placetype":"venue"
},
  "geometry": {"coordinates":[-75.01884099999999,39.658321],"type":"Point"}
}