{
  "type": "Feature",
  "properties": {
    "iso:country":"US",
    "sg:address":"79 Cypress Ave",
    "sg:city":"Jackson",
    "sg:classifiers":[
        {
            "category":"Professional",
            "subcategory":"Business Services",
            "type":"Services"
        }
    ],
    "sg:phone":"+1   ",
    "sg:postcode":"08527",
    "sg:province":"NJ",
    "sg:tags":[
        "special",
        "investigator"
    ],
    "wof:name":"Edward A Hegstetter",
    "wof:placetype":"venue"
},
  "geometry": {"coordinates":[-74.285718,40.129367],"type":"Point"}
}