{
  "type": "Feature",
  "properties": {
    "iso:country":"US",
    "sg:address":"606 Wardell St",
    "sg:city":"Long Branch",
    "sg:classifiers":[
        {
            "category":"Arts & Performance",
            "subcategory":"Theater",
            "type":"Entertainment"
        }
    ],
    "sg:phone":"+1 732 222 5556",
    "sg:postcode":"07740",
    "sg:province":"NJ",
    "sg:tags":[
        "entertainer",
        "group"
    ],
    "wof:name":"A Pure Satisfaction",
    "wof:placetype":"venue"
},
  "geometry": {"coordinates":[-74.00658900000001,40.306648],"type":"Point"}
}