{
  "type": "Feature",
  "properties": {
    "iso:country":"US",
    "sg:address":"88 Rock Rd E",
    "sg:city":"Dunellen",
    "sg:classifiers":[
        {
            "category":"Professional",
            "subcategory":"Management & Consulting",
            "type":"Services"
        }
    ],
    "sg:phone":"+1 908 822 9812",
    "sg:postcode":"08812",
    "sg:province":"NJ",
    "sg:tags":[
        "consultant"
    ],
    "wof:name":"Enlighten Corporation",
    "wof:placetype":"venue"
},
  "geometry": {"coordinates":[-74.467122,40.619259],"type":"Point"}
}