{
  "type": "Feature",
  "properties": {
    "iso:country":"US",
    "sg:address":"14 Washington Ave",
    "sg:city":"Princeton",
    "sg:classifiers":[
        {
            "category":"Professional",
            "subcategory":"Computer Services",
            "type":"Services"
        }
    ],
    "sg:phone":"+1   ",
    "sg:postcode":"08540",
    "sg:province":"NJ",
    "sg:tags":[
        "prepackaged",
        "software"
    ],
    "wof:name":"Pdb Software Company Inc",
    "wof:placetype":"venue"
},
  "geometry": {"coordinates":[-74.597151,40.43823],"type":"Point"}
}