{
  "type": "Feature",
  "properties": {
    "iso:country":"US",
    "sg:address":"600 Clinton Ave",
    "sg:city":"Newark",
    "sg:classifiers":[
        {
            "category":"Education",
            "subcategory":"School",
            "type":"Public Place"
        }
    ],
    "sg:phone":"+1 973 622 2016",
    "sg:postcode":"07108",
    "sg:province":"NJ",
    "sg:tags":[
        "high",
        "middle",
        "elementary"
    ],
    "wof:name":"North Star Academy Clinton Hill Campus",
    "wof:placetype":"venue"
},
  "geometry": {"coordinates":[-74.20548599999999,40.722444],"type":"Point"}
}