{
  "type": "Feature",
  "properties": {
    "iso:country":"US",
    "sg:address":"465 Broad Ave",
    "sg:city":"Leonia",
    "sg:classifiers":[
        {
            "category":"Shopping",
            "subcategory":"Books",
            "type":"Retail Goods"
        }
    ],
    "sg:phone":"+1 201 947 3471",
    "sg:postcode":"07605",
    "sg:province":"NJ",
    "sg:tags":[
        "textbook"
    ],
    "wof:name":"Booklink",
    "wof:placetype":"venue"
},
  "geometry": {"coordinates":[-73.983923,40.867208],"type":"Point"}
}