{
  "type": "Feature",
  "properties": {
    "iso:country":"US",
    "sg:address":"1878 State Rte 70",
    "sg:city":"Cherry Hill",
    "sg:classifiers":[
        {
            "category":"Real Estate",
            "subcategory":"Real Estate Agent",
            "type":"Services"
        }
    ],
    "sg:phone":"+1   ",
    "sg:postcode":"08003",
    "sg:province":"NJ",
    "wof:name":"Michael Tcknoff Apprsder Assoc",
    "wof:placetype":"venue"
},
  "geometry": {"coordinates":[-74.968903,39.903731],"type":"Point"}
}