{
  "type": "Feature",
  "properties": {
    "iso:country":"US",
    "sg:address":"1059 State Rte 40",
    "sg:city":"Penns Grove",
    "sg:classifiers":[
        {
            "category":"Retail",
            "subcategory":"Animal Services",
            "type":"Services"
        }
    ],
    "sg:phone":"+1 856 299 9292",
    "sg:postcode":"08069",
    "sg:province":"NJ",
    "wof:name":"Society Hill Pet Care & Boardi",
    "wof:placetype":"venue"
},
  "geometry": {"coordinates":[-75.40961900000001,39.680811],"type":"Point"}
}