{
  "type": "Feature",
  "properties": {
    "iso:country":"US",
    "sg:address":"20 Church St",
    "sg:city":"Camden",
    "sg:classifiers":[
        {
            "category":"Building & Trades",
            "subcategory":"Construction",
            "type":"Services"
        }
    ],
    "sg:phone":"+1 856 966 8117",
    "sg:postcode":"08105",
    "sg:province":"NJ",
    "sg:tags":[
        "carpenter"
    ],
    "sg:website":"http://www.sjcscamden.org",
    "wof:name":"Saint Joseph's Carpenter Society Inc",
    "wof:placetype":"venue"
},
  "geometry": {"coordinates":[-75.08242799999999,39.946861],"type":"Point"}
}