{
  "type": "Feature",
  "properties": {
    "iso:country":"US",
    "sg:address":"570 Egg Harbor Rd Ste D",
    "sg:city":"Sewell",
    "sg:classifiers":[
        {
            "category":"Social Services",
            "subcategory":"Child Care",
            "type":"Services"
        },
        {
            "category":"Education",
            "subcategory":"Preschool",
            "type":"Public Place"
        },
        {
            "category":"Recreation",
            "type":"Entertainment"
        }
    ],
    "sg:phone":"+1 856 582 6199",
    "sg:postcode":"08080",
    "sg:province":"NJ",
    "sg:tags":[
        "kindergarten",
        "nursery",
        "day",
        "camps-recreational"
    ],
    "sg:website":"http://www.beaconacademynj.com/",
    "wof:name":"Beacon Academy Inc",
    "wof:placetype":"venue"
},
  "geometry": {"coordinates":[-75.062763,39.733555],"type":"Point"}
}