{
  "type": "Feature",
  "properties": {
    "addr:full":"187 Brinckerhoff Ct Englewood NJ 07631",
    "addr:housenumber":"187",
    "addr:postcode":"07631",
    "addr:street":"Brinckerhoff Ct",
    "iso:country":"US",
    "sg:address":"187 Brinckerhoff Ct",
    "sg:city":"Englewood",
    "sg:classifiers":[
        {
            "category":"Recreation",
            "type":"Entertainment"
        },
        {
            "category":"Organizations",
            "subcategory":"Community Association",
            "type":"Services"
        }
    ],
    "sg:phone":"+1 201 568 7701",
    "sg:postcode":"07631",
    "sg:province":"NJ",
    "sg:tags":[
        "club",
        "membership"
    ],
    "wof:name":"Woman's Club Of Englewood",
    "wof:placetype":"venue"
},
  "geometry": {"coordinates":[-73.966273,40.89043],"type":"Point"}
}