{
  "type": "Feature",
  "properties": {
    "addr:full":"37 South Ave W Cranford NJ 07016",
    "addr:housenumber":"37",
    "addr:postcode":"07016",
    "addr:street":"South Ave W",
    "iso:country":"US",
    "sg:address":"37 South Ave W",
    "sg:city":"Cranford",
    "sg:classifiers":[
        {
            "category":"Organizations",
            "subcategory":"Religious Organization",
            "type":"Services"
        },
        {
            "category":"Organizations",
            "subcategory":"Non-profit Organization",
            "type":"Services"
        }
    ],
    "sg:phone":"+1 908 272 0888",
    "sg:postcode":"07016",
    "sg:province":"NJ",
    "sg:tags":[
        "service/non-profit",
        "community"
    ],
    "wof:name":"Iselin Christian Assembly",
    "wof:placetype":"venue"
},
  "geometry": {"coordinates":[-74.30860800000001,40.653832],"type":"Point"}
}