{
  "type": "Feature",
  "properties": {
    "addr:full":"1 Oakland Ter Maplewood NJ 07040",
    "addr:housenumber":"1",
    "addr:postcode":"07040",
    "addr:street":"Oakland Ter",
    "iso:country":"US",
    "sg:address":"1 Oakland Ter",
    "sg:city":"Maplewood",
    "sg:classifiers":[
        {
            "category":"Professional",
            "subcategory":"Business Services",
            "type":"Services"
        }
    ],
    "sg:phone":"+1 973 763 0206",
    "sg:postcode":"07040",
    "sg:province":"NJ",
    "wof:name":"Ry Mal Business Solutions",
    "wof:placetype":"venue"
},
  "geometry": {"coordinates":[-74.260274,40.728594],"type":"Point"}
}