{
  "type": "Feature",
  "properties": {
    "iso:country":"US",
    "sg:address":"205 33rd St S",
    "sg:city":"Brigantine",
    "sg:classifiers":[
        {
            "category":"Shopping",
            "subcategory":"Crafts & Fabrics",
            "type":"Retail Goods"
        }
    ],
    "sg:phone":"+1   ",
    "sg:postcode":"08203",
    "sg:province":"NJ",
    "sg:tags":[
        "sewing"
    ],
    "wof:name":"Little Knit Shoppe Inc",
    "wof:placetype":"venue"
},
  "geometry": {"coordinates":[-74.386538,39.39361],"type":"Point"}
}