{
  "type": "Feature",
  "properties": {
    "iso:country":"US",
    "sg:address":"910 Bergen Ave",
    "sg:city":"Jersey City",
    "sg:classifiers":[
        {
            "category":"Freight",
            "type":"Transportation"
        }
    ],
    "sg:phone":"+1 201 792 7777",
    "sg:postcode":"07306",
    "sg:province":"NJ",
    "sg:tags":[
        "mover"
    ],
    "wof:name":"Swift Movers Van Lines Inc",
    "wof:placetype":"venue"
},
  "geometry": {"coordinates":[-74.065657,40.729603],"type":"Point"}
}