{
  "type": "Feature",
  "properties": {
    "addr:full":"220 Jefferson St Newark NJ 07105",
    "addr:housenumber":"220",
    "addr:postcode":"07105",
    "addr:street":"Jefferson St",
    "iso:country":"US",
    "sg:address":"220 Jefferson St",
    "sg:city":"Newark",
    "sg:classifiers":[
        {
            "category":"Travel",
            "subcategory":"Travel Agent",
            "type":"Entertainment"
        }
    ],
    "sg:phone":"+1 973 589 3116",
    "sg:postcode":"07105",
    "sg:province":"NJ",
    "sg:tags":[
        "agency"
    ],
    "wof:name":"Joel Travel Agency Inc",
    "wof:placetype":"venue"
},
  "geometry": {"coordinates":[-74.16462799999999,40.724641],"type":"Point"}
}