{
  "type": "Feature",
  "properties": {
    "addr:full":"526 State Rt 17 Carlstadt NJ 07072",
    "addr:housenumber":"526",
    "addr:postcode":"07072",
    "addr:street":"State Rt 17",
    "iso:country":"US",
    "sg:address":"526 State Rt 17",
    "sg:city":"Carlstadt",
    "sg:classifiers":[
        {
            "category":"Building & Trades",
            "subcategory":"Construction",
            "type":"Services"
        }
    ],
    "sg:phone":"+1 201 935 6679",
    "sg:postcode":"07072",
    "sg:province":"NJ",
    "sg:tags":[
        "contractor"
    ],
    "wof:name":"Dovcon",
    "wof:placetype":"venue"
},
  "geometry": {"coordinates":[-74.084999,40.836102],"type":"Point"}
}