{
  "type": "Feature",
  "properties": {
    "iso:country":"US",
    "sg:address":"60 Governors Ln",
    "sg:city":"Princeton",
    "sg:classifiers":[
        {
            "category":"Professional",
            "subcategory":"Management & Consulting",
            "type":"Services"
        }
    ],
    "sg:phone":"+1 609 924 6386",
    "sg:postcode":"08540",
    "sg:province":"NJ",
    "sg:tags":[
        "medical",
        "administration",
        "business"
    ],
    "wof:name":"Frank Summers",
    "wof:placetype":"venue"
},
  "geometry": {"coordinates":[-74.651116,40.370567],"type":"Point"}
}