{
  "type": "Feature",
  "properties": {
    "iso:country":"US",
    "sg:address":"100 Overlook Dr",
    "sg:city":"Monroe Twp",
    "sg:classifiers":[
        {
            "category":"Health Services",
            "subcategory":"Chiropractor",
            "type":"Services"
        }
    ],
    "sg:phone":"+1 609 395 0880",
    "sg:postcode":"08831",
    "sg:province":"NJ",
    "wof:name":"Blitz Chiropractic Ctr",
    "wof:placetype":"venue"
},
  "geometry": {"coordinates":[-74.45569399999999,40.304108],"type":"Point"}
}