{
  "type": "Feature",
  "properties": {
    "iso:country":"US",
    "sg:address":"600 Main St",
    "sg:city":"Asbury Park",
    "sg:classifiers":[
        {
            "category":"Health Services",
            "subcategory":"Nursing And Care Facility",
            "type":"Services"
        }
    ],
    "sg:phone":"+1   ",
    "sg:postcode":"07712",
    "sg:province":"NJ",
    "sg:tags":[
        "skilled"
    ],
    "wof:name":"Long Term Care Education",
    "wof:placetype":"venue"
},
  "geometry": {"coordinates":[-74.01208200000001,40.219607],"type":"Point"}
}