{
  "type": "Feature",
  "properties": {
    "addr:full":"3134 Haven Ave Ocean City NJ 08226",
    "addr:housenumber":"3134",
    "addr:postcode":"08226",
    "addr:street":"Haven Ave",
    "iso:country":"US",
    "sg:address":"3134 Haven Ave",
    "sg:city":"Ocean City",
    "sg:classifiers":[
        {
            "category":"Professional",
            "type":"Services"
        }
    ],
    "sg:phone":"+1   ",
    "sg:postcode":"08226",
    "sg:province":"NJ",
    "wof:name":"Ocean Beach",
    "wof:placetype":"venue"
},
  "geometry": {"coordinates":[-74.609262,39.255456],"type":"Point"}
}