{
  "type": "Feature",
  "properties": {
    "iso:country":"US",
    "sg:address":"7 Washington St",
    "sg:city":"South Bound Brook",
    "sg:classifiers":[
        {
            "category":"Building & Trades",
            "subcategory":"Plumbing",
            "type":"Services"
        }
    ],
    "sg:phone":"+1   ",
    "sg:postcode":"08880",
    "sg:province":"NJ",
    "sg:tags":[
        "plumbing",
        "sewer",
        "heating",
        "cleaning"
    ],
    "wof:name":"AA Pro Plumbing Htg & Sewer Co",
    "wof:placetype":"venue"
},
  "geometry": {"coordinates":[-74.525201,40.555736],"type":"Point"}
}