{
  "type": "Feature",
  "properties": {
    "addr:full":"194 N Harrison St Princeton NJ 08540",
    "addr:housenumber":"194",
    "addr:postcode":"08540",
    "addr:street":"N Harrison St",
    "iso:country":"US",
    "sg:address":"194 N Harrison St",
    "sg:city":"Princeton",
    "sg:classifiers":[
        {
            "category":"Professional",
            "subcategory":"Computer Services",
            "type":"Services"
        },
        {
            "category":"Shopping",
            "subcategory":"Computers & Home Electronics",
            "type":"Retail Goods"
        }
    ],
    "sg:phone":"+1 609 924 5566",
    "sg:postcode":"08540",
    "sg:province":"NJ",
    "sg:tags":[
        "prepackaged",
        "software"
    ],
    "wof:name":"Brand Com Inc",
    "wof:placetype":"venue"
},
  "geometry": {"coordinates":[-74.64965599999999,40.359245],"type":"Point"}
}