{
  "type": "Feature",
  "properties": {
    "addr:full":"165 Changebridge Rd Montville NJ 07045",
    "addr:housenumber":"165",
    "addr:postcode":"07045",
    "addr:street":"Changebridge Rd",
    "iso:country":"US",
    "sg:address":"165 Changebridge Rd",
    "sg:city":"Montville",
    "sg:classifiers":[
        {
            "category":"Professional",
            "type":"Services"
        }
    ],
    "sg:phone":"+1 973 299 2552",
    "sg:postcode":"07045",
    "sg:province":"NJ",
    "sg:tags":[
        "establishment"
    ],
    "wof:name":"Sundance Rehap Corp",
    "wof:placetype":"venue"
},
  "geometry": {"coordinates":[-74.36534399999999,40.88862],"type":"Point"}
}