{
  "type": "Feature",
  "properties": {
    "iso:country":"US",
    "sg:address":"5 Pine Bluff Rd",
    "sg:city":"Glen Gardner",
    "sg:classifiers":[
        {
            "category":"Professional",
            "subcategory":"Employment Agencies",
            "type":"Services"
        }
    ],
    "sg:phone":"+1 908 537 6520",
    "sg:postcode":"08826",
    "sg:province":"NJ",
    "wof:name":"Eracent Inc",
    "wof:placetype":"venue"
},
  "geometry": {"coordinates":[-74.93800400000001,40.7243],"type":"Point"}
}