{
  "type": "Feature",
  "properties": {
    "iso:country":"US",
    "sg:address":"550 Sunderland Rd",
    "sg:city":"Teaneck",
    "sg:classifiers":[
        {
            "category":"Professional",
            "type":"Services"
        }
    ],
    "sg:phone":"+1 201 836 6451",
    "sg:postcode":"07666",
    "sg:province":"NJ",
    "sg:tags":[
        "establishment"
    ],
    "wof:name":"Organizer Systems Inc",
    "wof:placetype":"venue"
},
  "geometry": {"coordinates":[-74.01961799999999,40.902526],"type":"Point"}
}