{
  "type": "Feature",
  "properties": {
    "addr:full":"2001 Bellmore St Oakhurst NJ 07755",
    "addr:housenumber":"2001",
    "addr:postcode":"07755",
    "addr:street":"Bellmore St",
    "iso:country":"US",
    "sg:address":"2001 Bellmore St",
    "sg:city":"Oakhurst",
    "sg:classifiers":[
        {
            "category":"Restaurant",
            "type":"Food & Drink"
        }
    ],
    "sg:phone":"+1 732 531 4478",
    "sg:postcode":"07755",
    "sg:province":"NJ",
    "sg:tags":[
        "pizza"
    ],
    "wof:name":"Oakhurst Pizza & Restaurant",
    "wof:placetype":"venue"
},
  "geometry": {"coordinates":[-74.040741,40.263754],"type":"Point"}
}