{
  "type": "Feature",
  "properties": {
    "iso:country":"US",
    "sg:address":"55 Curtis Ave",
    "sg:city":"Woodbury",
    "sg:classifiers":[
        {
            "category":"Social Services",
            "type":"Services"
        }
    ],
    "sg:phone":"+1 856 537 7919",
    "sg:postcode":"08096",
    "sg:province":"NJ",
    "wof:name":"Avenues Of Independent Living Inc",
    "wof:placetype":"venue"
},
  "geometry": {"coordinates":[-75.15184499999999,39.836478],"type":"Point"}
}