{
  "type": "Feature",
  "properties": {
    "addr:full":"2480 Pennington Rd Pennington NJ 08534",
    "addr:housenumber":"2480",
    "addr:postcode":"08534",
    "addr:street":"Pennington Rd",
    "iso:country":"US",
    "sg:address":"2480 Pennington Rd",
    "sg:city":"Pennington",
    "sg:classifiers":[
        {
            "category":"Health Services",
            "subcategory":"Doctor",
            "type":"Services"
        }
    ],
    "sg:phone":"+1 609 737 7544",
    "sg:postcode":"08534",
    "sg:province":"NJ",
    "sg:tags":[
        "physician",
        "surgeon",
        "medical"
    ],
    "wof:name":"John A Harman MD",
    "wof:placetype":"venue"
},
  "geometry": {"coordinates":[-74.784132,40.301865],"type":"Point"}
}