{
  "type": "Feature",
  "properties": {
    "addr:full":"1197 Springfield Ave Irvington NJ 07111",
    "addr:housenumber":"1197",
    "addr:postcode":"07111",
    "addr:street":"Springfield Ave",
    "iso:country":"US",
    "sg:address":"1197 Springfield Ave",
    "sg:city":"Irvington",
    "sg:classifiers":[
        {
            "category":"Food & Beverages",
            "subcategory":"Groceries & Convenience Stores",
            "type":"Retail Goods"
        }
    ],
    "sg:phone":"+1 973 416 3400",
    "sg:postcode":"07111",
    "sg:province":"NJ",
    "sg:tags":[
        "grocer"
    ],
    "wof:name":"Betty & Betty African",
    "wof:placetype":"venue"
},
  "geometry": {"coordinates":[-74.23852599999999,40.724985],"type":"Point"}
}