{
  "type": "Feature",
  "properties": {
    "addr:full":"26 Bridge St Bergenfield NJ 07621",
    "addr:housenumber":"26",
    "addr:postcode":"07621",
    "addr:street":"Bridge St",
    "iso:country":"US",
    "sg:address":"26 Bridge St",
    "sg:city":"Bergenfield",
    "sg:classifiers":[
        {
            "category":"Building & Trades",
            "subcategory":"Construction",
            "type":"Services"
        }
    ],
    "sg:phone":"+1 201 384 3769",
    "sg:postcode":"07621",
    "sg:province":"NJ",
    "sg:tags":[
        "house",
        "remodeling",
        "general"
    ],
    "wof:name":"Varko Home Improvement Inc",
    "wof:placetype":"venue"
},
  "geometry": {"coordinates":[-74.00066099999999,40.922006],"type":"Point"}
}