{
  "type": "Feature",
  "properties": {
    "addr:full":"125 Washington Valley Rd Warren NJ 07059",
    "addr:housenumber":"125",
    "addr:postcode":"07059",
    "addr:street":"Washington Valley Rd",
    "iso:country":"US",
    "sg:address":"125 Washington Valley Rd",
    "sg:city":"Warren",
    "sg:classifiers":[
        {
            "category":"Shopping",
            "subcategory":"Jewelry",
            "type":"Retail Goods"
        }
    ],
    "sg:phone":"+1   ",
    "sg:postcode":"07059",
    "sg:province":"NJ",
    "sg:tags":[
        "repair",
        "for"
    ],
    "wof:name":"Bonded Jewelers",
    "wof:placetype":"venue"
},
  "geometry": {"coordinates":[-74.50817499999999,40.607297],"type":"Point"}
}