{
  "type": "Feature",
  "properties": {
    "iso:country":"US",
    "sg:address":"40 Mayne Ave",
    "sg:city":"Stanhope",
    "sg:classifiers":[
        {
            "category":"Freight",
            "type":"Transportation"
        }
    ],
    "sg:phone":"+1 973 347 2070",
    "sg:postcode":"07874",
    "sg:province":"NJ",
    "sg:tags":[
        "trucking"
    ],
    "wof:name":"Sadowski Trucking Service",
    "wof:placetype":"venue"
},
  "geometry": {"coordinates":[-74.720299,40.923344],"type":"Point"}
}