{
  "type": "Feature",
  "properties": {
    "addr:full":"29 Brier Ct New Providence NJ 07974",
    "addr:housenumber":"29",
    "addr:postcode":"07974",
    "addr:street":"Brier Ct",
    "iso:country":"US",
    "sg:address":"29 Brier Ct",
    "sg:city":"New Providence",
    "sg:classifiers":[
        {
            "category":"Professional",
            "subcategory":"Management & Consulting",
            "type":"Services"
        }
    ],
    "sg:phone":"+1   ",
    "sg:postcode":"07974",
    "sg:province":"NJ",
    "sg:tags":[
        "business"
    ],
    "wof:name":"Mdc Consulting Inc",
    "wof:placetype":"venue"
},
  "geometry": {"coordinates":[-74.414616,40.688133],"type":"Point"}
}