{
  "type": "Feature",
  "properties": {
    "addr:full":"76 Cobb St Rockaway NJ 07866",
    "addr:housenumber":"76",
    "addr:postcode":"07866",
    "addr:street":"Cobb St",
    "iso:country":"US",
    "sg:address":"76 Cobb St",
    "sg:city":"Rockaway",
    "sg:classifiers":[
        {
            "category":"Retail",
            "subcategory":"Auto Repair",
            "type":"Services"
        }
    ],
    "sg:phone":"+1   ",
    "sg:postcode":"07866",
    "sg:province":"NJ",
    "sg:tags":[
        "automotive"
    ],
    "wof:name":"Artic Wters Whl Auto Trck Radi",
    "wof:placetype":"venue"
},
  "geometry": {"coordinates":[-74.504696,40.904639],"type":"Point"}
}