{
  "type": "Feature",
  "properties": {
    "addr:full":"187 Washington Ave Fort Lee NJ 07024",
    "addr:housenumber":"187",
    "addr:postcode":"07024",
    "addr:street":"Washington Ave",
    "iso:country":"US",
    "sg:address":"187 Washington Ave",
    "sg:city":"Fort Lee",
    "sg:classifiers":[
        {
            "category":"Retail",
            "subcategory":"Repair Shop",
            "type":"Services"
        }
    ],
    "sg:phone":"+1 201 676 2618",
    "sg:postcode":"07024",
    "sg:province":"NJ",
    "sg:tags":[
        "hardware",
        "lock",
        "store",
        "locksmith"
    ],
    "wof:name":"Pete's Lock & Key Service",
    "wof:placetype":"venue"
},
  "geometry": {"coordinates":[-73.961213,40.863917],"type":"Point"}
}