{
  "type": "Feature",
  "properties": {
    "iso:country":"US",
    "sg:address":"49 Nathaniel Pl",
    "sg:city":"Englewood",
    "sg:classifiers":[
        {
            "category":"Shopping",
            "subcategory":"Music",
            "type":"Retail Goods"
        }
    ],
    "sg:phone":"+1   ",
    "sg:postcode":"07631",
    "sg:province":"NJ",
    "sg:tags":[
        "product",
        "video",
        "sm",
        "blank",
        "prerecorded",
        "tape",
        "audio"
    ],
    "wof:name":"Sam Goody 4697",
    "wof:placetype":"venue"
},
  "geometry": {"coordinates":[-73.976102,40.895047],"type":"Point"}
}