{
  "type": "Feature",
  "properties": {
    "addr:full":"120 Banker Rd Hewitt NJ 07421",
    "addr:housenumber":"120",
    "addr:postcode":"07421",
    "addr:street":"Banker Rd",
    "iso:country":"US",
    "sg:address":"120 Banker Rd",
    "sg:city":"Hewitt",
    "sg:classifiers":[
        {
            "category":"Wholesale",
            "subcategory":"Office Equipment",
            "type":"Manufacturing & Wholesale Goods"
        }
    ],
    "sg:phone":"+1 973 853 2087",
    "sg:postcode":"07421",
    "sg:province":"NJ",
    "wof:name":"Joy Products",
    "wof:placetype":"venue"
},
  "geometry": {"coordinates":[-74.397443,41.173898],"type":"Point"}
}