{
  "type": "Feature",
  "properties": {
    "addr:full":"696 Behl Rd Franklinville NJ 08322",
    "addr:housenumber":"696",
    "addr:postcode":"08322",
    "addr:street":"Behl Rd",
    "iso:country":"US",
    "sg:address":"696 Behl Rd",
    "sg:city":"Franklinville",
    "sg:classifiers":[
        {
            "category":"Building & Trades",
            "subcategory":"Construction",
            "type":"Services"
        }
    ],
    "sg:phone":"+1 856 728 4521",
    "sg:postcode":"08322",
    "sg:province":"NJ",
    "sg:tags":[
        "house"
    ],
    "wof:name":"Dorsey Rp Home Improvement",
    "wof:placetype":"venue"
},
  "geometry": {"coordinates":[-75.03385400000001,39.656594],"type":"Point"}
}