{
  "type": "Feature",
  "properties": {
    "iso:country":"US",
    "sg:address":"273 Murray Hill Ter",
    "sg:city":"Bergenfield",
    "sg:classifiers":[
        {
            "category":"Education",
            "subcategory":"School",
            "type":"Public Place"
        }
    ],
    "sg:phone":"+1 201 385 8582",
    "sg:postcode":"07621",
    "sg:province":"NJ",
    "sg:tags":[
        "high",
        "middle",
        "elementary"
    ],
    "wof:name":"Bergenfield School District",
    "wof:placetype":"venue"
},
  "geometry": {"coordinates":[-73.99409199999999,40.915245],"type":"Point"}
}