{
  "type": "Feature",
  "properties": {
    "addr:full":"14 Romaine Pl Newark NJ 07104",
    "addr:housenumber":"14",
    "addr:postcode":"07104",
    "addr:street":"Romaine Pl",
    "iso:country":"US",
    "sg:address":"14 Romaine Pl",
    "sg:city":"Newark",
    "sg:classifiers":[
        {
            "category":"Organizations",
            "subcategory":"Religious Organization",
            "type":"Services"
        }
    ],
    "sg:phone":"+1 973 485 8496",
    "sg:postcode":"07104",
    "sg:province":"NJ",
    "sg:tags":[
        "clergy"
    ],
    "wof:name":"Henry Marshall",
    "wof:placetype":"venue"
},
  "geometry": {"coordinates":[-74.161801,40.770308],"type":"Point"}
}