{
  "type": "Feature",
  "properties": {
    "addr:full":"831 S New Rd Pleasantville NJ 08232",
    "addr:housenumber":"831",
    "addr:postcode":"08232",
    "addr:street":"S New Rd",
    "iso:country":"US",
    "sg:address":"831 S New Rd",
    "sg:city":"Pleasantville",
    "sg:classifiers":[
        {
            "category":"Personal",
            "subcategory":"Barber",
            "type":"Services"
        }
    ],
    "sg:phone":"+1 609 646 3733",
    "sg:postcode":"08232",
    "sg:province":"NJ",
    "sg:tags":[
        "shop"
    ],
    "wof:name":"Legends Barber Shop",
    "wof:placetype":"venue"
},
  "geometry": {"coordinates":[-74.536869,39.387577],"type":"Point"}
}