{
  "type": "Feature",
  "properties": {
    "addr:full":"8 Lowell Dr Wayne NJ 07470",
    "addr:housenumber":"8",
    "addr:postcode":"07470",
    "addr:street":"Lowell Dr",
    "iso:country":"US",
    "sg:address":"8 Lowell Dr",
    "sg:city":"Wayne",
    "sg:classifiers":[
        {
            "category":"Real Estate",
            "subcategory":"Real Estate Agent",
            "type":"Services"
        }
    ],
    "sg:phone":"+1 856 810 7655",
    "sg:postcode":"07470",
    "sg:province":"NJ",
    "wof:name":"Weichert Realtors",
    "wof:placetype":"venue"
},
  "geometry": {"coordinates":[-74.235423,40.974919],"type":"Point"}
}