{
  "type": "Feature",
  "properties": {
    "addr:full":"1409 New York Ave Union City NJ 07087",
    "addr:housenumber":"1409",
    "addr:postcode":"07087",
    "addr:street":"New York Ave",
    "iso:country":"US",
    "sg:address":"1409 New York Ave",
    "sg:city":"Union City",
    "sg:classifiers":[
        {
            "category":"Freight",
            "type":"Transportation"
        }
    ],
    "sg:phone":"+1 201 617 5730",
    "sg:postcode":"07087",
    "sg:province":"NJ",
    "sg:tags":[
        "operator",
        "local",
        "trucking"
    ],
    "wof:name":"Lga Trucking Inc",
    "wof:placetype":"venue"
},
  "geometry": {"coordinates":[-74.035123,40.761111],"type":"Point"}
}