{
  "type": "Feature",
  "properties": {
    "addr:full":"381 E 22nd St Paterson NJ 07514",
    "addr:housenumber":"381",
    "addr:postcode":"07514",
    "addr:street":"E 22Nd St",
    "iso:country":"US",
    "sg:address":"381 E 22nd St",
    "sg:city":"Paterson",
    "sg:classifiers":[
        {
            "category":"Manufacturing",
            "subcategory":"Tools & Machinery",
            "type":"Manufacturing & Wholesale Goods"
        }
    ],
    "sg:phone":"+1 973 977 2345",
    "sg:postcode":"07514",
    "sg:province":"NJ",
    "sg:tags":[
        "woodworking",
        "mfg"
    ],
    "wof:name":"Prinz Woodworking Inc",
    "wof:placetype":"venue"
},
  "geometry": {"coordinates":[-74.14983700000001,40.927942],"type":"Point"}
}