{
  "type": "Feature",
  "properties": {
    "addr:full":"271 W End Ave Long Branch NJ 07740",
    "addr:housenumber":"271",
    "addr:postcode":"07740",
    "addr:street":"W End Ave",
    "iso:country":"US",
    "sg:address":"271 W End Ave",
    "sg:city":"Long Branch",
    "sg:classifiers":[
        {
            "category":"Building & Trades",
            "subcategory":"Construction",
            "type":"Services"
        }
    ],
    "sg:phone":"+1 732 870 9285",
    "sg:postcode":"07740",
    "sg:province":"NJ",
    "sg:tags":[
        "house"
    ],
    "wof:name":"Fredy Construction Co Inc",
    "wof:placetype":"venue"
},
  "geometry": {"coordinates":[-73.99123400000001,40.28656],"type":"Point"}
}