{
  "type": "Feature",
  "properties": {
    "iso:country":"US",
    "sg:address":"0 Hopper Ave",
    "sg:city":"Fair Lawn",
    "sg:classifiers":[
        {
            "category":"Education",
            "subcategory":"School",
            "type":"Public Place"
        }
    ],
    "sg:phone":"+1   ",
    "sg:postcode":"07410",
    "sg:province":"NJ",
    "wof:name":"John A Forrest Elementary",
    "wof:placetype":"venue"
},
  "geometry": {"coordinates":[-74.127583,40.935187],"type":"Point"}
}