{
  "type": "Feature",
  "properties": {
    "iso:country":"US",
    "sg:address":"42 Molter Ave",
    "sg:city":"Bayonne",
    "sg:classifiers":[
        {
            "category":"Professional",
            "type":"Services"
        }
    ],
    "sg:phone":"+1 201 339 1975",
    "sg:postcode":"07081",
    "sg:province":"NJ",
    "sg:tags":[
        "establishment"
    ],
    "wof:name":"Mid Atlantic Restoration",
    "wof:placetype":"venue"
},
  "geometry": {"coordinates":[-74.31959999999999,40.714749],"type":"Point"}
}