{
  "type": "Feature",
  "properties": {
    "addr:full":"370 State Rte 33 Mercerville NJ 08619",
    "addr:housenumber":"370",
    "addr:postcode":"08619",
    "addr:street":"State Rte 33",
    "iso:country":"US",
    "sg:address":"370 State Rte 33",
    "sg:city":"Mercerville",
    "sg:classifiers":[
        {
            "category":"Building & Trades",
            "subcategory":"Construction",
            "type":"Services"
        }
    ],
    "sg:phone":"+1 609 890 1001",
    "sg:postcode":"08619",
    "sg:province":"NJ",
    "sg:tags":[
        "company"
    ],
    "wof:name":"Princeton Arms Construction",
    "wof:placetype":"venue"
},
  "geometry": {"coordinates":[-74.686627,40.233445],"type":"Point"}
}