{
  "type": "Feature",
  "properties": {
    "iso:country":"US",
    "sg:address":"35 Mount Pleasant Rd",
    "sg:city":"Columbia",
    "sg:classifiers":[
        {
            "category":"Personal",
            "subcategory":"Beauty Salon",
            "type":"Services"
        }
    ],
    "sg:phone":"+1   ",
    "sg:postcode":"07832",
    "sg:province":"NJ",
    "sg:tags":[
        "shop"
    ],
    "wof:name":"Hair Club The",
    "wof:placetype":"venue"
},
  "geometry": {"coordinates":[-75.06364000000001,40.954087],"type":"Point"}
}