{
  "type": "Feature",
  "properties": {
    "addr:full":"70 Racquet Rd Belmar NJ 07719",
    "addr:housenumber":"70",
    "addr:postcode":"07719",
    "addr:street":"Racquet Rd",
    "iso:country":"US",
    "sg:address":"70 Racquet Rd",
    "sg:city":"Belmar",
    "sg:classifiers":[
        {
            "category":"Professional",
            "subcategory":"Business Services",
            "type":"Services"
        }
    ],
    "sg:phone":"+1   ",
    "sg:postcode":"07719",
    "sg:province":"NJ",
    "wof:name":"Small Wonders Interior",
    "wof:placetype":"venue"
},
  "geometry": {"coordinates":[-74.08002999999999,40.168552],"type":"Point"}
}