{
  "type": "Feature",
  "properties": {
    "addr:full":"424 US Hwy 46 Rockaway NJ 07866",
    "addr:housenumber":"424",
    "addr:postcode":"07866",
    "addr:street":"Us Hwy 46",
    "iso:country":"US",
    "sg:address":"424 US Hwy 46",
    "sg:city":"Rockaway",
    "sg:classifiers":[
        {
            "category":"Recreation",
            "type":"Entertainment"
        }
    ],
    "sg:phone":"+1 973 586 1124",
    "sg:postcode":"07866",
    "sg:province":"NJ",
    "sg:tags":[
        "instruction",
        "swimming"
    ],
    "wof:name":"Kim Swim Pool Academy",
    "wof:placetype":"venue"
},
  "geometry": {"coordinates":[-74.529113,40.886762],"type":"Point"}
}