{
  "type": "Feature",
  "properties": {
    "iso:country":"US",
    "sg:address":"340 Field Pl",
    "sg:city":"Hillside",
    "sg:classifiers":[
        {
            "category":"Home & Garden",
            "subcategory":"Building Materials",
            "type":"Retail Goods"
        }
    ],
    "sg:phone":"+1   ",
    "sg:postcode":"07205",
    "sg:province":"NJ",
    "sg:tags":[
        "paint"
    ],
    "wof:name":"Newark Paint & Wallpaper Co",
    "wof:placetype":"venue"
},
  "geometry": {"coordinates":[-74.22524799999999,40.707645],"type":"Point"}
}