{
  "type": "Feature",
  "properties": {
    "addr:full":"298 Paterson Ave West Paterson NJ 07424",
    "addr:housenumber":"298",
    "addr:postcode":"07424",
    "addr:street":"Paterson Ave West",
    "iso:country":"US",
    "sg:address":"298 Paterson Ave",
    "sg:city":"West Paterson",
    "sg:classifiers":[
        {
            "category":"Building & Trades",
            "subcategory":"Electrical",
            "type":"Services"
        }
    ],
    "sg:phone":"+1 973 684 0815",
    "sg:postcode":"07424",
    "sg:province":"NJ",
    "sg:tags":[
        "electric",
        "contractor"
    ],
    "wof:name":"Force Electric",
    "wof:placetype":"venue"
},
  "geometry": {"coordinates":[-74.219683,40.888763],"type":"Point"}
}