{
  "type": "Feature",
  "properties": {
    "addr:full":"51 Brunswick Woods Dr East Brunswick NJ 08816",
    "addr:housenumber":"51",
    "addr:postcode":"08816",
    "addr:street":"Brunswick Woods Dr",
    "iso:country":"US",
    "sg:address":"51 Brunswick Woods Dr",
    "sg:city":"East Brunswick",
    "sg:classifiers":[
        {
            "category":"Health Services",
            "subcategory":"Health Practitioner",
            "type":"Services"
        }
    ],
    "sg:phone":"+1 732 432 7600",
    "sg:postcode":"08816",
    "sg:province":"NJ",
    "sg:tags":[
        "acupuncture"
    ],
    "wof:name":"Brunswick Acupressure",
    "wof:placetype":"venue"
},
  "geometry": {"coordinates":[-74.39196099999999,40.421719],"type":"Point"}
}