{
  "type": "Feature",
  "properties": {
    "addr:full":"192 Brahma Ave Bridgewater NJ 08807",
    "addr:housenumber":"192",
    "addr:postcode":"08807",
    "addr:street":"Brahma Ave",
    "iso:country":"US",
    "sg:address":"192 Brahma Ave",
    "sg:city":"Bridgewater",
    "sg:classifiers":[
        {
            "category":"Building & Trades",
            "subcategory":"Construction",
            "type":"Services"
        }
    ],
    "sg:phone":"+1 908 707 1334",
    "sg:postcode":"08807",
    "sg:province":"NJ",
    "sg:tags":[
        "highway",
        "maintenance",
        "operates"
    ],
    "wof:name":"KSG Maintenance Svc",
    "wof:placetype":"venue"
},
  "geometry": {"coordinates":[-74.661303,40.564919],"type":"Point"}
}