{
  "type": "Feature",
  "properties": {
    "iso:country":"US",
    "sg:address":"235 Bloomfield Ave",
    "sg:city":"Bloomfield",
    "sg:classifiers":[
        {
            "category":"Shopping",
            "subcategory":"Crafts & Fabrics",
            "type":"Retail Goods"
        }
    ],
    "sg:phone":"+1   ",
    "sg:postcode":"07003",
    "sg:province":"NJ",
    "wof:name":"Sevens Fabrics",
    "wof:placetype":"venue"
},
  "geometry": {"coordinates":[-74.191805,40.782832],"type":"Point"}
}