{
  "type": "Feature",
  "properties": {
    "addr:full":"900 Easton Ave Somerset NJ 08873",
    "addr:housenumber":"900",
    "addr:postcode":"08873",
    "addr:street":"Easton Ave",
    "iso:country":"US",
    "sg:address":"900 Easton Ave",
    "sg:city":"Somerset",
    "sg:classifiers":[
        {
            "category":"Professional",
            "subcategory":"Business Services",
            "type":"Services"
        }
    ],
    "sg:phone":"+1   ",
    "sg:postcode":"08873",
    "sg:province":"NJ",
    "wof:name":"Yoo Enterprises",
    "wof:placetype":"venue"
},
  "geometry": {"coordinates":[-74.48383,40.511444],"type":"Point"}
}