{
  "type": "Feature",
  "properties": {
    "addr:full":"753 State Rte 35 Middletown NJ 07748",
    "addr:housenumber":"753",
    "addr:postcode":"07748",
    "addr:street":"State Rte 35",
    "iso:country":"US",
    "sg:address":"753 State Rte 35",
    "sg:city":"Middletown",
    "sg:classifiers":[
        {
            "category":"Shopping",
            "subcategory":"Optical Goods",
            "type":"Retail Goods"
        }
    ],
    "sg:phone":"+1   ",
    "sg:postcode":"07748",
    "sg:province":"NJ",
    "wof:name":"Normies Specs Inc",
    "wof:placetype":"venue"
},
  "geometry": {"coordinates":[-74.097143,40.388265],"type":"Point"}
}