{
  "type": "Feature",
  "properties": {
    "iso:country":"US",
    "sg:address":"635 State Rte 72",
    "sg:city":"Manahawkin",
    "sg:classifiers":[
        {
            "category":"Restaurant",
            "type":"Food & Drink"
        }
    ],
    "sg:phone":"+1 609 978 6565",
    "sg:postcode":"08050",
    "sg:province":"NJ",
    "sg:tags":[
        "bar"
    ],
    "sg:website":"www.fabians.com",
    "wof:name":"Fabian's Bar & Restaurant",
    "wof:placetype":"venue"
},
  "geometry": {"coordinates":[-74.238618,39.68051],"type":"Point"}
}