{
  "type": "Feature",
  "properties": {
    "iso:country":"US",
    "sg:address":"1038 State Rte 88",
    "sg:city":"Pt Pleasant Bch",
    "sg:classifiers":[
        {
            "category":"Real Estate",
            "subcategory":"Real Estate Services",
            "type":"Services"
        }
    ],
    "sg:phone":"+1 732 714 7377",
    "sg:postcode":"08742",
    "sg:province":"NJ",
    "sg:tags":[
        "company",
        "title"
    ],
    "wof:name":"Argent Title & Abstract LLC",
    "wof:placetype":"venue"
},
  "geometry": {"coordinates":[-74.06360599999999,40.084084],"type":"Point"}
}