{
  "type": "Feature",
  "properties": {
    "iso:country":"US",
    "sg:address":"4939 Stelton Rd",
    "sg:city":"South Plainfield",
    "sg:classifiers":[
        {
            "category":"Personal",
            "subcategory":"Beauty Salon",
            "type":"Services"
        }
    ],
    "sg:phone":"+1 908 222 1888",
    "sg:postcode":"07080",
    "sg:province":"NJ",
    "sg:tags":[
        "manicuring"
    ],
    "wof:name":"Exotic Nails",
    "wof:placetype":"venue"
},
  "geometry": {"coordinates":[-74.42941500000001,40.548463],"type":"Point"}
}