{
  "type": "Feature",
  "properties": {
    "addr:full":"22 School St Asbury NJ 08802",
    "addr:housenumber":"22",
    "addr:postcode":"08802",
    "addr:street":"School St",
    "iso:country":"US",
    "sg:address":"22 School St",
    "sg:city":"Asbury",
    "sg:classifiers":[
        {
            "category":"Professional",
            "type":"Services"
        }
    ],
    "sg:phone":"+1   ",
    "sg:postcode":"08802",
    "sg:province":"NJ",
    "wof:name":"Joanne Casale",
    "wof:placetype":"venue"
},
  "geometry": {"coordinates":[-75.013159,40.696493],"type":"Point"}
}