{
  "type": "Feature",
  "properties": {
    "addr:full":"211 E Main St Bound Brook NJ 08805",
    "addr:housenumber":"211",
    "addr:postcode":"08805",
    "addr:street":"E Main St",
    "iso:country":"US",
    "sg:address":"211 E Main St",
    "sg:city":"Bound Brook",
    "sg:classifiers":[
        {
            "category":"Restaurant",
            "type":"Food & Drink"
        }
    ],
    "sg:phone":"+1   ",
    "sg:postcode":"08805",
    "sg:province":"NJ",
    "sg:tags":[
        "eating"
    ],
    "wof:name":"Mamseom Tiacica",
    "wof:placetype":"venue"
},
  "geometry": {"coordinates":[-74.53094299999999,40.561661],"type":"Point"}
}