{
  "type": "Feature",
  "properties": {
    "iso:country":"US",
    "sg:address":"240 Kinderkamack Rd",
    "sg:city":"Oradell",
    "sg:classifiers":[
        {
            "category":"Professional",
            "subcategory":"Computer Services",
            "type":"Services"
        },
        {
            "category":"Shopping",
            "subcategory":"Computers & Home Electronics",
            "type":"Retail Goods"
        }
    ],
    "sg:phone":"+1 201 637 5906",
    "sg:postcode":"07649",
    "sg:province":"NJ",
    "sg:tags":[
        "develops",
        "consulting",
        "software"
    ],
    "sg:website":"www.vtgi.com",
    "wof:name":"Vision Technology Group Inc",
    "wof:placetype":"venue"
},
  "geometry": {"coordinates":[-74.03166400000001,40.948087],"type":"Point"}
}