{
  "type": "Feature",
  "properties": {
    "iso:country":"US",
    "sg:address":"25 N Farview Ave",
    "sg:city":"Paramus",
    "sg:classifiers":[
        {
            "category":"Health Services",
            "subcategory":"Chiropractor",
            "type":"Services"
        }
    ],
    "sg:phone":"+1   ",
    "sg:postcode":"07652",
    "sg:province":"NJ",
    "wof:name":"Sion Daftari DC",
    "wof:placetype":"venue"
},
  "geometry": {"coordinates":[-74.06775399999999,40.922008],"type":"Point"}
}