{
  "type": "Feature",
  "properties": {
    "iso:country":"US",
    "sg:address":"900 US Hwy 1",
    "sg:city":"Avenel",
    "sg:classifiers":[
        {
            "category":"Local Transit",
            "type":"Transportation"
        }
    ],
    "sg:phone":"+1 732 634 7373",
    "sg:postcode":"07001",
    "sg:province":"NJ",
    "sg:tags":[
        "bus",
        "line"
    ],
    "wof:name":"Howard Bus Co",
    "wof:placetype":"venue"
},
  "geometry": {"coordinates":[-74.283883,40.581194],"type":"Point"}
}