{
  "type": "Feature",
  "properties": {
    "addr:full":"248 Hendrickson Dr Princeton Junction NJ 08550",
    "addr:housenumber":"248",
    "addr:postcode":"08550",
    "addr:street":"Hendrickson Dr",
    "iso:country":"US",
    "sg:address":"248 Hendrickson Dr",
    "sg:city":"Princeton Junction",
    "sg:classifiers":[
        {
            "category":"Health Services",
            "subcategory":"Doctor",
            "type":"Services"
        }
    ],
    "sg:phone":"+1 609 799 1447",
    "sg:postcode":"08550",
    "sg:province":"NJ",
    "sg:tags":[
        "dentist"
    ],
    "wof:name":"John A Dipolvere DDS PA",
    "wof:placetype":"venue"
},
  "geometry": {"coordinates":[-74.614537,40.306774],"type":"Point"}
}