{
  "type": "Feature",
  "properties": {
    "iso:country":"US",
    "sg:address":"6 Sunflower Ln",
    "sg:city":"Trenton",
    "sg:classifiers":[
        {
            "category":"Communications",
            "subcategory":"Film & Video Production",
            "type":"Services"
        }
    ],
    "sg:phone":"+1 609 585 4620",
    "sg:postcode":"08620",
    "sg:province":"NJ",
    "sg:tags":[
        "motion",
        "picture"
    ],
    "wof:name":"Videos Forever",
    "wof:placetype":"venue"
},
  "geometry": {"coordinates":[-74.65858,40.165385],"type":"Point"}
}