{
  "type": "Feature",
  "properties": {
    "iso:country":"US",
    "sg:address":"1825 State Rte 35",
    "sg:city":"Wall Township",
    "sg:classifiers":[
        {
            "category":"Retail",
            "subcategory":"Laundry & Dry Cleaning",
            "type":"Services"
        }
    ],
    "sg:phone":"+1 732 280 1110",
    "sg:postcode":"07719",
    "sg:province":"NJ",
    "sg:tags":[
        "cleaners"
    ],
    "wof:name":"Clean-Rite Dry Cleaning",
    "wof:placetype":"venue"
},
  "geometry": {"coordinates":[-74.048816,40.166366],"type":"Point"}
}