{
  "type": "Feature",
  "properties": {
    "addr:full":"8606 5th Ave North Bergen NJ 07047",
    "addr:housenumber":"8606",
    "addr:postcode":"07047",
    "addr:street":"5Th Ave",
    "iso:country":"US",
    "sg:address":"8606 5th Ave",
    "sg:city":"North Bergen",
    "sg:classifiers":[
        {
            "category":"Building & Trades",
            "subcategory":"Construction",
            "type":"Services"
        }
    ],
    "sg:phone":"+1 201 869 1929",
    "sg:postcode":"07047",
    "sg:province":"NJ",
    "sg:tags":[
        "hanging",
        "contractor"
    ],
    "wof:name":"Hl Painting Company",
    "wof:placetype":"venue"
},
  "geometry": {"coordinates":[-74.007546,40.807436],"type":"Point"}
}