{
  "type": "Feature",
  "properties": {
    "iso:country":"US",
    "sg:address":"100 Jersey Ave",
    "sg:city":"New Brunswick",
    "sg:classifiers":[
        {
            "category":"Professional",
            "subcategory":"Research",
            "type":"Services"
        }
    ],
    "sg:phone":"+1 732 247 0022",
    "sg:postcode":"08901",
    "sg:province":"NJ",
    "sg:tags":[
        "development",
        "electronic"
    ],
    "wof:name":"T-Mac Inc",
    "wof:placetype":"venue"
},
  "geometry": {"coordinates":[-74.459807,40.486477],"type":"Point"}
}