{
  "type": "Feature",
  "properties": {
    "iso:country":"US",
    "sg:address":"663 15th Ave",
    "sg:city":"Irvington",
    "sg:classifiers":[
        {
            "category":"Building & Trades",
            "subcategory":"Construction",
            "type":"Services"
        }
    ],
    "sg:phone":"+1 973 371 8353",
    "sg:postcode":"07111",
    "sg:province":"NJ",
    "sg:tags":[
        "contractor"
    ],
    "wof:name":"L R W Waterproofing Company",
    "wof:placetype":"venue"
},
  "geometry": {"coordinates":[-74.211113,40.739429],"type":"Point"}
}