{
  "type": "Feature",
  "properties": {
    "addr:full":"47 Billingsley Dr Livingston NJ 07039",
    "addr:housenumber":"47",
    "addr:postcode":"07039",
    "addr:street":"Billingsley Dr",
    "iso:country":"US",
    "sg:address":"47 Billingsley Dr",
    "sg:city":"Livingston",
    "sg:classifiers":[
        {
            "category":"Manufacturing",
            "subcategory":"Tools & Machinery",
            "type":"Manufacturing & Wholesale Goods"
        }
    ],
    "sg:phone":"+1 973 992 5331",
    "sg:postcode":"07039",
    "sg:province":"NJ",
    "sg:tags":[
        "equipment",
        "peripheral",
        "computer",
        "mfg"
    ],
    "wof:name":"Avemark Tech Market Inc",
    "wof:placetype":"venue"
},
  "geometry": {"coordinates":[-74.311609,40.77599],"type":"Point"}
}