{
  "type": "Feature",
  "properties": {
    "iso:country":"US",
    "sg:address":"17 Vine St",
    "sg:city":"Hillside",
    "sg:classifiers":[
        {
            "category":"Building & Trades",
            "subcategory":"Plumbing",
            "type":"Services"
        }
    ],
    "sg:phone":"+1 908 436 0740",
    "sg:postcode":"07205",
    "sg:province":"NJ",
    "sg:tags":[
        "plumbing",
        "contractor"
    ],
    "wof:name":"A M Portela Plumbing & Htg",
    "wof:placetype":"venue"
},
  "geometry": {"coordinates":[-74.22395400000001,40.694642],"type":"Point"}
}