{
  "type": "Feature",
  "properties": {
    "addr:full":"400 N 9th St Haledon NJ 07508",
    "addr:housenumber":"400",
    "addr:postcode":"07508",
    "addr:street":"N 9Th St",
    "iso:country":"US",
    "sg:address":"400 N 9th St",
    "sg:city":"Haledon",
    "sg:classifiers":[
        {
            "category":"Building & Trades",
            "subcategory":"Plumbing",
            "type":"Services"
        }
    ],
    "sg:phone":"+1 973 595 1228",
    "sg:postcode":"07508",
    "sg:province":"NJ",
    "sg:tags":[
        "plumbing",
        "contractor"
    ],
    "wof:name":"David Binstock Plumbing & Htg",
    "wof:placetype":"venue"
},
  "geometry": {"coordinates":[-74.16851200000001,40.936529],"type":"Point"}
}