{
  "type": "Feature",
  "properties": {
    "addr:full":"106 Manito Rd Manasquan NJ 08736",
    "addr:housenumber":"106",
    "addr:postcode":"08736",
    "addr:street":"Manito Rd",
    "iso:country":"US",
    "sg:address":"106 Manito Rd",
    "sg:city":"Manasquan",
    "sg:classifiers":[
        {
            "category":"Professional",
            "type":"Services"
        }
    ],
    "sg:phone":"+1   ",
    "sg:postcode":"08736",
    "sg:province":"NJ",
    "wof:name":"Mace Motif",
    "wof:placetype":"venue"
},
  "geometry": {"coordinates":[-74.060402,40.121329],"type":"Point"}
}