{
  "type": "Feature",
  "properties": {
    "iso:country":"US",
    "sg:address":"1350 16th St",
    "sg:city":"Fort Lee",
    "sg:classifiers":[
        {
            "category":"Wholesale",
            "subcategory":"Computers",
            "type":"Manufacturing & Wholesale Goods"
        }
    ],
    "sg:phone":"+1 201 969 0804",
    "sg:postcode":"07024",
    "sg:province":"NJ",
    "sg:tags":[
        "sales"
    ],
    "wof:name":"Netzoa Computer & Consulting",
    "wof:placetype":"venue"
},
  "geometry": {"coordinates":[-73.979201,40.84574],"type":"Point"}
}