{
  "type": "Feature",
  "properties": {
    "iso:country":"US",
    "sg:address":"8 Somerdale Sq",
    "sg:city":"Somerdale",
    "sg:classifiers":[
        {
            "category":"Professional",
            "subcategory":"Management & Consulting",
            "type":"Services"
        },
        {
            "category":"Professional",
            "subcategory":"Advertising",
            "type":"Services"
        }
    ],
    "sg:phone":"+1 856 627 7100",
    "sg:postcode":"08083",
    "sg:province":"NJ",
    "sg:tags":[
        "fax",
        "consultant",
        "program",
        "marketing",
        "advertising-telephone",
        "telemarketing"
    ],
    "wof:name":"Telepoint Communications, Inc",
    "wof:placetype":"venue"
},
  "geometry": {"coordinates":[-75.055868,39.83775],"type":"Point"}
}