{
  "type": "Feature",
  "properties": {
    "iso:country":"US",
    "sg:address":"476 Neptune Ave",
    "sg:city":"Long Branch",
    "sg:classifiers":[
        {
            "category":"Professional",
            "subcategory":"Accounting & Tax Preparation",
            "type":"Services"
        }
    ],
    "sg:phone":"+1 732 222 3366",
    "sg:postcode":"07740",
    "sg:province":"NJ",
    "sg:tags":[
        "accountant"
    ],
    "wof:name":"Vincent Campanile CPA",
    "wof:placetype":"venue"
},
  "geometry": {"coordinates":[-73.978092,40.321545],"type":"Point"}
}