{
  "type": "Feature",
  "properties": {
    "addr:full":"50 Pompton Ave Verona NJ 07044",
    "addr:housenumber":"50",
    "addr:postcode":"07044",
    "addr:street":"Pompton Ave",
    "iso:country":"US",
    "sg:address":"50 Pompton Ave",
    "sg:city":"Verona",
    "sg:classifiers":[
        {
            "category":"Health Services",
            "subcategory":"Doctor",
            "type":"Services"
        }
    ],
    "sg:phone":"+1 973 857 3400",
    "sg:postcode":"07044",
    "sg:province":"NJ",
    "wof:name":"Lipsitch C MD",
    "wof:placetype":"venue"
},
  "geometry": {"coordinates":[-74.228897,40.828899],"type":"Point"}
}