{
  "type": "Feature",
  "properties": {
    "iso:country":"US",
    "sg:address":"946 Gloucester Ave",
    "sg:city":"Brick",
    "sg:classifiers":[
        {
            "category":"Professional",
            "subcategory":"Computer Services",
            "type":"Services"
        }
    ],
    "sg:phone":"+1 732 477 0535",
    "sg:postcode":"08723",
    "sg:province":"NJ",
    "sg:tags":[
        "datum"
    ],
    "wof:name":"Black Sheep PC",
    "wof:placetype":"venue"
},
  "geometry": {"coordinates":[-74.135654,40.051223],"type":"Point"}
}