{
  "type": "Feature",
  "properties": {
    "addr:full":"9 Wrightstown Cookstown Rd Cookstown NJ 08511",
    "addr:housenumber":"9",
    "addr:postcode":"08511",
    "addr:street":"Cookstown Rd",
    "iso:country":"US",
    "sg:address":"9 Wrightstown Cookstown Rd",
    "sg:city":"Cookstown",
    "sg:classifiers":[
        {
            "category":"Personal",
            "subcategory":"Beauty Salon",
            "type":"Services"
        },
        {
            "category":"Personal",
            "subcategory":"Barber",
            "type":"Services"
        }
    ],
    "sg:phone":"+1 609 723 1000",
    "sg:postcode":"08511",
    "sg:province":"NJ",
    "sg:tags":[
        "shop"
    ],
    "wof:name":"Cutting Edge Barber Shops",
    "wof:placetype":"venue"
},
  "geometry": {"coordinates":[-74.57978,40.041706],"type":"Point"}
}