{
  "type": "Feature",
  "properties": {
    "iso:country":"US",
    "sg:address":"928 E Hazelwood Ave",
    "sg:city":"Rahway",
    "sg:classifiers":[
        {
            "category":"Building & Trades",
            "subcategory":"Cleaning & Sanitation",
            "type":"Services"
        }
    ],
    "sg:phone":"+1 732 815 0220",
    "sg:postcode":"07065",
    "sg:province":"NJ",
    "sg:tags":[
        "environmental",
        "c",
        "industrial",
        "provides",
        "full"
    ],
    "wof:name":"Allstate Geo-Tek",
    "wof:placetype":"venue"
},
  "geometry": {"coordinates":[-74.262033,40.599754],"type":"Point"}
}