{
  "type": "Feature",
  "properties": {
    "iso:country":"US",
    "sg:address":"28 Grand Ave",
    "sg:city":"Englewood",
    "sg:classifiers":[
        {
            "category":"Autos & Motor Vehicles",
            "subcategory":"Automobile Sales",
            "type":"Retail Goods"
        },
        {
            "category":"Retail",
            "subcategory":"Auto Repair",
            "type":"Services"
        }
    ],
    "sg:phone":"+1 888 352 1679",
    "sg:postcode":"07631",
    "sg:province":"NJ",
    "sg:tags":[
        "car",
        "used",
        "new"
    ],
    "sg:website":"http://newyork.citysearch.com/profile/external/611253620/englewood_nj/benzel_busch_motor_car_corporation.html?publisher=yellowpages&reference_id=1&placement=ypwebsitemip",
    "wof:name":"Benzel - Busch Motor Car Corporation",
    "wof:placetype":"venue"
},
  "geometry": {"coordinates":[-73.97369399999999,40.891703],"type":"Point"}
}