{
  "type": "Feature",
  "properties": {
    "iso:country":"US",
    "sg:address":"147 Cornell Rd",
    "sg:city":"Pennsville",
    "sg:classifiers":[
        {
            "category":"Restaurant",
            "type":"Food & Drink"
        }
    ],
    "sg:phone":"+1   ",
    "sg:postcode":"08070",
    "sg:province":"NJ",
    "sg:tags":[
        "eating"
    ],
    "wof:name":"Kenny Os Steak & Sub Shop",
    "wof:placetype":"venue"
},
  "geometry": {"coordinates":[-75.53039,39.647931],"type":"Point"}
}