{
  "type": "Feature",
  "properties": {
    "iso:country":"US",
    "sg:address":"412 Mine Rd",
    "sg:city":"Asbury",
    "sg:classifiers":[
        {
            "category":"Recreation",
            "type":"Entertainment"
        }
    ],
    "sg:phone":"+1 908 735 4017",
    "sg:postcode":"08802",
    "sg:province":"NJ",
    "wof:name":"U S Family Martial Arts",
    "wof:placetype":"venue"
},
  "geometry": {"coordinates":[-75.004361,40.670362],"type":"Point"}
}