{
  "type": "Feature",
  "properties": {
    "iso:country":"US",
    "sg:address":"836 Camden Ave",
    "sg:city":"Blackwood",
    "sg:classifiers":[
        {
            "category":"Professional",
            "subcategory":"Business Services",
            "type":"Services"
        }
    ],
    "sg:phone":"+1   ",
    "sg:postcode":"08012",
    "sg:province":"NJ",
    "wof:name":"Mjg Technologies",
    "wof:placetype":"venue"
},
  "geometry": {"coordinates":[-75.06010999999999,39.81403],"type":"Point"}
}