{
  "type": "Feature",
  "properties": {
    "addr:full":"15 Bergenline Ave Westwood NJ 07675",
    "addr:housenumber":"15",
    "addr:postcode":"07675",
    "addr:street":"Bergenline Ave",
    "iso:country":"US",
    "sg:address":"15 Bergenline Ave",
    "sg:city":"Westwood",
    "sg:classifiers":[
        {
            "category":"Retail",
            "subcategory":"Auto Repair",
            "type":"Services"
        }
    ],
    "sg:phone":"+1 201 664 4563",
    "sg:postcode":"07675",
    "sg:province":"NJ",
    "sg:tags":[
        "repairing",
        "automobile"
    ],
    "wof:name":"KMD Tuning",
    "wof:placetype":"venue"
},
  "geometry": {"coordinates":[-74.01582999999999,40.983039],"type":"Point"}
}