{
  "type": "Feature",
  "properties": {
    "iso:country":"US",
    "sg:address":"1029 Main St",
    "sg:city":"Paterson",
    "sg:classifiers":[
        {
            "category":"Health Services",
            "subcategory":"Chiropractor",
            "type":"Services"
        }
    ],
    "sg:phone":"+1 973 523 4555",
    "sg:postcode":"07503",
    "sg:province":"NJ",
    "wof:name":"Kazan Nabil DC",
    "wof:placetype":"venue"
},
  "geometry": {"coordinates":[-74.15770000000001,40.892899],"type":"Point"}
}