{
  "type": "Feature",
  "properties": {
    "addr:full":"252 Co Rd 513 Glen Gardner NJ 08826",
    "addr:housenumber":"252;513",
    "addr:postcode":"08826",
    "addr:street":"Co Rd",
    "iso:country":"US",
    "sg:address":"252 Co Rd 513",
    "sg:city":"Glen Gardner",
    "sg:classifiers":[
        {
            "category":"Wholesale",
            "subcategory":"Electrical",
            "type":"Manufacturing & Wholesale Goods"
        }
    ],
    "sg:phone":"+1 908 638 0300",
    "sg:postcode":"08826",
    "sg:province":"NJ",
    "sg:tags":[
        "semiconductor"
    ],
    "wof:name":"Vishay Siliconix",
    "wof:placetype":"venue"
},
  "geometry": {"coordinates":[-74.886898,40.696081],"type":"Point"}
}