{
  "type": "Feature",
  "properties": {
    "addr:full":"25 Maplewood Ave Edison NJ 08837",
    "addr:housenumber":"25",
    "addr:postcode":"08837",
    "addr:street":"Maplewood Ave",
    "iso:country":"US",
    "sg:address":"25 Maplewood Ave",
    "sg:city":"Edison",
    "sg:classifiers":[
        {
            "category":"Professional",
            "subcategory":"Lawyer & Legal Services",
            "type":"Services"
        }
    ],
    "sg:phone":"+1 732 548 0261",
    "sg:postcode":"08837",
    "sg:province":"NJ",
    "sg:tags":[
        "attorney"
    ],
    "wof:name":"Gregg L Jensen Esq",
    "wof:placetype":"venue"
},
  "geometry": {"coordinates":[-74.34530700000001,40.537455],"type":"Point"}
}