{
  "type": "Feature",
  "properties": {
    "addr:full":"80 Leuning St South Hackensack NJ 07606",
    "addr:housenumber":"80",
    "addr:postcode":"07606",
    "addr:street":"Leuning St",
    "iso:country":"US",
    "sg:address":"80 Leuning St",
    "sg:city":"South Hackensack",
    "sg:classifiers":[
        {
            "category":"Professional",
            "subcategory":"Lawyer & Legal Services",
            "type":"Services"
        }
    ],
    "sg:phone":"+1 212 564 7368",
    "sg:postcode":"07606",
    "sg:province":"NJ",
    "wof:name":"Mercury Foam Corp",
    "wof:placetype":"venue"
},
  "geometry": {"coordinates":[-74.050697,40.872299],"type":"Point"}
}