{
  "type": "Feature",
  "properties": {
    "iso:country":"US",
    "sg:address":"139 Valley Rd",
    "sg:city":"Clifton",
    "sg:classifiers":[
        {
            "category":"Education",
            "subcategory":"Dance Studio",
            "type":"Public Place"
        }
    ],
    "sg:phone":"+1 973 881 1212",
    "sg:postcode":"07013",
    "sg:province":"NJ",
    "sg:tags":[
        "art",
        "performing",
        "instruction",
        "dancing"
    ],
    "wof:name":"Cathy Fierro's School of Dance",
    "wof:placetype":"venue"
},
  "geometry": {"coordinates":[-74.174301,40.893501],"type":"Point"}
}