{
  "type": "Feature",
  "properties": {
    "addr:full":"476 S Burlington Rd Bridgeton NJ 08302",
    "addr:housenumber":"476",
    "addr:postcode":"08302",
    "addr:street":"S Burlington Rd",
    "iso:country":"US",
    "sg:address":"476 S Burlington Rd",
    "sg:city":"Bridgeton",
    "sg:classifiers":[
        {
            "category":"Recreation",
            "type":"Entertainment"
        }
    ],
    "sg:phone":"+1 856 455 1050",
    "sg:postcode":"08302",
    "sg:province":"NJ",
    "wof:name":"Capps Picnic Park",
    "wof:placetype":"venue"
},
  "geometry": {"coordinates":[-75.198324,39.391895],"type":"Point"}
}