{
  "type": "Feature",
  "properties": {
    "addr:full":"423 Calhoun St Trenton NJ 08618",
    "addr:housenumber":"423",
    "addr:postcode":"08618",
    "addr:street":"Calhoun St",
    "iso:country":"US",
    "sg:address":"423 Calhoun St",
    "sg:city":"Trenton",
    "sg:classifiers":[
        {
            "category":"Food & Beverages",
            "subcategory":"Groceries & Convenience Stores",
            "type":"Retail Goods"
        }
    ],
    "sg:phone":"+1 609 392 7059",
    "sg:postcode":"08618",
    "sg:province":"NJ",
    "sg:tags":[
        "grocer"
    ],
    "wof:name":"Reyes Supermarket",
    "wof:placetype":"venue"
},
  "geometry": {"coordinates":[-74.77077800000001,40.22672],"type":"Point"}
}