{
  "type": "Feature",
  "properties": {
    "addr:full":"25 Railroad Pl Hopewell NJ 08525",
    "addr:housenumber":"25",
    "addr:postcode":"08525",
    "addr:street":"Railroad Pl",
    "iso:country":"US",
    "sg:address":"25 Railroad Pl",
    "sg:city":"Hopewell",
    "sg:classifiers":[
        {
            "category":"Professional",
            "subcategory":"Business Services",
            "type":"Services"
        }
    ],
    "sg:phone":"+1 609 466 9620",
    "sg:postcode":"08525",
    "sg:province":"NJ",
    "sg:tags":[
        "interior",
        "consultant",
        "design",
        "decorator"
    ],
    "wof:name":"Browning Sloane Designs",
    "wof:placetype":"venue"
},
  "geometry": {"coordinates":[-74.762658,40.391017],"type":"Point"}
}