{
  "type": "Feature",
  "properties": {
    "addr:full":"212 Carnegie Center, Suite 206 Princeton NJ 08540",
    "addr:housenumber":"212",
    "addr:postcode":"08540",
    "addr:street":"Carnegie Center Suite 206",
    "iso:country":"US",
    "sg:address":"212 Carnegie Center, Suite 206",
    "sg:city":"Princeton",
    "sg:classifiers":[
        {
            "category":"Professional",
            "subcategory":"Computer Services",
            "type":"Services"
        }
    ],
    "sg:phone":"+1 866 925 1441",
    "sg:postcode":"08540",
    "sg:province":"NJ",
    "sg:website":"http://www.mobilytics.net",
    "wof:name":"Mobilytics",
    "wof:placetype":"venue"
},
  "geometry": {"coordinates":[-74.691181,40.328347],"type":"Point"}
}