{
  "type": "Feature",
  "properties": {
    "addr:full":"4 Adelaide Pl Denville NJ 07834",
    "addr:housenumber":"4",
    "addr:postcode":"07834",
    "addr:street":"Adelaide Pl",
    "iso:country":"US",
    "sg:address":"4 Adelaide Pl",
    "sg:city":"Denville",
    "sg:classifiers":[
        {
            "category":"Wholesale",
            "subcategory":"Electrical",
            "type":"Manufacturing & Wholesale Goods"
        }
    ],
    "sg:phone":"+1 973 627 3264",
    "sg:postcode":"07834",
    "sg:province":"NJ",
    "sg:tags":[
        "repair",
        "parts",
        "electronic",
        "equipment"
    ],
    "wof:name":"Field Service Co",
    "wof:placetype":"venue"
},
  "geometry": {"coordinates":[-74.475472,40.881593],"type":"Point"}
}