{
  "type": "Feature",
  "properties": {
    "iso:country":"US",
    "sg:address":"7 Mills St",
    "sg:city":"Morristown",
    "sg:classifiers":[
        {
            "category":"Building & Trades",
            "subcategory":"Cleaning & Sanitation",
            "type":"Services"
        }
    ],
    "sg:phone":"+1 973 366 4009",
    "sg:postcode":"07960",
    "sg:province":"NJ",
    "sg:tags":[
        "maintenance"
    ],
    "wof:name":"Ultra Cleaning",
    "wof:placetype":"venue"
},
  "geometry": {"coordinates":[-74.489457,40.801451],"type":"Point"}
}