{
  "type": "Feature",
  "properties": {
    "addr:full":"349 Smith St Perth Amboy NJ 08861",
    "addr:housenumber":"349",
    "addr:postcode":"08861",
    "addr:street":"Smith St",
    "iso:country":"US",
    "sg:address":"349 Smith St",
    "sg:city":"Perth Amboy",
    "sg:classifiers":[
        {
            "category":"Food & Beverages",
            "subcategory":"Groceries & Convenience Stores",
            "type":"Retail Goods"
        }
    ],
    "sg:phone":"+1   ",
    "sg:postcode":"08861",
    "sg:province":"NJ",
    "wof:name":"Morronta Supermarket",
    "wof:placetype":"venue"
},
  "geometry": {"coordinates":[-74.277186,40.511007],"type":"Point"}
}