{
  "type": "Feature",
  "properties": {
    "iso:country":"US",
    "sg:address":"639 Ramsey Ave",
    "sg:city":"Hillside",
    "sg:classifiers":[
        {
            "category":"Retail",
            "subcategory":"Auto Rental",
            "type":"Services"
        }
    ],
    "sg:phone":"+1   ",
    "sg:postcode":"07205",
    "sg:province":"NJ",
    "sg:tags":[
        "truck"
    ],
    "wof:name":"Kruse Trucking Company",
    "wof:placetype":"venue"
},
  "geometry": {"coordinates":[-74.23868899999999,40.704264],"type":"Point"}
}