{
  "type": "Feature",
  "properties": {
    "addr:full":"176 Stowe St Toms River NJ 08753",
    "addr:housenumber":"176",
    "addr:postcode":"08753",
    "addr:street":"Stowe St",
    "iso:country":"US",
    "sg:address":"176 Stowe St",
    "sg:city":"Toms River",
    "sg:classifiers":[
        {
            "category":"Professional",
            "type":"Services"
        }
    ],
    "sg:phone":"+1   ",
    "sg:postcode":"08753",
    "sg:province":"NJ",
    "wof:name":"Michael Kushner",
    "wof:placetype":"venue"
},
  "geometry": {"coordinates":[-74.158794,39.990645],"type":"Point"}
}