{
  "type": "Feature",
  "properties": {
    "iso:country":"US",
    "sg:address":"912 Highway 35",
    "sg:city":"Ocean",
    "sg:classifiers":[
        {
            "category":"Professional",
            "subcategory":"Computer Services",
            "type":"Services"
        }
    ],
    "sg:postcode":"07712",
    "sg:province":"NJ",
    "sg:tags":[
        "furniture",
        "home-improvement"
    ],
    "sg:website":"http://jasonsfurniture.com/about.aspx",
    "wof:name":"Jason's Furniture",
    "wof:placetype":"venue"
},
  "geometry": {"coordinates":[-74.000406,40.219973],"type":"Point"}
}