{
  "type": "Feature",
  "properties": {
    "iso:country":"US",
    "sg:address":"240 Kinderkamack Rd",
    "sg:city":"Oradell",
    "sg:classifiers":[
        {
            "category":"Wholesale",
            "subcategory":"Machinery & Supplies",
            "type":"Manufacturing & Wholesale Goods"
        }
    ],
    "sg:phone":"+1 201 262 4241",
    "sg:postcode":"07649",
    "sg:province":"NJ",
    "sg:tags":[
        "equipment",
        "material",
        "handling"
    ],
    "wof:name":"Lawrence Gold",
    "wof:placetype":"venue"
},
  "geometry": {"coordinates":[-74.03166400000001,40.948087],"type":"Point"}
}