{
  "type": "Feature",
  "properties": {
    "addr:full":"665 Highland Ave Cherry Hill NJ 08002",
    "addr:housenumber":"665",
    "addr:postcode":"08002",
    "addr:street":"Highland Ave",
    "iso:country":"US",
    "sg:address":"665 Highland Ave",
    "sg:city":"Cherry Hill",
    "sg:classifiers":[
        {
            "category":"Wholesale",
            "subcategory":"Groceries",
            "type":"Manufacturing & Wholesale Goods"
        }
    ],
    "sg:phone":"+1 609 413 4398",
    "sg:postcode":"08002",
    "sg:province":"NJ",
    "sg:tags":[
        "hot",
        "sauce",
        "spice"
    ],
    "wof:name":"George Pappas Distributing Co",
    "wof:placetype":"venue"
},
  "geometry": {"coordinates":[-75.040803,39.9318],"type":"Point"}
}