{
  "type": "Feature",
  "properties": {
    "addr:full":"137 Washington Ave Elmwood Park NJ 07407",
    "addr:housenumber":"137",
    "addr:postcode":"07407",
    "addr:street":"Washington Ave",
    "iso:country":"US",
    "sg:address":"137 Washington Ave",
    "sg:city":"Elmwood Park",
    "sg:classifiers":[
        {
            "category":"Building & Trades",
            "subcategory":"Cleaning & Sanitation",
            "type":"Services"
        }
    ],
    "sg:phone":"+1 201 796 7521",
    "sg:postcode":"07407",
    "sg:province":"NJ",
    "sg:tags":[
        "polishing",
        "waxing",
        "floor"
    ],
    "wof:name":"J & G Hardwood Floors",
    "wof:placetype":"venue"
},
  "geometry": {"coordinates":[-74.122242,40.912726],"type":"Point"}
}