{
  "type": "Feature",
  "properties": {
    "iso:country":"US",
    "sg:address":"555 West 57th Street at 11th St.",
    "sg:city":"New York",
    "sg:classifiers":[
        {
            "category":"Retail",
            "subcategory":"Auto Repair",
            "type":"Services"
        }
    ],
    "sg:phone":"+1 212 586 6464",
    "sg:postcode":"10019",
    "sg:province":"NJ",
    "sg:website":"www.miniofmanhattan.com/",
    "wof:name":"MINI of Manhattan",
    "wof:placetype":"venue"
},
  "geometry": {"coordinates":[-73.989998,40.769901],"type":"Point"}
}