{
  "type": "Feature",
  "properties": {
    "addr:full":"4295 US Hwy 130 Beverly NJ 08010",
    "addr:housenumber":"4295",
    "addr:postcode":"08010",
    "addr:street":"Us Hwy 130",
    "iso:country":"US",
    "sg:address":"4295 US Hwy 130",
    "sg:city":"Beverly",
    "sg:classifiers":[
        {
            "category":"Restaurant",
            "type":"Food & Drink"
        }
    ],
    "sg:phone":"+1   ",
    "sg:postcode":"08010",
    "sg:province":"NJ",
    "sg:tags":[
        "eating"
    ],
    "wof:name":"McDonalds",
    "wof:placetype":"venue"
},
  "geometry": {"coordinates":[-74.904079,40.046373],"type":"Point"}
}