{
  "type": "Feature",
  "properties": {
    "addr:full":"1523 N High St Millville NJ 08332",
    "addr:housenumber":"1523",
    "addr:postcode":"08332",
    "addr:street":"N High St",
    "iso:country":"US",
    "sg:address":"1523 N High St",
    "sg:city":"Millville",
    "sg:classifiers":[
        {
            "category":"Restaurant",
            "type":"Food & Drink"
        }
    ],
    "sg:phone":"+1 856 327 0200",
    "sg:postcode":"08332",
    "sg:province":"NJ",
    "wof:name":"Hard Times Rstrnt & Pizzeria",
    "wof:placetype":"venue"
},
  "geometry": {"coordinates":[-75.039895,39.412562],"type":"Point"}
}