{
  "type": "Feature",
  "properties": {
    "addr:full":"150 W Browning Rd Bellmawr NJ 08031",
    "addr:housenumber":"150",
    "addr:postcode":"08031",
    "addr:street":"W Browning Rd",
    "iso:country":"US",
    "sg:address":"150 W Browning Rd",
    "sg:city":"Bellmawr",
    "sg:classifiers":[
        {
            "category":"Food & Beverages",
            "subcategory":"Groceries & Convenience Stores",
            "type":"Retail Goods"
        }
    ],
    "sg:phone":"+1   ",
    "sg:postcode":"08031",
    "sg:province":"NJ",
    "sg:tags":[
        "supermarket"
    ],
    "wof:name":"Heims Market",
    "wof:placetype":"venue"
},
  "geometry": {"coordinates":[-75.08819,39.866935],"type":"Point"}
}