{
  "type": "Feature",
  "properties": {
    "addr:full":"717 Franklin St Cape May NJ 08204",
    "addr:housenumber":"717",
    "addr:postcode":"08204",
    "addr:street":"Franklin St",
    "iso:country":"US",
    "sg:address":"717 Franklin St",
    "sg:city":"Cape May",
    "sg:classifiers":[
        {
            "category":"Organizations",
            "subcategory":"Religious Organization",
            "type":"Services"
        }
    ],
    "sg:phone":"+1 609 884 2626",
    "sg:postcode":"08204",
    "sg:province":"NJ",
    "sg:tags":[
        "church"
    ],
    "wof:name":"Allen African Methodist Epscpl",
    "wof:placetype":"venue"
},
  "geometry": {"coordinates":[-74.920198,38.935351],"type":"Point"}
}