{
  "type": "Feature",
  "properties": {
    "addr:full":"249 Westervelt Pl Lodi NJ 07644",
    "addr:housenumber":"249",
    "addr:postcode":"07644",
    "addr:street":"Westervelt Pl",
    "iso:country":"US",
    "sg:address":"249 Westervelt Pl",
    "sg:city":"Lodi",
    "sg:classifiers":[
        {
            "category":"Real Estate",
            "subcategory":"Real Estate Operator",
            "type":"Services"
        }
    ],
    "sg:phone":"+1   ",
    "sg:postcode":"07644",
    "sg:province":"NJ",
    "sg:tags":[
        "building",
        "nonresidential"
    ],
    "wof:name":"Alam Properties Ltd Liability",
    "wof:placetype":"venue"
},
  "geometry": {"coordinates":[-74.091341,40.879047],"type":"Point"}
}