{
  "type": "Feature",
  "properties": {
    "iso:country":"US",
    "sg:address":"156 Custer Ave",
    "sg:city":"Newark",
    "sg:classifiers":[
        {
            "category":"Organizations",
            "subcategory":"Religious Organization",
            "type":"Services"
        }
    ],
    "sg:phone":"+1 973 926 2880",
    "sg:postcode":"07112",
    "sg:province":"NJ",
    "sg:tags":[
        "church"
    ],
    "wof:name":"Pentecostal Family Prayer Ctr",
    "wof:placetype":"venue"
},
  "geometry": {"coordinates":[-74.20512600000001,40.711755],"type":"Point"}
}