{
  "type": "Feature",
  "properties": {
    "iso:country":"US",
    "sg:address":"144 Main St",
    "sg:city":"Fort Lee",
    "sg:classifiers":[
        {
            "category":"Professional",
            "subcategory":"Management & Consulting",
            "type":"Services"
        }
    ],
    "sg:phone":"+1 201 585 8100",
    "sg:postcode":"07024",
    "sg:province":"NJ",
    "sg:tags":[
        "marketing",
        "program"
    ],
    "wof:name":"American Audio Service Bureau",
    "wof:placetype":"venue"
},
  "geometry": {"coordinates":[-73.96659200000001,40.850638],"type":"Point"}
}