{
  "type": "Feature",
  "properties": {
    "iso:country":"US",
    "sg:address":"39 Lopatcong Dr",
    "sg:city":"Trenton",
    "sg:classifiers":[
        {
            "category":"Social Services",
            "subcategory":"Adult Care",
            "type":"Services"
        }
    ],
    "sg:phone":"+1 609 771 1360",
    "sg:postcode":"08638",
    "sg:province":"NJ",
    "sg:tags":[
        "home",
        "group"
    ],
    "wof:name":"Lopatcong Group Home",
    "wof:placetype":"venue"
},
  "geometry": {"coordinates":[-74.769583,40.282697],"type":"Point"}
}