{
  "type": "Feature",
  "properties": {
    "addr:full":"2 Germack Dr Carteret NJ 07008",
    "addr:housenumber":"2",
    "addr:postcode":"07008",
    "addr:street":"Germack Dr",
    "iso:country":"US",
    "sg:address":"2 Germack Dr",
    "sg:city":"Carteret",
    "sg:classifiers":[
        {
            "category":"Manufacturing",
            "subcategory":"Apparel",
            "type":"Manufacturing & Wholesale Goods"
        }
    ],
    "sg:phone":"+1 732 541 7670",
    "sg:postcode":"07008",
    "sg:province":"NJ",
    "sg:tags":[
        "mfg"
    ],
    "wof:name":"Age Group LTD",
    "wof:placetype":"venue"
},
  "geometry": {"coordinates":[-74.24251099999999,40.592423],"type":"Point"}
}