{
  "type": "Feature",
  "properties": {
    "iso:country":"US",
    "sg:address":"301 Stillwells Corner Rd",
    "sg:city":"Freehold",
    "sg:classifiers":[
        {
            "category":"Social Services",
            "type":"Services"
        }
    ],
    "sg:phone":"+1 732 577 9792",
    "sg:postcode":"07728",
    "sg:province":"NJ",
    "sg:tags":[
        "counseling"
    ],
    "wof:name":"Sznyters Pathway To Health",
    "wof:placetype":"venue"
},
  "geometry": {"coordinates":[-74.294478,40.233174],"type":"Point"}
}