{
  "type": "Feature",
  "properties": {
    "addr:full":"326 9th St Jersey City NJ 07302",
    "addr:housenumber":"326",
    "addr:postcode":"07302",
    "addr:street":"9Th St",
    "iso:country":"US",
    "sg:address":"326 9th St",
    "sg:city":"Jersey City",
    "sg:classifiers":[
        {
            "category":"Health Services",
            "subcategory":"Doctor",
            "type":"Services"
        }
    ],
    "sg:phone":"+1 201 716 7700",
    "sg:postcode":"07302",
    "sg:province":"NJ",
    "sg:tags":[
        "clinic"
    ],
    "wof:name":"Dialysis Center",
    "wof:placetype":"venue"
},
  "geometry": {"coordinates":[-74.049915,40.728866],"type":"Point"}
}