{
  "type": "Feature",
  "properties": {
    "iso:country":"US",
    "sg:address":"224 Highland Ave",
    "sg:city":"Newton",
    "sg:classifiers":[
        {
            "category":"Retail",
            "subcategory":"Repair Shop",
            "type":"Services"
        }
    ],
    "sg:phone":"+1   ",
    "sg:postcode":"07860",
    "sg:province":"NJ",
    "sg:tags":[
        "excavation"
    ],
    "wof:name":"Brodhecker Ldscpg & Excvtg",
    "wof:placetype":"venue"
},
  "geometry": {"coordinates":[-74.772655,41.121701],"type":"Point"}
}