{
  "type": "Feature",
  "properties": {
    "iso:country":"US",
    "sg:address":"893 North Ave W",
    "sg:city":"Westfield",
    "sg:classifiers":[
        {
            "category":"Insurance",
            "subcategory":"Title Insurance",
            "type":"Services"
        }
    ],
    "sg:phone":"+1   ",
    "sg:postcode":"07090",
    "sg:province":"NJ",
    "sg:tags":[
        "carrier"
    ],
    "wof:name":"Distinctive Land Ttle Svcs LLC",
    "wof:placetype":"venue"
},
  "geometry": {"coordinates":[-74.358457,40.648802],"type":"Point"}
}