{
  "type": "Feature",
  "properties": {
    "iso:country":"US",
    "sg:address":"13 N Hartford Ave",
    "sg:city":"Atlantic City",
    "sg:classifiers":[
        {
            "category":"Health Services",
            "subcategory":"Hospital",
            "type":"Services"
        },
        {
            "category":"Health Services",
            "subcategory":"Doctor",
            "type":"Services"
        }
    ],
    "sg:phone":"+1 609 348 1161",
    "sg:postcode":"08401",
    "sg:province":"NJ",
    "sg:tags":[
        "medical",
        "mental"
    ],
    "wof:name":"Atlantic Care Behavioral Healt",
    "wof:placetype":"venue"
},
  "geometry": {"coordinates":[-74.454604,39.35318],"type":"Point"}
}