{
  "type": "Feature",
  "properties": {
    "iso:country":"US",
    "sg:address":"5330 State Rte 42",
    "sg:city":"Blackwood",
    "sg:classifiers":[
        {
            "category":"Retail",
            "subcategory":"Auto Repair",
            "type":"Services"
        }
    ],
    "sg:phone":"+1 856 228 7676",
    "sg:postcode":"08012",
    "sg:province":"NJ",
    "sg:tags":[
        "body",
        "automobile",
        "painting"
    ],
    "wof:name":"Corsello's Auto Body",
    "wof:placetype":"venue"
},
  "geometry": {"coordinates":[-75.046431,39.754729],"type":"Point"}
}