{
  "type": "Feature",
  "properties": {
    "iso:country":"US",
    "sg:address":"207 Sloop Creek Rd",
    "sg:city":"Bayville",
    "sg:classifiers":[
        {
            "category":"Shopping",
            "subcategory":"Bicycles & Sporting Goods",
            "type":"Retail Goods"
        }
    ],
    "sg:phone":"+1   ",
    "sg:postcode":"08721",
    "sg:province":"NJ",
    "sg:tags":[
        "tackle",
        "shop",
        "bait"
    ],
    "wof:name":"Shack In Swamp Bait",
    "wof:placetype":"venue"
},
  "geometry": {"coordinates":[-74.136066,39.904891],"type":"Point"}
}