{
  "type": "Feature",
  "properties": {
    "addr:full":"33 W High St Somerville NJ 08876",
    "addr:housenumber":"33",
    "addr:postcode":"08876",
    "addr:street":"W High St",
    "iso:country":"US",
    "sg:address":"33 W High St",
    "sg:city":"Somerville",
    "sg:classifiers":[
        {
            "category":"Insurance",
            "subcategory":"Insurance Agent",
            "type":"Services"
        }
    ],
    "sg:phone":"+1 908 722 1700",
    "sg:postcode":"08876",
    "sg:province":"NJ",
    "sg:website":"www.riceagency.com",
    "wof:name":"Rice Agency",
    "wof:placetype":"venue"
},
  "geometry": {"coordinates":[-74.612769,40.570149],"type":"Point"}
}