{
  "type": "Feature",
  "properties": {
    "addr:full":"262 Gregory Ave Passaic NJ 07055",
    "addr:housenumber":"262",
    "addr:postcode":"07055",
    "addr:street":"Gregory Ave",
    "iso:country":"US",
    "sg:address":"262 Gregory Ave",
    "sg:city":"Passaic",
    "sg:classifiers":[
        {
            "category":"Professional",
            "subcategory":"Lawyer & Legal Services",
            "type":"Services"
        }
    ],
    "sg:phone":"+1 973 365 1200",
    "sg:postcode":"07055",
    "sg:province":"NJ",
    "sg:tags":[
        "attorney"
    ],
    "wof:name":"Chapman Wisotsky & Rosenberg",
    "wof:placetype":"venue"
},
  "geometry": {"coordinates":[-74.129671,40.858617],"type":"Point"}
}