{
  "type": "Feature",
  "properties": {
    "iso:country":"US",
    "sg:address":"116 Avignon Way",
    "sg:city":"Pennsauken",
    "sg:classifiers":[
        {
            "category":"Wholesale",
            "subcategory":"Metals & Minerals",
            "type":"Manufacturing & Wholesale Goods"
        }
    ],
    "sg:phone":"+1 856 665 6384",
    "sg:postcode":"08109",
    "sg:province":"NJ",
    "sg:tags":[
        "steel",
        "mill",
        "center",
        "broker"
    ],
    "wof:name":"Avignon Steel, Inc",
    "wof:placetype":"venue"
},
  "geometry": {"coordinates":[-75.021389,39.954266],"type":"Point"}
}