{
  "type": "Feature",
  "properties": {
    "iso:country":"US",
    "sg:address":"1315 Beaver Dam Rd",
    "sg:city":"Pt Pleasant Boro",
    "sg:classifiers":[
        {
            "category":"Shopping",
            "subcategory":"Clothing, Apparel, & Fashions",
            "type":"Retail Goods"
        }
    ],
    "sg:phone":"+1 732 892 3333",
    "sg:postcode":"08742",
    "sg:province":"NJ",
    "sg:tags":[
        "uniform"
    ],
    "wof:name":"Textiles-Plus",
    "wof:placetype":"venue"
},
  "geometry": {"coordinates":[-74.07233600000001,40.072015],"type":"Point"}
}