{
  "type": "Feature",
  "properties": {
    "addr:full":"63 Brunswick Woods Dr East Brunswick NJ 08816",
    "addr:housenumber":"63",
    "addr:postcode":"08816",
    "addr:street":"Brunswick Woods Dr",
    "iso:country":"US",
    "sg:address":"63 Brunswick Woods Dr",
    "sg:city":"East Brunswick",
    "sg:classifiers":[
        {
            "category":"Real Estate",
            "subcategory":"Real Estate Agent",
            "type":"Services"
        }
    ],
    "sg:phone":"+1   ",
    "sg:postcode":"08816",
    "sg:province":"NJ",
    "sg:tags":[
        "broker"
    ],
    "wof:name":"Grimm Agency",
    "wof:placetype":"venue"
},
  "geometry": {"coordinates":[-74.3918,40.421921],"type":"Point"}
}