{
  "type": "Feature",
  "properties": {
    "addr:full":"88 Lynn Ct Belford NJ 07718",
    "addr:housenumber":"88",
    "addr:postcode":"07718",
    "addr:street":"Lynn Ct",
    "iso:country":"US",
    "sg:address":"88 Lynn Ct",
    "sg:city":"Belford",
    "sg:classifiers":[
        {
            "category":"Shopping",
            "subcategory":"Stationery & Office Supplies",
            "type":"Retail Goods"
        }
    ],
    "sg:phone":"+1   ",
    "sg:postcode":"07718",
    "sg:province":"NJ",
    "sg:tags":[
        "merchandise"
    ],
    "wof:name":"American Business Supply Co",
    "wof:placetype":"venue"
},
  "geometry": {"coordinates":[-74.09527,40.413141],"type":"Point"}
}