{
  "type": "Feature",
  "properties": {
    "iso:country":"US",
    "sg:address":"3 Passaic Valley Rd",
    "sg:city":"Montville",
    "sg:classifiers":[
        {
            "category":"Wholesale",
            "subcategory":"Computers",
            "type":"Manufacturing & Wholesale Goods"
        }
    ],
    "sg:phone":"+1 973 402 5509",
    "sg:postcode":"07045",
    "sg:province":"NJ",
    "wof:name":"Eknowtech",
    "wof:placetype":"venue"
},
  "geometry": {"coordinates":[-74.359618,40.903545],"type":"Point"}
}