{
  "type": "Feature",
  "properties": {
    "addr:full":"5 Stelton Rd Piscataway NJ 08854",
    "addr:housenumber":"5",
    "addr:postcode":"08854",
    "addr:street":"Stelton Rd",
    "iso:country":"US",
    "sg:address":"5 Stelton Rd",
    "sg:city":"Piscataway",
    "sg:classifiers":[
        {
            "category":"Retail",
            "subcategory":"Auto Repair",
            "type":"Services"
        }
    ],
    "sg:phone":"+1 732 752 5225",
    "sg:postcode":"08854",
    "sg:province":"NJ",
    "sg:tags":[
        "repairing",
        "automobile"
    ],
    "wof:name":"Total Automotive Inc",
    "wof:placetype":"venue"
},
  "geometry": {"coordinates":[-74.457455,40.57499],"type":"Point"}
}