{
  "type": "Feature",
  "properties": {
    "addr:full":"138 W Union Ave Bound Brook NJ 08805",
    "addr:housenumber":"138",
    "addr:postcode":"08805",
    "addr:street":"W Union Ave",
    "iso:country":"US",
    "sg:address":"138 W Union Ave",
    "sg:city":"Bound Brook",
    "sg:classifiers":[
        {
            "category":"Shopping",
            "subcategory":"Used Merchandise",
            "type":"Retail Goods"
        }
    ],
    "sg:phone":"+1 732 469 5167",
    "sg:postcode":"08805",
    "sg:province":"NJ",
    "sg:tags":[
        "antique"
    ],
    "wof:name":"Lou's Antique & Book Buyers",
    "wof:placetype":"venue"
},
  "geometry": {"coordinates":[-74.53760699999999,40.567181],"type":"Point"}
}