{
  "type": "Feature",
  "properties": {
    "addr:full":"208 Warren St Harrison NJ 07029",
    "addr:housenumber":"208",
    "addr:postcode":"07029",
    "addr:street":"Warren St",
    "iso:country":"US",
    "sg:address":"208 Warren St",
    "sg:city":"Harrison",
    "sg:classifiers":[
        {
            "category":"Professional",
            "subcategory":"Detective & Security Services",
            "type":"Services"
        }
    ],
    "sg:phone":"+1   ",
    "sg:postcode":"07029",
    "sg:province":"NJ",
    "sg:tags":[
        "consulting",
        "guard"
    ],
    "wof:name":"Yankee Security",
    "wof:placetype":"venue"
},
  "geometry": {"coordinates":[-74.160235,40.744459],"type":"Point"}
}