{
  "type": "Feature",
  "properties": {
    "addr:full":"143 Brookside Dr Belford NJ 07718",
    "addr:housenumber":"143",
    "addr:postcode":"07718",
    "addr:street":"Brookside Dr",
    "iso:country":"US",
    "sg:address":"143 Brookside Dr",
    "sg:city":"Belford",
    "sg:classifiers":[
        {
            "category":"Professional",
            "subcategory":"Business Services",
            "type":"Services"
        }
    ],
    "sg:phone":"+1   ",
    "sg:postcode":"07718",
    "sg:province":"NJ",
    "wof:name":"Rowse Enterprises LLC",
    "wof:placetype":"venue"
},
  "geometry": {"coordinates":[-74.09253099999999,40.411183],"type":"Point"}
}