{
  "type": "Feature",
  "properties": {
    "addr:full":"347 Janes Chapel Rd Oxford NJ 07863",
    "addr:housenumber":"347",
    "addr:postcode":"07863",
    "addr:street":"Janes Chapel Rd",
    "iso:country":"US",
    "sg:address":"347 Janes Chapel Rd",
    "sg:city":"Oxford",
    "sg:classifiers":[
        {
            "category":"Professional",
            "type":"Services"
        }
    ],
    "sg:phone":"+1 908 637 8932",
    "sg:postcode":"07863",
    "sg:province":"NJ",
    "sg:tags":[
        "establishment"
    ],
    "wof:name":"Vey Bertolini & Co",
    "wof:placetype":"venue"
},
  "geometry": {"coordinates":[-74.923091,40.839581],"type":"Point"}
}