{
  "type": "Feature",
  "properties": {
    "addr:full":"84 Papscoe Rd Hewitt NJ 07421",
    "addr:housenumber":"84",
    "addr:postcode":"07421",
    "addr:street":"Papscoe Rd",
    "iso:country":"US",
    "sg:address":"84 Papscoe Rd",
    "sg:city":"Hewitt",
    "sg:classifiers":[
        {
            "category":"Manufacturing",
            "subcategory":"Textiles",
            "type":"Manufacturing & Wholesale Goods"
        }
    ],
    "sg:phone":"+1 973 853 6553",
    "sg:postcode":"07421",
    "sg:province":"NJ",
    "sg:tags":[
        "product",
        "sales"
    ],
    "wof:name":"Tree-Lite",
    "wof:placetype":"venue"
},
  "geometry": {"coordinates":[-74.36156699999999,41.187996],"type":"Point"}
}