{
  "type": "Feature",
  "properties": {
    "iso:country":"US",
    "sg:address":"376 Avon Ave",
    "sg:city":"Newark",
    "sg:classifiers":[
        {
            "category":"Recreation",
            "type":"Entertainment"
        }
    ],
    "sg:phone":"+1 973 624 9695",
    "sg:postcode":"07108",
    "sg:province":"NJ",
    "sg:tags":[
        "club",
        "membership"
    ],
    "wof:name":"Wolverine Rod & Gun Club",
    "wof:placetype":"venue"
},
  "geometry": {"coordinates":[-74.20679,40.726892],"type":"Point"}
}