{
  "type": "Feature",
  "properties": {
    "iso:country":"US",
    "sg:address":"47 Stone Ave",
    "sg:city":"Hopatcong",
    "sg:classifiers":[
        {
            "category":"Local Transit",
            "type":"Transportation"
        }
    ],
    "sg:phone":"+1 973 398 5606",
    "sg:postcode":"07843",
    "sg:province":"NJ",
    "sg:tags":[
        "passenger"
    ],
    "wof:name":"TW Fries Transportation",
    "wof:placetype":"venue"
},
  "geometry": {"coordinates":[-74.663234,40.92326],"type":"Point"}
}