{
  "type": "Feature",
  "properties": {
    "iso:country":"US",
    "sg:address":"84 Main St",
    "sg:city":"Matawan",
    "sg:classifiers":[
        {
            "category":"Professional",
            "subcategory":"Lawyer & Legal Services",
            "type":"Services"
        }
    ],
    "sg:phone":"+1 732 583 3400",
    "sg:postcode":"07747",
    "sg:province":"NJ",
    "sg:tags":[
        "attorney"
    ],
    "wof:name":"Frederick J Kalma",
    "wof:placetype":"venue"
},
  "geometry": {"coordinates":[-74.228566,40.417026],"type":"Point"}
}