{
  "type": "Feature",
  "properties": {
    "addr:full":"150 River Rd Montville NJ 07045",
    "addr:housenumber":"150",
    "addr:postcode":"07045",
    "addr:street":"River Rd",
    "iso:country":"US",
    "sg:address":"150 River Rd",
    "sg:city":"Montville",
    "sg:classifiers":[
        {
            "category":"Health Services",
            "subcategory":"Chiropractor",
            "type":"Services"
        }
    ],
    "sg:phone":"+1 973 263 0859",
    "sg:postcode":"07045",
    "sg:province":"NJ",
    "wof:name":"Greenbrook Chiropractic Center",
    "wof:placetype":"venue"
},
  "geometry": {"coordinates":[-74.369863,40.890696],"type":"Point"}
}