{
  "type": "Feature",
  "properties": {
    "iso:country":"US",
    "sg:address":"27 Whistler Dr",
    "sg:city":"Freehold",
    "sg:classifiers":[
        {
            "category":"Local Transit",
            "type":"Transportation"
        }
    ],
    "sg:phone":"+1 732 995 2420",
    "sg:postcode":"07728",
    "sg:province":"NJ",
    "sg:tags":[
        "limousine"
    ],
    "sg:website":"www.acarforhire.com",
    "wof:name":"ACARFORHIRE.COM",
    "wof:placetype":"venue"
},
  "geometry": {"coordinates":[-74.268354,40.248718],"type":"Point"}
}