{
  "type": "Feature",
  "properties": {
    "addr:full":"31 Park St Montclair NJ 07042",
    "addr:housenumber":"31",
    "addr:postcode":"07042",
    "addr:street":"Park St",
    "iso:country":"US",
    "sg:address":"31 Park St",
    "sg:city":"Montclair",
    "sg:classifiers":[
        {
            "category":"Professional",
            "subcategory":"Management & Consulting",
            "type":"Services"
        }
    ],
    "sg:phone":"+1 973 744 2500",
    "sg:postcode":"07042",
    "sg:province":"NJ",
    "sg:tags":[
        "consultant"
    ],
    "wof:name":"Acumen Strategic Consltng Grp",
    "wof:placetype":"venue"
},
  "geometry": {"coordinates":[-74.21914099999999,40.815124],"type":"Point"}
}