{
  "type": "Feature",
  "properties": {
    "iso:country":"US",
    "sg:address":"343 Mount Hope Ave",
    "sg:city":"Rockaway",
    "sg:classifiers":[
        {
            "category":"Food & Beverages",
            "subcategory":"Groceries & Convenience Stores",
            "type":"Retail Goods"
        }
    ],
    "sg:phone":"+1 973 989 8503",
    "sg:postcode":"07866",
    "sg:province":"NJ",
    "sg:tags":[
        "grocer"
    ],
    "wof:name":"Acme Markets",
    "wof:placetype":"venue"
},
  "geometry": {"coordinates":[-74.533287,40.916589],"type":"Point"}
}