{
  "type": "Feature",
  "properties": {
    "addr:full":"225 State Rt 23 S Hamburg NJ 07419",
    "addr:housenumber":"225",
    "addr:postcode":"07419",
    "addr:street":"State Rt 23 S",
    "iso:country":"US",
    "sg:address":"225 State Rt 23 S",
    "sg:city":"Hamburg",
    "sg:classifiers":[
        {
            "category":"Real Estate",
            "subcategory":"Real Estate Services",
            "type":"Services"
        },
        {
            "category":"Real Estate",
            "subcategory":"Real Estate Agent",
            "type":"Services"
        }
    ],
    "sg:phone":"+1 973 823 0231",
    "sg:postcode":"07419",
    "sg:province":"NJ",
    "sg:tags":[
        "buyer",
        "broker"
    ],
    "wof:name":"Exit 23 Realty",
    "wof:placetype":"venue"
},
  "geometry": {"coordinates":[-74.57223399999999,41.141587],"type":"Point"}
}