{
  "type": "Feature",
  "properties": {
    "iso:country":"US",
    "sg:address":"1380 Frontier Rd",
    "sg:city":"Bridgewater",
    "sg:classifiers":[
        {
            "category":"Utilities",
            "type":"Services"
        }
    ],
    "sg:phone":"+1 732 356 6320",
    "sg:postcode":"08807",
    "sg:province":"NJ",
    "sg:tags":[
        "combination"
    ],
    "wof:name":"Gray Supply Corp",
    "wof:placetype":"venue"
},
  "geometry": {"coordinates":[-74.566836,40.576403],"type":"Point"}
}