{
  "type": "Feature",
  "properties": {
    "addr:full":"158 Washington Ave Elizabeth NJ 07202",
    "addr:housenumber":"158",
    "addr:postcode":"07202",
    "addr:street":"Washington Ave",
    "iso:country":"US",
    "sg:address":"158 Washington Ave",
    "sg:city":"Elizabeth",
    "sg:classifiers":[
        {
            "category":"Education",
            "subcategory":"Dance Studio",
            "type":"Public Place"
        }
    ],
    "sg:phone":"+1 908 355 5535",
    "sg:postcode":"07202",
    "sg:province":"NJ",
    "sg:tags":[
        "instruction",
        "dancing"
    ],
    "wof:name":"Donna's Academy Of Dance",
    "wof:placetype":"venue"
},
  "geometry": {"coordinates":[-74.218463,40.657634],"type":"Point"}
}