{
  "type": "Feature",
  "properties": {
    "iso:country":"US",
    "sg:address":"501 N Pompess Ave",
    "sg:city":"Cinnaminson",
    "sg:classifiers":[
        {
            "category":"Manufacturing",
            "subcategory":"Tools & Machinery",
            "type":"Manufacturing & Wholesale Goods"
        }
    ],
    "sg:phone":"+1 856 829 0506",
    "sg:postcode":"08077",
    "sg:province":"NJ",
    "sg:tags":[
        "machine",
        "shop"
    ],
    "wof:name":"Brothers Tool & Machine Inc",
    "wof:placetype":"venue"
},
  "geometry": {"coordinates":[-75.006377,40.013062],"type":"Point"}
}