{
  "type": "Feature",
  "properties": {
    "addr:full":"143 Brookfield Ave Nutley NJ 07110",
    "addr:housenumber":"143",
    "addr:postcode":"07110",
    "addr:street":"Brookfield Ave",
    "iso:country":"US",
    "sg:address":"143 Brookfield Ave",
    "sg:city":"Nutley",
    "sg:classifiers":[
        {
            "category":"Wholesale",
            "subcategory":"Stationery",
            "type":"Manufacturing & Wholesale Goods"
        }
    ],
    "sg:phone":"+1 973 284 1900",
    "sg:postcode":"07110",
    "sg:province":"NJ",
    "sg:tags":[
        "product",
        "paper"
    ],
    "wof:name":"Semper Exeter Paper Co",
    "wof:placetype":"venue"
},
  "geometry": {"coordinates":[-74.151836,40.8241],"type":"Point"}
}