{
  "type": "Feature",
  "properties": {
    "addr:full":"6 Molly Bee Rd Flemington NJ 08822",
    "addr:housenumber":"6",
    "addr:postcode":"08822",
    "addr:street":"Molly Bee Rd",
    "iso:country":"US",
    "sg:address":"6 Molly Bee Rd",
    "sg:city":"Flemington",
    "sg:classifiers":[
        {
            "category":"Building & Trades",
            "subcategory":"Electrical",
            "type":"Services"
        }
    ],
    "sg:phone":"+1 908 788 7608",
    "sg:postcode":"08822",
    "sg:province":"NJ",
    "sg:tags":[
        "electrical",
        "contractor"
    ],
    "wof:name":"Chad A Minikus Elec Contrs",
    "wof:placetype":"venue"
},
  "geometry": {"coordinates":[-74.816238,40.50659],"type":"Point"}
}