{
  "type": "Feature",
  "properties": {
    "addr:full":"223 Franklin Ave Nutley NJ 07110",
    "addr:housenumber":"223",
    "addr:postcode":"07110",
    "addr:street":"Franklin Ave",
    "iso:country":"US",
    "sg:address":"223 Franklin Ave",
    "sg:city":"Nutley",
    "sg:classifiers":[
        {
            "category":"Bars & Pubs",
            "type":"Food & Drink"
        },
        {
            "category":"Restaurant",
            "type":"Food & Drink"
        }
    ],
    "sg:phone":"+1 973 320 5468",
    "sg:postcode":"07110",
    "sg:province":"NJ",
    "sg:tags":[
        "traditional",
        "american"
    ],
    "sg:website":"midtownbarandgrill.com",
    "wof:name":"Midtown Bar and Grill",
    "wof:placetype":"venue"
},
  "geometry": {"coordinates":[-74.162239,40.81545],"type":"Point"}
}