{
  "type": "Feature",
  "properties": {
    "iso:country":"US",
    "sg:address":"21 Grand Ave Ste 620",
    "sg:city":"Palisades Park",
    "sg:classifiers":[
        {
            "category":"Building & Trades",
            "subcategory":"Construction",
            "type":"Services"
        }
    ],
    "sg:phone":"+1 201 941 4200",
    "sg:postcode":"07650",
    "sg:province":"NJ",
    "sg:tags":[
        "contractor"
    ],
    "wof:name":"Fiorino Construction Comp Llc",
    "wof:placetype":"venue"
},
  "geometry": {"coordinates":[-74.00484299999999,40.844287],"type":"Point"}
}