{
  "type": "Feature",
  "properties": {
    "iso:country":"US",
    "sg:address":"844 State Rte 35",
    "sg:city":"Middletown",
    "sg:classifiers":[
        {
            "category":"Personal",
            "subcategory":"Beauty Salon",
            "type":"Services"
        }
    ],
    "sg:phone":"+1 732 796 0600",
    "sg:postcode":"07748",
    "sg:province":"NJ",
    "sg:tags":[
        "shop",
        "manicuring"
    ],
    "wof:name":"Art Pro Nails",
    "wof:placetype":"venue"
},
  "geometry": {"coordinates":[-74.100486,40.392033],"type":"Point"}
}