{
  "type": "Feature",
  "properties": {
    "addr:full":"115 Hayes St Clark NJ 07066",
    "addr:housenumber":"115",
    "addr:postcode":"07066",
    "addr:street":"Hayes St",
    "iso:country":"US",
    "sg:address":"115 Hayes St",
    "sg:city":"Clark",
    "sg:classifiers":[
        {
            "category":"Building & Trades",
            "subcategory":"Equipment Rental",
            "type":"Services"
        }
    ],
    "sg:phone":"+1   ",
    "sg:postcode":"07066",
    "sg:province":"NJ",
    "wof:name":"Nelson Dacosta",
    "wof:placetype":"venue"
},
  "geometry": {"coordinates":[-74.31027400000001,40.609179],"type":"Point"}
}