{
  "type": "Feature",
  "properties": {
    "addr:full":"2 W Front St Keyport NJ 07735",
    "addr:housenumber":"2",
    "addr:postcode":"07735",
    "addr:street":"W Front St",
    "iso:country":"US",
    "sg:address":"2 W Front St",
    "sg:city":"Keyport",
    "sg:classifiers":[
        {
            "category":"Bars & Pubs",
            "type":"Food & Drink"
        },
        {
            "category":"Restaurant",
            "type":"Food & Drink"
        }
    ],
    "sg:phone":"+1 732 264 0999",
    "sg:postcode":"07735",
    "sg:province":"NJ",
    "sg:tags":[
        "brew",
        "tavern"
    ],
    "sg:website":"http://www.mcdonaghs.com",
    "wof:name":"McDonagh's Pub",
    "wof:placetype":"venue"
},
  "geometry": {"coordinates":[-74.20201900000001,40.437599],"type":"Point"}
}