{
  "type": "Feature",
  "properties": {
    "addr:full":"138 Lakeview Dr S Gibbsboro NJ 08026",
    "addr:housenumber":"138",
    "addr:postcode":"08026",
    "addr:street":"Lakeview Dr S",
    "iso:country":"US",
    "sg:address":"138 Lakeview Dr S",
    "sg:city":"Gibbsboro",
    "sg:phone":"+1 856 783 3400",
    "sg:postcode":"08026",
    "sg:province":"NJ",
    "sg:tags":[
        "equipment",
        "supply"
    ],
    "sg:website":"www.schmiddewland.com",
    "wof:name":"Schmid-Dewland Assoc",
    "wof:placetype":"venue"
},
  "geometry": {"coordinates":[-74.95814900000001,39.834369],"type":"Point"}
}