{
  "type": "Feature",
  "properties": {
    "addr:full":"522 Commissioners Pike Woodstown NJ 08098",
    "addr:housenumber":"522",
    "addr:postcode":"08098",
    "addr:street":"Commissioners Pike",
    "iso:country":"US",
    "sg:address":"522 Commissioners Pike",
    "sg:city":"Woodstown",
    "sg:classifiers":[
        {
            "category":"Retail",
            "subcategory":"Repair Shop",
            "type":"Services"
        }
    ],
    "sg:phone":"+1   ",
    "sg:postcode":"08098",
    "sg:province":"NJ",
    "wof:name":"Triple D",
    "wof:placetype":"venue"
},
  "geometry": {"coordinates":[-75.274429,39.615631],"type":"Point"}
}