{
  "type": "Feature",
  "properties": {
    "addr:full":"1710 Wickford Rd South Plainfield NJ 07080",
    "addr:housenumber":"1710",
    "addr:postcode":"07080",
    "addr:street":"Wickford Rd",
    "iso:country":"US",
    "sg:address":"1710 Wickford Rd",
    "sg:city":"South Plainfield",
    "sg:classifiers":[
        {
            "category":"Building & Trades",
            "subcategory":"Construction",
            "type":"Services"
        }
    ],
    "sg:phone":"+1 732 290 1001",
    "sg:postcode":"07080",
    "sg:province":"NJ",
    "sg:tags":[
        "painter"
    ],
    "wof:name":"Paint Creations",
    "wof:placetype":"venue"
},
  "geometry": {"coordinates":[-74.41499399999999,40.593996],"type":"Point"}
}