{
  "type": "Feature",
  "properties": {
    "iso:country":"US",
    "sg:address":"1068 E Landis Ave",
    "sg:city":"Vineland",
    "sg:classifiers":[
        {
            "category":"Real Estate",
            "subcategory":"Surveying",
            "type":"Services"
        }
    ],
    "sg:phone":"+1 856 691 1982",
    "sg:postcode":"08360",
    "sg:province":"NJ",
    "sg:tags":[
        "surveyor"
    ],
    "wof:name":"Bernard Surveying",
    "wof:placetype":"venue"
},
  "geometry": {"coordinates":[-75.01106799999999,39.485482],"type":"Point"}
}