{
  "type": "Feature",
  "properties": {
    "iso:country":"US",
    "sg:address":"141 Lanza Ave",
    "sg:city":"Garfield",
    "sg:classifiers":[
        {
            "category":"Home & Garden",
            "subcategory":"Carpets & Floor Coverings",
            "type":"Retail Goods"
        }
    ],
    "sg:phone":"+1   ",
    "sg:postcode":"07026",
    "sg:province":"NJ",
    "wof:name":"United Rugs Wholesale",
    "wof:placetype":"venue"
},
  "geometry": {"coordinates":[-74.120329,40.88661],"type":"Point"}
}