{
  "type": "Feature",
  "properties": {
    "iso:country":"US",
    "sg:address":"17 Oregon Ave",
    "sg:city":"Hazlet",
    "sg:classifiers":[
        {
            "category":"Building & Trades",
            "subcategory":"Landscaping Services",
            "type":"Services"
        }
    ],
    "sg:phone":"+1 732 264 4724",
    "sg:postcode":"07730",
    "sg:province":"NJ",
    "wof:name":"Baranowski Landscaping",
    "wof:placetype":"venue"
},
  "geometry": {"coordinates":[-74.162958,40.428265],"type":"Point"}
}