{
  "type": "Feature",
  "properties": {
    "iso:country":"US",
    "sg:address":"202 Broad St",
    "sg:city":"Riverton",
    "sg:classifiers":[
        {
            "category":"Insurance",
            "subcategory":"Insurance Agent",
            "type":"Services"
        }
    ],
    "sg:phone":"+1   ",
    "sg:postcode":"08077",
    "sg:province":"NJ",
    "wof:name":"C B Financial",
    "wof:placetype":"venue"
},
  "geometry": {"coordinates":[-75.014703,40.008177],"type":"Point"}
}