{
  "type": "Feature",
  "properties": {
    "addr:full":"492 Ackerson Ave Wyckoff NJ 07481",
    "addr:housenumber":"492",
    "addr:postcode":"07481",
    "addr:street":"Ackerson Ave",
    "iso:country":"US",
    "sg:address":"492 Ackerson Ave",
    "sg:city":"Wyckoff",
    "sg:classifiers":[
        {
            "category":"Shopping",
            "subcategory":"Hobbies, Toys, & Games",
            "type":"Retail Goods"
        }
    ],
    "sg:phone":"+1 201 796 7377",
    "sg:postcode":"07481",
    "sg:province":"NJ",
    "sg:tags":[
        "supply"
    ],
    "wof:name":"Game Master LTD",
    "wof:placetype":"venue"
},
  "geometry": {"coordinates":[-74.179005,40.999184],"type":"Point"}
}