{
  "type": "Feature",
  "properties": {
    "iso:country":"US",
    "sg:address":"23 Schindler Dr",
    "sg:city":"Rockaway",
    "sg:classifiers":[
        {
            "category":"Shopping",
            "subcategory":"Bicycles & Sporting Goods",
            "type":"Retail Goods"
        }
    ],
    "sg:phone":"+1 973 989 5047",
    "sg:postcode":"07866",
    "sg:province":"NJ",
    "sg:tags":[
        "equipment",
        "camping"
    ],
    "wof:name":"Camping Expo",
    "wof:placetype":"venue"
},
  "geometry": {"coordinates":[-74.54802599999999,40.900738],"type":"Point"}
}