{
  "type": "Feature",
  "properties": {
    "iso:country":"US",
    "sg:address":"195 W Shore Ave",
    "sg:city":"Bogota",
    "sg:classifiers":[
        {
            "category":"Wholesale",
            "subcategory":"Machinery & Supplies",
            "type":"Manufacturing & Wholesale Goods"
        },
        {
            "category":"Manufacturing",
            "subcategory":"Tools & Machinery",
            "type":"Manufacturing & Wholesale Goods"
        }
    ],
    "sg:phone":"+1 201 342 3332",
    "sg:postcode":"07603",
    "sg:province":"NJ",
    "sg:tags":[
        "lubricating",
        "industrial",
        "system",
        "devices",
        "machine",
        "parts"
    ],
    "wof:name":"Brown M Fitting Specialists",
    "wof:placetype":"venue"
},
  "geometry": {"coordinates":[-74.02931,40.874662],"type":"Point"}
}