{
  "type": "Feature",
  "properties": {
    "iso:country":"US",
    "sg:address":"1403 Summit Ave",
    "sg:city":"Union City",
    "sg:classifiers":[
        {
            "category":"Insurance",
            "subcategory":"Hazard Insurance",
            "type":"Services"
        },
        {
            "category":"Professional",
            "subcategory":"Business Services",
            "type":"Services"
        }
    ],
    "sg:phone":"+1 201 864 9969",
    "sg:postcode":"07087",
    "sg:province":"NJ",
    "sg:tags":[
        "bond"
    ],
    "wof:name":"One Way Bail Bonds Inc",
    "wof:placetype":"venue"
},
  "geometry": {"coordinates":[-74.040469,40.763228],"type":"Point"}
}