{
  "type": "Feature",
  "properties": {
    "iso:country":"US",
    "sg:address":"516 Mickle Blvd",
    "sg:city":"Camden",
    "sg:classifiers":[
        {
            "category":"Education",
            "subcategory":"Special Training",
            "type":"Public Place"
        }
    ],
    "sg:phone":"+1 856 966 8600",
    "sg:postcode":"08103",
    "sg:province":"NJ",
    "sg:tags":[
        "school",
        "art"
    ],
    "wof:name":"Reese School of Art & Gallery",
    "wof:placetype":"venue"
},
  "geometry": {"coordinates":[-75.120912,39.942408],"type":"Point"}
}