{
  "type": "Feature",
  "properties": {
    "addr:full":"5300 Bergenline Pl West New York NJ 07093",
    "addr:housenumber":"5300",
    "addr:postcode":"07093",
    "addr:street":"Bergenline Pl West",
    "iso:country":"US",
    "sg:address":"5300 Bergenline Pl",
    "sg:city":"West New York",
    "sg:classifiers":[
        {
            "category":"Social Services",
            "type":"Services"
        }
    ],
    "sg:phone":"+1 201 330 9626",
    "sg:postcode":"07093",
    "sg:province":"NJ",
    "sg:tags":[
        "organization",
        "welfare"
    ],
    "wof:name":"Hispanic Information Center",
    "wof:placetype":"venue"
},
  "geometry": {"coordinates":[-74.019289,40.784897],"type":"Point"}
}