{
  "type": "Feature",
  "properties": {
    "addr:full":"453 Langley Rd Elmer NJ 08318",
    "addr:housenumber":"453",
    "addr:postcode":"08318",
    "addr:street":"Langley Rd",
    "iso:country":"US",
    "sg:address":"453 Langley Rd",
    "sg:city":"Elmer",
    "sg:classifiers":[
        {
            "category":"Wholesale",
            "subcategory":"Fruits & Vegetables",
            "type":"Manufacturing & Wholesale Goods"
        }
    ],
    "sg:phone":"+1 856 358 6618",
    "sg:postcode":"08318",
    "sg:province":"NJ",
    "sg:tags":[
        "fresh",
        "vegetables-wholesale"
    ],
    "sg:website":"http://www.abiimports.com",
    "wof:name":"Abi Imports Inc",
    "wof:placetype":"venue"
},
  "geometry": {"coordinates":[-75.097859,39.577457],"type":"Point"}
}