{
  "type": "Feature",
  "properties": {
    "addr:full":"910 Bergen Ave Jersey City NJ 07306",
    "addr:housenumber":"910",
    "addr:postcode":"07306",
    "addr:street":"Bergen Ave",
    "iso:country":"US",
    "sg:address":"910 Bergen Ave",
    "sg:city":"Jersey City",
    "sg:classifiers":[
        {
            "category":"Building & Trades",
            "subcategory":"Electrical",
            "type":"Services"
        }
    ],
    "sg:phone":"+1 201 656 4552",
    "sg:postcode":"07306",
    "sg:province":"NJ",
    "sg:tags":[
        "electrical",
        "contractor"
    ],
    "wof:name":"Electric Sound",
    "wof:placetype":"venue"
},
  "geometry": {"coordinates":[-74.065657,40.729603],"type":"Point"}
}