{
  "type": "Feature",
  "properties": {
    "addr:full":"1810 Warren Point Rd Toms River NJ 08753",
    "addr:housenumber":"1810",
    "addr:postcode":"08753",
    "addr:street":"Warren Point Rd",
    "iso:country":"US",
    "sg:address":"1810 Warren Point Rd",
    "sg:city":"Toms River",
    "sg:classifiers":[
        {
            "category":"Recreation",
            "type":"Entertainment"
        }
    ],
    "sg:phone":"+1 732 341 1000",
    "sg:postcode":"08753",
    "sg:province":"NJ",
    "sg:tags":[
        "center"
    ],
    "wof:name":"Dover Twp Recreation Dept",
    "wof:placetype":"venue"
},
  "geometry": {"coordinates":[-74.139921,39.987478],"type":"Point"}
}