{
  "type": "Feature",
  "properties": {
    "iso:country":"US",
    "sg:address":"14 Haddon Rd",
    "sg:city":"Wayne",
    "sg:classifiers":[
        {
            "category":"Building & Trades",
            "subcategory":"Electrical",
            "type":"Services"
        }
    ],
    "sg:phone":"+1 973 686 9001",
    "sg:postcode":"07470",
    "sg:province":"NJ",
    "sg:tags":[
        "electrical",
        "contractor"
    ],
    "wof:name":"Brus Electric",
    "wof:placetype":"venue"
},
  "geometry": {"coordinates":[-74.27032,40.963023],"type":"Point"}
}