{
  "type": "Feature",
  "properties": {
    "addr:full":"15 E Prospect St Waldwick NJ 07463",
    "addr:housenumber":"15",
    "addr:postcode":"07463",
    "addr:street":"E Prospect St",
    "iso:country":"US",
    "sg:address":"15 E Prospect St",
    "sg:city":"Waldwick",
    "sg:classifiers":[
        {
            "category":"Government",
            "subcategory":"Office",
            "type":"Public Place"
        }
    ],
    "sg:phone":"+1 201 652 5858",
    "sg:postcode":"07463",
    "sg:province":"NJ",
    "sg:tags":[
        "city",
        "taxation"
    ],
    "wof:name":"Waldwick City Tax Collector",
    "wof:placetype":"venue"
},
  "geometry": {"coordinates":[-74.11751,41.010812],"type":"Point"}
}