{
  "type": "Feature",
  "properties": {
    "iso:country":"US",
    "sg:address":"40 Beechwood Rd",
    "sg:city":"Caldwell",
    "sg:classifiers":[
        {
            "category":"Building & Trades",
            "subcategory":"Construction",
            "type":"Services"
        }
    ],
    "sg:phone":"+1 973 228 9501",
    "sg:postcode":"07006",
    "sg:province":"NJ",
    "sg:tags":[
        "contractor"
    ],
    "wof:name":"Potente Contracting",
    "wof:placetype":"venue"
},
  "geometry": {"coordinates":[-74.29782299999999,40.837113],"type":"Point"}
}