{
  "type": "Feature",
  "properties": {
    "addr:full":"203 Broad St Washington NJ 07882",
    "addr:housenumber":"203",
    "addr:postcode":"07882",
    "addr:street":"Broad St",
    "iso:country":"US",
    "sg:address":"203 Broad St",
    "sg:city":"Washington",
    "sg:classifiers":[
        {
            "category":"Retail",
            "subcategory":"Veterinary Services",
            "type":"Services"
        }
    ],
    "sg:phone":"+1 908 612 8860",
    "sg:postcode":"07882",
    "sg:province":"NJ",
    "wof:name":"Murphy Patrick Equine Warren",
    "wof:placetype":"venue"
},
  "geometry": {"coordinates":[-74.97806300000001,40.752474],"type":"Point"}
}