{
  "type": "Feature",
  "properties": {
    "iso:country":"US",
    "sg:address":"81 Rainflower Ln",
    "sg:city":"Princeton Junction",
    "sg:classifiers":[
        {
            "category":"Professional",
            "subcategory":"Management & Consulting",
            "type":"Services"
        }
    ],
    "sg:phone":"+1   ",
    "sg:postcode":"08550",
    "sg:province":"NJ",
    "sg:tags":[
        "business"
    ],
    "wof:name":"Marvin Greene Consulting",
    "wof:placetype":"venue"
},
  "geometry": {"coordinates":[-74.583828,40.272099],"type":"Point"}
}