{
  "type": "Feature",
  "properties": {
    "addr:full":"60 Asbury Rd Hackettstown NJ 07840",
    "addr:housenumber":"60",
    "addr:postcode":"07840",
    "addr:street":"Asbury Rd",
    "iso:country":"US",
    "sg:address":"60 Asbury Rd",
    "sg:city":"Hackettstown",
    "sg:classifiers":[
        {
            "category":"Building & Trades",
            "subcategory":"Equipment Rental",
            "type":"Services"
        }
    ],
    "sg:phone":"+1 973 208 8665",
    "sg:postcode":"07840",
    "sg:province":"NJ",
    "sg:tags":[
        "leasing"
    ],
    "wof:name":"Koudos Leasing Inc",
    "wof:placetype":"venue"
},
  "geometry": {"coordinates":[-74.86261399999999,40.864213],"type":"Point"}
}