{
  "type": "Feature",
  "properties": {
    "iso:country":"US",
    "sg:address":"2100 Boardwalk",
    "sg:city":"Atlantic City",
    "sg:classifiers":[
        {
            "category":"Restaurant",
            "type":"Food & Drink"
        }
    ],
    "sg:phone":"+1 609 345 7887",
    "sg:postcode":"08401",
    "sg:province":"NJ",
    "wof:name":"Cosimo's Cafe",
    "wof:placetype":"venue"
},
  "geometry": {"coordinates":[-74.43575199999999,39.35463],"type":"Point"}
}