{
  "type": "Feature",
  "properties": {
    "addr:full":"23 E 9th Ave Runnemede NJ 08078",
    "addr:housenumber":"23",
    "addr:postcode":"08078",
    "addr:street":"E 9Th Ave",
    "iso:country":"US",
    "sg:address":"23 E 9th Ave",
    "sg:city":"Runnemede",
    "sg:classifiers":[
        {
            "category":"Retail",
            "subcategory":"Auto Repair",
            "type":"Services"
        }
    ],
    "sg:phone":"+1 856 312 0101",
    "sg:postcode":"08078",
    "sg:province":"NJ",
    "sg:tags":[
        "body",
        "automobile",
        "painting"
    ],
    "wof:name":"9th Avenue Collision",
    "wof:placetype":"venue"
},
  "geometry": {"coordinates":[-75.073949,39.857209],"type":"Point"}
}