{
  "type": "Feature",
  "properties": {
    "addr:full":"400 S Orange Ave South Orange NJ 07079",
    "addr:housenumber":"400",
    "addr:postcode":"07079",
    "addr:street":"S Orange Ave",
    "iso:country":"US",
    "sg:address":"400 S Orange Ave",
    "sg:city":"South Orange",
    "sg:classifiers":[
        {
            "category":"Real Estate",
            "subcategory":"Real Estate Agent",
            "type":"Services"
        }
    ],
    "sg:phone":"+1 973 275 9393",
    "sg:postcode":"07079",
    "sg:province":"NJ",
    "wof:name":"Exit Realty Here For You",
    "wof:placetype":"venue"
},
  "geometry": {"coordinates":[-74.247563,40.744631],"type":"Point"}
}