{
  "type": "Feature",
  "properties": {
    "addr:full":"1925 Swarthmore Ave Lakewood NJ 08701",
    "addr:housenumber":"1925",
    "addr:postcode":"08701",
    "addr:street":"Swarthmore Ave",
    "iso:country":"US",
    "sg:address":"1925 Swarthmore Ave",
    "sg:city":"Lakewood",
    "sg:classifiers":[
        {
            "category":"Wholesale",
            "subcategory":"Electrical",
            "type":"Manufacturing & Wholesale Goods"
        }
    ],
    "sg:phone":"+1 732 901 8555",
    "sg:postcode":"08701",
    "sg:province":"NJ",
    "sg:tags":[
        "elements",
        "electric",
        "heating"
    ],
    "wof:name":"Thermco Electric Corp",
    "wof:placetype":"venue"
},
  "geometry": {"coordinates":[-74.16930499999999,40.077063],"type":"Point"}
}