{
  "type": "Feature",
  "properties": {
    "iso:country":"US",
    "sg:address":"168 Commerce St E",
    "sg:city":"Bridgeton",
    "sg:classifiers":[
        {
            "category":"Government",
            "subcategory":"Police Station",
            "type":"Public Place"
        }
    ],
    "sg:phone":"+1   ",
    "sg:postcode":"08302",
    "sg:province":"NJ",
    "sg:tags":[
        "protection"
    ],
    "wof:name":"Police Dept",
    "wof:placetype":"venue"
},
  "geometry": {"coordinates":[-75.230335,39.428616],"type":"Point"}
}