{
  "type": "Feature",
  "properties": {
    "iso:country":"US",
    "sg:address":"2276 US Hwy 9",
    "sg:city":"Cape May Ct Hse",
    "sg:classifiers":[
        {
            "category":"Recreation",
            "type":"Entertainment"
        }
    ],
    "sg:phone":"+1 609 624 1393",
    "sg:postcode":"08210",
    "sg:province":"NJ",
    "sg:tags":[
        "instruction",
        "golf"
    ],
    "wof:name":"Somerton Springs Golf",
    "wof:placetype":"venue"
},
  "geometry": {"coordinates":[-74.74464399999999,39.16653],"type":"Point"}
}