{
  "type": "Feature",
  "properties": {
    "iso:country":"US",
    "sg:address":"42 W Railroad Ave",
    "sg:city":"Tenafly",
    "sg:classifiers":[
        {
            "category":"Restaurant",
            "type":"Food & Drink"
        }
    ],
    "sg:phone":"+1   ",
    "sg:postcode":"07670",
    "sg:province":"NJ",
    "sg:tags":[
        "eating"
    ],
    "wof:name":"Good Taste Chinese Take-Out",
    "wof:placetype":"venue"
},
  "geometry": {"coordinates":[-73.96406899999999,40.928394],"type":"Point"}
}