{
  "type": "Feature",
  "properties": {
    "iso:country":"US",
    "sg:address":"775 Valley Rd",
    "sg:city":"Clifton",
    "sg:classifiers":[
        {
            "category":"Education",
            "subcategory":"School",
            "type":"Public Place"
        }
    ],
    "sg:phone":"+1 973 458 9282",
    "sg:postcode":"07013",
    "sg:province":"NJ",
    "sg:tags":[
        "high",
        "middle",
        "elementary"
    ],
    "wof:name":"Pope John Paul II School",
    "wof:placetype":"venue"
},
  "geometry": {"coordinates":[-74.18609600000001,40.874599],"type":"Point"}
}