{
  "type": "Feature",
  "properties": {
    "iso:country":"US",
    "sg:address":"2403 Appleby Dr",
    "sg:city":"Asbury Park",
    "sg:classifiers":[
        {
            "category":"Retail",
            "subcategory":"Portrait Studio",
            "type":"Services"
        },
        {
            "category":"Retail",
            "subcategory":"Photofinishing",
            "type":"Services"
        }
    ],
    "sg:phone":"+1 732 988 6972",
    "sg:postcode":"07712",
    "sg:province":"NJ",
    "sg:tags":[
        "photographer",
        "photographic"
    ],
    "wof:name":"Jeri Houseworth Photography",
    "wof:placetype":"venue"
},
  "geometry": {"coordinates":[-74.029995,40.231033],"type":"Point"}
}