{
  "type": "Feature",
  "properties": {
    "iso:country":"US",
    "sg:address":"124 Levgar St",
    "sg:city":"Piscataway",
    "sg:classifiers":[
        {
            "category":"Autos & Motor Vehicles",
            "subcategory":"Motorcycle Sales",
            "type":"Retail Goods"
        }
    ],
    "sg:phone":"+1   ",
    "sg:postcode":"08854",
    "sg:province":"NJ",
    "wof:name":"J M R Racing & Performance",
    "wof:placetype":"venue"
},
  "geometry": {"coordinates":[-74.470063,40.581073],"type":"Point"}
}