{
  "type": "Feature",
  "properties": {
    "iso:country":"US",
    "sg:address":"1575 State Rte 23",
    "sg:city":"Butler",
    "sg:classifiers":[
        {
            "category":"Real Estate",
            "subcategory":"Real Estate Agent",
            "type":"Services"
        }
    ],
    "sg:phone":"+1   ",
    "sg:postcode":"07405",
    "sg:province":"NJ",
    "wof:name":"Meyer Development",
    "wof:placetype":"venue"
},
  "geometry": {"coordinates":[-74.358749,41.005838],"type":"Point"}
}