{
  "type": "Feature",
  "properties": {
    "addr:full":"115 E Passaic St Maywood NJ 07607",
    "addr:housenumber":"115",
    "addr:postcode":"07607",
    "addr:street":"E Passaic St",
    "iso:country":"US",
    "sg:address":"115 E Passaic St",
    "sg:city":"Maywood",
    "sg:classifiers":[
        {
            "category":"Personal",
            "subcategory":"Beauty Salon",
            "type":"Services"
        }
    ],
    "sg:phone":"+1 201 843 6500",
    "sg:postcode":"07607",
    "sg:province":"NJ",
    "wof:name":"Lisa Brueh-A Salon",
    "wof:placetype":"venue"
},
  "geometry": {"coordinates":[-74.057492,40.900232],"type":"Point"}
}