{
  "type": "Feature",
  "properties": {
    "addr:full":"340 Changebridge Rd Pine Brook NJ 07058",
    "addr:housenumber":"340",
    "addr:postcode":"07058",
    "addr:street":"Changebridge Rd",
    "iso:country":"US",
    "sg:address":"340 Changebridge Rd",
    "sg:city":"Pine Brook",
    "sg:classifiers":[
        {
            "category":"Banks & Credit Unions",
            "subcategory":"Bank",
            "type":"Services"
        }
    ],
    "sg:phone":"+1 973 227 3560",
    "sg:postcode":"07058",
    "sg:province":"NJ",
    "wof:name":"Inova Federal Credit Union",
    "wof:placetype":"venue"
},
  "geometry": {"coordinates":[-74.344245,40.863892],"type":"Point"}
}