{
  "type": "Feature",
  "properties": {
    "addr:full":"Star Lake Road Bloomingdale NJ 07403",
    "addr:postcode":"07403",
    "addr:street":"Star Lake Road",
    "iso:country":"US",
    "sg:address":"Star Lake Road",
    "sg:city":"Bloomingdale",
    "sg:classifiers":[
        {
            "category":"Social Services",
            "subcategory":"Child Care",
            "type":"Services"
        }
    ],
    "sg:phone":"+1 973 703 3060",
    "sg:postcode":"07403",
    "sg:province":"NJ",
    "sg:tags":[
        "day"
    ],
    "sg:website":"www.cherylskidkonnection.com/",
    "wof:name":"Cheryl's Kid Konnection",
    "wof:placetype":"venue"
},
  "geometry": {"coordinates":[-74.342697,41.013599],"type":"Point"}
}