{
  "type": "Feature",
  "properties": {
    "iso:country":"US",
    "sg:address":"286 S 7th St",
    "sg:city":"Newark",
    "sg:classifiers":[
        {
            "category":"Social Services",
            "subcategory":"Child Care",
            "type":"Services"
        }
    ],
    "sg:phone":"+1 973 623 8400",
    "sg:postcode":"07103",
    "sg:province":"NJ",
    "sg:tags":[
        "day"
    ],
    "wof:name":"Sunshine Day Care",
    "wof:placetype":"venue"
},
  "geometry": {"coordinates":[-74.198066,40.738957],"type":"Point"}
}