{
  "type": "Feature",
  "properties": {
    "addr:full":"31 Winding Brook Way Edison NJ 08820",
    "addr:housenumber":"31",
    "addr:postcode":"08820",
    "addr:street":"Winding Brook Way",
    "iso:country":"US",
    "sg:address":"31 Winding Brook Way",
    "sg:city":"Edison",
    "sg:classifiers":[
        {
            "category":"Shopping",
            "subcategory":"Computers & Home Electronics",
            "type":"Retail Goods"
        }
    ],
    "sg:phone":"+1   ",
    "sg:postcode":"08820",
    "sg:province":"NJ",
    "wof:name":"Avon Technologies Inc",
    "wof:placetype":"venue"
},
  "geometry": {"coordinates":[-74.366314,40.591732],"type":"Point"}
}