{
  "type": "Feature",
  "properties": {
    "addr:full":"816 Gibbons Ct Elizabeth NJ 07202",
    "addr:housenumber":"816",
    "addr:postcode":"07202",
    "addr:street":"Gibbons Ct",
    "iso:country":"US",
    "sg:address":"816 Gibbons Ct",
    "sg:city":"Elizabeth",
    "sg:classifiers":[
        {
            "category":"Building & Trades",
            "subcategory":"Locksmith",
            "type":"Services"
        }
    ],
    "sg:phone":"+1 888 291 8505",
    "sg:postcode":"07202",
    "sg:province":"NJ",
    "sg:tags":[
        "key"
    ],
    "wof:name":"Emergency 24 Hour 7 Day Locksmith",
    "wof:placetype":"venue"
},
  "geometry": {"coordinates":[-74.21852800000001,40.65165],"type":"Point"}
}