{
  "type": "Feature",
  "properties": {
    "addr:full":"64 Casilda Dr Freehold NJ 07728",
    "addr:housenumber":"64",
    "addr:postcode":"07728",
    "addr:street":"Casilda Dr",
    "iso:country":"US",
    "sg:address":"64 Casilda Dr",
    "sg:city":"Freehold",
    "sg:classifiers":[
        {
            "category":"Retail",
            "subcategory":"Repair Shop",
            "type":"Services"
        }
    ],
    "sg:phone":"+1   ",
    "sg:postcode":"07728",
    "sg:province":"NJ",
    "sg:tags":[
        "musical"
    ],
    "wof:name":"Musicians Repair Services",
    "wof:placetype":"venue"
},
  "geometry": {"coordinates":[-74.263757,40.277704],"type":"Point"}
}