{
  "type": "Feature",
  "properties": {
    "addr:full":"127 W Oak St Basking Ridge NJ 07920",
    "addr:housenumber":"127",
    "addr:postcode":"07920",
    "addr:street":"W Oak St",
    "iso:country":"US",
    "sg:address":"127 W Oak St",
    "sg:city":"Basking Ridge",
    "sg:classifiers":[
        {
            "category":"Organizations",
            "subcategory":"Religious Organization",
            "type":"Services"
        }
    ],
    "sg:phone":"+1 908 766 6174",
    "sg:postcode":"07920",
    "sg:province":"NJ",
    "sg:tags":[
        "church"
    ],
    "sg:website":"www.covenantchapel.org",
    "wof:name":"Covenant Chapel-Reformed",
    "wof:placetype":"venue"
},
  "geometry": {"coordinates":[-74.56063,40.705707],"type":"Point"}
}