{
  "type": "Feature",
  "properties": {
    "addr:full":"411 Quackenbush Pl Ridgewood NJ 07450",
    "addr:housenumber":"411",
    "addr:postcode":"07450",
    "addr:street":"Quackenbush Pl",
    "iso:country":"US",
    "sg:address":"411 Quackenbush Pl",
    "sg:city":"Ridgewood",
    "sg:classifiers":[
        {
            "category":"Professional",
            "subcategory":"Computer Services",
            "type":"Services"
        }
    ],
    "sg:phone":"+1 201 670 6959",
    "sg:postcode":"07450",
    "sg:province":"NJ",
    "sg:tags":[
        "related"
    ],
    "wof:name":"Ergo Professionals Inc",
    "wof:placetype":"venue"
},
  "geometry": {"coordinates":[-74.086084,40.984735],"type":"Point"}
}