{
  "type": "Feature",
  "properties": {
    "iso:country":"US",
    "sg:address":"10 Buckingham Dr",
    "sg:city":"Princeton",
    "sg:classifiers":[
        {
            "category":"Banks & Credit Unions",
            "subcategory":"Financial Services",
            "type":"Services"
        }
    ],
    "sg:phone":"+1   ",
    "sg:postcode":"08540",
    "sg:province":"NJ",
    "sg:tags":[
        "company",
        "holding"
    ],
    "wof:name":"Gennari Holdings LLC",
    "wof:placetype":"venue"
},
  "geometry": {"coordinates":[-74.69612600000001,40.317569],"type":"Point"}
}