{
  "type": "Feature",
  "properties": {
    "addr:full":"6311 Broadway West New York NJ 07093",
    "addr:housenumber":"6311",
    "addr:postcode":"07093",
    "addr:street":"Broadway West",
    "iso:country":"US",
    "sg:address":"6311 Broadway",
    "sg:city":"West New York",
    "sg:classifiers":[
        {
            "category":"Personal",
            "subcategory":"Beauty Salon",
            "type":"Services"
        }
    ],
    "sg:phone":"+1   ",
    "sg:postcode":"07093",
    "sg:province":"NJ",
    "sg:tags":[
        "shop"
    ],
    "wof:name":"Tropical Hair Salon",
    "wof:placetype":"venue"
},
  "geometry": {"coordinates":[-74.008343,40.789862],"type":"Point"}
}