{
  "type": "Feature",
  "properties": {
    "addr:full":"160 S Prospect Ave Hackensack NJ 07601",
    "addr:housenumber":"160",
    "addr:postcode":"07601",
    "addr:street":"S Prospect Ave",
    "iso:country":"US",
    "sg:address":"160 S Prospect Ave",
    "sg:city":"Hackensack",
    "sg:classifiers":[
        {
            "category":"Building & Trades",
            "subcategory":"Construction",
            "type":"Services"
        }
    ],
    "sg:phone":"+1 201 488 6161",
    "sg:postcode":"07601",
    "sg:province":"NJ",
    "sg:tags":[
        "contractor"
    ],
    "wof:name":"Cage Construction Corp",
    "wof:placetype":"venue"
},
  "geometry": {"coordinates":[-74.062299,40.87931],"type":"Point"}
}