{
  "type": "Feature",
  "properties": {
    "iso:country":"US",
    "sg:address":"22 Chambord Ln",
    "sg:city":"Voorhees",
    "sg:classifiers":[
        {
            "category":"Professional",
            "subcategory":"Computer Services",
            "type":"Services"
        }
    ],
    "sg:phone":"+1   ",
    "sg:postcode":"08043",
    "sg:province":"NJ",
    "sg:tags":[
        "related"
    ],
    "wof:name":"Chambord Tech Inc",
    "wof:placetype":"venue"
},
  "geometry": {"coordinates":[-74.94139199999999,39.862133],"type":"Point"}
}