{
  "type": "Feature",
  "properties": {
    "iso:country":"US",
    "sg:address":"959 E Front St",
    "sg:city":"Plainfield",
    "sg:classifiers":[
        {
            "category":"Utilities",
            "subcategory":"Mobile Phone",
            "type":"Services"
        }
    ],
    "sg:phone":"+1 908 769 7101",
    "sg:postcode":"07062",
    "sg:province":"NJ",
    "sg:tags":[
        "telephone",
        "cellular"
    ],
    "wof:name":"Bravo Team Comm Group",
    "wof:placetype":"venue"
},
  "geometry": {"coordinates":[-74.412103,40.634219],"type":"Point"}
}