{
  "type": "Feature",
  "properties": {
    "iso:country":"US",
    "sg:address":"474 Chester Pl",
    "sg:city":"Roselle",
    "sg:classifiers":[
        {
            "category":"Bus Charters",
            "type":"Transportation"
        }
    ],
    "sg:phone":"+1 908 241 4990",
    "sg:postcode":"07203",
    "sg:province":"NJ",
    "wof:name":"Horizon Tours Inc",
    "wof:placetype":"venue"
},
  "geometry": {"coordinates":[-74.274067,40.656641],"type":"Point"}
}