{
  "type": "Feature",
  "properties": {
    "addr:full":"10 Broad St Keyport NJ 07735",
    "addr:housenumber":"10",
    "addr:postcode":"07735",
    "addr:street":"Broad St",
    "iso:country":"US",
    "sg:address":"10 Broad St",
    "sg:city":"Keyport",
    "sg:classifiers":[
        {
            "category":"Home & Garden",
            "subcategory":"Household Appliances",
            "type":"Retail Goods"
        },
        {
            "category":"Retail",
            "subcategory":"Repair Shop",
            "type":"Services"
        }
    ],
    "sg:phone":"+1 732 888 1110",
    "sg:postcode":"07735",
    "sg:province":"NJ",
    "wof:name":"Bay Shore Appliance",
    "wof:placetype":"venue"
},
  "geometry": {"coordinates":[-74.202434,40.438684],"type":"Point"}
}