{
  "type": "Feature",
  "properties": {
    "iso:country":"US",
    "sg:address":"1 Faith Dr",
    "sg:city":"Asbury Park",
    "sg:classifiers":[
        {
            "category":"Professional",
            "subcategory":"Computer Services",
            "type":"Services"
        }
    ],
    "sg:phone":"+1   ",
    "sg:postcode":"07712",
    "sg:province":"NJ",
    "sg:tags":[
        "programming",
        "custom"
    ],
    "wof:name":"Anchcomm Inc",
    "wof:placetype":"venue"
},
  "geometry": {"coordinates":[-74.04873499999999,40.243119],"type":"Point"}
}