{
  "type": "Feature",
  "properties": {
    "addr:full":"650 Black River Rd Far Hills NJ 07931",
    "addr:housenumber":"650",
    "addr:postcode":"07931",
    "addr:street":"Black River Rd",
    "iso:country":"US",
    "sg:address":"650 Black River Rd",
    "sg:city":"Far Hills",
    "sg:classifiers":[
        {
            "category":"Professional",
            "type":"Services"
        }
    ],
    "sg:phone":"+1 908 439 3483",
    "sg:postcode":"07931",
    "sg:province":"NJ",
    "sg:tags":[
        "establishment"
    ],
    "wof:name":"Mill House Assoc",
    "wof:placetype":"venue"
},
  "geometry": {"coordinates":[-74.721333,40.668769],"type":"Point"}
}