{
  "type": "Feature",
  "properties": {
    "addr:full":"55 E Broad St Hopewell NJ 08525",
    "addr:housenumber":"55",
    "addr:postcode":"08525",
    "addr:street":"E Broad St",
    "iso:country":"US",
    "sg:address":"55 E Broad St",
    "sg:city":"Hopewell",
    "sg:classifiers":[
        {
            "category":"Building & Trades",
            "subcategory":"Electrical",
            "type":"Services"
        }
    ],
    "sg:phone":"+1 609 466 0124",
    "sg:postcode":"08525",
    "sg:province":"NJ",
    "sg:tags":[
        "electrical",
        "electric",
        "contractor"
    ],
    "wof:name":"Williamson Electrical Service",
    "wof:placetype":"venue"
},
  "geometry": {"coordinates":[-74.75659,40.390548],"type":"Point"}
}