{
  "type": "Feature",
  "properties": {
    "addr:full":"73 W Main St Rockaway NJ 07866",
    "addr:housenumber":"73",
    "addr:postcode":"07866",
    "addr:street":"W Main St",
    "iso:country":"US",
    "sg:address":"73 W Main St",
    "sg:city":"Rockaway",
    "sg:classifiers":[
        {
            "category":"Food & Beverages",
            "subcategory":"Liquor & Beverages",
            "type":"Retail Goods"
        }
    ],
    "sg:phone":"+1 973 627 1890",
    "sg:postcode":"07866",
    "sg:province":"NJ",
    "wof:name":"Rockaway Wine & Liquor",
    "wof:placetype":"venue"
},
  "geometry": {"coordinates":[-74.515349,40.900901],"type":"Point"}
}