{
  "type": "Feature",
  "properties": {
    "iso:country":"US",
    "sg:address":"28 Evergreen Rd",
    "sg:city":"Woodbine",
    "sg:classifiers":[
        {
            "category":"Manufacturing",
            "subcategory":"Signs",
            "type":"Manufacturing & Wholesale Goods"
        }
    ],
    "sg:phone":"+1 609 861 7071",
    "sg:postcode":"08270",
    "sg:province":"NJ",
    "sg:tags":[
        "specialty",
        "mfg"
    ],
    "wof:name":"Sign Design By Lorraine",
    "wof:placetype":"venue"
},
  "geometry": {"coordinates":[-74.86366700000001,39.26307],"type":"Point"}
}