{
  "type": "Feature",
  "properties": {
    "iso:country":"US",
    "sg:address":"401 S Route 73",
    "sg:city":"Berlin",
    "sg:classifiers":[
        {
            "category":"Personal",
            "type":"Services"
        },
        {
            "category":"Retail",
            "subcategory":"Auto Repair",
            "type":"Services"
        }
    ],
    "sg:phone":"+1 856 767 6300",
    "sg:postcode":"08009",
    "sg:province":"NJ",
    "sg:tags":[
        "body",
        "shop",
        "towing"
    ],
    "wof:name":"Seventy Three Auto Body Shop",
    "wof:placetype":"venue"
},
  "geometry": {"coordinates":[-74.92150100000001,39.794601],"type":"Point"}
}