{
  "type": "Feature",
  "properties": {
    "iso:country":"US",
    "sg:address":"112 River Rd",
    "sg:city":"Clifton",
    "sg:classifiers":[
        {
            "category":"Personal",
            "subcategory":"Beauty Salon",
            "type":"Services"
        }
    ],
    "sg:phone":"+1 201 791 8484",
    "sg:postcode":"07014",
    "sg:province":"NJ",
    "sg:tags":[
        "shop"
    ],
    "wof:name":"Young Nails",
    "wof:placetype":"venue"
},
  "geometry": {"coordinates":[-74.132526,40.826349],"type":"Point"}
}