{
  "type": "Feature",
  "properties": {
    "iso:country":"US",
    "sg:address":"1815 B St",
    "sg:city":"Belmar",
    "sg:classifiers":[
        {
            "category":"Taxi",
            "type":"Transportation"
        }
    ],
    "sg:phone":"+1 732 556 0556",
    "sg:postcode":"07719",
    "sg:province":"NJ",
    "sg:tags":[
        "taxicab"
    ],
    "wof:name":"Citi South",
    "wof:placetype":"venue"
},
  "geometry": {"coordinates":[-74.020585,40.170215],"type":"Point"}
}