{
  "type": "Feature",
  "properties": {
    "iso:country":"US",
    "sg:address":"1011 Cooper St",
    "sg:city":"Woodbury",
    "sg:classifiers":[
        {
            "category":"Government",
            "subcategory":"Police Station",
            "type":"Public Place"
        }
    ],
    "sg:phone":"+1 856 845 6300",
    "sg:postcode":"08096",
    "sg:province":"NJ",
    "sg:tags":[
        "department"
    ],
    "wof:name":"Police Dept-Detective Bureau",
    "wof:placetype":"venue"
},
  "geometry": {"coordinates":[-75.124146,39.82824],"type":"Point"}
}