{
  "type": "Feature",
  "properties": {
    "iso:country":"US",
    "sg:address":"2049 Brookewood Dr",
    "sg:city":"Toms River",
    "sg:classifiers":[
        {
            "category":"Professional",
            "subcategory":"Business Services",
            "type":"Services"
        }
    ],
    "sg:phone":"+1   ",
    "sg:postcode":"08755",
    "sg:province":"NJ",
    "wof:name":"Entire Time Solutions LLC",
    "wof:placetype":"venue"
},
  "geometry": {"coordinates":[-74.243622,40.026754],"type":"Point"}
}