{
  "type": "Feature",
  "properties": {
    "iso:country":"US",
    "sg:address":"258 Wall St",
    "sg:city":"Princeton",
    "sg:classifiers":[
        {
            "category":"Organizations",
            "subcategory":"Religious Organization",
            "type":"Services"
        }
    ],
    "sg:phone":"+1 609 921 7866",
    "sg:postcode":"08540",
    "sg:province":"NJ",
    "wof:name":"Consultation On Church Union",
    "wof:placetype":"venue"
},
  "geometry": {"coordinates":[-74.650952,40.396717],"type":"Point"}
}