{
  "type": "Feature",
  "properties": {
    "iso:country":"US",
    "sg:address":"5 Garnet Ln",
    "sg:city":"Princeton Junction",
    "sg:classifiers":[
        {
            "category":"Professional",
            "subcategory":"Computer Services",
            "type":"Services"
        }
    ],
    "sg:phone":"+1   ",
    "sg:postcode":"08550",
    "sg:province":"NJ",
    "sg:tags":[
        "consulting"
    ],
    "wof:name":"T K Computer Consulting Inc",
    "wof:placetype":"venue"
},
  "geometry": {"coordinates":[-74.63537700000001,40.281857],"type":"Point"}
}