{
  "type": "Feature",
  "properties": {
    "addr:full":"2200 Genesee St Trenton NJ 08610",
    "addr:housenumber":"2200",
    "addr:postcode":"08610",
    "addr:street":"Genesee St",
    "iso:country":"US",
    "sg:address":"2200 Genesee St",
    "sg:city":"Trenton",
    "sg:classifiers":[
        {
            "category":"Place Of Worship",
            "subcategory":"Church",
            "type":"Public Place"
        },
        {
            "category":"Place Of Worship",
            "type":"Public Place"
        }
    ],
    "sg:phone":"+1 609 888 3039",
    "sg:postcode":"08610",
    "sg:province":"NJ",
    "sg:tags":[
        "churches-episcopal-anglican",
        "churches-episcopal"
    ],
    "wof:name":"Saint Matthias Episcopal Church Inc",
    "wof:placetype":"venue"
},
  "geometry": {"coordinates":[-74.723862,40.196999],"type":"Point"}
}