{
  "type": "Feature",
  "properties": {
    "addr:full":"675 Pompton Ave Cedar Grove NJ 07009",
    "addr:housenumber":"675",
    "addr:postcode":"07009",
    "addr:street":"Pompton Ave",
    "iso:country":"US",
    "sg:address":"675 Pompton Ave",
    "sg:city":"Cedar Grove",
    "sg:classifiers":[
        {
            "category":"Building & Trades",
            "subcategory":"Locksmith",
            "type":"Services"
        }
    ],
    "sg:phone":"+1 877 867 0933",
    "sg:postcode":"07009",
    "sg:province":"NJ",
    "sg:tags":[
        "key"
    ],
    "wof:name":"A 1 Emergency Locksmith",
    "wof:placetype":"venue"
},
  "geometry": {"coordinates":[-74.230114,40.85618],"type":"Point"}
}