{
  "type": "Feature",
  "properties": {
    "addr:full":"612 Atlantic Ave Ocean City NJ 08226",
    "addr:housenumber":"612",
    "addr:postcode":"08226",
    "addr:street":"Atlantic Ave",
    "iso:country":"US",
    "sg:address":"612 Atlantic Ave",
    "sg:city":"Ocean City",
    "sg:classifiers":[
        {
            "category":"Professional",
            "type":"Services"
        }
    ],
    "sg:phone":"+1 609 398 6362",
    "sg:postcode":"08226",
    "sg:province":"NJ",
    "sg:tags":[
        "establishment"
    ],
    "wof:name":"Jmj Partners LLC",
    "wof:placetype":"venue"
},
  "geometry": {"coordinates":[-74.56975799999999,39.27912],"type":"Point"}
}