{
  "type": "Feature",
  "properties": {
    "addr:full":"420 N Huntington Ave Margate City NJ 08402",
    "addr:housenumber":"420",
    "addr:postcode":"08402",
    "addr:street":"N Huntington Ave Margate",
    "iso:country":"US",
    "sg:address":"420 N Huntington Ave",
    "sg:city":"Margate City",
    "sg:classifiers":[
        {
            "category":"Professional",
            "type":"Services"
        }
    ],
    "sg:phone":"+1   ",
    "sg:postcode":"08402",
    "sg:province":"NJ",
    "wof:name":"I-Shen Yang Pres",
    "wof:placetype":"venue"
},
  "geometry": {"coordinates":[-74.508292,39.336411],"type":"Point"}
}