{
  "type": "Feature",
  "properties": {
    "addr:full":"700 Belleville Tpke Kearny NJ 07032",
    "addr:housenumber":"700",
    "addr:postcode":"07032",
    "addr:street":"Belleville Tpke",
    "iso:country":"US",
    "sg:address":"700 Belleville Tpke",
    "sg:city":"Kearny",
    "sg:classifiers":[
        {
            "category":"Freight",
            "type":"Transportation"
        }
    ],
    "sg:phone":"+1 201 997 4400",
    "sg:postcode":"07032",
    "sg:province":"NJ",
    "sg:tags":[
        "local",
        "trucking",
        "storage",
        "general"
    ],
    "wof:name":"American Terminals Dist",
    "wof:placetype":"venue"
},
  "geometry": {"coordinates":[-74.12056800000001,40.764891],"type":"Point"}
}