{
  "type": "Feature",
  "properties": {
    "iso:country":"US",
    "sg:address":"59 Anderson Ave",
    "sg:city":"Fairview",
    "sg:classifiers":[
        {
            "category":"Professional",
            "subcategory":"Detective & Security Services",
            "type":"Services"
        }
    ],
    "sg:phone":"+1   ",
    "sg:postcode":"07022",
    "sg:province":"NJ",
    "sg:tags":[
        "car",
        "executive"
    ],
    "wof:name":"Fairview Detective Bureau",
    "wof:placetype":"venue"
},
  "geometry": {"coordinates":[-74.000203,40.811108],"type":"Point"}
}