{
  "type": "Feature",
  "properties": {
    "iso:country":"US",
    "sg:address":"501 Lenox Ave",
    "sg:city":"Westfield",
    "sg:classifiers":[
        {
            "category":"Health Services",
            "subcategory":"Doctor",
            "type":"Services"
        }
    ],
    "sg:phone":"+1 908 233 7558",
    "sg:postcode":"07090",
    "sg:province":"NJ",
    "sg:tags":[
        "medical"
    ],
    "wof:name":"Psychiatric Services N J PC",
    "wof:placetype":"venue"
},
  "geometry": {"coordinates":[-74.34132700000001,40.655051],"type":"Point"}
}