{
  "type": "Feature",
  "properties": {
    "iso:country":"US",
    "sg:address":"163 Park Ave",
    "sg:city":"Paterson",
    "sg:classifiers":[
        {
            "category":"Home & Garden",
            "subcategory":"Carpets & Floor Coverings",
            "type":"Retail Goods"
        }
    ],
    "sg:phone":"+1   ",
    "sg:postcode":"07501",
    "sg:province":"NJ",
    "wof:name":"Caribe Floors & Tiles Inc",
    "wof:placetype":"venue"
},
  "geometry": {"coordinates":[-74.161323,40.915356],"type":"Point"}
}