{
  "type": "Feature",
  "properties": {
    "addr:full":"27 West St Red Bank NJ 07701",
    "addr:housenumber":"27",
    "addr:postcode":"07701",
    "addr:street":"West St",
    "iso:country":"US",
    "sg:address":"27 West St",
    "sg:city":"Red Bank",
    "sg:classifiers":[
        {
            "category":"Insurance",
            "subcategory":"Insurance Agent",
            "type":"Services"
        }
    ],
    "sg:phone":"+1 732 450 1735",
    "sg:postcode":"07701",
    "sg:province":"NJ",
    "wof:name":"Prudential Insurance Co",
    "wof:placetype":"venue"
},
  "geometry": {"coordinates":[-74.07305100000001,40.349065],"type":"Point"}
}