{
  "type": "Feature",
  "properties": {
    "addr:full":"120 Mountain Blvd Exd Warren NJ 07059",
    "addr:housenumber":"120",
    "addr:postcode":"07059",
    "addr:street":"Mountain Blvd Exd",
    "iso:country":"US",
    "sg:address":"120 Mountain Blvd Exd",
    "sg:city":"Warren",
    "sg:classifiers":[
        {
            "category":"Retail",
            "subcategory":"Laundry & Dry Cleaning",
            "type":"Services"
        }
    ],
    "sg:phone":"+1 732 356 0066",
    "sg:postcode":"07059",
    "sg:province":"NJ",
    "sg:tags":[
        "cleaners"
    ],
    "wof:name":"Pheasant Run Dry Cleaners",
    "wof:placetype":"venue"
},
  "geometry": {"coordinates":[-74.49551099999999,40.617714],"type":"Point"}
}