{
  "type": "Feature",
  "properties": {
    "addr:full":"49 Oxford St Paterson NJ 07522",
    "addr:housenumber":"49",
    "addr:postcode":"07522",
    "addr:street":"Oxford St",
    "iso:country":"US",
    "sg:address":"49 Oxford St",
    "sg:city":"Paterson",
    "sg:classifiers":[
        {
            "category":"Retail",
            "subcategory":"Auto Repair",
            "type":"Services"
        }
    ],
    "sg:phone":"+1 973 942 4001",
    "sg:postcode":"07522",
    "sg:province":"NJ",
    "sg:tags":[
        "body",
        "shop"
    ],
    "wof:name":"Berrios Carlos Auto Body Shop",
    "wof:placetype":"venue"
},
  "geometry": {"coordinates":[-74.17910000000001,40.923901],"type":"Point"}
}