{
  "type": "Feature",
  "properties": {
    "iso:country":"US",
    "sg:address":"147 Franklin St",
    "sg:city":"Bloomfield",
    "sg:classifiers":[
        {
            "category":"Building & Trades",
            "subcategory":"Plumbing",
            "type":"Services"
        }
    ],
    "sg:phone":"+1 973 731 1711",
    "sg:postcode":"07003",
    "sg:province":"NJ",
    "sg:tags":[
        "mechanical",
        "contractor"
    ],
    "wof:name":"Affordable Mechanical Svc",
    "wof:placetype":"venue"
},
  "geometry": {"coordinates":[-74.18862900000001,40.787485],"type":"Point"}
}