{
  "type": "Feature",
  "properties": {
    "addr:full":"71 Mercer St Trenton NJ 08690",
    "addr:housenumber":"71",
    "addr:postcode":"08690",
    "addr:street":"Mercer St",
    "iso:country":"US",
    "sg:address":"71 Mercer St",
    "sg:city":"Trenton",
    "sg:classifiers":[
        {
            "category":"Building & Trades",
            "subcategory":"Construction",
            "type":"Services"
        }
    ],
    "sg:phone":"+1 609 584 0020",
    "sg:postcode":"08690",
    "sg:province":"NJ",
    "sg:tags":[
        "general",
        "contractor"
    ],
    "wof:name":"JAS Enterprises",
    "wof:placetype":"venue"
},
  "geometry": {"coordinates":[-74.65862,40.232816],"type":"Point"}
}