{
  "type": "Feature",
  "properties": {
    "iso:country":"US",
    "sg:address":"384 Monroe St",
    "sg:city":"Passaic",
    "sg:classifiers":[
        {
            "category":"Restaurant",
            "type":"Food & Drink"
        }
    ],
    "sg:phone":"+1   ",
    "sg:postcode":"07055",
    "sg:province":"NJ",
    "sg:tags":[
        "eating"
    ],
    "wof:name":"Villas Restaurant",
    "wof:placetype":"venue"
},
  "geometry": {"coordinates":[-74.131953,40.863289],"type":"Point"}
}