{
  "type": "Feature",
  "properties": {
    "iso:country":"US",
    "sg:address":"200 Black Brook Rd",
    "sg:city":"Hampton",
    "sg:classifiers":[
        {
            "category":"Retail",
            "subcategory":"Repair Shop",
            "type":"Services"
        }
    ],
    "sg:phone":"+1   ",
    "sg:postcode":"08827",
    "sg:province":"NJ",
    "wof:name":"History In Making",
    "wof:placetype":"venue"
},
  "geometry": {"coordinates":[-74.95794600000001,40.698073],"type":"Point"}
}