{
  "type": "Feature",
  "properties": {
    "iso:country":"US",
    "sg:address":"739 Henderson Rd",
    "sg:city":"Lumberton",
    "sg:classifiers":[
        {
            "category":"Restaurant",
            "type":"Food & Drink"
        }
    ],
    "sg:phone":"+1   ",
    "sg:postcode":"08048",
    "sg:province":"NJ",
    "sg:tags":[
        "eating"
    ],
    "wof:name":"Clam Inc",
    "wof:placetype":"venue"
},
  "geometry": {"coordinates":[-74.79071999999999,39.971337],"type":"Point"}
}