{
  "type": "Feature",
  "properties": {
    "iso:country":"US",
    "sg:address":"1715 US Hwy 46",
    "sg:city":"Ledgewood",
    "sg:classifiers":[
        {
            "category":"Government",
            "subcategory":"Police Station",
            "type":"Public Place"
        }
    ],
    "sg:phone":"+1 973 448 2038",
    "sg:postcode":"07852",
    "sg:province":"NJ",
    "sg:tags":[
        "department"
    ],
    "wof:name":"Police Records",
    "wof:placetype":"venue"
},
  "geometry": {"coordinates":[-74.672073,40.890259],"type":"Point"}
}