{
  "type": "Feature",
  "properties": {
    "addr:full":"66 W Stewart St Washington NJ 07882",
    "addr:housenumber":"66",
    "addr:postcode":"07882",
    "addr:street":"W Stewart St",
    "iso:country":"US",
    "sg:address":"66 W Stewart St",
    "sg:city":"Washington",
    "sg:classifiers":[
        {
            "category":"Freight",
            "type":"Transportation"
        }
    ],
    "sg:phone":"+1 908 689 8312",
    "sg:postcode":"07882",
    "sg:province":"NJ",
    "sg:tags":[
        "trucking"
    ],
    "wof:name":"Foxee Enterprises",
    "wof:placetype":"venue"
},
  "geometry": {"coordinates":[-74.983705,40.759958],"type":"Point"}
}