{
  "type": "Feature",
  "properties": {
    "addr:full":"375 Drum Point Rd Brick NJ 08723",
    "addr:housenumber":"375",
    "addr:postcode":"08723",
    "addr:street":"Drum Point Rd",
    "iso:country":"US",
    "sg:address":"375 Drum Point Rd",
    "sg:city":"Brick",
    "sg:classifiers":[
        {
            "category":"Restaurant",
            "type":"Food & Drink"
        }
    ],
    "sg:phone":"+1 732 920 6200",
    "sg:postcode":"08723",
    "sg:province":"NJ",
    "wof:name":"LA Fontana Restaurant",
    "wof:placetype":"venue"
},
  "geometry": {"coordinates":[-74.108402,40.038653],"type":"Point"}
}