{
  "type": "Feature",
  "properties": {
    "addr:full":"10 Norma Ave Fair Lawn NJ 07410",
    "addr:housenumber":"10",
    "addr:postcode":"07410",
    "addr:street":"Norma Ave",
    "iso:country":"US",
    "sg:address":"10 Norma Ave",
    "sg:city":"Fair Lawn",
    "sg:classifiers":[
        {
            "category":"Banks & Credit Unions",
            "subcategory":"Bank",
            "type":"Services"
        }
    ],
    "sg:phone":"+1 201 791 8395",
    "sg:postcode":"07410",
    "sg:province":"NJ",
    "sg:tags":[
        "loan"
    ],
    "wof:name":"Paterson Hebrew Free Loan Assn",
    "wof:placetype":"venue"
},
  "geometry": {"coordinates":[-74.127546,40.93058],"type":"Point"}
}