{
  "type": "Feature",
  "properties": {
    "addr:full":"9 Bradley Rd Morristown NJ 07960",
    "addr:housenumber":"9",
    "addr:postcode":"07960",
    "addr:street":"Bradley Rd",
    "iso:country":"US",
    "sg:address":"9 Bradley Rd",
    "sg:city":"Morristown",
    "sg:classifiers":[
        {
            "category":"Professional",
            "subcategory":"Management & Consulting",
            "type":"Services"
        }
    ],
    "sg:phone":"+1   ",
    "sg:postcode":"07960",
    "sg:province":"NJ",
    "sg:tags":[
        "retail"
    ],
    "wof:name":"Mas Direct",
    "wof:placetype":"venue"
},
  "geometry": {"coordinates":[-74.450506,40.779577],"type":"Point"}
}