{
  "type": "Feature",
  "properties": {
    "addr:full":"271 Overmont Ave West Paterson NJ 07424",
    "addr:housenumber":"271",
    "addr:postcode":"07424",
    "addr:street":"Overmont Ave West",
    "iso:country":"US",
    "sg:address":"271 Overmont Ave",
    "sg:city":"West Paterson",
    "sg:classifiers":[
        {
            "category":"Fast Food",
            "type":"Food & Drink"
        },
        {
            "category":"Food & Beverages",
            "subcategory":"Bakery",
            "type":"Retail Goods"
        }
    ],
    "sg:phone":"+1 973 754 0700",
    "sg:postcode":"07424",
    "sg:province":"NJ",
    "sg:tags":[
        "sandwich"
    ],
    "sg:website":"www.subway.com",
    "wof:name":"Subway",
    "wof:placetype":"venue"
},
  "geometry": {"coordinates":[-74.206356,40.861496],"type":"Point"}
}