{
  "type": "Feature",
  "properties": {
    "addr:full":"530 Main St Fort Lee NJ 07024",
    "addr:housenumber":"530",
    "addr:postcode":"07024",
    "addr:street":"Main St",
    "iso:country":"US",
    "sg:address":"530 Main St",
    "sg:city":"Fort Lee",
    "sg:classifiers":[
        {
            "category":"Marine",
            "type":"Transportation"
        }
    ],
    "sg:phone":"+1 201 947 7775",
    "sg:postcode":"07024",
    "sg:province":"NJ",
    "sg:tags":[
        "overseas",
        "shipping"
    ],
    "wof:name":"Global Express Lines",
    "wof:placetype":"venue"
},
  "geometry": {"coordinates":[-73.97980099999999,40.857171],"type":"Point"}
}