{
  "type": "Feature",
  "properties": {
    "iso:country":"US",
    "sg:address":"758 Garfield Ave",
    "sg:city":"Jersey City",
    "sg:classifiers":[
        {
            "category":"Autos & Motor Vehicles",
            "subcategory":"Automobile Sales",
            "type":"Retail Goods"
        }
    ],
    "sg:phone":"+1 201 432 6407",
    "sg:postcode":"07305",
    "sg:province":"NJ",
    "sg:tags":[
        "car",
        "dealer"
    ],
    "wof:name":"Liberty Park Auto Sales",
    "wof:placetype":"venue"
},
  "geometry": {"coordinates":[-74.07395699999999,40.705461],"type":"Point"}
}