{
  "type": "Feature",
  "properties": {
    "iso:country":"US",
    "sg:address":"350 Mack Pl",
    "sg:city":"Woodbridge",
    "sg:classifiers":[
        {
            "category":"Travel",
            "subcategory":"Hotels & Motels",
            "type":"Entertainment"
        }
    ],
    "sg:phone":"+1 732 661 9171",
    "sg:postcode":"07080",
    "sg:province":"NJ",
    "sg:tags":[
        "operation"
    ],
    "wof:name":"Exel Direct Inc",
    "wof:placetype":"venue"
},
  "geometry": {"coordinates":[-74.411974,40.561415],"type":"Point"}
}