{
  "type": "Feature",
  "properties": {
    "addr:full":"5 Executive Ct Cherry Hill NJ 08046",
    "addr:housenumber":"5",
    "addr:postcode":"08046",
    "addr:street":"Executive Ct",
    "iso:country":"US",
    "sg:address":"5 Executive Ct",
    "sg:city":"Cherry Hill",
    "sg:classifiers":[
        {
            "category":"Professional",
            "subcategory":"Lawyer & Legal Services",
            "type":"Services"
        }
    ],
    "sg:phone":"+1 856 317 2201",
    "sg:postcode":"08046",
    "sg:province":"NJ",
    "sg:tags":[
        "attorney"
    ],
    "wof:name":"Freedman & Lorry PC",
    "wof:placetype":"venue"
},
  "geometry": {"coordinates":[-74.864521,40.018448],"type":"Point"}
}