{
  "type": "Feature",
  "properties": {
    "iso:country":"US",
    "sg:address":"83 Aberdeen Dr",
    "sg:city":"Sicklerville",
    "sg:classifiers":[
        {
            "category":"Autos & Motor Vehicles",
            "subcategory":"Auto Supplies",
            "type":"Retail Goods"
        }
    ],
    "sg:phone":"+1   ",
    "sg:postcode":"08081",
    "sg:province":"NJ",
    "wof:name":"New World Performance LLC",
    "wof:placetype":"venue"
},
  "geometry": {"coordinates":[-74.996617,39.755593],"type":"Point"}
}