{
  "type": "Feature",
  "properties": {
    "iso:country":"US",
    "sg:address":"36 Bunting Bridge Rd",
    "sg:city":"Cookstown",
    "sg:classifiers":[
        {
            "category":"Building & Trades",
            "subcategory":"Construction",
            "type":"Services"
        }
    ],
    "sg:phone":"+1 609 758 3489",
    "sg:postcode":"08511",
    "sg:province":"NJ",
    "sg:tags":[
        "masonry",
        "contractor"
    ],
    "wof:name":"Shel-Don Masonry Contractors",
    "wof:placetype":"venue"
},
  "geometry": {"coordinates":[-74.54258,40.046335],"type":"Point"}
}