{
  "type": "Feature",
  "properties": {
    "iso:country":"US",
    "sg:address":"42 Desai Ct",
    "sg:city":"Freehold",
    "sg:classifiers":[
        {
            "category":"Autos & Motor Vehicles",
            "subcategory":"Automobile Sales",
            "type":"Retail Goods"
        }
    ],
    "sg:phone":"+1 732 462 2965",
    "sg:postcode":"07728",
    "sg:province":"NJ",
    "sg:tags":[
        "new",
        "car"
    ],
    "wof:name":"Louisaire Corp",
    "wof:placetype":"venue"
},
  "geometry": {"coordinates":[-74.22213000000001,40.240084],"type":"Point"}
}