{
  "type": "Feature",
  "properties": {
    "addr:full":"1020 Atlantic Ave Atlantic City NJ 08401",
    "addr:housenumber":"1020",
    "addr:postcode":"08401",
    "addr:street":"Atlantic Ave",
    "iso:country":"US",
    "sg:address":"1020 Atlantic Ave",
    "sg:city":"Atlantic City",
    "sg:classifiers":[
        {
            "category":"Real Estate",
            "subcategory":"Surveying",
            "type":"Services"
        }
    ],
    "sg:phone":"+1 609 345 1887",
    "sg:postcode":"08401",
    "sg:province":"NJ",
    "sg:tags":[
        "engineering"
    ],
    "wof:name":"Catalano Robert J & Assoc",
    "wof:placetype":"venue"
},
  "geometry": {"coordinates":[-74.42422000000001,39.363587],"type":"Point"}
}