{
  "type": "Feature",
  "properties": {
    "addr:full":"301 US Hwy 22 Green Brook NJ 08812",
    "addr:housenumber":"301",
    "addr:postcode":"08812",
    "addr:street":"Us Hwy 22",
    "iso:country":"US",
    "sg:address":"301 US Hwy 22",
    "sg:city":"Green Brook",
    "sg:classifiers":[
        {
            "category":"Education",
            "subcategory":"Dance Studio",
            "type":"Public Place"
        }
    ],
    "sg:phone":"+1 732 968 7600",
    "sg:postcode":"08812",
    "sg:province":"NJ",
    "sg:tags":[
        "instruction",
        "dancing"
    ],
    "wof:name":"Arthur Murray Dance Studio",
    "wof:placetype":"venue"
},
  "geometry": {"coordinates":[-74.501515,40.589784],"type":"Point"}
}