{
  "type": "Feature",
  "properties": {
    "addr:full":"391 Hamilton Ave Paterson NJ 07514",
    "addr:housenumber":"391",
    "addr:postcode":"07514",
    "addr:street":"Hamilton Ave",
    "iso:country":"US",
    "sg:address":"391 Hamilton Ave",
    "sg:city":"Paterson",
    "sg:classifiers":[
        {
            "category":"Wholesale",
            "subcategory":"Auto Parts",
            "type":"Manufacturing & Wholesale Goods"
        }
    ],
    "sg:phone":"+1 973 279 0801",
    "sg:postcode":"07514",
    "sg:province":"NJ",
    "sg:tags":[
        "automobile",
        "retail",
        "tire"
    ],
    "wof:name":"Paterson Tire Co",
    "wof:placetype":"venue"
},
  "geometry": {"coordinates":[-74.154602,40.919899],"type":"Point"}
}