{
  "type": "Feature",
  "properties": {
    "addr:full":"11 Ridge Rd Lyndhurst NJ 07071",
    "addr:housenumber":"11",
    "addr:postcode":"07071",
    "addr:street":"Ridge Rd",
    "iso:country":"US",
    "sg:address":"11 Ridge Rd",
    "sg:city":"Lyndhurst",
    "sg:classifiers":[
        {
            "category":"Food & Beverages",
            "subcategory":"Liquor & Beverages",
            "type":"Retail Goods"
        }
    ],
    "sg:phone":"+1 201 933 8338",
    "sg:postcode":"07071",
    "sg:province":"NJ",
    "sg:tags":[
        "beer",
        "spirit",
        "wine"
    ],
    "wof:name":"Wine Pro",
    "wof:placetype":"venue"
},
  "geometry": {"coordinates":[-74.113585,40.815782],"type":"Point"}
}