{
  "type": "Feature",
  "properties": {
    "iso:country":"US",
    "sg:address":"3515 US Hwy 1",
    "sg:city":"Princeton",
    "sg:classifiers":[
        {
            "category":"Shopping",
            "type":"Retail Goods"
        }
    ],
    "sg:phone":"+1   ",
    "sg:postcode":"08540",
    "sg:province":"NJ",
    "sg:tags":[
        "merchandise"
    ],
    "wof:name":"P C W Communications",
    "wof:placetype":"venue"
},
  "geometry": {"coordinates":[-74.664041,40.310257],"type":"Point"}
}