{
  "type": "Feature",
  "properties": {
    "addr:full":"245 Nassau St Princeton NJ 08540",
    "addr:housenumber":"245",
    "addr:postcode":"08540",
    "addr:street":"Nassau St",
    "iso:country":"US",
    "sg:address":"245 Nassau St",
    "sg:city":"Princeton",
    "sg:classifiers":[
        {
            "category":"Professional",
            "type":"Services"
        }
    ],
    "sg:phone":"+1 609 924 0938",
    "sg:postcode":"08540",
    "sg:province":"NJ",
    "sg:tags":[
        "establishment"
    ],
    "wof:name":"BCM Direct",
    "wof:placetype":"venue"
},
  "geometry": {"coordinates":[-74.651251,40.352115],"type":"Point"}
}