{
  "type": "Feature",
  "properties": {
    "iso:country":"US",
    "sg:address":"108 Remsen Ave",
    "sg:city":"New Brunswick",
    "sg:classifiers":[
        {
            "category":"Food & Beverages",
            "subcategory":"Groceries & Convenience Stores",
            "type":"Retail Goods"
        }
    ],
    "sg:phone":"+1   ",
    "sg:postcode":"08901",
    "sg:province":"NJ",
    "wof:name":"Quisqueya Meat Market",
    "wof:placetype":"venue"
},
  "geometry": {"coordinates":[-74.445712,40.486709],"type":"Point"}
}