{
  "type": "Feature",
  "properties": {
    "addr:full":"18 Chesler Sq Succasunna NJ 07876",
    "addr:housenumber":"18",
    "addr:postcode":"07876",
    "addr:street":"Chesler Sq",
    "iso:country":"US",
    "sg:address":"18 Chesler Sq",
    "sg:city":"Succasunna",
    "sg:classifiers":[
        {
            "category":"Shopping",
            "subcategory":"Computers & Home Electronics",
            "type":"Retail Goods"
        }
    ],
    "sg:phone":"+1   ",
    "sg:postcode":"07876",
    "sg:province":"NJ",
    "wof:name":"Roxsat",
    "wof:placetype":"venue"
},
  "geometry": {"coordinates":[-74.631208,40.869416],"type":"Point"}
}