{
  "type": "Feature",
  "properties": {
    "addr:full":"187 S Washington Ave Bergenfield NJ 07621",
    "addr:housenumber":"187",
    "addr:postcode":"07621",
    "addr:street":"S Washington Ave",
    "iso:country":"US",
    "sg:address":"187 S Washington Ave",
    "sg:city":"Bergenfield",
    "sg:classifiers":[
        {
            "category":"Professional",
            "type":"Services"
        }
    ],
    "sg:phone":"+1 201 387 6685",
    "sg:postcode":"07621",
    "sg:province":"NJ",
    "sg:tags":[
        "establishment"
    ],
    "wof:name":"Position-Aire Inc",
    "wof:placetype":"venue"
},
  "geometry": {"coordinates":[-73.996837,40.922255],"type":"Point"}
}