{
  "type": "Feature",
  "properties": {
    "iso:country":"US",
    "sg:address":"54 Martha Pl",
    "sg:city":"Oakland",
    "sg:classifiers":[
        {
            "category":"Communications",
            "subcategory":"Radio Station",
            "type":"Services"
        },
        {
            "category":"Professional",
            "subcategory":"Business Services",
            "type":"Services"
        }
    ],
    "sg:phone":"+1 201 337 7784",
    "sg:postcode":"07436",
    "sg:province":"NJ",
    "sg:tags":[
        "medium",
        "publicity",
        "broker"
    ],
    "wof:name":"Boogie Store",
    "wof:placetype":"venue"
},
  "geometry": {"coordinates":[-74.255465,41.008114],"type":"Point"}
}