{
  "type": "Feature",
  "properties": {
    "iso:country":"US",
    "sg:address":"250 Mercer St",
    "sg:city":"Princeton",
    "sg:classifiers":[
        {
            "category":"Restaurant",
            "type":"Food & Drink"
        }
    ],
    "sg:phone":"+1   ",
    "sg:postcode":"08540",
    "sg:province":"NJ",
    "sg:tags":[
        "eating"
    ],
    "wof:name":"Chevys Fresh Mex",
    "wof:placetype":"venue"
},
  "geometry": {"coordinates":[-74.671406,40.338144],"type":"Point"}
}