{
  "type": "Feature",
  "properties": {
    "addr:full":"777 Bergen Ave Jersey City NJ 07306",
    "addr:housenumber":"777",
    "addr:postcode":"07306",
    "addr:street":"Bergen Ave",
    "iso:country":"US",
    "sg:address":"777 Bergen Ave",
    "sg:city":"Jersey City",
    "sg:classifiers":[
        {
            "category":"Building & Trades",
            "subcategory":"Construction",
            "type":"Services"
        }
    ],
    "sg:phone":"+1 201 435 1494",
    "sg:postcode":"07306",
    "sg:province":"NJ",
    "sg:tags":[
        "general",
        "contractor"
    ],
    "wof:name":"Neighborhood Construction Co",
    "wof:placetype":"venue"
},
  "geometry": {"coordinates":[-74.06762999999999,40.726094],"type":"Point"}
}