{
  "type": "Feature",
  "properties": {
    "addr:full":"12 Radburn Rd Fair Lawn NJ 07410",
    "addr:housenumber":"12",
    "addr:postcode":"07410",
    "addr:street":"Radburn Rd",
    "iso:country":"US",
    "sg:address":"12 Radburn Rd",
    "sg:city":"Fair Lawn",
    "sg:classifiers":[
        {
            "category":"Professional",
            "type":"Services"
        }
    ],
    "sg:phone":"+1   ",
    "sg:postcode":"07410",
    "sg:province":"NJ",
    "wof:name":"Leana Diker",
    "wof:placetype":"venue"
},
  "geometry": {"coordinates":[-74.12214299999999,40.949943],"type":"Point"}
}