{
  "type": "Feature",
  "properties": {
    "addr:full":"217 Winterberry Ln Hammonton NJ 08037",
    "addr:housenumber":"217",
    "addr:postcode":"08037",
    "addr:street":"Winterberry Ln",
    "iso:country":"US",
    "sg:address":"217 Winterberry Ln",
    "sg:city":"Hammonton",
    "sg:classifiers":[
        {
            "category":"Manufacturing",
            "subcategory":"Printing",
            "type":"Manufacturing & Wholesale Goods"
        }
    ],
    "sg:phone":"+1 856 753 5373",
    "sg:postcode":"08037",
    "sg:province":"NJ",
    "sg:tags":[
        "printer"
    ],
    "wof:name":"Basic Printing",
    "wof:placetype":"venue"
},
  "geometry": {"coordinates":[-74.883178,39.689846],"type":"Point"}
}