{
  "type": "Feature",
  "properties": {
    "iso:country":"US",
    "sg:address":"21 Boud Ave",
    "sg:city":"Farmingdale",
    "sg:classifiers":[
        {
            "category":"Building & Trades",
            "subcategory":"Cleaning & Sanitation",
            "type":"Services"
        }
    ],
    "sg:phone":"+1 732 938 4488",
    "sg:postcode":"07727",
    "sg:province":"NJ",
    "sg:tags":[
        "fireplace",
        "chimney"
    ],
    "wof:name":"Mailbox Market",
    "wof:placetype":"venue"
},
  "geometry": {"coordinates":[-74.166988,40.191165],"type":"Point"}
}