{
  "type": "Feature",
  "properties": {
    "iso:country":"US",
    "sg:address":"740 Broad St",
    "sg:city":"Newark",
    "sg:classifiers":[
        {
            "category":"Professional",
            "type":"Services"
        }
    ],
    "sg:phone":"+1   ",
    "sg:postcode":"07102",
    "sg:province":"NJ",
    "wof:name":"Executive Adj Bureau",
    "wof:placetype":"venue"
},
  "geometry": {"coordinates":[-74.171566,40.736585],"type":"Point"}
}