{
  "type": "Feature",
  "properties": {
    "addr:full":"151 Tappan St Kearny NJ 07032",
    "addr:housenumber":"151",
    "addr:postcode":"07032",
    "addr:street":"Tappan St",
    "iso:country":"US",
    "sg:address":"151 Tappan St",
    "sg:city":"Kearny",
    "sg:classifiers":[
        {
            "category":"Real Estate",
            "subcategory":"Architect",
            "type":"Services"
        }
    ],
    "sg:phone":"+1 201 246 7979",
    "sg:postcode":"07032",
    "sg:province":"NJ",
    "wof:name":"Neves Architects & Assoc",
    "wof:placetype":"venue"
},
  "geometry": {"coordinates":[-74.148118,40.753907],"type":"Point"}
}