{
  "type": "Feature",
  "properties": {
    "addr:full":"75 E Cherry St Rahway NJ 07065",
    "addr:housenumber":"75",
    "addr:postcode":"07065",
    "addr:street":"E Cherry St",
    "iso:country":"US",
    "sg:address":"75 E Cherry St",
    "sg:city":"Rahway",
    "sg:classifiers":[
        {
            "category":"Freight",
            "type":"Transportation"
        }
    ],
    "sg:phone":"+1 732 574 3000",
    "sg:postcode":"07065",
    "sg:province":"NJ",
    "sg:tags":[
        "operator",
        "hauling",
        "trucking"
    ],
    "wof:name":"Diamond Transportation Inc",
    "wof:placetype":"venue"
},
  "geometry": {"coordinates":[-74.274636,40.606912],"type":"Point"}
}