{
  "type": "Feature",
  "properties": {
    "iso:country":"US",
    "sg:address":"20 Cain Ct",
    "sg:city":"Montville",
    "sg:classifiers":[
        {
            "category":"Shopping",
            "subcategory":"Discount & Variety Stores",
            "type":"Retail Goods"
        }
    ],
    "sg:phone":"+1 973 882 4544",
    "sg:postcode":"07045",
    "sg:province":"NJ",
    "sg:tags":[
        "merchandise",
        "general"
    ],
    "wof:name":"Denso Sales California Inc",
    "wof:placetype":"venue"
},
  "geometry": {"coordinates":[-74.369765,40.881635],"type":"Point"}
}