{
  "type": "Feature",
  "properties": {
    "addr:full":"80 Wayne St Wayne NJ 07470",
    "addr:housenumber":"80",
    "addr:postcode":"07470",
    "addr:street":"Wayne St",
    "iso:country":"US",
    "sg:address":"80 Wayne St",
    "sg:city":"Wayne",
    "sg:classifiers":[
        {
            "category":"Shopping",
            "subcategory":"Books",
            "type":"Retail Goods"
        }
    ],
    "sg:phone":"+1   ",
    "sg:postcode":"07470",
    "sg:province":"NJ",
    "wof:name":"Borders",
    "wof:placetype":"venue"
},
  "geometry": {"coordinates":[-74.283627,40.921403],"type":"Point"}
}