{
  "type": "Feature",
  "properties": {
    "addr:full":"16 Garden St Wanaque NJ 07465",
    "addr:housenumber":"16",
    "addr:postcode":"07465",
    "addr:street":"Garden St",
    "iso:country":"US",
    "sg:address":"16 Garden St",
    "sg:city":"Wanaque",
    "sg:classifiers":[
        {
            "category":"Professional",
            "subcategory":"Accounting & Tax Preparation",
            "type":"Services"
        }
    ],
    "sg:phone":"+1 973 831 9117",
    "sg:postcode":"07465",
    "sg:province":"NJ",
    "wof:name":"Allpay Inc",
    "wof:placetype":"venue"
},
  "geometry": {"coordinates":[-74.279601,41.061283],"type":"Point"}
}