{
  "type": "Feature",
  "properties": {
    "addr:full":"44 Whispering Pines Ln Lakewood NJ 08701",
    "addr:housenumber":"44",
    "addr:postcode":"08701",
    "addr:street":"Whispering Pines Ln",
    "iso:country":"US",
    "sg:address":"44 Whispering Pines Ln",
    "sg:city":"Lakewood",
    "sg:classifiers":[
        {
            "category":"Professional",
            "type":"Services"
        }
    ],
    "sg:phone":"+1   ",
    "sg:postcode":"08701",
    "sg:province":"NJ",
    "wof:name":"Mini Belle",
    "wof:placetype":"venue"
},
  "geometry": {"coordinates":[-74.20244599999999,40.108222],"type":"Point"}
}