{
  "type": "Feature",
  "properties": {
    "addr:full":"525 McCarter Hwy Newark NJ 07102",
    "addr:housenumber":"525",
    "addr:postcode":"07102",
    "addr:street":"Mccarter Hwy",
    "iso:country":"US",
    "sg:address":"525 McCarter Hwy",
    "sg:city":"Newark",
    "sg:classifiers":[
        {
            "category":"Autos & Motor Vehicles",
            "subcategory":"Automobile Sales",
            "type":"Retail Goods"
        }
    ],
    "sg:phone":"+1 973 799 0882",
    "sg:postcode":"07102",
    "sg:province":"NJ",
    "sg:tags":[
        "car",
        "dealer"
    ],
    "wof:name":"Prestige Auto Plaza",
    "wof:placetype":"venue"
},
  "geometry": {"coordinates":[-74.174324,40.725032],"type":"Point"}
}