{
  "type": "Feature",
  "properties": {
    "addr:full":"81 Kingsbridge Rd Piscataway NJ 08854",
    "addr:housenumber":"81",
    "addr:postcode":"08854",
    "addr:street":"Kingsbridge Rd",
    "iso:country":"US",
    "sg:address":"81 Kingsbridge Rd",
    "sg:city":"Piscataway",
    "sg:classifiers":[
        {
            "category":"Professional",
            "subcategory":"Business Services",
            "type":"Services"
        },
        {
            "category":"Shopping",
            "subcategory":"Music",
            "type":"Retail Goods"
        }
    ],
    "sg:phone":"+1 732 885 1600",
    "sg:postcode":"08854",
    "sg:province":"NJ",
    "sg:tags":[
        "record",
        "document"
    ],
    "wof:name":"Records Management Servic",
    "wof:placetype":"venue"
},
  "geometry": {"coordinates":[-74.497578,40.545111],"type":"Point"}
}