{
  "type": "Feature",
  "properties": {
    "iso:country":"US",
    "sg:address":"21 Phillips Rd",
    "sg:city":"Newton",
    "sg:classifiers":[
        {
            "category":"Shopping",
            "type":"Retail Goods"
        }
    ],
    "sg:phone":"+1   ",
    "sg:postcode":"07860",
    "sg:province":"NJ",
    "sg:tags":[
        "merchandise"
    ],
    "wof:name":"Good Karma Collectibles",
    "wof:placetype":"venue"
},
  "geometry": {"coordinates":[-74.78126399999999,40.983827],"type":"Point"}
}