{
  "type": "Feature",
  "properties": {
    "addr:full":"6 E Woodcrest Ave Maple Shade NJ 08052",
    "addr:housenumber":"6",
    "addr:postcode":"08052",
    "addr:street":"E Woodcrest Ave",
    "iso:country":"US",
    "sg:address":"6 E Woodcrest Ave",
    "sg:city":"Maple Shade",
    "sg:classifiers":[
        {
            "category":"Building & Trades",
            "subcategory":"Construction",
            "type":"Services"
        }
    ],
    "sg:phone":"+1 856 482 6848",
    "sg:postcode":"08052",
    "sg:province":"NJ",
    "sg:tags":[
        "carpentry",
        "contractor"
    ],
    "wof:name":"First Choice Carpet Service",
    "wof:placetype":"venue"
},
  "geometry": {"coordinates":[-75.01143399999999,39.947627],"type":"Point"}
}