{
  "type": "Feature",
  "properties": {
    "iso:country":"US",
    "sg:address":"124 French St",
    "sg:city":"New Brunswick",
    "sg:classifiers":[
        {
            "category":"Organizations",
            "subcategory":"Religious Organization",
            "type":"Services"
        }
    ],
    "sg:phone":"+1   ",
    "sg:postcode":"08901",
    "sg:province":"NJ",
    "wof:name":"Progressive Church God Christ",
    "wof:placetype":"venue"
},
  "geometry": {"coordinates":[-74.451992,40.493252],"type":"Point"}
}