{
  "type": "Feature",
  "properties": {
    "iso:country":"US",
    "sg:address":"26 Old Milford Ln",
    "sg:city":"West Milford",
    "sg:classifiers":[
        {
            "category":"Wholesale",
            "subcategory":"Machinery & Supplies",
            "type":"Manufacturing & Wholesale Goods"
        }
    ],
    "sg:phone":"+1 973 728 7300",
    "sg:postcode":"07480",
    "sg:province":"NJ",
    "sg:tags":[
        "equipment",
        "welding"
    ],
    "wof:name":"Awisco",
    "wof:placetype":"venue"
},
  "geometry": {"coordinates":[-74.40530699999999,41.101867],"type":"Point"}
}