{
  "type": "Feature",
  "properties": {
    "addr:full":"473 Jersey Ave Jersey City NJ 07302",
    "addr:housenumber":"473",
    "addr:postcode":"07302",
    "addr:street":"Jersey Ave",
    "iso:country":"US",
    "sg:address":"473 Jersey Ave",
    "sg:city":"Jersey City",
    "sg:classifiers":[
        {
            "category":"Professional",
            "subcategory":"Business Services",
            "type":"Services"
        }
    ],
    "sg:phone":"+1   ",
    "sg:postcode":"07302",
    "sg:province":"NJ",
    "wof:name":"DJL Enterprises LLC",
    "wof:placetype":"venue"
},
  "geometry": {"coordinates":[-74.04754699999999,40.719219],"type":"Point"}
}