{
  "type": "Feature",
  "properties": {
    "addr:full":"342 Valley Rd Wayne NJ 07470",
    "addr:housenumber":"342",
    "addr:postcode":"07470",
    "addr:street":"Valley Rd",
    "iso:country":"US",
    "sg:address":"342 Valley Rd",
    "sg:city":"Wayne",
    "sg:classifiers":[
        {
            "category":"Professional",
            "subcategory":"Accounting & Tax Preparation",
            "type":"Services"
        }
    ],
    "sg:phone":"+1 973 694 0233",
    "sg:postcode":"07470",
    "sg:province":"NJ",
    "sg:tags":[
        "accountant"
    ],
    "wof:name":"Lawler Philip E Public Accountant",
    "wof:placetype":"venue"
},
  "geometry": {"coordinates":[-74.2323,40.925598],"type":"Point"}
}