{
  "type": "Feature",
  "properties": {
    "iso:country":"US",
    "sg:address":"163 11th St",
    "sg:city":"Hoboken",
    "sg:classifiers":[
        {
            "category":"Professional",
            "subcategory":"Computer Services",
            "type":"Services"
        }
    ],
    "sg:phone":"+1 201 792 2682",
    "sg:postcode":"07030",
    "sg:province":"NJ",
    "sg:tags":[
        "consultant",
        "designer"
    ],
    "sg:website":"www.soundcomputing.com",
    "wof:name":"Sound Computing Corp",
    "wof:placetype":"venue"
},
  "geometry": {"coordinates":[-74.028724,40.750025],"type":"Point"}
}