{
  "type": "Feature",
  "properties": {
    "addr:full":"2402 Hartford Dr Glendora NJ 08029",
    "addr:housenumber":"2402",
    "addr:postcode":"08029",
    "addr:street":"Hartford Dr",
    "iso:country":"US",
    "sg:address":"2402 Hartford Dr",
    "sg:city":"Glendora",
    "sg:classifiers":[
        {
            "category":"Building & Trades",
            "subcategory":"Construction",
            "type":"Services"
        }
    ],
    "sg:phone":"+1 856 939 2037",
    "sg:postcode":"08029",
    "sg:province":"NJ",
    "sg:tags":[
        "house"
    ],
    "wof:name":"J Breen Construction LLC",
    "wof:placetype":"venue"
},
  "geometry": {"coordinates":[-75.05968799999999,39.843862],"type":"Point"}
}