{
  "type": "Feature",
  "properties": {
    "addr:full":"35 Rupell Rd Hampton NJ 08827",
    "addr:housenumber":"35",
    "addr:postcode":"08827",
    "addr:street":"Rupell Rd",
    "iso:country":"US",
    "sg:address":"35 Rupell Rd",
    "sg:city":"Hampton",
    "sg:classifiers":[
        {
            "category":"Building & Trades",
            "subcategory":"Construction",
            "type":"Services"
        }
    ],
    "sg:phone":"+1 908 730 0009",
    "sg:postcode":"08827",
    "sg:province":"NJ",
    "sg:tags":[
        "bathroom",
        "remodeling",
        "contractor"
    ],
    "sg:website":"http://www.homesolutionsapc.com",
    "wof:name":"Home Solutions",
    "wof:placetype":"venue"
},
  "geometry": {"coordinates":[-74.938659,40.635986],"type":"Point"}
}