{
  "type": "Feature",
  "properties": {
    "iso:country":"US",
    "sg:address":"1150 Pottersville Rd",
    "sg:city":"Gladstone",
    "sg:classifiers":[
        {
            "category":"Education",
            "subcategory":"School",
            "type":"Public Place"
        }
    ],
    "sg:phone":"+1 908 470 9500",
    "sg:postcode":"07934",
    "sg:province":"NJ",
    "sg:tags":[
        "elementary"
    ],
    "sg:website":"www.willowschool.org",
    "wof:name":"Willow School Inc",
    "wof:placetype":"venue"
},
  "geometry": {"coordinates":[-74.678612,40.719294],"type":"Point"}
}