{
  "type": "Feature",
  "properties": {
    "addr:full":"6703 Park Ave West New York NJ 07093",
    "addr:housenumber":"6703",
    "addr:postcode":"07093",
    "addr:street":"Park Ave West",
    "iso:country":"US",
    "sg:address":"6703 Park Ave",
    "sg:city":"West New York",
    "sg:classifiers":[
        {
            "category":"Shopping",
            "subcategory":"Discount & Variety Stores",
            "type":"Retail Goods"
        }
    ],
    "sg:phone":"+1 201 861 2300",
    "sg:postcode":"07093",
    "sg:province":"NJ",
    "wof:name":"Liberty 99 & Up",
    "wof:placetype":"venue"
},
  "geometry": {"coordinates":[-74.00433,40.791279],"type":"Point"}
}