{
  "type": "Feature",
  "properties": {
    "addr:full":"69 E Main St Little Falls NJ 07424",
    "addr:housenumber":"69",
    "addr:postcode":"07424",
    "addr:street":"E Main St",
    "iso:country":"US",
    "sg:address":"69 E Main St",
    "sg:city":"Little Falls",
    "sg:classifiers":[
        {
            "category":"Food & Beverages",
            "subcategory":"Groceries & Convenience Stores",
            "type":"Retail Goods"
        }
    ],
    "sg:phone":"+1   ",
    "sg:postcode":"07424",
    "sg:province":"NJ",
    "wof:name":"Quick Chek 28",
    "wof:placetype":"venue"
},
  "geometry": {"coordinates":[-74.223086,40.88008],"type":"Point"}
}