{
  "type": "Feature",
  "properties": {
    "addr:full":"124 W Hanover Ave Randolph NJ 07869",
    "addr:housenumber":"124",
    "addr:postcode":"07869",
    "addr:street":"W Hanover Ave",
    "iso:country":"US",
    "sg:address":"124 W Hanover Ave",
    "sg:city":"Randolph",
    "sg:classifiers":[
        {
            "category":"Professional",
            "subcategory":"Management & Consulting",
            "type":"Services"
        }
    ],
    "sg:phone":"+1 973 895 4496",
    "sg:postcode":"07869",
    "sg:province":"NJ",
    "wof:name":"Aramark",
    "wof:placetype":"venue"
},
  "geometry": {"coordinates":[-74.547128,40.830014],"type":"Point"}
}