{
  "type": "Feature",
  "properties": {
    "iso:country":"US",
    "sg:address":"417 S Broadway",
    "sg:city":"Gloucester City",
    "sg:classifiers":[
        {
            "category":"Cinema",
            "subcategory":"Movie Rental",
            "type":"Entertainment"
        }
    ],
    "sg:phone":"+1 856 456 5100",
    "sg:postcode":"08030",
    "sg:province":"NJ",
    "sg:tags":[
        "game",
        "video"
    ],
    "wof:name":"West Coast Video of Gloucester City",
    "wof:placetype":"venue"
},
  "geometry": {"coordinates":[-75.12039900000001,39.888802],"type":"Point"}
}