{
  "type": "Feature",
  "properties": {
    "iso:country":"US",
    "sg:address":"767 Sanford Ave",
    "sg:city":"Newark",
    "sg:classifiers":[
        {
            "category":"Real Estate",
            "subcategory":"Real Estate Agent",
            "type":"Services"
        }
    ],
    "sg:phone":"+1 973 371 1793",
    "sg:postcode":"07106",
    "sg:province":"NJ",
    "wof:name":"New Jersey Affordable Homes",
    "wof:placetype":"venue"
},
  "geometry": {"coordinates":[-74.237173,40.735329],"type":"Point"}
}