{
  "type": "Feature",
  "properties": {
    "iso:country":"US",
    "sg:address":"320 Wabash Ave",
    "sg:city":"Paterson",
    "sg:classifiers":[
        {
            "category":"Manufacturing",
            "subcategory":"Metals",
            "type":"Manufacturing & Wholesale Goods"
        }
    ],
    "sg:phone":"+1 973 345 4182",
    "sg:postcode":"07503",
    "sg:province":"NJ",
    "sg:tags":[
        "fabricator",
        "metalwork",
        "sheet",
        "mfg"
    ],
    "wof:name":"Paterson Sheet Metal Works",
    "wof:placetype":"venue"
},
  "geometry": {"coordinates":[-74.148304,40.892123],"type":"Point"}
}