{
  "type": "Feature",
  "properties": {
    "iso:country":"US",
    "sg:address":"1 Raymond Blvd",
    "sg:city":"Newark",
    "sg:classifiers":[
        {
            "category":"Restaurant",
            "type":"Food & Drink"
        }
    ],
    "sg:phone":"+1 973 624 5034",
    "sg:postcode":"07105",
    "sg:province":"NJ",
    "wof:name":"Mc Donald's",
    "wof:placetype":"venue"
},
  "geometry": {"coordinates":[-74.120088,40.73291],"type":"Point"}
}