{
  "type": "Feature",
  "properties": {
    "iso:country":"US",
    "sg:address":"2 University Plz",
    "sg:city":"Hackensack",
    "sg:classifiers":[
        {
            "category":"Manufacturing",
            "subcategory":"Printing",
            "type":"Manufacturing & Wholesale Goods"
        }
    ],
    "sg:phone":"+1 201 487 7800",
    "sg:postcode":"07601",
    "sg:province":"NJ",
    "sg:tags":[
        "publisher"
    ],
    "sg:website":"www.cygnusb2b.com",
    "wof:name":"Kitchen Bath Design News",
    "wof:placetype":"venue"
},
  "geometry": {"coordinates":[-74.039788,40.895967],"type":"Point"}
}