{
  "type": "Feature",
  "properties": {
    "addr:full":"512 Union St Trenton NJ 08611",
    "addr:housenumber":"512",
    "addr:postcode":"08611",
    "addr:street":"Union St",
    "iso:country":"US",
    "sg:address":"512 Union St",
    "sg:city":"Trenton",
    "sg:classifiers":[
        {
            "category":"Professional",
            "type":"Services"
        }
    ],
    "sg:phone":"+1 609 396 0996",
    "sg:postcode":"08611",
    "sg:province":"NJ",
    "sg:tags":[
        "establishment"
    ],
    "wof:name":"Aculabs Inc",
    "wof:placetype":"venue"
},
  "geometry": {"coordinates":[-74.761849,40.206933],"type":"Point"}
}