{
  "type": "Feature",
  "properties": {
    "addr:full":"1202 Mindy Ln Piscataway NJ 08854",
    "addr:housenumber":"1202",
    "addr:postcode":"08854",
    "addr:street":"Mindy Ln",
    "iso:country":"US",
    "sg:address":"1202 Mindy Ln",
    "sg:city":"Piscataway",
    "sg:classifiers":[
        {
            "category":"Restaurant",
            "type":"Food & Drink"
        }
    ],
    "sg:phone":"+1 908 874 3737",
    "sg:postcode":"08854",
    "sg:province":"NJ",
    "wof:name":"Subway Sandwiches & Salads",
    "wof:placetype":"venue"
},
  "geometry": {"coordinates":[-74.41777399999999,40.528783],"type":"Point"}
}