{
  "type": "Feature",
  "properties": {
    "addr:full":"1001 Line St Camden NJ 08103",
    "addr:housenumber":"1001",
    "addr:postcode":"08103",
    "addr:street":"Line St",
    "iso:country":"US",
    "sg:address":"1001 Line St",
    "sg:city":"Camden",
    "sg:classifiers":[
        {
            "category":"Manufacturing",
            "subcategory":"Petroleum Products",
            "type":"Manufacturing & Wholesale Goods"
        }
    ],
    "sg:phone":"+1 856 963 0770",
    "sg:postcode":"08103",
    "sg:province":"NJ",
    "sg:tags":[
        "contract"
    ],
    "wof:name":"Kohlder Mfg",
    "wof:placetype":"venue"
},
  "geometry": {"coordinates":[-75.11145,39.937599],"type":"Point"}
}