{
  "type": "Feature",
  "properties": {
    "addr:full":"18 White Birch Trl Rockaway NJ 07866",
    "addr:housenumber":"18",
    "addr:postcode":"07866",
    "addr:street":"White Birch Trl",
    "iso:country":"US",
    "sg:address":"18 White Birch Trl",
    "sg:city":"Rockaway",
    "sg:classifiers":[
        {
            "category":"Building & Trades",
            "subcategory":"Construction",
            "type":"Services"
        }
    ],
    "sg:phone":"+1 973 627 8782",
    "sg:postcode":"07866",
    "sg:province":"NJ",
    "sg:tags":[
        "excavating",
        "contractor"
    ],
    "wof:name":"Carradini Excavating",
    "wof:placetype":"venue"
},
  "geometry": {"coordinates":[-74.498598,40.963174],"type":"Point"}
}