{
  "type": "Feature",
  "properties": {
    "addr:full":"15 Sheridan Ave Ho Ho Kus NJ 07423",
    "addr:housenumber":"15",
    "addr:postcode":"07423",
    "addr:street":"Sheridan Ave",
    "iso:country":"US",
    "sg:address":"15 Sheridan Ave",
    "sg:city":"Ho Ho Kus",
    "sg:classifiers":[
        {
            "category":"Personal",
            "subcategory":"Beauty Salon",
            "type":"Services"
        }
    ],
    "sg:phone":"+1 201 444 5303",
    "sg:postcode":"07423",
    "sg:province":"NJ",
    "sg:tags":[
        "shop"
    ],
    "wof:name":"Hair Designers",
    "wof:placetype":"venue"
},
  "geometry": {"coordinates":[-74.109961,40.998684],"type":"Point"}
}