{
  "type": "Feature",
  "properties": {
    "addr:full":"68 W Jimmie Leeds Rd Absecon NJ 08205",
    "addr:housenumber":"68",
    "addr:postcode":"08205",
    "addr:street":"W Jimmie Leeds Rd",
    "iso:country":"US",
    "sg:address":"68 W Jimmie Leeds Rd",
    "sg:city":"Absecon",
    "sg:classifiers":[
        {
            "category":"Personal",
            "subcategory":"Beauty Salon",
            "type":"Services"
        }
    ],
    "sg:phone":"+1 609 748 8989",
    "sg:postcode":"08205",
    "sg:province":"NJ",
    "sg:tags":[
        "manicuring"
    ],
    "wof:name":"Hale Nails",
    "wof:placetype":"venue"
},
  "geometry": {"coordinates":[-74.539416,39.476261],"type":"Point"}
}