{
  "type": "Feature",
  "properties": {
    "addr:full":"2648 State Rt 23 Newfoundland NJ 07435",
    "addr:housenumber":"2648",
    "addr:postcode":"07435",
    "addr:street":"State Rt 23",
    "iso:country":"US",
    "sg:address":"2648 State Rt 23",
    "sg:city":"Newfoundland",
    "sg:classifiers":[
        {
            "category":"Ice Cream",
            "type":"Food & Drink"
        }
    ],
    "sg:menulink":"http://www.allmenus.com/nj/west-milford/167810-dairy-queen/menu/",
    "sg:phone":"+1 973 697 1484",
    "sg:postcode":"07435",
    "sg:province":"NJ",
    "sg:tags":[
        "burger",
        "american"
    ],
    "wof:name":"Dairy Queen",
    "wof:placetype":"venue"
},
  "geometry": {"coordinates":[-74.414424,41.028306],"type":"Point"}
}