{
  "type": "Feature",
  "properties": {
    "addr:full":"865 Lower Ferry Rd Trenton NJ 08628",
    "addr:housenumber":"865",
    "addr:postcode":"08628",
    "addr:street":"Lower Ferry Rd",
    "iso:country":"US",
    "sg:address":"865 Lower Ferry Rd",
    "sg:city":"Trenton",
    "sg:classifiers":[
        {
            "category":"Professional",
            "subcategory":"Computer Services",
            "type":"Services"
        }
    ],
    "sg:phone":"+1   ",
    "sg:postcode":"08628",
    "sg:province":"NJ",
    "sg:tags":[
        "development",
        "software"
    ],
    "wof:name":"Fti",
    "wof:placetype":"venue"
},
  "geometry": {"coordinates":[-74.811696,40.249056],"type":"Point"}
}