{
  "type": "Feature",
  "properties": {
    "iso:country":"US",
    "sg:address":"151 Tennis Ct",
    "sg:city":"Belmar",
    "sg:classifiers":[
        {
            "category":"Professional",
            "type":"Services"
        }
    ],
    "sg:phone":"+1   ",
    "sg:postcode":"07719",
    "sg:province":"NJ",
    "wof:name":"Dave Butler",
    "wof:placetype":"venue"
},
  "geometry": {"coordinates":[-74.079999,40.16723],"type":"Point"}
}