{
  "type": "Feature",
  "properties": {
    "addr:full":"1 Spring Rd Newton NJ 07860",
    "addr:housenumber":"1",
    "addr:postcode":"07860",
    "addr:street":"Spring Rd",
    "iso:country":"US",
    "sg:address":"1 Spring Rd",
    "sg:city":"Newton",
    "sg:classifiers":[
        {
            "category":"Government",
            "subcategory":"Office",
            "type":"Public Place"
        }
    ],
    "sg:phone":"+1 973 579 0300",
    "sg:postcode":"07860",
    "sg:province":"NJ",
    "wof:name":"Sussex County Adm Dept",
    "wof:placetype":"venue"
},
  "geometry": {"coordinates":[-74.73146199999999,41.074837],"type":"Point"}
}