{
  "type": "Feature",
  "properties": {
    "iso:country":"US",
    "sg:address":"320 Beverly Rancocas Rd",
    "sg:city":"Willingboro",
    "sg:classifiers":[
        {
            "category":"Utilities",
            "subcategory":"Mobile Phone",
            "type":"Services"
        }
    ],
    "sg:phone":"+1 609 871 0018",
    "sg:postcode":"08046",
    "sg:province":"NJ",
    "sg:tags":[
        "telephone",
        "cellular"
    ],
    "wof:name":"Sound & Cell",
    "wof:placetype":"venue"
},
  "geometry": {"coordinates":[-74.906813,40.027513],"type":"Point"}
}