{
  "type": "Feature",
  "properties": {
    "iso:country":"US",
    "sg:address":"279 W End Ave",
    "sg:city":"Ridgewood",
    "sg:classifiers":[
        {
            "category":"Professional",
            "subcategory":"Management & Consulting",
            "type":"Services"
        }
    ],
    "sg:phone":"+1 201 445 8328",
    "sg:postcode":"07450",
    "sg:province":"NJ",
    "wof:name":"Jt Group Ltd",
    "wof:placetype":"venue"
},
  "geometry": {"coordinates":[-74.135937,40.976304],"type":"Point"}
}