{
  "type": "Feature",
  "properties": {
    "iso:country":"US",
    "sg:address":"8 Madison St",
    "sg:city":"Princeton",
    "sg:classifiers":[
        {
            "category":"Professional",
            "subcategory":"Engineering",
            "type":"Services"
        }
    ],
    "sg:phone":"+1 609 924 0536",
    "sg:postcode":"08542",
    "sg:province":"NJ",
    "sg:tags":[
        "engineer"
    ],
    "sg:website":"www.agricolametals.com",
    "wof:name":"Agricola Metals Corp",
    "wof:placetype":"venue"
},
  "geometry": {"coordinates":[-74.657308,40.35313],"type":"Point"}
}