{
  "type": "Feature",
  "properties": {
    "addr:full":"16 Debra Dr Dayton NJ 08810",
    "addr:housenumber":"16",
    "addr:postcode":"08810",
    "addr:street":"Debra Dr",
    "iso:country":"US",
    "sg:address":"16 Debra Dr",
    "sg:city":"Dayton",
    "sg:classifiers":[
        {
            "category":"Health Services",
            "subcategory":"Clinic",
            "type":"Services"
        }
    ],
    "sg:phone":"+1 732 274 1113",
    "sg:postcode":"08810",
    "sg:province":"NJ",
    "sg:tags":[
        "home"
    ],
    "wof:name":"Comfort Keepers",
    "wof:placetype":"venue"
},
  "geometry": {"coordinates":[-74.50325100000001,40.362932],"type":"Point"}
}