{
  "type": "Feature",
  "properties": {
    "addr:full":"112 Vozi Ct Long Branch NJ 07740",
    "addr:housenumber":"112",
    "addr:postcode":"07740",
    "addr:street":"Vozi Ct",
    "iso:country":"US",
    "sg:address":"112 Vozi Ct",
    "sg:city":"Long Branch",
    "sg:classifiers":[
        {
            "category":"Real Estate",
            "subcategory":"Real Estate Agent",
            "type":"Services"
        }
    ],
    "sg:phone":"+1   ",
    "sg:postcode":"07740",
    "sg:province":"NJ",
    "sg:tags":[
        "manager"
    ],
    "wof:name":"580 Broadway LLC",
    "wof:placetype":"venue"
},
  "geometry": {"coordinates":[-73.992586,40.27049],"type":"Point"}
}