{
  "type": "Feature",
  "properties": {
    "addr:full":"958 S Springfield Ave Springfield NJ 07081",
    "addr:housenumber":"958",
    "addr:postcode":"07081",
    "addr:street":"S Springfield Ave",
    "iso:country":"US",
    "sg:address":"958 S Springfield Ave",
    "sg:city":"Springfield",
    "sg:classifiers":[
        {
            "category":"Food & Beverages",
            "subcategory":"Groceries & Convenience Stores",
            "type":"Retail Goods"
        }
    ],
    "sg:phone":"+1 973 258 1858",
    "sg:postcode":"07081",
    "sg:province":"NJ",
    "wof:name":"Quick Mart Food Store",
    "wof:placetype":"venue"
},
  "geometry": {"coordinates":[-74.33090199999999,40.682999],"type":"Point"}
}