{
  "type": "Feature",
  "properties": {
    "addr:full":"1125 US Hwy 22 Bridgewater NJ 08807",
    "addr:housenumber":"1125",
    "addr:postcode":"08807",
    "addr:street":"Us Hwy 22",
    "iso:country":"US",
    "sg:address":"1125 US Hwy 22",
    "sg:city":"Bridgewater",
    "sg:classifiers":[
        {
            "category":"Banks & Credit Unions",
            "subcategory":"Bank",
            "type":"Services"
        }
    ],
    "sg:phone":"+1 908 000 1111",
    "sg:postcode":"08807",
    "sg:province":"NJ",
    "wof:name":"Bank Of America",
    "wof:placetype":"venue"
},
  "geometry": {"coordinates":[-74.58611399999999,40.578067],"type":"Point"}
}