{
  "type": "Feature",
  "properties": {
    "addr:full":"1 Wayne Towne Ctr Wayne NJ 07470",
    "addr:housenumber":"1",
    "addr:postcode":"07470",
    "addr:street":"Wayne Towne Ctr",
    "iso:country":"US",
    "sg:address":"1 Wayne Towne Ctr",
    "sg:city":"Wayne",
    "sg:classifiers":[
        {
            "category":"Restaurant",
            "type":"Food & Drink"
        }
    ],
    "sg:phone":"+1 973 812 3800",
    "sg:postcode":"07470",
    "sg:province":"NJ",
    "sg:tags":[
        "traditional",
        "american"
    ],
    "wof:name":"Friday's",
    "wof:placetype":"venue"
},
  "geometry": {"coordinates":[-74.254501,40.891102],"type":"Point"}
}