{
  "type": "Feature",
  "properties": {
    "iso:country":"US",
    "sg:address":"214 Engle St",
    "sg:city":"Englewood",
    "sg:classifiers":[
        {
            "category":"Health Services",
            "subcategory":"Doctor",
            "type":"Services"
        }
    ],
    "sg:phone":"+1 201 567 2206",
    "sg:postcode":"07631",
    "sg:province":"NJ",
    "sg:tags":[
        "physician",
        "surgeon"
    ],
    "wof:name":"Simon Kahn MD",
    "wof:placetype":"venue"
},
  "geometry": {"coordinates":[-73.969584,40.899621],"type":"Point"}
}