{
  "type": "Feature",
  "properties": {
    "iso:country":"US",
    "sg:address":"570 Leo St",
    "sg:city":"Hillside",
    "sg:classifiers":[
        {
            "category":"Freight",
            "type":"Transportation"
        }
    ],
    "sg:phone":"+1 973 220 3242",
    "sg:postcode":"07205",
    "sg:province":"NJ",
    "sg:tags":[
        "operator",
        "trucking"
    ],
    "wof:name":"Lias Trucking Inc",
    "wof:placetype":"venue"
},
  "geometry": {"coordinates":[-74.24114299999999,40.69951],"type":"Point"}
}