{
  "type": "Feature",
  "properties": {
    "iso:country":"US",
    "sg:address":"28 Pierson Ave",
    "sg:city":"Princeton",
    "sg:classifiers":[
        {
            "category":"Organizations",
            "subcategory":"Religious Organization",
            "type":"Services"
        }
    ],
    "sg:phone":"+1   ",
    "sg:postcode":"08540",
    "sg:province":"NJ",
    "wof:name":"Kenneth A Smith Rev",
    "wof:placetype":"venue"
},
  "geometry": {"coordinates":[-74.634455,40.326115],"type":"Point"}
}