{
  "type": "Feature",
  "properties": {
    "addr:full":"1265 Ocean Ave Long Branch NJ 07740",
    "addr:housenumber":"1265",
    "addr:postcode":"07740",
    "addr:street":"Ocean Ave",
    "iso:country":"US",
    "sg:address":"1265 Ocean Ave",
    "sg:city":"Long Branch",
    "sg:classifiers":[
        {
            "category":"Building & Trades",
            "subcategory":"Construction",
            "type":"Services"
        }
    ],
    "sg:phone":"+1 732 870 8221",
    "sg:postcode":"07740",
    "sg:province":"NJ",
    "sg:tags":[
        "company"
    ],
    "wof:name":"John E Robinson Construction",
    "wof:placetype":"venue"
},
  "geometry": {"coordinates":[-73.989628,40.26301],"type":"Point"}
}