{
  "type": "Feature",
  "properties": {
    "addr:full":"121 New Jersey Ave Absecon NJ 08201",
    "addr:housenumber":"121",
    "addr:postcode":"08201",
    "addr:street":"New Jersey Ave",
    "iso:country":"US",
    "sg:address":"121 New Jersey Ave",
    "sg:city":"Absecon",
    "sg:classifiers":[
        {
            "category":"Retail",
            "subcategory":"Laundry & Dry Cleaning",
            "type":"Services"
        }
    ],
    "sg:phone":"+1   ",
    "sg:postcode":"08201",
    "sg:province":"NJ",
    "sg:tags":[
        "cleaners",
        "tailor"
    ],
    "wof:name":"Peps Cleaners & Tailors",
    "wof:placetype":"venue"
},
  "geometry": {"coordinates":[-74.500765,39.424485],"type":"Point"}
}