{
  "type": "Feature",
  "properties": {
    "addr:full":"930 Lower Ferry Rd Trenton NJ 08628",
    "addr:housenumber":"930",
    "addr:postcode":"08628",
    "addr:street":"Lower Ferry Rd",
    "iso:country":"US",
    "sg:address":"930 Lower Ferry Rd",
    "sg:city":"Trenton",
    "sg:classifiers":[
        {
            "category":"Professional",
            "subcategory":"Testing Lab",
            "type":"Services"
        }
    ],
    "sg:phone":"+1 609 530 2307",
    "sg:postcode":"08628",
    "sg:province":"NJ",
    "sg:tags":[
        "laboratory"
    ],
    "sg:website":"www.state.nj.us",
    "wof:name":"Nj Dept-Trans Bureau-Materials",
    "wof:placetype":"venue"
},
  "geometry": {"coordinates":[-74.801913,40.25578],"type":"Point"}
}