{
  "type": "Feature",
  "properties": {
    "iso:country":"US",
    "sg:address":"3 Clearwater Dr",
    "sg:city":"Kinnelon",
    "sg:classifiers":[
        {
            "category":"Building & Trades",
            "subcategory":"Construction",
            "type":"Services"
        }
    ],
    "sg:phone":"+1 973 283 4614",
    "sg:postcode":"07405",
    "sg:province":"NJ",
    "sg:tags":[
        "general",
        "contractor"
    ],
    "wof:name":"M & D Contractors LLC",
    "wof:placetype":"venue"
},
  "geometry": {"coordinates":[-74.40014499999999,40.981056],"type":"Point"}
}