{
  "type": "Feature",
  "properties": {
    "addr:full":"627 Society Hill Blvd Cherry Hill NJ 08003",
    "addr:housenumber":"627",
    "addr:postcode":"08003",
    "addr:street":"Society Hill Blvd",
    "iso:country":"US",
    "sg:address":"627 Society Hill Blvd",
    "sg:city":"Cherry Hill",
    "sg:classifiers":[
        {
            "category":"Professional",
            "subcategory":"Management & Consulting",
            "type":"Services"
        }
    ],
    "sg:phone":"+1   ",
    "sg:postcode":"08003",
    "sg:province":"NJ",
    "sg:tags":[
        "business"
    ],
    "wof:name":"Baby Proofers Inc",
    "wof:placetype":"venue"
},
  "geometry": {"coordinates":[-74.967932,39.898846],"type":"Point"}
}