{
  "type": "Feature",
  "properties": {
    "addr:full":"82 South Ave Atlantic Highlands NJ 07716",
    "addr:housenumber":"82",
    "addr:postcode":"07716",
    "addr:street":"South Ave",
    "iso:country":"US",
    "sg:address":"82 South Ave",
    "sg:city":"Atlantic Highlands",
    "sg:classifiers":[
        {
            "category":"Freight",
            "type":"Transportation"
        }
    ],
    "sg:phone":"+1 973 584 3252",
    "sg:postcode":"07716",
    "sg:province":"NJ",
    "wof:name":"North Star Marine Enterprises",
    "wof:placetype":"venue"
},
  "geometry": {"coordinates":[-74.047798,40.415926],"type":"Point"}
}