{
  "type": "Feature",
  "properties": {
    "addr:full":"17 Banner Ct East Brunswick NJ 08816",
    "addr:housenumber":"17",
    "addr:postcode":"08816",
    "addr:street":"Banner Ct",
    "iso:country":"US",
    "sg:address":"17 Banner Ct",
    "sg:city":"East Brunswick",
    "sg:classifiers":[
        {
            "category":"Professional",
            "subcategory":"Management & Consulting",
            "type":"Services"
        }
    ],
    "sg:phone":"+1   ",
    "sg:postcode":"08816",
    "sg:province":"NJ",
    "sg:tags":[
        "business"
    ],
    "wof:name":"Hfe Consulting LLC",
    "wof:placetype":"venue"
},
  "geometry": {"coordinates":[-74.416087,40.471514],"type":"Point"}
}