{
  "type": "Feature",
  "properties": {
    "addr:full":"4 Gladys Ct Edison NJ 08817",
    "addr:housenumber":"4",
    "addr:postcode":"08817",
    "addr:street":"Gladys Ct",
    "iso:country":"US",
    "sg:address":"4 Gladys Ct",
    "sg:city":"Edison",
    "sg:classifiers":[
        {
            "category":"Building & Trades",
            "subcategory":"Electrical",
            "type":"Services"
        }
    ],
    "sg:phone":"+1 732 248 6868",
    "sg:postcode":"08817",
    "sg:province":"NJ",
    "sg:tags":[
        "electric",
        "contractor"
    ],
    "sg:website":"www.centuryconveyor.com",
    "wof:name":"Edison Electrical",
    "wof:placetype":"venue"
},
  "geometry": {"coordinates":[-74.403631,40.543922],"type":"Point"}
}