{
  "type": "Feature",
  "properties": {
    "iso:country":"US",
    "sg:address":"165 Union Ave",
    "sg:city":"Clifton",
    "sg:classifiers":[
        {
            "category":"Building & Trades",
            "subcategory":"Plumbing",
            "type":"Services"
        }
    ],
    "sg:phone":"+1 973 772 5100",
    "sg:postcode":"07011",
    "sg:province":"NJ",
    "sg:tags":[
        "air",
        "heating",
        "conditioning",
        "contractor"
    ],
    "wof:name":"Richs Heating and AC",
    "wof:placetype":"venue"
},
  "geometry": {"coordinates":[-74.148043,40.87545],"type":"Point"}
}