{
  "type": "Feature",
  "properties": {
    "addr:full":"600 Great Bay Blvd Little Egg Hbr NJ 08087",
    "addr:housenumber":"600",
    "addr:postcode":"08087",
    "addr:street":"Great Bay Blvd Little",
    "iso:country":"US",
    "sg:address":"600 Great Bay Blvd",
    "sg:city":"Little Egg Hbr",
    "sg:classifiers":[
        {
            "category":"Recreation",
            "type":"Entertainment"
        }
    ],
    "sg:phone":"+1 609 296 4457",
    "sg:postcode":"08087",
    "sg:province":"NJ",
    "sg:tags":[
        "charter",
        "boat"
    ],
    "wof:name":"Rand's U-Drive Motor Boats Inc",
    "wof:placetype":"venue"
},
  "geometry": {"coordinates":[-74.340458,39.559462],"type":"Point"}
}