{
  "type": "Feature",
  "properties": {
    "addr:full":"173 Morris St Morristown NJ 07960",
    "addr:housenumber":"173",
    "addr:postcode":"07960",
    "addr:street":"Morris St",
    "iso:country":"US",
    "sg:address":"173 Morris St",
    "sg:city":"Morristown",
    "sg:classifiers":[
        {
            "category":"Communications",
            "subcategory":"Newspaper",
            "type":"Services"
        }
    ],
    "sg:phone":"+1 973 605 1877",
    "sg:postcode":"07960",
    "sg:province":"NJ",
    "sg:tags":[
        "print",
        "medium"
    ],
    "wof:name":"Houses Magazine",
    "wof:placetype":"venue"
},
  "geometry": {"coordinates":[-74.47080200000001,40.795799],"type":"Point"}
}