{
  "type": "Feature",
  "properties": {
    "addr:full":"28 Harrison St Woodbury NJ 08096",
    "addr:housenumber":"28",
    "addr:postcode":"08096",
    "addr:street":"Harrison St",
    "iso:country":"US",
    "sg:address":"28 Harrison St",
    "sg:city":"Woodbury",
    "sg:classifiers":[
        {
            "category":"Food & Beverages",
            "subcategory":"Meat & Fish",
            "type":"Retail Goods"
        }
    ],
    "sg:phone":"+1 856 853 9540",
    "sg:postcode":"08096",
    "sg:province":"NJ",
    "sg:tags":[
        "sausage"
    ],
    "wof:name":"J W Fine Foods",
    "wof:placetype":"venue"
},
  "geometry": {"coordinates":[-75.15518899999999,39.838959],"type":"Point"}
}