{
  "type": "Feature",
  "properties": {
    "iso:country":"US",
    "sg:address":"117 N Black Horse Pike",
    "sg:city":"Runnemede",
    "sg:classifiers":[
        {
            "category":"Building & Trades",
            "subcategory":"Cleaning & Sanitation",
            "type":"Services"
        }
    ],
    "sg:phone":"+1 856 939 9766",
    "sg:postcode":"08078",
    "sg:province":"NJ",
    "sg:tags":[
        "janitor"
    ],
    "sg:website":"www.4servicemaster.com/nj/4538",
    "wof:name":"Service Master TBS Div",
    "wof:placetype":"venue"
},
  "geometry": {"coordinates":[-75.071541,39.845586],"type":"Point"}
}