{
  "type": "Feature",
  "properties": {
    "addr:full":"95 Long Hill Rd Gillette NJ 07933",
    "addr:housenumber":"95",
    "addr:postcode":"07933",
    "addr:street":"Long Hill Rd",
    "iso:country":"US",
    "sg:address":"95 Long Hill Rd",
    "sg:city":"Gillette",
    "sg:classifiers":[
        {
            "category":"Building & Trades",
            "subcategory":"Landscaping Services",
            "type":"Services"
        }
    ],
    "sg:phone":"+1 908 647 3110",
    "sg:postcode":"07933",
    "sg:province":"NJ",
    "sg:tags":[
        "landscape",
        "contractor"
    ],
    "wof:name":"Peluso Landscaping",
    "wof:placetype":"venue"
},
  "geometry": {"coordinates":[-74.445273,40.691395],"type":"Point"}
}