{
  "type": "Feature",
  "properties": {
    "iso:country":"US",
    "sg:address":"116 Spring St",
    "sg:city":"Red Bank",
    "sg:classifiers":[
        {
            "category":"Health Services",
            "subcategory":"Doctor",
            "type":"Services"
        }
    ],
    "sg:phone":"+1 732 747 3848",
    "sg:postcode":"07701",
    "sg:province":"NJ",
    "sg:tags":[
        "dentist"
    ],
    "wof:name":"John W Ryan DMD",
    "wof:placetype":"venue"
},
  "geometry": {"coordinates":[-74.06023999999999,40.349149],"type":"Point"}
}