{
  "type": "Feature",
  "properties": {
    "addr:full":"1181 Edgewater Ave Ridgefield NJ 07657",
    "addr:housenumber":"1181",
    "addr:postcode":"07657",
    "addr:street":"Edgewater Ave",
    "iso:country":"US",
    "sg:address":"1181 Edgewater Ave",
    "sg:city":"Ridgefield",
    "sg:classifiers":[
        {
            "category":"Wholesale",
            "subcategory":"Jewelry",
            "type":"Manufacturing & Wholesale Goods"
        }
    ],
    "sg:phone":"+1 201 840 6224",
    "sg:postcode":"07657",
    "sg:province":"NJ",
    "sg:tags":[
        "jeweler"
    ],
    "wof:name":"Four Seasons Beauty",
    "wof:placetype":"venue"
},
  "geometry": {"coordinates":[-74.01387099999999,40.835117],"type":"Point"}
}