{
  "type": "Feature",
  "properties": {
    "addr:full":"365 Essex St Hackensack NJ 07601",
    "addr:housenumber":"365",
    "addr:postcode":"07601",
    "addr:street":"Essex St",
    "iso:country":"US",
    "sg:address":"365 Essex St",
    "sg:city":"Hackensack",
    "sg:classifiers":[
        {
            "category":"Banks & Credit Unions",
            "subcategory":"Bank",
            "type":"Services"
        }
    ],
    "sg:phone":"+1   ",
    "sg:postcode":"07601",
    "sg:province":"NJ",
    "sg:tags":[
        "depository",
        "banking"
    ],
    "wof:name":"Money Stop Check Checking",
    "wof:placetype":"venue"
},
  "geometry": {"coordinates":[-74.05946400000001,40.88384],"type":"Point"}
}