{
  "type": "Feature",
  "properties": {
    "iso:country":"US",
    "sg:address":"618 Park Ave",
    "sg:city":"Freehold",
    "sg:classifiers":[
        {
            "category":"Restaurant",
            "type":"Food & Drink"
        }
    ],
    "sg:phone":"+1 732 462 5911",
    "sg:postcode":"07728",
    "sg:province":"NJ",
    "wof:name":"Denims",
    "wof:placetype":"venue"
},
  "geometry": {"coordinates":[-74.269381,40.249762],"type":"Point"}
}