{
  "type": "Feature",
  "properties": {
    "iso:country":"US",
    "sg:address":"257 Marlton Pike E",
    "sg:city":"Cherry Hill",
    "sg:classifiers":[
        {
            "category":"Restaurant",
            "type":"Food & Drink"
        }
    ],
    "sg:phone":"+1 856 795 2307",
    "sg:postcode":"08034",
    "sg:province":"NJ",
    "sg:tags":[
        "delicatessen"
    ],
    "wof:name":"Lou & Ann's Delicatessen",
    "wof:placetype":"venue"
},
  "geometry": {"coordinates":[-75.00667900000001,39.913072],"type":"Point"}
}