{
  "type": "Feature",
  "properties": {
    "addr:full":"671 W Edgar Rd Linden NJ 07036",
    "addr:housenumber":"671",
    "addr:postcode":"07036",
    "addr:street":"W Edgar Rd",
    "iso:country":"US",
    "sg:address":"671 W Edgar Rd",
    "sg:city":"Linden",
    "sg:classifiers":[
        {
            "category":"Wholesale",
            "subcategory":"Groceries",
            "type":"Manufacturing & Wholesale Goods"
        }
    ],
    "sg:phone":"+1 908 474 9436",
    "sg:postcode":"07036",
    "sg:province":"NJ",
    "sg:tags":[
        "food",
        "product"
    ],
    "wof:name":"Apple Food Svc Of Linden LLC",
    "wof:placetype":"venue"
},
  "geometry": {"coordinates":[-74.251594,40.618087],"type":"Point"}
}