{
  "type": "Feature",
  "properties": {
    "addr:full":"596 Bergen Ave Jersey City NJ 07304",
    "addr:housenumber":"596",
    "addr:postcode":"07304",
    "addr:street":"Bergen Ave",
    "iso:country":"US",
    "sg:address":"596 Bergen Ave",
    "sg:city":"Jersey City",
    "sg:classifiers":[
        {
            "category":"Professional",
            "subcategory":"Computer Services",
            "type":"Services"
        }
    ],
    "sg:phone":"+1   ",
    "sg:postcode":"07304",
    "sg:province":"NJ",
    "sg:tags":[
        "related"
    ],
    "wof:name":"Nu Tech Horizons Inc",
    "wof:placetype":"venue"
},
  "geometry": {"coordinates":[-74.073148,40.720285],"type":"Point"}
}