{
  "type": "Feature",
  "properties": {
    "addr:full":"21 Mechanic St Cape May Court House NJ 08210",
    "addr:housenumber":"21",
    "addr:postcode":"08210",
    "addr:street":"Mechanic St",
    "iso:country":"US",
    "sg:address":"21 Mechanic St",
    "sg:city":"Cape May Court House",
    "sg:classifiers":[
        {
            "category":"Shopping",
            "subcategory":"Bicycles & Sporting Goods",
            "type":"Retail Goods"
        }
    ],
    "sg:phone":"+1   ",
    "sg:postcode":"08210",
    "sg:province":"NJ",
    "wof:name":"Just Sports Inc",
    "wof:placetype":"venue"
},
  "geometry": {"coordinates":[-74.82546600000001,39.082955],"type":"Point"}
}