{
  "type": "Feature",
  "properties": {
    "iso:country":"US",
    "sg:address":"580 Raritan Rd",
    "sg:city":"Roselle",
    "sg:classifiers":[
        {
            "category":"Personal",
            "subcategory":"Beauty Salon",
            "type":"Services"
        }
    ],
    "sg:phone":"+1 908 936 0133",
    "sg:postcode":"07203",
    "sg:province":"NJ",
    "sg:tags":[
        "shop",
        "spa",
        "day"
    ],
    "sg:website":"http://www.fromhead2toe.com",
    "wof:name":"From Head to Toe",
    "wof:placetype":"venue"
},
  "geometry": {"coordinates":[-74.27328799999999,40.64463],"type":"Point"}
}