{
  "type": "Feature",
  "properties": {
    "iso:country":"US",
    "sg:address":"90 Lupton Ln",
    "sg:city":"Haledon",
    "sg:classifiers":[
        {
            "category":"Professional",
            "subcategory":"Management & Consulting",
            "type":"Services"
        }
    ],
    "sg:phone":"+1 973 595 6889",
    "sg:postcode":"07508",
    "sg:province":"NJ",
    "sg:tags":[
        "consultant",
        "telecommunication",
        "business"
    ],
    "wof:name":"Greenstar Enterprises",
    "wof:placetype":"venue"
},
  "geometry": {"coordinates":[-74.181128,40.938705],"type":"Point"}
}