{
  "type": "Feature",
  "properties": {
    "addr:full":"117 S Lecato Ave Audubon NJ 08106",
    "addr:housenumber":"117",
    "addr:postcode":"08106",
    "addr:street":"S Lecato Ave",
    "iso:country":"US",
    "sg:address":"117 S Lecato Ave",
    "sg:city":"Audubon",
    "sg:classifiers":[
        {
            "category":"Professional",
            "type":"Services"
        }
    ],
    "sg:phone":"+1   ",
    "sg:postcode":"08106",
    "sg:province":"NJ",
    "wof:name":"B & B Container Services",
    "wof:placetype":"venue"
},
  "geometry": {"coordinates":[-75.06737699999999,39.894557],"type":"Point"}
}