{
  "type": "Feature",
  "properties": {
    "iso:country":"US",
    "sg:address":"2351 US Hwy 130",
    "sg:city":"Dayton",
    "sg:classifiers":[
        {
            "category":"Professional",
            "subcategory":"Management & Consulting",
            "type":"Services"
        }
    ],
    "sg:phone":"+1 732 274 3000",
    "sg:postcode":"08810",
    "sg:province":"NJ",
    "sg:tags":[
        "marketing",
        "program"
    ],
    "wof:name":"Polymer Group Inc",
    "wof:placetype":"venue"
},
  "geometry": {"coordinates":[-74.499853,40.369892],"type":"Point"}
}