{
  "type": "Feature",
  "properties": {
    "addr:full":"179 Boyd St Newark NJ 07108",
    "addr:housenumber":"179",
    "addr:postcode":"07108",
    "addr:street":"Boyd St",
    "iso:country":"US",
    "sg:address":"179 Boyd St",
    "sg:city":"Newark",
    "sg:classifiers":[
        {
            "category":"Recreation",
            "type":"Entertainment"
        }
    ],
    "sg:phone":"+1 973 733 3959",
    "sg:postcode":"07108",
    "sg:province":"NJ",
    "sg:tags":[
        "center"
    ],
    "wof:name":"Hayes Park West Recreation Ctr",
    "wof:placetype":"venue"
},
  "geometry": {"coordinates":[-74.19288,40.728781],"type":"Point"}
}