{
  "type": "Feature",
  "properties": {
    "iso:country":"US",
    "sg:address":"108 Center Dr",
    "sg:city":"Pennington",
    "sg:classifiers":[
        {
            "category":"Banks & Credit Unions",
            "subcategory":"Investment Brokerage",
            "type":"Services"
        }
    ],
    "sg:phone":"+1 609 333 1363",
    "sg:postcode":"08558",
    "sg:province":"NJ",
    "sg:tags":[
        "security"
    ],
    "sg:website":"www.edwardjones.com",
    "wof:name":"Edward Jones",
    "wof:placetype":"venue"
},
  "geometry": {"coordinates":[-74.647097,40.405726],"type":"Point"}
}