{
  "type": "Feature",
  "properties": {
    "addr:full":"108 Glenwood Ave Merchantville NJ 08109",
    "addr:housenumber":"108",
    "addr:postcode":"08109",
    "addr:street":"Glenwood Ave",
    "iso:country":"US",
    "sg:address":"108 Glenwood Ave",
    "sg:city":"Merchantville",
    "sg:classifiers":[
        {
            "category":"Wholesale",
            "subcategory":"Office Equipment",
            "type":"Manufacturing & Wholesale Goods"
        },
        {
            "category":"Professional",
            "subcategory":"Business Services",
            "type":"Services"
        },
        {
            "category":"Professional",
            "subcategory":"Printing & Photocopies",
            "type":"Services"
        },
        {
            "category":"Shopping",
            "subcategory":"Computers & Home Electronics",
            "type":"Retail Goods"
        }
    ],
    "sg:phone":"+1 856 488 4408",
    "sg:postcode":"08109",
    "sg:province":"NJ",
    "sg:tags":[
        "scanning",
        "printer",
        "form",
        "supply",
        "system",
        "printers-business",
        "plotting"
    ],
    "wof:name":"Finnegans Forms",
    "wof:placetype":"venue"
},
  "geometry": {"coordinates":[-75.03702699999999,39.949554],"type":"Point"}
}