{
  "type": "Feature",
  "properties": {
    "addr:full":"11 Laurence Pkwy South Amboy NJ 08879",
    "addr:housenumber":"11",
    "addr:postcode":"08879",
    "addr:street":"Laurence Pkwy",
    "iso:country":"US",
    "sg:address":"11 Laurence Pkwy",
    "sg:city":"South Amboy",
    "sg:phone":"+1 732 290 0350",
    "sg:postcode":"08879",
    "sg:province":"NJ",
    "sg:tags":[
        "communications",
        "telegraph"
    ],
    "wof:name":"Umangcorp",
    "wof:placetype":"venue"
},
  "geometry": {"coordinates":[-74.24680499999999,40.456792],"type":"Point"}
}