{
  "type": "Feature",
  "properties": {
    "iso:country":"US",
    "sg:address":"1 Sommers Ave",
    "sg:city":"Somers Point",
    "sg:classifiers":[
        {
            "category":"Government",
            "subcategory":"Office",
            "type":"Public Place"
        }
    ],
    "sg:phone":"+1 609 927 9088",
    "sg:postcode":"08244",
    "sg:province":"NJ",
    "sg:tags":[
        "village"
    ],
    "wof:name":"Somers Point City Clerk's Ofc",
    "wof:placetype":"venue"
},
  "geometry": {"coordinates":[-74.595659,39.309816],"type":"Point"}
}