{
  "type": "Feature",
  "properties": {
    "iso:country":"US",
    "sg:address":"135 Walnut Ave",
    "sg:city":"Marlton",
    "sg:classifiers":[
        {
            "category":"Professional",
            "type":"Services"
        }
    ],
    "sg:phone":"+1   ",
    "sg:postcode":"08053",
    "sg:province":"NJ",
    "wof:name":"Drag Racing USA",
    "wof:placetype":"venue"
},
  "geometry": {"coordinates":[-74.901811,39.799884],"type":"Point"}
}