{
  "type": "Feature",
  "properties": {
    "addr:full":"38 Yorkshire Dr Monroe Twp NJ 08831",
    "addr:housenumber":"38",
    "addr:postcode":"08831",
    "addr:street":"Yorkshire Dr",
    "iso:country":"US",
    "sg:address":"38 Yorkshire Dr",
    "sg:city":"Monroe Twp",
    "sg:classifiers":[
        {
            "category":"Professional",
            "subcategory":"Accounting & Tax Preparation",
            "type":"Services"
        }
    ],
    "sg:phone":"+1 609 409 7890",
    "sg:postcode":"08831",
    "sg:province":"NJ",
    "sg:tags":[
        "accountant"
    ],
    "wof:name":"William Gelfond CPA",
    "wof:placetype":"venue"
},
  "geometry": {"coordinates":[-74.443476,40.313996],"type":"Point"}
}