{
  "type": "Feature",
  "properties": {
    "addr:full":"1945 Springfield Ave Maplewood NJ 07040",
    "addr:housenumber":"1945",
    "addr:postcode":"07040",
    "addr:street":"Springfield Ave",
    "iso:country":"US",
    "sg:address":"1945 Springfield Ave",
    "sg:city":"Maplewood",
    "sg:classifiers":[
        {
            "category":"Building & Trades",
            "subcategory":"Plumbing",
            "type":"Services"
        }
    ],
    "sg:phone":"+1 973 762 2759",
    "sg:postcode":"07040",
    "sg:province":"NJ",
    "sg:tags":[
        "plumbing",
        "contractor"
    ],
    "wof:name":"Fischetti Plumbing & Heating",
    "wof:placetype":"venue"
},
  "geometry": {"coordinates":[-74.273534,40.720127],"type":"Point"}
}