{
  "type": "Feature",
  "properties": {
    "iso:country":"US",
    "sg:address":"1100 US Highway 46",
    "sg:city":"Little Falls",
    "sg:classifiers":[
        {
            "category":"Banks & Credit Unions",
            "subcategory":"Bank",
            "type":"Services"
        }
    ],
    "sg:phone":"+1 973 256 4224",
    "sg:postcode":"07424",
    "sg:province":"NJ",
    "wof:name":"Td Bank Na",
    "wof:placetype":"venue"
},
  "geometry": {"coordinates":[-74.213089,40.884682],"type":"Point"}
}