{
  "type": "Feature",
  "properties": {
    "addr:full":"4 Edgewood Ct Ringwood NJ 07456",
    "addr:housenumber":"4",
    "addr:postcode":"07456",
    "addr:street":"Edgewood Ct",
    "iso:country":"US",
    "sg:address":"4 Edgewood Ct",
    "sg:city":"Ringwood",
    "sg:classifiers":[
        {
            "category":"Wholesale",
            "subcategory":"Jewelry",
            "type":"Manufacturing & Wholesale Goods"
        }
    ],
    "sg:phone":"+1 973 839 0483",
    "sg:postcode":"07456",
    "sg:province":"NJ",
    "sg:tags":[
        "stone"
    ],
    "wof:name":"Swiss Time Promotions Inc",
    "wof:placetype":"venue"
},
  "geometry": {"coordinates":[-74.279234,41.064681],"type":"Point"}
}