{
  "type": "Feature",
  "properties": {
    "iso:country":"US",
    "sg:address":"708 Jackson Ave",
    "sg:city":"Elizabeth",
    "sg:classifiers":[
        {
            "category":"Building & Trades",
            "subcategory":"Locksmith",
            "type":"Services"
        }
    ],
    "sg:phone":"+1 908 662 6246",
    "sg:postcode":"07201",
    "sg:province":"NJ",
    "sg:tags":[
        "key"
    ],
    "wof:name":"Always Affective Available Affective Available Emergency Locks",
    "wof:placetype":"venue"
},
  "geometry": {"coordinates":[-74.201213,40.676634],"type":"Point"}
}