{
  "type": "Feature",
  "properties": {
    "iso:country":"US",
    "sg:address":"501 Co Rd 639",
    "sg:city":"Bloomsbury",
    "sg:classifiers":[
        {
            "category":"Organizations",
            "subcategory":"Membership Organization",
            "type":"Services"
        }
    ],
    "sg:phone":"+1 908 268 4284",
    "sg:postcode":"08804",
    "sg:province":"NJ",
    "sg:tags":[
        "profit"
    ],
    "wof:name":"CRC of New Jersey",
    "wof:placetype":"venue"
},
  "geometry": {"coordinates":[-75.125564,40.650024],"type":"Point"}
}