{
  "type": "Feature",
  "properties": {
    "addr:full":"43 Still Hollow Rd Lebanon NJ 08833",
    "addr:housenumber":"43",
    "addr:postcode":"08833",
    "addr:street":"Still Hollow Rd",
    "iso:country":"US",
    "sg:address":"43 Still Hollow Rd",
    "sg:city":"Lebanon",
    "sg:classifiers":[
        {
            "category":"Professional",
            "subcategory":"Business Services",
            "type":"Services"
        }
    ],
    "sg:phone":"+1   ",
    "sg:postcode":"08833",
    "sg:province":"NJ",
    "wof:name":"Laramass Enterprises Inc",
    "wof:placetype":"venue"
},
  "geometry": {"coordinates":[-74.809478,40.677546],"type":"Point"}
}