{
  "type": "Feature",
  "properties": {
    "iso:country":"US",
    "sg:address":"11 W 25th St",
    "sg:city":"Bayonne",
    "sg:classifiers":[
        {
            "category":"Sports & Exercise",
            "subcategory":"Gym",
            "type":"Entertainment"
        }
    ],
    "sg:phone":"+1 201 436 5595",
    "sg:postcode":"07002",
    "sg:province":"NJ",
    "sg:tags":[
        "trainer"
    ],
    "wof:name":"Fitness At the Wellness Center",
    "wof:placetype":"venue"
},
  "geometry": {"coordinates":[-74.117599,40.665798],"type":"Point"}
}