{
  "type": "Feature",
  "properties": {
    "addr:full":"100 Franklin Square Dr Somerset NJ 08873",
    "addr:housenumber":"100",
    "addr:postcode":"08873",
    "addr:street":"Franklin Square Dr",
    "iso:country":"US",
    "sg:address":"100 Franklin Square Dr",
    "sg:city":"Somerset",
    "sg:classifiers":[
        {
            "category":"Banks & Credit Unions",
            "subcategory":"Bank",
            "type":"Services"
        }
    ],
    "sg:phone":"+1   ",
    "sg:postcode":"08873",
    "sg:province":"NJ",
    "sg:tags":[
        "mortgage"
    ],
    "wof:name":"Wells Fargo",
    "wof:placetype":"venue"
},
  "geometry": {"coordinates":[-74.527106,40.537017],"type":"Point"}
}