{
  "type": "Feature",
  "properties": {
    "addr:full":"356 Catawba Ave Newfield NJ 08344",
    "addr:housenumber":"356",
    "addr:postcode":"08344",
    "addr:street":"Catawba Ave",
    "iso:country":"US",
    "sg:address":"356 Catawba Ave",
    "sg:city":"Newfield",
    "sg:classifiers":[
        {
            "category":"Building & Trades",
            "subcategory":"Plumbing",
            "type":"Services"
        }
    ],
    "sg:phone":"+1 856 939 1080",
    "sg:postcode":"08344",
    "sg:province":"NJ",
    "sg:tags":[
        "air",
        "heating",
        "conditioning",
        "contractor"
    ],
    "wof:name":"Hosking's Heating & Cooling",
    "wof:placetype":"venue"
},
  "geometry": {"coordinates":[-75.01740599999999,39.547335],"type":"Point"}
}