{
  "type": "Feature",
  "properties": {
    "iso:country":"US",
    "sg:address":"24 Merchants Way",
    "sg:city":"Colts Neck",
    "sg:classifiers":[
        {
            "category":"Restaurant",
            "type":"Food & Drink"
        }
    ],
    "sg:phone":"+1   ",
    "sg:postcode":"07722",
    "sg:province":"NJ",
    "sg:tags":[
        "eating"
    ],
    "wof:name":"Yoshi Limited",
    "wof:placetype":"venue"
},
  "geometry": {"coordinates":[-74.17478,40.290724],"type":"Point"}
}