{
  "type": "Feature",
  "properties": {
    "iso:country":"US",
    "sg:address":"7410 2nd Ave",
    "sg:city":"North Bergen",
    "sg:classifiers":[
        {
            "category":"Home & Garden",
            "subcategory":"Furniture",
            "type":"Retail Goods"
        }
    ],
    "sg:phone":"+1 201 430 6325",
    "sg:postcode":"07047",
    "sg:province":"NJ",
    "sg:tags":[
        "store"
    ],
    "wof:name":"Rrm Furniture",
    "wof:placetype":"venue"
},
  "geometry": {"coordinates":[-74.01038,40.799228],"type":"Point"}
}