{
  "type": "Feature",
  "properties": {
    "iso:country":"US",
    "sg:address":"542 W Scott Ave",
    "sg:city":"Rahway",
    "sg:classifiers":[
        {
            "category":"Building & Trades",
            "subcategory":"Construction",
            "type":"Services"
        }
    ],
    "sg:phone":"+1 732 382 9566",
    "sg:postcode":"07065",
    "sg:province":"NJ",
    "sg:tags":[
        "excavation",
        "contractor"
    ],
    "wof:name":"Holder J Back Hoe Service",
    "wof:placetype":"venue"
},
  "geometry": {"coordinates":[-74.27627,40.617841],"type":"Point"}
}