{
  "type": "Feature",
  "properties": {
    "addr:full":"21 N Clinton Ave Trenton NJ 08609",
    "addr:housenumber":"21",
    "addr:postcode":"08609",
    "addr:street":"N Clinton Ave",
    "iso:country":"US",
    "sg:address":"21 N Clinton Ave",
    "sg:city":"Trenton",
    "sg:classifiers":[
        {
            "category":"Social Services",
            "type":"Services"
        }
    ],
    "sg:phone":"+1 609 396 9186",
    "sg:postcode":"08609",
    "sg:province":"NJ",
    "sg:website":"www.njc.org",
    "wof:name":"Clinton House",
    "wof:placetype":"venue"
},
  "geometry": {"coordinates":[-74.755353,40.221419],"type":"Point"}
}