{
  "type": "Feature",
  "properties": {
    "iso:country":"US",
    "sg:address":"400 Maltese Dr",
    "sg:city":"Totowa",
    "sg:classifiers":[
        {
            "category":"Freight",
            "type":"Transportation"
        }
    ],
    "sg:phone":"+1 973 256 1010",
    "sg:postcode":"07512",
    "sg:province":"NJ",
    "sg:tags":[
        "company",
        "consolidation",
        "trucking"
    ],
    "wof:name":"N C D",
    "wof:placetype":"venue"
},
  "geometry": {"coordinates":[-74.24536500000001,40.90225],"type":"Point"}
}