{
  "type": "Feature",
  "properties": {
    "iso:country":"US",
    "sg:address":"151 Trenton Rd",
    "sg:city":"Browns Mills",
    "sg:classifiers":[
        {
            "category":"Food & Beverages",
            "subcategory":"Groceries & Convenience Stores",
            "type":"Retail Goods"
        }
    ],
    "sg:phone":"+1 609 893 7019",
    "sg:postcode":"08015",
    "sg:province":"NJ",
    "wof:name":"7-Eleven",
    "wof:placetype":"venue"
},
  "geometry": {"coordinates":[-74.585745,39.976425],"type":"Point"}
}