{
  "type": "Feature",
  "properties": {
    "iso:country":"US",
    "sg:address":"319 Amboy Ave",
    "sg:city":"Metuchen",
    "sg:classifiers":[
        {
            "category":"Retail",
            "subcategory":"Funeral Services",
            "type":"Services"
        }
    ],
    "sg:phone":"+1 732 548 2134",
    "sg:postcode":"08840",
    "sg:province":"NJ",
    "sg:tags":[
        "director"
    ],
    "wof:name":"Flynn & Sons/Koyen Funeral Hm",
    "wof:placetype":"venue"
},
  "geometry": {"coordinates":[-74.362489,40.537883],"type":"Point"}
}