{
  "type": "Feature",
  "properties": {
    "addr:full":"13 Broadway Fair Lawn NJ 07410",
    "addr:housenumber":"13",
    "addr:postcode":"07410",
    "addr:street":"Broadway",
    "iso:country":"US",
    "sg:address":"13 Broadway",
    "sg:city":"Fair Lawn",
    "sg:classifiers":[
        {
            "category":"Shopping",
            "type":"Retail Goods"
        }
    ],
    "sg:phone":"+1   ",
    "sg:postcode":"07410",
    "sg:province":"NJ",
    "sg:tags":[
        "merchandise"
    ],
    "wof:name":"Sonotone of Paterson",
    "wof:placetype":"venue"
},
  "geometry": {"coordinates":[-74.121326,40.920178],"type":"Point"}
}