{
  "type": "Feature",
  "properties": {
    "iso:country":"US",
    "sg:address":"151 State Rte 37",
    "sg:city":"Toms River",
    "sg:classifiers":[
        {
            "category":"Health Services",
            "subcategory":"Doctor",
            "type":"Services"
        }
    ],
    "sg:phone":"+1 732 505 1188",
    "sg:postcode":"08755",
    "sg:province":"NJ",
    "sg:tags":[
        "dentist"
    ],
    "wof:name":"Community Dental",
    "wof:placetype":"venue"
},
  "geometry": {"coordinates":[-74.22027,39.965959],"type":"Point"}
}