{
  "type": "Feature",
  "properties": {
    "iso:country":"US",
    "sg:address":"2 Concord Ln",
    "sg:city":"Morristown",
    "sg:classifiers":[
        {
            "category":"Communications",
            "type":"Services"
        }
    ],
    "sg:phone":"+1 973 993 9687",
    "sg:postcode":"07960",
    "sg:province":"NJ",
    "wof:name":"MGB Communications",
    "wof:placetype":"venue"
},
  "geometry": {"coordinates":[-74.457354,40.777502],"type":"Point"}
}