{
  "type": "Feature",
  "properties": {
    "addr:full":"190 Murray St Newark NJ 07114",
    "addr:housenumber":"190",
    "addr:postcode":"07114",
    "addr:street":"Murray St",
    "iso:country":"US",
    "sg:address":"190 Murray St",
    "sg:city":"Newark",
    "sg:classifiers":[
        {
            "category":"Home & Garden",
            "subcategory":"Building Materials",
            "type":"Retail Goods"
        }
    ],
    "sg:phone":"+1 973 643 6700",
    "sg:postcode":"07114",
    "sg:province":"NJ",
    "sg:website":"www.flexibletrim.com",
    "wof:name":"Zago Manufacturing Co Inc",
    "wof:placetype":"venue"
},
  "geometry": {"coordinates":[-74.175068,40.720309],"type":"Point"}
}