{
  "type": "Feature",
  "properties": {
    "addr:full":"520 Devon St Kearny NJ 07032",
    "addr:housenumber":"520",
    "addr:postcode":"07032",
    "addr:street":"Devon St",
    "iso:country":"US",
    "sg:address":"520 Devon St",
    "sg:city":"Kearny",
    "sg:classifiers":[
        {
            "category":"Building & Trades",
            "subcategory":"Construction",
            "type":"Services"
        }
    ],
    "sg:phone":"+1 201 991 0797",
    "sg:postcode":"07032",
    "sg:province":"NJ",
    "sg:tags":[
        "carpentry",
        "contractor"
    ],
    "wof:name":"Entrefolhas Carpentry Inc",
    "wof:placetype":"venue"
},
  "geometry": {"coordinates":[-74.14217499999999,40.769185],"type":"Point"}
}