{
  "type": "Feature",
  "properties": {
    "addr:full":"276 Alpine Dr Paramus NJ 07652",
    "addr:housenumber":"276",
    "addr:postcode":"07652",
    "addr:street":"Alpine Dr",
    "iso:country":"US",
    "sg:address":"276 Alpine Dr",
    "sg:city":"Paramus",
    "sg:classifiers":[
        {
            "category":"Building & Trades",
            "subcategory":"Electrical",
            "type":"Services"
        }
    ],
    "sg:phone":"+1 201 226 0330",
    "sg:postcode":"07652",
    "sg:province":"NJ",
    "sg:tags":[
        "electrical",
        "contractor"
    ],
    "wof:name":"City Lights Electric",
    "wof:placetype":"venue"
},
  "geometry": {"coordinates":[-74.08968400000001,40.935387],"type":"Point"}
}