{
  "type": "Feature",
  "properties": {
    "iso:country":"US",
    "sg:address":"777 North Dr",
    "sg:city":"Brick",
    "sg:classifiers":[
        {
            "category":"Autos & Motor Vehicles",
            "subcategory":"Boat Sales",
            "type":"Retail Goods"
        }
    ],
    "sg:phone":"+1   ",
    "sg:postcode":"08724",
    "sg:province":"NJ",
    "wof:name":"Bob Massey Yacht Sales Inc",
    "wof:placetype":"venue"
},
  "geometry": {"coordinates":[-74.065344,40.058976],"type":"Point"}
}