{
  "type": "Feature",
  "properties": {
    "addr:full":"5th & Berkley Sts Camden NJ 08102",
    "addr:housenumber":"sts",
    "addr:postcode":"08102",
    "iso:country":"US",
    "sg:address":"5th & Berkley Sts",
    "sg:city":"Camden",
    "sg:classifiers":[
        {
            "category":"Education",
            "subcategory":"School",
            "type":"Public Place"
        }
    ],
    "sg:phone":"+1 856 966 8950",
    "sg:postcode":"08102",
    "sg:province":"NJ",
    "sg:tags":[
        "high",
        "middle",
        "elementary"
    ],
    "wof:name":"Camden City School District",
    "wof:placetype":"venue"
},
  "geometry": {"coordinates":[-75.12097300000001,39.939249],"type":"Point"}
}