{
  "type": "Feature",
  "properties": {
    "iso:country":"US",
    "sg:address":"6688 Black Horse Pike",
    "sg:city":"Egg Harbor Twp",
    "sg:classifiers":[
        {
            "category":"Restaurant",
            "type":"Food & Drink"
        }
    ],
    "sg:phone":"+1 609 484 7007",
    "sg:postcode":"08234",
    "sg:province":"NJ",
    "wof:name":"Mc Donald's",
    "wof:placetype":"venue"
},
  "geometry": {"coordinates":[-74.56467499999999,39.407863],"type":"Point"}
}