{
  "type": "Feature",
  "properties": {
    "addr:full":"36 Emley's Hill Rd Cream Ridge NJ 08514",
    "addr:housenumber":"36",
    "addr:postcode":"08514",
    "addr:street":"Emley'S Hill Rd",
    "iso:country":"US",
    "sg:address":"36 Emley's Hill Rd",
    "sg:city":"Cream Ridge",
    "sg:classifiers":[
        {
            "category":"Sports & Exercise",
            "subcategory":"Race Track",
            "type":"Entertainment"
        },
        {
            "category":"Retail",
            "subcategory":"Animal Services",
            "type":"Services"
        }
    ],
    "sg:phone":"+1 609 758 0593",
    "sg:postcode":"08514",
    "sg:province":"NJ",
    "sg:tags":[
        "horse",
        "excavation",
        "contractor",
        "breeder",
        "operation",
        "racing",
        "or"
    ],
    "wof:name":"Low Meadow Farm Inc",
    "wof:placetype":"venue"
},
  "geometry": {"coordinates":[-74.476277,40.13243],"type":"Point"}
}