{
  "type": "Feature",
  "properties": {
    "addr:full":"354 Lynn St Harrington Park NJ 07640",
    "addr:housenumber":"354",
    "addr:postcode":"07640",
    "addr:street":"Lynn St",
    "iso:country":"US",
    "sg:address":"354 Lynn St",
    "sg:city":"Harrington Park",
    "sg:classifiers":[
        {
            "category":"Travel",
            "subcategory":"Travel Agent",
            "type":"Entertainment"
        }
    ],
    "sg:phone":"+1 201 767 3003",
    "sg:postcode":"07640",
    "sg:province":"NJ",
    "sg:tags":[
        "tours",
        "skiing"
    ],
    "sg:website":"www.dspinc.net",
    "wof:name":"DSP Inc",
    "wof:placetype":"venue"
},
  "geometry": {"coordinates":[-73.983507,40.994865],"type":"Point"}
}