{
  "type": "Feature",
  "properties": {
    "iso:country":"US",
    "sg:address":"316 US Hwy 46",
    "sg:city":"Rockaway",
    "sg:classifiers":[
        {
            "category":"Manufacturing",
            "subcategory":"Printing",
            "type":"Manufacturing & Wholesale Goods"
        }
    ],
    "sg:phone":"+1 973 586 1700",
    "sg:postcode":"07866",
    "sg:province":"NJ",
    "sg:tags":[
        "broker"
    ],
    "wof:name":"Printronic Document Solutions",
    "wof:placetype":"venue"
},
  "geometry": {"coordinates":[-74.519361,40.891677],"type":"Point"}
}