{
  "type": "Feature",
  "properties": {
    "addr:full":"1058 S Broad St Trenton NJ 08611",
    "addr:housenumber":"1058",
    "addr:postcode":"08611",
    "addr:street":"S Broad St",
    "iso:country":"US",
    "sg:address":"1058 S Broad St",
    "sg:city":"Trenton",
    "sg:classifiers":[
        {
            "category":"Bars & Pubs",
            "type":"Food & Drink"
        }
    ],
    "sg:phone":"+1   ",
    "sg:postcode":"08611",
    "sg:province":"NJ",
    "sg:tags":[
        "drinking"
    ],
    "wof:name":"Peters Place",
    "wof:placetype":"venue"
},
  "geometry": {"coordinates":[-74.744635,40.20483],"type":"Point"}
}