{
  "type": "Feature",
  "properties": {
    "iso:country":"US",
    "sg:address":"1052 Broadway",
    "sg:city":"Bayonne",
    "sg:classifiers":[
        {
            "category":"Restaurant",
            "type":"Food & Drink"
        }
    ],
    "sg:phone":"+1 201 339 8898",
    "sg:postcode":"07002",
    "sg:province":"NJ",
    "sg:tags":[
        "delicatessen"
    ],
    "wof:name":"St Micheal Gyro & Deli",
    "wof:placetype":"venue"
},
  "geometry": {"coordinates":[-74.101805,40.683372],"type":"Point"}
}