{
  "type": "Feature",
  "properties": {
    "iso:country":"US",
    "sg:address":"46 King George Rd",
    "sg:city":"Green Brook",
    "sg:classifiers":[
        {
            "category":"Autos & Motor Vehicles",
            "subcategory":"Recreational Vehicle Sales",
            "type":"Retail Goods"
        }
    ],
    "sg:phone":"+1 732 868 9077",
    "sg:postcode":"08812",
    "sg:province":"NJ",
    "wof:name":"Bates International",
    "wof:placetype":"venue"
},
  "geometry": {"coordinates":[-74.508847,40.586912],"type":"Point"}
}