{
  "type": "Feature",
  "properties": {
    "addr:full":"25 N Main St Medford NJ 08055",
    "addr:housenumber":"25",
    "addr:postcode":"08055",
    "addr:street":"N Main St",
    "iso:country":"US",
    "sg:address":"25 N Main St",
    "sg:city":"Medford",
    "sg:classifiers":[
        {
            "category":"Health Services",
            "subcategory":"Doctor",
            "type":"Services"
        }
    ],
    "sg:phone":"+1   ",
    "sg:postcode":"08055",
    "sg:province":"NJ",
    "wof:name":"Medford Village Dental Care",
    "wof:placetype":"venue"
},
  "geometry": {"coordinates":[-74.823431,39.900409],"type":"Point"}
}