{
  "type": "Feature",
  "properties": {
    "iso:country":"US",
    "sg:address":"29 Atno Ave",
    "sg:city":"Morristown",
    "sg:classifiers":[
        {
            "category":"Building & Trades",
            "subcategory":"Electrical",
            "type":"Services"
        }
    ],
    "sg:phone":"+1 973 538 2333",
    "sg:postcode":"07960",
    "sg:province":"NJ",
    "sg:tags":[
        "electric",
        "contractor"
    ],
    "wof:name":"Stark Electric",
    "wof:placetype":"venue"
},
  "geometry": {"coordinates":[-74.48499,40.800744],"type":"Point"}
}