{
  "type": "Feature",
  "properties": {
    "addr:full":"269 US Hwy 206 Branchville NJ 07826",
    "addr:housenumber":"269",
    "addr:postcode":"07826",
    "addr:street":"Us Hwy 206",
    "iso:country":"US",
    "sg:address":"269 US Hwy 206",
    "sg:city":"Branchville",
    "sg:classifiers":[
        {
            "category":"Restaurant",
            "type":"Food & Drink"
        }
    ],
    "sg:phone":"+1 973 948 4418",
    "sg:postcode":"07826",
    "sg:province":"NJ",
    "sg:tags":[
        "eating"
    ],
    "wof:name":"De Angelis Restaurant",
    "wof:placetype":"venue"
},
  "geometry": {"coordinates":[-74.80082299999999,41.257779],"type":"Point"}
}