{
  "type": "Feature",
  "properties": {
    "iso:country":"US",
    "sg:address":"111 N Jefferson Rd",
    "sg:city":"Whippany",
    "sg:classifiers":[
        {
            "category":"Professional",
            "type":"Services"
        }
    ],
    "sg:phone":"+1 973 884 2318",
    "sg:postcode":"07981",
    "sg:province":"NJ",
    "sg:tags":[
        "establishment"
    ],
    "wof:name":"Utensco",
    "wof:placetype":"venue"
},
  "geometry": {"coordinates":[-74.425867,40.839358],"type":"Point"}
}