{
  "type": "Feature",
  "properties": {
    "iso:country":"US",
    "sg:address":"30 Kinderkamack Rd",
    "sg:city":"Park Ridge",
    "sg:classifiers":[
        {
            "category":"Building & Trades",
            "subcategory":"Construction",
            "type":"Services"
        }
    ],
    "sg:phone":"+1 201 573 4048",
    "sg:postcode":"07656",
    "sg:province":"NJ",
    "sg:tags":[
        "floor",
        "laying",
        "contractor"
    ],
    "wof:name":"Franco Floor Finishing",
    "wof:placetype":"venue"
},
  "geometry": {"coordinates":[-74.03579999999999,41.027766],"type":"Point"}
}