{
  "type": "Feature",
  "properties": {
    "iso:country":"US",
    "sg:address":"5 New St",
    "sg:city":"High Bridge",
    "sg:classifiers":[
        {
            "category":"Building & Trades",
            "subcategory":"Cleaning & Sanitation",
            "type":"Services"
        }
    ],
    "sg:phone":"+1 908 638 8985",
    "sg:postcode":"08829",
    "sg:province":"NJ",
    "sg:tags":[
        "home",
        "window"
    ],
    "sg:website":"www.dynakleen.net",
    "wof:name":"Dynakleen",
    "wof:placetype":"venue"
},
  "geometry": {"coordinates":[-74.89160200000001,40.669498],"type":"Point"}
}