{
  "type": "Feature",
  "properties": {
    "addr:full":"274 Main St West Orange NJ 07052",
    "addr:housenumber":"274",
    "addr:postcode":"07052",
    "addr:street":"Main St",
    "iso:country":"US",
    "sg:address":"274 Main St",
    "sg:city":"West Orange",
    "sg:classifiers":[
        {
            "category":"Bars & Pubs",
            "type":"Food & Drink"
        }
    ],
    "sg:phone":"+1   ",
    "sg:postcode":"07052",
    "sg:province":"NJ",
    "sg:tags":[
        "tavern"
    ],
    "wof:name":"Tory Corner Tavern",
    "wof:placetype":"venue"
},
  "geometry": {"coordinates":[-74.23128699999999,40.787465],"type":"Point"}
}