{
  "type": "Feature",
  "properties": {
    "addr:full":"6 Orange Pl West Orange NJ 07052",
    "addr:housenumber":"6",
    "addr:postcode":"07052",
    "addr:street":"Orange Pl",
    "iso:country":"US",
    "sg:address":"6 Orange Pl",
    "sg:city":"West Orange",
    "sg:classifiers":[
        {
            "category":"Real Estate",
            "subcategory":"Real Estate Agent",
            "type":"Services"
        }
    ],
    "sg:phone":"+1 973 243 9330",
    "sg:postcode":"07052",
    "sg:province":"NJ",
    "sg:website":"www.cassrealtors.com",
    "wof:name":"Cass Inc Realty",
    "wof:placetype":"venue"
},
  "geometry": {"coordinates":[-74.232365,40.792685],"type":"Point"}
}