{
  "type": "Feature",
  "properties": {
    "addr:full":"315 Rahway Ave Elizabeth NJ 07202",
    "addr:housenumber":"315",
    "addr:postcode":"07202",
    "addr:street":"Rahway Ave",
    "iso:country":"US",
    "sg:address":"315 Rahway Ave",
    "sg:city":"Elizabeth",
    "sg:classifiers":[
        {
            "category":"Professional",
            "subcategory":"Lawyer & Legal Services",
            "type":"Services"
        }
    ],
    "sg:phone":"+1 908 289 5111",
    "sg:postcode":"07202",
    "sg:province":"NJ",
    "sg:tags":[
        "attorney"
    ],
    "wof:name":"Philip E Di Giovanni",
    "wof:placetype":"venue"
},
  "geometry": {"coordinates":[-74.225437,40.658467],"type":"Point"}
}