{
  "type": "Feature",
  "properties": {
    "iso:country":"US",
    "sg:address":"73 US Highway 46",
    "sg:city":"Fairfield",
    "sg:classifiers":[
        {
            "category":"Building & Trades",
            "subcategory":"Locksmith",
            "type":"Services"
        },
        {
            "category":"Retail",
            "subcategory":"Auto Repair",
            "type":"Services"
        }
    ],
    "sg:phone":"+1 973 882 0350",
    "sg:postcode":"07004",
    "sg:province":"NJ",
    "sg:tags":[
        "key"
    ],
    "wof:name":"Karis Lock Co",
    "wof:placetype":"venue"
},
  "geometry": {"coordinates":[-74.31289700000001,40.867699],"type":"Point"}
}