{
  "type": "Feature",
  "properties": {
    "addr:full":"224 State Rte 35 Pt Pleasant Bch NJ 08742",
    "addr:housenumber":"224",
    "addr:postcode":"08742",
    "addr:street":"State Rte 35 Pt",
    "iso:country":"US",
    "sg:address":"224 State Rte 35",
    "sg:city":"Pt Pleasant Bch",
    "sg:classifiers":[
        {
            "category":"Autos & Motor Vehicles",
            "subcategory":"Fuel & Gas Station",
            "type":"Retail Goods"
        }
    ],
    "sg:phone":"+1 732 295 3377",
    "sg:postcode":"08742",
    "sg:province":"NJ",
    "sg:tags":[
        "oil"
    ],
    "wof:name":"Prospect Point Sunoco",
    "wof:placetype":"venue"
},
  "geometry": {"coordinates":[-74.042911,40.074011],"type":"Point"}
}