{
  "type": "Feature",
  "properties": {
    "iso:country":"US",
    "sg:address":"570 Piermont Rd",
    "sg:city":"Closter",
    "sg:classifiers":[
        {
            "category":"Personal",
            "subcategory":"Barber",
            "type":"Services"
        }
    ],
    "sg:phone":"+1 201 767 4541",
    "sg:postcode":"07624",
    "sg:province":"NJ",
    "sg:tags":[
        "shop"
    ],
    "wof:name":"Yang Dong Barber Shop",
    "wof:placetype":"venue"
},
  "geometry": {"coordinates":[-73.952935,40.9685],"type":"Point"}
}