{
  "type": "Feature",
  "properties": {
    "addr:full":"508 Broad Ave Palisades Park NJ 07650",
    "addr:housenumber":"508",
    "addr:postcode":"07650",
    "addr:street":"Broad Ave",
    "iso:country":"US",
    "sg:address":"508 Broad Ave",
    "sg:city":"Palisades Park",
    "sg:classifiers":[
        {
            "category":"Professional",
            "subcategory":"Business Services",
            "type":"Services"
        }
    ],
    "sg:phone":"+1 201 461 3984",
    "sg:postcode":"07650",
    "sg:province":"NJ",
    "wof:name":"Park Brothers Corporation",
    "wof:placetype":"venue"
},
  "geometry": {"coordinates":[-73.993756,40.853404],"type":"Point"}
}