{
  "type": "Feature",
  "properties": {
    "addr:full":"1346 Saint Georges Ave Avenel NJ 07001",
    "addr:housenumber":"1346",
    "addr:postcode":"07001",
    "addr:street":"Saint Georges Ave",
    "iso:country":"US",
    "sg:address":"1346 Saint Georges Ave",
    "sg:city":"Avenel",
    "sg:classifiers":[
        {
            "category":"Food & Beverages",
            "subcategory":"Bakery",
            "type":"Retail Goods"
        }
    ],
    "sg:phone":"+1   ",
    "sg:postcode":"07001",
    "sg:province":"NJ",
    "wof:name":"LAfaire Bakery",
    "wof:placetype":"venue"
},
  "geometry": {"coordinates":[-74.29272899999999,40.584577],"type":"Point"}
}