{
  "type": "Feature",
  "properties": {
    "addr:full":"443 Orange St Newark NJ 07107",
    "addr:housenumber":"443",
    "addr:postcode":"07107",
    "addr:street":"Orange St",
    "iso:country":"US",
    "sg:address":"443 Orange St",
    "sg:city":"Newark",
    "sg:classifiers":[
        {
            "category":"Wholesale",
            "subcategory":"Jewelry",
            "type":"Manufacturing & Wholesale Goods"
        }
    ],
    "sg:phone":"+1 973 481 9100",
    "sg:postcode":"07107",
    "sg:province":"NJ",
    "sg:tags":[
        "stone"
    ],
    "wof:name":"Gold & Silver Exchange",
    "wof:placetype":"venue"
},
  "geometry": {"coordinates":[-74.188901,40.752741],"type":"Point"}
}