{
  "type": "Feature",
  "properties": {
    "addr:full":"9416 Ventnor Ave Margate City NJ 08402",
    "addr:housenumber":"9416",
    "addr:postcode":"08402",
    "addr:street":"Ventnor Ave Margate",
    "iso:country":"US",
    "sg:address":"9416 Ventnor Ave",
    "sg:city":"Margate City",
    "sg:classifiers":[
        {
            "category":"Social Services",
            "subcategory":"Child Care",
            "type":"Services"
        },
        {
            "category":"Personal",
            "subcategory":"Beauty Salon",
            "type":"Services"
        }
    ],
    "sg:phone":"+1 609 823 6900",
    "sg:postcode":"08402",
    "sg:province":"NJ",
    "sg:tags":[
        "spa",
        "day"
    ],
    "wof:name":"Serenity Day Spa",
    "wof:placetype":"venue"
},
  "geometry": {"coordinates":[-74.515452,39.321411],"type":"Point"}
}