{
  "type": "Feature",
  "properties": {
    "addr:full":"41 Tompkins Point Rd Newark NJ 07114",
    "addr:housenumber":"41",
    "addr:postcode":"07114",
    "addr:street":"Tompkins Point Rd",
    "iso:country":"US",
    "sg:address":"41 Tompkins Point Rd",
    "sg:city":"Newark",
    "sg:classifiers":[
        {
            "category":"Professional",
            "subcategory":"Research",
            "type":"Services"
        }
    ],
    "sg:phone":"+1 973 824 7555",
    "sg:postcode":"07114",
    "sg:province":"NJ",
    "sg:tags":[
        "environmental",
        "ecological"
    ],
    "sg:website":"www.cleanharbors.com",
    "wof:name":"Clean Harbors Environmental",
    "wof:placetype":"venue"
},
  "geometry": {"coordinates":[-74.170286,40.71923],"type":"Point"}
}