{
  "type": "Feature",
  "properties": {
    "iso:country":"US",
    "sg:address":"210 Mountain Ave",
    "sg:city":"Springfield",
    "sg:classifiers":[
        {
            "category":"Government",
            "subcategory":"Post Office",
            "type":"Public Place"
        }
    ],
    "sg:phone":"+1 973 564 6184",
    "sg:postcode":"07081",
    "sg:province":"NJ",
    "sg:tags":[
        "postal",
        "us"
    ],
    "wof:name":"US Post Office",
    "wof:placetype":"venue"
},
  "geometry": {"coordinates":[-74.317094,40.705162],"type":"Point"}
}