{
  "type": "Feature",
  "properties": {
    "addr:full":"81 Vesey St Newark NJ 07105",
    "addr:housenumber":"81",
    "addr:postcode":"07105",
    "addr:street":"Vesey St",
    "iso:country":"US",
    "sg:address":"81 Vesey St",
    "sg:city":"Newark",
    "sg:classifiers":[
        {
            "category":"Building & Trades",
            "subcategory":"Construction",
            "type":"Services"
        }
    ],
    "sg:phone":"+1   ",
    "sg:postcode":"07105",
    "sg:province":"NJ",
    "sg:tags":[
        "contractor",
        "general",
        "developer"
    ],
    "wof:name":"Highland Port Development",
    "wof:placetype":"venue"
},
  "geometry": {"coordinates":[-74.168198,40.723647],"type":"Point"}
}