{
  "type": "Feature",
  "properties": {
    "addr:full":"425 Belmont Ave Haledon NJ 07508",
    "addr:housenumber":"425",
    "addr:postcode":"07508",
    "addr:street":"Belmont Ave",
    "iso:country":"US",
    "sg:address":"425 Belmont Ave",
    "sg:city":"Haledon",
    "sg:classifiers":[
        {
            "category":"Personal",
            "subcategory":"Beauty Salon",
            "type":"Services"
        }
    ],
    "sg:phone":"+1 973 790 5434",
    "sg:postcode":"07508",
    "sg:province":"NJ",
    "sg:tags":[
        "shop"
    ],
    "wof:name":"Patti's Place",
    "wof:placetype":"venue"
},
  "geometry": {"coordinates":[-74.184864,40.937245],"type":"Point"}
}