{
  "type": "Feature",
  "properties": {
    "addr:full":"107 Bergen St Harrison NJ 07029",
    "addr:housenumber":"107",
    "addr:postcode":"07029",
    "addr:street":"Bergen St",
    "iso:country":"US",
    "sg:address":"107 Bergen St",
    "sg:city":"Harrison",
    "sg:classifiers":[
        {
            "category":"Professional",
            "subcategory":"Art Services",
            "type":"Services"
        }
    ],
    "sg:phone":"+1 973 483 6193",
    "sg:postcode":"07029",
    "sg:province":"NJ",
    "sg:tags":[
        "commercial",
        "design"
    ],
    "wof:name":"J Correia Graphic Arts",
    "wof:placetype":"venue"
},
  "geometry": {"coordinates":[-74.16022100000001,40.742959],"type":"Point"}
}