{
  "type": "Feature",
  "properties": {
    "addr:full":"648 Winthrop Rd Teaneck NJ 07666",
    "addr:housenumber":"648",
    "addr:postcode":"07666",
    "addr:street":"Winthrop Rd",
    "iso:country":"US",
    "sg:address":"648 Winthrop Rd",
    "sg:city":"Teaneck",
    "sg:classifiers":[
        {
            "category":"Recreation",
            "type":"Entertainment"
        }
    ],
    "sg:phone":"+1 201 836 4081",
    "sg:postcode":"07666",
    "sg:province":"NJ",
    "wof:name":"Nesheemah Yoga Center LLC",
    "wof:placetype":"venue"
},
  "geometry": {"coordinates":[-74.018383,40.911166],"type":"Point"}
}