{
  "type": "Feature",
  "properties": {
    "addr:full":"70 Grand Ave River Edge NJ 07661",
    "addr:housenumber":"70",
    "addr:postcode":"07661",
    "addr:street":"Grand Ave",
    "iso:country":"US",
    "sg:address":"70 Grand Ave",
    "sg:city":"River Edge",
    "sg:classifiers":[
        {
            "category":"Professional",
            "subcategory":"Lawyer & Legal Services",
            "type":"Services"
        }
    ],
    "sg:phone":"+1 201 488 7707",
    "sg:postcode":"07661",
    "sg:province":"NJ",
    "sg:tags":[
        "attorney"
    ],
    "wof:name":"Paul B Brickfield Law Offices",
    "wof:placetype":"venue"
},
  "geometry": {"coordinates":[-74.036824,40.910942],"type":"Point"}
}