{
  "type": "Feature",
  "properties": {
    "iso:country":"US",
    "sg:address":"321 6th Ave",
    "sg:city":"Asbury Park",
    "sg:classifiers":[
        {
            "category":"Professional",
            "type":"Services"
        }
    ],
    "sg:phone":"+1 732 775 7784",
    "sg:postcode":"07712",
    "sg:province":"NJ",
    "sg:tags":[
        "establishment"
    ],
    "wof:name":"IPCM Inc",
    "wof:placetype":"venue"
},
  "geometry": {"coordinates":[-74.00288399999999,40.226756],"type":"Point"}
}