{
  "type": "Feature",
  "properties": {
    "iso:country":"US",
    "sg:address":"143 William St",
    "sg:city":"South River",
    "sg:classifiers":[
        {
            "category":"Wholesale",
            "subcategory":"Durable Goods & Equipment",
            "type":"Manufacturing & Wholesale Goods"
        }
    ],
    "sg:phone":"+1 732 238 7300",
    "sg:postcode":"08882",
    "sg:province":"NJ",
    "sg:tags":[
        "science",
        "product"
    ],
    "wof:name":"Effective Education Systems",
    "wof:placetype":"venue"
},
  "geometry": {"coordinates":[-74.390505,40.460987],"type":"Point"}
}