{
  "type": "Feature",
  "properties": {
    "iso:country":"US",
    "sg:address":"1580 Dutch Mill Rd",
    "sg:city":"Franklinville",
    "sg:classifiers":[
        {
            "category":"Professional",
            "subcategory":"Management & Consulting",
            "type":"Services"
        }
    ],
    "sg:phone":"+1   ",
    "sg:postcode":"08322",
    "sg:province":"NJ",
    "sg:tags":[
        "retail",
        "direct",
        "sales"
    ],
    "wof:name":"Afua Chez",
    "wof:placetype":"venue"
},
  "geometry": {"coordinates":[-74.996314,39.57985],"type":"Point"}
}