{
  "type": "Feature",
  "properties": {
    "addr:full":"9 Spruce Ct Bedminster NJ 07921",
    "addr:housenumber":"9",
    "addr:postcode":"07921",
    "addr:street":"Spruce Ct",
    "iso:country":"US",
    "sg:address":"9 Spruce Ct",
    "sg:city":"Bedminster",
    "sg:classifiers":[
        {
            "category":"Home & Garden",
            "subcategory":"Building Materials",
            "type":"Retail Goods"
        }
    ],
    "sg:phone":"+1 908 901 9511",
    "sg:postcode":"07921",
    "sg:province":"NJ",
    "sg:tags":[
        "paint"
    ],
    "wof:name":"A 1 Painting",
    "wof:placetype":"venue"
},
  "geometry": {"coordinates":[-74.630989,40.647776],"type":"Point"}
}