{
  "type": "Feature",
  "properties": {
    "iso:country":"US",
    "sg:address":"1721 Irving St",
    "sg:city":"Rahway",
    "sg:classifiers":[
        {
            "category":"Retail",
            "subcategory":"Laundry & Dry Cleaning",
            "type":"Services"
        }
    ],
    "sg:phone":"+1 732 574 1481",
    "sg:postcode":"07065",
    "sg:province":"NJ",
    "wof:name":"Joy Cleaners",
    "wof:placetype":"venue"
},
  "geometry": {"coordinates":[-74.2771,40.611198],"type":"Point"}
}