{
  "type": "Feature",
  "properties": {
    "addr:full":"19 Exeter Rd Jersey City NJ 07305",
    "addr:housenumber":"19",
    "addr:postcode":"07305",
    "addr:street":"Exeter Rd",
    "iso:country":"US",
    "sg:address":"19 Exeter Rd",
    "sg:city":"Jersey City",
    "sg:classifiers":[
        {
            "category":"Building & Trades",
            "subcategory":"Construction",
            "type":"Services"
        }
    ],
    "sg:phone":"+1 201 435 6114",
    "sg:postcode":"07305",
    "sg:province":"NJ",
    "sg:tags":[
        "house"
    ],
    "wof:name":"Al S Roofing & Home Imp",
    "wof:placetype":"venue"
},
  "geometry": {"coordinates":[-74.102671,40.697954],"type":"Point"}
}