{
  "type": "Feature",
  "properties": {
    "iso:country":"US",
    "sg:address":"423 Shades of Death Rd",
    "sg:city":"Great Meadows",
    "sg:classifiers":[
        {
            "category":"Professional",
            "subcategory":"Computer Services",
            "type":"Services"
        }
    ],
    "sg:phone":"+1 908 852 6738",
    "sg:postcode":"07838",
    "sg:province":"NJ",
    "sg:tags":[
        "related"
    ],
    "wof:name":"Graven Technologies",
    "wof:placetype":"venue"
},
  "geometry": {"coordinates":[-74.87376,40.932546],"type":"Point"}
}