{
  "type": "Feature",
  "properties": {
    "iso:country":"US",
    "sg:address":"374 Clifton Ave",
    "sg:city":"Lakewood",
    "sg:classifiers":[
        {
            "category":"Shopping",
            "subcategory":"Shoes",
            "type":"Retail Goods"
        }
    ],
    "sg:phone":"+1   ",
    "sg:postcode":"08701",
    "sg:province":"NJ",
    "wof:name":"Kleins Shoes",
    "wof:placetype":"venue"
},
  "geometry": {"coordinates":[-74.21495899999999,40.093339],"type":"Point"}
}