{
  "type": "Feature",
  "properties": {
    "iso:country":"US",
    "sg:address":"24 Meadow Ln",
    "sg:city":"Pennington",
    "sg:classifiers":[
        {
            "category":"Professional",
            "subcategory":"Business Services",
            "type":"Services"
        }
    ],
    "sg:phone":"+1   ",
    "sg:postcode":"08534",
    "sg:province":"NJ",
    "wof:name":"Brooke Graziano Interiors",
    "wof:placetype":"venue"
},
  "geometry": {"coordinates":[-74.750469,40.346856],"type":"Point"}
}