{
  "type": "Feature",
  "properties": {
    "addr:full":"49 S Summit St Bergenfield NJ 07621",
    "addr:housenumber":"49",
    "addr:postcode":"07621",
    "addr:street":"S Summit St",
    "iso:country":"US",
    "sg:address":"49 S Summit St",
    "sg:city":"Bergenfield",
    "sg:classifiers":[
        {
            "category":"Education",
            "subcategory":"School",
            "type":"Public Place"
        }
    ],
    "sg:phone":"+1   ",
    "sg:postcode":"07621",
    "sg:province":"NJ",
    "wof:name":"Washington Elementary School",
    "wof:placetype":"venue"
},
  "geometry": {"coordinates":[-73.99341099999999,40.927711],"type":"Point"}
}