{
  "type": "Feature",
  "properties": {
    "addr:full":"2095 State Rte 70 Cherry Hill NJ 08003",
    "addr:housenumber":"2095",
    "addr:postcode":"08003",
    "addr:street":"State Rte 70",
    "iso:country":"US",
    "sg:address":"2095 State Rte 70",
    "sg:city":"Cherry Hill",
    "sg:classifiers":[
        {
            "category":"Home & Garden",
            "subcategory":"Hardware",
            "type":"Retail Goods"
        }
    ],
    "sg:phone":"+1   ",
    "sg:postcode":"08003",
    "sg:province":"NJ",
    "sg:website":"www.acehardware.com",
    "wof:name":"Ace Hardware",
    "wof:placetype":"venue"
},
  "geometry": {"coordinates":[-74.95227,39.897687],"type":"Point"}
}