{
  "type": "Feature",
  "properties": {
    "addr:full":"4501 Dell Ave North Bergen NJ 07047",
    "addr:housenumber":"4501",
    "addr:postcode":"07047",
    "addr:street":"Dell Ave",
    "iso:country":"US",
    "sg:address":"4501 Dell Ave",
    "sg:city":"North Bergen",
    "sg:classifiers":[
        {
            "category":"Wholesale",
            "subcategory":"Groceries",
            "type":"Manufacturing & Wholesale Goods"
        }
    ],
    "sg:phone":"+1 201 770 9988",
    "sg:postcode":"07047",
    "sg:province":"NJ",
    "sg:tags":[
        "beverage"
    ],
    "wof:name":"668 Beverage Wrhse Wholesale",
    "wof:placetype":"venue"
},
  "geometry": {"coordinates":[-74.03510300000001,40.785515],"type":"Point"}
}