{
  "type": "Feature",
  "properties": {
    "addr:full":"421 State Rte 79 Morganville NJ 07751",
    "addr:housenumber":"421",
    "addr:postcode":"07751",
    "addr:street":"State Rte 79",
    "iso:country":"US",
    "sg:address":"421 State Rte 79",
    "sg:city":"Morganville",
    "sg:classifiers":[
        {
            "category":"Professional",
            "subcategory":"Lawyer & Legal Services",
            "type":"Services"
        }
    ],
    "sg:phone":"+1 732 617 6166",
    "sg:postcode":"07751",
    "sg:province":"NJ",
    "sg:tags":[
        "attorney"
    ],
    "wof:name":"Lawrence S Grossman",
    "wof:placetype":"venue"
},
  "geometry": {"coordinates":[-74.244733,40.376103],"type":"Point"}
}