{
  "type": "Feature",
  "properties": {
    "iso:country":"US",
    "sg:address":"611 Bergen Blvd",
    "sg:city":"Ridgefield",
    "sg:classifiers":[
        {
            "category":"Shopping",
            "subcategory":"Used Merchandise",
            "type":"Retail Goods"
        }
    ],
    "sg:phone":"+1 201 945 5577",
    "sg:postcode":"07657",
    "sg:province":"NJ",
    "sg:tags":[
        "antique"
    ],
    "wof:name":"Cello Antiques",
    "wof:placetype":"venue"
},
  "geometry": {"coordinates":[-73.99479700000001,40.8284],"type":"Point"}
}