{
  "type": "Feature",
  "properties": {
    "addr:full":"66 Parsonage Rd Edison NJ 08837",
    "addr:housenumber":"66",
    "addr:postcode":"08837",
    "addr:street":"Parsonage Rd",
    "iso:country":"US",
    "sg:address":"66 Parsonage Rd",
    "sg:city":"Edison",
    "sg:classifiers":[
        {
            "category":"Shopping",
            "subcategory":"Computers & Home Electronics",
            "type":"Retail Goods"
        }
    ],
    "sg:phone":"+1 732 321 5506",
    "sg:postcode":"08837",
    "sg:province":"NJ",
    "sg:tags":[
        "equipment",
        "dealer"
    ],
    "wof:name":"Apple Store",
    "wof:placetype":"venue"
},
  "geometry": {"coordinates":[-74.333326,40.547653],"type":"Point"}
}