{
  "type": "Feature",
  "properties": {
    "addr:full":"580 Newark Ave Jersey City NJ 07306",
    "addr:housenumber":"580",
    "addr:postcode":"07306",
    "addr:street":"Newark Ave",
    "iso:country":"US",
    "sg:address":"580 Newark Ave",
    "sg:city":"Jersey City",
    "sg:classifiers":[
        {
            "category":"Professional",
            "subcategory":"Lawyer & Legal Services",
            "type":"Services"
        }
    ],
    "sg:phone":"+1 201 656 6504",
    "sg:postcode":"07306",
    "sg:province":"NJ",
    "sg:tags":[
        "attorney"
    ],
    "wof:name":"Patrick G Patel",
    "wof:placetype":"venue"
},
  "geometry": {"coordinates":[-74.057024,40.732022],"type":"Point"}
}