{
  "type": "Feature",
  "properties": {
    "iso:country":"US",
    "sg:address":"2 Dena Ct",
    "sg:city":"Park Ridge",
    "sg:classifiers":[
        {
            "category":"Manufacturing",
            "subcategory":"Metals",
            "type":"Manufacturing & Wholesale Goods"
        },
        {
            "category":"Home & Garden",
            "subcategory":"Garden Supply",
            "type":"Retail Goods"
        }
    ],
    "sg:phone":"+1 201 930 0199",
    "sg:postcode":"07656",
    "sg:province":"NJ",
    "sg:tags":[
        "fitting",
        "cont",
        "sprinkler",
        "mfg"
    ],
    "wof:name":"Aqua-Duck Inc",
    "wof:placetype":"venue"
},
  "geometry": {"coordinates":[-74.063126,41.035624],"type":"Point"}
}