{
  "type": "Feature",
  "properties": {
    "addr:full":"319 Washington St Hoboken NJ 07030",
    "addr:housenumber":"319",
    "addr:postcode":"07030",
    "addr:street":"Washington St",
    "iso:country":"US",
    "sg:address":"319 Washington St",
    "sg:city":"Hoboken",
    "sg:classifiers":[
        {
            "category":"Fast Food",
            "type":"Food & Drink"
        }
    ],
    "sg:phone":"+1 201 683 3273",
    "sg:postcode":"07030",
    "sg:province":"NJ",
    "sg:tags":[
        "burger"
    ],
    "sg:website":"www.gofiveguys.com",
    "wof:name":"Five Guys Famous Burgers & Fries",
    "wof:placetype":"venue"
},
  "geometry": {"coordinates":[-74.029582,40.740569],"type":"Point"}
}