{
  "type": "Feature",
  "properties": {
    "iso:country":"US",
    "sg:address":"110 Halsey St",
    "sg:city":"Newark",
    "sg:classifiers":[
        {
            "category":"Professional",
            "type":"Services"
        }
    ],
    "sg:phone":"+1   ",
    "sg:postcode":"07102",
    "sg:province":"NJ",
    "wof:name":"Vinyl Room Com LLC",
    "wof:placetype":"venue"
},
  "geometry": {"coordinates":[-74.17226100000001,40.738527],"type":"Point"}
}