{
  "type": "Feature",
  "properties": {
    "addr:full":"159 McAdoo Ave Jersey City NJ 07305",
    "addr:housenumber":"159",
    "addr:postcode":"07305",
    "addr:street":"Mcadoo Ave",
    "iso:country":"US",
    "sg:address":"159 McAdoo Ave",
    "sg:city":"Jersey City",
    "sg:classifiers":[
        {
            "category":"Arts & Performance",
            "subcategory":"Theater",
            "type":"Entertainment"
        }
    ],
    "sg:phone":"+1 201 725 6788",
    "sg:postcode":"07305",
    "sg:province":"NJ",
    "sg:tags":[
        "theatrical"
    ],
    "wof:name":"Milieu Entertainment",
    "wof:placetype":"venue"
},
  "geometry": {"coordinates":[-74.0942,40.704095],"type":"Point"}
}