{
  "type": "Feature",
  "properties": {
    "addr:full":"229 Kinderkamack Rd Oradell NJ 07649",
    "addr:housenumber":"229",
    "addr:postcode":"07649",
    "addr:street":"Kinderkamack Rd",
    "iso:country":"US",
    "sg:address":"229 Kinderkamack Rd",
    "sg:city":"Oradell",
    "sg:classifiers":[
        {
            "category":"Professional",
            "subcategory":"Accounting & Tax Preparation",
            "type":"Services"
        }
    ],
    "sg:phone":"+1   ",
    "sg:postcode":"07649",
    "sg:province":"NJ",
    "sg:tags":[
        "sc",
        "return"
    ],
    "wof:name":"H & R Block",
    "wof:placetype":"venue"
},
  "geometry": {"coordinates":[-74.031294,40.947651],"type":"Point"}
}