{
  "type": "Feature",
  "properties": {
    "iso:country":"US",
    "sg:address":"37 Lenape Trl",
    "sg:city":"Vincentown",
    "sg:classifiers":[
        {
            "category":"Building & Trades",
            "subcategory":"Construction",
            "type":"Services"
        }
    ],
    "sg:phone":"+1 609 261 0292",
    "sg:postcode":"08088",
    "sg:province":"NJ",
    "sg:tags":[
        "repair",
        "general"
    ],
    "wof:name":"S & R Repairs",
    "wof:placetype":"venue"
},
  "geometry": {"coordinates":[-74.7323,39.979755],"type":"Point"}
}