{
  "type": "Feature",
  "properties": {
    "addr:full":"2215 Merchantville Ave Pennsauken NJ 08110",
    "addr:housenumber":"2215",
    "addr:postcode":"08110",
    "addr:street":"Merchantville Ave",
    "iso:country":"US",
    "sg:address":"2215 Merchantville Ave",
    "sg:city":"Pennsauken",
    "sg:classifiers":[
        {
            "category":"Government",
            "subcategory":"Fire Station",
            "type":"Public Place"
        }
    ],
    "sg:phone":"+1 856 663 1313",
    "sg:postcode":"08110",
    "sg:province":"NJ",
    "sg:tags":[
        "department"
    ],
    "wof:name":"Pennsauken Volunteer Fire Co",
    "wof:placetype":"venue"
},
  "geometry": {"coordinates":[-75.060906,39.959634],"type":"Point"}
}