{
  "type": "Feature",
  "properties": {
    "iso:country":"US",
    "sg:address":"14 N Stiles Ave",
    "sg:city":"Maple Shade",
    "sg:classifiers":[
        {
            "category":"Building & Trades",
            "subcategory":"Plumbing",
            "type":"Services"
        }
    ],
    "sg:phone":"+1 856 665 6167",
    "sg:postcode":"08052",
    "sg:province":"NJ",
    "sg:tags":[
        "plumbing",
        "contractor"
    ],
    "wof:name":"Bukowski Plumbing",
    "wof:placetype":"venue"
},
  "geometry": {"coordinates":[-74.995445,39.957999],"type":"Point"}
}