{
  "type": "Feature",
  "properties": {
    "iso:country":"US",
    "sg:address":"2002 State Rte 31",
    "sg:city":"Clinton",
    "sg:classifiers":[
        {
            "category":"Retail",
            "subcategory":"Auto Rental",
            "type":"Services"
        }
    ],
    "sg:phone":"+1 908 638 8333",
    "sg:postcode":"08809",
    "sg:province":"NJ",
    "sg:tags":[
        "renting",
        "automobile",
        "passenger",
        "car"
    ],
    "wof:name":"Enterprise Rent A Car",
    "wof:placetype":"venue"
},
  "geometry": {"coordinates":[-74.915142,40.671148],"type":"Point"}
}