{
  "type": "Feature",
  "properties": {
    "addr:full":"208 Main St Asbury Park NJ 07712",
    "addr:housenumber":"208",
    "addr:postcode":"07712",
    "addr:street":"Main St Asbury",
    "iso:country":"US",
    "sg:address":"208 Main St",
    "sg:city":"Asbury Park",
    "sg:classifiers":[
        {
            "category":"Professional",
            "subcategory":"Lawyer & Legal Services",
            "type":"Services"
        }
    ],
    "sg:phone":"+1 732 774 5520",
    "sg:postcode":"07712",
    "sg:province":"NJ",
    "wof:name":"Jules Rossi",
    "wof:placetype":"venue"
},
  "geometry": {"coordinates":[-74.013077,40.21662],"type":"Point"}
}