{
  "type": "Feature",
  "properties": {
    "addr:full":"43 Naden Ave Irvington NJ 07111",
    "addr:housenumber":"43",
    "addr:postcode":"07111",
    "addr:street":"Naden Ave",
    "iso:country":"US",
    "sg:address":"43 Naden Ave",
    "sg:city":"Irvington",
    "sg:classifiers":[
        {
            "category":"Professional",
            "subcategory":"Art Services",
            "type":"Services"
        }
    ],
    "sg:phone":"+1   ",
    "sg:postcode":"07111",
    "sg:province":"NJ",
    "sg:tags":[
        "commercial",
        "design"
    ],
    "wof:name":"Golden Boy Graphics",
    "wof:placetype":"venue"
},
  "geometry": {"coordinates":[-74.24128899999999,40.712204],"type":"Point"}
}