{
  "type": "Feature",
  "properties": {
    "addr:full":"935 Lincoln Blvd Middlesex NJ 08846",
    "addr:housenumber":"935",
    "addr:postcode":"08846",
    "addr:street":"Lincoln Blvd",
    "iso:country":"US",
    "sg:address":"935 Lincoln Blvd",
    "sg:city":"Middlesex",
    "sg:classifiers":[
        {
            "category":"Building & Trades",
            "subcategory":"Construction",
            "type":"Services"
        }
    ],
    "sg:phone":"+1 732 271 1416",
    "sg:postcode":"08846",
    "sg:province":"NJ",
    "sg:tags":[
        "contractor"
    ],
    "wof:name":"Zimbo Construction Inc",
    "wof:placetype":"venue"
},
  "geometry": {"coordinates":[-74.485922,40.577095],"type":"Point"}
}