{
  "type": "Feature",
  "properties": {
    "iso:country":"US",
    "sg:address":"223 Exeter St",
    "sg:city":"Highland Park",
    "sg:classifiers":[
        {
            "category":"Retail",
            "subcategory":"Auto Repair",
            "type":"Services"
        }
    ],
    "sg:phone":"+1   ",
    "sg:postcode":"08904",
    "sg:province":"NJ",
    "sg:tags":[
        "general"
    ],
    "wof:name":"Fbn Auto Service",
    "wof:placetype":"venue"
},
  "geometry": {"coordinates":[-74.41242800000001,40.501467],"type":"Point"}
}