{
  "type": "Feature",
  "properties": {
    "addr:full":"270 North St Teterboro NJ 07608",
    "addr:housenumber":"270",
    "addr:postcode":"07608",
    "addr:street":"North St",
    "iso:country":"US",
    "sg:address":"270 North St",
    "sg:city":"Teterboro",
    "sg:classifiers":[
        {
            "category":"Home & Garden",
            "subcategory":"Hardware",
            "type":"Retail Goods"
        },
        {
            "category":"Manufacturing",
            "subcategory":"Lumber",
            "type":"Manufacturing & Wholesale Goods"
        }
    ],
    "sg:phone":"+1 201 736 5282",
    "sg:postcode":"07608",
    "sg:province":"NJ",
    "sg:tags":[
        "company",
        "used",
        "logging",
        "tool"
    ],
    "wof:name":"American Logging Tool Co",
    "wof:placetype":"venue"
},
  "geometry": {"coordinates":[-74.055171,40.866093],"type":"Point"}
}