{
  "type": "Feature",
  "properties": {
    "iso:country":"US",
    "sg:address":"36 Sunnyside Rd",
    "sg:city":"Mahwah",
    "sg:classifiers":[
        {
            "category":"Professional",
            "subcategory":"Lawyer & Legal Services",
            "type":"Services"
        }
    ],
    "sg:phone":"+1   ",
    "sg:postcode":"07430",
    "sg:province":"NJ",
    "wof:name":"Robert J English Esq",
    "wof:placetype":"venue"
},
  "geometry": {"coordinates":[-74.130224,41.092501],"type":"Point"}
}