{
  "type": "Feature",
  "properties": {
    "iso:country":"US",
    "sg:address":"602 Prospect St",
    "sg:city":"Westfield",
    "sg:classifiers":[
        {
            "category":"Professional",
            "subcategory":"Management & Consulting",
            "type":"Services"
        }
    ],
    "sg:phone":"+1 908 928 9093",
    "sg:postcode":"07090",
    "sg:province":"NJ",
    "sg:tags":[
        "party",
        "planning"
    ],
    "wof:name":"6 Degrees Of Celebration",
    "wof:placetype":"venue"
},
  "geometry": {"coordinates":[-74.358146,40.655588],"type":"Point"}
}