{
  "type": "Feature",
  "properties": {
    "addr:full":"150 Donnybrook Dr Demarest NJ 07627",
    "addr:housenumber":"150",
    "addr:postcode":"07627",
    "addr:street":"Donnybrook Dr",
    "iso:country":"US",
    "sg:address":"150 Donnybrook Dr",
    "sg:city":"Demarest",
    "sg:classifiers":[
        {
            "category":"Building & Trades",
            "subcategory":"Construction",
            "type":"Services"
        }
    ],
    "sg:phone":"+1 201 768 8993",
    "sg:postcode":"07627",
    "sg:province":"NJ",
    "sg:tags":[
        "house"
    ],
    "wof:name":"Drew Construction Inc",
    "wof:placetype":"venue"
},
  "geometry": {"coordinates":[-73.96913000000001,40.967003],"type":"Point"}
}