{
  "type": "Feature",
  "properties": {
    "iso:country":"US",
    "sg:address":"1 E Main St",
    "sg:city":"Mendham",
    "sg:classifiers":[
        {
            "category":"Professional",
            "type":"Services"
        }
    ],
    "sg:phone":"+1 973 543 8361",
    "sg:postcode":"07945",
    "sg:province":"NJ",
    "sg:tags":[
        "establishment"
    ],
    "wof:name":"One Main Street",
    "wof:placetype":"venue"
},
  "geometry": {"coordinates":[-74.59735999999999,40.777],"type":"Point"}
}