{
  "type": "Feature",
  "properties": {
    "addr:full":"238 Inman Ave Colonia NJ 07067",
    "addr:housenumber":"238",
    "addr:postcode":"07067",
    "addr:street":"Inman Ave",
    "iso:country":"US",
    "sg:address":"238 Inman Ave",
    "sg:city":"Colonia",
    "sg:classifiers":[
        {
            "category":"Professional",
            "type":"Services"
        }
    ],
    "sg:phone":"+1 732 574 8290",
    "sg:postcode":"07067",
    "sg:province":"NJ",
    "sg:tags":[
        "establishment"
    ],
    "wof:name":"Jane & Lorraine's Inc",
    "wof:placetype":"venue"
},
  "geometry": {"coordinates":[-74.312915,40.600133],"type":"Point"}
}