{
  "type": "Feature",
  "properties": {
    "iso:country":"US",
    "sg:address":"218 Sanhican Dr",
    "sg:city":"Trenton",
    "sg:classifiers":[
        {
            "category":"Education",
            "subcategory":"Special Training",
            "type":"Public Place"
        }
    ],
    "sg:phone":"+1   ",
    "sg:postcode":"08618",
    "sg:province":"NJ",
    "wof:name":"Deborah Ford",
    "wof:placetype":"venue"
},
  "geometry": {"coordinates":[-74.806214,40.238301],"type":"Point"}
}