{
  "type": "Feature",
  "properties": {
    "iso:country":"US",
    "sg:address":"56 Lenox Rd",
    "sg:city":"Wayne",
    "sg:classifiers":[
        {
            "category":"Building & Trades",
            "subcategory":"Construction",
            "type":"Services"
        }
    ],
    "sg:phone":"+1 973 628 8774",
    "sg:postcode":"07470",
    "sg:province":"NJ",
    "sg:tags":[
        "general",
        "contractor"
    ],
    "wof:name":"Britton J Construction LLC",
    "wof:placetype":"venue"
},
  "geometry": {"coordinates":[-74.26257200000001,40.942389],"type":"Point"}
}