{
  "type": "Feature",
  "properties": {
    "addr:full":"554 Bloomfield Ave Bloomfield NJ 07003",
    "addr:housenumber":"554",
    "addr:postcode":"07003",
    "addr:street":"Bloomfield Ave",
    "iso:country":"US",
    "sg:address":"554 Bloomfield Ave",
    "sg:city":"Bloomfield",
    "sg:classifiers":[
        {
            "category":"Professional",
            "subcategory":"Detective & Security Services",
            "type":"Services"
        }
    ],
    "sg:phone":"+1 973 680 0008",
    "sg:postcode":"07003",
    "sg:province":"NJ",
    "sg:tags":[
        "car",
        "guard",
        "patrol",
        "system"
    ],
    "wof:name":"Winfield Security Corporation",
    "wof:placetype":"venue"
},
  "geometry": {"coordinates":[-74.19739,40.79261],"type":"Point"}
}