{
  "type": "Feature",
  "properties": {
    "addr:full":"1199 Amboy Ave Ste 3 Edison NJ 08837",
    "addr:housenumber":"1199",
    "addr:postcode":"08837",
    "addr:street":"Amboy Ave Ste 3",
    "iso:country":"US",
    "sg:address":"1199 Amboy Ave Ste 3",
    "sg:city":"Edison",
    "sg:classifiers":[
        {
            "category":"Shopping",
            "subcategory":"Pets & Pet Supplies",
            "type":"Retail Goods"
        }
    ],
    "sg:phone":"+1 732 549 5250",
    "sg:postcode":"08837",
    "sg:province":"NJ",
    "sg:tags":[
        "feed"
    ],
    "sg:website":"http://www.wildbirdcountry.net/",
    "wof:name":"Bird Wild Country",
    "wof:placetype":"venue"
},
  "geometry": {"coordinates":[-74.347313,40.536572],"type":"Point"}
}