{
  "type": "Feature",
  "properties": {
    "iso:country":"US",
    "sg:address":"291 Birch St",
    "sg:city":"Emerson",
    "sg:classifiers":[
        {
            "category":"Building & Trades",
            "subcategory":"Landscaping Services",
            "type":"Services"
        }
    ],
    "sg:phone":"+1 201 634 0466",
    "sg:postcode":"07630",
    "sg:province":"NJ",
    "sg:tags":[
        "landscape",
        "contractor"
    ],
    "wof:name":"Schult Landscape Contracting",
    "wof:placetype":"venue"
},
  "geometry": {"coordinates":[-74.031603,40.979502],"type":"Point"}
}