{
  "type": "Feature",
  "properties": {
    "addr:full":"281 Carranza Rd Vincentown NJ 08088",
    "addr:housenumber":"281",
    "addr:postcode":"08088",
    "addr:street":"Carranza Rd",
    "iso:country":"US",
    "sg:address":"281 Carranza Rd",
    "sg:city":"Vincentown",
    "sg:classifiers":[
        {
            "category":"Retail",
            "subcategory":"Veterinary Services",
            "type":"Services"
        }
    ],
    "sg:phone":"+1 609 268 9400",
    "sg:postcode":"08088",
    "sg:province":"NJ",
    "wof:name":"Bende Robert H Dvm",
    "wof:placetype":"venue"
},
  "geometry": {"coordinates":[-74.704162,39.823701],"type":"Point"}
}