{
  "type": "Feature",
  "properties": {
    "iso:country":"US",
    "sg:address":"59 Urban Club Rd",
    "sg:city":"Wayne",
    "sg:classifiers":[
        {
            "category":"Professional",
            "subcategory":"Lawyer & Legal Services",
            "type":"Services"
        }
    ],
    "sg:phone":"+1 973 628 1110",
    "sg:postcode":"07470",
    "sg:province":"NJ",
    "sg:tags":[
        "attorney"
    ],
    "wof:name":"James F Carroll",
    "wof:placetype":"venue"
},
  "geometry": {"coordinates":[-74.220985,40.96213],"type":"Point"}
}