{
  "type": "Feature",
  "properties": {
    "iso:country":"US",
    "sg:address":"4 Journal Sq",
    "sg:city":"Jersey City",
    "sg:classifiers":[
        {
            "category":"Food & Beverages",
            "subcategory":"Fruits & Vegetables",
            "type":"Retail Goods"
        }
    ],
    "sg:phone":"+1 201 239 0442",
    "sg:postcode":"07306",
    "sg:province":"NJ",
    "sg:tags":[
        "produce"
    ],
    "wof:name":"Journal Square Fresh Fruit",
    "wof:placetype":"venue"
},
  "geometry": {"coordinates":[-74.063929,40.732081],"type":"Point"}
}