{
  "type": "Feature",
  "properties": {
    "addr:full":"54 Locust Ave Wallington NJ 07057",
    "addr:housenumber":"54",
    "addr:postcode":"07057",
    "addr:street":"Locust Ave",
    "iso:country":"US",
    "sg:address":"54 Locust Ave",
    "sg:city":"Wallington",
    "sg:classifiers":[
        {
            "category":"Building & Trades",
            "subcategory":"Construction",
            "type":"Services"
        }
    ],
    "sg:phone":"+1 973 470 0125",
    "sg:postcode":"07057",
    "sg:province":"NJ",
    "sg:tags":[
        "contractor"
    ],
    "wof:name":"Quality Masonary Job",
    "wof:placetype":"venue"
},
  "geometry": {"coordinates":[-74.112495,40.851458],"type":"Point"}
}