{
  "type": "Feature",
  "properties": {
    "iso:country":"US",
    "sg:address":"4 Applegate Dr",
    "sg:city":"Robbinsville",
    "sg:classifiers":[
        {
            "category":"Professional",
            "type":"Services"
        },
        {
            "category":"Professional",
            "subcategory":"Advertising",
            "type":"Services"
        }
    ],
    "sg:phone":"+1 609 208 0100",
    "sg:postcode":"08691",
    "sg:province":"NJ",
    "sg:tags":[
        "co",
        "marketing",
        "support",
        "direct",
        "mail",
        "establishment"
    ],
    "wof:name":"Direct Fulfillment LP",
    "wof:placetype":"venue"
},
  "geometry": {"coordinates":[-74.58140299999999,40.197904],"type":"Point"}
}