{
  "type": "Feature",
  "properties": {
    "iso:country":"US",
    "sg:address":"503 N Franklin Tpke",
    "sg:city":"Ramsey",
    "sg:classifiers":[
        {
            "category":"Shopping",
            "type":"Retail Goods"
        }
    ],
    "sg:phone":"+1 201 995 9110",
    "sg:postcode":"07446",
    "sg:province":"NJ",
    "sg:tags":[
        "electronic",
        "merchandise",
        "cellular",
        "telephone"
    ],
    "wof:name":"Auricle Wireless II",
    "wof:placetype":"venue"
},
  "geometry": {"coordinates":[-74.137049,41.072126],"type":"Point"}
}