{
  "type": "Feature",
  "properties": {
    "iso:country":"US",
    "sg:address":"136 Compass Rd",
    "sg:city":"Manahawkin",
    "sg:classifiers":[
        {
            "category":"Professional",
            "subcategory":"Computer Services",
            "type":"Services"
        }
    ],
    "sg:phone":"+1 609 698 1153",
    "sg:postcode":"08050",
    "sg:province":"NJ",
    "sg:tags":[
        "consulting",
        "related",
        "business"
    ],
    "wof:name":"P M C S Inc",
    "wof:placetype":"venue"
},
  "geometry": {"coordinates":[-74.291837,39.749507],"type":"Point"}
}