{
  "type": "Feature",
  "properties": {
    "addr:full":"25 Market St Trenton NJ 08611",
    "addr:housenumber":"25",
    "addr:postcode":"08611",
    "addr:street":"Market St",
    "iso:country":"US",
    "sg:address":"25 Market St",
    "sg:city":"Trenton",
    "sg:classifiers":[
        {
            "category":"Government",
            "subcategory":"Office",
            "type":"Public Place"
        }
    ],
    "sg:phone":"+1 609 292 5939",
    "sg:postcode":"08611",
    "sg:province":"NJ",
    "sg:tags":[
        "state",
        "safety",
        "order"
    ],
    "wof:name":"Grants Program Dev",
    "wof:placetype":"venue"
},
  "geometry": {"coordinates":[-74.76401199999999,40.214405],"type":"Point"}
}