{
  "type": "Feature",
  "properties": {
    "addr:full":"278 Stonetown Rd Ringwood NJ 07456",
    "addr:housenumber":"278",
    "addr:postcode":"07456",
    "addr:street":"Stonetown Rd",
    "iso:country":"US",
    "sg:address":"278 Stonetown Rd",
    "sg:city":"Ringwood",
    "sg:classifiers":[
        {
            "category":"Professional",
            "subcategory":"Management & Consulting",
            "type":"Services"
        }
    ],
    "sg:phone":"+1 973 835 7373",
    "sg:postcode":"07456",
    "sg:province":"NJ",
    "sg:tags":[
        "consultant",
        "business"
    ],
    "wof:name":"L P Management Inc",
    "wof:placetype":"venue"
},
  "geometry": {"coordinates":[-74.303561,41.091369],"type":"Point"}
}