{
  "type": "Feature",
  "properties": {
    "iso:country":"US",
    "sg:address":"36 Sun Valley Way",
    "sg:city":"Morris Plains",
    "sg:classifiers":[
        {
            "category":"Real Estate",
            "subcategory":"Real Estate Agent",
            "type":"Services"
        }
    ],
    "sg:phone":"+1   ",
    "sg:postcode":"07950",
    "sg:province":"NJ",
    "wof:name":"CNG Realty LLC",
    "wof:placetype":"venue"
},
  "geometry": {"coordinates":[-74.479699,40.836229],"type":"Point"}
}