{
  "type": "Feature",
  "properties": {
    "iso:country":"US",
    "sg:address":"16 Florida Ave",
    "sg:city":"Lake Hopatcong",
    "sg:classifiers":[
        {
            "category":"Building & Trades",
            "subcategory":"Construction",
            "type":"Services"
        }
    ],
    "sg:phone":"+1 973 663 5744",
    "sg:postcode":"07849",
    "sg:province":"NJ",
    "sg:tags":[
        "contractor"
    ],
    "wof:name":"Garrison & Son Contracting LLC",
    "wof:placetype":"venue"
},
  "geometry": {"coordinates":[-74.624481,40.966142],"type":"Point"}
}