{
  "type": "Feature",
  "properties": {
    "iso:country":"US",
    "sg:address":"473 State Rte 38",
    "sg:city":"Maple Shade",
    "sg:classifiers":[
        {
            "category":"Shopping",
            "subcategory":"Computers & Home Electronics",
            "type":"Retail Goods"
        }
    ],
    "sg:phone":"+1   ",
    "sg:postcode":"08052",
    "sg:province":"NJ",
    "wof:name":"Barracks Trading Post",
    "wof:placetype":"venue"
},
  "geometry": {"coordinates":[-74.996458,39.94196],"type":"Point"}
}