{
  "type": "Feature",
  "properties": {
    "iso:country":"US",
    "sg:address":"1000 Atlantic Ave",
    "sg:city":"Camden",
    "sg:classifiers":[
        {
            "category":"Social Services",
            "type":"Services"
        }
    ],
    "sg:phone":"+1 856 963 1311",
    "sg:postcode":"08104",
    "sg:province":"NJ",
    "sg:tags":[
        "youth",
        "organization",
        "center"
    ],
    "wof:name":"Genesis School Of Business Inc",
    "wof:placetype":"venue"
},
  "geometry": {"coordinates":[-75.107685,39.92955],"type":"Point"}
}