{
  "type": "Feature",
  "properties": {
    "iso:country":"US",
    "sg:address":"1000 White Horse Rd",
    "sg:city":"Voorhees",
    "sg:classifiers":[
        {
            "category":"Building & Trades",
            "subcategory":"Pest Control",
            "type":"Services"
        }
    ],
    "sg:phone":"+1 609 254 7141",
    "sg:postcode":"08043",
    "sg:province":"NJ",
    "wof:name":"Western Termite & Pest Control",
    "wof:placetype":"venue"
},
  "geometry": {"coordinates":[-74.989093,39.847591],"type":"Point"}
}