{
  "type": "Feature",
  "properties": {
    "addr:full":"Orton Rd Caldwell NJ 07006",
    "addr:postcode":"07006",
    "addr:street":"Orton Rd",
    "iso:country":"US",
    "sg:address":"Orton Rd",
    "sg:city":"Caldwell",
    "sg:classifiers":[
        {
            "category":"Social Services",
            "subcategory":"Child Care",
            "type":"Services"
        }
    ],
    "sg:phone":"+1 973 228 8999",
    "sg:postcode":"07006",
    "sg:province":"NJ",
    "sg:tags":[
        "day"
    ],
    "wof:name":"West Essex Y M C A Extended Day",
    "wof:placetype":"venue"
},
  "geometry": {"coordinates":[-74.281998,40.847301],"type":"Point"}
}