{
  "type": "Feature",
  "properties": {
    "iso:country":"US",
    "sg:address":"1294 Springfield Ave",
    "sg:city":"Irvington",
    "sg:classifiers":[
        {
            "category":"Food & Beverages",
            "subcategory":"Groceries & Convenience Stores",
            "type":"Retail Goods"
        }
    ],
    "sg:phone":"+1   ",
    "sg:postcode":"07111",
    "sg:province":"NJ",
    "wof:name":"Corner Grocery Store",
    "wof:placetype":"venue"
},
  "geometry": {"coordinates":[-74.24183600000001,40.724554],"type":"Point"}
}