{
  "type": "Feature",
  "properties": {
    "iso:country":"US",
    "sg:address":"16 Eagle Dr",
    "sg:city":"Lakehurst",
    "sg:classifiers":[
        {
            "category":"Organizations",
            "subcategory":"Religious Organization",
            "type":"Services"
        }
    ],
    "sg:phone":"+1   ",
    "sg:postcode":"08759",
    "sg:province":"NJ",
    "wof:name":"John Carhart Rev",
    "wof:placetype":"venue"
},
  "geometry": {"coordinates":[-74.31550799999999,39.956998],"type":"Point"}
}