{
  "type": "Feature",
  "properties": {
    "iso:country":"US",
    "sg:address":"22 Bloomfield Ave",
    "sg:city":"Flemington",
    "sg:classifiers":[
        {
            "category":"Restaurant",
            "type":"Food & Drink"
        }
    ],
    "sg:phone":"+1 908 788 7050",
    "sg:postcode":"08822",
    "sg:province":"NJ",
    "sg:website":"www.mattsredroostergrill.com",
    "wof:name":"Matt's Red Rooster Grill",
    "wof:placetype":"venue"
},
  "geometry": {"coordinates":[-74.85780200000001,40.511332],"type":"Point"}
}