{
  "type": "Feature",
  "properties": {
    "addr:full":"1600 Saint Georges Ave Rahway NJ 07065",
    "addr:housenumber":"1600",
    "addr:postcode":"07065",
    "addr:street":"Saint Georges Ave",
    "iso:country":"US",
    "sg:address":"1600 Saint Georges Ave",
    "sg:city":"Rahway",
    "sg:classifiers":[
        {
            "category":"Health Services",
            "subcategory":"Doctor",
            "type":"Services"
        }
    ],
    "sg:phone":"+1 732 396 1200",
    "sg:postcode":"07065",
    "sg:province":"NJ",
    "sg:tags":[
        "osteopathic"
    ],
    "wof:name":"John M Sawicki DO",
    "wof:placetype":"venue"
},
  "geometry": {"coordinates":[-74.285357,40.61577],"type":"Point"}
}