{
  "type": "Feature",
  "properties": {
    "iso:country":"US",
    "sg:address":"79 Shrewsbury Dr",
    "sg:city":"Livingston",
    "sg:classifiers":[
        {
            "category":"Professional",
            "subcategory":"Lawyer & Legal Services",
            "type":"Services"
        }
    ],
    "sg:phone":"+1 973 740 1250",
    "sg:postcode":"07039",
    "sg:province":"NJ",
    "wof:name":"Shapiro Terry L Attorney",
    "wof:placetype":"venue"
},
  "geometry": {"coordinates":[-74.298698,40.790901],"type":"Point"}
}