{
  "type": "Feature",
  "properties": {
    "addr:full":"94 E Mount Pleasant Ave Livingston NJ 07039",
    "addr:housenumber":"94",
    "addr:postcode":"07039",
    "addr:street":"E Mount Pleasant Ave",
    "iso:country":"US",
    "sg:address":"94 E Mount Pleasant Ave",
    "sg:city":"Livingston",
    "sg:classifiers":[
        {
            "category":"Social Services",
            "subcategory":"Child Care",
            "type":"Services"
        },
        {
            "category":"Education",
            "subcategory":"Preschool",
            "type":"Public Place"
        },
        {
            "category":"Education",
            "subcategory":"School",
            "type":"Public Place"
        }
    ],
    "sg:phone":"+1 973 994 9511",
    "sg:postcode":"07039",
    "sg:province":"NJ",
    "sg:tags":[
        "elementary",
        "day"
    ],
    "wof:name":"Strawberry Hill Pre-School",
    "wof:placetype":"venue"
},
  "geometry": {"coordinates":[-74.312798,40.796299],"type":"Point"}
}