{
  "type": "Feature",
  "properties": {
    "addr:full":"609 Park Ave Plainfield NJ 07060",
    "addr:housenumber":"609",
    "addr:postcode":"07060",
    "addr:street":"Park Ave",
    "iso:country":"US",
    "sg:address":"609 Park Ave",
    "sg:city":"Plainfield",
    "sg:classifiers":[
        {
            "category":"Restaurant",
            "type":"Food & Drink"
        }
    ],
    "sg:phone":"+1 908 753 4444",
    "sg:postcode":"07060",
    "sg:province":"NJ",
    "sg:tags":[
        "eating"
    ],
    "wof:name":"Pizza Stop and Cafe",
    "wof:placetype":"venue"
},
  "geometry": {"coordinates":[-74.417356,40.615097],"type":"Point"}
}