{
  "type": "Feature",
  "properties": {
    "iso:country":"US",
    "sg:address":"35 Hurlingham Club Rd",
    "sg:city":"Far Hills",
    "sg:classifiers":[
        {
            "category":"Professional",
            "type":"Services"
        }
    ],
    "sg:phone":"+1   ",
    "sg:postcode":"07931",
    "sg:province":"NJ",
    "wof:name":"540 Mine Brook Corp",
    "wof:placetype":"venue"
},
  "geometry": {"coordinates":[-74.637091,40.686857],"type":"Point"}
}