{
  "type": "Feature",
  "properties": {
    "addr:full":"33 Reeves St Millville NJ 08332",
    "addr:housenumber":"33",
    "addr:postcode":"08332",
    "addr:street":"Reeves St",
    "iso:country":"US",
    "sg:address":"33 Reeves St",
    "sg:city":"Millville",
    "sg:classifiers":[
        {
            "category":"Manufacturing",
            "subcategory":"Printing",
            "type":"Manufacturing & Wholesale Goods"
        }
    ],
    "sg:phone":"+1 856 327 8366",
    "sg:postcode":"08332",
    "sg:province":"NJ",
    "sg:tags":[
        "printer"
    ],
    "wof:name":"Trout Printing & Publishing",
    "wof:placetype":"venue"
},
  "geometry": {"coordinates":[-75.22052499999999,39.430337],"type":"Point"}
}