{
  "type": "Feature",
  "properties": {
    "addr:full":"1813 State Rte 35 Oakhurst NJ 07755",
    "addr:housenumber":"1813",
    "addr:postcode":"07755",
    "addr:street":"State Rte 35",
    "iso:country":"US",
    "sg:address":"1813 State Rte 35",
    "sg:city":"Oakhurst",
    "sg:classifiers":[
        {
            "category":"Shopping",
            "type":"Retail Goods"
        }
    ],
    "sg:phone":"+1 732 660 0001",
    "sg:postcode":"07755",
    "sg:province":"NJ",
    "sg:tags":[
        "telephone",
        "cellular"
    ],
    "wof:name":"Access Wireless",
    "wof:placetype":"venue"
},
  "geometry": {"coordinates":[-74.04116999999999,40.261219],"type":"Point"}
}