{
  "type": "Feature",
  "properties": {
    "addr:full":"76 Herbert Rd Robbinsville NJ 08691",
    "addr:housenumber":"76",
    "addr:postcode":"08691",
    "addr:street":"Herbert Rd",
    "iso:country":"US",
    "sg:address":"76 Herbert Rd",
    "sg:city":"Robbinsville",
    "sg:classifiers":[
        {
            "category":"Building & Trades",
            "subcategory":"Construction",
            "type":"Services"
        }
    ],
    "sg:phone":"+1 609 259 3008",
    "sg:postcode":"08691",
    "sg:province":"NJ",
    "sg:tags":[
        "asphalt",
        "maintenance",
        "driveway"
    ],
    "sg:website":"www.collegiatesealers.com",
    "wof:name":"Collegiate Sealers Inc",
    "wof:placetype":"venue"
},
  "geometry": {"coordinates":[-74.538415,40.207213],"type":"Point"}
}