{
  "type": "Feature",
  "properties": {
    "iso:country":"US",
    "sg:address":"108 Piermont Rd",
    "sg:city":"Cresskill",
    "sg:classifiers":[
        {
            "category":"Autos & Motor Vehicles",
            "subcategory":"Fuel & Gas Station",
            "type":"Retail Goods"
        }
    ],
    "sg:phone":"+1 201 541 9090",
    "sg:postcode":"07626",
    "sg:province":"NJ",
    "sg:tags":[
        "oil"
    ],
    "wof:name":"Pyramid Service Station",
    "wof:placetype":"venue"
},
  "geometry": {"coordinates":[-73.96252200000001,40.942173],"type":"Point"}
}