{
  "type": "Feature",
  "properties": {
    "addr:full":"804 Ocean Ave Belmar NJ 07719",
    "addr:housenumber":"804",
    "addr:postcode":"07719",
    "addr:street":"Ocean Ave",
    "iso:country":"US",
    "sg:address":"804 Ocean Ave",
    "sg:city":"Belmar",
    "sg:classifiers":[
        {
            "category":"Restaurant",
            "type":"Food & Drink"
        }
    ],
    "sg:phone":"+1 732 280 2241",
    "sg:postcode":"07719",
    "sg:province":"NJ",
    "wof:name":"Giovanni's Pizza",
    "wof:placetype":"venue"
},
  "geometry": {"coordinates":[-74.01309999999999,40.178834],"type":"Point"}
}