{
  "type": "Feature",
  "properties": {
    "addr:full":"212 Norwood Ave Oakhurst NJ 07755",
    "addr:housenumber":"212",
    "addr:postcode":"07755",
    "addr:street":"Norwood Ave",
    "iso:country":"US",
    "sg:address":"212 Norwood Ave",
    "sg:city":"Oakhurst",
    "sg:classifiers":[
        {
            "category":"Organizations",
            "subcategory":"Community Association",
            "type":"Services"
        }
    ],
    "sg:phone":"+1   ",
    "sg:postcode":"07755",
    "sg:province":"NJ",
    "sg:tags":[
        "tavern",
        "veteran"
    ],
    "wof:name":"Oakhurst VFW Post 2226",
    "wof:placetype":"venue"
},
  "geometry": {"coordinates":[-73.999711,40.262379],"type":"Point"}
}