{
  "type": "Feature",
  "properties": {
    "addr:full":"107 Wagonwheel Ct Marlton NJ 08053",
    "addr:housenumber":"107",
    "addr:postcode":"08053",
    "addr:street":"Wagonwheel Ct",
    "iso:country":"US",
    "sg:address":"107 Wagonwheel Ct",
    "sg:city":"Marlton",
    "sg:classifiers":[
        {
            "category":"Building & Trades",
            "subcategory":"Cleaning & Sanitation",
            "type":"Services"
        }
    ],
    "sg:phone":"+1   ",
    "sg:postcode":"08053",
    "sg:province":"NJ",
    "sg:tags":[
        "maintenance"
    ],
    "wof:name":"Camden Window Cleaning & Maoin",
    "wof:placetype":"venue"
},
  "geometry": {"coordinates":[-74.915148,39.867971],"type":"Point"}
}