{
  "type": "Feature",
  "properties": {
    "iso:country":"US",
    "sg:address":"88 E Main St",
    "sg:city":"Mendham",
    "sg:classifiers":[
        {
            "category":"Professional",
            "subcategory":"Management & Consulting",
            "type":"Services"
        }
    ],
    "sg:phone":"+1 973 543 8844",
    "sg:postcode":"07945",
    "sg:province":"NJ",
    "sg:tags":[
        "business"
    ],
    "wof:name":"Martin Gertler",
    "wof:placetype":"venue"
},
  "geometry": {"coordinates":[-74.59074099999999,40.780575],"type":"Point"}
}