{
  "type": "Feature",
  "properties": {
    "addr:full":"128 Florence Ave Denville NJ 07834",
    "addr:housenumber":"128",
    "addr:postcode":"07834",
    "addr:street":"Florence Ave",
    "iso:country":"US",
    "sg:address":"128 Florence Ave",
    "sg:city":"Denville",
    "sg:classifiers":[
        {
            "category":"Professional",
            "subcategory":"Computer Services",
            "type":"Services"
        },
        {
            "category":"Shopping",
            "subcategory":"Computers & Home Electronics",
            "type":"Retail Goods"
        }
    ],
    "sg:phone":"+1 973 625 7720",
    "sg:postcode":"07834",
    "sg:province":"NJ",
    "sg:tags":[
        "implementation",
        "consulting",
        "design",
        "software"
    ],
    "sg:website":"www.mallardcovemarina.com",
    "wof:name":"European American Service",
    "wof:placetype":"venue"
},
  "geometry": {"coordinates":[-74.46821300000001,40.912317],"type":"Point"}
}