{
  "type": "Feature",
  "properties": {
    "iso:country":"US",
    "sg:address":"112 Connecticut Dr",
    "sg:city":"Burlington",
    "sg:classifiers":[
        {
            "category":"Banks & Credit Unions",
            "subcategory":"Financial Services",
            "type":"Services"
        }
    ],
    "sg:phone":"+1   ",
    "sg:postcode":"08016",
    "sg:province":"NJ",
    "sg:tags":[
        "company",
        "holding"
    ],
    "wof:name":"Kennedy Holding Corp",
    "wof:placetype":"venue"
},
  "geometry": {"coordinates":[-74.84089400000001,40.042533],"type":"Point"}
}