{
  "type": "Feature",
  "properties": {
    "iso:country":"US",
    "sg:address":"944 18th Ave",
    "sg:city":"Newark",
    "sg:classifiers":[
        {
            "category":"Food & Beverages",
            "subcategory":"Meat & Fish",
            "type":"Retail Goods"
        }
    ],
    "sg:phone":"+1   ",
    "sg:postcode":"07106",
    "sg:province":"NJ",
    "wof:name":"Andy Fish Market",
    "wof:placetype":"venue"
},
  "geometry": {"coordinates":[-74.22568,40.738472],"type":"Point"}
}