{
  "type": "Feature",
  "properties": {
    "addr:full":"136 Merritt St Jersey City NJ 07305",
    "addr:housenumber":"136",
    "addr:postcode":"07305",
    "addr:street":"Merritt St",
    "iso:country":"US",
    "sg:address":"136 Merritt St",
    "sg:city":"Jersey City",
    "sg:classifiers":[
        {
            "category":"Building & Trades",
            "subcategory":"Construction",
            "type":"Services"
        }
    ],
    "sg:phone":"+1 201 332 7827",
    "sg:postcode":"07305",
    "sg:province":"NJ",
    "sg:tags":[
        "general",
        "contractor"
    ],
    "wof:name":"Ingerman Construction Co",
    "wof:placetype":"venue"
},
  "geometry": {"coordinates":[-74.098781,40.689434],"type":"Point"}
}