{
  "type": "Feature",
  "properties": {
    "iso:country":"US",
    "sg:address":"190 Somerset St",
    "sg:city":"North Plainfield",
    "sg:classifiers":[
        {
            "category":"Shopping",
            "subcategory":"Music",
            "type":"Retail Goods"
        },
        {
            "category":"Shopping",
            "subcategory":"Musical Instruments",
            "type":"Retail Goods"
        }
    ],
    "sg:phone":"+1 908 222 7050",
    "sg:postcode":"07060",
    "sg:province":"NJ",
    "sg:tags":[
        "car",
        "accessory",
        "take",
        "passport",
        "photo",
        "dealer"
    ],
    "wof:name":"J S J Music & More",
    "wof:placetype":"venue"
},
  "geometry": {"coordinates":[-74.427159,40.620433],"type":"Point"}
}