{
  "type": "Feature",
  "properties": {
    "iso:country":"US",
    "sg:address":"11 Spring St",
    "sg:city":"Chatham",
    "sg:classifiers":[
        {
            "category":"Professional",
            "subcategory":"Management & Consulting",
            "type":"Services"
        }
    ],
    "sg:phone":"+1 973 701 0080",
    "sg:postcode":"07928",
    "sg:province":"NJ",
    "sg:tags":[
        "consultant"
    ],
    "wof:name":"Gammon Institutional Advisors",
    "wof:placetype":"venue"
},
  "geometry": {"coordinates":[-74.407929,40.729496],"type":"Point"}
}