{
  "type": "Feature",
  "properties": {
    "addr:full":"645 Greenway Pl Westwood NJ 07675",
    "addr:housenumber":"645",
    "addr:postcode":"07675",
    "addr:street":"Greenway Pl",
    "iso:country":"US",
    "sg:address":"645 Greenway Pl",
    "sg:city":"Westwood",
    "sg:classifiers":[
        {
            "category":"Manufacturing",
            "subcategory":"Printing",
            "type":"Manufacturing & Wholesale Goods"
        }
    ],
    "sg:phone":"+1 201 307 1531",
    "sg:postcode":"07675",
    "sg:province":"NJ",
    "sg:tags":[
        "print",
        "graphic",
        "artwork"
    ],
    "wof:name":"Wet Stone Graphics LLC",
    "wof:placetype":"venue"
},
  "geometry": {"coordinates":[-74.01491799999999,41.024625],"type":"Point"}
}