{
  "type": "Feature",
  "properties": {
    "iso:country":"US",
    "sg:address":"815 W Front St",
    "sg:city":"Plainfield",
    "sg:classifiers":[
        {
            "category":"Retail",
            "subcategory":"Self-service Laundry",
            "type":"Services"
        }
    ],
    "sg:phone":"+1 908 754 1247",
    "sg:postcode":"07063",
    "sg:province":"NJ",
    "wof:name":"Suds R Us",
    "wof:placetype":"venue"
},
  "geometry": {"coordinates":[-74.43867400000001,40.607494],"type":"Point"}
}