{
  "type": "Feature",
  "properties": {
    "addr:full":"175 Fairfield Ave West Caldwell NJ 07006",
    "addr:housenumber":"175",
    "addr:postcode":"07006",
    "addr:street":"Fairfield Ave",
    "iso:country":"US",
    "sg:address":"175 Fairfield Ave",
    "sg:city":"West Caldwell",
    "sg:classifiers":[
        {
            "category":"Banks & Credit Unions",
            "subcategory":"Financial Services",
            "type":"Services"
        }
    ],
    "sg:phone":"+1 973 226 9010",
    "sg:postcode":"07006",
    "sg:province":"NJ",
    "sg:tags":[
        "broker",
        "mortgage"
    ],
    "wof:name":"First Acceptance Mortgage Corp",
    "wof:placetype":"venue"
},
  "geometry": {"coordinates":[-74.286102,40.858501],"type":"Point"}
}