{
  "type": "Feature",
  "properties": {
    "iso:country":"US",
    "sg:address":"1100 Route 72 W Ste 202",
    "sg:city":"Manahawkin",
    "sg:classifiers":[
        {
            "category":"Health Services",
            "subcategory":"Doctor",
            "type":"Services"
        }
    ],
    "sg:phone":"+1 609 978 1300",
    "sg:postcode":"08050",
    "sg:province":"NJ",
    "sg:tags":[
        "physician",
        "pediatrics-emergency",
        "pediatrics",
        "surgeons",
        "medicine",
        "surgeon"
    ],
    "wof:name":"Southern Ocean O.M.S.",
    "wof:placetype":"venue"
},
  "geometry": {"coordinates":[-74.284943,39.718746],"type":"Point"}
}