{
  "type": "Feature",
  "properties": {
    "addr:full":"299 Atlantic St Bridgeton NJ 08302",
    "addr:housenumber":"299",
    "addr:postcode":"08302",
    "addr:street":"Atlantic St",
    "iso:country":"US",
    "sg:address":"299 Atlantic St",
    "sg:city":"Bridgeton",
    "sg:classifiers":[
        {
            "category":"Professional",
            "subcategory":"Research",
            "type":"Services"
        }
    ],
    "sg:phone":"+1   ",
    "sg:postcode":"08302",
    "sg:province":"NJ",
    "sg:tags":[
        "nonphysical",
        "commercial"
    ],
    "wof:name":"Douglass Frederick Center Ced",
    "wof:placetype":"venue"
},
  "geometry": {"coordinates":[-75.23997199999999,39.421824],"type":"Point"}
}