{
  "type": "Feature",
  "properties": {
    "iso:country":"US",
    "sg:address":"55 Amwell Rd",
    "sg:city":"Flemington",
    "sg:classifiers":[
        {
            "category":"Professional",
            "subcategory":"Computer Services",
            "type":"Services"
        }
    ],
    "sg:phone":"+1 908 782 0027",
    "sg:postcode":"08822",
    "sg:province":"NJ",
    "sg:tags":[
        "datum"
    ],
    "wof:name":"Multimedia",
    "wof:placetype":"venue"
},
  "geometry": {"coordinates":[-74.80206,40.483475],"type":"Point"}
}