{
  "type": "Feature",
  "properties": {
    "iso:country":"US",
    "sg:address":"891 Holmdel Rd",
    "sg:city":"Holmdel",
    "sg:classifiers":[
        {
            "category":"Recreation",
            "type":"Entertainment"
        }
    ],
    "sg:phone":"+1   ",
    "sg:postcode":"07733",
    "sg:province":"NJ",
    "wof:name":"Ime Partnership",
    "wof:placetype":"venue"
},
  "geometry": {"coordinates":[-74.190831,40.373944],"type":"Point"}
}