{
  "type": "Feature",
  "properties": {
    "iso:country":"US",
    "sg:address":"1285 Grays Rd",
    "sg:city":"Barnegat",
    "sg:classifiers":[
        {
            "category":"Retail",
            "subcategory":"Animal Services",
            "type":"Services"
        }
    ],
    "sg:phone":"+1 609 698 7600",
    "sg:postcode":"08005",
    "sg:province":"NJ",
    "sg:tags":[
        "pet",
        "funeral"
    ],
    "wof:name":"Pine Forest Pet Cemetery",
    "wof:placetype":"venue"
},
  "geometry": {"coordinates":[-74.352791,39.748358],"type":"Point"}
}