{
  "type": "Feature",
  "properties": {
    "iso:country":"US",
    "sg:address":"262 Old New Brunswick Rd",
    "sg:city":"Piscataway",
    "sg:classifiers":[
        {
            "category":"Manufacturing",
            "subcategory":"Signs",
            "type":"Manufacturing & Wholesale Goods"
        }
    ],
    "sg:phone":"+1 732 981 1120",
    "sg:postcode":"08854",
    "sg:province":"NJ",
    "sg:tags":[
        "exhibit"
    ],
    "wof:name":"Graphic Systems",
    "wof:placetype":"venue"
},
  "geometry": {"coordinates":[-74.474566,40.553236],"type":"Point"}
}