{
  "type": "Feature",
  "properties": {
    "iso:country":"US",
    "sg:address":"20 Green St",
    "sg:city":"Newark",
    "sg:classifiers":[
        {
            "category":"Professional",
            "subcategory":"Lawyer & Legal Services",
            "type":"Services"
        }
    ],
    "sg:phone":"+1 973 848 0500",
    "sg:postcode":"07102",
    "sg:province":"NJ",
    "wof:name":"Garces & Grabler",
    "wof:placetype":"venue"
},
  "geometry": {"coordinates":[-74.17210799999999,40.731789],"type":"Point"}
}