{
  "type": "Feature",
  "properties": {
    "addr:full":"23 Jason Ct Colonia NJ 07067",
    "addr:housenumber":"23",
    "addr:postcode":"07067",
    "addr:street":"Jason Ct",
    "iso:country":"US",
    "sg:address":"23 Jason Ct",
    "sg:city":"Colonia",
    "sg:classifiers":[
        {
            "category":"Professional",
            "subcategory":"Management & Consulting",
            "type":"Services"
        }
    ],
    "sg:phone":"+1   ",
    "sg:postcode":"07067",
    "sg:province":"NJ",
    "sg:tags":[
        "business"
    ],
    "wof:name":"Furey Consulting Inc",
    "wof:placetype":"venue"
},
  "geometry": {"coordinates":[-74.320549,40.59335],"type":"Point"}
}