{
  "type": "Feature",
  "properties": {
    "iso:country":"US",
    "sg:address":"375 Georgia Dr",
    "sg:city":"Brick",
    "sg:classifiers":[
        {
            "category":"Insurance",
            "subcategory":"Insurance Agent",
            "type":"Services"
        }
    ],
    "sg:phone":"+1   ",
    "sg:postcode":"08723",
    "sg:province":"NJ",
    "wof:name":"Tobin Realty",
    "wof:placetype":"venue"
},
  "geometry": {"coordinates":[-74.147852,40.044382],"type":"Point"}
}