{
  "type": "Feature",
  "properties": {
    "iso:country":"US",
    "sg:address":"109 Grand Ave",
    "sg:city":"Englewood",
    "sg:classifiers":[
        {
            "category":"Communications",
            "type":"Services"
        }
    ],
    "sg:phone":"+1 201 567 8034",
    "sg:postcode":"07631",
    "sg:province":"NJ",
    "sg:tags":[
        "communication"
    ],
    "wof:name":"Blair Communications",
    "wof:placetype":"venue"
},
  "geometry": {"coordinates":[-73.976097,40.888858],"type":"Point"}
}