{
  "type": "Feature",
  "properties": {
    "addr:full":"547 E Saddle River Rd Saddle River NJ 07458",
    "addr:housenumber":"547",
    "addr:postcode":"07458",
    "addr:street":"E Saddle River Rd",
    "iso:country":"US",
    "sg:address":"547 E Saddle River Rd",
    "sg:city":"Saddle River",
    "sg:classifiers":[
        {
            "category":"Retail",
            "subcategory":"Animal Services",
            "type":"Services"
        }
    ],
    "sg:phone":"+1 201 236 8259",
    "sg:postcode":"07458",
    "sg:province":"NJ",
    "wof:name":"Canine Kinship",
    "wof:placetype":"venue"
},
  "geometry": {"coordinates":[-74.082008,41.076048],"type":"Point"}
}