{
  "type": "Feature",
  "properties": {
    "addr:full":"101 Margaret Ave Nutley NJ 07110",
    "addr:housenumber":"101",
    "addr:postcode":"07110",
    "addr:street":"Margaret Ave",
    "iso:country":"US",
    "sg:address":"101 Margaret Ave",
    "sg:city":"Nutley",
    "sg:classifiers":[
        {
            "category":"Building & Trades",
            "subcategory":"Construction",
            "type":"Services"
        }
    ],
    "sg:phone":"+1 973 667 6048",
    "sg:postcode":"07110",
    "sg:province":"NJ",
    "sg:tags":[
        "contractor"
    ],
    "wof:name":"Mason FDL Inc",
    "wof:placetype":"venue"
},
  "geometry": {"coordinates":[-74.17636,40.814832],"type":"Point"}
}