{
  "type": "Feature",
  "properties": {
    "iso:country":"US",
    "sg:address":"841 Englishtown Rd",
    "sg:city":"Old Bridge",
    "sg:classifiers":[
        {
            "category":"Education",
            "subcategory":"Junior College",
            "type":"Public Place"
        }
    ],
    "sg:phone":"+1   ",
    "sg:postcode":"08857",
    "sg:province":"NJ",
    "sg:tags":[
        "consulting",
        "computer"
    ],
    "wof:name":"Carilon Enterprises",
    "wof:placetype":"venue"
},
  "geometry": {"coordinates":[-74.361598,40.408671],"type":"Point"}
}