{
  "type": "Feature",
  "properties": {
    "addr:full":"43 Sheridan Ave Paterson NJ 07502",
    "addr:housenumber":"43",
    "addr:postcode":"07502",
    "addr:street":"Sheridan Ave",
    "iso:country":"US",
    "sg:address":"43 Sheridan Ave",
    "sg:city":"Paterson",
    "sg:classifiers":[
        {
            "category":"Building & Trades",
            "subcategory":"Construction",
            "type":"Services"
        }
    ],
    "sg:phone":"+1 973 389 9770",
    "sg:postcode":"07502",
    "sg:province":"NJ",
    "sg:tags":[
        "contractor"
    ],
    "wof:name":"Bbm Contractor",
    "wof:placetype":"venue"
},
  "geometry": {"coordinates":[-74.18566300000001,40.92068],"type":"Point"}
}