{
  "type": "Feature",
  "properties": {
    "iso:country":"US",
    "sg:address":"633 Bloomfield Ave",
    "sg:city":"Bloomfield",
    "sg:classifiers":[
        {
            "category":"Personal",
            "subcategory":"Beauty Salon",
            "type":"Services"
        }
    ],
    "sg:phone":"+1 973 429 0456",
    "sg:postcode":"07003",
    "sg:province":"NJ",
    "sg:tags":[
        "shop"
    ],
    "wof:name":"Secrets of Hair Design",
    "wof:placetype":"venue"
},
  "geometry": {"coordinates":[-74.199716,40.796264],"type":"Point"}
}