{
  "type": "Feature",
  "properties": {
    "addr:full":"4971 Stelton Rd South Plainfield NJ 07080",
    "addr:housenumber":"4971",
    "addr:postcode":"07080",
    "addr:street":"Stelton Rd",
    "iso:country":"US",
    "sg:address":"4971 Stelton Rd",
    "sg:city":"South Plainfield",
    "sg:classifiers":[
        {
            "category":"Shopping",
            "subcategory":"Department Store",
            "type":"Retail Goods"
        }
    ],
    "sg:phone":"+1   ",
    "sg:postcode":"07080",
    "sg:province":"NJ",
    "wof:name":"Kohls Department Stores Inc",
    "wof:placetype":"venue"
},
  "geometry": {"coordinates":[-74.429911,40.549066],"type":"Point"}
}