{
  "type": "Feature",
  "properties": {
    "iso:country":"US",
    "sg:address":"153 E Main St",
    "sg:city":"Rockaway",
    "sg:classifiers":[
        {
            "category":"Professional",
            "subcategory":"Research",
            "type":"Services"
        }
    ],
    "sg:phone":"+1 973 625 4224",
    "sg:postcode":"07866",
    "sg:province":"NJ",
    "sg:tags":[
        "environmental",
        "ecological"
    ],
    "wof:name":"Environmental Health Invstgtns",
    "wof:placetype":"venue"
},
  "geometry": {"coordinates":[-74.50633999999999,40.897499],"type":"Point"}
}