{
  "type": "Feature",
  "properties": {
    "iso:country":"US",
    "sg:address":"140 Parkside Ave",
    "sg:city":"Phillipsburg",
    "sg:classifiers":[
        {
            "category":"Professional",
            "type":"Services"
        }
    ],
    "sg:phone":"+1   ",
    "sg:postcode":"08865",
    "sg:province":"NJ",
    "wof:name":"Susan Dewitt",
    "wof:placetype":"venue"
},
  "geometry": {"coordinates":[-75.157335,40.680023],"type":"Point"}
}