{
  "type": "Feature",
  "properties": {
    "iso:country":"US",
    "sg:address":"53 US Hwy 1",
    "sg:city":"Metuchen",
    "sg:classifiers":[
        {
            "category":"Restaurant",
            "type":"Food & Drink"
        }
    ],
    "sg:phone":"+1   ",
    "sg:postcode":"08840",
    "sg:province":"NJ",
    "wof:name":"Steak and Ale",
    "wof:placetype":"venue"
},
  "geometry": {"coordinates":[-74.32465999999999,40.548572],"type":"Point"}
}