{
  "type": "Feature",
  "properties": {
    "iso:country":"US",
    "sg:address":"19 Baltimore St",
    "sg:city":"Nutley",
    "sg:classifiers":[
        {
            "category":"Professional",
            "subcategory":"Business Services",
            "type":"Services"
        }
    ],
    "sg:phone":"+1 973 667 2395",
    "sg:postcode":"07110",
    "sg:province":"NJ",
    "wof:name":"Rare",
    "wof:placetype":"venue"
},
  "geometry": {"coordinates":[-74.14525399999999,40.827625],"type":"Point"}
}