{
  "type": "Feature",
  "properties": {
    "addr:full":"1500 State Rte 35 Middletown NJ 07748",
    "addr:housenumber":"1500",
    "addr:postcode":"07748",
    "addr:street":"State Rte 35",
    "iso:country":"US",
    "sg:address":"1500 State Rte 35",
    "sg:city":"Middletown",
    "sg:classifiers":[
        {
            "category":"Retail",
            "subcategory":"Portrait Studio",
            "type":"Services"
        }
    ],
    "sg:phone":"+1   ",
    "sg:postcode":"07748",
    "sg:province":"NJ",
    "sg:tags":[
        "photo"
    ],
    "wof:name":"Sears Portrait Studio 1574",
    "wof:placetype":"venue"
},
  "geometry": {"coordinates":[-74.125854,40.40373],"type":"Point"}
}