{
  "type": "Feature",
  "properties": {
    "iso:country":"US",
    "sg:address":"15 Hamilton Rd",
    "sg:city":"Glen Ridge",
    "sg:classifiers":[
        {
            "category":"Building & Trades",
            "subcategory":"Landscaping Services",
            "type":"Services"
        }
    ],
    "sg:phone":"+1 973 259 0031",
    "sg:postcode":"07028",
    "sg:province":"NJ",
    "wof:name":"Hamilton Ridge Landscape Svcs",
    "wof:placetype":"venue"
},
  "geometry": {"coordinates":[-74.21111999999999,40.796736],"type":"Point"}
}