{
  "type": "Feature",
  "properties": {
    "addr:full":"1624 Beaver Dam Rd Pt Pleasant Boro NJ 08742",
    "addr:housenumber":"1624",
    "addr:postcode":"08742",
    "addr:street":"Beaver Dam Rd Pt",
    "iso:country":"US",
    "sg:address":"1624 Beaver Dam Rd",
    "sg:city":"Pt Pleasant Boro",
    "sg:classifiers":[
        {
            "category":"Wholesale",
            "subcategory":"Hardware",
            "type":"Manufacturing & Wholesale Goods"
        },
        {
            "category":"Building & Trades",
            "subcategory":"Plumbing",
            "type":"Services"
        }
    ],
    "sg:phone":"+1 732 295 2167",
    "sg:postcode":"08742",
    "sg:province":"NJ",
    "sg:tags":[
        "heating",
        "air",
        "conditioning",
        "plumbing",
        "contractor",
        "refrigerating"
    ],
    "wof:name":"Patrick T Kerwin Inc",
    "wof:placetype":"venue"
},
  "geometry": {"coordinates":[-74.072317,40.064457],"type":"Point"}
}