{
  "type": "Feature",
  "properties": {
    "addr:full":"512 Haddonfield Rd Cherry Hill NJ 08002",
    "addr:housenumber":"512",
    "addr:postcode":"08002",
    "addr:street":"Haddonfield Rd",
    "iso:country":"US",
    "sg:address":"512 Haddonfield Rd",
    "sg:city":"Cherry Hill",
    "sg:classifiers":[
        {
            "category":"Building & Trades",
            "subcategory":"Locksmith",
            "type":"Services"
        }
    ],
    "sg:phone":"+1 856 532 0368",
    "sg:postcode":"08002",
    "sg:province":"NJ",
    "sg:tags":[
        "key"
    ],
    "wof:name":"0 And 0 and 1 24 Hour A Emergency A L",
    "wof:placetype":"venue"
},
  "geometry": {"coordinates":[-75.030743,39.934516],"type":"Point"}
}