{
  "type": "Feature",
  "properties": {
    "iso:country":"US",
    "sg:address":"163 Washington Valley Rd",
    "sg:city":"Warren",
    "sg:classifiers":[
        {
            "category":"Wholesale",
            "subcategory":"Chemicals & Plastics",
            "type":"Manufacturing & Wholesale Goods"
        }
    ],
    "sg:phone":"+1 732 302 1686",
    "sg:postcode":"07059",
    "sg:province":"NJ",
    "sg:tags":[
        "silicone"
    ],
    "wof:name":"ELCAT Inc",
    "wof:placetype":"venue"
},
  "geometry": {"coordinates":[-74.494974,40.615047],"type":"Point"}
}