{
  "type": "Feature",
  "properties": {
    "addr:full":"220 Hamburg Tpke Paterson NJ 07510",
    "addr:housenumber":"220",
    "addr:postcode":"07510",
    "addr:street":"Hamburg Tpke",
    "iso:country":"US",
    "sg:address":"220 Hamburg Tpke",
    "sg:city":"Paterson",
    "sg:classifiers":[
        {
            "category":"Health Services",
            "subcategory":"Doctor",
            "type":"Services"
        }
    ],
    "sg:phone":"+1 973 956 1200",
    "sg:postcode":"07510",
    "sg:province":"NJ",
    "sg:tags":[
        "throat",
        "surgeon",
        "ear",
        "cosmetic",
        "nose"
    ],
    "wof:name":"Kardos F L MD PA Ear Nose & Throat",
    "wof:placetype":"venue"
},
  "geometry": {"coordinates":[-74.167603,40.9147],"type":"Point"}
}