{
  "type": "Feature",
  "properties": {
    "iso:country":"US",
    "sg:address":"204 S Plainfield Ave",
    "sg:city":"South Plainfield",
    "sg:classifiers":[
        {
            "category":"Professional",
            "subcategory":"Business Services",
            "type":"Services"
        }
    ],
    "sg:phone":"+1   ",
    "sg:postcode":"07080",
    "sg:province":"NJ",
    "wof:name":"Arts Baseball Cards",
    "wof:placetype":"venue"
},
  "geometry": {"coordinates":[-74.40601100000001,40.581411],"type":"Point"}
}