{
  "type": "Feature",
  "properties": {
    "iso:country":"US",
    "sg:address":"10 Seagarden Dr",
    "sg:city":"Linwood",
    "sg:classifiers":[
        {
            "category":"Building & Trades",
            "subcategory":"Plumbing",
            "type":"Services"
        }
    ],
    "sg:phone":"+1 609 653 1592",
    "sg:postcode":"08221",
    "sg:province":"NJ",
    "sg:tags":[
        "plumbing",
        "contractor"
    ],
    "wof:name":"Martin & Sons Plumbing & Htg",
    "wof:placetype":"venue"
},
  "geometry": {"coordinates":[-74.58240000000001,39.329953],"type":"Point"}
}