{
  "type": "Feature",
  "properties": {
    "iso:country":"US",
    "sg:address":"1 Undercliff Rd",
    "sg:city":"Butler",
    "sg:classifiers":[
        {
            "category":"Professional",
            "subcategory":"Business Services",
            "type":"Services"
        }
    ],
    "sg:phone":"+1   ",
    "sg:postcode":"07405",
    "sg:province":"NJ",
    "wof:name":"Prime Express Inc",
    "wof:placetype":"venue"
},
  "geometry": {"coordinates":[-74.41784199999999,41.016338],"type":"Point"}
}