{
  "type": "Feature",
  "properties": {
    "addr:full":"1750 Deptford Center Rd Ste 2069 Woodbury NJ 08096",
    "addr:housenumber":"1750",
    "addr:postcode":"08096",
    "addr:street":"Deptford Center Rd Ste 2069",
    "iso:country":"US",
    "sg:address":"1750 Deptford Center Rd Ste 2069",
    "sg:city":"Woodbury",
    "sg:classifiers":[
        {
            "category":"Shopping",
            "subcategory":"Clothing, Apparel, & Fashions",
            "type":"Retail Goods"
        },
        {
            "category":"Shopping",
            "subcategory":"Baby Store",
            "type":"Retail Goods"
        }
    ],
    "sg:phone":"+1 856 853 5188",
    "sg:postcode":"08096",
    "sg:province":"NJ",
    "sg:tags":[
        "children's",
        "infant",
        "clothing",
        "wear",
        "girls'"
    ],
    "sg:website":"http://www.shopjustice.com",
    "wof:name":"Justice Just For Girls",
    "wof:placetype":"venue"
},
  "geometry": {"coordinates":[-75.09884099999999,39.828223],"type":"Point"}
}