{
  "type": "Feature",
  "properties": {
    "iso:country":"US",
    "sg:address":"830 Bloomfield Ave",
    "sg:city":"Clifton",
    "sg:classifiers":[
        {
            "category":"Manufacturing",
            "subcategory":"Furniture",
            "type":"Manufacturing & Wholesale Goods"
        }
    ],
    "sg:phone":"+1 973 777 7898",
    "sg:postcode":"07012",
    "sg:province":"NJ",
    "sg:tags":[
        "mfg"
    ],
    "wof:name":"Gerson Mattress Company",
    "wof:placetype":"venue"
},
  "geometry": {"coordinates":[-74.16125599999999,40.840376],"type":"Point"}
}