{
  "type": "Feature",
  "properties": {
    "addr:full":"460 State Rte 17 Paramus NJ 07652",
    "addr:housenumber":"460",
    "addr:postcode":"07652",
    "addr:street":"State Rte 17",
    "iso:country":"US",
    "sg:address":"460 State Rte 17",
    "sg:city":"Paramus",
    "sg:classifiers":[
        {
            "category":"Professional",
            "type":"Services"
        }
    ],
    "sg:phone":"+1 201 262 8423",
    "sg:postcode":"07652",
    "sg:province":"NJ",
    "sg:tags":[
        "establishment"
    ],
    "wof:name":"Peter F Pasbjerg Development",
    "wof:placetype":"venue"
},
  "geometry": {"coordinates":[-74.07269100000001,40.952594],"type":"Point"}
}