{
  "type": "Feature",
  "properties": {
    "iso:country":"US",
    "sg:address":"79 Ridge Ave",
    "sg:city":"Neptune City",
    "sg:classifiers":[
        {
            "category":"Organizations",
            "subcategory":"Professional Association",
            "type":"Services"
        }
    ],
    "sg:phone":"+1 732 776 6496",
    "sg:postcode":"07753",
    "sg:province":"NJ",
    "wof:name":"Home Based Business Council",
    "wof:placetype":"venue"
},
  "geometry": {"coordinates":[-74.026996,40.199104],"type":"Point"}
}