{
  "type": "Feature",
  "properties": {
    "iso:country":"US",
    "sg:address":"301 Federal St",
    "sg:city":"Camden",
    "sg:classifiers":[
        {
            "category":"Building & Trades",
            "subcategory":"Locksmith",
            "type":"Services"
        }
    ],
    "sg:phone":"+1 609 945 5922",
    "sg:postcode":"08103",
    "sg:province":"NJ",
    "sg:tags":[
        "key"
    ],
    "wof:name":"Adam Locksmith",
    "wof:placetype":"venue"
},
  "geometry": {"coordinates":[-75.124318,39.944427],"type":"Point"}
}