{
  "type": "Feature",
  "properties": {
    "addr:full":"570 Stelton Rd Piscataway NJ 08854",
    "addr:housenumber":"570",
    "addr:postcode":"08854",
    "addr:street":"Stelton Rd",
    "iso:country":"US",
    "sg:address":"570 Stelton Rd",
    "sg:city":"Piscataway",
    "sg:classifiers":[
        {
            "category":"Autos & Motor Vehicles",
            "subcategory":"Fuel & Gas Station",
            "type":"Retail Goods"
        }
    ],
    "sg:phone":"+1   ",
    "sg:postcode":"08854",
    "sg:province":"NJ",
    "sg:tags":[
        "station",
        "gasoline"
    ],
    "wof:name":"Amoco",
    "wof:placetype":"venue"
},
  "geometry": {"coordinates":[-74.44035,40.559463],"type":"Point"}
}