{
  "type": "Feature",
  "properties": {
    "addr:full":"146 Sherman Ave Teaneck NJ 07666",
    "addr:housenumber":"146",
    "addr:postcode":"07666",
    "addr:street":"Sherman Ave",
    "iso:country":"US",
    "sg:address":"146 Sherman Ave",
    "sg:city":"Teaneck",
    "sg:classifiers":[
        {
            "category":"Restaurant",
            "type":"Food & Drink"
        }
    ],
    "sg:phone":"+1   ",
    "sg:postcode":"07666",
    "sg:province":"NJ",
    "sg:tags":[
        "eating"
    ],
    "wof:name":"Ken Fried",
    "wof:placetype":"venue"
},
  "geometry": {"coordinates":[-74.013632,40.88048],"type":"Point"}
}