{
  "type": "Feature",
  "properties": {
    "addr:full":"1273 Broad St Bloomfield NJ 07003",
    "addr:housenumber":"1273",
    "addr:postcode":"07003",
    "addr:street":"Broad St",
    "iso:country":"US",
    "sg:address":"1273 Broad St",
    "sg:city":"Bloomfield",
    "sg:classifiers":[
        {
            "category":"Building & Trades",
            "subcategory":"Locksmith",
            "type":"Services"
        }
    ],
    "sg:phone":"+1 973 780 1478",
    "sg:postcode":"07003",
    "sg:province":"NJ",
    "sg:tags":[
        "key"
    ],
    "wof:name":"Always Available Locksmith",
    "wof:placetype":"venue"
},
  "geometry": {"coordinates":[-74.180476,40.833863],"type":"Point"}
}