{
  "type": "Feature",
  "properties": {
    "addr:full":"40 Wicklow Dr Vincentown NJ 08088",
    "addr:housenumber":"40",
    "addr:postcode":"08088",
    "addr:street":"Wicklow Dr",
    "iso:country":"US",
    "sg:address":"40 Wicklow Dr",
    "sg:city":"Vincentown",
    "sg:classifiers":[
        {
            "category":"Professional",
            "subcategory":"Management & Consulting",
            "type":"Services"
        }
    ],
    "sg:phone":"+1   ",
    "sg:postcode":"08088",
    "sg:province":"NJ",
    "sg:tags":[
        "public",
        "relations"
    ],
    "wof:name":"Denise Salnes",
    "wof:placetype":"venue"
},
  "geometry": {"coordinates":[-74.746925,39.83372],"type":"Point"}
}