{
  "type": "Feature",
  "properties": {
    "iso:country":"US",
    "sg:address":"133 Skyline Dr",
    "sg:city":"Ringwood",
    "sg:classifiers":[
        {
            "category":"Insurance",
            "subcategory":"Insurance Agent",
            "type":"Services"
        }
    ],
    "sg:phone":"+1 973 839 5678",
    "sg:postcode":"07456",
    "sg:province":"NJ",
    "wof:name":"Bischoff Insurance Inc",
    "wof:placetype":"venue"
},
  "geometry": {"coordinates":[-74.262157,41.084015],"type":"Point"}
}