{
  "type": "Feature",
  "properties": {
    "addr:full":"183 Bloom St Hackensack NJ 07601",
    "addr:housenumber":"183",
    "addr:postcode":"07601",
    "addr:street":"Bloom St",
    "iso:country":"US",
    "sg:address":"183 Bloom St",
    "sg:city":"Hackensack",
    "sg:classifiers":[
        {
            "category":"Retail",
            "subcategory":"Auto Repair",
            "type":"Services"
        }
    ],
    "sg:phone":"+1 201 342 1444",
    "sg:postcode":"07601",
    "sg:province":"NJ",
    "wof:name":"Car Check Inc",
    "wof:placetype":"venue"
},
  "geometry": {"coordinates":[-74.0466,40.872101],"type":"Point"}
}