{
  "type": "Feature",
  "properties": {
    "addr:full":"8 5th St Ridgefield Park NJ 07660",
    "addr:housenumber":"8",
    "addr:postcode":"07660",
    "addr:street":"5Th St",
    "iso:country":"US",
    "sg:address":"8 5th St",
    "sg:city":"Ridgefield Park",
    "sg:classifiers":[
        {
            "category":"Building & Trades",
            "subcategory":"Construction",
            "type":"Services"
        }
    ],
    "sg:phone":"+1 201 807 1311",
    "sg:postcode":"07660",
    "sg:province":"NJ",
    "sg:tags":[
        "carpentry",
        "contractor"
    ],
    "wof:name":"Robert Schreiber Creations",
    "wof:placetype":"venue"
},
  "geometry": {"coordinates":[-74.028897,40.859516],"type":"Point"}
}