{
  "type": "Feature",
  "properties": {
    "addr:full":"1025 E Linden Ave Linden NJ 07036",
    "addr:housenumber":"1025",
    "addr:postcode":"07036",
    "addr:street":"E Linden Ave",
    "iso:country":"US",
    "sg:address":"1025 E Linden Ave",
    "sg:city":"Linden",
    "sg:classifiers":[
        {
            "category":"Personal",
            "type":"Services"
        }
    ],
    "sg:phone":"+1 908 862 3000",
    "sg:postcode":"07036",
    "sg:province":"NJ",
    "sg:tags":[
        "towing"
    ],
    "wof:name":"Arcuri Truck & Trailer Repair Inc",
    "wof:placetype":"venue"
},
  "geometry": {"coordinates":[-74.2397,40.639301],"type":"Point"}
}