{
  "type": "Feature",
  "properties": {
    "addr:full":"61 Kresson Rd Ste A Cherry Hill NJ 08034",
    "addr:housenumber":"61",
    "addr:postcode":"08034",
    "addr:street":"Kresson Rd Ste A",
    "iso:country":"US",
    "sg:address":"61 Kresson Rd Ste A",
    "sg:city":"Cherry Hill",
    "sg:classifiers":[
        {
            "category":"Professional",
            "subcategory":"Lawyer & Legal Services",
            "type":"Services"
        }
    ],
    "sg:phone":"+1 856 428 9111",
    "sg:postcode":"08034",
    "sg:province":"NJ",
    "wof:name":"Muller James L ESQ",
    "wof:placetype":"venue"
},
  "geometry": {"coordinates":[-75.022301,39.894501],"type":"Point"}
}