{
  "type": "Feature",
  "properties": {
    "addr:full":"25 Gardenia Ct Sayreville NJ 08872",
    "addr:housenumber":"25",
    "addr:postcode":"08872",
    "addr:street":"Gardenia Ct",
    "iso:country":"US",
    "sg:address":"25 Gardenia Ct",
    "sg:city":"Sayreville",
    "sg:classifiers":[
        {
            "category":"Professional",
            "type":"Services"
        }
    ],
    "sg:phone":"+1   ",
    "sg:postcode":"08872",
    "sg:province":"NJ",
    "wof:name":"Sind Inc",
    "wof:placetype":"venue"
},
  "geometry": {"coordinates":[-74.333262,40.470483],"type":"Point"}
}