{
  "type": "Feature",
  "properties": {
    "addr:full":"34 Seaview Ave Ocean Grove NJ 07756",
    "addr:housenumber":"34",
    "addr:postcode":"07756",
    "addr:street":"Seaview Ave",
    "iso:country":"US",
    "sg:address":"34 Seaview Ave",
    "sg:city":"Ocean Grove",
    "sg:classifiers":[
        {
            "category":"Travel",
            "subcategory":"Hotels & Motels",
            "type":"Entertainment"
        }
    ],
    "sg:phone":"+1 732 774 5404",
    "sg:postcode":"07756",
    "sg:province":"NJ",
    "sg:tags":[
        "breakfast",
        "accommodation",
        "bed"
    ],
    "sg:website":"www.melroseog.com",
    "wof:name":"Melrose",
    "wof:placetype":"venue"
},
  "geometry": {"coordinates":[-74.00415,40.215811],"type":"Point"}
}