{
  "type": "Feature",
  "properties": {
    "iso:country":"US",
    "sg:address":"326 3rd St",
    "sg:city":"Lakewood",
    "sg:classifiers":[
        {
            "category":"Real Estate",
            "subcategory":"Real Estate Agent",
            "type":"Services"
        }
    ],
    "sg:phone":"+1 732 367 0129",
    "sg:postcode":"08701",
    "sg:province":"NJ",
    "sg:tags":[
        "computer",
        "sales"
    ],
    "wof:name":"Dorchester Service Corp",
    "wof:placetype":"venue"
},
  "geometry": {"coordinates":[-74.215199,40.092983],"type":"Point"}
}