{
  "type": "Feature",
  "properties": {
    "addr:full":"136 Boulevard Passaic NJ 07055",
    "addr:housenumber":"136",
    "addr:postcode":"07055",
    "addr:street":"Boulevard",
    "iso:country":"US",
    "sg:address":"136 Boulevard",
    "sg:city":"Passaic",
    "sg:classifiers":[
        {
            "category":"Shopping",
            "subcategory":"Gifts & Souvenirs",
            "type":"Retail Goods"
        }
    ],
    "sg:phone":"+1 973 473 8130",
    "sg:postcode":"07055",
    "sg:province":"NJ",
    "sg:tags":[
        "announcement",
        "invitation"
    ],
    "wof:name":"Creativations",
    "wof:placetype":"venue"
},
  "geometry": {"coordinates":[-74.129869,40.854126],"type":"Point"}
}