{
  "type": "Feature",
  "properties": {
    "addr:full":"15 Lock St Lake Hopatcong NJ 07882",
    "addr:housenumber":"15",
    "addr:postcode":"07882",
    "addr:street":"Lock St",
    "iso:country":"US",
    "sg:address":"15 Lock St",
    "sg:city":"Lake Hopatcong",
    "sg:classifiers":[
        {
            "category":"Retail",
            "subcategory":"Laundry & Dry Cleaning",
            "type":"Services"
        }
    ],
    "sg:phone":"+1 973 663 1642",
    "sg:postcode":"07882",
    "sg:province":"NJ",
    "sg:tags":[
        "cleaners"
    ],
    "wof:name":"Lakeside Quality Cleaners",
    "wof:placetype":"venue"
},
  "geometry": {"coordinates":[-74.955905,40.76473],"type":"Point"}
}