{
  "type": "Feature",
  "properties": {
    "iso:country":"US",
    "sg:address":"600 North Blvd",
    "sg:city":"Belmar",
    "sg:classifiers":[
        {
            "category":"Professional",
            "type":"Services"
        }
    ],
    "sg:phone":"+1   ",
    "sg:postcode":"07719",
    "sg:province":"NJ",
    "wof:name":"Nicholas M Jandies",
    "wof:placetype":"venue"
},
  "geometry": {"coordinates":[-74.026701,40.16734],"type":"Point"}
}