{
  "type": "Feature",
  "properties": {
    "iso:country":"US",
    "sg:address":"2214 Millburn Ave",
    "sg:city":"Maplewood",
    "sg:classifiers":[
        {
            "category":"Retail",
            "subcategory":"Repair Shop",
            "type":"Services"
        }
    ],
    "sg:phone":"+1   ",
    "sg:postcode":"07040",
    "sg:province":"NJ",
    "wof:name":"Williams Upholstery",
    "wof:placetype":"venue"
},
  "geometry": {"coordinates":[-74.285158,40.722677],"type":"Point"}
}