{
  "type": "Feature",
  "properties": {
    "iso:country":"US",
    "sg:address":"4 Bridge Ct",
    "sg:city":"Jackson",
    "sg:classifiers":[
        {
            "category":"Freight",
            "type":"Transportation"
        }
    ],
    "sg:phone":"+1 732 363 2808",
    "sg:postcode":"08527",
    "sg:province":"NJ",
    "sg:tags":[
        "local",
        "trucking"
    ],
    "wof:name":"Penntex",
    "wof:placetype":"venue"
},
  "geometry": {"coordinates":[-74.277602,40.10532],"type":"Point"}
}