{
  "type": "Feature",
  "properties": {
    "addr:full":"17 Commerce St Chatham NJ 07928",
    "addr:housenumber":"17",
    "addr:postcode":"07928",
    "addr:street":"Commerce St",
    "iso:country":"US",
    "sg:address":"17 Commerce St",
    "sg:city":"Chatham",
    "sg:classifiers":[
        {
            "category":"Real Estate",
            "subcategory":"Architect",
            "type":"Services"
        }
    ],
    "sg:phone":"+1 973 635 5900",
    "sg:postcode":"07928",
    "sg:province":"NJ",
    "wof:name":"Cts Group Architectureplanning",
    "wof:placetype":"venue"
},
  "geometry": {"coordinates":[-74.381038,40.730601],"type":"Point"}
}