{
  "type": "Feature",
  "properties": {
    "iso:country":"US",
    "sg:address":"275 Pine St",
    "sg:city":"Wyckoff",
    "sg:classifiers":[
        {
            "category":"Travel",
            "subcategory":"Travel Agent",
            "type":"Entertainment"
        }
    ],
    "sg:phone":"+1 201 934 6800",
    "sg:postcode":"07481",
    "sg:province":"NJ",
    "sg:tags":[
        "agency"
    ],
    "wof:name":"World Vision Travel Inc",
    "wof:placetype":"venue"
},
  "geometry": {"coordinates":[-74.163961,41.017023],"type":"Point"}
}