{
  "type": "Feature",
  "properties": {
    "addr:full":"6601 Ventnor Ave Ventnor City NJ 08406",
    "addr:housenumber":"6601",
    "addr:postcode":"08406",
    "addr:street":"Ventnor Ave",
    "iso:country":"US",
    "sg:address":"6601 Ventnor Ave",
    "sg:city":"Ventnor City",
    "sg:classifiers":[
        {
            "category":"Professional",
            "subcategory":"Detective & Security Services",
            "type":"Services"
        }
    ],
    "sg:phone":"+1 609 487 9001",
    "sg:postcode":"08406",
    "sg:province":"NJ",
    "sg:tags":[
        "investigator"
    ],
    "wof:name":"Tax Help",
    "wof:placetype":"venue"
},
  "geometry": {"coordinates":[-74.48483299999999,39.336907],"type":"Point"}
}