{
  "type": "Feature",
  "properties": {
    "addr:full":"18122 Allison Sq Princeton Jct NJ 08550",
    "addr:housenumber":"18122",
    "addr:postcode":"08550",
    "addr:street":"Allison Sq",
    "iso:country":"US",
    "sg:address":"18122 Allison Sq",
    "sg:city":"Princeton Jct",
    "sg:classifiers":[
        {
            "category":"Professional",
            "type":"Services"
        }
    ],
    "sg:phone":"+1 609 799 5025",
    "sg:postcode":"08550",
    "sg:province":"NJ",
    "wof:name":"Corporate Services Churchill",
    "wof:placetype":"venue"
},
  "geometry": {"coordinates":[-74.640456,40.298851],"type":"Point"}
}