{
  "type": "Feature",
  "properties": {
    "iso:country":"US",
    "sg:address":"215 Westfield Ave E",
    "sg:city":"Roselle Park",
    "sg:classifiers":[
        {
            "category":"Shopping",
            "subcategory":"Gifts & Souvenirs",
            "type":"Retail Goods"
        }
    ],
    "sg:phone":"+1   ",
    "sg:postcode":"07204",
    "sg:province":"NJ",
    "wof:name":"Telephone Calling Cards",
    "wof:placetype":"venue"
},
  "geometry": {"coordinates":[-74.25774699999999,40.662568],"type":"Point"}
}