{
  "type": "Feature",
  "properties": {
    "iso:country":"US",
    "sg:address":"298 S Delsea Dr",
    "sg:city":"Vineland",
    "sg:classifiers":[
        {
            "category":"Health Services",
            "subcategory":"Doctor",
            "type":"Services"
        }
    ],
    "sg:phone":"+1 856 342 3321",
    "sg:postcode":"08360",
    "sg:province":"NJ",
    "sg:tags":[
        "physician",
        "surgeon"
    ],
    "wof:name":"Premier Orthopaedic Assoc",
    "wof:placetype":"venue"
},
  "geometry": {"coordinates":[-75.043637,39.480291],"type":"Point"}
}