{
  "type": "Feature",
  "properties": {
    "iso:country":"US",
    "sg:address":"54 Plauderville Ave Ste 2",
    "sg:city":"Garfield",
    "sg:classifiers":[
        {
            "category":"Health Services",
            "subcategory":"Doctor",
            "type":"Services"
        }
    ],
    "sg:phone":"+1 973 253 0600",
    "sg:postcode":"07026",
    "sg:province":"NJ",
    "sg:tags":[
        "surgeon",
        "oral"
    ],
    "wof:name":"Dziarmaga Mare DDS",
    "wof:placetype":"venue"
},
  "geometry": {"coordinates":[-74.1091,40.885201],"type":"Point"}
}