{
  "type": "Feature",
  "properties": {
    "addr:full":"64 Hansbury Ave Newark NJ 07112",
    "addr:housenumber":"64",
    "addr:postcode":"07112",
    "addr:street":"Hansbury Ave",
    "iso:country":"US",
    "sg:address":"64 Hansbury Ave",
    "sg:city":"Newark",
    "sg:classifiers":[
        {
            "category":"Shopping",
            "subcategory":"Clothing, Apparel, & Fashions",
            "type":"Retail Goods"
        }
    ],
    "sg:phone":"+1   ",
    "sg:postcode":"07112",
    "sg:province":"NJ",
    "wof:name":"Snl Boutiques LLC",
    "wof:placetype":"venue"
},
  "geometry": {"coordinates":[-74.21467800000001,40.704285],"type":"Point"}
}