{
  "type": "Feature",
  "properties": {
    "addr:full":"1222 Atlantic Ave Atlantic City NJ 08401",
    "addr:housenumber":"1222",
    "addr:postcode":"08401",
    "addr:street":"Atlantic Ave",
    "iso:country":"US",
    "sg:address":"1222 Atlantic Ave",
    "sg:city":"Atlantic City",
    "sg:classifiers":[
        {
            "category":"Retail",
            "subcategory":"Laundry & Dry Cleaning",
            "type":"Services"
        }
    ],
    "sg:phone":"+1   ",
    "sg:postcode":"08401",
    "sg:province":"NJ",
    "sg:tags":[
        "drycleaning",
        "plant"
    ],
    "wof:name":"Atlantic Cleaners",
    "wof:placetype":"venue"
},
  "geometry": {"coordinates":[-74.425527,39.363139],"type":"Point"}
}