{
  "type": "Feature",
  "properties": {
    "iso:country":"US",
    "sg:address":"2005 State Rte 35",
    "sg:city":"Oakhurst",
    "sg:classifiers":[
        {
            "category":"Education",
            "subcategory":"Special Training",
            "type":"Public Place"
        }
    ],
    "sg:phone":"+1 732 531 7676",
    "sg:postcode":"07755",
    "sg:province":"NJ",
    "sg:tags":[
        "instruction",
        "music"
    ],
    "wof:name":"Shore Music Academy LLC",
    "wof:placetype":"venue"
},
  "geometry": {"coordinates":[-74.04191,40.264576],"type":"Point"}
}