{
  "type": "Feature",
  "properties": {
    "addr:full":"145 State Rte 73 Voorhees NJ 08043",
    "addr:housenumber":"145",
    "addr:postcode":"08043",
    "addr:street":"State Rte 73",
    "iso:country":"US",
    "sg:address":"145 State Rte 73",
    "sg:city":"Voorhees",
    "sg:classifiers":[
        {
            "category":"Wholesale",
            "subcategory":"Machinery & Supplies",
            "type":"Manufacturing & Wholesale Goods"
        }
    ],
    "sg:phone":"+1 856 767 5900",
    "sg:postcode":"08043",
    "sg:province":"NJ",
    "sg:tags":[
        "equipment"
    ],
    "sg:website":"www.bindermachinery.com",
    "wof:name":"Binder Machinery Co Inc",
    "wof:placetype":"venue"
},
  "geometry": {"coordinates":[-74.925887,39.834994],"type":"Point"}
}