{
  "type": "Feature",
  "properties": {
    "iso:country":"US",
    "sg:address":"101 S Orange Ave",
    "sg:city":"South Orange",
    "sg:classifiers":[
        {
            "category":"Government",
            "subcategory":"Office",
            "type":"Public Place"
        }
    ],
    "sg:phone":"+1 973 378 7741",
    "sg:postcode":"07079",
    "sg:province":"NJ",
    "sg:tags":[
        "village"
    ],
    "wof:name":"South Orange Recycling Info",
    "wof:placetype":"venue"
},
  "geometry": {"coordinates":[-74.256917,40.745483],"type":"Point"}
}