{
  "type": "Feature",
  "properties": {
    "iso:country":"US",
    "sg:address":"25 Berkeley Ter",
    "sg:city":"Livingston",
    "sg:classifiers":[
        {
            "category":"Real Estate",
            "subcategory":"Real Estate Operator",
            "type":"Services"
        }
    ],
    "sg:phone":"+1   ",
    "sg:postcode":"07039",
    "sg:province":"NJ",
    "sg:tags":[
        "building",
        "nonresidential"
    ],
    "wof:name":"Leico Realestate",
    "wof:placetype":"venue"
},
  "geometry": {"coordinates":[-74.31836699999999,40.7867],"type":"Point"}
}