{
  "type": "Feature",
  "properties": {
    "addr:full":"133 Nottingham Dr Eatontown NJ 07724",
    "addr:housenumber":"133",
    "addr:postcode":"07724",
    "addr:street":"Nottingham Dr",
    "iso:country":"US",
    "sg:address":"133 Nottingham Dr",
    "sg:city":"Eatontown",
    "sg:classifiers":[
        {
            "category":"Professional",
            "type":"Services"
        }
    ],
    "sg:phone":"+1   ",
    "sg:postcode":"07724",
    "sg:province":"NJ",
    "wof:name":"Grimsgaard Stenography",
    "wof:placetype":"venue"
},
  "geometry": {"coordinates":[-74.069371,40.289034],"type":"Point"}
}