{
  "type": "Feature",
  "properties": {
    "iso:country":"US",
    "sg:address":"201 Terminal Ave",
    "sg:city":"Clark",
    "sg:classifiers":[
        {
            "category":"Manufacturing",
            "subcategory":"Chemicals & Compounds",
            "type":"Manufacturing & Wholesale Goods"
        }
    ],
    "sg:phone":"+1 732 499 4489",
    "sg:postcode":"07066",
    "sg:province":"NJ",
    "sg:tags":[
        "hair",
        "mfg",
        "color",
        "cosmetic",
        "preparation",
        "fragrance"
    ],
    "wof:name":"LOreal USA Inc",
    "wof:placetype":"venue"
},
  "geometry": {"coordinates":[-74.314272,40.63196],"type":"Point"}
}