{
  "type": "Feature",
  "properties": {
    "addr:full":"1135 US Hwy 9 Cape May Ct Hse NJ 08210",
    "addr:housenumber":"1135",
    "addr:postcode":"08210",
    "addr:street":"Us Hwy 9 Cape May Ct",
    "iso:country":"US",
    "sg:address":"1135 US Hwy 9",
    "sg:city":"Cape May Ct Hse",
    "sg:classifiers":[
        {
            "category":"Home & Garden",
            "subcategory":"Building Materials",
            "type":"Retail Goods"
        }
    ],
    "sg:phone":"+1 609 465 8787",
    "sg:postcode":"08210",
    "sg:province":"NJ",
    "sg:website":"www.universalsupply.com",
    "wof:name":"Universal Supply Co Inc",
    "wof:placetype":"venue"
},
  "geometry": {"coordinates":[-74.83772,39.058858],"type":"Point"}
}