{
  "type": "Feature",
  "properties": {
    "addr:full":"271 South St Eatontown NJ 07724",
    "addr:housenumber":"271",
    "addr:postcode":"07724",
    "addr:street":"South St",
    "iso:country":"US",
    "sg:address":"271 South St",
    "sg:city":"Eatontown",
    "sg:classifiers":[
        {
            "category":"Organizations",
            "subcategory":"Religious Organization",
            "type":"Services"
        }
    ],
    "sg:phone":"+1 732 460 0787",
    "sg:postcode":"07724",
    "sg:province":"NJ",
    "sg:tags":[
        "church"
    ],
    "wof:name":"Mt Zion AME Zion Church",
    "wof:placetype":"venue"
},
  "geometry": {"coordinates":[-74.059983,40.296529],"type":"Point"}
}