{
  "type": "Feature",
  "properties": {
    "addr:full":"2 Buck Ln Marlboro NJ 07746",
    "addr:housenumber":"2",
    "addr:postcode":"07746",
    "addr:street":"Buck Ln",
    "iso:country":"US",
    "sg:address":"2 Buck Ln",
    "sg:city":"Marlboro",
    "sg:classifiers":[
        {
            "category":"Health Services",
            "subcategory":"Doctor",
            "type":"Services"
        }
    ],
    "sg:phone":"+1 732 431 8111",
    "sg:postcode":"07746",
    "sg:province":"NJ",
    "sg:tags":[
        "dentist"
    ],
    "wof:name":"Stuart S Albin DDS",
    "wof:placetype":"venue"
},
  "geometry": {"coordinates":[-74.244039,40.317098],"type":"Point"}
}