{
  "type": "Feature",
  "properties": {
    "addr:full":"18 Statesboro Rd Freehold NJ 07728",
    "addr:housenumber":"18",
    "addr:postcode":"07728",
    "addr:street":"Statesboro Rd",
    "iso:country":"US",
    "sg:address":"18 Statesboro Rd",
    "sg:city":"Freehold",
    "sg:classifiers":[
        {
            "category":"Building & Trades",
            "subcategory":"Construction",
            "type":"Services"
        }
    ],
    "sg:phone":"+1 732 866 0503",
    "sg:postcode":"07728",
    "sg:province":"NJ",
    "sg:tags":[
        "excavating",
        "contractor"
    ],
    "wof:name":"Ted's Landscaping & Paving Inc",
    "wof:placetype":"venue"
},
  "geometry": {"coordinates":[-74.21026999999999,40.212714],"type":"Point"}
}