{
  "type": "Feature",
  "properties": {
    "addr:full":"387 Berryman Pl Orange NJ 07050",
    "addr:housenumber":"387",
    "addr:postcode":"07050",
    "addr:street":"Berryman Pl",
    "iso:country":"US",
    "sg:address":"387 Berryman Pl",
    "sg:city":"Orange",
    "sg:classifiers":[
        {
            "category":"Home & Garden",
            "subcategory":"Carpets & Floor Coverings",
            "type":"Retail Goods"
        }
    ],
    "sg:phone":"+1   ",
    "sg:postcode":"07050",
    "sg:province":"NJ",
    "wof:name":"A1 Carpet Wholesalers & Clean",
    "wof:placetype":"venue"
},
  "geometry": {"coordinates":[-74.228195,40.783328],"type":"Point"}
}