{
  "type": "Feature",
  "properties": {
    "iso:country":"US",
    "sg:address":"2200 Fletcher Ave Ste 10",
    "sg:city":"Fort Lee",
    "sg:classifiers":[
        {
            "category":"Banks & Credit Unions",
            "subcategory":"Investment Brokerage",
            "type":"Services"
        }
    ],
    "sg:phone":"+1 201 346 4335",
    "sg:postcode":"07024",
    "sg:province":"NJ",
    "sg:tags":[
        "investing"
    ],
    "wof:name":"Grand Slam",
    "wof:placetype":"venue"
},
  "geometry": {"coordinates":[-73.971209,40.859693],"type":"Point"}
}