{
  "type": "Feature",
  "properties": {
    "addr:full":"7000 Kennedy Blvd E West New York NJ 07093",
    "addr:housenumber":"7000",
    "addr:postcode":"07093",
    "addr:street":"Kennedy Blvd E West",
    "iso:country":"US",
    "sg:address":"7000 Kennedy Blvd E",
    "sg:city":"West New York",
    "sg:classifiers":[
        {
            "category":"Professional",
            "subcategory":"Accounting & Tax Preparation",
            "type":"Services"
        }
    ],
    "sg:phone":"+1 201 662 8800",
    "sg:postcode":"07093",
    "sg:province":"NJ",
    "sg:tags":[
        "accountant"
    ],
    "wof:name":"Baldomero Joseph A Jr CPA",
    "wof:placetype":"venue"
},
  "geometry": {"coordinates":[-74.00050400000001,40.791302],"type":"Point"}
}