{
  "type": "Feature",
  "properties": {
    "addr:full":"22 Madison Ave Paramus NJ 07652",
    "addr:housenumber":"22",
    "addr:postcode":"07652",
    "addr:street":"Madison Ave",
    "iso:country":"US",
    "sg:address":"22 Madison Ave",
    "sg:city":"Paramus",
    "sg:classifiers":[
        {
            "category":"Health Services",
            "subcategory":"Doctor",
            "type":"Services"
        },
        {
            "category":"Health Services",
            "subcategory":"Medical Lab",
            "type":"Services"
        }
    ],
    "sg:phone":"+1 201 546 5336",
    "sg:postcode":"07652",
    "sg:province":"NJ",
    "sg:tags":[
        "physician",
        "practitioner",
        "medicine",
        "laboratory",
        "alternative",
        "surgeon"
    ],
    "sg:website":"http://drfinn.net",
    "wof:name":"Advanced Medical Care Center",
    "wof:placetype":"venue"
},
  "geometry": {"coordinates":[-74.07048,40.922058],"type":"Point"}
}