{
  "type": "Feature",
  "properties": {
    "iso:country":"US",
    "sg:address":"366 Pacific St",
    "sg:city":"Paterson",
    "sg:classifiers":[
        {
            "category":"Professional",
            "subcategory":"Computer Services",
            "type":"Services"
        }
    ],
    "sg:phone":"+1 973 523 7073",
    "sg:postcode":"07503",
    "sg:province":"NJ",
    "sg:tags":[
        "programing",
        "custom"
    ],
    "wof:name":"Java Java",
    "wof:placetype":"venue"
},
  "geometry": {"coordinates":[-74.16007999999999,40.894447],"type":"Point"}
}