{
  "type": "Feature",
  "properties": {
    "addr:full":"101 Harmon St Jersey City NJ 07304",
    "addr:housenumber":"101",
    "addr:postcode":"07304",
    "addr:street":"Harmon St",
    "iso:country":"US",
    "sg:address":"101 Harmon St",
    "sg:city":"Jersey City",
    "sg:classifiers":[
        {
            "category":"Professional",
            "type":"Services"
        }
    ],
    "sg:phone":"+1   ",
    "sg:postcode":"07304",
    "sg:province":"NJ",
    "wof:name":"Manic Management",
    "wof:placetype":"venue"
},
  "geometry": {"coordinates":[-74.070088,40.715519],"type":"Point"}
}