{
  "type": "Feature",
  "properties": {
    "addr:full":"59 S White Horse Pike Berlin NJ 08009",
    "addr:housenumber":"59",
    "addr:postcode":"08009",
    "addr:street":"S White Horse Pike",
    "iso:country":"US",
    "sg:address":"59 S White Horse Pike",
    "sg:city":"Berlin",
    "sg:classifiers":[
        {
            "category":"Government",
            "subcategory":"Office",
            "type":"Public Place"
        }
    ],
    "sg:phone":"+1 856 767 0022",
    "sg:postcode":"08009",
    "sg:province":"NJ",
    "sg:tags":[
        "village"
    ],
    "wof:name":"Berlin Sewer Clerk",
    "wof:placetype":"venue"
},
  "geometry": {"coordinates":[-74.932743,39.79649],"type":"Point"}
}