{
  "type": "Feature",
  "properties": {
    "addr:full":"6511 Mill Rd Egg Harbor Twp NJ 08234",
    "addr:housenumber":"6511",
    "addr:postcode":"08234",
    "addr:street":"Mill Rd",
    "iso:country":"US",
    "sg:address":"6511 Mill Rd",
    "sg:city":"Egg Harbor Twp",
    "sg:classifiers":[
        {
            "category":"Real Estate",
            "subcategory":"Architect",
            "type":"Services"
        }
    ],
    "sg:phone":"+1 609 927 9287",
    "sg:postcode":"08234",
    "sg:province":"NJ",
    "wof:name":"Blackney Hayes Architects",
    "wof:placetype":"venue"
},
  "geometry": {"coordinates":[-74.606261,39.382553],"type":"Point"}
}