{
  "type": "Feature",
  "properties": {
    "addr:full":"300 Cromwell St Phillipsburg NJ 08865",
    "addr:housenumber":"300",
    "addr:postcode":"08865",
    "addr:street":"Cromwell St",
    "iso:country":"US",
    "sg:address":"300 Cromwell St",
    "sg:city":"Phillipsburg",
    "sg:classifiers":[
        {
            "category":"Organizations",
            "subcategory":"Religious Organization",
            "type":"Services"
        }
    ],
    "sg:phone":"+1 908 859 0134",
    "sg:postcode":"08865",
    "sg:province":"NJ",
    "sg:tags":[
        "church"
    ],
    "sg:website":"www.fellowshipch.org",
    "wof:name":"Fellowship Church",
    "wof:placetype":"venue"
},
  "geometry": {"coordinates":[-75.17144999999999,40.701088],"type":"Point"}
}