{
  "type": "Feature",
  "properties": {
    "iso:country":"US",
    "sg:address":"12 W Mantua Ave",
    "sg:city":"Wenonah",
    "sg:classifiers":[
        {
            "category":"Real Estate",
            "subcategory":"Surveying",
            "type":"Services"
        }
    ],
    "sg:phone":"+1   ",
    "sg:postcode":"08090",
    "sg:province":"NJ",
    "sg:tags":[
        "engineering"
    ],
    "wof:name":"Civalier Engrg & Surveying",
    "wof:placetype":"venue"
},
  "geometry": {"coordinates":[-75.151995,39.791092],"type":"Point"}
}