{
  "type": "Feature",
  "properties": {
    "iso:country":"US",
    "sg:address":"189 George St",
    "sg:city":"New Brunswick",
    "sg:classifiers":[
        {
            "category":"Professional",
            "type":"Services"
        }
    ],
    "sg:phone":"+1 732 246 5198",
    "sg:postcode":"08901",
    "sg:province":"NJ",
    "sg:tags":[
        "establishment"
    ],
    "wof:name":"YCS New Brunswick",
    "wof:placetype":"venue"
},
  "geometry": {"coordinates":[-74.440288,40.487543],"type":"Point"}
}