{
  "type": "Feature",
  "properties": {
    "addr:full":"12E Great Meadow Ln East Hanover NJ 07936",
    "addr:housenumber":"12e",
    "addr:postcode":"07936",
    "addr:street":"Great Meadow Ln",
    "iso:country":"US",
    "sg:address":"12E Great Meadow Ln",
    "sg:city":"East Hanover",
    "sg:classifiers":[
        {
            "category":"Building & Trades",
            "subcategory":"Cleaning & Sanitation",
            "type":"Services"
        }
    ],
    "sg:phone":"+1 973 887 9100",
    "sg:postcode":"07936",
    "sg:province":"NJ",
    "sg:tags":[
        "carpet"
    ],
    "wof:name":"Servpro of East Central Morris County",
    "wof:placetype":"venue"
},
  "geometry": {"coordinates":[-74.394859,40.80254],"type":"Point"}
}