{
  "type": "Feature",
  "properties": {
    "iso:country":"US",
    "sg:address":"39 Hewson Ave",
    "sg:city":"Waldwick",
    "sg:classifiers":[
        {
            "category":"Manufacturing",
            "subcategory":"Electronics",
            "type":"Manufacturing & Wholesale Goods"
        },
        {
            "category":"Building & Trades",
            "subcategory":"Electrical",
            "type":"Services"
        }
    ],
    "sg:phone":"+1 201 445 7808",
    "sg:postcode":"07463",
    "sg:province":"NJ",
    "sg:tags":[
        "control",
        "system",
        "controls",
        "regulator",
        "regulators-control",
        "panel"
    ],
    "wof:name":"Tri-Tec Manufacturing",
    "wof:placetype":"venue"
},
  "geometry": {"coordinates":[-74.123397,41.014874],"type":"Point"}
}