{
  "type": "Feature",
  "properties": {
    "addr:full":"2372 Atco Ave Atco NJ 08004",
    "addr:postcode":"2372;08004",
    "addr:street":"Atco Ave",
    "iso:country":"US",
    "sg:address":"2372 Atco Ave",
    "sg:city":"Atco",
    "sg:classifiers":[
        {
            "category":"Professional",
            "type":"Services"
        }
    ],
    "sg:phone":"+1 856 719 0451",
    "sg:postcode":"08004",
    "sg:province":"NJ",
    "sg:tags":[
        "establishment"
    ],
    "wof:name":"Heat & Control Inc",
    "wof:placetype":"venue"
},
  "geometry": {"coordinates":[-74.87169799999999,39.776629],"type":"Point"}
}