{
  "type": "Feature",
  "properties": {
    "iso:country":"US",
    "sg:address":"2325 South Ave",
    "sg:city":"Scotch Plains",
    "sg:classifiers":[
        {
            "category":"Government",
            "subcategory":"Office",
            "type":"Public Place"
        }
    ],
    "sg:phone":"+1 908 789 3690",
    "sg:postcode":"07076",
    "sg:province":"NJ",
    "sg:website":"www.ucnj.org",
    "wof:name":"Union County Operational Svc",
    "wof:placetype":"venue"
},
  "geometry": {"coordinates":[-74.367294,40.64595],"type":"Point"}
}