{
  "type": "Feature",
  "properties": {
    "addr:full":"301 Springfield Ave Berkeley Heights NJ 07922",
    "addr:housenumber":"301",
    "addr:postcode":"07922",
    "addr:street":"Springfield Ave",
    "iso:country":"US",
    "sg:address":"301 Springfield Ave",
    "sg:city":"Berkeley Heights",
    "sg:classifiers":[
        {
            "category":"Restaurant",
            "type":"Food & Drink"
        }
    ],
    "sg:phone":"+1 908 665 8555",
    "sg:postcode":"07922",
    "sg:province":"NJ",
    "sg:website":"www.grossipizza.com/",
    "wof:name":"Cafe Grossi",
    "wof:placetype":"venue"
},
  "geometry": {"coordinates":[-74.435472,40.688466],"type":"Point"}
}