{
  "type": "Feature",
  "properties": {
    "iso:country":"US",
    "sg:address":"13 Wagaraw Blvd",
    "sg:city":"Haledon",
    "sg:classifiers":[
        {
            "category":"Education",
            "subcategory":"School",
            "type":"Public Place"
        }
    ],
    "sg:phone":"+1   ",
    "sg:postcode":"07508",
    "sg:province":"NJ",
    "wof:name":"Pissaic Cnty Eductl Svcs Comm",
    "wof:placetype":"venue"
},
  "geometry": {"coordinates":[-74.177097,40.934633],"type":"Point"}
}