{
  "type": "Feature",
  "properties": {
    "iso:country":"US",
    "sg:address":"442 Willow Grove Rd",
    "sg:city":"Elmer",
    "sg:classifiers":[
        {
            "category":"Professional",
            "subcategory":"Management & Consulting",
            "type":"Services"
        }
    ],
    "sg:phone":"+1   ",
    "sg:postcode":"08318",
    "sg:province":"NJ",
    "sg:tags":[
        "product",
        "promotional"
    ],
    "wof:name":"Adventures In Advertising Mark",
    "wof:placetype":"venue"
},
  "geometry": {"coordinates":[-75.124886,39.573233],"type":"Point"}
}