{
  "type": "Feature",
  "properties": {
    "iso:country":"US",
    "sg:address":"500 Lincoln Blvd",
    "sg:city":"Middlesex",
    "sg:classifiers":[
        {
            "category":"Professional",
            "subcategory":"Research",
            "type":"Services"
        }
    ],
    "sg:phone":"+1 732 271 8588",
    "sg:postcode":"08846",
    "sg:province":"NJ",
    "sg:tags":[
        "laboratory"
    ],
    "wof:name":"Nutrabiotics Research Labs",
    "wof:placetype":"venue"
},
  "geometry": {"coordinates":[-74.49514499999999,40.571146],"type":"Point"}
}