{
  "type": "Feature",
  "properties": {
    "addr:full":"671 East Dr Oradell NJ 07649",
    "addr:housenumber":"671",
    "addr:postcode":"07649",
    "addr:street":"East Dr",
    "iso:country":"US",
    "sg:address":"671 East Dr",
    "sg:city":"Oradell",
    "sg:classifiers":[
        {
            "category":"Communications",
            "subcategory":"Film & Video Production",
            "type":"Services"
        }
    ],
    "sg:phone":"+1   ",
    "sg:postcode":"07649",
    "sg:province":"NJ",
    "sg:tags":[
        "motion"
    ],
    "wof:name":"Young Productions",
    "wof:placetype":"venue"
},
  "geometry": {"coordinates":[-74.03308800000001,40.963441],"type":"Point"}
}