{
  "type": "Feature",
  "properties": {
    "iso:country":"US",
    "sg:address":"321 Maple St",
    "sg:city":"Perth Amboy",
    "sg:classifiers":[
        {
            "category":"Professional",
            "subcategory":"Detective & Security Services",
            "type":"Services"
        }
    ],
    "sg:phone":"+1 732 826 2583",
    "sg:postcode":"08861",
    "sg:province":"NJ",
    "sg:tags":[
        "car"
    ],
    "wof:name":"Gotcha Investigation",
    "wof:placetype":"venue"
},
  "geometry": {"coordinates":[-74.271246,40.511177],"type":"Point"}
}