{
  "type": "Feature",
  "properties": {
    "addr:full":"31 Evergreen Rd New Egypt NJ 08533",
    "addr:housenumber":"31",
    "addr:postcode":"08533",
    "addr:street":"Evergreen Rd",
    "iso:country":"US",
    "sg:address":"31 Evergreen Rd",
    "sg:city":"New Egypt",
    "sg:classifiers":[
        {
            "category":"Building & Trades",
            "subcategory":"Construction",
            "type":"Services"
        }
    ],
    "sg:phone":"+1 609 758 0623",
    "sg:postcode":"08533",
    "sg:province":"NJ",
    "sg:tags":[
        "roofing",
        "contractor"
    ],
    "wof:name":"S & L Roofing & Siding",
    "wof:placetype":"venue"
},
  "geometry": {"coordinates":[-74.53071799999999,40.069193],"type":"Point"}
}