{
  "type": "Feature",
  "properties": {
    "iso:country":"US",
    "sg:address":"105 E Front St",
    "sg:city":"Plainfield",
    "sg:classifiers":[
        {
            "category":"Professional",
            "subcategory":"Accounting & Tax Preparation",
            "type":"Services"
        }
    ],
    "sg:phone":"+1 908 226 1040",
    "sg:postcode":"07060",
    "sg:province":"NJ",
    "sg:tags":[
        "consultant"
    ],
    "sg:website":"www.taxjohn.com",
    "wof:name":"John Tax Income Tax Svc",
    "wof:placetype":"venue"
},
  "geometry": {"coordinates":[-74.422162,40.620216],"type":"Point"}
}