{
  "type": "Feature",
  "properties": {
    "iso:country":"US",
    "sg:address":"43 Floral Ave",
    "sg:city":"New Providence",
    "sg:classifiers":[
        {
            "category":"Manufacturing",
            "subcategory":"Printing",
            "type":"Manufacturing & Wholesale Goods"
        }
    ],
    "sg:phone":"+1 908 464 9163",
    "sg:postcode":"07974",
    "sg:province":"NJ",
    "sg:tags":[
        "lithographic",
        "commercial",
        "typesetting"
    ],
    "wof:name":"Bantam Press",
    "wof:placetype":"venue"
},
  "geometry": {"coordinates":[-74.402593,40.695873],"type":"Point"}
}