{
  "type": "Feature",
  "properties": {
    "iso:country":"US",
    "sg:address":"71 Roseland Ave",
    "sg:city":"Caldwell",
    "sg:classifiers":[
        {
            "category":"Building & Trades",
            "subcategory":"Landscaping Services",
            "type":"Services"
        }
    ],
    "sg:phone":"+1 973 226 5764",
    "sg:postcode":"07006",
    "sg:province":"NJ",
    "sg:tags":[
        "landscape",
        "contractor"
    ],
    "wof:name":"Redbud Landscaping",
    "wof:placetype":"venue"
},
  "geometry": {"coordinates":[-74.276871,40.837452],"type":"Point"}
}