{
  "type": "Feature",
  "properties": {
    "iso:country":"US",
    "sg:address":"853 Briar Ave",
    "sg:city":"Toms River",
    "sg:classifiers":[
        {
            "category":"Building & Trades",
            "subcategory":"Landscaping Services",
            "type":"Services"
        }
    ],
    "sg:phone":"+1 732 270 9422",
    "sg:postcode":"08753",
    "sg:province":"NJ",
    "sg:tags":[
        "lawn",
        "landscape",
        "maintenance",
        "grounds"
    ],
    "wof:name":"Earth Groomers Inc",
    "wof:placetype":"venue"
},
  "geometry": {"coordinates":[-74.15892599999999,39.96763],"type":"Point"}
}