{
  "type": "Feature",
  "properties": {
    "iso:country":"US",
    "sg:address":"1757 Mohawk Dr",
    "sg:city":"Toms River",
    "sg:classifiers":[
        {
            "category":"Building & Trades",
            "subcategory":"Landscaping Services",
            "type":"Services"
        }
    ],
    "sg:phone":"+1 732 929 0690",
    "sg:postcode":"08753",
    "sg:province":"NJ",
    "sg:tags":[
        "landscape",
        "contractor"
    ],
    "wof:name":"Zebra Lawn Care",
    "wof:placetype":"venue"
},
  "geometry": {"coordinates":[-74.14694299999999,39.956],"type":"Point"}
}