{
  "type": "Feature",
  "properties": {
    "iso:country":"US",
    "sg:address":"2601 Belmar Blvd",
    "sg:city":"Belmar",
    "sg:classifiers":[
        {
            "category":"Building & Trades",
            "subcategory":"Electrical",
            "type":"Services"
        },
        {
            "category":"Professional",
            "subcategory":"Computer Services",
            "type":"Services"
        }
    ],
    "sg:phone":"+1 732 681 6820",
    "sg:postcode":"07719",
    "sg:province":"NJ",
    "wof:name":"Jersey Network Associates Inc",
    "wof:placetype":"venue"
},
  "geometry": {"coordinates":[-74.064438,40.177516],"type":"Point"}
}