{
  "type": "Feature",
  "properties": {
    "iso:country":"US",
    "sg:address":"73 Lime Kiln Rd",
    "sg:city":"Columbia",
    "sg:classifiers":[
        {
            "category":"Building & Trades",
            "subcategory":"Construction",
            "type":"Services"
        }
    ],
    "sg:phone":"+1 908 496 9742",
    "sg:postcode":"07832",
    "sg:province":"NJ",
    "sg:tags":[
        "excavating",
        "contractor"
    ],
    "wof:name":"Eric Neuwirth Excavating Inc",
    "wof:placetype":"venue"
},
  "geometry": {"coordinates":[-75.038129,40.915708],"type":"Point"}
}