{
  "type": "Feature",
  "properties": {
    "iso:country":"US",
    "sg:address":"368 Janes Chapel Rd",
    "sg:city":"Oxford",
    "sg:classifiers":[
        {
            "category":"Freight",
            "type":"Transportation"
        }
    ],
    "sg:phone":"+1 908 637 8329",
    "sg:postcode":"07863",
    "sg:province":"NJ",
    "sg:tags":[
        "operator",
        "local",
        "trucking"
    ],
    "wof:name":"L&L Express",
    "wof:placetype":"venue"
},
  "geometry": {"coordinates":[-74.934849,40.836831],"type":"Point"}
}