{
  "type": "Feature",
  "properties": {
    "addr:full":"710 Springfield Ave Newark NJ 07103",
    "addr:housenumber":"710",
    "addr:postcode":"07103",
    "addr:street":"Springfield Ave",
    "iso:country":"US",
    "sg:address":"710 Springfield Ave",
    "sg:city":"Newark",
    "sg:classifiers":[
        {
            "category":"Personal",
            "subcategory":"Beauty Salon",
            "type":"Services"
        }
    ],
    "sg:phone":"+1   ",
    "sg:postcode":"07103",
    "sg:province":"NJ",
    "sg:tags":[
        "shop"
    ],
    "wof:name":"Nubian Kuts",
    "wof:placetype":"venue"
},
  "geometry": {"coordinates":[-74.213477,40.729839],"type":"Point"}
}