{
  "type": "Feature",
  "properties": {
    "addr:full":"17 Sweetmans Ln Manalapan NJ 07726",
    "addr:housenumber":"17",
    "addr:postcode":"07726",
    "addr:street":"Sweetmans Ln",
    "iso:country":"US",
    "sg:address":"17 Sweetmans Ln",
    "sg:city":"Manalapan",
    "sg:classifiers":[
        {
            "category":"Home & Garden",
            "subcategory":"Building Materials",
            "type":"Retail Goods"
        }
    ],
    "sg:phone":"+1 732 462 2000",
    "sg:postcode":"07726",
    "sg:province":"NJ",
    "sg:tags":[
        "lumber"
    ],
    "wof:name":"Millhurst Mills & Ace Hardware",
    "wof:placetype":"venue"
},
  "geometry": {"coordinates":[-74.345735,40.24744],"type":"Point"}
}