{
  "type": "Feature",
  "properties": {
    "addr:full":"110 Raritan Ave Highland Park NJ 08904",
    "addr:housenumber":"110",
    "addr:postcode":"08904",
    "addr:street":"Raritan Ave",
    "iso:country":"US",
    "sg:address":"110 Raritan Ave",
    "sg:city":"Highland Park",
    "sg:classifiers":[
        {
            "category":"Autos & Motor Vehicles",
            "subcategory":"Automobile Sales",
            "type":"Retail Goods"
        }
    ],
    "sg:phone":"+1   ",
    "sg:postcode":"08904",
    "sg:province":"NJ",
    "sg:tags":[
        "used"
    ],
    "wof:name":"Style Auto Leasing",
    "wof:placetype":"venue"
},
  "geometry": {"coordinates":[-74.43044399999999,40.498341],"type":"Point"}
}