{
  "type": "Feature",
  "properties": {
    "iso:country":"US",
    "sg:address":"997 Macarthur Blvd",
    "sg:city":"Mahwah",
    "sg:classifiers":[
        {
            "category":"Professional",
            "subcategory":"Accounting & Tax Preparation",
            "type":"Services"
        }
    ],
    "sg:phone":"+1 201 825 8959",
    "sg:postcode":"07430",
    "sg:province":"NJ",
    "wof:name":"Paulist Fathers Dev Off",
    "wof:placetype":"venue"
},
  "geometry": {"coordinates":[-74.167755,41.077387],"type":"Point"}
}