{
  "type": "Feature",
  "properties": {
    "addr:full":"99 Westwood Ave Westwood NJ 07675",
    "addr:housenumber":"99",
    "addr:postcode":"07675",
    "addr:street":"Westwood Ave",
    "iso:country":"US",
    "sg:address":"99 Westwood Ave",
    "sg:city":"Westwood",
    "sg:classifiers":[
        {
            "category":"Shopping",
            "subcategory":"Jewelry",
            "type":"Retail Goods"
        }
    ],
    "sg:phone":"+1 201 664 2211",
    "sg:postcode":"07675",
    "sg:province":"NJ",
    "sg:tags":[
        "store",
        "jeweler"
    ],
    "wof:name":"Parian Jewelers Inc",
    "wof:placetype":"venue"
},
  "geometry": {"coordinates":[-74.03173099999999,40.991839],"type":"Point"}
}