{
  "type": "Feature",
  "properties": {
    "iso:country":"US",
    "sg:address":"138 E Holly Ave",
    "sg:city":"Pitman",
    "sg:classifiers":[
        {
            "category":"Education",
            "subcategory":"School",
            "type":"Public Place"
        }
    ],
    "sg:phone":"+1   ",
    "sg:postcode":"08071",
    "sg:province":"NJ",
    "sg:tags":[
        "executive"
    ],
    "wof:name":"Pitman Middle School",
    "wof:placetype":"venue"
},
  "geometry": {"coordinates":[-75.128134,39.734401],"type":"Point"}
}