{
  "type": "Feature",
  "properties": {
    "addr:full":"644 Newman Springs Rd Lincroft NJ 07738",
    "addr:housenumber":"644",
    "addr:postcode":"07738",
    "addr:street":"Newman Springs Rd",
    "iso:country":"US",
    "sg:address":"644 Newman Springs Rd",
    "sg:city":"Lincroft",
    "sg:classifiers":[
        {
            "category":"Restaurant",
            "type":"Food & Drink"
        }
    ],
    "sg:phone":"+1 732 345 1511",
    "sg:postcode":"07738",
    "sg:province":"NJ",
    "sg:tags":[
        "caterer"
    ],
    "wof:name":"Chefs Gourmet Caterers",
    "wof:placetype":"venue"
},
  "geometry": {"coordinates":[-74.120413,40.33093],"type":"Point"}
}