{
  "type": "Feature",
  "properties": {
    "addr:full":"719 New York Ave Raritan NJ 08869",
    "addr:housenumber":"719",
    "addr:postcode":"08869",
    "addr:street":"New York Ave",
    "iso:country":"US",
    "sg:address":"719 New York Ave",
    "sg:city":"Raritan",
    "sg:classifiers":[
        {
            "category":"Professional",
            "type":"Services"
        }
    ],
    "sg:phone":"+1   ",
    "sg:postcode":"08869",
    "sg:province":"NJ",
    "wof:name":"Husband For Hire LLC",
    "wof:placetype":"venue"
},
  "geometry": {"coordinates":[-74.6408,40.577158],"type":"Point"}
}