{
  "type": "Feature",
  "properties": {
    "addr:full":"359 Amboy Ave Metuchen NJ 08840",
    "addr:housenumber":"359",
    "addr:postcode":"08840",
    "addr:street":"Amboy Ave",
    "iso:country":"US",
    "sg:address":"359 Amboy Ave",
    "sg:city":"Metuchen",
    "sg:classifiers":[
        {
            "category":"Retail",
            "subcategory":"Auto Repair",
            "type":"Services"
        }
    ],
    "sg:phone":"+1 732 549 1111",
    "sg:postcode":"08840",
    "sg:province":"NJ",
    "sg:tags":[
        "repairing",
        "automobile"
    ],
    "wof:name":"Suburban Auto Mall",
    "wof:placetype":"venue"
},
  "geometry": {"coordinates":[-74.363333,40.537945],"type":"Point"}
}