{
  "type": "Feature",
  "properties": {
    "addr:full":"1039 Louisa St Elizabeth NJ 07201",
    "addr:housenumber":"1039",
    "addr:postcode":"07201",
    "addr:street":"Louisa St",
    "iso:country":"US",
    "sg:address":"1039 Louisa St",
    "sg:city":"Elizabeth",
    "sg:classifiers":[
        {
            "category":"Building & Trades",
            "subcategory":"Locksmith",
            "type":"Services"
        }
    ],
    "sg:phone":"+1 877 873 9974",
    "sg:postcode":"07201",
    "sg:province":"NJ",
    "sg:tags":[
        "key"
    ],
    "wof:name":"AAA Emergency Locksmith",
    "wof:placetype":"venue"
},
  "geometry": {"coordinates":[-74.20111900000001,40.676506],"type":"Point"}
}