{
  "type": "Feature",
  "properties": {
    "addr:full":"101 Executive Dr Moorestown NJ 08057",
    "addr:housenumber":"101",
    "addr:postcode":"08057",
    "addr:street":"Executive Dr",
    "iso:country":"US",
    "sg:address":"101 Executive Dr",
    "sg:city":"Moorestown",
    "sg:classifiers":[
        {
            "category":"Professional",
            "subcategory":"Management & Consulting",
            "type":"Services"
        }
    ],
    "sg:phone":"+1   ",
    "sg:postcode":"08057",
    "sg:province":"NJ",
    "sg:tags":[
        "agency",
        "employment"
    ],
    "wof:name":"Claims Contracts & Projects",
    "wof:placetype":"venue"
},
  "geometry": {"coordinates":[-74.990509,39.969457],"type":"Point"}
}