{
  "type": "Feature",
  "properties": {
    "iso:country":"US",
    "sg:address":"1 Center St",
    "sg:city":"Newark",
    "sg:classifiers":[
        {
            "category":"Sports & Exercise",
            "subcategory":"Gym",
            "type":"Entertainment"
        }
    ],
    "sg:phone":"+1 973 642 6070",
    "sg:postcode":"07102",
    "sg:province":"NJ",
    "sg:tags":[
        "gymnasium"
    ],
    "wof:name":"New York Sports Clubs",
    "wof:placetype":"venue"
},
  "geometry": {"coordinates":[-74.167751,40.73956],"type":"Point"}
}