{
  "type": "Feature",
  "properties": {
    "iso:country":"US",
    "sg:address":"1 High St",
    "sg:city":"Morristown",
    "sg:classifiers":[
        {
            "category":"Professional",
            "subcategory":"Art Services",
            "type":"Services"
        },
        {
            "category":"Professional",
            "subcategory":"Advertising",
            "type":"Services"
        }
    ],
    "sg:phone":"+1 973 326 8877",
    "sg:postcode":"07901",
    "sg:province":"NJ",
    "sg:tags":[
        "graphic",
        "promotion",
        "counselor",
        "design"
    ],
    "sg:website":"www.harringtongroup.com",
    "wof:name":"Harrington Group The",
    "wof:placetype":"venue"
},
  "geometry": {"coordinates":[-74.370047,40.714089],"type":"Point"}
}