{
  "type": "Feature",
  "properties": {
    "addr:full":"30 Tall Pine Ct Medford NJ 08055",
    "addr:housenumber":"30",
    "addr:postcode":"08055",
    "addr:street":"Tall Pine Ct",
    "iso:country":"US",
    "sg:address":"30 Tall Pine Ct",
    "sg:city":"Medford",
    "sg:classifiers":[
        {
            "category":"Wholesale",
            "subcategory":"Non-durable Goods",
            "type":"Manufacturing & Wholesale Goods"
        }
    ],
    "sg:phone":"+1 609 953 3336",
    "sg:postcode":"08055",
    "sg:province":"NJ",
    "wof:name":"B L Distribution",
    "wof:placetype":"venue"
},
  "geometry": {"coordinates":[-74.807047,39.84551],"type":"Point"}
}