{
  "type": "Feature",
  "properties": {
    "iso:country":"US",
    "sg:address":"130 Union St",
    "sg:city":"Northvale",
    "sg:classifiers":[
        {
            "category":"Manufacturing",
            "subcategory":"Furniture",
            "type":"Manufacturing & Wholesale Goods"
        }
    ],
    "sg:phone":"+1 201 767 0255",
    "sg:postcode":"07647",
    "sg:province":"NJ",
    "sg:tags":[
        "mfg",
        "wooden",
        "medical",
        "ins",
        "equipment",
        "therapy",
        "physical"
    ],
    "wof:name":"Hausmann Industries Inc",
    "wof:placetype":"venue"
},
  "geometry": {"coordinates":[-73.94076800000001,41.012513],"type":"Point"}
}