{
  "type": "Feature",
  "properties": {
    "iso:country":"US",
    "sg:address":"172 Market",
    "sg:city":"Newark",
    "sg:classifiers":[
        {
            "category":"Professional",
            "subcategory":"Computer Services",
            "type":"Services"
        }
    ],
    "sg:phone":"+1 973 474 1488",
    "sg:postcode":"07102",
    "sg:province":"NJ",
    "sg:tags":[
        "repair"
    ],
    "sg:website":"www.newarkinternetmarketingseo.com",
    "wof:name":"Newark Internet Marketing SEO",
    "wof:placetype":"venue"
},
  "geometry": {"coordinates":[-74.172442,40.735636],"type":"Point"}
}