{
  "type": "Feature",
  "properties": {
    "iso:country":"US",
    "sg:address":"675 Paterson Plank Rd",
    "sg:city":"Carlstadt",
    "sg:classifiers":[
        {
            "category":"Cinema",
            "subcategory":"Movie Rental",
            "type":"Entertainment"
        }
    ],
    "sg:phone":"+1 201 729 1944",
    "sg:postcode":"07072",
    "sg:province":"NJ",
    "sg:tags":[
        "video",
        "tape"
    ],
    "wof:name":"Blockbuster",
    "wof:placetype":"venue"
},
  "geometry": {"coordinates":[-74.062589,40.811295],"type":"Point"}
}