{
  "type": "Feature",
  "properties": {
    "addr:full":"35 Grant St Ramsey NJ 07446",
    "addr:housenumber":"35",
    "addr:postcode":"07446",
    "addr:street":"Grant St",
    "iso:country":"US",
    "sg:address":"35 Grant St",
    "sg:city":"Ramsey",
    "sg:classifiers":[
        {
            "category":"Retail",
            "subcategory":"Auto Repair",
            "type":"Services"
        }
    ],
    "sg:phone":"+1   ",
    "sg:postcode":"07446",
    "sg:province":"NJ",
    "sg:tags":[
        "general"
    ],
    "wof:name":"F & M Motorworks",
    "wof:placetype":"venue"
},
  "geometry": {"coordinates":[-74.142982,41.074705],"type":"Point"}
}