{
  "type": "Feature",
  "properties": {
    "addr:full":"200 Engle St Englewood NJ 07631",
    "addr:housenumber":"200",
    "addr:postcode":"07631",
    "addr:street":"Engle St",
    "iso:country":"US",
    "sg:address":"200 Engle St",
    "sg:city":"Englewood",
    "sg:classifiers":[
        {
            "category":"Health Services",
            "subcategory":"Doctor",
            "type":"Services"
        }
    ],
    "sg:phone":"+1 201 816 9493",
    "sg:postcode":"07631",
    "sg:province":"NJ",
    "sg:tags":[
        "medical"
    ],
    "wof:name":"MD Michael L Gruber",
    "wof:placetype":"venue"
},
  "geometry": {"coordinates":[-73.969331,40.900285],"type":"Point"}
}