{
  "type": "Feature",
  "properties": {
    "iso:country":"US",
    "sg:address":"2628 Dune Dr",
    "sg:city":"Avalon",
    "sg:classifiers":[
        {
            "category":"Banks & Credit Unions",
            "subcategory":"Bank",
            "type":"Services"
        }
    ],
    "sg:phone":"+1 609 967 7541",
    "sg:postcode":"08202",
    "sg:province":"NJ",
    "sg:website":"www.sturdyonline.com",
    "wof:name":"Sturdy Savings Bank",
    "wof:placetype":"venue"
},
  "geometry": {"coordinates":[-74.721001,39.098202],"type":"Point"}
}