{
  "type": "Feature",
  "properties": {
    "addr:full":"2083 Center Ave Fort Lee NJ 07024",
    "addr:housenumber":"2083",
    "addr:postcode":"07024",
    "addr:street":"Center Ave",
    "iso:country":"US",
    "sg:address":"2083 Center Ave",
    "sg:city":"Fort Lee",
    "sg:classifiers":[
        {
            "category":"Health Services",
            "subcategory":"Clinic",
            "type":"Services"
        },
        {
            "category":"Health Services",
            "subcategory":"Health Practitioner",
            "type":"Services"
        }
    ],
    "sg:phone":"+1 201 585 1677",
    "sg:postcode":"07024",
    "sg:province":"NJ",
    "sg:tags":[
        "holistic"
    ],
    "wof:name":"Marcy Prisco",
    "wof:placetype":"venue"
},
  "geometry": {"coordinates":[-73.971362,40.853083],"type":"Point"}
}