{
  "type": "Feature",
  "properties": {
    "addr:full":"390 Sip Avenue Jersey City NJ 07306",
    "addr:housenumber":"390",
    "addr:postcode":"07306",
    "addr:street":"Sip Avenue",
    "iso:country":"US",
    "sg:address":"390 Sip Avenue",
    "sg:city":"Jersey City",
    "sg:classifiers":[
        {
            "category":"Retail",
            "subcategory":"Car Wash",
            "type":"Services"
        }
    ],
    "sg:phone":"+1 201 915 0303",
    "sg:postcode":"07306",
    "sg:province":"NJ",
    "wof:name":"Flores Car Wash",
    "wof:placetype":"venue"
},
  "geometry": {"coordinates":[-74.079345,40.734014],"type":"Point"}
}