{
  "type": "Feature",
  "properties": {
    "addr:full":"149 Yellowbrook Rd Farmingdale NJ 07727",
    "addr:housenumber":"149",
    "addr:postcode":"07727",
    "addr:street":"Yellowbrook Rd",
    "iso:country":"US",
    "sg:address":"149 Yellowbrook Rd",
    "sg:city":"Farmingdale",
    "sg:classifiers":[
        {
            "category":"Real Estate",
            "subcategory":"Real Estate Agent",
            "type":"Services"
        }
    ],
    "sg:phone":"+1 732 751 1005",
    "sg:postcode":"07727",
    "sg:province":"NJ",
    "wof:name":"River Tree Realty",
    "wof:placetype":"venue"
},
  "geometry": {"coordinates":[-74.18687300000001,40.202573],"type":"Point"}
}