{
  "type": "Feature",
  "properties": {
    "addr:full":"250 Moonachie Rd Moonachie NJ 07074",
    "addr:housenumber":"250",
    "addr:postcode":"07074",
    "addr:street":"Moonachie Rd",
    "iso:country":"US",
    "sg:address":"250 Moonachie Rd",
    "sg:city":"Moonachie",
    "sg:classifiers":[
        {
            "category":"Real Estate",
            "subcategory":"Real Estate Agent",
            "type":"Services"
        }
    ],
    "sg:phone":"+1   ",
    "sg:postcode":"07074",
    "sg:province":"NJ",
    "sg:tags":[
        "broker",
        "developer"
    ],
    "wof:name":"Weiss Realty",
    "wof:placetype":"venue"
},
  "geometry": {"coordinates":[-74.053066,40.833666],"type":"Point"}
}