{
  "type": "Feature",
  "properties": {
    "iso:country":"US",
    "sg:address":"217 Red Lion Rd",
    "sg:city":"Southampton",
    "sg:classifiers":[
        {
            "category":"Shopping",
            "subcategory":"Hobbies, Toys, & Games",
            "type":"Retail Goods"
        },
        {
            "category":"Manufacturing",
            "subcategory":"Toys & Sporting Goods",
            "type":"Manufacturing & Wholesale Goods"
        }
    ],
    "sg:phone":"+1 609 859 0651",
    "sg:postcode":"08088",
    "sg:province":"NJ",
    "sg:tags":[
        "product",
        "wood",
        "craft",
        "mfg"
    ],
    "wof:name":"Sherri's Decorative Crafts",
    "wof:placetype":"venue"
},
  "geometry": {"coordinates":[-74.743572,39.906167],"type":"Point"}
}