{
  "type": "Feature",
  "properties": {
    "iso:country":"US",
    "sg:address":"1011 State Rte 168",
    "sg:city":"Blackwood",
    "sg:classifiers":[
        {
            "category":"Food & Beverages",
            "subcategory":"Groceries & Convenience Stores",
            "type":"Retail Goods"
        }
    ],
    "sg:phone":"+1   ",
    "sg:postcode":"08012",
    "sg:province":"NJ",
    "sg:tags":[
        "independent"
    ],
    "wof:name":"Supervalue",
    "wof:placetype":"venue"
},
  "geometry": {"coordinates":[-75.05709,39.787516],"type":"Point"}
}