{
  "type": "Feature",
  "properties": {
    "addr:full":"102 S Union Ave Cranford NJ 07016",
    "addr:housenumber":"102",
    "addr:postcode":"07016",
    "addr:street":"S Union Ave",
    "iso:country":"US",
    "sg:address":"102 S Union Ave",
    "sg:city":"Cranford",
    "sg:classifiers":[
        {
            "category":"Professional",
            "subcategory":"Management & Consulting",
            "type":"Services"
        }
    ],
    "sg:phone":"+1   ",
    "sg:postcode":"07016",
    "sg:province":"NJ",
    "sg:tags":[
        "business"
    ],
    "wof:name":"J Haley PHD",
    "wof:placetype":"venue"
},
  "geometry": {"coordinates":[-74.309218,40.650934],"type":"Point"}
}