{
  "type": "Feature",
  "properties": {
    "iso:country":"US",
    "sg:address":"535 Roosevelt Ave",
    "sg:city":"Carteret",
    "sg:classifiers":[
        {
            "category":"Bars & Pubs",
            "subcategory":"Nightclub",
            "type":"Food & Drink"
        }
    ],
    "sg:phone":"+1 732 802 9333",
    "sg:postcode":"07008",
    "sg:province":"NJ",
    "sg:tags":[
        "nightlife"
    ],
    "wof:name":"Gio's Bar & Restaurant",
    "wof:placetype":"venue"
},
  "geometry": {"coordinates":[-74.215628,40.582875],"type":"Point"}
}