{
  "type": "Feature",
  "properties": {
    "addr:full":"250C Sicklerville Rd Sicklerville NJ 08081",
    "addr:housenumber":"250c",
    "addr:postcode":"08081",
    "addr:street":"Sicklerville Rd",
    "iso:country":"US",
    "sg:address":"250C Sicklerville Rd",
    "sg:city":"Sicklerville",
    "sg:classifiers":[
        {
            "category":"Restaurant",
            "type":"Food & Drink"
        }
    ],
    "sg:phone":"+1 856 875 5202",
    "sg:postcode":"08081",
    "sg:province":"NJ",
    "sg:tags":[
        "pizza"
    ],
    "wof:name":"Paisano's Pizza",
    "wof:placetype":"venue"
},
  "geometry": {"coordinates":[-74.968002,39.716301],"type":"Point"}
}