{
  "type": "Feature",
  "properties": {
    "iso:country":"US",
    "sg:address":"5 Stevens Rd",
    "sg:city":"Kendall Park",
    "sg:classifiers":[
        {
            "category":"Professional",
            "subcategory":"Computer Services",
            "type":"Services"
        }
    ],
    "sg:phone":"+1 732 821 2004",
    "sg:postcode":"08817",
    "sg:province":"NJ",
    "sg:tags":[
        "related"
    ],
    "wof:name":"Jtg Consulting Inc",
    "wof:placetype":"venue"
},
  "geometry": {"coordinates":[-74.387124,40.505973],"type":"Point"}
}