{
  "type": "Feature",
  "properties": {
    "addr:full":"200 Hackensack St Wood Ridge NJ 07075",
    "addr:housenumber":"200",
    "addr:postcode":"07075",
    "addr:street":"Hackensack St",
    "iso:country":"US",
    "sg:address":"200 Hackensack St",
    "sg:city":"Wood Ridge",
    "sg:classifiers":[
        {
            "category":"Restaurant",
            "type":"Food & Drink"
        }
    ],
    "sg:phone":"+1 201 939 7788",
    "sg:postcode":"07075",
    "sg:province":"NJ",
    "sg:tags":[
        "pizza"
    ],
    "wof:name":"Uncle Tony's Pizzeria & Luncheonette",
    "wof:placetype":"venue"
},
  "geometry": {"coordinates":[-74.082632,40.846802],"type":"Point"}
}