{
  "type": "Feature",
  "properties": {
    "addr:full":"744 Hamburg Tpke Pompton Lakes NJ 07442",
    "addr:housenumber":"744",
    "addr:postcode":"07442",
    "addr:street":"Hamburg Tpke",
    "iso:country":"US",
    "sg:address":"744 Hamburg Tpke",
    "sg:city":"Pompton Lakes",
    "sg:classifiers":[
        {
            "category":"Food & Beverages",
            "subcategory":"Groceries & Convenience Stores",
            "type":"Retail Goods"
        }
    ],
    "sg:phone":"+1 973 835 8887",
    "sg:postcode":"07442",
    "sg:province":"NJ",
    "wof:name":"Kansha Corporation",
    "wof:placetype":"venue"
},
  "geometry": {"coordinates":[-74.281345,40.99324],"type":"Point"}
}