{
  "type": "Feature",
  "properties": {
    "addr:full":"156 Quakerbridge Mall Trenton NJ 08648",
    "addr:housenumber":"156",
    "addr:postcode":"08648",
    "addr:street":"Quakerbridge Mall",
    "iso:country":"US",
    "sg:address":"156 Quakerbridge Mall",
    "sg:city":"Trenton",
    "sg:classifiers":[
        {
            "category":"Restaurant",
            "type":"Food & Drink"
        }
    ],
    "sg:phone":"+1   ",
    "sg:postcode":"08648",
    "sg:province":"NJ",
    "sg:tags":[
        "ice",
        "store",
        "cream"
    ],
    "wof:name":"Baskin-Robbins",
    "wof:placetype":"venue"
},
  "geometry": {"coordinates":[-74.68500400000001,40.290762],"type":"Point"}
}