{
  "type": "Feature",
  "properties": {
    "iso:country":"US",
    "sg:address":"210 Turkey Hill Rd",
    "sg:city":"Asbury",
    "sg:classifiers":[
        {
            "category":"Professional",
            "subcategory":"Management & Consulting",
            "type":"Services"
        }
    ],
    "sg:phone":"+1 908 479 6056",
    "sg:postcode":"08802",
    "sg:province":"NJ",
    "sg:tags":[
        "commercial"
    ],
    "wof:name":"Frank Keller Consult",
    "wof:placetype":"venue"
},
  "geometry": {"coordinates":[-75.049004,40.652312],"type":"Point"}
}