{
  "type": "Feature",
  "properties": {
    "iso:country":"US",
    "sg:address":"1596 US Hwy 130",
    "sg:city":"North Brunswick",
    "sg:classifiers":[
        {
            "category":"Professional",
            "type":"Services"
        }
    ],
    "sg:phone":"+1 732 951 8942",
    "sg:postcode":"08902",
    "sg:province":"NJ",
    "sg:tags":[
        "establishment"
    ],
    "wof:name":"Bellini Associates",
    "wof:placetype":"venue"
},
  "geometry": {"coordinates":[-74.465968,40.446581],"type":"Point"}
}