{
  "type": "Feature",
  "properties": {
    "addr:full":"873 Somerset St Somerset NJ 08873",
    "addr:housenumber":"873",
    "addr:postcode":"08873",
    "addr:street":"Somerset St",
    "iso:country":"US",
    "sg:address":"873 Somerset St",
    "sg:city":"Somerset",
    "sg:classifiers":[
        {
            "category":"Retail",
            "subcategory":"Auto Repair",
            "type":"Services"
        }
    ],
    "sg:phone":"+1   ",
    "sg:postcode":"08873",
    "sg:province":"NJ",
    "sg:tags":[
        "body",
        "shop",
        "towing",
        "collision"
    ],
    "wof:name":"Dependable Motors",
    "wof:placetype":"venue"
},
  "geometry": {"coordinates":[-74.48329699999999,40.480988],"type":"Point"}
}