{
  "type": "Feature",
  "properties": {
    "addr:full":"49 Mount Pleasant Ave West Orange NJ 07052",
    "addr:housenumber":"49",
    "addr:postcode":"07052",
    "addr:street":"Mount Pleasant Ave",
    "iso:country":"US",
    "sg:address":"49 Mount Pleasant Ave",
    "sg:city":"West Orange",
    "sg:classifiers":[
        {
            "category":"Professional",
            "subcategory":"Lawyer & Legal Services",
            "type":"Services"
        }
    ],
    "sg:phone":"+1 973 731 7227",
    "sg:postcode":"07052",
    "sg:province":"NJ",
    "wof:name":"Strahan Christopher C Attorney-At-Law",
    "wof:placetype":"venue"
},
  "geometry": {"coordinates":[-74.243797,40.780201],"type":"Point"}
}