{
  "type": "Feature",
  "properties": {
    "addr:full":"25 Olcott Sq Bernardsville NJ 07924",
    "addr:housenumber":"25",
    "addr:postcode":"07924",
    "addr:street":"Olcott Sq",
    "iso:country":"US",
    "sg:address":"25 Olcott Sq",
    "sg:city":"Bernardsville",
    "sg:classifiers":[
        {
            "category":"Retail",
            "subcategory":"Photofinishing",
            "type":"Services"
        }
    ],
    "sg:phone":"+1   ",
    "sg:postcode":"07924",
    "sg:province":"NJ",
    "sg:tags":[
        "laboratory"
    ],
    "wof:name":"Raimo Imaging Group Inc",
    "wof:placetype":"venue"
},
  "geometry": {"coordinates":[-74.569186,40.718712],"type":"Point"}
}