{
  "type": "Feature",
  "properties": {
    "addr:full":"565 Bergen Ave Jersey City NJ 07304",
    "addr:housenumber":"565",
    "addr:postcode":"07304",
    "addr:street":"Bergen Ave",
    "iso:country":"US",
    "sg:address":"565 Bergen Ave",
    "sg:city":"Jersey City",
    "sg:classifiers":[
        {
            "category":"Food & Beverages",
            "subcategory":"Groceries & Convenience Stores",
            "type":"Retail Goods"
        }
    ],
    "sg:phone":"+1   ",
    "sg:postcode":"07304",
    "sg:province":"NJ",
    "wof:name":"Brother Mini Market",
    "wof:placetype":"venue"
},
  "geometry": {"coordinates":[-74.07396,40.719703],"type":"Point"}
}