{
  "type": "Feature",
  "properties": {
    "addr:full":"141 Miry Brook Rd Trenton NJ 08690",
    "addr:housenumber":"141",
    "addr:postcode":"08690",
    "addr:street":"Miry Brook Rd",
    "iso:country":"US",
    "sg:address":"141 Miry Brook Rd",
    "sg:city":"Trenton",
    "sg:classifiers":[
        {
            "category":"Health Services",
            "subcategory":"Health Practitioner",
            "type":"Services"
        }
    ],
    "sg:phone":"+1   ",
    "sg:postcode":"08690",
    "sg:province":"NJ",
    "wof:name":"Kristine S Dueker",
    "wof:placetype":"venue"
},
  "geometry": {"coordinates":[-74.651859,40.236033],"type":"Point"}
}