{
  "type": "Feature",
  "properties": {
    "addr:full":"2300 State Rte 33 Trenton NJ 08691",
    "addr:housenumber":"2300",
    "addr:postcode":"08691",
    "addr:street":"State Rte 33",
    "iso:country":"US",
    "sg:address":"2300 State Rte 33",
    "sg:city":"Trenton",
    "sg:classifiers":[
        {
            "category":"Banks & Credit Unions",
            "subcategory":"Bank",
            "type":"Services"
        }
    ],
    "sg:phone":"+1 609 585 6300",
    "sg:postcode":"08691",
    "sg:province":"NJ",
    "sg:website":"www.romabank.com",
    "wof:name":"Roma Bank",
    "wof:placetype":"venue"
},
  "geometry": {"coordinates":[-74.63503300000001,40.220771],"type":"Point"}
}