{
  "type": "Feature",
  "properties": {
    "addr:full":"315 State Rte 17 Paramus NJ 07652",
    "addr:housenumber":"315",
    "addr:postcode":"07652",
    "addr:street":"State Rte 17",
    "iso:country":"US",
    "sg:address":"315 State Rte 17",
    "sg:city":"Paramus",
    "sg:classifiers":[
        {
            "category":"Communications",
            "subcategory":"Film & Video Production",
            "type":"Services"
        }
    ],
    "sg:phone":"+1   ",
    "sg:postcode":"07652",
    "sg:province":"NJ",
    "sg:tags":[
        "motion",
        "picture"
    ],
    "wof:name":"Mediamix Inc",
    "wof:placetype":"venue"
},
  "geometry": {"coordinates":[-74.070826,40.910398],"type":"Point"}
}