{
  "type": "Feature",
  "properties": {
    "addr:full":"24 Daniel Dr Cedar Grove NJ 07009",
    "addr:housenumber":"24",
    "addr:postcode":"07009",
    "addr:street":"Daniel Dr",
    "iso:country":"US",
    "sg:address":"24 Daniel Dr",
    "sg:city":"Cedar Grove",
    "sg:classifiers":[
        {
            "category":"Real Estate",
            "subcategory":"Real Estate Agent",
            "type":"Services"
        }
    ],
    "sg:phone":"+1   ",
    "sg:postcode":"07009",
    "sg:province":"NJ",
    "wof:name":"C W S Appraisal",
    "wof:placetype":"venue"
},
  "geometry": {"coordinates":[-74.221434,40.855925],"type":"Point"}
}