{
  "type": "Feature",
  "properties": {
    "addr:full":"91 Main St West Orange NJ 07052",
    "addr:housenumber":"91",
    "addr:postcode":"07052",
    "addr:street":"Main St",
    "iso:country":"US",
    "sg:address":"91 Main St",
    "sg:city":"West Orange",
    "sg:classifiers":[
        {
            "category":"Professional",
            "subcategory":"Management & Consulting",
            "type":"Services"
        }
    ],
    "sg:phone":"+1   ",
    "sg:postcode":"07052",
    "sg:province":"NJ",
    "sg:tags":[
        "business"
    ],
    "wof:name":"Wilson Consulting Svc",
    "wof:placetype":"venue"
},
  "geometry": {"coordinates":[-74.237737,40.780082],"type":"Point"}
}