{
  "type": "Feature",
  "properties": {
    "addr:full":"218 State Rte 17 Rochelle Park NJ 07607",
    "addr:housenumber":"218",
    "addr:postcode":"07607",
    "addr:street":"State Rte 17",
    "iso:country":"US",
    "sg:address":"218 State Rte 17",
    "sg:city":"Rochelle Park",
    "sg:classifiers":[
        {
            "category":"Professional",
            "subcategory":"Lawyer & Legal Services",
            "type":"Services"
        }
    ],
    "sg:phone":"+1 201 226 9199",
    "sg:postcode":"07607",
    "sg:province":"NJ",
    "sg:tags":[
        "attorney"
    ],
    "wof:name":"Nachamie Silverman & Di Luccio",
    "wof:placetype":"venue"
},
  "geometry": {"coordinates":[-74.071206,40.892718],"type":"Point"}
}