{
  "type": "Feature",
  "properties": {
    "iso:country":"US",
    "sg:address":"3321 Doris Ave",
    "sg:city":"Asbury Park",
    "sg:classifiers":[
        {
            "category":"Professional",
            "subcategory":"Accounting & Tax Preparation",
            "type":"Services"
        }
    ],
    "sg:phone":"+1 732 517 2085",
    "sg:postcode":"07712",
    "sg:province":"NJ",
    "sg:tags":[
        "accountant"
    ],
    "wof:name":"Henry P Meier CPA",
    "wof:placetype":"venue"
},
  "geometry": {"coordinates":[-74.03474300000001,40.239199],"type":"Point"}
}