{
  "type": "Feature",
  "properties": {
    "iso:country":"US",
    "sg:address":"251 Highland Ave",
    "sg:city":"Long Branch",
    "sg:classifiers":[
        {
            "category":"Shopping",
            "subcategory":"Clothing, Apparel, & Fashions",
            "type":"Retail Goods"
        }
    ],
    "sg:phone":"+1   ",
    "sg:postcode":"07740",
    "sg:province":"NJ",
    "sg:tags":[
        "jewelry"
    ],
    "wof:name":"Lori Nesser",
    "wof:placetype":"venue"
},
  "geometry": {"coordinates":[-73.995422,40.274494],"type":"Point"}
}