{
  "type": "Feature",
  "properties": {
    "iso:country":"US",
    "sg:address":"1814 Bergenline Ave",
    "sg:city":"Union City",
    "sg:classifiers":[
        {
            "category":"Restaurant",
            "type":"Food & Drink"
        }
    ],
    "sg:phone":"+1 201 558 9108",
    "sg:postcode":"07087",
    "sg:province":"NJ",
    "sg:tags":[
        "eating",
        "chinese"
    ],
    "wof:name":"Goody Chinese Restaurant",
    "wof:placetype":"venue"
},
  "geometry": {"coordinates":[-74.035004,40.763699],"type":"Point"}
}