{
  "type": "Feature",
  "properties": {
    "iso:country":"US",
    "sg:address":"509 N Main St",
    "sg:city":"Barnegat",
    "sg:classifiers":[
        {
            "category":"Retail",
            "subcategory":"Repair Shop",
            "type":"Services"
        }
    ],
    "sg:phone":"+1   ",
    "sg:postcode":"08005",
    "sg:province":"NJ",
    "sg:tags":[
        "electrical"
    ],
    "wof:name":"Lacey Vacuum",
    "wof:placetype":"venue"
},
  "geometry": {"coordinates":[-74.218867,39.762301],"type":"Point"}
}