{
  "type": "Feature",
  "properties": {
    "iso:country":"US",
    "sg:address":"48 Walker Rd",
    "sg:city":"West Orange",
    "sg:classifiers":[
        {
            "category":"Professional",
            "subcategory":"Lawyer & Legal Services",
            "type":"Services"
        }
    ],
    "sg:phone":"+1 973 669 1776",
    "sg:postcode":"07052",
    "sg:province":"NJ",
    "wof:name":"Vantuno John",
    "wof:placetype":"venue"
},
  "geometry": {"coordinates":[-74.255601,40.763788],"type":"Point"}
}