{
  "type": "Feature",
  "properties": {
    "iso:country":"US",
    "sg:address":"851 Carleton Rd",
    "sg:city":"Westfield",
    "sg:classifiers":[
        {
            "category":"Professional",
            "type":"Services"
        }
    ],
    "sg:phone":"+1   ",
    "sg:postcode":"07090",
    "sg:province":"NJ",
    "wof:name":"Kathryn C Bizzarro",
    "wof:placetype":"venue"
},
  "geometry": {"coordinates":[-74.335989,40.643218],"type":"Point"}
}