{
  "type": "Feature",
  "properties": {
    "addr:full":"277 Westcott Blvd Pennington NJ 08534",
    "addr:housenumber":"277",
    "addr:postcode":"08534",
    "addr:street":"Westcott Blvd",
    "iso:country":"US",
    "sg:address":"277 Westcott Blvd",
    "sg:city":"Pennington",
    "sg:classifiers":[
        {
            "category":"Shopping",
            "subcategory":"Hobbies, Toys, & Games",
            "type":"Retail Goods"
        }
    ],
    "sg:phone":"+1   ",
    "sg:postcode":"08534",
    "sg:province":"NJ",
    "wof:name":"W & J Dolls & Toys",
    "wof:placetype":"venue"
},
  "geometry": {"coordinates":[-74.76011200000001,40.361654],"type":"Point"}
}