{
  "type": "Feature",
  "properties": {
    "addr:full":"459 McCarter Hwy Newark NJ 07114",
    "addr:housenumber":"459",
    "addr:postcode":"07114",
    "addr:street":"Mccarter Hwy",
    "iso:country":"US",
    "sg:address":"459 McCarter Hwy",
    "sg:city":"Newark",
    "sg:classifiers":[
        {
            "category":"Retail",
            "subcategory":"Auto Repair",
            "type":"Services"
        }
    ],
    "sg:phone":"+1   ",
    "sg:postcode":"07114",
    "sg:province":"NJ",
    "sg:tags":[
        "general"
    ],
    "wof:name":"Rodriguez Auto Glass",
    "wof:placetype":"venue"
},
  "geometry": {"coordinates":[-74.17657699999999,40.722909],"type":"Point"}
}