{
  "type": "Feature",
  "properties": {
    "iso:country":"US",
    "sg:address":"444 Union Ave",
    "sg:city":"Middlesex",
    "sg:classifiers":[
        {
            "category":"Banks & Credit Unions",
            "subcategory":"Bank",
            "type":"Services"
        }
    ],
    "sg:phone":"+1 732 980 2611",
    "sg:postcode":"08846",
    "sg:province":"NJ",
    "wof:name":"Wachovia Bank",
    "wof:placetype":"venue"
},
  "geometry": {"coordinates":[-74.512201,40.57086],"type":"Point"}
}