{
  "type": "Feature",
  "properties": {
    "iso:country":"US",
    "sg:address":"18 US Hwy 202",
    "sg:city":"Ringoes",
    "sg:classifiers":[
        {
            "category":"Home & Garden",
            "subcategory":"Furniture",
            "type":"Retail Goods"
        }
    ],
    "sg:phone":"+1 908 782 7222",
    "sg:postcode":"08551",
    "sg:province":"NJ",
    "wof:name":"Olde York Road Furniture Inc",
    "wof:placetype":"venue"
},
  "geometry": {"coordinates":[-74.85827500000001,40.445026],"type":"Point"}
}