{
  "type": "Feature",
  "properties": {
    "iso:country":"US",
    "sg:address":"25 W Madison Ave",
    "sg:city":"Paulsboro",
    "sg:classifiers":[
        {
            "category":"Professional",
            "subcategory":"Management & Consulting",
            "type":"Services"
        }
    ],
    "sg:phone":"+1   ",
    "sg:postcode":"08066",
    "sg:province":"NJ",
    "sg:tags":[
        "water",
        "ice"
    ],
    "wof:name":"Dairy D",
    "wof:placetype":"venue"
},
  "geometry": {"coordinates":[-75.243264,39.833347],"type":"Point"}
}