{
  "type": "Feature",
  "properties": {
    "addr:full":"379 Kearny Ave Kearny NJ 07032",
    "addr:housenumber":"379",
    "addr:postcode":"07032",
    "addr:street":"Kearny Ave",
    "iso:country":"US",
    "sg:address":"379 Kearny Ave",
    "sg:city":"Kearny",
    "sg:classifiers":[
        {
            "category":"Real Estate",
            "subcategory":"Real Estate Agent",
            "type":"Services"
        }
    ],
    "sg:phone":"+1 201 997 7900",
    "sg:postcode":"07032",
    "sg:province":"NJ",
    "wof:name":"Borgos & Borgos Real Estate",
    "wof:placetype":"venue"
},
  "geometry": {"coordinates":[-74.149637,40.762588],"type":"Point"}
}