{
  "type": "Feature",
  "properties": {
    "addr:full":"225 Demott Ln Somerset NJ 08873",
    "addr:housenumber":"225",
    "addr:postcode":"08873",
    "addr:street":"Demott Ln",
    "iso:country":"US",
    "sg:address":"225 Demott Ln",
    "sg:city":"Somerset",
    "sg:classifiers":[
        {
            "category":"Retail",
            "subcategory":"Laundry & Dry Cleaning",
            "type":"Services"
        },
        {
            "category":"Shopping",
            "subcategory":"Clothing, Apparel, & Fashions",
            "type":"Retail Goods"
        }
    ],
    "sg:phone":"+1 732 247 5770",
    "sg:postcode":"08873",
    "sg:province":"NJ",
    "sg:tags":[
        "cleaners",
        "plant",
        "drycleaning"
    ],
    "wof:name":"Jem Cleaners Iv",
    "wof:placetype":"venue"
},
  "geometry": {"coordinates":[-74.50795599999999,40.509372],"type":"Point"}
}