{
  "type": "Feature",
  "properties": {
    "addr:full":"357 Dusty Miller Dr Beach Haven NJ 08008",
    "addr:housenumber":"357",
    "addr:postcode":"08008",
    "addr:street":"Dusty Miller Dr",
    "iso:country":"US",
    "sg:address":"357 Dusty Miller Dr",
    "sg:city":"Beach Haven",
    "sg:classifiers":[
        {
            "category":"Health Services",
            "subcategory":"Doctor",
            "type":"Services"
        }
    ],
    "sg:phone":"+1 609 494 8351",
    "sg:postcode":"08008",
    "sg:province":"NJ",
    "sg:tags":[
        "medical"
    ],
    "wof:name":"S Zimberg MD",
    "wof:placetype":"venue"
},
  "geometry": {"coordinates":[-74.12950600000001,39.729129],"type":"Point"}
}