{
  "type": "Feature",
  "properties": {
    "addr:full":"512 Raritan St Sayreville NJ 08872",
    "addr:housenumber":"512",
    "addr:postcode":"08872",
    "addr:street":"Raritan St",
    "iso:country":"US",
    "sg:address":"512 Raritan St",
    "sg:city":"Sayreville",
    "sg:classifiers":[
        {
            "category":"Building & Trades",
            "subcategory":"Landscaping Services",
            "type":"Services"
        }
    ],
    "sg:phone":"+1 732 727 6767",
    "sg:postcode":"08872",
    "sg:province":"NJ",
    "sg:tags":[
        "lawn",
        "custom",
        "care"
    ],
    "wof:name":"Lawn Doctor Sayrevilleedison",
    "wof:placetype":"venue"
},
  "geometry": {"coordinates":[-74.298098,40.479816],"type":"Point"}
}