{
  "type": "Feature",
  "properties": {
    "iso:country":"US",
    "sg:address":"353 Livingston Ave",
    "sg:city":"New Brunswick",
    "sg:classifiers":[
        {
            "category":"Professional",
            "subcategory":"Lawyer & Legal Services",
            "type":"Services"
        }
    ],
    "sg:phone":"+1   ",
    "sg:postcode":"08901",
    "sg:province":"NJ",
    "sg:tags":[
        "attorney"
    ],
    "wof:name":"Hector Rodriguez",
    "wof:placetype":"venue"
},
  "geometry": {"coordinates":[-74.456125,40.481992],"type":"Point"}
}