{
  "type": "Feature",
  "properties": {
    "iso:country":"US",
    "sg:address":"166 Bridge Ave",
    "sg:city":"Red Bank",
    "sg:classifiers":[
        {
            "category":"Building & Trades",
            "subcategory":"Landscaping Services",
            "type":"Services"
        }
    ],
    "sg:phone":"+1 732 842 6762",
    "sg:postcode":"07701",
    "sg:province":"NJ",
    "sg:tags":[
        "landscape",
        "contractor"
    ],
    "wof:name":"Ed Matthews Lawn & Tree Svc",
    "wof:placetype":"venue"
},
  "geometry": {"coordinates":[-74.07462700000001,40.344476],"type":"Point"}
}