{
  "type": "Feature",
  "properties": {
    "iso:country":"US",
    "sg:address":"322 W 72 St",
    "sg:city":"New York",
    "sg:classifiers":[
        {
            "category":"Retail",
            "subcategory":"Repair Shop",
            "type":"Services"
        }
    ],
    "sg:phone":"+1 646 224 0492",
    "sg:postcode":"10023",
    "sg:province":"NY",
    "sg:tags":[
        "lock",
        "locksmith"
    ],
    "wof:name":"Locksmith Svc",
    "wof:placetype":"venue"
},
  "geometry": {"coordinates":[-73.98657900000001,40.780609],"type":"Point"}
}