{
  "type": "Feature",
  "properties": {
    "addr:full":"167 Main St Flemington NJ 08822",
    "addr:housenumber":"167",
    "addr:postcode":"08822",
    "addr:street":"Main St",
    "iso:country":"US",
    "sg:address":"167 Main St",
    "sg:city":"Flemington",
    "sg:classifiers":[
        {
            "category":"Building & Trades",
            "subcategory":"Construction",
            "type":"Services"
        }
    ],
    "sg:phone":"+1 908 782 8200",
    "sg:postcode":"08822",
    "sg:province":"NJ",
    "sg:tags":[
        "house"
    ],
    "wof:name":"Clinton Construction Group",
    "wof:placetype":"venue"
},
  "geometry": {"coordinates":[-74.858378,40.505855],"type":"Point"}
}