{
  "type": "Feature",
  "properties": {
    "addr:full":"16 Kira Ln Englewood NJ 07631",
    "addr:housenumber":"16",
    "addr:postcode":"07631",
    "addr:street":"Kira Ln",
    "iso:country":"US",
    "sg:address":"16 Kira Ln",
    "sg:city":"Englewood",
    "sg:classifiers":[
        {
            "category":"Professional",
            "type":"Services"
        }
    ],
    "sg:phone":"+1   ",
    "sg:postcode":"07631",
    "sg:province":"NJ",
    "wof:name":"A Place For Women",
    "wof:placetype":"venue"
},
  "geometry": {"coordinates":[-73.95789499999999,40.882762],"type":"Point"}
}