{
  "type": "Feature",
  "properties": {
    "addr:full":"11 Dundee Ter Freehold NJ 07728",
    "addr:housenumber":"11",
    "addr:postcode":"07728",
    "addr:street":"Dundee Ter",
    "iso:country":"US",
    "sg:address":"11 Dundee Ter",
    "sg:city":"Freehold",
    "sg:classifiers":[
        {
            "category":"Personal",
            "subcategory":"Beauty Salon",
            "type":"Services"
        }
    ],
    "sg:phone":"+1 732 682 4821",
    "sg:postcode":"07728",
    "sg:province":"NJ",
    "sg:tags":[
        "shop"
    ],
    "wof:name":"Total Look Promotions",
    "wof:placetype":"venue"
},
  "geometry": {"coordinates":[-74.26807700000001,40.231033],"type":"Point"}
}