{
  "type": "Feature",
  "properties": {
    "addr:full":"3112 Sunset Ave Atlantic City NJ 08401",
    "addr:housenumber":"3112",
    "addr:postcode":"08401",
    "addr:street":"Sunset Ave",
    "iso:country":"US",
    "sg:address":"3112 Sunset Ave",
    "sg:city":"Atlantic City",
    "sg:classifiers":[
        {
            "category":"Building & Trades",
            "subcategory":"Construction",
            "type":"Services"
        }
    ],
    "sg:phone":"+1 609 345 8400",
    "sg:postcode":"08401",
    "sg:province":"NJ",
    "sg:tags":[
        "handyman"
    ],
    "wof:name":"Husband For Hire",
    "wof:placetype":"venue"
},
  "geometry": {"coordinates":[-74.452585,39.35745],"type":"Point"}
}