{
  "type": "Feature",
  "properties": {
    "iso:country":"US",
    "sg:address":"4 Mulberry Ln",
    "sg:city":"Colts Neck",
    "sg:classifiers":[
        {
            "category":"Manufacturing",
            "subcategory":"Paper Products",
            "type":"Manufacturing & Wholesale Goods"
        }
    ],
    "sg:phone":"+1 732 332 0810",
    "sg:postcode":"07722",
    "sg:province":"NJ",
    "sg:tags":[
        "stationery",
        "prod"
    ],
    "wof:name":"Paper Angel",
    "wof:placetype":"venue"
},
  "geometry": {"coordinates":[-74.19743800000001,40.32764],"type":"Point"}
}