{
  "type": "Feature",
  "properties": {
    "iso:country":"US",
    "sg:address":"9 Davison Ave",
    "sg:city":"Jamesburg",
    "sg:classifiers":[
        {
            "category":"Banks & Credit Unions",
            "subcategory":"Investment Brokerage",
            "type":"Services"
        },
        {
            "category":"Professional",
            "subcategory":"Management & Consulting",
            "type":"Services"
        }
    ],
    "sg:phone":"+1 732 521 6125",
    "sg:postcode":"08831",
    "sg:province":"NJ",
    "sg:tags":[
        "consultant",
        "planning",
        "financial"
    ],
    "wof:name":"Knights Financial Group",
    "wof:placetype":"venue"
},
  "geometry": {"coordinates":[-74.439874,40.347708],"type":"Point"}
}