{
  "type": "Feature",
  "properties": {
    "iso:country":"US",
    "sg:address":"92 Grove St",
    "sg:city":"Elmwood Park",
    "sg:classifiers":[
        {
            "category":"Professional",
            "subcategory":"Management & Consulting",
            "type":"Services"
        }
    ],
    "sg:phone":"+1   ",
    "sg:postcode":"07407",
    "sg:province":"NJ",
    "wof:name":"Atlantic Siteworks LLC",
    "wof:placetype":"venue"
},
  "geometry": {"coordinates":[-74.122038,40.906138],"type":"Point"}
}