{
  "type": "Feature",
  "properties": {
    "iso:country":"US",
    "sg:address":"800 5th Ave",
    "sg:city":"Asbury Park",
    "sg:classifiers":[
        {
            "category":"Professional",
            "subcategory":"Business Services",
            "type":"Services"
        }
    ],
    "sg:phone":"+1 732 988 8301",
    "sg:postcode":"07712",
    "sg:province":"NJ",
    "sg:tags":[
        "interior",
        "consultant",
        "design",
        "decorator"
    ],
    "wof:name":"ASL Design Studio",
    "wof:placetype":"venue"
},
  "geometry": {"coordinates":[-74.01078699999999,40.225843],"type":"Point"}
}