{
  "type": "Feature",
  "properties": {
    "iso:country":"US",
    "sg:address":"4608 Westfield Ave",
    "sg:city":"Pennsauken",
    "sg:classifiers":[
        {
            "category":"Health Services",
            "subcategory":"Dentist",
            "type":"Services"
        }
    ],
    "sg:phone":"+1 856 910 0400",
    "sg:postcode":"08110",
    "sg:province":"NJ",
    "wof:name":"Haider Fatema DMD",
    "wof:placetype":"venue"
},
  "geometry": {"coordinates":[-75.067902,39.956902],"type":"Point"}
}