{
  "type": "Feature",
  "properties": {
    "iso:country":"US",
    "sg:address":"80 County Rd",
    "sg:city":"Jersey City",
    "sg:classifiers":[
        {
            "category":"Food & Beverages",
            "subcategory":"Bakery",
            "type":"Retail Goods"
        }
    ],
    "sg:phone":"+1 201 656 6050",
    "sg:postcode":"07307",
    "sg:province":"NJ",
    "sg:tags":[
        "doughnut"
    ],
    "sg:website":"www.dunkindonuts.com",
    "wof:name":"Dunkin' Donuts",
    "wof:placetype":"venue"
},
  "geometry": {"coordinates":[-74.06672500000001,40.758728],"type":"Point"}
}