{
  "type": "Feature",
  "properties": {
    "addr:full":"14 Orchard St Wallington NJ 07057",
    "addr:housenumber":"14",
    "addr:postcode":"07057",
    "addr:street":"Orchard St",
    "iso:country":"US",
    "sg:address":"14 Orchard St",
    "sg:city":"Wallington",
    "sg:classifiers":[
        {
            "category":"Wholesale",
            "subcategory":"Non-durable Goods",
            "type":"Manufacturing & Wholesale Goods"
        }
    ],
    "sg:phone":"+1 973 778 1660",
    "sg:postcode":"07057",
    "sg:province":"NJ",
    "sg:tags":[
        "rubber",
        "foam"
    ],
    "wof:name":"Stanley Foam Rbr Uphl Supplie",
    "wof:placetype":"venue"
},
  "geometry": {"coordinates":[-74.106821,40.855183],"type":"Point"}
}