{
  "type": "Feature",
  "properties": {
    "addr:full":"5 Central Ave Red Bank NJ 07701",
    "addr:housenumber":"5",
    "addr:postcode":"07701",
    "addr:street":"Central Ave",
    "iso:country":"US",
    "sg:address":"5 Central Ave",
    "sg:city":"Red Bank",
    "sg:classifiers":[
        {
            "category":"Railroad",
            "type":"Transportation"
        }
    ],
    "sg:phone":"+1 732 530 3727",
    "sg:postcode":"07701",
    "sg:province":"NJ",
    "sg:tags":[
        "operator",
        "line"
    ],
    "wof:name":"NJ Transit",
    "wof:placetype":"venue"
},
  "geometry": {"coordinates":[-74.071967,40.344889],"type":"Point"}
}