{
  "type": "Feature",
  "properties": {
    "addr:full":"3117 Willowbrook Mall Wayne NJ 07470",
    "addr:housenumber":"3117",
    "addr:postcode":"07470",
    "addr:street":"Willowbrook Mall",
    "iso:country":"US",
    "sg:address":"3117 Willowbrook Mall",
    "sg:city":"Wayne",
    "sg:classifiers":[
        {
            "category":"Restaurant",
            "type":"Food & Drink"
        }
    ],
    "sg:phone":"+1 973 256 9778",
    "sg:postcode":"07470",
    "sg:province":"NJ",
    "wof:name":"Greenleaf Grille",
    "wof:placetype":"venue"
},
  "geometry": {"coordinates":[-74.255214,40.88966],"type":"Point"}
}