{
  "type": "Feature",
  "properties": {
    "addr:full":"236 Livingston St Northvale NJ 07647",
    "addr:housenumber":"236",
    "addr:postcode":"07647",
    "addr:street":"Livingston St",
    "iso:country":"US",
    "sg:address":"236 Livingston St",
    "sg:city":"Northvale",
    "sg:classifiers":[
        {
            "category":"Personal",
            "subcategory":"Beauty Salon",
            "type":"Services"
        }
    ],
    "sg:phone":"+1 201 784 9725",
    "sg:postcode":"07647",
    "sg:province":"NJ",
    "sg:tags":[
        "shop"
    ],
    "wof:name":"Lorgines Hair Design",
    "wof:placetype":"venue"
},
  "geometry": {"coordinates":[-73.946991,41.010601],"type":"Point"}
}