{
  "type": "Feature",
  "properties": {
    "addr:full":"119 N Michigan Ave Atlantic City NJ 08401",
    "addr:housenumber":"119",
    "addr:postcode":"08401",
    "addr:street":"N Michigan Ave",
    "iso:country":"US",
    "sg:address":"119 N Michigan Ave",
    "sg:city":"Atlantic City",
    "sg:classifiers":[
        {
            "category":"Recreation",
            "subcategory":"Amusement Park",
            "type":"Entertainment"
        }
    ],
    "sg:phone":"+1 609 678 0400",
    "sg:postcode":"08401",
    "sg:province":"NJ",
    "wof:name":"Passport Voyages",
    "wof:placetype":"venue"
},
  "geometry": {"coordinates":[-74.436764,39.360824],"type":"Point"}
}