{
  "type": "Feature",
  "properties": {
    "addr:full":"451 High St Ste 1 Burlington NJ 08016",
    "addr:housenumber":"451",
    "addr:postcode":"08016",
    "addr:street":"High St Ste 1",
    "iso:country":"US",
    "sg:address":"451 High St Ste 1",
    "sg:city":"Burlington",
    "sg:classifiers":[
        {
            "category":"Landmark",
            "subcategory":"Historic",
            "type":"Public Place"
        },
        {
            "category":"Museum",
            "type":"Entertainment"
        }
    ],
    "sg:phone":"+1 609 386 4773",
    "sg:postcode":"08016",
    "sg:province":"NJ",
    "sg:tags":[
        "historical"
    ],
    "wof:name":"Burlington County Historical Society",
    "wof:placetype":"venue"
},
  "geometry": {"coordinates":[-74.857528,40.076388],"type":"Point"}
}