{
  "type": "Feature",
  "properties": {
    "addr:full":"151 Fenwick Ct Riverside NJ 08075",
    "addr:housenumber":"151",
    "addr:postcode":"08075",
    "addr:street":"Fenwick Ct",
    "iso:country":"US",
    "sg:address":"151 Fenwick Ct",
    "sg:city":"Riverside",
    "sg:classifiers":[
        {
            "category":"Building & Trades",
            "subcategory":"Construction",
            "type":"Services"
        }
    ],
    "sg:phone":"+1 856 764 7762",
    "sg:postcode":"08075",
    "sg:province":"NJ",
    "sg:tags":[
        "contractor"
    ],
    "wof:name":"Richard E Wright Associates",
    "wof:placetype":"venue"
},
  "geometry": {"coordinates":[-74.95722000000001,39.993794],"type":"Point"}
}