{
  "type": "Feature",
  "properties": {
    "iso:country":"US",
    "sg:address":"164 Parkview Rd",
    "sg:city":"Stratford",
    "sg:classifiers":[
        {
            "category":"Professional",
            "subcategory":"Computer Services",
            "type":"Services"
        }
    ],
    "sg:phone":"+1 856 435 8600",
    "sg:postcode":"08084",
    "sg:province":"NJ",
    "sg:tags":[
        "prepackaged",
        "software"
    ],
    "wof:name":"Pclegal Software Inc",
    "wof:placetype":"venue"
},
  "geometry": {"coordinates":[-75.02757,39.827983],"type":"Point"}
}