{
  "type": "Feature",
  "properties": {
    "addr:full":"808 Rivervale Rd Rivervale NJ 07675",
    "addr:housenumber":"808",
    "addr:postcode":"07675",
    "addr:street":"Rivervale Rd",
    "iso:country":"US",
    "sg:address":"808 Rivervale Rd",
    "sg:city":"Rivervale",
    "sg:classifiers":[
        {
            "category":"Manufacturing",
            "subcategory":"Textiles",
            "type":"Manufacturing & Wholesale Goods"
        }
    ],
    "sg:phone":"+1 201 476 1011",
    "sg:postcode":"07675",
    "sg:province":"NJ",
    "sg:tags":[
        "fabrics-wholesale",
        "manufacturer"
    ],
    "wof:name":"Umbrellas Unlimited",
    "wof:placetype":"venue"
},
  "geometry": {"coordinates":[-74.01165,41.034119],"type":"Point"}
}