{
  "type": "Feature",
  "properties": {
    "addr:full":"43 Bloomfield Ave Caldwell NJ 07006",
    "addr:housenumber":"43",
    "addr:postcode":"07006",
    "addr:street":"Bloomfield Ave",
    "iso:country":"US",
    "sg:address":"43 Bloomfield Ave",
    "sg:city":"Caldwell",
    "sg:classifiers":[
        {
            "category":"Personal",
            "subcategory":"Beauty Salon",
            "type":"Services"
        }
    ],
    "sg:phone":"+1 973 228 2229",
    "sg:postcode":"07006",
    "sg:province":"NJ",
    "sg:tags":[
        "shop",
        "facility",
        "fitness",
        "spa",
        "day",
        "physical"
    ],
    "sg:website":"www.aurasalonandspa.com",
    "wof:name":"Aura Salon Spa",
    "wof:placetype":"venue"
},
  "geometry": {"coordinates":[-74.264297,40.835201],"type":"Point"}
}