{
  "type": "Feature",
  "properties": {
    "addr:full":"103 Howell Dr Somerville NJ 08876",
    "addr:housenumber":"103",
    "addr:postcode":"08876",
    "addr:street":"Howell Dr",
    "iso:country":"US",
    "sg:address":"103 Howell Dr",
    "sg:city":"Somerville",
    "sg:classifiers":[
        {
            "category":"Organizations",
            "subcategory":"Political Organization",
            "type":"Services"
        }
    ],
    "sg:phone":"+1 908 725 8406",
    "sg:postcode":"08876",
    "sg:province":"NJ",
    "wof:name":"League of Women Voters of US",
    "wof:placetype":"venue"
},
  "geometry": {"coordinates":[-74.697129,40.615831],"type":"Point"}
}