{
  "type": "Feature",
  "properties": {
    "addr:full":"27 Fell St Trenton NJ 08638",
    "addr:housenumber":"27",
    "addr:postcode":"08638",
    "addr:street":"Fell St",
    "iso:country":"US",
    "sg:address":"27 Fell St",
    "sg:city":"Trenton",
    "sg:classifiers":[
        {
            "category":"Professional",
            "subcategory":"Detective & Security Services",
            "type":"Services"
        }
    ],
    "sg:phone":"+1 609 989 3464",
    "sg:postcode":"08638",
    "sg:province":"NJ",
    "sg:tags":[
        "information",
        "bureau"
    ],
    "wof:name":"Dept Of Health Human Services",
    "wof:placetype":"venue"
},
  "geometry": {"coordinates":[-74.75655399999999,40.235466],"type":"Point"}
}