{
  "type": "Feature",
  "properties": {
    "iso:country":"US",
    "sg:address":"59 W Front St",
    "sg:city":"Keyport",
    "sg:classifiers":[
        {
            "category":"Professional",
            "type":"Services"
        }
    ],
    "sg:phone":"+1 732 739 5210",
    "sg:postcode":"07735",
    "sg:province":"NJ",
    "sg:tags":[
        "establishment"
    ],
    "wof:name":"Bauer Barbara Literary Agcy",
    "wof:placetype":"venue"
},
  "geometry": {"coordinates":[-74.20540699999999,40.436273],"type":"Point"}
}