{
  "type": "Feature",
  "properties": {
    "addr:full":"10 Sandford St New Brunswick NJ 08901",
    "addr:housenumber":"10",
    "addr:postcode":"08901",
    "addr:street":"Sandford St",
    "iso:country":"US",
    "sg:address":"10 Sandford St",
    "sg:city":"New Brunswick",
    "sg:classifiers":[
        {
            "category":"Building & Trades",
            "subcategory":"Construction",
            "type":"Services"
        }
    ],
    "sg:phone":"+1 732 418 0992",
    "sg:postcode":"08901",
    "sg:province":"NJ",
    "sg:tags":[
        "house"
    ],
    "wof:name":"Mento Construction LLC",
    "wof:placetype":"venue"
},
  "geometry": {"coordinates":[-74.445564,40.481219],"type":"Point"}
}