{
  "type": "Feature",
  "properties": {
    "iso:country":"US",
    "sg:address":"127 Arthur St",
    "sg:city":"Ridgefield Park",
    "sg:classifiers":[
        {
            "category":"Professional",
            "type":"Services"
        }
    ],
    "sg:phone":"+1 201 440 3640",
    "sg:postcode":"07660",
    "sg:province":"NJ",
    "wof:name":"Images In Glass",
    "wof:placetype":"venue"
},
  "geometry": {"coordinates":[-74.019561,40.864909],"type":"Point"}
}