{
  "type": "Feature",
  "properties": {
    "addr:full":"1271 US Highway 22 Lebanon NJ 08833",
    "addr:housenumber":"1271",
    "addr:postcode":"08833",
    "addr:street":"Us Highway 22",
    "iso:country":"US",
    "sg:address":"1271 US Highway 22",
    "sg:city":"Lebanon",
    "sg:classifiers":[
        {
            "category":"Deli",
            "type":"Food & Drink"
        }
    ],
    "sg:phone":"+1 908 236 0026",
    "sg:postcode":"08833",
    "sg:province":"NJ",
    "wof:name":"Lebanon Plaza Deli",
    "wof:placetype":"venue"
},
  "geometry": {"coordinates":[-74.830399,40.6437],"type":"Point"}
}