{
  "type": "Feature",
  "properties": {
    "iso:country":"US",
    "sg:address":"75 Essex St Ste 200",
    "sg:city":"Hackensack",
    "sg:classifiers":[
        {
            "category":"Professional",
            "subcategory":"Accounting & Tax Preparation",
            "type":"Services"
        }
    ],
    "sg:phone":"+1 201 487 7744",
    "sg:postcode":"07601",
    "sg:province":"NJ",
    "sg:tags":[
        "accountant"
    ],
    "sg:website":"www.tccpa.net",
    "wof:name":"Tobin Richard C CPA",
    "wof:placetype":"venue"
},
  "geometry": {"coordinates":[-74.047798,40.8783],"type":"Point"}
}