{
  "type": "Feature",
  "properties": {
    "addr:full":"285 N Main St Phillipsburg NJ 08865",
    "addr:housenumber":"285",
    "addr:postcode":"08865",
    "addr:street":"N Main St",
    "iso:country":"US",
    "sg:address":"285 N Main St",
    "sg:city":"Phillipsburg",
    "sg:classifiers":[
        {
            "category":"Retail",
            "subcategory":"Animal Services",
            "type":"Services"
        }
    ],
    "sg:phone":"+1 908 859 0889",
    "sg:postcode":"08865",
    "sg:province":"NJ",
    "wof:name":"For The Love Of Dogs Day Care",
    "wof:placetype":"venue"
},
  "geometry": {"coordinates":[-75.196461,40.699497],"type":"Point"}
}