{
  "type": "Feature",
  "properties": {
    "addr:full":"90 Taylor Ln Barnegat NJ 08005",
    "addr:housenumber":"90",
    "addr:postcode":"08005",
    "addr:street":"Taylor Ln",
    "iso:country":"US",
    "sg:address":"90 Taylor Ln",
    "sg:city":"Barnegat",
    "sg:classifiers":[
        {
            "category":"Wholesale",
            "subcategory":"Electrical",
            "type":"Manufacturing & Wholesale Goods"
        }
    ],
    "sg:phone":"+1 609 607 8666",
    "sg:postcode":"08005",
    "sg:province":"NJ",
    "sg:tags":[
        "communication",
        "radio",
        "system"
    ],
    "wof:name":"Windspan Communications",
    "wof:placetype":"venue"
},
  "geometry": {"coordinates":[-74.22727999999999,39.729091],"type":"Point"}
}