{
  "type": "Feature",
  "properties": {
    "iso:country":"US",
    "sg:address":"14 Bridge St",
    "sg:city":"Stockton",
    "sg:classifiers":[
        {
            "category":"Retail",
            "subcategory":"Auto Repair",
            "type":"Services"
        }
    ],
    "sg:phone":"+1 609 397 7282",
    "sg:postcode":"08559",
    "sg:province":"NJ",
    "sg:website":"www.texaco.com",
    "wof:name":"Ryan's Texaco",
    "wof:placetype":"venue"
},
  "geometry": {"coordinates":[-74.97779800000001,40.405701],"type":"Point"}
}