{
  "type": "Feature",
  "properties": {
    "addr:full":"19 Di Pilla Dr Thorofare NJ 08086",
    "addr:housenumber":"19",
    "addr:postcode":"08086",
    "addr:street":"Di Pilla Dr",
    "iso:country":"US",
    "sg:address":"19 Di Pilla Dr",
    "sg:city":"Thorofare",
    "sg:classifiers":[
        {
            "category":"Real Estate",
            "subcategory":"Real Estate Operator",
            "type":"Services"
        }
    ],
    "sg:phone":"+1 856 848 9422",
    "sg:postcode":"08086",
    "sg:province":"NJ",
    "sg:tags":[
        "apartment"
    ],
    "wof:name":"Westwood Gardens",
    "wof:placetype":"venue"
},
  "geometry": {"coordinates":[-75.18527,39.847851],"type":"Point"}
}