{
  "type": "Feature",
  "properties": {
    "iso:country":"US",
    "sg:address":"389 Lexington Ave",
    "sg:city":"Clifton",
    "sg:classifiers":[
        {
            "category":"Restaurant",
            "type":"Food & Drink"
        }
    ],
    "sg:phone":"+1 973 546 2549",
    "sg:postcode":"07011",
    "sg:province":"NJ",
    "sg:tags":[
        "eating",
        "chinese"
    ],
    "wof:name":"Jamito's Chinese Restaurant",
    "wof:placetype":"venue"
},
  "geometry": {"coordinates":[-74.13200399999999,40.874699],"type":"Point"}
}