{
  "type": "Feature",
  "properties": {
    "addr:full":"1018 Whitehead Rd Trenton NJ 08638",
    "addr:housenumber":"1018",
    "addr:postcode":"08638",
    "addr:street":"Whitehead Rd",
    "iso:country":"US",
    "sg:address":"1018 Whitehead Rd",
    "sg:city":"Trenton",
    "sg:classifiers":[
        {
            "category":"Real Estate",
            "subcategory":"Real Estate Agent",
            "type":"Services"
        }
    ],
    "sg:phone":"+1   ",
    "sg:postcode":"08638",
    "sg:province":"NJ",
    "sg:tags":[
        "broker"
    ],
    "wof:name":"John Simone Realty Inc",
    "wof:placetype":"venue"
},
  "geometry": {"coordinates":[-74.75728599999999,40.261508],"type":"Point"}
}