{
  "type": "Feature",
  "properties": {
    "addr:full":"1603 Mulberry Ct Monmouth Junction NJ 08852",
    "addr:housenumber":"1603",
    "addr:postcode":"08852",
    "addr:street":"Mulberry Ct",
    "iso:country":"US",
    "sg:address":"1603 Mulberry Ct",
    "sg:city":"Monmouth Junction",
    "sg:classifiers":[
        {
            "category":"Recreation",
            "type":"Entertainment"
        }
    ],
    "sg:phone":"+1   ",
    "sg:postcode":"08852",
    "sg:province":"NJ",
    "sg:tags":[
        "recreational",
        "family",
        "facility"
    ],
    "wof:name":"South Brunswick Grand Slam",
    "wof:placetype":"venue"
},
  "geometry": {"coordinates":[-74.561955,40.391662],"type":"Point"}
}