{
  "type": "Feature",
  "properties": {
    "iso:country":"US",
    "sg:address":"467 Main St",
    "sg:city":"Orange",
    "sg:classifiers":[
        {
            "category":"Shopping",
            "subcategory":"Clothing, Apparel, & Fashions",
            "type":"Retail Goods"
        }
    ],
    "sg:phone":"+1   ",
    "sg:postcode":"07050",
    "sg:province":"NJ",
    "wof:name":"Dresses Unlimited",
    "wof:placetype":"venue"
},
  "geometry": {"coordinates":[-74.23525600000001,40.774549],"type":"Point"}
}