{
  "type": "Feature",
  "properties": {
    "addr:full":"78 Mount Vernon Rd Englishtown NJ 07726",
    "addr:housenumber":"78",
    "addr:postcode":"07726",
    "addr:street":"Mount Vernon Rd",
    "iso:country":"US",
    "sg:address":"78 Mount Vernon Rd",
    "sg:city":"Englishtown",
    "sg:classifiers":[
        {
            "category":"Organizations",
            "subcategory":"Religious Organization",
            "type":"Services"
        }
    ],
    "sg:phone":"+1 732 446 4652",
    "sg:postcode":"07726",
    "sg:province":"NJ",
    "sg:tags":[
        "church"
    ],
    "wof:name":"Jehovah's Witnesses",
    "wof:placetype":"venue"
},
  "geometry": {"coordinates":[-74.376183,40.283705],"type":"Point"}
}