{
  "type": "Feature",
  "properties": {
    "addr:full":"30 Central Ave Newark NJ 07102",
    "addr:housenumber":"30",
    "addr:postcode":"07102",
    "addr:street":"Central Ave",
    "iso:country":"US",
    "sg:address":"30 Central Ave",
    "sg:city":"Newark",
    "sg:classifiers":[
        {
            "category":"Wholesale",
            "subcategory":"Non-durable Goods",
            "type":"Manufacturing & Wholesale Goods"
        }
    ],
    "sg:phone":"+1 973 621 1616",
    "sg:postcode":"07102",
    "sg:province":"NJ",
    "wof:name":"Ampadu-Fofie Janet A",
    "wof:placetype":"venue"
},
  "geometry": {"coordinates":[-74.169454,40.741357],"type":"Point"}
}