{
  "type": "Feature",
  "properties": {
    "iso:country":"US",
    "sg:address":"550 Central Ave",
    "sg:city":"Bridgewater",
    "sg:classifiers":[
        {
            "category":"Freight",
            "type":"Transportation"
        }
    ],
    "sg:phone":"+1 908 526 0730",
    "sg:postcode":"08807",
    "sg:province":"NJ",
    "sg:tags":[
        "general",
        "warehousing"
    ],
    "wof:name":"ICI Americas Inc",
    "wof:placetype":"venue"
},
  "geometry": {"coordinates":[-74.587913,40.561741],"type":"Point"}
}