{
  "type": "Feature",
  "properties": {
    "addr:full":"145 Lower Notch Rd Little Falls NJ 07424",
    "addr:housenumber":"145",
    "addr:postcode":"07424",
    "addr:street":"Lower Notch Rd",
    "iso:country":"US",
    "sg:address":"145 Lower Notch Rd",
    "sg:city":"Little Falls",
    "sg:classifiers":[
        {
            "category":"Health Services",
            "subcategory":"Doctor",
            "type":"Services"
        }
    ],
    "sg:phone":"+1 973 684 3663",
    "sg:postcode":"07424",
    "sg:province":"NJ",
    "sg:tags":[
        "physician",
        "surgeon"
    ],
    "wof:name":"Antonio Rizzo MD",
    "wof:placetype":"venue"
},
  "geometry": {"coordinates":[-74.208085,40.878593],"type":"Point"}
}