{
  "type": "Feature",
  "properties": {
    "addr:full":"428 W 4th St Plainfield NJ 07060",
    "addr:housenumber":"428",
    "addr:postcode":"07060",
    "addr:street":"W 4Th St",
    "iso:country":"US",
    "sg:address":"428 W 4th St",
    "sg:city":"Plainfield",
    "sg:classifiers":[
        {
            "category":"Retail",
            "subcategory":"Funeral Services",
            "type":"Services"
        }
    ],
    "sg:phone":"+1 908 756 4429",
    "sg:postcode":"07060",
    "sg:province":"NJ",
    "sg:tags":[
        "director"
    ],
    "wof:name":"Judkins' Colonial Home",
    "wof:placetype":"venue"
},
  "geometry": {"coordinates":[-74.425297,40.612906],"type":"Point"}
}