{
  "type": "Feature",
  "properties": {
    "iso:country":"US",
    "sg:address":"3 Hillside Rd",
    "sg:city":"Englishtown",
    "sg:classifiers":[
        {
            "category":"Wholesale",
            "subcategory":"Metals & Minerals",
            "type":"Manufacturing & Wholesale Goods"
        }
    ],
    "sg:phone":"+1 732 780 4134",
    "sg:postcode":"07726",
    "sg:province":"NJ",
    "sg:tags":[
        "conditioning",
        "air",
        "heating",
        "supply"
    ],
    "wof:name":"A C C I Inc",
    "wof:placetype":"venue"
},
  "geometry": {"coordinates":[-74.364283,40.239559],"type":"Point"}
}