{
  "type": "Feature",
  "properties": {
    "addr:full":"110 Bentley Ave Jersey City NJ 07304",
    "addr:housenumber":"110",
    "addr:postcode":"07304",
    "addr:street":"Bentley Ave",
    "iso:country":"US",
    "sg:address":"110 Bentley Ave",
    "sg:city":"Jersey City",
    "sg:classifiers":[
        {
            "category":"Insurance",
            "subcategory":"Insurance Agent",
            "type":"Services"
        }
    ],
    "sg:phone":"+1   ",
    "sg:postcode":"07304",
    "sg:province":"NJ",
    "wof:name":"Galante & Riotto Inc",
    "wof:placetype":"venue"
},
  "geometry": {"coordinates":[-74.078874,40.721752],"type":"Point"}
}