{
  "type": "Feature",
  "properties": {
    "addr:full":"17 N Minnisink Ave Parlin NJ 08859",
    "addr:housenumber":"17",
    "addr:postcode":"08859",
    "addr:street":"N Minnisink Ave",
    "iso:country":"US",
    "sg:address":"17 N Minnisink Ave",
    "sg:city":"Parlin",
    "sg:classifiers":[
        {
            "category":"Food & Beverages",
            "subcategory":"Groceries & Convenience Stores",
            "type":"Retail Goods"
        }
    ],
    "sg:phone":"+1   ",
    "sg:postcode":"08859",
    "sg:province":"NJ",
    "wof:name":"Lucky 7 Investments Inc",
    "wof:placetype":"venue"
},
  "geometry": {"coordinates":[-74.33815800000001,40.461835],"type":"Point"}
}