{
  "type": "Feature",
  "properties": {
    "addr:full":"147 Alpine Trl Sparta NJ 07871",
    "addr:housenumber":"147",
    "addr:postcode":"07871",
    "addr:street":"Alpine Trl",
    "iso:country":"US",
    "sg:address":"147 Alpine Trl",
    "sg:city":"Sparta",
    "sg:classifiers":[
        {
            "category":"Professional",
            "subcategory":"Management & Consulting",
            "type":"Services"
        }
    ],
    "sg:phone":"+1   ",
    "sg:postcode":"07871",
    "sg:province":"NJ",
    "wof:name":"David Wills",
    "wof:placetype":"venue"
},
  "geometry": {"coordinates":[-74.671514,41.019942],"type":"Point"}
}