{
  "type": "Feature",
  "properties": {
    "addr:full":"28 Virginia St Kendall Park NJ 08824",
    "addr:housenumber":"28",
    "addr:postcode":"08824",
    "addr:street":"Virginia St",
    "iso:country":"US",
    "sg:address":"28 Virginia St",
    "sg:city":"Kendall Park",
    "sg:classifiers":[
        {
            "category":"Retail",
            "subcategory":"Portrait Studio",
            "type":"Services"
        }
    ],
    "sg:phone":"+1   ",
    "sg:postcode":"08824",
    "sg:province":"NJ",
    "sg:tags":[
        "photo"
    ],
    "wof:name":"Moochalla Photographers",
    "wof:placetype":"venue"
},
  "geometry": {"coordinates":[-74.52946900000001,40.427994],"type":"Point"}
}