{
  "type": "Feature",
  "properties": {
    "iso:country":"US",
    "sg:address":"1090 King Georges Rd",
    "sg:city":"Edison",
    "sg:classifiers":[
        {
            "category":"Wholesale",
            "subcategory":"Groceries",
            "type":"Manufacturing & Wholesale Goods"
        }
    ],
    "sg:phone":"+1 732 627 9881",
    "sg:postcode":"08837",
    "sg:province":"NJ",
    "sg:tags":[
        "seasoning",
        "spice"
    ],
    "wof:name":"Herbakraft Inc",
    "wof:placetype":"venue"
},
  "geometry": {"coordinates":[-74.32618600000001,40.524342],"type":"Point"}
}