{
  "type": "Feature",
  "properties": {
    "addr:full":"16 W Browning Rd Collingswood NJ 08108",
    "addr:housenumber":"16",
    "addr:postcode":"08108",
    "addr:street":"W Browning Rd",
    "iso:country":"US",
    "sg:address":"16 W Browning Rd",
    "sg:city":"Collingswood",
    "sg:classifiers":[
        {
            "category":"Banks & Credit Unions",
            "subcategory":"Financial Services",
            "type":"Services"
        }
    ],
    "sg:phone":"+1   ",
    "sg:postcode":"08108",
    "sg:province":"NJ",
    "sg:tags":[
        "trust",
        "management"
    ],
    "wof:name":"Frances C Prutzman",
    "wof:placetype":"venue"
},
  "geometry": {"coordinates":[-75.081818,39.919353],"type":"Point"}
}