{
  "type": "Feature",
  "properties": {
    "addr:full":"612 Hanover Dr Wrightstown NJ 08562",
    "addr:housenumber":"612",
    "addr:postcode":"08562",
    "addr:street":"Hanover Dr",
    "iso:country":"US",
    "sg:address":"612 Hanover Dr",
    "sg:city":"Wrightstown",
    "sg:classifiers":[
        {
            "category":"Professional",
            "subcategory":"Management & Consulting",
            "type":"Services"
        }
    ],
    "sg:phone":"+1   ",
    "sg:postcode":"08562",
    "sg:province":"NJ",
    "wof:name":"Clayton Marketing Group",
    "wof:placetype":"venue"
},
  "geometry": {"coordinates":[-74.566205,40.089386],"type":"Point"}
}