{
  "type": "Feature",
  "properties": {
    "addr:full":"103 S Washington Ave Bergenfield NJ 07621",
    "addr:housenumber":"103",
    "addr:postcode":"07621",
    "addr:street":"S Washington Ave",
    "iso:country":"US",
    "sg:address":"103 S Washington Ave",
    "sg:city":"Bergenfield",
    "sg:classifiers":[
        {
            "category":"Retail",
            "subcategory":"Animal Services",
            "type":"Services"
        }
    ],
    "sg:phone":"+1 201 387 0070",
    "sg:postcode":"07621",
    "sg:province":"NJ",
    "wof:name":"All Our Furry Friends",
    "wof:placetype":"venue"
},
  "geometry": {"coordinates":[-73.99688,40.924605],"type":"Point"}
}