{
  "type": "Feature",
  "properties": {
    "iso:country":"US",
    "sg:address":"10 Banta Pl",
    "sg:city":"Hackensack",
    "sg:classifiers":[
        {
            "category":"Social Services",
            "type":"Services"
        }
    ],
    "sg:phone":"+1   ",
    "sg:postcode":"07601",
    "sg:province":"NJ",
    "sg:tags":[
        "individual",
        "family"
    ],
    "wof:name":"Lainstitute",
    "wof:placetype":"venue"
},
  "geometry": {"coordinates":[-74.04368100000001,40.885358],"type":"Point"}
}