{
  "type": "Feature",
  "properties": {
    "iso:country":"US",
    "sg:address":"2190 Meadow Dr",
    "sg:city":"Vineland",
    "sg:classifiers":[
        {
            "category":"Home & Garden",
            "subcategory":"Carpets & Floor Coverings",
            "type":"Retail Goods"
        }
    ],
    "sg:phone":"+1   ",
    "sg:postcode":"08361",
    "sg:province":"NJ",
    "wof:name":"Pro Finish Floors LLC",
    "wof:placetype":"venue"
},
  "geometry": {"coordinates":[-74.9845,39.487993],"type":"Point"}
}