{
  "type": "Feature",
  "properties": {
    "addr:full":"223 Ridge Rd North Arlington NJ 07031",
    "addr:housenumber":"223",
    "addr:postcode":"07031",
    "addr:street":"Ridge Rd North",
    "iso:country":"US",
    "sg:address":"223 Ridge Rd",
    "sg:city":"North Arlington",
    "sg:classifiers":[
        {
            "category":"Organizations",
            "subcategory":"Religious Organization",
            "type":"Services"
        }
    ],
    "sg:phone":"+1 201 991 2883",
    "sg:postcode":"07031",
    "sg:province":"NJ",
    "wof:name":"Grace Lutheran Church",
    "wof:placetype":"venue"
},
  "geometry": {"coordinates":[-74.132355,40.789912],"type":"Point"}
}