{
  "type": "Feature",
  "properties": {
    "addr:full":"22 Union Ave Lakehurst NJ 08733",
    "addr:housenumber":"22",
    "addr:postcode":"08733",
    "addr:street":"Union Ave",
    "iso:country":"US",
    "sg:address":"22 Union Ave",
    "sg:city":"Lakehurst",
    "sg:classifiers":[
        {
            "category":"Restaurant",
            "type":"Food & Drink"
        }
    ],
    "sg:phone":"+1   ",
    "sg:postcode":"08733",
    "sg:province":"NJ",
    "sg:tags":[
        "eating"
    ],
    "wof:name":"Mrs Walkers Ice Cream",
    "wof:placetype":"venue"
},
  "geometry": {"coordinates":[-74.31204700000001,40.012167],"type":"Point"}
}