{
  "type": "Feature",
  "properties": {
    "addr:full":"76 Tenafly Rd Englewood NJ 07631",
    "addr:housenumber":"76",
    "addr:postcode":"07631",
    "addr:street":"Tenafly Rd",
    "iso:country":"US",
    "sg:address":"76 Tenafly Rd",
    "sg:city":"Englewood",
    "sg:classifiers":[
        {
            "category":"Professional",
            "subcategory":"Art Services",
            "type":"Services"
        }
    ],
    "sg:phone":"+1 201 894 4711",
    "sg:postcode":"07631",
    "sg:province":"NJ",
    "sg:tags":[
        "artist"
    ],
    "wof:name":"M Rodriguez",
    "wof:placetype":"venue"
},
  "geometry": {"coordinates":[-73.977536,40.898838],"type":"Point"}
}