{
  "type": "Feature",
  "properties": {
    "addr:full":"42 Summerhill Ave Jackson NJ 08527",
    "addr:housenumber":"42",
    "addr:postcode":"08527",
    "addr:street":"Summerhill Ave",
    "iso:country":"US",
    "sg:address":"42 Summerhill Ave",
    "sg:city":"Jackson",
    "sg:classifiers":[
        {
            "category":"Professional",
            "type":"Services"
        }
    ],
    "sg:phone":"+1 732 905 4544",
    "sg:postcode":"08527",
    "sg:province":"NJ",
    "sg:tags":[
        "establishment"
    ],
    "wof:name":"Suttons International Inc",
    "wof:placetype":"venue"
},
  "geometry": {"coordinates":[-74.277849,40.155566],"type":"Point"}
}