{
  "type": "Feature",
  "properties": {
    "iso:country":"US",
    "sg:address":"1137 Bloomfield Ave",
    "sg:city":"West Caldwell",
    "sg:classifiers":[
        {
            "category":"Professional",
            "type":"Services"
        }
    ],
    "sg:phone":"+1 973 276 6047",
    "sg:postcode":"07006",
    "sg:province":"NJ",
    "sg:tags":[
        "establishment"
    ],
    "wof:name":"Toyota",
    "wof:placetype":"venue"
},
  "geometry": {"coordinates":[-74.310969,40.855454],"type":"Point"}
}