{
  "type": "Feature",
  "properties": {
    "iso:country":"US",
    "sg:address":"15 Hillside Pl",
    "sg:city":"Lodi",
    "sg:classifiers":[
        {
            "category":"Wholesale",
            "subcategory":"Vending Machines",
            "type":"Manufacturing & Wholesale Goods"
        }
    ],
    "sg:phone":"+1   ",
    "sg:postcode":"07644",
    "sg:province":"NJ",
    "sg:tags":[
        "operator"
    ],
    "wof:name":"A A Automatic Kold Snack",
    "wof:placetype":"venue"
},
  "geometry": {"coordinates":[-74.090099,40.883981],"type":"Point"}
}