{
  "type": "Feature",
  "properties": {
    "iso:country":"US",
    "sg:address":"75 Academy Dr",
    "sg:city":"Hammonton",
    "sg:classifiers":[
        {
            "category":"Airport",
            "type":"Transportation"
        }
    ],
    "sg:phone":"+1 609 704 1119",
    "sg:postcode":"08037",
    "sg:province":"NJ",
    "wof:name":"Hammonton Airport",
    "wof:placetype":"venue"
},
  "geometry": {"coordinates":[-74.755951,39.66721],"type":"Point"}
}