{
  "type": "Feature",
  "properties": {
    "addr:full":"140 John St Brick NJ 08724",
    "addr:housenumber":"140",
    "addr:postcode":"08724",
    "addr:street":"John St",
    "iso:country":"US",
    "sg:address":"140 John St",
    "sg:city":"Brick",
    "sg:classifiers":[
        {
            "category":"Utilities",
            "subcategory":"Telephone",
            "type":"Services"
        }
    ],
    "sg:phone":"+1 732 458 0459",
    "sg:postcode":"08724",
    "sg:province":"NJ",
    "sg:tags":[
        "telecommunication"
    ],
    "wof:name":"Continental Telecommunications",
    "wof:placetype":"venue"
},
  "geometry": {"coordinates":[-74.13211800000001,40.0745],"type":"Point"}
}