{
  "type": "Feature",
  "properties": {
    "iso:country":"US",
    "sg:address":"413 Springfield Ave",
    "sg:city":"Summit",
    "sg:classifiers":[
        {
            "category":"Shopping",
            "subcategory":"Shoes",
            "type":"Retail Goods"
        }
    ],
    "sg:phone":"+1 908 273 7979",
    "sg:postcode":"07901",
    "sg:province":"NJ",
    "sg:tags":[
        "store"
    ],
    "wof:name":"Walk Well Wright Arch Preservers",
    "wof:placetype":"venue"
},
  "geometry": {"coordinates":[-74.358902,40.717899],"type":"Point"}
}