{
  "type": "Feature",
  "properties": {
    "iso:country":"US",
    "sg:address":"3101 US Hwy 9",
    "sg:city":"Old Bridge",
    "sg:classifiers":[
        {
            "category":"Social Services",
            "subcategory":"Child Care",
            "type":"Services"
        }
    ],
    "sg:phone":"+1   ",
    "sg:postcode":"08857",
    "sg:province":"NJ",
    "wof:name":"Child Care Howell LLC",
    "wof:placetype":"venue"
},
  "geometry": {"coordinates":[-74.30810099999999,40.382727],"type":"Point"}
}