{
  "type": "Feature",
  "properties": {
    "addr:full":"661 Lincoln Ave Orange NJ 07050",
    "addr:housenumber":"661",
    "addr:postcode":"07050",
    "addr:street":"Lincoln Ave",
    "iso:country":"US",
    "sg:address":"661 Lincoln Ave",
    "sg:city":"Orange",
    "sg:classifiers":[
        {
            "category":"Building & Trades",
            "subcategory":"Construction",
            "type":"Services"
        }
    ],
    "sg:phone":"+1 973 673 5961",
    "sg:postcode":"07050",
    "sg:province":"NJ",
    "sg:tags":[
        "contractor"
    ],
    "wof:name":"Rpm Contracting LLC",
    "wof:placetype":"venue"
},
  "geometry": {"coordinates":[-74.247856,40.75845],"type":"Point"}
}