{
  "type": "Feature",
  "properties": {
    "iso:country":"US",
    "sg:address":"125 Cresskill Ave",
    "sg:city":"Dumont",
    "sg:classifiers":[
        {
            "category":"Building & Trades",
            "subcategory":"Landscaping Services",
            "type":"Services"
        }
    ],
    "sg:phone":"+1 201 501 8511",
    "sg:postcode":"07628",
    "sg:province":"NJ",
    "sg:tags":[
        "landscape",
        "contractor"
    ],
    "wof:name":"M F De Kovessey Inc",
    "wof:placetype":"venue"
},
  "geometry": {"coordinates":[-73.985472,40.947318],"type":"Point"}
}