{
  "type": "Feature",
  "properties": {
    "addr:full":"1403 Texas Ave Cape May NJ 08204",
    "addr:housenumber":"1403",
    "addr:postcode":"08204",
    "addr:street":"Texas Ave",
    "iso:country":"US",
    "sg:address":"1403 Texas Ave",
    "sg:city":"Cape May",
    "sg:classifiers":[
        {
            "category":"Health Services",
            "subcategory":"Chiropractor",
            "type":"Services"
        }
    ],
    "sg:phone":"+1 609 884 2162",
    "sg:postcode":"08204",
    "sg:province":"NJ",
    "wof:name":"Rizzo Joseph J Dr Chiropractor",
    "wof:placetype":"venue"
},
  "geometry": {"coordinates":[-74.907402,38.946201],"type":"Point"}
}