{
  "type": "Feature",
  "properties": {
    "addr:full":"602 Ridge Rd Lyndhurst NJ 07071",
    "addr:housenumber":"602",
    "addr:postcode":"07071",
    "addr:street":"Ridge Rd",
    "iso:country":"US",
    "sg:address":"602 Ridge Rd",
    "sg:city":"Lyndhurst",
    "sg:classifiers":[
        {
            "category":"Home & Garden",
            "subcategory":"Hardware",
            "type":"Retail Goods"
        }
    ],
    "sg:phone":"+1 201 939 5761",
    "sg:postcode":"07071",
    "sg:province":"NJ",
    "sg:tags":[
        "store"
    ],
    "wof:name":"H & H Hardware",
    "wof:placetype":"venue"
},
  "geometry": {"coordinates":[-74.12339799999999,40.802299],"type":"Point"}
}