{
  "type": "Feature",
  "properties": {
    "iso:country":"US",
    "sg:address":"220 Patricia Ave",
    "sg:city":"Colonia",
    "sg:classifiers":[
        {
            "category":"Building & Trades",
            "subcategory":"Construction",
            "type":"Services"
        }
    ],
    "sg:phone":"+1 732 381 6942",
    "sg:postcode":"07067",
    "sg:province":"NJ",
    "sg:tags":[
        "carpentry",
        "contractor"
    ],
    "wof:name":"N Dreams Wood Inc",
    "wof:placetype":"venue"
},
  "geometry": {"coordinates":[-74.31102799999999,40.603068],"type":"Point"}
}