{
  "type": "Feature",
  "properties": {
    "addr:full":"112 Evergreen Rd New Egypt NJ 08533",
    "addr:housenumber":"112",
    "addr:postcode":"08533",
    "addr:street":"Evergreen Rd",
    "iso:country":"US",
    "sg:address":"112 Evergreen Rd",
    "sg:city":"New Egypt",
    "sg:classifiers":[
        {
            "category":"Building & Trades",
            "subcategory":"Construction",
            "type":"Services"
        }
    ],
    "sg:phone":"+1 609 758 2324",
    "sg:postcode":"08533",
    "sg:province":"NJ",
    "sg:tags":[
        "painter"
    ],
    "wof:name":"T Whitaker Co Painter Paper",
    "wof:placetype":"venue"
},
  "geometry": {"coordinates":[-74.531745,40.07596],"type":"Point"}
}