{
  "type": "Feature",
  "properties": {
    "addr:full":"644 S Center St Orange NJ 07050",
    "addr:housenumber":"644",
    "addr:postcode":"07050",
    "addr:street":"S Center St",
    "iso:country":"US",
    "sg:address":"644 S Center St",
    "sg:city":"Orange",
    "sg:classifiers":[
        {
            "category":"Autos & Motor Vehicles",
            "subcategory":"Fuel & Gas Station",
            "type":"Retail Goods"
        }
    ],
    "sg:phone":"+1   ",
    "sg:postcode":"07050",
    "sg:province":"NJ",
    "sg:tags":[
        "station"
    ],
    "wof:name":"Exxon",
    "wof:placetype":"venue"
},
  "geometry": {"coordinates":[-74.236064,40.755049],"type":"Point"}
}