{
  "type": "Feature",
  "properties": {
    "addr:full":"152 Crestview Ave Absecon NJ 08201",
    "addr:housenumber":"152",
    "addr:postcode":"08201",
    "addr:street":"Crestview Ave",
    "iso:country":"US",
    "sg:address":"152 Crestview Ave",
    "sg:city":"Absecon",
    "sg:classifiers":[
        {
            "category":"Building & Trades",
            "subcategory":"Electrical",
            "type":"Services"
        }
    ],
    "sg:phone":"+1 609 645 8589",
    "sg:postcode":"08201",
    "sg:province":"NJ",
    "sg:tags":[
        "electrical",
        "contractor"
    ],
    "wof:name":"Barrella Electric",
    "wof:placetype":"venue"
},
  "geometry": {"coordinates":[-74.50297500000001,39.442264],"type":"Point"}
}