{
  "type": "Feature",
  "properties": {
    "iso:country":"US",
    "sg:address":"413 Belmont Ave",
    "sg:city":"Haledon",
    "sg:classifiers":[
        {
            "category":"Government",
            "subcategory":"Police Station",
            "type":"Public Place"
        }
    ],
    "sg:phone":"+1 973 790 4444",
    "sg:postcode":"07508",
    "sg:province":"NJ",
    "sg:tags":[
        "department"
    ],
    "wof:name":"Haledon Police Department",
    "wof:placetype":"venue"
},
  "geometry": {"coordinates":[-74.184921,40.93772],"type":"Point"}
}