{
  "type": "Feature",
  "properties": {
    "iso:country":"US",
    "sg:address":"601 W 4th St",
    "sg:city":"Plainfield",
    "sg:classifiers":[
        {
            "category":"Food & Beverages",
            "subcategory":"Specialty",
            "type":"Retail Goods"
        }
    ],
    "sg:phone":"+1   ",
    "sg:postcode":"07060",
    "sg:province":"NJ",
    "wof:name":"West Fourth Superett",
    "wof:placetype":"venue"
},
  "geometry": {"coordinates":[-74.42883999999999,40.609668],"type":"Point"}
}