{
  "type": "Feature",
  "properties": {
    "addr:full":"24 Regency Way Manalapan NJ 07726",
    "addr:housenumber":"24",
    "addr:postcode":"07726",
    "addr:street":"Regency Way",
    "iso:country":"US",
    "sg:address":"24 Regency Way",
    "sg:city":"Manalapan",
    "sg:classifiers":[
        {
            "category":"Shopping",
            "subcategory":"Computers & Home Electronics",
            "type":"Retail Goods"
        }
    ],
    "sg:phone":"+1 732 409 1041",
    "sg:postcode":"07726",
    "sg:province":"NJ",
    "sg:tags":[
        "software"
    ],
    "wof:name":"M & M Techsport",
    "wof:placetype":"venue"
},
  "geometry": {"coordinates":[-74.33853999999999,40.225964],"type":"Point"}
}