{
  "type": "Feature",
  "properties": {
    "addr:full":"36 Glen Ave E Harrington Park NJ 07640",
    "addr:housenumber":"36",
    "addr:postcode":"07640",
    "addr:street":"Glen Ave E",
    "iso:country":"US",
    "sg:address":"36 Glen Ave E",
    "sg:city":"Harrington Park",
    "sg:classifiers":[
        {
            "category":"Shopping",
            "subcategory":"Clothing, Apparel, & Fashions",
            "type":"Retail Goods"
        }
    ],
    "sg:phone":"+1   ",
    "sg:postcode":"07640",
    "sg:province":"NJ",
    "wof:name":"Cutups",
    "wof:placetype":"venue"
},
  "geometry": {"coordinates":[-73.97762400000001,40.988244],"type":"Point"}
}