{
  "type": "Feature",
  "properties": {
    "addr:full":"25 Kimberly Dr Runnemede NJ 08078",
    "addr:housenumber":"25",
    "addr:postcode":"08078",
    "addr:street":"Kimberly Dr",
    "iso:country":"US",
    "sg:address":"25 Kimberly Dr",
    "sg:city":"Runnemede",
    "sg:classifiers":[
        {
            "category":"Professional",
            "subcategory":"Research",
            "type":"Services"
        }
    ],
    "sg:phone":"+1   ",
    "sg:postcode":"08078",
    "sg:province":"NJ",
    "sg:tags":[
        "commercial",
        "physical"
    ],
    "wof:name":"Demartin Environmental Net Lab",
    "wof:placetype":"venue"
},
  "geometry": {"coordinates":[-75.052227,39.850554],"type":"Point"}
}