{
  "type": "Feature",
  "properties": {
    "iso:country":"US",
    "sg:address":"2211 Crossing Way",
    "sg:city":"Wayne",
    "sg:classifiers":[
        {
            "category":"Manufacturing",
            "subcategory":"Retail Goods",
            "type":"Manufacturing & Wholesale Goods"
        }
    ],
    "sg:phone":"+1 973 633 1797",
    "sg:postcode":"07470",
    "sg:province":"NJ",
    "sg:tags":[
        "product",
        "mfg"
    ],
    "wof:name":"Anatek Industries Liabilit",
    "wof:placetype":"venue"
},
  "geometry": {"coordinates":[-74.256799,40.90535],"type":"Point"}
}