{
  "type": "Feature",
  "properties": {
    "addr:full":"4 Trading Post Way Medford Lakes NJ 08055",
    "addr:housenumber":"4",
    "addr:postcode":"08055",
    "addr:street":"Post Way",
    "iso:country":"US",
    "sg:address":"4 Trading Post Way",
    "sg:city":"Medford Lakes",
    "sg:classifiers":[
        {
            "category":"Professional",
            "subcategory":"Computer Services",
            "type":"Services"
        }
    ],
    "sg:phone":"+1 609 714 2214",
    "sg:postcode":"08055",
    "sg:province":"NJ",
    "sg:tags":[
        "consultant",
        "designer",
        "programing",
        "custom"
    ],
    "wof:name":"Wepresent",
    "wof:placetype":"venue"
},
  "geometry": {"coordinates":[-74.80536499999999,39.862964],"type":"Point"}
}