{
  "type": "Feature",
  "properties": {
    "addr:full":"20 Milford Rd Bloomsbury NJ 08804",
    "addr:housenumber":"20",
    "addr:postcode":"08804",
    "addr:street":"Milford Rd",
    "iso:country":"US",
    "sg:address":"20 Milford Rd",
    "sg:city":"Bloomsbury",
    "sg:classifiers":[
        {
            "category":"Farming",
            "subcategory":"Berry Farm",
            "type":"Manufacturing & Wholesale Goods"
        }
    ],
    "sg:phone":"+1 908 479 6418",
    "sg:postcode":"08804",
    "sg:province":"NJ",
    "sg:tags":[
        "crop"
    ],
    "wof:name":"Walnut Meadows Farms",
    "wof:placetype":"venue"
},
  "geometry": {"coordinates":[-75.091902,40.649055],"type":"Point"}
}