{
  "type": "Feature",
  "properties": {
    "addr:full":"26 Rainbow Trl Sparta NJ 07871",
    "addr:housenumber":"26",
    "addr:postcode":"07871",
    "addr:street":"Rainbow Trl",
    "iso:country":"US",
    "sg:address":"26 Rainbow Trl",
    "sg:city":"Sparta",
    "sg:classifiers":[
        {
            "category":"Real Estate",
            "subcategory":"Real Estate Agent",
            "type":"Services"
        }
    ],
    "sg:phone":"+1 973 729 7871",
    "sg:postcode":"07871",
    "sg:province":"NJ",
    "sg:tags":[
        "appraiser"
    ],
    "wof:name":"Valuation Associates Corp",
    "wof:placetype":"venue"
},
  "geometry": {"coordinates":[-74.647856,41.033156],"type":"Point"}
}