{
  "type": "Feature",
  "properties": {
    "iso:country":"US",
    "sg:address":"11 Troy Dr",
    "sg:city":"Springfield",
    "sg:classifiers":[
        {
            "category":"Professional",
            "subcategory":"Business Services",
            "type":"Services"
        }
    ],
    "sg:phone":"+1   ",
    "sg:postcode":"07081",
    "sg:province":"NJ",
    "sg:tags":[
        "translation"
    ],
    "wof:name":"Afrassiabian Kourosh",
    "wof:placetype":"venue"
},
  "geometry": {"coordinates":[-74.33277,40.714307],"type":"Point"}
}