{
  "type": "Feature",
  "properties": {
    "addr:full":"399 Lake Shore Dr Hewitt NJ 07421",
    "addr:housenumber":"399",
    "addr:postcode":"07421",
    "addr:street":"Lake Shore Dr",
    "iso:country":"US",
    "sg:address":"399 Lake Shore Dr",
    "sg:city":"Hewitt",
    "sg:classifiers":[
        {
            "category":"Building & Trades",
            "subcategory":"Construction",
            "type":"Services"
        }
    ],
    "sg:phone":"+1 973 853 7674",
    "sg:postcode":"07421",
    "sg:province":"NJ",
    "sg:tags":[
        "insulation",
        "heat",
        "contractor"
    ],
    "wof:name":"Bal A Insulation Corp",
    "wof:placetype":"venue"
},
  "geometry": {"coordinates":[-74.370233,41.186202],"type":"Point"}
}