{
  "type": "Feature",
  "properties": {
    "addr:full":"18 Greylock Ave Belleville NJ 07109",
    "addr:housenumber":"18",
    "addr:postcode":"07109",
    "addr:street":"Greylock Ave",
    "iso:country":"US",
    "sg:address":"18 Greylock Ave",
    "sg:city":"Belleville",
    "sg:classifiers":[
        {
            "category":"Utilities",
            "subcategory":"Refuse",
            "type":"Services"
        }
    ],
    "sg:phone":"+1 973 759 5440",
    "sg:postcode":"07109",
    "sg:province":"NJ",
    "sg:tags":[
        "garbage",
        "collection"
    ],
    "wof:name":"Coppola Brothers",
    "wof:placetype":"venue"
},
  "geometry": {"coordinates":[-74.141773,40.799148],"type":"Point"}
}