{
  "type": "Feature",
  "properties": {
    "addr:full":"232 Willow Ave Hoboken NJ 07030",
    "addr:housenumber":"232",
    "addr:postcode":"07030",
    "addr:street":"Willow Ave",
    "iso:country":"US",
    "sg:address":"232 Willow Ave",
    "sg:city":"Hoboken",
    "sg:classifiers":[
        {
            "category":"Professional",
            "subcategory":"Computer Services",
            "type":"Services"
        }
    ],
    "sg:phone":"+1   ",
    "sg:postcode":"07030",
    "sg:province":"NJ",
    "sg:tags":[
        "related"
    ],
    "wof:name":"Lyric Systems LLC",
    "wof:placetype":"venue"
},
  "geometry": {"coordinates":[-74.033897,40.740208],"type":"Point"}
}