{
  "type": "Feature",
  "properties": {
    "iso:country":"US",
    "sg:address":"19 Miko Rd",
    "sg:city":"Edison",
    "sg:classifiers":[
        {
            "category":"Restaurant",
            "type":"Food & Drink"
        }
    ],
    "sg:phone":"+1   ",
    "sg:postcode":"08817",
    "sg:province":"NJ",
    "sg:tags":[
        "eating"
    ],
    "wof:name":"Jacks Food Service",
    "wof:placetype":"venue"
},
  "geometry": {"coordinates":[-74.382964,40.517969],"type":"Point"}
}