{
  "type": "Feature",
  "properties": {
    "addr:full":"65 Hickory Ave Bergenfield NJ 07621",
    "addr:housenumber":"65",
    "addr:postcode":"07621",
    "addr:street":"Hickory Ave",
    "iso:country":"US",
    "sg:address":"65 Hickory Ave",
    "sg:city":"Bergenfield",
    "sg:classifiers":[
        {
            "category":"Professional",
            "subcategory":"Business Services",
            "type":"Services"
        },
        {
            "category":"Real Estate",
            "subcategory":"Developer",
            "type":"Services"
        }
    ],
    "sg:phone":"+1 201 384 9236",
    "sg:postcode":"07621",
    "sg:province":"NJ",
    "sg:tags":[
        "land",
        "holding"
    ],
    "wof:name":"Clemens Edward",
    "wof:placetype":"venue"
},
  "geometry": {"coordinates":[-73.992447,40.93224],"type":"Point"}
}