{
  "type": "Feature",
  "properties": {
    "iso:country":"US",
    "sg:address":"10 Reed Ct",
    "sg:city":"Wayne",
    "sg:classifiers":[
        {
            "category":"Health Services",
            "subcategory":"Doctor",
            "type":"Services"
        }
    ],
    "sg:phone":"+1 973 696 2941",
    "sg:postcode":"07470",
    "sg:province":"NJ",
    "wof:name":"Schwarz Herbert F MD",
    "wof:placetype":"venue"
},
  "geometry": {"coordinates":[-74.265297,40.956501],"type":"Point"}
}