{
  "type": "Feature",
  "properties": {
    "addr:full":"360 Crider Ave Moorestown NJ 08057",
    "addr:housenumber":"360",
    "addr:postcode":"08057",
    "addr:street":"Crider Ave",
    "iso:country":"US",
    "sg:address":"360 Crider Ave",
    "sg:city":"Moorestown",
    "sg:classifiers":[
        {
            "category":"Manufacturing",
            "subcategory":"Signs",
            "type":"Manufacturing & Wholesale Goods"
        }
    ],
    "sg:phone":"+1 856 802 1677",
    "sg:postcode":"08057",
    "sg:province":"NJ",
    "sg:tags":[
        "installs",
        "mfg",
        "custom"
    ],
    "wof:name":"NW Sign Industries Inc",
    "wof:placetype":"venue"
},
  "geometry": {"coordinates":[-74.981824,39.965641],"type":"Point"}
}