{
  "type": "Feature",
  "properties": {
    "addr:full":"25 Buckley Hill Rd Morristown NJ 07960",
    "addr:housenumber":"25",
    "addr:postcode":"07960",
    "addr:street":"Buckley Hill Rd",
    "iso:country":"US",
    "sg:address":"25 Buckley Hill Rd",
    "sg:city":"Morristown",
    "sg:classifiers":[
        {
            "category":"Wholesale",
            "subcategory":"Motor Vehicles",
            "type":"Manufacturing & Wholesale Goods"
        }
    ],
    "sg:phone":"+1 973 285 1330",
    "sg:postcode":"07960",
    "sg:province":"NJ",
    "sg:tags":[
        "automobile",
        "accessory"
    ],
    "wof:name":"Autobern Trading Corporation",
    "wof:placetype":"venue"
},
  "geometry": {"coordinates":[-74.51866699999999,40.822504],"type":"Point"}
}