{
  "type": "Feature",
  "properties": {
    "addr:full":"2 Paragon Way Freehold NJ 07728",
    "addr:housenumber":"2",
    "addr:postcode":"07728",
    "addr:street":"Paragon Way",
    "iso:country":"US",
    "sg:address":"2 Paragon Way",
    "sg:city":"Freehold",
    "sg:classifiers":[
        {
            "category":"Professional",
            "type":"Services"
        }
    ],
    "sg:phone":"+1 732 683 1712",
    "sg:postcode":"07728",
    "sg:province":"NJ",
    "sg:tags":[
        "establishment"
    ],
    "wof:name":"Arraycom",
    "wof:placetype":"venue"
},
  "geometry": {"coordinates":[-74.253317,40.239245],"type":"Point"}
}