{
  "type": "Feature",
  "properties": {
    "addr:full":"2117 Rancocas Rd Burlington NJ 08016",
    "addr:housenumber":"2117",
    "addr:postcode":"08016",
    "addr:street":"Rancocas Rd",
    "iso:country":"US",
    "sg:address":"2117 Rancocas Rd",
    "sg:city":"Burlington",
    "sg:classifiers":[
        {
            "category":"Retail",
            "subcategory":"Auto Repair",
            "type":"Services"
        }
    ],
    "sg:phone":"+1 609 387 1656",
    "sg:postcode":"08016",
    "sg:province":"NJ",
    "sg:tags":[
        "body",
        "go"
    ],
    "wof:name":"Klassic Auto Upholstery",
    "wof:placetype":"venue"
},
  "geometry": {"coordinates":[-74.85119400000001,40.041173],"type":"Point"}
}