{
  "type": "Feature",
  "properties": {
    "iso:country":"US",
    "sg:address":"28 Autumnwood Ln",
    "sg:city":"Mount Laurel",
    "sg:classifiers":[
        {
            "category":"Professional",
            "subcategory":"Business Services",
            "type":"Services"
        }
    ],
    "sg:phone":"+1   ",
    "sg:postcode":"08054",
    "sg:province":"NJ",
    "wof:name":"Computer Access Solutions LLC",
    "wof:placetype":"venue"
},
  "geometry": {"coordinates":[-74.874821,39.931734],"type":"Point"}
}