{
  "type": "Feature",
  "properties": {
    "iso:country":"US",
    "sg:address":"9 Elm St",
    "sg:city":"Westfield",
    "sg:classifiers":[
        {
            "category":"Shopping",
            "subcategory":"Gifts & Souvenirs",
            "type":"Retail Goods"
        }
    ],
    "sg:phone":"+1   ",
    "sg:postcode":"07090",
    "sg:province":"NJ",
    "sg:tags":[
        "shop"
    ],
    "wof:name":"Periwinkles Group",
    "wof:placetype":"venue"
},
  "geometry": {"coordinates":[-74.347971,40.650607],"type":"Point"}
}