{
  "type": "Feature",
  "properties": {
    "iso:country":"US",
    "sg:address":"53 Green Ave",
    "sg:city":"Trenton",
    "sg:classifiers":[
        {
            "category":"Retail",
            "subcategory":"Portrait Studio",
            "type":"Services"
        }
    ],
    "sg:phone":"+1 609 219 0040",
    "sg:postcode":"08648",
    "sg:province":"NJ",
    "sg:tags":[
        "photo"
    ],
    "wof:name":"Jeff Rotman Photography",
    "wof:placetype":"venue"
},
  "geometry": {"coordinates":[-74.737652,40.297577],"type":"Point"}
}