{
  "type": "Feature",
  "properties": {
    "iso:country":"US",
    "sg:address":"726 Walling Ave",
    "sg:city":"Belmar",
    "sg:classifiers":[
        {
            "category":"Building & Trades",
            "subcategory":"Plumbing",
            "type":"Services"
        }
    ],
    "sg:phone":"+1 732 556 0981",
    "sg:postcode":"07719",
    "sg:province":"NJ",
    "sg:tags":[
        "contractor"
    ],
    "wof:name":"R F Solomon Fire Protection",
    "wof:placetype":"venue"
},
  "geometry": {"coordinates":[-74.029893,40.172415],"type":"Point"}
}