{
  "type": "Feature",
  "properties": {
    "addr:full":"41 Babcock Ln Willingboro NJ 08046",
    "addr:housenumber":"41",
    "addr:postcode":"08046",
    "addr:street":"Babcock Ln",
    "iso:country":"US",
    "sg:address":"41 Babcock Ln",
    "sg:city":"Willingboro",
    "sg:classifiers":[
        {
            "category":"Manufacturing",
            "subcategory":"Retail Goods",
            "type":"Manufacturing & Wholesale Goods"
        }
    ],
    "sg:phone":"+1 609 835 4420",
    "sg:postcode":"08046",
    "sg:province":"NJ",
    "sg:tags":[
        "product",
        "mfg"
    ],
    "wof:name":"Eastern Global Industries",
    "wof:placetype":"venue"
},
  "geometry": {"coordinates":[-74.882851,40.03772],"type":"Point"}
}