{
  "type": "Feature",
  "properties": {
    "addr:full":"6050 Black Horse Pike Egg Harbor Twp NJ 08234",
    "addr:housenumber":"6050",
    "addr:postcode":"08234",
    "addr:street":"Black Horse Pike",
    "iso:country":"US",
    "sg:address":"6050 Black Horse Pike",
    "sg:city":"Egg Harbor Twp",
    "sg:classifiers":[
        {
            "category":"Shopping",
            "subcategory":"Pharmacy",
            "type":"Retail Goods"
        }
    ],
    "sg:phone":"+1 609 484 7065",
    "sg:postcode":"08234",
    "sg:province":"NJ",
    "wof:name":"Eckerd",
    "wof:placetype":"venue"
},
  "geometry": {"coordinates":[-74.615617,39.437816],"type":"Point"}
}