{
  "type": "Feature",
  "properties": {
    "addr:full":"61 Brighton Ave Long Branch NJ 07740",
    "addr:housenumber":"61",
    "addr:postcode":"07740",
    "addr:street":"Brighton Ave",
    "iso:country":"US",
    "sg:address":"61 Brighton Ave",
    "sg:city":"Long Branch",
    "sg:classifiers":[
        {
            "category":"Shopping",
            "subcategory":"Used Merchandise",
            "type":"Retail Goods"
        }
    ],
    "sg:phone":"+1 732 222 7880",
    "sg:postcode":"07740",
    "sg:province":"NJ",
    "sg:tags":[
        "antique"
    ],
    "wof:name":"Hy Spot Antiques & Collectible",
    "wof:placetype":"venue"
},
  "geometry": {"coordinates":[-73.984222,40.284633],"type":"Point"}
}