{
  "type": "Feature",
  "properties": {
    "iso:country":"US",
    "sg:address":"348 Essex St",
    "sg:city":"Hackensack",
    "sg:classifiers":[
        {
            "category":"Retail",
            "subcategory":"Repair Shop",
            "type":"Services"
        }
    ],
    "sg:phone":"+1 201 498 0404",
    "sg:postcode":"07601",
    "sg:province":"NJ",
    "sg:tags":[
        "lock",
        "locksmith"
    ],
    "wof:name":"Five Star Locksmith",
    "wof:placetype":"venue"
},
  "geometry": {"coordinates":[-74.05640099999999,40.881951],"type":"Point"}
}