{
  "type": "Feature",
  "properties": {
    "addr:full":"250 Centre St Nutley NJ 07110",
    "addr:housenumber":"250",
    "addr:postcode":"07110",
    "addr:street":"Centre St",
    "iso:country":"US",
    "sg:address":"250 Centre St",
    "sg:city":"Nutley",
    "sg:classifiers":[
        {
            "category":"Retail",
            "subcategory":"Laundry & Dry Cleaning",
            "type":"Services"
        }
    ],
    "sg:phone":"+1 973 562 0084",
    "sg:postcode":"07110",
    "sg:province":"NJ",
    "wof:name":"Judy's Dry Cleaners",
    "wof:placetype":"venue"
},
  "geometry": {"coordinates":[-74.15709699999999,40.812901],"type":"Point"}
}