{
  "type": "Feature",
  "properties": {
    "iso:country":"US",
    "sg:address":"170 Kinnelon Rd",
    "sg:city":"Kinnelon",
    "sg:classifiers":[
        {
            "category":"Professional",
            "subcategory":"Accounting & Tax Preparation",
            "type":"Services"
        }
    ],
    "sg:phone":"+1 973 838 9400",
    "sg:postcode":"07405",
    "sg:province":"NJ",
    "sg:tags":[
        "accountant"
    ],
    "sg:website":"www.cgsc-cpa.com",
    "wof:name":"Cullari Gallo Soojian",
    "wof:placetype":"venue"
},
  "geometry": {"coordinates":[-74.384738,40.989068],"type":"Point"}
}