{
  "type": "Feature",
  "properties": {
    "addr:full":"160 E Midland Ave Paramus NJ 07652",
    "addr:housenumber":"160",
    "addr:postcode":"07652",
    "addr:street":"E Midland Ave",
    "iso:country":"US",
    "sg:address":"160 E Midland Ave",
    "sg:city":"Paramus",
    "sg:classifiers":[
        {
            "category":"Wholesale",
            "subcategory":"Groceries",
            "type":"Manufacturing & Wholesale Goods"
        }
    ],
    "sg:phone":"+1 201 261 3718",
    "sg:postcode":"07652",
    "sg:province":"NJ",
    "sg:tags":[
        "confectionery",
        "candy"
    ],
    "wof:name":"Lemberger Candy Co",
    "wof:placetype":"venue"
},
  "geometry": {"coordinates":[-74.05794899999999,40.947829],"type":"Point"}
}