{
  "type": "Feature",
  "properties": {
    "iso:country":"US",
    "sg:address":"325 Carlton Ave",
    "sg:city":"Piscataway",
    "sg:classifiers":[
        {
            "category":"Professional",
            "subcategory":"Computer Services",
            "type":"Services"
        }
    ],
    "sg:phone":"+1   ",
    "sg:postcode":"08854",
    "sg:province":"NJ",
    "sg:tags":[
        "datum"
    ],
    "wof:name":"Radhakrishnananair",
    "wof:placetype":"venue"
},
  "geometry": {"coordinates":[-74.442339,40.568392],"type":"Point"}
}