{
  "type": "Feature",
  "properties": {
    "addr:full":"88 Quenby Mountain Rd Great Meadows NJ 07838",
    "addr:housenumber":"88",
    "addr:postcode":"07838",
    "addr:street":"Quenby Mountain Rd",
    "iso:country":"US",
    "sg:address":"88 Quenby Mountain Rd",
    "sg:city":"Great Meadows",
    "sg:classifiers":[
        {
            "category":"Professional",
            "type":"Services"
        }
    ],
    "sg:phone":"+1   ",
    "sg:postcode":"07838",
    "sg:province":"NJ",
    "wof:name":"Inspired Designs Inc",
    "wof:placetype":"venue"
},
  "geometry": {"coordinates":[-74.959557,40.848285],"type":"Point"}
}