{
  "type": "Feature",
  "properties": {
    "iso:country":"US",
    "sg:address":"432 Sand Shore Rd",
    "sg:city":"Budd Lake",
    "sg:classifiers":[
        {
            "category":"Manufacturing",
            "subcategory":"Electronics",
            "type":"Manufacturing & Wholesale Goods"
        },
        {
            "category":"Wholesale",
            "subcategory":"Electrical",
            "type":"Manufacturing & Wholesale Goods"
        }
    ],
    "sg:phone":"+1 908 684 2390",
    "sg:postcode":"07840",
    "sg:province":"NJ",
    "sg:tags":[
        "sub",
        "component",
        "system",
        "microwave",
        "communications",
        "comm"
    ],
    "wof:name":"Jersey Microwave LLC",
    "wof:placetype":"venue"
},
  "geometry": {"coordinates":[-74.776889,40.856999],"type":"Point"}
}