{
  "type": "Feature",
  "properties": {
    "addr:full":"8 Myrtle Dr Montague NJ 07827",
    "addr:housenumber":"8",
    "addr:postcode":"07827",
    "addr:street":"Myrtle Dr",
    "iso:country":"US",
    "sg:address":"8 Myrtle Dr",
    "sg:city":"Montague",
    "sg:classifiers":[
        {
            "category":"Wholesale",
            "subcategory":"Motor Vehicles",
            "type":"Manufacturing & Wholesale Goods"
        },
        {
            "category":"Personal",
            "type":"Services"
        }
    ],
    "sg:phone":"+1 973 293 3734",
    "sg:postcode":"07827",
    "sg:province":"NJ",
    "sg:tags":[
        "automobile",
        "towing",
        "transporter"
    ],
    "wof:name":"Vic's Towing & Auto Transport",
    "wof:placetype":"venue"
},
  "geometry": {"coordinates":[-74.790176,41.284809],"type":"Point"}
}