{
  "type": "Feature",
  "properties": {
    "iso:country":"US",
    "sg:address":"33 W Avon Ave",
    "sg:city":"Irvington",
    "sg:classifiers":[
        {
            "category":"Shopping",
            "subcategory":"Discount & Variety Stores",
            "type":"Retail Goods"
        }
    ],
    "sg:phone":"+1   ",
    "sg:postcode":"07111",
    "sg:province":"NJ",
    "wof:name":"H&J Variety",
    "wof:placetype":"venue"
},
  "geometry": {"coordinates":[-74.225126,40.731811],"type":"Point"}
}