{
  "type": "Feature",
  "properties": {
    "addr:full":"131 Oregon Ave Trenton NJ 08638",
    "addr:housenumber":"131",
    "addr:postcode":"08638",
    "addr:street":"Oregon Ave",
    "iso:country":"US",
    "sg:address":"131 Oregon Ave",
    "sg:city":"Trenton",
    "sg:classifiers":[
        {
            "category":"Building & Trades",
            "subcategory":"Construction",
            "type":"Services"
        }
    ],
    "sg:phone":"+1 609 883 4772",
    "sg:postcode":"08638",
    "sg:province":"NJ",
    "sg:tags":[
        "general",
        "contractor"
    ],
    "wof:name":"Lums Custom Builder Inc",
    "wof:placetype":"venue"
},
  "geometry": {"coordinates":[-74.777148,40.261843],"type":"Point"}
}