{
  "type": "Feature",
  "properties": {
    "addr:full":"69 Broad St Red Bank NJ 07701",
    "addr:housenumber":"69",
    "addr:postcode":"07701",
    "addr:street":"Broad St",
    "iso:country":"US",
    "sg:address":"69 Broad St",
    "sg:city":"Red Bank",
    "sg:classifiers":[
        {
            "category":"Restaurant",
            "type":"Food & Drink"
        }
    ],
    "sg:menulink":"http://www.allmenus.com/nj/red-bank/292313-monticello-at-red-bank/menu/",
    "sg:phone":"+1 732 450 0255",
    "sg:postcode":"07701",
    "sg:province":"NJ",
    "sg:tags":[
        "italian"
    ],
    "wof:name":"Monticello At Red Bank",
    "wof:placetype":"venue"
},
  "geometry": {"coordinates":[-74.065394,40.350292],"type":"Point"}
}