{
  "type": "Feature",
  "properties": {
    "iso:country":"US",
    "sg:address":"434 US Hwy 46",
    "sg:city":"South Hackensack",
    "sg:classifiers":[
        {
            "category":"Building & Trades",
            "subcategory":"Construction",
            "type":"Services"
        }
    ],
    "sg:phone":"+1 201 440 4070",
    "sg:postcode":"07606",
    "sg:province":"NJ",
    "sg:tags":[
        "general",
        "contractor"
    ],
    "wof:name":"A'Italia United Construction",
    "wof:placetype":"venue"
},
  "geometry": {"coordinates":[-74.05117300000001,40.857433],"type":"Point"}
}