{
  "type": "Feature",
  "properties": {
    "addr:full":"1126 Concord Dr Brick NJ 08724",
    "addr:housenumber":"1126",
    "addr:postcode":"08724",
    "addr:street":"Concord Dr",
    "iso:country":"US",
    "sg:address":"1126 Concord Dr",
    "sg:city":"Brick",
    "sg:classifiers":[
        {
            "category":"Professional",
            "subcategory":"Research",
            "type":"Services"
        }
    ],
    "sg:phone":"+1 732 458 1700",
    "sg:postcode":"08724",
    "sg:province":"NJ",
    "sg:tags":[
        "environmental",
        "ecological"
    ],
    "wof:name":"Jmc Environmental Consultants",
    "wof:placetype":"venue"
},
  "geometry": {"coordinates":[-74.12102299999999,40.116287],"type":"Point"}
}