{
  "type": "Feature",
  "properties": {
    "addr:full":"11 N Main St Cape May Ct Hse NJ 08210",
    "addr:housenumber":"11",
    "addr:postcode":"08210",
    "addr:street":"N Main St Cape May Ct",
    "iso:country":"US",
    "sg:address":"11 N Main St",
    "sg:city":"Cape May Ct Hse",
    "sg:classifiers":[
        {
            "category":"Government",
            "subcategory":"Office",
            "type":"Public Place"
        }
    ],
    "sg:phone":"+1 609 463 6481",
    "sg:postcode":"08210",
    "sg:province":"NJ",
    "sg:tags":[
        "county",
        "resource"
    ],
    "wof:name":"Child Abuse Unit",
    "wof:placetype":"venue"
},
  "geometry": {"coordinates":[-74.823412,39.083024],"type":"Point"}
}