{
  "type": "Feature",
  "properties": {
    "iso:country":"US",
    "sg:address":"224 Central Ave",
    "sg:city":"Newark",
    "sg:classifiers":[
        {
            "category":"Building & Trades",
            "subcategory":"Plumbing",
            "type":"Services"
        }
    ],
    "sg:phone":"+1 973 375 0960",
    "sg:postcode":"07103",
    "sg:province":"NJ",
    "sg:tags":[
        "contractor"
    ],
    "wof:name":"Allied Air Compressor",
    "wof:placetype":"venue"
},
  "geometry": {"coordinates":[-74.180942,40.744963],"type":"Point"}
}