{
  "type": "Feature",
  "properties": {
    "iso:country":"US",
    "sg:address":"26 Elmswell Ave",
    "sg:city":"Lakehurst",
    "sg:classifiers":[
        {
            "category":"Organizations",
            "subcategory":"Religious Organization",
            "type":"Services"
        }
    ],
    "sg:phone":"+1   ",
    "sg:postcode":"08759",
    "sg:province":"NJ",
    "wof:name":"United Church of Christ Toms R",
    "wof:placetype":"venue"
},
  "geometry": {"coordinates":[-74.284706,40.018011],"type":"Point"}
}