{
  "type": "Feature",
  "properties": {
    "iso:country":"US",
    "sg:address":"38 E Mill Rd",
    "sg:city":"Long Valley",
    "sg:classifiers":[
        {
            "category":"Health Services",
            "subcategory":"Doctor",
            "type":"Services"
        }
    ],
    "sg:phone":"+1 908 876 9711",
    "sg:postcode":"07853",
    "sg:province":"NJ",
    "sg:tags":[
        "physician",
        "surgeon"
    ],
    "wof:name":"Long Valley Medical Assoc",
    "wof:placetype":"venue"
},
  "geometry": {"coordinates":[-74.775131,40.784353],"type":"Point"}
}