{
  "type": "Feature",
  "properties": {
    "iso:country":"US",
    "sg:address":"82 Old Mountain Rd",
    "sg:city":"Lebanon",
    "sg:classifiers":[
        {
            "category":"Utilities",
            "subcategory":"Telephone",
            "type":"Services"
        }
    ],
    "sg:phone":"+1 908 268 1629",
    "sg:postcode":"08833",
    "sg:province":"NJ",
    "sg:tags":[
        "security",
        "internet"
    ],
    "wof:name":"Identaware Security",
    "wof:placetype":"venue"
},
  "geometry": {"coordinates":[-74.811001,40.630789],"type":"Point"}
}