{
  "type": "Feature",
  "properties": {
    "addr:full":"403 Green Village Rd Green Village NJ 07935",
    "addr:housenumber":"403",
    "addr:postcode":"07935",
    "addr:street":"Green Village Rd",
    "iso:country":"US",
    "sg:address":"403 Green Village Rd",
    "sg:city":"Green Village",
    "sg:classifiers":[
        {
            "category":"Home & Garden",
            "subcategory":"Garden Supply",
            "type":"Retail Goods"
        }
    ],
    "sg:phone":"+1 973 377 8703",
    "sg:postcode":"07935",
    "sg:province":"NJ",
    "sg:tags":[
        "nursery",
        "gardening"
    ],
    "wof:name":"Farm At Green Village the",
    "wof:placetype":"venue"
},
  "geometry": {"coordinates":[-74.437698,40.741699],"type":"Point"}
}