{
  "type": "Feature",
  "properties": {
    "addr:full":"335 60th St West New York NJ 07093",
    "addr:housenumber":"335",
    "addr:postcode":"nj 07093",
    "addr:street":"60Th St West",
    "iso:country":"US",
    "sg:address":"335 60th St",
    "sg:city":"West New York",
    "sg:classifiers":[
        {
            "category":"Shopping",
            "subcategory":"Pharmacy",
            "type":"Retail Goods"
        }
    ],
    "sg:phone":"+1 201 854 1829",
    "sg:postcode":"07093",
    "sg:province":"NJ",
    "sg:tags":[
        "drugstore"
    ],
    "wof:name":"Central Pharmacy",
    "wof:placetype":"venue"
},
  "geometry": {"coordinates":[-74.014099,40.787701],"type":"Point"}
}