{
  "type": "Feature",
  "properties": {
    "addr:full":"470 Martin Luther King Jr Blvd Newark NJ 07102",
    "addr:housenumber":"470",
    "addr:postcode":"07102",
    "addr:street":"Martin Luther King Jr Blvd",
    "iso:country":"US",
    "sg:address":"470 Martin Luther King Jr Blvd",
    "sg:city":"Newark",
    "sg:classifiers":[
        {
            "category":"Building & Trades",
            "subcategory":"Electrical",
            "type":"Services"
        }
    ],
    "sg:phone":"+1 973 622 6928",
    "sg:postcode":"07102",
    "sg:province":"NJ",
    "sg:tags":[
        "electric",
        "contractor"
    ],
    "wof:name":"Lighton Electric Inc",
    "wof:placetype":"venue"
},
  "geometry": {"coordinates":[-74.179215,40.737301],"type":"Point"}
}