{
  "type": "Feature",
  "properties": {
    "addr:full":"5254 US Highway 130 Bordentown NJ 08505",
    "addr:housenumber":"5254",
    "addr:postcode":"08505",
    "addr:street":"Us Highway 130",
    "iso:country":"US",
    "sg:address":"5254 US Highway 130",
    "sg:city":"Bordentown",
    "sg:classifiers":[
        {
            "category":"Food & Beverages",
            "subcategory":"Bakery",
            "type":"Retail Goods"
        }
    ],
    "sg:phone":"+1 609 298 8933",
    "sg:postcode":"08505",
    "sg:province":"NJ",
    "sg:tags":[
        "sandwich"
    ],
    "wof:name":"Liberty Two Diner",
    "wof:placetype":"venue"
},
  "geometry": {"coordinates":[-74.76799800000001,40.113201],"type":"Point"}
}