{
  "type": "Feature",
  "properties": {
    "addr:full":"6 S Fullerton Ave Ste 5 Montclair NJ 07042",
    "addr:housenumber":"6",
    "addr:postcode":"07042",
    "addr:street":"S Fullerton Ave Ste 5",
    "iso:country":"US",
    "sg:address":"6 S Fullerton Ave Ste 5",
    "sg:city":"Montclair",
    "sg:classifiers":[
        {
            "category":"Real Estate",
            "subcategory":"Architect",
            "type":"Services"
        }
    ],
    "sg:phone":"+1 973 746 5100",
    "sg:postcode":"07042",
    "sg:province":"NJ",
    "wof:name":"Fabiano Designs International",
    "wof:placetype":"venue"
},
  "geometry": {"coordinates":[-74.217697,40.813702],"type":"Point"}
}