{
  "type": "Feature",
  "properties": {
    "iso:country":"US",
    "sg:address":"246 Welch Way",
    "sg:city":"Westfield",
    "sg:classifiers":[
        {
            "category":"Shopping",
            "subcategory":"Hobbies, Toys, & Games",
            "type":"Retail Goods"
        }
    ],
    "sg:phone":"+1 908 233 0688",
    "sg:postcode":"07090",
    "sg:province":"NJ",
    "sg:tags":[
        "craft"
    ],
    "wof:name":"R T Sales",
    "wof:placetype":"venue"
},
  "geometry": {"coordinates":[-74.32206600000001,40.641111],"type":"Point"}
}