{
  "type": "Feature",
  "properties": {
    "addr:full":"450 Hamburg Tpke Wayne NJ 07470",
    "addr:housenumber":"450",
    "addr:postcode":"07470",
    "addr:street":"Hamburg Tpke",
    "iso:country":"US",
    "sg:address":"450 Hamburg Tpke",
    "sg:city":"Wayne",
    "sg:classifiers":[
        {
            "category":"Health Services",
            "subcategory":"Podiatrist",
            "type":"Services"
        }
    ],
    "sg:phone":"+1 973 595 8900",
    "sg:postcode":"07470",
    "sg:province":"NJ",
    "wof:name":"Wayne Foot & Ankle Ctr",
    "wof:placetype":"venue"
},
  "geometry": {"coordinates":[-74.21033799999999,40.952],"type":"Point"}
}