{
  "type": "Feature",
  "properties": {
    "iso:country":"US",
    "sg:address":"79 Alexander Ave",
    "sg:city":"Montclair",
    "sg:classifiers":[
        {
            "category":"Professional",
            "subcategory":"Research",
            "type":"Services"
        }
    ],
    "sg:phone":"+1   ",
    "sg:postcode":"07043",
    "sg:province":"NJ",
    "sg:tags":[
        "nonphysical",
        "commercial"
    ],
    "wof:name":"M & A London LLC",
    "wof:placetype":"venue"
},
  "geometry": {"coordinates":[-74.191996,40.849357],"type":"Point"}
}