{
  "type": "Feature",
  "properties": {
    "addr:full":"421 Cokesbury Rd Annandale NJ 08801",
    "addr:housenumber":"421",
    "addr:postcode":"08801",
    "addr:street":"Cokesbury Rd",
    "iso:country":"US",
    "sg:address":"421 Cokesbury Rd",
    "sg:city":"Annandale",
    "sg:classifiers":[
        {
            "category":"Professional",
            "subcategory":"Business Services",
            "type":"Services"
        }
    ],
    "sg:phone":"+1   ",
    "sg:postcode":"08801",
    "sg:province":"NJ",
    "sg:tags":[
        "pool",
        "hot",
        "tub",
        "maintenance",
        "swimming"
    ],
    "wof:name":"Pool Works",
    "wof:placetype":"venue"
},
  "geometry": {"coordinates":[-74.86673399999999,40.682015],"type":"Point"}
}