{
  "type": "Feature",
  "properties": {
    "iso:country":"US",
    "sg:address":"111 Ave A",
    "sg:city":"Bayonne",
    "sg:classifiers":[
        {
            "category":"Airline",
            "type":"Transportation"
        }
    ],
    "sg:phone":"+1 201 437 3668",
    "sg:postcode":"07002",
    "sg:province":"NJ",
    "sg:tags":[
        "scheduled",
        "air"
    ],
    "wof:name":"Flight Power Inc",
    "wof:placetype":"venue"
},
  "geometry": {"coordinates":[-74.137815,40.651776],"type":"Point"}
}