{
  "type": "Feature",
  "properties": {
    "addr:full":"329 Undercliff Ave Edgewater NJ 07020",
    "addr:housenumber":"329",
    "addr:postcode":"07020",
    "addr:street":"Undercliff Ave",
    "iso:country":"US",
    "sg:address":"329 Undercliff Ave",
    "sg:city":"Edgewater",
    "sg:classifiers":[
        {
            "category":"Shopping",
            "subcategory":"Computers & Home Electronics",
            "type":"Retail Goods"
        }
    ],
    "sg:phone":"+1   ",
    "sg:postcode":"07020",
    "sg:province":"NJ",
    "wof:name":"Pkc Technical Svc",
    "wof:placetype":"venue"
},
  "geometry": {"coordinates":[-73.976482,40.825821],"type":"Point"}
}