{
  "type": "Feature",
  "properties": {
    "iso:country":"US",
    "sg:address":"32 Scotch Rd",
    "sg:city":"Trenton",
    "sg:classifiers":[
        {
            "category":"Insurance",
            "subcategory":"Insurance Agent",
            "type":"Services"
        }
    ],
    "sg:phone":"+1 609 392 1528",
    "sg:postcode":"08628",
    "sg:province":"NJ",
    "wof:name":"Harrison Insurance",
    "wof:placetype":"venue"
},
  "geometry": {"coordinates":[-74.801174,40.266041],"type":"Point"}
}