{
  "type": "Feature",
  "properties": {
    "addr:full":"209 N 9th St Newark NJ 07107",
    "addr:housenumber":"209",
    "addr:postcode":"07107",
    "addr:street":"N 9Th St",
    "iso:country":"US",
    "sg:address":"209 N 9th St",
    "sg:city":"Newark",
    "sg:classifiers":[
        {
            "category":"Wholesale",
            "subcategory":"Non-durable Goods",
            "type":"Manufacturing & Wholesale Goods"
        }
    ],
    "sg:phone":"+1 973 485 6218",
    "sg:postcode":"07107",
    "sg:province":"NJ",
    "sg:tags":[
        "export",
        "gen"
    ],
    "wof:name":"Bonnie Hannah",
    "wof:placetype":"venue"
},
  "geometry": {"coordinates":[-74.18875300000001,40.763094],"type":"Point"}
}