{
  "type": "Feature",
  "properties": {
    "iso:country":"US",
    "sg:address":"1018 Palisade Ave",
    "sg:city":"Fort Lee",
    "sg:classifiers":[
        {
            "category":"Wholesale",
            "subcategory":"Durable Goods & Equipment",
            "type":"Manufacturing & Wholesale Goods"
        }
    ],
    "sg:phone":"+1 201 569 2475",
    "sg:postcode":"07024",
    "sg:province":"NJ",
    "sg:tags":[
        "exporter"
    ],
    "wof:name":"Fibre Group Inc",
    "wof:placetype":"venue"
},
  "geometry": {"coordinates":[-73.979046,40.831116],"type":"Point"}
}