{
  "type": "Feature",
  "properties": {
    "iso:country":"US",
    "sg:address":"530 Edison St",
    "sg:city":"Ridgefield",
    "sg:classifiers":[
        {
            "category":"Retail",
            "subcategory":"Auto Repair",
            "type":"Services"
        }
    ],
    "sg:phone":"+1 201 943 3535",
    "sg:postcode":"07657",
    "sg:province":"NJ",
    "sg:tags":[
        "truck"
    ],
    "wof:name":"Tony's Towing Svc",
    "wof:placetype":"venue"
},
  "geometry": {"coordinates":[-74.001474,40.831868],"type":"Point"}
}