{
  "type": "Feature",
  "properties": {
    "addr:full":"496 Park Edison NJ 08837",
    "addr:housenumber":"496",
    "addr:postcode":"08837",
    "addr:street":"Park Edison",
    "iso:country":"US",
    "sg:address":"496 Park",
    "sg:city":"Edison",
    "sg:classifiers":[
        {
            "category":"Manufacturing",
            "subcategory":"Leather Goods",
            "type":"Manufacturing & Wholesale Goods"
        }
    ],
    "sg:phone":"+1 732 494 4344",
    "sg:postcode":"08837",
    "sg:province":"NJ",
    "sg:tags":[
        "mfg"
    ],
    "wof:name":"Designers Leather",
    "wof:placetype":"venue"
},
  "geometry": {"coordinates":[-74.33564200000001,40.550312],"type":"Point"}
}