{
  "type": "Feature",
  "properties": {
    "iso:country":"US",
    "sg:address":"833 Hampden St",
    "sg:city":"Linden",
    "sg:classifiers":[
        {
            "category":"Utilities",
            "subcategory":"Mobile Phone",
            "type":"Services"
        }
    ],
    "sg:phone":"+1 908 523 0827",
    "sg:postcode":"07036",
    "sg:province":"NJ",
    "sg:tags":[
        "communication",
        "radiotelephone"
    ],
    "wof:name":"Keep In Touch Wireless Inc",
    "wof:placetype":"venue"
},
  "geometry": {"coordinates":[-74.256118,40.616422],"type":"Point"}
}