{
  "type": "Feature",
  "properties": {
    "addr:full":"174 Main St Hackettstown NJ 07840",
    "addr:housenumber":"174",
    "addr:postcode":"07840",
    "addr:street":"Main St",
    "iso:country":"US",
    "sg:address":"174 Main St",
    "sg:city":"Hackettstown",
    "sg:classifiers":[
        {
            "category":"Banks & Credit Unions",
            "subcategory":"Investment Brokerage",
            "type":"Services"
        }
    ],
    "sg:phone":"+1   ",
    "sg:postcode":"07840",
    "sg:province":"NJ",
    "sg:tags":[
        "security"
    ],
    "wof:name":"Edward Jones 06500",
    "wof:placetype":"venue"
},
  "geometry": {"coordinates":[-74.828782,40.853275],"type":"Point"}
}