{
  "type": "Feature",
  "properties": {
    "addr:full":"202 Fulling Mill Rd Cape May NJ 08204",
    "addr:housenumber":"202",
    "addr:postcode":"08204",
    "addr:street":"Fulling Mill Rd",
    "iso:country":"US",
    "sg:address":"202 Fulling Mill Rd",
    "sg:city":"Cape May",
    "sg:classifiers":[
        {
            "category":"Autos & Motor Vehicles",
            "subcategory":"Automobile Sales",
            "type":"Retail Goods"
        },
        {
            "category":"Taxi",
            "type":"Transportation"
        },
        {
            "category":"Airline",
            "type":"Transportation"
        }
    ],
    "sg:phone":"+1 609 886 0111",
    "sg:postcode":"08204",
    "sg:province":"NJ",
    "sg:tags":[
        "shuttle",
        "airport",
        "limo"
    ],
    "wof:name":"Victorian Cape Limousine",
    "wof:placetype":"venue"
},
  "geometry": {"coordinates":[-74.929199,38.9701],"type":"Point"}
}