{
  "type": "Feature",
  "properties": {
    "addr:full":"56 Progress Pl Jackson NJ 08527",
    "addr:housenumber":"56",
    "addr:postcode":"08527",
    "addr:street":"Progress Pl",
    "iso:country":"US",
    "sg:address":"56 Progress Pl",
    "sg:city":"Jackson",
    "sg:classifiers":[
        {
            "category":"Wholesale",
            "subcategory":"Construction Materials",
            "type":"Manufacturing & Wholesale Goods"
        },
        {
            "category":"Organizations",
            "subcategory":"Community Association",
            "type":"Services"
        }
    ],
    "sg:phone":"+1 732 928 7990",
    "sg:postcode":"08527",
    "sg:province":"NJ",
    "sg:tags":[
        "club",
        "cage",
        "batting"
    ],
    "wof:name":"Jackson Baseball Softball Academy",
    "wof:placetype":"venue"
},
  "geometry": {"coordinates":[-74.352253,40.157051],"type":"Point"}
}