{
  "type": "Feature",
  "properties": {
    "iso:country":"US",
    "sg:address":"1690 State Rte 38",
    "sg:city":"Mt Holly",
    "sg:classifiers":[
        {
            "category":"Shopping",
            "type":"Retail Goods"
        },
        {
            "category":"Building & Trades",
            "subcategory":"Construction",
            "type":"Services"
        }
    ],
    "sg:phone":"+1 609 267 2600",
    "sg:postcode":"08060",
    "sg:province":"NJ",
    "sg:tags":[
        "designer",
        "merchandise",
        "t",
        "dealer",
        "pool",
        "swimming"
    ],
    "wof:name":"Discount Pool & Supplies",
    "wof:placetype":"venue"
},
  "geometry": {"coordinates":[-74.80839400000001,39.988257],"type":"Point"}
}