{
  "type": "Feature",
  "properties": {
    "iso:country":"US",
    "sg:address":"168 Stevens St",
    "sg:city":"Cape May",
    "sg:classifiers":[
        {
            "category":"Home & Garden",
            "subcategory":"Garden Supply",
            "type":"Retail Goods"
        }
    ],
    "sg:phone":"+1 609 884 8101",
    "sg:postcode":"08204",
    "sg:province":"NJ",
    "sg:tags":[
        "nurseryman"
    ],
    "wof:name":"Willow Creek Farm Nursery",
    "wof:placetype":"venue"
},
  "geometry": {"coordinates":[-74.941705,38.942817],"type":"Point"}
}