{
  "type": "Feature",
  "properties": {
    "addr:full":"525 W Broad St Paulsboro NJ 08066",
    "addr:housenumber":"525",
    "addr:postcode":"08066",
    "addr:street":"W Broad St",
    "iso:country":"US",
    "sg:address":"525 W Broad St",
    "sg:city":"Paulsboro",
    "sg:classifiers":[
        {
            "category":"Organizations",
            "subcategory":"Community Association",
            "type":"Services"
        }
    ],
    "sg:phone":"+1 856 423 2622",
    "sg:postcode":"08066",
    "sg:province":"NJ",
    "sg:tags":[
        "fraternal"
    ],
    "wof:name":"Sons Of Italy Lodge",
    "wof:placetype":"venue"
},
  "geometry": {"coordinates":[-75.25167,39.827325],"type":"Point"}
}