{
  "type": "Feature",
  "properties": {
    "addr:full":"7001 N Park Dr Merchantville NJ 08109",
    "addr:housenumber":"7001",
    "addr:postcode":"08109",
    "addr:street":"N Park Dr",
    "iso:country":"US",
    "sg:address":"7001 N Park Dr",
    "sg:city":"Merchantville",
    "sg:classifiers":[
        {
            "category":"Manufacturing",
            "subcategory":"Printing",
            "type":"Manufacturing & Wholesale Goods"
        }
    ],
    "sg:phone":"+1 856 665 5200",
    "sg:postcode":"08109",
    "sg:province":"NJ",
    "sg:tags":[
        "commercial",
        "offset"
    ],
    "wof:name":"Lehigh Press Lithographers",
    "wof:placetype":"venue"
},
  "geometry": {"coordinates":[-75.083803,39.927955],"type":"Point"}
}