{
  "type": "Feature",
  "properties": {
    "addr:full":"620 High Bridge Rd Colts Neck NJ 07722",
    "addr:housenumber":"620",
    "addr:postcode":"07722",
    "addr:street":"High Bridge Rd",
    "iso:country":"US",
    "sg:address":"620 High Bridge Rd",
    "sg:city":"Colts Neck",
    "sg:classifiers":[
        {
            "category":"Professional",
            "subcategory":"Advertising",
            "type":"Services"
        }
    ],
    "sg:phone":"+1   ",
    "sg:postcode":"07722",
    "sg:province":"NJ",
    "sg:tags":[
        "agency"
    ],
    "sg:website":"www.homeimprovementguides.com",
    "wof:name":"White Mountain Advertising",
    "wof:placetype":"venue"
},
  "geometry": {"coordinates":[-74.142321,40.321487],"type":"Point"}
}