{
  "type": "Feature",
  "properties": {
    "addr:full":"42 Mercer St Phillipsburg NJ 08865",
    "addr:housenumber":"42",
    "addr:postcode":"08865",
    "addr:street":"Mercer St",
    "iso:country":"US",
    "sg:address":"42 Mercer St",
    "sg:city":"Phillipsburg",
    "sg:classifiers":[
        {
            "category":"Organizations",
            "subcategory":"Religious Organization",
            "type":"Services"
        }
    ],
    "sg:phone":"+1 908 454 5070",
    "sg:postcode":"08865",
    "sg:province":"NJ",
    "sg:tags":[
        "church"
    ],
    "wof:name":"Blessed Hope Church",
    "wof:placetype":"venue"
},
  "geometry": {"coordinates":[-75.196321,40.686164],"type":"Point"}
}