{
  "type": "Feature",
  "properties": {
    "iso:country":"US",
    "sg:address":"514 N Main St",
    "sg:city":"Elmer",
    "sg:classifiers":[
        {
            "category":"Organizations",
            "subcategory":"Religious Organization",
            "type":"Services"
        }
    ],
    "sg:phone":"+1 856 358 4374",
    "sg:postcode":"08318",
    "sg:province":"NJ",
    "sg:tags":[
        "clergy"
    ],
    "wof:name":"Thomas N Austin",
    "wof:placetype":"venue"
},
  "geometry": {"coordinates":[-75.17518099999999,39.599855],"type":"Point"}
}