{
  "type": "Feature",
  "properties": {
    "addr:full":"2050 Center Ave Fort Lee NJ 07024",
    "addr:housenumber":"2050",
    "addr:postcode":"07024",
    "addr:street":"Center Ave",
    "iso:country":"US",
    "sg:address":"2050 Center Ave",
    "sg:city":"Fort Lee",
    "sg:classifiers":[
        {
            "category":"Shopping",
            "type":"Retail Goods"
        }
    ],
    "sg:phone":"+1 201 944 0770",
    "sg:postcode":"07024",
    "sg:province":"NJ",
    "sg:tags":[
        "candle"
    ],
    "wof:name":"Illume Candles",
    "wof:placetype":"venue"
},
  "geometry": {"coordinates":[-73.97076,40.854672],"type":"Point"}
}