{
  "type": "Feature",
  "properties": {
    "addr:full":"2606 State Rte 37 Toms River NJ 08753",
    "addr:housenumber":"2606",
    "addr:postcode":"08753",
    "addr:street":"State Rte 37",
    "iso:country":"US",
    "sg:address":"2606 State Rte 37",
    "sg:city":"Toms River",
    "sg:classifiers":[
        {
            "category":"Shopping",
            "subcategory":"Clothing, Apparel, & Fashions",
            "type":"Retail Goods"
        }
    ],
    "sg:phone":"+1 732 929 4070",
    "sg:postcode":"08753",
    "sg:province":"NJ",
    "sg:tags":[
        "shop",
        "bridal"
    ],
    "wof:name":"Forever Yours Bridal",
    "wof:placetype":"venue"
},
  "geometry": {"coordinates":[-74.128461,39.950317],"type":"Point"}
}