{
  "type": "Feature",
  "properties": {
    "iso:country":"US",
    "sg:address":"310 Belmont Ave",
    "sg:city":"Haledon",
    "sg:classifiers":[
        {
            "category":"Home & Garden",
            "subcategory":"Home Furnishings",
            "type":"Retail Goods"
        }
    ],
    "sg:phone":"+1 973 720 9990",
    "sg:postcode":"07508",
    "sg:province":"NJ",
    "sg:tags":[
        "draperies",
        "window",
        "treatment",
        "curtain",
        "drapery",
        "trimming"
    ],
    "wof:name":"Curtains Plus",
    "wof:placetype":"venue"
},
  "geometry": {"coordinates":[-74.184174,40.933703],"type":"Point"}
}