{
  "type": "Feature",
  "properties": {
    "addr:full":"111 N Thurlow Ave Margate City NJ 08402",
    "addr:housenumber":"111",
    "addr:postcode":"08402",
    "addr:street":"N Thurlow Ave Margate",
    "iso:country":"US",
    "sg:address":"111 N Thurlow Ave",
    "sg:city":"Margate City",
    "sg:classifiers":[
        {
            "category":"Professional",
            "subcategory":"Business Services",
            "type":"Services"
        }
    ],
    "sg:phone":"+1   ",
    "sg:postcode":"08402",
    "sg:province":"NJ",
    "wof:name":"Ean Assoc",
    "wof:placetype":"venue"
},
  "geometry": {"coordinates":[-74.511978,39.327016],"type":"Point"}
}