{
  "type": "Feature",
  "properties": {
    "iso:country":"US",
    "sg:address":"420 Hirsch Ave",
    "sg:city":"Runnemede",
    "sg:classifiers":[
        {
            "category":"Building & Trades",
            "subcategory":"Landscaping Services",
            "type":"Services"
        }
    ],
    "sg:phone":"+1 856 931 5336",
    "sg:postcode":"08078",
    "sg:province":"NJ",
    "wof:name":"Greenery Lawn Service",
    "wof:placetype":"venue"
},
  "geometry": {"coordinates":[-75.081504,39.851224],"type":"Point"}
}