{
  "type": "Feature",
  "properties": {
    "iso:country":"US",
    "sg:address":"205 US Hwy 46",
    "sg:city":"Totowa",
    "sg:classifiers":[
        {
            "category":"Personal",
            "type":"Services"
        }
    ],
    "sg:phone":"+1 973 785 8586",
    "sg:postcode":"07512",
    "sg:province":"NJ",
    "sg:tags":[
        "therapist",
        "massage"
    ],
    "wof:name":"Hot Dancers",
    "wof:placetype":"venue"
},
  "geometry": {"coordinates":[-74.23621900000001,40.894871],"type":"Point"}
}