{
  "type": "Feature",
  "properties": {
    "iso:country":"US",
    "sg:address":"29 Connor Ave",
    "sg:city":"Metuchen",
    "sg:classifiers":[
        {
            "category":"Recreation",
            "type":"Entertainment"
        }
    ],
    "sg:phone":"+1 732 548 4358",
    "sg:postcode":"08840",
    "sg:province":"NJ",
    "sg:tags":[
        "club",
        "membership"
    ],
    "wof:name":"Penn State Club Northern NJ",
    "wof:placetype":"venue"
},
  "geometry": {"coordinates":[-74.377145,40.538206],"type":"Point"}
}