{
  "type": "Feature",
  "properties": {
    "iso:country":"US",
    "sg:address":"3902 Smith Dr",
    "sg:city":"Pt Pleasant Bch",
    "sg:classifiers":[
        {
            "category":"Professional",
            "subcategory":"Management & Consulting",
            "type":"Services"
        }
    ],
    "sg:phone":"+1 732 892 6608",
    "sg:postcode":"08742",
    "sg:province":"NJ",
    "sg:tags":[
        "consultant",
        "business"
    ],
    "wof:name":"Dokus Consulting Inc",
    "wof:placetype":"venue"
},
  "geometry": {"coordinates":[-74.090469,40.091208],"type":"Point"}
}