{
  "type": "Feature",
  "properties": {
    "addr:full":"466 US Hwy 202 Bedminster NJ 07921",
    "addr:housenumber":"466",
    "addr:postcode":"07921",
    "addr:street":"Us Hwy 202",
    "iso:country":"US",
    "sg:address":"466 US Hwy 202",
    "sg:city":"Bedminster",
    "sg:classifiers":[
        {
            "category":"Retail",
            "subcategory":"Repair Shop",
            "type":"Services"
        }
    ],
    "sg:phone":"+1 908 364 0185",
    "sg:postcode":"07921",
    "sg:province":"NJ",
    "sg:tags":[
        "lock",
        "locksmith"
    ],
    "wof:name":"USA Locksmith",
    "wof:placetype":"venue"
},
  "geometry": {"coordinates":[-74.63846599999999,40.682823],"type":"Point"}
}