{
  "type": "Feature",
  "properties": {
    "addr:full":"59 Main St Hackensack NJ 07601",
    "addr:housenumber":"59",
    "addr:postcode":"07601",
    "addr:street":"Main St",
    "iso:country":"US",
    "sg:address":"59 Main St",
    "sg:city":"Hackensack",
    "sg:classifiers":[
        {
            "category":"Retail",
            "subcategory":"Repair Shop",
            "type":"Services"
        }
    ],
    "sg:phone":"+1 201 786 0550",
    "sg:postcode":"07601",
    "sg:province":"NJ",
    "sg:tags":[
        "lock",
        "locksmith"
    ],
    "wof:name":"24 Hour Emergency Locksmith",
    "wof:placetype":"venue"
},
  "geometry": {"coordinates":[-74.04422700000001,40.879657],"type":"Point"}
}