{
  "type": "Feature",
  "properties": {
    "iso:country":"US",
    "sg:address":"2324 Penn St",
    "sg:city":"Pennsauken",
    "sg:classifiers":[
        {
            "category":"Organizations",
            "subcategory":"Professional Association",
            "type":"Services"
        }
    ],
    "sg:phone":"+1   ",
    "sg:postcode":"08110",
    "sg:province":"NJ",
    "sg:tags":[
        "business"
    ],
    "wof:name":"VFW Post 1270",
    "wof:placetype":"venue"
},
  "geometry": {"coordinates":[-75.053293,39.961378],"type":"Point"}
}