{
  "type": "Feature",
  "properties": {
    "iso:country":"US",
    "sg:address":"73 Elizabeth St",
    "sg:city":"Bloomingdale",
    "sg:classifiers":[
        {
            "category":"Professional",
            "subcategory":"Secretarial Services",
            "type":"Services"
        }
    ],
    "sg:phone":"+1   ",
    "sg:postcode":"07403",
    "sg:province":"NJ",
    "sg:tags":[
        "reporting"
    ],
    "wof:name":"Prestige Transcription",
    "wof:placetype":"venue"
},
  "geometry": {"coordinates":[-74.342693,41.013507],"type":"Point"}
}