{
  "type": "Feature",
  "properties": {
    "iso:country":"US",
    "sg:address":"127 Main St",
    "sg:city":"Metuchen",
    "sg:classifiers":[
        {
            "category":"Social Services",
            "type":"Services"
        }
    ],
    "sg:phone":"+1 732 452 9699",
    "sg:postcode":"08840",
    "sg:province":"NJ",
    "sg:tags":[
        "counseling"
    ],
    "wof:name":"Korean American Women",
    "wof:placetype":"venue"
},
  "geometry": {"coordinates":[-74.35878599999999,40.531144],"type":"Point"}
}