{
  "type": "Feature",
  "properties": {
    "addr:full":"10 Liberty Rd Marlboro NJ 07746",
    "addr:housenumber":"10",
    "addr:postcode":"07746",
    "addr:street":"Liberty Rd",
    "iso:country":"US",
    "sg:address":"10 Liberty Rd",
    "sg:city":"Marlboro",
    "sg:classifiers":[
        {
            "category":"Real Estate",
            "subcategory":"Real Estate Agent",
            "type":"Services"
        }
    ],
    "sg:phone":"+1   ",
    "sg:postcode":"07746",
    "sg:province":"NJ",
    "wof:name":"4111 Bergenline Realty Corp",
    "wof:placetype":"venue"
},
  "geometry": {"coordinates":[-74.26455799999999,40.324276],"type":"Point"}
}