{
  "type": "Feature",
  "properties": {
    "addr:full":"128 Elliott Pl South Plainfield NJ 07080",
    "addr:housenumber":"128",
    "addr:postcode":"07080",
    "addr:street":"Elliott Pl",
    "iso:country":"US",
    "sg:address":"128 Elliott Pl",
    "sg:city":"South Plainfield",
    "sg:classifiers":[
        {
            "category":"Professional",
            "subcategory":"Employment Agencies",
            "type":"Services"
        }
    ],
    "sg:phone":"+1 908 753 3751",
    "sg:postcode":"07080",
    "sg:province":"NJ",
    "sg:tags":[
        "consultant",
        "search",
        "executive"
    ],
    "wof:name":"Allen Associates Inc",
    "wof:placetype":"venue"
},
  "geometry": {"coordinates":[-74.420174,40.568047],"type":"Point"}
}