{
  "type": "Feature",
  "properties": {
    "addr:full":"74 Franklin Ave Nutley NJ 07110",
    "addr:housenumber":"74",
    "addr:postcode":"07110",
    "addr:street":"Franklin Ave",
    "iso:country":"US",
    "sg:address":"74 Franklin Ave",
    "sg:city":"Nutley",
    "sg:classifiers":[
        {
            "category":"Real Estate",
            "subcategory":"Real Estate Agent",
            "type":"Services"
        }
    ],
    "sg:phone":"+1   ",
    "sg:postcode":"07110",
    "sg:province":"NJ",
    "sg:tags":[
        "brokerage"
    ],
    "wof:name":"Monaco Realty",
    "wof:placetype":"venue"
},
  "geometry": {"coordinates":[-74.164813,40.811651],"type":"Point"}
}