{
  "type": "Feature",
  "properties": {
    "addr:full":"607 Anderson Ave Cliffside Park NJ 07010",
    "addr:housenumber":"607",
    "addr:postcode":"07010",
    "addr:street":"Anderson Ave",
    "iso:country":"US",
    "sg:address":"607 Anderson Ave",
    "sg:city":"Cliffside Park",
    "sg:classifiers":[
        {
            "category":"Shopping",
            "subcategory":"Music",
            "type":"Retail Goods"
        }
    ],
    "sg:phone":"+1 201 945 6489",
    "sg:postcode":"07010",
    "sg:province":"NJ",
    "sg:tags":[
        "compact",
        "record",
        "disc",
        "tape",
        "dvd's"
    ],
    "wof:name":"Things From England",
    "wof:placetype":"venue"
},
  "geometry": {"coordinates":[-73.988297,40.825001],"type":"Point"}
}