{
  "type": "Feature",
  "properties": {
    "iso:country":"US",
    "sg:address":"9601 Atlantic Ave",
    "sg:city":"Wildwood",
    "sg:classifiers":[
        {
            "category":"Restaurant",
            "type":"Food & Drink"
        }
    ],
    "sg:phone":"+1 609 729 4600",
    "sg:postcode":"08260",
    "sg:province":"NJ",
    "wof:name":"Pizza House",
    "wof:placetype":"venue"
},
  "geometry": {"coordinates":[-74.848411,38.959052],"type":"Point"}
}