{
  "type": "Feature",
  "properties": {
    "iso:country":"US",
    "sg:address":"194 Buckelew Ave",
    "sg:city":"Monroe Township",
    "sg:classifiers":[
        {
            "category":"Restaurant",
            "type":"Food & Drink"
        }
    ],
    "sg:menulink":"http://www.allmenus.com/nj/jamesburg/32919-marias-authentic-mexican-restaurant/menu/",
    "sg:phone":"+1 732 656 9722",
    "sg:postcode":"08831",
    "sg:province":"NJ",
    "sg:tags":[
        "mexican"
    ],
    "wof:name":"Maria's Authentic Mexican Restaurant",
    "wof:placetype":"venue"
},
  "geometry": {"coordinates":[-74.432546,40.346594],"type":"Point"}
}