{
  "type": "Feature",
  "properties": {
    "addr:full":"14 Harvest Ct Jackson NJ 08527",
    "addr:housenumber":"14",
    "addr:postcode":"08527",
    "addr:street":"Harvest Ct",
    "iso:country":"US",
    "sg:address":"14 Harvest Ct",
    "sg:city":"Jackson",
    "sg:classifiers":[
        {
            "category":"Professional",
            "subcategory":"Computer Services",
            "type":"Services"
        }
    ],
    "sg:phone":"+1   ",
    "sg:postcode":"08527",
    "sg:province":"NJ",
    "sg:tags":[
        "programing",
        "custom"
    ],
    "wof:name":"Automationdevelopers Co",
    "wof:placetype":"venue"
},
  "geometry": {"coordinates":[-74.260501,40.126596],"type":"Point"}
}