{
  "type": "Feature",
  "properties": {
    "addr:full":"58 Crestview Dr Willingboro NJ 08046",
    "addr:housenumber":"58",
    "addr:postcode":"08046",
    "addr:street":"Crestview Dr",
    "iso:country":"US",
    "sg:address":"58 Crestview Dr",
    "sg:city":"Willingboro",
    "sg:classifiers":[
        {
            "category":"Social Services",
            "type":"Services"
        }
    ],
    "sg:phone":"+1   ",
    "sg:postcode":"08046",
    "sg:province":"NJ",
    "wof:name":"E & L Caring Agency Inc",
    "wof:placetype":"venue"
},
  "geometry": {"coordinates":[-74.89211299999999,40.017056],"type":"Point"}
}