{
  "type": "Feature",
  "properties": {
    "addr:full":"0 State Rte 208 Fair Lawn NJ 07410",
    "addr:housenumber":"0",
    "addr:postcode":"07410",
    "addr:street":"State Rte 208",
    "iso:country":"US",
    "sg:address":"0 State Rte 208",
    "sg:city":"Fair Lawn",
    "sg:classifiers":[
        {
            "category":"Professional",
            "type":"Services"
        },
        {
            "category":"Manufacturing",
            "subcategory":"Tools & Machinery",
            "type":"Manufacturing & Wholesale Goods"
        }
    ],
    "sg:phone":"+1 201 796 7770",
    "sg:postcode":"07410",
    "sg:province":"NJ",
    "sg:tags":[
        "manufacture",
        "establishment",
        "software"
    ],
    "wof:name":"Connectiva Systems Inc",
    "wof:placetype":"venue"
},
  "geometry": {"coordinates":[-74.132098,40.945156],"type":"Point"}
}