{
  "type": "Feature",
  "properties": {
    "addr:full":"158 Wyoming Ave Audubon NJ 08106",
    "addr:housenumber":"158",
    "addr:postcode":"08106",
    "addr:street":"Wyoming Ave",
    "iso:country":"US",
    "sg:address":"158 Wyoming Ave",
    "sg:city":"Audubon",
    "sg:classifiers":[
        {
            "category":"Retail",
            "subcategory":"Portrait Studio",
            "type":"Services"
        }
    ],
    "sg:phone":"+1   ",
    "sg:postcode":"08106",
    "sg:province":"NJ",
    "sg:tags":[
        "photo"
    ],
    "wof:name":"Walsh Robert A Photography",
    "wof:placetype":"venue"
},
  "geometry": {"coordinates":[-75.074172,39.889995],"type":"Point"}
}