{
  "type": "Feature",
  "properties": {
    "addr:full":"6 Hillcrest Ave Mendham NJ 07945",
    "addr:housenumber":"6",
    "addr:postcode":"07945",
    "addr:street":"Hillcrest Ave",
    "iso:country":"US",
    "sg:address":"6 Hillcrest Ave",
    "sg:city":"Mendham",
    "sg:classifiers":[
        {
            "category":"Building & Trades",
            "subcategory":"Construction",
            "type":"Services"
        }
    ],
    "sg:phone":"+1 973 543 7558",
    "sg:postcode":"07945",
    "sg:province":"NJ",
    "sg:tags":[
        "contractor"
    ],
    "wof:name":"ARK Enterprises Inc",
    "wof:placetype":"venue"
},
  "geometry": {"coordinates":[-74.596802,40.779267],"type":"Point"}
}