{
  "type": "Feature",
  "properties": {
    "addr:full":"6 Baldwin Ave South Bound Brook NJ 08880",
    "addr:housenumber":"6",
    "addr:postcode":"08880",
    "addr:street":"Baldwin Ave",
    "iso:country":"US",
    "sg:address":"6 Baldwin Ave",
    "sg:city":"South Bound Brook",
    "sg:classifiers":[
        {
            "category":"Professional",
            "type":"Services"
        }
    ],
    "sg:phone":"+1   ",
    "sg:postcode":"08880",
    "sg:province":"NJ",
    "wof:name":"Robert E Cann",
    "wof:placetype":"venue"
},
  "geometry": {"coordinates":[-74.52452599999999,40.549952],"type":"Point"}
}