{
  "type": "Feature",
  "properties": {
    "iso:country":"US",
    "sg:address":"10 Paterson St",
    "sg:city":"Jersey City",
    "sg:classifiers":[
        {
            "category":"Health Services",
            "subcategory":"Clinic",
            "type":"Services"
        }
    ],
    "sg:phone":"+1 201 656 6120",
    "sg:postcode":"07307",
    "sg:province":"NJ",
    "sg:tags":[
        "counseling",
        "testing"
    ],
    "wof:name":"First Chice Wman Reasearch Ctr",
    "wof:placetype":"venue"
},
  "geometry": {"coordinates":[-74.047747,40.750898],"type":"Point"}
}