{
  "type": "Feature",
  "properties": {
    "iso:country":"US",
    "sg:address":"3373 Bargaintown Rd",
    "sg:city":"Egg Harbor Twp",
    "sg:classifiers":[
        {
            "category":"Restaurant",
            "type":"Food & Drink"
        }
    ],
    "sg:phone":"+1 609 927 5777",
    "sg:postcode":"08234",
    "sg:province":"NJ",
    "sg:website":"www.cousinscountryhouse.com",
    "wof:name":"Cousin's Country House",
    "wof:placetype":"venue"
},
  "geometry": {"coordinates":[-74.581873,39.370262],"type":"Point"}
}