{
  "type": "Feature",
  "properties": {
    "iso:country":"US",
    "sg:address":"321 E State Rt 4",
    "sg:city":"Paramus",
    "sg:classifiers":[
        {
            "category":"Shopping",
            "subcategory":"Jewelry",
            "type":"Retail Goods"
        }
    ],
    "sg:phone":"+1 201 489 3984",
    "sg:postcode":"07652",
    "sg:province":"NJ",
    "wof:name":"La Mirage Jewelers",
    "wof:placetype":"venue"
},
  "geometry": {"coordinates":[-74.046656,40.914036],"type":"Point"}
}