{
  "type": "Feature",
  "properties": {
    "addr:full":"37 Haines Rd Stockton NJ 08559",
    "addr:housenumber":"37",
    "addr:postcode":"08559",
    "addr:street":"Haines Rd",
    "iso:country":"US",
    "sg:address":"37 Haines Rd",
    "sg:city":"Stockton",
    "sg:classifiers":[
        {
            "category":"Professional",
            "subcategory":"Art Services",
            "type":"Services"
        }
    ],
    "sg:phone":"+1 609 397 2716",
    "sg:postcode":"08559",
    "sg:province":"NJ",
    "sg:tags":[
        "commercial",
        "design"
    ],
    "wof:name":"Sands Creative Studios Inc",
    "wof:placetype":"venue"
},
  "geometry": {"coordinates":[-74.899756,40.442455],"type":"Point"}
}