{
  "type": "Feature",
  "properties": {
    "iso:country":"US",
    "sg:address":"640 White Horse Pike",
    "sg:city":"Hammonton",
    "sg:classifiers":[
        {
            "category":"Health Services",
            "subcategory":"Doctor",
            "type":"Services"
        }
    ],
    "sg:phone":"+1 609 567 9003",
    "sg:postcode":"08037",
    "sg:province":"NJ",
    "sg:tags":[
        "physician",
        "surgeon"
    ],
    "wof:name":"Visiting Physician Assoc",
    "wof:placetype":"venue"
},
  "geometry": {"coordinates":[-74.771826,39.629253],"type":"Point"}
}