{
  "type": "Feature",
  "properties": {
    "iso:country":"US",
    "sg:address":"629 Berlin Cross Keys Rd",
    "sg:city":"Sicklerville",
    "sg:classifiers":[
        {
            "category":"Building & Trades",
            "subcategory":"Plumbing",
            "type":"Services"
        }
    ],
    "sg:phone":"+1 856 728 7273",
    "sg:postcode":"08081",
    "sg:province":"NJ",
    "sg:tags":[
        "septic"
    ],
    "wof:name":"Albert Brewin Septic Svc",
    "wof:placetype":"venue"
},
  "geometry": {"coordinates":[-75.01012900000001,39.730979],"type":"Point"}
}