{
  "type": "Feature",
  "properties": {
    "addr:full":"301 S Pitney Rd Absecon NJ 08205",
    "addr:housenumber":"301",
    "addr:postcode":"08205",
    "addr:street":"S Pitney Rd",
    "iso:country":"US",
    "sg:address":"301 S Pitney Rd",
    "sg:city":"Absecon",
    "sg:classifiers":[
        {
            "category":"Building & Trades",
            "subcategory":"Construction",
            "type":"Services"
        }
    ],
    "sg:phone":"+1 609 652 2779",
    "sg:postcode":"08205",
    "sg:province":"NJ",
    "sg:tags":[
        "concrete",
        "contractor"
    ],
    "wof:name":"Bruno Concrete Contractors",
    "wof:placetype":"venue"
},
  "geometry": {"coordinates":[-74.494041,39.463291],"type":"Point"}
}