{
  "type": "Feature",
  "properties": {
    "iso:country":"US",
    "sg:address":"421 S Route 73",
    "sg:city":"Berlin",
    "sg:classifiers":[
        {
            "category":"Banks & Credit Unions",
            "subcategory":"Financial Services",
            "type":"Services"
        }
    ],
    "sg:phone":"+1 856 809 9555",
    "sg:postcode":"08009",
    "sg:province":"NJ",
    "sg:tags":[
        "broker",
        "mortgage"
    ],
    "wof:name":"S L M Financial Corp",
    "wof:placetype":"venue"
},
  "geometry": {"coordinates":[-74.921204,39.7943],"type":"Point"}
}