{
  "type": "Feature",
  "properties": {
    "iso:country":"US",
    "sg:address":"7406 Ventnor Ave",
    "sg:city":"Margate City",
    "sg:classifiers":[
        {
            "category":"Manufacturing",
            "subcategory":"Apparel",
            "type":"Manufacturing & Wholesale Goods"
        }
    ],
    "sg:phone":"+1 609 822 6165",
    "sg:postcode":"08402",
    "sg:province":"NJ",
    "wof:name":"Shore Embroidery & Monograming",
    "wof:placetype":"venue"
},
  "geometry": {"coordinates":[-74.49378,39.332558],"type":"Point"}
}