{
  "type": "Feature",
  "properties": {
    "iso:country":"US",
    "sg:address":"188 Jefferson St",
    "sg:city":"Newark",
    "sg:classifiers":[
        {
            "category":"Professional",
            "subcategory":"Business Services",
            "type":"Services"
        }
    ],
    "sg:phone":"+1 973 817 9001",
    "sg:postcode":"07105",
    "sg:province":"NJ",
    "sg:tags":[
        "delivery",
        "courier"
    ],
    "sg:website":"www.gopostalctr.com",
    "wof:name":"Postal Center",
    "wof:placetype":"venue"
},
  "geometry": {"coordinates":[-74.16419999999999,40.726101],"type":"Point"}
}