{
  "type": "Feature",
  "properties": {
    "iso:country":"US",
    "sg:address":"1317 8th Ave",
    "sg:city":"Neptune",
    "sg:classifiers":[
        {
            "category":"Food & Beverages",
            "subcategory":"Groceries & Convenience Stores",
            "type":"Retail Goods"
        }
    ],
    "sg:phone":"+1   ",
    "sg:postcode":"07753",
    "sg:province":"NJ",
    "wof:name":"Victorias Deli Inc",
    "wof:placetype":"venue"
},
  "geometry": {"coordinates":[-74.025721,40.206501],"type":"Point"}
}