{
  "type": "Feature",
  "properties": {
    "addr:full":"1064 Long Beach Blvd Beach Haven NJ 08008",
    "addr:housenumber":"1064",
    "addr:postcode":"08008",
    "addr:street":"Long Beach Blvd",
    "iso:country":"US",
    "sg:address":"1064 Long Beach Blvd",
    "sg:city":"Beach Haven",
    "sg:classifiers":[
        {
            "category":"Professional",
            "subcategory":"Management & Consulting",
            "type":"Services"
        }
    ],
    "sg:phone":"+1   ",
    "sg:postcode":"08008",
    "sg:province":"NJ",
    "sg:tags":[
        "business"
    ],
    "wof:name":"Frank E Pannone Consulting ARC",
    "wof:placetype":"venue"
},
  "geometry": {"coordinates":[-74.235406,39.570343],"type":"Point"}
}