{
  "type": "Feature",
  "properties": {
    "addr:full":"188 Bloomfield Ave Newark NJ 07104",
    "addr:housenumber":"188",
    "addr:postcode":"07104",
    "addr:street":"Bloomfield Ave",
    "iso:country":"US",
    "sg:address":"188 Bloomfield Ave",
    "sg:city":"Newark",
    "sg:classifiers":[
        {
            "category":"Food & Beverages",
            "subcategory":"Groceries & Convenience Stores",
            "type":"Retail Goods"
        }
    ],
    "sg:phone":"+1 973 482 2147",
    "sg:postcode":"07104",
    "sg:province":"NJ",
    "wof:name":"Bloomfield Deli",
    "wof:placetype":"venue"
},
  "geometry": {"coordinates":[-74.176498,40.760399],"type":"Point"}
}