{
  "type": "Feature",
  "properties": {
    "addr:full":"610 Pompton Ave Cedar Grove NJ 07009",
    "addr:housenumber":"610",
    "addr:postcode":"07009",
    "addr:street":"Pompton Ave",
    "iso:country":"US",
    "sg:address":"610 Pompton Ave",
    "sg:city":"Cedar Grove",
    "sg:classifiers":[
        {
            "category":"Professional",
            "subcategory":"Lawyer & Legal Services",
            "type":"Services"
        }
    ],
    "sg:phone":"+1 973 239 7675",
    "sg:postcode":"07009",
    "sg:province":"NJ",
    "wof:name":"Librizzi Victor Jr Attorney",
    "wof:placetype":"venue"
},
  "geometry": {"coordinates":[-74.229797,40.854599],"type":"Point"}
}