{
  "type": "Feature",
  "properties": {
    "iso:country":"US",
    "sg:address":"208 Fernwood Ave",
    "sg:city":"Edison",
    "sg:classifiers":[
        {
            "category":"Professional",
            "subcategory":"Accounting & Tax Preparation",
            "type":"Services"
        }
    ],
    "sg:phone":"+1   ",
    "sg:postcode":"08837",
    "sg:province":"NJ",
    "wof:name":"Lvmh Perfumes & Cosmetics Svcs",
    "wof:placetype":"venue"
},
  "geometry": {"coordinates":[-74.352452,40.501231],"type":"Point"}
}