{
  "type": "Feature",
  "properties": {
    "iso:country":"US",
    "sg:address":"1619 Stelton Rd",
    "sg:city":"Piscataway",
    "sg:classifiers":[
        {
            "category":"Recreation",
            "type":"Entertainment"
        }
    ],
    "sg:phone":"+1 732 572 0023",
    "sg:postcode":"08854",
    "sg:province":"NJ",
    "sg:tags":[
        "karate",
        "judo",
        "instr"
    ],
    "wof:name":"State Of The Arts Karate Inst",
    "wof:placetype":"venue"
},
  "geometry": {"coordinates":[-74.420383,40.535485],"type":"Point"}
}