{
  "type": "Feature",
  "properties": {
    "iso:country":"US",
    "sg:address":"213 State Rte 37",
    "sg:city":"Toms River",
    "sg:classifiers":[
        {
            "category":"Wholesale",
            "subcategory":"Machinery & Supplies",
            "type":"Manufacturing & Wholesale Goods"
        },
        {
            "category":"Shopping",
            "subcategory":"Beauty & Cosmetics",
            "type":"Retail Goods"
        }
    ],
    "sg:phone":"+1 732 240 3015",
    "sg:postcode":"08753",
    "sg:province":"NJ",
    "sg:tags":[
        "salon"
    ],
    "wof:name":"Nuance Retail Beauty Supplies",
    "wof:placetype":"venue"
},
  "geometry": {"coordinates":[-74.202703,39.96328],"type":"Point"}
}