{
  "type": "Feature",
  "properties": {
    "iso:country":"US",
    "sg:address":"1044 Owassa Rd",
    "sg:city":"Newton",
    "sg:classifiers":[
        {
            "category":"Professional",
            "subcategory":"Computer Services",
            "type":"Services"
        }
    ],
    "sg:phone":"+1   ",
    "sg:postcode":"07860",
    "sg:province":"NJ",
    "sg:tags":[
        "software"
    ],
    "wof:name":"Xplore Technologies LLC",
    "wof:placetype":"venue"
},
  "geometry": {"coordinates":[-74.85136199999999,41.130427],"type":"Point"}
}