{
  "type": "Feature",
  "properties": {
    "addr:full":"119 Danville Mountain Rd Great Meadows NJ 07838",
    "addr:housenumber":"119",
    "addr:postcode":"07838",
    "addr:street":"Danville Mountain Rd",
    "iso:country":"US",
    "sg:address":"119 Danville Mountain Rd",
    "sg:city":"Great Meadows",
    "sg:classifiers":[
        {
            "category":"Building & Trades",
            "subcategory":"Construction",
            "type":"Services"
        }
    ],
    "sg:phone":"+1 908 637 8823",
    "sg:postcode":"07838",
    "sg:province":"NJ",
    "sg:tags":[
        "painting",
        "contractor"
    ],
    "wof:name":"American Restoration Services",
    "wof:placetype":"venue"
},
  "geometry": {"coordinates":[-74.94685200000001,40.863572],"type":"Point"}
}