{
  "type": "Feature",
  "properties": {
    "iso:country":"US",
    "sg:address":"500 N Bay Ave",
    "sg:city":"Beach Haven",
    "sg:classifiers":[
        {
            "category":"Government",
            "subcategory":"Post Office",
            "type":"Public Place"
        }
    ],
    "sg:phone":"+1 609 494 7234",
    "sg:postcode":"08008",
    "sg:province":"NJ",
    "sg:tags":[
        "postal",
        "us"
    ],
    "wof:name":"Beach Haven Main Office",
    "wof:placetype":"venue"
},
  "geometry": {"coordinates":[-74.23761399999999,39.567128],"type":"Point"}
}