{
  "type": "Feature",
  "properties": {
    "addr:full":"1050 State Rte 35 Shrewsbury NJ 07702",
    "addr:housenumber":"1050",
    "addr:postcode":"07702",
    "addr:street":"State Rte 35",
    "iso:country":"US",
    "sg:address":"1050 State Rte 35",
    "sg:city":"Shrewsbury",
    "sg:classifiers":[
        {
            "category":"Professional",
            "subcategory":"Accounting & Tax Preparation",
            "type":"Services"
        }
    ],
    "sg:phone":"+1 732 530 7433",
    "sg:postcode":"07702",
    "sg:province":"NJ",
    "wof:name":"Quality Billing Center",
    "wof:placetype":"venue"
},
  "geometry": {"coordinates":[-74.063168,40.315334],"type":"Point"}
}