{
  "type": "Feature",
  "properties": {
    "addr:full":"669 Nassau St North Brunswick NJ 08902",
    "addr:housenumber":"669",
    "addr:postcode":"08902",
    "addr:street":"Nassau St",
    "iso:country":"US",
    "sg:address":"669 Nassau St",
    "sg:city":"North Brunswick",
    "sg:classifiers":[
        {
            "category":"Wholesale",
            "subcategory":"Office Equipment",
            "type":"Manufacturing & Wholesale Goods"
        },
        {
            "category":"Professional",
            "subcategory":"Computer Services",
            "type":"Services"
        }
    ],
    "sg:phone":"+1 732 828 2156",
    "sg:postcode":"08902",
    "sg:province":"NJ",
    "sg:tags":[
        "repair",
        "refurbishes",
        "laser",
        "duplicating",
        "photocopier",
        "machine",
        "printer",
        "copying"
    ],
    "wof:name":"Jersey Cartridge Recycling-PC",
    "wof:placetype":"venue"
},
  "geometry": {"coordinates":[-74.448414,40.472249],"type":"Point"}
}