{
  "type": "Feature",
  "properties": {
    "iso:country":"US",
    "sg:address":"185 Dutch Rd",
    "sg:city":"Marlton",
    "sg:classifiers":[
        {
            "category":"Home & Garden",
            "subcategory":"Furniture",
            "type":"Retail Goods"
        }
    ],
    "sg:phone":"+1 856 988 0137",
    "sg:postcode":"08053",
    "sg:province":"NJ",
    "sg:tags":[
        "store"
    ],
    "sg:website":"http://www.bamboovillagehawaii.org",
    "wof:name":"Bamboo Village Mfg Co",
    "wof:placetype":"venue"
},
  "geometry": {"coordinates":[-74.91449,39.85931],"type":"Point"}
}