{
  "type": "Feature",
  "properties": {
    "addr:full":"10 Unami Ln Scotch Plains NJ 07076",
    "addr:housenumber":"10",
    "addr:postcode":"07076",
    "addr:street":"Unami Ln",
    "iso:country":"US",
    "sg:address":"10 Unami Ln",
    "sg:city":"Scotch Plains",
    "sg:classifiers":[
        {
            "category":"Manufacturing",
            "subcategory":"Printing",
            "type":"Manufacturing & Wholesale Goods"
        }
    ],
    "sg:phone":"+1 908 889 0700",
    "sg:postcode":"07076",
    "sg:province":"NJ",
    "sg:tags":[
        "typesetting"
    ],
    "wof:name":"Technical Typesetter",
    "wof:placetype":"venue"
},
  "geometry": {"coordinates":[-74.364892,40.622252],"type":"Point"}
}