{
  "type": "Feature",
  "properties": {
    "addr:full":"2034 State Rte 27 Edison NJ 08817",
    "addr:housenumber":"2034",
    "addr:postcode":"08817",
    "addr:street":"State Rte 27",
    "iso:country":"US",
    "sg:address":"2034 State Rte 27",
    "sg:city":"Edison",
    "sg:classifiers":[
        {
            "category":"Autos & Motor Vehicles",
            "subcategory":"Automobile Sales",
            "type":"Retail Goods"
        }
    ],
    "sg:phone":"+1 732 287 2828",
    "sg:postcode":"08817",
    "sg:province":"NJ",
    "sg:tags":[
        "car",
        "dealer"
    ],
    "wof:name":"Volkswagen Authorized Dealer",
    "wof:placetype":"venue"
},
  "geometry": {"coordinates":[-74.388991,40.524709],"type":"Point"}
}