{
  "type": "Feature",
  "properties": {
    "addr:full":"21 Hancock Ct Basking Ridge NJ 07920",
    "addr:housenumber":"21",
    "addr:postcode":"07920",
    "addr:street":"Hancock Ct",
    "iso:country":"US",
    "sg:address":"21 Hancock Ct",
    "sg:city":"Basking Ridge",
    "sg:classifiers":[
        {
            "category":"Health Services",
            "subcategory":"Medical Lab",
            "type":"Services"
        }
    ],
    "sg:phone":"+1 908 719 9688",
    "sg:postcode":"07920",
    "sg:province":"NJ",
    "sg:tags":[
        "laboratory",
        "dental"
    ],
    "wof:name":"Dental Arts & Vision",
    "wof:placetype":"venue"
},
  "geometry": {"coordinates":[-74.613247,40.650106],"type":"Point"}
}