{
  "type": "Feature",
  "properties": {
    "iso:country":"US",
    "sg:address":"2423 State Rte 57",
    "sg:city":"Stewartsville",
    "sg:classifiers":[
        {
            "category":"Restaurant",
            "type":"Food & Drink"
        }
    ],
    "sg:phone":"+1 908 213 1889",
    "sg:postcode":"07882",
    "sg:province":"NJ",
    "sg:tags":[
        "eating"
    ],
    "wof:name":"Candy's Country Cafe",
    "wof:placetype":"venue"
},
  "geometry": {"coordinates":[-75.05334999999999,40.731429],"type":"Point"}
}