{
  "type": "Feature",
  "properties": {
    "addr:full":"447 Springfield Ave Summit NJ 07901",
    "addr:housenumber":"447",
    "addr:postcode":"07901",
    "addr:street":"Springfield Ave",
    "iso:country":"US",
    "sg:address":"447 Springfield Ave",
    "sg:city":"Summit",
    "sg:classifiers":[
        {
            "category":"Shopping",
            "subcategory":"Jewelry",
            "type":"Retail Goods"
        }
    ],
    "sg:phone":"+1 908 273 3777",
    "sg:postcode":"07901",
    "sg:province":"NJ",
    "sg:tags":[
        "repair",
        "designer"
    ],
    "wof:name":"No Problems With Henry Inc",
    "wof:placetype":"venue"
},
  "geometry": {"coordinates":[-74.361338,40.717735],"type":"Point"}
}