{
  "type": "Feature",
  "properties": {
    "addr:full":"121 Diamond Spring Rd Denville NJ 07834",
    "addr:housenumber":"121",
    "addr:postcode":"07834",
    "addr:street":"Diamond Spring Rd",
    "iso:country":"US",
    "sg:address":"121 Diamond Spring Rd",
    "sg:city":"Denville",
    "sg:classifiers":[
        {
            "category":"Education",
            "subcategory":"Library",
            "type":"Public Place"
        }
    ],
    "sg:phone":"+1 973 627 6555",
    "sg:postcode":"07834",
    "sg:province":"NJ",
    "sg:tags":[
        "executive"
    ],
    "sg:website":"www.denvillelibrary.org",
    "wof:name":"Denville Free Public Library",
    "wof:placetype":"venue"
},
  "geometry": {"coordinates":[-74.473921,40.894924],"type":"Point"}
}