{
  "type": "Feature",
  "properties": {
    "iso:country":"US",
    "sg:address":"75 Livingston Ave",
    "sg:city":"Roseland",
    "sg:classifiers":[
        {
            "category":"Professional",
            "subcategory":"Management & Consulting",
            "type":"Services"
        }
    ],
    "sg:phone":"+1 973 535 7000",
    "sg:postcode":"07068",
    "sg:province":"NJ",
    "sg:tags":[
        "consultant",
        "business"
    ],
    "sg:website":"www.cgi-ams.com",
    "wof:name":"Cgi Ams",
    "wof:placetype":"venue"
},
  "geometry": {"coordinates":[-74.30618699999999,40.813839],"type":"Point"}
}