{
  "type": "Feature",
  "properties": {
    "addr:full":"180 W High St Bound Brook NJ 08805",
    "addr:housenumber":"180",
    "addr:postcode":"08805",
    "addr:street":"W High St",
    "iso:country":"US",
    "sg:address":"180 W High St",
    "sg:city":"Bound Brook",
    "sg:classifiers":[
        {
            "category":"Building & Trades",
            "subcategory":"Construction",
            "type":"Services"
        }
    ],
    "sg:phone":"+1 732 563 0945",
    "sg:postcode":"08805",
    "sg:province":"NJ",
    "sg:tags":[
        "contractor"
    ],
    "wof:name":"Crescent Contractor",
    "wof:placetype":"venue"
},
  "geometry": {"coordinates":[-74.54070900000001,40.564563],"type":"Point"}
}