{
  "type": "Feature",
  "properties": {
    "addr:full":"443 Trinity Pl Elizabeth NJ 07201",
    "addr:housenumber":"443",
    "addr:postcode":"07201",
    "addr:street":"Trinity Pl",
    "iso:country":"US",
    "sg:address":"443 Trinity Pl",
    "sg:city":"Elizabeth",
    "sg:classifiers":[
        {
            "category":"Retail",
            "subcategory":"Auto Repair",
            "type":"Services"
        }
    ],
    "sg:phone":"+1 908 355 2006",
    "sg:postcode":"07201",
    "sg:province":"NJ",
    "sg:tags":[
        "general"
    ],
    "wof:name":"D & D Car Care",
    "wof:placetype":"venue"
},
  "geometry": {"coordinates":[-74.212979,40.671587],"type":"Point"}
}