{
  "type": "Feature",
  "properties": {
    "iso:country":"US",
    "sg:address":"1200 US Hwy 46",
    "sg:city":"Clifton",
    "sg:classifiers":[
        {
            "category":"Real Estate",
            "subcategory":"Architect",
            "type":"Services"
        }
    ],
    "sg:phone":"+1 973 472 4800",
    "sg:postcode":"07013",
    "sg:province":"NJ",
    "sg:tags":[
        "merchandise"
    ],
    "wof:name":"Eisenstein Merle H A I A",
    "wof:placetype":"venue"
},
  "geometry": {"coordinates":[-74.183958,40.869944],"type":"Point"}
}