{
  "type": "Feature",
  "properties": {
    "addr:full":"11 Bedford Ter Mantua NJ 08051",
    "addr:housenumber":"11",
    "addr:postcode":"08051",
    "addr:street":"Bedford Ter",
    "iso:country":"US",
    "sg:address":"11 Bedford Ter",
    "sg:city":"Mantua",
    "sg:classifiers":[
        {
            "category":"Professional",
            "type":"Services"
        }
    ],
    "sg:phone":"+1   ",
    "sg:postcode":"08051",
    "sg:province":"NJ",
    "wof:name":"Visions Unlimited Inc",
    "wof:placetype":"venue"
},
  "geometry": {"coordinates":[-75.17845800000001,39.802929],"type":"Point"}
}