{
  "type": "Feature",
  "properties": {
    "addr:full":"1600 Absecon Blvd Atlantic City NJ 08401",
    "addr:housenumber":"1600",
    "addr:postcode":"08401",
    "addr:street":"Absecon Blvd",
    "iso:country":"US",
    "sg:address":"1600 Absecon Blvd",
    "sg:city":"Atlantic City",
    "sg:classifiers":[
        {
            "category":"Travel",
            "subcategory":"Hotels & Motels",
            "type":"Entertainment"
        }
    ],
    "sg:phone":"+1 609 344 1975",
    "sg:postcode":"08401",
    "sg:province":"NJ",
    "wof:name":"Sunset Inn Of America-Marina",
    "wof:placetype":"venue"
},
  "geometry": {"coordinates":[-74.449398,39.376484],"type":"Point"}
}