{
  "type": "Feature",
  "properties": {
    "addr:full":"9100 Tonnelle Ave North Bergen NJ 07047",
    "addr:postcode":"9100;07047",
    "addr:street":"Tonnelle Ave",
    "iso:country":"US",
    "sg:address":"9100 Tonnelle Ave",
    "sg:city":"North Bergen",
    "sg:classifiers":[
        {
            "category":"Building & Trades",
            "subcategory":"Locksmith",
            "type":"Services"
        }
    ],
    "sg:phone":"+1 201 520 1276",
    "sg:postcode":"07047",
    "sg:province":"NJ",
    "sg:tags":[
        "key"
    ],
    "wof:name":"Locksmith",
    "wof:placetype":"venue"
},
  "geometry": {"coordinates":[-74.010327,40.813457],"type":"Point"}
}