{
  "type": "Feature",
  "properties": {
    "addr:full":"610 Hessian Ave National Park NJ 08063",
    "addr:housenumber":"610",
    "addr:postcode":"08063",
    "addr:street":"Hessian Ave",
    "iso:country":"US",
    "sg:address":"610 Hessian Ave",
    "sg:city":"National Park",
    "sg:classifiers":[
        {
            "category":"Restaurant",
            "type":"Food & Drink"
        }
    ],
    "sg:phone":"+1   ",
    "sg:postcode":"08063",
    "sg:province":"NJ",
    "sg:tags":[
        "drinking",
        "eating"
    ],
    "wof:name":"CJ Tavern",
    "wof:placetype":"venue"
},
  "geometry": {"coordinates":[-75.17824,39.865413],"type":"Point"}
}