{
  "type": "Feature",
  "properties": {
    "iso:country":"US",
    "sg:address":"250 Maple Ave",
    "sg:city":"Red Bank",
    "sg:classifiers":[
        {
            "category":"Health Services",
            "subcategory":"Doctor",
            "type":"Services"
        }
    ],
    "sg:phone":"+1 732 741 0022",
    "sg:postcode":"07701",
    "sg:province":"NJ",
    "sg:tags":[
        "dentist"
    ],
    "wof:name":"Studio For Cosmetic Dentistry",
    "wof:placetype":"venue"
},
  "geometry": {"coordinates":[-74.06785000000001,40.342988],"type":"Point"}
}