{
  "type": "Feature",
  "properties": {
    "addr:full":"115 Mechanic St Cape May Court House NJ 08210",
    "addr:housenumber":"115",
    "addr:postcode":"08210",
    "addr:street":"Mechanic St",
    "iso:country":"US",
    "sg:address":"115 Mechanic St",
    "sg:city":"Cape May Court House",
    "sg:classifiers":[
        {
            "category":"Building & Trades",
            "subcategory":"Construction",
            "type":"Services"
        }
    ],
    "sg:phone":"+1 609 463 6870",
    "sg:postcode":"08210",
    "sg:province":"NJ",
    "sg:tags":[
        "contractor"
    ],
    "wof:name":"Art Anderson Inc",
    "wof:placetype":"venue"
},
  "geometry": {"coordinates":[-74.82631499999999,39.083263],"type":"Point"}
}