{
  "type": "Feature",
  "properties": {
    "iso:country":"US",
    "sg:address":"763 White Horse Pike",
    "sg:city":"Atco",
    "sg:classifiers":[
        {
            "category":"Restaurant",
            "type":"Food & Drink"
        }
    ],
    "sg:phone":"+1   ",
    "sg:postcode":"08004",
    "sg:province":"NJ",
    "sg:tags":[
        "eating"
    ],
    "wof:name":"Maplewood Iv",
    "wof:placetype":"venue"
},
  "geometry": {"coordinates":[-74.879214,39.74754],"type":"Point"}
}