{
  "type": "Feature",
  "properties": {
    "addr:full":"173 Davis Ave Mount Ephraim NJ 08059",
    "addr:housenumber":"173",
    "addr:postcode":"08059",
    "addr:street":"Davis Ave",
    "iso:country":"US",
    "sg:address":"173 Davis Ave",
    "sg:city":"Mount Ephraim",
    "sg:classifiers":[
        {
            "category":"Arts & Performance",
            "subcategory":"Theater",
            "type":"Entertainment"
        }
    ],
    "sg:phone":"+1 856 931 5446",
    "sg:postcode":"08059",
    "sg:province":"NJ",
    "sg:tags":[
        "dj",
        "live",
        "music",
        "group"
    ],
    "wof:name":"Marky D's Disc Jockey",
    "wof:placetype":"venue"
},
  "geometry": {"coordinates":[-75.089457,39.878671],"type":"Point"}
}