{
  "type": "Feature",
  "properties": {
    "addr:full":"96 Us Highway 9 Englishtown NJ 07726",
    "addr:housenumber":"96",
    "addr:postcode":"07726",
    "addr:street":"Us Highway 9",
    "iso:country":"US",
    "sg:address":"96 Us Highway 9",
    "sg:city":"Englishtown",
    "sg:classifiers":[
        {
            "category":"Deli",
            "type":"Food & Drink"
        }
    ],
    "sg:menulink":"http://www.allmenus.com/nj/manalapan/30409-jerry--harveys/menu/",
    "sg:phone":"+1 732 972 1122",
    "sg:postcode":"07726",
    "sg:province":"NJ",
    "sg:tags":[
        "american"
    ],
    "wof:name":"Jerry & Harvey's",
    "wof:placetype":"venue"
},
  "geometry": {"coordinates":[-74.304095,40.299084],"type":"Point"}
}