{
  "type": "Feature",
  "properties": {
    "iso:country":"US",
    "sg:address":"45 Tobago Ave",
    "sg:city":"Toms River",
    "sg:classifiers":[
        {
            "category":"Real Estate",
            "subcategory":"Developer",
            "type":"Services"
        }
    ],
    "sg:phone":"+1   ",
    "sg:postcode":"08753",
    "sg:province":"NJ",
    "wof:name":"Residential Development Inc",
    "wof:placetype":"venue"
},
  "geometry": {"coordinates":[-74.12185599999999,39.9619],"type":"Point"}
}