{
  "type": "Feature",
  "properties": {
    "addr:full":"2 Deer Hill Dr Montville NJ 07045",
    "addr:housenumber":"2",
    "addr:postcode":"07045",
    "addr:street":"Deer Hill Dr",
    "iso:country":"US",
    "sg:address":"2 Deer Hill Dr",
    "sg:city":"Montville",
    "sg:classifiers":[
        {
            "category":"Building & Trades",
            "subcategory":"Electrical",
            "type":"Services"
        }
    ],
    "sg:phone":"+1 973 316 1157",
    "sg:postcode":"07045",
    "sg:province":"NJ",
    "sg:tags":[
        "electrical",
        "contractor"
    ],
    "wof:name":"Traditional Electric LLC",
    "wof:placetype":"venue"
},
  "geometry": {"coordinates":[-74.351214,40.895167],"type":"Point"}
}