{
  "type": "Feature",
  "properties": {
    "addr:full":"183 Hollywood Ave Fairfield NJ 07004",
    "addr:housenumber":"183",
    "addr:postcode":"07004",
    "addr:street":"Hollywood Ave",
    "iso:country":"US",
    "sg:address":"183 Hollywood Ave",
    "sg:city":"Fairfield",
    "sg:classifiers":[
        {
            "category":"Retail",
            "subcategory":"Auto Repair",
            "type":"Services"
        }
    ],
    "sg:phone":"+1 973 227 0919",
    "sg:postcode":"07004",
    "sg:province":"NJ",
    "sg:tags":[
        "general"
    ],
    "wof:name":"Biancos Inc",
    "wof:placetype":"venue"
},
  "geometry": {"coordinates":[-74.30513000000001,40.884914],"type":"Point"}
}