{
  "type": "Feature",
  "properties": {
    "iso:country":"US",
    "sg:address":"80 Bloomfield Ave",
    "sg:city":"Verona",
    "sg:classifiers":[
        {
            "category":"Health Services",
            "subcategory":"Doctor",
            "type":"Services"
        }
    ],
    "sg:phone":"+1 973 857 7455",
    "sg:postcode":"07044",
    "sg:province":"NJ",
    "sg:tags":[
        "medical"
    ],
    "wof:name":"Cynthia Prestigiacomo",
    "wof:placetype":"venue"
},
  "geometry": {"coordinates":[-74.229946,40.825229],"type":"Point"}
}