{
  "type": "Feature",
  "properties": {
    "addr:full":"1100 Raymond Blvd Newark NJ 07102",
    "addr:housenumber":"1100",
    "addr:postcode":"07102",
    "addr:street":"Raymond Blvd",
    "iso:country":"US",
    "sg:address":"1100 Raymond Blvd",
    "sg:city":"Newark",
    "sg:classifiers":[
        {
            "category":"Government",
            "subcategory":"Office",
            "type":"Public Place"
        }
    ],
    "sg:phone":"+1 973 648 2058",
    "sg:postcode":"07102",
    "sg:province":"NJ",
    "wof:name":"Electrical Contractors Board",
    "wof:placetype":"venue"
},
  "geometry": {"coordinates":[-74.167558,40.736346],"type":"Point"}
}