{
  "type": "Feature",
  "properties": {
    "iso:country":"US",
    "sg:address":"37 Clinton Ave",
    "sg:city":"Budd Lake",
    "sg:classifiers":[
        {
            "category":"Professional",
            "subcategory":"Advertising",
            "type":"Services"
        }
    ],
    "sg:phone":"+1 973 448 0234",
    "sg:postcode":"07828",
    "sg:province":"NJ",
    "wof:name":"MOMSBARGIANBASEMENT.COM",
    "wof:placetype":"venue"
},
  "geometry": {"coordinates":[-74.72775300000001,40.867948],"type":"Point"}
}