{
  "type": "Feature",
  "properties": {
    "iso:country":"US",
    "sg:address":"137 Bloomfield Ave",
    "sg:city":"Newark",
    "sg:classifiers":[
        {
            "category":"Insurance",
            "subcategory":"Health Insurance",
            "type":"Services"
        }
    ],
    "sg:phone":"+1 973 484 2278",
    "sg:postcode":"07104",
    "sg:province":"NJ",
    "sg:tags":[
        "market"
    ],
    "wof:name":"All Natural Vitamins Health & Beauty Products",
    "wof:placetype":"venue"
},
  "geometry": {"coordinates":[-74.174896,40.7579],"type":"Point"}
}