{
  "type": "Feature",
  "properties": {
    "addr:full":"1 Ethel Ave Hawthorne NJ 07506",
    "addr:housenumber":"1",
    "addr:postcode":"07506",
    "addr:street":"Ethel Ave",
    "iso:country":"US",
    "sg:address":"1 Ethel Ave",
    "sg:city":"Hawthorne",
    "sg:classifiers":[
        {
            "category":"Building & Trades",
            "subcategory":"Construction",
            "type":"Services"
        }
    ],
    "sg:phone":"+1   ",
    "sg:postcode":"07506",
    "sg:province":"NJ",
    "sg:tags":[
        "business",
        "contractor"
    ],
    "wof:name":"Blue Sparkle Pools",
    "wof:placetype":"venue"
},
  "geometry": {"coordinates":[-74.15378699999999,40.962218],"type":"Point"}
}