{
  "type": "Feature",
  "properties": {
    "addr:full":"600 Mule Rd Toms River NJ 08757",
    "addr:housenumber":"600",
    "addr:postcode":"08757",
    "addr:street":"Mule Rd",
    "iso:country":"US",
    "sg:address":"600 Mule Rd",
    "sg:city":"Toms River",
    "sg:classifiers":[
        {
            "category":"Professional",
            "subcategory":"Lawyer & Legal Services",
            "type":"Services"
        }
    ],
    "sg:phone":"+1 732 240 7530",
    "sg:postcode":"08757",
    "sg:province":"NJ",
    "sg:tags":[
        "attorney"
    ],
    "wof:name":"Janet M Richter",
    "wof:placetype":"venue"
},
  "geometry": {"coordinates":[-74.246388,39.955783],"type":"Point"}
}