{
  "type": "Feature",
  "properties": {
    "addr:full":"5045 US Hwy 130 Delran NJ 08075",
    "addr:housenumber":"5045",
    "addr:postcode":"08075",
    "addr:street":"Us Hwy 130",
    "iso:country":"US",
    "sg:address":"5045 US Hwy 130",
    "sg:city":"Delran",
    "sg:classifiers":[
        {
            "category":"Health Services",
            "subcategory":"Doctor",
            "type":"Services"
        }
    ],
    "sg:phone":"+1 856 764 1002",
    "sg:postcode":"08075",
    "sg:province":"NJ",
    "sg:tags":[
        "physician",
        "surgeon"
    ],
    "wof:name":"Radiology Associates",
    "wof:placetype":"venue"
},
  "geometry": {"coordinates":[-74.954728,40.015806],"type":"Point"}
}