{
  "type": "Feature",
  "properties": {
    "iso:country":"US",
    "sg:address":"11 Bennetts Ln",
    "sg:city":"Somerset",
    "sg:classifiers":[
        {
            "category":"Health Services",
            "subcategory":"Doctor",
            "type":"Services"
        }
    ],
    "sg:phone":"+1 732 828 8777",
    "sg:postcode":"08873",
    "sg:province":"NJ",
    "sg:tags":[
        "medical"
    ],
    "wof:name":"Vatsala Rao MD",
    "wof:placetype":"venue"
},
  "geometry": {"coordinates":[-74.50016599999999,40.473083],"type":"Point"}
}