{
  "type": "Feature",
  "properties": {
    "addr:full":"420 Broadway Bayonne NJ 07002",
    "addr:housenumber":"420",
    "addr:postcode":"07002",
    "addr:street":"Broadway",
    "iso:country":"US",
    "sg:address":"420 Broadway",
    "sg:city":"Bayonne",
    "sg:classifiers":[
        {
            "category":"Professional",
            "subcategory":"Lawyer & Legal Services",
            "type":"Services"
        }
    ],
    "sg:phone":"+1 201 858 2109",
    "sg:postcode":"07002",
    "sg:province":"NJ",
    "wof:name":"John F Coffey II",
    "wof:placetype":"venue"
},
  "geometry": {"coordinates":[-74.119917,40.661974],"type":"Point"}
}