{
  "type": "Feature",
  "properties": {
    "addr:full":"37 Commonwealth Blvd Lakehurst NJ 08759",
    "addr:housenumber":"37",
    "addr:postcode":"08759",
    "addr:street":"Commonwealth Blvd",
    "iso:country":"US",
    "sg:address":"37 Commonwealth Blvd",
    "sg:city":"Lakehurst",
    "sg:classifiers":[
        {
            "category":"Food & Beverages",
            "subcategory":"Groceries & Convenience Stores",
            "type":"Retail Goods"
        }
    ],
    "sg:phone":"+1   ",
    "sg:postcode":"08759",
    "sg:province":"NJ",
    "sg:tags":[
        "supermarket"
    ],
    "wof:name":"Wawa",
    "wof:placetype":"venue"
},
  "geometry": {"coordinates":[-74.279036,39.996866],"type":"Point"}
}