{
  "type": "Feature",
  "properties": {
    "addr:full":"203 Passaic Ave Passaic NJ 07055",
    "addr:housenumber":"203",
    "addr:postcode":"07055",
    "addr:street":"Passaic Ave",
    "iso:country":"US",
    "sg:address":"203 Passaic Ave",
    "sg:city":"Passaic",
    "sg:classifiers":[
        {
            "category":"Health Services",
            "subcategory":"Doctor",
            "type":"Services"
        }
    ],
    "sg:phone":"+1 973 246 6999",
    "sg:postcode":"07055",
    "sg:province":"NJ",
    "wof:name":"Dr Milinda Carson MD",
    "wof:placetype":"venue"
},
  "geometry": {"coordinates":[-74.131162,40.853667],"type":"Point"}
}