{
  "type": "Feature",
  "properties": {
    "addr:full":"160 Summit St Englewood NJ 07631",
    "addr:housenumber":"160",
    "addr:postcode":"07631",
    "addr:street":"Summit St",
    "iso:country":"US",
    "sg:address":"160 Summit St",
    "sg:city":"Englewood",
    "sg:classifiers":[
        {
            "category":"Wholesale",
            "subcategory":"Machinery & Supplies",
            "type":"Manufacturing & Wholesale Goods"
        }
    ],
    "sg:phone":"+1 201 894 0064",
    "sg:postcode":"07631",
    "sg:province":"NJ",
    "sg:tags":[
        "industrial"
    ],
    "wof:name":"Sabtex NY Ltd",
    "wof:placetype":"venue"
},
  "geometry": {"coordinates":[-73.96028099999999,40.8778],"type":"Point"}
}