{
  "type": "Feature",
  "properties": {
    "iso:country":"US",
    "sg:address":"17 Embroidery St",
    "sg:city":"Sayreville",
    "sg:classifiers":[
        {
            "category":"Building & Trades",
            "subcategory":"Construction",
            "type":"Services"
        }
    ],
    "sg:phone":"+1 732 586 0650",
    "sg:postcode":"08872",
    "sg:province":"NJ",
    "sg:tags":[
        "concrete",
        "contractor"
    ],
    "wof:name":"D K Concrete & Masonry",
    "wof:placetype":"venue"
},
  "geometry": {"coordinates":[-74.35561199999999,40.457674],"type":"Point"}
}