{
  "type": "Feature",
  "properties": {
    "addr:full":"111 Pavonia Ave Jersey City NJ 07310",
    "addr:housenumber":"111",
    "addr:postcode":"07310",
    "addr:street":"Pavonia Ave",
    "iso:country":"US",
    "sg:address":"111 Pavonia Ave",
    "sg:city":"Jersey City",
    "sg:classifiers":[
        {
            "category":"Utilities",
            "subcategory":"Mobile Phone",
            "type":"Services"
        }
    ],
    "sg:phone":"+1 201 386 1000",
    "sg:postcode":"07310",
    "sg:province":"NJ",
    "sg:tags":[
        "telephone",
        "cellular"
    ],
    "wof:name":"Saturn Wireless",
    "wof:placetype":"venue"
},
  "geometry": {"coordinates":[-74.03402,40.726516],"type":"Point"}
}