{
  "type": "Feature",
  "properties": {
    "iso:country":"US",
    "sg:address":"27 Orange Pl",
    "sg:city":"West Orange",
    "sg:classifiers":[
        {
            "category":"Building & Trades",
            "subcategory":"Electrical",
            "type":"Services"
        }
    ],
    "sg:phone":"+1 973 731 8998",
    "sg:postcode":"07052",
    "sg:province":"NJ",
    "sg:tags":[
        "electrical",
        "contractor"
    ],
    "wof:name":"E Scott Gaipa",
    "wof:placetype":"venue"
},
  "geometry": {"coordinates":[-74.231306,40.792975],"type":"Point"}
}