{
  "type": "Feature",
  "properties": {
    "addr:full":"1022 Tuckahoe Rd Newfield NJ 08344",
    "addr:housenumber":"1022",
    "addr:postcode":"08344",
    "addr:street":"Tuckahoe Rd",
    "iso:country":"US",
    "sg:address":"1022 Tuckahoe Rd",
    "sg:city":"Newfield",
    "sg:classifiers":[
        {
            "category":"Organizations",
            "subcategory":"Religious Organization",
            "type":"Services"
        }
    ],
    "sg:phone":"+1 856 507 9756",
    "sg:postcode":"08344",
    "sg:province":"NJ",
    "sg:tags":[
        "church"
    ],
    "wof:name":"Christian Church",
    "wof:placetype":"venue"
},
  "geometry": {"coordinates":[-74.972525,39.561617],"type":"Point"}
}