{
  "type": "Feature",
  "properties": {
    "addr:full":"302 Eastern Blvd Bayville NJ 08721",
    "addr:housenumber":"302",
    "addr:postcode":"08721",
    "addr:street":"Eastern Blvd",
    "iso:country":"US",
    "sg:address":"302 Eastern Blvd",
    "sg:city":"Bayville",
    "sg:classifiers":[
        {
            "category":"Building & Trades",
            "subcategory":"Construction",
            "type":"Services"
        }
    ],
    "sg:phone":"+1 732 237 2080",
    "sg:postcode":"08721",
    "sg:province":"NJ",
    "sg:tags":[
        "contractor"
    ],
    "wof:name":"Starlite Ceilings",
    "wof:placetype":"venue"
},
  "geometry": {"coordinates":[-74.181248,39.904446],"type":"Point"}
}