{
  "type": "Feature",
  "properties": {
    "iso:country":"US",
    "sg:address":"43 Spring St",
    "sg:city":"Ramsey",
    "sg:classifiers":[
        {
            "category":"Real Estate",
            "subcategory":"Surveying",
            "type":"Services"
        }
    ],
    "sg:phone":"+1 201 236 0385",
    "sg:postcode":"07446",
    "sg:province":"NJ",
    "sg:tags":[
        "surveyor"
    ],
    "wof:name":"Kirch C Peter & Assoc",
    "wof:placetype":"venue"
},
  "geometry": {"coordinates":[-74.140911,41.075109],"type":"Point"}
}