{
  "type": "Feature",
  "properties": {
    "iso:country":"US",
    "sg:address":"690 S 12th St",
    "sg:city":"Newark",
    "sg:classifiers":[
        {
            "category":"Organizations",
            "subcategory":"Religious Organization",
            "type":"Services"
        }
    ],
    "sg:phone":"+1 973 642 6618",
    "sg:postcode":"07103",
    "sg:province":"NJ",
    "wof:name":"New Eden Baptist Church",
    "wof:placetype":"venue"
},
  "geometry": {"coordinates":[-74.206479,40.730464],"type":"Point"}
}