{
  "type": "Feature",
  "properties": {
    "iso:country":"US",
    "sg:address":"1545 Lamberton Rd",
    "sg:city":"Trenton",
    "sg:classifiers":[
        {
            "category":"Real Estate",
            "subcategory":"Real Estate Agent",
            "type":"Services"
        }
    ],
    "sg:phone":"+1 609 882 3737",
    "sg:postcode":"08611",
    "sg:province":"NJ",
    "sg:website":"www.segalinc.com",
    "wof:name":"Segal Commercial Real Estate",
    "wof:placetype":"venue"
},
  "geometry": {"coordinates":[-74.750454,40.185413],"type":"Point"}
}