{
  "type": "Feature",
  "properties": {
    "addr:full":"4005 Crawford Ct Bridgewater NJ 08807",
    "addr:housenumber":"4005",
    "addr:postcode":"08807",
    "addr:street":"Crawford Ct",
    "iso:country":"US",
    "sg:address":"4005 Crawford Ct",
    "sg:city":"Bridgewater",
    "sg:classifiers":[
        {
            "category":"Personal",
            "type":"Services"
        }
    ],
    "sg:phone":"+1   ",
    "sg:postcode":"08807",
    "sg:province":"NJ",
    "wof:name":"Delnero Fith Massage Therapist",
    "wof:placetype":"venue"
},
  "geometry": {"coordinates":[-74.668598,40.578066],"type":"Point"}
}