{
  "type": "Feature",
  "properties": {
    "addr:full":"201 Grove Rd Thorofare NJ 08086",
    "addr:housenumber":"201",
    "addr:postcode":"08086",
    "addr:street":"Grove Rd",
    "iso:country":"US",
    "sg:address":"201 Grove Rd",
    "sg:city":"Thorofare",
    "sg:classifiers":[
        {
            "category":"Professional",
            "subcategory":"Accounting & Tax Preparation",
            "type":"Services"
        }
    ],
    "sg:phone":"+1 856 848 2028",
    "sg:postcode":"08086",
    "sg:province":"NJ",
    "sg:tags":[
        "accountant"
    ],
    "wof:name":"Bernard Spak CPA",
    "wof:placetype":"venue"
},
  "geometry": {"coordinates":[-75.19431400000001,39.837164],"type":"Point"}
}