{
  "type": "Feature",
  "properties": {
    "addr:full":"32 Pine Ridge Dr Edison NJ 08820",
    "addr:housenumber":"32",
    "addr:postcode":"08820",
    "addr:street":"Pine Ridge Dr",
    "iso:country":"US",
    "sg:address":"32 Pine Ridge Dr",
    "sg:city":"Edison",
    "sg:classifiers":[
        {
            "category":"Shopping",
            "subcategory":"Catalog Store",
            "type":"Retail Goods"
        }
    ],
    "sg:phone":"+1   ",
    "sg:postcode":"08820",
    "sg:province":"NJ",
    "sg:tags":[
        "mail",
        "house"
    ],
    "wof:name":"Executive Displays",
    "wof:placetype":"venue"
},
  "geometry": {"coordinates":[-74.345872,40.576004],"type":"Point"}
}