{
  "type": "Feature",
  "properties": {
    "iso:country":"US",
    "sg:address":"403 McKinley St",
    "sg:city":"Fairview",
    "sg:classifiers":[
        {
            "category":"Professional",
            "subcategory":"Management & Consulting",
            "type":"Services"
        }
    ],
    "sg:phone":"+1 201 313 0482",
    "sg:postcode":"07022",
    "sg:province":"NJ",
    "wof:name":"Barton & Company Management",
    "wof:placetype":"venue"
},
  "geometry": {"coordinates":[-74.00153299999999,40.815216],"type":"Point"}
}