{
  "type": "Feature",
  "properties": {
    "iso:country":"US",
    "sg:address":"1 Sportssystem Plz",
    "sg:city":"Bordentown",
    "sg:classifiers":[
        {
            "category":"Manufacturing",
            "subcategory":"Toys & Sporting Goods",
            "type":"Manufacturing & Wholesale Goods"
        },
        {
            "category":"Shopping",
            "subcategory":"Bicycles & Sporting Goods",
            "type":"Retail Goods"
        }
    ],
    "sg:phone":"+1 609 291 5800",
    "sg:postcode":"08505",
    "sg:province":"NJ",
    "sg:tags":[
        "racket",
        "mfg"
    ],
    "wof:name":"Prince Sports Group Inc",
    "wof:placetype":"venue"
},
  "geometry": {"coordinates":[-74.711449,40.122218],"type":"Point"}
}