{
  "type": "Feature",
  "properties": {
    "addr:full":"36 Seabury St Newark NJ 07104",
    "addr:housenumber":"36",
    "addr:postcode":"07104",
    "addr:street":"Seabury St",
    "iso:country":"US",
    "sg:address":"36 Seabury St",
    "sg:city":"Newark",
    "sg:classifiers":[
        {
            "category":"Professional",
            "type":"Services"
        }
    ],
    "sg:phone":"+1 973 483 9421",
    "sg:postcode":"07104",
    "sg:province":"NJ",
    "sg:tags":[
        "establishment"
    ],
    "wof:name":"T S Inc",
    "wof:placetype":"venue"
},
  "geometry": {"coordinates":[-74.159757,40.770421],"type":"Point"}
}