{
  "type": "Feature",
  "properties": {
    "addr:full":"72 Berlin Rd Stratford NJ 08084",
    "addr:housenumber":"72",
    "addr:postcode":"08084",
    "addr:street":"Berlin Rd",
    "iso:country":"US",
    "sg:address":"72 Berlin Rd",
    "sg:city":"Stratford",
    "sg:classifiers":[
        {
            "category":"Retail",
            "subcategory":"Auto Repair",
            "type":"Services"
        }
    ],
    "sg:phone":"+1 856 784 7277",
    "sg:postcode":"08084",
    "sg:province":"NJ",
    "sg:tags":[
        "shop",
        "repairing",
        "tire",
        "automotive",
        "general",
        "automobile"
    ],
    "wof:name":"Stratford Tire & Auto Service",
    "wof:placetype":"venue"
},
  "geometry": {"coordinates":[-74.999768,39.83142],"type":"Point"}
}