{
  "type": "Feature",
  "properties": {
    "iso:country":"US",
    "sg:address":"198 US Hwy 46",
    "sg:city":"Fairfield",
    "sg:classifiers":[
        {
            "category":"Real Estate",
            "subcategory":"Real Estate Agent",
            "type":"Services"
        }
    ],
    "sg:phone":"+1 973 808 1206",
    "sg:postcode":"07004",
    "sg:province":"NJ",
    "sg:tags":[
        "appraiser"
    ],
    "wof:name":"Real Estate Store",
    "wof:placetype":"venue"
},
  "geometry": {"coordinates":[-74.30386799999999,40.872768],"type":"Point"}
}