{
  "type": "Feature",
  "properties": {
    "iso:country":"US",
    "sg:address":"37 E 1st St",
    "sg:city":"Howell",
    "sg:classifiers":[
        {
            "category":"Retail",
            "subcategory":"Repair Shop",
            "type":"Services"
        }
    ],
    "sg:phone":"+1 732 363 5223",
    "sg:postcode":"07731",
    "sg:province":"NJ",
    "sg:tags":[
        "appliance"
    ],
    "wof:name":"Fix-It Appliance",
    "wof:placetype":"venue"
},
  "geometry": {"coordinates":[-74.236053,40.174534],"type":"Point"}
}