{
  "type": "Feature",
  "properties": {
    "addr:full":"811 W Main St Millville NJ 08332",
    "addr:housenumber":"811",
    "addr:postcode":"08332",
    "addr:street":"W Main St",
    "iso:country":"US",
    "sg:address":"811 W Main St",
    "sg:city":"Millville",
    "sg:classifiers":[
        {
            "category":"Shopping",
            "subcategory":"Clothing, Apparel, & Fashions",
            "type":"Retail Goods"
        }
    ],
    "sg:phone":"+1 856 825 8840",
    "sg:postcode":"08332",
    "sg:province":"NJ",
    "wof:name":"Marlo's Outlet I",
    "wof:placetype":"venue"
},
  "geometry": {"coordinates":[-75.058924,39.398001],"type":"Point"}
}