{
  "type": "Feature",
  "properties": {
    "iso:country":"US",
    "sg:address":"1189 Englishtown Rd",
    "sg:city":"Old Bridge",
    "sg:classifiers":[
        {
            "category":"Autos & Motor Vehicles",
            "subcategory":"Fuel & Gas Station",
            "type":"Retail Goods"
        }
    ],
    "sg:phone":"+1 732 251 0053",
    "sg:postcode":"08857",
    "sg:province":"NJ",
    "sg:tags":[
        "oil"
    ],
    "wof:name":"R J Bridge Svc Ctr & Conv Str",
    "wof:placetype":"venue"
},
  "geometry": {"coordinates":[-74.36044800000001,40.39974],"type":"Point"}
}