{
  "type": "Feature",
  "properties": {
    "iso:country":"US",
    "sg:address":"681 River Rd",
    "sg:city":"New Milford",
    "sg:classifiers":[
        {
            "category":"Health Services",
            "subcategory":"Chiropractor",
            "type":"Services"
        }
    ],
    "sg:phone":"+1 201 262 0433",
    "sg:postcode":"07646",
    "sg:province":"NJ",
    "wof:name":"Richard R Lubow DC",
    "wof:placetype":"venue"
},
  "geometry": {"coordinates":[-74.02533200000001,40.931936],"type":"Point"}
}