{
  "type": "Feature",
  "properties": {
    "addr:full":"741 Northfield Ave Ste 201 West Orange NJ 07052",
    "addr:housenumber":"741",
    "addr:postcode":"07052",
    "addr:street":"Northfield Ave Ste 201",
    "iso:country":"US",
    "sg:address":"741 Northfield Ave Ste 201",
    "sg:city":"West Orange",
    "sg:classifiers":[
        {
            "category":"Health Services",
            "subcategory":"Doctor",
            "type":"Services"
        }
    ],
    "sg:phone":"+1 973 325 6120",
    "sg:postcode":"07052",
    "sg:province":"NJ",
    "wof:name":"Sathaye Nirmal MD",
    "wof:placetype":"venue"
},
  "geometry": {"coordinates":[-74.29409800000001,40.7677],"type":"Point"}
}