{
  "type": "Feature",
  "properties": {
    "addr:full":"200 Federal St Ste 435 Camden NJ 08103",
    "addr:housenumber":"200",
    "addr:postcode":"08103",
    "addr:street":"Federal St Ste 435",
    "iso:country":"US",
    "sg:address":"200 Federal St Ste 435",
    "sg:city":"Camden",
    "sg:classifiers":[
        {
            "category":"Professional",
            "subcategory":"Employment Agencies",
            "type":"Services"
        }
    ],
    "sg:phone":"+1 856 225 6221",
    "sg:postcode":"08103",
    "sg:province":"NJ",
    "sg:website":"http://www.sbdcrvcc.com",
    "wof:name":"New Jersey Small Bus Dev Ctr",
    "wof:placetype":"venue"
},
  "geometry": {"coordinates":[-75.12572900000001,39.944354],"type":"Point"}
}