{
  "type": "Feature",
  "properties": {
    "iso:country":"US",
    "sg:address":"215 State Rte 37",
    "sg:city":"Toms River",
    "sg:classifiers":[
        {
            "category":"Retail",
            "subcategory":"Laundry & Dry Cleaning",
            "type":"Services"
        }
    ],
    "sg:phone":"+1 732 341 0255",
    "sg:postcode":"08755",
    "sg:province":"NJ",
    "sg:tags":[
        "drycleaning",
        "plant",
        "fur"
    ],
    "wof:name":"Dart Cleaners",
    "wof:placetype":"venue"
},
  "geometry": {"coordinates":[-74.222933,39.96632],"type":"Point"}
}