{
  "type": "Feature",
  "properties": {
    "iso:country":"US",
    "sg:address":"138 Mount Hope Ave",
    "sg:city":"Dover",
    "sg:classifiers":[
        {
            "category":"Building & Trades",
            "subcategory":"Cleaning & Sanitation",
            "type":"Services"
        }
    ],
    "sg:phone":"+1 973 361 2622",
    "sg:postcode":"07801",
    "sg:province":"NJ",
    "sg:tags":[
        "maintenance"
    ],
    "wof:name":"Clarence Cleaning Service",
    "wof:placetype":"venue"
},
  "geometry": {"coordinates":[-74.554434,40.892883],"type":"Point"}
}