{
  "type": "Feature",
  "properties": {
    "iso:country":"US",
    "sg:address":"131 State Rte 10",
    "sg:city":"Succasunna",
    "sg:classifiers":[
        {
            "category":"Home & Garden",
            "subcategory":"Garden Supply",
            "type":"Retail Goods"
        }
    ],
    "sg:phone":"+1 973 584 4488",
    "sg:postcode":"07876",
    "sg:province":"NJ",
    "sg:tags":[
        "nurseryman",
        "tool"
    ],
    "wof:name":"Dering's Garden Supply",
    "wof:placetype":"venue"
},
  "geometry": {"coordinates":[-74.63703099999999,40.86555],"type":"Point"}
}