{
  "type": "Feature",
  "properties": {
    "addr:full":"150 E Fish Rd Jackson NJ 08527",
    "addr:housenumber":"150",
    "addr:postcode":"08527",
    "addr:street":"E Fish Rd",
    "iso:country":"US",
    "sg:address":"150 E Fish Rd",
    "sg:city":"Jackson",
    "sg:classifiers":[
        {
            "category":"Building & Trades",
            "subcategory":"Construction",
            "type":"Services"
        }
    ],
    "sg:phone":"+1 732 928 3206",
    "sg:postcode":"08527",
    "sg:province":"NJ",
    "sg:tags":[
        "painter"
    ],
    "wof:name":"J & J Rutherford Ent Inc",
    "wof:placetype":"venue"
},
  "geometry": {"coordinates":[-74.339192,40.131635],"type":"Point"}
}