{
  "type": "Feature",
  "properties": {
    "addr:full":"2560 US Hwy 22 Scotch Plains NJ 07076",
    "addr:housenumber":"2560",
    "addr:postcode":"07076",
    "addr:street":"Us Hwy 22",
    "iso:country":"US",
    "sg:address":"2560 US Hwy 22",
    "sg:city":"Scotch Plains",
    "sg:classifiers":[
        {
            "category":"Wholesale",
            "subcategory":"Groceries",
            "type":"Manufacturing & Wholesale Goods"
        }
    ],
    "sg:phone":"+1 908 663 2145",
    "sg:postcode":"07076",
    "sg:province":"NJ",
    "sg:tags":[
        "food",
        "broker"
    ],
    "sg:website":"www.atlanticfds.com",
    "wof:name":"Tmc Foods LLC",
    "wof:placetype":"venue"
},
  "geometry": {"coordinates":[-74.39175299999999,40.662609],"type":"Point"}
}