{
  "type": "Feature",
  "properties": {
    "iso:country":"US",
    "sg:address":"16 Maple Ave",
    "sg:city":"Netcong",
    "sg:classifiers":[
        {
            "category":"Retail",
            "subcategory":"Auto Repair",
            "type":"Services"
        }
    ],
    "sg:phone":"+1 973 347 5442",
    "sg:postcode":"07857",
    "sg:province":"NJ",
    "sg:tags":[
        "body",
        "automobile",
        "painting"
    ],
    "wof:name":"Family Ford Auto Body",
    "wof:placetype":"venue"
},
  "geometry": {"coordinates":[-74.705376,40.898681],"type":"Point"}
}