{
  "type": "Feature",
  "properties": {
    "addr:full":"651 State Rte 72 Manahawkin NJ 08050",
    "addr:housenumber":"651",
    "addr:postcode":"08050",
    "addr:street":"State Rte 72",
    "iso:country":"US",
    "sg:address":"651 State Rte 72",
    "sg:city":"Manahawkin",
    "sg:classifiers":[
        {
            "category":"Professional",
            "subcategory":"Business Services",
            "type":"Services"
        }
    ],
    "sg:phone":"+1   ",
    "sg:postcode":"08050",
    "sg:province":"NJ",
    "sg:tags":[
        "company",
        "holding"
    ],
    "wof:name":"Millar Holdings",
    "wof:placetype":"venue"
},
  "geometry": {"coordinates":[-74.238145,39.680262],"type":"Point"}
}