{
  "type": "Feature",
  "properties": {
    "addr:full":"508 S Orange Ave Newark NJ 07103",
    "addr:housenumber":"508",
    "addr:postcode":"07103",
    "addr:street":"S Orange Ave",
    "iso:country":"US",
    "sg:address":"508 S Orange Ave",
    "sg:city":"Newark",
    "sg:classifiers":[
        {
            "category":"Food & Beverages",
            "subcategory":"Groceries & Convenience Stores",
            "type":"Retail Goods"
        }
    ],
    "sg:phone":"+1 973 991 2023",
    "sg:postcode":"07103",
    "sg:province":"NJ",
    "wof:name":"G & C African Food Store",
    "wof:placetype":"venue"
},
  "geometry": {"coordinates":[-74.20773800000001,40.742903],"type":"Point"}
}