{
  "type": "Feature",
  "properties": {
    "iso:country":"US",
    "sg:address":"23 Cattano Ave",
    "sg:city":"Morristown",
    "sg:classifiers":[
        {
            "category":"Professional",
            "subcategory":"Lawyer & Legal Services",
            "type":"Services"
        }
    ],
    "sg:phone":"+1 973 267 3333",
    "sg:postcode":"07960",
    "sg:province":"NJ",
    "wof:name":"Jensen James C",
    "wof:placetype":"venue"
},
  "geometry": {"coordinates":[-74.482193,40.798857],"type":"Point"}
}