{
  "type": "Feature",
  "properties": {
    "addr:full":"83 Burlews Ct # A Hackensack NJ 07601",
    "addr:housenumber":"83",
    "addr:postcode":"07601",
    "addr:street":"Burlews Ct # A",
    "iso:country":"US",
    "sg:address":"83 Burlews Ct # A",
    "sg:city":"Hackensack",
    "sg:classifiers":[
        {
            "category":"Sports & Exercise",
            "subcategory":"Swimming Pool",
            "type":"Entertainment"
        }
    ],
    "sg:phone":"+1 201 880 9898",
    "sg:postcode":"07601",
    "sg:province":"NJ",
    "sg:website":"www.kaydenmfg.com",
    "wof:name":"Kayden Manufacturing, Inc",
    "wof:placetype":"venue"
},
  "geometry": {"coordinates":[-74.039997,40.902918],"type":"Point"}
}