{
  "type": "Feature",
  "properties": {
    "addr:full":"2 Saddle Hill Rd Far Hills NJ 07931",
    "addr:housenumber":"2",
    "addr:postcode":"07931",
    "addr:street":"Saddle Hill Rd",
    "iso:country":"US",
    "sg:address":"2 Saddle Hill Rd",
    "sg:city":"Far Hills",
    "sg:classifiers":[
        {
            "category":"Professional",
            "subcategory":"Business Services",
            "type":"Services"
        }
    ],
    "sg:phone":"+1   ",
    "sg:postcode":"07931",
    "sg:province":"NJ",
    "sg:tags":[
        "arbitration"
    ],
    "wof:name":"Randi E Lowitt",
    "wof:placetype":"venue"
},
  "geometry": {"coordinates":[-74.644279,40.756285],"type":"Point"}
}