{
  "type": "Feature",
  "properties": {
    "addr:full":"20 Evergreen Dr N Browns Mills NJ 08015",
    "addr:housenumber":"20",
    "addr:postcode":"08015",
    "addr:street":"Evergreen Dr N",
    "iso:country":"US",
    "sg:address":"20 Evergreen Dr N",
    "sg:city":"Browns Mills",
    "sg:classifiers":[
        {
            "category":"Professional",
            "subcategory":"Business Services",
            "type":"Services"
        }
    ],
    "sg:phone":"+1   ",
    "sg:postcode":"08015",
    "sg:province":"NJ",
    "wof:name":"Js Partnership",
    "wof:placetype":"venue"
},
  "geometry": {"coordinates":[-74.55427,39.951492],"type":"Point"}
}