{
  "type": "Feature",
  "properties": {
    "iso:country":"US",
    "sg:address":"733 S Main St",
    "sg:city":"Phillipsburg",
    "sg:classifiers":[
        {
            "category":"Building & Trades",
            "subcategory":"Construction",
            "type":"Services"
        }
    ],
    "sg:phone":"+1 908 342 0266",
    "sg:postcode":"08865",
    "sg:province":"NJ",
    "sg:tags":[
        "house"
    ],
    "wof:name":"John P Jones Construction",
    "wof:placetype":"venue"
},
  "geometry": {"coordinates":[-75.181167,40.682328],"type":"Point"}
}