{
  "type": "Feature",
  "properties": {
    "iso:country":"US",
    "sg:address":"127 Klockner Rd",
    "sg:city":"Trenton",
    "sg:classifiers":[
        {
            "category":"Building & Trades",
            "subcategory":"Construction",
            "type":"Services"
        }
    ],
    "sg:phone":"+1 609 587 6709",
    "sg:postcode":"08619",
    "sg:province":"NJ",
    "sg:tags":[
        "heavy"
    ],
    "wof:name":"Best Landscaping",
    "wof:placetype":"venue"
},
  "geometry": {"coordinates":[-74.71097399999999,40.247671],"type":"Point"}
}