{
  "type": "Feature",
  "properties": {
    "iso:country":"US",
    "sg:address":"13 Franklin St",
    "sg:city":"Belleville",
    "sg:classifiers":[
        {
            "category":"Personal",
            "subcategory":"Beauty Salon",
            "type":"Services"
        }
    ],
    "sg:phone":"+1 973 759 9669",
    "sg:postcode":"07109",
    "sg:province":"NJ",
    "sg:tags":[
        "shop"
    ],
    "wof:name":"Ginas Beauty Salon",
    "wof:placetype":"venue"
},
  "geometry": {"coordinates":[-74.177404,40.77895],"type":"Point"}
}