{
  "type": "Feature",
  "properties": {
    "addr:full":"159 Nottingham Dr Willingboro NJ 08046",
    "addr:housenumber":"159",
    "addr:postcode":"08046",
    "addr:street":"Nottingham Dr",
    "iso:country":"US",
    "sg:address":"159 Nottingham Dr",
    "sg:city":"Willingboro",
    "sg:classifiers":[
        {
            "category":"Building & Trades",
            "subcategory":"Construction",
            "type":"Services"
        }
    ],
    "sg:phone":"+1 609 346 4119",
    "sg:postcode":"08046",
    "sg:province":"NJ",
    "sg:tags":[
        "house"
    ],
    "wof:name":"Progressive Home Solutions",
    "wof:placetype":"venue"
},
  "geometry": {"coordinates":[-74.859588,40.031054],"type":"Point"}
}