{
  "type": "Feature",
  "properties": {
    "addr:full":"852 2nd Ave Elizabeth NJ 07202",
    "addr:housenumber":"852",
    "addr:postcode":"07202",
    "addr:street":"2Nd Ave",
    "iso:country":"US",
    "sg:address":"852 2nd Ave",
    "sg:city":"Elizabeth",
    "sg:classifiers":[
        {
            "category":"Retail",
            "subcategory":"Laundry & Dry Cleaning",
            "type":"Services"
        }
    ],
    "sg:phone":"+1 908 629 1484",
    "sg:postcode":"07202",
    "sg:province":"NJ",
    "sg:tags":[
        "power"
    ],
    "wof:name":"Juniper Inc",
    "wof:placetype":"venue"
},
  "geometry": {"coordinates":[-74.205088,40.659022],"type":"Point"}
}