{
  "type": "Feature",
  "properties": {
    "iso:country":"US",
    "sg:address":"54 Grange Ct",
    "sg:city":"Woodstown",
    "sg:classifiers":[
        {
            "category":"Professional",
            "subcategory":"Computer Services",
            "type":"Services"
        }
    ],
    "sg:phone":"+1 856 769 1750",
    "sg:postcode":"08098",
    "sg:province":"NJ",
    "sg:tags":[
        "related"
    ],
    "wof:name":"R S M Solution Inc",
    "wof:placetype":"venue"
},
  "geometry": {"coordinates":[-75.328369,39.660585],"type":"Point"}
}