{
  "type": "Feature",
  "properties": {
    "addr:full":"240 Division Ave Garfield NJ 07026",
    "addr:housenumber":"240",
    "addr:postcode":"07026",
    "addr:street":"Division Ave",
    "iso:country":"US",
    "sg:address":"240 Division Ave",
    "sg:city":"Garfield",
    "sg:classifiers":[
        {
            "category":"Building & Trades",
            "subcategory":"Construction",
            "type":"Services"
        }
    ],
    "sg:phone":"+1 973 772 2060",
    "sg:postcode":"07026",
    "sg:province":"NJ",
    "sg:tags":[
        "roofing",
        "contractor"
    ],
    "wof:name":"Arco Construction Inc",
    "wof:placetype":"venue"
},
  "geometry": {"coordinates":[-74.117098,40.886283],"type":"Point"}
}