{
  "type": "Feature",
  "properties": {
    "addr:full":"714 Sunderland Rd Teaneck NJ 07666",
    "addr:housenumber":"714",
    "addr:postcode":"07666",
    "addr:street":"Sunderland Rd",
    "iso:country":"US",
    "sg:address":"714 Sunderland Rd",
    "sg:city":"Teaneck",
    "sg:classifiers":[
        {
            "category":"Professional",
            "subcategory":"Engineering",
            "type":"Services"
        },
        {
            "category":"Building & Trades",
            "subcategory":"Construction",
            "type":"Services"
        }
    ],
    "sg:phone":"+1 201 836 7437",
    "sg:postcode":"07666",
    "sg:province":"NJ",
    "sg:tags":[
        "designer"
    ],
    "wof:name":"Custom Prototype",
    "wof:placetype":"venue"
},
  "geometry": {"coordinates":[-74.022351,40.902233],"type":"Point"}
}