{
  "type": "Feature",
  "properties": {
    "addr:full":"348 Broad Ave Palisades Park NJ 07650",
    "addr:housenumber":"348",
    "addr:postcode":"07650",
    "addr:street":"Broad Ave",
    "iso:country":"US",
    "sg:address":"348 Broad Ave",
    "sg:city":"Palisades Park",
    "sg:classifiers":[
        {
            "category":"Personal",
            "subcategory":"Beauty Salon",
            "type":"Services"
        }
    ],
    "sg:phone":"+1 201 944 2025",
    "sg:postcode":"07650",
    "sg:province":"NJ",
    "wof:name":"Charlie Jeong Hair",
    "wof:placetype":"venue"
},
  "geometry": {"coordinates":[-73.99651,40.84983],"type":"Point"}
}