{
  "type": "Feature",
  "properties": {
    "iso:country":"US",
    "sg:address":"919 State Rte 33",
    "sg:city":"Freehold",
    "sg:classifiers":[
        {
            "category":"Building & Trades",
            "subcategory":"Plumbing",
            "type":"Services"
        }
    ],
    "sg:phone":"+1 732 536 2233",
    "sg:postcode":"07728",
    "sg:province":"NJ",
    "sg:tags":[
        "plumbing",
        "heating",
        "contractor"
    ],
    "wof:name":"Caballero & Sons Inc",
    "wof:placetype":"venue"
},
  "geometry": {"coordinates":[-74.227346,40.238039],"type":"Point"}
}