{
  "type": "Feature",
  "properties": {
    "iso:country":"US",
    "sg:address":"125 Potter St",
    "sg:city":"Haddonfield",
    "sg:classifiers":[
        {
            "category":"Professional",
            "subcategory":"Business Services",
            "type":"Services"
        }
    ],
    "sg:phone":"+1   ",
    "sg:postcode":"08033",
    "sg:province":"NJ",
    "wof:name":"Leslie Fog Interiors",
    "wof:placetype":"venue"
},
  "geometry": {"coordinates":[-75.025312,39.895755],"type":"Point"}
}