{
  "type": "Feature",
  "properties": {
    "iso:country":"US",
    "sg:address":"6 Senate Pl",
    "sg:city":"Jersey City",
    "sg:classifiers":[
        {
            "category":"Personal",
            "type":"Services"
        }
    ],
    "sg:phone":"+1 800 605 2574",
    "sg:postcode":"07306",
    "sg:province":"NJ",
    "sg:tags":[
        "mover"
    ],
    "sg:website":"www.newjerseymovers.com",
    "wof:name":"Alpha Relocation Services",
    "wof:placetype":"venue"
},
  "geometry": {"coordinates":[-74.06735,40.737748],"type":"Point"}
}