{
  "type": "Feature",
  "properties": {
    "addr:full":"1206 Ocean Ave Lakewood NJ 08701",
    "addr:housenumber":"1206",
    "addr:postcode":"08701",
    "addr:street":"Ocean Ave",
    "iso:country":"US",
    "sg:address":"1206 Ocean Ave",
    "sg:city":"Lakewood",
    "sg:classifiers":[
        {
            "category":"Autos & Motor Vehicles",
            "subcategory":"Automobile Sales",
            "type":"Retail Goods"
        }
    ],
    "sg:phone":"+1   ",
    "sg:postcode":"08701",
    "sg:province":"NJ",
    "wof:name":"Ocean Freightliner",
    "wof:placetype":"venue"
},
  "geometry": {"coordinates":[-74.16664400000001,40.082218],"type":"Point"}
}