{
  "type": "Feature",
  "properties": {
    "addr:full":"2912 Park Blvd Wildwood NJ 08260",
    "addr:housenumber":"2912",
    "addr:postcode":"08260",
    "addr:street":"Park Blvd",
    "iso:country":"US",
    "sg:address":"2912 Park Blvd",
    "sg:city":"Wildwood",
    "sg:classifiers":[
        {
            "category":"Restaurant",
            "type":"Food & Drink"
        },
        {
            "category":"Food & Beverages",
            "subcategory":"Groceries & Convenience Stores",
            "type":"Retail Goods"
        }
    ],
    "sg:phone":"+1 609 729 4599",
    "sg:postcode":"08260",
    "sg:province":"NJ",
    "sg:tags":[
        "delicatessen",
        "pizza"
    ],
    "wof:name":"Bill's Corner Deli",
    "wof:placetype":"venue"
},
  "geometry": {"coordinates":[-74.815201,38.994999],"type":"Point"}
}