{
  "type": "Feature",
  "properties": {
    "addr:full":"401 Avon Ave Newark NJ 07108",
    "addr:housenumber":"401",
    "addr:postcode":"07108",
    "addr:street":"Avon Ave",
    "iso:country":"US",
    "sg:address":"401 Avon Ave",
    "sg:city":"Newark",
    "sg:classifiers":[
        {
            "category":"Social Services",
            "subcategory":"Child Care",
            "type":"Services"
        }
    ],
    "sg:phone":"+1 973 642 3380",
    "sg:postcode":"07108",
    "sg:province":"NJ",
    "sg:tags":[
        "center",
        "day"
    ],
    "wof:name":"New Life Community Center",
    "wof:placetype":"venue"
},
  "geometry": {"coordinates":[-74.209136,40.72745],"type":"Point"}
}