{
  "type": "Feature",
  "properties": {
    "addr:full":"798 S Route 9 Cape May Court House NJ 08210",
    "addr:housenumber":"798",
    "addr:postcode":"08210",
    "addr:street":"S Route 9 Cape May",
    "iso:country":"US",
    "sg:address":"798 S Route 9",
    "sg:city":"Cape May Court House",
    "sg:classifiers":[
        {
            "category":"Restaurant",
            "type":"Food & Drink"
        }
    ],
    "sg:menulink":"http://www.allmenus.com/nj/middle/25931-santos/menu/",
    "sg:phone":"+1 609 463 1999",
    "sg:postcode":"08210",
    "sg:province":"NJ",
    "sg:tags":[
        "italian"
    ],
    "wof:name":"Santo's",
    "wof:placetype":"venue"
},
  "geometry": {"coordinates":[-74.831035,39.068496],"type":"Point"}
}