{
  "type": "Feature",
  "properties": {
    "iso:country":"US",
    "sg:address":"103 Dewey St",
    "sg:city":"Bloomfield",
    "sg:classifiers":[
        {
            "category":"Manufacturing",
            "subcategory":"Tools & Machinery",
            "type":"Manufacturing & Wholesale Goods"
        }
    ],
    "sg:phone":"+1 973 338 6500",
    "sg:postcode":"07003",
    "sg:province":"NJ",
    "sg:tags":[
        "industrial",
        "temperature",
        "process",
        "high",
        "mfr",
        "laboratory",
        "furnace"
    ],
    "sg:website":"www.cmfurnaces.com",
    "wof:name":"C-M Furnaces Inc",
    "wof:placetype":"venue"
},
  "geometry": {"coordinates":[-74.18153100000001,40.821314],"type":"Point"}
}