{
  "type": "Feature",
  "properties": {
    "addr:full":"150 Union Ave East Rutherford NJ 07073",
    "addr:housenumber":"150",
    "addr:postcode":"07073",
    "addr:street":"Union Ave",
    "iso:country":"US",
    "sg:address":"150 Union Ave",
    "sg:city":"East Rutherford",
    "sg:classifiers":[
        {
            "category":"Sports & Exercise",
            "subcategory":"Gym",
            "type":"Entertainment"
        }
    ],
    "sg:phone":"+1 201 896 1360",
    "sg:postcode":"07073",
    "sg:province":"NJ",
    "sg:tags":[
        "club",
        "studio",
        "health",
        "gymnasium"
    ],
    "sg:website":"www.strong-and-shapely.com",
    "wof:name":"Strong & Shapely Gym",
    "wof:placetype":"venue"
},
  "geometry": {"coordinates":[-74.099425,40.828177],"type":"Point"}
}