{
  "type": "Feature",
  "properties": {
    "addr:full":"19 Shady St Paterson NJ 07524",
    "addr:housenumber":"19",
    "addr:postcode":"07524",
    "addr:street":"Shady St",
    "iso:country":"US",
    "sg:address":"19 Shady St",
    "sg:city":"Paterson",
    "sg:classifiers":[
        {
            "category":"Manufacturing",
            "subcategory":"Metals",
            "type":"Manufacturing & Wholesale Goods"
        }
    ],
    "sg:phone":"+1 973 278 2100",
    "sg:postcode":"07524",
    "sg:province":"NJ",
    "sg:tags":[
        "fabrication",
        "structural"
    ],
    "wof:name":"Moeller Welding",
    "wof:placetype":"venue"
},
  "geometry": {"coordinates":[-74.165886,40.932763],"type":"Point"}
}