{
  "type": "Feature",
  "properties": {
    "addr:full":"96 Brainard Ave Port Monmouth NJ 07758",
    "addr:housenumber":"96",
    "addr:postcode":"07758",
    "addr:street":"Brainard Ave",
    "iso:country":"US",
    "sg:address":"96 Brainard Ave",
    "sg:city":"Port Monmouth",
    "sg:classifiers":[
        {
            "category":"Building & Trades",
            "subcategory":"Electrical",
            "type":"Services"
        }
    ],
    "sg:phone":"+1 732 495 1371",
    "sg:postcode":"07758",
    "sg:province":"NJ",
    "sg:tags":[
        "electric",
        "contractor"
    ],
    "wof:name":"Harry Huber",
    "wof:placetype":"venue"
},
  "geometry": {"coordinates":[-74.096009,40.431314],"type":"Point"}
}