{
  "type": "Feature",
  "properties": {
    "iso:country":"US",
    "sg:address":"957 Co Rd 517",
    "sg:city":"Glenwood",
    "sg:classifiers":[
        {
            "category":"Professional",
            "subcategory":"Advertising",
            "type":"Services"
        }
    ],
    "sg:phone":"+1 973 764 1490",
    "sg:postcode":"07418",
    "sg:province":"NJ",
    "sg:tags":[
        "representative"
    ],
    "wof:name":"Taplinger Associates",
    "wof:placetype":"venue"
},
  "geometry": {"coordinates":[-74.479445,41.241008],"type":"Point"}
}