{
  "type": "Feature",
  "properties": {
    "addr:full":"3 Berry Ct Maywood NJ 07607",
    "addr:housenumber":"3",
    "addr:postcode":"07607",
    "addr:street":"Berry Ct",
    "iso:country":"US",
    "sg:address":"3 Berry Ct",
    "sg:city":"Maywood",
    "sg:classifiers":[
        {
            "category":"Shopping",
            "subcategory":"Bicycles & Sporting Goods",
            "type":"Retail Goods"
        }
    ],
    "sg:phone":"+1   ",
    "sg:postcode":"07607",
    "sg:province":"NJ",
    "wof:name":"Bergen Ammo Co",
    "wof:placetype":"venue"
},
  "geometry": {"coordinates":[-74.065628,40.893675],"type":"Point"}
}