{
  "type": "Feature",
  "properties": {
    "iso:country":"US",
    "sg:address":"263 Crescent Ln",
    "sg:city":"Cliffside Park",
    "sg:classifiers":[
        {
            "category":"Building & Trades",
            "subcategory":"Locksmith",
            "type":"Services"
        }
    ],
    "sg:phone":"+1 201 368 7823",
    "sg:postcode":"07010",
    "sg:province":"NJ",
    "sg:tags":[
        "key"
    ],
    "wof:name":"R & R Locksmith",
    "wof:placetype":"venue"
},
  "geometry": {"coordinates":[-73.986465,40.825911],"type":"Point"}
}