{
  "type": "Feature",
  "properties": {
    "addr:full":"1110 Boardwalk Ocean City NJ 08226",
    "addr:housenumber":"1110",
    "addr:postcode":"08226",
    "addr:street":"Boardwalk",
    "iso:country":"US",
    "sg:address":"1110 Boardwalk",
    "sg:city":"Ocean City",
    "sg:classifiers":[
        {
            "category":"Shopping",
            "subcategory":"Clothing, Apparel, & Fashions",
            "type":"Retail Goods"
        }
    ],
    "sg:phone":"+1   ",
    "sg:postcode":"08226",
    "sg:province":"NJ",
    "sg:tags":[
        "family"
    ],
    "wof:name":"Connection The",
    "wof:placetype":"venue"
},
  "geometry": {"coordinates":[-74.577584,39.273343],"type":"Point"}
}