{
  "type": "Feature",
  "properties": {
    "iso:country":"US",
    "sg:address":"3192 N West Blvd",
    "sg:city":"Vineland",
    "sg:classifiers":[
        {
            "category":"Building & Trades",
            "subcategory":"Landscaping Services",
            "type":"Services"
        }
    ],
    "sg:phone":"+1 856 692 9504",
    "sg:postcode":"08360",
    "sg:province":"NJ",
    "sg:tags":[
        "lawn",
        "garden",
        "landscape",
        "contractor"
    ],
    "wof:name":"Turf Construction Co Inc",
    "wof:placetype":"venue"
},
  "geometry": {"coordinates":[-75.022561,39.534521],"type":"Point"}
}