{
  "type": "Feature",
  "properties": {
    "iso:country":"US",
    "sg:address":"3000 US Hwy 1",
    "sg:city":"Lawrenceville",
    "sg:classifiers":[
        {
            "category":"Travel",
            "subcategory":"Hotels & Motels",
            "type":"Entertainment"
        }
    ],
    "sg:phone":"+1 609 896 0900",
    "sg:postcode":"08648",
    "sg:province":"NJ",
    "wof:name":"Sleep-E-Hollow Motel",
    "wof:placetype":"venue"
},
  "geometry": {"coordinates":[-74.700065,40.280069],"type":"Point"}
}