{
  "type": "Feature",
  "properties": {
    "addr:full":"1039 Valley Rd Stirling NJ 07980",
    "addr:housenumber":"1039",
    "addr:postcode":"07980",
    "addr:street":"Valley Rd",
    "iso:country":"US",
    "sg:address":"1039 Valley Rd",
    "sg:city":"Stirling",
    "sg:classifiers":[
        {
            "category":"Autos & Motor Vehicles",
            "subcategory":"Fuel & Gas Station",
            "type":"Retail Goods"
        }
    ],
    "sg:phone":"+1 908 604 8599",
    "sg:postcode":"07980",
    "sg:province":"NJ",
    "wof:name":"Mobil Quick Farm",
    "wof:placetype":"venue"
},
  "geometry": {"coordinates":[-74.482226,40.669177],"type":"Point"}
}