{
  "type": "Feature",
  "properties": {
    "addr:full":"291 Wooley Rd West Milford NJ 07480",
    "addr:housenumber":"291",
    "addr:postcode":"07480",
    "addr:street":"Wooley Rd",
    "iso:country":"US",
    "sg:address":"291 Wooley Rd",
    "sg:city":"West Milford",
    "sg:classifiers":[
        {
            "category":"Building & Trades",
            "subcategory":"Construction",
            "type":"Services"
        }
    ],
    "sg:phone":"+1 973 697 7682",
    "sg:postcode":"07480",
    "sg:province":"NJ",
    "sg:tags":[
        "television",
        "line",
        "cable"
    ],
    "wof:name":"Bmw Splicing Inc",
    "wof:placetype":"venue"
},
  "geometry": {"coordinates":[-74.385983,41.094499],"type":"Point"}
}