{
  "type": "Feature",
  "properties": {
    "iso:country":"US",
    "sg:address":"102 E Bennett Ave",
    "sg:city":"Wildwood",
    "sg:classifiers":[
        {
            "category":"Restaurant",
            "type":"Food & Drink"
        }
    ],
    "sg:phone":"+1 609 522 7894",
    "sg:postcode":"08260",
    "sg:province":"NJ",
    "sg:website":"www.raviolihouse.com/index.html",
    "wof:name":"Ravioli House",
    "wof:placetype":"venue"
},
  "geometry": {"coordinates":[-74.8265,38.9823],"type":"Point"}
}