{
  "type": "Feature",
  "properties": {
    "iso:country":"US",
    "sg:address":"12 Olcott Ave",
    "sg:city":"Bernardsville",
    "sg:classifiers":[
        {
            "category":"Health Services",
            "subcategory":"Clinic",
            "type":"Services"
        }
    ],
    "sg:phone":"+1 908 766 0180",
    "sg:postcode":"07924",
    "sg:province":"NJ",
    "sg:tags":[
        "home"
    ],
    "sg:website":"www.visitingnurse.org",
    "wof:name":"Visiting Nurse Assn",
    "wof:placetype":"venue"
},
  "geometry": {"coordinates":[-74.568736,40.721082],"type":"Point"}
}