{
  "type": "Feature",
  "properties": {
    "addr:full":"810 Bear Tavern Rd Trenton NJ 08628",
    "addr:housenumber":"810",
    "addr:postcode":"08628",
    "addr:street":"Bear Tavern Rd",
    "iso:country":"US",
    "sg:address":"810 Bear Tavern Rd",
    "sg:city":"Trenton",
    "sg:classifiers":[
        {
            "category":"Government",
            "subcategory":"Office",
            "type":"Public Place"
        }
    ],
    "sg:phone":"+1   ",
    "sg:postcode":"08628",
    "sg:province":"NJ",
    "sg:tags":[
        "water",
        "resource"
    ],
    "wof:name":"Cost Ctr 2454-NJ Wtr Dst Off",
    "wof:placetype":"venue"
},
  "geometry": {"coordinates":[-74.83063199999999,40.278354],"type":"Point"}
}