{
  "type": "Feature",
  "properties": {
    "addr:full":"1925 Pacific Ave Atlantic City NJ 08401",
    "addr:housenumber":"1925",
    "addr:postcode":"08401",
    "addr:street":"Pacific Ave",
    "iso:country":"US",
    "sg:address":"1925 Pacific Ave",
    "sg:city":"Atlantic City",
    "sg:classifiers":[
        {
            "category":"Health Services",
            "subcategory":"Clinic",
            "type":"Services"
        }
    ],
    "sg:phone":"+1 609 441 8930",
    "sg:postcode":"08401",
    "sg:province":"NJ",
    "wof:name":"Community Health Svc",
    "wof:placetype":"venue"
},
  "geometry": {"coordinates":[-74.434365,39.357731],"type":"Point"}
}