{
  "type": "Feature",
  "properties": {
    "addr:full":"98 Audubon Rd Teaneck NJ 07666",
    "addr:housenumber":"98",
    "addr:postcode":"07666",
    "addr:street":"Audubon Rd",
    "iso:country":"US",
    "sg:address":"98 Audubon Rd",
    "sg:city":"Teaneck",
    "sg:classifiers":[
        {
            "category":"Manufacturing",
            "subcategory":"Printing",
            "type":"Manufacturing & Wholesale Goods"
        }
    ],
    "sg:phone":"+1 201 837 8783",
    "sg:postcode":"07666",
    "sg:province":"NJ",
    "sg:tags":[
        "lithographic",
        "printer",
        "commercial"
    ],
    "wof:name":"Bauer Printing Co",
    "wof:placetype":"venue"
},
  "geometry": {"coordinates":[-74.003293,40.88599],"type":"Point"}
}