{
  "type": "Feature",
  "properties": {
    "iso:country":"US",
    "sg:address":"101 Monmouth St",
    "sg:city":"Red Bank",
    "sg:classifiers":[
        {
            "category":"Shopping",
            "type":"Retail Goods"
        },
        {
            "category":"Professional",
            "subcategory":"Computer Services",
            "type":"Services"
        }
    ],
    "sg:phone":"+1 732 747 0485",
    "sg:postcode":"07701",
    "sg:province":"NJ",
    "sg:tags":[
        "a",
        "datum",
        "sales",
        "related",
        "base",
        "design"
    ],
    "wof:name":"Serpico's Business Machines",
    "wof:placetype":"venue"
},
  "geometry": {"coordinates":[-74.07034299999999,40.349142],"type":"Point"}
}