{
  "type": "Feature",
  "properties": {
    "iso:country":"US",
    "sg:address":"741 N Stiles St",
    "sg:city":"Linden",
    "sg:classifiers":[
        {
            "category":"Sports & Exercise",
            "subcategory":"Bowling",
            "type":"Entertainment"
        }
    ],
    "sg:phone":"+1   ",
    "sg:postcode":"07036",
    "sg:province":"NJ",
    "sg:tags":[
        "center"
    ],
    "wof:name":"Nation Wide Building Company",
    "wof:placetype":"venue"
},
  "geometry": {"coordinates":[-74.269537,40.627211],"type":"Point"}
}