{
  "type": "Feature",
  "properties": {
    "iso:country":"US",
    "sg:address":"801 2nd Ave",
    "sg:city":"Elizabeth",
    "sg:classifiers":[
        {
            "category":"Wholesale",
            "subcategory":"Fruits & Vegetables",
            "type":"Manufacturing & Wholesale Goods"
        }
    ],
    "sg:phone":"+1 908 527 8090",
    "sg:postcode":"07202",
    "sg:province":"NJ",
    "wof:name":"Dee Bel Produce",
    "wof:placetype":"venue"
},
  "geometry": {"coordinates":[-74.204707,40.658581],"type":"Point"}
}