{
  "type": "Feature",
  "properties": {
    "iso:country":"US",
    "sg:address":"319 11th Ave",
    "sg:city":"Belmar",
    "sg:classifiers":[
        {
            "category":"Professional",
            "subcategory":"Accounting & Tax Preparation",
            "type":"Services"
        }
    ],
    "sg:phone":"+1   ",
    "sg:postcode":"07719",
    "sg:province":"NJ",
    "wof:name":"Harry W Wolfmuller Accoun",
    "wof:placetype":"venue"
},
  "geometry": {"coordinates":[-74.019881,40.176972],"type":"Point"}
}