{
  "type": "Feature",
  "properties": {
    "iso:country":"US",
    "sg:address":"450 7th St",
    "sg:city":"Hoboken",
    "sg:classifiers":[
        {
            "category":"Professional",
            "subcategory":"Art Services",
            "type":"Services"
        }
    ],
    "sg:phone":"+1   ",
    "sg:postcode":"07030",
    "sg:province":"NJ",
    "sg:tags":[
        "communication",
        "graphic",
        "production",
        "creative"
    ],
    "wof:name":"Graphic Art Resource Assoc",
    "wof:placetype":"venue"
},
  "geometry": {"coordinates":[-74.03591400000001,40.746053],"type":"Point"}
}