{
  "type": "Feature",
  "properties": {
    "addr:full":"1420 Willowbrook Mall Wayne NJ 07470",
    "addr:housenumber":"1420",
    "addr:postcode":"07470",
    "addr:street":"Willowbrook Mall",
    "iso:country":"US",
    "sg:address":"1420 Willowbrook Mall",
    "sg:city":"Wayne",
    "sg:classifiers":[
        {
            "category":"Shopping",
            "subcategory":"Clothing, Apparel, & Fashions",
            "type":"Retail Goods"
        }
    ],
    "sg:phone":"+1 973 812 9355",
    "sg:postcode":"07470",
    "sg:province":"NJ",
    "wof:name":"Ann Taylor",
    "wof:placetype":"venue"
},
  "geometry": {"coordinates":[-74.255011,40.889541],"type":"Point"}
}