{
  "type": "Feature",
  "properties": {
    "addr:full":"40 High St Ste 200 Mount Holly NJ 08060",
    "addr:housenumber":"40",
    "addr:postcode":"08060",
    "addr:street":"High St Ste 200",
    "iso:country":"US",
    "sg:address":"40 High St Ste 200",
    "sg:city":"Mount Holly",
    "sg:classifiers":[
        {
            "category":"Shopping",
            "subcategory":"Florist",
            "type":"Retail Goods"
        }
    ],
    "sg:phone":"+1 609 261 3866",
    "sg:postcode":"08060",
    "sg:province":"NJ",
    "wof:name":"Horse Feathers Floral Design",
    "wof:placetype":"venue"
},
  "geometry": {"coordinates":[-74.7882,39.9941],"type":"Point"}
}