{
  "type": "Feature",
  "properties": {
    "iso:country":"US",
    "sg:address":"204 Eagle Rock Ave",
    "sg:city":"Roseland",
    "sg:classifiers":[
        {
            "category":"Professional",
            "subcategory":"Lawyer & Legal Services",
            "type":"Services"
        }
    ],
    "sg:phone":"+1 973 228 7900",
    "sg:postcode":"07068",
    "sg:province":"NJ",
    "wof:name":"Wishnia Bernard Attorney",
    "wof:placetype":"venue"
},
  "geometry": {"coordinates":[-74.29740099999999,40.820999],"type":"Point"}
}