{
  "type": "Feature",
  "properties": {
    "iso:country":"US",
    "sg:address":"1430 Oak Tree Rd",
    "sg:city":"Iselin",
    "sg:classifiers":[
        {
            "category":"Travel",
            "subcategory":"Travel Agent",
            "type":"Entertainment"
        }
    ],
    "sg:phone":"+1 732 283 0854",
    "sg:postcode":"08830",
    "sg:province":"NJ",
    "sg:tags":[
        "agency",
        "bureau"
    ],
    "wof:name":"Darpan Travel",
    "wof:placetype":"venue"
},
  "geometry": {"coordinates":[-74.32800400000001,40.573606],"type":"Point"}
}