{
  "type": "Feature",
  "properties": {
    "addr:full":"779 Eves Dr Somerville NJ 08844",
    "addr:housenumber":"779",
    "addr:postcode":"08844",
    "addr:street":"Eves Dr",
    "iso:country":"US",
    "sg:address":"779 Eves Dr",
    "sg:city":"Somerville",
    "sg:classifiers":[
        {
            "category":"Professional",
            "subcategory":"Business Services",
            "type":"Services"
        }
    ],
    "sg:phone":"+1   ",
    "sg:postcode":"08844",
    "sg:province":"NJ",
    "wof:name":"Genie Errand",
    "wof:placetype":"venue"
},
  "geometry": {"coordinates":[-74.65962,40.500893],"type":"Point"}
}