{
  "type": "Feature",
  "properties": {
    "addr:full":"45 W River Rd Rumson NJ 07760",
    "addr:housenumber":"45",
    "addr:postcode":"07760",
    "addr:street":"W River Rd",
    "iso:country":"US",
    "sg:address":"45 W River Rd",
    "sg:city":"Rumson",
    "sg:classifiers":[
        {
            "category":"Railroad",
            "type":"Transportation"
        }
    ],
    "sg:phone":"+1 732 747 2218",
    "sg:postcode":"07760",
    "sg:province":"NJ",
    "wof:name":"Interdom Partners LTD",
    "wof:placetype":"venue"
},
  "geometry": {"coordinates":[-74.013063,40.374853],"type":"Point"}
}