{
  "type": "Feature",
  "properties": {
    "iso:country":"US",
    "sg:address":"180 Van Buren St",
    "sg:city":"Newark",
    "sg:classifiers":[
        {
            "category":"Real Estate",
            "subcategory":"Real Estate Agent",
            "type":"Services"
        }
    ],
    "sg:phone":"+1 973 491 0009",
    "sg:postcode":"07105",
    "sg:province":"NJ",
    "wof:name":"Viles Contracting Corp",
    "wof:placetype":"venue"
},
  "geometry": {"coordinates":[-74.15809299999999,40.72706],"type":"Point"}
}