{
  "type": "Feature",
  "properties": {
    "addr:full":"2090 Springdale Rd Cherry Hill NJ 08003",
    "addr:housenumber":"2090",
    "addr:postcode":"08003",
    "addr:street":"Springdale Rd",
    "iso:country":"US",
    "sg:address":"2090 Springdale Rd",
    "sg:city":"Cherry Hill",
    "sg:classifiers":[
        {
            "category":"Retail",
            "subcategory":"Repair Shop",
            "type":"Services"
        }
    ],
    "sg:phone":"+1   ",
    "sg:postcode":"08003",
    "sg:province":"NJ",
    "sg:tags":[
        "locksmith"
    ],
    "wof:name":"Cherry Lock & Security Service",
    "wof:placetype":"venue"
},
  "geometry": {"coordinates":[-74.964354,39.919995],"type":"Point"}
}