{
  "type": "Feature",
  "properties": {
    "addr:full":"100 East Ave Woodstown NJ 08098",
    "addr:housenumber":"100",
    "addr:postcode":"08098",
    "addr:street":"East Ave",
    "iso:country":"US",
    "sg:address":"100 East Ave",
    "sg:city":"Woodstown",
    "sg:classifiers":[
        {
            "category":"Sports & Exercise",
            "subcategory":"Gym",
            "type":"Entertainment"
        }
    ],
    "sg:phone":"+1 856 769 8448",
    "sg:postcode":"08098",
    "sg:province":"NJ",
    "sg:tags":[
        "fitness",
        "physical",
        "facility"
    ],
    "wof:name":"Curves For Women",
    "wof:placetype":"venue"
},
  "geometry": {"coordinates":[-75.32383,39.65138],"type":"Point"}
}