{
  "type": "Feature",
  "properties": {
    "iso:country":"US",
    "sg:address":"865 Lower Ferry Rd",
    "sg:city":"Trenton",
    "sg:classifiers":[
        {
            "category":"Restaurant",
            "type":"Food & Drink"
        }
    ],
    "sg:phone":"+1   ",
    "sg:postcode":"08628",
    "sg:province":"NJ",
    "sg:tags":[
        "eating"
    ],
    "wof:name":"Kosher Cafe",
    "wof:placetype":"venue"
},
  "geometry": {"coordinates":[-74.811696,40.249056],"type":"Point"}
}