{
  "type": "Feature",
  "properties": {
    "iso:country":"US",
    "sg:address":"665 Martinsville Rd",
    "sg:city":"Basking Ridge",
    "sg:classifiers":[
        {
            "category":"Restaurant",
            "type":"Food & Drink"
        }
    ],
    "sg:phone":"+1 908 580 9588",
    "sg:postcode":"07920",
    "sg:province":"NJ",
    "wof:name":"Ling Ling Riverwalk",
    "wof:placetype":"venue"
},
  "geometry": {"coordinates":[-74.57752000000001,40.659807],"type":"Point"}
}