{
  "type": "Feature",
  "properties": {
    "iso:country":"US",
    "sg:address":"2305 New Jersey Ave",
    "sg:city":"Wildwood",
    "sg:classifiers":[
        {
            "category":"Personal",
            "subcategory":"Barber",
            "type":"Services"
        }
    ],
    "sg:phone":"+1 609 729 3636",
    "sg:postcode":"08260",
    "sg:province":"NJ",
    "wof:name":"Martino's Barber & Beauty Salon",
    "wof:placetype":"venue"
},
  "geometry": {"coordinates":[-74.808296,38.995701],"type":"Point"}
}