{
  "type": "Feature",
  "properties": {
    "iso:country":"US",
    "sg:address":"382 Morris Ave",
    "sg:city":"Long Branch",
    "sg:classifiers":[
        {
            "category":"Organizations",
            "subcategory":"Non-profit Organization",
            "type":"Services"
        }
    ],
    "sg:phone":"+1 732 222 4465",
    "sg:postcode":"07740",
    "sg:province":"NJ",
    "sg:tags":[
        "social"
    ],
    "wof:name":"National Assoc of Retired",
    "wof:placetype":"venue"
},
  "geometry": {"coordinates":[-73.994705,40.299734],"type":"Point"}
}