{
  "type": "Feature",
  "properties": {
    "iso:country":"US",
    "sg:address":"5050 Industrial Rd",
    "sg:city":"Farmingdale",
    "sg:classifiers":[
        {
            "category":"Building & Trades",
            "subcategory":"Construction",
            "type":"Services"
        }
    ],
    "sg:phone":"+1 732 751 0510",
    "sg:postcode":"07727",
    "sg:province":"NJ",
    "sg:tags":[
        "carpentry",
        "contractor"
    ],
    "wof:name":"Kne Corporation",
    "wof:placetype":"venue"
},
  "geometry": {"coordinates":[-74.125502,40.189907],"type":"Point"}
}