{
  "type": "Feature",
  "properties": {
    "iso:country":"US",
    "sg:address":"129 Newark Pompton Tpke",
    "sg:city":"Pequannock",
    "sg:classifiers":[
        {
            "category":"Retail",
            "subcategory":"Auto Repair",
            "type":"Services"
        }
    ],
    "sg:phone":"+1 973 696 6789",
    "sg:postcode":"07440",
    "sg:province":"NJ",
    "wof:name":"Lee Imports",
    "wof:placetype":"venue"
},
  "geometry": {"coordinates":[-74.286598,40.946301],"type":"Point"}
}