{
  "type": "Feature",
  "properties": {
    "addr:full":"357 Amwell Rd Hillsborough NJ 08844",
    "addr:housenumber":"357",
    "addr:postcode":"08844",
    "addr:street":"Amwell Rd",
    "iso:country":"US",
    "sg:address":"357 Amwell Rd",
    "sg:city":"Hillsborough",
    "sg:classifiers":[
        {
            "category":"Social Services",
            "subcategory":"Child Care",
            "type":"Services"
        }
    ],
    "sg:phone":"+1 908 359 2499",
    "sg:postcode":"08844",
    "sg:province":"NJ",
    "sg:website":"www.rainbowchilddevelopment.com",
    "wof:name":"Rainbow Child Development Ctr",
    "wof:placetype":"venue"
},
  "geometry": {"coordinates":[-74.641659,40.501777],"type":"Point"}
}