{
  "type": "Feature",
  "properties": {
    "iso:country":"US",
    "sg:address":"43 Winding Ln",
    "sg:city":"Bloomfield",
    "sg:classifiers":[
        {
            "category":"Professional",
            "subcategory":"Computer Services",
            "type":"Services"
        }
    ],
    "sg:phone":"+1 973 893 1457",
    "sg:postcode":"07003",
    "sg:province":"NJ",
    "sg:tags":[
        "related"
    ],
    "wof:name":"Graphic Image",
    "wof:placetype":"venue"
},
  "geometry": {"coordinates":[-74.182112,40.830085],"type":"Point"}
}