{
  "type": "Feature",
  "properties": {
    "addr:full":"29 Fellswood Dr Livingston NJ 07039",
    "addr:housenumber":"29",
    "addr:postcode":"07039",
    "addr:street":"Fellswood Dr",
    "iso:country":"US",
    "sg:address":"29 Fellswood Dr",
    "sg:city":"Livingston",
    "sg:classifiers":[
        {
            "category":"Shopping",
            "subcategory":"Gifts & Souvenirs",
            "type":"Retail Goods"
        }
    ],
    "sg:phone":"+1   ",
    "sg:postcode":"07039",
    "sg:province":"NJ",
    "wof:name":"Gala Affaire",
    "wof:placetype":"venue"
},
  "geometry": {"coordinates":[-74.308257,40.799014],"type":"Point"}
}