{
  "type": "Feature",
  "properties": {
    "iso:country":"US",
    "sg:address":"4813 Westfield Ave",
    "sg:city":"Pennsauken",
    "sg:classifiers":[
        {
            "category":"Personal",
            "subcategory":"Beauty Salon",
            "type":"Services"
        }
    ],
    "sg:phone":"+1 856 665 9797",
    "sg:postcode":"08110",
    "sg:province":"NJ",
    "sg:tags":[
        "nail",
        "barber"
    ],
    "wof:name":"Hollywood Beauty Salon",
    "wof:placetype":"venue"
},
  "geometry": {"coordinates":[-75.065997,39.958395],"type":"Point"}
}