{
  "type": "Feature",
  "properties": {
    "iso:country":"US",
    "sg:address":"2 Colfax Ave",
    "sg:city":"Pompton Lakes",
    "sg:classifiers":[
        {
            "category":"Personal",
            "subcategory":"Beauty Salon",
            "type":"Services"
        }
    ],
    "sg:phone":"+1 973 831 7554",
    "sg:postcode":"07442",
    "sg:province":"NJ",
    "sg:tags":[
        "shop",
        "piercing"
    ],
    "wof:name":"Ray & Rita's Hairstyling",
    "wof:placetype":"venue"
},
  "geometry": {"coordinates":[-74.291496,41.005402],"type":"Point"}
}