{
  "type": "Feature",
  "properties": {
    "iso:country":"US",
    "sg:address":"22 Kohomo Ave",
    "sg:city":"Sicklerville",
    "sg:classifiers":[
        {
            "category":"Shopping",
            "subcategory":"Bicycles & Sporting Goods",
            "type":"Retail Goods"
        }
    ],
    "sg:phone":"+1   ",
    "sg:postcode":"08081",
    "sg:province":"NJ",
    "wof:name":"Fishing Tackle Plus",
    "wof:placetype":"venue"
},
  "geometry": {"coordinates":[-75.006443,39.766871],"type":"Point"}
}