{
  "type": "Feature",
  "properties": {
    "iso:country":"US",
    "sg:address":"315 N Broadway",
    "sg:city":"Pitman",
    "sg:classifiers":[
        {
            "category":"Retail",
            "subcategory":"Auto Repair",
            "type":"Services"
        }
    ],
    "sg:phone":"+1 856 218 7077",
    "sg:postcode":"08071",
    "sg:province":"NJ",
    "sg:tags":[
        "repairing",
        "automobile"
    ],
    "wof:name":"Pitman Auto Repair & Svc",
    "wof:placetype":"venue"
},
  "geometry": {"coordinates":[-75.134542,39.736367],"type":"Point"}
}