{
  "type": "Feature",
  "properties": {
    "iso:country":"US",
    "sg:address":"730 Cardinal Dr",
    "sg:city":"Bridgeport",
    "sg:classifiers":[
        {
            "category":"Wholesale",
            "subcategory":"Machinery & Supplies",
            "type":"Manufacturing & Wholesale Goods"
        }
    ],
    "sg:phone":"+1 856 467 2307",
    "sg:postcode":"08085",
    "sg:province":"NJ",
    "sg:tags":[
        "new",
        "fitting",
        "valve"
    ],
    "wof:name":"Industrial Valco Inc",
    "wof:placetype":"venue"
},
  "geometry": {"coordinates":[-75.368966,39.776156],"type":"Point"}
}