{
  "type": "Feature",
  "properties": {
    "iso:country":"US",
    "sg:address":"23 Main St",
    "sg:city":"Robbinsville",
    "sg:classifiers":[
        {
            "category":"Restaurant",
            "type":"Food & Drink"
        }
    ],
    "sg:phone":"+1 609 259 3994",
    "sg:postcode":"08691",
    "sg:province":"NJ",
    "sg:tags":[
        "delicatessen"
    ],
    "wof:name":"Main Street Deli",
    "wof:placetype":"venue"
},
  "geometry": {"coordinates":[-74.622512,40.215126],"type":"Point"}
}