{
  "type": "Feature",
  "properties": {
    "iso:country":"US",
    "sg:address":"266 Main Ave",
    "sg:city":"Stirling",
    "sg:classifiers":[
        {
            "category":"Retail",
            "subcategory":"Car Wash",
            "type":"Services"
        }
    ],
    "sg:phone":"+1 908 665 1930",
    "sg:postcode":"07980",
    "sg:province":"NJ",
    "sg:tags":[
        "automobile"
    ],
    "wof:name":"Buff By Jimmy",
    "wof:placetype":"venue"
},
  "geometry": {"coordinates":[-74.49493099999999,40.672282],"type":"Point"}
}