{
  "type": "Feature",
  "properties": {
    "iso:country":"US",
    "sg:address":"1612 Summit Ave",
    "sg:city":"Union City",
    "sg:classifiers":[
        {
            "category":"Retail",
            "subcategory":"Laundry & Dry Cleaning",
            "type":"Services"
        }
    ],
    "sg:phone":"+1 201 866 9184",
    "sg:postcode":"07087",
    "sg:province":"NJ",
    "sg:tags":[
        "garment",
        "agent"
    ],
    "wof:name":"Dry Cleaner & Tailor",
    "wof:placetype":"venue"
},
  "geometry": {"coordinates":[-74.0395,40.764525],"type":"Point"}
}