{
  "type": "Feature",
  "properties": {
    "iso:country":"US",
    "sg:address":"123 E Clearview Ave",
    "sg:city":"Pine Hill",
    "sg:classifiers":[
        {
            "category":"Government",
            "subcategory":"Office",
            "type":"Public Place"
        }
    ],
    "sg:phone":"+1 856 783 3856",
    "sg:postcode":"08021",
    "sg:province":"NJ",
    "sg:tags":[
        "village"
    ],
    "wof:name":"Pine Hill Building Inspector",
    "wof:placetype":"venue"
},
  "geometry": {"coordinates":[-74.989712,39.780487],"type":"Point"}
}