{
  "type": "Feature",
  "properties": {
    "iso:country":"US",
    "sg:address":"559 Livingston St",
    "sg:city":"Norwood",
    "sg:classifiers":[
        {
            "category":"Restaurant",
            "type":"Food & Drink"
        }
    ],
    "sg:phone":"+1 201 767 3636",
    "sg:postcode":"07648",
    "sg:province":"NJ",
    "wof:name":"Pizza Express",
    "wof:placetype":"venue"
},
  "geometry": {"coordinates":[-73.956056,40.996466],"type":"Point"}
}