{
  "type": "Feature",
  "properties": {
    "iso:country":"US",
    "sg:address":"9 Ebert Dr",
    "sg:city":"Hillsborough",
    "sg:classifiers":[
        {
            "category":"Professional",
            "type":"Services"
        }
    ],
    "sg:phone":"+1 908 281 7730",
    "sg:postcode":"08844",
    "sg:province":"NJ",
    "wof:name":"Trading As",
    "wof:placetype":"venue"
},
  "geometry": {"coordinates":[-74.62957900000001,40.528877],"type":"Point"}
}