{
  "type": "Feature",
  "properties": {
    "addr:full":"182 S Lake Dr Red Bank NJ 07701",
    "addr:housenumber":"182",
    "addr:postcode":"07701",
    "addr:street":"S Lake Dr",
    "iso:country":"US",
    "sg:address":"182 S Lake Dr",
    "sg:city":"Red Bank",
    "sg:classifiers":[
        {
            "category":"Professional",
            "subcategory":"Computer Services",
            "type":"Services"
        }
    ],
    "sg:phone":"+1 732 747 8989",
    "sg:postcode":"07701",
    "sg:province":"NJ",
    "sg:tags":[
        "related"
    ],
    "wof:name":"Woodlake Associates Ltd",
    "wof:placetype":"venue"
},
  "geometry": {"coordinates":[-74.095938,40.36056],"type":"Point"}
}