{
  "type": "Feature",
  "properties": {
    "iso:country":"US",
    "sg:address":"2 Tiverstock Dr",
    "sg:city":"Elmer",
    "sg:classifiers":[
        {
            "category":"Social Services",
            "subcategory":"Child Care",
            "type":"Services"
        }
    ],
    "sg:phone":"+1 856 358 0039",
    "sg:postcode":"08318",
    "sg:province":"NJ",
    "sg:tags":[
        "day"
    ],
    "wof:name":"In Learning Combination",
    "wof:placetype":"venue"
},
  "geometry": {"coordinates":[-75.158851,39.53862],"type":"Point"}
}