{
  "type": "Feature",
  "properties": {
    "addr:full":"562 Boulevard Kenilworth NJ 07033",
    "addr:housenumber":"562",
    "addr:postcode":"07033",
    "addr:street":"Boulevard",
    "iso:country":"US",
    "sg:address":"562 Boulevard",
    "sg:city":"Kenilworth",
    "sg:classifiers":[
        {
            "category":"Wholesale",
            "subcategory":"Medical Equipment & Supplies",
            "type":"Manufacturing & Wholesale Goods"
        }
    ],
    "sg:phone":"+1 908 272 8550",
    "sg:postcode":"07033",
    "sg:province":"NJ",
    "sg:tags":[
        "physician",
        "surgeon"
    ],
    "wof:name":"Orthomedix",
    "wof:placetype":"venue"
},
  "geometry": {"coordinates":[-74.28884600000001,40.676495],"type":"Point"}
}