{
  "type": "Feature",
  "properties": {
    "addr:full":"3088 Shore Rd Ocean View NJ 08230",
    "addr:housenumber":"3088",
    "addr:postcode":"08230",
    "addr:street":"Shore Rd",
    "iso:country":"US",
    "sg:address":"3088 Shore Rd",
    "sg:city":"Ocean View",
    "sg:classifiers":[
        {
            "category":"Organizations",
            "subcategory":"Religious Organization",
            "type":"Services"
        }
    ],
    "sg:phone":"+1   ",
    "sg:postcode":"08230",
    "sg:province":"NJ",
    "wof:name":"Seaville Friends Meeting",
    "wof:placetype":"venue"
},
  "geometry": {"coordinates":[-74.71427199999999,39.196237],"type":"Point"}
}