{
  "type": "Feature",
  "properties": {
    "addr:full":"878 Queen Anne Rd Teaneck NJ 07666",
    "addr:housenumber":"878",
    "addr:postcode":"07666",
    "addr:street":"Queen Anne Rd",
    "iso:country":"US",
    "sg:address":"878 Queen Anne Rd",
    "sg:city":"Teaneck",
    "sg:classifiers":[
        {
            "category":"Health Services",
            "subcategory":"Clinic",
            "type":"Services"
        },
        {
            "category":"Social Services",
            "subcategory":"Child Care",
            "type":"Services"
        }
    ],
    "sg:phone":"+1 201 836 1776",
    "sg:postcode":"07666",
    "sg:province":"NJ",
    "sg:tags":[
        "counseling",
        "mental",
        "day"
    ],
    "wof:name":"Simmonds Chana Lcsw Rcsw",
    "wof:placetype":"venue"
},
  "geometry": {"coordinates":[-74.013603,40.888802],"type":"Point"}
}