{
  "type": "Feature",
  "properties": {
    "iso:country":"US",
    "sg:address":"1031 Old Foundry Rd",
    "sg:city":"Newton",
    "sg:classifiers":[
        {
            "category":"Building & Trades",
            "subcategory":"Construction",
            "type":"Services"
        }
    ],
    "sg:phone":"+1 973 383 1894",
    "sg:postcode":"07860",
    "sg:province":"NJ",
    "sg:tags":[
        "house"
    ],
    "wof:name":"Old Foundry Construction",
    "wof:placetype":"venue"
},
  "geometry": {"coordinates":[-74.88486,41.082095],"type":"Point"}
}