{
  "type": "Feature",
  "properties": {
    "iso:country":"US",
    "sg:address":"200 Mercer St",
    "sg:city":"Hightstown",
    "sg:classifiers":[
        {
            "category":"Personal",
            "subcategory":"Beauty Salon",
            "type":"Services"
        }
    ],
    "sg:phone":"+1 609 443 1895",
    "sg:postcode":"08520",
    "sg:province":"NJ",
    "sg:tags":[
        "shop"
    ],
    "wof:name":"Charisma Beauty Center",
    "wof:placetype":"venue"
},
  "geometry": {"coordinates":[-74.52772299999999,40.2671],"type":"Point"}
}