{
  "type": "Feature",
  "properties": {
    "addr:full":"200 Summerhill Rd Spotswood NJ 08884",
    "addr:housenumber":"200",
    "addr:postcode":"08884",
    "addr:street":"Summerhill Rd",
    "iso:country":"US",
    "sg:address":"200 Summerhill Rd",
    "sg:city":"Spotswood",
    "sg:classifiers":[
        {
            "category":"Banks & Credit Unions",
            "subcategory":"Bank",
            "type":"Services"
        }
    ],
    "sg:phone":"+1 732 251 6660",
    "sg:postcode":"08884",
    "sg:province":"NJ",
    "wof:name":"Wachovia Bank",
    "wof:placetype":"venue"
},
  "geometry": {"coordinates":[-74.38716599999999,40.40529],"type":"Point"}
}