{
  "type": "Feature",
  "properties": {
    "iso:country":"US",
    "sg:address":"23 Ann St",
    "sg:city":"Newark",
    "sg:classifiers":[
        {
            "category":"Building & Trades",
            "subcategory":"Construction",
            "type":"Services"
        }
    ],
    "sg:phone":"+1 973 589 1968",
    "sg:postcode":"07105",
    "sg:province":"NJ",
    "sg:tags":[
        "general",
        "contractor"
    ],
    "wof:name":"Mollof Mechanical Contr Inc",
    "wof:placetype":"venue"
},
  "geometry": {"coordinates":[-74.15554899999999,40.722884],"type":"Point"}
}