{
  "type": "Feature",
  "properties": {
    "iso:country":"US",
    "sg:address":"11 San Bar Dr",
    "sg:city":"Lake Hopatcong",
    "sg:classifiers":[
        {
            "category":"Building & Trades",
            "subcategory":"Construction",
            "type":"Services"
        }
    ],
    "sg:phone":"+1 973 663 4131",
    "sg:postcode":"07849",
    "sg:province":"NJ",
    "wof:name":"Discount Paving",
    "wof:placetype":"venue"
},
  "geometry": {"coordinates":[-74.620947,40.941953],"type":"Point"}
}