{
  "type": "Feature",
  "properties": {
    "addr:full":"146 2nd St Bergenfield NJ 07621",
    "addr:housenumber":"146",
    "addr:postcode":"07621",
    "addr:street":"2Nd St",
    "iso:country":"US",
    "sg:address":"146 2nd St",
    "sg:city":"Bergenfield",
    "sg:classifiers":[
        {
            "category":"Retail",
            "subcategory":"Repair Shop",
            "type":"Services"
        }
    ],
    "sg:phone":"+1 201 384 5976",
    "sg:postcode":"07621",
    "sg:province":"NJ",
    "sg:tags":[
        "television",
        "radio"
    ],
    "wof:name":"Al's TV Svc",
    "wof:placetype":"venue"
},
  "geometry": {"coordinates":[-73.989221,40.932558],"type":"Point"}
}