{
  "type": "Feature",
  "properties": {
    "addr:full":"70 Hickory Rd Sussex NJ 07461",
    "addr:housenumber":"70",
    "addr:postcode":"07461",
    "addr:street":"Hickory Rd",
    "iso:country":"US",
    "sg:address":"70 Hickory Rd",
    "sg:city":"Sussex",
    "sg:classifiers":[
        {
            "category":"Utilities",
            "subcategory":"Refuse",
            "type":"Services"
        }
    ],
    "sg:phone":"+1 973 702 8321",
    "sg:postcode":"07461",
    "sg:province":"NJ",
    "sg:tags":[
        "disposal",
        "collection"
    ],
    "wof:name":"Quality Cleanups & Hauling",
    "wof:placetype":"venue"
},
  "geometry": {"coordinates":[-74.64945400000001,41.246038],"type":"Point"}
}