{
  "type": "Feature",
  "properties": {
    "iso:country":"US",
    "sg:address":"1085 Stuyvesant Ave",
    "sg:city":"Irvington",
    "sg:classifiers":[
        {
            "category":"Food & Beverages",
            "subcategory":"Groceries & Convenience Stores",
            "type":"Retail Goods"
        }
    ],
    "sg:phone":"+1   ",
    "sg:postcode":"07111",
    "sg:province":"NJ",
    "wof:name":"Eakta & Ronak Corp",
    "wof:placetype":"venue"
},
  "geometry": {"coordinates":[-74.252278,40.715174],"type":"Point"}
}