{
  "type": "Feature",
  "properties": {
    "iso:country":"US",
    "sg:address":"1731 Church St",
    "sg:city":"Rahway",
    "sg:classifiers":[
        {
            "category":"Organizations",
            "subcategory":"Religious Organization",
            "type":"Services"
        }
    ],
    "sg:phone":"+1 732 382 0803",
    "sg:postcode":"07065",
    "sg:province":"NJ",
    "sg:tags":[
        "church"
    ],
    "wof:name":"First Presbyterian Church Inc",
    "wof:placetype":"venue"
},
  "geometry": {"coordinates":[-74.280778,40.615154],"type":"Point"}
}