{
  "type": "Feature",
  "properties": {
    "iso:country":"US",
    "sg:address":"123 Spring Hill Dr",
    "sg:city":"Swedesboro",
    "sg:classifiers":[
        {
            "category":"Freight",
            "type":"Transportation"
        }
    ],
    "sg:phone":"+1 856 467 1334",
    "sg:postcode":"08085",
    "sg:province":"NJ",
    "sg:tags":[
        "operator",
        "trucking"
    ],
    "wof:name":"John C Bitting Jr Inc",
    "wof:placetype":"venue"
},
  "geometry": {"coordinates":[-75.29319,39.770976],"type":"Point"}
}