{
  "type": "Feature",
  "properties": {
    "addr:full":"24 Chestnut Ridge Rd Montvale NJ 07645",
    "addr:housenumber":"24",
    "addr:postcode":"07645",
    "addr:street":"Chestnut Ridge Rd",
    "iso:country":"US",
    "sg:address":"24 Chestnut Ridge Rd",
    "sg:city":"Montvale",
    "sg:classifiers":[
        {
            "category":"Shopping",
            "subcategory":"Jewelry",
            "type":"Retail Goods"
        }
    ],
    "sg:phone":"+1 201 930 8883",
    "sg:postcode":"07645",
    "sg:province":"NJ",
    "sg:tags":[
        "jeweler"
    ],
    "wof:name":"F Silverman Jewelers",
    "wof:placetype":"venue"
},
  "geometry": {"coordinates":[-74.069553,41.05109],"type":"Point"}
}