{
  "type": "Feature",
  "properties": {
    "iso:country":"US",
    "sg:address":"86 Miller Rd",
    "sg:city":"Morristown",
    "sg:classifiers":[
        {
            "category":"Building & Trades",
            "subcategory":"Construction",
            "type":"Services"
        }
    ],
    "sg:phone":"+1 973 540 1629",
    "sg:postcode":"07960",
    "sg:province":"NJ",
    "sg:tags":[
        "contractor"
    ],
    "wof:name":"KQD Construction Inc",
    "wof:placetype":"venue"
},
  "geometry": {"coordinates":[-74.482868,40.790366],"type":"Point"}
}