{
  "type": "Feature",
  "properties": {
    "addr:full":"868 Inverness Ct Lakewood NJ 08701",
    "addr:housenumber":"868",
    "addr:postcode":"08701",
    "addr:street":"Inverness Ct",
    "iso:country":"US",
    "sg:address":"868 Inverness Ct",
    "sg:city":"Lakewood",
    "sg:classifiers":[
        {
            "category":"Professional",
            "type":"Services"
        }
    ],
    "sg:phone":"+1   ",
    "sg:postcode":"08701",
    "sg:province":"NJ",
    "wof:name":"O Neill L",
    "wof:placetype":"venue"
},
  "geometry": {"coordinates":[-74.165758,40.035091],"type":"Point"}
}