{
  "type": "Feature",
  "properties": {
    "iso:country":"US",
    "sg:address":"1368 Clinton Ave",
    "sg:city":"Irvington",
    "sg:classifiers":[
        {
            "category":"Restaurant",
            "type":"Food & Drink"
        }
    ],
    "sg:phone":"+1   ",
    "sg:postcode":"07111",
    "sg:province":"NJ",
    "sg:tags":[
        "eating"
    ],
    "wof:name":"Bouillon Fille",
    "wof:placetype":"venue"
},
  "geometry": {"coordinates":[-74.238715,40.729191],"type":"Point"}
}