{
  "type": "Feature",
  "properties": {
    "iso:country":"US",
    "sg:address":"671 3rd St",
    "sg:city":"Newark",
    "sg:classifiers":[
        {
            "category":"Building & Trades",
            "subcategory":"Plumbing",
            "type":"Services"
        }
    ],
    "sg:phone":"+1 973 481 5550",
    "sg:postcode":"07107",
    "sg:province":"NJ",
    "sg:tags":[
        "metalwork",
        "sheet",
        "mfg"
    ],
    "wof:name":"Airmet Inc",
    "wof:placetype":"venue"
},
  "geometry": {"coordinates":[-74.178117,40.769626],"type":"Point"}
}