{
  "type": "Feature",
  "properties": {
    "addr:full":"1625 E 2nd St Scotch Plains NJ 07076",
    "addr:housenumber":"1625",
    "addr:postcode":"07076",
    "addr:street":"E 2Nd St",
    "iso:country":"US",
    "sg:address":"1625 E 2nd St",
    "sg:city":"Scotch Plains",
    "sg:classifiers":[
        {
            "category":"Food & Beverages",
            "subcategory":"Specialty",
            "type":"Retail Goods"
        }
    ],
    "sg:phone":"+1   ",
    "sg:postcode":"07076",
    "sg:province":"NJ",
    "wof:name":"Autumn Harvest Health Foods",
    "wof:placetype":"venue"
},
  "geometry": {"coordinates":[-74.401005,40.644317],"type":"Point"}
}