{
  "type": "Feature",
  "properties": {
    "iso:country":"US",
    "sg:address":"674 Mountain View Rd",
    "sg:city":"Washington",
    "sg:classifiers":[
        {
            "category":"Travel",
            "subcategory":"Travel Agent",
            "type":"Entertainment"
        }
    ],
    "sg:phone":"+1 908 689 0971",
    "sg:postcode":"07882",
    "sg:province":"NJ",
    "sg:tags":[
        "tours",
        "promoter"
    ],
    "wof:name":"Blue Army Tours",
    "wof:placetype":"venue"
},
  "geometry": {"coordinates":[-75.00340799999999,40.728625],"type":"Point"}
}