{
  "type": "Feature",
  "properties": {
    "iso:country":"US",
    "sg:address":"28 Union Ave",
    "sg:city":"Manasquan",
    "sg:classifiers":[
        {
            "category":"Social Services",
            "type":"Services"
        }
    ],
    "sg:phone":"+1 732 223 1477",
    "sg:postcode":"08736",
    "sg:province":"NJ",
    "sg:tags":[
        "counselor",
        "marriage",
        "family"
    ],
    "wof:name":"Rosemarie D Poverman",
    "wof:placetype":"venue"
},
  "geometry": {"coordinates":[-74.049897,40.1207],"type":"Point"}
}