{
  "type": "Feature",
  "properties": {
    "iso:country":"US",
    "sg:address":"8 Lennon Pl",
    "sg:city":"Clifton",
    "sg:classifiers":[
        {
            "category":"Wholesale",
            "subcategory":"Electrical",
            "type":"Manufacturing & Wholesale Goods"
        }
    ],
    "sg:phone":"+1 973 778 0149",
    "sg:postcode":"07013",
    "sg:province":"NJ",
    "sg:tags":[
        "equipment"
    ],
    "wof:name":"International Components Inc",
    "wof:placetype":"venue"
},
  "geometry": {"coordinates":[-74.18007900000001,40.863236],"type":"Point"}
}