{
  "type": "Feature",
  "properties": {
    "iso:country":"US",
    "sg:address":"1 Center St",
    "sg:city":"Newark",
    "sg:classifiers":[
        {
            "category":"Professional",
            "subcategory":"Management & Consulting",
            "type":"Services"
        }
    ],
    "sg:phone":"+1 888 466 5722",
    "sg:postcode":"07102",
    "sg:province":"NJ",
    "sg:tags":[
        "marketing",
        "program",
        "performing",
        "art"
    ],
    "sg:website":"www.njpac.org",
    "wof:name":"New Jersey Performing Arts Center",
    "wof:placetype":"venue"
},
  "geometry": {"coordinates":[-74.16788,40.739693],"type":"Point"}
}