{
  "type": "Feature",
  "properties": {
    "addr:full":"151 Westfield Ave Clark NJ 07066",
    "addr:housenumber":"151",
    "addr:postcode":"07066",
    "addr:street":"Westfield Ave",
    "iso:country":"US",
    "sg:address":"151 Westfield Ave",
    "sg:city":"Clark",
    "sg:classifiers":[
        {
            "category":"Wholesale",
            "subcategory":"Electrical",
            "type":"Manufacturing & Wholesale Goods"
        },
        {
            "category":"Professional",
            "subcategory":"Computer Services",
            "type":"Services"
        }
    ],
    "sg:phone":"+1 732 388 5285",
    "sg:postcode":"07066",
    "sg:province":"NJ",
    "sg:tags":[
        "wholesaler",
        "communications"
    ],
    "wof:name":"Lan Wan Systems Inc",
    "wof:placetype":"venue"
},
  "geometry": {"coordinates":[-74.300487,40.62066],"type":"Point"}
}