{
  "type": "Feature",
  "properties": {
    "iso:country":"US",
    "sg:address":"1285 Wellington Ave",
    "sg:city":"Teaneck",
    "sg:classifiers":[
        {
            "category":"Professional",
            "subcategory":"Management & Consulting",
            "type":"Services"
        }
    ],
    "sg:phone":"+1 201 287 0789",
    "sg:postcode":"07666",
    "sg:province":"NJ",
    "sg:tags":[
        "consultant"
    ],
    "wof:name":"Edward Susman Consulting",
    "wof:placetype":"venue"
},
  "geometry": {"coordinates":[-74.017368,40.902209],"type":"Point"}
}