{
  "type": "Feature",
  "properties": {
    "iso:country":"US",
    "sg:address":"219 Laurel Rd",
    "sg:city":"Voorhees",
    "sg:classifiers":[
        {
            "category":"Real Estate",
            "subcategory":"Real Estate Operator",
            "type":"Services"
        }
    ],
    "sg:phone":"+1   ",
    "sg:postcode":"08043",
    "sg:province":"NJ",
    "sg:tags":[
        "building",
        "apartment"
    ],
    "wof:name":"Echelon Towers",
    "wof:placetype":"venue"
},
  "geometry": {"coordinates":[-75.000028,39.84917],"type":"Point"}
}