{
  "type": "Feature",
  "properties": {
    "iso:country":"US",
    "sg:address":"75 W Pleasant Ave",
    "sg:city":"Maywood",
    "sg:classifiers":[
        {
            "category":"Professional",
            "type":"Services"
        }
    ],
    "sg:phone":"+1 201 843 7466",
    "sg:postcode":"07607",
    "sg:province":"NJ",
    "sg:tags":[
        "information",
        "bureau"
    ],
    "wof:name":"Stone & Webster Inc",
    "wof:placetype":"venue"
},
  "geometry": {"coordinates":[-74.06361699999999,40.905213],"type":"Point"}
}