{
  "type": "Feature",
  "properties": {
    "iso:country":"US",
    "sg:address":"55 State Rte 15",
    "sg:city":"Lake Hopatcong",
    "sg:classifiers":[
        {
            "category":"Autos & Motor Vehicles",
            "subcategory":"Fuel & Gas Station",
            "type":"Retail Goods"
        }
    ],
    "sg:phone":"+1 973 537 6808",
    "sg:postcode":"07801",
    "sg:province":"NJ",
    "sg:tags":[
        "oil"
    ],
    "wof:name":"Shell Oil Co Inc",
    "wof:placetype":"venue"
},
  "geometry": {"coordinates":[-74.556104,40.887132],"type":"Point"}
}