{
  "type": "Feature",
  "properties": {
    "addr:full":"1093 US Hwy 9 Old Bridge NJ 08857",
    "addr:housenumber":"1093",
    "addr:postcode":"08857",
    "addr:street":"Us Hwy 9",
    "iso:country":"US",
    "sg:address":"1093 US Hwy 9",
    "sg:city":"Old Bridge",
    "sg:classifiers":[
        {
            "category":"Shopping",
            "subcategory":"Clothing, Apparel, & Fashions",
            "type":"Retail Goods"
        }
    ],
    "sg:phone":"+1   ",
    "sg:postcode":"08857",
    "sg:province":"NJ",
    "wof:name":"Joyce Leslie Inc",
    "wof:placetype":"venue"
},
  "geometry": {"coordinates":[-74.297116,40.453729],"type":"Point"}
}