{
  "type": "Feature",
  "properties": {
    "iso:country":"US",
    "sg:address":"201 Franklin Ave",
    "sg:city":"Oakland",
    "sg:classifiers":[
        {
            "category":"Organizations",
            "subcategory":"Religious Organization",
            "type":"Services"
        }
    ],
    "sg:phone":"+1 201 337 8917",
    "sg:postcode":"07436",
    "sg:province":"NJ",
    "sg:tags":[
        "clergy"
    ],
    "wof:name":"John Minnema",
    "wof:placetype":"venue"
},
  "geometry": {"coordinates":[-74.220416,41.026523],"type":"Point"}
}