{
  "type": "Feature",
  "properties": {
    "iso:country":"US",
    "sg:address":"1518 W 3rd St",
    "sg:city":"Plainfield",
    "sg:classifiers":[
        {
            "category":"Organizations",
            "subcategory":"Religious Organization",
            "type":"Services"
        }
    ],
    "sg:phone":"+1 908 757 2666",
    "sg:postcode":"07063",
    "sg:province":"NJ",
    "sg:tags":[
        "church"
    ],
    "wof:name":"Evangelical Tabernacle",
    "wof:placetype":"venue"
},
  "geometry": {"coordinates":[-74.448635,40.597549],"type":"Point"}
}