{
  "type": "Feature",
  "properties": {
    "iso:country":"US",
    "sg:address":"1358 Teaneck Rd",
    "sg:city":"Teaneck",
    "sg:classifiers":[
        {
            "category":"Personal",
            "subcategory":"Beauty Salon",
            "type":"Services"
        }
    ],
    "sg:phone":"+1 201 871 1827",
    "sg:postcode":"07666",
    "sg:province":"NJ",
    "sg:tags":[
        "hair"
    ],
    "wof:name":"Ana Beauty Salon",
    "wof:placetype":"venue"
},
  "geometry": {"coordinates":[-74.000355,40.89861],"type":"Point"}
}