{
  "type": "Feature",
  "properties": {
    "addr:full":"208 Piermont Rd Closter NJ 07624",
    "addr:housenumber":"208",
    "addr:postcode":"07624",
    "addr:street":"Piermont Rd",
    "iso:country":"US",
    "sg:address":"208 Piermont Rd",
    "sg:city":"Closter",
    "sg:classifiers":[
        {
            "category":"Restaurant",
            "type":"Food & Drink"
        }
    ],
    "sg:phone":"+1   ",
    "sg:postcode":"07624",
    "sg:province":"NJ",
    "sg:tags":[
        "korean",
        "bar"
    ],
    "wof:name":"Serock Korean Steak House",
    "wof:placetype":"venue"
},
  "geometry": {"coordinates":[-73.944901,40.976777],"type":"Point"}
}