{
  "type": "Feature",
  "properties": {
    "addr:full":"666 Mill St Belleville NJ 07109",
    "addr:housenumber":"666",
    "addr:postcode":"07109",
    "addr:street":"Mill St",
    "iso:country":"US",
    "sg:address":"666 Mill St",
    "sg:city":"Belleville",
    "sg:classifiers":[
        {
            "category":"Government",
            "subcategory":"Fire Station",
            "type":"Public Place"
        }
    ],
    "sg:phone":"+1   ",
    "sg:postcode":"07109",
    "sg:province":"NJ",
    "sg:tags":[
        "protection"
    ],
    "wof:name":"Fire Department",
    "wof:placetype":"venue"
},
  "geometry": {"coordinates":[-74.17804,40.792009],"type":"Point"}
}