{
  "type": "Feature",
  "properties": {
    "addr:full":"1020 Woodlane Rd Beverly NJ 08010",
    "addr:housenumber":"1020",
    "addr:postcode":"08010",
    "addr:street":"Woodlane Rd",
    "iso:country":"US",
    "sg:address":"1020 Woodlane Rd",
    "sg:city":"Beverly",
    "sg:classifiers":[
        {
            "category":"Retail",
            "subcategory":"Laundry & Dry Cleaning",
            "type":"Services"
        }
    ],
    "sg:phone":"+1 609 877 9708",
    "sg:postcode":"08010",
    "sg:province":"NJ",
    "sg:tags":[
        "garment",
        "agent"
    ],
    "wof:name":"Orange Plaza Cleaners",
    "wof:placetype":"venue"
},
  "geometry": {"coordinates":[-74.89477599999999,40.052681],"type":"Point"}
}