{
  "type": "Feature",
  "properties": {
    "addr:full":"2806 Kathleen Ter Union NJ 07083",
    "addr:housenumber":"2806",
    "addr:postcode":"07083",
    "addr:street":"Kathleen Ter",
    "iso:country":"US",
    "sg:address":"2806 Kathleen Ter",
    "sg:city":"Union",
    "sg:classifiers":[
        {
            "category":"Professional",
            "subcategory":"Management & Consulting",
            "type":"Services"
        }
    ],
    "sg:phone":"+1   ",
    "sg:postcode":"07083",
    "sg:province":"NJ",
    "sg:tags":[
        "consultant",
        "financial"
    ],
    "wof:name":"Henry C Green Jr",
    "wof:placetype":"venue"
},
  "geometry": {"coordinates":[-74.29342699999999,40.712822],"type":"Point"}
}