{
  "type": "Feature",
  "properties": {
    "iso:country":"US",
    "sg:address":"220 Prospect St",
    "sg:city":"East Orange",
    "sg:classifiers":[
        {
            "category":"Real Estate",
            "subcategory":"Real Estate Operator",
            "type":"Services"
        }
    ],
    "sg:phone":"+1 973 674 0802",
    "sg:postcode":"07017",
    "sg:province":"NJ",
    "sg:tags":[
        "apartment"
    ],
    "wof:name":"Pavilion Senior Citizens",
    "wof:placetype":"venue"
},
  "geometry": {"coordinates":[-74.206802,40.770802],"type":"Point"}
}