{
  "type": "Feature",
  "properties": {
    "iso:country":"US",
    "sg:address":"39 Harding Ave",
    "sg:city":"Clifton",
    "sg:classifiers":[
        {
            "category":"Arts & Performance",
            "subcategory":"Arts Center",
            "type":"Entertainment"
        }
    ],
    "sg:phone":"+1 973 779 4466",
    "sg:postcode":"07011",
    "sg:province":"NJ",
    "sg:tags":[
        "performing"
    ],
    "sg:website":"www.continentaldance.info",
    "wof:name":"Continental Dance Clubs",
    "wof:placetype":"venue"
},
  "geometry": {"coordinates":[-74.140232,40.876028],"type":"Point"}
}