{
  "type": "Feature",
  "properties": {
    "iso:country":"US",
    "sg:address":"112 Centre Blvd",
    "sg:city":"Marlton",
    "sg:classifiers":[
        {
            "category":"Banks & Credit Unions",
            "subcategory":"Investment Brokerage",
            "type":"Services"
        },
        {
            "category":"Professional",
            "subcategory":"Management & Consulting",
            "type":"Services"
        },
        {
            "category":"Insurance",
            "subcategory":"Insurance Agent",
            "type":"Services"
        }
    ],
    "sg:phone":"+1 856 596 4700",
    "sg:postcode":"08053",
    "sg:province":"NJ",
    "sg:tags":[
        "consultant",
        "financial"
    ],
    "wof:name":"Financial Resources Network",
    "wof:placetype":"venue"
},
  "geometry": {"coordinates":[-74.930075,39.891451],"type":"Point"}
}