{
  "type": "Feature",
  "properties": {
    "iso:country":"US",
    "sg:address":"3 Crown Plz",
    "sg:city":"Hazlet",
    "sg:classifiers":[
        {
            "category":"Manufacturing",
            "subcategory":"Tools & Machinery",
            "type":"Manufacturing & Wholesale Goods"
        }
    ],
    "sg:phone":"+1 732 203 9300",
    "sg:postcode":"07730",
    "sg:province":"NJ",
    "sg:tags":[
        "mfg",
        "industrial",
        "motherboards",
        "panel"
    ],
    "sg:website":"www.aaeon.com",
    "wof:name":"Aaeon Electronics Inc",
    "wof:placetype":"venue"
},
  "geometry": {"coordinates":[-74.15857099999999,40.420384],"type":"Point"}
}