{
  "type": "Feature",
  "properties": {
    "iso:country":"US",
    "sg:address":"434 Co Rd 513",
    "sg:city":"Califon",
    "sg:classifiers":[
        {
            "category":"Health Services",
            "subcategory":"Health Practitioner",
            "type":"Services"
        }
    ],
    "sg:phone":"+1   ",
    "sg:postcode":"07830",
    "sg:province":"NJ",
    "wof:name":"Personal Touch By Debbie",
    "wof:placetype":"venue"
},
  "geometry": {"coordinates":[-74.84463,40.726338],"type":"Point"}
}