{
  "type": "Feature",
  "properties": {
    "addr:full":"625 Main St Lumberton NJ 08048",
    "addr:housenumber":"625",
    "addr:postcode":"08048",
    "addr:street":"Main St",
    "iso:country":"US",
    "sg:address":"625 Main St",
    "sg:city":"Lumberton",
    "sg:classifiers":[
        {
            "category":"Home & Garden",
            "subcategory":"Home Furnishings",
            "type":"Retail Goods"
        }
    ],
    "sg:phone":"+1 609 518 0300",
    "sg:postcode":"08048",
    "sg:province":"NJ",
    "sg:tags":[
        "mirror"
    ],
    "wof:name":"Mirrors Unlimited",
    "wof:placetype":"venue"
},
  "geometry": {"coordinates":[-74.80457800000001,39.967411],"type":"Point"}
}