{
  "type": "Feature",
  "properties": {
    "addr:full":"591 College Blvd Wenonah NJ 08090",
    "addr:housenumber":"591",
    "addr:postcode":"08090",
    "addr:street":"College Blvd",
    "iso:country":"US",
    "sg:address":"591 College Blvd",
    "sg:city":"Wenonah",
    "sg:classifiers":[
        {
            "category":"Building & Trades",
            "subcategory":"Landscaping Services",
            "type":"Services"
        }
    ],
    "sg:phone":"+1 856 468 5749",
    "sg:postcode":"08090",
    "sg:province":"NJ",
    "sg:tags":[
        "lawn",
        "designer",
        "consultant",
        "contractor",
        "landscape",
        "maintenance",
        "gardener"
    ],
    "wof:name":"Ehrmann's Landscaping & Lawn Service",
    "wof:placetype":"venue"
},
  "geometry": {"coordinates":[-75.15836299999999,39.803251],"type":"Point"}
}