{
  "type": "Feature",
  "properties": {
    "addr:full":"27 Hamiltonian Apartment Middlesex NJ 08846",
    "addr:housenumber":"27;apartment",
    "addr:postcode":"08846",
    "addr:street":"Middlesex",
    "iso:country":"US",
    "sg:address":"27 Hamiltonian Apartment",
    "sg:city":"Middlesex",
    "sg:classifiers":[
        {
            "category":"Real Estate",
            "subcategory":"Real Estate Agent",
            "type":"Services"
        }
    ],
    "sg:phone":"+1 732 968 8209",
    "sg:postcode":"08846",
    "sg:province":"NJ",
    "wof:name":"Frieman Realty",
    "wof:placetype":"venue"
},
  "geometry": {"coordinates":[-74.47656600000001,40.586446],"type":"Point"}
}