{
  "type": "Feature",
  "properties": {
    "iso:country":"US",
    "sg:address":"12 Beryl Ct",
    "sg:city":"Kendall Park",
    "sg:classifiers":[
        {
            "category":"Professional",
            "subcategory":"Art Services",
            "type":"Services"
        }
    ],
    "sg:phone":"+1   ",
    "sg:postcode":"08824",
    "sg:province":"NJ",
    "sg:tags":[
        "photography",
        "commercial"
    ],
    "wof:name":"Model Connection On Line The",
    "wof:placetype":"venue"
},
  "geometry": {"coordinates":[-74.562979,40.412985],"type":"Point"}
}