{
  "type": "Feature",
  "properties": {
    "addr:full":"189 6th St Saddle Brook NJ 07663",
    "addr:housenumber":"189",
    "addr:postcode":"07663",
    "addr:street":"6Th St",
    "iso:country":"US",
    "sg:address":"189 6th St",
    "sg:city":"Saddle Brook",
    "sg:classifiers":[
        {
            "category":"Personal",
            "type":"Services"
        }
    ],
    "sg:phone":"+1 201 291 9222",
    "sg:postcode":"07663",
    "sg:province":"NJ",
    "wof:name":"Beach Bum Tanning",
    "wof:placetype":"venue"
},
  "geometry": {"coordinates":[-74.09797500000001,40.890908],"type":"Point"}
}