{
  "type": "Feature",
  "properties": {
    "iso:country":"US",
    "sg:address":"18 Church St",
    "sg:city":"Penns Grove",
    "sg:classifiers":[
        {
            "category":"Social Services",
            "type":"Services"
        }
    ],
    "sg:phone":"+1 856 299 1296",
    "sg:postcode":"08069",
    "sg:province":"NJ",
    "sg:tags":[
        "organization",
        "welfare"
    ],
    "wof:name":"Catholic Charities",
    "wof:placetype":"venue"
},
  "geometry": {"coordinates":[-75.47218100000001,39.725345],"type":"Point"}
}