{
  "type": "Feature",
  "properties": {
    "addr:full":"140 Monroe St Garfield NJ 07026",
    "addr:housenumber":"140",
    "addr:postcode":"07026",
    "addr:street":"Monroe St",
    "iso:country":"US",
    "sg:address":"140 Monroe St",
    "sg:city":"Garfield",
    "sg:classifiers":[
        {
            "category":"Communications",
            "subcategory":"Newspaper",
            "type":"Services"
        }
    ],
    "sg:phone":"+1 973 253 1207",
    "sg:postcode":"07026",
    "sg:province":"NJ",
    "sg:tags":[
        "print",
        "medium"
    ],
    "wof:name":"Pass Point Inc",
    "wof:placetype":"venue"
},
  "geometry": {"coordinates":[-74.10556800000001,40.870212],"type":"Point"}
}