{
  "type": "Feature",
  "properties": {
    "iso:country":"US",
    "sg:address":"11009 Lincoln Dr W",
    "sg:city":"Marlton",
    "sg:classifiers":[
        {
            "category":"Health Services",
            "subcategory":"Doctor",
            "type":"Services"
        }
    ],
    "sg:phone":"+1 856 985 9851",
    "sg:postcode":"08053",
    "sg:province":"NJ",
    "sg:tags":[
        "medical"
    ],
    "wof:name":"Allen J Rubin MD",
    "wof:placetype":"venue"
},
  "geometry": {"coordinates":[-74.935458,39.902579],"type":"Point"}
}