{
  "type": "Feature",
  "properties": {
    "iso:country":"US",
    "sg:address":"560 Springfield Ave",
    "sg:city":"Westfield",
    "sg:classifiers":[
        {
            "category":"Manufacturing",
            "subcategory":"Motor Vehicles & Parts",
            "type":"Manufacturing & Wholesale Goods"
        }
    ],
    "sg:phone":"+1 973 589 4876",
    "sg:postcode":"07090",
    "sg:province":"NJ",
    "sg:tags":[
        "automobile",
        "supply"
    ],
    "wof:name":"George Ulanet Co",
    "wof:placetype":"venue"
},
  "geometry": {"coordinates":[-74.33147599999999,40.675315],"type":"Point"}
}