{
  "type": "Feature",
  "properties": {
    "addr:full":"148 Bloomfield Ave Verona NJ 07044",
    "addr:housenumber":"148",
    "addr:postcode":"07044",
    "addr:street":"Bloomfield Ave",
    "iso:country":"US",
    "sg:address":"148 Bloomfield Ave",
    "sg:city":"Verona",
    "sg:classifiers":[
        {
            "category":"Restaurant",
            "type":"Food & Drink"
        }
    ],
    "sg:phone":"+1 973 571 1499",
    "sg:postcode":"07044",
    "sg:province":"NJ",
    "wof:name":"EDO2",
    "wof:placetype":"venue"
},
  "geometry": {"coordinates":[-74.232213,40.825568],"type":"Point"}
}