{
  "type": "Feature",
  "properties": {
    "addr:full":"39 Central Ave East Newark NJ 07029",
    "addr:housenumber":"39",
    "addr:postcode":"07029",
    "addr:street":"Central Ave",
    "iso:country":"US",
    "sg:address":"39 Central Ave",
    "sg:city":"East Newark",
    "sg:classifiers":[
        {
            "category":"Manufacturing",
            "subcategory":"Retail Goods",
            "type":"Manufacturing & Wholesale Goods"
        },
        {
            "category":"Manufacturing",
            "subcategory":"Tobacco Products",
            "type":"Manufacturing & Wholesale Goods"
        }
    ],
    "sg:phone":"+1 973 483 0795",
    "sg:postcode":"07029",
    "sg:province":"NJ",
    "sg:tags":[
        "smoking",
        "accessory",
        "moistener",
        "mfg"
    ],
    "wof:name":"Aztec Clay Moistener Co Inc",
    "wof:placetype":"venue"
},
  "geometry": {"coordinates":[-74.162156,40.750573],"type":"Point"}
}