{
  "type": "Feature",
  "properties": {
    "iso:country":"US",
    "sg:address":"77 Hudson St.",
    "sg:city":"Jersey City",
    "sg:classifiers":[
        {
            "category":"Real Estate",
            "subcategory":"Real Estate Services",
            "type":"Services"
        }
    ],
    "sg:phone":"+1 201 433 2609",
    "sg:postcode":"07302",
    "sg:province":"NJ",
    "sg:website":"www.77Hudson.com",
    "wof:name":"77 Hudson",
    "wof:placetype":"venue"
},
  "geometry": {"coordinates":[-74.034901,40.712901],"type":"Point"}
}