{
  "type": "Feature",
  "properties": {
    "addr:full":"44 Boonton Ave Butler NJ 07405",
    "addr:housenumber":"44",
    "addr:postcode":"07405",
    "addr:street":"Boonton Ave",
    "iso:country":"US",
    "sg:address":"44 Boonton Ave",
    "sg:city":"Butler",
    "sg:classifiers":[
        {
            "category":"Retail",
            "subcategory":"Laundry & Dry Cleaning",
            "type":"Services"
        }
    ],
    "sg:phone":"+1 973 838 1062",
    "sg:postcode":"07405",
    "sg:province":"NJ",
    "sg:tags":[
        "drycleaning",
        "plant"
    ],
    "wof:name":"Classic Cleaners",
    "wof:placetype":"venue"
},
  "geometry": {"coordinates":[-74.34200300000001,41.000301],"type":"Point"}
}