{
  "type": "Feature",
  "properties": {
    "iso:country":"US",
    "sg:address":"20 Corkery Ln",
    "sg:city":"Williamstown",
    "sg:classifiers":[
        {
            "category":"Social Services",
            "type":"Services"
        }
    ],
    "sg:phone":"+1 856 629 8477",
    "sg:postcode":"08094",
    "sg:province":"NJ",
    "wof:name":"Sunny Estates",
    "wof:placetype":"venue"
},
  "geometry": {"coordinates":[-75.007751,39.67028],"type":"Point"}
}