{
  "type": "Feature",
  "properties": {
    "addr:full":"1001 Newark Ave Elizabeth NJ 07208",
    "addr:housenumber":"1001",
    "addr:postcode":"07208",
    "addr:street":"Newark Ave",
    "iso:country":"US",
    "sg:address":"1001 Newark Ave",
    "sg:city":"Elizabeth",
    "sg:classifiers":[
        {
            "category":"Wholesale",
            "subcategory":"Hardware",
            "type":"Manufacturing & Wholesale Goods"
        }
    ],
    "sg:phone":"+1 908 354 8758",
    "sg:postcode":"07208",
    "sg:province":"NJ",
    "sg:tags":[
        "tool"
    ],
    "wof:name":"Delancey Streetcom Inc",
    "wof:placetype":"venue"
},
  "geometry": {"coordinates":[-74.204092,40.687836],"type":"Point"}
}