{
  "type": "Feature",
  "properties": {
    "iso:country":"US",
    "sg:address":"27 Oregon Ave",
    "sg:city":"Jackson",
    "sg:classifiers":[
        {
            "category":"Utilities",
            "subcategory":"Telephone",
            "type":"Services"
        }
    ],
    "sg:phone":"+1 732 886 5717",
    "sg:postcode":"08527",
    "sg:province":"NJ",
    "sg:tags":[
        "communications"
    ],
    "wof:name":"J&K Assoc",
    "wof:placetype":"venue"
},
  "geometry": {"coordinates":[-74.252179,40.117256],"type":"Point"}
}