{
  "type": "Feature",
  "properties": {
    "iso:country":"US",
    "sg:address":"272 Changebridge Rd",
    "sg:city":"Pine Brook",
    "sg:classifiers":[
        {
            "category":"Health Services",
            "subcategory":"Dentist",
            "type":"Services"
        }
    ],
    "sg:phone":"+1 973 227 1888",
    "sg:postcode":"07058",
    "sg:province":"NJ",
    "wof:name":"Sudol Thomas DDS",
    "wof:placetype":"venue"
},
  "geometry": {"coordinates":[-74.358091,40.86999],"type":"Point"}
}