{
  "type": "Feature",
  "properties": {
    "iso:country":"US",
    "sg:address":"60 Riverview Dr",
    "sg:city":"Wayne",
    "sg:classifiers":[
        {
            "category":"Autos & Motor Vehicles",
            "subcategory":"Fuel & Gas Station",
            "type":"Retail Goods"
        }
    ],
    "sg:phone":"+1 973 872 0084",
    "sg:postcode":"07470",
    "sg:province":"NJ",
    "sg:tags":[
        "oil"
    ],
    "wof:name":"Shell Of Wayne",
    "wof:placetype":"venue"
},
  "geometry": {"coordinates":[-74.242166,40.9134],"type":"Point"}
}