{
  "type": "Feature",
  "properties": {
    "iso:country":"US",
    "sg:address":"198 Green Pond Rd",
    "sg:city":"Rockaway",
    "sg:classifiers":[
        {
            "category":"Shopping",
            "type":"Retail Goods"
        }
    ],
    "sg:phone":"+1   ",
    "sg:postcode":"07866",
    "sg:province":"NJ",
    "sg:tags":[
        "medical",
        "component"
    ],
    "wof:name":"R & S Medical LLC",
    "wof:placetype":"venue"
},
  "geometry": {"coordinates":[-74.49000100000001,40.933879],"type":"Point"}
}