{
  "type": "Feature",
  "properties": {
    "addr:full":"177 Main St West Orange NJ 07052",
    "addr:housenumber":"177",
    "addr:postcode":"07052",
    "addr:street":"Main St",
    "iso:country":"US",
    "sg:address":"177 Main St",
    "sg:city":"West Orange",
    "sg:classifiers":[
        {
            "category":"Real Estate",
            "subcategory":"Real Estate Agent",
            "type":"Services"
        }
    ],
    "sg:phone":"+1 973 736 8822",
    "sg:postcode":"07052",
    "sg:province":"NJ",
    "sg:tags":[
        "management"
    ],
    "wof:name":"Hillside Industrial Ctr Realty",
    "wof:placetype":"venue"
},
  "geometry": {"coordinates":[-74.235378,40.782748],"type":"Point"}
}