{
  "type": "Feature",
  "properties": {
    "iso:country":"US",
    "sg:address":"61 Captains Dr",
    "sg:city":"Brick",
    "sg:classifiers":[
        {
            "category":"Building & Trades",
            "subcategory":"Construction",
            "type":"Services"
        }
    ],
    "sg:phone":"+1 732 920 1816",
    "sg:postcode":"08723",
    "sg:province":"NJ",
    "sg:tags":[
        "general",
        "contractor"
    ],
    "wof:name":"P D Construction",
    "wof:placetype":"venue"
},
  "geometry": {"coordinates":[-74.11759000000001,40.02477],"type":"Point"}
}