{
  "type": "Feature",
  "properties": {
    "addr:full":"345 US Hwy 206 Bridgewater NJ 08807",
    "addr:housenumber":"345",
    "addr:postcode":"08807",
    "addr:street":"Us Hwy 206",
    "iso:country":"US",
    "sg:address":"345 US Hwy 206",
    "sg:city":"Bridgewater",
    "sg:classifiers":[
        {
            "category":"Shopping",
            "subcategory":"Stationery & Office Supplies",
            "type":"Retail Goods"
        },
        {
            "category":"Home & Garden",
            "subcategory":"Furniture",
            "type":"Retail Goods"
        }
    ],
    "sg:phone":"+1 908 725 7733",
    "sg:postcode":"08807",
    "sg:province":"NJ",
    "wof:name":"Office Max",
    "wof:placetype":"venue"
},
  "geometry": {"coordinates":[-74.622067,40.582477],"type":"Point"}
}