{
  "type": "Feature",
  "properties": {
    "addr:full":"12 Thornton Pl Clifton NJ 07012",
    "addr:housenumber":"12",
    "addr:postcode":"07012",
    "addr:street":"Thornton Pl",
    "iso:country":"US",
    "sg:address":"12 Thornton Pl",
    "sg:city":"Clifton",
    "sg:classifiers":[
        {
            "category":"Wholesale",
            "subcategory":"Electrical",
            "type":"Manufacturing & Wholesale Goods"
        }
    ],
    "sg:phone":"+1 973 489 2300",
    "sg:postcode":"07012",
    "sg:province":"NJ",
    "sg:tags":[
        "transmission",
        "equipment",
        "power"
    ],
    "wof:name":"Gp Industrial Distributors LLC",
    "wof:placetype":"venue"
},
  "geometry": {"coordinates":[-74.168632,40.853069],"type":"Point"}
}