{
  "type": "Feature",
  "properties": {
    "iso:country":"US",
    "sg:address":"1770 Hooper Ave",
    "sg:city":"Toms River",
    "sg:classifiers":[
        {
            "category":"Manufacturing",
            "subcategory":"Paper Products",
            "type":"Manufacturing & Wholesale Goods"
        }
    ],
    "sg:phone":"+1 732 239 3668",
    "sg:postcode":"08753",
    "sg:province":"NJ",
    "sg:tags":[
        "die",
        "mfg"
    ],
    "wof:name":"Rhino Linings Of Toms River",
    "wof:placetype":"venue"
},
  "geometry": {"coordinates":[-74.147457,40.009826],"type":"Point"}
}