{
  "type": "Feature",
  "properties": {
    "iso:country":"US",
    "sg:address":"600 Main St",
    "sg:city":"Hackensack",
    "sg:classifiers":[
        {
            "category":"Food & Beverages",
            "subcategory":"Liquor & Beverages",
            "type":"Retail Goods"
        }
    ],
    "sg:phone":"+1 201 487 3000",
    "sg:postcode":"07601",
    "sg:province":"NJ",
    "sg:tags":[
        "beer",
        "spirit",
        "wine"
    ],
    "wof:name":"Packard's Fine Wines & Spirits Shops",
    "wof:placetype":"venue"
},
  "geometry": {"coordinates":[-74.03980300000001,40.8969],"type":"Point"}
}