{
  "type": "Feature",
  "properties": {
    "addr:full":"2000 Route 38 Ste 1775 Cherry Hill NJ 08002",
    "addr:housenumber":"2000",
    "addr:postcode":"08002",
    "addr:street":"Route 38 Ste 1775",
    "iso:country":"US",
    "sg:address":"2000 Route 38 Ste 1775",
    "sg:city":"Cherry Hill",
    "sg:classifiers":[
        {
            "category":"Shopping",
            "subcategory":"Clothing, Apparel, & Fashions",
            "type":"Retail Goods"
        }
    ],
    "sg:phone":"+1 856 488 5660",
    "sg:postcode":"08002",
    "sg:province":"NJ",
    "sg:tags":[
        "accessory",
        "clothing",
        "women's"
    ],
    "wof:name":"Bcbg Max Azria",
    "wof:placetype":"venue"
},
  "geometry": {"coordinates":[-75.02535899999999,39.938986],"type":"Point"}
}