{
  "type": "Feature",
  "properties": {
    "iso:country":"US",
    "sg:address":"1430 Saint Georges Ave",
    "sg:city":"Avenel",
    "sg:classifiers":[
        {
            "category":"Autos & Motor Vehicles",
            "subcategory":"Auto Supplies",
            "type":"Retail Goods"
        }
    ],
    "sg:phone":"+1 732 381 0100",
    "sg:postcode":"07001",
    "sg:province":"NJ",
    "sg:tags":[
        "tire"
    ],
    "sg:website":"www.bfgoodrichtires.com",
    "wof:name":"Atlantic Tire & Supply Co Inc",
    "wof:placetype":"venue"
},
  "geometry": {"coordinates":[-74.291298,40.5872],"type":"Point"}
}