{
  "type": "Feature",
  "properties": {
    "iso:country":"US",
    "sg:address":"170 Boulevard",
    "sg:city":"Mountain Lakes",
    "sg:classifiers":[
        {
            "category":"Wholesale",
            "subcategory":"Chemicals & Plastics",
            "type":"Manufacturing & Wholesale Goods"
        },
        {
            "category":"Wholesale",
            "subcategory":"Scrap",
            "type":"Manufacturing & Wholesale Goods"
        }
    ],
    "sg:phone":"+1 973 316 9152",
    "sg:postcode":"07046",
    "sg:province":"NJ",
    "sg:tags":[
        "distributor",
        "whole"
    ],
    "sg:website":"www.lakelandpolymers.com",
    "wof:name":"Lakeland Polymers LLC",
    "wof:placetype":"venue"
},
  "geometry": {"coordinates":[-74.43755,40.895368],"type":"Point"}
}