{
  "type": "Feature",
  "properties": {
    "addr:full":"804 Bloomfield Ave Caldwell NJ 07006",
    "addr:housenumber":"804",
    "addr:postcode":"07006",
    "addr:street":"Bloomfield Ave",
    "iso:country":"US",
    "sg:address":"804 Bloomfield Ave",
    "sg:city":"Caldwell",
    "sg:classifiers":[
        {
            "category":"Professional",
            "subcategory":"Business Services",
            "type":"Services"
        }
    ],
    "sg:phone":"+1   ",
    "sg:postcode":"07006",
    "sg:province":"NJ",
    "wof:name":"Panera Cafe",
    "wof:placetype":"venue"
},
  "geometry": {"coordinates":[-74.297701,40.850989],"type":"Point"}
}