{
  "type": "Feature",
  "properties": {
    "iso:country":"US",
    "sg:address":"745 River St",
    "sg:city":"Paterson",
    "sg:classifiers":[
        {
            "category":"Shopping",
            "subcategory":"Hobbies, Toys, & Games",
            "type":"Retail Goods"
        },
        {
            "category":"Building & Trades",
            "subcategory":"Construction",
            "type":"Services"
        }
    ],
    "sg:phone":"+1 973 684 4647",
    "sg:postcode":"07524",
    "sg:province":"NJ",
    "sg:tags":[
        "designer",
        "wholesale",
        "poo",
        "dealer",
        "pool",
        "swimming"
    ],
    "wof:name":"Joe Ordini's",
    "wof:placetype":"venue"
},
  "geometry": {"coordinates":[-74.151252,40.938047],"type":"Point"}
}