{
  "type": "Feature",
  "properties": {
    "iso:country":"US",
    "sg:address":"590 Stelton Rd",
    "sg:city":"Piscataway",
    "sg:classifiers":[
        {
            "category":"Retail",
            "subcategory":"Repair Shop",
            "type":"Services"
        }
    ],
    "sg:phone":"+1   ",
    "sg:postcode":"08854",
    "sg:province":"NJ",
    "wof:name":"A24 All Day Emergency A Locksm",
    "wof:placetype":"venue"
},
  "geometry": {"coordinates":[-74.441047,40.559641],"type":"Point"}
}