{
  "type": "Feature",
  "properties": {
    "addr:full":"21 Smith St Englewood NJ 07631",
    "addr:housenumber":"21",
    "addr:postcode":"07631",
    "addr:street":"Smith St",
    "iso:country":"US",
    "sg:address":"21 Smith St",
    "sg:city":"Englewood",
    "sg:classifiers":[
        {
            "category":"Manufacturing",
            "subcategory":"Printing",
            "type":"Manufacturing & Wholesale Goods"
        }
    ],
    "sg:phone":"+1 212 594 7057",
    "sg:postcode":"07631",
    "sg:province":"NJ",
    "sg:tags":[
        "publisher"
    ],
    "wof:name":"German Language Publications",
    "wof:placetype":"venue"
},
  "geometry": {"coordinates":[-73.98336500000001,40.885385],"type":"Point"}
}