{
  "type": "Feature",
  "properties": {
    "iso:country":"US",
    "sg:address":"43 Stoneham Dr",
    "sg:city":"Delran",
    "sg:classifiers":[
        {
            "category":"Home & Garden",
            "subcategory":"Carpets & Floor Coverings",
            "type":"Retail Goods"
        },
        {
            "category":"Shopping",
            "subcategory":"Gifts & Souvenirs",
            "type":"Retail Goods"
        }
    ],
    "sg:phone":"+1 856 824 0212",
    "sg:postcode":"08075",
    "sg:province":"NJ",
    "sg:tags":[
        "shop"
    ],
    "wof:name":"Second Floor Studio",
    "wof:placetype":"venue"
},
  "geometry": {"coordinates":[-74.925979,40.017183],"type":"Point"}
}