{
  "type": "Feature",
  "properties": {
    "addr:full":"29 Warren Dr Parsippany NJ 07054",
    "addr:housenumber":"29",
    "addr:postcode":"07054",
    "addr:street":"Warren Dr",
    "iso:country":"US",
    "sg:address":"29 Warren Dr",
    "sg:city":"Parsippany",
    "sg:classifiers":[
        {
            "category":"Building & Trades",
            "subcategory":"Electrical",
            "type":"Services"
        }
    ],
    "sg:phone":"+1 973 560 9828",
    "sg:postcode":"07054",
    "sg:province":"NJ",
    "sg:tags":[
        "electric",
        "contractor"
    ],
    "wof:name":"Dury Electric Co",
    "wof:placetype":"venue"
},
  "geometry": {"coordinates":[-74.44217,40.850971],"type":"Point"}
}