{
  "type": "Feature",
  "properties": {
    "iso:country":"US",
    "sg:address":"1610 State Route 23",
    "sg:city":"Wayne",
    "sg:classifiers":[
        {
            "category":"Restaurant",
            "type":"Food & Drink"
        }
    ],
    "sg:phone":"+1 973 686 9001",
    "sg:postcode":"07470",
    "sg:province":"NJ",
    "sg:website":"www.wildnoodles.com",
    "wof:name":"Wild Noodles",
    "wof:placetype":"venue"
},
  "geometry": {"coordinates":[-74.243202,40.88205],"type":"Point"}
}