{
  "type": "Feature",
  "properties": {
    "addr:full":"45 New York Ave Newark NJ 07105",
    "addr:housenumber":"45",
    "addr:postcode":"07105",
    "addr:street":"New York Ave",
    "iso:country":"US",
    "sg:address":"45 New York Ave",
    "sg:city":"Newark",
    "sg:classifiers":[
        {
            "category":"Wholesale",
            "subcategory":"Durable Goods & Equipment",
            "type":"Manufacturing & Wholesale Goods"
        }
    ],
    "sg:phone":"+1 973 344 7748",
    "sg:postcode":"07105",
    "sg:province":"NJ",
    "wof:name":"Pinto Trading Corp",
    "wof:placetype":"venue"
},
  "geometry": {"coordinates":[-74.170366,40.728383],"type":"Point"}
}