{
  "type": "Feature",
  "properties": {
    "iso:country":"US",
    "sg:address":"553 State Rte 94",
    "sg:city":"Newton",
    "sg:classifiers":[
        {
            "category":"Professional",
            "subcategory":"Engineering",
            "type":"Services"
        }
    ],
    "sg:phone":"+1 973 300 1677",
    "sg:postcode":"07860",
    "sg:province":"NJ",
    "sg:tags":[
        "construction"
    ],
    "wof:name":"Gegenheimer Construction Inc",
    "wof:placetype":"venue"
},
  "geometry": {"coordinates":[-74.843385,41.015175],"type":"Point"}
}