{
  "type": "Feature",
  "properties": {
    "iso:country":"US",
    "sg:address":"1400 Parkway Ave",
    "sg:city":"Ewing",
    "sg:classifiers":[
        {
            "category":"Restaurant",
            "type":"Food & Drink"
        },
        {
            "category":"Bakery",
            "type":"Food & Drink"
        },
        {
            "category":"Food & Beverages",
            "subcategory":"Groceries & Convenience Stores",
            "type":"Retail Goods"
        }
    ],
    "sg:phone":"+1 609 771 8550",
    "sg:postcode":"08628",
    "sg:province":"NJ",
    "sg:tags":[
        "pretzel"
    ],
    "sg:website":"http://www.phillypretzelfactoryewing.com",
    "wof:name":"Philly Pretzel Factory",
    "wof:placetype":"venue"
},
  "geometry": {"coordinates":[-74.80617100000001,40.265902],"type":"Point"}
}