{
  "type": "Feature",
  "properties": {
    "addr:full":"5716 Berkshire Valley Rd Oak Ridge NJ 07438",
    "addr:housenumber":"5716",
    "addr:postcode":"07438",
    "addr:street":"Berkshire Valley Rd",
    "iso:country":"US",
    "sg:address":"5716 Berkshire Valley Rd",
    "sg:city":"Oak Ridge",
    "sg:classifiers":[
        {
            "category":"Professional",
            "subcategory":"Management & Consulting",
            "type":"Services"
        }
    ],
    "sg:phone":"+1 973 208 5387",
    "sg:postcode":"07438",
    "sg:province":"NJ",
    "sg:tags":[
        "consultant",
        "business"
    ],
    "wof:name":"Azarian Management",
    "wof:placetype":"venue"
},
  "geometry": {"coordinates":[-74.507087,41.034846],"type":"Point"}
}