{
  "type": "Feature",
  "properties": {
    "addr:full":"161 New Rd Montague NJ 07827",
    "addr:housenumber":"161",
    "addr:postcode":"07827",
    "addr:street":"New Rd",
    "iso:country":"US",
    "sg:address":"161 New Rd",
    "sg:city":"Montague",
    "sg:classifiers":[
        {
            "category":"Fast Food",
            "type":"Food & Drink"
        },
        {
            "category":"Restaurant",
            "type":"Food & Drink"
        }
    ],
    "sg:phone":"+1 973 293 8310",
    "sg:postcode":"07827",
    "sg:province":"NJ",
    "sg:tags":[
        "chicken"
    ],
    "wof:name":"Kfc",
    "wof:placetype":"venue"
},
  "geometry": {"coordinates":[-74.775745,41.278323],"type":"Point"}
}