{
  "type": "Feature",
  "properties": {
    "iso:country":"US",
    "sg:address":"36 Watchung Ave",
    "sg:city":"Plainfield",
    "sg:classifiers":[
        {
            "category":"Restaurant",
            "type":"Food & Drink"
        }
    ],
    "sg:phone":"+1   ",
    "sg:postcode":"07060",
    "sg:province":"NJ",
    "sg:tags":[
        "vietnamese"
    ],
    "wof:name":"Quyen Restaurant",
    "wof:placetype":"venue"
},
  "geometry": {"coordinates":[-74.42253100000001,40.620378],"type":"Point"}
}