{
  "type": "Feature",
  "properties": {
    "iso:country":"US",
    "sg:address":"51 Hanover Rd",
    "sg:city":"East Hanover",
    "sg:classifiers":[
        {
            "category":"Wholesale",
            "subcategory":"Computers",
            "type":"Manufacturing & Wholesale Goods"
        }
    ],
    "sg:phone":"+1 973 887 3040",
    "sg:postcode":"07936",
    "sg:province":"NJ",
    "sg:tags":[
        "software"
    ],
    "wof:name":"AVS Training",
    "wof:placetype":"venue"
},
  "geometry": {"coordinates":[-74.37123,40.800469],"type":"Point"}
}