{
  "type": "Feature",
  "properties": {
    "addr:full":"727 State Rte 15 Lake Hopatcong NJ 07849",
    "addr:housenumber":"727",
    "addr:postcode":"07849",
    "addr:street":"State Rte 15",
    "iso:country":"US",
    "sg:address":"727 State Rte 15",
    "sg:city":"Lake Hopatcong",
    "sg:classifiers":[
        {
            "category":"Autos & Motor Vehicles",
            "subcategory":"Auto Supplies",
            "type":"Retail Goods"
        }
    ],
    "sg:phone":"+1 973 663 3110",
    "sg:postcode":"07849",
    "sg:province":"NJ",
    "sg:tags":[
        "automobile",
        "parts"
    ],
    "wof:name":"BAS Auto Parts",
    "wof:placetype":"venue"
},
  "geometry": {"coordinates":[-74.597337,40.959055],"type":"Point"}
}