{
  "type": "Feature",
  "properties": {
    "addr:full":"6 Karyn Ct Westwood NJ 07675",
    "addr:housenumber":"6",
    "addr:postcode":"07675",
    "addr:street":"Karyn Ct",
    "iso:country":"US",
    "sg:address":"6 Karyn Ct",
    "sg:city":"Westwood",
    "sg:classifiers":[
        {
            "category":"Building & Trades",
            "subcategory":"Construction",
            "type":"Services"
        }
    ],
    "sg:phone":"+1 201 767 0117",
    "sg:postcode":"07675",
    "sg:province":"NJ",
    "sg:tags":[
        "house"
    ],
    "wof:name":"Arpaca Craftsmen",
    "wof:placetype":"venue"
},
  "geometry": {"coordinates":[-73.968084,41.017582],"type":"Point"}
}