{
  "type": "Feature",
  "properties": {
    "addr:full":"11 Redwood Ln Ringwood NJ 07456",
    "addr:housenumber":"11",
    "addr:postcode":"07456",
    "addr:street":"Redwood Ln",
    "iso:country":"US",
    "sg:address":"11 Redwood Ln",
    "sg:city":"Ringwood",
    "sg:classifiers":[
        {
            "category":"Professional",
            "subcategory":"Management & Consulting",
            "type":"Services"
        }
    ],
    "sg:phone":"+1 973 616 1325",
    "sg:postcode":"07456",
    "sg:province":"NJ",
    "sg:tags":[
        "business"
    ],
    "wof:name":"American Chamber Orchestra",
    "wof:placetype":"venue"
},
  "geometry": {"coordinates":[-74.25869400000001,41.068149],"type":"Point"}
}