{
  "type": "Feature",
  "properties": {
    "iso:country":"US",
    "sg:address":"144 Kearny Ave",
    "sg:city":"Kearny",
    "sg:classifiers":[
        {
            "category":"Freight",
            "type":"Transportation"
        }
    ],
    "sg:phone":"+1 201 955 4403",
    "sg:postcode":"07032",
    "sg:province":"NJ",
    "sg:tags":[
        "trucking"
    ],
    "wof:name":"Fernandez Transport",
    "wof:placetype":"venue"
},
  "geometry": {"coordinates":[-74.153441,40.757296],"type":"Point"}
}