{
  "type": "Feature",
  "properties": {
    "iso:country":"US",
    "sg:address":"1179 E Landis Ave",
    "sg:city":"Vineland",
    "sg:classifiers":[
        {
            "category":"Professional",
            "subcategory":"Lawyer & Legal Services",
            "type":"Services"
        }
    ],
    "sg:phone":"+1 856 405 0900",
    "sg:postcode":"08360",
    "sg:province":"NJ",
    "wof:name":"Mitchell S Berman LLC",
    "wof:placetype":"venue"
},
  "geometry": {"coordinates":[-75.00279399999999,39.485015],"type":"Point"}
}