{
  "type": "Feature",
  "properties": {
    "iso:country":"US",
    "sg:address":"6524 Ventnor Ave",
    "sg:city":"Ventnor City",
    "sg:classifiers":[
        {
            "category":"Shopping",
            "subcategory":"Bicycles & Sporting Goods",
            "type":"Retail Goods"
        }
    ],
    "sg:phone":"+1 609 823 2000",
    "sg:postcode":"08406",
    "sg:province":"NJ",
    "sg:tags":[
        "surfboard"
    ],
    "wof:name":"Surf Shack",
    "wof:placetype":"venue"
},
  "geometry": {"coordinates":[-74.484086,39.337224],"type":"Point"}
}