{
  "type": "Feature",
  "properties": {
    "iso:country":"US",
    "sg:address":"31 Mulberry St",
    "sg:city":"Newark",
    "sg:classifiers":[
        {
            "category":"Organizations",
            "subcategory":"Religious Organization",
            "type":"Services"
        }
    ],
    "sg:phone":"+1 973 622 4306",
    "sg:postcode":"07102",
    "sg:province":"NJ",
    "sg:tags":[
        "church"
    ],
    "sg:website":"www.dioceseofnewark.org",
    "wof:name":"Diocese Of Newark Protestant",
    "wof:placetype":"venue"
},
  "geometry": {"coordinates":[-74.1681,40.736625],"type":"Point"}
}