{
  "type": "Feature",
  "properties": {
    "addr:full":"26 Pine Blvd Lakewood NJ 08701",
    "addr:housenumber":"26",
    "addr:postcode":"08701",
    "addr:street":"Pine Blvd",
    "iso:country":"US",
    "sg:address":"26 Pine Blvd",
    "sg:city":"Lakewood",
    "sg:classifiers":[
        {
            "category":"Health Services",
            "subcategory":"Medical Lab",
            "type":"Services"
        }
    ],
    "sg:phone":"+1 732 905 8555",
    "sg:postcode":"08701",
    "sg:province":"NJ",
    "sg:tags":[
        "laboratory"
    ],
    "sg:website":"www.diagnostichealth.com",
    "wof:name":"Diagnostic Health Systems Inc",
    "wof:placetype":"venue"
},
  "geometry": {"coordinates":[-74.219931,40.065641],"type":"Point"}
}