{
  "type": "Feature",
  "properties": {
    "addr:full":"4201 Church Rd Mt Laurel NJ 08054",
    "addr:housenumber":"4201",
    "addr:postcode":"08054",
    "addr:street":"Church Rd",
    "iso:country":"US",
    "sg:address":"4201 Church Rd",
    "sg:city":"Mt Laurel",
    "sg:classifiers":[
        {
            "category":"Freight",
            "type":"Transportation"
        },
        {
            "category":"Professional",
            "subcategory":"Business Services",
            "type":"Services"
        }
    ],
    "sg:phone":"+1 856 234 6262",
    "sg:postcode":"08054",
    "sg:province":"NJ",
    "sg:tags":[
        "packaging"
    ],
    "wof:name":"Mail Express",
    "wof:placetype":"venue"
},
  "geometry": {"coordinates":[-74.94402100000001,39.922157],"type":"Point"}
}