{
  "type": "Feature",
  "properties": {
    "addr:full":"1990 Swarthmore Ave Lakewood NJ 08701",
    "addr:housenumber":"1990",
    "addr:postcode":"08701",
    "addr:street":"Swarthmore Ave",
    "iso:country":"US",
    "sg:address":"1990 Swarthmore Ave",
    "sg:city":"Lakewood",
    "sg:classifiers":[
        {
            "category":"Professional",
            "subcategory":"Computer Services",
            "type":"Services"
        }
    ],
    "sg:phone":"+1 732 370 8840",
    "sg:postcode":"08701",
    "sg:province":"NJ",
    "sg:tags":[
        "processing",
        "datum"
    ],
    "sg:website":"www.dpfdata.com",
    "wof:name":"DPF",
    "wof:placetype":"venue"
},
  "geometry": {"coordinates":[-74.168848,40.071709],"type":"Point"}
}