{
  "type": "Feature",
  "properties": {
    "addr:full":"1210 Eagles Chase Dr Trenton NJ 08648",
    "addr:housenumber":"1210",
    "addr:postcode":"08648",
    "addr:street":"Eagles Chase Dr",
    "iso:country":"US",
    "sg:address":"1210 Eagles Chase Dr",
    "sg:city":"Trenton",
    "sg:classifiers":[
        {
            "category":"Professional",
            "type":"Services"
        }
    ],
    "sg:phone":"+1   ",
    "sg:postcode":"08648",
    "sg:province":"NJ",
    "wof:name":"Visconto Wahl LLC",
    "wof:placetype":"venue"
},
  "geometry": {"coordinates":[-74.710359,40.277274],"type":"Point"}
}