{
  "type": "Feature",
  "properties": {
    "addr:full":"36 Yorkshire Dr Hackettstown NJ 07840",
    "addr:housenumber":"36",
    "addr:postcode":"07840",
    "addr:street":"Yorkshire Dr",
    "iso:country":"US",
    "sg:address":"36 Yorkshire Dr",
    "sg:city":"Hackettstown",
    "sg:classifiers":[
        {
            "category":"Building & Trades",
            "subcategory":"Construction",
            "type":"Services"
        }
    ],
    "sg:phone":"+1 908 850 4995",
    "sg:postcode":"07840",
    "sg:province":"NJ",
    "sg:tags":[
        "roofing",
        "contractor"
    ],
    "wof:name":"Barry Roofing Co Inc",
    "wof:placetype":"venue"
},
  "geometry": {"coordinates":[-74.787387,40.847006],"type":"Point"}
}