{
  "type": "Feature",
  "properties": {
    "addr:full":"10 Stanford Pl Princeton NJ 08550",
    "addr:housenumber":"10",
    "addr:postcode":"08550",
    "addr:street":"Stanford Pl",
    "iso:country":"US",
    "sg:address":"10 Stanford Pl",
    "sg:city":"Princeton",
    "sg:classifiers":[
        {
            "category":"Professional",
            "subcategory":"Computer Services",
            "type":"Services"
        }
    ],
    "sg:phone":"+1 212 965 5353",
    "sg:postcode":"08550",
    "sg:province":"NJ",
    "sg:tags":[
        "consulting",
        "sales"
    ],
    "wof:name":"Most Networks Inc",
    "wof:placetype":"venue"
},
  "geometry": {"coordinates":[-74.615831,40.29244],"type":"Point"}
}