{
  "type": "Feature",
  "properties": {
    "iso:country":"US",
    "sg:address":"64 W Somerset St",
    "sg:city":"Raritan",
    "sg:classifiers":[
        {
            "category":"Personal",
            "subcategory":"Beauty Salon",
            "type":"Services"
        }
    ],
    "sg:phone":"+1 908 203 0100",
    "sg:postcode":"08869",
    "sg:province":"NJ",
    "sg:tags":[
        "shop"
    ],
    "wof:name":"Nail Art",
    "wof:placetype":"venue"
},
  "geometry": {"coordinates":[-74.636511,40.566647],"type":"Point"}
}