{
  "type": "Feature",
  "properties": {
    "iso:country":"US",
    "sg:address":"558 W Broad St",
    "sg:city":"Westfield",
    "sg:classifiers":[
        {
            "category":"Social Services",
            "type":"Services"
        }
    ],
    "sg:phone":"+1   ",
    "sg:postcode":"07090",
    "sg:province":"NJ",
    "sg:tags":[
        "agency"
    ],
    "wof:name":"Westfield Community Ctr Assn",
    "wof:placetype":"venue"
},
  "geometry": {"coordinates":[-74.355756,40.644492],"type":"Point"}
}