{
  "type": "Feature",
  "properties": {
    "addr:full":"1205 Berlin Rd Cherry Hill NJ 08034",
    "addr:housenumber":"1205",
    "addr:postcode":"08034",
    "addr:street":"Berlin Rd",
    "iso:country":"US",
    "sg:address":"1205 Berlin Rd",
    "sg:city":"Cherry Hill",
    "sg:classifiers":[
        {
            "category":"Organizations",
            "subcategory":"Membership Organization",
            "type":"Services"
        },
        {
            "category":"Organizations",
            "subcategory":"Professional Association",
            "type":"Services"
        }
    ],
    "sg:phone":"+1 856 429 9823",
    "sg:postcode":"08034",
    "sg:province":"NJ",
    "wof:name":"West Jersey Masonic Assoc",
    "wof:placetype":"venue"
},
  "geometry": {"coordinates":[-75.010789,39.881923],"type":"Point"}
}