{
  "type": "Feature",
  "properties": {
    "iso:country":"US",
    "sg:address":"711 Delsea Dr N",
    "sg:city":"Glassboro",
    "sg:classifiers":[
        {
            "category":"Autos & Motor Vehicles",
            "subcategory":"Auto Supplies",
            "type":"Retail Goods"
        }
    ],
    "sg:phone":"+1 856 218 0025",
    "sg:postcode":"08028",
    "sg:province":"NJ",
    "sg:tags":[
        "automobile",
        "parts"
    ],
    "sg:website":"www.pepboys.com",
    "wof:name":"Pep Boys Supercenter",
    "wof:placetype":"venue"
},
  "geometry": {"coordinates":[-75.11527,39.721454],"type":"Point"}
}