{
  "type": "Feature",
  "properties": {
    "iso:country":"US",
    "sg:address":"653 Westwood Ave",
    "sg:city":"Westwood",
    "sg:classifiers":[
        {
            "category":"Banks & Credit Unions",
            "subcategory":"Bank",
            "type":"Services"
        }
    ],
    "sg:phone":"+1   ",
    "sg:postcode":"07675",
    "sg:province":"NJ",
    "sg:tags":[
        "savings",
        "institution"
    ],
    "wof:name":"West Essex Bank",
    "wof:placetype":"venue"
},
  "geometry": {"coordinates":[-74.007369,40.994744],"type":"Point"}
}