{
  "type": "Feature",
  "properties": {
    "iso:country":"US",
    "sg:address":"1545 US RT 206 First Floor",
    "sg:city":"Bedminster",
    "sg:classifiers":[
        {
            "category":"Professional",
            "subcategory":"Computer Services",
            "type":"Services"
        }
    ],
    "sg:phone":"+1 866 352 7481",
    "sg:postcode":"07921",
    "sg:province":"NJ",
    "sg:website":"http://www.gettinghired.com/",
    "wof:name":"GettingHired",
    "wof:placetype":"venue"
},
  "geometry": {"coordinates":[-74.64987000000001,40.679182],"type":"Point"}
}