{
  "type": "Feature",
  "properties": {
    "iso:country":"US",
    "sg:address":"1054 N Broad St",
    "sg:city":"Hillside",
    "sg:classifiers":[
        {
            "category":"Freight",
            "type":"Transportation"
        }
    ],
    "sg:phone":"+1 908 353 1682",
    "sg:postcode":"07205",
    "sg:province":"NJ",
    "sg:tags":[
        "hauling",
        "trucking"
    ],
    "wof:name":"Grm Trucking LLC",
    "wof:placetype":"venue"
},
  "geometry": {"coordinates":[-74.214821,40.688105],"type":"Point"}
}