{
  "type": "Feature",
  "properties": {
    "iso:country":"US",
    "sg:address":"110 Larch Ave",
    "sg:city":"Bogota",
    "sg:classifiers":[
        {
            "category":"Professional",
            "type":"Services"
        }
    ],
    "sg:phone":"+1 201 883 1624",
    "sg:postcode":"07603",
    "sg:province":"NJ",
    "sg:tags":[
        "establishment"
    ],
    "wof:name":"Fed Ex Trade Networks",
    "wof:placetype":"venue"
},
  "geometry": {"coordinates":[-74.032437,40.871531],"type":"Point"}
}