{
  "type": "Feature",
  "properties": {
    "iso:country":"US",
    "sg:address":"33 Lincoln Park",
    "sg:city":"Newark",
    "sg:classifiers":[
        {
            "category":"Real Estate",
            "subcategory":"Real Estate Operator",
            "type":"Services"
        }
    ],
    "sg:phone":"+1   ",
    "sg:postcode":"07102",
    "sg:province":"NJ",
    "sg:tags":[
        "property",
        "company",
        "management"
    ],
    "wof:name":"Lincoln Park Towers",
    "wof:placetype":"venue"
},
  "geometry": {"coordinates":[-74.178567,40.727033],"type":"Point"}
}