{
  "type": "Feature",
  "properties": {
    "iso:country":"US",
    "sg:address":"3600 Bergenline Ave",
    "sg:city":"Union City",
    "sg:classifiers":[
        {
            "category":"Professional",
            "subcategory":"Accounting & Tax Preparation",
            "type":"Services"
        }
    ],
    "sg:phone":"+1 201 867 8400",
    "sg:postcode":"07087",
    "sg:province":"NJ",
    "sg:tags":[
        "accountant"
    ],
    "wof:name":"Velazquez Rolando Public Accountant",
    "wof:placetype":"venue"
},
  "geometry": {"coordinates":[-74.03299699999999,40.7668],"type":"Point"}
}