{
  "type": "Feature",
  "properties": {
    "addr:full":"50 Engle St Englewood NJ 07631",
    "addr:housenumber":"50",
    "addr:postcode":"07631",
    "addr:street":"Engle St",
    "iso:country":"US",
    "sg:address":"50 Engle St",
    "sg:city":"Englewood",
    "sg:classifiers":[
        {
            "category":"Professional",
            "type":"Services"
        }
    ],
    "sg:phone":"+1 201 568 2158",
    "sg:postcode":"07631",
    "sg:province":"NJ",
    "sg:tags":[
        "establishment"
    ],
    "wof:name":"France Com Inc",
    "wof:placetype":"venue"
},
  "geometry": {"coordinates":[-73.972267,40.89434],"type":"Point"}
}