{
  "type": "Feature",
  "properties": {
    "addr:full":"15 Warren St Hackensack NJ 07601",
    "addr:housenumber":"15",
    "addr:postcode":"07601",
    "addr:street":"Warren St",
    "iso:country":"US",
    "sg:address":"15 Warren St",
    "sg:city":"Hackensack",
    "sg:classifiers":[
        {
            "category":"Professional",
            "type":"Services"
        }
    ],
    "sg:phone":"+1 201 487 0311",
    "sg:postcode":"07601",
    "sg:province":"NJ",
    "sg:tags":[
        "establishment"
    ],
    "wof:name":"Feltz Associates",
    "wof:placetype":"venue"
},
  "geometry": {"coordinates":[-74.04544,40.881415],"type":"Point"}
}