{
  "type": "Feature",
  "properties": {
    "iso:country":"US",
    "sg:address":"1016 Stuyvesant Ave",
    "sg:city":"Union",
    "sg:classifiers":[
        {
            "category":"Building & Trades",
            "subcategory":"Construction",
            "type":"Services"
        }
    ],
    "sg:phone":"+1 908 688 6500",
    "sg:postcode":"07083",
    "sg:province":"NJ",
    "sg:tags":[
        "bathroom",
        "remodeling"
    ],
    "wof:name":"Designer Bathrooms & Kitchens",
    "wof:placetype":"venue"
},
  "geometry": {"coordinates":[-74.270551,40.695866],"type":"Point"}
}