{
  "type": "Feature",
  "properties": {
    "addr:full":"19 Karen St Kendall Park NJ 08824",
    "addr:housenumber":"19",
    "addr:postcode":"08824",
    "addr:street":"Karen St",
    "iso:country":"US",
    "sg:address":"19 Karen St",
    "sg:city":"Kendall Park",
    "sg:classifiers":[
        {
            "category":"Professional",
            "subcategory":"Management & Consulting",
            "type":"Services"
        }
    ],
    "sg:phone":"+1   ",
    "sg:postcode":"08824",
    "sg:province":"NJ",
    "wof:name":"Ellen T Miller",
    "wof:placetype":"venue"
},
  "geometry": {"coordinates":[-74.52880399999999,40.439005],"type":"Point"}
}