{
  "type": "Feature",
  "properties": {
    "iso:country":"US",
    "sg:address":"109 N Main St",
    "sg:city":"Pleasantville",
    "sg:classifiers":[
        {
            "category":"Professional",
            "subcategory":"Computer Services",
            "type":"Services"
        }
    ],
    "sg:phone":"+1 609 407 0007",
    "sg:postcode":"08232",
    "sg:province":"NJ",
    "sg:tags":[
        "home",
        "consulting",
        "page",
        "dev",
        "internet"
    ],
    "wof:name":"One Find Web Magicicans",
    "wof:placetype":"venue"
},
  "geometry": {"coordinates":[-74.52043,39.394153],"type":"Point"}
}