{
  "type": "Feature",
  "properties": {
    "addr:full":"81 Montclair Ave Paterson NJ 07503",
    "addr:housenumber":"81",
    "addr:postcode":"07503",
    "addr:street":"Montclair Ave",
    "iso:country":"US",
    "sg:address":"81 Montclair Ave",
    "sg:city":"Paterson",
    "sg:classifiers":[
        {
            "category":"Retail",
            "subcategory":"Auto Repair",
            "type":"Services"
        }
    ],
    "sg:phone":"+1 973 279 1414",
    "sg:postcode":"07503",
    "sg:province":"NJ",
    "sg:tags":[
        "repairing",
        "automobile"
    ],
    "wof:name":"Abe Auto Repair",
    "wof:placetype":"venue"
},
  "geometry": {"coordinates":[-74.163101,40.893398],"type":"Point"}
}