{
  "type": "Feature",
  "properties": {
    "addr:full":"58 Brown Ave Springfield NJ 07081",
    "addr:housenumber":"58",
    "addr:postcode":"07081",
    "addr:street":"Brown Ave",
    "iso:country":"US",
    "sg:address":"58 Brown Ave",
    "sg:city":"Springfield",
    "sg:classifiers":[
        {
            "category":"Health Services",
            "subcategory":"Doctor",
            "type":"Services"
        }
    ],
    "sg:phone":"+1   ",
    "sg:postcode":"07081",
    "sg:province":"NJ",
    "sg:tags":[
        "outpatient",
        "facility"
    ],
    "wof:name":"Social Club House",
    "wof:placetype":"venue"
},
  "geometry": {"coordinates":[-74.316323,40.690639],"type":"Point"}
}