{
  "type": "Feature",
  "properties": {
    "addr:full":"220 Stuyvesant Ave Lyndhurst NJ 07071",
    "addr:housenumber":"220",
    "addr:postcode":"07071",
    "addr:street":"Stuyvesant Ave",
    "iso:country":"US",
    "sg:address":"220 Stuyvesant Ave",
    "sg:city":"Lyndhurst",
    "sg:classifiers":[
        {
            "category":"Personal",
            "subcategory":"Beauty Salon",
            "type":"Services"
        }
    ],
    "sg:phone":"+1 201 842 8889",
    "sg:postcode":"07071",
    "sg:province":"NJ",
    "sg:tags":[
        "nail",
        "manicuring"
    ],
    "wof:name":"Tiffany Nail Salon",
    "wof:placetype":"venue"
},
  "geometry": {"coordinates":[-74.125101,40.815477],"type":"Point"}
}