{
  "type": "Feature",
  "properties": {
    "addr:full":"877 W Park Ave Asbury Park NJ 07712",
    "addr:housenumber":"877",
    "addr:postcode":"07712",
    "addr:street":"W Park Ave Asbury",
    "iso:country":"US",
    "sg:address":"877 W Park Ave",
    "sg:city":"Asbury Park",
    "sg:classifiers":[
        {
            "category":"Professional",
            "subcategory":"Management & Consulting",
            "type":"Services"
        }
    ],
    "sg:phone":"+1 732 380 9111",
    "sg:postcode":"07712",
    "sg:province":"NJ",
    "wof:name":"Vehicle Management Services",
    "wof:placetype":"venue"
},
  "geometry": {"coordinates":[-74.046076,40.263449],"type":"Point"}
}