{
  "type": "Feature",
  "properties": {
    "addr:full":"501 9th St. Hoboken NJ 07030",
    "addr:housenumber":"501",
    "addr:postcode":"07030",
    "addr:street":"9Th St.",
    "iso:country":"US",
    "sg:address":"501 9th St.",
    "sg:city":"Hoboken",
    "sg:classifiers":[
        {
            "category":"Personal",
            "subcategory":"Nail Salon",
            "type":"Services"
        }
    ],
    "sg:phone":"+1 201 459 1555",
    "sg:postcode":"07030",
    "sg:province":"NJ",
    "wof:name":"The Nail Bar",
    "wof:placetype":"venue"
},
  "geometry": {"coordinates":[-74.035256,40.748505],"type":"Point"}
}