{
  "type": "Feature",
  "properties": {
    "iso:country":"US",
    "sg:address":"60 Yahara Ave",
    "sg:city":"Rutherford",
    "sg:classifiers":[
        {
            "category":"Professional",
            "subcategory":"Computer Services",
            "type":"Services"
        }
    ],
    "sg:phone":"+1 201 896 3990",
    "sg:postcode":"07070",
    "sg:province":"NJ",
    "sg:tags":[
        "programing",
        "custom"
    ],
    "wof:name":"L Com Technology Inc",
    "wof:placetype":"venue"
},
  "geometry": {"coordinates":[-74.117952,40.842385],"type":"Point"}
}