{
  "type": "Feature",
  "properties": {
    "iso:country":"US",
    "sg:address":"329 Carolina St",
    "sg:city":"Clark",
    "sg:classifiers":[
        {
            "category":"Shopping",
            "subcategory":"Hobbies, Toys, & Games",
            "type":"Retail Goods"
        }
    ],
    "sg:phone":"+1   ",
    "sg:postcode":"07066",
    "sg:province":"NJ",
    "wof:name":"J&S Ceramics",
    "wof:placetype":"venue"
},
  "geometry": {"coordinates":[-74.313958,40.636251],"type":"Point"}
}