{
  "type": "Feature",
  "properties": {
    "iso:country":"US",
    "sg:address":"1409 Liberty Ave",
    "sg:city":"Hillside",
    "sg:classifiers":[
        {
            "category":"Government",
            "subcategory":"Office",
            "type":"Public Place"
        }
    ],
    "sg:phone":"+1 973 926 3000",
    "sg:postcode":"07205",
    "sg:province":"NJ",
    "sg:tags":[
        "village"
    ],
    "wof:name":"Hillside Township Clerk",
    "wof:placetype":"venue"
},
  "geometry": {"coordinates":[-74.22892400000001,40.701657],"type":"Point"}
}