{
  "type": "Feature",
  "properties": {
    "iso:country":"US",
    "sg:address":"173 Matilda Dr",
    "sg:city":"Manahawkin",
    "sg:classifiers":[
        {
            "category":"Home & Garden",
            "subcategory":"Garden Supply",
            "type":"Retail Goods"
        }
    ],
    "sg:phone":"+1 609 597 7337",
    "sg:postcode":"08050",
    "sg:province":"NJ",
    "sg:tags":[
        "sprinkler"
    ],
    "wof:name":"All Southern Sprinkler",
    "wof:placetype":"venue"
},
  "geometry": {"coordinates":[-74.239822,39.667758],"type":"Point"}
}