{
  "type": "Feature",
  "properties": {
    "addr:full":"4 Charlotte Ter Wayne NJ 07470",
    "addr:housenumber":"4",
    "addr:postcode":"07470",
    "addr:street":"Charlotte Ter",
    "iso:country":"US",
    "sg:address":"4 Charlotte Ter",
    "sg:city":"Wayne",
    "sg:classifiers":[
        {
            "category":"Building & Trades",
            "subcategory":"Cleaning & Sanitation",
            "type":"Services"
        }
    ],
    "sg:phone":"+1   ",
    "sg:postcode":"07470",
    "sg:province":"NJ",
    "sg:tags":[
        "maintenance"
    ],
    "wof:name":"Federal Maintainence",
    "wof:placetype":"venue"
},
  "geometry": {"coordinates":[-74.236935,40.95351],"type":"Point"}
}