{
  "type": "Feature",
  "properties": {
    "addr:full":"400 Paterson Plank Rd Carlstadt NJ 07072",
    "addr:housenumber":"400",
    "addr:postcode":"07072",
    "addr:street":"Paterson Plank Rd",
    "iso:country":"US",
    "sg:address":"400 Paterson Plank Rd",
    "sg:city":"Carlstadt",
    "sg:classifiers":[
        {
            "category":"Shopping",
            "subcategory":"Catalog Store",
            "type":"Retail Goods"
        }
    ],
    "sg:phone":"+1 201 372 9250",
    "sg:postcode":"07072",
    "sg:province":"NJ",
    "sg:tags":[
        "internet"
    ],
    "sg:website":"www.800giftcertificate.com",
    "wof:name":"One Eight Hundred Gift Certif",
    "wof:placetype":"venue"
},
  "geometry": {"coordinates":[-74.065511,40.815821],"type":"Point"}
}