{
  "type": "Feature",
  "properties": {
    "iso:country":"US",
    "sg:address":"256 Cedar Ave",
    "sg:city":"Hackensack",
    "sg:classifiers":[
        {
            "category":"Professional",
            "subcategory":"Computer Services",
            "type":"Services"
        }
    ],
    "sg:phone":"+1 201 488 6820",
    "sg:postcode":"07601",
    "sg:province":"NJ",
    "sg:tags":[
        "development",
        "software"
    ],
    "wof:name":"Data Tech Systems Inc",
    "wof:placetype":"venue"
},
  "geometry": {"coordinates":[-74.050736,40.909479],"type":"Point"}
}