{
  "type": "Feature",
  "properties": {
    "iso:country":"US",
    "sg:address":"3 University Plaza Dr",
    "sg:city":"Hackensack",
    "sg:classifiers":[
        {
            "category":"Professional",
            "subcategory":"Printing & Photocopies",
            "type":"Services"
        }
    ],
    "sg:phone":"+1 201 343 0333",
    "sg:postcode":"07601",
    "sg:province":"NJ",
    "sg:tags":[
        "copying"
    ],
    "wof:name":"Genuine Copies",
    "wof:placetype":"venue"
},
  "geometry": {"coordinates":[-74.03960600000001,40.89601],"type":"Point"}
}