{
  "type": "Feature",
  "properties": {
    "iso:country":"US",
    "sg:address":"205 E 2nd St",
    "sg:city":"Plainfield",
    "sg:classifiers":[
        {
            "category":"Food & Beverages",
            "subcategory":"Meat & Fish",
            "type":"Retail Goods"
        }
    ],
    "sg:phone":"+1 908 756 1656",
    "sg:postcode":"07060",
    "sg:province":"NJ",
    "sg:tags":[
        "seafood"
    ],
    "wof:name":"Pete's Fish Market",
    "wof:placetype":"venue"
},
  "geometry": {"coordinates":[-74.42033000000001,40.620264],"type":"Point"}
}