{
  "type": "Feature",
  "properties": {
    "iso:country":"US",
    "sg:address":"3 Chester Ave",
    "sg:city":"Medford",
    "sg:classifiers":[
        {
            "category":"Building & Trades",
            "subcategory":"Electrical",
            "type":"Services"
        }
    ],
    "sg:phone":"+1 609 654 7790",
    "sg:postcode":"08055",
    "sg:province":"NJ",
    "sg:tags":[
        "electrical",
        "contractor"
    ],
    "wof:name":"Straddick Electric & Systems",
    "wof:placetype":"venue"
},
  "geometry": {"coordinates":[-74.835435,39.898304],"type":"Point"}
}