{
  "type": "Feature",
  "properties": {
    "addr:full":"703 Grand Central Ave Lavallette NJ 08735",
    "addr:housenumber":"703",
    "addr:postcode":"08735",
    "addr:street":"Grand Central Ave",
    "iso:country":"US",
    "sg:address":"703 Grand Central Ave",
    "sg:city":"Lavallette",
    "sg:classifiers":[
        {
            "category":"Shopping",
            "subcategory":"Clothing, Apparel, & Fashions",
            "type":"Retail Goods"
        }
    ],
    "sg:phone":"+1 732 830 1188",
    "sg:postcode":"08735",
    "sg:province":"NJ",
    "sg:tags":[
        "swimwear",
        "accessory"
    ],
    "wof:name":"Martins Casuals",
    "wof:placetype":"venue"
},
  "geometry": {"coordinates":[-74.068483,39.972607],"type":"Point"}
}