{
  "type": "Feature",
  "properties": {
    "addr:full":"127 Durban Ave Hopatcong NJ 07843",
    "addr:housenumber":"127",
    "addr:postcode":"07843",
    "addr:street":"Durban Ave",
    "iso:country":"US",
    "sg:address":"127 Durban Ave",
    "sg:city":"Hopatcong",
    "sg:classifiers":[
        {
            "category":"Professional",
            "subcategory":"Art Services",
            "type":"Services"
        }
    ],
    "sg:phone":"+1 973 398 3776",
    "sg:postcode":"07843",
    "sg:province":"NJ",
    "sg:tags":[
        "commercial",
        "design"
    ],
    "wof:name":"C & J Graphics",
    "wof:placetype":"venue"
},
  "geometry": {"coordinates":[-74.664727,40.930752],"type":"Point"}
}