{
  "type": "Feature",
  "properties": {
    "iso:country":"US",
    "sg:address":"8 Ely Ave",
    "sg:city":"South Amboy",
    "sg:classifiers":[
        {
            "category":"Professional",
            "subcategory":"Computer Services",
            "type":"Services"
        }
    ],
    "sg:phone":"+1   ",
    "sg:postcode":"08879",
    "sg:province":"NJ",
    "sg:tags":[
        "related"
    ],
    "wof:name":"Joe Lopez LLC",
    "wof:placetype":"venue"
},
  "geometry": {"coordinates":[-74.249978,40.446134],"type":"Point"}
}