{
  "type": "Feature",
  "properties": {
    "addr:full":"12 Gordon Ave Lawrenceville NJ 08648",
    "addr:housenumber":"12",
    "addr:postcode":"08648",
    "addr:street":"Gordon Ave",
    "iso:country":"US",
    "sg:address":"12 Gordon Ave",
    "sg:city":"Lawrenceville",
    "sg:classifiers":[
        {
            "category":"Utilities",
            "subcategory":"Water",
            "type":"Services"
        }
    ],
    "sg:phone":"+1 609 896 0919",
    "sg:postcode":"08648",
    "sg:province":"NJ",
    "sg:tags":[
        "company",
        "system",
        "sewage",
        "supply"
    ],
    "wof:name":"Lawrenceville Water Company",
    "wof:placetype":"venue"
},
  "geometry": {"coordinates":[-74.730058,40.298622],"type":"Point"}
}