{
  "type": "Feature",
  "properties": {
    "addr:full":"909 Summit Ave Union City NJ 07087",
    "addr:housenumber":"909",
    "addr:postcode":"07087",
    "addr:street":"Summit Ave",
    "iso:country":"US",
    "sg:address":"909 Summit Ave",
    "sg:city":"Union City",
    "sg:classifiers":[
        {
            "category":"Banks & Credit Unions",
            "subcategory":"Bank",
            "type":"Services"
        }
    ],
    "sg:phone":"+1   ",
    "sg:postcode":"07087",
    "sg:province":"NJ",
    "sg:tags":[
        "mortgage"
    ],
    "wof:name":"Express Mortgage Nationwide In",
    "wof:placetype":"venue"
},
  "geometry": {"coordinates":[-74.043314,40.75903],"type":"Point"}
}