{
  "type": "Feature",
  "properties": {
    "iso:country":"US",
    "sg:address":"299 Inman Ave",
    "sg:city":"Colonia",
    "sg:classifiers":[
        {
            "category":"Arts & Performance",
            "subcategory":"Theater",
            "type":"Entertainment"
        }
    ],
    "sg:phone":"+1 732 574 2518",
    "sg:postcode":"07067",
    "sg:province":"NJ",
    "sg:tags":[
        "magician"
    ],
    "wof:name":"Magic Fountain Of Colonia",
    "wof:placetype":"venue"
},
  "geometry": {"coordinates":[-74.31555,40.599767],"type":"Point"}
}