{
  "type": "Feature",
  "properties": {
    "addr:full":"722 Whitaker Ave Millville NJ 08332",
    "addr:housenumber":"722",
    "addr:postcode":"08332",
    "addr:street":"Whitaker Ave",
    "iso:country":"US",
    "sg:address":"722 Whitaker Ave",
    "sg:city":"Millville",
    "sg:classifiers":[
        {
            "category":"Building & Trades",
            "subcategory":"Construction",
            "type":"Services"
        }
    ],
    "sg:phone":"+1 609 823 0734",
    "sg:postcode":"08332",
    "sg:province":"NJ",
    "sg:tags":[
        "residential",
        "commercial",
        "painting"
    ],
    "wof:name":"D J Painting",
    "wof:placetype":"venue"
},
  "geometry": {"coordinates":[-75.02240999999999,39.416627],"type":"Point"}
}