{
  "type": "Feature",
  "properties": {
    "iso:country":"US",
    "sg:address":"172 Johnson Ave",
    "sg:city":"Hackensack",
    "sg:classifiers":[
        {
            "category":"Retail",
            "subcategory":"Laundry & Dry Cleaning",
            "type":"Services"
        }
    ],
    "sg:phone":"+1   ",
    "sg:postcode":"07601",
    "sg:province":"NJ",
    "sg:tags":[
        "drycleaning",
        "plant",
        "clothing"
    ],
    "sg:website":"www.hallakcleaners.com",
    "wof:name":"Hallak Cleaners",
    "wof:placetype":"venue"
},
  "geometry": {"coordinates":[-74.039863,40.906578],"type":"Point"}
}