{
  "type": "Feature",
  "properties": {
    "addr:full":"158 Rogers Ave Millville NJ 08332",
    "addr:housenumber":"158",
    "addr:postcode":"08332",
    "addr:street":"Rogers Ave",
    "iso:country":"US",
    "sg:address":"158 Rogers Ave",
    "sg:city":"Millville",
    "sg:classifiers":[
        {
            "category":"Banks & Credit Unions",
            "subcategory":"Investment Brokerage",
            "type":"Services"
        }
    ],
    "sg:phone":"+1   ",
    "sg:postcode":"08332",
    "sg:province":"NJ",
    "sg:tags":[
        "advisory"
    ],
    "wof:name":"Burton Financial Services",
    "wof:placetype":"venue"
},
  "geometry": {"coordinates":[-75.146885,39.441291],"type":"Point"}
}