{
  "type": "Feature",
  "properties": {
    "iso:country":"US",
    "sg:address":"9 Patton Pl",
    "sg:city":"Montclair",
    "sg:classifiers":[
        {
            "category":"Recreation",
            "type":"Entertainment"
        }
    ],
    "sg:phone":"+1 973 746 6707",
    "sg:postcode":"07043",
    "sg:province":"NJ",
    "wof:name":"Yoga Mdtation Ctr Montclair Th",
    "wof:placetype":"venue"
},
  "geometry": {"coordinates":[-74.198111,40.852175],"type":"Point"}
}