{
  "type": "Feature",
  "properties": {
    "addr:full":"136 Blackburn Rd Summit NJ 07901",
    "addr:housenumber":"136",
    "addr:postcode":"07901",
    "addr:street":"Blackburn Rd",
    "iso:country":"US",
    "sg:address":"136 Blackburn Rd",
    "sg:city":"Summit",
    "sg:classifiers":[
        {
            "category":"Education",
            "subcategory":"School",
            "type":"Public Place"
        }
    ],
    "sg:phone":"+1 908 277 2613",
    "sg:postcode":"07901",
    "sg:province":"NJ",
    "sg:tags":[
        "high",
        "middle",
        "elementary"
    ],
    "wof:name":"Summit City School District",
    "wof:placetype":"venue"
},
  "geometry": {"coordinates":[-74.375305,40.70942],"type":"Point"}
}