{
  "type": "Feature",
  "properties": {
    "addr:full":"207 Hillcrest Ave Trenton NJ 08618",
    "addr:housenumber":"207",
    "addr:postcode":"08618",
    "addr:street":"Hillcrest Ave",
    "iso:country":"US",
    "sg:address":"207 Hillcrest Ave",
    "sg:city":"Trenton",
    "sg:classifiers":[
        {
            "category":"Social Services",
            "type":"Services"
        }
    ],
    "sg:phone":"+1 609 393 9922",
    "sg:postcode":"08618",
    "sg:province":"NJ",
    "wof:name":"Interfith Crgvers Grter Trnton",
    "wof:placetype":"venue"
},
  "geometry": {"coordinates":[-74.78568799999999,40.24155],"type":"Point"}
}