{
  "type": "Feature",
  "properties": {
    "iso:country":"US",
    "sg:address":"657 Fulton St",
    "sg:city":"Elizabethport",
    "sg:classifiers":[
        {
            "category":"Professional",
            "subcategory":"Detective & Security Services",
            "type":"Services"
        }
    ],
    "sg:phone":"+1 908 353 8028",
    "sg:postcode":"07206",
    "sg:province":"NJ",
    "sg:tags":[
        "information",
        "bureau"
    ],
    "wof:name":"Jose Premier Services",
    "wof:placetype":"venue"
},
  "geometry": {"coordinates":[-74.199057,40.658843],"type":"Point"}
}