{
  "type": "Feature",
  "properties": {
    "iso:country":"US",
    "sg:address":"3001 Hadley Rd",
    "sg:city":"South Plainfield",
    "sg:classifiers":[
        {
            "category":"Freight",
            "type":"Transportation"
        }
    ],
    "sg:phone":"+1 908 791 1009",
    "sg:postcode":"07080",
    "sg:province":"NJ",
    "sg:tags":[
        "delivery"
    ],
    "wof:name":"K & G Delivery Svc Inc",
    "wof:placetype":"venue"
},
  "geometry": {"coordinates":[-74.42389300000001,40.553404],"type":"Point"}
}