{
  "type": "Feature",
  "properties": {
    "iso:country":"US",
    "sg:address":"29 E Price St",
    "sg:city":"Linden",
    "sg:classifiers":[
        {
            "category":"Manufacturing",
            "subcategory":"Food",
            "type":"Manufacturing & Wholesale Goods"
        }
    ],
    "sg:phone":"+1 908 925 9040",
    "sg:postcode":"07036",
    "sg:province":"NJ",
    "sg:tags":[
        "frozen",
        "bakery",
        "product",
        "mfg"
    ],
    "wof:name":"Twin Hens",
    "wof:placetype":"venue"
},
  "geometry": {"coordinates":[-74.250907,40.633814],"type":"Point"}
}