{
  "type": "Feature",
  "properties": {
    "addr:full":"378 S Branch Rd Hillsborough NJ 08844",
    "addr:housenumber":"378",
    "addr:postcode":"08844",
    "addr:street":"S Branch Rd",
    "iso:country":"US",
    "sg:address":"378 S Branch Rd",
    "sg:city":"Hillsborough",
    "sg:classifiers":[
        {
            "category":"Utilities",
            "subcategory":"Cable",
            "type":"Services"
        }
    ],
    "sg:phone":"+1 908 371 2146",
    "sg:postcode":"08844",
    "sg:province":"NJ",
    "sg:tags":[
        "telecommunication",
        "internet"
    ],
    "wof:name":"Simmons/Pat",
    "wof:placetype":"venue"
},
  "geometry": {"coordinates":[-74.68553900000001,40.509591],"type":"Point"}
}