{
  "type": "Feature",
  "properties": {
    "iso:country":"US",
    "sg:address":"59 E Ridgewood Ave",
    "sg:city":"Paramus",
    "sg:classifiers":[
        {
            "category":"Autos & Motor Vehicles",
            "subcategory":"Auto Supplies",
            "type":"Retail Goods"
        }
    ],
    "sg:phone":"+1 201 261 0410",
    "sg:postcode":"07652",
    "sg:province":"NJ",
    "sg:tags":[
        "automobile",
        "parts"
    ],
    "wof:name":"P & A Auto Parts Inc",
    "wof:placetype":"venue"
},
  "geometry": {"coordinates":[-74.08680699999999,40.970854],"type":"Point"}
}