{
  "type": "Feature",
  "properties": {
    "iso:country":"US",
    "sg:address":"100 Wellington Dr",
    "sg:city":"Tinton Falls",
    "sg:classifiers":[
        {
            "category":"Building & Trades",
            "subcategory":"Construction",
            "type":"Services"
        }
    ],
    "sg:phone":"+1 609 737 2658",
    "sg:postcode":"07724",
    "sg:province":"NJ",
    "sg:tags":[
        "home",
        "builder"
    ],
    "wof:name":"Beazer Homes",
    "wof:placetype":"venue"
},
  "geometry": {"coordinates":[-74.102014,40.310363],"type":"Point"}
}