{
  "type": "Feature",
  "properties": {
    "iso:country":"US",
    "sg:address":"39 Waverly Ave",
    "sg:city":"Springfield",
    "sg:classifiers":[
        {
            "category":"Wholesale",
            "subcategory":"Machinery & Supplies",
            "type":"Manufacturing & Wholesale Goods"
        }
    ],
    "sg:phone":"+1 973 912 9455",
    "sg:postcode":"07081",
    "sg:province":"NJ",
    "wof:name":"Poseidon Irrigation",
    "wof:placetype":"venue"
},
  "geometry": {"coordinates":[-74.316,40.704413],"type":"Point"}
}