{
  "type": "Feature",
  "properties": {
    "iso:country":"US",
    "sg:address":"243 Closter Dock Rd",
    "sg:city":"Closter",
    "sg:classifiers":[
        {
            "category":"Personal",
            "subcategory":"Beauty Salon",
            "type":"Services"
        }
    ],
    "sg:phone":"+1   ",
    "sg:postcode":"07624",
    "sg:province":"NJ",
    "sg:tags":[
        "shop"
    ],
    "wof:name":"Metropolitan Hair",
    "wof:placetype":"venue"
},
  "geometry": {"coordinates":[-73.96106,40.972643],"type":"Point"}
}