{
  "type": "Feature",
  "properties": {
    "addr:full":"39 Hudson St Ste 404 Hackensack NJ 07601",
    "addr:housenumber":"39",
    "addr:postcode":"07601",
    "addr:street":"Hudson St Ste 404",
    "iso:country":"US",
    "sg:address":"39 Hudson St Ste 404",
    "sg:city":"Hackensack",
    "sg:classifiers":[
        {
            "category":"Professional",
            "subcategory":"Lawyer & Legal Services",
            "type":"Services"
        }
    ],
    "sg:phone":"+1 201 488 0070",
    "sg:postcode":"07601",
    "sg:province":"NJ",
    "wof:name":"Dilullo & Sweeney",
    "wof:placetype":"venue"
},
  "geometry": {"coordinates":[-74.043999,40.877499],"type":"Point"}
}