{
  "type": "Feature",
  "properties": {
    "iso:country":"US",
    "sg:address":"301 Grand Central Ave",
    "sg:city":"Lavallette",
    "sg:phone":"+1 732 793 8303",
    "sg:postcode":"08735",
    "sg:province":"NJ",
    "sg:tags":[
        "communications",
        "printing",
        "commercial",
        "telegraph"
    ],
    "wof:name":"Lavallette Printing",
    "wof:placetype":"venue"
},
  "geometry": {"coordinates":[-74.068061,39.975638],"type":"Point"}
}