{
  "type": "Feature",
  "properties": {
    "addr:full":"525 Moonachie Ave Wood-Ridge NJ 07075",
    "addr:housenumber":"525",
    "addr:postcode":"07075",
    "addr:street":"Moonachie Ave",
    "iso:country":"US",
    "sg:address":"525 Moonachie Ave",
    "sg:city":"Wood-Ridge",
    "sg:classifiers":[
        {
            "category":"Restaurant",
            "type":"Food & Drink"
        }
    ],
    "sg:phone":"+1 201 728 4501",
    "sg:postcode":"07075",
    "sg:province":"NJ",
    "sg:tags":[
        "new",
        "american",
        "french"
    ],
    "sg:website":"www.redhenbistro.com/",
    "wof:name":"Red Hen Bistro",
    "wof:placetype":"venue"
},
  "geometry": {"coordinates":[-74.08261400000001,40.846651],"type":"Point"}
}