{
  "type": "Feature",
  "properties": {
    "iso:country":"US",
    "sg:address":"71 Lakeview Dr S",
    "sg:city":"Gibbsboro",
    "sg:classifiers":[
        {
            "category":"Restaurant",
            "type":"Food & Drink"
        }
    ],
    "sg:phone":"+1 856 783 9812",
    "sg:postcode":"08026",
    "sg:province":"NJ",
    "sg:tags":[
        "sandwich"
    ],
    "sg:website":"www.wawa.com",
    "wof:name":"Wawa Food Market",
    "wof:placetype":"venue"
},
  "geometry": {"coordinates":[-74.958551,39.837935],"type":"Point"}
}