{
  "type": "Feature",
  "properties": {
    "iso:country":"US",
    "sg:address":"5318 Boardwalk",
    "sg:city":"Wildwood",
    "sg:classifiers":[
        {
            "category":"Shopping",
            "subcategory":"Clothing, Apparel, & Fashions",
            "type":"Retail Goods"
        }
    ],
    "sg:phone":"+1 609 522 1127",
    "sg:postcode":"08260",
    "sg:province":"NJ",
    "wof:name":"Dot's Place",
    "wof:placetype":"venue"
},
  "geometry": {"coordinates":[-74.822861,38.977797],"type":"Point"}
}