{
  "type": "Feature",
  "properties": {
    "iso:country":"US",
    "sg:address":"1200 Atlantic Ave",
    "sg:city":"Atlantic City",
    "sg:classifiers":[
        {
            "category":"Utilities",
            "subcategory":"Sewage",
            "type":"Services"
        }
    ],
    "sg:phone":"+1 609 345 0131",
    "sg:postcode":"08401",
    "sg:province":"NJ",
    "sg:tags":[
        "disposal",
        "system"
    ],
    "wof:name":"Atlantic City Sewerage Co",
    "wof:placetype":"venue"
},
  "geometry": {"coordinates":[-74.426174,39.362894],"type":"Point"}
}