{
  "type": "Feature",
  "properties": {
    "addr:full":"1200 US Highway 46 Ste 4 Parsippany NJ 07054",
    "addr:housenumber":"1200",
    "addr:postcode":"07054",
    "addr:street":"Us Highway 46 Ste 4",
    "iso:country":"US",
    "sg:address":"1200 US Highway 46 Ste 4",
    "sg:city":"Parsippany",
    "sg:classifiers":[
        {
            "category":"Shopping",
            "subcategory":"Florist",
            "type":"Retail Goods"
        }
    ],
    "sg:phone":"+1 973 334 5517",
    "sg:postcode":"07054",
    "sg:province":"NJ",
    "sg:website":"www.parsippanyflowersandgifts.com",
    "wof:name":"Parsippany Flowers & Gifts",
    "wof:placetype":"venue"
},
  "geometry": {"coordinates":[-74.389197,40.863312],"type":"Point"}
}