{
  "type": "Feature",
  "properties": {
    "addr:full":"15 Old Mill Rd Old Bridge NJ 07747",
    "addr:housenumber":"15",
    "addr:postcode":"07747",
    "addr:street":"Old Mill Rd",
    "iso:country":"US",
    "sg:address":"15 Old Mill Rd",
    "sg:city":"Old Bridge",
    "sg:classifiers":[
        {
            "category":"Wholesale",
            "subcategory":"Metals & Minerals",
            "type":"Manufacturing & Wholesale Goods"
        }
    ],
    "sg:phone":"+1 732 727 0638",
    "sg:postcode":"07747",
    "sg:province":"NJ",
    "sg:tags":[
        "steel",
        "warehouse"
    ],
    "wof:name":"Steven Nicolas Inc",
    "wof:placetype":"venue"
},
  "geometry": {"coordinates":[-74.30168999999999,40.430414],"type":"Point"}
}