{
  "type": "Feature",
  "properties": {
    "iso:country":"US",
    "sg:address":"101 US Hwy 46",
    "sg:city":"Pine Brook",
    "sg:classifiers":[
        {
            "category":"Professional",
            "subcategory":"Management & Consulting",
            "type":"Services"
        }
    ],
    "sg:phone":"+1 973 716 9283",
    "sg:postcode":"07058",
    "sg:province":"NJ",
    "sg:tags":[
        "cards",
        "phone",
        "telecommunication"
    ],
    "wof:name":"Prepaid-Guycom Inc",
    "wof:placetype":"venue"
},
  "geometry": {"coordinates":[-74.32420999999999,40.85995],"type":"Point"}
}