{
  "type": "Feature",
  "properties": {
    "iso:country":"US",
    "sg:address":"180 Kingsland St",
    "sg:city":"Nutley",
    "sg:classifiers":[
        {
            "category":"Personal",
            "subcategory":"Beauty Salon",
            "type":"Services"
        }
    ],
    "sg:phone":"+1 973 542 0100",
    "sg:postcode":"07110",
    "sg:province":"NJ",
    "sg:tags":[
        "nail",
        "shop"
    ],
    "wof:name":"Diva Nail Salon",
    "wof:placetype":"venue"
},
  "geometry": {"coordinates":[-74.14987000000001,40.828609],"type":"Point"}
}