{
  "type": "Feature",
  "properties": {
    "iso:country":"US",
    "sg:address":"14 Kings Rd",
    "sg:city":"Madison",
    "sg:classifiers":[
        {
            "category":"Shopping",
            "subcategory":"Bicycles & Sporting Goods",
            "type":"Retail Goods"
        }
    ],
    "sg:phone":"+1 973 377 6616",
    "sg:postcode":"07940",
    "sg:province":"NJ",
    "sg:tags":[
        "bike"
    ],
    "sg:website":"www.madisonbicycleshop.com",
    "wof:name":"Madison Bicycle Shop",
    "wof:placetype":"venue"
},
  "geometry": {"coordinates":[-74.418222,40.76059],"type":"Point"}
}