{
  "type": "Feature",
  "properties": {
    "addr:full":"57 E Washington Ave Washington NJ 07882",
    "addr:housenumber":"57",
    "addr:postcode":"07882",
    "addr:street":"E Washington Ave",
    "iso:country":"US",
    "sg:address":"57 E Washington Ave",
    "sg:city":"Washington",
    "sg:classifiers":[
        {
            "category":"Recreation",
            "type":"Entertainment"
        }
    ],
    "sg:phone":"+1   ",
    "sg:postcode":"07882",
    "sg:province":"NJ",
    "sg:tags":[
        "astrologer"
    ],
    "wof:name":"Julias Astrlogy Psyshic Rdings",
    "wof:placetype":"venue"
},
  "geometry": {"coordinates":[-74.97743199999999,40.758869],"type":"Point"}
}