{
  "type": "Feature",
  "properties": {
    "addr:full":"502 Carnegie Center Princeton NJ 08540",
    "addr:housenumber":"502",
    "addr:postcode":"08540",
    "addr:street":"Carnegie Center",
    "iso:country":"US",
    "sg:address":"502 Carnegie Center",
    "sg:city":"Princeton",
    "sg:classifiers":[
        {
            "category":"Professional",
            "subcategory":"Management & Consulting",
            "type":"Services"
        }
    ],
    "sg:phone":"+1   ",
    "sg:postcode":"08540",
    "sg:province":"NJ",
    "sg:tags":[
        "business"
    ],
    "wof:name":"Maritz",
    "wof:placetype":"venue"
},
  "geometry": {"coordinates":[-74.649389,40.32136],"type":"Point"}
}