{
  "type": "Feature",
  "properties": {
    "iso:country":"US",
    "sg:address":"5 James St",
    "sg:city":"South Hackensack",
    "sg:classifiers":[
        {
            "category":"Home & Garden",
            "subcategory":"Building Materials",
            "type":"Retail Goods"
        }
    ],
    "sg:phone":"+1 201 621 0240",
    "sg:postcode":"07606",
    "sg:province":"NJ",
    "sg:tags":[
        "door"
    ],
    "wof:name":"Vanguard SMR Inc",
    "wof:placetype":"venue"
},
  "geometry": {"coordinates":[-74.05539400000001,40.872102],"type":"Point"}
}