{
  "type": "Feature",
  "properties": {
    "iso:country":"US",
    "sg:address":"590 Ave C",
    "sg:city":"Bayonne",
    "sg:classifiers":[
        {
            "category":"Professional",
            "subcategory":"Lawyer & Legal Services",
            "type":"Services"
        }
    ],
    "sg:phone":"+1 201 436 9644",
    "sg:postcode":"07002",
    "sg:province":"NJ",
    "sg:tags":[
        "attorney"
    ],
    "wof:name":"Grodberg Law Firm",
    "wof:placetype":"venue"
},
  "geometry": {"coordinates":[-74.118809,40.666911],"type":"Point"}
}