{
  "type": "Feature",
  "properties": {
    "addr:full":"820 Main St Hackensack NJ 07601",
    "addr:housenumber":"820",
    "addr:postcode":"07601",
    "addr:street":"Main St",
    "iso:country":"US",
    "sg:address":"820 Main St",
    "sg:city":"Hackensack",
    "sg:classifiers":[
        {
            "category":"Personal",
            "subcategory":"Nail Salon",
            "type":"Services"
        }
    ],
    "sg:phone":"+1 201 488 9500",
    "sg:postcode":"07601",
    "sg:province":"NJ",
    "wof:name":"Cool Nail Salon",
    "wof:placetype":"venue"
},
  "geometry": {"coordinates":[-74.042198,40.904598],"type":"Point"}
}