{
  "type": "Feature",
  "properties": {
    "addr:full":"2401 US Highway 22 W Union NJ 07083",
    "addr:housenumber":"2401",
    "addr:postcode":"07083",
    "addr:street":"Us Highway 22 W",
    "iso:country":"US",
    "sg:address":"2401 US Highway 22 W",
    "sg:city":"Union",
    "sg:classifiers":[
        {
            "category":"Real Estate",
            "subcategory":"Real Estate Operator",
            "type":"Services"
        }
    ],
    "sg:phone":"+1 908 688 4537",
    "sg:postcode":"07083",
    "sg:province":"NJ",
    "sg:tags":[
        "apartment"
    ],
    "wof:name":"Robbins Agency",
    "wof:placetype":"venue"
},
  "geometry": {"coordinates":[-74.296999,40.690506],"type":"Point"}
}