{
  "type": "Feature",
  "properties": {
    "iso:country":"US",
    "sg:address":"130 University Pl",
    "sg:city":"Princeton",
    "sg:classifiers":[
        {
            "category":"Professional",
            "subcategory":"Management & Consulting",
            "type":"Services"
        }
    ],
    "sg:phone":"+1   ",
    "sg:postcode":"08540",
    "sg:province":"NJ",
    "sg:tags":[
        "retail",
        "eating",
        "direct",
        "sales"
    ],
    "wof:name":"Princeton Dining Service",
    "wof:placetype":"venue"
},
  "geometry": {"coordinates":[-74.66001799999999,40.34423],"type":"Point"}
}