{
  "type": "Feature",
  "properties": {
    "iso:country":"US",
    "sg:address":"42 Virginia Ave S",
    "sg:city":"Lake Hopatcong",
    "sg:classifiers":[
        {
            "category":"Professional",
            "type":"Services"
        }
    ],
    "sg:phone":"+1   ",
    "sg:postcode":"07849",
    "sg:province":"NJ",
    "wof:name":"Daniel S Gold",
    "wof:placetype":"venue"
},
  "geometry": {"coordinates":[-74.62469900000001,40.965293],"type":"Point"}
}