{
  "type": "Feature",
  "properties": {
    "addr:full":"12 Parrott Mill Rd Chatham NJ 07928",
    "addr:housenumber":"12",
    "addr:postcode":"07928",
    "addr:street":"Parrott Mill Rd",
    "iso:country":"US",
    "sg:address":"12 Parrott Mill Rd",
    "sg:city":"Chatham",
    "sg:classifiers":[
        {
            "category":"Health Services",
            "subcategory":"Doctor",
            "type":"Services"
        }
    ],
    "sg:phone":"+1 973 635 4511",
    "sg:postcode":"07928",
    "sg:province":"NJ",
    "sg:tags":[
        "physician",
        "surgeon"
    ],
    "wof:name":"Chatham Pediatrics",
    "wof:placetype":"venue"
},
  "geometry": {"coordinates":[-74.373985,40.738619],"type":"Point"}
}