{
  "type": "Feature",
  "properties": {
    "addr:full":"156 Main St Newton NJ 07860",
    "addr:housenumber":"156",
    "addr:postcode":"07860",
    "addr:street":"Main St",
    "iso:country":"US",
    "sg:address":"156 Main St",
    "sg:city":"Newton",
    "sg:classifiers":[
        {
            "category":"Retail",
            "subcategory":"Funeral Services",
            "type":"Services"
        }
    ],
    "sg:phone":"+1 973 383 5200",
    "sg:postcode":"07860",
    "sg:province":"NJ",
    "sg:tags":[
        "director",
        "supply"
    ],
    "sg:website":"http://iliff-ruggierofuneralhome.com",
    "wof:name":"Iliff-Ruggiero Funeral Home",
    "wof:placetype":"venue"
},
  "geometry": {"coordinates":[-74.75681299999999,41.051929],"type":"Point"}
}