{
  "type": "Feature",
  "properties": {
    "iso:country":"US",
    "sg:address":"3 Mc Cue Rd",
    "sg:city":"Morganville",
    "sg:classifiers":[
        {
            "category":"Manufacturing",
            "subcategory":"Signs",
            "type":"Manufacturing & Wholesale Goods"
        }
    ],
    "sg:phone":"+1 732 972 1776",
    "sg:postcode":"07751",
    "sg:province":"NJ",
    "sg:tags":[
        "specialty",
        "mfg"
    ],
    "wof:name":"Eric P Ericcson",
    "wof:placetype":"venue"
},
  "geometry": {"coordinates":[-74.286879,40.335564],"type":"Point"}
}