{
  "type": "Feature",
  "properties": {
    "addr:full":"7 Harbor Rd Morganville NJ 07751",
    "addr:housenumber":"7",
    "addr:postcode":"07751",
    "addr:street":"Harbor Rd",
    "iso:country":"US",
    "sg:address":"7 Harbor Rd",
    "sg:city":"Morganville",
    "sg:classifiers":[
        {
            "category":"Professional",
            "subcategory":"Art Services",
            "type":"Services"
        }
    ],
    "sg:phone":"+1   ",
    "sg:postcode":"07751",
    "sg:province":"NJ",
    "sg:tags":[
        "commercial",
        "design"
    ],
    "sg:website":"www.ampersandgraphics.com",
    "wof:name":"Ampersand Graphics",
    "wof:placetype":"venue"
},
  "geometry": {"coordinates":[-74.25023899999999,40.358212],"type":"Point"}
}