{
  "type": "Feature",
  "properties": {
    "addr:full":"202 Goffle Hill Rd Hawthorne NJ 07506",
    "addr:housenumber":"202",
    "addr:postcode":"07506",
    "addr:street":"Goffle Hill Rd",
    "iso:country":"US",
    "sg:address":"202 Goffle Hill Rd",
    "sg:city":"Hawthorne",
    "sg:classifiers":[
        {
            "category":"Building & Trades",
            "subcategory":"Landscaping Services",
            "type":"Services"
        }
    ],
    "sg:phone":"+1 973 427 5620",
    "sg:postcode":"07506",
    "sg:province":"NJ",
    "sg:tags":[
        "landscape"
    ],
    "wof:name":"James Mierop",
    "wof:placetype":"venue"
},
  "geometry": {"coordinates":[-74.161565,40.968881],"type":"Point"}
}