{
  "type": "Feature",
  "properties": {
    "iso:country":"US",
    "sg:address":"295 Bay Ave",
    "sg:city":"Highlands",
    "sg:classifiers":[
        {
            "category":"Retail",
            "subcategory":"Auto Repair",
            "type":"Services"
        }
    ],
    "sg:phone":"+1 732 872 2222",
    "sg:postcode":"07732",
    "sg:province":"NJ",
    "sg:tags":[
        "general"
    ],
    "wof:name":"Auto Imports",
    "wof:placetype":"venue"
},
  "geometry": {"coordinates":[-73.991905,40.404106],"type":"Point"}
}