{
  "type": "Feature",
  "properties": {
    "iso:country":"US",
    "sg:address":"125 Howard Blvd",
    "sg:city":"Ledgewood",
    "sg:classifiers":[
        {
            "category":"Shopping",
            "subcategory":"Computers & Home Electronics",
            "type":"Retail Goods"
        }
    ],
    "sg:phone":"+1 973 598 0561",
    "sg:postcode":"07852",
    "sg:province":"NJ",
    "sg:tags":[
        "equipment",
        "electronic",
        "supply"
    ],
    "wof:name":"Electronics Expo",
    "wof:placetype":"venue"
},
  "geometry": {"coordinates":[-74.63853899999999,40.892725],"type":"Point"}
}