{
  "type": "Feature",
  "properties": {
    "addr:full":"10 Victorian Dr Old Bridge NJ 08857",
    "addr:housenumber":"10",
    "addr:postcode":"08857",
    "addr:street":"Victorian Dr",
    "iso:country":"US",
    "sg:address":"10 Victorian Dr",
    "sg:city":"Old Bridge",
    "sg:classifiers":[
        {
            "category":"Professional",
            "subcategory":"Computer Services",
            "type":"Services"
        }
    ],
    "sg:phone":"+1   ",
    "sg:postcode":"08857",
    "sg:province":"NJ",
    "sg:tags":[
        "related"
    ],
    "wof:name":"Sls Network Solutions Inc",
    "wof:placetype":"venue"
},
  "geometry": {"coordinates":[-74.313982,40.385487],"type":"Point"}
}