{
  "type": "Feature",
  "properties": {
    "addr:full":"1560 US Hwy 46 Parsippany NJ 07054",
    "addr:housenumber":"1560",
    "addr:postcode":"07054",
    "addr:street":"Us Hwy 46",
    "iso:country":"US",
    "sg:address":"1560 US Hwy 46",
    "sg:city":"Parsippany",
    "sg:classifiers":[
        {
            "category":"Restaurant",
            "type":"Food & Drink"
        }
    ],
    "sg:phone":"+1   ",
    "sg:postcode":"07054",
    "sg:province":"NJ",
    "sg:tags":[
        "eating"
    ],
    "wof:name":"Taco Bell",
    "wof:placetype":"venue"
},
  "geometry": {"coordinates":[-74.403758,40.864737],"type":"Point"}
}