{
  "type": "Feature",
  "properties": {
    "addr:full":"141 E Main St Ramsey NJ 07446",
    "addr:housenumber":"141",
    "addr:postcode":"07446",
    "addr:street":"E Main St",
    "iso:country":"US",
    "sg:address":"141 E Main St",
    "sg:city":"Ramsey",
    "sg:classifiers":[
        {
            "category":"Shopping",
            "type":"Retail Goods"
        }
    ],
    "sg:phone":"+1   ",
    "sg:postcode":"07446",
    "sg:province":"NJ",
    "sg:tags":[
        "merchandise"
    ],
    "wof:name":"Golden Triangle Stamp & Coin",
    "wof:placetype":"venue"
},
  "geometry": {"coordinates":[-74.13874199999999,41.057625],"type":"Point"}
}