{
  "type": "Feature",
  "properties": {
    "addr:full":"2656 Nottingham Way Trenton NJ 08619",
    "addr:housenumber":"2656",
    "addr:postcode":"08619",
    "addr:street":"Nottingham Way",
    "iso:country":"US",
    "sg:address":"2656 Nottingham Way",
    "sg:city":"Trenton",
    "sg:classifiers":[
        {
            "category":"Building & Trades",
            "subcategory":"Construction",
            "type":"Services"
        }
    ],
    "sg:phone":"+1 609 584 8731",
    "sg:postcode":"08619",
    "sg:province":"NJ",
    "sg:tags":[
        "nonresidential"
    ],
    "wof:name":"Luisi Bros Construction Inc",
    "wof:placetype":"venue"
},
  "geometry": {"coordinates":[-74.6901,40.235937],"type":"Point"}
}