{
  "type": "Feature",
  "properties": {
    "addr:full":"255 Kings Hwy E Haddonfield NJ 08033",
    "addr:housenumber":"255",
    "addr:postcode":"08033",
    "addr:street":"Kings Hwy E",
    "iso:country":"US",
    "sg:address":"255 Kings Hwy E",
    "sg:city":"Haddonfield",
    "sg:classifiers":[
        {
            "category":"Professional",
            "subcategory":"Lawyer & Legal Services",
            "type":"Services"
        }
    ],
    "sg:phone":"+1 856 216 0800",
    "sg:postcode":"08033",
    "sg:province":"NJ",
    "sg:website":"www.legalcost.com",
    "wof:name":"Legal Cost Control Inc",
    "wof:placetype":"venue"
},
  "geometry": {"coordinates":[-75.030602,39.898701],"type":"Point"}
}