{
  "type": "Feature",
  "properties": {
    "addr:full":"9 Bayberry Dr Bordentown NJ 08505",
    "addr:housenumber":"9",
    "addr:postcode":"08505",
    "addr:street":"Bayberry Dr",
    "iso:country":"US",
    "sg:address":"9 Bayberry Dr",
    "sg:city":"Bordentown",
    "sg:classifiers":[
        {
            "category":"Manufacturing",
            "subcategory":"Printing",
            "type":"Manufacturing & Wholesale Goods"
        }
    ],
    "sg:phone":"+1 609 298 3491",
    "sg:postcode":"08505",
    "sg:province":"NJ",
    "sg:tags":[
        "lithographic",
        "commercial"
    ],
    "wof:name":"Rose Antonia Printing",
    "wof:placetype":"venue"
},
  "geometry": {"coordinates":[-74.692669,40.14923],"type":"Point"}
}