{
  "type": "Feature",
  "properties": {
    "addr:full":"17 Hilliard Ave Edgewater NJ 07020",
    "addr:housenumber":"17",
    "addr:postcode":"07020",
    "addr:street":"Hilliard Ave",
    "iso:country":"US",
    "sg:address":"17 Hilliard Ave",
    "sg:city":"Edgewater",
    "sg:classifiers":[
        {
            "category":"Professional",
            "subcategory":"Lawyer & Legal Services",
            "type":"Services"
        }
    ],
    "sg:phone":"+1 201 941 3155",
    "sg:postcode":"07020",
    "sg:province":"NJ",
    "sg:tags":[
        "attorney"
    ],
    "wof:name":"Donald W Becker Esq",
    "wof:placetype":"venue"
},
  "geometry": {"coordinates":[-73.97415599999999,40.826093],"type":"Point"}
}