{
  "type": "Feature",
  "properties": {
    "addr:full":"154 Linwood Plz Fort Lee NJ 07024",
    "addr:housenumber":"154",
    "addr:postcode":"07024",
    "addr:street":"Linwood Plz",
    "iso:country":"US",
    "sg:address":"154 Linwood Plz",
    "sg:city":"Fort Lee",
    "sg:classifiers":[
        {
            "category":"Banks & Credit Unions",
            "subcategory":"Bank",
            "type":"Services"
        }
    ],
    "sg:phone":"+1 201 000 1111",
    "sg:postcode":"07024",
    "sg:province":"NJ",
    "wof:name":"Bank Of America",
    "wof:placetype":"venue"
},
  "geometry": {"coordinates":[-73.96804,40.861155],"type":"Point"}
}