{
  "type": "Feature",
  "properties": {
    "addr:full":"222 Thomas St Newark NJ 07114",
    "addr:housenumber":"222",
    "addr:postcode":"07114",
    "addr:street":"Thomas St",
    "iso:country":"US",
    "sg:address":"222 Thomas St",
    "sg:city":"Newark",
    "sg:classifiers":[
        {
            "category":"Manufacturing",
            "subcategory":"Tools & Machinery",
            "type":"Manufacturing & Wholesale Goods"
        }
    ],
    "sg:phone":"+1 973 596 1121",
    "sg:postcode":"07114",
    "sg:province":"NJ",
    "sg:tags":[
        "plate",
        "industry",
        "work",
        "fabricated",
        "mfg"
    ],
    "wof:name":"Bush Tank Fabricators Inc",
    "wof:placetype":"venue"
},
  "geometry": {"coordinates":[-74.172597,40.721615],"type":"Point"}
}