{
  "type": "Feature",
  "properties": {
    "iso:country":"US",
    "sg:address":"3112 Fire Rd",
    "sg:city":"Egg Harbor Twp",
    "sg:classifiers":[
        {
            "category":"Wholesale",
            "subcategory":"Office Equipment",
            "type":"Manufacturing & Wholesale Goods"
        },
        {
            "category":"Retail",
            "subcategory":"Repair Shop",
            "type":"Services"
        }
    ],
    "sg:phone":"+1 609 645 7587",
    "sg:postcode":"08234",
    "sg:province":"NJ",
    "sg:tags":[
        "machine",
        "duplicating",
        "copying",
        "supply"
    ],
    "sg:website":"www.aplusimaging.com",
    "wof:name":"Copiers Plus",
    "wof:placetype":"venue"
},
  "geometry": {"coordinates":[-74.561139,39.392786],"type":"Point"}
}