{
  "type": "Feature",
  "properties": {
    "iso:country":"US",
    "sg:address":"3709 Scenic Ct",
    "sg:city":"Denville",
    "sg:classifiers":[
        {
            "category":"Building & Trades",
            "subcategory":"Construction",
            "type":"Services"
        }
    ],
    "sg:phone":"+1 973 989 5549",
    "sg:postcode":"07834",
    "sg:province":"NJ",
    "sg:tags":[
        "general",
        "contractor"
    ],
    "wof:name":"Berkshire Hills Constr Office",
    "wof:placetype":"venue"
},
  "geometry": {"coordinates":[-74.519355,40.875049],"type":"Point"}
}