{
  "type": "Feature",
  "properties": {
    "iso:country":"US",
    "sg:address":"409 Lincoln Blvd",
    "sg:city":"Middlesex",
    "sg:classifiers":[
        {
            "category":"Restaurant",
            "type":"Food & Drink"
        }
    ],
    "sg:phone":"+1 732 537 9600",
    "sg:postcode":"08846",
    "sg:province":"NJ",
    "sg:tags":[
        "eating"
    ],
    "wof:name":"Jozanna's Restaurant",
    "wof:placetype":"venue"
},
  "geometry": {"coordinates":[-74.497703,40.569524],"type":"Point"}
}