{
  "type": "Feature",
  "properties": {
    "addr:full":"100 Nassau Park Blvd Princeton NJ 08540",
    "addr:housenumber":"100",
    "addr:postcode":"08540",
    "addr:street":"Nassau Park Blvd",
    "iso:country":"US",
    "sg:address":"100 Nassau Park Blvd",
    "sg:city":"Princeton",
    "sg:classifiers":[
        {
            "category":"Professional",
            "subcategory":"Lawyer & Legal Services",
            "type":"Services"
        }
    ],
    "sg:phone":"+1 609 520 0900",
    "sg:postcode":"08540",
    "sg:province":"NJ",
    "sg:tags":[
        "attorney"
    ],
    "wof:name":"Pellettieri Rabstein & Altman",
    "wof:placetype":"venue"
},
  "geometry": {"coordinates":[-74.67451199999999,40.302377],"type":"Point"}
}