{
  "type": "Feature",
  "properties": {
    "iso:country":"US",
    "sg:address":"116 Denver Ave",
    "sg:city":"Collingswood",
    "sg:classifiers":[
        {
            "category":"Retail",
            "subcategory":"Repair Shop",
            "type":"Services"
        }
    ],
    "sg:phone":"+1   ",
    "sg:postcode":"08108",
    "sg:province":"NJ",
    "wof:name":"Termite Tool Repair",
    "wof:placetype":"venue"
},
  "geometry": {"coordinates":[-75.041325,39.910215],"type":"Point"}
}