{
  "type": "Feature",
  "properties": {
    "addr:full":"222 Route 37 E Toms River NJ 08753",
    "addr:housenumber":"222",
    "addr:postcode":"08753",
    "addr:street":"Route 37 E",
    "iso:country":"US",
    "sg:address":"222 Route 37 E",
    "sg:city":"Toms River",
    "sg:classifiers":[
        {
            "category":"Restaurant",
            "type":"Food & Drink"
        }
    ],
    "sg:menulink":"http://www.allmenus.com/nj/toms-river/183613-kfc---kentucky-fried-chicken/menu/",
    "sg:phone":"+1 732 244 2020",
    "sg:postcode":"08753",
    "sg:province":"NJ",
    "sg:tags":[
        "american",
        "chicken"
    ],
    "wof:name":"KFC - Kentucky Fried Chicken",
    "wof:placetype":"venue"
},
  "geometry": {"coordinates":[-74.18196399999999,39.962542],"type":"Point"}
}