{
  "type": "Feature",
  "properties": {
    "iso:country":"US",
    "sg:address":"12 Holly Rd",
    "sg:city":"Iselin",
    "sg:classifiers":[
        {
            "category":"Communications",
            "subcategory":"Film & Video Production",
            "type":"Services"
        }
    ],
    "sg:phone":"+1 732 635 1080",
    "sg:postcode":"08830",
    "sg:province":"NJ",
    "wof:name":"Personal Tuch Vdeo Productions",
    "wof:placetype":"venue"
},
  "geometry": {"coordinates":[-74.331835,40.572019],"type":"Point"}
}