{
  "type": "Feature",
  "properties": {
    "addr:full":"2954 E Octagon Rd Camden NJ 08104",
    "addr:housenumber":"2954",
    "addr:postcode":"08104",
    "addr:street":"E Octagon Rd",
    "iso:country":"US",
    "sg:address":"2954 E Octagon Rd",
    "sg:city":"Camden",
    "sg:classifiers":[
        {
            "category":"Building & Trades",
            "subcategory":"Landscaping Services",
            "type":"Services"
        }
    ],
    "sg:phone":"+1 856 962 7872",
    "sg:postcode":"08104",
    "sg:province":"NJ",
    "sg:tags":[
        "lawn",
        "maintenance",
        "grounds"
    ],
    "wof:name":"Onsite Enterprises",
    "wof:placetype":"venue"
},
  "geometry": {"coordinates":[-75.10463300000001,39.906617],"type":"Point"}
}