{
  "type": "Feature",
  "properties": {
    "addr:full":"778 US Hwy 1 North Brunswick NJ 08902",
    "addr:housenumber":"778",
    "addr:postcode":"08902",
    "addr:street":"Us Hwy 1",
    "iso:country":"US",
    "sg:address":"778 US Hwy 1",
    "sg:city":"North Brunswick",
    "sg:classifiers":[
        {
            "category":"Shopping",
            "subcategory":"Optical Goods",
            "type":"Retail Goods"
        }
    ],
    "sg:phone":"+1 732 828 3937",
    "sg:postcode":"08902",
    "sg:province":"NJ",
    "wof:name":"Optical Insight LLC",
    "wof:placetype":"venue"
},
  "geometry": {"coordinates":[-74.471789,40.458217],"type":"Point"}
}