{
  "type": "Feature",
  "properties": {
    "iso:country":"US",
    "sg:address":"230 Trumbull St",
    "sg:city":"Elizabeth",
    "sg:classifiers":[
        {
            "category":"Bars & Pubs",
            "type":"Food & Drink"
        }
    ],
    "sg:phone":"+1   ",
    "sg:postcode":"07206",
    "sg:province":"NJ",
    "sg:tags":[
        "drinking"
    ],
    "wof:name":"Starlight Tavern Inc",
    "wof:placetype":"venue"
},
  "geometry": {"coordinates":[-74.17986399999999,40.65572],"type":"Point"}
}