{
  "type": "Feature",
  "properties": {
    "iso:country":"US",
    "sg:address":"1924 Broadway Blvd",
    "sg:city":"Toms River",
    "sg:classifiers":[
        {
            "category":"Building & Trades",
            "subcategory":"Construction",
            "type":"Services"
        }
    ],
    "sg:phone":"+1 732 281 0859",
    "sg:postcode":"08757",
    "sg:province":"NJ",
    "sg:tags":[
        "contractor"
    ],
    "wof:name":"Marcelo Drywall",
    "wof:placetype":"venue"
},
  "geometry": {"coordinates":[-74.24329299999999,39.999909],"type":"Point"}
}