{
  "type": "Feature",
  "properties": {
    "addr:full":"184 W Englewood Ave Teaneck NJ 07666",
    "addr:housenumber":"184",
    "addr:postcode":"07666",
    "addr:street":"W Englewood Ave",
    "iso:country":"US",
    "sg:address":"184 W Englewood Ave",
    "sg:city":"Teaneck",
    "sg:classifiers":[
        {
            "category":"Recreation",
            "type":"Entertainment"
        }
    ],
    "sg:phone":"+1 201 833 1741",
    "sg:postcode":"07666",
    "sg:province":"NJ",
    "sg:tags":[
        "instruction",
        "chess"
    ],
    "wof:name":"Chess Academy",
    "wof:placetype":"venue"
},
  "geometry": {"coordinates":[-74.00637500000001,40.901093],"type":"Point"}
}