{
  "type": "Feature",
  "properties": {
    "iso:country":"US",
    "sg:address":"604 Washington St",
    "sg:city":"Hoboken",
    "sg:classifiers":[
        {
            "category":"Sports & Exercise",
            "subcategory":"Bicycle Rental",
            "type":"Entertainment"
        }
    ],
    "sg:phone":"+1 201 533 1200",
    "sg:postcode":"07030",
    "sg:province":"NJ",
    "sg:tags":[
        "wear"
    ],
    "sg:website":"www.fleetfeethoboken.com",
    "wof:name":"Fleet Feet Sports",
    "wof:placetype":"venue"
},
  "geometry": {"coordinates":[-74.028954,40.743537],"type":"Point"}
}