{
  "type": "Feature",
  "properties": {
    "iso:country":"US",
    "sg:address":"350 Ridge Rd",
    "sg:city":"Lyndhurst",
    "sg:classifiers":[
        {
            "category":"Education",
            "subcategory":"Music School",
            "type":"Public Place"
        }
    ],
    "sg:phone":"+1 201 933 2257",
    "sg:postcode":"07071",
    "sg:province":"NJ",
    "sg:tags":[
        "instrument",
        "teacher",
        "musical"
    ],
    "wof:name":"Sweetest Sounds",
    "wof:placetype":"venue"
},
  "geometry": {"coordinates":[-74.11990400000001,40.806999],"type":"Point"}
}