{
  "type": "Feature",
  "properties": {
    "iso:country":"US",
    "sg:address":"713 Bergen Ave",
    "sg:city":"Jersey City",
    "sg:classifiers":[
        {
            "category":"Real Estate",
            "subcategory":"Real Estate Agent",
            "type":"Services"
        }
    ],
    "sg:phone":"+1 201 369 1788",
    "sg:postcode":"07306",
    "sg:province":"NJ",
    "wof:name":"Myrage & Palis",
    "wof:placetype":"venue"
},
  "geometry": {"coordinates":[-74.069993,40.724081],"type":"Point"}
}