{
  "type": "Feature",
  "properties": {
    "addr:full":"33 State Rte 17 East Rutherford NJ 07073",
    "addr:housenumber":"33",
    "addr:postcode":"07073",
    "addr:street":"State Rte 17",
    "iso:country":"US",
    "sg:address":"33 State Rte 17",
    "sg:city":"East Rutherford",
    "sg:classifiers":[
        {
            "category":"Manufacturing",
            "subcategory":"Signs",
            "type":"Manufacturing & Wholesale Goods"
        }
    ],
    "sg:phone":"+1 201 438 0600",
    "sg:postcode":"07073",
    "sg:province":"NJ",
    "sg:tags":[
        "mfg"
    ],
    "wof:name":"A Plus Signs",
    "wof:placetype":"venue"
},
  "geometry": {"coordinates":[-74.088971,40.832528],"type":"Point"}
}