{
  "type": "Feature",
  "properties": {
    "addr:full":"1176 Hamburg Tpke Wayne NJ 07470",
    "addr:housenumber":"1176",
    "addr:postcode":"07470",
    "addr:street":"Hamburg Tpke",
    "iso:country":"US",
    "sg:address":"1176 Hamburg Tpke",
    "sg:city":"Wayne",
    "sg:classifiers":[
        {
            "category":"Retail",
            "subcategory":"Self-service Laundry",
            "type":"Services"
        }
    ],
    "sg:phone":"+1 973 628 0237",
    "sg:postcode":"07470",
    "sg:province":"NJ",
    "sg:tags":[
        "laundromat"
    ],
    "wof:name":"Preakness Laundromat Inc",
    "wof:placetype":"venue"
},
  "geometry": {"coordinates":[-74.24112,40.960518],"type":"Point"}
}