{
  "type": "Feature",
  "properties": {
    "addr:full":"160 W Rio Grande Ave Wildwood NJ 08260",
    "addr:housenumber":"160",
    "addr:postcode":"08260",
    "addr:street":"W Rio Grande Ave",
    "iso:country":"US",
    "sg:address":"160 W Rio Grande Ave",
    "sg:city":"Wildwood",
    "sg:classifiers":[
        {
            "category":"Home & Garden",
            "subcategory":"Building Materials",
            "type":"Retail Goods"
        }
    ],
    "sg:phone":"+1 609 522 0251",
    "sg:postcode":"08260",
    "sg:province":"NJ",
    "sg:tags":[
        "paint",
        "floor",
        "covering"
    ],
    "wof:name":"Sherwin-Williams Paints",
    "wof:placetype":"venue"
},
  "geometry": {"coordinates":[-74.825596,38.984551],"type":"Point"}
}