{
  "type": "Feature",
  "properties": {
    "iso:country":"US",
    "sg:address":"19 River Rd",
    "sg:city":"Fair Lawn",
    "sg:classifiers":[
        {
            "category":"Health Services",
            "subcategory":"Doctor",
            "type":"Services"
        }
    ],
    "sg:phone":"+1 201 797 8899",
    "sg:postcode":"07410",
    "sg:province":"NJ",
    "wof:name":"Joy Dental",
    "wof:placetype":"venue"
},
  "geometry": {"coordinates":[-74.129696,40.926719],"type":"Point"}
}