{
  "type": "Feature",
  "properties": {
    "iso:country":"US",
    "sg:address":"29 Oberlin St",
    "sg:city":"Maplewood",
    "sg:classifiers":[
        {
            "category":"Organizations",
            "subcategory":"Labor Organization",
            "type":"Services"
        }
    ],
    "sg:phone":"+1 973 762 6506",
    "sg:postcode":"07040",
    "sg:province":"NJ",
    "wof:name":"Assoc Assistant Principal",
    "wof:placetype":"venue"
},
  "geometry": {"coordinates":[-74.266548,40.724599],"type":"Point"}
}