{
  "type": "Feature",
  "properties": {
    "iso:country":"US",
    "sg:address":"1088 State Rte 34",
    "sg:city":"Matawan",
    "sg:classifiers":[
        {
            "category":"Health Services",
            "subcategory":"Hospital",
            "type":"Services"
        }
    ],
    "sg:phone":"+1 732 441 0240",
    "sg:postcode":"07747",
    "sg:province":"NJ",
    "sg:tags":[
        "mental"
    ],
    "wof:name":"CPC Behavioral Healthcare",
    "wof:placetype":"venue"
},
  "geometry": {"coordinates":[-74.22766300000001,40.398951],"type":"Point"}
}