{
  "type": "Feature",
  "properties": {
    "addr:full":"5009 English Creek Ave Egg Harbor Twp NJ 08234",
    "addr:housenumber":"5009",
    "addr:postcode":"08234",
    "addr:street":"English Creek Ave",
    "iso:country":"US",
    "sg:address":"5009 English Creek Ave",
    "sg:city":"Egg Harbor Twp",
    "sg:classifiers":[
        {
            "category":"Building & Trades",
            "subcategory":"Landscaping Services",
            "type":"Services"
        }
    ],
    "sg:phone":"+1 609 641 7713",
    "sg:postcode":"08234",
    "sg:province":"NJ",
    "sg:tags":[
        "designer",
        "landscape"
    ],
    "wof:name":"J Adamson & Assoc",
    "wof:placetype":"venue"
},
  "geometry": {"coordinates":[-74.62776100000001,39.406006],"type":"Point"}
}