{
  "type": "Feature",
  "properties": {
    "iso:country":"US",
    "sg:address":"500 US Hwy 46",
    "sg:city":"Clifton",
    "sg:classifiers":[
        {
            "category":"Professional",
            "subcategory":"Advertising",
            "type":"Services"
        }
    ],
    "sg:phone":"+1   ",
    "sg:postcode":"07011",
    "sg:province":"NJ",
    "sg:tags":[
        "international",
        "distribution",
        "printed",
        "papers"
    ],
    "wof:name":"Postal Links International",
    "wof:placetype":"venue"
},
  "geometry": {"coordinates":[-74.155861,40.878439],"type":"Point"}
}