{
  "type": "Feature",
  "properties": {
    "addr:full":"103 Mansfield Blvd S Cherry Hill NJ 08034",
    "addr:housenumber":"103",
    "addr:postcode":"08034",
    "addr:street":"Mansfield Blvd S",
    "iso:country":"US",
    "sg:address":"103 Mansfield Blvd S",
    "sg:city":"Cherry Hill",
    "sg:classifiers":[
        {
            "category":"Retail",
            "subcategory":"Repair Shop",
            "type":"Services"
        }
    ],
    "sg:phone":"+1 856 429 6495",
    "sg:postcode":"08034",
    "sg:province":"NJ",
    "sg:tags":[
        "sharpening"
    ],
    "wof:name":"William Jones Sharpening Svc",
    "wof:placetype":"venue"
},
  "geometry": {"coordinates":[-75.01551600000001,39.887503],"type":"Point"}
}