{
  "type": "Feature",
  "properties": {
    "iso:country":"US",
    "sg:address":"904 Summit Ave",
    "sg:city":"Union City",
    "sg:classifiers":[
        {
            "category":"Travel",
            "subcategory":"Travel Agent",
            "type":"Entertainment"
        }
    ],
    "sg:phone":"+1 201 223 4747",
    "sg:postcode":"07087",
    "sg:province":"NJ",
    "sg:tags":[
        "agency"
    ],
    "wof:name":"Carolina Travel Agency",
    "wof:placetype":"venue"
},
  "geometry": {"coordinates":[-74.043497,40.758868],"type":"Point"}
}