{
  "type": "Feature",
  "properties": {
    "addr:full":"159 Millburn Ave Ste 3 Millburn NJ 07041",
    "addr:housenumber":"159",
    "addr:postcode":"07041",
    "addr:street":"Millburn Ave Ste 3",
    "iso:country":"US",
    "sg:address":"159 Millburn Ave Ste 3",
    "sg:city":"Millburn",
    "sg:classifiers":[
        {
            "category":"Health Services",
            "subcategory":"Doctor",
            "type":"Services"
        }
    ],
    "sg:phone":"+1 973 912 4433",
    "sg:postcode":"07041",
    "sg:province":"NJ",
    "wof:name":"Shulman Gayle S MD",
    "wof:placetype":"venue"
},
  "geometry": {"coordinates":[-74.292388,40.722371],"type":"Point"}
}