{
  "type": "Feature",
  "properties": {
    "iso:country":"US",
    "sg:address":"1401 Industrial Hwy",
    "sg:city":"Cinnaminson",
    "sg:classifiers":[
        {
            "category":"Shopping",
            "subcategory":"Gifts & Souvenirs",
            "type":"Retail Goods"
        },
        {
            "category":"Manufacturing",
            "subcategory":"Retail Goods",
            "type":"Manufacturing & Wholesale Goods"
        }
    ],
    "sg:phone":"+1 856 829 2280",
    "sg:postcode":"08077",
    "sg:province":"NJ",
    "sg:tags":[
        "shop",
        "giftware's-wholesale",
        "manufacturer"
    ],
    "wof:name":"Mgn Sales Inc",
    "wof:placetype":"venue"
},
  "geometry": {"coordinates":[-74.98849800000001,40.008804],"type":"Point"}
}