{
  "type": "Feature",
  "properties": {
    "addr:full":"17 E Curlis Ave Pennington NJ 08534",
    "addr:housenumber":"17",
    "addr:postcode":"08534",
    "addr:street":"E Curlis Ave",
    "iso:country":"US",
    "sg:address":"17 E Curlis Ave",
    "sg:city":"Pennington",
    "sg:classifiers":[
        {
            "category":"Shopping",
            "subcategory":"Catalog Store",
            "type":"Retail Goods"
        }
    ],
    "sg:phone":"+1   ",
    "sg:postcode":"08534",
    "sg:province":"NJ",
    "sg:tags":[
        "mail",
        "house"
    ],
    "wof:name":"Karen Ogren",
    "wof:placetype":"venue"
},
  "geometry": {"coordinates":[-74.78825999999999,40.321656],"type":"Point"}
}