{
  "type": "Feature",
  "properties": {
    "iso:country":"US",
    "sg:address":"113 Hillside Ave",
    "sg:city":"Verona",
    "sg:classifiers":[
        {
            "category":"Autos & Motor Vehicles",
            "subcategory":"Auto Supplies",
            "type":"Retail Goods"
        }
    ],
    "sg:phone":"+1   ",
    "sg:postcode":"07044",
    "sg:province":"NJ",
    "wof:name":"Njg Wholesalers Inc",
    "wof:placetype":"venue"
},
  "geometry": {"coordinates":[-74.260384,40.82774],"type":"Point"}
}