{
  "type": "Feature",
  "properties": {
    "addr:full":"13 Beech St Ramsey NJ 07446",
    "addr:housenumber":"13",
    "addr:postcode":"07446",
    "addr:street":"Beech St",
    "iso:country":"US",
    "sg:address":"13 Beech St",
    "sg:city":"Ramsey",
    "sg:classifiers":[
        {
            "category":"Professional",
            "type":"Services"
        }
    ],
    "sg:phone":"+1   ",
    "sg:postcode":"07446",
    "sg:province":"NJ",
    "wof:name":"Ceramico",
    "wof:placetype":"venue"
},
  "geometry": {"coordinates":[-74.154318,41.065465],"type":"Point"}
}