{
  "type": "Feature",
  "properties": {
    "addr:full":"30 Oak Rd Boonton NJ 07005",
    "addr:housenumber":"30",
    "addr:postcode":"07005",
    "addr:street":"Oak Rd",
    "iso:country":"US",
    "sg:address":"30 Oak Rd",
    "sg:city":"Boonton",
    "sg:classifiers":[
        {
            "category":"Building & Trades",
            "subcategory":"Construction",
            "type":"Services"
        }
    ],
    "sg:phone":"+1 973 316 5513",
    "sg:postcode":"07005",
    "sg:province":"NJ",
    "sg:tags":[
        "contractor"
    ],
    "wof:name":"J K Stickle Building Contrs",
    "wof:placetype":"venue"
},
  "geometry": {"coordinates":[-74.42424,40.920983],"type":"Point"}
}