{
  "type": "Feature",
  "properties": {
    "addr:full":"542 Prospect Ave Little Silver NJ 07739",
    "addr:housenumber":"542",
    "addr:postcode":"07739",
    "addr:street":"Prospect Ave",
    "iso:country":"US",
    "sg:address":"542 Prospect Ave",
    "sg:city":"Little Silver",
    "sg:classifiers":[
        {
            "category":"Professional",
            "subcategory":"Engineering",
            "type":"Services"
        }
    ],
    "sg:phone":"+1 732 842 2303",
    "sg:postcode":"07739",
    "sg:province":"NJ",
    "sg:tags":[
        "civil",
        "structural",
        "engineer"
    ],
    "wof:name":"ABH Design Group",
    "wof:placetype":"venue"
},
  "geometry": {"coordinates":[-74.04047,40.337556],"type":"Point"}
}