{
  "type": "Feature",
  "properties": {
    "addr:full":"10 Lawrence Dr Brick NJ 08724",
    "addr:housenumber":"10",
    "addr:postcode":"08724",
    "addr:street":"Lawrence Dr",
    "iso:country":"US",
    "sg:address":"10 Lawrence Dr",
    "sg:city":"Brick",
    "sg:classifiers":[
        {
            "category":"Manufacturing",
            "subcategory":"Retail Goods",
            "type":"Manufacturing & Wholesale Goods"
        }
    ],
    "sg:phone":"+1 732 295 7589",
    "sg:postcode":"08724",
    "sg:province":"NJ",
    "sg:tags":[
        "product",
        "mfg"
    ],
    "wof:name":"Debara M Mayo",
    "wof:placetype":"venue"
},
  "geometry": {"coordinates":[-74.114339,40.06078],"type":"Point"}
}