{
  "type": "Feature",
  "properties": {
    "addr:full":"2201 74th St North Bergen NJ 07047",
    "addr:housenumber":"2201",
    "addr:postcode":"07047",
    "addr:street":"74Th St",
    "iso:country":"US",
    "sg:address":"2201 74th St",
    "sg:city":"North Bergen",
    "sg:classifiers":[
        {
            "category":"Shopping",
            "subcategory":"Jewelry",
            "type":"Retail Goods"
        }
    ],
    "sg:phone":"+1 201 453 0040",
    "sg:postcode":"07047",
    "sg:province":"NJ",
    "sg:tags":[
        "jeweler"
    ],
    "sg:website":"www.onyxwel.com",
    "wof:name":"Onyx Collections",
    "wof:placetype":"venue"
},
  "geometry": {"coordinates":[-74.021061,40.803263],"type":"Point"}
}