{
  "type": "Feature",
  "properties": {
    "iso:country":"US",
    "sg:address":"2141 Woodbridge Ave",
    "sg:city":"Edison",
    "sg:classifiers":[
        {
            "category":"Home & Garden",
            "subcategory":"Carpets & Floor Coverings",
            "type":"Retail Goods"
        }
    ],
    "sg:phone":"+1   ",
    "sg:postcode":"08817",
    "sg:province":"NJ",
    "sg:tags":[
        "installation",
        "sales"
    ],
    "wof:name":"Alan Peck Carpet Inc",
    "wof:placetype":"venue"
},
  "geometry": {"coordinates":[-74.39535100000001,40.501012],"type":"Point"}
}