{
  "type": "Feature",
  "properties": {
    "iso:country":"US",
    "sg:address":"23 Tindall Rd",
    "sg:city":"Middletown",
    "sg:classifiers":[
        {
            "category":"Insurance",
            "subcategory":"Insurance Agent",
            "type":"Services"
        }
    ],
    "sg:phone":"+1 732 671 9455",
    "sg:postcode":"07748",
    "sg:province":"NJ",
    "sg:tags":[
        "consultant"
    ],
    "wof:name":"Web Insurance Consultants Inc",
    "wof:placetype":"venue"
},
  "geometry": {"coordinates":[-74.101375,40.395031],"type":"Point"}
}