{
  "type": "Feature",
  "properties": {
    "addr:full":"5 Tomalyn Hill Rd Montville NJ 07045",
    "addr:housenumber":"5",
    "addr:postcode":"07045",
    "addr:street":"Tomalyn Hill Rd",
    "iso:country":"US",
    "sg:address":"5 Tomalyn Hill Rd",
    "sg:city":"Montville",
    "sg:classifiers":[
        {
            "category":"Professional",
            "subcategory":"Business Services",
            "type":"Services"
        }
    ],
    "sg:phone":"+1   ",
    "sg:postcode":"07045",
    "sg:province":"NJ",
    "wof:name":"Indian Community Center C",
    "wof:placetype":"venue"
},
  "geometry": {"coordinates":[-74.35787999999999,40.902561],"type":"Point"}
}