{
  "type": "Feature",
  "properties": {
    "addr:full":"150 E Main St Marlton NJ 08053",
    "addr:housenumber":"150",
    "addr:postcode":"08053",
    "addr:street":"E Main St",
    "iso:country":"US",
    "sg:address":"150 E Main St",
    "sg:city":"Marlton",
    "sg:classifiers":[
        {
            "category":"Building & Trades",
            "subcategory":"Construction",
            "type":"Services"
        }
    ],
    "sg:phone":"+1 856 810 0586",
    "sg:postcode":"08053",
    "sg:province":"NJ",
    "sg:tags":[
        "contractor"
    ],
    "wof:name":"Orleans Builders Inc",
    "wof:placetype":"venue"
},
  "geometry": {"coordinates":[-74.906588,39.885401],"type":"Point"}
}