{
  "type": "Feature",
  "properties": {
    "iso:country":"US",
    "sg:address":"630 Washington St",
    "sg:city":"Hoboken",
    "sg:classifiers":[
        {
            "category":"Restaurant",
            "type":"Food & Drink"
        }
    ],
    "sg:phone":"+1   ",
    "sg:postcode":"07030",
    "sg:province":"NJ",
    "sg:tags":[
        "eating"
    ],
    "wof:name":"Chicken & Rib Crib",
    "wof:placetype":"venue"
},
  "geometry": {"coordinates":[-74.02883199999999,40.744357],"type":"Point"}
}