{
  "type": "Feature",
  "properties": {
    "addr:full":"85 State Park Rd Blairstown NJ 07825",
    "addr:housenumber":"85",
    "addr:postcode":"07825",
    "addr:street":"State Park Rd",
    "iso:country":"US",
    "sg:address":"85 State Park Rd",
    "sg:city":"Blairstown",
    "sg:classifiers":[
        {
            "category":"Building & Trades",
            "subcategory":"Construction",
            "type":"Services"
        }
    ],
    "sg:phone":"+1 570 897 6627",
    "sg:postcode":"07825",
    "sg:province":"NJ",
    "sg:tags":[
        "underground",
        "demolition",
        "tank",
        "storage",
        "removal"
    ],
    "wof:name":"Res Inc",
    "wof:placetype":"venue"
},
  "geometry": {"coordinates":[-74.92429799999999,40.926418],"type":"Point"}
}