{
  "type": "Feature",
  "properties": {
    "iso:country":"US",
    "sg:address":"317 Arnold Ave",
    "sg:city":"Point Pleasant Beach",
    "sg:classifiers":[
        {
            "category":"Professional",
            "type":"Services"
        }
    ],
    "sg:phone":"+1   ",
    "sg:postcode":"08742",
    "sg:province":"NJ",
    "wof:name":"118 By Ocean Inc",
    "wof:placetype":"venue"
},
  "geometry": {"coordinates":[-74.04588200000001,40.092119],"type":"Point"}
}