{
  "type": "Feature",
  "properties": {
    "addr:full":"511 Franklin Ave Belleville NJ 07109",
    "addr:housenumber":"511",
    "addr:postcode":"07109",
    "addr:street":"Franklin Ave",
    "iso:country":"US",
    "sg:address":"511 Franklin Ave",
    "sg:city":"Belleville",
    "sg:classifiers":[
        {
            "category":"Building & Trades",
            "subcategory":"Construction",
            "type":"Services"
        }
    ],
    "sg:phone":"+1 973 661 2308",
    "sg:postcode":"07109",
    "sg:province":"NJ",
    "sg:tags":[
        "hanging",
        "contractor"
    ],
    "wof:name":"Capasso Painting",
    "wof:placetype":"venue"
},
  "geometry": {"coordinates":[-74.167466,40.807103],"type":"Point"}
}