{
  "type": "Feature",
  "properties": {
    "iso:country":"US",
    "sg:address":"2035 John F Kennedy Blvd",
    "sg:city":"North Bergen",
    "sg:classifiers":[
        {
            "category":"Real Estate",
            "subcategory":"Real Estate Services",
            "type":"Services"
        }
    ],
    "sg:phone":"+1 201 863 5555",
    "sg:postcode":"07305",
    "sg:province":"NJ",
    "sg:tags":[
        "management",
        "property"
    ],
    "wof:name":"Tri-City Realty",
    "wof:placetype":"venue"
},
  "geometry": {"coordinates":[-74.04109699999999,40.768135],"type":"Point"}
}