{
  "type": "Feature",
  "properties": {
    "iso:country":"US",
    "sg:address":"608 Florence Rd",
    "sg:city":"Westwood",
    "sg:classifiers":[
        {
            "category":"Real Estate",
            "subcategory":"Real Estate Agent",
            "type":"Services"
        }
    ],
    "sg:phone":"+1   ",
    "sg:postcode":"07675",
    "sg:province":"NJ",
    "wof:name":"Rite Aid Real Est 9601",
    "wof:placetype":"venue"
},
  "geometry": {"coordinates":[-74.004299,41.000125],"type":"Point"}
}