{
  "type": "Feature",
  "properties": {
    "addr:full":"539 Forest Ave Paramus NJ 07652",
    "addr:housenumber":"539",
    "addr:postcode":"07652",
    "addr:street":"Forest Ave",
    "iso:country":"US",
    "sg:address":"539 Forest Ave",
    "sg:city":"Paramus",
    "sg:classifiers":[
        {
            "category":"Autos & Motor Vehicles",
            "subcategory":"Fuel & Gas Station",
            "type":"Retail Goods"
        }
    ],
    "sg:phone":"+1   ",
    "sg:postcode":"07652",
    "sg:province":"NJ",
    "sg:tags":[
        "station",
        "gasoline"
    ],
    "wof:name":"Citgo",
    "wof:placetype":"venue"
},
  "geometry": {"coordinates":[-74.05116599999999,40.950706],"type":"Point"}
}