{
  "type": "Feature",
  "properties": {
    "addr:full":"262 22nd Ave Paterson NJ 07513",
    "addr:housenumber":"262",
    "addr:postcode":"07513",
    "addr:street":"22Nd Ave",
    "iso:country":"US",
    "sg:address":"262 22nd Ave",
    "sg:city":"Paterson",
    "sg:classifiers":[
        {
            "category":"Retail",
            "subcategory":"Self-service Laundry",
            "type":"Services"
        }
    ],
    "sg:phone":"+1 973 523 9991",
    "sg:postcode":"07513",
    "sg:province":"NJ",
    "wof:name":"Splash Laundromat",
    "wof:placetype":"venue"
},
  "geometry": {"coordinates":[-74.145203,40.903015],"type":"Point"}
}