{
  "type": "Feature",
  "properties": {
    "addr:full":"1248 Mount Horeb Rd Martinsville NJ 08836",
    "addr:housenumber":"1248",
    "addr:postcode":"08836",
    "addr:street":"Mount Horeb Rd",
    "iso:country":"US",
    "sg:address":"1248 Mount Horeb Rd",
    "sg:city":"Martinsville",
    "sg:classifiers":[
        {
            "category":"Bars & Pubs",
            "type":"Food & Drink"
        }
    ],
    "sg:phone":"+1   ",
    "sg:postcode":"08836",
    "sg:province":"NJ",
    "sg:tags":[
        "drinking"
    ],
    "wof:name":"Showplace Go Go Lounge",
    "wof:placetype":"venue"
},
  "geometry": {"coordinates":[-74.56380799999999,40.602845],"type":"Point"}
}