{
  "type": "Feature",
  "properties": {
    "iso:country":"US",
    "sg:address":"138 Brookside Ln",
    "sg:city":"Hillsborough",
    "sg:classifiers":[
        {
            "category":"Building & Trades",
            "subcategory":"Construction",
            "type":"Services"
        }
    ],
    "sg:phone":"+1 908 874 0818",
    "sg:postcode":"08844",
    "sg:province":"NJ",
    "sg:tags":[
        "specialty"
    ],
    "wof:name":"Earcorp of New Jersey",
    "wof:placetype":"venue"
},
  "geometry": {"coordinates":[-74.637044,40.511846],"type":"Point"}
}