{
  "type": "Feature",
  "properties": {
    "iso:country":"US",
    "sg:address":"740 Anderson Ave",
    "sg:city":"Cliffside Park",
    "sg:classifiers":[
        {
            "category":"Shopping",
            "subcategory":"Optical Goods",
            "type":"Retail Goods"
        }
    ],
    "sg:phone":"+1   ",
    "sg:postcode":"07010",
    "sg:province":"NJ",
    "wof:name":"Cliffside Park Eye Assoc",
    "wof:placetype":"venue"
},
  "geometry": {"coordinates":[-73.98564,40.830024],"type":"Point"}
}