{
  "type": "Feature",
  "properties": {
    "addr:full":"88 Merritt Dr Oradell NJ 07649",
    "addr:housenumber":"88",
    "addr:postcode":"07649",
    "addr:street":"Merritt Dr",
    "iso:country":"US",
    "sg:address":"88 Merritt Dr",
    "sg:city":"Oradell",
    "sg:classifiers":[
        {
            "category":"Professional",
            "subcategory":"Advertising",
            "type":"Services"
        }
    ],
    "sg:phone":"+1 201 387 7677",
    "sg:postcode":"07649",
    "sg:province":"NJ",
    "sg:tags":[
        "travel",
        "agency"
    ],
    "wof:name":"Ross Associates",
    "wof:placetype":"venue"
},
  "geometry": {"coordinates":[-74.009675,40.952544],"type":"Point"}
}