{
  "type": "Feature",
  "properties": {
    "iso:country":"US",
    "sg:address":"1577 Reed Rd",
    "sg:city":"Pennington",
    "sg:classifiers":[
        {
            "category":"Retail",
            "subcategory":"Repair Shop",
            "type":"Services"
        }
    ],
    "sg:phone":"+1 609 737 8100",
    "sg:postcode":"08534",
    "sg:province":"NJ",
    "sg:tags":[
        "lock",
        "locksmith"
    ],
    "sg:website":"www.hogansecuritygroup.com",
    "wof:name":"Hogan Security Group",
    "wof:placetype":"venue"
},
  "geometry": {"coordinates":[-74.797676,40.29259],"type":"Point"}
}