{
  "type": "Feature",
  "properties": {
    "iso:country":"US",
    "sg:address":"331 Lakeview Ave",
    "sg:city":"Clifton",
    "sg:classifiers":[
        {
            "category":"Retail",
            "subcategory":"Repair Shop",
            "type":"Services"
        }
    ],
    "sg:phone":"+1 973 340 0414",
    "sg:postcode":"07011",
    "sg:province":"NJ",
    "sg:tags":[
        "watch",
        "jewelry"
    ],
    "wof:name":"Arthur Smetana & Sons",
    "wof:placetype":"venue"
},
  "geometry": {"coordinates":[-74.138454,40.886634],"type":"Point"}
}