{
  "type": "Feature",
  "properties": {
    "addr:full":"1038 Sheila Dr Toms River NJ 08753",
    "addr:housenumber":"1038",
    "addr:postcode":"08753",
    "addr:street":"Sheila Dr",
    "iso:country":"US",
    "sg:address":"1038 Sheila Dr",
    "sg:city":"Toms River",
    "sg:classifiers":[
        {
            "category":"Retail",
            "subcategory":"Auto Repair",
            "type":"Services"
        }
    ],
    "sg:phone":"+1 732 506 7944",
    "sg:postcode":"08753",
    "sg:province":"NJ",
    "sg:tags":[
        "body"
    ],
    "wof:name":"Baby Your Body",
    "wof:placetype":"venue"
},
  "geometry": {"coordinates":[-74.15368599999999,39.977991],"type":"Point"}
}