{
  "type": "Feature",
  "properties": {
    "iso:country":"US",
    "sg:address":"72 Co Rd 537",
    "sg:city":"Colts Neck",
    "sg:classifiers":[
        {
            "category":"Social Services",
            "subcategory":"Child Care",
            "type":"Services"
        }
    ],
    "sg:phone":"+1 732 462 4662",
    "sg:postcode":"07722",
    "sg:province":"NJ",
    "sg:tags":[
        "kindergarten",
        "academic",
        "school"
    ],
    "wof:name":"Reformed Church Nursery School",
    "wof:placetype":"venue"
},
  "geometry": {"coordinates":[-74.17856399999999,40.28693],"type":"Point"}
}