{
  "type": "Feature",
  "properties": {
    "iso:country":"US",
    "sg:address":"1 Palisade Ave",
    "sg:city":"Emerson",
    "sg:classifiers":[
        {
            "category":"Manufacturing",
            "subcategory":"Tools & Machinery",
            "type":"Manufacturing & Wholesale Goods"
        }
    ],
    "sg:phone":"+1 201 265 8868",
    "sg:postcode":"07630",
    "sg:province":"NJ",
    "sg:tags":[
        "manufacture",
        "diamond",
        "cutting"
    ],
    "sg:website":"www.accuratediamondtool.com",
    "wof:name":"Accurate Diamond Tool Corp",
    "wof:placetype":"venue"
},
  "geometry": {"coordinates":[-74.02742000000001,40.972828],"type":"Point"}
}