{
  "type": "Feature",
  "properties": {
    "addr:full":"112 Hixson Rd Flemington NJ 08822",
    "addr:housenumber":"112",
    "addr:postcode":"08822",
    "addr:street":"Hixson Rd",
    "iso:country":"US",
    "sg:address":"112 Hixson Rd",
    "sg:city":"Flemington",
    "sg:classifiers":[
        {
            "category":"Health Services",
            "subcategory":"Clinic",
            "type":"Services"
        }
    ],
    "sg:phone":"+1 908 788 3712",
    "sg:postcode":"08822",
    "sg:province":"NJ",
    "sg:tags":[
        "professional"
    ],
    "wof:name":"Creative Concepts Company",
    "wof:placetype":"venue"
},
  "geometry": {"coordinates":[-74.78299199999999,40.539072],"type":"Point"}
}