{
  "type": "Feature",
  "properties": {
    "addr:full":"379 Thornall St Edison NJ 08837",
    "addr:housenumber":"379",
    "addr:postcode":"08837",
    "addr:street":"Thornall St",
    "iso:country":"US",
    "sg:address":"379 Thornall St",
    "sg:city":"Edison",
    "sg:classifiers":[
        {
            "category":"Professional",
            "subcategory":"Management & Consulting",
            "type":"Services"
        }
    ],
    "sg:phone":"+1   ",
    "sg:postcode":"08837",
    "sg:province":"NJ",
    "sg:tags":[
        "consultant",
        "telecommunication",
        "enhancement"
    ],
    "wof:name":"Call Sciences Inc",
    "wof:placetype":"venue"
},
  "geometry": {"coordinates":[-74.332121,40.564518],"type":"Point"}
}