{
  "type": "Feature",
  "properties": {
    "addr:full":"979 Edinburgh Dr Toms River NJ 08753",
    "addr:housenumber":"979",
    "addr:postcode":"08753",
    "addr:street":"Edinburgh Dr",
    "iso:country":"US",
    "sg:address":"979 Edinburgh Dr",
    "sg:city":"Toms River",
    "sg:classifiers":[
        {
            "category":"Building & Trades",
            "subcategory":"Construction",
            "type":"Services"
        }
    ],
    "sg:phone":"+1 732 929 0500",
    "sg:postcode":"08753",
    "sg:province":"NJ",
    "sg:tags":[
        "layer",
        "contractor",
        "laying",
        "floor",
        "carpet"
    ],
    "wof:name":"Custom Rug Installations",
    "wof:placetype":"venue"
},
  "geometry": {"coordinates":[-74.15124400000001,39.96445],"type":"Point"}
}