{
  "type": "Feature",
  "properties": {
    "addr:full":"92 Fairview Ave Jersey City NJ 07304",
    "addr:housenumber":"92",
    "addr:postcode":"07304",
    "addr:street":"Fairview Ave",
    "iso:country":"US",
    "sg:address":"92 Fairview Ave",
    "sg:city":"Jersey City",
    "sg:classifiers":[
        {
            "category":"Personal",
            "subcategory":"Beauty Salon",
            "type":"Services"
        }
    ],
    "sg:phone":"+1 201 453 1003",
    "sg:postcode":"07304",
    "sg:province":"NJ",
    "sg:tags":[
        "shop"
    ],
    "wof:name":"Super Brows Beauty Salon",
    "wof:placetype":"venue"
},
  "geometry": {"coordinates":[-74.072804,40.723737],"type":"Point"}
}