{
  "type": "Feature",
  "properties": {
    "addr:full":"21 Gemini Ln Englishtown NJ 07726",
    "addr:housenumber":"21",
    "addr:postcode":"07726",
    "addr:street":"Gemini Ln",
    "iso:country":"US",
    "sg:address":"21 Gemini Ln",
    "sg:city":"Englishtown",
    "sg:classifiers":[
        {
            "category":"Professional",
            "subcategory":"Lawyer & Legal Services",
            "type":"Services"
        }
    ],
    "sg:phone":"+1   ",
    "sg:postcode":"07726",
    "sg:province":"NJ",
    "wof:name":"Beth B Reisman-Sholom Es",
    "wof:placetype":"venue"
},
  "geometry": {"coordinates":[-74.346447,40.234783],"type":"Point"}
}