{
  "type": "Feature",
  "properties": {
    "addr:full":"110 Quimby St Westfield NJ 07090",
    "addr:housenumber":"110",
    "addr:postcode":"07090",
    "addr:street":"Quimby St",
    "iso:country":"US",
    "sg:address":"110 Quimby St",
    "sg:city":"Westfield",
    "sg:classifiers":[
        {
            "category":"Personal",
            "subcategory":"Beauty Salon",
            "type":"Services"
        }
    ],
    "sg:phone":"+1 908 928 1901",
    "sg:postcode":"07090",
    "sg:province":"NJ",
    "wof:name":"Westfield Hair Co",
    "wof:placetype":"venue"
},
  "geometry": {"coordinates":[-74.34779,40.650818],"type":"Point"}
}