{
  "type": "Feature",
  "properties": {
    "iso:country":"US",
    "sg:address":"110 E Midland Ave",
    "sg:city":"Paramus",
    "sg:classifiers":[
        {
            "category":"Professional",
            "subcategory":"Art Services",
            "type":"Services"
        }
    ],
    "sg:phone":"+1 201 634 0583",
    "sg:postcode":"07652",
    "sg:province":"NJ",
    "sg:tags":[
        "photo",
        "canvas",
        "to"
    ],
    "wof:name":"Image 2 Art Inc",
    "wof:placetype":"venue"
},
  "geometry": {"coordinates":[-74.06291,40.948989],"type":"Point"}
}