{
  "type": "Feature",
  "properties": {
    "addr:full":"102 Rafkind Rd Bloomingdale NJ 07403",
    "addr:housenumber":"102",
    "addr:postcode":"07403",
    "addr:street":"Rafkind Rd",
    "iso:country":"US",
    "sg:address":"102 Rafkind Rd",
    "sg:city":"Bloomingdale",
    "sg:classifiers":[
        {
            "category":"Professional",
            "subcategory":"Secretarial Services",
            "type":"Services"
        }
    ],
    "sg:phone":"+1   ",
    "sg:postcode":"07403",
    "sg:province":"NJ",
    "sg:tags":[
        "reporting"
    ],
    "wof:name":"Cg Services",
    "wof:placetype":"venue"
},
  "geometry": {"coordinates":[-74.326297,41.013134],"type":"Point"}
}