{
  "type": "Feature",
  "properties": {
    "iso:country":"US",
    "sg:address":"1000 Mount Kemble Ave",
    "sg:city":"Morristown",
    "sg:classifiers":[
        {
            "category":"Shopping",
            "subcategory":"Clothing, Apparel, & Fashions",
            "type":"Retail Goods"
        }
    ],
    "sg:phone":"+1 973 425 5873",
    "sg:postcode":"07960",
    "sg:province":"NJ",
    "sg:tags":[
        "accessory"
    ],
    "wof:name":"The Talbots",
    "wof:placetype":"venue"
},
  "geometry": {"coordinates":[-74.52179700000001,40.759102],"type":"Point"}
}