{
  "type": "Feature",
  "properties": {
    "addr:full":"230 Moses Milch Dr Howell NJ 07731",
    "addr:housenumber":"230",
    "addr:postcode":"07731",
    "addr:street":"Moses Milch Dr",
    "iso:country":"US",
    "sg:address":"230 Moses Milch Dr",
    "sg:city":"Howell",
    "sg:classifiers":[
        {
            "category":"Building & Trades",
            "subcategory":"Construction",
            "type":"Services"
        }
    ],
    "sg:phone":"+1 732 785 2559",
    "sg:postcode":"07731",
    "sg:province":"NJ",
    "sg:tags":[
        "fire",
        "restoration",
        "damage"
    ],
    "wof:name":"American Lifestyle Contracting",
    "wof:placetype":"venue"
},
  "geometry": {"coordinates":[-74.156497,40.107973],"type":"Point"}
}