{
  "type": "Feature",
  "properties": {
    "addr:full":"62 15th St Toms River NJ 08753",
    "addr:housenumber":"62",
    "addr:postcode":"08753",
    "addr:street":"15Th St",
    "iso:country":"US",
    "sg:address":"62 15th St",
    "sg:city":"Toms River",
    "sg:classifiers":[
        {
            "category":"Professional",
            "type":"Services"
        }
    ],
    "sg:phone":"+1   ",
    "sg:postcode":"08753",
    "sg:province":"NJ",
    "wof:name":"Wind River Systems Inc",
    "wof:placetype":"venue"
},
  "geometry": {"coordinates":[-74.12479,40.009014],"type":"Point"}
}