{
  "type": "Feature",
  "properties": {
    "addr:full":"750 N Broad St Elizabeth NJ 07208",
    "addr:housenumber":"750",
    "addr:postcode":"07208",
    "addr:street":"N Broad St",
    "iso:country":"US",
    "sg:address":"750 N Broad St",
    "sg:city":"Elizabeth",
    "sg:classifiers":[
        {
            "category":"Real Estate",
            "subcategory":"Real Estate Operator",
            "type":"Services"
        }
    ],
    "sg:phone":"+1 908 352 2361",
    "sg:postcode":"07208",
    "sg:province":"NJ",
    "sg:tags":[
        "apartment"
    ],
    "wof:name":"Imperial Broad Assoc",
    "wof:placetype":"venue"
},
  "geometry": {"coordinates":[-74.21427,40.682275],"type":"Point"}
}