{
  "type": "Feature",
  "properties": {
    "iso:country":"US",
    "sg:address":"12 Roszel Rd",
    "sg:city":"Princeton",
    "sg:classifiers":[
        {
            "category":"Professional",
            "subcategory":"Employment Agencies",
            "type":"Services"
        }
    ],
    "sg:phone":"+1 609 452 0175",
    "sg:postcode":"08540",
    "sg:province":"NJ",
    "sg:tags":[
        "consultant",
        "search",
        "executive"
    ],
    "wof:name":"Pomerantz Search Group",
    "wof:placetype":"venue"
},
  "geometry": {"coordinates":[-74.63752700000001,40.3214],"type":"Point"}
}