{
  "type": "Feature",
  "properties": {
    "addr:full":"795 State St Perth Amboy NJ 08861",
    "addr:housenumber":"795",
    "addr:postcode":"08861",
    "addr:street":"State St",
    "iso:country":"US",
    "sg:address":"795 State St",
    "sg:city":"Perth Amboy",
    "sg:classifiers":[
        {
            "category":"Organizations",
            "subcategory":"Religious Organization",
            "type":"Services"
        }
    ],
    "sg:phone":"+1 732 826 0877",
    "sg:postcode":"08861",
    "sg:province":"NJ",
    "sg:tags":[
        "church"
    ],
    "wof:name":"Concord Missionary Baptist Chr",
    "wof:placetype":"venue"
},
  "geometry": {"coordinates":[-74.26474399999999,40.52504],"type":"Point"}
}