{
  "type": "Feature",
  "properties": {
    "iso:country":"US",
    "sg:address":"243 Sherman Ave",
    "sg:city":"Jersey City",
    "sg:classifiers":[
        {
            "category":"Building & Trades",
            "subcategory":"Construction",
            "type":"Services"
        }
    ],
    "sg:phone":"+1 201 963 3681",
    "sg:postcode":"07307",
    "sg:province":"NJ",
    "sg:tags":[
        "home",
        "remodeling"
    ],
    "wof:name":"G N R Contractors Inc",
    "wof:placetype":"venue"
},
  "geometry": {"coordinates":[-74.044062,40.749392],"type":"Point"}
}