{
  "type": "Feature",
  "properties": {
    "addr:full":"90 Broad St Red Bank NJ 07701",
    "addr:housenumber":"90",
    "addr:postcode":"07701",
    "addr:street":"Broad St",
    "iso:country":"US",
    "sg:address":"90 Broad St",
    "sg:city":"Red Bank",
    "sg:classifiers":[
        {
            "category":"Restaurant",
            "type":"Food & Drink"
        },
        {
            "category":"Ice Cream",
            "type":"Food & Drink"
        }
    ],
    "sg:menulink":"http://www.allmenus.com/nj/red-bank/232626-haagen-dazs/menu/",
    "sg:phone":"+1 732 747 6978",
    "sg:postcode":"07701",
    "sg:province":"NJ",
    "sg:tags":[
        "american",
        "ice",
        "cream"
    ],
    "wof:name":"Haagen Dazs",
    "wof:placetype":"venue"
},
  "geometry": {"coordinates":[-74.065279,40.349227],"type":"Point"}
}