{
  "type": "Feature",
  "properties": {
    "addr:full":"190 Market St Saddle Brook NJ 07663",
    "addr:housenumber":"190",
    "addr:postcode":"07663",
    "addr:street":"Market St",
    "iso:country":"US",
    "sg:address":"190 Market St",
    "sg:city":"Saddle Brook",
    "sg:classifiers":[
        {
            "category":"Building & Trades",
            "subcategory":"Construction",
            "type":"Services"
        }
    ],
    "sg:phone":"+1 201 368 8060",
    "sg:postcode":"07663",
    "sg:province":"NJ",
    "sg:tags":[
        "contractor"
    ],
    "wof:name":"O'keefe Construction Inc",
    "wof:placetype":"venue"
},
  "geometry": {"coordinates":[-74.08722299999999,40.895724],"type":"Point"}
}