{
  "type": "Feature",
  "properties": {
    "iso:country":"US",
    "sg:address":"1147 Stanton Lebanon Rd",
    "sg:city":"Lebanon",
    "sg:classifiers":[
        {
            "category":"Building & Trades",
            "subcategory":"Construction",
            "type":"Services"
        }
    ],
    "sg:phone":"+1 908 236 9906",
    "sg:postcode":"08833",
    "sg:province":"NJ",
    "sg:tags":[
        "natural",
        "station",
        "gas",
        "compressor"
    ],
    "wof:name":"Gas Management Systems LLC",
    "wof:placetype":"venue"
},
  "geometry": {"coordinates":[-74.85924900000001,40.611578],"type":"Point"}
}