{
  "type": "Feature",
  "properties": {
    "iso:country":"US",
    "sg:address":"7 Sioux Trl",
    "sg:city":"Browns Mills",
    "sg:classifiers":[
        {
            "category":"Building & Trades",
            "subcategory":"Cleaning & Sanitation",
            "type":"Services"
        }
    ],
    "sg:phone":"+1 609 893 4091",
    "sg:postcode":"08015",
    "sg:province":"NJ",
    "sg:tags":[
        "maintenance"
    ],
    "wof:name":"Johnson Janitorial Service",
    "wof:placetype":"venue"
},
  "geometry": {"coordinates":[-74.55079000000001,39.948135],"type":"Point"}
}