{
  "type": "Feature",
  "properties": {
    "iso:country":"US",
    "sg:address":"130 Main St",
    "sg:city":"Butler",
    "sg:classifiers":[
        {
            "category":"Banks & Credit Unions",
            "subcategory":"Bank",
            "type":"Services"
        }
    ],
    "sg:phone":"+1 973 838 2750",
    "sg:postcode":"07405",
    "sg:province":"NJ",
    "wof:name":"Glen Ridge Savings Bank Sla",
    "wof:placetype":"venue"
},
  "geometry": {"coordinates":[-74.339461,41.002504],"type":"Point"}
}