{
  "type": "Feature",
  "properties": {
    "iso:country":"US",
    "sg:address":"12 Oakland Rd",
    "sg:city":"Maplewood",
    "sg:classifiers":[
        {
            "category":"Building & Trades",
            "subcategory":"Construction",
            "type":"Services"
        }
    ],
    "sg:phone":"+1 973 762 8035",
    "sg:postcode":"07040",
    "sg:province":"NJ",
    "sg:tags":[
        "house"
    ],
    "wof:name":"He Nonemaker Inc",
    "wof:placetype":"venue"
},
  "geometry": {"coordinates":[-74.269976,40.731761],"type":"Point"}
}