{
  "type": "Feature",
  "properties": {
    "iso:country":"US",
    "sg:address":"24 S Kinderkamack Rd",
    "sg:city":"Montvale",
    "sg:classifiers":[
        {
            "category":"Banks & Credit Unions",
            "subcategory":"Bank",
            "type":"Services"
        }
    ],
    "sg:phone":"+1 201 000 1111",
    "sg:postcode":"07645",
    "sg:province":"NJ",
    "wof:name":"Valley National Bank",
    "wof:placetype":"venue"
},
  "geometry": {"coordinates":[-74.02991400000001,41.038182],"type":"Point"}
}