{
  "type": "Feature",
  "properties": {
    "iso:country":"US",
    "sg:address":"21 Neville Dr",
    "sg:city":"Lincroft",
    "sg:classifiers":[
        {
            "category":"Home & Garden",
            "subcategory":"Furniture",
            "type":"Retail Goods"
        }
    ],
    "sg:phone":"+1   ",
    "sg:postcode":"07738",
    "sg:province":"NJ",
    "wof:name":"Y&P Furniture Inc",
    "wof:placetype":"venue"
},
  "geometry": {"coordinates":[-74.105757,40.337498],"type":"Point"}
}