{
  "type": "Feature",
  "properties": {
    "iso:country":"US",
    "sg:address":"400 Valley Brook Ave",
    "sg:city":"Lyndhurst",
    "sg:classifiers":[
        {
            "category":"Wholesale",
            "subcategory":"Drugs",
            "type":"Manufacturing & Wholesale Goods"
        }
    ],
    "sg:phone":"+1 201 896 8139",
    "sg:postcode":"07071",
    "sg:province":"NJ",
    "wof:name":"Nsd Trading",
    "wof:placetype":"venue"
},
  "geometry": {"coordinates":[-74.124706,40.812071],"type":"Point"}
}