{
  "type": "Feature",
  "properties": {
    "iso:country":"US",
    "sg:address":"40 Drexel Ter",
    "sg:city":"Monroe Twp",
    "sg:classifiers":[
        {
            "category":"Building & Trades",
            "subcategory":"Construction",
            "type":"Services"
        }
    ],
    "sg:phone":"+1 732 251 5792",
    "sg:postcode":"08831",
    "sg:province":"NJ",
    "sg:tags":[
        "planning",
        "remodeling",
        "kitchen"
    ],
    "wof:name":"Kitchens Baths & More",
    "wof:placetype":"venue"
},
  "geometry": {"coordinates":[-74.377949,40.373015],"type":"Point"}
}