{
  "type": "Feature",
  "properties": {
    "addr:full":"877 Main St Belford NJ 07718",
    "addr:housenumber":"877",
    "addr:postcode":"07718",
    "addr:street":"Main St",
    "iso:country":"US",
    "sg:address":"877 Main St",
    "sg:city":"Belford",
    "sg:classifiers":[
        {
            "category":"Shopping",
            "subcategory":"Discount & Variety Stores",
            "type":"Retail Goods"
        },
        {
            "category":"Shopping",
            "subcategory":"Department Store",
            "type":"Retail Goods"
        }
    ],
    "sg:phone":"+1 732 471 1941",
    "sg:postcode":"07718",
    "sg:province":"NJ",
    "sg:tags":[
        "shop"
    ],
    "wof:name":"Family Dollar Stores",
    "wof:placetype":"venue"
},
  "geometry": {"coordinates":[-74.093598,40.416712],"type":"Point"}
}