{
  "type": "Feature",
  "properties": {
    "iso:country":"US",
    "sg:address":"304 Haddon St",
    "sg:city":"Haddon Heights",
    "sg:classifiers":[
        {
            "category":"Professional",
            "subcategory":"Engineering",
            "type":"Services"
        }
    ],
    "sg:phone":"+1 856 546 8611",
    "sg:postcode":"08035",
    "sg:province":"NJ",
    "sg:tags":[
        "engineer"
    ],
    "sg:website":"www.bachdesigngroup.com",
    "wof:name":"Bach Associates",
    "wof:placetype":"venue"
},
  "geometry": {"coordinates":[-75.05099300000001,39.879681],"type":"Point"}
}