{
  "type": "Feature",
  "properties": {
    "addr:full":"125 Greenrale Ave Wayne NJ 07470",
    "addr:housenumber":"125",
    "addr:postcode":"07470",
    "addr:street":"Greenrale Ave",
    "iso:country":"US",
    "sg:address":"125 Greenrale Ave",
    "sg:city":"Wayne",
    "sg:classifiers":[
        {
            "category":"Professional",
            "subcategory":"Computer Services",
            "type":"Services"
        }
    ],
    "sg:phone":"+1 973 942 1371",
    "sg:postcode":"07470",
    "sg:province":"NJ",
    "sg:tags":[
        "prepackaged",
        "software"
    ],
    "wof:name":"Wizdata Systems Inc",
    "wof:placetype":"venue"
},
  "geometry": {"coordinates":[-74.22058199999999,40.945915],"type":"Point"}
}