{
  "type": "Feature",
  "properties": {
    "addr:full":"26 Wrightstown Cookstown Rd Cookstown NJ 08511",
    "addr:housenumber":"26",
    "addr:postcode":"08511",
    "addr:street":"Cookstown Rd",
    "iso:country":"US",
    "sg:address":"26 Wrightstown Cookstown Rd",
    "sg:city":"Cookstown",
    "sg:classifiers":[
        {
            "category":"Restaurant",
            "type":"Food & Drink"
        }
    ],
    "sg:phone":"+1 609 758 1103",
    "sg:postcode":"08511",
    "sg:province":"NJ",
    "wof:name":"Dave's Famous Subs",
    "wof:placetype":"venue"
},
  "geometry": {"coordinates":[-74.57628800000001,40.042643],"type":"Point"}
}