{
  "type": "Feature",
  "properties": {
    "iso:country":"US",
    "sg:address":"13 Orange Pl",
    "sg:city":"West Orange",
    "sg:classifiers":[
        {
            "category":"Wholesale",
            "subcategory":"Electrical",
            "type":"Manufacturing & Wholesale Goods"
        }
    ],
    "sg:phone":"+1 973 325 1333",
    "sg:postcode":"07052",
    "sg:province":"NJ",
    "sg:tags":[
        "control",
        "security",
        "system"
    ],
    "wof:name":"Fro Pro Alarms",
    "wof:placetype":"venue"
},
  "geometry": {"coordinates":[-74.232029,40.792602],"type":"Point"}
}