{
  "type": "Feature",
  "properties": {
    "iso:country":"US",
    "sg:address":"39 Hartmans Corner Rd",
    "sg:city":"Washington",
    "sg:classifiers":[
        {
            "category":"Manufacturing",
            "subcategory":"Electronics",
            "type":"Manufacturing & Wholesale Goods"
        }
    ],
    "sg:phone":"+1 908 453 3300",
    "sg:postcode":"07882",
    "sg:province":"NJ",
    "sg:tags":[
        "control",
        "electronic",
        "component",
        "mfg"
    ],
    "sg:website":"www.hazlabs.com",
    "wof:name":"HAZ Laboratories",
    "wof:placetype":"venue"
},
  "geometry": {"coordinates":[-75.023325,40.77068],"type":"Point"}
}