{
  "type": "Feature",
  "properties": {
    "iso:country":"US",
    "sg:address":"76 W Jimmie Leeds Rd",
    "sg:city":"Absecon",
    "sg:classifiers":[
        {
            "category":"Health Services",
            "subcategory":"Podiatrist",
            "type":"Services"
        },
        {
            "category":"Health Services",
            "subcategory":"Doctor",
            "type":"Services"
        }
    ],
    "sg:phone":"+1 609 404 1300",
    "sg:postcode":"08205",
    "sg:province":"NJ",
    "sg:tags":[
        "medical"
    ],
    "wof:name":"Atlantic Foot & Ankle Care",
    "wof:placetype":"venue"
},
  "geometry": {"coordinates":[-74.543722,39.476931],"type":"Point"}
}