{
  "type": "Feature",
  "properties": {
    "addr:full":"910 Haddonfield Berlin Rd Voorhees NJ 08043",
    "addr:housenumber":"910",
    "addr:postcode":"08043",
    "addr:street":"Haddonfield Berlin Rd",
    "iso:country":"US",
    "sg:address":"910 Haddonfield Berlin Rd",
    "sg:city":"Voorhees",
    "sg:classifiers":[
        {
            "category":"Food & Beverages",
            "subcategory":"Specialty",
            "type":"Retail Goods"
        }
    ],
    "sg:phone":"+1 856 346 6960",
    "sg:postcode":"08043",
    "sg:province":"NJ",
    "sg:tags":[
        "health",
        "diet"
    ],
    "wof:name":"GNC",
    "wof:placetype":"venue"
},
  "geometry": {"coordinates":[-74.981201,39.85251],"type":"Point"}
}