{
  "type": "Feature",
  "properties": {
    "addr:full":"4914 Kennedy Blvd W West New York NJ 07093",
    "addr:housenumber":"4914",
    "addr:postcode":"07093",
    "addr:street":"Kennedy Blvd W West",
    "iso:country":"US",
    "sg:address":"4914 Kennedy Blvd W",
    "sg:city":"West New York",
    "sg:classifiers":[
        {
            "category":"Shopping",
            "subcategory":"Beauty & Cosmetics",
            "type":"Retail Goods"
        }
    ],
    "sg:phone":"+1 201 865 3150",
    "sg:postcode":"07093",
    "sg:province":"NJ",
    "sg:tags":[
        "supply"
    ],
    "wof:name":"Emiliani Beauty Supplies",
    "wof:placetype":"venue"
},
  "geometry": {"coordinates":[-74.022724,40.783106],"type":"Point"}
}