{
  "type": "Feature",
  "properties": {
    "addr:full":"119 Grant Ave Seaside Heights NJ 08751",
    "addr:housenumber":"119",
    "addr:postcode":"08751",
    "addr:street":"Grant Ave",
    "iso:country":"US",
    "sg:address":"119 Grant Ave",
    "sg:city":"Seaside Heights",
    "sg:classifiers":[
        {
            "category":"Restaurant",
            "type":"Food & Drink"
        }
    ],
    "sg:phone":"+1 732 793 7827",
    "sg:postcode":"08751",
    "sg:province":"NJ",
    "wof:name":"Blimpie Subs & Salads",
    "wof:placetype":"venue"
},
  "geometry": {"coordinates":[-74.073712,39.942613],"type":"Point"}
}