{
  "type": "Feature",
  "properties": {
    "iso:country":"US",
    "sg:address":"244 Central Ave",
    "sg:city":"Rahway",
    "sg:classifiers":[
        {
            "category":"Organizations",
            "subcategory":"Religious Organization",
            "type":"Services"
        }
    ],
    "sg:phone":"+1 732 382 1132",
    "sg:postcode":"07065",
    "sg:province":"NJ",
    "wof:name":"Bukas-Loob Sa Diyos Foundation Inc",
    "wof:placetype":"venue"
},
  "geometry": {"coordinates":[-74.278502,40.609924],"type":"Point"}
}