{
  "type": "Feature",
  "properties": {
    "iso:country":"US",
    "sg:address":"127 Brandon Rd",
    "sg:city":"Pennington",
    "sg:classifiers":[
        {
            "category":"Shopping",
            "type":"Retail Goods"
        }
    ],
    "sg:phone":"+1   ",
    "sg:postcode":"08534",
    "sg:province":"NJ",
    "sg:tags":[
        "merchandise"
    ],
    "wof:name":"Pure Life Essentials",
    "wof:placetype":"venue"
},
  "geometry": {"coordinates":[-74.764374,40.295711],"type":"Point"}
}