{
  "type": "Feature",
  "properties": {
    "iso:country":"US",
    "sg:address":"29 E 16th St",
    "sg:city":"Paterson",
    "sg:classifiers":[
        {
            "category":"Organizations",
            "subcategory":"Religious Organization",
            "type":"Services"
        }
    ],
    "sg:phone":"+1 973 523 1886",
    "sg:postcode":"07524",
    "sg:province":"NJ",
    "sg:tags":[
        "clergy"
    ],
    "wof:name":"Trinity United Methodist Chr",
    "wof:placetype":"venue"
},
  "geometry": {"coordinates":[-74.15267299999999,40.934579],"type":"Point"}
}