{
  "type": "Feature",
  "properties": {
    "addr:full":"600 Lawrence St Pennsauken NJ 08102",
    "addr:housenumber":"600",
    "addr:postcode":"08102",
    "addr:street":"Lawrence St",
    "iso:country":"US",
    "sg:address":"600 Lawrence St",
    "sg:city":"Pennsauken",
    "sg:classifiers":[
        {
            "category":"Professional",
            "subcategory":"Lawyer & Legal Services",
            "type":"Services"
        }
    ],
    "sg:phone":"+1 856 406 9300",
    "sg:postcode":"08102",
    "sg:province":"NJ",
    "sg:tags":[
        "attorney"
    ],
    "wof:name":"Lawrence A Fox",
    "wof:placetype":"venue"
},
  "geometry": {"coordinates":[-75.119473,39.94714],"type":"Point"}
}