{
  "type": "Feature",
  "properties": {
    "iso:country":"US",
    "sg:address":"5 E State St",
    "sg:city":"Trenton",
    "sg:classifiers":[
        {
            "category":"Manufacturing",
            "subcategory":"Apparel",
            "type":"Manufacturing & Wholesale Goods"
        }
    ],
    "sg:phone":"+1 973 764 1777",
    "sg:postcode":"08608",
    "sg:province":"NJ",
    "sg:tags":[
        "cap",
        "hat",
        "millinery"
    ],
    "wof:name":"Norel's Millinery",
    "wof:placetype":"venue"
},
  "geometry": {"coordinates":[-74.76427,40.220082],"type":"Point"}
}