{
  "type": "Feature",
  "properties": {
    "iso:country":"US",
    "sg:address":"1171 Elizabeth Ave",
    "sg:city":"Elizabeth",
    "sg:classifiers":[
        {
            "category":"Health Services",
            "subcategory":"Doctor",
            "type":"Services"
        }
    ],
    "sg:phone":"+1 908 527 0200",
    "sg:postcode":"07201",
    "sg:province":"NJ",
    "sg:tags":[
        "physician",
        "surgeon"
    ],
    "wof:name":"Boro Health Care Of Union",
    "wof:placetype":"venue"
},
  "geometry": {"coordinates":[-74.214493,40.66218],"type":"Point"}
}