{
  "type": "Feature",
  "properties": {
    "iso:country":"US",
    "sg:address":"186 Mountainview Blvd",
    "sg:city":"Wayne",
    "sg:classifiers":[
        {
            "category":"Food & Beverages",
            "subcategory":"Meat & Fish",
            "type":"Retail Goods"
        }
    ],
    "sg:phone":"+1 973 694 4467",
    "sg:postcode":"07470",
    "sg:province":"NJ",
    "sg:tags":[
        "seafood",
        "market"
    ],
    "wof:name":"Lucy's Gourmet Seafood",
    "wof:placetype":"venue"
},
  "geometry": {"coordinates":[-74.269897,40.914501],"type":"Point"}
}