{
  "type": "Feature",
  "properties": {
    "addr:full":"689 Mercer Rd Princeton NJ 08540",
    "addr:housenumber":"689",
    "addr:postcode":"08540",
    "addr:street":"Mercer Rd",
    "iso:country":"US",
    "sg:address":"689 Mercer Rd",
    "sg:city":"Princeton",
    "sg:classifiers":[
        {
            "category":"Retail",
            "subcategory":"Animal Services",
            "type":"Services"
        }
    ],
    "sg:phone":"+1 609 924 0729",
    "sg:postcode":"08540",
    "sg:province":"NJ",
    "wof:name":"Hunt Boarding LLC",
    "wof:placetype":"venue"
},
  "geometry": {"coordinates":[-74.679258,40.327913],"type":"Point"}
}