{
  "type": "Feature",
  "properties": {
    "iso:country":"US",
    "sg:address":"151 Big Hill Rd",
    "sg:city":"Vincentown",
    "sg:classifiers":[
        {
            "category":"Building & Trades",
            "subcategory":"Equipment Rental",
            "type":"Services"
        }
    ],
    "sg:phone":"+1   ",
    "sg:postcode":"08088",
    "sg:province":"NJ",
    "sg:tags":[
        "toilet",
        "tank",
        "portable",
        "septic",
        "cleaning"
    ],
    "wof:name":"Mr Bobs Portable Toilets",
    "wof:placetype":"venue"
},
  "geometry": {"coordinates":[-74.710264,39.914047],"type":"Point"}
}