{
  "type": "Feature",
  "properties": {
    "addr:full":"8 Cove Rd Toms River NJ 08753",
    "addr:housenumber":"8",
    "addr:postcode":"08753",
    "addr:street":"Cove Rd",
    "iso:country":"US",
    "sg:address":"8 Cove Rd",
    "sg:city":"Toms River",
    "sg:classifiers":[
        {
            "category":"Home & Garden",
            "subcategory":"Carpets & Floor Coverings",
            "type":"Retail Goods"
        }
    ],
    "sg:phone":"+1   ",
    "sg:postcode":"08753",
    "sg:province":"NJ",
    "wof:name":"Capital Carpet & Tile Care",
    "wof:placetype":"venue"
},
  "geometry": {"coordinates":[-74.115931,39.964376],"type":"Point"}
}