{
  "type": "Feature",
  "properties": {
    "addr:full":"327 Clems Run Mullica Hill NJ 08062",
    "addr:housenumber":"327",
    "addr:postcode":"08062",
    "addr:street":"Clems Run",
    "iso:country":"US",
    "sg:address":"327 Clems Run",
    "sg:city":"Mullica Hill",
    "sg:classifiers":[
        {
            "category":"Real Estate",
            "subcategory":"Surveying",
            "type":"Services"
        }
    ],
    "sg:phone":"+1   ",
    "sg:postcode":"08062",
    "sg:province":"NJ",
    "wof:name":"Pennell Land Surveying",
    "wof:placetype":"venue"
},
  "geometry": {"coordinates":[-75.192601,39.711376],"type":"Point"}
}