{
  "type": "Feature",
  "properties": {
    "iso:country":"US",
    "sg:address":"995 S Orange Ave",
    "sg:city":"Newark",
    "sg:classifiers":[
        {
            "category":"Personal",
            "subcategory":"Beauty Salon",
            "type":"Services"
        }
    ],
    "sg:phone":"+1 973 429 2107",
    "sg:postcode":"07106",
    "sg:province":"NJ",
    "wof:name":"Queen Of Styles Unisex Beauty",
    "wof:placetype":"venue"
},
  "geometry": {"coordinates":[-74.229797,40.746522],"type":"Point"}
}