{
  "type": "Feature",
  "properties": {
    "iso:country":"US",
    "sg:address":"343 Bergen Blvd",
    "sg:city":"Palisades Park",
    "sg:classifiers":[
        {
            "category":"Restaurant",
            "type":"Food & Drink"
        }
    ],
    "sg:phone":"+1 201 947 1038",
    "sg:postcode":"07650",
    "sg:province":"NJ",
    "sg:tags":[
        "spanish"
    ],
    "sg:website":"www.mesonmadridrestaurant.com",
    "wof:name":"Meson Madrid Restaurant",
    "wof:placetype":"venue"
},
  "geometry": {"coordinates":[-73.98811000000001,40.84178],"type":"Point"}
}