{
  "type": "Feature",
  "properties": {
    "iso:country":"US",
    "sg:address":"23 State Rte 31",
    "sg:city":"Pennington",
    "sg:classifiers":[
        {
            "category":"Health Services",
            "subcategory":"Doctor",
            "type":"Services"
        }
    ],
    "sg:phone":"+1 609 730 0220",
    "sg:postcode":"08534",
    "sg:province":"NJ",
    "sg:tags":[
        "dentist"
    ],
    "wof:name":"Thomas M Hipple DMD",
    "wof:placetype":"venue"
},
  "geometry": {"coordinates":[-74.798534,40.331459],"type":"Point"}
}