{
  "type": "Feature",
  "properties": {
    "addr:full":"1 Alice Ct Cedar Brook NJ 08081",
    "addr:housenumber":"1",
    "addr:postcode":"08081",
    "addr:street":"Alice Ct Cedar",
    "iso:country":"US",
    "sg:address":"1 Alice Ct",
    "sg:city":"Cedar Brook",
    "sg:classifiers":[
        {
            "category":"Restaurant",
            "type":"Food & Drink"
        }
    ],
    "sg:phone":"+1   ",
    "sg:postcode":"08081",
    "sg:province":"NJ",
    "sg:tags":[
        "eating"
    ],
    "wof:name":"Petaccios Family Restaurant C",
    "wof:placetype":"venue"
},
  "geometry": {"coordinates":[-74.90507100000001,39.711284],"type":"Point"}
}