{
  "type": "Feature",
  "properties": {
    "addr:full":"273 New Rd Parsippany NJ 07054",
    "addr:housenumber":"273",
    "addr:postcode":"07054",
    "addr:street":"New Rd",
    "iso:country":"US",
    "sg:address":"273 New Rd",
    "sg:city":"Parsippany",
    "sg:classifiers":[
        {
            "category":"Professional",
            "subcategory":"Lawyer & Legal Services",
            "type":"Services"
        }
    ],
    "sg:phone":"+1 973 276 0200",
    "sg:postcode":"07054",
    "sg:province":"NJ",
    "wof:name":"Maenza Philip J Attorney",
    "wof:placetype":"venue"
},
  "geometry": {"coordinates":[-74.34832,40.851476],"type":"Point"}
}