{
  "type": "Feature",
  "properties": {
    "addr:full":"Seventh Avenue & Clifton Ave Newark NJ 07102",
    "addr:postcode":"07102",
    "addr:street":"Ave",
    "iso:country":"US",
    "sg:address":"Seventh Avenue & Clifton Ave",
    "sg:city":"Newark",
    "sg:classifiers":[
        {
            "category":"Sports & Exercise",
            "subcategory":"Ice Rink",
            "type":"Entertainment"
        }
    ],
    "sg:phone":"+1 973 482 8900",
    "sg:postcode":"07102",
    "sg:province":"NJ",
    "sg:tags":[
        "skating"
    ],
    "wof:name":"Essex County Offices & Institutions",
    "wof:placetype":"venue"
},
  "geometry": {"coordinates":[-74.179635,40.751553],"type":"Point"}
}