{
  "type": "Feature",
  "properties": {
    "addr:full":"11 Farrand Dr Parsippany NJ 07054",
    "addr:housenumber":"11",
    "addr:postcode":"07054",
    "addr:street":"Farrand Dr",
    "iso:country":"US",
    "sg:address":"11 Farrand Dr",
    "sg:city":"Parsippany",
    "sg:classifiers":[
        {
            "category":"Building & Trades",
            "subcategory":"Construction",
            "type":"Services"
        }
    ],
    "sg:phone":"+1 973 335 3405",
    "sg:postcode":"07054",
    "sg:province":"NJ",
    "sg:tags":[
        "house"
    ],
    "wof:name":"Tlj Inc",
    "wof:placetype":"venue"
},
  "geometry": {"coordinates":[-74.384518,40.868096],"type":"Point"}
}