{
  "type": "Feature",
  "properties": {
    "iso:country":"US",
    "sg:address":"43 Nautilus Rd",
    "sg:city":"Waretown",
    "sg:classifiers":[
        {
            "category":"Personal",
            "subcategory":"Beauty Salon",
            "type":"Services"
        }
    ],
    "sg:phone":"+1 609 242 4311",
    "sg:postcode":"08005",
    "sg:province":"NJ",
    "sg:tags":[
        "shop"
    ],
    "wof:name":"Gotcha Lookin Stable",
    "wof:placetype":"venue"
},
  "geometry": {"coordinates":[-74.178732,39.801801],"type":"Point"}
}