{
  "type": "Feature",
  "properties": {
    "iso:country":"US",
    "sg:address":"1430 Oak Tree Rd",
    "sg:city":"Iselin",
    "sg:classifiers":[
        {
            "category":"Professional",
            "subcategory":"Lawyer & Legal Services",
            "type":"Services"
        }
    ],
    "sg:phone":"+1 732 283 0900",
    "sg:postcode":"08830",
    "sg:province":"NJ",
    "wof:name":"Gazi Wm H Attorney",
    "wof:placetype":"venue"
},
  "geometry": {"coordinates":[-74.327814,40.573698],"type":"Point"}
}