{
  "type": "Feature",
  "properties": {
    "iso:country":"US",
    "sg:address":"310 43rd St S",
    "sg:city":"Brigantine",
    "sg:classifiers":[
        {
            "category":"Building & Trades",
            "subcategory":"Construction",
            "type":"Services"
        }
    ],
    "sg:phone":"+1 609 264 1520",
    "sg:postcode":"08203",
    "sg:province":"NJ",
    "sg:tags":[
        "general",
        "contractor"
    ],
    "wof:name":"Helduser General Contractor",
    "wof:placetype":"venue"
},
  "geometry": {"coordinates":[-74.390882,39.387114],"type":"Point"}
}