{
  "type": "Feature",
  "properties": {
    "iso:country":"US",
    "sg:address":"50 South Ave W",
    "sg:city":"Cranford",
    "sg:classifiers":[
        {
            "category":"Banks & Credit Unions",
            "subcategory":"Bank",
            "type":"Services"
        }
    ],
    "sg:phone":"+1 908 272 2104",
    "sg:postcode":"07016",
    "sg:province":"NJ",
    "wof:name":"J P Morgan",
    "wof:placetype":"venue"
},
  "geometry": {"coordinates":[-74.30947500000001,40.653989],"type":"Point"}
}