{
  "type": "Feature",
  "properties": {
    "addr:full":"1275 Valley Brook Ave Lyndhurst NJ 07071",
    "addr:housenumber":"1275",
    "addr:postcode":"07071",
    "addr:street":"Valley Brook Ave",
    "iso:country":"US",
    "sg:address":"1275 Valley Brook Ave",
    "sg:city":"Lyndhurst",
    "sg:classifiers":[
        {
            "category":"Wholesale",
            "subcategory":"Electrical",
            "type":"Manufacturing & Wholesale Goods"
        }
    ],
    "sg:phone":"+1 201 939 5313",
    "sg:postcode":"07071",
    "sg:province":"NJ",
    "sg:tags":[
        "security",
        "system"
    ],
    "wof:name":"Johnson Controls",
    "wof:placetype":"venue"
},
  "geometry": {"coordinates":[-74.10294399999999,40.800239],"type":"Point"}
}