{
  "type": "Feature",
  "properties": {
    "addr:full":"31 Jericho Rd Salem NJ 08079",
    "addr:housenumber":"31",
    "addr:postcode":"08079",
    "addr:street":"Jericho Rd",
    "iso:country":"US",
    "sg:address":"31 Jericho Rd",
    "sg:city":"Salem",
    "sg:classifiers":[
        {
            "category":"Wholesale",
            "subcategory":"Meat",
            "type":"Manufacturing & Wholesale Goods"
        }
    ],
    "sg:phone":"+1 856 935 6636",
    "sg:postcode":"08079",
    "sg:province":"NJ",
    "wof:name":"Niblock's Pork Store",
    "wof:placetype":"venue"
},
  "geometry": {"coordinates":[-75.404501,39.537669],"type":"Point"}
}