{
  "type": "Feature",
  "properties": {
    "addr:full":"29 E Church St Washington NJ 07882",
    "addr:housenumber":"29",
    "addr:postcode":"07882",
    "addr:street":"E Church St",
    "iso:country":"US",
    "sg:address":"29 E Church St",
    "sg:city":"Washington",
    "sg:classifiers":[
        {
            "category":"Health Services",
            "subcategory":"Clinic",
            "type":"Services"
        }
    ],
    "sg:phone":"+1 908 689 6245",
    "sg:postcode":"07882",
    "sg:province":"NJ",
    "wof:name":"Association of Childbirth",
    "wof:placetype":"venue"
},
  "geometry": {"coordinates":[-74.979579,40.759776],"type":"Point"}
}