{
  "type": "Feature",
  "properties": {
    "addr:full":"200 Anderson Ave Fairview NJ 07022",
    "addr:housenumber":"200",
    "addr:postcode":"07022",
    "addr:street":"Anderson Ave",
    "iso:country":"US",
    "sg:address":"200 Anderson Ave",
    "sg:city":"Fairview",
    "sg:classifiers":[
        {
            "category":"Restaurant",
            "type":"Food & Drink"
        }
    ],
    "sg:phone":"+1 201 941 1884",
    "sg:postcode":"07022",
    "sg:province":"NJ",
    "wof:name":"El Quetzal Restaurant",
    "wof:placetype":"venue"
},
  "geometry": {"coordinates":[-73.994781,40.816541],"type":"Point"}
}