{
  "type": "Feature",
  "properties": {
    "iso:country":"US",
    "sg:address":"50 W High St",
    "sg:city":"Bound Brook",
    "sg:classifiers":[
        {
            "category":"Education",
            "subcategory":"School",
            "type":"Public Place"
        }
    ],
    "sg:phone":"+1 732 271 2840",
    "sg:postcode":"08805",
    "sg:province":"NJ",
    "wof:name":"Lafayette School",
    "wof:placetype":"venue"
},
  "geometry": {"coordinates":[-74.535985,40.564397],"type":"Point"}
}