{
  "type": "Feature",
  "properties": {
    "iso:country":"US",
    "sg:address":"209 S 8th St",
    "sg:city":"Vineland",
    "sg:classifiers":[
        {
            "category":"Health Services",
            "subcategory":"Doctor",
            "type":"Services"
        }
    ],
    "sg:phone":"+1 856 794 1001",
    "sg:postcode":"08360",
    "sg:province":"NJ",
    "sg:tags":[
        "dentist"
    ],
    "wof:name":"Eight Street Dental",
    "wof:placetype":"venue"
},
  "geometry": {"coordinates":[-75.018863,39.482865],"type":"Point"}
}