{
  "type": "Feature",
  "properties": {
    "iso:country":"US",
    "sg:address":"106 Kathleen Ave",
    "sg:city":"Delran",
    "sg:classifiers":[
        {
            "category":"Building & Trades",
            "subcategory":"Plumbing",
            "type":"Services"
        }
    ],
    "sg:phone":"+1 856 722 8021",
    "sg:postcode":"08075",
    "sg:province":"NJ",
    "wof:name":"Independent Gas Works",
    "wof:placetype":"venue"
},
  "geometry": {"coordinates":[-74.947951,39.999632],"type":"Point"}
}