{
  "type": "Feature",
  "properties": {
    "addr:full":"305 Edlys Ln North Brunswick NJ 08902",
    "addr:housenumber":"305",
    "addr:postcode":"08902",
    "addr:street":"Edlys Ln",
    "iso:country":"US",
    "sg:address":"305 Edlys Ln",
    "sg:city":"North Brunswick",
    "sg:classifiers":[
        {
            "category":"Building & Trades",
            "subcategory":"Construction",
            "type":"Services"
        }
    ],
    "sg:phone":"+1 732 422 7468",
    "sg:postcode":"08902",
    "sg:province":"NJ",
    "sg:tags":[
        "carpentry",
        "contractor"
    ],
    "wof:name":"T Veloso Carpentry",
    "wof:placetype":"venue"
},
  "geometry": {"coordinates":[-74.463998,40.444596],"type":"Point"}
}