{
  "type": "Feature",
  "properties": {
    "addr:full":"490 S Dean St Englewood NJ 07631",
    "addr:housenumber":"490",
    "addr:postcode":"07631",
    "addr:street":"S Dean St",
    "iso:country":"US",
    "sg:address":"490 S Dean St",
    "sg:city":"Englewood",
    "sg:classifiers":[
        {
            "category":"Shopping",
            "subcategory":"Clothing, Apparel, & Fashions",
            "type":"Retail Goods"
        }
    ],
    "sg:phone":"+1   ",
    "sg:postcode":"07631",
    "sg:province":"NJ",
    "sg:tags":[
        "casual",
        "store"
    ],
    "wof:name":"Stylish",
    "wof:placetype":"venue"
},
  "geometry": {"coordinates":[-73.985225,40.877756],"type":"Point"}
}