{
  "type": "Feature",
  "properties": {
    "iso:country":"US",
    "sg:address":"110 Charlotte Pl",
    "sg:city":"Englewood Cliffs",
    "sg:classifiers":[
        {
            "category":"Professional",
            "subcategory":"Management & Consulting",
            "type":"Services"
        }
    ],
    "sg:phone":"+1 201 816 9486",
    "sg:postcode":"07632",
    "sg:province":"NJ",
    "sg:tags":[
        "marketing",
        "consultant"
    ],
    "wof:name":"Plus Marketing Corp",
    "wof:placetype":"venue"
},
  "geometry": {"coordinates":[-73.954607,40.873528],"type":"Point"}
}