{
  "type": "Feature",
  "properties": {
    "iso:country":"US",
    "sg:address":"133 Belmont Dr",
    "sg:city":"Somerset",
    "sg:classifiers":[
        {
            "category":"Building & Trades",
            "subcategory":"Landscaping Services",
            "type":"Services"
        }
    ],
    "sg:phone":"+1 732 564 1221",
    "sg:postcode":"08873",
    "sg:province":"NJ",
    "sg:tags":[
        "designer",
        "landscape"
    ],
    "wof:name":"Morrison Landscape & Design",
    "wof:placetype":"venue"
},
  "geometry": {"coordinates":[-74.538905,40.539008],"type":"Point"}
}