{
  "type": "Feature",
  "properties": {
    "iso:country":"US",
    "sg:address":"222 S Black Horse Pike",
    "sg:city":"Blackwood",
    "sg:classifiers":[
        {
            "category":"Building & Trades",
            "subcategory":"Construction",
            "type":"Services"
        }
    ],
    "sg:phone":"+1 856 374 4625",
    "sg:postcode":"08012",
    "sg:province":"NJ",
    "sg:tags":[
        "contractor"
    ],
    "wof:name":"General Contractors Co",
    "wof:placetype":"venue"
},
  "geometry": {"coordinates":[-75.064663,39.797447],"type":"Point"}
}