{
  "type": "Feature",
  "properties": {
    "addr:full":"19 Columbia Ave Hopewell NJ 08525",
    "addr:housenumber":"19",
    "addr:postcode":"08525",
    "addr:street":"Columbia Ave",
    "iso:country":"US",
    "sg:address":"19 Columbia Ave",
    "sg:city":"Hopewell",
    "sg:classifiers":[
        {
            "category":"Building & Trades",
            "subcategory":"Electrical",
            "type":"Services"
        }
    ],
    "sg:phone":"+1 609 466 0546",
    "sg:postcode":"08525",
    "sg:province":"NJ",
    "sg:tags":[
        "equipment",
        "protection",
        "lightning"
    ],
    "wof:name":"Zeus Lightning Rods",
    "wof:placetype":"venue"
},
  "geometry": {"coordinates":[-74.757863,40.389049],"type":"Point"}
}