{
  "type": "Feature",
  "properties": {
    "iso:country":"US",
    "sg:address":"750 State Rte 73",
    "sg:city":"Marlton",
    "sg:classifiers":[
        {
            "category":"Shopping",
            "subcategory":"Computers & Home Electronics",
            "type":"Retail Goods"
        }
    ],
    "sg:phone":"+1 856 988 8284",
    "sg:postcode":"08053",
    "sg:province":"NJ",
    "sg:tags":[
        "equipment",
        "electronic",
        "supply"
    ],
    "wof:name":"Linear Sales LTD",
    "wof:placetype":"venue"
},
  "geometry": {"coordinates":[-74.921694,39.867715],"type":"Point"}
}