{
  "type": "Feature",
  "properties": {
    "addr:full":"872 N Concourse Keyport NJ 07735",
    "addr:housenumber":"872",
    "addr:postcode":"07735",
    "addr:street":"N Concourse",
    "iso:country":"US",
    "sg:address":"872 N Concourse",
    "sg:city":"Keyport",
    "sg:classifiers":[
        {
            "category":"Building & Trades",
            "subcategory":"Electrical",
            "type":"Services"
        }
    ],
    "sg:phone":"+1 732 290 2455",
    "sg:postcode":"07735",
    "sg:province":"NJ",
    "sg:tags":[
        "electrical",
        "contractor"
    ],
    "wof:name":"SDS Electric",
    "wof:placetype":"venue"
},
  "geometry": {"coordinates":[-74.216668,40.445268],"type":"Point"}
}