{
  "type": "Feature",
  "properties": {
    "iso:country":"US",
    "sg:address":"211 N 7th St",
    "sg:city":"Vineland",
    "sg:classifiers":[
        {
            "category":"Shopping",
            "subcategory":"Hobbies, Toys, & Games",
            "type":"Retail Goods"
        }
    ],
    "sg:phone":"+1 856 691 6705",
    "sg:postcode":"08360",
    "sg:province":"NJ",
    "sg:tags":[
        "equipment",
        "ceramic",
        "supply"
    ],
    "wof:name":"Daley's Ceramic & Pottery Supl",
    "wof:placetype":"venue"
},
  "geometry": {"coordinates":[-75.020787,39.488911],"type":"Point"}
}