{
  "type": "Feature",
  "properties": {
    "iso:country":"US",
    "sg:address":"54 N Holly Ave",
    "sg:city":"Maple Shade",
    "sg:classifiers":[
        {
            "category":"Professional",
            "subcategory":"Lawyer & Legal Services",
            "type":"Services"
        }
    ],
    "sg:phone":"+1 856 667 7115",
    "sg:postcode":"08052",
    "sg:province":"NJ",
    "sg:tags":[
        "attorney"
    ],
    "wof:name":"Brian S Mc Donnell",
    "wof:placetype":"venue"
},
  "geometry": {"coordinates":[-74.993469,39.957379],"type":"Point"}
}