{
  "type": "Feature",
  "properties": {
    "iso:country":"US",
    "sg:address":"163 Shaw Ave",
    "sg:city":"Irvington",
    "sg:classifiers":[
        {
            "category":"Manufacturing",
            "subcategory":"Furniture",
            "type":"Manufacturing & Wholesale Goods"
        }
    ],
    "sg:phone":"+1 973 589 0877",
    "sg:postcode":"07111",
    "sg:province":"NJ",
    "sg:tags":[
        "manufacture",
        "purchase",
        "point",
        "display",
        "advertising"
    ],
    "wof:name":"Ron Comito & Associates Inc",
    "wof:placetype":"venue"
},
  "geometry": {"coordinates":[-74.22327,40.716875],"type":"Point"}
}