{
  "type": "Feature",
  "properties": {
    "addr:full":"496 Boulevard Kenilworth NJ 07033",
    "addr:housenumber":"496",
    "addr:postcode":"07033",
    "addr:street":"Boulevard",
    "iso:country":"US",
    "sg:address":"496 Boulevard",
    "sg:city":"Kenilworth",
    "sg:classifiers":[
        {
            "category":"Restaurant",
            "type":"Food & Drink"
        }
    ],
    "sg:phone":"+1 908 272 6633",
    "sg:postcode":"07033",
    "sg:province":"NJ",
    "sg:tags":[
        "indian"
    ],
    "wof:name":"Star of India Restaurant",
    "wof:placetype":"venue"
},
  "geometry": {"coordinates":[-74.29239699999999,40.6758],"type":"Point"}
}