{
  "type": "Feature",
  "properties": {
    "iso:country":"US",
    "sg:address":"301 Garden St",
    "sg:city":"Hoboken",
    "sg:classifiers":[
        {
            "category":"Social Services",
            "subcategory":"Child Care",
            "type":"Services"
        }
    ],
    "sg:phone":"+1 201 656 8317",
    "sg:postcode":"07030",
    "sg:province":"NJ",
    "sg:tags":[
        "day"
    ],
    "wof:name":"Nuestro Nino Day Care Center Inc",
    "wof:placetype":"venue"
},
  "geometry": {"coordinates":[-74.031853,40.740313],"type":"Point"}
}