{
  "type": "Feature",
  "properties": {
    "iso:country":"US",
    "sg:address":"51 Shaffer Rd",
    "sg:city":"Bridgewater",
    "sg:classifiers":[
        {
            "category":"Professional",
            "subcategory":"Management & Consulting",
            "type":"Services"
        }
    ],
    "sg:phone":"+1 908 575 0704",
    "sg:postcode":"08807",
    "sg:province":"NJ",
    "sg:tags":[
        "business"
    ],
    "wof:name":"Green Energy Inc",
    "wof:placetype":"venue"
},
  "geometry": {"coordinates":[-74.65966400000001,40.585915],"type":"Point"}
}