{
  "type": "Feature",
  "properties": {
    "iso:country":"US",
    "sg:address":"114 Moonachie Ave",
    "sg:city":"Moonachie",
    "sg:classifiers":[
        {
            "category":"Manufacturing",
            "subcategory":"Furniture",
            "type":"Manufacturing & Wholesale Goods"
        }
    ],
    "sg:phone":"+1 201 438 4100",
    "sg:postcode":"07074",
    "sg:province":"NJ",
    "sg:tags":[
        "equipment",
        "supply"
    ],
    "sg:website":"www.unitedshowcase.com",
    "wof:name":"United Showcase Co",
    "wof:placetype":"venue"
},
  "geometry": {"coordinates":[-74.05888,40.835254],"type":"Point"}
}