{
  "type": "Feature",
  "properties": {
    "addr:full":"172 State Rte 50 Ocean View NJ 08230",
    "addr:housenumber":"172",
    "addr:postcode":"08230",
    "addr:street":"State Rte 50",
    "iso:country":"US",
    "sg:address":"172 State Rte 50",
    "sg:city":"Ocean View",
    "sg:classifiers":[
        {
            "category":"Personal",
            "subcategory":"Beauty Salon",
            "type":"Services"
        }
    ],
    "sg:phone":"+1 609 390 7233",
    "sg:postcode":"08230",
    "sg:province":"NJ",
    "wof:name":"Cutting Edge",
    "wof:placetype":"venue"
},
  "geometry": {"coordinates":[-74.707835,39.232371],"type":"Point"}
}