{
  "type": "Feature",
  "properties": {
    "addr:full":"649 Chestnut Ave Teaneck NJ 07666",
    "addr:housenumber":"649",
    "addr:postcode":"07666",
    "addr:street":"Chestnut Ave",
    "iso:country":"US",
    "sg:address":"649 Chestnut Ave",
    "sg:city":"Teaneck",
    "sg:classifiers":[
        {
            "category":"Wholesale",
            "subcategory":"Stationery",
            "type":"Manufacturing & Wholesale Goods"
        },
        {
            "category":"Wholesale",
            "subcategory":"Non-durable Goods",
            "type":"Manufacturing & Wholesale Goods"
        }
    ],
    "sg:phone":"+1 201 692 0202",
    "sg:postcode":"07666",
    "sg:province":"NJ",
    "sg:tags":[
        "packaging",
        "material"
    ],
    "wof:name":"R & S Innovative Packaging",
    "wof:placetype":"venue"
},
  "geometry": {"coordinates":[-74.02332,40.886201],"type":"Point"}
}