{
  "type": "Feature",
  "properties": {
    "addr:full":"400 Central Ave Newark NJ 07107",
    "addr:housenumber":"400",
    "addr:postcode":"07107",
    "addr:street":"Central Ave",
    "iso:country":"US",
    "sg:address":"400 Central Ave",
    "sg:city":"Newark",
    "sg:classifiers":[
        {
            "category":"Food & Beverages",
            "subcategory":"Groceries & Convenience Stores",
            "type":"Retail Goods"
        }
    ],
    "sg:phone":"+1 973 645 1157",
    "sg:postcode":"07107",
    "sg:province":"NJ",
    "sg:tags":[
        "grocer"
    ],
    "wof:name":"Nubian's Also Grocery & Deli",
    "wof:placetype":"venue"
},
  "geometry": {"coordinates":[-74.189781,40.747311],"type":"Point"}
}