{
  "type": "Feature",
  "properties": {
    "addr:full":"439 Union Ave Middlesex NJ 08846",
    "addr:housenumber":"439",
    "addr:postcode":"08846",
    "addr:street":"Union Ave",
    "iso:country":"US",
    "sg:address":"439 Union Ave",
    "sg:city":"Middlesex",
    "sg:classifiers":[
        {
            "category":"Professional",
            "subcategory":"Business Services",
            "type":"Services"
        }
    ],
    "sg:phone":"+1   ",
    "sg:postcode":"08846",
    "sg:province":"NJ",
    "wof:name":"H & J Homecare",
    "wof:placetype":"venue"
},
  "geometry": {"coordinates":[-74.51261,40.570845],"type":"Point"}
}