{
  "type": "Feature",
  "properties": {
    "addr:full":"760 Vasser Ave Lakewood NJ 08701",
    "addr:housenumber":"760",
    "addr:postcode":"08701",
    "addr:street":"Vasser Ave",
    "iso:country":"US",
    "sg:address":"760 Vasser Ave",
    "sg:city":"Lakewood",
    "sg:classifiers":[
        {
            "category":"Manufacturing",
            "subcategory":"Metals",
            "type":"Manufacturing & Wholesale Goods"
        }
    ],
    "sg:phone":"+1 732 364 6000",
    "sg:postcode":"08701",
    "sg:province":"NJ",
    "sg:tags":[
        "alloy",
        "fabricator"
    ],
    "wof:name":"Roben Manufacturing Co Inc",
    "wof:placetype":"venue"
},
  "geometry": {"coordinates":[-74.183922,40.067661],"type":"Point"}
}