{
  "type": "Feature",
  "properties": {
    "iso:country":"US",
    "sg:address":"1130 Old Indian Mills Rd",
    "sg:city":"Vincentown",
    "sg:phone":"+1 609 268 0452",
    "sg:postcode":"08088",
    "sg:province":"NJ",
    "sg:tags":[
        "farm",
        "field",
        "crop"
    ],
    "wof:name":"Indian Mills Nursery Inc",
    "wof:placetype":"venue"
},
  "geometry": {"coordinates":[-74.727137,39.826915],"type":"Point"}
}