{
  "type": "Feature",
  "properties": {
    "addr:full":"9 Society Hill Way Eatontown NJ 07724",
    "addr:housenumber":"9",
    "addr:postcode":"07724",
    "addr:street":"Society Hill Way",
    "iso:country":"US",
    "sg:address":"9 Society Hill Way",
    "sg:city":"Eatontown",
    "sg:classifiers":[
        {
            "category":"Professional",
            "type":"Services"
        }
    ],
    "sg:phone":"+1   ",
    "sg:postcode":"07724",
    "sg:province":"NJ",
    "wof:name":"Just For Starters",
    "wof:placetype":"venue"
},
  "geometry": {"coordinates":[-74.075255,40.312399],"type":"Point"}
}