{
  "type": "Feature",
  "properties": {
    "iso:country":"US",
    "sg:address":"158 Taft Ave",
    "sg:city":"Trenton",
    "sg:classifiers":[
        {
            "category":"Professional",
            "type":"Services"
        }
    ],
    "sg:phone":"+1 609 581 4936",
    "sg:postcode":"08610",
    "sg:province":"NJ",
    "sg:tags":[
        "establishment"
    ],
    "wof:name":"George Gieger & Assoc Inc",
    "wof:placetype":"venue"
},
  "geometry": {"coordinates":[-74.699842,40.200714],"type":"Point"}
}