{
  "type": "Feature",
  "properties": {
    "addr:full":"208 Hasbrouck Ave Hasbrouck Heights NJ 07604",
    "addr:housenumber":"208",
    "addr:postcode":"07604",
    "addr:street":"Hasbrouck Ave",
    "iso:country":"US",
    "sg:address":"208 Hasbrouck Ave",
    "sg:city":"Hasbrouck Heights",
    "sg:classifiers":[
        {
            "category":"Manufacturing",
            "subcategory":"Printing",
            "type":"Manufacturing & Wholesale Goods"
        }
    ],
    "sg:phone":"+1 201 393 9500",
    "sg:postcode":"07604",
    "sg:province":"NJ",
    "sg:tags":[
        "lithographic",
        "commercial"
    ],
    "wof:name":"Tape Graphics",
    "wof:placetype":"venue"
},
  "geometry": {"coordinates":[-74.065819,40.865597],"type":"Point"}
}