{
  "type": "Feature",
  "properties": {
    "addr:full":"139 Lakeview Ave Clifton NJ 07011",
    "addr:housenumber":"139",
    "addr:postcode":"07011",
    "addr:street":"Lakeview Ave",
    "iso:country":"US",
    "sg:address":"139 Lakeview Ave",
    "sg:city":"Clifton",
    "sg:classifiers":[
        {
            "category":"Professional",
            "subcategory":"Lawyer & Legal Services",
            "type":"Services"
        }
    ],
    "sg:phone":"+1 973 772 8900",
    "sg:postcode":"07011",
    "sg:province":"NJ",
    "wof:name":"Iannarella Peter Attorney",
    "wof:placetype":"venue"
},
  "geometry": {"coordinates":[-74.137001,40.8797],"type":"Point"}
}