{
  "type": "Feature",
  "properties": {
    "addr:full":"330 US Hwy 202 Bedminster NJ 07921",
    "addr:housenumber":"330",
    "addr:postcode":"07921",
    "addr:street":"Us Hwy 202",
    "iso:country":"US",
    "sg:address":"330 US Hwy 202",
    "sg:city":"Bedminster",
    "sg:classifiers":[
        {
            "category":"Retail",
            "subcategory":"Veterinary Services",
            "type":"Services"
        }
    ],
    "sg:phone":"+1 908 234 0650",
    "sg:postcode":"07921",
    "sg:province":"NJ",
    "sg:tags":[
        "veterinarian"
    ],
    "wof:name":"Bedminster Animal Hospital",
    "wof:placetype":"venue"
},
  "geometry": {"coordinates":[-74.64536699999999,40.680613],"type":"Point"}
}