{
  "type": "Feature",
  "properties": {
    "iso:country":"US",
    "sg:address":"20 Ave A",
    "sg:city":"Hasbrouck Hts",
    "sg:classifiers":[
        {
            "category":"Shopping",
            "subcategory":"Florist",
            "type":"Retail Goods"
        }
    ],
    "sg:phone":"+1 201 257 8249",
    "sg:postcode":"07644",
    "sg:province":"NJ",
    "wof:name":"Peralta's Floral Designs",
    "wof:placetype":"venue"
},
  "geometry": {"coordinates":[-74.07897699999999,40.884321],"type":"Point"}
}