{
  "type": "Feature",
  "properties": {
    "addr:full":"195 Lexington Ave Passaic NJ 07055",
    "addr:housenumber":"195",
    "addr:postcode":"07055",
    "addr:street":"Lexington Ave",
    "iso:country":"US",
    "sg:address":"195 Lexington Ave",
    "sg:city":"Passaic",
    "sg:classifiers":[
        {
            "category":"Arts & Performance",
            "subcategory":"Theater",
            "type":"Entertainment"
        }
    ],
    "sg:phone":"+1   ",
    "sg:postcode":"07055",
    "sg:province":"NJ",
    "sg:tags":[
        "group"
    ],
    "wof:name":"Murda Inkorporate US",
    "wof:placetype":"venue"
},
  "geometry": {"coordinates":[-74.127432,40.86817],"type":"Point"}
}