{
  "type": "Feature",
  "properties": {
    "iso:country":"US",
    "sg:address":"55 Brick Blvd",
    "sg:city":"Brick",
    "sg:classifiers":[
        {
            "category":"Banks & Credit Unions",
            "subcategory":"Financial Services",
            "type":"Services"
        }
    ],
    "sg:phone":"+1   ",
    "sg:postcode":"08723",
    "sg:province":"NJ",
    "sg:tags":[
        "company",
        "holding"
    ],
    "wof:name":"Lady of American Fitness",
    "wof:placetype":"venue"
},
  "geometry": {"coordinates":[-74.143871,40.025086],"type":"Point"}
}