{
  "type": "Feature",
  "properties": {
    "iso:country":"US",
    "sg:address":"1731 Nottingham Way",
    "sg:city":"Trenton",
    "sg:classifiers":[
        {
            "category":"Home & Garden",
            "subcategory":"Home Furnishings",
            "type":"Retail Goods"
        }
    ],
    "sg:phone":"+1 609 586 3344",
    "sg:postcode":"08619",
    "sg:province":"NJ",
    "sg:tags":[
        "housewares",
        "fireplace",
        "accessory",
        "installation",
        "equipment"
    ],
    "wof:name":"Bowden's Fireside Shop",
    "wof:placetype":"venue"
},
  "geometry": {"coordinates":[-74.71426599999999,40.232584],"type":"Point"}
}