{
  "type": "Feature",
  "properties": {
    "addr:full":"367 Brick Blvd Brick NJ 08723",
    "addr:housenumber":"367",
    "addr:postcode":"08723",
    "addr:street":"Brick Blvd",
    "iso:country":"US",
    "sg:address":"367 Brick Blvd",
    "sg:city":"Brick",
    "sg:classifiers":[
        {
            "category":"Manufacturing",
            "subcategory":"Printing",
            "type":"Manufacturing & Wholesale Goods"
        }
    ],
    "sg:phone":"+1 732 477 7468",
    "sg:postcode":"08723",
    "sg:province":"NJ",
    "sg:tags":[
        "printer"
    ],
    "wof:name":"Print N Ship Inc",
    "wof:placetype":"venue"
},
  "geometry": {"coordinates":[-74.142053,40.043503],"type":"Point"}
}