{
  "type": "Feature",
  "properties": {
    "addr:full":"616 Willow St Lakehurst NJ 08733",
    "addr:housenumber":"616",
    "addr:postcode":"08733",
    "addr:street":"Willow St",
    "iso:country":"US",
    "sg:address":"616 Willow St",
    "sg:city":"Lakehurst",
    "sg:classifiers":[
        {
            "category":"Building & Trades",
            "subcategory":"Construction",
            "type":"Services"
        }
    ],
    "sg:phone":"+1 732 657 9865",
    "sg:postcode":"08733",
    "sg:province":"NJ",
    "sg:tags":[
        "contractor"
    ],
    "wof:name":"Potkay Exteriors Inc",
    "wof:placetype":"venue"
},
  "geometry": {"coordinates":[-74.324923,40.016706],"type":"Point"}
}