{
  "type": "Feature",
  "properties": {
    "iso:country":"US",
    "sg:address":"38 Pine Ridge Blvd",
    "sg:city":"Lakehurst",
    "sg:classifiers":[
        {
            "category":"Home & Garden",
            "subcategory":"Mobile Homes",
            "type":"Retail Goods"
        },
        {
            "category":"Real Estate",
            "subcategory":"Real Estate Operator",
            "type":"Services"
        }
    ],
    "sg:phone":"+1 732 849 4600",
    "sg:postcode":"08759",
    "sg:province":"NJ",
    "sg:tags":[
        "management",
        "park",
        "community"
    ],
    "wof:name":"Pine Ridge South LP",
    "wof:placetype":"venue"
},
  "geometry": {"coordinates":[-74.331062,39.943749],"type":"Point"}
}