{
  "type": "Feature",
  "properties": {
    "addr:full":"816 E End Ave Lakewood NJ 08701",
    "addr:housenumber":"816",
    "addr:postcode":"08701",
    "addr:street":"E End Ave",
    "iso:country":"US",
    "sg:address":"816 E End Ave",
    "sg:city":"Lakewood",
    "sg:classifiers":[
        {
            "category":"Organizations",
            "subcategory":"Community Association",
            "type":"Services"
        }
    ],
    "sg:phone":"+1   ",
    "sg:postcode":"08701",
    "sg:province":"NJ",
    "wof:name":"LMaan Hashabbos",
    "wof:placetype":"venue"
},
  "geometry": {"coordinates":[-74.200232,40.102892],"type":"Point"}
}