{
  "type": "Feature",
  "properties": {
    "addr:full":"1933 State Rte 35 Middletown NJ 07748",
    "addr:housenumber":"1933",
    "addr:postcode":"07748",
    "addr:street":"State Rte 35",
    "iso:country":"US",
    "sg:address":"1933 State Rte 35",
    "sg:city":"Middletown",
    "sg:classifiers":[
        {
            "category":"Freight",
            "type":"Transportation"
        }
    ],
    "sg:phone":"+1 732 758 6444",
    "sg:postcode":"07748",
    "sg:province":"NJ",
    "sg:tags":[
        "mover"
    ],
    "wof:name":"Econo-Line Movers",
    "wof:placetype":"venue"
},
  "geometry": {"coordinates":[-74.13112700000001,40.408674],"type":"Point"}
}