{
  "type": "Feature",
  "properties": {
    "iso:country":"US",
    "sg:address":"908 Jersey Ave",
    "sg:city":"Spring Lake",
    "sg:classifiers":[
        {
            "category":"Retail",
            "subcategory":"Repair Shop",
            "type":"Services"
        }
    ],
    "sg:phone":"+1   ",
    "sg:postcode":"07762",
    "sg:province":"NJ",
    "sg:tags":[
        "antique",
        "restoration",
        "maker",
        "cabinet"
    ],
    "wof:name":"Ruding & Wood",
    "wof:placetype":"venue"
},
  "geometry": {"coordinates":[-74.047167,40.142615],"type":"Point"}
}