{
  "type": "Feature",
  "properties": {
    "addr:full":"19 Hampton Pl Nutley NJ 07110",
    "addr:housenumber":"19",
    "addr:postcode":"07110",
    "addr:street":"Hampton Pl",
    "iso:country":"US",
    "sg:address":"19 Hampton Pl",
    "sg:city":"Nutley",
    "sg:classifiers":[
        {
            "category":"Building & Trades",
            "subcategory":"Plumbing",
            "type":"Services"
        }
    ],
    "sg:phone":"+1 973 662 1580",
    "sg:postcode":"07110",
    "sg:province":"NJ",
    "sg:tags":[
        "contractor"
    ],
    "wof:name":"Quality Cmfort Sltons Heat LLC",
    "wof:placetype":"venue"
},
  "geometry": {"coordinates":[-74.15124299999999,40.815335],"type":"Point"}
}