{
  "type": "Feature",
  "properties": {
    "addr:full":"244 Shell Rd Carneys Point NJ 08069",
    "addr:housenumber":"244",
    "addr:postcode":"08069",
    "addr:street":"Shell Rd",
    "iso:country":"US",
    "sg:address":"244 Shell Rd",
    "sg:city":"Carneys Point",
    "sg:classifiers":[
        {
            "category":"Insurance",
            "subcategory":"Insurance Agent",
            "type":"Services"
        }
    ],
    "sg:phone":"+1 856 299 9016",
    "sg:postcode":"08069",
    "sg:province":"NJ",
    "wof:name":"Insurance Network Inc",
    "wof:placetype":"venue"
},
  "geometry": {"coordinates":[-75.47090300000001,39.714717],"type":"Point"}
}