{
  "type": "Feature",
  "properties": {
    "iso:country":"US",
    "sg:address":"225 W 24th Ave",
    "sg:city":"Wildwood",
    "sg:classifiers":[
        {
            "category":"Cinema",
            "subcategory":"Movie Theater",
            "type":"Entertainment"
        }
    ],
    "sg:phone":"+1 609 523 0288",
    "sg:postcode":"08260",
    "sg:province":"NJ",
    "wof:name":"Strand Movie Theater",
    "wof:placetype":"venue"
},
  "geometry": {"coordinates":[-74.81050999999999,38.996819],"type":"Point"}
}