{
  "type": "Feature",
  "properties": {
    "iso:country":"US",
    "sg:address":"160 Stelton Rd",
    "sg:city":"Piscataway",
    "sg:classifiers":[
        {
            "category":"Restaurant",
            "type":"Food & Drink"
        }
    ],
    "sg:phone":"+1 732 752 6900",
    "sg:postcode":"08854",
    "sg:province":"NJ",
    "sg:tags":[
        "caterer"
    ],
    "wof:name":"Cedar Grove Catering Inc",
    "wof:placetype":"venue"
},
  "geometry": {"coordinates":[-74.45696700000001,40.570396],"type":"Point"}
}