{
  "type": "Feature",
  "properties": {
    "addr:full":"715 Broadway Paterson NJ 07514",
    "addr:housenumber":"715",
    "addr:postcode":"07514",
    "addr:street":"Broadway",
    "iso:country":"US",
    "sg:address":"715 Broadway",
    "sg:city":"Paterson",
    "sg:classifiers":[
        {
            "category":"Shopping",
            "subcategory":"Pharmacy",
            "type":"Retail Goods"
        }
    ],
    "sg:phone":"+1 973 742 6556",
    "sg:postcode":"07514",
    "sg:province":"NJ",
    "sg:tags":[
        "drugstore"
    ],
    "wof:name":"Sinai Quick Stop Pharmacy",
    "wof:placetype":"venue"
},
  "geometry": {"coordinates":[-74.14250199999999,40.918301],"type":"Point"}
}