{
  "type": "Feature",
  "properties": {
    "addr:full":"1193 Bay Ave Toms River NJ 08753",
    "addr:housenumber":"1193",
    "addr:postcode":"08753",
    "addr:street":"Bay Ave",
    "iso:country":"US",
    "sg:address":"1193 Bay Ave",
    "sg:city":"Toms River",
    "sg:classifiers":[
        {
            "category":"Health Services",
            "subcategory":"Doctor",
            "type":"Services"
        }
    ],
    "sg:phone":"+1 732 270 8282",
    "sg:postcode":"08753",
    "sg:province":"NJ",
    "wof:name":"De Stephan Joseph DMD P A",
    "wof:placetype":"venue"
},
  "geometry": {"coordinates":[-74.134962,39.969237],"type":"Point"}
}