{
  "type": "Feature",
  "properties": {
    "iso:country":"US",
    "sg:address":"497 Lake Ave",
    "sg:city":"Lyndhurst",
    "sg:classifiers":[
        {
            "category":"Shopping",
            "subcategory":"Luggage & Leather Goods",
            "type":"Retail Goods"
        }
    ],
    "sg:phone":"+1 201 842 0433",
    "sg:postcode":"07071",
    "sg:province":"NJ",
    "wof:name":"Tijen Leather",
    "wof:placetype":"venue"
},
  "geometry": {"coordinates":[-74.117841,40.815848],"type":"Point"}
}