{
  "type": "Feature",
  "properties": {
    "iso:country":"US",
    "sg:address":"2191 Washington Valley Rd",
    "sg:city":"Martinsville",
    "sg:classifiers":[
        {
            "category":"Real Estate",
            "subcategory":"Real Estate Operator",
            "type":"Services"
        }
    ],
    "sg:phone":"+1   ",
    "sg:postcode":"08836",
    "sg:province":"NJ",
    "sg:tags":[
        "building",
        "nonresidential"
    ],
    "wof:name":"Somerset Hills Shopping Center",
    "wof:placetype":"venue"
},
  "geometry": {"coordinates":[-74.542913,40.600205],"type":"Point"}
}