{
  "type": "Feature",
  "properties": {
    "iso:country":"US",
    "sg:address":"405 Ridge Rd",
    "sg:city":"Dayton",
    "sg:classifiers":[
        {
            "category":"Personal",
            "subcategory":"Beauty Salon",
            "type":"Services"
        }
    ],
    "sg:phone":"+1   ",
    "sg:postcode":"08810",
    "sg:province":"NJ",
    "sg:tags":[
        "shop"
    ],
    "wof:name":"Images Hair Design",
    "wof:placetype":"venue"
},
  "geometry": {"coordinates":[-74.51219500000001,40.374799],"type":"Point"}
}