{
  "type": "Feature",
  "properties": {
    "addr:full":"107 W Camden Ave Moorestown NJ 08057",
    "addr:housenumber":"107",
    "addr:postcode":"08057",
    "addr:street":"W Camden Ave",
    "iso:country":"US",
    "sg:address":"107 W Camden Ave",
    "sg:city":"Moorestown",
    "sg:classifiers":[
        {
            "category":"Autos & Motor Vehicles",
            "subcategory":"Fuel & Gas Station",
            "type":"Retail Goods"
        }
    ],
    "sg:phone":"+1 856 234 4767",
    "sg:postcode":"08057",
    "sg:province":"NJ",
    "sg:tags":[
        "oil"
    ],
    "wof:name":"Hillman's Auto Svc",
    "wof:placetype":"venue"
},
  "geometry": {"coordinates":[-74.983183,39.957364],"type":"Point"}
}