{
  "type": "Feature",
  "properties": {
    "iso:country":"US",
    "sg:address":"103 Bound Brook Rd",
    "sg:city":"Middlesex",
    "sg:classifiers":[
        {
            "category":"Building & Trades",
            "subcategory":"Construction",
            "type":"Services"
        }
    ],
    "sg:phone":"+1   ",
    "sg:postcode":"08846",
    "sg:province":"NJ",
    "sg:tags":[
        "installs",
        "retail",
        "monument"
    ],
    "wof:name":"Greenbrook Memorials",
    "wof:placetype":"venue"
},
  "geometry": {"coordinates":[-74.47614,40.586088],"type":"Point"}
}