{
  "type": "Feature",
  "properties": {
    "iso:country":"US",
    "sg:address":"4 Steelman Ave",
    "sg:city":"Bridgeport",
    "sg:classifiers":[
        {
            "category":"Government",
            "subcategory":"Fire Station",
            "type":"Public Place"
        }
    ],
    "sg:phone":"+1   ",
    "sg:postcode":"08014",
    "sg:province":"NJ",
    "sg:tags":[
        "co",
        "volunteer"
    ],
    "wof:name":"Bridgeport Volunteer Fire Co",
    "wof:placetype":"venue"
},
  "geometry": {"coordinates":[-75.343869,39.800959],"type":"Point"}
}