{
  "type": "Feature",
  "properties": {
    "addr:full":"7 Forum Ct Morris Plains NJ 07950",
    "addr:postcode":"07950",
    "addr:street":"Forum Ct",
    "iso:country":"US",
    "sg:address":"7 Forum Ct",
    "sg:city":"Morris Plains",
    "sg:classifiers":[
        {
            "category":"Organizations",
            "subcategory":"Professional Association",
            "type":"Services"
        }
    ],
    "sg:phone":"+1 973 455 9835",
    "sg:postcode":"07950",
    "sg:province":"NJ",
    "wof:name":"Glacier Hills Assn",
    "wof:placetype":"venue"
},
  "geometry": {"coordinates":[-74.466268,40.855687],"type":"Point"}
}