{
  "type": "Feature",
  "properties": {
    "addr:full":"36 S Broad St Trenton NJ 08608",
    "addr:housenumber":"36",
    "addr:postcode":"08608",
    "addr:street":"S Broad St",
    "iso:country":"US",
    "sg:address":"36 S Broad St",
    "sg:city":"Trenton",
    "sg:classifiers":[
        {
            "category":"Professional",
            "subcategory":"Research",
            "type":"Services"
        }
    ],
    "sg:phone":"+1 609 695 4922",
    "sg:postcode":"08608",
    "sg:province":"NJ",
    "sg:tags":[
        "environmental",
        "ecological"
    ],
    "wof:name":"Sarva Bio-Remed",
    "wof:placetype":"venue"
},
  "geometry": {"coordinates":[-74.764084,40.21906],"type":"Point"}
}