{
  "type": "Feature",
  "properties": {
    "iso:country":"US",
    "sg:address":"117 Midland Ave",
    "sg:city":"Garfield",
    "sg:classifiers":[
        {
            "category":"Professional",
            "subcategory":"Management & Consulting",
            "type":"Services"
        }
    ],
    "sg:phone":"+1   ",
    "sg:postcode":"07026",
    "sg:province":"NJ",
    "wof:name":"Municipal Financial Services",
    "wof:placetype":"venue"
},
  "geometry": {"coordinates":[-74.10490299999999,40.868132],"type":"Point"}
}