{
  "type": "Feature",
  "properties": {
    "iso:country":"US",
    "sg:address":"29 Ramkay Dr",
    "sg:city":"Fairfield",
    "sg:classifiers":[
        {
            "category":"Health Services",
            "subcategory":"Clinic",
            "type":"Services"
        }
    ],
    "sg:phone":"+1   ",
    "sg:postcode":"07004",
    "sg:province":"NJ",
    "wof:name":"Hillmar Inc",
    "wof:placetype":"venue"
},
  "geometry": {"coordinates":[-74.320663,40.876717],"type":"Point"}
}