{
  "type": "Feature",
  "properties": {
    "iso:country":"US",
    "sg:address":"1861 Springfield Ave",
    "sg:city":"Maplewood",
    "sg:classifiers":[
        {
            "category":"Manufacturing",
            "subcategory":"Metals",
            "type":"Manufacturing & Wholesale Goods"
        }
    ],
    "sg:phone":"+1 973 762 7231",
    "sg:postcode":"07040",
    "sg:province":"NJ",
    "wof:name":"AG Engraving Plus",
    "wof:placetype":"venue"
},
  "geometry": {"coordinates":[-74.267535,40.720994],"type":"Point"}
}