{
  "type": "Feature",
  "properties": {
    "addr:full":"751 Fairfield Ave Kenilworth NJ 07033",
    "addr:housenumber":"751",
    "addr:postcode":"07033",
    "addr:street":"Fairfield Ave",
    "iso:country":"US",
    "sg:address":"751 Fairfield Ave",
    "sg:city":"Kenilworth",
    "sg:classifiers":[
        {
            "category":"Building & Trades",
            "subcategory":"Plumbing",
            "type":"Services"
        }
    ],
    "sg:phone":"+1 908 620 1910",
    "sg:postcode":"07033",
    "sg:province":"NJ",
    "sg:tags":[
        "conditioning",
        "air",
        "system",
        "contractor"
    ],
    "wof:name":"AMV Conditioning",
    "wof:placetype":"venue"
},
  "geometry": {"coordinates":[-74.279856,40.66943],"type":"Point"}
}