{
  "type": "Feature",
  "properties": {
    "iso:country":"US",
    "sg:address":"715 Broadway",
    "sg:city":"Paterson",
    "sg:classifiers":[
        {
            "category":"Health Services",
            "subcategory":"Doctor",
            "type":"Services"
        }
    ],
    "sg:phone":"+1 973 684 8617",
    "sg:postcode":"07514",
    "sg:province":"NJ",
    "sg:tags":[
        "cardiologist"
    ],
    "wof:name":"Agarwal Ashoke MD",
    "wof:placetype":"venue"
},
  "geometry": {"coordinates":[-74.14250199999999,40.918301],"type":"Point"}
}