{
  "type": "Feature",
  "properties": {
    "iso:country":"US",
    "sg:address":"134 Espanong Rd",
    "sg:city":"Lake Hopatcong",
    "sg:classifiers":[
        {
            "category":"Recreation",
            "subcategory":"Marina",
            "type":"Entertainment"
        }
    ],
    "sg:phone":"+1 973 663 2045",
    "sg:postcode":"07849",
    "sg:province":"NJ",
    "sg:website":"www.marinemax.com",
    "wof:name":"Marine Max Inc",
    "wof:placetype":"venue"
},
  "geometry": {"coordinates":[-74.612948,40.960619],"type":"Point"}
}