{
  "type": "Feature",
  "properties": {
    "addr:full":"50 Railroad Ave Forked River NJ 08731",
    "addr:housenumber":"50",
    "addr:postcode":"08731",
    "addr:street":"Railroad Ave",
    "iso:country":"US",
    "sg:address":"50 Railroad Ave",
    "sg:city":"Forked River",
    "sg:classifiers":[
        {
            "category":"Government",
            "subcategory":"Police Station",
            "type":"Public Place"
        }
    ],
    "sg:phone":"+1   ",
    "sg:postcode":"08731",
    "sg:province":"NJ",
    "sg:tags":[
        "protection"
    ],
    "wof:name":"Ocean Twp Police Dept",
    "wof:placetype":"venue"
},
  "geometry": {"coordinates":[-74.19398,39.837532],"type":"Point"}
}