{
  "type": "Feature",
  "properties": {
    "addr:full":"2408 Dune Dr Avalon NJ 08202",
    "addr:housenumber":"2408",
    "addr:postcode":"08202",
    "addr:street":"Dune Dr",
    "iso:country":"US",
    "sg:address":"2408 Dune Dr",
    "sg:city":"Avalon",
    "sg:classifiers":[
        {
            "category":"Restaurant",
            "type":"Food & Drink"
        }
    ],
    "sg:phone":"+1 609 967 3058",
    "sg:postcode":"08202",
    "sg:province":"NJ",
    "wof:name":"Brian's Waffle House",
    "wof:placetype":"venue"
},
  "geometry": {"coordinates":[-74.719722,39.0997],"type":"Point"}
}