{
  "type": "Feature",
  "properties": {
    "iso:country":"US",
    "sg:address":"2090 Greenwood Ave",
    "sg:city":"Trenton",
    "sg:classifiers":[
        {
            "category":"Government",
            "subcategory":"Office",
            "type":"Public Place"
        }
    ],
    "sg:phone":"+1   ",
    "sg:postcode":"08609",
    "sg:province":"NJ",
    "sg:tags":[
        "agency",
        "purchasing"
    ],
    "wof:name":"Dept of Budget and Purchasing",
    "wof:placetype":"venue"
},
  "geometry": {"coordinates":[-74.72326700000001,40.230621],"type":"Point"}
}