{
  "type": "Feature",
  "properties": {
    "addr:full":"3391 State Rte 27 Franklin Park NJ 08823",
    "addr:housenumber":"3391",
    "addr:postcode":"08823",
    "addr:street":"State Rte 27",
    "iso:country":"US",
    "sg:address":"3391 State Rte 27",
    "sg:city":"Franklin Park",
    "sg:classifiers":[
        {
            "category":"Food & Beverages",
            "subcategory":"Liquor & Beverages",
            "type":"Retail Goods"
        }
    ],
    "sg:phone":"+1 732 940 0440",
    "sg:postcode":"08823",
    "sg:province":"NJ",
    "wof:name":"Bottle King Liquors",
    "wof:placetype":"venue"
},
  "geometry": {"coordinates":[-74.556304,40.429723],"type":"Point"}
}