{
  "type": "Feature",
  "properties": {
    "iso:country":"US",
    "sg:address":"138 Michigan Ave",
    "sg:city":"Paterson",
    "sg:classifiers":[
        {
            "category":"Building & Trades",
            "subcategory":"Construction",
            "type":"Services"
        },
        {
            "category":"Manufacturing",
            "subcategory":"Tools & Machinery",
            "type":"Manufacturing & Wholesale Goods"
        }
    ],
    "sg:phone":"+1 973 278 5106",
    "sg:postcode":"07503",
    "sg:province":"NJ",
    "sg:tags":[
        "industrial",
        "balancing",
        "mfg"
    ],
    "wof:name":"New Jersey Balancing Svc Inc",
    "wof:placetype":"venue"
},
  "geometry": {"coordinates":[-74.152432,40.895142],"type":"Point"}
}