{
  "type": "Feature",
  "properties": {
    "iso:country":"US",
    "sg:address":"5 Hawthorne Ct",
    "sg:city":"Trenton",
    "sg:classifiers":[
        {
            "category":"Government",
            "subcategory":"Office",
            "type":"Public Place"
        }
    ],
    "sg:phone":"+1   ",
    "sg:postcode":"08690",
    "sg:province":"NJ",
    "sg:tags":[
        "space"
    ],
    "wof:name":"Syntech Solutions Inc",
    "wof:placetype":"venue"
},
  "geometry": {"coordinates":[-74.675493,40.202235],"type":"Point"}
}