{
  "type": "Feature",
  "properties": {
    "iso:country":"US",
    "sg:address":"210 Central Ave",
    "sg:city":"Passaic",
    "sg:classifiers":[
        {
            "category":"Retail",
            "subcategory":"Auto Repair",
            "type":"Services"
        }
    ],
    "sg:phone":"+1 973 777 4325",
    "sg:postcode":"07055",
    "sg:province":"NJ",
    "sg:tags":[
        "transmission",
        "tractor"
    ],
    "wof:name":"Carde's Transmission Inc",
    "wof:placetype":"venue"
},
  "geometry": {"coordinates":[-74.131451,40.8695],"type":"Point"}
}