{
  "type": "Feature",
  "properties": {
    "addr:full":"7 Westwood Ct Hewitt NJ 07421",
    "addr:housenumber":"7",
    "addr:postcode":"07421",
    "addr:street":"Westwood Ct",
    "iso:country":"US",
    "sg:address":"7 Westwood Ct",
    "sg:city":"Hewitt",
    "sg:classifiers":[
        {
            "category":"Building & Trades",
            "subcategory":"Plumbing",
            "type":"Services"
        }
    ],
    "sg:phone":"+1 973 853 1532",
    "sg:postcode":"07421",
    "sg:province":"NJ",
    "sg:tags":[
        "plumbing",
        "contractor"
    ],
    "wof:name":"J & D Plumbing",
    "wof:placetype":"venue"
},
  "geometry": {"coordinates":[-74.394611,41.164354],"type":"Point"}
}