{
  "type": "Feature",
  "properties": {
    "iso:country":"US",
    "sg:address":"336 Spencer Pl",
    "sg:city":"Paramus",
    "sg:classifiers":[
        {
            "category":"Professional",
            "type":"Services"
        }
    ],
    "sg:phone":"+1   ",
    "sg:postcode":"07652",
    "sg:province":"NJ",
    "wof:name":"Ciccio Inc",
    "wof:placetype":"venue"
},
  "geometry": {"coordinates":[-74.05226999999999,40.960787],"type":"Point"}
}