{
  "type": "Feature",
  "properties": {
    "iso:country":"US",
    "sg:address":"1107 Mount Kemble Ave",
    "sg:city":"Morristown",
    "sg:classifiers":[
        {
            "category":"Shopping",
            "subcategory":"Jewelry",
            "type":"Retail Goods"
        }
    ],
    "sg:phone":"+1 973 425 4485",
    "sg:postcode":"07960",
    "sg:province":"NJ",
    "wof:name":"New F Gerald Inc",
    "wof:placetype":"venue"
},
  "geometry": {"coordinates":[-74.523903,40.757301],"type":"Point"}
}