{
  "type": "Feature",
  "properties": {
    "addr:full":"425 Greenwood Ave Trenton NJ 08609",
    "addr:housenumber":"425",
    "addr:postcode":"08609",
    "addr:street":"Greenwood Ave",
    "iso:country":"US",
    "sg:address":"425 Greenwood Ave",
    "sg:city":"Trenton",
    "sg:classifiers":[
        {
            "category":"Organizations",
            "subcategory":"Political Organization",
            "type":"Services"
        }
    ],
    "sg:phone":"+1 609 989 1160",
    "sg:postcode":"08609",
    "sg:province":"NJ",
    "wof:name":"Environmental Fund New Jersey",
    "wof:placetype":"venue"
},
  "geometry": {"coordinates":[-74.753535,40.216956],"type":"Point"}
}