{
  "type": "Feature",
  "properties": {
    "addr:full":"12 S Broadway Camden NJ 08103",
    "addr:housenumber":"12",
    "addr:postcode":"08103",
    "addr:street":"S Broadway",
    "iso:country":"US",
    "sg:address":"12 S Broadway",
    "sg:city":"Camden",
    "sg:classifiers":[
        {
            "category":"Wholesale",
            "subcategory":"Hardware",
            "type":"Manufacturing & Wholesale Goods"
        }
    ],
    "sg:phone":"+1 856 964 0110",
    "sg:postcode":"08103",
    "sg:province":"NJ",
    "sg:tags":[
        "hardware-wholesale",
        "manufacturer"
    ],
    "wof:name":"Dion Gama",
    "wof:placetype":"venue"
},
  "geometry": {"coordinates":[-75.119184,39.943921],"type":"Point"}
}