{
  "type": "Feature",
  "properties": {
    "addr:full":"131 Wilcox Ct Matawan NJ 07747",
    "addr:housenumber":"131",
    "addr:postcode":"07747",
    "addr:street":"Wilcox Ct",
    "iso:country":"US",
    "sg:address":"131 Wilcox Ct",
    "sg:city":"Matawan",
    "sg:classifiers":[
        {
            "category":"Sports & Exercise",
            "subcategory":"Gym",
            "type":"Entertainment"
        }
    ],
    "sg:phone":"+1 732 409 6900",
    "sg:postcode":"07747",
    "sg:province":"NJ",
    "sg:tags":[
        "club",
        "health",
        "studio",
        "gymnasium"
    ],
    "wof:name":"Ladies Workout Express",
    "wof:placetype":"venue"
},
  "geometry": {"coordinates":[-74.257554,40.420071],"type":"Point"}
}