{
  "type": "Feature",
  "properties": {
    "addr:full":"212 Kuhl Rd Flemington NJ 08822",
    "addr:housenumber":"212",
    "addr:postcode":"08822",
    "addr:street":"Kuhl Rd",
    "iso:country":"US",
    "sg:address":"212 Kuhl Rd",
    "sg:city":"Flemington",
    "sg:classifiers":[
        {
            "category":"Personal",
            "subcategory":"Beauty Salon",
            "type":"Services"
        }
    ],
    "sg:phone":"+1   ",
    "sg:postcode":"08822",
    "sg:province":"NJ",
    "sg:tags":[
        "shop"
    ],
    "wof:name":"Weintraub & Weintraub Inc",
    "wof:placetype":"venue"
},
  "geometry": {"coordinates":[-74.816783,40.482133],"type":"Point"}
}