{
  "type": "Feature",
  "properties": {
    "iso:country":"US",
    "sg:address":"1420 Willow Ave",
    "sg:city":"Hoboken",
    "sg:classifiers":[
        {
            "category":"Freight",
            "type":"Transportation"
        }
    ],
    "sg:phone":"+1 201 798 8600",
    "sg:postcode":"07030",
    "sg:province":"NJ",
    "wof:name":"Transportation Solutions",
    "wof:placetype":"venue"
},
  "geometry": {"coordinates":[-74.02941199999999,40.754859],"type":"Point"}
}