{
  "type": "Feature",
  "properties": {
    "addr:full":"77 Willowbrook Blvd Wayne NJ 07470",
    "addr:housenumber":"77",
    "addr:postcode":"07470",
    "addr:street":"Willowbrook Blvd",
    "iso:country":"US",
    "sg:address":"77 Willowbrook Blvd",
    "sg:city":"Wayne",
    "sg:classifiers":[
        {
            "category":"Utilities",
            "subcategory":"Mobile Phone",
            "type":"Services"
        }
    ],
    "sg:phone":"+1 973 785 1993",
    "sg:postcode":"07470",
    "sg:province":"NJ",
    "sg:tags":[
        "communication",
        "radiotelephone"
    ],
    "wof:name":"Central Cellular Services",
    "wof:placetype":"venue"
},
  "geometry": {"coordinates":[-74.251418,40.888483],"type":"Point"}
}