{
  "type": "Feature",
  "properties": {
    "iso:country":"US",
    "sg:address":"49 W Mount Pleasant Ave",
    "sg:city":"Livingston",
    "sg:classifiers":[
        {
            "category":"Shopping",
            "subcategory":"Florist",
            "type":"Retail Goods"
        }
    ],
    "sg:postcode":"07039",
    "sg:province":"NJ",
    "sg:website":"www.FloristLivingston.com",
    "wof:name":"Livingston Florist",
    "wof:placetype":"venue"
},
  "geometry": {"coordinates":[-74.317567,40.795456],"type":"Point"}
}