{
  "type": "Feature",
  "properties": {
    "addr:full":"305 Saint Nicholas Ave Hillsdale NJ 07642",
    "addr:housenumber":"305",
    "addr:postcode":"07642",
    "addr:street":"Saint Nicholas Ave",
    "iso:country":"US",
    "sg:address":"305 Saint Nicholas Ave",
    "sg:city":"Hillsdale",
    "sg:classifiers":[
        {
            "category":"Professional",
            "subcategory":"Computer Services",
            "type":"Services"
        }
    ],
    "sg:phone":"+1 201 666 7411",
    "sg:postcode":"07642",
    "sg:province":"NJ",
    "sg:tags":[
        "consultant",
        "designer",
        "programing",
        "custom"
    ],
    "sg:website":"www.ncom-tech.com",
    "wof:name":"N Com Technology Inc",
    "wof:placetype":"venue"
},
  "geometry": {"coordinates":[-74.03891,41.01154],"type":"Point"}
}