{
  "type": "Feature",
  "properties": {
    "iso:country":"US",
    "sg:address":"105 Rodney St",
    "sg:city":"Glen Rock",
    "sg:classifiers":[
        {
            "category":"Building & Trades",
            "subcategory":"Construction",
            "type":"Services"
        }
    ],
    "sg:phone":"+1 201 670 6677",
    "sg:postcode":"07452",
    "sg:province":"NJ",
    "sg:tags":[
        "general",
        "contractor"
    ],
    "wof:name":"Covenant Construction",
    "wof:placetype":"venue"
},
  "geometry": {"coordinates":[-74.13117099999999,40.958601],"type":"Point"}
}