{
  "type": "Feature",
  "properties": {
    "addr:full":"222 N Wood Ave Linden NJ 07036",
    "addr:housenumber":"222",
    "addr:postcode":"07036",
    "addr:street":"N Wood Ave",
    "iso:country":"US",
    "sg:address":"222 N Wood Ave",
    "sg:city":"Linden",
    "sg:classifiers":[
        {
            "category":"Shopping",
            "subcategory":"Computers & Home Electronics",
            "type":"Retail Goods"
        }
    ],
    "sg:phone":"+1   ",
    "sg:postcode":"07036",
    "sg:province":"NJ",
    "wof:name":"Timco 110-220 Trading Co",
    "wof:placetype":"venue"
},
  "geometry": {"coordinates":[-74.254198,40.631553],"type":"Point"}
}