{
  "type": "Feature",
  "properties": {
    "addr:full":"619 Freeman St Lyndhurst NJ 07071",
    "addr:housenumber":"619",
    "addr:postcode":"07071",
    "addr:street":"Freeman St",
    "iso:country":"US",
    "sg:address":"619 Freeman St",
    "sg:city":"Lyndhurst",
    "sg:classifiers":[
        {
            "category":"Arts & Performance",
            "subcategory":"Theater",
            "type":"Entertainment"
        }
    ],
    "sg:phone":"+1   ",
    "sg:postcode":"07071",
    "sg:province":"NJ",
    "sg:tags":[
        "group"
    ],
    "wof:name":"Classic Entrmt By Dj Bobby G",
    "wof:placetype":"venue"
},
  "geometry": {"coordinates":[-74.117451,40.809692],"type":"Point"}
}