{
  "type": "Feature",
  "properties": {
    "addr:full":"126 Maple Pl Keyport NJ 07735",
    "addr:housenumber":"126",
    "addr:postcode":"07735",
    "addr:street":"Maple Pl",
    "iso:country":"US",
    "sg:address":"126 Maple Pl",
    "sg:city":"Keyport",
    "sg:classifiers":[
        {
            "category":"Shopping",
            "subcategory":"Beauty & Cosmetics",
            "type":"Retail Goods"
        }
    ],
    "sg:phone":"+1   ",
    "sg:postcode":"07735",
    "sg:province":"NJ",
    "sg:tags":[
        "merchandise"
    ],
    "wof:name":"Judy Thomas",
    "wof:placetype":"venue"
},
  "geometry": {"coordinates":[-74.204626,40.431695],"type":"Point"}
}