{
  "type": "Feature",
  "properties": {
    "iso:country":"US",
    "sg:address":"6 Jerome Smith Dr",
    "sg:city":"Asbury Park",
    "sg:classifiers":[
        {
            "category":"Professional",
            "type":"Services"
        }
    ],
    "sg:phone":"+1   ",
    "sg:postcode":"07712",
    "sg:province":"NJ",
    "wof:name":"Bonnies Baking World Inc",
    "wof:placetype":"venue"
},
  "geometry": {"coordinates":[-74.061498,40.242785],"type":"Point"}
}