{
  "type": "Feature",
  "properties": {
    "addr:full":"176 Saddle River Rd South Hackensack NJ 07606",
    "addr:housenumber":"176",
    "addr:postcode":"07606",
    "addr:street":"Saddle River Rd",
    "iso:country":"US",
    "sg:address":"176 Saddle River Rd",
    "sg:city":"South Hackensack",
    "sg:classifiers":[
        {
            "category":"Building & Trades",
            "subcategory":"Construction",
            "type":"Services"
        }
    ],
    "sg:phone":"+1 973 246 7079",
    "sg:postcode":"07606",
    "sg:province":"NJ",
    "sg:tags":[
        "contractor"
    ],
    "wof:name":"Custom Exteriors",
    "wof:placetype":"venue"
},
  "geometry": {"coordinates":[-74.097706,40.865106],"type":"Point"}
}