{
  "type": "Feature",
  "properties": {
    "addr:full":"181 Long Hill Rd Little Falls NJ 07424",
    "addr:housenumber":"181",
    "addr:postcode":"07424",
    "addr:street":"Long Hill Rd",
    "iso:country":"US",
    "sg:address":"181 Long Hill Rd",
    "sg:city":"Little Falls",
    "sg:classifiers":[
        {
            "category":"Professional",
            "subcategory":"Accounting & Tax Preparation",
            "type":"Services"
        }
    ],
    "sg:phone":"+1 973 256 8191",
    "sg:postcode":"07424",
    "sg:province":"NJ",
    "wof:name":"Ardnas Consulting",
    "wof:placetype":"venue"
},
  "geometry": {"coordinates":[-74.20674099999999,40.873269],"type":"Point"}
}