{
  "type": "Feature",
  "properties": {
    "iso:country":"US",
    "sg:address":"127 Belleville Ave",
    "sg:city":"Belleville",
    "sg:classifiers":[
        {
            "category":"Retail",
            "subcategory":"Auto Repair",
            "type":"Services"
        }
    ],
    "sg:phone":"+1 973 751 3900",
    "sg:postcode":"07109",
    "sg:province":"NJ",
    "sg:tags":[
        "gasoline"
    ],
    "wof:name":"Ravi Gas Supply Inc",
    "wof:placetype":"venue"
},
  "geometry": {"coordinates":[-74.154701,40.7864],"type":"Point"}
}