{
  "type": "Feature",
  "properties": {
    "addr:full":"2306 Eagle Row Marlton NJ 08053",
    "addr:housenumber":"2306",
    "addr:postcode":"08053",
    "addr:street":"Eagle Row",
    "iso:country":"US",
    "sg:address":"2306 Eagle Row",
    "sg:city":"Marlton",
    "sg:classifiers":[
        {
            "category":"Education",
            "subcategory":"Special Training",
            "type":"Public Place"
        }
    ],
    "sg:phone":"+1 856 988 6308",
    "sg:postcode":"08053",
    "sg:province":"NJ",
    "sg:tags":[
        "aircraft",
        "flight",
        "sales",
        "maintenance",
        "airline"
    ],
    "wof:name":"Ikaros Aviation International",
    "wof:placetype":"venue"
},
  "geometry": {"coordinates":[-74.94905900000001,39.91339],"type":"Point"}
}