{
  "type": "Feature",
  "properties": {
    "iso:country":"US",
    "sg:address":"224 Ramblewood Pkwy",
    "sg:city":"Mount Laurel",
    "sg:classifiers":[
        {
            "category":"Social Services",
            "subcategory":"Child Care",
            "type":"Services"
        }
    ],
    "sg:phone":"+1   ",
    "sg:postcode":"08054",
    "sg:province":"NJ",
    "sg:tags":[
        "day"
    ],
    "wof:name":"Family Fun Daycare",
    "wof:placetype":"venue"
},
  "geometry": {"coordinates":[-74.94447099999999,39.932365],"type":"Point"}
}