{
  "type": "Feature",
  "properties": {
    "iso:country":"US",
    "sg:address":"281 Roycefield Rd",
    "sg:city":"Hillsborough",
    "sg:classifiers":[
        {
            "category":"Retail",
            "subcategory":"Animal Services",
            "type":"Services"
        }
    ],
    "sg:phone":"+1 908 431 0100",
    "sg:postcode":"08844",
    "sg:province":"NJ",
    "sg:tags":[
        "pet",
        "boarding",
        "sitting"
    ],
    "wof:name":"Dog Days Daycare Ctr",
    "wof:placetype":"venue"
},
  "geometry": {"coordinates":[-74.640512,40.53628],"type":"Point"}
}