{
  "type": "Feature",
  "properties": {
    "iso:country":"US",
    "sg:address":"23 Henning Dr",
    "sg:city":"Fairfield",
    "sg:classifiers":[
        {
            "category":"Wholesale",
            "subcategory":"Non-durable Goods",
            "type":"Manufacturing & Wholesale Goods"
        }
    ],
    "sg:phone":"+1 973 989 9191",
    "sg:postcode":"07004",
    "sg:province":"NJ",
    "sg:tags":[
        "souvenir"
    ],
    "wof:name":"Fred Bolton",
    "wof:placetype":"venue"
},
  "geometry": {"coordinates":[-74.30499399999999,40.879418],"type":"Point"}
}