{
  "type": "Feature",
  "properties": {
    "addr:full":"498 Watchung Ave Bloomfield NJ 07003",
    "addr:housenumber":"498",
    "addr:postcode":"07003",
    "addr:street":"Watchung Ave",
    "iso:country":"US",
    "sg:address":"498 Watchung Ave",
    "sg:city":"Bloomfield",
    "sg:classifiers":[
        {
            "category":"Organizations",
            "subcategory":"Religious Organization",
            "type":"Services"
        }
    ],
    "sg:phone":"+1 973 338 1350",
    "sg:postcode":"07003",
    "sg:province":"NJ",
    "sg:tags":[
        "church"
    ],
    "wof:name":"Christ Temple Church God In",
    "wof:placetype":"venue"
},
  "geometry": {"coordinates":[-74.18911900000001,40.828374],"type":"Point"}
}