{
  "type": "Feature",
  "properties": {
    "iso:country":"US",
    "sg:address":"760 Memorial Pkwy",
    "sg:city":"Phillipsburg",
    "sg:classifiers":[
        {
            "category":"Shopping",
            "subcategory":"Computers & Home Electronics",
            "type":"Retail Goods"
        }
    ],
    "sg:phone":"+1 908 213 0001",
    "sg:postcode":"08865",
    "sg:province":"NJ",
    "sg:tags":[
        "system"
    ],
    "wof:name":"Audio-Video Synergy Inc",
    "wof:placetype":"venue"
},
  "geometry": {"coordinates":[-75.17268,40.697879],"type":"Point"}
}