{
  "type": "Feature",
  "properties": {
    "iso:country":"US",
    "sg:address":"114 Essex St",
    "sg:city":"Rochelle Park",
    "sg:classifiers":[
        {
            "category":"Wholesale",
            "subcategory":"Durable Goods & Equipment",
            "type":"Manufacturing & Wholesale Goods"
        }
    ],
    "sg:phone":"+1 201 501 8336",
    "sg:postcode":"07662",
    "sg:province":"NJ",
    "sg:tags":[
        "representative",
        "manufacturer"
    ],
    "sg:website":"www.davemurphy.com",
    "wof:name":"David Murphy & Assoc",
    "wof:placetype":"venue"
},
  "geometry": {"coordinates":[-74.074066,40.892834],"type":"Point"}
}