{
  "type": "Feature",
  "properties": {
    "iso:country":"US",
    "sg:address":"97 Brunswick Woods Dr",
    "sg:city":"East Brunswick",
    "sg:classifiers":[
        {
            "category":"Restaurant",
            "type":"Food & Drink"
        }
    ],
    "sg:phone":"+1 732 821 4409",
    "sg:postcode":"08816",
    "sg:province":"NJ",
    "wof:name":"Tamarack Snack Bar",
    "wof:placetype":"venue"
},
  "geometry": {"coordinates":[-74.390406,40.422249],"type":"Point"}
}