{
  "type": "Feature",
  "properties": {
    "iso:country":"US",
    "sg:address":"2069 State Rte 35",
    "sg:city":"South Amboy",
    "sg:classifiers":[
        {
            "category":"Building & Trades",
            "subcategory":"Landscaping Services",
            "type":"Services"
        }
    ],
    "sg:phone":"+1 732 721 7200",
    "sg:postcode":"08879",
    "sg:province":"NJ",
    "wof:name":"Applied Landscape Technologies",
    "wof:placetype":"venue"
},
  "geometry": {"coordinates":[-74.27637900000001,40.464583],"type":"Point"}
}