{
  "type": "Feature",
  "properties": {
    "addr:full":"100 Richey Ave Collingswood NJ 08107",
    "addr:housenumber":"100",
    "addr:postcode":"08107",
    "addr:street":"Richey Ave",
    "iso:country":"US",
    "sg:address":"100 Richey Ave",
    "sg:city":"Collingswood",
    "sg:classifiers":[
        {
            "category":"Professional",
            "subcategory":"Accounting & Tax Preparation",
            "type":"Services"
        }
    ],
    "sg:phone":"+1 856 854 2224",
    "sg:postcode":"08107",
    "sg:province":"NJ",
    "sg:tags":[
        "accountant"
    ],
    "wof:name":"Shm Associates",
    "wof:placetype":"venue"
},
  "geometry": {"coordinates":[-75.09047200000001,39.918527],"type":"Point"}
}