{
  "type": "Feature",
  "properties": {
    "iso:country":"US",
    "sg:address":"41 Hillcrest Rd",
    "sg:city":"Caldwell",
    "sg:classifiers":[
        {
            "category":"Professional",
            "subcategory":"Management & Consulting",
            "type":"Services"
        }
    ],
    "sg:phone":"+1   ",
    "sg:postcode":"07006",
    "sg:province":"NJ",
    "sg:tags":[
        "computer",
        "custom"
    ],
    "wof:name":"Van Guard Data Systems",
    "wof:placetype":"venue"
},
  "geometry": {"coordinates":[-74.281902,40.847902],"type":"Point"}
}