{
  "type": "Feature",
  "properties": {
    "addr:full":"183 Smith St Salem NJ 08079",
    "addr:housenumber":"183",
    "addr:postcode":"08079",
    "addr:street":"Smith St",
    "iso:country":"US",
    "sg:address":"183 Smith St",
    "sg:city":"Salem",
    "sg:classifiers":[
        {
            "category":"Education",
            "subcategory":"School",
            "type":"Public Place"
        }
    ],
    "sg:phone":"+1   ",
    "sg:postcode":"08079",
    "sg:province":"NJ",
    "sg:website":"www.salemnj.org",
    "wof:name":"John Fenwick Elementary School",
    "wof:placetype":"venue"
},
  "geometry": {"coordinates":[-75.468726,39.567278],"type":"Point"}
}