{
  "type": "Feature",
  "properties": {
    "addr:full":"5 Meadowlark Ct Jackson NJ 08527",
    "addr:housenumber":"5",
    "addr:postcode":"08527",
    "addr:street":"Meadowlark Ct",
    "iso:country":"US",
    "sg:address":"5 Meadowlark Ct",
    "sg:city":"Jackson",
    "sg:classifiers":[
        {
            "category":"Travel",
            "subcategory":"Travel Agent",
            "type":"Entertainment"
        }
    ],
    "sg:phone":"+1 732 689 2251",
    "sg:postcode":"08527",
    "sg:province":"NJ",
    "sg:tags":[
        "agency"
    ],
    "wof:name":"Garden State Getaways",
    "wof:placetype":"venue"
},
  "geometry": {"coordinates":[-74.351409,40.128416],"type":"Point"}
}