{
  "type": "Feature",
  "properties": {
    "addr:full":"32 Berkshire Dr Sewell NJ 08080",
    "addr:housenumber":"32",
    "addr:postcode":"08080",
    "addr:street":"Berkshire Dr",
    "iso:country":"US",
    "sg:address":"32 Berkshire Dr",
    "sg:city":"Sewell",
    "sg:classifiers":[
        {
            "category":"Retail",
            "subcategory":"Car Wash",
            "type":"Services"
        }
    ],
    "sg:phone":"+1 856 374 3355",
    "sg:postcode":"08080",
    "sg:province":"NJ",
    "sg:tags":[
        "carwash"
    ],
    "wof:name":"Chriss Pressure Wash",
    "wof:placetype":"venue"
},
  "geometry": {"coordinates":[-75.081124,39.771207],"type":"Point"}
}