{
  "type": "Feature",
  "properties": {
    "iso:country":"US",
    "sg:address":"8 N 3rd St",
    "sg:city":"Park Ridge",
    "sg:classifiers":[
        {
            "category":"Manufacturing",
            "subcategory":"Printing",
            "type":"Manufacturing & Wholesale Goods"
        }
    ],
    "sg:phone":"+1 201 391 5215",
    "sg:postcode":"07656",
    "sg:province":"NJ",
    "sg:tags":[
        "book"
    ],
    "wof:name":"J K R Publishing",
    "wof:placetype":"venue"
},
  "geometry": {"coordinates":[-74.04794,41.038991],"type":"Point"}
}