{
  "type": "Feature",
  "properties": {
    "iso:country":"US",
    "sg:address":"85 Bayberry Dr",
    "sg:city":"Somerset",
    "sg:classifiers":[
        {
            "category":"Professional",
            "subcategory":"Management & Consulting",
            "type":"Services"
        }
    ],
    "sg:phone":"+1 732 873 8383",
    "sg:postcode":"08873",
    "sg:province":"NJ",
    "sg:tags":[
        "business"
    ],
    "wof:name":"Adar Consulting",
    "wof:placetype":"venue"
},
  "geometry": {"coordinates":[-74.50477600000001,40.506195],"type":"Point"}
}