{
  "type": "Feature",
  "properties": {
    "addr:full":"424 Coolidge Ave Westwood NJ 07676",
    "addr:housenumber":"424",
    "addr:postcode":"07676",
    "addr:street":"Coolidge Ave",
    "iso:country":"US",
    "sg:address":"424 Coolidge Ave",
    "sg:city":"Westwood",
    "sg:classifiers":[
        {
            "category":"Banks & Credit Unions",
            "subcategory":"Investment Brokerage",
            "type":"Services"
        }
    ],
    "sg:phone":"+1   ",
    "sg:postcode":"07676",
    "sg:province":"NJ",
    "wof:name":"Raymond C Bolleria",
    "wof:placetype":"venue"
},
  "geometry": {"coordinates":[-74.06950999999999,40.989791],"type":"Point"}
}