{
  "type": "Feature",
  "properties": {
    "addr:full":"490 Broadway Bayonne NJ 07002",
    "addr:housenumber":"490",
    "addr:postcode":"07002",
    "addr:street":"Broadway",
    "iso:country":"US",
    "sg:address":"490 Broadway",
    "sg:city":"Bayonne",
    "sg:classifiers":[
        {
            "category":"Building & Trades",
            "subcategory":"Construction",
            "type":"Services"
        }
    ],
    "sg:phone":"+1 201 858 2568",
    "sg:postcode":"07002",
    "sg:province":"NJ",
    "sg:tags":[
        "contractor"
    ],
    "wof:name":"Vvm General Contracting Inc",
    "wof:placetype":"venue"
},
  "geometry": {"coordinates":[-74.118556,40.663318],"type":"Point"}
}