{
  "type": "Feature",
  "properties": {
    "iso:country":"US",
    "sg:address":"468 Chancellor Ave",
    "sg:city":"Irvington",
    "sg:classifiers":[
        {
            "category":"Shopping",
            "type":"Retail Goods"
        }
    ],
    "sg:phone":"+1   ",
    "sg:postcode":"07111",
    "sg:province":"NJ",
    "sg:tags":[
        "merchandise"
    ],
    "wof:name":"Mahogany Store",
    "wof:placetype":"venue"
},
  "geometry": {"coordinates":[-74.227265,40.712465],"type":"Point"}
}