{
  "type": "Feature",
  "properties": {
    "iso:country":"US",
    "sg:address":"106 Goffle Rd",
    "sg:city":"Hawthorne",
    "sg:classifiers":[
        {
            "category":"Retail",
            "subcategory":"Auto Repair",
            "type":"Services"
        }
    ],
    "sg:phone":"+1   ",
    "sg:postcode":"07506",
    "sg:province":"NJ",
    "sg:tags":[
        "automotive"
    ],
    "wof:name":"Lubexpress",
    "wof:placetype":"venue"
},
  "geometry": {"coordinates":[-74.164108,40.940028],"type":"Point"}
}