{
  "type": "Feature",
  "properties": {
    "addr:full":"248 Fowler Ave Jersey City NJ 07305",
    "addr:housenumber":"248",
    "addr:postcode":"07305",
    "addr:street":"Fowler Ave",
    "iso:country":"US",
    "sg:address":"248 Fowler Ave",
    "sg:city":"Jersey City",
    "sg:classifiers":[
        {
            "category":"Freight",
            "type":"Transportation"
        }
    ],
    "sg:phone":"+1 201 435 0821",
    "sg:postcode":"07305",
    "sg:province":"NJ",
    "sg:tags":[
        "operator",
        "trucking"
    ],
    "wof:name":"Amse Transport Corp",
    "wof:placetype":"venue"
},
  "geometry": {"coordinates":[-74.092056,40.703252],"type":"Point"}
}