{
  "type": "Feature",
  "properties": {
    "addr:full":"226 State Rte 94 Vernon NJ 07462",
    "addr:housenumber":"226",
    "addr:postcode":"07462",
    "addr:street":"State Rte 94",
    "iso:country":"US",
    "sg:address":"226 State Rte 94",
    "sg:city":"Vernon",
    "sg:classifiers":[
        {
            "category":"Education",
            "subcategory":"Special Training",
            "type":"Public Place"
        }
    ],
    "sg:phone":"+1 973 823 9368",
    "sg:postcode":"07462",
    "sg:province":"NJ",
    "sg:tags":[
        "center"
    ],
    "wof:name":"Primary Colors Early Learning",
    "wof:placetype":"venue"
},
  "geometry": {"coordinates":[-74.49373900000001,41.195249],"type":"Point"}
}