{
  "type": "Feature",
  "properties": {
    "addr:full":"6 Dougal Ave Livingston NJ 07039",
    "addr:housenumber":"6",
    "addr:postcode":"07039",
    "addr:street":"Dougal Ave",
    "iso:country":"US",
    "sg:address":"6 Dougal Ave",
    "sg:city":"Livingston",
    "sg:classifiers":[
        {
            "category":"Professional",
            "type":"Services"
        }
    ],
    "sg:phone":"+1   ",
    "sg:postcode":"07039",
    "sg:province":"NJ",
    "wof:name":"Salvatore Rainone Co",
    "wof:placetype":"venue"
},
  "geometry": {"coordinates":[-74.30737000000001,40.783833],"type":"Point"}
}