{
  "type": "Feature",
  "properties": {
    "addr:full":"6 Beachview Ct Stockholm NJ 07460",
    "addr:housenumber":"6",
    "addr:postcode":"07460",
    "addr:street":"Beachview Ct",
    "iso:country":"US",
    "sg:address":"6 Beachview Ct",
    "sg:city":"Stockholm",
    "sg:classifiers":[
        {
            "category":"Building & Trades",
            "subcategory":"Construction",
            "type":"Services"
        }
    ],
    "sg:phone":"+1 973 872 1335",
    "sg:postcode":"07460",
    "sg:province":"NJ",
    "sg:tags":[
        "system",
        "contractor",
        "air conditioning"
    ],
    "wof:name":"Air-Network North",
    "wof:placetype":"venue"
},
  "geometry": {"coordinates":[-74.535842,41.095969],"type":"Point"}
}