{
  "type": "Feature",
  "properties": {
    "addr:full":"1778 E 2nd St Scotch Plains NJ 07076",
    "addr:housenumber":"1778",
    "addr:postcode":"07076",
    "addr:street":"E 2Nd St",
    "iso:country":"US",
    "sg:address":"1778 E 2nd St",
    "sg:city":"Scotch Plains",
    "sg:classifiers":[
        {
            "category":"Shopping",
            "subcategory":"Bicycles & Sporting Goods",
            "type":"Retail Goods"
        }
    ],
    "sg:phone":"+1 908 322 3330",
    "sg:postcode":"07076",
    "sg:province":"NJ",
    "wof:name":"Bike Stand",
    "wof:placetype":"venue"
},
  "geometry": {"coordinates":[-74.397835,40.647935],"type":"Point"}
}