{
  "type": "Feature",
  "properties": {
    "iso:country":"US",
    "sg:address":"196 W Midland Ave",
    "sg:city":"Paramus",
    "sg:classifiers":[
        {
            "category":"Government",
            "subcategory":"Fire Station",
            "type":"Public Place"
        }
    ],
    "sg:phone":"+1 201 652 6226",
    "sg:postcode":"07652",
    "sg:province":"NJ",
    "sg:tags":[
        "department"
    ],
    "sg:website":"www.paramusfire.org",
    "wof:name":"Paramus Boro Fire Co No 3",
    "wof:placetype":"venue"
},
  "geometry": {"coordinates":[-74.08630100000001,40.95805],"type":"Point"}
}