{
  "type": "Feature",
  "properties": {
    "addr:full":"288 State St Hackensack NJ 07601",
    "addr:housenumber":"288",
    "addr:postcode":"07601",
    "addr:street":"State St",
    "iso:country":"US",
    "sg:address":"288 State St",
    "sg:city":"Hackensack",
    "sg:classifiers":[
        {
            "category":"Travel",
            "subcategory":"Hotels & Motels",
            "type":"Entertainment"
        }
    ],
    "sg:phone":"+1 201 343 4615",
    "sg:postcode":"07601",
    "sg:province":"NJ",
    "wof:name":"State Hotel",
    "wof:placetype":"venue"
},
  "geometry": {"coordinates":[-74.042603,40.887501],"type":"Point"}
}