{
  "type": "Feature",
  "properties": {
    "iso:country":"US",
    "sg:address":"111 Main St",
    "sg:city":"Allenhurst",
    "sg:classifiers":[
        {
            "category":"Professional",
            "subcategory":"Lawyer & Legal Services",
            "type":"Services"
        }
    ],
    "sg:phone":"+1 732 774 8005",
    "sg:postcode":"07711",
    "sg:province":"NJ",
    "sg:tags":[
        "attorney"
    ],
    "wof:name":"Stacey C Maiden",
    "wof:placetype":"venue"
},
  "geometry": {"coordinates":[-74.005861,40.238099],"type":"Point"}
}