{
  "type": "Feature",
  "properties": {
    "addr:full":"95 Fleming Ave Newark NJ 07105",
    "addr:housenumber":"95",
    "addr:postcode":"07105",
    "addr:street":"Fleming Ave",
    "iso:country":"US",
    "sg:address":"95 Fleming Ave",
    "sg:city":"Newark",
    "sg:classifiers":[
        {
            "category":"Social Services",
            "type":"Services"
        }
    ],
    "sg:phone":"+1 973 344 6695",
    "sg:postcode":"07105",
    "sg:province":"NJ",
    "wof:name":"Senior Ride",
    "wof:placetype":"venue"
},
  "geometry": {"coordinates":[-74.142984,40.732054],"type":"Point"}
}