{
  "type": "Feature",
  "properties": {
    "iso:country":"US",
    "sg:address":"370 Whitesville Rd",
    "sg:city":"Jackson",
    "sg:classifiers":[
        {
            "category":"Wholesale",
            "subcategory":"Medical Equipment & Supplies",
            "type":"Manufacturing & Wholesale Goods"
        }
    ],
    "sg:phone":"+1 732 730 1900",
    "sg:postcode":"08527",
    "sg:province":"NJ",
    "sg:tags":[
        "hospital"
    ],
    "sg:website":"www.meritmedical.com",
    "wof:name":"Merit Medical Systems Inc",
    "wof:placetype":"venue"
},
  "geometry": {"coordinates":[-74.26722100000001,40.066405],"type":"Point"}
}