{
  "type": "Feature",
  "properties": {
    "addr:full":"480 N Beverwyck Rd Lake Hiawatha NJ 07034",
    "addr:housenumber":"480",
    "addr:postcode":"07034",
    "addr:street":"N Beverwyck Rd",
    "iso:country":"US",
    "sg:address":"480 N Beverwyck Rd",
    "sg:city":"Lake Hiawatha",
    "sg:classifiers":[
        {
            "category":"Banks & Credit Unions",
            "subcategory":"Bank",
            "type":"Services"
        }
    ],
    "sg:phone":"+1 973 000 1111",
    "sg:postcode":"07034",
    "sg:province":"NJ",
    "sg:website":"www.fleet.com",
    "wof:name":"Bank Of America",
    "wof:placetype":"venue"
},
  "geometry": {"coordinates":[-74.37795300000001,40.890885],"type":"Point"}
}