{
  "type": "Feature",
  "properties": {
    "iso:country":"US",
    "sg:address":"2117 Whitesville Rd",
    "sg:city":"Toms River",
    "sg:classifiers":[
        {
            "category":"Professional",
            "subcategory":"Accounting & Tax Preparation",
            "type":"Services"
        }
    ],
    "sg:phone":"+1 732 785 0040",
    "sg:postcode":"08755",
    "sg:province":"NJ",
    "sg:tags":[
        "return",
        "filing"
    ],
    "wof:name":"Accurate Facts N Figures",
    "wof:placetype":"venue"
},
  "geometry": {"coordinates":[-74.242919,40.038079],"type":"Point"}
}