{
  "type": "Feature",
  "properties": {
    "iso:country":"US",
    "sg:address":"507 Elm Ave",
    "sg:city":"Woodbury",
    "sg:classifiers":[
        {
            "category":"Wholesale",
            "subcategory":"Vending Machines",
            "type":"Manufacturing & Wholesale Goods"
        }
    ],
    "sg:phone":"+1 856 845 4913",
    "sg:postcode":"08096",
    "sg:province":"NJ",
    "wof:name":"Bekay Vending",
    "wof:placetype":"venue"
},
  "geometry": {"coordinates":[-75.147914,39.826635],"type":"Point"}
}