{
  "type": "Feature",
  "properties": {
    "iso:country":"US",
    "sg:address":"256 Tenafly Rd",
    "sg:city":"Tenafly",
    "sg:classifiers":[
        {
            "category":"Shopping",
            "subcategory":"Gifts & Souvenirs",
            "type":"Retail Goods"
        }
    ],
    "sg:phone":"+1 201 816 8815",
    "sg:postcode":"07670",
    "sg:province":"NJ",
    "sg:tags":[
        "shop"
    ],
    "wof:name":"Art Of Gifts Too",
    "wof:placetype":"venue"
},
  "geometry": {"coordinates":[-73.968557,40.922547],"type":"Point"}
}