{
  "type": "Feature",
  "properties": {
    "addr:full":"10 Hillsdale Ave Long Branch NJ 07740",
    "addr:housenumber":"10",
    "addr:postcode":"07740",
    "addr:street":"Hillsdale Ave",
    "iso:country":"US",
    "sg:address":"10 Hillsdale Ave",
    "sg:city":"Long Branch",
    "sg:classifiers":[
        {
            "category":"Retail",
            "subcategory":"Laundry & Dry Cleaning",
            "type":"Services"
        }
    ],
    "sg:phone":"+1 732 263 9177",
    "sg:postcode":"07740",
    "sg:province":"NJ",
    "sg:tags":[
        "cleaners",
        "upholstery",
        "rug",
        "carpet"
    ],
    "wof:name":"Acey Ducey Enterprise Inc",
    "wof:placetype":"venue"
},
  "geometry": {"coordinates":[-73.99103599999999,40.318709],"type":"Point"}
}