{
  "type": "Feature",
  "properties": {
    "iso:country":"US",
    "sg:address":"768 Ramsey Ave",
    "sg:city":"Hillside",
    "sg:classifiers":[
        {
            "category":"Freight",
            "type":"Transportation"
        }
    ],
    "sg:phone":"+1 973 371 0888",
    "sg:postcode":"07205",
    "sg:province":"NJ",
    "sg:tags":[
        "warehouse"
    ],
    "wof:name":"Irvington Beauty & Barber Sups",
    "wof:placetype":"venue"
},
  "geometry": {"coordinates":[-74.23304899999999,40.708722],"type":"Point"}
}