{
  "type": "Feature",
  "properties": {
    "addr:full":"132 Liberty Blvd Phillipsburg NJ 08865",
    "addr:housenumber":"132",
    "addr:postcode":"08865",
    "addr:street":"Liberty Blvd",
    "iso:country":"US",
    "sg:address":"132 Liberty Blvd",
    "sg:city":"Phillipsburg",
    "sg:classifiers":[
        {
            "category":"Arts & Performance",
            "subcategory":"Theater",
            "type":"Entertainment"
        }
    ],
    "sg:phone":"+1   ",
    "sg:postcode":"08865",
    "sg:province":"NJ",
    "sg:tags":[
        "group"
    ],
    "wof:name":"Forgery The",
    "wof:placetype":"venue"
},
  "geometry": {"coordinates":[-75.15628599999999,40.679474],"type":"Point"}
}