{
  "type": "Feature",
  "properties": {
    "iso:country":"US",
    "sg:address":"1523 John St",
    "sg:city":"Fort Lee",
    "sg:classifiers":[
        {
            "category":"Professional",
            "type":"Services"
        }
    ],
    "sg:phone":"+1   ",
    "sg:postcode":"07024",
    "sg:province":"NJ",
    "wof:name":"Pricemix Co Inc",
    "wof:placetype":"venue"
},
  "geometry": {"coordinates":[-73.97932400000001,40.853223],"type":"Point"}
}