{
  "type": "Feature",
  "properties": {
    "addr:full":"5 Oakridge Rd Washington NJ 07882",
    "addr:housenumber":"5",
    "addr:postcode":"07882",
    "addr:street":"Oakridge Rd",
    "iso:country":"US",
    "sg:address":"5 Oakridge Rd",
    "sg:city":"Washington",
    "sg:classifiers":[
        {
            "category":"Building & Trades",
            "subcategory":"Electrical",
            "type":"Services"
        }
    ],
    "sg:phone":"+1 908 689 6259",
    "sg:postcode":"07882",
    "sg:province":"NJ",
    "sg:tags":[
        "electric",
        "contractor"
    ],
    "wof:name":"A & M Electric Inc",
    "wof:placetype":"venue"
},
  "geometry": {"coordinates":[-74.974165,40.767959],"type":"Point"}
}