{
  "type": "Feature",
  "properties": {
    "addr:full":"687 Colgate Ave Lanoka Harbor NJ 08734",
    "addr:housenumber":"687",
    "addr:postcode":"08734",
    "addr:street":"Colgate Ave",
    "iso:country":"US",
    "sg:address":"687 Colgate Ave",
    "sg:city":"Lanoka Harbor",
    "sg:classifiers":[
        {
            "category":"Manufacturing",
            "subcategory":"Tools & Machinery",
            "type":"Manufacturing & Wholesale Goods"
        }
    ],
    "sg:phone":"+1 609 971 3176",
    "sg:postcode":"08734",
    "sg:province":"NJ",
    "sg:tags":[
        "food",
        "product",
        "engineering",
        "mfg"
    ],
    "wof:name":"A P V Crepaco",
    "wof:placetype":"venue"
},
  "geometry": {"coordinates":[-74.193383,39.873745],"type":"Point"}
}