{
  "type": "Feature",
  "properties": {
    "iso:country":"US",
    "sg:address":"4 Acorn Dr",
    "sg:city":"Vincentown",
    "sg:classifiers":[
        {
            "category":"Building & Trades",
            "subcategory":"Construction",
            "type":"Services"
        }
    ],
    "sg:phone":"+1 609 859 1118",
    "sg:postcode":"08088",
    "sg:province":"NJ",
    "sg:tags":[
        "residential"
    ],
    "wof:name":"Lou Love & Sons Inc",
    "wof:placetype":"venue"
},
  "geometry": {"coordinates":[-74.685913,39.873225],"type":"Point"}
}