{
  "type": "Feature",
  "properties": {
    "addr:full":"110 Bartley Rd Flanders NJ 07836",
    "addr:housenumber":"110",
    "addr:postcode":"07836",
    "addr:street":"Bartley Rd",
    "iso:country":"US",
    "sg:address":"110 Bartley Rd",
    "sg:city":"Flanders",
    "sg:classifiers":[
        {
            "category":"Recreation",
            "type":"Entertainment"
        }
    ],
    "sg:phone":"+1 973 927 5059",
    "sg:postcode":"07836",
    "sg:province":"NJ",
    "sg:tags":[
        "consulting",
        "management"
    ],
    "wof:name":"Flanders Yoga Studio",
    "wof:placetype":"venue"
},
  "geometry": {"coordinates":[-74.71991800000001,40.827564],"type":"Point"}
}