{
  "type": "Feature",
  "properties": {
    "addr:full":"1703 Main St Belmar NJ 07719",
    "addr:housenumber":"1703",
    "addr:postcode":"07719",
    "addr:street":"Main St",
    "iso:country":"US",
    "sg:address":"1703 Main St",
    "sg:city":"Belmar",
    "sg:classifiers":[
        {
            "category":"Autos & Motor Vehicles",
            "subcategory":"Automobile Sales",
            "type":"Retail Goods"
        }
    ],
    "sg:phone":"+1 732 280 0677",
    "sg:postcode":"07719",
    "sg:province":"NJ",
    "sg:tags":[
        "car",
        "dealer"
    ],
    "wof:name":"BSK Auto Sales",
    "wof:placetype":"venue"
},
  "geometry": {"coordinates":[-74.027473,40.171857],"type":"Point"}
}