{
  "type": "Feature",
  "properties": {
    "addr:full":"18 Ekstrom St Dover NJ 07801",
    "addr:housenumber":"18",
    "addr:postcode":"07801",
    "addr:street":"Ekstrom St",
    "iso:country":"US",
    "sg:address":"18 Ekstrom St",
    "sg:city":"Dover",
    "sg:classifiers":[
        {
            "category":"Building & Trades",
            "subcategory":"Landscaping Services",
            "type":"Services"
        }
    ],
    "sg:phone":"+1 973 361 5053",
    "sg:postcode":"07801",
    "sg:province":"NJ",
    "sg:tags":[
        "designer",
        "landscape"
    ],
    "wof:name":"Wag",
    "wof:placetype":"venue"
},
  "geometry": {"coordinates":[-74.540935,40.888129],"type":"Point"}
}