{
  "type": "Feature",
  "properties": {
    "addr:full":"2506 E Landis Ave Vineland NJ 08361",
    "addr:housenumber":"2506",
    "addr:postcode":"08361",
    "addr:street":"E Landis Ave",
    "iso:country":"US",
    "sg:address":"2506 E Landis Ave",
    "sg:city":"Vineland",
    "sg:classifiers":[
        {
            "category":"Shopping",
            "subcategory":"Clothing, Apparel, & Fashions",
            "type":"Retail Goods"
        }
    ],
    "sg:phone":"+1   ",
    "sg:postcode":"08361",
    "sg:province":"NJ",
    "wof:name":"Killbrand",
    "wof:placetype":"venue"
},
  "geometry": {"coordinates":[-74.978337,39.484001],"type":"Point"}
}