{
  "type": "Feature",
  "properties": {
    "iso:country":"US",
    "sg:address":"710 US Hwy 46",
    "sg:city":"Fairfield",
    "sg:classifiers":[
        {
            "category":"Professional",
            "subcategory":"Accounting & Tax Preparation",
            "type":"Services"
        }
    ],
    "sg:phone":"+1 973 575 7999",
    "sg:postcode":"07004",
    "sg:province":"NJ",
    "sg:tags":[
        "accountant",
        "bookkeeping"
    ],
    "wof:name":"Nevoso & Pivirotto PA",
    "wof:placetype":"venue"
},
  "geometry": {"coordinates":[-74.26821099999999,40.891818],"type":"Point"}
}