{
  "type": "Feature",
  "properties": {
    "addr:full":"38 Oak St Ridgewood NJ 07450",
    "addr:housenumber":"38",
    "addr:postcode":"07450",
    "addr:street":"Oak St",
    "iso:country":"US",
    "sg:address":"38 Oak St",
    "sg:city":"Ridgewood",
    "sg:classifiers":[
        {
            "category":"Professional",
            "subcategory":"Management & Consulting",
            "type":"Services"
        }
    ],
    "sg:phone":"+1   ",
    "sg:postcode":"07450",
    "sg:province":"NJ",
    "sg:tags":[
        "business"
    ],
    "wof:name":"Mohr Access LLC",
    "wof:placetype":"venue"
},
  "geometry": {"coordinates":[-74.117893,40.980193],"type":"Point"}
}