{
  "type": "Feature",
  "properties": {
    "iso:country":"US",
    "sg:address":"8 la Tourette Rd",
    "sg:city":"White House Station",
    "sg:classifiers":[
        {
            "category":"Shopping",
            "subcategory":"Gifts & Souvenirs",
            "type":"Retail Goods"
        }
    ],
    "sg:phone":"+1   ",
    "sg:postcode":"08889",
    "sg:province":"NJ",
    "sg:tags":[
        "basket"
    ],
    "wof:name":"Something Special",
    "wof:placetype":"venue"
},
  "geometry": {"coordinates":[-74.399384,40.421271],"type":"Point"}
}