{
  "type": "Feature",
  "properties": {
    "iso:country":"US",
    "sg:address":"106 Watchung Ave",
    "sg:city":"Plainfield",
    "sg:classifiers":[
        {
            "category":"Wholesale",
            "subcategory":"Chemicals & Plastics",
            "type":"Manufacturing & Wholesale Goods"
        }
    ],
    "sg:phone":"+1 908 561 8200",
    "sg:postcode":"07060",
    "sg:province":"NJ",
    "sg:tags":[
        "raw",
        "scrap",
        "paper",
        "metal",
        "export"
    ],
    "wof:name":"Ameecizia",
    "wof:placetype":"venue"
},
  "geometry": {"coordinates":[-74.426328,40.622384],"type":"Point"}
}