{
  "type": "Feature",
  "properties": {
    "iso:country":"US",
    "sg:address":"170 Ocean Ave",
    "sg:city":"Long Branch",
    "sg:classifiers":[
        {
            "category":"Travel",
            "subcategory":"Hotels & Motels",
            "type":"Entertainment"
        }
    ],
    "sg:phone":"+1 732 728 1505",
    "sg:postcode":"07740",
    "sg:province":"NJ",
    "sg:website":"www.oceancourt.net",
    "wof:name":"Ocean Court Motel",
    "wof:placetype":"venue"
},
  "geometry": {"coordinates":[-73.979421,40.297295],"type":"Point"}
}