{
  "type": "Feature",
  "properties": {
    "addr:full":"259 S Zurich Ave Egg Harbor City NJ 08215",
    "addr:housenumber":"259",
    "addr:postcode":"08215",
    "addr:street":"S Zurich Ave",
    "iso:country":"US",
    "sg:address":"259 S Zurich Ave",
    "sg:city":"Egg Harbor City",
    "sg:classifiers":[
        {
            "category":"Insurance",
            "subcategory":"Insurance Agent",
            "type":"Services"
        }
    ],
    "sg:phone":"+1 609 965 9446",
    "sg:postcode":"08215",
    "sg:province":"NJ",
    "sg:tags":[
        "adjuster"
    ],
    "wof:name":"Altman & Altman Inc",
    "wof:placetype":"venue"
},
  "geometry": {"coordinates":[-74.557728,39.48971],"type":"Point"}
}