{
  "type": "Feature",
  "properties": {
    "iso:country":"US",
    "sg:address":"99 Sherman Ave",
    "sg:city":"Newark",
    "sg:classifiers":[
        {
            "category":"Building & Trades",
            "subcategory":"Construction",
            "type":"Services"
        }
    ],
    "sg:phone":"+1 973 624 0400",
    "sg:postcode":"07114",
    "sg:province":"NJ",
    "sg:tags":[
        "general",
        "contractor"
    ],
    "wof:name":"Woodpecker Construction",
    "wof:placetype":"venue"
},
  "geometry": {"coordinates":[-74.185551,40.721988],"type":"Point"}
}