{
  "type": "Feature",
  "properties": {
    "iso:country":"US",
    "sg:address":"554 Davina Ct",
    "sg:city":"Lakewood",
    "sg:classifiers":[
        {
            "category":"Building & Trades",
            "subcategory":"Construction",
            "type":"Services"
        }
    ],
    "sg:phone":"+1 732 886 3661",
    "sg:postcode":"08701",
    "sg:province":"NJ",
    "sg:tags":[
        "resurfacing",
        "laying",
        "refinishing",
        "floor"
    ],
    "wof:name":"First Quality Hardwood Floors",
    "wof:placetype":"venue"
},
  "geometry": {"coordinates":[-74.20160199999999,40.048654],"type":"Point"}
}