{
  "type": "Feature",
  "properties": {
    "iso:country":"US",
    "sg:address":"23 Grant Ave",
    "sg:city":"Fords",
    "sg:classifiers":[
        {
            "category":"Professional",
            "subcategory":"Accounting & Tax Preparation",
            "type":"Services"
        }
    ],
    "sg:phone":"+1   ",
    "sg:postcode":"08863",
    "sg:province":"NJ",
    "wof:name":"Criag L Venokur CPA",
    "wof:placetype":"venue"
},
  "geometry": {"coordinates":[-74.314397,40.533163],"type":"Point"}
}