{
  "type": "Feature",
  "properties": {
    "iso:country":"US",
    "sg:address":"391 Clinton Ave",
    "sg:city":"Wyckoff",
    "sg:classifiers":[
        {
            "category":"Professional",
            "type":"Services"
        }
    ],
    "sg:phone":"+1 201 891 3443",
    "sg:postcode":"07481",
    "sg:province":"NJ",
    "sg:tags":[
        "arts",
        "artist"
    ],
    "wof:name":"West Highland Fine Art",
    "wof:placetype":"venue"
},
  "geometry": {"coordinates":[-74.17163600000001,41.011795],"type":"Point"}
}