{
  "type": "Feature",
  "properties": {
    "addr:full":"3564 Quakerbridge Rd Trenton NJ 08619",
    "addr:housenumber":"3564",
    "addr:postcode":"08619",
    "addr:street":"Quakerbridge Rd",
    "iso:country":"US",
    "sg:address":"3564 Quakerbridge Rd",
    "sg:city":"Trenton",
    "sg:classifiers":[
        {
            "category":"Social Services",
            "subcategory":"Child Care",
            "type":"Services"
        }
    ],
    "sg:phone":"+1 609 588 0880",
    "sg:postcode":"08619",
    "sg:province":"NJ",
    "sg:tags":[
        "day"
    ],
    "sg:website":"www.njpreschool.com",
    "wof:name":"The Goddard School",
    "wof:placetype":"venue"
},
  "geometry": {"coordinates":[-74.675781,40.262443],"type":"Point"}
}