{
  "type": "Feature",
  "properties": {
    "iso:country":"US",
    "sg:address":"91 Bay Ave",
    "sg:city":"Newark",
    "sg:classifiers":[
        {
            "category":"Freight",
            "type":"Transportation"
        }
    ],
    "sg:phone":"+1 973 344 5254",
    "sg:postcode":"07105",
    "sg:province":"NJ",
    "sg:tags":[
        "distance",
        "local",
        "long",
        "trucking"
    ],
    "wof:name":"Roadlink USA Systems Inc",
    "wof:placetype":"venue"
},
  "geometry": {"coordinates":[-74.159137,40.717818],"type":"Point"}
}