{
  "type": "Feature",
  "properties": {
    "addr:full":"2 University Plz Hackensack NJ 07601",
    "addr:housenumber":"2",
    "addr:postcode":"07601",
    "addr:street":"University Plz",
    "iso:country":"US",
    "sg:address":"2 University Plz",
    "sg:city":"Hackensack",
    "sg:classifiers":[
        {
            "category":"Professional",
            "subcategory":"Lawyer & Legal Services",
            "type":"Services"
        }
    ],
    "sg:phone":"+1 201 343 6800",
    "sg:postcode":"07601",
    "sg:province":"NJ",
    "wof:name":"Goodman Michael S ESQ",
    "wof:placetype":"venue"
},
  "geometry": {"coordinates":[-74.03479799999999,40.900101],"type":"Point"}
}