{
  "type": "Feature",
  "properties": {
    "iso:country":"US",
    "sg:address":"40 Hillcrest Rd",
    "sg:city":"Caldwell",
    "sg:classifiers":[
        {
            "category":"Banks & Credit Unions",
            "subcategory":"Financial Services",
            "type":"Services"
        }
    ],
    "sg:phone":"+1   ",
    "sg:postcode":"07006",
    "sg:province":"NJ",
    "sg:tags":[
        "investor"
    ],
    "wof:name":"Mej 37 Investors LLC",
    "wof:placetype":"venue"
},
  "geometry": {"coordinates":[-74.281656,40.848021],"type":"Point"}
}