{
  "type": "Feature",
  "properties": {
    "iso:country":"US",
    "sg:address":"326 Elizabeth Ave",
    "sg:city":"Point Pleasant Beach",
    "sg:classifiers":[
        {
            "category":"Professional",
            "type":"Services"
        }
    ],
    "sg:phone":"+1   ",
    "sg:postcode":"08742",
    "sg:province":"NJ",
    "wof:name":"Program Assistance Center",
    "wof:placetype":"venue"
},
  "geometry": {"coordinates":[-74.044262,40.081807],"type":"Point"}
}