{
  "type": "Feature",
  "properties": {
    "addr:full":"1321 Sleepy Hollow Rd Point Pleasant Beach NJ 08742",
    "addr:housenumber":"1321",
    "addr:postcode":"08742",
    "addr:street":"Sleepy Hollow Rd",
    "iso:country":"US",
    "sg:address":"1321 Sleepy Hollow Rd",
    "sg:city":"Point Pleasant Beach",
    "sg:classifiers":[
        {
            "category":"Building & Trades",
            "subcategory":"Plumbing",
            "type":"Services"
        }
    ],
    "sg:phone":"+1 732 295 1419",
    "sg:postcode":"08742",
    "sg:province":"NJ",
    "sg:tags":[
        "cooling",
        "heating"
    ],
    "wof:name":"Scarpello Heating & Elec Svcs",
    "wof:placetype":"venue"
},
  "geometry": {"coordinates":[-74.082686,40.07343],"type":"Point"}
}