{
  "type": "Feature",
  "properties": {
    "addr:full":"110 Westbury Ct Marlton NJ 08053",
    "addr:housenumber":"110",
    "addr:postcode":"08053",
    "addr:street":"Westbury Ct",
    "iso:country":"US",
    "sg:address":"110 Westbury Ct",
    "sg:city":"Marlton",
    "sg:classifiers":[
        {
            "category":"Real Estate",
            "subcategory":"Real Estate Agent",
            "type":"Services"
        }
    ],
    "sg:phone":"+1   ",
    "sg:postcode":"08053",
    "sg:province":"NJ",
    "wof:name":"Hammer Co",
    "wof:placetype":"venue"
},
  "geometry": {"coordinates":[-74.925134,39.874955],"type":"Point"}
}