{
  "type": "Feature",
  "properties": {
    "addr:full":"36 Dell Rd Stanhope NJ 07874",
    "addr:housenumber":"36",
    "addr:postcode":"07874",
    "addr:street":"Dell Rd",
    "iso:country":"US",
    "sg:address":"36 Dell Rd",
    "sg:city":"Stanhope",
    "sg:classifiers":[
        {
            "category":"Building & Trades",
            "subcategory":"Cleaning & Sanitation",
            "type":"Services"
        }
    ],
    "sg:phone":"+1   ",
    "sg:postcode":"07874",
    "sg:province":"NJ",
    "sg:tags":[
        "maintenance"
    ],
    "wof:name":"Tiger Cleaning Service",
    "wof:placetype":"venue"
},
  "geometry": {"coordinates":[-74.710741,40.91478],"type":"Point"}
}