{
  "type": "Feature",
  "properties": {
    "iso:country":"US",
    "sg:address":"483 Jersey Ave",
    "sg:city":"Jersey City",
    "sg:classifiers":[
        {
            "category":"Wholesale",
            "subcategory":"Apparel",
            "type":"Manufacturing & Wholesale Goods"
        }
    ],
    "sg:phone":"+1 201 324 0936",
    "sg:postcode":"07302",
    "sg:province":"NJ",
    "sg:tags":[
        "clothing"
    ],
    "wof:name":"Accent By Janet",
    "wof:placetype":"venue"
},
  "geometry": {"coordinates":[-74.047748,40.718741],"type":"Point"}
}