{
  "type": "Feature",
  "properties": {
    "iso:country":"US",
    "sg:address":"60 Prince St",
    "sg:city":"Elizabeth",
    "sg:classifiers":[
        {
            "category":"Organizations",
            "subcategory":"Religious Organization",
            "type":"Services"
        }
    ],
    "sg:phone":"+1 908 353 8640",
    "sg:postcode":"07208",
    "sg:province":"NJ",
    "wof:name":"Marriage Encounter",
    "wof:placetype":"venue"
},
  "geometry": {"coordinates":[-74.218598,40.671449],"type":"Point"}
}