{
  "type": "Feature",
  "properties": {
    "iso:country":"US",
    "sg:address":"7 Larsen Dr",
    "sg:city":"Succasunna",
    "sg:classifiers":[
        {
            "category":"Professional",
            "subcategory":"Computer Services",
            "type":"Services"
        }
    ],
    "sg:phone":"+1   ",
    "sg:postcode":"07876",
    "sg:province":"NJ",
    "sg:tags":[
        "related"
    ],
    "wof:name":"Pazer Consulting Service",
    "wof:placetype":"venue"
},
  "geometry": {"coordinates":[-74.65329199999999,40.856567],"type":"Point"}
}