{
  "type": "Feature",
  "properties": {
    "iso:country":"US",
    "sg:address":"633 Franklin Ave",
    "sg:city":"Nutley",
    "sg:classifiers":[
        {
            "category":"Building & Trades",
            "subcategory":"Cleaning & Sanitation",
            "type":"Services"
        }
    ],
    "sg:phone":"+1 973 680 8906",
    "sg:postcode":"07110",
    "sg:province":"NJ",
    "sg:tags":[
        "snow",
        "removal"
    ],
    "sg:website":"www.springgarden.com",
    "wof:name":"Spring Garden Landscape Design",
    "wof:placetype":"venue"
},
  "geometry": {"coordinates":[-74.151591,40.826473],"type":"Point"}
}