{
  "type": "Feature",
  "properties": {
    "iso:country":"US",
    "sg:address":"193 S Creek Dr",
    "sg:city":"West Creek",
    "sg:classifiers":[
        {
            "category":"Professional",
            "subcategory":"Business Services",
            "type":"Services"
        }
    ],
    "sg:phone":"+1   ",
    "sg:postcode":"08092",
    "sg:province":"NJ",
    "wof:name":"Rich Interiors LLC",
    "wof:placetype":"venue"
},
  "geometry": {"coordinates":[-74.283387,39.621591],"type":"Point"}
}