{
  "type": "Feature",
  "properties": {
    "addr:full":"255 State Rte 31 Washington NJ 07882",
    "addr:housenumber":"255",
    "addr:postcode":"07882",
    "addr:street":"State Rte 31",
    "iso:country":"US",
    "sg:address":"255 State Rte 31",
    "sg:city":"Washington",
    "sg:classifiers":[
        {
            "category":"Retail",
            "subcategory":"Auto Repair",
            "type":"Services"
        }
    ],
    "sg:phone":"+1   ",
    "sg:postcode":"07882",
    "sg:province":"NJ",
    "sg:tags":[
        "general"
    ],
    "wof:name":"Sams Auto Service Inc",
    "wof:placetype":"venue"
},
  "geometry": {"coordinates":[-74.980012,40.770228],"type":"Point"}
}