{
  "type": "Feature",
  "properties": {
    "iso:country":"US",
    "sg:address":"105 Eisenhower Pkwy",
    "sg:city":"Roseland",
    "sg:classifiers":[
        {
            "category":"Fast Food",
            "type":"Food & Drink"
        }
    ],
    "sg:phone":"+1 973 403 0390",
    "sg:postcode":"07068",
    "sg:province":"NJ",
    "wof:name":"McDonald's Corp",
    "wof:placetype":"venue"
},
  "geometry": {"coordinates":[-74.31687100000001,40.830494],"type":"Point"}
}