{
  "type": "Feature",
  "properties": {
    "iso:country":"US",
    "sg:address":"8900 New Jersey Ave",
    "sg:city":"Wildwood",
    "sg:classifiers":[
        {
            "category":"Utilities",
            "subcategory":"Mobile Phone",
            "type":"Services"
        }
    ],
    "sg:phone":"+1 609 522 6669",
    "sg:postcode":"08260",
    "sg:province":"NJ",
    "sg:tags":[
        "communication",
        "radiotelephone"
    ],
    "wof:name":"Wildwood Police Officers Assn",
    "wof:placetype":"venue"
},
  "geometry": {"coordinates":[-74.849859,38.965604],"type":"Point"}
}