{
  "type": "Feature",
  "properties": {
    "addr:full":"7 Malcolm Rd Mahwah NJ 07430",
    "addr:housenumber":"7",
    "addr:postcode":"07430",
    "addr:street":"Malcolm Rd",
    "iso:country":"US",
    "sg:address":"7 Malcolm Rd",
    "sg:city":"Mahwah",
    "sg:classifiers":[
        {
            "category":"Professional",
            "subcategory":"Business Services",
            "type":"Services"
        }
    ],
    "sg:phone":"+1   ",
    "sg:postcode":"07430",
    "sg:province":"NJ",
    "wof:name":"Howcom Technologies LLC",
    "wof:placetype":"venue"
},
  "geometry": {"coordinates":[-74.140525,41.094319],"type":"Point"}
}