{
  "type": "Feature",
  "properties": {
    "iso:country":"US",
    "sg:address":"25 Kinnelon Rd",
    "sg:city":"Kinnelon",
    "sg:classifiers":[
        {
            "category":"Retail",
            "subcategory":"Laundry & Dry Cleaning",
            "type":"Services"
        }
    ],
    "sg:phone":"+1 973 492 0827",
    "sg:postcode":"07405",
    "sg:province":"NJ",
    "sg:tags":[
        "cleaner"
    ],
    "wof:name":"Kinnelon Cleaners",
    "wof:placetype":"venue"
},
  "geometry": {"coordinates":[-74.361801,41.0037],"type":"Point"}
}