{
  "type": "Feature",
  "properties": {
    "addr:full":"123 S Main St Marlboro NJ 07746",
    "addr:housenumber":"123",
    "addr:postcode":"07746",
    "addr:street":"S Main St",
    "iso:country":"US",
    "sg:address":"123 S Main St",
    "sg:city":"Marlboro",
    "sg:classifiers":[
        {
            "category":"Social Services",
            "subcategory":"Child Care",
            "type":"Services"
        }
    ],
    "sg:phone":"+1 732 431 0718",
    "sg:postcode":"07746",
    "sg:province":"NJ",
    "sg:tags":[
        "kindergarten",
        "academic",
        "school",
        "day"
    ],
    "wof:name":"Kinderland Learning & Day Care",
    "wof:placetype":"venue"
},
  "geometry": {"coordinates":[-74.256169,40.295641],"type":"Point"}
}