{
  "type": "Feature",
  "properties": {
    "addr:full":"103 Montgomery St Jersey City NJ 07302",
    "addr:housenumber":"103",
    "addr:postcode":"07302",
    "addr:street":"Montgomery St",
    "iso:country":"US",
    "sg:address":"103 Montgomery St",
    "sg:city":"Jersey City",
    "sg:classifiers":[
        {
            "category":"Building & Trades",
            "subcategory":"Locksmith",
            "type":"Services"
        }
    ],
    "sg:phone":"+1 877 862 4783",
    "sg:postcode":"07302",
    "sg:province":"NJ",
    "sg:tags":[
        "key"
    ],
    "wof:name":"1 24 Hour Emergency Locksmith",
    "wof:placetype":"venue"
},
  "geometry": {"coordinates":[-74.03817600000001,40.716818],"type":"Point"}
}