{
  "type": "Feature",
  "properties": {
    "iso:country":"US",
    "sg:address":"144 Wegman Pkwy",
    "sg:city":"Jersey City",
    "sg:classifiers":[
        {
            "category":"Building & Trades",
            "subcategory":"Cleaning & Sanitation",
            "type":"Services"
        }
    ],
    "sg:phone":"+1   ",
    "sg:postcode":"07305",
    "sg:province":"NJ",
    "sg:tags":[
        "maintenance"
    ],
    "wof:name":"B Anderson Maintenance Corp",
    "wof:placetype":"venue"
},
  "geometry": {"coordinates":[-74.084,40.705624],"type":"Point"}
}