{
  "type": "Feature",
  "properties": {
    "iso:country":"US",
    "sg:address":"10 Wilmot St",
    "sg:city":"Morristown",
    "sg:classifiers":[
        {
            "category":"Manufacturing",
            "subcategory":"Printing",
            "type":"Manufacturing & Wholesale Goods"
        }
    ],
    "sg:phone":"+1 973 539 7910",
    "sg:postcode":"07960",
    "sg:province":"NJ",
    "sg:tags":[
        "newspaper"
    ],
    "wof:name":"Star Ledger",
    "wof:placetype":"venue"
},
  "geometry": {"coordinates":[-74.47855199999999,40.796068],"type":"Point"}
}