{
  "type": "Feature",
  "properties": {
    "addr:full":"74 W Main St Bogota NJ 07603",
    "addr:housenumber":"74",
    "addr:postcode":"07603",
    "addr:street":"W Main St",
    "iso:country":"US",
    "sg:address":"74 W Main St",
    "sg:city":"Bogota",
    "sg:classifiers":[
        {
            "category":"Food & Beverages",
            "subcategory":"Liquor & Beverages",
            "type":"Retail Goods"
        }
    ],
    "sg:phone":"+1 201 646 0407",
    "sg:postcode":"07603",
    "sg:province":"NJ",
    "sg:tags":[
        "beer",
        "wine",
        "spirit",
        "alcoholic"
    ],
    "wof:name":"Santa Fe Wines & Liquors",
    "wof:placetype":"venue"
},
  "geometry": {"coordinates":[-74.03040300000001,40.8783],"type":"Point"}
}