{
  "type": "Feature",
  "properties": {
    "addr:full":"751 Broadway Newark NJ 07104",
    "addr:housenumber":"751",
    "addr:postcode":"07104",
    "addr:street":"Broadway",
    "iso:country":"US",
    "sg:address":"751 Broadway",
    "sg:city":"Newark",
    "sg:classifiers":[
        {
            "category":"Shopping",
            "subcategory":"Pharmacy",
            "type":"Retail Goods"
        }
    ],
    "sg:phone":"+1 973 481 2400",
    "sg:postcode":"07104",
    "sg:province":"NJ",
    "sg:tags":[
        "drugstore"
    ],
    "wof:name":"Newark Community Pharmacy",
    "wof:placetype":"venue"
},
  "geometry": {"coordinates":[-74.158537,40.77558],"type":"Point"}
}