{
  "type": "Feature",
  "properties": {
    "addr:full":"65 W Greenbrook Rd Caldwell NJ 07006",
    "addr:housenumber":"65",
    "addr:postcode":"07006",
    "addr:street":"W Greenbrook Rd",
    "iso:country":"US",
    "sg:address":"65 W Greenbrook Rd",
    "sg:city":"Caldwell",
    "sg:classifiers":[
        {
            "category":"Education",
            "subcategory":"School",
            "type":"Public Place"
        }
    ],
    "sg:phone":"+1 973 228 1200",
    "sg:postcode":"07006",
    "sg:province":"NJ",
    "sg:tags":[
        "high",
        "middle",
        "elementary"
    ],
    "wof:name":"West Essex Regional School District",
    "wof:placetype":"venue"
},
  "geometry": {"coordinates":[-74.274519,40.872005],"type":"Point"}
}