{
  "type": "Feature",
  "properties": {
    "iso:country":"US",
    "sg:address":"134 Wild Oaks Dr",
    "sg:city":"Salem",
    "sg:classifiers":[
        {
            "category":"Shopping",
            "type":"Retail Goods"
        }
    ],
    "sg:phone":"+1   ",
    "sg:postcode":"08079",
    "sg:province":"NJ",
    "sg:tags":[
        "merchandise"
    ],
    "wof:name":"Scentimental Candles",
    "wof:placetype":"venue"
},
  "geometry": {"coordinates":[-75.42150100000001,39.526375],"type":"Point"}
}