{
  "type": "Feature",
  "properties": {
    "iso:country":"US",
    "sg:address":"15 Amanda Ln",
    "sg:city":"Howell",
    "sg:classifiers":[
        {
            "category":"Wholesale",
            "subcategory":"Medical Equipment & Supplies",
            "type":"Manufacturing & Wholesale Goods"
        }
    ],
    "sg:phone":"+1 732 961 1620",
    "sg:postcode":"07731",
    "sg:province":"NJ",
    "sg:tags":[
        "hospital"
    ],
    "wof:name":"Quinton Instrument Co",
    "wof:placetype":"venue"
},
  "geometry": {"coordinates":[-74.197506,40.142664],"type":"Point"}
}