{
  "type": "Feature",
  "properties": {
    "addr:full":"4934 Westfield Ave Pennsauken NJ 08110",
    "addr:housenumber":"4934",
    "addr:postcode":"08110",
    "addr:street":"Westfield Ave",
    "iso:country":"US",
    "sg:address":"4934 Westfield Ave",
    "sg:city":"Pennsauken",
    "sg:classifiers":[
        {
            "category":"Banks & Credit Unions",
            "subcategory":"Bank",
            "type":"Services"
        }
    ],
    "sg:phone":"+1 856 661 3101",
    "sg:postcode":"08110",
    "sg:province":"NJ",
    "sg:website":"www.pnc.com",
    "wof:name":"Pnc Bank",
    "wof:placetype":"venue"
},
  "geometry": {"coordinates":[-75.064902,39.958725],"type":"Point"}
}