{
  "type": "Feature",
  "properties": {
    "iso:country":"US",
    "sg:address":"985 Coles Mill Rd",
    "sg:city":"Williamstown",
    "sg:classifiers":[
        {
            "category":"Professional",
            "subcategory":"Business Services",
            "type":"Services"
        }
    ],
    "sg:phone":"+1   ",
    "sg:postcode":"08094",
    "sg:province":"NJ",
    "wof:name":"Academy Holding Group Inc",
    "wof:placetype":"venue"
},
  "geometry": {"coordinates":[-74.954857,39.619218],"type":"Point"}
}