{
  "type": "Feature",
  "properties": {
    "iso:country":"US",
    "sg:address":"561 W Crystal Lake Ave",
    "sg:city":"Haddonfield",
    "sg:classifiers":[
        {
            "category":"Recreation",
            "type":"Entertainment"
        }
    ],
    "sg:phone":"+1 856 795 6030",
    "sg:postcode":"08033",
    "sg:province":"NJ",
    "sg:tags":[
        "amusement"
    ],
    "wof:name":"Drama Kids Of South Jersey",
    "wof:placetype":"venue"
},
  "geometry": {"coordinates":[-75.052696,39.895319],"type":"Point"}
}