{
  "type": "Feature",
  "properties": {
    "addr:full":"3 Theatre Center Sparta NJ 07871",
    "addr:housenumber":"3",
    "addr:postcode":"07871",
    "addr:street":"Theatre Center",
    "iso:country":"US",
    "sg:address":"3 Theatre Center",
    "sg:city":"Sparta",
    "sg:classifiers":[
        {
            "category":"Personal",
            "subcategory":"Beauty Salon",
            "type":"Services"
        }
    ],
    "sg:phone":"+1 973 729 2662",
    "sg:postcode":"07871",
    "sg:province":"NJ",
    "sg:tags":[
        "shop"
    ],
    "wof:name":"Sparta Nail Salon",
    "wof:placetype":"venue"
},
  "geometry": {"coordinates":[-74.63502200000001,41.029979],"type":"Point"}
}