{
  "type": "Feature",
  "properties": {
    "addr:full":"165 E Prospect St South River NJ 08882",
    "addr:housenumber":"165",
    "addr:postcode":"08882",
    "addr:street":"E Prospect St",
    "iso:country":"US",
    "sg:address":"165 E Prospect St",
    "sg:city":"South River",
    "sg:classifiers":[
        {
            "category":"Retail",
            "subcategory":"Auto Repair",
            "type":"Services"
        }
    ],
    "sg:phone":"+1 732 698 9400",
    "sg:postcode":"08882",
    "sg:province":"NJ",
    "sg:tags":[
        "repairing",
        "automobile"
    ],
    "wof:name":"Prospect Auto Svc",
    "wof:placetype":"venue"
},
  "geometry": {"coordinates":[-74.39051499999999,40.455557],"type":"Point"}
}