{
  "type": "Feature",
  "properties": {
    "addr:full":"29 Franklin St Bloomfield NJ 07003",
    "addr:housenumber":"29",
    "addr:postcode":"07003",
    "addr:street":"Franklin St",
    "iso:country":"US",
    "sg:address":"29 Franklin St",
    "sg:city":"Bloomfield",
    "sg:classifiers":[
        {
            "category":"Building & Trades",
            "subcategory":"Plumbing",
            "type":"Services"
        }
    ],
    "sg:phone":"+1 973 429 1204",
    "sg:postcode":"07003",
    "sg:province":"NJ",
    "sg:tags":[
        "conditioning",
        "air",
        "system",
        "contractor"
    ],
    "wof:name":"Cool Effects Inc",
    "wof:placetype":"venue"
},
  "geometry": {"coordinates":[-74.18402399999999,40.784295],"type":"Point"}
}