{
  "type": "Feature",
  "properties": {
    "addr:full":"322 48th St Union City NJ 07087",
    "addr:housenumber":"322",
    "addr:postcode":"07087",
    "addr:street":"48Th St",
    "iso:country":"US",
    "sg:address":"322 48th St",
    "sg:city":"Union City",
    "sg:classifiers":[
        {
            "category":"Professional",
            "subcategory":"Lawyer & Legal Services",
            "type":"Services"
        }
    ],
    "sg:phone":"+1 201 867 6678",
    "sg:postcode":"07087",
    "sg:province":"NJ",
    "wof:name":"John C Spadora",
    "wof:placetype":"venue"
},
  "geometry": {"coordinates":[-74.02069899999999,40.7813],"type":"Point"}
}