{
  "type": "Feature",
  "properties": {
    "iso:country":"US",
    "sg:address":"14 Kerr Rd",
    "sg:city":"Newton",
    "sg:classifiers":[
        {
            "category":"Professional",
            "subcategory":"Management & Consulting",
            "type":"Services"
        }
    ],
    "sg:phone":"+1   ",
    "sg:postcode":"07825",
    "sg:province":"NJ",
    "wof:name":"Kory Consulting",
    "wof:placetype":"venue"
},
  "geometry": {"coordinates":[-74.872805,40.992839],"type":"Point"}
}