{
  "type": "Feature",
  "properties": {
    "iso:country":"US",
    "sg:address":"1086 S Orange Ave",
    "sg:city":"Newark",
    "sg:classifiers":[
        {
            "category":"Restaurant",
            "type":"Food & Drink"
        }
    ],
    "sg:phone":"+1 973 374 8311",
    "sg:postcode":"07106",
    "sg:province":"NJ",
    "sg:tags":[
        "eating"
    ],
    "wof:name":"Kiwi Restaurant",
    "wof:placetype":"venue"
},
  "geometry": {"coordinates":[-74.233102,40.745748],"type":"Point"}
}