{
  "type": "Feature",
  "properties": {
    "iso:country":"US",
    "sg:address":"123 Almond Rd",
    "sg:city":"Freehold",
    "sg:classifiers":[
        {
            "category":"Professional",
            "type":"Services"
        }
    ],
    "sg:phone":"+1   ",
    "sg:postcode":"07728",
    "sg:province":"NJ",
    "wof:name":"William Katz",
    "wof:placetype":"venue"
},
  "geometry": {"coordinates":[-74.31606600000001,40.246445],"type":"Point"}
}