{
  "type": "Feature",
  "properties": {
    "addr:full":"304 W Revere Ave Northfield NJ 08225",
    "addr:housenumber":"304",
    "addr:postcode":"08225",
    "addr:street":"W Revere Ave",
    "iso:country":"US",
    "sg:address":"304 W Revere Ave",
    "sg:city":"Northfield",
    "sg:classifiers":[
        {
            "category":"Building & Trades",
            "subcategory":"Construction",
            "type":"Services"
        }
    ],
    "sg:phone":"+1 609 645 0833",
    "sg:postcode":"08225",
    "sg:province":"NJ",
    "sg:tags":[
        "hanging",
        "contractor"
    ],
    "wof:name":"Sadowl Painting",
    "wof:placetype":"venue"
},
  "geometry": {"coordinates":[-74.565309,39.36206],"type":"Point"}
}