{
  "type": "Feature",
  "properties": {
    "iso:country":"US",
    "sg:address":"151 E 33rd St",
    "sg:city":"Paterson",
    "sg:classifiers":[
        {
            "category":"Education",
            "subcategory":"School",
            "type":"Public Place"
        }
    ],
    "sg:phone":"+1 973 321 0580",
    "sg:postcode":"07514",
    "sg:province":"NJ",
    "sg:tags":[
        "high",
        "middle",
        "elementary"
    ],
    "wof:name":"Build Academey",
    "wof:placetype":"venue"
},
  "geometry": {"coordinates":[-74.14160200000001,40.918598],"type":"Point"}
}