{
  "type": "Feature",
  "properties": {
    "iso:country":"US",
    "sg:address":"929 Kings Hwy S",
    "sg:city":"Cherry Hill",
    "sg:classifiers":[
        {
            "category":"Professional",
            "subcategory":"Employment Agencies",
            "type":"Services"
        }
    ],
    "sg:phone":"+1 856 779 9030",
    "sg:postcode":"08034",
    "sg:province":"NJ",
    "sg:tags":[
        "opportunity"
    ],
    "wof:name":"S-H-S Intl Of Cherry Hill",
    "wof:placetype":"venue"
},
  "geometry": {"coordinates":[-75.019747,39.905347],"type":"Point"}
}