{
  "type": "Feature",
  "properties": {
    "addr:full":"37 N Trenton Ave Atlantic City NJ 08401",
    "addr:housenumber":"37",
    "addr:postcode":"08401",
    "addr:street":"N Trenton Ave",
    "iso:country":"US",
    "sg:address":"37 N Trenton Ave",
    "sg:city":"Atlantic City",
    "sg:classifiers":[
        {
            "category":"Retail",
            "subcategory":"Auto Repair",
            "type":"Services"
        }
    ],
    "sg:phone":"+1 609 344 4746",
    "sg:postcode":"08401",
    "sg:province":"NJ",
    "sg:tags":[
        "repairing",
        "automobile",
        "general"
    ],
    "wof:name":"Bill's Auto Clinic",
    "wof:placetype":"venue"
},
  "geometry": {"coordinates":[-74.456439,39.351512],"type":"Point"}
}