{
  "type": "Feature",
  "properties": {
    "iso:country":"US",
    "sg:address":"200 Grove Rd Suite C",
    "sg:city":"Paulsboro",
    "sg:classifiers":[
        {
            "category":"Professional",
            "subcategory":"Advertising",
            "type":"Services"
        },
        {
            "category":"Professional",
            "subcategory":"Art Services",
            "type":"Services"
        },
        {
            "category":"Manufacturing",
            "subcategory":"Signs",
            "type":"Manufacturing & Wholesale Goods"
        }
    ],
    "sg:phone":"+1 856 853 0200",
    "sg:postcode":"08066",
    "sg:province":"NJ",
    "sg:tags":[
        "graphic",
        "specialty",
        "designer"
    ],
    "wof:name":"Sunrise Signs",
    "wof:placetype":"venue"
},
  "geometry": {"coordinates":[-75.194366,39.837101],"type":"Point"}
}