{
  "type": "Feature",
  "properties": {
    "iso:country":"US",
    "sg:address":"900 Madison Ave",
    "sg:city":"Paterson",
    "sg:classifiers":[
        {
            "category":"Organizations",
            "subcategory":"Religious Organization",
            "type":"Services"
        }
    ],
    "sg:phone":"+1 973 279 5800",
    "sg:postcode":"07501",
    "sg:province":"NJ",
    "sg:tags":[
        "church"
    ],
    "wof:name":"Madison Avenue Baptist Church",
    "wof:placetype":"venue"
},
  "geometry": {"coordinates":[-74.156459,40.910098],"type":"Point"}
}