{
  "type": "Feature",
  "properties": {
    "iso:country":"US",
    "sg:address":"25 Evans Rd",
    "sg:city":"Bloomfield",
    "sg:classifiers":[
        {
            "category":"Professional",
            "type":"Services"
        }
    ],
    "sg:phone":"+1   ",
    "sg:postcode":"07003",
    "sg:province":"NJ",
    "wof:name":"P E Florian",
    "wof:placetype":"venue"
},
  "geometry": {"coordinates":[-74.16674500000001,40.839645],"type":"Point"}
}