{
  "type": "Feature",
  "properties": {
    "addr:full":"22 E Quackenbush Ave Dumont NJ 07628",
    "addr:housenumber":"22",
    "addr:postcode":"07628",
    "addr:street":"E Quackenbush Ave",
    "iso:country":"US",
    "sg:address":"22 E Quackenbush Ave",
    "sg:city":"Dumont",
    "sg:classifiers":[
        {
            "category":"Professional",
            "subcategory":"Research",
            "type":"Services"
        }
    ],
    "sg:phone":"+1 201 384 1080",
    "sg:postcode":"07628",
    "sg:province":"NJ",
    "sg:tags":[
        "nonphysical",
        "commercial"
    ],
    "wof:name":"Baines Corp",
    "wof:placetype":"venue"
},
  "geometry": {"coordinates":[-73.99350099999999,40.938587],"type":"Point"}
}