{
  "type": "Feature",
  "properties": {
    "iso:country":"US",
    "sg:address":"1431 Boardwalk",
    "sg:city":"Atlantic City",
    "sg:classifiers":[
        {
            "category":"Personal",
            "type":"Services"
        }
    ],
    "sg:phone":"+1 609 348 0899",
    "sg:postcode":"08401",
    "sg:province":"NJ",
    "sg:tags":[
        "therapist",
        "massage"
    ],
    "wof:name":"Massage Heaven",
    "wof:placetype":"venue"
},
  "geometry": {"coordinates":[-74.424977,39.357074],"type":"Point"}
}