{
  "type": "Feature",
  "properties": {
    "addr:full":"111 1st St Jersey City NJ 07302",
    "addr:housenumber":"111",
    "addr:postcode":"07302",
    "addr:street":"1St St",
    "iso:country":"US",
    "sg:address":"111 1st St",
    "sg:city":"Jersey City",
    "sg:classifiers":[
        {
            "category":"Building & Trades",
            "subcategory":"Construction",
            "type":"Services"
        }
    ],
    "sg:phone":"+1 201 222 8595",
    "sg:postcode":"07302",
    "sg:province":"NJ",
    "sg:tags":[
        "carpentry",
        "contractor"
    ],
    "wof:name":"Woodworks",
    "wof:placetype":"venue"
},
  "geometry": {"coordinates":[-74.037969,40.721197],"type":"Point"}
}