{
  "type": "Feature",
  "properties": {
    "iso:country":"US",
    "sg:address":"368 Medford Lakes Rd",
    "sg:city":"Tabernacle",
    "sg:classifiers":[
        {
            "category":"Building & Trades",
            "subcategory":"Construction",
            "type":"Services"
        }
    ],
    "sg:phone":"+1 609 268 8500",
    "sg:postcode":"08088",
    "sg:province":"NJ",
    "sg:tags":[
        "resurfacing",
        "laying",
        "refinishing",
        "floor"
    ],
    "wof:name":"Ritter Flooring Inc",
    "wof:placetype":"venue"
},
  "geometry": {"coordinates":[-74.73711,39.847739],"type":"Point"}
}