{
  "type": "Feature",
  "properties": {
    "addr:full":"623 N Wood Ave Linden NJ 07036",
    "addr:housenumber":"623",
    "addr:postcode":"07036",
    "addr:street":"N Wood Ave",
    "iso:country":"US",
    "sg:address":"623 N Wood Ave",
    "sg:city":"Linden",
    "sg:phone":"+1 800 925 6499",
    "sg:postcode":"07036",
    "sg:province":"NJ",
    "wof:name":"Mix 'em Up Bartending School Inc /La Toll Free",
    "wof:placetype":"venue"
},
  "geometry": {"coordinates":[-74.258917,40.633928],"type":"Point"}
}