{
  "type": "Feature",
  "properties": {
    "iso:country":"US",
    "sg:address":"3318 Boardwalk",
    "sg:city":"Wildwood",
    "sg:classifiers":[
        {
            "category":"Restaurant",
            "type":"Food & Drink"
        }
    ],
    "sg:phone":"+1 609 522 4654",
    "sg:postcode":"08260",
    "sg:province":"NJ",
    "sg:tags":[
        "parlor",
        "ice",
        "cream"
    ],
    "wof:name":"Fire & Ice",
    "wof:placetype":"venue"
},
  "geometry": {"coordinates":[-74.809274,38.987802],"type":"Point"}
}