{
  "type": "Feature",
  "properties": {
    "addr:full":"723 W Adams Ave Pleasantville NJ 08232",
    "addr:housenumber":"723",
    "addr:postcode":"08232",
    "addr:street":"W Adams Ave",
    "iso:country":"US",
    "sg:address":"723 W Adams Ave",
    "sg:city":"Pleasantville",
    "sg:classifiers":[
        {
            "category":"Social Services",
            "subcategory":"Child Care",
            "type":"Services"
        }
    ],
    "sg:phone":"+1 609 641 2926",
    "sg:postcode":"08232",
    "sg:province":"NJ",
    "sg:tags":[
        "day"
    ],
    "wof:name":"Wilson Child Care Center II",
    "wof:placetype":"venue"
},
  "geometry": {"coordinates":[-74.531656,39.400041],"type":"Point"}
}