{
  "type": "Feature",
  "properties": {
    "iso:country":"US",
    "sg:address":"304 Ryders Ln",
    "sg:city":"Milltown",
    "sg:classifiers":[
        {
            "category":"Restaurant",
            "type":"Food & Drink"
        }
    ],
    "sg:phone":"+1   ",
    "sg:postcode":"08850",
    "sg:province":"NJ",
    "sg:tags":[
        "eating"
    ],
    "wof:name":"China One Restaurant",
    "wof:placetype":"venue"
},
  "geometry": {"coordinates":[-74.424528,40.45436],"type":"Point"}
}