{
  "type": "Feature",
  "properties": {
    "iso:country":"US",
    "sg:address":"31 Equestrian Dr",
    "sg:city":"Burlington",
    "sg:classifiers":[
        {
            "category":"Building & Trades",
            "subcategory":"Landscaping Services",
            "type":"Services"
        }
    ],
    "sg:phone":"+1 609 387 3293",
    "sg:postcode":"08016",
    "sg:province":"NJ",
    "sg:tags":[
        "landscape"
    ],
    "wof:name":"Green W/Envy Lndscpng &LWn Cre",
    "wof:placetype":"venue"
},
  "geometry": {"coordinates":[-74.815273,40.086995],"type":"Point"}
}