{
  "type": "Feature",
  "properties": {
    "addr:full":"592 Benson St Camden NJ 08103",
    "addr:housenumber":"592",
    "addr:postcode":"08103",
    "addr:street":"Benson St",
    "iso:country":"US",
    "sg:address":"592 Benson St",
    "sg:city":"Camden",
    "sg:classifiers":[
        {
            "category":"Health Services",
            "subcategory":"Doctor",
            "type":"Services"
        }
    ],
    "sg:phone":"+1 856 963 1551",
    "sg:postcode":"08103",
    "sg:province":"NJ",
    "wof:name":"Edelman Robert W DO",
    "wof:placetype":"venue"
},
  "geometry": {"coordinates":[-75.11773700000001,39.940674],"type":"Point"}
}