{
  "type": "Feature",
  "properties": {
    "addr:full":"6 Oak Tree Ln Ocean NJ 07712",
    "addr:housenumber":"6",
    "addr:postcode":"07712",
    "addr:street":"Oak Tree Ln",
    "iso:country":"US",
    "sg:address":"6 Oak Tree Ln",
    "sg:city":"Ocean",
    "sg:classifiers":[
        {
            "category":"Health Services",
            "subcategory":"Medical Lab",
            "type":"Services"
        }
    ],
    "sg:phone":"+1 732 695 0340",
    "sg:postcode":"07712",
    "sg:province":"NJ",
    "sg:tags":[
        "laboratory"
    ],
    "wof:name":"Molecular Diagnostic Lab Inc",
    "wof:placetype":"venue"
},
  "geometry": {"coordinates":[-74.049937,40.248479],"type":"Point"}
}