{
  "type": "Feature",
  "properties": {
    "iso:country":"US",
    "sg:address":"225 Old New Brunswick Rd",
    "sg:city":"Piscataway",
    "sg:classifiers":[
        {
            "category":"Professional",
            "subcategory":"Computer Services",
            "type":"Services"
        }
    ],
    "sg:phone":"+1   ",
    "sg:postcode":"08854",
    "sg:province":"NJ",
    "sg:tags":[
        "processing"
    ],
    "wof:name":"Ix Telecom Services",
    "wof:placetype":"venue"
},
  "geometry": {"coordinates":[-74.471183,40.55629],"type":"Point"}
}