{
  "type": "Feature",
  "properties": {
    "iso:country":"US",
    "sg:address":"19 Progress Pl",
    "sg:city":"Voorhees",
    "sg:classifiers":[
        {
            "category":"Building & Trades",
            "subcategory":"Landscaping Services",
            "type":"Services"
        }
    ],
    "sg:phone":"+1 856 435 8776",
    "sg:postcode":"08043",
    "sg:province":"NJ",
    "wof:name":"Commercial Grounds Maintenance",
    "wof:placetype":"venue"
},
  "geometry": {"coordinates":[-74.940298,39.86845],"type":"Point"}
}