{
  "type": "Feature",
  "properties": {
    "iso:country":"US",
    "sg:address":"97 E Blackwell St",
    "sg:city":"Dover",
    "sg:classifiers":[
        {
            "category":"Bars & Pubs",
            "type":"Food & Drink"
        }
    ],
    "sg:phone":"+1 973 366 6593",
    "sg:postcode":"07801",
    "sg:province":"NJ",
    "sg:tags":[
        "tavern"
    ],
    "wof:name":"Unique Bar & Grill",
    "wof:placetype":"venue"
},
  "geometry": {"coordinates":[-74.554506,40.884594],"type":"Point"}
}