{
  "type": "Feature",
  "properties": {
    "iso:country":"US",
    "sg:address":"2540 US Highway 22 E",
    "sg:city":"Union",
    "sg:classifiers":[
        {
            "category":"Home & Garden",
            "subcategory":"Furniture",
            "type":"Retail Goods"
        }
    ],
    "sg:phone":"+1 908 810 9800",
    "sg:postcode":"07083",
    "sg:province":"NJ",
    "sg:tags":[
        "store"
    ],
    "wof:name":"American Comfort Dinettes",
    "wof:placetype":"venue"
},
  "geometry": {"coordinates":[-74.301598,40.689201],"type":"Point"}
}