{
  "type": "Feature",
  "properties": {
    "iso:country":"US",
    "sg:address":"31 Chamberlain Ave",
    "sg:city":"Little Ferry",
    "sg:classifiers":[
        {
            "category":"Organizations",
            "subcategory":"Religious Organization",
            "type":"Services"
        }
    ],
    "sg:phone":"+1 201 641 2988",
    "sg:postcode":"07643",
    "sg:province":"NJ",
    "sg:tags":[
        "church"
    ],
    "wof:name":"St Margaret's Of Cortona Chr",
    "wof:placetype":"venue"
},
  "geometry": {"coordinates":[-74.042283,40.846269],"type":"Point"}
}