{
  "type": "Feature",
  "properties": {
    "addr:full":"501 N Black Horse Pike Glendora NJ 08029",
    "addr:housenumber":"501",
    "addr:postcode":"08029",
    "addr:street":"N Black Horse Pike",
    "iso:country":"US",
    "sg:address":"501 N Black Horse Pike",
    "sg:city":"Glendora",
    "sg:classifiers":[
        {
            "category":"Food & Beverages",
            "subcategory":"Groceries & Convenience Stores",
            "type":"Retail Goods"
        }
    ],
    "sg:phone":"+1   ",
    "sg:postcode":"08029",
    "sg:province":"NJ",
    "wof:name":"Pantry",
    "wof:placetype":"venue"
},
  "geometry": {"coordinates":[-75.08833199999999,39.886694],"type":"Point"}
}