{
  "type": "Feature",
  "properties": {
    "addr:full":"520 New Egypt Rd Lakewood NJ 08701",
    "addr:housenumber":"520",
    "addr:postcode":"08701",
    "addr:street":"New Egypt Rd",
    "iso:country":"US",
    "sg:address":"520 New Egypt Rd",
    "sg:city":"Lakewood",
    "sg:classifiers":[
        {
            "category":"Building & Trades",
            "subcategory":"Construction",
            "type":"Services"
        }
    ],
    "sg:phone":"+1 732 886 2003",
    "sg:postcode":"08701",
    "sg:province":"NJ",
    "wof:name":"S T C Paving",
    "wof:placetype":"venue"
},
  "geometry": {"coordinates":[-74.247958,40.087045],"type":"Point"}
}