{
  "type": "Feature",
  "properties": {
    "iso:country":"US",
    "sg:address":"75 Prescott St",
    "sg:city":"Demarest",
    "sg:classifiers":[
        {
            "category":"Building & Trades",
            "subcategory":"Construction",
            "type":"Services"
        }
    ],
    "sg:phone":"+1 201 768 8766",
    "sg:postcode":"07627",
    "sg:province":"NJ",
    "sg:tags":[
        "house",
        "general",
        "contractor"
    ],
    "wof:name":"Clockwork Construction Co Inc",
    "wof:placetype":"venue"
},
  "geometry": {"coordinates":[-73.97250200000001,40.958206],"type":"Point"}
}