{
  "type": "Feature",
  "properties": {
    "iso:country":"US",
    "sg:address":"21 Old Farm Rd",
    "sg:city":"Chatham",
    "sg:classifiers":[
        {
            "category":"Health Services",
            "subcategory":"Doctor",
            "type":"Services"
        }
    ],
    "sg:phone":"+1 973 377 3117",
    "sg:postcode":"07928",
    "sg:province":"NJ",
    "sg:tags":[
        "surgeon",
        "oral"
    ],
    "wof:name":"Philippi Harry R DDS",
    "wof:placetype":"venue"
},
  "geometry": {"coordinates":[-74.419601,40.737099],"type":"Point"}
}