{
  "type": "Feature",
  "properties": {
    "addr:full":"208 Rock Rd Glen Rock NJ 07452",
    "addr:housenumber":"208",
    "addr:postcode":"07452",
    "addr:street":"Rock Rd",
    "iso:country":"US",
    "sg:address":"208 Rock Rd",
    "sg:city":"Glen Rock",
    "sg:classifiers":[
        {
            "category":"Restaurant",
            "type":"Food & Drink"
        }
    ],
    "sg:menulink":"http://www.allmenus.com/nj/glen-rock/146177-subway/menu/",
    "sg:phone":"+1 201 251 2922",
    "sg:postcode":"07452",
    "sg:province":"NJ",
    "sg:tags":[
        "american",
        "sandwich"
    ],
    "wof:name":"Subway",
    "wof:placetype":"venue"
},
  "geometry": {"coordinates":[-74.13190299999999,40.962575],"type":"Point"}
}