{
  "type": "Feature",
  "properties": {
    "addr:full":"54 South St Morristown NJ 07960",
    "addr:housenumber":"54",
    "addr:postcode":"07960",
    "addr:street":"South St",
    "iso:country":"US",
    "sg:address":"54 South St",
    "sg:city":"Morristown",
    "sg:classifiers":[
        {
            "category":"Insurance",
            "subcategory":"Health Insurance",
            "type":"Services"
        }
    ],
    "sg:phone":"+1 973 538 3337",
    "sg:postcode":"07960",
    "sg:province":"NJ",
    "sg:tags":[
        "market"
    ],
    "wof:name":"General Nutrition Center",
    "wof:placetype":"venue"
},
  "geometry": {"coordinates":[-74.48049899999999,40.7957],"type":"Point"}
}