{
  "type": "Feature",
  "properties": {
    "iso:country":"US",
    "sg:address":"46 E 37th St",
    "sg:city":"Paterson",
    "sg:classifiers":[
        {
            "category":"Recreation",
            "type":"Entertainment"
        }
    ],
    "sg:phone":"+1   ",
    "sg:postcode":"07514",
    "sg:province":"NJ",
    "sg:tags":[
        "specialist",
        "fish"
    ],
    "wof:name":"Aaron Goar",
    "wof:placetype":"venue"
},
  "geometry": {"coordinates":[-74.13721099999999,40.922259],"type":"Point"}
}