{
  "type": "Feature",
  "properties": {
    "addr:full":"61 Acadia Dr Voorhees NJ 08043",
    "addr:housenumber":"61",
    "addr:postcode":"08043",
    "addr:street":"Acadia Dr",
    "iso:country":"US",
    "sg:address":"61 Acadia Dr",
    "sg:city":"Voorhees",
    "sg:classifiers":[
        {
            "category":"Professional",
            "subcategory":"Computer Services",
            "type":"Services"
        }
    ],
    "sg:phone":"+1   ",
    "sg:postcode":"08043",
    "sg:province":"NJ",
    "sg:tags":[
        "related"
    ],
    "wof:name":"Advanced Data Analysis Inc",
    "wof:placetype":"venue"
},
  "geometry": {"coordinates":[-74.934552,39.86953],"type":"Point"}
}