{
  "type": "Feature",
  "properties": {
    "iso:country":"US",
    "sg:address":"213 Clinton Ave",
    "sg:city":"Plainfield",
    "sg:classifiers":[
        {
            "category":"Building & Trades",
            "subcategory":"Landscaping Services",
            "type":"Services"
        }
    ],
    "sg:phone":"+1 908 412 8240",
    "sg:postcode":"07063",
    "sg:province":"NJ",
    "sg:tags":[
        "landscape"
    ],
    "wof:name":"Palisades Landscaping LLC",
    "wof:placetype":"venue"
},
  "geometry": {"coordinates":[-74.44371,40.60082],"type":"Point"}
}