{
  "type": "Feature",
  "properties": {
    "addr:full":"216 Grand St New Milford NJ 07646",
    "addr:housenumber":"216",
    "addr:postcode":"07646",
    "addr:street":"Grand St",
    "iso:country":"US",
    "sg:address":"216 Grand St",
    "sg:city":"New Milford",
    "sg:classifiers":[
        {
            "category":"Health Services",
            "subcategory":"Medical Lab",
            "type":"Services"
        }
    ],
    "sg:phone":"+1 201 384 0084",
    "sg:postcode":"07646",
    "sg:province":"NJ",
    "sg:tags":[
        "laboratory",
        "dental"
    ],
    "wof:name":"New Life Dental Laboratory",
    "wof:placetype":"venue"
},
  "geometry": {"coordinates":[-74.01993299999999,40.950292],"type":"Point"}
}