{
  "type": "Feature",
  "properties": {
    "addr:full":"239 Park Pl Irvington NJ 07111",
    "addr:housenumber":"239",
    "addr:postcode":"07111",
    "addr:street":"Park Pl",
    "iso:country":"US",
    "sg:address":"239 Park Pl",
    "sg:city":"Irvington",
    "sg:classifiers":[
        {
            "category":"Professional",
            "subcategory":"Business Services",
            "type":"Services"
        }
    ],
    "sg:phone":"+1   ",
    "sg:postcode":"07111",
    "sg:province":"NJ",
    "wof:name":"Rl Early Bird Express",
    "wof:placetype":"venue"
},
  "geometry": {"coordinates":[-74.24242,40.718677],"type":"Point"}
}