{
  "type": "Feature",
  "properties": {
    "addr:full":"190 Summerhill Dr Morris Plains NJ 07950",
    "addr:housenumber":"190",
    "addr:postcode":"07950",
    "addr:street":"Summerhill Dr",
    "iso:country":"US",
    "sg:address":"190 Summerhill Dr",
    "sg:city":"Morris Plains",
    "sg:classifiers":[
        {
            "category":"Travel",
            "subcategory":"Travel Agent",
            "type":"Entertainment"
        }
    ],
    "sg:phone":"+1 973 451 0600",
    "sg:postcode":"07950",
    "sg:province":"NJ",
    "sg:tags":[
        "agency"
    ],
    "wof:name":"Tour & Cruise Connection",
    "wof:placetype":"venue"
},
  "geometry": {"coordinates":[-74.50400399999999,40.854209],"type":"Point"}
}