{
  "type": "Feature",
  "properties": {
    "addr:full":"4 Gatehall Dr Parsippany NJ 07054",
    "addr:housenumber":"4",
    "addr:postcode":"07054",
    "addr:street":"Gatehall Dr",
    "iso:country":"US",
    "sg:address":"4 Gatehall Dr",
    "sg:city":"Parsippany",
    "sg:classifiers":[
        {
            "category":"Professional",
            "subcategory":"Accounting & Tax Preparation",
            "type":"Services"
        }
    ],
    "sg:phone":"+1 973 605 1040",
    "sg:postcode":"07054",
    "sg:province":"NJ",
    "sg:tags":[
        "accountant"
    ],
    "wof:name":"Heidrich Toni J CPA",
    "wof:placetype":"venue"
},
  "geometry": {"coordinates":[-74.46199799999999,40.847698],"type":"Point"}
}