{
  "type": "Feature",
  "properties": {
    "addr:full":"16 S Main St Manville NJ 08835",
    "addr:housenumber":"16",
    "addr:postcode":"08835",
    "addr:street":"S Main St",
    "iso:country":"US",
    "sg:address":"16 S Main St",
    "sg:city":"Manville",
    "sg:classifiers":[
        {
            "category":"Restaurant",
            "type":"Food & Drink"
        }
    ],
    "sg:phone":"+1   ",
    "sg:postcode":"08835",
    "sg:province":"NJ",
    "sg:tags":[
        "eating"
    ],
    "wof:name":"Corner Cafe",
    "wof:placetype":"venue"
},
  "geometry": {"coordinates":[-74.587046,40.544381],"type":"Point"}
}