{
  "type": "Feature",
  "properties": {
    "iso:country":"US",
    "sg:address":"496 4th Ave",
    "sg:city":"Westwood",
    "sg:classifiers":[
        {
            "category":"Building & Trades",
            "subcategory":"Plumbing",
            "type":"Services"
        }
    ],
    "sg:phone":"+1 201 666 5936",
    "sg:postcode":"07675",
    "sg:province":"NJ",
    "sg:tags":[
        "plumbing",
        "contractor"
    ],
    "wof:name":"Michael Farmilette Plumbing",
    "wof:placetype":"venue"
},
  "geometry": {"coordinates":[-74.03622900000001,40.989935],"type":"Point"}
}