{
  "type": "Feature",
  "properties": {
    "addr:full":"69 W Main St Somerville NJ 08876",
    "addr:housenumber":"69",
    "addr:postcode":"08876",
    "addr:street":"W Main St",
    "iso:country":"US",
    "sg:address":"69 W Main St",
    "sg:city":"Somerville",
    "sg:classifiers":[
        {
            "category":"Restaurant",
            "type":"Food & Drink"
        }
    ],
    "sg:phone":"+1 908 252 1777",
    "sg:postcode":"08876",
    "sg:province":"NJ",
    "sg:tags":[
        "eating"
    ],
    "wof:name":"East Star Restaurant East",
    "wof:placetype":"venue"
},
  "geometry": {"coordinates":[-74.614586,40.568911],"type":"Point"}
}