{
  "type": "Feature",
  "properties": {
    "iso:country":"US",
    "sg:address":"1931 Filmore St",
    "sg:city":"Camden",
    "sg:classifiers":[
        {
            "category":"Professional",
            "subcategory":"Advertising",
            "type":"Services"
        }
    ],
    "sg:phone":"+1 856 541 6522",
    "sg:postcode":"08104",
    "sg:province":"NJ",
    "sg:tags":[
        "mail",
        "direct"
    ],
    "sg:website":"http://www.riddicksfolly.org",
    "wof:name":"Riddick Inc",
    "wof:placetype":"venue"
},
  "geometry": {"coordinates":[-75.118759,39.920691],"type":"Point"}
}