{
  "type": "Feature",
  "properties": {
    "addr:full":"260 Columbia Ave Fort Lee NJ 07024",
    "addr:housenumber":"260",
    "addr:postcode":"07024",
    "addr:street":"Columbia Ave",
    "iso:country":"US",
    "sg:address":"260 Columbia Ave",
    "sg:city":"Fort Lee",
    "sg:classifiers":[
        {
            "category":"Wholesale",
            "subcategory":"Drugs",
            "type":"Manufacturing & Wholesale Goods"
        }
    ],
    "sg:phone":"+1 201 886 1500",
    "sg:postcode":"07024",
    "sg:province":"NJ",
    "wof:name":"Michael Mastromarino",
    "wof:placetype":"venue"
},
  "geometry": {"coordinates":[-73.98206,40.831732],"type":"Point"}
}