{
  "type": "Feature",
  "properties": {
    "addr:full":"150 S Main Rd Vineland NJ 08360",
    "addr:housenumber":"150",
    "addr:postcode":"08360",
    "addr:street":"S Main Rd",
    "iso:country":"US",
    "sg:address":"150 S Main Rd",
    "sg:city":"Vineland",
    "sg:classifiers":[
        {
            "category":"Banks & Credit Unions",
            "subcategory":"Investment Brokerage",
            "type":"Services"
        }
    ],
    "sg:phone":"+1   ",
    "sg:postcode":"08360",
    "sg:province":"NJ",
    "sg:tags":[
        "advisory"
    ],
    "wof:name":"Provest Financial Services",
    "wof:placetype":"venue"
},
  "geometry": {"coordinates":[-74.999973,39.483103],"type":"Point"}
}