{
  "type": "Feature",
  "properties": {
    "addr:full":"1240 State Rte 166 Toms River NJ 08753",
    "addr:housenumber":"1240",
    "addr:postcode":"08753",
    "addr:street":"State Rte 166",
    "iso:country":"US",
    "sg:address":"1240 State Rte 166",
    "sg:city":"Toms River",
    "sg:classifiers":[
        {
            "category":"Shopping",
            "subcategory":"Florist",
            "type":"Retail Goods"
        }
    ],
    "sg:phone":"+1 732 797 1956",
    "sg:postcode":"08753",
    "sg:province":"NJ",
    "wof:name":"Flowers With Class Inc",
    "wof:placetype":"venue"
},
  "geometry": {"coordinates":[-74.21047799999999,39.985731],"type":"Point"}
}