{
  "type": "Feature",
  "properties": {
    "iso:country":"US",
    "sg:address":"648 Maple Ave",
    "sg:city":"Wyckoff",
    "sg:classifiers":[
        {
            "category":"Manufacturing",
            "subcategory":"Tools & Machinery",
            "type":"Manufacturing & Wholesale Goods"
        }
    ],
    "sg:phone":"+1 201 848 5035",
    "sg:postcode":"07481",
    "sg:province":"NJ",
    "sg:tags":[
        "equipment",
        "surgical",
        "mfg"
    ],
    "wof:name":"Specialty Medical Supply",
    "wof:placetype":"venue"
},
  "geometry": {"coordinates":[-74.175691,41.010859],"type":"Point"}
}