{
  "type": "Feature",
  "properties": {
    "iso:country":"US",
    "sg:address":"660 W 1st Ave",
    "sg:city":"Roselle",
    "sg:classifiers":[
        {
            "category":"Retail",
            "subcategory":"Car Wash",
            "type":"Services"
        }
    ],
    "sg:phone":"+1 908 245 6437",
    "sg:postcode":"07203",
    "sg:province":"NJ",
    "sg:tags":[
        "polishing",
        "washing"
    ],
    "wof:name":"Wash Rack",
    "wof:placetype":"venue"
},
  "geometry": {"coordinates":[-74.28312099999999,40.657527],"type":"Point"}
}