{
  "type": "Feature",
  "properties": {
    "addr:full":"1796 Hinds Rd Toms River NJ 08753",
    "addr:housenumber":"1796",
    "addr:postcode":"08753",
    "addr:street":"Hinds Rd",
    "iso:country":"US",
    "sg:address":"1796 Hinds Rd",
    "sg:city":"Toms River",
    "sg:classifiers":[
        {
            "category":"Professional",
            "type":"Services"
        }
    ],
    "sg:phone":"+1   ",
    "sg:postcode":"08753",
    "sg:province":"NJ",
    "wof:name":"Healing Way LLC",
    "wof:placetype":"venue"
},
  "geometry": {"coordinates":[-74.148481,40.009314],"type":"Point"}
}