{
  "type": "Feature",
  "properties": {
    "addr:full":"288 Teaneck Rd Ridgefield Park NJ 07660",
    "addr:housenumber":"288",
    "addr:postcode":"07660",
    "addr:street":"Teaneck Rd",
    "iso:country":"US",
    "sg:address":"288 Teaneck Rd",
    "sg:city":"Ridgefield Park",
    "sg:classifiers":[
        {
            "category":"Personal",
            "subcategory":"Beauty Salon",
            "type":"Services"
        }
    ],
    "sg:phone":"+1 201 440 1557",
    "sg:postcode":"07660",
    "sg:province":"NJ",
    "sg:tags":[
        "hair"
    ],
    "sg:website":"www.mayamallya.com/",
    "wof:name":"Maya Mallya",
    "wof:placetype":"venue"
},
  "geometry": {"coordinates":[-74.019651,40.853467],"type":"Point"}
}