{
  "type": "Feature",
  "properties": {
    "addr:full":"100 Campus Dr Edison NJ 08837",
    "addr:housenumber":"100",
    "addr:postcode":"08837",
    "addr:street":"Campus Dr",
    "iso:country":"US",
    "sg:address":"100 Campus Dr",
    "sg:city":"Edison",
    "sg:classifiers":[
        {
            "category":"Freight",
            "type":"Transportation"
        }
    ],
    "sg:phone":"+1 732 225 3322",
    "sg:postcode":"08837",
    "sg:province":"NJ",
    "sg:tags":[
        "general"
    ],
    "wof:name":"Egs Electrical Group LLC",
    "wof:placetype":"venue"
},
  "geometry": {"coordinates":[-74.34090500000001,40.508798],"type":"Point"}
}