{
  "type": "Feature",
  "properties": {
    "addr:full":"115 Ave A Cranford NJ 07002",
    "addr:housenumber":"115",
    "addr:postcode":"07002",
    "addr:street":"Ave A",
    "iso:country":"US",
    "sg:address":"115 Ave A",
    "sg:city":"Cranford",
    "sg:classifiers":[
        {
            "category":"Professional",
            "subcategory":"Employment Agencies",
            "type":"Services"
        }
    ],
    "sg:phone":"+1 908 653 9200",
    "sg:postcode":"07002",
    "sg:province":"NJ",
    "sg:tags":[
        "opportunity"
    ],
    "wof:name":"Key Personnel Inc",
    "wof:placetype":"venue"
},
  "geometry": {"coordinates":[-74.13727299999999,40.652383],"type":"Point"}
}