{
  "type": "Feature",
  "properties": {
    "addr:full":"22 Winfield Ave Pompton Plains NJ 07444",
    "addr:housenumber":"22",
    "addr:postcode":"07444",
    "addr:street":"Winfield Ave",
    "iso:country":"US",
    "sg:address":"22 Winfield Ave",
    "sg:city":"Pompton Plains",
    "sg:classifiers":[
        {
            "category":"Wholesale",
            "subcategory":"Groceries",
            "type":"Manufacturing & Wholesale Goods"
        }
    ],
    "sg:phone":"+1 973 835 8283",
    "sg:postcode":"07444",
    "sg:province":"NJ",
    "sg:tags":[
        "tea",
        "coffee"
    ],
    "wof:name":"D & D Associates",
    "wof:placetype":"venue"
},
  "geometry": {"coordinates":[-74.300506,40.970878],"type":"Point"}
}