{
  "type": "Feature",
  "properties": {
    "iso:country":"US",
    "sg:address":"387 Piaget Ave",
    "sg:city":"Clifton",
    "sg:classifiers":[
        {
            "category":"Shopping",
            "subcategory":"Hobbies, Toys, & Games",
            "type":"Retail Goods"
        },
        {
            "category":"Cinema",
            "subcategory":"Movie Rental",
            "type":"Entertainment"
        },
        {
            "category":"Recreation",
            "subcategory":"Arcade",
            "type":"Entertainment"
        }
    ],
    "sg:phone":"+1 973 772 1111",
    "sg:postcode":"07011",
    "sg:province":"NJ",
    "sg:tags":[
        "toy",
        "video",
        "store"
    ],
    "sg:website":"www.digitpress.com/store",
    "wof:name":"Digital Press Videogames",
    "wof:placetype":"venue"
},
  "geometry": {"coordinates":[-74.151968,40.879138],"type":"Point"}
}