{
  "type": "Feature",
  "properties": {
    "addr:full":"250 Huntington Dr Vincentown NJ 08088",
    "addr:housenumber":"250",
    "addr:postcode":"08088",
    "addr:street":"Huntington Dr",
    "iso:country":"US",
    "sg:address":"250 Huntington Dr",
    "sg:city":"Vincentown",
    "sg:classifiers":[
        {
            "category":"Social Services",
            "type":"Services"
        }
    ],
    "sg:phone":"+1 609 859 1707",
    "sg:postcode":"08088",
    "sg:province":"NJ",
    "wof:name":"Leisuretown Civic League",
    "wof:placetype":"venue"
},
  "geometry": {"coordinates":[-74.71140699999999,39.90356],"type":"Point"}
}