{
  "type": "Feature",
  "properties": {
    "addr:full":"403 E 14th St Ocean City NJ 08226",
    "addr:housenumber":"403",
    "addr:postcode":"08226",
    "addr:street":"E 14Th St",
    "iso:country":"US",
    "sg:address":"403 E 14th St",
    "sg:city":"Ocean City",
    "sg:classifiers":[
        {
            "category":"Restaurant",
            "type":"Food & Drink"
        }
    ],
    "sg:menulink":"http://www.allmenus.com/nj/ocean-city/31086-island-shore-ii/menu/",
    "sg:phone":"+1 609 391 7520",
    "sg:postcode":"08226",
    "sg:province":"NJ",
    "sg:tags":[
        "asian",
        "chinese"
    ],
    "wof:name":"Island Shore II",
    "wof:placetype":"venue"
},
  "geometry": {"coordinates":[-74.58340800000001,39.273423],"type":"Point"}
}