{
  "type": "Feature",
  "properties": {
    "addr:full":"765 Columbus Ave Phillipsburg NJ 08865",
    "addr:housenumber":"765",
    "addr:postcode":"08865",
    "addr:street":"Columbus Ave",
    "iso:country":"US",
    "sg:address":"765 Columbus Ave",
    "sg:city":"Phillipsburg",
    "sg:classifiers":[
        {
            "category":"Government",
            "subcategory":"Fire Station",
            "type":"Public Place"
        }
    ],
    "sg:phone":"+1 908 454 1621",
    "sg:postcode":"08865",
    "sg:province":"NJ",
    "sg:tags":[
        "department"
    ],
    "wof:name":"Phillipsburg Fire Dept",
    "wof:placetype":"venue"
},
  "geometry": {"coordinates":[-75.17324000000001,40.68571],"type":"Point"}
}