{
  "type": "Feature",
  "properties": {
    "iso:country":"US",
    "sg:address":"5 Rosewood Dr",
    "sg:city":"Glen Gardner",
    "sg:classifiers":[
        {
            "category":"Professional",
            "subcategory":"Computer Services",
            "type":"Services"
        }
    ],
    "sg:phone":"+1   ",
    "sg:postcode":"08826",
    "sg:province":"NJ",
    "wof:name":"Networks Works Inc",
    "wof:placetype":"venue"
},
  "geometry": {"coordinates":[-74.912826,40.671297],"type":"Point"}
}