{
  "type": "Feature",
  "properties": {
    "iso:country":"US",
    "sg:address":"1100 East Blvd",
    "sg:city":"Alpha",
    "sg:classifiers":[
        {
            "category":"Food & Beverages",
            "subcategory":"Groceries & Convenience Stores",
            "type":"Retail Goods"
        }
    ],
    "sg:phone":"+1 908 454 3968",
    "sg:postcode":"08865",
    "sg:province":"NJ",
    "sg:tags":[
        "grocer"
    ],
    "wof:name":"Central Super Market",
    "wof:placetype":"venue"
},
  "geometry": {"coordinates":[-75.160331,40.662503],"type":"Point"}
}