{
  "type": "Feature",
  "properties": {
    "iso:country":"US",
    "sg:address":"195 Mountain Ave",
    "sg:city":"Springfield",
    "sg:classifiers":[
        {
            "category":"Professional",
            "type":"Services"
        }
    ],
    "sg:phone":"+1 973 275 0811",
    "sg:postcode":"07081",
    "sg:province":"NJ",
    "sg:tags":[
        "establishment"
    ],
    "wof:name":"Nalfleet Bull & Roberts Inc",
    "wof:placetype":"venue"
},
  "geometry": {"coordinates":[-74.316444,40.70565],"type":"Point"}
}