{
  "type": "Feature",
  "properties": {
    "iso:country":"US",
    "sg:address":"24 Taylor St",
    "sg:city":"Parsippany",
    "sg:classifiers":[
        {
            "category":"Professional",
            "type":"Services"
        }
    ],
    "sg:phone":"+1 973 439 6886",
    "sg:postcode":"07013",
    "sg:province":"NJ",
    "sg:tags":[
        "establishment"
    ],
    "wof:name":"Data Recovery",
    "wof:placetype":"venue"
},
  "geometry": {"coordinates":[-74.173329,40.893569],"type":"Point"}
}