{
  "type": "Feature",
  "properties": {
    "addr:full":"1101 Black Horse Pike Glendora NJ 08029",
    "addr:housenumber":"1101",
    "addr:postcode":"08029",
    "addr:street":"Black Horse Pike",
    "iso:country":"US",
    "sg:address":"1101 Black Horse Pike",
    "sg:city":"Glendora",
    "sg:classifiers":[
        {
            "category":"Professional",
            "subcategory":"Engineering",
            "type":"Services"
        },
        {
            "category":"Wholesale",
            "subcategory":"Machinery & Supplies",
            "type":"Manufacturing & Wholesale Goods"
        }
    ],
    "sg:phone":"+1 856 939 0588",
    "sg:postcode":"08029",
    "sg:province":"NJ",
    "sg:tags":[
        "system",
        "equipment-parts",
        "equipment",
        "refrigeration",
        "freezers-wholesale",
        "engineer",
        "air conditioning",
        "refrigerator",
        "manufacturer"
    ],
    "wof:name":"Associate Refrigeration Inc",
    "wof:placetype":"venue"
},
  "geometry": {"coordinates":[-75.070122,39.842041],"type":"Point"}
}