{
  "type": "Feature",
  "properties": {
    "addr:full":"349 E Clements Bridge Rd Runnemede NJ 08078",
    "addr:housenumber":"349",
    "addr:postcode":"08078",
    "addr:street":"E Clements Bridge Rd",
    "iso:country":"US",
    "sg:address":"349 E Clements Bridge Rd",
    "sg:city":"Runnemede",
    "sg:classifiers":[
        {
            "category":"Restaurant",
            "type":"Food & Drink"
        }
    ],
    "sg:phone":"+1 856 939 5800",
    "sg:postcode":"08078",
    "sg:province":"NJ",
    "wof:name":"Bahs' Restaurant",
    "wof:placetype":"venue"
},
  "geometry": {"coordinates":[-75.067092,39.853246],"type":"Point"}
}