{
  "type": "Feature",
  "properties": {
    "addr:full":"440 60th St West New York NJ 07093",
    "addr:housenumber":"440",
    "addr:postcode":"nj 07093",
    "addr:street":"60Th St West",
    "iso:country":"US",
    "sg:address":"440 60th St",
    "sg:city":"West New York",
    "sg:classifiers":[
        {
            "category":"Professional",
            "subcategory":"Lawyer & Legal Services",
            "type":"Services"
        }
    ],
    "sg:phone":"+1 201 758 1919",
    "sg:postcode":"07093",
    "sg:province":"NJ",
    "sg:tags":[
        "attorney"
    ],
    "wof:name":"Castro & Martell PC",
    "wof:placetype":"venue"
},
  "geometry": {"coordinates":[-74.016319,40.788873],"type":"Point"}
}