{
  "type": "Feature",
  "properties": {
    "addr:full":"25 Lafayette St Riverside NJ 08075",
    "addr:housenumber":"25",
    "addr:postcode":"08075",
    "addr:street":"Lafayette St",
    "iso:country":"US",
    "sg:address":"25 Lafayette St",
    "sg:city":"Riverside",
    "sg:classifiers":[
        {
            "category":"Insurance",
            "subcategory":"Insurance Agent",
            "type":"Services"
        }
    ],
    "sg:phone":"+1   ",
    "sg:postcode":"08075",
    "sg:province":"NJ",
    "wof:name":"Burton Financial Services",
    "wof:placetype":"venue"
},
  "geometry": {"coordinates":[-74.960565,40.03859],"type":"Point"}
}