{
  "type": "Feature",
  "properties": {
    "iso:country":"US",
    "sg:address":"728 Newman Springs Rd",
    "sg:city":"Lincroft",
    "sg:classifiers":[
        {
            "category":"Health Services",
            "subcategory":"Doctor",
            "type":"Services"
        }
    ],
    "sg:phone":"+1 732 345 9772",
    "sg:postcode":"07738",
    "sg:province":"NJ",
    "sg:tags":[
        "physician",
        "surgeon"
    ],
    "wof:name":"Family Practice-Central Jerse",
    "wof:placetype":"venue"
},
  "geometry": {"coordinates":[-74.12163,40.33085],"type":"Point"}
}