{
  "type": "Feature",
  "properties": {
    "addr:full":"188 8th Ave Hawthorne NJ 07506",
    "addr:housenumber":"188",
    "addr:postcode":"07506",
    "addr:street":"8Th Ave",
    "iso:country":"US",
    "sg:address":"188 8th Ave",
    "sg:city":"Hawthorne",
    "sg:classifiers":[
        {
            "category":"Building & Trades",
            "subcategory":"Plumbing",
            "type":"Services"
        }
    ],
    "sg:phone":"+1 973 423 3968",
    "sg:postcode":"07506",
    "sg:province":"NJ",
    "sg:tags":[
        "heating",
        "contractor"
    ],
    "wof:name":"W Moore",
    "wof:placetype":"venue"
},
  "geometry": {"coordinates":[-74.14998799999999,40.963715],"type":"Point"}
}