{
  "type": "Feature",
  "properties": {
    "iso:country":"US",
    "sg:address":"48 Zeliff Ave",
    "sg:city":"Little Falls",
    "sg:classifiers":[
        {
            "category":"Building & Trades",
            "subcategory":"Construction",
            "type":"Services"
        }
    ],
    "sg:phone":"+1 973 812 8901",
    "sg:postcode":"07424",
    "sg:province":"NJ",
    "sg:tags":[
        "painter"
    ],
    "wof:name":"Painting & More Corp",
    "wof:placetype":"venue"
},
  "geometry": {"coordinates":[-74.242897,40.888],"type":"Point"}
}