{
  "type": "Feature",
  "properties": {
    "iso:country":"US",
    "sg:address":"705 Boulevard",
    "sg:city":"Kenilworth",
    "sg:classifiers":[
        {
            "category":"Donuts",
            "subcategory":"None",
            "type":"Food & Drink"
        }
    ],
    "sg:phone":"+1 908 241 8115",
    "sg:postcode":"07033",
    "sg:province":"NJ",
    "sg:website":"www.dunkindonuts.com",
    "wof:name":"Dunkin Donuts",
    "wof:placetype":"venue"
},
  "geometry": {"coordinates":[-74.2861,40.6771],"type":"Point"}
}