{
  "type": "Feature",
  "properties": {
    "iso:country":"US",
    "sg:address":"188 State Rte 31",
    "sg:city":"Flemington",
    "sg:classifiers":[
        {
            "category":"Social Services",
            "subcategory":"Adult Care",
            "type":"Services"
        }
    ],
    "sg:phone":"+1 908 788 4893",
    "sg:postcode":"08822",
    "sg:province":"NJ",
    "sg:tags":[
        "home",
        "residential"
    ],
    "sg:website":"www.independencemanor.com",
    "wof:name":"Indepndence Manor At Hunterdon",
    "wof:placetype":"venue"
},
  "geometry": {"coordinates":[-74.85706999999999,40.530578],"type":"Point"}
}