{
  "type": "Feature",
  "properties": {
    "iso:country":"US",
    "sg:address":"43 Florence Ave",
    "sg:city":"Trenton",
    "sg:classifiers":[
        {
            "category":"Professional",
            "type":"Services"
        }
    ],
    "sg:phone":"+1   ",
    "sg:postcode":"08618",
    "sg:province":"NJ",
    "wof:name":"N Forrest Neressa",
    "wof:placetype":"venue"
},
  "geometry": {"coordinates":[-74.779764,40.255424],"type":"Point"}
}