{
  "type": "Feature",
  "properties": {
    "addr:full":"1984 State Rte 35 South Amboy NJ 08879",
    "addr:housenumber":"1984",
    "addr:postcode":"08879",
    "addr:street":"State Rte 35",
    "iso:country":"US",
    "sg:address":"1984 State Rte 35",
    "sg:city":"South Amboy",
    "sg:classifiers":[
        {
            "category":"Wholesale",
            "subcategory":"Groceries",
            "type":"Manufacturing & Wholesale Goods"
        }
    ],
    "sg:phone":"+1 732 721 1256",
    "sg:postcode":"08879",
    "sg:province":"NJ",
    "sg:tags":[
        "food",
        "broker"
    ],
    "wof:name":"Quality Food Products",
    "wof:placetype":"venue"
},
  "geometry": {"coordinates":[-74.27512299999999,40.464293],"type":"Point"}
}