{
  "type": "Feature",
  "properties": {
    "addr:full":"176 Mallory Ave Jersey City NJ 07304",
    "addr:housenumber":"176",
    "addr:postcode":"07304",
    "addr:street":"Mallory Ave",
    "iso:country":"US",
    "sg:address":"176 Mallory Ave",
    "sg:city":"Jersey City",
    "sg:classifiers":[
        {
            "category":"Social Services",
            "type":"Services"
        }
    ],
    "sg:phone":"+1   ",
    "sg:postcode":"07304",
    "sg:province":"NJ",
    "wof:name":"G V C",
    "wof:placetype":"venue"
},
  "geometry": {"coordinates":[-74.087879,40.719832],"type":"Point"}
}