{
  "type": "Feature",
  "properties": {
    "iso:country":"US",
    "sg:address":"393 1st St",
    "sg:city":"Hackensack",
    "sg:classifiers":[
        {
            "category":"Organizations",
            "subcategory":"Religious Organization",
            "type":"Services"
        }
    ],
    "sg:phone":"+1 201 342 6155",
    "sg:postcode":"07601",
    "sg:province":"NJ",
    "sg:tags":[
        "church"
    ],
    "wof:name":"Tabernacle-Our Lord Jesus",
    "wof:placetype":"venue"
},
  "geometry": {"coordinates":[-74.047237,40.893654],"type":"Point"}
}