{
  "type": "Feature",
  "properties": {
    "addr:full":"773 Central Ave Westfield NJ 07090",
    "addr:housenumber":"773",
    "addr:postcode":"07090",
    "addr:street":"Central Ave",
    "iso:country":"US",
    "sg:address":"773 Central Ave",
    "sg:city":"Westfield",
    "sg:classifiers":[
        {
            "category":"Professional",
            "subcategory":"Lawyer & Legal Services",
            "type":"Services"
        }
    ],
    "sg:phone":"+1 908 232 2040",
    "sg:postcode":"07090",
    "sg:province":"NJ",
    "sg:tags":[
        "attorney"
    ],
    "wof:name":"Kessler Di Giovanni & Jesuele",
    "wof:placetype":"venue"
},
  "geometry": {"coordinates":[-74.33551900000001,40.645288],"type":"Point"}
}