{
  "type": "Feature",
  "properties": {
    "iso:country":"US",
    "sg:address":"66 Maple Ave",
    "sg:city":"Irvington",
    "sg:classifiers":[
        {
            "category":"Professional",
            "type":"Services"
        }
    ],
    "sg:phone":"+1   ",
    "sg:postcode":"07111",
    "sg:province":"NJ",
    "wof:name":"A-1 Merchant",
    "wof:placetype":"venue"
},
  "geometry": {"coordinates":[-74.22277099999999,40.726789],"type":"Point"}
}