{
  "type": "Feature",
  "properties": {
    "iso:country":"US",
    "sg:address":"200 Lake Dr E",
    "sg:city":"Cherry Hill",
    "sg:classifiers":[
        {
            "category":"Professional",
            "subcategory":"Lawyer & Legal Services",
            "type":"Services"
        }
    ],
    "sg:phone":"+1 856 667 6644",
    "sg:postcode":"08002",
    "sg:province":"NJ",
    "wof:name":"Prusky Law Assoc PC",
    "wof:placetype":"venue"
},
  "geometry": {"coordinates":[-75.00315500000001,39.938553],"type":"Point"}
}