{
  "type": "Feature",
  "properties": {
    "iso:country":"US",
    "sg:address":"100 Elm Rd",
    "sg:city":"Princeton",
    "sg:classifiers":[
        {
            "category":"Health Services",
            "subcategory":"Doctor",
            "type":"Services"
        }
    ],
    "sg:phone":"+1 609 921 3895",
    "sg:postcode":"08540",
    "sg:province":"NJ",
    "sg:tags":[
        "physician",
        "surgeon"
    ],
    "wof:name":"Stanley Rosenberg Dr",
    "wof:placetype":"venue"
},
  "geometry": {"coordinates":[-74.67427499999999,40.34576],"type":"Point"}
}