{
  "type": "Feature",
  "properties": {
    "addr:full":"70 Parker Ave Passaic NJ 07055",
    "addr:housenumber":"70",
    "addr:postcode":"07055",
    "addr:street":"Parker Ave",
    "iso:country":"US",
    "sg:address":"70 Parker Ave",
    "sg:city":"Passaic",
    "sg:classifiers":[
        {
            "category":"Health Services",
            "subcategory":"Hospital",
            "type":"Services"
        }
    ],
    "sg:phone":"+1 973 594 9100",
    "sg:postcode":"07055",
    "sg:province":"NJ",
    "sg:tags":[
        "dialysis"
    ],
    "wof:name":"Renal Center of Passaic",
    "wof:placetype":"venue"
},
  "geometry": {"coordinates":[-74.121144,40.869459],"type":"Point"}
}