{
  "type": "Feature",
  "properties": {
    "addr:full":"850 Edgewater Ave Ridgefield NJ 07657",
    "addr:housenumber":"850",
    "addr:postcode":"07657",
    "addr:street":"Edgewater Ave",
    "iso:country":"US",
    "sg:address":"850 Edgewater Ave",
    "sg:city":"Ridgefield",
    "sg:classifiers":[
        {
            "category":"Organizations",
            "subcategory":"Professional Association",
            "type":"Services"
        }
    ],
    "sg:phone":"+1 201 943 6908",
    "sg:postcode":"07657",
    "sg:province":"NJ",
    "sg:tags":[
        "business"
    ],
    "wof:name":"US Chamber of Commerce N",
    "wof:placetype":"venue"
},
  "geometry": {"coordinates":[-74.003827,40.83172],"type":"Point"}
}