{
  "type": "Feature",
  "properties": {
    "iso:country":"US",
    "sg:address":"24 N Main St",
    "sg:city":"Fairton",
    "sg:classifiers":[
        {
            "category":"Shopping",
            "subcategory":"Bicycles & Sporting Goods",
            "type":"Retail Goods"
        }
    ],
    "sg:phone":"+1 856 451 3288",
    "sg:postcode":"08312",
    "sg:province":"NJ",
    "sg:tags":[
        "bait",
        "fishing"
    ],
    "wof:name":"Bartone Bait",
    "wof:placetype":"venue"
},
  "geometry": {"coordinates":[-75.08872700000001,39.656482],"type":"Point"}
}