{
  "type": "Feature",
  "properties": {
    "addr:full":"26 Henderson Ln Willingboro NJ 08046",
    "addr:housenumber":"26",
    "addr:postcode":"08046",
    "addr:street":"Henderson Ln",
    "iso:country":"US",
    "sg:address":"26 Henderson Ln",
    "sg:city":"Willingboro",
    "sg:classifiers":[
        {
            "category":"Professional",
            "subcategory":"Management & Consulting",
            "type":"Services"
        }
    ],
    "sg:phone":"+1   ",
    "sg:postcode":"08046",
    "sg:province":"NJ",
    "sg:tags":[
        "retail",
        "direct",
        "sales"
    ],
    "wof:name":"Glendas Home Decor & More",
    "wof:placetype":"venue"
},
  "geometry": {"coordinates":[-74.87042599999999,40.038143],"type":"Point"}
}