{
  "type": "Feature",
  "properties": {
    "iso:country":"US",
    "sg:address":"39 N Cherokee Ln",
    "sg:city":"Brick",
    "sg:classifiers":[
        {
            "category":"Professional",
            "type":"Services"
        }
    ],
    "sg:phone":"+1   ",
    "sg:postcode":"08724",
    "sg:province":"NJ",
    "wof:name":"Pcgb Inc",
    "wof:placetype":"venue"
},
  "geometry": {"coordinates":[-74.105394,40.060027],"type":"Point"}
}