{
  "type": "Feature",
  "properties": {
    "iso:country":"US",
    "sg:address":"1 Salem St",
    "sg:city":"Basking Ridge",
    "sg:classifiers":[
        {
            "category":"Wholesale",
            "subcategory":"Machinery & Supplies",
            "type":"Manufacturing & Wholesale Goods"
        }
    ],
    "sg:phone":"+1 908 647 1945",
    "sg:postcode":"07920",
    "sg:province":"NJ",
    "sg:tags":[
        "chemical",
        "equipment",
        "processing"
    ],
    "wof:name":"Nsr Technologies Inc",
    "wof:placetype":"venue"
},
  "geometry": {"coordinates":[-74.542631,40.662704],"type":"Point"}
}