{
  "type": "Feature",
  "properties": {
    "addr:full":"369 Ringwood Ave Wanaque NJ 07465",
    "addr:housenumber":"369",
    "addr:postcode":"07465",
    "addr:street":"Ringwood Ave",
    "iso:country":"US",
    "sg:address":"369 Ringwood Ave",
    "sg:city":"Wanaque",
    "sg:classifiers":[
        {
            "category":"Building & Trades",
            "subcategory":"Locksmith",
            "type":"Services"
        }
    ],
    "sg:phone":"+1 973 831 7607",
    "sg:postcode":"07465",
    "sg:province":"NJ",
    "sg:tags":[
        "key"
    ],
    "wof:name":"Antonio Andolini T A King Locksmith Co",
    "wof:placetype":"venue"
},
  "geometry": {"coordinates":[-74.2855,41.059898],"type":"Point"}
}