{
  "type": "Feature",
  "properties": {
    "addr:full":"790 Trumbull St Elizabeth NJ 07201",
    "addr:housenumber":"790",
    "addr:postcode":"07201",
    "addr:street":"Trumbull St",
    "iso:country":"US",
    "sg:address":"790 Trumbull St",
    "sg:city":"Elizabeth",
    "sg:classifiers":[
        {
            "category":"Building & Trades",
            "subcategory":"Construction",
            "type":"Services"
        }
    ],
    "sg:phone":"+1 908 289 0480",
    "sg:postcode":"07201",
    "sg:province":"NJ",
    "sg:tags":[
        "company"
    ],
    "wof:name":"Universal Construction",
    "wof:placetype":"venue"
},
  "geometry": {"coordinates":[-74.19650300000001,40.662478],"type":"Point"}
}