{
  "type": "Feature",
  "properties": {
    "iso:country":"US",
    "sg:address":"1602 Lawrence Ave",
    "sg:city":"Asbury Park",
    "sg:classifiers":[
        {
            "category":"Wholesale",
            "subcategory":"Dairy",
            "type":"Manufacturing & Wholesale Goods"
        }
    ],
    "sg:phone":"+1 732 922 9009",
    "sg:postcode":"07712",
    "sg:province":"NJ",
    "sg:tags":[
        "product"
    ],
    "wof:name":"Casein International",
    "wof:placetype":"venue"
},
  "geometry": {"coordinates":[-74.040661,40.242993],"type":"Point"}
}