{
  "type": "Feature",
  "properties": {
    "iso:country":"US",
    "sg:address":"105 S White Horse Pike",
    "sg:city":"Berlin",
    "sg:classifiers":[
        {
            "category":"Restaurant",
            "type":"Food & Drink"
        }
    ],
    "sg:phone":"+1 856 768 7919",
    "sg:postcode":"08009",
    "sg:province":"NJ",
    "sg:tags":[
        "caterer"
    ],
    "wof:name":"Berlin Deli & Catering",
    "wof:placetype":"venue"
},
  "geometry": {"coordinates":[-74.93111399999999,39.794205],"type":"Point"}
}