{
  "type": "Feature",
  "properties": {
    "addr:full":"764 Ave C Bayonne NJ 07002",
    "addr:housenumber":"764",
    "addr:postcode":"07002",
    "addr:street":"Ave C",
    "iso:country":"US",
    "sg:address":"764 Ave C",
    "sg:city":"Bayonne",
    "sg:classifiers":[
        {
            "category":"Real Estate",
            "subcategory":"Architect",
            "type":"Services"
        }
    ],
    "sg:phone":"+1 201 437 0648",
    "sg:postcode":"07002",
    "sg:province":"NJ",
    "wof:name":"Harold J Kawalek",
    "wof:placetype":"venue"
},
  "geometry": {"coordinates":[-74.113333,40.673462],"type":"Point"}
}