{
  "type": "Feature",
  "properties": {
    "addr:full":"233 Canoe Brook Rd Short Hills NJ 07078",
    "addr:housenumber":"233",
    "addr:postcode":"07078",
    "addr:street":"Canoe Brook Rd",
    "iso:country":"US",
    "sg:address":"233 Canoe Brook Rd",
    "sg:city":"Short Hills",
    "sg:classifiers":[
        {
            "category":"Real Estate",
            "subcategory":"Real Estate Agent",
            "type":"Services"
        }
    ],
    "sg:phone":"+1   ",
    "sg:postcode":"07078",
    "sg:province":"NJ",
    "sg:tags":[
        "management"
    ],
    "wof:name":"Roseland Management Co LLC",
    "wof:placetype":"venue"
},
  "geometry": {"coordinates":[-74.362709,40.739004],"type":"Point"}
}