{
  "type": "Feature",
  "properties": {
    "iso:country":"US",
    "sg:address":"27 Bowers Ln",
    "sg:city":"Chatham",
    "sg:classifiers":[
        {
            "category":"Building & Trades",
            "subcategory":"Construction",
            "type":"Services"
        }
    ],
    "sg:phone":"+1 973 635 9030",
    "sg:postcode":"07928",
    "sg:province":"NJ",
    "sg:tags":[
        "asbestos",
        "removal"
    ],
    "wof:name":"Pinnacle Environmental Corp",
    "wof:placetype":"venue"
},
  "geometry": {"coordinates":[-74.380905,40.73948],"type":"Point"}
}