{
  "type": "Feature",
  "properties": {
    "iso:country":"US",
    "sg:address":"180 3rd St",
    "sg:city":"Elizabeth",
    "sg:classifiers":[
        {
            "category":"Food & Beverages",
            "subcategory":"Liquor & Beverages",
            "type":"Retail Goods"
        }
    ],
    "sg:phone":"+1 908 527 9505",
    "sg:postcode":"07206",
    "sg:province":"NJ",
    "wof:name":"Seaport Liquors Inc",
    "wof:placetype":"venue"
},
  "geometry": {"coordinates":[-74.187714,40.653958],"type":"Point"}
}