{
  "type": "Feature",
  "properties": {
    "addr:full":"42 Main St Andover NJ 07821",
    "addr:housenumber":"42",
    "addr:postcode":"07821",
    "addr:street":"Main St",
    "iso:country":"US",
    "sg:address":"42 Main St",
    "sg:city":"Andover",
    "sg:classifiers":[
        {
            "category":"Shopping",
            "subcategory":"Used Merchandise",
            "type":"Retail Goods"
        },
        {
            "category":"Manufacturing",
            "subcategory":"Wood Products",
            "type":"Manufacturing & Wholesale Goods"
        }
    ],
    "sg:phone":"+1 973 786 6414",
    "sg:postcode":"07821",
    "sg:province":"NJ",
    "sg:tags":[
        "antique",
        "mfg"
    ],
    "wof:name":"Scranberry Coop LLC",
    "wof:placetype":"venue"
},
  "geometry": {"coordinates":[-74.74087900000001,40.971586],"type":"Point"}
}