{
  "type": "Feature",
  "properties": {
    "iso:country":"US",
    "sg:address":"5000 Atrium Way",
    "sg:city":"Mount Laurel",
    "sg:classifiers":[
        {
            "category":"Wholesale",
            "subcategory":"Computers",
            "type":"Manufacturing & Wholesale Goods"
        }
    ],
    "sg:phone":"+1 856 234 5100",
    "sg:postcode":"08054",
    "sg:province":"NJ",
    "sg:tags":[
        "peripheral"
    ],
    "wof:name":"Continental Resources Inc",
    "wof:placetype":"venue"
},
  "geometry": {"coordinates":[-74.95038099999999,39.918416],"type":"Point"}
}