{
  "type": "Feature",
  "properties": {
    "addr:full":"205 Lathrop Ave Boonton NJ 07005",
    "addr:housenumber":"205",
    "addr:postcode":"07005",
    "addr:street":"Lathrop Ave",
    "iso:country":"US",
    "sg:address":"205 Lathrop Ave",
    "sg:city":"Boonton",
    "sg:classifiers":[
        {
            "category":"Building & Trades",
            "subcategory":"Electrical",
            "type":"Services"
        }
    ],
    "sg:phone":"+1 973 331 0755",
    "sg:postcode":"07005",
    "sg:province":"NJ",
    "sg:tags":[
        "electric",
        "contractor"
    ],
    "wof:name":"Cast Electric",
    "wof:placetype":"venue"
},
  "geometry": {"coordinates":[-74.40547599999999,40.902055],"type":"Point"}
}