{
  "type": "Feature",
  "properties": {
    "iso:country":"US",
    "sg:address":"130 Spring Garden Rd",
    "sg:city":"Milford",
    "sg:classifiers":[
        {
            "category":"Real Estate",
            "subcategory":"Real Estate Operator",
            "type":"Services"
        }
    ],
    "sg:phone":"+1   ",
    "sg:postcode":"08848",
    "sg:province":"NJ",
    "sg:tags":[
        "building",
        "nonresidential"
    ],
    "wof:name":"McEasy Shopping Co",
    "wof:placetype":"venue"
},
  "geometry": {"coordinates":[-75.122775,40.582325],"type":"Point"}
}