{
  "type": "Feature",
  "properties": {
    "iso:country":"US",
    "sg:address":"608 McCabe Ave",
    "sg:city":"Bradley Beach",
    "sg:classifiers":[
        {
            "category":"Arts & Performance",
            "subcategory":"Theater",
            "type":"Entertainment"
        }
    ],
    "sg:phone":"+1   ",
    "sg:postcode":"07720",
    "sg:province":"NJ",
    "sg:tags":[
        "group"
    ],
    "wof:name":"Artist Group Music Publis",
    "wof:placetype":"venue"
},
  "geometry": {"coordinates":[-74.01652300000001,40.205039],"type":"Point"}
}