{
  "type": "Feature",
  "properties": {
    "iso:country":"US",
    "sg:address":"2500 McClellan Ave",
    "sg:city":"Pennsauken",
    "sg:classifiers":[
        {
            "category":"Organizations",
            "subcategory":"Non-profit Organization",
            "type":"Services"
        }
    ],
    "sg:phone":"+1 856 665 6000",
    "sg:postcode":"08109",
    "sg:province":"NJ",
    "wof:name":"Southern New Jersey Perinatal",
    "wof:placetype":"venue"
},
  "geometry": {"coordinates":[-75.06714100000001,39.93195],"type":"Point"}
}