{
  "type": "Feature",
  "properties": {
    "iso:country":"US",
    "sg:address":"32 Monroe Ave",
    "sg:city":"Carteret",
    "sg:classifiers":[
        {
            "category":"Retail",
            "subcategory":"Laundry & Dry Cleaning",
            "type":"Services"
        }
    ],
    "sg:phone":"+1 732 541 5005",
    "sg:postcode":"07008",
    "sg:province":"NJ",
    "sg:tags":[
        "garment",
        "plant",
        "agent",
        "drycleaning"
    ],
    "wof:name":"South Broad Tailor & Cleaners",
    "wof:placetype":"venue"
},
  "geometry": {"coordinates":[-74.234537,40.590751],"type":"Point"}
}