{
  "type": "Feature",
  "properties": {
    "addr:full":"536 Mantua Pike Woodbury NJ 08096",
    "addr:housenumber":"536",
    "addr:postcode":"08096",
    "addr:street":"Mantua Pike",
    "iso:country":"US",
    "sg:address":"536 Mantua Pike",
    "sg:city":"Woodbury",
    "sg:classifiers":[
        {
            "category":"Restaurant",
            "type":"Food & Drink"
        }
    ],
    "sg:menulink":"http://www.allmenus.com/nj/woodbury/82486-dominos-pizza/menu/",
    "sg:phone":"+1 856 845 6444",
    "sg:postcode":"08096",
    "sg:province":"NJ",
    "sg:tags":[
        "american",
        "wing",
        "pizza"
    ],
    "wof:name":"Domino's Pizza",
    "wof:placetype":"venue"
},
  "geometry": {"coordinates":[-75.15847100000001,39.829096],"type":"Point"}
}