{
  "type": "Feature",
  "properties": {
    "iso:country":"US",
    "sg:address":"261 Halsey St",
    "sg:city":"Newark",
    "sg:classifiers":[
        {
            "category":"Personal",
            "subcategory":"Beauty Salon",
            "type":"Services"
        }
    ],
    "sg:phone":"+1 973 242 5115",
    "sg:postcode":"07102",
    "sg:province":"NJ",
    "sg:tags":[
        "shop"
    ],
    "wof:name":"Krystyles Cuts Studio Designs",
    "wof:placetype":"venue"
},
  "geometry": {"coordinates":[-74.175432,40.733242],"type":"Point"}
}