{
  "type": "Feature",
  "properties": {
    "iso:country":"US",
    "sg:address":"118 W End Ave",
    "sg:city":"Summit",
    "sg:classifiers":[
        {
            "category":"Building & Trades",
            "subcategory":"Construction",
            "type":"Services"
        }
    ],
    "sg:phone":"+1 908 273 7487",
    "sg:postcode":"07901",
    "sg:province":"NJ",
    "sg:tags":[
        "floor",
        "laying",
        "contractor"
    ],
    "wof:name":"Floorshine Floors",
    "wof:placetype":"venue"
},
  "geometry": {"coordinates":[-74.376363,40.718887],"type":"Point"}
}