{
  "type": "Feature",
  "properties": {
    "addr:full":"117 Smith St Perth Amboy NJ 08861",
    "addr:housenumber":"117",
    "addr:postcode":"08861",
    "addr:street":"Smith St",
    "iso:country":"US",
    "sg:address":"117 Smith St",
    "sg:city":"Perth Amboy",
    "sg:classifiers":[
        {
            "category":"Shopping",
            "subcategory":"Beauty & Cosmetics",
            "type":"Retail Goods"
        }
    ],
    "sg:phone":"+1 732 826 7800",
    "sg:postcode":"08861",
    "sg:province":"NJ",
    "sg:tags":[
        "supply"
    ],
    "wof:name":"Canela Beauty Supply",
    "wof:placetype":"venue"
},
  "geometry": {"coordinates":[-74.267899,40.5084],"type":"Point"}
}