{
  "type": "Feature",
  "properties": {
    "iso:country":"US",
    "sg:address":"600 Summit Ave",
    "sg:city":"Union City",
    "sg:classifiers":[
        {
            "category":"Restaurant",
            "type":"Food & Drink"
        }
    ],
    "sg:phone":"+1 201 330 9898",
    "sg:postcode":"07087",
    "sg:province":"NJ",
    "wof:name":"Papi's Pizza",
    "wof:placetype":"venue"
},
  "geometry": {"coordinates":[-74.044079,40.758067],"type":"Point"}
}