{
  "type": "Feature",
  "properties": {
    "iso:country":"US",
    "sg:address":"15 Overlook Dr",
    "sg:city":"Clinton",
    "sg:classifiers":[
        {
            "category":"Utilities",
            "subcategory":"Telephone",
            "type":"Services"
        }
    ],
    "sg:phone":"+1 908 730 8474",
    "sg:postcode":"08809",
    "sg:province":"NJ",
    "sg:tags":[
        "communications"
    ],
    "wof:name":"Daniel Coulthard",
    "wof:placetype":"venue"
},
  "geometry": {"coordinates":[-74.934415,40.634879],"type":"Point"}
}