{
  "type": "Feature",
  "properties": {
    "iso:country":"US",
    "sg:address":"726 Oak Glen Rd",
    "sg:city":"Howell",
    "sg:classifiers":[
        {
            "category":"Professional",
            "subcategory":"Business Services",
            "type":"Services"
        }
    ],
    "sg:phone":"+1   ",
    "sg:postcode":"07731",
    "sg:province":"NJ",
    "wof:name":"Penny Landscaping Powerwa",
    "wof:placetype":"venue"
},
  "geometry": {"coordinates":[-74.18171100000001,40.116276],"type":"Point"}
}