{
  "type": "Feature",
  "properties": {
    "iso:country":"US",
    "sg:address":"194 Sayre Dr",
    "sg:city":"Princeton",
    "sg:classifiers":[
        {
            "category":"Health Services",
            "subcategory":"Doctor",
            "type":"Services"
        }
    ],
    "sg:phone":"+1 609 919 1770",
    "sg:postcode":"08540",
    "sg:province":"NJ",
    "sg:tags":[
        "physician",
        "surgeon"
    ],
    "wof:name":"Arthur Rudy MD",
    "wof:placetype":"venue"
},
  "geometry": {"coordinates":[-74.619157,40.350665],"type":"Point"}
}