{
  "type": "Feature",
  "properties": {
    "iso:country":"US",
    "sg:address":"249 Twin Lakes Blvd",
    "sg:city":"Tuckerton",
    "sg:classifiers":[
        {
            "category":"Manufacturing",
            "subcategory":"Glass & Minerals",
            "type":"Manufacturing & Wholesale Goods"
        }
    ],
    "sg:phone":"+1 609 294 9435",
    "sg:postcode":"08087",
    "sg:province":"NJ",
    "sg:tags":[
        "ready",
        "concrete",
        "mfg"
    ],
    "wof:name":"Moving Labor Ready",
    "wof:placetype":"venue"
},
  "geometry": {"coordinates":[-74.37337599999999,39.575198],"type":"Point"}
}