{
  "type": "Feature",
  "properties": {
    "iso:country":"US",
    "sg:address":"20 Cotswold Cir",
    "sg:city":"Asbury Park",
    "sg:classifiers":[
        {
            "category":"Health Services",
            "subcategory":"Doctor",
            "type":"Services"
        }
    ],
    "sg:phone":"+1 732 493 3234",
    "sg:postcode":"07712",
    "sg:province":"NJ",
    "sg:tags":[
        "medical"
    ],
    "wof:name":"Ziad Ambhud MD",
    "wof:placetype":"venue"
},
  "geometry": {"coordinates":[-74.050066,40.258963],"type":"Point"}
}