{
  "type": "Feature",
  "properties": {
    "iso:country":"US",
    "sg:address":"101 E Sheffield Ave",
    "sg:city":"Englewood",
    "sg:classifiers":[
        {
            "category":"Building & Trades",
            "subcategory":"Cleaning & Sanitation",
            "type":"Services"
        }
    ],
    "sg:phone":"+1 201 871 3003",
    "sg:postcode":"07631",
    "sg:province":"NJ",
    "sg:tags":[
        "window"
    ],
    "wof:name":"American Eagle Window Clean",
    "wof:placetype":"venue"
},
  "geometry": {"coordinates":[-73.981977,40.87534],"type":"Point"}
}