{
  "type": "Feature",
  "properties": {
    "iso:country":"US",
    "sg:address":"46 Wood St",
    "sg:city":"Garfield",
    "sg:classifiers":[
        {
            "category":"Food & Beverages",
            "subcategory":"Liquor & Beverages",
            "type":"Retail Goods"
        }
    ],
    "sg:phone":"+1 973 478 3772",
    "sg:postcode":"07026",
    "sg:province":"NJ",
    "sg:tags":[
        "beer",
        "spirit",
        "wine"
    ],
    "wof:name":"Garfield Liquor & Bar",
    "wof:placetype":"venue"
},
  "geometry": {"coordinates":[-74.108902,40.8866],"type":"Point"}
}