{
  "type": "Feature",
  "properties": {
    "iso:country":"US",
    "sg:address":"138 Terrace Dr",
    "sg:city":"Chatham",
    "sg:classifiers":[
        {
            "category":"Professional",
            "subcategory":"Management & Consulting",
            "type":"Services"
        }
    ],
    "sg:phone":"+1   ",
    "sg:postcode":"07928",
    "sg:province":"NJ",
    "wof:name":"Orbis International",
    "wof:placetype":"venue"
},
  "geometry": {"coordinates":[-74.396225,40.720147],"type":"Point"}
}