{
  "type": "Feature",
  "properties": {
    "iso:country":"US",
    "sg:address":"1014 State Rte 33",
    "sg:city":"Freehold",
    "sg:classifiers":[
        {
            "category":"Building & Trades",
            "subcategory":"Plumbing",
            "type":"Services"
        }
    ],
    "sg:phone":"+1 732 308 9592",
    "sg:postcode":"07728",
    "sg:province":"NJ",
    "sg:tags":[
        "heating",
        "contractor"
    ],
    "wof:name":"Robert T Schmitt Heating & Air",
    "wof:placetype":"venue"
},
  "geometry": {"coordinates":[-74.20325699999999,40.229188],"type":"Point"}
}