{
  "type": "Feature",
  "properties": {
    "addr:full":"836 Mantua Blvd Sewell NJ 08080",
    "addr:housenumber":"836",
    "addr:postcode":"08080",
    "addr:street":"Mantua Blvd",
    "iso:country":"US",
    "sg:address":"836 Mantua Blvd",
    "sg:city":"Sewell",
    "sg:classifiers":[
        {
            "category":"Professional",
            "subcategory":"Engineering",
            "type":"Services"
        },
        {
            "category":"Building & Trades",
            "subcategory":"Construction",
            "type":"Services"
        }
    ],
    "sg:phone":"+1 856 468 2355",
    "sg:postcode":"08080",
    "sg:province":"NJ",
    "sg:tags":[
        "repair",
        "management",
        "energy",
        "systems-service",
        "equipment",
        "solar",
        "engineer"
    ],
    "wof:name":"Onpeak Solar Inc",
    "wof:placetype":"venue"
},
  "geometry": {"coordinates":[-75.13977199999999,39.766789],"type":"Point"}
}