{
  "type": "Feature",
  "properties": {
    "addr:full":"128 Sussex St Jersey City NJ 07302",
    "addr:housenumber":"128",
    "addr:postcode":"07302",
    "addr:street":"Sussex St",
    "iso:country":"US",
    "sg:address":"128 Sussex St",
    "sg:city":"Jersey City",
    "sg:classifiers":[
        {
            "category":"Banks & Credit Unions",
            "subcategory":"Bank",
            "type":"Services"
        }
    ],
    "sg:phone":"+1 201 333 9909",
    "sg:postcode":"07302",
    "sg:province":"NJ",
    "sg:tags":[
        "money",
        "transfer"
    ],
    "wof:name":"Emoney Tran",
    "wof:placetype":"venue"
},
  "geometry": {"coordinates":[-74.04115899999999,40.714981],"type":"Point"}
}