{
  "type": "Feature",
  "properties": {
    "addr:full":"1018 Broad St Bloomfield NJ 07003",
    "addr:housenumber":"1018",
    "addr:postcode":"07003",
    "addr:street":"Broad St",
    "iso:country":"US",
    "sg:address":"1018 Broad St",
    "sg:city":"Bloomfield",
    "sg:classifiers":[
        {
            "category":"Health Services",
            "subcategory":"Doctor",
            "type":"Services"
        }
    ],
    "sg:phone":"+1 973 338 3300",
    "sg:postcode":"07003",
    "sg:province":"NJ",
    "wof:name":"Carluccio Joseph MD",
    "wof:placetype":"venue"
},
  "geometry": {"coordinates":[-74.18789700000001,40.826801],"type":"Point"}
}