{
  "type": "Feature",
  "properties": {
    "addr:full":"35 Heman St Edison NJ 08837",
    "addr:housenumber":"35",
    "addr:postcode":"08837",
    "addr:street":"Heman St",
    "iso:country":"US",
    "sg:address":"35 Heman St",
    "sg:city":"Edison",
    "sg:classifiers":[
        {
            "category":"Health Services",
            "subcategory":"Clinic",
            "type":"Services"
        }
    ],
    "sg:phone":"+1   ",
    "sg:postcode":"08837",
    "sg:province":"NJ",
    "sg:tags":[
        "counseling"
    ],
    "wof:name":"Holistic Health Concepts",
    "wof:placetype":"venue"
},
  "geometry": {"coordinates":[-74.348463,40.528272],"type":"Point"}
}