{
  "type": "Feature",
  "properties": {
    "addr:full":"8 Martin Pl Chatham NJ 07928",
    "addr:housenumber":"8",
    "addr:postcode":"07928",
    "addr:street":"Martin Pl",
    "iso:country":"US",
    "sg:address":"8 Martin Pl",
    "sg:city":"Chatham",
    "sg:classifiers":[
        {
            "category":"Professional",
            "subcategory":"Business Services",
            "type":"Services"
        }
    ],
    "sg:phone":"+1 973 701 9218",
    "sg:postcode":"07928",
    "sg:province":"NJ",
    "wof:name":"Frank Truilo Assoc",
    "wof:placetype":"venue"
},
  "geometry": {"coordinates":[-74.388867,40.743896],"type":"Point"}
}