{
  "type": "Feature",
  "properties": {
    "addr:full":"1354 River Rd Teaneck NJ 07666",
    "addr:housenumber":"1354",
    "addr:postcode":"07666",
    "addr:street":"River Rd",
    "iso:country":"US",
    "sg:address":"1354 River Rd",
    "sg:city":"Teaneck",
    "sg:classifiers":[
        {
            "category":"Insurance",
            "subcategory":"Insurance Agent",
            "type":"Services"
        }
    ],
    "sg:phone":"+1   ",
    "sg:postcode":"07666",
    "sg:province":"NJ",
    "wof:name":"Goldfischer Financial Services",
    "wof:placetype":"venue"
},
  "geometry": {"coordinates":[-74.024215,40.905279],"type":"Point"}
}