{
  "type": "Feature",
  "properties": {
    "iso:country":"US",
    "sg:address":"555 Main St",
    "sg:city":"Fort Lee",
    "sg:classifiers":[
        {
            "category":"Restaurant",
            "type":"Food & Drink"
        }
    ],
    "sg:phone":"+1 201 585 8811",
    "sg:postcode":"07024",
    "sg:province":"NJ",
    "sg:tags":[
        "chinese"
    ],
    "wof:name":"Joyce Chinese",
    "wof:placetype":"venue"
},
  "geometry": {"coordinates":[-73.979586,40.857285],"type":"Point"}
}