{
  "type": "Feature",
  "properties": {
    "addr:full":"100 Railroad Ave Paterson NJ 07501",
    "addr:housenumber":"100",
    "addr:postcode":"07501",
    "addr:street":"Railroad Ave",
    "iso:country":"US",
    "sg:address":"100 Railroad Ave",
    "sg:city":"Paterson",
    "sg:classifiers":[
        {
            "category":"Food & Beverages",
            "subcategory":"Cheese",
            "type":"Retail Goods"
        },
        {
            "category":"Ice Cream",
            "type":"Food & Drink"
        }
    ],
    "sg:phone":"+1 973 523 2001",
    "sg:postcode":"07501",
    "sg:province":"NJ",
    "sg:tags":[
        "shop",
        "frozen",
        "yogurt"
    ],
    "wof:name":"Romi's Farm Product",
    "wof:placetype":"venue"
},
  "geometry": {"coordinates":[-74.16799899999999,40.9086],"type":"Point"}
}