{
  "type": "Feature",
  "properties": {
    "iso:country":"US",
    "sg:address":"22 Browning Ave",
    "sg:city":"Bayville",
    "sg:classifiers":[
        {
            "category":"Building & Trades",
            "subcategory":"Construction",
            "type":"Services"
        }
    ],
    "sg:phone":"+1 732 604 2095",
    "sg:postcode":"08721",
    "sg:province":"NJ",
    "sg:tags":[
        "house"
    ],
    "wof:name":"B & M Home Improvements",
    "wof:placetype":"venue"
},
  "geometry": {"coordinates":[-74.161708,39.926044],"type":"Point"}
}