{
  "type": "Feature",
  "properties": {
    "addr:full":"268 Merion Ave Haddonfield NJ 08033",
    "addr:housenumber":"268",
    "addr:postcode":"08033",
    "addr:street":"Merion Ave",
    "iso:country":"US",
    "sg:address":"268 Merion Ave",
    "sg:city":"Haddonfield",
    "sg:classifiers":[
        {
            "category":"Professional",
            "subcategory":"Employment Agencies",
            "type":"Services"
        }
    ],
    "sg:phone":"+1 856 616 2978",
    "sg:postcode":"08033",
    "sg:province":"NJ",
    "wof:name":"Global Recruiters Network Of W",
    "wof:placetype":"venue"
},
  "geometry": {"coordinates":[-75.033413,39.905651],"type":"Point"}
}