{
  "type": "Feature",
  "properties": {
    "iso:country":"US",
    "sg:address":"10 Jay St",
    "sg:city":"Englewood",
    "sg:classifiers":[
        {
            "category":"Personal",
            "subcategory":"Beauty Salon",
            "type":"Services"
        }
    ],
    "sg:phone":"+1 201 568 8378",
    "sg:postcode":"07631",
    "sg:province":"NJ",
    "sg:tags":[
        "nail",
        "shop"
    ],
    "wof:name":"Elegant Endings By Janis",
    "wof:placetype":"venue"
},
  "geometry": {"coordinates":[-73.977654,40.891393],"type":"Point"}
}