{
  "type": "Feature",
  "properties": {
    "iso:country":"US",
    "sg:address":"166 Salem Rd",
    "sg:city":"North Brunswick",
    "sg:classifiers":[
        {
            "category":"Retail",
            "subcategory":"Repair Shop",
            "type":"Services"
        }
    ],
    "sg:phone":"+1   ",
    "sg:postcode":"08902",
    "sg:province":"NJ",
    "sg:tags":[
        "electrical"
    ],
    "wof:name":"Integrity Appliance Servi",
    "wof:placetype":"venue"
},
  "geometry": {"coordinates":[-74.487002,40.438382],"type":"Point"}
}