{
  "type": "Feature",
  "properties": {
    "addr:full":"980 Somerset St New Brunswick NJ 08901",
    "addr:housenumber":"980",
    "addr:postcode":"08901",
    "addr:street":"Somerset St",
    "iso:country":"US",
    "sg:address":"980 Somerset St",
    "sg:city":"New Brunswick",
    "sg:classifiers":[
        {
            "category":"Food & Beverages",
            "subcategory":"Groceries & Convenience Stores",
            "type":"Retail Goods"
        }
    ],
    "sg:phone":"+1 732 000 1111",
    "sg:postcode":"08901",
    "sg:province":"NJ",
    "sg:tags":[
        "grocer"
    ],
    "wof:name":"Aldi",
    "wof:placetype":"venue"
},
  "geometry": {"coordinates":[-74.45940899999999,40.491245],"type":"Point"}
}