{
  "type": "Feature",
  "properties": {
    "addr:full":"176 Kansas St Hackensack NJ 07601",
    "addr:housenumber":"176",
    "addr:postcode":"07601",
    "addr:street":"Kansas St",
    "iso:country":"US",
    "sg:address":"176 Kansas St",
    "sg:city":"Hackensack",
    "sg:classifiers":[
        {
            "category":"Home & Garden",
            "subcategory":"Home Furnishings",
            "type":"Retail Goods"
        }
    ],
    "sg:phone":"+1 201 525 0222",
    "sg:postcode":"07601",
    "sg:province":"NJ",
    "sg:tags":[
        "blind",
        "curtain",
        "made",
        "drapery",
        "shade"
    ],
    "wof:name":"Lvc Window Blinds & Drapery Inc",
    "wof:placetype":"venue"
},
  "geometry": {"coordinates":[-74.050499,40.877399],"type":"Point"}
}