{
  "type": "Feature",
  "properties": {
    "iso:country":"US",
    "sg:address":"57 Oakley Ter",
    "sg:city":"Nutley",
    "sg:classifiers":[
        {
            "category":"Wholesale",
            "subcategory":"Vending Machines",
            "type":"Manufacturing & Wholesale Goods"
        }
    ],
    "sg:phone":"+1   ",
    "sg:postcode":"07110",
    "sg:province":"NJ",
    "sg:tags":[
        "operator"
    ],
    "wof:name":"Rainbow Vending Co",
    "wof:placetype":"venue"
},
  "geometry": {"coordinates":[-74.16073299999999,40.833052],"type":"Point"}
}