{
  "type": "Feature",
  "properties": {
    "iso:country":"US",
    "sg:address":"7 E Broad St",
    "sg:city":"Palmyra",
    "sg:classifiers":[
        {
            "category":"Personal",
            "type":"Services"
        },
        {
            "category":"Retail",
            "subcategory":"Portrait Studio",
            "type":"Services"
        },
        {
            "category":"Professional",
            "subcategory":"Art Services",
            "type":"Services"
        }
    ],
    "sg:phone":"+1 856 829 6767",
    "sg:postcode":"08065",
    "sg:province":"NJ",
    "sg:tags":[
        "photographers-portrait",
        "videography",
        "darkroom",
        "rental",
        "photography",
        "wedding",
        "photographic"
    ],
    "wof:name":"Renaissance Photography",
    "wof:placetype":"venue"
},
  "geometry": {"coordinates":[-75.021698,40.004106],"type":"Point"}
}