{
  "type": "Feature",
  "properties": {
    "iso:country":"US",
    "sg:address":"438 Springfield Ave",
    "sg:city":"Berkeley Heights",
    "sg:classifiers":[
        {
            "category":"Personal",
            "subcategory":"Massage",
            "type":"Services"
        }
    ],
    "sg:phone":"+1 908 464 4068",
    "sg:postcode":"07922",
    "sg:province":"NJ",
    "wof:name":"Rasmussen Massage Therapist",
    "wof:placetype":"venue"
},
  "geometry": {"coordinates":[-74.431099,40.676102],"type":"Point"}
}