{
  "type": "Feature",
  "properties": {
    "iso:country":"US",
    "sg:address":"400 Creek Road",
    "sg:city":"Riverside",
    "sg:classifiers":[
        {
            "category":"Government",
            "subcategory":"Department Of Motor Vehicles",
            "type":"Public Place"
        }
    ],
    "sg:postcode":"08075",
    "sg:province":"NJ",
    "wof:name":"NJ Motor Vehicle Inspection Center",
    "wof:placetype":"venue"
},
  "geometry": {"coordinates":[-74.9372,40.0449],"type":"Point"}
}