{
  "type": "Feature",
  "properties": {
    "addr:full":"699 Irish Hill Rd Runnemede NJ 08078",
    "addr:housenumber":"699",
    "addr:postcode":"08078",
    "addr:street":"Irish Hill Rd",
    "iso:country":"US",
    "sg:address":"699 Irish Hill Rd",
    "sg:city":"Runnemede",
    "sg:classifiers":[
        {
            "category":"Building & Trades",
            "subcategory":"Locksmith",
            "type":"Services"
        }
    ],
    "sg:phone":"+1 856 208 4028",
    "sg:postcode":"08078",
    "sg:province":"NJ",
    "sg:tags":[
        "key"
    ],
    "wof:name":"One Eight Hundred Locksmith",
    "wof:placetype":"venue"
},
  "geometry": {"coordinates":[-75.068348,39.8565],"type":"Point"}
}