{
  "type": "Feature",
  "properties": {
    "iso:country":"US",
    "sg:address":"26 E Madison Ave",
    "sg:city":"Dumont",
    "sg:classifiers":[
        {
            "category":"Retail",
            "subcategory":"Car Wash",
            "type":"Services"
        },
        {
            "category":"Building & Trades",
            "subcategory":"Construction",
            "type":"Services"
        }
    ],
    "sg:phone":"+1 201 244 1234",
    "sg:postcode":"07628",
    "sg:province":"NJ",
    "sg:tags":[
        "automobile",
        "detail",
        "clean",
        "contractor"
    ],
    "wof:name":"Madison Avenue Auto Salon",
    "wof:placetype":"venue"
},
  "geometry": {"coordinates":[-73.99333799999999,40.940527],"type":"Point"}
}