{
  "type": "Feature",
  "properties": {
    "iso:country":"US",
    "sg:address":"719 Franklin Ave",
    "sg:city":"Franklin Lakes",
    "sg:classifiers":[
        {
            "category":"Health Services",
            "subcategory":"Chiropractor",
            "type":"Services"
        }
    ],
    "sg:phone":"+1 201 891 6100",
    "sg:postcode":"07417",
    "sg:province":"NJ",
    "wof:name":"Michael W Golz Dr",
    "wof:placetype":"venue"
},
  "geometry": {"coordinates":[-74.201725,41.018321],"type":"Point"}
}