{
  "type": "Feature",
  "properties": {
    "addr:full":"301 60th St West New York NJ 07093",
    "addr:housenumber":"301",
    "addr:postcode":"nj 07093",
    "addr:street":"60Th St West",
    "iso:country":"US",
    "sg:address":"301 60th St",
    "sg:city":"West New York",
    "sg:classifiers":[
        {
            "category":"Health Services",
            "subcategory":"Health Practitioner",
            "type":"Services"
        }
    ],
    "sg:phone":"+1 201 758 9170",
    "sg:postcode":"07093",
    "sg:province":"NJ",
    "sg:tags":[
        "nurse",
        "registry"
    ],
    "sg:website":"www.nursefinders.com",
    "wof:name":"Nursefinders",
    "wof:placetype":"venue"
},
  "geometry": {"coordinates":[-74.013352,40.787438],"type":"Point"}
}