{
  "type": "Feature",
  "properties": {
    "iso:country":"US",
    "sg:address":"935 Washington St",
    "sg:city":"Hoboken",
    "sg:classifiers":[
        {
            "category":"Professional",
            "subcategory":"Lawyer & Legal Services",
            "type":"Services"
        }
    ],
    "sg:phone":"+1 212 877 2550",
    "sg:postcode":"07030",
    "sg:province":"NJ",
    "wof:name":"EBEC Legal Search",
    "wof:placetype":"venue"
},
  "geometry": {"coordinates":[-74.027534,40.748092],"type":"Point"}
}