{
  "type": "Feature",
  "properties": {
    "addr:full":"475 Washington Ave Belleville NJ 07109",
    "addr:housenumber":"475",
    "addr:postcode":"07109",
    "addr:street":"Washington Ave",
    "iso:country":"US",
    "sg:address":"475 Washington Ave",
    "sg:city":"Belleville",
    "sg:classifiers":[
        {
            "category":"Real Estate",
            "subcategory":"Real Estate Agent",
            "type":"Services"
        }
    ],
    "sg:phone":"+1 201 997 2550",
    "sg:postcode":"07109",
    "sg:province":"NJ",
    "wof:name":"Riverstone Realty LLC",
    "wof:placetype":"venue"
},
  "geometry": {"coordinates":[-74.148883,40.796248],"type":"Point"}
}