{
  "type": "Feature",
  "properties": {
    "iso:country":"US",
    "sg:address":"357 Hedge Row",
    "sg:city":"Mountainside",
    "sg:classifiers":[
        {
            "category":"Professional",
            "subcategory":"Management & Consulting",
            "type":"Services"
        }
    ],
    "sg:phone":"+1 908 518 0183",
    "sg:postcode":"07092",
    "sg:province":"NJ",
    "sg:tags":[
        "business"
    ],
    "wof:name":"Inter European Intl",
    "wof:placetype":"venue"
},
  "geometry": {"coordinates":[-74.35836399999999,40.681446],"type":"Point"}
}