{
  "type": "Feature",
  "properties": {
    "addr:full":"80 Bloomfield Ave Nutley NJ 07110",
    "addr:housenumber":"80",
    "addr:postcode":"07110",
    "addr:street":"Bloomfield Ave",
    "iso:country":"US",
    "sg:address":"80 Bloomfield Ave",
    "sg:city":"Nutley",
    "sg:classifiers":[
        {
            "category":"Health Services",
            "subcategory":"Chiropractor",
            "type":"Services"
        }
    ],
    "sg:phone":"+1 973 235 0703",
    "sg:postcode":"07110",
    "sg:province":"NJ",
    "wof:name":"Scarpelli Joseph P DC",
    "wof:placetype":"venue"
},
  "geometry": {"coordinates":[-74.17379800000001,40.811798],"type":"Point"}
}