{
  "type": "Feature",
  "properties": {
    "iso:country":"US",
    "sg:address":"121 W Jersey Ave",
    "sg:city":"Pitman",
    "sg:classifiers":[
        {
            "category":"Professional",
            "subcategory":"Business Services",
            "type":"Services"
        }
    ],
    "sg:phone":"+1   ",
    "sg:postcode":"08071",
    "sg:province":"NJ",
    "wof:name":"Sharon M Gallinelli",
    "wof:placetype":"venue"
},
  "geometry": {"coordinates":[-75.128305,39.730646],"type":"Point"}
}