{
  "type": "Feature",
  "properties": {
    "iso:country":"US",
    "sg:address":"14 Holmes St",
    "sg:city":"Belleville",
    "sg:classifiers":[
        {
            "category":"Retail",
            "subcategory":"Auto Repair",
            "type":"Services"
        }
    ],
    "sg:phone":"+1 973 751 1271",
    "sg:postcode":"07109",
    "sg:province":"NJ",
    "sg:tags":[
        "body",
        "shop"
    ],
    "wof:name":"P J's Valley Auto Body & Service",
    "wof:placetype":"venue"
},
  "geometry": {"coordinates":[-74.14679700000001,40.789902],"type":"Point"}
}