{
  "type": "Feature",
  "properties": {
    "addr:full":"200 Harbor Rd Marmora NJ 08223",
    "addr:housenumber":"200",
    "addr:postcode":"08223",
    "addr:street":"Harbor Rd",
    "iso:country":"US",
    "sg:address":"200 Harbor Rd",
    "sg:city":"Marmora",
    "sg:classifiers":[
        {
            "category":"Building & Trades",
            "subcategory":"Construction",
            "type":"Services"
        }
    ],
    "sg:phone":"+1 609 390 0311",
    "sg:postcode":"08223",
    "sg:province":"NJ",
    "sg:tags":[
        "marine",
        "contractor"
    ],
    "wof:name":"Davenport & Lord Inc",
    "wof:placetype":"venue"
},
  "geometry": {"coordinates":[-74.62027399999999,39.286114],"type":"Point"}
}