{
  "type": "Feature",
  "properties": {
    "addr:full":"110 Newton Ave Oaklyn NJ 08107",
    "addr:housenumber":"110",
    "addr:postcode":"08107",
    "addr:street":"Newton Ave",
    "iso:country":"US",
    "sg:address":"110 Newton Ave",
    "sg:city":"Oaklyn",
    "sg:classifiers":[
        {
            "category":"Health Services",
            "subcategory":"Doctor",
            "type":"Services"
        }
    ],
    "sg:phone":"+1 856 854 6025",
    "sg:postcode":"08107",
    "sg:province":"NJ",
    "sg:tags":[
        "medical"
    ],
    "wof:name":"Herbert M Marks MD",
    "wof:placetype":"venue"
},
  "geometry": {"coordinates":[-75.082556,39.905424],"type":"Point"}
}