{
  "type": "Feature",
  "properties": {
    "iso:country":"US",
    "sg:address":"220 Arbor St",
    "sg:city":"Cranford",
    "sg:classifiers":[
        {
            "category":"Professional",
            "type":"Services"
        }
    ],
    "sg:phone":"+1 908 276 0424",
    "sg:postcode":"07016",
    "sg:province":"NJ",
    "sg:tags":[
        "establishment"
    ],
    "wof:name":"Amex Joseph Norton",
    "wof:placetype":"venue"
},
  "geometry": {"coordinates":[-74.300539,40.671149],"type":"Point"}
}