{
  "type": "Feature",
  "properties": {
    "addr:full":"176 Cokesbury Rd Lebanon NJ 08833",
    "addr:housenumber":"176",
    "addr:postcode":"08833",
    "addr:street":"Cokesbury Rd",
    "iso:country":"US",
    "sg:address":"176 Cokesbury Rd",
    "sg:city":"Lebanon",
    "sg:classifiers":[
        {
            "category":"Retail",
            "subcategory":"Pet Boarding",
            "type":"Services"
        }
    ],
    "sg:phone":"+1 908 236 2544",
    "sg:postcode":"08833",
    "sg:province":"NJ",
    "sg:tags":[
        "boarding/pet",
        "sitting"
    ],
    "wof:name":"Dianne's Dogpatch",
    "wof:placetype":"venue"
},
  "geometry": {"coordinates":[-74.827003,40.6637],"type":"Point"}
}