{
  "type": "Feature",
  "properties": {
    "iso:country":"US",
    "sg:address":"34 Farley Pl",
    "sg:city":"Short Hills",
    "sg:classifiers":[
        {
            "category":"Personal",
            "subcategory":"Beauty Salon",
            "type":"Services"
        }
    ],
    "sg:phone":"+1 973 379 3898",
    "sg:postcode":"07078",
    "sg:province":"NJ",
    "sg:tags":[
        "shop"
    ],
    "wof:name":"Shear Sophistication Inc",
    "wof:placetype":"venue"
},
  "geometry": {"coordinates":[-74.325391,40.717713],"type":"Point"}
}