{
  "type": "Feature",
  "properties": {
    "addr:full":"7 Patten Pl Newark NJ 07112",
    "addr:housenumber":"7",
    "addr:postcode":"07112",
    "addr:street":"Patten Pl",
    "iso:country":"US",
    "sg:address":"7 Patten Pl",
    "sg:city":"Newark",
    "sg:classifiers":[
        {
            "category":"Professional",
            "subcategory":"Management & Consulting",
            "type":"Services"
        }
    ],
    "sg:phone":"+1 973 373 0461",
    "sg:postcode":"07112",
    "sg:province":"NJ",
    "wof:name":"Dufunk Management",
    "wof:placetype":"venue"
},
  "geometry": {"coordinates":[-74.209901,40.717466],"type":"Point"}
}