{
  "type": "Feature",
  "properties": {
    "iso:country":"US",
    "sg:address":"119 Hill Pl",
    "sg:city":"Watchung",
    "sg:classifiers":[
        {
            "category":"Professional",
            "subcategory":"Management & Consulting",
            "type":"Services"
        }
    ],
    "sg:phone":"+1 908 769 5066",
    "sg:postcode":"07069",
    "sg:province":"NJ",
    "sg:tags":[
        "consultant"
    ],
    "wof:name":"Nantron Associates",
    "wof:placetype":"venue"
},
  "geometry": {"coordinates":[-74.461308,40.638405],"type":"Point"}
}