{
  "type": "Feature",
  "properties": {
    "iso:country":"US",
    "sg:address":"505 42nd St",
    "sg:city":"Union City",
    "sg:classifiers":[
        {
            "category":"Wholesale",
            "subcategory":"Tobacco Products",
            "type":"Manufacturing & Wholesale Goods"
        }
    ],
    "sg:phone":"+1 201 864 2627",
    "sg:postcode":"07087",
    "sg:province":"NJ",
    "sg:tags":[
        "cigar",
        "mfg"
    ],
    "wof:name":"La Isla Cigar",
    "wof:placetype":"venue"
},
  "geometry": {"coordinates":[-74.027317,40.778489],"type":"Point"}
}