{
  "type": "Feature",
  "properties": {
    "iso:country":"US",
    "sg:address":"607 Oak Crest Ave",
    "sg:city":"Linwood",
    "sg:classifiers":[
        {
            "category":"Professional",
            "type":"Services"
        }
    ],
    "sg:phone":"+1   ",
    "sg:postcode":"08221",
    "sg:province":"NJ",
    "wof:name":"Pops Pepper Products Inc",
    "wof:placetype":"venue"
},
  "geometry": {"coordinates":[-74.569659,39.363022],"type":"Point"}
}