{
  "type": "Feature",
  "properties": {
    "iso:country":"US",
    "sg:address":"667 Ave A",
    "sg:city":"Bayonne",
    "sg:classifiers":[
        {
            "category":"Education",
            "subcategory":"School",
            "type":"Public Place"
        }
    ],
    "sg:phone":"+1 201 858 5900",
    "sg:postcode":"07002",
    "sg:province":"NJ",
    "wof:name":"Bayonne High School",
    "wof:placetype":"venue"
},
  "geometry": {"coordinates":[-74.121297,40.671297],"type":"Point"}
}