{
  "type": "Feature",
  "properties": {
    "iso:country":"US",
    "sg:address":"56 US Highway 22",
    "sg:city":"Hillside",
    "sg:classifiers":[
        {
            "category":"Autos & Motor Vehicles",
            "subcategory":"Automobile Sales",
            "type":"Retail Goods"
        }
    ],
    "sg:phone":"+1 973 923 9300",
    "sg:postcode":"07112",
    "sg:province":"NJ",
    "sg:tags":[
        "car"
    ],
    "sg:website":"gsnewford.com",
    "wof:name":"Garden State Auto Plaza",
    "wof:placetype":"venue"
},
  "geometry": {"coordinates":[-74.212434,40.699681],"type":"Point"}
}