{
  "type": "Feature",
  "properties": {
    "addr:full":"1508 Broadway Tpke Camden NJ 08104",
    "addr:housenumber":"1508",
    "addr:postcode":"08104",
    "addr:street":"Broadway Tpke",
    "iso:country":"US",
    "sg:address":"1508 Broadway Tpke",
    "sg:city":"Camden",
    "sg:classifiers":[
        {
            "category":"Building & Trades",
            "subcategory":"Landscaping Services",
            "type":"Services"
        }
    ],
    "sg:phone":"+1 856 964 9348",
    "sg:postcode":"08104",
    "sg:province":"NJ",
    "sg:tags":[
        "tree"
    ],
    "wof:name":"Vincent's Christmas Tree Mart",
    "wof:placetype":"venue"
},
  "geometry": {"coordinates":[-75.11956000000001,39.924965],"type":"Point"}
}