{
  "type": "Feature",
  "properties": {
    "addr:full":"7721 Pleasure Ave Sea Isle City NJ 08243",
    "addr:housenumber":"7721",
    "addr:postcode":"08243",
    "addr:street":"Pleasure Ave",
    "iso:country":"US",
    "sg:address":"7721 Pleasure Ave",
    "sg:city":"Sea Isle City",
    "sg:classifiers":[
        {
            "category":"Real Estate",
            "subcategory":"Real Estate Operator",
            "type":"Services"
        }
    ],
    "sg:phone":"+1   ",
    "sg:postcode":"08243",
    "sg:province":"NJ",
    "sg:tags":[
        "property",
        "lessor"
    ],
    "wof:name":"Sandcastle II Partnerships",
    "wof:placetype":"venue"
},
  "geometry": {"coordinates":[-74.705934,39.130877],"type":"Point"}
}