{
  "type": "Feature",
  "properties": {
    "iso:country":"US",
    "sg:address":"26 Chestnut St",
    "sg:city":"Beachwood",
    "sg:classifiers":[
        {
            "category":"Wholesale",
            "subcategory":"Electrical",
            "type":"Manufacturing & Wholesale Goods"
        }
    ],
    "sg:phone":"+1 732 797 0576",
    "sg:postcode":"08722",
    "sg:province":"NJ",
    "sg:tags":[
        "lighting"
    ],
    "wof:name":"JSM Stage Lighting",
    "wof:placetype":"venue"
},
  "geometry": {"coordinates":[-74.196308,39.922011],"type":"Point"}
}