{
  "type": "Feature",
  "properties": {
    "iso:country":"US",
    "sg:address":"26 Fraley Dr",
    "sg:city":"Somerset",
    "sg:classifiers":[
        {
            "category":"Organizations",
            "subcategory":"Religious Organization",
            "type":"Services"
        }
    ],
    "sg:phone":"+1   ",
    "sg:postcode":"08873",
    "sg:province":"NJ",
    "wof:name":"Bryan Miller Pastor",
    "wof:placetype":"venue"
},
  "geometry": {"coordinates":[-74.47533799999999,40.502553],"type":"Point"}
}