{
  "type": "Feature",
  "properties": {
    "iso:country":"US",
    "sg:address":"511 Washington St",
    "sg:city":"Cape May",
    "sg:classifiers":[
        {
            "category":"Shopping",
            "subcategory":"Jewelry",
            "type":"Retail Goods"
        }
    ],
    "sg:phone":"+1 609 898 8786",
    "sg:postcode":"08204",
    "sg:province":"NJ",
    "sg:tags":[
        "jeweler"
    ],
    "wof:name":"Maryann's",
    "wof:placetype":"venue"
},
  "geometry": {"coordinates":[-74.922096,38.933102],"type":"Point"}
}