{
  "type": "Feature",
  "properties": {
    "addr:full":"1926 Westfield Ave Scotch Plains NJ 07076",
    "addr:housenumber":"1926",
    "addr:postcode":"07076",
    "addr:street":"Westfield Ave",
    "iso:country":"US",
    "sg:address":"1926 Westfield Ave",
    "sg:city":"Scotch Plains",
    "sg:classifiers":[
        {
            "category":"Home & Garden",
            "subcategory":"Home Furnishings",
            "type":"Retail Goods"
        }
    ],
    "sg:phone":"+1   ",
    "sg:postcode":"07076",
    "sg:province":"NJ",
    "sg:tags":[
        "picture",
        "frame",
        "art",
        "dealer",
        "mirror"
    ],
    "wof:name":"Barrys Frame Sp & Art Gallery",
    "wof:placetype":"venue"
},
  "geometry": {"coordinates":[-74.39597500000001,40.649827],"type":"Point"}
}