{
  "type": "Feature",
  "properties": {
    "iso:country":"US",
    "sg:address":"21 Harrison Ave",
    "sg:city":"Red Bank",
    "sg:classifiers":[
        {
            "category":"Manufacturing",
            "subcategory":"Signs",
            "type":"Manufacturing & Wholesale Goods"
        }
    ],
    "sg:phone":"+1 732 933 4634",
    "sg:postcode":"07701",
    "sg:province":"NJ",
    "sg:tags":[
        "specialty",
        "mfg"
    ],
    "wof:name":"Capital Signs LLC",
    "wof:placetype":"venue"
},
  "geometry": {"coordinates":[-74.053799,40.355937],"type":"Point"}
}