{
  "type": "Feature",
  "properties": {
    "addr:full":"1319 Memorial Ave Atlantic City NJ 08401",
    "addr:housenumber":"1319",
    "addr:postcode":"08401",
    "addr:street":"Memorial Ave",
    "iso:country":"US",
    "sg:address":"1319 Memorial Ave",
    "sg:city":"Atlantic City",
    "sg:classifiers":[
        {
            "category":"Professional",
            "subcategory":"Art Services",
            "type":"Services"
        }
    ],
    "sg:phone":"+1 609 344 5057",
    "sg:postcode":"08401",
    "sg:province":"NJ",
    "sg:tags":[
        "silk",
        "screen",
        "printing"
    ],
    "wof:name":"Atlantic City Sportswear II",
    "wof:placetype":"venue"
},
  "geometry": {"coordinates":[-74.427244,39.360977],"type":"Point"}
}