{
  "type": "Feature",
  "properties": {
    "iso:country":"US",
    "sg:address":"830 Mount Prospect Ave",
    "sg:city":"Newark",
    "sg:classifiers":[
        {
            "category":"Deli",
            "type":"Food & Drink"
        }
    ],
    "sg:phone":"+1 973 878 2884",
    "sg:postcode":"07104",
    "sg:province":"NJ",
    "wof:name":"Pepe's Produce Market",
    "wof:placetype":"venue"
},
  "geometry": {"coordinates":[-74.16300200000001,40.780499],"type":"Point"}
}