{
  "type": "Feature",
  "properties": {
    "addr:full":"1511 43rd St North Bergen NJ 07047",
    "addr:housenumber":"1511",
    "addr:postcode":"07047",
    "addr:street":"43Rd St",
    "iso:country":"US",
    "sg:address":"1511 43rd St",
    "sg:city":"North Bergen",
    "sg:classifiers":[
        {
            "category":"Food & Beverages",
            "subcategory":"Groceries & Convenience Stores",
            "type":"Retail Goods"
        }
    ],
    "sg:phone":"+1   ",
    "sg:postcode":"07047",
    "sg:province":"NJ",
    "wof:name":"M Do 2000 Inc",
    "wof:placetype":"venue"
},
  "geometry": {"coordinates":[-74.03314399999999,40.782234],"type":"Point"}
}