{
  "type": "Feature",
  "properties": {
    "iso:country":"US",
    "sg:address":"270 Bank St",
    "sg:city":"Bridgeton",
    "sg:classifiers":[
        {
            "category":"Organizations",
            "subcategory":"Religious Organization",
            "type":"Services"
        }
    ],
    "sg:phone":"+1 856 455 3895",
    "sg:postcode":"08302",
    "sg:province":"NJ",
    "sg:tags":[
        "church"
    ],
    "wof:name":"Evangelistic World Church",
    "wof:placetype":"venue"
},
  "geometry": {"coordinates":[-75.227605,39.43554],"type":"Point"}
}