{
  "type": "Feature",
  "properties": {
    "iso:country":"US",
    "sg:address":"5 W Main St",
    "sg:city":"Bergenfield",
    "sg:classifiers":[
        {
            "category":"Personal",
            "subcategory":"Beauty Salon",
            "type":"Services"
        }
    ],
    "sg:phone":"+1 201 387 7644",
    "sg:postcode":"07621",
    "sg:province":"NJ",
    "sg:tags":[
        "shop"
    ],
    "wof:name":"Elma's Unisex Beauty Salon LLC",
    "wof:placetype":"venue"
},
  "geometry": {"coordinates":[-73.99720000000001,40.927934],"type":"Point"}
}