{
  "type": "Feature",
  "properties": {
    "iso:country":"US",
    "sg:address":"1 Frassetto Way",
    "sg:city":"Lincoln Park",
    "sg:classifiers":[
        {
            "category":"Wholesale",
            "subcategory":"Non-durable Goods",
            "type":"Manufacturing & Wholesale Goods"
        }
    ],
    "sg:phone":"+1 973 305 1000",
    "sg:postcode":"07035",
    "sg:province":"NJ",
    "sg:tags":[
        "premium",
        "advertising",
        "specialty"
    ],
    "wof:name":"Cmti Inc",
    "wof:placetype":"venue"
},
  "geometry": {"coordinates":[-74.28961099999999,40.917776],"type":"Point"}
}