{
  "type": "Feature",
  "properties": {
    "addr:full":"29 Parkway Maywood NJ 07607",
    "addr:housenumber":"29",
    "addr:postcode":"07607",
    "addr:street":"Parkway",
    "iso:country":"US",
    "sg:address":"29 Parkway",
    "sg:city":"Maywood",
    "sg:classifiers":[
        {
            "category":"Organizations",
            "subcategory":"Religious Organization",
            "type":"Services"
        }
    ],
    "sg:phone":"+1 201 843 5360",
    "sg:postcode":"07607",
    "sg:province":"NJ",
    "sg:tags":[
        "church"
    ],
    "wof:name":"Saint Martins Episcopal Church",
    "wof:placetype":"venue"
},
  "geometry": {"coordinates":[-74.06179,40.907365],"type":"Point"}
}