{
  "type": "Feature",
  "properties": {
    "iso:country":"US",
    "sg:address":"2 Holland Ter",
    "sg:city":"Trenton",
    "sg:classifiers":[
        {
            "category":"Building & Trades",
            "subcategory":"Construction",
            "type":"Services"
        }
    ],
    "sg:phone":"+1 609 585 7167",
    "sg:postcode":"08610",
    "sg:province":"NJ",
    "sg:tags":[
        "carpentry",
        "contractor"
    ],
    "wof:name":"Wards Carpentry",
    "wof:placetype":"venue"
},
  "geometry": {"coordinates":[-74.693015,40.197613],"type":"Point"}
}