{
  "type": "Feature",
  "properties": {
    "addr:full":"39 Prospect St Bloomfield NJ 07003",
    "addr:housenumber":"39",
    "addr:postcode":"07003",
    "addr:street":"Prospect St",
    "iso:country":"US",
    "sg:address":"39 Prospect St",
    "sg:city":"Bloomfield",
    "sg:classifiers":[
        {
            "category":"Personal",
            "subcategory":"Beauty Salon",
            "type":"Services"
        }
    ],
    "sg:phone":"+1 973 680 8272",
    "sg:postcode":"07003",
    "sg:province":"NJ",
    "sg:tags":[
        "shop"
    ],
    "wof:name":"Tera's Salon",
    "wof:placetype":"venue"
},
  "geometry": {"coordinates":[-74.204652,40.783514],"type":"Point"}
}