{
  "type": "Feature",
  "properties": {
    "iso:country":"US",
    "sg:address":"446 State Rte 70",
    "sg:city":"Marlton",
    "sg:classifiers":[
        {
            "category":"Sports & Exercise",
            "subcategory":"Gym",
            "type":"Entertainment"
        }
    ],
    "sg:phone":"+1 856 904 9290",
    "sg:postcode":"08053",
    "sg:province":"NJ",
    "sg:tags":[
        "center",
        "fitness"
    ],
    "wof:name":"Tank Tech LLC",
    "wof:placetype":"venue"
},
  "geometry": {"coordinates":[-74.78882299999999,39.898618],"type":"Point"}
}