{
  "type": "Feature",
  "properties": {
    "addr:full":"4 Mayne Ave Stanhope NJ 07874",
    "addr:housenumber":"4",
    "addr:postcode":"07874",
    "addr:street":"Mayne Ave",
    "iso:country":"US",
    "sg:address":"4 Mayne Ave",
    "sg:city":"Stanhope",
    "sg:classifiers":[
        {
            "category":"Professional",
            "type":"Services"
        }
    ],
    "sg:phone":"+1   ",
    "sg:postcode":"07874",
    "sg:province":"NJ",
    "wof:name":"Robert Heller",
    "wof:placetype":"venue"
},
  "geometry": {"coordinates":[-74.726614,40.921139],"type":"Point"}
}