{
  "type": "Feature",
  "properties": {
    "addr:full":"28 Stonegate Dr Mount Holly NJ 08060",
    "addr:housenumber":"28",
    "addr:postcode":"08060",
    "addr:street":"Stonegate Dr",
    "iso:country":"US",
    "sg:address":"28 Stonegate Dr",
    "sg:city":"Mount Holly",
    "sg:classifiers":[
        {
            "category":"Building & Trades",
            "subcategory":"Construction",
            "type":"Services"
        }
    ],
    "sg:phone":"+1 609 518 2038",
    "sg:postcode":"08060",
    "sg:province":"NJ",
    "sg:tags":[
        "carpentry",
        "contractor"
    ],
    "wof:name":"Gardon Carpentry Inc",
    "wof:placetype":"venue"
},
  "geometry": {"coordinates":[-74.76622500000001,39.998421],"type":"Point"}
}