{
  "type": "Feature",
  "properties": {
    "addr:full":"1 N 7th St Newark NJ 07107",
    "addr:housenumber":"1",
    "addr:postcode":"07107",
    "addr:street":"N 7Th St",
    "iso:country":"US",
    "sg:address":"1 N 7th St",
    "sg:city":"Newark",
    "sg:classifiers":[
        {
            "category":"Education",
            "subcategory":"Dance Studio",
            "type":"Public Place"
        }
    ],
    "sg:phone":"+1   ",
    "sg:postcode":"07107",
    "sg:province":"NJ",
    "wof:name":"L T Dance Inc",
    "wof:placetype":"venue"
},
  "geometry": {"coordinates":[-74.192988,40.74989],"type":"Point"}
}