{
  "type": "Feature",
  "properties": {
    "iso:country":"US",
    "sg:address":"1448 Lincoln Ave",
    "sg:city":"Pompton Lakes",
    "sg:classifiers":[
        {
            "category":"Building & Trades",
            "subcategory":"Landscaping Services",
            "type":"Services"
        }
    ],
    "sg:phone":"+1 973 248 1182",
    "sg:postcode":"07442",
    "sg:province":"NJ",
    "sg:tags":[
        "landscape"
    ],
    "wof:name":"Cardinal Landscaping",
    "wof:placetype":"venue"
},
  "geometry": {"coordinates":[-74.283711,40.986583],"type":"Point"}
}