{
  "type": "Feature",
  "properties": {
    "addr:full":"1715 Oak St Lakewood NJ 08701",
    "addr:housenumber":"1715",
    "addr:postcode":"08701",
    "addr:street":"Oak St",
    "iso:country":"US",
    "sg:address":"1715 Oak St",
    "sg:city":"Lakewood",
    "sg:classifiers":[
        {
            "category":"Professional",
            "type":"Services"
        }
    ],
    "sg:phone":"+1 732 961 0963",
    "sg:postcode":"08701",
    "sg:province":"NJ",
    "sg:tags":[
        "establishment"
    ],
    "wof:name":"DPT Lakewood Inc",
    "wof:placetype":"venue"
},
  "geometry": {"coordinates":[-74.186965,40.059568],"type":"Point"}
}