{
  "type": "Feature",
  "properties": {
    "addr:full":"18 Chestnut St Livingston NJ 07039",
    "addr:housenumber":"18",
    "addr:postcode":"07039",
    "addr:street":"Chestnut St",
    "iso:country":"US",
    "sg:address":"18 Chestnut St",
    "sg:city":"Livingston",
    "sg:classifiers":[
        {
            "category":"Building & Trades",
            "subcategory":"Construction",
            "type":"Services"
        }
    ],
    "sg:phone":"+1 973 994 4255",
    "sg:postcode":"07039",
    "sg:province":"NJ",
    "sg:tags":[
        "contractor"
    ],
    "wof:name":"George Hine General Contracting Inc",
    "wof:placetype":"venue"
},
  "geometry": {"coordinates":[-74.31120300000001,40.770599],"type":"Point"}
}