{
  "type": "Feature",
  "properties": {
    "addr:full":"38 Culver Ave Jersey City NJ 07305",
    "addr:housenumber":"38",
    "addr:postcode":"07305",
    "addr:street":"Culver Ave",
    "iso:country":"US",
    "sg:address":"38 Culver Ave",
    "sg:city":"Jersey City",
    "sg:classifiers":[
        {
            "category":"Professional",
            "subcategory":"Management & Consulting",
            "type":"Services"
        }
    ],
    "sg:phone":"+1   ",
    "sg:postcode":"07305",
    "sg:province":"NJ",
    "sg:tags":[
        "business"
    ],
    "wof:name":"Quartech Consulting",
    "wof:placetype":"venue"
},
  "geometry": {"coordinates":[-74.086935,40.710707],"type":"Point"}
}