{
  "type": "Feature",
  "properties": {
    "addr:full":"60 Memorial Pkwy Atlantic Hghlnds NJ 07716",
    "addr:housenumber":"60",
    "addr:postcode":"07716",
    "addr:street":"Memorial Pkwy",
    "iso:country":"US",
    "sg:address":"60 Memorial Pkwy",
    "sg:city":"Atlantic Hghlnds",
    "sg:classifiers":[
        {
            "category":"Personal",
            "subcategory":"Tanning Parlor",
            "type":"Services"
        }
    ],
    "sg:phone":"+1 732 291 4150",
    "sg:postcode":"07716",
    "sg:province":"NJ",
    "sg:tags":[
        "salon"
    ],
    "wof:name":"Atlantic Tan At Video Movie",
    "wof:placetype":"venue"
},
  "geometry": {"coordinates":[-74.035276,40.406926],"type":"Point"}
}