{
  "type": "Feature",
  "properties": {
    "iso:country":"US",
    "sg:address":"586 S Springfield Ave",
    "sg:city":"Springfield",
    "sg:classifiers":[
        {
            "category":"Retail",
            "subcategory":"Repair Shop",
            "type":"Services"
        }
    ],
    "sg:phone":"+1 973 376 1066",
    "sg:postcode":"07081",
    "sg:province":"NJ",
    "wof:name":"Waynes Key Shop",
    "wof:placetype":"venue"
},
  "geometry": {"coordinates":[-74.321146,40.693194],"type":"Point"}
}