{
  "type": "Feature",
  "properties": {
    "iso:country":"US",
    "sg:address":"470 Main St",
    "sg:city":"Little Falls",
    "sg:classifiers":[
        {
            "category":"Food & Beverages",
            "subcategory":"Meat & Fish",
            "type":"Retail Goods"
        }
    ],
    "sg:phone":"+1 973 256 1477",
    "sg:postcode":"07424",
    "sg:province":"NJ",
    "sg:tags":[
        "shop"
    ],
    "wof:name":"Buono's Prime Meats & Deli",
    "wof:placetype":"venue"
},
  "geometry": {"coordinates":[-74.2444,40.885799],"type":"Point"}
}