{
  "type": "Feature",
  "properties": {
    "addr:full":"231 Herbert Ave Closter NJ 07624",
    "addr:housenumber":"231",
    "addr:postcode":"07624",
    "addr:street":"Herbert Ave",
    "iso:country":"US",
    "sg:address":"231 Herbert Ave",
    "sg:city":"Closter",
    "sg:classifiers":[
        {
            "category":"Wholesale",
            "subcategory":"Computers",
            "type":"Manufacturing & Wholesale Goods"
        },
        {
            "category":"Shopping",
            "subcategory":"Computers & Home Electronics",
            "type":"Retail Goods"
        }
    ],
    "sg:phone":"+1 201 767 2210",
    "sg:postcode":"07624",
    "sg:province":"NJ",
    "sg:tags":[
        "software"
    ],
    "wof:name":"Ericom Software Inc",
    "wof:placetype":"venue"
},
  "geometry": {"coordinates":[-73.959574,40.975238],"type":"Point"}
}