{
  "type": "Feature",
  "properties": {
    "iso:country":"US",
    "sg:address":"52 Simpson Rd",
    "sg:city":"Ocean City",
    "sg:classifiers":[
        {
            "category":"Professional",
            "subcategory":"Art Services",
            "type":"Services"
        }
    ],
    "sg:phone":"+1   ",
    "sg:postcode":"08226",
    "sg:province":"NJ",
    "sg:tags":[
        "commercial",
        "design"
    ],
    "wof:name":"Klein Design Group",
    "wof:placetype":"venue"
},
  "geometry": {"coordinates":[-74.565388,39.291258],"type":"Point"}
}