{
  "type": "Feature",
  "properties": {
    "addr:full":"188 College View Dr Hackettstown NJ 07840",
    "addr:housenumber":"188",
    "addr:postcode":"07840",
    "addr:street":"College View Dr",
    "iso:country":"US",
    "sg:address":"188 College View Dr",
    "sg:city":"Hackettstown",
    "sg:classifiers":[
        {
            "category":"Professional",
            "subcategory":"Business Services",
            "type":"Services"
        }
    ],
    "sg:phone":"+1   ",
    "sg:postcode":"07840",
    "sg:province":"NJ",
    "wof:name":"Tmb Choices",
    "wof:placetype":"venue"
},
  "geometry": {"coordinates":[-74.845606,40.838819],"type":"Point"}
}