{
  "type": "Feature",
  "properties": {
    "iso:country":"US",
    "sg:address":"111 Cobblestone Dr",
    "sg:city":"Mount Laurel",
    "sg:classifiers":[
        {
            "category":"Professional",
            "subcategory":"Business Services",
            "type":"Services"
        }
    ],
    "sg:phone":"+1   ",
    "sg:postcode":"08054",
    "sg:province":"NJ",
    "wof:name":"Miko Enterprises Inc",
    "wof:placetype":"venue"
},
  "geometry": {"coordinates":[-74.93733400000001,39.9329],"type":"Point"}
}