{
  "type": "Feature",
  "properties": {
    "addr:full":"402 Sicklerville Rd Williamstown NJ 08094",
    "addr:housenumber":"402",
    "addr:postcode":"08094",
    "addr:street":"Sicklerville Rd",
    "iso:country":"US",
    "sg:address":"402 Sicklerville Rd",
    "sg:city":"Williamstown",
    "sg:phone":"+1 856 629 0622",
    "sg:postcode":"08094",
    "sg:province":"NJ",
    "sg:tags":[
        "oil"
    ],
    "wof:name":"Nosco Fuels & Supplies",
    "wof:placetype":"venue"
},
  "geometry": {"coordinates":[-74.990244,39.692826],"type":"Point"}
}