{
  "type": "Feature",
  "properties": {
    "iso:country":"US",
    "sg:address":"3 Haytown Rd",
    "sg:city":"Lebanon",
    "sg:classifiers":[
        {
            "category":"Education",
            "subcategory":"Preschool",
            "type":"Public Place"
        },
        {
            "category":"Education",
            "subcategory":"School",
            "type":"Public Place"
        }
    ],
    "sg:phone":"+1 908 236 7669",
    "sg:postcode":"08833",
    "sg:province":"NJ",
    "sg:tags":[
        "elementary"
    ],
    "wof:name":"First Step Learning Center",
    "wof:placetype":"venue"
},
  "geometry": {"coordinates":[-74.829498,40.6586],"type":"Point"}
}