{
  "type": "Feature",
  "properties": {
    "addr:full":"1581 State Rte 50 Woodbine NJ 08270",
    "addr:housenumber":"1581",
    "addr:postcode":"08270",
    "addr:street":"State Rte 50",
    "iso:country":"US",
    "sg:address":"1581 State Rte 50",
    "sg:city":"Woodbine",
    "sg:classifiers":[
        {
            "category":"Retail",
            "subcategory":"Repair Shop",
            "type":"Services"
        },
        {
            "category":"Recreation",
            "subcategory":"Marina",
            "type":"Entertainment"
        }
    ],
    "sg:phone":"+1 609 628 3115",
    "sg:postcode":"08270",
    "sg:province":"NJ",
    "sg:tags":[
        "repairing",
        "boat"
    ],
    "wof:name":"Maximum Marine Svc",
    "wof:placetype":"venue"
},
  "geometry": {"coordinates":[-74.744665,39.272895],"type":"Point"}
}