{
  "type": "Feature",
  "properties": {
    "addr:full":"157 Verona Ave Newark NJ 07104",
    "addr:housenumber":"157",
    "addr:postcode":"07104",
    "addr:street":"Verona Ave",
    "iso:country":"US",
    "sg:address":"157 Verona Ave",
    "sg:city":"Newark",
    "sg:classifiers":[
        {
            "category":"Recreation",
            "type":"Entertainment"
        },
        {
            "category":"Organizations",
            "subcategory":"Community Association",
            "type":"Services"
        }
    ],
    "sg:phone":"+1 973 483 8935",
    "sg:postcode":"07104",
    "sg:province":"NJ",
    "sg:tags":[
        "club",
        "membership"
    ],
    "wof:name":"Eighth Ward Non Partisan Club",
    "wof:placetype":"venue"
},
  "geometry": {"coordinates":[-74.158598,40.780317],"type":"Point"}
}