{
  "type": "Feature",
  "properties": {
    "iso:country":"US",
    "sg:address":"9 W Golden Oak Ln",
    "sg:city":"Marmora",
    "sg:classifiers":[
        {
            "category":"Building & Trades",
            "subcategory":"Cleaning & Sanitation",
            "type":"Services"
        }
    ],
    "sg:phone":"+1 609 748 1100",
    "sg:postcode":"08223",
    "sg:province":"NJ",
    "sg:tags":[
        "fireplace",
        "chimney"
    ],
    "wof:name":"Clean Sweep Chimney Cleaning",
    "wof:placetype":"venue"
},
  "geometry": {"coordinates":[-74.638493,39.276187],"type":"Point"}
}