{
  "type": "Feature",
  "properties": {
    "addr:full":"70 Barbour Pl Piscataway NJ 08854",
    "addr:housenumber":"70",
    "addr:postcode":"08854",
    "addr:street":"Barbour Pl",
    "iso:country":"US",
    "sg:address":"70 Barbour Pl",
    "sg:city":"Piscataway",
    "sg:classifiers":[
        {
            "category":"Professional",
            "subcategory":"Business Services",
            "type":"Services"
        }
    ],
    "sg:phone":"+1   ",
    "sg:postcode":"08854",
    "sg:province":"NJ",
    "wof:name":"Zedash Enterprises LLC",
    "wof:placetype":"venue"
},
  "geometry": {"coordinates":[-74.510423,40.547533],"type":"Point"}
}