{
  "type": "Feature",
  "properties": {
    "iso:country":"US",
    "sg:address":"66 Franklin St",
    "sg:city":"Paterson",
    "sg:classifiers":[
        {
            "category":"Retail",
            "subcategory":"Auto Repair",
            "type":"Services"
        }
    ],
    "sg:phone":"+1   ",
    "sg:postcode":"07524",
    "sg:province":"NJ",
    "sg:tags":[
        "body"
    ],
    "wof:name":"Merejo Auto Repair",
    "wof:placetype":"venue"
},
  "geometry": {"coordinates":[-74.16112699999999,40.926224],"type":"Point"}
}