{
  "type": "Feature",
  "properties": {
    "addr:full":"24 Terrier Ct Neptune NJ 07753",
    "addr:housenumber":"24",
    "addr:postcode":"07753",
    "addr:street":"Terrier Ct",
    "iso:country":"US",
    "sg:address":"24 Terrier Ct",
    "sg:city":"Neptune",
    "sg:classifiers":[
        {
            "category":"Retail",
            "subcategory":"Self-service Laundry",
            "type":"Services"
        }
    ],
    "sg:phone":"+1 732 643 1513",
    "sg:postcode":"07753",
    "sg:province":"NJ",
    "sg:tags":[
        "coin"
    ],
    "wof:name":"Laundry King",
    "wof:placetype":"venue"
},
  "geometry": {"coordinates":[-74.095308,40.242354],"type":"Point"}
}