{
  "type": "Feature",
  "properties": {
    "addr:full":"917 Haddonfield Rd Cherry Hill NJ 08002",
    "addr:housenumber":"917",
    "addr:postcode":"08002",
    "addr:street":"Haddonfield Rd",
    "iso:country":"US",
    "sg:address":"917 Haddonfield Rd",
    "sg:city":"Cherry Hill",
    "sg:classifiers":[
        {
            "category":"Professional",
            "subcategory":"Research",
            "type":"Services"
        }
    ],
    "sg:phone":"+1 856 910 1000",
    "sg:postcode":"08002",
    "sg:province":"NJ",
    "sg:tags":[
        "nonphysical",
        "commercial"
    ],
    "wof:name":"Heakin Research Inc",
    "wof:placetype":"venue"
},
  "geometry": {"coordinates":[-75.03326199999999,39.924229],"type":"Point"}
}