{
  "type": "Feature",
  "properties": {
    "iso:country":"US",
    "sg:address":"315 Wooton St",
    "sg:city":"Boonton",
    "sg:classifiers":[
        {
            "category":"Sports & Exercise",
            "subcategory":"Gym",
            "type":"Entertainment"
        }
    ],
    "sg:phone":"+1 973 331 9901",
    "sg:postcode":"07005",
    "sg:province":"NJ",
    "sg:tags":[
        "club",
        "health",
        "studio",
        "gymnasium"
    ],
    "wof:name":"Curves",
    "wof:placetype":"venue"
},
  "geometry": {"coordinates":[-74.404213,40.910296],"type":"Point"}
}