{
  "type": "Feature",
  "properties": {
    "addr:full":"87 N Pocono Rd Mountain Lakes NJ 07046",
    "addr:housenumber":"87",
    "addr:postcode":"07046",
    "addr:street":"N Pocono Rd",
    "iso:country":"US",
    "sg:address":"87 N Pocono Rd",
    "sg:city":"Mountain Lakes",
    "sg:classifiers":[
        {
            "category":"Building & Trades",
            "subcategory":"Landscaping Services",
            "type":"Services"
        }
    ],
    "sg:phone":"+1 973 983 0613",
    "sg:postcode":"07046",
    "sg:province":"NJ",
    "sg:tags":[
        "landscape"
    ],
    "wof:name":"Andrea Buckingham Landscape",
    "wof:placetype":"venue"
},
  "geometry": {"coordinates":[-74.456135,40.890026],"type":"Point"}
}