{
  "type": "Feature",
  "properties": {
    "iso:country":"US",
    "sg:address":"223 Sterling Dr",
    "sg:city":"Millington",
    "sg:classifiers":[
        {
            "category":"Real Estate",
            "subcategory":"Real Estate Agent",
            "type":"Services"
        }
    ],
    "sg:phone":"+1 908 647 7785",
    "sg:postcode":"07932",
    "sg:province":"NJ",
    "sg:tags":[
        "management"
    ],
    "wof:name":"Vantage Development",
    "wof:placetype":"venue"
},
  "geometry": {"coordinates":[-74.37027999999999,40.753151],"type":"Point"}
}