{
  "type": "Feature",
  "properties": {
    "addr:full":"1 Nystrom Trl Matawan NJ 07747",
    "addr:housenumber":"1",
    "addr:postcode":"07747",
    "addr:street":"Nystrom Trl",
    "iso:country":"US",
    "sg:address":"1 Nystrom Trl",
    "sg:city":"Matawan",
    "sg:classifiers":[
        {
            "category":"Professional",
            "subcategory":"Management & Consulting",
            "type":"Services"
        }
    ],
    "sg:phone":"+1   ",
    "sg:postcode":"07747",
    "sg:province":"NJ",
    "sg:tags":[
        "business"
    ],
    "wof:name":"Tech Alliance & Consulting Ltd",
    "wof:placetype":"venue"
},
  "geometry": {"coordinates":[-74.264371,40.407841],"type":"Point"}
}