{
  "type": "Feature",
  "properties": {
    "iso:country":"US",
    "sg:address":"1346 Clifton Ave",
    "sg:city":"Clifton",
    "sg:classifiers":[
        {
            "category":"Personal",
            "subcategory":"Beauty Salon",
            "type":"Services"
        }
    ],
    "sg:phone":"+1 973 473 3990",
    "sg:postcode":"07012",
    "sg:province":"NJ",
    "sg:tags":[
        "nail",
        "shop"
    ],
    "wof:name":"Exclusively Skin & Nails",
    "wof:placetype":"venue"
},
  "geometry": {"coordinates":[-74.172501,40.853802],"type":"Point"}
}