{
  "type": "Feature",
  "properties": {
    "addr:full":"41 E Kennedy Blvd Lakewood NJ 08701",
    "addr:housenumber":"41",
    "addr:postcode":"08701",
    "addr:street":"E Kennedy Blvd",
    "iso:country":"US",
    "sg:address":"41 E Kennedy Blvd",
    "sg:city":"Lakewood",
    "sg:classifiers":[
        {
            "category":"Wholesale",
            "subcategory":"Non-durable Goods",
            "type":"Manufacturing & Wholesale Goods"
        }
    ],
    "sg:phone":"+1 732 370 9297",
    "sg:postcode":"08701",
    "sg:province":"NJ",
    "sg:tags":[
        "leather",
        "clothes"
    ],
    "wof:name":"Young's Shoe Repair",
    "wof:placetype":"venue"
},
  "geometry": {"coordinates":[-74.21745900000001,40.106911],"type":"Point"}
}