{
  "type": "Feature",
  "properties": {
    "addr:full":"8 Sherman Ave Morris Plains NJ 07950",
    "addr:housenumber":"8",
    "addr:postcode":"07950",
    "addr:street":"Sherman Ave",
    "iso:country":"US",
    "sg:address":"8 Sherman Ave",
    "sg:city":"Morris Plains",
    "sg:classifiers":[
        {
            "category":"Professional",
            "type":"Services"
        }
    ],
    "sg:phone":"+1   ",
    "sg:postcode":"07950",
    "sg:province":"NJ",
    "wof:name":"Mel & Steve Inc",
    "wof:placetype":"venue"
},
  "geometry": {"coordinates":[-74.48510400000001,40.820018],"type":"Point"}
}