{
  "type": "Feature",
  "properties": {
    "addr:full":"834 Parry Ave Palmyra NJ 08065",
    "addr:housenumber":"834",
    "addr:postcode":"08065",
    "addr:street":"Parry Ave",
    "iso:country":"US",
    "sg:address":"834 Parry Ave",
    "sg:city":"Palmyra",
    "sg:classifiers":[
        {
            "category":"Real Estate",
            "subcategory":"Surveying",
            "type":"Services"
        }
    ],
    "sg:phone":"+1 856 829 1833",
    "sg:postcode":"08065",
    "sg:province":"NJ",
    "sg:tags":[
        "engineer"
    ],
    "wof:name":"Fisher, Donald P",
    "wof:placetype":"venue"
},
  "geometry": {"coordinates":[-75.018765,40.000601],"type":"Point"}
}