{
  "type": "Feature",
  "properties": {
    "addr:full":"380 S Washington Ave Bergenfield NJ 07621",
    "addr:housenumber":"380",
    "addr:postcode":"07621",
    "addr:street":"S Washington Ave",
    "iso:country":"US",
    "sg:address":"380 S Washington Ave",
    "sg:city":"Bergenfield",
    "sg:classifiers":[
        {
            "category":"Building & Trades",
            "subcategory":"Plumbing",
            "type":"Services"
        }
    ],
    "sg:phone":"+1 201 387 6605",
    "sg:postcode":"07621",
    "sg:province":"NJ",
    "sg:tags":[
        "heating",
        "contractor"
    ],
    "sg:website":"www.ctfarinella.com",
    "wof:name":"C T Farinella & Sons Plumbers",
    "wof:placetype":"venue"
},
  "geometry": {"coordinates":[-73.99744699999999,40.915051],"type":"Point"}
}