{
  "type": "Feature",
  "properties": {
    "addr:full":"2215 Knollwood Dr Middletown NJ 07748",
    "addr:housenumber":"2215",
    "addr:postcode":"07748",
    "addr:street":"Knollwood Dr",
    "iso:country":"US",
    "sg:address":"2215 Knollwood Dr",
    "sg:city":"Middletown",
    "sg:classifiers":[
        {
            "category":"Professional",
            "subcategory":"Management & Consulting",
            "type":"Services"
        }
    ],
    "sg:phone":"+1   ",
    "sg:postcode":"07748",
    "sg:province":"NJ",
    "sg:tags":[
        "business"
    ],
    "wof:name":"Life Balance Consulting LLC",
    "wof:placetype":"venue"
},
  "geometry": {"coordinates":[-74.09817200000001,40.392659],"type":"Point"}
}