{
  "type": "Feature",
  "properties": {
    "addr:full":"521 US Hwy 130 Hightstown NJ 08520",
    "addr:housenumber":"521",
    "addr:postcode":"08520",
    "addr:street":"Us Hwy 130",
    "iso:country":"US",
    "sg:address":"521 US Hwy 130",
    "sg:city":"Hightstown",
    "sg:classifiers":[
        {
            "category":"Autos & Motor Vehicles",
            "subcategory":"Fuel & Gas Station",
            "type":"Retail Goods"
        }
    ],
    "sg:phone":"+1   ",
    "sg:postcode":"08520",
    "sg:province":"NJ",
    "sg:tags":[
        "station",
        "gasoline"
    ],
    "wof:name":"Sunoco",
    "wof:placetype":"venue"
},
  "geometry": {"coordinates":[-74.54265100000001,40.267837],"type":"Point"}
}