{
  "type": "Feature",
  "properties": {
    "iso:country":"US",
    "sg:address":"3 Arvida Dr",
    "sg:city":"Pennington",
    "sg:classifiers":[
        {
            "category":"Professional",
            "subcategory":"Research",
            "type":"Services"
        }
    ],
    "sg:phone":"+1 609 730 0575",
    "sg:postcode":"08534",
    "sg:province":"NJ",
    "sg:tags":[
        "laboratory"
    ],
    "wof:name":"Gmp Material Testing Lab",
    "wof:placetype":"venue"
},
  "geometry": {"coordinates":[-74.75360999999999,40.347863],"type":"Point"}
}