{
  "type": "Feature",
  "properties": {
    "addr:full":"4 Edgewood Ct Parsippany NJ 07054",
    "addr:housenumber":"4",
    "addr:postcode":"07054",
    "addr:street":"Edgewood Ct",
    "iso:country":"US",
    "sg:address":"4 Edgewood Ct",
    "sg:city":"Parsippany",
    "sg:classifiers":[
        {
            "category":"Professional",
            "subcategory":"Engineering",
            "type":"Services"
        }
    ],
    "sg:phone":"+1 973 887 4774",
    "sg:postcode":"07054",
    "sg:province":"NJ",
    "sg:tags":[
        "engineer"
    ],
    "wof:name":"Wharton Engineering LLC",
    "wof:placetype":"venue"
},
  "geometry": {"coordinates":[-74.395636,40.851853],"type":"Point"}
}