{
  "type": "Feature",
  "properties": {
    "iso:country":"US",
    "sg:address":"19 Forest Rd",
    "sg:city":"Ringwood",
    "sg:classifiers":[
        {
            "category":"Shopping",
            "type":"Retail Goods"
        }
    ],
    "sg:phone":"+1   ",
    "sg:postcode":"07456",
    "sg:province":"NJ",
    "sg:tags":[
        "merchandise"
    ],
    "wof:name":"Hielschler U S A Inc",
    "wof:placetype":"venue"
},
  "geometry": {"coordinates":[-74.27649099999999,41.071766],"type":"Point"}
}