{
  "type": "Feature",
  "properties": {
    "iso:country":"US",
    "sg:address":"114 Nelson Pl",
    "sg:city":"Westfield",
    "sg:classifiers":[
        {
            "category":"Home & Garden",
            "subcategory":"Furniture",
            "type":"Retail Goods"
        }
    ],
    "sg:phone":"+1 908 232 9696",
    "sg:postcode":"07090",
    "sg:province":"NJ",
    "sg:tags":[
        "house",
        "furnishing"
    ],
    "wof:name":"J & D Custom Decor",
    "wof:placetype":"venue"
},
  "geometry": {"coordinates":[-74.35239,40.651505],"type":"Point"}
}