{
  "type": "Feature",
  "properties": {
    "iso:country":"US",
    "sg:address":"1481 State Rte 88",
    "sg:city":"Brick",
    "sg:classifiers":[
        {
            "category":"Health Services",
            "subcategory":"Doctor",
            "type":"Services"
        }
    ],
    "sg:phone":"+1 732 458 0909",
    "sg:postcode":"08724",
    "sg:province":"NJ",
    "sg:tags":[
        "physician",
        "surgeon"
    ],
    "wof:name":"Betty Benjamin MD",
    "wof:placetype":"venue"
},
  "geometry": {"coordinates":[-74.144183,40.082282],"type":"Point"}
}