{
  "type": "Feature",
  "properties": {
    "addr:full":"1772 S Lincoln Ave Vineland NJ 08361",
    "addr:housenumber":"1772",
    "addr:postcode":"08361",
    "addr:street":"S Lincoln Ave",
    "iso:country":"US",
    "sg:address":"1772 S Lincoln Ave",
    "sg:city":"Vineland",
    "sg:classifiers":[
        {
            "category":"Restaurant",
            "type":"Food & Drink"
        }
    ],
    "sg:phone":"+1   ",
    "sg:postcode":"08361",
    "sg:province":"NJ",
    "sg:tags":[
        "eating"
    ],
    "wof:name":"Peking Garden Chinese Rest",
    "wof:placetype":"venue"
},
  "geometry": {"coordinates":[-74.984656,39.458987],"type":"Point"}
}