{
  "type": "Feature",
  "properties": {
    "iso:country":"US",
    "sg:address":"18 Redwood Rd",
    "sg:city":"Martinsville",
    "sg:classifiers":[
        {
            "category":"Professional",
            "subcategory":"Lawyer & Legal Services",
            "type":"Services"
        }
    ],
    "sg:phone":"+1   ",
    "sg:postcode":"08836",
    "sg:province":"NJ",
    "wof:name":"William L Clough Attorney",
    "wof:placetype":"venue"
},
  "geometry": {"coordinates":[-74.52822500000001,40.586884],"type":"Point"}
}