{
  "type": "Feature",
  "properties": {
    "addr:full":"148 W Broad St Burlington NJ 08016",
    "addr:housenumber":"148",
    "addr:postcode":"08016",
    "addr:street":"W Broad St",
    "iso:country":"US",
    "sg:address":"148 W Broad St",
    "sg:city":"Burlington",
    "sg:classifiers":[
        {
            "category":"Bars & Pubs",
            "type":"Food & Drink"
        }
    ],
    "sg:phone":"+1   ",
    "sg:postcode":"08016",
    "sg:province":"NJ",
    "sg:tags":[
        "drinking"
    ],
    "wof:name":"Barb Jer Inc",
    "wof:placetype":"venue"
},
  "geometry": {"coordinates":[-74.86149,40.076638],"type":"Point"}
}