{
  "type": "Feature",
  "properties": {
    "iso:country":"US",
    "sg:address":"9380 N Crescent Blvd # 84",
    "sg:city":"Pennsauken",
    "sg:classifiers":[
        {
            "category":"Manufacturing",
            "subcategory":"Food",
            "type":"Manufacturing & Wholesale Goods"
        },
        {
            "category":"Building & Trades",
            "subcategory":"Equipment Rental",
            "type":"Services"
        },
        {
            "category":"Home & Garden",
            "subcategory":"Kitchen Supply",
            "type":"Retail Goods"
        }
    ],
    "sg:phone":"+1 856 488 8110",
    "sg:postcode":"08110",
    "sg:province":"NJ",
    "sg:tags":[
        "equipment-repair",
        "manufacturer",
        "supply-wholesale",
        "restaurant"
    ],
    "sg:website":"http://www.restaurantequipmentsupply.org",
    "wof:name":"AAA Restaurant Equipment",
    "wof:placetype":"venue"
},
  "geometry": {"coordinates":[-75.022228,39.981546],"type":"Point"}
}