{
  "type": "Feature",
  "properties": {
    "addr:full":"21 E Palisade Ave Englewood NJ 07631",
    "addr:housenumber":"21",
    "addr:postcode":"07631",
    "addr:street":"E Palisade Ave",
    "iso:country":"US",
    "sg:address":"21 E Palisade Ave",
    "sg:city":"Englewood",
    "sg:classifiers":[
        {
            "category":"Retail",
            "subcategory":"Repair Shop",
            "type":"Services"
        }
    ],
    "sg:phone":"+1 201 334 3196",
    "sg:postcode":"07631",
    "sg:province":"NJ",
    "sg:tags":[
        "lock",
        "locksmith"
    ],
    "wof:name":"24 Hour Emergency Locksmith",
    "wof:placetype":"venue"
},
  "geometry": {"coordinates":[-73.97319299999999,40.893065],"type":"Point"}
}