{
  "type": "Feature",
  "properties": {
    "addr:full":"762 State Rte 15 Lake Hopatcong NJ 07849",
    "addr:housenumber":"762",
    "addr:postcode":"07849",
    "addr:street":"State Rte 15",
    "iso:country":"US",
    "sg:address":"762 State Rte 15",
    "sg:city":"Lake Hopatcong",
    "sg:classifiers":[
        {
            "category":"Wholesale",
            "subcategory":"Electrical",
            "type":"Manufacturing & Wholesale Goods"
        }
    ],
    "sg:phone":"+1 973 663 4800",
    "sg:postcode":"07849",
    "sg:province":"NJ",
    "sg:tags":[
        "parts",
        "mfg"
    ],
    "wof:name":"Yaskawa Electric America Inc",
    "wof:placetype":"venue"
},
  "geometry": {"coordinates":[-74.595553,40.962487],"type":"Point"}
}