{
  "type": "Feature",
  "properties": {
    "iso:country":"US",
    "sg:address":"23 Old Milford Ln",
    "sg:city":"West Milford",
    "sg:classifiers":[
        {
            "category":"Building & Trades",
            "subcategory":"Cleaning & Sanitation",
            "type":"Services"
        }
    ],
    "sg:phone":"+1 973 208 8172",
    "sg:postcode":"07480",
    "sg:province":"NJ",
    "sg:tags":[
        "janitor"
    ],
    "wof:name":"K D Cleaning",
    "wof:placetype":"venue"
},
  "geometry": {"coordinates":[-74.407689,41.103227],"type":"Point"}
}