{
  "type": "Feature",
  "properties": {
    "iso:country":"US",
    "sg:address":"22 Skyline Dr",
    "sg:city":"West Orange",
    "sg:classifiers":[
        {
            "category":"Shopping",
            "subcategory":"Stationery & Office Supplies",
            "type":"Retail Goods"
        },
        {
            "category":"Building & Trades",
            "subcategory":"Construction",
            "type":"Services"
        }
    ],
    "sg:phone":"+1 973 736 7005",
    "sg:postcode":"07052",
    "sg:province":"NJ",
    "sg:tags":[
        "interior",
        "equipment",
        "design"
    ],
    "wof:name":"Maximum Design Concepts",
    "wof:placetype":"venue"
},
  "geometry": {"coordinates":[-74.27600099999999,40.788601],"type":"Point"}
}