{
  "type": "Feature",
  "properties": {
    "iso:country":"US",
    "sg:address":"516 Delsea Dr N",
    "sg:city":"Glassboro",
    "sg:classifiers":[
        {
            "category":"Personal",
            "subcategory":"Beauty Salon",
            "type":"Services"
        }
    ],
    "sg:phone":"+1 856 307 7570",
    "sg:postcode":"08028",
    "sg:province":"NJ",
    "sg:tags":[
        "shop"
    ],
    "wof:name":"Delsea Nails",
    "wof:placetype":"venue"
},
  "geometry": {"coordinates":[-75.111994,39.714084],"type":"Point"}
}