{
  "type": "Feature",
  "properties": {
    "addr:full":"401 Washington St Toms River NJ 08753",
    "addr:housenumber":"401",
    "addr:postcode":"08753",
    "addr:street":"Washington St",
    "iso:country":"US",
    "sg:address":"401 Washington St",
    "sg:city":"Toms River",
    "sg:classifiers":[
        {
            "category":"Professional",
            "subcategory":"Lawyer & Legal Services",
            "type":"Services"
        }
    ],
    "sg:phone":"+1 732 341 8061",
    "sg:postcode":"08753",
    "sg:province":"NJ",
    "wof:name":"Edward F Bezdecki",
    "wof:placetype":"venue"
},
  "geometry": {"coordinates":[-74.18646699999999,39.952127],"type":"Point"}
}