{
  "type": "Feature",
  "properties": {
    "iso:country":"US",
    "sg:address":"10 W Railroad Ave",
    "sg:city":"Monroe Township",
    "sg:classifiers":[
        {
            "category":"Travel",
            "subcategory":"Travel Agent",
            "type":"Entertainment"
        }
    ],
    "sg:phone":"+1 732 521 9570",
    "sg:postcode":"08831",
    "sg:province":"NJ",
    "sg:tags":[
        "agency"
    ],
    "wof:name":"Wright Travel Inc",
    "wof:placetype":"venue"
},
  "geometry": {"coordinates":[-74.436036,40.348109],"type":"Point"}
}