{
  "type": "Feature",
  "properties": {
    "iso:country":"US",
    "sg:address":"50 Honeck St",
    "sg:city":"Englewood",
    "sg:classifiers":[
        {
            "category":"Retail",
            "subcategory":"Auto Repair",
            "type":"Services"
        }
    ],
    "sg:phone":"+1 201 833 7644",
    "sg:postcode":"07631",
    "sg:province":"NJ",
    "sg:tags":[
        "repairing",
        "automobile",
        "automotive"
    ],
    "wof:name":"George's Garage LLC",
    "wof:placetype":"venue"
},
  "geometry": {"coordinates":[-73.98059499999999,40.882758],"type":"Point"}
}