{
  "type": "Feature",
  "properties": {
    "iso:country":"US",
    "sg:address":"1204 Parvin Mill Rd",
    "sg:city":"Elmer",
    "sg:classifiers":[
        {
            "category":"Shopping",
            "subcategory":"Computers & Home Electronics",
            "type":"Retail Goods"
        }
    ],
    "sg:phone":"+1 856 696 8030",
    "sg:postcode":"08318",
    "sg:province":"NJ",
    "sg:tags":[
        "equipment",
        "electronic",
        "supply"
    ],
    "wof:name":"North Star Electronics Inc",
    "wof:placetype":"venue"
},
  "geometry": {"coordinates":[-75.12065200000001,39.523226],"type":"Point"}
}