{
  "type": "Feature",
  "properties": {
    "addr:full":"1944 E Landis Ave Vineland NJ 08361",
    "addr:housenumber":"1944",
    "addr:postcode":"08361",
    "addr:street":"E Landis Ave",
    "iso:country":"US",
    "sg:address":"1944 E Landis Ave",
    "sg:city":"Vineland",
    "sg:classifiers":[
        {
            "category":"Social Services",
            "type":"Services"
        }
    ],
    "sg:phone":"+1   ",
    "sg:postcode":"08361",
    "sg:province":"NJ",
    "wof:name":"Bbbs Assn Cumberland Cnty",
    "wof:placetype":"venue"
},
  "geometry": {"coordinates":[-74.995648,39.484924],"type":"Point"}
}