{
  "type": "Feature",
  "properties": {
    "iso:country":"US",
    "sg:address":"213 Waters Edge Dr",
    "sg:city":"Toms River",
    "sg:classifiers":[
        {
            "category":"Building & Trades",
            "subcategory":"Construction",
            "type":"Services"
        }
    ],
    "sg:phone":"+1 732 270 2435",
    "sg:postcode":"08753",
    "sg:province":"NJ",
    "sg:tags":[
        "contractor"
    ],
    "wof:name":"Ronald Cuccinello",
    "wof:placetype":"venue"
},
  "geometry": {"coordinates":[-74.15134,39.998623],"type":"Point"}
}