{
  "type": "Feature",
  "properties": {
    "iso:country":"US",
    "sg:address":"4205 New Jersey Ave",
    "sg:city":"Wildwood",
    "sg:classifiers":[
        {
            "category":"Personal",
            "type":"Services"
        },
        {
            "category":"Autos & Motor Vehicles",
            "subcategory":"Motorcycle Sales",
            "type":"Retail Goods"
        }
    ],
    "sg:phone":"+1 609 522 4455",
    "sg:postcode":"08260",
    "sg:province":"NJ",
    "sg:tags":[
        "towing"
    ],
    "wof:name":"Righter's Cycle Parts & Accessories",
    "wof:placetype":"venue"
},
  "geometry": {"coordinates":[-74.820297,38.987099],"type":"Point"}
}