{
  "type": "Feature",
  "properties": {
    "iso:country":"US",
    "sg:address":"450 Anstatt Way",
    "sg:city":"Haworth",
    "sg:classifiers":[
        {
            "category":"Home & Garden",
            "subcategory":"Carpets & Floor Coverings",
            "type":"Retail Goods"
        }
    ],
    "sg:phone":"+1 201 384 4655",
    "sg:postcode":"07641",
    "sg:province":"NJ",
    "sg:tags":[
        "dealer",
        "rug"
    ],
    "wof:name":"Majestic Rug Co",
    "wof:placetype":"venue"
},
  "geometry": {"coordinates":[-73.98832899999999,40.969716],"type":"Point"}
}