{
  "type": "Feature",
  "properties": {
    "iso:country":"US",
    "sg:address":"1199 Cropwell Rd",
    "sg:city":"Cherry Hill",
    "sg:classifiers":[
        {
            "category":"Retail",
            "subcategory":"Portrait Studio",
            "type":"Services"
        }
    ],
    "sg:phone":"+1 856 489 4439",
    "sg:postcode":"08003",
    "sg:province":"NJ",
    "sg:tags":[
        "photographer",
        "photo"
    ],
    "wof:name":"Lesha Studios Inc",
    "wof:placetype":"venue"
},
  "geometry": {"coordinates":[-74.95174799999999,39.880627],"type":"Point"}
}