{
  "type": "Feature",
  "properties": {
    "iso:country":"US",
    "sg:address":"142 4th Ave",
    "sg:city":"Paterson",
    "sg:classifiers":[
        {
            "category":"Building & Trades",
            "subcategory":"Construction",
            "type":"Services"
        }
    ],
    "sg:phone":"+1 973 278 1643",
    "sg:postcode":"07524",
    "sg:province":"NJ",
    "sg:tags":[
        "general",
        "contractor"
    ],
    "wof:name":"Oscar's Handyman",
    "wof:placetype":"venue"
},
  "geometry": {"coordinates":[-74.148426,40.935679],"type":"Point"}
}