{
  "type": "Feature",
  "properties": {
    "addr:full":"165 Branchport Ave Long Branch NJ 07740",
    "addr:housenumber":"165",
    "addr:postcode":"07740",
    "addr:street":"Branchport Ave",
    "iso:country":"US",
    "sg:address":"165 Branchport Ave",
    "sg:city":"Long Branch",
    "sg:classifiers":[
        {
            "category":"Shopping",
            "subcategory":"Clothing, Apparel, & Fashions",
            "type":"Retail Goods"
        }
    ],
    "sg:phone":"+1 732 229 6660",
    "sg:postcode":"07740",
    "sg:province":"NJ",
    "wof:name":"Merc Medical Apparel",
    "wof:placetype":"venue"
},
  "geometry": {"coordinates":[-74.003241,40.305144],"type":"Point"}
}