{
  "type": "Feature",
  "properties": {
    "addr:full":"1861 Hooper Ave Toms River NJ 08753",
    "addr:housenumber":"1861",
    "addr:postcode":"08753",
    "addr:street":"Hooper Ave",
    "iso:country":"US",
    "sg:address":"1861 Hooper Ave",
    "sg:city":"Toms River",
    "sg:classifiers":[
        {
            "category":"Professional",
            "subcategory":"Lawyer & Legal Services",
            "type":"Services"
        }
    ],
    "sg:phone":"+1 732 308 0200",
    "sg:postcode":"08753",
    "sg:province":"NJ",
    "sg:tags":[
        "attorney"
    ],
    "wof:name":"Herbert Ellis Law Offices",
    "wof:placetype":"venue"
},
  "geometry": {"coordinates":[-74.14521000000001,40.015139],"type":"Point"}
}