{
  "type": "Feature",
  "properties": {
    "addr:full":"244 Livingston St Northvale NJ 07647",
    "addr:housenumber":"244",
    "addr:postcode":"07647",
    "addr:street":"Livingston St",
    "iso:country":"US",
    "sg:address":"244 Livingston St",
    "sg:city":"Northvale",
    "sg:classifiers":[
        {
            "category":"Restaurant",
            "type":"Food & Drink"
        }
    ],
    "sg:phone":"+1 201 784 9592",
    "sg:postcode":"07647",
    "sg:province":"NJ",
    "wof:name":"Great Wall Kitchen",
    "wof:placetype":"venue"
},
  "geometry": {"coordinates":[-73.94586200000001,41.014209],"type":"Point"}
}