{
  "type": "Feature",
  "properties": {
    "iso:country":"US",
    "sg:address":"932 Anchor Ave",
    "sg:city":"Beachwood",
    "sg:classifiers":[
        {
            "category":"Building & Trades",
            "subcategory":"Construction",
            "type":"Services"
        }
    ],
    "sg:phone":"+1 732 349 4104",
    "sg:postcode":"08722",
    "sg:province":"NJ",
    "sg:tags":[
        "floor",
        "laying",
        "contractor"
    ],
    "wof:name":"Phil Potter",
    "wof:placetype":"venue"
},
  "geometry": {"coordinates":[-74.199522,39.927381],"type":"Point"}
}