{
  "type": "Feature",
  "properties": {
    "iso:country":"US",
    "sg:address":"1259 US Hwy 46",
    "sg:city":"Parsippany",
    "sg:classifiers":[
        {
            "category":"Professional",
            "subcategory":"Management & Consulting",
            "type":"Services"
        }
    ],
    "sg:phone":"+1   ",
    "sg:postcode":"07054",
    "sg:province":"NJ",
    "sg:tags":[
        "information",
        "technology",
        "telecommunication"
    ],
    "wof:name":"Billingitcom",
    "wof:placetype":"venue"
},
  "geometry": {"coordinates":[-74.38668800000001,40.862899],"type":"Point"}
}