{
  "type": "Feature",
  "properties": {
    "iso:country":"US",
    "sg:address":"111 W Nicholson Rd",
    "sg:city":"Audubon",
    "sg:classifiers":[
        {
            "category":"Shopping",
            "subcategory":"Gifts & Souvenirs",
            "type":"Retail Goods"
        }
    ],
    "sg:phone":"+1 856 547 0094",
    "sg:postcode":"08106",
    "sg:province":"NJ",
    "sg:tags":[
        "shop"
    ],
    "wof:name":"Power Star Collectibles Inc",
    "wof:placetype":"venue"
},
  "geometry": {"coordinates":[-75.073402,39.895739],"type":"Point"}
}