{
  "type": "Feature",
  "properties": {
    "iso:country":"US",
    "sg:address":"437 Simpson Ave",
    "sg:city":"Ocean City",
    "sg:classifiers":[
        {
            "category":"Real Estate",
            "subcategory":"Real Estate Operator",
            "type":"Services"
        }
    ],
    "sg:phone":"+1   ",
    "sg:postcode":"08226",
    "sg:province":"NJ",
    "sg:tags":[
        "property",
        "lessor"
    ],
    "wof:name":"Sam Rowell Landlord",
    "wof:placetype":"venue"
},
  "geometry": {"coordinates":[-74.571913,39.285976],"type":"Point"}
}