{
  "type": "Feature",
  "properties": {
    "addr:full":"51 Feronia Way Rutherford NJ 07070",
    "addr:housenumber":"51",
    "addr:postcode":"07070",
    "addr:street":"Feronia Way",
    "iso:country":"US",
    "sg:address":"51 Feronia Way",
    "sg:city":"Rutherford",
    "sg:classifiers":[
        {
            "category":"Restaurant",
            "type":"Food & Drink"
        }
    ],
    "sg:phone":"+1 973 783 1220",
    "sg:postcode":"07070",
    "sg:province":"NJ",
    "wof:name":"Quiznos Sub",
    "wof:placetype":"venue"
},
  "geometry": {"coordinates":[-74.10055,40.826368],"type":"Point"}
}