{
  "type": "Feature",
  "properties": {
    "addr:full":"124 Morristown Rd Basking Ridge NJ 07920",
    "addr:housenumber":"124",
    "addr:postcode":"07920",
    "addr:street":"Morristown Rd",
    "iso:country":"US",
    "sg:address":"124 Morristown Rd",
    "sg:city":"Basking Ridge",
    "sg:classifiers":[
        {
            "category":"Building & Trades",
            "subcategory":"Construction",
            "type":"Services"
        }
    ],
    "sg:phone":"+1 908 766 1948",
    "sg:postcode":"07920",
    "sg:province":"NJ",
    "sg:tags":[
        "water",
        "well",
        "drilling"
    ],
    "wof:name":"Gould's Well & Pump Co",
    "wof:placetype":"venue"
},
  "geometry": {"coordinates":[-74.54880799999999,40.724363],"type":"Point"}
}