{
  "type": "Feature",
  "properties": {
    "addr:full":"919 State Rte 35 Ocean NJ 07712",
    "addr:housenumber":"919",
    "addr:postcode":"07712",
    "addr:street":"State Rte 35",
    "iso:country":"US",
    "sg:address":"919 State Rte 35",
    "sg:city":"Ocean",
    "sg:classifiers":[
        {
            "category":"Home & Garden",
            "subcategory":"Furniture",
            "type":"Retail Goods"
        }
    ],
    "sg:phone":"+1 732 517 1111",
    "sg:postcode":"07712",
    "sg:province":"NJ",
    "wof:name":"Jasons Furniture",
    "wof:placetype":"venue"
},
  "geometry": {"coordinates":[-74.038274,40.232792],"type":"Point"}
}