{
  "type": "Feature",
  "properties": {
    "addr:full":"36 Kimberly Dr Barnegat NJ 08005",
    "addr:housenumber":"36",
    "addr:postcode":"08005",
    "addr:street":"Kimberly Dr",
    "iso:country":"US",
    "sg:address":"36 Kimberly Dr",
    "sg:city":"Barnegat",
    "sg:classifiers":[
        {
            "category":"Wholesale",
            "subcategory":"Electrical",
            "type":"Manufacturing & Wholesale Goods"
        }
    ],
    "sg:phone":"+1 609 698 6452",
    "sg:postcode":"08005",
    "sg:province":"NJ",
    "sg:tags":[
        "equipment"
    ],
    "wof:name":"MCP",
    "wof:placetype":"venue"
},
  "geometry": {"coordinates":[-74.32337200000001,39.761841],"type":"Point"}
}