{
  "type": "Feature",
  "properties": {
    "addr:full":"16 Roy Pl Ramsey NJ 07446",
    "addr:housenumber":"16",
    "addr:postcode":"07446",
    "addr:street":"Roy Pl",
    "iso:country":"US",
    "sg:address":"16 Roy Pl",
    "sg:city":"Ramsey",
    "sg:classifiers":[
        {
            "category":"Professional",
            "subcategory":"Computer Services",
            "type":"Services"
        }
    ],
    "sg:phone":"+1   ",
    "sg:postcode":"07446",
    "sg:province":"NJ",
    "sg:tags":[
        "prepackaged",
        "software"
    ],
    "wof:name":"Jk Mulligan Software Inc",
    "wof:placetype":"venue"
},
  "geometry": {"coordinates":[-74.16321499999999,41.063425],"type":"Point"}
}