{
  "type": "Feature",
  "properties": {
    "iso:country":"US",
    "sg:address":"92 Clover Hill Rd",
    "sg:city":"Colts Neck",
    "sg:classifiers":[
        {
            "category":"Professional",
            "subcategory":"Management & Consulting",
            "type":"Services"
        },
        {
            "category":"Professional",
            "subcategory":"Computer Services",
            "type":"Services"
        }
    ],
    "sg:phone":"+1 732 332 1885",
    "sg:postcode":"07722",
    "sg:province":"NJ",
    "sg:tags":[
        "consultant",
        "integrated",
        "business",
        "solution"
    ],
    "wof:name":"Colts Neck Solutions LLC",
    "wof:placetype":"venue"
},
  "geometry": {"coordinates":[-74.21601099999999,40.33498],"type":"Point"}
}