{
  "type": "Feature",
  "properties": {
    "iso:country":"US",
    "sg:address":"265 Center Grove Rd",
    "sg:city":"Randolph",
    "sg:classifiers":[
        {
            "category":"Shopping",
            "subcategory":"Discount & Variety Stores",
            "type":"Retail Goods"
        }
    ],
    "sg:phone":"+1 973 361 2172",
    "sg:postcode":"07869",
    "sg:province":"NJ",
    "sg:tags":[
        "merchandise",
        "general"
    ],
    "wof:name":"Atlantic Finishing Supply",
    "wof:placetype":"venue"
},
  "geometry": {"coordinates":[-74.58306899999999,40.848972],"type":"Point"}
}