{
  "type": "Feature",
  "properties": {
    "addr:full":"3495 US Hwy 1 Princeton NJ 08540",
    "addr:housenumber":"3495",
    "addr:postcode":"08540",
    "addr:street":"Us Hwy 1",
    "iso:country":"US",
    "sg:address":"3495 US Hwy 1",
    "sg:city":"Princeton",
    "sg:classifiers":[
        {
            "category":"Food & Beverages",
            "subcategory":"Groceries & Convenience Stores",
            "type":"Retail Goods"
        }
    ],
    "sg:phone":"+1 609 799 2919",
    "sg:postcode":"08540",
    "sg:province":"NJ",
    "sg:tags":[
        "grocer"
    ],
    "wof:name":"Whole Foods Market",
    "wof:placetype":"venue"
},
  "geometry": {"coordinates":[-74.665812,40.308778],"type":"Point"}
}