{
  "type": "Feature",
  "properties": {
    "addr:full":"9 Westwood Dr Cape May Court House NJ 08210",
    "addr:housenumber":"9",
    "addr:postcode":"08210",
    "addr:street":"Westwood Dr Cape May",
    "iso:country":"US",
    "sg:address":"9 Westwood Dr",
    "sg:city":"Cape May Court House",
    "sg:classifiers":[
        {
            "category":"Farming",
            "subcategory":"Farm & Veterinary Services",
            "type":"Manufacturing & Wholesale Goods"
        }
    ],
    "sg:phone":"+1 609 465 7491",
    "sg:postcode":"08210",
    "sg:province":"NJ",
    "sg:tags":[
        "crop"
    ],
    "wof:name":"Sterling Irrrigation",
    "wof:placetype":"venue"
},
  "geometry": {"coordinates":[-74.840836,39.08656],"type":"Point"}
}