{
  "type": "Feature",
  "properties": {
    "addr:full":"100 Princeton Ave Princeton NJ 08540",
    "addr:housenumber":"100",
    "addr:postcode":"08540",
    "addr:street":"Princeton Ave",
    "iso:country":"US",
    "sg:address":"100 Princeton Ave",
    "sg:city":"Princeton",
    "sg:classifiers":[
        {
            "category":"Banks & Credit Unions",
            "subcategory":"Investment Brokerage",
            "type":"Services"
        }
    ],
    "sg:phone":"+1   ",
    "sg:postcode":"08540",
    "sg:province":"NJ",
    "sg:tags":[
        "advisory"
    ],
    "wof:name":"American Express",
    "wof:placetype":"venue"
},
  "geometry": {"coordinates":[-74.646096,40.350606],"type":"Point"}
}