{
  "type": "Feature",
  "properties": {
    "addr:full":"557 State Rte 17 Paramus NJ 07652",
    "addr:housenumber":"557",
    "addr:postcode":"07652",
    "addr:street":"State Rte 17",
    "iso:country":"US",
    "sg:address":"557 State Rte 17",
    "sg:city":"Paramus",
    "sg:classifiers":[
        {
            "category":"Shopping",
            "subcategory":"Stationery & Office Supplies",
            "type":"Retail Goods"
        }
    ],
    "sg:phone":"+1 201 670 6090",
    "sg:postcode":"07652",
    "sg:province":"NJ",
    "wof:name":"Staples",
    "wof:placetype":"venue"
},
  "geometry": {"coordinates":[-74.074977,40.95859],"type":"Point"}
}