{
  "type": "Feature",
  "properties": {
    "iso:country":"US",
    "sg:address":"116 Millburn Ave",
    "sg:city":"Millburn",
    "sg:classifiers":[
        {
            "category":"Personal",
            "type":"Services"
        }
    ],
    "sg:phone":"+1 973 379 0567",
    "sg:postcode":"07041",
    "sg:province":"NJ",
    "sg:tags":[
        "therapist",
        "massage"
    ],
    "wof:name":"R & R Therapeutic Massage Ctr",
    "wof:placetype":"venue"
},
  "geometry": {"coordinates":[-74.28915600000001,40.721883],"type":"Point"}
}