{
  "type": "Feature",
  "properties": {
    "addr:full":"230 Douglas Rd Far Hills NJ 07931",
    "addr:housenumber":"230",
    "addr:postcode":"07931",
    "addr:street":"Douglas Rd",
    "iso:country":"US",
    "sg:address":"230 Douglas Rd",
    "sg:city":"Far Hills",
    "sg:classifiers":[
        {
            "category":"Professional",
            "subcategory":"Management & Consulting",
            "type":"Services"
        }
    ],
    "sg:phone":"+1 908 604 9782",
    "sg:postcode":"07931",
    "sg:province":"NJ",
    "wof:name":"Mjp Services Inc",
    "wof:placetype":"venue"
},
  "geometry": {"coordinates":[-74.60941699999999,40.671003],"type":"Point"}
}