{
  "type": "Feature",
  "properties": {
    "iso:country":"US",
    "sg:address":"70 Cohansey St",
    "sg:city":"Bridgeton",
    "sg:classifiers":[
        {
            "category":"Health Services",
            "subcategory":"Doctor",
            "type":"Services"
        }
    ],
    "sg:phone":"+1 856 451 4700",
    "sg:postcode":"08302",
    "sg:province":"NJ",
    "sg:tags":[
        "clinic",
        "care",
        "primary",
        "facility"
    ],
    "wof:name":"Community Health Care Inc",
    "wof:placetype":"venue"
},
  "geometry": {"coordinates":[-75.234402,39.43049],"type":"Point"}
}