{
  "type": "Feature",
  "properties": {
    "iso:country":"US",
    "sg:address":"237 S Delsea Dr",
    "sg:city":"Vineland",
    "sg:classifiers":[
        {
            "category":"Professional",
            "subcategory":"Business Services",
            "type":"Services"
        }
    ],
    "sg:phone":"+1 856 692 4900",
    "sg:postcode":"08360",
    "sg:province":"NJ",
    "sg:tags":[
        "postal"
    ],
    "wof:name":"UPS Store 1314 The",
    "wof:placetype":"venue"
},
  "geometry": {"coordinates":[-75.043226,39.483742],"type":"Point"}
}