{
  "type": "Feature",
  "properties": {
    "addr:full":"45 Meadowlands Pkwy Secaucus NJ 07094",
    "addr:housenumber":"45",
    "addr:postcode":"07094",
    "addr:street":"Meadowlands Pkwy",
    "iso:country":"US",
    "sg:address":"45 Meadowlands Pkwy",
    "sg:city":"Secaucus",
    "sg:classifiers":[
        {
            "category":"Shopping",
            "subcategory":"Clothing, Apparel, & Fashions",
            "type":"Retail Goods"
        }
    ],
    "sg:phone":"+1 201 864 4248",
    "sg:postcode":"07094",
    "sg:province":"NJ",
    "sg:tags":[
        "lingerie"
    ],
    "wof:name":"Maidenform",
    "wof:placetype":"venue"
},
  "geometry": {"coordinates":[-74.06709499999999,40.796574],"type":"Point"}
}