{
  "type": "Feature",
  "properties": {
    "iso:country":"US",
    "sg:address":"141 S Black Horse Pike",
    "sg:city":"Blackwood",
    "sg:classifiers":[
        {
            "category":"Professional",
            "subcategory":"Accounting & Tax Preparation",
            "type":"Services"
        }
    ],
    "sg:phone":"+1 856 227 1100",
    "sg:postcode":"08012",
    "sg:province":"NJ",
    "wof:name":"Herbert Wachtel CPA & Co LLC",
    "wof:placetype":"venue"
},
  "geometry": {"coordinates":[-75.066114,39.800791],"type":"Point"}
}