{
  "type": "Feature",
  "properties": {
    "addr:full":"408 State Rte 71 Spring Lake NJ 07762",
    "addr:housenumber":"408",
    "addr:postcode":"07762",
    "addr:street":"State Rte 71",
    "iso:country":"US",
    "sg:address":"408 State Rte 71",
    "sg:city":"Spring Lake",
    "sg:classifiers":[
        {
            "category":"Shopping",
            "subcategory":"Used Merchandise",
            "type":"Retail Goods"
        }
    ],
    "sg:phone":"+1 732 974 6999",
    "sg:postcode":"07762",
    "sg:province":"NJ",
    "sg:tags":[
        "antique"
    ],
    "wof:name":"Inheritables",
    "wof:placetype":"venue"
},
  "geometry": {"coordinates":[-74.04144599999999,40.145641],"type":"Point"}
}