{
  "type": "Feature",
  "properties": {
    "addr:full":"1090 King Georges Post Rd Edison NJ 08837",
    "addr:housenumber":"1090",
    "addr:postcode":"08837",
    "addr:street":"King Georges Post Rd",
    "iso:country":"US",
    "sg:address":"1090 King Georges Post Rd",
    "sg:city":"Edison",
    "sg:classifiers":[
        {
            "category":"Wholesale",
            "subcategory":"Computers",
            "type":"Manufacturing & Wholesale Goods"
        }
    ],
    "sg:phone":"+1 732 417 0184",
    "sg:postcode":"08837",
    "sg:province":"NJ",
    "wof:name":"C C I Triad",
    "wof:placetype":"venue"
},
  "geometry": {"coordinates":[-74.32618600000001,40.524342],"type":"Point"}
}