{
  "type": "Feature",
  "properties": {
    "iso:country":"US",
    "sg:address":"1044 Lacey Rd",
    "sg:city":"Forked River",
    "sg:classifiers":[
        {
            "category":"Utilities",
            "subcategory":"Refuse",
            "type":"Services"
        }
    ],
    "sg:phone":"+1 609 646 7343",
    "sg:postcode":"08731",
    "sg:province":"NJ",
    "sg:tags":[
        "garbage",
        "collection"
    ],
    "wof:name":"MAB Debris Removal",
    "wof:placetype":"venue"
},
  "geometry": {"coordinates":[-74.216239,39.862633],"type":"Point"}
}