{
  "type": "Feature",
  "properties": {
    "addr:full":"545 Prospect St Maplewood NJ 07040",
    "addr:housenumber":"545",
    "addr:postcode":"07040",
    "addr:street":"Prospect St",
    "iso:country":"US",
    "sg:address":"545 Prospect St",
    "sg:city":"Maplewood",
    "sg:classifiers":[
        {
            "category":"Organizations",
            "subcategory":"Religious Organization",
            "type":"Services"
        }
    ],
    "sg:phone":"+1   ",
    "sg:postcode":"07040",
    "sg:province":"NJ",
    "sg:tags":[
        "training",
        "consulting",
        "computer",
        "company"
    ],
    "wof:name":"Knowhow2 Training",
    "wof:placetype":"venue"
},
  "geometry": {"coordinates":[-74.264601,40.732519],"type":"Point"}
}