{
  "type": "Feature",
  "properties": {
    "addr:full":"43 Alvin Sloan Rd Washington NJ 07882",
    "addr:housenumber":"43",
    "addr:postcode":"07882",
    "addr:street":"Alvin Sloan Rd",
    "iso:country":"US",
    "sg:address":"43 Alvin Sloan Rd",
    "sg:city":"Washington",
    "sg:classifiers":[
        {
            "category":"Building & Trades",
            "subcategory":"Construction",
            "type":"Services"
        }
    ],
    "sg:phone":"+1 908 689 7303",
    "sg:postcode":"07882",
    "sg:province":"NJ",
    "sg:tags":[
        "home",
        "builder"
    ],
    "wof:name":"Centex Homes",
    "wof:placetype":"venue"
},
  "geometry": {"coordinates":[-74.995772,40.762843],"type":"Point"}
}