{
  "type": "Feature",
  "properties": {
    "iso:country":"US",
    "sg:address":"125 Half Mile Rd",
    "sg:city":"Red Bank",
    "sg:classifiers":[
        {
            "category":"Professional",
            "subcategory":"Employment Agencies",
            "type":"Services"
        }
    ],
    "sg:phone":"+1 732 345 7163",
    "sg:postcode":"07701",
    "sg:province":"NJ",
    "sg:tags":[
        "help",
        "supply"
    ],
    "wof:name":"Officeteam",
    "wof:placetype":"venue"
},
  "geometry": {"coordinates":[-74.096047,40.340208],"type":"Point"}
}