{
  "type": "Feature",
  "properties": {
    "addr:full":"1 Louis St Carlstadt NJ 07072",
    "addr:housenumber":"1",
    "addr:postcode":"07072",
    "addr:street":"Louis St",
    "iso:country":"US",
    "sg:address":"1 Louis St",
    "sg:city":"Carlstadt",
    "sg:classifiers":[
        {
            "category":"Building & Trades",
            "subcategory":"Locksmith",
            "type":"Services"
        }
    ],
    "sg:phone":"+1 877 813 7228",
    "sg:postcode":"07072",
    "sg:province":"NJ",
    "sg:tags":[
        "key"
    ],
    "wof:name":"Emergency 24 Hour 7 Day Locksmith",
    "wof:placetype":"venue"
},
  "geometry": {"coordinates":[-74.038003,40.844269],"type":"Point"}
}