{
  "type": "Feature",
  "properties": {
    "addr:full":"50 Princeton Pl Princeton Jct NJ 08550",
    "addr:housenumber":"50",
    "addr:postcode":"08550",
    "addr:street":"Princeton Pl",
    "iso:country":"US",
    "sg:address":"50 Princeton Pl",
    "sg:city":"Princeton Jct",
    "sg:classifiers":[
        {
            "category":"Insurance",
            "subcategory":"Insurance Agent",
            "type":"Services"
        }
    ],
    "sg:phone":"+1 609 897 0788",
    "sg:postcode":"08550",
    "sg:province":"NJ",
    "wof:name":"Foram Insurance Corp",
    "wof:placetype":"venue"
},
  "geometry": {"coordinates":[-74.62077499999999,40.30086],"type":"Point"}
}