{
  "type": "Feature",
  "properties": {
    "addr:full":"250 Grant Ave Lyndhurst NJ 07071",
    "addr:housenumber":"250",
    "addr:postcode":"07071",
    "addr:street":"Grant Ave",
    "iso:country":"US",
    "sg:address":"250 Grant Ave",
    "sg:city":"Lyndhurst",
    "sg:classifiers":[
        {
            "category":"Arts & Performance",
            "subcategory":"Theater",
            "type":"Entertainment"
        }
    ],
    "sg:phone":"+1   ",
    "sg:postcode":"07071",
    "sg:province":"NJ",
    "sg:tags":[
        "group"
    ],
    "wof:name":"Renrek Entertainment Inc",
    "wof:placetype":"venue"
},
  "geometry": {"coordinates":[-74.122911,40.811113],"type":"Point"}
}