{
  "type": "Feature",
  "properties": {
    "iso:country":"US",
    "sg:address":"102 N Chelsea Ave",
    "sg:city":"Atlantic City",
    "sg:classifiers":[
        {
            "category":"Social Services",
            "type":"Services"
        }
    ],
    "sg:phone":"+1 609 345 2772",
    "sg:postcode":"08401",
    "sg:province":"NJ",
    "sg:tags":[
        "organization",
        "welfare"
    ],
    "wof:name":"Hispanic Alliance Of Atlantic",
    "wof:placetype":"venue"
},
  "geometry": {"coordinates":[-74.450643,39.35607],"type":"Point"}
}