{
  "type": "Feature",
  "properties": {
    "addr:full":"3118 Boardwalk Wildwood NJ 08260",
    "addr:housenumber":"3118",
    "addr:postcode":"08260",
    "addr:street":"Boardwalk",
    "iso:country":"US",
    "sg:address":"3118 Boardwalk",
    "sg:city":"Wildwood",
    "sg:classifiers":[
        {
            "category":"Food & Beverages",
            "subcategory":"Specialty",
            "type":"Retail Goods"
        }
    ],
    "sg:phone":"+1 877 247 8899",
    "sg:postcode":"08260",
    "sg:province":"NJ",
    "sg:website":"www.tornadofries.com",
    "wof:name":"Tornado Fries",
    "wof:placetype":"venue"
},
  "geometry": {"coordinates":[-74.808172,38.988186],"type":"Point"}
}