{
  "type": "Feature",
  "properties": {
    "addr:full":"30 Wheeler Rd Wayne NJ 07470",
    "addr:housenumber":"30",
    "addr:postcode":"07470",
    "addr:street":"Wheeler Rd",
    "iso:country":"US",
    "sg:address":"30 Wheeler Rd",
    "sg:city":"Wayne",
    "sg:classifiers":[
        {
            "category":"Professional",
            "subcategory":"Lawyer & Legal Services",
            "type":"Services"
        }
    ],
    "sg:phone":"+1 973 340 4600",
    "sg:postcode":"07470",
    "sg:province":"NJ",
    "wof:name":"Kornitzer Robert B Attorney At Law",
    "wof:placetype":"venue"
},
  "geometry": {"coordinates":[-74.267762,40.949372],"type":"Point"}
}