{
  "type": "Feature",
  "properties": {
    "iso:country":"US",
    "sg:address":"1955 S Orchard Rd",
    "sg:city":"Vineland",
    "sg:classifiers":[
        {
            "category":"Building & Trades",
            "subcategory":"Cleaning & Sanitation",
            "type":"Services"
        }
    ],
    "sg:phone":"+1 856 794 2286",
    "sg:postcode":"08360",
    "sg:province":"NJ",
    "sg:tags":[
        "janitor"
    ],
    "wof:name":"L & L Janitorial Svc",
    "wof:placetype":"venue"
},
  "geometry": {"coordinates":[-75.054762,39.456254],"type":"Point"}
}