{
  "type": "Feature",
  "properties": {
    "addr:full":"33 Richmond Ct Tinton Falls NJ 07712",
    "addr:housenumber":"33",
    "addr:postcode":"07712",
    "addr:street":"Richmond Ct",
    "iso:country":"US",
    "sg:address":"33 Richmond Ct",
    "sg:city":"Tinton Falls",
    "sg:classifiers":[
        {
            "category":"Shopping",
            "subcategory":"Hobbies, Toys, & Games",
            "type":"Retail Goods"
        }
    ],
    "sg:phone":"+1 732 493 8264",
    "sg:postcode":"07712",
    "sg:province":"NJ",
    "sg:tags":[
        "craft"
    ],
    "wof:name":"Paw Print Originals",
    "wof:placetype":"venue"
},
  "geometry": {"coordinates":[-74.083688,40.256676],"type":"Point"}
}