{
  "type": "Feature",
  "properties": {
    "addr:full":"3337 Teal Ln Lavallette NJ 08735",
    "addr:housenumber":"3337",
    "addr:postcode":"08735",
    "addr:street":"Teal Ln",
    "iso:country":"US",
    "sg:address":"3337 Teal Ln",
    "sg:city":"Lavallette",
    "sg:classifiers":[
        {
            "category":"Shopping",
            "subcategory":"Used Merchandise",
            "type":"Retail Goods"
        }
    ],
    "sg:phone":"+1   ",
    "sg:postcode":"08735",
    "sg:province":"NJ",
    "sg:tags":[
        "sales"
    ],
    "wof:name":"Bayshore Enterprises",
    "wof:placetype":"venue"
},
  "geometry": {"coordinates":[-74.06836699999999,39.99227],"type":"Point"}
}