{
  "type": "Feature",
  "properties": {
    "iso:country":"US",
    "sg:address":"621 Pinehurst Rd",
    "sg:city":"New Egypt",
    "sg:classifiers":[
        {
            "category":"Personal",
            "subcategory":"Beauty Salon",
            "type":"Services"
        }
    ],
    "sg:phone":"+1 609 752 0660",
    "sg:postcode":"08533",
    "sg:province":"NJ",
    "sg:tags":[
        "shop"
    ],
    "wof:name":"Nail Pro 2",
    "wof:placetype":"venue"
},
  "geometry": {"coordinates":[-74.478944,40.082593],"type":"Point"}
}