{
  "type": "Feature",
  "properties": {
    "iso:country":"US",
    "sg:address":"345 Commercial Ave",
    "sg:city":"Palisades Park",
    "sg:classifiers":[
        {
            "category":"Shopping",
            "subcategory":"Musical Instruments",
            "type":"Retail Goods"
        }
    ],
    "sg:phone":"+1   ",
    "sg:postcode":"07650",
    "sg:province":"NJ",
    "wof:name":"Ben Bridge Musical Instruments",
    "wof:placetype":"venue"
},
  "geometry": {"coordinates":[-74.000682,40.853297],"type":"Point"}
}