{
  "type": "Feature",
  "properties": {
    "addr:full":"248 Cannon Range Ave Milmay NJ 08340",
    "addr:housenumber":"248",
    "addr:postcode":"08340",
    "addr:street":"Cannon Range Ave",
    "iso:country":"US",
    "sg:address":"248 Cannon Range Ave",
    "sg:city":"Milmay",
    "sg:classifiers":[
        {
            "category":"Professional",
            "subcategory":"Detective & Security Services",
            "type":"Services"
        }
    ],
    "sg:phone":"+1   ",
    "sg:postcode":"08340",
    "sg:province":"NJ",
    "sg:tags":[
        "car"
    ],
    "wof:name":"L M Investigations LLC",
    "wof:placetype":"venue"
},
  "geometry": {"coordinates":[-74.890382,39.459162],"type":"Point"}
}