{
  "type": "Feature",
  "properties": {
    "iso:country":"US",
    "sg:address":"108 S Orange Ave",
    "sg:city":"South Orange",
    "sg:classifiers":[
        {
            "category":"Professional",
            "type":"Services"
        }
    ],
    "sg:phone":"+1 973 378 2005",
    "sg:postcode":"07079",
    "sg:province":"NJ",
    "wof:name":"SOS Special Occasion Svc",
    "wof:placetype":"venue"
},
  "geometry": {"coordinates":[-74.257284,40.745473],"type":"Point"}
}