{
  "type": "Feature",
  "properties": {
    "addr:full":"438 State Rte 35 Mantoloking NJ 08738",
    "addr:housenumber":"438",
    "addr:postcode":"08738",
    "addr:street":"State Rte 35",
    "iso:country":"US",
    "sg:address":"438 State Rte 35",
    "sg:city":"Mantoloking",
    "sg:classifiers":[
        {
            "category":"Real Estate",
            "subcategory":"Real Estate Agent",
            "type":"Services"
        }
    ],
    "sg:phone":"+1 732 830 1010",
    "sg:postcode":"08738",
    "sg:province":"NJ",
    "wof:name":"Gloria Nilson GMAC Rl Est",
    "wof:placetype":"venue"
},
  "geometry": {"coordinates":[-74.05860199999999,40.009828],"type":"Point"}
}