{
  "type": "Feature",
  "properties": {
    "addr:full":"101 W Main St Maple Shade NJ 08052",
    "addr:housenumber":"101",
    "addr:postcode":"08052",
    "addr:street":"W Main St",
    "iso:country":"US",
    "sg:address":"101 W Main St",
    "sg:city":"Maple Shade",
    "sg:classifiers":[
        {
            "category":"Food & Beverages",
            "subcategory":"Liquor & Beverages",
            "type":"Retail Goods"
        }
    ],
    "sg:phone":"+1 856 779 7878",
    "sg:postcode":"08052",
    "sg:province":"NJ",
    "wof:name":"Good Spirits",
    "wof:placetype":"venue"
},
  "geometry": {"coordinates":[-75.005748,39.954966],"type":"Point"}
}