{
  "type": "Feature",
  "properties": {
    "iso:country":"US",
    "sg:address":"3 Fox Run Dr",
    "sg:city":"Allamuchy",
    "sg:classifiers":[
        {
            "category":"Professional",
            "type":"Services"
        }
    ],
    "sg:phone":"+1   ",
    "sg:postcode":"07821",
    "sg:province":"NJ",
    "wof:name":"James Rollo",
    "wof:placetype":"venue"
},
  "geometry": {"coordinates":[-74.801084,40.977727],"type":"Point"}
}