{
  "type": "Feature",
  "properties": {
    "iso:country":"US",
    "sg:address":"3509 New York Ave",
    "sg:city":"Union City",
    "sg:classifiers":[
        {
            "category":"Freight",
            "type":"Transportation"
        }
    ],
    "sg:phone":"+1 201 392 1520",
    "sg:postcode":"07087",
    "sg:province":"NJ",
    "wof:name":"Ramstar Transportation Inc",
    "wof:placetype":"venue"
},
  "geometry": {"coordinates":[-74.026656,40.773534],"type":"Point"}
}