{
  "type": "Feature",
  "properties": {
    "addr:full":"715 N Haddon Ave Haddonfield NJ 08033",
    "addr:housenumber":"715",
    "addr:postcode":"08033",
    "addr:street":"N Haddon Ave",
    "iso:country":"US",
    "sg:address":"715 N Haddon Ave",
    "sg:city":"Haddonfield",
    "sg:classifiers":[
        {
            "category":"Shopping",
            "subcategory":"Pharmacy",
            "type":"Retail Goods"
        }
    ],
    "sg:phone":"+1 856 429 0252",
    "sg:postcode":"08033",
    "sg:province":"NJ",
    "sg:tags":[
        "supply",
        "drug",
        "aid",
        "drugstore",
        "store",
        "first"
    ],
    "sg:website":"http://www.riteaid.com",
    "wof:name":"Rite Aid",
    "wof:placetype":"venue"
},
  "geometry": {"coordinates":[-75.041901,39.9048],"type":"Point"}
}