{
  "type": "Feature",
  "properties": {
    "iso:country":"US",
    "sg:address":"2 Terrace Ave",
    "sg:city":"Lodi",
    "sg:classifiers":[
        {
            "category":"Real Estate",
            "subcategory":"Developer",
            "type":"Services"
        }
    ],
    "sg:phone":"+1 973 779 7272",
    "sg:postcode":"07644",
    "sg:province":"NJ",
    "sg:tags":[
        "funeral",
        "cemetery"
    ],
    "wof:name":"St Nicholas Cemetery",
    "wof:placetype":"venue"
},
  "geometry": {"coordinates":[-74.09030199999999,40.869301],"type":"Point"}
}