{
  "type": "Feature",
  "properties": {
    "iso:country":"US",
    "sg:address":"100 Frank E Rodgers Blvd S",
    "sg:city":"Harrison",
    "sg:classifiers":[
        {
            "category":"Social Services",
            "subcategory":"Child Care",
            "type":"Services"
        }
    ],
    "sg:phone":"+1   ",
    "sg:postcode":"07029",
    "sg:province":"NJ",
    "sg:tags":[
        "day"
    ],
    "wof:name":"The Tot Spot",
    "wof:placetype":"venue"
},
  "geometry": {"coordinates":[-74.156002,40.744628],"type":"Point"}
}