{
  "type": "Feature",
  "properties": {
    "addr:full":"325 S Hope Chapel Rd Jackson NJ 08527",
    "addr:housenumber":"325",
    "addr:postcode":"08527",
    "addr:street":"S Hope Chapel Rd",
    "iso:country":"US",
    "sg:address":"325 S Hope Chapel Rd",
    "sg:city":"Jackson",
    "sg:classifiers":[
        {
            "category":"Retail",
            "subcategory":"Animal Services",
            "type":"Services"
        }
    ],
    "sg:phone":"+1 732 364 3759",
    "sg:postcode":"08527",
    "sg:province":"NJ",
    "wof:name":"Clearfields Farm",
    "wof:placetype":"venue"
},
  "geometry": {"coordinates":[-74.273567,40.063728],"type":"Point"}
}