{
  "type": "Feature",
  "properties": {
    "addr:full":"254 Mountain Ave Hackettstown NJ 07840",
    "addr:housenumber":"254",
    "addr:postcode":"07840",
    "addr:street":"Mountain Ave",
    "iso:country":"US",
    "sg:address":"254 Mountain Ave",
    "sg:city":"Hackettstown",
    "sg:classifiers":[
        {
            "category":"Real Estate",
            "subcategory":"Real Estate Operator",
            "type":"Services"
        }
    ],
    "sg:phone":"+1 908 852 7232",
    "sg:postcode":"07840",
    "sg:province":"NJ",
    "sg:tags":[
        "building",
        "parks"
    ],
    "wof:name":"Mountainview Park",
    "wof:placetype":"venue"
},
  "geometry": {"coordinates":[-74.82343299999999,40.838502],"type":"Point"}
}