{
  "type": "Feature",
  "properties": {
    "iso:country":"US",
    "sg:address":"87 Main St",
    "sg:city":"Lincoln Park",
    "sg:classifiers":[
        {
            "category":"Utilities",
            "subcategory":"Refuse",
            "type":"Services"
        }
    ],
    "sg:phone":"+1 973 872 9452",
    "sg:postcode":"07035",
    "sg:province":"NJ",
    "sg:tags":[
        "environmental",
        "construction"
    ],
    "wof:name":"Abateco Construction Company",
    "wof:placetype":"venue"
},
  "geometry": {"coordinates":[-74.31371799999999,40.923662],"type":"Point"}
}