{
  "type": "Feature",
  "properties": {
    "iso:country":"US",
    "sg:address":"5 Hengeli Dr",
    "sg:city":"Bordentown",
    "sg:classifiers":[
        {
            "category":"Building & Trades",
            "subcategory":"Construction",
            "type":"Services"
        }
    ],
    "sg:phone":"+1 609 298 4824",
    "sg:postcode":"08515",
    "sg:province":"NJ",
    "sg:tags":[
        "residential",
        "industrial",
        "commercial",
        "painting",
        "contractor"
    ],
    "wof:name":"Alltype Painting Contractors",
    "wof:placetype":"venue"
},
  "geometry": {"coordinates":[-74.681192,40.1457],"type":"Point"}
}