{
  "type": "Feature",
  "properties": {
    "iso:country":"US",
    "sg:address":"470 Clifton Ave",
    "sg:city":"Clifton",
    "sg:classifiers":[
        {
            "category":"Wholesale",
            "subcategory":"Electrical",
            "type":"Manufacturing & Wholesale Goods"
        }
    ],
    "sg:phone":"+1 973 546 5022",
    "sg:postcode":"07011",
    "sg:province":"NJ",
    "sg:tags":[
        "parts",
        "electronic",
        "capacitor"
    ],
    "wof:name":"Elcon Sales Distributor",
    "wof:placetype":"venue"
},
  "geometry": {"coordinates":[-74.147592,40.873967],"type":"Point"}
}