{
  "type": "Feature",
  "properties": {
    "iso:country":"US",
    "sg:address":"1366 Kings Hwy",
    "sg:city":"Pilesgrove",
    "sg:classifiers":[
        {
            "category":"Building & Trades",
            "subcategory":"Construction",
            "type":"Services"
        }
    ],
    "sg:phone":"+1 856 769 1144",
    "sg:postcode":"08098",
    "sg:province":"NJ",
    "sg:tags":[
        "steel",
        "erectors"
    ],
    "wof:name":"Holly Steel Erectors Inc",
    "wof:placetype":"venue"
},
  "geometry": {"coordinates":[-75.33809100000001,39.687534],"type":"Point"}
}