{
  "type": "Feature",
  "properties": {
    "addr:full":"592 10th St Hammonton NJ 08037",
    "addr:housenumber":"592",
    "addr:postcode":"08037",
    "addr:street":"10Th St",
    "iso:country":"US",
    "sg:address":"592 10th St",
    "sg:city":"Hammonton",
    "sg:classifiers":[
        {
            "category":"Wholesale",
            "subcategory":"Fruits & Vegetables",
            "type":"Manufacturing & Wholesale Goods"
        }
    ],
    "sg:phone":"+1 856 691 3711",
    "sg:postcode":"08037",
    "sg:province":"NJ",
    "wof:name":"Don-A-Lynn Produce Inc",
    "wof:placetype":"venue"
},
  "geometry": {"coordinates":[-74.80459399999999,39.612505],"type":"Point"}
}