{
  "type": "Feature",
  "properties": {
    "iso:country":"US",
    "sg:address":"12 Trojan Ave",
    "sg:city":"Parsippany",
    "sg:classifiers":[
        {
            "category":"Professional",
            "type":"Services"
        }
    ],
    "sg:phone":"+1   ",
    "sg:postcode":"07054",
    "sg:province":"NJ",
    "wof:name":"Docutek Services LLC",
    "wof:placetype":"venue"
},
  "geometry": {"coordinates":[-74.434794,40.867564],"type":"Point"}
}