{
  "type": "Feature",
  "properties": {
    "iso:country":"US",
    "sg:address":"79 Union Blvd Ste 16",
    "sg:city":"Totowa",
    "sg:classifiers":[
        {
            "category":"Health Services",
            "subcategory":"Health Practitioner",
            "type":"Services"
        }
    ],
    "sg:phone":"+1 973 956 7807",
    "sg:postcode":"07512",
    "sg:province":"NJ",
    "sg:tags":[
        "therapy",
        "physical"
    ],
    "wof:name":"Action Physcial Therapy & Sports Rehab Inc",
    "wof:placetype":"venue"
},
  "geometry": {"coordinates":[-74.20334200000001,40.90968],"type":"Point"}
}