{
  "type": "Feature",
  "properties": {
    "iso:country":"US",
    "sg:address":"42 Wynnewood Rd",
    "sg:city":"Livingston",
    "sg:classifiers":[
        {
            "category":"Professional",
            "subcategory":"Business Services",
            "type":"Services"
        }
    ],
    "sg:phone":"+1   ",
    "sg:postcode":"07039",
    "sg:province":"NJ",
    "wof:name":"Galaxy Technologies Inc",
    "wof:placetype":"venue"
},
  "geometry": {"coordinates":[-74.33975599999999,40.789072],"type":"Point"}
}