{
  "type": "Feature",
  "properties": {
    "addr:full":"55 Cloverdale Cir Tinton Falls NJ 07724",
    "addr:housenumber":"55",
    "addr:postcode":"07724",
    "addr:street":"Cloverdale Cir",
    "iso:country":"US",
    "sg:address":"55 Cloverdale Cir",
    "sg:city":"Tinton Falls",
    "sg:classifiers":[
        {
            "category":"Professional",
            "subcategory":"Business Services",
            "type":"Services"
        }
    ],
    "sg:phone":"+1 732 544 9492",
    "sg:postcode":"07724",
    "sg:province":"NJ",
    "sg:tags":[
        "development"
    ],
    "wof:name":"Monmouth Business Referral Grp",
    "wof:placetype":"venue"
},
  "geometry": {"coordinates":[-74.089669,40.312423],"type":"Point"}
}