{
  "type": "Feature",
  "properties": {
    "iso:country":"US",
    "sg:address":"2510 Belmar Blvd",
    "sg:city":"Belmar",
    "sg:classifiers":[
        {
            "category":"Professional",
            "subcategory":"Management & Consulting",
            "type":"Services"
        }
    ],
    "sg:phone":"+1 732 681 1770",
    "sg:postcode":"07719",
    "sg:province":"NJ",
    "sg:tags":[
        "consultant",
        "automation"
    ],
    "wof:name":"Jersey Shore Automation",
    "wof:placetype":"venue"
},
  "geometry": {"coordinates":[-74.061998,40.175866],"type":"Point"}
}