{
  "type": "Feature",
  "properties": {
    "iso:country":"US",
    "sg:address":"707 Bergen Ave",
    "sg:city":"Jersey City",
    "sg:classifiers":[
        {
            "category":"Wholesale",
            "subcategory":"Machinery & Supplies",
            "type":"Manufacturing & Wholesale Goods"
        }
    ],
    "sg:phone":"+1 201 946 0400",
    "sg:postcode":"07306",
    "sg:province":"NJ",
    "sg:tags":[
        "contractor"
    ],
    "wof:name":"One On One General Contracting",
    "wof:placetype":"venue"
},
  "geometry": {"coordinates":[-74.06988,40.724291],"type":"Point"}
}