{
  "type": "Feature",
  "properties": {
    "iso:country":"US",
    "sg:address":"300 Locust St",
    "sg:city":"Roselle Park",
    "sg:classifiers":[
        {
            "category":"Restaurant",
            "type":"Food & Drink"
        }
    ],
    "sg:phone":"+1 908 245 9795",
    "sg:postcode":"07204",
    "sg:province":"NJ",
    "sg:tags":[
        "sandwich"
    ],
    "wof:name":"Larry's Submarine Sandwiches",
    "wof:placetype":"venue"
},
  "geometry": {"coordinates":[-74.26771599999999,40.664376],"type":"Point"}
}