{
  "type": "Feature",
  "properties": {
    "iso:country":"US",
    "sg:address":"101 Lassen Ct",
    "sg:city":"Princeton",
    "sg:classifiers":[
        {
            "category":"Professional",
            "subcategory":"Lawyer & Legal Services",
            "type":"Services"
        }
    ],
    "sg:phone":"+1 609 734 0308",
    "sg:postcode":"08540",
    "sg:province":"NJ",
    "sg:tags":[
        "attorney"
    ],
    "wof:name":"Joseph M Jacobs Law Offices",
    "wof:placetype":"venue"
},
  "geometry": {"coordinates":[-74.66405399999999,40.316167],"type":"Point"}
}