{
  "type": "Feature",
  "properties": {
    "addr:full":"400 E Randolph Ave Dover NJ 07803",
    "addr:housenumber":"400",
    "addr:postcode":"07803",
    "addr:street":"E Randolph Ave",
    "iso:country":"US",
    "sg:address":"400 E Randolph Ave",
    "sg:city":"Dover",
    "sg:classifiers":[
        {
            "category":"Professional",
            "subcategory":"Computer Services",
            "type":"Services"
        }
    ],
    "sg:phone":"+1 973 361 4310",
    "sg:postcode":"07803",
    "sg:province":"NJ",
    "sg:tags":[
        "programing",
        "custom"
    ],
    "wof:name":"Curwell Consultants Inc",
    "wof:placetype":"venue"
},
  "geometry": {"coordinates":[-74.59704000000001,40.869491],"type":"Point"}
}