{
  "type": "Feature",
  "properties": {
    "iso:country":"US",
    "sg:address":"66 Willow Ave",
    "sg:city":"Hoboken",
    "sg:classifiers":[
        {
            "category":"Professional",
            "subcategory":"Management & Consulting",
            "type":"Services"
        }
    ],
    "sg:phone":"+1 201 610 1063",
    "sg:postcode":"07030",
    "sg:province":"NJ",
    "sg:tags":[
        "construction"
    ],
    "wof:name":"Will Wallace Carpenters",
    "wof:placetype":"venue"
},
  "geometry": {"coordinates":[-74.034943,40.73654],"type":"Point"}
}