{
  "type": "Feature",
  "properties": {
    "addr:full":"150 Overlook Ave Hackensack NJ 07601",
    "addr:housenumber":"150",
    "addr:postcode":"07601",
    "addr:street":"Overlook Ave",
    "iso:country":"US",
    "sg:address":"150 Overlook Ave",
    "sg:city":"Hackensack",
    "sg:classifiers":[
        {
            "category":"Health Services",
            "subcategory":"Doctor",
            "type":"Services"
        }
    ],
    "sg:phone":"+1 201 487 8010",
    "sg:postcode":"07601",
    "sg:province":"NJ",
    "sg:website":"www.mdslim.com",
    "wof:name":"Chhabra Anjana MD",
    "wof:placetype":"venue"
},
  "geometry": {"coordinates":[-74.05471900000001,40.887576],"type":"Point"}
}