{
  "type": "Feature",
  "properties": {
    "addr:full":"421 N Otter Branch Dr Glendora NJ 08029",
    "addr:housenumber":"421",
    "addr:postcode":"08029",
    "addr:street":"N Otter Branch Dr",
    "iso:country":"US",
    "sg:address":"421 N Otter Branch Dr",
    "sg:city":"Glendora",
    "sg:classifiers":[
        {
            "category":"Health Services",
            "subcategory":"Health Practitioner",
            "type":"Services"
        }
    ],
    "sg:phone":"+1 856 939 5560",
    "sg:postcode":"08029",
    "sg:province":"NJ",
    "sg:tags":[
        "physician"
    ],
    "wof:name":"Nature's Hospital",
    "wof:placetype":"venue"
},
  "geometry": {"coordinates":[-75.061778,39.840896],"type":"Point"}
}