{
  "type": "Feature",
  "properties": {
    "addr:full":"65 Maplewood Dr Middletown NJ 07748",
    "addr:housenumber":"65",
    "addr:postcode":"07748",
    "addr:street":"Maplewood Dr",
    "iso:country":"US",
    "sg:address":"65 Maplewood Dr",
    "sg:city":"Middletown",
    "sg:classifiers":[
        {
            "category":"Building & Trades",
            "subcategory":"Construction",
            "type":"Services"
        }
    ],
    "sg:phone":"+1 732 615 0129",
    "sg:postcode":"07748",
    "sg:province":"NJ",
    "sg:tags":[
        "builder"
    ],
    "wof:name":"R Lee Builders",
    "wof:placetype":"venue"
},
  "geometry": {"coordinates":[-74.111958,40.419236],"type":"Point"}
}