{
  "type": "Feature",
  "properties": {
    "addr:full":"19 Autumn Dr Moorestown NJ 08057",
    "addr:housenumber":"19",
    "addr:postcode":"08057",
    "addr:street":"Autumn Dr",
    "iso:country":"US",
    "sg:address":"19 Autumn Dr",
    "sg:city":"Moorestown",
    "sg:classifiers":[
        {
            "category":"Restaurant",
            "type":"Food & Drink"
        }
    ],
    "sg:phone":"+1   ",
    "sg:postcode":"08057",
    "sg:province":"NJ",
    "sg:tags":[
        "eating"
    ],
    "wof:name":"McDonalds",
    "wof:placetype":"venue"
},
  "geometry": {"coordinates":[-74.91612600000001,39.99136],"type":"Point"}
}