{
  "type": "Feature",
  "properties": {
    "iso:country":"US",
    "sg:address":"200 Fulton St",
    "sg:city":"Riverton",
    "sg:classifiers":[
        {
            "category":"Professional",
            "subcategory":"Business Services",
            "type":"Services"
        }
    ],
    "sg:phone":"+1   ",
    "sg:postcode":"08077",
    "sg:province":"NJ",
    "wof:name":"Assoc of Operating Room N",
    "wof:placetype":"venue"
},
  "geometry": {"coordinates":[-75.012241,40.013039],"type":"Point"}
}