{
  "type": "Feature",
  "properties": {
    "iso:country":"US",
    "sg:address":"3135 Us Highway 9",
    "sg:city":"Old Bridge",
    "sg:classifiers":[
        {
            "category":"Restaurant",
            "type":"Food & Drink"
        }
    ],
    "sg:menulink":"http://www.allmenus.com/nj/old-bridge/32910-ciccones/menu/",
    "sg:phone":"+1 732 679 5006",
    "sg:postcode":"08857",
    "sg:province":"NJ",
    "sg:tags":[
        "italian"
    ],
    "wof:name":"Ciccone's",
    "wof:placetype":"venue"
},
  "geometry": {"coordinates":[-74.307777,40.380994],"type":"Point"}
}