{
  "type": "Feature",
  "properties": {
    "addr:full":"16 Taylor St Washington NJ 07882",
    "addr:housenumber":"16",
    "addr:postcode":"07882",
    "addr:street":"Taylor St",
    "iso:country":"US",
    "sg:address":"16 Taylor St",
    "sg:city":"Washington",
    "sg:classifiers":[
        {
            "category":"Education",
            "subcategory":"School",
            "type":"Public Place"
        }
    ],
    "sg:phone":"+1 908 689 3549",
    "sg:postcode":"07882",
    "sg:province":"NJ",
    "wof:name":"Washington Borough Public",
    "wof:placetype":"venue"
},
  "geometry": {"coordinates":[-74.97986400000001,40.761002],"type":"Point"}
}