{
  "type": "Feature",
  "properties": {
    "iso:country":"US",
    "sg:address":"489 Radovan Ave",
    "sg:city":"Bayville",
    "sg:classifiers":[
        {
            "category":"Building & Trades",
            "subcategory":"Construction",
            "type":"Services"
        }
    ],
    "sg:phone":"+1 732 269 1059",
    "sg:postcode":"08721",
    "sg:province":"NJ",
    "wof:name":"Price Custom Builders",
    "wof:placetype":"venue"
},
  "geometry": {"coordinates":[-74.17026300000001,39.889199],"type":"Point"}
}