{
  "type": "Feature",
  "properties": {
    "iso:country":"US",
    "sg:address":"9 Tulip St",
    "sg:city":"Passaic",
    "sg:classifiers":[
        {
            "category":"Organizations",
            "subcategory":"Religious Organization",
            "type":"Services"
        }
    ],
    "sg:phone":"+1 973 471 7949",
    "sg:postcode":"07055",
    "sg:province":"NJ",
    "wof:name":"Mt Moriah Baptist Church",
    "wof:placetype":"venue"
},
  "geometry": {"coordinates":[-74.134102,40.8629],"type":"Point"}
}