{
  "type": "Feature",
  "properties": {
    "addr:full":"17 W Park Ave Merchantville NJ 08109",
    "addr:housenumber":"17",
    "addr:postcode":"08109",
    "addr:street":"W Park Ave",
    "iso:country":"US",
    "sg:address":"17 W Park Ave",
    "sg:city":"Merchantville",
    "sg:classifiers":[
        {
            "category":"Home & Garden",
            "subcategory":"Furniture",
            "type":"Retail Goods"
        }
    ],
    "sg:phone":"+1 856 662 7753",
    "sg:postcode":"08109",
    "sg:province":"NJ",
    "sg:tags":[
        "cabinet"
    ],
    "wof:name":"Cabinet Master",
    "wof:placetype":"venue"
},
  "geometry": {"coordinates":[-75.050282,39.950471],"type":"Point"}
}