{
  "type": "Feature",
  "properties": {
    "iso:country":"US",
    "sg:address":"115 S Plainfield Ave",
    "sg:city":"South Plainfield",
    "sg:classifiers":[
        {
            "category":"Real Estate",
            "subcategory":"Real Estate Operator",
            "type":"Services"
        }
    ],
    "sg:phone":"+1   ",
    "sg:postcode":"07080",
    "sg:province":"NJ",
    "sg:tags":[
        "building",
        "nonresidential"
    ],
    "wof:name":"McGraw Properties LLC",
    "wof:placetype":"venue"
},
  "geometry": {"coordinates":[-74.40876,40.580309],"type":"Point"}
}