{
  "type": "Feature",
  "properties": {
    "iso:country":"US",
    "sg:address":"123 Morris St Ste 2",
    "sg:city":"Morristown",
    "sg:classifiers":[
        {
            "category":"Home & Garden",
            "subcategory":"Garden Supply",
            "type":"Retail Goods"
        }
    ],
    "sg:phone":"+1 973 538 1819",
    "sg:postcode":"07960",
    "sg:province":"NJ",
    "sg:tags":[
        "nursery",
        "gardening"
    ],
    "wof:name":"Moore's Hardware",
    "wof:placetype":"venue"
},
  "geometry": {"coordinates":[-74.474602,40.796799],"type":"Point"}
}