{
  "type": "Feature",
  "properties": {
    "addr:full":"863 Nancy Way Westfield NJ 07090",
    "addr:housenumber":"863",
    "addr:postcode":"07090",
    "addr:street":"Nancy Way",
    "iso:country":"US",
    "sg:address":"863 Nancy Way",
    "sg:city":"Westfield",
    "sg:classifiers":[
        {
            "category":"Wholesale",
            "subcategory":"Furniture",
            "type":"Manufacturing & Wholesale Goods"
        }
    ],
    "sg:phone":"+1 908 232 6245",
    "sg:postcode":"07090",
    "sg:province":"NJ",
    "wof:name":"Michael Christian Designs Inc",
    "wof:placetype":"venue"
},
  "geometry": {"coordinates":[-74.347244,40.630644],"type":"Point"}
}