{
  "type": "Feature",
  "properties": {
    "iso:country":"US",
    "sg:address":"480 Bergen Blvd",
    "sg:city":"Ridgefield",
    "sg:classifiers":[
        {
            "category":"Travel",
            "subcategory":"Travel Agent",
            "type":"Entertainment"
        }
    ],
    "sg:phone":"+1 201 854 6900",
    "sg:postcode":"07657",
    "sg:province":"NJ",
    "sg:tags":[
        "agency",
        "bureau"
    ],
    "wof:name":"World Premiere Travel Inc",
    "wof:placetype":"venue"
},
  "geometry": {"coordinates":[-73.997686,40.823809],"type":"Point"}
}