{
  "type": "Feature",
  "properties": {
    "addr:full":"478 Mark Rd Allendale NJ 07401",
    "addr:housenumber":"478",
    "addr:postcode":"07401",
    "addr:street":"Mark Rd",
    "iso:country":"US",
    "sg:address":"478 Mark Rd",
    "sg:city":"Allendale",
    "sg:classifiers":[
        {
            "category":"Professional",
            "subcategory":"Computer Services",
            "type":"Services"
        }
    ],
    "sg:phone":"+1   ",
    "sg:postcode":"07401",
    "sg:province":"NJ",
    "sg:tags":[
        "programing",
        "custom"
    ],
    "wof:name":"Cz Solutions Inc",
    "wof:placetype":"venue"
},
  "geometry": {"coordinates":[-74.15251000000001,41.024182],"type":"Point"}
}