{
  "type": "Feature",
  "properties": {
    "addr:full":"800 S 15th St Newark NJ 07108",
    "addr:housenumber":"800",
    "addr:postcode":"07108",
    "addr:street":"S 15Th St",
    "iso:country":"US",
    "sg:address":"800 S 15th St",
    "sg:city":"Newark",
    "sg:classifiers":[
        {
            "category":"Professional",
            "subcategory":"Business Services",
            "type":"Services"
        }
    ],
    "sg:phone":"+1   ",
    "sg:postcode":"07108",
    "sg:province":"NJ",
    "wof:name":"K&A Assoc",
    "wof:placetype":"venue"
},
  "geometry": {"coordinates":[-74.210717,40.726896],"type":"Point"}
}