{
  "type": "Feature",
  "properties": {
    "addr:full":"1071 Co Rd 523 Flemington NJ 08822",
    "addr:housenumber":"1071",
    "addr:postcode":"08822",
    "addr:street":"Co Rd 523",
    "iso:country":"US",
    "sg:address":"1071 Co Rd 523",
    "sg:city":"Flemington",
    "sg:classifiers":[
        {
            "category":"Utilities",
            "subcategory":"Refuse",
            "type":"Services"
        }
    ],
    "sg:phone":"+1 908 782 7686",
    "sg:postcode":"08822",
    "sg:province":"NJ",
    "sg:tags":[
        "system"
    ],
    "wof:name":"Space Savers Inc",
    "wof:placetype":"venue"
},
  "geometry": {"coordinates":[-74.82794199999999,40.543608],"type":"Point"}
}