{
  "type": "Feature",
  "properties": {
    "addr:full":"303 Holly Dell Dr Sewell NJ 08080",
    "addr:housenumber":"303",
    "addr:postcode":"08080",
    "addr:street":"Holly Dell Dr",
    "iso:country":"US",
    "sg:address":"303 Holly Dell Dr",
    "sg:city":"Sewell",
    "sg:classifiers":[
        {
            "category":"Real Estate",
            "subcategory":"Developer",
            "type":"Services"
        }
    ],
    "sg:phone":"+1   ",
    "sg:postcode":"08080",
    "sg:province":"NJ",
    "wof:name":"Hedenberg & Gerstein",
    "wof:placetype":"venue"
},
  "geometry": {"coordinates":[-75.10964300000001,39.746666],"type":"Point"}
}