{
  "type": "Feature",
  "properties": {
    "iso:country":"US",
    "sg:address":"520 Sicklerville Rd",
    "sg:city":"Sicklerville",
    "sg:classifiers":[
        {
            "category":"Shopping",
            "subcategory":"Florist",
            "type":"Retail Goods"
        }
    ],
    "sg:phone":"+1 856 740 4491",
    "sg:postcode":"08081",
    "sg:province":"NJ",
    "wof:name":"Addie Rose Gift & Floral Shop",
    "wof:placetype":"venue"
},
  "geometry": {"coordinates":[-74.977715,39.722314],"type":"Point"}
}