{
  "type": "Feature",
  "properties": {
    "iso:country":"US",
    "sg:address":"1 Frassetto Way",
    "sg:city":"Lincoln Park",
    "sg:classifiers":[
        {
            "category":"Building & Trades",
            "subcategory":"Construction",
            "type":"Services"
        }
    ],
    "sg:phone":"+1 973 709 1240",
    "sg:postcode":"07035",
    "sg:province":"NJ",
    "sg:tags":[
        "fire",
        "restoration",
        "damage"
    ],
    "wof:name":"Belfor",
    "wof:placetype":"venue"
},
  "geometry": {"coordinates":[-74.28961099999999,40.917776],"type":"Point"}
}