{
  "type": "Feature",
  "properties": {
    "iso:country":"US",
    "sg:address":"289 Stuyvesant Ave",
    "sg:city":"Lyndhurst",
    "sg:classifiers":[
        {
            "category":"Arts & Performance",
            "subcategory":"Arts Center",
            "type":"Entertainment"
        }
    ],
    "sg:phone":"+1 201 460 1088",
    "sg:postcode":"07071",
    "sg:province":"NJ",
    "sg:tags":[
        "performing"
    ],
    "wof:name":"Studio Workshop",
    "wof:placetype":"venue"
},
  "geometry": {"coordinates":[-74.126801,40.813702],"type":"Point"}
}