{
  "type": "Feature",
  "properties": {
    "addr:full":"346 Newark Pompton Tpke Wayne NJ 07470",
    "addr:housenumber":"346",
    "addr:postcode":"07470",
    "addr:street":"Newark Pompton Tpke",
    "iso:country":"US",
    "sg:address":"346 Newark Pompton Tpke",
    "sg:city":"Wayne",
    "sg:classifiers":[
        {
            "category":"Food & Beverages",
            "subcategory":"Groceries & Convenience Stores",
            "type":"Retail Goods"
        }
    ],
    "sg:phone":"+1   ",
    "sg:postcode":"07470",
    "sg:province":"NJ",
    "wof:name":"Safeway Elevator Co",
    "wof:placetype":"venue"
},
  "geometry": {"coordinates":[-74.273971,40.93701],"type":"Point"}
}