{
  "type": "Feature",
  "properties": {
    "addr:full":"53 Center Ave Morristown NJ 07960",
    "addr:housenumber":"53",
    "addr:postcode":"07960",
    "addr:street":"Center Ave",
    "iso:country":"US",
    "sg:address":"53 Center Ave",
    "sg:city":"Morristown",
    "sg:classifiers":[
        {
            "category":"Professional",
            "subcategory":"Business Services",
            "type":"Services"
        }
    ],
    "sg:phone":"+1   ",
    "sg:postcode":"07960",
    "sg:province":"NJ",
    "wof:name":"Snail Mail Express LLC",
    "wof:placetype":"venue"
},
  "geometry": {"coordinates":[-74.49648000000001,40.793063],"type":"Point"}
}