{
  "type": "Feature",
  "properties": {
    "iso:country":"US",
    "sg:address":"339 N Front St",
    "sg:city":"Camden",
    "sg:phone":"+1 856 964 5330",
    "sg:postcode":"08102",
    "sg:province":"NJ",
    "wof:name":"Andrew M Duclair Pc",
    "wof:placetype":"venue"
},
  "geometry": {"coordinates":[-75.125663,39.949359],"type":"Point"}
}