{
  "type": "Feature",
  "properties": {
    "iso:country":"US",
    "sg:address":"1313 Tanner Ave",
    "sg:city":"Burlington",
    "sg:classifiers":[
        {
            "category":"Professional",
            "type":"Services"
        }
    ],
    "sg:phone":"+1 609 386 3311",
    "sg:postcode":"08016",
    "sg:province":"NJ",
    "sg:tags":[
        "establishment"
    ],
    "wof:name":"Z E C O",
    "wof:placetype":"venue"
},
  "geometry": {"coordinates":[-74.87080899999999,40.059627],"type":"Point"}
}