{
  "type": "Feature",
  "properties": {
    "addr:full":"26 E Palisade Ave Englewood NJ 07631",
    "addr:housenumber":"26",
    "addr:postcode":"07631",
    "addr:street":"E Palisade Ave",
    "iso:country":"US",
    "sg:address":"26 E Palisade Ave",
    "sg:city":"Englewood",
    "sg:classifiers":[
        {
            "category":"Shopping",
            "subcategory":"Clothing, Apparel, & Fashions",
            "type":"Retail Goods"
        }
    ],
    "sg:phone":"+1   ",
    "sg:postcode":"07631",
    "sg:province":"NJ",
    "sg:tags":[
        "boy",
        "man"
    ],
    "wof:name":"Vero Uomo",
    "wof:placetype":"venue"
},
  "geometry": {"coordinates":[-73.973206,40.892886],"type":"Point"}
}