{
  "type": "Feature",
  "properties": {
    "iso:country":"US",
    "sg:address":"60 Madison Pl",
    "sg:city":"Ridgewood",
    "sg:classifiers":[
        {
            "category":"Health Services",
            "subcategory":"Doctor",
            "type":"Services"
        }
    ],
    "sg:phone":"+1 201 445 4844",
    "sg:postcode":"07450",
    "sg:province":"NJ",
    "sg:tags":[
        "physician",
        "surgeon"
    ],
    "wof:name":"William H Bristow Jr MD",
    "wof:placetype":"venue"
},
  "geometry": {"coordinates":[-74.123338,40.982283],"type":"Point"}
}