{
  "type": "Feature",
  "properties": {
    "addr:full":"946 State Rte 17 Ramsey NJ 07446",
    "addr:housenumber":"946",
    "addr:postcode":"07446",
    "addr:street":"State Rte 17",
    "iso:country":"US",
    "sg:address":"946 State Rte 17",
    "sg:city":"Ramsey",
    "sg:classifiers":[
        {
            "category":"Travel",
            "subcategory":"Hotels & Motels",
            "type":"Entertainment"
        }
    ],
    "sg:phone":"+1   ",
    "sg:postcode":"07446",
    "sg:province":"NJ",
    "wof:name":"Wellesley Inn",
    "wof:placetype":"venue"
},
  "geometry": {"coordinates":[-74.132248,41.066067],"type":"Point"}
}