{
  "type": "Feature",
  "properties": {
    "iso:country":"US",
    "sg:address":"700 Main St",
    "sg:city":"Avon By The Sea",
    "sg:classifiers":[
        {
            "category":"Professional",
            "subcategory":"Lawyer & Legal Services",
            "type":"Services"
        }
    ],
    "sg:phone":"+1 732 502 0200",
    "sg:postcode":"07717",
    "sg:province":"NJ",
    "sg:tags":[
        "attorney"
    ],
    "wof:name":"Alfred J D'Auria",
    "wof:placetype":"venue"
},
  "geometry": {"coordinates":[-74.020737,40.195442],"type":"Point"}
}