{
  "type": "Feature",
  "properties": {
    "iso:country":"US",
    "sg:address":"821 Haddon Ave",
    "sg:city":"Collingswood",
    "sg:classifiers":[
        {
            "category":"Home & Garden",
            "subcategory":"Furniture",
            "type":"Retail Goods"
        }
    ],
    "sg:phone":"+1 856 833 1611",
    "sg:postcode":"08108",
    "sg:province":"NJ",
    "wof:name":"I Wood",
    "wof:placetype":"venue"
},
  "geometry": {"coordinates":[-75.065558,39.915378],"type":"Point"}
}