{
  "type": "Feature",
  "properties": {
    "iso:country":"US",
    "sg:address":"1189 Broad St",
    "sg:city":"Clifton",
    "sg:classifiers":[
        {
            "category":"Food & Beverages",
            "subcategory":"Groceries & Convenience Stores",
            "type":"Retail Goods"
        }
    ],
    "sg:phone":"+1 973 473 7766",
    "sg:postcode":"07013",
    "sg:province":"NJ",
    "sg:tags":[
        "grocer"
    ],
    "sg:website":"www.stopandshop.com",
    "wof:name":"Stop & Shop Supermarket",
    "wof:placetype":"venue"
},
  "geometry": {"coordinates":[-74.17716900000001,40.856372],"type":"Point"}
}