{
  "type": "Feature",
  "properties": {
    "addr:full":"1275 Bloomfield Ave Ste 72 Fairfield NJ 07004",
    "addr:housenumber":"1275;72",
    "addr:postcode":"07004",
    "addr:street":"Bloomfield Ave Ste",
    "iso:country":"US",
    "sg:address":"1275 Bloomfield Ave Ste 72",
    "sg:city":"Fairfield",
    "sg:classifiers":[
        {
            "category":"Professional",
            "type":"Services"
        }
    ],
    "sg:phone":"+1 973 227 4119",
    "sg:postcode":"07004",
    "sg:province":"NJ",
    "sg:tags":[
        "caterer"
    ],
    "wof:name":"Executive Suite Catering Service",
    "wof:placetype":"venue"
},
  "geometry": {"coordinates":[-74.31815,40.858338],"type":"Point"}
}