{
  "type": "Feature",
  "properties": {
    "iso:country":"US",
    "sg:address":"44 Cooper St",
    "sg:city":"Woodbury",
    "sg:classifiers":[
        {
            "category":"Insurance",
            "subcategory":"Hazard Insurance",
            "type":"Services"
        }
    ],
    "sg:phone":"+1 856 853 5566",
    "sg:postcode":"08096",
    "sg:province":"NJ",
    "sg:tags":[
        "bond"
    ],
    "wof:name":"Donald C Burton & Assoc Inc",
    "wof:placetype":"venue"
},
  "geometry": {"coordinates":[-75.150604,39.837041],"type":"Point"}
}