{
  "type": "Feature",
  "properties": {
    "iso:country":"US",
    "sg:address":"314 Church Rd",
    "sg:city":"Cherry Hill",
    "sg:classifiers":[
        {
            "category":"Shopping",
            "subcategory":"Computers & Home Electronics",
            "type":"Retail Goods"
        }
    ],
    "sg:phone":"+1   ",
    "sg:postcode":"08002",
    "sg:province":"NJ",
    "wof:name":"Desire PC Corp",
    "wof:placetype":"venue"
},
  "geometry": {"coordinates":[-75.034772,39.948863],"type":"Point"}
}