{
  "type": "Feature",
  "properties": {
    "addr:full":"150 English St Hackensack NJ 07601",
    "addr:housenumber":"150",
    "addr:postcode":"07601",
    "addr:street":"English St",
    "iso:country":"US",
    "sg:address":"150 English St",
    "sg:city":"Hackensack",
    "sg:classifiers":[
        {
            "category":"Building & Trades",
            "subcategory":"Construction",
            "type":"Services"
        }
    ],
    "sg:phone":"+1 201 498 1477",
    "sg:postcode":"07601",
    "sg:province":"NJ",
    "sg:tags":[
        "contractor"
    ],
    "sg:website":"www.jacarpentryinc.com",
    "wof:name":"J A Carpentry Inc",
    "wof:placetype":"venue"
},
  "geometry": {"coordinates":[-74.04945499999999,40.875632],"type":"Point"}
}