{
  "type": "Feature",
  "properties": {
    "addr:full":"90 Woodbridge Ctr Dr Ste 100 Woodbridge NJ 07095",
    "addr:housenumber":"90",
    "addr:postcode":"07095",
    "addr:street":"Woodbridge Ctr Dr Ste 100",
    "iso:country":"US",
    "sg:address":"90 Woodbridge Ctr Dr Ste 100",
    "sg:city":"Woodbridge",
    "sg:classifiers":[
        {
            "category":"Banks & Credit Unions",
            "subcategory":"Bank",
            "type":"Services"
        }
    ],
    "sg:phone":"+1 732 855 1842",
    "sg:postcode":"07095",
    "sg:province":"NJ",
    "wof:name":"Amboy National Bank",
    "wof:placetype":"venue"
},
  "geometry": {"coordinates":[-74.298897,40.550701],"type":"Point"}
}