{
  "type": "Feature",
  "properties": {
    "iso:country":"US",
    "sg:address":"53 Harrington St",
    "sg:city":"Bergenfield",
    "sg:classifiers":[
        {
            "category":"Building & Trades",
            "subcategory":"Construction",
            "type":"Services"
        }
    ],
    "sg:phone":"+1 201 244 1221",
    "sg:postcode":"07621",
    "sg:province":"NJ",
    "sg:tags":[
        "contractor"
    ],
    "wof:name":"Custom Marble Inc",
    "wof:placetype":"venue"
},
  "geometry": {"coordinates":[-74.009326,40.928079],"type":"Point"}
}