{
  "type": "Feature",
  "properties": {
    "iso:country":"US",
    "sg:address":"3108 Fox Run Dr",
    "sg:city":"Plainsboro",
    "sg:classifiers":[
        {
            "category":"Professional",
            "subcategory":"Computer Services",
            "type":"Services"
        }
    ],
    "sg:phone":"+1 609 716 0794",
    "sg:postcode":"08536",
    "sg:province":"NJ",
    "sg:tags":[
        "related"
    ],
    "wof:name":"First Reliable International",
    "wof:placetype":"venue"
},
  "geometry": {"coordinates":[-74.58929999999999,40.330483],"type":"Point"}
}