{
  "type": "Feature",
  "properties": {
    "iso:country":"US",
    "sg:address":"251 Clifton Ave",
    "sg:city":"Clifton",
    "sg:classifiers":[
        {
            "category":"Health Services",
            "subcategory":"Optometrist",
            "type":"Services"
        }
    ],
    "sg:phone":"+1 973 340 2300",
    "sg:postcode":"07011",
    "sg:province":"NJ",
    "wof:name":"Eye Doctor",
    "wof:placetype":"venue"
},
  "geometry": {"coordinates":[-74.135201,40.876099],"type":"Point"}
}