{
  "type": "Feature",
  "properties": {
    "iso:country":"US",
    "sg:address":"313 7th St",
    "sg:city":"Carlstadt",
    "sg:classifiers":[
        {
            "category":"Autos & Motor Vehicles",
            "subcategory":"Fuel & Gas Station",
            "type":"Retail Goods"
        }
    ],
    "sg:phone":"+1   ",
    "sg:postcode":"07072",
    "sg:province":"NJ",
    "sg:tags":[
        "station",
        "gasoline"
    ],
    "wof:name":"Knehr Charles & Sons",
    "wof:placetype":"venue"
},
  "geometry": {"coordinates":[-74.089876,40.836095],"type":"Point"}
}