{
  "type": "Feature",
  "properties": {
    "addr:full":"428 9th St Fairview NJ 07022",
    "addr:housenumber":"428",
    "addr:postcode":"07022",
    "addr:street":"9Th St",
    "iso:country":"US",
    "sg:address":"428 9th St",
    "sg:city":"Fairview",
    "sg:classifiers":[
        {
            "category":"Professional",
            "type":"Services"
        }
    ],
    "sg:phone":"+1 201 313 2682",
    "sg:postcode":"07022",
    "sg:province":"NJ",
    "wof:name":"Fourth Generation Svc",
    "wof:placetype":"venue"
},
  "geometry": {"coordinates":[-73.995476,40.822781],"type":"Point"}
}