{
  "type": "Feature",
  "properties": {
    "iso:country":"US",
    "sg:address":"407 23rd St",
    "sg:city":"Union City",
    "sg:classifiers":[
        {
            "category":"Organizations",
            "subcategory":"Religious Organization",
            "type":"Services"
        }
    ],
    "sg:phone":"+1   ",
    "sg:postcode":"07087",
    "sg:province":"NJ",
    "sg:tags":[
        "child",
        "day",
        "care"
    ],
    "wof:name":"Iglesia Metodista Unida",
    "wof:placetype":"venue"
},
  "geometry": {"coordinates":[-74.03286900000001,40.766871],"type":"Point"}
}