{
  "type": "Feature",
  "properties": {
    "iso:country":"US",
    "sg:address":"Liberty",
    "sg:city":"Little Ferry",
    "sg:classifiers":[
        {
            "category":"Education",
            "subcategory":"School",
            "type":"Public Place"
        }
    ],
    "sg:phone":"+1 201 641 6186",
    "sg:postcode":"07643",
    "sg:province":"NJ",
    "sg:tags":[
        "high",
        "middle",
        "elementary"
    ],
    "wof:name":"Little Ferry Borough of",
    "wof:placetype":"venue"
},
  "geometry": {"coordinates":[-74.04389500000001,40.850281],"type":"Point"}
}