{
  "type": "Feature",
  "properties": {
    "addr:full":"12 Highland Dr Englishtown NJ 07726",
    "addr:housenumber":"12",
    "addr:postcode":"07726",
    "addr:street":"Highland Dr",
    "iso:country":"US",
    "sg:address":"12 Highland Dr",
    "sg:city":"Englishtown",
    "sg:classifiers":[
        {
            "category":"Home & Garden",
            "subcategory":"Carpets & Floor Coverings",
            "type":"Retail Goods"
        }
    ],
    "sg:phone":"+1   ",
    "sg:postcode":"07726",
    "sg:province":"NJ",
    "wof:name":"Al Hassan Sales Agency",
    "wof:placetype":"venue"
},
  "geometry": {"coordinates":[-74.29912400000001,40.319875],"type":"Point"}
}