{
  "type": "Feature",
  "properties": {
    "iso:country":"US",
    "sg:address":"22 Regency Cir",
    "sg:city":"Englewood",
    "sg:classifiers":[
        {
            "category":"Home & Garden",
            "subcategory":"Furniture",
            "type":"Retail Goods"
        }
    ],
    "sg:phone":"+1 201 894 1666",
    "sg:postcode":"07631",
    "sg:province":"NJ",
    "sg:tags":[
        "builder",
        "custom"
    ],
    "wof:name":"Promique Design",
    "wof:placetype":"venue"
},
  "geometry": {"coordinates":[-73.978363,40.872966],"type":"Point"}
}