{
  "type": "Feature",
  "properties": {
    "iso:country":"US",
    "sg:address":"1064 Clinton Ave",
    "sg:city":"Irvington",
    "sg:classifiers":[
        {
            "category":"Organizations",
            "subcategory":"Religious Organization",
            "type":"Services"
        }
    ],
    "sg:phone":"+1 973 399 0300",
    "sg:postcode":"07111",
    "sg:province":"NJ",
    "sg:tags":[
        "church"
    ],
    "wof:name":"Church Of Jesus Christ Of Lds",
    "wof:placetype":"venue"
},
  "geometry": {"coordinates":[-74.22683499999999,40.725741],"type":"Point"}
}