{
  "type": "Feature",
  "properties": {
    "addr:full":"611 Chapel Ave E Cherry Hill NJ 08034",
    "addr:housenumber":"611",
    "addr:postcode":"08034",
    "addr:street":"Chapel Ave E",
    "iso:country":"US",
    "sg:address":"611 Chapel Ave E",
    "sg:city":"Cherry Hill",
    "sg:classifiers":[
        {
            "category":"Building & Trades",
            "subcategory":"Construction",
            "type":"Services"
        }
    ],
    "sg:phone":"+1 856 616 0666",
    "sg:postcode":"08034",
    "sg:province":"NJ",
    "sg:tags":[
        "excavation",
        "demolition",
        "contractor"
    ],
    "wof:name":"Universal Constructors Inc",
    "wof:placetype":"venue"
},
  "geometry": {"coordinates":[-74.97763399999999,39.920729],"type":"Point"}
}