{
  "type": "Feature",
  "properties": {
    "addr:full":"215 Uncle Pete's Rd Trenton NJ 08691",
    "addr:housenumber":"215",
    "addr:postcode":"08691",
    "addr:street":"Uncle Pete'S Rd",
    "iso:country":"US",
    "sg:address":"215 Uncle Pete's Rd",
    "sg:city":"Trenton",
    "sg:classifiers":[
        {
            "category":"Organizations",
            "subcategory":"Community Association",
            "type":"Services"
        }
    ],
    "sg:phone":"+1 609 585 5200",
    "sg:postcode":"08691",
    "sg:province":"NJ",
    "sg:tags":[
        "club"
    ],
    "wof:name":"German American Society",
    "wof:placetype":"venue"
},
  "geometry": {"coordinates":[-74.64160800000001,40.172249],"type":"Point"}
}