{
  "type": "Feature",
  "properties": {
    "iso:country":"US",
    "sg:address":"205 Christie Ave",
    "sg:city":"Clifton",
    "sg:classifiers":[
        {
            "category":"Professional",
            "subcategory":"Business Services",
            "type":"Services"
        }
    ],
    "sg:phone":"+1   ",
    "sg:postcode":"07011",
    "sg:province":"NJ",
    "wof:name":"Rock Vale Associates",
    "wof:placetype":"venue"
},
  "geometry": {"coordinates":[-74.14116199999999,40.882642],"type":"Point"}
}