{
  "type": "Feature",
  "properties": {
    "iso:country":"US",
    "sg:address":"237 US Hwy 206",
    "sg:city":"Chester",
    "sg:classifiers":[
        {
            "category":"Restaurant",
            "type":"Food & Drink"
        }
    ],
    "sg:phone":"+1 908 879 2848",
    "sg:postcode":"07930",
    "sg:province":"NJ",
    "wof:name":"Venezia Restaurant Inc",
    "wof:placetype":"venue"
},
  "geometry": {"coordinates":[-74.701956,40.789326],"type":"Point"}
}