{
  "type": "Feature",
  "properties": {
    "iso:country":"US",
    "sg:address":"191 Woodport Rd",
    "sg:city":"Sparta",
    "sg:classifiers":[
        {
            "category":"Insurance",
            "subcategory":"Insurance Agent",
            "type":"Services"
        }
    ],
    "sg:phone":"+1 973 726 9455",
    "sg:postcode":"07871",
    "sg:province":"NJ",
    "wof:name":"Edsall Insurance",
    "wof:placetype":"venue"
},
  "geometry": {"coordinates":[-74.63085100000001,41.025174],"type":"Point"}
}