{
  "type": "Feature",
  "properties": {
    "iso:country":"US",
    "sg:address":"206 Center St",
    "sg:city":"Moorestown",
    "sg:classifiers":[
        {
            "category":"Home & Garden",
            "subcategory":"Carpets & Floor Coverings",
            "type":"Retail Goods"
        }
    ],
    "sg:phone":"+1 856 439 1576",
    "sg:postcode":"08057",
    "sg:province":"NJ",
    "sg:tags":[
        "distributor",
        "rug",
        "manufacturer"
    ],
    "wof:name":"Stanton Carpets",
    "wof:placetype":"venue"
},
  "geometry": {"coordinates":[-74.981099,39.969023],"type":"Point"}
}