{
  "type": "Feature",
  "properties": {
    "addr:full":"795 State Rte 73 West Berlin NJ 08091",
    "addr:housenumber":"795",
    "addr:postcode":"08091",
    "addr:street":"State Rte 73",
    "iso:country":"US",
    "sg:address":"795 State Rte 73",
    "sg:city":"West Berlin",
    "sg:classifiers":[
        {
            "category":"Restaurant",
            "type":"Food & Drink"
        }
    ],
    "sg:phone":"+1 856 768 5454",
    "sg:postcode":"08091",
    "sg:province":"NJ",
    "wof:name":"Victory Lane",
    "wof:placetype":"venue"
},
  "geometry": {"coordinates":[-74.91126199999999,39.788541],"type":"Point"}
}