{
  "type": "Feature",
  "properties": {
    "addr:full":"61 Pleasant Ave Fanwood NJ 07023",
    "addr:housenumber":"61",
    "addr:postcode":"07023",
    "addr:street":"Pleasant Ave",
    "iso:country":"US",
    "sg:address":"61 Pleasant Ave",
    "sg:city":"Fanwood",
    "sg:classifiers":[
        {
            "category":"Organizations",
            "subcategory":"Religious Organization",
            "type":"Services"
        }
    ],
    "sg:phone":"+1   ",
    "sg:postcode":"07023",
    "sg:province":"NJ",
    "wof:name":"Gospel Chapel Kenilworth",
    "wof:placetype":"venue"
},
  "geometry": {"coordinates":[-74.389798,40.64825],"type":"Point"}
}