{
  "type": "Feature",
  "properties": {
    "addr:full":"1 Clarkton Dr Clark NJ 07066",
    "addr:housenumber":"1",
    "addr:postcode":"07066",
    "addr:street":"Clarkton Dr",
    "iso:country":"US",
    "sg:address":"1 Clarkton Dr",
    "sg:city":"Clark",
    "sg:classifiers":[
        {
            "category":"Shopping",
            "subcategory":"Gifts & Souvenirs",
            "type":"Retail Goods"
        }
    ],
    "sg:phone":"+1 732 381 7555",
    "sg:postcode":"07066",
    "sg:province":"NJ",
    "sg:tags":[
        "shop"
    ],
    "wof:name":"Mary's Hallmark",
    "wof:placetype":"venue"
},
  "geometry": {"coordinates":[-74.31419099999999,40.627503],"type":"Point"}
}