{
  "type": "Feature",
  "properties": {
    "iso:country":"US",
    "sg:address":"707 White Horse Pike",
    "sg:city":"Absecon",
    "sg:classifiers":[
        {
            "category":"Health Services",
            "subcategory":"Nursing And Care Facility",
            "type":"Services"
        }
    ],
    "sg:phone":"+1   ",
    "sg:postcode":"08201",
    "sg:province":"NJ",
    "sg:tags":[
        "adult",
        "day"
    ],
    "wof:name":"Trinity Medical Day Care Ctr",
    "wof:placetype":"venue"
},
  "geometry": {"coordinates":[-74.517875,39.438306],"type":"Point"}
}