{
  "type": "Feature",
  "properties": {
    "addr:full":"125 Main Ave Elmwood Park NJ 07407",
    "addr:housenumber":"125",
    "addr:postcode":"07407",
    "addr:street":"Main Ave",
    "iso:country":"US",
    "sg:address":"125 Main Ave",
    "sg:city":"Elmwood Park",
    "sg:classifiers":[
        {
            "category":"Real Estate",
            "subcategory":"Real Estate Agent",
            "type":"Services"
        }
    ],
    "sg:phone":"+1   ",
    "sg:postcode":"07407",
    "sg:province":"NJ",
    "sg:tags":[
        "management"
    ],
    "wof:name":"Granatell Associates",
    "wof:placetype":"venue"
},
  "geometry": {"coordinates":[-74.112235,40.909293],"type":"Point"}
}