{
  "type": "Feature",
  "properties": {
    "iso:country":"US",
    "sg:address":"568 Central Ave",
    "sg:city":"Bridgewater",
    "sg:classifiers":[
        {
            "category":"Freight",
            "type":"Transportation"
        }
    ],
    "sg:phone":"+1 908 722 1234",
    "sg:postcode":"08807",
    "sg:province":"NJ",
    "sg:tags":[
        "trucking"
    ],
    "sg:website":"www.dameo.com",
    "wof:name":"Dameo Trucking Inc",
    "wof:placetype":"venue"
},
  "geometry": {"coordinates":[-74.58086400000001,40.560792],"type":"Point"}
}