{
  "type": "Feature",
  "properties": {
    "addr:full":"7 Hawk Dr Ringoes NJ 08551",
    "addr:housenumber":"7",
    "addr:postcode":"08551",
    "addr:street":"Hawk Dr",
    "iso:country":"US",
    "sg:address":"7 Hawk Dr",
    "sg:city":"Ringoes",
    "sg:classifiers":[
        {
            "category":"Professional",
            "subcategory":"Computer Services",
            "type":"Services"
        }
    ],
    "sg:phone":"+1 908 284 1669",
    "sg:postcode":"08551",
    "sg:province":"NJ",
    "sg:tags":[
        "consultant",
        "designer",
        "programing",
        "custom"
    ],
    "wof:name":"Parla Computing Consulting Inc",
    "wof:placetype":"venue"
},
  "geometry": {"coordinates":[-74.85471,40.444941],"type":"Point"}
}