{
  "type": "Feature",
  "properties": {
    "addr:full":"100 Westfield Ave Elizabeth NJ 07208",
    "addr:housenumber":"100",
    "addr:postcode":"07208",
    "addr:street":"Westfield Ave",
    "iso:country":"US",
    "sg:address":"100 Westfield Ave",
    "sg:city":"Elizabeth",
    "sg:classifiers":[
        {
            "category":"Restaurant",
            "type":"Food & Drink"
        }
    ],
    "sg:phone":"+1   ",
    "sg:postcode":"07208",
    "sg:province":"NJ",
    "sg:tags":[
        "eating"
    ],
    "wof:name":"McDonalds",
    "wof:placetype":"venue"
},
  "geometry": {"coordinates":[-74.22434699999999,40.666956],"type":"Point"}
}