{
  "type": "Feature",
  "properties": {
    "addr:full":"123 Munsonhurst Rd Franklin NJ 07416",
    "addr:housenumber":"123",
    "addr:postcode":"07416",
    "addr:street":"Munsonhurst Rd",
    "iso:country":"US",
    "sg:address":"123 Munsonhurst Rd",
    "sg:city":"Franklin",
    "sg:classifiers":[
        {
            "category":"Utilities",
            "subcategory":"Telephone",
            "type":"Services"
        }
    ],
    "sg:phone":"+1 973 209 2885",
    "sg:postcode":"07416",
    "sg:province":"NJ",
    "sg:tags":[
        "distance",
        "long"
    ],
    "wof:name":"Excel Communications Inc",
    "wof:placetype":"venue"
},
  "geometry": {"coordinates":[-74.58197699999999,41.094545],"type":"Point"}
}