{
  "type": "Feature",
  "properties": {
    "iso:country":"US",
    "sg:address":"700 Violet Rd",
    "sg:city":"Millville",
    "sg:classifiers":[
        {
            "category":"Organizations",
            "subcategory":"Religious Organization",
            "type":"Services"
        }
    ],
    "sg:phone":"+1 856 825 4551",
    "sg:postcode":"08332",
    "sg:province":"NJ",
    "sg:tags":[
        "clergy"
    ],
    "wof:name":"W H Marshall",
    "wof:placetype":"venue"
},
  "geometry": {"coordinates":[-75.037746,39.337511],"type":"Point"}
}