{
  "type": "Feature",
  "properties": {
    "iso:country":"US",
    "sg:address":"15 Legion Pl",
    "sg:city":"North Arlington",
    "sg:classifiers":[
        {
            "category":"Building & Trades",
            "subcategory":"Construction",
            "type":"Services"
        }
    ],
    "sg:phone":"+1 201 998 0894",
    "sg:postcode":"07031",
    "sg:province":"NJ",
    "sg:tags":[
        "church",
        "painting",
        "renovation",
        "contractor"
    ],
    "wof:name":"John Tiedemann Inc",
    "wof:placetype":"venue"
},
  "geometry": {"coordinates":[-74.13201599999999,40.7874],"type":"Point"}
}