{
  "type": "Feature",
  "properties": {
    "addr:full":"214 Jefferson St Hoboken NJ 07030",
    "addr:housenumber":"214",
    "addr:postcode":"07030",
    "addr:street":"Jefferson St",
    "iso:country":"US",
    "sg:address":"214 Jefferson St",
    "sg:city":"Hoboken",
    "sg:classifiers":[
        {
            "category":"Deli",
            "type":"Food & Drink"
        },
        {
            "category":"Food & Beverages",
            "subcategory":"Groceries & Convenience Stores",
            "type":"Retail Goods"
        }
    ],
    "sg:menulink":"http://www.allmenus.com/nj/hoboken/280175-the-little-grocery/menu/",
    "sg:phone":"+1 201 610 9220",
    "sg:postcode":"07030",
    "sg:province":"NJ",
    "sg:tags":[
        "deli",
        "american"
    ],
    "wof:name":"The Little Grocery",
    "wof:placetype":"venue"
},
  "geometry": {"coordinates":[-74.037936,40.740322],"type":"Point"}
}