{
  "type": "Feature",
  "properties": {
    "addr:full":"25 Thomas St Newark NJ 07114",
    "addr:housenumber":"25",
    "addr:postcode":"07114",
    "addr:street":"Thomas St",
    "iso:country":"US",
    "sg:address":"25 Thomas St",
    "sg:city":"Newark",
    "sg:classifiers":[
        {
            "category":"Organizations",
            "subcategory":"Religious Organization",
            "type":"Services"
        }
    ],
    "sg:phone":"+1 973 622 7712",
    "sg:postcode":"07114",
    "sg:province":"NJ",
    "sg:tags":[
        "church"
    ],
    "wof:name":"St Columba's Church",
    "wof:placetype":"venue"
},
  "geometry": {"coordinates":[-74.18086599999999,40.724487],"type":"Point"}
}