{
  "type": "Feature",
  "properties": {
    "iso:country":"US",
    "sg:address":"8 N Willow St",
    "sg:city":"Montclair",
    "sg:classifiers":[
        {
            "category":"Personal",
            "type":"Services"
        }
    ],
    "sg:phone":"+1 973 746 5226",
    "sg:postcode":"07042",
    "sg:province":"NJ",
    "sg:tags":[
        "towing"
    ],
    "wof:name":"Roach's Towing Service",
    "wof:placetype":"venue"
},
  "geometry": {"coordinates":[-74.215087,40.812907],"type":"Point"}
}