{
  "type": "Feature",
  "properties": {
    "addr:full":"37 S Durst Dr Milltown NJ 08850",
    "addr:housenumber":"37",
    "addr:postcode":"08850",
    "addr:street":"S Durst Dr",
    "iso:country":"US",
    "sg:address":"37 S Durst Dr",
    "sg:city":"Milltown",
    "sg:classifiers":[
        {
            "category":"Organizations",
            "subcategory":"Membership Organization",
            "type":"Services"
        }
    ],
    "sg:phone":"+1 732 246 3427",
    "sg:postcode":"08850",
    "sg:province":"NJ",
    "wof:name":"Little Apple Prdctons Milltown",
    "wof:placetype":"venue"
},
  "geometry": {"coordinates":[-74.429067,40.45424],"type":"Point"}
}