{
  "type": "Feature",
  "properties": {
    "addr:full":"400 Linden Ave Pine Beach NJ 08741",
    "addr:housenumber":"400",
    "addr:postcode":"08741",
    "addr:street":"Linden Ave",
    "iso:country":"US",
    "sg:address":"400 Linden Ave",
    "sg:city":"Pine Beach",
    "sg:classifiers":[
        {
            "category":"Manufacturing",
            "subcategory":"Tools & Machinery",
            "type":"Manufacturing & Wholesale Goods"
        }
    ],
    "sg:phone":"+1 732 473 0604",
    "sg:postcode":"08741",
    "sg:province":"NJ",
    "sg:tags":[
        "analytical",
        "instrument",
        "mfg"
    ],
    "wof:name":"R E Gourley and Son Company",
    "wof:placetype":"venue"
},
  "geometry": {"coordinates":[-74.171369,39.935153],"type":"Point"}
}