{
  "type": "Feature",
  "properties": {
    "addr:full":"5 Timberline Dr Voorhees NJ 08043",
    "addr:housenumber":"5",
    "addr:postcode":"08043",
    "addr:street":"Timberline Dr",
    "iso:country":"US",
    "sg:address":"5 Timberline Dr",
    "sg:city":"Voorhees",
    "sg:classifiers":[
        {
            "category":"Professional",
            "subcategory":"Management & Consulting",
            "type":"Services"
        }
    ],
    "sg:phone":"+1 856 784 3468",
    "sg:postcode":"08043",
    "sg:province":"NJ",
    "sg:tags":[
        "training",
        "sales"
    ],
    "sg:website":"www.creativetraining.com",
    "wof:name":"Creative Training Solutions",
    "wof:placetype":"venue"
},
  "geometry": {"coordinates":[-74.949376,39.846647],"type":"Point"}
}