{
  "type": "Feature",
  "properties": {
    "iso:country":"US",
    "sg:address":"10 Corporate Place South",
    "sg:city":"Piscataway",
    "sg:classifiers":[
        {
            "category":"Professional",
            "subcategory":"Computer Services",
            "type":"Services"
        }
    ],
    "sg:phone":"+1 732 981 8191",
    "sg:postcode":"08854",
    "sg:province":"NJ",
    "sg:website":"http://www.celebros.com",
    "wof:name":"Celebros",
    "wof:placetype":"venue"
},
  "geometry": {"coordinates":[-74.45857100000001,40.548159],"type":"Point"}
}