{
  "type": "Feature",
  "properties": {
    "addr:full":"1642 Terrill Rd Scotch Plains NJ 07076",
    "addr:housenumber":"1642",
    "addr:postcode":"07076",
    "addr:street":"Terrill Rd",
    "iso:country":"US",
    "sg:address":"1642 Terrill Rd",
    "sg:city":"Scotch Plains",
    "sg:classifiers":[
        {
            "category":"Retail",
            "subcategory":"Portrait Studio",
            "type":"Services"
        }
    ],
    "sg:phone":"+1   ",
    "sg:postcode":"07076",
    "sg:province":"NJ",
    "sg:tags":[
        "photo"
    ],
    "wof:name":"Sears Portrait Studio C54",
    "wof:placetype":"venue"
},
  "geometry": {"coordinates":[-74.365996,40.617408],"type":"Point"}
}