{
  "type": "Feature",
  "properties": {
    "iso:country":"US",
    "sg:address":"524 Jemco Pl",
    "sg:city":"Ridgewood",
    "sg:classifiers":[
        {
            "category":"Wholesale",
            "subcategory":"Non-durable Goods",
            "type":"Manufacturing & Wholesale Goods"
        }
    ],
    "sg:phone":"+1 201 251 1511",
    "sg:postcode":"07450",
    "sg:province":"NJ",
    "wof:name":"Jeff Muhlstock Inc",
    "wof:placetype":"venue"
},
  "geometry": {"coordinates":[-74.107483,40.965342],"type":"Point"}
}