{
  "type": "Feature",
  "properties": {
    "iso:country":"US",
    "sg:address":"575 State Route 23",
    "sg:city":"Wayne",
    "sg:classifiers":[
        {
            "category":"Retail",
            "subcategory":"Storage",
            "type":"Services"
        }
    ],
    "sg:phone":"+1 973 628 7766",
    "sg:postcode":"07470",
    "sg:province":"NJ",
    "sg:tags":[
        "self"
    ],
    "wof:name":"Access Self Storage",
    "wof:placetype":"venue"
},
  "geometry": {"coordinates":[-74.268097,40.922001],"type":"Point"}
}