{
  "type": "Feature",
  "properties": {
    "iso:country":"US",
    "sg:address":"19 White Lake Rd",
    "sg:city":"Lafayette",
    "sg:classifiers":[
        {
            "category":"Freight",
            "type":"Transportation"
        }
    ],
    "sg:phone":"+1 973 579 6000",
    "sg:postcode":"07871",
    "sg:province":"NJ",
    "sg:tags":[
        "commercial",
        "storage",
        "general"
    ],
    "wof:name":"Super Self Storage Center Inc",
    "wof:placetype":"venue"
},
  "geometry": {"coordinates":[-74.663477,41.078489],"type":"Point"}
}