{
  "type": "Feature",
  "properties": {
    "addr:full":"284 Queen Anne Rd Teaneck NJ 07666",
    "addr:housenumber":"284",
    "addr:postcode":"07666",
    "addr:street":"Queen Anne Rd",
    "iso:country":"US",
    "sg:address":"284 Queen Anne Rd",
    "sg:city":"Teaneck",
    "sg:classifiers":[
        {
            "category":"Food & Beverages",
            "subcategory":"Groceries & Convenience Stores",
            "type":"Retail Goods"
        }
    ],
    "sg:phone":"+1 201 836 6002",
    "sg:postcode":"07666",
    "sg:province":"NJ",
    "wof:name":"Oaxaca Grocery",
    "wof:placetype":"venue"
},
  "geometry": {"coordinates":[-74.02069899999999,40.874699],"type":"Point"}
}