{
  "type": "Feature",
  "properties": {
    "iso:country":"US",
    "sg:address":"500 Franklin Ave",
    "sg:city":"Nutley",
    "sg:classifiers":[
        {
            "category":"Health Services",
            "subcategory":"Optometrist",
            "type":"Services"
        }
    ],
    "sg:phone":"+1 973 667 0600",
    "sg:postcode":"07110",
    "sg:province":"NJ",
    "wof:name":"Arpino David F OD",
    "wof:placetype":"venue"
},
  "geometry": {"coordinates":[-74.155602,40.823502],"type":"Point"}
}