{
  "type": "Feature",
  "properties": {
    "iso:country":"US",
    "sg:address":"1115 E Jersey St",
    "sg:city":"Elizabeth",
    "sg:classifiers":[
        {
            "category":"Recreation",
            "type":"Entertainment"
        }
    ],
    "sg:phone":"+1 908 354 0999",
    "sg:postcode":"07201",
    "sg:province":"NJ",
    "sg:tags":[
        "karate",
        "judo",
        "instr"
    ],
    "wof:name":"National Taekwondo Commission",
    "wof:placetype":"venue"
},
  "geometry": {"coordinates":[-74.212639,40.664698],"type":"Point"}
}