{
  "type": "Feature",
  "properties": {
    "addr:full":"6 Greenleaf Dr Englishtown NJ 07726",
    "addr:housenumber":"6",
    "addr:postcode":"07726",
    "addr:street":"Greenleaf Dr",
    "iso:country":"US",
    "sg:address":"6 Greenleaf Dr",
    "sg:city":"Englishtown",
    "sg:classifiers":[
        {
            "category":"Home & Garden",
            "subcategory":"Building Materials",
            "type":"Retail Goods"
        }
    ],
    "sg:phone":"+1   ",
    "sg:postcode":"07726",
    "sg:province":"NJ",
    "sg:tags":[
        "rolling",
        "repair",
        "door"
    ],
    "sg:website":"www.proroll.com",
    "wof:name":"Professional Rolling Door Svc",
    "wof:placetype":"venue"
},
  "geometry": {"coordinates":[-74.343203,40.298485],"type":"Point"}
}