{
  "type": "Feature",
  "properties": {
    "iso:country":"US",
    "sg:address":"132 Clark Ave",
    "sg:city":"Westwood",
    "sg:classifiers":[
        {
            "category":"Shopping",
            "type":"Retail Goods"
        }
    ],
    "sg:phone":"+1   ",
    "sg:postcode":"07675",
    "sg:province":"NJ",
    "sg:tags":[
        "merchandise"
    ],
    "wof:name":"Laminate Shop Inc",
    "wof:placetype":"venue"
},
  "geometry": {"coordinates":[-73.965186,41.010286],"type":"Point"}
}