{
  "type": "Feature",
  "properties": {
    "addr:full":"23 Groff Rd Monroeville NJ 08343",
    "addr:housenumber":"23",
    "addr:postcode":"08343",
    "addr:street":"Groff Rd",
    "iso:country":"US",
    "sg:address":"23 Groff Rd",
    "sg:city":"Monroeville",
    "sg:classifiers":[
        {
            "category":"Farming",
            "subcategory":"Livestock Farm",
            "type":"Manufacturing & Wholesale Goods"
        }
    ],
    "sg:phone":"+1 856 358 8251",
    "sg:postcode":"08343",
    "sg:province":"NJ",
    "sg:tags":[
        "beef",
        "feedlot",
        "cattle"
    ],
    "wof:name":"Thomas Brothers",
    "wof:placetype":"venue"
},
  "geometry": {"coordinates":[-75.179453,39.636736],"type":"Point"}
}