{
  "type": "Feature",
  "properties": {
    "iso:country":"US",
    "sg:address":"292 Co Rd 539",
    "sg:city":"Cream Ridge",
    "sg:classifiers":[
        {
            "category":"Home & Garden",
            "subcategory":"Home Furnishings",
            "type":"Retail Goods"
        },
        {
            "category":"Shopping",
            "subcategory":"Gifts & Souvenirs",
            "type":"Retail Goods"
        }
    ],
    "sg:phone":"+1 609 758 0191",
    "sg:postcode":"08514",
    "sg:province":"NJ",
    "sg:tags":[
        "curtain",
        "made",
        "drapery"
    ],
    "wof:name":"Bloomin' Baskets & Windows",
    "wof:placetype":"venue"
},
  "geometry": {"coordinates":[-74.523949,40.126415],"type":"Point"}
}