{
  "type": "Feature",
  "properties": {
    "addr:full":"139 Smith St Perth Amboy NJ 08861",
    "addr:housenumber":"139",
    "addr:postcode":"08861",
    "addr:street":"Smith St",
    "iso:country":"US",
    "sg:address":"139 Smith St",
    "sg:city":"Perth Amboy",
    "sg:classifiers":[
        {
            "category":"Home & Garden",
            "subcategory":"Home Furnishings",
            "type":"Retail Goods"
        }
    ],
    "sg:phone":"+1 732 442 2879",
    "sg:postcode":"08861",
    "sg:province":"NJ",
    "sg:tags":[
        "blind",
        "curtain",
        "made",
        "drapery",
        "shade"
    ],
    "wof:name":"Finks Department Store Inc",
    "wof:placetype":"venue"
},
  "geometry": {"coordinates":[-74.268303,40.508499],"type":"Point"}
}