{
  "type": "Feature",
  "properties": {
    "addr:full":"11 N Colonial Dr Bordentown NJ 08505",
    "addr:housenumber":"11",
    "addr:postcode":"08505",
    "addr:street":"N Colonial Dr",
    "iso:country":"US",
    "sg:address":"11 N Colonial Dr",
    "sg:city":"Bordentown",
    "sg:classifiers":[
        {
            "category":"Professional",
            "subcategory":"Business Services",
            "type":"Services"
        }
    ],
    "sg:phone":"+1   ",
    "sg:postcode":"08505",
    "sg:province":"NJ",
    "wof:name":"Deals 2000",
    "wof:placetype":"venue"
},
  "geometry": {"coordinates":[-74.692499,40.13634],"type":"Point"}
}