{
  "type": "Feature",
  "properties": {
    "addr:full":"96 Plymouth St Fairfield NJ 07004",
    "addr:housenumber":"96",
    "addr:postcode":"07004",
    "addr:street":"Plymouth St",
    "iso:country":"US",
    "sg:address":"96 Plymouth St",
    "sg:city":"Fairfield",
    "sg:classifiers":[
        {
            "category":"Home & Garden",
            "subcategory":"Garden Supply",
            "type":"Retail Goods"
        }
    ],
    "sg:phone":"+1 973 227 6171",
    "sg:postcode":"07004",
    "sg:province":"NJ",
    "sg:tags":[
        "equipment",
        "lawn",
        "snow",
        "mower"
    ],
    "wof:name":"Fairfield Power Equipment Inc",
    "wof:placetype":"venue"
},
  "geometry": {"coordinates":[-74.313558,40.874577],"type":"Point"}
}