{
  "type": "Feature",
  "properties": {
    "iso:country":"US",
    "sg:address":"379 E Milton Ave",
    "sg:city":"Rahway",
    "sg:classifiers":[
        {
            "category":"Organizations",
            "subcategory":"Religious Organization",
            "type":"Services"
        }
    ],
    "sg:phone":"+1   ",
    "sg:postcode":"07065",
    "sg:province":"NJ",
    "wof:name":"James W Ealey Rev",
    "wof:placetype":"venue"
},
  "geometry": {"coordinates":[-74.27063800000001,40.60434],"type":"Point"}
}