{
  "type": "Feature",
  "properties": {
    "iso:country":"US",
    "sg:address":"395 W Passaic St",
    "sg:city":"Rochelle Park",
    "sg:classifiers":[
        {
            "category":"Real Estate",
            "subcategory":"Developer",
            "type":"Services"
        }
    ],
    "sg:phone":"+1   ",
    "sg:postcode":"07662",
    "sg:province":"NJ",
    "sg:tags":[
        "company",
        "holding"
    ],
    "wof:name":"Kajima Real Estate Development",
    "wof:placetype":"venue"
},
  "geometry": {"coordinates":[-74.084253,40.916367],"type":"Point"}
}