{
  "type": "Feature",
  "properties": {
    "iso:country":"US",
    "sg:address":"6 Chelsea Rd",
    "sg:city":"Clifton",
    "sg:classifiers":[
        {
            "category":"Manufacturing",
            "subcategory":"Chemicals & Compounds",
            "type":"Manufacturing & Wholesale Goods"
        }
    ],
    "sg:phone":"+1 973 472 9292",
    "sg:postcode":"07012",
    "sg:province":"NJ",
    "sg:tags":[
        "detergent",
        "mfg"
    ],
    "wof:name":"Magnuson Products",
    "wof:placetype":"venue"
},
  "geometry": {"coordinates":[-74.16073799999999,40.847499],"type":"Point"}
}