{
  "type": "Feature",
  "properties": {
    "addr:full":"4 Banta Pl Hackensack NJ 07601",
    "addr:housenumber":"4",
    "addr:postcode":"07601",
    "addr:street":"Banta Pl",
    "iso:country":"US",
    "sg:address":"4 Banta Pl",
    "sg:city":"Hackensack",
    "sg:classifiers":[
        {
            "category":"Professional",
            "type":"Services"
        }
    ],
    "sg:phone":"+1 201 488 9119",
    "sg:postcode":"07601",
    "sg:province":"NJ",
    "sg:tags":[
        "establishment"
    ],
    "wof:name":"O'Sullivan Group",
    "wof:placetype":"venue"
},
  "geometry": {"coordinates":[-74.043857,40.885425],"type":"Point"}
}