{
  "type": "Feature",
  "properties": {
    "addr:full":"1136 Main St Paterson NJ 07503",
    "addr:housenumber":"1136",
    "addr:postcode":"07503",
    "addr:street":"Main St",
    "iso:country":"US",
    "sg:address":"1136 Main St",
    "sg:city":"Paterson",
    "sg:classifiers":[
        {
            "category":"Personal",
            "subcategory":"Beauty Salon",
            "type":"Services"
        }
    ],
    "sg:phone":"+1 973 742 3227",
    "sg:postcode":"07503",
    "sg:province":"NJ",
    "wof:name":"Classic Touch Beauty Salon",
    "wof:placetype":"venue"
},
  "geometry": {"coordinates":[-74.154696,40.88981],"type":"Point"}
}