{
  "type": "Feature",
  "properties": {
    "iso:country":"US",
    "sg:address":"130 Lake Ave",
    "sg:city":"Clifton",
    "sg:classifiers":[
        {
            "category":"Professional",
            "subcategory":"Business Services",
            "type":"Services"
        }
    ],
    "sg:phone":"+1   ",
    "sg:postcode":"07011",
    "sg:province":"NJ",
    "wof:name":"Transamerica Corporation",
    "wof:placetype":"venue"
},
  "geometry": {"coordinates":[-74.12658399999999,40.874503],"type":"Point"}
}