{
  "type": "Feature",
  "properties": {
    "addr:full":"195 Howell St Jersey City NJ 07306",
    "addr:housenumber":"195",
    "addr:postcode":"07306",
    "addr:street":"Howell St",
    "iso:country":"US",
    "sg:address":"195 Howell St",
    "sg:city":"Jersey City",
    "sg:classifiers":[
        {
            "category":"Manufacturing",
            "subcategory":"Paper Products",
            "type":"Manufacturing & Wholesale Goods"
        },
        {
            "category":"Mining & Drilling",
            "type":"Manufacturing & Wholesale Goods"
        }
    ],
    "sg:phone":"+1 201 653 7336",
    "sg:postcode":"07306",
    "sg:province":"NJ",
    "sg:tags":[
        "operator",
        "crude",
        "oil",
        "gas",
        "mfg"
    ],
    "wof:name":"Terminal Ventures Inc",
    "wof:placetype":"venue"
},
  "geometry": {"coordinates":[-74.07688899999999,40.7401],"type":"Point"}
}