{
  "type": "Feature",
  "properties": {
    "iso:country":"US",
    "sg:address":"110 Davidson Ave",
    "sg:city":"Somerset",
    "sg:classifiers":[
        {
            "category":"Restaurant",
            "type":"Food & Drink"
        }
    ],
    "sg:phone":"+1 732 764 6470",
    "sg:postcode":"08873",
    "sg:province":"NJ",
    "wof:name":"Allie's American Grille & Bar",
    "wof:placetype":"venue"
},
  "geometry": {"coordinates":[-74.51892599999999,40.541931],"type":"Point"}
}