{
  "type": "Feature",
  "properties": {
    "iso:country":"US",
    "sg:address":"9-05 1st St",
    "sg:city":"Fair Lawn",
    "sg:classifiers":[
        {
            "category":"Health Services",
            "subcategory":"Dentist",
            "type":"Services"
        }
    ],
    "sg:phone":"+1 201 791 9756",
    "sg:postcode":"07410",
    "sg:province":"NJ",
    "wof:name":"Parker Jonathan",
    "wof:placetype":"venue"
},
  "geometry": {"coordinates":[-74.135751,40.926913],"type":"Point"}
}