{
  "type": "Feature",
  "properties": {
    "iso:country":"US",
    "sg:address":"38 Donald Cir",
    "sg:city":"Matawan",
    "sg:classifiers":[
        {
            "category":"Professional",
            "subcategory":"Accounting & Tax Preparation",
            "type":"Services"
        }
    ],
    "sg:phone":"+1   ",
    "sg:postcode":"07747",
    "sg:province":"NJ",
    "wof:name":"Arvelo Tax Svcs",
    "wof:placetype":"venue"
},
  "geometry": {"coordinates":[-74.257678,40.410179],"type":"Point"}
}