{
  "type": "Feature",
  "properties": {
    "iso:country":"US",
    "sg:address":"5 Wester Pl",
    "sg:city":"Clifton",
    "sg:classifiers":[
        {
            "category":"Arts & Performance",
            "subcategory":"Theater",
            "type":"Entertainment"
        }
    ],
    "sg:phone":"+1 973 773 4664",
    "sg:postcode":"07013",
    "sg:province":"NJ",
    "sg:tags":[
        "group"
    ],
    "wof:name":"Evelyn Vernay Enchanted Doves",
    "wof:placetype":"venue"
},
  "geometry": {"coordinates":[-74.18166100000001,40.852647],"type":"Point"}
}