{
  "type": "Feature",
  "properties": {
    "iso:country":"US",
    "sg:address":"65 Blanchard Rd",
    "sg:city":"Marlton",
    "sg:classifiers":[
        {
            "category":"Real Estate",
            "subcategory":"Real Estate Agent",
            "type":"Services"
        }
    ],
    "sg:phone":"+1   ",
    "sg:postcode":"08053",
    "sg:province":"NJ",
    "wof:name":"Acumen Appraisals",
    "wof:placetype":"venue"
},
  "geometry": {"coordinates":[-74.90250899999999,39.892919],"type":"Point"}
}