{
  "type": "Feature",
  "properties": {
    "iso:country":"US",
    "sg:address":"3 Haytown Rd",
    "sg:city":"Lebanon",
    "sg:classifiers":[
        {
            "category":"Organizations",
            "subcategory":"Religious Organization",
            "type":"Services"
        }
    ],
    "sg:phone":"+1 908 236 6301",
    "sg:postcode":"08833",
    "sg:province":"NJ",
    "sg:website":"www.churchholyspirit.org",
    "wof:name":"Church Of The Holy Spirit",
    "wof:placetype":"venue"
},
  "geometry": {"coordinates":[-74.82965900000001,40.658703],"type":"Point"}
}