{
  "type": "Feature",
  "properties": {
    "iso:country":"US",
    "sg:address":"344 Rea Ave",
    "sg:city":"Hawthorne",
    "sg:classifiers":[
        {
            "category":"Wholesale",
            "subcategory":"Durable Goods & Equipment",
            "type":"Manufacturing & Wholesale Goods"
        }
    ],
    "sg:phone":"+1 973 423 0830",
    "sg:postcode":"07506",
    "sg:province":"NJ",
    "wof:name":"Kpl Sales",
    "wof:placetype":"venue"
},
  "geometry": {"coordinates":[-74.149314,40.95913],"type":"Point"}
}