{
  "type": "Feature",
  "properties": {
    "addr:full":"591 Lakehurst Rd Toms River NJ 08755",
    "addr:housenumber":"591",
    "addr:postcode":"08755",
    "addr:street":"Lakehurst Rd",
    "iso:country":"US",
    "sg:address":"591 Lakehurst Rd",
    "sg:city":"Toms River",
    "sg:classifiers":[
        {
            "category":"Social Services",
            "type":"Services"
        }
    ],
    "sg:phone":"+1 732 505 9420",
    "sg:postcode":"08755",
    "sg:province":"NJ",
    "sg:tags":[
        "care",
        "center",
        "day"
    ],
    "wof:name":"Adult Day Health Care Ctr",
    "wof:placetype":"venue"
},
  "geometry": {"coordinates":[-74.228534,39.967085],"type":"Point"}
}