{
  "type": "Feature",
  "properties": {
    "addr:full":"125 Louis St South Hackensack NJ 07606",
    "addr:housenumber":"125",
    "addr:postcode":"07606",
    "addr:street":"Louis St South",
    "iso:country":"US",
    "sg:address":"125 Louis St",
    "sg:city":"South Hackensack",
    "sg:classifiers":[
        {
            "category":"Professional",
            "type":"Services"
        }
    ],
    "sg:phone":"+1   ",
    "sg:postcode":"07606",
    "sg:province":"NJ",
    "wof:name":"Anderton United Products Inc",
    "wof:placetype":"venue"
},
  "geometry": {"coordinates":[-74.04684399999999,40.857365],"type":"Point"}
}