{
  "type": "Feature",
  "properties": {
    "addr:full":"58 Beechwood Rd Florham Park NJ 07932",
    "addr:housenumber":"58",
    "addr:postcode":"07932",
    "addr:street":"Beechwood Rd",
    "iso:country":"US",
    "sg:address":"58 Beechwood Rd",
    "sg:city":"Florham Park",
    "sg:classifiers":[
        {
            "category":"Professional",
            "subcategory":"Business Services",
            "type":"Services"
        }
    ],
    "sg:phone":"+1   ",
    "sg:postcode":"07932",
    "sg:province":"NJ",
    "wof:name":"R J Lake Enterprises Inc",
    "wof:placetype":"venue"
},
  "geometry": {"coordinates":[-74.38978899999999,40.756431],"type":"Point"}
}