{
  "type": "Feature",
  "properties": {
    "addr:full":"9 Riverview Ave Rumson NJ 07760",
    "addr:housenumber":"9",
    "addr:postcode":"07760",
    "addr:street":"Riverview Ave",
    "iso:country":"US",
    "sg:address":"9 Riverview Ave",
    "sg:city":"Rumson",
    "sg:classifiers":[
        {
            "category":"Professional",
            "subcategory":"Management & Consulting",
            "type":"Services"
        }
    ],
    "sg:phone":"+1   ",
    "sg:postcode":"07760",
    "sg:province":"NJ",
    "wof:name":"C F Stroh",
    "wof:placetype":"venue"
},
  "geometry": {"coordinates":[-73.996871,40.374221],"type":"Point"}
}