{
  "type": "Feature",
  "properties": {
    "addr:full":"784 E 23rd St Paterson NJ 07513",
    "addr:housenumber":"784",
    "addr:postcode":"07513",
    "addr:street":"E 23Rd St",
    "iso:country":"US",
    "sg:address":"784 E 23rd St",
    "sg:city":"Paterson",
    "sg:classifiers":[
        {
            "category":"Education",
            "subcategory":"Special Training",
            "type":"Public Place"
        }
    ],
    "sg:phone":"+1 973 523 6253",
    "sg:postcode":"07513",
    "sg:province":"NJ",
    "sg:tags":[
        "school",
        "instruction",
        "driving"
    ],
    "wof:name":"Alpine Driving",
    "wof:placetype":"venue"
},
  "geometry": {"coordinates":[-74.152489,40.913669],"type":"Point"}
}