{
  "type": "Feature",
  "properties": {
    "iso:country":"US",
    "sg:address":"18 Oliver St",
    "sg:city":"Newark",
    "sg:classifiers":[
        {
            "category":"Arts & Performance",
            "subcategory":"Arts Center",
            "type":"Entertainment"
        }
    ],
    "sg:phone":"+1 973 902 9040",
    "sg:postcode":"07101",
    "sg:province":"NJ",
    "sg:tags":[
        "performing"
    ],
    "sg:website":"wwwsirrich6@yahoo.com",
    "wof:name":"The Rich Place Your Performing Arts Center",
    "wof:placetype":"venue"
},
  "geometry": {"coordinates":[-74.172358,40.726874],"type":"Point"}
}