{
  "type": "Feature",
  "properties": {
    "addr:full":"432 Bergen Blvd Ste C Ridgefield NJ 07657",
    "addr:housenumber":"432",
    "addr:postcode":"07657",
    "addr:street":"Bergen Blvd Ste C",
    "iso:country":"US",
    "sg:address":"432 Bergen Blvd Ste C",
    "sg:city":"Ridgefield",
    "sg:classifiers":[
        {
            "category":"Health Services",
            "subcategory":"Doctor",
            "type":"Services"
        }
    ],
    "sg:phone":"+1 201 943 8746",
    "sg:postcode":"07657",
    "sg:province":"NJ",
    "sg:tags":[
        "surgeon",
        "oral"
    ],
    "wof:name":"Kaprielian Raffi DDS",
    "wof:placetype":"venue"
},
  "geometry": {"coordinates":[-73.998199,40.823299],"type":"Point"}
}