{
  "type": "Feature",
  "properties": {
    "iso:country":"US",
    "sg:address":"300 Gordons Corner Rd",
    "sg:city":"Englishtown",
    "sg:classifiers":[
        {
            "category":"Sports & Exercise",
            "subcategory":"Gym",
            "type":"Entertainment"
        }
    ],
    "sg:phone":"+1 732 972 8200",
    "sg:postcode":"07726",
    "sg:province":"NJ",
    "sg:tags":[
        "club",
        "health",
        "studio",
        "gymnasium"
    ],
    "wof:name":"Elite Fitness Ctr",
    "wof:placetype":"venue"
},
  "geometry": {"coordinates":[-74.32288200000001,40.308671],"type":"Point"}
}