{
  "type": "Feature",
  "properties": {
    "addr:full":"42 N Beverwyck Rd Lake Hiawatha NJ 07034",
    "addr:housenumber":"42",
    "addr:postcode":"07034",
    "addr:street":"N Beverwyck Rd",
    "iso:country":"US",
    "sg:address":"42 N Beverwyck Rd",
    "sg:city":"Lake Hiawatha",
    "sg:classifiers":[
        {
            "category":"Retail",
            "subcategory":"Auto Repair",
            "type":"Services"
        }
    ],
    "sg:phone":"+1 973 299 2900",
    "sg:postcode":"07034",
    "sg:province":"NJ",
    "wof:name":"Richs Automotive",
    "wof:placetype":"venue"
},
  "geometry": {"coordinates":[-74.38227999999999,40.878841],"type":"Point"}
}