{
  "type": "Feature",
  "properties": {
    "iso:country":"US",
    "sg:address":"31 Ashley Dr",
    "sg:city":"Holmdel",
    "sg:classifiers":[
        {
            "category":"Professional",
            "type":"Services"
        }
    ],
    "sg:phone":"+1   ",
    "sg:postcode":"07733",
    "sg:province":"NJ",
    "wof:name":"Vrajsan Inc",
    "wof:placetype":"venue"
},
  "geometry": {"coordinates":[-74.195261,40.374323],"type":"Point"}
}