{
  "type": "Feature",
  "properties": {
    "addr:full":"286 W Valley Brook Rd Califon NJ 07830",
    "addr:housenumber":"286",
    "addr:postcode":"07830",
    "addr:street":"W Valley Brook Rd",
    "iso:country":"US",
    "sg:address":"286 W Valley Brook Rd",
    "sg:city":"Califon",
    "sg:classifiers":[
        {
            "category":"Personal",
            "type":"Services"
        }
    ],
    "sg:phone":"+1 908 975 9119",
    "sg:postcode":"07830",
    "sg:province":"NJ",
    "sg:tags":[
        "local"
    ],
    "sg:website":"www.roalex.com",
    "wof:name":"Roalex Web Design",
    "wof:placetype":"venue"
},
  "geometry": {"coordinates":[-74.812139,40.743297],"type":"Point"}
}