{
  "type": "Feature",
  "properties": {
    "iso:country":"US",
    "sg:address":"413 Winslow Rd",
    "sg:city":"Williamstown",
    "sg:classifiers":[
        {
            "category":"Building & Trades",
            "subcategory":"Construction",
            "type":"Services"
        }
    ],
    "sg:phone":"+1 856 629 4452",
    "sg:postcode":"08094",
    "sg:province":"NJ",
    "sg:tags":[
        "general",
        "contractor"
    ],
    "wof:name":"J Williams and Sons",
    "wof:placetype":"venue"
},
  "geometry": {"coordinates":[-74.984397,39.685834],"type":"Point"}
}