{
  "type": "Feature",
  "properties": {
    "addr:full":"488 Mulberry St Newark NJ 07114",
    "addr:housenumber":"488",
    "addr:postcode":"07114",
    "addr:street":"Mulberry St",
    "iso:country":"US",
    "sg:address":"488 Mulberry St",
    "sg:city":"Newark",
    "sg:classifiers":[
        {
            "category":"Manufacturing",
            "subcategory":"Chemicals & Compounds",
            "type":"Manufacturing & Wholesale Goods"
        }
    ],
    "sg:phone":"+1 973 596 8342",
    "sg:postcode":"07114",
    "sg:province":"NJ",
    "sg:tags":[
        "adhesive",
        "sealant"
    ],
    "wof:name":"Craig Adhesives Co",
    "wof:placetype":"venue"
},
  "geometry": {"coordinates":[-74.175771,40.722022],"type":"Point"}
}