{
  "type": "Feature",
  "properties": {
    "iso:country":"US",
    "sg:address":"Foot of Princeton",
    "sg:city":"Chatham",
    "sg:classifiers":[
        {
            "category":"Bars & Pubs",
            "subcategory":"Nightclub",
            "type":"Food & Drink"
        }
    ],
    "sg:phone":"+1 973 635 9848",
    "sg:postcode":"07928",
    "sg:province":"NJ",
    "sg:tags":[
        "nightlife"
    ],
    "sg:website":"www.minisinkclub.com",
    "wof:name":"Minisink Club Inc Paddle Court",
    "wof:placetype":"venue"
},
  "geometry": {"coordinates":[-74.40280199999999,40.724899],"type":"Point"}
}