{
  "type": "Feature",
  "properties": {
    "addr:full":"610 White Horse Pike Oaklyn NJ 08107",
    "addr:housenumber":"610",
    "addr:postcode":"08107",
    "addr:street":"White Horse Pike",
    "iso:country":"US",
    "sg:address":"610 White Horse Pike",
    "sg:city":"Oaklyn",
    "sg:classifiers":[
        {
            "category":"Personal",
            "subcategory":"Shoe Repair & Shine",
            "type":"Services"
        }
    ],
    "sg:phone":"+1   ",
    "sg:postcode":"08107",
    "sg:province":"NJ",
    "sg:tags":[
        "parlor"
    ],
    "wof:name":"Bufanios Shoe Repair",
    "wof:placetype":"venue"
},
  "geometry": {"coordinates":[-75.07741,39.902611],"type":"Point"}
}