{
  "type": "Feature",
  "properties": {
    "addr:full":"64 Brinckerhoff Ave Freehold NJ 07728",
    "addr:housenumber":"64",
    "addr:postcode":"07728",
    "addr:street":"Brinckerhoff Ave",
    "iso:country":"US",
    "sg:address":"64 Brinckerhoff Ave",
    "sg:city":"Freehold",
    "sg:classifiers":[
        {
            "category":"Wholesale",
            "subcategory":"Durable Goods & Equipment",
            "type":"Manufacturing & Wholesale Goods"
        }
    ],
    "sg:phone":"+1 732 431 2089",
    "sg:postcode":"07728",
    "sg:province":"NJ",
    "sg:tags":[
        "representative",
        "manufacturer"
    ],
    "wof:name":"John D Rocco Sales Co",
    "wof:placetype":"venue"
},
  "geometry": {"coordinates":[-74.27449300000001,40.252019],"type":"Point"}
}