{
  "type": "Feature",
  "properties": {
    "iso:country":"US",
    "sg:address":"1191 Valley Rd",
    "sg:city":"Clifton",
    "sg:classifiers":[
        {
            "category":"Banks & Credit Unions",
            "subcategory":"Financial Services",
            "type":"Services"
        }
    ],
    "sg:phone":"+1 973 337 1010",
    "sg:postcode":"07013",
    "sg:province":"NJ",
    "sg:tags":[
        "broker",
        "mortgage"
    ],
    "wof:name":"First Lenders Mortgage",
    "wof:placetype":"venue"
},
  "geometry": {"coordinates":[-74.192812,40.864945],"type":"Point"}
}