{
  "type": "Feature",
  "properties": {
    "addr:full":"3 Riverview Dr W Montclair NJ 07043",
    "addr:housenumber":"3",
    "addr:postcode":"07043",
    "addr:street":"Riverview Dr W",
    "iso:country":"US",
    "sg:address":"3 Riverview Dr W",
    "sg:city":"Montclair",
    "sg:classifiers":[
        {
            "category":"Communications",
            "subcategory":"Film & Video Production",
            "type":"Services"
        }
    ],
    "sg:phone":"+1   ",
    "sg:postcode":"07043",
    "sg:province":"NJ",
    "sg:tags":[
        "motion",
        "business"
    ],
    "wof:name":"Proteus Music",
    "wof:placetype":"venue"
},
  "geometry": {"coordinates":[-74.189742,40.849329],"type":"Point"}
}