{
  "type": "Feature",
  "properties": {
    "addr:full":"205 Pershing Rd Clifton NJ 07013",
    "addr:housenumber":"205",
    "addr:postcode":"07013",
    "addr:street":"Pershing Rd",
    "iso:country":"US",
    "sg:address":"205 Pershing Rd",
    "sg:city":"Clifton",
    "sg:classifiers":[
        {
            "category":"Building & Trades",
            "subcategory":"Construction",
            "type":"Services"
        }
    ],
    "sg:phone":"+1 973 779 2067",
    "sg:postcode":"07013",
    "sg:province":"NJ",
    "sg:tags":[
        "apartment",
        "general",
        "contractor"
    ],
    "wof:name":"Tbaka Associates Inc",
    "wof:placetype":"venue"
},
  "geometry": {"coordinates":[-74.16939600000001,40.861714],"type":"Point"}
}