{
  "type": "Feature",
  "properties": {
    "addr:full":"171 N Haledon Ave Haledon NJ 07508",
    "addr:housenumber":"171",
    "addr:postcode":"07508",
    "addr:street":"N Haledon Ave",
    "iso:country":"US",
    "sg:address":"171 N Haledon Ave",
    "sg:city":"Haledon",
    "sg:classifiers":[
        {
            "category":"Retail",
            "subcategory":"Auto Repair",
            "type":"Services"
        }
    ],
    "sg:phone":"+1 973 423 1979",
    "sg:postcode":"07508",
    "sg:province":"NJ",
    "sg:tags":[
        "transmission",
        "general"
    ],
    "wof:name":"Ray Auto Repair",
    "wof:placetype":"venue"
},
  "geometry": {"coordinates":[-74.179479,40.9629],"type":"Point"}
}