{
  "type": "Feature",
  "properties": {
    "addr:full":"1355 Blackwood Clementon Rd Clementon NJ 08021",
    "addr:housenumber":"1355",
    "addr:postcode":"08021",
    "addr:street":"Blackwood Clementon Rd",
    "iso:country":"US",
    "sg:address":"1355 Blackwood Clementon Rd",
    "sg:city":"Clementon",
    "sg:classifiers":[
        {
            "category":"Fast Food",
            "type":"Food & Drink"
        },
        {
            "category":"Restaurant",
            "type":"Food & Drink"
        }
    ],
    "sg:phone":"+1 856 566 5727",
    "sg:postcode":"08021",
    "sg:province":"NJ",
    "sg:tags":[
        "take",
        "pizza"
    ],
    "wof:name":"Bisirri Pizza & Wings",
    "wof:placetype":"venue"
},
  "geometry": {"coordinates":[-75.034019,39.803699],"type":"Point"}
}