{
  "type": "Feature",
  "properties": {
    "iso:country":"US",
    "sg:address":"264 Terrace Ave",
    "sg:city":"Lodi",
    "sg:classifiers":[
        {
            "category":"Organizations",
            "subcategory":"Religious Organization",
            "type":"Services"
        }
    ],
    "sg:phone":"+1   ",
    "sg:postcode":"07644",
    "sg:province":"NJ",
    "wof:name":"Premi Sangat Church",
    "wof:placetype":"venue"
},
  "geometry": {"coordinates":[-74.085629,40.866807],"type":"Point"}
}