{
  "type": "Feature",
  "properties": {
    "iso:country":"US",
    "sg:address":"610 Winters Ave",
    "sg:city":"Paramus",
    "sg:classifiers":[
        {
            "category":"Manufacturing",
            "subcategory":"Tools & Machinery",
            "type":"Manufacturing & Wholesale Goods"
        }
    ],
    "sg:phone":"+1 201 599 1400",
    "sg:postcode":"07652",
    "sg:province":"NJ",
    "sg:tags":[
        "equipment",
        "laboratory",
        "supply"
    ],
    "sg:website":"www.globescientific.com",
    "wof:name":"Globe Scientific Inc",
    "wof:placetype":"venue"
},
  "geometry": {"coordinates":[-74.07248,40.963725],"type":"Point"}
}