{
  "type": "Feature",
  "properties": {
    "iso:country":"US",
    "sg:address":"150 E Kinney St",
    "sg:city":"Newark",
    "sg:classifiers":[
        {
            "category":"Building & Trades",
            "subcategory":"Locksmith",
            "type":"Services"
        }
    ],
    "sg:phone":"+1 973 854 5738",
    "sg:postcode":"07105",
    "sg:province":"NJ",
    "sg:tags":[
        "key"
    ],
    "wof:name":"0 7 7 Day Emergency A 24 Hour Locksmith",
    "wof:placetype":"venue"
},
  "geometry": {"coordinates":[-74.169078,40.726666],"type":"Point"}
}