{
  "type": "Feature",
  "properties": {
    "addr:full":"4 Connell Dr Berkeley Heights NJ 07922",
    "addr:housenumber":"4",
    "addr:postcode":"07922",
    "addr:street":"Connell Dr",
    "iso:country":"US",
    "sg:address":"4 Connell Dr",
    "sg:city":"Berkeley Heights",
    "sg:classifiers":[
        {
            "category":"Professional",
            "subcategory":"Employment Agencies",
            "type":"Services"
        }
    ],
    "sg:phone":"+1 908 464 4660",
    "sg:postcode":"07922",
    "sg:province":"NJ",
    "sg:tags":[
        "opportunity"
    ],
    "wof:name":"Update Legal",
    "wof:placetype":"venue"
},
  "geometry": {"coordinates":[-74.40883599999999,40.666067],"type":"Point"}
}