{
  "type": "Feature",
  "properties": {
    "addr:full":"832 Winchester Ave Hillside NJ 07205",
    "addr:housenumber":"832",
    "addr:postcode":"07205",
    "addr:street":"Winchester Ave",
    "iso:country":"US",
    "sg:address":"832 Winchester Ave",
    "sg:city":"Hillside",
    "sg:classifiers":[
        {
            "category":"Restaurant",
            "type":"Food & Drink"
        }
    ],
    "sg:phone":"+1   ",
    "sg:postcode":"07205",
    "sg:province":"NJ",
    "sg:tags":[
        "eating"
    ],
    "wof:name":"Chicks & Ribs Inc",
    "wof:placetype":"venue"
},
  "geometry": {"coordinates":[-74.22088599999999,40.681611],"type":"Point"}
}