{
  "type": "Feature",
  "properties": {
    "iso:country":"US",
    "sg:address":"2047 S Black Horse Pike",
    "sg:city":"Williamstown",
    "sg:classifiers":[
        {
            "category":"Manufacturing",
            "subcategory":"Glass & Minerals",
            "type":"Manufacturing & Wholesale Goods"
        }
    ],
    "sg:phone":"+1 856 728 2597",
    "sg:postcode":"08094",
    "sg:province":"NJ",
    "sg:tags":[
        "product",
        "r",
        "mfg"
    ],
    "wof:name":"Phillips Stained Glass Works",
    "wof:placetype":"venue"
},
  "geometry": {"coordinates":[-74.959433,39.656641],"type":"Point"}
}