{
  "type": "Feature",
  "properties": {
    "iso:country":"US",
    "sg:address":"1300 Ocean Ave",
    "sg:city":"Asbury Park",
    "sg:classifiers":[
        {
            "category":"Bars & Pubs",
            "type":"Food & Drink"
        }
    ],
    "sg:menulink":"http://www.allmenus.com/nj/asbury-park/283880-biggies-clam-bar/menu/",
    "sg:phone":"+1 201 656 2161",
    "sg:postcode":"07712",
    "sg:province":"NJ",
    "sg:tags":[
        "american"
    ],
    "wof:name":"Biggies Clam Bar",
    "wof:placetype":"venue"
},
  "geometry": {"coordinates":[-73.99892199999999,40.224417],"type":"Point"}
}