{
  "type": "Feature",
  "properties": {
    "iso:country":"US",
    "sg:address":"449 W Main St",
    "sg:city":"Maple Shade",
    "sg:classifiers":[
        {
            "category":"Home & Garden",
            "subcategory":"Garden Supply",
            "type":"Retail Goods"
        }
    ],
    "sg:phone":"+1 856 665 2761",
    "sg:postcode":"08052",
    "sg:province":"NJ",
    "sg:tags":[
        "lawn",
        "mower"
    ],
    "wof:name":"Lawnmower Repair Svc",
    "wof:placetype":"venue"
},
  "geometry": {"coordinates":[-75.009185,39.954687],"type":"Point"}
}