{
  "type": "Feature",
  "properties": {
    "iso:country":"US",
    "sg:address":"576 Raritan Rd",
    "sg:city":"Roselle",
    "sg:classifiers":[
        {
            "category":"Restaurant",
            "type":"Food & Drink"
        }
    ],
    "sg:phone":"+1 908 259 1100",
    "sg:postcode":"07203",
    "sg:province":"NJ",
    "sg:tags":[
        "eating",
        "pizza"
    ],
    "wof:name":"Mama's Gourmet Pizza",
    "wof:placetype":"venue"
},
  "geometry": {"coordinates":[-74.273201,40.644798],"type":"Point"}
}