{
  "type": "Feature",
  "properties": {
    "iso:country":"US",
    "sg:address":"315 Essex St",
    "sg:city":"Harrison",
    "sg:classifiers":[
        {
            "category":"Retail",
            "subcategory":"Auto Repair",
            "type":"Services"
        }
    ],
    "sg:phone":"+1 973 484 1485",
    "sg:postcode":"07029",
    "sg:province":"NJ",
    "wof:name":"Costa's Auto Repair Inc",
    "wof:placetype":"venue"
},
  "geometry": {"coordinates":[-74.15759300000001,40.7423],"type":"Point"}
}