{
  "type": "Feature",
  "properties": {
    "addr:full":"158 State Rte 10 Succasunna NJ 07876",
    "addr:housenumber":"158",
    "addr:postcode":"07876",
    "addr:street":"State Rte 10",
    "iso:country":"US",
    "sg:address":"158 State Rte 10",
    "sg:city":"Succasunna",
    "sg:classifiers":[
        {
            "category":"Personal",
            "subcategory":"Beauty Salon",
            "type":"Services"
        }
    ],
    "sg:phone":"+1 973 584 4522",
    "sg:postcode":"07876",
    "sg:province":"NJ",
    "sg:tags":[
        "shop"
    ],
    "wof:name":"Sondras Finale",
    "wof:placetype":"venue"
},
  "geometry": {"coordinates":[-74.64001399999999,40.868046],"type":"Point"}
}