{
  "type": "Feature",
  "properties": {
    "addr:full":"1242 Asbury Ave Asbury Park NJ 07712",
    "addr:housenumber":"1242",
    "addr:postcode":"07712",
    "addr:street":"Asbury Ave Asbury",
    "iso:country":"US",
    "sg:address":"1242 Asbury Ave",
    "sg:city":"Asbury Park",
    "sg:classifiers":[
        {
            "category":"Insurance",
            "subcategory":"Insurance Agent",
            "type":"Services"
        }
    ],
    "sg:phone":"+1 732 776 5910",
    "sg:postcode":"07712",
    "sg:province":"NJ",
    "wof:name":"Powell Insurance Service",
    "wof:placetype":"venue"
},
  "geometry": {"coordinates":[-74.019846,40.221985],"type":"Point"}
}