{
  "type": "Feature",
  "properties": {
    "iso:country":"US",
    "sg:address":"435 Hamburg Tpke",
    "sg:city":"Pompton Lakes",
    "sg:classifiers":[
        {
            "category":"Freight",
            "type":"Transportation"
        }
    ],
    "sg:phone":"+1 973 790 5677",
    "sg:postcode":"07442",
    "sg:province":"NJ",
    "sg:tags":[
        "delivery"
    ],
    "wof:name":"Ward Delivery",
    "wof:placetype":"venue"
},
  "geometry": {"coordinates":[-74.285304,40.997315],"type":"Point"}
}