{
  "type": "Feature",
  "properties": {
    "addr:full":"342 Audubon Rd Englewood NJ 07631",
    "addr:housenumber":"342",
    "addr:postcode":"07631",
    "addr:street":"Audubon Rd",
    "iso:country":"US",
    "sg:address":"342 Audubon Rd",
    "sg:city":"Englewood",
    "sg:classifiers":[
        {
            "category":"Social Services",
            "type":"Services"
        }
    ],
    "sg:phone":"+1 201 568 0562",
    "sg:postcode":"07631",
    "sg:province":"NJ",
    "sg:tags":[
        "counselor",
        "marriage",
        "family"
    ],
    "wof:name":"Naomi Feder",
    "wof:placetype":"venue"
},
  "geometry": {"coordinates":[-73.976812,40.8811],"type":"Point"}
}