{
  "type": "Feature",
  "properties": {
    "iso:country":"US",
    "sg:address":"175 US Hwy 46",
    "sg:city":"Fairfield",
    "sg:classifiers":[
        {
            "category":"Professional",
            "type":"Services"
        }
    ],
    "sg:phone":"+1 973 575 6037",
    "sg:postcode":"07004",
    "sg:province":"NJ",
    "sg:tags":[
        "establishment"
    ],
    "wof:name":"New Jersey Auto Test",
    "wof:placetype":"venue"
},
  "geometry": {"coordinates":[-74.305925,40.871134],"type":"Point"}
}