{
  "type": "Feature",
  "properties": {
    "iso:country":"US",
    "sg:address":"11 Longview Trl",
    "sg:city":"Denville",
    "sg:classifiers":[
        {
            "category":"Health Services",
            "subcategory":"Doctor",
            "type":"Services"
        }
    ],
    "sg:phone":"+1 973 627 2368",
    "sg:postcode":"07834",
    "sg:province":"NJ",
    "wof:name":"E Dougherty DMD",
    "wof:placetype":"venue"
},
  "geometry": {"coordinates":[-74.484213,40.886764],"type":"Point"}
}