{
  "type": "Feature",
  "properties": {
    "addr:full":"1 Maiden Ln Toms River NJ 08753",
    "addr:housenumber":"1",
    "addr:postcode":"08753",
    "addr:street":"Maiden Ln",
    "iso:country":"US",
    "sg:address":"1 Maiden Ln",
    "sg:city":"Toms River",
    "sg:classifiers":[
        {
            "category":"Professional",
            "subcategory":"Management & Consulting",
            "type":"Services"
        }
    ],
    "sg:phone":"+1 732 244 1100",
    "sg:postcode":"08753",
    "sg:province":"NJ",
    "sg:tags":[
        "product",
        "premium",
        "provides",
        "promotional"
    ],
    "wof:name":"Net Return LLC",
    "wof:placetype":"venue"
},
  "geometry": {"coordinates":[-74.188395,39.952152],"type":"Point"}
}