{
  "type": "Feature",
  "properties": {
    "addr:full":"341 Martin Luther King Jr Dr Jersey City NJ 07305",
    "addr:housenumber":"341",
    "addr:postcode":"07305",
    "addr:street":"Martin Luther King Jr Dr",
    "iso:country":"US",
    "sg:address":"341 Martin Luther King Jr Dr",
    "sg:city":"Jersey City",
    "sg:classifiers":[
        {
            "category":"Professional",
            "type":"Services"
        }
    ],
    "sg:phone":"+1 201 332 0076",
    "sg:postcode":"07305",
    "sg:province":"NJ",
    "sg:tags":[
        "establishment"
    ],
    "wof:name":"Luck 3",
    "wof:placetype":"venue"
},
  "geometry": {"coordinates":[-74.081204,40.709019],"type":"Point"}
}