{
  "type": "Feature",
  "properties": {
    "iso:country":"US",
    "sg:address":"333 Meadowlands Pkwy",
    "sg:city":"Secaucus",
    "sg:classifiers":[
        {
            "category":"Professional",
            "subcategory":"Engineering",
            "type":"Services"
        }
    ],
    "sg:phone":"+1 201 866 7171",
    "sg:postcode":"07094",
    "sg:province":"NJ",
    "sg:tags":[
        "engineer"
    ],
    "wof:name":"Mayo Lynch & Assoc Inc",
    "wof:placetype":"venue"
},
  "geometry": {"coordinates":[-74.07996199999999,40.780096],"type":"Point"}
}