{
  "type": "Feature",
  "properties": {
    "addr:full":"9 Switlik Rd Trenton NJ 08690",
    "addr:housenumber":"9",
    "addr:postcode":"08690",
    "addr:street":"Switlik Rd",
    "iso:country":"US",
    "sg:address":"9 Switlik Rd",
    "sg:city":"Trenton",
    "sg:classifiers":[
        {
            "category":"Building & Trades",
            "subcategory":"Construction",
            "type":"Services"
        }
    ],
    "sg:phone":"+1 609 890 0299",
    "sg:postcode":"08690",
    "sg:province":"NJ",
    "sg:tags":[
        "wallcoverings-installation",
        "wallpaper",
        "painting",
        "waterproofing",
        "contractor"
    ],
    "wof:name":"Malakates Pericles",
    "wof:placetype":"venue"
},
  "geometry": {"coordinates":[-74.64570000000001,40.208434],"type":"Point"}
}