{
  "type": "Feature",
  "properties": {
    "addr:full":"2299 Vauxhall Rd Union NJ 07083",
    "addr:housenumber":"2299",
    "addr:postcode":"07083",
    "addr:street":"Vauxhall Rd",
    "iso:country":"US",
    "sg:address":"2299 Vauxhall Rd",
    "sg:city":"Union",
    "sg:classifiers":[
        {
            "category":"Education",
            "subcategory":"Vocational School",
            "type":"Public Place"
        }
    ],
    "sg:phone":"+1   ",
    "sg:postcode":"07083",
    "sg:province":"NJ",
    "sg:tags":[
        "trade"
    ],
    "sg:website":"www.lincolntech.com",
    "wof:name":"Lincoln Technical Institute",
    "wof:placetype":"venue"
},
  "geometry": {"coordinates":[-74.275657,40.706333],"type":"Point"}
}