{
  "type": "Feature",
  "properties": {
    "addr:full":"61 Grove St Elmwood Park NJ 07407",
    "addr:housenumber":"61",
    "addr:postcode":"07407",
    "addr:street":"Grove St",
    "iso:country":"US",
    "sg:address":"61 Grove St",
    "sg:city":"Elmwood Park",
    "sg:classifiers":[
        {
            "category":"Freight",
            "type":"Transportation"
        }
    ],
    "sg:phone":"+1 201 475 1377",
    "sg:postcode":"07407",
    "sg:province":"NJ",
    "sg:tags":[
        "operator",
        "local",
        "trucking"
    ],
    "wof:name":"Wr Delivery Service",
    "wof:placetype":"venue"
},
  "geometry": {"coordinates":[-74.125339,40.90539],"type":"Point"}
}