{
  "type": "Feature",
  "properties": {
    "addr:full":"78 Lake St Jersey City NJ 07306",
    "addr:housenumber":"78",
    "addr:postcode":"07306",
    "addr:street":"Lake St",
    "iso:country":"US",
    "sg:address":"78 Lake St",
    "sg:city":"Jersey City",
    "sg:classifiers":[
        {
            "category":"Shopping",
            "subcategory":"News",
            "type":"Retail Goods"
        }
    ],
    "sg:phone":"+1   ",
    "sg:postcode":"07306",
    "sg:province":"NJ",
    "wof:name":"Spama Inc",
    "wof:placetype":"venue"
},
  "geometry": {"coordinates":[-74.05828200000001,40.742877],"type":"Point"}
}