{
  "type": "Feature",
  "properties": {
    "iso:country":"US",
    "sg:address":"17 Arcadian Way Ste 200",
    "sg:city":"Paramus",
    "sg:classifiers":[
        {
            "category":"Social Services",
            "type":"Services"
        },
        {
            "category":"Social Services",
            "subcategory":"Job Training",
            "type":"Services"
        }
    ],
    "sg:phone":"+1 201 368 1414",
    "sg:postcode":"07652",
    "sg:province":"NJ",
    "sg:tags":[
        "employment"
    ],
    "sg:website":"http://www.hird.org",
    "wof:name":"Hispanic Institute For Research & Development Of Bergen County Inc",
    "wof:placetype":"venue"
},
  "geometry": {"coordinates":[-74.08506800000001,40.922588],"type":"Point"}
}