{
  "type": "Feature",
  "properties": {
    "addr:full":"149 Birchview Dr Piscataway NJ 08854",
    "addr:housenumber":"149",
    "addr:postcode":"08854",
    "addr:street":"Birchview Dr",
    "iso:country":"US",
    "sg:address":"149 Birchview Dr",
    "sg:city":"Piscataway",
    "sg:classifiers":[
        {
            "category":"Local Transit",
            "type":"Transportation"
        }
    ],
    "sg:phone":"+1 732 564 0601",
    "sg:postcode":"08854",
    "sg:province":"NJ",
    "sg:tags":[
        "passenger"
    ],
    "wof:name":"A Travel A Limousine LLC",
    "wof:placetype":"venue"
},
  "geometry": {"coordinates":[-74.51047,40.543699],"type":"Point"}
}