{
  "type": "Feature",
  "properties": {
    "iso:country":"US",
    "sg:address":"250 Spring Valley Ave",
    "sg:city":"Hackensack",
    "sg:classifiers":[
        {
            "category":"Personal",
            "subcategory":"Beauty Salon",
            "type":"Services"
        }
    ],
    "sg:phone":"+1 201 498 1777",
    "sg:postcode":"07601",
    "sg:province":"NJ",
    "sg:tags":[
        "shop"
    ],
    "wof:name":"Cindys Hair Studio",
    "wof:placetype":"venue"
},
  "geometry": {"coordinates":[-74.051879,40.909029],"type":"Point"}
}