{
  "type": "Feature",
  "properties": {
    "iso:country":"US",
    "sg:address":"1805 New Rd",
    "sg:city":"Northfield",
    "sg:classifiers":[
        {
            "category":"Insurance",
            "subcategory":"Insurance Agent",
            "type":"Services"
        }
    ],
    "sg:phone":"+1 609 407 1299",
    "sg:postcode":"08225",
    "sg:province":"NJ",
    "wof:name":"Gold Coast Mortgage LLC",
    "wof:placetype":"venue"
},
  "geometry": {"coordinates":[-74.559837,39.369212],"type":"Point"}
}