{
  "type": "Feature",
  "properties": {
    "iso:country":"US",
    "sg:address":"200 South St",
    "sg:city":"Morristown",
    "sg:classifiers":[
        {
            "category":"Government",
            "subcategory":"Office",
            "type":"Public Place"
        }
    ],
    "sg:phone":"+1 973 292 6709",
    "sg:postcode":"07960",
    "sg:province":"NJ",
    "sg:tags":[
        "village"
    ],
    "wof:name":"Morristown Rent Leveling Div",
    "wof:placetype":"venue"
},
  "geometry": {"coordinates":[-74.47326700000001,40.789712],"type":"Point"}
}