{
  "type": "Feature",
  "properties": {
    "addr:full":"51 S Woodside Ave Bergenfield NJ 07621",
    "addr:housenumber":"51",
    "addr:postcode":"07621",
    "addr:street":"S Woodside Ave",
    "iso:country":"US",
    "sg:address":"51 S Woodside Ave",
    "sg:city":"Bergenfield",
    "sg:classifiers":[
        {
            "category":"Building & Trades",
            "subcategory":"Construction",
            "type":"Services"
        }
    ],
    "sg:phone":"+1 201 244 1918",
    "sg:postcode":"07621",
    "sg:province":"NJ",
    "sg:tags":[
        "carpentry",
        "contractor"
    ],
    "wof:name":"Ten Point Construction",
    "wof:placetype":"venue"
},
  "geometry": {"coordinates":[-73.991619,40.927078],"type":"Point"}
}