{
  "type": "Feature",
  "properties": {
    "iso:country":"US",
    "sg:address":"749 W Side Ave",
    "sg:city":"Jersey City",
    "sg:classifiers":[
        {
            "category":"Restaurant",
            "type":"Food & Drink"
        }
    ],
    "sg:phone":"+1 201 985 2440",
    "sg:postcode":"07306",
    "sg:province":"NJ",
    "sg:tags":[
        "eating"
    ],
    "wof:name":"Amy's Ihawan Restaurant",
    "wof:placetype":"venue"
},
  "geometry": {"coordinates":[-74.076818,40.726447],"type":"Point"}
}