{
  "type": "Feature",
  "properties": {
    "iso:country":"US",
    "sg:address":"255 Poplar Ave",
    "sg:city":"Hackensack",
    "sg:classifiers":[
        {
            "category":"Shopping",
            "subcategory":"Hobbies, Toys, & Games",
            "type":"Retail Goods"
        }
    ],
    "sg:phone":"+1 201 342 6969",
    "sg:postcode":"07601",
    "sg:province":"NJ",
    "sg:tags":[
        "supply"
    ],
    "wof:name":"Gamers Dream",
    "wof:placetype":"venue"
},
  "geometry": {"coordinates":[-74.049323,40.903651],"type":"Point"}
}