{
  "type": "Feature",
  "properties": {
    "iso:country":"US",
    "sg:address":"523 Berlin Cross Keys Rd",
    "sg:city":"Sicklerville",
    "sg:classifiers":[
        {
            "category":"Shopping",
            "subcategory":"Discount & Variety Stores",
            "type":"Retail Goods"
        }
    ],
    "sg:phone":"+1 856 629 9888",
    "sg:postcode":"08081",
    "sg:province":"NJ",
    "wof:name":"D J Dollar World",
    "wof:placetype":"venue"
},
  "geometry": {"coordinates":[-74.993863,39.744887],"type":"Point"}
}