{
  "type": "Feature",
  "properties": {
    "addr:full":"10 John St Little Ferry NJ 07643",
    "addr:housenumber":"10",
    "addr:postcode":"07643",
    "addr:street":"John St",
    "iso:country":"US",
    "sg:address":"10 John St",
    "sg:city":"Little Ferry",
    "sg:classifiers":[
        {
            "category":"Retail",
            "subcategory":"Auto Repair",
            "type":"Services"
        }
    ],
    "sg:phone":"+1 201 641 1541",
    "sg:postcode":"07643",
    "sg:province":"NJ",
    "sg:tags":[
        "body",
        "automobile",
        "painting"
    ],
    "wof:name":"Mike Romano's Auto Body",
    "wof:placetype":"venue"
},
  "geometry": {"coordinates":[-74.041298,40.851501],"type":"Point"}
}