{
  "type": "Feature",
  "properties": {
    "iso:country":"US",
    "sg:address":"1358 State Rt 17",
    "sg:city":"Ramsey",
    "sg:classifiers":[
        {
            "category":"Restaurant",
            "type":"Food & Drink"
        }
    ],
    "sg:menulink":"http://www.allmenus.com/nj/ramsey/181749-wendys/menu/",
    "sg:phone":"+1 201 785 1079",
    "sg:postcode":"07446",
    "sg:province":"NJ",
    "sg:tags":[
        "burger",
        "american",
        "soup"
    ],
    "wof:name":"Wendy's",
    "wof:placetype":"venue"
},
  "geometry": {"coordinates":[-74.140849,41.072452],"type":"Point"}
}