{
  "type": "Feature",
  "properties": {
    "iso:country":"US",
    "sg:address":"102 Pleasant Grove Rd",
    "sg:city":"Long Valley",
    "sg:classifiers":[
        {
            "category":"Building & Trades",
            "subcategory":"Plumbing",
            "type":"Services"
        }
    ],
    "sg:phone":"+1 908 979 1555",
    "sg:postcode":"07853",
    "sg:province":"NJ",
    "wof:name":"Daly Plumbing & Heating",
    "wof:placetype":"venue"
},
  "geometry": {"coordinates":[-74.84719800000001,40.7803],"type":"Point"}
}