{
  "type": "Feature",
  "properties": {
    "iso:country":"US",
    "sg:address":"16 E Maple Ave",
    "sg:city":"Moorestown",
    "sg:classifiers":[
        {
            "category":"Professional",
            "subcategory":"Management & Consulting",
            "type":"Services"
        }
    ],
    "sg:phone":"+1 856 231 0096",
    "sg:postcode":"08057",
    "sg:province":"NJ",
    "sg:tags":[
        "construction"
    ],
    "wof:name":"E A Ulrichsen Inc",
    "wof:placetype":"venue"
},
  "geometry": {"coordinates":[-74.95061200000001,39.970808],"type":"Point"}
}