{
  "type": "Feature",
  "properties": {
    "addr:full":"4 Kings Hwy E Haddonfield NJ 08033",
    "addr:housenumber":"4",
    "addr:postcode":"08033",
    "addr:street":"Kings Hwy E",
    "iso:country":"US",
    "sg:address":"4 Kings Hwy E",
    "sg:city":"Haddonfield",
    "sg:classifiers":[
        {
            "category":"Professional",
            "subcategory":"Lawyer & Legal Services",
            "type":"Services"
        }
    ],
    "sg:phone":"+1 856 795 1113",
    "sg:postcode":"08033",
    "sg:province":"NJ",
    "sg:website":"www.astorweiss.com",
    "wof:name":"Astor Weiss & Newman",
    "wof:placetype":"venue"
},
  "geometry": {"coordinates":[-75.035794,39.89603],"type":"Point"}
}