{
  "type": "Feature",
  "properties": {
    "addr:full":"334 Yale Ave Hillside NJ 07205",
    "addr:housenumber":"334",
    "addr:postcode":"07205",
    "addr:street":"Yale Ave",
    "iso:country":"US",
    "sg:address":"334 Yale Ave",
    "sg:city":"Hillside",
    "sg:classifiers":[
        {
            "category":"Personal",
            "type":"Services"
        }
    ],
    "sg:phone":"+1   ",
    "sg:postcode":"07205",
    "sg:province":"NJ",
    "wof:name":"Lyons Manor",
    "wof:placetype":"venue"
},
  "geometry": {"coordinates":[-74.233525,40.698373],"type":"Point"}
}