{
  "type": "Feature",
  "properties": {
    "iso:country":"US",
    "sg:address":"56 Evergreen Rd",
    "sg:city":"Woodbine",
    "sg:classifiers":[
        {
            "category":"Manufacturing",
            "subcategory":"Building Materials",
            "type":"Manufacturing & Wholesale Goods"
        }
    ],
    "sg:phone":"+1 609 861 7069",
    "sg:postcode":"08270",
    "sg:province":"NJ",
    "sg:tags":[
        "mfg"
    ],
    "wof:name":"Belleplain Woodworks",
    "wof:placetype":"venue"
},
  "geometry": {"coordinates":[-74.865493,39.261811],"type":"Point"}
}