{
  "type": "Feature",
  "properties": {
    "iso:country":"US",
    "sg:address":"575 Alabama Ave",
    "sg:city":"Brick",
    "sg:classifiers":[
        {
            "category":"Personal",
            "subcategory":"Beauty Salon",
            "type":"Services"
        }
    ],
    "sg:phone":"+1 732 458 5082",
    "sg:postcode":"08724",
    "sg:province":"NJ",
    "sg:tags":[
        "shop"
    ],
    "wof:name":"Cavalier Hair Stylst",
    "wof:placetype":"venue"
},
  "geometry": {"coordinates":[-74.12603,40.107574],"type":"Point"}
}