{
  "type": "Feature",
  "properties": {
    "iso:country":"US",
    "sg:address":"3 Robby Dr",
    "sg:city":"Oakhurst",
    "sg:classifiers":[
        {
            "category":"Manufacturing",
            "subcategory":"Printing",
            "type":"Manufacturing & Wholesale Goods"
        }
    ],
    "sg:phone":"+1 732 531 5450",
    "sg:postcode":"07755",
    "sg:province":"NJ",
    "sg:tags":[
        "commercial",
        "offset"
    ],
    "wof:name":"M R Daniels Associates",
    "wof:placetype":"venue"
},
  "geometry": {"coordinates":[-74.018889,40.263938],"type":"Point"}
}