{
  "type": "Feature",
  "properties": {
    "iso:country":"US",
    "sg:address":"37 Main Ave",
    "sg:city":"Wallington",
    "sg:classifiers":[
        {
            "category":"Restaurant",
            "type":"Food & Drink"
        },
        {
            "category":"Food & Beverages",
            "subcategory":"Groceries & Convenience Stores",
            "type":"Retail Goods"
        }
    ],
    "sg:phone":"+1 973 473 3771",
    "sg:postcode":"07057",
    "sg:province":"NJ",
    "sg:tags":[
        "deli",
        "delicatessen"
    ],
    "wof:name":"K & D's Meats & Deli",
    "wof:placetype":"venue"
},
  "geometry": {"coordinates":[-74.117401,40.854801],"type":"Point"}
}