{
  "type": "Feature",
  "properties": {
    "iso:country":"US",
    "sg:address":"1690 State Rte 38",
    "sg:city":"Mount Holly",
    "sg:classifiers":[
        {
            "category":"Cinema",
            "subcategory":"Movie Rental",
            "type":"Entertainment"
        }
    ],
    "sg:phone":"+1   ",
    "sg:postcode":"08060",
    "sg:province":"NJ",
    "wof:name":"T & S Video",
    "wof:placetype":"venue"
},
  "geometry": {"coordinates":[-74.83313800000001,39.976905],"type":"Point"}
}