{
  "type": "Feature",
  "properties": {
    "addr:full":"253 Livingston Ave New Brunswick NJ 08901",
    "addr:housenumber":"253",
    "addr:postcode":"08901",
    "addr:street":"Livingston Ave",
    "iso:country":"US",
    "sg:address":"253 Livingston Ave",
    "sg:city":"New Brunswick",
    "sg:classifiers":[
        {
            "category":"Local Transit",
            "type":"Transportation"
        }
    ],
    "sg:phone":"+1 732 937 5006",
    "sg:postcode":"08901",
    "sg:province":"NJ",
    "sg:tags":[
        "limousine"
    ],
    "wof:name":"Latino Car & Limo Svc",
    "wof:placetype":"venue"
},
  "geometry": {"coordinates":[-74.4539,40.484098],"type":"Point"}
}