{
  "type": "Feature",
  "properties": {
    "iso:country":"US",
    "sg:address":"10 Everittstown Hill Rd",
    "sg:city":"Frenchtown",
    "sg:classifiers":[
        {
            "category":"Building & Trades",
            "subcategory":"Landscaping Services",
            "type":"Services"
        }
    ],
    "sg:phone":"+1 908 996 8000",
    "sg:postcode":"08825",
    "sg:province":"NJ",
    "sg:tags":[
        "landscape",
        "contractor"
    ],
    "wof:name":"Hille Landscaping",
    "wof:placetype":"venue"
},
  "geometry": {"coordinates":[-75.059161,40.528751],"type":"Point"}
}