{
  "type": "Feature",
  "properties": {
    "iso:country":"US",
    "sg:address":"1208 Delsea Dr",
    "sg:city":"Westville",
    "sg:classifiers":[
        {
            "category":"Social Services",
            "subcategory":"Job Training",
            "type":"Services"
        }
    ],
    "sg:phone":"+1 856 848 1025",
    "sg:postcode":"08093",
    "sg:province":"NJ",
    "sg:tags":[
        "packing",
        "crating",
        "center",
        "vocational"
    ],
    "sg:website":"http://www.abilities4work.com",
    "wof:name":"Abilities Center",
    "wof:placetype":"venue"
},
  "geometry": {"coordinates":[-75.12509900000001,39.843672],"type":"Point"}
}