{
  "type": "Feature",
  "properties": {
    "iso:country":"US",
    "sg:address":"24 Church St",
    "sg:city":"Montclair",
    "sg:classifiers":[
        {
            "category":"Professional",
            "subcategory":"Art Services",
            "type":"Services"
        }
    ],
    "sg:phone":"+1 973 783 1155",
    "sg:postcode":"07042",
    "sg:province":"NJ",
    "sg:tags":[
        "arts",
        "designer",
        "commercial",
        "related",
        "graphic",
        "design"
    ],
    "wof:name":"U P Design Inc",
    "wof:placetype":"venue"
},
  "geometry": {"coordinates":[-74.21924,40.81389],"type":"Point"}
}