{
  "type": "Feature",
  "properties": {
    "addr:full":"300 Grand St Hoboken NJ 07030",
    "addr:housenumber":"300",
    "addr:postcode":"07030",
    "addr:street":"Grand St",
    "iso:country":"US",
    "sg:address":"300 Grand St",
    "sg:city":"Hoboken",
    "sg:classifiers":[
        {
            "category":"Real Estate",
            "subcategory":"Real Estate Agent",
            "type":"Services"
        }
    ],
    "sg:phone":"+1 201 222 0021",
    "sg:postcode":"07030",
    "sg:province":"NJ",
    "wof:name":"Torchmark Properties LLC",
    "wof:placetype":"venue"
},
  "geometry": {"coordinates":[-74.03522599999999,40.742191],"type":"Point"}
}