{
  "type": "Feature",
  "properties": {
    "iso:country":"US",
    "sg:address":"169 E Main St",
    "sg:city":"Prospect Park",
    "sg:classifiers":[
        {
            "category":"Autos & Motor Vehicles",
            "subcategory":"Automobile Sales",
            "type":"Retail Goods"
        }
    ],
    "sg:phone":"+1 973 790 7005",
    "sg:postcode":"07508",
    "sg:province":"NJ",
    "sg:tags":[
        "car",
        "dealer"
    ],
    "wof:name":"Walsh Auto",
    "wof:placetype":"venue"
},
  "geometry": {"coordinates":[-74.16821400000001,40.932243],"type":"Point"}
}