{
  "type": "Feature",
  "properties": {
    "addr:full":"8 Casey Ave Edison NJ 08817",
    "addr:housenumber":"8",
    "addr:postcode":"08817",
    "addr:street":"Casey Ave",
    "iso:country":"US",
    "sg:address":"8 Casey Ave",
    "sg:city":"Edison",
    "sg:classifiers":[
        {
            "category":"Building & Trades",
            "subcategory":"Plumbing",
            "type":"Services"
        }
    ],
    "sg:phone":"+1 732 287 0770",
    "sg:postcode":"08817",
    "sg:province":"NJ",
    "sg:tags":[
        "plumbing",
        "contractor"
    ],
    "wof:name":"Family Plumbing & Heating Inc",
    "wof:placetype":"venue"
},
  "geometry": {"coordinates":[-74.393404,40.522761],"type":"Point"}
}