{
  "type": "Feature",
  "properties": {
    "addr:full":"151 Broadway Long Branch NJ 07740",
    "addr:housenumber":"151",
    "addr:postcode":"07740",
    "addr:street":"Broadway",
    "iso:country":"US",
    "sg:address":"151 Broadway",
    "sg:city":"Long Branch",
    "sg:classifiers":[
        {
            "category":"Retail",
            "subcategory":"Repair Shop",
            "type":"Services"
        }
    ],
    "sg:phone":"+1 732 229 7419",
    "sg:postcode":"07740",
    "sg:province":"NJ",
    "sg:tags":[
        "refinishing",
        "furniture"
    ],
    "wof:name":"A and K Furniture Restoration",
    "wof:placetype":"venue"
},
  "geometry": {"coordinates":[-73.983898,40.3051],"type":"Point"}
}