{
  "type": "Feature",
  "properties": {
    "iso:country":"US",
    "sg:address":"71 Woodmont Dr",
    "sg:city":"Trenton",
    "sg:classifiers":[
        {
            "category":"Professional",
            "subcategory":"Management & Consulting",
            "type":"Services"
        }
    ],
    "sg:phone":"+1   ",
    "sg:postcode":"08648",
    "sg:province":"NJ",
    "wof:name":"Noel Consulting",
    "wof:placetype":"venue"
},
  "geometry": {"coordinates":[-74.723422,40.284081],"type":"Point"}
}