{
  "type": "Feature",
  "properties": {
    "addr:full":"3 N Beverwyck Rd Lake Hiawatha NJ 07034",
    "addr:housenumber":"3",
    "addr:postcode":"07034",
    "addr:street":"N Beverwyck Rd",
    "iso:country":"US",
    "sg:address":"3 N Beverwyck Rd",
    "sg:city":"Lake Hiawatha",
    "sg:classifiers":[
        {
            "category":"Retail",
            "subcategory":"Auto Repair",
            "type":"Services"
        }
    ],
    "sg:phone":"+1 973 402 5542",
    "sg:postcode":"07034",
    "sg:province":"NJ",
    "sg:tags":[
        "body",
        "shop"
    ],
    "wof:name":"Eastern Asia Auto Care Center",
    "wof:placetype":"venue"
},
  "geometry": {"coordinates":[-74.382559,40.878639],"type":"Point"}
}