{
  "type": "Feature",
  "properties": {
    "addr:full":"326 Victor St Scotch Plains NJ 07076",
    "addr:housenumber":"326",
    "addr:postcode":"07076",
    "addr:street":"Victor St",
    "iso:country":"US",
    "sg:address":"326 Victor St",
    "sg:city":"Scotch Plains",
    "sg:classifiers":[
        {
            "category":"Professional",
            "subcategory":"Employment Agencies",
            "type":"Services"
        }
    ],
    "sg:phone":"+1 908 889 6226",
    "sg:postcode":"07076",
    "sg:province":"NJ",
    "wof:name":"Deployed Resources LLC",
    "wof:placetype":"venue"
},
  "geometry": {"coordinates":[-74.386498,40.661843],"type":"Point"}
}