{
  "type": "Feature",
  "properties": {
    "addr:full":"144 W Pleasant Ave Maywood NJ 07607",
    "addr:housenumber":"144",
    "addr:postcode":"07607",
    "addr:street":"W Pleasant Ave",
    "iso:country":"US",
    "sg:address":"144 W Pleasant Ave",
    "sg:city":"Maywood",
    "sg:classifiers":[
        {
            "category":"Building & Trades",
            "subcategory":"Locksmith",
            "type":"Services"
        }
    ],
    "sg:phone":"+1 888 265 6767",
    "sg:postcode":"07607",
    "sg:province":"NJ",
    "sg:tags":[
        "key"
    ],
    "wof:name":"1 24 Hour Emergency Locksmith",
    "wof:placetype":"venue"
},
  "geometry": {"coordinates":[-74.06547399999999,40.906089],"type":"Point"}
}