{
  "type": "Feature",
  "properties": {
    "iso:country":"US",
    "sg:address":"925 US Hwy 130",
    "sg:city":"North Brunswick",
    "sg:classifiers":[
        {
            "category":"Freight",
            "type":"Transportation"
        }
    ],
    "sg:phone":"+1 732 422 9900",
    "sg:postcode":"08902",
    "sg:province":"NJ",
    "wof:name":"Pioneer Logistics Inc",
    "wof:placetype":"venue"
},
  "geometry": {"coordinates":[-74.455314,40.459806],"type":"Point"}
}