{
  "type": "Feature",
  "properties": {
    "iso:country":"US",
    "sg:address":"78 Bradford Ln",
    "sg:city":"Plainsboro",
    "sg:classifiers":[
        {
            "category":"Professional",
            "type":"Services"
        }
    ],
    "sg:phone":"+1   ",
    "sg:postcode":"08536",
    "sg:province":"NJ",
    "wof:name":"E Co Net Services Inc",
    "wof:placetype":"venue"
},
  "geometry": {"coordinates":[-74.551579,40.330212],"type":"Point"}
}