{
  "type": "Feature",
  "properties": {
    "iso:country":"US",
    "sg:address":"126 East Ave",
    "sg:city":"Bridgeton",
    "sg:classifiers":[
        {
            "category":"Taxi",
            "type":"Transportation"
        }
    ],
    "sg:phone":"+1 856 453 7789",
    "sg:postcode":"08302",
    "sg:province":"NJ",
    "sg:tags":[
        "taxicab",
        "local",
        "passenger"
    ],
    "wof:name":"Lavenia Transportation Inc",
    "wof:placetype":"venue"
},
  "geometry": {"coordinates":[-75.22595099999999,39.43386],"type":"Point"}
}