{
  "type": "Feature",
  "properties": {
    "addr:full":"1004 Haddonfield Rd Cherry Hill NJ 08002",
    "addr:housenumber":"1004",
    "addr:postcode":"08002",
    "addr:street":"Haddonfield Rd",
    "iso:country":"US",
    "sg:address":"1004 Haddonfield Rd",
    "sg:city":"Cherry Hill",
    "sg:classifiers":[
        {
            "category":"Health Services",
            "subcategory":"Doctor",
            "type":"Services"
        }
    ],
    "sg:phone":"+1 856 662 7733",
    "sg:postcode":"08002",
    "sg:province":"NJ",
    "sg:tags":[
        "physician",
        "surgeon"
    ],
    "wof:name":"South Jersey Sports Medicine",
    "wof:placetype":"venue"
},
  "geometry": {"coordinates":[-75.03359399999999,39.922077],"type":"Point"}
}