{
  "type": "Feature",
  "properties": {
    "addr:full":"2907 Bergenline Ave Union City NJ 07087",
    "addr:housenumber":"2907",
    "addr:postcode":"07087",
    "addr:street":"Bergenline Ave",
    "iso:country":"US",
    "sg:address":"2907 Bergenline Ave",
    "sg:city":"Union City",
    "sg:classifiers":[
        {
            "category":"Food & Beverages",
            "subcategory":"Specialty",
            "type":"Retail Goods"
        }
    ],
    "sg:phone":"+1   ",
    "sg:postcode":"07087",
    "sg:province":"NJ",
    "sg:tags":[
        "stone",
        "herb",
        "sale",
        "preparation",
        "statue",
        "candle",
        "medal"
    ],
    "wof:name":"Belie Belcan Botanica Corp",
    "wof:placetype":"venue"
},
  "geometry": {"coordinates":[-74.03000400000001,40.771133],"type":"Point"}
}