{
  "type": "Feature",
  "properties": {
    "iso:country":"US",
    "sg:address":"16 Mayflower Dr",
    "sg:city":"Sicklerville",
    "sg:classifiers":[
        {
            "category":"Health Services",
            "subcategory":"Doctor",
            "type":"Services"
        }
    ],
    "sg:phone":"+1 856 728 1543",
    "sg:postcode":"08081",
    "sg:province":"NJ",
    "sg:tags":[
        "physician",
        "surgeon"
    ],
    "wof:name":"Heart Institute Of Southern Nj",
    "wof:placetype":"venue"
},
  "geometry": {"coordinates":[-75.01848099999999,39.728259],"type":"Point"}
}