{
  "type": "Feature",
  "properties": {
    "addr:full":"227 N Vermont Ave Atlantic City NJ 08401",
    "addr:housenumber":"227",
    "addr:postcode":"08401",
    "addr:street":"N Vermont Ave",
    "iso:country":"US",
    "sg:address":"227 N Vermont Ave",
    "sg:city":"Atlantic City",
    "sg:classifiers":[
        {
            "category":"Government",
            "subcategory":"Office",
            "type":"Public Place"
        }
    ],
    "sg:phone":"+1 609 344 4106",
    "sg:postcode":"08401",
    "sg:province":"NJ",
    "wof:name":"Jeffries Towers Nutrition Site",
    "wof:placetype":"venue"
},
  "geometry": {"coordinates":[-74.41692999999999,39.371869],"type":"Point"}
}