{
  "type": "Feature",
  "properties": {
    "addr:full":"1457 Kenwood Ave Camden NJ 08103",
    "addr:housenumber":"1457",
    "addr:postcode":"08103",
    "addr:street":"Kenwood Ave",
    "iso:country":"US",
    "sg:address":"1457 Kenwood Ave",
    "sg:city":"Camden",
    "sg:classifiers":[
        {
            "category":"Health Services",
            "subcategory":"Nursing And Care Facility",
            "type":"Services"
        }
    ],
    "sg:phone":"+1 856 966 1932",
    "sg:postcode":"08103",
    "sg:province":"NJ",
    "sg:tags":[
        "home",
        "aged",
        "convalescent",
        "homes-institutional"
    ],
    "wof:name":"Nancy's Rest Home",
    "wof:placetype":"venue"
},
  "geometry": {"coordinates":[-75.097742,39.930407],"type":"Point"}
}