{
  "type": "Feature",
  "properties": {
    "iso:country":"US",
    "sg:address":"69 E Main St",
    "sg:city":"Little Falls",
    "sg:classifiers":[
        {
            "category":"Restaurant",
            "type":"Food & Drink"
        }
    ],
    "sg:phone":"+1   ",
    "sg:postcode":"07424",
    "sg:province":"NJ",
    "sg:tags":[
        "eating"
    ],
    "wof:name":"Chang Sing Restaurant",
    "wof:placetype":"venue"
},
  "geometry": {"coordinates":[-74.223086,40.88008],"type":"Point"}
}