{
  "type": "Feature",
  "properties": {
    "iso:country":"US",
    "sg:address":"29 New Mashipacong Rd",
    "sg:city":"Montague",
    "sg:classifiers":[
        {
            "category":"Retail",
            "subcategory":"Laundry & Dry Cleaning",
            "type":"Services"
        }
    ],
    "sg:phone":"+1 973 293 8824",
    "sg:postcode":"07827",
    "sg:province":"NJ",
    "sg:tags":[
        "cleaner",
        "rug",
        "carpet"
    ],
    "wof:name":"Suzanne Mcmickle",
    "wof:placetype":"venue"
},
  "geometry": {"coordinates":[-74.73770500000001,41.324046],"type":"Point"}
}