{
  "type": "Feature",
  "properties": {
    "addr:full":"620 S 7th St Vineland NJ 08360",
    "addr:housenumber":"620",
    "addr:postcode":"08360",
    "addr:street":"S 7Th St",
    "iso:country":"US",
    "sg:address":"620 S 7th St",
    "sg:city":"Vineland",
    "sg:classifiers":[
        {
            "category":"Personal",
            "subcategory":"Barber",
            "type":"Services"
        }
    ],
    "sg:phone":"+1 856 205 1440",
    "sg:postcode":"08360",
    "sg:province":"NJ",
    "sg:tags":[
        "shop"
    ],
    "wof:name":"Reyes Barber Shop",
    "wof:placetype":"venue"
},
  "geometry": {"coordinates":[-75.021719,39.479008],"type":"Point"}
}