{
  "type": "Feature",
  "properties": {
    "iso:country":"US",
    "sg:address":"128 Iozia Ter",
    "sg:city":"Elmwood Park",
    "sg:phone":"+1 201 873 1122",
    "sg:postcode":"07407",
    "sg:province":"NJ",
    "sg:tags":[
        "equipment",
        "commercial"
    ],
    "wof:name":"Polyar",
    "wof:placetype":"venue"
},
  "geometry": {"coordinates":[-74.12151,40.916102],"type":"Point"}
}