{
  "type": "Feature",
  "properties": {
    "iso:country":"US",
    "sg:address":"224 Washington Ave",
    "sg:city":"Little Ferry",
    "sg:classifiers":[
        {
            "category":"Personal",
            "subcategory":"Barber",
            "type":"Services"
        }
    ],
    "sg:phone":"+1 201 641 1776",
    "sg:postcode":"07643",
    "sg:province":"NJ",
    "sg:tags":[
        "shop"
    ],
    "wof:name":"Juliano's Hair Styling",
    "wof:placetype":"venue"
},
  "geometry": {"coordinates":[-74.04119900000001,40.845798],"type":"Point"}
}