{
  "type": "Feature",
  "properties": {
    "iso:country":"US",
    "sg:address":"18 Osprey Ln",
    "sg:city":"Oceanport",
    "sg:classifiers":[
        {
            "category":"Farming",
            "subcategory":"Farm & Veterinary Services",
            "type":"Manufacturing & Wholesale Goods"
        }
    ],
    "sg:phone":"+1 732 542 5572",
    "sg:postcode":"07757",
    "sg:province":"NJ",
    "sg:tags":[
        "water",
        "crop",
        "supply"
    ],
    "wof:name":"BCM Irrigation",
    "wof:placetype":"venue"
},
  "geometry": {"coordinates":[-74.031854,40.307363],"type":"Point"}
}