{
  "type": "Feature",
  "properties": {
    "iso:country":"US",
    "sg:address":"50 Hillside Ave",
    "sg:city":"Midland Park",
    "sg:classifiers":[
        {
            "category":"Professional",
            "type":"Services"
        }
    ],
    "sg:phone":"+1   ",
    "sg:postcode":"07432",
    "sg:province":"NJ",
    "wof:name":"Cleary Associates",
    "wof:placetype":"venue"
},
  "geometry": {"coordinates":[-74.148844,40.98947],"type":"Point"}
}