{
  "type": "Feature",
  "properties": {
    "addr:full":"35 Greentree Dr Burlington NJ 08016",
    "addr:housenumber":"35",
    "addr:postcode":"08016",
    "addr:street":"Greentree Dr",
    "iso:country":"US",
    "sg:address":"35 Greentree Dr",
    "sg:city":"Burlington",
    "sg:classifiers":[
        {
            "category":"Manufacturing",
            "subcategory":"Soap",
            "type":"Manufacturing & Wholesale Goods"
        }
    ],
    "sg:phone":"+1 609 387 5287",
    "sg:postcode":"08016",
    "sg:province":"NJ",
    "sg:tags":[
        "product",
        "industrial",
        "laundry",
        "cleaning",
        "mfg"
    ],
    "wof:name":"Berg Laboratories",
    "wof:placetype":"venue"
},
  "geometry": {"coordinates":[-74.853635,40.051546],"type":"Point"}
}