{
  "type": "Feature",
  "properties": {
    "iso:country":"US",
    "sg:address":"2605 Shore Rd",
    "sg:city":"Northfield",
    "sg:classifiers":[
        {
            "category":"Shopping",
            "subcategory":"Department Store",
            "type":"Retail Goods"
        }
    ],
    "sg:phone":"+1   ",
    "sg:postcode":"08225",
    "sg:province":"NJ",
    "sg:tags":[
        "discount"
    ],
    "wof:name":"Coastal Designs",
    "wof:placetype":"venue"
},
  "geometry": {"coordinates":[-74.559212,39.359008],"type":"Point"}
}