{
  "type": "Feature",
  "properties": {
    "iso:country":"US",
    "sg:address":"40 Jersey Pl",
    "sg:city":"Hackensack",
    "sg:classifiers":[
        {
            "category":"Building & Trades",
            "subcategory":"Landscaping Services",
            "type":"Services"
        }
    ],
    "sg:phone":"+1 201 498 0644",
    "sg:postcode":"07601",
    "sg:province":"NJ",
    "wof:name":"Landscapeworks",
    "wof:placetype":"venue"
},
  "geometry": {"coordinates":[-74.054253,40.874242],"type":"Point"}
}