{
  "type": "Feature",
  "properties": {
    "addr:full":"719 Division St Trenton NJ 08611",
    "addr:housenumber":"719",
    "addr:postcode":"08611",
    "addr:street":"Division St",
    "iso:country":"US",
    "sg:address":"719 Division St",
    "sg:city":"Trenton",
    "sg:classifiers":[
        {
            "category":"Professional",
            "type":"Services"
        }
    ],
    "sg:phone":"+1   ",
    "sg:postcode":"08611",
    "sg:province":"NJ",
    "wof:name":"Fonceca Contracting Inc",
    "wof:placetype":"venue"
},
  "geometry": {"coordinates":[-74.743825,40.207554],"type":"Point"}
}