{
  "type": "Feature",
  "properties": {
    "addr:full":"81 Dorsa Ave Livingston NJ 07039",
    "addr:housenumber":"81",
    "addr:postcode":"07039",
    "addr:street":"Dorsa Ave",
    "iso:country":"US",
    "sg:address":"81 Dorsa Ave",
    "sg:city":"Livingston",
    "sg:classifiers":[
        {
            "category":"Building & Trades",
            "subcategory":"Cleaning & Sanitation",
            "type":"Services"
        }
    ],
    "sg:phone":"+1 973 740 0032",
    "sg:postcode":"07039",
    "sg:province":"NJ",
    "sg:tags":[
        "janitor"
    ],
    "wof:name":"Tri-Maintenance Contractors",
    "wof:placetype":"venue"
},
  "geometry": {"coordinates":[-74.34360700000001,40.810054],"type":"Point"}
}