{
  "type": "Feature",
  "properties": {
    "iso:country":"US",
    "sg:address":"168 Mercer St",
    "sg:city":"Trenton",
    "sg:classifiers":[
        {
            "category":"Travel",
            "subcategory":"Travel Agent",
            "type":"Entertainment"
        }
    ],
    "sg:phone":"+1 609 987 0577",
    "sg:postcode":"08611",
    "sg:province":"NJ",
    "sg:tags":[
        "agency"
    ],
    "wof:name":"Empress Travel",
    "wof:placetype":"venue"
},
  "geometry": {"coordinates":[-74.76088300000001,40.217596],"type":"Point"}
}