{
  "type": "Feature",
  "properties": {
    "iso:country":"US",
    "sg:address":"18 Green St",
    "sg:city":"Newark",
    "sg:classifiers":[
        {
            "category":"Professional",
            "subcategory":"Detective & Security Services",
            "type":"Services"
        }
    ],
    "sg:phone":"+1   ",
    "sg:postcode":"07102",
    "sg:province":"NJ",
    "sg:tags":[
        "car"
    ],
    "wof:name":"Prince Detective Agency Inc",
    "wof:placetype":"venue"
},
  "geometry": {"coordinates":[-74.173962,40.732391],"type":"Point"}
}