{
  "type": "Feature",
  "properties": {
    "addr:full":"490 East Rd Belford NJ 07718",
    "addr:housenumber":"490",
    "addr:postcode":"07718",
    "addr:street":"East Rd",
    "iso:country":"US",
    "sg:address":"490 East Rd",
    "sg:city":"Belford",
    "sg:classifiers":[
        {
            "category":"Manufacturing",
            "subcategory":"Wood Products",
            "type":"Manufacturing & Wholesale Goods"
        }
    ],
    "sg:phone":"+1 732 787 3324",
    "sg:postcode":"07718",
    "sg:province":"NJ",
    "sg:tags":[
        "mfg"
    ],
    "wof:name":"Louis Pallets",
    "wof:placetype":"venue"
},
  "geometry": {"coordinates":[-74.086416,40.412186],"type":"Point"}
}