{
  "type": "Feature",
  "properties": {
    "iso:country":"US",
    "sg:address":"1348 McCarter Hwy",
    "sg:city":"Newark",
    "sg:classifiers":[
        {
            "category":"Travel",
            "subcategory":"Hotels & Motels",
            "type":"Entertainment"
        }
    ],
    "sg:phone":"+1 973 481 5200",
    "sg:postcode":"07104",
    "sg:province":"NJ",
    "wof:name":"Comfort Suites",
    "wof:placetype":"venue"
},
  "geometry": {"coordinates":[-74.16729100000001,40.754444],"type":"Point"}
}