{
  "type": "Feature",
  "properties": {
    "addr:full":"897 Tanglewood Rd Toms River NJ 08753",
    "addr:housenumber":"897",
    "addr:postcode":"08753",
    "addr:street":"Tanglewood Rd",
    "iso:country":"US",
    "sg:address":"897 Tanglewood Rd",
    "sg:city":"Toms River",
    "sg:classifiers":[
        {
            "category":"Building & Trades",
            "subcategory":"Electrical",
            "type":"Services"
        }
    ],
    "sg:phone":"+1 732 929 4444",
    "sg:postcode":"08753",
    "sg:province":"NJ",
    "sg:tags":[
        "electrical",
        "electric",
        "contractor"
    ],
    "wof:name":"Cove Electrice",
    "wof:placetype":"venue"
},
  "geometry": {"coordinates":[-74.159987,39.968048],"type":"Point"}
}