{
  "type": "Feature",
  "properties": {
    "addr:full":"16 Shawns Way Lumberton NJ 08048",
    "addr:housenumber":"16",
    "addr:postcode":"08048",
    "addr:street":"Shawns Way",
    "iso:country":"US",
    "sg:address":"16 Shawns Way",
    "sg:city":"Lumberton",
    "sg:classifiers":[
        {
            "category":"Professional",
            "subcategory":"Management & Consulting",
            "type":"Services"
        }
    ],
    "sg:phone":"+1 609 267 5031",
    "sg:postcode":"08048",
    "sg:province":"NJ",
    "wof:name":"Caribou Aviation Management LL",
    "wof:placetype":"venue"
},
  "geometry": {"coordinates":[-74.767174,39.95907],"type":"Point"}
}