{
  "type": "Feature",
  "properties": {
    "addr:full":"312 Berlin Rd N Clementon NJ 08021",
    "addr:housenumber":"312",
    "addr:postcode":"08021",
    "addr:street":"Berlin Rd N",
    "iso:country":"US",
    "sg:address":"312 Berlin Rd N",
    "sg:city":"Clementon",
    "sg:classifiers":[
        {
            "category":"Real Estate",
            "subcategory":"Real Estate Agent",
            "type":"Services"
        }
    ],
    "sg:phone":"+1 856 435 8222",
    "sg:postcode":"08021",
    "sg:province":"NJ",
    "wof:name":"Cite Properties",
    "wof:placetype":"venue"
},
  "geometry": {"coordinates":[-74.99184099999999,39.827399],"type":"Point"}
}