{
  "type": "Feature",
  "properties": {
    "iso:country":"US",
    "sg:address":"17 Hilliard Ave",
    "sg:city":"Edgewater",
    "sg:classifiers":[
        {
            "category":"Professional",
            "type":"Services"
        }
    ],
    "sg:phone":"+1   ",
    "sg:postcode":"07020",
    "sg:province":"NJ",
    "wof:name":"Kim P & Jeon Jungah",
    "wof:placetype":"venue"
},
  "geometry": {"coordinates":[-73.97415599999999,40.826093],"type":"Point"}
}