{
  "type": "Feature",
  "properties": {
    "iso:country":"US",
    "sg:address":"35 Muhammad Ali Ave",
    "sg:city":"Newark",
    "sg:classifiers":[
        {
            "category":"Shopping",
            "subcategory":"Clothing, Apparel, & Fashions",
            "type":"Retail Goods"
        }
    ],
    "sg:phone":"+1   ",
    "sg:postcode":"07108",
    "sg:province":"NJ",
    "wof:name":"Magnifique En Vogue",
    "wof:placetype":"venue"
},
  "geometry": {"coordinates":[-74.186311,40.725768],"type":"Point"}
}