{
  "type": "Feature",
  "properties": {
    "addr:full":"1138 Main Ave Clifton NJ 07011",
    "addr:housenumber":"1138",
    "addr:postcode":"07011",
    "addr:street":"Main Ave",
    "iso:country":"US",
    "sg:address":"1138 Main Ave",
    "sg:city":"Clifton",
    "sg:classifiers":[
        {
            "category":"Retail",
            "subcategory":"Portrait Studio",
            "type":"Services"
        },
        {
            "category":"Shopping",
            "subcategory":"Pharmacy",
            "type":"Retail Goods"
        }
    ],
    "sg:phone":"+1 973 773 1998",
    "sg:postcode":"07011",
    "sg:province":"NJ",
    "sg:tags":[
        "photography",
        "drugstore",
        "store"
    ],
    "sg:website":"www.walgreens.com",
    "wof:name":"Walgreens Drug Store",
    "wof:placetype":"venue"
},
  "geometry": {"coordinates":[-74.139,40.874901],"type":"Point"}
}