{
  "type": "Feature",
  "properties": {
    "iso:country":"US",
    "sg:address":"12 Bunker Hill Rd",
    "sg:city":"Freehold",
    "sg:classifiers":[
        {
            "category":"Organizations",
            "subcategory":"Religious Organization",
            "type":"Services"
        }
    ],
    "sg:phone":"+1   ",
    "sg:postcode":"07728",
    "sg:province":"NJ",
    "wof:name":"Christian W Revealed",
    "wof:placetype":"venue"
},
  "geometry": {"coordinates":[-74.29034900000001,40.288735],"type":"Point"}
}