{
  "type": "Feature",
  "properties": {
    "addr:full":"270 Spring Valley Rd Paramus NJ 07652",
    "addr:housenumber":"270",
    "addr:postcode":"07652",
    "addr:street":"Spring Valley Rd",
    "iso:country":"US",
    "sg:address":"270 Spring Valley Rd",
    "sg:city":"Paramus",
    "sg:classifiers":[
        {
            "category":"Health Services",
            "subcategory":"Doctor",
            "type":"Services"
        }
    ],
    "sg:phone":"+1 201 576 0088",
    "sg:postcode":"07652",
    "sg:province":"NJ",
    "sg:tags":[
        "physician",
        "surgeon"
    ],
    "sg:website":"www.forensic-psych-assoc.com",
    "wof:name":"Forensic Psychiatric Assoc",
    "wof:placetype":"venue"
},
  "geometry": {"coordinates":[-74.053134,40.934042],"type":"Point"}
}