{
  "type": "Feature",
  "properties": {
    "addr:full":"600 Warwick Rd Haddonfield NJ 08033",
    "addr:housenumber":"600",
    "addr:postcode":"08033",
    "addr:street":"Warwick Rd",
    "iso:country":"US",
    "sg:address":"600 Warwick Rd",
    "sg:city":"Haddonfield",
    "sg:classifiers":[
        {
            "category":"Recreation",
            "type":"Entertainment"
        }
    ],
    "sg:phone":"+1 856 783 1133",
    "sg:postcode":"08033",
    "sg:province":"NJ",
    "sg:tags":[
        "martial",
        "arts",
        "instruction"
    ],
    "wof:name":"Black Belt Karate Academy",
    "wof:placetype":"venue"
},
  "geometry": {"coordinates":[-75.037735,39.884623],"type":"Point"}
}