{
  "type": "Feature",
  "properties": {
    "addr:full":"1015 Bergenline Ave Union City NJ 07087",
    "addr:housenumber":"1015",
    "addr:postcode":"07087",
    "addr:street":"Bergenline Ave",
    "iso:country":"US",
    "sg:address":"1015 Bergenline Ave",
    "sg:city":"Union City",
    "sg:classifiers":[
        {
            "category":"Wholesale",
            "subcategory":"Meat",
            "type":"Manufacturing & Wholesale Goods"
        }
    ],
    "sg:phone":"+1 201 866 9090",
    "sg:postcode":"07087",
    "sg:province":"NJ",
    "sg:tags":[
        "shop"
    ],
    "wof:name":"Superior Foods Distributors",
    "wof:placetype":"venue"
},
  "geometry": {"coordinates":[-74.03847500000001,40.758373],"type":"Point"}
}