{
  "type": "Feature",
  "properties": {
    "addr:full":"109 Broughton Ave Bloomfield NJ 07003",
    "addr:housenumber":"109",
    "addr:postcode":"07003",
    "addr:street":"Broughton Ave",
    "iso:country":"US",
    "sg:address":"109 Broughton Ave",
    "sg:city":"Bloomfield",
    "sg:classifiers":[
        {
            "category":"Retail",
            "subcategory":"Repair Shop",
            "type":"Services"
        }
    ],
    "sg:phone":"+1 973 854 5661",
    "sg:postcode":"07003",
    "sg:province":"NJ",
    "sg:tags":[
        "lock",
        "key",
        "locksmith"
    ],
    "wof:name":"A 24-7 Emergency A Locksmith",
    "wof:placetype":"venue"
},
  "geometry": {"coordinates":[-74.18712600000001,40.81433],"type":"Point"}
}