{
  "type": "Feature",
  "properties": {
    "addr:full":"171 Ridgedale Ave Florham Park NJ 07932",
    "addr:housenumber":"171",
    "addr:postcode":"07932",
    "addr:street":"Ridgedale Ave",
    "iso:country":"US",
    "sg:address":"171 Ridgedale Ave",
    "sg:city":"Florham Park",
    "sg:classifiers":[
        {
            "category":"Professional",
            "subcategory":"Lawyer & Legal Services",
            "type":"Services"
        }
    ],
    "sg:phone":"+1 973 443 0658",
    "sg:postcode":"07932",
    "sg:province":"NJ",
    "wof:name":"Gregory S Grasso Esq",
    "wof:placetype":"venue"
},
  "geometry": {"coordinates":[-74.392027,40.786576],"type":"Point"}
}