{
  "type": "Feature",
  "properties": {
    "iso:country":"US",
    "sg:address":"1212 Thomas Ave",
    "sg:city":"North Brunswick",
    "sg:classifiers":[
        {
            "category":"Professional",
            "type":"Services"
        }
    ],
    "sg:phone":"+1   ",
    "sg:postcode":"08902",
    "sg:province":"NJ",
    "wof:name":"Joan A Walton",
    "wof:placetype":"venue"
},
  "geometry": {"coordinates":[-74.521845,40.440744],"type":"Point"}
}