{
  "type": "Feature",
  "properties": {
    "iso:country":"US",
    "sg:address":"412 Park Ave",
    "sg:city":"Paterson",
    "sg:classifiers":[
        {
            "category":"Health Services",
            "subcategory":"Doctor",
            "type":"Services"
        }
    ],
    "sg:phone":"+1   ",
    "sg:postcode":"07504",
    "sg:province":"NJ",
    "sg:tags":[
        "medical"
    ],
    "wof:name":"Park Ave Medical Assoc",
    "wof:placetype":"venue"
},
  "geometry": {"coordinates":[-74.147829,40.913944],"type":"Point"}
}