{
  "type": "Feature",
  "properties": {
    "iso:country":"US",
    "sg:address":"3265 S Black Horse Pike",
    "sg:city":"Williamstown",
    "sg:classifiers":[
        {
            "category":"Home & Garden",
            "subcategory":"Building Materials",
            "type":"Retail Goods"
        },
        {
            "category":"Building & Trades",
            "subcategory":"Construction",
            "type":"Services"
        }
    ],
    "sg:phone":"+1 856 629 7188",
    "sg:postcode":"08094",
    "sg:province":"NJ",
    "sg:tags":[
        "plate",
        "window",
        "contractor",
        "glass",
        "auto"
    ],
    "wof:name":"Williamstown Auto Glass Co",
    "wof:placetype":"venue"
},
  "geometry": {"coordinates":[-74.932964,39.635824],"type":"Point"}
}