{
  "type": "Feature",
  "properties": {
    "addr:full":"36 Hornerstown Rd Cream Ridge NJ 08514",
    "addr:housenumber":"36",
    "addr:postcode":"08514",
    "addr:street":"Hornerstown Rd",
    "iso:country":"US",
    "sg:address":"36 Hornerstown Rd",
    "sg:city":"Cream Ridge",
    "sg:classifiers":[
        {
            "category":"Building & Trades",
            "subcategory":"Electrical",
            "type":"Services"
        }
    ],
    "sg:phone":"+1 609 921 3238",
    "sg:postcode":"08514",
    "sg:province":"NJ",
    "sg:tags":[
        "electric",
        "contractor"
    ],
    "wof:name":"E Tech Electrical Contractor",
    "wof:placetype":"venue"
},
  "geometry": {"coordinates":[-74.505529,40.099952],"type":"Point"}
}