{
  "type": "Feature",
  "properties": {
    "addr:full":"30 Two Bridges Rd Fairfield NJ 07004",
    "addr:housenumber":"30",
    "addr:postcode":"07004",
    "addr:street":"Two Bridges Rd",
    "iso:country":"US",
    "sg:address":"30 Two Bridges Rd",
    "sg:city":"Fairfield",
    "sg:classifiers":[
        {
            "category":"Banks & Credit Unions",
            "subcategory":"Investment Brokerage",
            "type":"Services"
        }
    ],
    "sg:phone":"+1 973 276 9580",
    "sg:postcode":"07004",
    "sg:province":"NJ",
    "sg:tags":[
        "consultant",
        "financing"
    ],
    "wof:name":"Birchwood Capital Advisers",
    "wof:placetype":"venue"
},
  "geometry": {"coordinates":[-74.27382,40.891808],"type":"Point"}
}