{
  "type": "Feature",
  "properties": {
    "iso:country":"US",
    "sg:address":"267 Millard Ave",
    "sg:city":"Hillside",
    "sg:classifiers":[
        {
            "category":"Organizations",
            "subcategory":"Religious Organization",
            "type":"Services"
        }
    ],
    "sg:phone":"+1 908 355 1013",
    "sg:postcode":"07205",
    "sg:province":"NJ",
    "sg:tags":[
        "clergy"
    ],
    "wof:name":"R Gamble",
    "wof:placetype":"venue"
},
  "geometry": {"coordinates":[-74.233817,40.696128],"type":"Point"}
}