{
  "type": "Feature",
  "properties": {
    "addr:full":"2333 Morris Ave Ste B18 Union NJ 07083",
    "addr:housenumber":"2333",
    "addr:postcode":"07083",
    "addr:street":"Morris Ave Ste B18",
    "iso:country":"US",
    "sg:address":"2333 Morris Ave Ste B18",
    "sg:city":"Union",
    "sg:classifiers":[
        {
            "category":"Health Services",
            "subcategory":"Doctor",
            "type":"Services"
        }
    ],
    "sg:phone":"+1 908 810 8551",
    "sg:postcode":"07083",
    "sg:province":"NJ",
    "sg:website":"www.trinitypediatrics.com",
    "wof:name":"Trinity Pediatrics Llc",
    "wof:placetype":"venue"
},
  "geometry": {"coordinates":[-74.28368,40.700018],"type":"Point"}
}