{
  "type": "Feature",
  "properties": {
    "iso:country":"US",
    "sg:address":"2 Chase Pl",
    "sg:city":"Montville",
    "sg:classifiers":[
        {
            "category":"Organizations",
            "subcategory":"Community Association",
            "type":"Services"
        }
    ],
    "sg:phone":"+1   ",
    "sg:postcode":"07009",
    "sg:province":"NJ",
    "wof:name":"Montville Chase Condo Assn",
    "wof:placetype":"venue"
},
  "geometry": {"coordinates":[-74.232607,40.872667],"type":"Point"}
}