{
  "type": "Feature",
  "properties": {
    "iso:country":"US",
    "sg:address":"14 Main St",
    "sg:city":"Millburn",
    "sg:classifiers":[
        {
            "category":"Building & Trades",
            "subcategory":"Construction",
            "type":"Services"
        }
    ],
    "sg:phone":"+1 973 218 9004",
    "sg:postcode":"07041",
    "sg:province":"NJ",
    "sg:tags":[
        "contractor",
        "carpentry"
    ],
    "sg:website":"www.eckitchens.com",
    "wof:name":"European Country Kitchen",
    "wof:placetype":"venue"
},
  "geometry": {"coordinates":[-74.30777,40.725369],"type":"Point"}
}