{
  "type": "Feature",
  "properties": {
    "addr:full":"771 S Black Horse Pike Blackwood NJ 08012",
    "addr:housenumber":"771",
    "addr:postcode":"08012",
    "addr:street":"S Black Horse Pike",
    "iso:country":"US",
    "sg:address":"771 S Black Horse Pike",
    "sg:city":"Blackwood",
    "sg:classifiers":[
        {
            "category":"Food & Beverages",
            "subcategory":"Specialty",
            "type":"Retail Goods"
        }
    ],
    "sg:phone":"+1   ",
    "sg:postcode":"08012",
    "sg:province":"NJ",
    "sg:tags":[
        "health",
        "store"
    ],
    "wof:name":"Nutri Sun",
    "wof:placetype":"venue"
},
  "geometry": {"coordinates":[-75.059349,39.790631],"type":"Point"}
}