{
  "type": "Feature",
  "properties": {
    "addr:full":"280 Western Blvd Bayville NJ 08721",
    "addr:housenumber":"280",
    "addr:postcode":"08721",
    "addr:street":"Western Blvd",
    "iso:country":"US",
    "sg:address":"280 Western Blvd",
    "sg:city":"Bayville",
    "sg:classifiers":[
        {
            "category":"Manufacturing",
            "subcategory":"Toys & Sporting Goods",
            "type":"Manufacturing & Wholesale Goods"
        }
    ],
    "sg:phone":"+1 732 269 1479",
    "sg:postcode":"08721",
    "sg:province":"NJ",
    "sg:tags":[
        "craft"
    ],
    "wof:name":"Moore Crafts",
    "wof:placetype":"venue"
},
  "geometry": {"coordinates":[-74.19370499999999,39.903584],"type":"Point"}
}