{
  "type": "Feature",
  "properties": {
    "addr:full":"11 Bergen Hill Rd Rockaway NJ 07866",
    "addr:housenumber":"11",
    "addr:postcode":"07866",
    "addr:street":"Bergen Hill Rd",
    "iso:country":"US",
    "sg:address":"11 Bergen Hill Rd",
    "sg:city":"Rockaway",
    "sg:classifiers":[
        {
            "category":"Manufacturing",
            "subcategory":"Apparel",
            "type":"Manufacturing & Wholesale Goods"
        }
    ],
    "sg:phone":"+1 973 586 1639",
    "sg:postcode":"07866",
    "sg:province":"NJ",
    "sg:tags":[
        "textile",
        "product",
        "mfg",
        "sporting",
        "fabricated"
    ],
    "wof:name":"Everything Equine",
    "wof:placetype":"venue"
},
  "geometry": {"coordinates":[-74.497246,40.951714],"type":"Point"}
}