{
  "type": "Feature",
  "properties": {
    "addr:full":"1 Linwood Dr Mullica Hill NJ 08062",
    "addr:housenumber":"1",
    "addr:postcode":"08062",
    "addr:street":"Linwood Dr",
    "iso:country":"US",
    "sg:address":"1 Linwood Dr",
    "sg:city":"Mullica Hill",
    "sg:classifiers":[
        {
            "category":"Building & Trades",
            "subcategory":"Construction",
            "type":"Services"
        }
    ],
    "sg:phone":"+1 609 860 7881",
    "sg:postcode":"08062",
    "sg:province":"NJ",
    "sg:tags":[
        "home",
        "builder"
    ],
    "wof:name":"Centex Homes",
    "wof:placetype":"venue"
},
  "geometry": {"coordinates":[-75.22161199999999,39.671242],"type":"Point"}
}