{
  "type": "Feature",
  "properties": {
    "addr:full":"8 Hopkinson Ct Hightstown NJ 08520",
    "addr:housenumber":"8",
    "addr:postcode":"08520",
    "addr:street":"Hopkinson Ct",
    "iso:country":"US",
    "sg:address":"8 Hopkinson Ct",
    "sg:city":"Hightstown",
    "sg:classifiers":[
        {
            "category":"Arts & Performance",
            "subcategory":"Theater",
            "type":"Entertainment"
        }
    ],
    "sg:phone":"+1 609 443 0300",
    "sg:postcode":"08520",
    "sg:province":"NJ",
    "sg:tags":[
        "group"
    ],
    "wof:name":"Magic By Westcraft Inc",
    "wof:placetype":"venue"
},
  "geometry": {"coordinates":[-74.524176,40.283591],"type":"Point"}
}