{
  "type": "Feature",
  "properties": {
    "iso:country":"US",
    "sg:address":"80 Morgan Pl",
    "sg:city":"East Brunswick",
    "sg:classifiers":[
        {
            "category":"Building & Trades",
            "subcategory":"Construction",
            "type":"Services"
        }
    ],
    "sg:phone":"+1 732 238 7827",
    "sg:postcode":"08816",
    "sg:province":"NJ",
    "sg:tags":[
        "hanging",
        "contractor"
    ],
    "wof:name":"Randy Ingram Painting",
    "wof:placetype":"venue"
},
  "geometry": {"coordinates":[-74.41540000000001,40.40718],"type":"Point"}
}