{
  "type": "Feature",
  "properties": {
    "addr:full":"39 Lakeview Pl Verona NJ 07044",
    "addr:housenumber":"39",
    "addr:postcode":"07044",
    "addr:street":"Lakeview Pl",
    "iso:country":"US",
    "sg:address":"39 Lakeview Pl",
    "sg:city":"Verona",
    "sg:classifiers":[
        {
            "category":"Shopping",
            "subcategory":"Gifts & Souvenirs",
            "type":"Retail Goods"
        }
    ],
    "sg:phone":"+1   ",
    "sg:postcode":"07044",
    "sg:province":"NJ",
    "wof:name":"Smilemaker Gifts LLC",
    "wof:placetype":"venue"
},
  "geometry": {"coordinates":[-74.24335000000001,40.829925],"type":"Point"}
}