{
  "type": "Feature",
  "properties": {
    "iso:country":"US",
    "sg:address":"2310 US Hwy 206",
    "sg:city":"Southampton",
    "sg:classifiers":[
        {
            "category":"Wholesale",
            "subcategory":"Farm Supplies",
            "type":"Manufacturing & Wholesale Goods"
        }
    ],
    "sg:phone":"+1 609 265 1695",
    "sg:postcode":"08088",
    "sg:province":"NJ",
    "sg:tags":[
        "alfalfa",
        "for",
        "crop",
        "preparation",
        "hay",
        "market"
    ],
    "wof:name":"Ro-Ann Farm",
    "wof:placetype":"venue"
},
  "geometry": {"coordinates":[-74.737515,39.965209],"type":"Point"}
}