{
  "type": "Feature",
  "properties": {
    "iso:country":"US",
    "sg:address":"340 Pompton Ave",
    "sg:city":"Verona",
    "sg:classifiers":[
        {
            "category":"Shopping",
            "subcategory":"Clothing, Apparel, & Fashions",
            "type":"Retail Goods"
        }
    ],
    "sg:phone":"+1 973 239 3311",
    "sg:postcode":"07044",
    "sg:province":"NJ",
    "sg:tags":[
        "accessory"
    ],
    "wof:name":"Mandee Shop",
    "wof:placetype":"venue"
},
  "geometry": {"coordinates":[-74.226997,40.834301],"type":"Point"}
}