{
  "type": "Feature",
  "properties": {
    "addr:full":"140 Poplar St Williamstown NJ 08094",
    "addr:housenumber":"140",
    "addr:postcode":"08094",
    "addr:street":"Poplar St",
    "iso:country":"US",
    "sg:address":"140 Poplar St",
    "sg:city":"Williamstown",
    "sg:classifiers":[
        {
            "category":"Real Estate",
            "subcategory":"Real Estate Agent",
            "type":"Services"
        },
        {
            "category":"Professional",
            "subcategory":"Business Services",
            "type":"Services"
        }
    ],
    "sg:phone":"+1 856 629 9700",
    "sg:postcode":"08094",
    "sg:province":"NJ",
    "sg:tags":[
        "appraiser"
    ],
    "wof:name":"Dixon & Assoc Appraisers",
    "wof:placetype":"venue"
},
  "geometry": {"coordinates":[-74.991429,39.685616],"type":"Point"}
}