{
  "type": "Feature",
  "properties": {
    "addr:full":"803 Perkins Ln Beverly NJ 08010",
    "addr:housenumber":"803",
    "addr:postcode":"08010",
    "addr:street":"Perkins Ln",
    "iso:country":"US",
    "sg:address":"803 Perkins Ln",
    "sg:city":"Beverly",
    "sg:classifiers":[
        {
            "category":"Professional",
            "subcategory":"Management & Consulting",
            "type":"Services"
        }
    ],
    "sg:phone":"+1   ",
    "sg:postcode":"08010",
    "sg:province":"NJ",
    "sg:tags":[
        "business"
    ],
    "wof:name":"Dinda & Associates Inc",
    "wof:placetype":"venue"
},
  "geometry": {"coordinates":[-74.930313,40.052534],"type":"Point"}
}