{
  "type": "Feature",
  "properties": {
    "iso:country":"US",
    "sg:address":"81 Van Ness Ter",
    "sg:city":"Maplewood",
    "sg:classifiers":[
        {
            "category":"Building & Trades",
            "subcategory":"Construction",
            "type":"Services"
        }
    ],
    "sg:phone":"+1 973 313 1950",
    "sg:postcode":"07040",
    "sg:province":"NJ",
    "sg:tags":[
        "house"
    ],
    "wof:name":"Handyman Home Services",
    "wof:placetype":"venue"
},
  "geometry": {"coordinates":[-74.257632,40.714713],"type":"Point"}
}