{
  "type": "Feature",
  "properties": {
    "iso:country":"US",
    "sg:address":"45 David Dr",
    "sg:city":"Augusta",
    "sg:classifiers":[
        {
            "category":"Building & Trades",
            "subcategory":"Electrical",
            "type":"Services"
        }
    ],
    "sg:phone":"+1 973 875 2039",
    "sg:postcode":"07822",
    "sg:province":"NJ",
    "sg:tags":[
        "electrical",
        "contractor"
    ],
    "wof:name":"Maciag Electric",
    "wof:placetype":"venue"
},
  "geometry": {"coordinates":[-74.67941999999999,41.152577],"type":"Point"}
}