{
  "type": "Feature",
  "properties": {
    "addr:full":"1985 S Spring Rd Vineland NJ 08361",
    "addr:housenumber":"1985",
    "addr:postcode":"08361",
    "addr:street":"S Spring Rd",
    "iso:country":"US",
    "sg:address":"1985 S Spring Rd",
    "sg:city":"Vineland",
    "sg:classifiers":[
        {
            "category":"Food & Beverages",
            "subcategory":"Liquor & Beverages",
            "type":"Retail Goods"
        }
    ],
    "sg:phone":"+1   ",
    "sg:postcode":"08361",
    "sg:province":"NJ",
    "sg:tags":[
        "alcoholic"
    ],
    "wof:name":"Ingrahams Liquor Store",
    "wof:placetype":"venue"
},
  "geometry": {"coordinates":[-74.990769,39.454159],"type":"Point"}
}