{
  "type": "Feature",
  "properties": {
    "addr:full":"83 Godwin Ave Ridgewood NJ 07450",
    "addr:housenumber":"83",
    "addr:postcode":"07450",
    "addr:street":"Godwin Ave",
    "iso:country":"US",
    "sg:address":"83 Godwin Ave",
    "sg:city":"Ridgewood",
    "sg:classifiers":[
        {
            "category":"Food & Beverages",
            "subcategory":"Groceries & Convenience Stores",
            "type":"Retail Goods"
        }
    ],
    "sg:phone":"+1 201 447 5015",
    "sg:postcode":"07450",
    "sg:province":"NJ",
    "sg:tags":[
        "market"
    ],
    "wof:name":"Quick Stop Food Mart",
    "wof:placetype":"venue"
},
  "geometry": {"coordinates":[-74.122794,40.979243],"type":"Point"}
}