{
  "type": "Feature",
  "properties": {
    "iso:country":"US",
    "sg:address":"810 Raymond Blvd",
    "sg:city":"Newark",
    "sg:classifiers":[
        {
            "category":"Shopping",
            "subcategory":"Computers & Home Electronics",
            "type":"Retail Goods"
        }
    ],
    "sg:phone":"+1 973 622 6101",
    "sg:postcode":"07105",
    "sg:province":"NJ",
    "sg:tags":[
        "equipment",
        "dealer"
    ],
    "wof:name":"Computer Intelligence Inc",
    "wof:placetype":"venue"
},
  "geometry": {"coordinates":[-74.154005,40.732687],"type":"Point"}
}