{
  "type": "Feature",
  "properties": {
    "addr:full":"828 8th St Union Beach NJ 07735",
    "addr:housenumber":"828",
    "addr:postcode":"07735",
    "addr:street":"8Th St",
    "iso:country":"US",
    "sg:address":"828 8th St",
    "sg:city":"Union Beach",
    "sg:classifiers":[
        {
            "category":"Freight",
            "type":"Transportation"
        }
    ],
    "sg:phone":"+1 732 642 2324",
    "sg:postcode":"07735",
    "sg:province":"NJ",
    "sg:tags":[
        "trucking"
    ],
    "wof:name":"DTA Trucking",
    "wof:placetype":"venue"
},
  "geometry": {"coordinates":[-74.175121,40.447296],"type":"Point"}
}