{
  "type": "Feature",
  "properties": {
    "addr:full":"247 S Washington Ave Bergenfield NJ 07621",
    "addr:housenumber":"247",
    "addr:postcode":"07621",
    "addr:street":"S Washington Ave",
    "iso:country":"US",
    "sg:address":"247 S Washington Ave",
    "sg:city":"Bergenfield",
    "sg:classifiers":[
        {
            "category":"Autos & Motor Vehicles",
            "subcategory":"Automobile Sales",
            "type":"Retail Goods"
        },
        {
            "category":"Retail",
            "subcategory":"Auto Repair",
            "type":"Services"
        }
    ],
    "sg:phone":"+1 201 501 0499",
    "sg:postcode":"07621",
    "sg:province":"NJ",
    "sg:tags":[
        "automotive",
        "dealer",
        "car",
        "sales"
    ],
    "wof:name":"Swedish Connection Sales",
    "wof:placetype":"venue"
},
  "geometry": {"coordinates":[-73.996866,40.920176],"type":"Point"}
}