{
  "type": "Feature",
  "properties": {
    "iso:country":"US",
    "sg:address":"145 Broad St",
    "sg:city":"Matawan",
    "sg:classifiers":[
        {
            "category":"Personal",
            "type":"Services"
        }
    ],
    "sg:phone":"+1   ",
    "sg:postcode":"07747",
    "sg:province":"NJ",
    "sg:tags":[
        "statistics",
        "registrar",
        "vital"
    ],
    "wof:name":"Matawan Rgstrar Vtal Sttistics",
    "wof:placetype":"venue"
},
  "geometry": {"coordinates":[-74.229685,40.412149],"type":"Point"}
}