{
  "type": "Feature",
  "properties": {
    "addr:full":"1815 Greenwood Lake Tpke Hewitt NJ 07421",
    "addr:housenumber":"1815",
    "addr:postcode":"07421",
    "addr:street":"Greenwood Lake Tpke",
    "iso:country":"US",
    "sg:address":"1815 Greenwood Lake Tpke",
    "sg:city":"Hewitt",
    "sg:classifiers":[
        {
            "category":"Freight",
            "type":"Transportation"
        }
    ],
    "sg:phone":"+1 973 728 2419",
    "sg:postcode":"07421",
    "sg:province":"NJ",
    "sg:tags":[
        "commercial",
        "storage"
    ],
    "wof:name":"Mc Cann's Mini Warehouses LTD",
    "wof:placetype":"venue"
},
  "geometry": {"coordinates":[-74.34465299999999,41.139768],"type":"Point"}
}