{
  "type": "Feature",
  "properties": {
    "addr:full":"11 Broadacre Dr Mount Laurel NJ 08054",
    "addr:housenumber":"11",
    "addr:postcode":"08054",
    "addr:street":"Broadacre Dr",
    "iso:country":"US",
    "sg:address":"11 Broadacre Dr",
    "sg:city":"Mount Laurel",
    "sg:classifiers":[
        {
            "category":"Utilities",
            "subcategory":"Telephone",
            "type":"Services"
        }
    ],
    "sg:phone":"+1 856 222 0725",
    "sg:postcode":"08054",
    "sg:province":"NJ",
    "sg:tags":[
        "development",
        "co",
        "database",
        "marketing",
        "analytical",
        "software"
    ],
    "wof:name":"Direct Logic Solutions Inc",
    "wof:placetype":"venue"
},
  "geometry": {"coordinates":[-74.89988700000001,39.924181],"type":"Point"}
}