{
  "type": "Feature",
  "properties": {
    "addr:full":"30 Vail Pl Rahway NJ 07065",
    "addr:housenumber":"30",
    "addr:postcode":"07065",
    "addr:street":"Vail Pl",
    "iso:country":"US",
    "sg:address":"30 Vail Pl",
    "sg:city":"Rahway",
    "sg:classifiers":[
        {
            "category":"Professional",
            "subcategory":"Lawyer & Legal Services",
            "type":"Services"
        }
    ],
    "sg:phone":"+1 732 388 0281",
    "sg:postcode":"07065",
    "sg:province":"NJ",
    "wof:name":"Little W F Jr Lawyer",
    "wof:placetype":"venue"
},
  "geometry": {"coordinates":[-74.27619900000001,40.6064],"type":"Point"}
}