{
  "type": "Feature",
  "properties": {
    "addr:full":"527 Lafayette Ave Hawthorne NJ 07506",
    "addr:housenumber":"527",
    "addr:postcode":"07506",
    "addr:street":"Lafayette Ave",
    "iso:country":"US",
    "sg:address":"527 Lafayette Ave",
    "sg:city":"Hawthorne",
    "sg:classifiers":[
        {
            "category":"Shopping",
            "type":"Retail Goods"
        }
    ],
    "sg:phone":"+1 973 427 4200",
    "sg:postcode":"07506",
    "sg:province":"NJ",
    "sg:tags":[
        "spa",
        "hot",
        "tub"
    ],
    "wof:name":"Prisco Better Quality Spa",
    "wof:placetype":"venue"
},
  "geometry": {"coordinates":[-74.155518,40.958255],"type":"Point"}
}