{
  "type": "Feature",
  "properties": {
    "iso:country":"US",
    "sg:address":"30 W 2nd St",
    "sg:city":"Moorestown",
    "sg:classifiers":[
        {
            "category":"Restaurant",
            "type":"Food & Drink"
        }
    ],
    "sg:phone":"+1   ",
    "sg:postcode":"08057",
    "sg:province":"NJ",
    "wof:name":"Bob Barbecue",
    "wof:placetype":"venue"
},
  "geometry": {"coordinates":[-74.948643,39.964386],"type":"Point"}
}