{
  "type": "Feature",
  "properties": {
    "iso:country":"US",
    "sg:address":"17 W Washington Ave",
    "sg:city":"Washington",
    "sg:classifiers":[
        {
            "category":"Health Services",
            "subcategory":"Health Practitioner",
            "type":"Services"
        }
    ],
    "sg:phone":"+1 908 689 4120",
    "sg:postcode":"07882",
    "sg:province":"NJ",
    "wof:name":"A Center For Change",
    "wof:placetype":"venue"
},
  "geometry": {"coordinates":[-74.979865,40.758261],"type":"Point"}
}