{
  "type": "Feature",
  "properties": {
    "iso:country":"US",
    "sg:address":"2 Meadowlands Plz",
    "sg:city":"East Rutherford",
    "sg:classifiers":[
        {
            "category":"Restaurant",
            "type":"Food & Drink"
        }
    ],
    "sg:phone":"+1 201 507 2701",
    "sg:postcode":"07073",
    "sg:province":"NJ",
    "wof:name":"Terrace Bistro Restaurant",
    "wof:placetype":"venue"
},
  "geometry": {"coordinates":[-74.077003,40.802898],"type":"Point"}
}