{
  "type": "Feature",
  "properties": {
    "iso:country":"US",
    "sg:address":"131 Prospect St",
    "sg:city":"Nutley",
    "sg:classifiers":[
        {
            "category":"Professional",
            "subcategory":"Management & Consulting",
            "type":"Services"
        }
    ],
    "sg:phone":"+1   ",
    "sg:postcode":"07110",
    "sg:province":"NJ",
    "sg:tags":[
        "business"
    ],
    "wof:name":"Mendoza Consultancy",
    "wof:placetype":"venue"
},
  "geometry": {"coordinates":[-74.16932199999999,40.810632],"type":"Point"}
}