{
  "type": "Feature",
  "properties": {
    "addr:full":"3009 Plaza Dr Woodbridge NJ 07095",
    "addr:housenumber":"3009",
    "addr:postcode":"07095",
    "addr:street":"Plaza Dr",
    "iso:country":"US",
    "sg:address":"3009 Plaza Dr",
    "sg:city":"Woodbridge",
    "sg:classifiers":[
        {
            "category":"Professional",
            "type":"Services"
        }
    ],
    "sg:phone":"+1   ",
    "sg:postcode":"07095",
    "sg:province":"NJ",
    "wof:name":"Gill Data Systems",
    "wof:placetype":"venue"
},
  "geometry": {"coordinates":[-74.29834200000001,40.548421],"type":"Point"}
}