{
  "type": "Feature",
  "properties": {
    "iso:country":"US",
    "sg:address":"6 Bruce St",
    "sg:city":"Old Bridge",
    "sg:classifiers":[
        {
            "category":"Real Estate",
            "subcategory":"Architect",
            "type":"Services"
        }
    ],
    "sg:phone":"+1   ",
    "sg:postcode":"08857",
    "sg:province":"NJ",
    "sg:tags":[
        "architectural"
    ],
    "wof:name":"Blair Design Group Inc",
    "wof:placetype":"venue"
},
  "geometry": {"coordinates":[-74.31083,40.391872],"type":"Point"}
}