{
  "type": "Feature",
  "properties": {
    "addr:full":"8 Oates Dr Farmingdale NJ 07727",
    "addr:housenumber":"8",
    "addr:postcode":"07727",
    "addr:street":"Oates Dr",
    "iso:country":"US",
    "sg:address":"8 Oates Dr",
    "sg:city":"Farmingdale",
    "sg:classifiers":[
        {
            "category":"Building & Trades",
            "subcategory":"Construction",
            "type":"Services"
        }
    ],
    "sg:phone":"+1 732 919 1177",
    "sg:postcode":"07727",
    "sg:province":"NJ",
    "sg:tags":[
        "resurfacing",
        "laying",
        "refinishing",
        "floor"
    ],
    "wof:name":"Alvarado Floors",
    "wof:placetype":"venue"
},
  "geometry": {"coordinates":[-74.201678,40.191722],"type":"Point"}
}