{
  "type": "Feature",
  "properties": {
    "addr:full":"7 Etheridge Pl Park Ridge NJ 07656",
    "addr:housenumber":"7",
    "addr:postcode":"07656",
    "addr:street":"Etheridge Pl",
    "iso:country":"US",
    "sg:address":"7 Etheridge Pl",
    "sg:city":"Park Ridge",
    "sg:classifiers":[
        {
            "category":"Manufacturing",
            "subcategory":"Glass & Minerals",
            "type":"Manufacturing & Wholesale Goods"
        }
    ],
    "sg:phone":"+1 201 573 9150",
    "sg:postcode":"07656",
    "sg:province":"NJ",
    "sg:tags":[
        "product",
        "nonmetallic",
        "mfg"
    ],
    "wof:name":"Sculpturesque Inc",
    "wof:placetype":"venue"
},
  "geometry": {"coordinates":[-74.03913,41.040523],"type":"Point"}
}