{
  "type": "Feature",
  "properties": {
    "addr:full":"108 Shire Ln Swedesboro NJ 08085",
    "addr:housenumber":"108",
    "addr:postcode":"08085",
    "addr:street":"Shire Ln",
    "iso:country":"US",
    "sg:address":"108 Shire Ln",
    "sg:city":"Swedesboro",
    "sg:classifiers":[
        {
            "category":"Professional",
            "subcategory":"Business Services",
            "type":"Services"
        }
    ],
    "sg:phone":"+1 856 241 1255",
    "sg:postcode":"08085",
    "sg:province":"NJ",
    "sg:tags":[
        "fund",
        "promotion",
        "raising"
    ],
    "wof:name":"Obie Graphics",
    "wof:placetype":"venue"
},
  "geometry": {"coordinates":[-75.34542500000001,39.755616],"type":"Point"}
}