{
  "type": "Feature",
  "properties": {
    "addr:full":"608 Nottingham Way Flemington NJ 08822",
    "addr:housenumber":"608",
    "addr:postcode":"08822",
    "addr:street":"Nottingham Way",
    "iso:country":"US",
    "sg:address":"608 Nottingham Way",
    "sg:city":"Flemington",
    "sg:classifiers":[
        {
            "category":"Building & Trades",
            "subcategory":"Construction",
            "type":"Services"
        }
    ],
    "sg:phone":"+1 908 782 2728",
    "sg:postcode":"08822",
    "sg:province":"NJ",
    "sg:tags":[
        "carpentry"
    ],
    "wof:name":"Gilio Construction",
    "wof:placetype":"venue"
},
  "geometry": {"coordinates":[-74.84966900000001,40.499924],"type":"Point"}
}