{
  "type": "Feature",
  "properties": {
    "addr:full":"10 Cape May Ave Dorothy NJ 08317",
    "addr:housenumber":"10",
    "addr:postcode":"08317",
    "addr:street":"Cape May Ave",
    "iso:country":"US",
    "sg:address":"10 Cape May Ave",
    "sg:city":"Dorothy",
    "sg:classifiers":[
        {
            "category":"Retail",
            "subcategory":"Animal Services",
            "type":"Services"
        }
    ],
    "sg:phone":"+1 609 652 7100",
    "sg:postcode":"08317",
    "sg:province":"NJ",
    "sg:tags":[
        "pet",
        "grooming",
        "washing"
    ],
    "wof:name":"Happy Tails",
    "wof:placetype":"venue"
},
  "geometry": {"coordinates":[-74.841427,39.416421],"type":"Point"}
}