{
  "type": "Feature",
  "properties": {
    "iso:country":"US",
    "sg:address":"328 9th St",
    "sg:city":"Jersey City",
    "sg:classifiers":[
        {
            "category":"Health Services",
            "subcategory":"Clinic",
            "type":"Services"
        }
    ],
    "sg:phone":"+1 201 716 8400",
    "sg:postcode":"07302",
    "sg:province":"NJ",
    "sg:tags":[
        "specialty",
        "outpatient"
    ],
    "wof:name":"Wellness Center At Hamilton PA",
    "wof:placetype":"venue"
},
  "geometry": {"coordinates":[-74.04983,40.728857],"type":"Point"}
}