{
  "type": "Feature",
  "properties": {
    "iso:country":"US",
    "sg:address":"1 Stephanie Ln",
    "sg:city":"Trenton",
    "sg:classifiers":[
        {
            "category":"Restaurant",
            "type":"Food & Drink"
        }
    ],
    "sg:phone":"+1 609 585 1641",
    "sg:postcode":"08691",
    "sg:province":"NJ",
    "sg:tags":[
        "parlor",
        "ice",
        "cream"
    ],
    "wof:name":"Kramerica Inc",
    "wof:placetype":"venue"
},
  "geometry": {"coordinates":[-74.648651,40.170232],"type":"Point"}
}