{
  "type": "Feature",
  "properties": {
    "iso:country":"US",
    "sg:address":"304 High St",
    "sg:city":"Burlington",
    "sg:classifiers":[
        {
            "category":"Professional",
            "subcategory":"Business Services",
            "type":"Services"
        }
    ],
    "sg:phone":"+1 609 239 0990",
    "sg:postcode":"08016",
    "sg:province":"NJ",
    "sg:tags":[
        "interior",
        "consultant",
        "design",
        "decorator"
    ],
    "wof:name":"Bits N Pieces Home Decor",
    "wof:placetype":"venue"
},
  "geometry": {"coordinates":[-74.858633,40.078778],"type":"Point"}
}