{
  "type": "Feature",
  "properties": {
    "iso:country":"US",
    "sg:address":"769 Main Ave",
    "sg:city":"Passaic",
    "sg:classifiers":[
        {
            "category":"Food & Beverages",
            "subcategory":"Meat & Fish",
            "type":"Retail Goods"
        }
    ],
    "sg:phone":"+1   ",
    "sg:postcode":"07055",
    "sg:province":"NJ",
    "wof:name":"Key West Fish Market",
    "wof:placetype":"venue"
},
  "geometry": {"coordinates":[-74.128005,40.86286],"type":"Point"}
}