{
  "type": "Feature",
  "properties": {
    "addr:full":"93 Heller Pkwy Newark NJ 07104",
    "addr:housenumber":"93",
    "addr:postcode":"07104",
    "addr:street":"Heller Pkwy",
    "iso:country":"US",
    "sg:address":"93 Heller Pkwy",
    "sg:city":"Newark",
    "sg:classifiers":[
        {
            "category":"Communications",
            "subcategory":"Film & Video Production",
            "type":"Services"
        }
    ],
    "sg:phone":"+1 973 482 0525",
    "sg:postcode":"07104",
    "sg:province":"NJ",
    "sg:tags":[
        "audio"
    ],
    "wof:name":"In Video Productions",
    "wof:placetype":"venue"
},
  "geometry": {"coordinates":[-74.167858,40.776067],"type":"Point"}
}