{
  "type": "Feature",
  "properties": {
    "addr:full":"1 S Locust Lake Rd Blairstown NJ 07825",
    "addr:housenumber":"1",
    "addr:postcode":"07825",
    "addr:street":"S Locust Lake Rd",
    "iso:country":"US",
    "sg:address":"1 S Locust Lake Rd",
    "sg:city":"Blairstown",
    "sg:classifiers":[
        {
            "category":"Travel",
            "subcategory":"Hotels & Motels",
            "type":"Entertainment"
        }
    ],
    "sg:phone":"+1 908 459 5398",
    "sg:postcode":"07825",
    "sg:province":"NJ",
    "sg:tags":[
        "breakfast",
        "accommodation",
        "bed"
    ],
    "wof:name":"Blue Eyed Dog Bed & Breakfast",
    "wof:placetype":"venue"
},
  "geometry": {"coordinates":[-74.993081,40.924068],"type":"Point"}
}