{
  "type": "Feature",
  "properties": {
    "addr:full":"11 Cypress Ave Verona NJ 07044",
    "addr:housenumber":"11",
    "addr:postcode":"07044",
    "addr:street":"Cypress Ave",
    "iso:country":"US",
    "sg:address":"11 Cypress Ave",
    "sg:city":"Verona",
    "sg:classifiers":[
        {
            "category":"Building & Trades",
            "subcategory":"Pest Control",
            "type":"Services"
        }
    ],
    "sg:phone":"+1 973 571 0057",
    "sg:postcode":"07044",
    "sg:province":"NJ",
    "wof:name":"West Essex Termite & Pest Co",
    "wof:placetype":"venue"
},
  "geometry": {"coordinates":[-74.242099,40.839399],"type":"Point"}
}