{
  "type": "Feature",
  "properties": {
    "iso:country":"US",
    "sg:address":"60 Walnut Ave",
    "sg:city":"Clark",
    "sg:classifiers":[
        {
            "category":"Manufacturing",
            "subcategory":"Chemicals & Compounds",
            "type":"Manufacturing & Wholesale Goods"
        }
    ],
    "sg:phone":"+1 732 815 7798",
    "sg:postcode":"07066",
    "sg:province":"NJ",
    "sg:tags":[
        "carbon",
        "black"
    ],
    "wof:name":"Degussa Corp",
    "wof:placetype":"venue"
},
  "geometry": {"coordinates":[-74.30159399999999,40.629485],"type":"Point"}
}