{
  "type": "Feature",
  "properties": {
    "addr:full":"328 Spruce Mill Ln Scotch Plains NJ 07076",
    "addr:housenumber":"328",
    "addr:postcode":"07076",
    "addr:street":"Spruce Mill Ln",
    "iso:country":"US",
    "sg:address":"328 Spruce Mill Ln",
    "sg:city":"Scotch Plains",
    "sg:classifiers":[
        {
            "category":"Professional",
            "subcategory":"Management & Consulting",
            "type":"Services"
        }
    ],
    "sg:phone":"+1   ",
    "sg:postcode":"07076",
    "sg:province":"NJ",
    "sg:tags":[
        "business"
    ],
    "wof:name":"S F Malaker Dr",
    "wof:placetype":"venue"
},
  "geometry": {"coordinates":[-74.332268,40.62584],"type":"Point"}
}