{
  "type": "Feature",
  "properties": {
    "addr:full":"119 Avenel St Avenel NJ 07001",
    "addr:housenumber":"119",
    "addr:postcode":"07001",
    "addr:street":"Avenel St",
    "iso:country":"US",
    "sg:address":"119 Avenel St",
    "sg:city":"Avenel",
    "sg:classifiers":[
        {
            "category":"Food & Beverages",
            "subcategory":"Groceries & Convenience Stores",
            "type":"Retail Goods"
        }
    ],
    "sg:phone":"+1 732 750 4010",
    "sg:postcode":"07001",
    "sg:province":"NJ",
    "wof:name":"Avenel News & Food Store",
    "wof:placetype":"venue"
},
  "geometry": {"coordinates":[-74.274902,40.576302],"type":"Point"}
}