{
  "type": "Feature",
  "properties": {
    "iso:country":"US",
    "sg:address":"1513 Main St",
    "sg:city":"Rahway",
    "sg:classifiers":[
        {
            "category":"Real Estate",
            "subcategory":"Real Estate Agent",
            "type":"Services"
        }
    ],
    "sg:phone":"+1   ",
    "sg:postcode":"07065",
    "sg:province":"NJ",
    "wof:name":"Interamerican Real Estate Inc",
    "wof:placetype":"venue"
},
  "geometry": {"coordinates":[-74.273658,40.607706],"type":"Point"}
}