{
  "type": "Feature",
  "properties": {
    "iso:country":"US",
    "sg:address":"200 Gates Rd",
    "sg:city":"Little Ferry",
    "sg:classifiers":[
        {
            "category":"Shopping",
            "subcategory":"Bicycles & Sporting Goods",
            "type":"Retail Goods"
        }
    ],
    "sg:phone":"+1 201 440 8703",
    "sg:postcode":"07643",
    "sg:province":"NJ",
    "wof:name":"Wellzher Corp",
    "wof:placetype":"venue"
},
  "geometry": {"coordinates":[-74.03355000000001,40.844856],"type":"Point"}
}