{
  "type": "Feature",
  "properties": {
    "iso:country":"US",
    "sg:address":"6209 Bergenline Pl",
    "sg:city":"West New York",
    "sg:classifiers":[
        {
            "category":"Personal",
            "subcategory":"Beauty Salon",
            "type":"Services"
        }
    ],
    "sg:phone":"+1 201 869 1149",
    "sg:postcode":"07093",
    "sg:province":"NJ",
    "sg:tags":[
        "shop"
    ],
    "wof:name":"Lazara I Perez",
    "wof:placetype":"venue"
},
  "geometry": {"coordinates":[-74.014197,40.791819],"type":"Point"}
}