{
  "type": "Feature",
  "properties": {
    "iso:country":"US",
    "sg:address":"725 Slocum Ave",
    "sg:city":"Ridgefield",
    "sg:classifiers":[
        {
            "category":"Social Services",
            "type":"Services"
        }
    ],
    "sg:phone":"+1 201 941 0963",
    "sg:postcode":"07657",
    "sg:province":"NJ",
    "wof:name":"Ridgefeld Snior Ctzen Ntrtonal",
    "wof:placetype":"venue"
},
  "geometry": {"coordinates":[-73.998277,40.834835],"type":"Point"}
}