{
  "type": "Feature",
  "properties": {
    "iso:country":"US",
    "sg:address":"65 Halstead St",
    "sg:city":"Kearny",
    "sg:classifiers":[
        {
            "category":"Communications",
            "subcategory":"Film & Video Production",
            "type":"Services"
        }
    ],
    "sg:phone":"+1   ",
    "sg:postcode":"07032",
    "sg:province":"NJ",
    "sg:tags":[
        "motion"
    ],
    "wof:name":"Mike Enoches",
    "wof:placetype":"venue"
},
  "geometry": {"coordinates":[-74.15127699999999,40.763225],"type":"Point"}
}