{
  "type": "Feature",
  "properties": {
    "addr:full":"831 State Rte 10 Whippany NJ 07981",
    "addr:housenumber":"831",
    "addr:postcode":"07981",
    "addr:street":"State Rte 10",
    "iso:country":"US",
    "sg:address":"831 State Rte 10",
    "sg:city":"Whippany",
    "sg:classifiers":[
        {
            "category":"Restaurant",
            "type":"Food & Drink"
        }
    ],
    "sg:phone":"+1 973 884 1439",
    "sg:postcode":"07981",
    "sg:province":"NJ",
    "wof:name":"Lotus House",
    "wof:placetype":"venue"
},
  "geometry": {"coordinates":[-74.42433800000001,40.826482],"type":"Point"}
}