{
  "type": "Feature",
  "properties": {
    "addr:full":"24 Cedar Rd White House Station NJ 08889",
    "addr:housenumber":"24",
    "addr:postcode":"08889",
    "addr:street":"Cedar Rd",
    "iso:country":"US",
    "sg:address":"24 Cedar Rd",
    "sg:city":"White House Station",
    "sg:classifiers":[
        {
            "category":"Professional",
            "type":"Services"
        }
    ],
    "sg:phone":"+1   ",
    "sg:postcode":"08889",
    "sg:province":"NJ",
    "wof:name":"Knowware Corporation",
    "wof:placetype":"venue"
},
  "geometry": {"coordinates":[-74.746433,40.642499],"type":"Point"}
}