{
  "type": "Feature",
  "properties": {
    "iso:country":"US",
    "sg:address":"5 Morningside Dr",
    "sg:city":"Trenton",
    "sg:classifiers":[
        {
            "category":"Shopping",
            "subcategory":"Clothing, Apparel, & Fashions",
            "type":"Retail Goods"
        }
    ],
    "sg:phone":"+1   ",
    "sg:postcode":"08618",
    "sg:province":"NJ",
    "sg:tags":[
        "millinery"
    ],
    "wof:name":"Sandras Hat Box",
    "wof:placetype":"venue"
},
  "geometry": {"coordinates":[-74.80921600000001,40.239386],"type":"Point"}
}