{
  "type": "Feature",
  "properties": {
    "addr:full":"256 Wanaque Ave Pompton Lakes NJ 07442",
    "addr:housenumber":"256",
    "addr:postcode":"07442",
    "addr:street":"Wanaque Ave",
    "iso:country":"US",
    "sg:address":"256 Wanaque Ave",
    "sg:city":"Pompton Lakes",
    "sg:classifiers":[
        {
            "category":"Travel",
            "subcategory":"Travel Agent",
            "type":"Entertainment"
        }
    ],
    "sg:phone":"+1 973 835 7721",
    "sg:postcode":"07442",
    "sg:province":"NJ",
    "sg:tags":[
        "tours",
        "promoter"
    ],
    "wof:name":"Group Tours Inc",
    "wof:placetype":"venue"
},
  "geometry": {"coordinates":[-74.29146299999999,41.003152],"type":"Point"}
}