{
  "type": "Feature",
  "properties": {
    "iso:country":"US",
    "sg:address":"578 Oak Glen Rd",
    "sg:city":"Howell",
    "sg:classifiers":[
        {
            "category":"Wholesale",
            "subcategory":"Plants",
            "type":"Manufacturing & Wholesale Goods"
        }
    ],
    "sg:phone":"+1 732 364 1884",
    "sg:postcode":"07731",
    "sg:province":"NJ",
    "sg:tags":[
        "supply"
    ],
    "wof:name":"East Creek Greenhouses Inc",
    "wof:placetype":"venue"
},
  "geometry": {"coordinates":[-74.187348,40.130893],"type":"Point"}
}