{
  "type": "Feature",
  "properties": {
    "iso:country":"US",
    "sg:address":"375 Douglas Rd",
    "sg:city":"Roselle",
    "sg:classifiers":[
        {
            "category":"Building & Trades",
            "subcategory":"Pest Control",
            "type":"Services"
        }
    ],
    "sg:phone":"+1 908 241 3021",
    "sg:postcode":"07203",
    "sg:province":"NJ",
    "wof:name":"Bee-Gone Pest Control",
    "wof:placetype":"venue"
},
  "geometry": {"coordinates":[-74.267945,40.641843],"type":"Point"}
}