{
  "type": "Feature",
  "properties": {
    "iso:country":"US",
    "sg:address":"1361 Nixon Dr",
    "sg:city":"Moorestown",
    "sg:classifiers":[
        {
            "category":"Restaurant",
            "type":"Food & Drink"
        }
    ],
    "sg:menulink":"http://www.allmenus.com/nj/moorestown/10281-don-pablos/menu/",
    "sg:phone":"+1 856 642 6160",
    "sg:postcode":"08057",
    "sg:province":"NJ",
    "sg:tags":[
        "sandwich",
        "mexican",
        "salad",
        "soup",
        "american",
        "wrap",
        "tex-mex"
    ],
    "wof:name":"Don Pablo's",
    "wof:placetype":"venue"
},
  "geometry": {"coordinates":[-74.963995,39.948731],"type":"Point"}
}