{
  "type": "Feature",
  "properties": {
    "iso:country":"US",
    "sg:address":"635 Ramsey Ave",
    "sg:city":"Hillside",
    "sg:classifiers":[
        {
            "category":"Manufacturing",
            "subcategory":"Food",
            "type":"Manufacturing & Wholesale Goods"
        }
    ],
    "sg:phone":"+1 908 964 0477",
    "sg:postcode":"07205",
    "sg:province":"NJ",
    "sg:tags":[
        "preparation"
    ],
    "sg:website":"www.oasisfoodsco.com",
    "wof:name":"Oasis Co",
    "wof:placetype":"venue"
},
  "geometry": {"coordinates":[-74.23844800000001,40.704564],"type":"Point"}
}