{
  "type": "Feature",
  "properties": {
    "addr:full":"2903 Bayland Dr Ocean City NJ 08226",
    "addr:housenumber":"2903",
    "addr:postcode":"08226",
    "addr:street":"Bayland Dr",
    "iso:country":"US",
    "sg:address":"2903 Bayland Dr",
    "sg:city":"Ocean City",
    "sg:classifiers":[
        {
            "category":"Wholesale",
            "subcategory":"Machinery & Supplies",
            "type":"Manufacturing & Wholesale Goods"
        }
    ],
    "sg:phone":"+1 609 391 0773",
    "sg:postcode":"08226",
    "sg:province":"NJ",
    "sg:tags":[
        "distributor",
        "industrial"
    ],
    "wof:name":"Valley Forge Machine",
    "wof:placetype":"venue"
},
  "geometry": {"coordinates":[-74.608648,39.259761],"type":"Point"}
}