{
  "type": "Feature",
  "properties": {
    "addr:full":"964 Cordes Ct Oradell NJ 07649",
    "addr:housenumber":"964",
    "addr:postcode":"07649",
    "addr:street":"Cordes Ct",
    "iso:country":"US",
    "sg:address":"964 Cordes Ct",
    "sg:city":"Oradell",
    "sg:classifiers":[
        {
            "category":"Insurance",
            "subcategory":"Insurance Agent",
            "type":"Services"
        }
    ],
    "sg:phone":"+1 201 967 0145",
    "sg:postcode":"07649",
    "sg:province":"NJ",
    "wof:name":"Prudential Insurance Co",
    "wof:placetype":"venue"
},
  "geometry": {"coordinates":[-74.046254,40.957295],"type":"Point"}
}