{
  "type": "Feature",
  "properties": {
    "iso:country":"US",
    "sg:address":"31 Market St",
    "sg:city":"Passaic",
    "sg:classifiers":[
        {
            "category":"Retail",
            "subcategory":"Repair Shop",
            "type":"Services"
        }
    ],
    "sg:phone":"+1 973 365 9635",
    "sg:postcode":"07055",
    "sg:province":"NJ",
    "sg:tags":[
        "upholsterer"
    ],
    "wof:name":"Tony Plastic Covers",
    "wof:placetype":"venue"
},
  "geometry": {"coordinates":[-74.116429,40.863371],"type":"Point"}
}