{
  "type": "Feature",
  "properties": {
    "iso:country":"US",
    "sg:address":"184 Kinderkamack Rd",
    "sg:city":"Park Ridge",
    "sg:classifiers":[
        {
            "category":"Food & Beverages",
            "subcategory":"Bakery",
            "type":"Retail Goods"
        }
    ],
    "sg:phone":"+1   ",
    "sg:postcode":"07656",
    "sg:province":"NJ",
    "wof:name":"Dunkin Donuts",
    "wof:placetype":"venue"
},
  "geometry": {"coordinates":[-74.03219300000001,41.035412],"type":"Point"}
}