{
  "type": "Feature",
  "properties": {
    "addr:full":"448 Whitehead Rd Trenton NJ 08619",
    "addr:housenumber":"448",
    "addr:postcode":"08619",
    "addr:street":"Whitehead Rd",
    "iso:country":"US",
    "sg:address":"448 Whitehead Rd",
    "sg:city":"Trenton",
    "sg:classifiers":[
        {
            "category":"Professional",
            "subcategory":"Computer Services",
            "type":"Services"
        }
    ],
    "sg:phone":"+1 609 584 8484",
    "sg:postcode":"08619",
    "sg:province":"NJ",
    "sg:website":"www.cvt1.com",
    "wof:name":"Computer Vision Technology",
    "wof:placetype":"venue"
},
  "geometry": {"coordinates":[-74.72626200000001,40.244388],"type":"Point"}
}