{
  "type": "Feature",
  "properties": {
    "iso:country":"US",
    "sg:address":"842 Edgewater Ave",
    "sg:city":"Ridgefield",
    "sg:classifiers":[
        {
            "category":"Building & Trades",
            "subcategory":"Construction",
            "type":"Services"
        }
    ],
    "sg:phone":"+1 201 943 3833",
    "sg:postcode":"07657",
    "sg:province":"NJ",
    "sg:tags":[
        "contractor"
    ],
    "wof:name":"Jtt Development Llc",
    "wof:placetype":"venue"
},
  "geometry": {"coordinates":[-74.005402,40.8311],"type":"Point"}
}