{
  "type": "Feature",
  "properties": {
    "iso:country":"US",
    "sg:address":"2168 Camilla Ave",
    "sg:city":"Atco",
    "sg:classifiers":[
        {
            "category":"Personal",
            "type":"Services"
        }
    ],
    "sg:phone":"+1 856 768 6735",
    "sg:postcode":"08004",
    "sg:province":"NJ",
    "sg:tags":[
        "towing"
    ],
    "wof:name":"Marks Towing",
    "wof:placetype":"venue"
},
  "geometry": {"coordinates":[-74.889999,39.7733],"type":"Point"}
}