{
  "type": "Feature",
  "properties": {
    "addr:full":"549 Redwood Ave Haddonfield NJ 08033",
    "addr:housenumber":"549",
    "addr:postcode":"08033",
    "addr:street":"Redwood Ave",
    "iso:country":"US",
    "sg:address":"549 Redwood Ave",
    "sg:city":"Haddonfield",
    "sg:classifiers":[
        {
            "category":"Professional",
            "subcategory":"Detective & Security Services",
            "type":"Services"
        },
        {
            "category":"Professional",
            "subcategory":"Lawyer & Legal Services",
            "type":"Services"
        }
    ],
    "sg:phone":"+1 856 428 2379",
    "sg:postcode":"08033",
    "sg:province":"NJ",
    "sg:tags":[
        "process",
        "server",
        "private",
        "investigator"
    ],
    "sg:website":"http://www.selectivesubpoena.com",
    "wof:name":"Striped Bull",
    "wof:placetype":"venue"
},
  "geometry": {"coordinates":[-75.034116,39.909915],"type":"Point"}
}