{
  "type": "Feature",
  "properties": {
    "addr:full":"502 Hasbrouck Ave Hasbrouck Heights NJ 07604",
    "addr:housenumber":"502",
    "addr:postcode":"07604",
    "addr:street":"Hasbrouck Ave",
    "iso:country":"US",
    "sg:address":"502 Hasbrouck Ave",
    "sg:city":"Hasbrouck Heights",
    "sg:classifiers":[
        {
            "category":"Autos & Motor Vehicles",
            "subcategory":"Fuel & Gas Station",
            "type":"Retail Goods"
        }
    ],
    "sg:phone":"+1   ",
    "sg:postcode":"07604",
    "sg:province":"NJ",
    "sg:tags":[
        "station",
        "gasoline"
    ],
    "wof:name":"Citgo",
    "wof:placetype":"venue"
},
  "geometry": {"coordinates":[-74.064984,40.86622],"type":"Point"}
}