{
  "type": "Feature",
  "properties": {
    "addr:full":"251 Forest Ave Paramus NJ 07652",
    "addr:housenumber":"251",
    "addr:postcode":"07652",
    "addr:street":"Forest Ave",
    "iso:country":"US",
    "sg:address":"251 Forest Ave",
    "sg:city":"Paramus",
    "sg:classifiers":[
        {
            "category":"Building & Trades",
            "subcategory":"Construction",
            "type":"Services"
        }
    ],
    "sg:phone":"+1 201 261 5708",
    "sg:postcode":"07652",
    "sg:province":"NJ",
    "sg:tags":[
        "roofing",
        "contractor"
    ],
    "wof:name":"S R Roofing",
    "wof:placetype":"venue"
},
  "geometry": {"coordinates":[-74.05126,40.934073],"type":"Point"}
}