{
  "type": "Feature",
  "properties": {
    "iso:country":"US",
    "sg:address":"209 Shunpike Rd",
    "sg:city":"Cape May Court House",
    "sg:classifiers":[
        {
            "category":"Building & Trades",
            "subcategory":"Construction",
            "type":"Services"
        }
    ],
    "sg:phone":"+1 609 465 2242",
    "sg:postcode":"08210",
    "sg:province":"NJ",
    "sg:tags":[
        "house"
    ],
    "wof:name":"DAndrea Construction",
    "wof:placetype":"venue"
},
  "geometry": {"coordinates":[-74.832367,39.08191],"type":"Point"}
}