{
  "type": "Feature",
  "properties": {
    "iso:country":"US",
    "sg:address":"28 W River Styx Rd",
    "sg:city":"Hopatcong",
    "sg:classifiers":[
        {
            "category":"Wholesale",
            "subcategory":"Groceries",
            "type":"Manufacturing & Wholesale Goods"
        }
    ],
    "sg:phone":"+1 973 398 0370",
    "sg:postcode":"07843",
    "sg:province":"NJ",
    "sg:tags":[
        "tea",
        "coffee"
    ],
    "wof:name":"Lake End Coffee Co",
    "wof:placetype":"venue"
},
  "geometry": {"coordinates":[-74.655824,40.943213],"type":"Point"}
}