{
  "type": "Feature",
  "properties": {
    "addr:full":"404 Washington St Orange NJ 07050",
    "addr:housenumber":"404",
    "addr:postcode":"07050",
    "addr:street":"Washington St",
    "iso:country":"US",
    "sg:address":"404 Washington St",
    "sg:city":"Orange",
    "sg:classifiers":[
        {
            "category":"Restaurant",
            "type":"Food & Drink"
        }
    ],
    "sg:phone":"+1 973 678 3907",
    "sg:postcode":"07050",
    "sg:province":"NJ",
    "sg:tags":[
        "chinese"
    ],
    "wof:name":"China Garden Restaurant",
    "wof:placetype":"venue"
},
  "geometry": {"coordinates":[-74.225675,40.783473],"type":"Point"}
}