{
  "type": "Feature",
  "properties": {
    "addr:full":"219 S Burnt Mill Rd Voorhees NJ 08043",
    "addr:housenumber":"219",
    "addr:postcode":"08043",
    "addr:street":"S Burnt Mill Rd",
    "iso:country":"US",
    "sg:address":"219 S Burnt Mill Rd",
    "sg:city":"Voorhees",
    "sg:classifiers":[
        {
            "category":"Shopping",
            "subcategory":"Hobbies, Toys, & Games",
            "type":"Retail Goods"
        }
    ],
    "sg:phone":"+1 856 616 1735",
    "sg:postcode":"08043",
    "sg:province":"NJ",
    "sg:tags":[
        "craft",
        "supply"
    ],
    "wof:name":"Scrapbook Station",
    "wof:placetype":"venue"
},
  "geometry": {"coordinates":[-75.007299,39.855083],"type":"Point"}
}