{
  "type": "Feature",
  "properties": {
    "addr:full":"1045 Main Ave Clifton NJ 07011",
    "addr:housenumber":"1045",
    "addr:postcode":"07011",
    "addr:street":"Main Ave",
    "iso:country":"US",
    "sg:address":"1045 Main Ave",
    "sg:city":"Clifton",
    "sg:classifiers":[
        {
            "category":"Autos & Motor Vehicles",
            "subcategory":"Fuel & Gas Station",
            "type":"Retail Goods"
        }
    ],
    "sg:phone":"+1 973 472 7653",
    "sg:postcode":"07011",
    "sg:province":"NJ",
    "wof:name":"Farino's Passaic-Clifton Service Center",
    "wof:placetype":"venue"
},
  "geometry": {"coordinates":[-74.13690200000001,40.872299],"type":"Point"}
}