{
  "type": "Feature",
  "properties": {
    "addr:full":"7501 Ocean Ave Wildwood NJ 08260",
    "addr:housenumber":"7501",
    "addr:postcode":"08260",
    "addr:street":"Ocean Ave",
    "iso:country":"US",
    "sg:address":"7501 Ocean Ave",
    "sg:city":"Wildwood",
    "sg:classifiers":[
        {
            "category":"Travel",
            "subcategory":"Hotels & Motels",
            "type":"Entertainment"
        }
    ],
    "sg:phone":"+1 609 522 7712",
    "sg:postcode":"08260",
    "sg:province":"NJ",
    "wof:name":"Saratoga Inn",
    "wof:placetype":"venue"
},
  "geometry": {"coordinates":[-74.837402,38.967701],"type":"Point"}
}