{
  "type": "Feature",
  "properties": {
    "addr:full":"288 Egg Harbor Rd Sewell NJ 08080",
    "addr:housenumber":"288",
    "addr:postcode":"08080",
    "addr:street":"Egg Harbor Rd",
    "iso:country":"US",
    "sg:address":"288 Egg Harbor Rd",
    "sg:city":"Sewell",
    "sg:classifiers":[
        {
            "category":"Shopping",
            "subcategory":"Pharmacy",
            "type":"Retail Goods"
        }
    ],
    "sg:phone":"+1   ",
    "sg:postcode":"08080",
    "sg:province":"NJ",
    "sg:tags":[
        "prescription",
        "proprietary",
        "drug"
    ],
    "wof:name":"CVS",
    "wof:placetype":"venue"
},
  "geometry": {"coordinates":[-75.08646,39.766053],"type":"Point"}
}