{
  "type": "Feature",
  "properties": {
    "iso:country":"US",
    "sg:address":"487 RT-27",
    "sg:city":"Iselin",
    "sg:classifiers":[
        {
            "category":"Restaurant",
            "type":"Food & Drink"
        }
    ],
    "sg:menulink":"http://www.allmenus.com/nj/woodbridge/27570-casa-giuseppe/menu/",
    "sg:phone":"+1 732 283 9111",
    "sg:postcode":"08830",
    "sg:province":"NJ",
    "sg:tags":[
        "italian"
    ],
    "wof:name":"Casa Giuseppe",
    "wof:placetype":"venue"
},
  "geometry": {"coordinates":[-74.318586,40.575215],"type":"Point"}
}