{
  "type": "Feature",
  "properties": {
    "addr:full":"3 Harker Ave Berlin NJ 08009",
    "addr:housenumber":"3",
    "addr:postcode":"08009",
    "addr:street":"Harker Ave",
    "iso:country":"US",
    "sg:address":"3 Harker Ave",
    "sg:city":"Berlin",
    "sg:classifiers":[
        {
            "category":"Insurance",
            "subcategory":"Insurance Agent",
            "type":"Services"
        }
    ],
    "sg:phone":"+1 856 767 5020",
    "sg:postcode":"08009",
    "sg:province":"NJ",
    "wof:name":"Edgewood Associates Inc",
    "wof:placetype":"venue"
},
  "geometry": {"coordinates":[-74.93164400000001,39.796955],"type":"Point"}
}