{
  "type": "Feature",
  "properties": {
    "addr:full":"110 E Main St Tuckerton NJ 08087",
    "addr:housenumber":"110",
    "addr:postcode":"08087",
    "addr:street":"E Main St",
    "iso:country":"US",
    "sg:address":"110 E Main St",
    "sg:city":"Tuckerton",
    "sg:classifiers":[
        {
            "category":"Shopping",
            "subcategory":"Hobbies, Toys, & Games",
            "type":"Retail Goods"
        }
    ],
    "sg:phone":"+1 609 294 0455",
    "sg:postcode":"08087",
    "sg:province":"NJ",
    "sg:tags":[
        "piece"
    ],
    "wof:name":"Clamtowne Crafts",
    "wof:placetype":"venue"
},
  "geometry": {"coordinates":[-74.338936,39.603367],"type":"Point"}
}