{
  "type": "Feature",
  "properties": {
    "addr:full":"152 Mountainview Blvd Wayne NJ 07470",
    "addr:housenumber":"152",
    "addr:postcode":"07470",
    "addr:street":"Mountainview Blvd",
    "iso:country":"US",
    "sg:address":"152 Mountainview Blvd",
    "sg:city":"Wayne",
    "sg:classifiers":[
        {
            "category":"Restaurant",
            "type":"Food & Drink"
        }
    ],
    "sg:menulink":"http://www.allmenus.com/nj/wayne/146187-subway/menu/",
    "sg:phone":"+1 973 872 0001",
    "sg:postcode":"07470",
    "sg:province":"NJ",
    "sg:tags":[
        "american",
        "sandwich"
    ],
    "wof:name":"Subway",
    "wof:placetype":"venue"
},
  "geometry": {"coordinates":[-74.26800299999999,40.914729],"type":"Point"}
}