{
  "type": "Feature",
  "properties": {
    "addr:full":"4104 Galloping Hill Ln Toms River NJ 08755",
    "addr:housenumber":"4104",
    "addr:postcode":"08755",
    "addr:street":"Galloping Hill Ln",
    "iso:country":"US",
    "sg:address":"4104 Galloping Hill Ln",
    "sg:city":"Toms River",
    "sg:classifiers":[
        {
            "category":"Sports & Exercise",
            "subcategory":"Gym",
            "type":"Entertainment"
        }
    ],
    "sg:phone":"+1   ",
    "sg:postcode":"08755",
    "sg:province":"NJ",
    "sg:tags":[
        "fitness",
        "physical",
        "facility"
    ],
    "wof:name":"Irish Eyes Fitness Corp",
    "wof:placetype":"venue"
},
  "geometry": {"coordinates":[-74.240953,40.042933],"type":"Point"}
}