{
  "type": "Feature",
  "properties": {
    "addr:full":"1973 Whitesville Rd Toms River NJ 08755",
    "addr:housenumber":"1973",
    "addr:postcode":"08755",
    "addr:street":"Whitesville Rd",
    "iso:country":"US",
    "sg:address":"1973 Whitesville Rd",
    "sg:city":"Toms River",
    "sg:classifiers":[
        {
            "category":"Building & Trades",
            "subcategory":"Construction",
            "type":"Services"
        }
    ],
    "sg:phone":"+1 732 505 8003",
    "sg:postcode":"08755",
    "sg:province":"NJ",
    "sg:tags":[
        "general",
        "contractor"
    ],
    "wof:name":"Behr Construction Corp",
    "wof:placetype":"venue"
},
  "geometry": {"coordinates":[-74.235736,40.026508],"type":"Point"}
}