{
  "type": "Feature",
  "properties": {
    "iso:country":"US",
    "sg:address":"66 N Van Brunt St",
    "sg:city":"Englewood",
    "sg:classifiers":[
        {
            "category":"Health Services",
            "subcategory":"Doctor",
            "type":"Services"
        }
    ],
    "sg:phone":"+1 201 585 9368",
    "sg:postcode":"07631",
    "sg:province":"NJ",
    "sg:tags":[
        "physician",
        "surgeon"
    ],
    "wof:name":"Center For Nutrition",
    "wof:placetype":"venue"
},
  "geometry": {"coordinates":[-73.974739,40.895176],"type":"Point"}
}