{
  "type": "Feature",
  "properties": {
    "iso:country":"US",
    "sg:address":"350 US Hwy 46",
    "sg:city":"Dover",
    "sg:classifiers":[
        {
            "category":"Insurance",
            "subcategory":"Insurance Agent",
            "type":"Services"
        },
        {
            "category":"Insurance",
            "subcategory":"Life Insurance",
            "type":"Services"
        }
    ],
    "sg:phone":"+1 973 927 6300",
    "sg:postcode":"07803",
    "sg:province":"NJ",
    "wof:name":"American United Life Insurance",
    "wof:placetype":"venue"
},
  "geometry": {"coordinates":[-74.608626,40.879797],"type":"Point"}
}