{
  "type": "Feature",
  "properties": {
    "iso:country":"US",
    "sg:address":"815 McBride Ave",
    "sg:city":"Little Falls",
    "sg:classifiers":[
        {
            "category":"Manufacturing",
            "subcategory":"Tools & Machinery",
            "type":"Manufacturing & Wholesale Goods"
        }
    ],
    "sg:phone":"+1 973 278 6605",
    "sg:postcode":"07424",
    "sg:province":"NJ",
    "sg:tags":[
        "machine",
        "shop",
        "job"
    ],
    "wof:name":"Ace Metal Kraft Co Inc",
    "wof:placetype":"venue"
},
  "geometry": {"coordinates":[-74.20036500000001,40.897476],"type":"Point"}
}