{
  "type": "Feature",
  "properties": {
    "iso:country":"US",
    "sg:address":"101 Galleon Rd",
    "sg:city":"Manahawkin",
    "sg:classifiers":[
        {
            "category":"Travel",
            "subcategory":"Travel Agent",
            "type":"Entertainment"
        }
    ],
    "sg:phone":"+1 609 607 1102",
    "sg:postcode":"08050",
    "sg:province":"NJ",
    "sg:tags":[
        "agency"
    ],
    "wof:name":"Blue Moon Travel",
    "wof:placetype":"venue"
},
  "geometry": {"coordinates":[-74.294758,39.73768],"type":"Point"}
}