{
  "type": "Feature",
  "properties": {
    "iso:country":"US",
    "sg:address":"6 Wall St",
    "sg:city":"Passaic",
    "sg:classifiers":[
        {
            "category":"Organizations",
            "subcategory":"Religious Organization",
            "type":"Services"
        }
    ],
    "sg:phone":"+1 973 473 1773",
    "sg:postcode":"07055",
    "sg:province":"NJ",
    "sg:tags":[
        "clergy"
    ],
    "wof:name":"Andrzej Las",
    "wof:placetype":"venue"
},
  "geometry": {"coordinates":[-74.11079599999999,40.863884],"type":"Point"}
}