{
  "type": "Feature",
  "properties": {
    "iso:country":"US",
    "sg:address":"701 Creek Rd",
    "sg:city":"Bellmawr",
    "sg:classifiers":[
        {
            "category":"Home & Garden",
            "subcategory":"Garden Supply",
            "type":"Retail Goods"
        }
    ],
    "sg:phone":"+1 856 931 0041",
    "sg:postcode":"08031",
    "sg:province":"NJ",
    "sg:tags":[
        "sprinkler"
    ],
    "wof:name":"Sprinkler Co LLC",
    "wof:placetype":"venue"
},
  "geometry": {"coordinates":[-75.110444,39.86343],"type":"Point"}
}