{
  "type": "Feature",
  "properties": {
    "iso:country":"US",
    "sg:address":"149 Washington Ave",
    "sg:city":"Carteret",
    "sg:classifiers":[
        {
            "category":"Cinema",
            "subcategory":"Movie Theater",
            "type":"Entertainment"
        }
    ],
    "sg:phone":"+1 732 969 3336",
    "sg:postcode":"07008",
    "sg:province":"NJ",
    "wof:name":"Movie Video Ctr",
    "wof:placetype":"venue"
},
  "geometry": {"coordinates":[-74.226885,40.580214],"type":"Point"}
}