{
  "type": "Feature",
  "properties": {
    "addr:full":"56 Newton Ave Sussex NJ 07461",
    "addr:housenumber":"56",
    "addr:postcode":"07461",
    "addr:street":"Newton Ave",
    "iso:country":"US",
    "sg:address":"56 Newton Ave",
    "sg:city":"Sussex",
    "sg:classifiers":[
        {
            "category":"Professional",
            "subcategory":"Computer Services",
            "type":"Services"
        }
    ],
    "sg:phone":"+1 973 702 0454",
    "sg:postcode":"07461",
    "sg:province":"NJ",
    "sg:tags":[
        "consultant",
        "designer"
    ],
    "wof:name":"Logic Applied Computer Inc",
    "wof:placetype":"venue"
},
  "geometry": {"coordinates":[-74.61170199999999,41.208265],"type":"Point"}
}