{
  "type": "Feature",
  "properties": {
    "addr:full":"60 Crest Dr Basking Ridge NJ 07920",
    "addr:housenumber":"60",
    "addr:postcode":"07920",
    "addr:street":"Crest Dr",
    "iso:country":"US",
    "sg:address":"60 Crest Dr",
    "sg:city":"Basking Ridge",
    "sg:classifiers":[
        {
            "category":"Building & Trades",
            "subcategory":"Construction",
            "type":"Services"
        }
    ],
    "sg:phone":"+1 908 647 7469",
    "sg:postcode":"07920",
    "sg:province":"NJ",
    "sg:tags":[
        "house"
    ],
    "wof:name":"Abbaticola Construction LLC",
    "wof:placetype":"venue"
},
  "geometry": {"coordinates":[-74.530337,40.662642],"type":"Point"}
}