{
  "type": "Feature",
  "properties": {
    "iso:country":"US",
    "sg:address":"203 16th Ave",
    "sg:city":"Newark",
    "sg:classifiers":[
        {
            "category":"Food & Beverages",
            "subcategory":"Liquor & Beverages",
            "type":"Retail Goods"
        }
    ],
    "sg:phone":"+1 973 596 1616",
    "sg:postcode":"07103",
    "sg:province":"NJ",
    "sg:tags":[
        "beer",
        "wine",
        "spirit",
        "alcoholic"
    ],
    "wof:name":"Jersey Liquor",
    "wof:placetype":"venue"
},
  "geometry": {"coordinates":[-74.20459700000001,40.736],"type":"Point"}
}