{
  "type": "Feature",
  "properties": {
    "addr:full":"220 Blue Anchor Rd Sicklerville NJ 08009",
    "addr:housenumber":"220",
    "addr:postcode":"08009",
    "addr:street":"Blue Anchor Rd",
    "iso:country":"US",
    "sg:address":"220 Blue Anchor Rd",
    "sg:city":"Sicklerville",
    "sg:classifiers":[
        {
            "category":"Government",
            "subcategory":"Office",
            "type":"Public Place"
        }
    ],
    "sg:phone":"+1   ",
    "sg:postcode":"08009",
    "sg:province":"NJ",
    "sg:tags":[
        "conservation"
    ],
    "wof:name":"Fish & Wildlife",
    "wof:placetype":"venue"
},
  "geometry": {"coordinates":[-74.908539,39.739007],"type":"Point"}
}