{
  "type": "Feature",
  "properties": {
    "addr:full":"4612 Westfield Ave Pennsauken NJ 08110",
    "addr:housenumber":"4612",
    "addr:postcode":"08110",
    "addr:street":"Westfield Ave",
    "iso:country":"US",
    "sg:address":"4612 Westfield Ave",
    "sg:city":"Pennsauken",
    "sg:classifiers":[
        {
            "category":"Personal",
            "subcategory":"Beauty Salon",
            "type":"Services"
        }
    ],
    "sg:phone":"+1 856 662 7447",
    "sg:postcode":"08110",
    "sg:province":"NJ",
    "wof:name":"Maria's Beauty Salon",
    "wof:placetype":"venue"
},
  "geometry": {"coordinates":[-75.067435,39.957219],"type":"Point"}
}