{
  "type": "Feature",
  "properties": {
    "iso:country":"US",
    "sg:address":"1606 Long Hill Rd",
    "sg:city":"Millington",
    "sg:classifiers":[
        {
            "category":"Wholesale",
            "subcategory":"Machinery & Supplies",
            "type":"Manufacturing & Wholesale Goods"
        }
    ],
    "sg:phone":"+1 908 647 7377",
    "sg:postcode":"07946",
    "sg:province":"NJ",
    "sg:tags":[
        "chemical"
    ],
    "wof:name":"North American Products",
    "wof:placetype":"venue"
},
  "geometry": {"coordinates":[-74.509733,40.678173],"type":"Point"}
}