{
  "type": "Feature",
  "properties": {
    "addr:full":"16 Broad St Washington NJ 07882",
    "addr:housenumber":"16",
    "addr:postcode":"07882",
    "addr:street":"Broad St",
    "iso:country":"US",
    "sg:address":"16 Broad St",
    "sg:city":"Washington",
    "sg:classifiers":[
        {
            "category":"Wholesale",
            "subcategory":"Electrical",
            "type":"Manufacturing & Wholesale Goods"
        }
    ],
    "sg:phone":"+1 908 835 0065",
    "sg:postcode":"07882",
    "sg:province":"NJ",
    "wof:name":"Mr Appliance of Warren County",
    "wof:placetype":"venue"
},
  "geometry": {"coordinates":[-74.979434,40.758019],"type":"Point"}
}