{
  "type": "Feature",
  "properties": {
    "iso:country":"US",
    "sg:address":"100 1st St",
    "sg:city":"Hackensack",
    "sg:classifiers":[
        {
            "category":"Professional",
            "subcategory":"Computer Services",
            "type":"Services"
        }
    ],
    "sg:phone":"+1 201 489 7500",
    "sg:postcode":"07601",
    "sg:province":"NJ",
    "sg:tags":[
        "control",
        "prepackaged",
        "system",
        "computerized",
        "design",
        "traffic",
        "software"
    ],
    "wof:name":"Computran Systems Corporation",
    "wof:placetype":"venue"
},
  "geometry": {"coordinates":[-74.052207,40.884684],"type":"Point"}
}