{
  "type": "Feature",
  "properties": {
    "addr:full":"118 N Bridge St Somerville NJ 08876",
    "addr:housenumber":"118",
    "addr:postcode":"08876",
    "addr:street":"N Bridge St",
    "iso:country":"US",
    "sg:address":"118 N Bridge St",
    "sg:city":"Somerville",
    "sg:classifiers":[
        {
            "category":"Retail",
            "subcategory":"Auto Repair",
            "type":"Services"
        }
    ],
    "sg:phone":"+1   ",
    "sg:postcode":"08876",
    "sg:province":"NJ",
    "sg:tags":[
        "automotive",
        "carrier",
        "insurance"
    ],
    "wof:name":"Auto Critic",
    "wof:placetype":"venue"
},
  "geometry": {"coordinates":[-74.610589,40.571704],"type":"Point"}
}