{
  "type": "Feature",
  "properties": {
    "addr:full":"716 7th St Union City NJ 07087",
    "addr:housenumber":"716",
    "addr:postcode":"07087",
    "addr:street":"7Th St",
    "iso:country":"US",
    "sg:address":"716 7th St",
    "sg:city":"Union City",
    "sg:classifiers":[
        {
            "category":"Retail",
            "subcategory":"Laundry & Dry Cleaning",
            "type":"Services"
        }
    ],
    "sg:phone":"+1 201 867 8059",
    "sg:postcode":"07087",
    "sg:province":"NJ",
    "wof:name":"Eagle Cleaning Group Inc",
    "wof:placetype":"venue"
},
  "geometry": {"coordinates":[-74.043695,40.758213],"type":"Point"}
}