{
  "type": "Feature",
  "properties": {
    "iso:country":"US",
    "sg:address":"736 Cherry Tree Ln",
    "sg:city":"Trenton",
    "sg:classifiers":[
        {
            "category":"Organizations",
            "subcategory":"Community Association",
            "type":"Services"
        }
    ],
    "sg:phone":"+1 609 695 9801",
    "sg:postcode":"08648",
    "sg:province":"NJ",
    "wof:name":"Veterans Fgn Wars Post No 3022",
    "wof:placetype":"venue"
},
  "geometry": {"coordinates":[-74.731104,40.24834],"type":"Point"}
}