{
  "type": "Feature",
  "properties": {
    "iso:country":"US",
    "sg:address":"436 Cokesbury Rd",
    "sg:city":"Annandale",
    "sg:classifiers":[
        {
            "category":"Social Services",
            "subcategory":"Child Care",
            "type":"Services"
        }
    ],
    "sg:phone":"+1 908 638 4320",
    "sg:postcode":"08801",
    "sg:province":"NJ",
    "sg:tags":[
        "day"
    ],
    "wof:name":"Apple Dumpling Day Care",
    "wof:placetype":"venue"
},
  "geometry": {"coordinates":[-74.870369,40.681701],"type":"Point"}
}