{
  "type": "Feature",
  "properties": {
    "iso:country":"US",
    "sg:address":"2707 Belmar Blvd",
    "sg:city":"Belmar",
    "sg:classifiers":[
        {
            "category":"Food & Beverages",
            "subcategory":"Fruits & Vegetables",
            "type":"Retail Goods"
        }
    ],
    "sg:phone":"+1 732 681 3500",
    "sg:postcode":"07719",
    "sg:province":"NJ",
    "sg:tags":[
        "produce"
    ],
    "wof:name":"Sandra's Market Place",
    "wof:placetype":"venue"
},
  "geometry": {"coordinates":[-74.065662,40.178306],"type":"Point"}
}