{
  "type": "Feature",
  "properties": {
    "iso:country":"US",
    "sg:address":"25 Thomas Ave",
    "sg:city":"Maple Shade",
    "sg:classifiers":[
        {
            "category":"Organizations",
            "subcategory":"Professional Association",
            "type":"Services"
        }
    ],
    "sg:phone":"+1 856 667 7046",
    "sg:postcode":"08052",
    "sg:province":"NJ",
    "wof:name":"Penn State Alumni Club",
    "wof:placetype":"venue"
},
  "geometry": {"coordinates":[-75.003315,39.950311],"type":"Point"}
}