{
  "type": "Feature",
  "properties": {
    "iso:country":"US",
    "sg:address":"28 Canterbury Rd",
    "sg:city":"Ringwood",
    "sg:classifiers":[
        {
            "category":"Building & Trades",
            "subcategory":"Landscaping Services",
            "type":"Services"
        }
    ],
    "sg:phone":"+1 973 839 5800",
    "sg:postcode":"07456",
    "sg:province":"NJ",
    "wof:name":"Stanton Tree Experts",
    "wof:placetype":"venue"
},
  "geometry": {"coordinates":[-74.275926,41.064794],"type":"Point"}
}