{
  "type": "Feature",
  "properties": {
    "iso:country":"US",
    "sg:address":"1106 Mercer Dr",
    "sg:city":"Haddonfield",
    "sg:classifiers":[
        {
            "category":"Professional",
            "subcategory":"Management & Consulting",
            "type":"Services"
        }
    ],
    "sg:phone":"+1   ",
    "sg:postcode":"08033",
    "sg:province":"NJ",
    "wof:name":"Schmidt Glbl Consult",
    "wof:placetype":"venue"
},
  "geometry": {"coordinates":[-75.038968,39.877813],"type":"Point"}
}