{
  "type": "Feature",
  "properties": {
    "addr:full":"39 Columbus Ave Hillsdale NJ 07642",
    "addr:housenumber":"39",
    "addr:postcode":"07642",
    "addr:street":"Columbus Ave",
    "iso:country":"US",
    "sg:address":"39 Columbus Ave",
    "sg:city":"Hillsdale",
    "sg:classifiers":[
        {
            "category":"Retail",
            "subcategory":"Repair Shop",
            "type":"Services"
        }
    ],
    "sg:phone":"+1 201 664 3400",
    "sg:postcode":"07642",
    "sg:province":"NJ",
    "sg:tags":[
        "refinish",
        "furniture"
    ],
    "wof:name":"Advantage Office Furniture Rpr",
    "wof:placetype":"venue"
},
  "geometry": {"coordinates":[-74.040277,41.015229],"type":"Point"}
}