{
  "type": "Feature",
  "properties": {
    "iso:country":"US",
    "sg:address":"34 Williams St",
    "sg:city":"Lakewood",
    "sg:classifiers":[
        {
            "category":"Building & Trades",
            "subcategory":"Construction",
            "type":"Services"
        }
    ],
    "sg:phone":"+1 732 370 4083",
    "sg:postcode":"08701",
    "sg:province":"NJ",
    "sg:tags":[
        "contractor"
    ],
    "wof:name":"A J Di9stefano Contractors",
    "wof:placetype":"venue"
},
  "geometry": {"coordinates":[-74.221615,40.075265],"type":"Point"}
}