{
  "type": "Feature",
  "properties": {
    "addr:full":"3900 River Rd Point Pleasant Beach NJ 08742",
    "addr:housenumber":"3900",
    "addr:postcode":"08742",
    "addr:street":"River Rd",
    "iso:country":"US",
    "sg:address":"3900 River Rd",
    "sg:city":"Point Pleasant Beach",
    "sg:classifiers":[
        {
            "category":"Travel",
            "subcategory":"Hotels & Motels",
            "type":"Entertainment"
        }
    ],
    "sg:phone":"+1   ",
    "sg:postcode":"08742",
    "sg:province":"NJ",
    "sg:tags":[
        "operation",
        "catering"
    ],
    "wof:name":"Crystal Point Inn",
    "wof:placetype":"venue"
},
  "geometry": {"coordinates":[-74.087203,40.094325],"type":"Point"}
}