{
  "type": "Feature",
  "properties": {
    "iso:country":"US",
    "sg:address":"864 Patterson Rd",
    "sg:city":"Jackson",
    "sg:classifiers":[
        {
            "category":"Professional",
            "subcategory":"Business Services",
            "type":"Services"
        }
    ],
    "sg:phone":"+1   ",
    "sg:postcode":"08527",
    "sg:province":"NJ",
    "wof:name":"Lubin Window Design Inc",
    "wof:placetype":"venue"
},
  "geometry": {"coordinates":[-74.394274,40.155191],"type":"Point"}
}