{
  "type": "Feature",
  "properties": {
    "iso:country":"US",
    "sg:address":"41 Victoria Ave",
    "sg:city":"Newark",
    "sg:classifiers":[
        {
            "category":"Restaurant",
            "type":"Food & Drink"
        }
    ],
    "sg:phone":"+1   ",
    "sg:postcode":"07104",
    "sg:province":"NJ",
    "sg:tags":[
        "eating"
    ],
    "wof:name":"La Mera Esquina",
    "wof:placetype":"venue"
},
  "geometry": {"coordinates":[-74.176643,40.75336],"type":"Point"}
}