{
  "type": "Feature",
  "properties": {
    "addr:full":"47 Broad St Eatontown NJ 07724",
    "addr:housenumber":"47",
    "addr:postcode":"07724",
    "addr:street":"Broad St",
    "iso:country":"US",
    "sg:address":"47 Broad St",
    "sg:city":"Eatontown",
    "sg:classifiers":[
        {
            "category":"Government",
            "subcategory":"Office",
            "type":"Public Place"
        }
    ],
    "sg:phone":"+1 732 389 7623",
    "sg:postcode":"07724",
    "sg:province":"NJ",
    "sg:tags":[
        "city"
    ],
    "wof:name":"Eatontown Borough Mayor",
    "wof:placetype":"venue"
},
  "geometry": {"coordinates":[-74.0592,40.304877],"type":"Point"}
}