{
  "type": "Feature",
  "properties": {
    "iso:country":"US",
    "sg:address":"351 Irving Ave",
    "sg:city":"Bridgeton",
    "sg:classifiers":[
        {
            "category":"Health Services",
            "subcategory":"Doctor",
            "type":"Services"
        }
    ],
    "sg:phone":"+1 856 453 4400",
    "sg:postcode":"08302",
    "sg:province":"NJ",
    "sg:tags":[
        "physician",
        "surgeon"
    ],
    "wof:name":"Cumberland Nephrology Assoc",
    "wof:placetype":"venue"
},
  "geometry": {"coordinates":[-75.217501,39.435887],"type":"Point"}
}