{
  "type": "Feature",
  "properties": {
    "iso:country":"US",
    "sg:address":"139 Chestnut St",
    "sg:city":"Nutley",
    "sg:classifiers":[
        {
            "category":"Building & Trades",
            "subcategory":"Plumbing",
            "type":"Services"
        }
    ],
    "sg:phone":"+1 973 667 7550",
    "sg:postcode":"07110",
    "sg:province":"NJ",
    "sg:tags":[
        "maintenance",
        "mechanical"
    ],
    "wof:name":"Major Mechanical",
    "wof:placetype":"venue"
},
  "geometry": {"coordinates":[-74.15530200000001,40.818055],"type":"Point"}
}