{
  "type": "Feature",
  "properties": {
    "addr:full":"609 Franklinville Rd Mullica Hill NJ 08062",
    "addr:housenumber":"609",
    "addr:postcode":"08062",
    "addr:street":"Franklinville Rd",
    "iso:country":"US",
    "sg:address":"609 Franklinville Rd",
    "sg:city":"Mullica Hill",
    "sg:classifiers":[
        {
            "category":"Food & Beverages",
            "subcategory":"Fruits & Vegetables",
            "type":"Retail Goods"
        }
    ],
    "sg:phone":"+1 856 478 2428",
    "sg:postcode":"08062",
    "sg:province":"NJ",
    "sg:tags":[
        "produce"
    ],
    "wof:name":"C Diamond Produce",
    "wof:placetype":"venue"
},
  "geometry": {"coordinates":[-75.246308,39.712918],"type":"Point"}
}