{
  "type": "Feature",
  "properties": {
    "addr:full":"15 Treaty Rd Randolph NJ 07869",
    "addr:housenumber":"15",
    "addr:postcode":"07869",
    "addr:street":"Treaty Rd",
    "iso:country":"US",
    "sg:address":"15 Treaty Rd",
    "sg:city":"Randolph",
    "sg:classifiers":[
        {
            "category":"Retail",
            "subcategory":"Repair Shop",
            "type":"Services"
        }
    ],
    "sg:phone":"+1   ",
    "sg:postcode":"07869",
    "sg:province":"NJ",
    "sg:tags":[
        "welding"
    ],
    "wof:name":"M J Post Welding",
    "wof:placetype":"venue"
},
  "geometry": {"coordinates":[-74.589618,40.870627],"type":"Point"}
}