{
  "type": "Feature",
  "properties": {
    "addr:full":"216 Haddon Ave Collingswood NJ 08108",
    "addr:housenumber":"216",
    "addr:postcode":"08108",
    "addr:street":"Haddon Ave",
    "iso:country":"US",
    "sg:address":"216 Haddon Ave",
    "sg:city":"Collingswood",
    "sg:classifiers":[
        {
            "category":"Insurance",
            "subcategory":"Insurance Agent",
            "type":"Services"
        }
    ],
    "sg:phone":"+1   ",
    "sg:postcode":"08108",
    "sg:province":"NJ",
    "sg:tags":[
        "management",
        "disability"
    ],
    "wof:name":"Crawford & Company",
    "wof:placetype":"venue"
},
  "geometry": {"coordinates":[-75.0829,39.920887],"type":"Point"}
}