{
  "type": "Feature",
  "properties": {
    "addr:full":"51 S Wandling Ave Washington NJ 07882",
    "addr:housenumber":"51",
    "addr:postcode":"07882",
    "addr:street":"S Wandling Ave",
    "iso:country":"US",
    "sg:address":"51 S Wandling Ave",
    "sg:city":"Washington",
    "sg:classifiers":[
        {
            "category":"Manufacturing",
            "subcategory":"Chemicals & Compounds",
            "type":"Manufacturing & Wholesale Goods"
        }
    ],
    "sg:phone":"+1 908 689 9020",
    "sg:postcode":"07882",
    "sg:province":"NJ",
    "sg:tags":[
        "herb",
        "extract",
        "mfg"
    ],
    "sg:website":"www.herbalist-alchemist.com",
    "wof:name":"Herbalist & Alchemist Inc",
    "wof:placetype":"venue"
},
  "geometry": {"coordinates":[-74.98291399999999,40.754256],"type":"Point"}
}