{
  "type": "Feature",
  "properties": {
    "addr:full":"110 S Broadway St South Amboy NJ 08879",
    "addr:housenumber":"110",
    "addr:postcode":"08879",
    "addr:street":"S Broadway St",
    "iso:country":"US",
    "sg:address":"110 S Broadway St",
    "sg:city":"South Amboy",
    "sg:classifiers":[
        {
            "category":"Shopping",
            "type":"Retail Goods"
        }
    ],
    "sg:phone":"+1 732 778 5051",
    "sg:postcode":"08879",
    "sg:province":"NJ",
    "sg:tags":[
        "cards",
        "sport",
        "baseball",
        "memorabilia"
    ],
    "wof:name":"Sports Hounds",
    "wof:placetype":"venue"
},
  "geometry": {"coordinates":[-74.28026199999999,40.483397],"type":"Point"}
}