{
  "type": "Feature",
  "properties": {
    "addr:full":"9 62nd St West New York NJ 07093",
    "addr:housenumber":"9",
    "addr:postcode":"nj 07093",
    "addr:street":"62Nd St West",
    "iso:country":"US",
    "sg:address":"9 62nd St",
    "sg:city":"West New York",
    "sg:classifiers":[
        {
            "category":"Banks & Credit Unions",
            "subcategory":"Investment Brokerage",
            "type":"Services"
        }
    ],
    "sg:phone":"+1   ",
    "sg:postcode":"07093",
    "sg:province":"NJ",
    "sg:tags":[
        "advisory"
    ],
    "wof:name":"Greensboro Investors LLC",
    "wof:placetype":"venue"
},
  "geometry": {"coordinates":[-74.005335,40.786801],"type":"Point"}
}