{
  "type": "Feature",
  "properties": {
    "iso:country":"US",
    "sg:address":"41 Stirling Ct",
    "sg:city":"Stirling",
    "sg:classifiers":[
        {
            "category":"Building & Trades",
            "subcategory":"Construction",
            "type":"Services"
        }
    ],
    "sg:phone":"+1 908 626 0856",
    "sg:postcode":"07980",
    "sg:province":"NJ",
    "sg:tags":[
        "nonresidential"
    ],
    "wof:name":"Roman Contractors Inc",
    "wof:placetype":"venue"
},
  "geometry": {"coordinates":[-74.490593,40.677541],"type":"Point"}
}