{
  "type": "Feature",
  "properties": {
    "addr:full":"273 Paterson Ave East Rutherford NJ 07073",
    "addr:housenumber":"273",
    "addr:postcode":"07073",
    "addr:street":"Paterson Ave",
    "iso:country":"US",
    "sg:address":"273 Paterson Ave",
    "sg:city":"East Rutherford",
    "sg:classifiers":[
        {
            "category":"Professional",
            "subcategory":"Business Services",
            "type":"Services"
        }
    ],
    "sg:phone":"+1   ",
    "sg:postcode":"07073",
    "sg:province":"NJ",
    "sg:tags":[
        "executive"
    ],
    "wof:name":"East Rutherford Bldg Inspector",
    "wof:placetype":"venue"
},
  "geometry": {"coordinates":[-74.09801299999999,40.834546],"type":"Point"}
}