{
  "type": "Feature",
  "properties": {
    "addr:full":"534 Cooper St Camden NJ 08102",
    "addr:housenumber":"534",
    "addr:postcode":"08102",
    "addr:street":"Cooper St",
    "iso:country":"US",
    "sg:address":"534 Cooper St",
    "sg:city":"Camden",
    "sg:classifiers":[
        {
            "category":"Professional",
            "subcategory":"Research",
            "type":"Services"
        },
        {
            "category":"Professional",
            "subcategory":"Management & Consulting",
            "type":"Services"
        }
    ],
    "sg:phone":"+1 856 963 1113",
    "sg:postcode":"08102",
    "sg:province":"NJ",
    "sg:tags":[
        "educational",
        "business"
    ],
    "wof:name":"Excellent Education Everyone",
    "wof:placetype":"venue"
},
  "geometry": {"coordinates":[-75.119426,39.946561],"type":"Point"}
}