{
  "type": "Feature",
  "properties": {
    "iso:country":"US",
    "sg:address":"574 Newark Pompton Tpke",
    "sg:city":"Pompton Plains",
    "sg:classifiers":[
        {
            "category":"Professional",
            "type":"Services"
        }
    ],
    "sg:phone":"+1 973 835 0006",
    "sg:postcode":"07444",
    "sg:province":"NJ",
    "sg:tags":[
        "caterer"
    ],
    "wof:name":"Tas Realty Inc",
    "wof:placetype":"venue"
},
  "geometry": {"coordinates":[-74.29555000000001,40.967386],"type":"Point"}
}