{
  "type": "Feature",
  "properties": {
    "addr:full":"1151 Broad St Ste 116 Shrewsbury NJ 07702",
    "addr:housenumber":"1151",
    "addr:postcode":"07702",
    "addr:street":"Broad St Ste 116",
    "iso:country":"US",
    "sg:address":"1151 Broad St Ste 116",
    "sg:city":"Shrewsbury",
    "sg:classifiers":[
        {
            "category":"Banks & Credit Unions",
            "subcategory":"Bank",
            "type":"Services"
        }
    ],
    "sg:phone":"+1 732 544 8225",
    "sg:postcode":"07702",
    "sg:province":"NJ",
    "sg:tags":[
        "saving",
        "commercial"
    ],
    "sg:website":"http://www.swfeast.com",
    "wof:name":"Swf East Inc",
    "wof:placetype":"venue"
},
  "geometry": {"coordinates":[-74.063856,40.313382],"type":"Point"}
}