{
  "type": "Feature",
  "properties": {
    "addr:full":"214 Newark Ave Jersey City NJ 07302",
    "addr:housenumber":"214",
    "addr:postcode":"07302",
    "addr:street":"Newark Ave",
    "iso:country":"US",
    "sg:address":"214 Newark Ave",
    "sg:city":"Jersey City",
    "sg:classifiers":[
        {
            "category":"Banks & Credit Unions",
            "subcategory":"Bank",
            "type":"Services"
        }
    ],
    "sg:phone":"+1 201 795 7752",
    "sg:postcode":"07302",
    "sg:province":"NJ",
    "sg:website":"www.sovereignbank.com",
    "wof:name":"Sovereign Bank",
    "wof:placetype":"venue"
},
  "geometry": {"coordinates":[-74.047201,40.722327],"type":"Point"}
}