{
  "type": "Feature",
  "properties": {
    "addr:full":"9 Kelsey St Rockaway NJ 07866",
    "addr:housenumber":"9",
    "addr:postcode":"07866",
    "addr:street":"Kelsey St",
    "iso:country":"US",
    "sg:address":"9 Kelsey St",
    "sg:city":"Rockaway",
    "sg:classifiers":[
        {
            "category":"Building & Trades",
            "subcategory":"Landscaping Services",
            "type":"Services"
        }
    ],
    "sg:phone":"+1 973 627 1803",
    "sg:postcode":"07866",
    "sg:province":"NJ",
    "sg:tags":[
        "landscape",
        "contractor"
    ],
    "wof:name":"Monti Landscaping Landscape",
    "wof:placetype":"venue"
},
  "geometry": {"coordinates":[-74.507012,40.908508],"type":"Point"}
}