{
  "type": "Feature",
  "properties": {
    "addr:full":"16 White Horse Pike Lawnside NJ 08045",
    "addr:housenumber":"16",
    "addr:postcode":"08045",
    "addr:street":"White Horse Pike",
    "iso:country":"US",
    "sg:address":"16 White Horse Pike",
    "sg:city":"Lawnside",
    "sg:classifiers":[
        {
            "category":"Professional",
            "type":"Services"
        }
    ],
    "sg:phone":"+1   ",
    "sg:postcode":"08045",
    "sg:province":"NJ",
    "wof:name":"16 Whp LLC",
    "wof:placetype":"venue"
},
  "geometry": {"coordinates":[-75.03835100000001,39.865855],"type":"Point"}
}