{
  "type": "Feature",
  "properties": {
    "addr:full":"20 River Rd North Arlington NJ 07031",
    "addr:housenumber":"20",
    "addr:postcode":"07031",
    "addr:street":"River Rd North",
    "iso:country":"US",
    "sg:address":"20 River Rd",
    "sg:city":"North Arlington",
    "sg:classifiers":[
        {
            "category":"Retail",
            "subcategory":"Auto Repair",
            "type":"Services"
        }
    ],
    "sg:phone":"+1 201 998 9666",
    "sg:postcode":"07031",
    "sg:province":"NJ",
    "sg:tags":[
        "transmission",
        "shop"
    ],
    "wof:name":"Kirks Automatic Transmissions",
    "wof:placetype":"venue"
},
  "geometry": {"coordinates":[-74.14529899999999,40.786482],"type":"Point"}
}