{
  "type": "Feature",
  "properties": {
    "iso:country":"US",
    "sg:address":"5 Washington Ave",
    "sg:city":"Fairfield",
    "sg:classifiers":[
        {
            "category":"Wholesale",
            "subcategory":"Durable Goods & Equipment",
            "type":"Manufacturing & Wholesale Goods"
        }
    ],
    "sg:phone":"+1 973 227 8850",
    "sg:postcode":"07004",
    "sg:province":"NJ",
    "wof:name":"Viking Supply Net",
    "wof:placetype":"venue"
},
  "geometry": {"coordinates":[-74.283917,40.867661],"type":"Point"}
}