{
  "type": "Feature",
  "properties": {
    "iso:country":"US",
    "sg:address":"217 Dayton Ave",
    "sg:city":"Clifton",
    "sg:classifiers":[
        {
            "category":"Professional",
            "type":"Services"
        },
        {
            "category":"Professional",
            "subcategory":"Management & Consulting",
            "type":"Services"
        }
    ],
    "sg:phone":"+1 973 340 9961",
    "sg:postcode":"07011",
    "sg:province":"NJ",
    "sg:tags":[
        "personnel",
        "consultant"
    ],
    "wof:name":"Construction Force Services",
    "wof:placetype":"venue"
},
  "geometry": {"coordinates":[-74.122598,40.875045],"type":"Point"}
}