{
  "type": "Feature",
  "properties": {
    "addr:full":"1 Stewart Ct Denville NJ 07834",
    "addr:housenumber":"1",
    "addr:postcode":"07834",
    "addr:street":"Stewart Ct",
    "iso:country":"US",
    "sg:address":"1 Stewart Ct",
    "sg:city":"Denville",
    "sg:classifiers":[
        {
            "category":"Manufacturing",
            "subcategory":"Metals",
            "type":"Manufacturing & Wholesale Goods"
        },
        {
            "category":"Building & Trades",
            "subcategory":"Plumbing",
            "type":"Services"
        }
    ],
    "sg:phone":"+1 973 328 2800",
    "sg:postcode":"07834",
    "sg:province":"NJ",
    "sg:tags":[
        "plumbing",
        "contractor",
        "fixture",
        "supply"
    ],
    "wof:name":"State Plumbing & Heating Corp",
    "wof:placetype":"venue"
},
  "geometry": {"coordinates":[-74.516458,40.878595],"type":"Point"}
}