{
  "type": "Feature",
  "properties": {
    "addr:full":"1036 Ye Greate St Greenwich NJ 08323",
    "addr:housenumber":"1036",
    "addr:postcode":"08323",
    "addr:street":"Ye Greate St",
    "iso:country":"US",
    "sg:address":"1036 Ye Greate St",
    "sg:city":"Greenwich",
    "sg:classifiers":[
        {
            "category":"Autos & Motor Vehicles",
            "subcategory":"Boat Sales",
            "type":"Retail Goods"
        }
    ],
    "sg:phone":"+1 856 451 7961",
    "sg:postcode":"08323",
    "sg:province":"NJ",
    "sg:tags":[
        "dealer",
        "sales"
    ],
    "wof:name":"Down Jersey Marine Svc",
    "wof:placetype":"venue"
},
  "geometry": {"coordinates":[-75.336637,39.386859],"type":"Point"}
}