{
  "type": "Feature",
  "properties": {
    "iso:country":"US",
    "sg:address":"213 E Bergen Pl",
    "sg:city":"Red Bank",
    "sg:classifiers":[
        {
            "category":"Manufacturing",
            "subcategory":"Textiles",
            "type":"Manufacturing & Wholesale Goods"
        }
    ],
    "sg:phone":"+1 732 747 4558",
    "sg:postcode":"07701",
    "sg:province":"NJ",
    "sg:tags":[
        "mfg"
    ],
    "wof:name":"Beaulieu of America Inc",
    "wof:placetype":"venue"
},
  "geometry": {"coordinates":[-74.06752899999999,40.341924],"type":"Point"}
}