{
  "type": "Feature",
  "properties": {
    "addr:full":"96 Westside Ave Bergenfield NJ 07621",
    "addr:housenumber":"96",
    "addr:postcode":"07621",
    "addr:street":"Westside Ave",
    "iso:country":"US",
    "sg:address":"96 Westside Ave",
    "sg:city":"Bergenfield",
    "sg:classifiers":[
        {
            "category":"Social Services",
            "subcategory":"Child Care",
            "type":"Services"
        }
    ],
    "sg:phone":"+1 201 384 1852",
    "sg:postcode":"07621",
    "sg:province":"NJ",
    "wof:name":"Parks Ave Child Development",
    "wof:placetype":"venue"
},
  "geometry": {"coordinates":[-74.00304199999999,40.920654],"type":"Point"}
}