{
  "type": "Feature",
  "properties": {
    "addr:full":"39 Paterson Ave Wallington NJ 07057",
    "addr:housenumber":"39",
    "addr:postcode":"07057",
    "addr:street":"Paterson Ave",
    "iso:country":"US",
    "sg:address":"39 Paterson Ave",
    "sg:city":"Wallington",
    "sg:classifiers":[
        {
            "category":"Professional",
            "subcategory":"Computer Services",
            "type":"Services"
        }
    ],
    "sg:phone":"+1 908 604 6000",
    "sg:postcode":"07057",
    "sg:province":"NJ",
    "sg:tags":[
        "repair"
    ],
    "wof:name":"Mc2 Squared Corporation",
    "wof:placetype":"venue"
},
  "geometry": {"coordinates":[-74.118599,40.853199],"type":"Point"}
}