{
  "type": "Feature",
  "properties": {
    "iso:country":"US",
    "sg:address":"420 Valley Brook Ave Ste 202",
    "sg:city":"Lyndhurst",
    "sg:classifiers":[
        {
            "category":"Professional",
            "subcategory":"Art Services",
            "type":"Services"
        }
    ],
    "sg:phone":"+1 201 438 3018",
    "sg:postcode":"07071",
    "sg:province":"NJ",
    "sg:tags":[
        "photographer"
    ],
    "sg:website":"www.miltongil.com",
    "wof:name":"Milton Gill Photographers",
    "wof:placetype":"venue"
},
  "geometry": {"coordinates":[-74.124123,40.81153],"type":"Point"}
}