{
  "type": "Feature",
  "properties": {
    "iso:country":"US",
    "sg:address":"276 E Main St",
    "sg:city":"Denville",
    "sg:classifiers":[
        {
            "category":"Restaurant",
            "type":"Food & Drink"
        }
    ],
    "sg:phone":"+1 973 983 0707",
    "sg:postcode":"07834",
    "sg:province":"NJ",
    "sg:tags":[
        "chinese"
    ],
    "wof:name":"China Pabilion",
    "wof:placetype":"venue"
},
  "geometry": {"coordinates":[-74.47959899999999,40.8834],"type":"Point"}
}