{
  "type": "Feature",
  "properties": {
    "addr:full":"105 Smith St Perth Amboy NJ 08861",
    "addr:housenumber":"105",
    "addr:postcode":"08861",
    "addr:street":"Smith St",
    "iso:country":"US",
    "sg:address":"105 Smith St",
    "sg:city":"Perth Amboy",
    "sg:classifiers":[
        {
            "category":"Shopping",
            "subcategory":"Discount & Variety Stores",
            "type":"Retail Goods"
        }
    ],
    "sg:phone":"+1   ",
    "sg:postcode":"08861",
    "sg:province":"NJ",
    "sg:tags":[
        "merchandise",
        "general"
    ],
    "wof:name":"Bargan Man The",
    "wof:placetype":"venue"
},
  "geometry": {"coordinates":[-74.26744600000001,40.50833],"type":"Point"}
}