{
  "type": "Feature",
  "properties": {
    "addr:full":"55 W Commerce St Bridgeton NJ 08302",
    "addr:housenumber":"55",
    "addr:postcode":"08302",
    "addr:street":"W Commerce St",
    "iso:country":"US",
    "sg:address":"55 W Commerce St",
    "sg:city":"Bridgeton",
    "sg:classifiers":[
        {
            "category":"Government",
            "subcategory":"Office",
            "type":"Public Place"
        }
    ],
    "sg:phone":"+1 856 453 4850",
    "sg:postcode":"08302",
    "sg:province":"NJ",
    "sg:tags":[
        "county",
        "taxation"
    ],
    "wof:name":"County Taxation Board",
    "wof:placetype":"venue"
},
  "geometry": {"coordinates":[-75.237381,39.429531],"type":"Point"}
}