{
  "type": "Feature",
  "properties": {
    "iso:country":"US",
    "sg:address":"1821 Lillian Dr",
    "sg:city":"Williamstown",
    "sg:classifiers":[
        {
            "category":"Building & Trades",
            "subcategory":"Construction",
            "type":"Services"
        }
    ],
    "sg:phone":"+1 856 740 9501",
    "sg:postcode":"08094",
    "sg:province":"NJ",
    "wof:name":"Landstar Paving Inc",
    "wof:placetype":"venue"
},
  "geometry": {"coordinates":[-75.013907,39.713185],"type":"Point"}
}