{
  "type": "Feature",
  "properties": {
    "addr:full":"43 Newark Way Maplewood NJ 07040",
    "addr:housenumber":"43",
    "addr:postcode":"07040",
    "addr:street":"Newark Way",
    "iso:country":"US",
    "sg:address":"43 Newark Way",
    "sg:city":"Maplewood",
    "sg:classifiers":[
        {
            "category":"Manufacturing",
            "subcategory":"Tools & Machinery",
            "type":"Manufacturing & Wholesale Goods"
        }
    ],
    "sg:phone":"+1 908 755 2900",
    "sg:postcode":"07040",
    "sg:province":"NJ",
    "sg:tags":[
        "pump"
    ],
    "sg:website":"www.emcontrol.com",
    "wof:name":"Eastern Motion Control",
    "wof:placetype":"venue"
},
  "geometry": {"coordinates":[-74.25904300000001,40.71818],"type":"Point"}
}