{
  "type": "Feature",
  "properties": {
    "iso:country":"US",
    "sg:address":"66 Malcolm Rd",
    "sg:city":"Mahwah",
    "sg:classifiers":[
        {
            "category":"Banks & Credit Unions",
            "subcategory":"Investment Brokerage",
            "type":"Services"
        }
    ],
    "sg:phone":"+1 201 529 8083",
    "sg:postcode":"07430",
    "sg:province":"NJ",
    "sg:tags":[
        "management"
    ],
    "wof:name":"Malcolm Associates",
    "wof:placetype":"venue"
},
  "geometry": {"coordinates":[-74.139145,41.09043],"type":"Point"}
}