{
  "type": "Feature",
  "properties": {
    "iso:country":"US",
    "sg:address":"91 Northfield Rd",
    "sg:city":"Millington",
    "sg:classifiers":[
        {
            "category":"Education",
            "subcategory":"School",
            "type":"Public Place"
        }
    ],
    "sg:phone":"+1   ",
    "sg:postcode":"07946",
    "sg:province":"NJ",
    "sg:tags":[
        "executive"
    ],
    "wof:name":"Millington School",
    "wof:placetype":"venue"
},
  "geometry": {"coordinates":[-74.517555,40.671886],"type":"Point"}
}