{
  "type": "Feature",
  "properties": {
    "addr:full":"80 River St Hoboken NJ 07030",
    "addr:housenumber":"80",
    "addr:postcode":"07030",
    "addr:street":"River St",
    "iso:country":"US",
    "sg:address":"80 River St",
    "sg:city":"Hoboken",
    "sg:classifiers":[
        {
            "category":"Bars & Pubs",
            "type":"Food & Drink"
        },
        {
            "category":"Restaurant",
            "type":"Food & Drink"
        },
        {
            "category":"Bars & Pubs",
            "subcategory":"Lounge",
            "type":"Food & Drink"
        }
    ],
    "sg:phone":"+1 201 656 9009",
    "sg:postcode":"07030",
    "sg:province":"NJ",
    "sg:tags":[
        "creole",
        "cajun",
        "cajun/creole",
        "american",
        "cocktail"
    ],
    "sg:website":"www.oddfellowsrest.com/",
    "wof:name":"Oddfellows Rest Louisiana Bar & Restaurant",
    "wof:placetype":"venue"
},
  "geometry": {"coordinates":[-74.028986,40.736604],"type":"Point"}
}