{
  "type": "Feature",
  "properties": {
    "iso:country":"US",
    "sg:address":"50 Main Ave",
    "sg:city":"Elmwood Park",
    "sg:classifiers":[
        {
            "category":"Real Estate",
            "subcategory":"Real Estate Agent",
            "type":"Services"
        }
    ],
    "sg:phone":"+1   ",
    "sg:postcode":"07407",
    "sg:province":"NJ",
    "wof:name":"Sally Hertel",
    "wof:placetype":"venue"
},
  "geometry": {"coordinates":[-74.10981200000001,40.909969],"type":"Point"}
}