{
  "type": "Feature",
  "properties": {
    "addr:full":"328 Creek Rd Bellmawr NJ 08031",
    "addr:housenumber":"328",
    "addr:postcode":"08031",
    "addr:street":"Creek Rd",
    "iso:country":"US",
    "sg:address":"328 Creek Rd",
    "sg:city":"Bellmawr",
    "sg:classifiers":[
        {
            "category":"Organizations",
            "subcategory":"Religious Organization",
            "type":"Services"
        }
    ],
    "sg:phone":"+1 856 933 1965",
    "sg:postcode":"08031",
    "sg:province":"NJ",
    "wof:name":"Bellmawr Baptist Church",
    "wof:placetype":"venue"
},
  "geometry": {"coordinates":[-75.096828,39.865691],"type":"Point"}
}