{
  "type": "Feature",
  "properties": {
    "iso:country":"US",
    "sg:address":"15 Tiger Lily Ct",
    "sg:city":"Sayreville",
    "sg:classifiers":[
        {
            "category":"Professional",
            "subcategory":"Management & Consulting",
            "type":"Services"
        }
    ],
    "sg:phone":"+1   ",
    "sg:postcode":"08872",
    "sg:province":"NJ",
    "sg:tags":[
        "business"
    ],
    "wof:name":"Niji Consulting Company",
    "wof:placetype":"venue"
},
  "geometry": {"coordinates":[-74.334149,40.470797],"type":"Point"}
}