{
  "type": "Feature",
  "properties": {
    "addr:full":"21 Phyllis Dr Succasunna NJ 07876",
    "addr:housenumber":"21",
    "addr:postcode":"07876",
    "addr:street":"Phyllis Dr",
    "iso:country":"US",
    "sg:address":"21 Phyllis Dr",
    "sg:city":"Succasunna",
    "sg:classifiers":[
        {
            "category":"Professional",
            "subcategory":"Business Services",
            "type":"Services"
        }
    ],
    "sg:phone":"+1 973 927 1770",
    "sg:postcode":"07876",
    "sg:province":"NJ",
    "sg:tags":[
        "appraiser"
    ],
    "wof:name":"Clifford Appraisals",
    "wof:placetype":"venue"
},
  "geometry": {"coordinates":[-74.681293,40.841104],"type":"Point"}
}