{
  "type": "Feature",
  "properties": {
    "addr:full":"2169 Hidden Brook Dr Wall Township NJ 07719",
    "addr:housenumber":"2169",
    "addr:postcode":"07719",
    "addr:street":"Hidden Brook Dr Wall",
    "iso:country":"US",
    "sg:address":"2169 Hidden Brook Dr",
    "sg:city":"Wall Township",
    "sg:classifiers":[
        {
            "category":"Building & Trades",
            "subcategory":"Construction",
            "type":"Services"
        }
    ],
    "sg:phone":"+1 732 974 0520",
    "sg:postcode":"07719",
    "sg:province":"NJ",
    "sg:tags":[
        "restoration",
        "cleaning",
        "patio",
        "deck"
    ],
    "wof:name":"South Monmouth Painting",
    "wof:placetype":"venue"
},
  "geometry": {"coordinates":[-74.077624,40.140632],"type":"Point"}
}