{
  "type": "Feature",
  "properties": {
    "iso:country":"US",
    "sg:address":"437 Summit St",
    "sg:city":"Englewood Cliffs",
    "sg:classifiers":[
        {
            "category":"Professional",
            "subcategory":"Management & Consulting",
            "type":"Services"
        }
    ],
    "sg:phone":"+1 201 568 8346",
    "sg:postcode":"07632",
    "sg:province":"NJ",
    "sg:tags":[
        "marketing",
        "consultant"
    ],
    "wof:name":"Production Co",
    "wof:placetype":"venue"
},
  "geometry": {"coordinates":[-73.95911099999999,40.879072],"type":"Point"}
}