{
  "type": "Feature",
  "properties": {
    "iso:country":"US",
    "sg:address":"87 Chestnut St",
    "sg:city":"Montclair",
    "sg:classifiers":[
        {
            "category":"Professional",
            "subcategory":"Business Services",
            "type":"Services"
        }
    ],
    "sg:phone":"+1   ",
    "sg:postcode":"07042",
    "sg:province":"NJ",
    "wof:name":"Lasiter Design",
    "wof:placetype":"venue"
},
  "geometry": {"coordinates":[-74.212276,40.821862],"type":"Point"}
}