{
  "type": "Feature",
  "properties": {
    "addr:full":"18 Bank St Morristown NJ 07960",
    "addr:housenumber":"18",
    "addr:postcode":"07960",
    "addr:street":"Bank St",
    "iso:country":"US",
    "sg:address":"18 Bank St",
    "sg:city":"Morristown",
    "sg:classifiers":[
        {
            "category":"Banks & Credit Unions",
            "subcategory":"Bank",
            "type":"Services"
        }
    ],
    "sg:phone":"+1 973 889 3580",
    "sg:postcode":"07960",
    "sg:province":"NJ",
    "sg:tags":[
        "loan",
        "real estate"
    ],
    "wof:name":"Wells Fargo Home Mortgage",
    "wof:placetype":"venue"
},
  "geometry": {"coordinates":[-74.482697,40.796183],"type":"Point"}
}