{
  "type": "Feature",
  "properties": {
    "iso:country":"US",
    "sg:address":"28 Main St",
    "sg:city":"Helmetta",
    "sg:classifiers":[
        {
            "category":"Professional",
            "type":"Services"
        }
    ],
    "sg:phone":"+1   ",
    "sg:postcode":"08804",
    "sg:province":"NJ",
    "wof:name":"Spring Inc",
    "wof:placetype":"venue"
},
  "geometry": {"coordinates":[-75.085849,40.654506],"type":"Point"}
}