{
  "type": "Feature",
  "properties": {
    "addr:full":"119 Somerset St New Brunswick NJ 08901",
    "addr:housenumber":"119",
    "addr:postcode":"08901",
    "addr:street":"Somerset St",
    "iso:country":"US",
    "sg:address":"119 Somerset St",
    "sg:city":"New Brunswick",
    "sg:classifiers":[
        {
            "category":"Professional",
            "subcategory":"Printing & Photocopies",
            "type":"Services"
        }
    ],
    "sg:phone":"+1 732 214 8787",
    "sg:postcode":"08901",
    "sg:province":"NJ",
    "sg:tags":[
        "photocopying"
    ],
    "wof:name":"Pequod Copy",
    "wof:placetype":"venue"
},
  "geometry": {"coordinates":[-74.44905799999999,40.496796],"type":"Point"}
}