{
  "type": "Feature",
  "properties": {
    "iso:country":"US",
    "sg:address":"109 Wilson St",
    "sg:city":"Nutley",
    "sg:classifiers":[
        {
            "category":"Building & Trades",
            "subcategory":"Construction",
            "type":"Services"
        }
    ],
    "sg:phone":"+1 973 661 4009",
    "sg:postcode":"07110",
    "sg:province":"NJ",
    "sg:tags":[
        "contractor"
    ],
    "wof:name":"Patty Drywall & Son",
    "wof:placetype":"venue"
},
  "geometry": {"coordinates":[-74.175202,40.812352],"type":"Point"}
}