{
  "type": "Feature",
  "properties": {
    "iso:country":"US",
    "sg:address":"80 Walman Ave",
    "sg:city":"Clifton",
    "sg:classifiers":[
        {
            "category":"Building & Trades",
            "subcategory":"Construction",
            "type":"Services"
        }
    ],
    "sg:phone":"+1 973 253 8734",
    "sg:postcode":"07011",
    "sg:province":"NJ",
    "sg:tags":[
        "house"
    ],
    "wof:name":"Vigor Construction",
    "wof:placetype":"venue"
},
  "geometry": {"coordinates":[-74.162601,40.882234],"type":"Point"}
}