{
  "type": "Feature",
  "properties": {
    "iso:country":"US",
    "sg:address":"110 Marter Ave",
    "sg:city":"Moorestown",
    "sg:classifiers":[
        {
            "category":"Real Estate",
            "subcategory":"Real Estate Agent",
            "type":"Services"
        }
    ],
    "sg:phone":"+1   ",
    "sg:postcode":"08057",
    "sg:province":"NJ",
    "wof:name":"Joanne Melton",
    "wof:placetype":"venue"
},
  "geometry": {"coordinates":[-74.922189,39.972415],"type":"Point"}
}