{
  "type": "Feature",
  "properties": {
    "addr:full":"10 South St Morristown NJ 07961",
    "addr:housenumber":"10",
    "addr:postcode":"07961",
    "addr:street":"South St",
    "iso:country":"US",
    "sg:address":"10 South St",
    "sg:city":"Morristown",
    "sg:classifiers":[
        {
            "category":"Restaurant",
            "type":"Food & Drink"
        }
    ],
    "sg:phone":"+1 973 971 9933",
    "sg:postcode":"07961",
    "sg:province":"NJ",
    "sg:tags":[
        "thai",
        "french"
    ],
    "sg:website":"www.originthai.com",
    "wof:name":"Origin French Thai II",
    "wof:placetype":"venue"
},
  "geometry": {"coordinates":[-74.467887,40.782503],"type":"Point"}
}