{
  "type": "Feature",
  "properties": {
    "iso:country":"US",
    "sg:address":"32 Monroe Blvd",
    "sg:city":"Monroe Twp",
    "sg:classifiers":[
        {
            "category":"Banks & Credit Unions",
            "subcategory":"Investment Brokerage",
            "type":"Services"
        }
    ],
    "sg:phone":"+1 732 446 5333",
    "sg:postcode":"08831",
    "sg:province":"NJ",
    "sg:tags":[
        "commodity"
    ],
    "wof:name":"C J Nesti Material",
    "wof:placetype":"venue"
},
  "geometry": {"coordinates":[-74.393996,40.302102],"type":"Point"}
}