{
  "type": "Feature",
  "properties": {
    "iso:country":"US",
    "sg:address":"845 Becker Dr",
    "sg:city":"Vineland",
    "sg:classifiers":[
        {
            "category":"Building & Trades",
            "subcategory":"Construction",
            "type":"Services"
        }
    ],
    "sg:phone":"+1 856 794 8520",
    "sg:postcode":"08361",
    "sg:province":"NJ",
    "sg:tags":[
        "house",
        "home",
        "improvement",
        "residential"
    ],
    "wof:name":"Antro Builders Inc",
    "wof:placetype":"venue"
},
  "geometry": {"coordinates":[-74.98902099999999,39.494355],"type":"Point"}
}