{
  "type": "Feature",
  "properties": {
    "iso:country":"US",
    "sg:address":"246 Washington Ave",
    "sg:city":"Belleville",
    "sg:classifiers":[
        {
            "category":"Real Estate",
            "subcategory":"Real Estate Agent",
            "type":"Services"
        }
    ],
    "sg:phone":"+1 973 751 0122",
    "sg:postcode":"07109",
    "sg:province":"NJ",
    "wof:name":"Anthony M De George",
    "wof:placetype":"venue"
},
  "geometry": {"coordinates":[-74.15246500000001,40.788584],"type":"Point"}
}