{
  "type": "Feature",
  "properties": {
    "iso:country":"US",
    "sg:address":"181 Hillside Ave",
    "sg:city":"Piscataway",
    "sg:classifiers":[
        {
            "category":"Professional",
            "subcategory":"Management & Consulting",
            "type":"Services"
        }
    ],
    "sg:phone":"+1 732 463 3918",
    "sg:postcode":"08854",
    "sg:province":"NJ",
    "sg:tags":[
        "consultant",
        "business"
    ],
    "wof:name":"Back Office Support Services",
    "wof:placetype":"venue"
},
  "geometry": {"coordinates":[-74.492018,40.534881],"type":"Point"}
}