{
  "type": "Feature",
  "properties": {
    "addr:full":"7 Highland Pl Maplewood NJ 07040",
    "addr:housenumber":"7",
    "addr:postcode":"07040",
    "addr:street":"Highland Pl",
    "iso:country":"US",
    "sg:address":"7 Highland Pl",
    "sg:city":"Maplewood",
    "sg:classifiers":[
        {
            "category":"Insurance",
            "subcategory":"Insurance Agent",
            "type":"Services"
        }
    ],
    "sg:phone":"+1   ",
    "sg:postcode":"07040",
    "sg:province":"NJ",
    "wof:name":"State Farm Insurance",
    "wof:placetype":"venue"
},
  "geometry": {"coordinates":[-74.279184,40.731417],"type":"Point"}
}