{
  "type": "Feature",
  "properties": {
    "iso:country":"US",
    "sg:address":"1460 Hurffville Rd",
    "sg:city":"Woodbury",
    "sg:classifiers":[
        {
            "category":"Professional",
            "subcategory":"Computer Services",
            "type":"Services"
        }
    ],
    "sg:phone":"+1 856 374 0277",
    "sg:postcode":"08096",
    "sg:province":"NJ",
    "wof:name":"Axis Computer Svc",
    "wof:placetype":"venue"
},
  "geometry": {"coordinates":[-75.092899,39.811684],"type":"Point"}
}