{
  "type": "Feature",
  "properties": {
    "iso:country":"US",
    "sg:address":"184 Outwater Ln",
    "sg:city":"Garfield",
    "sg:classifiers":[
        {
            "category":"Shopping",
            "subcategory":"Computers & Home Electronics",
            "type":"Retail Goods"
        }
    ],
    "sg:phone":"+1   ",
    "sg:postcode":"07026",
    "sg:province":"NJ",
    "wof:name":"Dale Computer Services",
    "wof:placetype":"venue"
},
  "geometry": {"coordinates":[-74.110242,40.882034],"type":"Point"}
}