{
  "type": "Feature",
  "properties": {
    "iso:country":"US",
    "sg:address":"159 Arthur St",
    "sg:city":"Ridgefield Park",
    "sg:classifiers":[
        {
            "category":"Organizations",
            "subcategory":"Religious Organization",
            "type":"Services"
        }
    ],
    "sg:phone":"+1   ",
    "sg:postcode":"07660",
    "sg:province":"NJ",
    "wof:name":"Mt Carmel Investment Club LLC",
    "wof:placetype":"venue"
},
  "geometry": {"coordinates":[-74.016132,40.864373],"type":"Point"}
}