{
  "type": "Feature",
  "properties": {
    "addr:full":"209 Oak Ridge Rd Oak Ridge NJ 07438",
    "addr:housenumber":"209",
    "addr:postcode":"07438",
    "addr:street":"Oak Ridge Rd",
    "iso:country":"US",
    "sg:address":"209 Oak Ridge Rd",
    "sg:city":"Oak Ridge",
    "sg:classifiers":[
        {
            "category":"Retail",
            "subcategory":"Auto Repair",
            "type":"Services"
        }
    ],
    "sg:phone":"+1 973 697 7009",
    "sg:postcode":"07438",
    "sg:province":"NJ",
    "sg:tags":[
        "repairing",
        "automobile",
        "general"
    ],
    "wof:name":"Tim's Auto",
    "wof:placetype":"venue"
},
  "geometry": {"coordinates":[-74.476887,41.051233],"type":"Point"}
}