{
  "type": "Feature",
  "properties": {
    "addr:full":"327 Main St Paterson NJ 07505",
    "addr:housenumber":"327",
    "addr:postcode":"07505",
    "addr:street":"Main St",
    "iso:country":"US",
    "sg:address":"327 Main St",
    "sg:city":"Paterson",
    "sg:classifiers":[
        {
            "category":"Personal",
            "subcategory":"Beauty Salon",
            "type":"Services"
        }
    ],
    "sg:phone":"+1 973 977 9607",
    "sg:postcode":"07505",
    "sg:province":"NJ",
    "sg:tags":[
        "shop"
    ],
    "wof:name":"Gapos Hair Crew",
    "wof:placetype":"venue"
},
  "geometry": {"coordinates":[-74.173394,40.914612],"type":"Point"}
}