{
  "type": "Feature",
  "properties": {
    "iso:country":"US",
    "sg:address":"28 Burnet St",
    "sg:city":"Newark",
    "sg:classifiers":[
        {
            "category":"Education",
            "subcategory":"School",
            "type":"Public Place"
        }
    ],
    "sg:phone":"+1 973 733 7138",
    "sg:postcode":"07102",
    "sg:province":"NJ",
    "wof:name":"Newark Public Schools",
    "wof:placetype":"venue"
},
  "geometry": {"coordinates":[-74.173238,40.746553],"type":"Point"}
}