{
  "type": "Feature",
  "properties": {
    "iso:country":"US",
    "sg:address":"75 Court St",
    "sg:city":"Paterson",
    "sg:classifiers":[
        {
            "category":"Wholesale",
            "subcategory":"Apparel",
            "type":"Manufacturing & Wholesale Goods"
        },
        {
            "category":"Manufacturing",
            "subcategory":"Textiles",
            "type":"Manufacturing & Wholesale Goods"
        }
    ],
    "sg:phone":"+1 973 247 1120",
    "sg:postcode":"07503",
    "sg:province":"NJ",
    "wof:name":"New Venezia Textile Inc",
    "wof:placetype":"venue"
},
  "geometry": {"coordinates":[-74.166359,40.899078],"type":"Point"}
}