{
  "type": "Feature",
  "properties": {
    "iso:country":"US",
    "sg:address":"14 Sheryl Dr",
    "sg:city":"Edison",
    "sg:classifiers":[
        {
            "category":"Building & Trades",
            "subcategory":"Landscaping Services",
            "type":"Services"
        }
    ],
    "sg:phone":"+1 732 388 5100",
    "sg:postcode":"08820",
    "sg:province":"NJ",
    "sg:tags":[
        "landscape"
    ],
    "wof:name":"Dreamdesign Landscaping",
    "wof:placetype":"venue"
},
  "geometry": {"coordinates":[-74.343609,40.60487],"type":"Point"}
}