{
  "type": "Feature",
  "properties": {
    "addr:full":"34 Olev Dr Jackson NJ 08527",
    "addr:housenumber":"34",
    "addr:postcode":"08527",
    "addr:street":"Olev Dr",
    "iso:country":"US",
    "sg:address":"34 Olev Dr",
    "sg:city":"Jackson",
    "sg:classifiers":[
        {
            "category":"Professional",
            "subcategory":"Advertising",
            "type":"Services"
        }
    ],
    "sg:phone":"+1 732 928 3530",
    "sg:postcode":"08527",
    "sg:province":"NJ",
    "wof:name":"Total Confusion LLC",
    "wof:placetype":"venue"
},
  "geometry": {"coordinates":[-74.303292,40.120369],"type":"Point"}
}