{
  "type": "Feature",
  "properties": {
    "addr:full":"10 Washington St Bridgeton NJ 08302",
    "addr:housenumber":"10",
    "addr:postcode":"08302",
    "addr:street":"Washington St",
    "iso:country":"US",
    "sg:address":"10 Washington St",
    "sg:city":"Bridgeton",
    "sg:classifiers":[
        {
            "category":"Social Services",
            "subcategory":"Child Care",
            "type":"Services"
        }
    ],
    "sg:phone":"+1   ",
    "sg:postcode":"08302",
    "sg:province":"NJ",
    "sg:tags":[
        "day"
    ],
    "wof:name":"Test City Child Center",
    "wof:placetype":"venue"
},
  "geometry": {"coordinates":[-75.235224,39.431521],"type":"Point"}
}