{
  "type": "Feature",
  "properties": {
    "iso:country":"US",
    "sg:address":"444 State Rte 79",
    "sg:city":"Morganville",
    "sg:classifiers":[
        {
            "category":"Building & Trades",
            "subcategory":"Construction",
            "type":"Services"
        }
    ],
    "sg:phone":"+1 732 970 0777",
    "sg:postcode":"07751",
    "sg:province":"NJ",
    "sg:tags":[
        "driveway"
    ],
    "wof:name":"Driveway Armor",
    "wof:placetype":"venue"
},
  "geometry": {"coordinates":[-74.24343,40.378627],"type":"Point"}
}