{
  "type": "Feature",
  "properties": {
    "iso:country":"US",
    "sg:address":"339 Fairview Ave",
    "sg:city":"Westwood",
    "sg:classifiers":[
        {
            "category":"Manufacturing",
            "subcategory":"Printing",
            "type":"Manufacturing & Wholesale Goods"
        }
    ],
    "sg:phone":"+1 201 358 0038",
    "sg:postcode":"07675",
    "sg:province":"NJ",
    "sg:tags":[
        "commercial"
    ],
    "wof:name":"Kristofick Enterprises",
    "wof:placetype":"venue"
},
  "geometry": {"coordinates":[-74.031195,40.993066],"type":"Point"}
}