{
  "type": "Feature",
  "properties": {
    "iso:country":"US",
    "sg:address":"5900 Bergenline Pl",
    "sg:city":"West New York",
    "sg:classifiers":[
        {
            "category":"Utilities",
            "subcategory":"Mobile Phone",
            "type":"Services"
        }
    ],
    "sg:phone":"+1 201 854 3100",
    "sg:postcode":"07093",
    "sg:province":"NJ",
    "sg:tags":[
        "communication",
        "radiotelephone"
    ],
    "wof:name":"Clair Telecommunications",
    "wof:placetype":"venue"
},
  "geometry": {"coordinates":[-74.016729,40.788345],"type":"Point"}
}