{
  "type": "Feature",
  "properties": {
    "addr:full":"717 Westfield Ave Elizabeth NJ 07208",
    "addr:housenumber":"717",
    "addr:postcode":"07208",
    "addr:street":"Westfield Ave",
    "iso:country":"US",
    "sg:address":"717 Westfield Ave",
    "sg:city":"Elizabeth",
    "sg:classifiers":[
        {
            "category":"Health Services",
            "subcategory":"Doctor",
            "type":"Services"
        }
    ],
    "sg:phone":"+1 908 353 7500",
    "sg:postcode":"07208",
    "sg:province":"NJ",
    "sg:tags":[
        "physician",
        "surgeon"
    ],
    "wof:name":"J M Arrunategui MD",
    "wof:placetype":"venue"
},
  "geometry": {"coordinates":[-74.23875099999999,40.665169],"type":"Point"}
}