{
  "type": "Feature",
  "properties": {
    "iso:country":"US",
    "sg:address":"700 Springfield Ave",
    "sg:city":"Berkeley Heights",
    "sg:classifiers":[
        {
            "category":"Wholesale",
            "subcategory":"Home Furnishings",
            "type":"Manufacturing & Wholesale Goods"
        },
        {
            "category":"Home & Garden",
            "subcategory":"Carpets & Floor Coverings",
            "type":"Retail Goods"
        }
    ],
    "sg:phone":"+1 908 665 2424",
    "sg:postcode":"07922",
    "sg:province":"NJ",
    "sg:tags":[
        "blind",
        "shade",
        "carpeting"
    ],
    "wof:name":"Eagle Tile & Carpet",
    "wof:placetype":"venue"
},
  "geometry": {"coordinates":[-74.449303,40.680698],"type":"Point"}
}