{
  "type": "Feature",
  "properties": {
    "addr:full":"439 Quaker Church Rd Randolph NJ 07869",
    "addr:housenumber":"439",
    "addr:postcode":"07869",
    "addr:street":"Quaker Church Rd",
    "iso:country":"US",
    "sg:address":"439 Quaker Church Rd",
    "sg:city":"Randolph",
    "sg:classifiers":[
        {
            "category":"Organizations",
            "subcategory":"Religious Organization",
            "type":"Services"
        }
    ],
    "sg:phone":"+1 973 361 3243",
    "sg:postcode":"07869",
    "sg:province":"NJ",
    "sg:tags":[
        "clergy"
    ],
    "wof:name":"Diane R Gilbert",
    "wof:placetype":"venue"
},
  "geometry": {"coordinates":[-74.585319,40.866665],"type":"Point"}
}