{
  "type": "Feature",
  "properties": {
    "iso:country":"US",
    "sg:address":"42 Summit Ave",
    "sg:city":"Hackensack",
    "sg:classifiers":[
        {
            "category":"Health Services",
            "subcategory":"Dentist",
            "type":"Services"
        }
    ],
    "sg:phone":"+1 201 487 1135",
    "sg:postcode":"07601",
    "sg:province":"NJ",
    "wof:name":"Drozd Edward B DMD",
    "wof:placetype":"venue"
},
  "geometry": {"coordinates":[-74.057602,40.887901],"type":"Point"}
}