{
  "type": "Feature",
  "properties": {
    "addr:full":"77 Oceanport Ave West Long Branch NJ 07764",
    "addr:housenumber":"77",
    "addr:postcode":"07764",
    "addr:street":"Oceanport Ave West",
    "iso:country":"US",
    "sg:address":"77 Oceanport Ave",
    "sg:city":"West Long Branch",
    "sg:classifiers":[
        {
            "category":"Retail",
            "subcategory":"Auto Rental",
            "type":"Services"
        }
    ],
    "sg:phone":"+1 732 571 6995",
    "sg:postcode":"07764",
    "sg:province":"NJ",
    "sg:tags":[
        "trailer",
        "utility"
    ],
    "wof:name":"U-Haul",
    "wof:placetype":"venue"
},
  "geometry": {"coordinates":[-74.014433,40.303435],"type":"Point"}
}