{
  "type": "Feature",
  "properties": {
    "addr:full":"150 River Rd Montville NJ 07045",
    "addr:housenumber":"150",
    "addr:postcode":"07045",
    "addr:street":"River Rd",
    "iso:country":"US",
    "sg:address":"150 River Rd",
    "sg:city":"Montville",
    "sg:classifiers":[
        {
            "category":"Professional",
            "subcategory":"Accounting & Tax Preparation",
            "type":"Services"
        }
    ],
    "sg:phone":"+1 973 331 0800",
    "sg:postcode":"07045",
    "sg:province":"NJ",
    "sg:tags":[
        "accountant"
    ],
    "wof:name":"Loffredo & Assoc",
    "wof:placetype":"venue"
},
  "geometry": {"coordinates":[-74.374298,40.9007],"type":"Point"}
}