{
  "type": "Feature",
  "properties": {
    "iso:country":"US",
    "sg:address":"1022 W Browning Rd",
    "sg:city":"Bellmawr",
    "sg:classifiers":[
        {
            "category":"Professional",
            "subcategory":"Management & Consulting",
            "type":"Services"
        }
    ],
    "sg:phone":"+1 856 933 3342",
    "sg:postcode":"08031",
    "sg:province":"NJ",
    "sg:tags":[
        "podiatrist",
        "business"
    ],
    "wof:name":"Fortuna Amedeo",
    "wof:placetype":"venue"
},
  "geometry": {"coordinates":[-75.110001,39.876301],"type":"Point"}
}