{
  "type": "Feature",
  "properties": {
    "addr:full":"467 Valley St Maplewood NJ 07040",
    "addr:housenumber":"467",
    "addr:postcode":"07040",
    "addr:street":"Valley St",
    "iso:country":"US",
    "sg:address":"467 Valley St",
    "sg:city":"Maplewood",
    "sg:classifiers":[
        {
            "category":"Health Services",
            "subcategory":"Doctor",
            "type":"Services"
        }
    ],
    "sg:phone":"+1 973 763 3300",
    "sg:postcode":"07040",
    "sg:province":"NJ",
    "sg:tags":[
        "physician",
        "surgeon"
    ],
    "wof:name":"Charles Steiner DO",
    "wof:placetype":"venue"
},
  "geometry": {"coordinates":[-74.26717600000001,40.736541],"type":"Point"}
}