{
  "type": "Feature",
  "properties": {
    "iso:country":"US",
    "sg:address":"33 Overlook Rd Ste 303",
    "sg:city":"Summit",
    "sg:classifiers":[
        {
            "category":"Health Services",
            "subcategory":"Doctor",
            "type":"Services"
        }
    ],
    "sg:phone":"+1 908 522 1000",
    "sg:postcode":"07901",
    "sg:province":"NJ",
    "wof:name":"Iuzzolino Anthony MD",
    "wof:placetype":"venue"
},
  "geometry": {"coordinates":[-74.351601,40.712898],"type":"Point"}
}