{
  "type": "Feature",
  "properties": {
    "addr:full":"164 Page St Elmwood Park NJ 07407",
    "addr:housenumber":"164",
    "addr:postcode":"07407",
    "addr:street":"Page St",
    "iso:country":"US",
    "sg:address":"164 Page St",
    "sg:city":"Elmwood Park",
    "sg:classifiers":[
        {
            "category":"Building & Trades",
            "subcategory":"Plumbing",
            "type":"Services"
        }
    ],
    "sg:phone":"+1 201 791 6133",
    "sg:postcode":"07407",
    "sg:province":"NJ",
    "sg:website":"www.thekgplumbingheating.com",
    "wof:name":"K & G Plumbing & Heating",
    "wof:placetype":"venue"
},
  "geometry": {"coordinates":[-74.11815900000001,40.890795],"type":"Point"}
}