{
  "type": "Feature",
  "properties": {
    "addr:full":"2225 Bridge Ave Pt Pleasant Boro NJ 08742",
    "addr:housenumber":"2225",
    "addr:postcode":"08742",
    "addr:street":"Bridge Ave Pt",
    "iso:country":"US",
    "sg:address":"2225 Bridge Ave",
    "sg:city":"Pt Pleasant Boro",
    "sg:classifiers":[
        {
            "category":"Food & Beverages",
            "subcategory":"Groceries & Convenience Stores",
            "type":"Retail Goods"
        }
    ],
    "sg:phone":"+1 732 714 7300",
    "sg:postcode":"08742",
    "sg:province":"NJ",
    "sg:tags":[
        "grocer"
    ],
    "wof:name":"Hometown Market",
    "wof:placetype":"venue"
},
  "geometry": {"coordinates":[-74.06797,40.071906],"type":"Point"}
}