{
  "type": "Feature",
  "properties": {
    "iso:country":"US",
    "sg:address":"16 Wright Way",
    "sg:city":"Oakland",
    "sg:classifiers":[
        {
            "category":"Education",
            "subcategory":"Music School",
            "type":"Public Place"
        }
    ],
    "sg:phone":"+1 201 337 1290",
    "sg:postcode":"07436",
    "sg:province":"NJ",
    "sg:tags":[
        "instrument",
        "teacher",
        "musical"
    ],
    "wof:name":"American Musical Supply",
    "wof:placetype":"venue"
},
  "geometry": {"coordinates":[-74.247714,41.005812],"type":"Point"}
}