{
  "type": "Feature",
  "properties": {
    "iso:country":"US",
    "sg:address":"318 Madison St",
    "sg:city":"Carlstadt",
    "sg:classifiers":[
        {
            "category":"Building & Trades",
            "subcategory":"Construction",
            "type":"Services"
        }
    ],
    "sg:phone":"+1 201 460 1227",
    "sg:postcode":"07072",
    "sg:province":"NJ",
    "sg:tags":[
        "contractor"
    ],
    "wof:name":"All World Construction",
    "wof:placetype":"venue"
},
  "geometry": {"coordinates":[-74.097042,40.839175],"type":"Point"}
}