{
  "type": "Feature",
  "properties": {
    "addr:full":"1200 Wall St W Lyndhurst NJ 07071",
    "addr:housenumber":"1200",
    "addr:postcode":"07071",
    "addr:street":"Wall St W",
    "iso:country":"US",
    "sg:address":"1200 Wall St W",
    "sg:city":"Lyndhurst",
    "sg:classifiers":[
        {
            "category":"Insurance",
            "subcategory":"Insurance Agent",
            "type":"Services"
        }
    ],
    "sg:phone":"+1 201 460 7077",
    "sg:postcode":"07071",
    "sg:province":"NJ",
    "wof:name":"Personal Lines Ins Brokerage",
    "wof:placetype":"venue"
},
  "geometry": {"coordinates":[-74.103627,40.806257],"type":"Point"}
}