{
  "type": "Feature",
  "properties": {
    "addr:full":"3 Wayside Ln Lebanon NJ 08833",
    "addr:housenumber":"3",
    "addr:postcode":"08833",
    "addr:street":"Wayside Ln",
    "iso:country":"US",
    "sg:address":"3 Wayside Ln",
    "sg:city":"Lebanon",
    "sg:classifiers":[
        {
            "category":"Manufacturing",
            "subcategory":"Tools & Machinery",
            "type":"Manufacturing & Wholesale Goods"
        }
    ],
    "sg:phone":"+1 908 437 4170",
    "sg:postcode":"08833",
    "sg:province":"NJ",
    "sg:tags":[
        "equipment",
        "mfg"
    ],
    "wof:name":"Stellex Precision Machining",
    "wof:placetype":"venue"
},
  "geometry": {"coordinates":[-74.79883599999999,40.647083],"type":"Point"}
}