{
  "type": "Feature",
  "properties": {
    "iso:country":"US",
    "sg:address":"10000 Lincoln Dr W",
    "sg:city":"Marlton",
    "sg:classifiers":[
        {
            "category":"Professional",
            "subcategory":"Lawyer & Legal Services",
            "type":"Services"
        }
    ],
    "sg:phone":"+1 856 797 9090",
    "sg:postcode":"08053",
    "sg:province":"NJ",
    "sg:tags":[
        "attorney"
    ],
    "wof:name":"Joseph Chaiken Law Firm",
    "wof:placetype":"venue"
},
  "geometry": {"coordinates":[-74.935609,39.902434],"type":"Point"}
}