{
  "type": "Feature",
  "properties": {
    "iso:country":"US",
    "sg:address":"635 Heron Dr",
    "sg:city":"Swedesboro",
    "sg:classifiers":[
        {
            "category":"Professional",
            "type":"Services"
        }
    ],
    "sg:phone":"+1 856 467 5246",
    "sg:postcode":"08085",
    "sg:province":"NJ",
    "sg:tags":[
        "establishment"
    ],
    "wof:name":"Heron Technologies",
    "wof:placetype":"venue"
},
  "geometry": {"coordinates":[-75.359719,39.766765],"type":"Point"}
}