{
  "type": "Feature",
  "properties": {
    "addr:full":"22 Pitman Ave Pitman NJ 08071",
    "addr:housenumber":"22",
    "addr:postcode":"08071",
    "addr:street":"Pitman Ave",
    "iso:country":"US",
    "sg:address":"22 Pitman Ave",
    "sg:city":"Pitman",
    "sg:classifiers":[
        {
            "category":"Restaurant",
            "type":"Food & Drink"
        }
    ],
    "sg:phone":"+1 856 589 6161",
    "sg:postcode":"08071",
    "sg:province":"NJ",
    "sg:tags":[
        "eating"
    ],
    "wof:name":"Ming Lok Chinese Restaurant",
    "wof:placetype":"venue"
},
  "geometry": {"coordinates":[-75.12956699999999,39.731796],"type":"Point"}
}