{
  "type": "Feature",
  "properties": {
    "addr:full":"441 Nassau Park Blvd Princeton NJ 08540",
    "addr:housenumber":"441",
    "addr:postcode":"08540",
    "addr:street":"Nassau Park Blvd",
    "iso:country":"US",
    "sg:address":"441 Nassau Park Blvd",
    "sg:city":"Princeton",
    "sg:classifiers":[
        {
            "category":"Personal",
            "subcategory":"Beauty Salon",
            "type":"Services"
        },
        {
            "category":"Personal",
            "subcategory":"Barber",
            "type":"Services"
        }
    ],
    "sg:phone":"+1 609 750 1777",
    "sg:postcode":"08540",
    "sg:province":"NJ",
    "sg:tags":[
        "hair",
        "accessory",
        "stylist",
        "supply"
    ],
    "sg:website":"http://www.greatclips.com",
    "wof:name":"Great Clips",
    "wof:placetype":"venue"
},
  "geometry": {"coordinates":[-74.678017,40.304589],"type":"Point"}
}