{
  "type": "Feature",
  "properties": {
    "addr:full":"140 Summit Ave Montclair NJ 07043",
    "addr:housenumber":"140",
    "addr:postcode":"07043",
    "addr:street":"Summit Ave",
    "iso:country":"US",
    "sg:address":"140 Summit Ave",
    "sg:city":"Montclair",
    "sg:classifiers":[
        {
            "category":"Professional",
            "subcategory":"Engineering",
            "type":"Services"
        }
    ],
    "sg:phone":"+1 973 746 6471",
    "sg:postcode":"07043",
    "sg:province":"NJ",
    "wof:name":"RAD Design Engineering",
    "wof:placetype":"venue"
},
  "geometry": {"coordinates":[-74.19801699999999,40.836118],"type":"Point"}
}