{
  "type": "Feature",
  "properties": {
    "iso:country":"US",
    "sg:address":"379 Bloomfield Ave",
    "sg:city":"Caldwell",
    "sg:classifiers":[
        {
            "category":"Bars & Pubs",
            "type":"Food & Drink"
        }
    ],
    "sg:phone":"+1 973 226 6781",
    "sg:postcode":"07006",
    "sg:province":"NJ",
    "sg:website":"www.ringsidepub.com",
    "wof:name":"Ringside Pub",
    "wof:placetype":"venue"
},
  "geometry": {"coordinates":[-74.278198,40.840801],"type":"Point"}
}