{
  "type": "Feature",
  "properties": {
    "iso:country":"US",
    "sg:address":"525 Washington Blvd",
    "sg:city":"Jersey City",
    "sg:classifiers":[
        {
            "category":"Food & Beverages",
            "subcategory":"Bakery",
            "type":"Retail Goods"
        }
    ],
    "sg:phone":"+1 201 659 6668",
    "sg:postcode":"07310",
    "sg:province":"NJ",
    "sg:tags":[
        "baker"
    ],
    "wof:name":"Seattle Coffee Roasters",
    "wof:placetype":"venue"
},
  "geometry": {"coordinates":[-74.034564,40.729988],"type":"Point"}
}