{
  "type": "Feature",
  "properties": {
    "iso:country":"US",
    "sg:address":"1337 West Blvd",
    "sg:city":"Newfield",
    "sg:classifiers":[
        {
            "category":"Professional",
            "subcategory":"Business Services",
            "type":"Services"
        }
    ],
    "sg:phone":"+1   ",
    "sg:postcode":"08344",
    "sg:province":"NJ",
    "wof:name":"Honor Title Agency of NJ",
    "wof:placetype":"venue"
},
  "geometry": {"coordinates":[-75.03395500000001,39.560159],"type":"Point"}
}