{
  "type": "Feature",
  "properties": {
    "iso:country":"US",
    "sg:address":"823 Jackson Ave",
    "sg:city":"Elizabeth",
    "sg:classifiers":[
        {
            "category":"Professional",
            "subcategory":"Management & Consulting",
            "type":"Services"
        }
    ],
    "sg:phone":"+1   ",
    "sg:postcode":"07201",
    "sg:province":"NJ",
    "sg:tags":[
        "transportation"
    ],
    "wof:name":"Ferry J Trucking Co",
    "wof:placetype":"venue"
},
  "geometry": {"coordinates":[-74.198505,40.679852],"type":"Point"}
}