{
  "type": "Feature",
  "properties": {
    "addr:full":"200 US Highway 46 Little Falls NJ 07424",
    "addr:housenumber":"200",
    "addr:postcode":"07424",
    "addr:street":"Us Highway 46",
    "iso:country":"US",
    "sg:address":"200 US Highway 46",
    "sg:city":"Little Falls",
    "sg:classifiers":[
        {
            "category":"Autos & Motor Vehicles",
            "subcategory":"Fuel & Gas Station",
            "type":"Retail Goods"
        }
    ],
    "sg:phone":"+1 973 256 2168",
    "sg:postcode":"07424",
    "sg:province":"NJ",
    "wof:name":"Ayvazian Corporation",
    "wof:placetype":"venue"
},
  "geometry": {"coordinates":[-74.205607,40.879817],"type":"Point"}
}