{
  "type": "Feature",
  "properties": {
    "addr:full":"5100 Arctic Ave Wildwood NJ 08260",
    "addr:housenumber":"5100",
    "addr:postcode":"08260",
    "addr:street":"Arctic Ave",
    "iso:country":"US",
    "sg:address":"5100 Arctic Ave",
    "sg:city":"Wildwood",
    "sg:classifiers":[
        {
            "category":"Building & Trades",
            "subcategory":"Construction",
            "type":"Services"
        }
    ],
    "sg:phone":"+1 609 729 6556",
    "sg:postcode":"08260",
    "sg:province":"NJ",
    "sg:tags":[
        "contractor"
    ],
    "wof:name":"Marzullo Ken Contractor",
    "wof:placetype":"venue"
},
  "geometry": {"coordinates":[-74.827904,38.984402],"type":"Point"}
}