{
  "type": "Feature",
  "properties": {
    "addr:full":"143 Walnut Ave Clark NJ 07066",
    "addr:housenumber":"143",
    "addr:postcode":"07066",
    "addr:street":"Walnut Ave",
    "iso:country":"US",
    "sg:address":"143 Walnut Ave",
    "sg:city":"Clark",
    "sg:classifiers":[
        {
            "category":"Wholesale",
            "subcategory":"Chemicals & Plastics",
            "type":"Manufacturing & Wholesale Goods"
        }
    ],
    "sg:phone":"+1 732 499 7347",
    "sg:postcode":"07066",
    "sg:province":"NJ",
    "sg:tags":[
        "product",
        "industrial",
        "janitorial"
    ],
    "wof:name":"Northstar Service & Supply",
    "wof:placetype":"venue"
},
  "geometry": {"coordinates":[-74.302542,40.631978],"type":"Point"}
}