{
  "type": "Feature",
  "properties": {
    "iso:country":"US",
    "sg:address":"219 Crown Point Rd",
    "sg:city":"Thorofare",
    "sg:classifiers":[
        {
            "category":"Building & Trades",
            "subcategory":"Landscaping Services",
            "type":"Services"
        }
    ],
    "sg:phone":"+1 856 423 2570",
    "sg:postcode":"08086",
    "sg:province":"NJ",
    "sg:tags":[
        "landscape",
        "contractor"
    ],
    "wof:name":"John's Landscaping & Lawn Svc",
    "wof:placetype":"venue"
},
  "geometry": {"coordinates":[-75.20171000000001,39.840624],"type":"Point"}
}