{
  "type": "Feature",
  "properties": {
    "addr:full":"270 Summit Ave Jersey City NJ 07306",
    "addr:housenumber":"270",
    "addr:postcode":"07306",
    "addr:street":"Summit Ave",
    "iso:country":"US",
    "sg:address":"270 Summit Ave",
    "sg:city":"Jersey City",
    "sg:classifiers":[
        {
            "category":"Building & Trades",
            "subcategory":"Construction",
            "type":"Services"
        }
    ],
    "sg:phone":"+1 201 435 8624",
    "sg:postcode":"07306",
    "sg:province":"NJ",
    "sg:tags":[
        "hanging",
        "contractor"
    ],
    "wof:name":"American Home Improvement",
    "wof:placetype":"venue"
},
  "geometry": {"coordinates":[-74.064623,40.724809],"type":"Point"}
}