{
  "type": "Feature",
  "properties": {
    "iso:country":"US",
    "sg:address":"637 Highland Ave",
    "sg:city":"Westville",
    "sg:classifiers":[
        {
            "category":"Building & Trades",
            "subcategory":"Construction",
            "type":"Services"
        }
    ],
    "sg:phone":"+1 856 456 4561",
    "sg:postcode":"08093",
    "sg:province":"NJ",
    "sg:tags":[
        "siding",
        "contractor"
    ],
    "wof:name":"Johnson's Roofing & Siding",
    "wof:placetype":"venue"
},
  "geometry": {"coordinates":[-75.1356,39.87707],"type":"Point"}
}