{
  "type": "Feature",
  "properties": {
    "addr:full":"213 Wanaque Ave Pompton Lakes NJ 07442",
    "addr:housenumber":"213",
    "addr:postcode":"07442",
    "addr:street":"Wanaque Ave",
    "iso:country":"US",
    "sg:address":"213 Wanaque Ave",
    "sg:city":"Pompton Lakes",
    "sg:classifiers":[
        {
            "category":"Professional",
            "type":"Services"
        },
        {
            "category":"Deli",
            "type":"Food & Drink"
        }
    ],
    "sg:phone":"+1 973 839 9291",
    "sg:postcode":"07442",
    "sg:province":"NJ",
    "sg:tags":[
        "caterer"
    ],
    "wof:name":"Town & Country Delicatessen & Catering",
    "wof:placetype":"venue"
},
  "geometry": {"coordinates":[-74.291496,41.005199],"type":"Point"}
}