{
  "type": "Feature",
  "properties": {
    "iso:country":"US",
    "sg:address":"84 Keasler Ave",
    "sg:city":"Lodi",
    "sg:classifiers":[
        {
            "category":"Travel",
            "subcategory":"Travel Agent",
            "type":"Entertainment"
        }
    ],
    "sg:phone":"+1 973 546 8200",
    "sg:postcode":"07644",
    "sg:province":"NJ",
    "sg:tags":[
        "agency"
    ],
    "wof:name":"Rennor Travel",
    "wof:placetype":"venue"
},
  "geometry": {"coordinates":[-74.08399900000001,40.885146],"type":"Point"}
}