{
  "type": "Feature",
  "properties": {
    "iso:country":"US",
    "sg:address":"586 Main Ave",
    "sg:city":"Passaic",
    "sg:classifiers":[
        {
            "category":"Personal",
            "subcategory":"Beauty Salon",
            "type":"Services"
        }
    ],
    "sg:phone":"+1 973 473 9005",
    "sg:postcode":"07055",
    "sg:province":"NJ",
    "sg:tags":[
        "hair",
        "shop"
    ],
    "wof:name":"Sylvia's Beauty Salon",
    "wof:placetype":"venue"
},
  "geometry": {"coordinates":[-74.123901,40.8587],"type":"Point"}
}