{
  "type": "Feature",
  "properties": {
    "iso:country":"US",
    "sg:address":"705 Blue Hill Rd",
    "sg:city":"Westwood",
    "sg:classifiers":[
        {
            "category":"Retail",
            "subcategory":"Auto Repair",
            "type":"Services"
        }
    ],
    "sg:phone":"+1 201 930 1419",
    "sg:postcode":"07675",
    "sg:province":"NJ",
    "sg:tags":[
        "general"
    ],
    "wof:name":"Franklin Auto Care LLC",
    "wof:placetype":"venue"
},
  "geometry": {"coordinates":[-74.004194,41.039139],"type":"Point"}
}