{
  "type": "Feature",
  "properties": {
    "addr:full":"194 Clinton Ave Newark NJ 07108",
    "addr:housenumber":"194",
    "addr:postcode":"07108",
    "addr:street":"Clinton Ave",
    "iso:country":"US",
    "sg:address":"194 Clinton Ave",
    "sg:city":"Newark",
    "sg:classifiers":[
        {
            "category":"Shopping",
            "subcategory":"Pharmacy",
            "type":"Retail Goods"
        }
    ],
    "sg:phone":"+1 973 273 1100",
    "sg:postcode":"07108",
    "sg:province":"NJ",
    "wof:name":"Bergen Pharmacy At Clinton Ave",
    "wof:placetype":"venue"
},
  "geometry": {"coordinates":[-74.18560100000001,40.723758],"type":"Point"}
}