{
  "type": "Feature",
  "properties": {
    "iso:country":"US",
    "sg:address":"2522 Bergenline Ave",
    "sg:city":"Union City",
    "sg:classifiers":[
        {
            "category":"Food & Beverages",
            "subcategory":"Liquor & Beverages",
            "type":"Retail Goods"
        }
    ],
    "sg:phone":"+1 201 223 5550",
    "sg:postcode":"07087",
    "sg:province":"NJ",
    "sg:tags":[
        "beer",
        "spirit",
        "wine"
    ],
    "wof:name":"Check Cashing Plus",
    "wof:placetype":"venue"
},
  "geometry": {"coordinates":[-74.031998,40.768398],"type":"Point"}
}