{
  "type": "Feature",
  "properties": {
    "addr:full":"235 Raritan Ave Highland Park NJ 08904",
    "addr:housenumber":"235",
    "addr:postcode":"08904",
    "addr:street":"Raritan Ave",
    "iso:country":"US",
    "sg:address":"235 Raritan Ave",
    "sg:city":"Highland Park",
    "sg:classifiers":[
        {
            "category":"Education",
            "subcategory":"Special Training",
            "type":"Public Place"
        }
    ],
    "sg:phone":"+1   ",
    "sg:postcode":"08904",
    "sg:province":"NJ",
    "wof:name":"I M Pottery Studio & Gallery",
    "wof:placetype":"venue"
},
  "geometry": {"coordinates":[-74.430009,40.498551],"type":"Point"}
}