{
  "type": "Feature",
  "properties": {
    "addr:full":"3 Mill Creek Dr Secaucus NJ 07094",
    "addr:housenumber":"3",
    "addr:postcode":"07094",
    "addr:street":"Mill Creek Dr",
    "iso:country":"US",
    "sg:address":"3 Mill Creek Dr",
    "sg:city":"Secaucus",
    "sg:phone":"+1 201 553 9143",
    "sg:postcode":"07094",
    "sg:province":"NJ",
    "sg:website":"http://www.kohls.com",
    "wof:name":"Kohl's",
    "wof:placetype":"venue"
},
  "geometry": {"coordinates":[-74.052266,40.790352],"type":"Point"}
}