{
  "type": "Feature",
  "properties": {
    "iso:country":"US",
    "sg:address":"223 Mallory Ave",
    "sg:city":"Jersey City",
    "sg:classifiers":[
        {
            "category":"Banks & Credit Unions",
            "subcategory":"Bank",
            "type":"Services"
        }
    ],
    "sg:phone":"+1 201 333 7099",
    "sg:postcode":"07304",
    "sg:province":"NJ",
    "sg:tags":[
        "financing"
    ],
    "wof:name":"Clo Funding Corp",
    "wof:placetype":"venue"
},
  "geometry": {"coordinates":[-74.08644,40.721519],"type":"Point"}
}