{
  "type": "Feature",
  "properties": {
    "iso:country":"US",
    "sg:address":"4000 Susquehanna Ave",
    "sg:city":"Wildwood",
    "sg:classifiers":[
        {
            "category":"Retail",
            "subcategory":"Repair Shop",
            "type":"Services"
        }
    ],
    "sg:phone":"+1 609 522 7352",
    "sg:postcode":"08260",
    "sg:province":"NJ",
    "sg:tags":[
        "welding"
    ],
    "wof:name":"Bluewater Welding & Fab",
    "wof:placetype":"venue"
},
  "geometry": {"coordinates":[-74.823477,38.992579],"type":"Point"}
}