{
  "type": "Feature",
  "properties": {
    "iso:country":"US",
    "sg:address":"84 Hazelton Ter",
    "sg:city":"Tenafly",
    "sg:classifiers":[
        {
            "category":"Professional",
            "subcategory":"Management & Consulting",
            "type":"Services"
        }
    ],
    "sg:phone":"+1   ",
    "sg:postcode":"07670",
    "sg:province":"NJ",
    "sg:tags":[
        "business"
    ],
    "wof:name":"Zaccario Consulting Services L",
    "wof:placetype":"venue"
},
  "geometry": {"coordinates":[-73.97371099999999,40.933652],"type":"Point"}
}