{
  "type": "Feature",
  "properties": {
    "iso:country":"US",
    "sg:address":"21 Manning St",
    "sg:city":"Red Bank",
    "sg:classifiers":[
        {
            "category":"Building & Trades",
            "subcategory":"Construction",
            "type":"Services"
        }
    ],
    "sg:phone":"+1 732 933 1229",
    "sg:postcode":"07701",
    "sg:province":"NJ",
    "sg:tags":[
        "masonry",
        "contractor"
    ],
    "wof:name":"Fitzpatrick Masonry",
    "wof:placetype":"venue"
},
  "geometry": {"coordinates":[-74.086386,40.34907],"type":"Point"}
}