{
  "type": "Feature",
  "properties": {
    "addr:full":"183 Wyckoff Ave Wyckoff NJ 07481",
    "addr:housenumber":"183",
    "addr:postcode":"07481",
    "addr:street":"Wyckoff Ave",
    "iso:country":"US",
    "sg:address":"183 Wyckoff Ave",
    "sg:city":"Wyckoff",
    "sg:classifiers":[
        {
            "category":"Wholesale",
            "subcategory":"Apparel",
            "type":"Manufacturing & Wholesale Goods"
        }
    ],
    "sg:phone":"+1 201 923 8184",
    "sg:postcode":"07481",
    "sg:province":"NJ",
    "sg:tags":[
        "clothing"
    ],
    "wof:name":"Lane Tortoise",
    "wof:placetype":"venue"
},
  "geometry": {"coordinates":[-74.156358,40.986027],"type":"Point"}
}