{
  "type": "Feature",
  "properties": {
    "addr:full":"10 Sisco St Wayne NJ 07470",
    "addr:housenumber":"10",
    "addr:postcode":"07470",
    "addr:street":"Sisco St",
    "iso:country":"US",
    "sg:address":"10 Sisco St",
    "sg:city":"Wayne",
    "sg:classifiers":[
        {
            "category":"Insurance",
            "subcategory":"Insurance Agent",
            "type":"Services"
        }
    ],
    "sg:phone":"+1   ",
    "sg:postcode":"07470",
    "sg:province":"NJ",
    "wof:name":"Pension Protection Group",
    "wof:placetype":"venue"
},
  "geometry": {"coordinates":[-74.266727,40.955576],"type":"Point"}
}