{
  "type": "Feature",
  "properties": {
    "iso:country":"US",
    "sg:address":"127 Cold Indian Springs Rd",
    "sg:city":"Asbury Park",
    "sg:classifiers":[
        {
            "category":"Building & Trades",
            "subcategory":"Construction",
            "type":"Services"
        }
    ],
    "sg:phone":"+1 732 922 2233",
    "sg:postcode":"07712",
    "sg:province":"NJ",
    "sg:tags":[
        "roofing",
        "contractor"
    ],
    "wof:name":"Dave's Roofing",
    "wof:placetype":"venue"
},
  "geometry": {"coordinates":[-74.067699,40.24078],"type":"Point"}
}