{
  "type": "Feature",
  "properties": {
    "iso:country":"US",
    "sg:address":"7700 River Rd",
    "sg:city":"North Bergen",
    "sg:classifiers":[
        {
            "category":"Health Services",
            "subcategory":"Doctor",
            "type":"Services"
        }
    ],
    "sg:phone":"+1 201 766 1541",
    "sg:postcode":"07047",
    "sg:province":"NJ",
    "wof:name":"Saeed Abbassi MD",
    "wof:placetype":"venue"
},
  "geometry": {"coordinates":[-73.996953,40.794614],"type":"Point"}
}