{
  "type": "Feature",
  "properties": {
    "addr:full":"276 Lafayette Pl Englewood NJ 07631",
    "addr:housenumber":"276",
    "addr:postcode":"07631",
    "addr:street":"Lafayette Pl",
    "iso:country":"US",
    "sg:address":"276 Lafayette Pl",
    "sg:city":"Englewood",
    "sg:classifiers":[
        {
            "category":"Building & Trades",
            "subcategory":"Locksmith",
            "type":"Services"
        }
    ],
    "sg:phone":"+1 201 408 0403",
    "sg:postcode":"07631",
    "sg:province":"NJ",
    "sg:tags":[
        "key"
    ],
    "wof:name":"AA 24",
    "wof:placetype":"venue"
},
  "geometry": {"coordinates":[-73.99024,40.890286],"type":"Point"}
}