{
  "type": "Feature",
  "properties": {
    "addr:full":"494 Kinderkamack Rd River Edge NJ 07661",
    "addr:housenumber":"494",
    "addr:postcode":"07661",
    "addr:street":"Kinderkamack Rd",
    "iso:country":"US",
    "sg:address":"494 Kinderkamack Rd",
    "sg:city":"River Edge",
    "sg:classifiers":[
        {
            "category":"Food & Beverages",
            "subcategory":"Bakery",
            "type":"Retail Goods"
        }
    ],
    "sg:phone":"+1 201 634 1131",
    "sg:postcode":"07661",
    "sg:province":"NJ",
    "sg:tags":[
        "baker"
    ],
    "wof:name":"Serin's",
    "wof:placetype":"venue"
},
  "geometry": {"coordinates":[-74.034102,40.921958],"type":"Point"}
}