{
  "type": "Feature",
  "properties": {
    "iso:country":"US",
    "sg:address":"244 E 3rd St",
    "sg:city":"Plainfield",
    "sg:classifiers":[
        {
            "category":"Manufacturing",
            "subcategory":"Tools & Machinery",
            "type":"Manufacturing & Wholesale Goods"
        }
    ],
    "sg:phone":"+1 908 226 1777",
    "sg:postcode":"07060",
    "sg:province":"NJ",
    "sg:tags":[
        "testing",
        "apparatus"
    ],
    "wof:name":"Dek Tron Intl Corp",
    "wof:placetype":"venue"
},
  "geometry": {"coordinates":[-74.418222,40.620321],"type":"Point"}
}