{
  "type": "Feature",
  "properties": {
    "iso:country":"US",
    "sg:address":"219 Dayton Ave",
    "sg:city":"Clifton",
    "sg:classifiers":[
        {
            "category":"Professional",
            "type":"Services"
        }
    ],
    "sg:phone":"+1   ",
    "sg:postcode":"07011",
    "sg:province":"NJ",
    "wof:name":"HMB Corp",
    "wof:placetype":"venue"
},
  "geometry": {"coordinates":[-74.122654,40.875122],"type":"Point"}
}