{
  "type": "Feature",
  "properties": {
    "addr:full":"19 Scottsdale Ct Cranbury NJ 08512",
    "addr:housenumber":"19",
    "addr:postcode":"08512",
    "addr:street":"Scottsdale Ct",
    "iso:country":"US",
    "sg:address":"19 Scottsdale Ct",
    "sg:city":"Cranbury",
    "sg:classifiers":[
        {
            "category":"Banks & Credit Unions",
            "subcategory":"Investment Brokerage",
            "type":"Services"
        }
    ],
    "sg:phone":"+1   ",
    "sg:postcode":"08512",
    "sg:province":"NJ",
    "sg:tags":[
        "advisory",
        "consulting",
        "management"
    ],
    "wof:name":"Glen Eagle Investments Inc",
    "wof:placetype":"venue"
},
  "geometry": {"coordinates":[-74.52922700000001,40.297315],"type":"Point"}
}