{
  "type": "Feature",
  "properties": {
    "iso:country":"US",
    "sg:address":"1812 Springfield Ave",
    "sg:city":"Maplewood",
    "sg:classifiers":[
        {
            "category":"Recreation",
            "type":"Entertainment"
        }
    ],
    "sg:phone":"+1 973 761 8444",
    "sg:postcode":"07040",
    "sg:province":"NJ",
    "wof:name":"Prestige Tours",
    "wof:placetype":"venue"
},
  "geometry": {"coordinates":[-74.26696200000001,40.721176],"type":"Point"}
}