{
  "type": "Feature",
  "properties": {
    "iso:country":"US",
    "sg:address":"119 Shippen St",
    "sg:city":"Weehawken",
    "sg:classifiers":[
        {
            "category":"Utilities",
            "subcategory":"Telephone",
            "type":"Services"
        }
    ],
    "sg:phone":"+1 201 974 1455",
    "sg:postcode":"07086",
    "sg:province":"NJ",
    "sg:tags":[
        "communications"
    ],
    "wof:name":"Alx Productions",
    "wof:placetype":"venue"
},
  "geometry": {"coordinates":[-74.027958,40.765806],"type":"Point"}
}