{
  "type": "Feature",
  "properties": {
    "iso:country":"US",
    "sg:address":"146 Haddon Ave",
    "sg:city":"West Berlin",
    "sg:classifiers":[
        {
            "category":"Retail",
            "subcategory":"Repair Shop",
            "type":"Services"
        }
    ],
    "sg:phone":"+1 856 767 7527",
    "sg:postcode":"08091",
    "sg:province":"NJ",
    "sg:tags":[
        "electrical"
    ],
    "wof:name":"Atlas Electronics",
    "wof:placetype":"venue"
},
  "geometry": {"coordinates":[-74.941166,39.80798],"type":"Point"}
}