{
  "type": "Feature",
  "properties": {
    "iso:country":"US",
    "sg:address":"55 Morris Ave",
    "sg:city":"Springfield",
    "sg:classifiers":[
        {
            "category":"Personal",
            "type":"Services"
        }
    ],
    "sg:phone":"+1 908 358 5297",
    "sg:postcode":"07081",
    "sg:province":"NJ",
    "sg:tags":[
        "therapist",
        "massage"
    ],
    "wof:name":"Body & Soul Massage Therapy",
    "wof:placetype":"venue"
},
  "geometry": {"coordinates":[-74.304445,40.708812],"type":"Point"}
}