{
  "type": "Feature",
  "properties": {
    "iso:country":"US",
    "sg:address":"21 Portland Ave",
    "sg:city":"Bergenfield",
    "sg:classifiers":[
        {
            "category":"Home & Garden",
            "subcategory":"Household Appliances",
            "type":"Retail Goods"
        },
        {
            "category":"Retail",
            "subcategory":"Repair Shop",
            "type":"Services"
        }
    ],
    "sg:phone":"+1 201 384 4471",
    "sg:postcode":"07621",
    "sg:province":"NJ",
    "sg:tags":[
        "small"
    ],
    "wof:name":"Mc Dowell's Appliances",
    "wof:placetype":"venue"
},
  "geometry": {"coordinates":[-73.997587,40.926303],"type":"Point"}
}