{
  "type": "Feature",
  "properties": {
    "iso:country":"US",
    "sg:address":"1628 Mayflower Ln",
    "sg:city":"Cherry Hill",
    "sg:classifiers":[
        {
            "category":"Shopping",
            "subcategory":"Catalog Store",
            "type":"Retail Goods"
        }
    ],
    "sg:phone":"+1   ",
    "sg:postcode":"08003",
    "sg:province":"NJ",
    "sg:tags":[
        "mail",
        "house"
    ],
    "wof:name":"Nostalgia Collectibles",
    "wof:placetype":"venue"
},
  "geometry": {"coordinates":[-74.985833,39.885563],"type":"Point"}
}