{
  "type": "Feature",
  "properties": {
    "iso:country":"US",
    "sg:address":"2812 Kennedy Blvd",
    "sg:city":"Union City",
    "sg:classifiers":[
        {
            "category":"Wholesale",
            "subcategory":"Hardware",
            "type":"Manufacturing & Wholesale Goods"
        }
    ],
    "sg:phone":"+1 201 863 8587",
    "sg:postcode":"07087",
    "sg:province":"NJ",
    "sg:tags":[
        "equipment",
        "heating",
        "system"
    ],
    "sg:website":"www.palermo.com",
    "wof:name":"Palermo Supply Co",
    "wof:placetype":"venue"
},
  "geometry": {"coordinates":[-74.034683,40.773228],"type":"Point"}
}