{
  "type": "Feature",
  "properties": {
    "addr:full":"1305 Tooz Pl South Plainfield NJ 07080",
    "addr:housenumber":"1305",
    "addr:postcode":"07080",
    "addr:street":"Tooz Pl",
    "iso:country":"US",
    "sg:address":"1305 Tooz Pl",
    "sg:city":"South Plainfield",
    "sg:classifiers":[
        {
            "category":"Building & Trades",
            "subcategory":"Landscaping Services",
            "type":"Services"
        }
    ],
    "sg:phone":"+1 908 753 0074",
    "sg:postcode":"07080",
    "sg:province":"NJ",
    "wof:name":"DMD Landscapes & Lawn Care",
    "wof:placetype":"venue"
},
  "geometry": {"coordinates":[-74.43161000000001,40.589703],"type":"Point"}
}