{
  "type": "Feature",
  "properties": {
    "addr:full":"301 Essex St Gloucester City NJ 08030",
    "addr:housenumber":"301",
    "addr:postcode":"08030",
    "addr:street":"Essex St",
    "iso:country":"US",
    "sg:address":"301 Essex St",
    "sg:city":"Gloucester City",
    "sg:classifiers":[
        {
            "category":"Bars & Pubs",
            "type":"Food & Drink"
        }
    ],
    "sg:phone":"+1   ",
    "sg:postcode":"08030",
    "sg:province":"NJ",
    "sg:tags":[
        "bar"
    ],
    "wof:name":"Mealeys Pub and Grill",
    "wof:placetype":"venue"
},
  "geometry": {"coordinates":[-75.120205,39.900909],"type":"Point"}
}