{
  "type": "Feature",
  "properties": {
    "iso:country":"US",
    "sg:address":"116 4th Ave",
    "sg:city":"Cape May",
    "sg:classifiers":[
        {
            "category":"Real Estate",
            "subcategory":"Real Estate Operator",
            "type":"Services"
        }
    ],
    "sg:phone":"+1   ",
    "sg:postcode":"08204",
    "sg:province":"NJ",
    "sg:tags":[
        "building",
        "nonresidential"
    ],
    "wof:name":"Padj Properties",
    "wof:placetype":"venue"
},
  "geometry": {"coordinates":[-74.930419,38.938244],"type":"Point"}
}