{
  "type": "Feature",
  "properties": {
    "addr:full":"6529 Black Horse Pike Egg Harbor Township NJ 08234",
    "addr:housenumber":"6529",
    "addr:postcode":"08234",
    "addr:street":"Black Horse Pike",
    "iso:country":"US",
    "sg:address":"6529 Black Horse Pike",
    "sg:city":"Egg Harbor Township",
    "sg:classifiers":[
        {
            "category":"Health Services",
            "subcategory":"Doctor",
            "type":"Services"
        }
    ],
    "sg:phone":"+1   ",
    "sg:postcode":"08234",
    "sg:province":"NJ",
    "sg:tags":[
        "pediatrician"
    ],
    "wof:name":"Kessler Barry MD",
    "wof:placetype":"venue"
},
  "geometry": {"coordinates":[-74.584057,39.419407],"type":"Point"}
}