{
  "type": "Feature",
  "properties": {
    "iso:country":"US",
    "sg:address":"69 7th St",
    "sg:city":"Harrison",
    "sg:classifiers":[
        {
            "category":"Food & Beverages",
            "subcategory":"Liquor & Beverages",
            "type":"Retail Goods"
        }
    ],
    "sg:phone":"+1 973 350 0555",
    "sg:postcode":"07029",
    "sg:province":"NJ",
    "sg:tags":[
        "beer",
        "spirit",
        "wine"
    ],
    "wof:name":"Cesar's Liquor Store",
    "wof:placetype":"venue"
},
  "geometry": {"coordinates":[-74.15084899999999,40.746523],"type":"Point"}
}