{
  "type": "Feature",
  "properties": {
    "iso:country":"US",
    "sg:address":"9 Kyle Dr",
    "sg:city":"Phillipsburg",
    "sg:classifiers":[
        {
            "category":"Real Estate",
            "subcategory":"Real Estate Agent",
            "type":"Services"
        }
    ],
    "sg:phone":"+1 908 387 1845",
    "sg:postcode":"08865",
    "sg:province":"NJ",
    "wof:name":"Ww Buy Houses",
    "wof:placetype":"venue"
},
  "geometry": {"coordinates":[-75.169355,40.714745],"type":"Point"}
}