{
  "type": "Feature",
  "properties": {
    "iso:country":"US",
    "sg:address":"706 Lawlins Rd",
    "sg:city":"Wyckoff",
    "sg:classifiers":[
        {
            "category":"Shopping",
            "subcategory":"Florist",
            "type":"Retail Goods"
        },
        {
            "category":"Home & Garden",
            "subcategory":"Garden Supply",
            "type":"Retail Goods"
        }
    ],
    "sg:phone":"+1 201 891 3161",
    "sg:postcode":"07481",
    "sg:province":"NJ",
    "sg:tags":[
        "plant",
        "nurseryman"
    ],
    "wof:name":"Abma's Farm & Nurseries",
    "wof:placetype":"venue"
},
  "geometry": {"coordinates":[-74.18512,41.017213],"type":"Point"}
}