{
  "type": "Feature",
  "properties": {
    "iso:country":"US",
    "sg:address":"532 Old Marlton Pike W",
    "sg:city":"Marlton",
    "sg:classifiers":[
        {
            "category":"Professional",
            "subcategory":"Computer Services",
            "type":"Services"
        }
    ],
    "sg:phone":"+1 856 424 7475",
    "sg:postcode":"08053",
    "sg:province":"NJ",
    "sg:tags":[
        "consultant"
    ],
    "wof:name":"Edgetech Solutions",
    "wof:placetype":"venue"
},
  "geometry": {"coordinates":[-74.93251600000001,39.893161],"type":"Point"}
}