{
  "type": "Feature",
  "properties": {
    "iso:country":"US",
    "sg:address":"513 Anderson Ave",
    "sg:city":"Cliffside Park",
    "sg:classifiers":[
        {
            "category":"Health Services",
            "subcategory":"Doctor",
            "type":"Services"
        }
    ],
    "sg:phone":"+1 201 945 3354",
    "sg:postcode":"07010",
    "sg:province":"NJ",
    "sg:tags":[
        "medicine",
        "internal"
    ],
    "wof:name":"Sethi Virender MD",
    "wof:placetype":"venue"
},
  "geometry": {"coordinates":[-73.99250000000001,40.819698],"type":"Point"}
}