{
  "type": "Feature",
  "properties": {
    "addr:full":"111 Cumberland Ct Wyckoff NJ 07481",
    "addr:housenumber":"111",
    "addr:postcode":"07481",
    "addr:street":"Cumberland Ct",
    "iso:country":"US",
    "sg:address":"111 Cumberland Ct",
    "sg:city":"Wyckoff",
    "sg:classifiers":[
        {
            "category":"Professional",
            "type":"Services"
        }
    ],
    "sg:phone":"+1   ",
    "sg:postcode":"07481",
    "sg:province":"NJ",
    "wof:name":"David Shaver",
    "wof:placetype":"venue"
},
  "geometry": {"coordinates":[-74.159266,41.001362],"type":"Point"}
}