{
  "type": "Feature",
  "properties": {
    "iso:country":"US",
    "sg:address":"275 Willow Way",
    "sg:city":"Mount Laurel",
    "sg:classifiers":[
        {
            "category":"Communications",
            "type":"Services"
        }
    ],
    "sg:phone":"+1 856 642 1590",
    "sg:postcode":"08054",
    "sg:province":"NJ",
    "sg:tags":[
        "communication"
    ],
    "wof:name":"South Jersey Communication",
    "wof:placetype":"venue"
},
  "geometry": {"coordinates":[-74.86397100000001,39.984207],"type":"Point"}
}