{
  "type": "Feature",
  "properties": {
    "addr:full":"350 Belleville Tpke Kearny NJ 07032",
    "addr:housenumber":"350",
    "addr:postcode":"07032",
    "addr:street":"Belleville Tpke",
    "iso:country":"US",
    "sg:address":"350 Belleville Tpke",
    "sg:city":"Kearny",
    "sg:classifiers":[
        {
            "category":"Wholesale",
            "subcategory":"Home Furnishings",
            "type":"Manufacturing & Wholesale Goods"
        }
    ],
    "sg:phone":"+1 201 991 4900",
    "sg:postcode":"07032",
    "sg:province":"NJ",
    "sg:tags":[
        "blind",
        "shade"
    ],
    "wof:name":"Hudson & Bergen Co",
    "wof:placetype":"venue"
},
  "geometry": {"coordinates":[-74.13310199999999,40.777599],"type":"Point"}
}