{
  "type": "Feature",
  "properties": {
    "iso:country":"US",
    "sg:address":"370 Beecroft Pl",
    "sg:city":"Oakhurst",
    "sg:classifiers":[
        {
            "category":"Building & Trades",
            "subcategory":"Construction",
            "type":"Services"
        }
    ],
    "sg:phone":"+1 732 571 0370",
    "sg:postcode":"07755",
    "sg:province":"NJ",
    "sg:tags":[
        "house"
    ],
    "wof:name":"Colorfast Painting Inc",
    "wof:placetype":"venue"
},
  "geometry": {"coordinates":[-74.01777800000001,40.268425],"type":"Point"}
}