{
  "type": "Feature",
  "properties": {
    "iso:country":"US",
    "sg:address":"104 8th St",
    "sg:city":"Wood Ridge",
    "sg:classifiers":[
        {
            "category":"Retail",
            "subcategory":"Repair Shop",
            "type":"Services"
        }
    ],
    "sg:phone":"+1 201 438 2011",
    "sg:postcode":"07075",
    "sg:province":"NJ",
    "sg:tags":[
        "refrigerator",
        "freezer"
    ],
    "wof:name":"Gardella Refrigeration",
    "wof:placetype":"venue"
},
  "geometry": {"coordinates":[-74.09124,40.848521],"type":"Point"}
}