{
  "type": "Feature",
  "properties": {
    "iso:country":"US",
    "sg:address":"113 Main St",
    "sg:city":"Franklin",
    "sg:classifiers":[
        {
            "category":"Retail",
            "subcategory":"Animal Services",
            "type":"Services"
        }
    ],
    "sg:phone":"+1 973 827 9113",
    "sg:postcode":"07416",
    "sg:province":"NJ",
    "sg:tags":[
        "pet",
        "grooming",
        "washing"
    ],
    "wof:name":"Mark's Critter Grooming",
    "wof:placetype":"venue"
},
  "geometry": {"coordinates":[-74.585903,41.121674],"type":"Point"}
}