{
  "type": "Feature",
  "properties": {
    "iso:country":"US",
    "sg:address":"61 Neville St",
    "sg:city":"Tinton Falls",
    "sg:classifiers":[
        {
            "category":"Building & Trades",
            "subcategory":"Construction",
            "type":"Services"
        }
    ],
    "sg:phone":"+1 732 935 0040",
    "sg:postcode":"07724",
    "sg:province":"NJ",
    "sg:tags":[
        "general",
        "contractor"
    ],
    "wof:name":"Infinity Construction LLC",
    "wof:placetype":"venue"
},
  "geometry": {"coordinates":[-74.10869099999999,40.318919],"type":"Point"}
}