{
  "type": "Feature",
  "properties": {
    "iso:country":"US",
    "sg:address":"116 Tennent Rd",
    "sg:city":"Morganville",
    "sg:classifiers":[
        {
            "category":"Retail",
            "subcategory":"Auto Repair",
            "type":"Services"
        }
    ],
    "sg:phone":"+1 732 591 8424",
    "sg:postcode":"07751",
    "sg:province":"NJ",
    "sg:tags":[
        "repairing",
        "automotive",
        "general",
        "automobile"
    ],
    "wof:name":"T & D Auto Repair Inc",
    "wof:placetype":"venue"
},
  "geometry": {"coordinates":[-74.259331,40.373079],"type":"Point"}
}