{
  "type": "Feature",
  "properties": {
    "addr:full":"88 Lakeview Dr S Gibbsboro NJ 08026",
    "addr:housenumber":"88",
    "addr:postcode":"08026",
    "addr:street":"Lakeview Dr S",
    "iso:country":"US",
    "sg:address":"88 Lakeview Dr S",
    "sg:city":"Gibbsboro",
    "sg:classifiers":[
        {
            "category":"Health Services",
            "subcategory":"Doctor",
            "type":"Services"
        }
    ],
    "sg:phone":"+1 856 489 3111",
    "sg:postcode":"08026",
    "sg:province":"NJ",
    "sg:tags":[
        "physician",
        "surgeon"
    ],
    "wof:name":"Ent Specialty Ctr",
    "wof:placetype":"venue"
},
  "geometry": {"coordinates":[-74.958624,39.835855],"type":"Point"}
}