{
  "type": "Feature",
  "properties": {
    "addr:full":"198 Bellevue Ave Montclair NJ 07043",
    "addr:housenumber":"198",
    "addr:postcode":"07043",
    "addr:street":"Bellevue Ave",
    "iso:country":"US",
    "sg:address":"198 Bellevue Ave",
    "sg:city":"Montclair",
    "sg:classifiers":[
        {
            "category":"Retail",
            "subcategory":"Auto Repair",
            "type":"Services"
        }
    ],
    "sg:phone":"+1 973 744 9539",
    "sg:postcode":"07043",
    "sg:province":"NJ",
    "sg:tags":[
        "repairing",
        "automobile"
    ],
    "wof:name":"Bellevue Upper Montclair",
    "wof:placetype":"venue"
},
  "geometry": {"coordinates":[-74.204947,40.840351],"type":"Point"}
}