{
  "type": "Feature",
  "properties": {
    "addr:full":"79 Ringwood Ave Wanaque NJ 07465",
    "addr:housenumber":"79",
    "addr:postcode":"07465",
    "addr:street":"Ringwood Ave",
    "iso:country":"US",
    "sg:address":"79 Ringwood Ave",
    "sg:city":"Wanaque",
    "sg:classifiers":[
        {
            "category":"Shopping",
            "subcategory":"Bicycles & Sporting Goods",
            "type":"Retail Goods"
        }
    ],
    "sg:phone":"+1 973 839 3885",
    "sg:postcode":"07465",
    "sg:province":"NJ",
    "sg:tags":[
        "mfg"
    ],
    "wof:name":"Benbrook Bait",
    "wof:placetype":"venue"
},
  "geometry": {"coordinates":[-74.283322,41.06707],"type":"Point"}
}