{
  "type": "Feature",
  "properties": {
    "addr:full":"507 Bloomfield Ave Montclair NJ 07042",
    "addr:housenumber":"507",
    "addr:postcode":"07042",
    "addr:street":"Bloomfield Ave",
    "iso:country":"US",
    "sg:address":"507 Bloomfield Ave",
    "sg:city":"Montclair",
    "sg:classifiers":[
        {
            "category":"Professional",
            "subcategory":"Art Services",
            "type":"Services"
        }
    ],
    "sg:phone":"+1   ",
    "sg:postcode":"07042",
    "sg:province":"NJ",
    "sg:tags":[
        "commercial",
        "graphic",
        "design"
    ],
    "wof:name":"Frederick Froberg Design Offs",
    "wof:placetype":"venue"
},
  "geometry": {"coordinates":[-74.21914099999999,40.815124],"type":"Point"}
}