{
  "type": "Feature",
  "properties": {
    "iso:country":"US",
    "sg:address":"29 Imlaystown Hightstown Rd",
    "sg:city":"Imlaystown",
    "sg:classifiers":[
        {
            "category":"Restaurant",
            "type":"Food & Drink"
        }
    ],
    "sg:phone":"+1 609 259 7889",
    "sg:postcode":"08520",
    "sg:province":"NJ",
    "sg:website":"www.happyappleinn.com",
    "wof:name":"Happy Apple Of Imlaystown",
    "wof:placetype":"venue"
},
  "geometry": {"coordinates":[-74.513777,40.198824],"type":"Point"}
}