{
  "type": "Feature",
  "properties": {
    "iso:country":"US",
    "sg:address":"519 Bay Ave",
    "sg:city":"Pt Pleasant Bch",
    "sg:classifiers":[
        {
            "category":"Shopping",
            "subcategory":"Clothing, Apparel, & Fashions",
            "type":"Retail Goods"
        }
    ],
    "sg:phone":"+1 732 899 7884",
    "sg:postcode":"08742",
    "sg:province":"NJ",
    "sg:tags":[
        "lady"
    ],
    "wof:name":"Lola's Boutique",
    "wof:placetype":"venue"
},
  "geometry": {"coordinates":[-74.051895,40.091364],"type":"Point"}
}