{
  "type": "Feature",
  "properties": {
    "addr:full":"179 State Rte 37 Toms River NJ 08755",
    "addr:housenumber":"179",
    "addr:postcode":"08755",
    "addr:street":"State Rte 37",
    "iso:country":"US",
    "sg:address":"179 State Rte 37",
    "sg:city":"Toms River",
    "sg:classifiers":[
        {
            "category":"Shopping",
            "subcategory":"Shoes",
            "type":"Retail Goods"
        },
        {
            "category":"Shopping",
            "subcategory":"Clothing, Apparel, & Fashions",
            "type":"Retail Goods"
        }
    ],
    "sg:phone":"+1 732 505 0588",
    "sg:postcode":"08755",
    "sg:province":"NJ",
    "sg:tags":[
        "shoe",
        "store"
    ],
    "wof:name":"Flannery's Wide Width Shoes",
    "wof:placetype":"venue"
},
  "geometry": {"coordinates":[-74.221172,39.966068],"type":"Point"}
}