{
  "type": "Feature",
  "properties": {
    "iso:country":"US",
    "sg:address":"623 Bloomfield Ave",
    "sg:city":"Bloomfield",
    "sg:classifiers":[
        {
            "category":"Professional",
            "type":"Services"
        }
    ],
    "sg:phone":"+1 973 743 9783",
    "sg:postcode":"07003",
    "sg:province":"NJ",
    "sg:tags":[
        "establishment"
    ],
    "wof:name":"BEC Inc",
    "wof:placetype":"venue"
},
  "geometry": {"coordinates":[-74.199766,40.796357],"type":"Point"}
}