{
  "type": "Feature",
  "properties": {
    "iso:country":"US",
    "sg:address":"105 Grove Ter",
    "sg:city":"Newark",
    "sg:classifiers":[
        {
            "category":"Organizations",
            "subcategory":"Religious Organization",
            "type":"Services"
        }
    ],
    "sg:phone":"+1 973 371 4803",
    "sg:postcode":"07106",
    "sg:province":"NJ",
    "sg:tags":[
        "church"
    ],
    "wof:name":"Dove Community Child Care",
    "wof:placetype":"venue"
},
  "geometry": {"coordinates":[-74.22256,40.739824],"type":"Point"}
}