{
  "type": "Feature",
  "properties": {
    "addr:full":"280 Saint Georges Ave Rahway NJ 07065",
    "addr:housenumber":"280",
    "addr:postcode":"07065",
    "addr:street":"Saint Georges Ave",
    "iso:country":"US",
    "sg:address":"280 Saint Georges Ave",
    "sg:city":"Rahway",
    "sg:classifiers":[
        {
            "category":"Personal",
            "type":"Services"
        }
    ],
    "sg:phone":"+1 732 396 4826",
    "sg:postcode":"07065",
    "sg:province":"NJ",
    "wof:name":"Tanzibar",
    "wof:placetype":"venue"
},
  "geometry": {"coordinates":[-74.290701,40.594929],"type":"Point"}
}