{
  "type": "Feature",
  "properties": {
    "iso:country":"US",
    "sg:address":"Perryville III  53 Frontage Road, Suite 210",
    "sg:city":"Hampton",
    "sg:classifiers":[
        {
            "category":"Manufacturing",
            "subcategory":"Electronics",
            "type":"Manufacturing & Wholesale Goods"
        }
    ],
    "sg:phone":"+1 908 894 6000",
    "sg:postcode":"08827",
    "sg:province":"NJ",
    "sg:website":"http://www.enpirion.com/",
    "wof:name":"Enpirion",
    "wof:placetype":"venue"
},
  "geometry": {"coordinates":[-74.970186,40.634222],"type":"Point"}
}