{
  "type": "Feature",
  "properties": {
    "addr:full":"5 Heather Dr Old Bridge NJ 08857",
    "addr:housenumber":"5",
    "addr:postcode":"08857",
    "addr:street":"Heather Dr",
    "iso:country":"US",
    "sg:address":"5 Heather Dr",
    "sg:city":"Old Bridge",
    "sg:classifiers":[
        {
            "category":"Professional",
            "subcategory":"Business Services",
            "type":"Services"
        }
    ],
    "sg:phone":"+1   ",
    "sg:postcode":"08857",
    "sg:province":"NJ",
    "wof:name":"Riddleworks",
    "wof:placetype":"venue"
},
  "geometry": {"coordinates":[-74.323888,40.398614],"type":"Point"}
}