{
  "type": "Feature",
  "properties": {
    "iso:country":"US",
    "sg:address":"53 Main St",
    "sg:city":"Metuchen",
    "sg:classifiers":[
        {
            "category":"Building & Trades",
            "subcategory":"Equipment Rental",
            "type":"Services"
        }
    ],
    "sg:phone":"+1   ",
    "sg:postcode":"08840",
    "sg:province":"NJ",
    "sg:tags":[
        "machine",
        "vending"
    ],
    "wof:name":"Associated Amusements Inc",
    "wof:placetype":"venue"
},
  "geometry": {"coordinates":[-74.358722,40.529402],"type":"Point"}
}