{
  "type": "Feature",
  "properties": {
    "addr:full":"43 John St Fairfield NJ 07004",
    "addr:housenumber":"43",
    "addr:postcode":"07004",
    "addr:street":"John St",
    "iso:country":"US",
    "sg:address":"43 John St",
    "sg:city":"Fairfield",
    "sg:classifiers":[
        {
            "category":"Wholesale",
            "subcategory":"Non-durable Goods",
            "type":"Manufacturing & Wholesale Goods"
        }
    ],
    "sg:phone":"+1 973 227 0449",
    "sg:postcode":"07004",
    "sg:province":"NJ",
    "sg:tags":[
        "a",
        "wholesaler",
        "as",
        "operates",
        "poster"
    ],
    "wof:name":"Thomas Alicandri Posters",
    "wof:placetype":"venue"
},
  "geometry": {"coordinates":[-74.29573499999999,40.890385],"type":"Point"}
}