{
  "type": "Feature",
  "properties": {
    "addr:full":"105 State Rte 35 Eatontown NJ 07724",
    "addr:housenumber":"105",
    "addr:postcode":"07724",
    "addr:street":"State Rte 35",
    "iso:country":"US",
    "sg:address":"105 State Rte 35",
    "sg:city":"Eatontown",
    "sg:classifiers":[
        {
            "category":"Recreation",
            "type":"Entertainment"
        }
    ],
    "sg:phone":"+1 732 542 5891",
    "sg:postcode":"07724",
    "sg:province":"NJ",
    "sg:tags":[
        "skating",
        "rink"
    ],
    "wof:name":"Eatontown Roller Rink",
    "wof:placetype":"venue"
},
  "geometry": {"coordinates":[-74.053579,40.295457],"type":"Point"}
}