{
  "type": "Feature",
  "properties": {
    "addr:full":"419 US Highway 46 South Hackensack NJ 07606",
    "addr:housenumber":"419",
    "addr:postcode":"07606",
    "addr:street":"Us Highway 46 South",
    "iso:country":"US",
    "sg:address":"419 US Highway 46",
    "sg:city":"South Hackensack",
    "sg:classifiers":[
        {
            "category":"Retail",
            "subcategory":"Auto Repair",
            "type":"Services"
        }
    ],
    "sg:phone":"+1 201 440 0600",
    "sg:postcode":"07606",
    "sg:province":"NJ",
    "wof:name":"Inter Motors Inc",
    "wof:placetype":"venue"
},
  "geometry": {"coordinates":[-74.047997,40.857498],"type":"Point"}
}