{
  "type": "Feature",
  "properties": {
    "addr:full":"35 Spruce Ln Colts Neck NJ 07722",
    "addr:housenumber":"35",
    "addr:postcode":"07722",
    "addr:street":"Spruce Ln",
    "iso:country":"US",
    "sg:address":"35 Spruce Ln",
    "sg:city":"Colts Neck",
    "sg:classifiers":[
        {
            "category":"Professional",
            "subcategory":"Management & Consulting",
            "type":"Services"
        }
    ],
    "sg:phone":"+1 732 530 4592",
    "sg:postcode":"07722",
    "sg:province":"NJ",
    "wof:name":"Systems Management Teh Inc",
    "wof:placetype":"venue"
},
  "geometry": {"coordinates":[-74.149891,40.315757],"type":"Point"}
}