{
  "type": "Feature",
  "properties": {
    "iso:country":"US",
    "sg:address":"118 Main St",
    "sg:city":"Hightstown",
    "sg:classifiers":[
        {
            "category":"Food & Beverages",
            "subcategory":"Bakery",
            "type":"Retail Goods"
        }
    ],
    "sg:phone":"+1 609 918 1800",
    "sg:postcode":"08520",
    "sg:province":"NJ",
    "sg:tags":[
        "baker"
    ],
    "wof:name":"Orquideas Bakery",
    "wof:placetype":"venue"
},
  "geometry": {"coordinates":[-74.523534,40.269276],"type":"Point"}
}