{
  "type": "Feature",
  "properties": {
    "addr:full":"470 State Rte 27 Iselin NJ 08830",
    "addr:housenumber":"470",
    "addr:postcode":"08830",
    "addr:street":"State Rte 27",
    "iso:country":"US",
    "sg:address":"470 State Rte 27",
    "sg:city":"Iselin",
    "sg:classifiers":[
        {
            "category":"Shopping",
            "type":"Retail Goods"
        }
    ],
    "sg:phone":"+1   ",
    "sg:postcode":"08830",
    "sg:province":"NJ",
    "sg:tags":[
        "merchandise"
    ],
    "wof:name":"Poolworks",
    "wof:placetype":"venue"
},
  "geometry": {"coordinates":[-74.321432,40.573284],"type":"Point"}
}