{
  "type": "Feature",
  "properties": {
    "addr:full":"71 Spring Ln Englewood NJ 07631",
    "addr:housenumber":"71",
    "addr:postcode":"07631",
    "addr:street":"Spring Ln",
    "iso:country":"US",
    "sg:address":"71 Spring Ln",
    "sg:city":"Englewood",
    "sg:classifiers":[
        {
            "category":"Real Estate",
            "subcategory":"Developer",
            "type":"Services"
        }
    ],
    "sg:phone":"+1   ",
    "sg:postcode":"07631",
    "sg:province":"NJ",
    "wof:name":"Rathod Group Inc",
    "wof:placetype":"venue"
},
  "geometry": {"coordinates":[-73.970411,40.89453],"type":"Point"}
}