{
  "type": "Feature",
  "properties": {
    "addr:full":"14 Cedar Dr Lakewood NJ 08701",
    "addr:housenumber":"14",
    "addr:postcode":"08701",
    "addr:street":"Cedar Dr",
    "iso:country":"US",
    "sg:address":"14 Cedar Dr",
    "sg:city":"Lakewood",
    "sg:classifiers":[
        {
            "category":"Banks & Credit Unions",
            "subcategory":"Financial Services",
            "type":"Services"
        }
    ],
    "sg:phone":"+1   ",
    "sg:postcode":"08701",
    "sg:province":"NJ",
    "sg:tags":[
        "company",
        "holding"
    ],
    "wof:name":"Whisper Holdings LLC",
    "wof:placetype":"venue"
},
  "geometry": {"coordinates":[-74.238384,40.086999],"type":"Point"}
}