{
  "type": "Feature",
  "properties": {
    "iso:country":"US",
    "sg:address":"30 Pearl St",
    "sg:city":"Long Branch",
    "sg:classifiers":[
        {
            "category":"Building & Trades",
            "subcategory":"Construction",
            "type":"Services"
        }
    ],
    "sg:phone":"+1 732 571 3331",
    "sg:postcode":"07740",
    "sg:province":"NJ",
    "sg:tags":[
        "house"
    ],
    "wof:name":"Oakley Construction & Assoc",
    "wof:placetype":"venue"
},
  "geometry": {"coordinates":[-74.001178,40.29987],"type":"Point"}
}