{
  "type": "Feature",
  "properties": {
    "iso:country":"US",
    "sg:address":"1122 22nd St",
    "sg:city":"North Bergen",
    "sg:classifiers":[
        {
            "category":"Professional",
            "subcategory":"Computer Services",
            "type":"Services"
        }
    ],
    "sg:phone":"+1   ",
    "sg:postcode":"07047",
    "sg:province":"NJ",
    "sg:tags":[
        "related"
    ],
    "wof:name":"Digital Network Support Inc",
    "wof:placetype":"venue"
},
  "geometry": {"coordinates":[-74.039941,40.769261],"type":"Point"}
}