{
  "type": "Feature",
  "properties": {
    "addr:full":"891 Main St Paterson NJ 07503",
    "addr:housenumber":"891",
    "addr:postcode":"07503",
    "addr:street":"Main St",
    "iso:country":"US",
    "sg:address":"891 Main St",
    "sg:city":"Paterson",
    "sg:classifiers":[
        {
            "category":"Banks & Credit Unions",
            "subcategory":"Bank",
            "type":"Services"
        }
    ],
    "sg:phone":"+1   ",
    "sg:postcode":"07503",
    "sg:province":"NJ",
    "sg:tags":[
        "personal",
        "institution"
    ],
    "wof:name":"Columbia Expreso Enbia",
    "wof:placetype":"venue"
},
  "geometry": {"coordinates":[-74.161669,40.897249],"type":"Point"}
}