{
  "type": "Feature",
  "properties": {
    "iso:country":"US",
    "sg:address":"608 S Broadway",
    "sg:city":"Camden",
    "sg:classifiers":[
        {
            "category":"Social Services",
            "subcategory":"Child Care",
            "type":"Services"
        }
    ],
    "sg:phone":"+1 856 966 9166",
    "sg:postcode":"08103",
    "sg:province":"NJ",
    "sg:tags":[
        "day"
    ],
    "wof:name":"Our Little Ones Child Care Center",
    "wof:placetype":"venue"
},
  "geometry": {"coordinates":[-75.11918300000001,39.937763],"type":"Point"}
}