{
  "type": "Feature",
  "properties": {
    "iso:country":"US",
    "sg:address":"313 Millburn Ave",
    "sg:city":"Millburn",
    "sg:classifiers":[
        {
            "category":"Shopping",
            "type":"Retail Goods"
        }
    ],
    "sg:phone":"+1 973 379 4002",
    "sg:postcode":"07041",
    "sg:province":"NJ",
    "sg:tags":[
        "hearing",
        "equipment",
        "supply",
        "impaired"
    ],
    "wof:name":"Vp Audiology & Hearing Aid Ctr",
    "wof:placetype":"venue"
},
  "geometry": {"coordinates":[-74.30672800000001,40.724019],"type":"Point"}
}