{
  "type": "Feature",
  "properties": {
    "iso:country":"US",
    "sg:address":"34 Grady Rd",
    "sg:city":"Trenton",
    "sg:classifiers":[
        {
            "category":"Professional",
            "type":"Services"
        }
    ],
    "sg:phone":"+1 609 888 5840",
    "sg:postcode":"08610",
    "sg:province":"NJ",
    "sg:tags":[
        "establishment"
    ],
    "wof:name":"Allies Inc",
    "wof:placetype":"venue"
},
  "geometry": {"coordinates":[-74.71973199999999,40.207887],"type":"Point"}
}