{
  "type": "Feature",
  "properties": {
    "addr:full":"627 N Broad St Woodbury NJ 08096",
    "addr:housenumber":"627",
    "addr:postcode":"08096",
    "addr:street":"N Broad St",
    "iso:country":"US",
    "sg:address":"627 N Broad St",
    "sg:city":"Woodbury",
    "sg:classifiers":[
        {
            "category":"Restaurant",
            "type":"Food & Drink"
        }
    ],
    "sg:phone":"+1 856 845 3450",
    "sg:postcode":"08096",
    "sg:province":"NJ",
    "sg:tags":[
        "eating"
    ],
    "wof:name":"Angelo's Pizza",
    "wof:placetype":"venue"
},
  "geometry": {"coordinates":[-75.14685799999999,39.846148],"type":"Point"}
}