{
  "type": "Feature",
  "properties": {
    "iso:country":"US",
    "sg:address":"28 Pennsylvania Ave",
    "sg:city":"Flemington",
    "sg:classifiers":[
        {
            "category":"Building & Trades",
            "subcategory":"Construction",
            "type":"Services"
        }
    ],
    "sg:phone":"+1 908 782 3589",
    "sg:postcode":"08822",
    "sg:province":"NJ",
    "sg:tags":[
        "industrial"
    ],
    "wof:name":"Building History Inc",
    "wof:placetype":"venue"
},
  "geometry": {"coordinates":[-74.856086,40.513386],"type":"Point"}
}