{
  "type": "Feature",
  "properties": {
    "iso:country":"US",
    "sg:address":"25 Hartley Pl",
    "sg:city":"Fair Lawn",
    "sg:classifiers":[
        {
            "category":"Health Services",
            "subcategory":"Doctor",
            "type":"Services"
        }
    ],
    "sg:phone":"+1 201 797 8534",
    "sg:postcode":"07410",
    "sg:province":"NJ",
    "sg:tags":[
        "physician",
        "surgeon",
        "medical"
    ],
    "wof:name":"Anthony M Giliberti DO",
    "wof:placetype":"venue"
},
  "geometry": {"coordinates":[-74.114262,40.926242],"type":"Point"}
}