{
  "type": "Feature",
  "properties": {
    "iso:country":"US",
    "sg:address":"1600 N Albany Ave",
    "sg:city":"Atlantic City",
    "sg:classifiers":[
        {
            "category":"Travel",
            "subcategory":"Hotels & Motels",
            "type":"Entertainment"
        }
    ],
    "sg:phone":"+1   ",
    "sg:postcode":"08401",
    "sg:province":"NJ",
    "sg:tags":[
        "operation"
    ],
    "wof:name":"Sun & Surf Motel",
    "wof:placetype":"venue"
},
  "geometry": {"coordinates":[-74.478189,39.371214],"type":"Point"}
}