{
  "type": "Feature",
  "properties": {
    "iso:country":"US",
    "sg:address":"27 McKinley Ave",
    "sg:city":"Caldwell",
    "sg:classifiers":[
        {
            "category":"Professional",
            "subcategory":"Advertising",
            "type":"Services"
        }
    ],
    "sg:phone":"+1 973 403 8873",
    "sg:postcode":"07006",
    "sg:province":"NJ",
    "sg:tags":[
        "agency"
    ],
    "wof:name":"Lehmann Richard & Co",
    "wof:placetype":"venue"
},
  "geometry": {"coordinates":[-74.26987699999999,40.847682],"type":"Point"}
}