{
  "type": "Feature",
  "properties": {
    "iso:country":"US",
    "sg:address":"440 Lakeside Blvd",
    "sg:city":"Hopatcong",
    "sg:classifiers":[
        {
            "category":"Restaurant",
            "type":"Food & Drink"
        }
    ],
    "sg:phone":"+1   ",
    "sg:postcode":"07843",
    "sg:province":"NJ",
    "sg:tags":[
        "eating"
    ],
    "wof:name":"American Pig Roast",
    "wof:placetype":"venue"
},
  "geometry": {"coordinates":[-74.65611,40.939679],"type":"Point"}
}