{
  "type": "Feature",
  "properties": {
    "iso:country":"US",
    "sg:address":"109 Main St",
    "sg:city":"Hackensack",
    "sg:classifiers":[
        {
            "category":"Shopping",
            "subcategory":"Clothing, Apparel, & Fashions",
            "type":"Retail Goods"
        }
    ],
    "sg:phone":"+1   ",
    "sg:postcode":"07601",
    "sg:province":"NJ",
    "wof:name":"Mase 3",
    "wof:placetype":"venue"
},
  "geometry": {"coordinates":[-74.043656,40.881996],"type":"Point"}
}