{
  "type": "Feature",
  "properties": {
    "addr:full":"322 Park Ave Plainfield NJ 07060",
    "addr:housenumber":"322",
    "addr:postcode":"07060",
    "addr:street":"Park Ave",
    "iso:country":"US",
    "sg:address":"322 Park Ave",
    "sg:city":"Plainfield",
    "sg:classifiers":[
        {
            "category":"Social Services",
            "subcategory":"Child Care",
            "type":"Services"
        }
    ],
    "sg:phone":"+1 908 756 5040",
    "sg:postcode":"07060",
    "sg:province":"NJ",
    "sg:tags":[
        "day"
    ],
    "wof:name":"Precious Steps Child Care",
    "wof:placetype":"venue"
},
  "geometry": {"coordinates":[-74.420903,40.617014],"type":"Point"}
}