{
  "type": "Feature",
  "properties": {
    "addr:full":"104 N Spruce St Ramsey NJ 07446",
    "addr:housenumber":"104",
    "addr:postcode":"07446",
    "addr:street":"N Spruce St",
    "iso:country":"US",
    "sg:address":"104 N Spruce St",
    "sg:city":"Ramsey",
    "sg:classifiers":[
        {
            "category":"Professional",
            "subcategory":"Management & Consulting",
            "type":"Services"
        }
    ],
    "sg:phone":"+1 201 818 2630",
    "sg:postcode":"07446",
    "sg:province":"NJ",
    "sg:tags":[
        "computer",
        "system"
    ],
    "wof:name":"Highland Technology Group Inc",
    "wof:placetype":"venue"
},
  "geometry": {"coordinates":[-74.14050400000001,41.061632],"type":"Point"}
}