{
  "type": "Feature",
  "properties": {
    "iso:country":"US",
    "sg:address":"36 Morton Ct",
    "sg:city":"Trenton",
    "sg:classifiers":[
        {
            "category":"Health Services",
            "subcategory":"Doctor",
            "type":"Services"
        }
    ],
    "sg:phone":"+1 609 620 0022",
    "sg:postcode":"08648",
    "sg:province":"NJ",
    "sg:tags":[
        "physician",
        "surgeon"
    ],
    "wof:name":"Sherwood Vine MD",
    "wof:placetype":"venue"
},
  "geometry": {"coordinates":[-74.719419,40.281495],"type":"Point"}
}