{
  "type": "Feature",
  "properties": {
    "addr:full":"492 State Rte 28 Bridgewater NJ 08807",
    "addr:housenumber":"492",
    "addr:postcode":"08807",
    "addr:street":"State Rte 28",
    "iso:country":"US",
    "sg:address":"492 State Rte 28",
    "sg:city":"Bridgewater",
    "sg:classifiers":[
        {
            "category":"Personal",
            "subcategory":"Beauty Salon",
            "type":"Services"
        }
    ],
    "sg:phone":"+1 908 526 7441",
    "sg:postcode":"08807",
    "sg:province":"NJ",
    "sg:tags":[
        "shop"
    ],
    "wof:name":"Hair Unique",
    "wof:placetype":"venue"
},
  "geometry": {"coordinates":[-74.65087800000001,40.587698],"type":"Point"}
}