{
  "type": "Feature",
  "properties": {
    "iso:country":"US",
    "sg:address":"36 Park Ave",
    "sg:city":"Rutherford",
    "sg:classifiers":[
        {
            "category":"Shopping",
            "subcategory":"Clothing, Apparel, & Fashions",
            "type":"Retail Goods"
        }
    ],
    "sg:phone":"+1 201 935 1311",
    "sg:postcode":"07070",
    "sg:province":"NJ",
    "sg:tags":[
        "accessory",
        "clothing",
        "women's"
    ],
    "wof:name":"Three's Company",
    "wof:placetype":"venue"
},
  "geometry": {"coordinates":[-74.102594,40.828271],"type":"Point"}
}