{
  "type": "Feature",
  "properties": {
    "addr:full":"280 State Rte 35 Red Bank NJ 07701",
    "addr:housenumber":"280",
    "addr:postcode":"07701",
    "addr:street":"State Rte 35",
    "iso:country":"US",
    "sg:address":"280 State Rte 35",
    "sg:city":"Red Bank",
    "sg:classifiers":[
        {
            "category":"Professional",
            "type":"Services"
        },
        {
            "category":"Professional",
            "subcategory":"Management & Consulting",
            "type":"Services"
        }
    ],
    "sg:phone":"+1 732 741 2900",
    "sg:postcode":"07701",
    "sg:province":"NJ",
    "sg:tags":[
        "noncommercial",
        "o",
        "research"
    ],
    "wof:name":"Shields Institutional Service",
    "wof:placetype":"venue"
},
  "geometry": {"coordinates":[-74.083591,40.366092],"type":"Point"}
}