{
  "type": "Feature",
  "properties": {
    "addr:full":"175 Morris St Morristown NJ 07960",
    "addr:housenumber":"175",
    "addr:postcode":"07960",
    "addr:street":"Morris St",
    "iso:country":"US",
    "sg:address":"175 Morris St",
    "sg:city":"Morristown",
    "sg:classifiers":[
        {
            "category":"Retail",
            "subcategory":"Auto Repair",
            "type":"Services"
        }
    ],
    "sg:phone":"+1 973 267 1737",
    "sg:postcode":"07960",
    "sg:province":"NJ",
    "sg:tags":[
        "repairing",
        "automobile"
    ],
    "wof:name":"Thriftway Auto Ctr",
    "wof:placetype":"venue"
},
  "geometry": {"coordinates":[-74.469179,40.795321],"type":"Point"}
}