{
  "type": "Feature",
  "properties": {
    "addr:full":"230 Laird Ave Cliffside Park NJ 07010",
    "addr:housenumber":"230",
    "addr:postcode":"07010",
    "addr:street":"Laird Ave",
    "iso:country":"US",
    "sg:address":"230 Laird Ave",
    "sg:city":"Cliffside Park",
    "sg:classifiers":[
        {
            "category":"Recreation",
            "type":"Entertainment"
        }
    ],
    "sg:phone":"+1 201 840 1991",
    "sg:postcode":"07010",
    "sg:province":"NJ",
    "wof:name":"World Gymnastics Academy Inc",
    "wof:placetype":"venue"
},
  "geometry": {"coordinates":[-73.991761,40.812129],"type":"Point"}
}