{
  "type": "Feature",
  "properties": {
    "iso:country":"US",
    "sg:address":"3 D'Altrui Dr",
    "sg:city":"Hillsborough",
    "sg:classifiers":[
        {
            "category":"Health Services",
            "subcategory":"Health Practitioner",
            "type":"Services"
        }
    ],
    "sg:phone":"+1   ",
    "sg:postcode":"08844",
    "sg:province":"NJ",
    "wof:name":"Pasqual Sargiotto Adolscnt & F",
    "wof:placetype":"venue"
},
  "geometry": {"coordinates":[-74.586664,40.470383],"type":"Point"}
}