{
  "type": "Feature",
  "properties": {
    "addr:full":"1779 Delsea Dr Woodbury NJ 08096",
    "addr:housenumber":"1779",
    "addr:postcode":"08096",
    "addr:street":"Delsea Dr",
    "iso:country":"US",
    "sg:address":"1779 Delsea Dr",
    "sg:city":"Woodbury",
    "sg:classifiers":[
        {
            "category":"Building & Trades",
            "subcategory":"Construction",
            "type":"Services"
        }
    ],
    "sg:phone":"+1 856 464 8501",
    "sg:postcode":"08096",
    "sg:province":"NJ",
    "sg:tags":[
        "excavating",
        "contractor"
    ],
    "wof:name":"Bogey Trucking and Paving Inc",
    "wof:placetype":"venue"
},
  "geometry": {"coordinates":[-75.124466,39.809821],"type":"Point"}
}