{
  "type": "Feature",
  "properties": {
    "iso:country":"US",
    "sg:address":"1314 S Broad St",
    "sg:city":"Trenton",
    "sg:classifiers":[
        {
            "category":"Autos & Motor Vehicles",
            "subcategory":"Automobile Sales",
            "type":"Retail Goods"
        }
    ],
    "sg:phone":"+1   ",
    "sg:postcode":"08610",
    "sg:province":"NJ",
    "sg:tags":[
        "used"
    ],
    "wof:name":"Mid-Town Auto Sales",
    "wof:placetype":"venue"
},
  "geometry": {"coordinates":[-74.73890900000001,40.202423],"type":"Point"}
}