{
  "type": "Feature",
  "properties": {
    "addr:full":"69 King St Ste 11 Dover NJ 07801",
    "addr:housenumber":"69;11",
    "addr:postcode":"07801",
    "addr:street":"King St Ste",
    "iso:country":"US",
    "sg:address":"69 King St Ste 11",
    "sg:city":"Dover",
    "sg:classifiers":[
        {
            "category":"Shopping",
            "subcategory":"Books",
            "type":"Retail Goods"
        }
    ],
    "sg:phone":"+1 973 361 1100",
    "sg:postcode":"07801",
    "sg:province":"NJ",
    "sg:tags":[
        "bookstore"
    ],
    "sg:website":"www.backtobooks.com",
    "wof:name":"Back To Books Inc",
    "wof:placetype":"venue"
},
  "geometry": {"coordinates":[-74.551845,40.890942],"type":"Point"}
}