{
  "type": "Feature",
  "properties": {
    "iso:country":"US",
    "sg:address":"302 Redwood Ave",
    "sg:city":"Absecon",
    "sg:classifiers":[
        {
            "category":"Professional",
            "type":"Services"
        }
    ],
    "sg:phone":"+1   ",
    "sg:postcode":"08205",
    "sg:province":"NJ",
    "wof:name":"Designworks Studio",
    "wof:placetype":"venue"
},
  "geometry": {"coordinates":[-74.548863,39.477495],"type":"Point"}
}