{
  "type": "Feature",
  "properties": {
    "iso:country":"US",
    "sg:address":"39 E Railroad Ave",
    "sg:city":"Monroe Township",
    "sg:classifiers":[
        {
            "category":"Restaurant",
            "type":"Food & Drink"
        }
    ],
    "sg:phone":"+1   ",
    "sg:postcode":"08831",
    "sg:province":"NJ",
    "sg:tags":[
        "eating"
    ],
    "wof:name":"Sir Ives Catering Co Inc",
    "wof:placetype":"venue"
},
  "geometry": {"coordinates":[-74.436824,40.349472],"type":"Point"}
}