{
  "type": "Feature",
  "properties": {
    "iso:country":"US",
    "sg:address":"163 Decker Rd",
    "sg:city":"Sussex",
    "sg:classifiers":[
        {
            "category":"Retail",
            "subcategory":"Laundry & Dry Cleaning",
            "type":"Services"
        },
        {
            "category":"Building & Trades",
            "subcategory":"Cleaning & Sanitation",
            "type":"Services"
        }
    ],
    "sg:phone":"+1 973 875 8634",
    "sg:postcode":"07461",
    "sg:province":"NJ",
    "sg:tags":[
        "cleaner",
        "carpet",
        "rug",
        "janitorial"
    ],
    "wof:name":"Aero Century Maintenance Company",
    "wof:placetype":"venue"
},
  "geometry": {"coordinates":[-74.67235100000001,41.206086],"type":"Point"}
}