{
  "type": "Feature",
  "properties": {
    "addr:full":"45 Sunset Strip Succasunna NJ 07876",
    "addr:housenumber":"45",
    "addr:postcode":"07876",
    "addr:street":"Sunset Strip",
    "iso:country":"US",
    "sg:address":"45 Sunset Strip",
    "sg:city":"Succasunna",
    "sg:classifiers":[
        {
            "category":"Personal",
            "subcategory":"Beauty Salon",
            "type":"Services"
        }
    ],
    "sg:phone":"+1 973 584 9030",
    "sg:postcode":"07876",
    "sg:province":"NJ",
    "sg:tags":[
        "shop",
        "school"
    ],
    "wof:name":"Capri Institute Cosmetology Tr",
    "wof:placetype":"venue"
},
  "geometry": {"coordinates":[-74.649528,40.867403],"type":"Point"}
}