{
  "type": "Feature",
  "properties": {
    "iso:country":"US",
    "sg:address":"1 Glass St",
    "sg:city":"Bridgeton",
    "sg:classifiers":[
        {
            "category":"Freight",
            "type":"Transportation"
        }
    ],
    "sg:phone":"+1 856 451 9091",
    "sg:postcode":"08302",
    "sg:province":"NJ",
    "sg:tags":[
        "warehouse",
        "general",
        "storage",
        "warehousing"
    ],
    "wof:name":"Carpenter Warehousing",
    "wof:placetype":"venue"
},
  "geometry": {"coordinates":[-75.233093,39.425186],"type":"Point"}
}