{
  "type": "Feature",
  "properties": {
    "addr:full":"104 Chestnut St Ridgewood NJ 07450",
    "addr:housenumber":"104",
    "addr:postcode":"07450",
    "addr:street":"Chestnut St",
    "iso:country":"US",
    "sg:address":"104 Chestnut St",
    "sg:city":"Ridgewood",
    "sg:classifiers":[
        {
            "category":"Health Services",
            "subcategory":"Health Practitioner",
            "type":"Services"
        }
    ],
    "sg:phone":"+1 201 493 8111",
    "sg:postcode":"07450",
    "sg:province":"NJ",
    "sg:tags":[
        "therapist",
        "physical"
    ],
    "wof:name":"Ridgewood Physical Thrpy & Rhb",
    "wof:placetype":"venue"
},
  "geometry": {"coordinates":[-74.118183,40.983184],"type":"Point"}
}