{
  "type": "Feature",
  "properties": {
    "addr:full":"211 Hawthorne Ave Haddonfield NJ 08033",
    "addr:housenumber":"211",
    "addr:postcode":"08033",
    "addr:street":"Hawthorne Ave",
    "iso:country":"US",
    "sg:address":"211 Hawthorne Ave",
    "sg:city":"Haddonfield",
    "sg:classifiers":[
        {
            "category":"Wholesale",
            "subcategory":"Non-durable Goods",
            "type":"Manufacturing & Wholesale Goods"
        }
    ],
    "sg:phone":"+1 856 427 7878",
    "sg:postcode":"08033",
    "sg:province":"NJ",
    "wof:name":"Horton Jacobs Import Export",
    "wof:placetype":"venue"
},
  "geometry": {"coordinates":[-75.033162,39.906823],"type":"Point"}
}