{
  "type": "Feature",
  "properties": {
    "addr:full":"151 E 33rd St Paterson NJ 07514",
    "addr:housenumber":"151",
    "addr:postcode":"07514",
    "addr:street":"E 33Rd St",
    "iso:country":"US",
    "sg:address":"151 E 33rd St",
    "sg:city":"Paterson",
    "sg:classifiers":[
        {
            "category":"Organizations",
            "subcategory":"Non-profit Organization",
            "type":"Services"
        },
        {
            "category":"Banks & Credit Unions",
            "subcategory":"Bank",
            "type":"Services"
        }
    ],
    "sg:phone":"+1 973 742 8395",
    "sg:postcode":"07514",
    "sg:province":"NJ",
    "sg:tags":[
        "loan",
        "broker",
        "association"
    ],
    "wof:name":"Paterson Hebrew Free Loan Assn",
    "wof:placetype":"venue"
},
  "geometry": {"coordinates":[-74.141732,40.918565],"type":"Point"}
}