{
  "type": "Feature",
  "properties": {
    "iso:country":"US",
    "sg:address":"148 Deer Trl N",
    "sg:city":"Ramsey",
    "sg:classifiers":[
        {
            "category":"Freight",
            "type":"Transportation"
        }
    ],
    "sg:phone":"+1 201 825 7705",
    "sg:postcode":"07446",
    "sg:province":"NJ",
    "sg:tags":[
        "international"
    ],
    "wof:name":"Hag International LLC",
    "wof:placetype":"venue"
},
  "geometry": {"coordinates":[-74.169372,41.051612],"type":"Point"}
}