{
  "type": "Feature",
  "properties": {
    "addr:full":"111 Lakeview Ave Clifton NJ 07011",
    "addr:housenumber":"111",
    "addr:postcode":"07011",
    "addr:street":"Lakeview Ave",
    "iso:country":"US",
    "sg:address":"111 Lakeview Ave",
    "sg:city":"Clifton",
    "sg:classifiers":[
        {
            "category":"Food & Beverages",
            "subcategory":"Liquor & Beverages",
            "type":"Retail Goods"
        }
    ],
    "sg:phone":"+1 973 772 1117",
    "sg:postcode":"07011",
    "sg:province":"NJ",
    "sg:tags":[
        "beer",
        "spirit",
        "store",
        "wine"
    ],
    "wof:name":"Clifton Wine & Liquors",
    "wof:placetype":"venue"
},
  "geometry": {"coordinates":[-74.136803,40.878799],"type":"Point"}
}