{
  "type": "Feature",
  "properties": {
    "iso:country":"US",
    "sg:address":"108 Main St",
    "sg:city":"Allenhurst",
    "sg:classifiers":[
        {
            "category":"Professional",
            "subcategory":"Accounting & Tax Preparation",
            "type":"Services"
        }
    ],
    "sg:phone":"+1 732 531 3355",
    "sg:postcode":"07711",
    "sg:province":"NJ",
    "sg:tags":[
        "accountant",
        "auditing",
        "bookkeeping"
    ],
    "wof:name":"Paul R Greenblatt & Co",
    "wof:placetype":"venue"
},
  "geometry": {"coordinates":[-74.00572099999999,40.238041],"type":"Point"}
}