{
  "type": "Feature",
  "properties": {
    "addr:full":"1021 Pinehurst Ests Lakehurst NJ 08733",
    "addr:housenumber":"1021",
    "addr:postcode":"08733",
    "addr:street":"Pinehurst Ests",
    "iso:country":"US",
    "sg:address":"1021 Pinehurst Ests",
    "sg:city":"Lakehurst",
    "sg:classifiers":[
        {
            "category":"Government",
            "subcategory":"Office",
            "type":"Public Place"
        }
    ],
    "sg:phone":"+1   ",
    "sg:postcode":"08733",
    "sg:province":"NJ",
    "sg:tags":[
        "national",
        "security"
    ],
    "wof:name":"Lakehurst Navy Air Engrg Stn",
    "wof:placetype":"venue"
},
  "geometry": {"coordinates":[-74.32820700000001,40.01622],"type":"Point"}
}