{
  "type": "Feature",
  "properties": {
    "iso:country":"US",
    "sg:address":"99 Ivy Ave",
    "sg:city":"Moorestown",
    "sg:classifiers":[
        {
            "category":"Professional",
            "subcategory":"Management & Consulting",
            "type":"Services"
        },
        {
            "category":"Professional",
            "subcategory":"Business Services",
            "type":"Services"
        },
        {
            "category":"Organizations",
            "subcategory":"Membership Organization",
            "type":"Services"
        }
    ],
    "sg:phone":"+1 856 630 1858",
    "sg:postcode":"08057",
    "sg:province":"NJ",
    "sg:tags":[
        "product",
        "consultant",
        "environmental",
        "ecological",
        "conservation"
    ],
    "wof:name":"Green Environmental Organization (GEO)",
    "wof:placetype":"venue"
},
  "geometry": {"coordinates":[-74.972359,39.95232],"type":"Point"}
}