{
  "type": "Feature",
  "properties": {
    "iso:country":"US",
    "sg:address":"1415 State Rte 70",
    "sg:city":"Cherry Hill",
    "sg:classifiers":[
        {
            "category":"Social Services",
            "type":"Services"
        }
    ],
    "sg:phone":"+1 856 616 0884",
    "sg:postcode":"08034",
    "sg:province":"NJ",
    "sg:tags":[
        "organization",
        "welfare"
    ],
    "wof:name":"Make A Wish",
    "wof:placetype":"venue"
},
  "geometry": {"coordinates":[-74.988653,39.91009],"type":"Point"}
}