{
  "type": "Feature",
  "properties": {
    "iso:country":"US",
    "sg:address":"56 E Bay Ave",
    "sg:city":"Manahawkin",
    "sg:classifiers":[
        {
            "category":"Building & Trades",
            "subcategory":"Landscaping Services",
            "type":"Services"
        }
    ],
    "sg:phone":"+1 609 597 3600",
    "sg:postcode":"08050",
    "sg:province":"NJ",
    "wof:name":"Men-At Work Landscaping",
    "wof:placetype":"venue"
},
  "geometry": {"coordinates":[-74.25722,39.694393],"type":"Point"}
}