{
  "type": "Feature",
  "properties": {
    "addr:full":"629 Wood St Vineland NJ 08360",
    "addr:housenumber":"629",
    "addr:postcode":"08360",
    "addr:street":"Wood St",
    "iso:country":"US",
    "sg:address":"629 Wood St",
    "sg:city":"Vineland",
    "sg:classifiers":[
        {
            "category":"Professional",
            "type":"Services"
        }
    ],
    "sg:phone":"+1   ",
    "sg:postcode":"08360",
    "sg:province":"NJ",
    "wof:name":"Underwood & Micklin",
    "wof:placetype":"venue"
},
  "geometry": {"coordinates":[-75.02153300000001,39.486964],"type":"Point"}
}