{
  "type": "Feature",
  "properties": {
    "addr:full":"344 Lincoln Ave Hawthorne NJ 07506",
    "addr:housenumber":"344",
    "addr:postcode":"07506",
    "addr:street":"Lincoln Ave",
    "iso:country":"US",
    "sg:address":"344 Lincoln Ave",
    "sg:city":"Hawthorne",
    "sg:classifiers":[
        {
            "category":"Food & Beverages",
            "subcategory":"Bakery",
            "type":"Retail Goods"
        }
    ],
    "sg:phone":"+1 973 427 2295",
    "sg:postcode":"07506",
    "sg:province":"NJ",
    "sg:tags":[
        "bagel"
    ],
    "wof:name":"Lincoln Bagels",
    "wof:placetype":"venue"
},
  "geometry": {"coordinates":[-74.144961,40.954167],"type":"Point"}
}