{
  "type": "Feature",
  "properties": {
    "iso:country":"US",
    "sg:address":"70 E Holly Ave",
    "sg:city":"Sewell",
    "sg:classifiers":[
        {
            "category":"Professional",
            "subcategory":"Management & Consulting",
            "type":"Services"
        }
    ],
    "sg:phone":"+1 856 582 8620",
    "sg:postcode":"08080",
    "sg:province":"NJ",
    "sg:tags":[
        "consultant"
    ],
    "wof:name":"Sauper Associates",
    "wof:placetype":"venue"
},
  "geometry": {"coordinates":[-75.091666,39.758407],"type":"Point"}
}