{
  "type": "Feature",
  "properties": {
    "iso:country":"US",
    "sg:address":"1405 N Maple Dr",
    "sg:city":"Vineland",
    "sg:classifiers":[
        {
            "category":"Retail",
            "subcategory":"Auto Repair",
            "type":"Services"
        }
    ],
    "sg:phone":"+1   ",
    "sg:postcode":"08360",
    "sg:province":"NJ",
    "sg:tags":[
        "general"
    ],
    "wof:name":"Dave Glover Enterprises",
    "wof:placetype":"venue"
},
  "geometry": {"coordinates":[-74.998977,39.493022],"type":"Point"}
}