{
  "type": "Feature",
  "properties": {
    "addr:full":"714 E Main St Moorestown NJ 08057",
    "addr:housenumber":"714",
    "addr:postcode":"08057",
    "addr:street":"E Main St",
    "iso:country":"US",
    "sg:address":"714 E Main St",
    "sg:city":"Moorestown",
    "sg:classifiers":[
        {
            "category":"Professional",
            "subcategory":"Lawyer & Legal Services",
            "type":"Services"
        }
    ],
    "sg:phone":"+1 856 608 9797",
    "sg:postcode":"08057",
    "sg:province":"NJ",
    "sg:tags":[
        "attorney"
    ],
    "sg:website":"www.whbuckman.com",
    "wof:name":"William H Buckman",
    "wof:placetype":"venue"
},
  "geometry": {"coordinates":[-74.918165,39.972997],"type":"Point"}
}