{
  "type": "Feature",
  "properties": {
    "iso:country":"US",
    "sg:address":"733 Green Mount Ave",
    "sg:city":"Woodbury",
    "sg:classifiers":[
        {
            "category":"Professional",
            "subcategory":"Management & Consulting",
            "type":"Services"
        }
    ],
    "sg:phone":"+1   ",
    "sg:postcode":"08096",
    "sg:province":"NJ",
    "wof:name":"Shane Michael Marketing",
    "wof:placetype":"venue"
},
  "geometry": {"coordinates":[-75.092484,39.801797],"type":"Point"}
}