{
  "type": "Feature",
  "properties": {
    "iso:country":"US",
    "sg:address":"204 Holly Ln",
    "sg:city":"Linwood",
    "sg:classifiers":[
        {
            "category":"Professional",
            "subcategory":"Lawyer & Legal Services",
            "type":"Services"
        }
    ],
    "sg:phone":"+1 609 653 8800",
    "sg:postcode":"08221",
    "sg:province":"NJ",
    "sg:tags":[
        "attorney"
    ],
    "wof:name":"Paarz Master Koernig Crammer",
    "wof:placetype":"venue"
},
  "geometry": {"coordinates":[-74.572079,39.338225],"type":"Point"}
}