{
  "type": "Feature",
  "properties": {
    "iso:country":"US",
    "sg:address":"40 Hillside Dr",
    "sg:city":"Haledon",
    "sg:classifiers":[
        {
            "category":"Retail",
            "subcategory":"Repair Shop",
            "type":"Services"
        }
    ],
    "sg:phone":"+1   ",
    "sg:postcode":"07508",
    "sg:province":"NJ",
    "wof:name":"Dave Walsh Electronics",
    "wof:placetype":"venue"
},
  "geometry": {"coordinates":[-74.192994,40.970974],"type":"Point"}
}