{
  "type": "Feature",
  "properties": {
    "addr:full":"13 Red Fox Run Englishtown NJ 07726",
    "addr:housenumber":"13",
    "addr:postcode":"07726",
    "addr:street":"Red Fox Run",
    "iso:country":"US",
    "sg:address":"13 Red Fox Run",
    "sg:city":"Englishtown",
    "sg:classifiers":[
        {
            "category":"Professional",
            "subcategory":"Computer Services",
            "type":"Services"
        }
    ],
    "sg:phone":"+1 732 431 0193",
    "sg:postcode":"07726",
    "sg:province":"NJ",
    "sg:tags":[
        "consulting",
        "design",
        "system",
        "analysis"
    ],
    "wof:name":"Palma-Lee Associates Inc",
    "wof:placetype":"venue"
},
  "geometry": {"coordinates":[-74.343047,40.24196],"type":"Point"}
}