{
  "type": "Feature",
  "properties": {
    "iso:country":"US",
    "sg:address":"17 N Broad St",
    "sg:city":"Woodbury",
    "sg:classifiers":[
        {
            "category":"Food & Beverages",
            "subcategory":"Candy",
            "type":"Retail Goods"
        },
        {
            "category":"Food & Beverages",
            "subcategory":"Specialty",
            "type":"Retail Goods"
        }
    ],
    "sg:phone":"+1 856 848 0485",
    "sg:postcode":"08096",
    "sg:province":"NJ",
    "sg:tags":[
        "confectionery",
        "nuts-edible"
    ],
    "wof:name":"Nut Shop",
    "wof:placetype":"venue"
},
  "geometry": {"coordinates":[-75.152961,39.838431],"type":"Point"}
}