{
  "type": "Feature",
  "properties": {
    "addr:full":"575 W Mount Pleasant Ave  Livingston NJ 07039",
    "addr:housenumber":"575",
    "addr:postcode":"07039",
    "addr:street":"W Mount Pleasant Ave",
    "iso:country":"US",
    "sg:address":"575 W Mount Pleasant Ave ",
    "sg:city":"Livingston",
    "sg:classifiers":[
        {
            "category":"Deli",
            "type":"Food & Drink"
        }
    ],
    "sg:menulink":"http://www.allmenus.com/nj/livingston/293655-irvings-delicatessen/menu/",
    "sg:phone":"+1 973 994 5100",
    "sg:postcode":"07039",
    "sg:province":"NJ",
    "wof:name":"Irving's Delicatessen",
    "wof:placetype":"venue"
},
  "geometry": {"coordinates":[-74.352585,40.797513],"type":"Point"}
}