{
  "type": "Feature",
  "properties": {
    "iso:country":"US",
    "sg:address":"43 Silverton Ave",
    "sg:city":"Little Silver",
    "sg:classifiers":[
        {
            "category":"Professional",
            "subcategory":"Business Services",
            "type":"Services"
        }
    ],
    "sg:phone":"+1 732 747 5574",
    "sg:postcode":"07739",
    "sg:province":"NJ",
    "sg:tags":[
        "estimating"
    ],
    "wof:name":"Cost Resources",
    "wof:placetype":"venue"
},
  "geometry": {"coordinates":[-74.04919700000001,40.34003],"type":"Point"}
}