{
  "type": "Feature",
  "properties": {
    "iso:country":"US",
    "sg:address":"22 Letts Landing Rd",
    "sg:city":"Waretown",
    "sg:classifiers":[
        {
            "category":"Building & Trades",
            "subcategory":"Construction",
            "type":"Services"
        }
    ],
    "sg:phone":"+1 609 693 8076",
    "sg:postcode":"08758",
    "sg:province":"NJ",
    "sg:tags":[
        "painter"
    ],
    "wof:name":"Don's Drywall",
    "wof:placetype":"venue"
},
  "geometry": {"coordinates":[-74.191575,39.801468],"type":"Point"}
}