{
  "type": "Feature",
  "properties": {
    "addr:full":"307 N Clinton Ave Trenton NJ 08638",
    "addr:housenumber":"307",
    "addr:postcode":"08638",
    "addr:street":"N Clinton Ave",
    "iso:country":"US",
    "sg:address":"307 N Clinton Ave",
    "sg:city":"Trenton",
    "sg:classifiers":[
        {
            "category":"Wholesale",
            "subcategory":"Hardware",
            "type":"Manufacturing & Wholesale Goods"
        }
    ],
    "sg:phone":"+1 609 393 0313",
    "sg:postcode":"08638",
    "sg:province":"NJ",
    "wof:name":"Fastenal Company",
    "wof:placetype":"venue"
},
  "geometry": {"coordinates":[-74.751046,40.228533],"type":"Point"}
}