{
  "type": "Feature",
  "properties": {
    "iso:country":"US",
    "sg:address":"100 6th Ave",
    "sg:city":"Paterson",
    "sg:classifiers":[
        {
            "category":"Manufacturing",
            "subcategory":"Food",
            "type":"Manufacturing & Wholesale Goods"
        }
    ],
    "sg:phone":"+1 973 278 2800",
    "sg:postcode":"07524",
    "sg:province":"NJ",
    "sg:tags":[
        "bakery",
        "prod",
        "cookie"
    ],
    "sg:website":"www.kontos.com",
    "wof:name":"Kontos Foods Inc",
    "wof:placetype":"venue"
},
  "geometry": {"coordinates":[-74.160735,40.933911],"type":"Point"}
}