{
  "type": "Feature",
  "properties": {
    "iso:country":"US",
    "sg:address":"1151 E Jersey St",
    "sg:city":"Elizabeth",
    "sg:classifiers":[
        {
            "category":"Health Services",
            "subcategory":"Doctor",
            "type":"Services"
        }
    ],
    "sg:phone":"+1 908 289 0222",
    "sg:postcode":"07201",
    "sg:province":"NJ",
    "sg:tags":[
        "physician",
        "surgeon"
    ],
    "wof:name":"Spinal & Head Trama",
    "wof:placetype":"venue"
},
  "geometry": {"coordinates":[-74.21437299999999,40.66529],"type":"Point"}
}