{
  "type": "Feature",
  "properties": {
    "addr:full":"1722 Hurffville Rd Sewell NJ 08080",
    "addr:housenumber":"1722",
    "addr:postcode":"08080",
    "addr:street":"Hurffville Rd",
    "iso:country":"US",
    "sg:address":"1722 Hurffville Rd",
    "sg:city":"Sewell",
    "sg:classifiers":[
        {
            "category":"Wholesale",
            "subcategory":"Electrical",
            "type":"Manufacturing & Wholesale Goods"
        }
    ],
    "sg:phone":"+1 856 228 3833",
    "sg:postcode":"08080",
    "sg:province":"NJ",
    "sg:tags":[
        "battery"
    ],
    "wof:name":"Redy Battery Sales & Svc",
    "wof:placetype":"venue"
},
  "geometry": {"coordinates":[-75.09884099999999,39.793628],"type":"Point"}
}