{
  "type": "Feature",
  "properties": {
    "addr:full":"108 Goodwin Ave Newark NJ 07112",
    "addr:housenumber":"108",
    "addr:postcode":"07112",
    "addr:street":"Goodwin Ave",
    "iso:country":"US",
    "sg:address":"108 Goodwin Ave",
    "sg:city":"Newark",
    "sg:classifiers":[
        {
            "category":"Professional",
            "type":"Services"
        }
    ],
    "sg:phone":"+1   ",
    "sg:postcode":"07112",
    "sg:province":"NJ",
    "wof:name":"Bonns Environmental Systems",
    "wof:placetype":"venue"
},
  "geometry": {"coordinates":[-74.211631,40.714888],"type":"Point"}
}