{
  "type": "Feature",
  "properties": {
    "addr:full":"579 Raritan Rd Roselle NJ 07203",
    "addr:housenumber":"579",
    "addr:postcode":"07203",
    "addr:street":"Raritan Rd",
    "iso:country":"US",
    "sg:address":"579 Raritan Rd",
    "sg:city":"Roselle",
    "sg:classifiers":[
        {
            "category":"Health Services",
            "subcategory":"Optometrist",
            "type":"Services"
        }
    ],
    "sg:phone":"+1 908 241 5777",
    "sg:postcode":"07203",
    "sg:province":"NJ",
    "wof:name":"Lonsk Stuart M PA",
    "wof:placetype":"venue"
},
  "geometry": {"coordinates":[-74.272797,40.644699],"type":"Point"}
}