{
  "type": "Feature",
  "properties": {
    "addr:full":"63 Eldora Rd Parsippany NJ 07054",
    "addr:housenumber":"63",
    "addr:postcode":"07054",
    "addr:street":"Eldora Rd",
    "iso:country":"US",
    "sg:address":"63 Eldora Rd",
    "sg:city":"Parsippany",
    "sg:classifiers":[
        {
            "category":"Freight",
            "type":"Transportation"
        }
    ],
    "sg:phone":"+1 973 296 2379",
    "sg:postcode":"07054",
    "sg:province":"NJ",
    "sg:tags":[
        "operator",
        "trucking"
    ],
    "wof:name":"Ndj Bulk Transport LLC",
    "wof:placetype":"venue"
},
  "geometry": {"coordinates":[-74.431679,40.84655],"type":"Point"}
}