{
  "type": "Feature",
  "properties": {
    "iso:country":"US",
    "sg:address":"3 Princess Rd",
    "sg:city":"Trenton",
    "sg:classifiers":[
        {
            "category":"Wholesale",
            "subcategory":"Chemicals & Plastics",
            "type":"Manufacturing & Wholesale Goods"
        }
    ],
    "sg:phone":"+1 609 844 0801",
    "sg:postcode":"08648",
    "sg:province":"NJ",
    "sg:tags":[
        "industry",
        "intermediary",
        "for",
        "specialty"
    ],
    "wof:name":"Chemical Consultants Inc",
    "wof:placetype":"venue"
},
  "geometry": {"coordinates":[-74.70975900000001,40.2839],"type":"Point"}
}