{
  "type": "Feature",
  "properties": {
    "iso:country":"US",
    "sg:address":"409 E Baldwin St",
    "sg:city":"Hackettstown",
    "sg:classifiers":[
        {
            "category":"Social Services",
            "subcategory":"Child Care",
            "type":"Services"
        }
    ],
    "sg:phone":"+1 908 852 2285",
    "sg:postcode":"07840",
    "sg:province":"NJ",
    "sg:tags":[
        "kindergarten",
        "academic",
        "school"
    ],
    "wof:name":"Gethsemane Nursery School",
    "wof:placetype":"venue"
},
  "geometry": {"coordinates":[-74.83429099999999,40.859605],"type":"Point"}
}