{
  "type": "Feature",
  "properties": {
    "addr:full":"53 Childsworth Ave Bernardsville NJ 07924",
    "addr:housenumber":"53",
    "addr:postcode":"07924",
    "addr:street":"Childsworth Ave",
    "iso:country":"US",
    "sg:address":"53 Childsworth Ave",
    "sg:city":"Bernardsville",
    "sg:classifiers":[
        {
            "category":"Food & Beverages",
            "subcategory":"Groceries & Convenience Stores",
            "type":"Retail Goods"
        }
    ],
    "sg:phone":"+1   ",
    "sg:postcode":"07924",
    "sg:province":"NJ",
    "sg:tags":[
        "legal"
    ],
    "wof:name":"David S Gaus",
    "wof:placetype":"venue"
},
  "geometry": {"coordinates":[-74.561747,40.726343],"type":"Point"}
}