{
  "type": "Feature",
  "properties": {
    "iso:country":"US",
    "sg:address":"204 Haledon Ave",
    "sg:city":"Haledon",
    "sg:classifiers":[
        {
            "category":"Health Services",
            "subcategory":"Doctor",
            "type":"Services"
        }
    ],
    "sg:phone":"+1 973 790 0070",
    "sg:postcode":"07508",
    "sg:province":"NJ",
    "sg:tags":[
        "medical"
    ],
    "wof:name":"Bhatnagar Dr N P MD",
    "wof:placetype":"venue"
},
  "geometry": {"coordinates":[-74.175262,40.932215],"type":"Point"}
}