{
  "type": "Feature",
  "properties": {
    "addr:full":"326 37th St Union City NJ 07087",
    "addr:housenumber":"326",
    "addr:postcode":"07087",
    "addr:street":"37Th St",
    "iso:country":"US",
    "sg:address":"326 37th St",
    "sg:city":"Union City",
    "sg:classifiers":[
        {
            "category":"Building & Trades",
            "subcategory":"Pest Control",
            "type":"Services"
        }
    ],
    "sg:phone":"+1   ",
    "sg:postcode":"07087",
    "sg:province":"NJ",
    "wof:name":"Mr Bugman Inc",
    "wof:placetype":"venue"
},
  "geometry": {"coordinates":[-74.025829,40.774027],"type":"Point"}
}