{
  "type": "Feature",
  "properties": {
    "addr:full":"1001 Timber Oaks Rd Edison NJ 08820",
    "addr:housenumber":"1001",
    "addr:postcode":"08820",
    "addr:street":"Timber Oaks Rd",
    "iso:country":"US",
    "sg:address":"1001 Timber Oaks Rd",
    "sg:city":"Edison",
    "sg:classifiers":[
        {
            "category":"Shopping",
            "subcategory":"Pharmacy",
            "type":"Retail Goods"
        }
    ],
    "sg:phone":"+1 908 755 3333",
    "sg:postcode":"08820",
    "sg:province":"NJ",
    "sg:tags":[
        "pharmaceutical",
        "consultant"
    ],
    "wof:name":"Global Quality Consultants",
    "wof:placetype":"venue"
},
  "geometry": {"coordinates":[-74.370848,40.587124],"type":"Point"}
}