{
  "type": "Feature",
  "properties": {
    "addr:full":"10 Old Milford Ln West Milford NJ 07480",
    "addr:housenumber":"10",
    "addr:postcode":"07480",
    "addr:street":"Old Milford Ln",
    "iso:country":"US",
    "sg:address":"10 Old Milford Ln",
    "sg:city":"West Milford",
    "sg:classifiers":[
        {
            "category":"Social Services",
            "subcategory":"Child Care",
            "type":"Services"
        }
    ],
    "sg:phone":"+1 973 728 0731",
    "sg:postcode":"07480",
    "sg:province":"NJ",
    "wof:name":"Diane Kohlsaat's Child Care",
    "wof:placetype":"venue"
},
  "geometry": {"coordinates":[-74.40607199999999,41.102707],"type":"Point"}
}