{
  "type": "Feature",
  "properties": {
    "iso:country":"US",
    "sg:address":"150 Clove Rd",
    "sg:city":"Little Falls",
    "sg:classifiers":[
        {
            "category":"Professional",
            "subcategory":"Business Services",
            "type":"Services"
        }
    ],
    "sg:phone":"+1 973 812 1988",
    "sg:postcode":"07424",
    "sg:province":"NJ",
    "sg:tags":[
        "interior",
        "consultant",
        "design",
        "decorator"
    ],
    "wof:name":"TUK Assoc Inc",
    "wof:placetype":"venue"
},
  "geometry": {"coordinates":[-74.196275,40.873035],"type":"Point"}
}