{
  "type": "Feature",
  "properties": {
    "iso:country":"US",
    "sg:address":"202 Yorktown Blvd",
    "sg:city":"Hammonton",
    "sg:classifiers":[
        {
            "category":"Professional",
            "subcategory":"Management & Consulting",
            "type":"Services"
        }
    ],
    "sg:phone":"+1   ",
    "sg:postcode":"08037",
    "sg:province":"NJ",
    "sg:tags":[
        "business"
    ],
    "wof:name":"AMR Consultants",
    "wof:placetype":"venue"
},
  "geometry": {"coordinates":[-74.76256100000001,39.634507],"type":"Point"}
}