{
  "type": "Feature",
  "properties": {
    "iso:country":"US",
    "sg:address":"842 Delsea Dr N",
    "sg:city":"Glassboro",
    "sg:classifiers":[
        {
            "category":"Retail",
            "subcategory":"Laundry & Dry Cleaning",
            "type":"Services"
        }
    ],
    "sg:phone":"+1 856 863 1611",
    "sg:postcode":"08028",
    "sg:province":"NJ",
    "sg:tags":[
        "cleaners"
    ],
    "wof:name":"Double Tree Quality Cleaners",
    "wof:placetype":"venue"
},
  "geometry": {"coordinates":[-75.115836,39.724087],"type":"Point"}
}