{
  "type": "Feature",
  "properties": {
    "iso:country":"US",
    "sg:address":"49 Kirkwood Rd",
    "sg:city":"Gibbsboro",
    "sg:classifiers":[
        {
            "category":"Government",
            "subcategory":"Court House",
            "type":"Public Place"
        }
    ],
    "sg:phone":"+1 856 783 6956",
    "sg:postcode":"08026",
    "sg:province":"NJ",
    "sg:tags":[
        "city"
    ],
    "wof:name":"Gibbsboro Court Clerk",
    "wof:placetype":"venue"
},
  "geometry": {"coordinates":[-74.971529,39.837128],"type":"Point"}
}