{
  "type": "Feature",
  "properties": {
    "iso:country":"US",
    "sg:address":"167 Worcester Dr",
    "sg:city":"Wayne",
    "sg:classifiers":[
        {
            "category":"Real Estate",
            "subcategory":"Real Estate Agent",
            "type":"Services"
        }
    ],
    "sg:phone":"+1   ",
    "sg:postcode":"07470",
    "sg:province":"NJ",
    "wof:name":"Woods At Waterview Estate",
    "wof:placetype":"venue"
},
  "geometry": {"coordinates":[-74.237673,40.975967],"type":"Point"}
}