{
  "type": "Feature",
  "properties": {
    "iso:country":"US",
    "sg:address":"14 Brentwood Dr",
    "sg:city":"Jackson",
    "sg:classifiers":[
        {
            "category":"Manufacturing",
            "subcategory":"Building Materials",
            "type":"Manufacturing & Wholesale Goods"
        }
    ],
    "sg:phone":"+1 732 833 8478",
    "sg:postcode":"08527",
    "sg:province":"NJ",
    "sg:tags":[
        "mfg",
        "wood",
        "kitchen",
        "cabinet"
    ],
    "wof:name":"Vafiadis Custom Cabinetry & RE",
    "wof:placetype":"venue"
},
  "geometry": {"coordinates":[-74.36365600000001,40.114884],"type":"Point"}
}