{
  "type": "Feature",
  "properties": {
    "addr:full":"181 Fairmount Ave Jersey City NJ 07306",
    "addr:housenumber":"181",
    "addr:postcode":"07306",
    "addr:street":"Fairmount Ave",
    "iso:country":"US",
    "sg:address":"181 Fairmount Ave",
    "sg:city":"Jersey City",
    "sg:classifiers":[
        {
            "category":"Retail",
            "subcategory":"Auto Repair",
            "type":"Services"
        }
    ],
    "sg:phone":"+1 201 333 8685",
    "sg:postcode":"07306",
    "sg:province":"NJ",
    "wof:name":"Speedy's Auto",
    "wof:placetype":"venue"
},
  "geometry": {"coordinates":[-74.066498,40.7318],"type":"Point"}
}