{
  "type": "Feature",
  "properties": {
    "addr:full":"13 Old Farmstead Rd Chester NJ 07930",
    "addr:housenumber":"13",
    "addr:postcode":"07930",
    "addr:street":"Old Farmstead Rd",
    "iso:country":"US",
    "sg:address":"13 Old Farmstead Rd",
    "sg:city":"Chester",
    "sg:classifiers":[
        {
            "category":"Professional",
            "subcategory":"Business Services",
            "type":"Services"
        }
    ],
    "sg:phone":"+1   ",
    "sg:postcode":"07930",
    "sg:province":"NJ",
    "wof:name":"Ehm Group",
    "wof:placetype":"venue"
},
  "geometry": {"coordinates":[-74.649399,40.81345],"type":"Point"}
}