{
  "type": "Feature",
  "properties": {
    "iso:country":"US",
    "sg:address":"890 Van Houten Ave",
    "sg:city":"Clifton",
    "sg:classifiers":[
        {
            "category":"Food & Beverages",
            "subcategory":"Fruits & Vegetables",
            "type":"Retail Goods"
        }
    ],
    "sg:phone":"+1 973 249 0220",
    "sg:postcode":"07013",
    "sg:province":"NJ",
    "sg:tags":[
        "florist",
        "produce"
    ],
    "wof:name":"Edible Arrangements Llc",
    "wof:placetype":"venue"
},
  "geometry": {"coordinates":[-74.15750800000001,40.863608],"type":"Point"}
}