{
  "type": "Feature",
  "properties": {
    "iso:country":"US",
    "sg:address":"202 Norman Rd",
    "sg:city":"Newark",
    "sg:classifiers":[
        {
            "category":"Organizations",
            "subcategory":"Religious Organization",
            "type":"Services"
        }
    ],
    "sg:phone":"+1 973 375 0019",
    "sg:postcode":"07106",
    "sg:province":"NJ",
    "sg:tags":[
        "church"
    ],
    "wof:name":"Seventh-Day Adventist Church",
    "wof:placetype":"venue"
},
  "geometry": {"coordinates":[-74.24420499999999,40.733525],"type":"Point"}
}