{
  "type": "Feature",
  "properties": {
    "iso:country":"US",
    "sg:address":"13 Hackett St",
    "sg:city":"Newark",
    "sg:classifiers":[
        {
            "category":"Professional",
            "subcategory":"Management & Consulting",
            "type":"Services"
        }
    ],
    "sg:phone":"+1 973 596 0800",
    "sg:postcode":"07102",
    "sg:province":"NJ",
    "sg:tags":[
        "construction"
    ],
    "sg:website":"www.mackenziecompanies.com",
    "wof:name":"Garrison Keck Inc",
    "wof:placetype":"venue"
},
  "geometry": {"coordinates":[-74.176202,40.739175],"type":"Point"}
}