{
  "type": "Feature",
  "properties": {
    "addr:full":"61 Frederick Pl Morristown NJ 07960",
    "addr:housenumber":"61",
    "addr:postcode":"07960",
    "addr:street":"Frederick Pl",
    "iso:country":"US",
    "sg:address":"61 Frederick Pl",
    "sg:city":"Morristown",
    "sg:classifiers":[
        {
            "category":"Retail",
            "subcategory":"Repair Shop",
            "type":"Services"
        }
    ],
    "sg:phone":"+1 973 631 1204",
    "sg:postcode":"07960",
    "sg:province":"NJ",
    "wof:name":"Recreation Specialists",
    "wof:placetype":"venue"
},
  "geometry": {"coordinates":[-74.494613,40.766071],"type":"Point"}
}