{
  "type": "Feature",
  "properties": {
    "addr:full":"6 Mountain Ter Montclair NJ 07043",
    "addr:housenumber":"6",
    "addr:postcode":"07043",
    "addr:street":"Mountain Ter",
    "iso:country":"US",
    "sg:address":"6 Mountain Ter",
    "sg:city":"Montclair",
    "sg:classifiers":[
        {
            "category":"Professional",
            "subcategory":"Management & Consulting",
            "type":"Services"
        }
    ],
    "sg:phone":"+1 973 783 9267",
    "sg:postcode":"07043",
    "sg:province":"NJ",
    "sg:tags":[
        "consultant",
        "business"
    ],
    "wof:name":"Worldwide Marketing",
    "wof:placetype":"venue"
},
  "geometry": {"coordinates":[-74.20935299999999,40.847733],"type":"Point"}
}