{
  "type": "Feature",
  "properties": {
    "iso:country":"US",
    "sg:address":"308 Casey Ln",
    "sg:city":"Jackson",
    "sg:classifiers":[
        {
            "category":"Building & Trades",
            "subcategory":"Construction",
            "type":"Services"
        }
    ],
    "sg:phone":"+1 732 928 9668",
    "sg:postcode":"08527",
    "sg:province":"NJ",
    "sg:tags":[
        "treatment",
        "for",
        "floor"
    ],
    "wof:name":"Surface Technologies",
    "wof:placetype":"venue"
},
  "geometry": {"coordinates":[-74.379133,40.126681],"type":"Point"}
}