{
  "type": "Feature",
  "properties": {
    "iso:country":"US",
    "sg:address":"3 State Rte 31",
    "sg:city":"Flemington",
    "sg:classifiers":[
        {
            "category":"Home & Garden",
            "subcategory":"Furniture",
            "type":"Retail Goods"
        }
    ],
    "sg:phone":"+1 908 782 4177",
    "sg:postcode":"08822",
    "sg:province":"NJ",
    "sg:tags":[
        "bedding"
    ],
    "sg:website":"www.rockawaybedding.com",
    "wof:name":"Rockaway Bedding Inc",
    "wof:placetype":"venue"
},
  "geometry": {"coordinates":[-74.853171,40.503888],"type":"Point"}
}