{
  "type": "Feature",
  "properties": {
    "iso:country":"US",
    "sg:address":"45 Broadway",
    "sg:city":"Passaic",
    "sg:classifiers":[
        {
            "category":"Professional",
            "type":"Services"
        }
    ],
    "sg:phone":"+1 973 773 6660",
    "sg:postcode":"07055",
    "sg:province":"NJ",
    "sg:tags":[
        "establishment"
    ],
    "wof:name":"Pic",
    "wof:placetype":"venue"
},
  "geometry": {"coordinates":[-74.127233,40.860333],"type":"Point"}
}