{
  "type": "Feature",
  "properties": {
    "iso:country":"US",
    "sg:address":"12 Cedar St",
    "sg:city":"Alloway",
    "sg:classifiers":[
        {
            "category":"Professional",
            "type":"Services"
        }
    ],
    "sg:phone":"+1   ",
    "sg:postcode":"08001",
    "sg:province":"NJ",
    "wof:name":"Edward Dorrell",
    "wof:placetype":"venue"
},
  "geometry": {"coordinates":[-75.364515,39.560272],"type":"Point"}
}