{
  "type": "Feature",
  "properties": {
    "iso:country":"US",
    "sg:address":"9 Lakeside Rd",
    "sg:city":"Hewitt",
    "sg:classifiers":[
        {
            "category":"Restaurant",
            "type":"Food & Drink"
        }
    ],
    "sg:phone":"+1 973 728 4722",
    "sg:postcode":"07421",
    "sg:province":"NJ",
    "sg:tags":[
        "italian"
    ],
    "wof:name":"Le Bistro Restaurant Ii",
    "wof:placetype":"venue"
},
  "geometry": {"coordinates":[-74.350838,41.15403],"type":"Point"}
}