{
  "type": "Feature",
  "properties": {
    "iso:country":"US",
    "sg:address":"19 Main Rd",
    "sg:city":"Allamuchy",
    "sg:classifiers":[
        {
            "category":"Food & Beverages",
            "subcategory":"Liquor & Beverages",
            "type":"Retail Goods"
        }
    ],
    "sg:phone":"+1 908 852 6043",
    "sg:postcode":"07850",
    "sg:province":"NJ",
    "sg:tags":[
        "wine"
    ],
    "wof:name":"Allamuchy Liquors",
    "wof:placetype":"venue"
},
  "geometry": {"coordinates":[-74.665035,40.904921],"type":"Point"}
}