{
  "type": "Feature",
  "properties": {
    "addr:full":"17 E Highland Ave Atlantic Hghlnds NJ 07716",
    "addr:housenumber":"17",
    "addr:postcode":"07716",
    "addr:street":"E Highland Ave",
    "iso:country":"US",
    "sg:address":"17 E Highland Ave",
    "sg:city":"Atlantic Hghlnds",
    "sg:classifiers":[
        {
            "category":"Social Services",
            "subcategory":"Child Care",
            "type":"Services"
        }
    ],
    "sg:phone":"+1 732 291 0101",
    "sg:postcode":"07716",
    "sg:province":"NJ",
    "wof:name":"Tod-L-Lyn Day Care Ctr",
    "wof:placetype":"venue"
},
  "geometry": {"coordinates":[-74.03786599999999,40.412311],"type":"Point"}
}