{
  "type": "Feature",
  "properties": {
    "iso:country":"US",
    "sg:address":"79 US Hwy 46",
    "sg:city":"Fairfield",
    "sg:classifiers":[
        {
            "category":"Home & Garden",
            "subcategory":"Building Materials",
            "type":"Retail Goods"
        }
    ],
    "sg:phone":"+1 973 575 0823",
    "sg:postcode":"07004",
    "sg:province":"NJ",
    "sg:tags":[
        "center"
    ],
    "wof:name":"Home Depot",
    "wof:placetype":"venue"
},
  "geometry": {"coordinates":[-74.311419,40.868226],"type":"Point"}
}