{
  "type": "Feature",
  "properties": {
    "addr:full":"86 Paterson Ave West Paterson NJ 07424",
    "addr:housenumber":"86",
    "addr:postcode":"07424",
    "addr:street":"Paterson Ave West",
    "iso:country":"US",
    "sg:address":"86 Paterson Ave",
    "sg:city":"West Paterson",
    "sg:classifiers":[
        {
            "category":"Retail",
            "subcategory":"Auto Repair",
            "type":"Services"
        }
    ],
    "sg:phone":"+1 973 237 0929",
    "sg:postcode":"07424",
    "sg:province":"NJ",
    "sg:tags":[
        "automobile",
        "top",
        "upholstery"
    ],
    "wof:name":"Auto Craft Trim Inc",
    "wof:placetype":"venue"
},
  "geometry": {"coordinates":[-74.22667800000001,40.881788],"type":"Point"}
}