{
  "type": "Feature",
  "properties": {
    "iso:country":"US",
    "sg:address":"5 Blandford Rd",
    "sg:city":"Wayne",
    "sg:classifiers":[
        {
            "category":"Health Services",
            "subcategory":"Doctor",
            "type":"Services"
        }
    ],
    "sg:phone":"+1 973 696 5306",
    "sg:postcode":"07470",
    "sg:province":"NJ",
    "sg:tags":[
        "dentist"
    ],
    "wof:name":"Scott Podell DDS",
    "wof:placetype":"venue"
},
  "geometry": {"coordinates":[-74.225364,40.938614],"type":"Point"}
}