{
  "type": "Feature",
  "properties": {
    "iso:country":"US",
    "sg:address":"82 Freeport Blvd",
    "sg:city":"Toms River",
    "sg:classifiers":[
        {
            "category":"Professional",
            "subcategory":"Management & Consulting",
            "type":"Services"
        }
    ],
    "sg:phone":"+1   ",
    "sg:postcode":"08757",
    "sg:province":"NJ",
    "wof:name":"Robert Nocere",
    "wof:placetype":"venue"
},
  "geometry": {"coordinates":[-74.229073,39.954931],"type":"Point"}
}