{
  "type": "Feature",
  "properties": {
    "iso:country":"US",
    "sg:address":"571 Bound Brook Rd",
    "sg:city":"Middlesex",
    "sg:classifiers":[
        {
            "category":"Restaurant",
            "type":"Food & Drink"
        }
    ],
    "sg:menulink":"http://www.allmenus.com/nj/middlesex/8949-romanos-chicken-italian-ristorante-and-pizzeria/menu/",
    "sg:phone":"+1 732 424 0466",
    "sg:postcode":"08846",
    "sg:province":"NJ",
    "sg:tags":[
        "italian"
    ],
    "wof:name":"Romano's Chicken Italian Ristorante and Pizzeria",
    "wof:placetype":"venue"
},
  "geometry": {"coordinates":[-74.487893,40.582718],"type":"Point"}
}