{
  "type": "Feature",
  "properties": {
    "addr:full":"34 Exchange Pl Jersey City NJ 07302",
    "addr:housenumber":"34",
    "addr:postcode":"07302",
    "addr:street":"Exchange Pl",
    "iso:country":"US",
    "sg:address":"34 Exchange Pl",
    "sg:city":"Jersey City",
    "sg:classifiers":[
        {
            "category":"Manufacturing",
            "subcategory":"Printing",
            "type":"Manufacturing & Wholesale Goods"
        }
    ],
    "sg:phone":"+1 201 938 2340",
    "sg:postcode":"07302",
    "sg:province":"NJ",
    "sg:tags":[
        "publishing"
    ],
    "wof:name":"Dow Jones",
    "wof:placetype":"venue"
},
  "geometry": {"coordinates":[-74.033086,40.716212],"type":"Point"}
}