{
  "type": "Feature",
  "properties": {
    "addr:full":"849 King George Rd Fords NJ 08863",
    "addr:housenumber":"849",
    "addr:postcode":"08863",
    "addr:street":"King George Rd",
    "iso:country":"US",
    "sg:address":"849 King George Rd",
    "sg:city":"Fords",
    "sg:classifiers":[
        {
            "category":"Banks & Credit Unions",
            "subcategory":"Financial Services",
            "type":"Services"
        }
    ],
    "sg:phone":"+1 732 738 7195",
    "sg:postcode":"08863",
    "sg:province":"NJ",
    "sg:tags":[
        "broker",
        "mortgage"
    ],
    "wof:name":"First Jersey Mortgage",
    "wof:placetype":"venue"
},
  "geometry": {"coordinates":[-74.31440000000001,40.5294],"type":"Point"}
}