{
  "type": "Feature",
  "properties": {
    "addr:full":"325 4th St Lakewood NJ 08701",
    "addr:housenumber":"325",
    "addr:postcode":"08701",
    "addr:street":"4Th St",
    "iso:country":"US",
    "sg:address":"325 4th St",
    "sg:city":"Lakewood",
    "sg:classifiers":[
        {
            "category":"Shopping",
            "subcategory":"Musical Instruments",
            "type":"Retail Goods"
        }
    ],
    "sg:phone":"+1 732 886 0909",
    "sg:postcode":"08701",
    "sg:province":"NJ",
    "sg:tags":[
        "music",
        "dealer"
    ],
    "wof:name":"Roca Eterna Christian Music",
    "wof:placetype":"venue"
},
  "geometry": {"coordinates":[-74.215378,40.094113],"type":"Point"}
}