{
  "type": "Feature",
  "properties": {
    "iso:country":"US",
    "sg:address":"30 Stern Ave",
    "sg:city":"Springfield",
    "sg:classifiers":[
        {
            "category":"Building & Trades",
            "subcategory":"Locksmith",
            "type":"Services"
        }
    ],
    "sg:phone":"+1 973 671 0713",
    "sg:postcode":"07081",
    "sg:province":"NJ",
    "sg:tags":[
        "key"
    ],
    "wof:name":"Anytime Locksmith",
    "wof:placetype":"venue"
},
  "geometry": {"coordinates":[-74.31617,40.688455],"type":"Point"}
}