{
  "type": "Feature",
  "properties": {
    "iso:country":"US",
    "sg:address":"90 US Hwy 206",
    "sg:city":"Stanhope",
    "sg:classifiers":[
        {
            "category":"Shopping",
            "subcategory":"Computers & Home Electronics",
            "type":"Retail Goods"
        }
    ],
    "sg:phone":"+1 973 448 1963",
    "sg:postcode":"07874",
    "sg:province":"NJ",
    "sg:tags":[
        "equipment",
        "electronic",
        "supply"
    ],
    "wof:name":"Radio Shack",
    "wof:placetype":"venue"
},
  "geometry": {"coordinates":[-74.720759,40.934813],"type":"Point"}
}