{
  "type": "Feature",
  "properties": {
    "iso:country":"US",
    "sg:address":"550 Dorian Rd",
    "sg:city":"Westfield",
    "sg:classifiers":[
        {
            "category":"Education",
            "subcategory":"School",
            "type":"Public Place"
        }
    ],
    "sg:phone":"+1 908 789 4500",
    "sg:postcode":"07090",
    "sg:province":"NJ",
    "sg:website":"www.westfieldnj.com",
    "wof:name":"Westfield High School",
    "wof:placetype":"venue"
},
  "geometry": {"coordinates":[-74.348589,40.643459],"type":"Point"}
}