{
  "type": "Feature",
  "properties": {
    "addr:full":"1949 State Rte 35 South Amboy NJ 08879",
    "addr:housenumber":"1949",
    "addr:postcode":"08879",
    "addr:street":"State Rte 35",
    "iso:country":"US",
    "sg:address":"1949 State Rte 35",
    "sg:city":"South Amboy",
    "sg:classifiers":[
        {
            "category":"Retail",
            "subcategory":"Auto Repair",
            "type":"Services"
        }
    ],
    "sg:phone":"+1 732 316 9000",
    "sg:postcode":"08879",
    "sg:province":"NJ",
    "sg:tags":[
        "automobile",
        "inspection"
    ],
    "wof:name":"American Service Ctr",
    "wof:placetype":"venue"
},
  "geometry": {"coordinates":[-74.27587200000001,40.464474],"type":"Point"}
}