{
  "type": "Feature",
  "properties": {
    "iso:country":"US",
    "sg:address":"22 Van Wyck Dr",
    "sg:city":"Princeton Jct",
    "sg:classifiers":[
        {
            "category":"Professional",
            "subcategory":"Computer Services",
            "type":"Services"
        }
    ],
    "sg:phone":"+1 609 750 0511",
    "sg:postcode":"08550",
    "sg:province":"NJ",
    "sg:tags":[
        "consultant",
        "designer",
        "programing",
        "custom"
    ],
    "wof:name":"M 2z Consulting Inc",
    "wof:placetype":"venue"
},
  "geometry": {"coordinates":[-74.61309799999999,40.303302],"type":"Point"}
}