{
  "type": "Feature",
  "properties": {
    "addr:full":"1993 Leonard Dr Toms River NJ 08755",
    "addr:housenumber":"1993",
    "addr:postcode":"08755",
    "addr:street":"Leonard Dr",
    "iso:country":"US",
    "sg:address":"1993 Leonard Dr",
    "sg:city":"Toms River",
    "sg:classifiers":[
        {
            "category":"Communications",
            "type":"Services"
        }
    ],
    "sg:phone":"+1 732 286 1027",
    "sg:postcode":"08755",
    "sg:province":"NJ",
    "wof:name":"V To V Communications",
    "wof:placetype":"venue"
},
  "geometry": {"coordinates":[-74.210778,40.025263],"type":"Point"}
}