{
  "type": "Feature",
  "properties": {
    "addr:full":"4129 Church Rd Mt Laurel NJ 08054",
    "addr:housenumber":"4129",
    "addr:postcode":"08054",
    "addr:street":"Church Rd",
    "iso:country":"US",
    "sg:address":"4129 Church Rd",
    "sg:city":"Mt Laurel",
    "sg:classifiers":[
        {
            "category":"Banks & Credit Unions",
            "subcategory":"Bank",
            "type":"Services"
        }
    ],
    "sg:phone":"+1 856 234 0088",
    "sg:postcode":"08054",
    "sg:province":"NJ",
    "sg:tags":[
        "loan",
        "real estate"
    ],
    "wof:name":"Suncoast National Mortgage",
    "wof:placetype":"venue"
},
  "geometry": {"coordinates":[-74.95336399999999,39.924392],"type":"Point"}
}