{
  "type": "Feature",
  "properties": {
    "addr:full":"3 Meadow Ct Englishtown NJ 07726",
    "addr:housenumber":"3",
    "addr:postcode":"07726",
    "addr:street":"Meadow Ct",
    "iso:country":"US",
    "sg:address":"3 Meadow Ct",
    "sg:city":"Englishtown",
    "sg:classifiers":[
        {
            "category":"Professional",
            "subcategory":"Employment Agencies",
            "type":"Services"
        }
    ],
    "sg:phone":"+1   ",
    "sg:postcode":"07726",
    "sg:province":"NJ",
    "sg:tags":[
        "recruitment",
        "executive"
    ],
    "wof:name":"Clinnovative Careers LLC",
    "wof:placetype":"venue"
},
  "geometry": {"coordinates":[-74.30765100000001,40.299439],"type":"Point"}
}