{
  "type": "Feature",
  "properties": {
    "addr:full":"1100 Industrial Pkwy Brick NJ 08724",
    "addr:housenumber":"1100",
    "addr:postcode":"08724",
    "addr:street":"Industrial Pkwy",
    "iso:country":"US",
    "sg:address":"1100 Industrial Pkwy",
    "sg:city":"Brick",
    "sg:classifiers":[
        {
            "category":"Building & Trades",
            "subcategory":"Construction",
            "type":"Services"
        }
    ],
    "sg:phone":"+1 732 836 0988",
    "sg:postcode":"08724",
    "sg:province":"NJ",
    "sg:tags":[
        "carpentry",
        "contractor"
    ],
    "wof:name":"Premier Woodworking LLC",
    "wof:placetype":"venue"
},
  "geometry": {"coordinates":[-74.11350299999999,40.083206],"type":"Point"}
}