{
  "type": "Feature",
  "properties": {
    "iso:country":"US",
    "sg:address":"1320 W 7th St",
    "sg:city":"Piscataway",
    "sg:classifiers":[
        {
            "category":"Food & Beverages",
            "subcategory":"Groceries & Convenience Stores",
            "type":"Retail Goods"
        }
    ],
    "sg:phone":"+1 908 668 8570",
    "sg:postcode":"08854",
    "sg:province":"NJ",
    "wof:name":"Stop N Go",
    "wof:placetype":"venue"
},
  "geometry": {"coordinates":[-74.438562,40.596262],"type":"Point"}
}