{
  "type": "Feature",
  "properties": {
    "iso:country":"US",
    "sg:address":"350 Engle St",
    "sg:city":"Englewood",
    "sg:classifiers":[
        {
            "category":"Building & Trades",
            "subcategory":"Electrical",
            "type":"Services"
        }
    ],
    "sg:phone":"+1 201 227 7616",
    "sg:postcode":"07631",
    "sg:province":"NJ",
    "sg:tags":[
        "electric",
        "contractor"
    ],
    "wof:name":"Unity Electric LLC",
    "wof:placetype":"venue"
},
  "geometry": {"coordinates":[-73.96580899999999,40.907279],"type":"Point"}
}