{
  "type": "Feature",
  "properties": {
    "addr:full":"10 Orben Dr Landing NJ 07850",
    "addr:housenumber":"10",
    "addr:postcode":"07850",
    "addr:street":"Orben Dr",
    "iso:country":"US",
    "sg:address":"10 Orben Dr",
    "sg:city":"Landing",
    "sg:classifiers":[
        {
            "category":"Education",
            "subcategory":"Dance Studio",
            "type":"Public Place"
        }
    ],
    "sg:phone":"+1 973 398 1888",
    "sg:postcode":"07850",
    "sg:province":"NJ",
    "sg:tags":[
        "instruction",
        "dancing"
    ],
    "wof:name":"Dream Dance Studio Inc",
    "wof:placetype":"venue"
},
  "geometry": {"coordinates":[-74.660617,40.894541],"type":"Point"}
}