{
  "type": "Feature",
  "properties": {
    "addr:full":"5311 Palisade Ave West New York NJ 07093",
    "addr:housenumber":"5311",
    "addr:postcode":"07093",
    "addr:street":"Palisade Ave West",
    "iso:country":"US",
    "sg:address":"5311 Palisade Ave",
    "sg:city":"West New York",
    "sg:classifiers":[
        {
            "category":"Banks & Credit Unions",
            "subcategory":"Financial Services",
            "type":"Services"
        }
    ],
    "sg:phone":"+1 201 864 2191",
    "sg:postcode":"07093",
    "sg:province":"NJ",
    "sg:tags":[
        "company",
        "holding"
    ],
    "wof:name":"Lee & Lee Holdings Inc",
    "wof:placetype":"venue"
},
  "geometry": {"coordinates":[-74.017162,40.784127],"type":"Point"}
}