{
  "type": "Feature",
  "properties": {
    "iso:country":"US",
    "sg:address":"170 State St",
    "sg:city":"Teaneck",
    "sg:classifiers":[
        {
            "category":"Manufacturing",
            "subcategory":"Printing",
            "type":"Manufacturing & Wholesale Goods"
        }
    ],
    "sg:phone":"+1 201 837 1373",
    "sg:postcode":"07666",
    "sg:province":"NJ",
    "sg:tags":[
        "screen"
    ],
    "wof:name":"Walter Popick",
    "wof:placetype":"venue"
},
  "geometry": {"coordinates":[-74.004892,40.903075],"type":"Point"}
}