{
  "type": "Feature",
  "properties": {
    "iso:country":"US",
    "sg:address":"1300 Central Ave",
    "sg:city":"Union City",
    "sg:classifiers":[
        {
            "category":"Restaurant",
            "type":"Food & Drink"
        }
    ],
    "sg:phone":"+1 201 867 2909",
    "sg:postcode":"07087",
    "sg:province":"NJ",
    "sg:tags":[
        "delicatessen"
    ],
    "wof:name":"Deli Store Oaxaca",
    "wof:placetype":"venue"
},
  "geometry": {"coordinates":[-74.03936899999999,40.762057],"type":"Point"}
}