{
  "type": "Feature",
  "properties": {
    "addr:full":"37 Dakota St Passaic NJ 07055",
    "addr:housenumber":"37",
    "addr:postcode":"07055",
    "addr:street":"Dakota St",
    "iso:country":"US",
    "sg:address":"37 Dakota St",
    "sg:city":"Passaic",
    "sg:classifiers":[
        {
            "category":"Manufacturing",
            "subcategory":"Chemicals & Compounds",
            "type":"Manufacturing & Wholesale Goods"
        }
    ],
    "sg:phone":"+1 973 471 8500",
    "sg:postcode":"07055",
    "sg:province":"NJ",
    "sg:tags":[
        "exterminating",
        "product",
        "mfg"
    ],
    "wof:name":"Oak Stump Farm LLC",
    "wof:placetype":"venue"
},
  "geometry": {"coordinates":[-74.13633799999999,40.845602],"type":"Point"}
}