{
  "type": "Feature",
  "properties": {
    "iso:country":"US",
    "sg:address":"926 Newark Ave",
    "sg:city":"Jersey City",
    "sg:classifiers":[
        {
            "category":"Wholesale",
            "subcategory":"Apparel",
            "type":"Manufacturing & Wholesale Goods"
        }
    ],
    "sg:phone":"+1 201 239 0800",
    "sg:postcode":"07306",
    "sg:province":"NJ",
    "sg:tags":[
        "bra"
    ],
    "wof:name":"Lunaire Inc",
    "wof:placetype":"venue"
},
  "geometry": {"coordinates":[-74.069467,40.736638],"type":"Point"}
}