{
  "type": "Feature",
  "properties": {
    "iso:country":"US",
    "sg:address":"916 Grove St",
    "sg:city":"Elizabeth",
    "sg:classifiers":[
        {
            "category":"Retail",
            "subcategory":"Laundry & Dry Cleaning",
            "type":"Services"
        }
    ],
    "sg:phone":"+1 908 353 1616",
    "sg:postcode":"07202",
    "sg:province":"NJ",
    "sg:tags":[
        "cleaners",
        "rug",
        "carpet"
    ],
    "wof:name":"Professional Carpet Cleaning",
    "wof:placetype":"venue"
},
  "geometry": {"coordinates":[-74.22044099999999,40.655521],"type":"Point"}
}