{
  "type": "Feature",
  "properties": {
    "iso:country":"US",
    "sg:address":"2090 Oak Tree Rd",
    "sg:city":"Edison",
    "sg:classifiers":[
        {
            "category":"Health Services",
            "subcategory":"Health Practitioner",
            "type":"Services"
        }
    ],
    "sg:phone":"+1 732 321 4033",
    "sg:postcode":"08820",
    "sg:province":"NJ",
    "sg:tags":[
        "psychologist"
    ],
    "wof:name":"Baglel Chateau",
    "wof:placetype":"venue"
},
  "geometry": {"coordinates":[-74.374397,40.57541],"type":"Point"}
}