{
  "type": "Feature",
  "properties": {
    "iso:country":"US",
    "sg:address":"23 Willet St",
    "sg:city":"Bloomfield",
    "sg:classifiers":[
        {
            "category":"Restaurant",
            "type":"Food & Drink"
        }
    ],
    "sg:phone":"+1 973 743 0910",
    "sg:postcode":"07003",
    "sg:province":"NJ",
    "sg:tags":[
        "caterer",
        "catering"
    ],
    "wof:name":"F & B Caterers",
    "wof:placetype":"venue"
},
  "geometry": {"coordinates":[-74.18000000000001,40.7939],"type":"Point"}
}