{
  "type": "Feature",
  "properties": {
    "iso:country":"US",
    "sg:address":"314 S Main St",
    "sg:city":"Phillipsburg",
    "sg:classifiers":[
        {
            "category":"Education",
            "subcategory":"Special Training",
            "type":"Public Place"
        }
    ],
    "sg:phone":"+1   ",
    "sg:postcode":"08865",
    "sg:province":"NJ",
    "wof:name":"New Life Childcare Academy",
    "wof:placetype":"venue"
},
  "geometry": {"coordinates":[-75.19439199999999,40.686787],"type":"Point"}
}