{
  "type": "Feature",
  "properties": {
    "iso:country":"US",
    "sg:address":"5 State Rte 94",
    "sg:city":"Vernon",
    "sg:classifiers":[
        {
            "category":"Professional",
            "type":"Services"
        }
    ],
    "sg:phone":"+1 973 827 1001",
    "sg:postcode":"07462",
    "sg:province":"NJ",
    "sg:tags":[
        "establishment"
    ],
    "wof:name":"D Q Of New Jersey Inc",
    "wof:placetype":"venue"
},
  "geometry": {"coordinates":[-74.551299,41.171665],"type":"Point"}
}