{
  "type": "Feature",
  "properties": {
    "iso:country":"US",
    "sg:address":"26 Iron Horse Dr",
    "sg:city":"Ringoes",
    "sg:classifiers":[
        {
            "category":"Building & Trades",
            "subcategory":"Construction",
            "type":"Services"
        }
    ],
    "sg:phone":"+1 908 237 2482",
    "sg:postcode":"08551",
    "sg:province":"NJ",
    "sg:tags":[
        "house"
    ],
    "wof:name":"Black Bass Construction",
    "wof:placetype":"venue"
},
  "geometry": {"coordinates":[-74.867681,40.435021],"type":"Point"}
}