{
  "type": "Feature",
  "properties": {
    "addr:full":"21 Roslyn Rd Branchville NJ 07826",
    "addr:housenumber":"21",
    "addr:postcode":"07826",
    "addr:street":"Roslyn Rd",
    "iso:country":"US",
    "sg:address":"21 Roslyn Rd",
    "sg:city":"Branchville",
    "sg:classifiers":[
        {
            "category":"Building & Trades",
            "subcategory":"Construction",
            "type":"Services"
        }
    ],
    "sg:phone":"+1 201 230 4073",
    "sg:postcode":"07826",
    "sg:province":"NJ",
    "sg:tags":[
        "residential"
    ],
    "wof:name":"Crothers Construction",
    "wof:placetype":"venue"
},
  "geometry": {"coordinates":[-74.751318,41.154268],"type":"Point"}
}