{
  "type": "Feature",
  "properties": {
    "iso:country":"US",
    "sg:address":"56 Arlington Ave",
    "sg:city":"Caldwell",
    "sg:classifiers":[
        {
            "category":"Building & Trades",
            "subcategory":"Construction",
            "type":"Services"
        }
    ],
    "sg:phone":"+1 973 228 4063",
    "sg:postcode":"07006",
    "sg:province":"NJ",
    "sg:tags":[
        "house"
    ],
    "wof:name":"Tjw Construction LLC",
    "wof:placetype":"venue"
},
  "geometry": {"coordinates":[-74.269457,40.837884],"type":"Point"}
}