{
  "type": "Feature",
  "properties": {
    "addr:full":"334 South Ave E Westfield NJ 07090",
    "addr:housenumber":"334",
    "addr:postcode":"07090",
    "addr:street":"South Ave E",
    "iso:country":"US",
    "sg:address":"334 South Ave E",
    "sg:city":"Westfield",
    "sg:classifiers":[
        {
            "category":"Personal",
            "type":"Services"
        },
        {
            "category":"Shopping",
            "subcategory":"Clothing, Apparel, & Fashions",
            "type":"Retail Goods"
        }
    ],
    "sg:phone":"+1 908 233 7000",
    "sg:postcode":"07090",
    "sg:province":"NJ",
    "sg:tags":[
        "tuxedo",
        "formal",
        "rental",
        "wear",
        "sales"
    ],
    "wof:name":"Moonlight Tuxedos Inc",
    "wof:placetype":"venue"
},
  "geometry": {"coordinates":[-74.336046,40.649832],"type":"Point"}
}