{
  "type": "Feature",
  "properties": {
    "addr:full":"14 S Orange Ave South Orange NJ 07079",
    "addr:housenumber":"14",
    "addr:postcode":"07079",
    "addr:street":"S Orange Ave",
    "iso:country":"US",
    "sg:address":"14 S Orange Ave",
    "sg:city":"South Orange",
    "sg:classifiers":[
        {
            "category":"Professional",
            "subcategory":"Lawyer & Legal Services",
            "type":"Services"
        }
    ],
    "sg:phone":"+1   ",
    "sg:postcode":"07079",
    "sg:province":"NJ",
    "wof:name":"Reimer & Neidweski",
    "wof:placetype":"venue"
},
  "geometry": {"coordinates":[-74.258546,40.745818],"type":"Point"}
}