{
  "type": "Feature",
  "properties": {
    "iso:country":"US",
    "sg:address":"176 Prospect St",
    "sg:city":"Nutley",
    "sg:classifiers":[
        {
            "category":"Building & Trades",
            "subcategory":"Construction",
            "type":"Services"
        }
    ],
    "sg:phone":"+1 973 661 2870",
    "sg:postcode":"07110",
    "sg:province":"NJ",
    "sg:tags":[
        "hanging",
        "contractor"
    ],
    "wof:name":"Garden State Line Co",
    "wof:placetype":"venue"
},
  "geometry": {"coordinates":[-74.167239,40.813784],"type":"Point"}
}