{
  "type": "Feature",
  "properties": {
    "addr:full":"510 Wood Ave North Brunswick NJ 08902",
    "addr:housenumber":"510",
    "addr:postcode":"08902",
    "addr:street":"Wood Ave",
    "iso:country":"US",
    "sg:address":"510 Wood Ave",
    "sg:city":"North Brunswick",
    "sg:classifiers":[
        {
            "category":"Professional",
            "subcategory":"Computer Services",
            "type":"Services"
        }
    ],
    "sg:phone":"+1 732 951 1136",
    "sg:postcode":"08902",
    "sg:province":"NJ",
    "sg:tags":[
        "programing",
        "custom"
    ],
    "wof:name":"J B B Consultants U S A Inc",
    "wof:placetype":"venue"
},
  "geometry": {"coordinates":[-74.477109,40.444544],"type":"Point"}
}