{
  "type": "Feature",
  "properties": {
    "addr:full":"120 N High St Millville NJ 08332",
    "addr:housenumber":"120",
    "addr:postcode":"08332",
    "addr:street":"N High St",
    "iso:country":"US",
    "sg:address":"120 N High St",
    "sg:city":"Millville",
    "sg:classifiers":[
        {
            "category":"Building & Trades",
            "subcategory":"Equipment Rental",
            "type":"Services"
        }
    ],
    "sg:phone":"+1 856 293 0358",
    "sg:postcode":"08332",
    "sg:province":"NJ",
    "sg:tags":[
        "leasing"
    ],
    "wof:name":"AMI Leasing",
    "wof:placetype":"venue"
},
  "geometry": {"coordinates":[-75.038543,39.397073],"type":"Point"}
}