{
  "type": "Feature",
  "properties": {
    "iso:country":"US",
    "sg:address":"312 S Cologne Ave",
    "sg:city":"Egg Harbor City",
    "sg:classifiers":[
        {
            "category":"Government",
            "subcategory":"Office",
            "type":"Public Place"
        }
    ],
    "sg:phone":"+1   ",
    "sg:postcode":"08215",
    "sg:province":"NJ",
    "sg:tags":[
        "executive"
    ],
    "wof:name":"Germania Volunteer Fire Co",
    "wof:placetype":"venue"
},
  "geometry": {"coordinates":[-74.600037,39.510997],"type":"Point"}
}