{
  "type": "Feature",
  "properties": {
    "iso:country":"US",
    "sg:address":"965 Newton St",
    "sg:city":"North Brunswick",
    "sg:classifiers":[
        {
            "category":"Professional",
            "subcategory":"Art Services",
            "type":"Services"
        }
    ],
    "sg:phone":"+1   ",
    "sg:postcode":"08902",
    "sg:province":"NJ",
    "sg:tags":[
        "commercial",
        "photography",
        "production",
        "video",
        "editing"
    ],
    "wof:name":"Warner Studios Inc",
    "wof:placetype":"venue"
},
  "geometry": {"coordinates":[-74.469328,40.464769],"type":"Point"}
}