{
  "type": "Feature",
  "properties": {
    "addr:full":"92 Belle Ave Maywood NJ 07607",
    "addr:housenumber":"92",
    "addr:postcode":"07607",
    "addr:street":"Belle Ave",
    "iso:country":"US",
    "sg:address":"92 Belle Ave",
    "sg:city":"Maywood",
    "sg:classifiers":[
        {
            "category":"Real Estate",
            "subcategory":"Real Estate Agent",
            "type":"Services"
        }
    ],
    "sg:phone":"+1   ",
    "sg:postcode":"07607",
    "sg:province":"NJ",
    "wof:name":"Milano Property Management LLC",
    "wof:placetype":"venue"
},
  "geometry": {"coordinates":[-74.063683,40.906069],"type":"Point"}
}