{
  "type": "Feature",
  "properties": {
    "addr:full":"354 Conover Pl Red Bank NJ 07701",
    "addr:housenumber":"354",
    "addr:postcode":"07701",
    "addr:street":"Conover Pl",
    "iso:country":"US",
    "sg:address":"354 Conover Pl",
    "sg:city":"Red Bank",
    "sg:classifiers":[
        {
            "category":"Health Services",
            "subcategory":"Health Practitioner",
            "type":"Services"
        }
    ],
    "sg:phone":"+1 732 842 9100",
    "sg:postcode":"07701",
    "sg:province":"NJ",
    "sg:tags":[
        "therapist",
        "physical"
    ],
    "wof:name":"Pam Roussell Physical Therapy",
    "wof:placetype":"venue"
},
  "geometry": {"coordinates":[-74.080153,40.363583],"type":"Point"}
}