{
  "type": "Feature",
  "properties": {
    "addr:full":"458 N Franklin Tpke Allendale NJ 07401",
    "addr:housenumber":"458",
    "addr:postcode":"07401",
    "addr:street":"N Franklin Tpke",
    "iso:country":"US",
    "sg:address":"458 N Franklin Tpke",
    "sg:city":"Allendale",
    "sg:classifiers":[
        {
            "category":"Shopping",
            "subcategory":"Crafts & Fabrics",
            "type":"Retail Goods"
        }
    ],
    "sg:phone":"+1   ",
    "sg:postcode":"07401",
    "sg:province":"NJ",
    "sg:tags":[
        "sewing"
    ],
    "wof:name":"Simone Fabrics Ltd",
    "wof:placetype":"venue"
},
  "geometry": {"coordinates":[-74.12647200000001,41.032671],"type":"Point"}
}