{
  "type": "Feature",
  "properties": {
    "addr:full":"240 N Center Dr North Brunswick NJ 08902",
    "addr:housenumber":"240",
    "addr:postcode":"08902",
    "addr:street":"N Center Dr",
    "iso:country":"US",
    "sg:address":"240 N Center Dr",
    "sg:city":"North Brunswick",
    "sg:classifiers":[
        {
            "category":"Personal",
            "type":"Services"
        }
    ],
    "sg:phone":"+1   ",
    "sg:postcode":"08902",
    "sg:province":"NJ",
    "wof:name":"Plaster Craft Shop",
    "wof:placetype":"venue"
},
  "geometry": {"coordinates":[-74.50090299999999,40.445599],"type":"Point"}
}