{
  "type": "Feature",
  "properties": {
    "addr:full":"202 Monmouth Rd Oakhurst NJ 07755",
    "addr:housenumber":"202",
    "addr:postcode":"07755",
    "addr:street":"Monmouth Rd",
    "iso:country":"US",
    "sg:address":"202 Monmouth Rd",
    "sg:city":"Oakhurst",
    "sg:classifiers":[
        {
            "category":"Real Estate",
            "subcategory":"Real Estate Agent",
            "type":"Services"
        }
    ],
    "sg:phone":"+1 732 517 0725",
    "sg:postcode":"07755",
    "sg:province":"NJ",
    "wof:name":"Charles Mc Laughlin",
    "wof:placetype":"venue"
},
  "geometry": {"coordinates":[-74.012345,40.26225],"type":"Point"}
}