{
  "type": "Feature",
  "properties": {
    "iso:country":"US",
    "sg:address":"303 North St",
    "sg:city":"Teterboro",
    "sg:classifiers":[
        {
            "category":"Professional",
            "subcategory":"Art Services",
            "type":"Services"
        }
    ],
    "sg:phone":"+1 201 462 9280",
    "sg:postcode":"07608",
    "sg:province":"NJ",
    "sg:tags":[
        "development",
        "package",
        "designing"
    ],
    "wof:name":"MHI Inc",
    "wof:placetype":"venue"
},
  "geometry": {"coordinates":[-74.058897,40.868177],"type":"Point"}
}