{
  "type": "Feature",
  "properties": {
    "addr:full":"4100 New Jersey Ave Wildwood NJ 08260",
    "addr:housenumber":"4100",
    "addr:postcode":"08260",
    "addr:street":"New Jersey Ave",
    "iso:country":"US",
    "sg:address":"4100 New Jersey Ave",
    "sg:city":"Wildwood",
    "sg:classifiers":[
        {
            "category":"Restaurant",
            "type":"Food & Drink"
        }
    ],
    "sg:phone":"+1 609 729 8700",
    "sg:postcode":"08260",
    "sg:province":"NJ",
    "sg:tags":[
        "chinese"
    ],
    "wof:name":"China House Restaurant",
    "wof:placetype":"venue"
},
  "geometry": {"coordinates":[-74.819395,38.98812],"type":"Point"}
}