{
  "type": "Feature",
  "properties": {
    "iso:country":"US",
    "sg:address":"2017 Ohio Ave",
    "sg:city":"Atco",
    "sg:classifiers":[
        {
            "category":"Building & Trades",
            "subcategory":"Landscaping Services",
            "type":"Services"
        }
    ],
    "sg:phone":"+1 856 767 7884",
    "sg:postcode":"08004",
    "sg:province":"NJ",
    "sg:tags":[
        "landfill",
        "maintenance"
    ],
    "wof:name":"Environmental Erosion Control",
    "wof:placetype":"venue"
},
  "geometry": {"coordinates":[-74.878232,39.748018],"type":"Point"}
}