{
  "type": "Feature",
  "properties": {
    "addr:full":"174 Paterson Ave Midland Park NJ 07432",
    "addr:housenumber":"174",
    "addr:postcode":"07432",
    "addr:street":"Paterson Ave",
    "iso:country":"US",
    "sg:address":"174 Paterson Ave",
    "sg:city":"Midland Park",
    "sg:classifiers":[
        {
            "category":"Social Services",
            "type":"Services"
        }
    ],
    "sg:phone":"+1 201 612 8118",
    "sg:postcode":"07432",
    "sg:province":"NJ",
    "sg:tags":[
        "organization",
        "welfare"
    ],
    "wof:name":"Emmanuel Cancer Foundation",
    "wof:placetype":"venue"
},
  "geometry": {"coordinates":[-74.14440500000001,40.989159],"type":"Point"}
}