{
  "type": "Feature",
  "properties": {
    "iso:country":"US",
    "sg:address":"201 Palisade Ave",
    "sg:city":"Jersey City",
    "sg:classifiers":[
        {
            "category":"Social Services",
            "type":"Services"
        }
    ],
    "sg:phone":"+1 201 653 3434",
    "sg:postcode":"07306",
    "sg:province":"NJ",
    "sg:tags":[
        "counseling"
    ],
    "wof:name":"Ronald Becker",
    "wof:placetype":"venue"
},
  "geometry": {"coordinates":[-74.04952400000001,40.735997],"type":"Point"}
}