{
  "type": "Feature",
  "properties": {
    "addr:full":"383 Valley Rd Clifton NJ 07013",
    "addr:housenumber":"383",
    "addr:postcode":"07013",
    "addr:street":"Valley Rd",
    "iso:country":"US",
    "sg:address":"383 Valley Rd",
    "sg:city":"Clifton",
    "sg:classifiers":[
        {
            "category":"Building & Trades",
            "subcategory":"Locksmith",
            "type":"Services"
        }
    ],
    "sg:phone":"+1 888 267 6085",
    "sg:postcode":"07013",
    "sg:province":"NJ",
    "sg:tags":[
        "key"
    ],
    "wof:name":"24 Hour 7 Day Emergency Locksmith",
    "wof:placetype":"venue"
},
  "geometry": {"coordinates":[-74.178138,40.885551],"type":"Point"}
}