{
  "type": "Feature",
  "properties": {
    "iso:country":"US",
    "sg:address":"471 Chestnut St",
    "sg:city":"Ridgefield",
    "sg:classifiers":[
        {
            "category":"Building & Trades",
            "subcategory":"Construction",
            "type":"Services"
        }
    ],
    "sg:phone":"+1 201 945 8527",
    "sg:postcode":"07657",
    "sg:province":"NJ",
    "sg:tags":[
        "contractor"
    ],
    "wof:name":"C & C Masonry Inc",
    "wof:placetype":"venue"
},
  "geometry": {"coordinates":[-73.99948999999999,40.829694],"type":"Point"}
}