{
  "type": "Feature",
  "properties": {
    "iso:country":"US",
    "sg:address":"843 State Rte 33",
    "sg:city":"Freehold",
    "sg:classifiers":[
        {
            "category":"Communications",
            "type":"Services"
        }
    ],
    "sg:phone":"+1 732 409 0277",
    "sg:postcode":"07728",
    "sg:province":"NJ",
    "wof:name":"KDR Communications Inc",
    "wof:placetype":"venue"
},
  "geometry": {"coordinates":[-74.216545,40.232831],"type":"Point"}
}