{
  "type": "Feature",
  "properties": {
    "addr:full":"35 Church St Lodi NJ 07644",
    "addr:housenumber":"35",
    "addr:postcode":"07644",
    "addr:street":"Church St",
    "iso:country":"US",
    "sg:address":"35 Church St",
    "sg:city":"Lodi",
    "sg:classifiers":[
        {
            "category":"Building & Trades",
            "subcategory":"Landscaping Services",
            "type":"Services"
        }
    ],
    "sg:phone":"+1 973 470 2208",
    "sg:postcode":"07644",
    "sg:province":"NJ",
    "sg:tags":[
        "landscape"
    ],
    "wof:name":"Elmwood Landscaping",
    "wof:placetype":"venue"
},
  "geometry": {"coordinates":[-74.083755,40.880197],"type":"Point"}
}