{
  "type": "Feature",
  "properties": {
    "addr:full":"215 Main St Paterson NJ 07505",
    "addr:housenumber":"215",
    "addr:postcode":"07505",
    "addr:street":"Main St",
    "iso:country":"US",
    "sg:address":"215 Main St",
    "sg:city":"Paterson",
    "sg:classifiers":[
        {
            "category":"Shopping",
            "type":"Retail Goods"
        },
        {
            "category":"Shopping",
            "subcategory":"Computers & Home Electronics",
            "type":"Retail Goods"
        }
    ],
    "sg:phone":"+1 973 925 1012",
    "sg:postcode":"07505",
    "sg:province":"NJ",
    "sg:tags":[
        "game",
        "video",
        "merchandise"
    ],
    "wof:name":"Galaxie New & Used Games",
    "wof:placetype":"venue"
},
  "geometry": {"coordinates":[-74.173129,40.916667],"type":"Point"}
}