{
  "type": "Feature",
  "properties": {
    "addr:full":"83 Osceola Rd Wayne NJ 07470",
    "addr:housenumber":"83",
    "addr:postcode":"07470",
    "addr:street":"Osceola Rd",
    "iso:country":"US",
    "sg:address":"83 Osceola Rd",
    "sg:city":"Wayne",
    "sg:classifiers":[
        {
            "category":"Professional",
            "subcategory":"Management & Consulting",
            "type":"Services"
        }
    ],
    "sg:phone":"+1 973 616 1103",
    "sg:postcode":"07470",
    "sg:province":"NJ",
    "sg:tags":[
        "party",
        "planning"
    ],
    "wof:name":"Balloon Works",
    "wof:placetype":"venue"
},
  "geometry": {"coordinates":[-74.257475,40.989138],"type":"Point"}
}