{
  "type": "Feature",
  "properties": {
    "addr:full":"450 State Rte 70 Cherry Hill NJ 08034",
    "addr:housenumber":"450",
    "addr:postcode":"08034",
    "addr:street":"State Rte 70",
    "iso:country":"US",
    "sg:address":"450 State Rte 70",
    "sg:city":"Cherry Hill",
    "sg:classifiers":[
        {
            "category":"Restaurant",
            "type":"Food & Drink"
        }
    ],
    "sg:phone":"+1   ",
    "sg:postcode":"08034",
    "sg:province":"NJ",
    "sg:tags":[
        "eating"
    ],
    "wof:name":"Apollo Pizza",
    "wof:placetype":"venue"
},
  "geometry": {"coordinates":[-75.002388,39.91253],"type":"Point"}
}