{
  "type": "Feature",
  "properties": {
    "iso:country":"US",
    "sg:address":"148 Prospect St",
    "sg:city":"Ridgewood",
    "sg:classifiers":[
        {
            "category":"Organizations",
            "subcategory":"Political Organization",
            "type":"Services"
        }
    ],
    "sg:phone":"+1   ",
    "sg:postcode":"07450",
    "sg:province":"NJ",
    "wof:name":"Fcsa Holiday Boutiques",
    "wof:placetype":"venue"
},
  "geometry": {"coordinates":[-74.11764700000001,40.97568],"type":"Point"}
}