{
  "type": "Feature",
  "properties": {
    "iso:country":"US",
    "sg:address":"4 Heather Dr",
    "sg:city":"Egg Harbor Twp",
    "sg:classifiers":[
        {
            "category":"Restaurant",
            "type":"Food & Drink"
        }
    ],
    "sg:phone":"+1 609 646 7799",
    "sg:postcode":"08234",
    "sg:province":"NJ",
    "sg:tags":[
        "shop",
        "sandwich",
        "sub"
    ],
    "sg:website":"www.atlanticcitysubshops.com",
    "wof:name":"Atlantic City Sub Shop Inc",
    "wof:placetype":"venue"
},
  "geometry": {"coordinates":[-74.56432,39.388689],"type":"Point"}
}