{
  "type": "Feature",
  "properties": {
    "iso:country":"US",
    "sg:address":"40 Broad St",
    "sg:city":"Freehold",
    "sg:classifiers":[
        {
            "category":"Professional",
            "subcategory":"Accounting & Tax Preparation",
            "type":"Services"
        }
    ],
    "sg:phone":"+1 732 303 8400",
    "sg:postcode":"07728",
    "sg:province":"NJ",
    "sg:tags":[
        "accountant"
    ],
    "wof:name":"J H Marin PC",
    "wof:placetype":"venue"
},
  "geometry": {"coordinates":[-74.278611,40.259194],"type":"Point"}
}