{
  "type": "Feature",
  "properties": {
    "addr:full":"3502 Park Ave Weehawken NJ 07086",
    "addr:housenumber":"3502",
    "addr:postcode":"07086",
    "addr:street":"Park Ave",
    "iso:country":"US",
    "sg:address":"3502 Park Ave",
    "sg:city":"Weehawken",
    "sg:classifiers":[
        {
            "category":"Restaurant",
            "type":"Food & Drink"
        }
    ],
    "sg:phone":"+1 201 223 0400",
    "sg:postcode":"07086",
    "sg:province":"NJ",
    "sg:tags":[
        "pizza"
    ],
    "wof:name":"Pizza Villa",
    "wof:placetype":"venue"
},
  "geometry": {"coordinates":[-74.022499,40.771099],"type":"Point"}
}