{
  "type": "Feature",
  "properties": {
    "iso:country":"US",
    "sg:address":"39 Winifred Dr",
    "sg:city":"Totowa",
    "sg:classifiers":[
        {
            "category":"Building & Trades",
            "subcategory":"Plumbing",
            "type":"Services"
        }
    ],
    "sg:phone":"+1 973 890 4371",
    "sg:postcode":"07512",
    "sg:province":"NJ",
    "sg:tags":[
        "contractor"
    ],
    "wof:name":"Airecool Inc",
    "wof:placetype":"venue"
},
  "geometry": {"coordinates":[-74.238427,40.90603],"type":"Point"}
}