{
  "type": "Feature",
  "properties": {
    "addr:full":"103 Carriage Hill Cir Mantua NJ 08051",
    "addr:housenumber":"103",
    "addr:postcode":"08051",
    "addr:street":"Carriage Hill Cir",
    "iso:country":"US",
    "sg:address":"103 Carriage Hill Cir",
    "sg:city":"Mantua",
    "sg:classifiers":[
        {
            "category":"Place Of Worship",
            "type":"Public Place"
        }
    ],
    "sg:phone":"+1 609 870 1517",
    "sg:postcode":"08051",
    "sg:province":"NJ",
    "sg:tags":[
        "church"
    ],
    "wof:name":"Glaxosmthkline Hldngs Ame",
    "wof:placetype":"venue"
},
  "geometry": {"coordinates":[-75.170801,39.785047],"type":"Point"}
}