{
  "type": "Feature",
  "properties": {
    "iso:country":"US",
    "sg:address":"84 Corabelle Ave",
    "sg:city":"Lodi",
    "sg:classifiers":[
        {
            "category":"Building & Trades",
            "subcategory":"Construction",
            "type":"Services"
        }
    ],
    "sg:phone":"+1 973 340 7500",
    "sg:postcode":"07644",
    "sg:province":"NJ",
    "sg:tags":[
        "downspouts",
        "gutter",
        "contractor"
    ],
    "wof:name":"A & I Express Gutters Inc",
    "wof:placetype":"venue"
},
  "geometry": {"coordinates":[-74.089799,40.877702],"type":"Point"}
}