{
  "type": "Feature",
  "properties": {
    "iso:country":"US",
    "sg:address":"139 Mc Clellan St",
    "sg:city":"Newark",
    "sg:classifiers":[
        {
            "category":"Retail",
            "subcategory":"Auto Rental",
            "type":"Services"
        }
    ],
    "sg:phone":"+1 973 483 5202",
    "sg:postcode":"07114",
    "sg:province":"NJ",
    "sg:tags":[
        "trailer",
        "utility"
    ],
    "wof:name":"U-Haul",
    "wof:placetype":"venue"
},
  "geometry": {"coordinates":[-74.197129,40.687722],"type":"Point"}
}