{
  "type": "Feature",
  "properties": {
    "iso:country":"US",
    "sg:address":"229 Orange Rd",
    "sg:city":"Montclair",
    "sg:classifiers":[
        {
            "category":"Building & Trades",
            "subcategory":"Construction",
            "type":"Services"
        }
    ],
    "sg:phone":"+1 973 783 4468",
    "sg:postcode":"07042",
    "sg:province":"NJ",
    "sg:tags":[
        "contractor"
    ],
    "wof:name":"Craftsman Builders",
    "wof:placetype":"venue"
},
  "geometry": {"coordinates":[-74.21970899999999,40.805013],"type":"Point"}
}