{
  "type": "Feature",
  "properties": {
    "addr:full":"842 Glassboro Rd Williamstown NJ 08094",
    "addr:housenumber":"842",
    "addr:postcode":"08094",
    "addr:street":"Glassboro Rd",
    "iso:country":"US",
    "sg:address":"842 Glassboro Rd",
    "sg:city":"Williamstown",
    "sg:classifiers":[
        {
            "category":"Government",
            "subcategory":"Office",
            "type":"Public Place"
        }
    ],
    "sg:phone":"+1   ",
    "sg:postcode":"08094",
    "sg:province":"NJ",
    "sg:tags":[
        "child",
        "day",
        "care"
    ],
    "wof:name":"Human Svcs Rgional Schl Campus",
    "wof:placetype":"venue"
},
  "geometry": {"coordinates":[-75.01486,39.689261],"type":"Point"}
}