{
  "type": "Feature",
  "properties": {
    "iso:country":"US",
    "sg:address":"434 State Rte 72",
    "sg:city":"Manahawkin",
    "sg:classifiers":[
        {
            "category":"Health Services",
            "subcategory":"Doctor",
            "type":"Services"
        }
    ],
    "sg:phone":"+1 609 978 9870",
    "sg:postcode":"08050",
    "sg:province":"NJ",
    "sg:tags":[
        "physician",
        "surgeon"
    ],
    "wof:name":"Ocean Women's Health Care Grp",
    "wof:placetype":"venue"
},
  "geometry": {"coordinates":[-74.26708000000001,39.699421],"type":"Point"}
}