{
  "type": "Feature",
  "properties": {
    "iso:country":"US",
    "sg:address":"611 S Emerson Ave",
    "sg:city":"Clementon",
    "sg:classifiers":[
        {
            "category":"Real Estate",
            "subcategory":"Real Estate Operator",
            "type":"Services"
        },
        {
            "category":"Social Services",
            "type":"Services"
        }
    ],
    "sg:phone":"+1 856 783 1112",
    "sg:postcode":"08021",
    "sg:province":"NJ",
    "sg:tags":[
        "apartment"
    ],
    "wof:name":"Lindenwold Towers",
    "wof:placetype":"venue"
},
  "geometry": {"coordinates":[-74.98232,39.819156],"type":"Point"}
}