{
  "type": "Feature",
  "properties": {
    "iso:country":"US",
    "sg:address":"620 Marketplace Blvd",
    "sg:city":"Trenton",
    "sg:classifiers":[
        {
            "category":"Restaurant",
            "type":"Food & Drink"
        }
    ],
    "sg:menulink":"http://www.allmenus.com/nj/hamilton/228835-jersey-mikes/menu/",
    "sg:phone":"+1 609 585 6081",
    "sg:postcode":"08691",
    "sg:province":"NJ",
    "sg:tags":[
        "american",
        "sandwich"
    ],
    "wof:name":"Jersey Mike's",
    "wof:placetype":"venue"
},
  "geometry": {"coordinates":[-74.63976099999999,40.19553],"type":"Point"}
}