{
  "type": "Feature",
  "properties": {
    "addr:full":"300 US Highway 46 Little Ferry NJ 07643",
    "addr:housenumber":"300",
    "addr:postcode":"07643",
    "addr:street":"Us Highway 46;Ferry",
    "iso:country":"US",
    "sg:address":"300 US Highway 46",
    "sg:city":"Little Ferry",
    "sg:classifiers":[
        {
            "category":"Building & Trades",
            "subcategory":"Locksmith",
            "type":"Services"
        }
    ],
    "sg:phone":"+1 201 403 9366",
    "sg:postcode":"07643",
    "sg:province":"NJ",
    "sg:tags":[
        "key"
    ],
    "wof:name":"Always Available Emergency Locksmith",
    "wof:placetype":"venue"
},
  "geometry": {"coordinates":[-74.042191,40.854812],"type":"Point"}
}