{
  "type": "Feature",
  "properties": {
    "addr:full":"31 Scotch Rd Trenton NJ 08628",
    "addr:housenumber":"31",
    "addr:postcode":"08628",
    "addr:street":"Scotch Rd",
    "iso:country":"US",
    "sg:address":"31 Scotch Rd",
    "sg:city":"Trenton",
    "sg:classifiers":[
        {
            "category":"Food & Beverages",
            "subcategory":"Bakery",
            "type":"Retail Goods"
        }
    ],
    "sg:phone":"+1 609 771 1369",
    "sg:postcode":"08628",
    "sg:province":"NJ",
    "sg:tags":[
        "baker"
    ],
    "wof:name":"Italian Peoples Bakery",
    "wof:placetype":"venue"
},
  "geometry": {"coordinates":[-74.801129,40.266573],"type":"Point"}
}