{
  "type": "Feature",
  "properties": {
    "iso:country":"US",
    "sg:address":"12 Glynn Ct",
    "sg:city":"Parlin",
    "sg:classifiers":[
        {
            "category":"Building & Trades",
            "subcategory":"Construction",
            "type":"Services"
        }
    ],
    "sg:phone":"+1 732 254 3226",
    "sg:postcode":"08859",
    "sg:province":"NJ",
    "sg:tags":[
        "general",
        "contractor"
    ],
    "wof:name":"PMJ Construction",
    "wof:placetype":"venue"
},
  "geometry": {"coordinates":[-74.339292,40.465454],"type":"Point"}
}