{
  "type": "Feature",
  "properties": {
    "addr:full":"1322 Atlantic Ave Atlantic City NJ 08401",
    "addr:housenumber":"1322",
    "addr:postcode":"08401",
    "addr:street":"Atlantic Ave",
    "iso:country":"US",
    "sg:address":"1322 Atlantic Ave",
    "sg:city":"Atlantic City",
    "sg:classifiers":[
        {
            "category":"Personal",
            "subcategory":"Beauty Salon",
            "type":"Services"
        }
    ],
    "sg:phone":"+1 609 441 0096",
    "sg:postcode":"08401",
    "sg:province":"NJ",
    "wof:name":"Fantah African Hair Braiding",
    "wof:placetype":"venue"
},
  "geometry": {"coordinates":[-74.42779299999999,39.362184],"type":"Point"}
}