{
  "type": "Feature",
  "properties": {
    "addr:full":"155 Ave A Bayonne NJ 07002",
    "addr:housenumber":"155",
    "addr:postcode":"07002",
    "addr:street":"Ave A",
    "iso:country":"US",
    "sg:address":"155 Ave A",
    "sg:city":"Bayonne",
    "sg:classifiers":[
        {
            "category":"Manufacturing",
            "subcategory":"Tools & Machinery",
            "type":"Manufacturing & Wholesale Goods"
        }
    ],
    "sg:phone":"+1 201 339 1179",
    "sg:postcode":"07002",
    "sg:province":"NJ",
    "sg:tags":[
        "pattern",
        "maker"
    ],
    "wof:name":"Tri-Delta Patterns Inc",
    "wof:placetype":"venue"
},
  "geometry": {"coordinates":[-74.136011,40.653855],"type":"Point"}
}