{
  "type": "Feature",
  "properties": {
    "addr:full":"154 South St Newark NJ 07114",
    "addr:housenumber":"154",
    "addr:postcode":"07114",
    "addr:street":"South St",
    "iso:country":"US",
    "sg:address":"154 South St",
    "sg:city":"Newark",
    "sg:classifiers":[
        {
            "category":"Personal",
            "subcategory":"Barber",
            "type":"Services"
        }
    ],
    "sg:phone":"+1 973 465 0666",
    "sg:postcode":"07114",
    "sg:province":"NJ",
    "wof:name":"International Barbershop",
    "wof:placetype":"venue"
},
  "geometry": {"coordinates":[-74.17075800000001,40.721914],"type":"Point"}
}