{
  "type": "Feature",
  "properties": {
    "addr:full":"268 Brookside Ave Allendale NJ 07401",
    "addr:housenumber":"268",
    "addr:postcode":"07401",
    "addr:street":"Brookside Ave",
    "iso:country":"US",
    "sg:address":"268 Brookside Ave",
    "sg:city":"Allendale",
    "sg:classifiers":[
        {
            "category":"Professional",
            "type":"Services"
        }
    ],
    "sg:phone":"+1 201 995 1988",
    "sg:postcode":"07401",
    "sg:province":"NJ",
    "sg:tags":[
        "establishment"
    ],
    "wof:name":"Novo Search",
    "wof:placetype":"venue"
},
  "geometry": {"coordinates":[-74.141541,41.028152],"type":"Point"}
}