{
  "type": "Feature",
  "properties": {
    "iso:country":"US",
    "sg:address":"12 Tucker Ct",
    "sg:city":"Willingboro",
    "sg:classifiers":[
        {
            "category":"Wholesale",
            "subcategory":"Groceries",
            "type":"Manufacturing & Wholesale Goods"
        }
    ],
    "sg:phone":"+1 609 871 7148",
    "sg:postcode":"08046",
    "sg:province":"NJ",
    "sg:tags":[
        "food",
        "broker"
    ],
    "wof:name":"The Source",
    "wof:placetype":"venue"
},
  "geometry": {"coordinates":[-74.879615,40.005959],"type":"Point"}
}