{
  "type": "Feature",
  "properties": {
    "iso:country":"US",
    "sg:address":"240 Co Rd 519",
    "sg:city":"Phillipsburg",
    "sg:classifiers":[
        {
            "category":"Education",
            "subcategory":"School",
            "type":"Public Place"
        }
    ],
    "sg:phone":"+1   ",
    "sg:postcode":"08865",
    "sg:province":"NJ",
    "sg:tags":[
        "grade",
        "elementary",
        "k",
        "secondary"
    ],
    "wof:name":"Warren Glen School",
    "wof:placetype":"venue"
},
  "geometry": {"coordinates":[-75.15812699999999,40.669208],"type":"Point"}
}