{
  "type": "Feature",
  "properties": {
    "addr:full":"231 Market St Paterson NJ 07505",
    "addr:housenumber":"231",
    "addr:postcode":"07505",
    "addr:street":"Market St",
    "iso:country":"US",
    "sg:address":"231 Market St",
    "sg:city":"Paterson",
    "sg:classifiers":[
        {
            "category":"Shopping",
            "subcategory":"Computers & Home Electronics",
            "type":"Retail Goods"
        }
    ],
    "sg:phone":"+1 973 777 7454",
    "sg:postcode":"07505",
    "sg:province":"NJ",
    "sg:tags":[
        "equipment",
        "electronic",
        "supply"
    ],
    "wof:name":"Big Deal Electronics",
    "wof:placetype":"venue"
},
  "geometry": {"coordinates":[-74.16963800000001,40.916258],"type":"Point"}
}