{
  "type": "Feature",
  "properties": {
    "iso:country":"US",
    "sg:address":"162 Smith St",
    "sg:city":"Perth Amboy",
    "sg:classifiers":[
        {
            "category":"Shopping",
            "subcategory":"Computers & Home Electronics",
            "type":"Retail Goods"
        }
    ],
    "sg:phone":"+1   ",
    "sg:postcode":"08861",
    "sg:province":"NJ",
    "sg:tags":[
        "consumer"
    ],
    "wof:name":"First Stop Electronics",
    "wof:placetype":"venue"
},
  "geometry": {"coordinates":[-74.26965199999999,40.50909],"type":"Point"}
}