{
  "type": "Feature",
  "properties": {
    "iso:country":"US",
    "sg:address":"538 Mount Laurel Rd",
    "sg:city":"Mt Laurel",
    "sg:classifiers":[
        {
            "category":"Local Transit",
            "type":"Transportation"
        }
    ],
    "sg:phone":"+1 856 235 3053",
    "sg:postcode":"08054",
    "sg:province":"NJ",
    "sg:tags":[
        "bus",
        "line"
    ],
    "wof:name":"Greyhound Trailways Bus Lines",
    "wof:placetype":"venue"
},
  "geometry": {"coordinates":[-74.889788,39.932566],"type":"Point"}
}