{
  "type": "Feature",
  "properties": {
    "addr:full":"54 Mount Laurel Rd Mt Laurel NJ 08054",
    "addr:housenumber":"54",
    "addr:postcode":"08054",
    "addr:street":"Mount Laurel Rd",
    "iso:country":"US",
    "sg:address":"54 Mount Laurel Rd",
    "sg:city":"Mt Laurel",
    "sg:classifiers":[
        {
            "category":"Travel",
            "subcategory":"Campground",
            "type":"Entertainment"
        }
    ],
    "sg:phone":"+1 856 547 8367",
    "sg:postcode":"08054",
    "sg:province":"NJ",
    "sg:tags":[
        "camp"
    ],
    "wof:name":"Camp Cheer",
    "wof:placetype":"venue"
},
  "geometry": {"coordinates":[-74.92762500000001,39.958946],"type":"Point"}
}