{
  "type": "Feature",
  "properties": {
    "addr:full":"344 US Hwy 9 Lanoka Harbor NJ 08734",
    "addr:housenumber":"344",
    "addr:postcode":"08734",
    "addr:street":"Us Hwy 9 Lanoka",
    "iso:country":"US",
    "sg:address":"344 US Hwy 9",
    "sg:city":"Lanoka Harbor",
    "sg:classifiers":[
        {
            "category":"Professional",
            "subcategory":"Business Services",
            "type":"Services"
        }
    ],
    "sg:phone":"+1   ",
    "sg:postcode":"08734",
    "sg:province":"NJ",
    "wof:name":"UPS Stores The",
    "wof:placetype":"venue"
},
  "geometry": {"coordinates":[-74.18268399999999,39.851461],"type":"Point"}
}