{
  "type": "Feature",
  "properties": {
    "addr:full":"265 Main St Apt 611 Ridgefield Park NJ 07660",
    "addr:housenumber":"265;611",
    "addr:postcode":"07660",
    "addr:street":"Main St Apt",
    "iso:country":"US",
    "sg:address":"265 Main St Apt 611",
    "sg:city":"Ridgefield Park",
    "sg:classifiers":[
        {
            "category":"Real Estate",
            "subcategory":"Real Estate Operator",
            "type":"Services"
        }
    ],
    "sg:phone":"+1 201 440 2638",
    "sg:postcode":"07660",
    "sg:province":"NJ",
    "sg:tags":[
        "apartment"
    ],
    "wof:name":"Marlboro House",
    "wof:placetype":"venue"
},
  "geometry": {"coordinates":[-74.0243,40.859798],"type":"Point"}
}