{
  "type": "Feature",
  "properties": {
    "iso:country":"US",
    "sg:address":"130 Newton Sparta Ave",
    "sg:city":"Newton",
    "sg:classifiers":[
        {
            "category":"Shopping",
            "subcategory":"Gifts & Souvenirs",
            "type":"Retail Goods"
        }
    ],
    "sg:phone":"+1 973 579 5508",
    "sg:postcode":"07860",
    "sg:province":"NJ",
    "sg:tags":[
        "shop"
    ],
    "wof:name":"Country Crossings",
    "wof:placetype":"venue"
},
  "geometry": {"coordinates":[-74.72143800000001,41.041486],"type":"Point"}
}