{
  "type": "Feature",
  "properties": {
    "iso:country":"US",
    "sg:address":"423 Cooper Rd",
    "sg:city":"Voorhees",
    "sg:classifiers":[
        {
            "category":"Government",
            "subcategory":"Fire Station",
            "type":"Public Place"
        }
    ],
    "sg:phone":"+1   ",
    "sg:postcode":"08043",
    "sg:province":"NJ",
    "sg:tags":[
        "protection"
    ],
    "wof:name":"Kresson Fire District",
    "wof:placetype":"venue"
},
  "geometry": {"coordinates":[-74.94117199999999,39.843616],"type":"Point"}
}