{
  "type": "Feature",
  "properties": {
    "iso:country":"US",
    "sg:address":"15 Iron Horse Rd",
    "sg:city":"Oakland",
    "sg:classifiers":[
        {
            "category":"Building & Trades",
            "subcategory":"Construction",
            "type":"Services"
        }
    ],
    "sg:phone":"+1 973 835 6540",
    "sg:postcode":"07436",
    "sg:province":"NJ",
    "sg:tags":[
        "housing"
    ],
    "wof:name":"J and K Construction Inc",
    "wof:placetype":"venue"
},
  "geometry": {"coordinates":[-74.260578,41.02328],"type":"Point"}
}