{
  "type": "Feature",
  "properties": {
    "iso:country":"US",
    "sg:address":"1601 Madison St",
    "sg:city":"Hoboken",
    "sg:classifiers":[
        {
            "category":"Food & Beverages",
            "subcategory":"Specialty",
            "type":"Retail Goods"
        },
        {
            "category":"Wholesale",
            "subcategory":"Groceries",
            "type":"Manufacturing & Wholesale Goods"
        }
    ],
    "sg:phone":"+1 201 963 2329",
    "sg:postcode":"07030",
    "sg:province":"NJ",
    "sg:tags":[
        "manufacture",
        "water",
        "coffee",
        "tea",
        "bulk",
        "import"
    ],
    "wof:name":"Pan American Coffee Co Inc",
    "wof:placetype":"venue"
},
  "geometry": {"coordinates":[-74.033897,40.756199],"type":"Point"}
}