{
  "type": "Feature",
  "properties": {
    "iso:country":"US",
    "sg:address":"1030 Washington St",
    "sg:city":"Hoboken",
    "sg:classifiers":[
        {
            "category":"Shopping",
            "subcategory":"Clothing, Apparel, & Fashions",
            "type":"Retail Goods"
        }
    ],
    "sg:phone":"+1   ",
    "sg:postcode":"07030",
    "sg:province":"NJ",
    "sg:tags":[
        "store"
    ],
    "wof:name":"Peper",
    "wof:placetype":"venue"
},
  "geometry": {"coordinates":[-74.027265,40.749456],"type":"Point"}
}