{
  "type": "Feature",
  "properties": {
    "addr:full":"112 Wood St Wyckoff NJ 07481",
    "addr:housenumber":"112",
    "addr:postcode":"07481",
    "addr:street":"Wood St",
    "iso:country":"US",
    "sg:address":"112 Wood St",
    "sg:city":"Wyckoff",
    "sg:classifiers":[
        {
            "category":"Professional",
            "subcategory":"Business Services",
            "type":"Services"
        }
    ],
    "sg:phone":"+1 201 838 5773",
    "sg:postcode":"07481",
    "sg:province":"NJ",
    "sg:tags":[
        "designer",
        "display",
        "producer"
    ],
    "sg:website":"http://www.pixel8studio.com",
    "wof:name":"Pixel 8 Studio",
    "wof:placetype":"venue"
},
  "geometry": {"coordinates":[-74.156355,41.009164],"type":"Point"}
}