{
  "type": "Feature",
  "properties": {
    "iso:country":"US",
    "sg:address":"23 Church St",
    "sg:city":"Lambertville",
    "sg:classifiers":[
        {
            "category":"Home & Garden",
            "subcategory":"Home Furnishings",
            "type":"Retail Goods"
        }
    ],
    "sg:phone":"+1   ",
    "sg:postcode":"08530",
    "sg:province":"NJ",
    "wof:name":"Soma",
    "wof:placetype":"venue"
},
  "geometry": {"coordinates":[-74.944315,40.366893],"type":"Point"}
}