{
  "type": "Feature",
  "properties": {
    "addr:full":"1 Magnolia Dr & Dennis Ave Cape May Court House NJ 08210",
    "addr:housenumber":"1",
    "addr:postcode":"08210",
    "addr:street":"Magnolia Dr & Dennis Ave Cape May",
    "iso:country":"US",
    "sg:address":"1 Magnolia Dr & Dennis Ave",
    "sg:city":"Cape May Court House",
    "sg:classifiers":[
        {
            "category":"Restaurant",
            "type":"Food & Drink"
        }
    ],
    "sg:phone":"+1 609 465 2039",
    "sg:postcode":"08210",
    "sg:province":"NJ",
    "sg:tags":[
        "pizza",
        "italian"
    ],
    "wof:name":"Alfredo's Italian Restaurant & Pizzeria",
    "wof:placetype":"venue"
},
  "geometry": {"coordinates":[-74.81953,39.08839],"type":"Point"}
}