{
  "type": "Feature",
  "properties": {
    "iso:country":"US",
    "sg:address":"1501 Admiral Wilson Blvd",
    "sg:city":"Pennsauken",
    "sg:classifiers":[
        {
            "category":"Autos & Motor Vehicles",
            "subcategory":"Auto Supplies",
            "type":"Retail Goods"
        }
    ],
    "sg:phone":"+1 856 541 1220",
    "sg:postcode":"08109",
    "sg:province":"NJ",
    "sg:tags":[
        "wheel",
        "cover"
    ],
    "wof:name":"Wheels Coach Inc",
    "wof:placetype":"venue"
},
  "geometry": {"coordinates":[-75.100944,39.940881],"type":"Point"}
}