{
  "type": "Feature",
  "properties": {
    "iso:country":"US",
    "sg:address":"1278 Valley Rd",
    "sg:city":"Stirling",
    "sg:classifiers":[
        {
            "category":"Retail",
            "subcategory":"Laundry & Dry Cleaning",
            "type":"Services"
        }
    ],
    "sg:phone":"+1   ",
    "sg:postcode":"07980",
    "sg:province":"NJ",
    "sg:tags":[
        "drycleaning",
        "plant"
    ],
    "wof:name":"Regal Cleaning",
    "wof:placetype":"venue"
},
  "geometry": {"coordinates":[-74.49328199999999,40.667896],"type":"Point"}
}