{
  "type": "Feature",
  "properties": {
    "addr:full":"145 Commerce Rd Carlstadt NJ 07072",
    "addr:housenumber":"145",
    "addr:postcode":"07072",
    "addr:street":"Commerce Rd",
    "iso:country":"US",
    "sg:address":"145 Commerce Rd",
    "sg:city":"Carlstadt",
    "sg:classifiers":[
        {
            "category":"Professional",
            "subcategory":"Business Services",
            "type":"Services"
        }
    ],
    "sg:phone":"+1 201 935 0700",
    "sg:postcode":"07072",
    "sg:province":"NJ",
    "sg:tags":[
        "packaging",
        "specialty"
    ],
    "wof:name":"Rjf Graphics Inc",
    "wof:placetype":"venue"
},
  "geometry": {"coordinates":[-74.059066,40.830222],"type":"Point"}
}