{
  "type": "Feature",
  "properties": {
    "iso:country":"US",
    "sg:address":"80 Hague St",
    "sg:city":"Jersey City",
    "sg:classifiers":[
        {
            "category":"Freight",
            "type":"Transportation"
        }
    ],
    "sg:phone":"+1 201 420 4219",
    "sg:postcode":"07307",
    "sg:province":"NJ",
    "sg:tags":[
        "packing",
        "crating"
    ],
    "wof:name":"Despatch International Co",
    "wof:placetype":"venue"
},
  "geometry": {"coordinates":[-74.04908399999999,40.757807],"type":"Point"}
}