{
  "type": "Feature",
  "properties": {
    "addr:full":"1222 Maple Ave Atco NJ 08004",
    "addr:housenumber":"1222",
    "addr:postcode":"08004",
    "addr:street":"Maple Ave",
    "iso:country":"US",
    "sg:address":"1222 Maple Ave",
    "sg:city":"Atco",
    "sg:classifiers":[
        {
            "category":"Professional",
            "subcategory":"Computer Services",
            "type":"Services"
        }
    ],
    "sg:phone":"+1 856 753 0107",
    "sg:postcode":"08004",
    "sg:province":"NJ",
    "sg:tags":[
        "datum",
        "business"
    ],
    "wof:name":"Applied Check Technology",
    "wof:placetype":"venue"
},
  "geometry": {"coordinates":[-74.826538,39.755511],"type":"Point"}
}