{
  "type": "Feature",
  "properties": {
    "addr:full":"21 Maple Ave Rockaway NJ 07866",
    "addr:housenumber":"21",
    "addr:postcode":"07866",
    "addr:street":"Maple Ave",
    "iso:country":"US",
    "sg:address":"21 Maple Ave",
    "sg:city":"Rockaway",
    "sg:classifiers":[
        {
            "category":"Wholesale",
            "subcategory":"Scrap",
            "type":"Manufacturing & Wholesale Goods"
        }
    ],
    "sg:phone":"+1 973 625 2177",
    "sg:postcode":"07866",
    "sg:province":"NJ",
    "sg:tags":[
        "material"
    ],
    "wof:name":"Wholly Scrap",
    "wof:placetype":"venue"
},
  "geometry": {"coordinates":[-74.51274600000001,40.901299],"type":"Point"}
}