{
  "type": "Feature",
  "properties": {
    "addr:full":"254 Tilton Rd Northfield NJ 08225",
    "addr:housenumber":"254",
    "addr:postcode":"08225",
    "addr:street":"Tilton Rd",
    "iso:country":"US",
    "sg:address":"254 Tilton Rd",
    "sg:city":"Northfield",
    "sg:classifiers":[
        {
            "category":"Wholesale",
            "subcategory":"Sporting Goods",
            "type":"Manufacturing & Wholesale Goods"
        }
    ],
    "sg:phone":"+1 609 569 1973",
    "sg:postcode":"08225",
    "sg:province":"NJ",
    "sg:tags":[
        "equipment",
        "billiard",
        "supply"
    ],
    "wof:name":"Recreation Depot",
    "wof:placetype":"venue"
},
  "geometry": {"coordinates":[-74.55830899999999,39.391253],"type":"Point"}
}