{
  "type": "Feature",
  "properties": {
    "iso:country":"US",
    "sg:address":"296 Midland Ave Ste G",
    "sg:city":"Saddle Brook",
    "sg:classifiers":[
        {
            "category":"Professional",
            "type":"Services"
        }
    ],
    "sg:phone":"+1 973 405 6226",
    "sg:postcode":"07663",
    "sg:province":"NJ",
    "sg:tags":[
        "caterer"
    ],
    "wof:name":"Kosher Productions Inc",
    "wof:placetype":"venue"
},
  "geometry": {"coordinates":[-74.10677099999999,40.907867],"type":"Point"}
}