{
  "type": "Feature",
  "properties": {
    "addr:full":"115 Columbia Ave Passaic NJ 07055",
    "addr:housenumber":"115",
    "addr:postcode":"07055",
    "addr:street":"Columbia Ave",
    "iso:country":"US",
    "sg:address":"115 Columbia Ave",
    "sg:city":"Passaic",
    "sg:classifiers":[
        {
            "category":"Retail",
            "subcategory":"Auto Repair",
            "type":"Services"
        }
    ],
    "sg:phone":"+1   ",
    "sg:postcode":"07055",
    "sg:province":"NJ",
    "sg:tags":[
        "body",
        "general"
    ],
    "wof:name":"Vinces Auto Body Inc",
    "wof:placetype":"venue"
},
  "geometry": {"coordinates":[-74.122862,40.864437],"type":"Point"}
}