{
  "type": "Feature",
  "properties": {
    "addr:full":"1200 Morris Tpke Short Hills NJ 07078",
    "addr:housenumber":"1200",
    "addr:postcode":"07078",
    "addr:street":"Morris Tpke",
    "iso:country":"US",
    "sg:address":"1200 Morris Tpke",
    "sg:city":"Short Hills",
    "sg:classifiers":[
        {
            "category":"Shopping",
            "subcategory":"Shoes",
            "type":"Retail Goods"
        }
    ],
    "sg:phone":"+1 973 258 0131",
    "sg:postcode":"07078",
    "sg:province":"NJ",
    "sg:tags":[
        "store"
    ],
    "wof:name":"Aldo Shoes",
    "wof:placetype":"venue"
},
  "geometry": {"coordinates":[-74.36370100000001,40.737701],"type":"Point"}
}