{
  "type": "Feature",
  "properties": {
    "iso:country":"US",
    "sg:address":"6528 Black Horse Pike",
    "sg:city":"Egg Harbor Twp",
    "sg:classifiers":[
        {
            "category":"Retail",
            "subcategory":"Auto Repair",
            "type":"Services"
        }
    ],
    "sg:phone":"+1 609 407 9888",
    "sg:postcode":"08234",
    "sg:province":"NJ",
    "sg:tags":[
        "body",
        "automobile",
        "painting"
    ],
    "wof:name":"Carl's Auto Body Svc",
    "wof:placetype":"venue"
},
  "geometry": {"coordinates":[-74.583967,39.419527],"type":"Point"}
}