{
  "type": "Feature",
  "properties": {
    "addr:full":"1 Howe Ave Ste 5 Passaic NJ 07055",
    "addr:housenumber":"1",
    "addr:postcode":"07055",
    "addr:street":"Howe Ave Ste 5",
    "iso:country":"US",
    "sg:address":"1 Howe Ave Ste 5",
    "sg:city":"Passaic",
    "sg:classifiers":[
        {
            "category":"Professional",
            "subcategory":"Lawyer & Legal Services",
            "type":"Services"
        }
    ],
    "sg:phone":"+1 973 473 1113",
    "sg:postcode":"07055",
    "sg:province":"NJ",
    "sg:tags":[
        "personal",
        "injury"
    ],
    "sg:website":"www.gbowlaw.com",
    "wof:name":"Goldstein Ballen O'rourke & Wildstein Lawyers",
    "wof:placetype":"venue"
},
  "geometry": {"coordinates":[-74.126801,40.861099],"type":"Point"}
}