{
  "type": "Feature",
  "properties": {
    "iso:country":"US",
    "sg:address":"265 E Bay Ave",
    "sg:city":"Manahawkin",
    "sg:classifiers":[
        {
            "category":"Retail",
            "subcategory":"Auto Repair",
            "type":"Services"
        }
    ],
    "sg:phone":"+1 609 597 3461",
    "sg:postcode":"08050",
    "sg:province":"NJ",
    "sg:tags":[
        "repairing",
        "automobile"
    ],
    "wof:name":"Bob Beron's Auto Repair",
    "wof:placetype":"venue"
},
  "geometry": {"coordinates":[-74.25127500000001,39.691639],"type":"Point"}
}