{
  "type": "Feature",
  "properties": {
    "addr:full":"11 E Price St Linden NJ 07036",
    "addr:housenumber":"11",
    "addr:postcode":"07036",
    "addr:street":"E Price St",
    "iso:country":"US",
    "sg:address":"11 E Price St",
    "sg:city":"Linden",
    "sg:classifiers":[
        {
            "category":"Deli",
            "type":"Food & Drink"
        }
    ],
    "sg:phone":"+1 908 486 2860",
    "sg:postcode":"07036",
    "sg:province":"NJ",
    "wof:name":"C & C Polish Delicatessen",
    "wof:placetype":"venue"
},
  "geometry": {"coordinates":[-74.25340300000001,40.631401],"type":"Point"}
}