{
  "type": "Feature",
  "properties": {
    "addr:full":"240 Martin Luther King Jr Blvd Newark NJ 07102",
    "addr:housenumber":"240",
    "addr:postcode":"07102",
    "addr:street":"Martin Luther King Jr Blvd",
    "iso:country":"US",
    "sg:address":"240 Martin Luther King Jr Blvd",
    "sg:city":"Newark",
    "sg:classifiers":[
        {
            "category":"Organizations",
            "subcategory":"Membership Organization",
            "type":"Services"
        }
    ],
    "sg:phone":"+1 973 623 5700",
    "sg:postcode":"07102",
    "sg:province":"NJ",
    "wof:name":"Friends The Media",
    "wof:placetype":"venue"
},
  "geometry": {"coordinates":[-74.174606,40.746207],"type":"Point"}
}