{
  "type": "Feature",
  "properties": {
    "iso:country":"US",
    "sg:address":"427 Bloomfield Ave",
    "sg:city":"Montclair",
    "sg:classifiers":[
        {
            "category":"Banks & Credit Unions",
            "subcategory":"Bank",
            "type":"Services"
        }
    ],
    "sg:phone":"+1 973 233 0901",
    "sg:postcode":"07042",
    "sg:province":"NJ",
    "wof:name":"Proponet Fcu",
    "wof:placetype":"venue"
},
  "geometry": {"coordinates":[-74.216391,40.813187],"type":"Point"}
}