{
  "type": "Feature",
  "properties": {
    "addr:full":"47 Walnut Ave Bogota NJ 07603",
    "addr:housenumber":"47",
    "addr:postcode":"07603",
    "addr:street":"Walnut Ave",
    "iso:country":"US",
    "sg:address":"47 Walnut Ave",
    "sg:city":"Bogota",
    "sg:classifiers":[
        {
            "category":"Shopping",
            "subcategory":"Books",
            "type":"Retail Goods"
        }
    ],
    "sg:phone":"+1   ",
    "sg:postcode":"07603",
    "sg:province":"NJ",
    "wof:name":"By Books",
    "wof:placetype":"venue"
},
  "geometry": {"coordinates":[-74.028582,40.871529],"type":"Point"}
}