{
  "type": "Feature",
  "properties": {
    "addr:full":"6810 Atlantic Ave Wildwood NJ 08260",
    "addr:housenumber":"6810",
    "addr:postcode":"08260",
    "addr:street":"Atlantic Ave",
    "iso:country":"US",
    "sg:address":"6810 Atlantic Ave",
    "sg:city":"Wildwood",
    "sg:classifiers":[
        {
            "category":"Professional",
            "subcategory":"Lawyer & Legal Services",
            "type":"Services"
        }
    ],
    "sg:phone":"+1 609 522 1553",
    "sg:postcode":"08260",
    "sg:province":"NJ",
    "wof:name":"Kay E W",
    "wof:placetype":"venue"
},
  "geometry": {"coordinates":[-74.834023,38.97228],"type":"Point"}
}