{
  "type": "Feature",
  "properties": {
    "iso:country":"US",
    "sg:address":"112 South Ave E",
    "sg:city":"Cranford",
    "sg:classifiers":[
        {
            "category":"Building & Trades",
            "subcategory":"Locksmith",
            "type":"Services"
        }
    ],
    "sg:phone":"+1 908 956 0205",
    "sg:postcode":"07016",
    "sg:province":"NJ",
    "sg:tags":[
        "key"
    ],
    "wof:name":"A Emergency Locksmith",
    "wof:placetype":"venue"
},
  "geometry": {"coordinates":[-74.304271,40.654419],"type":"Point"}
}