{
  "type": "Feature",
  "properties": {
    "addr:full":"201 Veterans Ave West Berlin NJ 08091",
    "addr:housenumber":"201",
    "addr:postcode":"08091",
    "addr:street":"Veterans Ave",
    "iso:country":"US",
    "sg:address":"201 Veterans Ave",
    "sg:city":"West Berlin",
    "sg:classifiers":[
        {
            "category":"Education",
            "subcategory":"Library",
            "type":"Public Place"
        }
    ],
    "sg:phone":"+1 856 767 0439",
    "sg:postcode":"08091",
    "sg:province":"NJ",
    "sg:website":"www.berlintwp.com",
    "wof:name":"Berlin Township Library",
    "wof:placetype":"venue"
},
  "geometry": {"coordinates":[-74.939114,39.813849],"type":"Point"}
}