{
  "type": "Feature",
  "properties": {
    "addr:full":"23 Ridgeway Ave Hillside NJ 07205",
    "addr:housenumber":"23",
    "addr:postcode":"07205",
    "addr:street":"Ridgeway Ave",
    "iso:country":"US",
    "sg:address":"23 Ridgeway Ave",
    "sg:city":"Hillside",
    "sg:classifiers":[
        {
            "category":"Building & Trades",
            "subcategory":"Pest Control",
            "type":"Services"
        }
    ],
    "sg:phone":"+1 908 352 7959",
    "sg:postcode":"07205",
    "sg:province":"NJ",
    "wof:name":"Portugal Exterminating Service",
    "wof:placetype":"venue"
},
  "geometry": {"coordinates":[-74.21732,40.695299],"type":"Point"}
}