{
  "type": "Feature",
  "properties": {
    "addr:full":"1601 N Wood Ave Linden NJ 07036",
    "addr:housenumber":"1601",
    "addr:postcode":"07036",
    "addr:street":"N Wood Ave",
    "iso:country":"US",
    "sg:address":"1601 N Wood Ave",
    "sg:city":"Linden",
    "sg:classifiers":[
        {
            "category":"Health Services",
            "subcategory":"Chiropractor",
            "type":"Services"
        }
    ],
    "sg:phone":"+1 908 486 8964",
    "sg:postcode":"07036",
    "sg:province":"NJ",
    "wof:name":"Watter M J Chiropractor",
    "wof:placetype":"venue"
},
  "geometry": {"coordinates":[-74.26849799999999,40.64021],"type":"Point"}
}