{
  "type": "Feature",
  "properties": {
    "addr:full":"15 Lee Pl Paterson NJ 07505",
    "addr:housenumber":"15",
    "addr:postcode":"07505",
    "addr:street":"Lee Pl",
    "iso:country":"US",
    "sg:address":"15 Lee Pl",
    "sg:city":"Paterson",
    "sg:classifiers":[
        {
            "category":"Professional",
            "subcategory":"Lawyer & Legal Services",
            "type":"Services"
        }
    ],
    "sg:phone":"+1 973 279 5405",
    "sg:postcode":"07505",
    "sg:province":"NJ",
    "sg:tags":[
        "attorney",
        "apartment"
    ],
    "wof:name":"Colt Associates",
    "wof:placetype":"venue"
},
  "geometry": {"coordinates":[-74.17240099999999,40.914101],"type":"Point"}
}