{
  "type": "Feature",
  "properties": {
    "addr:full":"899 S Broad St Trenton NJ 08611",
    "addr:housenumber":"899",
    "addr:postcode":"08611",
    "addr:street":"S Broad St",
    "iso:country":"US",
    "sg:address":"899 S Broad St",
    "sg:city":"Trenton",
    "sg:classifiers":[
        {
            "category":"Health Services",
            "subcategory":"Chiropractor",
            "type":"Services"
        }
    ],
    "sg:phone":"+1 609 392 8707",
    "sg:postcode":"08611",
    "sg:province":"NJ",
    "wof:name":"Trenton Chiropractic Office",
    "wof:placetype":"venue"
},
  "geometry": {"coordinates":[-74.74962499999999,40.206837],"type":"Point"}
}