{
  "type": "Feature",
  "properties": {
    "iso:country":"US",
    "sg:address":"4 Olsen Dr",
    "sg:city":"Franklin Park",
    "sg:classifiers":[
        {
            "category":"Shopping",
            "subcategory":"Computers & Home Electronics",
            "type":"Retail Goods"
        }
    ],
    "sg:phone":"+1 732 398 0113",
    "sg:postcode":"08823",
    "sg:province":"NJ",
    "sg:tags":[
        "software"
    ],
    "wof:name":"Systemetic Software Solutions",
    "wof:placetype":"venue"
},
  "geometry": {"coordinates":[-74.574088,40.443356],"type":"Point"}
}