{
  "type": "Feature",
  "properties": {
    "addr:full":"67 Stirling Rd Watchung NJ 07069",
    "addr:housenumber":"67",
    "addr:postcode":"07069",
    "addr:street":"Stirling Rd",
    "iso:country":"US",
    "sg:address":"67 Stirling Rd",
    "sg:city":"Watchung",
    "sg:classifiers":[
        {
            "category":"Retail",
            "subcategory":"Repair Shop",
            "type":"Services"
        }
    ],
    "sg:phone":"+1 908 372 6544",
    "sg:postcode":"07069",
    "sg:province":"NJ",
    "sg:tags":[
        "lock",
        "locksmith"
    ],
    "wof:name":"USA Locksmith",
    "wof:placetype":"venue"
},
  "geometry": {"coordinates":[-74.45125299999999,40.637618],"type":"Point"}
}