{
  "type": "Feature",
  "properties": {
    "addr:full":"3 1st Ave Raritan NJ 08869",
    "addr:housenumber":"3",
    "addr:postcode":"08869",
    "addr:street":"1St Ave",
    "iso:country":"US",
    "sg:address":"3 1st Ave",
    "sg:city":"Raritan",
    "sg:classifiers":[
        {
            "category":"Restaurant",
            "type":"Food & Drink"
        }
    ],
    "sg:phone":"+1 908 725 1322",
    "sg:postcode":"08869",
    "sg:province":"NJ",
    "sg:tags":[
        "pizza"
    ],
    "wof:name":"De Lucia's Pizzeria",
    "wof:placetype":"venue"
},
  "geometry": {"coordinates":[-74.63784099999999,40.566958],"type":"Point"}
}