{
  "type": "Feature",
  "properties": {
    "addr:full":"1065 Main St River Edge NJ 07661",
    "addr:housenumber":"1065",
    "addr:postcode":"07661",
    "addr:street":"Main St",
    "iso:country":"US",
    "sg:address":"1065 Main St",
    "sg:city":"River Edge",
    "sg:classifiers":[
        {
            "category":"Personal",
            "subcategory":"Beauty Salon",
            "type":"Services"
        }
    ],
    "sg:phone":"+1 201 342 4829",
    "sg:postcode":"07661",
    "sg:province":"NJ",
    "wof:name":"Hair Biz",
    "wof:placetype":"venue"
},
  "geometry": {"coordinates":[-74.036557,40.912618],"type":"Point"}
}