{
  "type": "Feature",
  "properties": {
    "iso:country":"US",
    "sg:address":"1063 Broad Street",
    "sg:city":"Bloomfield",
    "sg:classifiers":[
        {
            "category":"Ice Cream",
            "type":"Food & Drink"
        }
    ],
    "sg:postcode":"07003",
    "sg:province":"NJ",
    "sg:tags":[
        "frozen",
        "yogurt"
    ],
    "sg:website":"www.holstens.com",
    "wof:name":"Holsten's",
    "wof:placetype":"venue"
},
  "geometry": {"coordinates":[-74.18677599999999,40.828469],"type":"Point"}
}