{
  "type": "Feature",
  "properties": {
    "addr:full":"850 Warwick Tpke Hewitt NJ 07421",
    "addr:housenumber":"850",
    "addr:postcode":"07421",
    "addr:street":"Warwick Tpke",
    "iso:country":"US",
    "sg:address":"850 Warwick Tpke",
    "sg:city":"Hewitt",
    "sg:classifiers":[
        {
            "category":"Building & Trades",
            "subcategory":"Construction",
            "type":"Services"
        }
    ],
    "sg:phone":"+1 973 492 2861",
    "sg:postcode":"07421",
    "sg:province":"NJ",
    "sg:tags":[
        "excavation",
        "excavating",
        "contractor"
    ],
    "wof:name":"Vreeland Excavating Corp",
    "wof:placetype":"venue"
},
  "geometry": {"coordinates":[-74.385036,41.209568],"type":"Point"}
}