{
  "type": "Feature",
  "properties": {
    "iso:country":"US",
    "sg:address":"114 Kings Mountain Rd",
    "sg:city":"Freehold",
    "sg:classifiers":[
        {
            "category":"Insurance",
            "subcategory":"Insurance Agent",
            "type":"Services"
        }
    ],
    "sg:phone":"+1 732 303 0818",
    "sg:postcode":"07728",
    "sg:province":"NJ",
    "sg:tags":[
        "processing"
    ],
    "wof:name":"Med-A-Claims Svc",
    "wof:placetype":"venue"
},
  "geometry": {"coordinates":[-74.297827,40.225323],"type":"Point"}
}