{
  "type": "Feature",
  "properties": {
    "addr:full":"709 Dettmar Ter Runnemede NJ 08078",
    "addr:housenumber":"709",
    "addr:postcode":"08078",
    "addr:street":"Dettmar Ter",
    "iso:country":"US",
    "sg:address":"709 Dettmar Ter",
    "sg:city":"Runnemede",
    "sg:classifiers":[
        {
            "category":"Recreation",
            "subcategory":"Boat Charter",
            "type":"Entertainment"
        },
        {
            "category":"Building & Trades",
            "subcategory":"Electrical",
            "type":"Services"
        }
    ],
    "sg:phone":"+1 856 933 2838",
    "sg:postcode":"08078",
    "sg:province":"NJ",
    "sg:tags":[
        "boating",
        "electrician"
    ],
    "wof:name":"Colonial Electric",
    "wof:placetype":"venue"
},
  "geometry": {"coordinates":[-75.089699,39.8498],"type":"Point"}
}