{
  "type": "Feature",
  "properties": {
    "addr:full":"135 W Main St Somerville NJ 08876",
    "addr:housenumber":"135",
    "addr:postcode":"08876",
    "addr:street":"W Main St",
    "iso:country":"US",
    "sg:address":"135 W Main St",
    "sg:city":"Somerville",
    "sg:classifiers":[
        {
            "category":"Shopping",
            "subcategory":"Computers & Home Electronics",
            "type":"Retail Goods"
        }
    ],
    "sg:phone":"+1   ",
    "sg:postcode":"08876",
    "sg:province":"NJ",
    "wof:name":"Radio Shack",
    "wof:placetype":"venue"
},
  "geometry": {"coordinates":[-74.614954,40.569139],"type":"Point"}
}