{
  "type": "Feature",
  "properties": {
    "addr:full":"108 N Union Ave Cranford NJ 07016",
    "addr:housenumber":"108",
    "addr:postcode":"07016",
    "addr:street":"N Union Ave",
    "iso:country":"US",
    "sg:address":"108 N Union Ave",
    "sg:city":"Cranford",
    "sg:classifiers":[
        {
            "category":"Professional",
            "subcategory":"Lawyer & Legal Services",
            "type":"Services"
        }
    ],
    "sg:phone":"+1 908 272 0075",
    "sg:postcode":"07016",
    "sg:province":"NJ",
    "sg:tags":[
        "attorney"
    ],
    "wof:name":"Andrew M Baron",
    "wof:placetype":"venue"
},
  "geometry": {"coordinates":[-74.30266,40.657244],"type":"Point"}
}