{
  "type": "Feature",
  "properties": {
    "iso:country":"US",
    "sg:address":"297 Gardner Rd",
    "sg:city":"Ridgewood",
    "sg:classifiers":[
        {
            "category":"Professional",
            "subcategory":"Business Services",
            "type":"Services"
        }
    ],
    "sg:phone":"+1 201 670 9555",
    "sg:postcode":"07450",
    "sg:province":"NJ",
    "sg:tags":[
        "interior",
        "consultant",
        "design",
        "decorator"
    ],
    "wof:name":"O'Pray Interiors",
    "wof:placetype":"venue"
},
  "geometry": {"coordinates":[-74.141088,40.974182],"type":"Point"}
}