{
  "type": "Feature",
  "properties": {
    "addr:full":"2629 State Rte 516 Old Bridge NJ 08857",
    "addr:housenumber":"2629",
    "addr:postcode":"08857",
    "addr:street":"State Rte 516",
    "iso:country":"US",
    "sg:address":"2629 State Rte 516",
    "sg:city":"Old Bridge",
    "sg:classifiers":[
        {
            "category":"Food & Beverages",
            "subcategory":"Liquor & Beverages",
            "type":"Retail Goods"
        }
    ],
    "sg:phone":"+1 732 679 0066",
    "sg:postcode":"08857",
    "sg:province":"NJ",
    "sg:tags":[
        "wine"
    ],
    "wof:name":"Browntown Inn",
    "wof:placetype":"venue"
},
  "geometry": {"coordinates":[-74.33127500000001,40.405782],"type":"Point"}
}