{
  "type": "Feature",
  "properties": {
    "addr:full":"1612 State Rte 34 Neptune NJ 07756",
    "addr:housenumber":"1612",
    "addr:postcode":"07756",
    "addr:street":"State Rte 34",
    "iso:country":"US",
    "sg:address":"1612 State Rte 34",
    "sg:city":"Neptune",
    "sg:classifiers":[
        {
            "category":"Building & Trades",
            "subcategory":"Plumbing",
            "type":"Services"
        }
    ],
    "sg:phone":"+1 732 681 3988",
    "sg:postcode":"07756",
    "sg:province":"NJ",
    "sg:tags":[
        "plumbing",
        "contractor"
    ],
    "wof:name":"Bill Shrewsbury Plumbing & Htg",
    "wof:placetype":"venue"
},
  "geometry": {"coordinates":[-74.116581,40.190516],"type":"Point"}
}