{
  "type": "Feature",
  "properties": {
    "addr:full":"15 Maple Ave Fair Lawn NJ 07410",
    "addr:housenumber":"15",
    "addr:postcode":"07410",
    "addr:street":"Maple Ave",
    "iso:country":"US",
    "sg:address":"15 Maple Ave",
    "sg:city":"Fair Lawn",
    "sg:classifiers":[
        {
            "category":"Shopping",
            "subcategory":"Optical Goods",
            "type":"Retail Goods"
        }
    ],
    "sg:phone":"+1 201 796 4414",
    "sg:postcode":"07410",
    "sg:province":"NJ",
    "wof:name":"Art Of Eyewear",
    "wof:placetype":"venue"
},
  "geometry": {"coordinates":[-74.13998599999999,40.945477],"type":"Point"}
}