{
  "type": "Feature",
  "properties": {
    "iso:country":"US",
    "sg:address":"32 Moorsgate Cir",
    "sg:city":"Hightstown",
    "sg:classifiers":[
        {
            "category":"Professional",
            "subcategory":"Computer Services",
            "type":"Services"
        }
    ],
    "sg:phone":"+1   ",
    "sg:postcode":"08520",
    "sg:province":"NJ",
    "sg:tags":[
        "development",
        "software"
    ],
    "wof:name":"Gatim Inc",
    "wof:placetype":"venue"
},
  "geometry": {"coordinates":[-74.535104,40.252581],"type":"Point"}
}