{
  "type": "Feature",
  "properties": {
    "iso:country":"US",
    "sg:address":"180 Boulevard",
    "sg:city":"Hasbrouck Heights",
    "sg:classifiers":[
        {
            "category":"Autos & Motor Vehicles",
            "subcategory":"Fuel & Gas Station",
            "type":"Retail Goods"
        }
    ],
    "sg:phone":"+1 201 288 0538",
    "sg:postcode":"07604",
    "sg:province":"NJ",
    "wof:name":"Borough Exxon Service",
    "wof:placetype":"venue"
},
  "geometry": {"coordinates":[-74.079498,40.8605],"type":"Point"}
}