{
  "type": "Feature",
  "properties": {
    "iso:country":"US",
    "sg:address":"399 Baldwin Ave",
    "sg:city":"Jersey City",
    "sg:classifiers":[
        {
            "category":"Manufacturing",
            "subcategory":"Furniture",
            "type":"Manufacturing & Wholesale Goods"
        }
    ],
    "sg:phone":"+1 201 420 8855",
    "sg:postcode":"07306",
    "sg:province":"NJ",
    "sg:tags":[
        "upholstered",
        "household",
        "mfg"
    ],
    "wof:name":"Molina Furniture and Gift Shop",
    "wof:placetype":"venue"
},
  "geometry": {"coordinates":[-74.05365399999999,40.73437],"type":"Point"}
}