{
  "type": "Feature",
  "properties": {
    "iso:country":"US",
    "sg:address":"48 N Demarest Ave",
    "sg:city":"Bergenfield",
    "sg:classifiers":[
        {
            "category":"Building & Trades",
            "subcategory":"Construction",
            "type":"Services"
        }
    ],
    "sg:phone":"+1 201 501 0494",
    "sg:postcode":"07621",
    "sg:province":"NJ",
    "sg:tags":[
        "house"
    ],
    "wof:name":"Pandelis Home Improvements",
    "wof:placetype":"venue"
},
  "geometry": {"coordinates":[-74.000925,40.929763],"type":"Point"}
}