{
  "type": "Feature",
  "properties": {
    "addr:full":"93 Market St Saddle Brook NJ 07663",
    "addr:housenumber":"93",
    "addr:postcode":"07663",
    "addr:street":"Market St",
    "iso:country":"US",
    "sg:address":"93 Market St",
    "sg:city":"Saddle Brook",
    "sg:classifiers":[
        {
            "category":"Utilities",
            "subcategory":"Water",
            "type":"Services"
        }
    ],
    "sg:phone":"+1 201 587 2905",
    "sg:postcode":"07663",
    "sg:province":"NJ",
    "sg:tags":[
        "executive",
        "supply"
    ],
    "wof:name":"Saddle Brook Wtr Billing Dept",
    "wof:placetype":"venue"
},
  "geometry": {"coordinates":[-74.08243400000001,40.895487],"type":"Point"}
}