{
  "type": "Feature",
  "properties": {
    "iso:country":"US",
    "sg:address":"376 Fork Bridge Rd",
    "sg:city":"Elmer",
    "sg:classifiers":[
        {
            "category":"Professional",
            "subcategory":"Management & Consulting",
            "type":"Services"
        },
        {
            "category":"Education",
            "subcategory":"Special Training",
            "type":"Public Place"
        }
    ],
    "sg:phone":"+1 856 691 0907",
    "sg:postcode":"08318",
    "sg:province":"NJ",
    "sg:tags":[
        "consultant",
        "educational"
    ],
    "wof:name":"Castle Education Inc",
    "wof:placetype":"venue"
},
  "geometry": {"coordinates":[-75.08827100000001,39.566924],"type":"Point"}
}