{
  "type": "Feature",
  "properties": {
    "addr:full":"191 Orchard Ter Clark NJ 07066",
    "addr:housenumber":"191",
    "addr:postcode":"07066",
    "addr:street":"Orchard Ter",
    "iso:country":"US",
    "sg:address":"191 Orchard Ter",
    "sg:city":"Clark",
    "sg:classifiers":[
        {
            "category":"Autos & Motor Vehicles",
            "subcategory":"Automobile Sales",
            "type":"Retail Goods"
        }
    ],
    "sg:phone":"+1   ",
    "sg:postcode":"07066",
    "sg:province":"NJ",
    "sg:tags":[
        "used"
    ],
    "wof:name":"C&E Auto Sales Inc",
    "wof:placetype":"venue"
},
  "geometry": {"coordinates":[-74.33644700000001,40.608417],"type":"Point"}
}