{
  "type": "Feature",
  "properties": {
    "addr:full":"1231 US Hwy 9 Ocean View NJ 08230",
    "addr:housenumber":"1231",
    "addr:postcode":"08230",
    "addr:street":"Us Hwy 9",
    "iso:country":"US",
    "sg:address":"1231 US Hwy 9",
    "sg:city":"Ocean View",
    "sg:classifiers":[
        {
            "category":"Marine",
            "type":"Transportation"
        }
    ],
    "sg:phone":"+1 609 390 0050",
    "sg:postcode":"08230",
    "sg:province":"NJ",
    "sg:tags":[
        "cleaning",
        "boat"
    ],
    "wof:name":"Pro Marine Clean",
    "wof:placetype":"venue"
},
  "geometry": {"coordinates":[-74.678528,39.236525],"type":"Point"}
}