{
  "type": "Feature",
  "properties": {
    "addr:full":"1087 Broad St Shrewsbury NJ 07702",
    "addr:housenumber":"1087",
    "addr:postcode":"07702",
    "addr:street":"Broad St",
    "iso:country":"US",
    "sg:address":"1087 Broad St",
    "sg:city":"Shrewsbury",
    "sg:classifiers":[
        {
            "category":"Personal",
            "type":"Services"
        }
    ],
    "sg:phone":"+1 732 460 9607",
    "sg:postcode":"07702",
    "sg:province":"NJ",
    "sg:tags":[
        "program",
        "physical",
        "exercise",
        "fitness"
    ],
    "wof:name":"Bulls N Bears Fitness For Men",
    "wof:placetype":"venue"
},
  "geometry": {"coordinates":[-74.063519,40.314102],"type":"Point"}
}