{
  "type": "Feature",
  "properties": {
    "addr:full":"200 Lenape Trl Brielle NJ 08730",
    "addr:housenumber":"200",
    "addr:postcode":"08730",
    "addr:street":"Lenape Trl",
    "iso:country":"US",
    "sg:address":"200 Lenape Trl",
    "sg:city":"Brielle",
    "sg:classifiers":[
        {
            "category":"Professional",
            "subcategory":"Computer Services",
            "type":"Services"
        }
    ],
    "sg:phone":"+1   ",
    "sg:postcode":"08730",
    "sg:province":"NJ",
    "sg:tags":[
        "programing",
        "custom"
    ],
    "wof:name":"Hd Consulting Corp",
    "wof:placetype":"venue"
},
  "geometry": {"coordinates":[-74.062713,40.11886],"type":"Point"}
}