{
  "type": "Feature",
  "properties": {
    "iso:country":"US",
    "sg:address":"238 Broadway",
    "sg:city":"Elmwood Park",
    "sg:classifiers":[
        {
            "category":"Restaurant",
            "type":"Food & Drink"
        }
    ],
    "sg:phone":"+1   ",
    "sg:postcode":"07407",
    "sg:province":"NJ",
    "sg:tags":[
        "eating"
    ],
    "wof:name":"Escape Restaurant",
    "wof:placetype":"venue"
},
  "geometry": {"coordinates":[-74.119221,40.920661],"type":"Point"}
}