{
  "type": "Feature",
  "properties": {
    "addr:full":"48 Portland Ave Fanwood NJ 07023",
    "addr:housenumber":"48",
    "addr:postcode":"07023",
    "addr:street":"Portland Ave",
    "iso:country":"US",
    "sg:address":"48 Portland Ave",
    "sg:city":"Fanwood",
    "sg:classifiers":[
        {
            "category":"Building & Trades",
            "subcategory":"Construction",
            "type":"Services"
        }
    ],
    "sg:phone":"+1 908 322 5409",
    "sg:postcode":"07023",
    "sg:province":"NJ",
    "sg:tags":[
        "land",
        "grading",
        "contractor"
    ],
    "wof:name":"Sanguiliano Enterprises Inc",
    "wof:placetype":"venue"
},
  "geometry": {"coordinates":[-74.390013,40.650217],"type":"Point"}
}