{
  "type": "Feature",
  "properties": {
    "addr:full":"31 Oakhurst Ln Wharton NJ 07885",
    "addr:housenumber":"31",
    "addr:postcode":"07885",
    "addr:street":"Oakhurst Ln",
    "iso:country":"US",
    "sg:address":"31 Oakhurst Ln",
    "sg:city":"Wharton",
    "sg:classifiers":[
        {
            "category":"Professional",
            "type":"Services"
        }
    ],
    "sg:phone":"+1   ",
    "sg:postcode":"07885",
    "sg:province":"NJ",
    "wof:name":"All In Inc",
    "wof:placetype":"venue"
},
  "geometry": {"coordinates":[-74.579881,40.906128],"type":"Point"}
}