{
  "type": "Feature",
  "properties": {
    "iso:country":"US",
    "sg:address":"1124 Atlantic Ave",
    "sg:city":"Atlantic City",
    "sg:classifiers":[
        {
            "category":"Restaurant",
            "type":"Food & Drink"
        }
    ],
    "sg:phone":"+1   ",
    "sg:postcode":"08401",
    "sg:province":"NJ",
    "sg:tags":[
        "eating"
    ],
    "wof:name":"Com Tam Ninh Kieu",
    "wof:placetype":"venue"
},
  "geometry": {"coordinates":[-74.425425,39.363107],"type":"Point"}
}