{
  "type": "Feature",
  "properties": {
    "iso:country":"US",
    "sg:address":"9 S Main St",
    "sg:city":"Pleasantville",
    "sg:classifiers":[
        {
            "category":"Social Services",
            "type":"Services"
        }
    ],
    "sg:phone":"+1 609 272 8800",
    "sg:postcode":"08232",
    "sg:province":"NJ",
    "sg:tags":[
        "organization",
        "welfare"
    ],
    "wof:name":"Pleasantville Family Center",
    "wof:placetype":"venue"
},
  "geometry": {"coordinates":[-74.523127,39.391213],"type":"Point"}
}