{
  "type": "Feature",
  "properties": {
    "addr:full":"134 Heights Ter Middletown NJ 07748",
    "addr:housenumber":"134",
    "addr:postcode":"07748",
    "addr:street":"Heights Ter",
    "iso:country":"US",
    "sg:address":"134 Heights Ter",
    "sg:city":"Middletown",
    "sg:classifiers":[
        {
            "category":"Professional",
            "subcategory":"Management & Consulting",
            "type":"Services"
        }
    ],
    "sg:phone":"+1   ",
    "sg:postcode":"07748",
    "sg:province":"NJ",
    "wof:name":"Ciriano Management Consulting",
    "wof:placetype":"venue"
},
  "geometry": {"coordinates":[-74.108181,40.383729],"type":"Point"}
}