{
  "type": "Feature",
  "properties": {
    "addr:full":"80 Reservoir Ave Butler NJ 07405",
    "addr:housenumber":"80",
    "addr:postcode":"07405",
    "addr:street":"Reservoir Ave",
    "iso:country":"US",
    "sg:address":"80 Reservoir Ave",
    "sg:city":"Butler",
    "sg:classifiers":[
        {
            "category":"Banks & Credit Unions",
            "subcategory":"Investment Brokerage",
            "type":"Services"
        }
    ],
    "sg:phone":"+1   ",
    "sg:postcode":"07405",
    "sg:province":"NJ",
    "sg:tags":[
        "advisory"
    ],
    "wof:name":"Rinaldi Financial Services LLC",
    "wof:placetype":"venue"
},
  "geometry": {"coordinates":[-74.357201,40.995202],"type":"Point"}
}