{
  "type": "Feature",
  "properties": {
    "iso:country":"US",
    "sg:address":"27 State Rte 34",
    "sg:city":"Colts Neck",
    "sg:classifiers":[
        {
            "category":"Shopping",
            "subcategory":"Clothing, Apparel, & Fashions",
            "type":"Retail Goods"
        }
    ],
    "sg:phone":"+1 732 866 4006",
    "sg:postcode":"07722",
    "sg:province":"NJ",
    "sg:tags":[
        "item",
        "boutique"
    ],
    "wof:name":"Blame On Rio Boutique",
    "wof:placetype":"venue"
},
  "geometry": {"coordinates":[-74.17441100000001,40.294087],"type":"Point"}
}