{
  "type": "Feature",
  "properties": {
    "addr:full":"1370 Delsea Dr Deptford NJ 08096",
    "addr:housenumber":"1370",
    "addr:postcode":"08096",
    "addr:street":"Delsea Dr",
    "iso:country":"US",
    "sg:address":"1370 Delsea Dr",
    "sg:city":"Deptford",
    "sg:classifiers":[
        {
            "category":"Government",
            "subcategory":"Fire Station",
            "type":"Public Place"
        }
    ],
    "sg:phone":"+1 856 848 3098",
    "sg:postcode":"08096",
    "sg:province":"NJ",
    "sg:tags":[
        "department"
    ],
    "sg:website":"www.deptfordfd.org",
    "wof:name":"Fire Dept",
    "wof:placetype":"venue"
},
  "geometry": {"coordinates":[-75.124878,39.83099],"type":"Point"}
}