{
  "type": "Feature",
  "properties": {
    "addr:full":"1614 Winans Ave Linden NJ 07036",
    "addr:housenumber":"1614",
    "addr:postcode":"07036",
    "addr:street":"Winans Ave",
    "iso:country":"US",
    "sg:address":"1614 Winans Ave",
    "sg:city":"Linden",
    "sg:classifiers":[
        {
            "category":"Personal",
            "type":"Services"
        }
    ],
    "sg:phone":"+1   ",
    "sg:postcode":"07036",
    "sg:province":"NJ",
    "sg:tags":[
        "business"
    ],
    "wof:name":"Joamar Packaging Inc",
    "wof:placetype":"venue"
},
  "geometry": {"coordinates":[-74.239301,40.6213],"type":"Point"}
}