{
  "type": "Feature",
  "properties": {
    "iso:country":"US",
    "sg:address":"160 Sooy Place Rd",
    "sg:city":"Vincentown",
    "sg:classifiers":[
        {
            "category":"Professional",
            "type":"Services"
        }
    ],
    "sg:phone":"+1   ",
    "sg:postcode":"08088",
    "sg:province":"NJ",
    "wof:name":"Net Services",
    "wof:placetype":"venue"
},
  "geometry": {"coordinates":[-74.660527,39.872774],"type":"Point"}
}