{
  "type": "Feature",
  "properties": {
    "iso:country":"US",
    "sg:address":"1072 S Broad St",
    "sg:city":"Trenton",
    "sg:classifiers":[
        {
            "category":"Building & Trades",
            "subcategory":"Construction",
            "type":"Services"
        }
    ],
    "sg:phone":"+1 609 396 5082",
    "sg:postcode":"08611",
    "sg:province":"NJ",
    "sg:tags":[
        "general",
        "contractor"
    ],
    "wof:name":"Burg Home Improvements",
    "wof:placetype":"venue"
},
  "geometry": {"coordinates":[-74.743638,40.204418],"type":"Point"}
}