{
  "type": "Feature",
  "properties": {
    "addr:full":"1300 Tonnelle Ave North Bergen NJ 07047",
    "addr:housenumber":"1300",
    "addr:postcode":"07047",
    "addr:street":"Tonnelle Ave",
    "iso:country":"US",
    "sg:address":"1300 Tonnelle Ave",
    "sg:city":"North Bergen",
    "sg:classifiers":[
        {
            "category":"Travel",
            "subcategory":"Hotels & Motels",
            "type":"Entertainment"
        }
    ],
    "sg:phone":"+1 201 863 6363",
    "sg:postcode":"07047",
    "sg:province":"NJ",
    "sg:website":"www.howardjohnson.com",
    "wof:name":"Howard Johnson's",
    "wof:placetype":"venue"
},
  "geometry": {"coordinates":[-74.04761000000001,40.764754],"type":"Point"}
}