{
  "type": "Feature",
  "properties": {
    "addr:full":"37 Roberts Dr Mount Holly NJ 08060",
    "addr:housenumber":"37",
    "addr:postcode":"08060",
    "addr:street":"Roberts Dr",
    "iso:country":"US",
    "sg:address":"37 Roberts Dr",
    "sg:city":"Mount Holly",
    "sg:classifiers":[
        {
            "category":"Professional",
            "subcategory":"Computer Services",
            "type":"Services"
        }
    ],
    "sg:phone":"+1 609 351 8200",
    "sg:postcode":"08060",
    "sg:province":"NJ",
    "sg:tags":[
        "consulting"
    ],
    "wof:name":"Denarius Enterprises Inc",
    "wof:placetype":"venue"
},
  "geometry": {"coordinates":[-74.80820799999999,40.028971],"type":"Point"}
}