{
  "type": "Feature",
  "properties": {
    "addr:full":"65 Burnett Ter Maplewood NJ 07040",
    "addr:housenumber":"65",
    "addr:postcode":"07040",
    "addr:street":"Burnett Ter",
    "iso:country":"US",
    "sg:address":"65 Burnett Ter",
    "sg:city":"Maplewood",
    "sg:classifiers":[
        {
            "category":"Professional",
            "subcategory":"Management & Consulting",
            "type":"Services"
        }
    ],
    "sg:phone":"+1 973 762 2166",
    "sg:postcode":"07040",
    "sg:province":"NJ",
    "wof:name":"Vratitsa Fincl Consulting LLC",
    "wof:placetype":"venue"
},
  "geometry": {"coordinates":[-74.261774,40.727064],"type":"Point"}
}