{
  "type": "Feature",
  "properties": {
    "iso:country":"US",
    "sg:address":"6 E Cape May Ave",
    "sg:city":"Harvey Cedars",
    "sg:classifiers":[
        {
            "category":"Organizations",
            "subcategory":"Community Association",
            "type":"Services"
        }
    ],
    "sg:phone":"+1 609 494 8780",
    "sg:postcode":"08008",
    "sg:province":"NJ",
    "sg:tags":[
        "club"
    ],
    "wof:name":"Long Beach Island Fishing Club",
    "wof:placetype":"venue"
},
  "geometry": {"coordinates":[-74.144066,39.690103],"type":"Point"}
}