{
  "type": "Feature",
  "properties": {
    "iso:country":"US",
    "sg:address":"4 McCready's Aly",
    "sg:city":"Lambertville",
    "sg:classifiers":[
        {
            "category":"Personal",
            "subcategory":"Shoe Repair & Shine",
            "type":"Services"
        }
    ],
    "sg:phone":"+1   ",
    "sg:postcode":"08530",
    "sg:province":"NJ",
    "sg:tags":[
        "parlor"
    ],
    "wof:name":"Aircraft Shoe & Leather Repair",
    "wof:placetype":"venue"
},
  "geometry": {"coordinates":[-74.94228200000001,40.366212],"type":"Point"}
}