{
  "type": "Feature",
  "properties": {
    "addr:full":"82 Union St Montclair NJ 07042",
    "addr:housenumber":"82",
    "addr:postcode":"07042",
    "addr:street":"Union St",
    "iso:country":"US",
    "sg:address":"82 Union St",
    "sg:city":"Montclair",
    "sg:classifiers":[
        {
            "category":"Organizations",
            "subcategory":"Community Association",
            "type":"Services"
        }
    ],
    "sg:phone":"+1 973 744 9552",
    "sg:postcode":"07042",
    "sg:province":"NJ",
    "sg:tags":[
        "club",
        "woman"
    ],
    "wof:name":"Montclair Women's Club",
    "wof:placetype":"venue"
},
  "geometry": {"coordinates":[-74.22026200000001,40.810611],"type":"Point"}
}