{
  "type": "Feature",
  "properties": {
    "iso:country":"US",
    "sg:address":"39 Henry Ter",
    "sg:city":"Lincoln Park",
    "sg:classifiers":[
        {
            "category":"Shopping",
            "subcategory":"Clothing, Apparel, & Fashions",
            "type":"Retail Goods"
        }
    ],
    "sg:phone":"+1   ",
    "sg:postcode":"07035",
    "sg:province":"NJ",
    "wof:name":"Danuta Kleczek Inc",
    "wof:placetype":"venue"
},
  "geometry": {"coordinates":[-74.286328,40.915996],"type":"Point"}
}