{
  "type": "Feature",
  "properties": {
    "iso:country":"US",
    "sg:address":"1620 US Hwy 22",
    "sg:city":"Union",
    "sg:classifiers":[
        {
            "category":"Professional",
            "subcategory":"Employment Agencies",
            "type":"Services"
        }
    ],
    "sg:phone":"+1 908 624 1155",
    "sg:postcode":"07083",
    "sg:province":"NJ",
    "sg:tags":[
        "medical"
    ],
    "wof:name":"ATC Healthcare Svc",
    "wof:placetype":"venue"
},
  "geometry": {"coordinates":[-74.271113,40.691879],"type":"Point"}
}