{
  "type": "Feature",
  "properties": {
    "addr:full":"500 Hoes Ln Piscataway NJ 08854",
    "addr:housenumber":"500",
    "addr:postcode":"08854",
    "addr:street":"Hoes Ln",
    "iso:country":"US",
    "sg:address":"500 Hoes Ln",
    "sg:city":"Piscataway",
    "sg:classifiers":[
        {
            "category":"Education",
            "subcategory":"Library",
            "type":"Public Place"
        }
    ],
    "sg:phone":"+1   ",
    "sg:postcode":"08854",
    "sg:province":"NJ",
    "sg:tags":[
        "executive"
    ],
    "wof:name":"John F Kennedy Memorial Lib",
    "wof:placetype":"venue"
},
  "geometry": {"coordinates":[-74.469089,40.53292],"type":"Point"}
}