{
  "type": "Feature",
  "properties": {
    "addr:full":"178 Piermont Rd Cresskill NJ 07626",
    "addr:housenumber":"178",
    "addr:postcode":"07626",
    "addr:street":"Piermont Rd",
    "iso:country":"US",
    "sg:address":"178 Piermont Rd",
    "sg:city":"Cresskill",
    "sg:classifiers":[
        {
            "category":"Restaurant",
            "type":"Food & Drink"
        }
    ],
    "sg:menulink":"http://www.allmenus.com/nj/cresskill/23714-samdan/menu/",
    "sg:phone":"+1 201 816 7343",
    "sg:postcode":"07626",
    "sg:province":"NJ",
    "sg:tags":[
        "middle",
        "eastern"
    ],
    "wof:name":"Samdan",
    "wof:placetype":"venue"
},
  "geometry": {"coordinates":[-73.96236399999999,40.943367],"type":"Point"}
}