{
  "type": "Feature",
  "properties": {
    "iso:country":"US",
    "sg:address":"134 Sussex St",
    "sg:city":"Harrison",
    "sg:classifiers":[
        {
            "category":"Building & Trades",
            "subcategory":"Electrical",
            "type":"Services"
        }
    ],
    "sg:phone":"+1 973 481 3358",
    "sg:postcode":"07029",
    "sg:province":"NJ",
    "sg:tags":[
        "electrical",
        "contractor"
    ],
    "wof:name":"Compliance Electric Co",
    "wof:placetype":"venue"
},
  "geometry": {"coordinates":[-74.160676,40.743788],"type":"Point"}
}