{
  "type": "Feature",
  "properties": {
    "iso:country":"US",
    "sg:address":"421 Wall St",
    "sg:city":"Princeton",
    "sg:classifiers":[
        {
            "category":"Coffee & Tea",
            "type":"Food & Drink"
        },
        {
            "category":"Restaurant",
            "type":"Food & Drink"
        }
    ],
    "sg:phone":"+1 609 683 1660",
    "sg:postcode":"08540",
    "sg:province":"NJ",
    "sg:tags":[
        "espresso"
    ],
    "wof:name":"Carver's Cafe",
    "wof:placetype":"venue"
},
  "geometry": {"coordinates":[-74.650301,40.399521],"type":"Point"}
}