{
  "type": "Feature",
  "properties": {
    "iso:country":"US",
    "sg:address":"15 Hollister Rd",
    "sg:city":"Lincoln Park",
    "sg:classifiers":[
        {
            "category":"Retail",
            "subcategory":"Repair Shop",
            "type":"Services"
        }
    ],
    "sg:phone":"+1 973 403 1558",
    "sg:postcode":"07035",
    "sg:province":"NJ",
    "sg:tags":[
        "repairing",
        "piano",
        "refinishing"
    ],
    "wof:name":"Damien Del Russo",
    "wof:placetype":"venue"
},
  "geometry": {"coordinates":[-74.321445,40.924689],"type":"Point"}
}