{
  "type": "Feature",
  "properties": {
    "iso:country":"US",
    "sg:address":"11 Evergreen Ave",
    "sg:city":"Neptune City",
    "sg:classifiers":[
        {
            "category":"Building & Trades",
            "subcategory":"Construction",
            "type":"Services"
        }
    ],
    "sg:phone":"+1 732 502 0808",
    "sg:postcode":"07753",
    "sg:province":"NJ",
    "sg:tags":[
        "specializing",
        "housing",
        "contractor",
        "general",
        "government"
    ],
    "wof:name":"Omega Service Maintenance Corp",
    "wof:placetype":"venue"
},
  "geometry": {"coordinates":[-74.021187,40.199297],"type":"Point"}
}