{
  "type": "Feature",
  "properties": {
    "iso:country":"US",
    "sg:address":"124 Halsey St",
    "sg:city":"Newark",
    "sg:classifiers":[
        {
            "category":"Government",
            "subcategory":"Court House",
            "type":"Public Place"
        }
    ],
    "sg:phone":"+1   ",
    "sg:postcode":"07102",
    "sg:province":"NJ",
    "sg:tags":[
        "independent",
        "agency"
    ],
    "wof:name":"Audiology & Speech Pathology",
    "wof:placetype":"venue"
},
  "geometry": {"coordinates":[-74.172539,40.738052],"type":"Point"}
}