{
  "type": "Feature",
  "properties": {
    "addr:full":"2000 New Jersey Ave North Wildwood NJ 08260",
    "addr:housenumber":"2000",
    "addr:postcode":"08260",
    "addr:street":"New Jersey Ave North",
    "iso:country":"US",
    "sg:address":"2000 New Jersey Ave",
    "sg:city":"North Wildwood",
    "sg:classifiers":[
        {
            "category":"Building & Trades",
            "subcategory":"Construction",
            "type":"Services"
        }
    ],
    "sg:phone":"+1 609 522 3035",
    "sg:postcode":"08260",
    "sg:province":"NJ",
    "sg:tags":[
        "contractor"
    ],
    "sg:website":"www.premiercustomhomesnj.com",
    "wof:name":"Premier Contractors",
    "wof:placetype":"venue"
},
  "geometry": {"coordinates":[-74.807551,38.996517],"type":"Point"}
}