{
  "type": "Feature",
  "properties": {
    "iso:country":"US",
    "sg:address":"19 Wildflower Trl",
    "sg:city":"Trenton",
    "sg:classifiers":[
        {
            "category":"Education",
            "subcategory":"Vocational School",
            "type":"Public Place"
        }
    ],
    "sg:phone":"+1   ",
    "sg:postcode":"08691",
    "sg:province":"NJ",
    "wof:name":"Blanchard Training and Dev",
    "wof:placetype":"venue"
},
  "geometry": {"coordinates":[-74.599192,40.233059],"type":"Point"}
}