{
  "type": "Feature",
  "properties": {
    "addr:full":"715 Newark Pompton Tpke Pompton Plains NJ 07444",
    "addr:housenumber":"715",
    "addr:postcode":"07444",
    "addr:street":"Newark Pompton Tpke",
    "iso:country":"US",
    "sg:address":"715 Newark Pompton Tpke",
    "sg:city":"Pompton Plains",
    "sg:classifiers":[
        {
            "category":"Health Services",
            "subcategory":"Health Practitioner",
            "type":"Services"
        }
    ],
    "sg:phone":"+1 973 835 6115",
    "sg:postcode":"07444",
    "sg:province":"NJ",
    "sg:tags":[
        "therapist",
        "physical"
    ],
    "wof:name":"Physical Therapy Svc",
    "wof:placetype":"venue"
},
  "geometry": {"coordinates":[-74.296875,40.972803],"type":"Point"}
}