{
  "type": "Feature",
  "properties": {
    "addr:full":"58 Green St Newark NJ 07102",
    "addr:housenumber":"58",
    "addr:postcode":"07102",
    "addr:street":"Green St",
    "iso:country":"US",
    "sg:address":"58 Green St",
    "sg:city":"Newark",
    "sg:classifiers":[
        {
            "category":"Restaurant",
            "type":"Food & Drink"
        }
    ],
    "sg:phone":"+1 973 242 2020",
    "sg:postcode":"07102",
    "sg:province":"NJ",
    "wof:name":"Golden City Chinese Resta",
    "wof:placetype":"venue"
},
  "geometry": {"coordinates":[-74.17121,40.731504],"type":"Point"}
}