{
  "type": "Feature",
  "properties": {
    "addr:full":"67 Howard St Vineland NJ 08360",
    "addr:housenumber":"67",
    "addr:postcode":"08360",
    "addr:street":"Howard St",
    "iso:country":"US",
    "sg:address":"67 Howard St",
    "sg:city":"Vineland",
    "sg:classifiers":[
        {
            "category":"Manufacturing",
            "subcategory":"Metals",
            "type":"Manufacturing & Wholesale Goods"
        }
    ],
    "sg:phone":"+1 856 696 1565",
    "sg:postcode":"08360",
    "sg:province":"NJ",
    "sg:tags":[
        "fabricator",
        "sheet"
    ],
    "wof:name":"Molter Construction Co",
    "wof:placetype":"venue"
},
  "geometry": {"coordinates":[-75.011337,39.481157],"type":"Point"}
}