{
  "type": "Feature",
  "properties": {
    "addr:full":"519 Lake St Newark NJ 07104",
    "addr:housenumber":"519",
    "addr:postcode":"07104",
    "addr:street":"Lake St",
    "iso:country":"US",
    "sg:address":"519 Lake St",
    "sg:city":"Newark",
    "sg:classifiers":[
        {
            "category":"Building & Trades",
            "subcategory":"Construction",
            "type":"Services"
        }
    ],
    "sg:phone":"+1 973 482 0110",
    "sg:postcode":"07104",
    "sg:province":"NJ",
    "sg:tags":[
        "restoration",
        "cleaning",
        "patio",
        "deck"
    ],
    "wof:name":"Fred's Steam & Pressure Clean",
    "wof:placetype":"venue"
},
  "geometry": {"coordinates":[-74.17441599999999,40.769058],"type":"Point"}
}