{
  "type": "Feature",
  "properties": {
    "iso:country":"US",
    "sg:address":"709 Sycamore Ave",
    "sg:city":"Red Bank",
    "sg:classifiers":[
        {
            "category":"Health Services",
            "subcategory":"Doctor",
            "type":"Services"
        }
    ],
    "sg:phone":"+1   ",
    "sg:postcode":"07701",
    "sg:province":"NJ",
    "wof:name":"Mitchel L Friedman DDS",
    "wof:placetype":"venue"
},
  "geometry": {"coordinates":[-74.075714,40.322672],"type":"Point"}
}