{
  "type": "Feature",
  "properties": {
    "iso:country":"US",
    "sg:address":"154 S Orange Ave",
    "sg:city":"South Orange",
    "sg:classifiers":[
        {
            "category":"Shopping",
            "type":"Retail Goods"
        }
    ],
    "sg:phone":"+1   ",
    "sg:postcode":"07079",
    "sg:province":"NJ",
    "sg:tags":[
        "pet",
        "store",
        "supply"
    ],
    "wof:name":"NJ Pets",
    "wof:placetype":"venue"
},
  "geometry": {"coordinates":[-74.25384200000001,40.745057],"type":"Point"}
}