{
  "type": "Feature",
  "properties": {
    "iso:country":"US",
    "sg:address":"117 Cooper Ave",
    "sg:city":"Iselin",
    "sg:classifiers":[
        {
            "category":"Building & Trades",
            "subcategory":"Construction",
            "type":"Services"
        }
    ],
    "sg:phone":"+1 732 283 0873",
    "sg:postcode":"08830",
    "sg:province":"NJ",
    "sg:tags":[
        "home",
        "all",
        "improvement"
    ],
    "wof:name":"Aces High Contracting",
    "wof:placetype":"venue"
},
  "geometry": {"coordinates":[-74.32017,40.570379],"type":"Point"}
}