{
  "type": "Feature",
  "properties": {
    "addr:full":"156 Maple Ave Oaklyn NJ 08107",
    "addr:housenumber":"156",
    "addr:postcode":"08107",
    "addr:street":"Maple Ave",
    "iso:country":"US",
    "sg:address":"156 Maple Ave",
    "sg:city":"Oaklyn",
    "sg:classifiers":[
        {
            "category":"Food & Beverages",
            "subcategory":"Groceries & Convenience Stores",
            "type":"Retail Goods"
        }
    ],
    "sg:phone":"+1   ",
    "sg:postcode":"08107",
    "sg:province":"NJ",
    "wof:name":"Diem Market",
    "wof:placetype":"venue"
},
  "geometry": {"coordinates":[-75.100008,39.917419],"type":"Point"}
}