{
  "type": "Feature",
  "properties": {
    "iso:country":"US",
    "sg:address":"765 State Rte 70",
    "sg:city":"Marlton",
    "sg:classifiers":[
        {
            "category":"Health Services",
            "subcategory":"Hospital",
            "type":"Services"
        }
    ],
    "sg:phone":"+1 856 983 3900",
    "sg:postcode":"08053",
    "sg:province":"NJ",
    "sg:tags":[
        "mental"
    ],
    "sg:website":"www.ctrfamilyguidance.com",
    "wof:name":"Center For Family Guidance",
    "wof:placetype":"venue"
},
  "geometry": {"coordinates":[-74.884413,39.894127],"type":"Point"}
}