{
  "type": "Feature",
  "properties": {
    "addr:full":"331 Bailey Ave Maple Shade NJ 08052",
    "addr:housenumber":"331",
    "addr:postcode":"08052",
    "addr:street":"Bailey Ave",
    "iso:country":"US",
    "sg:address":"331 Bailey Ave",
    "sg:city":"Maple Shade",
    "sg:classifiers":[
        {
            "category":"Building & Trades",
            "subcategory":"Construction",
            "type":"Services"
        }
    ],
    "sg:phone":"+1 856 482 1156",
    "sg:postcode":"08052",
    "sg:province":"NJ",
    "sg:tags":[
        "carpentry",
        "contractor"
    ],
    "wof:name":"Kek Carpentry",
    "wof:placetype":"venue"
},
  "geometry": {"coordinates":[-74.98869999999999,39.951956],"type":"Point"}
}