{
  "type": "Feature",
  "properties": {
    "addr:full":"619 Campgaw Rd Mahwah NJ 07430",
    "addr:housenumber":"619",
    "addr:postcode":"07430",
    "addr:street":"Campgaw Rd",
    "iso:country":"US",
    "sg:address":"619 Campgaw Rd",
    "sg:city":"Mahwah",
    "sg:classifiers":[
        {
            "category":"Farming",
            "subcategory":"Farm & Veterinary Services",
            "type":"Manufacturing & Wholesale Goods"
        }
    ],
    "sg:phone":"+1 201 825 3288",
    "sg:postcode":"07430",
    "sg:province":"NJ",
    "sg:tags":[
        "preparation",
        "soil"
    ],
    "wof:name":"ADM",
    "wof:placetype":"venue"
},
  "geometry": {"coordinates":[-74.185498,41.038826],"type":"Point"}
}