{
  "type": "Feature",
  "properties": {
    "iso:country":"US",
    "sg:address":"233 Main St",
    "sg:city":"Lebanon",
    "sg:classifiers":[
        {
            "category":"Restaurant",
            "type":"Food & Drink"
        }
    ],
    "sg:menulink":"http://www.allmenus.com/nj/lebanon/14284-mimmas-pizza/menu/",
    "sg:phone":"+1 908 236 0006",
    "sg:postcode":"08833",
    "sg:province":"NJ",
    "sg:tags":[
        "american",
        "pizza"
    ],
    "wof:name":"Mimma's Pizza",
    "wof:placetype":"venue"
},
  "geometry": {"coordinates":[-74.824496,40.642277],"type":"Point"}
}