{
  "type": "Feature",
  "properties": {
    "addr:full":"317 Belleville Ave Bloomfield NJ 07003",
    "addr:housenumber":"317",
    "addr:postcode":"07003",
    "addr:street":"Belleville Ave",
    "iso:country":"US",
    "sg:address":"317 Belleville Ave",
    "sg:city":"Bloomfield",
    "sg:classifiers":[
        {
            "category":"Professional",
            "subcategory":"Lawyer & Legal Services",
            "type":"Services"
        }
    ],
    "sg:phone":"+1 973 748 7535",
    "sg:postcode":"07003",
    "sg:province":"NJ",
    "sg:tags":[
        "attorney"
    ],
    "wof:name":"Moscowitz & Novin LLP",
    "wof:placetype":"venue"
},
  "geometry": {"coordinates":[-74.194682,40.799798],"type":"Point"}
}