{
  "type": "Feature",
  "properties": {
    "addr:full":"1356 Sherwood Dr Vineland NJ 08361",
    "addr:housenumber":"1356",
    "addr:postcode":"08361",
    "addr:street":"Sherwood Dr",
    "iso:country":"US",
    "sg:address":"1356 Sherwood Dr",
    "sg:city":"Vineland",
    "sg:classifiers":[
        {
            "category":"Building & Trades",
            "subcategory":"Cleaning & Sanitation",
            "type":"Services"
        }
    ],
    "sg:phone":"+1   ",
    "sg:postcode":"08361",
    "sg:province":"NJ",
    "sg:tags":[
        "maintenance"
    ],
    "wof:name":"Calio Janitorial Service",
    "wof:placetype":"venue"
},
  "geometry": {"coordinates":[-74.987469,39.464422],"type":"Point"}
}