{
  "type": "Feature",
  "properties": {
    "iso:country":"US",
    "sg:address":"53 Whippany Rd",
    "sg:city":"Whippany",
    "sg:classifiers":[
        {
            "category":"Health Services",
            "subcategory":"Doctor",
            "type":"Services"
        }
    ],
    "sg:phone":"+1 973 887 7776",
    "sg:postcode":"07981",
    "sg:province":"NJ",
    "sg:tags":[
        "physician"
    ],
    "wof:name":"Whippany Family Practice",
    "wof:placetype":"venue"
},
  "geometry": {"coordinates":[-74.414103,40.820454],"type":"Point"}
}