{
  "type": "Feature",
  "properties": {
    "addr:full":"24 Rue Chagall Somerset NJ 08873",
    "addr:housenumber":"24",
    "addr:postcode":"08873",
    "addr:street":"Rue Chagall",
    "iso:country":"US",
    "sg:address":"24 Rue Chagall",
    "sg:city":"Somerset",
    "sg:classifiers":[
        {
            "category":"Professional",
            "subcategory":"Computer Services",
            "type":"Services"
        }
    ],
    "sg:phone":"+1 732 846 0778",
    "sg:postcode":"08873",
    "sg:province":"NJ",
    "sg:tags":[
        "telephone",
        "information",
        "retrieval",
        "communications"
    ],
    "wof:name":"Best Racing Systems",
    "wof:placetype":"venue"
},
  "geometry": {"coordinates":[-74.50581200000001,40.516615],"type":"Point"}
}