{
  "type": "Feature",
  "properties": {
    "addr:full":"604 Wheatfield Ct Flemington NJ 08822",
    "addr:housenumber":"604",
    "addr:postcode":"08822",
    "addr:street":"Wheatfield Ct",
    "iso:country":"US",
    "sg:address":"604 Wheatfield Ct",
    "sg:city":"Flemington",
    "sg:classifiers":[
        {
            "category":"Social Services",
            "type":"Services"
        }
    ],
    "sg:phone":"+1 908 237 2608",
    "sg:postcode":"08822",
    "sg:province":"NJ",
    "sg:tags":[
        "youth",
        "organization",
        "center"
    ],
    "wof:name":"American Heart Assoc Youth Mkt",
    "wof:placetype":"venue"
},
  "geometry": {"coordinates":[-74.846564,40.495592],"type":"Point"}
}