{
  "type": "Feature",
  "properties": {
    "iso:country":"US",
    "sg:address":"310 Passaic Ave",
    "sg:city":"East Newark",
    "sg:classifiers":[
        {
            "category":"Wholesale",
            "subcategory":"Durable Goods & Equipment",
            "type":"Manufacturing & Wholesale Goods"
        }
    ],
    "sg:phone":"+1 973 482 0904",
    "sg:postcode":"07029",
    "sg:province":"NJ",
    "sg:tags":[
        "importer"
    ],
    "sg:website":"www.dynamiccapitalfunding.com",
    "wof:name":"Dynamic Imports & Exports Inc",
    "wof:placetype":"venue"
},
  "geometry": {"coordinates":[-74.164626,40.747803],"type":"Point"}
}