{
  "type": "Feature",
  "properties": {
    "iso:country":"US",
    "sg:address":"37 Park Ave",
    "sg:city":"Park Ridge",
    "sg:classifiers":[
        {
            "category":"Shopping",
            "subcategory":"Computers & Home Electronics",
            "type":"Retail Goods"
        }
    ],
    "sg:phone":"+1   ",
    "sg:postcode":"07656",
    "sg:province":"NJ",
    "sg:tags":[
        "sales",
        "maintenance"
    ],
    "wof:name":"Ex-Cel Solutions Inc",
    "wof:placetype":"venue"
},
  "geometry": {"coordinates":[-74.038774,41.033597],"type":"Point"}
}