{
  "type": "Feature",
  "properties": {
    "addr:full":"54 Ave L Newark NJ 07105",
    "addr:postcode":"07105",
    "addr:street":"54 Ave",
    "iso:country":"US",
    "sg:address":"54 Ave L",
    "sg:city":"Newark",
    "sg:classifiers":[
        {
            "category":"Autos & Motor Vehicles",
            "subcategory":"Automobile Sales",
            "type":"Retail Goods"
        }
    ],
    "sg:phone":"+1   ",
    "sg:postcode":"07105",
    "sg:province":"NJ",
    "sg:tags":[
        "used"
    ],
    "wof:name":"Bay Shore Auto Sales",
    "wof:placetype":"venue"
},
  "geometry": {"coordinates":[-74.14466899999999,40.719554],"type":"Point"}
}