{
  "type": "Feature",
  "properties": {
    "iso:country":"US",
    "sg:address":"97 Mount Horeb Rd",
    "sg:city":"Warren",
    "sg:classifiers":[
        {
            "category":"Professional",
            "subcategory":"Art Services",
            "type":"Services"
        }
    ],
    "sg:phone":"+1   ",
    "sg:postcode":"07059",
    "sg:province":"NJ",
    "sg:tags":[
        "commercial",
        "design"
    ],
    "wof:name":"Big Fish Mural Co LLC",
    "wof:placetype":"venue"
},
  "geometry": {"coordinates":[-74.53066200000001,40.622088],"type":"Point"}
}