{
  "type": "Feature",
  "properties": {
    "addr:full":"190 Oak St Teaneck NJ 07666",
    "addr:housenumber":"190",
    "addr:postcode":"07666",
    "addr:street":"Oak St",
    "iso:country":"US",
    "sg:address":"190 Oak St",
    "sg:city":"Teaneck",
    "sg:classifiers":[
        {
            "category":"Personal",
            "type":"Services"
        }
    ],
    "sg:phone":"+1   ",
    "sg:postcode":"07666",
    "sg:province":"NJ",
    "wof:name":"F X Lofgren",
    "wof:placetype":"venue"
},
  "geometry": {"coordinates":[-74.02078899999999,40.868891],"type":"Point"}
}