{
  "type": "Feature",
  "properties": {
    "iso:country":"US",
    "sg:address":"303 College Rd E",
    "sg:city":"Princeton",
    "sg:classifiers":[
        {
            "category":"Professional",
            "subcategory":"Business Services",
            "type":"Services"
        }
    ],
    "sg:phone":"+1   ",
    "sg:postcode":"08540",
    "sg:province":"NJ",
    "wof:name":"Orchid Biosciences Inc",
    "wof:placetype":"venue"
},
  "geometry": {"coordinates":[-74.59692200000001,40.355787],"type":"Point"}
}