{
  "type": "Feature",
  "properties": {
    "addr:full":"1514 River Rd Edgewater NJ 07020",
    "addr:housenumber":"1514",
    "addr:postcode":"07020",
    "addr:street":"River Rd",
    "iso:country":"US",
    "sg:address":"1514 River Rd",
    "sg:city":"Edgewater",
    "sg:classifiers":[
        {
            "category":"Building & Trades",
            "subcategory":"Construction",
            "type":"Services"
        }
    ],
    "sg:phone":"+1 201 886 2197",
    "sg:postcode":"07020",
    "sg:province":"NJ",
    "sg:tags":[
        "house"
    ],
    "wof:name":"Young Kwang Construction Inc",
    "wof:placetype":"venue"
},
  "geometry": {"coordinates":[-73.966677,40.84601],"type":"Point"}
}