{
  "type": "Feature",
  "properties": {
    "iso:country":"US",
    "sg:address":"1715 New Bedford Rd",
    "sg:city":"Wall Township",
    "sg:classifiers":[
        {
            "category":"Building & Trades",
            "subcategory":"Electrical",
            "type":"Services"
        }
    ],
    "sg:phone":"+1 732 280 3201",
    "sg:postcode":"07719",
    "sg:province":"NJ",
    "sg:tags":[
        "electric",
        "contractor"
    ],
    "wof:name":"Sodon's Electric",
    "wof:placetype":"venue"
},
  "geometry": {"coordinates":[-74.063581,40.173159],"type":"Point"}
}