{
  "type": "Feature",
  "properties": {
    "addr:full":"3500 Boardwalk Wildwood NJ 08260",
    "addr:housenumber":"3500",
    "addr:postcode":"08260",
    "addr:street":"Boardwalk",
    "iso:country":"US",
    "sg:address":"3500 Boardwalk",
    "sg:city":"Wildwood",
    "sg:classifiers":[
        {
            "category":"Restaurant",
            "type":"Food & Drink"
        }
    ],
    "sg:phone":"+1 609 523 8584",
    "sg:postcode":"08260",
    "sg:province":"NJ",
    "wof:name":"Burger King",
    "wof:placetype":"venue"
},
  "geometry": {"coordinates":[-74.81059399999999,38.987005],"type":"Point"}
}