{
  "type": "Feature",
  "properties": {
    "iso:country":"US",
    "sg:address":"401 State Rte 73",
    "sg:city":"Marlton",
    "sg:classifiers":[
        {
            "category":"Autos & Motor Vehicles",
            "subcategory":"Automobile Sales",
            "type":"Retail Goods"
        }
    ],
    "sg:phone":"+1 856 983 9200",
    "sg:postcode":"08053",
    "sg:province":"NJ",
    "sg:tags":[
        "car",
        "dealer"
    ],
    "wof:name":"Elkins Chevrolet LLC",
    "wof:placetype":"venue"
},
  "geometry": {"coordinates":[-74.931038,39.897836],"type":"Point"}
}