{
  "type": "Feature",
  "properties": {
    "addr:full":"311 State Rte 17 Paramus NJ 07652",
    "addr:housenumber":"311",
    "addr:postcode":"07652",
    "addr:street":"State Rte 17",
    "iso:country":"US",
    "sg:address":"311 State Rte 17",
    "sg:city":"Paramus",
    "sg:classifiers":[
        {
            "category":"Utilities",
            "subcategory":"Mobile Phone",
            "type":"Services"
        }
    ],
    "sg:phone":"+1 201 599 3091",
    "sg:postcode":"07652",
    "sg:province":"NJ",
    "sg:tags":[
        "telephone",
        "cellular"
    ],
    "wof:name":"Verizon Wireless",
    "wof:placetype":"venue"
},
  "geometry": {"coordinates":[-74.070825,40.910381],"type":"Point"}
}