{
  "type": "Feature",
  "properties": {
    "iso:country":"US",
    "sg:address":"14 Carey Cir",
    "sg:city":"Burlington",
    "sg:classifiers":[
        {
            "category":"Building & Trades",
            "subcategory":"Electrical",
            "type":"Services"
        }
    ],
    "sg:phone":"+1 609 386 9699",
    "sg:postcode":"08016",
    "sg:province":"NJ",
    "sg:tags":[
        "installs",
        "alarm",
        "system"
    ],
    "wof:name":"Liberty Electronic Security",
    "wof:placetype":"venue"
},
  "geometry": {"coordinates":[-74.846448,40.05466],"type":"Point"}
}