{
  "type": "Feature",
  "properties": {
    "addr:full":"58 W Main St Somerville NJ 08876",
    "addr:housenumber":"58",
    "addr:postcode":"08876",
    "addr:street":"W Main St",
    "iso:country":"US",
    "sg:address":"58 W Main St",
    "sg:city":"Somerville",
    "sg:classifiers":[
        {
            "category":"Professional",
            "subcategory":"Accounting & Tax Preparation",
            "type":"Services"
        }
    ],
    "sg:phone":"+1   ",
    "sg:postcode":"08876",
    "sg:province":"NJ",
    "sg:tags":[
        "return"
    ],
    "wof:name":"Powderfinger LLC",
    "wof:placetype":"venue"
},
  "geometry": {"coordinates":[-74.61476399999999,40.569144],"type":"Point"}
}