{
  "type": "Feature",
  "properties": {
    "addr:full":"169 Florence Pl South Plainfield NJ 07080",
    "addr:housenumber":"169",
    "addr:postcode":"07080",
    "addr:street":"Florence Pl",
    "iso:country":"US",
    "sg:address":"169 Florence Pl",
    "sg:city":"South Plainfield",
    "sg:classifiers":[
        {
            "category":"Freight",
            "type":"Transportation"
        }
    ],
    "sg:phone":"+1 908 755 2606",
    "sg:postcode":"07080",
    "sg:province":"NJ",
    "sg:tags":[
        "hauling",
        "trucking"
    ],
    "wof:name":"Cross Creek Trucking Inc",
    "wof:placetype":"venue"
},
  "geometry": {"coordinates":[-74.422828,40.589228],"type":"Point"}
}