{
  "type": "Feature",
  "properties": {
    "addr:full":"24 Jabez St Newark NJ 07105",
    "addr:housenumber":"24",
    "addr:postcode":"07105",
    "addr:street":"Jabez St",
    "iso:country":"US",
    "sg:address":"24 Jabez St",
    "sg:city":"Newark",
    "sg:classifiers":[
        {
            "category":"Wholesale",
            "subcategory":"Apparel",
            "type":"Manufacturing & Wholesale Goods"
        }
    ],
    "sg:phone":"+1 973 344 1739",
    "sg:postcode":"07105",
    "sg:province":"NJ",
    "sg:tags":[
        "clothing"
    ],
    "wof:name":"Alexis Fashions",
    "wof:placetype":"venue"
},
  "geometry": {"coordinates":[-74.154641,40.719393],"type":"Point"}
}