{
  "type": "Feature",
  "properties": {
    "iso:country":"US",
    "sg:address":"108 S Essex Ave",
    "sg:city":"Orange",
    "sg:classifiers":[
        {
            "category":"Restaurant",
            "type":"Food & Drink"
        }
    ],
    "sg:phone":"+1 973 672 7220",
    "sg:postcode":"07050",
    "sg:province":"NJ",
    "sg:tags":[
        "pizza"
    ],
    "wof:name":"Pizza Subwich Llc",
    "wof:placetype":"venue"
},
  "geometry": {"coordinates":[-74.23257,40.769831],"type":"Point"}
}