{
  "type": "Feature",
  "properties": {
    "addr:full":"950 W Chestnut St Union NJ 07083",
    "addr:housenumber":"950",
    "addr:postcode":"07083",
    "addr:street":"W Chestnut St",
    "iso:country":"US",
    "sg:address":"950 W Chestnut St",
    "sg:city":"Union",
    "sg:classifiers":[
        {
            "category":"Health Services",
            "subcategory":"Clinic",
            "type":"Services"
        }
    ],
    "sg:phone":"+1 908 687 2552",
    "sg:postcode":"07083",
    "sg:province":"NJ",
    "wof:name":"Dynamic Medical Imaging LLC",
    "wof:placetype":"venue"
},
  "geometry": {"coordinates":[-74.277811,40.692791],"type":"Point"}
}