{
  "type": "Feature",
  "properties": {
    "addr:full":"23 Linden Ave Montclair NJ 07042",
    "addr:housenumber":"23",
    "addr:postcode":"07042",
    "addr:street":"Linden Ave",
    "iso:country":"US",
    "sg:address":"23 Linden Ave",
    "sg:city":"Montclair",
    "sg:classifiers":[
        {
            "category":"Building & Trades",
            "subcategory":"Plumbing",
            "type":"Services"
        }
    ],
    "sg:phone":"+1 973 233 0035",
    "sg:postcode":"07042",
    "sg:province":"NJ",
    "sg:tags":[
        "plumbing",
        "contractor"
    ],
    "wof:name":"Add Heating and Cooling Inc",
    "wof:placetype":"venue"
},
  "geometry": {"coordinates":[-74.217209,40.795488],"type":"Point"}
}