{
  "type": "Feature",
  "properties": {
    "addr:full":"43 Riverside Dr Hillsdale NJ 07642",
    "addr:housenumber":"43",
    "addr:postcode":"07642",
    "addr:street":"Riverside Dr",
    "iso:country":"US",
    "sg:address":"43 Riverside Dr",
    "sg:city":"Hillsdale",
    "sg:classifiers":[
        {
            "category":"Building & Trades",
            "subcategory":"Construction",
            "type":"Services"
        }
    ],
    "sg:phone":"+1 201 358 4045",
    "sg:postcode":"07642",
    "sg:province":"NJ",
    "sg:tags":[
        "house"
    ],
    "wof:name":"Mr Home Repair",
    "wof:placetype":"venue"
},
  "geometry": {"coordinates":[-74.042159,40.999711],"type":"Point"}
}