{
  "type": "Feature",
  "properties": {
    "iso:country":"US",
    "sg:address":"104 N High St",
    "sg:city":"Millville",
    "sg:classifiers":[
        {
            "category":"Professional",
            "type":"Services"
        }
    ],
    "sg:phone":"+1 856 327 1992",
    "sg:postcode":"08332",
    "sg:province":"NJ",
    "sg:tags":[
        "establishment"
    ],
    "wof:name":"Industrial Glassware",
    "wof:placetype":"venue"
},
  "geometry": {"coordinates":[-75.038544,39.397244],"type":"Point"}
}