{
  "type": "Feature",
  "properties": {
    "addr:full":"392 S Livingston Ave Livingston NJ 07039",
    "addr:housenumber":"392",
    "addr:postcode":"07039",
    "addr:street":"S Livingston Ave",
    "iso:country":"US",
    "sg:address":"392 S Livingston Ave",
    "sg:city":"Livingston",
    "sg:classifiers":[
        {
            "category":"Organizations",
            "subcategory":"Religious Organization",
            "type":"Services"
        }
    ],
    "sg:phone":"+1 973 992 1581",
    "sg:postcode":"07039",
    "sg:province":"NJ",
    "sg:tags":[
        "monastery",
        "convent"
    ],
    "wof:name":"St Philomena's Convent",
    "wof:placetype":"venue"
},
  "geometry": {"coordinates":[-74.316681,40.78058],"type":"Point"}
}