{
  "type": "Feature",
  "properties": {
    "addr:full":"350 State Rte 35 Red Bank NJ 07701",
    "addr:housenumber":"350",
    "addr:postcode":"07701",
    "addr:street":"State Rte 35",
    "iso:country":"US",
    "sg:address":"350 State Rte 35",
    "sg:city":"Red Bank",
    "sg:classifiers":[
        {
            "category":"Real Estate",
            "subcategory":"Real Estate Agent",
            "type":"Services"
        }
    ],
    "sg:phone":"+1   ",
    "sg:postcode":"07701",
    "sg:province":"NJ",
    "wof:name":"GMAC",
    "wof:placetype":"venue"
},
  "geometry": {"coordinates":[-74.085415,40.369302],"type":"Point"}
}