{
  "type": "Feature",
  "properties": {
    "addr:full":"153 Halsey St Newark NJ 07102",
    "addr:housenumber":"153",
    "addr:postcode":"07102",
    "addr:street":"Halsey St",
    "iso:country":"US",
    "sg:address":"153 Halsey St",
    "sg:city":"Newark",
    "sg:classifiers":[
        {
            "category":"Government",
            "subcategory":"Office",
            "type":"Public Place"
        }
    ],
    "sg:phone":"+1 973 645 4280",
    "sg:postcode":"07102",
    "sg:province":"NJ",
    "wof:name":"Honorable Raymond A Hayser",
    "wof:placetype":"venue"
},
  "geometry": {"coordinates":[-74.173176,40.737227],"type":"Point"}
}