{
  "type": "Feature",
  "properties": {
    "addr:full":"107 South Ave W Cranford NJ 07016",
    "addr:housenumber":"107",
    "addr:postcode":"07016",
    "addr:street":"South Ave W",
    "iso:country":"US",
    "sg:address":"107 South Ave W",
    "sg:city":"Cranford",
    "sg:classifiers":[
        {
            "category":"Social Services",
            "subcategory":"Job Training",
            "type":"Services"
        }
    ],
    "sg:phone":"+1 908 931 1400",
    "sg:postcode":"07016",
    "sg:province":"NJ",
    "sg:tags":[
        "rehabilitation"
    ],
    "wof:name":"Procura Management Inc",
    "wof:placetype":"venue"
},
  "geometry": {"coordinates":[-74.31341,40.653165],"type":"Point"}
}