{
  "type": "Feature",
  "properties": {
    "iso:country":"US",
    "sg:address":"529 Northfield Ave",
    "sg:city":"West Orange",
    "sg:classifiers":[
        {
            "category":"Food & Beverages",
            "subcategory":"Liquor & Beverages",
            "type":"Retail Goods"
        },
        {
            "category":"Professional",
            "subcategory":"Lawyer & Legal Services",
            "type":"Services"
        }
    ],
    "sg:phone":"+1 973 736 8582",
    "sg:postcode":"07052",
    "sg:province":"NJ",
    "sg:tags":[
        "notary",
        "beer",
        "spirit",
        "wine"
    ],
    "wof:name":"St Cloud Wine and Liquors",
    "wof:placetype":"venue"
},
  "geometry": {"coordinates":[-74.27780199999999,40.770302],"type":"Point"}
}