{
  "type": "Feature",
  "properties": {
    "addr:full":"302 Howard Ave Passaic NJ 07055",
    "addr:housenumber":"302",
    "addr:postcode":"07055",
    "addr:street":"Howard Ave",
    "iso:country":"US",
    "sg:address":"302 Howard Ave",
    "sg:city":"Passaic",
    "sg:classifiers":[
        {
            "category":"Professional",
            "subcategory":"Management & Consulting",
            "type":"Services"
        }
    ],
    "sg:phone":"+1 973 916 1951",
    "sg:postcode":"07055",
    "sg:province":"NJ",
    "wof:name":"J L N",
    "wof:placetype":"venue"
},
  "geometry": {"coordinates":[-74.13678899999999,40.847293],"type":"Point"}
}