{
  "type": "Feature",
  "properties": {
    "addr:full":"26 Wordsworth Rd Short Hills NJ 07078",
    "addr:housenumber":"26",
    "addr:postcode":"07078",
    "addr:street":"Wordsworth Rd",
    "iso:country":"US",
    "sg:address":"26 Wordsworth Rd",
    "sg:city":"Short Hills",
    "sg:classifiers":[
        {
            "category":"Professional",
            "subcategory":"Employment Agencies",
            "type":"Services"
        }
    ],
    "sg:phone":"+1   ",
    "sg:postcode":"07078",
    "sg:province":"NJ",
    "wof:name":"Rmb Legal Search Inc",
    "wof:placetype":"venue"
},
  "geometry": {"coordinates":[-74.344133,40.740204],"type":"Point"}
}