{
  "type": "Feature",
  "properties": {
    "addr:full":"138 State Rte 23 Franklin NJ 07416",
    "addr:housenumber":"138",
    "addr:postcode":"07416",
    "addr:street":"State Rte 23",
    "iso:country":"US",
    "sg:address":"138 State Rte 23",
    "sg:city":"Franklin",
    "sg:classifiers":[
        {
            "category":"Restaurant",
            "type":"Food & Drink"
        }
    ],
    "sg:phone":"+1 973 209 2226",
    "sg:postcode":"07416",
    "sg:province":"NJ",
    "sg:website":"www.crystalgolfresort.com",
    "wof:name":"Bear Den Restaurant",
    "wof:placetype":"venue"
},
  "geometry": {"coordinates":[-74.58023799999999,41.112411],"type":"Point"}
}