{
  "type": "Feature",
  "properties": {
    "addr:full":"299 Main St Lodi NJ 07644",
    "addr:housenumber":"299",
    "addr:postcode":"07644",
    "addr:street":"Main St",
    "iso:country":"US",
    "sg:address":"299 Main St",
    "sg:city":"Lodi",
    "sg:classifiers":[
        {
            "category":"Communications",
            "subcategory":"Newspaper",
            "type":"Services"
        }
    ],
    "sg:phone":"+1 973 471 7233",
    "sg:postcode":"07644",
    "sg:province":"NJ",
    "sg:tags":[
        "magazine"
    ],
    "wof:name":"Hipnosis Productions",
    "wof:placetype":"venue"
},
  "geometry": {"coordinates":[-74.083099,40.8834],"type":"Point"}
}