{
  "type": "Feature",
  "properties": {
    "addr:full":"170 Regina Ave Rahway NJ 07065",
    "addr:housenumber":"170",
    "addr:postcode":"07065",
    "addr:street":"Regina Ave",
    "iso:country":"US",
    "sg:address":"170 Regina Ave",
    "sg:city":"Rahway",
    "sg:classifiers":[
        {
            "category":"Shopping",
            "subcategory":"Gifts & Souvenirs",
            "type":"Retail Goods"
        }
    ],
    "sg:phone":"+1   ",
    "sg:postcode":"07065",
    "sg:province":"NJ",
    "wof:name":"Sajawat",
    "wof:placetype":"venue"
},
  "geometry": {"coordinates":[-74.282521,40.598691],"type":"Point"}
}