{
  "type": "Feature",
  "properties": {
    "iso:country":"US",
    "sg:address":"7 Harwich Rd",
    "sg:city":"Morristown",
    "sg:classifiers":[
        {
            "category":"Health Services",
            "subcategory":"Health Practitioner",
            "type":"Services"
        }
    ],
    "sg:phone":"+1   ",
    "sg:postcode":"07960",
    "sg:province":"NJ",
    "wof:name":"Stuart Mrian R Psychotherapist",
    "wof:placetype":"venue"
},
  "geometry": {"coordinates":[-74.52172400000001,40.823718],"type":"Point"}
}