{
  "type": "Feature",
  "properties": {
    "addr:full":"337 Market St Saddle Brook NJ 07663",
    "addr:housenumber":"337",
    "addr:postcode":"07663",
    "addr:street":"Market St",
    "iso:country":"US",
    "sg:address":"337 Market St",
    "sg:city":"Saddle Brook",
    "sg:classifiers":[
        {
            "category":"Health Services",
            "subcategory":"Health Practitioner",
            "type":"Services"
        }
    ],
    "sg:phone":"+1 201 368 3800",
    "sg:postcode":"07663",
    "sg:province":"NJ",
    "sg:tags":[
        "nutritionist"
    ],
    "wof:name":"William MD Song H",
    "wof:placetype":"venue"
},
  "geometry": {"coordinates":[-74.093953,40.896797],"type":"Point"}
}