{
  "type": "Feature",
  "properties": {
    "iso:country":"US",
    "sg:address":"913 Middlesex Ave",
    "sg:city":"Metuchen",
    "sg:classifiers":[
        {
            "category":"Freight",
            "type":"Transportation"
        }
    ],
    "sg:phone":"+1 732 205 1550",
    "sg:postcode":"08840",
    "sg:province":"NJ",
    "sg:tags":[
        "arrangement"
    ],
    "wof:name":"Magcor Corp",
    "wof:placetype":"venue"
},
  "geometry": {"coordinates":[-74.374392,40.5366],"type":"Point"}
}