{
  "type": "Feature",
  "properties": {
    "iso:country":"US",
    "sg:address":"10 Old Swartswood Station Rd",
    "sg:city":"Newton",
    "sg:classifiers":[
        {
            "category":"Professional",
            "subcategory":"Art Services",
            "type":"Services"
        }
    ],
    "sg:phone":"+1 973 300 9800",
    "sg:postcode":"07860",
    "sg:province":"NJ",
    "sg:tags":[
        "photographer",
        "photography",
        "commercial"
    ],
    "sg:website":"www.joeg.com",
    "wof:name":"Joe Guerriero Photography",
    "wof:placetype":"venue"
},
  "geometry": {"coordinates":[-74.81491,41.049779],"type":"Point"}
}