{
  "type": "Feature",
  "properties": {
    "addr:full":"136 Sylvania Pl South Plainfield NJ 07080",
    "addr:housenumber":"136",
    "addr:postcode":"07080",
    "addr:street":"Sylvania Pl",
    "iso:country":"US",
    "sg:address":"136 Sylvania Pl",
    "sg:city":"South Plainfield",
    "sg:classifiers":[
        {
            "category":"Wholesale",
            "subcategory":"Drugs",
            "type":"Manufacturing & Wholesale Goods"
        }
    ],
    "sg:phone":"+1 908 753 7874",
    "sg:postcode":"07080",
    "sg:province":"NJ",
    "sg:tags":[
        "cologne",
        "perfume"
    ],
    "wof:name":"Sushmaa International Inc",
    "wof:placetype":"venue"
},
  "geometry": {"coordinates":[-74.42694400000001,40.57377],"type":"Point"}
}