{
  "type": "Feature",
  "properties": {
    "iso:country":"US",
    "sg:address":"199 Evesboro Medford Rd",
    "sg:city":"Marlton",
    "sg:classifiers":[
        {
            "category":"Education",
            "subcategory":"School",
            "type":"Public Place"
        }
    ],
    "sg:phone":"+1 856 983 8132",
    "sg:postcode":"08053",
    "sg:province":"NJ",
    "wof:name":"Evesham Child Care",
    "wof:placetype":"venue"
},
  "geometry": {"coordinates":[-74.903881,39.904764],"type":"Point"}
}