{
  "type": "Feature",
  "properties": {
    "iso:country":"US",
    "sg:address":"177 Prospect St",
    "sg:city":"Passaic",
    "sg:classifiers":[
        {
            "category":"Health Services",
            "subcategory":"Doctor",
            "type":"Services"
        }
    ],
    "sg:phone":"+1 973 777 4343",
    "sg:postcode":"07055",
    "sg:province":"NJ",
    "sg:tags":[
        "physician",
        "surgeon"
    ],
    "wof:name":"Passaic Eye Care Center",
    "wof:placetype":"venue"
},
  "geometry": {"coordinates":[-74.126999,40.8615],"type":"Point"}
}