{
  "type": "Feature",
  "properties": {
    "iso:country":"US",
    "sg:address":"34 W Front St",
    "sg:city":"Keyport",
    "sg:classifiers":[
        {
            "category":"Shopping",
            "subcategory":"Gifts & Souvenirs",
            "type":"Retail Goods"
        }
    ],
    "sg:phone":"+1 732 264 3993",
    "sg:postcode":"07735",
    "sg:province":"NJ",
    "sg:tags":[
        "shop"
    ],
    "wof:name":"Clever Hen",
    "wof:placetype":"venue"
},
  "geometry": {"coordinates":[-74.20211500000001,40.437515],"type":"Point"}
}