{
  "type": "Feature",
  "properties": {
    "addr:full":"311 Fairview Ave Fairview NJ 07022",
    "addr:housenumber":"311",
    "addr:postcode":"07022",
    "addr:street":"Fairview Ave",
    "iso:country":"US",
    "sg:address":"311 Fairview Ave",
    "sg:city":"Fairview",
    "sg:classifiers":[
        {
            "category":"Banks & Credit Unions",
            "subcategory":"Bank",
            "type":"Services"
        }
    ],
    "sg:phone":"+1 201 943 0050",
    "sg:postcode":"07022",
    "sg:province":"NJ",
    "sg:tags":[
        "federal",
        "saving",
        "institution"
    ],
    "wof:name":"Oritani Savings Bank",
    "wof:placetype":"venue"
},
  "geometry": {"coordinates":[-74.0009,40.8102],"type":"Point"}
}