{
  "type": "Feature",
  "properties": {
    "iso:country":"US",
    "sg:address":"1421 Atlantic Ave",
    "sg:city":"Atlantic City",
    "sg:classifiers":[
        {
            "category":"Government",
            "subcategory":"Office",
            "type":"Public Place"
        }
    ],
    "sg:phone":"+1 609 441 3280",
    "sg:postcode":"08401",
    "sg:province":"NJ",
    "sg:tags":[
        "state",
        "inspection"
    ],
    "wof:name":"Labor Dept",
    "wof:placetype":"venue"
},
  "geometry": {"coordinates":[-74.429148,39.36179],"type":"Point"}
}