{
  "type": "Feature",
  "properties": {
    "iso:country":"US",
    "sg:address":"130 Mount Pleasant Ave",
    "sg:city":"Newark",
    "sg:classifiers":[
        {
            "category":"Professional",
            "type":"Services"
        }
    ],
    "sg:phone":"+1 973 481 9900",
    "sg:postcode":"07104",
    "sg:province":"NJ",
    "sg:tags":[
        "establishment"
    ],
    "wof:name":"First Friday Global Inc",
    "wof:placetype":"venue"
},
  "geometry": {"coordinates":[-74.167687,40.757408],"type":"Point"}
}