{
  "type": "Feature",
  "properties": {
    "iso:country":"US",
    "sg:address":"967 S Elmora Ave",
    "sg:city":"Elizabeth",
    "sg:classifiers":[
        {
            "category":"Retail",
            "subcategory":"Auto Repair",
            "type":"Services"
        }
    ],
    "sg:phone":"+1 908 355 2200",
    "sg:postcode":"07202",
    "sg:province":"NJ",
    "sg:tags":[
        "repairing",
        "automobile"
    ],
    "wof:name":"Elmora Auto Care",
    "wof:placetype":"venue"
},
  "geometry": {"coordinates":[-74.224098,40.652599],"type":"Point"}
}