{
  "type": "Feature",
  "properties": {
    "iso:country":"US",
    "sg:address":"137 N 3rd St",
    "sg:city":"Paterson",
    "sg:classifiers":[
        {
            "category":"Shopping Center",
            "type":"Public Place"
        }
    ],
    "sg:phone":"+1 973 595 5111",
    "sg:postcode":"07522",
    "sg:province":"NJ",
    "sg:tags":[
        "soccer"
    ],
    "wof:name":"Premier Indoor Soccer",
    "wof:placetype":"venue"
},
  "geometry": {"coordinates":[-74.172809,40.927695],"type":"Point"}
}