{
  "type": "Feature",
  "properties": {
    "iso:country":"US",
    "sg:address":"485 Woodbury Glassboro Rd",
    "sg:city":"Sewell",
    "sg:classifiers":[
        {
            "category":"Bars & Pubs",
            "type":"Food & Drink"
        }
    ],
    "sg:phone":"+1 856 589 8989",
    "sg:postcode":"08080",
    "sg:province":"NJ",
    "sg:tags":[
        "drinking"
    ],
    "wof:name":"Clancy's Pub Inc",
    "wof:placetype":"venue"
},
  "geometry": {"coordinates":[-75.125491,39.744204],"type":"Point"}
}