{
  "type": "Feature",
  "properties": {
    "iso:country":"US",
    "sg:address":"75 Campo Ter",
    "sg:city":"Red Bank",
    "sg:classifiers":[
        {
            "category":"Building & Trades",
            "subcategory":"Landscaping Services",
            "type":"Services"
        }
    ],
    "sg:phone":"+1 732 219 6500",
    "sg:postcode":"07701",
    "sg:province":"NJ",
    "wof:name":"Lawn Patrol Inc",
    "wof:placetype":"venue"
},
  "geometry": {"coordinates":[-74.091337,40.358927],"type":"Point"}
}