{
  "type": "Feature",
  "properties": {
    "addr:full":"172 Union Ave Bloomingdale NJ 07403",
    "addr:housenumber":"172",
    "addr:postcode":"07403",
    "addr:street":"Union Ave",
    "iso:country":"US",
    "sg:address":"172 Union Ave",
    "sg:city":"Bloomingdale",
    "sg:classifiers":[
        {
            "category":"Professional",
            "subcategory":"Detective & Security Services",
            "type":"Services"
        }
    ],
    "sg:phone":"+1 973 492 9549",
    "sg:postcode":"07403",
    "sg:province":"NJ",
    "sg:tags":[
        "guard",
        "patrol"
    ],
    "wof:name":"R Congleton Private Detective",
    "wof:placetype":"venue"
},
  "geometry": {"coordinates":[-74.316418,41.013624],"type":"Point"}
}