{
  "type": "Feature",
  "properties": {
    "addr:full":"9 Sequoia Dr Dayton NJ 08810",
    "addr:housenumber":"9",
    "addr:postcode":"08810",
    "addr:street":"Sequoia Dr",
    "iso:country":"US",
    "sg:address":"9 Sequoia Dr",
    "sg:city":"Dayton",
    "sg:classifiers":[
        {
            "category":"Shopping",
            "subcategory":"Jewelry",
            "type":"Retail Goods"
        }
    ],
    "sg:phone":"+1   ",
    "sg:postcode":"08810",
    "sg:province":"NJ",
    "wof:name":"C P Jewellers LLC",
    "wof:placetype":"venue"
},
  "geometry": {"coordinates":[-74.51075899999999,40.38389],"type":"Point"}
}