{
  "type": "Feature",
  "properties": {
    "addr:full":"6 N Main St Pennington NJ 08534",
    "addr:housenumber":"6",
    "addr:postcode":"08534",
    "addr:street":"N Main St",
    "iso:country":"US",
    "sg:address":"6 N Main St",
    "sg:city":"Pennington",
    "sg:classifiers":[
        {
            "category":"Shopping",
            "subcategory":"Pharmacy",
            "type":"Retail Goods"
        }
    ],
    "sg:phone":"+1 609 737 9297",
    "sg:postcode":"08534",
    "sg:province":"NJ",
    "wof:name":"Pennington Apothecary LLC",
    "wof:placetype":"venue"
},
  "geometry": {"coordinates":[-74.79203200000001,40.331428],"type":"Point"}
}