{
  "type": "Feature",
  "properties": {
    "addr:full":"1321 Alina St Elizabeth NJ 07208",
    "addr:housenumber":"1321",
    "addr:postcode":"07208",
    "addr:street":"Alina St",
    "iso:country":"US",
    "sg:address":"1321 Alina St",
    "sg:city":"Elizabeth",
    "sg:classifiers":[
        {
            "category":"Personal",
            "subcategory":"Beauty Salon",
            "type":"Services"
        }
    ],
    "sg:phone":"+1 908 820 8371",
    "sg:postcode":"07208",
    "sg:province":"NJ",
    "sg:tags":[
        "shop"
    ],
    "wof:name":"Bluestone Beauty Salon",
    "wof:placetype":"venue"
},
  "geometry": {"coordinates":[-74.210092,40.686439],"type":"Point"}
}