{
  "type": "Feature",
  "properties": {
    "addr:full":"4 Indian Ln Califon NJ 07830",
    "addr:housenumber":"4",
    "addr:postcode":"07830",
    "addr:street":"Indian Ln",
    "iso:country":"US",
    "sg:address":"4 Indian Ln",
    "sg:city":"Califon",
    "sg:classifiers":[
        {
            "category":"Insurance",
            "subcategory":"Insurance Agent",
            "type":"Services"
        }
    ],
    "sg:phone":"+1   ",
    "sg:postcode":"07830",
    "sg:province":"NJ",
    "sg:tags":[
        "consulting"
    ],
    "wof:name":"Ursa Advisors LLC",
    "wof:placetype":"venue"
},
  "geometry": {"coordinates":[-74.82406400000001,40.729258],"type":"Point"}
}