{
  "type": "Feature",
  "properties": {
    "iso:country":"US",
    "sg:address":"1133 Prospect St",
    "sg:city":"Ewing",
    "sg:classifiers":[
        {
            "category":"Communications",
            "subcategory":"Radio Station",
            "type":"Services"
        },
        {
            "category":"Utilities",
            "subcategory":"Telephone",
            "type":"Services"
        },
        {
            "category":"Recreation",
            "type":"Entertainment"
        }
    ],
    "sg:phone":"+1 609 882 2891",
    "sg:postcode":"08638",
    "sg:province":"NJ",
    "sg:tags":[
        "equipment",
        "radios-citizens",
        "system",
        "band"
    ],
    "wof:name":"B&S Mobile Communications",
    "wof:placetype":"venue"
},
  "geometry": {"coordinates":[-74.768744,40.240098],"type":"Point"}
}