{
  "type": "Feature",
  "properties": {
    "iso:country":"US",
    "sg:address":"25 Washington St",
    "sg:city":"Morristown",
    "sg:classifiers":[
        {
            "category":"Building & Trades",
            "subcategory":"Locksmith",
            "type":"Services"
        }
    ],
    "sg:phone":"+1 888 594 4529",
    "sg:postcode":"07960",
    "sg:province":"NJ",
    "sg:tags":[
        "key"
    ],
    "wof:name":"1 24 Hour Emergency Locksmith",
    "wof:placetype":"venue"
},
  "geometry": {"coordinates":[-74.48313400000001,40.79795],"type":"Point"}
}