{
  "type": "Feature",
  "properties": {
    "addr:full":"374 Midland Ave Saddle Brook NJ 07663",
    "addr:housenumber":"374",
    "addr:postcode":"07663",
    "addr:street":"Midland Ave",
    "iso:country":"US",
    "sg:address":"374 Midland Ave",
    "sg:city":"Saddle Brook",
    "sg:classifiers":[
        {
            "category":"Restaurant",
            "type":"Food & Drink"
        }
    ],
    "sg:phone":"+1 201 794 7266",
    "sg:postcode":"07663",
    "sg:province":"NJ",
    "wof:name":"Chumley's",
    "wof:placetype":"venue"
},
  "geometry": {"coordinates":[-74.105566,40.905931],"type":"Point"}
}