{
  "type": "Feature",
  "properties": {
    "iso:country":"US",
    "sg:address":"150 State Rte 37",
    "sg:city":"Toms River",
    "sg:classifiers":[
        {
            "category":"Health Services",
            "subcategory":"Doctor",
            "type":"Services"
        }
    ],
    "sg:phone":"+1 732 244 2299",
    "sg:postcode":"08755",
    "sg:province":"NJ",
    "sg:tags":[
        "physician",
        "medical",
        "surgeon"
    ],
    "sg:website":"www.biobehavioralhealth.com",
    "wof:name":"Bio Behavioral Health",
    "wof:placetype":"venue"
},
  "geometry": {"coordinates":[-74.22035099999999,39.966136],"type":"Point"}
}