{
  "type": "Feature",
  "properties": {
    "addr:full":"1360 Clifton Ave Clifton NJ 07012",
    "addr:housenumber":"1360",
    "addr:postcode":"07012",
    "addr:street":"Clifton Ave",
    "iso:country":"US",
    "sg:address":"1360 Clifton Ave",
    "sg:city":"Clifton",
    "sg:classifiers":[
        {
            "category":"Professional",
            "type":"Services"
        }
    ],
    "sg:phone":"+1 973 916 0441",
    "sg:postcode":"07012",
    "sg:province":"NJ",
    "wof:name":"Fast Dater New York",
    "wof:placetype":"venue"
},
  "geometry": {"coordinates":[-74.17233299999999,40.854154],"type":"Point"}
}