{
  "type": "Feature",
  "properties": {
    "iso:country":"US",
    "sg:address":"940 State Rte 73",
    "sg:city":"Marlton",
    "sg:classifiers":[
        {
            "category":"Food & Beverages",
            "subcategory":"Groceries & Convenience Stores",
            "type":"Retail Goods"
        }
    ],
    "sg:phone":"+1 856 797 1115",
    "sg:postcode":"08053",
    "sg:province":"NJ",
    "sg:tags":[
        "grocer"
    ],
    "sg:website":"www.wholefoodsmarket.com",
    "wof:name":"Whole Foods Market",
    "wof:placetype":"venue"
},
  "geometry": {"coordinates":[-74.92167000000001,39.860886],"type":"Point"}
}