{
  "type": "Feature",
  "properties": {
    "iso:country":"US",
    "sg:address":"39 Rolling Ridge Rd",
    "sg:city":"Upper Saddle Rvr",
    "sg:classifiers":[
        {
            "category":"Building & Trades",
            "subcategory":"Construction",
            "type":"Services"
        }
    ],
    "sg:phone":"+1 201 825 9474",
    "sg:postcode":"07458",
    "sg:province":"NJ",
    "sg:tags":[
        "masonry",
        "contractor"
    ],
    "wof:name":"Jim Aufiero Builder Inc",
    "wof:placetype":"venue"
},
  "geometry": {"coordinates":[-74.08553499999999,41.066334],"type":"Point"}
}