{
  "type": "Feature",
  "properties": {
    "addr:full":"405 S Broadway Pitman NJ 08071",
    "addr:housenumber":"405",
    "addr:postcode":"08071",
    "addr:street":"S Broadway",
    "iso:country":"US",
    "sg:address":"405 S Broadway",
    "sg:city":"Pitman",
    "sg:classifiers":[
        {
            "category":"Shopping",
            "subcategory":"Musical Instruments",
            "type":"Retail Goods"
        }
    ],
    "sg:phone":"+1   ",
    "sg:postcode":"08071",
    "sg:province":"NJ",
    "sg:tags":[
        "lease",
        "rent",
        "supply"
    ],
    "wof:name":"Music Museum",
    "wof:placetype":"venue"
},
  "geometry": {"coordinates":[-75.126459,39.728024],"type":"Point"}
}