{
  "type": "Feature",
  "properties": {
    "addr:full":"313 Boulevard Hasbrouck Hts NJ 07604",
    "addr:housenumber":"313",
    "addr:postcode":"07604",
    "addr:street":"Boulevard",
    "iso:country":"US",
    "sg:address":"313 Boulevard",
    "sg:city":"Hasbrouck Hts",
    "sg:classifiers":[
        {
            "category":"Retail",
            "subcategory":"Laundry & Dry Cleaning",
            "type":"Services"
        }
    ],
    "sg:phone":"+1 201 288 5882",
    "sg:postcode":"07604",
    "sg:province":"NJ",
    "sg:tags":[
        "cleaners"
    ],
    "wof:name":"Payless Cleaners Inc",
    "wof:placetype":"venue"
},
  "geometry": {"coordinates":[-74.07490900000001,40.865226],"type":"Point"}
}