{
  "type": "Feature",
  "properties": {
    "addr:full":"555 E 31st St Paterson NJ 07513",
    "addr:housenumber":"555",
    "addr:postcode":"07513",
    "addr:street":"E 31St St",
    "iso:country":"US",
    "sg:address":"555 E 31st St",
    "sg:city":"Paterson",
    "sg:classifiers":[
        {
            "category":"Retail",
            "subcategory":"Laundry & Dry Cleaning",
            "type":"Services"
        }
    ],
    "sg:phone":"+1 973 754 0568",
    "sg:postcode":"07513",
    "sg:province":"NJ",
    "sg:tags":[
        "dyer"
    ],
    "wof:name":"Pearl Fabrics",
    "wof:placetype":"venue"
},
  "geometry": {"coordinates":[-74.146327,40.905651],"type":"Point"}
}