{
  "type": "Feature",
  "properties": {
    "addr:full":"214 Broad St Red Bank NJ 07701",
    "addr:housenumber":"214",
    "addr:postcode":"07701",
    "addr:street":"Broad St",
    "iso:country":"US",
    "sg:address":"214 Broad St",
    "sg:city":"Red Bank",
    "sg:classifiers":[
        {
            "category":"Professional",
            "subcategory":"Lawyer & Legal Services",
            "type":"Services"
        }
    ],
    "sg:phone":"+1 732 219 9350",
    "sg:postcode":"07701",
    "sg:province":"NJ",
    "sg:tags":[
        "attorney"
    ],
    "wof:name":"Mary E Scrupski",
    "wof:placetype":"venue"
},
  "geometry": {"coordinates":[-74.06465300000001,40.344583],"type":"Point"}
}