{
  "type": "Feature",
  "properties": {
    "iso:country":"US",
    "sg:address":"836 Cooper Landing Rd",
    "sg:city":"Cherry Hill",
    "sg:classifiers":[
        {
            "category":"Personal",
            "subcategory":"Beauty Salon",
            "type":"Services"
        }
    ],
    "sg:phone":"+1 856 414 1523",
    "sg:postcode":"08002",
    "sg:province":"NJ",
    "sg:tags":[
        "shop"
    ],
    "wof:name":"U Got Nails Inc",
    "wof:placetype":"venue"
},
  "geometry": {"coordinates":[-75.010223,39.939105],"type":"Point"}
}