{
  "type": "Feature",
  "properties": {
    "addr:full":"51 Ethel Rd W Piscataway NJ 08854",
    "addr:housenumber":"51",
    "addr:postcode":"08854",
    "addr:street":"Ethel Rd W",
    "iso:country":"US",
    "sg:address":"51 Ethel Rd W",
    "sg:city":"Piscataway",
    "sg:classifiers":[
        {
            "category":"Manufacturing",
            "subcategory":"Chemicals & Compounds",
            "type":"Manufacturing & Wholesale Goods"
        }
    ],
    "sg:phone":"+1 732 572 5600",
    "sg:postcode":"08854",
    "sg:province":"NJ",
    "sg:tags":[
        "fragrance",
        "mfg"
    ],
    "wof:name":"Alpine Aromatics International",
    "wof:placetype":"venue"
},
  "geometry": {"coordinates":[-74.421164,40.53174],"type":"Point"}
}