{
  "type": "Feature",
  "properties": {
    "iso:country":"US",
    "sg:address":"24 Rockaway Ave",
    "sg:city":"Rockaway",
    "sg:classifiers":[
        {
            "category":"Shopping",
            "subcategory":"Clothing, Apparel, & Fashions",
            "type":"Retail Goods"
        }
    ],
    "sg:phone":"+1   ",
    "sg:postcode":"07866",
    "sg:province":"NJ",
    "sg:tags":[
        "sport",
        "accessory"
    ],
    "wof:name":"The Athletes Foot",
    "wof:placetype":"venue"
},
  "geometry": {"coordinates":[-74.504892,40.897105],"type":"Point"}
}