{
  "type": "Feature",
  "properties": {
    "addr:full":"5144 W Hurley Pond Rd Wall Township NJ 07727",
    "addr:housenumber":"5144",
    "addr:postcode":"07727",
    "addr:street":"W Hurley Pond Rd Wall",
    "iso:country":"US",
    "sg:address":"5144 W Hurley Pond Rd",
    "sg:city":"Wall Township",
    "sg:classifiers":[
        {
            "category":"Manufacturing",
            "subcategory":"Rubber & Plastics",
            "type":"Manufacturing & Wholesale Goods"
        }
    ],
    "sg:phone":"+1 732 938 3500",
    "sg:postcode":"07727",
    "sg:province":"NJ",
    "sg:tags":[
        "producer"
    ],
    "wof:name":"Haygro Sales Inc",
    "wof:placetype":"venue"
},
  "geometry": {"coordinates":[-74.135403,40.179954],"type":"Point"}
}