{
  "type": "Feature",
  "properties": {
    "iso:country":"US",
    "sg:address":"3 Ashburn Pl",
    "sg:city":"Fair Lawn",
    "sg:classifiers":[
        {
            "category":"Shopping",
            "subcategory":"Computers & Home Electronics",
            "type":"Retail Goods"
        }
    ],
    "sg:phone":"+1   ",
    "sg:postcode":"07410",
    "sg:province":"NJ",
    "sg:tags":[
        "professional",
        "consulting"
    ],
    "wof:name":"Katie Associates",
    "wof:placetype":"venue"
},
  "geometry": {"coordinates":[-74.118554,40.941924],"type":"Point"}
}