{
  "type": "Feature",
  "properties": {
    "addr:full":"615 Mantua Blvd Sewell NJ 08080",
    "addr:housenumber":"615",
    "addr:postcode":"08080",
    "addr:street":"Mantua Blvd",
    "iso:country":"US",
    "sg:address":"615 Mantua Blvd",
    "sg:city":"Sewell",
    "sg:classifiers":[
        {
            "category":"Food & Beverages",
            "subcategory":"Groceries & Convenience Stores",
            "type":"Retail Goods"
        }
    ],
    "sg:phone":"+1   ",
    "sg:postcode":"08080",
    "sg:province":"NJ",
    "sg:tags":[
        "product",
        "dairy"
    ],
    "wof:name":"Heritage Dairy Stores Inc",
    "wof:placetype":"venue"
},
  "geometry": {"coordinates":[-75.148072,39.773748],"type":"Point"}
}