{
  "type": "Feature",
  "properties": {
    "iso:country":"US",
    "sg:address":"430 Emory Ave",
    "sg:city":"Trenton",
    "sg:classifiers":[
        {
            "category":"Wholesale",
            "subcategory":"Toys & Hobbies",
            "type":"Manufacturing & Wholesale Goods"
        }
    ],
    "sg:phone":"+1 609 396 6916",
    "sg:postcode":"08611",
    "sg:province":"NJ",
    "sg:tags":[
        "wholesaler"
    ],
    "wof:name":"Sun Wholesale Inc",
    "wof:placetype":"venue"
},
  "geometry": {"coordinates":[-74.74289,40.211032],"type":"Point"}
}