{
  "type": "Feature",
  "properties": {
    "iso:country":"US",
    "sg:address":"150 Morris Ave Ste 101",
    "sg:city":"Springfield",
    "sg:classifiers":[
        {
            "category":"Professional",
            "subcategory":"Employment Agencies",
            "type":"Services"
        }
    ],
    "sg:phone":"+1 973 921 9777",
    "sg:postcode":"07081",
    "sg:province":"NJ",
    "sg:website":"www.nauticusgroup.com",
    "wof:name":"Nauticus Group",
    "wof:placetype":"venue"
},
  "geometry": {"coordinates":[-74.30789900000001,40.7104],"type":"Point"}
}