{
  "type": "Feature",
  "properties": {
    "addr:full":"608 Alexander Ave Maple Shade NJ 08052",
    "addr:housenumber":"608",
    "addr:postcode":"08052",
    "addr:street":"Alexander Ave",
    "iso:country":"US",
    "sg:address":"608 Alexander Ave",
    "sg:city":"Maple Shade",
    "sg:classifiers":[
        {
            "category":"Wholesale",
            "subcategory":"Machinery & Supplies",
            "type":"Manufacturing & Wholesale Goods"
        }
    ],
    "sg:phone":"+1 856 482 5605",
    "sg:postcode":"08052",
    "sg:province":"NJ",
    "sg:tags":[
        "crane",
        "derrick"
    ],
    "wof:name":"Scott Crane Svc",
    "wof:placetype":"venue"
},
  "geometry": {"coordinates":[-74.995487,39.940364],"type":"Point"}
}