{
  "type": "Feature",
  "properties": {
    "addr:full":"736 S White Horse Pike Audubon NJ 08106",
    "addr:housenumber":"736",
    "addr:postcode":"08106",
    "addr:street":"S White Horse Pike",
    "iso:country":"US",
    "sg:address":"736 S White Horse Pike",
    "sg:city":"Audubon",
    "sg:classifiers":[
        {
            "category":"Real Estate",
            "subcategory":"Real Estate Agent",
            "type":"Services"
        }
    ],
    "sg:phone":"+1 856 546 4771",
    "sg:postcode":"08106",
    "sg:province":"NJ",
    "wof:name":"Harris Referral Realty",
    "wof:placetype":"venue"
},
  "geometry": {"coordinates":[-75.06070200000001,39.886517],"type":"Point"}
}