{
  "type": "Feature",
  "properties": {
    "addr:full":"65 Osborne Pl Cranford NJ 07016",
    "addr:housenumber":"65",
    "addr:postcode":"07016",
    "addr:street":"Osborne Pl",
    "iso:country":"US",
    "sg:address":"65 Osborne Pl",
    "sg:city":"Cranford",
    "sg:classifiers":[
        {
            "category":"Wholesale",
            "subcategory":"Vending Machines",
            "type":"Manufacturing & Wholesale Goods"
        }
    ],
    "sg:phone":"+1   ",
    "sg:postcode":"07016",
    "sg:province":"NJ",
    "sg:tags":[
        "sales"
    ],
    "wof:name":"Kens Vends",
    "wof:placetype":"venue"
},
  "geometry": {"coordinates":[-74.285945,40.661488],"type":"Point"}
}