{
  "type": "Feature",
  "properties": {
    "addr:full":"1325 Boardwalk Atlantic City NJ 08401",
    "addr:housenumber":"1325",
    "addr:postcode":"08401",
    "addr:street":"Boardwalk",
    "iso:country":"US",
    "sg:address":"1325 Boardwalk",
    "sg:city":"Atlantic City",
    "sg:classifiers":[
        {
            "category":"Shopping",
            "subcategory":"Gifts & Souvenirs",
            "type":"Retail Goods"
        }
    ],
    "sg:phone":"+1 609 345 2600",
    "sg:postcode":"08401",
    "sg:province":"NJ",
    "sg:website":"www.boardwalkshop.com",
    "wof:name":"Boardwalk Shop",
    "wof:placetype":"venue"
},
  "geometry": {"coordinates":[-74.423558,39.357551],"type":"Point"}
}