{
  "type": "Feature",
  "properties": {
    "addr:full":"137 Palisade Ave Emerson NJ 07630",
    "addr:housenumber":"137",
    "addr:postcode":"07630",
    "addr:street":"Palisade Ave",
    "iso:country":"US",
    "sg:address":"137 Palisade Ave",
    "sg:city":"Emerson",
    "sg:classifiers":[
        {
            "category":"Restaurant",
            "type":"Food & Drink"
        }
    ],
    "sg:phone":"+1   ",
    "sg:postcode":"07630",
    "sg:province":"NJ",
    "sg:tags":[
        "bar"
    ],
    "wof:name":"Nolas Down Under Pub",
    "wof:placetype":"venue"
},
  "geometry": {"coordinates":[-74.02091799999999,40.971577],"type":"Point"}
}