{
  "type": "Feature",
  "properties": {
    "addr:full":"161 Woodbridge Ctr Woodbridge NJ 07095",
    "addr:housenumber":"161",
    "addr:postcode":"07095",
    "addr:street":"Woodbridge Ctr",
    "iso:country":"US",
    "sg:address":"161 Woodbridge Ctr",
    "sg:city":"Woodbridge",
    "sg:classifiers":[
        {
            "category":"Shopping",
            "subcategory":"Optician",
            "type":"Retail Goods"
        }
    ],
    "sg:phone":"+1 732 855 7900",
    "sg:postcode":"07095",
    "sg:province":"NJ",
    "sg:tags":[
        "eyewear"
    ],
    "wof:name":"Lenscrafters",
    "wof:placetype":"venue"
},
  "geometry": {"coordinates":[-74.298203,40.549702],"type":"Point"}
}