{
  "type": "Feature",
  "properties": {
    "addr:full":"65 Central Ave Hackensack NJ 07601",
    "addr:housenumber":"65",
    "addr:postcode":"07601",
    "addr:street":"Central Ave",
    "iso:country":"US",
    "sg:address":"65 Central Ave",
    "sg:city":"Hackensack",
    "sg:classifiers":[
        {
            "category":"Government",
            "subcategory":"Office",
            "type":"Public Place"
        }
    ],
    "sg:phone":"+1 201 646 3914",
    "sg:postcode":"07601",
    "sg:province":"NJ",
    "sg:tags":[
        "city",
        "planning",
        "zoning",
        "dev",
        "board"
    ],
    "sg:website":"www.hackensack.org",
    "wof:name":"Hackensack Planning Board",
    "wof:placetype":"venue"
},
  "geometry": {"coordinates":[-74.044785,40.886001],"type":"Point"}
}