{
  "type": "Feature",
  "properties": {
    "iso:country":"US",
    "sg:address":"250 Quakerbridge Mall",
    "sg:city":"Lawrenceville",
    "sg:classifiers":[
        {
            "category":"Home & Garden",
            "subcategory":"Building Materials",
            "type":"Retail Goods"
        }
    ],
    "sg:phone":"+1 609 897 0440",
    "sg:postcode":"08648",
    "sg:province":"NJ",
    "sg:tags":[
        "furnishing",
        "accessory"
    ],
    "sg:website":"www.kirklands.com",
    "wof:name":"Kirkland's",
    "wof:placetype":"venue"
},
  "geometry": {"coordinates":[-74.684224,40.28872],"type":"Point"}
}