{
  "type": "Feature",
  "properties": {
    "iso:country":"US",
    "sg:address":"5200 New Jersey Ave",
    "sg:city":"Wildwood",
    "sg:classifiers":[
        {
            "category":"Insurance",
            "subcategory":"Insurance Agent",
            "type":"Services"
        }
    ],
    "sg:phone":"+1 609 522 3406",
    "sg:postcode":"08260",
    "sg:province":"NJ",
    "sg:website":"www.jbyrneagency.com",
    "wof:name":"J Byrne Agency Inc",
    "wof:placetype":"venue"
},
  "geometry": {"coordinates":[-74.826695,38.982603],"type":"Point"}
}