{
  "type": "Feature",
  "properties": {
    "iso:country":"US",
    "sg:address":"222 Cavour St",
    "sg:city":"Colonia",
    "sg:classifiers":[
        {
            "category":"Cinema",
            "subcategory":"Movie Rental",
            "type":"Entertainment"
        }
    ],
    "sg:phone":"+1 732 382 2333",
    "sg:postcode":"07067",
    "sg:province":"NJ",
    "sg:tags":[
        "production",
        "video"
    ],
    "wof:name":"All Jersey Video Productions",
    "wof:placetype":"venue"
},
  "geometry": {"coordinates":[-74.31223900000001,40.600841],"type":"Point"}
}