{
  "type": "Feature",
  "properties": {
    "addr:full":"152 Daretown Rd Elmer NJ 08318",
    "addr:housenumber":"152",
    "addr:postcode":"08318",
    "addr:street":"Daretown Rd",
    "iso:country":"US",
    "sg:address":"152 Daretown Rd",
    "sg:city":"Elmer",
    "sg:classifiers":[
        {
            "category":"Retail",
            "subcategory":"Auto Repair",
            "type":"Services"
        }
    ],
    "sg:phone":"+1 856 358 1248",
    "sg:postcode":"08318",
    "sg:province":"NJ",
    "sg:tags":[
        "body",
        "automobile",
        "painting"
    ],
    "wof:name":"Pete's Rod Nest",
    "wof:placetype":"venue"
},
  "geometry": {"coordinates":[-75.26580300000001,39.586608],"type":"Point"}
}