{
  "type": "Feature",
  "properties": {
    "iso:country":"US",
    "sg:address":"510 W Leeds Ave",
    "sg:city":"Pleasantville",
    "sg:classifiers":[
        {
            "category":"Wholesale",
            "subcategory":"Home Furnishings",
            "type":"Manufacturing & Wholesale Goods"
        }
    ],
    "sg:phone":"+1 609 677 4999",
    "sg:postcode":"08232",
    "sg:province":"NJ",
    "sg:tags":[
        "linen",
        "blanket",
        "drapery",
        "bedspread"
    ],
    "wof:name":"Sobel Westex",
    "wof:placetype":"venue"
},
  "geometry": {"coordinates":[-74.518096,39.412094],"type":"Point"}
}