{
  "type": "Feature",
  "properties": {
    "addr:full":"631 E Woodbridge Ave Avenel NJ 07001",
    "addr:housenumber":"631",
    "addr:postcode":"07001",
    "addr:street":"E Woodbridge Ave",
    "iso:country":"US",
    "sg:address":"631 E Woodbridge Ave",
    "sg:city":"Avenel",
    "sg:classifiers":[
        {
            "category":"Social Services",
            "type":"Services"
        }
    ],
    "sg:phone":"+1 732 634 5360",
    "sg:postcode":"07001",
    "sg:province":"NJ",
    "wof:name":"Middlesex Co Habitat",
    "wof:placetype":"venue"
},
  "geometry": {"coordinates":[-74.280975,40.581182],"type":"Point"}
}