{
  "type": "Feature",
  "properties": {
    "addr:full":"35 Broadway Point Pleasant Beach NJ 08742",
    "addr:housenumber":"35",
    "addr:postcode":"08742",
    "addr:street":"Broadway",
    "iso:country":"US",
    "sg:address":"35 Broadway",
    "sg:city":"Point Pleasant Beach",
    "sg:classifiers":[
        {
            "category":"Recreation",
            "type":"Entertainment"
        }
    ],
    "sg:phone":"+1   ",
    "sg:postcode":"08742",
    "sg:province":"NJ",
    "wof:name":"Norma-K 3",
    "wof:placetype":"venue"
},
  "geometry": {"coordinates":[-74.037064,40.100646],"type":"Point"}
}