{
  "type": "Feature",
  "properties": {
    "addr:full":"801 Broad St Shrewsbury NJ 07702",
    "addr:housenumber":"801",
    "addr:postcode":"07702",
    "addr:street":"Broad St",
    "iso:country":"US",
    "sg:address":"801 Broad St",
    "sg:city":"Shrewsbury",
    "sg:classifiers":[
        {
            "category":"Organizations",
            "subcategory":"Professional Association",
            "type":"Services"
        }
    ],
    "sg:phone":"+1 732 758 8220",
    "sg:postcode":"07702",
    "sg:province":"NJ",
    "wof:name":"American Cancer Society",
    "wof:placetype":"venue"
},
  "geometry": {"coordinates":[-74.06152,40.324829],"type":"Point"}
}