{
  "type": "Feature",
  "properties": {
    "iso:country":"US",
    "sg:address":"6715 Delilah Rd",
    "sg:city":"Egg Harbor Township",
    "sg:classifiers":[
        {
            "category":"Building & Trades",
            "subcategory":"Pest Control",
            "type":"Services"
        }
    ],
    "sg:phone":"+1   ",
    "sg:postcode":"08234",
    "sg:province":"NJ",
    "wof:name":"Rid Pest Control Inc",
    "wof:placetype":"venue"
},
  "geometry": {"coordinates":[-74.54130499999999,39.416799],"type":"Point"}
}