{
  "type": "Feature",
  "properties": {
    "iso:country":"US",
    "sg:address":"101 Glenbrook Blvd",
    "sg:city":"Mount Laurel",
    "sg:classifiers":[
        {
            "category":"Personal",
            "subcategory":"Beauty Salon",
            "type":"Services"
        }
    ],
    "sg:phone":"+1   ",
    "sg:postcode":"08054",
    "sg:province":"NJ",
    "sg:tags":[
        "shop",
        "clothing"
    ],
    "wof:name":"Lindas Place",
    "wof:placetype":"venue"
},
  "geometry": {"coordinates":[-74.97217999999999,39.927821],"type":"Point"}
}