{
  "type": "Feature",
  "properties": {
    "addr:full":"1650 Stuyvesant Ave Union NJ 07083",
    "addr:housenumber":"1650",
    "addr:postcode":"07083",
    "addr:street":"Stuyvesant Ave",
    "iso:country":"US",
    "sg:address":"1650 Stuyvesant Ave",
    "sg:city":"Union",
    "sg:classifiers":[
        {
            "category":"Restaurant",
            "type":"Food & Drink"
        }
    ],
    "sg:phone":"+1   ",
    "sg:postcode":"07083",
    "sg:province":"NJ",
    "sg:tags":[
        "eating"
    ],
    "wof:name":"Spada Sub & Deli",
    "wof:placetype":"venue"
},
  "geometry": {"coordinates":[-74.257914,40.711808],"type":"Point"}
}