{
  "type": "Feature",
  "properties": {
    "addr:full":"383 Springfield Ave Summit NJ 07901",
    "addr:housenumber":"383",
    "addr:postcode":"07901",
    "addr:street":"Springfield Ave",
    "iso:country":"US",
    "sg:address":"383 Springfield Ave",
    "sg:city":"Summit",
    "sg:classifiers":[
        {
            "category":"Shopping",
            "subcategory":"Photographic Equipment",
            "type":"Retail Goods"
        }
    ],
    "sg:phone":"+1 908 273 7427",
    "sg:postcode":"07901",
    "sg:province":"NJ",
    "sg:tags":[
        "photography",
        "store",
        "supply"
    ],
    "sg:website":"www.photosummit.com",
    "wof:name":"Photo Summit the",
    "wof:placetype":"venue"
},
  "geometry": {"coordinates":[-74.35790299999999,40.717899],"type":"Point"}
}