{
  "type": "Feature",
  "properties": {
    "iso:country":"US",
    "sg:address":"253 Closter Dock Rd",
    "sg:city":"Closter",
    "sg:classifiers":[
        {
            "category":"Personal",
            "subcategory":"Beauty Salon",
            "type":"Services"
        }
    ],
    "sg:phone":"+1 201 784 4448",
    "sg:postcode":"07624",
    "sg:province":"NJ",
    "sg:tags":[
        "shop"
    ],
    "wof:name":"Lux Nails",
    "wof:placetype":"venue"
},
  "geometry": {"coordinates":[-73.960584,40.972385],"type":"Point"}
}