{
  "type": "Feature",
  "properties": {
    "addr:full":"409 E 5th Ave Roselle NJ 07203",
    "addr:housenumber":"409",
    "addr:postcode":"07203",
    "addr:street":"E 5Th Ave",
    "iso:country":"US",
    "sg:address":"409 E 5th Ave",
    "sg:city":"Roselle",
    "sg:classifiers":[
        {
            "category":"Communications",
            "subcategory":"Film & Video Production",
            "type":"Services"
        }
    ],
    "sg:phone":"+1 908 241 8685",
    "sg:postcode":"07203",
    "sg:province":"NJ",
    "sg:tags":[
        "motion"
    ],
    "wof:name":"Cannon Productions",
    "wof:placetype":"venue"
},
  "geometry": {"coordinates":[-74.251076,40.656896],"type":"Point"}
}