{
  "type": "Feature",
  "properties": {
    "iso:country":"US",
    "sg:address":"125 Van Buren St",
    "sg:city":"Newark",
    "sg:classifiers":[
        {
            "category":"Education",
            "subcategory":"Special Training",
            "type":"Public Place"
        }
    ],
    "sg:phone":"+1 973 578 8300",
    "sg:postcode":"07105",
    "sg:province":"NJ",
    "sg:tags":[
        "school",
        "language"
    ],
    "wof:name":"Uceda School Inc",
    "wof:placetype":"venue"
},
  "geometry": {"coordinates":[-74.156998,40.7285],"type":"Point"}
}