{
  "type": "Feature",
  "properties": {
    "iso:country":"US",
    "sg:address":"1037 S Broad St",
    "sg:city":"Trenton",
    "sg:classifiers":[
        {
            "category":"Food & Beverages",
            "subcategory":"Groceries & Convenience Stores",
            "type":"Retail Goods"
        }
    ],
    "sg:phone":"+1 609 656 4009",
    "sg:postcode":"08611",
    "sg:province":"NJ",
    "sg:tags":[
        "grocer"
    ],
    "wof:name":"F & F Supermarket",
    "wof:placetype":"venue"
},
  "geometry": {"coordinates":[-74.74545500000001,40.205093],"type":"Point"}
}