{
  "type": "Feature",
  "properties": {
    "iso:country":"US",
    "sg:address":"1300 Ocean Ave",
    "sg:city":"Belmar",
    "sg:classifiers":[
        {
            "category":"Restaurant",
            "type":"Food & Drink"
        }
    ],
    "sg:menulink":"http://www.allmenus.com/nj/belmar/41025-matisse/menu/",
    "sg:phone":"+1 732 681 7680",
    "sg:postcode":"07719",
    "sg:province":"NJ",
    "sg:tags":[
        "seafood",
        "american"
    ],
    "wof:name":"Matisse",
    "wof:placetype":"venue"
},
  "geometry": {"coordinates":[-74.01267199999999,40.178889],"type":"Point"}
}