{
  "type": "Feature",
  "properties": {
    "addr:full":"102 Fair Haven Hill Ct Absecon NJ 08205",
    "addr:housenumber":"102",
    "addr:postcode":"08205",
    "addr:street":"Fair Haven Hill Ct",
    "iso:country":"US",
    "sg:address":"102 Fair Haven Hill Ct",
    "sg:city":"Absecon",
    "sg:classifiers":[
        {
            "category":"Real Estate",
            "subcategory":"Real Estate Operator",
            "type":"Services"
        }
    ],
    "sg:phone":"+1 609 641 2233",
    "sg:postcode":"08205",
    "sg:province":"NJ",
    "sg:tags":[
        "apartment"
    ],
    "wof:name":"Pinnacle Apartments",
    "wof:placetype":"venue"
},
  "geometry": {"coordinates":[-74.50637,39.482457],"type":"Point"}
}