{
  "type": "Feature",
  "properties": {
    "addr:full":"622 Gravelly Hollow Rd Medford NJ 08055",
    "addr:housenumber":"622",
    "addr:postcode":"08055",
    "addr:street":"Gravelly Hollow Rd",
    "iso:country":"US",
    "sg:address":"622 Gravelly Hollow Rd",
    "sg:city":"Medford",
    "sg:classifiers":[
        {
            "category":"Retail",
            "subcategory":"Repair Shop",
            "type":"Services"
        },
        {
            "category":"Home & Garden",
            "subcategory":"Garden Supply",
            "type":"Retail Goods"
        }
    ],
    "sg:phone":"+1 609 654 0955",
    "sg:postcode":"08055",
    "sg:province":"NJ",
    "sg:tags":[
        "lawn",
        "merchandise",
        "mower"
    ],
    "wof:name":"Robey's Lawn Mower Repair",
    "wof:placetype":"venue"
},
  "geometry": {"coordinates":[-74.82049499999999,39.842568],"type":"Point"}
}