{
  "type": "Feature",
  "properties": {
    "iso:country":"US",
    "sg:address":"99 Crusher Rd",
    "sg:city":"Hopewell",
    "sg:classifiers":[
        {
            "category":"Building & Trades",
            "subcategory":"Construction",
            "type":"Services"
        }
    ],
    "sg:phone":"+1 609 466 9529",
    "sg:postcode":"08525",
    "sg:province":"NJ",
    "sg:tags":[
        "excavating",
        "contractor"
    ],
    "wof:name":"Travis Wagner Backhoe Svc",
    "wof:placetype":"venue"
},
  "geometry": {"coordinates":[-74.759316,40.374386],"type":"Point"}
}