{
  "type": "Feature",
  "properties": {
    "addr:full":"83 Hauxhurst Ave Weehawken NJ 07086",
    "addr:housenumber":"83",
    "addr:postcode":"07086",
    "addr:street":"Hauxhurst Ave",
    "iso:country":"US",
    "sg:address":"83 Hauxhurst Ave",
    "sg:city":"Weehawken",
    "sg:classifiers":[
        {
            "category":"Banks & Credit Unions",
            "subcategory":"Bank",
            "type":"Services"
        }
    ],
    "sg:phone":"+1   ",
    "sg:postcode":"07086",
    "sg:province":"NJ",
    "sg:tags":[
        "depository",
        "banking"
    ],
    "wof:name":"La Belle Epoche Inc",
    "wof:placetype":"venue"
},
  "geometry": {"coordinates":[-74.022318,40.770101],"type":"Point"}
}