{
  "type": "Feature",
  "properties": {
    "iso:country":"US",
    "sg:address":"150 7th St",
    "sg:city":"Clifton",
    "sg:classifiers":[
        {
            "category":"Building & Trades",
            "subcategory":"Locksmith",
            "type":"Services"
        }
    ],
    "sg:phone":"+1 866 382 7023",
    "sg:postcode":"07011",
    "sg:province":"NJ",
    "sg:tags":[
        "key"
    ],
    "wof:name":"0 0 0 0 1 Hour Emergency Locksmith",
    "wof:placetype":"venue"
},
  "geometry": {"coordinates":[-74.155681,40.877794],"type":"Point"}
}