{
  "type": "Feature",
  "properties": {
    "iso:country":"US",
    "sg:address":"7 Briarwood Ct",
    "sg:city":"West Berlin",
    "sg:classifiers":[
        {
            "category":"Building & Trades",
            "subcategory":"Construction",
            "type":"Services"
        }
    ],
    "sg:phone":"+1 856 753 7080",
    "sg:postcode":"08091",
    "sg:province":"NJ",
    "sg:tags":[
        "hanging",
        "contractor"
    ],
    "wof:name":"Jims Painting",
    "wof:placetype":"venue"
},
  "geometry": {"coordinates":[-74.915735,39.799321],"type":"Point"}
}