{
  "type": "Feature",
  "properties": {
    "iso:country":"US",
    "sg:address":"315 Sherman Ave",
    "sg:city":"Teaneck",
    "sg:classifiers":[
        {
            "category":"Building & Trades",
            "subcategory":"Electrical",
            "type":"Services"
        }
    ],
    "sg:phone":"+1 201 358 9383",
    "sg:postcode":"07666",
    "sg:province":"NJ",
    "sg:tags":[
        "electric",
        "contractor"
    ],
    "wof:name":"NAF Electric & Security Corp",
    "wof:placetype":"venue"
},
  "geometry": {"coordinates":[-74.021393,40.883222],"type":"Point"}
}