{
  "type": "Feature",
  "properties": {
    "addr:full":"315 Broadway Passaic NJ 07055",
    "addr:housenumber":"315",
    "addr:postcode":"07055",
    "addr:street":"Broadway",
    "iso:country":"US",
    "sg:address":"315 Broadway",
    "sg:city":"Passaic",
    "sg:classifiers":[
        {
            "category":"Restaurant",
            "type":"Food & Drink"
        }
    ],
    "sg:phone":"+1   ",
    "sg:postcode":"07055",
    "sg:province":"NJ",
    "sg:tags":[
        "eating"
    ],
    "wof:name":"Herencia Azteca Restaurant",
    "wof:placetype":"venue"
},
  "geometry": {"coordinates":[-74.136205,40.855755],"type":"Point"}
}