{
  "type": "Feature",
  "properties": {
    "iso:country":"US",
    "sg:address":"340 US Hwy 46",
    "sg:city":"Dover",
    "sg:classifiers":[
        {
            "category":"Banks & Credit Unions",
            "subcategory":"Bank",
            "type":"Services"
        }
    ],
    "sg:phone":"+1 973 328 6289",
    "sg:postcode":"07801",
    "sg:province":"NJ",
    "sg:website":"www.firstmorris.com",
    "wof:name":"First Morris Bank",
    "wof:placetype":"venue"
},
  "geometry": {"coordinates":[-74.570807,40.886057],"type":"Point"}
}