{
  "type": "Feature",
  "properties": {
    "addr:full":"27 Newark Pompton Tpke Little Falls NJ 07424",
    "addr:housenumber":"27",
    "addr:postcode":"07424",
    "addr:street":"Newark Pompton Tpke",
    "iso:country":"US",
    "sg:address":"27 Newark Pompton Tpke",
    "sg:city":"Little Falls",
    "sg:classifiers":[
        {
            "category":"Retail",
            "subcategory":"Repair Shop",
            "type":"Services"
        }
    ],
    "sg:phone":"+1 973 854 5307",
    "sg:postcode":"07424",
    "sg:province":"NJ",
    "sg:tags":[
        "lock",
        "key",
        "locksmith"
    ],
    "wof:name":"0 1 All Day A Emergency Locksmith",
    "wof:placetype":"venue"
},
  "geometry": {"coordinates":[-74.245767,40.886051],"type":"Point"}
}