{
  "type": "Feature",
  "properties": {
    "iso:country":"US",
    "sg:address":"561 N East Blvd",
    "sg:city":"Vineland",
    "sg:classifiers":[
        {
            "category":"Professional",
            "type":"Services"
        }
    ],
    "sg:phone":"+1 856 692 1543",
    "sg:postcode":"08360",
    "sg:province":"NJ",
    "sg:tags":[
        "establishment"
    ],
    "wof:name":"Secundino Rordriguez",
    "wof:placetype":"venue"
},
  "geometry": {"coordinates":[-75.02479,39.499514],"type":"Point"}
}