{
  "type": "Feature",
  "properties": {
    "iso:country":"US",
    "sg:address":"997 Lenox Dr",
    "sg:city":"Trenton",
    "sg:classifiers":[
        {
            "category":"Professional",
            "subcategory":"Lawyer & Legal Services",
            "type":"Services"
        }
    ],
    "sg:phone":"+1 609 895 3333",
    "sg:postcode":"08648",
    "sg:province":"NJ",
    "wof:name":"Elaine C Britt",
    "wof:placetype":"venue"
},
  "geometry": {"coordinates":[-74.705158,40.287796],"type":"Point"}
}