{
  "type": "Feature",
  "properties": {
    "iso:country":"US",
    "sg:address":"55 Princeton Hightstown Rd",
    "sg:city":"Princeton Junction",
    "sg:classifiers":[
        {
            "category":"Professional",
            "subcategory":"Computer Services",
            "type":"Services"
        }
    ],
    "sg:phone":"+1 609 750 9881",
    "sg:postcode":"08550",
    "sg:province":"NJ",
    "sg:tags":[
        "development",
        "software"
    ],
    "wof:name":"Trade Management Services Inc",
    "wof:placetype":"venue"
},
  "geometry": {"coordinates":[-74.619985,40.316333],"type":"Point"}
}