{
  "type": "Feature",
  "properties": {
    "iso:country":"US",
    "sg:address":"217 Mulberry St",
    "sg:city":"Newark",
    "sg:classifiers":[
        {
            "category":"Building & Trades",
            "subcategory":"Construction",
            "type":"Services"
        }
    ],
    "sg:phone":"+1 973 242 4862",
    "sg:postcode":"07102",
    "sg:province":"NJ",
    "sg:tags":[
        "general",
        "contractor"
    ],
    "wof:name":"Central One Construction",
    "wof:placetype":"venue"
},
  "geometry": {"coordinates":[-74.170843,40.732184],"type":"Point"}
}