{
  "type": "Feature",
  "properties": {
    "iso:country":"US",
    "sg:address":"102 Walnut St",
    "sg:city":"Neptune",
    "sg:classifiers":[
        {
            "category":"Organizations",
            "subcategory":"Religious Organization",
            "type":"Services"
        }
    ],
    "sg:phone":"+1 732 774 6748",
    "sg:postcode":"07753",
    "sg:province":"NJ",
    "sg:tags":[
        "church"
    ],
    "wof:name":"Neptune West Grove Untd Mthdst",
    "wof:placetype":"venue"
},
  "geometry": {"coordinates":[-74.047269,40.206606],"type":"Point"}
}