{
  "type": "Feature",
  "properties": {
    "iso:country":"US",
    "sg:address":"132 Crescent Ave",
    "sg:city":"Wyckoff",
    "sg:classifiers":[
        {
            "category":"Professional",
            "type":"Services"
        }
    ],
    "sg:phone":"+1   ",
    "sg:postcode":"07481",
    "sg:province":"NJ",
    "wof:name":"Barbaras Maid Service Inc",
    "wof:placetype":"venue"
},
  "geometry": {"coordinates":[-74.155821,41.008283],"type":"Point"}
}