{
  "type": "Feature",
  "properties": {
    "addr:full":"231 Riverside Sq Hackensack NJ 07601",
    "addr:housenumber":"231",
    "addr:postcode":"07601",
    "addr:street":"Riverside Sq",
    "iso:country":"US",
    "sg:address":"231 Riverside Sq",
    "sg:city":"Hackensack",
    "sg:classifiers":[
        {
            "category":"Shopping",
            "subcategory":"Department Store",
            "type":"Retail Goods"
        }
    ],
    "sg:phone":"+1 201 498 0883",
    "sg:postcode":"07601",
    "sg:province":"NJ",
    "wof:name":"Talbots",
    "wof:placetype":"venue"
},
  "geometry": {"coordinates":[-74.031277,40.907577],"type":"Point"}
}