{
  "type": "Feature",
  "properties": {
    "addr:full":"258 E Grand Ave Rahway NJ 07065",
    "addr:housenumber":"258",
    "addr:postcode":"07065",
    "addr:street":"E Grand Ave",
    "iso:country":"US",
    "sg:address":"258 E Grand Ave",
    "sg:city":"Rahway",
    "sg:classifiers":[
        {
            "category":"Personal",
            "subcategory":"Barber",
            "type":"Services"
        }
    ],
    "sg:phone":"+1 732 499 8448",
    "sg:postcode":"07065",
    "sg:province":"NJ",
    "sg:tags":[
        "shop"
    ],
    "wof:name":"Royal Barber Shop",
    "wof:placetype":"venue"
},
  "geometry": {"coordinates":[-74.267966,40.60922],"type":"Point"}
}