{
  "type": "Feature",
  "properties": {
    "iso:country":"US",
    "sg:address":"317 Main St",
    "sg:city":"Bradley Beach",
    "sg:classifiers":[
        {
            "category":"Organizations",
            "subcategory":"Community Association",
            "type":"Services"
        }
    ],
    "sg:phone":"+1   ",
    "sg:postcode":"07720",
    "sg:province":"NJ",
    "wof:name":"Home Owners Choice",
    "wof:placetype":"venue"
},
  "geometry": {"coordinates":[-74.018821,40.200917],"type":"Point"}
}