{
  "type": "Feature",
  "properties": {
    "iso:country":"US",
    "sg:address":"3016 US Hwy 9",
    "sg:city":"Ocean View",
    "sg:classifiers":[
        {
            "category":"Personal",
            "subcategory":"Beauty Salon",
            "type":"Services"
        }
    ],
    "sg:phone":"+1 609 624 3161",
    "sg:postcode":"08230",
    "sg:province":"NJ",
    "wof:name":"Dannyrose Hair Salon",
    "wof:placetype":"venue"
},
  "geometry": {"coordinates":[-74.705527,39.206627],"type":"Point"}
}