{
  "type": "Feature",
  "properties": {
    "addr:full":"2807 Green Hollow Dr Iselin NJ 08830",
    "addr:housenumber":"2807",
    "addr:postcode":"08830",
    "addr:street":"Green Hollow Dr",
    "iso:country":"US",
    "sg:address":"2807 Green Hollow Dr",
    "sg:city":"Iselin",
    "sg:classifiers":[
        {
            "category":"Professional",
            "subcategory":"Business Services",
            "type":"Services"
        }
    ],
    "sg:phone":"+1   ",
    "sg:postcode":"08830",
    "sg:province":"NJ",
    "wof:name":"Algologix Inc",
    "wof:placetype":"venue"
},
  "geometry": {"coordinates":[-74.30739,40.565134],"type":"Point"}
}