{
  "type": "Feature",
  "properties": {
    "addr:full":"339 Elizabeth Ave Elizabeth NJ 07206",
    "addr:housenumber":"339",
    "addr:postcode":"07206",
    "addr:street":"Elizabeth Ave",
    "iso:country":"US",
    "sg:address":"339 Elizabeth Ave",
    "sg:city":"Elizabeth",
    "sg:classifiers":[
        {
            "category":"Personal",
            "subcategory":"Beauty Salon",
            "type":"Services"
        }
    ],
    "sg:phone":"+1 908 355 1002",
    "sg:postcode":"07206",
    "sg:province":"NJ",
    "sg:tags":[
        "hair"
    ],
    "wof:name":"Peters Hair Styling",
    "wof:placetype":"venue"
},
  "geometry": {"coordinates":[-74.195525,40.651617],"type":"Point"}
}