{
  "type": "Feature",
  "properties": {
    "iso:country":"US",
    "sg:address":"135 Stiles Pl",
    "sg:city":"Freehold",
    "sg:classifiers":[
        {
            "category":"Professional",
            "subcategory":"Management & Consulting",
            "type":"Services"
        }
    ],
    "sg:phone":"+1 732 761 2488",
    "sg:postcode":"07728",
    "sg:province":"NJ",
    "sg:tags":[
        "marketing",
        "program"
    ],
    "wof:name":"Netrix Marketing",
    "wof:placetype":"venue"
},
  "geometry": {"coordinates":[-74.29670900000001,40.239459],"type":"Point"}
}