{
  "type": "Feature",
  "properties": {
    "addr:full":"35 Beaverson Blvd Ste 5A Brick NJ 08723",
    "addr:housenumber":"35",
    "addr:postcode":"08723",
    "addr:street":"Beaverson Blvd Ste 5A",
    "iso:country":"US",
    "sg:address":"35 Beaverson Blvd Ste 5A",
    "sg:city":"Brick",
    "sg:classifiers":[
        {
            "category":"Professional",
            "subcategory":"Lawyer & Legal Services",
            "type":"Services"
        }
    ],
    "sg:phone":"+1 732 920 9000",
    "sg:postcode":"08723",
    "sg:province":"NJ",
    "sg:tags":[
        "attorney",
        "law",
        "family",
        "divorce",
        "wills",
        "practice",
        "business",
        "elder",
        "planning",
        "real estate",
        "trust",
        "bankruptcy"
    ],
    "sg:website":"http://www.pllucaslaw.com",
    "wof:name":"Phillip L. Lucas Attorney at Law",
    "wof:placetype":"venue"
},
  "geometry": {"coordinates":[-74.14579500000001,40.032424],"type":"Point"}
}