{
  "type": "Feature",
  "properties": {
    "iso:country":"US",
    "sg:address":"515 E Atlantic Blvd",
    "sg:city":"Ocean City",
    "sg:classifiers":[
        {
            "category":"Wholesale",
            "subcategory":"Durable Goods & Equipment",
            "type":"Manufacturing & Wholesale Goods"
        }
    ],
    "sg:phone":"+1 609 398 4622",
    "sg:postcode":"08226",
    "sg:province":"NJ",
    "sg:tags":[
        "professional"
    ],
    "wof:name":"Wright & Wright",
    "wof:placetype":"venue"
},
  "geometry": {"coordinates":[-74.55766800000001,39.292702],"type":"Point"}
}