{
  "type": "Feature",
  "properties": {
    "addr:full":"20 Brick Blvd Brick NJ 08723",
    "addr:housenumber":"20",
    "addr:postcode":"08723",
    "addr:street":"Brick Blvd",
    "iso:country":"US",
    "sg:address":"20 Brick Blvd",
    "sg:city":"Brick",
    "sg:classifiers":[
        {
            "category":"Shopping",
            "subcategory":"Optical Goods",
            "type":"Retail Goods"
        }
    ],
    "sg:phone":"+1   ",
    "sg:postcode":"08723",
    "sg:province":"NJ",
    "wof:name":"Sight Saver",
    "wof:placetype":"venue"
},
  "geometry": {"coordinates":[-74.144611,40.020613],"type":"Point"}
}