{
  "type": "Feature",
  "properties": {
    "iso:country":"US",
    "sg:address":"114 N High St",
    "sg:city":"Millville",
    "sg:classifiers":[
        {
            "category":"Shopping",
            "subcategory":"Used Merchandise",
            "type":"Retail Goods"
        }
    ],
    "sg:phone":"+1 856 825 3334",
    "sg:postcode":"08332",
    "sg:province":"NJ",
    "sg:tags":[
        "antique"
    ],
    "wof:name":"Roaring Lion",
    "wof:placetype":"venue"
},
  "geometry": {"coordinates":[-75.038543,39.397137],"type":"Point"}
}