{
  "type": "Feature",
  "properties": {
    "addr:full":"3510 Asbury Ave Neptune NJ 07753",
    "addr:housenumber":"3510",
    "addr:postcode":"07753",
    "addr:street":"Asbury Ave",
    "iso:country":"US",
    "sg:address":"3510 Asbury Ave",
    "sg:city":"Neptune",
    "sg:classifiers":[
        {
            "category":"Building & Trades",
            "subcategory":"Construction",
            "type":"Services"
        }
    ],
    "sg:phone":"+1 732 643 9000",
    "sg:postcode":"07753",
    "sg:province":"NJ",
    "sg:tags":[
        "custom",
        "residential",
        "builder",
        "general",
        "home",
        "contractor"
    ],
    "wof:name":"Casabella Builders Inc",
    "wof:placetype":"venue"
},
  "geometry": {"coordinates":[-74.071427,40.232909],"type":"Point"}
}