{
  "type": "Feature",
  "properties": {
    "iso:country":"US",
    "sg:address":"175 Mountainview Ave",
    "sg:city":"Scotch Plains",
    "sg:classifiers":[
        {
            "category":"Professional",
            "subcategory":"Computer Services",
            "type":"Services"
        }
    ],
    "sg:phone":"+1   ",
    "sg:postcode":"07076",
    "sg:province":"NJ",
    "sg:tags":[
        "programing",
        "custom"
    ],
    "wof:name":"Century Software Inc",
    "wof:placetype":"venue"
},
  "geometry": {"coordinates":[-74.393249,40.662391],"type":"Point"}
}