{
  "type": "Feature",
  "properties": {
    "addr:full":"780 Salem Ave Elizabeth NJ 07208",
    "addr:housenumber":"780",
    "addr:postcode":"07208",
    "addr:street":"Salem Ave",
    "iso:country":"US",
    "sg:address":"780 Salem Ave",
    "sg:city":"Elizabeth",
    "sg:classifiers":[
        {
            "category":"Organizations",
            "subcategory":"Religious Organization",
            "type":"Services"
        }
    ],
    "sg:phone":"+1 908 352 5827",
    "sg:postcode":"07208",
    "sg:province":"NJ",
    "sg:tags":[
        "church"
    ],
    "wof:name":"Third Westminster Presbyterian",
    "wof:placetype":"venue"
},
  "geometry": {"coordinates":[-74.217073,40.681017],"type":"Point"}
}