{
  "type": "Feature",
  "properties": {
    "addr:full":"10 Furler St Totowa NJ 07512",
    "addr:housenumber":"10",
    "addr:postcode":"07512",
    "addr:street":"Furler St",
    "iso:country":"US",
    "sg:address":"10 Furler St",
    "sg:city":"Totowa",
    "sg:classifiers":[
        {
            "category":"Professional",
            "subcategory":"Lawyer & Legal Services",
            "type":"Services"
        }
    ],
    "sg:phone":"+1 973 785 9522",
    "sg:postcode":"07512",
    "sg:province":"NJ",
    "wof:name":"Bavagnoli Ronald C Attorney At Law",
    "wof:placetype":"venue"
},
  "geometry": {"coordinates":[-74.224701,40.895199],"type":"Point"}
}