{
  "type": "Feature",
  "properties": {
    "iso:country":"US",
    "sg:address":"322 Anderson Ave",
    "sg:city":"Fairview",
    "sg:classifiers":[
        {
            "category":"Building & Trades",
            "subcategory":"Cleaning & Sanitation",
            "type":"Services"
        }
    ],
    "sg:phone":"+1   ",
    "sg:postcode":"07022",
    "sg:province":"NJ",
    "sg:tags":[
        "maintenance"
    ],
    "wof:name":"Mr Cleaning Service",
    "wof:placetype":"venue"
},
  "geometry": {"coordinates":[-73.99431,40.816794],"type":"Point"}
}