{
  "type": "Feature",
  "properties": {
    "iso:country":"US",
    "sg:address":"353 Hamilton Blvd",
    "sg:city":"Piscataway",
    "sg:classifiers":[
        {
            "category":"Shopping",
            "subcategory":"Computers & Home Electronics",
            "type":"Retail Goods"
        }
    ],
    "sg:phone":"+1   ",
    "sg:postcode":"08854",
    "sg:province":"NJ",
    "wof:name":"Telnet Computer Inc",
    "wof:placetype":"venue"
},
  "geometry": {"coordinates":[-74.468186,40.56748],"type":"Point"}
}