{
  "type": "Feature",
  "properties": {
    "addr:full":"2131 Asbury Ave Ocean City NJ 08226",
    "addr:housenumber":"2131",
    "addr:postcode":"08226",
    "addr:street":"Asbury Ave",
    "iso:country":"US",
    "sg:address":"2131 Asbury Ave",
    "sg:city":"Ocean City",
    "sg:classifiers":[
        {
            "category":"Insurance",
            "subcategory":"Insurance Agent",
            "type":"Services"
        }
    ],
    "sg:phone":"+1 609 399 0060",
    "sg:postcode":"08226",
    "sg:province":"NJ",
    "sg:website":"www.mcmahonagency.com",
    "wof:name":"Mc Mahon Agency Inc",
    "wof:placetype":"venue"
},
  "geometry": {"coordinates":[-74.593889,39.26577],"type":"Point"}
}