{
  "type": "Feature",
  "properties": {
    "iso:country":"US",
    "sg:address":"9 Ackerman Ave",
    "sg:city":"Emerson",
    "sg:classifiers":[
        {
            "category":"Home & Garden",
            "subcategory":"Home Furnishings",
            "type":"Retail Goods"
        }
    ],
    "sg:phone":"+1   ",
    "sg:postcode":"07630",
    "sg:province":"NJ",
    "wof:name":"Elegant Window Fashion Inc",
    "wof:placetype":"venue"
},
  "geometry": {"coordinates":[-74.02856,40.974419],"type":"Point"}
}