{
  "type": "Feature",
  "properties": {
    "addr:full":"282 Newark Ave Jersey City NJ 07302",
    "addr:housenumber":"282",
    "addr:postcode":"07302",
    "addr:street":"Newark Ave",
    "iso:country":"US",
    "sg:address":"282 Newark Ave",
    "sg:city":"Jersey City",
    "sg:classifiers":[
        {
            "category":"Freight",
            "type":"Transportation"
        }
    ],
    "sg:phone":"+1 201 386 5550",
    "sg:postcode":"07302",
    "sg:province":"NJ",
    "sg:tags":[
        "mover"
    ],
    "wof:name":"Guaranteed Price Moving Llc",
    "wof:placetype":"venue"
},
  "geometry": {"coordinates":[-74.049623,40.723639],"type":"Point"}
}