{
  "type": "Feature",
  "properties": {
    "addr:full":"320 Broad St Red Bank NJ 07701",
    "addr:housenumber":"320",
    "addr:postcode":"07701",
    "addr:street":"Broad St",
    "iso:country":"US",
    "sg:address":"320 Broad St",
    "sg:city":"Red Bank",
    "sg:classifiers":[
        {
            "category":"Home & Garden",
            "subcategory":"Home Furnishings",
            "type":"Retail Goods"
        }
    ],
    "sg:phone":"+1   ",
    "sg:postcode":"07701",
    "sg:province":"NJ",
    "sg:tags":[
        "linen",
        "bedding",
        "bath",
        "accessory"
    ],
    "wof:name":"Linens n Things",
    "wof:placetype":"venue"
},
  "geometry": {"coordinates":[-74.06413499999999,40.341186],"type":"Point"}
}