{
  "type": "Feature",
  "properties": {
    "addr:full":"16 Valley View Rd Morristown NJ 07960",
    "addr:housenumber":"16",
    "addr:postcode":"07960",
    "addr:street":"Valley View Rd",
    "iso:country":"US",
    "sg:address":"16 Valley View Rd",
    "sg:city":"Morristown",
    "sg:classifiers":[
        {
            "category":"Professional",
            "subcategory":"Computer Services",
            "type":"Services"
        }
    ],
    "sg:phone":"+1   ",
    "sg:postcode":"07960",
    "sg:province":"NJ",
    "sg:tags":[
        "related",
        "programing",
        "custom"
    ],
    "wof:name":"Microcomputer Systems Corp",
    "wof:placetype":"venue"
},
  "geometry": {"coordinates":[-74.518305,40.788487],"type":"Point"}
}