{
  "type": "Feature",
  "properties": {
    "addr:full":"111 S Black Horse Pike Williamstown NJ 08094",
    "addr:housenumber":"111",
    "addr:postcode":"08094",
    "addr:street":"S Black Horse Pike",
    "iso:country":"US",
    "sg:address":"111 S Black Horse Pike",
    "sg:city":"Williamstown",
    "sg:classifiers":[
        {
            "category":"Professional",
            "type":"Services"
        }
    ],
    "sg:phone":"+1 856 875 2592",
    "sg:postcode":"08094",
    "sg:province":"NJ",
    "sg:tags":[
        "establishment"
    ],
    "wof:name":"Dollarland",
    "wof:placetype":"venue"
},
  "geometry": {"coordinates":[-74.990968,39.687219],"type":"Point"}
}