{
  "type": "Feature",
  "properties": {
    "addr:full":"3 Zeliff Ave Little Falls NJ 07424",
    "addr:housenumber":"3",
    "addr:postcode":"07424",
    "addr:street":"Zeliff Ave",
    "iso:country":"US",
    "sg:address":"3 Zeliff Ave",
    "sg:city":"Little Falls",
    "sg:classifiers":[
        {
            "category":"Shopping",
            "subcategory":"Computers & Home Electronics",
            "type":"Retail Goods"
        }
    ],
    "sg:phone":"+1 973 812 2499",
    "sg:postcode":"07424",
    "sg:province":"NJ",
    "sg:tags":[
        "publishing"
    ],
    "wof:name":"Genesis Graphics",
    "wof:placetype":"venue"
},
  "geometry": {"coordinates":[-74.242662,40.886753],"type":"Point"}
}