{
  "type": "Feature",
  "properties": {
    "addr:full":"1 Smith St Perth Amboy NJ 08861",
    "addr:housenumber":"1",
    "addr:postcode":"08861",
    "addr:street":"Smith St",
    "iso:country":"US",
    "sg:address":"1 Smith St",
    "sg:city":"Perth Amboy",
    "sg:classifiers":[
        {
            "category":"Restaurant",
            "type":"Food & Drink"
        }
    ],
    "sg:phone":"+1 732 442 5766",
    "sg:postcode":"08861",
    "sg:province":"NJ",
    "wof:name":"Mo Bay Jamaican Restaurant",
    "wof:placetype":"venue"
},
  "geometry": {"coordinates":[-74.26224999999999,40.506994],"type":"Point"}
}