{
  "type": "Feature",
  "properties": {
    "addr:full":"808 South Ave W Westfield NJ 07090",
    "addr:housenumber":"808",
    "addr:postcode":"07090",
    "addr:street":"South Ave W",
    "iso:country":"US",
    "sg:address":"808 South Ave W",
    "sg:city":"Westfield",
    "sg:classifiers":[
        {
            "category":"Real Estate",
            "subcategory":"Real Estate Services",
            "type":"Services"
        }
    ],
    "sg:phone":"+1 908 232 2116",
    "sg:postcode":"07090",
    "sg:province":"NJ",
    "sg:tags":[
        "company",
        "title"
    ],
    "wof:name":"Suburban Title Examiners",
    "wof:placetype":"venue"
},
  "geometry": {"coordinates":[-74.356386,40.647373],"type":"Point"}
}