{
  "type": "Feature",
  "properties": {
    "iso:country":"US",
    "sg:address":"170 Kinnelon Rd",
    "sg:city":"Butler",
    "sg:classifiers":[
        {
            "category":"Health Services",
            "subcategory":"Medical Lab",
            "type":"Services"
        }
    ],
    "sg:phone":"+1 973 492 9700",
    "sg:postcode":"07405",
    "sg:province":"NJ",
    "sg:tags":[
        "specializing",
        "laboratory",
        "dental",
        "crown",
        "bridgework"
    ],
    "wof:name":"Lakeland Dental Studios Inc",
    "wof:placetype":"venue"
},
  "geometry": {"coordinates":[-74.384738,40.989068],"type":"Point"}
}