{
  "type": "Feature",
  "properties": {
    "addr:full":"850 Gates Ave Piscataway NJ 08854",
    "addr:housenumber":"850",
    "addr:postcode":"08854",
    "addr:street":"Gates Ave",
    "iso:country":"US",
    "sg:address":"850 Gates Ave",
    "sg:city":"Piscataway",
    "sg:classifiers":[
        {
            "category":"Building & Trades",
            "subcategory":"Construction",
            "type":"Services"
        }
    ],
    "sg:phone":"+1 732 463 1016",
    "sg:postcode":"08854",
    "sg:province":"NJ",
    "sg:tags":[
        "carpentry"
    ],
    "wof:name":"JB Construction",
    "wof:placetype":"venue"
},
  "geometry": {"coordinates":[-74.465945,40.531326],"type":"Point"}
}