{
  "type": "Feature",
  "properties": {
    "iso:country":"US",
    "sg:address":"42 Colonial Dr",
    "sg:city":"Piscataway",
    "sg:classifiers":[
        {
            "category":"Wholesale",
            "subcategory":"Machinery & Supplies",
            "type":"Manufacturing & Wholesale Goods"
        }
    ],
    "sg:phone":"+1 732 981 9300",
    "sg:postcode":"08854",
    "sg:province":"NJ",
    "sg:tags":[
        "industrial"
    ],
    "wof:name":"J M Fry Printing Inks",
    "wof:placetype":"venue"
},
  "geometry": {"coordinates":[-74.463038,40.553081],"type":"Point"}
}