{
  "type": "Feature",
  "properties": {
    "addr:full":"6917 US Hwy 130 Pennsauken NJ 08110",
    "addr:housenumber":"6917",
    "addr:postcode":"08110",
    "addr:street":"Us Hwy 130",
    "iso:country":"US",
    "sg:address":"6917 US Hwy 130",
    "sg:city":"Pennsauken",
    "sg:classifiers":[
        {
            "category":"Retail",
            "subcategory":"Auto Repair",
            "type":"Services"
        }
    ],
    "sg:phone":"+1 856 662 1140",
    "sg:postcode":"08110",
    "sg:province":"NJ",
    "sg:tags":[
        "automobile",
        "lubrication"
    ],
    "wof:name":"Valvoline Instant Oil Change",
    "wof:placetype":"venue"
},
  "geometry": {"coordinates":[-75.07856200000001,39.935954],"type":"Point"}
}