{
  "type": "Feature",
  "properties": {
    "iso:country":"US",
    "sg:address":"2775 State Route 23",
    "sg:city":"West Milford",
    "sg:classifiers":[
        {
            "category":"Retail",
            "subcategory":"Auto Repair",
            "type":"Services"
        }
    ],
    "sg:phone":"+1 973 208 3232",
    "sg:postcode":"07480",
    "sg:province":"NJ",
    "wof:name":"Ac Automotive",
    "wof:placetype":"venue"
},
  "geometry": {"coordinates":[-74.440911,41.04791],"type":"Point"}
}