{
  "type": "Feature",
  "properties": {
    "iso:country":"US",
    "sg:address":"1302 Laurel Oak Rd",
    "sg:city":"Voorhees",
    "sg:classifiers":[
        {
            "category":"Health Services",
            "subcategory":"Nursing And Care Facility",
            "type":"Services"
        }
    ],
    "sg:phone":"+1 856 346 1200",
    "sg:postcode":"08043",
    "sg:province":"NJ",
    "sg:tags":[
        "home",
        "convalescent"
    ],
    "wof:name":"Lakewood Of Voorhees",
    "wof:placetype":"venue"
},
  "geometry": {"coordinates":[-74.969036,39.850253],"type":"Point"}
}