{
  "type": "Feature",
  "properties": {
    "addr:full":"1819 Springdale Rd Cherry Hill NJ 08003",
    "addr:housenumber":"1819",
    "addr:postcode":"08003",
    "addr:street":"Springdale Rd",
    "iso:country":"US",
    "sg:address":"1819 Springdale Rd",
    "sg:city":"Cherry Hill",
    "sg:classifiers":[
        {
            "category":"Food & Beverages",
            "subcategory":"Groceries & Convenience Stores",
            "type":"Retail Goods"
        }
    ],
    "sg:phone":"+1 856 424 9749",
    "sg:postcode":"08003",
    "sg:province":"NJ",
    "wof:name":"Friendly Food Mart",
    "wof:placetype":"venue"
},
  "geometry": {"coordinates":[-74.96673800000001,39.90297],"type":"Point"}
}