{
  "type": "Feature",
  "properties": {
    "addr:full":"495 Prospect Ave Ste 15 West Orange NJ 07052",
    "addr:housenumber":"495",
    "addr:postcode":"07052",
    "addr:street":"Prospect Ave Ste 15",
    "iso:country":"US",
    "sg:address":"495 Prospect Ave Ste 15",
    "sg:city":"West Orange",
    "sg:classifiers":[
        {
            "category":"Shopping",
            "subcategory":"Mobile Phones",
            "type":"Retail Goods"
        },
        {
            "category":"Wholesale",
            "subcategory":"Computers",
            "type":"Manufacturing & Wholesale Goods"
        }
    ],
    "sg:phone":"+1 973 731 4451",
    "sg:postcode":"07052",
    "sg:province":"NJ",
    "wof:name":"Radioshack",
    "wof:placetype":"venue"
},
  "geometry": {"coordinates":[-74.25488,40.791034],"type":"Point"}
}