{
  "type": "Feature",
  "properties": {
    "addr:full":"103 College Rd E Princeton NJ 08540",
    "addr:housenumber":"103",
    "addr:postcode":"08540",
    "addr:street":"College Rd E",
    "iso:country":"US",
    "sg:address":"103 College Rd E",
    "sg:city":"Princeton",
    "sg:classifiers":[
        {
            "category":"Education",
            "subcategory":"Special Training",
            "type":"Public Place"
        }
    ],
    "sg:phone":"+1 609 720 0237",
    "sg:postcode":"08540",
    "sg:province":"NJ",
    "sg:tags":[
        "educational"
    ],
    "wof:name":"New Jersey Educational",
    "wof:placetype":"venue"
},
  "geometry": {"coordinates":[-74.606602,40.35695],"type":"Point"}
}