{
  "type": "Feature",
  "properties": {
    "iso:country":"US",
    "sg:address":"221 Eyland Ave",
    "sg:city":"Succasunna",
    "sg:classifiers":[
        {
            "category":"Building & Trades",
            "subcategory":"Construction",
            "type":"Services"
        }
    ],
    "sg:phone":"+1 973 663 4103",
    "sg:postcode":"07876",
    "sg:province":"NJ",
    "sg:tags":[
        "equipment",
        "installing"
    ],
    "wof:name":"Hopatcong Rigging Inc",
    "wof:placetype":"venue"
},
  "geometry": {"coordinates":[-74.662424,40.84941],"type":"Point"}
}