{
  "type": "Feature",
  "properties": {
    "addr:full":"1574 Reed Rd Pennington NJ 08534",
    "addr:housenumber":"1574",
    "addr:postcode":"08534",
    "addr:street":"Reed Rd",
    "iso:country":"US",
    "sg:address":"1574 Reed Rd",
    "sg:city":"Pennington",
    "sg:classifiers":[
        {
            "category":"Professional",
            "subcategory":"Business Services",
            "type":"Services"
        }
    ],
    "sg:phone":"+1 215 355 5422",
    "sg:postcode":"08534",
    "sg:province":"NJ",
    "sg:tags":[
        "microfilm",
        "furniture"
    ],
    "sg:website":"www.cbs-nj.com",
    "wof:name":"County Business Systems Inc",
    "wof:placetype":"venue"
},
  "geometry": {"coordinates":[-74.797134,40.293592],"type":"Point"}
}