{
  "type": "Feature",
  "properties": {
    "addr:full":"1 Columbia Ave Cliffside Park NJ 07010",
    "addr:housenumber":"1",
    "addr:postcode":"07010",
    "addr:street":"Columbia Ave",
    "iso:country":"US",
    "sg:address":"1 Columbia Ave",
    "sg:city":"Cliffside Park",
    "sg:classifiers":[
        {
            "category":"Restaurant",
            "type":"Food & Drink"
        }
    ],
    "sg:phone":"+1   ",
    "sg:postcode":"07010",
    "sg:province":"NJ",
    "sg:tags":[
        "eating"
    ],
    "wof:name":"China Moon Restaurant Inc",
    "wof:placetype":"venue"
},
  "geometry": {"coordinates":[-73.9808,40.82333],"type":"Point"}
}