{
  "type": "Feature",
  "properties": {
    "addr:full":"99 Beauvoir Ave Summit NJ 07901",
    "addr:housenumber":"99",
    "addr:postcode":"07901",
    "addr:street":"Beauvoir Ave",
    "iso:country":"US",
    "sg:address":"99 Beauvoir Ave",
    "sg:city":"Summit",
    "sg:classifiers":[
        {
            "category":"Health Services",
            "subcategory":"Doctor",
            "type":"Services"
        }
    ],
    "sg:phone":"+1 973 971 5996",
    "sg:postcode":"07901",
    "sg:province":"NJ",
    "wof:name":"Kaufman Stuart MD",
    "wof:placetype":"venue"
},
  "geometry": {"coordinates":[-74.354298,40.712374],"type":"Point"}
}