{
  "type": "Feature",
  "properties": {
    "iso:country":"US",
    "sg:address":"5 Lexington Ave",
    "sg:city":"Toms River",
    "sg:classifiers":[
        {
            "category":"Wholesale",
            "subcategory":"Auto Parts",
            "type":"Manufacturing & Wholesale Goods"
        }
    ],
    "sg:phone":"+1 732 286 1576",
    "sg:postcode":"08753",
    "sg:province":"NJ",
    "sg:tags":[
        "automobile",
        "wrecking"
    ],
    "wof:name":"Universal Wrecking",
    "wof:placetype":"venue"
},
  "geometry": {"coordinates":[-74.188453,39.953012],"type":"Point"}
}