{
  "type": "Feature",
  "properties": {
    "iso:country":"US",
    "sg:address":"649 Monmouth Ave",
    "sg:city":"Port Monmouth",
    "sg:classifiers":[
        {
            "category":"Building & Trades",
            "subcategory":"Construction",
            "type":"Services"
        }
    ],
    "sg:phone":"+1 732 495 5115",
    "sg:postcode":"07758",
    "sg:province":"NJ",
    "sg:tags":[
        "demolition",
        "contractor"
    ],
    "wof:name":"Kencore Core Drilling",
    "wof:placetype":"venue"
},
  "geometry": {"coordinates":[-74.09542,40.433426],"type":"Point"}
}