{
  "type": "Feature",
  "properties": {
    "iso:country":"US",
    "sg:address":"207 Odonnells Ln",
    "sg:city":"Cinnaminson",
    "sg:classifiers":[
        {
            "category":"Retail",
            "subcategory":"Auto Rental",
            "type":"Services"
        }
    ],
    "sg:phone":"+1 856 663 6613",
    "sg:postcode":"08077",
    "sg:province":"NJ",
    "sg:tags":[
        "limousine"
    ],
    "wof:name":"Elegant Limousine Inc",
    "wof:placetype":"venue"
},
  "geometry": {"coordinates":[-75.009246,39.974138],"type":"Point"}
}