{
  "type": "Feature",
  "properties": {
    "iso:country":"US",
    "sg:address":"1165 Cranbury South River Rd",
    "sg:city":"Dayton",
    "sg:classifiers":[
        {
            "category":"Freight",
            "type":"Transportation"
        }
    ],
    "sg:phone":"+1 609 409 1640",
    "sg:postcode":"08810",
    "sg:province":"NJ",
    "sg:tags":[
        "local",
        "storage",
        "trucking"
    ],
    "wof:name":"Warehouse",
    "wof:placetype":"venue"
},
  "geometry": {"coordinates":[-74.481202,40.348864],"type":"Point"}
}