{
  "type": "Feature",
  "properties": {
    "iso:country":"US",
    "sg:address":"22 Jefferson St",
    "sg:city":"Red Bank",
    "sg:classifiers":[
        {
            "category":"Shopping",
            "subcategory":"Optical Goods",
            "type":"Retail Goods"
        }
    ],
    "sg:phone":"+1   ",
    "sg:postcode":"07701",
    "sg:province":"NJ",
    "wof:name":"KATZ Eyes Lighting",
    "wof:placetype":"venue"
},
  "geometry": {"coordinates":[-74.08827599999999,40.365268],"type":"Point"}
}