{
  "type": "Feature",
  "properties": {
    "addr:full":"636 Elizabeth Ave Elizabeth NJ 07206",
    "addr:housenumber":"636",
    "addr:postcode":"07206",
    "addr:street":"Elizabeth Ave",
    "iso:country":"US",
    "sg:address":"636 Elizabeth Ave",
    "sg:city":"Elizabeth",
    "sg:classifiers":[
        {
            "category":"Retail",
            "subcategory":"Self-service Laundry",
            "type":"Services"
        }
    ],
    "sg:phone":"+1 908 352 9830",
    "sg:postcode":"07206",
    "sg:province":"NJ",
    "wof:name":"Jomar Laundromat",
    "wof:placetype":"venue"
},
  "geometry": {"coordinates":[-74.201099,40.657162],"type":"Point"}
}