{
  "type": "Feature",
  "properties": {
    "addr:full":"19 W Harding Ave Long Beach Twp NJ 08008",
    "addr:housenumber":"19",
    "addr:postcode":"08008",
    "addr:street":"W Harding Ave",
    "iso:country":"US",
    "sg:address":"19 W Harding Ave",
    "sg:city":"Long Beach Twp",
    "sg:classifiers":[
        {
            "category":"Travel",
            "subcategory":"Campground",
            "type":"Entertainment"
        }
    ],
    "sg:phone":"+1 609 492 9151",
    "sg:postcode":"08008",
    "sg:province":"NJ",
    "wof:name":"Long Beach Island Trailer Park",
    "wof:placetype":"venue"
},
  "geometry": {"coordinates":[-74.263481,39.534359],"type":"Point"}
}