{
  "type": "Feature",
  "properties": {
    "iso:country":"US",
    "sg:address":"82 Centre St",
    "sg:city":"Nutley",
    "sg:classifiers":[
        {
            "category":"Building & Trades",
            "subcategory":"Construction",
            "type":"Services"
        }
    ],
    "sg:phone":"+1 973 235 9372",
    "sg:postcode":"07110",
    "sg:province":"NJ",
    "sg:tags":[
        "tile",
        "dealer"
    ],
    "wof:name":"Professional Floor & Tile Inc",
    "wof:placetype":"venue"
},
  "geometry": {"coordinates":[-74.15104100000001,40.811044],"type":"Point"}
}