{
  "type": "Feature",
  "properties": {
    "addr:full":"1214 State Rte 37 Toms River NJ 08753",
    "addr:housenumber":"1214",
    "addr:postcode":"08753",
    "addr:street":"State Rte 37",
    "iso:country":"US",
    "sg:address":"1214 State Rte 37",
    "sg:city":"Toms River",
    "sg:classifiers":[
        {
            "category":"Restaurant",
            "type":"Food & Drink"
        }
    ],
    "sg:phone":"+1 732 506 6866",
    "sg:postcode":"08753",
    "sg:province":"NJ",
    "wof:name":"New Hey Bird Chinese Restrnt",
    "wof:placetype":"venue"
},
  "geometry": {"coordinates":[-74.15985499999999,39.953729],"type":"Point"}
}