{
  "type": "Feature",
  "properties": {
    "iso:country":"US",
    "sg:address":"51 Bennington Sq",
    "sg:city":"Hackettstown",
    "sg:classifiers":[
        {
            "category":"Shopping",
            "subcategory":"Florist",
            "type":"Retail Goods"
        }
    ],
    "sg:phone":"+1   ",
    "sg:postcode":"07840",
    "sg:province":"NJ",
    "wof:name":"Everythings Bloomin",
    "wof:placetype":"venue"
},
  "geometry": {"coordinates":[-74.82173400000001,40.828108],"type":"Point"}
}