{
  "type": "Feature",
  "properties": {
    "addr:full":"4237 US Highway 130 North S Edgewater Park NJ 08010",
    "addr:housenumber":"4237",
    "addr:postcode":"08010",
    "addr:street":"Us Highway 130 North S Edgewater Park",
    "iso:country":"US",
    "sg:address":"4237 US Highway 130 North S",
    "sg:city":"Edgewater Park",
    "sg:classifiers":[
        {
            "category":"Sports & Exercise",
            "subcategory":"Gym",
            "type":"Entertainment"
        },
        {
            "category":"Arena",
            "subcategory":"Sports Club",
            "type":"Entertainment"
        }
    ],
    "sg:phone":"+1 609 871 6000",
    "sg:postcode":"08010",
    "sg:province":"NJ",
    "sg:tags":[
        "trainer",
        "martial art"
    ],
    "wof:name":"Team Torres Martial Arts Training",
    "wof:placetype":"venue"
},
  "geometry": {"coordinates":[-74.912026,40.041132],"type":"Point"}
}