{
  "type": "Feature",
  "properties": {
    "iso:country":"US",
    "sg:address":"465 W Mount Pleasant Ave",
    "sg:city":"Livingston",
    "sg:classifiers":[
        {
            "category":"Professional",
            "subcategory":"Printing & Photocopies",
            "type":"Services"
        }
    ],
    "sg:phone":"+1 973 533 9330",
    "sg:postcode":"07039",
    "sg:province":"NJ",
    "wof:name":"Pip Printing",
    "wof:placetype":"venue"
},
  "geometry": {"coordinates":[-74.343002,40.7962],"type":"Point"}
}