{
  "type": "Feature",
  "properties": {
    "iso:country":"US",
    "sg:address":"455 Edgewood Ave",
    "sg:city":"Westfield",
    "sg:classifiers":[
        {
            "category":"Building & Trades",
            "subcategory":"Construction",
            "type":"Services"
        }
    ],
    "sg:phone":"+1 908 654 3801",
    "sg:postcode":"07090",
    "sg:province":"NJ",
    "sg:tags":[
        "hanging",
        "contractor"
    ],
    "wof:name":"Nics Painting Renvs",
    "wof:placetype":"venue"
},
  "geometry": {"coordinates":[-74.36386,40.649499],"type":"Point"}
}