{
  "type": "Feature",
  "properties": {
    "iso:country":"US",
    "sg:address":"508 S Livingston Ave",
    "sg:city":"Livingston",
    "sg:classifiers":[
        {
            "category":"Professional",
            "type":"Services"
        }
    ],
    "sg:phone":"+1 973 994 1200",
    "sg:postcode":"07039",
    "sg:province":"NJ",
    "sg:tags":[
        "establishment"
    ],
    "wof:name":"Mobile Office",
    "wof:placetype":"venue"
},
  "geometry": {"coordinates":[-74.32403499999999,40.774726],"type":"Point"}
}