{
  "type": "Feature",
  "properties": {
    "addr:full":"6 Willow Brook Dr Caldwell NJ 07006",
    "addr:housenumber":"6",
    "addr:postcode":"07006",
    "addr:street":"Willow Brook Dr",
    "iso:country":"US",
    "sg:address":"6 Willow Brook Dr",
    "sg:city":"Caldwell",
    "sg:classifiers":[
        {
            "category":"Professional",
            "type":"Services"
        }
    ],
    "sg:phone":"+1   ",
    "sg:postcode":"07006",
    "sg:province":"NJ",
    "wof:name":"Robert & Carole Cerasia F",
    "wof:placetype":"venue"
},
  "geometry": {"coordinates":[-74.24709,40.864853],"type":"Point"}
}