{
  "type": "Feature",
  "properties": {
    "addr:full":"41 N Bridge St Somerville NJ 08876",
    "addr:housenumber":"41",
    "addr:postcode":"08876",
    "addr:street":"N Bridge St",
    "iso:country":"US",
    "sg:address":"41 N Bridge St",
    "sg:city":"Somerville",
    "sg:classifiers":[
        {
            "category":"Health Services",
            "subcategory":"Doctor",
            "type":"Services"
        }
    ],
    "sg:phone":"+1 908 526 1937",
    "sg:postcode":"08876",
    "sg:province":"NJ",
    "sg:tags":[
        "medical"
    ],
    "wof:name":"B V Hollandt MD",
    "wof:placetype":"venue"
},
  "geometry": {"coordinates":[-74.611655,40.568647],"type":"Point"}
}