{
  "type": "Feature",
  "properties": {
    "iso:country":"US",
    "sg:address":"11 Sommers Ave",
    "sg:city":"Somers Point",
    "sg:classifiers":[
        {
            "category":"Home & Garden",
            "subcategory":"Furniture",
            "type":"Retail Goods"
        }
    ],
    "sg:phone":"+1 609 927 4000",
    "sg:postcode":"08244",
    "sg:province":"NJ",
    "sg:website":"www.surfsidecasualfurniture.com",
    "wof:name":"Surfside Casual Furniture",
    "wof:placetype":"venue"
},
  "geometry": {"coordinates":[-74.595747,39.309981],"type":"Point"}
}