{
  "type": "Feature",
  "properties": {
    "iso:country":"US",
    "sg:address":"71 Balboa Ln",
    "sg:city":"Franklin Park",
    "sg:classifiers":[
        {
            "category":"Shopping",
            "type":"Retail Goods"
        }
    ],
    "sg:phone":"+1   ",
    "sg:postcode":"08823",
    "sg:province":"NJ",
    "sg:tags":[
        "pet",
        "house",
        "sitting"
    ],
    "wof:name":"Family Pet By Riouxs",
    "wof:placetype":"venue"
},
  "geometry": {"coordinates":[-74.56017900000001,40.434951],"type":"Point"}
}