{
  "type": "Feature",
  "properties": {
    "iso:country":"US",
    "sg:address":"16 Leonard Rd",
    "sg:city":"Butler",
    "sg:classifiers":[
        {
            "category":"Building & Trades",
            "subcategory":"Construction",
            "type":"Services"
        }
    ],
    "sg:phone":"+1 973 492 8232",
    "sg:postcode":"07405",
    "sg:province":"NJ",
    "sg:tags":[
        "painter"
    ],
    "wof:name":"Jewett Painting Contractors",
    "wof:placetype":"venue"
},
  "geometry": {"coordinates":[-74.356217,41.007515],"type":"Point"}
}