{
  "type": "Feature",
  "properties": {
    "iso:country":"US",
    "sg:address":"341 Opossum Rd",
    "sg:city":"Skillman",
    "sg:classifiers":[
        {
            "category":"Building & Trades",
            "subcategory":"Construction",
            "type":"Services"
        }
    ],
    "sg:phone":"+1 609 430 0222",
    "sg:postcode":"08558",
    "sg:province":"NJ",
    "sg:tags":[
        "painter"
    ],
    "wof:name":"New Image Paint & Wallpapering",
    "wof:placetype":"venue"
},
  "geometry": {"coordinates":[-74.66701999999999,40.406983],"type":"Point"}
}