{
  "type": "Feature",
  "properties": {
    "addr:full":"1 S Raritan Ave Middlesex NJ 08846",
    "addr:housenumber":"1",
    "addr:postcode":"08846",
    "addr:street":"S Raritan Ave",
    "iso:country":"US",
    "sg:address":"1 S Raritan Ave",
    "sg:city":"Middlesex",
    "sg:classifiers":[
        {
            "category":"Professional",
            "subcategory":"Business Services",
            "type":"Services"
        }
    ],
    "sg:phone":"+1 732 356 3559",
    "sg:postcode":"08846",
    "sg:province":"NJ",
    "wof:name":"B & G Enterprises Inc",
    "wof:placetype":"venue"
},
  "geometry": {"coordinates":[-74.520909,40.559785],"type":"Point"}
}