{
  "type": "Feature",
  "properties": {
    "addr:full":"2285 South Ave Scotch Plains NJ 07076",
    "addr:housenumber":"2285",
    "addr:postcode":"07076",
    "addr:street":"South Ave",
    "iso:country":"US",
    "sg:address":"2285 South Ave",
    "sg:city":"Scotch Plains",
    "sg:classifiers":[
        {
            "category":"Professional",
            "subcategory":"Business Services",
            "type":"Services"
        }
    ],
    "sg:phone":"+1 908 359 7931",
    "sg:postcode":"07076",
    "sg:province":"NJ",
    "sg:tags":[
        "water",
        "treatment"
    ],
    "wof:name":"Portasoft Co",
    "wof:placetype":"venue"
},
  "geometry": {"coordinates":[-74.369964,40.645584],"type":"Point"}
}