{
  "type": "Feature",
  "properties": {
    "addr:full":"78 Quakertown Rd Pittstown NJ 08867",
    "addr:housenumber":"78",
    "addr:postcode":"08867",
    "addr:street":"Quakertown Rd",
    "iso:country":"US",
    "sg:address":"78 Quakertown Rd",
    "sg:city":"Pittstown",
    "sg:classifiers":[
        {
            "category":"Building & Trades",
            "subcategory":"Construction",
            "type":"Services"
        }
    ],
    "sg:phone":"+1 908 730 6226",
    "sg:postcode":"08867",
    "sg:province":"NJ",
    "sg:tags":[
        "fire",
        "restoration",
        "damage"
    ],
    "wof:name":"Purofirst",
    "wof:placetype":"venue"
},
  "geometry": {"coordinates":[-74.95304400000001,40.571802],"type":"Point"}
}