{
  "type": "Feature",
  "properties": {
    "addr:full":"7 2nd St Bordentown NJ 08505",
    "addr:housenumber":"7",
    "addr:postcode":"08505",
    "addr:street":"2Nd St",
    "iso:country":"US",
    "sg:address":"7 2nd St",
    "sg:city":"Bordentown",
    "sg:classifiers":[
        {
            "category":"Organizations",
            "subcategory":"Religious Organization",
            "type":"Services"
        }
    ],
    "sg:phone":"+1 609 291 9184",
    "sg:postcode":"08505",
    "sg:province":"NJ",
    "sg:tags":[
        "church"
    ],
    "wof:name":"Fieldsboro United Methodist",
    "wof:placetype":"venue"
},
  "geometry": {"coordinates":[-74.71342,40.151142],"type":"Point"}
}