{
  "type": "Feature",
  "properties": {
    "addr:full":"4 Lisa Ct East Brunswick NJ 08816",
    "addr:housenumber":"4",
    "addr:postcode":"08816",
    "addr:street":"Lisa Ct",
    "iso:country":"US",
    "sg:address":"4 Lisa Ct",
    "sg:city":"East Brunswick",
    "sg:classifiers":[
        {
            "category":"Professional",
            "subcategory":"Management & Consulting",
            "type":"Services"
        }
    ],
    "sg:phone":"+1   ",
    "sg:postcode":"08816",
    "sg:province":"NJ",
    "sg:tags":[
        "business"
    ],
    "wof:name":"Mw Energy Consultants",
    "wof:placetype":"venue"
},
  "geometry": {"coordinates":[-74.415381,40.426429],"type":"Point"}
}