{
  "type": "Feature",
  "properties": {
    "iso:country":"US",
    "sg:address":"41 Gates Pl",
    "sg:city":"Wayne",
    "sg:classifiers":[
        {
            "category":"Health Services",
            "subcategory":"Doctor",
            "type":"Services"
        }
    ],
    "sg:phone":"+1 973 872 9065",
    "sg:postcode":"07470",
    "sg:province":"NJ",
    "sg:tags":[
        "dentist"
    ],
    "wof:name":"Lawrence Piekarsky DDS",
    "wof:placetype":"venue"
},
  "geometry": {"coordinates":[-74.23385500000001,40.972687],"type":"Point"}
}