{
  "type": "Feature",
  "properties": {
    "addr:full":"16 Erindale Dr Marlton NJ 08053",
    "addr:housenumber":"16",
    "addr:postcode":"08053",
    "addr:street":"Erindale Dr",
    "iso:country":"US",
    "sg:address":"16 Erindale Dr",
    "sg:city":"Marlton",
    "sg:classifiers":[
        {
            "category":"Building & Trades",
            "subcategory":"Construction",
            "type":"Services"
        }
    ],
    "sg:phone":"+1 856 983 1842",
    "sg:postcode":"08053",
    "sg:province":"NJ",
    "sg:tags":[
        "resurfacing",
        "laying",
        "refinishing",
        "floor"
    ],
    "wof:name":"Whitaker & Co Flooring",
    "wof:placetype":"venue"
},
  "geometry": {"coordinates":[-74.906665,39.87694],"type":"Point"}
}