{
  "type": "Feature",
  "properties": {
    "iso:country":"US",
    "sg:address":"183 Hasbrouck Ave",
    "sg:city":"Hasbrouck Heights",
    "sg:classifiers":[
        {
            "category":"Food & Beverages",
            "subcategory":"Groceries & Convenience Stores",
            "type":"Retail Goods"
        }
    ],
    "sg:phone":"+1   ",
    "sg:postcode":"07604",
    "sg:province":"NJ",
    "wof:name":"Nicks Quick Stop",
    "wof:placetype":"venue"
},
  "geometry": {"coordinates":[-74.065889,40.865752],"type":"Point"}
}