{
  "type": "Feature",
  "properties": {
    "iso:country":"US",
    "sg:address":"70 Washington St",
    "sg:city":"Newark",
    "sg:classifiers":[
        {
            "category":"Building & Trades",
            "subcategory":"Locksmith",
            "type":"Services"
        }
    ],
    "sg:phone":"+1 973 735 5460",
    "sg:postcode":"07102",
    "sg:province":"NJ",
    "sg:tags":[
        "key"
    ],
    "wof:name":"AA Millenium Locksmith",
    "wof:placetype":"venue"
},
  "geometry": {"coordinates":[-74.171284,40.742357],"type":"Point"}
}