{
  "type": "Feature",
  "properties": {
    "iso:country":"US",
    "sg:address":"550 Passaic Ave",
    "sg:city":"West Caldwell",
    "sg:classifiers":[
        {
            "category":"Building & Trades",
            "subcategory":"Locksmith",
            "type":"Services"
        }
    ],
    "sg:phone":"+1 888 277 2738",
    "sg:postcode":"07006",
    "sg:province":"NJ",
    "sg:tags":[
        "key"
    ],
    "wof:name":"7 Day 24 Hour Emergency Locksmith",
    "wof:placetype":"venue"
},
  "geometry": {"coordinates":[-74.29609499999999,40.85033],"type":"Point"}
}