{
  "type": "Feature",
  "properties": {
    "iso:country":"US",
    "sg:address":"777 US Hwy 30",
    "sg:city":"Hammonton",
    "sg:classifiers":[
        {
            "category":"Health Services",
            "subcategory":"Doctor",
            "type":"Services"
        }
    ],
    "sg:phone":"+1 609 561 9344",
    "sg:postcode":"08037",
    "sg:province":"NJ",
    "sg:tags":[
        "physician",
        "surgeon"
    ],
    "wof:name":"University Of Medicine Of Nj",
    "wof:placetype":"venue"
},
  "geometry": {"coordinates":[-74.818485,39.6671],"type":"Point"}
}