{
  "type": "Feature",
  "properties": {
    "addr:full":"10 Magnolia Ave Bridgeton NJ 08302",
    "addr:housenumber":"10",
    "addr:postcode":"08302",
    "addr:street":"Magnolia Ave",
    "iso:country":"US",
    "sg:address":"10 Magnolia Ave",
    "sg:city":"Bridgeton",
    "sg:classifiers":[
        {
            "category":"Health Services",
            "subcategory":"Doctor",
            "type":"Services"
        }
    ],
    "sg:phone":"+1 856 451 2900",
    "sg:postcode":"08302",
    "sg:province":"NJ",
    "sg:tags":[
        "physician",
        "surgeon"
    ],
    "wof:name":"Family Foot Care Ctr",
    "wof:placetype":"venue"
},
  "geometry": {"coordinates":[-75.22027,39.436754],"type":"Point"}
}