{
  "type": "Feature",
  "properties": {
    "iso:country":"US",
    "sg:address":"13 Grandview Ter",
    "sg:city":"Sparta",
    "sg:classifiers":[
        {
            "category":"Insurance",
            "subcategory":"Insurance Agent",
            "type":"Services"
        }
    ],
    "sg:phone":"+1   ",
    "sg:postcode":"07871",
    "sg:province":"NJ",
    "wof:name":"Health Plan Design",
    "wof:placetype":"venue"
},
  "geometry": {"coordinates":[-74.622354,41.089146],"type":"Point"}
}