{
  "type": "Feature",
  "properties": {
    "addr:full":"1 Lethbridge Plz Mahwah NJ 07430",
    "addr:housenumber":"1",
    "addr:postcode":"07430",
    "addr:street":"Lethbridge Plz",
    "iso:country":"US",
    "sg:address":"1 Lethbridge Plz",
    "sg:city":"Mahwah",
    "sg:classifiers":[
        {
            "category":"Autos & Motor Vehicles",
            "subcategory":"Auto Supplies",
            "type":"Retail Goods"
        }
    ],
    "sg:phone":"+1 201 529 4700",
    "sg:postcode":"07430",
    "sg:province":"NJ",
    "sg:tags":[
        "automobile",
        "alarm"
    ],
    "wof:name":"Lynch Systems",
    "wof:placetype":"venue"
},
  "geometry": {"coordinates":[-74.15084,41.08301],"type":"Point"}
}