{
  "type": "Feature",
  "properties": {
    "iso:country":"US",
    "sg:address":"105 9th St",
    "sg:city":"Thorofare",
    "sg:classifiers":[
        {
            "category":"Banks & Credit Unions",
            "subcategory":"Investment Brokerage",
            "type":"Services"
        }
    ],
    "sg:phone":"+1 856 686 1555",
    "sg:postcode":"08086",
    "sg:province":"NJ",
    "wof:name":"Society Hill Investment Group",
    "wof:placetype":"venue"
},
  "geometry": {"coordinates":[-75.171729,39.869726],"type":"Point"}
}