{
  "type": "Feature",
  "properties": {
    "addr:full":"349 Matawan Rd Matawan NJ 07747",
    "addr:housenumber":"349",
    "addr:postcode":"07747",
    "addr:street":"Matawan Rd",
    "iso:country":"US",
    "sg:address":"349 Matawan Rd",
    "sg:city":"Matawan",
    "sg:classifiers":[
        {
            "category":"Shopping",
            "subcategory":"Pharmacy",
            "type":"Retail Goods"
        }
    ],
    "sg:phone":"+1 732 583 4347",
    "sg:postcode":"07747",
    "sg:province":"NJ",
    "wof:name":"CVS Pharmacy",
    "wof:placetype":"venue"
},
  "geometry": {"coordinates":[-74.250647,40.430699],"type":"Point"}
}