{
  "type": "Feature",
  "properties": {
    "addr:full":"36 Stillman Ave Bergenfield NJ 07621",
    "addr:housenumber":"36",
    "addr:postcode":"07621",
    "addr:street":"Stillman Ave",
    "iso:country":"US",
    "sg:address":"36 Stillman Ave",
    "sg:city":"Bergenfield",
    "sg:classifiers":[
        {
            "category":"Insurance",
            "subcategory":"Insurance Agent",
            "type":"Services"
        }
    ],
    "sg:phone":"+1   ",
    "sg:postcode":"07621",
    "sg:province":"NJ",
    "wof:name":"Nu Wave Medical Claims Service",
    "wof:placetype":"venue"
},
  "geometry": {"coordinates":[-73.999488,40.935373],"type":"Point"}
}