{
  "type": "Feature",
  "properties": {
    "iso:country":"US",
    "sg:address":"1858 Mount Ephraim Ave",
    "sg:city":"Camden",
    "sg:classifiers":[
        {
            "category":"Food & Beverages",
            "subcategory":"Meat & Fish",
            "type":"Retail Goods"
        }
    ],
    "sg:phone":"+1 856 541 0776",
    "sg:postcode":"08104",
    "sg:province":"NJ",
    "sg:tags":[
        "seafood",
        "market"
    ],
    "wof:name":"Crab Stop",
    "wof:placetype":"venue"
},
  "geometry": {"coordinates":[-75.1036,39.921101],"type":"Point"}
}