{
  "type": "Feature",
  "properties": {
    "iso:country":"US",
    "sg:address":"67 W Chestnut Ave",
    "sg:city":"Vineland",
    "sg:classifiers":[
        {
            "category":"Wholesale",
            "subcategory":"Machinery & Supplies",
            "type":"Manufacturing & Wholesale Goods"
        }
    ],
    "sg:phone":"+1 856 691 4040",
    "sg:postcode":"08360",
    "sg:province":"NJ",
    "sg:tags":[
        "concrete",
        "product"
    ],
    "wof:name":"Cummines R E",
    "wof:placetype":"venue"
},
  "geometry": {"coordinates":[-75.036778,39.479429],"type":"Point"}
}