{
  "type": "Feature",
  "properties": {
    "iso:country":"US",
    "sg:address":"206 W Harmony Ave",
    "sg:city":"Beach Haven",
    "sg:classifiers":[
        {
            "category":"Professional",
            "type":"Services"
        }
    ],
    "sg:phone":"+1   ",
    "sg:postcode":"08008",
    "sg:province":"NJ",
    "wof:name":"Vincent Farias",
    "wof:placetype":"venue"
},
  "geometry": {"coordinates":[-74.199523,39.624112],"type":"Point"}
}