{
  "type": "Feature",
  "properties": {
    "addr:full":"216 Lake Dr Bellmawr NJ 08031",
    "addr:housenumber":"216",
    "addr:postcode":"08031",
    "addr:street":"Lake Dr",
    "iso:country":"US",
    "sg:address":"216 Lake Dr",
    "sg:city":"Bellmawr",
    "sg:classifiers":[
        {
            "category":"Professional",
            "subcategory":"Business Services",
            "type":"Services"
        }
    ],
    "sg:phone":"+1 856 931 0474",
    "sg:postcode":"08031",
    "sg:province":"NJ",
    "wof:name":"Lutner Enterprises",
    "wof:placetype":"venue"
},
  "geometry": {"coordinates":[-75.071558,39.864172],"type":"Point"}
}