{
  "type": "Feature",
  "properties": {
    "iso:country":"US",
    "sg:address":"60 S Fullerton Ave",
    "sg:city":"Montclair",
    "sg:classifiers":[
        {
            "category":"Organizations",
            "subcategory":"Community Association",
            "type":"Services"
        }
    ],
    "sg:phone":"+1 973 746 9614",
    "sg:postcode":"07042",
    "sg:province":"NJ",
    "wof:name":"Garden Club Of Montclair",
    "wof:placetype":"venue"
},
  "geometry": {"coordinates":[-74.21831400000001,40.811419],"type":"Point"}
}