{
  "type": "Feature",
  "properties": {
    "addr:full":"1 Myrtle Ave Allendale NJ 07401",
    "addr:housenumber":"1",
    "addr:postcode":"07401",
    "addr:street":"Myrtle Ave",
    "iso:country":"US",
    "sg:address":"1 Myrtle Ave",
    "sg:city":"Allendale",
    "sg:classifiers":[
        {
            "category":"Restaurant",
            "type":"Food & Drink"
        }
    ],
    "sg:phone":"+1   ",
    "sg:postcode":"07401",
    "sg:province":"NJ",
    "sg:tags":[
        "eating"
    ],
    "wof:name":"Pastafino Restorante Inc",
    "wof:placetype":"venue"
},
  "geometry": {"coordinates":[-74.130201,41.031541],"type":"Point"}
}