{
  "type": "Feature",
  "properties": {
    "addr:full":"133 Saint George Ave Roselle NJ 07203",
    "addr:housenumber":"133",
    "addr:postcode":"07203",
    "addr:street":"Saint George Ave",
    "iso:country":"US",
    "sg:address":"133 Saint George Ave",
    "sg:city":"Roselle",
    "sg:classifiers":[
        {
            "category":"Building & Trades",
            "subcategory":"Locksmith",
            "type":"Services"
        }
    ],
    "sg:phone":"+1 908 372 6634",
    "sg:postcode":"07203",
    "sg:province":"NJ",
    "sg:tags":[
        "key"
    ],
    "wof:name":"1 24 Hour A Day A Locksmith",
    "wof:placetype":"venue"
},
  "geometry": {"coordinates":[-74.262744,40.639302],"type":"Point"}
}