{
  "type": "Feature",
  "properties": {
    "iso:country":"US",
    "sg:address":"240 Pacific Ave",
    "sg:city":"Beachwood",
    "sg:classifiers":[
        {
            "category":"Taxi",
            "type":"Transportation"
        }
    ],
    "sg:phone":"+1 732 341 3388",
    "sg:postcode":"08722",
    "sg:province":"NJ",
    "sg:tags":[
        "taxicab"
    ],
    "wof:name":"A Amber Taxi",
    "wof:placetype":"venue"
},
  "geometry": {"coordinates":[-74.18634299999999,39.934177],"type":"Point"}
}