{
  "type": "Feature",
  "properties": {
    "iso:country":"US",
    "sg:address":"460 Queen Anne Rd",
    "sg:city":"Teaneck",
    "sg:classifiers":[
        {
            "category":"Arts & Performance",
            "subcategory":"Theater",
            "type":"Entertainment"
        },
        {
            "category":"Professional",
            "subcategory":"Business Services",
            "type":"Services"
        }
    ],
    "sg:phone":"+1 201 928 1999",
    "sg:postcode":"07666",
    "sg:province":"NJ",
    "sg:tags":[
        "group"
    ],
    "sg:website":"www.chewentertainment.com",
    "wof:name":"Chews Entertainment",
    "wof:placetype":"venue"
},
  "geometry": {"coordinates":[-74.019379,40.878247],"type":"Point"}
}