{
  "type": "Feature",
  "properties": {
    "iso:country":"US",
    "sg:address":"764 US Hwy 1",
    "sg:city":"Edison",
    "sg:classifiers":[
        {
            "category":"Shopping",
            "subcategory":"Gifts & Souvenirs",
            "type":"Retail Goods"
        }
    ],
    "sg:phone":"+1 732 985 3050",
    "sg:postcode":"08817",
    "sg:province":"NJ",
    "sg:tags":[
        "party",
        "supply"
    ],
    "sg:website":"www.millersrentals.com",
    "wof:name":"Miller's Rentals & Party Ctr",
    "wof:placetype":"venue"
},
  "geometry": {"coordinates":[-74.38546599999999,40.510746],"type":"Point"}
}