{
  "type": "Feature",
  "properties": {
    "iso:country":"US",
    "sg:address":"149 Kearny Ave",
    "sg:city":"Perth Amboy",
    "sg:classifiers":[
        {
            "category":"Government",
            "subcategory":"Office",
            "type":"Public Place"
        }
    ],
    "sg:phone":"+1 732 826 0440",
    "sg:postcode":"08861",
    "sg:province":"NJ",
    "sg:tags":[
        "county",
        "program",
        "health"
    ],
    "wof:name":"Middlesex County Health Dept",
    "wof:placetype":"venue"
},
  "geometry": {"coordinates":[-74.26959600000001,40.501803],"type":"Point"}
}