{
  "type": "Feature",
  "properties": {
    "addr:full":"661 W 8th St Plainfield NJ 07060",
    "addr:housenumber":"661",
    "addr:postcode":"07060",
    "addr:street":"W 8Th St",
    "iso:country":"US",
    "sg:address":"661 W 8th St",
    "sg:city":"Plainfield",
    "sg:classifiers":[
        {
            "category":"Education",
            "subcategory":"School",
            "type":"Public Place"
        }
    ],
    "sg:phone":"+1   ",
    "sg:postcode":"07060",
    "sg:province":"NJ",
    "wof:name":"Hubbard Middle School",
    "wof:placetype":"venue"
},
  "geometry": {"coordinates":[-74.424992,40.60605],"type":"Point"}
}