{
  "type": "Feature",
  "properties": {
    "iso:country":"US",
    "sg:address":"1 Georgetown Rd",
    "sg:city":"Bordentown",
    "sg:classifiers":[
        {
            "category":"Professional",
            "type":"Services"
        }
    ],
    "sg:phone":"+1 609 298 8113",
    "sg:postcode":"08505",
    "sg:province":"NJ",
    "sg:tags":[
        "establishment"
    ],
    "wof:name":"Paws On The Go",
    "wof:placetype":"venue"
},
  "geometry": {"coordinates":[-74.703073,40.135247],"type":"Point"}
}