{
  "type": "Feature",
  "properties": {
    "addr:full":"495 Broadway Long Branch NJ 07740",
    "addr:housenumber":"495",
    "addr:postcode":"07740",
    "addr:street":"Broadway",
    "iso:country":"US",
    "sg:address":"495 Broadway",
    "sg:city":"Long Branch",
    "sg:classifiers":[
        {
            "category":"Organizations",
            "subcategory":"Political Organization",
            "type":"Services"
        }
    ],
    "sg:phone":"+1 732 571 4141",
    "sg:postcode":"07740",
    "sg:province":"NJ",
    "wof:name":"Pallone For Congress Campaign",
    "wof:placetype":"venue"
},
  "geometry": {"coordinates":[-73.997174,40.301201],"type":"Point"}
}