{
  "type": "Feature",
  "properties": {
    "iso:country":"US",
    "sg:address":"2137 River Rd",
    "sg:city":"Egg Harbor City",
    "sg:classifiers":[
        {
            "category":"Utilities",
            "subcategory":"Cable",
            "type":"Services"
        }
    ],
    "sg:phone":"+1 609 965 7300",
    "sg:postcode":"08215",
    "sg:province":"NJ",
    "sg:tags":[
        "television"
    ],
    "wof:name":"Mullica Cable TV Inc",
    "wof:placetype":"venue"
},
  "geometry": {"coordinates":[-74.544438,39.589329],"type":"Point"}
}