{
  "type": "Feature",
  "properties": {
    "iso:country":"US",
    "sg:address":"3769 Highway 46 East",
    "sg:city":"Parsippany",
    "sg:classifiers":[
        {
            "category":"Travel",
            "subcategory":"Hotels & Motels",
            "type":"Entertainment"
        }
    ],
    "sg:phone":"+1 973 394 0303",
    "sg:postcode":"07054",
    "sg:province":"NJ",
    "sg:website":"www.marriott.com",
    "wof:name":"Courtyard Parsippany",
    "wof:placetype":"venue"
},
  "geometry": {"coordinates":[-74.44640099999999,40.87821],"type":"Point"}
}