{
  "type": "Feature",
  "properties": {
    "addr:full":"125 Oakview Ave Maplewood NJ 07040",
    "addr:housenumber":"125",
    "addr:postcode":"07040",
    "addr:street":"Oakview Ave",
    "iso:country":"US",
    "sg:address":"125 Oakview Ave",
    "sg:city":"Maplewood",
    "sg:classifiers":[
        {
            "category":"Manufacturing",
            "subcategory":"Retail Goods",
            "type":"Manufacturing & Wholesale Goods"
        }
    ],
    "sg:phone":"+1 973 763 4072",
    "sg:postcode":"07040",
    "sg:province":"NJ",
    "sg:tags":[
        "product",
        "mfg"
    ],
    "wof:name":"Mfg Professionals Inc",
    "wof:placetype":"venue"
},
  "geometry": {"coordinates":[-74.26055100000001,40.724536],"type":"Point"}
}