{
  "type": "Feature",
  "properties": {
    "addr:full":"218 Summit Rd Mount Laurel NJ 08054",
    "addr:housenumber":"218",
    "addr:postcode":"08054",
    "addr:street":"Summit Rd",
    "iso:country":"US",
    "sg:address":"218 Summit Rd",
    "sg:city":"Mount Laurel",
    "sg:classifiers":[
        {
            "category":"Professional",
            "subcategory":"Management & Consulting",
            "type":"Services"
        }
    ],
    "sg:phone":"+1   ",
    "sg:postcode":"08054",
    "sg:province":"NJ",
    "sg:tags":[
        "business"
    ],
    "wof:name":"Operational Solutions Inc",
    "wof:placetype":"venue"
},
  "geometry": {"coordinates":[-74.901065,39.918939],"type":"Point"}
}