{
  "type": "Feature",
  "properties": {
    "addr:full":"623 Paulison Ave Clifton NJ 07011",
    "addr:housenumber":"623",
    "addr:postcode":"07011",
    "addr:street":"Paulison Ave",
    "iso:country":"US",
    "sg:address":"623 Paulison Ave",
    "sg:city":"Clifton",
    "sg:classifiers":[
        {
            "category":"Personal",
            "subcategory":"Beauty Salon",
            "type":"Services"
        }
    ],
    "sg:phone":"+1 973 458 1555",
    "sg:postcode":"07011",
    "sg:province":"NJ",
    "wof:name":"Tiffany's Beauty Salon",
    "wof:placetype":"venue"
},
  "geometry": {"coordinates":[-74.14432100000001,40.865177],"type":"Point"}
}