{
  "type": "Feature",
  "properties": {
    "addr:full":"192 Livingston St Northvale NJ 07647",
    "addr:housenumber":"192",
    "addr:postcode":"07647",
    "addr:street":"Livingston St",
    "iso:country":"US",
    "sg:address":"192 Livingston St",
    "sg:city":"Northvale",
    "sg:classifiers":[
        {
            "category":"Retail",
            "subcategory":"Auto Repair",
            "type":"Services"
        }
    ],
    "sg:phone":"+1 201 768 1378",
    "sg:postcode":"07647",
    "sg:province":"NJ",
    "sg:tags":[
        "machine",
        "automobile",
        "shop"
    ],
    "wof:name":"Northvale Auto Parts",
    "wof:placetype":"venue"
},
  "geometry": {"coordinates":[-73.94922800000001,41.006098],"type":"Point"}
}