{
  "type": "Feature",
  "properties": {
    "addr:full":"604 Brinley Ave Bradley Beach NJ 07720",
    "addr:housenumber":"604",
    "addr:postcode":"07720",
    "addr:street":"Brinley Ave Bradley",
    "iso:country":"US",
    "sg:address":"604 Brinley Ave",
    "sg:city":"Bradley Beach",
    "sg:classifiers":[
        {
            "category":"Professional",
            "subcategory":"Credit Reporting & Collection",
            "type":"Services"
        }
    ],
    "sg:phone":"+1 732 775 0714",
    "sg:postcode":"07720",
    "sg:province":"NJ",
    "sg:tags":[
        "adjustment"
    ],
    "wof:name":"Outwater Truck & Auto Inc",
    "wof:placetype":"venue"
},
  "geometry": {"coordinates":[-74.01789599999999,40.203138],"type":"Point"}
}