{
  "type": "Feature",
  "properties": {
    "addr:full":"225 N Beverwyck Rd Parsippany NJ 07054",
    "addr:housenumber":"225",
    "addr:postcode":"07054",
    "addr:street":"N Beverwyck Rd",
    "iso:country":"US",
    "sg:address":"225 N Beverwyck Rd",
    "sg:city":"Parsippany",
    "sg:classifiers":[
        {
            "category":"Professional",
            "subcategory":"Accounting & Tax Preparation",
            "type":"Services"
        }
    ],
    "sg:phone":"+1 973 263 4419",
    "sg:postcode":"07054",
    "sg:province":"NJ",
    "sg:tags":[
        "return"
    ],
    "wof:name":"P L Swartz & Associates Co",
    "wof:placetype":"venue"
},
  "geometry": {"coordinates":[-74.38330000000001,40.86913],"type":"Point"}
}