{
  "type": "Feature",
  "properties": {
    "iso:country":"US",
    "sg:address":"22 Galassi Ct",
    "sg:city":"Jackson",
    "sg:classifiers":[
        {
            "category":"Shopping",
            "subcategory":"Computers & Home Electronics",
            "type":"Retail Goods"
        }
    ],
    "sg:phone":"+1 732 370 5481",
    "sg:postcode":"08527",
    "sg:province":"NJ",
    "sg:tags":[
        "software"
    ],
    "wof:name":"MDS Computer Systems",
    "wof:placetype":"venue"
},
  "geometry": {"coordinates":[-74.261482,40.079519],"type":"Point"}
}