{
  "type": "Feature",
  "properties": {
    "addr:full":"3001 Fenwick Rd Camden NJ 08104",
    "addr:housenumber":"3001",
    "addr:postcode":"08104",
    "addr:street":"Fenwick Rd",
    "iso:country":"US",
    "sg:address":"3001 Fenwick Rd",
    "sg:city":"Camden",
    "sg:classifiers":[
        {
            "category":"Social Services",
            "subcategory":"Child Care",
            "type":"Services"
        },
        {
            "category":"Education",
            "subcategory":"Preschool",
            "type":"Public Place"
        },
        {
            "category":"Education",
            "subcategory":"School",
            "type":"Public Place"
        }
    ],
    "sg:phone":"+1 856 342 7997",
    "sg:postcode":"08104",
    "sg:province":"NJ",
    "sg:tags":[
        "elementary",
        "day"
    ],
    "wof:name":"Respond Inc",
    "wof:placetype":"venue"
},
  "geometry": {"coordinates":[-75.11129800000001,39.904499],"type":"Point"}
}