{
  "type": "Feature",
  "properties": {
    "addr:full":"30 Ayrmont Ln Matawan NJ 07747",
    "addr:housenumber":"30",
    "addr:postcode":"07747",
    "addr:street":"Ayrmont Ln",
    "iso:country":"US",
    "sg:address":"30 Ayrmont Ln",
    "sg:city":"Matawan",
    "sg:classifiers":[
        {
            "category":"Wholesale",
            "subcategory":"Metals & Minerals",
            "type":"Manufacturing & Wholesale Goods"
        }
    ],
    "sg:phone":"+1 732 583 7488",
    "sg:postcode":"07747",
    "sg:province":"NJ",
    "sg:tags":[
        "warehouse"
    ],
    "wof:name":"Cambridge-Lee Industries Inc",
    "wof:placetype":"venue"
},
  "geometry": {"coordinates":[-74.210773,40.407687],"type":"Point"}
}