{
  "type": "Feature",
  "properties": {
    "iso:country":"US",
    "sg:address":"2700 US Highway 22 E",
    "sg:city":"Union",
    "sg:classifiers":[
        {
            "category":"Home & Garden",
            "subcategory":"Household Appliances",
            "type":"Retail Goods"
        }
    ],
    "sg:phone":"+1 908 964 5447",
    "sg:postcode":"07083",
    "sg:province":"NJ",
    "sg:tags":[
        "repair"
    ],
    "sg:website":"www.circuitcity.com",
    "wof:name":"Circuit City",
    "wof:placetype":"venue"
},
  "geometry": {"coordinates":[-74.3078,40.688301],"type":"Point"}
}