{
  "type": "Feature",
  "properties": {
    "iso:country":"US",
    "sg:address":"18 Green St",
    "sg:city":"Woodstown",
    "sg:classifiers":[
        {
            "category":"Restaurant",
            "type":"Food & Drink"
        }
    ],
    "sg:phone":"+1   ",
    "sg:postcode":"08098",
    "sg:province":"NJ",
    "sg:tags":[
        "eating"
    ],
    "wof:name":"Lauren H Moore",
    "wof:placetype":"venue"
},
  "geometry": {"coordinates":[-75.327816,39.649502],"type":"Point"}
}