{
  "type": "Feature",
  "properties": {
    "addr:full":"291 Avenue A Bayonne NJ 07002",
    "addr:housenumber":"291",
    "addr:postcode":"07002",
    "addr:street":"Avenue A",
    "iso:country":"US",
    "sg:address":"291 Avenue A",
    "sg:city":"Bayonne",
    "sg:classifiers":[
        {
            "category":"Building & Trades",
            "subcategory":"Locksmith",
            "type":"Services"
        }
    ],
    "sg:phone":"+1 877 862 4777",
    "sg:postcode":"07002",
    "sg:province":"NJ",
    "sg:tags":[
        "key"
    ],
    "wof:name":"7 Day 24 Hour Emergency Locksmith",
    "wof:placetype":"venue"
},
  "geometry": {"coordinates":[-74.131789,40.658256],"type":"Point"}
}