{
  "type": "Feature",
  "properties": {
    "iso:country":"US",
    "sg:address":"251 Powers St",
    "sg:city":"New Brunswick",
    "sg:classifiers":[
        {
            "category":"Health Services",
            "subcategory":"Clinic",
            "type":"Services"
        },
        {
            "category":"Health Services",
            "subcategory":"Doctor",
            "type":"Services"
        }
    ],
    "sg:phone":"+1 732 545 9191",
    "sg:postcode":"08901",
    "sg:province":"NJ",
    "sg:tags":[
        "physician",
        "surgeon",
        "specialty",
        "outpatient"
    ],
    "wof:name":"Powers Street Orthopaedic Ctr",
    "wof:placetype":"venue"
},
  "geometry": {"coordinates":[-74.45446200000001,40.485883],"type":"Point"}
}