{
  "type": "Feature",
  "properties": {
    "addr:full":"2412 Atlantic Ave Atlantic City NJ 08401",
    "addr:housenumber":"2412",
    "addr:postcode":"08401",
    "addr:street":"Atlantic Ave",
    "iso:country":"US",
    "sg:address":"2412 Atlantic Ave",
    "sg:city":"Atlantic City",
    "sg:classifiers":[
        {
            "category":"Health Services",
            "subcategory":"Doctor",
            "type":"Services"
        }
    ],
    "sg:phone":"+1 609 344 8726",
    "sg:postcode":"08401",
    "sg:province":"NJ",
    "sg:tags":[
        "dentist"
    ],
    "wof:name":"Tran Family & Cosmetic Dntstry",
    "wof:placetype":"venue"
},
  "geometry": {"coordinates":[-74.441749,39.356514],"type":"Point"}
}