{
  "type": "Feature",
  "properties": {
    "addr:full":"967 Cedar Dr Newton NJ 07860",
    "addr:housenumber":"967",
    "addr:postcode":"07860",
    "addr:street":"Cedar Dr",
    "iso:country":"US",
    "sg:address":"967 Cedar Dr",
    "sg:city":"Newton",
    "sg:classifiers":[
        {
            "category":"Manufacturing",
            "subcategory":"Printing",
            "type":"Manufacturing & Wholesale Goods"
        }
    ],
    "sg:phone":"+1 973 300 4720",
    "sg:postcode":"07860",
    "sg:province":"NJ",
    "sg:tags":[
        "publisher"
    ],
    "wof:name":"Git North America Inc",
    "wof:placetype":"venue"
},
  "geometry": {"coordinates":[-74.814171,41.063709],"type":"Point"}
}