{
  "type": "Feature",
  "properties": {
    "iso:country":"US",
    "sg:address":"30 Hartz Way",
    "sg:city":"Secaucus",
    "sg:classifiers":[
        {
            "category":"Freight",
            "type":"Transportation"
        }
    ],
    "sg:phone":"+1 201 348 7566",
    "sg:postcode":"07094",
    "sg:province":"NJ",
    "sg:tags":[
        "warehouse"
    ],
    "wof:name":"R Siskind & Co Inc",
    "wof:placetype":"venue"
},
  "geometry": {"coordinates":[-74.07445,40.781911],"type":"Point"}
}