{
  "type": "Feature",
  "properties": {
    "addr:full":"39 Broad St Elizabeth NJ 07201",
    "addr:housenumber":"39",
    "addr:postcode":"07201",
    "addr:street":"Broad St",
    "iso:country":"US",
    "sg:address":"39 Broad St",
    "sg:city":"Elizabeth",
    "sg:classifiers":[
        {
            "category":"Shopping",
            "subcategory":"Clothing, Apparel, & Fashions",
            "type":"Retail Goods"
        }
    ],
    "sg:phone":"+1   ",
    "sg:postcode":"07201",
    "sg:province":"NJ",
    "wof:name":"Top Designs",
    "wof:placetype":"venue"
},
  "geometry": {"coordinates":[-74.214839,40.663375],"type":"Point"}
}