{
  "type": "Feature",
  "properties": {
    "iso:country":"US",
    "sg:address":"685 Mount Prospect Ave Ste 1",
    "sg:city":"Newark",
    "sg:classifiers":[
        {
            "category":"Personal",
            "subcategory":"Tattoo Parlor",
            "type":"Services"
        }
    ],
    "sg:phone":"+1 973 483 3007",
    "sg:postcode":"07104",
    "sg:province":"NJ",
    "wof:name":"Avenue Inc Avenue Cuts",
    "wof:placetype":"venue"
},
  "geometry": {"coordinates":[-74.165649,40.775407],"type":"Point"}
}