{
  "type": "Feature",
  "properties": {
    "iso:country":"US",
    "sg:address":"34 Dogwood Dr",
    "sg:city":"Chatham",
    "sg:classifiers":[
        {
            "category":"Building & Trades",
            "subcategory":"Plumbing",
            "type":"Services"
        }
    ],
    "sg:phone":"+1 973 701 1650",
    "sg:postcode":"07928",
    "sg:province":"NJ",
    "sg:tags":[
        "contractor"
    ],
    "wof:name":"Power Plumbing Inc",
    "wof:placetype":"venue"
},
  "geometry": {"coordinates":[-74.438698,40.700298],"type":"Point"}
}