{
  "type": "Feature",
  "properties": {
    "addr:full":"304 Cleveland Ave Trenton NJ 08629",
    "addr:housenumber":"304",
    "addr:postcode":"08629",
    "addr:street":"Cleveland Ave",
    "iso:country":"US",
    "sg:address":"304 Cleveland Ave",
    "sg:city":"Trenton",
    "sg:classifiers":[
        {
            "category":"Home & Garden",
            "subcategory":"Carpets & Floor Coverings",
            "type":"Retail Goods"
        }
    ],
    "sg:phone":"+1 609 393 2727",
    "sg:postcode":"08629",
    "sg:province":"NJ",
    "sg:tags":[
        "dealer",
        "rug"
    ],
    "wof:name":"Moore Carpet Sales & Svc",
    "wof:placetype":"venue"
},
  "geometry": {"coordinates":[-74.732523,40.222847],"type":"Point"}
}