{
  "type": "Feature",
  "properties": {
    "iso:country":"US",
    "sg:address":"3338 US Hwy 9",
    "sg:city":"Freehold",
    "sg:classifiers":[
        {
            "category":"Restaurant",
            "type":"Food & Drink"
        }
    ],
    "sg:phone":"+1 732 431 2323",
    "sg:postcode":"07728",
    "sg:province":"NJ",
    "sg:tags":[
        "eating"
    ],
    "wof:name":"Szechuan Star Restaurant Corp",
    "wof:placetype":"venue"
},
  "geometry": {"coordinates":[-74.26864,40.222463],"type":"Point"}
}