{
  "type": "Feature",
  "properties": {
    "iso:country":"US",
    "sg:address":"2810 Boardwalk",
    "sg:city":"Wildwood",
    "sg:classifiers":[
        {
            "category":"Restaurant",
            "type":"Food & Drink"
        }
    ],
    "sg:phone":"+1 609 522 2600",
    "sg:postcode":"08260",
    "sg:province":"NJ",
    "wof:name":"Pierre's Restaurant",
    "wof:placetype":"venue"
},
  "geometry": {"coordinates":[-74.80551699999999,38.989626],"type":"Point"}
}