{
  "type": "Feature",
  "properties": {
    "addr:full":"62 N Broad St Penns Grove NJ 08069",
    "addr:housenumber":"62",
    "addr:postcode":"08069",
    "addr:street":"N Broad St",
    "iso:country":"US",
    "sg:address":"62 N Broad St",
    "sg:city":"Penns Grove",
    "sg:classifiers":[
        {
            "category":"Wholesale",
            "subcategory":"Machinery & Supplies",
            "type":"Manufacturing & Wholesale Goods"
        }
    ],
    "sg:phone":"+1 856 299 4500",
    "sg:postcode":"08069",
    "sg:province":"NJ",
    "sg:tags":[
        "chemical",
        "process",
        "refining",
        "equipment"
    ],
    "wof:name":"//wwwecreconcom",
    "wof:placetype":"venue"
},
  "geometry": {"coordinates":[-75.466972,39.731624],"type":"Point"}
}