{
  "type": "Feature",
  "properties": {
    "iso:country":"US",
    "sg:address":"1903 Long Hill Rd",
    "sg:city":"Millington",
    "sg:classifiers":[
        {
            "category":"Retail",
            "subcategory":"Repair Shop",
            "type":"Services"
        },
        {
            "category":"Utilities",
            "subcategory":"Fuel Oil & Lpg",
            "type":"Services"
        }
    ],
    "sg:phone":"+1 908 647 0577",
    "sg:postcode":"07946",
    "sg:province":"NJ",
    "sg:tags":[
        "drain",
        "heating",
        "air",
        "sewer",
        "cleaning",
        "plumbing",
        "conditioning"
    ],
    "wof:name":"Karg's Plumbing & Heating",
    "wof:placetype":"venue"
},
  "geometry": {"coordinates":[-74.520839,40.674489],"type":"Point"}
}