{
  "type": "Feature",
  "properties": {
    "addr:full":"718 7th Ave River Edge NJ 07661",
    "addr:housenumber":"718",
    "addr:postcode":"07661",
    "addr:street":"7Th Ave",
    "iso:country":"US",
    "sg:address":"718 7th Ave",
    "sg:city":"River Edge",
    "sg:classifiers":[
        {
            "category":"Retail",
            "subcategory":"Laundry & Dry Cleaning",
            "type":"Services"
        }
    ],
    "sg:phone":"+1 201 265 9146",
    "sg:postcode":"07661",
    "sg:province":"NJ",
    "sg:tags":[
        "drycleaning",
        "plant"
    ],
    "wof:name":"Helen Cleaners",
    "wof:placetype":"venue"
},
  "geometry": {"coordinates":[-74.04273999999999,40.936906],"type":"Point"}
}