{
  "type": "Feature",
  "properties": {
    "addr:full":"55 Moonachie Ave Moonachie NJ 07074",
    "addr:housenumber":"55",
    "addr:postcode":"07074",
    "addr:street":"Moonachie Ave",
    "iso:country":"US",
    "sg:address":"55 Moonachie Ave",
    "sg:city":"Moonachie",
    "sg:classifiers":[
        {
            "category":"Professional",
            "subcategory":"Management & Consulting",
            "type":"Services"
        }
    ],
    "sg:phone":"+1 201 896 8800",
    "sg:postcode":"07074",
    "sg:province":"NJ",
    "sg:tags":[
        "food"
    ],
    "sg:website":"www.fab-foods.com",
    "wof:name":"North American Food Concepts",
    "wof:placetype":"venue"
},
  "geometry": {"coordinates":[-74.074742,40.842025],"type":"Point"}
}