{
  "type": "Feature",
  "properties": {
    "iso:country":"US",
    "sg:address":"1427 Willow Ave",
    "sg:city":"Hoboken",
    "sg:classifiers":[
        {
            "category":"Autos & Motor Vehicles",
            "subcategory":"Auto Supplies",
            "type":"Retail Goods"
        }
    ],
    "sg:phone":"+1   ",
    "sg:postcode":"07030",
    "sg:province":"NJ",
    "wof:name":"Engine Depot LLC",
    "wof:placetype":"venue"
},
  "geometry": {"coordinates":[-74.02928300000001,40.754753],"type":"Point"}
}