{
  "type": "Feature",
  "properties": {
    "iso:country":"US",
    "sg:address":"259 Sunset Ave",
    "sg:city":"Englewood",
    "sg:classifiers":[
        {
            "category":"Health Services",
            "subcategory":"Health Practitioner",
            "type":"Services"
        }
    ],
    "sg:phone":"+1 908 995 9073",
    "sg:postcode":"07631",
    "sg:province":"NJ",
    "sg:tags":[
        "nutritionist"
    ],
    "wof:name":"Appetite For Healthy Living",
    "wof:placetype":"venue"
},
  "geometry": {"coordinates":[-73.97286699999999,40.878499],"type":"Point"}
}