{
  "type": "Feature",
  "properties": {
    "iso:country":"US",
    "sg:address":"1250 State Rte 35",
    "sg:city":"Middletown",
    "sg:classifiers":[
        {
            "category":"Professional",
            "subcategory":"Lawyer & Legal Services",
            "type":"Services"
        }
    ],
    "sg:phone":"+1 732 706 2955",
    "sg:postcode":"07748",
    "sg:province":"NJ",
    "sg:tags":[
        "attorney"
    ],
    "wof:name":"C Brian Daly",
    "wof:placetype":"venue"
},
  "geometry": {"coordinates":[-74.115976,40.399159],"type":"Point"}
}