{
  "type": "Feature",
  "properties": {
    "iso:country":"US",
    "sg:address":"555 North Ave Ste 11J",
    "sg:city":"Fort Lee",
    "sg:classifiers":[
        {
            "category":"Arts & Performance",
            "subcategory":"Arts Center",
            "type":"Entertainment"
        }
    ],
    "sg:postcode":"07024",
    "sg:province":"NJ",
    "sg:website":"www.notoriousmsg.com",
    "wof:name":"The Notorious MSG",
    "wof:placetype":"venue"
},
  "geometry": {"coordinates":[-73.982169,40.854024],"type":"Point"}
}