{
  "type": "Feature",
  "properties": {
    "addr:full":"204 White Horse Pike Barrington NJ 08007",
    "addr:housenumber":"204",
    "addr:postcode":"08007",
    "addr:street":"White Horse Pike",
    "iso:country":"US",
    "sg:address":"204 White Horse Pike",
    "sg:city":"Barrington",
    "sg:classifiers":[
        {
            "category":"Banks & Credit Unions",
            "subcategory":"Investment Brokerage",
            "type":"Services"
        },
        {
            "category":"Banks & Credit Unions",
            "subcategory":"Financial Services",
            "type":"Services"
        }
    ],
    "sg:phone":"+1 856 547 3339",
    "sg:postcode":"08007",
    "sg:province":"NJ",
    "sg:tags":[
        "investing",
        "advising"
    ],
    "sg:website":"www.ameripriseadvisors.com/",
    "wof:name":"Ameriprise Financial Advisors - Lose, Neal, Burcher, Cagande",
    "wof:placetype":"venue"
},
  "geometry": {"coordinates":[-75.04611300000001,39.873164],"type":"Point"}
}