{
  "type": "Feature",
  "properties": {
    "addr:full":"164 Belmont Ave Paterson NJ 07522",
    "addr:housenumber":"164",
    "addr:postcode":"07522",
    "addr:street":"Belmont Ave",
    "iso:country":"US",
    "sg:address":"164 Belmont Ave",
    "sg:city":"Paterson",
    "sg:classifiers":[
        {
            "category":"Food & Beverages",
            "subcategory":"Groceries & Convenience Stores",
            "type":"Retail Goods"
        }
    ],
    "sg:phone":"+1 973 790 7322",
    "sg:postcode":"07522",
    "sg:province":"NJ",
    "wof:name":"Bellmont Mini Store",
    "wof:placetype":"venue"
},
  "geometry": {"coordinates":[-74.181602,40.929199],"type":"Point"}
}