{
  "type": "Feature",
  "properties": {
    "addr:full":"71 N Dean St Englewood NJ 07631",
    "addr:housenumber":"71",
    "addr:postcode":"07631",
    "addr:street":"N Dean St",
    "iso:country":"US",
    "sg:address":"71 N Dean St",
    "sg:city":"Englewood",
    "sg:classifiers":[
        {
            "category":"Personal",
            "subcategory":"Beauty Salon",
            "type":"Services"
        }
    ],
    "sg:phone":"+1 201 816 1195",
    "sg:postcode":"07631",
    "sg:province":"NJ",
    "sg:tags":[
        "shop"
    ],
    "wof:name":"Englewood Nail Salon",
    "wof:placetype":"venue"
},
  "geometry": {"coordinates":[-73.973382,40.895345],"type":"Point"}
}