{
  "type": "Feature",
  "properties": {
    "addr:full":"511 Batchelor St Toms River NJ 08753",
    "addr:housenumber":"511",
    "addr:postcode":"08753",
    "addr:street":"Batchelor St",
    "iso:country":"US",
    "sg:address":"511 Batchelor St",
    "sg:city":"Toms River",
    "sg:classifiers":[
        {
            "category":"Building & Trades",
            "subcategory":"Construction",
            "type":"Services"
        }
    ],
    "sg:phone":"+1 732 341 9547",
    "sg:postcode":"08753",
    "sg:province":"NJ",
    "sg:tags":[
        "carpentry",
        "general"
    ],
    "wof:name":"Waterproof Construction",
    "wof:placetype":"venue"
},
  "geometry": {"coordinates":[-74.179778,39.956863],"type":"Point"}
}