{
  "type": "Feature",
  "properties": {
    "addr:full":"308 Dover Chester Rd Randolph NJ 07869",
    "addr:housenumber":"308",
    "addr:postcode":"07869",
    "addr:street":"Dover Chester Rd",
    "iso:country":"US",
    "sg:address":"308 Dover Chester Rd",
    "sg:city":"Randolph",
    "sg:classifiers":[
        {
            "category":"Building & Trades",
            "subcategory":"Construction",
            "type":"Services"
        }
    ],
    "sg:phone":"+1 973 584 2482",
    "sg:postcode":"07869",
    "sg:province":"NJ",
    "sg:tags":[
        "concrete",
        "contractor"
    ],
    "wof:name":"Seal Coat of New Jersey Inc",
    "wof:placetype":"venue"
},
  "geometry": {"coordinates":[-74.61259200000001,40.835204],"type":"Point"}
}