{
  "type": "Feature",
  "properties": {
    "iso:country":"US",
    "sg:address":"1218 Steeplechase Ct",
    "sg:city":"Toms River",
    "sg:classifiers":[
        {
            "category":"Professional",
            "type":"Services"
        }
    ],
    "sg:phone":"+1   ",
    "sg:postcode":"08755",
    "sg:province":"NJ",
    "wof:name":"Redlig Systems",
    "wof:placetype":"venue"
},
  "geometry": {"coordinates":[-74.20504,40.00401],"type":"Point"}
}