{
  "type": "Feature",
  "properties": {
    "iso:country":"US",
    "sg:address":"18 Hunter Pl",
    "sg:city":"Fair Lawn",
    "sg:classifiers":[
        {
            "category":"Professional",
            "subcategory":"Computer Services",
            "type":"Services"
        }
    ],
    "sg:phone":"+1 201 794 2221",
    "sg:postcode":"07410",
    "sg:province":"NJ",
    "sg:tags":[
        "consultant",
        "designer"
    ],
    "sg:website":"www.cfsimaging.com",
    "wof:name":"Choices For Svc In Imaging Inc",
    "wof:placetype":"venue"
},
  "geometry": {"coordinates":[-74.113094,40.950122],"type":"Point"}
}