{
  "type": "Feature",
  "properties": {
    "iso:country":"US",
    "sg:address":"72 Walraven Dr",
    "sg:city":"Teaneck",
    "sg:classifiers":[
        {
            "category":"Organizations",
            "subcategory":"Political Organization",
            "type":"Services"
        }
    ],
    "sg:phone":"+1 201 837 9492",
    "sg:postcode":"07666",
    "sg:province":"NJ",
    "wof:name":"Glass For Congress Inc",
    "wof:placetype":"venue"
},
  "geometry": {"coordinates":[-74.00421299999999,40.901102],"type":"Point"}
}