{
  "type": "Feature",
  "properties": {
    "addr:full":"17 Clinton Ave Westwood NJ 07675",
    "addr:housenumber":"17",
    "addr:postcode":"07675",
    "addr:street":"Clinton Ave",
    "iso:country":"US",
    "sg:address":"17 Clinton Ave",
    "sg:city":"Westwood",
    "sg:classifiers":[
        {
            "category":"Manufacturing",
            "subcategory":"Furniture",
            "type":"Manufacturing & Wholesale Goods"
        }
    ],
    "sg:phone":"+1 201 358 8194",
    "sg:postcode":"07675",
    "sg:province":"NJ",
    "sg:tags":[
        "woodwork",
        "kitchen",
        "architectural",
        "cabinet"
    ],
    "wof:name":"Peter Salerno Inc",
    "wof:placetype":"venue"
},
  "geometry": {"coordinates":[-74.04116399999999,40.991459],"type":"Point"}
}