{
  "type": "Feature",
  "properties": {
    "addr:full":"536 Irving Ave Bridgeton NJ 08302",
    "addr:housenumber":"536",
    "addr:postcode":"08302",
    "addr:street":"Irving Ave",
    "iso:country":"US",
    "sg:address":"536 Irving Ave",
    "sg:city":"Bridgeton",
    "sg:classifiers":[
        {
            "category":"Organizations",
            "subcategory":"Religious Organization",
            "type":"Services"
        }
    ],
    "sg:phone":"+1 856 451 1988",
    "sg:postcode":"08302",
    "sg:province":"NJ",
    "sg:tags":[
        "church"
    ],
    "wof:name":"True Liberty Church",
    "wof:placetype":"venue"
},
  "geometry": {"coordinates":[-75.210677,39.436032],"type":"Point"}
}