{
  "type": "Feature",
  "properties": {
    "iso:country":"US",
    "sg:address":"126 Jefferson Rd",
    "sg:city":"Princeton",
    "sg:classifiers":[
        {
            "category":"Manufacturing",
            "subcategory":"Printing",
            "type":"Manufacturing & Wholesale Goods"
        }
    ],
    "sg:phone":"+1 609 924 9784",
    "sg:postcode":"08540",
    "sg:province":"NJ",
    "sg:tags":[
        "book"
    ],
    "wof:name":"Tuttle & Quinn Publishing",
    "wof:placetype":"venue"
},
  "geometry": {"coordinates":[-74.659082,40.358116],"type":"Point"}
}