{
  "type": "Feature",
  "properties": {
    "iso:country":"US",
    "sg:address":"15 Princeton Ave",
    "sg:city":"Brick",
    "sg:classifiers":[
        {
            "category":"Health Services",
            "subcategory":"Doctor",
            "type":"Services"
        }
    ],
    "sg:phone":"+1 732 840 1199",
    "sg:postcode":"08724",
    "sg:province":"NJ",
    "sg:tags":[
        "dentist"
    ],
    "wof:name":"Princeton Dental",
    "wof:placetype":"venue"
},
  "geometry": {"coordinates":[-74.128381,40.067742],"type":"Point"}
}