{
  "type": "Feature",
  "properties": {
    "addr:full":"249 Kenilworth Blvd Kenilworth NJ 07033",
    "addr:housenumber":"249",
    "addr:postcode":"07033",
    "addr:street":"Kenilworth Blvd",
    "iso:country":"US",
    "sg:address":"249 Kenilworth Blvd",
    "sg:city":"Kenilworth",
    "sg:classifiers":[
        {
            "category":"Building & Trades",
            "subcategory":"Landscaping Services",
            "type":"Services"
        }
    ],
    "sg:phone":"+1 908 653 0349",
    "sg:postcode":"07033",
    "sg:province":"NJ",
    "sg:tags":[
        "landscape"
    ],
    "wof:name":"Universal Landscaping & Maint",
    "wof:placetype":"venue"
},
  "geometry": {"coordinates":[-74.303394,40.674742],"type":"Point"}
}