{
  "type": "Feature",
  "properties": {
    "iso:country":"US",
    "sg:address":"187 Columbia Tpke",
    "sg:city":"Florham Park",
    "sg:classifiers":[
        {
            "category":"Home & Garden",
            "subcategory":"Furniture",
            "type":"Retail Goods"
        }
    ],
    "sg:phone":"+1   ",
    "sg:postcode":"07932",
    "sg:province":"NJ",
    "wof:name":"Treasure Island Florham Park",
    "wof:placetype":"venue"
},
  "geometry": {"coordinates":[-74.392929,40.788509],"type":"Point"}
}