{
  "type": "Feature",
  "properties": {
    "addr:full":"174 State Rte 31 Flemington NJ 08822",
    "addr:housenumber":"174",
    "addr:postcode":"08822",
    "addr:street":"State Rte 31",
    "iso:country":"US",
    "sg:address":"174 State Rte 31",
    "sg:city":"Flemington",
    "sg:classifiers":[
        {
            "category":"Retail",
            "subcategory":"Repair Shop",
            "type":"Services"
        },
        {
            "category":"Building & Trades",
            "subcategory":"Construction",
            "type":"Services"
        }
    ],
    "sg:phone":"+1 908 782 8883",
    "sg:postcode":"08822",
    "sg:province":"NJ",
    "sg:tags":[
        "sewer",
        "contractor"
    ],
    "wof:name":"Riccioni G High Pressure Water",
    "wof:placetype":"venue"
},
  "geometry": {"coordinates":[-74.856841,40.529552],"type":"Point"}
}