{
  "type": "Feature",
  "properties": {
    "iso:country":"US",
    "sg:address":"3 Trenton Lakewood Rd",
    "sg:city":"Clarksburg",
    "sg:classifiers":[
        {
            "category":"Retail",
            "subcategory":"Auto Repair",
            "type":"Services"
        }
    ],
    "sg:phone":"+1 732 446 7770",
    "sg:postcode":"08510",
    "sg:province":"NJ",
    "sg:tags":[
        "body",
        "automobile",
        "painting"
    ],
    "wof:name":"Compact KARS Inc",
    "wof:placetype":"venue"
},
  "geometry": {"coordinates":[-74.417056,40.165488],"type":"Point"}
}