{
  "type": "Feature",
  "properties": {
    "addr:full":"182A Smith St Perth Amboy NJ 08861",
    "addr:housenumber":"182a",
    "addr:postcode":"08861",
    "addr:street":"Smith St",
    "iso:country":"US",
    "sg:address":"182A Smith St",
    "sg:city":"Perth Amboy",
    "sg:classifiers":[
        {
            "category":"Restaurant",
            "type":"Food & Drink"
        }
    ],
    "sg:phone":"+1 732 325 2953",
    "sg:postcode":"08861",
    "sg:province":"NJ",
    "sg:tags":[
        "vietnamese"
    ],
    "wof:name":"The Pho Zone Noodle Soup",
    "wof:placetype":"venue"
},
  "geometry": {"coordinates":[-74.270753,40.509408],"type":"Point"}
}