{
  "type": "Feature",
  "properties": {
    "addr:full":"1715 Amwell Rd Somerset NJ 08873",
    "addr:housenumber":"1715",
    "addr:postcode":"08873",
    "addr:street":"Amwell Rd",
    "iso:country":"US",
    "sg:address":"1715 Amwell Rd",
    "sg:city":"Somerset",
    "sg:classifiers":[
        {
            "category":"Professional",
            "subcategory":"Management & Consulting",
            "type":"Services"
        }
    ],
    "sg:phone":"+1 732 873 0433",
    "sg:postcode":"08873",
    "sg:province":"NJ",
    "sg:tags":[
        "consultant"
    ],
    "wof:name":"Waterstone Wealth Advisors LLC",
    "wof:placetype":"venue"
},
  "geometry": {"coordinates":[-74.526617,40.496389],"type":"Point"}
}