{
  "type": "Feature",
  "properties": {
    "addr:full":"143 West Mill Rd Long Valley NJ 07853",
    "addr:housenumber":"143",
    "addr:postcode":"07853",
    "addr:street":"West Mill Rd",
    "iso:country":"US",
    "sg:address":"143 West Mill Rd",
    "sg:city":"Long Valley",
    "sg:classifiers":[
        {
            "category":"Building & Trades",
            "subcategory":"Construction",
            "type":"Services"
        }
    ],
    "sg:phone":"+1 908 693 1928",
    "sg:postcode":"07853",
    "sg:province":"NJ",
    "sg:tags":[
        "contractor"
    ],
    "sg:website":"www.rkconstructionhome.com",
    "wof:name":"RK Construction Inc",
    "wof:placetype":"venue"
},
  "geometry": {"coordinates":[-74.792023,40.777283],"type":"Point"}
}