{
  "type": "Feature",
  "properties": {
    "addr:full":"79 1st Ave Paterson NJ 07514",
    "addr:housenumber":"79",
    "addr:postcode":"07514",
    "addr:street":"1St Ave",
    "iso:country":"US",
    "sg:address":"79 1st Ave",
    "sg:city":"Paterson",
    "sg:classifiers":[
        {
            "category":"Wholesale",
            "subcategory":"Motor Vehicles",
            "type":"Manufacturing & Wholesale Goods"
        }
    ],
    "sg:phone":"+1 973 279 5145",
    "sg:postcode":"07514",
    "sg:province":"NJ",
    "sg:tags":[
        "automobile",
        "used"
    ],
    "wof:name":"Riverside Wholesalers",
    "wof:placetype":"venue"
},
  "geometry": {"coordinates":[-74.145004,40.940316],"type":"Point"}
}