{
  "type": "Feature",
  "properties": {
    "addr:full":"3721 Bloomingdale Dr Hillsborough NJ 08844",
    "addr:housenumber":"3721",
    "addr:postcode":"08844",
    "addr:street":"Bloomingdale Dr",
    "iso:country":"US",
    "sg:address":"3721 Bloomingdale Dr",
    "sg:city":"Hillsborough",
    "sg:classifiers":[
        {
            "category":"Retail",
            "subcategory":"Auto Repair",
            "type":"Services"
        }
    ],
    "sg:phone":"+1 908 904 9312",
    "sg:postcode":"08844",
    "sg:province":"NJ",
    "sg:tags":[
        "repairing",
        "automobile"
    ],
    "wof:name":"C K's Automotive",
    "wof:placetype":"venue"
},
  "geometry": {"coordinates":[-74.655648,40.501604],"type":"Point"}
}