{
  "type": "Feature",
  "properties": {
    "iso:country":"US",
    "sg:address":"375 Hessian Ave",
    "sg:city":"Woodbury",
    "sg:classifiers":[
        {
            "category":"Professional",
            "type":"Services"
        }
    ],
    "sg:phone":"+1   ",
    "sg:postcode":"08096",
    "sg:province":"NJ",
    "wof:name":"Molloy",
    "wof:placetype":"venue"
},
  "geometry": {"coordinates":[-75.153744,39.85767],"type":"Point"}
}