{
  "type": "Feature",
  "properties": {
    "iso:country":"US",
    "sg:address":"140 N Black Horse Pike",
    "sg:city":"Runnemede",
    "sg:classifiers":[
        {
            "category":"Retail",
            "subcategory":"Repair Shop",
            "type":"Services"
        }
    ],
    "sg:phone":"+1 856 227 8959",
    "sg:postcode":"08078",
    "sg:province":"NJ",
    "sg:tags":[
        "appliance"
    ],
    "wof:name":"John Fox's Gloucester Appl",
    "wof:placetype":"venue"
},
  "geometry": {"coordinates":[-75.071853,39.846911],"type":"Point"}
}