{
  "type": "Feature",
  "properties": {
    "addr:full":"485 Main St Fort Lee NJ 07024",
    "addr:housenumber":"485",
    "addr:postcode":"07024",
    "addr:street":"Main St",
    "iso:country":"US",
    "sg:address":"485 Main St",
    "sg:city":"Fort Lee",
    "sg:classifiers":[
        {
            "category":"Restaurant",
            "type":"Food & Drink"
        }
    ],
    "sg:phone":"+1 201 242 1333",
    "sg:postcode":"07024",
    "sg:province":"NJ",
    "sg:tags":[
        "korean"
    ],
    "wof:name":"Gam Mee Ok Restaurant",
    "wof:placetype":"venue"
},
  "geometry": {"coordinates":[-73.977557,40.855459],"type":"Point"}
}