{
  "type": "Feature",
  "properties": {
    "addr:full":"5 State Rte 23 Wayne NJ 07470",
    "addr:housenumber":"5",
    "addr:postcode":"07470",
    "addr:street":"State Rte 23",
    "iso:country":"US",
    "sg:address":"5 State Rte 23",
    "sg:city":"Wayne",
    "sg:classifiers":[
        {
            "category":"Retail",
            "subcategory":"Car Wash",
            "type":"Services"
        }
    ],
    "sg:phone":"+1 973 785 8622",
    "sg:postcode":"07470",
    "sg:province":"NJ",
    "sg:tags":[
        "automobile",
        "detail",
        "clean"
    ],
    "wof:name":"Willowbrook Car & Van Wash",
    "wof:placetype":"venue"
},
  "geometry": {"coordinates":[-74.246786,40.888051],"type":"Point"}
}