{
  "type": "Feature",
  "properties": {
    "addr:full":"129 Kearny Ave Kearny NJ 07032",
    "addr:housenumber":"129",
    "addr:postcode":"07032",
    "addr:street":"Kearny Ave",
    "iso:country":"US",
    "sg:address":"129 Kearny Ave",
    "sg:city":"Kearny",
    "sg:classifiers":[
        {
            "category":"Building & Trades",
            "subcategory":"Construction",
            "type":"Services"
        }
    ],
    "sg:phone":"+1 201 955 2254",
    "sg:postcode":"07032",
    "sg:province":"NJ",
    "sg:tags":[
        "home",
        "improvement"
    ],
    "wof:name":"Sil Andre Home Improvement",
    "wof:placetype":"venue"
},
  "geometry": {"coordinates":[-74.155005,40.755801],"type":"Point"}
}