{
  "type": "Feature",
  "properties": {
    "addr:full":"921 Main St Boonton NJ 07005",
    "addr:housenumber":"921",
    "addr:postcode":"07005",
    "addr:street":"Main St",
    "iso:country":"US",
    "sg:address":"921 Main St",
    "sg:city":"Boonton",
    "sg:classifiers":[
        {
            "category":"Home & Garden",
            "subcategory":"Home Furnishings",
            "type":"Retail Goods"
        }
    ],
    "sg:phone":"+1 973 265 8536",
    "sg:postcode":"07005",
    "sg:province":"NJ",
    "sg:tags":[
        "window",
        "covering"
    ],
    "wof:name":"Robert Scott Window Fashions",
    "wof:placetype":"venue"
},
  "geometry": {"coordinates":[-74.41390699999999,40.906516],"type":"Point"}
}