{
  "type": "Feature",
  "properties": {
    "iso:country":"US",
    "sg:address":"1640 E State St",
    "sg:city":"Trenton",
    "sg:classifiers":[
        {
            "category":"Retail",
            "subcategory":"Self-service Laundry",
            "type":"Services"
        },
        {
            "category":"Retail",
            "subcategory":"Laundry & Dry Cleaning",
            "type":"Services"
        }
    ],
    "sg:phone":"+1 609 890 8366",
    "sg:postcode":"08609",
    "sg:province":"NJ",
    "sg:tags":[
        "coin",
        "power"
    ],
    "wof:name":"A & G Laundromat",
    "wof:placetype":"venue"
},
  "geometry": {"coordinates":[-74.73183400000001,40.23199],"type":"Point"}
}