{
  "type": "Feature",
  "properties": {
    "iso:country":"US",
    "sg:address":"1555 State Rte 73",
    "sg:city":"Pennsauken",
    "sg:classifiers":[
        {
            "category":"Shopping",
            "subcategory":"Discount & Variety Stores",
            "type":"Retail Goods"
        },
        {
            "category":"Wholesale",
            "subcategory":"Books, Periodicals, & Newspapers",
            "type":"Manufacturing & Wholesale Goods"
        }
    ],
    "sg:phone":"+1 856 662 3344",
    "sg:postcode":"08110",
    "sg:province":"NJ",
    "sg:tags":[
        "post",
        "trading"
    ],
    "sg:website":"www.muffsandcuffs.com",
    "wof:name":"William's Trading Co Inc",
    "wof:placetype":"venue"
},
  "geometry": {"coordinates":[-75.022057,39.988348],"type":"Point"}
}