{
  "type": "Feature",
  "properties": {
    "iso:country":"US",
    "sg:address":"33 Darwin Ave",
    "sg:city":"Rutherford",
    "sg:classifiers":[
        {
            "category":"Building & Trades",
            "subcategory":"Plumbing",
            "type":"Services"
        }
    ],
    "sg:phone":"+1 201 933 9098",
    "sg:postcode":"07070",
    "sg:province":"NJ",
    "sg:tags":[
        "contractor"
    ],
    "wof:name":"Maik Co",
    "wof:placetype":"venue"
},
  "geometry": {"coordinates":[-74.118741,40.842011],"type":"Point"}
}