{
  "type": "Feature",
  "properties": {
    "iso:country":"US",
    "sg:address":"3215 John F Kennedy Blvd",
    "sg:city":"Jersey City",
    "sg:classifiers":[
        {
            "category":"Professional",
            "subcategory":"Lawyer & Legal Services",
            "type":"Services"
        }
    ],
    "sg:phone":"+1 201 656 8898",
    "sg:postcode":"07306",
    "sg:province":"NJ",
    "sg:tags":[
        "attorney"
    ],
    "wof:name":"Francis R Monahan Jr",
    "wof:placetype":"venue"
},
  "geometry": {"coordinates":[-74.060025,40.742296],"type":"Point"}
}