{
  "type": "Feature",
  "properties": {
    "addr:full":"402 36th St Union City NJ 07087",
    "addr:housenumber":"402",
    "addr:postcode":"07087",
    "addr:street":"36Th St",
    "iso:country":"US",
    "sg:address":"402 36th St",
    "sg:city":"Union City",
    "sg:classifiers":[
        {
            "category":"Health Services",
            "subcategory":"Dentist",
            "type":"Services"
        }
    ],
    "sg:phone":"+1 201 866 3299",
    "sg:postcode":"07087",
    "sg:province":"NJ",
    "wof:name":"United Dental Center",
    "wof:placetype":"venue"
},
  "geometry": {"coordinates":[-74.026703,40.7738],"type":"Point"}
}