{
  "type": "Feature",
  "properties": {
    "iso:country":"US",
    "sg:address":"201 Spring Garden Rd",
    "sg:city":"Hammonton",
    "sg:classifiers":[
        {
            "category":"Education",
            "subcategory":"Library",
            "type":"Public Place"
        }
    ],
    "sg:phone":"+1 609 561 1700",
    "sg:postcode":"08037",
    "sg:province":"NJ",
    "sg:tags":[
        "special",
        "interest"
    ],
    "wof:name":"Ancora Psychiatric Hosp Libr",
    "wof:placetype":"venue"
},
  "geometry": {"coordinates":[-74.860912,39.671754],"type":"Point"}
}