{
  "type": "Feature",
  "properties": {
    "addr:full":"214 Desoto Pl Cliffside Park NJ 07010",
    "addr:housenumber":"214",
    "addr:postcode":"07010",
    "addr:street":"Desoto Pl",
    "iso:country":"US",
    "sg:address":"214 Desoto Pl",
    "sg:city":"Cliffside Park",
    "sg:classifiers":[
        {
            "category":"Communications",
            "subcategory":"Film & Video Production",
            "type":"Services"
        }
    ],
    "sg:phone":"+1 201 943 7195",
    "sg:postcode":"07010",
    "sg:province":"NJ",
    "sg:tags":[
        "motion"
    ],
    "wof:name":"Up Past Midnight Productions L",
    "wof:placetype":"venue"
},
  "geometry": {"coordinates":[-73.99588900000001,40.809361],"type":"Point"}
}