{
  "type": "Feature",
  "properties": {
    "iso:country":"US",
    "sg:address":"505 Duser Rd",
    "sg:city":"Burlington",
    "sg:classifiers":[
        {
            "category":"Building & Trades",
            "subcategory":"Construction",
            "type":"Services"
        }
    ],
    "sg:phone":"+1 609 387 1922",
    "sg:postcode":"08016",
    "sg:province":"NJ",
    "sg:tags":[
        "hanging",
        "contractor"
    ],
    "wof:name":"Michaels Custom Painting",
    "wof:placetype":"venue"
},
  "geometry": {"coordinates":[-74.840131,40.075399],"type":"Point"}
}