{
  "type": "Feature",
  "properties": {
    "iso:country":"US",
    "sg:address":"50 S Franklin Tpke",
    "sg:city":"Ramsey",
    "sg:classifiers":[
        {
            "category":"Manufacturing",
            "subcategory":"Printing",
            "type":"Manufacturing & Wholesale Goods"
        }
    ],
    "sg:phone":"+1 201 236 9336",
    "sg:postcode":"07446",
    "sg:province":"NJ",
    "sg:tags":[
        "publisher"
    ],
    "wof:name":"Homiletic & Pastoral Review",
    "wof:placetype":"venue"
},
  "geometry": {"coordinates":[-74.131748,41.05688],"type":"Point"}
}