{
  "type": "Feature",
  "properties": {
    "iso:country":"US",
    "sg:address":"98 Broadway",
    "sg:city":"Passaic",
    "sg:classifiers":[
        {
            "category":"Cinema",
            "subcategory":"Movie Rental",
            "type":"Entertainment"
        }
    ],
    "sg:phone":"+1 973 779 7336",
    "sg:postcode":"07055",
    "sg:province":"NJ",
    "sg:tags":[
        "game",
        "video"
    ],
    "wof:name":"Sagar Video of Passaic",
    "wof:placetype":"venue"
},
  "geometry": {"coordinates":[-74.130334,40.859041],"type":"Point"}
}