{
  "type": "Feature",
  "properties": {
    "addr:full":"154 Newark Ave Jersey City NJ 07302",
    "addr:housenumber":"154",
    "addr:postcode":"07302",
    "addr:street":"Newark Ave",
    "iso:country":"US",
    "sg:address":"154 Newark Ave",
    "sg:city":"Jersey City",
    "sg:classifiers":[
        {
            "category":"Utilities",
            "subcategory":"Mobile Phone",
            "type":"Services"
        }
    ],
    "sg:phone":"+1 201 332 0477",
    "sg:postcode":"07302",
    "sg:province":"NJ",
    "sg:tags":[
        "communication",
        "radiotelephone"
    ],
    "wof:name":"Wireless Center",
    "wof:placetype":"venue"
},
  "geometry": {"coordinates":[-74.04337,40.720121],"type":"Point"}
}