{
  "type": "Feature",
  "properties": {
    "addr:full":"7 Smith St Paterson NJ 07505",
    "addr:housenumber":"7",
    "addr:postcode":"07505",
    "addr:street":"Smith St",
    "iso:country":"US",
    "sg:address":"7 Smith St",
    "sg:city":"Paterson",
    "sg:classifiers":[
        {
            "category":"Shopping",
            "type":"Retail Goods"
        }
    ],
    "sg:phone":"+1 973 742 2300",
    "sg:postcode":"07505",
    "sg:province":"NJ",
    "sg:tags":[
        "telephone",
        "cellular"
    ],
    "wof:name":"Bargains",
    "wof:placetype":"venue"
},
  "geometry": {"coordinates":[-74.172286,40.915397],"type":"Point"}
}