{
  "type": "Feature",
  "properties": {
    "iso:country":"US",
    "sg:address":"364 W Grand Ave",
    "sg:city":"Rahway",
    "sg:classifiers":[
        {
            "category":"Organizations",
            "subcategory":"Labor Organization",
            "type":"Services"
        }
    ],
    "sg:phone":"+1 732 382 1221",
    "sg:postcode":"07065",
    "sg:province":"NJ",
    "wof:name":"Pace Local 575",
    "wof:placetype":"venue"
},
  "geometry": {"coordinates":[-74.277416,40.613197],"type":"Point"}
}