{
  "type": "Feature",
  "properties": {
    "iso:country":"US",
    "sg:address":"23 Laurel Rd E",
    "sg:city":"Stratford",
    "sg:classifiers":[
        {
            "category":"Health Services",
            "subcategory":"Doctor",
            "type":"Services"
        }
    ],
    "sg:phone":"+1 856 346 2400",
    "sg:postcode":"08084",
    "sg:province":"NJ",
    "sg:tags":[
        "physician",
        "surgeon"
    ],
    "wof:name":"Laurel Pediatrics",
    "wof:placetype":"venue"
},
  "geometry": {"coordinates":[-75.009017,39.828575],"type":"Point"}
}