{
  "type": "Feature",
  "properties": {
    "addr:full":"2543 N Blue Bell Rd Franklinville NJ 08322",
    "addr:housenumber":"2543",
    "addr:postcode":"08322",
    "addr:street":"N Blue Bell Rd",
    "iso:country":"US",
    "sg:address":"2543 N Blue Bell Rd",
    "sg:city":"Franklinville",
    "sg:classifiers":[
        {
            "category":"Building & Trades",
            "subcategory":"Construction",
            "type":"Services"
        }
    ],
    "sg:phone":"+1 856 697 5406",
    "sg:postcode":"08322",
    "sg:province":"NJ",
    "sg:tags":[
        "carpentry",
        "contractor"
    ],
    "wof:name":"Dunright",
    "wof:placetype":"venue"
},
  "geometry": {"coordinates":[-74.975827,39.582254],"type":"Point"}
}