{
  "type": "Feature",
  "properties": {
    "addr:full":"795 Woodlane Rd Westampton NJ 08060",
    "addr:housenumber":"795",
    "addr:postcode":"08060",
    "addr:street":"Woodlane Rd",
    "iso:country":"US",
    "sg:address":"795 Woodlane Rd",
    "sg:city":"Westampton",
    "sg:classifiers":[
        {
            "category":"Education",
            "subcategory":"Special Training",
            "type":"Public Place"
        }
    ],
    "sg:phone":"+1 609 702 0500",
    "sg:postcode":"08060",
    "sg:province":"NJ",
    "sg:tags":[
        "school",
        "specialty"
    ],
    "wof:name":"Educational Services Unit",
    "wof:placetype":"venue"
},
  "geometry": {"coordinates":[-74.80491000000001,40.012037],"type":"Point"}
}