{
  "type": "Feature",
  "properties": {
    "addr:full":"3032 Valley Rd Basking Ridge NJ 07920",
    "addr:housenumber":"3032",
    "addr:postcode":"07920",
    "addr:street":"Valley Rd",
    "iso:country":"US",
    "sg:address":"3032 Valley Rd",
    "sg:city":"Basking Ridge",
    "sg:classifiers":[
        {
            "category":"Building & Trades",
            "subcategory":"Electrical",
            "type":"Services"
        }
    ],
    "sg:phone":"+1 908 647 5288",
    "sg:postcode":"07920",
    "sg:province":"NJ",
    "sg:tags":[
        "electrical",
        "contractor"
    ],
    "wof:name":"R Menzel Electrical Cont",
    "wof:placetype":"venue"
},
  "geometry": {"coordinates":[-74.530106,40.664791],"type":"Point"}
}