{
  "type": "Feature",
  "properties": {
    "iso:country":"US",
    "sg:address":"440 Sylvan Ave",
    "sg:city":"Englewood Cliffs",
    "sg:classifiers":[
        {
            "category":"Professional",
            "subcategory":"Lawyer & Legal Services",
            "type":"Services"
        }
    ],
    "sg:phone":"+1 201 567 6869",
    "sg:postcode":"07632",
    "sg:province":"NJ",
    "sg:tags":[
        "attorney"
    ],
    "wof:name":"Peter A Cross",
    "wof:placetype":"venue"
},
  "geometry": {"coordinates":[-73.953282,40.873499],"type":"Point"}
}