{
  "type": "Feature",
  "properties": {
    "iso:country":"US",
    "sg:address":"116 Salem Rd",
    "sg:city":"North Brunswick",
    "sg:classifiers":[
        {
            "category":"Professional",
            "subcategory":"Computer Services",
            "type":"Services"
        }
    ],
    "sg:phone":"+1 732 297 8908",
    "sg:postcode":"08902",
    "sg:province":"NJ",
    "sg:tags":[
        "developer"
    ],
    "wof:name":"Paksys Software LLC",
    "wof:placetype":"venue"
},
  "geometry": {"coordinates":[-74.487516,40.438097],"type":"Point"}
}