{
  "type": "Feature",
  "properties": {
    "addr:full":"18 West Dr Livingston NJ 07039",
    "addr:housenumber":"18",
    "addr:postcode":"07039",
    "addr:street":"West Dr",
    "iso:country":"US",
    "sg:address":"18 West Dr",
    "sg:city":"Livingston",
    "sg:classifiers":[
        {
            "category":"Professional",
            "type":"Services"
        }
    ],
    "sg:phone":"+1   ",
    "sg:postcode":"07039",
    "sg:province":"NJ",
    "wof:name":"Jonathan Bressman",
    "wof:placetype":"venue"
},
  "geometry": {"coordinates":[-74.344188,40.780052],"type":"Point"}
}