{
  "type": "Feature",
  "properties": {
    "addr:full":"194 Co Rd 526 Allentown NJ 08501",
    "addr:housenumber":"194;526",
    "addr:postcode":"08501",
    "addr:street":"Co Rd",
    "iso:country":"US",
    "sg:address":"194 Co Rd 526",
    "sg:city":"Allentown",
    "sg:classifiers":[
        {
            "category":"Manufacturing",
            "subcategory":"Retail Goods",
            "type":"Manufacturing & Wholesale Goods"
        }
    ],
    "sg:phone":"+1 609 259 3114",
    "sg:postcode":"08501",
    "sg:province":"NJ",
    "sg:tags":[
        "florist"
    ],
    "sg:website":"www.kubepak.com",
    "wof:name":"KUBE-Pak Garden Plants",
    "wof:placetype":"venue"
},
  "geometry": {"coordinates":[-74.53623399999999,40.170556],"type":"Point"}
}