{
  "type": "Feature",
  "properties": {
    "addr:full":"860 Union Mill Rd Mount Laurel NJ 08054",
    "addr:housenumber":"860",
    "addr:postcode":"08054",
    "addr:street":"Union Mill Rd",
    "iso:country":"US",
    "sg:address":"860 Union Mill Rd",
    "sg:city":"Mount Laurel",
    "sg:classifiers":[
        {
            "category":"Banks & Credit Unions",
            "subcategory":"Bank",
            "type":"Services"
        }
    ],
    "sg:phone":"+1   ",
    "sg:postcode":"08054",
    "sg:province":"NJ",
    "sg:tags":[
        "savings",
        "institution"
    ],
    "wof:name":"Wachovia Bank National Assn",
    "wof:placetype":"venue"
},
  "geometry": {"coordinates":[-74.91373900000001,39.940467],"type":"Point"}
}