{
  "type": "Feature",
  "properties": {
    "iso:country":"US",
    "sg:address":"219 Quaker Church Rd",
    "sg:city":"Randolph",
    "sg:classifiers":[
        {
            "category":"Professional",
            "subcategory":"Accounting & Tax Preparation",
            "type":"Services"
        }
    ],
    "sg:phone":"+1 973 366 2265",
    "sg:postcode":"07869",
    "sg:province":"NJ",
    "sg:tags":[
        "accountant"
    ],
    "wof:name":"Harry J Lufft",
    "wof:placetype":"venue"
},
  "geometry": {"coordinates":[-74.567365,40.864031],"type":"Point"}
}