{
  "type": "Feature",
  "properties": {
    "iso:country":"US",
    "sg:address":"431 Martn Lthr Kng Jr Dr",
    "sg:city":"Jersey City",
    "sg:classifiers":[
        {
            "category":"Food & Beverages",
            "subcategory":"Liquor & Beverages",
            "type":"Retail Goods"
        }
    ],
    "sg:phone":"+1 201 432 6054",
    "sg:postcode":"07304",
    "sg:province":"NJ",
    "sg:tags":[
        "beer",
        "spirit",
        "wine"
    ],
    "wof:name":"Jersey City Liquors",
    "wof:placetype":"venue"
},
  "geometry": {"coordinates":[-74.077003,40.7132],"type":"Point"}
}