{
  "type": "Feature",
  "properties": {
    "iso:country":"US",
    "sg:address":"60 Crow Hill Rd",
    "sg:city":"Freehold",
    "sg:classifiers":[
        {
            "category":"Building & Trades",
            "subcategory":"Construction",
            "type":"Services"
        }
    ],
    "sg:phone":"+1 732 681 7750",
    "sg:postcode":"07728",
    "sg:province":"NJ",
    "sg:tags":[
        "bathroom",
        "remodeling"
    ],
    "wof:name":"J P's Bath & Kitchen Specs",
    "wof:placetype":"venue"
},
  "geometry": {"coordinates":[-74.22874299999999,40.250001],"type":"Point"}
}