{
  "type": "Feature",
  "properties": {
    "iso:country":"US",
    "sg:address":"380 Palisade Ave",
    "sg:city":"Jersey City",
    "sg:classifiers":[
        {
            "category":"Restaurant",
            "type":"Food & Drink"
        }
    ],
    "sg:phone":"+1 201 386 8411",
    "sg:postcode":"07307",
    "sg:province":"NJ",
    "sg:tags":[
        "eating"
    ],
    "wof:name":"Robalino's Restaurant",
    "wof:placetype":"venue"
},
  "geometry": {"coordinates":[-74.04540299999999,40.742599],"type":"Point"}
}