{
  "type": "Feature",
  "properties": {
    "addr:full":"116 Ford St Wayne NJ 07470",
    "addr:housenumber":"116",
    "addr:postcode":"07470",
    "addr:street":"Ford St",
    "iso:country":"US",
    "sg:address":"116 Ford St",
    "sg:city":"Wayne",
    "sg:classifiers":[
        {
            "category":"Retail",
            "subcategory":"Auto Repair",
            "type":"Services"
        }
    ],
    "sg:phone":"+1 973 696 9390",
    "sg:postcode":"07470",
    "sg:province":"NJ",
    "sg:tags":[
        "towing"
    ],
    "sg:website":"www.jmtowing.com",
    "wof:name":"J & M Towing",
    "wof:placetype":"venue"
},
  "geometry": {"coordinates":[-74.277603,40.926102],"type":"Point"}
}