{
  "type": "Feature",
  "properties": {
    "addr:full":"159 Ridgeview Pl Boonton NJ 07005",
    "addr:housenumber":"159",
    "addr:postcode":"07005",
    "addr:street":"Ridgeview Pl",
    "iso:country":"US",
    "sg:address":"159 Ridgeview Pl",
    "sg:city":"Boonton",
    "sg:classifiers":[
        {
            "category":"Social Services",
            "type":"Services"
        }
    ],
    "sg:phone":"+1 973 335 3695",
    "sg:postcode":"07005",
    "sg:province":"NJ",
    "sg:tags":[
        "hospital",
        "specialty"
    ],
    "wof:name":"McGreal Maureen PH D",
    "wof:placetype":"venue"
},
  "geometry": {"coordinates":[-74.421526,40.903184],"type":"Point"}
}