{
  "type": "Feature",
  "properties": {
    "iso:country":"US",
    "sg:address":"486 Cook Rd",
    "sg:city":"Jackson",
    "sg:classifiers":[
        {
            "category":"Building & Trades",
            "subcategory":"Landscaping Services",
            "type":"Services"
        }
    ],
    "sg:phone":"+1 732 367 5334",
    "sg:postcode":"08527",
    "sg:province":"NJ",
    "wof:name":"Scotts Outdoor Works",
    "wof:placetype":"venue"
},
  "geometry": {"coordinates":[-74.29549299999999,40.15076],"type":"Point"}
}