{
  "type": "Feature",
  "properties": {
    "addr:full":"2400 Arctic Ave Atlantic City NJ 08401",
    "addr:housenumber":"2400",
    "addr:postcode":"08401",
    "addr:street":"Arctic Ave",
    "iso:country":"US",
    "sg:address":"2400 Arctic Ave",
    "sg:city":"Atlantic City",
    "sg:classifiers":[
        {
            "category":"Restaurant",
            "type":"Food & Drink"
        }
    ],
    "sg:menulink":"http://www.allmenus.com/nj/atlantic-city/279637-angelonis-ii/menu/",
    "sg:phone":"+1 609 344 7875",
    "sg:postcode":"08401",
    "sg:province":"NJ",
    "sg:tags":[
        "italian"
    ],
    "wof:name":"Angeloni's II",
    "wof:placetype":"venue"
},
  "geometry": {"coordinates":[-74.441754,39.358433],"type":"Point"}
}