{
  "type": "Feature",
  "properties": {
    "iso:country":"US",
    "sg:address":"1003 Bergen St",
    "sg:city":"Newark",
    "sg:classifiers":[
        {
            "category":"Building & Trades",
            "subcategory":"Locksmith",
            "type":"Services"
        }
    ],
    "sg:phone":"+1 973 735 1551",
    "sg:postcode":"07112",
    "sg:province":"NJ",
    "sg:tags":[
        "key"
    ],
    "wof:name":"Locksmith 24 Hr 7 Day",
    "wof:placetype":"venue"
},
  "geometry": {"coordinates":[-74.206965,40.709747],"type":"Point"}
}