{
  "type": "Feature",
  "properties": {
    "addr:full":"338 Ferry St Newark NJ 07105",
    "addr:housenumber":"338",
    "addr:postcode":"07105",
    "addr:street":"Ferry St",
    "iso:country":"US",
    "sg:address":"338 Ferry St",
    "sg:city":"Newark",
    "sg:classifiers":[
        {
            "category":"Restaurant",
            "type":"Food & Drink"
        }
    ],
    "sg:phone":"+1 973 491 6600",
    "sg:postcode":"07105",
    "sg:province":"NJ",
    "sg:tags":[
        "american",
        "latin"
    ],
    "wof:name":"Latin American Restaurant",
    "wof:placetype":"venue"
},
  "geometry": {"coordinates":[-74.148201,40.729301],"type":"Point"}
}