{
  "type": "Feature",
  "properties": {
    "iso:country":"US",
    "sg:address":"437 Webster Ave",
    "sg:city":"Piscataway",
    "sg:classifiers":[
        {
            "category":"Professional",
            "subcategory":"Management & Consulting",
            "type":"Services"
        }
    ],
    "sg:phone":"+1   ",
    "sg:postcode":"08854",
    "sg:province":"NJ",
    "sg:tags":[
        "computer",
        "desktop"
    ],
    "wof:name":"R Leslie Consulting",
    "wof:placetype":"venue"
},
  "geometry": {"coordinates":[-74.46673699999999,40.580473],"type":"Point"}
}