{
  "type": "Feature",
  "properties": {
    "iso:country":"US",
    "sg:address":"1874 Marlton Pike E",
    "sg:city":"Cherry Hill",
    "sg:classifiers":[
        {
            "category":"Building & Trades",
            "subcategory":"Construction",
            "type":"Services"
        }
    ],
    "sg:phone":"+1 856 751 3901",
    "sg:postcode":"08003",
    "sg:province":"NJ",
    "sg:tags":[
        "contractor"
    ],
    "wof:name":"A N Construction LLC",
    "wof:placetype":"venue"
},
  "geometry": {"coordinates":[-74.969042,39.903793],"type":"Point"}
}