{
  "type": "Feature",
  "properties": {
    "addr:full":"17 Metro Vista Dr Hawthorne NJ 07506",
    "addr:housenumber":"17",
    "addr:postcode":"07506",
    "addr:street":"Metro Vista Dr",
    "iso:country":"US",
    "sg:address":"17 Metro Vista Dr",
    "sg:city":"Hawthorne",
    "sg:classifiers":[
        {
            "category":"Health Services",
            "subcategory":"Doctor",
            "type":"Services"
        }
    ],
    "sg:phone":"+1 973 423 5356",
    "sg:postcode":"07506",
    "sg:province":"NJ",
    "sg:tags":[
        "medical"
    ],
    "wof:name":"Amer Kashoga MD",
    "wof:placetype":"venue"
},
  "geometry": {"coordinates":[-74.16589399999999,40.956778],"type":"Point"}
}