{
  "type": "Feature",
  "properties": {
    "iso:country":"US",
    "sg:address":"23 S Union Ave",
    "sg:city":"Cranford",
    "sg:classifiers":[
        {
            "category":"Food & Beverages",
            "subcategory":"Meat & Fish",
            "type":"Retail Goods"
        }
    ],
    "sg:phone":"+1 908 272 4980",
    "sg:postcode":"07016",
    "sg:province":"NJ",
    "sg:tags":[
        "shop",
        "grocery"
    ],
    "wof:name":"Perrotti's Quality Meats & Groceries",
    "wof:placetype":"venue"
},
  "geometry": {"coordinates":[-74.30590100000001,40.653999],"type":"Point"}
}