{
  "type": "Feature",
  "properties": {
    "addr:full":"520 Adams St Hoboken NJ 07030",
    "addr:housenumber":"520",
    "addr:postcode":"07030",
    "addr:street":"Adams St",
    "iso:country":"US",
    "sg:address":"520 Adams St",
    "sg:city":"Hoboken",
    "sg:classifiers":[
        {
            "category":"Professional",
            "subcategory":"Art Services",
            "type":"Services"
        }
    ],
    "sg:phone":"+1 201 653 5542",
    "sg:postcode":"07030",
    "sg:province":"NJ",
    "sg:tags":[
        "photography",
        "commercial"
    ],
    "wof:name":"Burstein Goldman Photography",
    "wof:placetype":"venue"
},
  "geometry": {"coordinates":[-74.035613,40.744319],"type":"Point"}
}