{
  "type": "Feature",
  "properties": {
    "iso:country":"US",
    "sg:address":"765 Anderson Ave",
    "sg:city":"Cliffside Park",
    "sg:classifiers":[
        {
            "category":"Professional",
            "subcategory":"Lawyer & Legal Services",
            "type":"Services"
        }
    ],
    "sg:phone":"+1 201 945 5337",
    "sg:postcode":"07010",
    "sg:province":"NJ",
    "wof:name":"Dorian Hward M Attrnery At Law",
    "wof:placetype":"venue"
},
  "geometry": {"coordinates":[-73.98538499999999,40.830812],"type":"Point"}
}