{
  "type": "Feature",
  "properties": {
    "iso:country":"US",
    "sg:address":"2 Riverview Dr",
    "sg:city":"Somerset",
    "sg:classifiers":[
        {
            "category":"Professional",
            "type":"Services"
        }
    ],
    "sg:phone":"+1 732 805 0995",
    "sg:postcode":"08882",
    "sg:province":"NJ",
    "sg:tags":[
        "establishment"
    ],
    "wof:name":"Callsoft Inc",
    "wof:placetype":"venue"
},
  "geometry": {"coordinates":[-74.368031,40.445658],"type":"Point"}
}