{
  "type": "Feature",
  "properties": {
    "iso:country":"US",
    "sg:address":"29 Copeland Rd",
    "sg:city":"Denville",
    "sg:classifiers":[
        {
            "category":"Professional",
            "subcategory":"Detective & Security Services",
            "type":"Services"
        }
    ],
    "sg:phone":"+1 973 989 8390",
    "sg:postcode":"07834",
    "sg:province":"NJ",
    "sg:tags":[
        "system"
    ],
    "wof:name":"C K Electronics",
    "wof:placetype":"venue"
},
  "geometry": {"coordinates":[-74.525966,40.844798],"type":"Point"}
}