{
  "type": "Feature",
  "properties": {
    "addr:full":"174 High St Leesburg NJ 08327",
    "addr:housenumber":"174",
    "addr:postcode":"08327",
    "addr:street":"High St",
    "iso:country":"US",
    "sg:address":"174 High St",
    "sg:city":"Leesburg",
    "sg:classifiers":[
        {
            "category":"Government",
            "subcategory":"Post Office",
            "type":"Public Place"
        }
    ],
    "sg:phone":"+1 856 785 0300",
    "sg:postcode":"08327",
    "sg:province":"NJ",
    "wof:name":"US Post Office",
    "wof:placetype":"venue"
},
  "geometry": {"coordinates":[-74.9892,39.258094],"type":"Point"}
}