{
  "type": "Feature",
  "properties": {
    "addr:full":"27 Haas Rd Basking Ridge NJ 07920",
    "addr:housenumber":"27",
    "addr:postcode":"07920",
    "addr:street":"Haas Rd",
    "iso:country":"US",
    "sg:address":"27 Haas Rd",
    "sg:city":"Basking Ridge",
    "sg:classifiers":[
        {
            "category":"Shopping",
            "subcategory":"Photographic Equipment",
            "type":"Retail Goods"
        }
    ],
    "sg:phone":"+1   ",
    "sg:postcode":"07920",
    "sg:province":"NJ",
    "sg:tags":[
        "supply"
    ],
    "wof:name":"Photo Impressions",
    "wof:placetype":"venue"
},
  "geometry": {"coordinates":[-74.532743,40.66975],"type":"Point"}
}