{
  "type": "Feature",
  "properties": {
    "iso:country":"US",
    "sg:address":"307 Beachway Ave",
    "sg:city":"Keansburg",
    "sg:classifiers":[
        {
            "category":"Restaurant",
            "type":"Food & Drink"
        }
    ],
    "sg:phone":"+1 732 495 7500",
    "sg:postcode":"07734",
    "sg:province":"NJ",
    "wof:name":"Jersey Shore Bar & Grill",
    "wof:placetype":"venue"
},
  "geometry": {"coordinates":[-74.139008,40.453677],"type":"Point"}
}