{
  "type": "Feature",
  "properties": {
    "addr:full":"12 N Dean St Englewood NJ 07631",
    "addr:housenumber":"12",
    "addr:postcode":"07631",
    "addr:street":"N Dean St",
    "iso:country":"US",
    "sg:address":"12 N Dean St",
    "sg:city":"Englewood",
    "sg:classifiers":[
        {
            "category":"Shopping",
            "subcategory":"Gifts & Souvenirs",
            "type":"Retail Goods"
        }
    ],
    "sg:phone":"+1 201 568 6517",
    "sg:postcode":"07631",
    "sg:province":"NJ",
    "sg:tags":[
        "shop"
    ],
    "wof:name":"Golden Ladder",
    "wof:placetype":"venue"
},
  "geometry": {"coordinates":[-73.974217,40.894043],"type":"Point"}
}