{
  "type": "Feature",
  "properties": {
    "addr:full":"455 Warren St Edgewater Park NJ 08010",
    "addr:housenumber":"455",
    "addr:postcode":"08010",
    "addr:street":"Warren St;Park",
    "iso:country":"US",
    "sg:address":"455 Warren St",
    "sg:city":"Edgewater Park",
    "sg:classifiers":[
        {
            "category":"Professional",
            "subcategory":"Research",
            "type":"Services"
        }
    ],
    "sg:phone":"+1 609 387 2010",
    "sg:postcode":"08010",
    "sg:province":"NJ",
    "sg:tags":[
        "laboratory"
    ],
    "wof:name":"Fyth Lab Inc",
    "wof:placetype":"venue"
},
  "geometry": {"coordinates":[-74.920948,40.064723],"type":"Point"}
}