{
  "type": "Feature",
  "properties": {
    "addr:full":"174 Norman Dr Ramsey NJ 07446",
    "addr:housenumber":"174",
    "addr:postcode":"07446",
    "addr:street":"Norman Dr",
    "iso:country":"US",
    "sg:address":"174 Norman Dr",
    "sg:city":"Ramsey",
    "sg:classifiers":[
        {
            "category":"Education",
            "subcategory":"School",
            "type":"Public Place"
        }
    ],
    "sg:phone":"+1   ",
    "sg:postcode":"07446",
    "sg:province":"NJ",
    "wof:name":"Jhs Consulting SA",
    "wof:placetype":"venue"
},
  "geometry": {"coordinates":[-74.126498,41.053929],"type":"Point"}
}