{
  "type": "Feature",
  "properties": {
    "addr:full":"65 Biddle Way Mount Laurel NJ 08054",
    "addr:housenumber":"65",
    "addr:postcode":"08054",
    "addr:street":"Biddle Way",
    "iso:country":"US",
    "sg:address":"65 Biddle Way",
    "sg:city":"Mount Laurel",
    "sg:classifiers":[
        {
            "category":"Building & Trades",
            "subcategory":"Cleaning & Sanitation",
            "type":"Services"
        }
    ],
    "sg:phone":"+1   ",
    "sg:postcode":"08054",
    "sg:province":"NJ",
    "sg:tags":[
        "maintenance"
    ],
    "wof:name":"Cnc Janitorial Services LLC",
    "wof:placetype":"venue"
},
  "geometry": {"coordinates":[-74.922918,39.943279],"type":"Point"}
}