{
  "type": "Feature",
  "properties": {
    "iso:country":"US",
    "sg:address":"1945 State Rte 35",
    "sg:city":"South Amboy",
    "sg:classifiers":[
        {
            "category":"Manufacturing",
            "subcategory":"Metals",
            "type":"Manufacturing & Wholesale Goods"
        }
    ],
    "sg:phone":"+1 732 525 8111",
    "sg:postcode":"08879",
    "sg:province":"NJ",
    "wof:name":"Scorpion Choppers Inc",
    "wof:placetype":"venue"
},
  "geometry": {"coordinates":[-74.275854,40.464574],"type":"Point"}
}