{
  "type": "Feature",
  "properties": {
    "addr:full":"476 Branchport Ave Oceanport NJ 07757",
    "addr:housenumber":"476",
    "addr:postcode":"07757",
    "addr:street":"Branchport Ave",
    "iso:country":"US",
    "sg:address":"476 Branchport Ave",
    "sg:city":"Oceanport",
    "sg:classifiers":[
        {
            "category":"Personal",
            "subcategory":"Massage",
            "type":"Services"
        }
    ],
    "sg:phone":"+1 732 741 1900",
    "sg:postcode":"07757",
    "sg:province":"NJ",
    "wof:name":"Red Bank Fitness",
    "wof:placetype":"venue"
},
  "geometry": {"coordinates":[-74.00857999999999,40.315737],"type":"Point"}
}