{
  "type": "Feature",
  "properties": {
    "addr:full":"776 Thornwood Dr Mount Laurel NJ 08054",
    "addr:housenumber":"776",
    "addr:postcode":"08054",
    "addr:street":"Thornwood Dr",
    "iso:country":"US",
    "sg:address":"776 Thornwood Dr",
    "sg:city":"Mount Laurel",
    "sg:classifiers":[
        {
            "category":"Personal",
            "type":"Services"
        }
    ],
    "sg:phone":"+1 856 778 5783",
    "sg:postcode":"08054",
    "sg:province":"NJ",
    "wof:name":"Gene Oppenheim & Associates",
    "wof:placetype":"venue"
},
  "geometry": {"coordinates":[-74.872765,39.973777],"type":"Point"}
}