{
  "type": "Feature",
  "properties": {
    "addr:full":"227 Center Grove Rd Randolph NJ 07869",
    "addr:housenumber":"227",
    "addr:postcode":"07869",
    "addr:street":"Center Grove Rd",
    "iso:country":"US",
    "sg:address":"227 Center Grove Rd",
    "sg:city":"Randolph",
    "sg:classifiers":[
        {
            "category":"Shopping",
            "subcategory":"Bicycles & Sporting Goods",
            "type":"Retail Goods"
        }
    ],
    "sg:phone":"+1 973 989 8957",
    "sg:postcode":"07869",
    "sg:province":"NJ",
    "sg:tags":[
        "equipment",
        "archery",
        "supply"
    ],
    "wof:name":"Wing Archery Inc",
    "wof:placetype":"venue"
},
  "geometry": {"coordinates":[-74.578228,40.851355],"type":"Point"}
}