{
  "type": "Feature",
  "properties": {
    "addr:full":"420 Fairview Ave Fort Lee NJ 07024",
    "addr:housenumber":"420",
    "addr:postcode":"07024",
    "addr:street":"Fairview Ave",
    "iso:country":"US",
    "sg:address":"420 Fairview Ave",
    "sg:city":"Fort Lee",
    "sg:classifiers":[
        {
            "category":"Professional",
            "subcategory":"Computer Services",
            "type":"Services"
        }
    ],
    "sg:phone":"+1   ",
    "sg:postcode":"07024",
    "sg:province":"NJ",
    "sg:tags":[
        "consulting",
        "it"
    ],
    "wof:name":"Carpe Diem Technoogies",
    "wof:placetype":"venue"
},
  "geometry": {"coordinates":[-73.96886499999999,40.864157],"type":"Point"}
}