{
  "type": "Feature",
  "properties": {
    "iso:country":"US",
    "sg:address":"41 Sunset Pl",
    "sg:city":"Bergenfield",
    "sg:classifiers":[
        {
            "category":"Building & Trades",
            "subcategory":"Construction",
            "type":"Services"
        }
    ],
    "sg:phone":"+1 201 387 4776",
    "sg:postcode":"07621",
    "sg:province":"NJ",
    "sg:tags":[
        "maintenance",
        "contractor"
    ],
    "wof:name":"Maintenance-R-Us",
    "wof:placetype":"venue"
},
  "geometry": {"coordinates":[-74.003902,40.925768],"type":"Point"}
}