{
  "type": "Feature",
  "properties": {
    "iso:country":"US",
    "sg:address":"49 Central Ave",
    "sg:city":"Orange",
    "sg:classifiers":[
        {
            "category":"Restaurant",
            "type":"Food & Drink"
        }
    ],
    "sg:phone":"+1 973 675 6726",
    "sg:postcode":"07050",
    "sg:province":"NJ",
    "sg:tags":[
        "eating"
    ],
    "wof:name":"Hop Poh Kitchens",
    "wof:placetype":"venue"
},
  "geometry": {"coordinates":[-74.226997,40.762798],"type":"Point"}
}