{
  "type": "Feature",
  "properties": {
    "iso:country":"US",
    "sg:address":"917 Armstrong Blvd",
    "sg:city":"Ocean",
    "sg:classifiers":[
        {
            "category":"Building & Trades",
            "subcategory":"Cleaning & Sanitation",
            "type":"Services"
        }
    ],
    "sg:phone":"+1 732 544 0541",
    "sg:postcode":"07712",
    "sg:province":"NJ",
    "sg:tags":[
        "janitor"
    ],
    "wof:name":"D H Janitorial",
    "wof:placetype":"venue"
},
  "geometry": {"coordinates":[-74.045663,40.271157],"type":"Point"}
}