{
  "type": "Feature",
  "properties": {
    "iso:country":"US",
    "sg:address":"272 Prospect Ave",
    "sg:city":"Park Ridge",
    "sg:classifiers":[
        {
            "category":"Health Services",
            "subcategory":"Chiropractor",
            "type":"Services"
        }
    ],
    "sg:phone":"+1 201 391 2690",
    "sg:postcode":"07656",
    "sg:province":"NJ",
    "wof:name":"Robt Jacoby DC",
    "wof:placetype":"venue"
},
  "geometry": {"coordinates":[-74.021952,41.021111],"type":"Point"}
}