{
  "type": "Feature",
  "properties": {
    "addr:full":"396 Paterson Ave East Rutherford NJ 07073",
    "addr:housenumber":"396",
    "addr:postcode":"07073",
    "addr:street":"Paterson Ave",
    "iso:country":"US",
    "sg:address":"396 Paterson Ave",
    "sg:city":"East Rutherford",
    "sg:classifiers":[
        {
            "category":"Building & Trades",
            "subcategory":"Locksmith",
            "type":"Services"
        }
    ],
    "sg:phone":"+1 877 759 5805",
    "sg:postcode":"07073",
    "sg:province":"NJ",
    "sg:tags":[
        "key"
    ],
    "wof:name":"24 Hour 7 Day Emergency Locksmith",
    "wof:placetype":"venue"
},
  "geometry": {"coordinates":[-74.10022600000001,40.838795],"type":"Point"}
}