{
  "type": "Feature",
  "properties": {
    "addr:full":"270 Fox Hill Rd Denville NJ 07834",
    "addr:housenumber":"270",
    "addr:postcode":"07834",
    "addr:street":"Fox Hill Rd",
    "iso:country":"US",
    "sg:address":"270 Fox Hill Rd",
    "sg:city":"Denville",
    "sg:classifiers":[
        {
            "category":"Manufacturing",
            "subcategory":"Toys & Sporting Goods",
            "type":"Manufacturing & Wholesale Goods"
        }
    ],
    "sg:phone":"+1 973 586 7884",
    "sg:postcode":"07834",
    "sg:province":"NJ",
    "sg:tags":[
        "mfg"
    ],
    "wof:name":"Zhou & Associates Inc",
    "wof:placetype":"venue"
},
  "geometry": {"coordinates":[-74.471676,40.878782],"type":"Point"}
}