{
  "type": "Feature",
  "properties": {
    "iso:country":"US",
    "sg:address":"91 Fieldcrest Ave",
    "sg:city":"Edison",
    "sg:classifiers":[
        {
            "category":"Organizations",
            "subcategory":"Professional Association",
            "type":"Services"
        }
    ],
    "sg:phone":"+1 732 225 2265",
    "sg:postcode":"08837",
    "sg:province":"NJ",
    "sg:tags":[
        "contractor"
    ],
    "sg:website":"www.bcanj.com",
    "wof:name":"Building Contractors Assn NJ",
    "wof:placetype":"venue"
},
  "geometry": {"coordinates":[-74.340327,40.520334],"type":"Point"}
}