{
  "type": "Feature",
  "properties": {
    "addr:full":"55 N Maple Ave Tuckerton NJ 08224",
    "addr:housenumber":"55",
    "addr:postcode":"08224",
    "addr:street":"N Maple Ave",
    "iso:country":"US",
    "sg:address":"55 N Maple Ave",
    "sg:city":"Tuckerton",
    "sg:classifiers":[
        {
            "category":"Professional",
            "type":"Services"
        }
    ],
    "sg:phone":"+1   ",
    "sg:postcode":"08224",
    "sg:province":"NJ",
    "wof:name":"Creativity By Hartman",
    "wof:placetype":"venue"
},
  "geometry": {"coordinates":[-74.45075799999999,39.605269],"type":"Point"}
}