{
  "type": "Feature",
  "properties": {
    "addr:full":"82 Home Ave Rutherford NJ 07070",
    "addr:housenumber":"82",
    "addr:postcode":"07070",
    "addr:street":"Home Ave",
    "iso:country":"US",
    "sg:address":"82 Home Ave",
    "sg:city":"Rutherford",
    "sg:classifiers":[
        {
            "category":"Professional",
            "type":"Services"
        }
    ],
    "sg:phone":"+1   ",
    "sg:postcode":"07070",
    "sg:province":"NJ",
    "wof:name":"Goodday Service",
    "wof:placetype":"venue"
},
  "geometry": {"coordinates":[-74.10632699999999,40.829028],"type":"Point"}
}