{
  "type": "Feature",
  "properties": {
    "addr:full":"397 Lyons Ave Newark NJ 07112",
    "addr:housenumber":"397",
    "addr:postcode":"07112",
    "addr:street":"Lyons Ave",
    "iso:country":"US",
    "sg:address":"397 Lyons Ave",
    "sg:city":"Newark",
    "sg:classifiers":[
        {
            "category":"Organizations",
            "subcategory":"Religious Organization",
            "type":"Services"
        }
    ],
    "sg:phone":"+1 973 923 2406",
    "sg:postcode":"07112",
    "sg:province":"NJ",
    "sg:tags":[
        "church"
    ],
    "wof:name":"Lydia Baptist Church",
    "wof:placetype":"venue"
},
  "geometry": {"coordinates":[-74.221001,40.713646],"type":"Point"}
}