{
  "type": "Feature",
  "properties": {
    "addr:full":"6047 English Creek Ave Egg Harbor Twp NJ 08234",
    "addr:housenumber":"6047",
    "addr:postcode":"08234",
    "addr:street":"English Creek Ave",
    "iso:country":"US",
    "sg:address":"6047 English Creek Ave",
    "sg:city":"Egg Harbor Twp",
    "sg:classifiers":[
        {
            "category":"Building & Trades",
            "subcategory":"Construction",
            "type":"Services"
        }
    ],
    "sg:phone":"+1 609 601 0801",
    "sg:postcode":"08234",
    "sg:province":"NJ",
    "sg:tags":[
        "residential",
        "general",
        "contractor"
    ],
    "wof:name":"B & T Cummings Construction",
    "wof:placetype":"venue"
},
  "geometry": {"coordinates":[-74.64397599999999,39.383046],"type":"Point"}
}