{
  "type": "Feature",
  "properties": {
    "iso:country":"US",
    "sg:address":"6 Long Way",
    "sg:city":"Hopewell",
    "sg:classifiers":[
        {
            "category":"Professional",
            "subcategory":"Management & Consulting",
            "type":"Services"
        }
    ],
    "sg:phone":"+1   ",
    "sg:postcode":"08525",
    "sg:province":"NJ",
    "wof:name":"Misawa Consulting Corp",
    "wof:placetype":"venue"
},
  "geometry": {"coordinates":[-74.738867,40.402266],"type":"Point"}
}