{
  "type": "Feature",
  "properties": {
    "addr:full":"321 Pennsylvania Ave Linden NJ 07036",
    "addr:housenumber":"321",
    "addr:postcode":"07036",
    "addr:street":"Pennsylvania Ave",
    "iso:country":"US",
    "sg:address":"321 Pennsylvania Ave",
    "sg:city":"Linden",
    "sg:classifiers":[
        {
            "category":"Wholesale",
            "subcategory":"Electrical",
            "type":"Manufacturing & Wholesale Goods"
        }
    ],
    "sg:phone":"+1 908 486 3300",
    "sg:postcode":"07036",
    "sg:province":"NJ",
    "sg:tags":[
        "electronic"
    ],
    "wof:name":"Summit Electronics Corp",
    "wof:placetype":"venue"
},
  "geometry": {"coordinates":[-74.24800399999999,40.633478],"type":"Point"}
}