{
  "type": "Feature",
  "properties": {
    "iso:country":"US",
    "sg:address":"204 Philadelphia Ave",
    "sg:city":"Egg Harbor City",
    "sg:classifiers":[
        {
            "category":"Professional",
            "type":"Services"
        }
    ],
    "sg:phone":"+1 609 965 8077",
    "sg:postcode":"08215",
    "sg:province":"NJ",
    "sg:tags":[
        "establishment"
    ],
    "wof:name":"Hamilton Group",
    "wof:placetype":"venue"
},
  "geometry": {"coordinates":[-74.64448299999999,39.53134],"type":"Point"}
}