{
  "type": "Feature",
  "properties": {
    "iso:country":"US",
    "sg:address":"3081 Edwin Ave",
    "sg:city":"Fort Lee",
    "sg:classifiers":[
        {
            "category":"Real Estate",
            "subcategory":"Real Estate Services",
            "type":"Services"
        }
    ],
    "sg:phone":"+1 201 944 1547",
    "sg:postcode":"07024",
    "sg:province":"NJ",
    "wof:name":"Linwood Park Cooperative",
    "wof:placetype":"venue"
},
  "geometry": {"coordinates":[-73.96986800000001,40.864109],"type":"Point"}
}