{
  "type": "Feature",
  "properties": {
    "iso:country":"US",
    "sg:address":"500 Brunswick Ave",
    "sg:city":"Trenton",
    "sg:classifiers":[
        {
            "category":"Wholesale",
            "subcategory":"Scrap",
            "type":"Manufacturing & Wholesale Goods"
        }
    ],
    "sg:phone":"+1 609 989 3265",
    "sg:postcode":"08638",
    "sg:province":"NJ",
    "sg:tags":[
        "recycling",
        "center"
    ],
    "wof:name":"City Of Trenton Recycling Ctr",
    "wof:placetype":"venue"
},
  "geometry": {"coordinates":[-74.754254,40.233188],"type":"Point"}
}