{
  "type": "Feature",
  "properties": {
    "iso:country":"US",
    "sg:address":"3301 Bay Ave",
    "sg:city":"Ocean City",
    "sg:classifiers":[
        {
            "category":"Building & Trades",
            "subcategory":"Construction",
            "type":"Services"
        }
    ],
    "sg:phone":"+1 609 398 2929",
    "sg:postcode":"08226",
    "sg:province":"NJ",
    "sg:tags":[
        "general",
        "contractor"
    ],
    "wof:name":"Castlemar Construction Co Inc",
    "wof:placetype":"venue"
},
  "geometry": {"coordinates":[-74.613096,39.254553],"type":"Point"}
}