{
  "type": "Feature",
  "properties": {
    "iso:country":"US",
    "sg:address":"869 Hillside Ave",
    "sg:city":"Mountainside",
    "sg:classifiers":[
        {
            "category":"Real Estate",
            "subcategory":"Architect",
            "type":"Services"
        }
    ],
    "sg:phone":"+1 908 654 6929",
    "sg:postcode":"07092",
    "sg:province":"NJ",
    "sg:tags":[
        "architectural"
    ],
    "wof:name":"Hamir L Vadi",
    "wof:placetype":"venue"
},
  "geometry": {"coordinates":[-74.354225,40.666841],"type":"Point"}
}