{
  "type": "Feature",
  "properties": {
    "addr:full":"79 Marion Rd E Princeton NJ 08540",
    "addr:housenumber":"79",
    "addr:postcode":"08540",
    "addr:street":"Marion Rd E",
    "iso:country":"US",
    "sg:address":"79 Marion Rd E",
    "sg:city":"Princeton",
    "sg:classifiers":[
        {
            "category":"Professional",
            "type":"Services"
        }
    ],
    "sg:phone":"+1 609 924 8240",
    "sg:postcode":"08540",
    "sg:province":"NJ",
    "wof:name":"Princeton Chemgroup Inc",
    "wof:placetype":"venue"
},
  "geometry": {"coordinates":[-74.62717000000001,40.369007],"type":"Point"}
}