{
  "type": "Feature",
  "properties": {
    "iso:country":"US",
    "sg:address":"5 Charles Dr",
    "sg:city":"Fairfield",
    "sg:classifiers":[
        {
            "category":"Professional",
            "type":"Services"
        }
    ],
    "sg:phone":"+1 973 227 9028",
    "sg:postcode":"07004",
    "sg:province":"NJ",
    "sg:tags":[
        "establishment"
    ],
    "wof:name":"David Hubay & Son Inc",
    "wof:placetype":"venue"
},
  "geometry": {"coordinates":[-74.284955,40.887225],"type":"Point"}
}