{
  "type": "Feature",
  "properties": {
    "iso:country":"US",
    "sg:address":"346 Park Ave",
    "sg:city":"Scotch Plains",
    "sg:classifiers":[
        {
            "category":"Home & Garden",
            "subcategory":"Building Materials",
            "type":"Retail Goods"
        },
        {
            "category":"Building & Trades",
            "subcategory":"Construction",
            "type":"Services"
        }
    ],
    "sg:phone":"+1 973 635 9122",
    "sg:postcode":"07076",
    "sg:province":"NJ",
    "sg:tags":[
        "windows",
        "door",
        "installation"
    ],
    "wof:name":"Essex Replacement Door Win Co",
    "wof:placetype":"venue"
},
  "geometry": {"coordinates":[-74.400665,40.6525],"type":"Point"}
}