{
  "type": "Feature",
  "properties": {
    "iso:country":"US",
    "sg:address":"100 Lighting Way",
    "sg:city":"Secaucus",
    "sg:classifiers":[
        {
            "category":"Banks & Credit Unions",
            "subcategory":"Bank",
            "type":"Services"
        }
    ],
    "sg:phone":"+1   ",
    "sg:postcode":"07094",
    "sg:province":"NJ",
    "sg:tags":[
        "federal",
        "savings",
        "institution"
    ],
    "wof:name":"Chase Manhattan",
    "wof:placetype":"venue"
},
  "geometry": {"coordinates":[-74.048512,40.789846],"type":"Point"}
}