{
  "type": "Feature",
  "properties": {
    "iso:country":"US",
    "sg:address":"28 Silvers Rd",
    "sg:city":"Freehold",
    "sg:classifiers":[
        {
            "category":"Professional",
            "type":"Services"
        }
    ],
    "sg:phone":"+1 732 409 1000",
    "sg:postcode":"07728",
    "sg:province":"NJ",
    "sg:tags":[
        "establishment"
    ],
    "wof:name":"Pavillion Residential LTD",
    "wof:placetype":"venue"
},
  "geometry": {"coordinates":[-74.285516,40.290102],"type":"Point"}
}