{
  "type": "Feature",
  "properties": {
    "addr:full":"240 S Lincoln Ave Long Branch NJ 07740",
    "addr:housenumber":"240",
    "addr:postcode":"07740",
    "addr:street":"S Lincoln Ave",
    "iso:country":"US",
    "sg:address":"240 S Lincoln Ave",
    "sg:city":"Long Branch",
    "sg:classifiers":[
        {
            "category":"Wholesale",
            "subcategory":"Hardware",
            "type":"Manufacturing & Wholesale Goods"
        }
    ],
    "sg:phone":"+1 732 229 6092",
    "sg:postcode":"07740",
    "sg:province":"NJ",
    "wof:name":"U S Plusair",
    "wof:placetype":"venue"
},
  "geometry": {"coordinates":[-74.000325,40.264],"type":"Point"}
}