{
  "type": "Feature",
  "properties": {
    "iso:country":"US",
    "sg:address":"111 E Pine Ave",
    "sg:city":"Wildwood",
    "sg:classifiers":[
        {
            "category":"Government",
            "subcategory":"Fire Station",
            "type":"Public Place"
        }
    ],
    "sg:phone":"+1 609 522 2654",
    "sg:postcode":"08260",
    "sg:province":"NJ",
    "sg:tags":[
        "department"
    ],
    "wof:name":"Wildwood Volunteer Fire Co",
    "wof:placetype":"venue"
},
  "geometry": {"coordinates":[-74.812213,38.991073],"type":"Point"}
}