{
  "type": "Feature",
  "properties": {
    "addr:full":"255 Ogden Ave Jersey City NJ 07307",
    "addr:housenumber":"255",
    "addr:postcode":"07307",
    "addr:street":"Ogden Ave",
    "iso:country":"US",
    "sg:address":"255 Ogden Ave",
    "sg:city":"Jersey City",
    "sg:classifiers":[
        {
            "category":"Shopping",
            "subcategory":"Clothing, Apparel, & Fashions",
            "type":"Retail Goods"
        }
    ],
    "sg:phone":"+1 201 610 0920",
    "sg:postcode":"07307",
    "sg:province":"NJ",
    "wof:name":"Alfred's Party Time",
    "wof:placetype":"venue"
},
  "geometry": {"coordinates":[-74.044518,40.741838],"type":"Point"}
}