{
  "type": "Feature",
  "properties": {
    "addr:full":"1032 State Rte 34 Matawan NJ 07747",
    "addr:housenumber":"1032",
    "addr:postcode":"07747",
    "addr:street":"State Rte 34",
    "iso:country":"US",
    "sg:address":"1032 State Rte 34",
    "sg:city":"Matawan",
    "sg:classifiers":[
        {
            "category":"Shopping",
            "subcategory":"Clothing, Apparel, & Fashions",
            "type":"Retail Goods"
        }
    ],
    "sg:phone":"+1 732 566 4305",
    "sg:postcode":"07747",
    "sg:province":"NJ",
    "sg:tags":[
        "shop",
        "bridal"
    ],
    "wof:name":"Frills Limited",
    "wof:placetype":"venue"
},
  "geometry": {"coordinates":[-74.231009,40.403214],"type":"Point"}
}