{
  "type": "Feature",
  "properties": {
    "iso:country":"US",
    "sg:address":"120 N Center St",
    "sg:city":"Orange",
    "sg:classifiers":[
        {
            "category":"Building & Trades",
            "subcategory":"Construction",
            "type":"Services"
        }
    ],
    "sg:phone":"+1 973 676 4344",
    "sg:postcode":"07050",
    "sg:province":"NJ",
    "sg:tags":[
        "hanging",
        "contractor"
    ],
    "wof:name":"Washington Painting Co",
    "wof:placetype":"venue"
},
  "geometry": {"coordinates":[-74.226299,40.774527],"type":"Point"}
}