{
  "type": "Feature",
  "properties": {
    "addr:full":"499 Cape May St Englewood NJ 07631",
    "addr:housenumber":"499",
    "addr:postcode":"07631",
    "addr:street":"Cape May St",
    "iso:country":"US",
    "sg:address":"499 Cape May St",
    "sg:city":"Englewood",
    "sg:classifiers":[
        {
            "category":"Health Services",
            "subcategory":"Doctor",
            "type":"Services"
        }
    ],
    "sg:phone":"+1 201 568 1210",
    "sg:postcode":"07631",
    "sg:province":"NJ",
    "sg:tags":[
        "medical"
    ],
    "wof:name":"M A Schleider Dr",
    "wof:placetype":"venue"
},
  "geometry": {"coordinates":[-73.967051,40.87545],"type":"Point"}
}