{
  "type": "Feature",
  "properties": {
    "iso:country":"US",
    "sg:address":"921 Main St",
    "sg:city":"Belmar",
    "sg:classifiers":[
        {
            "category":"Professional",
            "subcategory":"Lawyer & Legal Services",
            "type":"Services"
        }
    ],
    "sg:phone":"+1 732 681 7922",
    "sg:postcode":"07719",
    "sg:province":"NJ",
    "sg:tags":[
        "attorney"
    ],
    "wof:name":"Michael T Mills",
    "wof:placetype":"venue"
},
  "geometry": {"coordinates":[-74.02540500000001,40.180109],"type":"Point"}
}