{
  "type": "Feature",
  "properties": {
    "iso:country":"US",
    "sg:address":"94 Market St",
    "sg:city":"Salem",
    "sg:classifiers":[
        {
            "category":"Education",
            "subcategory":"School",
            "type":"Public Place"
        }
    ],
    "sg:phone":"+1 856 935 7510",
    "sg:postcode":"08079",
    "sg:province":"NJ",
    "wof:name":"Salem County School Supt",
    "wof:placetype":"venue"
},
  "geometry": {"coordinates":[-75.466256,39.573774],"type":"Point"}
}