{
  "type": "Feature",
  "properties": {
    "iso:country":"US",
    "sg:address":"60 US Hwy 46",
    "sg:city":"Fairfield",
    "sg:classifiers":[
        {
            "category":"Professional",
            "subcategory":"Management & Consulting",
            "type":"Services"
        }
    ],
    "sg:phone":"+1   ",
    "sg:postcode":"07004",
    "sg:province":"NJ",
    "wof:name":"Financial Management Group LP",
    "wof:placetype":"venue"
},
  "geometry": {"coordinates":[-74.311628,40.868082],"type":"Point"}
}