{
  "type": "Feature",
  "properties": {
    "addr:full":"333 Elizabeth Ave Newark NJ 07112",
    "addr:housenumber":"333",
    "addr:postcode":"07112",
    "addr:street":"Elizabeth Ave",
    "iso:country":"US",
    "sg:address":"333 Elizabeth Ave",
    "sg:city":"Newark",
    "sg:classifiers":[
        {
            "category":"Retail",
            "subcategory":"Auto Repair",
            "type":"Services"
        }
    ],
    "sg:phone":"+1 973 242 6200",
    "sg:postcode":"07112",
    "sg:province":"NJ",
    "sg:tags":[
        "gas"
    ],
    "wof:name":"Ventura Motors",
    "wof:placetype":"venue"
},
  "geometry": {"coordinates":[-74.194901,40.7117],"type":"Point"}
}