{
  "type": "Feature",
  "properties": {
    "iso:country":"US",
    "sg:address":"1600 State Rte 208",
    "sg:city":"Hawthorne",
    "sg:classifiers":[
        {
            "category":"Professional",
            "subcategory":"Art Services",
            "type":"Services"
        }
    ],
    "sg:phone":"+1   ",
    "sg:postcode":"07506",
    "sg:province":"NJ",
    "sg:tags":[
        "commercial",
        "design"
    ],
    "wof:name":"To B B Graphics",
    "wof:placetype":"venue"
},
  "geometry": {"coordinates":[-74.159902,40.975963],"type":"Point"}
}