{
  "type": "Feature",
  "properties": {
    "iso:country":"US",
    "sg:address":"13 Stiles Rd",
    "sg:city":"Summit",
    "sg:classifiers":[
        {
            "category":"Local Transit",
            "type":"Transportation"
        }
    ],
    "sg:phone":"+1 908 522 1199",
    "sg:postcode":"07901",
    "sg:province":"NJ",
    "sg:tags":[
        "limousine",
        "limo"
    ],
    "wof:name":"Aabbey Limousine Service",
    "wof:placetype":"venue"
},
  "geometry": {"coordinates":[-74.35633900000001,40.706666],"type":"Point"}
}