{
  "type": "Feature",
  "properties": {
    "addr:full":"450 Bergen St Harrison NJ 07029",
    "addr:housenumber":"450",
    "addr:postcode":"07029",
    "addr:street":"Bergen St",
    "iso:country":"US",
    "sg:address":"450 Bergen St",
    "sg:city":"Harrison",
    "sg:classifiers":[
        {
            "category":"Health Services",
            "subcategory":"Doctor",
            "type":"Services"
        }
    ],
    "sg:phone":"+1 973 497 2608",
    "sg:postcode":"07029",
    "sg:province":"NJ",
    "sg:tags":[
        "clinic"
    ],
    "wof:name":"Veincare & Circulation Ctr",
    "wof:placetype":"venue"
},
  "geometry": {"coordinates":[-74.154658,40.74332],"type":"Point"}
}