{
  "type": "Feature",
  "properties": {
    "iso:country":"US",
    "sg:address":"521 Main St",
    "sg:city":"Little Falls",
    "sg:classifiers":[
        {
            "category":"Personal",
            "subcategory":"Beauty Salon",
            "type":"Services"
        }
    ],
    "sg:phone":"+1   ",
    "sg:postcode":"07424",
    "sg:province":"NJ",
    "sg:tags":[
        "shop"
    ],
    "wof:name":"Final Move",
    "wof:placetype":"venue"
},
  "geometry": {"coordinates":[-74.245867,40.885181],"type":"Point"}
}