{
  "type": "Feature",
  "properties": {
    "addr:full":"265 Pennsylvania Ave Hillside NJ 07205",
    "addr:housenumber":"265",
    "addr:postcode":"07205",
    "addr:street":"Pennsylvania Ave",
    "iso:country":"US",
    "sg:address":"265 Pennsylvania Ave",
    "sg:city":"Hillside",
    "sg:classifiers":[
        {
            "category":"Professional",
            "type":"Services"
        }
    ],
    "sg:phone":"+1 908 436 1100",
    "sg:postcode":"07205",
    "sg:province":"NJ",
    "sg:tags":[
        "establishment"
    ],
    "wof:name":"Everflow Supplies Inc",
    "wof:placetype":"venue"
},
  "geometry": {"coordinates":[-74.22383000000001,40.693236],"type":"Point"}
}