{
  "type": "Feature",
  "properties": {
    "addr:full":"444 Hunter Rd Ridgewood NJ 07450",
    "addr:housenumber":"444",
    "addr:postcode":"07450",
    "addr:street":"Hunter Rd",
    "iso:country":"US",
    "sg:address":"444 Hunter Rd",
    "sg:city":"Ridgewood",
    "sg:classifiers":[
        {
            "category":"Building & Trades",
            "subcategory":"Construction",
            "type":"Services"
        }
    ],
    "sg:phone":"+1 201 652 1842",
    "sg:postcode":"07450",
    "sg:province":"NJ",
    "sg:tags":[
        "residential",
        "general",
        "contractor"
    ],
    "wof:name":"RC Jennee Construction Company",
    "wof:placetype":"venue"
},
  "geometry": {"coordinates":[-74.100033,40.960451],"type":"Point"}
}