{
  "type": "Feature",
  "properties": {
    "addr:full":"1120 Bloomfield Ave West Caldwell NJ 07006",
    "addr:housenumber":"1120",
    "addr:postcode":"07006",
    "addr:street":"Bloomfield Ave",
    "iso:country":"US",
    "sg:address":"1120 Bloomfield Ave",
    "sg:city":"West Caldwell",
    "sg:classifiers":[
        {
            "category":"Professional",
            "subcategory":"Accounting & Tax Preparation",
            "type":"Services"
        }
    ],
    "sg:phone":"+1 973 575 0559",
    "sg:postcode":"07006",
    "sg:province":"NJ",
    "sg:tags":[
        "accountant"
    ],
    "wof:name":"O'connor Deisler & Co",
    "wof:placetype":"venue"
},
  "geometry": {"coordinates":[-74.308701,40.854698],"type":"Point"}
}