{
  "type": "Feature",
  "properties": {
    "addr:full":"63 Rolling Brook Dr Edison NJ 08820",
    "addr:housenumber":"63",
    "addr:postcode":"08820",
    "addr:street":"Rolling Brook Dr",
    "iso:country":"US",
    "sg:address":"63 Rolling Brook Dr",
    "sg:city":"Edison",
    "sg:classifiers":[
        {
            "category":"Professional",
            "subcategory":"Management & Consulting",
            "type":"Services"
        }
    ],
    "sg:phone":"+1   ",
    "sg:postcode":"08820",
    "sg:province":"NJ",
    "sg:tags":[
        "business"
    ],
    "wof:name":"Heavyweight Consulting Inc",
    "wof:placetype":"venue"
},
  "geometry": {"coordinates":[-74.36879999999999,40.592031],"type":"Point"}
}