{
  "type": "Feature",
  "properties": {
    "iso:country":"US",
    "sg:address":"217 Morgan Ave",
    "sg:city":"Pennsauken",
    "sg:classifiers":[
        {
            "category":"Retail",
            "subcategory":"Animal Services",
            "type":"Services"
        }
    ],
    "sg:phone":"+1 856 486 2180",
    "sg:postcode":"08110",
    "sg:province":"NJ",
    "sg:tags":[
        "shelter"
    ],
    "wof:name":"West Jersey Animal Shelter",
    "wof:placetype":"venue"
},
  "geometry": {"coordinates":[-75.06121,39.979198],"type":"Point"}
}