{
  "type": "Feature",
  "properties": {
    "iso:country":"US",
    "sg:address":"1000 State Rte 35",
    "sg:city":"Ocean",
    "sg:classifiers":[
        {
            "category":"Shopping",
            "type":"Retail Goods"
        }
    ],
    "sg:phone":"+1 732 493 4551",
    "sg:postcode":"07712",
    "sg:province":"NJ",
    "sg:tags":[
        "cosmetic",
        "perfume"
    ],
    "wof:name":"Harmon Cosmetics",
    "wof:placetype":"venue"
},
  "geometry": {"coordinates":[-74.03797299999999,40.23569],"type":"Point"}
}