{
  "type": "Feature",
  "properties": {
    "addr:full":"2648 State Rte 27 North Brunswick NJ 08902",
    "addr:housenumber":"2648",
    "addr:postcode":"08902",
    "addr:street":"State Rte 27",
    "iso:country":"US",
    "sg:address":"2648 State Rte 27",
    "sg:city":"North Brunswick",
    "sg:classifiers":[
        {
            "category":"Health Services",
            "subcategory":"Doctor",
            "type":"Services"
        }
    ],
    "sg:phone":"+1 732 951 8585",
    "sg:postcode":"08902",
    "sg:province":"NJ",
    "sg:tags":[
        "physician",
        "surgeon"
    ],
    "wof:name":"Mehnaz A Haq MD",
    "wof:placetype":"venue"
},
  "geometry": {"coordinates":[-74.52624,40.445192],"type":"Point"}
}