{
  "type": "Feature",
  "properties": {
    "iso:country":"US",
    "sg:address":"420 Benigno Blvd",
    "sg:city":"Bellmawr",
    "sg:classifiers":[
        {
            "category":"Wholesale",
            "subcategory":"Machinery & Supplies",
            "type":"Manufacturing & Wholesale Goods"
        }
    ],
    "sg:phone":"+1 856 931 4334",
    "sg:postcode":"08031",
    "sg:province":"NJ",
    "sg:tags":[
        "cleaner",
        "industrial",
        "chemical",
        "paper",
        "janitor",
        "janitorial"
    ],
    "sg:website":"http://www.envirotrolinc.com",
    "wof:name":"Envirotrol Inc",
    "wof:placetype":"venue"
},
  "geometry": {"coordinates":[-75.09495699999999,39.858818],"type":"Point"}
}