{
  "type": "Feature",
  "properties": {
    "iso:country":"US",
    "sg:address":"10 Emley Rd",
    "sg:city":"Pittstown",
    "sg:classifiers":[
        {
            "category":"Banks & Credit Unions",
            "subcategory":"Financial Services",
            "type":"Services"
        }
    ],
    "sg:phone":"+1   ",
    "sg:postcode":"08867",
    "sg:province":"NJ",
    "sg:tags":[
        "company",
        "holding"
    ],
    "wof:name":"Raymond James Financial Svcs",
    "wof:placetype":"venue"
},
  "geometry": {"coordinates":[-74.97053,40.577043],"type":"Point"}
}