{
  "type": "Feature",
  "properties": {
    "addr:full":"5 Dorset Rd Hackettstown NJ 07853",
    "addr:housenumber":"5",
    "addr:postcode":"07853",
    "addr:street":"Dorset Rd",
    "iso:country":"US",
    "sg:address":"5 Dorset Rd",
    "sg:city":"Hackettstown",
    "sg:classifiers":[
        {
            "category":"Parking",
            "type":"Transportation"
        }
    ],
    "sg:phone":"+1 908 979 0096",
    "sg:postcode":"07853",
    "sg:province":"NJ",
    "sg:tags":[
        "automobile"
    ],
    "wof:name":"Larry Merritt",
    "wof:placetype":"venue"
},
  "geometry": {"coordinates":[-74.774563,40.820706],"type":"Point"}
}