{
  "type": "Feature",
  "properties": {
    "addr:full":"132 Main St Fort Lee NJ 07024",
    "addr:housenumber":"132",
    "addr:postcode":"07024",
    "addr:street":"Main St",
    "iso:country":"US",
    "sg:address":"132 Main St",
    "sg:city":"Fort Lee",
    "sg:classifiers":[
        {
            "category":"Wholesale",
            "subcategory":"Metals & Minerals",
            "type":"Manufacturing & Wholesale Goods"
        }
    ],
    "sg:phone":"+1 201 944 5050",
    "sg:postcode":"07024",
    "sg:province":"NJ",
    "sg:tags":[
        "aluminum"
    ],
    "wof:name":"Astro Aluminum Co",
    "wof:placetype":"venue"
},
  "geometry": {"coordinates":[-73.96678199999999,40.850663],"type":"Point"}
}