{
  "type": "Feature",
  "properties": {
    "addr:full":"207 Merrywood Dr Edison NJ 08817",
    "addr:housenumber":"207",
    "addr:postcode":"08817",
    "addr:street":"Merrywood Dr",
    "iso:country":"US",
    "sg:address":"207 Merrywood Dr",
    "sg:city":"Edison",
    "sg:classifiers":[
        {
            "category":"Health Services",
            "subcategory":"Clinic",
            "type":"Services"
        }
    ],
    "sg:phone":"+1   ",
    "sg:postcode":"08817",
    "sg:province":"NJ",
    "sg:tags":[
        "specialty",
        "outpatient"
    ],
    "wof:name":"Zalrand Inc",
    "wof:placetype":"venue"
},
  "geometry": {"coordinates":[-74.410963,40.527933],"type":"Point"}
}