{
  "type": "Feature",
  "properties": {
    "addr:full":"23 Militia Rd Whitehouse NJ 08889",
    "addr:housenumber":"23",
    "addr:postcode":"08889",
    "addr:street":"Militia Rd",
    "iso:country":"US",
    "sg:address":"23 Militia Rd",
    "sg:city":"Whitehouse",
    "sg:classifiers":[
        {
            "category":"Wholesale",
            "subcategory":"Electrical",
            "type":"Manufacturing & Wholesale Goods"
        }
    ],
    "sg:phone":"+1 908 534 0518",
    "sg:postcode":"08889",
    "sg:province":"NJ",
    "sg:tags":[
        "control"
    ],
    "wof:name":"Aquatech Controls Inc",
    "wof:placetype":"venue"
},
  "geometry": {"coordinates":[-74.78062300000001,40.592139],"type":"Point"}
}