{
  "type": "Feature",
  "properties": {
    "iso:country":"US",
    "sg:address":"5 Morris Ave",
    "sg:city":"Summit",
    "sg:classifiers":[
        {
            "category":"Local Transit",
            "type":"Transportation"
        }
    ],
    "sg:phone":"+1 908 522 0404",
    "sg:postcode":"07901",
    "sg:province":"NJ",
    "sg:tags":[
        "rental",
        "hearse",
        "limousine",
        "limo"
    ],
    "wof:name":"De Franco Limousine",
    "wof:placetype":"venue"
},
  "geometry": {"coordinates":[-74.339798,40.715801],"type":"Point"}
}