{
  "type": "Feature",
  "properties": {
    "addr:full":"198 Midland Ave Kearny NJ 07032",
    "addr:housenumber":"198",
    "addr:postcode":"07032",
    "addr:street":"Midland Ave",
    "iso:country":"US",
    "sg:address":"198 Midland Ave",
    "sg:city":"Kearny",
    "sg:classifiers":[
        {
            "category":"Social Services",
            "subcategory":"Child Care",
            "type":"Services"
        }
    ],
    "sg:phone":"+1 201 246 8444",
    "sg:postcode":"07032",
    "sg:province":"NJ",
    "sg:tags":[
        "day"
    ],
    "wof:name":"Tiny Hearts Child Care Andlearning Center",
    "wof:placetype":"venue"
},
  "geometry": {"coordinates":[-74.13995300000001,40.767968],"type":"Point"}
}