{
  "type": "Feature",
  "properties": {
    "iso:country":"US",
    "sg:address":"104 Burr St",
    "sg:city":"Barnegat",
    "sg:classifiers":[
        {
            "category":"Education",
            "subcategory":"School",
            "type":"Public Place"
        }
    ],
    "sg:phone":"+1 609 660 7500",
    "sg:postcode":"08005",
    "sg:province":"NJ",
    "wof:name":"Robert L Horbelt Elem School",
    "wof:placetype":"venue"
},
  "geometry": {"coordinates":[-74.231585,39.756998],"type":"Point"}
}