{
  "type": "Feature",
  "properties": {
    "iso:country":"US",
    "sg:address":"2 Malsbury Ln",
    "sg:city":"Clarksburg",
    "sg:classifiers":[
        {
            "category":"Building & Trades",
            "subcategory":"Construction",
            "type":"Services"
        }
    ],
    "sg:phone":"+1 609 208 2591",
    "sg:postcode":"08533",
    "sg:province":"NJ",
    "sg:tags":[
        "contractor"
    ],
    "wof:name":"Scenic Builders Inc",
    "wof:placetype":"venue"
},
  "geometry": {"coordinates":[-74.47555199999999,40.124609],"type":"Point"}
}