{
  "type": "Feature",
  "properties": {
    "iso:country":"US",
    "sg:address":"119 Holland Ave",
    "sg:city":"New Milford",
    "sg:classifiers":[
        {
            "category":"Shopping",
            "type":"Retail Goods"
        }
    ],
    "sg:phone":"+1 201 265 6634",
    "sg:postcode":"07646",
    "sg:province":"NJ",
    "sg:tags":[
        "instrument",
        "s",
        "merchandise",
        "mfg"
    ],
    "wof:name":"Aroma Therapy Products",
    "wof:placetype":"venue"
},
  "geometry": {"coordinates":[-74.023951,40.935472],"type":"Point"}
}