{
  "type": "Feature",
  "properties": {
    "iso:country":"US",
    "sg:address":"58 S Broad St",
    "sg:city":"Woodbury",
    "sg:classifiers":[
        {
            "category":"Manufacturing",
            "subcategory":"Printing",
            "type":"Manufacturing & Wholesale Goods"
        }
    ],
    "sg:phone":"+1 856 845 0225",
    "sg:postcode":"08096",
    "sg:province":"NJ",
    "sg:tags":[
        "services-commercial",
        "commercial"
    ],
    "wof:name":"Constitution Co",
    "wof:placetype":"venue"
},
  "geometry": {"coordinates":[-75.153938,39.837202],"type":"Point"}
}