{
  "type": "Feature",
  "properties": {
    "iso:country":"US",
    "sg:address":"40 New St",
    "sg:city":"Hampton",
    "sg:classifiers":[
        {
            "category":"Building & Trades",
            "subcategory":"Construction",
            "type":"Services"
        }
    ],
    "sg:phone":"+1 908 537 4985",
    "sg:postcode":"08827",
    "sg:province":"NJ",
    "sg:tags":[
        "altering",
        "remodeling",
        "contractor"
    ],
    "wof:name":"Murzyn Home Improvements",
    "wof:placetype":"venue"
},
  "geometry": {"coordinates":[-74.954712,40.70652],"type":"Point"}
}