{
  "type": "Feature",
  "properties": {
    "addr:full":"27 Carolina Ave Trenton NJ 08618",
    "addr:housenumber":"27",
    "addr:postcode":"08618",
    "addr:street":"Carolina Ave",
    "iso:country":"US",
    "sg:address":"27 Carolina Ave",
    "sg:city":"Trenton",
    "sg:classifiers":[
        {
            "category":"Professional",
            "subcategory":"Management & Consulting",
            "type":"Services"
        }
    ],
    "sg:phone":"+1   ",
    "sg:postcode":"08618",
    "sg:province":"NJ",
    "sg:tags":[
        "business"
    ],
    "wof:name":"Michael C Fina Company",
    "wof:placetype":"venue"
},
  "geometry": {"coordinates":[-74.78201900000001,40.259582],"type":"Point"}
}