{
  "type": "Feature",
  "properties": {
    "iso:country":"US",
    "sg:address":"29 County Rd",
    "sg:city":"Tenafly",
    "sg:classifiers":[
        {
            "category":"Retail",
            "subcategory":"Auto Repair",
            "type":"Services"
        }
    ],
    "sg:phone":"+1 201 568 0734",
    "sg:postcode":"07670",
    "sg:province":"NJ",
    "sg:tags":[
        "repairing",
        "automobile"
    ],
    "wof:name":"Y's Auto Plus Inc",
    "wof:placetype":"venue"
},
  "geometry": {"coordinates":[-73.963489,40.924785],"type":"Point"}
}