{
  "type": "Feature",
  "properties": {
    "addr:full":"78 Henry St Secaucus NJ 07094",
    "addr:housenumber":"78",
    "addr:postcode":"07094",
    "addr:street":"Henry St",
    "iso:country":"US",
    "sg:address":"78 Henry St",
    "sg:city":"Secaucus",
    "sg:classifiers":[
        {
            "category":"Shopping",
            "subcategory":"Beauty & Cosmetics",
            "type":"Retail Goods"
        }
    ],
    "sg:phone":"+1 201 330 0700",
    "sg:postcode":"07094",
    "sg:province":"NJ",
    "sg:tags":[
        "supply"
    ],
    "wof:name":"Goldwell of New Jersey Inc",
    "wof:placetype":"venue"
},
  "geometry": {"coordinates":[-74.060303,40.770699],"type":"Point"}
}