{
  "type": "Feature",
  "properties": {
    "iso:country":"US",
    "sg:address":"161 Thomas Dr",
    "sg:city":"Paramus",
    "sg:classifiers":[
        {
            "category":"Building & Trades",
            "subcategory":"Construction",
            "type":"Services"
        }
    ],
    "sg:phone":"+1 201 262 1086",
    "sg:postcode":"07652",
    "sg:province":"NJ",
    "sg:tags":[
        "house"
    ],
    "wof:name":"J W S Construction",
    "wof:placetype":"venue"
},
  "geometry": {"coordinates":[-74.05705399999999,40.936814],"type":"Point"}
}