{
  "type": "Feature",
  "properties": {
    "addr:full":"36 Orange Ave Irvington NJ 07111",
    "addr:housenumber":"36",
    "addr:postcode":"07111",
    "addr:street":"Orange Ave",
    "iso:country":"US",
    "sg:address":"36 Orange Ave",
    "sg:city":"Irvington",
    "sg:classifiers":[
        {
            "category":"Professional",
            "subcategory":"Business Services",
            "type":"Services"
        }
    ],
    "sg:phone":"+1 973 373 7186",
    "sg:postcode":"07111",
    "sg:province":"NJ",
    "sg:tags":[
        "sign"
    ],
    "wof:name":"Ellis Sign Co",
    "wof:placetype":"venue"
},
  "geometry": {"coordinates":[-74.231375,40.726857],"type":"Point"}
}