{
  "type": "Feature",
  "properties": {
    "iso:country":"US",
    "sg:address":"17 McIntire Dr",
    "sg:city":"Hillsborough",
    "sg:classifiers":[
        {
            "category":"Professional",
            "type":"Services"
        }
    ],
    "sg:phone":"+1 908 359 7791",
    "sg:postcode":"08844",
    "sg:province":"NJ",
    "wof:name":"Tech Reg Svc Inc",
    "wof:placetype":"venue"
},
  "geometry": {"coordinates":[-74.595793,40.475657],"type":"Point"}
}