{
  "type": "Feature",
  "properties": {
    "addr:full":"155 Poor St Hackensack NJ 07601",
    "addr:housenumber":"155",
    "addr:postcode":"07601",
    "addr:street":"Poor St",
    "iso:country":"US",
    "sg:address":"155 Poor St",
    "sg:city":"Hackensack",
    "sg:classifiers":[
        {
            "category":"Social Services",
            "type":"Services"
        }
    ],
    "sg:phone":"+1 201 342 1084",
    "sg:postcode":"07601",
    "sg:province":"NJ",
    "sg:tags":[
        "organization",
        "welfare"
    ],
    "wof:name":"Community Action-Independent",
    "wof:placetype":"venue"
},
  "geometry": {"coordinates":[-74.061982,40.878155],"type":"Point"}
}