{
  "type": "Feature",
  "properties": {
    "iso:country":"US",
    "sg:address":"392 Washington Ave",
    "sg:city":"Belleville",
    "sg:classifiers":[
        {
            "category":"Health Services",
            "subcategory":"Doctor",
            "type":"Services"
        }
    ],
    "sg:phone":"+1 973 759 4115",
    "sg:postcode":"07109",
    "sg:province":"NJ",
    "sg:tags":[
        "surgeon",
        "oral"
    ],
    "wof:name":"Liloia Peter DDS",
    "wof:placetype":"venue"
},
  "geometry": {"coordinates":[-74.14980300000001,40.794201],"type":"Point"}
}