{
  "type": "Feature",
  "properties": {
    "addr:full":"645 Denver Blvd Edison NJ 08820",
    "addr:housenumber":"645",
    "addr:postcode":"08820",
    "addr:street":"Denver Blvd",
    "iso:country":"US",
    "sg:address":"645 Denver Blvd",
    "sg:city":"Edison",
    "sg:classifiers":[
        {
            "category":"Professional",
            "subcategory":"Engineering",
            "type":"Services"
        }
    ],
    "sg:phone":"+1 732 381 6208",
    "sg:postcode":"08820",
    "sg:province":"NJ",
    "wof:name":"Ceridian Business Solutio",
    "wof:placetype":"venue"
},
  "geometry": {"coordinates":[-74.340199,40.587496],"type":"Point"}
}