{
  "type": "Feature",
  "properties": {
    "iso:country":"US",
    "sg:address":"533 Central Ave",
    "sg:city":"Newark",
    "sg:classifiers":[
        {
            "category":"Food & Beverages",
            "subcategory":"Groceries & Convenience Stores",
            "type":"Retail Goods"
        }
    ],
    "sg:phone":"+1 973 485 4310",
    "sg:postcode":"07107",
    "sg:province":"NJ",
    "sg:tags":[
        "grocer"
    ],
    "wof:name":"Bisono Supermarket",
    "wof:placetype":"venue"
},
  "geometry": {"coordinates":[-74.196297,40.748798],"type":"Point"}
}