{
  "type": "Feature",
  "properties": {
    "addr:full":"40 Middlebury Ln Willingboro NJ 08046",
    "addr:housenumber":"40",
    "addr:postcode":"08046",
    "addr:street":"Middlebury Ln",
    "iso:country":"US",
    "sg:address":"40 Middlebury Ln",
    "sg:city":"Willingboro",
    "sg:classifiers":[
        {
            "category":"Education",
            "subcategory":"School",
            "type":"Public Place"
        }
    ],
    "sg:phone":"+1 609 835 8930",
    "sg:postcode":"08046",
    "sg:province":"NJ",
    "sg:tags":[
        "high",
        "middle",
        "elementary"
    ],
    "wof:name":"Willingboro Township School District",
    "wof:placetype":"venue"
},
  "geometry": {"coordinates":[-74.88641,40.026506],"type":"Point"}
}