{
  "type": "Feature",
  "properties": {
    "addr:full":"201 Kresson Gibbsboro Rd Voorhees NJ 08043",
    "addr:housenumber":"201",
    "addr:postcode":"08043",
    "addr:street":"Kresson Gibbsboro Rd",
    "iso:country":"US",
    "sg:address":"201 Kresson Gibbsboro Rd",
    "sg:city":"Voorhees",
    "sg:classifiers":[
        {
            "category":"Retail",
            "subcategory":"Laundry & Dry Cleaning",
            "type":"Services"
        }
    ],
    "sg:phone":"+1 856 784 1919",
    "sg:postcode":"08043",
    "sg:province":"NJ",
    "sg:tags":[
        "cleaners"
    ],
    "wof:name":"Angel Cleaners",
    "wof:placetype":"venue"
},
  "geometry": {"coordinates":[-74.940017,39.845576],"type":"Point"}
}