{
  "type": "Feature",
  "properties": {
    "addr:full":"1600 Riverview Ter Belmar NJ 07719",
    "addr:housenumber":"1600",
    "addr:postcode":"07719",
    "addr:street":"Riverview Ter",
    "iso:country":"US",
    "sg:address":"1600 Riverview Ter",
    "sg:city":"Belmar",
    "sg:classifiers":[
        {
            "category":"Health Services",
            "subcategory":"Doctor",
            "type":"Services"
        }
    ],
    "sg:phone":"+1 732 681 1989",
    "sg:postcode":"07719",
    "sg:province":"NJ",
    "sg:tags":[
        "medical"
    ],
    "wof:name":"Dr Lawrence Collins",
    "wof:placetype":"venue"
},
  "geometry": {"coordinates":[-74.04058999999999,40.175951],"type":"Point"}
}