{
  "type": "Feature",
  "properties": {
    "iso:country":"US",
    "sg:address":"208 Sanhican Dr",
    "sg:city":"Trenton",
    "sg:classifiers":[
        {
            "category":"Shopping",
            "type":"Retail Goods"
        }
    ],
    "sg:phone":"+1 609 393 9399",
    "sg:postcode":"08618",
    "sg:province":"NJ",
    "sg:tags":[
        "equipment",
        "beer",
        "supply"
    ],
    "wof:name":"Princeton Homebrew",
    "wof:placetype":"venue"
},
  "geometry": {"coordinates":[-74.80627200000001,40.238323],"type":"Point"}
}