{
  "type": "Feature",
  "properties": {
    "addr:full":"150 Fox Dr Allendale NJ 07401",
    "addr:housenumber":"150",
    "addr:postcode":"07401",
    "addr:street":"Fox Dr",
    "iso:country":"US",
    "sg:address":"150 Fox Dr",
    "sg:city":"Allendale",
    "sg:classifiers":[
        {
            "category":"Shopping",
            "subcategory":"Beauty & Cosmetics",
            "type":"Retail Goods"
        },
        {
            "category":"Personal",
            "subcategory":"Barber",
            "type":"Services"
        }
    ],
    "sg:phone":"+1 201 736 1900",
    "sg:postcode":"07401",
    "sg:province":"NJ",
    "sg:tags":[
        "equipment",
        "salons-equipment",
        "supply"
    ],
    "wof:name":"Designer Workshop",
    "wof:placetype":"venue"
},
  "geometry": {"coordinates":[-74.145273,41.030717],"type":"Point"}
}