{
  "type": "Feature",
  "properties": {
    "iso:country":"US",
    "sg:address":"180 Kearny Ave",
    "sg:city":"Kearny",
    "sg:classifiers":[
        {
            "category":"Food & Beverages",
            "subcategory":"Liquor & Beverages",
            "type":"Retail Goods"
        },
        {
            "category":"Food & Beverages",
            "subcategory":"Groceries & Convenience Stores",
            "type":"Retail Goods"
        }
    ],
    "sg:phone":"+1 201 991 5616",
    "sg:postcode":"07032",
    "sg:province":"NJ",
    "sg:tags":[
        "beer",
        "spirit",
        "wine"
    ],
    "wof:name":"Family Convenience & Liquors",
    "wof:placetype":"venue"
},
  "geometry": {"coordinates":[-74.15300000000001,40.7579],"type":"Point"}
}