{
  "type": "Feature",
  "properties": {
    "iso:country":"US",
    "sg:address":"170 Kinnelon Rd",
    "sg:city":"Butler",
    "sg:classifiers":[
        {
            "category":"Professional",
            "subcategory":"Management & Consulting",
            "type":"Services"
        }
    ],
    "sg:phone":"+1 973 492 1040",
    "sg:postcode":"07405",
    "sg:province":"NJ",
    "sg:tags":[
        "marketing",
        "consultant"
    ],
    "wof:name":"Sustainable Marketing Inc",
    "wof:placetype":"venue"
},
  "geometry": {"coordinates":[-74.384738,40.989068],"type":"Point"}
}