{
  "type": "Feature",
  "properties": {
    "addr:full":"1002 S 8th St Camden NJ 08103",
    "addr:housenumber":"1002",
    "addr:postcode":"08103",
    "addr:street":"S 8Th St",
    "iso:country":"US",
    "sg:address":"1002 S 8th St",
    "sg:city":"Camden",
    "sg:classifiers":[
        {
            "category":"Organizations",
            "subcategory":"Religious Organization",
            "type":"Services"
        }
    ],
    "sg:phone":"+1 856 963 5124",
    "sg:postcode":"08103",
    "sg:province":"NJ",
    "wof:name":"Russell David W Rev",
    "wof:placetype":"venue"
},
  "geometry": {"coordinates":[-75.113297,39.933899],"type":"Point"}
}