{
  "type": "Feature",
  "properties": {
    "iso:country":"US",
    "sg:address":"299 Market St",
    "sg:city":"Saddle Brook",
    "sg:classifiers":[
        {
            "category":"Banks & Credit Unions",
            "subcategory":"Bank",
            "type":"Services"
        }
    ],
    "sg:phone":"+1 201 291 1435",
    "sg:postcode":"07663",
    "sg:province":"NJ",
    "sg:tags":[
        "loan",
        "mortgage",
        "real estate"
    ],
    "sg:website":"www.ivanhoe.com",
    "wof:name":"Ivanhoe Financial Inc",
    "wof:placetype":"venue"
},
  "geometry": {"coordinates":[-74.09387,40.896744],"type":"Point"}
}