{
  "type": "Feature",
  "properties": {
    "addr:full":"303 Jeffry Ln Glen Gardner NJ 08826",
    "addr:housenumber":"303",
    "addr:postcode":"08826",
    "addr:street":"Jeffry Ln",
    "iso:country":"US",
    "sg:address":"303 Jeffry Ln",
    "sg:city":"Glen Gardner",
    "sg:classifiers":[
        {
            "category":"Building & Trades",
            "subcategory":"Construction",
            "type":"Services"
        }
    ],
    "sg:phone":"+1 908 537 4533",
    "sg:postcode":"08826",
    "sg:province":"NJ",
    "sg:tags":[
        "siding",
        "contractor"
    ],
    "wof:name":"Woodglen Siding & Home Imprvmt",
    "wof:placetype":"venue"
},
  "geometry": {"coordinates":[-74.908986,40.709557],"type":"Point"}
}