{
  "type": "Feature",
  "properties": {
    "iso:country":"US",
    "sg:address":"785 Twin Rivers Dr N",
    "sg:city":"Hightstown",
    "sg:classifiers":[
        {
            "category":"Retail",
            "subcategory":"Repair Shop",
            "type":"Services"
        }
    ],
    "sg:phone":"+1   ",
    "sg:postcode":"08520",
    "sg:province":"NJ",
    "sg:tags":[
        "refrigeration"
    ],
    "wof:name":"Pauls A/C",
    "wof:placetype":"venue"
},
  "geometry": {"coordinates":[-74.483671,40.270452],"type":"Point"}
}