{
  "type": "Feature",
  "properties": {
    "iso:country":"US",
    "sg:address":"564 Grand Ave",
    "sg:city":"Englewood",
    "sg:classifiers":[
        {
            "category":"Personal",
            "subcategory":"Barber",
            "type":"Services"
        }
    ],
    "sg:phone":"+1 201 871 0807",
    "sg:postcode":"07631",
    "sg:province":"NJ",
    "wof:name":"Main Street Barber Shop",
    "wof:placetype":"venue"
},
  "geometry": {"coordinates":[-73.98404499999999,40.876189],"type":"Point"}
}