{
  "type": "Feature",
  "properties": {
    "addr:full":"37 Cosgrove Ct East Brunswick NJ 08816",
    "addr:housenumber":"37",
    "addr:postcode":"08816",
    "addr:street":"Cosgrove Ct",
    "iso:country":"US",
    "sg:address":"37 Cosgrove Ct",
    "sg:city":"East Brunswick",
    "sg:classifiers":[
        {
            "category":"Wholesale",
            "subcategory":"Durable Goods & Equipment",
            "type":"Manufacturing & Wholesale Goods"
        }
    ],
    "sg:phone":"+1 732 698 1225",
    "sg:postcode":"08816",
    "sg:province":"NJ",
    "wof:name":"Justed Supplies",
    "wof:placetype":"venue"
},
  "geometry": {"coordinates":[-74.40428300000001,40.426051],"type":"Point"}
}