{
  "type": "Feature",
  "properties": {
    "addr:full":"10 Lincoln Ln Dayton NJ 08810",
    "addr:housenumber":"10",
    "addr:postcode":"08810",
    "addr:street":"Lincoln Ln",
    "iso:country":"US",
    "sg:address":"10 Lincoln Ln",
    "sg:city":"Dayton",
    "sg:classifiers":[
        {
            "category":"Building & Trades",
            "subcategory":"Construction",
            "type":"Services"
        }
    ],
    "sg:phone":"+1 732 438 5005",
    "sg:postcode":"08810",
    "sg:province":"NJ",
    "sg:tags":[
        "home",
        "house",
        "improvement"
    ],
    "wof:name":"J Alzin Contracting",
    "wof:placetype":"venue"
},
  "geometry": {"coordinates":[-74.51782,40.378129],"type":"Point"}
}