{
  "type": "Feature",
  "properties": {
    "addr:full":"421 Sampton Ave South Plainfield NJ 07080",
    "addr:housenumber":"421",
    "addr:postcode":"07080",
    "addr:street":"Sampton Ave",
    "iso:country":"US",
    "sg:address":"421 Sampton Ave",
    "sg:city":"South Plainfield",
    "sg:classifiers":[
        {
            "category":"Local Transit",
            "type":"Transportation"
        }
    ],
    "sg:phone":"+1 908 561 2382",
    "sg:postcode":"07080",
    "sg:province":"NJ",
    "sg:tags":[
        "limousine"
    ],
    "wof:name":"Execu-Jet Limousine Svc",
    "wof:placetype":"venue"
},
  "geometry": {"coordinates":[-74.422177,40.585652],"type":"Point"}
}