{
  "type": "Feature",
  "properties": {
    "addr:full":"8 Tamarack Rd Somerset NJ 08873",
    "addr:housenumber":"8",
    "addr:postcode":"08873",
    "addr:street":"Tamarack Rd",
    "iso:country":"US",
    "sg:address":"8 Tamarack Rd",
    "sg:city":"Somerset",
    "sg:classifiers":[
        {
            "category":"Real Estate",
            "subcategory":"Real Estate Agent",
            "type":"Services"
        }
    ],
    "sg:phone":"+1   ",
    "sg:postcode":"08873",
    "sg:province":"NJ",
    "wof:name":"Chrisma LLC",
    "wof:placetype":"venue"
},
  "geometry": {"coordinates":[-74.50378499999999,40.496713],"type":"Point"}
}