{
  "type": "Feature",
  "properties": {
    "addr:full":"800 Inman Ave Colonia NJ 07067",
    "addr:housenumber":"800",
    "addr:postcode":"07067",
    "addr:street":"Inman Ave",
    "iso:country":"US",
    "sg:address":"800 Inman Ave",
    "sg:city":"Colonia",
    "sg:classifiers":[
        {
            "category":"Banks & Credit Unions",
            "subcategory":"Bank",
            "type":"Services"
        }
    ],
    "sg:phone":"+1   ",
    "sg:postcode":"07067",
    "sg:province":"NJ",
    "sg:tags":[
        "state",
        "commercial"
    ],
    "wof:name":"Fleet",
    "wof:placetype":"venue"
},
  "geometry": {"coordinates":[-74.336566,40.598029],"type":"Point"}
}