{
  "type": "Feature",
  "properties": {
    "addr:full":"8 Pinewood Dr Manalapan NJ 07726",
    "addr:housenumber":"8",
    "addr:postcode":"07726",
    "addr:street":"Pinewood Dr",
    "iso:country":"US",
    "sg:address":"8 Pinewood Dr",
    "sg:city":"Manalapan",
    "sg:classifiers":[
        {
            "category":"Manufacturing",
            "subcategory":"Printing",
            "type":"Manufacturing & Wholesale Goods"
        }
    ],
    "sg:phone":"+1 914 243 0864",
    "sg:postcode":"07726",
    "sg:province":"NJ",
    "sg:tags":[
        "printer"
    ],
    "wof:name":"Advance Printing Inc",
    "wof:placetype":"venue"
},
  "geometry": {"coordinates":[-74.331857,40.329117],"type":"Point"}
}