{
  "type": "Feature",
  "properties": {
    "addr:full":"197 Indiana Ave Blackwood NJ 08012",
    "addr:housenumber":"197",
    "addr:postcode":"08012",
    "addr:street":"Indiana Ave",
    "iso:country":"US",
    "sg:address":"197 Indiana Ave",
    "sg:city":"Blackwood",
    "sg:classifiers":[
        {
            "category":"Professional",
            "type":"Services"
        }
    ],
    "sg:phone":"+1   ",
    "sg:postcode":"08012",
    "sg:province":"NJ",
    "wof:name":"Samuel Ragonese",
    "wof:placetype":"venue"
},
  "geometry": {"coordinates":[-75.05974999999999,39.79672],"type":"Point"}
}