{
  "type": "Feature",
  "properties": {
    "iso:country":"US",
    "sg:address":"35 Princeton Ave",
    "sg:city":"Brick",
    "sg:classifiers":[
        {
            "category":"Banks & Credit Unions",
            "subcategory":"Bank",
            "type":"Services"
        }
    ],
    "sg:phone":"+1 732 785 5600",
    "sg:postcode":"08724",
    "sg:province":"NJ",
    "sg:tags":[
        "loan",
        "real estate"
    ],
    "wof:name":"Centennial Mortgage Group",
    "wof:placetype":"venue"
},
  "geometry": {"coordinates":[-74.126087,40.067276],"type":"Point"}
}