{
  "type": "Feature",
  "properties": {
    "addr:full":"309 Woodbridge Ctr Woodbridge NJ 07095",
    "addr:housenumber":"309",
    "addr:postcode":"07095",
    "addr:street":"Woodbridge Ctr",
    "iso:country":"US",
    "sg:address":"309 Woodbridge Ctr",
    "sg:city":"Woodbridge",
    "sg:classifiers":[
        {
            "category":"Shopping",
            "subcategory":"Mobile Phones",
            "type":"Retail Goods"
        }
    ],
    "sg:phone":"+1 732 326 0277",
    "sg:postcode":"07095",
    "sg:province":"NJ",
    "sg:website":"sprint.com",
    "wof:name":"Sprint",
    "wof:placetype":"venue"
},
  "geometry": {"coordinates":[-74.301429,40.555443],"type":"Point"}
}