{
  "type": "Feature",
  "properties": {
    "iso:country":"US",
    "sg:address":"56 Hamilton Dr E",
    "sg:city":"Caldwell",
    "sg:classifiers":[
        {
            "category":"Health Services",
            "subcategory":"Doctor",
            "type":"Services"
        }
    ],
    "sg:phone":"+1 973 226 2311",
    "sg:postcode":"07006",
    "sg:province":"NJ",
    "sg:tags":[
        "surgeon",
        "oral"
    ],
    "wof:name":"Skibiak Edward M DDS",
    "wof:placetype":"venue"
},
  "geometry": {"coordinates":[-74.25299800000001,40.876099],"type":"Point"}
}