{
  "type": "Feature",
  "properties": {
    "iso:country":"US",
    "sg:address":"948 US Hwy 206",
    "sg:city":"Bridgewater",
    "sg:classifiers":[
        {
            "category":"Building & Trades",
            "subcategory":"Landscaping Services",
            "type":"Services"
        }
    ],
    "sg:phone":"+1 908 231 1010",
    "sg:postcode":"08807",
    "sg:province":"NJ",
    "wof:name":"Outdoor Impressions Inc",
    "wof:placetype":"venue"
},
  "geometry": {"coordinates":[-74.628536,40.62243],"type":"Point"}
}