{
  "type": "Feature",
  "properties": {
    "addr:full":"266 S Dean St Englewood NJ 07631",
    "addr:housenumber":"266",
    "addr:postcode":"07631",
    "addr:street":"S Dean St",
    "iso:country":"US",
    "sg:address":"266 S Dean St",
    "sg:city":"Englewood",
    "sg:classifiers":[
        {
            "category":"Building & Trades",
            "subcategory":"Landscaping Services",
            "type":"Services"
        },
        {
            "category":"Manufacturing",
            "subcategory":"Building Materials",
            "type":"Manufacturing & Wholesale Goods"
        }
    ],
    "sg:phone":"+1 201 567 3966",
    "sg:postcode":"07631",
    "sg:province":"NJ",
    "sg:tags":[
        "ponds",
        "designer",
        "garden",
        "consultant",
        "lake",
        "contractor",
        "water",
        "construction",
        "landscape"
    ],
    "wof:name":"Perennial Plantings, Inc",
    "wof:placetype":"venue"
},
  "geometry": {"coordinates":[-73.98008900000001,40.885602],"type":"Point"}
}