{
  "type": "Feature",
  "properties": {
    "iso:country":"US",
    "sg:address":"123 Hillside Ave",
    "sg:city":"Englewood",
    "sg:classifiers":[
        {
            "category":"Shopping",
            "subcategory":"Music",
            "type":"Retail Goods"
        }
    ],
    "sg:phone":"+1   ",
    "sg:postcode":"07631",
    "sg:province":"NJ",
    "wof:name":"Ajm Records LLC",
    "wof:placetype":"venue"
},
  "geometry": {"coordinates":[-73.967382,40.895433],"type":"Point"}
}