{
  "type": "Feature",
  "properties": {
    "iso:country":"US",
    "sg:address":"1 Hamilton Health Pl",
    "sg:city":"Trenton",
    "sg:classifiers":[
        {
            "category":"Health Services",
            "subcategory":"Hospital",
            "type":"Services"
        }
    ],
    "sg:phone":"+1 609 584 2229",
    "sg:postcode":"08690",
    "sg:province":"NJ",
    "sg:tags":[
        "center",
        "birth"
    ],
    "sg:website":"www.rwjhamilton.org",
    "wof:name":"Women-Infants Pavilion Hotline",
    "wof:placetype":"venue"
},
  "geometry": {"coordinates":[-74.672026,40.215108],"type":"Point"}
}