{
  "type": "Feature",
  "properties": {
    "addr:full":"2 Bridge Ave Red Bank NJ 07701",
    "addr:housenumber":"2",
    "addr:postcode":"07701",
    "addr:street":"Bridge Ave",
    "iso:country":"US",
    "sg:address":"2 Bridge Ave",
    "sg:city":"Red Bank",
    "sg:classifiers":[
        {
            "category":"Professional",
            "type":"Services"
        },
        {
            "category":"Professional",
            "subcategory":"Advertising",
            "type":"Services"
        }
    ],
    "sg:phone":"+1 732 345 3500",
    "sg:postcode":"07701",
    "sg:province":"NJ",
    "sg:tags":[
        "counselor"
    ],
    "wof:name":"Fallon Medica",
    "wof:placetype":"venue"
},
  "geometry": {"coordinates":[-74.075333,40.350916],"type":"Point"}
}