{
  "type": "Feature",
  "properties": {
    "addr:full":"257 Wilson St Hackensack NJ 07601",
    "addr:housenumber":"257",
    "addr:postcode":"07601",
    "addr:street":"Wilson St",
    "iso:country":"US",
    "sg:address":"257 Wilson St",
    "sg:city":"Hackensack",
    "sg:classifiers":[
        {
            "category":"Utilities",
            "subcategory":"Cable",
            "type":"Services"
        }
    ],
    "sg:phone":"+1 201 525 0564",
    "sg:postcode":"07601",
    "sg:province":"NJ",
    "sg:tags":[
        "home",
        "satellite",
        "theater"
    ],
    "wof:name":"East Coast Satellite Wireless",
    "wof:placetype":"venue"
},
  "geometry": {"coordinates":[-74.044028,40.910663],"type":"Point"}
}