{
  "type": "Feature",
  "properties": {
    "addr:full":"2447 State Rte 33 Neptune NJ 07753",
    "addr:housenumber":"2447",
    "addr:postcode":"07753",
    "addr:street":"State Rte 33",
    "iso:country":"US",
    "sg:address":"2447 State Rte 33",
    "sg:city":"Neptune",
    "sg:classifiers":[
        {
            "category":"Food & Beverages",
            "subcategory":"Liquor & Beverages",
            "type":"Retail Goods"
        }
    ],
    "sg:phone":"+1 732 922 3565",
    "sg:postcode":"07753",
    "sg:province":"NJ",
    "sg:tags":[
        "drinking",
        "alcoholic"
    ],
    "wof:name":"Garden Bar Liquors Inc",
    "wof:placetype":"venue"
},
  "geometry": {"coordinates":[-74.05626100000001,40.207015],"type":"Point"}
}