{
  "type": "Feature",
  "properties": {
    "iso:country":"US",
    "sg:address":"2838 John F Kennedy Blvd",
    "sg:city":"Jersey City",
    "sg:classifiers":[
        {
            "category":"Shopping",
            "subcategory":"Clothing, Apparel, & Fashions",
            "type":"Retail Goods"
        }
    ],
    "sg:phone":"+1 201 420 1811",
    "sg:postcode":"07306",
    "sg:province":"NJ",
    "sg:tags":[
        "infant",
        "wear"
    ],
    "wof:name":"Childrens Fashions",
    "wof:placetype":"venue"
},
  "geometry": {"coordinates":[-74.06717999999999,40.731738],"type":"Point"}
}