{
  "type": "Feature",
  "properties": {
    "addr:full":"51 Flatbrook Rd Sandyston NJ 07826",
    "addr:housenumber":"51",
    "addr:postcode":"07826",
    "addr:street":"Flatbrook Rd",
    "iso:country":"US",
    "sg:address":"51 Flatbrook Rd",
    "sg:city":"Sandyston",
    "sg:classifiers":[
        {
            "category":"Building & Trades",
            "subcategory":"Plumbing",
            "type":"Services"
        },
        {
            "category":"Building & Trades",
            "subcategory":"Construction",
            "type":"Services"
        }
    ],
    "sg:phone":"+1 973 948 5048",
    "sg:postcode":"07826",
    "sg:province":"NJ",
    "sg:tags":[
        "system",
        "specialty",
        "heating",
        "clean",
        "contractor",
        "air conditioning",
        "boilers-repair"
    ],
    "wof:name":"All Tech Enterprise",
    "wof:placetype":"venue"
},
  "geometry": {"coordinates":[-74.788416,41.216953],"type":"Point"}
}