{
  "type": "Feature",
  "properties": {
    "iso:country":"US",
    "sg:address":"393 S Washington Ave",
    "sg:city":"Bergenfield",
    "sg:classifiers":[
        {
            "category":"Food & Beverages",
            "subcategory":"Groceries & Convenience Stores",
            "type":"Retail Goods"
        }
    ],
    "sg:phone":"+1 201 387 9101",
    "sg:postcode":"07621",
    "sg:province":"NJ",
    "wof:name":"Quik Shop",
    "wof:placetype":"venue"
},
  "geometry": {"coordinates":[-73.997299,40.914101],"type":"Point"}
}