{
  "type": "Feature",
  "properties": {
    "iso:country":"US",
    "sg:address":"2 Applewood Ct",
    "sg:city":"Milltown",
    "sg:classifiers":[
        {
            "category":"Freight",
            "type":"Transportation"
        }
    ],
    "sg:phone":"+1 732 937 5111",
    "sg:postcode":"08850",
    "sg:province":"NJ",
    "wof:name":"Elmo Transportation Inc",
    "wof:placetype":"venue"
},
  "geometry": {"coordinates":[-74.42748,40.452917],"type":"Point"}
}