{
  "type": "Feature",
  "properties": {
    "iso:country":"US",
    "sg:address":"23 3rd Ave",
    "sg:city":"Toms River",
    "sg:classifiers":[
        {
            "category":"Professional",
            "type":"Services"
        }
    ],
    "sg:phone":"+1   ",
    "sg:postcode":"08757",
    "sg:province":"NJ",
    "wof:name":"Hilltop Products",
    "wof:placetype":"venue"
},
  "geometry": {"coordinates":[-74.21166700000001,39.945421],"type":"Point"}
}