{
  "type": "Feature",
  "properties": {
    "iso:country":"US",
    "sg:address":"47 Strong St",
    "sg:city":"Wallington",
    "sg:classifiers":[
        {
            "category":"Building & Trades",
            "subcategory":"Construction",
            "type":"Services"
        }
    ],
    "sg:phone":"+1 973 916 1724",
    "sg:postcode":"07057",
    "sg:province":"NJ",
    "sg:tags":[
        "contractor"
    ],
    "wof:name":"Jt Contractor",
    "wof:placetype":"venue"
},
  "geometry": {"coordinates":[-74.108918,40.854235],"type":"Point"}
}