{
  "type": "Feature",
  "properties": {
    "iso:country":"US",
    "sg:address":"545 Broadway",
    "sg:city":"Bayonne",
    "sg:classifiers":[
        {
            "category":"Real Estate",
            "subcategory":"Real Estate Agent",
            "type":"Services"
        }
    ],
    "sg:phone":"+1 201 436 9600",
    "sg:postcode":"07002",
    "sg:province":"NJ",
    "wof:name":"ALD Realty",
    "wof:placetype":"venue"
},
  "geometry": {"coordinates":[-74.11612100000001,40.66645],"type":"Point"}
}