{
  "type": "Feature",
  "properties": {
    "addr:full":"30 W Price St Linden NJ 07036",
    "addr:housenumber":"30",
    "addr:postcode":"07036",
    "addr:street":"W Price St",
    "iso:country":"US",
    "sg:address":"30 W Price St",
    "sg:city":"Linden",
    "sg:classifiers":[
        {
            "category":"Manufacturing",
            "subcategory":"Leather Goods",
            "type":"Manufacturing & Wholesale Goods"
        }
    ],
    "sg:phone":"+1 908 862 7447",
    "sg:postcode":"07036",
    "sg:province":"NJ",
    "wof:name":"Toskana",
    "wof:placetype":"venue"
},
  "geometry": {"coordinates":[-74.254204,40.630699],"type":"Point"}
}