{
  "type": "Feature",
  "properties": {
    "iso:country":"US",
    "sg:address":"31 Perry St Ste 3",
    "sg:city":"Cape May",
    "sg:classifiers":[
        {
            "category":"Arts & Performance",
            "subcategory":"Art Gallery",
            "type":"Entertainment"
        }
    ],
    "sg:phone":"+1 609 898 7488",
    "sg:postcode":"08204",
    "sg:province":"NJ",
    "wof:name":"Artdecor Gallery",
    "wof:placetype":"venue"
},
  "geometry": {"coordinates":[-74.92330200000001,38.930599],"type":"Point"}
}