{
  "type": "Feature",
  "properties": {
    "iso:country":"US",
    "sg:address":"365 Main St",
    "sg:city":"Sayreville",
    "sg:classifiers":[
        {
            "category":"Restaurant",
            "type":"Food & Drink"
        }
    ],
    "sg:menulink":"http://www.allmenus.com/nj/sayreville/274686-country-kitchen/menu/",
    "sg:phone":"+1 732 254 9919",
    "sg:postcode":"08872",
    "sg:province":"NJ",
    "sg:tags":[
        "american"
    ],
    "wof:name":"Country Kitchen",
    "wof:placetype":"venue"
},
  "geometry": {"coordinates":[-74.354753,40.471178],"type":"Point"}
}