{
  "type": "Feature",
  "properties": {
    "addr:full":"790 Main St Hackensack NJ 07601",
    "addr:housenumber":"790",
    "addr:postcode":"07601",
    "addr:street":"Main St",
    "iso:country":"US",
    "sg:address":"790 Main St",
    "sg:city":"Hackensack",
    "sg:classifiers":[
        {
            "category":"Wholesale",
            "subcategory":"Machinery & Supplies",
            "type":"Manufacturing & Wholesale Goods"
        }
    ],
    "sg:phone":"+1 201 342 1887",
    "sg:postcode":"07601",
    "sg:province":"NJ",
    "sg:tags":[
        "equipment",
        "laundry"
    ],
    "wof:name":"Bob's Machinery Svc",
    "wof:placetype":"venue"
},
  "geometry": {"coordinates":[-74.042154,40.905006],"type":"Point"}
}