{
  "type": "Feature",
  "properties": {
    "addr:full":"6 Kingsbridge Rd Fairfield NJ 07004",
    "addr:housenumber":"6",
    "addr:postcode":"07004",
    "addr:street":"Kingsbridge Rd",
    "iso:country":"US",
    "sg:address":"6 Kingsbridge Rd",
    "sg:city":"Fairfield",
    "sg:classifiers":[
        {
            "category":"Professional",
            "type":"Services"
        }
    ],
    "sg:phone":"+1   ",
    "sg:postcode":"07004",
    "sg:province":"NJ",
    "wof:name":"Community Alert",
    "wof:placetype":"venue"
},
  "geometry": {"coordinates":[-74.269396,40.879953],"type":"Point"}
}