{
  "type": "Feature",
  "properties": {
    "addr:full":"1423 Tilton Rd Northfield NJ 08225",
    "addr:housenumber":"1423",
    "addr:postcode":"08225",
    "addr:street":"Tilton Rd",
    "iso:country":"US",
    "sg:address":"1423 Tilton Rd",
    "sg:city":"Northfield",
    "sg:classifiers":[
        {
            "category":"Professional",
            "subcategory":"Lawyer & Legal Services",
            "type":"Services"
        }
    ],
    "sg:phone":"+1 609 272 1111",
    "sg:postcode":"08225",
    "sg:province":"NJ",
    "wof:name":"James E Robertson",
    "wof:placetype":"venue"
},
  "geometry": {"coordinates":[-74.553049,39.371544],"type":"Point"}
}