{
  "type": "Feature",
  "properties": {
    "iso:country":"US",
    "sg:address":"92 E Centre St",
    "sg:city":"Nutley",
    "sg:classifiers":[
        {
            "category":"Retail",
            "subcategory":"Auto Repair",
            "type":"Services"
        }
    ],
    "sg:phone":"+1 973 667 0541",
    "sg:postcode":"07110",
    "sg:province":"NJ",
    "sg:tags":[
        "body",
        "shop"
    ],
    "wof:name":"Elite Auto Body",
    "wof:placetype":"venue"
},
  "geometry": {"coordinates":[-74.145798,40.809399],"type":"Point"}
}