{
  "type": "Feature",
  "properties": {
    "addr:full":"603 Boozer Ln Hillsborough NJ 08844",
    "addr:housenumber":"603",
    "addr:postcode":"08844",
    "addr:street":"Boozer Ln",
    "iso:country":"US",
    "sg:address":"603 Boozer Ln",
    "sg:city":"Hillsborough",
    "sg:classifiers":[
        {
            "category":"Professional",
            "subcategory":"Business Services",
            "type":"Services"
        }
    ],
    "sg:phone":"+1   ",
    "sg:postcode":"08844",
    "sg:province":"NJ",
    "sg:tags":[
        "documentation",
        "custom"
    ],
    "wof:name":"CAN Associates",
    "wof:placetype":"venue"
},
  "geometry": {"coordinates":[-74.696482,40.51597],"type":"Point"}
}