{
  "type": "Feature",
  "properties": {
    "addr:full":"452 Philadelphia Ave Egg Harbor City NJ 08215",
    "addr:housenumber":"452",
    "addr:postcode":"08215",
    "addr:street":"Philadelphia Ave",
    "iso:country":"US",
    "sg:address":"452 Philadelphia Ave",
    "sg:city":"Egg Harbor City",
    "sg:classifiers":[
        {
            "category":"Restaurant",
            "type":"Food & Drink"
        }
    ],
    "sg:phone":"+1 609 965 2037",
    "sg:postcode":"08215",
    "sg:province":"NJ",
    "sg:tags":[
        "sandwich",
        "eating"
    ],
    "wof:name":"Al's Luncheonette",
    "wof:placetype":"venue"
},
  "geometry": {"coordinates":[-74.64199499999999,39.53335],"type":"Point"}
}