{
  "type": "Feature",
  "properties": {
    "addr:full":"23 Walnut St Summit NJ 07901",
    "addr:housenumber":"23",
    "addr:postcode":"07901",
    "addr:street":"Walnut St",
    "iso:country":"US",
    "sg:address":"23 Walnut St",
    "sg:city":"Summit",
    "sg:classifiers":[
        {
            "category":"Professional",
            "type":"Services"
        }
    ],
    "sg:phone":"+1 908 608 9111",
    "sg:postcode":"07901",
    "sg:province":"NJ",
    "sg:tags":[
        "establishment"
    ],
    "wof:name":"IMC Assoc",
    "wof:placetype":"venue"
},
  "geometry": {"coordinates":[-74.35592699999999,40.714232],"type":"Point"}
}