{
  "type": "Feature",
  "properties": {
    "iso:country":"US",
    "sg:address":"679 S 10th St",
    "sg:city":"Newark",
    "sg:classifiers":[
        {
            "category":"Building & Trades",
            "subcategory":"Construction",
            "type":"Services"
        }
    ],
    "sg:phone":"+1 973 242 8400",
    "sg:postcode":"07108",
    "sg:province":"NJ",
    "sg:tags":[
        "builder",
        "repairer",
        "chimney"
    ],
    "wof:name":"A 1 Access",
    "wof:placetype":"venue"
},
  "geometry": {"coordinates":[-74.204976,40.72892],"type":"Point"}
}