{
  "type": "Feature",
  "properties": {
    "addr:full":"35 N Colonial Dr Harrington Park NJ 07640",
    "addr:housenumber":"35",
    "addr:postcode":"07640",
    "addr:street":"N Colonial Dr",
    "iso:country":"US",
    "sg:address":"35 N Colonial Dr",
    "sg:city":"Harrington Park",
    "sg:classifiers":[
        {
            "category":"Retail",
            "subcategory":"Repair Shop",
            "type":"Services"
        }
    ],
    "sg:phone":"+1 201 767 3037",
    "sg:postcode":"07640",
    "sg:province":"NJ",
    "wof:name":"Hans J Nebel LLC",
    "wof:placetype":"venue"
},
  "geometry": {"coordinates":[-73.977414,41.004996],"type":"Point"}
}