{
  "type": "Feature",
  "properties": {
    "addr:full":"279 Wall St Princeton NJ 08540",
    "addr:housenumber":"279",
    "addr:postcode":"08540",
    "addr:street":"Wall St",
    "iso:country":"US",
    "sg:address":"279 Wall St",
    "sg:city":"Princeton",
    "sg:classifiers":[
        {
            "category":"Professional",
            "subcategory":"Management & Consulting",
            "type":"Services"
        }
    ],
    "sg:phone":"+1 609 683 4035",
    "sg:postcode":"08540",
    "sg:province":"NJ",
    "sg:tags":[
        "marketing",
        "program"
    ],
    "sg:website":"www.imsworld.com",
    "wof:name":"Integrated Marketing Svc Inc",
    "wof:placetype":"venue"
},
  "geometry": {"coordinates":[-74.65091200000001,40.39655],"type":"Point"}
}