{
  "type": "Feature",
  "properties": {
    "addr:full":"2 Macarthur Ave Lodi NJ 07644",
    "addr:housenumber":"2",
    "addr:postcode":"07644",
    "addr:street":"Macarthur Ave",
    "iso:country":"US",
    "sg:address":"2 Macarthur Ave",
    "sg:city":"Lodi",
    "sg:classifiers":[
        {
            "category":"Professional",
            "subcategory":"Management & Consulting",
            "type":"Services"
        }
    ],
    "sg:phone":"+1 914 830 3535",
    "sg:postcode":"07644",
    "sg:province":"NJ",
    "sg:tags":[
        "business"
    ],
    "wof:name":"AB Medical Consulting LLC",
    "wof:placetype":"venue"
},
  "geometry": {"coordinates":[-74.07384399999999,40.8786],"type":"Point"}
}