{
  "type": "Feature",
  "properties": {
    "addr:full":"21 Church St Basking Ridge NJ 07920",
    "addr:housenumber":"21",
    "addr:postcode":"07920",
    "addr:street":"Church St",
    "iso:country":"US",
    "sg:address":"21 Church St",
    "sg:city":"Basking Ridge",
    "sg:classifiers":[
        {
            "category":"Food & Beverages",
            "subcategory":"Bakery",
            "type":"Retail Goods"
        }
    ],
    "sg:phone":"+1 908 604 0600",
    "sg:postcode":"07920",
    "sg:province":"NJ",
    "sg:tags":[
        "baker"
    ],
    "wof:name":"Gourmet Touch",
    "wof:placetype":"venue"
},
  "geometry": {"coordinates":[-74.584141,40.666181],"type":"Point"}
}