{
  "type": "Feature",
  "properties": {
    "addr:full":"360 1st St Hoboken NJ 07030",
    "addr:housenumber":"360",
    "addr:postcode":"07030",
    "addr:street":"1St St",
    "iso:country":"US",
    "sg:address":"360 1st St",
    "sg:city":"Hoboken",
    "sg:classifiers":[
        {
            "category":"Utilities",
            "subcategory":"Cable",
            "type":"Services"
        },
        {
            "category":"Professional",
            "subcategory":"Advertising",
            "type":"Services"
        }
    ],
    "sg:phone":"+1 201 798 6060",
    "sg:postcode":"07030",
    "sg:province":"NJ",
    "sg:tags":[
        "television"
    ],
    "wof:name":"Cablevision",
    "wof:placetype":"venue"
},
  "geometry": {"coordinates":[-74.036035,40.738394],"type":"Point"}
}