{
  "type": "Feature",
  "properties": {
    "addr:full":"8 Market St Clifton NJ 07012",
    "addr:housenumber":"8",
    "addr:postcode":"07012",
    "addr:street":"Market St",
    "iso:country":"US",
    "sg:address":"8 Market St",
    "sg:city":"Clifton",
    "sg:classifiers":[
        {
            "category":"Building & Trades",
            "subcategory":"Locksmith",
            "type":"Services"
        }
    ],
    "sg:phone":"+1 888 277 2906",
    "sg:postcode":"07012",
    "sg:province":"NJ",
    "sg:tags":[
        "key"
    ],
    "wof:name":"24 Hour 7 Day Emergency Locksmith",
    "wof:placetype":"venue"
},
  "geometry": {"coordinates":[-74.158202,40.845672],"type":"Point"}
}