{
  "type": "Feature",
  "properties": {
    "addr:full":"373 Broadway Passaic NJ 07055",
    "addr:housenumber":"373",
    "addr:postcode":"07055",
    "addr:street":"Broadway",
    "iso:country":"US",
    "sg:address":"373 Broadway",
    "sg:city":"Passaic",
    "sg:classifiers":[
        {
            "category":"Bars & Pubs",
            "subcategory":"Lounge",
            "type":"Food & Drink"
        }
    ],
    "sg:phone":"+1 973 365 0807",
    "sg:postcode":"07055",
    "sg:province":"NJ",
    "wof:name":"The Loop Lounge",
    "wof:placetype":"venue"
},
  "geometry": {"coordinates":[-74.138603,40.854],"type":"Point"}
}