{
  "type": "Feature",
  "properties": {
    "iso:country":"US",
    "sg:address":"248 Columbia Tpke",
    "sg:city":"Florham Park",
    "sg:classifiers":[
        {
            "category":"Social Services",
            "type":"Services"
        }
    ],
    "sg:phone":"+1 973 377 0055",
    "sg:postcode":"07932",
    "sg:province":"NJ",
    "sg:tags":[
        "counselor",
        "marriage",
        "family"
    ],
    "wof:name":"Nancy Beckerman",
    "wof:placetype":"venue"
},
  "geometry": {"coordinates":[-74.397898,40.789071],"type":"Point"}
}