{
  "type": "Feature",
  "properties": {
    "iso:country":"US",
    "sg:address":"7 Hillside Ave",
    "sg:city":"Jamesburg",
    "sg:classifiers":[
        {
            "category":"Professional",
            "subcategory":"Management & Consulting",
            "type":"Services"
        }
    ],
    "sg:phone":"+1 732 521 2514",
    "sg:postcode":"08831",
    "sg:province":"NJ",
    "sg:tags":[
        "consultant",
        "business"
    ],
    "wof:name":"Daniel Dobromilsky & Assoc",
    "wof:placetype":"venue"
},
  "geometry": {"coordinates":[-74.442858,40.351221],"type":"Point"}
}