{
  "type": "Feature",
  "properties": {
    "iso:country":"US",
    "sg:address":"1612 Wight St",
    "sg:city":"Belmar",
    "sg:classifiers":[
        {
            "category":"Shopping",
            "subcategory":"Used Merchandise",
            "type":"Retail Goods"
        }
    ],
    "sg:phone":"+1   ",
    "sg:postcode":"07719",
    "sg:province":"NJ",
    "wof:name":"Whispering Marsh Antiques",
    "wof:placetype":"venue"
},
  "geometry": {"coordinates":[-74.04967499999999,40.179442],"type":"Point"}
}