{
  "type": "Feature",
  "properties": {
    "addr:full":"290 Davidson Ave Somerset NJ 08873",
    "addr:housenumber":"290",
    "addr:postcode":"08873",
    "addr:street":"Davidson Ave",
    "iso:country":"US",
    "sg:address":"290 Davidson Ave",
    "sg:city":"Somerset",
    "sg:classifiers":[
        {
            "category":"Utilities",
            "subcategory":"Telephone",
            "type":"Services"
        }
    ],
    "sg:phone":"+1 732 805 2200",
    "sg:postcode":"08873",
    "sg:province":"NJ",
    "sg:tags":[
        "communications"
    ],
    "wof:name":"AT&T Securities",
    "wof:placetype":"venue"
},
  "geometry": {"coordinates":[-74.528097,40.533076],"type":"Point"}
}