{
  "type": "Feature",
  "properties": {
    "iso:country":"US",
    "sg:address":"40 Morristown Rd",
    "sg:city":"Bernardsville",
    "sg:classifiers":[
        {
            "category":"Professional",
            "subcategory":"Employment Agencies",
            "type":"Services"
        }
    ],
    "sg:phone":"+1   ",
    "sg:postcode":"07924",
    "sg:province":"NJ",
    "sg:tags":[
        "firm",
        "search",
        "executive",
        "placement"
    ],
    "wof:name":"Dtx Inc",
    "wof:placetype":"venue"
},
  "geometry": {"coordinates":[-74.56199700000001,40.719616],"type":"Point"}
}