{
  "type": "Feature",
  "properties": {
    "addr:full":"105 E Hand Ave Wildwood NJ 08260",
    "addr:housenumber":"105",
    "addr:postcode":"08260",
    "addr:street":"E Hand Ave",
    "iso:country":"US",
    "sg:address":"105 E Hand Ave",
    "sg:city":"Wildwood",
    "sg:classifiers":[
        {
            "category":"Building & Trades",
            "subcategory":"Electrical",
            "type":"Services"
        }
    ],
    "sg:phone":"+1 609 729 5929",
    "sg:postcode":"08260",
    "sg:province":"NJ",
    "sg:tags":[
        "electrical",
        "contractor"
    ],
    "wof:name":"Lauriello Electric",
    "wof:placetype":"venue"
},
  "geometry": {"coordinates":[-74.825253,38.983578],"type":"Point"}
}