{
  "type": "Feature",
  "properties": {
    "addr:full":"416 Howard St Millville NJ 08332",
    "addr:housenumber":"416",
    "addr:postcode":"08332",
    "addr:street":"Howard St",
    "iso:country":"US",
    "sg:address":"416 Howard St",
    "sg:city":"Millville",
    "sg:classifiers":[
        {
            "category":"Building & Trades",
            "subcategory":"Plumbing",
            "type":"Services"
        }
    ],
    "sg:phone":"+1 856 825 2072",
    "sg:postcode":"08332",
    "sg:province":"NJ",
    "sg:tags":[
        "heating",
        "contractor"
    ],
    "wof:name":"Harrell Heating Svc",
    "wof:placetype":"venue"
},
  "geometry": {"coordinates":[-75.049291,39.39548],"type":"Point"}
}