{
  "type": "Feature",
  "properties": {
    "iso:country":"US",
    "sg:address":"30 Brautigam Ln",
    "sg:city":"Midland Park",
    "sg:classifiers":[
        {
            "category":"Building & Trades",
            "subcategory":"Construction",
            "type":"Services"
        }
    ],
    "sg:phone":"+1 201 493 0787",
    "sg:postcode":"07432",
    "sg:province":"NJ",
    "sg:tags":[
        "house"
    ],
    "wof:name":"Primo Remodeling Inc",
    "wof:placetype":"venue"
},
  "geometry": {"coordinates":[-74.133025,40.988097],"type":"Point"}
}