{
  "type": "Feature",
  "properties": {
    "iso:country":"US",
    "sg:address":"417 Main St",
    "sg:city":"Little Falls",
    "sg:classifiers":[
        {
            "category":"Retail",
            "subcategory":"Auto Repair",
            "type":"Services"
        }
    ],
    "sg:phone":"+1 973 256 0686",
    "sg:postcode":"07424",
    "sg:province":"NJ",
    "sg:tags":[
        "body",
        "shop"
    ],
    "wof:name":"Malanga Auto Body",
    "wof:placetype":"venue"
},
  "geometry": {"coordinates":[-74.240898,40.886101],"type":"Point"}
}