{
  "type": "Feature",
  "properties": {
    "iso:country":"US",
    "sg:address":"649 Newark Ave",
    "sg:city":"Jersey City",
    "sg:classifiers":[
        {
            "category":"Professional",
            "subcategory":"Lawyer & Legal Services",
            "type":"Services"
        }
    ],
    "sg:phone":"+1 201 533 1100",
    "sg:postcode":"07306",
    "sg:province":"NJ",
    "sg:tags":[
        "attorney"
    ],
    "wof:name":"Nicholas Fitzgerald Law Ofcs",
    "wof:placetype":"venue"
},
  "geometry": {"coordinates":[-74.058734,40.733821],"type":"Point"}
}