{
  "type": "Feature",
  "properties": {
    "addr:full":"1101 Barclay Ct Randolph NJ 07869",
    "addr:housenumber":"1101",
    "addr:postcode":"07869",
    "addr:street":"Barclay Ct",
    "iso:country":"US",
    "sg:address":"1101 Barclay Ct",
    "sg:city":"Randolph",
    "sg:classifiers":[
        {
            "category":"Retail",
            "subcategory":"Repair Shop",
            "type":"Services"
        }
    ],
    "sg:phone":"+1   ",
    "sg:postcode":"07869",
    "sg:province":"NJ",
    "wof:name":"Absolute Repairs",
    "wof:placetype":"venue"
},
  "geometry": {"coordinates":[-74.61228,40.860867],"type":"Point"}
}