{
  "type": "Feature",
  "properties": {
    "iso:country":"US",
    "sg:address":"72 W Main St",
    "sg:city":"Ramsey",
    "sg:classifiers":[
        {
            "category":"Home & Garden",
            "subcategory":"Carpets & Floor Coverings",
            "type":"Retail Goods"
        }
    ],
    "sg:phone":"+1 201 819 7932",
    "sg:postcode":"07446",
    "sg:province":"NJ",
    "sg:tags":[
        "dealer",
        "rug"
    ],
    "wof:name":"B & M Carpet Etc",
    "wof:placetype":"venue"
},
  "geometry": {"coordinates":[-74.14396000000001,41.057148],"type":"Point"}
}