{
  "type": "Feature",
  "properties": {
    "addr:full":"56 Elmwood Ave Montclair NJ 07042",
    "addr:housenumber":"56",
    "addr:postcode":"07042",
    "addr:street":"Elmwood Ave",
    "iso:country":"US",
    "sg:address":"56 Elmwood Ave",
    "sg:city":"Montclair",
    "sg:classifiers":[
        {
            "category":"Organizations",
            "subcategory":"Religious Organization",
            "type":"Services"
        }
    ],
    "sg:phone":"+1 973 783 4852",
    "sg:postcode":"07042",
    "sg:province":"NJ",
    "sg:tags":[
        "service/non-profit",
        "community",
        "church"
    ],
    "sg:website":"www.saintpeterclaverchurch.org",
    "wof:name":"St Peter Claver R C Church",
    "wof:placetype":"venue"
},
  "geometry": {"coordinates":[-74.21489699999999,40.806499],"type":"Point"}
}