{
  "type": "Feature",
  "properties": {
    "iso:country":"US",
    "sg:address":"480 Memorial Pkwy",
    "sg:city":"Phillipsburg",
    "sg:classifiers":[
        {
            "category":"Banks & Credit Unions",
            "subcategory":"Bank",
            "type":"Services"
        }
    ],
    "sg:phone":"+1 908 454 8009",
    "sg:postcode":"08865",
    "sg:province":"NJ",
    "sg:tags":[
        "loan",
        "real estate"
    ],
    "wof:name":"JSI Mortgage LLC",
    "wof:placetype":"venue"
},
  "geometry": {"coordinates":[-75.189485,40.695587],"type":"Point"}
}