{
  "type": "Feature",
  "properties": {
    "addr:full":"106 Ark Rd Lumberton NJ 08048",
    "addr:housenumber":"106",
    "addr:postcode":"08048",
    "addr:street":"Ark Rd",
    "iso:country":"US",
    "sg:address":"106 Ark Rd",
    "sg:city":"Lumberton",
    "sg:classifiers":[
        {
            "category":"Professional",
            "subcategory":"Research",
            "type":"Services"
        }
    ],
    "sg:phone":"+1 609 953 0878",
    "sg:postcode":"08048",
    "sg:province":"NJ",
    "sg:tags":[
        "environmental",
        "ecological"
    ],
    "wof:name":"Soiltech Inc",
    "wof:placetype":"venue"
},
  "geometry": {"coordinates":[-74.852181,39.936312],"type":"Point"}
}