{
  "type": "Feature",
  "properties": {
    "addr:full":"51 Dean Rd Mendham NJ 07945",
    "addr:housenumber":"51",
    "addr:postcode":"07945",
    "addr:street":"Dean Rd",
    "iso:country":"US",
    "sg:address":"51 Dean Rd",
    "sg:city":"Mendham",
    "sg:classifiers":[
        {
            "category":"Health Services",
            "subcategory":"Health Practitioner",
            "type":"Services"
        }
    ],
    "sg:phone":"+1   ",
    "sg:postcode":"07945",
    "sg:province":"NJ",
    "wof:name":"Johanna Burani Ms Rd",
    "wof:placetype":"venue"
},
  "geometry": {"coordinates":[-74.595322,40.785527],"type":"Point"}
}