{
  "type": "Feature",
  "properties": {
    "addr:full":"412 77th St North Bergen NJ 07047",
    "addr:housenumber":"412",
    "addr:postcode":"07047",
    "addr:street":"77Th St",
    "iso:country":"US",
    "sg:address":"412 77th St",
    "sg:city":"North Bergen",
    "sg:classifiers":[
        {
            "category":"Banks & Credit Unions",
            "subcategory":"Financial Services",
            "type":"Services"
        }
    ],
    "sg:phone":"+1   ",
    "sg:postcode":"07047",
    "sg:province":"NJ",
    "sg:tags":[
        "investor"
    ],
    "wof:name":"Campbell Investment Group Inc",
    "wof:placetype":"venue"
},
  "geometry": {"coordinates":[-74.007653,40.800324],"type":"Point"}
}