{
  "type": "Feature",
  "properties": {
    "iso:country":"US",
    "sg:address":"238 Quail Ln N",
    "sg:city":"Lanoka Harbor",
    "sg:classifiers":[
        {
            "category":"Building & Trades",
            "subcategory":"Landscaping Services",
            "type":"Services"
        }
    ],
    "sg:phone":"+1 609 971 0548",
    "sg:postcode":"08734",
    "sg:province":"NJ",
    "sg:tags":[
        "landscape",
        "contractor"
    ],
    "wof:name":"Landscaping By Cerami",
    "wof:placetype":"venue"
},
  "geometry": {"coordinates":[-74.19167899999999,39.87029],"type":"Point"}
}