{
  "type": "Feature",
  "properties": {
    "addr:full":"20 Hutton Dr Mahwah NJ 07430",
    "addr:housenumber":"20",
    "addr:postcode":"07430",
    "addr:street":"Hutton Dr",
    "iso:country":"US",
    "sg:address":"20 Hutton Dr",
    "sg:city":"Mahwah",
    "sg:classifiers":[
        {
            "category":"Professional",
            "subcategory":"Management & Consulting",
            "type":"Services"
        }
    ],
    "sg:phone":"+1   ",
    "sg:postcode":"07430",
    "sg:province":"NJ",
    "wof:name":"Thomas Pizzillo/Son",
    "wof:placetype":"venue"
},
  "geometry": {"coordinates":[-74.16948499999999,41.032789],"type":"Point"}
}