{
  "type": "Feature",
  "properties": {
    "addr:full":"2325 Elizabeth Ave Rahway NJ 07065",
    "addr:housenumber":"2325",
    "addr:postcode":"07065",
    "addr:street":"Elizabeth Ave",
    "iso:country":"US",
    "sg:address":"2325 Elizabeth Ave",
    "sg:city":"Rahway",
    "sg:classifiers":[
        {
            "category":"Food & Beverages",
            "subcategory":"Meat & Fish",
            "type":"Retail Goods"
        }
    ],
    "sg:phone":"+1 732 499 4600",
    "sg:postcode":"07065",
    "sg:province":"NJ",
    "sg:tags":[
        "seafood",
        "market"
    ],
    "wof:name":"Western Fish Department",
    "wof:placetype":"venue"
},
  "geometry": {"coordinates":[-74.2668,40.6171],"type":"Point"}
}