{
  "type": "Feature",
  "properties": {
    "addr:full":"84 Washington St Hoboken NJ 07030",
    "addr:housenumber":"84",
    "addr:postcode":"07030",
    "addr:street":"Washington St",
    "iso:country":"US",
    "sg:address":"84 Washington St",
    "sg:city":"Hoboken",
    "sg:classifiers":[
        {
            "category":"Recreation",
            "subcategory":"Dance Hall",
            "type":"Entertainment"
        }
    ],
    "sg:phone":"+1 201 420 1112",
    "sg:postcode":"07030",
    "sg:province":"NJ",
    "sg:tags":[
        "club"
    ],
    "sg:website":"www.room84hoboken.com/home.html",
    "wof:name":"Room 84",
    "wof:placetype":"venue"
},
  "geometry": {"coordinates":[-74.031099,40.736886],"type":"Point"}
}