{
  "type": "Feature",
  "properties": {
    "addr:full":"758 Paterson Plank Rd East Rutherford NJ 07073",
    "addr:housenumber":"758",
    "addr:postcode":"07073",
    "addr:street":"Paterson Plank Rd",
    "iso:country":"US",
    "sg:address":"758 Paterson Plank Rd",
    "sg:city":"East Rutherford",
    "sg:classifiers":[
        {
            "category":"Autos & Motor Vehicles",
            "subcategory":"Fuel & Gas Station",
            "type":"Retail Goods"
        }
    ],
    "sg:phone":"+1 201 438 8600",
    "sg:postcode":"07073",
    "sg:province":"NJ",
    "wof:name":"Meadowland Truckstop",
    "wof:placetype":"venue"
},
  "geometry": {"coordinates":[-74.0896,40.821602],"type":"Point"}
}