{
  "type": "Feature",
  "properties": {
    "iso:country":"US",
    "sg:address":"301 N High St",
    "sg:city":"Millville",
    "sg:classifiers":[
        {
            "category":"Personal",
            "subcategory":"Barber",
            "type":"Services"
        }
    ],
    "sg:phone":"+1   ",
    "sg:postcode":"08332",
    "sg:province":"NJ",
    "sg:tags":[
        "shop"
    ],
    "wof:name":"B&B Barbershop",
    "wof:placetype":"venue"
},
  "geometry": {"coordinates":[-75.03859,39.399507],"type":"Point"}
}