{
  "type": "Feature",
  "properties": {
    "iso:country":"US",
    "sg:address":"2445 State Rte 34",
    "sg:city":"Manasquan",
    "sg:classifiers":[
        {
            "category":"Food & Beverages",
            "subcategory":"Groceries & Convenience Stores",
            "type":"Retail Goods"
        }
    ],
    "sg:phone":"+1 732 292 9780",
    "sg:postcode":"08736",
    "sg:province":"NJ",
    "sg:tags":[
        "grocer"
    ],
    "sg:website":"www.shoprite.com",
    "wof:name":"Shop Rite Supermarket",
    "wof:placetype":"venue"
},
  "geometry": {"coordinates":[-74.07827899999999,40.120416],"type":"Point"}
}