{
  "type": "Feature",
  "properties": {
    "iso:country":"US",
    "sg:address":"5 Whitman Rd",
    "sg:city":"Morganville",
    "sg:classifiers":[
        {
            "category":"Wholesale",
            "subcategory":"Non-durable Goods",
            "type":"Manufacturing & Wholesale Goods"
        }
    ],
    "sg:phone":"+1 732 972 8788",
    "sg:postcode":"07751",
    "sg:province":"NJ",
    "sg:tags":[
        "advertising",
        "specialty"
    ],
    "sg:website":"www.oceanpromotion.net",
    "wof:name":"An Ocean Promotion Inc",
    "wof:placetype":"venue"
},
  "geometry": {"coordinates":[-74.315591,40.345344],"type":"Point"}
}