{
  "type": "Feature",
  "properties": {
    "iso:country":"US",
    "sg:address":"101 E 9th Ave",
    "sg:city":"Runnemede",
    "sg:classifiers":[
        {
            "category":"Travel",
            "subcategory":"Hotels & Motels",
            "type":"Entertainment"
        }
    ],
    "sg:phone":"+1 856 939 6700",
    "sg:postcode":"08078",
    "sg:province":"NJ",
    "sg:tags":[
        "operation"
    ],
    "wof:name":"Comfort Inn",
    "wof:placetype":"venue"
},
  "geometry": {"coordinates":[-75.069222,39.858101],"type":"Point"}
}