{
  "type": "Feature",
  "properties": {
    "iso:country":"US",
    "sg:address":"48 N Ashby Ave",
    "sg:city":"Livingston",
    "sg:classifiers":[
        {
            "category":"Communications",
            "type":"Services"
        }
    ],
    "sg:phone":"+1 973 422 1437",
    "sg:postcode":"07039",
    "sg:province":"NJ",
    "wof:name":"Murphy Douglas Communications",
    "wof:placetype":"venue"
},
  "geometry": {"coordinates":[-74.32115400000001,40.798663],"type":"Point"}
}