{
  "type": "Feature",
  "properties": {
    "addr:full":"62 E Mill Rd #A3 Long Valley NJ 07853",
    "addr:housenumber":"62",
    "addr:postcode":"07853",
    "addr:street":"E Mill Rd # A3",
    "iso:country":"US",
    "sg:address":"62 E Mill Rd #A3",
    "sg:city":"Long Valley",
    "sg:classifiers":[
        {
            "category":"Home & Garden",
            "subcategory":"Home Furnishings",
            "type":"Retail Goods"
        },
        {
            "category":"Home & Garden",
            "subcategory":"Carpets & Floor Coverings",
            "type":"Retail Goods"
        }
    ],
    "sg:phone":"+1 908 876 3790",
    "sg:postcode":"07853",
    "sg:province":"NJ",
    "sg:tags":[
        "bath",
        "flooring",
        "kitchen"
    ],
    "sg:website":"tilestudiolv.com",
    "wof:name":"The Tile Studio Of Long Valley",
    "wof:placetype":"venue"
},
  "geometry": {"coordinates":[-74.77146,40.784681],"type":"Point"}
}