{
  "type": "Feature",
  "properties": {
    "iso:country":"US",
    "sg:address":"663 Mount Prospect Ave",
    "sg:city":"Newark",
    "sg:classifiers":[
        {
            "category":"Banks & Credit Unions",
            "subcategory":"Bank",
            "type":"Services"
        }
    ],
    "sg:phone":"+1 973 412 1032",
    "sg:postcode":"07104",
    "sg:province":"NJ",
    "sg:tags":[
        "cashing",
        "check"
    ],
    "wof:name":"Express Check Cashing",
    "wof:placetype":"venue"
},
  "geometry": {"coordinates":[-74.166763,40.773711],"type":"Point"}
}