{
  "type": "Feature",
  "properties": {
    "iso:country":"US",
    "sg:address":"35 Hackensack Ave",
    "sg:city":"Kearny",
    "sg:classifiers":[
        {
            "category":"Wholesale",
            "subcategory":"Machinery & Supplies",
            "type":"Manufacturing & Wholesale Goods"
        }
    ],
    "sg:phone":"+1 973 344 2443",
    "sg:postcode":"07032",
    "sg:province":"NJ",
    "sg:tags":[
        "equipment",
        "industrial"
    ],
    "wof:name":"GE Supply",
    "wof:placetype":"venue"
},
  "geometry": {"coordinates":[-74.102572,40.73172],"type":"Point"}
}