{
  "type": "Feature",
  "properties": {
    "addr:full":"422 E 4th Ave North Wildwood NJ 08260",
    "addr:housenumber":"422",
    "addr:postcode":"08260",
    "addr:street":"E 4Th Ave North",
    "iso:country":"US",
    "sg:address":"422 E 4th Ave",
    "sg:city":"North Wildwood",
    "sg:classifiers":[
        {
            "category":"Real Estate",
            "subcategory":"Real Estate Agent",
            "type":"Services"
        },
        {
            "category":"Travel",
            "subcategory":"Hotels & Motels",
            "type":"Entertainment"
        }
    ],
    "sg:phone":"+1 609 729 1907",
    "sg:postcode":"08260",
    "sg:province":"NJ",
    "wof:name":"Oceanaire",
    "wof:placetype":"venue"
},
  "geometry": {"coordinates":[-74.790947,39.002507],"type":"Point"}
}