{
  "type": "Feature",
  "properties": {
    "iso:country":"US",
    "sg:address":"152 Hillside Ave",
    "sg:city":"South River",
    "sg:classifiers":[
        {
            "category":"Home & Garden",
            "subcategory":"Garden Supply",
            "type":"Retail Goods"
        }
    ],
    "sg:phone":"+1 732 432 6476",
    "sg:postcode":"08882",
    "sg:province":"NJ",
    "sg:tags":[
        "sprinkler"
    ],
    "wof:name":"Enterprise Irrigation",
    "wof:placetype":"venue"
},
  "geometry": {"coordinates":[-74.38822999999999,40.441871],"type":"Point"}
}