{
  "type": "Feature",
  "properties": {
    "addr:full":"30 James St Edison NJ 08820",
    "addr:housenumber":"30",
    "addr:postcode":"08820",
    "addr:street":"James St",
    "iso:country":"US",
    "sg:address":"30 James St",
    "sg:city":"Edison",
    "sg:classifiers":[
        {
            "category":"Food & Beverages",
            "subcategory":"Bakery",
            "type":"Retail Goods"
        }
    ],
    "sg:phone":"+1 732 494 9883",
    "sg:postcode":"08820",
    "sg:province":"NJ",
    "sg:tags":[
        "doughnut"
    ],
    "wof:name":"Dunkin' Donuts",
    "wof:placetype":"venue"
},
  "geometry": {"coordinates":[-74.346076,40.556644],"type":"Point"}
}