{
  "type": "Feature",
  "properties": {
    "addr:full":"415 Boulevard Pompton Plains NJ 07444",
    "addr:housenumber":"415",
    "addr:postcode":"07444",
    "addr:street":"Boulevard",
    "iso:country":"US",
    "sg:address":"415 Boulevard",
    "sg:city":"Pompton Plains",
    "sg:classifiers":[
        {
            "category":"Organizations",
            "subcategory":"Religious Organization",
            "type":"Services"
        }
    ],
    "sg:phone":"+1 973 835 4778",
    "sg:postcode":"07444",
    "sg:province":"NJ",
    "wof:name":"Pompton Plains Reformed Bible Church",
    "wof:placetype":"venue"
},
  "geometry": {"coordinates":[-74.3032,40.975899],"type":"Point"}
}