{
  "type": "Feature",
  "properties": {
    "iso:country":"US",
    "sg:address":"707 10th Ave",
    "sg:city":"Belmar",
    "sg:classifiers":[
        {
            "category":"Wholesale",
            "subcategory":"Machinery & Supplies",
            "type":"Manufacturing & Wholesale Goods"
        }
    ],
    "sg:phone":"+1 732 280 2424",
    "sg:postcode":"07719",
    "sg:province":"NJ",
    "sg:tags":[
        "retail",
        "beauty"
    ],
    "wof:name":"Beauty Plus",
    "wof:placetype":"venue"
},
  "geometry": {"coordinates":[-74.025746,40.179247],"type":"Point"}
}