{
  "type": "Feature",
  "properties": {
    "addr:full":"1338 Sussex Tpke Randolph NJ 07869",
    "addr:housenumber":"1338",
    "addr:postcode":"07869",
    "addr:street":"Sussex Tpke",
    "iso:country":"US",
    "sg:address":"1338 Sussex Tpke",
    "sg:city":"Randolph",
    "sg:classifiers":[
        {
            "category":"Recreation",
            "type":"Entertainment"
        }
    ],
    "sg:phone":"+1 973 895 2865",
    "sg:postcode":"07869",
    "sg:province":"NJ",
    "sg:tags":[
        "instruction",
        "swimming"
    ],
    "wof:name":"Physique Swimming Lessons Prgm",
    "wof:placetype":"venue"
},
  "geometry": {"coordinates":[-74.595946,40.836953],"type":"Point"}
}