{
  "type": "Feature",
  "properties": {
    "addr:full":"396 Kennedy St Iselin NJ 08830",
    "addr:housenumber":"396",
    "addr:postcode":"08830",
    "addr:street":"Kennedy St",
    "iso:country":"US",
    "sg:address":"396 Kennedy St",
    "sg:city":"Iselin",
    "sg:classifiers":[
        {
            "category":"Building & Trades",
            "subcategory":"Cleaning & Sanitation",
            "type":"Services"
        }
    ],
    "sg:phone":"+1 732 381 4646",
    "sg:postcode":"08830",
    "sg:province":"NJ",
    "sg:tags":[
        "maintenance"
    ],
    "wof:name":"Professional Maintenance Plus",
    "wof:placetype":"venue"
},
  "geometry": {"coordinates":[-74.32574099999999,40.584203],"type":"Point"}
}