{
  "type": "Feature",
  "properties": {
    "iso:country":"US",
    "sg:address":"400 Gill Ln",
    "sg:city":"Iselin",
    "sg:classifiers":[
        {
            "category":"Health Services",
            "subcategory":"Doctor",
            "type":"Services"
        }
    ],
    "sg:phone":"+1 732 404 1580",
    "sg:postcode":"08830",
    "sg:province":"NJ",
    "wof:name":"Nelson Yvonne",
    "wof:placetype":"venue"
},
  "geometry": {"coordinates":[-74.313042,40.560712],"type":"Point"}
}