{
  "type": "Feature",
  "properties": {
    "addr:full":"377 Franklin Ave Wyckoff NJ 07481",
    "addr:housenumber":"377",
    "addr:postcode":"07481",
    "addr:street":"Franklin Ave",
    "iso:country":"US",
    "sg:address":"377 Franklin Ave",
    "sg:city":"Wyckoff",
    "sg:classifiers":[
        {
            "category":"Professional",
            "subcategory":"Business Services",
            "type":"Services"
        }
    ],
    "sg:phone":"+1 201 891 3622",
    "sg:postcode":"07481",
    "sg:province":"NJ",
    "sg:tags":[
        "interior",
        "consultant",
        "design",
        "decorator"
    ],
    "wof:name":"Interieurs Inc",
    "wof:placetype":"venue"
},
  "geometry": {"coordinates":[-74.17128200000001,41.009487],"type":"Point"}
}