{
  "type": "Feature",
  "properties": {
    "iso:country":"US",
    "sg:address":"1150 River Rd",
    "sg:city":"Edgewater",
    "sg:classifiers":[
        {
            "category":"Real Estate",
            "subcategory":"Real Estate Operator",
            "type":"Services"
        }
    ],
    "sg:phone":"+1 201 886 0671",
    "sg:postcode":"07020",
    "sg:province":"NJ",
    "sg:tags":[
        "condominium"
    ],
    "wof:name":"Riverview On The Park",
    "wof:placetype":"venue"
},
  "geometry": {"coordinates":[-73.972024,40.829428],"type":"Point"}
}