{
  "type": "Feature",
  "properties": {
    "iso:country":"US",
    "sg:address":"6 Sunset Ter",
    "sg:city":"Maplewood",
    "sg:classifiers":[
        {
            "category":"Real Estate",
            "subcategory":"Real Estate Agent",
            "type":"Services"
        }
    ],
    "sg:phone":"+1 973 763 9114",
    "sg:postcode":"07040",
    "sg:province":"NJ",
    "wof:name":"J A Langheld",
    "wof:placetype":"venue"
},
  "geometry": {"coordinates":[-74.27967200000001,40.740972],"type":"Point"}
}