{
  "type": "Feature",
  "properties": {
    "addr:full":"83 Cordier St Irvington NJ 07111",
    "addr:housenumber":"83",
    "addr:postcode":"07111",
    "addr:street":"Cordier St",
    "iso:country":"US",
    "sg:address":"83 Cordier St",
    "sg:city":"Irvington",
    "sg:classifiers":[
        {
            "category":"Manufacturing",
            "subcategory":"Chemicals & Compounds",
            "type":"Manufacturing & Wholesale Goods"
        }
    ],
    "sg:phone":"+1 973 926 0333",
    "sg:postcode":"07111",
    "sg:province":"NJ",
    "sg:tags":[
        "miller",
        "drug"
    ],
    "wof:name":"Amend Drug & Chemical Co",
    "wof:placetype":"venue"
},
  "geometry": {"coordinates":[-74.226153,40.713577],"type":"Point"}
}