{
  "type": "Feature",
  "properties": {
    "addr:full":"26 Menlo Ave Metuchen NJ 08840",
    "addr:housenumber":"26",
    "addr:postcode":"08840",
    "addr:street":"Menlo Ave",
    "iso:country":"US",
    "sg:address":"26 Menlo Ave",
    "sg:city":"Metuchen",
    "sg:classifiers":[
        {
            "category":"Building & Trades",
            "subcategory":"Cleaning & Sanitation",
            "type":"Services"
        }
    ],
    "sg:phone":"+1   ",
    "sg:postcode":"08840",
    "sg:province":"NJ",
    "sg:tags":[
        "maintenance"
    ],
    "wof:name":"Dustpals",
    "wof:placetype":"venue"
},
  "geometry": {"coordinates":[-74.325834,40.549903],"type":"Point"}
}