{
  "type": "Feature",
  "properties": {
    "addr:full":"255 Orange Ave Irvington NJ 07111",
    "addr:housenumber":"255",
    "addr:postcode":"07111",
    "addr:street":"Orange Ave",
    "iso:country":"US",
    "sg:address":"255 Orange Ave",
    "sg:city":"Irvington",
    "sg:classifiers":[
        {
            "category":"Banks & Credit Unions",
            "subcategory":"Investment Brokerage",
            "type":"Services"
        }
    ],
    "sg:phone":"+1 973 373 8633",
    "sg:postcode":"07111",
    "sg:province":"NJ",
    "wof:name":"Wardmaster Investments",
    "wof:placetype":"venue"
},
  "geometry": {"coordinates":[-74.228257,40.735029],"type":"Point"}
}