{
  "type": "Feature",
  "properties": {
    "iso:country":"US",
    "sg:address":"40 Brighton Ave",
    "sg:city":"Passaic",
    "sg:classifiers":[
        {
            "category":"Shopping",
            "subcategory":"Adult",
            "type":"Retail Goods"
        }
    ],
    "sg:phone":"+1 973 779 7455",
    "sg:postcode":"07055",
    "sg:province":"NJ",
    "sg:tags":[
        "entertainment"
    ],
    "sg:website":"www.platinumdollzgc.com/",
    "wof:name":"Platinum Dollz",
    "wof:placetype":"venue"
},
  "geometry": {"coordinates":[-74.143877,40.856875],"type":"Point"}
}