{
  "type": "Feature",
  "properties": {
    "iso:country":"US",
    "sg:address":"100 32nd St",
    "sg:city":"Union City",
    "sg:classifiers":[
        {
            "category":"Retail",
            "subcategory":"Self-service Laundry",
            "type":"Services"
        }
    ],
    "sg:phone":"+1 201 867 5337",
    "sg:postcode":"07087",
    "sg:province":"NJ",
    "sg:tags":[
        "coin"
    ],
    "wof:name":"U C Laundromat",
    "wof:placetype":"venue"
},
  "geometry": {"coordinates":[-74.026893,40.769307],"type":"Point"}
}