{
  "type": "Feature",
  "properties": {
    "addr:full":"56 Wildcat Branch Rd Sicklerville NJ 08081",
    "addr:housenumber":"56",
    "addr:postcode":"08081",
    "addr:street":"Wildcat Branch Rd",
    "iso:country":"US",
    "sg:address":"56 Wildcat Branch Rd",
    "sg:city":"Sicklerville",
    "sg:classifiers":[
        {
            "category":"Banks & Credit Unions",
            "subcategory":"Financial Services",
            "type":"Services"
        }
    ],
    "sg:phone":"+1   ",
    "sg:postcode":"08081",
    "sg:province":"NJ",
    "sg:tags":[
        "investor"
    ],
    "wof:name":"Rcs Property Investment Group",
    "wof:placetype":"venue"
},
  "geometry": {"coordinates":[-74.974475,39.749235],"type":"Point"}
}