{
  "type": "Feature",
  "properties": {
    "iso:country":"US",
    "sg:address":"408 Bellevue Ave",
    "sg:city":"Hammonton",
    "sg:classifiers":[
        {
            "category":"Health Services",
            "subcategory":"Chiropractor",
            "type":"Services"
        }
    ],
    "sg:phone":"+1 609 561 5466",
    "sg:postcode":"08037",
    "sg:province":"NJ",
    "wof:name":"Hammonton Chiropractic Center",
    "wof:placetype":"venue"
},
  "geometry": {"coordinates":[-74.800499,39.638413],"type":"Point"}
}