{
  "type": "Feature",
  "properties": {
    "iso:country":"US",
    "sg:address":"1402 River Rd",
    "sg:city":"Edgewater",
    "sg:classifiers":[
        {
            "category":"Health Services",
            "subcategory":"Doctor",
            "type":"Services"
        }
    ],
    "sg:phone":"+1 201 886 0888",
    "sg:postcode":"07020",
    "sg:province":"NJ",
    "wof:name":"Barry Kantor DDS",
    "wof:placetype":"venue"
},
  "geometry": {"coordinates":[-73.96909100000001,40.842173],"type":"Point"}
}