{
  "type": "Feature",
  "properties": {
    "addr:full":"1406 Autumn Ln Cherry Hill NJ 08003",
    "addr:housenumber":"1406",
    "addr:postcode":"08003",
    "addr:street":"Autumn Ln",
    "iso:country":"US",
    "sg:address":"1406 Autumn Ln",
    "sg:city":"Cherry Hill",
    "sg:classifiers":[
        {
            "category":"Health Services",
            "subcategory":"Doctor",
            "type":"Services"
        }
    ],
    "sg:phone":"+1 856 354 0133",
    "sg:postcode":"08003",
    "sg:province":"NJ",
    "wof:name":"Michael Rulnick DMD",
    "wof:placetype":"venue"
},
  "geometry": {"coordinates":[-74.97094800000001,39.863882],"type":"Point"}
}