{
  "type": "Feature",
  "properties": {
    "iso:country":"US",
    "sg:address":"24 E Logan Rd",
    "sg:city":"Randolph",
    "sg:classifiers":[
        {
            "category":"Health Services",
            "subcategory":"Doctor",
            "type":"Services"
        }
    ],
    "sg:phone":"+1 973 927 1818",
    "sg:postcode":"07869",
    "sg:province":"NJ",
    "sg:tags":[
        "physician",
        "surgeon"
    ],
    "wof:name":"Gina E Rayfield MD",
    "wof:placetype":"venue"
},
  "geometry": {"coordinates":[-74.61507400000001,40.838659],"type":"Point"}
}