{
  "type": "Feature",
  "properties": {
    "iso:country":"US",
    "sg:address":"100 N Wood Ave",
    "sg:city":"Linden",
    "sg:classifiers":[
        {
            "category":"Building & Trades",
            "subcategory":"Construction",
            "type":"Services"
        }
    ],
    "sg:phone":"+1 908 925 6555",
    "sg:postcode":"07036",
    "sg:province":"NJ",
    "sg:tags":[
        "general",
        "contractor"
    ],
    "wof:name":"EMR Contracting",
    "wof:placetype":"venue"
},
  "geometry": {"coordinates":[-74.253551,40.631234],"type":"Point"}
}