{
  "type": "Feature",
  "properties": {
    "iso:country":"US",
    "sg:address":"25 Meadow Dr",
    "sg:city":"Totowa",
    "sg:classifiers":[
        {
            "category":"Wholesale",
            "subcategory":"Furniture",
            "type":"Manufacturing & Wholesale Goods"
        }
    ],
    "sg:phone":"+1 973 595 6241",
    "sg:postcode":"07512",
    "sg:province":"NJ",
    "sg:tags":[
        "retail"
    ],
    "wof:name":"Bob Kabana Associate",
    "wof:placetype":"venue"
},
  "geometry": {"coordinates":[-74.22164100000001,40.90149],"type":"Point"}
}