{
  "type": "Feature",
  "properties": {
    "iso:country":"US",
    "sg:address":"229 Harrison Ave",
    "sg:city":"Garfield",
    "sg:classifiers":[
        {
            "category":"Deli",
            "type":"Food & Drink"
        },
        {
            "category":"Food & Beverages",
            "subcategory":"Bakery",
            "type":"Retail Goods"
        }
    ],
    "sg:phone":"+1 973 246 1543",
    "sg:postcode":"07026",
    "sg:province":"NJ",
    "sg:tags":[
        "sandwich"
    ],
    "wof:name":"Poblanos Deil",
    "wof:placetype":"venue"
},
  "geometry": {"coordinates":[-74.097987,40.874006],"type":"Point"}
}