{
  "type": "Feature",
  "properties": {
    "addr:full":"1146 Raritan Rd Clark NJ 07066",
    "addr:housenumber":"1146",
    "addr:postcode":"07066",
    "addr:street":"Raritan Rd",
    "iso:country":"US",
    "sg:address":"1146 Raritan Rd",
    "sg:city":"Clark",
    "sg:classifiers":[
        {
            "category":"Real Estate",
            "subcategory":"Real Estate Agent",
            "type":"Services"
        }
    ],
    "sg:phone":"+1   ",
    "sg:postcode":"07066",
    "sg:province":"NJ",
    "wof:name":"All Towne Realty Inc",
    "wof:placetype":"venue"
},
  "geometry": {"coordinates":[-74.312123,40.629489],"type":"Point"}
}