{
  "type": "Feature",
  "properties": {
    "addr:full":"131 Hancock Ave Jersey City NJ 07307",
    "addr:housenumber":"131",
    "addr:postcode":"07307",
    "addr:street":"Hancock Ave",
    "iso:country":"US",
    "sg:address":"131 Hancock Ave",
    "sg:city":"Jersey City",
    "sg:classifiers":[
        {
            "category":"Cinema",
            "subcategory":"Movie Rental",
            "type":"Entertainment"
        }
    ],
    "sg:phone":"+1 201 714 4251",
    "sg:postcode":"07307",
    "sg:province":"NJ",
    "sg:tags":[
        "video",
        "tape"
    ],
    "wof:name":"Pro Digital Video Corp",
    "wof:placetype":"venue"
},
  "geometry": {"coordinates":[-74.045491,40.748552],"type":"Point"}
}