{
  "type": "Feature",
  "properties": {
    "addr:full":"9 Dogwood Ln Skillman NJ 08558",
    "addr:housenumber":"9",
    "addr:postcode":"08558",
    "addr:street":"Dogwood Ln",
    "iso:country":"US",
    "sg:address":"9 Dogwood Ln",
    "sg:city":"Skillman",
    "sg:classifiers":[
        {
            "category":"Professional",
            "subcategory":"Lawyer & Legal Services",
            "type":"Services"
        }
    ],
    "sg:phone":"+1 908 359 7178",
    "sg:postcode":"08558",
    "sg:province":"NJ",
    "wof:name":"Perkins Eric Attorney At Law",
    "wof:placetype":"venue"
},
  "geometry": {"coordinates":[-74.715923,40.438346],"type":"Point"}
}