{
  "type": "Feature",
  "properties": {
    "addr:full":"27 Mountain Blvd Warren NJ 07059",
    "addr:housenumber":"27",
    "addr:postcode":"07059",
    "addr:street":"Mountain Blvd",
    "iso:country":"US",
    "sg:address":"27 Mountain Blvd",
    "sg:city":"Warren",
    "sg:classifiers":[
        {
            "category":"Social Services",
            "type":"Services"
        }
    ],
    "sg:phone":"+1 908 226 0727",
    "sg:postcode":"07059",
    "sg:province":"NJ",
    "sg:tags":[
        "organization",
        "welfare"
    ],
    "wof:name":"Jewish Family Svc Agency",
    "wof:placetype":"venue"
},
  "geometry": {"coordinates":[-74.485512,40.620747],"type":"Point"}
}