{
  "type": "Feature",
  "properties": {
    "addr:full":"1325 State Rte 77 Seabrook NJ 08302",
    "addr:housenumber":"1325",
    "addr:postcode":"08302",
    "addr:street":"State Rte 77",
    "iso:country":"US",
    "sg:address":"1325 State Rte 77",
    "sg:city":"Seabrook",
    "sg:classifiers":[
        {
            "category":"Government",
            "subcategory":"Office",
            "type":"Public Place"
        }
    ],
    "sg:phone":"+1 856 455 9591",
    "sg:postcode":"08302",
    "sg:province":"NJ",
    "sg:tags":[
        "village"
    ],
    "wof:name":"Upper Deerfield Housing Dept",
    "wof:placetype":"venue"
},
  "geometry": {"coordinates":[-75.21416600000001,39.495034],"type":"Point"}
}