{
  "type": "Feature",
  "properties": {
    "addr:full":"295 Swedesboro Ave Gibbstown NJ 08027",
    "addr:housenumber":"295",
    "addr:postcode":"08027",
    "addr:street":"Swedesboro Ave",
    "iso:country":"US",
    "sg:address":"295 Swedesboro Ave",
    "sg:city":"Gibbstown",
    "sg:classifiers":[
        {
            "category":"Restaurant",
            "type":"Food & Drink"
        }
    ],
    "sg:phone":"+1   ",
    "sg:postcode":"08027",
    "sg:province":"NJ",
    "sg:tags":[
        "grocery",
        "eating"
    ],
    "wof:name":"Mr PS Deli",
    "wof:placetype":"venue"
},
  "geometry": {"coordinates":[-75.251502,39.818592],"type":"Point"}
}