{
  "type": "Feature",
  "properties": {
    "iso:country":"US",
    "sg:address":"428 Manchester Ave",
    "sg:city":"Haledon",
    "sg:classifiers":[
        {
            "category":"Building & Trades",
            "subcategory":"Construction",
            "type":"Services"
        }
    ],
    "sg:phone":"+1 973 423 5338",
    "sg:postcode":"07508",
    "sg:province":"NJ",
    "sg:tags":[
        "excavation",
        "contractor"
    ],
    "wof:name":"L & L Construction",
    "wof:placetype":"venue"
},
  "geometry": {"coordinates":[-74.17335199999999,40.967794],"type":"Point"}
}