{
  "type": "Feature",
  "properties": {
    "iso:country":"US",
    "sg:address":"33 Snyder St",
    "sg:city":"Toms River",
    "sg:classifiers":[
        {
            "category":"Professional",
            "subcategory":"Management & Consulting",
            "type":"Services"
        }
    ],
    "sg:phone":"+1 732 349 2208",
    "sg:postcode":"08753",
    "sg:province":"NJ",
    "sg:tags":[
        "consultant",
        "business"
    ],
    "wof:name":"Preferred Consulting Group",
    "wof:placetype":"venue"
},
  "geometry": {"coordinates":[-74.199608,39.954251],"type":"Point"}
}