{
  "type": "Feature",
  "properties": {
    "iso:country":"US",
    "sg:address":"370 Demarest Ave",
    "sg:city":"Closter",
    "sg:classifiers":[
        {
            "category":"Organizations",
            "subcategory":"Religious Organization",
            "type":"Services"
        }
    ],
    "sg:phone":"+1   ",
    "sg:postcode":"07624",
    "sg:province":"NJ",
    "wof:name":"Grace House",
    "wof:placetype":"venue"
},
  "geometry": {"coordinates":[-73.96267400000001,40.969958],"type":"Point"}
}