{
  "type": "Feature",
  "properties": {
    "iso:country":"US",
    "sg:address":"82 Valley View Ave",
    "sg:city":"Summit",
    "sg:classifiers":[
        {
            "category":"Professional",
            "subcategory":"Research",
            "type":"Services"
        }
    ],
    "sg:phone":"+1 908 608 1170",
    "sg:postcode":"07901",
    "sg:province":"NJ",
    "sg:tags":[
        "nonphysical",
        "commercial"
    ],
    "wof:name":"Summit Marketing Research Team",
    "wof:placetype":"venue"
},
  "geometry": {"coordinates":[-74.379766,40.709145],"type":"Point"}
}