{
  "type": "Feature",
  "properties": {
    "addr:full":"6116 Bergenline Ave West New York NJ 07093",
    "addr:housenumber":"6116",
    "addr:postcode":"07093",
    "addr:street":"Bergenline Ave West",
    "iso:country":"US",
    "sg:address":"6116 Bergenline Ave",
    "sg:city":"West New York",
    "sg:classifiers":[
        {
            "category":"Shopping",
            "subcategory":"Mobile Phones",
            "type":"Retail Goods"
        }
    ],
    "sg:phone":"+1 201 868 7432",
    "sg:postcode":"07093",
    "sg:province":"NJ",
    "sg:website":"www.radioshack.com",
    "wof:name":"Radioshack",
    "wof:placetype":"venue"
},
  "geometry": {"coordinates":[-74.015297,40.7901],"type":"Point"}
}