{
  "type": "Feature",
  "properties": {
    "addr:full":"517 5th Ave Belmar NJ 07719",
    "addr:housenumber":"517",
    "addr:postcode":"07719",
    "addr:street":"5Th Ave",
    "iso:country":"US",
    "sg:address":"517 5th Ave",
    "sg:city":"Belmar",
    "sg:classifiers":[
        {
            "category":"Professional",
            "subcategory":"Lawyer & Legal Services",
            "type":"Services"
        }
    ],
    "sg:phone":"+1 732 681 1500",
    "sg:postcode":"07719",
    "sg:province":"NJ",
    "wof:name":"Joseph Hillman Jr",
    "wof:placetype":"venue"
},
  "geometry": {"coordinates":[-74.02063,40.183649],"type":"Point"}
}