{
  "type": "Feature",
  "properties": {
    "addr:full":"946 Broad St Newark NJ 07102",
    "addr:housenumber":"946",
    "addr:postcode":"07102",
    "addr:street":"Broad St",
    "iso:country":"US",
    "sg:address":"946 Broad St",
    "sg:city":"Newark",
    "sg:classifiers":[
        {
            "category":"Professional",
            "subcategory":"Lawyer & Legal Services",
            "type":"Services"
        }
    ],
    "sg:phone":"+1 973 596 1079",
    "sg:postcode":"07102",
    "sg:province":"NJ",
    "sg:tags":[
        "naturalization",
        "immigration"
    ],
    "wof:name":"ABC Service Co",
    "wof:placetype":"venue"
},
  "geometry": {"coordinates":[-74.17468599999999,40.731058],"type":"Point"}
}