{
  "type": "Feature",
  "properties": {
    "iso:country":"US",
    "sg:address":"615 Sherwood Pkwy",
    "sg:city":"Mountainside",
    "sg:classifiers":[
        {
            "category":"Professional",
            "subcategory":"Lawyer & Legal Services",
            "type":"Services"
        }
    ],
    "sg:phone":"+1   ",
    "sg:postcode":"07092",
    "sg:province":"NJ",
    "wof:name":"Michael Margello Attorney",
    "wof:placetype":"venue"
},
  "geometry": {"coordinates":[-74.348919,40.666287],"type":"Point"}
}