{
  "type": "Feature",
  "properties": {
    "iso:country":"US",
    "sg:address":"250 N Black Horse Pike",
    "sg:city":"Blackwood",
    "sg:classifiers":[
        {
            "category":"Real Estate",
            "subcategory":"Real Estate Agent",
            "type":"Services"
        }
    ],
    "sg:phone":"+1   ",
    "sg:postcode":"08012",
    "sg:province":"NJ",
    "wof:name":"Jamatt Glass Bar House",
    "wof:placetype":"venue"
},
  "geometry": {"coordinates":[-75.068057,39.804272],"type":"Point"}
}