{
  "type": "Feature",
  "properties": {
    "addr:full":"169 Conestoga Trl Sparta NJ 07871",
    "addr:housenumber":"169",
    "addr:postcode":"07871",
    "addr:street":"Conestoga Trl",
    "iso:country":"US",
    "sg:address":"169 Conestoga Trl",
    "sg:city":"Sparta",
    "sg:classifiers":[
        {
            "category":"Professional",
            "subcategory":"Management & Consulting",
            "type":"Services"
        }
    ],
    "sg:phone":"+1   ",
    "sg:postcode":"07871",
    "sg:province":"NJ",
    "sg:tags":[
        "business"
    ],
    "wof:name":"TSS",
    "wof:placetype":"venue"
},
  "geometry": {"coordinates":[-74.62780100000001,41.010686],"type":"Point"}
}