{
  "type": "Feature",
  "properties": {
    "addr:full":"61 Passaic St Garfield NJ 07026",
    "addr:housenumber":"61",
    "addr:postcode":"07026",
    "addr:street":"Passaic St",
    "iso:country":"US",
    "sg:address":"61 Passaic St",
    "sg:city":"Garfield",
    "sg:classifiers":[
        {
            "category":"Building & Trades",
            "subcategory":"Locksmith",
            "type":"Services"
        }
    ],
    "sg:phone":"+1 888 228 0812",
    "sg:postcode":"07026",
    "sg:province":"NJ",
    "sg:tags":[
        "key"
    ],
    "wof:name":"7 Day 24 Hour Emergency Locksmith",
    "wof:placetype":"venue"
},
  "geometry": {"coordinates":[-74.10699099999999,40.866073],"type":"Point"}
}