{
  "type": "Feature",
  "properties": {
    "addr:full":"1214 Kerwin St Piscataway NJ 08854",
    "addr:housenumber":"1214",
    "addr:postcode":"08854",
    "addr:street":"Kerwin St",
    "iso:country":"US",
    "sg:address":"1214 Kerwin St",
    "sg:city":"Piscataway",
    "sg:classifiers":[
        {
            "category":"Professional",
            "subcategory":"Business Services",
            "type":"Services"
        }
    ],
    "sg:phone":"+1   ",
    "sg:postcode":"08854",
    "sg:province":"NJ",
    "sg:tags":[
        "product",
        "retailer"
    ],
    "wof:name":"Lots of Stuff",
    "wof:placetype":"venue"
},
  "geometry": {"coordinates":[-74.447123,40.562166],"type":"Point"}
}