{
  "type": "Feature",
  "properties": {
    "addr:full":"19 E Main St Little Falls NJ 07424",
    "addr:housenumber":"19",
    "addr:postcode":"07424",
    "addr:street":"E Main St",
    "iso:country":"US",
    "sg:address":"19 E Main St",
    "sg:city":"Little Falls",
    "sg:classifiers":[
        {
            "category":"Building & Trades",
            "subcategory":"Locksmith",
            "type":"Services"
        }
    ],
    "sg:phone":"+1 201 798 5914",
    "sg:postcode":"07424",
    "sg:province":"NJ",
    "sg:tags":[
        "key"
    ],
    "wof:name":"Miles Square Locksmith & Hardware",
    "wof:placetype":"venue"
},
  "geometry": {"coordinates":[-74.206497,40.883801],"type":"Point"}
}