{
  "type": "Feature",
  "properties": {
    "addr:full":"6 Heather Dr Sicklerville NJ 08081",
    "addr:housenumber":"6",
    "addr:postcode":"08081",
    "addr:street":"Heather Dr",
    "iso:country":"US",
    "sg:address":"6 Heather Dr",
    "sg:city":"Sicklerville",
    "sg:classifiers":[
        {
            "category":"Building & Trades",
            "subcategory":"Plumbing",
            "type":"Services"
        }
    ],
    "sg:phone":"+1 856 667 3153",
    "sg:postcode":"08081",
    "sg:province":"NJ",
    "sg:tags":[
        "contractor"
    ],
    "wof:name":"Gaudian Fire Protection Inc",
    "wof:placetype":"venue"
},
  "geometry": {"coordinates":[-74.98352800000001,39.7164],"type":"Point"}
}