{
  "type": "Feature",
  "properties": {
    "addr:full":"7 Danforth Dr Voorhees NJ 08043",
    "addr:housenumber":"7",
    "addr:postcode":"08043",
    "addr:street":"Danforth Dr",
    "iso:country":"US",
    "sg:address":"7 Danforth Dr",
    "sg:city":"Voorhees",
    "sg:classifiers":[
        {
            "category":"Professional",
            "subcategory":"Business Services",
            "type":"Services"
        }
    ],
    "sg:phone":"+1   ",
    "sg:postcode":"08043",
    "sg:province":"NJ",
    "wof:name":"Perkin Design Inc",
    "wof:placetype":"venue"
},
  "geometry": {"coordinates":[-74.920276,39.816725],"type":"Point"}
}