{
  "type": "Feature",
  "properties": {
    "iso:country":"US",
    "sg:address":"177 Main St",
    "sg:city":"Fort Lee",
    "sg:classifiers":[
        {
            "category":"Recreation",
            "type":"Entertainment"
        }
    ],
    "sg:phone":"+1 516 681 1157",
    "sg:postcode":"07024",
    "sg:province":"NJ",
    "sg:tags":[
        "ticket",
        "sales",
        "for",
        "concert"
    ],
    "wof:name":"A1entertainmenteventscom",
    "wof:placetype":"venue"
},
  "geometry": {"coordinates":[-73.969476,40.851156],"type":"Point"}
}