{
  "type": "Feature",
  "properties": {
    "addr:full":"76 Reaville Ave Flemington NJ 08822",
    "addr:housenumber":"76",
    "addr:postcode":"08822",
    "addr:street":"Reaville Ave",
    "iso:country":"US",
    "sg:address":"76 Reaville Ave",
    "sg:city":"Flemington",
    "sg:classifiers":[
        {
            "category":"Shopping",
            "subcategory":"Pharmacy",
            "type":"Retail Goods"
        }
    ],
    "sg:phone":"+1   ",
    "sg:postcode":"08822",
    "sg:province":"NJ",
    "sg:tags":[
        "drug",
        "store"
    ],
    "wof:name":"Eckerd",
    "wof:placetype":"venue"
},
  "geometry": {"coordinates":[-74.850706,40.497988],"type":"Point"}
}