{
  "type": "Feature",
  "properties": {
    "addr:full":"1831 Old Cuthbert Rd Cherry Hill NJ 08034",
    "addr:housenumber":"1831",
    "addr:postcode":"08034",
    "addr:street":"Old Cuthbert Rd",
    "iso:country":"US",
    "sg:address":"1831 Old Cuthbert Rd",
    "sg:city":"Cherry Hill",
    "sg:classifiers":[
        {
            "category":"Freight",
            "type":"Transportation"
        }
    ],
    "sg:phone":"+1 856 428 4355",
    "sg:postcode":"08034",
    "sg:province":"NJ",
    "sg:tags":[
        "commercial",
        "storage"
    ],
    "wof:name":"Storage USA",
    "wof:placetype":"venue"
},
  "geometry": {"coordinates":[-74.980442,39.907855],"type":"Point"}
}