{
  "type": "Feature",
  "properties": {
    "iso:country":"US",
    "sg:address":"700 Monmouth St",
    "sg:city":"Gloucester City",
    "sg:classifiers":[
        {
            "category":"Food & Beverages",
            "subcategory":"Bakery",
            "type":"Retail Goods"
        }
    ],
    "sg:phone":"+1 856 742 0770",
    "sg:postcode":"08030",
    "sg:province":"NJ",
    "sg:tags":[
        "baker"
    ],
    "wof:name":"Gloucester City Train Stop",
    "wof:placetype":"venue"
},
  "geometry": {"coordinates":[-75.11912599999999,39.895742],"type":"Point"}
}