{
  "type": "Feature",
  "properties": {
    "iso:country":"US",
    "sg:address":"754 Village Dr",
    "sg:city":"Edison",
    "sg:classifiers":[
        {
            "category":"Professional",
            "subcategory":"Management & Consulting",
            "type":"Services"
        }
    ],
    "sg:phone":"+1   ",
    "sg:postcode":"08817",
    "sg:province":"NJ",
    "sg:tags":[
        "business"
    ],
    "wof:name":"Sachi Consulting Inc",
    "wof:placetype":"venue"
},
  "geometry": {"coordinates":[-74.409378,40.524059],"type":"Point"}
}