{
  "type": "Feature",
  "properties": {
    "addr:full":"1203 Paterson Plank Rd Secaucus NJ 07094",
    "addr:housenumber":"1203",
    "addr:postcode":"07094",
    "addr:street":"Paterson Plank Rd",
    "iso:country":"US",
    "sg:address":"1203 Paterson Plank Rd",
    "sg:city":"Secaucus",
    "sg:classifiers":[
        {
            "category":"Government",
            "subcategory":"Office",
            "type":"Public Place"
        }
    ],
    "sg:phone":"+1 201 330 2030",
    "sg:postcode":"07094",
    "sg:province":"NJ",
    "sg:tags":[
        "city",
        "taxation"
    ],
    "wof:name":"Secaucus Tax Assessor Office",
    "wof:placetype":"venue"
},
  "geometry": {"coordinates":[-74.05520799999999,40.788282],"type":"Point"}
}