{
  "type": "Feature",
  "properties": {
    "iso:country":"US",
    "sg:address":"1300 Clements Bridge Rd",
    "sg:city":"Deptford",
    "sg:classifiers":[
        {
            "category":"Autos & Motor Vehicles",
            "subcategory":"Motorcycle Sales",
            "type":"Retail Goods"
        }
    ],
    "sg:phone":"+1 856 848 8500",
    "sg:postcode":"08096",
    "sg:province":"NJ",
    "sg:tags":[
        "water",
        "lawn",
        "scooter",
        "mower"
    ],
    "sg:website":"www.dhy.com",
    "wof:name":"Deptford Honda Yamaha",
    "wof:placetype":"venue"
},
  "geometry": {"coordinates":[-75.110688,39.829245],"type":"Point"}
}