{
  "type": "Feature",
  "properties": {
    "addr:full":"3475 US Hwy 9 Freehold NJ 07728",
    "addr:housenumber":"3475",
    "addr:postcode":"07728",
    "addr:street":"Us Hwy 9",
    "iso:country":"US",
    "sg:address":"3475 US Hwy 9",
    "sg:city":"Freehold",
    "sg:classifiers":[
        {
            "category":"Personal",
            "subcategory":"Beauty Salon",
            "type":"Services"
        }
    ],
    "sg:phone":"+1 732 866 0801",
    "sg:postcode":"07728",
    "sg:province":"NJ",
    "sg:tags":[
        "shop"
    ],
    "wof:name":"Beauty Secret Corp",
    "wof:placetype":"venue"
},
  "geometry": {"coordinates":[-74.272582,40.231769],"type":"Point"}
}