{
  "type": "Feature",
  "properties": {
    "iso:country":"US",
    "sg:address":"3120 N West Blvd",
    "sg:city":"Vineland",
    "sg:classifiers":[
        {
            "category":"Retail",
            "subcategory":"Car Wash",
            "type":"Services"
        }
    ],
    "sg:phone":"+1 856 794 9071",
    "sg:postcode":"08360",
    "sg:province":"NJ",
    "sg:tags":[
        "automobile",
        "detail",
        "clean"
    ],
    "wof:name":"D J's Auto Detailing",
    "wof:placetype":"venue"
},
  "geometry": {"coordinates":[-75.023104,39.526393],"type":"Point"}
}