{
  "type": "Feature",
  "properties": {
    "iso:country":"US",
    "sg:address":"218 Woodlawn Ave",
    "sg:city":"Merchantville",
    "sg:classifiers":[
        {
            "category":"Building & Trades",
            "subcategory":"Construction",
            "type":"Services"
        }
    ],
    "sg:phone":"+1 856 663 0153",
    "sg:postcode":"08109",
    "sg:province":"NJ",
    "sg:tags":[
        "concrete",
        "contractor"
    ],
    "wof:name":"Villari Bros Concrete Co",
    "wof:placetype":"venue"
},
  "geometry": {"coordinates":[-75.045727,39.947535],"type":"Point"}
}