{
  "type": "Feature",
  "properties": {
    "addr:full":"2574 Ridge Ave Egg Harbor Township NJ 08234",
    "addr:housenumber":"2574",
    "addr:postcode":"08234",
    "addr:street":"Ridge Ave",
    "iso:country":"US",
    "sg:address":"2574 Ridge Ave",
    "sg:city":"Egg Harbor Township",
    "sg:classifiers":[
        {
            "category":"Retail",
            "subcategory":"Auto Repair",
            "type":"Services"
        }
    ],
    "sg:phone":"+1   ",
    "sg:postcode":"08234",
    "sg:province":"NJ",
    "sg:tags":[
        "automotive"
    ],
    "wof:name":"A1 Affordable Towing",
    "wof:placetype":"venue"
},
  "geometry": {"coordinates":[-74.58627,39.426908],"type":"Point"}
}