{
  "type": "Feature",
  "properties": {
    "iso:country":"US",
    "sg:address":"146 Linwood Ave",
    "sg:city":"Emerson",
    "sg:classifiers":[
        {
            "category":"Government",
            "subcategory":"Office",
            "type":"Public Place"
        }
    ],
    "sg:phone":"+1 201 262 7169",
    "sg:postcode":"07630",
    "sg:province":"NJ",
    "sg:tags":[
        "village"
    ],
    "wof:name":"Emerson Building Dept",
    "wof:placetype":"venue"
},
  "geometry": {"coordinates":[-74.024018,40.974764],"type":"Point"}
}