{
  "type": "Feature",
  "properties": {
    "addr:full":"427 S Plainfield Ave South Plainfield NJ 07080",
    "addr:housenumber":"427",
    "addr:postcode":"07080",
    "addr:street":"S Plainfield Ave",
    "iso:country":"US",
    "sg:address":"427 S Plainfield Ave",
    "sg:city":"South Plainfield",
    "sg:classifiers":[
        {
            "category":"Building & Trades",
            "subcategory":"Landscaping Services",
            "type":"Services"
        }
    ],
    "sg:phone":"+1 908 769 7137",
    "sg:postcode":"07080",
    "sg:province":"NJ",
    "wof:name":"Sunset Landscape",
    "wof:placetype":"venue"
},
  "geometry": {"coordinates":[-74.39798500000001,40.585479],"type":"Point"}
}