{
  "type": "Feature",
  "properties": {
    "iso:country":"US",
    "sg:address":"132 Carter Rd",
    "sg:city":"Princeton",
    "sg:classifiers":[
        {
            "category":"Coffee & Tea",
            "type":"Food & Drink"
        },
        {
            "category":"Restaurant",
            "type":"Food & Drink"
        }
    ],
    "sg:phone":"+1 609 921 3710",
    "sg:postcode":"08540",
    "sg:province":"NJ",
    "sg:tags":[
        "espresso"
    ],
    "wof:name":"Cutting Edge Lawn & Landscaping",
    "wof:placetype":"venue"
},
  "geometry": {"coordinates":[-74.716684,40.327379],"type":"Point"}
}