{
  "type": "Feature",
  "properties": {
    "addr:full":"331 Jackson Rd Atco NJ 08004",
    "addr:housenumber":"331",
    "addr:postcode":"08004",
    "addr:street":"Jackson Rd",
    "iso:country":"US",
    "sg:address":"331 Jackson Rd",
    "sg:city":"Atco",
    "sg:classifiers":[
        {
            "category":"Professional",
            "subcategory":"Lawyer & Legal Services",
            "type":"Services"
        }
    ],
    "sg:phone":"+1 856 767 7232",
    "sg:postcode":"08004",
    "sg:province":"NJ",
    "sg:tags":[
        "divorce",
        "law",
        "family"
    ],
    "wof:name":"Wilson Howard S Attorney-At Law",
    "wof:placetype":"venue"
},
  "geometry": {"coordinates":[-74.88220200000001,39.7798],"type":"Point"}
}