{
  "type": "Feature",
  "properties": {
    "iso:country":"US",
    "sg:address":"71 Washington Ave",
    "sg:city":"Cliffside Park",
    "sg:classifiers":[
        {
            "category":"Building & Trades",
            "subcategory":"Cleaning & Sanitation",
            "type":"Services"
        }
    ],
    "sg:phone":"+1 201 945 2552",
    "sg:postcode":"07010",
    "sg:province":"NJ",
    "sg:tags":[
        "janitor"
    ],
    "wof:name":"J C Cleaning Inc",
    "wof:placetype":"venue"
},
  "geometry": {"coordinates":[-73.983541,40.823065],"type":"Point"}
}