{
  "type": "Feature",
  "properties": {
    "addr:full":"112 Hayward Pl Wallington NJ 07057",
    "addr:housenumber":"112",
    "addr:postcode":"07057",
    "addr:street":"Hayward Pl",
    "iso:country":"US",
    "sg:address":"112 Hayward Pl",
    "sg:city":"Wallington",
    "sg:classifiers":[
        {
            "category":"Food & Beverages",
            "subcategory":"Groceries & Convenience Stores",
            "type":"Retail Goods"
        }
    ],
    "sg:phone":"+1   ",
    "sg:postcode":"07057",
    "sg:province":"NJ",
    "wof:name":"Labibs Food Lion",
    "wof:placetype":"venue"
},
  "geometry": {"coordinates":[-74.116,40.85588],"type":"Point"}
}