{
  "type": "Feature",
  "properties": {
    "addr:full":"20 Old Milford Ln West Milford NJ 07480",
    "addr:housenumber":"20",
    "addr:postcode":"07480",
    "addr:street":"Old Milford Ln",
    "iso:country":"US",
    "sg:address":"20 Old Milford Ln",
    "sg:city":"West Milford",
    "sg:classifiers":[
        {
            "category":"Professional",
            "subcategory":"Employment Agencies",
            "type":"Services"
        }
    ],
    "sg:phone":"+1   ",
    "sg:postcode":"07480",
    "sg:province":"NJ",
    "sg:tags":[
        "help",
        "supply"
    ],
    "wof:name":"JAS Contracting LLC",
    "wof:placetype":"venue"
},
  "geometry": {"coordinates":[-74.40546000000001,41.102192],"type":"Point"}
}