{
  "type": "Feature",
  "properties": {
    "addr:full":"347 S Broad St Woodbury NJ 08096",
    "addr:housenumber":"347",
    "addr:postcode":"08096",
    "addr:street":"S Broad St",
    "iso:country":"US",
    "sg:address":"347 S Broad St",
    "sg:city":"Woodbury",
    "sg:classifiers":[
        {
            "category":"Professional",
            "subcategory":"Employment Agencies",
            "type":"Services"
        }
    ],
    "sg:phone":"+1   ",
    "sg:postcode":"08096",
    "sg:province":"NJ",
    "sg:tags":[
        "temporary",
        "labor"
    ],
    "wof:name":"Labor Ready 2817",
    "wof:placetype":"venue"
},
  "geometry": {"coordinates":[-75.156201,39.834261],"type":"Point"}
}