{
  "type": "Feature",
  "properties": {
    "addr:full":"35 Church St Lambertville NJ 08530",
    "addr:housenumber":"35",
    "addr:postcode":"08530",
    "addr:street":"Church St",
    "iso:country":"US",
    "sg:address":"35 Church St",
    "sg:city":"Lambertville",
    "sg:classifiers":[
        {
            "category":"Building & Trades",
            "subcategory":"Construction",
            "type":"Services"
        }
    ],
    "sg:phone":"+1 609 397 1685",
    "sg:postcode":"08530",
    "sg:province":"NJ",
    "sg:tags":[
        "house"
    ],
    "wof:name":"Hixson Construction Company",
    "wof:placetype":"venue"
},
  "geometry": {"coordinates":[-74.943549,40.366993],"type":"Point"}
}