{
  "type": "Feature",
  "properties": {
    "addr:full":"1259 Washington Ave Asbury Park NJ 07712",
    "addr:housenumber":"1259",
    "addr:postcode":"07712",
    "addr:street":"Washington Ave Asbury",
    "iso:country":"US",
    "sg:address":"1259 Washington Ave",
    "sg:city":"Asbury Park",
    "sg:classifiers":[
        {
            "category":"Professional",
            "subcategory":"Business Services",
            "type":"Services"
        }
    ],
    "sg:phone":"+1   ",
    "sg:postcode":"07712",
    "sg:province":"NJ",
    "sg:tags":[
        "educational",
        "social",
        "activity"
    ],
    "wof:name":"Project Progress",
    "wof:placetype":"venue"
},
  "geometry": {"coordinates":[-74.019836,40.219965],"type":"Point"}
}