{
  "type": "Feature",
  "properties": {
    "iso:country":"US",
    "sg:address":"101 William Penn Ave",
    "sg:city":"Pennsville",
    "sg:classifiers":[
        {
            "category":"Shopping",
            "subcategory":"Used Merchandise",
            "type":"Retail Goods"
        }
    ],
    "sg:phone":"+1   ",
    "sg:postcode":"08070",
    "sg:province":"NJ",
    "wof:name":"Holly Tree Antiques",
    "wof:placetype":"venue"
},
  "geometry": {"coordinates":[-75.509528,39.658316],"type":"Point"}
}