{
  "type": "Feature",
  "properties": {
    "addr:full":"751 Co Rd 579 Flemington NJ 08822",
    "addr:housenumber":"751",
    "addr:postcode":"08822",
    "addr:street":"Co Rd 579",
    "iso:country":"US",
    "sg:address":"751 Co Rd 579",
    "sg:city":"Flemington",
    "sg:classifiers":[
        {
            "category":"Building & Trades",
            "subcategory":"Construction",
            "type":"Services"
        }
    ],
    "sg:phone":"+1 908 782 2284",
    "sg:postcode":"08822",
    "sg:province":"NJ",
    "sg:tags":[
        "house"
    ],
    "wof:name":"Markert Builders",
    "wof:placetype":"venue"
},
  "geometry": {"coordinates":[-74.92234500000001,40.485895],"type":"Point"}
}