{
  "type": "Feature",
  "properties": {
    "iso:country":"US",
    "sg:address":"310 White Horse Pike",
    "sg:city":"Lawnside",
    "sg:classifiers":[
        {
            "category":"Restaurant",
            "type":"Food & Drink"
        }
    ],
    "sg:phone":"+1   ",
    "sg:postcode":"08045",
    "sg:province":"NJ",
    "sg:tags":[
        "eating"
    ],
    "wof:name":"Wendys",
    "wof:placetype":"venue"
},
  "geometry": {"coordinates":[-75.035528,39.86326],"type":"Point"}
}