{
  "type": "Feature",
  "properties": {
    "iso:country":"US",
    "sg:address":"21 Edison Ave",
    "sg:city":"Ogdensburg",
    "sg:classifiers":[
        {
            "category":"Home & Garden",
            "subcategory":"Carpets & Floor Coverings",
            "type":"Retail Goods"
        }
    ],
    "sg:phone":"+1   ",
    "sg:postcode":"07439",
    "sg:province":"NJ",
    "sg:tags":[
        "sales"
    ],
    "wof:name":"Campbells Carpet Sales",
    "wof:placetype":"venue"
},
  "geometry": {"coordinates":[-74.591594,41.081465],"type":"Point"}
}