{
  "type": "Feature",
  "properties": {
    "iso:country":"US",
    "sg:address":"22 E Henry St",
    "sg:city":"Basking Ridge",
    "sg:classifiers":[
        {
            "category":"Real Estate",
            "subcategory":"Real Estate Agent",
            "type":"Services"
        }
    ],
    "sg:phone":"+1   ",
    "sg:postcode":"07920",
    "sg:province":"NJ",
    "wof:name":"Weichert Realtors Rental",
    "wof:placetype":"venue"
},
  "geometry": {"coordinates":[-74.548377,40.705341],"type":"Point"}
}