{
  "type": "Feature",
  "properties": {
    "addr:full":"1196 Broad St Newark NJ 07114",
    "addr:housenumber":"1196",
    "addr:postcode":"07114",
    "addr:street":"Broad St",
    "iso:country":"US",
    "sg:address":"1196 Broad St",
    "sg:city":"Newark",
    "sg:classifiers":[
        {
            "category":"Retail",
            "subcategory":"Car Wash",
            "type":"Services"
        }
    ],
    "sg:phone":"+1 973 824 5666",
    "sg:postcode":"07114",
    "sg:province":"NJ",
    "wof:name":"Ultimate Car Care Centers",
    "wof:placetype":"venue"
},
  "geometry": {"coordinates":[-74.181099,40.7202],"type":"Point"}
}