{
  "type": "Feature",
  "properties": {
    "iso:country":"US",
    "sg:address":"390 Newkirk Ave",
    "sg:city":"Trenton",
    "sg:classifiers":[
        {
            "category":"Recreation",
            "type":"Entertainment"
        }
    ],
    "sg:phone":"+1 609 890 3630",
    "sg:postcode":"08610",
    "sg:province":"NJ",
    "sg:tags":[
        "parks"
    ],
    "sg:website":"www.hamiltonnj.com",
    "wof:name":"Kuser Farm Park",
    "wof:placetype":"venue"
},
  "geometry": {"coordinates":[-74.722239,40.216119],"type":"Point"}
}