{
  "type": "Feature",
  "properties": {
    "iso:country":"US",
    "sg:address":"7 Madaline Dr",
    "sg:city":"Edison",
    "sg:classifiers":[
        {
            "category":"Professional",
            "type":"Services"
        }
    ],
    "sg:phone":"+1   ",
    "sg:postcode":"08820",
    "sg:province":"NJ",
    "wof:name":"N Mendelsohn & Son",
    "wof:placetype":"venue"
},
  "geometry": {"coordinates":[-74.375964,40.598361],"type":"Point"}
}