{
  "type": "Feature",
  "properties": {
    "addr:full":"957 Main Ave Passaic NJ 07055",
    "addr:housenumber":"957",
    "addr:postcode":"07055",
    "addr:street":"Main Ave",
    "iso:country":"US",
    "sg:address":"957 Main Ave",
    "sg:city":"Passaic",
    "sg:classifiers":[
        {
            "category":"Restaurant",
            "type":"Food & Drink"
        }
    ],
    "sg:phone":"+1 973 470 4040",
    "sg:postcode":"07055",
    "sg:province":"NJ",
    "sg:tags":[
        "eating",
        "chinese"
    ],
    "wof:name":"China Star Kitchen",
    "wof:placetype":"venue"
},
  "geometry": {"coordinates":[-74.134399,40.869701],"type":"Point"}
}