{
  "type": "Feature",
  "properties": {
    "addr:full":"423 North Ave W Westfield NJ 07090",
    "addr:housenumber":"423",
    "addr:postcode":"07090",
    "addr:street":"North Ave W",
    "iso:country":"US",
    "sg:address":"423 North Ave W",
    "sg:city":"Westfield",
    "sg:classifiers":[
        {
            "category":"Banks & Credit Unions",
            "subcategory":"Investment Brokerage",
            "type":"Services"
        }
    ],
    "sg:phone":"+1 908 654 8768",
    "sg:postcode":"07090",
    "sg:province":"NJ",
    "sg:tags":[
        "advisory",
        "financial"
    ],
    "wof:name":"Lightner Capital Management",
    "wof:placetype":"venue"
},
  "geometry": {"coordinates":[-74.3498,40.649844],"type":"Point"}
}