{
  "type": "Feature",
  "properties": {
    "addr:full":"496 Long Hill Dr Short Hills NJ 07078",
    "addr:housenumber":"496",
    "addr:postcode":"07078",
    "addr:street":"Long Hill Dr",
    "iso:country":"US",
    "sg:address":"496 Long Hill Dr",
    "sg:city":"Short Hills",
    "sg:classifiers":[
        {
            "category":"Professional",
            "subcategory":"Management & Consulting",
            "type":"Services"
        }
    ],
    "sg:phone":"+1   ",
    "sg:postcode":"07078",
    "sg:province":"NJ",
    "sg:tags":[
        "business"
    ],
    "wof:name":"Nim Cheung & Associates",
    "wof:placetype":"venue"
},
  "geometry": {"coordinates":[-74.32335399999999,40.750857],"type":"Point"}
}