{
  "type": "Feature",
  "properties": {
    "iso:country":"US",
    "sg:address":"57 Bloomfield Ave",
    "sg:city":"Denville",
    "sg:classifiers":[
        {
            "category":"Wholesale",
            "subcategory":"Auto Parts",
            "type":"Manufacturing & Wholesale Goods"
        }
    ],
    "sg:phone":"+1 973 627 0086",
    "sg:postcode":"07834",
    "sg:province":"NJ",
    "sg:tags":[
        "supply"
    ],
    "wof:name":"Ren Auto Parts",
    "wof:placetype":"venue"
},
  "geometry": {"coordinates":[-74.471476,40.890105],"type":"Point"}
}