{
  "type": "Feature",
  "properties": {
    "addr:full":"137 Wood Ave Middlesex NJ 08846",
    "addr:housenumber":"137",
    "addr:postcode":"08846",
    "addr:street":"Wood Ave",
    "iso:country":"US",
    "sg:address":"137 Wood Ave",
    "sg:city":"Middlesex",
    "sg:classifiers":[
        {
            "category":"Manufacturing",
            "subcategory":"Tools & Machinery",
            "type":"Manufacturing & Wholesale Goods"
        }
    ],
    "sg:phone":"+1 732 356 0049",
    "sg:postcode":"08846",
    "sg:province":"NJ",
    "sg:tags":[
        "machine",
        "shop"
    ],
    "wof:name":"Central Jersey Machine & Tl Co",
    "wof:placetype":"venue"
},
  "geometry": {"coordinates":[-74.488355,40.571192],"type":"Point"}
}