{
  "type": "Feature",
  "properties": {
    "iso:country":"US",
    "sg:address":"30 Pershing Ln",
    "sg:city":"Sicklerville",
    "sg:classifiers":[
        {
            "category":"Professional",
            "subcategory":"Management & Consulting",
            "type":"Services"
        }
    ],
    "sg:phone":"+1 856 875 4851",
    "sg:postcode":"08081",
    "sg:province":"NJ",
    "sg:tags":[
        "promotion",
        "relation",
        "sale",
        "public"
    ],
    "wof:name":"Will Bid Co",
    "wof:placetype":"venue"
},
  "geometry": {"coordinates":[-74.959608,39.708548],"type":"Point"}
}