{
  "type": "Feature",
  "properties": {
    "iso:country":"US",
    "sg:address":"214 Webster Ave",
    "sg:city":"Jersey City",
    "sg:classifiers":[
        {
            "category":"Building & Trades",
            "subcategory":"Electrical",
            "type":"Services"
        }
    ],
    "sg:phone":"+1 201 656 7089",
    "sg:postcode":"07307",
    "sg:province":"NJ",
    "sg:tags":[
        "equipment",
        "electrical",
        "contractor"
    ],
    "wof:name":"Arc & Spark Electrical Contrs",
    "wof:placetype":"venue"
},
  "geometry": {"coordinates":[-74.04495199999999,40.746106],"type":"Point"}
}