{
  "type": "Feature",
  "properties": {
    "iso:country":"US",
    "sg:address":"13 Van Blarcom Ave",
    "sg:city":"Midland Park",
    "sg:classifiers":[
        {
            "category":"Home & Garden",
            "subcategory":"Garden Supply",
            "type":"Retail Goods"
        }
    ],
    "sg:phone":"+1   ",
    "sg:postcode":"07432",
    "sg:province":"NJ",
    "wof:name":"Midland Park Honda",
    "wof:placetype":"venue"
},
  "geometry": {"coordinates":[-74.13996400000001,40.985696],"type":"Point"}
}