{
  "type": "Feature",
  "properties": {
    "addr:full":"629 Hamburg Tpke Wayne NJ 07470",
    "addr:housenumber":"629",
    "addr:postcode":"07470",
    "addr:street":"Hamburg Tpke",
    "iso:country":"US",
    "sg:address":"629 Hamburg Tpke",
    "sg:city":"Wayne",
    "sg:classifiers":[
        {
            "category":"Restaurant",
            "type":"Food & Drink"
        }
    ],
    "sg:menulink":"http://www.allmenus.com/nj/wayne/5941-bensi-restaurant/menu/",
    "sg:phone":"+1 973 904 3004",
    "sg:postcode":"07470",
    "sg:province":"NJ",
    "sg:tags":[
        "italian"
    ],
    "wof:name":"Bensi Restaurant",
    "wof:placetype":"venue"
},
  "geometry": {"coordinates":[-74.220336,40.955929],"type":"Point"}
}