{
  "type": "Feature",
  "properties": {
    "addr:full":"7 Royal Dr Brick NJ 08723",
    "addr:housenumber":"7",
    "addr:postcode":"08723",
    "addr:street":"Royal Dr",
    "iso:country":"US",
    "sg:address":"7 Royal Dr",
    "sg:city":"Brick",
    "sg:classifiers":[
        {
            "category":"Professional",
            "subcategory":"Management & Consulting",
            "type":"Services"
        }
    ],
    "sg:phone":"+1 732 920 1883",
    "sg:postcode":"08723",
    "sg:province":"NJ",
    "sg:tags":[
        "consultant"
    ],
    "wof:name":"Skott Burkland Consultants",
    "wof:placetype":"venue"
},
  "geometry": {"coordinates":[-74.120582,40.032332],"type":"Point"}
}