{
  "type": "Feature",
  "properties": {
    "iso:country":"US",
    "sg:address":"6719 Bergenline Ave",
    "sg:city":"West New York",
    "sg:classifiers":[
        {
            "category":"Professional",
            "subcategory":"Accounting & Tax Preparation",
            "type":"Services"
        }
    ],
    "sg:phone":"+1 201 869 7766",
    "sg:postcode":"07093",
    "sg:province":"NJ",
    "sg:tags":[
        "accountant"
    ],
    "wof:name":"Grisales Ruben G CPA Tax Consultants",
    "wof:placetype":"venue"
},
  "geometry": {"coordinates":[-74.012398,40.794399],"type":"Point"}
}