{
  "type": "Feature",
  "properties": {
    "iso:country":"US",
    "sg:address":"118 Central Ave",
    "sg:city":"Clark",
    "sg:classifiers":[
        {
            "category":"Building & Trades",
            "subcategory":"Locksmith",
            "type":"Services"
        }
    ],
    "sg:phone":"+1 732 428 1758",
    "sg:postcode":"07066",
    "sg:province":"NJ",
    "sg:tags":[
        "key"
    ],
    "wof:name":"Nj Local All Day Locksmith",
    "wof:placetype":"venue"
},
  "geometry": {"coordinates":[-74.30697000000001,40.629029],"type":"Point"}
}