{
  "type": "Feature",
  "properties": {
    "addr:full":"2 Andrews Dr Little Falls NJ 07424",
    "addr:housenumber":"2",
    "addr:postcode":"07424",
    "addr:street":"Andrews Dr",
    "iso:country":"US",
    "sg:address":"2 Andrews Dr",
    "sg:city":"Little Falls",
    "sg:classifiers":[
        {
            "category":"Professional",
            "subcategory":"Management & Consulting",
            "type":"Services"
        }
    ],
    "sg:phone":"+1   ",
    "sg:postcode":"07424",
    "sg:province":"NJ",
    "sg:tags":[
        "computer",
        "design",
        "integrated",
        "system"
    ],
    "wof:name":"A DEVELOPMENT STAGE COMPANY",
    "wof:placetype":"venue"
},
  "geometry": {"coordinates":[-74.207763,40.886173],"type":"Point"}
}