{
  "type": "Feature",
  "properties": {
    "iso:country":"US",
    "sg:address":"6 Cooper Ln",
    "sg:city":"New Vernon",
    "sg:classifiers":[
        {
            "category":"Building & Trades",
            "subcategory":"Construction",
            "type":"Services"
        }
    ],
    "sg:phone":"+1 973 267 1990",
    "sg:postcode":"07946",
    "sg:province":"NJ",
    "sg:tags":[
        "general",
        "contractor"
    ],
    "wof:name":"Consolidated Contractors",
    "wof:placetype":"venue"
},
  "geometry": {"coordinates":[-74.523887,40.668908],"type":"Point"}
}