{
  "type": "Feature",
  "properties": {
    "addr:full":"87 Berdan Ave Wayne NJ 07470",
    "addr:housenumber":"87",
    "addr:postcode":"07470",
    "addr:street":"Berdan Ave",
    "iso:country":"US",
    "sg:address":"87 Berdan Ave",
    "sg:city":"Wayne",
    "sg:classifiers":[
        {
            "category":"Banks & Credit Unions",
            "subcategory":"Bank",
            "type":"Services"
        }
    ],
    "sg:phone":"+1 973 686 3200",
    "sg:postcode":"07470",
    "sg:province":"NJ",
    "sg:tags":[
        "mortgage",
        "loan",
        "broker",
        "real estate"
    ],
    "sg:website":"www.wellsfargo.com",
    "wof:name":"Wells Fargo Home Mortgage",
    "wof:placetype":"venue"
},
  "geometry": {"coordinates":[-74.242401,40.963001],"type":"Point"}
}