{
  "type": "Feature",
  "properties": {
    "iso:country":"US",
    "sg:address":"2 Richard Ct",
    "sg:city":"Bordentown",
    "sg:classifiers":[
        {
            "category":"Arts & Performance",
            "subcategory":"Theater",
            "type":"Entertainment"
        }
    ],
    "sg:phone":"+1   ",
    "sg:postcode":"08505",
    "sg:province":"NJ",
    "sg:tags":[
        "group"
    ],
    "wof:name":"Papp John",
    "wof:placetype":"venue"
},
  "geometry": {"coordinates":[-74.69037,40.141036],"type":"Point"}
}