{
  "type": "Feature",
  "properties": {
    "addr:full":"59 New St Newark NJ 07102",
    "addr:housenumber":"59",
    "addr:postcode":"07102",
    "addr:street":"New St",
    "iso:country":"US",
    "sg:address":"59 New St",
    "sg:city":"Newark",
    "sg:classifiers":[
        {
            "category":"Restaurant",
            "type":"Food & Drink"
        }
    ],
    "sg:phone":"+1   ",
    "sg:postcode":"07102",
    "sg:province":"NJ",
    "sg:tags":[
        "eating"
    ],
    "wof:name":"Burrito Grande",
    "wof:placetype":"venue"
},
  "geometry": {"coordinates":[-74.171741,40.740473],"type":"Point"}
}