{
  "type": "Feature",
  "properties": {
    "iso:country":"US",
    "sg:address":"724 Longboat Ave",
    "sg:city":"Beachwood",
    "sg:classifiers":[
        {
            "category":"Professional",
            "subcategory":"Business Services",
            "type":"Services"
        }
    ],
    "sg:phone":"+1 732 341 5983",
    "sg:postcode":"08722",
    "sg:province":"NJ",
    "wof:name":"Anchor Fire Protection",
    "wof:placetype":"venue"
},
  "geometry": {"coordinates":[-74.193439,39.928513],"type":"Point"}
}