{
  "type": "Feature",
  "properties": {
    "iso:country":"US",
    "sg:address":"185 Hackensack St",
    "sg:city":"Wood Ridge",
    "sg:classifiers":[
        {
            "category":"Organizations",
            "subcategory":"Religious Organization",
            "type":"Services"
        }
    ],
    "sg:phone":"+1 201 438 4520",
    "sg:postcode":"07075",
    "sg:province":"NJ",
    "sg:tags":[
        "clergy"
    ],
    "wof:name":"Dianna Bell",
    "wof:placetype":"venue"
},
  "geometry": {"coordinates":[-74.083229,40.84664],"type":"Point"}
}