{
  "type": "Feature",
  "properties": {
    "iso:country":"US",
    "sg:address":"1400 Madison Ave",
    "sg:city":"Lakewood",
    "sg:classifiers":[
        {
            "category":"Shopping",
            "subcategory":"Bicycles & Sporting Goods",
            "type":"Retail Goods"
        }
    ],
    "sg:phone":"+1 732 363 6618",
    "sg:postcode":"08701",
    "sg:province":"NJ",
    "sg:tags":[
        "equipment",
        "camping"
    ],
    "wof:name":"Ledmark Industries LLC",
    "wof:placetype":"venue"
},
  "geometry": {"coordinates":[-74.21911,40.104521],"type":"Point"}
}