{
  "type": "Feature",
  "properties": {
    "addr:full":"63 Pine St Ramsey NJ 07446",
    "addr:housenumber":"63",
    "addr:postcode":"07446",
    "addr:street":"Pine St",
    "iso:country":"US",
    "sg:address":"63 Pine St",
    "sg:city":"Ramsey",
    "sg:classifiers":[
        {
            "category":"Wholesale",
            "subcategory":"Vending Machines",
            "type":"Manufacturing & Wholesale Goods"
        }
    ],
    "sg:phone":"+1   ",
    "sg:postcode":"07446",
    "sg:province":"NJ",
    "sg:tags":[
        "operator"
    ],
    "wof:name":"Ramapo Vending Co",
    "wof:placetype":"venue"
},
  "geometry": {"coordinates":[-74.151143,41.045101],"type":"Point"}
}