{
  "type": "Feature",
  "properties": {
    "iso:country":"US",
    "sg:address":"62 Runyon Dr",
    "sg:city":"Trenton",
    "sg:classifiers":[
        {
            "category":"Wholesale",
            "subcategory":"Electrical",
            "type":"Manufacturing & Wholesale Goods"
        }
    ],
    "sg:phone":"+1 609 888 0780",
    "sg:postcode":"08610",
    "sg:province":"NJ",
    "sg:tags":[
        "parts",
        "electronic",
        "conditioning",
        "air"
    ],
    "wof:name":"Service Parts & Supply Co Inc",
    "wof:placetype":"venue"
},
  "geometry": {"coordinates":[-74.71475700000001,40.189362],"type":"Point"}
}