{
  "type": "Feature",
  "properties": {
    "addr:full":"739 E Broad St Gibbstown NJ 08027",
    "addr:housenumber":"739",
    "addr:postcode":"08027",
    "addr:street":"E Broad St",
    "iso:country":"US",
    "sg:address":"739 E Broad St",
    "sg:city":"Gibbstown",
    "sg:classifiers":[
        {
            "category":"Shopping",
            "subcategory":"Florist",
            "type":"Retail Goods"
        }
    ],
    "sg:phone":"+1   ",
    "sg:postcode":"08027",
    "sg:province":"NJ",
    "wof:name":"Felician Flowers",
    "wof:placetype":"venue"
},
  "geometry": {"coordinates":[-75.25706,39.826305],"type":"Point"}
}