{
  "type": "Feature",
  "properties": {
    "addr:full":"684 N Franklin Tpke Allendale NJ 07401",
    "addr:housenumber":"684",
    "addr:postcode":"07401",
    "addr:street":"N Franklin Tpke",
    "iso:country":"US",
    "sg:address":"684 N Franklin Tpke",
    "sg:city":"Allendale",
    "sg:classifiers":[
        {
            "category":"Building & Trades",
            "subcategory":"Construction",
            "type":"Services"
        }
    ],
    "sg:phone":"+1 201 236 8332",
    "sg:postcode":"07401",
    "sg:province":"NJ",
    "sg:tags":[
        "roofing",
        "contractor"
    ],
    "wof:name":"Ridgeview Roofing Co Inc",
    "wof:placetype":"venue"
},
  "geometry": {"coordinates":[-74.128339,41.038126],"type":"Point"}
}