{
  "type": "Feature",
  "properties": {
    "iso:country":"US",
    "sg:address":"6 Dakarla Dr",
    "sg:city":"Middletown",
    "sg:classifiers":[
        {
            "category":"Manufacturing",
            "subcategory":"Printing",
            "type":"Manufacturing & Wholesale Goods"
        }
    ],
    "sg:phone":"+1 732 615 0972",
    "sg:postcode":"07748",
    "sg:province":"NJ",
    "sg:tags":[
        "commercial"
    ],
    "wof:name":"Graphic Trade Bindery",
    "wof:placetype":"venue"
},
  "geometry": {"coordinates":[-74.123362,40.356407],"type":"Point"}
}