{
  "type": "Feature",
  "properties": {
    "iso:country":"US",
    "sg:address":"515 Woodbury Glassboro Rd",
    "sg:city":"Sewell",
    "sg:classifiers":[
        {
            "category":"Banks & Credit Unions",
            "subcategory":"Financial Services",
            "type":"Services"
        }
    ],
    "sg:phone":"+1   ",
    "sg:postcode":"08080",
    "sg:province":"NJ",
    "sg:tags":[
        "company",
        "bank",
        "holding"
    ],
    "wof:name":"Newfield National Bank",
    "wof:placetype":"venue"
},
  "geometry": {"coordinates":[-75.127291,39.749441],"type":"Point"}
}