{
  "type": "Feature",
  "properties": {
    "iso:country":"US",
    "sg:address":"45 Pershing Ave",
    "sg:city":"Elizabeth",
    "sg:classifiers":[
        {
            "category":"Freight",
            "type":"Transportation"
        }
    ],
    "sg:phone":"+1 908 965 1127",
    "sg:postcode":"07202",
    "sg:province":"NJ",
    "sg:tags":[
        "operator",
        "local",
        "trucking"
    ],
    "wof:name":"Ortiz Trucking Leonides O",
    "wof:placetype":"venue"
},
  "geometry": {"coordinates":[-74.233013,40.657733],"type":"Point"}
}