{
  "type": "Feature",
  "properties": {
    "addr:full":"250 Woodbridge Ctr Woodbridge NJ 07095",
    "addr:housenumber":"250",
    "addr:postcode":"07095",
    "addr:street":"Woodbridge Ctr",
    "iso:country":"US",
    "sg:address":"250 Woodbridge Ctr",
    "sg:city":"Woodbridge",
    "sg:classifiers":[
        {
            "category":"Sports & Exercise",
            "subcategory":"Bicycle Rental",
            "type":"Entertainment"
        }
    ],
    "sg:phone":"+1 732 855 0626",
    "sg:postcode":"07095",
    "sg:province":"NJ",
    "sg:tags":[
        "wear"
    ],
    "wof:name":"Lids",
    "wof:placetype":"venue"
},
  "geometry": {"coordinates":[-74.297997,40.550598],"type":"Point"}
}