{
  "type": "Feature",
  "properties": {
    "iso:country":"US",
    "sg:address":"554 Harrison Ave",
    "sg:city":"Lodi",
    "sg:classifiers":[
        {
            "category":"Building & Trades",
            "subcategory":"Construction",
            "type":"Services"
        }
    ],
    "sg:phone":"+1 973 340 3555",
    "sg:postcode":"07644",
    "sg:province":"NJ",
    "sg:tags":[
        "house",
        "contractor"
    ],
    "wof:name":"AAA Builders Inc",
    "wof:placetype":"venue"
},
  "geometry": {"coordinates":[-74.092236,40.884973],"type":"Point"}
}