{
  "type": "Feature",
  "properties": {
    "iso:country":"US",
    "sg:address":"109 Brass Castle Rd",
    "sg:city":"Washington",
    "sg:classifiers":[
        {
            "category":"Health Services",
            "subcategory":"Clinic",
            "type":"Services"
        },
        {
            "category":"Health Services",
            "subcategory":"Medical Lab",
            "type":"Services"
        }
    ],
    "sg:phone":"+1 908 835 0992",
    "sg:postcode":"07882",
    "sg:province":"NJ",
    "sg:tags":[
        "treatment",
        "cancer"
    ],
    "wof:name":"American Childrens Cancer",
    "wof:placetype":"venue"
},
  "geometry": {"coordinates":[-75.009987,40.76408],"type":"Point"}
}