{
  "type": "Feature",
  "properties": {
    "addr:full":"8 Daniel Dr Cedar Grove NJ 07009",
    "addr:housenumber":"8",
    "addr:postcode":"07009",
    "addr:street":"Daniel Dr",
    "iso:country":"US",
    "sg:address":"8 Daniel Dr",
    "sg:city":"Cedar Grove",
    "sg:classifiers":[
        {
            "category":"Freight",
            "type":"Transportation"
        }
    ],
    "sg:phone":"+1 973 239 4145",
    "sg:postcode":"07009",
    "sg:province":"NJ",
    "sg:tags":[
        "operator",
        "local",
        "trucking"
    ],
    "wof:name":"A Scaff Trucking Inc",
    "wof:placetype":"venue"
},
  "geometry": {"coordinates":[-74.22299700000001,40.857176],"type":"Point"}
}