{
  "type": "Feature",
  "properties": {
    "iso:country":"US",
    "sg:address":"121 Broadway",
    "sg:city":"Elmwood Park",
    "sg:classifiers":[
        {
            "category":"Autos & Motor Vehicles",
            "subcategory":"Fuel & Gas Station",
            "type":"Retail Goods"
        }
    ],
    "sg:phone":"+1 201 796 9630",
    "sg:postcode":"07407",
    "sg:province":"NJ",
    "sg:tags":[
        "oil"
    ],
    "wof:name":"Hess Service Station",
    "wof:placetype":"venue"
},
  "geometry": {"coordinates":[-74.12273999999999,40.919809],"type":"Point"}
}