{
  "type": "Feature",
  "properties": {
    "addr:full":"8 Cove Rd Lake Hopatcong NJ 07849",
    "addr:housenumber":"8",
    "addr:postcode":"07849",
    "addr:street":"Cove Rd",
    "iso:country":"US",
    "sg:address":"8 Cove Rd",
    "sg:city":"Lake Hopatcong",
    "sg:classifiers":[
        {
            "category":"Building & Trades",
            "subcategory":"Cleaning & Sanitation",
            "type":"Services"
        }
    ],
    "sg:phone":"+1 973 663 4254",
    "sg:postcode":"07849",
    "sg:province":"NJ",
    "sg:tags":[
        "construction",
        "chimney",
        "maintenance"
    ],
    "wof:name":"Assurance Chimney Services",
    "wof:placetype":"venue"
},
  "geometry": {"coordinates":[-74.62643,40.945473],"type":"Point"}
}