{
  "type": "Feature",
  "properties": {
    "iso:country":"US",
    "sg:address":"39 N Leonard Ave",
    "sg:city":"Leonardo",
    "sg:classifiers":[
        {
            "category":"Professional",
            "subcategory":"Management & Consulting",
            "type":"Services"
        }
    ],
    "sg:phone":"+1 732 708 1049",
    "sg:postcode":"07737",
    "sg:province":"NJ",
    "sg:tags":[
        "personnel",
        "consultant"
    ],
    "wof:name":"Uniqe Staffing",
    "wof:placetype":"venue"
},
  "geometry": {"coordinates":[-74.057131,40.417413],"type":"Point"}
}