{
  "type": "Feature",
  "properties": {
    "iso:country":"US",
    "sg:address":"329 Co Rd 526",
    "sg:city":"Cream Ridge",
    "sg:classifiers":[
        {
            "category":"Retail",
            "subcategory":"Animal Services",
            "type":"Services"
        }
    ],
    "sg:phone":"+1 609 259 7555",
    "sg:postcode":"08514",
    "sg:province":"NJ",
    "sg:tags":[
        "breeder",
        "horse"
    ],
    "sg:website":"www.perrettifarms.com",
    "wof:name":"Perretti Farm Inc",
    "wof:placetype":"venue"
},
  "geometry": {"coordinates":[-74.47995299999999,40.162559],"type":"Point"}
}