{
  "type": "Feature",
  "properties": {
    "addr:full":"4 Forest Dr Springfield NJ 07081",
    "addr:housenumber":"4",
    "addr:postcode":"07081",
    "addr:street":"Forest Dr",
    "iso:country":"US",
    "sg:address":"4 Forest Dr",
    "sg:city":"Springfield",
    "sg:classifiers":[
        {
            "category":"Education",
            "subcategory":"School",
            "type":"Public Place"
        }
    ],
    "sg:phone":"+1 973 376 4540",
    "sg:postcode":"07081",
    "sg:province":"NJ",
    "wof:name":"Short Hills Vlg Superintendent",
    "wof:placetype":"venue"
},
  "geometry": {"coordinates":[-74.318713,40.718395],"type":"Point"}
}