{
  "type": "Feature",
  "properties": {
    "addr:full":"140 Clements Bridge Rd Barrington NJ 08007",
    "addr:housenumber":"140",
    "addr:postcode":"08007",
    "addr:street":"Clements Bridge Rd",
    "iso:country":"US",
    "sg:address":"140 Clements Bridge Rd",
    "sg:city":"Barrington",
    "sg:classifiers":[
        {
            "category":"Organizations",
            "subcategory":"Religious Organization",
            "type":"Services"
        }
    ],
    "sg:phone":"+1 856 547 0814",
    "sg:postcode":"08007",
    "sg:province":"NJ",
    "sg:tags":[
        "church"
    ],
    "wof:name":"Barrington First United Mthdst",
    "wof:placetype":"venue"
},
  "geometry": {"coordinates":[-75.051441,39.871927],"type":"Point"}
}