{
  "type": "Feature",
  "properties": {
    "addr:full":"200 W Merchant St Audubon NJ 08106",
    "addr:housenumber":"200",
    "addr:postcode":"08106",
    "addr:street":"W Merchant St",
    "iso:country":"US",
    "sg:address":"200 W Merchant St",
    "sg:city":"Audubon",
    "sg:classifiers":[
        {
            "category":"Real Estate",
            "subcategory":"Real Estate Operator",
            "type":"Services"
        }
    ],
    "sg:phone":"+1 856 310 9296",
    "sg:postcode":"08106",
    "sg:province":"NJ",
    "sg:tags":[
        "apartment"
    ],
    "wof:name":"Commons At Audubon",
    "wof:placetype":"venue"
},
  "geometry": {"coordinates":[-75.07260100000001,39.8936],"type":"Point"}
}