{
  "type": "Feature",
  "properties": {
    "addr:full":"55 Park St Montclair NJ 07042",
    "addr:housenumber":"55",
    "addr:postcode":"07042",
    "addr:street":"Park St",
    "iso:country":"US",
    "sg:address":"55 Park St",
    "sg:city":"Montclair",
    "sg:classifiers":[
        {
            "category":"Professional",
            "subcategory":"Accounting & Tax Preparation",
            "type":"Services"
        }
    ],
    "sg:phone":"+1 973 509 8060",
    "sg:postcode":"07042",
    "sg:province":"NJ",
    "sg:tags":[
        "accountant"
    ],
    "wof:name":"Chiappone Robert A CPA",
    "wof:placetype":"venue"
},
  "geometry": {"coordinates":[-74.217697,40.811401],"type":"Point"}
}