{
  "type": "Feature",
  "properties": {
    "iso:country":"US",
    "sg:address":"5625 Westfield Ave Ste A",
    "sg:city":"Pennsauken",
    "sg:classifiers":[
        {
            "category":"Health Services",
            "subcategory":"Doctor",
            "type":"Services"
        }
    ],
    "sg:phone":"+1 856 662 8999",
    "sg:postcode":"08110",
    "sg:province":"NJ",
    "sg:tags":[
        "podiatrist"
    ],
    "wof:name":"Udell Samuel DPM",
    "wof:placetype":"venue"
},
  "geometry": {"coordinates":[-75.0625,39.960602],"type":"Point"}
}