{
  "type": "Feature",
  "properties": {
    "addr:full":"27 Liberty Pl Keansburg NJ 07734",
    "addr:housenumber":"27",
    "addr:postcode":"07734",
    "addr:street":"Liberty Pl",
    "iso:country":"US",
    "sg:address":"27 Liberty Pl",
    "sg:city":"Keansburg",
    "sg:classifiers":[
        {
            "category":"Building & Trades",
            "subcategory":"Construction",
            "type":"Services"
        }
    ],
    "sg:phone":"+1 732 787 8282",
    "sg:postcode":"07734",
    "sg:province":"NJ",
    "sg:tags":[
        "contractor"
    ],
    "wof:name":"All Perspective Tile",
    "wof:placetype":"venue"
},
  "geometry": {"coordinates":[-74.140169,40.436344],"type":"Point"}
}