{
  "type": "Feature",
  "properties": {
    "addr:full":"94 Tindall Rd Middletown NJ 07748",
    "addr:housenumber":"94",
    "addr:postcode":"07748",
    "addr:street":"Tindall Rd",
    "iso:country":"US",
    "sg:address":"94 Tindall Rd",
    "sg:city":"Middletown",
    "sg:classifiers":[
        {
            "category":"Organizations",
            "subcategory":"Religious Organization",
            "type":"Services"
        }
    ],
    "sg:phone":"+1 732 671 2585",
    "sg:postcode":"07748",
    "sg:province":"NJ",
    "sg:tags":[
        "church"
    ],
    "wof:name":"Westminster Presbyterian Chr",
    "wof:placetype":"venue"
},
  "geometry": {"coordinates":[-74.100837,40.402578],"type":"Point"}
}