{
  "type": "Feature",
  "properties": {
    "addr:full":"904 Somerset Ct Ramsey NJ 07446",
    "addr:housenumber":"904",
    "addr:postcode":"07446",
    "addr:street":"Somerset Ct",
    "iso:country":"US",
    "sg:address":"904 Somerset Ct",
    "sg:city":"Ramsey",
    "sg:classifiers":[
        {
            "category":"Retail",
            "subcategory":"Laundry & Dry Cleaning",
            "type":"Services"
        }
    ],
    "sg:phone":"+1   ",
    "sg:postcode":"07446",
    "sg:province":"NJ",
    "wof:name":"Custom Carpet Cleaners",
    "wof:placetype":"venue"
},
  "geometry": {"coordinates":[-74.12553699999999,41.072517],"type":"Point"}
}