{
  "type": "Feature",
  "properties": {
    "addr:full":"1206 Kennebec Rd Forked River NJ 08731",
    "addr:housenumber":"1206",
    "addr:postcode":"08731",
    "addr:street":"Kennebec Rd",
    "iso:country":"US",
    "sg:address":"1206 Kennebec Rd",
    "sg:city":"Forked River",
    "sg:classifiers":[
        {
            "category":"Professional",
            "subcategory":"Computer Services",
            "type":"Services"
        }
    ],
    "sg:phone":"+1   ",
    "sg:postcode":"08731",
    "sg:province":"NJ",
    "sg:tags":[
        "sales"
    ],
    "wof:name":"Lan-Scape Networks and Cmpt",
    "wof:placetype":"venue"
},
  "geometry": {"coordinates":[-74.203868,39.830933],"type":"Point"}
}