{
  "type": "Feature",
  "properties": {
    "iso:country":"US",
    "sg:address":"3 E Palisade Ave",
    "sg:city":"Englewood",
    "sg:classifiers":[
        {
            "category":"Food & Beverages",
            "subcategory":"Liquor & Beverages",
            "type":"Retail Goods"
        }
    ],
    "sg:phone":"+1 201 568 8820",
    "sg:postcode":"07631",
    "sg:province":"NJ",
    "sg:tags":[
        "wine"
    ],
    "wof:name":"Englewood Wine Merchants",
    "wof:placetype":"venue"
},
  "geometry": {"coordinates":[-73.97456099999999,40.893719],"type":"Point"}
}