{
  "type": "Feature",
  "properties": {
    "addr:full":"6 Bergen Ave Bellmawr NJ 08031",
    "addr:housenumber":"6",
    "addr:postcode":"08031",
    "addr:street":"Bergen Ave",
    "iso:country":"US",
    "sg:address":"6 Bergen Ave",
    "sg:city":"Bellmawr",
    "sg:classifiers":[
        {
            "category":"Professional",
            "type":"Services"
        }
    ],
    "sg:phone":"+1   ",
    "sg:postcode":"08031",
    "sg:province":"NJ",
    "wof:name":"Alarmax Services LLC",
    "wof:placetype":"venue"
},
  "geometry": {"coordinates":[-75.109841,39.874731],"type":"Point"}
}