{
  "type": "Feature",
  "properties": {
    "iso:country":"US",
    "sg:address":"39 Safran Ave",
    "sg:city":"Edison",
    "sg:classifiers":[
        {
            "category":"Building & Trades",
            "subcategory":"Plumbing",
            "type":"Services"
        }
    ],
    "sg:phone":"+1 732 738 9373",
    "sg:postcode":"08837",
    "sg:province":"NJ",
    "sg:tags":[
        "electrical",
        "contractor"
    ],
    "wof:name":"Edbridge Electric Inc",
    "wof:placetype":"venue"
},
  "geometry": {"coordinates":[-74.32002,40.528495],"type":"Point"}
}