{
  "type": "Feature",
  "properties": {
    "addr:full":"357 Lake St Newark NJ 07104",
    "addr:housenumber":"357",
    "addr:postcode":"07104",
    "addr:street":"Lake St",
    "iso:country":"US",
    "sg:address":"357 Lake St",
    "sg:city":"Newark",
    "sg:classifiers":[
        {
            "category":"Arts & Performance",
            "subcategory":"Theater",
            "type":"Entertainment"
        }
    ],
    "sg:phone":"+1 973 485 3503",
    "sg:postcode":"07104",
    "sg:province":"NJ",
    "sg:tags":[
        "group"
    ],
    "wof:name":"Brick Born Entertainment",
    "wof:placetype":"venue"
},
  "geometry": {"coordinates":[-74.17739899999999,40.763316],"type":"Point"}
}