{
  "type": "Feature",
  "properties": {
    "iso:country":"US",
    "sg:address":"106 Harvey Pl",
    "sg:city":"Mt Laurel",
    "sg:classifiers":[
        {
            "category":"Wholesale",
            "subcategory":"Electrical",
            "type":"Manufacturing & Wholesale Goods"
        },
        {
            "category":"Manufacturing",
            "subcategory":"Electronics",
            "type":"Manufacturing & Wholesale Goods"
        }
    ],
    "sg:phone":"+1 856 722 0025",
    "sg:postcode":"08054",
    "sg:province":"NJ",
    "sg:tags":[
        "control",
        "equipment",
        "security",
        "system"
    ],
    "wof:name":"Accredited Alarm Systems",
    "wof:placetype":"venue"
},
  "geometry": {"coordinates":[-74.94070499999999,39.937786],"type":"Point"}
}