{
  "type": "Feature",
  "properties": {
    "iso:country":"US",
    "sg:address":"970 Spruce St",
    "sg:city":"Trenton",
    "sg:classifiers":[
        {
            "category":"Food & Beverages",
            "subcategory":"Dairy",
            "type":"Retail Goods"
        }
    ],
    "sg:phone":"+1 609 695 3311",
    "sg:postcode":"08648",
    "sg:province":"NJ",
    "sg:tags":[
        "product"
    ],
    "wof:name":"Halo Farm",
    "wof:placetype":"venue"
},
  "geometry": {"coordinates":[-74.75068899999999,40.241872],"type":"Point"}
}