{
  "type": "Feature",
  "properties": {
    "addr:full":"3817 Crosswicks Hamilton Sq Rd Trenton NJ 08691",
    "addr:housenumber":"3817",
    "addr:postcode":"08691",
    "addr:street":"Crosswicks Hamilton Sq Rd",
    "iso:country":"US",
    "sg:address":"3817 Crosswicks Hamilton Sq Rd",
    "sg:city":"Trenton",
    "sg:phone":"+1 609 585 5255",
    "sg:postcode":"08691",
    "sg:province":"NJ",
    "sg:website":"http://www.spigola.net/main.swf",
    "wof:name":"Spigola Ristorante Vino e Cucina",
    "wof:placetype":"venue"
},
  "geometry": {"coordinates":[-74.645662,40.19169],"type":"Point"}
}