{
  "type": "Feature",
  "properties": {
    "iso:country":"US",
    "sg:address":"862 Kearny Ave",
    "sg:city":"Kearny",
    "sg:classifiers":[
        {
            "category":"Professional",
            "subcategory":"Business Services",
            "type":"Services"
        }
    ],
    "sg:phone":"+1 201 997 1708",
    "sg:postcode":"07032",
    "sg:province":"NJ",
    "sg:tags":[
        "broker",
        "merchandise"
    ],
    "wof:name":"Elite Brokers LLC",
    "wof:placetype":"venue"
},
  "geometry": {"coordinates":[-74.138711,40.781332],"type":"Point"}
}