{
  "type": "Feature",
  "properties": {
    "addr:full":"268 Green Village Rd Green Village NJ 07935",
    "addr:housenumber":"268",
    "addr:postcode":"07935",
    "addr:street":"Green Village Rd",
    "iso:country":"US",
    "sg:address":"268 Green Village Rd",
    "sg:city":"Green Village",
    "sg:classifiers":[
        {
            "category":"Health Services",
            "subcategory":"Clinic",
            "type":"Services"
        }
    ],
    "sg:phone":"+1 973 822 9620",
    "sg:postcode":"07935",
    "sg:province":"NJ",
    "sg:tags":[
        "counseling",
        "mental"
    ],
    "wof:name":"Skinner Pierce R Psy D",
    "wof:placetype":"venue"
},
  "geometry": {"coordinates":[-74.432198,40.7463],"type":"Point"}
}