{
  "type": "Feature",
  "properties": {
    "iso:country":"US",
    "sg:address":"145 King St",
    "sg:city":"Dover",
    "sg:classifiers":[
        {
            "category":"Restaurant",
            "type":"Food & Drink"
        }
    ],
    "sg:phone":"+1 973 366 3535",
    "sg:postcode":"07801",
    "sg:province":"NJ",
    "sg:tags":[
        "pizza",
        "italian"
    ],
    "wof:name":"Delizia Pizza",
    "wof:placetype":"venue"
},
  "geometry": {"coordinates":[-74.550028,40.889768],"type":"Point"}
}