{
  "type": "Feature",
  "properties": {
    "addr:full":"210 Malapardis Rd Cedar Knolls NJ 07927",
    "addr:housenumber":"210",
    "addr:postcode":"07927",
    "addr:street":"Malapardis Rd",
    "iso:country":"US",
    "sg:address":"210 Malapardis Rd",
    "sg:city":"Cedar Knolls",
    "sg:classifiers":[
        {
            "category":"Banks & Credit Unions",
            "subcategory":"Investment Brokerage",
            "type":"Services"
        }
    ],
    "sg:phone":"+1 973 292 0049",
    "sg:postcode":"07927",
    "sg:province":"NJ",
    "sg:tags":[
        "advisory",
        "financial"
    ],
    "wof:name":"Pitch Financial Svc",
    "wof:placetype":"venue"
},
  "geometry": {"coordinates":[-74.451657,40.831413],"type":"Point"}
}