{
  "type": "Feature",
  "properties": {
    "iso:country":"US",
    "sg:address":"75 Livingston Ave",
    "sg:city":"Roseland",
    "sg:classifiers":[
        {
            "category":"Professional",
            "subcategory":"Lawyer & Legal Services",
            "type":"Services"
        }
    ],
    "sg:phone":"+1 973 992 4800",
    "sg:postcode":"07068",
    "sg:province":"NJ",
    "wof:name":"Hoffman Harold L Lawyer",
    "wof:placetype":"venue"
},
  "geometry": {"coordinates":[-74.30259700000001,40.815201],"type":"Point"}
}