{
  "type": "Feature",
  "properties": {
    "addr:full":"43 Industrial Ave Fairview NJ 07022",
    "addr:housenumber":"43",
    "addr:postcode":"07022",
    "addr:street":"Industrial Ave",
    "iso:country":"US",
    "sg:address":"43 Industrial Ave",
    "sg:city":"Fairview",
    "sg:classifiers":[
        {
            "category":"Professional",
            "subcategory":"Business Services",
            "type":"Services"
        }
    ],
    "sg:phone":"+1 201 943 8700",
    "sg:postcode":"07022",
    "sg:province":"NJ",
    "sg:tags":[
        "embroidery"
    ],
    "wof:name":"Embroidery Group",
    "wof:placetype":"venue"
},
  "geometry": {"coordinates":[-74.002898,40.81817],"type":"Point"}
}