{
  "type": "Feature",
  "properties": {
    "addr:full":"1114 Black Horse Pike Hammonton NJ 08037",
    "addr:housenumber":"1114",
    "addr:postcode":"08037",
    "addr:street":"Black Horse Pike",
    "iso:country":"US",
    "sg:address":"1114 Black Horse Pike",
    "sg:city":"Hammonton",
    "sg:classifiers":[
        {
            "category":"Wholesale",
            "subcategory":"Motor Vehicles",
            "type":"Manufacturing & Wholesale Goods"
        },
        {
            "category":"Retail",
            "subcategory":"Auto Repair",
            "type":"Services"
        }
    ],
    "sg:phone":"+1 609 567 3009",
    "sg:postcode":"08037",
    "sg:province":"NJ",
    "sg:tags":[
        "repairing",
        "automobile"
    ],
    "wof:name":"Axis Auto & Truck Service",
    "wof:placetype":"venue"
},
  "geometry": {"coordinates":[-74.841131,39.58468],"type":"Point"}
}