{
  "type": "Feature",
  "properties": {
    "addr:full":"286 Rues Ln East Brunswick NJ 08816",
    "addr:housenumber":"286",
    "addr:postcode":"08816",
    "addr:street":"Rues Ln",
    "iso:country":"US",
    "sg:address":"286 Rues Ln",
    "sg:city":"East Brunswick",
    "sg:classifiers":[
        {
            "category":"Food & Beverages",
            "subcategory":"Groceries & Convenience Stores",
            "type":"Retail Goods"
        }
    ],
    "sg:phone":"+1   ",
    "sg:postcode":"08816",
    "sg:province":"NJ",
    "wof:name":"7-Eleven",
    "wof:placetype":"venue"
},
  "geometry": {"coordinates":[-74.405269,40.417994],"type":"Point"}
}