{
  "type": "Feature",
  "properties": {
    "iso:country":"US",
    "sg:address":"600 Fischer Blvd",
    "sg:city":"Toms River",
    "sg:classifiers":[
        {
            "category":"Food & Beverages",
            "subcategory":"Groceries & Convenience Stores",
            "type":"Retail Goods"
        }
    ],
    "sg:phone":"+1   ",
    "sg:postcode":"08753",
    "sg:province":"NJ",
    "wof:name":"Wawa 797",
    "wof:placetype":"venue"
},
  "geometry": {"coordinates":[-74.12471600000001,39.957699],"type":"Point"}
}