{
  "type": "Feature",
  "properties": {
    "addr:full":"322 E 5th St Lakewood NJ 08701",
    "addr:housenumber":"322",
    "addr:postcode":"08701",
    "addr:street":"E 5Th St",
    "iso:country":"US",
    "sg:address":"322 E 5th St",
    "sg:city":"Lakewood",
    "sg:classifiers":[
        {
            "category":"Organizations",
            "subcategory":"Religious Organization",
            "type":"Services"
        }
    ],
    "sg:phone":"+1   ",
    "sg:postcode":"08701",
    "sg:province":"NJ",
    "wof:name":"Church God Pntecostal Holiness",
    "wof:placetype":"venue"
},
  "geometry": {"coordinates":[-74.20078100000001,40.094871],"type":"Point"}
}