{
  "type": "Feature",
  "properties": {
    "addr:full":"22 Horseshoe Dr Perrineville NJ 08535",
    "addr:housenumber":"22",
    "addr:postcode":"08535",
    "addr:street":"Horseshoe Dr",
    "iso:country":"US",
    "sg:address":"22 Horseshoe Dr",
    "sg:city":"Perrineville",
    "sg:classifiers":[
        {
            "category":"Freight",
            "type":"Transportation"
        }
    ],
    "sg:phone":"+1 732 446 4837",
    "sg:postcode":"08535",
    "sg:province":"NJ",
    "wof:name":"R & S Logistics LLC",
    "wof:placetype":"venue"
},
  "geometry": {"coordinates":[-74.434825,40.217956],"type":"Point"}
}