{
  "type": "Feature",
  "properties": {
    "addr:full":"1050 Broad St Bloomfield NJ 07003",
    "addr:housenumber":"1050",
    "addr:postcode":"07003",
    "addr:street":"Broad St",
    "iso:country":"US",
    "sg:address":"1050 Broad St",
    "sg:city":"Bloomfield",
    "sg:classifiers":[
        {
            "category":"Retail",
            "subcategory":"Auto Repair",
            "type":"Services"
        }
    ],
    "sg:phone":"+1 973 893 9239",
    "sg:postcode":"07003",
    "sg:province":"NJ",
    "wof:name":"J Q Automotive",
    "wof:placetype":"venue"
},
  "geometry": {"coordinates":[-74.186897,40.828098],"type":"Point"}
}