{
  "type": "Feature",
  "properties": {
    "addr:full":"28 Sinnickson Landing Rd Salem NJ 08079",
    "addr:housenumber":"28",
    "addr:postcode":"08079",
    "addr:street":"Sinnickson Landing Rd",
    "iso:country":"US",
    "sg:address":"28 Sinnickson Landing Rd",
    "sg:city":"Salem",
    "sg:classifiers":[
        {
            "category":"Personal",
            "subcategory":"Barber",
            "type":"Services"
        }
    ],
    "sg:phone":"+1 856 935 3633",
    "sg:postcode":"08079",
    "sg:province":"NJ",
    "sg:tags":[
        "shop"
    ],
    "wof:name":"Bill's Barber Shop",
    "wof:placetype":"venue"
},
  "geometry": {"coordinates":[-75.495015,39.571387],"type":"Point"}
}