{
  "type": "Feature",
  "properties": {
    "iso:country":"US",
    "sg:address":"15 3rd Ave",
    "sg:city":"Garwood",
    "sg:classifiers":[
        {
            "category":"Arts & Performance",
            "subcategory":"Theater",
            "type":"Entertainment"
        }
    ],
    "sg:phone":"+1 732 680 0333",
    "sg:postcode":"07027",
    "sg:province":"NJ",
    "sg:tags":[
        "live",
        "music"
    ],
    "sg:website":"www.partyhostdjs.com",
    "wof:name":"Party Host DJS",
    "wof:placetype":"venue"
},
  "geometry": {"coordinates":[-74.320103,40.655938],"type":"Point"}
}