{
  "type": "Feature",
  "properties": {
    "iso:country":"US",
    "sg:address":"715 Comly Ave",
    "sg:city":"Collingswood",
    "sg:classifiers":[
        {
            "category":"Professional",
            "subcategory":"Advertising",
            "type":"Services"
        },
        {
            "category":"Communications",
            "type":"Services"
        }
    ],
    "sg:phone":"+1 267 978 2705",
    "sg:postcode":"08107",
    "sg:province":"NJ",
    "sg:tags":[
        "marketing",
        "design",
        "web"
    ],
    "sg:website":"kttks.com",
    "wof:name":"Kronos Technologies",
    "wof:placetype":"venue"
},
  "geometry": {"coordinates":[-75.08660999999999,39.908365],"type":"Point"}
}