{
  "type": "Feature",
  "properties": {
    "addr:full":"35 Beach Rd Monmouth Beach NJ 07750",
    "addr:housenumber":"35",
    "addr:postcode":"07750",
    "addr:street":"Beach Rd",
    "iso:country":"US",
    "sg:address":"35 Beach Rd",
    "sg:city":"Monmouth Beach",
    "sg:classifiers":[
        {
            "category":"Real Estate",
            "subcategory":"Real Estate Agent",
            "type":"Services"
        }
    ],
    "sg:phone":"+1 732 870 2700",
    "sg:postcode":"07750",
    "sg:province":"NJ",
    "wof:name":"Better Homes & Shirvanian Rlty",
    "wof:placetype":"venue"
},
  "geometry": {"coordinates":[-73.981798,40.3309],"type":"Point"}
}