{
  "type": "Feature",
  "properties": {
    "addr:full":"4 Sawmill Rd Vincentown NJ 08088",
    "addr:housenumber":"4",
    "addr:postcode":"08088",
    "addr:street":"Sawmill Rd",
    "iso:country":"US",
    "sg:address":"4 Sawmill Rd",
    "sg:city":"Vincentown",
    "sg:classifiers":[
        {
            "category":"Retail",
            "subcategory":"Auto Repair",
            "type":"Services"
        }
    ],
    "sg:phone":"+1 609 268 9032",
    "sg:postcode":"08088",
    "sg:province":"NJ",
    "sg:tags":[
        "automotive"
    ],
    "wof:name":"S&S Power Haus Auto",
    "wof:placetype":"venue"
},
  "geometry": {"coordinates":[-74.699209,39.863231],"type":"Point"}
}