{
  "type": "Feature",
  "properties": {
    "iso:country":"US",
    "sg:address":"5454 Witherspoon Ave",
    "sg:city":"Pennsauken",
    "sg:classifiers":[
        {
            "category":"Professional",
            "subcategory":"Art Services",
            "type":"Services"
        }
    ],
    "sg:phone":"+1 856 665 3565",
    "sg:postcode":"08109",
    "sg:province":"NJ",
    "sg:tags":[
        "graphic",
        "designer"
    ],
    "wof:name":"Visual Dynamics",
    "wof:placetype":"venue"
},
  "geometry": {"coordinates":[-75.061886,39.934259],"type":"Point"}
}