{
  "type": "Feature",
  "properties": {
    "iso:country":"US",
    "sg:address":"856 US Hwy 206",
    "sg:city":"Hillsborough",
    "sg:classifiers":[
        {
            "category":"Professional",
            "subcategory":"Lawyer & Legal Services",
            "type":"Services"
        }
    ],
    "sg:phone":"+1 908 281 5466",
    "sg:postcode":"08844",
    "sg:province":"NJ",
    "sg:tags":[
        "attorney"
    ],
    "wof:name":"Simpkins & Simpkins",
    "wof:placetype":"venue"
},
  "geometry": {"coordinates":[-74.655129,40.47884],"type":"Point"}
}