{
  "type": "Feature",
  "properties": {
    "iso:country":"US",
    "sg:address":"152 Columbia Ave",
    "sg:city":"Jersey City",
    "sg:classifiers":[
        {
            "category":"Professional",
            "type":"Services"
        }
    ],
    "sg:phone":"+1   ",
    "sg:postcode":"07307",
    "sg:province":"NJ",
    "wof:name":"Techbiz Services Inc",
    "wof:placetype":"venue"
},
  "geometry": {"coordinates":[-74.05236600000001,40.7548],"type":"Point"}
}