{
  "type": "Feature",
  "properties": {
    "iso:country":"US",
    "sg:address":"880 Mount Prospect Ave",
    "sg:city":"Newark",
    "sg:classifiers":[
        {
            "category":"Restaurant",
            "type":"Food & Drink"
        }
    ],
    "sg:phone":"+1 973 482 2821",
    "sg:postcode":"07104",
    "sg:province":"NJ",
    "wof:name":"Lin's Garden Restaurant",
    "wof:placetype":"venue"
},
  "geometry": {"coordinates":[-74.162102,40.782501],"type":"Point"}
}