{
  "type": "Feature",
  "properties": {
    "iso:country":"US",
    "sg:address":"374 Millburn Ave",
    "sg:city":"Millburn",
    "sg:classifiers":[
        {
            "category":"Building & Trades",
            "subcategory":"Construction",
            "type":"Services"
        }
    ],
    "sg:phone":"+1 973 376 7650",
    "sg:postcode":"07041",
    "sg:province":"NJ",
    "sg:tags":[
        "contractor"
    ],
    "sg:website":"www.murrayconstruction.com",
    "wof:name":"Murray Construction Co Inc",
    "wof:placetype":"venue"
},
  "geometry": {"coordinates":[-74.308717,40.723053],"type":"Point"}
}