{
  "type": "Feature",
  "properties": {
    "addr:full":"917 Sturwood Way Lawrenceville NJ 08648",
    "addr:housenumber":"917",
    "addr:postcode":"08648",
    "addr:street":"Sturwood Way",
    "iso:country":"US",
    "sg:address":"917 Sturwood Way",
    "sg:city":"Lawrenceville",
    "sg:classifiers":[
        {
            "category":"Real Estate",
            "subcategory":"Real Estate Operator",
            "type":"Services"
        }
    ],
    "sg:phone":"+1 609 896 2035",
    "sg:postcode":"08648",
    "sg:province":"NJ",
    "sg:tags":[
        "building",
        "apartment"
    ],
    "wof:name":"Sturwood Hamlet Apartments",
    "wof:placetype":"venue"
},
  "geometry": {"coordinates":[-74.74955,40.29238],"type":"Point"}
}