{
  "type": "Feature",
  "properties": {
    "iso:country":"US",
    "sg:address":"5825 Westfield Ave",
    "sg:city":"Pennsauken",
    "sg:classifiers":[
        {
            "category":"Restaurant",
            "type":"Food & Drink"
        }
    ],
    "sg:phone":"+1 856 910 9000",
    "sg:postcode":"08110",
    "sg:province":"NJ",
    "sg:tags":[
        "pizza"
    ],
    "wof:name":"Montegrillo Pizza & Restaurant",
    "wof:placetype":"venue"
},
  "geometry": {"coordinates":[-75.060799,39.9617],"type":"Point"}
}