{
  "type": "Feature",
  "properties": {
    "addr:full":"96 Bergen St Trenton NJ 08648",
    "addr:housenumber":"96",
    "addr:postcode":"08648",
    "addr:street":"Bergen St",
    "iso:country":"US",
    "sg:address":"96 Bergen St",
    "sg:city":"Trenton",
    "sg:classifiers":[
        {
            "category":"Professional",
            "subcategory":"Management & Consulting",
            "type":"Services"
        }
    ],
    "sg:phone":"+1   ",
    "sg:postcode":"08648",
    "sg:province":"NJ",
    "wof:name":"Cec",
    "wof:placetype":"venue"
},
  "geometry": {"coordinates":[-74.74051799999999,40.298393],"type":"Point"}
}