{
  "type": "Feature",
  "properties": {
    "iso:country":"US",
    "sg:address":"17 Center Ave",
    "sg:city":"Leonardo",
    "sg:classifiers":[
        {
            "category":"Professional",
            "subcategory":"Computer Services",
            "type":"Services"
        }
    ],
    "sg:phone":"+1 732 291 5938",
    "sg:postcode":"07737",
    "sg:province":"NJ",
    "sg:tags":[
        "repair"
    ],
    "sg:website":"www.tconnection.com",
    "wof:name":"Connection",
    "wof:placetype":"venue"
},
  "geometry": {"coordinates":[-74.05025999999999,40.418079],"type":"Point"}
}