{
  "type": "Feature",
  "properties": {
    "addr:full":"196 Washington Pl Passaic NJ 07055",
    "addr:housenumber":"196",
    "addr:postcode":"07055",
    "addr:street":"Washington Pl",
    "iso:country":"US",
    "sg:address":"196 Washington Pl",
    "sg:city":"Passaic",
    "sg:classifiers":[
        {
            "category":"Personal",
            "subcategory":"Beauty Salon",
            "type":"Services"
        }
    ],
    "sg:phone":"+1 973 472 2374",
    "sg:postcode":"07055",
    "sg:province":"NJ",
    "sg:tags":[
        "shop"
    ],
    "wof:name":"Guilianas Beauty Salon",
    "wof:placetype":"venue"
},
  "geometry": {"coordinates":[-74.124601,40.861608],"type":"Point"}
}