{
  "type": "Feature",
  "properties": {
    "addr:full":"75 Summit Ave Ste 3 Hackensack NJ 07601",
    "addr:housenumber":"75",
    "addr:postcode":"07601",
    "addr:street":"Summit Ave Ste 3",
    "iso:country":"US",
    "sg:address":"75 Summit Ave Ste 3",
    "sg:city":"Hackensack",
    "sg:classifiers":[
        {
            "category":"Professional",
            "subcategory":"Lawyer & Legal Services",
            "type":"Services"
        }
    ],
    "sg:phone":"+1 201 487 7537",
    "sg:postcode":"07601",
    "sg:province":"NJ",
    "wof:name":"Carilli Albert F ESQ",
    "wof:placetype":"venue"
},
  "geometry": {"coordinates":[-74.058886,40.886815],"type":"Point"}
}