{
  "type": "Feature",
  "properties": {
    "iso:country":"US",
    "sg:address":"293 Main St",
    "sg:city":"Hackettstown",
    "sg:classifiers":[
        {
            "category":"Government",
            "subcategory":"Office",
            "type":"Public Place"
        }
    ],
    "sg:phone":"+1 908 850 5438",
    "sg:postcode":"07840",
    "sg:province":"NJ",
    "wof:name":"Warren County Nutrition",
    "wof:placetype":"venue"
},
  "geometry": {"coordinates":[-74.824817,40.849659],"type":"Point"}
}