{
  "type": "Feature",
  "properties": {
    "iso:country":"US",
    "sg:address":"1509 Arboretum Pkwy",
    "sg:city":"Lakewood",
    "sg:classifiers":[
        {
            "category":"Banks & Credit Unions",
            "subcategory":"Financial Services",
            "type":"Services"
        }
    ],
    "sg:phone":"+1   ",
    "sg:postcode":"08701",
    "sg:province":"NJ",
    "sg:tags":[
        "trust",
        "investment",
        "real estate"
    ],
    "wof:name":"Third Ave Associates Inc",
    "wof:placetype":"venue"
},
  "geometry": {"coordinates":[-74.230574,40.105902],"type":"Point"}
}