{
  "type": "Feature",
  "properties": {
    "iso:country":"US",
    "sg:address":"598 River Rd",
    "sg:city":"Clifton",
    "sg:classifiers":[
        {
            "category":"Professional",
            "subcategory":"Business Services",
            "type":"Services"
        }
    ],
    "sg:phone":"+1   ",
    "sg:postcode":"07014",
    "sg:province":"NJ",
    "wof:name":"Marble & Granite Solutions",
    "wof:placetype":"venue"
},
  "geometry": {"coordinates":[-74.124574,40.835329],"type":"Point"}
}