{
  "type": "Feature",
  "properties": {
    "addr:full":"356 Neptune Dr Manahawkin NJ 08050",
    "addr:housenumber":"356",
    "addr:postcode":"08050",
    "addr:street":"Neptune Dr",
    "iso:country":"US",
    "sg:address":"356 Neptune Dr",
    "sg:city":"Manahawkin",
    "sg:classifiers":[
        {
            "category":"Building & Trades",
            "subcategory":"Construction",
            "type":"Services"
        }
    ],
    "sg:phone":"+1 609 698 9505",
    "sg:postcode":"08050",
    "sg:province":"NJ",
    "sg:tags":[
        "house"
    ],
    "wof:name":"Albanese Builders",
    "wof:placetype":"venue"
},
  "geometry": {"coordinates":[-74.287434,39.743829],"type":"Point"}
}