{
  "type": "Feature",
  "properties": {
    "addr:full":"201 S Washington Ave Cherry Hill NJ 08002",
    "addr:housenumber":"201",
    "addr:postcode":"08002",
    "addr:street":"S Washington Ave",
    "iso:country":"US",
    "sg:address":"201 S Washington Ave",
    "sg:city":"Cherry Hill",
    "sg:classifiers":[
        {
            "category":"Recreation",
            "subcategory":"Amusement Park",
            "type":"Entertainment"
        }
    ],
    "sg:phone":"+1   ",
    "sg:postcode":"08002",
    "sg:province":"NJ",
    "sg:tags":[
        "park"
    ],
    "wof:name":"Manhunt Paintball",
    "wof:placetype":"venue"
},
  "geometry": {"coordinates":[-75.038169,39.917742],"type":"Point"}
}