{
  "type": "Feature",
  "properties": {
    "addr:full":"115 Enterprise Ave S Secaucus NJ 07094",
    "addr:housenumber":"115",
    "addr:postcode":"07094",
    "addr:street":"Enterprise Ave S",
    "iso:country":"US",
    "sg:address":"115 Enterprise Ave S",
    "sg:city":"Secaucus",
    "sg:classifiers":[
        {
            "category":"Wholesale",
            "subcategory":"Groceries",
            "type":"Manufacturing & Wholesale Goods"
        }
    ],
    "sg:phone":"+1 201 770 9130",
    "sg:postcode":"07094",
    "sg:province":"NJ",
    "sg:tags":[
        "gourmet",
        "import",
        "product",
        "distributes",
        "italian"
    ],
    "sg:website":"www.italianproducts.it",
    "wof:name":"Italian Products",
    "wof:placetype":"venue"
},
  "geometry": {"coordinates":[-74.07204,40.776821],"type":"Point"}
}