{
  "type": "Feature",
  "properties": {
    "iso:country":"US",
    "sg:address":"172 Stowaway Rd",
    "sg:city":"Manahawkin",
    "sg:classifiers":[
        {
            "category":"Retail",
            "subcategory":"Repair Shop",
            "type":"Services"
        }
    ],
    "sg:phone":"+1 609 607 0922",
    "sg:postcode":"08050",
    "sg:province":"NJ",
    "sg:tags":[
        "lock",
        "locksmith"
    ],
    "wof:name":"Dependable Safe & Lock LLC",
    "wof:placetype":"venue"
},
  "geometry": {"coordinates":[-74.291538,39.74451],"type":"Point"}
}