{
  "type": "Feature",
  "properties": {
    "addr:full":"255 Broad St Bloomfield NJ 07003",
    "addr:housenumber":"255",
    "addr:postcode":"07003",
    "addr:street":"Broad St",
    "iso:country":"US",
    "sg:address":"255 Broad St",
    "sg:city":"Bloomfield",
    "sg:classifiers":[
        {
            "category":"Health Services",
            "subcategory":"Doctor",
            "type":"Services"
        }
    ],
    "sg:phone":"+1 973 743 2455",
    "sg:postcode":"07003",
    "sg:province":"NJ",
    "sg:tags":[
        "medical"
    ],
    "wof:name":"Napolitano Ralph A MD PA",
    "wof:placetype":"venue"
},
  "geometry": {"coordinates":[-74.195702,40.8027],"type":"Point"}
}