{
  "type": "Feature",
  "properties": {
    "iso:country":"US",
    "sg:address":"12 Century Ct",
    "sg:city":"Montville",
    "sg:classifiers":[
        {
            "category":"Wholesale",
            "subcategory":"Machinery & Supplies",
            "type":"Manufacturing & Wholesale Goods"
        }
    ],
    "sg:phone":"+1 973 394 0450",
    "sg:postcode":"07045",
    "sg:province":"NJ",
    "wof:name":"Bert Mastriani & Co Inc",
    "wof:placetype":"venue"
},
  "geometry": {"coordinates":[-74.358276,40.914281],"type":"Point"}
}