{
  "type": "Feature",
  "properties": {
    "iso:country":"US",
    "sg:address":"737 New Durham Rd",
    "sg:city":"Edison",
    "sg:classifiers":[
        {
            "category":"Building & Trades",
            "subcategory":"Plumbing",
            "type":"Services"
        }
    ],
    "sg:phone":"+1 732 632 9200",
    "sg:postcode":"08817",
    "sg:province":"NJ",
    "sg:tags":[
        "contractor"
    ],
    "wof:name":"Northern Conditioning Inc",
    "wof:placetype":"venue"
},
  "geometry": {"coordinates":[-74.38543300000001,40.54049],"type":"Point"}
}