{
  "type": "Feature",
  "properties": {
    "addr:full":"240 Williams Rd Woodstown NJ 08098",
    "addr:housenumber":"240",
    "addr:postcode":"08098",
    "addr:street":"Williams Rd",
    "iso:country":"US",
    "sg:address":"240 Williams Rd",
    "sg:city":"Woodstown",
    "sg:classifiers":[
        {
            "category":"Building & Trades",
            "subcategory":"Construction",
            "type":"Services"
        }
    ],
    "sg:phone":"+1 856 769 0231",
    "sg:postcode":"08098",
    "sg:province":"NJ",
    "sg:tags":[
        "excavation",
        "contractor"
    ],
    "wof:name":"Shelton Terry Excavating",
    "wof:placetype":"venue"
},
  "geometry": {"coordinates":[-75.31449000000001,39.593326],"type":"Point"}
}