{
  "type": "Feature",
  "properties": {
    "iso:country":"US",
    "sg:address":"244 Dover Rd",
    "sg:city":"Toms River",
    "sg:classifiers":[
        {
            "category":"Building & Trades",
            "subcategory":"Construction",
            "type":"Services"
        }
    ],
    "sg:phone":"+1 732 818 7854",
    "sg:postcode":"08757",
    "sg:province":"NJ",
    "sg:tags":[
        "water",
        "well",
        "drilling"
    ],
    "wof:name":"Well Doctor",
    "wof:placetype":"venue"
},
  "geometry": {"coordinates":[-74.207504,39.942856],"type":"Point"}
}