{
  "type": "Feature",
  "properties": {
    "addr:full":"3219 US Hwy 46 Parsippany NJ 07054",
    "addr:housenumber":"3219",
    "addr:postcode":"07054",
    "addr:street":"Us Hwy 46",
    "iso:country":"US",
    "sg:address":"3219 US Hwy 46",
    "sg:city":"Parsippany",
    "sg:classifiers":[
        {
            "category":"Organizations",
            "subcategory":"Non-profit Organization",
            "type":"Services"
        }
    ],
    "sg:phone":"+1 973 257 7867",
    "sg:postcode":"07054",
    "sg:province":"NJ",
    "sg:tags":[
        "information",
        "treatment",
        "center",
        "smoker"
    ],
    "wof:name":"New Beginnings Laser Therapy",
    "wof:placetype":"venue"
},
  "geometry": {"coordinates":[-74.428623,40.872413],"type":"Point"}
}