{
  "type": "Feature",
  "properties": {
    "addr:full":"605 Orange St Newark NJ 07107",
    "addr:housenumber":"605",
    "addr:postcode":"07107",
    "addr:street":"Orange St",
    "iso:country":"US",
    "sg:address":"605 Orange St",
    "sg:city":"Newark",
    "sg:classifiers":[
        {
            "category":"Freight",
            "type":"Transportation"
        }
    ],
    "sg:phone":"+1 973 649 9211",
    "sg:postcode":"07107",
    "sg:province":"NJ",
    "sg:tags":[
        "operator",
        "local",
        "trucking"
    ],
    "wof:name":"Tommy Solesbee Trucking",
    "wof:placetype":"venue"
},
  "geometry": {"coordinates":[-74.195899,40.755192],"type":"Point"}
}