{
  "type": "Feature",
  "properties": {
    "iso:country":"US",
    "sg:address":"310 W Farms Rd",
    "sg:city":"Farmingdale",
    "sg:classifiers":[
        {
            "category":"Building & Trades",
            "subcategory":"Landscaping Services",
            "type":"Services"
        }
    ],
    "sg:phone":"+1 732 938 7098",
    "sg:postcode":"07727",
    "sg:province":"NJ",
    "sg:tags":[
        "contractor",
        "landscape",
        "maintenance",
        "ground"
    ],
    "wof:name":"Giejda Landscape Contractors",
    "wof:placetype":"venue"
},
  "geometry": {"coordinates":[-74.208713,40.190968],"type":"Point"}
}