{
  "type": "Feature",
  "properties": {
    "iso:country":"US",
    "sg:address":"414 Roselle St",
    "sg:city":"Linden",
    "sg:classifiers":[
        {
            "category":"Wholesale",
            "subcategory":"Machinery & Supplies",
            "type":"Manufacturing & Wholesale Goods"
        }
    ],
    "sg:phone":"+1 908 486 7077",
    "sg:postcode":"07036",
    "sg:province":"NJ",
    "sg:tags":[
        "export"
    ],
    "wof:name":"Polonex Export Inc",
    "wof:placetype":"venue"
},
  "geometry": {"coordinates":[-74.25004,40.637475],"type":"Point"}
}