{
  "type": "Feature",
  "properties": {
    "addr:full":"193 Chambersbridge Rd Brick NJ 08723",
    "addr:housenumber":"193",
    "addr:postcode":"08723",
    "addr:street":"Chambersbridge Rd",
    "iso:country":"US",
    "sg:address":"193 Chambersbridge Rd",
    "sg:city":"Brick",
    "sg:classifiers":[
        {
            "category":"Sports & Exercise",
            "subcategory":"Gym",
            "type":"Entertainment"
        }
    ],
    "sg:phone":"+1   ",
    "sg:postcode":"08723",
    "sg:province":"NJ",
    "sg:tags":[
        "fitness",
        "physical",
        "facility"
    ],
    "sg:website":"www.ballyfitness.com",
    "wof:name":"Bally Total Fitness",
    "wof:placetype":"venue"
},
  "geometry": {"coordinates":[-74.14388599999999,40.064689],"type":"Point"}
}