{
  "type": "Feature",
  "properties": {
    "addr:full":"740 Federal Ave Kenilworth NJ 07033",
    "addr:housenumber":"740",
    "addr:postcode":"07033",
    "addr:street":"Federal Ave",
    "iso:country":"US",
    "sg:address":"740 Federal Ave",
    "sg:city":"Kenilworth",
    "sg:classifiers":[
        {
            "category":"Retail",
            "subcategory":"Auto Repair",
            "type":"Services"
        }
    ],
    "sg:phone":"+1 908 620 1266",
    "sg:postcode":"07033",
    "sg:province":"NJ",
    "sg:tags":[
        "body",
        "shop"
    ],
    "wof:name":"Perfection Plus Auto Body Inc",
    "wof:placetype":"venue"
},
  "geometry": {"coordinates":[-74.2864,40.679001],"type":"Point"}
}