{
  "type": "Feature",
  "properties": {
    "iso:country":"US",
    "sg:address":"7 Barberry Way",
    "sg:city":"Essex Fells",
    "sg:classifiers":[
        {
            "category":"Professional",
            "type":"Services"
        }
    ],
    "sg:phone":"+1   ",
    "sg:postcode":"07021",
    "sg:province":"NJ",
    "wof:name":"American Amputee Foundati",
    "wof:placetype":"venue"
},
  "geometry": {"coordinates":[-74.26477300000001,40.83402],"type":"Point"}
}