{
  "type": "Feature",
  "properties": {
    "iso:country":"US",
    "sg:address":"30 Pemberton Ln",
    "sg:city":"Hightstown",
    "sg:classifiers":[
        {
            "category":"Professional",
            "subcategory":"Accounting & Tax Preparation",
            "type":"Services"
        }
    ],
    "sg:phone":"+1   ",
    "sg:postcode":"08520",
    "sg:province":"NJ",
    "wof:name":"Raymond H Goslin CPA",
    "wof:placetype":"venue"
},
  "geometry": {"coordinates":[-74.53091999999999,40.24151],"type":"Point"}
}