{
  "type": "Feature",
  "properties": {
    "iso:country":"US",
    "sg:address":"557 Elizabeth Ave",
    "sg:city":"Elizabeth",
    "sg:classifiers":[
        {
            "category":"Professional",
            "subcategory":"Employment Agencies",
            "type":"Services"
        }
    ],
    "sg:phone":"+1 908 436 2122",
    "sg:postcode":"07206",
    "sg:province":"NJ",
    "sg:tags":[
        "help",
        "contractor"
    ],
    "wof:name":"Constructo Temps",
    "wof:placetype":"venue"
},
  "geometry": {"coordinates":[-74.199028,40.654933],"type":"Point"}
}