{
  "type": "Feature",
  "properties": {
    "iso:country":"US",
    "sg:address":"535 Locust Rd",
    "sg:city":"Flemington",
    "sg:classifiers":[
        {
            "category":"Professional",
            "subcategory":"Art Services",
            "type":"Services"
        }
    ],
    "sg:phone":"+1   ",
    "sg:postcode":"08822",
    "sg:province":"NJ",
    "sg:tags":[
        "commercial",
        "design"
    ],
    "wof:name":"Karen Peterson Design",
    "wof:placetype":"venue"
},
  "geometry": {"coordinates":[-74.79304,40.551107],"type":"Point"}
}