{
  "type": "Feature",
  "properties": {
    "addr:full":"8014 Tamarron Dr Plainsboro NJ 08536",
    "addr:housenumber":"8014",
    "addr:postcode":"08536",
    "addr:street":"Tamarron Dr",
    "iso:country":"US",
    "sg:address":"8014 Tamarron Dr",
    "sg:city":"Plainsboro",
    "sg:classifiers":[
        {
            "category":"Professional",
            "subcategory":"Computer Services",
            "type":"Services"
        }
    ],
    "sg:phone":"+1 609 750 9629",
    "sg:postcode":"08536",
    "sg:province":"NJ",
    "sg:tags":[
        "prepackaged",
        "software"
    ],
    "wof:name":"Brennan Software Developm",
    "wof:placetype":"venue"
},
  "geometry": {"coordinates":[-74.56397,40.328801],"type":"Point"}
}