{
  "type": "Feature",
  "properties": {
    "iso:country":"US",
    "sg:address":"423 Broad Ave",
    "sg:city":"Palisades Park",
    "sg:classifiers":[
        {
            "category":"Restaurant",
            "type":"Food & Drink"
        }
    ],
    "sg:phone":"+1   ",
    "sg:postcode":"07650",
    "sg:province":"NJ",
    "sg:tags":[
        "eating"
    ],
    "wof:name":"Cafe Piola 46",
    "wof:placetype":"venue"
},
  "geometry": {"coordinates":[-73.99475700000001,40.852399],"type":"Point"}
}