{
  "type": "Feature",
  "properties": {
    "addr:full":"109 N Wood Ave Linden NJ 07036",
    "addr:housenumber":"109",
    "addr:postcode":"07036",
    "addr:street":"N Wood Ave",
    "iso:country":"US",
    "sg:address":"109 N Wood Ave",
    "sg:city":"Linden",
    "sg:classifiers":[
        {
            "category":"Personal",
            "subcategory":"Shoe Repair & Shine",
            "type":"Services"
        }
    ],
    "sg:phone":"+1 908 486 9514",
    "sg:postcode":"07036",
    "sg:province":"NJ",
    "sg:tags":[
        "repairing",
        "boot"
    ],
    "wof:name":"Mancino's Shoe & Leather Repair",
    "wof:placetype":"venue"
},
  "geometry": {"coordinates":[-74.252899,40.630798],"type":"Point"}
}