{
  "type": "Feature",
  "properties": {
    "addr:full":"2628 Nottingham Way Trenton NJ 08619",
    "addr:housenumber":"2628",
    "addr:postcode":"08619",
    "addr:street":"Nottingham Way",
    "iso:country":"US",
    "sg:address":"2628 Nottingham Way",
    "sg:city":"Trenton",
    "sg:classifiers":[
        {
            "category":"Health Services",
            "subcategory":"Doctor",
            "type":"Services"
        }
    ],
    "sg:phone":"+1 609 587 8195",
    "sg:postcode":"08619",
    "sg:province":"NJ",
    "wof:name":"Mary K Flood DDS",
    "wof:placetype":"venue"
},
  "geometry": {"coordinates":[-74.689764,40.236093],"type":"Point"}
}