{
  "type": "Feature",
  "properties": {
    "addr:full":"1820 Frontage Rd Cherry Hill NJ 08034",
    "addr:housenumber":"1820",
    "addr:postcode":"08034",
    "addr:street":"Frontage Rd",
    "iso:country":"US",
    "sg:address":"1820 Frontage Rd",
    "sg:city":"Cherry Hill",
    "sg:classifiers":[
        {
            "category":"Freight",
            "type":"Transportation"
        }
    ],
    "sg:phone":"+1 856 216 9300",
    "sg:postcode":"08034",
    "sg:province":"NJ",
    "sg:tags":[
        "commercial",
        "storage",
        "special"
    ],
    "wof:name":"Citadel Self Storage",
    "wof:placetype":"venue"
},
  "geometry": {"coordinates":[-74.98193000000001,39.916105],"type":"Point"}
}