{
  "type": "Feature",
  "properties": {
    "iso:country":"US",
    "sg:address":"229 Cedar St",
    "sg:city":"South Amboy",
    "sg:classifiers":[
        {
            "category":"Education",
            "subcategory":"School",
            "type":"Public Place"
        }
    ],
    "sg:phone":"+1   ",
    "sg:postcode":"08879",
    "sg:province":"NJ",
    "wof:name":"Sacred Heart School",
    "wof:placetype":"venue"
},
  "geometry": {"coordinates":[-74.29110799999999,40.480892],"type":"Point"}
}