{
  "type": "Feature",
  "properties": {
    "addr:full":"4 Hedgerow Ct Haddon Twp NJ 08107",
    "addr:housenumber":"4",
    "addr:postcode":"08107",
    "addr:street":"Hedgerow Ct",
    "iso:country":"US",
    "sg:address":"4 Hedgerow Ct",
    "sg:city":"Haddon Twp",
    "sg:classifiers":[
        {
            "category":"Food & Beverages",
            "subcategory":"Candy",
            "type":"Retail Goods"
        },
        {
            "category":"Professional",
            "subcategory":"Business Services",
            "type":"Services"
        }
    ],
    "sg:phone":"+1 856 858 9070",
    "sg:postcode":"08107",
    "sg:province":"NJ",
    "sg:tags":[
        "confectionery"
    ],
    "wof:name":"Custom Candy Bar Wrappers",
    "wof:placetype":"venue"
},
  "geometry": {"coordinates":[-75.067922,39.903142],"type":"Point"}
}