{
  "type": "Feature",
  "properties": {
    "iso:country":"US",
    "sg:address":"173 Franklin Ave",
    "sg:city":"Nutley",
    "sg:classifiers":[
        {
            "category":"Home & Garden",
            "subcategory":"Furniture",
            "type":"Retail Goods"
        }
    ],
    "sg:phone":"+1 973 667 4467",
    "sg:postcode":"07110",
    "sg:province":"NJ",
    "sg:tags":[
        "equipment",
        "kitchen",
        "cabinet"
    ],
    "wof:name":"Customs Designs By Sam Inc",
    "wof:placetype":"venue"
},
  "geometry": {"coordinates":[-74.16271500000001,40.814939],"type":"Point"}
}