{
  "type": "Feature",
  "properties": {
    "addr:full":"60 Industrial Rd Lodi NJ 07644",
    "addr:housenumber":"60",
    "addr:postcode":"07644",
    "addr:street":"Industrial Rd",
    "iso:country":"US",
    "sg:address":"60 Industrial Rd",
    "sg:city":"Lodi",
    "sg:classifiers":[
        {
            "category":"Shopping",
            "subcategory":"Books",
            "type":"Retail Goods"
        }
    ],
    "sg:phone":"+1 973 458 8150",
    "sg:postcode":"07644",
    "sg:province":"NJ",
    "sg:tags":[
        "dealer"
    ],
    "wof:name":"Books & Media",
    "wof:placetype":"venue"
},
  "geometry": {"coordinates":[-74.07481,40.884318],"type":"Point"}
}