{
  "type": "Feature",
  "properties": {
    "addr:full":"14 Pinecrest Dr Medford NJ 08055",
    "addr:housenumber":"14",
    "addr:postcode":"08055",
    "addr:street":"Pinecrest Dr",
    "iso:country":"US",
    "sg:address":"14 Pinecrest Dr",
    "sg:city":"Medford",
    "sg:classifiers":[
        {
            "category":"Building & Trades",
            "subcategory":"Plumbing",
            "type":"Services"
        }
    ],
    "sg:phone":"+1 609 953 4037",
    "sg:postcode":"08055",
    "sg:province":"NJ",
    "sg:tags":[
        "heating",
        "contractor"
    ],
    "wof:name":"Tara Heating & Air Condition",
    "wof:placetype":"venue"
},
  "geometry": {"coordinates":[-74.802666,39.845688],"type":"Point"}
}