{
  "type": "Feature",
  "properties": {
    "addr:full":"415 S Washington Ave Bergenfield NJ 07621",
    "addr:housenumber":"415",
    "addr:postcode":"07621",
    "addr:street":"S Washington Ave",
    "iso:country":"US",
    "sg:address":"415 S Washington Ave",
    "sg:city":"Bergenfield",
    "sg:classifiers":[
        {
            "category":"Shopping",
            "subcategory":"Computers & Home Electronics",
            "type":"Retail Goods"
        }
    ],
    "sg:phone":"+1 201 384 5688",
    "sg:postcode":"07621",
    "sg:province":"NJ",
    "sg:tags":[
        "equipment",
        "electronic",
        "supply"
    ],
    "sg:website":"www.radioshack.com",
    "wof:name":"Radio Shack",
    "wof:placetype":"venue"
},
  "geometry": {"coordinates":[-73.997389,40.914476],"type":"Point"}
}