{
  "type": "Feature",
  "properties": {
    "iso:country":"US",
    "sg:address":"652 Rahway Ave",
    "sg:city":"Union",
    "sg:classifiers":[
        {
            "category":"Retail",
            "subcategory":"Laundry & Dry Cleaning",
            "type":"Services"
        }
    ],
    "sg:phone":"+1 908 686 2400",
    "sg:postcode":"07083",
    "sg:province":"NJ",
    "wof:name":"Aqua Dry Systems Llc of Northern Nj",
    "wof:placetype":"venue"
},
  "geometry": {"coordinates":[-74.297303,40.696376],"type":"Point"}
}