{
  "type": "Feature",
  "properties": {
    "iso:country":"US",
    "sg:address":"101 Main St",
    "sg:city":"Sparta",
    "sg:classifiers":[
        {
            "category":"Building & Trades",
            "subcategory":"Cleaning & Sanitation",
            "type":"Services"
        }
    ],
    "sg:phone":"+1 973 729 9573",
    "sg:postcode":"07871",
    "sg:province":"NJ",
    "sg:tags":[
        "maintenance"
    ],
    "wof:name":"Mane Mortgages Svc",
    "wof:placetype":"venue"
},
  "geometry": {"coordinates":[-74.629395,41.042465],"type":"Point"}
}