{
  "type": "Feature",
  "properties": {
    "iso:country":"US",
    "sg:address":"5 Susie Ln",
    "sg:city":"Jackson",
    "sg:classifiers":[
        {
            "category":"Professional",
            "subcategory":"Computer Services",
            "type":"Services"
        }
    ],
    "sg:phone":"+1   ",
    "sg:postcode":"08527",
    "sg:province":"NJ",
    "sg:tags":[
        "accounting",
        "consulting"
    ],
    "wof:name":"Consultant Concepts Inc",
    "wof:placetype":"venue"
},
  "geometry": {"coordinates":[-74.352413,40.109676],"type":"Point"}
}