{
  "type": "Feature",
  "properties": {
    "addr:full":"900 Briggs Rd Mount Laurel NJ 08054",
    "addr:housenumber":"900",
    "addr:postcode":"08054",
    "addr:street":"Briggs Rd",
    "iso:country":"US",
    "sg:address":"900 Briggs Rd",
    "sg:city":"Mount Laurel",
    "sg:classifiers":[
        {
            "category":"Professional",
            "type":"Services"
        }
    ],
    "sg:phone":"+1 856 222 1146",
    "sg:postcode":"08054",
    "sg:province":"NJ",
    "sg:tags":[
        "process",
        "development"
    ],
    "wof:name":"Ptc Technology",
    "wof:placetype":"venue"
},
  "geometry": {"coordinates":[-74.89647600000001,39.974652],"type":"Point"}
}