{
  "type": "Feature",
  "properties": {
    "addr:full":"3 Overhill Rd Belleville NJ 07109",
    "addr:housenumber":"3",
    "addr:postcode":"07109",
    "addr:street":"Overhill Rd",
    "iso:country":"US",
    "sg:address":"3 Overhill Rd",
    "sg:city":"Belleville",
    "sg:classifiers":[
        {
            "category":"Building & Trades",
            "subcategory":"Construction",
            "type":"Services"
        }
    ],
    "sg:phone":"+1 973 857 0507",
    "sg:postcode":"07109",
    "sg:province":"NJ",
    "sg:tags":[
        "waterproofing",
        "contractor"
    ],
    "wof:name":"Graciano Corp",
    "wof:placetype":"venue"
},
  "geometry": {"coordinates":[-74.17474,40.801616],"type":"Point"}
}