{
  "type": "Feature",
  "properties": {
    "iso:country":"US",
    "sg:address":"28 Ramapo Valley Rd",
    "sg:city":"Mahwah",
    "sg:classifiers":[
        {
            "category":"Building & Trades",
            "subcategory":"Landscaping Services",
            "type":"Services"
        }
    ],
    "sg:phone":"+1 201 529 5633",
    "sg:postcode":"07430",
    "sg:province":"NJ",
    "wof:name":"Stephen J Miller Enterprises",
    "wof:placetype":"venue"
},
  "geometry": {"coordinates":[-74.151139,41.105287],"type":"Point"}
}