{
  "type": "Feature",
  "properties": {
    "addr:full":"328 Stokes Ave Trenton NJ 08638",
    "addr:housenumber":"328",
    "addr:postcode":"08638",
    "addr:street":"Stokes Ave",
    "iso:country":"US",
    "sg:address":"328 Stokes Ave",
    "sg:city":"Trenton",
    "sg:classifiers":[
        {
            "category":"Building & Trades",
            "subcategory":"Construction",
            "type":"Services"
        }
    ],
    "sg:phone":"+1 609 882 9234",
    "sg:postcode":"08638",
    "sg:province":"NJ",
    "sg:tags":[
        "house",
        "nonresidential",
        "general",
        "contractor"
    ],
    "wof:name":"Charles Hart Builders",
    "wof:placetype":"venue"
},
  "geometry": {"coordinates":[-74.76446,40.241425],"type":"Point"}
}