{
  "type": "Feature",
  "properties": {
    "iso:country":"US",
    "sg:address":"23 E Seaview Ave",
    "sg:city":"Linwood",
    "sg:classifiers":[
        {
            "category":"Shopping",
            "subcategory":"Crafts & Fabrics",
            "type":"Retail Goods"
        }
    ],
    "sg:phone":"+1   ",
    "sg:postcode":"08221",
    "sg:province":"NJ",
    "sg:tags":[
        "sewing"
    ],
    "wof:name":"Said Sew",
    "wof:placetype":"venue"
},
  "geometry": {"coordinates":[-74.57529100000001,39.334325],"type":"Point"}
}