{
  "type": "Feature",
  "properties": {
    "addr:full":"1 Commerce Dr Barrington NJ 08057",
    "addr:housenumber":"1",
    "addr:postcode":"08057",
    "addr:street":"Commerce Dr",
    "iso:country":"US",
    "sg:address":"1 Commerce Dr",
    "sg:city":"Barrington",
    "sg:classifiers":[
        {
            "category":"Real Estate",
            "subcategory":"Real Estate Operator",
            "type":"Services"
        }
    ],
    "sg:phone":"+1 856 547 9206",
    "sg:postcode":"08057",
    "sg:province":"NJ",
    "sg:tags":[
        "building",
        "parks"
    ],
    "wof:name":"Barrington Business Ctr",
    "wof:placetype":"venue"
},
  "geometry": {"coordinates":[-74.98487799999999,39.968989],"type":"Point"}
}