{
  "type": "Feature",
  "properties": {
    "addr:full":"770 Bloomfield Ave Caldwell NJ 07006",
    "addr:housenumber":"770",
    "addr:postcode":"07006",
    "addr:street":"Bloomfield Ave",
    "iso:country":"US",
    "sg:address":"770 Bloomfield Ave",
    "sg:city":"Caldwell",
    "sg:classifiers":[
        {
            "category":"Shopping",
            "subcategory":"Computers & Home Electronics",
            "type":"Retail Goods"
        }
    ],
    "sg:phone":"+1 973 575 1822",
    "sg:postcode":"07006",
    "sg:province":"NJ",
    "sg:tags":[
        "equipment",
        "electronic",
        "supply"
    ],
    "wof:name":"Radio Shack",
    "wof:placetype":"venue"
},
  "geometry": {"coordinates":[-74.29581,40.850209],"type":"Point"}
}