{
  "type": "Feature",
  "properties": {
    "addr:full":"404 Crestview Ter Brick NJ 08723",
    "addr:housenumber":"404",
    "addr:postcode":"08723",
    "addr:street":"Crestview Ter Brick",
    "iso:country":"US",
    "sg:address":"404 Crestview Ter",
    "sg:city":"Brick",
    "sg:classifiers":[
        {
            "category":"Building & Trades",
            "subcategory":"Construction",
            "type":"Services"
        }
    ],
    "sg:phone":"+1 732 920 5591",
    "sg:postcode":"08723",
    "sg:province":"NJ",
    "sg:tags":[
        "carpentry",
        "contractor"
    ],
    "wof:name":"Beautiful Windows & Doors",
    "wof:placetype":"venue"
},
  "geometry": {"coordinates":[-74.153942,40.047895],"type":"Point"}
}