{
  "type": "Feature",
  "properties": {
    "addr:full":"238 Sutton Dr Berkeley Heights NJ 07922",
    "addr:housenumber":"238",
    "addr:postcode":"07922",
    "addr:street":"Sutton Dr",
    "iso:country":"US",
    "sg:address":"238 Sutton Dr",
    "sg:city":"Berkeley Heights",
    "sg:classifiers":[
        {
            "category":"Shopping",
            "subcategory":"Bicycles & Sporting Goods",
            "type":"Retail Goods"
        }
    ],
    "sg:phone":"+1   ",
    "sg:postcode":"07922",
    "sg:province":"NJ",
    "wof:name":"Michael A Wolhfert",
    "wof:placetype":"venue"
},
  "geometry": {"coordinates":[-74.42782099999999,40.666412],"type":"Point"}
}