{
  "type": "Feature",
  "properties": {
    "iso:country":"US",
    "sg:address":"655 US Highway 46",
    "sg:city":"Little Falls",
    "sg:classifiers":[
        {
            "category":"Restaurant",
            "type":"Food & Drink"
        }
    ],
    "sg:phone":"+1 973 785 1878",
    "sg:postcode":"07424",
    "sg:province":"NJ",
    "sg:website":"www.burgerking.com",
    "wof:name":"Burger King",
    "wof:placetype":"venue"
},
  "geometry": {"coordinates":[-74.20819899999999,40.8811],"type":"Point"}
}