{
  "type": "Feature",
  "properties": {
    "addr:full":"1229 State Rte 23 Wayne NJ 07470",
    "addr:housenumber":"1229",
    "addr:postcode":"07470",
    "addr:street":"State Rte 23",
    "iso:country":"US",
    "sg:address":"1229 State Rte 23",
    "sg:city":"Wayne",
    "sg:classifiers":[
        {
            "category":"Restaurant",
            "type":"Food & Drink"
        }
    ],
    "sg:phone":"+1   ",
    "sg:postcode":"07470",
    "sg:province":"NJ",
    "sg:tags":[
        "eating"
    ],
    "wof:name":"Burger King",
    "wof:placetype":"venue"
},
  "geometry": {"coordinates":[-74.268281,40.924499],"type":"Point"}
}