{
  "type": "Feature",
  "properties": {
    "addr:full":"523 Washington Blvd Sea Girt NJ 08750",
    "addr:housenumber":"523",
    "addr:postcode":"08750",
    "addr:street":"Washington Blvd",
    "iso:country":"US",
    "sg:address":"523 Washington Blvd",
    "sg:city":"Sea Girt",
    "sg:classifiers":[
        {
            "category":"Restaurant",
            "type":"Food & Drink"
        }
    ],
    "sg:phone":"+1 732 449 1717",
    "sg:postcode":"08750",
    "sg:province":"NJ",
    "sg:tags":[
        "luncheonette"
    ],
    "wof:name":"Ray's Cafe",
    "wof:placetype":"venue"
},
  "geometry": {"coordinates":[-74.040746,40.129902],"type":"Point"}
}