{
  "type": "Feature",
  "properties": {
    "iso:country":"US",
    "sg:address":"100 Castle Rd",
    "sg:city":"Secaucus",
    "sg:classifiers":[
        {
            "category":"Manufacturing",
            "subcategory":"Printing",
            "type":"Manufacturing & Wholesale Goods"
        }
    ],
    "sg:phone":"+1 201 863 8100",
    "sg:postcode":"07094",
    "sg:province":"NJ",
    "sg:tags":[
        "lithographer",
        "book",
        "printer"
    ],
    "wof:name":"Command Web Offset Co",
    "wof:placetype":"venue"
},
  "geometry": {"coordinates":[-74.08443699999999,40.773456],"type":"Point"}
}