{
  "type": "Feature",
  "properties": {
    "iso:country":"US",
    "sg:address":"713 Main St",
    "sg:city":"Boonton",
    "sg:classifiers":[
        {
            "category":"Building & Trades",
            "subcategory":"Construction",
            "type":"Services"
        }
    ],
    "sg:phone":"+1   ",
    "sg:postcode":"07005",
    "sg:province":"NJ",
    "sg:tags":[
        "special",
        "contractor"
    ],
    "wof:name":"Poseidon Pool & Spa Inc",
    "wof:placetype":"venue"
},
  "geometry": {"coordinates":[-74.412004,40.905555],"type":"Point"}
}