{
  "type": "Feature",
  "properties": {
    "iso:country":"US",
    "sg:address":"14 Volkmar Pl",
    "sg:city":"Metuchen",
    "sg:classifiers":[
        {
            "category":"Building & Trades",
            "subcategory":"Construction",
            "type":"Services"
        }
    ],
    "sg:phone":"+1 732 548 4652",
    "sg:postcode":"08840",
    "sg:province":"NJ",
    "sg:tags":[
        "carpenter"
    ],
    "wof:name":"ASAP Carpentry",
    "wof:placetype":"venue"
},
  "geometry": {"coordinates":[-74.37204,40.538572],"type":"Point"}
}