{
  "type": "Feature",
  "properties": {
    "iso:country":"US",
    "sg:address":"39 US Hwy 22",
    "sg:city":"Dunellen",
    "sg:classifiers":[
        {
            "category":"Bars & Pubs",
            "type":"Food & Drink"
        }
    ],
    "sg:phone":"+1   ",
    "sg:postcode":"08812",
    "sg:province":"NJ",
    "sg:tags":[
        "drinking"
    ],
    "wof:name":"Players Sports Club",
    "wof:placetype":"venue"
},
  "geometry": {"coordinates":[-74.46642799999999,40.608382],"type":"Point"}
}