{
  "type": "Feature",
  "properties": {
    "addr:full":"8 Mulberry Ln Colts Neck NJ 07722",
    "addr:housenumber":"8",
    "addr:postcode":"07722",
    "addr:street":"Mulberry Ln",
    "iso:country":"US",
    "sg:address":"8 Mulberry Ln",
    "sg:city":"Colts Neck",
    "sg:classifiers":[
        {
            "category":"Health Services",
            "subcategory":"Clinic",
            "type":"Services"
        }
    ],
    "sg:phone":"+1 732 772 0444",
    "sg:postcode":"07722",
    "sg:province":"NJ",
    "sg:tags":[
        "home",
        "care"
    ],
    "wof:name":"Mommiecare TLC LLC",
    "wof:placetype":"venue"
},
  "geometry": {"coordinates":[-74.19764000000001,40.326834],"type":"Point"}
}