{
  "type": "Feature",
  "properties": {
    "addr:full":"14 John St Chatham NJ 07928",
    "addr:housenumber":"14",
    "addr:postcode":"07928",
    "addr:street":"John St",
    "iso:country":"US",
    "sg:address":"14 John St",
    "sg:city":"Chatham",
    "sg:classifiers":[
        {
            "category":"Professional",
            "subcategory":"Computer Services",
            "type":"Services"
        }
    ],
    "sg:phone":"+1   ",
    "sg:postcode":"07928",
    "sg:province":"NJ",
    "sg:tags":[
        "related",
        "programing",
        "custom"
    ],
    "wof:name":"Princton Systems Cnsulting Ltd",
    "wof:placetype":"venue"
},
  "geometry": {"coordinates":[-74.38471800000001,40.745555],"type":"Point"}
}