{
  "type": "Feature",
  "properties": {
    "iso:country":"US",
    "sg:address":"1706 N West Blvd",
    "sg:city":"Vineland",
    "sg:classifiers":[
        {
            "category":"Building & Trades",
            "subcategory":"Construction",
            "type":"Services"
        }
    ],
    "sg:phone":"+1 856 692 3335",
    "sg:postcode":"08360",
    "sg:province":"NJ",
    "sg:tags":[
        "contractor"
    ],
    "wof:name":"Foster Construction",
    "wof:placetype":"venue"
},
  "geometry": {"coordinates":[-75.024404,39.510073],"type":"Point"}
}