{
  "type": "Feature",
  "properties": {
    "iso:country":"US",
    "sg:address":"70 Supor Blvd",
    "sg:city":"Harrison",
    "sg:classifiers":[
        {
            "category":"Wholesale",
            "subcategory":"Home Furnishings",
            "type":"Manufacturing & Wholesale Goods"
        }
    ],
    "sg:phone":"+1 973 483 8411",
    "sg:postcode":"07029",
    "sg:province":"NJ",
    "sg:tags":[
        "glass",
        "product",
        "mfg",
        "p"
    ],
    "wof:name":"Eastern Glass Resources Inc",
    "wof:placetype":"venue"
},
  "geometry": {"coordinates":[-74.14783199999999,40.747534],"type":"Point"}
}