{
  "type": "Feature",
  "properties": {
    "addr:full":"355 US Hwy 9 Bayville NJ 08721",
    "addr:housenumber":"355",
    "addr:postcode":"08721",
    "addr:street":"Us Hwy 9",
    "iso:country":"US",
    "sg:address":"355 US Hwy 9",
    "sg:city":"Bayville",
    "sg:classifiers":[
        {
            "category":"Health Services",
            "subcategory":"Doctor",
            "type":"Services"
        }
    ],
    "sg:phone":"+1 732 606 9980",
    "sg:postcode":"08721",
    "sg:province":"NJ",
    "sg:tags":[
        "physician",
        "surgeon"
    ],
    "wof:name":"Center For Physical Medicine",
    "wof:placetype":"venue"
},
  "geometry": {"coordinates":[-74.158987,39.918991],"type":"Point"}
}