{
  "type": "Feature",
  "properties": {
    "addr:full":"1126 Ridge Dr Mountainside NJ 07092",
    "addr:housenumber":"1126",
    "addr:postcode":"07092",
    "addr:street":"Ridge Dr",
    "iso:country":"US",
    "sg:address":"1126 Ridge Dr",
    "sg:city":"Mountainside",
    "sg:classifiers":[
        {
            "category":"Professional",
            "type":"Services"
        }
    ],
    "sg:phone":"+1 908 654 3704",
    "sg:postcode":"07092",
    "sg:province":"NJ",
    "sg:tags":[
        "establishment"
    ],
    "wof:name":"Intermodal Sales Agency",
    "wof:placetype":"venue"
},
  "geometry": {"coordinates":[-74.357788,40.683712],"type":"Point"}
}