{
  "type": "Feature",
  "properties": {
    "iso:country":"US",
    "sg:address":"725 River Rd",
    "sg:city":"Edgewater",
    "sg:classifiers":[
        {
            "category":"Organizations",
            "subcategory":"Non-profit Organization",
            "type":"Services"
        }
    ],
    "sg:phone":"+1 201 945 5885",
    "sg:postcode":"07020",
    "sg:province":"NJ",
    "sg:website":"www.matrixbiologyinstitute.org",
    "wof:name":"Matrix Biology Institute",
    "wof:placetype":"venue"
},
  "geometry": {"coordinates":[-73.979046,40.818479],"type":"Point"}
}