{
  "type": "Feature",
  "properties": {
    "iso:country":"US",
    "sg:address":"594 Cumberland Ave",
    "sg:city":"Teaneck",
    "sg:classifiers":[
        {
            "category":"Professional",
            "subcategory":"Art Services",
            "type":"Services"
        }
    ],
    "sg:phone":"+1   ",
    "sg:postcode":"07666",
    "sg:province":"NJ",
    "sg:tags":[
        "photography",
        "commercial"
    ],
    "wof:name":"Hillary Aiges Represents",
    "wof:placetype":"venue"
},
  "geometry": {"coordinates":[-74.024627,40.89382],"type":"Point"}
}