{
  "type": "Feature",
  "properties": {
    "iso:country":"US",
    "sg:address":"17 Watchung Ave",
    "sg:city":"Chatham",
    "sg:classifiers":[
        {
            "category":"Professional",
            "subcategory":"Lawyer & Legal Services",
            "type":"Services"
        }
    ],
    "sg:phone":"+1 973 635 5668",
    "sg:postcode":"07928",
    "sg:province":"NJ",
    "sg:tags":[
        "attorney"
    ],
    "wof:name":"Mc Quillan Robert E ESQ",
    "wof:placetype":"venue"
},
  "geometry": {"coordinates":[-74.379898,40.729301],"type":"Point"}
}