{
  "type": "Feature",
  "properties": {
    "addr:full":"210 Market St Kenilworth NJ 07033",
    "addr:housenumber":"210",
    "addr:postcode":"07033",
    "addr:street":"Market St",
    "iso:country":"US",
    "sg:address":"210 Market St",
    "sg:city":"Kenilworth",
    "sg:classifiers":[
        {
            "category":"Retail",
            "subcategory":"Repair Shop",
            "type":"Services"
        }
    ],
    "sg:phone":"+1   ",
    "sg:postcode":"07033",
    "sg:province":"NJ",
    "sg:tags":[
        "body",
        "auto"
    ],
    "wof:name":"Four Star TV & Video",
    "wof:placetype":"venue"
},
  "geometry": {"coordinates":[-74.27827000000001,40.669335],"type":"Point"}
}