{
  "type": "Feature",
  "properties": {
    "iso:country":"US",
    "sg:address":"534 Quinton Rd",
    "sg:city":"Salem",
    "sg:classifiers":[
        {
            "category":"Restaurant",
            "type":"Food & Drink"
        }
    ],
    "sg:phone":"+1   ",
    "sg:postcode":"08079",
    "sg:province":"NJ",
    "sg:tags":[
        "eating"
    ],
    "wof:name":"Quinton Diner & Restaurant",
    "wof:placetype":"venue"
},
  "geometry": {"coordinates":[-75.45134,39.561142],"type":"Point"}
}