{
  "type": "Feature",
  "properties": {
    "addr:full":"25 Gray St Montclair NJ 07042",
    "addr:housenumber":"25",
    "addr:postcode":"07042",
    "addr:street":"Gray St",
    "iso:country":"US",
    "sg:address":"25 Gray St",
    "sg:city":"Montclair",
    "sg:classifiers":[
        {
            "category":"Professional",
            "subcategory":"Management & Consulting",
            "type":"Services"
        }
    ],
    "sg:phone":"+1 973 746 9123",
    "sg:postcode":"07042",
    "sg:province":"NJ",
    "wof:name":"J&D Production",
    "wof:placetype":"venue"
},
  "geometry": {"coordinates":[-74.197845,40.82533],"type":"Point"}
}