{
  "type": "Feature",
  "properties": {
    "addr:full":"28 Asbury Ave Linwood NJ 08221",
    "addr:housenumber":"28",
    "addr:postcode":"08221",
    "addr:street":"Asbury Ave",
    "iso:country":"US",
    "sg:address":"28 Asbury Ave",
    "sg:city":"Linwood",
    "sg:classifiers":[
        {
            "category":"Professional",
            "subcategory":"Business Services",
            "type":"Services"
        }
    ],
    "sg:phone":"+1 609 653 9547",
    "sg:postcode":"08221",
    "sg:province":"NJ",
    "sg:tags":[
        "interior",
        "consultant",
        "design",
        "decorator"
    ],
    "wof:name":"Home Couture",
    "wof:placetype":"venue"
},
  "geometry": {"coordinates":[-74.578982,39.337029],"type":"Point"}
}