{
  "type": "Feature",
  "properties": {
    "iso:country":"US",
    "sg:address":"36 W 53rd St",
    "sg:city":"Bayonne",
    "sg:classifiers":[
        {
            "category":"Building & Trades",
            "subcategory":"Construction",
            "type":"Services"
        }
    ],
    "sg:phone":"+1 201 339 2786",
    "sg:postcode":"07002",
    "sg:province":"NJ",
    "sg:tags":[
        "contractor"
    ],
    "wof:name":"Shoreline Contracting LLC",
    "wof:placetype":"venue"
},
  "geometry": {"coordinates":[-74.102057,40.684913],"type":"Point"}
}