{
  "type": "Feature",
  "properties": {
    "addr:full":"712 Springfield Ave Newark NJ 07103",
    "addr:housenumber":"712",
    "addr:postcode":"07103",
    "addr:street":"Springfield Ave",
    "iso:country":"US",
    "sg:address":"712 Springfield Ave",
    "sg:city":"Newark",
    "sg:classifiers":[
        {
            "category":"Social Services",
            "type":"Services"
        }
    ],
    "sg:phone":"+1 973 371 5266",
    "sg:postcode":"07103",
    "sg:province":"NJ",
    "sg:tags":[
        "organization",
        "welfare"
    ],
    "wof:name":"St Rocco's Outreach Ctr",
    "wof:placetype":"venue"
},
  "geometry": {"coordinates":[-74.215226,40.729448],"type":"Point"}
}