{
  "type": "Feature",
  "properties": {
    "addr:full":"29 N Washington Ave Bergenfield NJ 07621",
    "addr:housenumber":"29",
    "addr:postcode":"07621",
    "addr:street":"N Washington Ave",
    "iso:country":"US",
    "sg:address":"29 N Washington Ave",
    "sg:city":"Bergenfield",
    "sg:classifiers":[
        {
            "category":"Organizations",
            "subcategory":"Religious Organization",
            "type":"Services"
        }
    ],
    "sg:phone":"+1 201 384 0101",
    "sg:postcode":"07621",
    "sg:province":"NJ",
    "sg:tags":[
        "church"
    ],
    "sg:website":"www.sjrc.org",
    "wof:name":"St John Evangelist Roman Cthlc",
    "wof:placetype":"venue"
},
  "geometry": {"coordinates":[-73.995862,40.928107],"type":"Point"}
}