{
  "type": "Feature",
  "properties": {
    "addr:full":"48 Lake Valley Rd Morristown NJ 07960",
    "addr:housenumber":"48",
    "addr:postcode":"07960",
    "addr:street":"Lake Valley Rd",
    "iso:country":"US",
    "sg:address":"48 Lake Valley Rd",
    "sg:city":"Morristown",
    "sg:classifiers":[
        {
            "category":"Government",
            "subcategory":"Office",
            "type":"Public Place"
        }
    ],
    "sg:phone":"+1 973 326 7363",
    "sg:postcode":"07960",
    "sg:province":"NJ",
    "sg:tags":[
        "village"
    ],
    "sg:website":"www.morristwp.com",
    "wof:name":"Township-Morris Sewer Plant",
    "wof:placetype":"venue"
},
  "geometry": {"coordinates":[-74.49732,40.814262],"type":"Point"}
}