{
  "type": "Feature",
  "properties": {
    "addr:full":"29 Glenroy Rd S Fairfield NJ 07004",
    "addr:housenumber":"29",
    "addr:postcode":"07004",
    "addr:street":"Glenroy Rd S",
    "iso:country":"US",
    "sg:address":"29 Glenroy Rd S",
    "sg:city":"Fairfield",
    "sg:classifiers":[
        {
            "category":"Professional",
            "subcategory":"Advertising",
            "type":"Services"
        }
    ],
    "sg:phone":"+1 201 655 4198",
    "sg:postcode":"07004",
    "sg:province":"NJ",
    "sg:tags":[
        "mailing",
        "list"
    ],
    "wof:name":"Gt Marketing LTD",
    "wof:placetype":"venue"
},
  "geometry": {"coordinates":[-74.291432,40.889231],"type":"Point"}
}