{
  "type": "Feature",
  "properties": {
    "iso:country":"US",
    "sg:address":"827 Broad St",
    "sg:city":"Shrewsbury",
    "sg:classifiers":[
        {
            "category":"Insurance",
            "subcategory":"Insurance Agent",
            "type":"Services"
        }
    ],
    "sg:phone":"+1 732 747 2900",
    "sg:postcode":"07702",
    "sg:province":"NJ",
    "wof:name":"J R Harrison Agency Inc",
    "wof:placetype":"venue"
},
  "geometry": {"coordinates":[-74.061612,40.325612],"type":"Point"}
}