{
  "type": "Feature",
  "properties": {
    "addr:full":"145 Nedellec Dr Saddle Brook NJ 07663",
    "addr:housenumber":"145",
    "addr:postcode":"07663",
    "addr:street":"Nedellec Dr",
    "iso:country":"US",
    "sg:address":"145 Nedellec Dr",
    "sg:city":"Saddle Brook",
    "sg:classifiers":[
        {
            "category":"Building & Trades",
            "subcategory":"Electrical",
            "type":"Services"
        }
    ],
    "sg:phone":"+1 201 703 0718",
    "sg:postcode":"07663",
    "sg:province":"NJ",
    "sg:tags":[
        "installation",
        "telephone",
        "contractor"
    ],
    "wof:name":"Galluzzo Equipment & Excav",
    "wof:placetype":"venue"
},
  "geometry": {"coordinates":[-74.101551,40.913173],"type":"Point"}
}