{
  "type": "Feature",
  "properties": {
    "iso:country":"US",
    "sg:address":"4 Haelig Ct",
    "sg:city":"Bridgewater",
    "sg:classifiers":[
        {
            "category":"Professional",
            "subcategory":"Management & Consulting",
            "type":"Services"
        }
    ],
    "sg:phone":"+1   ",
    "sg:postcode":"08807",
    "sg:province":"NJ",
    "sg:website":"www.distribution-management.com",
    "wof:name":"Distribution Management Assoc",
    "wof:placetype":"venue"
},
  "geometry": {"coordinates":[-74.57529100000001,40.590429],"type":"Point"}
}