{
  "type": "Feature",
  "properties": {
    "iso:country":"US",
    "sg:address":"81 Akron Ave",
    "sg:city":"Haddon Twp",
    "sg:classifiers":[
        {
            "category":"Building & Trades",
            "subcategory":"Construction",
            "type":"Services"
        }
    ],
    "sg:phone":"+1 856 858 9466",
    "sg:postcode":"08108",
    "sg:province":"NJ",
    "sg:tags":[
        "roofing",
        "contractor"
    ],
    "wof:name":"R J Miller Roofing & Constr",
    "wof:placetype":"venue"
},
  "geometry": {"coordinates":[-75.048732,39.917494],"type":"Point"}
}