{
  "type": "Feature",
  "properties": {
    "iso:country":"US",
    "sg:address":"2603 River Rd",
    "sg:city":"Cinnaminson",
    "sg:classifiers":[
        {
            "category":"Manufacturing",
            "subcategory":"Tools & Machinery",
            "type":"Manufacturing & Wholesale Goods"
        }
    ],
    "sg:phone":"+1 856 303 0496",
    "sg:postcode":"08077",
    "sg:province":"NJ",
    "sg:tags":[
        "die",
        "maker"
    ],
    "wof:name":"LIT Industries",
    "wof:placetype":"venue"
},
  "geometry": {"coordinates":[-74.989976,40.022787],"type":"Point"}
}