{
  "type": "Feature",
  "properties": {
    "iso:country":"US",
    "sg:address":"11 New St",
    "sg:city":"New Brunswick",
    "sg:classifiers":[
        {
            "category":"Professional",
            "type":"Services"
        }
    ],
    "sg:phone":"+1 908 355 6309",
    "sg:postcode":"08901",
    "sg:province":"NJ",
    "sg:tags":[
        "establishment"
    ],
    "wof:name":"Bastardo J Accordion Studio",
    "wof:placetype":"venue"
},
  "geometry": {"coordinates":[-74.440319,40.492528],"type":"Point"}
}