{
  "type": "Feature",
  "properties": {
    "iso:country":"US",
    "sg:address":"39 Libra Ln",
    "sg:city":"Sewell",
    "sg:classifiers":[
        {
            "category":"Retail",
            "subcategory":"Funeral Services",
            "type":"Services"
        }
    ],
    "sg:phone":"+1   ",
    "sg:postcode":"08080",
    "sg:province":"NJ",
    "wof:name":"Think Ink",
    "wof:placetype":"venue"
},
  "geometry": {"coordinates":[-75.07006800000001,39.726829],"type":"Point"}
}