{
  "type": "Feature",
  "properties": {
    "iso:country":"US",
    "sg:address":"411 W Atlantic Ave",
    "sg:city":"Atco",
    "sg:classifiers":[
        {
            "category":"Retail",
            "subcategory":"Auto Repair",
            "type":"Services"
        }
    ],
    "sg:phone":"+1 856 767 9072",
    "sg:postcode":"08004",
    "sg:province":"NJ",
    "sg:tags":[
        "body"
    ],
    "wof:name":"D & J Auto Body",
    "wof:placetype":"venue"
},
  "geometry": {"coordinates":[-74.888689,39.77037],"type":"Point"}
}