{
  "type": "Feature",
  "properties": {
    "iso:country":"US",
    "sg:address":"157 Veterans Dr",
    "sg:city":"Northvale",
    "sg:classifiers":[
        {
            "category":"Professional",
            "subcategory":"Management & Consulting",
            "type":"Services"
        },
        {
            "category":"Professional",
            "subcategory":"Advertising",
            "type":"Services"
        }
    ],
    "sg:phone":"+1 201 750 5050",
    "sg:postcode":"07647",
    "sg:province":"NJ",
    "sg:tags":[
        "marketing",
        "program",
        "consultant"
    ],
    "sg:website":"http://www.staffordworldwide.com",
    "wof:name":"Stafford Worldwide Marketing",
    "wof:placetype":"venue"
},
  "geometry": {"coordinates":[-73.946995,41.00092],"type":"Point"}
}