{
  "type": "Feature",
  "properties": {
    "iso:country":"US",
    "sg:address":"599 Clifton Ave",
    "sg:city":"Clifton",
    "sg:classifiers":[
        {
            "category":"Shopping",
            "subcategory":"Mobile Phones",
            "type":"Retail Goods"
        }
    ],
    "sg:phone":"+1 973 928 2021",
    "sg:postcode":"07011",
    "sg:province":"NJ",
    "wof:name":"E Wireless Wholesale of Nj",
    "wof:placetype":"venue"
},
  "geometry": {"coordinates":[-74.151606,40.87284],"type":"Point"}
}