{
  "type": "Feature",
  "properties": {
    "addr:full":"270 US Hwy 206 Flanders NJ 07836",
    "addr:housenumber":"270",
    "addr:postcode":"07836",
    "addr:street":"Us Hwy 206",
    "iso:country":"US",
    "sg:address":"270 US Hwy 206",
    "sg:city":"Flanders",
    "sg:classifiers":[
        {
            "category":"Building & Trades",
            "subcategory":"Plumbing",
            "type":"Services"
        }
    ],
    "sg:phone":"+1 973 927 3525",
    "sg:postcode":"07836",
    "sg:province":"NJ",
    "sg:tags":[
        "boiler",
        "cleaning"
    ],
    "wof:name":"Alpha Combustion Corp",
    "wof:placetype":"venue"
},
  "geometry": {"coordinates":[-74.709827,40.834626],"type":"Point"}
}