{
  "type": "Feature",
  "properties": {
    "addr:full":"1992 US Hwy 9 Toms River NJ 08755",
    "addr:housenumber":"1992",
    "addr:postcode":"08755",
    "addr:street":"Us Hwy 9",
    "iso:country":"US",
    "sg:address":"1992 US Hwy 9",
    "sg:city":"Toms River",
    "sg:classifiers":[
        {
            "category":"Retail",
            "subcategory":"Repair Shop",
            "type":"Services"
        }
    ],
    "sg:phone":"+1 732 905 7740",
    "sg:postcode":"08755",
    "sg:province":"NJ",
    "sg:tags":[
        "welding"
    ],
    "wof:name":"Gnn Co LLC",
    "wof:placetype":"venue"
},
  "geometry": {"coordinates":[-74.222053,40.024871],"type":"Point"}
}