{
  "type": "Feature",
  "properties": {
    "iso:country":"US",
    "sg:address":"234 Ferry St",
    "sg:city":"Newark",
    "sg:classifiers":[
        {
            "category":"Food & Beverages",
            "subcategory":"Specialty",
            "type":"Retail Goods"
        }
    ],
    "sg:phone":"+1   ",
    "sg:postcode":"07105",
    "sg:province":"NJ",
    "sg:tags":[
        "health",
        "vitamin"
    ],
    "wof:name":"Health Place",
    "wof:placetype":"venue"
},
  "geometry": {"coordinates":[-74.153706,40.7283],"type":"Point"}
}