{
  "type": "Feature",
  "properties": {
    "addr:full":"602 Franklin Blvd Somerset NJ 08873",
    "addr:housenumber":"602",
    "addr:postcode":"08873",
    "addr:street":"Franklin Blvd",
    "iso:country":"US",
    "sg:address":"602 Franklin Blvd",
    "sg:city":"Somerset",
    "sg:classifiers":[
        {
            "category":"Government",
            "subcategory":"Post Office",
            "type":"Public Place"
        }
    ],
    "sg:phone":"+1 732 846 0732",
    "sg:postcode":"08873",
    "sg:province":"NJ",
    "sg:tags":[
        "postal",
        "us"
    ],
    "wof:name":"US Post Office",
    "wof:placetype":"venue"
},
  "geometry": {"coordinates":[-74.483344,40.488268],"type":"Point"}
}