{
  "type": "Feature",
  "properties": {
    "addr:full":"30 Newport Pkwy Jersey City NJ 07310",
    "addr:housenumber":"30",
    "addr:postcode":"07310",
    "addr:street":"Newport Pkwy",
    "iso:country":"US",
    "sg:address":"30 Newport Pkwy",
    "sg:city":"Jersey City",
    "sg:classifiers":[
        {
            "category":"Building & Trades",
            "subcategory":"Construction",
            "type":"Services"
        }
    ],
    "sg:phone":"+1 866 936 8160",
    "sg:postcode":"07310",
    "sg:province":"NJ",
    "sg:tags":[
        "contractor"
    ],
    "sg:website":"homeremodelingjerseycity.com#cid...",
    "wof:name":"That's My Concierge, LLC",
    "wof:placetype":"venue"
},
  "geometry": {"coordinates":[-74.033744,40.729655],"type":"Point"}
}