{
  "type": "Feature",
  "properties": {
    "addr:full":"3 Deal Lake Ct Asbury Park NJ 07712",
    "addr:housenumber":"3",
    "addr:postcode":"07712",
    "addr:street":"Deal Lake Ct Asbury",
    "iso:country":"US",
    "sg:address":"3 Deal Lake Ct",
    "sg:city":"Asbury Park",
    "sg:classifiers":[
        {
            "category":"Communications",
            "subcategory":"Radio Station",
            "type":"Services"
        }
    ],
    "sg:phone":"+1 732 774 0779",
    "sg:postcode":"07712",
    "sg:province":"NJ",
    "sg:tags":[
        "company",
        "broadcasting"
    ],
    "wof:name":"Restore By The Shore",
    "wof:placetype":"venue"
},
  "geometry": {"coordinates":[-74.00138200000001,40.229666],"type":"Point"}
}