{
  "type": "Feature",
  "properties": {
    "addr:full":"18 W Main St Penns Grove NJ 08069",
    "addr:housenumber":"18",
    "addr:postcode":"08069",
    "addr:street":"W Main St",
    "iso:country":"US",
    "sg:address":"18 W Main St",
    "sg:city":"Penns Grove",
    "sg:classifiers":[
        {
            "category":"Organizations",
            "subcategory":"Religious Organization",
            "type":"Services"
        }
    ],
    "sg:phone":"+1 856 351 1755",
    "sg:postcode":"08069",
    "sg:province":"NJ",
    "sg:tags":[
        "used",
        "merchandise",
        "church"
    ],
    "wof:name":"Friendship Mnnonite Thrift Str",
    "wof:placetype":"venue"
},
  "geometry": {"coordinates":[-75.46874200000001,39.730014],"type":"Point"}
}