{
  "type": "Feature",
  "properties": {
    "iso:country":"US",
    "sg:address":"610 Central Ave",
    "sg:city":"East Orange",
    "sg:classifiers":[
        {
            "category":"Food & Beverages",
            "subcategory":"Groceries & Convenience Stores",
            "type":"Retail Goods"
        }
    ],
    "sg:phone":"+1 973 674 3777",
    "sg:postcode":"07018",
    "sg:province":"NJ",
    "wof:name":"Metro Variety",
    "wof:placetype":"venue"
},
  "geometry": {"coordinates":[-74.225368,40.762251],"type":"Point"}
}