{
  "type": "Feature",
  "properties": {
    "addr:full":"65 Violet Ct Toms River NJ 08753",
    "addr:housenumber":"65",
    "addr:postcode":"08753",
    "addr:street":"Violet Ct",
    "iso:country":"US",
    "sg:address":"65 Violet Ct",
    "sg:city":"Toms River",
    "sg:classifiers":[
        {
            "category":"Building & Trades",
            "subcategory":"Construction",
            "type":"Services"
        }
    ],
    "sg:phone":"+1 732 255 4042",
    "sg:postcode":"08753",
    "sg:province":"NJ",
    "sg:tags":[
        "concrete",
        "contractor"
    ],
    "wof:name":"Demac Concrete Inc",
    "wof:placetype":"venue"
},
  "geometry": {"coordinates":[-74.190196,39.97977],"type":"Point"}
}