{
  "type": "Feature",
  "properties": {
    "addr:full":"56 S Talmadge St New Brunswick NJ 08901",
    "addr:housenumber":"56",
    "addr:postcode":"08901",
    "addr:street":"S Talmadge St",
    "iso:country":"US",
    "sg:address":"56 S Talmadge St",
    "sg:city":"New Brunswick",
    "sg:classifiers":[
        {
            "category":"Organizations",
            "subcategory":"Religious Organization",
            "type":"Services"
        }
    ],
    "sg:phone":"+1   ",
    "sg:postcode":"08901",
    "sg:province":"NJ",
    "wof:name":"Sisters of Charity St El Iz",
    "wof:placetype":"venue"
},
  "geometry": {"coordinates":[-74.44328899999999,40.477071],"type":"Point"}
}