{
  "type": "Feature",
  "properties": {
    "iso:country":"US",
    "sg:address":"100 Randolph Ave",
    "sg:city":"Dover",
    "sg:classifiers":[
        {
            "category":"Restaurant",
            "type":"Food & Drink"
        }
    ],
    "sg:phone":"+1 973 328 8391",
    "sg:postcode":"07803",
    "sg:province":"NJ",
    "sg:tags":[
        "eating"
    ],
    "wof:name":"Joanne's Restaurant",
    "wof:placetype":"venue"
},
  "geometry": {"coordinates":[-74.595821,40.875347],"type":"Point"}
}