{
  "type": "Feature",
  "properties": {
    "iso:country":"US",
    "sg:address":"1 Allison Dr",
    "sg:city":"East Brunswick",
    "sg:classifiers":[
        {
            "category":"Professional",
            "type":"Services"
        }
    ],
    "sg:phone":"+1   ",
    "sg:postcode":"08816",
    "sg:province":"NJ",
    "wof:name":"Dollar Lot Inc",
    "wof:placetype":"venue"
},
  "geometry": {"coordinates":[-74.36947499999999,40.420852],"type":"Point"}
}