{
  "type": "Feature",
  "properties": {
    "iso:country":"US",
    "sg:address":"615 23rd St",
    "sg:city":"Union City",
    "sg:classifiers":[
        {
            "category":"Health Services",
            "subcategory":"Nursing And Care Facility",
            "type":"Services"
        }
    ],
    "sg:phone":"+1 201 348 0818",
    "sg:postcode":"07087",
    "sg:province":"NJ",
    "sg:tags":[
        "home",
        "skilled",
        "convalescent"
    ],
    "wof:name":"Castle Hill Health Care Inc",
    "wof:placetype":"venue"
},
  "geometry": {"coordinates":[-74.035051,40.767772],"type":"Point"}
}