{
  "type": "Feature",
  "properties": {
    "addr:full":"88 Alexandria Dr Englishtown NJ 07726",
    "addr:housenumber":"88",
    "addr:postcode":"07726",
    "addr:street":"Alexandria Dr",
    "iso:country":"US",
    "sg:address":"88 Alexandria Dr",
    "sg:city":"Englishtown",
    "sg:classifiers":[
        {
            "category":"Professional",
            "subcategory":"Business Services",
            "type":"Services"
        }
    ],
    "sg:phone":"+1   ",
    "sg:postcode":"07726",
    "sg:province":"NJ",
    "wof:name":"In Pacific Commercial Alliance",
    "wof:placetype":"venue"
},
  "geometry": {"coordinates":[-74.315079,40.291316],"type":"Point"}
}