{
  "type": "Feature",
  "properties": {
    "addr:full":"97 Petticoat Ln Annandale NJ 08801",
    "addr:housenumber":"97",
    "addr:postcode":"08801",
    "addr:street":"Petticoat Ln",
    "iso:country":"US",
    "sg:address":"97 Petticoat Ln",
    "sg:city":"Annandale",
    "sg:classifiers":[
        {
            "category":"Utilities",
            "subcategory":"Refuse",
            "type":"Services"
        }
    ],
    "sg:phone":"+1 908 236 9088",
    "sg:postcode":"08801",
    "sg:province":"NJ",
    "sg:tags":[
        "garbage",
        "collection"
    ],
    "wof:name":"Waste Management Inc",
    "wof:placetype":"venue"
},
  "geometry": {"coordinates":[-74.856424,40.666853],"type":"Point"}
}