{
  "type": "Feature",
  "properties": {
    "iso:country":"US",
    "sg:address":"385 Saint Georges Ave",
    "sg:city":"Rahway",
    "sg:classifiers":[
        {
            "category":"Home & Garden",
            "subcategory":"Carpets & Floor Coverings",
            "type":"Retail Goods"
        }
    ],
    "sg:phone":"+1 732 499 8221",
    "sg:postcode":"07065",
    "sg:province":"NJ",
    "sg:tags":[
        "carpeting"
    ],
    "wof:name":"West Carpets Inc",
    "wof:placetype":"venue"
},
  "geometry": {"coordinates":[-74.290497,40.597301],"type":"Point"}
}