{
  "type": "Feature",
  "properties": {
    "addr:full":"20 Oak Ave West Orange NJ 07052",
    "addr:housenumber":"20",
    "addr:postcode":"07052",
    "addr:street":"Oak Ave",
    "iso:country":"US",
    "sg:address":"20 Oak Ave",
    "sg:city":"West Orange",
    "sg:classifiers":[
        {
            "category":"Professional",
            "subcategory":"Management & Consulting",
            "type":"Services"
        }
    ],
    "sg:phone":"+1   ",
    "sg:postcode":"07052",
    "sg:province":"NJ",
    "sg:tags":[
        "business"
    ],
    "wof:name":"A G K Associates Inc",
    "wof:placetype":"venue"
},
  "geometry": {"coordinates":[-74.274385,40.764075],"type":"Point"}
}