{
  "type": "Feature",
  "properties": {
    "iso:country":"US",
    "sg:address":"27 Appleton Pl",
    "sg:city":"Montclair",
    "sg:classifiers":[
        {
            "category":"Building & Trades",
            "subcategory":"Construction",
            "type":"Services"
        }
    ],
    "sg:phone":"+1 973 746 7013",
    "sg:postcode":"07043",
    "sg:province":"NJ",
    "sg:tags":[
        "contractor"
    ],
    "wof:name":"McGurk Thomas Builders",
    "wof:placetype":"venue"
},
  "geometry": {"coordinates":[-74.207703,40.832802],"type":"Point"}
}