{
  "type": "Feature",
  "properties": {
    "addr:full":"313 Elm Ct Brick NJ 08723",
    "addr:housenumber":"313",
    "addr:postcode":"08723",
    "addr:street":"Elm Ct",
    "iso:country":"US",
    "sg:address":"313 Elm Ct",
    "sg:city":"Brick",
    "sg:classifiers":[
        {
            "category":"Real Estate",
            "subcategory":"Surveying",
            "type":"Services"
        }
    ],
    "sg:phone":"+1 732 477 2723",
    "sg:postcode":"08723",
    "sg:province":"NJ",
    "wof:name":"DSV Assoc",
    "wof:placetype":"venue"
},
  "geometry": {"coordinates":[-74.114693,40.04069],"type":"Point"}
}