{
  "type": "Feature",
  "properties": {
    "addr:full":"24 Park West Orange NJ 07052",
    "addr:housenumber":"24",
    "addr:postcode":"07052",
    "addr:street":"Park",
    "iso:country":"US",
    "sg:address":"24 Park",
    "sg:city":"West Orange",
    "sg:classifiers":[
        {
            "category":"Health Services",
            "subcategory":"Doctor",
            "type":"Services"
        }
    ],
    "sg:phone":"+1 973 669 0878",
    "sg:postcode":"07052",
    "sg:province":"NJ",
    "wof:name":"Zisis Eleftherios MD",
    "wof:placetype":"venue"
},
  "geometry": {"coordinates":[-74.257401,40.786499],"type":"Point"}
}