{
  "type": "Feature",
  "properties": {
    "iso:country":"US",
    "sg:address":"75 Gorge Rd",
    "sg:city":"Edgewater",
    "sg:classifiers":[
        {
            "category":"Professional",
            "subcategory":"Accounting & Tax Preparation",
            "type":"Services"
        }
    ],
    "sg:phone":"+1 201 313 1100",
    "sg:postcode":"07020",
    "sg:province":"NJ",
    "sg:tags":[
        "return",
        "filing"
    ],
    "wof:name":"R C Financial",
    "wof:placetype":"venue"
},
  "geometry": {"coordinates":[-73.99163,40.808498],"type":"Point"}
}