{
  "type": "Feature",
  "properties": {
    "iso:country":"US",
    "sg:address":"490 Hendricks Cswy",
    "sg:city":"Ridgefield",
    "sg:classifiers":[
        {
            "category":"Wholesale",
            "subcategory":"Hardware",
            "type":"Manufacturing & Wholesale Goods"
        }
    ],
    "sg:phone":"+1 201 941 0711",
    "sg:postcode":"07657",
    "sg:province":"NJ",
    "sg:tags":[
        "water",
        "equipment",
        "purification"
    ],
    "wof:name":"U S Filter Iron/Pure Inc",
    "wof:placetype":"venue"
},
  "geometry": {"coordinates":[-74.017751,40.837208],"type":"Point"}
}