{
  "type": "Feature",
  "properties": {
    "iso:country":"US",
    "sg:address":"3805 State Rte 33",
    "sg:city":"Neptune City",
    "sg:classifiers":[
        {
            "category":"Travel",
            "subcategory":"Travel Agent",
            "type":"Entertainment"
        }
    ],
    "sg:phone":"+1 732 918 1900",
    "sg:postcode":"07753",
    "sg:province":"NJ",
    "sg:tags":[
        "agency",
        "bureau"
    ],
    "wof:name":"Fantasy Travel",
    "wof:placetype":"venue"
},
  "geometry": {"coordinates":[-74.093011,40.211203],"type":"Point"}
}