{
  "type": "Feature",
  "properties": {
    "iso:country":"US",
    "sg:address":"500 Park Rd",
    "sg:city":"Cherry Hill",
    "sg:classifiers":[
        {
            "category":"Education",
            "subcategory":"School",
            "type":"Public Place"
        }
    ],
    "sg:phone":"+1   ",
    "sg:postcode":"08034",
    "sg:province":"NJ",
    "sg:tags":[
        "elementary",
        "secondary",
        "private",
        "for",
        "combined"
    ],
    "wof:name":"Cherry Hill Group Home",
    "wof:placetype":"venue"
},
  "geometry": {"coordinates":[-74.983728,39.918501],"type":"Point"}
}