{
  "type": "Feature",
  "properties": {
    "addr:full":"29 Myrtle Ave Edgewater NJ 07020",
    "addr:housenumber":"29",
    "addr:postcode":"07020",
    "addr:street":"Myrtle Ave",
    "iso:country":"US",
    "sg:address":"29 Myrtle Ave",
    "sg:city":"Edgewater",
    "sg:classifiers":[
        {
            "category":"Personal",
            "subcategory":"Beauty Salon",
            "type":"Services"
        }
    ],
    "sg:phone":"+1 201 886 8741",
    "sg:postcode":"07020",
    "sg:province":"NJ",
    "sg:tags":[
        "shop"
    ],
    "wof:name":"Beauty & Beast",
    "wof:placetype":"venue"
},
  "geometry": {"coordinates":[-73.971771,40.836404],"type":"Point"}
}