{
  "type": "Feature",
  "properties": {
    "addr:full":"630 Herman Rd Jackson NJ 08527",
    "addr:housenumber":"630",
    "addr:postcode":"08527",
    "addr:street":"Herman Rd",
    "iso:country":"US",
    "sg:address":"630 Herman Rd",
    "sg:city":"Jackson",
    "sg:classifiers":[
        {
            "category":"Banks & Credit Unions",
            "subcategory":"Bank",
            "type":"Services"
        }
    ],
    "sg:phone":"+1 732 833 6350",
    "sg:postcode":"08527",
    "sg:province":"NJ",
    "sg:tags":[
        "loan"
    ],
    "wof:name":"Corner Stone Equity Group",
    "wof:placetype":"venue"
},
  "geometry": {"coordinates":[-74.336521,40.153033],"type":"Point"}
}