{
  "type": "Feature",
  "properties": {
    "iso:country":"US",
    "sg:address":"161 Main Rd",
    "sg:city":"Montville",
    "sg:classifiers":[
        {
            "category":"Professional",
            "subcategory":"Management & Consulting",
            "type":"Services"
        }
    ],
    "sg:phone":"+1   ",
    "sg:postcode":"07045",
    "sg:province":"NJ",
    "wof:name":"Diversified Fincl Svcs Group",
    "wof:placetype":"venue"
},
  "geometry": {"coordinates":[-74.379262,40.915264],"type":"Point"}
}