{
  "type": "Feature",
  "properties": {
    "iso:country":"US",
    "sg:address":"10 Commerce Ct",
    "sg:city":"Newark",
    "sg:classifiers":[
        {
            "category":"Social Services",
            "subcategory":"Child Care",
            "type":"Services"
        }
    ],
    "sg:phone":"+1 973 639 6622",
    "sg:postcode":"07102",
    "sg:province":"NJ",
    "sg:tags":[
        "day"
    ],
    "wof:name":"Mt Carmel Guild Preschool",
    "wof:placetype":"venue"
},
  "geometry": {"coordinates":[-74.169935,40.737043],"type":"Point"}
}