{
  "type": "Feature",
  "properties": {
    "addr:full":"11 Riverside Dr Hackettstown NJ 07834",
    "addr:housenumber":"11",
    "addr:postcode":"07834",
    "addr:street":"Riverside Dr",
    "iso:country":"US",
    "sg:address":"11 Riverside Dr",
    "sg:city":"Hackettstown",
    "sg:classifiers":[
        {
            "category":"Professional",
            "type":"Services"
        },
        {
            "category":"Shopping",
            "subcategory":"Gifts & Souvenirs",
            "type":"Retail Goods"
        }
    ],
    "sg:phone":"+1 908 850 8942",
    "sg:postcode":"07834",
    "sg:province":"NJ",
    "sg:tags":[
        "shop"
    ],
    "wof:name":"What In The World",
    "wof:placetype":"venue"
},
  "geometry": {"coordinates":[-74.475212,40.896523],"type":"Point"}
}