{
  "type": "Feature",
  "properties": {
    "addr:full":"756 Memorial Pkwy Phillipsburg NJ 08865",
    "addr:housenumber":"756",
    "addr:postcode":"08865",
    "addr:street":"Memorial Pkwy",
    "iso:country":"US",
    "sg:address":"756 Memorial Pkwy",
    "sg:city":"Phillipsburg",
    "sg:classifiers":[
        {
            "category":"Banks & Credit Unions",
            "subcategory":"Investment Brokerage",
            "type":"Services"
        },
        {
            "category":"Shopping",
            "subcategory":"Computers & Home Electronics",
            "type":"Retail Goods"
        }
    ],
    "sg:phone":"+1 908 454 3110",
    "sg:postcode":"08865",
    "sg:province":"NJ",
    "sg:tags":[
        "dvd",
        "video",
        "tape",
        "sale",
        "dvds-rental"
    ],
    "sg:website":"http://www.blockbuster.com",
    "wof:name":"Blockbuster Video",
    "wof:placetype":"venue"
},
  "geometry": {"coordinates":[-75.174522,40.697701],"type":"Point"}
}