{
  "type": "Feature",
  "properties": {
    "addr:full":"201 Railroad Ave Ste 500 East Rutherford NJ 07073",
    "addr:housenumber":"201",
    "addr:postcode":"07073",
    "addr:street":"Railroad Ave Ste 500",
    "iso:country":"US",
    "sg:address":"201 Railroad Ave Ste 500",
    "sg:city":"East Rutherford",
    "sg:classifiers":[
        {
            "category":"Arts & Performance",
            "subcategory":"Music",
            "type":"Entertainment"
        }
    ],
    "sg:phone":"+1 201 933 8070",
    "sg:postcode":"07073",
    "sg:province":"NJ",
    "sg:tags":[
        "dj"
    ],
    "wof:name":"Jam Music Entertainment",
    "wof:placetype":"venue"
},
  "geometry": {"coordinates":[-74.100853,40.829644],"type":"Point"}
}