{
  "type": "Feature",
  "properties": {
    "addr:full":"58 Hartford Rd Sewell NJ 08080",
    "addr:housenumber":"58",
    "addr:postcode":"08080",
    "addr:street":"Hartford Rd",
    "iso:country":"US",
    "sg:address":"58 Hartford Rd",
    "sg:city":"Sewell",
    "sg:classifiers":[
        {
            "category":"Manufacturing",
            "subcategory":"Printing",
            "type":"Manufacturing & Wholesale Goods"
        }
    ],
    "sg:phone":"+1 856 582 0879",
    "sg:postcode":"08080",
    "sg:province":"NJ",
    "sg:tags":[
        "publishing"
    ],
    "wof:name":"Jeppe Verasal Music Publishing",
    "wof:placetype":"venue"
},
  "geometry": {"coordinates":[-75.060901,39.727041],"type":"Point"}
}