{
  "type": "Feature",
  "properties": {
    "addr:full":"459 Whittier Ave Westfield NJ 07090",
    "addr:housenumber":"459",
    "addr:postcode":"07090",
    "addr:street":"Whittier Ave",
    "iso:country":"US",
    "sg:address":"459 Whittier Ave",
    "sg:city":"Westfield",
    "sg:classifiers":[
        {
            "category":"Professional",
            "subcategory":"Engineering",
            "type":"Services"
        }
    ],
    "sg:phone":"+1 908 928 0128",
    "sg:postcode":"07090",
    "sg:province":"NJ",
    "wof:name":"Weldon Chin",
    "wof:placetype":"venue"
},
  "geometry": {"coordinates":[-74.366356,40.648686],"type":"Point"}
}