{
  "type": "Feature",
  "properties": {
    "addr:full":"187 Mountain Ave Gillette NJ 07933",
    "addr:housenumber":"187",
    "addr:postcode":"07933",
    "addr:street":"Mountain Ave",
    "iso:country":"US",
    "sg:address":"187 Mountain Ave",
    "sg:city":"Gillette",
    "sg:classifiers":[
        {
            "category":"Manufacturing",
            "subcategory":"Apparel",
            "type":"Manufacturing & Wholesale Goods"
        }
    ],
    "sg:phone":"+1 908 647 6842",
    "sg:postcode":"07933",
    "sg:province":"NJ",
    "sg:tags":[
        "outerwear",
        "mfg"
    ],
    "wof:name":"Nans Original Leotards",
    "wof:placetype":"venue"
},
  "geometry": {"coordinates":[-74.47335,40.682624],"type":"Point"}
}