{
  "type": "Feature",
  "properties": {
    "addr:full":"181 Hasbrouck Ave Hasbrouck Heights NJ 07604",
    "addr:housenumber":"181",
    "addr:postcode":"07604",
    "addr:street":"Hasbrouck Ave",
    "iso:country":"US",
    "sg:address":"181 Hasbrouck Ave",
    "sg:city":"Hasbrouck Heights",
    "sg:classifiers":[
        {
            "category":"Health Services",
            "subcategory":"Doctor",
            "type":"Services"
        }
    ],
    "sg:phone":"+1 201 288 6500",
    "sg:postcode":"07604",
    "sg:province":"NJ",
    "wof:name":"Roger J Szanto DMD",
    "wof:placetype":"venue"
},
  "geometry": {"coordinates":[-74.065879,40.865765],"type":"Point"}
}