{
  "type": "Feature",
  "properties": {
    "addr:full":"371 Kinderkamack Rd Emerson NJ 07630",
    "addr:housenumber":"371",
    "addr:postcode":"07630",
    "addr:street":"Kinderkamack Rd",
    "iso:country":"US",
    "sg:address":"371 Kinderkamack Rd",
    "sg:city":"Emerson",
    "sg:classifiers":[
        {
            "category":"Retail",
            "subcategory":"Veterinary Services",
            "type":"Services"
        }
    ],
    "sg:phone":"+1 201 262 2950",
    "sg:postcode":"07630",
    "sg:province":"NJ",
    "sg:tags":[
        "clinic",
        "hospital"
    ],
    "sg:website":"http://www.emersonvet.com",
    "wof:name":"Emerson Animal Hospital",
    "wof:placetype":"venue"
},
  "geometry": {"coordinates":[-74.024292,40.981541],"type":"Point"}
}