{
  "type": "Feature",
  "properties": {
    "addr:full":"1000 S Elmora Ave Ste I Elizabeth NJ 07202",
    "addr:housenumber":"1000",
    "addr:postcode":"07202",
    "addr:street":"S Elmora Ave Ste I",
    "iso:country":"US",
    "sg:address":"1000 S Elmora Ave Ste I",
    "sg:city":"Elizabeth",
    "sg:classifiers":[
        {
            "category":"Restaurant",
            "type":"Food & Drink"
        }
    ],
    "sg:phone":"+1 908 527 8888",
    "sg:postcode":"07202",
    "sg:province":"NJ",
    "sg:tags":[
        "chinese"
    ],
    "wof:name":"Fuhing Chinese Restaurants",
    "wof:placetype":"venue"
},
  "geometry": {"coordinates":[-74.225403,40.653599],"type":"Point"}
}