{
  "type": "Feature",
  "properties": {
    "addr:full":"18 Rosewood Ter Middletown NJ 07748",
    "addr:housenumber":"18",
    "addr:postcode":"07748",
    "addr:street":"Rosewood Ter",
    "iso:country":"US",
    "sg:address":"18 Rosewood Ter",
    "sg:city":"Middletown",
    "sg:classifiers":[
        {
            "category":"Professional",
            "subcategory":"Accounting & Tax Preparation",
            "type":"Services"
        }
    ],
    "sg:phone":"+1   ",
    "sg:postcode":"07748",
    "sg:province":"NJ",
    "wof:name":"Deborah A Rauch CPA",
    "wof:placetype":"venue"
},
  "geometry": {"coordinates":[-74.10675500000001,40.398899],"type":"Point"}
}