{
  "type": "Feature",
  "properties": {
    "addr:full":"343 US Hwy 46 Dover NJ 07801",
    "addr:housenumber":"343",
    "addr:postcode":"07801",
    "addr:street":"Us Hwy 46",
    "iso:country":"US",
    "sg:address":"343 US Hwy 46",
    "sg:city":"Dover",
    "sg:classifiers":[
        {
            "category":"Health Services",
            "subcategory":"Chiropractor",
            "type":"Services"
        }
    ],
    "sg:phone":"+1 973 584 7776",
    "sg:postcode":"07801",
    "sg:province":"NJ",
    "wof:name":"Mine Hill Chiropractic Center",
    "wof:placetype":"venue"
},
  "geometry": {"coordinates":[-74.538707,40.887751],"type":"Point"}
}