{
  "type": "Feature",
  "properties": {
    "iso:country":"US",
    "sg:address":"109 North Ave W",
    "sg:city":"Westfield",
    "sg:classifiers":[
        {
            "category":"Cinema",
            "subcategory":"Movie Rental",
            "type":"Entertainment"
        }
    ],
    "sg:phone":"+1 908 928 9198",
    "sg:postcode":"07090",
    "sg:province":"NJ",
    "sg:tags":[
        "leasing",
        "video",
        "disc",
        "tape"
    ],
    "sg:website":"www.blockbuster.com",
    "wof:name":"Blockbuster Video",
    "wof:placetype":"venue"
},
  "geometry": {"coordinates":[-74.34638,40.650455],"type":"Point"}
}