{
  "type": "Feature",
  "properties": {
    "addr:full":"75 Leighton Ave Red Bank NJ 07701",
    "addr:housenumber":"75",
    "addr:postcode":"07701",
    "addr:street":"Leighton Ave",
    "iso:country":"US",
    "sg:address":"75 Leighton Ave",
    "sg:city":"Red Bank",
    "sg:classifiers":[
        {
            "category":"Personal",
            "subcategory":"Tanning Parlor",
            "type":"Services"
        }
    ],
    "sg:phone":"+1 732 530 6821",
    "sg:postcode":"07701",
    "sg:province":"NJ",
    "sg:tags":[
        "salon"
    ],
    "wof:name":"Tan Atm",
    "wof:placetype":"venue"
},
  "geometry": {"coordinates":[-74.078754,40.344476],"type":"Point"}
}