{
  "type": "Feature",
  "properties": {
    "iso:country":"US",
    "sg:address":"354 Hoover Ave Unit 97",
    "sg:city":"Bloomfield",
    "sg:classifiers":[
        {
            "category":"Building & Trades",
            "subcategory":"Construction",
            "type":"Services"
        }
    ],
    "sg:phone":"+1 973 710 0310",
    "sg:postcode":"07003",
    "sg:province":"NJ",
    "sg:tags":[
        "contractor"
    ],
    "sg:website":"www.njkitchensandbaths.com",
    "wof:name":"NJ Kitchens and Baths",
    "wof:placetype":"venue"
},
  "geometry": {"coordinates":[-74.19032300000001,40.809895],"type":"Point"}
}