{
  "type": "Feature",
  "properties": {
    "addr:full":"330 Reservoir St Trenton NJ 08618",
    "addr:housenumber":"330",
    "addr:postcode":"08618",
    "addr:street":"Reservoir St",
    "iso:country":"US",
    "sg:address":"330 Reservoir St",
    "sg:city":"Trenton",
    "sg:classifiers":[
        {
            "category":"Autos & Motor Vehicles",
            "subcategory":"Automobile Sales",
            "type":"Retail Goods"
        }
    ],
    "sg:phone":"+1 609 392 3033",
    "sg:postcode":"08618",
    "sg:province":"NJ",
    "sg:tags":[
        "car",
        "dealer"
    ],
    "wof:name":"Arena Auto Sales LLC",
    "wof:placetype":"venue"
},
  "geometry": {"coordinates":[-74.769254,40.230268],"type":"Point"}
}