{
  "type": "Feature",
  "properties": {
    "addr:full":"398 Stuyvesant Ave Irvington NJ 07111",
    "addr:housenumber":"398",
    "addr:postcode":"07111",
    "addr:street":"Stuyvesant Ave",
    "iso:country":"US",
    "sg:address":"398 Stuyvesant Ave",
    "sg:city":"Irvington",
    "sg:classifiers":[
        {
            "category":"Real Estate",
            "subcategory":"Real Estate Operator",
            "type":"Services"
        }
    ],
    "sg:phone":"+1   ",
    "sg:postcode":"07111",
    "sg:province":"NJ",
    "sg:tags":[
        "apartment",
        "complex"
    ],
    "wof:name":"Irvington Arms APT",
    "wof:placetype":"venue"
},
  "geometry": {"coordinates":[-74.234444,40.73365],"type":"Point"}
}