{
  "type": "Feature",
  "properties": {
    "addr:full":"240 Monmouth Rd Oakhurst NJ 07755",
    "addr:housenumber":"240",
    "addr:postcode":"07755",
    "addr:street":"Monmouth Rd",
    "iso:country":"US",
    "sg:address":"240 Monmouth Rd",
    "sg:city":"Oakhurst",
    "sg:classifiers":[
        {
            "category":"Health Services",
            "subcategory":"Doctor",
            "type":"Services"
        }
    ],
    "sg:phone":"+1   ",
    "sg:postcode":"07755",
    "sg:province":"NJ",
    "sg:tags":[
        "medical"
    ],
    "wof:name":"Immediate Medical Services",
    "wof:placetype":"venue"
},
  "geometry": {"coordinates":[-74.011336,40.257848],"type":"Point"}
}