{
  "type": "Feature",
  "properties": {
    "iso:country":"US",
    "sg:address":"11 Wadsworth Ave",
    "sg:city":"Metuchen",
    "sg:classifiers":[
        {
            "category":"Professional",
            "type":"Services"
        }
    ],
    "sg:phone":"+1   ",
    "sg:postcode":"08840",
    "sg:province":"NJ",
    "wof:name":"Are You Being Served Inc",
    "wof:placetype":"venue"
},
  "geometry": {"coordinates":[-74.35781299999999,40.553294],"type":"Point"}
}