{
  "type": "Feature",
  "properties": {
    "addr:full":"24 Winding Way Mount Laurel NJ 08054",
    "addr:housenumber":"24",
    "addr:postcode":"08054",
    "addr:street":"Winding Way",
    "iso:country":"US",
    "sg:address":"24 Winding Way",
    "sg:city":"Mount Laurel",
    "sg:classifiers":[
        {
            "category":"Manufacturing",
            "subcategory":"Printing",
            "type":"Manufacturing & Wholesale Goods"
        }
    ],
    "sg:phone":"+1 856 642 7788",
    "sg:postcode":"08054",
    "sg:province":"NJ",
    "sg:tags":[
        "lithographic",
        "commercial"
    ],
    "wof:name":"Xerox",
    "wof:placetype":"venue"
},
  "geometry": {"coordinates":[-74.88000099999999,39.933455],"type":"Point"}
}