{
  "type": "Feature",
  "properties": {
    "addr:full":"32 Brambling Ln Voorhees NJ 08043",
    "addr:housenumber":"32",
    "addr:postcode":"08043",
    "addr:street":"Brambling Ln",
    "iso:country":"US",
    "sg:address":"32 Brambling Ln",
    "sg:city":"Voorhees",
    "sg:classifiers":[
        {
            "category":"Banks & Credit Unions",
            "subcategory":"Investment Brokerage",
            "type":"Services"
        }
    ],
    "sg:phone":"+1 856 751 8044",
    "sg:postcode":"08043",
    "sg:province":"NJ",
    "sg:tags":[
        "advisory",
        "financial"
    ],
    "wof:name":"Main Street Financial & Pnsn",
    "wof:placetype":"venue"
},
  "geometry": {"coordinates":[-74.931237,39.863178],"type":"Point"}
}