{
  "type": "Feature",
  "properties": {
    "iso:country":"US",
    "sg:address":"160 Mountain Ave",
    "sg:city":"Springfield",
    "sg:classifiers":[
        {
            "category":"Banks & Credit Unions",
            "subcategory":"Financial Services",
            "type":"Services"
        }
    ],
    "sg:phone":"+1   ",
    "sg:postcode":"07081",
    "sg:province":"NJ",
    "sg:tags":[
        "franchise",
        "convenient",
        "store"
    ],
    "wof:name":"Speedy Mart Development Inc",
    "wof:placetype":"venue"
},
  "geometry": {"coordinates":[-74.316371,40.705876],"type":"Point"}
}