{
  "type": "Feature",
  "properties": {
    "iso:country":"US",
    "sg:address":"725 Newark Ave",
    "sg:city":"Jersey City",
    "sg:classifiers":[
        {
            "category":"Shopping",
            "subcategory":"Gifts & Souvenirs",
            "type":"Retail Goods"
        }
    ],
    "sg:phone":"+1 201 386 0999",
    "sg:postcode":"07306",
    "sg:province":"NJ",
    "sg:tags":[
        "shop"
    ],
    "wof:name":"New Ujala",
    "wof:placetype":"venue"
},
  "geometry": {"coordinates":[-74.06134,40.734972],"type":"Point"}
}