{
  "type": "Feature",
  "properties": {
    "addr:full":"2913 Woodbridge Ave Edison NJ 08837",
    "addr:housenumber":"2913",
    "addr:postcode":"08837",
    "addr:street":"Woodbridge Ave",
    "iso:country":"US",
    "sg:address":"2913 Woodbridge Ave",
    "sg:city":"Edison",
    "sg:classifiers":[
        {
            "category":"Retail",
            "subcategory":"Auto Rental",
            "type":"Services"
        }
    ],
    "sg:phone":"+1 732 516 1079",
    "sg:postcode":"08837",
    "sg:province":"NJ",
    "sg:tags":[
        "renting",
        "automobile",
        "passenger",
        "car"
    ],
    "wof:name":"Enterprise Rent A Car",
    "wof:placetype":"venue"
},
  "geometry": {"coordinates":[-74.35469399999999,40.516128],"type":"Point"}
}