{
  "type": "Feature",
  "properties": {
    "iso:country":"US",
    "sg:address":"3191 State Rte 27",
    "sg:city":"Franklin Park",
    "sg:classifiers":[
        {
            "category":"Retail",
            "subcategory":"Laundry & Dry Cleaning",
            "type":"Services"
        }
    ],
    "sg:phone":"+1 732 297 0055",
    "sg:postcode":"08823",
    "sg:province":"NJ",
    "sg:tags":[
        "drycleaning",
        "plant",
        "cleaners"
    ],
    "wof:name":"Dependable Dry Cleaners",
    "wof:placetype":"venue"
},
  "geometry": {"coordinates":[-74.544549,40.434523],"type":"Point"}
}