{
  "type": "Feature",
  "properties": {
    "iso:country":"US",
    "sg:address":"433 Heath Pl",
    "sg:city":"Hackensack",
    "sg:classifiers":[
        {
            "category":"Bus Charters",
            "type":"Transportation"
        }
    ],
    "sg:phone":"+1 201 342 8055",
    "sg:postcode":"07601",
    "sg:province":"NJ",
    "wof:name":"Sonny Delight Corp",
    "wof:placetype":"venue"
},
  "geometry": {"coordinates":[-74.05857,40.894893],"type":"Point"}
}