{
  "type": "Feature",
  "properties": {
    "iso:country":"US",
    "sg:address":"160 Woodbine St",
    "sg:city":"Bergenfield",
    "sg:classifiers":[
        {
            "category":"Home & Garden",
            "subcategory":"Building Materials",
            "type":"Retail Goods"
        }
    ],
    "sg:phone":"+1   ",
    "sg:postcode":"07621",
    "sg:province":"NJ",
    "wof:name":"APA Glass Company",
    "wof:placetype":"venue"
},
  "geometry": {"coordinates":[-74.000247,40.920039],"type":"Point"}
}