{
  "type": "Feature",
  "properties": {
    "addr:full":"130 Cedar St Garfield NJ 07026",
    "addr:housenumber":"130",
    "addr:postcode":"07026",
    "addr:street":"Cedar St",
    "iso:country":"US",
    "sg:address":"130 Cedar St",
    "sg:city":"Garfield",
    "sg:classifiers":[
        {
            "category":"Building & Trades",
            "subcategory":"Construction",
            "type":"Services"
        }
    ],
    "sg:phone":"+1 201 796 6009",
    "sg:postcode":"07026",
    "sg:province":"NJ",
    "sg:tags":[
        "dry wall",
        "contractor"
    ],
    "wof:name":"JMD Construction",
    "wof:placetype":"venue"
},
  "geometry": {"coordinates":[-74.10880299999999,40.879807],"type":"Point"}
}