{
  "type": "Feature",
  "properties": {
    "iso:country":"US",
    "sg:address":"39 Polo Club Dr",
    "sg:city":"Freehold",
    "sg:classifiers":[
        {
            "category":"Building & Trades",
            "subcategory":"Landscaping Services",
            "type":"Services"
        }
    ],
    "sg:phone":"+1 732 866 1747",
    "sg:postcode":"07728",
    "sg:province":"NJ",
    "sg:tags":[
        "landscape"
    ],
    "wof:name":"Calymon Associates",
    "wof:placetype":"venue"
},
  "geometry": {"coordinates":[-74.27967200000001,40.214926],"type":"Point"}
}