{
  "type": "Feature",
  "properties": {
    "addr:full":"298 Union Blvd Totowa NJ 07512",
    "addr:housenumber":"298",
    "addr:postcode":"07512",
    "addr:street":"Union Blvd",
    "iso:country":"US",
    "sg:address":"298 Union Blvd",
    "sg:city":"Totowa",
    "sg:classifiers":[
        {
            "category":"Building & Trades",
            "subcategory":"Locksmith",
            "type":"Services"
        }
    ],
    "sg:phone":"+1 888 401 2474",
    "sg:postcode":"07512",
    "sg:province":"NJ",
    "sg:tags":[
        "key"
    ],
    "wof:name":"24 Hour 7 Day Emergency Locksmith",
    "wof:placetype":"venue"
},
  "geometry": {"coordinates":[-74.210296,40.904821],"type":"Point"}
}