{
  "type": "Feature",
  "properties": {
    "iso:country":"US",
    "sg:address":"170 Washington Ave",
    "sg:city":"Belleville",
    "sg:classifiers":[
        {
            "category":"Restaurant",
            "type":"Food & Drink"
        }
    ],
    "sg:phone":"+1 973 751 2241",
    "sg:postcode":"07109",
    "sg:province":"NJ",
    "sg:tags":[
        "eating"
    ],
    "wof:name":"Three Guys From Italy Rest",
    "wof:placetype":"venue"
},
  "geometry": {"coordinates":[-74.152911,40.787315],"type":"Point"}
}