{
  "type": "Feature",
  "properties": {
    "addr:full":"110 Ocean Rd Ocean City NJ 08226",
    "addr:housenumber":"110",
    "addr:postcode":"08226",
    "addr:street":"Ocean Rd",
    "iso:country":"US",
    "sg:address":"110 Ocean Rd",
    "sg:city":"Ocean City",
    "sg:classifiers":[
        {
            "category":"Building & Trades",
            "subcategory":"Landscaping Services",
            "type":"Services"
        }
    ],
    "sg:phone":"+1 609 399 5693",
    "sg:postcode":"08226",
    "sg:province":"NJ",
    "wof:name":"F W Becker Company Inc",
    "wof:placetype":"venue"
},
  "geometry": {"coordinates":[-74.556123,39.28749],"type":"Point"}
}