{
  "type": "Feature",
  "properties": {
    "addr:full":"13 Delmar Ln Brigantine NJ 08203",
    "addr:housenumber":"13",
    "addr:postcode":"08203",
    "addr:street":"Delmar Ln",
    "iso:country":"US",
    "sg:address":"13 Delmar Ln",
    "sg:city":"Brigantine",
    "sg:classifiers":[
        {
            "category":"Shopping",
            "subcategory":"Books",
            "type":"Retail Goods"
        }
    ],
    "sg:phone":"+1   ",
    "sg:postcode":"08203",
    "sg:province":"NJ",
    "wof:name":"Buried Treasure Bookshop",
    "wof:placetype":"venue"
},
  "geometry": {"coordinates":[-74.404246,39.385836],"type":"Point"}
}