{
  "type": "Feature",
  "properties": {
    "addr:full":"2347 John F Kennedy Blvd Jersey City NJ 07304",
    "addr:housenumber":"2347",
    "addr:postcode":"07304",
    "addr:street":"John F Kennedy Blvd",
    "iso:country":"US",
    "sg:address":"2347 John F Kennedy Blvd",
    "sg:city":"Jersey City",
    "sg:classifiers":[
        {
            "category":"Food & Beverages",
            "subcategory":"Liquor & Beverages",
            "type":"Retail Goods"
        }
    ],
    "sg:phone":"+1 201 200 1209",
    "sg:postcode":"07304",
    "sg:province":"NJ",
    "wof:name":"Sam's Liquors",
    "wof:placetype":"venue"
},
  "geometry": {"coordinates":[-74.079171,40.718294],"type":"Point"}
}