{
  "type": "Feature",
  "properties": {
    "iso:country":"US",
    "sg:address":"339 S 27th St",
    "sg:city":"Camden",
    "sg:classifiers":[
        {
            "category":"Wholesale",
            "subcategory":"Motor Vehicles",
            "type":"Manufacturing & Wholesale Goods"
        }
    ],
    "sg:phone":"+1 609 929 8663",
    "sg:postcode":"08105",
    "sg:province":"NJ",
    "wof:name":"Car Finder",
    "wof:placetype":"venue"
},
  "geometry": {"coordinates":[-75.082666,39.941215],"type":"Point"}
}