{
  "type": "Feature",
  "properties": {
    "addr:full":"1400 State Rte 70 Lakewood NJ 08701",
    "addr:housenumber":"1400",
    "addr:postcode":"08701",
    "addr:street":"State Rte 70",
    "iso:country":"US",
    "sg:address":"1400 State Rte 70",
    "sg:city":"Lakewood",
    "sg:classifiers":[
        {
            "category":"Real Estate",
            "subcategory":"Real Estate Operator",
            "type":"Services"
        }
    ],
    "sg:phone":"+1   ",
    "sg:postcode":"08701",
    "sg:province":"NJ",
    "sg:tags":[
        "building",
        "intermediate",
        "apartment",
        "care",
        "facility"
    ],
    "wof:name":"Marriott",
    "wof:placetype":"venue"
},
  "geometry": {"coordinates":[-74.173883,40.053719],"type":"Point"}
}