{
  "type": "Feature",
  "properties": {
    "addr:full":"1909 State Rte 38 Southampton NJ 08088",
    "addr:housenumber":"1909",
    "addr:postcode":"08088",
    "addr:street":"State Rte 38",
    "iso:country":"US",
    "sg:address":"1909 State Rte 38",
    "sg:city":"Southampton",
    "sg:classifiers":[
        {
            "category":"Retail",
            "subcategory":"Veterinary Services",
            "type":"Services"
        }
    ],
    "sg:phone":"+1 609 265 0100",
    "sg:postcode":"08088",
    "sg:province":"NJ",
    "sg:tags":[
        "veterinarian"
    ],
    "wof:name":"Pinelands Veterinary Clinic",
    "wof:placetype":"venue"
},
  "geometry": {"coordinates":[-74.74450899999999,39.972536],"type":"Point"}
}