{
  "type": "Feature",
  "properties": {
    "iso:country":"US",
    "sg:address":"23 Hickory Rd",
    "sg:city":"Oak Ridge",
    "sg:classifiers":[
        {
            "category":"Professional",
            "subcategory":"Advertising",
            "type":"Services"
        }
    ],
    "sg:phone":"+1   ",
    "sg:postcode":"07438",
    "sg:province":"NJ",
    "sg:tags":[
        "mail",
        "direct"
    ],
    "wof:name":"A Mac Mailing & ADM Svcs",
    "wof:placetype":"venue"
},
  "geometry": {"coordinates":[-74.50453,41.010698],"type":"Point"}
}