{
  "type": "Feature",
  "properties": {
    "iso:country":"US",
    "sg:address":"831 Norwood Ave",
    "sg:city":"Long Branch",
    "sg:classifiers":[
        {
            "category":"Professional",
            "subcategory":"Computer Services",
            "type":"Services"
        }
    ],
    "sg:phone":"+1   ",
    "sg:postcode":"07740",
    "sg:province":"NJ",
    "sg:tags":[
        "programing",
        "custom"
    ],
    "wof:name":"Edi Administration Instit",
    "wof:placetype":"venue"
},
  "geometry": {"coordinates":[-74.002185,40.270953],"type":"Point"}
}