{
  "type": "Feature",
  "properties": {
    "addr:full":"10 Courtland St Paterson NJ 07503",
    "addr:housenumber":"10",
    "addr:postcode":"07503",
    "addr:street":"Courtland St",
    "iso:country":"US",
    "sg:address":"10 Courtland St",
    "sg:city":"Paterson",
    "sg:classifiers":[
        {
            "category":"Freight",
            "type":"Transportation"
        }
    ],
    "sg:phone":"+1 973 523 5431",
    "sg:postcode":"07503",
    "sg:province":"NJ",
    "sg:tags":[
        "record",
        "conversion",
        "storage"
    ],
    "wof:name":"File Bank",
    "wof:placetype":"venue"
},
  "geometry": {"coordinates":[-74.166802,40.900889],"type":"Point"}
}