{
  "type": "Feature",
  "properties": {
    "iso:country":"US",
    "sg:address":"1210 State Rte 23",
    "sg:city":"Sussex",
    "sg:classifiers":[
        {
            "category":"Home & Garden",
            "subcategory":"Building Materials",
            "type":"Retail Goods"
        }
    ],
    "sg:phone":"+1 973 875 5151",
    "sg:postcode":"07461",
    "sg:province":"NJ",
    "sg:tags":[
        "modular"
    ],
    "wof:name":"Coyote Modular Homes",
    "wof:placetype":"venue"
},
  "geometry": {"coordinates":[-74.651848,41.276413],"type":"Point"}
}