{
  "type": "Feature",
  "properties": {
    "iso:country":"US",
    "sg:address":"1212 Raymond Blvd",
    "sg:city":"Newark",
    "sg:classifiers":[
        {
            "category":"Professional",
            "subcategory":"Business Services",
            "type":"Services"
        }
    ],
    "sg:phone":"+1   ",
    "sg:postcode":"07102",
    "sg:province":"NJ",
    "wof:name":"Postal Center",
    "wof:placetype":"venue"
},
  "geometry": {"coordinates":[-74.171905,40.737561],"type":"Point"}
}