{
  "type": "Feature",
  "properties": {
    "iso:country":"US",
    "sg:address":"324 Highland Ave",
    "sg:city":"Palisades Park",
    "sg:classifiers":[
        {
            "category":"Wholesale",
            "subcategory":"Jewelry",
            "type":"Manufacturing & Wholesale Goods"
        }
    ],
    "sg:phone":"+1 201 461 7215",
    "sg:postcode":"07650",
    "sg:province":"NJ",
    "sg:tags":[
        "cassette",
        "export",
        "import",
        "housewares",
        "video",
        "kitchen"
    ],
    "wof:name":"Finance Gold",
    "wof:placetype":"venue"
},
  "geometry": {"coordinates":[-73.997744,40.850463],"type":"Point"}
}