{
  "type": "Feature",
  "properties": {
    "addr:full":"1801 E 2nd St Scotch Plains NJ 07076",
    "addr:housenumber":"1801",
    "addr:postcode":"07076",
    "addr:street":"E 2Nd St",
    "iso:country":"US",
    "sg:address":"1801 E 2nd St",
    "sg:city":"Scotch Plains",
    "sg:classifiers":[
        {
            "category":"Health Services",
            "subcategory":"Doctor",
            "type":"Services"
        }
    ],
    "sg:phone":"+1 908 490 1699",
    "sg:postcode":"07076",
    "sg:province":"NJ",
    "sg:tags":[
        "physician",
        "surgeon"
    ],
    "wof:name":"Thoracic Cardiovascular Srgcl",
    "wof:placetype":"venue"
},
  "geometry": {"coordinates":[-74.397238,40.648809],"type":"Point"}
}