{
  "type": "Feature",
  "properties": {
    "addr:full":"5 Jackson Rd Medford NJ 08055",
    "addr:housenumber":"5",
    "addr:postcode":"08055",
    "addr:street":"Jackson Rd",
    "iso:country":"US",
    "sg:address":"5 Jackson Rd",
    "sg:city":"Medford",
    "sg:classifiers":[
        {
            "category":"Building & Trades",
            "subcategory":"Construction",
            "type":"Services"
        }
    ],
    "sg:phone":"+1 609 953 7542",
    "sg:postcode":"08055",
    "sg:province":"NJ",
    "sg:tags":[
        "contractor",
        "pool",
        "swimming"
    ],
    "wof:name":"Diamond Pool Service Inc",
    "wof:placetype":"venue"
},
  "geometry": {"coordinates":[-74.819154,39.870782],"type":"Point"}
}