{
  "type": "Feature",
  "properties": {
    "addr:full":"12 Riverside Dr Princeton NJ 08540",
    "addr:housenumber":"12",
    "addr:postcode":"08540",
    "addr:street":"Riverside Dr",
    "iso:country":"US",
    "sg:address":"12 Riverside Dr",
    "sg:city":"Princeton",
    "sg:classifiers":[
        {
            "category":"Professional",
            "subcategory":"Management & Consulting",
            "type":"Services"
        }
    ],
    "sg:phone":"+1 609 731 8728",
    "sg:postcode":"08540",
    "sg:province":"NJ",
    "sg:tags":[
        "marketing",
        "consultant"
    ],
    "wof:name":"Rosales Gottemoeller & Assoc",
    "wof:placetype":"venue"
},
  "geometry": {"coordinates":[-74.638908,40.355912],"type":"Point"}
}