{
  "type": "Feature",
  "properties": {
    "addr:full":"165 Danforth Ave Jersey City NJ 07305",
    "addr:housenumber":"165",
    "addr:postcode":"07305",
    "addr:street":"Danforth Ave",
    "iso:country":"US",
    "sg:address":"165 Danforth Ave",
    "sg:city":"Jersey City",
    "sg:classifiers":[
        {
            "category":"Professional",
            "type":"Services"
        }
    ],
    "sg:phone":"+1   ",
    "sg:postcode":"07305",
    "sg:province":"NJ",
    "wof:name":"Collado Marina Rdh",
    "wof:placetype":"venue"
},
  "geometry": {"coordinates":[-74.091506,40.696075],"type":"Point"}
}