{
  "type": "Feature",
  "properties": {
    "iso:country":"US",
    "sg:address":"1075 Easton Ave",
    "sg:city":"Somerset",
    "sg:classifiers":[
        {
            "category":"Shopping",
            "subcategory":"Clothing, Apparel, & Fashions",
            "type":"Retail Goods"
        }
    ],
    "sg:phone":"+1   ",
    "sg:postcode":"08873",
    "sg:province":"NJ",
    "wof:name":"Tay Half",
    "wof:placetype":"venue"
},
  "geometry": {"coordinates":[-74.488589,40.515492],"type":"Point"}
}