{
  "type": "Feature",
  "properties": {
    "addr:full":"7 White St Red Bank NJ 07701",
    "addr:housenumber":"7",
    "addr:postcode":"07701",
    "addr:street":"White St",
    "iso:country":"US",
    "sg:address":"7 White St",
    "sg:city":"Red Bank",
    "sg:classifiers":[
        {
            "category":"Personal",
            "subcategory":"Beauty Salon",
            "type":"Services"
        }
    ],
    "sg:phone":"+1 732 842 9037",
    "sg:postcode":"07701",
    "sg:province":"NJ",
    "sg:tags":[
        "shop"
    ],
    "wof:name":"Chelsea Morning",
    "wof:placetype":"venue"
},
  "geometry": {"coordinates":[-74.066394,40.3505],"type":"Point"}
}