{
  "type": "Feature",
  "properties": {
    "iso:country":"US",
    "sg:address":"1808 Long Beach Blvd",
    "sg:city":"Beach Haven",
    "sg:classifiers":[
        {
            "category":"Real Estate",
            "subcategory":"Architect",
            "type":"Services"
        }
    ],
    "sg:phone":"+1   ",
    "sg:postcode":"08008",
    "sg:province":"NJ",
    "sg:tags":[
        "architectural"
    ],
    "wof:name":"Keith Burns Architect",
    "wof:placetype":"venue"
},
  "geometry": {"coordinates":[-74.180437,39.64361],"type":"Point"}
}