{
  "type": "Feature",
  "properties": {
    "addr:full":"671 US Hwy 1 North Brunswick NJ 08902",
    "addr:housenumber":"671",
    "addr:postcode":"08902",
    "addr:street":"Us Hwy 1",
    "iso:country":"US",
    "sg:address":"671 US Hwy 1",
    "sg:city":"North Brunswick",
    "sg:classifiers":[
        {
            "category":"Wholesale",
            "subcategory":"Drugs",
            "type":"Manufacturing & Wholesale Goods"
        }
    ],
    "sg:phone":"+1 732 565 1101",
    "sg:postcode":"08902",
    "sg:province":"NJ",
    "sg:tags":[
        "pharmaceutical",
        "product"
    ],
    "wof:name":"Provid Pharmaceuticals Inc",
    "wof:placetype":"venue"
},
  "geometry": {"coordinates":[-74.471789,40.458217],"type":"Point"}
}