{
  "type": "Feature",
  "properties": {
    "iso:country":"US",
    "sg:address":"45 Horsehill Rd",
    "sg:city":"Cedar Knolls",
    "sg:classifiers":[
        {
            "category":"Professional",
            "subcategory":"Lawyer & Legal Services",
            "type":"Services"
        }
    ],
    "sg:phone":"+1 973 359 0090",
    "sg:postcode":"07927",
    "sg:province":"NJ",
    "wof:name":"Litvak & Trifiolis",
    "wof:placetype":"venue"
},
  "geometry": {"coordinates":[-74.462947,40.814234],"type":"Point"}
}