{
  "type": "Feature",
  "properties": {
    "addr:full":"334 Arneys Mount Rd Jobstown NJ 08041",
    "addr:housenumber":"334",
    "addr:postcode":"08041",
    "addr:street":"Arneys Mount Rd",
    "iso:country":"US",
    "sg:address":"334 Arneys Mount Rd",
    "sg:city":"Jobstown",
    "sg:classifiers":[
        {
            "category":"Autos & Motor Vehicles",
            "subcategory":"Fuel & Gas Station",
            "type":"Retail Goods"
        }
    ],
    "sg:phone":"+1   ",
    "sg:postcode":"08041",
    "sg:province":"NJ",
    "sg:tags":[
        "station",
        "gasoline"
    ],
    "wof:name":"Hanover Mobil Village",
    "wof:placetype":"venue"
},
  "geometry": {"coordinates":[-74.698211,40.013309],"type":"Point"}
}