{
  "type": "Feature",
  "properties": {
    "iso:country":"US",
    "sg:address":"39 Brunswick Woods Dr",
    "sg:city":"East Brunswick",
    "sg:classifiers":[
        {
            "category":"Health Services",
            "subcategory":"Doctor",
            "type":"Services"
        }
    ],
    "sg:phone":"+1 732 257 6012",
    "sg:postcode":"08816",
    "sg:province":"NJ",
    "sg:tags":[
        "physician",
        "surgeon"
    ],
    "wof:name":"Alan Herschman MD",
    "wof:placetype":"venue"
},
  "geometry": {"coordinates":[-74.391633,40.42123],"type":"Point"}
}