{
  "type": "Feature",
  "properties": {
    "addr:full":"2610 18th Ave Belmar NJ 07719",
    "addr:housenumber":"2610",
    "addr:postcode":"07719",
    "addr:street":"18Th Ave",
    "iso:country":"US",
    "sg:address":"2610 18th Ave",
    "sg:city":"Belmar",
    "sg:classifiers":[
        {
            "category":"Building & Trades",
            "subcategory":"Plumbing",
            "type":"Services"
        }
    ],
    "sg:phone":"+1 732 681 5329",
    "sg:postcode":"07719",
    "sg:province":"NJ",
    "sg:tags":[
        "system",
        "contractor",
        "ventilation",
        "heating",
        "conditioning",
        "air"
    ],
    "wof:name":"GBS Mechanical Inc",
    "wof:placetype":"venue"
},
  "geometry": {"coordinates":[-74.075444,40.165138],"type":"Point"}
}