{
  "type": "Feature",
  "properties": {
    "addr:full":"458 E Bay Ave Barnegat NJ 08005",
    "addr:housenumber":"458",
    "addr:postcode":"08005",
    "addr:street":"E Bay Ave",
    "iso:country":"US",
    "sg:address":"458 E Bay Ave",
    "sg:city":"Barnegat",
    "sg:classifiers":[
        {
            "category":"Building & Trades",
            "subcategory":"Construction",
            "type":"Services"
        }
    ],
    "sg:phone":"+1 609 607 9444",
    "sg:postcode":"08005",
    "sg:province":"NJ",
    "sg:tags":[
        "concrete",
        "contractor"
    ],
    "wof:name":"Blacktop Lines",
    "wof:placetype":"venue"
},
  "geometry": {"coordinates":[-74.196648,39.748236],"type":"Point"}
}