{
  "type": "Feature",
  "properties": {
    "addr:full":"400 Kinderkamack Rd Oradell NJ 07649",
    "addr:housenumber":"400",
    "addr:postcode":"07649",
    "addr:street":"Kinderkamack Rd",
    "iso:country":"US",
    "sg:address":"400 Kinderkamack Rd",
    "sg:city":"Oradell",
    "sg:classifiers":[
        {
            "category":"Health Services",
            "subcategory":"Doctor",
            "type":"Services"
        }
    ],
    "sg:phone":"+1 201 262 0211",
    "sg:postcode":"07649",
    "sg:province":"NJ",
    "sg:tags":[
        "dentist"
    ],
    "wof:name":"Kindersmiles Pediatric",
    "wof:placetype":"venue"
},
  "geometry": {"coordinates":[-74.031762,40.953348],"type":"Point"}
}