{
  "type": "Feature",
  "properties": {
    "addr:full":"583 Newark Pompton Tpke Wayne NJ 07470",
    "addr:housenumber":"583",
    "addr:postcode":"07470",
    "addr:street":"Newark Pompton Tpke",
    "iso:country":"US",
    "sg:address":"583 Newark Pompton Tpke",
    "sg:city":"Wayne",
    "sg:classifiers":[
        {
            "category":"Shopping",
            "subcategory":"Pets & Pet Supplies",
            "type":"Retail Goods"
        },
        {
            "category":"Retail",
            "subcategory":"Animal Services",
            "type":"Services"
        }
    ],
    "sg:phone":"+1 973 248 8440",
    "sg:postcode":"07470",
    "sg:province":"NJ",
    "sg:tags":[
        "food",
        "grooming",
        "dog",
        "store",
        "cat"
    ],
    "wof:name":"Chien Bone",
    "wof:placetype":"venue"
},
  "geometry": {"coordinates":[-74.278076,40.942523],"type":"Point"}
}