{
  "type": "Feature",
  "properties": {
    "addr:full":"575 N Main St Barnegat NJ 08005",
    "addr:housenumber":"575",
    "addr:postcode":"08005",
    "addr:street":"N Main St",
    "iso:country":"US",
    "sg:address":"575 N Main St",
    "sg:city":"Barnegat",
    "sg:classifiers":[
        {
            "category":"Real Estate",
            "subcategory":"Real Estate Agent",
            "type":"Services"
        }
    ],
    "sg:phone":"+1 609 698 4700",
    "sg:postcode":"08005",
    "sg:province":"NJ",
    "wof:name":"Compass Real Estate LLC",
    "wof:placetype":"venue"
},
  "geometry": {"coordinates":[-74.209996,39.771717],"type":"Point"}
}