{
  "type": "Feature",
  "properties": {
    "iso:country":"US",
    "sg:address":"1080 Springfield Ave",
    "sg:city":"Irvington",
    "sg:classifiers":[
        {
            "category":"Shopping",
            "subcategory":"Clothing, Apparel, & Fashions",
            "type":"Retail Goods"
        }
    ],
    "sg:phone":"+1 973 373 9777",
    "sg:postcode":"07111",
    "sg:province":"NJ",
    "wof:name":"God's Glory",
    "wof:placetype":"venue"
},
  "geometry": {"coordinates":[-74.233076,40.72587],"type":"Point"}
}