{
  "type": "Feature",
  "properties": {
    "iso:country":"US",
    "sg:address":"546 Main St",
    "sg:city":"Landing",
    "sg:classifiers":[
        {
            "category":"Organizations",
            "subcategory":"Religious Organization",
            "type":"Services"
        }
    ],
    "sg:phone":"+1 973 347 0381",
    "sg:postcode":"07850",
    "sg:province":"NJ",
    "sg:tags":[
        "church"
    ],
    "wof:name":"Port Morris United Methodist",
    "wof:placetype":"venue"
},
  "geometry": {"coordinates":[-74.683852,40.906899],"type":"Point"}
}