{
  "type": "Feature",
  "properties": {
    "iso:country":"US",
    "sg:address":"266 Harristown Rd",
    "sg:city":"Glen Rock",
    "sg:classifiers":[
        {
            "category":"Real Estate",
            "subcategory":"Real Estate Agent",
            "type":"Services"
        },
        {
            "category":"Professional",
            "subcategory":"Business Services",
            "type":"Services"
        }
    ],
    "sg:phone":"+1 201 444 5400",
    "sg:postcode":"07452",
    "sg:province":"NJ",
    "wof:name":"Goldstein Group",
    "wof:placetype":"venue"
},
  "geometry": {"coordinates":[-74.136329,40.951771],"type":"Point"}
}