{
  "type": "Feature",
  "properties": {
    "iso:country":"US",
    "sg:address":"322 Morris St",
    "sg:city":"Woodbury",
    "sg:classifiers":[
        {
            "category":"Wholesale",
            "subcategory":"Jewelry",
            "type":"Manufacturing & Wholesale Goods"
        },
        {
            "category":"Shopping",
            "subcategory":"Crafts & Fabrics",
            "type":"Retail Goods"
        }
    ],
    "sg:phone":"+1 856 384 8547",
    "sg:postcode":"08096",
    "sg:province":"NJ",
    "sg:tags":[
        "bead",
        "beads-wholesale",
        "manufacturer"
    ],
    "wof:name":"One Bead At A Time",
    "wof:placetype":"venue"
},
  "geometry": {"coordinates":[-75.159482,39.835197],"type":"Point"}
}