{
  "type": "Feature",
  "properties": {
    "addr:full":"582 Franklin Ave Nutley NJ 07110",
    "addr:housenumber":"582",
    "addr:postcode":"07110",
    "addr:street":"Franklin Ave",
    "iso:country":"US",
    "sg:address":"582 Franklin Ave",
    "sg:city":"Nutley",
    "sg:classifiers":[
        {
            "category":"Health Services",
            "subcategory":"Doctor",
            "type":"Services"
        },
        {
            "category":"Health Services",
            "subcategory":"Health Practitioner",
            "type":"Services"
        }
    ],
    "sg:phone":"+1 973 667 9555",
    "sg:postcode":"07110",
    "sg:province":"NJ",
    "sg:tags":[
        "medicine",
        "medical",
        "sport",
        "therapist",
        "physical"
    ],
    "sg:website":"www.jerseyrehab.com",
    "wof:name":"Jersey Rehab PA",
    "wof:placetype":"venue"
},
  "geometry": {"coordinates":[-74.15300000000001,40.8255],"type":"Point"}
}