{
  "type": "Feature",
  "properties": {
    "addr:full":"41 Lafetra Ave Eatontown NJ 07724",
    "addr:housenumber":"41",
    "addr:postcode":"07724",
    "addr:street":"Lafetra Ave",
    "iso:country":"US",
    "sg:address":"41 Lafetra Ave",
    "sg:city":"Eatontown",
    "sg:classifiers":[
        {
            "category":"Building & Trades",
            "subcategory":"Construction",
            "type":"Services"
        }
    ],
    "sg:phone":"+1 732 578 1000",
    "sg:postcode":"07724",
    "sg:province":"NJ",
    "sg:tags":[
        "waterproofing",
        "asphalt",
        "contractor",
        "paving",
        "fireproofing",
        "sealcoating"
    ],
    "wof:name":"Fornicola & Sons Asphalt",
    "wof:placetype":"venue"
},
  "geometry": {"coordinates":[-74.053619,40.304539],"type":"Point"}
}