{
  "type": "Feature",
  "properties": {
    "iso:country":"US",
    "sg:address":"806 Hasting Ln",
    "sg:city":"Point Pleasant Beach",
    "sg:classifiers":[
        {
            "category":"Professional",
            "subcategory":"Business Services",
            "type":"Services"
        }
    ],
    "sg:phone":"+1   ",
    "sg:postcode":"08742",
    "sg:province":"NJ",
    "wof:name":"Cfp Inc",
    "wof:placetype":"venue"
},
  "geometry": {"coordinates":[-74.06679699999999,40.080163],"type":"Point"}
}