{
  "type": "Feature",
  "properties": {
    "addr:full":"1981 Novins Dr Toms River NJ 08753",
    "addr:housenumber":"1981",
    "addr:postcode":"08753",
    "addr:street":"Novins Dr",
    "iso:country":"US",
    "sg:address":"1981 Novins Dr",
    "sg:city":"Toms River",
    "sg:classifiers":[
        {
            "category":"Professional",
            "type":"Services"
        }
    ],
    "sg:phone":"+1   ",
    "sg:postcode":"08753",
    "sg:province":"NJ",
    "wof:name":"Gary J Faden",
    "wof:placetype":"venue"
},
  "geometry": {"coordinates":[-74.153862,40.013696],"type":"Point"}
}