{
  "type": "Feature",
  "properties": {
    "iso:country":"US",
    "sg:address":"205 Rutgers St",
    "sg:city":"Maplewood",
    "sg:classifiers":[
        {
            "category":"Building & Trades",
            "subcategory":"Landscaping Services",
            "type":"Services"
        }
    ],
    "sg:phone":"+1 973 762 5221",
    "sg:postcode":"07040",
    "sg:province":"NJ",
    "sg:tags":[
        "ornamental",
        "tree",
        "shrub"
    ],
    "wof:name":"Maplewood Tree Experts",
    "wof:placetype":"venue"
},
  "geometry": {"coordinates":[-74.263138,40.716517],"type":"Point"}
}