{
  "type": "Feature",
  "properties": {
    "iso:country":"US",
    "sg:address":"24 Abingdon Ave",
    "sg:city":"Medford",
    "sg:classifiers":[
        {
            "category":"Health Services",
            "subcategory":"Medical Lab",
            "type":"Services"
        }
    ],
    "sg:phone":"+1 609 714 3680",
    "sg:postcode":"08055",
    "sg:province":"NJ",
    "sg:tags":[
        "laboratory"
    ],
    "wof:name":"Clinical Network Solutions",
    "wof:placetype":"venue"
},
  "geometry": {"coordinates":[-74.818145,39.837298],"type":"Point"}
}