{
  "type": "Feature",
  "properties": {
    "iso:country":"US",
    "sg:address":"7150 N Park Dr",
    "sg:city":"Merchantville",
    "sg:classifiers":[
        {
            "category":"Building & Trades",
            "subcategory":"Electrical",
            "type":"Services"
        },
        {
            "category":"Manufacturing",
            "subcategory":"Electronics",
            "type":"Manufacturing & Wholesale Goods"
        }
    ],
    "sg:phone":"+1 856 910 1166",
    "sg:postcode":"08109",
    "sg:province":"NJ",
    "sg:tags":[
        "telecommunication",
        "assembles",
        "equipment",
        "design",
        "intelligent",
        "market"
    ],
    "wof:name":"Science Dynamics Corp",
    "wof:placetype":"venue"
},
  "geometry": {"coordinates":[-75.082531,39.927553],"type":"Point"}
}