{
  "type": "Feature",
  "properties": {
    "addr:full":"42 Monroe St Passaic NJ 07055",
    "addr:housenumber":"42",
    "addr:postcode":"07055",
    "addr:street":"Monroe St",
    "iso:country":"US",
    "sg:address":"42 Monroe St",
    "sg:city":"Passaic",
    "sg:classifiers":[
        {
            "category":"Personal",
            "subcategory":"Beauty Salon",
            "type":"Services"
        }
    ],
    "sg:phone":"+1   ",
    "sg:postcode":"07055",
    "sg:province":"NJ",
    "sg:tags":[
        "shop"
    ],
    "wof:name":"Sonias Beauty Center Unisex",
    "wof:placetype":"venue"
},
  "geometry": {"coordinates":[-74.116674,40.868428],"type":"Point"}
}