{
  "type": "Feature",
  "properties": {
    "addr:full":"441 White Horse Pike Atco NJ 08004",
    "addr:housenumber":"441",
    "addr:postcode":"08004",
    "addr:street":"White Horse Pike",
    "iso:country":"US",
    "sg:address":"441 White Horse Pike",
    "sg:city":"Atco",
    "sg:classifiers":[
        {
            "category":"Retail",
            "subcategory":"Funeral Services",
            "type":"Services"
        }
    ],
    "sg:phone":"+1 856 767 0539",
    "sg:postcode":"08004",
    "sg:province":"NJ",
    "sg:tags":[
        "director"
    ],
    "wof:name":"Leroy P Wooster Funeral Home",
    "wof:placetype":"venue"
},
  "geometry": {"coordinates":[-74.89210300000001,39.765954],"type":"Point"}
}