{
  "type": "Feature",
  "properties": {
    "iso:country":"US",
    "sg:address":"3062 S Wood Ave",
    "sg:city":"Linden",
    "sg:classifiers":[
        {
            "category":"Deli",
            "type":"Food & Drink"
        },
        {
            "category":"Food & Beverages",
            "subcategory":"Bakery",
            "type":"Retail Goods"
        }
    ],
    "sg:phone":"+1 908 523 1313",
    "sg:postcode":"07036",
    "sg:province":"NJ",
    "sg:tags":[
        "sandwich"
    ],
    "wof:name":"Podlasie Deli",
    "wof:placetype":"venue"
},
  "geometry": {"coordinates":[-74.22737600000001,40.614508],"type":"Point"}
}