{
  "type": "Feature",
  "properties": {
    "addr:full":"152 Market St Newark NJ 07102",
    "addr:housenumber":"152",
    "addr:postcode":"07102",
    "addr:street":"Market St",
    "iso:country":"US",
    "sg:address":"152 Market St",
    "sg:city":"Newark",
    "sg:classifiers":[
        {
            "category":"Shopping",
            "subcategory":"Beauty & Cosmetics",
            "type":"Retail Goods"
        }
    ],
    "sg:phone":"+1 973 799 0800",
    "sg:postcode":"07102",
    "sg:province":"NJ",
    "sg:tags":[
        "supply"
    ],
    "wof:name":"Hair Man Beauty",
    "wof:placetype":"venue"
},
  "geometry": {"coordinates":[-74.173103,40.735699],"type":"Point"}
}