{
  "type": "Feature",
  "properties": {
    "addr:full":"1885 N Olden Ave Exd Trenton NJ 08638",
    "addr:housenumber":"1885",
    "addr:postcode":"08638",
    "addr:street":"N Olden Ave Exd",
    "iso:country":"US",
    "sg:address":"1885 N Olden Ave Exd",
    "sg:city":"Trenton",
    "sg:classifiers":[
        {
            "category":"Restaurant",
            "type":"Food & Drink"
        }
    ],
    "sg:phone":"+1 609 883 2815",
    "sg:postcode":"08638",
    "sg:province":"NJ",
    "wof:name":"Mc Donald's",
    "wof:placetype":"venue"
},
  "geometry": {"coordinates":[-74.77800499999999,40.250042],"type":"Point"}
}