{
  "type": "Feature",
  "properties": {
    "addr:full":"14 Coolidge Ave Caldwell NJ 07006",
    "addr:housenumber":"14",
    "addr:postcode":"07006",
    "addr:street":"Coolidge Ave",
    "iso:country":"US",
    "sg:address":"14 Coolidge Ave",
    "sg:city":"Caldwell",
    "sg:classifiers":[
        {
            "category":"Organizations",
            "subcategory":"Religious Organization",
            "type":"Services"
        }
    ],
    "sg:phone":"+1   ",
    "sg:postcode":"07006",
    "sg:province":"NJ",
    "wof:name":"David Bulka Rev",
    "wof:placetype":"venue"
},
  "geometry": {"coordinates":[-74.270115,40.848824],"type":"Point"}
}