{
  "type": "Feature",
  "properties": {
    "iso:country":"US",
    "sg:address":"99 W 22nd St",
    "sg:city":"Bayonne",
    "sg:classifiers":[
        {
            "category":"Building & Trades",
            "subcategory":"Construction",
            "type":"Services"
        }
    ],
    "sg:phone":"+1 732 254 6363",
    "sg:postcode":"07002",
    "sg:province":"NJ",
    "sg:tags":[
        "general",
        "contractor"
    ],
    "wof:name":"V & A Constr & Carpentry Inc",
    "wof:placetype":"venue"
},
  "geometry": {"coordinates":[-74.121965,40.664482],"type":"Point"}
}