{
  "type": "Feature",
  "properties": {
    "addr:full":"41 W Pleasant Ave Maywood NJ 07607",
    "addr:housenumber":"41",
    "addr:postcode":"07607",
    "addr:street":"W Pleasant Ave",
    "iso:country":"US",
    "sg:address":"41 W Pleasant Ave",
    "sg:city":"Maywood",
    "sg:classifiers":[
        {
            "category":"Restaurant",
            "type":"Food & Drink"
        }
    ],
    "sg:phone":"+1 201 368 0308",
    "sg:postcode":"07607",
    "sg:province":"NJ",
    "sg:tags":[
        "eating"
    ],
    "wof:name":"Dragons Garden",
    "wof:placetype":"venue"
},
  "geometry": {"coordinates":[-74.0625,40.904301],"type":"Point"}
}