{
  "type": "Feature",
  "properties": {
    "iso:country":"US",
    "sg:address":"1067 Arcadian Way",
    "sg:city":"Fort Lee",
    "sg:classifiers":[
        {
            "category":"Professional",
            "subcategory":"Business Services",
            "type":"Services"
        }
    ],
    "sg:phone":"+1   ",
    "sg:postcode":"07024",
    "sg:province":"NJ",
    "wof:name":"Effects",
    "wof:placetype":"venue"
},
  "geometry": {"coordinates":[-73.97497300000001,40.834322],"type":"Point"}
}