{
  "type": "Feature",
  "properties": {
    "iso:country":"US",
    "sg:address":"20 Jefferson St",
    "sg:city":"Riverside",
    "sg:classifiers":[
        {
            "category":"Building & Trades",
            "subcategory":"Construction",
            "type":"Services"
        }
    ],
    "sg:phone":"+1 856 764 0871",
    "sg:postcode":"08075",
    "sg:province":"NJ",
    "sg:tags":[
        "contractor"
    ],
    "wof:name":"B C S Construction",
    "wof:placetype":"venue"
},
  "geometry": {"coordinates":[-74.96060199999999,40.040298],"type":"Point"}
}