{
  "type": "Feature",
  "properties": {
    "iso:country":"US",
    "sg:address":"299 Woodward Rd",
    "sg:city":"Englishtown",
    "sg:classifiers":[
        {
            "category":"Home & Garden",
            "subcategory":"Garden Supply",
            "type":"Retail Goods"
        }
    ],
    "sg:phone":"+1 732 780 7022",
    "sg:postcode":"07726",
    "sg:province":"NJ",
    "sg:tags":[
        "nurseryman"
    ],
    "sg:website":"www.fourseasonsnursery.com",
    "wof:name":"Four Seasons Nursery Co",
    "wof:placetype":"venue"
},
  "geometry": {"coordinates":[-74.353877,40.266936],"type":"Point"}
}