{
  "type": "Feature",
  "properties": {
    "iso:country":"US",
    "sg:address":"31 Van Houten St",
    "sg:city":"Paterson",
    "sg:classifiers":[
        {
            "category":"Organizations",
            "subcategory":"Non-profit Organization",
            "type":"Services"
        },
        {
            "category":"Health Services",
            "subcategory":"Clinic",
            "type":"Services"
        }
    ],
    "sg:phone":"+1 973 742 1126",
    "sg:postcode":"07505",
    "sg:province":"NJ",
    "sg:tags":[
        "information",
        "treatment",
        "specialty",
        "alcoholism",
        "outpatient"
    ],
    "wof:name":"Adult Rehabilitation Center",
    "wof:placetype":"venue"
},
  "geometry": {"coordinates":[-74.17718499999999,40.917483],"type":"Point"}
}