{
  "type": "Feature",
  "properties": {
    "addr:full":"6 E Main St Clinton NJ 08809",
    "addr:housenumber":"6",
    "addr:postcode":"08809",
    "addr:street":"E Main St",
    "iso:country":"US",
    "sg:address":"6 E Main St",
    "sg:city":"Clinton",
    "sg:classifiers":[
        {
            "category":"Communications",
            "subcategory":"Film & Video Production",
            "type":"Services"
        }
    ],
    "sg:phone":"+1   ",
    "sg:postcode":"08809",
    "sg:province":"NJ",
    "sg:tags":[
        "motion",
        "picture"
    ],
    "wof:name":"Keepsake Family Tree Video",
    "wof:placetype":"venue"
},
  "geometry": {"coordinates":[-74.90812200000001,40.637592],"type":"Point"}
}