{
  "type": "Feature",
  "properties": {
    "iso:country":"US",
    "sg:address":"109 Lupine Way",
    "sg:city":"Stirling",
    "sg:classifiers":[
        {
            "category":"Insurance",
            "subcategory":"Hazard Insurance",
            "type":"Services"
        }
    ],
    "sg:phone":"+1   ",
    "sg:postcode":"07980",
    "sg:province":"NJ",
    "sg:tags":[
        "life",
        "carrier"
    ],
    "wof:name":"USAA",
    "wof:placetype":"venue"
},
  "geometry": {"coordinates":[-74.49634500000001,40.683495],"type":"Point"}
}