{
  "type": "Feature",
  "properties": {
    "iso:country":"US",
    "sg:address":"701 State Rte 73",
    "sg:city":"Marlton",
    "sg:classifiers":[
        {
            "category":"Banks & Credit Unions",
            "subcategory":"Bank",
            "type":"Services"
        }
    ],
    "sg:phone":"+1 856 797 8150",
    "sg:postcode":"08053",
    "sg:province":"NJ",
    "sg:tags":[
        "loan",
        "real estate"
    ],
    "sg:website":"www.windsorfinancial.com",
    "wof:name":"Windsor Financial Mtg Corp",
    "wof:placetype":"venue"
},
  "geometry": {"coordinates":[-74.921978,39.87103],"type":"Point"}
}