{
  "type": "Feature",
  "properties": {
    "addr:full":"225 Broadway Bayonne NJ 07002",
    "addr:housenumber":"225",
    "addr:postcode":"07002",
    "addr:street":"Broadway",
    "iso:country":"US",
    "sg:address":"225 Broadway",
    "sg:city":"Bayonne",
    "sg:phone":"+1 201 437 1800",
    "sg:postcode":"07002",
    "sg:province":"NJ",
    "sg:tags":[
        "equipment",
        "commercial",
        "restaurant"
    ],
    "wof:name":"Great Wall Restaurant",
    "wof:placetype":"venue"
},
  "geometry": {"coordinates":[-74.12640399999999,40.654301],"type":"Point"}
}