{
  "type": "Feature",
  "properties": {
    "iso:country":"US",
    "sg:address":"10 Sterling Ct",
    "sg:city":"Whippany",
    "sg:classifiers":[
        {
            "category":"Organizations",
            "subcategory":"Religious Organization",
            "type":"Services"
        }
    ],
    "sg:phone":"+1 973 560 9348",
    "sg:postcode":"07981",
    "sg:province":"NJ",
    "wof:name":"Word Faith Community Church",
    "wof:placetype":"venue"
},
  "geometry": {"coordinates":[-74.43179600000001,40.805488],"type":"Point"}
}