{
  "type": "Feature",
  "properties": {
    "addr:full":"949 Main Ave Passaic NJ 07055",
    "addr:housenumber":"949",
    "addr:postcode":"07055",
    "addr:street":"Main Ave",
    "iso:country":"US",
    "sg:address":"949 Main Ave",
    "sg:city":"Passaic",
    "sg:classifiers":[
        {
            "category":"Shopping",
            "subcategory":"Computers & Home Electronics",
            "type":"Retail Goods"
        }
    ],
    "sg:phone":"+1   ",
    "sg:postcode":"07055",
    "sg:province":"NJ",
    "wof:name":"Gateway Funding Inc",
    "wof:placetype":"venue"
},
  "geometry": {"coordinates":[-74.134005,40.869109],"type":"Point"}
}