{
  "type": "Feature",
  "properties": {
    "addr:full":"455 State Rte 17 Ramsey NJ 07446",
    "addr:housenumber":"455",
    "addr:postcode":"07446",
    "addr:street":"State Rte 17",
    "iso:country":"US",
    "sg:address":"455 State Rte 17",
    "sg:city":"Ramsey",
    "sg:classifiers":[
        {
            "category":"Home & Garden",
            "subcategory":"Furniture",
            "type":"Retail Goods"
        }
    ],
    "sg:phone":"+1 201 327 6257",
    "sg:postcode":"07446",
    "sg:province":"NJ",
    "sg:tags":[
        "equipment",
        "kitchen",
        "cabinet"
    ],
    "wof:name":"Platon Interiors Custom Cbntry",
    "wof:placetype":"venue"
},
  "geometry": {"coordinates":[-74.120422,41.055086],"type":"Point"}
}