{
  "type": "Feature",
  "properties": {
    "iso:country":"US",
    "sg:address":"17 Hulfish St",
    "sg:city":"Princeton",
    "sg:classifiers":[
        {
            "category":"Banks & Credit Unions",
            "subcategory":"Financial Services",
            "type":"Services"
        }
    ],
    "sg:phone":"+1 609 924 3453",
    "sg:postcode":"08542",
    "sg:province":"NJ",
    "sg:tags":[
        "company",
        "holding"
    ],
    "wof:name":"Hull Junction Holding Corp",
    "wof:placetype":"venue"
},
  "geometry": {"coordinates":[-74.663533,40.3502],"type":"Point"}
}