{
  "type": "Feature",
  "properties": {
    "iso:country":"US",
    "sg:address":"2 State Rte 37",
    "sg:city":"Toms River",
    "sg:classifiers":[
        {
            "category":"Shopping",
            "subcategory":"Photographic Equipment",
            "type":"Retail Goods"
        }
    ],
    "sg:phone":"+1   ",
    "sg:postcode":"08753",
    "sg:province":"NJ",
    "sg:tags":[
        "shop",
        "camera"
    ],
    "wof:name":"Cli",
    "wof:placetype":"venue"
},
  "geometry": {"coordinates":[-74.200453,39.963251],"type":"Point"}
}