{
  "type": "Feature",
  "properties": {
    "iso:country":"US",
    "sg:address":"284 US Hwy 206",
    "sg:city":"Hillsborough",
    "sg:classifiers":[
        {
            "category":"Health Services",
            "subcategory":"Health Practitioner",
            "type":"Services"
        }
    ],
    "sg:phone":"+1 908 874 3442",
    "sg:postcode":"08844",
    "sg:province":"NJ",
    "sg:tags":[
        "hypnotist"
    ],
    "wof:name":"Center For Positive Change",
    "wof:placetype":"venue"
},
  "geometry": {"coordinates":[-74.627797,40.524479],"type":"Point"}
}