{
  "type": "Feature",
  "properties": {
    "iso:country":"US",
    "sg:address":"255 Old New Brunswick Rd",
    "sg:city":"Piscataway",
    "sg:classifiers":[
        {
            "category":"Organizations",
            "subcategory":"Religious Organization",
            "type":"Services"
        }
    ],
    "sg:phone":"+1 732 562 1818",
    "sg:postcode":"08854",
    "sg:province":"NJ",
    "wof:name":"Grace Alliance Church",
    "wof:placetype":"venue"
},
  "geometry": {"coordinates":[-74.47490500000001,40.552335],"type":"Point"}
}