{
  "type": "Feature",
  "properties": {
    "iso:country":"US",
    "sg:address":"869 Fischer Blvd",
    "sg:city":"Toms River",
    "sg:classifiers":[
        {
            "category":"Taxi",
            "type":"Transportation"
        }
    ],
    "sg:phone":"+1 732 288 1213",
    "sg:postcode":"08753",
    "sg:province":"NJ",
    "sg:tags":[
        "taxicab"
    ],
    "wof:name":"A All Star Taxi",
    "wof:placetype":"venue"
},
  "geometry": {"coordinates":[-74.135006,39.972225],"type":"Point"}
}