{
  "type": "Feature",
  "properties": {
    "iso:country":"US",
    "sg:address":"5 Woodstone Dr",
    "sg:city":"Cedar Grove",
    "sg:classifiers":[
        {
            "category":"Organizations",
            "subcategory":"Religious Organization",
            "type":"Services"
        }
    ],
    "sg:phone":"+1 973 857 6671",
    "sg:postcode":"07009",
    "sg:province":"NJ",
    "sg:tags":[
        "church"
    ],
    "wof:name":"Coptic Orthodox Church",
    "wof:placetype":"venue"
},
  "geometry": {"coordinates":[-74.218819,40.840352],"type":"Point"}
}