{
  "type": "Feature",
  "properties": {
    "iso:country":"US",
    "sg:address":"233 Park St",
    "sg:city":"Hackensack",
    "sg:classifiers":[
        {
            "category":"Autos & Motor Vehicles",
            "subcategory":"Automobile Sales",
            "type":"Retail Goods"
        }
    ],
    "sg:phone":"+1 201 489 6770",
    "sg:postcode":"07601",
    "sg:province":"NJ",
    "sg:tags":[
        "limo"
    ],
    "wof:name":"Rodelli Uomo",
    "wof:placetype":"venue"
},
  "geometry": {"coordinates":[-74.0467,40.8866],"type":"Point"}
}