{
  "type": "Feature",
  "properties": {
    "iso:country":"US",
    "sg:address":"1127 S Main St",
    "sg:city":"Phillipsburg",
    "sg:classifiers":[
        {
            "category":"Shopping",
            "type":"Retail Goods"
        }
    ],
    "sg:phone":"+1 908 454 1127",
    "sg:postcode":"08865",
    "sg:province":"NJ",
    "sg:tags":[
        "pet",
        "food",
        "supply"
    ],
    "wof:name":"Harry S Pursel Inc",
    "wof:placetype":"venue"
},
  "geometry": {"coordinates":[-75.167215,40.677253],"type":"Point"}
}