{
  "type": "Feature",
  "properties": {
    "iso:country":"US",
    "sg:address":"585 Saddle River Rd",
    "sg:city":"Saddle Brook",
    "sg:classifiers":[
        {
            "category":"Organizations",
            "subcategory":"Professional Association",
            "type":"Services"
        }
    ],
    "sg:phone":"+1   ",
    "sg:postcode":"07663",
    "sg:province":"NJ",
    "sg:tags":[
        "business"
    ],
    "wof:name":"Armenian General Benevolent Un",
    "wof:placetype":"venue"
},
  "geometry": {"coordinates":[-74.09388199999999,40.911986],"type":"Point"}
}