{
  "type": "Feature",
  "properties": {
    "iso:country":"US",
    "sg:address":"735 Highland Ave",
    "sg:city":"Palmyra",
    "sg:classifiers":[
        {
            "category":"Building & Trades",
            "subcategory":"Equipment Rental",
            "type":"Services"
        }
    ],
    "sg:phone":"+1   ",
    "sg:postcode":"08065",
    "sg:province":"NJ",
    "wof:name":"Johns Jr Jumps",
    "wof:placetype":"venue"
},
  "geometry": {"coordinates":[-75.016085,40.002954],"type":"Point"}
}