{
  "type": "Feature",
  "properties": {
    "addr:full":"421 Hackensack St Carlstadt NJ 07072",
    "addr:housenumber":"421",
    "addr:postcode":"07072",
    "addr:street":"Hackensack St",
    "iso:country":"US",
    "sg:address":"421 Hackensack St",
    "sg:city":"Carlstadt",
    "sg:classifiers":[
        {
            "category":"Wholesale",
            "subcategory":"Medical Equipment & Supplies",
            "type":"Manufacturing & Wholesale Goods"
        },
        {
            "category":"Manufacturing",
            "subcategory":"Tools & Machinery",
            "type":"Manufacturing & Wholesale Goods"
        }
    ],
    "sg:phone":"+1 201 935 5561",
    "sg:postcode":"07072",
    "sg:province":"NJ",
    "sg:tags":[
        "manufacture",
        "electronics",
        "monitoring",
        "devices"
    ],
    "wof:name":"Alternative Design Systems Inc",
    "wof:placetype":"venue"
},
  "geometry": {"coordinates":[-74.090874,40.838413],"type":"Point"}
}