{
  "type": "Feature",
  "properties": {
    "addr:full":"150 River Rd Montville NJ 07045",
    "addr:housenumber":"150",
    "addr:postcode":"07045",
    "addr:street":"River Rd",
    "iso:country":"US",
    "sg:address":"150 River Rd",
    "sg:city":"Montville",
    "sg:classifiers":[
        {
            "category":"Communications",
            "type":"Services"
        },
        {
            "category":"Professional",
            "subcategory":"Advertising",
            "type":"Services"
        }
    ],
    "sg:phone":"+1 973 334 0300",
    "sg:postcode":"07045",
    "sg:province":"NJ",
    "sg:tags":[
        "agency"
    ],
    "wof:name":"Rienzi & Rienzi Communications",
    "wof:placetype":"venue"
},
  "geometry": {"coordinates":[-74.37064599999999,40.890465],"type":"Point"}
}