{
  "type": "Feature",
  "properties": {
    "iso:country":"US",
    "sg:address":"74 Main Ave",
    "sg:city":"Ocean Grove",
    "sg:classifiers":[
        {
            "category":"Building & Trades",
            "subcategory":"Construction",
            "type":"Services"
        }
    ],
    "sg:phone":"+1 732 776 6262",
    "sg:postcode":"07756",
    "sg:province":"NJ",
    "sg:tags":[
        "general",
        "contractor"
    ],
    "wof:name":"Jack Green Construction LLC",
    "wof:placetype":"venue"
},
  "geometry": {"coordinates":[-74.00805099999999,40.212207],"type":"Point"}
}