{
  "type": "Feature",
  "properties": {
    "iso:country":"US",
    "sg:address":"207 Omni Dr",
    "sg:city":"Hillsborough",
    "sg:classifiers":[
        {
            "category":"Organizations",
            "subcategory":"Religious Organization",
            "type":"Services"
        }
    ],
    "sg:phone":"+1 908 431 4373",
    "sg:postcode":"08844",
    "sg:province":"NJ",
    "sg:tags":[
        "church"
    ],
    "sg:website":"www.crossroadsnj.org",
    "wof:name":"Cross Roads Community Church",
    "wof:placetype":"venue"
},
  "geometry": {"coordinates":[-74.629071,40.524378],"type":"Point"}
}