{
  "type": "Feature",
  "properties": {
    "addr:full":"508 Brunswick Ave Trenton NJ 08638",
    "addr:housenumber":"508",
    "addr:postcode":"08638",
    "addr:street":"Brunswick Ave",
    "iso:country":"US",
    "sg:address":"508 Brunswick Ave",
    "sg:city":"Trenton",
    "sg:classifiers":[
        {
            "category":"Professional",
            "type":"Services"
        }
    ],
    "sg:phone":"+1 908 282 0901",
    "sg:postcode":"08638",
    "sg:province":"NJ",
    "sg:tags":[
        "establishment"
    ],
    "wof:name":"Cardtronics",
    "wof:placetype":"venue"
},
  "geometry": {"coordinates":[-74.754276,40.233141],"type":"Point"}
}