{
  "type": "Feature",
  "properties": {
    "addr:full":"323 61st St West New York NJ 07093",
    "addr:housenumber":"323",
    "addr:postcode":"nj 07093",
    "addr:street":"61St St West",
    "iso:country":"US",
    "sg:address":"323 61st St",
    "sg:city":"West New York",
    "sg:classifiers":[
        {
            "category":"Restaurant",
            "type":"Food & Drink"
        }
    ],
    "sg:phone":"+1 201 868 3155",
    "sg:postcode":"07093",
    "sg:province":"NJ",
    "sg:tags":[
        "mexican",
        "eating"
    ],
    "wof:name":"Xochimilco Mexican Restaurant",
    "wof:placetype":"venue"
},
  "geometry": {"coordinates":[-74.012299,40.788799],"type":"Point"}
}