{
  "type": "Feature",
  "properties": {
    "addr:full":"19 Mount Ephraim Ave Mt Ephraim NJ 08059",
    "addr:housenumber":"19",
    "addr:postcode":"08059",
    "addr:street":"Mount Ephraim Ave Mt",
    "iso:country":"US",
    "sg:address":"19 Mount Ephraim Ave",
    "sg:city":"Mt Ephraim",
    "sg:classifiers":[
        {
            "category":"Health Services",
            "subcategory":"Doctor",
            "type":"Services"
        }
    ],
    "sg:phone":"+1 856 931 3240",
    "sg:postcode":"08059",
    "sg:province":"NJ",
    "sg:tags":[
        "physician",
        "surgeon"
    ],
    "wof:name":"Family Practice",
    "wof:placetype":"venue"
},
  "geometry": {"coordinates":[-75.08753299999999,39.880595],"type":"Point"}
}