{
  "type": "Feature",
  "properties": {
    "iso:country":"US",
    "sg:address":"52 3rd St",
    "sg:city":"Newark",
    "sg:classifiers":[
        {
            "category":"Social Services",
            "subcategory":"Child Care",
            "type":"Services"
        }
    ],
    "sg:phone":"+1   ",
    "sg:postcode":"07107",
    "sg:province":"NJ",
    "sg:tags":[
        "day"
    ],
    "wof:name":"Terrys Learning Center",
    "wof:placetype":"venue"
},
  "geometry": {"coordinates":[-74.189404,40.749316],"type":"Point"}
}