{
  "type": "Feature",
  "properties": {
    "iso:country":"US",
    "sg:address":"4 Hartford Rd",
    "sg:city":"Medford",
    "sg:classifiers":[
        {
            "category":"Organizations",
            "subcategory":"Religious Organization",
            "type":"Services"
        }
    ],
    "sg:phone":"+1 609 654 4162",
    "sg:postcode":"08055",
    "sg:province":"NJ",
    "sg:tags":[
        "clergy"
    ],
    "wof:name":"Ernest Williams Rev",
    "wof:placetype":"venue"
},
  "geometry": {"coordinates":[-74.833077,39.885419],"type":"Point"}
}