{
  "type": "Feature",
  "properties": {
    "addr:full":"76 Woodvine Ave Trenton NJ 08610",
    "addr:housenumber":"76",
    "addr:postcode":"08610",
    "addr:street":"Woodvine Ave",
    "iso:country":"US",
    "sg:address":"76 Woodvine Ave",
    "sg:city":"Trenton",
    "sg:classifiers":[
        {
            "category":"Building & Trades",
            "subcategory":"Plumbing",
            "type":"Services"
        }
    ],
    "sg:phone":"+1 609 587 2561",
    "sg:postcode":"08610",
    "sg:province":"NJ",
    "sg:tags":[
        "air",
        "refrigeration",
        "conditioning",
        "contractor"
    ],
    "wof:name":"A-1 Air Conditioning",
    "wof:placetype":"venue"
},
  "geometry": {"coordinates":[-74.703709,40.201332],"type":"Point"}
}