{
  "type": "Feature",
  "properties": {
    "addr:full":"3101 Boardwalk Atlantic City NJ 08401",
    "addr:housenumber":"3101",
    "addr:postcode":"08401",
    "addr:street":"Boardwalk",
    "iso:country":"US",
    "sg:address":"3101 Boardwalk",
    "sg:city":"Atlantic City",
    "sg:classifiers":[
        {
            "category":"Wholesale",
            "subcategory":"Machinery & Supplies",
            "type":"Manufacturing & Wholesale Goods"
        }
    ],
    "sg:phone":"+1 609 344 5649",
    "sg:postcode":"08401",
    "sg:province":"NJ",
    "sg:tags":[
        "distributes",
        "truck"
    ],
    "wof:name":"Thayco Trailer Super Center",
    "wof:placetype":"venue"
},
  "geometry": {"coordinates":[-74.448134,39.350584],"type":"Point"}
}