{
  "type": "Feature",
  "properties": {
    "iso:country":"US",
    "sg:address":"409 North Ave E",
    "sg:city":"Cranford",
    "sg:classifiers":[
        {
            "category":"Professional",
            "subcategory":"Employment Agencies",
            "type":"Services"
        }
    ],
    "sg:phone":"+1   ",
    "sg:postcode":"07016",
    "sg:province":"NJ",
    "wof:name":"SFG International",
    "wof:placetype":"venue"
},
  "geometry": {"coordinates":[-74.288825,40.658243],"type":"Point"}
}