{
  "type": "Feature",
  "properties": {
    "iso:country":"US",
    "sg:address":"9 Slab Branch Rd",
    "sg:city":"Medford",
    "sg:classifiers":[
        {
            "category":"Professional",
            "type":"Services"
        }
    ],
    "sg:phone":"+1   ",
    "sg:postcode":"08055",
    "sg:province":"NJ",
    "wof:name":"Deskscribe",
    "wof:placetype":"venue"
},
  "geometry": {"coordinates":[-74.859218,39.83174],"type":"Point"}
}