{
  "type": "Feature",
  "properties": {
    "addr:full":"183 Vassar Ave Newark NJ 07112",
    "addr:housenumber":"183",
    "addr:postcode":"07112",
    "addr:street":"Vassar Ave",
    "iso:country":"US",
    "sg:address":"183 Vassar Ave",
    "sg:city":"Newark",
    "sg:classifiers":[
        {
            "category":"Professional",
            "type":"Services"
        }
    ],
    "sg:phone":"+1   ",
    "sg:postcode":"07112",
    "sg:province":"NJ",
    "wof:name":"Metro World Service",
    "wof:placetype":"venue"
},
  "geometry": {"coordinates":[-74.21544400000001,40.707337],"type":"Point"}
}