{
  "type": "Feature",
  "properties": {
    "iso:country":"US",
    "sg:address":"7 Brick Plant Rd",
    "sg:city":"South River",
    "sg:classifiers":[
        {
            "category":"Freight",
            "type":"Transportation"
        }
    ],
    "sg:phone":"+1 732 254 1041",
    "sg:postcode":"08882",
    "sg:province":"NJ",
    "wof:name":"Arnold Transportation Svc",
    "wof:placetype":"venue"
},
  "geometry": {"coordinates":[-74.390261,40.461152],"type":"Point"}
}