{
  "type": "Feature",
  "properties": {
    "iso:country":"US",
    "sg:address":"607 Parker Ave",
    "sg:city":"Brick",
    "sg:classifiers":[
        {
            "category":"Building & Trades",
            "subcategory":"Construction",
            "type":"Services"
        }
    ],
    "sg:phone":"+1 732 899 6947",
    "sg:postcode":"08724",
    "sg:province":"NJ",
    "sg:tags":[
        "drywall",
        "contractor"
    ],
    "wof:name":"H & F Drywall",
    "wof:placetype":"venue"
},
  "geometry": {"coordinates":[-74.083065,40.057992],"type":"Point"}
}