{
  "type": "Feature",
  "properties": {
    "addr:full":"1926 Union Valley Rd # 4 Hewitt NJ 07421",
    "addr:housenumber":"1926",
    "addr:postcode":"07421",
    "addr:street":"Union Valley Rd # 4",
    "iso:country":"US",
    "sg:address":"1926 Union Valley Rd # 4",
    "sg:city":"Hewitt",
    "sg:classifiers":[
        {
            "category":"Shopping",
            "subcategory":"Gifts & Souvenirs",
            "type":"Retail Goods"
        },
        {
            "category":"Shopping",
            "subcategory":"Jewelry",
            "type":"Retail Goods"
        },
        {
            "category":"Manufacturing",
            "subcategory":"Jewelry",
            "type":"Manufacturing & Wholesale Goods"
        }
    ],
    "sg:phone":"+1 973 728 2927",
    "sg:postcode":"07421",
    "sg:province":"NJ",
    "sg:tags":[
        "shop",
        "designer",
        "jeweler"
    ],
    "sg:website":"http://www.flagsandsilver.com",
    "wof:name":"That Special Gift",
    "wof:placetype":"venue"
},
  "geometry": {"coordinates":[-74.354134,41.15432],"type":"Point"}
}