{
  "type": "Feature",
  "properties": {
    "addr:full":"193 New York Ave Newark NJ 07105",
    "addr:housenumber":"193",
    "addr:postcode":"07105",
    "addr:street":"New York Ave",
    "iso:country":"US",
    "sg:address":"193 New York Ave",
    "sg:city":"Newark",
    "sg:classifiers":[
        {
            "category":"Real Estate",
            "subcategory":"Architect",
            "type":"Services"
        }
    ],
    "sg:phone":"+1   ",
    "sg:postcode":"07105",
    "sg:province":"NJ",
    "sg:tags":[
        "architectural"
    ],
    "wof:name":"Jose Gennaro AIA",
    "wof:placetype":"venue"
},
  "geometry": {"coordinates":[-74.162367,40.726275],"type":"Point"}
}