{
  "type": "Feature",
  "properties": {
    "addr:full":"96 Grant Ave Jersey City NJ 07305",
    "addr:housenumber":"96",
    "addr:postcode":"07305",
    "addr:street":"Grant Ave",
    "iso:country":"US",
    "sg:address":"96 Grant Ave",
    "sg:city":"Jersey City",
    "sg:classifiers":[
        {
            "category":"Building & Trades",
            "subcategory":"Construction",
            "type":"Services"
        }
    ],
    "sg:phone":"+1 201 435 0854",
    "sg:postcode":"07305",
    "sg:province":"NJ",
    "sg:tags":[
        "general",
        "contractor"
    ],
    "wof:name":"Fowlkes & Sons",
    "wof:placetype":"venue"
},
  "geometry": {"coordinates":[-74.083068,40.710508],"type":"Point"}
}