{
  "type": "Feature",
  "properties": {
    "iso:country":"US",
    "sg:address":"111 Mount Laurel Rd",
    "sg:city":"Mt Laurel",
    "sg:classifiers":[
        {
            "category":"Autos & Motor Vehicles",
            "subcategory":"Boat Sales",
            "type":"Retail Goods"
        }
    ],
    "sg:phone":"+1 856 231 0106",
    "sg:postcode":"08054",
    "sg:province":"NJ",
    "sg:tags":[
        "propeller"
    ],
    "wof:name":"Atlantis Propeller Inc",
    "wof:placetype":"venue"
},
  "geometry": {"coordinates":[-74.926925,39.958286],"type":"Point"}
}