{
  "type": "Feature",
  "properties": {
    "addr:full":"441 US Hwy 1 Elizabeth NJ 07202",
    "addr:housenumber":"441",
    "addr:postcode":"07202",
    "addr:street":"Us Hwy 1",
    "iso:country":"US",
    "sg:address":"441 US Hwy 1",
    "sg:city":"Elizabeth",
    "sg:classifiers":[
        {
            "category":"Retail",
            "subcategory":"Auto Rental",
            "type":"Services"
        }
    ],
    "sg:phone":"+1 908 820 4995",
    "sg:postcode":"07202",
    "sg:province":"NJ",
    "sg:tags":[
        "renting",
        "truck",
        "leasing"
    ],
    "wof:name":"U-Haul Co",
    "wof:placetype":"venue"
},
  "geometry": {"coordinates":[-74.212378,40.653616],"type":"Point"}
}