{
  "type": "Feature",
  "properties": {
    "addr:full":"314 1st St Elizabeth NJ 07206",
    "addr:housenumber":"314",
    "addr:postcode":"07206",
    "addr:street":"1St St",
    "iso:country":"US",
    "sg:address":"314 1st St",
    "sg:city":"Elizabeth",
    "sg:classifiers":[
        {
            "category":"Manufacturing",
            "subcategory":"Wood Products",
            "type":"Manufacturing & Wholesale Goods"
        }
    ],
    "sg:phone":"+1 908 527 6186",
    "sg:postcode":"07206",
    "sg:province":"NJ",
    "sg:tags":[
        "mfg"
    ],
    "wof:name":"Aja Woodworking",
    "wof:placetype":"venue"
},
  "geometry": {"coordinates":[-74.179794,40.652452],"type":"Point"}
}