{
  "type": "Feature",
  "properties": {
    "iso:country":"US",
    "sg:address":"859 Chambers St",
    "sg:city":"Trenton",
    "sg:classifiers":[
        {
            "category":"Autos & Motor Vehicles",
            "subcategory":"Automobile Sales",
            "type":"Retail Goods"
        }
    ],
    "sg:phone":"+1 609 392 0755",
    "sg:postcode":"08611",
    "sg:province":"NJ",
    "sg:tags":[
        "dealers-used",
        "car",
        "used",
        "cars-wholesale",
        "new"
    ],
    "wof:name":"East Coast Auto Sales",
    "wof:placetype":"venue"
},
  "geometry": {"coordinates":[-74.739746,40.212787],"type":"Point"}
}