{
  "type": "Feature",
  "properties": {
    "addr:full":"2800 US Hwy 130 Cinnaminson NJ 08077",
    "addr:housenumber":"2800",
    "addr:postcode":"08077",
    "addr:street":"Us Hwy 130",
    "iso:country":"US",
    "sg:address":"2800 US Hwy 130",
    "sg:city":"Cinnaminson",
    "sg:classifiers":[
        {
            "category":"Education",
            "subcategory":"Special Training",
            "type":"Public Place"
        }
    ],
    "sg:phone":"+1 856 824 1777",
    "sg:postcode":"08077",
    "sg:province":"NJ",
    "sg:tags":[
        "tutoring"
    ],
    "sg:website":"www.huntingtonlearning.com",
    "wof:name":"Huntington Learning Ctr",
    "wof:placetype":"venue"
},
  "geometry": {"coordinates":[-74.970241,40.008323],"type":"Point"}
}