{
  "type": "Feature",
  "properties": {
    "iso:country":"US",
    "sg:address":"21 Philips Pkwy",
    "sg:city":"Montvale",
    "sg:classifiers":[
        {
            "category":"Health Services",
            "subcategory":"Health Practitioner",
            "type":"Services"
        }
    ],
    "sg:phone":"+1 201 802 9723",
    "sg:postcode":"07645",
    "sg:province":"NJ",
    "wof:name":"Novacare Hudson Physcl Therapy",
    "wof:placetype":"venue"
},
  "geometry": {"coordinates":[-74.058207,41.047929],"type":"Point"}
}