{
  "type": "Feature",
  "properties": {
    "addr:full":"278 Clinton Pl Newark NJ 07112",
    "addr:housenumber":"278",
    "addr:postcode":"07112",
    "addr:street":"Clinton Pl",
    "iso:country":"US",
    "sg:address":"278 Clinton Pl",
    "sg:city":"Newark",
    "sg:classifiers":[
        {
            "category":"Personal",
            "subcategory":"Beauty Salon",
            "type":"Services"
        }
    ],
    "sg:phone":"+1 973 391 0506",
    "sg:postcode":"07112",
    "sg:province":"NJ",
    "wof:name":"Hair To Stay",
    "wof:placetype":"venue"
},
  "geometry": {"coordinates":[-74.21320299999999,40.714538],"type":"Point"}
}