{
  "type": "Feature",
  "properties": {
    "iso:country":"US",
    "sg:address":"339 Ueland Rd",
    "sg:city":"Red Bank",
    "sg:classifiers":[
        {
            "category":"Professional",
            "subcategory":"Art Services",
            "type":"Services"
        }
    ],
    "sg:phone":"+1 732 933 9182",
    "sg:postcode":"07701",
    "sg:province":"NJ",
    "sg:tags":[
        "commercial",
        "graphic",
        "design",
        "designer"
    ],
    "wof:name":"Penmax Graphix Inc",
    "wof:placetype":"venue"
},
  "geometry": {"coordinates":[-74.10826900000001,40.356025],"type":"Point"}
}