{
  "type": "Feature",
  "properties": {
    "iso:country":"US",
    "sg:address":"7001 Black Horse Pike",
    "sg:city":"Pleasantville",
    "sg:classifiers":[
        {
            "category":"Restaurant",
            "type":"Food & Drink"
        }
    ],
    "sg:phone":"+1 609 646 0637",
    "sg:postcode":"08232",
    "sg:province":"NJ",
    "sg:tags":[
        "drinking",
        "eating"
    ],
    "wof:name":"Essl's Dugout",
    "wof:placetype":"venue"
},
  "geometry": {"coordinates":[-74.517617,39.387574],"type":"Point"}
}