{
  "type": "Feature",
  "properties": {
    "iso:country":"US",
    "sg:address":"291 US Hwy 22",
    "sg:city":"Lebanon",
    "sg:classifiers":[
        {
            "category":"Shopping",
            "type":"Retail Goods"
        }
    ],
    "sg:phone":"+1 908 823 3388",
    "sg:postcode":"08833",
    "sg:province":"NJ",
    "sg:tags":[
        "cosmetic",
        "perfume"
    ],
    "wof:name":"Infa Us",
    "wof:placetype":"venue"
},
  "geometry": {"coordinates":[-74.79060200000001,40.637163],"type":"Point"}
}