{
  "type": "Feature",
  "properties": {
    "addr:full":"8 Camelia Ct Lawrenceville NJ 08648",
    "addr:housenumber":"8",
    "addr:postcode":"08648",
    "addr:street":"Camelia Ct",
    "iso:country":"US",
    "sg:address":"8 Camelia Ct",
    "sg:city":"Lawrenceville",
    "sg:classifiers":[
        {
            "category":"Personal",
            "type":"Services"
        },
        {
            "category":"Recreation",
            "type":"Entertainment"
        }
    ],
    "sg:phone":"+1 609 771 9191",
    "sg:postcode":"08648",
    "sg:province":"NJ",
    "sg:tags":[
        "program",
        "physical",
        "exercise",
        "fitness"
    ],
    "wof:name":"Fitness Plus Personal Training",
    "wof:placetype":"venue"
},
  "geometry": {"coordinates":[-74.71368,40.274556],"type":"Point"}
}