{
  "type": "Feature",
  "properties": {
    "addr:full":"1601 Sherman Ave Pennsauken NJ 08110",
    "addr:housenumber":"1601",
    "addr:postcode":"08110",
    "addr:street":"Sherman Ave",
    "iso:country":"US",
    "sg:address":"1601 Sherman Ave",
    "sg:city":"Pennsauken",
    "sg:classifiers":[
        {
            "category":"Wholesale",
            "subcategory":"Durable Goods & Equipment",
            "type":"Manufacturing & Wholesale Goods"
        }
    ],
    "sg:phone":"+1 856 661 1428",
    "sg:postcode":"08110",
    "sg:province":"NJ",
    "sg:tags":[
        "representative",
        "manufacturer"
    ],
    "sg:website":"www.datacenterdepot.com",
    "wof:name":"Gaw Assoc",
    "wof:placetype":"venue"
},
  "geometry": {"coordinates":[-75.05145,39.968665],"type":"Point"}
}