{
  "type": "Feature",
  "properties": {
    "iso:country":"US",
    "sg:address":"9 Drake Way",
    "sg:city":"Toms River",
    "sg:classifiers":[
        {
            "category":"Building & Trades",
            "subcategory":"Electrical",
            "type":"Services"
        }
    ],
    "sg:phone":"+1 732 279 1055",
    "sg:postcode":"08753",
    "sg:province":"NJ",
    "sg:tags":[
        "electrical",
        "contractor"
    ],
    "wof:name":"Turn On Electric",
    "wof:placetype":"venue"
},
  "geometry": {"coordinates":[-74.116985,40.010924],"type":"Point"}
}