{
  "type": "Feature",
  "properties": {
    "addr:full":"116 Weldon Way Pennington NJ 08534",
    "addr:housenumber":"116",
    "addr:postcode":"08534",
    "addr:street":"Weldon Way",
    "iso:country":"US",
    "sg:address":"116 Weldon Way",
    "sg:city":"Pennington",
    "sg:classifiers":[
        {
            "category":"Professional",
            "subcategory":"Advertising",
            "type":"Services"
        }
    ],
    "sg:phone":"+1 609 333 1400",
    "sg:postcode":"08534",
    "sg:province":"NJ",
    "sg:tags":[
        "agency"
    ],
    "sg:website":"www.hispanicamerica.com",
    "wof:name":"Hispanic America",
    "wof:placetype":"venue"
},
  "geometry": {"coordinates":[-74.755055,40.363197],"type":"Point"}
}