{
  "type": "Feature",
  "properties": {
    "addr:full":"95 Fostertown Rd Lumberton NJ 08048",
    "addr:housenumber":"95",
    "addr:postcode":"08048",
    "addr:street":"Fostertown Rd",
    "iso:country":"US",
    "sg:address":"95 Fostertown Rd",
    "sg:city":"Lumberton",
    "sg:classifiers":[
        {
            "category":"Wholesale",
            "subcategory":"Painting Supplies",
            "type":"Manufacturing & Wholesale Goods"
        },
        {
            "category":"Arts & Performance",
            "subcategory":"Arts Center",
            "type":"Entertainment"
        },
        {
            "category":"Building & Trades",
            "subcategory":"Construction",
            "type":"Services"
        }
    ],
    "sg:phone":"+1 609 267 4355",
    "sg:postcode":"08048",
    "sg:province":"NJ",
    "sg:tags":[
        "industrial",
        "wall",
        "coating",
        "hand",
        "contractors-commercial",
        "decorating",
        "contractor"
    ],
    "wof:name":"Nemeth's Painting Contractors",
    "wof:placetype":"venue"
},
  "geometry": {"coordinates":[-74.811943,39.939098],"type":"Point"}
}