{
  "type": "Feature",
  "properties": {
    "addr:full":"185 Green St Woodbridge NJ 07095",
    "addr:housenumber":"185",
    "addr:postcode":"07095",
    "addr:street":"Green St",
    "iso:country":"US",
    "sg:address":"185 Green St",
    "sg:city":"Woodbridge",
    "sg:classifiers":[
        {
            "category":"Banks & Credit Unions",
            "subcategory":"Bank",
            "type":"Services"
        }
    ],
    "sg:phone":"+1   ",
    "sg:postcode":"07095",
    "sg:province":"NJ",
    "sg:tags":[
        "federal",
        "savings",
        "institution"
    ],
    "wof:name":"L N SOS",
    "wof:placetype":"venue"
},
  "geometry": {"coordinates":[-74.285809,40.557146],"type":"Point"}
}