{
  "type": "Feature",
  "properties": {
    "addr:full":"215 Amboy Ave Metuchen NJ 08840",
    "addr:housenumber":"215",
    "addr:postcode":"08840",
    "addr:street":"Amboy Ave",
    "iso:country":"US",
    "sg:address":"215 Amboy Ave",
    "sg:city":"Metuchen",
    "sg:classifiers":[
        {
            "category":"Health Services",
            "subcategory":"Doctor",
            "type":"Services"
        }
    ],
    "sg:phone":"+1   ",
    "sg:postcode":"08840",
    "sg:province":"NJ",
    "sg:tags":[
        "medical"
    ],
    "wof:name":"Victor Tuma MD",
    "wof:placetype":"venue"
},
  "geometry": {"coordinates":[-74.358276,40.537536],"type":"Point"}
}