{
  "type": "Feature",
  "properties": {
    "addr:full":"379 Windsor Cmns East Windsor NJ 08512",
    "addr:housenumber":"379",
    "addr:postcode":"08512",
    "addr:street":"Windsor Cmns East",
    "iso:country":"US",
    "sg:address":"379 Windsor Cmns",
    "sg:city":"East Windsor",
    "sg:classifiers":[
        {
            "category":"Insurance",
            "subcategory":"Insurance Agent",
            "type":"Services"
        }
    ],
    "sg:phone":"+1 609 448 6700",
    "sg:postcode":"08512",
    "sg:province":"NJ",
    "wof:name":"State Farm Insurance",
    "wof:placetype":"venue"
},
  "geometry": {"coordinates":[-74.54705300000001,40.286628],"type":"Point"}
}