{
  "type": "Feature",
  "properties": {
    "addr:full":"4 Indian Trl Rd Randolph NJ 07869",
    "addr:housenumber":"4",
    "addr:postcode":"07869",
    "addr:street":"Indian Trl Rd",
    "iso:country":"US",
    "sg:address":"4 Indian Trl Rd",
    "sg:city":"Randolph",
    "sg:classifiers":[
        {
            "category":"Professional",
            "subcategory":"Management & Consulting",
            "type":"Services"
        }
    ],
    "sg:phone":"+1   ",
    "sg:postcode":"07869",
    "sg:province":"NJ",
    "sg:tags":[
        "business"
    ],
    "wof:name":"Cypress Consulting Corporation",
    "wof:placetype":"venue"
},
  "geometry": {"coordinates":[-74.544943,40.84421],"type":"Point"}
}