{
  "type": "Feature",
  "properties": {
    "iso:country":"US",
    "sg:address":"916 17th St",
    "sg:city":"Union City",
    "sg:classifiers":[
        {
            "category":"Professional",
            "type":"Services"
        }
    ],
    "sg:phone":"+1   ",
    "sg:postcode":"07087",
    "sg:province":"NJ",
    "wof:name":"Independent Assemblies of",
    "wof:placetype":"venue"
},
  "geometry": {"coordinates":[-74.04211599999999,40.765634],"type":"Point"}
}