{
  "type": "Feature",
  "properties": {
    "addr:full":"96 Merritt Dr Oradell NJ 07649",
    "addr:housenumber":"96",
    "addr:postcode":"07649",
    "addr:street":"Merritt Dr",
    "iso:country":"US",
    "sg:address":"96 Merritt Dr",
    "sg:city":"Oradell",
    "sg:classifiers":[
        {
            "category":"Health Services",
            "subcategory":"Doctor",
            "type":"Services"
        }
    ],
    "sg:phone":"+1 201 384 5250",
    "sg:postcode":"07649",
    "sg:province":"NJ",
    "sg:tags":[
        "physician",
        "surgeon"
    ],
    "wof:name":"M R Mateyka MD",
    "wof:placetype":"venue"
},
  "geometry": {"coordinates":[-74.00929600000001,40.952489],"type":"Point"}
}