{
  "type": "Feature",
  "properties": {
    "addr:full":"1197 Lincoln Sq Long Branch NJ 07740",
    "addr:housenumber":"1197",
    "addr:postcode":"07740",
    "addr:street":"Lincoln Sq",
    "iso:country":"US",
    "sg:address":"1197 Lincoln Sq",
    "sg:city":"Long Branch",
    "sg:classifiers":[
        {
            "category":"Shopping",
            "subcategory":"Optical Goods",
            "type":"Retail Goods"
        }
    ],
    "sg:phone":"+1 732 728 0405",
    "sg:postcode":"07740",
    "sg:province":"NJ",
    "wof:name":"Bright Eyes",
    "wof:placetype":"venue"
},
  "geometry": {"coordinates":[-73.99534300000001,40.268036],"type":"Point"}
}