{
  "type": "Feature",
  "properties": {
    "addr:full":"203 Peterson St Millville NJ 08332",
    "addr:housenumber":"203",
    "addr:postcode":"08332",
    "addr:street":"Peterson St",
    "iso:country":"US",
    "sg:address":"203 Peterson St",
    "sg:city":"Millville",
    "sg:classifiers":[
        {
            "category":"Manufacturing",
            "subcategory":"Tools & Machinery",
            "type":"Manufacturing & Wholesale Goods"
        }
    ],
    "sg:phone":"+1 856 825 3300",
    "sg:postcode":"08332",
    "sg:province":"NJ",
    "sg:tags":[
        "machine",
        "shop"
    ],
    "sg:website":"www.generalpolygon.com",
    "wof:name":"General Polygon Systems Inc",
    "wof:placetype":"venue"
},
  "geometry": {"coordinates":[-75.070863,39.373438],"type":"Point"}
}