{
  "type": "Feature",
  "properties": {
    "addr:full":"1303 Beaver Dam Rd Pt Pleasant Bch NJ 08742",
    "addr:housenumber":"1303",
    "addr:postcode":"08742",
    "addr:street":"Beaver Dam Rd Pt",
    "iso:country":"US",
    "sg:address":"1303 Beaver Dam Rd",
    "sg:city":"Pt Pleasant Bch",
    "sg:classifiers":[
        {
            "category":"Shopping",
            "subcategory":"Bicycles & Sporting Goods",
            "type":"Retail Goods"
        }
    ],
    "sg:phone":"+1 732 899 1050",
    "sg:postcode":"08742",
    "sg:province":"NJ",
    "wof:name":"1 Stop Sporting Goods",
    "wof:placetype":"venue"
},
  "geometry": {"coordinates":[-74.07233100000001,40.071842],"type":"Point"}
}