{
  "type": "Feature",
  "properties": {
    "addr:full":"101 Red Lion Rd Vincentown NJ 08088",
    "addr:housenumber":"101",
    "addr:postcode":"08088",
    "addr:street":"Red Lion Rd",
    "iso:country":"US",
    "sg:address":"101 Red Lion Rd",
    "sg:city":"Vincentown",
    "sg:classifiers":[
        {
            "category":"Restaurant",
            "type":"Food & Drink"
        }
    ],
    "sg:phone":"+1   ",
    "sg:postcode":"08088",
    "sg:province":"NJ",
    "sg:tags":[
        "drinking",
        "eating"
    ],
    "wof:name":"Hilton",
    "wof:placetype":"venue"
},
  "geometry": {"coordinates":[-74.74486400000001,39.889714],"type":"Point"}
}