{
  "type": "Feature",
  "properties": {
    "iso:country":"US",
    "sg:address":"1653 White Oak Rd",
    "sg:city":"Williamstown",
    "sg:classifiers":[
        {
            "category":"Insurance",
            "subcategory":"Insurance Agent",
            "type":"Services"
        }
    ],
    "sg:phone":"+1 856 728 2212",
    "sg:postcode":"08094",
    "sg:province":"NJ",
    "wof:name":"Herron Insurance",
    "wof:placetype":"venue"
},
  "geometry": {"coordinates":[-74.976444,39.664584],"type":"Point"}
}