{
  "type": "Feature",
  "properties": {
    "addr:full":"33 N 3rd St Camden NJ 08102",
    "addr:housenumber":"33",
    "addr:postcode":"08102",
    "addr:street":"N 3Rd St",
    "iso:country":"US",
    "sg:address":"33 N 3rd St",
    "sg:city":"Camden",
    "sg:classifiers":[
        {
            "category":"Building & Trades",
            "subcategory":"Locksmith",
            "type":"Services"
        }
    ],
    "sg:phone":"+1 856 479 9424",
    "sg:postcode":"08102",
    "sg:province":"NJ",
    "sg:tags":[
        "key"
    ],
    "wof:name":"AAA Locksmith",
    "wof:placetype":"venue"
},
  "geometry": {"coordinates":[-75.124336,39.944927],"type":"Point"}
}