{
  "type": "Feature",
  "properties": {
    "addr:full":"46 State Rte 36 Keyport NJ 07735",
    "addr:housenumber":"46",
    "addr:postcode":"07735",
    "addr:street":"State Rte 36",
    "iso:country":"US",
    "sg:address":"46 State Rte 36",
    "sg:city":"Keyport",
    "sg:classifiers":[
        {
            "category":"Building & Trades",
            "subcategory":"Construction",
            "type":"Services"
        }
    ],
    "sg:phone":"+1 732 888 9336",
    "sg:postcode":"07735",
    "sg:province":"NJ",
    "sg:tags":[
        "marine",
        "contractor"
    ],
    "wof:name":"Phoenix Marine Company Inc",
    "wof:placetype":"venue"
},
  "geometry": {"coordinates":[-74.192713,40.428115],"type":"Point"}
}