{
  "type": "Feature",
  "properties": {
    "addr:full":"576 N Main St Hightstown NJ 08520",
    "addr:housenumber":"576",
    "addr:postcode":"08520",
    "addr:street":"N Main St",
    "iso:country":"US",
    "sg:address":"576 N Main St",
    "sg:city":"Hightstown",
    "sg:classifiers":[
        {
            "category":"Health Services",
            "subcategory":"Health Practitioner",
            "type":"Services"
        }
    ],
    "sg:phone":"+1 609 448 0528",
    "sg:postcode":"08520",
    "sg:province":"NJ",
    "sg:tags":[
        "nurse",
        "registry"
    ],
    "wof:name":"Hightstown Sunlawn Nursing Hm",
    "wof:placetype":"venue"
},
  "geometry": {"coordinates":[-74.520825,40.276544],"type":"Point"}
}