{
  "type": "Feature",
  "properties": {
    "addr:full":"112 Elizabeth Ave Westfield NJ 07090",
    "addr:housenumber":"112",
    "addr:postcode":"07090",
    "addr:street":"Elizabeth Ave",
    "iso:country":"US",
    "sg:address":"112 Elizabeth Ave",
    "sg:city":"Westfield",
    "sg:classifiers":[
        {
            "category":"Retail",
            "subcategory":"Repair Shop",
            "type":"Services"
        }
    ],
    "sg:phone":"+1   ",
    "sg:postcode":"07090",
    "sg:province":"NJ",
    "wof:name":"Bila Inc Ta Metro TV Tim",
    "wof:placetype":"venue"
},
  "geometry": {"coordinates":[-74.33303100000001,40.645336],"type":"Point"}
}