{
  "type": "Feature",
  "properties": {
    "iso:country":"US",
    "sg:address":"665 N Broad St",
    "sg:city":"Woodbury",
    "sg:classifiers":[
        {
            "category":"Real Estate",
            "subcategory":"Real Estate Agent",
            "type":"Services"
        }
    ],
    "sg:phone":"+1 856 845 7188",
    "sg:postcode":"08096",
    "sg:province":"NJ",
    "sg:tags":[
        "management"
    ],
    "wof:name":"Crestwood Management Svc",
    "wof:placetype":"venue"
},
  "geometry": {"coordinates":[-75.147279,39.845509],"type":"Point"}
}