{
  "type": "Feature",
  "properties": {
    "addr:full":"277 Eisenhower Pkwy Livingston NJ 07039",
    "addr:housenumber":"277",
    "addr:postcode":"07039",
    "addr:street":"Eisenhower Pkwy",
    "iso:country":"US",
    "sg:address":"277 Eisenhower Pkwy",
    "sg:city":"Livingston",
    "sg:classifiers":[
        {
            "category":"Shopping",
            "subcategory":"Beauty & Cosmetics",
            "type":"Retail Goods"
        }
    ],
    "sg:phone":"+1   ",
    "sg:postcode":"07039",
    "sg:province":"NJ",
    "sg:tags":[
        "merchandise"
    ],
    "wof:name":"Shiseido Cosmetics",
    "wof:placetype":"venue"
},
  "geometry": {"coordinates":[-74.341641,40.796396],"type":"Point"}
}