{
  "type": "Feature",
  "properties": {
    "iso:country":"US",
    "sg:address":"417 E 19th Ave",
    "sg:city":"Wildwood",
    "sg:classifiers":[
        {
            "category":"Travel",
            "subcategory":"Hotels & Motels",
            "type":"Entertainment"
        }
    ],
    "sg:phone":"+1   ",
    "sg:postcode":"08260",
    "sg:province":"NJ",
    "sg:tags":[
        "resort"
    ],
    "sg:website":"www.malikai.com",
    "wof:name":"Mali Kai Condominiums",
    "wof:placetype":"venue"
},
  "geometry": {"coordinates":[-74.79953500000001,38.993824],"type":"Point"}
}