{
  "type": "Feature",
  "properties": {
    "iso:country":"US",
    "sg:address":"355 Valley Rd",
    "sg:city":"Gillette",
    "sg:classifiers":[
        {
            "category":"Professional",
            "subcategory":"Detective & Security Services",
            "type":"Services"
        }
    ],
    "sg:phone":"+1 908 604 8817",
    "sg:postcode":"07933",
    "sg:province":"NJ",
    "sg:tags":[
        "car"
    ],
    "wof:name":"Thomas J Crann Inc",
    "wof:placetype":"venue"
},
  "geometry": {"coordinates":[-74.455091,40.678477],"type":"Point"}
}