{
  "type": "Feature",
  "properties": {
    "addr:full":"10 Dakota Trl Browns Mills NJ 08015",
    "addr:housenumber":"10",
    "addr:postcode":"08015",
    "addr:street":"Dakota Trl",
    "iso:country":"US",
    "sg:address":"10 Dakota Trl",
    "sg:city":"Browns Mills",
    "sg:classifiers":[
        {
            "category":"Wholesale",
            "subcategory":"Vending Machines",
            "type":"Manufacturing & Wholesale Goods"
        }
    ],
    "sg:phone":"+1   ",
    "sg:postcode":"08015",
    "sg:province":"NJ",
    "sg:tags":[
        "operator"
    ],
    "wof:name":"Dintinger Vending",
    "wof:placetype":"venue"
},
  "geometry": {"coordinates":[-74.574271,39.90645],"type":"Point"}
}