{
  "type": "Feature",
  "properties": {
    "iso:country":"US",
    "sg:address":"163 Shaw Ave",
    "sg:city":"Irvington",
    "sg:classifiers":[
        {
            "category":"Professional",
            "subcategory":"Management & Consulting",
            "type":"Services"
        }
    ],
    "sg:phone":"+1 973 923 8200",
    "sg:postcode":"07111",
    "sg:province":"NJ",
    "sg:tags":[
        "marketing",
        "program"
    ],
    "wof:name":"Donner Medical Marketing Inc",
    "wof:placetype":"venue"
},
  "geometry": {"coordinates":[-74.22327,40.716875],"type":"Point"}
}