{
  "type": "Feature",
  "properties": {
    "iso:country":"US",
    "sg:address":"151 S Broadway St",
    "sg:city":"South Amboy",
    "sg:classifiers":[
        {
            "category":"Cinema",
            "subcategory":"Movie Rental",
            "type":"Entertainment"
        }
    ],
    "sg:phone":"+1   ",
    "sg:postcode":"08879",
    "sg:province":"NJ",
    "sg:tags":[
        "video",
        "tape"
    ],
    "wof:name":"Polski Club Video",
    "wof:placetype":"venue"
},
  "geometry": {"coordinates":[-74.27863000000001,40.481686],"type":"Point"}
}