{
  "type": "Feature",
  "properties": {
    "addr:full":"9 N Georgia Ave Atlantic City NJ 08401",
    "addr:housenumber":"9",
    "addr:postcode":"08401",
    "addr:street":"N Georgia Ave",
    "iso:country":"US",
    "sg:address":"9 N Georgia Ave",
    "sg:city":"Atlantic City",
    "sg:classifiers":[
        {
            "category":"Social Services",
            "type":"Services"
        }
    ],
    "sg:phone":"+1 609 345 3448",
    "sg:postcode":"08401",
    "sg:province":"NJ",
    "wof:name":"Catholic Charities",
    "wof:placetype":"venue"
},
  "geometry": {"coordinates":[-74.441074,39.357762],"type":"Point"}
}