{
  "type": "Feature",
  "properties": {
    "iso:country":"US",
    "sg:address":"2900 Mount Ephraim Ave",
    "sg:city":"Camden",
    "sg:classifiers":[
        {
            "category":"Restaurant",
            "type":"Food & Drink"
        }
    ],
    "sg:phone":"+1 856 858 9828",
    "sg:postcode":"08104",
    "sg:province":"NJ",
    "sg:tags":[
        "eating"
    ],
    "wof:name":"China Wonder",
    "wof:placetype":"venue"
},
  "geometry": {"coordinates":[-75.097154,39.907503],"type":"Point"}
}