{
  "type": "Feature",
  "properties": {
    "iso:country":"US",
    "sg:address":"535 Broad Ave",
    "sg:city":"Palisades Park",
    "sg:classifiers":[
        {
            "category":"Health Services",
            "subcategory":"Dentist",
            "type":"Services"
        }
    ],
    "sg:phone":"+1 201 592 0111",
    "sg:postcode":"07650",
    "sg:province":"NJ",
    "wof:name":"Chang Keith DDS",
    "wof:placetype":"venue"
},
  "geometry": {"coordinates":[-73.99435200000001,40.853065],"type":"Point"}
}