{
  "type": "Feature",
  "properties": {
    "iso:country":"US",
    "sg:address":"17 Peggys Ln",
    "sg:city":"Southampton",
    "sg:classifiers":[
        {
            "category":"Building & Trades",
            "subcategory":"Construction",
            "type":"Services"
        }
    ],
    "sg:phone":"+1 609 859 3479",
    "sg:postcode":"08088",
    "sg:province":"NJ",
    "sg:tags":[
        "dry wall",
        "contractor"
    ],
    "wof:name":"Journeigan's Dry Wall",
    "wof:placetype":"venue"
},
  "geometry": {"coordinates":[-74.65206999999999,39.876394],"type":"Point"}
}