{
  "type": "Feature",
  "properties": {
    "addr:full":"1253 Springfield Ave New Providence NJ 07974",
    "addr:housenumber":"1253",
    "addr:postcode":"07974",
    "addr:street":"Springfield Ave",
    "iso:country":"US",
    "sg:address":"1253 Springfield Ave",
    "sg:city":"New Providence",
    "sg:classifiers":[
        {
            "category":"Building & Trades",
            "subcategory":"Electrical",
            "type":"Services"
        }
    ],
    "sg:phone":"+1 908 464 8980",
    "sg:postcode":"07974",
    "sg:province":"NJ",
    "sg:tags":[
        "electrical",
        "contractor"
    ],
    "wof:name":"Kreder Electric",
    "wof:placetype":"venue"
},
  "geometry": {"coordinates":[-74.40610100000001,40.706225],"type":"Point"}
}