{
  "type": "Feature",
  "properties": {
    "addr:full":"490 Riverview Dr Totowa NJ 07512",
    "addr:housenumber":"490",
    "addr:postcode":"07512",
    "addr:street":"Riverview Dr",
    "iso:country":"US",
    "sg:address":"490 Riverview Dr",
    "sg:city":"Totowa",
    "sg:classifiers":[
        {
            "category":"Building & Trades",
            "subcategory":"Construction",
            "type":"Services"
        }
    ],
    "sg:phone":"+1 973 812 1119",
    "sg:postcode":"07512",
    "sg:province":"NJ",
    "sg:tags":[
        "contractor"
    ],
    "wof:name":"Totowa Awning Glass Products",
    "wof:placetype":"venue"
},
  "geometry": {"coordinates":[-74.219741,40.891812],"type":"Point"}
}