{
  "type": "Feature",
  "properties": {
    "iso:country":"US",
    "sg:address":"37 James St",
    "sg:city":"Newark",
    "sg:classifiers":[
        {
            "category":"Building & Trades",
            "subcategory":"Locksmith",
            "type":"Services"
        }
    ],
    "sg:phone":"+1 973 854 5202",
    "sg:postcode":"07102",
    "sg:province":"NJ",
    "sg:tags":[
        "key"
    ],
    "wof:name":"0 0 24 Hour 7 Day A Emergency Locksmith",
    "wof:placetype":"venue"
},
  "geometry": {"coordinates":[-74.172236,40.744419],"type":"Point"}
}