{
  "type": "Feature",
  "properties": {
    "iso:country":"US",
    "sg:address":"546 E 24th St",
    "sg:city":"Paterson",
    "sg:classifiers":[
        {
            "category":"Travel",
            "subcategory":"Travel Agent",
            "type":"Entertainment"
        }
    ],
    "sg:phone":"+1 973 742 4353",
    "sg:postcode":"07514",
    "sg:province":"NJ",
    "sg:tags":[
        "agency"
    ],
    "wof:name":"Unlimited Escapes",
    "wof:placetype":"venue"
},
  "geometry": {"coordinates":[-74.150052,40.920528],"type":"Point"}
}