{
  "type": "Feature",
  "properties": {
    "addr:full":"48 Parkway Dr Clark NJ 07066",
    "addr:housenumber":"48",
    "addr:postcode":"07066",
    "addr:street":"Parkway Dr",
    "iso:country":"US",
    "sg:address":"48 Parkway Dr",
    "sg:city":"Clark",
    "sg:classifiers":[
        {
            "category":"Organizations",
            "subcategory":"Community Association",
            "type":"Services"
        }
    ],
    "sg:phone":"+1 732 574 0003",
    "sg:postcode":"07066",
    "sg:province":"NJ",
    "wof:name":"Kiwanis Club Clark New Jersey",
    "wof:placetype":"venue"
},
  "geometry": {"coordinates":[-74.28663899999999,40.630296],"type":"Point"}
}