{
  "type": "Feature",
  "properties": {
    "addr:full":"2100 Marlton Pike E Cherry Hill NJ 08003",
    "addr:housenumber":"2100",
    "addr:postcode":"08003",
    "addr:street":"Marlton Pike E",
    "iso:country":"US",
    "sg:address":"2100 Marlton Pike E",
    "sg:city":"Cherry Hill",
    "sg:classifiers":[
        {
            "category":"Retail",
            "subcategory":"Auto Repair",
            "type":"Services"
        }
    ],
    "sg:phone":"+1 856 424 5591",
    "sg:postcode":"08003",
    "sg:province":"NJ",
    "sg:tags":[
        "automobile",
        "lubrication"
    ],
    "wof:name":"Jiffy Lube",
    "wof:placetype":"venue"
},
  "geometry": {"coordinates":[-74.950639,39.897226],"type":"Point"}
}