{
  "type": "Feature",
  "properties": {
    "addr:full":"36 Newark Ave Ste 212 Belleville NJ 07109",
    "addr:housenumber":"36",
    "addr:postcode":"07109",
    "addr:street":"Newark Ave Ste 212",
    "iso:country":"US",
    "sg:address":"36 Newark Ave Ste 212",
    "sg:city":"Belleville",
    "sg:classifiers":[
        {
            "category":"Health Services",
            "subcategory":"Optometrist",
            "type":"Services"
        }
    ],
    "sg:phone":"+1 973 751 8808",
    "sg:postcode":"07109",
    "sg:province":"NJ",
    "sg:tags":[
        "ophthalmologist"
    ],
    "wof:name":"Cangemi Francis E MD",
    "wof:placetype":"venue"
},
  "geometry": {"coordinates":[-74.177803,40.784],"type":"Point"}
}