{
  "type": "Feature",
  "properties": {
    "addr:full":"1636 Reed Rd Pennington NJ 08534",
    "addr:housenumber":"1636",
    "addr:postcode":"08534",
    "addr:street":"Reed Rd",
    "iso:country":"US",
    "sg:address":"1636 Reed Rd",
    "sg:city":"Pennington",
    "sg:classifiers":[
        {
            "category":"Sports & Exercise",
            "subcategory":"Race Track",
            "type":"Entertainment"
        }
    ],
    "sg:phone":"+1 609 737 8203",
    "sg:postcode":"08534",
    "sg:province":"NJ",
    "sg:tags":[
        "operation",
        "racing",
        "or"
    ],
    "wof:name":"Autosport Specialists",
    "wof:placetype":"venue"
},
  "geometry": {"coordinates":[-74.79520100000001,40.306187],"type":"Point"}
}