{
  "type": "Feature",
  "properties": {
    "iso:country":"US",
    "sg:address":"22 Arlington Ave",
    "sg:city":"Mt Arlington",
    "sg:classifiers":[
        {
            "category":"Real Estate",
            "subcategory":"Architect",
            "type":"Services"
        }
    ],
    "sg:phone":"+1 973 770 6800",
    "sg:postcode":"07856",
    "sg:province":"NJ",
    "wof:name":"Joseph Marra Architects",
    "wof:placetype":"venue"
},
  "geometry": {"coordinates":[-74.633402,40.930619],"type":"Point"}
}