{
  "type": "Feature",
  "properties": {
    "addr:full":"5908 Long Beach Blvd Beach Haven NJ 08008",
    "addr:housenumber":"5908",
    "addr:postcode":"08008",
    "addr:street":"Long Beach Blvd",
    "iso:country":"US",
    "sg:address":"5908 Long Beach Blvd",
    "sg:city":"Beach Haven",
    "sg:classifiers":[
        {
            "category":"Building & Trades",
            "subcategory":"Construction",
            "type":"Services"
        }
    ],
    "sg:phone":"+1 609 494 0298",
    "sg:postcode":"08008",
    "sg:province":"NJ",
    "sg:tags":[
        "home",
        "improvement"
    ],
    "wof:name":"Fine Line Home Improvements",
    "wof:placetype":"venue"
},
  "geometry": {"coordinates":[-74.196635,39.622134],"type":"Point"}
}