{
  "type": "Feature",
  "properties": {
    "iso:country":"US",
    "sg:address":"7 Boswell Ct",
    "sg:city":"Medford",
    "sg:classifiers":[
        {
            "category":"Personal",
            "type":"Services"
        }
    ],
    "sg:phone":"+1 609 714 0254",
    "sg:postcode":"08055",
    "sg:province":"NJ",
    "sg:tags":[
        "image",
        "consultants-personal"
    ],
    "wof:name":"Quillrose Calligraphy",
    "wof:placetype":"venue"
},
  "geometry": {"coordinates":[-74.80440299999999,39.909722],"type":"Point"}
}