{
  "type": "Feature",
  "properties": {
    "addr:full":"614 Hampton Rd Cherry Hill NJ 08002",
    "addr:housenumber":"614",
    "addr:postcode":"08002",
    "addr:street":"Hampton Rd",
    "iso:country":"US",
    "sg:address":"614 Hampton Rd",
    "sg:city":"Cherry Hill",
    "sg:classifiers":[
        {
            "category":"Freight",
            "type":"Transportation"
        }
    ],
    "sg:phone":"+1 856 662 7565",
    "sg:postcode":"08002",
    "sg:province":"NJ",
    "sg:tags":[
        "warehouse"
    ],
    "sg:website":"www.pssdist.com",
    "wof:name":"PSS Transportation",
    "wof:placetype":"venue"
},
  "geometry": {"coordinates":[-75.050027,39.938625],"type":"Point"}
}