{
  "type": "Feature",
  "properties": {
    "iso:country":"US",
    "sg:address":"784 US Highway 46",
    "sg:city":"Parsippany",
    "sg:classifiers":[
        {
            "category":"Shopping",
            "subcategory":"Clothing, Apparel, & Fashions",
            "type":"Retail Goods"
        }
    ],
    "sg:phone":"+1 973 334 4101",
    "sg:postcode":"07054",
    "sg:province":"NJ",
    "sg:tags":[
        "accessory",
        "clothing",
        "women's"
    ],
    "wof:name":"Fashion Bug Plus",
    "wof:placetype":"venue"
},
  "geometry": {"coordinates":[-74.378799,40.862598],"type":"Point"}
}