{
  "type": "Feature",
  "properties": {
    "iso:country":"US",
    "sg:address":"4300 Haddonfield Rd",
    "sg:city":"Merchantville",
    "sg:classifiers":[
        {
            "category":"Real Estate",
            "subcategory":"Real Estate Agent",
            "type":"Services"
        },
        {
            "category":"Real Estate",
            "subcategory":"Real Estate Operator",
            "type":"Services"
        }
    ],
    "sg:phone":"+1 856 662 1176",
    "sg:postcode":"08109",
    "sg:province":"NJ",
    "sg:tags":[
        "building",
        "management",
        "commercial",
        "complex",
        "manager",
        "apartment"
    ],
    "wof:name":"Allstate Management Corp",
    "wof:placetype":"venue"
},
  "geometry": {"coordinates":[-75.026527,39.954516],"type":"Point"}
}