{
  "type": "Feature",
  "properties": {
    "iso:country":"US",
    "sg:address":"9 Cameron Rd",
    "sg:city":"Saddle River",
    "sg:classifiers":[
        {
            "category":"Social Services",
            "type":"Services"
        }
    ],
    "sg:phone":"+1 201 934 9087",
    "sg:postcode":"07458",
    "sg:province":"NJ",
    "sg:tags":[
        "health"
    ],
    "wof:name":"Frieda Birnbaum Dr",
    "wof:placetype":"venue"
},
  "geometry": {"coordinates":[-74.117768,41.025307],"type":"Point"}
}