{
  "type": "Feature",
  "properties": {
    "addr:full":"155 Harwich St Browns Mills NJ 08015",
    "addr:housenumber":"155",
    "addr:postcode":"08015",
    "addr:street":"Harwich St",
    "iso:country":"US",
    "sg:address":"155 Harwich St",
    "sg:city":"Browns Mills",
    "sg:phone":"+1 609 893 8981",
    "sg:postcode":"08015",
    "sg:province":"NJ",
    "sg:tags":[
        "product",
        "petroleum"
    ],
    "wof:name":"Amsoil Synthetic Lubricants",
    "wof:placetype":"venue"
},
  "geometry": {"coordinates":[-74.575456,39.980146],"type":"Point"}
}