{
  "type": "Feature",
  "properties": {
    "iso:country":"US",
    "sg:address":"3084 State Rte 27",
    "sg:city":"Kendall Park",
    "sg:classifiers":[
        {
            "category":"Health Services",
            "subcategory":"Health Practitioner",
            "type":"Services"
        }
    ],
    "sg:phone":"+1 732 297 0591",
    "sg:postcode":"08824",
    "sg:province":"NJ",
    "wof:name":"Speech Alive",
    "wof:placetype":"venue"
},
  "geometry": {"coordinates":[-74.56196,40.427417],"type":"Point"}
}