{
  "type": "Feature",
  "properties": {
    "iso:country":"US",
    "sg:address":"520 Market St",
    "sg:city":"Camden",
    "sg:classifiers":[
        {
            "category":"Government",
            "subcategory":"Police Station",
            "type":"Public Place"
        }
    ],
    "sg:phone":"+1 856 225 5475",
    "sg:postcode":"08102",
    "sg:province":"NJ",
    "sg:tags":[
        "sheriff"
    ],
    "wof:name":"Camden County Sheriff",
    "wof:placetype":"venue"
},
  "geometry": {"coordinates":[-75.12027,39.945449],"type":"Point"}
}