{
  "type": "Feature",
  "properties": {
    "addr:full":"145 Morris Ave Trenton NJ 08611",
    "addr:housenumber":"145",
    "addr:postcode":"08611",
    "addr:street":"Morris Ave",
    "iso:country":"US",
    "sg:address":"145 Morris Ave",
    "sg:city":"Trenton",
    "sg:classifiers":[
        {
            "category":"Restaurant",
            "type":"Food & Drink"
        }
    ],
    "sg:phone":"+1 609 392 2934",
    "sg:postcode":"08611",
    "sg:province":"NJ",
    "sg:tags":[
        "caterer"
    ],
    "sg:website":"www.baldassari.com",
    "wof:name":"Baldassari Regency-Roebling",
    "wof:placetype":"venue"
},
  "geometry": {"coordinates":[-74.74539,40.209604],"type":"Point"}
}