{
  "type": "Feature",
  "properties": {
    "addr:full":"8 Delsea Dr N Glassboro NJ 08028",
    "addr:housenumber":"8",
    "addr:postcode":"08028",
    "addr:street":"Delsea Dr N",
    "iso:country":"US",
    "sg:address":"8 Delsea Dr N",
    "sg:city":"Glassboro",
    "sg:classifiers":[
        {
            "category":"Autos & Motor Vehicles",
            "subcategory":"Automobile Sales",
            "type":"Retail Goods"
        }
    ],
    "sg:phone":"+1 856 270 6384",
    "sg:postcode":"08028",
    "sg:province":"NJ",
    "sg:tags":[
        "used",
        "car",
        "dealers-used",
        "truck",
        "new",
        "cars-wholesale"
    ],
    "sg:website":"http://national.citysearch.com/profile/external/6789464/glassboro_nj/good_wheels.html?publisher=yellowpages&reference_id=15&placement=ypwebsitemip",
    "wof:name":"Good Wheels",
    "wof:placetype":"venue"
},
  "geometry": {"coordinates":[-75.115925,39.724039],"type":"Point"}
}