{
  "type": "Feature",
  "properties": {
    "iso:country":"US",
    "sg:address":"41 Coolidge Ave",
    "sg:city":"West Caldwell",
    "sg:classifiers":[
        {
            "category":"Social Services",
            "type":"Services"
        }
    ],
    "sg:phone":"+1 973 226 0068",
    "sg:postcode":"07006",
    "sg:province":"NJ",
    "sg:tags":[
        "worker"
    ],
    "wof:name":"Ian Harris",
    "wof:placetype":"venue"
},
  "geometry": {"coordinates":[-74.27150899999999,40.846971],"type":"Point"}
}