{
  "type": "Feature",
  "properties": {
    "iso:country":"US",
    "sg:address":"29 South St",
    "sg:city":"Freehold",
    "sg:classifiers":[
        {
            "category":"Personal",
            "subcategory":"Beauty Salon",
            "type":"Services"
        },
        {
            "category":"Personal",
            "subcategory":"Barber",
            "type":"Services"
        }
    ],
    "sg:phone":"+1 732 431 8404",
    "sg:postcode":"07728",
    "sg:province":"NJ",
    "sg:tags":[
        "shop"
    ],
    "wof:name":"Carroll's Cuts",
    "wof:placetype":"venue"
},
  "geometry": {"coordinates":[-74.273685,40.25812],"type":"Point"}
}