{
  "type": "Feature",
  "properties": {
    "iso:country":"US",
    "sg:address":"1 Gateway Ctr Ste 902",
    "sg:city":"Newark",
    "sg:classifiers":[
        {
            "category":"Professional",
            "type":"Services"
        },
        {
            "category":"Food & Beverages",
            "subcategory":"Meat & Fish",
            "type":"Retail Goods"
        }
    ],
    "sg:phone":"+1 908 232 0402",
    "sg:postcode":"07102",
    "sg:province":"NJ",
    "sg:tags":[
        "shop",
        "caterer"
    ],
    "wof:name":"J & M Market",
    "wof:placetype":"venue"
},
  "geometry": {"coordinates":[-74.169701,40.735298],"type":"Point"}
}