{
  "type": "Feature",
  "properties": {
    "addr:full":"802 Roadstown Rd Bridgeton NJ 08302",
    "addr:housenumber":"802",
    "addr:postcode":"08302",
    "addr:street":"Roadstown Rd",
    "iso:country":"US",
    "sg:address":"802 Roadstown Rd",
    "sg:city":"Bridgeton",
    "sg:phone":"+1 856 455 7043",
    "sg:postcode":"08302",
    "sg:province":"NJ",
    "sg:tags":[
        "farm"
    ],
    "wof:name":"Cherry Lane Farm",
    "wof:placetype":"venue"
},
  "geometry": {"coordinates":[-75.320662,39.442862],"type":"Point"}
}