{
  "type": "Feature",
  "properties": {
    "addr:full":"482 Summit Ave Hackensack NJ 07601",
    "addr:housenumber":"482",
    "addr:postcode":"07601",
    "addr:street":"Summit Ave",
    "iso:country":"US",
    "sg:address":"482 Summit Ave",
    "sg:city":"Hackensack",
    "sg:classifiers":[
        {
            "category":"Professional",
            "subcategory":"Advertising",
            "type":"Services"
        }
    ],
    "sg:phone":"+1   ",
    "sg:postcode":"07601",
    "sg:province":"NJ",
    "sg:tags":[
        "printing",
        "agency"
    ],
    "wof:name":"Peach Arts Inc",
    "wof:placetype":"venue"
},
  "geometry": {"coordinates":[-74.052334,40.899963],"type":"Point"}
}