{
  "type": "Feature",
  "properties": {
    "iso:country":"US",
    "sg:address":"6 Kings Ln",
    "sg:city":"Haddonfield",
    "sg:classifiers":[
        {
            "category":"Wholesale",
            "subcategory":"Plants",
            "type":"Manufacturing & Wholesale Goods"
        }
    ],
    "sg:phone":"+1 856 435 6363",
    "sg:postcode":"08033",
    "sg:province":"NJ",
    "sg:tags":[
        "silk"
    ],
    "wof:name":"Everlasting Of Haddonfield",
    "wof:placetype":"venue"
},
  "geometry": {"coordinates":[-75.027731,39.902295],"type":"Point"}
}