{
  "type": "Feature",
  "properties": {
    "iso:country":"US",
    "sg:address":"371 Massachusetts Ave",
    "sg:city":"Trenton",
    "sg:classifiers":[
        {
            "category":"Taxi",
            "type":"Transportation"
        }
    ],
    "sg:phone":"+1 609 890 4632",
    "sg:postcode":"08629",
    "sg:province":"NJ",
    "sg:tags":[
        "taxicab"
    ],
    "wof:name":"Vital Cab Inc",
    "wof:placetype":"venue"
},
  "geometry": {"coordinates":[-74.731155,40.22509],"type":"Point"}
}