{
  "type": "Feature",
  "properties": {
    "addr:full":"754 Dixie Ln Plainfield NJ 07062",
    "addr:housenumber":"754",
    "addr:postcode":"07062",
    "addr:street":"Dixie Ln",
    "iso:country":"US",
    "sg:address":"754 Dixie Ln",
    "sg:city":"Plainfield",
    "sg:classifiers":[
        {
            "category":"Professional",
            "subcategory":"Art Services",
            "type":"Services"
        }
    ],
    "sg:phone":"+1   ",
    "sg:postcode":"07062",
    "sg:province":"NJ",
    "sg:tags":[
        "commercial",
        "design"
    ],
    "wof:name":"First Looks",
    "wof:placetype":"venue"
},
  "geometry": {"coordinates":[-74.39778699999999,40.623275],"type":"Point"}
}