{
  "type": "Feature",
  "properties": {
    "iso:country":"US",
    "sg:address":"382 East Ave",
    "sg:city":"Perth Amboy",
    "sg:classifiers":[
        {
            "category":"Organizations",
            "subcategory":"Religious Organization",
            "type":"Services"
        }
    ],
    "sg:phone":"+1 732 324 0056",
    "sg:postcode":"08861",
    "sg:province":"NJ",
    "wof:name":"New Beginnings Deliverance",
    "wof:placetype":"venue"
},
  "geometry": {"coordinates":[-74.27052399999999,40.513492],"type":"Point"}
}