{
  "type": "Feature",
  "properties": {
    "iso:country":"US",
    "sg:address":"129 Brentwood Dr",
    "sg:city":"Mount Laurel",
    "sg:classifiers":[
        {
            "category":"Professional",
            "subcategory":"Computer Services",
            "type":"Services"
        }
    ],
    "sg:phone":"+1   ",
    "sg:postcode":"08054",
    "sg:province":"NJ",
    "sg:tags":[
        "related"
    ],
    "wof:name":"K B E",
    "wof:placetype":"venue"
},
  "geometry": {"coordinates":[-74.945579,39.931528],"type":"Point"}
}