{
  "type": "Feature",
  "properties": {
    "addr:full":"85 Reservoir Ave Jersey City NJ 07307",
    "addr:housenumber":"85",
    "addr:postcode":"07307",
    "addr:street":"Reservoir Ave",
    "iso:country":"US",
    "sg:address":"85 Reservoir Ave",
    "sg:city":"Jersey City",
    "sg:classifiers":[
        {
            "category":"Retail",
            "subcategory":"Self-service Laundry",
            "type":"Services"
        },
        {
            "category":"Retail",
            "subcategory":"Laundry & Dry Cleaning",
            "type":"Services"
        }
    ],
    "sg:phone":"+1 201 420 0865",
    "sg:postcode":"07307",
    "sg:province":"NJ",
    "sg:tags":[
        "power"
    ],
    "wof:name":"Lienau Laundromat",
    "wof:placetype":"venue"
},
  "geometry": {"coordinates":[-74.052318,40.740321],"type":"Point"}
}