{
  "type": "Feature",
  "properties": {
    "iso:country":"US",
    "sg:address":"2365 E State St Exd",
    "sg:city":"Trenton",
    "sg:classifiers":[
        {
            "category":"Banks & Credit Unions",
            "subcategory":"Bank",
            "type":"Services"
        }
    ],
    "sg:phone":"+1   ",
    "sg:postcode":"08619",
    "sg:province":"NJ",
    "sg:tags":[
        "banking",
        "facility"
    ],
    "wof:name":"Mellon",
    "wof:placetype":"venue"
},
  "geometry": {"coordinates":[-74.714675,40.245803],"type":"Point"}
}