{
  "type": "Feature",
  "properties": {
    "iso:country":"US",
    "sg:address":"285 Lackawanna Dr",
    "sg:city":"Andover",
    "sg:classifiers":[
        {
            "category":"Utilities",
            "subcategory":"Refuse",
            "type":"Services"
        }
    ],
    "sg:phone":"+1 973 448 0550",
    "sg:postcode":"07821",
    "sg:province":"NJ",
    "sg:tags":[
        "debris",
        "removal"
    ],
    "wof:name":"Cooperative Disposal Co Inc",
    "wof:placetype":"venue"
},
  "geometry": {"coordinates":[-74.677035,40.965083],"type":"Point"}
}