{
  "type": "Feature",
  "properties": {
    "addr:full":"535 Mountain Ave New Providence NJ 07974",
    "addr:housenumber":"535",
    "addr:postcode":"07974",
    "addr:street":"Mountain Ave",
    "iso:country":"US",
    "sg:address":"535 Mountain Ave",
    "sg:city":"New Providence",
    "sg:classifiers":[
        {
            "category":"Retail",
            "subcategory":"Repair Shop",
            "type":"Services"
        }
    ],
    "sg:phone":"+1 908 508 2064",
    "sg:postcode":"07974",
    "sg:province":"NJ",
    "sg:tags":[
        "electrical"
    ],
    "wof:name":"Unisource Wpc",
    "wof:placetype":"venue"
},
  "geometry": {"coordinates":[-74.40292100000001,40.685751],"type":"Point"}
}