{
  "type": "Feature",
  "properties": {
    "iso:country":"US",
    "sg:address":"53 Green Pond Rd",
    "sg:city":"Rockaway",
    "sg:classifiers":[
        {
            "category":"Wholesale",
            "subcategory":"Photographic Equipment",
            "type":"Manufacturing & Wholesale Goods"
        }
    ],
    "sg:phone":"+1 973 428 9800",
    "sg:postcode":"07866",
    "sg:province":"NJ",
    "sg:tags":[
        "supply"
    ],
    "sg:website":"www.tocad.com",
    "wof:name":"Tocad America Inc",
    "wof:placetype":"venue"
},
  "geometry": {"coordinates":[-74.494928,40.918794],"type":"Point"}
}