{
  "type": "Feature",
  "properties": {
    "addr:full":"18 Tea Rose Ln Trenton NJ 08620",
    "addr:housenumber":"18",
    "addr:postcode":"08620",
    "addr:street":"Tea Rose Ln",
    "iso:country":"US",
    "sg:address":"18 Tea Rose Ln",
    "sg:city":"Trenton",
    "sg:classifiers":[
        {
            "category":"Building & Trades",
            "subcategory":"Cleaning & Sanitation",
            "type":"Services"
        }
    ],
    "sg:phone":"+1   ",
    "sg:postcode":"08620",
    "sg:province":"NJ",
    "sg:tags":[
        "maintenance"
    ],
    "wof:name":"Torma Cleaning Services Inc",
    "wof:placetype":"venue"
},
  "geometry": {"coordinates":[-74.657008,40.16346],"type":"Point"}
}