{
  "type": "Feature",
  "properties": {
    "addr:full":"631 E Chestnut Ave Vineland NJ 08360",
    "addr:housenumber":"631",
    "addr:postcode":"08360",
    "addr:street":"E Chestnut Ave",
    "iso:country":"US",
    "sg:address":"631 E Chestnut Ave",
    "sg:city":"Vineland",
    "sg:classifiers":[
        {
            "category":"Food & Beverages",
            "subcategory":"Liquor & Beverages",
            "type":"Retail Goods"
        }
    ],
    "sg:phone":"+1   ",
    "sg:postcode":"08360",
    "sg:province":"NJ",
    "sg:tags":[
        "alcoholic"
    ],
    "wof:name":"Vineland Liquors",
    "wof:placetype":"venue"
},
  "geometry": {"coordinates":[-75.022223,39.478737],"type":"Point"}
}