{
  "type": "Feature",
  "properties": {
    "addr:full":"115 E Spring Valley Ave Maywood NJ 07607",
    "addr:housenumber":"115",
    "addr:postcode":"07607",
    "addr:street":"E Spring Valley Ave",
    "iso:country":"US",
    "sg:address":"115 E Spring Valley Ave",
    "sg:city":"Maywood",
    "sg:classifiers":[
        {
            "category":"Retail",
            "subcategory":"Auto Rental",
            "type":"Services"
        }
    ],
    "sg:phone":"+1 201 368 7006",
    "sg:postcode":"07607",
    "sg:province":"NJ",
    "sg:tags":[
        "truck"
    ],
    "wof:name":"Ryder",
    "wof:placetype":"venue"
},
  "geometry": {"coordinates":[-74.05436400000001,40.910559],"type":"Point"}
}