{
  "type": "Feature",
  "properties": {
    "iso:country":"US",
    "sg:address":"372 Broad St Ste 3",
    "sg:city":"Bloomfield",
    "sg:classifiers":[
        {
            "category":"Personal",
            "subcategory":"Tanning Parlor",
            "type":"Services"
        }
    ],
    "sg:phone":"+1 973 429 1404",
    "sg:postcode":"07003",
    "sg:province":"NJ",
    "wof:name":"Bodies In Heat Tanning Salon",
    "wof:placetype":"venue"
},
  "geometry": {"coordinates":[-74.192802,40.8064],"type":"Point"}
}