{
  "type": "Feature",
  "properties": {
    "iso:country":"US",
    "sg:address":"1485 Thomas Ave",
    "sg:city":"North Brunswick",
    "sg:classifiers":[
        {
            "category":"Professional",
            "subcategory":"Management & Consulting",
            "type":"Services"
        }
    ],
    "sg:phone":"+1 732 297 2172",
    "sg:postcode":"08902",
    "sg:province":"NJ",
    "sg:tags":[
        "lobbying",
        "consultant",
        "public",
        "relations"
    ],
    "wof:name":"ARC Associates LLC",
    "wof:placetype":"venue"
},
  "geometry": {"coordinates":[-74.525167,40.442547],"type":"Point"}
}