{
  "type": "Feature",
  "properties": {
    "iso:country":"US",
    "sg:address":"414 Central Ave",
    "sg:city":"Westfield",
    "sg:classifiers":[
        {
            "category":"Professional",
            "type":"Services"
        }
    ],
    "sg:phone":"+1 908 654 1619",
    "sg:postcode":"07090",
    "sg:province":"NJ",
    "sg:tags":[
        "establishment"
    ],
    "wof:name":"Glamour Studios LLC",
    "wof:placetype":"venue"
},
  "geometry": {"coordinates":[-74.341848,40.648434],"type":"Point"}
}