{
  "type": "Feature",
  "properties": {
    "addr:full":"218 N Roosevelt Blvd Brigantine NJ 08203",
    "addr:housenumber":"218",
    "addr:postcode":"08203",
    "addr:street":"N Roosevelt Blvd",
    "iso:country":"US",
    "sg:address":"218 N Roosevelt Blvd",
    "sg:city":"Brigantine",
    "sg:classifiers":[
        {
            "category":"Professional",
            "subcategory":"Engineering",
            "type":"Services"
        }
    ],
    "sg:phone":"+1 609 266 3272",
    "sg:postcode":"08203",
    "sg:province":"NJ",
    "sg:tags":[
        "general",
        "contractor"
    ],
    "wof:name":"GAJ Builders",
    "wof:placetype":"venue"
},
  "geometry": {"coordinates":[-74.37036999999999,39.418757],"type":"Point"}
}