{
  "type": "Feature",
  "properties": {
    "iso:country":"US",
    "sg:address":"175 Orient Way",
    "sg:city":"Rutherford",
    "sg:classifiers":[
        {
            "category":"Professional",
            "subcategory":"Management & Consulting",
            "type":"Services"
        }
    ],
    "sg:phone":"+1 201 507 5310",
    "sg:postcode":"07070",
    "sg:province":"NJ",
    "sg:tags":[
        "public",
        "relations"
    ],
    "wof:name":"Main Street Web Promotions",
    "wof:placetype":"venue"
},
  "geometry": {"coordinates":[-74.104398,40.821839],"type":"Point"}
}