{
  "type": "Feature",
  "properties": {
    "addr:full":"525 Somerset St Plainfield NJ 07060",
    "addr:housenumber":"525",
    "addr:postcode":"07060",
    "addr:street":"Somerset St",
    "iso:country":"US",
    "sg:address":"525 Somerset St",
    "sg:city":"Plainfield",
    "sg:classifiers":[
        {
            "category":"Food & Beverages",
            "subcategory":"Bakery",
            "type":"Retail Goods"
        }
    ],
    "sg:phone":"+1   ",
    "sg:postcode":"07060",
    "sg:province":"NJ",
    "sg:tags":[
        "sell",
        "bagel"
    ],
    "wof:name":"Bagel Master",
    "wof:placetype":"venue"
},
  "geometry": {"coordinates":[-74.436685,40.626143],"type":"Point"}
}