{
  "type": "Feature",
  "properties": {
    "addr:full":"132 Van Liew Ave Milltown NJ 08850",
    "addr:housenumber":"132",
    "addr:postcode":"08850",
    "addr:street":"Van Liew Ave",
    "iso:country":"US",
    "sg:address":"132 Van Liew Ave",
    "sg:city":"Milltown",
    "sg:classifiers":[
        {
            "category":"Autos & Motor Vehicles",
            "subcategory":"Auto Supplies",
            "type":"Retail Goods"
        }
    ],
    "sg:phone":"+1   ",
    "sg:postcode":"08850",
    "sg:province":"NJ",
    "sg:tags":[
        "trade",
        "contractor"
    ],
    "wof:name":"Heads Up Industries",
    "wof:placetype":"venue"
},
  "geometry": {"coordinates":[-74.439159,40.458697],"type":"Point"}
}