{
  "type": "Feature",
  "properties": {
    "iso:country":"US",
    "sg:address":"812 27th St",
    "sg:city":"Union City",
    "sg:classifiers":[
        {
            "category":"Retail",
            "subcategory":"Auto Repair",
            "type":"Services"
        }
    ],
    "sg:phone":"+1 201 867 2339",
    "sg:postcode":"07087",
    "sg:province":"NJ",
    "wof:name":"Del Sol & Son",
    "wof:placetype":"venue"
},
  "geometry": {"coordinates":[-74.035202,40.7715],"type":"Point"}
}