{
  "type": "Feature",
  "properties": {
    "iso:country":"US",
    "sg:address":"45 S Main St",
    "sg:city":"Manville",
    "sg:classifiers":[
        {
            "category":"Manufacturing",
            "subcategory":"Tools & Machinery",
            "type":"Manufacturing & Wholesale Goods"
        }
    ],
    "sg:phone":"+1 908 526 3408",
    "sg:postcode":"08835",
    "sg:province":"NJ",
    "sg:tags":[
        "analytical",
        "laboratory",
        "instrument"
    ],
    "sg:website":"www.voiceident.com",
    "wof:name":"Voice Identification Inc",
    "wof:placetype":"venue"
},
  "geometry": {"coordinates":[-74.58699,40.543815],"type":"Point"}
}