{
  "type": "Feature",
  "properties": {
    "addr:full":"1 Ironside Ct Willingboro NJ 08046",
    "addr:housenumber":"1",
    "addr:postcode":"08046",
    "addr:street":"Ironside Ct",
    "iso:country":"US",
    "sg:address":"1 Ironside Ct",
    "sg:city":"Willingboro",
    "sg:classifiers":[
        {
            "category":"Sports & Exercise",
            "subcategory":"Bicycle Rental",
            "type":"Entertainment"
        }
    ],
    "sg:phone":"+1 609 871 8888",
    "sg:postcode":"08046",
    "sg:province":"NJ",
    "sg:tags":[
        "wear"
    ],
    "wof:name":"Counter-Fit",
    "wof:placetype":"venue"
},
  "geometry": {"coordinates":[-74.913803,40.0336],"type":"Point"}
}