{
  "type": "Feature",
  "properties": {
    "addr:full":"325 S Main St Barnegat NJ 08005",
    "addr:housenumber":"325",
    "addr:postcode":"08005",
    "addr:street":"S Main St",
    "iso:country":"US",
    "sg:address":"325 S Main St",
    "sg:city":"Barnegat",
    "sg:classifiers":[
        {
            "category":"Home & Garden",
            "subcategory":"Carpets & Floor Coverings",
            "type":"Retail Goods"
        }
    ],
    "sg:phone":"+1 609 698 1111",
    "sg:postcode":"08005",
    "sg:province":"NJ",
    "sg:tags":[
        "dealer",
        "rug"
    ],
    "wof:name":"Bob's Carpet Svc",
    "wof:placetype":"venue"
},
  "geometry": {"coordinates":[-74.224563,39.750488],"type":"Point"}
}