{
  "type": "Feature",
  "properties": {
    "iso:country":"US",
    "sg:address":"10 Zelley Ave",
    "sg:city":"Yardville",
    "sg:classifiers":[
        {
            "category":"Building & Trades",
            "subcategory":"Construction",
            "type":"Services"
        }
    ],
    "sg:phone":"+1 609 989 0222",
    "sg:postcode":"08620",
    "sg:province":"NJ",
    "sg:tags":[
        "siding",
        "contractor"
    ],
    "wof:name":"DEI Roofing Contractors",
    "wof:placetype":"venue"
},
  "geometry": {"coordinates":[-74.66696399999999,40.173103],"type":"Point"}
}