{
  "type": "Feature",
  "properties": {
    "addr:full":"325 7th Ave Glendora NJ 08029",
    "addr:housenumber":"325",
    "addr:postcode":"08029",
    "addr:street":"7Th Ave",
    "iso:country":"US",
    "sg:address":"325 7th Ave",
    "sg:city":"Glendora",
    "sg:classifiers":[
        {
            "category":"Insurance",
            "subcategory":"Hazard Insurance",
            "type":"Services"
        }
    ],
    "sg:phone":"+1 856 939 5546",
    "sg:postcode":"08029",
    "sg:province":"NJ",
    "wof:name":"A J Rutkowski Limited Liability Company",
    "wof:placetype":"venue"
},
  "geometry": {"coordinates":[-75.064061,39.840309],"type":"Point"}
}