{
  "type": "Feature",
  "properties": {
    "iso:country":"US",
    "sg:address":"291 Pompton Ave",
    "sg:city":"Verona",
    "sg:classifiers":[
        {
            "category":"Wholesale",
            "subcategory":"Stationery",
            "type":"Manufacturing & Wholesale Goods"
        }
    ],
    "sg:phone":"+1 973 239 6255",
    "sg:postcode":"07044",
    "sg:province":"NJ",
    "sg:tags":[
        "card"
    ],
    "wof:name":"Victorias Hallmark",
    "wof:placetype":"venue"
},
  "geometry": {"coordinates":[-74.22663900000001,40.83506],"type":"Point"}
}