{
  "type": "Feature",
  "properties": {
    "addr:full":"68 Brass Castle Rd Washington NJ 07882",
    "addr:housenumber":"68",
    "addr:postcode":"07882",
    "addr:street":"Brass Castle Rd",
    "iso:country":"US",
    "sg:address":"68 Brass Castle Rd",
    "sg:city":"Washington",
    "sg:classifiers":[
        {
            "category":"Building & Trades",
            "subcategory":"Landscaping Services",
            "type":"Services"
        }
    ],
    "sg:phone":"+1 908 689 6824",
    "sg:postcode":"07882",
    "sg:province":"NJ",
    "sg:tags":[
        "landscape",
        "contractor"
    ],
    "wof:name":"C R SHOTWELL Landscape Ma",
    "wof:placetype":"venue"
},
  "geometry": {"coordinates":[-75.005357,40.760695],"type":"Point"}
}