{
  "type": "Feature",
  "properties": {
    "addr:full":"405 E 7th Ave North Wildwood NJ 08260",
    "addr:housenumber":"405",
    "addr:postcode":"08260",
    "addr:street":"E 7Th Ave North",
    "iso:country":"US",
    "sg:address":"405 E 7th Ave",
    "sg:city":"North Wildwood",
    "sg:classifiers":[
        {
            "category":"Travel",
            "subcategory":"Hotels & Motels",
            "type":"Entertainment"
        }
    ],
    "sg:phone":"+1 609 729 6900",
    "sg:postcode":"08260",
    "sg:province":"NJ",
    "sg:tags":[
        "operation"
    ],
    "wof:name":"Majestic Apartments",
    "wof:placetype":"venue"
},
  "geometry": {"coordinates":[-74.79300600000001,39.0012],"type":"Point"}
}