{
  "type": "Feature",
  "properties": {
    "addr:full":"84 Brighton Ave Long Branch NJ 07740",
    "addr:housenumber":"84",
    "addr:postcode":"07740",
    "addr:street":"Brighton Ave",
    "iso:country":"US",
    "sg:address":"84 Brighton Ave",
    "sg:city":"Long Branch",
    "sg:classifiers":[
        {
            "category":"Shopping",
            "subcategory":"Clothing, Apparel, & Fashions",
            "type":"Retail Goods"
        }
    ],
    "sg:phone":"+1   ",
    "sg:postcode":"07740",
    "sg:province":"NJ",
    "wof:name":"Bear Necessities",
    "wof:placetype":"venue"
},
  "geometry": {"coordinates":[-73.98409599999999,40.284561],"type":"Point"}
}