{
  "type": "Feature",
  "properties": {
    "iso:country":"US",
    "sg:address":"212 Maple Ave",
    "sg:city":"Red Bank",
    "sg:classifiers":[
        {
            "category":"Professional",
            "subcategory":"Lawyer & Legal Services",
            "type":"Services"
        }
    ],
    "sg:phone":"+1 732 842 7773",
    "sg:postcode":"07701",
    "sg:province":"NJ",
    "sg:tags":[
        "attorney"
    ],
    "wof:name":"Charles Moriarty LLC",
    "wof:placetype":"venue"
},
  "geometry": {"coordinates":[-74.067742,40.342189],"type":"Point"}
}