{
  "type": "Feature",
  "properties": {
    "iso:country":"US",
    "sg:address":"3007 Bridgeboro Rd",
    "sg:city":"Delran",
    "sg:classifiers":[
        {
            "category":"Wholesale",
            "subcategory":"Electrical",
            "type":"Manufacturing & Wholesale Goods"
        }
    ],
    "sg:phone":"+1 856 764 2730",
    "sg:postcode":"08075",
    "sg:province":"NJ",
    "sg:tags":[
        "electric",
        "motor"
    ],
    "wof:name":"Alert Motor Freight",
    "wof:placetype":"venue"
},
  "geometry": {"coordinates":[-74.935103,40.013233],"type":"Point"}
}