{
  "type": "Feature",
  "properties": {
    "addr:full":"649 Trenton Ave Kenilworth NJ 07033",
    "addr:housenumber":"649",
    "addr:postcode":"07033",
    "addr:street":"Trenton Ave",
    "iso:country":"US",
    "sg:address":"649 Trenton Ave",
    "sg:city":"Kenilworth",
    "sg:classifiers":[
        {
            "category":"Professional",
            "type":"Services"
        }
    ],
    "sg:phone":"+1   ",
    "sg:postcode":"07033",
    "sg:province":"NJ",
    "wof:name":"JD Mate LLC",
    "wof:placetype":"venue"
},
  "geometry": {"coordinates":[-74.284873,40.670742],"type":"Point"}
}