{
  "type": "Feature",
  "properties": {
    "addr:full":"3056 State Route 10 Denville NJ 07834",
    "addr:housenumber":"3056",
    "addr:postcode":"07834",
    "addr:street":"State Route 10",
    "iso:country":"US",
    "sg:address":"3056 State Route 10",
    "sg:city":"Denville",
    "sg:classifiers":[
        {
            "category":"Restaurant",
            "type":"Food & Drink"
        }
    ],
    "sg:phone":"+1 973 989 1023",
    "sg:postcode":"07834",
    "sg:province":"NJ",
    "sg:tags":[
        "pizza"
    ],
    "wof:name":"Bensi of Denville Inc",
    "wof:placetype":"venue"
},
  "geometry": {"coordinates":[-74.506929,40.86652],"type":"Point"}
}