{
  "type": "Feature",
  "properties": {
    "addr:full":"601 Whitall Ave Millville NJ 08332",
    "addr:housenumber":"601",
    "addr:postcode":"08332",
    "addr:street":"Whitall Ave",
    "iso:country":"US",
    "sg:address":"601 Whitall Ave",
    "sg:city":"Millville",
    "sg:classifiers":[
        {
            "category":"Real Estate",
            "subcategory":"Real Estate Services",
            "type":"Services"
        },
        {
            "category":"Real Estate",
            "subcategory":"Real Estate Agent",
            "type":"Services"
        }
    ],
    "sg:phone":"+1 856 327 2356",
    "sg:postcode":"08332",
    "sg:province":"NJ",
    "sg:tags":[
        "buyer",
        "broker"
    ],
    "wof:name":"Maturo Realty, Inc.",
    "wof:placetype":"venue"
},
  "geometry": {"coordinates":[-75.026009,39.386108],"type":"Point"}
}