{
  "type": "Feature",
  "properties": {
    "addr:full":"46 Club Ridge Ln Willingboro NJ 08046",
    "addr:housenumber":"46",
    "addr:postcode":"08046",
    "addr:street":"Club Ridge Ln",
    "iso:country":"US",
    "sg:address":"46 Club Ridge Ln",
    "sg:city":"Willingboro",
    "sg:classifiers":[
        {
            "category":"Professional",
            "subcategory":"Management & Consulting",
            "type":"Services"
        }
    ],
    "sg:phone":"+1 609 871 5885",
    "sg:postcode":"08046",
    "sg:province":"NJ",
    "wof:name":"Rancocas Financial Services",
    "wof:placetype":"venue"
},
  "geometry": {"coordinates":[-74.894307,40.012195],"type":"Point"}
}