{
  "type": "Feature",
  "properties": {
    "addr:full":"121 State Rte 73 Marlton NJ 08053",
    "addr:housenumber":"121",
    "addr:postcode":"08053",
    "addr:street":"State Rte 73",
    "iso:country":"US",
    "sg:address":"121 State Rte 73",
    "sg:city":"Marlton",
    "sg:classifiers":[
        {
            "category":"Personal",
            "subcategory":"Beauty Salon",
            "type":"Services"
        }
    ],
    "sg:phone":"+1   ",
    "sg:postcode":"08053",
    "sg:province":"NJ",
    "sg:tags":[
        "shop"
    ],
    "wof:name":"Scruples",
    "wof:placetype":"venue"
},
  "geometry": {"coordinates":[-74.926344,39.891543],"type":"Point"}
}