{
  "type": "Feature",
  "properties": {
    "addr:full":"712 Clinton Ave South Plainfield NJ 07080",
    "addr:housenumber":"712",
    "addr:postcode":"07080",
    "addr:street":"Clinton Ave",
    "iso:country":"US",
    "sg:address":"712 Clinton Ave",
    "sg:city":"South Plainfield",
    "sg:classifiers":[
        {
            "category":"Food & Beverages",
            "subcategory":"Groceries & Convenience Stores",
            "type":"Retail Goods"
        }
    ],
    "sg:phone":"+1   ",
    "sg:postcode":"07080",
    "sg:province":"NJ",
    "wof:name":"Food Fair",
    "wof:placetype":"venue"
},
  "geometry": {"coordinates":[-74.436356,40.596355],"type":"Point"}
}