{
  "type": "Feature",
  "properties": {
    "iso:country":"US",
    "sg:address":"1730 N Olden Avenue Ext",
    "sg:city":"Trenton",
    "sg:classifiers":[
        {
            "category":"Restaurant",
            "type":"Food & Drink"
        }
    ],
    "sg:menulink":"http://www.allmenus.com/nj/ewing/181766-wendys/menu/",
    "sg:phone":"+1 609 771 4147",
    "sg:postcode":"08638",
    "sg:province":"NJ",
    "sg:tags":[
        "burger",
        "american",
        "soup"
    ],
    "wof:name":"Wendy's",
    "wof:placetype":"venue"
},
  "geometry": {"coordinates":[-74.767556,40.248126],"type":"Point"}
}