{
  "type": "Feature",
  "properties": {
    "addr:full":"3258 Asbury Ave Ocean City NJ 08226",
    "addr:housenumber":"3258",
    "addr:postcode":"08226",
    "addr:street":"Asbury Ave",
    "iso:country":"US",
    "sg:address":"3258 Asbury Ave",
    "sg:city":"Ocean City",
    "sg:classifiers":[
        {
            "category":"Real Estate",
            "subcategory":"Real Estate Agent",
            "type":"Services"
        }
    ],
    "sg:phone":"+1 609 399 4663",
    "sg:postcode":"08226",
    "sg:province":"NJ",
    "wof:name":"Carl D Bradley",
    "wof:placetype":"venue"
},
  "geometry": {"coordinates":[-74.60914200000001,39.252926],"type":"Point"}
}