{
  "type": "Feature",
  "properties": {
    "addr:full":"3710 US Hwy 9 Freehold NJ 07728",
    "addr:housenumber":"3710",
    "addr:postcode":"07728",
    "addr:street":"Us Hwy 9",
    "iso:country":"US",
    "sg:address":"3710 US Hwy 9",
    "sg:city":"Freehold",
    "sg:classifiers":[
        {
            "category":"Shopping",
            "subcategory":"Clothing, Apparel, & Fashions",
            "type":"Retail Goods"
        }
    ],
    "sg:phone":"+1   ",
    "sg:postcode":"07728",
    "sg:province":"NJ",
    "sg:tags":[
        "department",
        "family",
        "store"
    ],
    "wof:name":"Nordstrom 522",
    "wof:placetype":"venue"
},
  "geometry": {"coordinates":[-74.2856,40.249722],"type":"Point"}
}