{
  "type": "Feature",
  "properties": {
    "addr:full":"55 Park St Montclair NJ 07042",
    "addr:housenumber":"55",
    "addr:postcode":"07042",
    "addr:street":"Park St",
    "iso:country":"US",
    "sg:address":"55 Park St",
    "sg:city":"Montclair",
    "sg:classifiers":[
        {
            "category":"Professional",
            "subcategory":"Management & Consulting",
            "type":"Services"
        }
    ],
    "sg:phone":"+1 973 744 8282",
    "sg:postcode":"07042",
    "sg:province":"NJ",
    "sg:tags":[
        "consultant",
        "business"
    ],
    "wof:name":"Bioxy Source",
    "wof:placetype":"venue"
},
  "geometry": {"coordinates":[-74.21745799999999,40.816858],"type":"Point"}
}