{
  "type": "Feature",
  "properties": {
    "addr:full":"1335 Belvidere Rd Phillipsburg NJ 08865",
    "addr:housenumber":"1335",
    "addr:postcode":"08865",
    "addr:street":"Belvidere Rd",
    "iso:country":"US",
    "sg:address":"1335 Belvidere Rd",
    "sg:city":"Phillipsburg",
    "sg:classifiers":[
        {
            "category":"Health Services",
            "subcategory":"Chiropractor",
            "type":"Services"
        }
    ],
    "sg:phone":"+1 908 859 6379",
    "sg:postcode":"08865",
    "sg:province":"NJ",
    "wof:name":"S B Krisanda DC",
    "wof:placetype":"venue"
},
  "geometry": {"coordinates":[-75.17462,40.712742],"type":"Point"}
}