{
  "type": "Feature",
  "properties": {
    "iso:country":"US",
    "sg:address":"136 Rounsaville Rd",
    "sg:city":"Hampton",
    "sg:classifiers":[
        {
            "category":"Building & Trades",
            "subcategory":"Construction",
            "type":"Services"
        }
    ],
    "sg:phone":"+1 908 537 4929",
    "sg:postcode":"08827",
    "sg:province":"NJ",
    "sg:tags":[
        "contractor"
    ],
    "wof:name":"Haines Construction Inc",
    "wof:placetype":"venue"
},
  "geometry": {"coordinates":[-74.987701,40.683601],"type":"Point"}
}