{
  "type": "Feature",
  "properties": {
    "addr:full":"786 River Dr Garfield NJ 07026",
    "addr:housenumber":"786",
    "addr:postcode":"07026",
    "addr:street":"River Dr",
    "iso:country":"US",
    "sg:address":"786 River Dr",
    "sg:city":"Garfield",
    "sg:classifiers":[
        {
            "category":"Autos & Motor Vehicles",
            "subcategory":"Fuel & Gas Station",
            "type":"Retail Goods"
        }
    ],
    "sg:phone":"+1   ",
    "sg:postcode":"07026",
    "sg:province":"NJ",
    "sg:tags":[
        "station",
        "gasoline"
    ],
    "wof:name":"Afro-Liberian One",
    "wof:placetype":"venue"
},
  "geometry": {"coordinates":[-74.125057,40.883645],"type":"Point"}
}