{
  "type": "Feature",
  "properties": {
    "addr:full":"1 E Shore Rd Mountain Lakes NJ 07046",
    "addr:housenumber":"1",
    "addr:postcode":"07046",
    "addr:street":"E Shore Rd",
    "iso:country":"US",
    "sg:address":"1 E Shore Rd",
    "sg:city":"Mountain Lakes",
    "sg:classifiers":[
        {
            "category":"Professional",
            "subcategory":"Computer Services",
            "type":"Services"
        }
    ],
    "sg:phone":"+1   ",
    "sg:postcode":"07046",
    "sg:province":"NJ",
    "sg:tags":[
        "consulting",
        "processing",
        "datum"
    ],
    "wof:name":"Elevan Inc",
    "wof:placetype":"venue"
},
  "geometry": {"coordinates":[-74.453818,40.887018],"type":"Point"}
}