{
  "type": "Feature",
  "properties": {
    "iso:country":"US",
    "sg:address":"545 Wilmerding Ave",
    "sg:city":"Teaneck",
    "sg:classifiers":[
        {
            "category":"Professional",
            "subcategory":"Research",
            "type":"Services"
        }
    ],
    "sg:phone":"+1 201 907 0904",
    "sg:postcode":"07666",
    "sg:province":"NJ",
    "sg:tags":[
        "merger",
        "financial",
        "advising"
    ],
    "wof:name":"Kestenbaum Associates",
    "wof:placetype":"venue"
},
  "geometry": {"coordinates":[-74.019625,40.9014],"type":"Point"}
}