{
  "type": "Feature",
  "properties": {
    "addr:full":"585 Somerset St Somerset NJ 08873",
    "addr:housenumber":"585",
    "addr:postcode":"08873",
    "addr:street":"Somerset St",
    "iso:country":"US",
    "sg:address":"585 Somerset St",
    "sg:city":"Somerset",
    "sg:classifiers":[
        {
            "category":"Food & Beverages",
            "subcategory":"Meat & Fish",
            "type":"Retail Goods"
        }
    ],
    "sg:phone":"+1   ",
    "sg:postcode":"08873",
    "sg:province":"NJ",
    "wof:name":"A & E Meat Market Inc",
    "wof:placetype":"venue"
},
  "geometry": {"coordinates":[-74.469318,40.486478],"type":"Point"}
}