{
  "type": "Feature",
  "properties": {
    "addr:full":"263 Glen Rd Monroe Twp NJ 08831",
    "addr:housenumber":"263",
    "addr:postcode":"08831",
    "addr:street":"Glen Rd",
    "iso:country":"US",
    "sg:address":"263 Glen Rd",
    "sg:city":"Monroe Twp",
    "sg:classifiers":[
        {
            "category":"Professional",
            "subcategory":"Accounting & Tax Preparation",
            "type":"Services"
        }
    ],
    "sg:phone":"+1 732 274 0901",
    "sg:postcode":"08831",
    "sg:province":"NJ",
    "sg:tags":[
        "accountant"
    ],
    "wof:name":"Herbert Kurzman CPA",
    "wof:placetype":"venue"
},
  "geometry": {"coordinates":[-74.460449,40.31338],"type":"Point"}
}