{
  "type": "Feature",
  "properties": {
    "iso:country":"US",
    "sg:address":"448 Broadway",
    "sg:city":"Hillsdale",
    "sg:classifiers":[
        {
            "category":"Building & Trades",
            "subcategory":"Equipment Rental",
            "type":"Services"
        }
    ],
    "sg:phone":"+1 201 664 0900",
    "sg:postcode":"07642",
    "sg:province":"NJ",
    "wof:name":"Taylor Rental Service",
    "wof:placetype":"venue"
},
  "geometry": {"coordinates":[-74.04159799999999,41.014812],"type":"Point"}
}