{
  "type": "Feature",
  "properties": {
    "addr:full":"6815 Woodland Ave Pennsauken NJ 08110",
    "addr:housenumber":"6815",
    "addr:postcode":"08110",
    "addr:street":"Woodland Ave",
    "iso:country":"US",
    "sg:address":"6815 Woodland Ave",
    "sg:city":"Pennsauken",
    "sg:classifiers":[
        {
            "category":"Organizations",
            "subcategory":"Religious Organization",
            "type":"Services"
        }
    ],
    "sg:phone":"+1 856 662 4949",
    "sg:postcode":"08110",
    "sg:province":"NJ",
    "sg:tags":[
        "church"
    ],
    "wof:name":"Judah Community Fellowship Chr",
    "wof:placetype":"venue"
},
  "geometry": {"coordinates":[-75.07894,39.936308],"type":"Point"}
}