{
  "type": "Feature",
  "properties": {
    "iso:country":"US",
    "sg:address":"116 S 2nd St",
    "sg:city":"Hammonton",
    "sg:classifiers":[
        {
            "category":"Professional",
            "type":"Services"
        }
    ],
    "sg:phone":"+1   ",
    "sg:postcode":"08037",
    "sg:province":"NJ",
    "wof:name":"Jose Luis Rodriguez",
    "wof:placetype":"venue"
},
  "geometry": {"coordinates":[-74.802521,39.635188],"type":"Point"}
}