{
  "type": "Feature",
  "properties": {
    "addr:full":"26 Morningside Pl Asbury Park NJ 07758",
    "addr:housenumber":"26",
    "addr:postcode":"07758",
    "addr:street":"Morningside Pl Asbury",
    "iso:country":"US",
    "sg:address":"26 Morningside Pl",
    "sg:city":"Asbury Park",
    "sg:classifiers":[
        {
            "category":"Professional",
            "type":"Services"
        }
    ],
    "sg:phone":"+1   ",
    "sg:postcode":"07758",
    "sg:province":"NJ",
    "wof:name":"Frances Greco",
    "wof:placetype":"venue"
},
  "geometry": {"coordinates":[-74.11742,40.422606],"type":"Point"}
}