{
  "type": "Feature",
  "properties": {
    "addr:full":"3250 Princeton Pike Lawrenceville NJ 08648",
    "addr:housenumber":"3250",
    "addr:postcode":"08648",
    "addr:street":"Princeton Pike",
    "iso:country":"US",
    "sg:address":"3250 Princeton Pike",
    "sg:city":"Lawrenceville",
    "sg:classifiers":[
        {
            "category":"Professional",
            "subcategory":"Accounting & Tax Preparation",
            "type":"Services"
        }
    ],
    "sg:phone":"+1 609 896 0660",
    "sg:postcode":"08648",
    "sg:province":"NJ",
    "sg:tags":[
        "bookkeeping",
        "general"
    ],
    "wof:name":"Quinn & Storey Inc",
    "wof:placetype":"venue"
},
  "geometry": {"coordinates":[-74.709943,40.289821],"type":"Point"}
}