{
  "type": "Feature",
  "properties": {
    "addr:full":"20 1st Ave Denville NJ 07834",
    "addr:housenumber":"20",
    "addr:postcode":"07834",
    "addr:street":"1St Ave",
    "iso:country":"US",
    "sg:address":"20 1st Ave",
    "sg:city":"Denville",
    "sg:classifiers":[
        {
            "category":"Retail",
            "subcategory":"Auto Rental",
            "type":"Services"
        }
    ],
    "sg:phone":"+1 973 625 0681",
    "sg:postcode":"07834",
    "sg:province":"NJ",
    "sg:tags":[
        "renting",
        "truck",
        "leasing"
    ],
    "wof:name":"Budget Truck Rental",
    "wof:placetype":"venue"
},
  "geometry": {"coordinates":[-74.47649800000001,40.892979],"type":"Point"}
}