{
  "type": "Feature",
  "properties": {
    "addr:full":"3 Ethel Ave Hawthorne NJ 07506",
    "addr:housenumber":"3",
    "addr:postcode":"07506",
    "addr:street":"Ethel Ave",
    "iso:country":"US",
    "sg:address":"3 Ethel Ave",
    "sg:city":"Hawthorne",
    "sg:classifiers":[
        {
            "category":"Shopping",
            "subcategory":"Clothing, Apparel, & Fashions",
            "type":"Retail Goods"
        }
    ],
    "sg:phone":"+1   ",
    "sg:postcode":"07506",
    "sg:province":"NJ",
    "wof:name":"Custom Clothes Corporation",
    "wof:placetype":"venue"
},
  "geometry": {"coordinates":[-74.15371500000001,40.962136],"type":"Point"}
}