{
  "type": "Feature",
  "properties": {
    "iso:country":"US",
    "sg:address":"25 Church St",
    "sg:city":"Montclair",
    "sg:classifiers":[
        {
            "category":"Food & Beverages",
            "subcategory":"Candy",
            "type":"Retail Goods"
        }
    ],
    "sg:phone":"+1 973 337 8019",
    "sg:postcode":"07042",
    "sg:province":"NJ",
    "sg:tags":[
        "dessert"
    ],
    "wof:name":"Cupcakes Galore",
    "wof:placetype":"venue"
},
  "geometry": {"coordinates":[-74.21886499999999,40.813974],"type":"Point"}
}