{
  "type": "Feature",
  "properties": {
    "addr:full":"504 Elbow Ln Burlington NJ 08016",
    "addr:housenumber":"504",
    "addr:postcode":"08016",
    "addr:street":"Elbow Ln",
    "iso:country":"US",
    "sg:address":"504 Elbow Ln",
    "sg:city":"Burlington",
    "sg:classifiers":[
        {
            "category":"Retail",
            "subcategory":"Pet Boarding",
            "type":"Services"
        }
    ],
    "sg:phone":"+1 609 386 6550",
    "sg:postcode":"08016",
    "sg:province":"NJ",
    "sg:tags":[
        "boarding/pet",
        "sitting"
    ],
    "wof:name":"Arbury Kennels",
    "wof:placetype":"venue"
},
  "geometry": {"coordinates":[-74.844902,40.037102],"type":"Point"}
}