{
  "type": "Feature",
  "properties": {
    "addr:full":"1500 Main St Rahway NJ 07065",
    "addr:housenumber":"1500",
    "addr:postcode":"07065",
    "addr:street":"Main St",
    "iso:country":"US",
    "sg:address":"1500 Main St",
    "sg:city":"Rahway",
    "sg:classifiers":[
        {
            "category":"Personal",
            "subcategory":"Shoe Repair & Shine",
            "type":"Services"
        }
    ],
    "sg:phone":"+1 732 388 1491",
    "sg:postcode":"07065",
    "sg:province":"NJ",
    "wof:name":"Main Shoe Repair",
    "wof:placetype":"venue"
},
  "geometry": {"coordinates":[-74.27403200000001,40.606961],"type":"Point"}
}