{
  "type": "Feature",
  "properties": {
    "addr:full":"515 Pennsylvania Ave Linden NJ 07036",
    "addr:housenumber":"515",
    "addr:postcode":"07036",
    "addr:street":"Pennsylvania Ave",
    "iso:country":"US",
    "sg:address":"515 Pennsylvania Ave",
    "sg:city":"Linden",
    "sg:classifiers":[
        {
            "category":"Utilities",
            "subcategory":"Water",
            "type":"Services"
        },
        {
            "category":"Building & Trades",
            "subcategory":"Plumbing",
            "type":"Services"
        },
        {
            "category":"Home & Garden",
            "subcategory":"Hardware",
            "type":"Retail Goods"
        }
    ],
    "sg:phone":"+1 908 486 2000",
    "sg:postcode":"07036",
    "sg:province":"NJ",
    "sg:tags":[
        "filtration",
        "softening",
        "supply",
        "work",
        "purification",
        "equipment",
        "conditioning"
    ],
    "wof:name":"Scientific Boiler Water Conditioning Co., Inc",
    "wof:placetype":"venue"
},
  "geometry": {"coordinates":[-74.247795,40.633694],"type":"Point"}
}