{
  "type": "Feature",
  "properties": {
    "iso:country":"US",
    "sg:address":"133 Carter Rd",
    "sg:city":"Princeton",
    "sg:classifiers":[
        {
            "category":"Building & Trades",
            "subcategory":"Landscaping Services",
            "type":"Services"
        }
    ],
    "sg:phone":"+1 609 921 9248",
    "sg:postcode":"08540",
    "sg:province":"NJ",
    "sg:tags":[
        "garden",
        "cent",
        "contractor",
        "nursery",
        "grows",
        "landscape",
        "stock"
    ],
    "sg:website":"www.kalesnursery.com",
    "wof:name":"Kale's Nursery & Landscape Svc",
    "wof:placetype":"venue"
},
  "geometry": {"coordinates":[-74.716835,40.327494],"type":"Point"}
}