{
  "type": "Feature",
  "properties": {
    "iso:country":"US",
    "sg:address":"812 State Rd",
    "sg:city":"Princeton",
    "sg:classifiers":[
        {
            "category":"Professional",
            "subcategory":"Secretarial Services",
            "type":"Services"
        }
    ],
    "sg:phone":"+1 609 497 0600",
    "sg:postcode":"08540",
    "sg:province":"NJ",
    "sg:tags":[
        "transcription",
        "medical"
    ],
    "wof:name":"Doc's Side Med Transcription",
    "wof:placetype":"venue"
},
  "geometry": {"coordinates":[-74.654415,40.390727],"type":"Point"}
}