{
  "type": "Feature",
  "properties": {
    "addr:full":"407 Bloomfield Dr West Berlin NJ 08091",
    "addr:housenumber":"407",
    "addr:postcode":"08091",
    "addr:street":"Bloomfield Dr",
    "iso:country":"US",
    "sg:address":"407 Bloomfield Dr",
    "sg:city":"West Berlin",
    "sg:classifiers":[
        {
            "category":"Wholesale",
            "subcategory":"Electrical",
            "type":"Manufacturing & Wholesale Goods"
        }
    ],
    "sg:phone":"+1 856 719 0081",
    "sg:postcode":"08091",
    "sg:province":"NJ",
    "sg:tags":[
        "meter"
    ],
    "wof:name":"SLC Meter Svc East Inc",
    "wof:placetype":"venue"
},
  "geometry": {"coordinates":[-74.92655000000001,39.81477],"type":"Point"}
}