{
  "type": "Feature",
  "properties": {
    "addr:full":"293 Eisenhower Pkwy Livingston NJ 07039",
    "addr:housenumber":"293",
    "addr:postcode":"07039",
    "addr:street":"Eisenhower Pkwy",
    "iso:country":"US",
    "sg:address":"293 Eisenhower Pkwy",
    "sg:city":"Livingston",
    "sg:classifiers":[
        {
            "category":"Banks & Credit Unions",
            "subcategory":"Investment Brokerage",
            "type":"Services"
        }
    ],
    "sg:phone":"+1 973 422 1110",
    "sg:postcode":"07039",
    "sg:province":"NJ",
    "sg:tags":[
        "consultant",
        "planning",
        "financial"
    ],
    "wof:name":"Puller Financial Svc",
    "wof:placetype":"venue"
},
  "geometry": {"coordinates":[-74.34140499999999,40.798795],"type":"Point"}
}