{
  "type": "Feature",
  "properties": {
    "addr:full":"22 Marlton Pike Cherry Hill NJ 08002",
    "addr:housenumber":"22",
    "addr:postcode":"08002",
    "addr:street":"Marlton Pike",
    "iso:country":"US",
    "sg:address":"22 Marlton Pike",
    "sg:city":"Cherry Hill",
    "sg:classifiers":[
        {
            "category":"Banks & Credit Unions",
            "subcategory":"Bank",
            "type":"Services"
        }
    ],
    "sg:phone":"+1 856 000 1111",
    "sg:postcode":"08002",
    "sg:province":"NJ",
    "wof:name":"Bank Of America",
    "wof:placetype":"venue"
},
  "geometry": {"coordinates":[-75.011844,39.914288],"type":"Point"}
}