{
  "type": "Feature",
  "properties": {
    "iso:country":"US",
    "sg:address":"12 Dorothy Dr",
    "sg:city":"Trenton",
    "sg:classifiers":[
        {
            "category":"Freight",
            "type":"Transportation"
        }
    ],
    "sg:phone":"+1 609 581 7654",
    "sg:postcode":"08610",
    "sg:province":"NJ",
    "sg:tags":[
        "operator",
        "local",
        "trucking"
    ],
    "wof:name":"Graham Trucking LLC",
    "wof:placetype":"venue"
},
  "geometry": {"coordinates":[-74.691658,40.192043],"type":"Point"}
}