{
  "type": "Feature",
  "properties": {
    "iso:country":"US",
    "sg:address":"7603 1st Ave",
    "sg:city":"North Bergen",
    "sg:classifiers":[
        {
            "category":"Professional",
            "subcategory":"Credit Reporting & Collection",
            "type":"Services"
        }
    ],
    "sg:phone":"+1 201 868 3768",
    "sg:postcode":"07047",
    "sg:province":"NJ",
    "sg:tags":[
        "agency"
    ],
    "wof:name":"Imperial Judgement Recovery",
    "wof:placetype":"venue"
},
  "geometry": {"coordinates":[-74.008287,40.801084],"type":"Point"}
}