{
  "type": "Feature",
  "properties": {
    "addr:full":"200 Luis Munoz Marin Blvd Jersey City NJ 07302",
    "addr:housenumber":"200",
    "addr:postcode":"07302",
    "addr:street":"Luis Munoz Marin Blvd",
    "iso:country":"US",
    "sg:address":"200 Luis Munoz Marin Blvd",
    "sg:city":"Jersey City",
    "sg:classifiers":[
        {
            "category":"Professional",
            "type":"Services"
        }
    ],
    "sg:phone":"+1 212 422 3967",
    "sg:postcode":"07302",
    "sg:province":"NJ",
    "sg:tags":[
        "establishment"
    ],
    "wof:name":"Maritime Power Corp",
    "wof:placetype":"venue"
},
  "geometry": {"coordinates":[-74.042508,40.716077],"type":"Point"}
}