{
  "type": "Feature",
  "properties": {
    "addr:full":"517 20th St Irvington NJ 07111",
    "addr:housenumber":"517",
    "addr:postcode":"07111",
    "addr:street":"20Th St",
    "iso:country":"US",
    "sg:address":"517 20th St",
    "sg:city":"Irvington",
    "sg:classifiers":[
        {
            "category":"Retail",
            "subcategory":"Auto Repair",
            "type":"Services"
        }
    ],
    "sg:phone":"+1 973 371 6900",
    "sg:postcode":"07111",
    "sg:province":"NJ",
    "sg:tags":[
        "repairing",
        "automobile"
    ],
    "wof:name":"Phil's Service Station",
    "wof:placetype":"venue"
},
  "geometry": {"coordinates":[-74.211461,40.737643],"type":"Point"}
}