{
  "type": "Feature",
  "properties": {
    "addr:full":"1120 Central Ave Ocean City NJ 08226",
    "addr:housenumber":"1120",
    "addr:postcode":"08226",
    "addr:street":"Central Ave",
    "iso:country":"US",
    "sg:address":"1120 Central Ave",
    "sg:city":"Ocean City",
    "sg:classifiers":[
        {
            "category":"Travel",
            "subcategory":"Hotels & Motels",
            "type":"Entertainment"
        }
    ],
    "sg:phone":"+1 609 399 0756",
    "sg:postcode":"08226",
    "sg:province":"NJ",
    "wof:name":"Georgian Hotel",
    "wof:placetype":"venue"
},
  "geometry": {"coordinates":[-74.579761,39.27532],"type":"Point"}
}