{
  "type": "Feature",
  "properties": {
    "iso:country":"US",
    "sg:address":"22 Mount Laurel Rd",
    "sg:city":"Mt Laurel",
    "sg:classifiers":[
        {
            "category":"Wholesale",
            "subcategory":"Groceries",
            "type":"Manufacturing & Wholesale Goods"
        }
    ],
    "sg:phone":"+1 856 235 0887",
    "sg:postcode":"08054",
    "sg:province":"NJ",
    "sg:tags":[
        "food",
        "product"
    ],
    "wof:name":"George Weston Foods Inc",
    "wof:placetype":"venue"
},
  "geometry": {"coordinates":[-74.928029,39.959143],"type":"Point"}
}