{
  "type": "Feature",
  "properties": {
    "addr:full":"10 Centerton Rd Mount Laurel NJ 08054",
    "addr:postcode":"08054",
    "addr:street":"10 Centerton Rd",
    "iso:country":"US",
    "sg:address":"10 Centerton Rd",
    "sg:city":"Mount Laurel",
    "sg:classifiers":[
        {
            "category":"Restaurant",
            "type":"Food & Drink"
        }
    ],
    "sg:menulink":"http://www.allmenus.com/nj/mount-laurel/151857-baja-fresh-mexican-grill/menu/",
    "sg:phone":"+1 856 802 0892",
    "sg:postcode":"08054",
    "sg:province":"NJ",
    "sg:tags":[
        "mexican"
    ],
    "wof:name":"Baja Fresh Mexican Grill",
    "wof:placetype":"venue"
},
  "geometry": {"coordinates":[-74.873608,39.962833],"type":"Point"}
}