{
  "type": "Feature",
  "properties": {
    "iso:country":"US",
    "sg:address":"303 Park Pl",
    "sg:city":"Irvington",
    "sg:classifiers":[
        {
            "category":"Professional",
            "subcategory":"Business Services",
            "type":"Services"
        }
    ],
    "sg:phone":"+1 908 522 0606",
    "sg:postcode":"07111",
    "sg:province":"NJ",
    "sg:tags":[
        "motivational",
        "speaker"
    ],
    "wof:name":"Pro Athletes",
    "wof:placetype":"venue"
},
  "geometry": {"coordinates":[-74.24550499999999,40.715387],"type":"Point"}
}