{
  "type": "Feature",
  "properties": {
    "iso:country":"US",
    "sg:address":"1606 Essex St",
    "sg:city":"Rahway",
    "sg:classifiers":[
        {
            "category":"Wholesale",
            "subcategory":"Machinery & Supplies",
            "type":"Manufacturing & Wholesale Goods"
        }
    ],
    "sg:phone":"+1 732 574 0900",
    "sg:postcode":"07065",
    "sg:province":"NJ",
    "sg:tags":[
        "marking",
        "code",
        "dating",
        "system"
    ],
    "wof:name":"Carteret Coding Inc",
    "wof:placetype":"venue"
},
  "geometry": {"coordinates":[-74.27139099999999,40.607044],"type":"Point"}
}