{
  "type": "Feature",
  "properties": {
    "addr:full":"3800 N Mill Rd Vineland NJ 08360",
    "addr:housenumber":"3800",
    "addr:postcode":"08360",
    "addr:street":"N Mill Rd",
    "iso:country":"US",
    "sg:address":"3800 N Mill Rd",
    "sg:city":"Vineland",
    "sg:classifiers":[
        {
            "category":"Manufacturing",
            "subcategory":"Chemicals & Compounds",
            "type":"Manufacturing & Wholesale Goods"
        }
    ],
    "sg:phone":"+1 856 794 9292",
    "sg:postcode":"08360",
    "sg:province":"NJ",
    "sg:tags":[
        "pharmaceutical",
        "cane",
        "mfg",
        "sugar",
        "preparation",
        "refining"
    ],
    "wof:name":"Hansen CHR Inc",
    "wof:placetype":"venue"
},
  "geometry": {"coordinates":[-75.058065,39.543057],"type":"Point"}
}