{
  "type": "Feature",
  "properties": {
    "addr:full":"608 Newman Springs Rd Lincroft NJ 07738",
    "addr:housenumber":"608",
    "addr:postcode":"07738",
    "addr:street":"Newman Springs Rd",
    "iso:country":"US",
    "sg:address":"608 Newman Springs Rd",
    "sg:city":"Lincroft",
    "sg:classifiers":[
        {
            "category":"Restaurant",
            "type":"Food & Drink"
        }
    ],
    "sg:menulink":"http://www.allmenus.com/nj/middletown/194686-mcdonalds/menu/",
    "sg:phone":"+1 732 936 0870",
    "sg:postcode":"07738",
    "sg:province":"NJ",
    "sg:tags":[
        "burger",
        "american"
    ],
    "wof:name":"McDonald's",
    "wof:placetype":"venue"
},
  "geometry": {"coordinates":[-74.11731399999999,40.331625],"type":"Point"}
}