{
  "type": "Feature",
  "properties": {
    "addr:full":"132 Westfield Ave Clark NJ 07066",
    "addr:housenumber":"132",
    "addr:postcode":"07066",
    "addr:street":"Westfield Ave",
    "iso:country":"US",
    "sg:address":"132 Westfield Ave",
    "sg:city":"Clark",
    "sg:classifiers":[
        {
            "category":"Banks & Credit Unions",
            "subcategory":"Bank",
            "type":"Services"
        }
    ],
    "sg:phone":"+1 732 340 9111",
    "sg:postcode":"07066",
    "sg:province":"NJ",
    "sg:tags":[
        "financing"
    ],
    "wof:name":"Liberty Funding",
    "wof:placetype":"venue"
},
  "geometry": {"coordinates":[-74.300528,40.620885],"type":"Point"}
}