{
  "type": "Feature",
  "properties": {
    "addr:full":"3223 Dell Ave North Bergen NJ 07047",
    "addr:housenumber":"3223",
    "addr:postcode":"07047",
    "addr:street":"Dell Ave",
    "iso:country":"US",
    "sg:address":"3223 Dell Ave",
    "sg:city":"North Bergen",
    "sg:classifiers":[
        {
            "category":"Professional",
            "subcategory":"Business Services",
            "type":"Services"
        }
    ],
    "sg:phone":"+1 201 330 1111",
    "sg:postcode":"07047",
    "sg:province":"NJ",
    "sg:tags":[
        "record",
        "document"
    ],
    "wof:name":"Intec Management Systems Corp",
    "wof:placetype":"venue"
},
  "geometry": {"coordinates":[-74.039841,40.778342],"type":"Point"}
}