{
  "type": "Feature",
  "properties": {
    "iso:country":"US",
    "sg:address":"33 Wilson Dr",
    "sg:city":"Sparta",
    "sg:classifiers":[
        {
            "category":"Manufacturing",
            "subcategory":"Printing",
            "type":"Manufacturing & Wholesale Goods"
        }
    ],
    "sg:phone":"+1 973 300 0890",
    "sg:postcode":"07871",
    "sg:province":"NJ",
    "sg:tags":[
        "newspaper"
    ],
    "wof:name":"Sparta Independent Advertiser",
    "wof:placetype":"venue"
},
  "geometry": {"coordinates":[-74.669237,41.073128],"type":"Point"}
}