{
  "type": "Feature",
  "properties": {
    "addr:full":"18 Redneck Ave Ste 5 Little Ferry NJ 07643",
    "addr:housenumber":"18",
    "addr:postcode":"07643",
    "addr:street":"Redneck Ave Ste 5 Little Ferry",
    "iso:country":"US",
    "sg:address":"18 Redneck Ave Ste 5",
    "sg:city":"Little Ferry",
    "sg:classifiers":[
        {
            "category":"Restaurant",
            "type":"Food & Drink"
        }
    ],
    "sg:phone":"+1 201 440 6007",
    "sg:postcode":"07643",
    "sg:province":"NJ",
    "sg:tags":[
        "pizza"
    ],
    "wof:name":"C & J Pizza Box",
    "wof:placetype":"venue"
},
  "geometry": {"coordinates":[-74.044601,40.851299],"type":"Point"}
}