{
  "type": "Feature",
  "properties": {
    "addr:full":"308 Ridge Rd Dayton NJ 08810",
    "addr:housenumber":"308",
    "addr:postcode":"08810",
    "addr:street":"Ridge Rd",
    "iso:country":"US",
    "sg:address":"308 Ridge Rd",
    "sg:city":"Dayton",
    "sg:classifiers":[
        {
            "category":"Professional",
            "subcategory":"Engineering",
            "type":"Services"
        },
        {
            "category":"Home & Garden",
            "subcategory":"Building Materials",
            "type":"Retail Goods"
        },
        {
            "category":"Building & Trades",
            "subcategory":"Construction",
            "type":"Services"
        }
    ],
    "sg:phone":"+1 732 329 3784",
    "sg:postcode":"08810",
    "sg:province":"NJ",
    "sg:tags":[
        "system",
        "specialty",
        "heating",
        "contractor",
        "equipment",
        "air conditioning"
    ],
    "sg:website":"http://find.trane.com/tcs-dealer-412417?utm_source=YP&utm_medium=banner&utm_campaign=TL",
    "wof:name":"Carrano Air Contracting",
    "wof:placetype":"venue"
},
  "geometry": {"coordinates":[-74.49472799999999,40.372827],"type":"Point"}
}