{
  "type": "Feature",
  "properties": {
    "iso:country":"US",
    "sg:address":"33 W 2nd St",
    "sg:city":"Moorestown",
    "sg:classifiers":[
        {
            "category":"Professional",
            "subcategory":"Lawyer & Legal Services",
            "type":"Services"
        }
    ],
    "sg:phone":"+1 856 727 5155",
    "sg:postcode":"08057",
    "sg:province":"NJ",
    "wof:name":"Karen Olejarz",
    "wof:placetype":"venue"
},
  "geometry": {"coordinates":[-74.948679,39.964539],"type":"Point"}
}