{
  "type": "Feature",
  "properties": {
    "iso:country":"US",
    "sg:address":"50 Franklin Ave",
    "sg:city":"Franklin",
    "sg:classifiers":[
        {
            "category":"Taxi",
            "type":"Transportation"
        }
    ],
    "sg:phone":"+1 973 697 9687",
    "sg:postcode":"07416",
    "sg:province":"NJ",
    "sg:tags":[
        "taxicab"
    ],
    "wof:name":"Anytime Taxi",
    "wof:placetype":"venue"
},
  "geometry": {"coordinates":[-74.59096599999999,41.114442],"type":"Point"}
}