{
  "type": "Feature",
  "properties": {
    "addr:full":"175 Manhattan Ave Jersey City NJ 07307",
    "addr:housenumber":"175",
    "addr:postcode":"07307",
    "addr:street":"Manhattan Ave",
    "iso:country":"US",
    "sg:address":"175 Manhattan Ave",
    "sg:city":"Jersey City",
    "sg:classifiers":[
        {
            "category":"Shopping",
            "subcategory":"Jewelry",
            "type":"Retail Goods"
        }
    ],
    "sg:phone":"+1 201 659 6264",
    "sg:postcode":"07307",
    "sg:province":"NJ",
    "sg:tags":[
        "designer"
    ],
    "wof:name":"Zavian Designs",
    "wof:placetype":"venue"
},
  "geometry": {"coordinates":[-74.057233,40.744947],"type":"Point"}
}