{
  "type": "Feature",
  "properties": {
    "addr:full":"570 Commerce Blvd Carlstadt NJ 07072",
    "addr:housenumber":"570",
    "addr:postcode":"07072",
    "addr:street":"Commerce Blvd",
    "iso:country":"US",
    "sg:address":"570 Commerce Blvd",
    "sg:city":"Carlstadt",
    "sg:classifiers":[
        {
            "category":"Freight",
            "type":"Transportation"
        }
    ],
    "sg:phone":"+1 201 507 0155",
    "sg:postcode":"07072",
    "sg:province":"NJ",
    "sg:tags":[
        "clothing",
        "general"
    ],
    "wof:name":"Maggy London International",
    "wof:placetype":"venue"
},
  "geometry": {"coordinates":[-74.04750300000001,40.827315],"type":"Point"}
}