{
  "type": "Feature",
  "properties": {
    "iso:country":"US",
    "sg:address":"1248 Sussex Tpke",
    "sg:city":"Randolph",
    "sg:classifiers":[
        {
            "category":"Professional",
            "subcategory":"Management & Consulting",
            "type":"Services"
        }
    ],
    "sg:phone":"+1 973 895 3700",
    "sg:postcode":"07869",
    "sg:province":"NJ",
    "sg:tags":[
        "personnel",
        "consultant"
    ],
    "wof:name":"Integral Staffing",
    "wof:placetype":"venue"
},
  "geometry": {"coordinates":[-74.582493,40.827074],"type":"Point"}
}