{
  "type": "Feature",
  "properties": {
    "addr:full":"209 Newton Sparta Ave Newton NJ 07860",
    "addr:housenumber":"209",
    "addr:postcode":"07860",
    "addr:street":"Newton Sparta Ave",
    "iso:country":"US",
    "sg:address":"209 Newton Sparta Ave",
    "sg:city":"Newton",
    "sg:classifiers":[
        {
            "category":"Professional",
            "subcategory":"Computer Services",
            "type":"Services"
        }
    ],
    "sg:phone":"+1 973 579 5724",
    "sg:postcode":"07860",
    "sg:province":"NJ",
    "sg:tags":[
        "related"
    ],
    "wof:name":"Betan Co",
    "wof:placetype":"venue"
},
  "geometry": {"coordinates":[-74.705282,41.038543],"type":"Point"}
}