{
  "type": "Feature",
  "properties": {
    "addr:full":"500 Park Ave Paterson NJ 07504",
    "addr:housenumber":"500",
    "addr:postcode":"07504",
    "addr:street":"Park Ave",
    "iso:country":"US",
    "sg:address":"500 Park Ave",
    "sg:city":"Paterson",
    "sg:classifiers":[
        {
            "category":"Real Estate",
            "subcategory":"Real Estate Agent",
            "type":"Services"
        }
    ],
    "sg:phone":"+1 973 278 0097",
    "sg:postcode":"07504",
    "sg:province":"NJ",
    "wof:name":"Gilmore Wright Realty",
    "wof:placetype":"venue"
},
  "geometry": {"coordinates":[-74.144445,40.913552],"type":"Point"}
}