{
  "type": "Feature",
  "properties": {
    "iso:country":"US",
    "sg:address":"216 Mountain Ave",
    "sg:city":"Caldwell",
    "sg:classifiers":[
        {
            "category":"Farming",
            "subcategory":"Farm",
            "type":"Manufacturing & Wholesale Goods"
        }
    ],
    "sg:phone":"+1 973 226 3289",
    "sg:postcode":"07006",
    "sg:province":"NJ",
    "sg:tags":[
        "supply"
    ],
    "wof:name":"Matarazzo's Farm",
    "wof:placetype":"venue"
},
  "geometry": {"coordinates":[-74.258899,40.853876],"type":"Point"}
}