{
  "type": "Feature",
  "properties": {
    "addr:full":"24 Outwater Ln Garfield NJ 07026",
    "addr:housenumber":"24",
    "addr:postcode":"07026",
    "addr:street":"Outwater Ln",
    "iso:country":"US",
    "sg:address":"24 Outwater Ln",
    "sg:city":"Garfield",
    "sg:classifiers":[
        {
            "category":"Professional",
            "type":"Services"
        }
    ],
    "sg:phone":"+1   ",
    "sg:postcode":"07026",
    "sg:province":"NJ",
    "wof:name":"Michael Musa Obregon PC",
    "wof:placetype":"venue"
},
  "geometry": {"coordinates":[-74.118838,40.879921],"type":"Point"}
}