{
  "type": "Feature",
  "properties": {
    "addr:full":"443 Westfield Ave E Roselle Park NJ 07204",
    "addr:housenumber":"443",
    "addr:postcode":"07204",
    "addr:street":"Westfield Ave E",
    "iso:country":"US",
    "sg:address":"443 Westfield Ave E",
    "sg:city":"Roselle Park",
    "sg:classifiers":[
        {
            "category":"Professional",
            "subcategory":"Advertising",
            "type":"Services"
        }
    ],
    "sg:phone":"+1 908 272 8145",
    "sg:postcode":"07204",
    "sg:province":"NJ",
    "sg:tags":[
        "designer",
        "display",
        "producer"
    ],
    "wof:name":"Fixturecraft Corp",
    "wof:placetype":"venue"
},
  "geometry": {"coordinates":[-74.24731300000001,40.663987],"type":"Point"}
}