{
  "type": "Feature",
  "properties": {
    "addr:full":"556 W Merchant St Audubon NJ 08106",
    "addr:housenumber":"556",
    "addr:postcode":"08106",
    "addr:street":"W Merchant St",
    "iso:country":"US",
    "sg:address":"556 W Merchant St",
    "sg:city":"Audubon",
    "sg:classifiers":[
        {
            "category":"Building & Trades",
            "subcategory":"Construction",
            "type":"Services"
        }
    ],
    "sg:phone":"+1 856 547 9300",
    "sg:postcode":"08106",
    "sg:province":"NJ",
    "sg:tags":[
        "painter"
    ],
    "wof:name":"Felli Painting",
    "wof:placetype":"venue"
},
  "geometry": {"coordinates":[-75.08306,39.889237],"type":"Point"}
}