{
  "type": "Feature",
  "properties": {
    "addr:full":"228 E Blackwell St Dover NJ 07801",
    "addr:housenumber":"228",
    "addr:postcode":"07801",
    "addr:street":"E Blackwell St",
    "iso:country":"US",
    "sg:address":"228 E Blackwell St",
    "sg:city":"Dover",
    "sg:classifiers":[
        {
            "category":"Retail",
            "subcategory":"Auto Repair",
            "type":"Services"
        }
    ],
    "sg:phone":"+1 973 366 9461",
    "sg:postcode":"07801",
    "sg:province":"NJ",
    "sg:tags":[
        "body",
        "automobile",
        "painting"
    ],
    "wof:name":"Classic Car Carriers",
    "wof:placetype":"venue"
},
  "geometry": {"coordinates":[-74.54758699999999,40.885262],"type":"Point"}
}