{
  "type": "Feature",
  "properties": {
    "iso:country":"US",
    "sg:address":"64 Saddle Shop Rd",
    "sg:city":"Ringoes",
    "sg:classifiers":[
        {
            "category":"Building & Trades",
            "subcategory":"Construction",
            "type":"Services"
        }
    ],
    "sg:phone":"+1 908 806 6880",
    "sg:postcode":"08551",
    "sg:province":"NJ",
    "sg:tags":[
        "hanging",
        "painter",
        "contractor"
    ],
    "wof:name":"Sourland Painting LLC",
    "wof:placetype":"venue"
},
  "geometry": {"coordinates":[-74.81561499999999,40.428076],"type":"Point"}
}