{
  "type": "Feature",
  "properties": {
    "iso:country":"US",
    "sg:address":"315 Pitcairn Rd",
    "sg:city":"Brick",
    "sg:classifiers":[
        {
            "category":"Building & Trades",
            "subcategory":"Landscaping Services",
            "type":"Services"
        }
    ],
    "sg:phone":"+1 732 477 0065",
    "sg:postcode":"08723",
    "sg:province":"NJ",
    "sg:tags":[
        "landscape",
        "contractor"
    ],
    "wof:name":"Jack's Landscaping & Lawn Care",
    "wof:placetype":"venue"
},
  "geometry": {"coordinates":[-74.11273300000001,40.040011],"type":"Point"}
}