{
  "type": "Feature",
  "properties": {
    "addr:full":"209 E 2nd St Bound Brook NJ 08805",
    "addr:housenumber":"209",
    "addr:postcode":"08805",
    "addr:street":"E 2Nd St",
    "iso:country":"US",
    "sg:address":"209 E 2nd St",
    "sg:city":"Bound Brook",
    "sg:classifiers":[
        {
            "category":"Retail",
            "subcategory":"Auto Repair",
            "type":"Services"
        }
    ],
    "sg:phone":"+1 732 356 1760",
    "sg:postcode":"08805",
    "sg:province":"NJ",
    "sg:tags":[
        "general"
    ],
    "wof:name":"Mohrings Auto Maintenance",
    "wof:placetype":"venue"
},
  "geometry": {"coordinates":[-74.530896,40.562641],"type":"Point"}
}