{
  "type": "Feature",
  "properties": {
    "iso:country":"US",
    "sg:address":"1777 Hamburg Tpke",
    "sg:city":"Wayne",
    "sg:classifiers":[
        {
            "category":"Health Services",
            "subcategory":"Doctor",
            "type":"Services"
        }
    ],
    "sg:phone":"+1 973 831 7455",
    "sg:postcode":"07470",
    "sg:province":"NJ",
    "sg:tags":[
        "physician",
        "surgeon"
    ],
    "wof:name":"Cardiology Associates Of N Nj",
    "wof:placetype":"venue"
},
  "geometry": {"coordinates":[-74.262812,40.971627],"type":"Point"}
}