{
  "type": "Feature",
  "properties": {
    "addr:full":"20 Wickapecko Dr Asbury Park NJ 07712",
    "addr:housenumber":"20",
    "addr:postcode":"07712",
    "addr:street":"Wickapecko Dr Asbury Park",
    "iso:country":"US",
    "sg:address":"20 Wickapecko Dr",
    "sg:city":"Asbury Park",
    "sg:classifiers":[
        {
            "category":"Professional",
            "type":"Services"
        }
    ],
    "sg:phone":"+1   ",
    "sg:postcode":"07712",
    "sg:province":"NJ",
    "wof:name":"Wilfred J McAloon",
    "wof:placetype":"venue"
},
  "geometry": {"coordinates":[-74.023985,40.23562],"type":"Point"}
}