{
  "type": "Feature",
  "properties": {
    "addr:full":"150 Mount Laurel Rd Mt Laurel NJ 08054",
    "addr:housenumber":"150",
    "addr:postcode":"08054",
    "addr:street":"Mount Laurel Rd",
    "iso:country":"US",
    "sg:address":"150 Mount Laurel Rd",
    "sg:city":"Mt Laurel",
    "sg:classifiers":[
        {
            "category":"Professional",
            "type":"Services"
        }
    ],
    "sg:phone":"+1 856 231 8283",
    "sg:postcode":"08054",
    "sg:province":"NJ",
    "sg:tags":[
        "establishment"
    ],
    "wof:name":"Colliers L & A",
    "wof:placetype":"venue"
},
  "geometry": {"coordinates":[-74.925687,39.957608],"type":"Point"}
}