{
  "type": "Feature",
  "properties": {
    "iso:country":"US",
    "sg:address":"180 Ashland Ave",
    "sg:city":"Bloomfield",
    "sg:classifiers":[
        {
            "category":"Real Estate",
            "subcategory":"Real Estate Operator",
            "type":"Services"
        }
    ],
    "sg:phone":"+1 973 743 7006",
    "sg:postcode":"07003",
    "sg:province":"NJ",
    "sg:tags":[
        "apartment"
    ],
    "wof:name":"Devon Court Apartments",
    "wof:placetype":"venue"
},
  "geometry": {"coordinates":[-74.20590199999999,40.7911],"type":"Point"}
}