{
  "type": "Feature",
  "properties": {
    "addr:full":"393 Springfield Ave Summit NJ 07901",
    "addr:housenumber":"393",
    "addr:postcode":"07901",
    "addr:street":"Springfield Ave",
    "iso:country":"US",
    "sg:address":"393 Springfield Ave",
    "sg:city":"Summit",
    "sg:classifiers":[
        {
            "category":"Freight",
            "type":"Transportation"
        }
    ],
    "sg:phone":"+1 908 273 4834",
    "sg:postcode":"07901",
    "sg:province":"NJ",
    "sg:tags":[
        "agent"
    ],
    "wof:name":"J B A Barge Line",
    "wof:placetype":"venue"
},
  "geometry": {"coordinates":[-74.35798,40.718113],"type":"Point"}
}