{
  "type": "Feature",
  "properties": {
    "iso:country":"US",
    "sg:address":"909 Main St",
    "sg:city":"Boonton",
    "sg:classifiers":[
        {
            "category":"Restaurant",
            "type":"Food & Drink"
        }
    ],
    "sg:phone":"+1 973 335 4897",
    "sg:postcode":"07005",
    "sg:province":"NJ",
    "sg:tags":[
        "diner"
    ],
    "wof:name":"Boonton Diner LLC",
    "wof:placetype":"venue"
},
  "geometry": {"coordinates":[-74.414007,40.906612],"type":"Point"}
}