{
  "type": "Feature",
  "properties": {
    "iso:country":"US",
    "sg:address":"90 Knickerbocker Rd",
    "sg:city":"Dumont",
    "sg:classifiers":[
        {
            "category":"Professional",
            "type":"Services"
        }
    ],
    "sg:phone":"+1   ",
    "sg:postcode":"07628",
    "sg:province":"NJ",
    "wof:name":"Nick Mennona",
    "wof:placetype":"venue"
},
  "geometry": {"coordinates":[-73.976596,40.943155],"type":"Point"}
}