{
  "type": "Feature",
  "properties": {
    "iso:country":"US",
    "sg:address":"330 Market St",
    "sg:city":"Camden",
    "sg:classifiers":[
        {
            "category":"Professional",
            "subcategory":"Lawyer & Legal Services",
            "type":"Services"
        }
    ],
    "sg:phone":"+1 856 428 7717",
    "sg:postcode":"08102",
    "sg:province":"NJ",
    "sg:tags":[
        "attorney"
    ],
    "wof:name":"Palmer Biezup & Henderson",
    "wof:placetype":"venue"
},
  "geometry": {"coordinates":[-75.12274499999999,39.94595],"type":"Point"}
}