{
  "type": "Feature",
  "properties": {
    "iso:country":"US",
    "sg:address":"970 US Hwy 22",
    "sg:city":"Bridgewater",
    "sg:classifiers":[
        {
            "category":"Restaurant",
            "type":"Food & Drink"
        }
    ],
    "sg:phone":"+1   ",
    "sg:postcode":"08807",
    "sg:province":"NJ",
    "sg:tags":[
        "eating"
    ],
    "sg:website":"www.lonestar.com",
    "wof:name":"Lone Star Steakhouse & Saloon",
    "wof:placetype":"venue"
},
  "geometry": {"coordinates":[-74.60701400000001,40.580379],"type":"Point"}
}