{
  "type": "Feature",
  "properties": {
    "addr:full":"29 State Rte 12 Flemington NJ 08822",
    "addr:housenumber":"29",
    "addr:postcode":"08822",
    "addr:street":"State Rte 12",
    "iso:country":"US",
    "sg:address":"29 State Rte 12",
    "sg:city":"Flemington",
    "sg:classifiers":[
        {
            "category":"Retail",
            "subcategory":"Auto Rental",
            "type":"Services"
        }
    ],
    "sg:phone":"+1   ",
    "sg:postcode":"08822",
    "sg:province":"NJ",
    "sg:tags":[
        "equipment",
        "car",
        "passenger"
    ],
    "wof:name":"Avis Rent A Car",
    "wof:placetype":"venue"
},
  "geometry": {"coordinates":[-74.861465,40.501734],"type":"Point"}
}