{
  "type": "Feature",
  "properties": {
    "addr:full":"2495 N Route 9 Ocean View NJ 08230",
    "addr:housenumber":"2495",
    "addr:postcode":"08230",
    "addr:street":"N Route 9",
    "iso:country":"US",
    "sg:address":"2495 N Route 9",
    "sg:city":"Ocean View",
    "sg:classifiers":[
        {
            "category":"Restaurant",
            "type":"Food & Drink"
        }
    ],
    "sg:menulink":"http://www.allmenus.com/nj/dennis/146456-subway/menu/",
    "sg:phone":"+1 609 624 0099",
    "sg:postcode":"08230",
    "sg:province":"NJ",
    "sg:tags":[
        "american",
        "sandwich"
    ],
    "wof:name":"Subway",
    "wof:placetype":"venue"
},
  "geometry": {"coordinates":[-74.73327,39.176812],"type":"Point"}
}