{
  "type": "Feature",
  "properties": {
    "iso:country":"US",
    "sg:address":"721 Mantoloking Rd",
    "sg:city":"Brick",
    "sg:classifiers":[
        {
            "category":"Shopping",
            "subcategory":"Florist",
            "type":"Retail Goods"
        }
    ],
    "sg:phone":"+1   ",
    "sg:postcode":"08723",
    "sg:province":"NJ",
    "sg:tags":[
        "flower",
        "provide",
        "produce",
        "nursery",
        "landscape",
        "stock"
    ],
    "wof:name":"Colony Farm Market & Grdn Ctr",
    "wof:placetype":"venue"
},
  "geometry": {"coordinates":[-74.120131,40.049629],"type":"Point"}
}