{
  "type": "Feature",
  "properties": {
    "iso:country":"US",
    "sg:address":"1600 New York Ave",
    "sg:city":"Union City",
    "sg:classifiers":[
        {
            "category":"Government",
            "subcategory":"Fire Station",
            "type":"Public Place"
        }
    ],
    "sg:phone":"+1 201 348 5817",
    "sg:postcode":"07087",
    "sg:province":"NJ",
    "sg:tags":[
        "department"
    ],
    "wof:name":"North Hudson Regl Fire &Rescue",
    "wof:placetype":"venue"
},
  "geometry": {"coordinates":[-74.034195,40.76244],"type":"Point"}
}