{
  "type": "Feature",
  "properties": {
    "addr:full":"8 S Warren St Trenton NJ 08608",
    "addr:housenumber":"8",
    "addr:postcode":"08608",
    "addr:street":"S Warren St",
    "iso:country":"US",
    "sg:address":"8 S Warren St",
    "sg:city":"Trenton",
    "sg:classifiers":[
        {
            "category":"Restaurant",
            "type":"Food & Drink"
        }
    ],
    "sg:phone":"+1 609 393 5707",
    "sg:postcode":"08608",
    "sg:province":"NJ",
    "sg:tags":[
        "eating"
    ],
    "wof:name":"Columbus International Pizza I",
    "wof:placetype":"venue"
},
  "geometry": {"coordinates":[-74.765964,40.219421],"type":"Point"}
}