{
  "type": "Feature",
  "properties": {
    "iso:country":"US",
    "sg:address":"216 Baltimore Ave",
    "sg:city":"Bridgeton",
    "sg:classifiers":[
        {
            "category":"Personal",
            "subcategory":"Beauty Salon",
            "type":"Services"
        }
    ],
    "sg:phone":"+1 856 451 5595",
    "sg:postcode":"08302",
    "sg:province":"NJ",
    "sg:tags":[
        "shop"
    ],
    "wof:name":"A Gentle Touch Salon",
    "wof:placetype":"venue"
},
  "geometry": {"coordinates":[-75.22394799999999,39.413052],"type":"Point"}
}