{
  "type": "Feature",
  "properties": {
    "iso:country":"US",
    "sg:address":"4 Byrne Ln",
    "sg:city":"Tenafly",
    "sg:classifiers":[
        {
            "category":"Professional",
            "type":"Services"
        }
    ],
    "sg:phone":"+1   ",
    "sg:postcode":"07670",
    "sg:province":"NJ",
    "wof:name":"S Winner LLC",
    "wof:placetype":"venue"
},
  "geometry": {"coordinates":[-73.96320799999999,40.916286],"type":"Point"}
}