{
  "type": "Feature",
  "properties": {
    "iso:country":"US",
    "sg:address":"101 Yorktown Ct",
    "sg:city":"Medford",
    "sg:classifiers":[
        {
            "category":"Real Estate",
            "subcategory":"Real Estate Agent",
            "type":"Services"
        }
    ],
    "sg:phone":"+1   ",
    "sg:postcode":"08055",
    "sg:province":"NJ",
    "wof:name":"Ware Appraisal Svcs",
    "wof:placetype":"venue"
},
  "geometry": {"coordinates":[-74.802055,39.83173],"type":"Point"}
}