{
  "type": "Feature",
  "properties": {
    "addr:full":"243 Chestnut St Newark NJ 07105",
    "addr:housenumber":"243",
    "addr:postcode":"07105",
    "addr:street":"Chestnut St",
    "iso:country":"US",
    "sg:address":"243 Chestnut St",
    "sg:city":"Newark",
    "sg:classifiers":[
        {
            "category":"Banks & Credit Unions",
            "subcategory":"Bank",
            "type":"Services"
        }
    ],
    "sg:phone":"+1 973 817 7455",
    "sg:postcode":"07105",
    "sg:province":"NJ",
    "wof:name":"Independence Community Bank",
    "wof:placetype":"venue"
},
  "geometry": {"coordinates":[-74.16549999999999,40.723142],"type":"Point"}
}