{
  "type": "Feature",
  "properties": {
    "addr:full":"2600 Tilton Rd Egg Harbor Twp NJ 08234",
    "addr:housenumber":"2600",
    "addr:postcode":"08234",
    "addr:street":"Tilton Rd",
    "iso:country":"US",
    "sg:address":"2600 Tilton Rd",
    "sg:city":"Egg Harbor Twp",
    "sg:classifiers":[
        {
            "category":"Building & Trades",
            "subcategory":"Plumbing",
            "type":"Services"
        }
    ],
    "sg:phone":"+1 609 646 1745",
    "sg:postcode":"08234",
    "sg:province":"NJ",
    "sg:tags":[
        "plumbing",
        "air",
        "heating",
        "contractor"
    ],
    "wof:name":"United Heating & Sheet Metal",
    "wof:placetype":"venue"
},
  "geometry": {"coordinates":[-74.567078,39.412842],"type":"Point"}
}