{
  "type": "Feature",
  "properties": {
    "addr:full":"390 S Van Brunt St Englewood NJ 07631",
    "addr:housenumber":"390",
    "addr:postcode":"07631",
    "addr:street":"S Van Brunt St",
    "iso:country":"US",
    "sg:address":"390 S Van Brunt St",
    "sg:city":"Englewood",
    "sg:classifiers":[
        {
            "category":"Freight",
            "type":"Transportation"
        }
    ],
    "sg:phone":"+1 201 569 6050",
    "sg:postcode":"07631",
    "sg:province":"NJ",
    "sg:tags":[
        "commercial",
        "storage"
    ],
    "wof:name":"Lackland Self Storage",
    "wof:placetype":"venue"
},
  "geometry": {"coordinates":[-73.985517,40.883975],"type":"Point"}
}