{
  "type": "Feature",
  "properties": {
    "iso:country":"US",
    "sg:address":"38 Valley Ct",
    "sg:city":"Secaucus",
    "sg:classifiers":[
        {
            "category":"Wholesale",
            "subcategory":"Drugs",
            "type":"Manufacturing & Wholesale Goods"
        }
    ],
    "sg:phone":"+1 201 319 0329",
    "sg:postcode":"07094",
    "sg:province":"NJ",
    "sg:tags":[
        "perfume"
    ],
    "wof:name":"Beauty Perfumes",
    "wof:placetype":"venue"
},
  "geometry": {"coordinates":[-74.05453799999999,40.794124],"type":"Point"}
}