{
  "type": "Feature",
  "properties": {
    "addr:full":"343 Murray Hill Pkwy East Rutherford NJ 07073",
    "addr:housenumber":"343",
    "addr:postcode":"07073",
    "addr:street":"Murray Hill Pkwy",
    "iso:country":"US",
    "sg:address":"343 Murray Hill Pkwy",
    "sg:city":"East Rutherford",
    "sg:classifiers":[
        {
            "category":"Manufacturing",
            "subcategory":"Chemicals & Compounds",
            "type":"Manufacturing & Wholesale Goods"
        }
    ],
    "sg:phone":"+1 201 933 7100",
    "sg:postcode":"07073",
    "sg:province":"NJ",
    "sg:tags":[
        "news",
        "mfg",
        "ink"
    ],
    "wof:name":"Sun Chemical Corporation",
    "wof:placetype":"venue"
},
  "geometry": {"coordinates":[-74.09168099999999,40.820259],"type":"Point"}
}