{
  "type": "Feature",
  "properties": {
    "addr:full":"1410 Springfield Ave Irvington NJ 07111",
    "addr:housenumber":"1410",
    "addr:postcode":"07111",
    "addr:street":"Springfield Ave",
    "iso:country":"US",
    "sg:address":"1410 Springfield Ave",
    "sg:city":"Irvington",
    "sg:classifiers":[
        {
            "category":"Banks & Credit Unions",
            "subcategory":"Bank",
            "type":"Services"
        }
    ],
    "sg:phone":"+1   ",
    "sg:postcode":"07111",
    "sg:province":"NJ",
    "sg:tags":[
        "depository",
        "banking"
    ],
    "wof:name":"Lider Express Inc",
    "wof:placetype":"venue"
},
  "geometry": {"coordinates":[-74.248535,40.723723],"type":"Point"}
}