{
  "type": "Feature",
  "properties": {
    "iso:country":"US",
    "sg:address":"326 W Main St",
    "sg:city":"Freehold",
    "sg:classifiers":[
        {
            "category":"Personal",
            "subcategory":"Beauty Salon",
            "type":"Services"
        }
    ],
    "sg:phone":"+1 732 308 1773",
    "sg:postcode":"07728",
    "sg:province":"NJ",
    "sg:tags":[
        "manicuring"
    ],
    "wof:name":"Regal Nails",
    "wof:placetype":"venue"
},
  "geometry": {"coordinates":[-74.30007500000001,40.243127],"type":"Point"}
}