{
  "type": "Feature",
  "properties": {
    "addr:full":"54 Bank St Medford NJ 08055",
    "addr:housenumber":"54",
    "addr:postcode":"08055",
    "addr:street":"Bank St",
    "iso:country":"US",
    "sg:address":"54 Bank St",
    "sg:city":"Medford",
    "sg:classifiers":[
        {
            "category":"Professional",
            "type":"Services"
        }
    ],
    "sg:phone":"+1   ",
    "sg:postcode":"08055",
    "sg:province":"NJ",
    "wof:name":"Randy Ruschak",
    "wof:placetype":"venue"
},
  "geometry": {"coordinates":[-74.820509,39.899386],"type":"Point"}
}