{
  "type": "Feature",
  "properties": {
    "addr:full":"676 Edgewater Ave Ridgefield NJ 07657",
    "addr:housenumber":"676",
    "addr:postcode":"07657",
    "addr:street":"Edgewater Ave",
    "iso:country":"US",
    "sg:address":"676 Edgewater Ave",
    "sg:city":"Ridgefield",
    "sg:classifiers":[
        {
            "category":"Wholesale",
            "subcategory":"Machinery & Supplies",
            "type":"Manufacturing & Wholesale Goods"
        }
    ],
    "sg:phone":"+1 201 840 7622",
    "sg:postcode":"07657",
    "sg:province":"NJ",
    "sg:tags":[
        "equipment",
        "establishment"
    ],
    "wof:name":"Pcpc Beauty Supply Wholesale",
    "wof:placetype":"venue"
},
  "geometry": {"coordinates":[-73.99854000000001,40.828945],"type":"Point"}
}