{
  "type": "Feature",
  "properties": {
    "iso:country":"US",
    "sg:address":"625 Lafayette Ave Ste 1",
    "sg:city":"Hawthorne",
    "sg:classifiers":[
        {
            "category":"Shopping",
            "subcategory":"Hobbies, Toys, & Games",
            "type":"Retail Goods"
        },
        {
            "category":"Shopping",
            "subcategory":"Jewelry",
            "type":"Retail Goods"
        },
        {
            "category":"Manufacturing",
            "subcategory":"Jewelry",
            "type":"Manufacturing & Wholesale Goods"
        }
    ],
    "sg:phone":"+1 973 304 0520",
    "sg:postcode":"07506",
    "sg:province":"NJ",
    "sg:tags":[
        "shop",
        "designer",
        "supply",
        "jeweler",
        "hobby",
        "model",
        "coin"
    ],
    "sg:website":"http://www.sgrarecoins.com",
    "wof:name":"S G Rare Coins Inc",
    "wof:placetype":"venue"
},
  "geometry": {"coordinates":[-74.155697,40.95969],"type":"Point"}
}