{
  "type": "Feature",
  "properties": {
    "iso:country":"US",
    "sg:address":"104 S Nashville Ave",
    "sg:city":"Ventnor City",
    "sg:classifiers":[
        {
            "category":"Health Services",
            "subcategory":"Doctor",
            "type":"Services"
        }
    ],
    "sg:phone":"+1 609 823 0387",
    "sg:postcode":"08406",
    "sg:province":"NJ",
    "sg:tags":[
        "medical"
    ],
    "wof:name":"J N Safer MD",
    "wof:placetype":"venue"
},
  "geometry": {"coordinates":[-74.46776,39.341861],"type":"Point"}
}