{
  "type": "Feature",
  "properties": {
    "iso:country":"US",
    "sg:address":"934 N 32nd St",
    "sg:city":"Camden",
    "sg:classifiers":[
        {
            "category":"Food & Beverages",
            "subcategory":"Specialty",
            "type":"Retail Goods"
        }
    ],
    "sg:phone":"+1   ",
    "sg:postcode":"08105",
    "sg:province":"NJ",
    "wof:name":"Todays Weight Loss Inc",
    "wof:placetype":"venue"
},
  "geometry": {"coordinates":[-75.085121,39.958628],"type":"Point"}
}