{
  "type": "Feature",
  "properties": {
    "addr:full":"74 Drift St New Brunswick NJ 08901",
    "addr:postcode":"08901",
    "addr:street":"Drift St",
    "iso:country":"US",
    "sg:address":"74 Drift St",
    "sg:city":"New Brunswick",
    "sg:classifiers":[
        {
            "category":"Organizations",
            "subcategory":"Religious Organization",
            "type":"Services"
        }
    ],
    "sg:phone":"+1 732 249 6803",
    "sg:postcode":"08901",
    "sg:province":"NJ",
    "wof:name":"Suydam St Reformed Church",
    "wof:placetype":"venue"
},
  "geometry": {"coordinates":[-74.450335,40.489828],"type":"Point"}
}