{
  "type": "Feature",
  "properties": {
    "addr:full":"78 Musiker Ave Randolph NJ 07869",
    "addr:housenumber":"78",
    "addr:postcode":"07869",
    "addr:street":"Musiker Ave",
    "iso:country":"US",
    "sg:address":"78 Musiker Ave",
    "sg:city":"Randolph",
    "sg:classifiers":[
        {
            "category":"Professional",
            "subcategory":"Management & Consulting",
            "type":"Services"
        }
    ],
    "sg:phone":"+1   ",
    "sg:postcode":"07869",
    "sg:province":"NJ",
    "sg:tags":[
        "engineering"
    ],
    "wof:name":"Extrusioneering International",
    "wof:placetype":"venue"
},
  "geometry": {"coordinates":[-74.559664,40.820307],"type":"Point"}
}