{
  "type": "Feature",
  "properties": {
    "iso:country":"US",
    "sg:address":"690 River Dr",
    "sg:city":"Elmwood Park",
    "sg:classifiers":[
        {
            "category":"Shopping",
            "subcategory":"Clothing, Apparel, & Fashions",
            "type":"Retail Goods"
        }
    ],
    "sg:phone":"+1   ",
    "sg:postcode":"07407",
    "sg:province":"NJ",
    "sg:tags":[
        "athletic",
        "boutique",
        "wear"
    ],
    "wof:name":"Infatuation Inc",
    "wof:placetype":"venue"
},
  "geometry": {"coordinates":[-74.12648900000001,40.89954],"type":"Point"}
}