{
  "type": "Feature",
  "properties": {
    "addr:full":"930 Ringwood Ave Haskell NJ 07420",
    "addr:housenumber":"930",
    "addr:postcode":"07420",
    "addr:street":"Ringwood Ave",
    "iso:country":"US",
    "sg:address":"930 Ringwood Ave",
    "sg:city":"Haskell",
    "sg:classifiers":[
        {
            "category":"Personal",
            "subcategory":"Barber",
            "type":"Services"
        }
    ],
    "sg:phone":"+1 973 835 5588",
    "sg:postcode":"07420",
    "sg:province":"NJ",
    "sg:tags":[
        "shop"
    ],
    "wof:name":"Johnnies Barber Shop",
    "wof:placetype":"venue"
},
  "geometry": {"coordinates":[-74.29448600000001,41.035719],"type":"Point"}
}