{
  "type": "Feature",
  "properties": {
    "addr:full":"324 Ringwood Ave Pompton Lakes NJ 07442",
    "addr:housenumber":"324",
    "addr:postcode":"07442",
    "addr:street":"Ringwood Ave",
    "iso:country":"US",
    "sg:address":"324 Ringwood Ave",
    "sg:city":"Pompton Lakes",
    "sg:classifiers":[
        {
            "category":"Building & Trades",
            "subcategory":"Construction",
            "type":"Services"
        }
    ],
    "sg:phone":"+1 973 835 7373",
    "sg:postcode":"07442",
    "sg:province":"NJ",
    "sg:tags":[
        "air",
        "heating",
        "conditioning/hvac"
    ],
    "sg:website":"onehourairpomptonlakes.com",
    "wof:name":"One Hour Air",
    "wof:placetype":"venue"
},
  "geometry": {"coordinates":[-74.295523,41.008097],"type":"Point"}
}