{
  "type": "Feature",
  "properties": {
    "addr:full":"4564 US Hwy 9 Howell NJ 07731",
    "addr:housenumber":"4564",
    "addr:postcode":"07731",
    "addr:street":"Us Hwy 9",
    "iso:country":"US",
    "sg:address":"4564 US Hwy 9",
    "sg:city":"Howell",
    "sg:classifiers":[
        {
            "category":"Food & Beverages",
            "subcategory":"Liquor & Beverages",
            "type":"Retail Goods"
        }
    ],
    "sg:phone":"+1   ",
    "sg:postcode":"07731",
    "sg:province":"NJ",
    "sg:tags":[
        "alcoholic"
    ],
    "wof:name":"Stooges Tavern & Liquors",
    "wof:placetype":"venue"
},
  "geometry": {"coordinates":[-74.22535999999999,40.140693],"type":"Point"}
}