{
  "type": "Feature",
  "properties": {
    "addr:full":"11 Palmetto Way North Brunswick NJ 08902",
    "addr:housenumber":"11",
    "addr:postcode":"08902",
    "addr:street":"Palmetto Way",
    "iso:country":"US",
    "sg:address":"11 Palmetto Way",
    "sg:city":"North Brunswick",
    "sg:classifiers":[
        {
            "category":"Real Estate",
            "subcategory":"Real Estate Agent",
            "type":"Services"
        }
    ],
    "sg:phone":"+1 732 398 2121",
    "sg:postcode":"08902",
    "sg:province":"NJ",
    "wof:name":"Atlantic Realty Dev Corp",
    "wof:placetype":"venue"
},
  "geometry": {"coordinates":[-74.49889899999999,40.427154],"type":"Point"}
}