{
  "type": "Feature",
  "properties": {
    "addr:full":"306 Lincoln Ave E Cranford NJ 07016",
    "addr:housenumber":"306",
    "addr:postcode":"07016",
    "addr:street":"Lincoln Ave E",
    "iso:country":"US",
    "sg:address":"306 Lincoln Ave E",
    "sg:city":"Cranford",
    "sg:classifiers":[
        {
            "category":"Professional",
            "subcategory":"Secretarial Services",
            "type":"Services"
        }
    ],
    "sg:phone":"+1   ",
    "sg:postcode":"07016",
    "sg:province":"NJ",
    "sg:tags":[
        "writing"
    ],
    "wof:name":"Strong Janet Adams PHD",
    "wof:placetype":"venue"
},
  "geometry": {"coordinates":[-74.302268,40.650216],"type":"Point"}
}