{
  "type": "Feature",
  "properties": {
    "iso:country":"US",
    "sg:address":"23 New St",
    "sg:city":"Metuchen",
    "sg:classifiers":[
        {
            "category":"Recreation",
            "type":"Entertainment"
        }
    ],
    "sg:phone":"+1 732 205 9797",
    "sg:postcode":"08840",
    "sg:province":"NJ",
    "wof:name":"Black Belt Institute",
    "wof:placetype":"venue"
},
  "geometry": {"coordinates":[-74.36194999999999,40.541799],"type":"Point"}
}