{
  "type": "Feature",
  "properties": {
    "addr:full":"77 Herrontown Ln Princeton NJ 08540",
    "addr:housenumber":"77",
    "addr:postcode":"08540",
    "addr:street":"Herrontown Ln",
    "iso:country":"US",
    "sg:address":"77 Herrontown Ln",
    "sg:city":"Princeton",
    "sg:classifiers":[
        {
            "category":"Wholesale",
            "subcategory":"Jewelry",
            "type":"Manufacturing & Wholesale Goods"
        }
    ],
    "sg:phone":"+1 609 921 1322",
    "sg:postcode":"08540",
    "sg:province":"NJ",
    "sg:tags":[
        "clocks"
    ],
    "wof:name":"Windsor Clock Company",
    "wof:placetype":"venue"
},
  "geometry": {"coordinates":[-74.643294,40.384933],"type":"Point"}
}