{
  "type": "Feature",
  "properties": {
    "iso:country":"US",
    "sg:address":"121 Goodwin Ter",
    "sg:city":"Westwood",
    "sg:classifiers":[
        {
            "category":"Manufacturing",
            "subcategory":"Tools & Machinery",
            "type":"Manufacturing & Wholesale Goods"
        }
    ],
    "sg:phone":"+1 973 927 1328",
    "sg:postcode":"07675",
    "sg:province":"NJ",
    "sg:tags":[
        "security",
        "tag",
        "mfg"
    ],
    "wof:name":"Demodulation LLC",
    "wof:placetype":"venue"
},
  "geometry": {"coordinates":[-74.03436499999999,40.984743],"type":"Point"}
}