{
  "type": "Feature",
  "properties": {
    "iso:country":"US",
    "sg:address":"1876 Springfield Ave",
    "sg:city":"Maplewood",
    "sg:classifiers":[
        {
            "category":"Personal",
            "subcategory":"Beauty Salon",
            "type":"Services"
        }
    ],
    "sg:phone":"+1   ",
    "sg:postcode":"07040",
    "sg:province":"NJ",
    "sg:tags":[
        "shop"
    ],
    "wof:name":"Cha Mais Hair Salon Inc",
    "wof:placetype":"venue"
},
  "geometry": {"coordinates":[-74.26976000000001,40.720785],"type":"Point"}
}