{
  "type": "Feature",
  "properties": {
    "addr:full":"1700 Wheaton Ave Millville NJ 08332",
    "addr:housenumber":"1700",
    "addr:postcode":"08332",
    "addr:street":"Wheaton Ave",
    "iso:country":"US",
    "sg:address":"1700 Wheaton Ave",
    "sg:city":"Millville",
    "sg:classifiers":[
        {
            "category":"Social Services",
            "type":"Services"
        }
    ],
    "sg:phone":"+1   ",
    "sg:postcode":"08332",
    "sg:province":"NJ",
    "sg:tags":[
        "counseling",
        "family"
    ],
    "wof:name":"Millville Counseling Service",
    "wof:placetype":"venue"
},
  "geometry": {"coordinates":[-75.030485,39.414059],"type":"Point"}
}