{
  "type": "Feature",
  "properties": {
    "addr:full":"29 Wall St Red Bank NJ 07701",
    "addr:housenumber":"29",
    "addr:postcode":"07701",
    "addr:street":"Wall St",
    "iso:country":"US",
    "sg:address":"29 Wall St",
    "sg:city":"Red Bank",
    "sg:classifiers":[
        {
            "category":"Real Estate",
            "subcategory":"Real Estate Agent",
            "type":"Services"
        }
    ],
    "sg:phone":"+1   ",
    "sg:postcode":"07701",
    "sg:province":"NJ",
    "sg:tags":[
        "brokerage",
        "management"
    ],
    "wof:name":"Layton Realty & Management",
    "wof:placetype":"venue"
},
  "geometry": {"coordinates":[-74.07105799999999,40.350046],"type":"Point"}
}