{
  "type": "Feature",
  "properties": {
    "iso:country":"US",
    "sg:address":"118 Pine Bank Rd",
    "sg:city":"Flemington",
    "sg:classifiers":[
        {
            "category":"Manufacturing",
            "subcategory":"Printing",
            "type":"Manufacturing & Wholesale Goods"
        }
    ],
    "sg:phone":"+1 908 534 8514",
    "sg:postcode":"08822",
    "sg:province":"NJ",
    "sg:tags":[
        "book"
    ],
    "wof:name":"N J R",
    "wof:placetype":"venue"
},
  "geometry": {"coordinates":[-74.781614,40.573615],"type":"Point"}
}