{
  "type": "Feature",
  "properties": {
    "addr:full":"616 Central Ave Minotola NJ 08341",
    "addr:housenumber":"616",
    "addr:postcode":"08341",
    "addr:street":"Central Ave",
    "iso:country":"US",
    "sg:address":"616 Central Ave",
    "sg:city":"Minotola",
    "sg:classifiers":[
        {
            "category":"Government",
            "subcategory":"Police Station",
            "type":"Public Place"
        }
    ],
    "sg:phone":"+1   ",
    "sg:postcode":"08341",
    "sg:province":"NJ",
    "sg:tags":[
        "protection"
    ],
    "wof:name":"Uniboro Police",
    "wof:placetype":"venue"
},
  "geometry": {"coordinates":[-74.948171,39.522667],"type":"Point"}
}