{
  "type": "Feature",
  "properties": {
    "addr:full":"29 Galloping Hill Rd Cherry Hill NJ 08003",
    "addr:housenumber":"29",
    "addr:postcode":"08003",
    "addr:street":"Galloping Hill Rd",
    "iso:country":"US",
    "sg:address":"29 Galloping Hill Rd",
    "sg:city":"Cherry Hill",
    "sg:classifiers":[
        {
            "category":"Building & Trades",
            "subcategory":"Construction",
            "type":"Services"
        }
    ],
    "sg:phone":"+1 856 795 2568",
    "sg:postcode":"08003",
    "sg:province":"NJ",
    "sg:tags":[
        "house",
        "nonresidential"
    ],
    "wof:name":"A & S Builders",
    "wof:placetype":"venue"
},
  "geometry": {"coordinates":[-74.963324,39.867725],"type":"Point"}
}