{
  "type": "Feature",
  "properties": {
    "iso:country":"US",
    "sg:address":"5 Ethel Ave",
    "sg:city":"Hawthorne",
    "sg:classifiers":[
        {
            "category":"Home & Garden",
            "subcategory":"Furniture",
            "type":"Retail Goods"
        }
    ],
    "sg:phone":"+1 973 427 1848",
    "sg:postcode":"07506",
    "sg:province":"NJ",
    "sg:tags":[
        "house",
        "furnishing"
    ],
    "wof:name":"Valley Furniture Shop Inc",
    "wof:placetype":"venue"
},
  "geometry": {"coordinates":[-74.153717,40.962056],"type":"Point"}
}