{
  "type": "Feature",
  "properties": {
    "iso:country":"US",
    "sg:address":"300 Broad St",
    "sg:city":"Bloomfield",
    "sg:classifiers":[
        {
            "category":"Food & Beverages",
            "subcategory":"Groceries & Convenience Stores",
            "type":"Retail Goods"
        }
    ],
    "sg:phone":"+1   ",
    "sg:postcode":"07003",
    "sg:province":"NJ",
    "wof:name":"Krausers",
    "wof:placetype":"venue"
},
  "geometry": {"coordinates":[-74.194866,40.803657],"type":"Point"}
}