{
  "type": "Feature",
  "properties": {
    "iso:country":"US",
    "sg:address":"3504 Bergenline Ave",
    "sg:city":"Union City",
    "sg:classifiers":[
        {
            "category":"Utilities",
            "subcategory":"Telephone",
            "type":"Services"
        }
    ],
    "sg:phone":"+1 201 866 8600",
    "sg:postcode":"07087",
    "sg:province":"NJ",
    "sg:tags":[
        "telecommunication"
    ],
    "wof:name":"Telediscount Communications",
    "wof:placetype":"venue"
},
  "geometry": {"coordinates":[-74.027653,40.774031],"type":"Point"}
}