{
  "type": "Feature",
  "properties": {
    "iso:country":"US",
    "sg:address":"989 Lenox Dr",
    "sg:city":"Lawrenceville",
    "sg:classifiers":[
        {
            "category":"Professional",
            "subcategory":"Accounting & Tax Preparation",
            "type":"Services"
        }
    ],
    "sg:phone":"+1 609 219 0703",
    "sg:postcode":"08648",
    "sg:province":"NJ",
    "sg:tags":[
        "accountant"
    ],
    "wof:name":"KPMGLLP",
    "wof:placetype":"venue"
},
  "geometry": {"coordinates":[-74.704882,40.287628],"type":"Point"}
}