{
  "type": "Feature",
  "properties": {
    "iso:country":"US",
    "sg:address":"111 1st St",
    "sg:city":"Jersey City",
    "sg:classifiers":[
        {
            "category":"Professional",
            "subcategory":"Computer Services",
            "type":"Services"
        }
    ],
    "sg:phone":"+1 201 222 5469",
    "sg:postcode":"07302",
    "sg:province":"NJ",
    "sg:tags":[
        "consultant",
        "designer",
        "datum"
    ],
    "sg:website":"www.breakthroughtek.com",
    "wof:name":"Break Through Technologies",
    "wof:placetype":"venue"
},
  "geometry": {"coordinates":[-74.037969,40.721197],"type":"Point"}
}