{
  "type": "Feature",
  "properties": {
    "iso:country":"US",
    "sg:address":"1 English Ln",
    "sg:city":"Egg Harbor Township",
    "sg:classifiers":[
        {
            "category":"Professional",
            "subcategory":"Business Services",
            "type":"Services"
        }
    ],
    "sg:phone":"+1   ",
    "sg:postcode":"08234",
    "sg:province":"NJ",
    "wof:name":"Fairway Interiors",
    "wof:placetype":"venue"
},
  "geometry": {"coordinates":[-74.675872,39.359639],"type":"Point"}
}