{
  "type": "Feature",
  "properties": {
    "addr:full":"1204 US Hwy 130 Cinnaminson NJ 08077",
    "addr:housenumber":"1204",
    "addr:postcode":"08077",
    "addr:street":"Us Hwy 130",
    "iso:country":"US",
    "sg:address":"1204 US Hwy 130",
    "sg:city":"Cinnaminson",
    "sg:classifiers":[
        {
            "category":"Shopping",
            "subcategory":"Computers & Home Electronics",
            "type":"Retail Goods"
        }
    ],
    "sg:phone":"+1 856 829 8300",
    "sg:postcode":"08077",
    "sg:province":"NJ",
    "sg:tags":[
        "equipment",
        "dealer"
    ],
    "wof:name":"CPS Computer",
    "wof:placetype":"venue"
},
  "geometry": {"coordinates":[-74.990807,39.997672],"type":"Point"}
}