{
  "type": "Feature",
  "properties": {
    "iso:country":"US",
    "sg:address":"1 Grand Tour",
    "sg:city":"Highlands",
    "sg:classifiers":[
        {
            "category":"Building & Trades",
            "subcategory":"Electrical",
            "type":"Services"
        }
    ],
    "sg:phone":"+1 732 291 0966",
    "sg:postcode":"07732",
    "sg:province":"NJ",
    "sg:tags":[
        "electric",
        "contractor"
    ],
    "wof:name":"Electrical Design & Constr",
    "wof:placetype":"venue"
},
  "geometry": {"coordinates":[-73.986853,40.39288],"type":"Point"}
}