{
  "type": "Feature",
  "properties": {
    "addr:full":"8 Federal Twist Rd Stockton NJ 08559",
    "addr:housenumber":"8",
    "addr:postcode":"08559",
    "addr:street":"Federal Twist Rd",
    "iso:country":"US",
    "sg:address":"8 Federal Twist Rd",
    "sg:city":"Stockton",
    "sg:classifiers":[
        {
            "category":"Building & Trades",
            "subcategory":"Landscaping Services",
            "type":"Services"
        }
    ],
    "sg:phone":"+1 609 397 2700",
    "sg:postcode":"08559",
    "sg:province":"NJ",
    "wof:name":"T & T Tree Service Inc",
    "wof:placetype":"venue"
},
  "geometry": {"coordinates":[-75.025164,40.409795],"type":"Point"}
}