{
  "type": "Feature",
  "properties": {
    "addr:full":"593 3rd St Newark NJ 07107",
    "addr:housenumber":"593",
    "addr:postcode":"07107",
    "addr:street":"3Rd St",
    "iso:country":"US",
    "sg:address":"593 3rd St",
    "sg:city":"Newark",
    "sg:classifiers":[
        {
            "category":"Organizations",
            "subcategory":"Religious Organization",
            "type":"Services"
        }
    ],
    "sg:phone":"+1 973 412 0200",
    "sg:postcode":"07107",
    "sg:province":"NJ",
    "sg:tags":[
        "church"
    ],
    "wof:name":"Act Of Apostle Ministries",
    "wof:placetype":"venue"
},
  "geometry": {"coordinates":[-74.17859300000001,40.768914],"type":"Point"}
}