{
  "type": "Feature",
  "properties": {
    "iso:country":"US",
    "sg:address":"54 Sand Shore Rd",
    "sg:city":"Budd Lake",
    "sg:classifiers":[
        {
            "category":"Organizations",
            "subcategory":"Religious Organization",
            "type":"Services"
        }
    ],
    "sg:phone":"+1 973 691 8855",
    "sg:postcode":"07828",
    "sg:province":"NJ",
    "wof:name":"Budd Lake Union Chapel",
    "wof:placetype":"venue"
},
  "geometry": {"coordinates":[-74.73731600000001,40.874058],"type":"Point"}
}