{
  "type": "Feature",
  "properties": {
    "addr:full":"27 Federal City Rd Trenton NJ 08638",
    "addr:housenumber":"27",
    "addr:postcode":"08638",
    "addr:street":"Federal City Rd",
    "iso:country":"US",
    "sg:address":"27 Federal City Rd",
    "sg:city":"Trenton",
    "sg:classifiers":[
        {
            "category":"Social Services",
            "type":"Services"
        }
    ],
    "sg:phone":"+1 609 771 0525",
    "sg:postcode":"08638",
    "sg:province":"NJ",
    "sg:tags":[
        "organization",
        "welfare"
    ],
    "wof:name":"Junior League-Central Delaware",
    "wof:placetype":"venue"
},
  "geometry": {"coordinates":[-74.76993400000001,40.278931],"type":"Point"}
}