{
  "type": "Feature",
  "properties": {
    "iso:country":"US",
    "sg:address":"82 Fawnridge Dr",
    "sg:city":"Long Valley",
    "sg:classifiers":[
        {
            "category":"Shopping",
            "subcategory":"Used Merchandise",
            "type":"Retail Goods"
        }
    ],
    "sg:phone":"+1   ",
    "sg:postcode":"07853",
    "sg:province":"NJ",
    "wof:name":"ABC Antique Buying Co",
    "wof:placetype":"venue"
},
  "geometry": {"coordinates":[-74.771044,40.807988],"type":"Point"}
}