{
  "type": "Feature",
  "properties": {
    "addr:full":"5 Nottingham Way Turnersville NJ 08012",
    "addr:housenumber":"5",
    "addr:postcode":"08012",
    "addr:street":"Nottingham Way",
    "iso:country":"US",
    "sg:address":"5 Nottingham Way",
    "sg:city":"Turnersville",
    "sg:classifiers":[
        {
            "category":"Manufacturing",
            "subcategory":"Metals",
            "type":"Manufacturing & Wholesale Goods"
        }
    ],
    "sg:phone":"+1 856 374 2525",
    "sg:postcode":"08012",
    "sg:province":"NJ",
    "sg:tags":[
        "tower"
    ],
    "wof:name":"MPI",
    "wof:placetype":"venue"
},
  "geometry": {"coordinates":[-75.058125,39.760497],"type":"Point"}
}