{
  "type": "Feature",
  "properties": {
    "iso:country":"US",
    "sg:address":"59 Berry St",
    "sg:city":"Somerset",
    "sg:classifiers":[
        {
            "category":"Professional",
            "type":"Services"
        }
    ],
    "sg:phone":"+1 732 828 8161",
    "sg:postcode":"08873",
    "sg:province":"NJ",
    "sg:tags":[
        "establishment"
    ],
    "wof:name":"Enviro Coatings & Resins",
    "wof:placetype":"venue"
},
  "geometry": {"coordinates":[-74.485826,40.482749],"type":"Point"}
}