{
  "type": "Feature",
  "properties": {
    "iso:country":"US",
    "sg:address":"2 Kensington Pl",
    "sg:city":"Roseland",
    "sg:classifiers":[
        {
            "category":"Professional",
            "subcategory":"Computer Services",
            "type":"Services"
        }
    ],
    "sg:phone":"+1 973 618 1234",
    "sg:postcode":"07068",
    "sg:province":"NJ",
    "sg:tags":[
        "consultant",
        "designer"
    ],
    "wof:name":"Nora Enterprises Inc",
    "wof:placetype":"venue"
},
  "geometry": {"coordinates":[-74.287762,40.811428],"type":"Point"}
}