{
  "type": "Feature",
  "properties": {
    "addr:full":"124 Yawpo Ave Oakland NJ 07436",
    "addr:housenumber":"124",
    "addr:postcode":"07436",
    "addr:street":"Yawpo Ave",
    "iso:country":"US",
    "sg:address":"124 Yawpo Ave",
    "sg:city":"Oakland",
    "sg:classifiers":[
        {
            "category":"Real Estate",
            "subcategory":"Architect",
            "type":"Services"
        }
    ],
    "sg:phone":"+1 201 337 4283",
    "sg:postcode":"07436",
    "sg:province":"NJ",
    "sg:tags":[
        "architectural"
    ],
    "wof:name":"J C Debruyle Arch Planner",
    "wof:placetype":"venue"
},
  "geometry": {"coordinates":[-74.232229,41.019887],"type":"Point"}
}