{
  "type": "Feature",
  "properties": {
    "addr:full":"13 US Hwy 206 Somerville NJ 08876",
    "addr:housenumber":"13",
    "addr:postcode":"08876",
    "addr:street":"Us Hwy 206",
    "iso:country":"US",
    "sg:address":"13 US Hwy 206",
    "sg:city":"Somerville",
    "sg:classifiers":[
        {
            "category":"Manufacturing",
            "subcategory":"Signs",
            "type":"Manufacturing & Wholesale Goods"
        }
    ],
    "sg:phone":"+1 908 231 0306",
    "sg:postcode":"08876",
    "sg:province":"NJ",
    "sg:website":"www.fastsigns.com",
    "wof:name":"Fastsigns",
    "wof:placetype":"venue"
},
  "geometry": {"coordinates":[-74.61825399999999,40.559451],"type":"Point"}
}