{
  "type": "Feature",
  "properties": {
    "iso:country":"US",
    "sg:address":"22 N Park Pl",
    "sg:city":"Morristown",
    "sg:classifiers":[
        {
            "category":"Insurance",
            "subcategory":"Insurance Agent",
            "type":"Services"
        }
    ],
    "sg:phone":"+1 973 993 1224",
    "sg:postcode":"07960",
    "sg:province":"NJ",
    "wof:name":"Pro Mutual Group",
    "wof:placetype":"venue"
},
  "geometry": {"coordinates":[-74.481652,40.797417],"type":"Point"}
}