{
  "type": "Feature",
  "properties": {
    "addr:full":"15 Oak St Ridgewood NJ 07450",
    "addr:housenumber":"15",
    "addr:postcode":"07450",
    "addr:street":"Oak St",
    "iso:country":"US",
    "sg:address":"15 Oak St",
    "sg:city":"Ridgewood",
    "sg:classifiers":[
        {
            "category":"Food & Beverages",
            "subcategory":"Bakery",
            "type":"Retail Goods"
        }
    ],
    "sg:phone":"+1 201 445 5090",
    "sg:postcode":"07450",
    "sg:province":"NJ",
    "sg:tags":[
        "baker"
    ],
    "wof:name":"Dupan Bakery & Cafe",
    "wof:placetype":"venue"
},
  "geometry": {"coordinates":[-74.117638,40.980572],"type":"Point"}
}