{
  "type": "Feature",
  "properties": {
    "addr:full":"17 Pascack Rd Park Ridge NJ 07656",
    "addr:housenumber":"17",
    "addr:postcode":"07656",
    "addr:street":"Pascack Rd Park",
    "iso:country":"US",
    "sg:address":"17 Pascack Rd",
    "sg:city":"Park Ridge",
    "sg:classifiers":[
        {
            "category":"Health Services",
            "subcategory":"Doctor",
            "type":"Services"
        }
    ],
    "sg:phone":"+1 201 391 2499",
    "sg:postcode":"07656",
    "sg:province":"NJ",
    "sg:tags":[
        "physician",
        "surgeon"
    ],
    "wof:name":"Frank T Gulla MD",
    "wof:placetype":"venue"
},
  "geometry": {"coordinates":[-74.04578100000001,41.02841],"type":"Point"}
}