{
  "type": "Feature",
  "properties": {
    "iso:country":"US",
    "sg:address":"614 Newark Ave",
    "sg:city":"Elizabeth",
    "sg:classifiers":[
        {
            "category":"Banks & Credit Unions",
            "subcategory":"Financial Services",
            "type":"Services"
        }
    ],
    "sg:phone":"+1 908 662 2930",
    "sg:postcode":"07208",
    "sg:province":"NJ",
    "sg:tags":[
        "broker",
        "mortgage"
    ],
    "wof:name":"Gateway Funding",
    "wof:placetype":"venue"
},
  "geometry": {"coordinates":[-74.211887,40.677095],"type":"Point"}
}