{
  "type": "Feature",
  "properties": {
    "iso:country":"US",
    "sg:address":"118 Orchard St",
    "sg:city":"Newark",
    "sg:classifiers":[
        {
            "category":"Building & Trades",
            "subcategory":"Construction",
            "type":"Services"
        }
    ],
    "sg:phone":"+1 973 242 4616",
    "sg:postcode":"07102",
    "sg:province":"NJ",
    "sg:tags":[
        "contractor"
    ],
    "wof:name":"Super Structure",
    "wof:placetype":"venue"
},
  "geometry": {"coordinates":[-74.175968,40.7257],"type":"Point"}
}