{
  "type": "Feature",
  "properties": {
    "iso:country":"US",
    "sg:address":"46 Joshua Dr",
    "sg:city":"Ramsey",
    "sg:classifiers":[
        {
            "category":"Recreation",
            "type":"Entertainment"
        }
    ],
    "sg:phone":"+1 201 995 1666",
    "sg:postcode":"07446",
    "sg:province":"NJ",
    "wof:name":"Classroom Yoga Lady",
    "wof:placetype":"venue"
},
  "geometry": {"coordinates":[-74.157453,41.066247],"type":"Point"}
}