{
  "type": "Feature",
  "properties": {
    "iso:country":"US",
    "sg:address":"64 Baptist Church Rd",
    "sg:city":"Hampton",
    "sg:classifiers":[
        {
            "category":"Shopping",
            "subcategory":"Gifts & Souvenirs",
            "type":"Retail Goods"
        }
    ],
    "sg:phone":"+1   ",
    "sg:postcode":"08827",
    "sg:province":"NJ",
    "wof:name":"Christmas Fantasy",
    "wof:placetype":"venue"
},
  "geometry": {"coordinates":[-74.995878,40.6381],"type":"Point"}
}