{
  "type": "Feature",
  "properties": {
    "iso:country":"US",
    "sg:address":"1935 S Broad St",
    "sg:city":"Trenton",
    "sg:classifiers":[
        {
            "category":"Restaurant",
            "type":"Food & Drink"
        }
    ],
    "sg:phone":"+1 609 394 4999",
    "sg:postcode":"08610",
    "sg:province":"NJ",
    "wof:name":"Shogun Wok Hamilton",
    "wof:placetype":"venue"
},
  "geometry": {"coordinates":[-74.728718,40.198053],"type":"Point"}
}