{
  "type": "Feature",
  "properties": {
    "iso:country":"US",
    "sg:address":"292 Willow Way",
    "sg:city":"Clark",
    "sg:classifiers":[
        {
            "category":"Professional",
            "subcategory":"Business Services",
            "type":"Services"
        }
    ],
    "sg:phone":"+1   ",
    "sg:postcode":"07066",
    "sg:province":"NJ",
    "wof:name":"Wjm Enterprises Inc",
    "wof:placetype":"venue"
},
  "geometry": {"coordinates":[-74.336721,40.606516],"type":"Point"}
}