{
  "type": "Feature",
  "properties": {
    "iso:country":"US",
    "sg:address":"1240 N 25th St",
    "sg:city":"Camden",
    "sg:classifiers":[
        {
            "category":"Professional",
            "type":"Services"
        }
    ],
    "sg:phone":"+1   ",
    "sg:postcode":"08105",
    "sg:province":"NJ",
    "wof:name":"Angel Orihuela",
    "wof:placetype":"venue"
},
  "geometry": {"coordinates":[-75.098178,39.956194],"type":"Point"}
}