{
  "type": "Feature",
  "properties": {
    "iso:country":"US",
    "sg:address":"59 Washburn St",
    "sg:city":"Jersey City",
    "sg:classifiers":[
        {
            "category":"Manufacturing",
            "subcategory":"Tools & Machinery",
            "type":"Manufacturing & Wholesale Goods"
        }
    ],
    "sg:phone":"+1 201 798 5709",
    "sg:postcode":"07306",
    "sg:province":"NJ",
    "sg:tags":[
        "measuring",
        "mfg",
        "related",
        "instrument",
        "s",
        "computer",
        "electrical"
    ],
    "wof:name":"Cyberlink Inc",
    "wof:placetype":"venue"
},
  "geometry": {"coordinates":[-74.05632900000001,40.733036],"type":"Point"}
}