{
  "type": "Feature",
  "properties": {
    "addr:full":"241 Carroll St Paterson NJ 07501",
    "addr:housenumber":"241",
    "addr:postcode":"07501",
    "addr:street":"Carroll St",
    "iso:country":"US",
    "sg:address":"241 Carroll St",
    "sg:city":"Paterson",
    "sg:classifiers":[
        {
            "category":"Building & Trades",
            "subcategory":"Construction",
            "type":"Services"
        }
    ],
    "sg:phone":"+1 973 523 4048",
    "sg:postcode":"07501",
    "sg:province":"NJ",
    "sg:tags":[
        "contractor"
    ],
    "wof:name":"Montesino General Contracting",
    "wof:placetype":"venue"
},
  "geometry": {"coordinates":[-74.16199,40.915636],"type":"Point"}
}