{
  "type": "Feature",
  "properties": {
    "addr:full":"110 Hardy Ave Bound Brook NJ 08805",
    "addr:housenumber":"110",
    "addr:postcode":"08805",
    "addr:street":"Hardy Ave",
    "iso:country":"US",
    "sg:address":"110 Hardy Ave",
    "sg:city":"Bound Brook",
    "sg:classifiers":[
        {
            "category":"Professional",
            "type":"Services"
        }
    ],
    "sg:phone":"+1 212 627 8984",
    "sg:postcode":"08805",
    "sg:province":"NJ",
    "wof:name":"Affinity Services Inc",
    "wof:placetype":"venue"
},
  "geometry": {"coordinates":[-74.545309,40.561525],"type":"Point"}
}