{
  "type": "Feature",
  "properties": {
    "iso:country":"US",
    "sg:address":"129 Dermody St",
    "sg:city":"Cranford",
    "sg:classifiers":[
        {
            "category":"Wholesale",
            "subcategory":"Durable Goods & Equipment",
            "type":"Manufacturing & Wholesale Goods"
        }
    ],
    "sg:phone":"+1 908 653 4433",
    "sg:postcode":"07016",
    "sg:province":"NJ",
    "wof:name":"Jaclo Industries",
    "wof:placetype":"venue"
},
  "geometry": {"coordinates":[-74.28376400000001,40.653273],"type":"Point"}
}