{
  "type": "Feature",
  "properties": {
    "iso:country":"US",
    "sg:address":"150 Winding Wood Dr",
    "sg:city":"Sayreville",
    "sg:classifiers":[
        {
            "category":"Real Estate",
            "subcategory":"Real Estate Operator",
            "type":"Services"
        }
    ],
    "sg:phone":"+1   ",
    "sg:postcode":"08872",
    "sg:province":"NJ",
    "sg:tags":[
        "building",
        "apartment"
    ],
    "wof:name":"Winding Woods Apartments",
    "wof:placetype":"venue"
},
  "geometry": {"coordinates":[-74.348995,40.429272],"type":"Point"}
}