{
  "type": "Feature",
  "properties": {
    "addr:full":"218 South Ave E Cranford NJ 07016",
    "addr:housenumber":"218",
    "addr:postcode":"07016",
    "addr:street":"South Ave E",
    "iso:country":"US",
    "sg:address":"218 South Ave E",
    "sg:city":"Cranford",
    "sg:classifiers":[
        {
            "category":"Shopping",
            "subcategory":"Used Merchandise",
            "type":"Retail Goods"
        }
    ],
    "sg:phone":"+1   ",
    "sg:postcode":"07016",
    "sg:province":"NJ",
    "wof:name":"Not Just Antiques",
    "wof:placetype":"venue"
},
  "geometry": {"coordinates":[-74.30175300000001,40.654781],"type":"Point"}
}