{
  "type": "Feature",
  "properties": {
    "iso:country":"US",
    "sg:address":"128 E Knight Ave",
    "sg:city":"Collingswood",
    "sg:classifiers":[
        {
            "category":"Professional",
            "subcategory":"Detective & Security Services",
            "type":"Services"
        }
    ],
    "sg:phone":"+1 856 854 5418",
    "sg:postcode":"08108",
    "sg:province":"NJ",
    "sg:tags":[
        "information",
        "bureau"
    ],
    "wof:name":"Jjc's Home Based Services",
    "wof:placetype":"venue"
},
  "geometry": {"coordinates":[-75.07167099999999,39.919313],"type":"Point"}
}