{
  "type": "Feature",
  "properties": {
    "addr:full":"31 Eisenhower Parkway Roseland NJ 07068",
    "addr:housenumber":"31",
    "addr:postcode":"07068",
    "addr:street":"Eisenhower Parkway",
    "iso:country":"US",
    "sg:address":"31 Eisenhower Parkway",
    "sg:city":"Roseland",
    "sg:classifiers":[
        {
            "category":"Home & Garden",
            "subcategory":"Carpets & Floor Coverings",
            "type":"Retail Goods"
        }
    ],
    "sg:phone":"+1 973 228 4128",
    "sg:postcode":"07068",
    "sg:province":"NJ",
    "sg:tags":[
        "flooring"
    ],
    "sg:website":"www.taubenfloors.com",
    "wof:name":"Tauben Floors",
    "wof:placetype":"venue"
},
  "geometry": {"coordinates":[-74.32664,40.821604],"type":"Point"}
}