{
  "type": "Feature",
  "properties": {
    "iso:country":"US",
    "sg:address":"104 Sandy Ridge Mount Airy Rd",
    "sg:city":"Stockton",
    "sg:classifiers":[
        {
            "category":"Professional",
            "subcategory":"Management & Consulting",
            "type":"Services"
        }
    ],
    "sg:phone":"+1   ",
    "sg:postcode":"08559",
    "sg:province":"NJ",
    "wof:name":"R & D Excellance LLC",
    "wof:placetype":"venue"
},
  "geometry": {"coordinates":[-74.950104,40.418494],"type":"Point"}
}