{
  "type": "Feature",
  "properties": {
    "iso:country":"US",
    "sg:address":"221 Rock Rd",
    "sg:city":"Glen Rock",
    "sg:classifiers":[
        {
            "category":"Restaurant",
            "type":"Food & Drink"
        }
    ],
    "sg:phone":"+1 201 447 3122",
    "sg:postcode":"07452",
    "sg:province":"NJ",
    "sg:tags":[
        "caterer"
    ],
    "wof:name":"Wilkes Country Deli",
    "wof:placetype":"venue"
},
  "geometry": {"coordinates":[-74.130004,40.962506],"type":"Point"}
}