{
  "type": "Feature",
  "properties": {
    "iso:country":"US",
    "sg:address":"428 Grand St",
    "sg:city":"Jersey City",
    "sg:classifiers":[
        {
            "category":"Fast Food",
            "type":"Food & Drink"
        }
    ],
    "sg:phone":"+1 201 433 0055",
    "sg:postcode":"07302",
    "sg:province":"NJ",
    "sg:website":"www.mcdonalds.com/",
    "wof:name":"McDonald's",
    "wof:placetype":"venue"
},
  "geometry": {"coordinates":[-74.05395900000001,40.717163],"type":"Point"}
}