{
  "type": "Feature",
  "properties": {
    "addr:full":"818 Haddonfield Rd Cherry Hill NJ 08002",
    "addr:housenumber":"818",
    "addr:postcode":"08002",
    "addr:street":"Haddonfield Rd",
    "iso:country":"US",
    "sg:address":"818 Haddonfield Rd",
    "sg:city":"Cherry Hill",
    "sg:classifiers":[
        {
            "category":"Restaurant",
            "type":"Food & Drink"
        }
    ],
    "sg:phone":"+1 856 910 2424",
    "sg:postcode":"08002",
    "sg:province":"NJ",
    "sg:tags":[
        "pizza"
    ],
    "sg:website":"www.cicispizza.com",
    "wof:name":"CiCi's Pizza",
    "wof:placetype":"venue"
},
  "geometry": {"coordinates":[-75.031904,39.927421],"type":"Point"}
}