{
  "type": "Feature",
  "properties": {
    "iso:country":"US",
    "sg:address":"61 W Kings Hwy",
    "sg:city":"Mount Ephraim",
    "sg:classifiers":[
        {
            "category":"Sports & Exercise",
            "subcategory":"Gym",
            "type":"Entertainment"
        },
        {
            "category":"Arena",
            "subcategory":"Sports Club",
            "type":"Entertainment"
        }
    ],
    "sg:phone":"+1 856 933 2800",
    "sg:postcode":"08059",
    "sg:province":"NJ",
    "sg:tags":[
        "martial art"
    ],
    "wof:name":"South Jersey Aikido Academy Inc",
    "wof:placetype":"venue"
},
  "geometry": {"coordinates":[-75.08910400000001,39.880901],"type":"Point"}
}