{
  "type": "Feature",
  "properties": {
    "iso:country":"US",
    "sg:address":"1190 Roosevelt Blvd",
    "sg:city":"Vineland",
    "sg:classifiers":[
        {
            "category":"Building & Trades",
            "subcategory":"Construction",
            "type":"Services"
        }
    ],
    "sg:phone":"+1 856 692 7293",
    "sg:postcode":"08361",
    "sg:province":"NJ",
    "sg:tags":[
        "excavation",
        "contractor"
    ],
    "wof:name":"Harold Brown Inc",
    "wof:placetype":"venue"
},
  "geometry": {"coordinates":[-74.99618100000001,39.457331],"type":"Point"}
}