{
  "type": "Feature",
  "properties": {
    "iso:country":"US",
    "sg:address":"685 Summit Ave",
    "sg:city":"Jersey City",
    "sg:classifiers":[
        {
            "category":"Professional",
            "type":"Services"
        }
    ],
    "sg:phone":"+1 201 656 8433",
    "sg:postcode":"07306",
    "sg:province":"NJ",
    "sg:tags":[
        "establishment"
    ],
    "wof:name":"Win Sum Refrigeration Co",
    "wof:placetype":"venue"
},
  "geometry": {"coordinates":[-74.058216,40.738763],"type":"Point"}
}