{
  "type": "Feature",
  "properties": {
    "addr:full":"23 Niagara St Newark NJ 07105",
    "addr:housenumber":"23",
    "addr:postcode":"07105",
    "addr:street":"Niagara St",
    "iso:country":"US",
    "sg:address":"23 Niagara St",
    "sg:city":"Newark",
    "sg:classifiers":[
        {
            "category":"Building & Trades",
            "subcategory":"Construction",
            "type":"Services"
        }
    ],
    "sg:phone":"+1 973 589 0330",
    "sg:postcode":"07105",
    "sg:province":"NJ",
    "sg:tags":[
        "contractor"
    ],
    "wof:name":"New Jersey Builders",
    "wof:placetype":"venue"
},
  "geometry": {"coordinates":[-74.152164,40.728202],"type":"Point"}
}