{
  "type": "Feature",
  "properties": {
    "addr:full":"328 Hurffville Grenloch Rd Sewell NJ 08080",
    "addr:housenumber":"328",
    "addr:postcode":"08080",
    "addr:street":"Hurffville Grenloch Rd",
    "iso:country":"US",
    "sg:address":"328 Hurffville Grenloch Rd",
    "sg:city":"Sewell",
    "sg:classifiers":[
        {
            "category":"Home & Garden",
            "subcategory":"Garden Supply",
            "type":"Retail Goods"
        }
    ],
    "sg:phone":"+1 856 228 7385",
    "sg:postcode":"08080",
    "sg:province":"NJ",
    "sg:tags":[
        "mulch"
    ],
    "wof:name":"Accent Garden Market",
    "wof:placetype":"venue"
},
  "geometry": {"coordinates":[-75.074094,39.769747],"type":"Point"}
}