{
  "type": "Feature",
  "properties": {
    "addr:full":"838 Market St Paterson NJ 07513",
    "addr:housenumber":"838",
    "addr:postcode":"07513",
    "addr:street":"Market St",
    "iso:country":"US",
    "sg:address":"838 Market St",
    "sg:city":"Paterson",
    "sg:classifiers":[
        {
            "category":"Retail",
            "subcategory":"Auto Rental",
            "type":"Services"
        }
    ],
    "sg:phone":"+1 973 278 3700",
    "sg:postcode":"07513",
    "sg:province":"NJ",
    "sg:tags":[
        "renting",
        "truck",
        "leasing"
    ],
    "wof:name":"U-Haul Co",
    "wof:placetype":"venue"
},
  "geometry": {"coordinates":[-74.14484299999999,40.903906],"type":"Point"}
}