{
  "type": "Feature",
  "properties": {
    "addr:full":"951 Elizabeth Ave Elizabeth NJ 07201",
    "addr:housenumber":"951",
    "addr:postcode":"07201",
    "addr:street":"Elizabeth Ave",
    "iso:country":"US",
    "sg:address":"951 Elizabeth Ave",
    "sg:city":"Elizabeth",
    "sg:classifiers":[
        {
            "category":"Professional",
            "type":"Services"
        }
    ],
    "sg:phone":"+1 908 352 4666",
    "sg:postcode":"07201",
    "sg:province":"NJ",
    "sg:tags":[
        "establishment"
    ],
    "wof:name":"Avianca Express",
    "wof:placetype":"venue"
},
  "geometry": {"coordinates":[-74.207263,40.660422],"type":"Point"}
}