{
  "type": "Feature",
  "properties": {
    "addr:full":"102 Haddonfield Berlin Rd Voorhees NJ 08043",
    "addr:housenumber":"102",
    "addr:postcode":"08043",
    "addr:street":"Haddonfield Berlin Rd",
    "iso:country":"US",
    "sg:address":"102 Haddonfield Berlin Rd",
    "sg:city":"Voorhees",
    "sg:classifiers":[
        {
            "category":"Shopping",
            "type":"Retail Goods"
        }
    ],
    "sg:phone":"+1   ",
    "sg:postcode":"08043",
    "sg:province":"NJ",
    "sg:tags":[
        "merchandise"
    ],
    "wof:name":"Frame Design",
    "wof:placetype":"venue"
},
  "geometry": {"coordinates":[-74.98715300000001,39.858239],"type":"Point"}
}