{
  "type": "Feature",
  "properties": {
    "addr:full":"17 Backus St Newark NJ 07105",
    "addr:housenumber":"17",
    "addr:postcode":"07105",
    "addr:street":"Backus St",
    "iso:country":"US",
    "sg:address":"17 Backus St",
    "sg:city":"Newark",
    "sg:classifiers":[
        {
            "category":"Home & Garden",
            "subcategory":"Building Materials",
            "type":"Retail Goods"
        }
    ],
    "sg:phone":"+1 973 491 9015",
    "sg:postcode":"07105",
    "sg:province":"NJ",
    "sg:tags":[
        "glass",
        "leaded"
    ],
    "wof:name":"Ramon Keith Designs",
    "wof:placetype":"venue"
},
  "geometry": {"coordinates":[-74.154781,40.718809],"type":"Point"}
}