{
  "type": "Feature",
  "properties": {
    "addr:full":"1100 E Landis Ave Vineland NJ 08360",
    "addr:housenumber":"1100",
    "addr:postcode":"08360",
    "addr:street":"E Landis Ave",
    "iso:country":"US",
    "sg:address":"1100 E Landis Ave",
    "sg:city":"Vineland",
    "sg:classifiers":[
        {
            "category":"Professional",
            "type":"Services"
        }
    ],
    "sg:phone":"+1 856 696 1117",
    "sg:postcode":"08360",
    "sg:province":"NJ",
    "sg:tags":[
        "establishment"
    ],
    "wof:name":"Moetronics Inc",
    "wof:placetype":"venue"
},
  "geometry": {"coordinates":[-75.00604800000001,39.485244],"type":"Point"}
}