{
  "type": "Feature",
  "properties": {
    "iso:country":"US",
    "sg:address":"286 US Hwy 46",
    "sg:city":"Great Meadows",
    "sg:classifiers":[
        {
            "category":"Education",
            "subcategory":"School",
            "type":"Public Place"
        }
    ],
    "sg:phone":"+1 908 637 4349",
    "sg:postcode":"07838",
    "sg:province":"NJ",
    "wof:name":"Independence Twp Middle School",
    "wof:placetype":"venue"
},
  "geometry": {"coordinates":[-74.89834999999999,40.872304],"type":"Point"}
}