{
  "type": "Feature",
  "properties": {
    "addr:full":"509 Kennedy St Palmyra NJ 08065",
    "addr:housenumber":"509",
    "addr:postcode":"08065",
    "addr:street":"Kennedy St",
    "iso:country":"US",
    "sg:address":"509 Kennedy St",
    "sg:city":"Palmyra",
    "sg:classifiers":[
        {
            "category":"Building & Trades",
            "subcategory":"Landscaping Services",
            "type":"Services"
        }
    ],
    "sg:phone":"+1 856 303 2770",
    "sg:postcode":"08065",
    "sg:province":"NJ",
    "wof:name":"Medford Village Landscaping",
    "wof:placetype":"venue"
},
  "geometry": {"coordinates":[-75.034181,40.002916],"type":"Point"}
}