{
  "type": "Feature",
  "properties": {
    "addr:full":"1663 Lincoln Hwy Edison NJ 08817",
    "addr:housenumber":"1663",
    "addr:postcode":"08817",
    "addr:street":"Lincoln Hwy",
    "iso:country":"US",
    "sg:address":"1663 Lincoln Hwy",
    "sg:city":"Edison",
    "sg:classifiers":[
        {
            "category":"Retail",
            "subcategory":"Repair Shop",
            "type":"Services"
        }
    ],
    "sg:phone":"+1   ",
    "sg:postcode":"08817",
    "sg:province":"NJ",
    "wof:name":"A24 7 Emergency A Locksmith",
    "wof:placetype":"venue"
},
  "geometry": {"coordinates":[-74.40922399999999,40.510396],"type":"Point"}
}