{
  "type": "Feature",
  "properties": {
    "iso:country":"US",
    "sg:address":"116 New York Ave",
    "sg:city":"Point Pleasant Beach",
    "sg:classifiers":[
        {
            "category":"Manufacturing",
            "subcategory":"Printing",
            "type":"Manufacturing & Wholesale Goods"
        }
    ],
    "sg:phone":"+1 732 892 6515",
    "sg:postcode":"08742",
    "sg:province":"NJ",
    "sg:tags":[
        "lithographic",
        "commercial"
    ],
    "wof:name":"Spectrum Screen Printing",
    "wof:placetype":"venue"
},
  "geometry": {"coordinates":[-74.04113,40.086797],"type":"Point"}
}