{
  "type": "Feature",
  "properties": {
    "iso:country":"US",
    "sg:address":"112 Academy Ln",
    "sg:city":"Cape May Ct Hse",
    "sg:classifiers":[
        {
            "category":"Shopping",
            "subcategory":"Clothing, Apparel, & Fashions",
            "type":"Retail Goods"
        }
    ],
    "sg:phone":"+1 609 624 8767",
    "sg:postcode":"08210",
    "sg:province":"NJ",
    "sg:tags":[
        "uniform"
    ],
    "wof:name":"Whatever Works",
    "wof:placetype":"venue"
},
  "geometry": {"coordinates":[-74.75610500000001,39.170556],"type":"Point"}
}