{
  "type": "Feature",
  "properties": {
    "addr:full":"163 Ridgedale Ave Florham Park NJ 07932",
    "addr:housenumber":"163",
    "addr:postcode":"07932",
    "addr:street":"Ridgedale Ave",
    "iso:country":"US",
    "sg:address":"163 Ridgedale Ave",
    "sg:city":"Florham Park",
    "sg:classifiers":[
        {
            "category":"Manufacturing",
            "subcategory":"Toys & Sporting Goods",
            "type":"Manufacturing & Wholesale Goods"
        }
    ],
    "sg:phone":"+1 973 377 4272",
    "sg:postcode":"07932",
    "sg:province":"NJ",
    "sg:tags":[
        "range",
        "pistol",
        "rifle"
    ],
    "wof:name":"Florham Pistol & Rifle Club",
    "wof:placetype":"venue"
},
  "geometry": {"coordinates":[-74.391976,40.786621],"type":"Point"}
}