{
  "type": "Feature",
  "properties": {
    "addr:full":"1191 Edgewater Ave Ridgefield NJ 07657",
    "addr:housenumber":"1191",
    "addr:postcode":"07657",
    "addr:street":"Edgewater Ave",
    "iso:country":"US",
    "sg:address":"1191 Edgewater Ave",
    "sg:city":"Ridgefield",
    "sg:classifiers":[
        {
            "category":"Professional",
            "type":"Services"
        }
    ],
    "sg:phone":"+1 201 941 2679",
    "sg:postcode":"07657",
    "sg:province":"NJ",
    "sg:tags":[
        "establishment"
    ],
    "wof:name":"Action America",
    "wof:placetype":"venue"
},
  "geometry": {"coordinates":[-74.01366,40.83509],"type":"Point"}
}