{
  "type": "Feature",
  "properties": {
    "addr:full":"4 N Main St Pennington NJ 08534",
    "addr:housenumber":"4",
    "addr:postcode":"08534",
    "addr:street":"N Main St",
    "iso:country":"US",
    "sg:address":"4 N Main St",
    "sg:city":"Pennington",
    "sg:classifiers":[
        {
            "category":"Deli",
            "type":"Food & Drink"
        },
        {
            "category":"Restaurant",
            "type":"Food & Drink"
        },
        {
            "category":"Food & Beverages",
            "subcategory":"Groceries & Convenience Stores",
            "type":"Retail Goods"
        }
    ],
    "sg:phone":"+1 609 737 8520",
    "sg:postcode":"08534",
    "sg:province":"NJ",
    "sg:tags":[
        "shop",
        "italian",
        "delicatessen",
        "sandwich",
        "pizza"
    ],
    "wof:name":"Vito's Pizza",
    "wof:placetype":"venue"
},
  "geometry": {"coordinates":[-74.791061,40.328089],"type":"Point"}
}