{
  "type": "Feature",
  "properties": {
    "addr:full":"347 Elizabeth Ave Somerset NJ 08873",
    "addr:housenumber":"347",
    "addr:postcode":"08873",
    "addr:street":"Elizabeth Ave",
    "iso:country":"US",
    "sg:address":"347 Elizabeth Ave",
    "sg:city":"Somerset",
    "sg:classifiers":[
        {
            "category":"Professional",
            "subcategory":"Computer Services",
            "type":"Services"
        }
    ],
    "sg:phone":"+1   ",
    "sg:postcode":"08873",
    "sg:province":"NJ",
    "sg:tags":[
        "networking"
    ],
    "wof:name":"I C N",
    "wof:placetype":"venue"
},
  "geometry": {"coordinates":[-74.532157,40.550325],"type":"Point"}
}