{
  "type": "Feature",
  "properties": {
    "iso:country":"US",
    "sg:address":"701 Green Grove Rd",
    "sg:city":"Neptune",
    "sg:classifiers":[
        {
            "category":"Social Services",
            "subcategory":"Adult Care",
            "type":"Services"
        },
        {
            "category":"Organizations",
            "subcategory":"Membership Organization",
            "type":"Services"
        }
    ],
    "sg:phone":"+1 732 922 8128",
    "sg:postcode":"07753",
    "sg:province":"NJ",
    "sg:tags":[
        "residential"
    ],
    "wof:name":"United Cerebral Palsy Inc",
    "wof:placetype":"venue"
},
  "geometry": {"coordinates":[-74.070279,40.218999],"type":"Point"}
}