{
  "type": "Feature",
  "properties": {
    "iso:country":"US",
    "sg:address":"33 N Bridge St",
    "sg:city":"Somerville",
    "sg:classifiers":[
        {
            "category":"Professional",
            "subcategory":"Lawyer & Legal Services",
            "type":"Services"
        }
    ],
    "sg:phone":"+1 908 707 4560",
    "sg:postcode":"08876",
    "sg:province":"NJ",
    "sg:tags":[
        "attorney"
    ],
    "wof:name":"Detzky & Hunter Atty At Law",
    "wof:placetype":"venue"
},
  "geometry": {"coordinates":[-74.611543,40.568876],"type":"Point"}
}