{
  "type": "Feature",
  "properties": {
    "iso:country":"US",
    "sg:address":"131 Park Ave",
    "sg:city":"Verona",
    "sg:classifiers":[
        {
            "category":"Arts & Performance",
            "subcategory":"Theater",
            "type":"Entertainment"
        }
    ],
    "sg:phone":"+1 973 239 5888",
    "sg:postcode":"07044",
    "sg:province":"NJ",
    "sg:tags":[
        "theatrical"
    ],
    "wof:name":"Artistic Entertainment",
    "wof:placetype":"venue"
},
  "geometry": {"coordinates":[-74.247546,40.82395],"type":"Point"}
}