{
  "type": "Feature",
  "properties": {
    "iso:country":"US",
    "sg:address":"100 Ludlow St",
    "sg:city":"Newark",
    "sg:classifiers":[
        {
            "category":"Personal",
            "subcategory":"Beauty Salon",
            "type":"Services"
        }
    ],
    "sg:phone":"+1 973 624 2233",
    "sg:postcode":"07114",
    "sg:province":"NJ",
    "wof:name":"Neal's Braiding Shop",
    "wof:placetype":"venue"
},
  "geometry": {"coordinates":[-74.20523900000001,40.689332],"type":"Point"}
}