{
  "type": "Feature",
  "properties": {
    "iso:country":"US",
    "sg:address":"55 E Main St",
    "sg:city":"Little Falls",
    "sg:classifiers":[
        {
            "category":"Personal",
            "subcategory":"Tanning Parlor",
            "type":"Services"
        }
    ],
    "sg:phone":"+1 973 785 8024",
    "sg:postcode":"07424",
    "sg:province":"NJ",
    "wof:name":"Exotic Image Tanning Salon",
    "wof:placetype":"venue"
},
  "geometry": {"coordinates":[-74.22339599999999,40.880199],"type":"Point"}
}