{
  "type": "Feature",
  "properties": {
    "iso:country":"US",
    "sg:address":"5090 Central Hwy",
    "sg:city":"Pennsauken",
    "sg:classifiers":[
        {
            "category":"Professional",
            "subcategory":"Research",
            "type":"Services"
        }
    ],
    "sg:phone":"+1 856 910 9750",
    "sg:postcode":"08109",
    "sg:province":"NJ",
    "sg:tags":[
        "environmental",
        "ecological"
    ],
    "wof:name":"Gei Consultants",
    "wof:placetype":"venue"
},
  "geometry": {"coordinates":[-75.070599,39.929464],"type":"Point"}
}