{
  "type": "Feature",
  "properties": {
    "iso:country":"US",
    "sg:address":"156 Lindbergh Rd",
    "sg:city":"Hopewell",
    "sg:classifiers":[
        {
            "category":"Government",
            "subcategory":"Office",
            "type":"Public Place"
        }
    ],
    "sg:phone":"+1   ",
    "sg:postcode":"08525",
    "sg:province":"NJ",
    "sg:tags":[
        "executive"
    ],
    "wof:name":"Tamara Lee Consulting LLC",
    "wof:placetype":"venue"
},
  "geometry": {"coordinates":[-74.757603,40.425311],"type":"Point"}
}