{
  "type": "Feature",
  "properties": {
    "addr:full":"443 Sayre Dr Princeton NJ 08540",
    "addr:housenumber":"443",
    "addr:postcode":"08540",
    "addr:street":"Sayre Dr",
    "iso:country":"US",
    "sg:address":"443 Sayre Dr",
    "sg:city":"Princeton",
    "sg:classifiers":[
        {
            "category":"Professional",
            "subcategory":"Management & Consulting",
            "type":"Services"
        }
    ],
    "sg:phone":"+1 609 919 0275",
    "sg:postcode":"08540",
    "sg:province":"NJ",
    "sg:tags":[
        "consultant",
        "occupational",
        "radiation",
        "health"
    ],
    "wof:name":"Edward A Christman",
    "wof:placetype":"venue"
},
  "geometry": {"coordinates":[-74.622873,40.352024],"type":"Point"}
}