{
  "type": "Feature",
  "properties": {
    "iso:country":"US",
    "sg:address":"124 Hawthorne Ave",
    "sg:city":"Newark",
    "sg:classifiers":[
        {
            "category":"Building & Trades",
            "subcategory":"Electrical",
            "type":"Services"
        }
    ],
    "sg:phone":"+1 973 621 0501",
    "sg:postcode":"07112",
    "sg:province":"NJ",
    "sg:tags":[
        "electrical",
        "contractor"
    ],
    "wof:name":"Hacksters Multimedia",
    "wof:placetype":"venue"
},
  "geometry": {"coordinates":[-74.19908,40.714504],"type":"Point"}
}