{
  "type": "Feature",
  "properties": {
    "addr:full":"112 North Ave W Cranford NJ 07016",
    "addr:housenumber":"112",
    "addr:postcode":"07016",
    "addr:street":"North Ave W",
    "iso:country":"US",
    "sg:address":"112 North Ave W",
    "sg:city":"Cranford",
    "sg:classifiers":[
        {
            "category":"Personal",
            "subcategory":"Nail Salon",
            "type":"Services"
        }
    ],
    "sg:phone":"+1 908 272 1332",
    "sg:postcode":"07016",
    "sg:province":"NJ",
    "wof:name":"Nail Plaza Plus",
    "wof:placetype":"venue"
},
  "geometry": {"coordinates":[-74.30950199999999,40.655499],"type":"Point"}
}