{
  "type": "Feature",
  "properties": {
    "addr:full":"1335 Sunset Ave Pt Pleasant Boro NJ 08742",
    "addr:housenumber":"1335",
    "addr:postcode":"08742",
    "addr:street":"Sunset Ave Pt",
    "iso:country":"US",
    "sg:address":"1335 Sunset Ave",
    "sg:city":"Pt Pleasant Boro",
    "sg:classifiers":[
        {
            "category":"Real Estate",
            "subcategory":"Surveying",
            "type":"Services"
        }
    ],
    "sg:phone":"+1 732 223 0735",
    "sg:postcode":"08742",
    "sg:province":"NJ",
    "sg:tags":[
        "surveyor"
    ],
    "wof:name":"Edwards Surveying",
    "wof:placetype":"venue"
},
  "geometry": {"coordinates":[-74.08208999999999,40.071911],"type":"Point"}
}