{
  "type": "Feature",
  "properties": {
    "addr:full":"15 Minneakoning Rd Flemington NJ 08822",
    "addr:housenumber":"15",
    "addr:postcode":"08822",
    "addr:street":"Minneakoning Rd",
    "iso:country":"US",
    "sg:address":"15 Minneakoning Rd",
    "sg:city":"Flemington",
    "sg:classifiers":[
        {
            "category":"Shopping",
            "subcategory":"Discount & Variety Stores",
            "type":"Retail Goods"
        }
    ],
    "sg:phone":"+1 908 237 9932",
    "sg:postcode":"08822",
    "sg:province":"NJ",
    "sg:tags":[
        "merchandise",
        "general"
    ],
    "wof:name":"Mt Hope Rock Products",
    "wof:placetype":"venue"
},
  "geometry": {"coordinates":[-74.851546,40.530078],"type":"Point"}
}