{
  "type": "Feature",
  "properties": {
    "iso:country":"US",
    "sg:address":"10 Damascus Dr",
    "sg:city":"Marlboro",
    "sg:classifiers":[
        {
            "category":"Wholesale",
            "subcategory":"Apparel",
            "type":"Manufacturing & Wholesale Goods"
        }
    ],
    "sg:phone":"+1 732 577 9554",
    "sg:postcode":"07746",
    "sg:province":"NJ",
    "wof:name":"One Source Apparel Group LLC",
    "wof:placetype":"venue"
},
  "geometry": {"coordinates":[-74.27308499999999,40.305059],"type":"Point"}
}