{
  "type": "Feature",
  "properties": {
    "iso:country":"US",
    "sg:address":"1943 Forest Grove Rd",
    "sg:city":"Vineland",
    "sg:classifiers":[
        {
            "category":"Building & Trades",
            "subcategory":"Plumbing",
            "type":"Services"
        }
    ],
    "sg:phone":"+1 856 697 6770",
    "sg:postcode":"08360",
    "sg:province":"NJ",
    "sg:tags":[
        "plumbing",
        "contractor"
    ],
    "wof:name":"Crescitelli Inc Plumbing & Htg",
    "wof:placetype":"venue"
},
  "geometry": {"coordinates":[-74.970088,39.529538],"type":"Point"}
}