{
  "type": "Feature",
  "properties": {
    "iso:country":"US",
    "sg:address":"17 Gloria Ln",
    "sg:city":"Fairfield",
    "sg:classifiers":[
        {
            "category":"Restaurant",
            "type":"Food & Drink"
        }
    ],
    "sg:phone":"+1 973 882 3422",
    "sg:postcode":"07004",
    "sg:province":"NJ",
    "sg:tags":[
        "caterer"
    ],
    "wof:name":"Fairfield Manor",
    "wof:placetype":"venue"
},
  "geometry": {"coordinates":[-74.29409800000001,40.8745],"type":"Point"}
}