{
  "type": "Feature",
  "properties": {
    "addr:full":"7 Aberdeen Ct Cranford NJ 07016",
    "addr:housenumber":"7",
    "addr:postcode":"07016",
    "addr:street":"Aberdeen Ct",
    "iso:country":"US",
    "sg:address":"7 Aberdeen Ct",
    "sg:city":"Cranford",
    "sg:classifiers":[
        {
            "category":"Freight",
            "type":"Transportation"
        }
    ],
    "sg:phone":"+1 908 276 5973",
    "sg:postcode":"07016",
    "sg:province":"NJ",
    "sg:tags":[
        "operator",
        "local",
        "trucking"
    ],
    "wof:name":"D & D Trucking",
    "wof:placetype":"venue"
},
  "geometry": {"coordinates":[-74.307123,40.64159],"type":"Point"}
}