{
  "type": "Feature",
  "properties": {
    "iso:country":"US",
    "sg:address":"17 Woodgate Dr",
    "sg:city":"Monmouth Junction",
    "sg:classifiers":[
        {
            "category":"Autos & Motor Vehicles",
            "subcategory":"Fuel & Gas Station",
            "type":"Retail Goods"
        }
    ],
    "sg:phone":"+1   ",
    "sg:postcode":"08852",
    "sg:province":"NJ",
    "sg:tags":[
        "station",
        "gasoline"
    ],
    "wof:name":"Greenbrook Exxon",
    "wof:placetype":"venue"
},
  "geometry": {"coordinates":[-74.556738,40.409757],"type":"Point"}
}