{
  "type": "Feature",
  "properties": {
    "addr:full":"600 Jockey Hollow Rd Morristown NJ 07960",
    "addr:housenumber":"600",
    "addr:postcode":"07960",
    "addr:street":"Jockey Hollow Rd",
    "iso:country":"US",
    "sg:address":"600 Jockey Hollow Rd",
    "sg:city":"Morristown",
    "sg:classifiers":[
        {
            "category":"Organizations",
            "subcategory":"Religious Organization",
            "type":"Services"
        }
    ],
    "sg:phone":"+1 973 359 0359",
    "sg:postcode":"07960",
    "sg:province":"NJ",
    "wof:name":"Tabernacle of Faith Family Church",
    "wof:placetype":"venue"
},
  "geometry": {"coordinates":[-74.522581,40.774862],"type":"Point"}
}