{
  "type": "Feature",
  "properties": {
    "iso:country":"US",
    "sg:address":"3 Thomas Dr",
    "sg:city":"Englishtown",
    "sg:classifiers":[
        {
            "category":"Shopping",
            "subcategory":"Computers & Home Electronics",
            "type":"Retail Goods"
        }
    ],
    "sg:phone":"+1   ",
    "sg:postcode":"07726",
    "sg:province":"NJ",
    "sg:tags":[
        "store"
    ],
    "wof:name":"Tcg",
    "wof:placetype":"venue"
},
  "geometry": {"coordinates":[-74.33004099999999,40.289755],"type":"Point"}
}