{
  "type": "Feature",
  "properties": {
    "addr:full":"315 Curtis Ave Point Pleasant Beach NJ 08742",
    "addr:housenumber":"315",
    "addr:postcode":"08742",
    "addr:street":"Curtis Ave",
    "iso:country":"US",
    "sg:address":"315 Curtis Ave",
    "sg:city":"Point Pleasant Beach",
    "sg:classifiers":[
        {
            "category":"Professional",
            "type":"Services"
        }
    ],
    "sg:phone":"+1   ",
    "sg:postcode":"08742",
    "sg:province":"NJ",
    "wof:name":"Curtis R Leach",
    "wof:placetype":"venue"
},
  "geometry": {"coordinates":[-74.052255,40.096923],"type":"Point"}
}