{
  "type": "Feature",
  "properties": {
    "iso:country":"US",
    "sg:address":"55 S Prospect St",
    "sg:city":"Verona",
    "sg:classifiers":[
        {
            "category":"Manufacturing",
            "subcategory":"Tools & Machinery",
            "type":"Manufacturing & Wholesale Goods"
        }
    ],
    "sg:phone":"+1 973 239 1616",
    "sg:postcode":"07044",
    "sg:province":"NJ",
    "sg:tags":[
        "product",
        "mfg",
        "personal",
        "related",
        "server",
        "computer"
    ],
    "wof:name":"HP",
    "wof:placetype":"venue"
},
  "geometry": {"coordinates":[-74.251114,40.829665],"type":"Point"}
}