{
  "type": "Feature",
  "properties": {
    "addr:full":"5 N Black Horse Pike Runnemede NJ 08078",
    "addr:housenumber":"5",
    "addr:postcode":"08078",
    "addr:street":"N Black Horse Pike",
    "iso:country":"US",
    "sg:address":"5 N Black Horse Pike",
    "sg:city":"Runnemede",
    "sg:classifiers":[
        {
            "category":"Restaurant",
            "type":"Food & Drink"
        }
    ],
    "sg:phone":"+1   ",
    "sg:postcode":"08078",
    "sg:province":"NJ",
    "sg:tags":[
        "eating"
    ],
    "wof:name":"Subway",
    "wof:placetype":"venue"
},
  "geometry": {"coordinates":[-75.073184,39.849872],"type":"Point"}
}