{
  "type": "Feature",
  "properties": {
    "addr:full":"314 67th St West New York NJ 07093",
    "addr:housenumber":"314",
    "addr:postcode":"nj 07093",
    "addr:street":"67Th St West",
    "iso:country":"US",
    "sg:address":"314 67th St",
    "sg:city":"West New York",
    "sg:classifiers":[
        {
            "category":"Social Services",
            "subcategory":"Child Care",
            "type":"Services"
        }
    ],
    "sg:phone":"+1 201 662 7722",
    "sg:postcode":"07093",
    "sg:province":"NJ",
    "sg:tags":[
        "day"
    ],
    "wof:name":"Head Start North Hudson Community Action Corp",
    "wof:placetype":"venue"
},
  "geometry": {"coordinates":[-74.00946500000001,40.793023],"type":"Point"}
}