{
  "type": "Feature",
  "properties": {
    "iso:country":"US",
    "sg:address":"910 Beechwood Ave",
    "sg:city":"Cherry Hill",
    "sg:classifiers":[
        {
            "category":"Home & Garden",
            "subcategory":"Home Furnishings",
            "type":"Retail Goods"
        }
    ],
    "sg:phone":"+1 856 665 3200",
    "sg:postcode":"08002",
    "sg:province":"NJ",
    "sg:tags":[
        "decor"
    ],
    "wof:name":"Co-Frank Assoc",
    "wof:placetype":"venue"
},
  "geometry": {"coordinates":[-75.047798,39.931099],"type":"Point"}
}