{
  "type": "Feature",
  "properties": {
    "addr:full":"12 Wardell Ave Rumson NJ 07760",
    "addr:housenumber":"12",
    "addr:postcode":"07760",
    "addr:street":"Wardell Ave",
    "iso:country":"US",
    "sg:address":"12 Wardell Ave",
    "sg:city":"Rumson",
    "sg:classifiers":[
        {
            "category":"Professional",
            "subcategory":"Business Services",
            "type":"Services"
        }
    ],
    "sg:phone":"+1   ",
    "sg:postcode":"07760",
    "sg:province":"NJ",
    "wof:name":"Interactive Webradio Co",
    "wof:placetype":"venue"
},
  "geometry": {"coordinates":[-74.024878,40.343311],"type":"Point"}
}