{
  "type": "Feature",
  "properties": {
    "addr:full":"298 Main St Hackensack NJ 07601",
    "addr:housenumber":"298",
    "addr:postcode":"07601",
    "addr:street":"Main St",
    "iso:country":"US",
    "sg:address":"298 Main St",
    "sg:city":"Hackensack",
    "sg:classifiers":[
        {
            "category":"Personal",
            "subcategory":"Beauty Salon",
            "type":"Services"
        }
    ],
    "sg:phone":"+1 201 343 6886",
    "sg:postcode":"07601",
    "sg:province":"NJ",
    "sg:tags":[
        "shop"
    ],
    "wof:name":"Santa's Beauty Salon",
    "wof:placetype":"venue"
},
  "geometry": {"coordinates":[-74.040666,40.887866],"type":"Point"}
}