{
  "type": "Feature",
  "properties": {
    "addr:full":"1255 State Rte 35 Middletown NJ 07748",
    "addr:housenumber":"1255",
    "addr:postcode":"07748",
    "addr:street":"State Rte 35",
    "iso:country":"US",
    "sg:address":"1255 State Rte 35",
    "sg:city":"Middletown",
    "sg:classifiers":[
        {
            "category":"Retail",
            "subcategory":"Auto Rental",
            "type":"Services"
        }
    ],
    "sg:phone":"+1 732 957 0800",
    "sg:postcode":"07748",
    "sg:province":"NJ",
    "sg:tags":[
        "passenger",
        "car"
    ],
    "wof:name":"Discount Auto Rental",
    "wof:placetype":"venue"
},
  "geometry": {"coordinates":[-74.114092,40.398686],"type":"Point"}
}