{
  "type": "Feature",
  "properties": {
    "addr:full":"100 W Charles St Palmyra NJ 08065",
    "addr:housenumber":"100",
    "addr:postcode":"08065",
    "addr:street":"W Charles St",
    "iso:country":"US",
    "sg:address":"100 W Charles St",
    "sg:city":"Palmyra",
    "sg:classifiers":[
        {
            "category":"Education",
            "subcategory":"School",
            "type":"Public Place"
        }
    ],
    "sg:phone":"+1 856 829 3601",
    "sg:postcode":"08065",
    "sg:province":"NJ",
    "sg:tags":[
        "high",
        "middle",
        "elementary"
    ],
    "wof:name":"Palmyra Borough School District",
    "wof:placetype":"venue"
},
  "geometry": {"coordinates":[-75.021756,39.998092],"type":"Point"}
}