{
  "type": "Feature",
  "properties": {
    "iso:country":"US",
    "sg:address":"94 Vollers Dr",
    "sg:city":"Somerville",
    "sg:classifiers":[
        {
            "category":"Professional",
            "subcategory":"Computer Services",
            "type":"Services"
        }
    ],
    "sg:phone":"+1 908 707 8566",
    "sg:postcode":"08876",
    "sg:province":"NJ",
    "sg:tags":[
        "design",
        "system"
    ],
    "wof:name":"Captive Web Design",
    "wof:placetype":"venue"
},
  "geometry": {"coordinates":[-74.701595,40.589352],"type":"Point"}
}