{
  "type": "Feature",
  "properties": {
    "iso:country":"US",
    "sg:address":"1035 Irving Pl",
    "sg:city":"Toms River",
    "sg:classifiers":[
        {
            "category":"Professional",
            "type":"Services"
        }
    ],
    "sg:phone":"+1   ",
    "sg:postcode":"08755",
    "sg:province":"NJ",
    "wof:name":"Move",
    "wof:placetype":"venue"
},
  "geometry": {"coordinates":[-74.242069,39.976619],"type":"Point"}
}