{
  "type": "Feature",
  "properties": {
    "addr:full":"184 Smith St Perth Amboy NJ 08861",
    "addr:housenumber":"184",
    "addr:postcode":"08861",
    "addr:street":"Smith St",
    "iso:country":"US",
    "sg:address":"184 Smith St",
    "sg:city":"Perth Amboy",
    "sg:classifiers":[
        {
            "category":"Shopping",
            "subcategory":"Photographic Equipment",
            "type":"Retail Goods"
        }
    ],
    "sg:phone":"+1 732 826 0048",
    "sg:postcode":"08861",
    "sg:province":"NJ",
    "sg:tags":[
        "supply"
    ],
    "sg:website":"www.fishkinbros.com",
    "wof:name":"Fishkin Brothers Inc",
    "wof:placetype":"venue"
},
  "geometry": {"coordinates":[-74.270409,40.509288],"type":"Point"}
}