{
  "type": "Feature",
  "properties": {
    "addr:full":"1308 Centennial Ave Piscataway NJ 08854",
    "addr:housenumber":"1308",
    "addr:postcode":"08854",
    "addr:street":"Centennial Ave",
    "iso:country":"US",
    "sg:address":"1308 Centennial Ave",
    "sg:city":"Piscataway",
    "sg:classifiers":[
        {
            "category":"Shopping",
            "subcategory":"Jewelry",
            "type":"Retail Goods"
        }
    ],
    "sg:phone":"+1   ",
    "sg:postcode":"08854",
    "sg:province":"NJ",
    "sg:tags":[
        "sales",
        "internet"
    ],
    "wof:name":"Phoenix Commercial Development",
    "wof:placetype":"venue"
},
  "geometry": {"coordinates":[-74.451534,40.551872],"type":"Point"}
}