{
  "type": "Feature",
  "properties": {
    "addr:full":"301 Main St Center City Mall Upper Level Food Court Paterson NJ 07505",
    "addr:housenumber":"301",
    "addr:postcode":"paterson;07505",
    "addr:street":"Main St;Upper",
    "iso:country":"US",
    "sg:address":"301 Main St Center City Mall Upper Level Food Court",
    "sg:city":"Paterson",
    "sg:classifiers":[
        {
            "category":"Restaurant",
            "type":"Food & Drink"
        }
    ],
    "sg:phone":"+1 973 345 1100",
    "sg:postcode":"07505",
    "sg:province":"NJ",
    "sg:tags":[
        "pizza"
    ],
    "wof:name":"Center City Pizza",
    "wof:placetype":"venue"
},
  "geometry": {"coordinates":[-74.173393,40.914834],"type":"Point"}
}