{
  "type": "Feature",
  "properties": {
    "addr:full":"800 Ocean Ter Seaside Heights NJ 08751",
    "addr:housenumber":"800",
    "addr:postcode":"08751",
    "addr:street":"Ocean Ter;Heights",
    "iso:country":"US",
    "sg:address":"800 Ocean Ter",
    "sg:city":"Seaside Heights",
    "sg:classifiers":[
        {
            "category":"Recreation",
            "subcategory":"Amusement Park",
            "type":"Entertainment"
        }
    ],
    "sg:phone":"+1 732 793 6489",
    "sg:postcode":"08751",
    "sg:province":"NJ",
    "sg:website":"www.casinopiernj.com",
    "wof:name":"Venice Amusement Corp",
    "wof:placetype":"venue"
},
  "geometry": {"coordinates":[-74.070875,39.943177],"type":"Point"}
}