{
  "type": "Feature",
  "properties": {
    "addr:full":"89 Louis Ave Middlesex NJ 08846",
    "addr:housenumber":"89",
    "addr:postcode":"08846",
    "addr:street":"Louis Ave",
    "iso:country":"US",
    "sg:address":"89 Louis Ave",
    "sg:city":"Middlesex",
    "sg:classifiers":[
        {
            "category":"Professional",
            "subcategory":"Business Services",
            "type":"Services"
        }
    ],
    "sg:phone":"+1   ",
    "sg:postcode":"08846",
    "sg:province":"NJ",
    "wof:name":"Fun Bus",
    "wof:placetype":"venue"
},
  "geometry": {"coordinates":[-74.50789399999999,40.583442],"type":"Point"}
}