{
  "type": "Feature",
  "properties": {
    "addr:full":"4259 US Hwy 130 Beverly NJ 08010",
    "addr:housenumber":"4259",
    "addr:postcode":"08010",
    "addr:street":"Us Hwy 130",
    "iso:country":"US",
    "sg:address":"4259 US Hwy 130",
    "sg:city":"Beverly",
    "sg:classifiers":[
        {
            "category":"Professional",
            "subcategory":"Business Services",
            "type":"Services"
        }
    ],
    "sg:phone":"+1 609 871 9300",
    "sg:postcode":"08010",
    "sg:province":"NJ",
    "sg:tags":[
        "appraiser"
    ],
    "wof:name":"AAR Appraisals",
    "wof:placetype":"venue"
},
  "geometry": {"coordinates":[-74.908952,40.04322],"type":"Point"}
}