{
  "type": "Feature",
  "properties": {
    "addr:full":"388-A Rte 46 W Parsippany NJ 07054",
    "addr:housenumber":"388-a",
    "addr:postcode":"07054",
    "addr:street":"Rte 46 W",
    "iso:country":"US",
    "sg:address":"388-A Rte 46 W",
    "sg:city":"Parsippany",
    "sg:classifiers":[
        {
            "category":"Arena",
            "subcategory":"Sports Club",
            "type":"Entertainment"
        }
    ],
    "sg:phone":"+1 973 227 8880",
    "sg:postcode":"07054",
    "sg:province":"NJ",
    "sg:tags":[
        "martial art"
    ],
    "sg:website":"www.wushukungfunj.com",
    "wof:name":"Wushu Kungfu Fitness Center",
    "wof:placetype":"venue"
},
  "geometry": {"coordinates":[-74.36063,40.860193],"type":"Point"}
}