{
  "type": "Feature",
  "properties": {
    "iso:country":"US",
    "sg:address":"840 N Lenola Rd",
    "sg:city":"Moorestown",
    "sg:classifiers":[
        {
            "category":"Real Estate",
            "subcategory":"Real Estate Agent",
            "type":"Services"
        }
    ],
    "sg:phone":"+1 856 273 7681",
    "sg:postcode":"08057",
    "sg:province":"NJ",
    "wof:name":"Mack Cali Realty Corp",
    "wof:placetype":"venue"
},
  "geometry": {"coordinates":[-74.99020400000001,39.96913],"type":"Point"}
}