{
  "type": "Feature",
  "properties": {
    "addr:full":"485 Broadway Newark NJ 07104",
    "addr:housenumber":"485",
    "addr:postcode":"07104",
    "addr:street":"Broadway",
    "iso:country":"US",
    "sg:address":"485 Broadway",
    "sg:city":"Newark",
    "sg:classifiers":[
        {
            "category":"Shopping",
            "subcategory":"Pharmacy",
            "type":"Retail Goods"
        }
    ],
    "sg:phone":"+1   ",
    "sg:postcode":"07104",
    "sg:province":"NJ",
    "sg:tags":[
        "beauty",
        "supply"
    ],
    "wof:name":"K-Moni Inc",
    "wof:placetype":"venue"
},
  "geometry": {"coordinates":[-74.164723,40.766075],"type":"Point"}
}