{
  "type": "Feature",
  "properties": {
    "addr:full":"441 W Side Ave Jersey City NJ 07304",
    "addr:housenumber":"441",
    "addr:postcode":"07304",
    "addr:street":"W Side Ave",
    "iso:country":"US",
    "sg:address":"441 W Side Ave",
    "sg:city":"Jersey City",
    "sg:classifiers":[
        {
            "category":"Shopping",
            "subcategory":"Books",
            "type":"Retail Goods"
        }
    ],
    "sg:phone":"+1   ",
    "sg:postcode":"07304",
    "sg:province":"NJ",
    "sg:tags":[
        "religious"
    ],
    "wof:name":"Jesus The Redeemer",
    "wof:placetype":"venue"
},
  "geometry": {"coordinates":[-74.08556799999999,40.716542],"type":"Point"}
}