{
  "type": "Feature",
  "properties": {
    "iso:country":"US",
    "sg:address":"24 Rosewood Ct",
    "sg:city":"Sayreville",
    "sg:classifiers":[
        {
            "category":"Wholesale",
            "subcategory":"Machinery & Supplies",
            "type":"Manufacturing & Wholesale Goods"
        }
    ],
    "sg:phone":"+1 732 257 1750",
    "sg:postcode":"08872",
    "sg:province":"NJ",
    "sg:tags":[
        "distributor",
        "fastener"
    ],
    "wof:name":"Precision Parts Inc",
    "wof:placetype":"venue"
},
  "geometry": {"coordinates":[-74.333382,40.471272],"type":"Point"}
}