{
  "type": "Feature",
  "properties": {
    "addr:full":"10 Gladys Ave Manville NJ 08835",
    "addr:housenumber":"10",
    "addr:postcode":"08835",
    "addr:street":"Gladys Ave",
    "iso:country":"US",
    "sg:address":"10 Gladys Ave",
    "sg:city":"Manville",
    "sg:classifiers":[
        {
            "category":"Government",
            "subcategory":"Office",
            "type":"Public Place"
        }
    ],
    "sg:phone":"+1   ",
    "sg:postcode":"08835",
    "sg:province":"NJ",
    "sg:tags":[
        "department",
        "works"
    ],
    "wof:name":"Public Works Department",
    "wof:placetype":"venue"
},
  "geometry": {"coordinates":[-74.587571,40.538382],"type":"Point"}
}