{
  "type": "Feature",
  "properties": {
    "iso:country":"US",
    "sg:address":"1122 US Highway 22",
    "sg:city":"Mountainside",
    "sg:classifiers":[
        {
            "category":"Professional",
            "subcategory":"Lawyer & Legal Services",
            "type":"Services"
        }
    ],
    "sg:phone":"+1 908 233 0024",
    "sg:postcode":"07092",
    "sg:province":"NJ",
    "wof:name":"Agnes S Wladyka Llc",
    "wof:placetype":"venue"
},
  "geometry": {"coordinates":[-74.341087,40.68112],"type":"Point"}
}