{
  "type": "Feature",
  "properties": {
    "iso:country":"US",
    "sg:address":"514 Tilden Ave",
    "sg:city":"Teaneck",
    "sg:classifiers":[
        {
            "category":"Professional",
            "subcategory":"Management & Consulting",
            "type":"Services"
        },
        {
            "category":"Professional",
            "subcategory":"Computer Services",
            "type":"Services"
        }
    ],
    "sg:phone":"+1 201 928 1495",
    "sg:postcode":"07666",
    "sg:province":"NJ",
    "sg:tags":[
        "information",
        "retrieval"
    ],
    "wof:name":"Emrdbs LLC",
    "wof:placetype":"venue"
},
  "geometry": {"coordinates":[-74.02471,40.892176],"type":"Point"}
}