{
  "type": "Feature",
  "properties": {
    "iso:country":"US",
    "sg:address":"36 Broad St",
    "sg:city":"Manasquan",
    "sg:classifiers":[
        {
            "category":"Professional",
            "subcategory":"Computer Services",
            "type":"Services"
        }
    ],
    "sg:phone":"+1 732 528 7635",
    "sg:postcode":"08736",
    "sg:province":"NJ",
    "wof:name":"Sure Solutions",
    "wof:placetype":"venue"
},
  "geometry": {"coordinates":[-74.04934,40.125996],"type":"Point"}
}