{
  "type": "Feature",
  "properties": {
    "addr:full":"109 Falmouth Ave Elmwood Park NJ 07407",
    "addr:housenumber":"109",
    "addr:postcode":"07407",
    "addr:street":"Falmouth Ave",
    "iso:country":"US",
    "sg:address":"109 Falmouth Ave",
    "sg:city":"Elmwood Park",
    "sg:classifiers":[
        {
            "category":"Home & Garden",
            "subcategory":"Building Materials",
            "type":"Retail Goods"
        }
    ],
    "sg:phone":"+1 201 398 0222",
    "sg:postcode":"07407",
    "sg:province":"NJ",
    "sg:tags":[
        "plumbing",
        "fixture",
        "supply"
    ],
    "wof:name":"A 1 Luxury Bathrooms & Ktchns",
    "wof:placetype":"venue"
},
  "geometry": {"coordinates":[-74.12384,40.909469],"type":"Point"}
}