{
  "type": "Feature",
  "properties": {
    "iso:country":"US",
    "sg:address":"45 Rensselaer Rd",
    "sg:city":"Essex Fells",
    "sg:classifiers":[
        {
            "category":"Health Services",
            "subcategory":"Doctor",
            "type":"Services"
        }
    ],
    "sg:phone":"+1 973 228 6152",
    "sg:postcode":"07021",
    "sg:province":"NJ",
    "sg:tags":[
        "medical"
    ],
    "wof:name":"Laszlo Fuzesi M D P A",
    "wof:placetype":"venue"
},
  "geometry": {"coordinates":[-74.275812,40.829318],"type":"Point"}
}