{
  "type": "Feature",
  "properties": {
    "iso:country":"US",
    "sg:address":"504 Campus Dr",
    "sg:city":"Williamstown",
    "sg:classifiers":[
        {
            "category":"Health Services",
            "subcategory":"Clinic",
            "type":"Services"
        }
    ],
    "sg:phone":"+1   ",
    "sg:postcode":"08094",
    "sg:province":"NJ",
    "sg:tags":[
        "home",
        "care"
    ],
    "wof:name":"Facility Health Care",
    "wof:placetype":"venue"
},
  "geometry": {"coordinates":[-74.97377299999999,39.69535],"type":"Point"}
}