{
  "type": "Feature",
  "properties": {
    "iso:country":"US",
    "sg:address":"109 1st St",
    "sg:city":"Dover",
    "sg:classifiers":[
        {
            "category":"Building & Trades",
            "subcategory":"Construction",
            "type":"Services"
        }
    ],
    "sg:phone":"+1 973 989 0053",
    "sg:postcode":"07801",
    "sg:province":"NJ",
    "sg:tags":[
        "painter"
    ],
    "wof:name":"Jersey Painting",
    "wof:placetype":"venue"
},
  "geometry": {"coordinates":[-74.557025,40.879005],"type":"Point"}
}