{
  "type": "Feature",
  "properties": {
    "addr:full":"349 East Northfield Rd Suite 214 Livingston NJ 07039",
    "addr:housenumber":"349",
    "addr:postcode":"07039",
    "addr:street":"East Northfield Rd Suite 214",
    "iso:country":"US",
    "sg:address":"349 East Northfield Rd Suite 214",
    "sg:city":"Livingston",
    "sg:classifiers":[
        {
            "category":"Health Services",
            "subcategory":"Dentist",
            "type":"Services"
        }
    ],
    "sg:phone":"+1 973 992 3990",
    "sg:postcode":"07039",
    "sg:province":"NJ",
    "sg:website":"www.ReadyToSmile.com",
    "wof:name":"The Silverstrom Group",
    "wof:placetype":"venue"
},
  "geometry": {"coordinates":[-74.29951,40.77027],"type":"Point"}
}