{
  "type": "Feature",
  "properties": {
    "addr:full":"11 Fisher Pl North Arlington NJ 07031",
    "addr:housenumber":"11",
    "addr:postcode":"07031",
    "addr:street":"Fisher Pl North",
    "iso:country":"US",
    "sg:address":"11 Fisher Pl",
    "sg:city":"North Arlington",
    "sg:classifiers":[
        {
            "category":"Professional",
            "subcategory":"Management & Consulting",
            "type":"Services"
        }
    ],
    "sg:phone":"+1   ",
    "sg:postcode":"07031",
    "sg:province":"NJ",
    "sg:tags":[
        "business"
    ],
    "wof:name":"Howard M Brady",
    "wof:placetype":"venue"
},
  "geometry": {"coordinates":[-74.14398799999999,40.787695],"type":"Point"}
}