{
  "type": "Feature",
  "properties": {
    "iso:country":"US",
    "sg:address":"91 Evergreen Ave",
    "sg:city":"Bloomfield",
    "sg:classifiers":[
        {
            "category":"Professional",
            "type":"Services"
        }
    ],
    "sg:phone":"+1 973 743 7771",
    "sg:postcode":"07003",
    "sg:province":"NJ",
    "sg:tags":[
        "establishment"
    ],
    "wof:name":"Smede International Inc",
    "wof:placetype":"venue"
},
  "geometry": {"coordinates":[-74.20619000000001,40.788383],"type":"Point"}
}