{
  "type": "Feature",
  "properties": {
    "iso:country":"US",
    "sg:address":"39 Church St",
    "sg:city":"Bloomsbury",
    "sg:classifiers":[
        {
            "category":"Restaurant",
            "type":"Food & Drink"
        }
    ],
    "sg:phone":"+1 908 479 6100",
    "sg:postcode":"08804",
    "sg:province":"NJ",
    "wof:name":"Cracker Barrel Corners Store",
    "wof:placetype":"venue"
},
  "geometry": {"coordinates":[-75.08796,40.654832],"type":"Point"}
}