{
  "type": "Feature",
  "properties": {
    "iso:country":"US",
    "sg:address":"220 W Clinton Ave",
    "sg:city":"Oaklyn",
    "sg:classifiers":[
        {
            "category":"Professional",
            "type":"Services"
        }
    ],
    "sg:phone":"+1   ",
    "sg:postcode":"08107",
    "sg:province":"NJ",
    "wof:name":"Isothermo",
    "wof:placetype":"venue"
},
  "geometry": {"coordinates":[-75.083096,39.901225],"type":"Point"}
}