{
  "type": "Feature",
  "properties": {
    "addr:full":"102 Oak St Ridgewood NJ 07450",
    "addr:housenumber":"102",
    "addr:postcode":"07450",
    "addr:street":"Oak St",
    "iso:country":"US",
    "sg:address":"102 Oak St",
    "sg:city":"Ridgewood",
    "sg:classifiers":[
        {
            "category":"Professional",
            "subcategory":"Computer Services",
            "type":"Services"
        }
    ],
    "sg:phone":"+1 201 652 1898",
    "sg:postcode":"07450",
    "sg:province":"NJ",
    "sg:tags":[
        "internet"
    ],
    "sg:website":"www.fourlinks.com",
    "wof:name":"FOURLINKS.COM",
    "wof:placetype":"venue"
},
  "geometry": {"coordinates":[-74.11696499999999,40.982971],"type":"Point"}
}