{
  "type": "Feature",
  "properties": {
    "iso:country":"US",
    "sg:address":"4092 E Main St",
    "sg:city":"Millville",
    "sg:classifiers":[
        {
            "category":"Retail",
            "subcategory":"Auto Repair",
            "type":"Services"
        }
    ],
    "sg:phone":"+1 856 825 4998",
    "sg:postcode":"08332",
    "sg:province":"NJ",
    "sg:tags":[
        "body",
        "automotive"
    ],
    "wof:name":"Bee Bros Auto Body & Repair",
    "wof:placetype":"venue"
},
  "geometry": {"coordinates":[-74.963875,39.379164],"type":"Point"}
}