{
  "type": "Feature",
  "properties": {
    "addr:full":"156 Westervelt Ave Hawthorne NJ 07506",
    "addr:housenumber":"156",
    "addr:postcode":"07506",
    "addr:street":"Westervelt Ave",
    "iso:country":"US",
    "sg:address":"156 Westervelt Ave",
    "sg:city":"Hawthorne",
    "sg:classifiers":[
        {
            "category":"Building & Trades",
            "subcategory":"Construction",
            "type":"Services"
        }
    ],
    "sg:phone":"+1 973 423 4222",
    "sg:postcode":"07506",
    "sg:province":"NJ",
    "sg:tags":[
        "general",
        "contractor"
    ],
    "wof:name":"GSN",
    "wof:placetype":"venue"
},
  "geometry": {"coordinates":[-74.16871399999999,40.939972],"type":"Point"}
}