{
  "type": "Feature",
  "properties": {
    "iso:country":"US",
    "sg:address":"805 Caldwell Ave",
    "sg:city":"Union",
    "sg:classifiers":[
        {
            "category":"Real Estate",
            "subcategory":"Real Estate Operator",
            "type":"Services"
        }
    ],
    "sg:phone":"+1   ",
    "sg:postcode":"07083",
    "sg:province":"NJ",
    "sg:tags":[
        "building",
        "apartment"
    ],
    "wof:name":"Court Apartments",
    "wof:placetype":"venue"
},
  "geometry": {"coordinates":[-74.281567,40.691993],"type":"Point"}
}