{
  "type": "Feature",
  "properties": {
    "iso:country":"US",
    "sg:address":"507 Main St",
    "sg:city":"Belleville",
    "sg:classifiers":[
        {
            "category":"Manufacturing",
            "subcategory":"Food",
            "type":"Manufacturing & Wholesale Goods"
        }
    ],
    "sg:phone":"+1 973 812 8118",
    "sg:postcode":"07109",
    "sg:province":"NJ",
    "sg:tags":[
        "product",
        "manufacturer"
    ],
    "wof:name":"Bindi North America",
    "wof:placetype":"venue"
},
  "geometry": {"coordinates":[-74.140186,40.798522],"type":"Point"}
}