{
  "type": "Feature",
  "properties": {
    "iso:country":"US",
    "sg:address":"371 George St",
    "sg:city":"New Brunswick",
    "sg:classifiers":[
        {
            "category":"Retail",
            "subcategory":"Repair Shop",
            "type":"Services"
        }
    ],
    "sg:phone":"+1   ",
    "sg:postcode":"08901",
    "sg:province":"NJ",
    "wof:name":"A 1 24 Hour 7 Day Emerg A Lock",
    "wof:placetype":"venue"
},
  "geometry": {"coordinates":[-74.44403200000001,40.495956],"type":"Point"}
}