{
  "type": "Feature",
  "properties": {
    "addr:full":"226 Grande River Blvd Toms River NJ 08755",
    "addr:housenumber":"226",
    "addr:postcode":"08755",
    "addr:street":"Grande River Blvd",
    "iso:country":"US",
    "sg:address":"226 Grande River Blvd",
    "sg:city":"Toms River",
    "sg:classifiers":[
        {
            "category":"Building & Trades",
            "subcategory":"Equipment Rental",
            "type":"Services"
        }
    ],
    "sg:phone":"+1 732 736 0300",
    "sg:postcode":"08755",
    "sg:province":"NJ",
    "wof:name":"Stork Rentals",
    "wof:placetype":"venue"
},
  "geometry": {"coordinates":[-74.23877,40.028441],"type":"Point"}
}