{
  "type": "Feature",
  "properties": {
    "iso:country":"US",
    "sg:address":"12 Austin Pl",
    "sg:city":"Bloomfield",
    "sg:classifiers":[
        {
            "category":"Professional",
            "type":"Services"
        }
    ],
    "sg:phone":"+1 973 680 0300",
    "sg:postcode":"07003",
    "sg:province":"NJ",
    "sg:tags":[
        "establishment"
    ],
    "wof:name":"Literacy Volunteers Of America",
    "wof:placetype":"venue"
},
  "geometry": {"coordinates":[-74.19548399999999,40.794971],"type":"Point"}
}