{
  "type": "Feature",
  "properties": {
    "addr:full":"367 Queen Anne Rd Teaneck NJ 07666",
    "addr:housenumber":"367",
    "addr:postcode":"07666",
    "addr:street":"Queen Anne Rd",
    "iso:country":"US",
    "sg:address":"367 Queen Anne Rd",
    "sg:city":"Teaneck",
    "sg:classifiers":[
        {
            "category":"Retail",
            "subcategory":"Laundry & Dry Cleaning",
            "type":"Services"
        }
    ],
    "sg:phone":"+1   ",
    "sg:postcode":"07666",
    "sg:province":"NJ",
    "sg:tags":[
        "power"
    ],
    "wof:name":"Modern Launderette",
    "wof:placetype":"venue"
},
  "geometry": {"coordinates":[-74.02053600000001,40.875302],"type":"Point"}
}