{
  "type": "Feature",
  "properties": {
    "addr:full":"28 Basset Ct Neptune NJ 07753",
    "addr:housenumber":"28",
    "addr:postcode":"07753",
    "addr:street":"Basset Ct",
    "iso:country":"US",
    "sg:address":"28 Basset Ct",
    "sg:city":"Neptune",
    "sg:classifiers":[
        {
            "category":"Education",
            "subcategory":"Dance Studio",
            "type":"Public Place"
        }
    ],
    "sg:phone":"+1   ",
    "sg:postcode":"07753",
    "sg:province":"NJ",
    "wof:name":"Rhythms In Dance Inc",
    "wof:placetype":"venue"
},
  "geometry": {"coordinates":[-74.095556,40.236185],"type":"Point"}
}