{
  "type": "Feature",
  "properties": {
    "addr:full":"16 Beechwood Dr Hillsdale NJ 07642",
    "addr:housenumber":"16",
    "addr:postcode":"07642",
    "addr:street":"Beechwood Dr",
    "iso:country":"US",
    "sg:address":"16 Beechwood Dr",
    "sg:city":"Hillsdale",
    "sg:classifiers":[
        {
            "category":"Professional",
            "type":"Services"
        }
    ],
    "sg:phone":"+1 609 448 2597",
    "sg:postcode":"07642",
    "sg:province":"NJ",
    "sg:tags":[
        "establishment"
    ],
    "wof:name":"Wirth & Wirth",
    "wof:placetype":"venue"
},
  "geometry": {"coordinates":[-74.04035399999999,40.999427],"type":"Point"}
}