{
  "type": "Feature",
  "properties": {
    "addr:full":"3116 Brigantine Blvd Brigantine NJ 08203",
    "addr:housenumber":"3116",
    "addr:postcode":"08203",
    "addr:street":"Brigantine Blvd",
    "iso:country":"US",
    "sg:address":"3116 Brigantine Blvd",
    "sg:city":"Brigantine",
    "sg:classifiers":[
        {
            "category":"Home & Garden",
            "subcategory":"Hardware",
            "type":"Retail Goods"
        }
    ],
    "sg:phone":"+1   ",
    "sg:postcode":"08203",
    "sg:province":"NJ",
    "wof:name":"True Value",
    "wof:placetype":"venue"
},
  "geometry": {"coordinates":[-74.38613100000001,39.394813],"type":"Point"}
}