{
  "type": "Feature",
  "properties": {
    "iso:country":"US",
    "sg:address":"2825 Marne Hwy",
    "sg:city":"Hainesport",
    "sg:classifiers":[
        {
            "category":"Restaurant",
            "type":"Food & Drink"
        }
    ],
    "sg:phone":"+1 609 261 9631",
    "sg:postcode":"08036",
    "sg:province":"NJ",
    "sg:tags":[
        "eating"
    ],
    "wof:name":"Aziza's Restaurant",
    "wof:placetype":"venue"
},
  "geometry": {"coordinates":[-74.856238,39.980179],"type":"Point"}
}