{
  "type": "Feature",
  "properties": {
    "addr:full":"3345 Us Highway 9 Old Bridge NJ 08857",
    "addr:housenumber":"3345",
    "addr:postcode":"08857",
    "addr:street":"Us Highway 9",
    "iso:country":"US",
    "sg:address":"3345 Us Highway 9",
    "sg:city":"Old Bridge",
    "sg:classifiers":[
        {
            "category":"Restaurant",
            "type":"Food & Drink"
        }
    ],
    "sg:menulink":"http://www.allmenus.com/nj/old-bridge/32901-tropical-hut/menu/",
    "sg:phone":"+1 732 679 7010",
    "sg:postcode":"08857",
    "sg:province":"NJ",
    "sg:tags":[
        "asian",
        "chinese"
    ],
    "wof:name":"Tropical Hut",
    "wof:placetype":"venue"
},
  "geometry": {"coordinates":[-74.30792099999999,40.386986],"type":"Point"}
}