{
  "type": "Feature",
  "properties": {
    "iso:country":"US",
    "sg:address":"771 River Rd",
    "sg:city":"Fair Haven",
    "sg:classifiers":[
        {
            "category":"Shopping",
            "subcategory":"Clothing, Apparel, & Fashions",
            "type":"Retail Goods"
        }
    ],
    "sg:phone":"+1   ",
    "sg:postcode":"07704",
    "sg:province":"NJ",
    "wof:name":"Yee Studio",
    "wof:placetype":"venue"
},
  "geometry": {"coordinates":[-74.034629,40.364909],"type":"Point"}
}