{
  "type": "Feature",
  "properties": {
    "iso:country":"US",
    "sg:address":"25 Broad Ave",
    "sg:city":"Palisades Park",
    "sg:classifiers":[
        {
            "category":"Personal",
            "subcategory":"Beauty Salon",
            "type":"Services"
        }
    ],
    "sg:phone":"+1   ",
    "sg:postcode":"07650",
    "sg:province":"NJ",
    "sg:tags":[
        "shop"
    ],
    "wof:name":"Onix Beauty Academy",
    "wof:placetype":"venue"
},
  "geometry": {"coordinates":[-74.001772,40.842404],"type":"Point"}
}