{
  "type": "Feature",
  "properties": {
    "iso:country":"US",
    "sg:address":"26 Madison Ave",
    "sg:city":"Morristown",
    "sg:classifiers":[
        {
            "category":"Health Services",
            "subcategory":"Doctor",
            "type":"Services"
        }
    ],
    "sg:phone":"+1 973 889 0200",
    "sg:postcode":"07960",
    "sg:province":"NJ",
    "sg:tags":[
        "medical"
    ],
    "wof:name":"Esra Onat MD",
    "wof:placetype":"venue"
},
  "geometry": {"coordinates":[-74.471045,40.788827],"type":"Point"}
}