{
  "type": "Feature",
  "properties": {
    "addr:full":"298 Naughright Rd Long Valley NJ 07853",
    "addr:housenumber":"298",
    "addr:postcode":"07853",
    "addr:street":"Naughright Rd",
    "iso:country":"US",
    "sg:address":"298 Naughright Rd",
    "sg:city":"Long Valley",
    "sg:classifiers":[
        {
            "category":"Building & Trades",
            "subcategory":"Landscaping Services",
            "type":"Services"
        }
    ],
    "sg:phone":"+1 908 876 1718",
    "sg:postcode":"07853",
    "sg:province":"NJ",
    "sg:tags":[
        "landscape"
    ],
    "wof:name":"R&D Landscape",
    "wof:placetype":"venue"
},
  "geometry": {"coordinates":[-74.785251,40.815969],"type":"Point"}
}