{
  "type": "Feature",
  "properties": {
    "addr:full":"25 Newark Pompton Tpke Pequannock NJ 07440",
    "addr:housenumber":"25",
    "addr:postcode":"07440",
    "addr:street":"Newark Pompton Tpke",
    "iso:country":"US",
    "sg:address":"25 Newark Pompton Tpke",
    "sg:city":"Pequannock",
    "sg:classifiers":[
        {
            "category":"Building & Trades",
            "subcategory":"Locksmith",
            "type":"Services"
        }
    ],
    "sg:phone":"+1 973 854 5680",
    "sg:postcode":"07440",
    "sg:province":"NJ",
    "sg:tags":[
        "key"
    ],
    "wof:name":"0 0 24 Hour 7 Day A Emergency Locksmith",
    "wof:placetype":"venue"
},
  "geometry": {"coordinates":[-74.281885,40.944408],"type":"Point"}
}