{
  "type": "Feature",
  "properties": {
    "iso:country":"US",
    "sg:address":"108 Hominy Hill Rd",
    "sg:city":"Colts Neck",
    "sg:classifiers":[
        {
            "category":"Retail",
            "subcategory":"Portrait Studio",
            "type":"Services"
        }
    ],
    "sg:phone":"+1 732 866 6942",
    "sg:postcode":"07722",
    "sg:province":"NJ",
    "sg:tags":[
        "photography"
    ],
    "wof:name":"Buena Vista Studio Photography",
    "wof:placetype":"venue"
},
  "geometry": {"coordinates":[-74.18754199999999,40.277756],"type":"Point"}
}