{
  "type": "Feature",
  "properties": {
    "iso:country":"US",
    "sg:address":"128 Market St",
    "sg:city":"Newark",
    "sg:classifiers":[
        {
            "category":"Professional",
            "type":"Services"
        }
    ],
    "sg:phone":"+1   ",
    "sg:postcode":"07102",
    "sg:province":"NJ",
    "wof:name":"KOOL Zone",
    "wof:placetype":"venue"
},
  "geometry": {"coordinates":[-74.174605,40.736265],"type":"Point"}
}