{
  "type": "Feature",
  "properties": {
    "addr:full":"220 N Centre St Merchantville NJ 08109",
    "addr:housenumber":"220",
    "addr:postcode":"08109",
    "addr:street":"N Centre St",
    "iso:country":"US",
    "sg:address":"220 N Centre St",
    "sg:city":"Merchantville",
    "sg:classifiers":[
        {
            "category":"Banks & Credit Unions",
            "subcategory":"Investment Brokerage",
            "type":"Services"
        },
        {
            "category":"Insurance",
            "subcategory":"Hazard Insurance",
            "type":"Services"
        }
    ],
    "sg:phone":"+1 856 663 4343",
    "sg:postcode":"08109",
    "sg:province":"NJ",
    "sg:tags":[
        "agent",
        "resume"
    ],
    "wof:name":"Secured Service Plan Corporation",
    "wof:placetype":"venue"
},
  "geometry": {"coordinates":[-75.049609,39.955419],"type":"Point"}
}