{
  "type": "Feature",
  "properties": {
    "iso:country":"US",
    "sg:address":"6 Baron Ave",
    "sg:city":"Marlton",
    "sg:classifiers":[
        {
            "category":"Professional",
            "subcategory":"Business Services",
            "type":"Services"
        }
    ],
    "sg:phone":"+1   ",
    "sg:postcode":"08053",
    "sg:province":"NJ",
    "wof:name":"R Comm Telecommunications",
    "wof:placetype":"venue"
},
  "geometry": {"coordinates":[-74.92908799999999,39.90097],"type":"Point"}
}