{
  "type": "Feature",
  "properties": {
    "addr:full":"242 Demarest St Ridgewood NJ 07450",
    "addr:housenumber":"242",
    "addr:postcode":"07450",
    "addr:street":"Demarest St",
    "iso:country":"US",
    "sg:address":"242 Demarest St",
    "sg:city":"Ridgewood",
    "sg:classifiers":[
        {
            "category":"Professional",
            "subcategory":"Advertising",
            "type":"Services"
        }
    ],
    "sg:phone":"+1 201 445 4067",
    "sg:postcode":"07450",
    "sg:province":"NJ",
    "sg:tags":[
        "agency"
    ],
    "wof:name":"Frances Film Inc",
    "wof:placetype":"venue"
},
  "geometry": {"coordinates":[-74.12824500000001,40.972497],"type":"Point"}
}