{
  "type": "Feature",
  "properties": {
    "addr:full":"2 Hamilton Ln Plainsboro NJ 08536",
    "addr:housenumber":"2",
    "addr:postcode":"08536",
    "addr:street":"Hamilton Ln",
    "iso:country":"US",
    "sg:address":"2 Hamilton Ln",
    "sg:city":"Plainsboro",
    "sg:classifiers":[
        {
            "category":"Professional",
            "subcategory":"Computer Services",
            "type":"Services"
        }
    ],
    "sg:phone":"+1   ",
    "sg:postcode":"08536",
    "sg:province":"NJ",
    "sg:tags":[
        "solution",
        "database"
    ],
    "wof:name":"Pb Computer Consulting",
    "wof:placetype":"venue"
},
  "geometry": {"coordinates":[-74.58672199999999,40.355933],"type":"Point"}
}