{
  "type": "Feature",
  "properties": {
    "iso:country":"US",
    "sg:address":"62 Quenby Mountain Rd",
    "sg:city":"Great Meadows",
    "sg:classifiers":[
        {
            "category":"Personal",
            "subcategory":"Beauty Salon",
            "type":"Services"
        }
    ],
    "sg:phone":"+1   ",
    "sg:postcode":"07838",
    "sg:province":"NJ",
    "sg:tags":[
        "shop"
    ],
    "wof:name":"Itc Hair Designers LLC",
    "wof:placetype":"venue"
},
  "geometry": {"coordinates":[-74.96087,40.847991],"type":"Point"}
}