{
  "type": "Feature",
  "properties": {
    "iso:country":"US",
    "sg:address":"732 Bergen Blvd",
    "sg:city":"Ridgefield",
    "sg:classifiers":[
        {
            "category":"Personal",
            "subcategory":"Beauty Salon",
            "type":"Services"
        }
    ],
    "sg:phone":"+1 201 941 0707",
    "sg:postcode":"07657",
    "sg:province":"NJ",
    "sg:tags":[
        "hair",
        "shop",
        "removal"
    ],
    "sg:website":"www.sebastianhairstudio.com",
    "wof:name":"Sebastian Hair Studio",
    "wof:placetype":"venue"
},
  "geometry": {"coordinates":[-73.991302,40.832699],"type":"Point"}
}