{
  "type": "Feature",
  "properties": {
    "iso:country":"US",
    "sg:address":"256 Broad Ave",
    "sg:city":"Palisades Park",
    "sg:classifiers":[
        {
            "category":"Education",
            "subcategory":"School",
            "type":"Public Place"
        }
    ],
    "sg:phone":"+1 201 346 1410",
    "sg:postcode":"07650",
    "sg:province":"NJ",
    "sg:tags":[
        "high",
        "middle",
        "elementary"
    ],
    "wof:name":"M E K Academy",
    "wof:placetype":"venue"
},
  "geometry": {"coordinates":[-73.99794199999999,40.847331],"type":"Point"}
}