{
  "type": "Feature",
  "properties": {
    "iso:country":"US",
    "sg:address":"122 Estates Blvd",
    "sg:city":"Trenton",
    "sg:classifiers":[
        {
            "category":"Real Estate",
            "subcategory":"Real Estate Operator",
            "type":"Services"
        }
    ],
    "sg:phone":"+1   ",
    "sg:postcode":"08610",
    "sg:province":"NJ",
    "sg:tags":[
        "apartment"
    ],
    "wof:name":"Victoria Apartments",
    "wof:placetype":"venue"
},
  "geometry": {"coordinates":[-74.704235,40.209331],"type":"Point"}
}