{
  "type": "Feature",
  "properties": {
    "addr:full":"610 Trenton Ave Point Pleasant Beach NJ 08742",
    "addr:housenumber":"610",
    "addr:postcode":"08742",
    "addr:street":"Trenton Ave",
    "iso:country":"US",
    "sg:address":"610 Trenton Ave",
    "sg:city":"Point Pleasant Beach",
    "sg:classifiers":[
        {
            "category":"Professional",
            "subcategory":"Art Services",
            "type":"Services"
        }
    ],
    "sg:phone":"+1   ",
    "sg:postcode":"08742",
    "sg:province":"NJ",
    "sg:tags":[
        "commercial",
        "design"
    ],
    "wof:name":"Pete Heineck Graphic Design",
    "wof:placetype":"venue"
},
  "geometry": {"coordinates":[-74.051614,40.089389],"type":"Point"}
}