{
  "type": "Feature",
  "properties": {
    "addr:full":"44 Miller Dr Metuchen NJ 08840",
    "addr:housenumber":"44",
    "addr:postcode":"08840",
    "addr:street":"Miller Dr",
    "iso:country":"US",
    "sg:address":"44 Miller Dr",
    "sg:city":"Metuchen",
    "sg:classifiers":[
        {
            "category":"Professional",
            "type":"Services"
        }
    ],
    "sg:phone":"+1   ",
    "sg:postcode":"08840",
    "sg:province":"NJ",
    "wof:name":"Whatever Works Inc",
    "wof:placetype":"venue"
},
  "geometry": {"coordinates":[-74.36888,40.552274],"type":"Point"}
}