{
  "type": "Feature",
  "properties": {
    "iso:country":"US",
    "sg:address":"15 Bristol Pl",
    "sg:city":"Wayne",
    "sg:classifiers":[
        {
            "category":"Food & Beverages",
            "subcategory":"Specialty",
            "type":"Retail Goods"
        }
    ],
    "sg:phone":"+1   ",
    "sg:postcode":"07470",
    "sg:province":"NJ",
    "wof:name":"Herbal Realities Inc",
    "wof:placetype":"venue"
},
  "geometry": {"coordinates":[-74.26033200000001,40.953942],"type":"Point"}
}