{
  "type": "Feature",
  "properties": {
    "iso:country":"US",
    "sg:address":"1600 Burlington Byp",
    "sg:city":"Burlington Township",
    "sg:classifiers":[
        {
            "category":"Building & Trades",
            "subcategory":"Locksmith",
            "type":"Services"
        }
    ],
    "sg:phone":"+1 609 526 9937",
    "sg:postcode":"08016",
    "sg:province":"NJ",
    "sg:tags":[
        "key"
    ],
    "wof:name":"7 Day 24 Hours Emergency Locksmith",
    "wof:placetype":"venue"
},
  "geometry": {"coordinates":[-74.841487,40.058678],"type":"Point"}
}