{
  "type": "Feature",
  "properties": {
    "addr:full":"36 Red Oak Row Princeton NJ 08540",
    "addr:housenumber":"36",
    "addr:postcode":"08540",
    "addr:street":"Red Oak Row",
    "iso:country":"US",
    "sg:address":"36 Red Oak Row",
    "sg:city":"Princeton",
    "sg:classifiers":[
        {
            "category":"Building & Trades",
            "subcategory":"Cleaning & Sanitation",
            "type":"Services"
        }
    ],
    "sg:phone":"+1   ",
    "sg:postcode":"08540",
    "sg:province":"NJ",
    "sg:tags":[
        "maintenance"
    ],
    "wof:name":"Te Maid Service",
    "wof:placetype":"venue"
},
  "geometry": {"coordinates":[-74.651481,40.377349],"type":"Point"}
}