{
  "type": "Feature",
  "properties": {
    "iso:country":"US",
    "sg:address":"1157 Haddon Ave",
    "sg:city":"Camden",
    "sg:classifiers":[
        {
            "category":"Social Services",
            "subcategory":"Child Care",
            "type":"Services"
        }
    ],
    "sg:phone":"+1 856 963 3083",
    "sg:postcode":"08103",
    "sg:province":"NJ",
    "sg:tags":[
        "daycare"
    ],
    "wof:name":"Our Future Academy Inc",
    "wof:placetype":"venue"
},
  "geometry": {"coordinates":[-75.103835,39.932813],"type":"Point"}
}