{
  "type": "Feature",
  "properties": {
    "iso:country":"US",
    "sg:address":"1310 Unami Ave",
    "sg:city":"Ocean",
    "sg:phone":"+1 732 776 6566",
    "sg:postcode":"07712",
    "sg:province":"NJ",
    "sg:tags":[
        "oil"
    ],
    "wof:name":"Asbury Fuel",
    "wof:placetype":"venue"
},
  "geometry": {"coordinates":[-74.022199,40.230541],"type":"Point"}
}