{
  "type": "Feature",
  "properties": {
    "addr:full":"1852 Deptford Center Rd Deptford NJ 08096",
    "addr:housenumber":"1852",
    "addr:postcode":"08096",
    "addr:street":"Deptford Center Rd",
    "iso:country":"US",
    "sg:address":"1852 Deptford Center Rd",
    "sg:city":"Deptford",
    "sg:classifiers":[
        {
            "category":"Restaurant",
            "type":"Food & Drink"
        }
    ],
    "sg:phone":"+1 856 401 8510",
    "sg:postcode":"08096",
    "sg:province":"NJ",
    "wof:name":"Pizza Hut",
    "wof:placetype":"venue"
},
  "geometry": {"coordinates":[-75.093712,39.828551],"type":"Point"}
}