{
  "type": "Feature",
  "properties": {
    "addr:full":"1405 West Ave Ocean City NJ 08226",
    "addr:housenumber":"1405",
    "addr:postcode":"08226",
    "addr:street":"West Ave",
    "iso:country":"US",
    "sg:address":"1405 West Ave",
    "sg:city":"Ocean City",
    "sg:classifiers":[
        {
            "category":"Food & Beverages",
            "subcategory":"Groceries & Convenience Stores",
            "type":"Retail Goods"
        }
    ],
    "sg:phone":"+1   ",
    "sg:postcode":"08226",
    "sg:province":"NJ",
    "wof:name":"Barnetts Market Inc",
    "wof:placetype":"venue"
},
  "geometry": {"coordinates":[-74.584194,39.273989],"type":"Point"}
}