{
  "type": "Feature",
  "properties": {
    "iso:country":"US",
    "sg:address":"12 River Rd",
    "sg:city":"Bogota",
    "sg:classifiers":[
        {
            "category":"Building & Trades",
            "subcategory":"Construction",
            "type":"Services"
        }
    ],
    "sg:phone":"+1 201 525 1005",
    "sg:postcode":"07603",
    "sg:province":"NJ",
    "sg:tags":[
        "builder",
        "repairer",
        "chimney"
    ],
    "wof:name":"A-1 Affordable Construction Co",
    "wof:placetype":"venue"
},
  "geometry": {"coordinates":[-74.033047,40.870869],"type":"Point"}
}