{
  "type": "Feature",
  "properties": {
    "iso:country":"US",
    "sg:address":"139 Speer Ave",
    "sg:city":"Clifton",
    "sg:classifiers":[
        {
            "category":"Travel",
            "subcategory":"Travel Agent",
            "type":"Entertainment"
        }
    ],
    "sg:phone":"+1 973 815 0348",
    "sg:postcode":"07013",
    "sg:province":"NJ",
    "sg:tags":[
        "operator",
        "tour"
    ],
    "wof:name":"Bednarz Tours Co",
    "wof:placetype":"venue"
},
  "geometry": {"coordinates":[-74.151245,40.857807],"type":"Point"}
}