{
  "type": "Feature",
  "properties": {
    "addr:full":"405 Cecelia Pl Cliffside Park NJ 07010",
    "addr:housenumber":"405",
    "addr:postcode":"07010",
    "addr:street":"Cecelia Pl",
    "iso:country":"US",
    "sg:address":"405 Cecelia Pl",
    "sg:city":"Cliffside Park",
    "sg:classifiers":[
        {
            "category":"Personal",
            "subcategory":"Beauty Salon",
            "type":"Services"
        }
    ],
    "sg:phone":"+1 201 945 9115",
    "sg:postcode":"07010",
    "sg:province":"NJ",
    "sg:tags":[
        "manicuring"
    ],
    "wof:name":"Finger Fitness Nail Salon",
    "wof:placetype":"venue"
},
  "geometry": {"coordinates":[-73.987956,40.817024],"type":"Point"}
}