{
  "type": "Feature",
  "properties": {
    "addr:full":"79 Union Blvd Totowa NJ 07512",
    "addr:housenumber":"79",
    "addr:postcode":"07512",
    "addr:street":"Union Blvd",
    "iso:country":"US",
    "sg:address":"79 Union Blvd",
    "sg:city":"Totowa",
    "sg:classifiers":[
        {
            "category":"Personal",
            "subcategory":"Tanning Parlor",
            "type":"Services"
        }
    ],
    "sg:phone":"+1 973 595 0333",
    "sg:postcode":"07512",
    "sg:province":"NJ",
    "wof:name":"Designer Skin Tanning & Spa",
    "wof:placetype":"venue"
},
  "geometry": {"coordinates":[-74.20334200000001,40.90968],"type":"Point"}
}