{
  "type": "Feature",
  "properties": {
    "addr:full":"530 US Hwy 130 Hightstown NJ 08520",
    "addr:housenumber":"530",
    "addr:postcode":"08520",
    "addr:street":"Us Hwy 130",
    "iso:country":"US",
    "sg:address":"530 US Hwy 130",
    "sg:city":"Hightstown",
    "sg:classifiers":[
        {
            "category":"Retail",
            "subcategory":"Auto Repair",
            "type":"Services"
        }
    ],
    "sg:phone":"+1 609 448 5800",
    "sg:postcode":"08520",
    "sg:province":"NJ",
    "sg:tags":[
        "automotive",
        "system",
        "exhaust"
    ],
    "wof:name":"Meineke Discount Mufflers",
    "wof:placetype":"venue"
},
  "geometry": {"coordinates":[-74.543251,40.267552],"type":"Point"}
}