{
  "type": "Feature",
  "properties": {
    "addr:full":"28 Ave At Port Imperial West New York NJ 07093",
    "addr:postcode":"07093",
    "addr:street":"28 Ave At Port Imperial West",
    "iso:country":"US",
    "sg:address":"28 Ave At Port Imperial",
    "sg:city":"West New York",
    "sg:classifiers":[
        {
            "category":"Building & Trades",
            "subcategory":"Construction",
            "type":"Services"
        }
    ],
    "sg:phone":"+1 201 863 2598",
    "sg:postcode":"07093",
    "sg:province":"NJ",
    "sg:tags":[
        "contractor"
    ],
    "wof:name":"Roseland Property Company",
    "wof:placetype":"venue"
},
  "geometry": {"coordinates":[-74.008872,40.778976],"type":"Point"}
}