{
  "type": "Feature",
  "properties": {
    "iso:country":"US",
    "sg:address":"20 Stewart Pl",
    "sg:city":"Fairfield",
    "sg:classifiers":[
        {
            "category":"Wholesale",
            "subcategory":"Groceries",
            "type":"Manufacturing & Wholesale Goods"
        }
    ],
    "sg:phone":"+1 973 439 0040",
    "sg:postcode":"07004",
    "sg:province":"NJ",
    "sg:tags":[
        "food",
        "product"
    ],
    "wof:name":"Vel-Mac Foods Distributors",
    "wof:placetype":"venue"
},
  "geometry": {"coordinates":[-74.317492,40.8673],"type":"Point"}
}