{
  "type": "Feature",
  "properties": {
    "iso:country":"US",
    "sg:address":"1134 State Rte 36",
    "sg:city":"Hazlet",
    "sg:classifiers":[
        {
            "category":"Autos & Motor Vehicles",
            "subcategory":"Boat Sales",
            "type":"Retail Goods"
        }
    ],
    "sg:phone":"+1 732 264 7711",
    "sg:postcode":"07730",
    "sg:province":"NJ",
    "sg:tags":[
        "equipment",
        "marine",
        "supply"
    ],
    "wof:name":"Tackle Box",
    "wof:placetype":"venue"
},
  "geometry": {"coordinates":[-74.179778,40.434074],"type":"Point"}
}