{
  "type": "Feature",
  "properties": {
    "addr:full":"158 Stonehenge Dr Phillipsburg NJ 08865",
    "addr:housenumber":"158",
    "addr:postcode":"08865",
    "addr:street":"Stonehenge Dr",
    "iso:country":"US",
    "sg:address":"158 Stonehenge Dr",
    "sg:city":"Phillipsburg",
    "sg:classifiers":[
        {
            "category":"Professional",
            "subcategory":"Management & Consulting",
            "type":"Services"
        }
    ],
    "sg:phone":"+1   ",
    "sg:postcode":"08865",
    "sg:province":"NJ",
    "wof:name":"Kom3kar",
    "wof:placetype":"venue"
},
  "geometry": {"coordinates":[-75.161644,40.711126],"type":"Point"}
}