{
  "type": "Feature",
  "properties": {
    "iso:country":"US",
    "sg:address":"988 Broadway",
    "sg:city":"Bayonne",
    "sg:classifiers":[
        {
            "category":"Building & Trades",
            "subcategory":"Equipment Rental",
            "type":"Services"
        }
    ],
    "sg:phone":"+1   ",
    "sg:postcode":"07002",
    "sg:province":"NJ",
    "sg:tags":[
        "lawn",
        "construction",
        "rent",
        "garden"
    ],
    "wof:name":"Nationsrent Inc",
    "wof:placetype":"venue"
},
  "geometry": {"coordinates":[-74.103844,40.680969],"type":"Point"}
}