{
  "type": "Feature",
  "properties": {
    "addr:full":"7 Bay Ave Bloomfield NJ 07003",
    "addr:housenumber":"7",
    "addr:postcode":"07003",
    "addr:street":"Bay Ave",
    "iso:country":"US",
    "sg:address":"7 Bay Ave",
    "sg:city":"Bloomfield",
    "sg:classifiers":[
        {
            "category":"Professional",
            "subcategory":"Detective & Security Services",
            "type":"Services"
        },
        {
            "category":"Professional",
            "subcategory":"Computer Services",
            "type":"Services"
        }
    ],
    "sg:phone":"+1 973 249 9591",
    "sg:postcode":"07003",
    "sg:province":"NJ",
    "sg:tags":[
        "consultant"
    ],
    "wof:name":"On Site Technology",
    "wof:placetype":"venue"
},
  "geometry": {"coordinates":[-74.18982200000001,40.81104],"type":"Point"}
}