{
  "type": "Feature",
  "properties": {
    "addr:full":"17 Theodore St Wharton NJ 07885",
    "addr:housenumber":"17",
    "addr:postcode":"07885",
    "addr:street":"Theodore St",
    "iso:country":"US",
    "sg:address":"17 Theodore St",
    "sg:city":"Wharton",
    "sg:classifiers":[
        {
            "category":"Shopping",
            "subcategory":"Gifts & Souvenirs",
            "type":"Retail Goods"
        }
    ],
    "sg:phone":"+1 973 328 7664",
    "sg:postcode":"07885",
    "sg:province":"NJ",
    "sg:tags":[
        "shop"
    ],
    "wof:name":"Home For The Holidays Gifts",
    "wof:placetype":"venue"
},
  "geometry": {"coordinates":[-74.58036,40.895525],"type":"Point"}
}