{
  "type": "Feature",
  "properties": {
    "addr:full":"16 Fairfield Rd Toms River NJ 08757",
    "addr:housenumber":"16",
    "addr:postcode":"08757",
    "addr:street":"Fairfield Rd",
    "iso:country":"US",
    "sg:address":"16 Fairfield Rd",
    "sg:city":"Toms River",
    "sg:classifiers":[
        {
            "category":"Insurance",
            "subcategory":"Life Insurance",
            "type":"Services"
        }
    ],
    "sg:phone":"+1   ",
    "sg:postcode":"08757",
    "sg:province":"NJ",
    "sg:tags":[
        "carrier"
    ],
    "wof:name":"Polish National Alliance",
    "wof:placetype":"venue"
},
  "geometry": {"coordinates":[-74.273762,39.96111],"type":"Point"}
}