{
  "type": "Feature",
  "properties": {
    "iso:country":"US",
    "sg:address":"17 Academy St Ste 1300",
    "sg:city":"Newark",
    "sg:classifiers":[
        {
            "category":"Real Estate",
            "subcategory":"Real Estate Services",
            "type":"Services"
        }
    ],
    "sg:phone":"+1 973 624 1888",
    "sg:postcode":"07102",
    "sg:province":"NJ",
    "sg:tags":[
        "management",
        "property"
    ],
    "wof:name":"Rock Management Corp",
    "wof:placetype":"venue"
},
  "geometry": {"coordinates":[-74.172104,40.737297],"type":"Point"}
}