{
  "type": "Feature",
  "properties": {
    "iso:country":"US",
    "sg:address":"29 Williams Ave",
    "sg:city":"Woodbury",
    "sg:classifiers":[
        {
            "category":"Retail",
            "subcategory":"Auto Repair",
            "type":"Services"
        }
    ],
    "sg:phone":"+1   ",
    "sg:postcode":"08096",
    "sg:province":"NJ",
    "sg:tags":[
        "diesel"
    ],
    "wof:name":"Diesel Doctor Inc",
    "wof:placetype":"venue"
},
  "geometry": {"coordinates":[-75.11753,39.827915],"type":"Point"}
}