{
  "type": "Feature",
  "properties": {
    "addr:full":"187 Mountainview Ave Nutley NJ 07110",
    "addr:housenumber":"187",
    "addr:postcode":"07110",
    "addr:street":"Mountainview Ave",
    "iso:country":"US",
    "sg:address":"187 Mountainview Ave",
    "sg:city":"Nutley",
    "sg:classifiers":[
        {
            "category":"Wholesale",
            "subcategory":"Chemicals & Plastics",
            "type":"Manufacturing & Wholesale Goods"
        }
    ],
    "sg:phone":"+1 973 661 0714",
    "sg:postcode":"07110",
    "sg:province":"NJ",
    "wof:name":"ICI Americas Inc",
    "wof:placetype":"venue"
},
  "geometry": {"coordinates":[-74.16716599999999,40.822967],"type":"Point"}
}