{
  "type": "Feature",
  "properties": {
    "addr:full":"40 Commerce Dr Cranbury NJ 08512",
    "addr:housenumber":"40",
    "addr:postcode":"08512",
    "addr:street":"Commerce Dr",
    "iso:country":"US",
    "sg:address":"40 Commerce Dr",
    "sg:city":"Cranbury",
    "sg:classifiers":[
        {
            "category":"Freight",
            "type":"Transportation"
        }
    ],
    "sg:phone":"+1 609 409 0700",
    "sg:postcode":"08512",
    "sg:province":"NJ",
    "sg:tags":[
        "warehouse"
    ],
    "wof:name":"Horizon USA Data Supplies Inc",
    "wof:placetype":"venue"
},
  "geometry": {"coordinates":[-74.486932,40.341002],"type":"Point"}
}