{
  "type": "Feature",
  "properties": {
    "addr:full":"10 Bridge St Frenchtown NJ 08825",
    "addr:housenumber":"10",
    "addr:postcode":"08825",
    "addr:street":"Bridge St",
    "iso:country":"US",
    "sg:address":"10 Bridge St",
    "sg:city":"Frenchtown",
    "sg:classifiers":[
        {
            "category":"Shopping",
            "subcategory":"Clothing, Apparel, & Fashions",
            "type":"Retail Goods"
        }
    ],
    "sg:phone":"+1 908 996 6787",
    "sg:postcode":"08825",
    "sg:province":"NJ",
    "sg:tags":[
        "infant",
        "wear"
    ],
    "wof:name":"Race Street Kids",
    "wof:placetype":"venue"
},
  "geometry": {"coordinates":[-75.062974,40.526245],"type":"Point"}
}