{
  "type": "Feature",
  "properties": {
    "addr:full":"12 Cherry Brook Ln Hightstown NJ 08520",
    "addr:housenumber":"12",
    "addr:postcode":"08520",
    "addr:street":"Cherry Brook Ln",
    "iso:country":"US",
    "sg:address":"12 Cherry Brook Ln",
    "sg:city":"Hightstown",
    "sg:classifiers":[
        {
            "category":"Building & Trades",
            "subcategory":"Plumbing",
            "type":"Services"
        }
    ],
    "sg:phone":"+1 609 443 6904",
    "sg:postcode":"08520",
    "sg:province":"NJ",
    "sg:tags":[
        "contractor"
    ],
    "wof:name":"Avamian",
    "wof:placetype":"venue"
},
  "geometry": {"coordinates":[-74.561533,40.271665],"type":"Point"}
}