{
  "type": "Feature",
  "properties": {
    "iso:country":"US",
    "sg:address":"65 W Main St",
    "sg:city":"Chester",
    "sg:classifiers":[
        {
            "category":"Insurance",
            "subcategory":"Insurance Agent",
            "type":"Services"
        }
    ],
    "sg:phone":"+1 908 879 4899",
    "sg:postcode":"07930",
    "sg:province":"NJ",
    "wof:name":"Prudential Insurance Co",
    "wof:placetype":"venue"
},
  "geometry": {"coordinates":[-74.70275599999999,40.781939],"type":"Point"}
}