{
  "type": "Feature",
  "properties": {
    "addr:full":"725 State Rte 15 Lake Hopatcong NJ 07849",
    "addr:housenumber":"725",
    "addr:postcode":"07849",
    "addr:street":"State Rte 15",
    "iso:country":"US",
    "sg:address":"725 State Rte 15",
    "sg:city":"Lake Hopatcong",
    "sg:classifiers":[
        {
            "category":"Sports & Exercise",
            "subcategory":"Gym",
            "type":"Entertainment"
        }
    ],
    "sg:phone":"+1 973 663 4433",
    "sg:postcode":"07849",
    "sg:province":"NJ",
    "sg:tags":[
        "club",
        "health",
        "studio",
        "gymnasium"
    ],
    "wof:name":"Curves",
    "wof:placetype":"venue"
},
  "geometry": {"coordinates":[-74.59730999999999,40.95893],"type":"Point"}
}