{
  "type": "Feature",
  "properties": {
    "iso:country":"US",
    "sg:address":"111 S Delancy Pl",
    "sg:city":"Atlantic City",
    "sg:classifiers":[
        {
            "category":"Communications",
            "subcategory":"Film & Video Production",
            "type":"Services"
        }
    ],
    "sg:phone":"+1 609 347 0051",
    "sg:postcode":"08401",
    "sg:province":"NJ",
    "sg:tags":[
        "motion",
        "picture"
    ],
    "wof:name":"J & J Productions",
    "wof:placetype":"venue"
},
  "geometry": {"coordinates":[-74.46015300000001,39.346008],"type":"Point"}
}