{
  "type": "Feature",
  "properties": {
    "iso:country":"US",
    "sg:address":"10 South Avenue",
    "sg:city":"Cranford",
    "sg:classifiers":[
        {
            "category":"Restaurant",
            "type":"Food & Drink"
        }
    ],
    "sg:phone":"+1 908 497 1990",
    "sg:postcode":"07016",
    "sg:province":"NJ",
    "sg:tags":[
        "italian"
    ],
    "sg:website":"cranfordbistro.com",
    "wof:name":"Il Gabbiano",
    "wof:placetype":"venue"
},
  "geometry": {"coordinates":[-74.305026,40.654188],"type":"Point"}
}