{
  "type": "Feature",
  "properties": {
    "addr:full":"8 Furlong Dr Cherry Hill NJ 08003",
    "addr:housenumber":"8",
    "addr:postcode":"08003",
    "addr:street":"Furlong Dr",
    "iso:country":"US",
    "sg:address":"8 Furlong Dr",
    "sg:city":"Cherry Hill",
    "sg:classifiers":[
        {
            "category":"Professional",
            "subcategory":"Computer Services",
            "type":"Services"
        }
    ],
    "sg:phone":"+1   ",
    "sg:postcode":"08003",
    "sg:province":"NJ",
    "sg:tags":[
        "related"
    ],
    "wof:name":"St Ives Creek",
    "wof:placetype":"venue"
},
  "geometry": {"coordinates":[-74.96625899999999,39.868688],"type":"Point"}
}