{
  "type": "Feature",
  "properties": {
    "addr:full":"2 Snuffys Ln Lebanon NJ 08833",
    "addr:housenumber":"2",
    "addr:postcode":"08833",
    "addr:street":"Snuffys Ln",
    "iso:country":"US",
    "sg:address":"2 Snuffys Ln",
    "sg:city":"Lebanon",
    "sg:classifiers":[
        {
            "category":"Banks & Credit Unions",
            "subcategory":"Financial Services",
            "type":"Services"
        }
    ],
    "sg:phone":"+1   ",
    "sg:postcode":"08833",
    "sg:province":"NJ",
    "sg:tags":[
        "company",
        "holding"
    ],
    "wof:name":"Ruffini Association LLC",
    "wof:placetype":"venue"
},
  "geometry": {"coordinates":[-74.79005600000001,40.670854],"type":"Point"}
}