{
  "type": "Feature",
  "properties": {
    "iso:country":"US",
    "sg:address":"6 Magnolia Dr",
    "sg:city":"Burlington",
    "sg:classifiers":[
        {
            "category":"Building & Trades",
            "subcategory":"Electrical",
            "type":"Services"
        }
    ],
    "sg:phone":"+1 609 387 0437",
    "sg:postcode":"08016",
    "sg:province":"NJ",
    "sg:tags":[
        "electric",
        "contractor"
    ],
    "wof:name":"J & J Electric LLC",
    "wof:placetype":"venue"
},
  "geometry": {"coordinates":[-74.860353,40.055505],"type":"Point"}
}