{
  "type": "Feature",
  "properties": {
    "iso:country":"US",
    "sg:address":"180 Broad St",
    "sg:city":"Clifton",
    "sg:classifiers":[
        {
            "category":"Wholesale",
            "subcategory":"Machinery & Supplies",
            "type":"Manufacturing & Wholesale Goods"
        }
    ],
    "sg:phone":"+1 973 279 5500",
    "sg:postcode":"07013",
    "sg:province":"NJ",
    "sg:tags":[
        "equipment",
        "design",
        "kitchen",
        "commercial",
        "contractor"
    ],
    "sg:website":"www.economysupply.com",
    "wof:name":"Economy Paper & Rest Sup Co",
    "wof:placetype":"venue"
},
  "geometry": {"coordinates":[-74.169212,40.889806],"type":"Point"}
}