{
  "type": "Feature",
  "properties": {
    "addr:full":"30 Jasmine Ln Sicklerville NJ 08081",
    "addr:housenumber":"30",
    "addr:postcode":"08081",
    "addr:street":"Jasmine Ln",
    "iso:country":"US",
    "sg:address":"30 Jasmine Ln",
    "sg:city":"Sicklerville",
    "sg:classifiers":[
        {
            "category":"Professional",
            "type":"Services"
        }
    ],
    "sg:phone":"+1 856 875 8464",
    "sg:postcode":"08081",
    "sg:province":"NJ",
    "wof:name":"Philcare Services Inc",
    "wof:placetype":"venue"
},
  "geometry": {"coordinates":[-75.018224,39.733168],"type":"Point"}
}