{
  "type": "Feature",
  "properties": {
    "iso:country":"US",
    "sg:address":"76 E 23rd St",
    "sg:city":"Bayonne",
    "sg:classifiers":[
        {
            "category":"Building & Trades",
            "subcategory":"Construction",
            "type":"Services"
        }
    ],
    "sg:phone":"+1 201 858 8348",
    "sg:postcode":"07002",
    "sg:province":"NJ",
    "sg:tags":[
        "contractor"
    ],
    "wof:name":"Dibella V Construction",
    "wof:placetype":"venue"
},
  "geometry": {"coordinates":[-74.11380699999999,40.662346],"type":"Point"}
}