{
  "type": "Feature",
  "properties": {
    "iso:country":"US",
    "sg:address":"6008 N Crescent Blvd",
    "sg:city":"Pennsauken",
    "sg:classifiers":[
        {
            "category":"Food & Beverages",
            "subcategory":"Meat & Fish",
            "type":"Retail Goods"
        }
    ],
    "sg:phone":"+1 856 663 0870",
    "sg:postcode":"08109",
    "sg:province":"NJ",
    "sg:tags":[
        "seafood",
        "market"
    ],
    "wof:name":"Alex's Seafood & Good Eats",
    "wof:placetype":"venue"
},
  "geometry": {"coordinates":[-75.054802,39.959202],"type":"Point"}
}