{
  "type": "Feature",
  "properties": {
    "iso:country":"US",
    "sg:address":"16 Dov Pl",
    "sg:city":"Kendall Park",
    "sg:classifiers":[
        {
            "category":"Professional",
            "subcategory":"Engineering",
            "type":"Services"
        }
    ],
    "sg:phone":"+1   ",
    "sg:postcode":"08824",
    "sg:province":"NJ",
    "sg:tags":[
        "consultation"
    ],
    "wof:name":"Priceton Management Consultant",
    "wof:placetype":"venue"
},
  "geometry": {"coordinates":[-74.560089,40.424135],"type":"Point"}
}