{
  "type": "Feature",
  "properties": {
    "addr:full":"64 Montgomery Ave Long Branch NJ 07740",
    "addr:housenumber":"64",
    "addr:postcode":"07740",
    "addr:street":"Montgomery Ave",
    "iso:country":"US",
    "sg:address":"64 Montgomery Ave",
    "sg:city":"Long Branch",
    "sg:classifiers":[
        {
            "category":"Personal",
            "type":"Services"
        }
    ],
    "sg:phone":"+1   ",
    "sg:postcode":"07740",
    "sg:province":"NJ",
    "wof:name":"Super It Therapy Center",
    "wof:placetype":"venue"
},
  "geometry": {"coordinates":[-73.984976,40.285094],"type":"Point"}
}