{
  "type": "Feature",
  "properties": {
    "iso:country":"US",
    "sg:address":"442 Lawn Ridge Rd",
    "sg:city":"Orange",
    "sg:classifiers":[
        {
            "category":"Arts & Performance",
            "subcategory":"Theater",
            "type":"Entertainment"
        }
    ],
    "sg:phone":"+1   ",
    "sg:postcode":"07050",
    "sg:province":"NJ",
    "sg:tags":[
        "group"
    ],
    "wof:name":"Hage Entertainment",
    "wof:placetype":"venue"
},
  "geometry": {"coordinates":[-74.24809,40.756875],"type":"Point"}
}