{
  "type": "Feature",
  "properties": {
    "addr:full":"429 N Broadway Pennsville NJ 08070",
    "addr:housenumber":"429",
    "addr:postcode":"08070",
    "addr:street":"N Broadway",
    "iso:country":"US",
    "sg:address":"429 N Broadway",
    "sg:city":"Pennsville",
    "sg:classifiers":[
        {
            "category":"Travel",
            "subcategory":"Hotels & Motels",
            "type":"Entertainment"
        }
    ],
    "sg:phone":"+1 856 351 1700",
    "sg:postcode":"08070",
    "sg:province":"NJ",
    "sg:tags":[
        "corporate",
        "lodging"
    ],
    "sg:website":"http://www.pennsville.hamptoninn.com",
    "wof:name":"Hampton Inn",
    "wof:placetype":"venue"
},
  "geometry": {"coordinates":[-75.494392,39.67765],"type":"Point"}
}