{
  "type": "Feature",
  "properties": {
    "addr:full":"530 State Rte 31 N Ringoes NJ 08551",
    "addr:housenumber":"530",
    "addr:postcode":"08551",
    "addr:street":"State Rte 31 N",
    "iso:country":"US",
    "sg:address":"530 State Rte 31 N",
    "sg:city":"Ringoes",
    "sg:classifiers":[
        {
            "category":"Building & Trades",
            "subcategory":"Construction",
            "type":"Services"
        }
    ],
    "sg:phone":"+1 908 782 8896",
    "sg:postcode":"08551",
    "sg:province":"NJ",
    "sg:tags":[
        "restoration",
        "preservation"
    ],
    "wof:name":"New Jersey Barn Co",
    "wof:placetype":"venue"
},
  "geometry": {"coordinates":[-74.861921,40.411376],"type":"Point"}
}