{
  "type": "Feature",
  "properties": {
    "addr:full":"35 Galloping Hill Rd Elizabeth NJ 07208",
    "addr:housenumber":"35",
    "addr:postcode":"07208",
    "addr:street":"Galloping Hill Rd",
    "iso:country":"US",
    "sg:address":"35 Galloping Hill Rd",
    "sg:city":"Elizabeth",
    "sg:classifiers":[
        {
            "category":"Cinema",
            "subcategory":"Movie Rental",
            "type":"Entertainment"
        }
    ],
    "sg:phone":"+1 908 289 8667",
    "sg:postcode":"07208",
    "sg:province":"NJ",
    "sg:tags":[
        "video",
        "tape"
    ],
    "wof:name":"Glamour Video",
    "wof:placetype":"venue"
},
  "geometry": {"coordinates":[-74.247122,40.665264],"type":"Point"}
}