{
  "type": "Feature",
  "properties": {
    "addr:full":"989 River Rd Edgewater NJ 07020",
    "addr:housenumber":"989",
    "addr:postcode":"07020",
    "addr:street":"River Rd",
    "iso:country":"US",
    "sg:address":"989 River Rd",
    "sg:city":"Edgewater",
    "sg:classifiers":[
        {
            "category":"Recreation",
            "subcategory":"Marina",
            "type":"Entertainment"
        }
    ],
    "sg:phone":"+1 201 944 2628",
    "sg:postcode":"07020",
    "sg:province":"NJ",
    "sg:tags":[
        "operation"
    ],
    "wof:name":"Edgewater Marina",
    "wof:placetype":"venue"
},
  "geometry": {"coordinates":[-73.972369,40.828544],"type":"Point"}
}