{
  "type": "Feature",
  "properties": {
    "iso:country":"US",
    "sg:address":"16 Lincoln Ave",
    "sg:city":"Dumont",
    "sg:classifiers":[
        {
            "category":"Building & Trades",
            "subcategory":"Construction",
            "type":"Services"
        }
    ],
    "sg:phone":"+1 201 384 6620",
    "sg:postcode":"07628",
    "sg:province":"NJ",
    "sg:tags":[
        "excavation",
        "contractor"
    ],
    "wof:name":"R T Stevens Excavating Inc",
    "wof:placetype":"venue"
},
  "geometry": {"coordinates":[-74.00945900000001,40.940399],"type":"Point"}
}