{
  "type": "Feature",
  "properties": {
    "iso:country":"US",
    "sg:address":"8 Veterans Plz",
    "sg:city":"Bergenfield",
    "sg:classifiers":[
        {
            "category":"Organizations",
            "subcategory":"Community Association",
            "type":"Services"
        }
    ],
    "sg:phone":"+1 201 384 0001",
    "sg:postcode":"07621",
    "sg:province":"NJ",
    "sg:tags":[
        "military"
    ],
    "sg:website":"www.dav.org",
    "wof:name":"Disabled American Veterans",
    "wof:placetype":"venue"
},
  "geometry": {"coordinates":[-73.998091,40.929223],"type":"Point"}
}