{
  "type": "Feature",
  "properties": {
    "addr:full":"28 Wellington Pl Burlington NJ 08016",
    "addr:housenumber":"28",
    "addr:postcode":"08016",
    "addr:street":"Wellington Pl",
    "iso:country":"US",
    "sg:address":"28 Wellington Pl",
    "sg:city":"Burlington",
    "sg:classifiers":[
        {
            "category":"Professional",
            "subcategory":"Accounting & Tax Preparation",
            "type":"Services"
        }
    ],
    "sg:phone":"+1   ",
    "sg:postcode":"08016",
    "sg:province":"NJ",
    "wof:name":"Travea Financial Corporation",
    "wof:placetype":"venue"
},
  "geometry": {"coordinates":[-74.84878399999999,40.065137],"type":"Point"}
}