{
  "type": "Feature",
  "properties": {
    "iso:country":"US",
    "sg:address":"500 Arlington Ave",
    "sg:city":"Lakewood",
    "sg:classifiers":[
        {
            "category":"Organizations",
            "subcategory":"Religious Organization",
            "type":"Services"
        }
    ],
    "sg:phone":"+1 732 905 7434",
    "sg:postcode":"08701",
    "sg:province":"NJ",
    "sg:tags":[
        "church"
    ],
    "wof:name":"Intercessory Tabernacle",
    "wof:placetype":"venue"
},
  "geometry": {"coordinates":[-74.209132,40.07794],"type":"Point"}
}