{
  "type": "Feature",
  "properties": {
    "addr:full":"305 Godwin Ave Ridgewood NJ 07450",
    "addr:housenumber":"305",
    "addr:postcode":"07450",
    "addr:street":"Godwin Ave",
    "iso:country":"US",
    "sg:address":"305 Godwin Ave",
    "sg:city":"Ridgewood",
    "sg:classifiers":[
        {
            "category":"Organizations",
            "subcategory":"Religious Organization",
            "type":"Services"
        }
    ],
    "sg:phone":"+1 201 445 4447",
    "sg:postcode":"07450",
    "sg:province":"NJ",
    "sg:tags":[
        "church"
    ],
    "wof:name":"Christian Science Churches",
    "wof:placetype":"venue"
},
  "geometry": {"coordinates":[-74.131677,40.981051],"type":"Point"}
}