{
  "type": "Feature",
  "properties": {
    "iso:country":"US",
    "sg:address":"48 Horse Hill Rd",
    "sg:city":"Cedar Knolls",
    "sg:classifiers":[
        {
            "category":"Manufacturing",
            "subcategory":"Tools & Machinery",
            "type":"Manufacturing & Wholesale Goods"
        }
    ],
    "sg:phone":"+1 973 753 2200",
    "sg:postcode":"07927",
    "sg:province":"NJ",
    "sg:tags":[
        "orthopedic"
    ],
    "wof:name":"Zimmer",
    "wof:placetype":"venue"
},
  "geometry": {"coordinates":[-74.4586,40.816366],"type":"Point"}
}