{
  "type": "Feature",
  "properties": {
    "iso:country":"US",
    "sg:address":"6 Grandin Dr",
    "sg:city":"Annandale",
    "sg:classifiers":[
        {
            "category":"Professional",
            "subcategory":"Engineering",
            "type":"Services"
        }
    ],
    "sg:phone":"+1 908 735 6389",
    "sg:postcode":"08801",
    "sg:province":"NJ",
    "wof:name":"Frey Engineering LLC",
    "wof:placetype":"venue"
},
  "geometry": {"coordinates":[-74.896415,40.608895],"type":"Point"}
}