{
  "type": "Feature",
  "properties": {
    "addr:full":"984 Route 166 Toms River NJ 08753",
    "addr:housenumber":"984",
    "addr:postcode":"08753",
    "addr:street":"Route 166",
    "iso:country":"US",
    "sg:address":"984 Route 166",
    "sg:city":"Toms River",
    "sg:classifiers":[
        {
            "category":"Restaurant",
            "type":"Food & Drink"
        }
    ],
    "sg:menulink":"http://www.allmenus.com/nj/toms-river/28182-bamboo-gardens-ii/menu/",
    "sg:phone":"+1 732 286 6800",
    "sg:postcode":"08753",
    "sg:province":"NJ",
    "sg:tags":[
        "asian",
        "chinese"
    ],
    "wof:name":"Bamboo Gardens II",
    "wof:placetype":"venue"
},
  "geometry": {"coordinates":[-74.202337,39.966667],"type":"Point"}
}