{
  "type": "Feature",
  "properties": {
    "iso:country":"US",
    "sg:address":"10 S 8th St",
    "sg:city":"Villas",
    "sg:classifiers":[
        {
            "category":"Building & Trades",
            "subcategory":"Plumbing",
            "type":"Services"
        }
    ],
    "sg:phone":"+1 609 886 5424",
    "sg:postcode":"08251",
    "sg:province":"NJ",
    "sg:tags":[
        "contractor"
    ],
    "wof:name":"Original Plumbing",
    "wof:placetype":"venue"
},
  "geometry": {"coordinates":[-74.923407,39.045865],"type":"Point"}
}