{
  "type": "Feature",
  "properties": {
    "addr:full":"8 South St New Providence NJ 07974",
    "addr:housenumber":"8",
    "addr:postcode":"07974",
    "addr:street":"South St",
    "iso:country":"US",
    "sg:address":"8 South St",
    "sg:city":"New Providence",
    "sg:classifiers":[
        {
            "category":"Building & Trades",
            "subcategory":"Locksmith",
            "type":"Services"
        }
    ],
    "sg:phone":"+1 888 225 7344",
    "sg:postcode":"07974",
    "sg:province":"NJ",
    "sg:tags":[
        "key"
    ],
    "wof:name":"24 Emergency Locksmith",
    "wof:placetype":"venue"
},
  "geometry": {"coordinates":[-74.406147,40.705817],"type":"Point"}
}