{
  "type": "Feature",
  "properties": {
    "iso:country":"US",
    "sg:address":"443 Main St Ste 1",
    "sg:city":"West Orange",
    "sg:classifiers":[
        {
            "category":"Shopping",
            "subcategory":"Pharmacy",
            "type":"Retail Goods"
        }
    ],
    "sg:phone":"+1 973 325 1020",
    "sg:postcode":"07052",
    "sg:province":"NJ",
    "sg:tags":[
        "drugstore"
    ],
    "wof:name":"West Orange Pharmacy",
    "wof:placetype":"venue"
},
  "geometry": {"coordinates":[-74.233299,40.792099],"type":"Point"}
}