{
  "type": "Feature",
  "properties": {
    "iso:country":"US",
    "sg:address":"649 Case Rd",
    "sg:city":"Neshanic Station",
    "sg:classifiers":[
        {
            "category":"Retail",
            "subcategory":"Animal Services",
            "type":"Services"
        }
    ],
    "sg:phone":"+1 908 369 7822",
    "sg:postcode":"08853",
    "sg:province":"NJ",
    "wof:name":"Happy Tails Grooming Spa",
    "wof:placetype":"venue"
},
  "geometry": {"coordinates":[-74.736053,40.537814],"type":"Point"}
}