{
  "type": "Feature",
  "properties": {
    "addr:full":"323 Plainfield Ave Piscataway NJ 08854",
    "addr:housenumber":"323",
    "addr:postcode":"08854",
    "addr:street":"Plainfield Ave",
    "iso:country":"US",
    "sg:address":"323 Plainfield Ave",
    "sg:city":"Piscataway",
    "sg:classifiers":[
        {
            "category":"Professional",
            "subcategory":"Business Services",
            "type":"Services"
        }
    ],
    "sg:phone":"+1 732 754 9751",
    "sg:postcode":"08854",
    "sg:province":"NJ",
    "wof:name":"Garden State Power Washing",
    "wof:placetype":"venue"
},
  "geometry": {"coordinates":[-74.49217899999999,40.541679],"type":"Point"}
}