{
  "type": "Feature",
  "properties": {
    "addr:full":"15 E Railroad Ave Monroe Township NJ 08831",
    "addr:housenumber":"15",
    "addr:postcode":"08831",
    "addr:street":"E Railroad Ave",
    "iso:country":"US",
    "sg:address":"15 E Railroad Ave",
    "sg:city":"Monroe Township",
    "sg:classifiers":[
        {
            "category":"Health Services",
            "subcategory":"Podiatrist",
            "type":"Services"
        }
    ],
    "sg:phone":"+1 732 521 2155",
    "sg:postcode":"08831",
    "sg:province":"NJ",
    "wof:name":"Monroe Foot & Ankle Care PC",
    "wof:placetype":"venue"
},
  "geometry": {"coordinates":[-74.43604999999999,40.348663],"type":"Point"}
}