{
  "type": "Feature",
  "properties": {
    "addr:full":"34 Leonard Ave Atlantic Highlands NJ 07716",
    "addr:housenumber":"34",
    "addr:postcode":"07716",
    "addr:street":"Leonard Ave",
    "iso:country":"US",
    "sg:address":"34 Leonard Ave",
    "sg:city":"Atlantic Highlands",
    "sg:classifiers":[
        {
            "category":"Professional",
            "type":"Services"
        }
    ],
    "sg:phone":"+1   ",
    "sg:postcode":"07716",
    "sg:province":"NJ",
    "wof:name":"Pho Ha Inc",
    "wof:placetype":"venue"
},
  "geometry": {"coordinates":[-74.04692,40.413011],"type":"Point"}
}