{
  "type": "Feature",
  "properties": {
    "addr:full":"62 W 47th St Secaucus NJ 07002",
    "addr:housenumber":"62",
    "addr:postcode":"07002",
    "addr:street":"W 47Th St",
    "iso:country":"US",
    "sg:address":"62 W 47th St",
    "sg:city":"Secaucus",
    "sg:classifiers":[
        {
            "category":"Professional",
            "subcategory":"Business Services",
            "type":"Services"
        }
    ],
    "sg:phone":"+1 201 866 3144",
    "sg:postcode":"07002",
    "sg:province":"NJ",
    "wof:name":"Fine Square Diamonds Inc",
    "wof:placetype":"venue"
},
  "geometry": {"coordinates":[-74.106933,40.682384],"type":"Point"}
}