{
  "type": "Feature",
  "properties": {
    "addr:full":"285 Hayes Dr Saddle Brook NJ 07663",
    "addr:housenumber":"285",
    "addr:postcode":"07663",
    "addr:street":"Hayes Dr",
    "iso:country":"US",
    "sg:address":"285 Hayes Dr",
    "sg:city":"Saddle Brook",
    "sg:classifiers":[
        {
            "category":"Food & Beverages",
            "subcategory":"Liquor & Beverages",
            "type":"Retail Goods"
        }
    ],
    "sg:phone":"+1   ",
    "sg:postcode":"07663",
    "sg:province":"NJ",
    "sg:tags":[
        "alcoholic"
    ],
    "wof:name":"New Jersey Beverage",
    "wof:placetype":"venue"
},
  "geometry": {"coordinates":[-74.105211,40.915986],"type":"Point"}
}