{
  "type": "Feature",
  "properties": {
    "iso:country":"US",
    "sg:address":"100 Pike Rd",
    "sg:city":"Mount Laurel",
    "sg:classifiers":[
        {
            "category":"Manufacturing",
            "subcategory":"Tools & Machinery",
            "type":"Manufacturing & Wholesale Goods"
        }
    ],
    "sg:phone":"+1 856 802 0602",
    "sg:postcode":"08054",
    "sg:province":"NJ",
    "sg:tags":[
        "flow",
        "meter",
        "mfg"
    ],
    "wof:name":"American Flow and Control",
    "wof:placetype":"venue"
},
  "geometry": {"coordinates":[-74.89420699999999,39.980813],"type":"Point"}
}