{
  "type": "Feature",
  "properties": {
    "iso:country":"US",
    "sg:address":"176 Parkside Dr",
    "sg:city":"Union",
    "sg:classifiers":[
        {
            "category":"Retail",
            "subcategory":"Car Wash",
            "type":"Services"
        }
    ],
    "sg:phone":"+1 908 810 0692",
    "sg:postcode":"07083",
    "sg:province":"NJ",
    "sg:tags":[
        "carwash"
    ],
    "wof:name":"Shamila Oil & Wash Inc",
    "wof:placetype":"venue"
},
  "geometry": {"coordinates":[-74.252555,40.700869],"type":"Point"}
}