{
  "type": "Feature",
  "properties": {
    "addr:full":"175 County Rd Tenafly NJ 07670",
    "addr:housenumber":"175",
    "addr:postcode":"07670",
    "addr:street":"County Rd",
    "iso:country":"US",
    "sg:address":"175 County Rd",
    "sg:city":"Tenafly",
    "sg:classifiers":[
        {
            "category":"Shopping",
            "subcategory":"Bicycles & Sporting Goods",
            "type":"Retail Goods"
        }
    ],
    "sg:phone":"+1   ",
    "sg:postcode":"07670",
    "sg:province":"NJ",
    "sg:tags":[
        "shop",
        "repair",
        "parts"
    ],
    "wof:name":"Tenafly Bicycle Workshop Inc",
    "wof:placetype":"venue"
},
  "geometry": {"coordinates":[-73.960455,40.931025],"type":"Point"}
}