{
  "type": "Feature",
  "properties": {
    "addr:full":"20 Ludlow Rd Parsippany NJ 07054",
    "addr:housenumber":"20",
    "addr:postcode":"07054",
    "addr:street":"Ludlow Rd",
    "iso:country":"US",
    "sg:address":"20 Ludlow Rd",
    "sg:city":"Parsippany",
    "sg:classifiers":[
        {
            "category":"Retail",
            "subcategory":"Repair Shop",
            "type":"Services"
        }
    ],
    "sg:phone":"+1 973 854 5689",
    "sg:postcode":"07054",
    "sg:province":"NJ",
    "sg:tags":[
        "lock",
        "locksmith"
    ],
    "wof:name":"A 24 7 Emergency Locksmith",
    "wof:placetype":"venue"
},
  "geometry": {"coordinates":[-74.441452,40.852384],"type":"Point"}
}