{
  "type": "Feature",
  "properties": {
    "iso:country":"US",
    "sg:address":"250 1st St",
    "sg:city":"Jersey City",
    "sg:classifiers":[
        {
            "category":"Professional",
            "subcategory":"Business Services",
            "type":"Services"
        }
    ],
    "sg:phone":"+1 201 217 0924",
    "sg:postcode":"07302",
    "sg:province":"NJ",
    "wof:name":"Florals By Ken & Lisa",
    "wof:placetype":"venue"
},
  "geometry": {"coordinates":[-74.04556599999999,40.721958],"type":"Point"}
}