{
  "type": "Feature",
  "properties": {
    "addr:full":"762 Van Houten Ave Clifton NJ 07013",
    "addr:housenumber":"762",
    "addr:postcode":"07013",
    "addr:street":"Van Houten Ave",
    "iso:country":"US",
    "sg:address":"762 Van Houten Ave",
    "sg:city":"Clifton",
    "sg:classifiers":[
        {
            "category":"Personal",
            "subcategory":"Beauty Salon",
            "type":"Services"
        }
    ],
    "sg:phone":"+1   ",
    "sg:postcode":"07013",
    "sg:province":"NJ",
    "sg:tags":[
        "shop"
    ],
    "wof:name":"Changes Not For Hair Only",
    "wof:placetype":"venue"
},
  "geometry": {"coordinates":[-74.152975,40.860927],"type":"Point"}
}