{
  "type": "Feature",
  "properties": {
    "addr:full":"1029 Gregory Ter Toms River NJ 08753",
    "addr:housenumber":"1029",
    "addr:postcode":"08753",
    "addr:street":"Gregory Ter",
    "iso:country":"US",
    "sg:address":"1029 Gregory Ter",
    "sg:city":"Toms River",
    "sg:classifiers":[
        {
            "category":"Building & Trades",
            "subcategory":"Plumbing",
            "type":"Services"
        }
    ],
    "sg:phone":"+1 732 341 2696",
    "sg:postcode":"08753",
    "sg:province":"NJ",
    "sg:tags":[
        "conditioning",
        "air",
        "system",
        "contractor"
    ],
    "wof:name":"Gabriel & Sons A-C & Refrig",
    "wof:placetype":"venue"
},
  "geometry": {"coordinates":[-74.198189,39.969629],"type":"Point"}
}