{
  "type": "Feature",
  "properties": {
    "addr:full":"565 Palisade Ave Jersey City NJ 07307",
    "addr:housenumber":"565",
    "addr:postcode":"07307",
    "addr:street":"Palisade Ave",
    "iso:country":"US",
    "sg:address":"565 Palisade Ave",
    "sg:city":"Jersey City",
    "sg:classifiers":[
        {
            "category":"Restaurant",
            "type":"Food & Drink"
        }
    ],
    "sg:phone":"+1 201 656 7266",
    "sg:postcode":"07307",
    "sg:province":"NJ",
    "sg:tags":[
        "american",
        "latin"
    ],
    "sg:website":"www.almalatinacafe.com",
    "wof:name":"Alma Latina Cafe",
    "wof:placetype":"venue"
},
  "geometry": {"coordinates":[-74.042039,40.747822],"type":"Point"}
}