{
  "type": "Feature",
  "properties": {
    "addr:full":"650 S Orange Ave Livingston NJ 07039",
    "addr:housenumber":"650",
    "addr:postcode":"07039",
    "addr:street":"S Orange Ave",
    "iso:country":"US",
    "sg:address":"650 S Orange Ave",
    "sg:city":"Livingston",
    "sg:classifiers":[
        {
            "category":"Social Services",
            "subcategory":"Child Care",
            "type":"Services"
        },
        {
            "category":"Education",
            "subcategory":"Preschool",
            "type":"Public Place"
        },
        {
            "category":"Education",
            "subcategory":"School",
            "type":"Public Place"
        }
    ],
    "sg:phone":"+1 973 758 1070",
    "sg:postcode":"07039",
    "sg:province":"NJ",
    "sg:tags":[
        "elementary",
        "day"
    ],
    "wof:name":"Tutor Time Learning",
    "wof:placetype":"venue"
},
  "geometry": {"coordinates":[-74.321899,40.759499],"type":"Point"}
}