{
  "type": "Feature",
  "properties": {
    "addr:full":"140 Spring St New Providence NJ 07974",
    "addr:housenumber":"140",
    "addr:postcode":"07974",
    "addr:street":"Spring St",
    "iso:country":"US",
    "sg:address":"140 Spring St",
    "sg:city":"New Providence",
    "sg:classifiers":[
        {
            "category":"Wholesale",
            "subcategory":"Apparel",
            "type":"Manufacturing & Wholesale Goods"
        },
        {
            "category":"Manufacturing",
            "subcategory":"Apparel",
            "type":"Manufacturing & Wholesale Goods"
        }
    ],
    "sg:phone":"+1 908 464 2400",
    "sg:postcode":"07974",
    "sg:province":"NJ",
    "sg:tags":[
        "clothing",
        "sportswear"
    ],
    "sg:website":"www.venusknittingmills.com",
    "wof:name":"Venus Knitting Mills Inc",
    "wof:placetype":"venue"
},
  "geometry": {"coordinates":[-74.410122,40.694243],"type":"Point"}
}