{
  "type": "Feature",
  "properties": {
    "addr:full":"23 Briarcliff Rd Saddle River NJ 07458",
    "addr:housenumber":"23",
    "addr:postcode":"07458",
    "addr:street":"Briarcliff Rd",
    "iso:country":"US",
    "sg:address":"23 Briarcliff Rd",
    "sg:city":"Saddle River",
    "sg:classifiers":[
        {
            "category":"Building & Trades",
            "subcategory":"Construction",
            "type":"Services"
        }
    ],
    "sg:phone":"+1 201 327 1591",
    "sg:postcode":"07458",
    "sg:province":"NJ",
    "sg:tags":[
        "contractor",
        "paving",
        "asphalt",
        "general"
    ],
    "wof:name":"Mc Farlane Paving Inc",
    "wof:placetype":"venue"
},
  "geometry": {"coordinates":[-74.10719400000001,41.075692],"type":"Point"}
}