{
  "type": "Feature",
  "properties": {
    "addr:full":"876 US Hwy 206 Hillsborough NJ 08844",
    "addr:housenumber":"876",
    "addr:postcode":"08844",
    "addr:street":"Us Hwy 206",
    "iso:country":"US",
    "sg:address":"876 US Hwy 206",
    "sg:city":"Hillsborough",
    "sg:classifiers":[
        {
            "category":"Retail",
            "subcategory":"Car Wash",
            "type":"Services"
        }
    ],
    "sg:phone":"+1 908 431 1004",
    "sg:postcode":"08844",
    "sg:province":"NJ",
    "sg:tags":[
        "automobile",
        "detail",
        "clean"
    ],
    "wof:name":"Every Little Detail",
    "wof:placetype":"venue"
},
  "geometry": {"coordinates":[-74.65534,40.478038],"type":"Point"}
}