{
  "type": "Feature",
  "properties": {
    "addr:full":"305 E Front St Plainfield NJ 07060",
    "addr:housenumber":"305",
    "addr:postcode":"07060",
    "addr:street":"E Front St",
    "iso:country":"US",
    "sg:address":"305 E Front St",
    "sg:city":"Plainfield",
    "sg:classifiers":[
        {
            "category":"Government",
            "subcategory":"Office",
            "type":"Public Place"
        }
    ],
    "sg:phone":"+1 908 753 3506",
    "sg:postcode":"07060",
    "sg:province":"NJ",
    "sg:tags":[
        "village"
    ],
    "wof:name":"Plainfield Senior Citizens Svc",
    "wof:placetype":"venue"
},
  "geometry": {"coordinates":[-74.419933,40.622462],"type":"Point"}
}