{
  "type": "Feature",
  "properties": {
    "addr:full":"134 33rd St Sea Isle City NJ 08243",
    "addr:housenumber":"134",
    "addr:postcode":"08243",
    "addr:street":"33Rd St;Isle",
    "iso:country":"US",
    "sg:address":"134 33rd St",
    "sg:city":"Sea Isle City",
    "sg:classifiers":[
        {
            "category":"Shopping",
            "subcategory":"Crafts & Fabrics",
            "type":"Retail Goods"
        }
    ],
    "sg:phone":"+1   ",
    "sg:postcode":"08243",
    "sg:province":"NJ",
    "sg:tags":[
        "sewing"
    ],
    "wof:name":"A Garden of Yarn Co",
    "wof:placetype":"venue"
},
  "geometry": {"coordinates":[-74.68763800000001,39.160949],"type":"Point"}
}