{
  "type": "Feature",
  "properties": {
    "iso:country":"US",
    "sg:address":"9 W Cedar St",
    "sg:city":"Metuchen",
    "sg:classifiers":[
        {
            "category":"Personal",
            "subcategory":"Tanning Parlor",
            "type":"Services"
        }
    ],
    "sg:phone":"+1 732 767 9676",
    "sg:postcode":"08840",
    "sg:province":"NJ",
    "sg:tags":[
        "salon"
    ],
    "wof:name":"Pacific Bronze Tanning Salon",
    "wof:placetype":"venue"
},
  "geometry": {"coordinates":[-74.359939,40.529199],"type":"Point"}
}