{
  "type": "Feature",
  "properties": {
    "iso:country":"US",
    "sg:address":"636 Main St",
    "sg:city":"Asbury",
    "sg:classifiers":[
        {
            "category":"Banks & Credit Unions",
            "subcategory":"Investment Brokerage",
            "type":"Services"
        }
    ],
    "sg:phone":"+1 908 730 6278",
    "sg:postcode":"08802",
    "sg:province":"NJ",
    "sg:tags":[
        "advisory",
        "financial"
    ],
    "wof:name":"GE Financial Assurance",
    "wof:placetype":"venue"
},
  "geometry": {"coordinates":[-75.002905,40.634866],"type":"Point"}
}