{
  "type": "Feature",
  "properties": {
    "iso:country":"US",
    "sg:address":"170 Changebridge Rd Bldg C53",
    "sg:city":"Montville",
    "sg:classifiers":[
        {
            "category":"Education",
            "subcategory":"School",
            "type":"Public Place"
        }
    ],
    "sg:phone":"+1 973 784 4786",
    "sg:postcode":"07045",
    "sg:province":"NJ",
    "sg:tags":[
        "high",
        "middle",
        "elementary"
    ],
    "wof:name":"Terranova Group",
    "wof:placetype":"venue"
},
  "geometry": {"coordinates":[-74.36569,40.889845],"type":"Point"}
}