{
  "type": "Feature",
  "properties": {
    "iso:country":"US",
    "sg:address":"1990 State Rte 70",
    "sg:city":"Cherry Hill",
    "sg:classifiers":[
        {
            "category":"Education",
            "subcategory":"Special Training",
            "type":"Public Place"
        }
    ],
    "sg:phone":"+1 856 424 0990",
    "sg:postcode":"08003",
    "sg:province":"NJ",
    "sg:tags":[
        "instruction",
        "music"
    ],
    "wof:name":"Music Garden",
    "wof:placetype":"venue"
},
  "geometry": {"coordinates":[-74.958186,39.899946],"type":"Point"}
}