{
  "type": "Feature",
  "properties": {
    "iso:country":"US",
    "sg:address":"761 Landis Ave",
    "sg:city":"Bridgeton",
    "sg:classifiers":[
        {
            "category":"Food & Beverages",
            "subcategory":"Groceries & Convenience Stores",
            "type":"Retail Goods"
        },
        {
            "category":"Restaurant",
            "type":"Food & Drink"
        }
    ],
    "sg:phone":"+1 856 455 5776",
    "sg:postcode":"08302",
    "sg:province":"NJ",
    "sg:tags":[
        "deli"
    ],
    "wof:name":"Speranzas Deli & Pizzeria",
    "wof:placetype":"venue"
},
  "geometry": {"coordinates":[-75.1354,39.481445],"type":"Point"}
}