{
  "type": "Feature",
  "properties": {
    "iso:country":"US",
    "sg:address":"350 Parsippany Rd",
    "sg:city":"Parsippany",
    "sg:classifiers":[
        {
            "category":"Communications",
            "subcategory":"Radio Station",
            "type":"Services"
        }
    ],
    "sg:phone":"+1 908 872 7931",
    "sg:postcode":"07054",
    "sg:province":"NJ",
    "sg:tags":[
        "broadcast"
    ],
    "wof:name":"Good World",
    "wof:placetype":"venue"
},
  "geometry": {"coordinates":[-74.427021,40.857406],"type":"Point"}
}