{
  "type": "Feature",
  "properties": {
    "addr:full":"3 Ithanell Rd Hopatcong NJ 07843",
    "addr:housenumber":"3",
    "addr:postcode":"07843",
    "addr:street":"Ithanell Rd",
    "iso:country":"US",
    "sg:address":"3 Ithanell Rd",
    "sg:city":"Hopatcong",
    "sg:classifiers":[
        {
            "category":"Personal",
            "type":"Services"
        }
    ],
    "sg:phone":"+1   ",
    "sg:postcode":"07843",
    "sg:province":"NJ",
    "wof:name":"Angel Errands",
    "wof:placetype":"venue"
},
  "geometry": {"coordinates":[-74.64268,40.944258],"type":"Point"}
}