{
  "type": "Feature",
  "properties": {
    "addr:full":"1259 US Hwy 46 Parsippany NJ 07054",
    "addr:housenumber":"1259",
    "addr:postcode":"07054",
    "addr:street":"Us Hwy 46",
    "iso:country":"US",
    "sg:address":"1259 US Hwy 46",
    "sg:city":"Parsippany",
    "sg:classifiers":[
        {
            "category":"Wholesale",
            "subcategory":"Electrical",
            "type":"Manufacturing & Wholesale Goods"
        }
    ],
    "sg:phone":"+1 973 331 1133",
    "sg:postcode":"07054",
    "sg:province":"NJ",
    "sg:tags":[
        "electronic"
    ],
    "wof:name":"FAI Electronics Corp",
    "wof:placetype":"venue"
},
  "geometry": {"coordinates":[-74.38668800000001,40.862899],"type":"Point"}
}