{
  "type": "Feature",
  "properties": {
    "addr:full":"4 Hartford Dr Tinton Falls NJ 07701",
    "addr:housenumber":"4",
    "addr:postcode":"07701",
    "addr:street":"Hartford Dr",
    "iso:country":"US",
    "sg:address":"4 Hartford Dr",
    "sg:city":"Tinton Falls",
    "sg:classifiers":[
        {
            "category":"Social Services",
            "subcategory":"Child Care",
            "type":"Services"
        }
    ],
    "sg:phone":"+1 732 933 4888",
    "sg:postcode":"07701",
    "sg:province":"NJ",
    "wof:name":"Goddard School",
    "wof:placetype":"venue"
},
  "geometry": {"coordinates":[-74.075812,40.329145],"type":"Point"}
}