{
  "type": "Feature",
  "properties": {
    "iso:country":"US",
    "sg:address":"366 Passaic Ave",
    "sg:city":"Nutley",
    "sg:classifiers":[
        {
            "category":"Professional",
            "subcategory":"Employment Agencies",
            "type":"Services"
        }
    ],
    "sg:phone":"+1 973 667 5777",
    "sg:postcode":"07110",
    "sg:province":"NJ",
    "sg:website":"www.statewiderecruitment.com",
    "wof:name":"Statewide Recruitment Services Inc",
    "wof:placetype":"venue"
},
  "geometry": {"coordinates":[-74.153198,40.818699],"type":"Point"}
}