{
  "type": "Feature",
  "properties": {
    "addr:full":"145 Maplewood Ave Maplewood NJ 07040",
    "addr:housenumber":"145",
    "addr:postcode":"07040",
    "addr:street":"Maplewood Ave",
    "iso:country":"US",
    "sg:address":"145 Maplewood Ave",
    "sg:city":"Maplewood",
    "sg:classifiers":[
        {
            "category":"Real Estate",
            "subcategory":"Real Estate Agent",
            "type":"Services"
        }
    ],
    "sg:phone":"+1 973 378 8300",
    "sg:postcode":"07040",
    "sg:province":"NJ",
    "wof:name":"Era Burgdorff Realtors",
    "wof:placetype":"venue"
},
  "geometry": {"coordinates":[-74.27397999999999,40.733632],"type":"Point"}
}