{
  "type": "Feature",
  "properties": {
    "addr:full":"56 N Haddon Ave Haddonfield NJ 08033",
    "addr:housenumber":"56",
    "addr:postcode":"08033",
    "addr:street":"N Haddon Ave",
    "iso:country":"US",
    "sg:address":"56 N Haddon Ave",
    "sg:city":"Haddonfield",
    "sg:classifiers":[
        {
            "category":"Professional",
            "subcategory":"Computer Services",
            "type":"Services"
        }
    ],
    "sg:phone":"+1 856 354 2200",
    "sg:postcode":"08033",
    "sg:province":"NJ",
    "sg:tags":[
        "publisher",
        "developer",
        "software"
    ],
    "wof:name":"Um Equity Corp",
    "wof:placetype":"venue"
},
  "geometry": {"coordinates":[-75.034088,39.899059],"type":"Point"}
}