{
  "type": "Feature",
  "properties": {
    "addr:full":"545 Palmer Ave Keansburg NJ 07734",
    "addr:housenumber":"545",
    "addr:postcode":"07734",
    "addr:street":"Palmer Ave",
    "iso:country":"US",
    "sg:address":"545 Palmer Ave",
    "sg:city":"Keansburg",
    "sg:classifiers":[
        {
            "category":"Building & Trades",
            "subcategory":"Landscaping Services",
            "type":"Services"
        }
    ],
    "sg:phone":"+1 732 787 9075",
    "sg:postcode":"07734",
    "sg:province":"NJ",
    "wof:name":"Minson Landscape",
    "wof:placetype":"venue"
},
  "geometry": {"coordinates":[-74.13168,40.433575],"type":"Point"}
}