{
  "type": "Feature",
  "properties": {
    "addr:full":"305 Grove St Jersey City NJ 07302",
    "addr:housenumber":"305",
    "addr:postcode":"07302",
    "addr:street":"Grove St",
    "iso:country":"US",
    "sg:address":"305 Grove St",
    "sg:city":"Jersey City",
    "sg:classifiers":[
        {
            "category":"Building & Trades",
            "subcategory":"Construction",
            "type":"Services"
        }
    ],
    "sg:phone":"+1 201 413 9110",
    "sg:postcode":"07302",
    "sg:province":"NJ",
    "sg:tags":[
        "contractor"
    ],
    "wof:name":"Best Rate Construction Inc",
    "wof:placetype":"venue"
},
  "geometry": {"coordinates":[-74.043549,40.718875],"type":"Point"}
}