{
  "type": "Feature",
  "properties": {
    "addr:full":"39 W Northfield Rd Livingston NJ 07039",
    "addr:housenumber":"39",
    "addr:postcode":"07039",
    "addr:street":"W Northfield Rd",
    "iso:country":"US",
    "sg:address":"39 W Northfield Rd",
    "sg:city":"Livingston",
    "sg:classifiers":[
        {
            "category":"Restaurant",
            "type":"Food & Drink"
        }
    ],
    "sg:phone":"+1   ",
    "sg:postcode":"07039",
    "sg:province":"NJ",
    "sg:tags":[
        "eating"
    ],
    "wof:name":"Bally Total Fitness",
    "wof:placetype":"venue"
},
  "geometry": {"coordinates":[-74.32513,40.774585],"type":"Point"}
}