{
  "type": "Feature",
  "properties": {
    "addr:full":"450 W Saddle River Rd Saddle River NJ 07458",
    "addr:housenumber":"450",
    "addr:postcode":"07458",
    "addr:street":"W Saddle River Rd",
    "iso:country":"US",
    "sg:address":"450 W Saddle River Rd",
    "sg:city":"Saddle River",
    "sg:classifiers":[
        {
            "category":"Professional",
            "subcategory":"Business Services",
            "type":"Services"
        }
    ],
    "sg:phone":"+1   ",
    "sg:postcode":"07458",
    "sg:province":"NJ",
    "wof:name":"Myers Enterprises",
    "wof:placetype":"venue"
},
  "geometry": {"coordinates":[-74.097915,41.069693],"type":"Point"}
}