{
  "type": "Feature",
  "properties": {
    "iso:country":"US",
    "sg:address":"354 Main St",
    "sg:city":"West Orange",
    "sg:classifiers":[
        {
            "category":"Health Services",
            "subcategory":"Doctor",
            "type":"Services"
        }
    ],
    "sg:phone":"+1 973 731 2201",
    "sg:postcode":"07052",
    "sg:province":"NJ",
    "wof:name":"Layne Trevor MD",
    "wof:placetype":"venue"
},
  "geometry": {"coordinates":[-74.232671,40.789952],"type":"Point"}
}