{
  "type": "Feature",
  "properties": {
    "iso:country":"US",
    "sg:address":"25 W Broadway",
    "sg:city":"Paterson",
    "sg:classifiers":[
        {
            "category":"Bus Charters",
            "type":"Transportation"
        }
    ],
    "sg:phone":"+1 973 279 4044",
    "sg:postcode":"07505",
    "sg:province":"NJ",
    "sg:tags":[
        "company"
    ],
    "wof:name":"Spanish Transportation Corp",
    "wof:placetype":"venue"
},
  "geometry": {"coordinates":[-74.17393300000001,40.919698],"type":"Point"}
}