{
  "type": "Feature",
  "properties": {
    "addr:full":"519 Sicklerville Rd Sicklerville NJ 08081",
    "addr:housenumber":"519",
    "addr:postcode":"08081",
    "addr:street":"Sicklerville Rd",
    "iso:country":"US",
    "sg:address":"519 Sicklerville Rd",
    "sg:city":"Sicklerville",
    "sg:classifiers":[
        {
            "category":"Banks & Credit Unions",
            "subcategory":"Bank",
            "type":"Services"
        }
    ],
    "sg:phone":"+1   ",
    "sg:postcode":"08081",
    "sg:province":"NJ",
    "sg:tags":[
        "depository",
        "banking"
    ],
    "wof:name":"Western Union To Pick Up or SE",
    "wof:placetype":"venue"
},
  "geometry": {"coordinates":[-74.97744899999999,39.722003],"type":"Point"}
}