{
  "type": "Feature",
  "properties": {
    "iso:country":"US",
    "sg:address":"400 State Rte 38",
    "sg:city":"Moorestown",
    "sg:classifiers":[
        {
            "category":"Shopping",
            "type":"Retail Goods"
        },
        {
            "category":"Shopping",
            "subcategory":"Gifts & Souvenirs",
            "type":"Retail Goods"
        }
    ],
    "sg:phone":"+1 856 273 6362",
    "sg:postcode":"08057",
    "sg:province":"NJ",
    "sg:tags":[
        "shop",
        "merchandise"
    ],
    "sg:website":"www.candleman.com",
    "wof:name":"Candleman",
    "wof:placetype":"venue"
},
  "geometry": {"coordinates":[-74.963235,39.946261],"type":"Point"}
}