{
  "type": "Feature",
  "properties": {
    "iso:country":"US",
    "sg:address":"17 Airport Rd",
    "sg:city":"Morristown",
    "sg:classifiers":[
        {
            "category":"Airport",
            "type":"Transportation"
        }
    ],
    "sg:phone":"+1 973 285 7519",
    "sg:postcode":"07960",
    "sg:province":"NJ",
    "sg:tags":[
        "aircraft",
        "maintenance"
    ],
    "wof:name":"GSC Partners",
    "wof:placetype":"venue"
},
  "geometry": {"coordinates":[-74.424554,40.792763],"type":"Point"}
}