{
  "type": "Feature",
  "properties": {
    "addr:full":"708 Liberty St Trenton NJ 08611",
    "addr:housenumber":"708",
    "addr:postcode":"08611",
    "addr:street":"Liberty St",
    "iso:country":"US",
    "sg:address":"708 Liberty St",
    "sg:city":"Trenton",
    "sg:classifiers":[
        {
            "category":"Local Transit",
            "type":"Transportation"
        }
    ],
    "sg:phone":"+1 609 393 0688",
    "sg:postcode":"08611",
    "sg:province":"NJ",
    "sg:tags":[
        "ambulance"
    ],
    "sg:website":"www.trentonems.com",
    "wof:name":"Trenton Emergency Medical Svc",
    "wof:placetype":"venue"
},
  "geometry": {"coordinates":[-74.74021,40.206745],"type":"Point"}
}