{
  "type": "Feature",
  "properties": {
    "addr:full":"1945 Amwell Rd Somerset NJ 08873",
    "addr:housenumber":"1945",
    "addr:postcode":"08873",
    "addr:street":"Amwell Rd",
    "iso:country":"US",
    "sg:address":"1945 Amwell Rd",
    "sg:city":"Somerset",
    "sg:classifiers":[
        {
            "category":"Building & Trades",
            "subcategory":"Landscaping Services",
            "type":"Services"
        }
    ],
    "sg:phone":"+1 732 873 8580",
    "sg:postcode":"08873",
    "sg:province":"NJ",
    "wof:name":"Picture Perfect Landscaping",
    "wof:placetype":"venue"
},
  "geometry": {"coordinates":[-74.546785,40.498124],"type":"Point"}
}