{
  "type": "Feature",
  "properties": {
    "iso:country":"US",
    "sg:address":"91 Hilltop Trl",
    "sg:city":"Sparta",
    "sg:classifiers":[
        {
            "category":"Organizations",
            "subcategory":"Religious Organization",
            "type":"Services"
        }
    ],
    "sg:phone":"+1   ",
    "sg:postcode":"07871",
    "sg:province":"NJ",
    "wof:name":"R B Hilderbrand Rev",
    "wof:placetype":"venue"
},
  "geometry": {"coordinates":[-74.64498500000001,41.020409],"type":"Point"}
}