{
  "type": "Feature",
  "properties": {
    "addr:full":"116 Lakeview Ave Clifton NJ 07011",
    "addr:housenumber":"116",
    "addr:postcode":"07011",
    "addr:street":"Lakeview Ave",
    "iso:country":"US",
    "sg:address":"116 Lakeview Ave",
    "sg:city":"Clifton",
    "sg:classifiers":[
        {
            "category":"Building & Trades",
            "subcategory":"Pest Control",
            "type":"Services"
        }
    ],
    "sg:phone":"+1 973 253 1432",
    "sg:postcode":"07011",
    "sg:province":"NJ",
    "wof:name":"De Bug Pest Control",
    "wof:placetype":"venue"
},
  "geometry": {"coordinates":[-74.136965,40.879602],"type":"Point"}
}