{
  "type": "Feature",
  "properties": {
    "addr:full":"39 Killian Pl Totowa NJ 07512",
    "addr:housenumber":"39",
    "addr:postcode":"07512",
    "addr:street":"Killian Pl",
    "iso:country":"US",
    "sg:address":"39 Killian Pl",
    "sg:city":"Totowa",
    "sg:classifiers":[
        {
            "category":"Professional",
            "type":"Services"
        }
    ],
    "sg:phone":"+1 973 595 1000",
    "sg:postcode":"07512",
    "sg:province":"NJ",
    "sg:tags":[
        "establishment"
    ],
    "wof:name":"K & R Bros Kitchen Instltn",
    "wof:placetype":"venue"
},
  "geometry": {"coordinates":[-74.213275,40.906324],"type":"Point"}
}