{
  "type": "Feature",
  "properties": {
    "iso:country":"US",
    "sg:address":"167 Mount Bethel Rd",
    "sg:city":"Warren",
    "sg:classifiers":[
        {
            "category":"Organizations",
            "subcategory":"Religious Organization",
            "type":"Services"
        }
    ],
    "sg:phone":"+1 908 647 1075",
    "sg:postcode":"07059",
    "sg:province":"NJ",
    "sg:tags":[
        "church"
    ],
    "sg:website":"www.ourladyofthemount.org",
    "wof:name":"Our Lady Of The Mt",
    "wof:placetype":"venue"
},
  "geometry": {"coordinates":[-74.51347199999999,40.636979],"type":"Point"}
}