{
  "type": "Feature",
  "properties": {
    "iso:country":"US",
    "sg:address":"701 Kings Hwy S",
    "sg:city":"Cherry Hill",
    "sg:classifiers":[
        {
            "category":"Shopping",
            "subcategory":"Discount & Variety Stores",
            "type":"Retail Goods"
        }
    ],
    "sg:phone":"+1   ",
    "sg:postcode":"08034",
    "sg:province":"NJ",
    "sg:website":"www.dollargeneral.com",
    "wof:name":"Dollar General",
    "wof:placetype":"venue"
},
  "geometry": {"coordinates":[-75.01827900000001,39.906746],"type":"Point"}
}