{
  "type": "Feature",
  "properties": {
    "iso:country":"US",
    "sg:address":"545 Valley Brook Ave",
    "sg:city":"Lyndhurst",
    "sg:classifiers":[
        {
            "category":"Shopping",
            "subcategory":"Shoes",
            "type":"Retail Goods"
        }
    ],
    "sg:phone":"+1 201 531 8674",
    "sg:postcode":"07071",
    "sg:province":"NJ",
    "sg:tags":[
        "store"
    ],
    "wof:name":"T O S I Group Company of Italy",
    "wof:placetype":"venue"
},
  "geometry": {"coordinates":[-74.119598,40.809299],"type":"Point"}
}