{
  "type": "Feature",
  "properties": {
    "addr:full":"309 Washington St Hackettstown NJ 07840",
    "addr:housenumber":"309",
    "addr:postcode":"07840",
    "addr:street":"Washington St",
    "iso:country":"US",
    "sg:address":"309 Washington St",
    "sg:city":"Hackettstown",
    "sg:classifiers":[
        {
            "category":"Retail",
            "subcategory":"Repair Shop",
            "type":"Services"
        }
    ],
    "sg:phone":"+1   ",
    "sg:postcode":"07840",
    "sg:province":"NJ",
    "wof:name":"1 Hour Emergency Locksmith",
    "wof:placetype":"venue"
},
  "geometry": {"coordinates":[-74.828838,40.851581],"type":"Point"}
}