{
  "type": "Feature",
  "properties": {
    "addr:full":"519 Jefferson St Hoboken NJ 07030",
    "addr:housenumber":"519",
    "addr:postcode":"07030",
    "addr:street":"Jefferson St",
    "iso:country":"US",
    "sg:address":"519 Jefferson St",
    "sg:city":"Hoboken",
    "sg:classifiers":[
        {
            "category":"Home & Garden",
            "subcategory":"Home Furnishings",
            "type":"Retail Goods"
        }
    ],
    "sg:phone":"+1   ",
    "sg:postcode":"07030",
    "sg:province":"NJ",
    "wof:name":"Aaraa",
    "wof:placetype":"venue"
},
  "geometry": {"coordinates":[-74.03638599999999,40.744469],"type":"Point"}
}