{
  "type": "Feature",
  "properties": {
    "addr:full":"131 Manalapan Rd Spotswood NJ 08884",
    "addr:housenumber":"131",
    "addr:postcode":"08884",
    "addr:street":"Manalapan Rd",
    "iso:country":"US",
    "sg:address":"131 Manalapan Rd",
    "sg:city":"Spotswood",
    "sg:classifiers":[
        {
            "category":"Retail",
            "subcategory":"Repair Shop",
            "type":"Services"
        }
    ],
    "sg:phone":"+1   ",
    "sg:postcode":"08884",
    "sg:province":"NJ",
    "wof:name":"Aaaaaaa Action Clean Up",
    "wof:placetype":"venue"
},
  "geometry": {"coordinates":[-74.396269,40.38833],"type":"Point"}
}