{
  "type": "Feature",
  "properties": {
    "addr:full":"2125 State Rte 88 Brick NJ 08724",
    "addr:housenumber":"2125",
    "addr:postcode":"08724",
    "addr:street":"State Rte 88",
    "iso:country":"US",
    "sg:address":"2125 State Rte 88",
    "sg:city":"Brick",
    "sg:classifiers":[
        {
            "category":"Social Services",
            "type":"Services"
        }
    ],
    "sg:phone":"+1 732 899 7942",
    "sg:postcode":"08724",
    "sg:province":"NJ",
    "sg:tags":[
        "care",
        "center",
        "day"
    ],
    "wof:name":"ACLL Corp",
    "wof:placetype":"venue"
},
  "geometry": {"coordinates":[-74.102794,40.076257],"type":"Point"}
}