{
  "type": "Feature",
  "properties": {
    "addr:full":"570 Mine Brook Rd Bernardsville NJ 07924",
    "addr:housenumber":"570",
    "addr:postcode":"07924",
    "addr:street":"Mine Brook Rd",
    "iso:country":"US",
    "sg:address":"570 Mine Brook Rd",
    "sg:city":"Bernardsville",
    "sg:classifiers":[
        {
            "category":"Retail",
            "subcategory":"Animal Services",
            "type":"Services"
        }
    ],
    "sg:phone":"+1 908 766 3929",
    "sg:postcode":"07924",
    "sg:province":"NJ",
    "wof:name":"Bernardsville Country Kennels",
    "wof:placetype":"venue"
},
  "geometry": {"coordinates":[-74.606566,40.69738],"type":"Point"}
}