{
  "type": "Feature",
  "properties": {
    "iso:country":"US",
    "sg:address":"243 Quakerbridge Mall",
    "sg:city":"Lawrenceville",
    "sg:classifiers":[
        {
            "category":"Shopping",
            "subcategory":"Clothing, Apparel, & Fashions",
            "type":"Retail Goods"
        }
    ],
    "sg:phone":"+1 609 275 6621",
    "sg:postcode":"08648",
    "sg:province":"NJ",
    "sg:tags":[
        "sportswear"
    ],
    "wof:name":"Demo",
    "wof:placetype":"venue"
},
  "geometry": {"coordinates":[-74.68435599999999,40.288853],"type":"Point"}
}