{
  "type": "Feature",
  "properties": {
    "addr:full":"381 Belle Mead Griggstwn Rd Belle Mead NJ 08502",
    "addr:housenumber":"381",
    "addr:postcode":"08502",
    "addr:street":"Belle Mead Griggstwn Rd",
    "iso:country":"US",
    "sg:address":"381 Belle Mead Griggstwn Rd",
    "sg:city":"Belle Mead",
    "sg:classifiers":[
        {
            "category":"Building & Trades",
            "subcategory":"Construction",
            "type":"Services"
        }
    ],
    "sg:phone":"+1 908 281 7702",
    "sg:postcode":"08502",
    "sg:province":"NJ",
    "sg:tags":[
        "house",
        "builder",
        "deck"
    ],
    "wof:name":"Statewide Vinyl Decking Inc",
    "wof:placetype":"venue"
},
  "geometry": {"coordinates":[-74.632103,40.444255],"type":"Point"}
}