{
  "type": "Feature",
  "properties": {
    "iso:country":"US",
    "sg:address":"48 Mountainview Blvd",
    "sg:city":"Wayne",
    "sg:classifiers":[
        {
            "category":"Banks & Credit Unions",
            "subcategory":"Atm",
            "type":"Services"
        }
    ],
    "sg:phone":"+1 973 696 1700",
    "sg:postcode":"07470",
    "sg:province":"NJ",
    "sg:tags":[
        "bankruptcy"
    ],
    "wof:name":"Zazella Alfred J Attorney",
    "wof:placetype":"venue"
},
  "geometry": {"coordinates":[-74.265198,40.91],"type":"Point"}
}