{
  "type": "Feature",
  "properties": {
    "iso:country":"US",
    "sg:address":"308 Watchung Ave",
    "sg:city":"Plainfield",
    "sg:classifiers":[
        {
            "category":"Restaurant",
            "type":"Food & Drink"
        }
    ],
    "sg:phone":"+1   ",
    "sg:postcode":"07060",
    "sg:province":"NJ",
    "sg:tags":[
        "bar"
    ],
    "wof:name":"Rusty Spigot",
    "wof:placetype":"venue"
},
  "geometry": {"coordinates":[-74.419045,40.618522],"type":"Point"}
}