{
  "type": "Feature",
  "properties": {
    "iso:country":"US",
    "sg:address":"667 Ave C",
    "sg:city":"Bayonne",
    "sg:classifiers":[
        {
            "category":"Organizations",
            "subcategory":"Community Association",
            "type":"Services"
        }
    ],
    "sg:phone":"+1 201 436 0035",
    "sg:postcode":"07002",
    "sg:province":"NJ",
    "wof:name":"Knights of Columbias",
    "wof:placetype":"venue"
},
  "geometry": {"coordinates":[-74.11539999999999,40.671203],"type":"Point"}
}