{
  "type": "Feature",
  "properties": {
    "iso:country":"US",
    "sg:address":"911 76th St",
    "sg:city":"North Bergen",
    "sg:classifiers":[
        {
            "category":"Professional",
            "subcategory":"Computer Services",
            "type":"Services"
        }
    ],
    "sg:phone":"+1   ",
    "sg:postcode":"07047",
    "sg:province":"NJ",
    "sg:tags":[
        "datum"
    ],
    "wof:name":"German Rodriguez",
    "wof:placetype":"venue"
},
  "geometry": {"coordinates":[-74.01165,40.801677],"type":"Point"}
}