{
  "type": "Feature",
  "properties": {
    "addr:full":"8 Tanner St Haddonfield NJ 08033",
    "addr:housenumber":"8",
    "addr:postcode":"08033",
    "addr:street":"Tanner St",
    "iso:country":"US",
    "sg:address":"8 Tanner St",
    "sg:city":"Haddonfield",
    "sg:classifiers":[
        {
            "category":"Shopping",
            "subcategory":"Jewelry",
            "type":"Retail Goods"
        },
        {
            "category":"Retail",
            "subcategory":"Repair Shop",
            "type":"Services"
        }
    ],
    "sg:phone":"+1 856 427 4444",
    "sg:postcode":"08033",
    "sg:province":"NJ",
    "sg:tags":[
        "part",
        "watch",
        "clock"
    ],
    "sg:website":"http://www.hughsclocks.com",
    "wof:name":"Hugh's Clock Shop",
    "wof:placetype":"venue"
},
  "geometry": {"coordinates":[-75.03388200000001,39.897393],"type":"Point"}
}