{
  "type": "Feature",
  "properties": {
    "iso:country":"US",
    "sg:address":"5 Brandywine Ct",
    "sg:city":"Succasunna",
    "sg:classifiers":[
        {
            "category":"Utilities",
            "subcategory":"Refuse",
            "type":"Services"
        }
    ],
    "sg:phone":"+1 973 598 9800",
    "sg:postcode":"07876",
    "sg:province":"NJ",
    "sg:tags":[
        "disposal",
        "waste"
    ],
    "sg:website":"www.bluediamonddisposal.com",
    "wof:name":"Blue Diamond Disposal Inc",
    "wof:placetype":"venue"
},
  "geometry": {"coordinates":[-74.68732799999999,40.85491],"type":"Point"}
}