{
  "type": "Feature",
  "properties": {
    "iso:country":"US",
    "sg:address":"511 New Brunswick Ave Ste 2",
    "sg:city":"Perth Amboy",
    "sg:classifiers":[
        {
            "category":"Health Services",
            "subcategory":"Doctor",
            "type":"Services"
        }
    ],
    "sg:phone":"+1 732 376 9200",
    "sg:postcode":"08861",
    "sg:province":"NJ",
    "wof:name":"ABC Pediatrics",
    "wof:placetype":"venue"
},
  "geometry": {"coordinates":[-74.280839,40.518235],"type":"Point"}
}