{
  "type": "Feature",
  "properties": {
    "iso:country":"US",
    "sg:address":"900 Ocean Ave",
    "sg:city":"Bradley Beach",
    "sg:classifiers":[
        {
            "category":"Travel",
            "subcategory":"Hotels & Motels",
            "type":"Entertainment"
        }
    ],
    "sg:phone":"+1 732 774 7000",
    "sg:postcode":"07720",
    "sg:province":"NJ",
    "sg:tags":[
        "operation"
    ],
    "wof:name":"Bradley Beach Inn",
    "wof:placetype":"venue"
},
  "geometry": {"coordinates":[-74.00619399999999,40.204957],"type":"Point"}
}