{
  "type": "Feature",
  "properties": {
    "addr:full":"867 Saint Georges Ave Rahway NJ 07065",
    "addr:housenumber":"867",
    "addr:postcode":"07065",
    "addr:street":"Saint Georges Ave",
    "iso:country":"US",
    "sg:address":"867 Saint Georges Ave",
    "sg:city":"Rahway",
    "sg:classifiers":[
        {
            "category":"Health Services",
            "subcategory":"Clinic",
            "type":"Services"
        }
    ],
    "sg:phone":"+1   ",
    "sg:postcode":"07065",
    "sg:province":"NJ",
    "sg:tags":[
        "specialty",
        "outpatient"
    ],
    "wof:name":"Handler Kenneth B S Rpt",
    "wof:placetype":"venue"
},
  "geometry": {"coordinates":[-74.28879999999999,40.605351],"type":"Point"}
}