{
  "type": "Feature",
  "properties": {
    "iso:country":"US",
    "sg:address":"13 Bostwick Ave",
    "sg:city":"Jersey City",
    "sg:classifiers":[
        {
            "category":"Social Services",
            "subcategory":"Child Care",
            "type":"Services"
        }
    ],
    "sg:phone":"+1 201 915 0128",
    "sg:postcode":"07305",
    "sg:province":"NJ",
    "sg:tags":[
        "day"
    ],
    "wof:name":"Small World Daycare Center",
    "wof:placetype":"venue"
},
  "geometry": {"coordinates":[-74.081784,40.707894],"type":"Point"}
}