{
  "type": "Feature",
  "properties": {
    "iso:country":"US",
    "sg:address":"901 Atlantic Ave",
    "sg:city":"Egg Harbor City",
    "sg:classifiers":[
        {
            "category":"Social Services",
            "type":"Services"
        }
    ],
    "sg:phone":"+1   ",
    "sg:postcode":"08215",
    "sg:province":"NJ",
    "sg:tags":[
        "rehabilitation",
        "center"
    ],
    "wof:name":"Codi",
    "wof:placetype":"venue"
},
  "geometry": {"coordinates":[-74.64585700000001,39.525096],"type":"Point"}
}