{
  "type": "Feature",
  "properties": {
    "addr:full":"1390 State Rte 36 Hazlet NJ 07730",
    "addr:housenumber":"1390",
    "addr:postcode":"07730",
    "addr:street":"State Rte 36",
    "iso:country":"US",
    "sg:address":"1390 State Rte 36",
    "sg:city":"Hazlet",
    "sg:classifiers":[
        {
            "category":"Professional",
            "subcategory":"Lawyer & Legal Services",
            "type":"Services"
        }
    ],
    "sg:phone":"+1 732 888 4400",
    "sg:postcode":"07730",
    "sg:province":"NJ",
    "sg:tags":[
        "attorney"
    ],
    "wof:name":"Marc B Schram PC",
    "wof:placetype":"venue"
},
  "geometry": {"coordinates":[-74.190046,40.428909],"type":"Point"}
}