{
  "type": "Feature",
  "properties": {
    "iso:country":"US",
    "sg:address":"1 Centennial Ave",
    "sg:city":"Piscataway",
    "sg:classifiers":[
        {
            "category":"Professional",
            "subcategory":"Management & Consulting",
            "type":"Services"
        }
    ],
    "sg:phone":"+1 732 980 3366",
    "sg:postcode":"08854",
    "sg:province":"NJ",
    "sg:tags":[
        "marketing",
        "consultant"
    ],
    "sg:website":"www.theamc.com",
    "wof:name":"Associated Merchandising Corp",
    "wof:placetype":"venue"
},
  "geometry": {"coordinates":[-74.49772299999999,40.54257],"type":"Point"}
}