{
  "type": "Feature",
  "properties": {
    "iso:country":"US",
    "sg:address":"1943 US Highway 9 N",
    "sg:city":"Cape May Court House",
    "sg:classifiers":[
        {
            "category":"Shopping",
            "subcategory":"Pets & Pet Supplies",
            "type":"Retail Goods"
        }
    ],
    "sg:phone":"+1 609 624 3322",
    "sg:postcode":"08210",
    "sg:province":"NJ",
    "sg:tags":[
        "store"
    ],
    "wof:name":"Woodland Pet Boutique",
    "wof:placetype":"venue"
},
  "geometry": {"coordinates":[-74.857764,39.037535],"type":"Point"}
}