{
  "type": "Feature",
  "properties": {
    "addr:full":"85 Godwin Ave Midland Park NJ 07432",
    "addr:housenumber":"85",
    "addr:postcode":"07432",
    "addr:street":"Godwin Ave",
    "iso:country":"US",
    "sg:address":"85 Godwin Ave",
    "sg:city":"Midland Park",
    "sg:classifiers":[
        {
            "category":"Education",
            "subcategory":"Dance Studio",
            "type":"Public Place"
        }
    ],
    "sg:phone":"+1 201 670 4422",
    "sg:postcode":"07432",
    "sg:province":"NJ",
    "sg:tags":[
        "instruction",
        "dancing"
    ],
    "sg:website":"www.misspatti.com",
    "wof:name":"Miss Patti's School Of Dance",
    "wof:placetype":"venue"
},
  "geometry": {"coordinates":[-74.138171,40.984773],"type":"Point"}
}