{
  "type": "Feature",
  "properties": {
    "iso:country":"US",
    "sg:address":"516 Pirate Ln",
    "sg:city":"Manahawkin",
    "sg:classifiers":[
        {
            "category":"Retail",
            "subcategory":"Repair Shop",
            "type":"Services"
        }
    ],
    "sg:phone":"+1 609 597 9562",
    "sg:postcode":"08050",
    "sg:province":"NJ",
    "sg:tags":[
        "upholsterer"
    ],
    "wof:name":"Johnny's Upholstery",
    "wof:placetype":"venue"
},
  "geometry": {"coordinates":[-74.269341,39.740936],"type":"Point"}
}