{
  "type": "Feature",
  "properties": {
    "iso:country":"US",
    "sg:address":"114 Beach St",
    "sg:city":"Rockaway",
    "sg:classifiers":[
        {
            "category":"Wholesale",
            "subcategory":"Home Furnishings",
            "type":"Manufacturing & Wholesale Goods"
        }
    ],
    "sg:phone":"+1 973 627 2200",
    "sg:postcode":"07866",
    "sg:province":"NJ",
    "wof:name":"Levolor Lorentzen Inc",
    "wof:placetype":"venue"
},
  "geometry": {"coordinates":[-74.504468,40.901214],"type":"Point"}
}