{
  "type": "Feature",
  "properties": {
    "iso:country":"US",
    "sg:address":"478 Roseville Ave",
    "sg:city":"Newark",
    "sg:classifiers":[
        {
            "category":"Personal",
            "subcategory":"Beauty Salon",
            "type":"Services"
        }
    ],
    "sg:phone":"+1 973 483 9350",
    "sg:postcode":"07107",
    "sg:province":"NJ",
    "sg:tags":[
        "shop"
    ],
    "wof:name":"Ineslees Unisex",
    "wof:placetype":"venue"
},
  "geometry": {"coordinates":[-74.18459300000001,40.767857],"type":"Point"}
}