{
  "type": "Feature",
  "properties": {
    "addr:full":"281 Gemini Dr Somerville NJ 08844",
    "addr:housenumber":"281",
    "addr:postcode":"08844",
    "addr:street":"Gemini Dr",
    "iso:country":"US",
    "sg:address":"281 Gemini Dr",
    "sg:city":"Somerville",
    "sg:classifiers":[
        {
            "category":"Real Estate",
            "subcategory":"Real Estate Agent",
            "type":"Services"
        }
    ],
    "sg:phone":"+1   ",
    "sg:postcode":"08844",
    "sg:province":"NJ",
    "wof:name":"Meadows Condominium Assoc",
    "wof:placetype":"venue"
},
  "geometry": {"coordinates":[-74.66461099999999,40.503431],"type":"Point"}
}