{
  "type": "Feature",
  "properties": {
    "iso:country":"US",
    "sg:address":"45 Cross Ave",
    "sg:city":"Midland Park",
    "sg:classifiers":[
        {
            "category":"Building & Trades",
            "subcategory":"Pest Control",
            "type":"Services"
        }
    ],
    "sg:phone":"+1 201 447 2530",
    "sg:postcode":"07432",
    "sg:province":"NJ",
    "sg:website":"www.horizonpestcontrol.com",
    "wof:name":"Horizon Termite & Pest Control",
    "wof:placetype":"venue"
},
  "geometry": {"coordinates":[-74.142456,40.989496],"type":"Point"}
}