{
  "type": "Feature",
  "properties": {
    "iso:country":"US",
    "sg:address":"375 20th Ave",
    "sg:city":"Paterson",
    "sg:classifiers":[
        {
            "category":"Retail",
            "subcategory":"Laundry & Dry Cleaning",
            "type":"Services"
        }
    ],
    "sg:phone":"+1   ",
    "sg:postcode":"07513",
    "sg:province":"NJ",
    "wof:name":"At Your Service Cleaning",
    "wof:placetype":"venue"
},
  "geometry": {"coordinates":[-74.154042,40.908241],"type":"Point"}
}