{
  "type": "Feature",
  "properties": {
    "addr:full":"733 Broadway Newark NJ 07104",
    "addr:housenumber":"733",
    "addr:postcode":"07104",
    "addr:street":"Broadway",
    "iso:country":"US",
    "sg:address":"733 Broadway",
    "sg:city":"Newark",
    "sg:classifiers":[
        {
            "category":"Shopping",
            "subcategory":"Shoes",
            "type":"Retail Goods"
        }
    ],
    "sg:phone":"+1   ",
    "sg:postcode":"07104",
    "sg:province":"NJ",
    "sg:tags":[
        "shoe",
        "store"
    ],
    "wof:name":"Payless Shoesource",
    "wof:placetype":"venue"
},
  "geometry": {"coordinates":[-74.159751,40.774201],"type":"Point"}
}