{
  "type": "Feature",
  "properties": {
    "iso:country":"US",
    "sg:address":"228 Main St",
    "sg:city":"Hackettstown",
    "sg:classifiers":[
        {
            "category":"Local Transit",
            "type":"Transportation"
        }
    ],
    "sg:phone":"+1 908 684 4470",
    "sg:postcode":"07840",
    "sg:province":"NJ",
    "sg:tags":[
        "passenger",
        "limousine"
    ],
    "wof:name":"Sterling Limousine Service",
    "wof:placetype":"venue"
},
  "geometry": {"coordinates":[-74.82696799999999,40.851654],"type":"Point"}
}