{
  "type": "Feature",
  "properties": {
    "iso:country":"US",
    "sg:address":"623 Gravelly Hollow Rd",
    "sg:city":"Medford",
    "sg:classifiers":[
        {
            "category":"Building & Trades",
            "subcategory":"Landscaping Services",
            "type":"Services"
        }
    ],
    "sg:phone":"+1 609 953 7943",
    "sg:postcode":"08055",
    "sg:province":"NJ",
    "sg:tags":[
        "contracting",
        "contractor",
        "garden",
        "landscape",
        "supply"
    ],
    "wof:name":"Laurel Oak Landscaping",
    "wof:placetype":"venue"
},
  "geometry": {"coordinates":[-74.820729,39.84271],"type":"Point"}
}