{
  "type": "Feature",
  "properties": {
    "addr:full":"993 S Atlantic Ave Haddonfield NJ 08033",
    "addr:housenumber":"993",
    "addr:postcode":"08033",
    "addr:street":"S Atlantic Ave",
    "iso:country":"US",
    "sg:address":"993 S Atlantic Ave",
    "sg:city":"Haddonfield",
    "sg:classifiers":[
        {
            "category":"Social Services",
            "type":"Services"
        }
    ],
    "sg:phone":"+1 856 429 6919",
    "sg:postcode":"08033",
    "sg:province":"NJ",
    "wof:name":"Haddonfield Soccer Club",
    "wof:placetype":"venue"
},
  "geometry": {"coordinates":[-75.02896,39.884724],"type":"Point"}
}