{
  "type": "Feature",
  "properties": {
    "iso:country":"US",
    "sg:address":"233 Schooner Rd",
    "sg:city":"Manahawkin",
    "sg:classifiers":[
        {
            "category":"Farming",
            "subcategory":"Fish & Marine Products",
            "type":"Manufacturing & Wholesale Goods"
        }
    ],
    "sg:phone":"+1 609 698 9577",
    "sg:postcode":"08050",
    "sg:province":"NJ",
    "sg:tags":[
        "fishing"
    ],
    "wof:name":"Traveller 2 Inc",
    "wof:placetype":"venue"
},
  "geometry": {"coordinates":[-74.292682,39.743836],"type":"Point"}
}