{
  "type": "Feature",
  "properties": {
    "addr:full":"3346 Bargaintown Rd Egg Harbor Twp NJ 08234",
    "addr:housenumber":"3346",
    "addr:postcode":"08234",
    "addr:street":"Bargaintown Rd",
    "iso:country":"US",
    "sg:address":"3346 Bargaintown Rd",
    "sg:city":"Egg Harbor Twp",
    "sg:classifiers":[
        {
            "category":"Wholesale",
            "subcategory":"Construction Materials",
            "type":"Manufacturing & Wholesale Goods"
        },
        {
            "category":"Home & Garden",
            "subcategory":"Building Materials",
            "type":"Retail Goods"
        }
    ],
    "sg:phone":"+1 609 653 0272",
    "sg:postcode":"08234",
    "sg:province":"NJ",
    "sg:tags":[
        "fence"
    ],
    "wof:name":"Capital Fence",
    "wof:placetype":"venue"
},
  "geometry": {"coordinates":[-74.58198899999999,39.372544],"type":"Point"}
}