{
  "type": "Feature",
  "properties": {
    "addr:full":"95 Boonton Rd Wayne NJ 07470",
    "addr:housenumber":"95",
    "addr:postcode":"07470",
    "addr:street":"Boonton Rd",
    "iso:country":"US",
    "sg:address":"95 Boonton Rd",
    "sg:city":"Wayne",
    "sg:classifiers":[
        {
            "category":"Restaurant",
            "type":"Food & Drink"
        }
    ],
    "sg:phone":"+1 973 694 0048",
    "sg:postcode":"07470",
    "sg:province":"NJ",
    "wof:name":"Gabriel's Restaurant",
    "wof:placetype":"venue"
},
  "geometry": {"coordinates":[-74.26517,40.914928],"type":"Point"}
}