{
  "type": "Feature",
  "properties": {
    "iso:country":"US",
    "sg:address":"125 West Ave",
    "sg:city":"Ocean City",
    "sg:classifiers":[
        {
            "category":"Retail",
            "subcategory":"Laundry & Dry Cleaning",
            "type":"Services"
        }
    ],
    "sg:phone":"+1 609 391 1400",
    "sg:postcode":"08226",
    "sg:province":"NJ",
    "sg:tags":[
        "cleaners",
        "rug",
        "carpet"
    ],
    "wof:name":"Raley's Pro Clean",
    "wof:placetype":"venue"
},
  "geometry": {"coordinates":[-74.566947,39.2873],"type":"Point"}
}