{
  "type": "Feature",
  "properties": {
    "addr:full":"27 US Highway 46 Pine Brook NJ 07058",
    "addr:housenumber":"27",
    "addr:postcode":"07058",
    "addr:street":"Us Highway 46",
    "iso:country":"US",
    "sg:address":"27 US Highway 46",
    "sg:city":"Pine Brook",
    "sg:classifiers":[
        {
            "category":"Autos & Motor Vehicles",
            "subcategory":"Fuel & Gas Station",
            "type":"Retail Goods"
        }
    ],
    "sg:phone":"+1 973 227 3223",
    "sg:postcode":"07058",
    "sg:province":"NJ",
    "wof:name":"Montville Getty",
    "wof:placetype":"venue"
},
  "geometry": {"coordinates":[-74.34369700000001,40.858398],"type":"Point"}
}