{
  "type": "Feature",
  "properties": {
    "addr:full":"1317 Northumberland Way Monmouth Junction NJ 08852",
    "addr:housenumber":"1317",
    "addr:postcode":"08852",
    "addr:street":"Northumberland Way",
    "iso:country":"US",
    "sg:address":"1317 Northumberland Way",
    "sg:city":"Monmouth Junction",
    "sg:classifiers":[
        {
            "category":"Professional",
            "type":"Services"
        }
    ],
    "sg:phone":"+1   ",
    "sg:postcode":"08852",
    "sg:province":"NJ",
    "wof:name":"Marc A Marini",
    "wof:placetype":"venue"
},
  "geometry": {"coordinates":[-74.5433,40.390545],"type":"Point"}
}