{
  "type": "Feature",
  "properties": {
    "addr:full":"49 W Church St Bergenfield NJ 07621",
    "addr:housenumber":"49",
    "addr:postcode":"07621",
    "addr:street":"W Church St",
    "iso:country":"US",
    "sg:address":"49 W Church St",
    "sg:city":"Bergenfield",
    "sg:classifiers":[
        {
            "category":"Building & Trades",
            "subcategory":"Construction",
            "type":"Services"
        }
    ],
    "sg:phone":"+1 201 501 8700",
    "sg:postcode":"07621",
    "sg:province":"NJ",
    "sg:tags":[
        "concrete",
        "contractor"
    ],
    "wof:name":"Mala'd Construction LTD",
    "wof:placetype":"venue"
},
  "geometry": {"coordinates":[-73.99713800000001,40.929361],"type":"Point"}
}