{
  "type": "Feature",
  "properties": {
    "addr:full":"726 Calhoun St Trenton NJ 08618",
    "addr:housenumber":"726",
    "addr:postcode":"08618",
    "addr:street":"Calhoun St",
    "iso:country":"US",
    "sg:address":"726 Calhoun St",
    "sg:city":"Trenton",
    "sg:classifiers":[
        {
            "category":"Retail",
            "subcategory":"Laundry & Dry Cleaning",
            "type":"Services"
        }
    ],
    "sg:phone":"+1 609 392 2579",
    "sg:postcode":"08618",
    "sg:province":"NJ",
    "sg:tags":[
        "curtain",
        "drapery",
        "cleaners"
    ],
    "wof:name":"Lou's Cleaners",
    "wof:placetype":"venue"
},
  "geometry": {"coordinates":[-74.76647199999999,40.231131],"type":"Point"}
}