{
  "type": "Feature",
  "properties": {
    "iso:country":"US",
    "sg:address":"106 Sunrise Ter",
    "sg:city":"Cedar Grove",
    "sg:classifiers":[
        {
            "category":"Communications",
            "subcategory":"Film & Video Production",
            "type":"Services"
        }
    ],
    "sg:phone":"+1 973 857 8105",
    "sg:postcode":"07009",
    "sg:province":"NJ",
    "sg:tags":[
        "motion"
    ],
    "wof:name":"Cross Land Movie Corp",
    "wof:placetype":"venue"
},
  "geometry": {"coordinates":[-74.23746300000001,40.855831],"type":"Point"}
}