{
  "type": "Feature",
  "properties": {
    "iso:country":"US",
    "sg:address":"81 White Rd",
    "sg:city":"Shrewsbury",
    "sg:classifiers":[
        {
            "category":"Building & Trades",
            "subcategory":"Plumbing",
            "type":"Services"
        }
    ],
    "sg:phone":"+1 732 224 9196",
    "sg:postcode":"07702",
    "sg:province":"NJ",
    "sg:tags":[
        "contractor"
    ],
    "wof:name":"States Heating & Cooling",
    "wof:placetype":"venue"
},
  "geometry": {"coordinates":[-74.059364,40.336146],"type":"Point"}
}