{
  "type": "Feature",
  "properties": {
    "addr:full":"400 N Church St Moorestown NJ 08057",
    "addr:housenumber":"400",
    "addr:postcode":"08057",
    "addr:street":"N Church St",
    "iso:country":"US",
    "sg:address":"400 N Church St",
    "sg:city":"Moorestown",
    "sg:classifiers":[
        {
            "category":"Building & Trades",
            "subcategory":"Construction",
            "type":"Services"
        }
    ],
    "sg:phone":"+1 856 778 9455",
    "sg:postcode":"08057",
    "sg:province":"NJ",
    "sg:tags":[
        "plant",
        "general",
        "water",
        "treatment",
        "contractor",
        "sewage"
    ],
    "wof:name":"Dugan Construction Co Inc",
    "wof:placetype":"venue"
},
  "geometry": {"coordinates":[-74.955366,39.9654],"type":"Point"}
}