{
  "type": "Feature",
  "properties": {
    "addr:full":"45 Custer Dr Ringwood NJ 07456",
    "addr:housenumber":"45",
    "addr:postcode":"07456",
    "addr:street":"Custer Dr",
    "iso:country":"US",
    "sg:address":"45 Custer Dr",
    "sg:city":"Ringwood",
    "sg:classifiers":[
        {
            "category":"Shopping",
            "subcategory":"Discount & Variety Stores",
            "type":"Retail Goods"
        }
    ],
    "sg:phone":"+1   ",
    "sg:postcode":"07456",
    "sg:province":"NJ",
    "sg:tags":[
        "merchandise",
        "general"
    ],
    "wof:name":"Gleeson Distributions Inc",
    "wof:placetype":"venue"
},
  "geometry": {"coordinates":[-74.317476,41.088353],"type":"Point"}
}