{
  "type": "Feature",
  "properties": {
    "iso:country":"US",
    "sg:address":"615 W Saint Georges Ave",
    "sg:city":"Linden",
    "sg:classifiers":[
        {
            "category":"Autos & Motor Vehicles",
            "subcategory":"Automobile Sales",
            "type":"Retail Goods"
        }
    ],
    "sg:phone":"+1 908 486 1888",
    "sg:postcode":"07036",
    "sg:province":"NJ",
    "sg:tags":[
        "car",
        "used",
        "dealer"
    ],
    "wof:name":"Park Avenue Auto Lot Inc",
    "wof:placetype":"venue"
},
  "geometry": {"coordinates":[-74.270177,40.630625],"type":"Point"}
}