{
  "type": "Feature",
  "properties": {
    "addr:full":"11 Foundry St Florence NJ 08518",
    "addr:housenumber":"11",
    "addr:postcode":"08518",
    "addr:street":"Foundry St",
    "iso:country":"US",
    "sg:address":"11 Foundry St",
    "sg:city":"Florence",
    "sg:classifiers":[
        {
            "category":"Professional",
            "subcategory":"Research",
            "type":"Services"
        }
    ],
    "sg:phone":"+1 908 453 2001",
    "sg:postcode":"08518",
    "sg:province":"NJ",
    "wof:name":"General Redi Chem Inc",
    "wof:placetype":"venue"
},
  "geometry": {"coordinates":[-74.816845,40.12374],"type":"Point"}
}