{
  "type": "Feature",
  "properties": {
    "addr:full":"10 Pembrook Dr Kenilworth NJ 07033",
    "addr:housenumber":"10",
    "addr:postcode":"07033",
    "addr:street":"Pembrook Dr",
    "iso:country":"US",
    "sg:address":"10 Pembrook Dr",
    "sg:city":"Kenilworth",
    "sg:classifiers":[
        {
            "category":"Building & Trades",
            "subcategory":"Construction",
            "type":"Services"
        }
    ],
    "sg:phone":"+1 908 276 3657",
    "sg:postcode":"07033",
    "sg:province":"NJ",
    "sg:tags":[
        "house"
    ],
    "wof:name":"Lospinoso Construction",
    "wof:placetype":"venue"
},
  "geometry": {"coordinates":[-74.308554,40.674621],"type":"Point"}
}