{
  "type": "Feature",
  "properties": {
    "addr:full":"774 Bridgeton Pike Monroeville NJ 08343",
    "addr:housenumber":"774",
    "addr:postcode":"08343",
    "addr:street":"Bridgeton Pike",
    "iso:country":"US",
    "sg:address":"774 Bridgeton Pike",
    "sg:city":"Monroeville",
    "sg:classifiers":[
        {
            "category":"Building & Trades",
            "subcategory":"Construction",
            "type":"Services"
        }
    ],
    "sg:phone":"+1 856 358 1239",
    "sg:postcode":"08343",
    "sg:province":"NJ",
    "sg:tags":[
        "roofing",
        "contractor"
    ],
    "wof:name":"C & H Roofing Co Inc",
    "wof:placetype":"venue"
},
  "geometry": {"coordinates":[-75.21604600000001,39.65559],"type":"Point"}
}