{
  "type": "Feature",
  "properties": {
    "iso:country":"US",
    "sg:address":"687 Cortlandt St",
    "sg:city":"Perth Amboy",
    "sg:classifiers":[
        {
            "category":"Health Services",
            "subcategory":"Hospital",
            "type":"Services"
        }
    ],
    "sg:phone":"+1   ",
    "sg:postcode":"08861",
    "sg:province":"NJ",
    "sg:tags":[
        "specialty"
    ],
    "wof:name":"Hogar Crea Contact Office",
    "wof:placetype":"venue"
},
  "geometry": {"coordinates":[-74.26672499999999,40.52135],"type":"Point"}
}