{
  "type": "Feature",
  "properties": {
    "addr:full":"111 W 2nd St Bayonne NJ 07002",
    "addr:housenumber":"111",
    "addr:postcode":"07002",
    "addr:street":"W 2Nd St",
    "iso:country":"US",
    "sg:address":"111 W 2nd St",
    "sg:city":"Bayonne",
    "sg:classifiers":[
        {
            "category":"Building & Trades",
            "subcategory":"Locksmith",
            "type":"Services"
        }
    ],
    "sg:phone":"+1 201 620 6295",
    "sg:postcode":"07002",
    "sg:province":"NJ",
    "sg:tags":[
        "key"
    ],
    "wof:name":"Locksmith 01 24 Hr Ask A",
    "wof:placetype":"venue"
},
  "geometry": {"coordinates":[-74.134755,40.647119],"type":"Point"}
}