{
  "type": "Feature",
  "properties": {
    "iso:country":"US",
    "sg:address":"531 US Hwy 46",
    "sg:city":"Fairfield",
    "sg:classifiers":[
        {
            "category":"Home & Garden",
            "subcategory":"Furniture",
            "type":"Retail Goods"
        }
    ],
    "sg:phone":"+1 973 227 2868",
    "sg:postcode":"07004",
    "sg:province":"NJ",
    "wof:name":"Raymour & Flanagan",
    "wof:placetype":"venue"
},
  "geometry": {"coordinates":[-74.280051,40.887468],"type":"Point"}
}