{
  "type": "Feature",
  "properties": {
    "iso:country":"US",
    "sg:address":"426 Herbertsville Rd",
    "sg:city":"Brick",
    "sg:classifiers":[
        {
            "category":"Real Estate",
            "subcategory":"Real Estate Agent",
            "type":"Services"
        }
    ],
    "sg:phone":"+1   ",
    "sg:postcode":"08724",
    "sg:province":"NJ",
    "wof:name":"Bill Frank",
    "wof:placetype":"venue"
},
  "geometry": {"coordinates":[-74.10408099999999,40.101654],"type":"Point"}
}