{
  "type": "Feature",
  "properties": {
    "addr:full":"1369 Burnet Ave Union NJ 07083",
    "addr:housenumber":"1369",
    "addr:postcode":"07083",
    "addr:street":"Burnet Ave",
    "iso:country":"US",
    "sg:address":"1369 Burnet Ave",
    "sg:city":"Union",
    "sg:classifiers":[
        {
            "category":"Retail",
            "subcategory":"Auto Repair",
            "type":"Services"
        }
    ],
    "sg:phone":"+1 908 688 0140",
    "sg:postcode":"07083",
    "sg:province":"NJ",
    "sg:tags":[
        "repairing",
        "automobile"
    ],
    "wof:name":"Unionville Service Center",
    "wof:placetype":"venue"
},
  "geometry": {"coordinates":[-74.28220399999999,40.7108],"type":"Point"}
}