{
  "type": "Feature",
  "properties": {
    "addr:full":"295 State Rte 31 Flemington NJ 08822",
    "addr:housenumber":"295",
    "addr:postcode":"08822",
    "addr:street":"State Rte 31",
    "iso:country":"US",
    "sg:address":"295 State Rte 31",
    "sg:city":"Flemington",
    "sg:classifiers":[
        {
            "category":"Utilities",
            "subcategory":"Mobile Phone",
            "type":"Services"
        }
    ],
    "sg:phone":"+1 908 788 7777",
    "sg:postcode":"08822",
    "sg:province":"NJ",
    "sg:tags":[
        "telephone",
        "cellular"
    ],
    "wof:name":"Sprint PCS",
    "wof:placetype":"venue"
},
  "geometry": {"coordinates":[-74.85597799999999,40.499198],"type":"Point"}
}