{
  "type": "Feature",
  "properties": {
    "addr:full":"198 US Hwy 46 Budd Lake NJ 07828",
    "addr:housenumber":"198",
    "addr:postcode":"07828",
    "addr:street":"Us Hwy 46",
    "iso:country":"US",
    "sg:address":"198 US Hwy 46",
    "sg:city":"Budd Lake",
    "sg:classifiers":[
        {
            "category":"Shopping",
            "subcategory":"Catalog Store",
            "type":"Retail Goods"
        }
    ],
    "sg:phone":"+1   ",
    "sg:postcode":"07828",
    "sg:province":"NJ",
    "sg:tags":[
        "product",
        "fiber",
        "natural"
    ],
    "wof:name":"Janices Natural Fibers",
    "wof:placetype":"venue"
},
  "geometry": {"coordinates":[-74.733217,40.874133],"type":"Point"}
}