{
  "type": "Feature",
  "properties": {
    "iso:country":"US",
    "sg:address":"105 Main St",
    "sg:city":"Chester",
    "sg:classifiers":[
        {
            "category":"Restaurant",
            "type":"Food & Drink"
        }
    ],
    "sg:phone":"+1 908 879 2903",
    "sg:postcode":"07930",
    "sg:province":"NJ",
    "sg:tags":[
        "eating",
        "caterer"
    ],
    "wof:name":"Once Upon A Table LLC",
    "wof:placetype":"venue"
},
  "geometry": {"coordinates":[-74.69525299999999,40.785911],"type":"Point"}
}