{
  "type": "Feature",
  "properties": {
    "addr:full":"401 Taunton Lake Rd Marlton NJ 08053",
    "addr:housenumber":"401",
    "addr:postcode":"08053",
    "addr:street":"Taunton Lake Rd",
    "iso:country":"US",
    "sg:address":"401 Taunton Lake Rd",
    "sg:city":"Marlton",
    "sg:classifiers":[
        {
            "category":"Personal",
            "subcategory":"Beauty Salon",
            "type":"Services"
        }
    ],
    "sg:phone":"+1 856 797 8071",
    "sg:postcode":"08053",
    "sg:province":"NJ",
    "wof:name":"Supercuts",
    "wof:placetype":"venue"
},
  "geometry": {"coordinates":[-74.87376399999999,39.859633],"type":"Point"}
}