{
  "type": "Feature",
  "properties": {
    "addr:full":"55 Mountain Blvd Exd Warren NJ 07059",
    "addr:housenumber":"55",
    "addr:postcode":"07059",
    "addr:street":"Mountain Blvd Exd",
    "iso:country":"US",
    "sg:address":"55 Mountain Blvd Exd",
    "sg:city":"Warren",
    "sg:classifiers":[
        {
            "category":"Health Services",
            "subcategory":"Health Practitioner",
            "type":"Services"
        }
    ],
    "sg:phone":"+1 908 791 1400",
    "sg:postcode":"07059",
    "sg:province":"NJ",
    "wof:name":"Roth Susan Ed D",
    "wof:placetype":"venue"
},
  "geometry": {"coordinates":[-74.49872999999999,40.614994],"type":"Point"}
}