{
  "type": "Feature",
  "properties": {
    "iso:country":"US",
    "sg:address":"120 Avis Ave",
    "sg:city":"Lakewood",
    "sg:classifiers":[
        {
            "category":"Professional",
            "type":"Services"
        }
    ],
    "sg:phone":"+1   ",
    "sg:postcode":"08701",
    "sg:province":"NJ",
    "wof:name":"R Pepose",
    "wof:placetype":"venue"
},
  "geometry": {"coordinates":[-74.240999,40.110554],"type":"Point"}
}