{
  "type": "Feature",
  "properties": {
    "addr:full":"201 Woodlawn Ave Jersey City NJ 07305",
    "addr:housenumber":"201",
    "addr:postcode":"07305",
    "addr:street":"Woodlawn Ave",
    "iso:country":"US",
    "sg:address":"201 Woodlawn Ave",
    "sg:city":"Jersey City",
    "sg:classifiers":[
        {
            "category":"Organizations",
            "subcategory":"Religious Organization",
            "type":"Services"
        }
    ],
    "sg:phone":"+1 201 333 3465",
    "sg:postcode":"07305",
    "sg:province":"NJ",
    "sg:tags":[
        "church"
    ],
    "wof:name":"First Wesleyan Church",
    "wof:placetype":"venue"
},
  "geometry": {"coordinates":[-74.087982,40.704086],"type":"Point"}
}