{
  "type": "Feature",
  "properties": {
    "addr:full":"95 Madison Ave Morristown NJ 07960",
    "addr:housenumber":"95",
    "addr:postcode":"07960",
    "addr:street":"Madison Ave",
    "iso:country":"US",
    "sg:address":"95 Madison Ave",
    "sg:city":"Morristown",
    "sg:classifiers":[
        {
            "category":"Health Services",
            "subcategory":"Doctor",
            "type":"Services"
        }
    ],
    "sg:phone":"+1 973 539 5330",
    "sg:postcode":"07960",
    "sg:province":"NJ",
    "sg:tags":[
        "clinic"
    ],
    "wof:name":"John Penek",
    "wof:placetype":"venue"
},
  "geometry": {"coordinates":[-74.463527,40.787814],"type":"Point"}
}