{
  "type": "Feature",
  "properties": {
    "addr:full":"400 State Rte 38 Moorestown NJ 08057",
    "addr:housenumber":"400",
    "addr:postcode":"08057",
    "addr:street":"State Rte 38",
    "iso:country":"US",
    "sg:address":"400 State Rte 38",
    "sg:city":"Moorestown",
    "sg:classifiers":[
        {
            "category":"Shopping",
            "subcategory":"Computers & Home Electronics",
            "type":"Retail Goods"
        }
    ],
    "sg:phone":"+1 856 722 1890",
    "sg:postcode":"08057",
    "sg:province":"NJ",
    "sg:tags":[
        "game",
        "video",
        "software"
    ],
    "wof:name":"Gamestop",
    "wof:placetype":"venue"
},
  "geometry": {"coordinates":[-74.963235,39.946261],"type":"Point"}
}