{
  "type": "Feature",
  "properties": {
    "addr:full":"40 William Penn Rd Warren NJ 07059",
    "addr:housenumber":"40",
    "addr:postcode":"07059",
    "addr:street":"William Penn Rd",
    "iso:country":"US",
    "sg:address":"40 William Penn Rd",
    "sg:city":"Warren",
    "sg:classifiers":[
        {
            "category":"Food & Beverages",
            "subcategory":"Groceries & Convenience Stores",
            "type":"Retail Goods"
        }
    ],
    "sg:phone":"+1   ",
    "sg:postcode":"07059",
    "sg:province":"NJ",
    "wof:name":"Vic Inc",
    "wof:placetype":"venue"
},
  "geometry": {"coordinates":[-74.535876,40.645006],"type":"Point"}
}