{
  "type": "Feature",
  "properties": {
    "addr:full":"89 Franklin Ave Nutley NJ 07110",
    "addr:housenumber":"89",
    "addr:postcode":"07110",
    "addr:street":"Franklin Ave",
    "iso:country":"US",
    "sg:address":"89 Franklin Ave",
    "sg:city":"Nutley",
    "sg:classifiers":[
        {
            "category":"Professional",
            "subcategory":"Lawyer & Legal Services",
            "type":"Services"
        }
    ],
    "sg:phone":"+1 973 562 0100",
    "sg:postcode":"07110",
    "sg:province":"NJ",
    "sg:tags":[
        "divorce",
        "law",
        "family"
    ],
    "wof:name":"Micklin Brad Attorney At Law",
    "wof:placetype":"venue"
},
  "geometry": {"coordinates":[-74.1651,40.8116],"type":"Point"}
}