{
  "type": "Feature",
  "properties": {
    "iso:country":"US",
    "sg:address":"152 US Hwy 46",
    "sg:city":"Rockaway",
    "sg:classifiers":[
        {
            "category":"Restaurant",
            "type":"Food & Drink"
        }
    ],
    "sg:phone":"+1   ",
    "sg:postcode":"07866",
    "sg:province":"NJ",
    "sg:tags":[
        "eating"
    ],
    "sg:website":"www.pizzahut.com",
    "wof:name":"Pizza Hut",
    "wof:placetype":"venue"
},
  "geometry": {"coordinates":[-74.506529,40.893926],"type":"Point"}
}