{
  "type": "Feature",
  "properties": {
    "addr:full":"101 Kings Hwy E Haddonfield NJ 08033",
    "addr:housenumber":"101",
    "addr:postcode":"08033",
    "addr:street":"Kings Hwy E",
    "iso:country":"US",
    "sg:address":"101 Kings Hwy E",
    "sg:city":"Haddonfield",
    "sg:classifiers":[
        {
            "category":"Home & Garden",
            "subcategory":"Home Furnishings",
            "type":"Retail Goods"
        }
    ],
    "sg:phone":"+1 856 428 2696",
    "sg:postcode":"08033",
    "sg:province":"NJ",
    "sg:tags":[
        "bath",
        "kitchen"
    ],
    "sg:website":"www.thepolishedplate.com",
    "wof:name":"Polished Plate the",
    "wof:placetype":"venue"
},
  "geometry": {"coordinates":[-75.033776,39.897294],"type":"Point"}
}