{
  "type": "Feature",
  "properties": {
    "iso:country":"US",
    "sg:address":"139 French St",
    "sg:city":"New Brunswick",
    "sg:classifiers":[
        {
            "category":"Food & Beverages",
            "subcategory":"Groceries & Convenience Stores",
            "type":"Retail Goods"
        }
    ],
    "sg:phone":"+1 732 937 9674",
    "sg:postcode":"08901",
    "sg:province":"NJ",
    "sg:tags":[
        "grocer"
    ],
    "wof:name":"New Brunswick Farmer's Market",
    "wof:placetype":"venue"
},
  "geometry": {"coordinates":[-74.452499,40.492883],"type":"Point"}
}