{
  "type": "Feature",
  "properties": {
    "iso:country":"US",
    "sg:address":"445 Hudson St",
    "sg:city":"Hackensack",
    "sg:classifiers":[
        {
            "category":"Health Services",
            "subcategory":"Chiropractor",
            "type":"Services"
        }
    ],
    "sg:phone":"+1 201 440 4666",
    "sg:postcode":"07601",
    "sg:province":"NJ",
    "wof:name":"Wolff Raymond H DC",
    "wof:placetype":"venue"
},
  "geometry": {"coordinates":[-74.038399,40.864498],"type":"Point"}
}