{
  "type": "Feature",
  "properties": {
    "iso:country":"US",
    "sg:address":"2371 Amwell Rd",
    "sg:city":"Somerset",
    "sg:classifiers":[
        {
            "category":"Building & Trades",
            "subcategory":"Construction",
            "type":"Services"
        }
    ],
    "sg:phone":"+1 732 873 7300",
    "sg:postcode":"08873",
    "sg:province":"NJ",
    "sg:tags":[
        "excavating",
        "contractor"
    ],
    "wof:name":"Kaiser Landscaping Inc",
    "wof:placetype":"venue"
},
  "geometry": {"coordinates":[-74.58122400000001,40.503491],"type":"Point"}
}