{
  "type": "Feature",
  "properties": {
    "addr:full":"354 Palisade Ave Cliffside Park NJ 07010",
    "addr:housenumber":"354",
    "addr:postcode":"07010",
    "addr:street":"Palisade Ave",
    "iso:country":"US",
    "sg:address":"354 Palisade Ave",
    "sg:city":"Cliffside Park",
    "sg:classifiers":[
        {
            "category":"Banks & Credit Unions",
            "subcategory":"Bank",
            "type":"Services"
        }
    ],
    "sg:phone":"+1 201 313 5211",
    "sg:postcode":"07010",
    "sg:province":"NJ",
    "sg:website":"www.tdbanknorth.com",
    "wof:name":"Td Banknorth",
    "wof:placetype":"venue"
},
  "geometry": {"coordinates":[-73.990172,40.816495],"type":"Point"}
}