{
  "type": "Feature",
  "properties": {
    "addr:full":"288 State Rte 23 Franklin NJ 07416",
    "addr:housenumber":"288",
    "addr:postcode":"07416",
    "addr:street":"State Rte 23",
    "iso:country":"US",
    "sg:address":"288 State Rte 23",
    "sg:city":"Franklin",
    "sg:classifiers":[
        {
            "category":"Banks & Credit Unions",
            "subcategory":"Bank",
            "type":"Services"
        }
    ],
    "sg:phone":"+1   ",
    "sg:postcode":"07416",
    "sg:province":"NJ",
    "sg:tags":[
        "national",
        "commercial"
    ],
    "wof:name":"Valley National Bank",
    "wof:placetype":"venue"
},
  "geometry": {"coordinates":[-74.580195,41.119519],"type":"Point"}
}