{
  "type": "Feature",
  "properties": {
    "iso:country":"US",
    "sg:address":"275 Summit St",
    "sg:city":"Norwood",
    "sg:classifiers":[
        {
            "category":"Professional",
            "subcategory":"Management & Consulting",
            "type":"Services"
        }
    ],
    "sg:phone":"+1 201 768 1035",
    "sg:postcode":"07648",
    "sg:province":"NJ",
    "sg:tags":[
        "business"
    ],
    "wof:name":"Experience In America Corp",
    "wof:placetype":"venue"
},
  "geometry": {"coordinates":[-73.959532,40.997634],"type":"Point"}
}