{
  "type": "Feature",
  "properties": {
    "iso:country":"US",
    "sg:address":"256 Cambridge Ave",
    "sg:city":"Englewood",
    "sg:classifiers":[
        {
            "category":"Building & Trades",
            "subcategory":"Plumbing",
            "type":"Services"
        }
    ],
    "sg:phone":"+1 201 871 0139",
    "sg:postcode":"07631",
    "sg:province":"NJ",
    "sg:tags":[
        "contractor"
    ],
    "wof:name":"Reliable Cooling & Heating",
    "wof:placetype":"venue"
},
  "geometry": {"coordinates":[-73.978882,40.908405],"type":"Point"}
}