{
  "type": "Feature",
  "properties": {
    "addr:full":"125 Alameda Ave Absecon NJ 08201",
    "addr:housenumber":"125",
    "addr:postcode":"08201",
    "addr:street":"Alameda Ave",
    "iso:country":"US",
    "sg:address":"125 Alameda Ave",
    "sg:city":"Absecon",
    "sg:classifiers":[
        {
            "category":"Building & Trades",
            "subcategory":"Construction",
            "type":"Services"
        }
    ],
    "sg:phone":"+1 609 484 8364",
    "sg:postcode":"08201",
    "sg:province":"NJ",
    "sg:tags":[
        "contractor"
    ],
    "wof:name":"Hanson Builders",
    "wof:placetype":"venue"
},
  "geometry": {"coordinates":[-74.504187,39.430552],"type":"Point"}
}