{
  "type": "Feature",
  "properties": {
    "iso:country":"US",
    "sg:address":"640 Herman Rd",
    "sg:city":"Jackson",
    "sg:classifiers":[
        {
            "category":"Wholesale",
            "subcategory":"Electrical",
            "type":"Manufacturing & Wholesale Goods"
        }
    ],
    "sg:phone":"+1 732 928 3237",
    "sg:postcode":"08527",
    "sg:province":"NJ",
    "sg:tags":[
        "equipment",
        "electronic",
        "supply"
    ],
    "wof:name":"Lynx Communications",
    "wof:placetype":"venue"
},
  "geometry": {"coordinates":[-74.33532,40.152935],"type":"Point"}
}