{
  "type": "Feature",
  "properties": {
    "iso:country":"US",
    "sg:address":"207 Hillcrest Ave",
    "sg:city":"Trenton",
    "sg:classifiers":[
        {
            "category":"Organizations",
            "subcategory":"Religious Organization",
            "type":"Services"
        }
    ],
    "sg:phone":"+1 609 393 0417",
    "sg:postcode":"08618",
    "sg:province":"NJ",
    "sg:tags":[
        "church"
    ],
    "wof:name":"Grace Evangelical Lutheran Chr",
    "wof:placetype":"venue"
},
  "geometry": {"coordinates":[-74.78568799999999,40.24155],"type":"Point"}
}