{
  "type": "Feature",
  "properties": {
    "iso:country":"US",
    "sg:address":"18 Wits End Dr",
    "sg:city":"Hamburg",
    "sg:classifiers":[
        {
            "category":"Building & Trades",
            "subcategory":"Construction",
            "type":"Services"
        }
    ],
    "sg:phone":"+1 973 827 0653",
    "sg:postcode":"07419",
    "sg:province":"NJ",
    "sg:tags":[
        "hanging",
        "contractor"
    ],
    "wof:name":"Precise Painting",
    "wof:placetype":"venue"
},
  "geometry": {"coordinates":[-74.60386099999999,41.139764],"type":"Point"}
}