{
  "type": "Feature",
  "properties": {
    "addr:full":"621 Beechwood Rd Linden NJ 07036",
    "addr:housenumber":"621",
    "addr:postcode":"07036",
    "addr:street":"Beechwood Rd",
    "iso:country":"US",
    "sg:address":"621 Beechwood Rd",
    "sg:city":"Linden",
    "sg:classifiers":[
        {
            "category":"Professional",
            "subcategory":"Lawyer & Legal Services",
            "type":"Services"
        }
    ],
    "sg:phone":"+1 908 925 3508",
    "sg:postcode":"07036",
    "sg:province":"NJ",
    "wof:name":"Halberstadter Sanford",
    "wof:placetype":"venue"
},
  "geometry": {"coordinates":[-74.279426,40.634874],"type":"Point"}
}