{
  "type": "Feature",
  "properties": {
    "iso:country":"US",
    "sg:address":"770 Friesburg Aldine Rd",
    "sg:city":"Elmer",
    "sg:classifiers":[
        {
            "category":"Farming",
            "subcategory":"Nursery",
            "type":"Manufacturing & Wholesale Goods"
        }
    ],
    "sg:phone":"+1 856 358 2248",
    "sg:postcode":"08318",
    "sg:province":"NJ",
    "wof:name":"English Acres",
    "wof:placetype":"venue"
},
  "geometry": {"coordinates":[-75.281544,39.557126],"type":"Point"}
}