{
  "type": "Feature",
  "properties": {
    "iso:country":"US",
    "sg:address":"227 Dayton Ave",
    "sg:city":"Clifton",
    "sg:classifiers":[
        {
            "category":"Recreation",
            "type":"Entertainment"
        }
    ],
    "sg:phone":"+1 973 340 4545",
    "sg:postcode":"07011",
    "sg:province":"NJ",
    "sg:tags":[
        "martial art"
    ],
    "wof:name":"Martial Arts Tae Kwon DO Center",
    "wof:placetype":"venue"
},
  "geometry": {"coordinates":[-74.123199,40.8755],"type":"Point"}
}