{
  "type": "Feature",
  "properties": {
    "iso:country":"US",
    "sg:address":"1475 US Hwy 46",
    "sg:city":"Ledgewood",
    "sg:classifiers":[
        {
            "category":"Manufacturing",
            "subcategory":"Food",
            "type":"Manufacturing & Wholesale Goods"
        }
    ],
    "sg:phone":"+1 973 584 9721",
    "sg:postcode":"07852",
    "sg:province":"NJ",
    "sg:tags":[
        "frozen",
        "dessert",
        "ice",
        "cream"
    ],
    "wof:name":"Cliff's Dairy Maid",
    "wof:placetype":"venue"
},
  "geometry": {"coordinates":[-74.662147,40.888248],"type":"Point"}
}