{
  "type": "Feature",
  "properties": {
    "addr:full":"907 Saint Georges Ave Roselle NJ 07203",
    "addr:housenumber":"907",
    "addr:postcode":"07203",
    "addr:street":"Saint Georges Ave",
    "iso:country":"US",
    "sg:address":"907 Saint Georges Ave",
    "sg:city":"Roselle",
    "sg:classifiers":[
        {
            "category":"Shopping",
            "subcategory":"Clothing, Apparel, & Fashions",
            "type":"Retail Goods"
        }
    ],
    "sg:phone":"+1   ",
    "sg:postcode":"07203",
    "sg:province":"NJ",
    "wof:name":"Flipside",
    "wof:placetype":"venue"
},
  "geometry": {"coordinates":[-74.25219,40.645027],"type":"Point"}
}