{
  "type": "Feature",
  "properties": {
    "iso:country":"US",
    "sg:address":"868 Ester Ave",
    "sg:city":"Teaneck",
    "sg:classifiers":[
        {
            "category":"Building & Trades",
            "subcategory":"Construction",
            "type":"Services"
        }
    ],
    "sg:phone":"+1 201 907 0938",
    "sg:postcode":"07666",
    "sg:province":"NJ",
    "sg:tags":[
        "roofing",
        "contractor"
    ],
    "wof:name":"Carlsen Roofing & Siding Co",
    "wof:placetype":"venue"
},
  "geometry": {"coordinates":[-74.020816,40.890129],"type":"Point"}
}