{
  "type": "Feature",
  "properties": {
    "addr:full":"69 W Palisade Ave Englewood NJ 07631",
    "addr:housenumber":"69",
    "addr:postcode":"07631",
    "addr:street":"W Palisade Ave",
    "iso:country":"US",
    "sg:address":"69 W Palisade Ave",
    "sg:city":"Englewood",
    "sg:classifiers":[
        {
            "category":"Food & Beverages",
            "subcategory":"Groceries & Convenience Stores",
            "type":"Retail Goods"
        }
    ],
    "sg:phone":"+1 201 894 0507",
    "sg:postcode":"07631",
    "sg:province":"NJ",
    "wof:name":"J R Mini Market",
    "wof:placetype":"venue"
},
  "geometry": {"coordinates":[-73.978247,40.895942],"type":"Point"}
}