{
  "type": "Feature",
  "properties": {
    "addr:full":"57 E Mount Pleasant Ave Livingston NJ 07039",
    "addr:housenumber":"57",
    "addr:postcode":"07039",
    "addr:street":"E Mount Pleasant Ave",
    "iso:country":"US",
    "sg:address":"57 E Mount Pleasant Ave",
    "sg:city":"Livingston",
    "sg:classifiers":[
        {
            "category":"Restaurant",
            "type":"Food & Drink"
        }
    ],
    "sg:phone":"+1 973 992 2838",
    "sg:postcode":"07039",
    "sg:province":"NJ",
    "sg:tags":[
        "chinese"
    ],
    "wof:name":"China Garden Chinese Food",
    "wof:placetype":"venue"
},
  "geometry": {"coordinates":[-74.313103,40.796501],"type":"Point"}
}