{
  "type": "Feature",
  "properties": {
    "addr:full":"75 Levine St Paterson NJ 07503",
    "addr:housenumber":"75",
    "addr:postcode":"07503",
    "addr:street":"Levine St",
    "iso:country":"US",
    "sg:address":"75 Levine St",
    "sg:city":"Paterson",
    "sg:classifiers":[
        {
            "category":"Manufacturing",
            "subcategory":"Textiles",
            "type":"Manufacturing & Wholesale Goods"
        },
        {
            "category":"Manufacturing",
            "subcategory":"Retail Goods",
            "type":"Manufacturing & Wholesale Goods"
        }
    ],
    "sg:phone":"+1 973 247 9150",
    "sg:postcode":"07503",
    "sg:province":"NJ",
    "sg:tags":[
        "linens-wholesale",
        "manufacturer"
    ],
    "wof:name":"New Venezia Textile",
    "wof:placetype":"venue"
},
  "geometry": {"coordinates":[-74.16595100000001,40.899528],"type":"Point"}
}