{
  "type": "Feature",
  "properties": {
    "addr:full":"33 Chamberlain Ave Elmwood Park NJ 07407",
    "addr:housenumber":"33",
    "addr:postcode":"07407",
    "addr:street":"Chamberlain Ave",
    "iso:country":"US",
    "sg:address":"33 Chamberlain Ave",
    "sg:city":"Elmwood Park",
    "sg:classifiers":[
        {
            "category":"Retail",
            "subcategory":"Auto Repair",
            "type":"Services"
        }
    ],
    "sg:phone":"+1 201 794 7171",
    "sg:postcode":"07407",
    "sg:province":"NJ",
    "sg:tags":[
        "repairing",
        "automobile",
        "component",
        "electrical",
        "automotive",
        "rebuilds"
    ],
    "wof:name":"Ray's Generator Exchange",
    "wof:placetype":"venue"
},
  "geometry": {"coordinates":[-74.126147,40.902959],"type":"Point"}
}