{
  "type": "Feature",
  "properties": {
    "iso:country":"US",
    "sg:address":"512 Westminster Ave",
    "sg:city":"Elizabeth",
    "sg:classifiers":[
        {
            "category":"Professional",
            "subcategory":"Lawyer & Legal Services",
            "type":"Services"
        }
    ],
    "sg:phone":"+1 201 659 1101",
    "sg:postcode":"07208",
    "sg:province":"NJ",
    "sg:tags":[
        "attorney"
    ],
    "wof:name":"Marciano & Topazio",
    "wof:placetype":"venue"
},
  "geometry": {"coordinates":[-74.215008,40.674813],"type":"Point"}
}