{
  "type": "Feature",
  "properties": {
    "iso:country":"US",
    "sg:address":"101 Tingley Ln",
    "sg:city":"Edison",
    "sg:classifiers":[
        {
            "category":"Professional",
            "subcategory":"Business Services",
            "type":"Services"
        }
    ],
    "sg:phone":"+1   ",
    "sg:postcode":"08820",
    "sg:province":"NJ",
    "wof:name":"Valerie Duffy Associates",
    "wof:placetype":"venue"
},
  "geometry": {"coordinates":[-74.373694,40.583863],"type":"Point"}
}