{
  "type": "Feature",
  "properties": {
    "addr:full":"1970 Rutgers Blvd Lakewood NJ 08701",
    "addr:housenumber":"1970",
    "addr:postcode":"08701",
    "addr:street":"Rutgers Blvd",
    "iso:country":"US",
    "sg:address":"1970 Rutgers Blvd",
    "sg:city":"Lakewood",
    "sg:classifiers":[
        {
            "category":"Retail",
            "subcategory":"Repair Shop",
            "type":"Services"
        }
    ],
    "sg:phone":"+1 732 730 8774",
    "sg:postcode":"08701",
    "sg:province":"NJ",
    "sg:tags":[
        "equipment",
        "medical"
    ],
    "wof:name":"Linac Systems Inc",
    "wof:placetype":"venue"
},
  "geometry": {"coordinates":[-74.16193,40.071008],"type":"Point"}
}