{
  "type": "Feature",
  "properties": {
    "iso:country":"US",
    "sg:address":"302 Elbow Ln",
    "sg:city":"Burlington",
    "sg:classifiers":[
        {
            "category":"Retail",
            "subcategory":"Auto Repair",
            "type":"Services"
        }
    ],
    "sg:phone":"+1 609 261 0006",
    "sg:postcode":"08016",
    "sg:province":"NJ",
    "sg:tags":[
        "wrecker"
    ],
    "wof:name":"Johnson Specialized Transprtn",
    "wof:placetype":"venue"
},
  "geometry": {"coordinates":[-74.844517,40.037009],"type":"Point"}
}