{
  "type": "Feature",
  "properties": {
    "iso:country":"US",
    "sg:address":"6404 Black Horse Pike",
    "sg:city":"Egg Harbor Twp",
    "sg:classifiers":[
        {
            "category":"Building & Trades",
            "subcategory":"Equipment Rental",
            "type":"Services"
        }
    ],
    "sg:phone":"+1 609 383 1970",
    "sg:postcode":"08234",
    "sg:province":"NJ",
    "sg:tags":[
        "yard"
    ],
    "wof:name":"A C Special Events",
    "wof:placetype":"venue"
},
  "geometry": {"coordinates":[-74.590898,39.423403],"type":"Point"}
}