{
  "type": "Feature",
  "properties": {
    "iso:country":"US",
    "sg:address":"760 Blanche Ave",
    "sg:city":"Norwood",
    "sg:classifiers":[
        {
            "category":"Social Services",
            "type":"Services"
        }
    ],
    "sg:phone":"+1   ",
    "sg:postcode":"07648",
    "sg:province":"NJ",
    "wof:name":"Martin Lazar Msw",
    "wof:placetype":"venue"
},
  "geometry": {"coordinates":[-73.963632,40.990959],"type":"Point"}
}