{
  "type": "Feature",
  "properties": {
    "iso:country":"US",
    "sg:address":"2177 Oak Tree Rd",
    "sg:city":"Edison",
    "sg:classifiers":[
        {
            "category":"Education",
            "subcategory":"Special Training",
            "type":"Public Place"
        }
    ],
    "sg:phone":"+1 908 757 0022",
    "sg:postcode":"08820",
    "sg:province":"NJ",
    "sg:tags":[
        "center"
    ],
    "wof:name":"JEI Learning Ctr",
    "wof:placetype":"venue"
},
  "geometry": {"coordinates":[-74.381457,40.577248],"type":"Point"}
}