{
  "type": "Feature",
  "properties": {
    "iso:country":"US",
    "sg:address":"215 State Route 10",
    "sg:city":"Randolph",
    "sg:classifiers":[
        {
            "category":"Retail",
            "subcategory":"Portrait Studio",
            "type":"Services"
        },
        {
            "category":"Professional",
            "subcategory":"Art Services",
            "type":"Services"
        }
    ],
    "sg:phone":"+1 973 537 8660",
    "sg:postcode":"07869",
    "sg:province":"NJ",
    "sg:tags":[
        "photographer",
        "photography",
        "store"
    ],
    "wof:name":"Zegre Francois Photography",
    "wof:placetype":"venue"
},
  "geometry": {"coordinates":[-74.54499800000001,40.871498],"type":"Point"}
}