{
  "type": "Feature",
  "properties": {
    "addr:full":"27 Atlantis Blvd Little Egg Hbr NJ 08087",
    "addr:housenumber":"27",
    "addr:postcode":"08087",
    "addr:street":"Atlantis Blvd Little",
    "iso:country":"US",
    "sg:address":"27 Atlantis Blvd",
    "sg:city":"Little Egg Hbr",
    "sg:classifiers":[
        {
            "category":"Local Transit",
            "type":"Transportation"
        }
    ],
    "sg:phone":"+1 609 296 0003",
    "sg:postcode":"08087",
    "sg:province":"NJ",
    "sg:tags":[
        "limousine"
    ],
    "wof:name":"Rosie's Rides",
    "wof:placetype":"venue"
},
  "geometry": {"coordinates":[-74.351517,39.578834],"type":"Point"}
}