{
  "type": "Feature",
  "properties": {
    "iso:country":"US",
    "sg:address":"50 Bayside Ct",
    "sg:city":"Margate City",
    "sg:classifiers":[
        {
            "category":"Organizations",
            "subcategory":"Professional Association",
            "type":"Services"
        }
    ],
    "sg:phone":"+1 609 823 2839",
    "sg:postcode":"08402",
    "sg:province":"NJ",
    "sg:tags":[
        "business"
    ],
    "wof:name":"Esharksolutions LLC",
    "wof:placetype":"venue"
},
  "geometry": {"coordinates":[-74.511071,39.337392],"type":"Point"}
}