{
  "type": "Feature",
  "properties": {
    "addr:full":"36 Newark Ave Ste 220 Belleville NJ 07109",
    "addr:housenumber":"36",
    "addr:postcode":"07109",
    "addr:street":"Newark Ave Ste 220",
    "iso:country":"US",
    "sg:address":"36 Newark Ave Ste 220",
    "sg:city":"Belleville",
    "sg:classifiers":[
        {
            "category":"Health Services",
            "subcategory":"Doctor",
            "type":"Services"
        }
    ],
    "sg:phone":"+1 973 759 8284",
    "sg:postcode":"07109",
    "sg:province":"NJ",
    "wof:name":"Greifinger David J MD",
    "wof:placetype":"venue"
},
  "geometry": {"coordinates":[-74.177803,40.784],"type":"Point"}
}