{
  "type": "Feature",
  "properties": {
    "iso:country":"US",
    "sg:address":"7 Cedar Ln",
    "sg:city":"Mendham",
    "sg:classifiers":[
        {
            "category":"Professional",
            "subcategory":"Accounting & Tax Preparation",
            "type":"Services"
        }
    ],
    "sg:phone":"+1   ",
    "sg:postcode":"07945",
    "sg:province":"NJ",
    "wof:name":"Henry C Kochan Jr",
    "wof:placetype":"venue"
},
  "geometry": {"coordinates":[-74.638098,40.798538],"type":"Point"}
}