{
  "type": "Feature",
  "properties": {
    "iso:country":"US",
    "sg:address":"137 Center Grove Rd",
    "sg:city":"Randolph",
    "sg:classifiers":[
        {
            "category":"Banks & Credit Unions",
            "subcategory":"Bank",
            "type":"Services"
        }
    ],
    "sg:phone":"+1   ",
    "sg:postcode":"07869",
    "sg:province":"NJ",
    "sg:tags":[
        "national",
        "commercial"
    ],
    "wof:name":"Fleet",
    "wof:placetype":"venue"
},
  "geometry": {"coordinates":[-74.56959000000001,40.863312],"type":"Point"}
}