{
  "type": "Feature",
  "properties": {
    "addr:full":"366 Maplewood Ave Kenilworth NJ 07033",
    "addr:housenumber":"366",
    "addr:postcode":"07033",
    "addr:street":"Maplewood Ave",
    "iso:country":"US",
    "sg:address":"366 Maplewood Ave",
    "sg:city":"Kenilworth",
    "sg:classifiers":[
        {
            "category":"Personal",
            "type":"Services"
        }
    ],
    "sg:phone":"+1   ",
    "sg:postcode":"07033",
    "sg:province":"NJ",
    "wof:name":"California Tan",
    "wof:placetype":"venue"
},
  "geometry": {"coordinates":[-74.278781,40.662155],"type":"Point"}
}