{
  "type": "Feature",
  "properties": {
    "addr:full":"160 Meadowbrook Dr Princeton NJ 08540",
    "addr:housenumber":"160",
    "addr:postcode":"08540",
    "addr:street":"Meadowbrook Dr",
    "iso:country":"US",
    "sg:address":"160 Meadowbrook Dr",
    "sg:city":"Princeton",
    "sg:classifiers":[
        {
            "category":"Professional",
            "subcategory":"Business Services",
            "type":"Services"
        }
    ],
    "sg:phone":"+1   ",
    "sg:postcode":"08540",
    "sg:province":"NJ",
    "wof:name":"Market Wisdom LLC",
    "wof:placetype":"venue"
},
  "geometry": {"coordinates":[-74.643827,40.369792],"type":"Point"}
}