{
  "type": "Feature",
  "properties": {
    "iso:country":"US",
    "sg:address":"4113 Bergenline Ave",
    "sg:city":"Union City",
    "sg:classifiers":[
        {
            "category":"Shopping",
            "subcategory":"Shoes",
            "type":"Retail Goods"
        }
    ],
    "sg:phone":"+1 201 348 0524",
    "sg:postcode":"07087",
    "sg:province":"NJ",
    "sg:tags":[
        "store"
    ],
    "wof:name":"Panda Shoe Center Inc",
    "wof:placetype":"venue"
},
  "geometry": {"coordinates":[-74.025299,40.777401],"type":"Point"}
}