{
  "type": "Feature",
  "properties": {
    "addr:full":"86 Windeler Rd Howell NJ 07731",
    "addr:housenumber":"86",
    "addr:postcode":"07731",
    "addr:street":"Windeler Rd",
    "iso:country":"US",
    "sg:address":"86 Windeler Rd",
    "sg:city":"Howell",
    "sg:classifiers":[
        {
            "category":"Building & Trades",
            "subcategory":"Landscaping Services",
            "type":"Services"
        }
    ],
    "sg:phone":"+1 732 370 4227",
    "sg:postcode":"07731",
    "sg:province":"NJ",
    "wof:name":"Spence Brothers Ls",
    "wof:placetype":"venue"
},
  "geometry": {"coordinates":[-74.222138,40.169146],"type":"Point"}
}