{
  "type": "Feature",
  "properties": {
    "iso:country":"US",
    "sg:address":"19 Spear Rd",
    "sg:city":"Ramsey",
    "sg:classifiers":[
        {
            "category":"Professional",
            "subcategory":"Computer Services",
            "type":"Services"
        }
    ],
    "sg:phone":"+1   ",
    "sg:postcode":"07446",
    "sg:province":"NJ",
    "sg:tags":[
        "programing",
        "custom"
    ],
    "wof:name":"First Direct Corporation",
    "wof:placetype":"venue"
},
  "geometry": {"coordinates":[-74.123779,41.064408],"type":"Point"}
}