{
  "type": "Feature",
  "properties": {
    "iso:country":"US",
    "sg:address":"61 Haddon Ave",
    "sg:city":"Haddon Township",
    "sg:classifiers":[
        {
            "category":"Shopping",
            "subcategory":"Jewelry",
            "type":"Retail Goods"
        },
        {
            "category":"Shopping",
            "subcategory":"Gifts & Souvenirs",
            "type":"Retail Goods"
        }
    ],
    "sg:phone":"+1 856 477 2458",
    "sg:postcode":"08108",
    "sg:province":"NJ",
    "sg:tags":[
        "flower"
    ],
    "wof:name":"Christopher Charles Fine Jewelry & Gift Boutique",
    "wof:placetype":"venue"
},
  "geometry": {"coordinates":[-75.08486600000001,39.921588],"type":"Point"}
}