{
  "type": "Feature",
  "properties": {
    "addr:full":"224 State Rte 37 Toms River NJ 08753",
    "addr:housenumber":"224",
    "addr:postcode":"08753",
    "addr:street":"State Rte 37",
    "iso:country":"US",
    "sg:address":"224 State Rte 37",
    "sg:city":"Toms River",
    "sg:classifiers":[
        {
            "category":"Wholesale",
            "subcategory":"Stationery",
            "type":"Manufacturing & Wholesale Goods"
        }
    ],
    "sg:phone":"+1 732 349 6262",
    "sg:postcode":"08753",
    "sg:province":"NJ",
    "sg:tags":[
        "business",
        "form",
        "system"
    ],
    "wof:name":"Minuteman Press",
    "wof:placetype":"venue"
},
  "geometry": {"coordinates":[-74.178448,39.961295],"type":"Point"}
}