{
  "type": "Feature",
  "properties": {
    "iso:country":"US",
    "sg:address":"825 Brook Rd",
    "sg:city":"Lakewood",
    "sg:classifiers":[
        {
            "category":"Building & Trades",
            "subcategory":"Construction",
            "type":"Services"
        },
        {
            "category":"Home & Garden",
            "subcategory":"Furniture",
            "type":"Retail Goods"
        }
    ],
    "sg:phone":"+1 732 370 4186",
    "sg:postcode":"08701",
    "sg:province":"NJ",
    "sg:tags":[
        "carpentry",
        "top",
        "counter",
        "contractor"
    ],
    "wof:name":"On The Level Counter Top Inc",
    "wof:placetype":"venue"
},
  "geometry": {"coordinates":[-74.18900499999999,40.102547],"type":"Point"}
}