{
  "type": "Feature",
  "properties": {
    "iso:country":"US",
    "sg:address":"327 Brunswick Ave",
    "sg:city":"Trenton",
    "sg:classifiers":[
        {
            "category":"Personal",
            "subcategory":"Barber",
            "type":"Services"
        }
    ],
    "sg:phone":"+1 609 656 9400",
    "sg:postcode":"08618",
    "sg:province":"NJ",
    "sg:tags":[
        "shop"
    ],
    "wof:name":"Big John's Barber Shop",
    "wof:placetype":"venue"
},
  "geometry": {"coordinates":[-74.760986,40.228221],"type":"Point"}
}