{
  "type": "Feature",
  "properties": {
    "iso:country":"US",
    "sg:address":"1 Walnut St",
    "sg:city":"Perth Amboy",
    "sg:classifiers":[
        {
            "category":"Manufacturing",
            "subcategory":"Chemicals & Compounds",
            "type":"Manufacturing & Wholesale Goods"
        }
    ],
    "sg:phone":"+1 732 376 9300",
    "sg:postcode":"08861",
    "sg:province":"NJ",
    "sg:tags":[
        "mfg",
        "coloring",
        "liquid",
        "plastic"
    ],
    "sg:website":"www.riverdalecolor.com",
    "wof:name":"Riverdale Color Mfg Inc",
    "wof:placetype":"venue"
},
  "geometry": {"coordinates":[-74.277255,40.509425],"type":"Point"}
}