{
  "type": "Feature",
  "properties": {
    "iso:country":"US",
    "sg:address":"103 River Rd",
    "sg:city":"Edgewater",
    "sg:classifiers":[
        {
            "category":"Health Services",
            "subcategory":"Doctor",
            "type":"Services"
        }
    ],
    "sg:phone":"+1 201 461 1843",
    "sg:postcode":"07020",
    "sg:province":"NJ",
    "sg:tags":[
        "physician",
        "surgeon"
    ],
    "wof:name":"Riverside Medical Group",
    "wof:placetype":"venue"
},
  "geometry": {"coordinates":[-73.991609,40.806233],"type":"Point"}
}