{
  "type": "Feature",
  "properties": {
    "addr:full":"472 Westfield Ave Clark NJ 07066",
    "addr:housenumber":"472",
    "addr:postcode":"07066",
    "addr:street":"Westfield Ave",
    "iso:country":"US",
    "sg:address":"472 Westfield Ave",
    "sg:city":"Clark",
    "sg:classifiers":[
        {
            "category":"Building & Trades",
            "subcategory":"Construction",
            "type":"Services"
        }
    ],
    "sg:phone":"+1 732 499 8138",
    "sg:postcode":"07066",
    "sg:province":"NJ",
    "sg:tags":[
        "stucco",
        "contractor"
    ],
    "wof:name":"Certified Stucco Restoration",
    "wof:placetype":"venue"
},
  "geometry": {"coordinates":[-74.31372,40.624202],"type":"Point"}
}