{
  "type": "Feature",
  "properties": {
    "iso:country":"US",
    "sg:address":"112 Leddon Ln",
    "sg:city":"Blackwood",
    "sg:classifiers":[
        {
            "category":"Home & Garden",
            "subcategory":"Building Materials",
            "type":"Retail Goods"
        },
        {
            "category":"Building & Trades",
            "subcategory":"Construction",
            "type":"Services"
        }
    ],
    "sg:phone":"+1 856 875 6455",
    "sg:postcode":"08012",
    "sg:province":"NJ",
    "sg:tags":[
        "altering",
        "gazebo",
        "builder",
        "contractor",
        "remodeling",
        "patio"
    ],
    "sg:website":"http://www.precisionbuildit.com",
    "wof:name":"Precision Decks & Remodeling",
    "wof:placetype":"venue"
},
  "geometry": {"coordinates":[-75.04261700000001,39.740186],"type":"Point"}
}