{
  "type": "Feature",
  "properties": {
    "addr:full":"71 Gordonhurst Ave Montclair NJ 07043",
    "addr:housenumber":"71",
    "addr:postcode":"07043",
    "addr:street":"Gordonhurst Ave",
    "iso:country":"US",
    "sg:address":"71 Gordonhurst Ave",
    "sg:city":"Montclair",
    "sg:classifiers":[
        {
            "category":"Real Estate",
            "subcategory":"Real Estate Agent",
            "type":"Services"
        }
    ],
    "sg:phone":"+1   ",
    "sg:postcode":"07043",
    "sg:province":"NJ",
    "sg:tags":[
        "management"
    ],
    "wof:name":"Wenhill Capital Corp",
    "wof:placetype":"venue"
},
  "geometry": {"coordinates":[-74.20170899999999,40.832676],"type":"Point"}
}