{
  "type": "Feature",
  "properties": {
    "iso:country":"US",
    "sg:address":"495 N Franklin Tpke",
    "sg:city":"Ramsey",
    "sg:classifiers":[
        {
            "category":"Education",
            "subcategory":"Special Training",
            "type":"Public Place"
        }
    ],
    "sg:phone":"+1   ",
    "sg:postcode":"07446",
    "sg:province":"NJ",
    "wof:name":"Stella Music School",
    "wof:placetype":"venue"
},
  "geometry": {"coordinates":[-74.137252,41.07281],"type":"Point"}
}