{
  "type": "Feature",
  "properties": {
    "iso:country":"US",
    "sg:address":"2 Towne Ln",
    "sg:city":"Voorhees",
    "sg:classifiers":[
        {
            "category":"Professional",
            "type":"Services"
        }
    ],
    "sg:phone":"+1   ",
    "sg:postcode":"08043",
    "sg:province":"NJ",
    "wof:name":"James Reiber",
    "wof:placetype":"venue"
},
  "geometry": {"coordinates":[-74.94320399999999,39.821832],"type":"Point"}
}