{
  "type": "Feature",
  "properties": {
    "iso:country":"US",
    "sg:address":"41 Henry Rd",
    "sg:city":"Hewitt",
    "sg:classifiers":[
        {
            "category":"Education",
            "subcategory":"School",
            "type":"Public Place"
        }
    ],
    "sg:phone":"+1 973 853 4466",
    "sg:postcode":"07421",
    "sg:province":"NJ",
    "sg:tags":[
        "elementary"
    ],
    "wof:name":"Upper Greenwood Lake Elementary School",
    "wof:placetype":"venue"
},
  "geometry": {"coordinates":[-74.38877100000001,41.18377],"type":"Point"}
}