{
  "type": "Feature",
  "properties": {
    "addr:full":"604 Highland Dr Pt Pleasant Boro NJ 08742",
    "addr:housenumber":"604",
    "addr:postcode":"08742",
    "addr:street":"Highland Dr Pt",
    "iso:country":"US",
    "sg:address":"604 Highland Dr",
    "sg:city":"Pt Pleasant Boro",
    "sg:classifiers":[
        {
            "category":"Building & Trades",
            "subcategory":"Construction",
            "type":"Services"
        }
    ],
    "sg:phone":"+1 732 295 3354",
    "sg:postcode":"08742",
    "sg:province":"NJ",
    "sg:tags":[
        "general",
        "contractor"
    ],
    "wof:name":"Pbs Custom Builders Inc",
    "wof:placetype":"venue"
},
  "geometry": {"coordinates":[-74.084262,40.082128],"type":"Point"}
}