{
  "type": "Feature",
  "properties": {
    "iso:country":"US",
    "sg:address":"722 Hamburg Tpke",
    "sg:city":"Pompton Lakes",
    "sg:classifiers":[
        {
            "category":"Deli",
            "type":"Food & Drink"
        },
        {
            "category":"Food & Beverages",
            "subcategory":"Bakery",
            "type":"Retail Goods"
        }
    ],
    "sg:phone":"+1 973 835 6200",
    "sg:postcode":"07442",
    "sg:province":"NJ",
    "sg:tags":[
        "sandwich"
    ],
    "wof:name":"Pompton Lakes Hot Bagels & Deli Llc",
    "wof:placetype":"venue"
},
  "geometry": {"coordinates":[-74.28172000000001,40.99359],"type":"Point"}
}