{
  "type": "Feature",
  "properties": {
    "addr:full":"1016 Laurel Oak Rd Voorhees NJ 08043",
    "addr:housenumber":"1016",
    "addr:postcode":"08043",
    "addr:street":"Laurel Oak Rd",
    "iso:country":"US",
    "sg:address":"1016 Laurel Oak Rd",
    "sg:city":"Voorhees",
    "sg:classifiers":[
        {
            "category":"Professional",
            "type":"Services"
        },
        {
            "category":"Health Services",
            "subcategory":"Medical Lab",
            "type":"Services"
        }
    ],
    "sg:phone":"+1 856 783 5533",
    "sg:postcode":"08043",
    "sg:province":"NJ",
    "sg:tags":[
        "x"
    ],
    "wof:name":"Lackawanna Mobile X Ray Inc",
    "wof:placetype":"venue"
},
  "geometry": {"coordinates":[-74.97762899999999,39.843957],"type":"Point"}
}