{
  "type": "Feature",
  "properties": {
    "iso:country":"US",
    "sg:address":"710 Washington St",
    "sg:city":"Hoboken",
    "sg:classifiers":[
        {
            "category":"Health Services",
            "subcategory":"Doctor",
            "type":"Services"
        }
    ],
    "sg:phone":"+1 201 659 8800",
    "sg:postcode":"07030",
    "sg:province":"NJ",
    "wof:name":"Sharon Stern DDS",
    "wof:placetype":"venue"
},
  "geometry": {"coordinates":[-74.028397,40.745861],"type":"Point"}
}