{
  "type": "Feature",
  "properties": {
    "iso:country":"US",
    "sg:address":"551 Main Ave",
    "sg:city":"Wallington",
    "sg:classifiers":[
        {
            "category":"Recreation",
            "type":"Entertainment"
        }
    ],
    "sg:phone":"+1 973 473 8900",
    "sg:postcode":"07057",
    "sg:province":"NJ",
    "sg:tags":[
        "skating",
        "rink"
    ],
    "sg:website":"http://www.iscahockey.com",
    "wof:name":"Inline Skating Club of America",
    "wof:placetype":"venue"
},
  "geometry": {"coordinates":[-74.09929700000001,40.8605],"type":"Point"}
}