{
  "type": "Feature",
  "properties": {
    "iso:country":"US",
    "sg:address":"68 Essex St",
    "sg:city":"Millburn",
    "sg:classifiers":[
        {
            "category":"Health Services",
            "subcategory":"Doctor",
            "type":"Services"
        }
    ],
    "sg:phone":"+1 973 467 9440",
    "sg:postcode":"07041",
    "sg:province":"NJ",
    "sg:tags":[
        "obstetrician",
        "gynecologist"
    ],
    "wof:name":"Sugarman G R MD",
    "wof:placetype":"venue"
},
  "geometry": {"coordinates":[-74.304346,40.725218],"type":"Point"}
}