{
  "type": "Feature",
  "properties": {
    "addr:full":"1401 Central Ave Beach Haven NJ 08008",
    "addr:housenumber":"1401",
    "addr:postcode":"08008",
    "addr:street":"Central Ave",
    "iso:country":"US",
    "sg:address":"1401 Central Ave",
    "sg:city":"Beach Haven",
    "sg:classifiers":[
        {
            "category":"Shopping",
            "subcategory":"Florist",
            "type":"Retail Goods"
        }
    ],
    "sg:phone":"+1   ",
    "sg:postcode":"08008",
    "sg:province":"NJ",
    "sg:tags":[
        "shop",
        "flower"
    ],
    "wof:name":"A Flower Shop",
    "wof:placetype":"venue"
},
  "geometry": {"coordinates":[-74.17959999999999,39.646761],"type":"Point"}
}