{
  "type": "Feature",
  "properties": {
    "addr:full":"305 US Hwy 130 Bordentown NJ 08505",
    "addr:housenumber":"305",
    "addr:postcode":"08505",
    "addr:street":"Us Hwy 130",
    "iso:country":"US",
    "sg:address":"305 US Hwy 130",
    "sg:city":"Bordentown",
    "sg:classifiers":[
        {
            "category":"Food & Beverages",
            "subcategory":"Groceries & Convenience Stores",
            "type":"Retail Goods"
        }
    ],
    "sg:phone":"+1 609 298 8899",
    "sg:postcode":"08505",
    "sg:province":"NJ",
    "sg:tags":[
        "product"
    ],
    "wof:name":"Quick Stop Food Stores",
    "wof:placetype":"venue"
},
  "geometry": {"coordinates":[-74.712039,40.136755],"type":"Point"}
}