{
  "type": "Feature",
  "properties": {
    "iso:country":"US",
    "sg:address":"8 Van Winkle St",
    "sg:city":"Bloomfield",
    "sg:classifiers":[
        {
            "category":"Manufacturing",
            "subcategory":"Apparel",
            "type":"Manufacturing & Wholesale Goods"
        }
    ],
    "sg:phone":"+1 973 429 2272",
    "sg:postcode":"07003",
    "sg:province":"NJ",
    "sg:tags":[
        "household",
        "furnishing",
        "mfg"
    ],
    "wof:name":"Aj Export",
    "wof:placetype":"venue"
},
  "geometry": {"coordinates":[-74.18188600000001,40.80004],"type":"Point"}
}