{
  "type": "Feature",
  "properties": {
    "iso:country":"US",
    "sg:address":"845 Broadway",
    "sg:city":"Bayonne",
    "sg:classifiers":[
        {
            "category":"Health Services",
            "subcategory":"Doctor",
            "type":"Services"
        }
    ],
    "sg:phone":"+1 201 823 9475",
    "sg:postcode":"07002",
    "sg:province":"NJ",
    "sg:tags":[
        "physician",
        "surgeon"
    ],
    "wof:name":"Shing Hong Lu MD",
    "wof:placetype":"venue"
},
  "geometry": {"coordinates":[-74.107544,40.676686],"type":"Point"}
}