{
  "type": "Feature",
  "properties": {
    "addr:full":"1525 Wabash Ave Linwood NJ 08221",
    "addr:housenumber":"1525",
    "addr:postcode":"08221",
    "addr:street":"Wabash Ave",
    "iso:country":"US",
    "sg:address":"1525 Wabash Ave",
    "sg:city":"Linwood",
    "sg:classifiers":[
        {
            "category":"Building & Trades",
            "subcategory":"Construction",
            "type":"Services"
        }
    ],
    "sg:phone":"+1 609 926 0220",
    "sg:postcode":"08221",
    "sg:province":"NJ",
    "sg:tags":[
        "contractor"
    ],
    "wof:name":"North Star Construction Co",
    "wof:placetype":"venue"
},
  "geometry": {"coordinates":[-74.57786,39.341124],"type":"Point"}
}