{
  "type": "Feature",
  "properties": {
    "addr:full":"151 Ferry St Newark NJ 07105",
    "addr:housenumber":"151",
    "addr:postcode":"07105",
    "addr:street":"Ferry St",
    "iso:country":"US",
    "sg:address":"151 Ferry St",
    "sg:city":"Newark",
    "sg:classifiers":[
        {
            "category":"Banks & Credit Unions",
            "subcategory":"Bank",
            "type":"Services"
        }
    ],
    "sg:phone":"+1 973 465 0157",
    "sg:postcode":"07105",
    "sg:province":"NJ",
    "sg:website":"www.hsbcusa.com",
    "wof:name":"Hsbc Bank USA Na National",
    "wof:placetype":"venue"
},
  "geometry": {"coordinates":[-74.15874100000001,40.729197],"type":"Point"}
}