{
  "type": "Feature",
  "properties": {
    "iso:country":"US",
    "sg:address":"87 Elm Rd",
    "sg:city":"Caldwell",
    "sg:classifiers":[
        {
            "category":"Professional",
            "type":"Services"
        }
    ],
    "sg:phone":"+1   ",
    "sg:postcode":"07006",
    "sg:province":"NJ",
    "wof:name":"Deaquino Joanne & Leone Anthon",
    "wof:placetype":"venue"
},
  "geometry": {"coordinates":[-74.270245,40.835795],"type":"Point"}
}