{
  "type": "Feature",
  "properties": {
    "addr:full":"593 Pennsylvania Ave Brick NJ 08724",
    "addr:housenumber":"593",
    "addr:postcode":"08724",
    "addr:street":"Pennsylvania Ave",
    "iso:country":"US",
    "sg:address":"593 Pennsylvania Ave",
    "sg:city":"Brick",
    "sg:classifiers":[
        {
            "category":"Building & Trades",
            "subcategory":"Construction",
            "type":"Services"
        }
    ],
    "sg:phone":"+1 732 840 4752",
    "sg:postcode":"08724",
    "sg:province":"NJ",
    "sg:tags":[
        "hanging",
        "contractor"
    ],
    "wof:name":"Dj Tredy Painting",
    "wof:placetype":"venue"
},
  "geometry": {"coordinates":[-74.123133,40.110323],"type":"Point"}
}