{
  "type": "Feature",
  "properties": {
    "addr:full":"5 Old Milford Ln West Milford NJ 07480",
    "addr:housenumber":"5",
    "addr:postcode":"07480",
    "addr:street":"Old Milford Ln",
    "iso:country":"US",
    "sg:address":"5 Old Milford Ln",
    "sg:city":"West Milford",
    "sg:classifiers":[
        {
            "category":"Cinema",
            "subcategory":"Movie Rental",
            "type":"Entertainment"
        }
    ],
    "sg:phone":"+1 973 657 9887",
    "sg:postcode":"07480",
    "sg:province":"NJ",
    "sg:tags":[
        "video",
        "tape"
    ],
    "wof:name":"Crystal Image Video",
    "wof:placetype":"venue"
},
  "geometry": {"coordinates":[-74.406249,41.102632],"type":"Point"}
}