{
  "type": "Feature",
  "properties": {
    "addr:full":"34 Charlotte Dr Bridgewater NJ 08807",
    "addr:housenumber":"34",
    "addr:postcode":"08807",
    "addr:street":"Charlotte Dr",
    "iso:country":"US",
    "sg:address":"34 Charlotte Dr",
    "sg:city":"Bridgewater",
    "sg:classifiers":[
        {
            "category":"Wholesale",
            "subcategory":"Machinery & Supplies",
            "type":"Manufacturing & Wholesale Goods"
        },
        {
            "category":"Manufacturing",
            "subcategory":"Tools & Machinery",
            "type":"Manufacturing & Wholesale Goods"
        }
    ],
    "sg:phone":"+1 908 722 2808",
    "sg:postcode":"08807",
    "sg:province":"NJ",
    "sg:tags":[
        "tubing",
        "industrial",
        "hose",
        "mfg"
    ],
    "wof:name":"B and A Flex Inc",
    "wof:placetype":"venue"
},
  "geometry": {"coordinates":[-74.65998500000001,40.573782],"type":"Point"}
}