{
  "type": "Feature",
  "properties": {
    "addr:full":"630 Broad St Carlstadt NJ 07072",
    "addr:housenumber":"630",
    "addr:postcode":"07072",
    "addr:street":"Broad St",
    "iso:country":"US",
    "sg:address":"630 Broad St",
    "sg:city":"Carlstadt",
    "sg:classifiers":[
        {
            "category":"Freight",
            "type":"Transportation"
        }
    ],
    "sg:phone":"+1 201 933 9985",
    "sg:postcode":"07072",
    "sg:province":"NJ",
    "wof:name":"Prospect Transportation",
    "wof:placetype":"venue"
},
  "geometry": {"coordinates":[-74.100083,40.841856],"type":"Point"}
}