{
  "type": "Feature",
  "properties": {
    "addr:full":"366 Forest Hill Way Mountainside NJ 07092",
    "addr:housenumber":"366",
    "addr:postcode":"07092",
    "addr:street":"Forest Hill Way",
    "iso:country":"US",
    "sg:address":"366 Forest Hill Way",
    "sg:city":"Mountainside",
    "sg:classifiers":[
        {
            "category":"Building & Trades",
            "subcategory":"Locksmith",
            "type":"Services"
        }
    ],
    "sg:phone":"+1 877 768 2565",
    "sg:postcode":"07092",
    "sg:province":"NJ",
    "sg:tags":[
        "key"
    ],
    "wof:name":"24 Hour 7 Day Emergency Locksmith",
    "wof:placetype":"venue"
},
  "geometry": {"coordinates":[-74.371172,40.677079],"type":"Point"}
}