{
  "type": "Feature",
  "properties": {
    "addr:full":"540 Nassau Park Blvd Princeton NJ 08540",
    "addr:housenumber":"540",
    "addr:postcode":"08540",
    "addr:street":"Nassau Park Blvd",
    "iso:country":"US",
    "sg:address":"540 Nassau Park Blvd",
    "sg:city":"Princeton",
    "sg:classifiers":[
        {
            "category":"Wholesale",
            "subcategory":"Drugs",
            "type":"Manufacturing & Wholesale Goods"
        }
    ],
    "sg:phone":"+1 609 452 1266",
    "sg:postcode":"08540",
    "sg:province":"NJ",
    "wof:name":"Ulta 3 Cosmetics",
    "wof:placetype":"venue"
},
  "geometry": {"coordinates":[-74.677785,40.304488],"type":"Point"}
}