{
  "type": "Feature",
  "properties": {
    "addr:full":"12 Red Barn Ln Randolph NJ 07869",
    "addr:housenumber":"12",
    "addr:postcode":"07869",
    "addr:street":"Red Barn Ln",
    "iso:country":"US",
    "sg:address":"12 Red Barn Ln",
    "sg:city":"Randolph",
    "sg:classifiers":[
        {
            "category":"Professional",
            "subcategory":"Business Services",
            "type":"Services"
        }
    ],
    "sg:phone":"+1   ",
    "sg:postcode":"07869",
    "sg:province":"NJ",
    "wof:name":"Retail Advisory Group",
    "wof:placetype":"venue"
},
  "geometry": {"coordinates":[-74.553549,40.840774],"type":"Point"}
}