{
  "type": "Feature",
  "properties": {
    "addr:full":"61 Kierst St Parlin NJ 08859",
    "addr:housenumber":"61",
    "addr:postcode":"08859",
    "addr:street":"Kierst St",
    "iso:country":"US",
    "sg:address":"61 Kierst St",
    "sg:city":"Parlin",
    "sg:classifiers":[
        {
            "category":"Professional",
            "subcategory":"Art Services",
            "type":"Services"
        }
    ],
    "sg:phone":"+1   ",
    "sg:postcode":"08859",
    "sg:province":"NJ",
    "sg:tags":[
        "commercial",
        "design"
    ],
    "wof:name":"Videotropics Corp",
    "wof:placetype":"venue"
},
  "geometry": {"coordinates":[-74.309121,40.465593],"type":"Point"}
}