{
  "type": "Feature",
  "properties": {
    "iso:country":"US",
    "sg:address":"14 Mine St",
    "sg:city":"Flemington",
    "sg:classifiers":[
        {
            "category":"Insurance",
            "subcategory":"Hazard Insurance",
            "type":"Services"
        }
    ],
    "sg:phone":"+1 908 788 8481",
    "sg:postcode":"08822",
    "sg:province":"NJ",
    "sg:tags":[
        "bond"
    ],
    "wof:name":"Accurate Bail Bonds",
    "wof:placetype":"venue"
},
  "geometry": {"coordinates":[-74.859865,40.508379],"type":"Point"}
}