{
  "type": "Feature",
  "properties": {
    "addr:full":"255 Mount Prospect Ave Clifton NJ 07012",
    "addr:housenumber":"255",
    "addr:postcode":"07012",
    "addr:street":"Mount Prospect Ave",
    "iso:country":"US",
    "sg:address":"255 Mount Prospect Ave",
    "sg:city":"Clifton",
    "sg:classifiers":[
        {
            "category":"Professional",
            "type":"Services"
        }
    ],
    "sg:phone":"+1   ",
    "sg:postcode":"07012",
    "sg:province":"NJ",
    "wof:name":"Ace Installing",
    "wof:placetype":"venue"
},
  "geometry": {"coordinates":[-74.158924,40.859137],"type":"Point"}
}