{
  "type": "Feature",
  "properties": {
    "addr:full":"104 N White Horse Pike Haddonfield NJ 08033",
    "addr:housenumber":"104",
    "addr:postcode":"08033",
    "addr:street":"N White Horse Pike",
    "iso:country":"US",
    "sg:address":"104 N White Horse Pike",
    "sg:city":"Haddonfield",
    "sg:classifiers":[
        {
            "category":"Banks & Credit Unions",
            "subcategory":"Bank",
            "type":"Services"
        }
    ],
    "sg:phone":"+1 856 772 4315",
    "sg:postcode":"08033",
    "sg:province":"NJ",
    "sg:website":"www.pnc.com",
    "wof:name":"Pnc Bank",
    "wof:placetype":"venue"
},
  "geometry": {"coordinates":[-75.04858400000001,39.875616],"type":"Point"}
}