{
  "type": "Feature",
  "properties": {
    "addr:full":"110 Prospect Ave Dunellen NJ 08812",
    "addr:housenumber":"110",
    "addr:postcode":"08812",
    "addr:street":"Prospect Ave",
    "iso:country":"US",
    "sg:address":"110 Prospect Ave",
    "sg:city":"Dunellen",
    "sg:classifiers":[
        {
            "category":"Taxi",
            "type":"Transportation"
        }
    ],
    "sg:phone":"+1 732 968 6699",
    "sg:postcode":"08812",
    "sg:province":"NJ",
    "sg:tags":[
        "taxicab"
    ],
    "wof:name":"Sunshine Taxi",
    "wof:placetype":"venue"
},
  "geometry": {"coordinates":[-74.463842,40.588451],"type":"Point"}
}