{
  "type": "Feature",
  "properties": {
    "iso:country":"US",
    "sg:address":"18 Sims St",
    "sg:city":"Dover",
    "sg:classifiers":[
        {
            "category":"Building & Trades",
            "subcategory":"Construction",
            "type":"Services"
        }
    ],
    "sg:phone":"+1 973 989 0724",
    "sg:postcode":"07801",
    "sg:province":"NJ",
    "sg:tags":[
        "house"
    ],
    "wof:name":"Senoz Construction",
    "wof:placetype":"venue"
},
  "geometry": {"coordinates":[-74.54218899999999,40.890925],"type":"Point"}
}