{
  "type": "Feature",
  "properties": {
    "iso:country":"US",
    "sg:address":"871 Broad St",
    "sg:city":"Newark",
    "sg:classifiers":[
        {
            "category":"Restaurant",
            "type":"Food & Drink"
        }
    ],
    "sg:menulink":"http://www.allmenus.com/nj/newark/27129-steak-house-1/menu/",
    "sg:phone":"+1 973 824 7703",
    "sg:postcode":"07102",
    "sg:province":"NJ",
    "sg:tags":[
        "american",
        "steakhouse"
    ],
    "wof:name":"Steak House 1",
    "wof:placetype":"venue"
},
  "geometry": {"coordinates":[-74.17350399999999,40.733294],"type":"Point"}
}