{
  "type": "Feature",
  "properties": {
    "iso:country":"US",
    "sg:address":"148 Lower Main St",
    "sg:city":"Matawan",
    "sg:classifiers":[
        {
            "category":"Wholesale",
            "subcategory":"Auto Parts",
            "type":"Manufacturing & Wholesale Goods"
        }
    ],
    "sg:phone":"+1 732 566 1088",
    "sg:postcode":"07747",
    "sg:province":"NJ",
    "sg:tags":[
        "body",
        "automobile",
        "shop"
    ],
    "sg:website":"www.mattysautoparts.com",
    "wof:name":"Matty's Auto Parts",
    "wof:placetype":"venue"
},
  "geometry": {"coordinates":[-74.22179800000001,40.422076],"type":"Point"}
}