{
  "type": "Feature",
  "properties": {
    "addr:full":"30 Eastbrook Rd Parsippany NJ 07054",
    "addr:housenumber":"30",
    "addr:postcode":"07054",
    "addr:street":"Eastbrook Rd",
    "iso:country":"US",
    "sg:address":"30 Eastbrook Rd",
    "sg:city":"Parsippany",
    "sg:classifiers":[
        {
            "category":"Professional",
            "subcategory":"Management & Consulting",
            "type":"Services"
        }
    ],
    "sg:phone":"+1   ",
    "sg:postcode":"07054",
    "sg:province":"NJ",
    "sg:tags":[
        "business"
    ],
    "wof:name":"Gray Toolbox Consulting I",
    "wof:placetype":"venue"
},
  "geometry": {"coordinates":[-74.414351,40.849602],"type":"Point"}
}