{
  "type": "Feature",
  "properties": {
    "addr:full":"600 Highland Dr Westampton NJ 08060",
    "addr:housenumber":"600",
    "addr:postcode":"08060",
    "addr:street":"Highland Dr",
    "iso:country":"US",
    "sg:address":"600 Highland Dr",
    "sg:city":"Westampton",
    "sg:classifiers":[
        {
            "category":"Professional",
            "type":"Services"
        }
    ],
    "sg:phone":"+1 609 265 1280",
    "sg:postcode":"08060",
    "sg:province":"NJ",
    "sg:tags":[
        "establishment"
    ],
    "wof:name":"Compassionate Care Hspcfndtns",
    "wof:placetype":"venue"
},
  "geometry": {"coordinates":[-74.85996900000001,40.005764],"type":"Point"}
}