{
  "type": "Feature",
  "properties": {
    "iso:country":"US",
    "sg:address":"200 Roosevelt Pl",
    "sg:city":"Palisades Park",
    "sg:classifiers":[
        {
            "category":"Real Estate",
            "subcategory":"Real Estate Services",
            "type":"Services"
        }
    ],
    "sg:phone":"+1 201 944 4425",
    "sg:postcode":"07650",
    "sg:province":"NJ",
    "sg:tags":[
        "management",
        "property"
    ],
    "wof:name":"Tryon Management",
    "wof:placetype":"venue"
},
  "geometry": {"coordinates":[-74.005769,40.85168],"type":"Point"}
}