{
  "type": "Feature",
  "properties": {
    "iso:country":"US",
    "sg:address":"500 State Rte 17",
    "sg:city":"Hasbrouck Heights",
    "sg:classifiers":[
        {
            "category":"Banks & Credit Unions",
            "subcategory":"Bank",
            "type":"Services"
        }
    ],
    "sg:phone":"+1   ",
    "sg:postcode":"07604",
    "sg:province":"NJ",
    "sg:tags":[
        "analysis",
        "billing",
        "bi"
    ],
    "wof:name":"Americn Natl Mortgage Assistnc",
    "wof:placetype":"venue"
},
  "geometry": {"coordinates":[-74.063295,40.869569],"type":"Point"}
}