{
  "type": "Feature",
  "properties": {
    "iso:country":"US",
    "sg:address":"270 Georgetown Rd",
    "sg:city":"Columbus",
    "sg:classifiers":[
        {
            "category":"Wholesale",
            "subcategory":"Apparel",
            "type":"Manufacturing & Wholesale Goods"
        }
    ],
    "sg:phone":"+1 609 298 1177",
    "sg:postcode":"08022",
    "sg:province":"NJ",
    "sg:tags":[
        "clothing",
        "footwear"
    ],
    "wof:name":"Hat Ta Boot Sales Inc",
    "wof:placetype":"venue"
},
  "geometry": {"coordinates":[-74.639278,40.079916],"type":"Point"}
}