{
  "type": "Feature",
  "properties": {
    "iso:country":"US",
    "sg:address":"39 Mohican Rd",
    "sg:city":"Blairstown",
    "sg:classifiers":[
        {
            "category":"Health Services",
            "subcategory":"Health Practitioner",
            "type":"Services"
        }
    ],
    "sg:phone":"+1 908 362 7574",
    "sg:postcode":"07825",
    "sg:province":"NJ",
    "wof:name":"Economic Soultions",
    "wof:placetype":"venue"
},
  "geometry": {"coordinates":[-74.97645,40.996728],"type":"Point"}
}