{
  "type": "Feature",
  "properties": {
    "addr:full":"160 Washington Corner Rd Bernardsville NJ 07924",
    "addr:housenumber":"160",
    "addr:postcode":"07924",
    "addr:street":"Washington Corner Rd",
    "iso:country":"US",
    "sg:address":"160 Washington Corner Rd",
    "sg:city":"Bernardsville",
    "sg:classifiers":[
        {
            "category":"Farming",
            "subcategory":"Farm",
            "type":"Manufacturing & Wholesale Goods"
        }
    ],
    "sg:phone":"+1 908 766 1852",
    "sg:postcode":"07924",
    "sg:province":"NJ",
    "sg:tags":[
        "crop",
        "general"
    ],
    "wof:name":"Top of Hill Farm",
    "wof:placetype":"venue"
},
  "geometry": {"coordinates":[-74.572447,40.749491],"type":"Point"}
}