{
  "type": "Feature",
  "properties": {
    "addr:full":"713 W Kennedy Blvd Lakewood NJ 08701",
    "addr:housenumber":"713",
    "addr:postcode":"08701",
    "addr:street":"W Kennedy Blvd",
    "iso:country":"US",
    "sg:address":"713 W Kennedy Blvd",
    "sg:city":"Lakewood",
    "sg:classifiers":[
        {
            "category":"Insurance",
            "subcategory":"Insurance Agent",
            "type":"Services"
        }
    ],
    "sg:phone":"+1   ",
    "sg:postcode":"08701",
    "sg:province":"NJ",
    "wof:name":"Mayco Financial Services",
    "wof:placetype":"venue"
},
  "geometry": {"coordinates":[-74.226394,40.107482],"type":"Point"}
}