{
  "type": "Feature",
  "properties": {
    "iso:country":"US",
    "sg:address":"537 Monmouth Rd",
    "sg:city":"Jackson",
    "sg:classifiers":[
        {
            "category":"Shopping",
            "subcategory":"Clothing, Apparel, & Fashions",
            "type":"Retail Goods"
        }
    ],
    "sg:phone":"+1 732 928 7747",
    "sg:postcode":"08527",
    "sg:province":"NJ",
    "sg:tags":[
        "lingerie"
    ],
    "wof:name":"Maidenform",
    "wof:placetype":"venue"
},
  "geometry": {"coordinates":[-74.42093199999999,40.16242],"type":"Point"}
}