{
  "type": "Feature",
  "properties": {
    "iso:country":"US",
    "sg:address":"50 Magnolia Rd",
    "sg:city":"Pemberton",
    "sg:classifiers":[
        {
            "category":"Food & Beverages",
            "subcategory":"Groceries & Convenience Stores",
            "type":"Retail Goods"
        }
    ],
    "sg:phone":"+1   ",
    "sg:postcode":"08068",
    "sg:province":"NJ",
    "wof:name":"Village Store",
    "wof:placetype":"venue"
},
  "geometry": {"coordinates":[-74.679315,39.963588],"type":"Point"}
}