{
  "type": "Feature",
  "properties": {
    "iso:country":"US",
    "sg:address":"13 Manhattan Pl",
    "sg:city":"Cliffside Park",
    "sg:classifiers":[
        {
            "category":"Arts & Performance",
            "subcategory":"Theater",
            "type":"Entertainment"
        }
    ],
    "sg:phone":"+1 201 313 9081",
    "sg:postcode":"07010",
    "sg:province":"NJ",
    "sg:tags":[
        "group"
    ],
    "wof:name":"Ylan Management Corp",
    "wof:placetype":"venue"
},
  "geometry": {"coordinates":[-73.994376,40.807787],"type":"Point"}
}