{
  "type": "Feature",
  "properties": {
    "iso:country":"US",
    "sg:address":"464 Broadway",
    "sg:city":"Bayonne",
    "sg:classifiers":[
        {
            "category":"Utilities",
            "subcategory":"Mobile Phone",
            "type":"Services"
        }
    ],
    "sg:phone":"+1 201 436 3555",
    "sg:postcode":"07002",
    "sg:province":"NJ",
    "sg:tags":[
        "telephone",
        "cellular"
    ],
    "wof:name":"Cellular Source 520a Inc",
    "wof:placetype":"venue"
},
  "geometry": {"coordinates":[-74.119029,40.662847],"type":"Point"}
}