{
  "type": "Feature",
  "properties": {
    "iso:country":"US",
    "sg:address":"60 Distribution Blvd",
    "sg:city":"Edison",
    "sg:classifiers":[
        {
            "category":"Shopping",
            "type":"Retail Goods"
        }
    ],
    "sg:phone":"+1   ",
    "sg:postcode":"08837",
    "sg:province":"NJ",
    "sg:tags":[
        "merchandise"
    ],
    "wof:name":"E G & G Dynatrend",
    "wof:placetype":"venue"
},
  "geometry": {"coordinates":[-74.379535,40.498986],"type":"Point"}
}