{
  "type": "Feature",
  "properties": {
    "iso:country":"US",
    "sg:address":"26 Worlds Fair Dr",
    "sg:city":"Somerset",
    "sg:classifiers":[
        {
            "category":"Manufacturing",
            "subcategory":"Printing",
            "type":"Manufacturing & Wholesale Goods"
        }
    ],
    "sg:phone":"+1 732 469 6166",
    "sg:postcode":"08873",
    "sg:province":"NJ",
    "sg:tags":[
        "commercial"
    ],
    "wof:name":"Mc Cartney Media Svc",
    "wof:placetype":"venue"
},
  "geometry": {"coordinates":[-74.518576,40.530229],"type":"Point"}
}