{
  "type": "Feature",
  "properties": {
    "addr:full":"1300 State Rt 17 Ramsey NJ 07446",
    "addr:housenumber":"1300",
    "addr:postcode":"07446",
    "addr:street":"State Rt 17",
    "iso:country":"US",
    "sg:address":"1300 State Rt 17",
    "sg:city":"Ramsey",
    "sg:classifiers":[
        {
            "category":"Utilities",
            "subcategory":"Mobile Phone",
            "type":"Services"
        },
        {
            "category":"Shopping",
            "subcategory":"Mobile Phones",
            "type":"Retail Goods"
        },
        {
            "category":"Utilities",
            "subcategory":"Telephone",
            "type":"Services"
        },
        {
            "category":"Professional",
            "subcategory":"Computer Services",
            "type":"Services"
        }
    ],
    "sg:phone":"+1 201 825 3993",
    "sg:postcode":"07446",
    "sg:province":"NJ",
    "sg:tags":[
        "telecommunication",
        "supply",
        "communication",
        "system",
        "wireless",
        "equipment",
        "cellular"
    ],
    "sg:website":"http://clickserve.dartsearch.net/link/click?lid=43000000308049899",
    "wof:name":"T-Mobile",
    "wof:placetype":"venue"
},
  "geometry": {"coordinates":[-74.13863000000001,41.070915],"type":"Point"}
}