{
  "type": "Feature",
  "properties": {
    "addr:full":"410 N Broad St Elizabeth NJ 07208",
    "addr:housenumber":"410",
    "addr:postcode":"07208",
    "addr:street":"N Broad St",
    "iso:country":"US",
    "sg:address":"410 N Broad St",
    "sg:city":"Elizabeth",
    "sg:classifiers":[
        {
            "category":"Banks & Credit Unions",
            "subcategory":"Bank",
            "type":"Services"
        }
    ],
    "sg:phone":"+1 908 558 0877",
    "sg:postcode":"07208",
    "sg:province":"NJ",
    "sg:tags":[
        "money",
        "transfer"
    ],
    "wof:name":"Centro Americas Svc",
    "wof:placetype":"venue"
},
  "geometry": {"coordinates":[-74.214203,40.672011],"type":"Point"}
}