{
  "type": "Feature",
  "properties": {
    "iso:country":"US",
    "sg:address":"113 13th Ave",
    "sg:city":"Belmar",
    "sg:classifiers":[
        {
            "category":"Professional",
            "subcategory":"Management & Consulting",
            "type":"Services"
        }
    ],
    "sg:phone":"+1 732 681 4003",
    "sg:postcode":"07719",
    "sg:province":"NJ",
    "sg:tags":[
        "consultant"
    ],
    "wof:name":"Sephmer Sciences",
    "wof:placetype":"venue"
},
  "geometry": {"coordinates":[-74.01549,40.174253],"type":"Point"}
}