{
  "type": "Feature",
  "properties": {
    "addr:full":"1750 Deptford Center Rd Woodbury NJ 08096",
    "addr:housenumber":"1750",
    "addr:postcode":"08096",
    "addr:street":"Deptford Center Rd",
    "iso:country":"US",
    "sg:address":"1750 Deptford Center Rd",
    "sg:city":"Woodbury",
    "sg:classifiers":[
        {
            "category":"Shopping",
            "subcategory":"Clothing, Apparel, & Fashions",
            "type":"Retail Goods"
        }
    ],
    "sg:phone":"+1 856 384 1808",
    "sg:postcode":"08096",
    "sg:province":"NJ",
    "sg:tags":[
        "furnishing"
    ],
    "wof:name":"Tie Shop",
    "wof:placetype":"venue"
},
  "geometry": {"coordinates":[-75.097632,39.828297],"type":"Point"}
}