{
  "type": "Feature",
  "properties": {
    "iso:country":"US",
    "sg:address":"71 S Orange Ave",
    "sg:city":"South Orange",
    "sg:classifiers":[
        {
            "category":"Real Estate",
            "subcategory":"Real Estate Agent",
            "type":"Services"
        }
    ],
    "sg:phone":"+1   ",
    "sg:postcode":"07079",
    "sg:province":"NJ",
    "wof:name":"Beechwood Gardens",
    "wof:placetype":"venue"
},
  "geometry": {"coordinates":[-74.258053,40.745835],"type":"Point"}
}