{
  "type": "Feature",
  "properties": {
    "addr:full":"3400 Atlantic Ave Wildwood NJ 08260",
    "addr:housenumber":"3400",
    "addr:postcode":"08260",
    "addr:street":"Atlantic Ave",
    "iso:country":"US",
    "sg:address":"3400 Atlantic Ave",
    "sg:city":"Wildwood",
    "sg:classifiers":[
        {
            "category":"Restaurant",
            "type":"Food & Drink"
        }
    ],
    "sg:phone":"+1 609 522 3085",
    "sg:postcode":"08260",
    "sg:province":"NJ",
    "wof:name":"Rusty Rudder Restaurant the",
    "wof:placetype":"venue"
},
  "geometry": {"coordinates":[-74.811897,38.988499],"type":"Point"}
}