{
  "type": "Feature",
  "properties": {
    "iso:country":"US",
    "sg:address":"66 State Rt 17",
    "sg:city":"Ramsey",
    "sg:classifiers":[
        {
            "category":"Fast Food",
            "type":"Food & Drink"
        },
        {
            "category":"Restaurant",
            "type":"Food & Drink"
        }
    ],
    "sg:phone":"+1 201 934 2953",
    "sg:postcode":"07446",
    "sg:province":"NJ",
    "sg:tags":[
        "style",
        "family",
        "american",
        "take",
        "pasta",
        "italian"
    ],
    "sg:website":"http://www.olivegarden.com",
    "wof:name":"Olive Garden",
    "wof:placetype":"venue"
},
  "geometry": {"coordinates":[-74.115376,41.043901],"type":"Point"}
}