{
  "type": "Feature",
  "properties": {
    "addr:full":"1603 State Rte 38 Lumberton NJ 08048",
    "addr:housenumber":"1603",
    "addr:postcode":"08048",
    "addr:street":"State Rte 38",
    "iso:country":"US",
    "sg:address":"1603 State Rte 38",
    "sg:city":"Lumberton",
    "sg:classifiers":[
        {
            "category":"Personal",
            "subcategory":"Barber",
            "type":"Services"
        }
    ],
    "sg:phone":"+1 609 267 0500",
    "sg:postcode":"08048",
    "sg:province":"NJ",
    "wof:name":"Headliners Barber & Beauty Sln",
    "wof:placetype":"venue"
},
  "geometry": {"coordinates":[-74.839781,39.975167],"type":"Point"}
}