{
  "type": "Feature",
  "properties": {
    "iso:country":"US",
    "sg:address":"6007 S US Highway 130 N",
    "sg:city":"Pennsauken",
    "sg:classifiers":[
        {
            "category":"Professional",
            "subcategory":"Employment Agencies",
            "type":"Services"
        }
    ],
    "sg:phone":"+1 856 910 9279",
    "sg:postcode":"08109",
    "sg:province":"NJ",
    "sg:website":"www.laborready.com",
    "wof:name":"Labor Ready",
    "wof:placetype":"venue"
},
  "geometry": {"coordinates":[-75.071455,39.942717],"type":"Point"}
}