{
  "type": "Feature",
  "properties": {
    "iso:country":"US",
    "sg:address":"41 Algonquin Ave.",
    "sg:city":"Lincoln Park",
    "sg:classifiers":[
        {
            "category":"Professional",
            "subcategory":"Advertising",
            "type":"Services"
        }
    ],
    "sg:phone":"+1 862 571 4036",
    "sg:postcode":"07035",
    "sg:province":"NJ",
    "sg:tags":[
        "advert",
        "advertising",
        "advertise",
        "advertisement",
        "subscription"
    ],
    "sg:website":"http://lagron.co.cc",
    "wof:name":"Premium Advert Solutions",
    "wof:placetype":"venue"
},
  "geometry": {"coordinates":[-74.284649,40.913278],"type":"Point"}
}