{
  "type": "Feature",
  "properties": {
    "addr:full":"1402 W Cleveland Ave Egg Harbor City NJ 08215",
    "addr:housenumber":"1402",
    "addr:postcode":"08215",
    "addr:street":"W Cleveland Ave",
    "iso:country":"US",
    "sg:address":"1402 W Cleveland Ave",
    "sg:city":"Egg Harbor City",
    "sg:classifiers":[
        {
            "category":"Retail",
            "subcategory":"Auto Repair",
            "type":"Services"
        }
    ],
    "sg:phone":"+1   ",
    "sg:postcode":"08215",
    "sg:province":"NJ",
    "sg:tags":[
        "general"
    ],
    "wof:name":"Hy Way Motors",
    "wof:placetype":"venue"
},
  "geometry": {"coordinates":[-74.652734,39.525438],"type":"Point"}
}