{
  "type": "Feature",
  "properties": {
    "addr:full":"7 Paley Pl Edison NJ 08817",
    "addr:housenumber":"7",
    "addr:postcode":"08817",
    "addr:street":"Paley Pl",
    "iso:country":"US",
    "sg:address":"7 Paley Pl",
    "sg:city":"Edison",
    "sg:classifiers":[
        {
            "category":"Freight",
            "type":"Transportation"
        }
    ],
    "sg:phone":"+1 732 985 2256",
    "sg:postcode":"08817",
    "sg:province":"NJ",
    "sg:tags":[
        "operator",
        "local",
        "trucking"
    ],
    "wof:name":"Maragoto Trucking Liabilit",
    "wof:placetype":"venue"
},
  "geometry": {"coordinates":[-74.38670399999999,40.512154],"type":"Point"}
}