{
  "type": "Feature",
  "properties": {
    "addr:full":"306 Bergen Mall Paramus NJ 07652",
    "addr:housenumber":"306",
    "addr:postcode":"07652",
    "addr:street":"Bergen Mall",
    "iso:country":"US",
    "sg:address":"306 Bergen Mall",
    "sg:city":"Paramus",
    "sg:classifiers":[
        {
            "category":"Restaurant",
            "type":"Food & Drink"
        }
    ],
    "sg:menulink":"http://www.allmenus.com/nj/paramus/82826-villa-pizza/menu/",
    "sg:phone":"+1 201 843 4453",
    "sg:postcode":"07652",
    "sg:province":"NJ",
    "sg:tags":[
        "american",
        "italian",
        "pizza"
    ],
    "wof:name":"Villa Pizza",
    "wof:placetype":"venue"
},
  "geometry": {"coordinates":[-74.062338,40.916285],"type":"Point"}
}