{
  "type": "Feature",
  "properties": {
    "iso:country":"US",
    "sg:address":"111 Park Ave",
    "sg:city":"Lyndhurst",
    "sg:classifiers":[
        {
            "category":"Retail",
            "subcategory":"Auto Repair",
            "type":"Services"
        }
    ],
    "sg:phone":"+1 201 939 2133",
    "sg:postcode":"07071",
    "sg:province":"NJ",
    "sg:tags":[
        "body",
        "shop"
    ],
    "wof:name":"Lyndhurst Auto Body",
    "wof:placetype":"venue"
},
  "geometry": {"coordinates":[-74.110497,40.825001],"type":"Point"}
}