{
  "type": "Feature",
  "properties": {
    "iso:country":"US",
    "sg:address":"196 Bartholdi Ave",
    "sg:city":"Jersey City",
    "sg:classifiers":[
        {
            "category":"Building & Trades",
            "subcategory":"Plumbing",
            "type":"Services"
        }
    ],
    "sg:phone":"+1 201 434 6438",
    "sg:postcode":"07305",
    "sg:province":"NJ",
    "wof:name":"Osnato P J Plumbing & Heating",
    "wof:placetype":"venue"
},
  "geometry": {"coordinates":[-74.098602,40.698799],"type":"Point"}
}