{
  "type": "Feature",
  "properties": {
    "iso:country":"US",
    "sg:address":"30 N Black Horse Pike",
    "sg:city":"Bellmawr",
    "sg:classifiers":[
        {
            "category":"Home & Garden",
            "subcategory":"Furniture",
            "type":"Retail Goods"
        }
    ],
    "sg:phone":"+1 856 933 7500",
    "sg:postcode":"08031",
    "sg:province":"NJ",
    "wof:name":"Globe Furniture Inc",
    "wof:placetype":"venue"
},
  "geometry": {"coordinates":[-75.07925,39.865827],"type":"Point"}
}