{
  "type": "Feature",
  "properties": {
    "iso:country":"US",
    "sg:address":"850 US Hwy 1",
    "sg:city":"North Brunswick",
    "sg:classifiers":[
        {
            "category":"Wholesale",
            "subcategory":"Medical Equipment & Supplies",
            "type":"Manufacturing & Wholesale Goods"
        }
    ],
    "sg:phone":"+1 732 296 9922",
    "sg:postcode":"08902",
    "sg:province":"NJ",
    "sg:tags":[
        "physician",
        "surgeon"
    ],
    "wof:name":"Anshe Emeth Comm Dev Corp",
    "wof:placetype":"venue"
},
  "geometry": {"coordinates":[-74.471519,40.458236],"type":"Point"}
}