{
  "type": "Feature",
  "properties": {
    "addr:full":"201 Sweetland Ave Hillside NJ 07205",
    "addr:housenumber":"201",
    "addr:postcode":"07205",
    "addr:street":"Sweetland Ave",
    "iso:country":"US",
    "sg:address":"201 Sweetland Ave",
    "sg:city":"Hillside",
    "sg:classifiers":[
        {
            "category":"Manufacturing",
            "subcategory":"Tools & Machinery",
            "type":"Manufacturing & Wholesale Goods"
        }
    ],
    "sg:phone":"+1 908 688 4216",
    "sg:postcode":"07205",
    "sg:province":"NJ",
    "sg:tags":[
        "equipment",
        "pump",
        "pumping",
        "mfg"
    ],
    "wof:name":"Vanton Pump & Equipment Corp",
    "wof:placetype":"venue"
},
  "geometry": {"coordinates":[-74.241399,40.703069],"type":"Point"}
}