{
  "type": "Feature",
  "properties": {
    "addr:full":"525 Old Rte 33 Englishtown NJ 07726",
    "addr:housenumber":"525",
    "addr:postcode":"07726",
    "addr:street":"Old Rte 33",
    "iso:country":"US",
    "sg:address":"525 Old Rte 33",
    "sg:city":"Englishtown",
    "sg:classifiers":[
        {
            "category":"Real Estate",
            "subcategory":"Real Estate Agent",
            "type":"Services"
        }
    ],
    "sg:phone":"+1   ",
    "sg:postcode":"07726",
    "sg:province":"NJ",
    "wof:name":"Prudential",
    "wof:placetype":"venue"
},
  "geometry": {"coordinates":[-74.41838799999999,40.262104],"type":"Point"}
}