{
  "type": "Feature",
  "properties": {
    "addr:full":"15 Chubby Ln Montague NJ 07827",
    "addr:housenumber":"15",
    "addr:postcode":"07827",
    "addr:street":"Chubby Ln",
    "iso:country":"US",
    "sg:address":"15 Chubby Ln",
    "sg:city":"Montague",
    "sg:classifiers":[
        {
            "category":"Building & Trades",
            "subcategory":"Electrical",
            "type":"Services"
        }
    ],
    "sg:phone":"+1 973 293 3760",
    "sg:postcode":"07827",
    "sg:province":"NJ",
    "sg:tags":[
        "electrical",
        "contractor"
    ],
    "wof:name":"B P Electric",
    "wof:placetype":"venue"
},
  "geometry": {"coordinates":[-74.761703,41.291449],"type":"Point"}
}