{
  "type": "Feature",
  "properties": {
    "iso:country":"US",
    "sg:address":"1948 State Rte 33",
    "sg:city":"Trenton",
    "sg:classifiers":[
        {
            "category":"Real Estate",
            "subcategory":"Real Estate Agent",
            "type":"Services"
        }
    ],
    "sg:phone":"+1 609 586 1400",
    "sg:postcode":"08690",
    "sg:province":"NJ",
    "wof:name":"Weidel Realtors",
    "wof:placetype":"venue"
},
  "geometry": {"coordinates":[-74.65397400000001,40.225172],"type":"Point"}
}