{
  "type": "Feature",
  "properties": {
    "iso:country":"US",
    "sg:address":"1103 Sedgefield Dr",
    "sg:city":"Mount Laurel",
    "sg:classifiers":[
        {
            "category":"Shopping",
            "subcategory":"Computers & Home Electronics",
            "type":"Retail Goods"
        }
    ],
    "sg:phone":"+1   ",
    "sg:postcode":"08054",
    "sg:province":"NJ",
    "wof:name":"Ldp Computers",
    "wof:placetype":"venue"
},
  "geometry": {"coordinates":[-74.880054,39.971973],"type":"Point"}
}