{
  "type": "Feature",
  "properties": {
    "addr:full":"57 Morristown Rd Bernardsville NJ 07924",
    "addr:housenumber":"57",
    "addr:postcode":"07924",
    "addr:street":"Morristown Rd",
    "iso:country":"US",
    "sg:address":"57 Morristown Rd",
    "sg:city":"Bernardsville",
    "sg:classifiers":[
        {
            "category":"Retail",
            "subcategory":"Auto Repair",
            "type":"Services"
        }
    ],
    "sg:phone":"+1 908 766 3588",
    "sg:postcode":"07924",
    "sg:province":"NJ",
    "sg:tags":[
        "body",
        "automobile",
        "painting"
    ],
    "wof:name":"Pace Collision Svc Inc",
    "wof:placetype":"venue"
},
  "geometry": {"coordinates":[-74.563551,40.719154],"type":"Point"}
}