{
  "type": "Feature",
  "properties": {
    "iso:country":"US",
    "sg:address":"37 Brookside Ct",
    "sg:city":"Toms River",
    "sg:classifiers":[
        {
            "category":"Autos & Motor Vehicles",
            "subcategory":"Fuel & Gas Station",
            "type":"Retail Goods"
        }
    ],
    "sg:phone":"+1   ",
    "sg:postcode":"08753",
    "sg:province":"NJ",
    "sg:tags":[
        "general",
        "automobile",
        "station",
        "gasoline",
        "repair"
    ],
    "wof:name":"Vosper & Son",
    "wof:placetype":"venue"
},
  "geometry": {"coordinates":[-74.175673,39.973338],"type":"Point"}
}