{
  "type": "Feature",
  "properties": {
    "addr:full":"211 Hamburg Tpke Bloomingdale NJ 07403",
    "addr:housenumber":"211",
    "addr:postcode":"07403",
    "addr:street":"Hamburg Tpke",
    "iso:country":"US",
    "sg:address":"211 Hamburg Tpke",
    "sg:city":"Bloomingdale",
    "sg:classifiers":[
        {
            "category":"Retail",
            "subcategory":"Repair Shop",
            "type":"Services"
        }
    ],
    "sg:phone":"+1 973 839 1348",
    "sg:postcode":"07403",
    "sg:province":"NJ",
    "sg:tags":[
        "appliance"
    ],
    "wof:name":"Adept Appliance Svc",
    "wof:placetype":"venue"
},
  "geometry": {"coordinates":[-74.348478,41.005378],"type":"Point"}
}