{
  "type": "Feature",
  "properties": {
    "iso:country":"US",
    "sg:address":"32 Delray Pl",
    "sg:city":"South Amboy",
    "sg:classifiers":[
        {
            "category":"Professional",
            "subcategory":"Business Services",
            "type":"Services"
        }
    ],
    "sg:phone":"+1   ",
    "sg:postcode":"08879",
    "sg:province":"NJ",
    "wof:name":"Empyreal Solutions LLC",
    "wof:placetype":"venue"
},
  "geometry": {"coordinates":[-74.24930500000001,40.457251],"type":"Point"}
}