{
  "type": "Feature",
  "properties": {
    "iso:country":"US",
    "sg:address":"24 Dare Ln",
    "sg:city":"Sewell",
    "sg:classifiers":[
        {
            "category":"Wholesale",
            "subcategory":"Stationery",
            "type":"Manufacturing & Wholesale Goods"
        }
    ],
    "sg:phone":"+1 856 589 6591",
    "sg:postcode":"08080",
    "sg:province":"NJ",
    "sg:tags":[
        "novelty",
        "supply"
    ],
    "wof:name":"Debbie Lynn Inc",
    "wof:placetype":"venue"
},
  "geometry": {"coordinates":[-75.103801,39.740752],"type":"Point"}
}