{
  "type": "Feature",
  "properties": {
    "iso:country":"US",
    "sg:address":"127 Chestnut St",
    "sg:city":"Roselle Park",
    "sg:classifiers":[
        {
            "category":"Shopping",
            "subcategory":"Clothing, Apparel, & Fashions",
            "type":"Retail Goods"
        }
    ],
    "sg:phone":"+1 908 241 5255",
    "sg:postcode":"07204",
    "sg:province":"NJ",
    "sg:tags":[
        "t"
    ],
    "sg:website":"www.acepromotionalproducts.com",
    "wof:name":"Ace Promotional Products",
    "wof:placetype":"venue"
},
  "geometry": {"coordinates":[-74.264263,40.663213],"type":"Point"}
}