{
  "type": "Feature",
  "properties": {
    "iso:country":"US",
    "sg:address":"125 State Rte 73",
    "sg:city":"Berlin",
    "sg:classifiers":[
        {
            "category":"Real Estate",
            "subcategory":"Real Estate Agent",
            "type":"Services"
        }
    ],
    "sg:phone":"+1 856 768 7270",
    "sg:postcode":"08009",
    "sg:province":"NJ",
    "wof:name":"Jeb's Realty",
    "wof:placetype":"venue"
},
  "geometry": {"coordinates":[-74.919679,39.793478],"type":"Point"}
}