{
  "type": "Feature",
  "properties": {
    "addr:full":"595 Stonetown Rd Ringwood NJ 07456",
    "addr:housenumber":"595",
    "addr:postcode":"07456",
    "addr:street":"Stonetown Rd",
    "iso:country":"US",
    "sg:address":"595 Stonetown Rd",
    "sg:city":"Ringwood",
    "sg:classifiers":[
        {
            "category":"Retail",
            "subcategory":"Portrait Studio",
            "type":"Services"
        }
    ],
    "sg:phone":"+1   ",
    "sg:postcode":"07456",
    "sg:province":"NJ",
    "sg:tags":[
        "photo"
    ],
    "wof:name":"Larry Katzman Photography Ltd",
    "wof:placetype":"venue"
},
  "geometry": {"coordinates":[-74.302942,41.111639],"type":"Point"}
}