{
  "type": "Feature",
  "properties": {
    "addr:full":"5 Independence Dr Princeton NJ 08540",
    "addr:housenumber":"5",
    "addr:postcode":"08540",
    "addr:street":"Independence Dr",
    "iso:country":"US",
    "sg:address":"5 Independence Dr",
    "sg:city":"Princeton",
    "sg:classifiers":[
        {
            "category":"Professional",
            "subcategory":"Computer Services",
            "type":"Services"
        }
    ],
    "sg:phone":"+1 609 919 6000",
    "sg:postcode":"08540",
    "sg:province":"NJ",
    "sg:tags":[
        "programing",
        "custom"
    ],
    "wof:name":"Trintech Inc",
    "wof:placetype":"venue"
},
  "geometry": {"coordinates":[-74.675505,40.341412],"type":"Point"}
}