{
  "type": "Feature",
  "properties": {
    "iso:country":"US",
    "sg:address":"405 Southgate Ct",
    "sg:city":"Mickleton",
    "sg:classifiers":[
        {
            "category":"Wholesale",
            "subcategory":"Machinery & Supplies",
            "type":"Manufacturing & Wholesale Goods"
        }
    ],
    "sg:phone":"+1 856 423 9400",
    "sg:postcode":"08056",
    "sg:province":"NJ",
    "sg:tags":[
        "rep",
        "valve",
        "piping",
        "specialty",
        "mfg"
    ],
    "wof:name":"Wiltech Inc",
    "wof:placetype":"venue"
},
  "geometry": {"coordinates":[-75.253743,39.806109],"type":"Point"}
}