{
  "type": "Feature",
  "properties": {
    "addr:full":"800 Cooper St Camden NJ 08102",
    "addr:housenumber":"800",
    "addr:postcode":"08102",
    "addr:street":"Cooper St",
    "iso:country":"US",
    "sg:address":"800 Cooper St",
    "sg:city":"Camden",
    "sg:classifiers":[
        {
            "category":"Government",
            "subcategory":"Court House",
            "type":"Public Place"
        }
    ],
    "sg:phone":"+1 856 757 5341",
    "sg:postcode":"08102",
    "sg:province":"NJ",
    "sg:tags":[
        "federal",
        "counsel"
    ],
    "wof:name":"Federal Public Defender",
    "wof:placetype":"venue"
},
  "geometry": {"coordinates":[-75.11620499999999,39.945965],"type":"Point"}
}