{
  "type": "Feature",
  "properties": {
    "iso:country":"US",
    "sg:address":"500 S Riverside Dr",
    "sg:city":"Neptune",
    "sg:classifiers":[
        {
            "category":"Professional",
            "subcategory":"Management & Consulting",
            "type":"Services"
        }
    ],
    "sg:phone":"+1   ",
    "sg:postcode":"07753",
    "sg:province":"NJ",
    "sg:tags":[
        "business"
    ],
    "wof:name":"A2z Consulting LLC",
    "wof:placetype":"venue"
},
  "geometry": {"coordinates":[-74.047675,40.188953],"type":"Point"}
}