{
  "type": "Feature",
  "properties": {
    "iso:country":"US",
    "sg:address":"150 River Rd",
    "sg:city":"Montville",
    "sg:classifiers":[
        {
            "category":"Professional",
            "type":"Services"
        }
    ],
    "sg:phone":"+1 973 263 0711",
    "sg:postcode":"07045",
    "sg:province":"NJ",
    "sg:tags":[
        "establishment"
    ],
    "wof:name":"Hirschberg Development Co Inc",
    "wof:placetype":"venue"
},
  "geometry": {"coordinates":[-74.37064599999999,40.890465],"type":"Point"}
}