{
  "type": "Feature",
  "properties": {
    "iso:country":"US",
    "sg:address":"1115 Hornberger Ave",
    "sg:city":"Roebling",
    "sg:classifiers":[
        {
            "category":"Food & Beverages",
            "subcategory":"Liquor & Beverages",
            "type":"Retail Goods"
        },
        {
            "category":"Retail",
            "subcategory":"Funeral Services",
            "type":"Services"
        }
    ],
    "sg:phone":"+1 609 499 0640",
    "sg:postcode":"08554",
    "sg:province":"NJ",
    "sg:tags":[
        "beer",
        "cemetery",
        "spirit",
        "wine"
    ],
    "wof:name":"Koschek and Porter Funeral Directors Inc",
    "wof:placetype":"venue"
},
  "geometry": {"coordinates":[-74.787201,40.115898],"type":"Point"}
}