{
  "type": "Feature",
  "properties": {
    "iso:country":"US",
    "sg:address":"31 Pheasant Dr",
    "sg:city":"Long Valley",
    "sg:classifiers":[
        {
            "category":"Professional",
            "subcategory":"Management & Consulting",
            "type":"Services"
        }
    ],
    "sg:phone":"+1   ",
    "sg:postcode":"07853",
    "sg:province":"NJ",
    "wof:name":"Db Consulting",
    "wof:placetype":"venue"
},
  "geometry": {"coordinates":[-74.806763,40.808291],"type":"Point"}
}