{
  "type": "Feature",
  "properties": {
    "iso:country":"US",
    "sg:address":"59 Lakeview Dr N",
    "sg:city":"Gibbsboro",
    "sg:classifiers":[
        {
            "category":"Health Services",
            "subcategory":"Doctor",
            "type":"Services"
        }
    ],
    "sg:phone":"+1   ",
    "sg:postcode":"08026",
    "sg:province":"NJ",
    "wof:name":"Gary A Linton DDS",
    "wof:placetype":"venue"
},
  "geometry": {"coordinates":[-74.96240299999999,39.841421],"type":"Point"}
}