{
  "type": "Feature",
  "properties": {
    "iso:country":"US",
    "sg:address":"271 US Highway 46",
    "sg:city":"Fairfield",
    "sg:classifiers":[
        {
            "category":"Retail",
            "subcategory":"Portrait Studio",
            "type":"Services"
        }
    ],
    "sg:phone":"+1 973 227 7817",
    "sg:postcode":"07004",
    "sg:province":"NJ",
    "sg:tags":[
        "photography",
        "store"
    ],
    "wof:name":"Plastican Corp",
    "wof:placetype":"venue"
},
  "geometry": {"coordinates":[-74.299103,40.8773],"type":"Point"}
}