{
  "type": "Feature",
  "properties": {
    "iso:country":"US",
    "sg:address":"74 Fox Hill Rd",
    "sg:city":"Denville",
    "sg:classifiers":[
        {
            "category":"Building & Trades",
            "subcategory":"Landscaping Services",
            "type":"Services"
        }
    ],
    "sg:phone":"+1 973 983 0640",
    "sg:postcode":"07834",
    "sg:province":"NJ",
    "wof:name":"Tuff Greens",
    "wof:placetype":"venue"
},
  "geometry": {"coordinates":[-74.474586,40.878809],"type":"Point"}
}