{
  "type": "Feature",
  "properties": {
    "iso:country":"US",
    "sg:address":"330 N Harrison St",
    "sg:city":"Princeton",
    "sg:classifiers":[
        {
            "category":"Social Services",
            "type":"Services"
        }
    ],
    "sg:phone":"+1   ",
    "sg:postcode":"08540",
    "sg:province":"NJ",
    "wof:name":"Linda M Perlin Lcsw Bcd",
    "wof:placetype":"venue"
},
  "geometry": {"coordinates":[-74.651399,40.361181],"type":"Point"}
}