{
  "type": "Feature",
  "properties": {
    "addr:full":"2200 State Rte 66 Neptune NJ 07753",
    "addr:housenumber":"2200",
    "addr:postcode":"07753",
    "addr:street":"State Rte 66",
    "iso:country":"US",
    "sg:address":"2200 State Rte 66",
    "sg:city":"Neptune",
    "sg:classifiers":[
        {
            "category":"Banks & Credit Unions",
            "subcategory":"Bank",
            "type":"Services"
        }
    ],
    "sg:phone":"+1   ",
    "sg:postcode":"07753",
    "sg:province":"NJ",
    "sg:tags":[
        "state",
        "commercial"
    ],
    "wof:name":"Fleet",
    "wof:placetype":"venue"
},
  "geometry": {"coordinates":[-74.041804,40.226632],"type":"Point"}
}