{
  "type": "Feature",
  "properties": {
    "iso:country":"US",
    "sg:address":"107 W 3rd St",
    "sg:city":"Clifton",
    "sg:classifiers":[
        {
            "category":"Retail",
            "subcategory":"Auto Repair",
            "type":"Services"
        }
    ],
    "sg:phone":"+1 973 340 8232",
    "sg:postcode":"07011",
    "sg:province":"NJ",
    "sg:tags":[
        "automotive",
        "wrecker"
    ],
    "wof:name":"Compadres Towing R & P",
    "wof:placetype":"venue"
},
  "geometry": {"coordinates":[-74.15301700000001,40.887523],"type":"Point"}
}