{
  "type": "Feature",
  "properties": {
    "addr:full":"39 Oakwood Dr Medford NJ 08055",
    "addr:housenumber":"39",
    "addr:postcode":"08055",
    "addr:street":"Oakwood Dr",
    "iso:country":"US",
    "sg:address":"39 Oakwood Dr",
    "sg:city":"Medford",
    "sg:classifiers":[
        {
            "category":"Building & Trades",
            "subcategory":"Pest Control",
            "type":"Services"
        }
    ],
    "sg:phone":"+1 856 235 8606",
    "sg:postcode":"08055",
    "sg:province":"NJ",
    "wof:name":"Colonial Pest Control Co",
    "wof:placetype":"venue"
},
  "geometry": {"coordinates":[-74.83635599999999,39.875158],"type":"Point"}
}