{
  "type": "Feature",
  "properties": {
    "addr:full":"236 Georges Rd Dayton NJ 08810",
    "addr:housenumber":"236",
    "addr:postcode":"08810",
    "addr:street":"Georges Rd",
    "iso:country":"US",
    "sg:address":"236 Georges Rd",
    "sg:city":"Dayton",
    "sg:classifiers":[
        {
            "category":"Wholesale",
            "subcategory":"Metals & Minerals",
            "type":"Manufacturing & Wholesale Goods"
        }
    ],
    "sg:phone":"+1 732 355 1900",
    "sg:postcode":"08810",
    "sg:province":"NJ",
    "sg:tags":[
        "center"
    ],
    "wof:name":"Ceb Associates Inc",
    "wof:placetype":"venue"
},
  "geometry": {"coordinates":[-74.50613300000001,40.367563],"type":"Point"}
}