{
  "type": "Feature",
  "properties": {
    "addr:full":"381 Haledon Ave Haledon NJ 07508",
    "addr:housenumber":"381",
    "addr:postcode":"07508",
    "addr:street":"Haledon Ave",
    "iso:country":"US",
    "sg:address":"381 Haledon Ave",
    "sg:city":"Haledon",
    "sg:classifiers":[
        {
            "category":"Organizations",
            "subcategory":"Religious Organization",
            "type":"Services"
        }
    ],
    "sg:phone":"+1   ",
    "sg:postcode":"07508",
    "sg:province":"NJ",
    "wof:name":"Bridgeway Community Church",
    "wof:placetype":"venue"
},
  "geometry": {"coordinates":[-74.180685,40.936516],"type":"Point"}
}