{
  "type": "Feature",
  "properties": {
    "iso:country":"US",
    "sg:address":"530 S Wood Ave",
    "sg:city":"Linden",
    "sg:classifiers":[
        {
            "category":"Insurance",
            "subcategory":"Insurance Agent",
            "type":"Services"
        }
    ],
    "sg:phone":"+1 908 862 7499",
    "sg:postcode":"07036",
    "sg:province":"NJ",
    "wof:name":"Tango Insurance",
    "wof:placetype":"venue"
},
  "geometry": {"coordinates":[-74.24579799999999,40.627599],"type":"Point"}
}