{
  "type": "Feature",
  "properties": {
    "iso:country":"US",
    "sg:address":"59 Rue Chagall",
    "sg:city":"Somerset",
    "sg:classifiers":[
        {
            "category":"Real Estate",
            "subcategory":"Real Estate Agent",
            "type":"Services"
        }
    ],
    "sg:phone":"+1   ",
    "sg:postcode":"08873",
    "sg:province":"NJ",
    "wof:name":"United Eastern Group LLC",
    "wof:placetype":"venue"
},
  "geometry": {"coordinates":[-74.50304199999999,40.517517],"type":"Point"}
}