{
  "type": "Feature",
  "properties": {
    "addr:full":"41 Tam O Shanter Dr Mahwah NJ 07430",
    "addr:housenumber":"41",
    "addr:postcode":"07430",
    "addr:street":"Tam O Shanter Dr",
    "iso:country":"US",
    "sg:address":"41 Tam O Shanter Dr",
    "sg:city":"Mahwah",
    "sg:classifiers":[
        {
            "category":"Professional",
            "subcategory":"Computer Services",
            "type":"Services"
        }
    ],
    "sg:phone":"+1   ",
    "sg:postcode":"07430",
    "sg:province":"NJ",
    "sg:tags":[
        "programing",
        "custom"
    ],
    "wof:name":"Ballistic Computing Inc",
    "wof:placetype":"venue"
},
  "geometry": {"coordinates":[-74.106364,41.087206],"type":"Point"}
}