{
  "type": "Feature",
  "properties": {
    "iso:country":"US",
    "sg:address":"495 Main St",
    "sg:city":"Metuchen",
    "sg:classifiers":[
        {
            "category":"Professional",
            "subcategory":"Lawyer & Legal Services",
            "type":"Services"
        }
    ],
    "sg:phone":"+1 732 516 0300",
    "sg:postcode":"08840",
    "sg:province":"NJ",
    "sg:tags":[
        "attorney"
    ],
    "wof:name":"Paul R Hymas Attorney At Law",
    "wof:placetype":"venue"
},
  "geometry": {"coordinates":[-74.363259,40.544319],"type":"Point"}
}