{
  "type": "Feature",
  "properties": {
    "addr:full":"43 Raymond Ave Rutherford NJ 07070",
    "addr:housenumber":"43",
    "addr:postcode":"07070",
    "addr:street":"Raymond Ave",
    "iso:country":"US",
    "sg:address":"43 Raymond Ave",
    "sg:city":"Rutherford",
    "sg:classifiers":[
        {
            "category":"Building & Trades",
            "subcategory":"Construction",
            "type":"Services"
        },
        {
            "category":"Wholesale",
            "subcategory":"Home Furnishings",
            "type":"Manufacturing & Wholesale Goods"
        }
    ],
    "sg:phone":"+1 201 460 7634",
    "sg:postcode":"07070",
    "sg:province":"NJ",
    "sg:tags":[
        "accessory",
        "closet",
        "contractor"
    ],
    "wof:name":"Closets N More Inc",
    "wof:placetype":"venue"
},
  "geometry": {"coordinates":[-74.112504,40.84104],"type":"Point"}
}