{
  "type": "Feature",
  "properties": {
    "iso:country":"US",
    "sg:address":"300 Sunnymeade Rd",
    "sg:city":"Hillsborough",
    "sg:classifiers":[
        {
            "category":"Manufacturing",
            "subcategory":"Metals",
            "type":"Manufacturing & Wholesale Goods"
        }
    ],
    "sg:phone":"+1 908 359 8561",
    "sg:postcode":"08844",
    "sg:province":"NJ",
    "sg:tags":[
        "steel",
        "fabrication",
        "structural"
    ],
    "wof:name":"C & F Metal Fabricators Inc",
    "wof:placetype":"venue"
},
  "geometry": {"coordinates":[-74.612604,40.516476],"type":"Point"}
}