{
  "type": "Feature",
  "properties": {
    "addr:full":"58 Main Ave Clifton NJ 07014",
    "addr:housenumber":"58",
    "addr:postcode":"07014",
    "addr:street":"Main Ave",
    "iso:country":"US",
    "sg:address":"58 Main Ave",
    "sg:city":"Clifton",
    "sg:classifiers":[
        {
            "category":"Retail",
            "subcategory":"Repair Shop",
            "type":"Services"
        }
    ],
    "sg:phone":"+1 973 788 0337",
    "sg:postcode":"07014",
    "sg:province":"NJ",
    "sg:tags":[
        "lock",
        "locksmith"
    ],
    "wof:name":"Emergency A Locksmith",
    "wof:placetype":"venue"
},
  "geometry": {"coordinates":[-74.144927,40.828509],"type":"Point"}
}