{
  "type": "Feature",
  "properties": {
    "iso:country":"US",
    "sg:address":"219 Deerwood Ave",
    "sg:city":"Milmay",
    "sg:classifiers":[
        {
            "category":"Building & Trades",
            "subcategory":"Construction",
            "type":"Services"
        }
    ],
    "sg:phone":"+1 856 696 9307",
    "sg:postcode":"08340",
    "sg:province":"NJ",
    "sg:tags":[
        "masonry",
        "contractor"
    ],
    "wof:name":"Frank Masonary LLC",
    "wof:placetype":"venue"
},
  "geometry": {"coordinates":[-74.87188,39.44406],"type":"Point"}
}