{
  "type": "Feature",
  "properties": {
    "addr:full":"392 21st Ave Paterson NJ 07513",
    "addr:housenumber":"392",
    "addr:postcode":"07513",
    "addr:street":"21St Ave",
    "iso:country":"US",
    "sg:address":"392 21st Ave",
    "sg:city":"Paterson",
    "sg:classifiers":[
        {
            "category":"Restaurant",
            "type":"Food & Drink"
        }
    ],
    "sg:phone":"+1 973 247 0044",
    "sg:postcode":"07513",
    "sg:province":"NJ",
    "sg:tags":[
        "eating",
        "pizza"
    ],
    "wof:name":"Pan Pizza Bakery 3",
    "wof:placetype":"venue"
},
  "geometry": {"coordinates":[-74.15698999999999,40.906614],"type":"Point"}
}