{
  "type": "Feature",
  "properties": {
    "addr:full":"2 Cherry Ln Brookside NJ 07928",
    "addr:housenumber":"2",
    "addr:postcode":"07928",
    "addr:street":"Cherry Ln",
    "iso:country":"US",
    "sg:address":"2 Cherry Ln",
    "sg:city":"Brookside",
    "sg:classifiers":[
        {
            "category":"Education",
            "subcategory":"Library",
            "type":"Public Place"
        }
    ],
    "sg:phone":"+1 973 543 4018",
    "sg:postcode":"07928",
    "sg:province":"NJ",
    "sg:tags":[
        "rental"
    ],
    "wof:name":"Mendham Township Library",
    "wof:placetype":"venue"
},
  "geometry": {"coordinates":[-74.390647,40.739607],"type":"Point"}
}