{
  "type": "Feature",
  "properties": {
    "addr:full":"189 Washington Rd Princeton NJ 08540",
    "addr:housenumber":"189",
    "addr:postcode":"08540",
    "addr:street":"Washington Rd",
    "iso:country":"US",
    "sg:address":"189 Washington Rd",
    "sg:city":"Princeton",
    "sg:classifiers":[
        {
            "category":"Shopping",
            "subcategory":"Florist",
            "type":"Retail Goods"
        }
    ],
    "sg:phone":"+1 609 452 1383",
    "sg:postcode":"08540",
    "sg:province":"NJ",
    "wof:name":"Perna's Plant & Flower Shop",
    "wof:placetype":"venue"
},
  "geometry": {"coordinates":[-74.63177899999999,40.32666],"type":"Point"}
}