{
  "type": "Feature",
  "properties": {
    "iso:country":"US",
    "sg:address":"11 Chanowich Ct",
    "sg:city":"Middletown",
    "sg:classifiers":[
        {
            "category":"Retail",
            "subcategory":"Portrait Studio",
            "type":"Services"
        }
    ],
    "sg:phone":"+1   ",
    "sg:postcode":"07748",
    "sg:province":"NJ",
    "sg:tags":[
        "photo"
    ],
    "wof:name":"Elegant Portrait",
    "wof:placetype":"venue"
},
  "geometry": {"coordinates":[-74.106697,40.411043],"type":"Point"}
}