{
  "type": "Feature",
  "properties": {
    "addr:full":"1126 State Rte 73 Mt Laurel NJ 08054",
    "addr:housenumber":"1126",
    "addr:postcode":"08054",
    "addr:street":"State Rte 73 Mt",
    "iso:country":"US",
    "sg:address":"1126 State Rte 73",
    "sg:city":"Mt Laurel",
    "sg:classifiers":[
        {
            "category":"Manufacturing",
            "subcategory":"Printing",
            "type":"Manufacturing & Wholesale Goods"
        }
    ],
    "sg:phone":"+1 856 222 0639",
    "sg:postcode":"08054",
    "sg:province":"NJ",
    "sg:tags":[
        "broker"
    ],
    "wof:name":"Sureline Print & Design",
    "wof:placetype":"venue"
},
  "geometry": {"coordinates":[-74.87873399999999,39.920819],"type":"Point"}
}