{
  "type": "Feature",
  "properties": {
    "iso:country":"US",
    "sg:address":"320 40th St",
    "sg:city":"Union City",
    "sg:classifiers":[
        {
            "category":"Utilities",
            "subcategory":"Telephone",
            "type":"Services"
        }
    ],
    "sg:phone":"+1 201 867 6140",
    "sg:postcode":"07087",
    "sg:province":"NJ",
    "sg:tags":[
        "promotion",
        "internet"
    ],
    "wof:name":"Internet Promotions",
    "wof:placetype":"venue"
},
  "geometry": {"coordinates":[-74.02456599999999,40.775762],"type":"Point"}
}