{
  "type": "Feature",
  "properties": {
    "iso:country":"US",
    "sg:address":"46 Union St",
    "sg:city":"Closter",
    "sg:classifiers":[
        {
            "category":"Building & Trades",
            "subcategory":"Construction",
            "type":"Services"
        }
    ],
    "sg:phone":"+1 201 768 6140",
    "sg:postcode":"07624",
    "sg:province":"NJ",
    "sg:tags":[
        "house",
        "nonresidential"
    ],
    "wof:name":"Minasco Inc",
    "wof:placetype":"venue"
},
  "geometry": {"coordinates":[-73.981453,40.97287],"type":"Point"}
}