{
  "type": "Feature",
  "properties": {
    "iso:country":"US",
    "sg:address":"3 Executive Ct",
    "sg:city":"Cherry Hill",
    "sg:classifiers":[
        {
            "category":"Utilities",
            "subcategory":"Telephone",
            "type":"Services"
        }
    ],
    "sg:phone":"+1 856 667 0623",
    "sg:postcode":"08046",
    "sg:province":"NJ",
    "sg:tags":[
        "telecommunication"
    ],
    "wof:name":"Zone Telecom",
    "wof:placetype":"venue"
},
  "geometry": {"coordinates":[-74.864518,40.018444],"type":"Point"}
}