{
  "type": "Feature",
  "properties": {
    "addr:full":"73 Nautilus Dr Barnegat NJ 08005",
    "addr:housenumber":"73",
    "addr:postcode":"08005",
    "addr:street":"Nautilus Dr",
    "iso:country":"US",
    "sg:address":"73 Nautilus Dr",
    "sg:city":"Barnegat",
    "sg:classifiers":[
        {
            "category":"Health Services",
            "subcategory":"Doctor",
            "type":"Services"
        }
    ],
    "sg:phone":"+1   ",
    "sg:postcode":"08005",
    "sg:province":"NJ",
    "sg:tags":[
        "medical"
    ],
    "wof:name":"Regional Ear Nose Throat Assoc",
    "wof:placetype":"venue"
},
  "geometry": {"coordinates":[-74.267132,39.754959],"type":"Point"}
}