{
  "type": "Feature",
  "properties": {
    "iso:country":"US",
    "sg:address":"43 Terrace St",
    "sg:city":"Haworth",
    "sg:classifiers":[
        {
            "category":"Professional",
            "subcategory":"Computer Services",
            "type":"Services"
        }
    ],
    "sg:phone":"+1   ",
    "sg:postcode":"07641",
    "sg:province":"NJ",
    "sg:tags":[
        "consulting",
        "related"
    ],
    "wof:name":"Computer Rx",
    "wof:placetype":"venue"
},
  "geometry": {"coordinates":[-73.990527,40.956202],"type":"Point"}
}