{
  "type": "Feature",
  "properties": {
    "iso:country":"US",
    "sg:address":"97 Hollywood Ave",
    "sg:city":"Clifton",
    "sg:classifiers":[
        {
            "category":"Building & Trades",
            "subcategory":"Construction",
            "type":"Services"
        }
    ],
    "sg:phone":"+1 973 574 0047",
    "sg:postcode":"07014",
    "sg:province":"NJ",
    "sg:tags":[
        "house"
    ],
    "wof:name":"Sal Lupinacci Construction",
    "wof:placetype":"venue"
},
  "geometry": {"coordinates":[-74.147885,40.832879],"type":"Point"}
}