{
  "type": "Feature",
  "properties": {
    "iso:country":"US",
    "sg:address":"662 Penn St",
    "sg:city":"Perth Amboy",
    "sg:classifiers":[
        {
            "category":"Retail",
            "subcategory":"Auto Repair",
            "type":"Services"
        }
    ],
    "sg:phone":"+1 732 442 3065",
    "sg:postcode":"08861",
    "sg:province":"NJ",
    "sg:tags":[
        "muffler",
        "exhaust",
        "gas",
        "system"
    ],
    "wof:name":"Ted's Service Station",
    "wof:placetype":"venue"
},
  "geometry": {"coordinates":[-74.26979799999999,40.5214],"type":"Point"}
}