{
  "type": "Feature",
  "properties": {
    "addr:full":"221 Middle Rd Hazlet NJ 07730",
    "addr:housenumber":"221",
    "addr:postcode":"07730",
    "addr:street":"Middle Rd",
    "iso:country":"US",
    "sg:address":"221 Middle Rd",
    "sg:city":"Hazlet",
    "sg:classifiers":[
        {
            "category":"Real Estate",
            "subcategory":"Real Estate Services",
            "type":"Services"
        },
        {
            "category":"Banks & Credit Unions",
            "subcategory":"Bank",
            "type":"Services"
        },
        {
            "category":"Banks & Credit Unions",
            "subcategory":"Financial Services",
            "type":"Services"
        }
    ],
    "sg:phone":"+1 732 264 5500",
    "sg:postcode":"07730",
    "sg:province":"NJ",
    "sg:tags":[
        "commercial",
        "loan",
        "processing",
        "saving"
    ],
    "wof:name":"Superior Mortgage",
    "wof:placetype":"venue"
},
  "geometry": {"coordinates":[-74.178909,40.427523],"type":"Point"}
}