{
  "type": "Feature",
  "properties": {
    "iso:country":"US",
    "sg:address":"397 Centre St",
    "sg:city":"Nutley",
    "sg:classifiers":[
        {
            "category":"Shopping",
            "subcategory":"Gifts & Souvenirs",
            "type":"Retail Goods"
        }
    ],
    "sg:phone":"+1 973 667 9088",
    "sg:postcode":"07110",
    "sg:province":"NJ",
    "sg:tags":[
        "balloon",
        "artist"
    ],
    "wof:name":"Carolyn's Gift Shoppe",
    "wof:placetype":"venue"
},
  "geometry": {"coordinates":[-74.16327200000001,40.81526],"type":"Point"}
}