{
  "type": "Feature",
  "properties": {
    "addr:full":"244 Lakeview Ave Clifton NJ 07011",
    "addr:housenumber":"244",
    "addr:postcode":"07011",
    "addr:street":"Lakeview Ave",
    "iso:country":"US",
    "sg:address":"244 Lakeview Ave",
    "sg:city":"Clifton",
    "sg:classifiers":[
        {
            "category":"Shopping",
            "subcategory":"Clothing, Apparel, & Fashions",
            "type":"Retail Goods"
        }
    ],
    "sg:phone":"+1 973 478 4178",
    "sg:postcode":"07011",
    "sg:province":"NJ",
    "sg:tags":[
        "children's",
        "clothing"
    ],
    "wof:name":"Black Flag",
    "wof:placetype":"venue"
},
  "geometry": {"coordinates":[-74.137916,40.883362],"type":"Point"}
}