{
  "type": "Feature",
  "properties": {
    "iso:country":"US",
    "sg:address":"14 Commerce St E",
    "sg:city":"Bridgeton",
    "sg:classifiers":[
        {
            "category":"Shopping",
            "subcategory":"Gifts & Souvenirs",
            "type":"Retail Goods"
        }
    ],
    "sg:phone":"+1   ",
    "sg:postcode":"08302",
    "sg:province":"NJ",
    "wof:name":"Maureens Gifts & Antiques",
    "wof:placetype":"venue"
},
  "geometry": {"coordinates":[-75.235051,39.428995],"type":"Point"}
}