{
  "type": "Feature",
  "properties": {
    "iso:country":"US",
    "sg:address":"302 E Monterey Ave",
    "sg:city":"Wildwood",
    "sg:classifiers":[
        {
            "category":"Professional",
            "subcategory":"Business Services",
            "type":"Services"
        }
    ],
    "sg:phone":"+1   ",
    "sg:postcode":"08260",
    "sg:province":"NJ",
    "wof:name":"Buckscape Partners",
    "wof:placetype":"venue"
},
  "geometry": {"coordinates":[-74.84126500000001,38.965399],"type":"Point"}
}