{
  "type": "Feature",
  "properties": {
    "addr:full":"165 E 9th Ave Runnemede NJ 08078",
    "addr:housenumber":"165",
    "addr:postcode":"08078",
    "addr:street":"E 9Th Ave",
    "iso:country":"US",
    "sg:address":"165 E 9th Ave",
    "sg:city":"Runnemede",
    "sg:classifiers":[
        {
            "category":"Health Services",
            "subcategory":"Doctor",
            "type":"Services"
        }
    ],
    "sg:phone":"+1 856 312 0046",
    "sg:postcode":"08078",
    "sg:province":"NJ",
    "wof:name":"Stryker Orthopaedics",
    "wof:placetype":"venue"
},
  "geometry": {"coordinates":[-75.068714,39.85831],"type":"Point"}
}