{
  "type": "Feature",
  "properties": {
    "iso:country":"US",
    "sg:address":"286 N Center St",
    "sg:city":"Orange",
    "sg:classifiers":[
        {
            "category":"Professional",
            "subcategory":"Business Services",
            "type":"Services"
        }
    ],
    "sg:phone":"+1   ",
    "sg:postcode":"07050",
    "sg:province":"NJ",
    "wof:name":"Red Tag Express",
    "wof:placetype":"venue"
},
  "geometry": {"coordinates":[-74.224661,40.776633],"type":"Point"}
}