{
  "type": "Feature",
  "properties": {
    "addr:full":"228 Park Ave Hoboken NJ 07030",
    "addr:housenumber":"228",
    "addr:postcode":"07030",
    "addr:street":"Park Ave",
    "iso:country":"US",
    "sg:address":"228 Park Ave",
    "sg:city":"Hoboken",
    "sg:classifiers":[
        {
            "category":"Health Services",
            "subcategory":"Doctor",
            "type":"Services"
        }
    ],
    "sg:phone":"+1 201 996 2765",
    "sg:postcode":"07030",
    "sg:province":"NJ",
    "sg:tags":[
        "physician",
        "surgeon"
    ],
    "wof:name":"R & R Perinatal Assoc Inc",
    "wof:placetype":"venue"
},
  "geometry": {"coordinates":[-74.032973,40.7401],"type":"Point"}
}