{
  "type": "Feature",
  "properties": {
    "iso:country":"US",
    "sg:address":"60 Passaic St",
    "sg:city":"Garfield",
    "sg:classifiers":[
        {
            "category":"Professional",
            "subcategory":"Lawyer & Legal Services",
            "type":"Services"
        }
    ],
    "sg:phone":"+1 973 779 7073",
    "sg:postcode":"07026",
    "sg:province":"NJ",
    "wof:name":"Messineo A J Jr Lawyer",
    "wof:placetype":"venue"
},
  "geometry": {"coordinates":[-74.10733399999999,40.865703],"type":"Point"}
}