{
  "type": "Feature",
  "properties": {
    "addr:full":"1007 Livingston Ave North Brunswick NJ 08902",
    "addr:housenumber":"1007",
    "addr:postcode":"08902",
    "addr:street":"Livingston Ave",
    "iso:country":"US",
    "sg:address":"1007 Livingston Ave",
    "sg:city":"North Brunswick",
    "sg:classifiers":[
        {
            "category":"Home & Garden",
            "subcategory":"Furniture",
            "type":"Retail Goods"
        }
    ],
    "sg:phone":"+1   ",
    "sg:postcode":"08902",
    "sg:province":"NJ",
    "sg:tags":[
        "mattress"
    ],
    "wof:name":"Jacks Famous Furniture",
    "wof:placetype":"venue"
},
  "geometry": {"coordinates":[-74.471013,40.468537],"type":"Point"}
}