{
  "type": "Feature",
  "properties": {
    "iso:country":"US",
    "sg:address":"121 Hook Mountain Rd",
    "sg:city":"Montville",
    "sg:classifiers":[
        {
            "category":"Professional",
            "subcategory":"Computer Services",
            "type":"Services"
        }
    ],
    "sg:phone":"+1 973 575 9110",
    "sg:postcode":"07045",
    "sg:province":"NJ",
    "sg:tags":[
        "related"
    ],
    "sg:website":"www.mwc-enterprises.com",
    "wof:name":"M W C Enterprises",
    "wof:placetype":"venue"
},
  "geometry": {"coordinates":[-74.340908,40.879936],"type":"Point"}
}