{
  "type": "Feature",
  "properties": {
    "iso:country":"US",
    "sg:address":"589 Herbertsville Rd",
    "sg:city":"Brick",
    "sg:classifiers":[
        {
            "category":"Building & Trades",
            "subcategory":"Construction",
            "type":"Services"
        }
    ],
    "sg:phone":"+1 732 840 1315",
    "sg:postcode":"08724",
    "sg:province":"NJ",
    "sg:tags":[
        "painting"
    ],
    "wof:name":"Customize Painting & Rm Design",
    "wof:placetype":"venue"
},
  "geometry": {"coordinates":[-74.107218,40.109807],"type":"Point"}
}