{
  "type": "Feature",
  "properties": {
    "iso:country":"US",
    "sg:address":"1749 Hooper Ave",
    "sg:city":"Toms River",
    "sg:classifiers":[
        {
            "category":"Shopping",
            "type":"Retail Goods"
        }
    ],
    "sg:phone":"+1 732 255 6200",
    "sg:postcode":"08753",
    "sg:province":"NJ",
    "sg:tags":[
        "hearing",
        "equipment",
        "supply",
        "impaired"
    ],
    "wof:name":"Bright Hearing Ctr",
    "wof:placetype":"venue"
},
  "geometry": {"coordinates":[-74.154433,40.003533],"type":"Point"}
}