{
  "type": "Feature",
  "properties": {
    "iso:country":"US",
    "sg:address":"810 Main St",
    "sg:city":"Hackensack",
    "sg:classifiers":[
        {
            "category":"Health Services",
            "subcategory":"Doctor",
            "type":"Services"
        }
    ],
    "sg:phone":"+1 201 488 0095",
    "sg:postcode":"07601",
    "sg:province":"NJ",
    "wof:name":"Ramos Rafael MD",
    "wof:placetype":"venue"
},
  "geometry": {"coordinates":[-74.042129,40.904644],"type":"Point"}
}