{
  "type": "Feature",
  "properties": {
    "iso:country":"US",
    "sg:address":"340 Longwood Dr",
    "sg:city":"Haddonfield",
    "sg:classifiers":[
        {
            "category":"Professional",
            "type":"Services"
        }
    ],
    "sg:phone":"+1   ",
    "sg:postcode":"08033",
    "sg:province":"NJ",
    "wof:name":"Rl Bloch Son",
    "wof:placetype":"venue"
},
  "geometry": {"coordinates":[-75.039647,39.913181],"type":"Point"}
}