{
  "type": "Feature",
  "properties": {
    "iso:country":"US",
    "sg:address":"59 Beaverbrook Rd Ste 101",
    "sg:city":"Lincoln Park",
    "sg:classifiers":[
        {
            "category":"Social Services",
            "subcategory":"Child Care",
            "type":"Services"
        }
    ],
    "sg:phone":"+1 973 628 8268",
    "sg:postcode":"07035",
    "sg:province":"NJ",
    "sg:tags":[
        "day"
    ],
    "wof:name":"Montville Country Day",
    "wof:placetype":"venue"
},
  "geometry": {"coordinates":[-74.309601,40.924599],"type":"Point"}
}