{
  "type": "Feature",
  "properties": {
    "addr:full":"15 Main St Butler NJ 07405",
    "addr:housenumber":"15",
    "addr:postcode":"07405",
    "addr:street":"Main St",
    "iso:country":"US",
    "sg:address":"15 Main St",
    "sg:city":"Butler",
    "sg:classifiers":[
        {
            "category":"Manufacturing",
            "subcategory":"Printing",
            "type":"Manufacturing & Wholesale Goods"
        },
        {
            "category":"Banks & Credit Unions",
            "subcategory":"Bank",
            "type":"Services"
        }
    ],
    "sg:phone":"+1 973 838 1740",
    "sg:postcode":"07405",
    "sg:province":"NJ",
    "sg:tags":[
        "money",
        "order",
        "publishing"
    ],
    "wof:name":"Service Xpress",
    "wof:placetype":"venue"
},
  "geometry": {"coordinates":[-74.335528,41.00344],"type":"Point"}
}