{
  "type": "Feature",
  "properties": {
    "addr:full":"1235 Central Ave Hillside NJ 07205",
    "addr:housenumber":"1235",
    "addr:postcode":"07205",
    "addr:street":"Central Ave",
    "iso:country":"US",
    "sg:address":"1235 Central Ave",
    "sg:city":"Hillside",
    "sg:classifiers":[
        {
            "category":"Wholesale",
            "subcategory":"Durable Goods & Equipment",
            "type":"Manufacturing & Wholesale Goods"
        }
    ],
    "sg:phone":"+1 908 355 2039",
    "sg:postcode":"07205",
    "sg:province":"NJ",
    "sg:tags":[
        "exporter"
    ],
    "sg:website":"www.lancasales.com",
    "wof:name":"Lanca Sales Inc",
    "wof:placetype":"venue"
},
  "geometry": {"coordinates":[-74.227019,40.692717],"type":"Point"}
}