{
  "type": "Feature",
  "properties": {
    "addr:full":"1167 State Rte 23 Kinnelon NJ 07405",
    "addr:housenumber":"1167",
    "addr:postcode":"07405",
    "addr:street":"State Rte 23",
    "iso:country":"US",
    "sg:address":"1167 State Rte 23",
    "sg:city":"Kinnelon",
    "sg:classifiers":[
        {
            "category":"Retail",
            "subcategory":"Auto Repair",
            "type":"Services"
        }
    ],
    "sg:phone":"+1 973 492 8308",
    "sg:postcode":"07405",
    "sg:province":"NJ",
    "sg:tags":[
        "automobile",
        "lubrication"
    ],
    "sg:website":"www.lubexpress.com",
    "wof:name":"Lubeexpress Co Inc",
    "wof:placetype":"venue"
},
  "geometry": {"coordinates":[-74.337912,40.990375],"type":"Point"}
}