{
  "type": "Feature",
  "properties": {
    "iso:country":"US",
    "sg:address":"1251 Landis Ave",
    "sg:city":"Elmer",
    "sg:classifiers":[
        {
            "category":"Autos & Motor Vehicles",
            "subcategory":"Fuel & Gas Station",
            "type":"Retail Goods"
        }
    ],
    "sg:phone":"+1 856 691 9448",
    "sg:postcode":"08318",
    "sg:province":"NJ",
    "sg:tags":[
        "oil"
    ],
    "wof:name":"BP",
    "wof:placetype":"venue"
},
  "geometry": {"coordinates":[-75.09161,39.489088],"type":"Point"}
}