{
  "type": "Feature",
  "properties": {
    "addr:full":"7 Birch Ln Hackettstown NJ 07840",
    "addr:housenumber":"7",
    "addr:postcode":"07840",
    "addr:street":"Birch Ln",
    "iso:country":"US",
    "sg:address":"7 Birch Ln",
    "sg:city":"Hackettstown",
    "sg:classifiers":[
        {
            "category":"Building & Trades",
            "subcategory":"Construction",
            "type":"Services"
        }
    ],
    "sg:phone":"+1 908 852 2082",
    "sg:postcode":"07840",
    "sg:province":"NJ",
    "sg:tags":[
        "house"
    ],
    "wof:name":"Glenn Cougle Construction",
    "wof:placetype":"venue"
},
  "geometry": {"coordinates":[-74.84507000000001,40.872604],"type":"Point"}
}