{
  "type": "Feature",
  "properties": {
    "addr:full":"13 N Laurel St Bridgeton NJ 08302",
    "addr:housenumber":"13",
    "addr:postcode":"08302",
    "addr:street":"N Laurel St",
    "iso:country":"US",
    "sg:address":"13 N Laurel St",
    "sg:city":"Bridgeton",
    "sg:classifiers":[
        {
            "category":"Restaurant",
            "type":"Food & Drink"
        }
    ],
    "sg:phone":"+1   ",
    "sg:postcode":"08302",
    "sg:province":"NJ",
    "sg:tags":[
        "eating"
    ],
    "wof:name":"Great Wall",
    "wof:placetype":"venue"
},
  "geometry": {"coordinates":[-75.233863,39.429572],"type":"Point"}
}