{
  "type": "Feature",
  "properties": {
    "addr:full":"1013 US Hwy 46 Ledgewood NJ 07852",
    "addr:housenumber":"1013",
    "addr:postcode":"07852",
    "addr:street":"Us Hwy 46",
    "iso:country":"US",
    "sg:address":"1013 US Hwy 46",
    "sg:city":"Ledgewood",
    "sg:classifiers":[
        {
            "category":"Farming",
            "subcategory":"Farm",
            "type":"Manufacturing & Wholesale Goods"
        },
        {
            "category":"Food & Beverages",
            "subcategory":"Fruits & Vegetables",
            "type":"Retail Goods"
        }
    ],
    "sg:phone":"+1 973 598 8400",
    "sg:postcode":"07852",
    "sg:province":"NJ",
    "sg:tags":[
        "produce",
        "crop",
        "general"
    ],
    "wof:name":"Ledgewood Farm",
    "wof:placetype":"venue"
},
  "geometry": {"coordinates":[-74.649327,40.879037],"type":"Point"}
}