{
  "type": "Feature",
  "properties": {
    "iso:country":"US",
    "sg:address":"50 Sommers Ave",
    "sg:city":"Somers Point",
    "sg:classifiers":[
        {
            "category":"Retail",
            "subcategory":"Repair Shop",
            "type":"Services"
        }
    ],
    "sg:phone":"+1 609 653 6133",
    "sg:postcode":"08244",
    "sg:province":"NJ",
    "sg:tags":[
        "repairing",
        "piano",
        "refinishing"
    ],
    "wof:name":"Jack Louis Piano Tuning & Repr",
    "wof:placetype":"venue"
},
  "geometry": {"coordinates":[-74.59636500000001,39.310279],"type":"Point"}
}