{
  "type": "Feature",
  "properties": {
    "iso:country":"US",
    "sg:address":"62 Tolkien Psge",
    "sg:city":"Medford",
    "sg:classifiers":[
        {
            "category":"Shopping",
            "type":"Retail Goods"
        }
    ],
    "sg:phone":"+1   ",
    "sg:postcode":"08055",
    "sg:province":"NJ",
    "sg:tags":[
        "merchandise"
    ],
    "wof:name":"Kristen Fine Art",
    "wof:placetype":"venue"
},
  "geometry": {"coordinates":[-74.806528,39.911365],"type":"Point"}
}