{
  "type": "Feature",
  "properties": {
    "addr:full":"33 Arden Ln Essex Fells NJ 07021",
    "addr:housenumber":"33",
    "addr:postcode":"07021",
    "addr:street":"Arden Ln",
    "iso:country":"US",
    "sg:address":"33 Arden Ln",
    "sg:city":"Essex Fells",
    "sg:classifiers":[
        {
            "category":"Professional",
            "subcategory":"Business Services",
            "type":"Services"
        }
    ],
    "sg:phone":"+1   ",
    "sg:postcode":"07021",
    "sg:province":"NJ",
    "wof:name":"Grak Enterprises LLC",
    "wof:placetype":"venue"
},
  "geometry": {"coordinates":[-74.286967,40.82387],"type":"Point"}
}