{
  "type": "Feature",
  "properties": {
    "iso:country":"US",
    "sg:address":"21 Mine Brook Rd",
    "sg:city":"Bernardsville",
    "sg:classifiers":[
        {
            "category":"Professional",
            "subcategory":"Business Services",
            "type":"Services"
        },
        {
            "category":"Professional",
            "subcategory":"Printing & Photocopies",
            "type":"Services"
        }
    ],
    "sg:phone":"+1 908 766 4073",
    "sg:postcode":"07924",
    "sg:province":"NJ",
    "sg:tags":[
        "mail",
        "duplicating",
        "shipping",
        "copying"
    ],
    "sg:website":"http://www.bvillepc.com",
    "wof:name":"Bernardsville;Print Center",
    "wof:placetype":"venue"
},
  "geometry": {"coordinates":[-74.570007,40.717888],"type":"Point"}
}