{
  "type": "Feature",
  "properties": {
    "iso:country":"US",
    "sg:address":"1402 US Hwy 9",
    "sg:city":"Cape May Court House",
    "sg:classifiers":[
        {
            "category":"Travel",
            "subcategory":"Campground",
            "type":"Entertainment"
        }
    ],
    "sg:phone":"+1   ",
    "sg:postcode":"08210",
    "sg:province":"NJ",
    "sg:tags":[
        "mobile",
        "home",
        "park",
        "trailer"
    ],
    "wof:name":"Pine Acers Manner",
    "wof:placetype":"venue"
},
  "geometry": {"coordinates":[-74.851432,39.045749],"type":"Point"}
}