{
  "type": "Feature",
  "properties": {
    "iso:country":"US",
    "sg:address":"1601 Stokes Rd",
    "sg:city":"Mount Laurel",
    "sg:classifiers":[
        {
            "category":"Shopping",
            "subcategory":"Gifts & Souvenirs",
            "type":"Retail Goods"
        }
    ],
    "sg:phone":"+1   ",
    "sg:postcode":"08054",
    "sg:province":"NJ",
    "wof:name":"Deeanns Treasures",
    "wof:placetype":"venue"
},
  "geometry": {"coordinates":[-74.92789,39.943946],"type":"Point"}
}