{
  "type": "Feature",
  "properties": {
    "addr:full":"94 Mount Bethel Rd Warren NJ 07059",
    "addr:housenumber":"94",
    "addr:postcode":"07059",
    "addr:street":"Mount Bethel Rd",
    "iso:country":"US",
    "sg:address":"94 Mount Bethel Rd",
    "sg:city":"Warren",
    "sg:classifiers":[
        {
            "category":"Organizations",
            "subcategory":"Non-profit Organization",
            "type":"Services"
        }
    ],
    "sg:phone":"+1 908 222 0315",
    "sg:postcode":"07059",
    "sg:province":"NJ",
    "wof:name":"Passaic River Coalition",
    "wof:placetype":"venue"
},
  "geometry": {"coordinates":[-74.497749,40.624672],"type":"Point"}
}