{
  "type": "Feature",
  "properties": {
    "addr:full":"400 Clarkson Ave Elizabeth NJ 07202",
    "addr:housenumber":"400",
    "addr:postcode":"07202",
    "addr:street":"Clarkson Ave",
    "iso:country":"US",
    "sg:address":"400 Clarkson Ave",
    "sg:city":"Elizabeth",
    "sg:classifiers":[
        {
            "category":"Retail",
            "subcategory":"Laundry & Dry Cleaning",
            "type":"Services"
        }
    ],
    "sg:phone":"+1 908 355 9390",
    "sg:postcode":"07202",
    "sg:province":"NJ",
    "sg:tags":[
        "cleaners",
        "rug",
        "carpet"
    ],
    "wof:name":"Authority Cleaning",
    "wof:placetype":"venue"
},
  "geometry": {"coordinates":[-74.21076600000001,40.654146],"type":"Point"}
}