{
  "type": "Feature",
  "properties": {
    "iso:country":"US",
    "sg:address":"136 Columbia Tpke",
    "sg:city":"Florham Park",
    "sg:classifiers":[
        {
            "category":"Local Transit",
            "type":"Transportation"
        }
    ],
    "sg:phone":"+1 973 236 9666",
    "sg:postcode":"07932",
    "sg:province":"NJ",
    "sg:tags":[
        "limousine",
        "limo"
    ],
    "wof:name":"Hanover Car & Limousine Service",
    "wof:placetype":"venue"
},
  "geometry": {"coordinates":[-74.386521,40.786562],"type":"Point"}
}