{
  "type": "Feature",
  "properties": {
    "addr:full":"55 River Rd Fair Lawn NJ 07410",
    "addr:housenumber":"55",
    "addr:postcode":"07410",
    "addr:street":"River Rd",
    "iso:country":"US",
    "sg:address":"55 River Rd",
    "sg:city":"Fair Lawn",
    "sg:classifiers":[
        {
            "category":"Real Estate",
            "subcategory":"Real Estate Agent",
            "type":"Services"
        }
    ],
    "sg:phone":"+1 201 796 0500",
    "sg:postcode":"07410",
    "sg:province":"NJ",
    "wof:name":"F Fisher & Co Lcc Real Estate",
    "wof:placetype":"venue"
},
  "geometry": {"coordinates":[-74.13649599999999,40.937684],"type":"Point"}
}