{
  "type": "Feature",
  "properties": {
    "iso:country":"US",
    "sg:address":"338 Spring Hill Rd",
    "sg:city":"Skillman",
    "sg:classifiers":[
        {
            "category":"Professional",
            "subcategory":"Management & Consulting",
            "type":"Services"
        }
    ],
    "sg:phone":"+1   ",
    "sg:postcode":"08558",
    "sg:province":"NJ",
    "wof:name":"Wm Darienzo Assoc",
    "wof:placetype":"venue"
},
  "geometry": {"coordinates":[-74.739773,40.419976],"type":"Point"}
}