{
  "type": "Feature",
  "properties": {
    "addr:full":"559 State Rte 53 Denville NJ 07834",
    "addr:housenumber":"559",
    "addr:postcode":"07834",
    "addr:street":"State Rte 53",
    "iso:country":"US",
    "sg:address":"559 State Rte 53",
    "sg:city":"Denville",
    "sg:classifiers":[
        {
            "category":"Shopping",
            "subcategory":"Florist",
            "type":"Retail Goods"
        }
    ],
    "sg:phone":"+1 973 625 0010",
    "sg:postcode":"07834",
    "sg:province":"NJ",
    "wof:name":"Flowers By Candle-Lite",
    "wof:placetype":"venue"
},
  "geometry": {"coordinates":[-74.48132,40.873964],"type":"Point"}
}