{
  "type": "Feature",
  "properties": {
    "iso:country":"US",
    "sg:address":"210 Palm Ave",
    "sg:city":"Browns Mills",
    "sg:classifiers":[
        {
            "category":"Building & Trades",
            "subcategory":"Construction",
            "type":"Services"
        }
    ],
    "sg:phone":"+1 609 893 1151",
    "sg:postcode":"08015",
    "sg:province":"NJ",
    "sg:tags":[
        "house",
        "carpentry",
        "contractor"
    ],
    "wof:name":"Steele Craft Builders",
    "wof:placetype":"venue"
},
  "geometry": {"coordinates":[-74.56662,39.968903],"type":"Point"}
}