{
  "type": "Feature",
  "properties": {
    "addr:full":"10 Woodbridge Ctr Dr # 140 Woodbridge NJ 07095",
    "addr:housenumber":"10",
    "addr:postcode":"07095",
    "addr:street":"Woodbridge Ctr Dr # 140",
    "iso:country":"US",
    "sg:address":"10 Woodbridge Ctr Dr # 140",
    "sg:city":"Woodbridge",
    "sg:classifiers":[
        {
            "category":"Professional",
            "subcategory":"Employment Agencies",
            "type":"Services"
        }
    ],
    "sg:phone":"+1 732 855 8664",
    "sg:postcode":"07095",
    "sg:province":"NJ",
    "sg:tags":[
        "opportunity",
        "contractor"
    ],
    "wof:name":"Volt Services Group",
    "wof:placetype":"venue"
},
  "geometry": {"coordinates":[-74.298058,40.547656],"type":"Point"}
}