{
  "type": "Feature",
  "properties": {
    "addr:full":"234 Main St Chatham NJ 07928",
    "addr:housenumber":"234",
    "addr:postcode":"07928",
    "addr:street":"Main St",
    "iso:country":"US",
    "sg:address":"234 Main St",
    "sg:city":"Chatham",
    "sg:classifiers":[
        {
            "category":"Restaurant",
            "type":"Food & Drink"
        }
    ],
    "sg:phone":"+1 973 701 8390",
    "sg:postcode":"07928",
    "sg:province":"NJ",
    "sg:tags":[
        "chinese"
    ],
    "sg:website":"www.gardenrice.com",
    "wof:name":"Garden Rice Chinese Restaurant",
    "wof:placetype":"venue"
},
  "geometry": {"coordinates":[-74.3815,40.740601],"type":"Point"}
}