{
  "type": "Feature",
  "properties": {
    "iso:country":"US",
    "sg:address":"600 Meadowlands Pkwy",
    "sg:city":"Secaucus",
    "sg:classifiers":[
        {
            "category":"Freight",
            "type":"Transportation"
        }
    ],
    "sg:phone":"+1 201 422 0782",
    "sg:postcode":"07094",
    "sg:province":"NJ",
    "sg:tags":[
        "sea",
        "foreign"
    ],
    "wof:name":"STC Agency",
    "wof:placetype":"venue"
},
  "geometry": {"coordinates":[-74.081641,40.779007],"type":"Point"}
}