{
  "type": "Feature",
  "properties": {
    "addr:full":"66 Scott Dr Bayville NJ 08721",
    "addr:housenumber":"66",
    "addr:postcode":"08721",
    "addr:street":"Scott Dr",
    "iso:country":"US",
    "sg:address":"66 Scott Dr",
    "sg:city":"Bayville",
    "sg:classifiers":[
        {
            "category":"Building & Trades",
            "subcategory":"Construction",
            "type":"Services"
        }
    ],
    "sg:phone":"+1 732 269 1818",
    "sg:postcode":"08721",
    "sg:province":"NJ",
    "sg:tags":[
        "general",
        "contractor"
    ],
    "wof:name":"EJB Construction",
    "wof:placetype":"venue"
},
  "geometry": {"coordinates":[-74.16112699999999,39.924726],"type":"Point"}
}