{
  "type": "Feature",
  "properties": {
    "addr:full":"45 Westfield Ave Elizabeth NJ 07208",
    "addr:housenumber":"45",
    "addr:postcode":"07208",
    "addr:street":"Westfield Ave",
    "iso:country":"US",
    "sg:address":"45 Westfield Ave",
    "sg:city":"Elizabeth",
    "sg:classifiers":[
        {
            "category":"Shopping",
            "subcategory":"Music",
            "type":"Retail Goods"
        }
    ],
    "sg:phone":"+1 908 994 0880",
    "sg:postcode":"07208",
    "sg:province":"NJ",
    "sg:tags":[
        "compact",
        "record",
        "disc",
        "tape"
    ],
    "wof:name":"LA Roosevelt Records",
    "wof:placetype":"venue"
},
  "geometry": {"coordinates":[-74.219363,40.668131],"type":"Point"}
}