{
  "type": "Feature",
  "properties": {
    "addr:full":"920 Middlesex St Gloucester City NJ 08030",
    "addr:housenumber":"920",
    "addr:postcode":"08030",
    "addr:street":"Middlesex St",
    "iso:country":"US",
    "sg:address":"920 Middlesex St",
    "sg:city":"Gloucester City",
    "sg:classifiers":[
        {
            "category":"Wholesale",
            "subcategory":"Sporting Goods",
            "type":"Manufacturing & Wholesale Goods"
        }
    ],
    "sg:phone":"+1 856 456 3756",
    "sg:postcode":"08030",
    "sg:province":"NJ",
    "wof:name":"Dockside Canvas",
    "wof:placetype":"venue"
},
  "geometry": {"coordinates":[-75.115122,39.898427],"type":"Point"}
}