{
  "type": "Feature",
  "properties": {
    "iso:country":"US",
    "sg:address":"154 Market St",
    "sg:city":"Paterson",
    "sg:classifiers":[
        {
            "category":"Shopping",
            "subcategory":"Jewelry",
            "type":"Retail Goods"
        }
    ],
    "sg:phone":"+1 973 278 0768",
    "sg:postcode":"07505",
    "sg:province":"NJ",
    "sg:tags":[
        "silverware"
    ],
    "wof:name":"Shim's Jewelry",
    "wof:placetype":"venue"
},
  "geometry": {"coordinates":[-74.17053799999999,40.916312],"type":"Point"}
}