{
  "type": "Feature",
  "properties": {
    "addr:full":"545 Houses Corner Rd Sparta NJ 07871",
    "addr:housenumber":"545",
    "addr:postcode":"07871",
    "addr:street":"Houses Corner Rd",
    "iso:country":"US",
    "sg:address":"545 Houses Corner Rd",
    "sg:city":"Sparta",
    "sg:classifiers":[
        {
            "category":"Manufacturing",
            "subcategory":"Textiles",
            "type":"Manufacturing & Wholesale Goods"
        }
    ],
    "sg:phone":"+1 973 300 4027",
    "sg:postcode":"07871",
    "sg:province":"NJ",
    "sg:tags":[
        "mill",
        "fabric"
    ],
    "wof:name":"Mad River Quilt Co Inc",
    "wof:placetype":"venue"
},
  "geometry": {"coordinates":[-74.63829,41.080286],"type":"Point"}
}