{
  "type": "Feature",
  "properties": {
    "iso:country":"US",
    "sg:address":"246 Raymond Blvd",
    "sg:city":"Newark",
    "sg:classifiers":[
        {
            "category":"Retail",
            "subcategory":"Auto Repair",
            "type":"Services"
        }
    ],
    "sg:phone":"+1   ",
    "sg:postcode":"07105",
    "sg:province":"NJ",
    "sg:tags":[
        "automotive",
        "computer",
        "programing",
        "custom"
    ],
    "wof:name":"Suspension Systems Inc",
    "wof:placetype":"venue"
},
  "geometry": {"coordinates":[-74.13138499999999,40.734203],"type":"Point"}
}