{
  "type": "Feature",
  "properties": {
    "iso:country":"US",
    "sg:address":"571 Central Ave",
    "sg:city":"New Providence",
    "sg:classifiers":[
        {
            "category":"Professional",
            "subcategory":"Research",
            "type":"Services"
        }
    ],
    "sg:phone":"+1   ",
    "sg:postcode":"07974",
    "sg:province":"NJ",
    "sg:tags":[
        "development"
    ],
    "wof:name":"Mitsubishi Electric & Elec USA",
    "wof:placetype":"venue"
},
  "geometry": {"coordinates":[-74.40501500000001,40.69805],"type":"Point"}
}