{
  "type": "Feature",
  "properties": {
    "addr:full":"325 Willow Way Clark NJ 07066",
    "addr:housenumber":"325",
    "addr:postcode":"07066",
    "addr:street":"Willow Way",
    "iso:country":"US",
    "sg:address":"325 Willow Way",
    "sg:city":"Clark",
    "sg:classifiers":[
        {
            "category":"Freight",
            "type":"Transportation"
        }
    ],
    "sg:phone":"+1 732 382 4553",
    "sg:postcode":"07066",
    "sg:province":"NJ",
    "sg:tags":[
        "operator",
        "local",
        "trucking"
    ],
    "wof:name":"Brunos Trucking Inc",
    "wof:placetype":"venue"
},
  "geometry": {"coordinates":[-74.335409,40.606348],"type":"Point"}
}