{
  "type": "Feature",
  "properties": {
    "addr:full":"635 Saint Georges Ave Roselle NJ 07203",
    "addr:housenumber":"635",
    "addr:postcode":"07203",
    "addr:street":"Saint Georges Ave",
    "iso:country":"US",
    "sg:address":"635 Saint Georges Ave",
    "sg:city":"Roselle",
    "sg:classifiers":[
        {
            "category":"Personal",
            "subcategory":"Beauty Salon",
            "type":"Services"
        }
    ],
    "sg:phone":"+1 908 241 6800",
    "sg:postcode":"07203",
    "sg:province":"NJ",
    "wof:name":"Hollywood II Unisex Salon",
    "wof:placetype":"venue"
},
  "geometry": {"coordinates":[-74.25846,40.643466],"type":"Point"}
}