{
  "type": "Feature",
  "properties": {
    "iso:country":"US",
    "sg:address":"140 Washington Ave",
    "sg:city":"Milltown",
    "sg:classifiers":[
        {
            "category":"Building & Trades",
            "subcategory":"Construction",
            "type":"Services"
        }
    ],
    "sg:phone":"+1 732 937 5771",
    "sg:postcode":"08850",
    "sg:province":"NJ",
    "wof:name":"Choice Construction Inc",
    "wof:placetype":"venue"
},
  "geometry": {"coordinates":[-74.43314100000001,40.453496],"type":"Point"}
}