{
  "type": "Feature",
  "properties": {
    "addr:full":"6407 Bergenline Pl West New York NJ 07093",
    "addr:housenumber":"6407",
    "addr:postcode":"07093",
    "addr:street":"Bergenline Pl West",
    "iso:country":"US",
    "sg:address":"6407 Bergenline Pl",
    "sg:city":"West New York",
    "sg:classifiers":[
        {
            "category":"Restaurant",
            "type":"Food & Drink"
        }
    ],
    "sg:phone":"+1   ",
    "sg:postcode":"07093",
    "sg:province":"NJ",
    "sg:tags":[
        "eating"
    ],
    "wof:name":"La Cumbia No 2",
    "wof:placetype":"venue"
},
  "geometry": {"coordinates":[-74.01330900000001,40.792998],"type":"Point"}
}