{
  "type": "Feature",
  "properties": {
    "addr:full":"54 Walnut Dr Upper Saddle Rvr NJ 07458",
    "addr:housenumber":"54",
    "addr:postcode":"07458",
    "addr:street":"Walnut Dr Upper Saddle Rvr",
    "iso:country":"US",
    "sg:address":"54 Walnut Dr",
    "sg:city":"Upper Saddle Rvr",
    "sg:classifiers":[
        {
            "category":"Building & Trades",
            "subcategory":"Construction",
            "type":"Services"
        }
    ],
    "sg:phone":"+1 845 429 1868",
    "sg:postcode":"07458",
    "sg:province":"NJ",
    "sg:tags":[
        "tile",
        "dealer"
    ],
    "wof:name":"Certified Tile",
    "wof:placetype":"venue"
},
  "geometry": {"coordinates":[-74.118932,41.061296],"type":"Point"}
}