{
  "type": "Feature",
  "properties": {
    "iso:country":"US",
    "sg:address":"15 Vanada Dr",
    "sg:city":"Neptune",
    "sg:classifiers":[
        {
            "category":"Shopping",
            "subcategory":"Shoes",
            "type":"Retail Goods"
        }
    ],
    "sg:phone":"+1   ",
    "sg:postcode":"07753",
    "sg:province":"NJ",
    "wof:name":"Jay AR Sons",
    "wof:placetype":"venue"
},
  "geometry": {"coordinates":[-74.077144,40.233109],"type":"Point"}
}