{
  "type": "Feature",
  "properties": {
    "addr:full":"1601 Malone St Millville NJ 08332",
    "addr:housenumber":"1601",
    "addr:postcode":"08332",
    "addr:street":"Malone St",
    "iso:country":"US",
    "sg:address":"1601 Malone St",
    "sg:city":"Millville",
    "sg:classifiers":[
        {
            "category":"Building & Trades",
            "subcategory":"Electrical",
            "type":"Services"
        }
    ],
    "sg:phone":"+1 856 327 4505",
    "sg:postcode":"08332",
    "sg:province":"NJ",
    "sg:tags":[
        "electric",
        "contractor"
    ],
    "wof:name":"General Electric Aviation",
    "wof:placetype":"venue"
},
  "geometry": {"coordinates":[-75.06128699999999,39.372796],"type":"Point"}
}