{
  "type": "Feature",
  "properties": {
    "iso:country":"US",
    "sg:address":"312 Amboy Ave",
    "sg:city":"Metuchen",
    "sg:classifiers":[
        {
            "category":"Real Estate",
            "subcategory":"Real Estate Agent",
            "type":"Services"
        }
    ],
    "sg:phone":"+1 732 494 8080",
    "sg:postcode":"08840",
    "sg:province":"NJ",
    "sg:tags":[
        "appraiser"
    ],
    "wof:name":"Era Burgdorff Realtors",
    "wof:placetype":"venue"
},
  "geometry": {"coordinates":[-74.36273300000001,40.53806],"type":"Point"}
}