{
  "type": "Feature",
  "properties": {
    "addr:full":"206 Van Houten Ave Wyckoff NJ 07481",
    "addr:housenumber":"206",
    "addr:postcode":"07481",
    "addr:street":"Van Houten Ave",
    "iso:country":"US",
    "sg:address":"206 Van Houten Ave",
    "sg:city":"Wyckoff",
    "sg:classifiers":[
        {
            "category":"Professional",
            "subcategory":"Computer Services",
            "type":"Services"
        }
    ],
    "sg:phone":"+1   ",
    "sg:postcode":"07481",
    "sg:province":"NJ",
    "sg:tags":[
        "prepackaged",
        "software"
    ],
    "wof:name":"Picturedisc LLC",
    "wof:placetype":"venue"
},
  "geometry": {"coordinates":[-74.165897,41.005484],"type":"Point"}
}