{
  "type": "Feature",
  "properties": {
    "addr:full":"65 Passaic Ave Fairfield NJ 07004",
    "addr:housenumber":"65",
    "addr:postcode":"07004",
    "addr:street":"Passaic Ave",
    "iso:country":"US",
    "sg:address":"65 Passaic Ave",
    "sg:city":"Fairfield",
    "sg:classifiers":[
        {
            "category":"Home & Garden",
            "subcategory":"Household Appliances",
            "type":"Retail Goods"
        }
    ],
    "sg:phone":"+1 973 227 1777",
    "sg:postcode":"07004",
    "sg:province":"NJ",
    "sg:website":"www.karlsappliance.com",
    "wof:name":"Karl's Appliance",
    "wof:placetype":"venue"
},
  "geometry": {"coordinates":[-74.28136000000001,40.869495],"type":"Point"}
}