{
  "type": "Feature",
  "properties": {
    "iso:country":"US",
    "sg:address":"943 Omar Ave",
    "sg:city":"Avenel",
    "sg:classifiers":[
        {
            "category":"Real Estate",
            "subcategory":"Real Estate Services",
            "type":"Services"
        }
    ],
    "sg:phone":"+1 732 634 1380",
    "sg:postcode":"07001",
    "sg:province":"NJ",
    "sg:tags":[
        "management",
        "property"
    ],
    "wof:name":"Land Air Express of New England",
    "wof:placetype":"venue"
},
  "geometry": {"coordinates":[-74.254684,40.584404],"type":"Point"}
}