{
  "type": "Feature",
  "properties": {
    "iso:country":"US",
    "sg:address":"860 US Hwy 1",
    "sg:city":"Edison",
    "sg:classifiers":[
        {
            "category":"Wholesale",
            "subcategory":"Durable Goods & Equipment",
            "type":"Manufacturing & Wholesale Goods"
        }
    ],
    "sg:phone":"+1 732 650 0203",
    "sg:postcode":"08817",
    "sg:province":"NJ",
    "sg:tags":[
        "importer"
    ],
    "wof:name":"Apex Consolidated Corp",
    "wof:placetype":"venue"
},
  "geometry": {"coordinates":[-74.375823,40.514663],"type":"Point"}
}