{
  "type": "Feature",
  "properties": {
    "iso:country":"US",
    "sg:address":"95 Broadway",
    "sg:city":"Jersey City",
    "sg:classifiers":[
        {
            "category":"Education",
            "subcategory":"School",
            "type":"Public Place"
        }
    ],
    "sg:phone":"+1 201 435 0209",
    "sg:postcode":"07306",
    "sg:province":"NJ",
    "sg:tags":[
        "high",
        "middle",
        "elementary"
    ],
    "wof:name":"Our Lady of Mount Carmel School",
    "wof:placetype":"venue"
},
  "geometry": {"coordinates":[-74.071198,40.735802],"type":"Point"}
}