{
  "type": "Feature",
  "properties": {
    "iso:country":"US",
    "sg:address":"9 Reading Rd",
    "sg:city":"Edison",
    "sg:classifiers":[
        {
            "category":"Professional",
            "subcategory":"Business Services",
            "type":"Services"
        }
    ],
    "sg:phone":"+1   ",
    "sg:postcode":"08817",
    "sg:province":"NJ",
    "wof:name":"Ingenius Business Solutions",
    "wof:placetype":"venue"
},
  "geometry": {"coordinates":[-74.391929,40.545277],"type":"Point"}
}