{
  "type": "Feature",
  "properties": {
    "addr:full":"1000 Springfield Ave Irvington NJ 07111",
    "addr:housenumber":"1000",
    "addr:postcode":"07111",
    "addr:street":"Springfield Ave",
    "iso:country":"US",
    "sg:address":"1000 Springfield Ave",
    "sg:city":"Irvington",
    "sg:classifiers":[
        {
            "category":"Professional",
            "subcategory":"Accounting & Tax Preparation",
            "type":"Services"
        }
    ],
    "sg:phone":"+1 973 416 4443",
    "sg:postcode":"07111",
    "sg:province":"NJ",
    "sg:tags":[
        "return",
        "filing"
    ],
    "wof:name":"Jackson Hewitt Tax Service",
    "wof:placetype":"venue"
},
  "geometry": {"coordinates":[-74.22878799999999,40.726427],"type":"Point"}
}