{
  "type": "Feature",
  "properties": {
    "addr:full":"54 Margaret Dr Somerset NJ 08873",
    "addr:housenumber":"54",
    "addr:postcode":"08873",
    "addr:street":"Margaret Dr",
    "iso:country":"US",
    "sg:address":"54 Margaret Dr",
    "sg:city":"Somerset",
    "sg:classifiers":[
        {
            "category":"Professional",
            "subcategory":"Computer Services",
            "type":"Services"
        }
    ],
    "sg:phone":"+1 732 718 7444",
    "sg:postcode":"08873",
    "sg:province":"NJ",
    "sg:tags":[
        "related"
    ],
    "wof:name":"Malicom Systems Inc",
    "wof:placetype":"venue"
},
  "geometry": {"coordinates":[-74.52435699999999,40.489684],"type":"Point"}
}