{
  "type": "Feature",
  "properties": {
    "iso:country":"US",
    "sg:address":"33 Anderson Ave",
    "sg:city":"Fairview",
    "sg:classifiers":[
        {
            "category":"Shopping",
            "subcategory":"Jewelry",
            "type":"Retail Goods"
        }
    ],
    "sg:phone":"+1 201 840 5900",
    "sg:postcode":"07022",
    "sg:province":"NJ",
    "sg:tags":[
        "jeweler"
    ],
    "wof:name":"Steven S Jewelry",
    "wof:placetype":"venue"
},
  "geometry": {"coordinates":[-74.00050400000001,40.810902],"type":"Point"}
}