{
  "type": "Feature",
  "properties": {
    "addr:full":"964 Parkway Ave Trenton NJ 08618",
    "addr:housenumber":"964",
    "addr:postcode":"08618",
    "addr:street":"Parkway Ave",
    "iso:country":"US",
    "sg:address":"964 Parkway Ave",
    "sg:city":"Trenton",
    "sg:classifiers":[
        {
            "category":"Food & Beverages",
            "subcategory":"Bakery",
            "type":"Retail Goods"
        }
    ],
    "sg:phone":"+1   ",
    "sg:postcode":"08618",
    "sg:province":"NJ",
    "wof:name":"Bakefair Inc",
    "wof:placetype":"venue"
},
  "geometry": {"coordinates":[-74.793166,40.255966],"type":"Point"}
}