{
  "type": "Feature",
  "properties": {
    "addr:full":"3231 State Rte 27 Franklin Park NJ 08823",
    "addr:housenumber":"3231",
    "addr:postcode":"08823",
    "addr:street":"State Rte 27",
    "iso:country":"US",
    "sg:address":"3231 State Rte 27",
    "sg:city":"Franklin Park",
    "sg:classifiers":[
        {
            "category":"Retail",
            "subcategory":"Auto Rental",
            "type":"Services"
        }
    ],
    "sg:phone":"+1 732 951 8080",
    "sg:postcode":"08823",
    "sg:province":"NJ",
    "sg:tags":[
        "passenger",
        "car"
    ],
    "wof:name":"Central Jersey Rental & Sales",
    "wof:placetype":"venue"
},
  "geometry": {"coordinates":[-74.549891,40.432284],"type":"Point"}
}