{
  "type": "Feature",
  "properties": {
    "addr:full":"203 W 9th St Plainfield NJ 07060",
    "addr:housenumber":"203",
    "addr:postcode":"07060",
    "addr:street":"W 9Th St",
    "iso:country":"US",
    "sg:address":"203 W 9th St",
    "sg:city":"Plainfield",
    "sg:classifiers":[
        {
            "category":"Health Services",
            "subcategory":"Doctor",
            "type":"Services"
        }
    ],
    "sg:phone":"+1 908 756 5550",
    "sg:postcode":"07060",
    "sg:province":"NJ",
    "sg:tags":[
        "physician",
        "surgeon",
        "medical"
    ],
    "wof:name":"Karl E Russell Brown MD",
    "wof:placetype":"venue"
},
  "geometry": {"coordinates":[-74.416363,40.611339],"type":"Point"}
}