{
  "type": "Feature",
  "properties": {
    "addr:full":"4 Tulip Ct Oakhurst NJ 07755",
    "addr:housenumber":"4",
    "addr:postcode":"07755",
    "addr:street":"Tulip Ct",
    "iso:country":"US",
    "sg:address":"4 Tulip Ct",
    "sg:city":"Oakhurst",
    "sg:classifiers":[
        {
            "category":"Professional",
            "subcategory":"Computer Services",
            "type":"Services"
        }
    ],
    "sg:phone":"+1 732 229 8969",
    "sg:postcode":"07755",
    "sg:province":"NJ",
    "sg:tags":[
        "related"
    ],
    "wof:name":"Tabush Consulting Group",
    "wof:placetype":"venue"
},
  "geometry": {"coordinates":[-74.012885,40.271982],"type":"Point"}
}