{
  "type": "Feature",
  "properties": {
    "iso:country":"US",
    "sg:address":"194 Hargreaves Ave",
    "sg:city":"Teaneck",
    "sg:classifiers":[
        {
            "category":"Retail",
            "subcategory":"Auto Repair",
            "type":"Services"
        }
    ],
    "sg:phone":"+1 201 833 9100",
    "sg:postcode":"07666",
    "sg:province":"NJ",
    "wof:name":"Ahr Service Center",
    "wof:placetype":"venue"
},
  "geometry": {"coordinates":[-73.98989899999999,40.902401],"type":"Point"}
}