{
  "type": "Feature",
  "properties": {
    "addr:full":"19 Church St Lambertville NJ 08530",
    "addr:housenumber":"19",
    "addr:postcode":"08530",
    "addr:street":"Church St",
    "iso:country":"US",
    "sg:address":"19 Church St",
    "sg:city":"Lambertville",
    "sg:classifiers":[
        {
            "category":"Professional",
            "type":"Services"
        }
    ],
    "sg:phone":"+1 609 397 1611",
    "sg:postcode":"08530",
    "sg:province":"NJ",
    "sg:tags":[
        "establishment"
    ],
    "wof:name":"Map Resources",
    "wof:placetype":"venue"
},
  "geometry": {"coordinates":[-74.944067,40.366869],"type":"Point"}
}