{
  "type": "Feature",
  "properties": {
    "iso:country":"US",
    "sg:address":"49 Kanes Ln",
    "sg:city":"Middletown",
    "sg:classifiers":[
        {
            "category":"Taxi",
            "type":"Transportation"
        }
    ],
    "sg:phone":"+1 732 741 4600",
    "sg:postcode":"07748",
    "sg:province":"NJ",
    "wof:name":"Yellow Cab Middletown",
    "wof:placetype":"venue"
},
  "geometry": {"coordinates":[-74.09331,40.386191],"type":"Point"}
}