{
  "type": "Feature",
  "properties": {
    "addr:full":"20 S Main St Cape May Court House NJ 08210",
    "addr:housenumber":"20",
    "addr:postcode":"08210",
    "addr:street":"S Main St",
    "iso:country":"US",
    "sg:address":"20 S Main St",
    "sg:city":"Cape May Court House",
    "sg:classifiers":[
        {
            "category":"Autos & Motor Vehicles",
            "subcategory":"Automobile Sales",
            "type":"Retail Goods"
        },
        {
            "category":"Autos & Motor Vehicles",
            "subcategory":"Motorcycle Sales",
            "type":"Retail Goods"
        }
    ],
    "sg:phone":"+1 609 465 3900",
    "sg:postcode":"08210",
    "sg:province":"NJ",
    "sg:tags":[
        "car"
    ],
    "wof:name":"Main Street Auto & Cycle Sales",
    "wof:placetype":"venue"
},
  "geometry": {"coordinates":[-74.8246,39.081001],"type":"Point"}
}