{
  "type": "Feature",
  "properties": {
    "addr:full":"1313 New Willow St Trenton NJ 08638",
    "addr:housenumber":"1313",
    "addr:postcode":"08638",
    "addr:street":"New Willow St",
    "iso:country":"US",
    "sg:address":"1313 New Willow St",
    "sg:city":"Trenton",
    "sg:classifiers":[
        {
            "category":"Retail",
            "subcategory":"Auto Repair",
            "type":"Services"
        }
    ],
    "sg:phone":"+1 609 393 6112",
    "sg:postcode":"08638",
    "sg:province":"NJ",
    "sg:tags":[
        "repairing",
        "automobile"
    ],
    "wof:name":"Mendez Auto Repair",
    "wof:placetype":"venue"
},
  "geometry": {"coordinates":[-74.758184,40.23667],"type":"Point"}
}