{
  "type": "Feature",
  "properties": {
    "addr:full":"531 Freeman St Orange NJ 07050",
    "addr:housenumber":"531",
    "addr:postcode":"07050",
    "addr:street":"Freeman St",
    "iso:country":"US",
    "sg:address":"531 Freeman St",
    "sg:city":"Orange",
    "sg:classifiers":[
        {
            "category":"Manufacturing",
            "subcategory":"Metals",
            "type":"Manufacturing & Wholesale Goods"
        },
        {
            "category":"Wholesale",
            "subcategory":"Construction Materials",
            "type":"Manufacturing & Wholesale Goods"
        }
    ],
    "sg:phone":"+1 973 672 4550",
    "sg:postcode":"07050",
    "sg:province":"NJ",
    "sg:tags":[
        "building",
        "downspouts",
        "gutter",
        "supply"
    ],
    "wof:name":"Premier Aluminum Corp",
    "wof:placetype":"venue"
},
  "geometry": {"coordinates":[-74.24430099999999,40.766102],"type":"Point"}
}