{
  "type": "Feature",
  "properties": {
    "iso:country":"US",
    "sg:address":"766 McCoy Rd",
    "sg:city":"Franklin Lakes",
    "sg:classifiers":[
        {
            "category":"Professional",
            "type":"Services"
        }
    ],
    "sg:phone":"+1   ",
    "sg:postcode":"07417",
    "sg:province":"NJ",
    "wof:name":"Michael Howland",
    "wof:placetype":"venue"
},
  "geometry": {"coordinates":[-74.22983499999999,41.013923],"type":"Point"}
}