{
  "type": "Feature",
  "properties": {
    "addr:full":"323 Sharon Gardens Ct Woodbridge NJ 07095",
    "addr:housenumber":"323",
    "addr:postcode":"07095",
    "addr:street":"Sharon Gardens Ct",
    "iso:country":"US",
    "sg:address":"323 Sharon Gardens Ct",
    "sg:city":"Woodbridge",
    "sg:classifiers":[
        {
            "category":"Retail",
            "subcategory":"Animal Services",
            "type":"Services"
        }
    ],
    "sg:phone":"+1 732 636 7570",
    "sg:postcode":"07095",
    "sg:province":"NJ",
    "wof:name":"Walking Paws By Nataly",
    "wof:placetype":"venue"
},
  "geometry": {"coordinates":[-74.297595,40.552318],"type":"Point"}
}