{
  "type": "Feature",
  "properties": {
    "iso:country":"US",
    "sg:address":"6 Colonial Lake Dr",
    "sg:city":"Trenton",
    "sg:classifiers":[
        {
            "category":"Health Services",
            "subcategory":"Doctor",
            "type":"Services"
        }
    ],
    "sg:phone":"+1 609 883 6900",
    "sg:postcode":"08648",
    "sg:province":"NJ",
    "wof:name":"Chacker Frederick M DDS",
    "wof:placetype":"venue"
},
  "geometry": {"coordinates":[-74.725015,40.257999],"type":"Point"}
}