{
  "type": "Feature",
  "properties": {
    "iso:country":"US",
    "sg:address":"12 Jersey Ave",
    "sg:city":"Metuchen",
    "sg:classifiers":[
        {
            "category":"Wholesale",
            "subcategory":"Metals & Minerals",
            "type":"Manufacturing & Wholesale Goods"
        }
    ],
    "sg:phone":"+1 732 494 5551",
    "sg:postcode":"08840",
    "sg:province":"NJ",
    "sg:tags":[
        "computer",
        "cable"
    ],
    "wof:name":"Gentech International Corp",
    "wof:placetype":"venue"
},
  "geometry": {"coordinates":[-74.372597,40.544361],"type":"Point"}
}