{
  "type": "Feature",
  "properties": {
    "iso:country":"US",
    "sg:address":"1100 Woodbridge Rd",
    "sg:city":"Rahway",
    "sg:classifiers":[
        {
            "category":"Organizations",
            "subcategory":"Non-profit Organization",
            "type":"Services"
        }
    ],
    "sg:phone":"+1 732 815 9595",
    "sg:postcode":"07065",
    "sg:province":"NJ",
    "sg:tags":[
        "info",
        "addiction",
        "abuse",
        "treatment",
        "drug"
    ],
    "wof:name":"New Direction Inc",
    "wof:placetype":"venue"
},
  "geometry": {"coordinates":[-74.268502,40.59859],"type":"Point"}
}