{
  "type": "Feature",
  "properties": {
    "iso:country":"US",
    "sg:address":"362 Prospect Ave",
    "sg:city":"Dumont",
    "sg:classifiers":[
        {
            "category":"Real Estate",
            "subcategory":"Surveying",
            "type":"Services"
        }
    ],
    "sg:phone":"+1   ",
    "sg:postcode":"07628",
    "sg:province":"NJ",
    "wof:name":"Frank N Dunn",
    "wof:placetype":"venue"
},
  "geometry": {"coordinates":[-74.002392,40.947509],"type":"Point"}
}