{
  "type": "Feature",
  "properties": {
    "iso:country":"US",
    "sg:address":"2715 Hooper Ave",
    "sg:city":"Brick",
    "sg:classifiers":[
        {
            "category":"Freight",
            "type":"Transportation"
        }
    ],
    "sg:phone":"+1 732 451 9099",
    "sg:postcode":"08723",
    "sg:province":"NJ",
    "sg:tags":[
        "broker"
    ],
    "wof:name":"Top of The Line Carriers Inc",
    "wof:placetype":"venue"
},
  "geometry": {"coordinates":[-74.129047,40.0483],"type":"Point"}
}