{
  "type": "Feature",
  "properties": {
    "addr:full":"16 Oak Forest Dr Sicklerville NJ 08081",
    "addr:housenumber":"16",
    "addr:postcode":"08081",
    "addr:street":"Oak Forest Dr",
    "iso:country":"US",
    "sg:address":"16 Oak Forest Dr",
    "sg:city":"Sicklerville",
    "sg:classifiers":[
        {
            "category":"Building & Trades",
            "subcategory":"Construction",
            "type":"Services"
        }
    ],
    "sg:phone":"+1 856 728 0769",
    "sg:postcode":"08081",
    "sg:province":"NJ",
    "sg:tags":[
        "contractor"
    ],
    "wof:name":"Jet Clean Power Washing",
    "wof:placetype":"venue"
},
  "geometry": {"coordinates":[-74.983974,39.708346],"type":"Point"}
}