{
  "type": "Feature",
  "properties": {
    "iso:country":"US",
    "sg:address":"77 US Hwy 1",
    "sg:city":"Metuchen",
    "sg:classifiers":[
        {
            "category":"Restaurant",
            "type":"Food & Drink"
        }
    ],
    "sg:phone":"+1 732 494 1645",
    "sg:postcode":"08817",
    "sg:province":"NJ",
    "sg:tags":[
        "caribbean"
    ],
    "sg:website":"www.pollotropical.com/",
    "wof:name":"Pollo Tropical",
    "wof:placetype":"venue"
},
  "geometry": {"coordinates":[-74.326477,40.547652],"type":"Point"}
}