{
  "type": "Feature",
  "properties": {
    "iso:country":"US",
    "sg:address":"820 Erial Rd",
    "sg:city":"Clementon",
    "sg:classifiers":[
        {
            "category":"Government",
            "subcategory":"Post Office",
            "type":"Public Place"
        }
    ],
    "sg:phone":"+1 856 784 1488",
    "sg:postcode":"08021",
    "sg:province":"NJ",
    "sg:tags":[
        "postal",
        "us"
    ],
    "wof:name":"US Post Office",
    "wof:placetype":"venue"
},
  "geometry": {"coordinates":[-74.991709,39.785363],"type":"Point"}
}