{
  "type": "Feature",
  "properties": {
    "iso:country":"US",
    "sg:address":"606 Co Rd 519",
    "sg:city":"Sussex",
    "sg:classifiers":[
        {
            "category":"Building & Trades",
            "subcategory":"Electrical",
            "type":"Services"
        }
    ],
    "sg:phone":"+1 973 875 8779",
    "sg:postcode":"07461",
    "sg:province":"NJ",
    "sg:tags":[
        "electrical",
        "contractor"
    ],
    "wof:name":"Martin Van Deweert Jr",
    "wof:placetype":"venue"
},
  "geometry": {"coordinates":[-74.672764,41.241846],"type":"Point"}
}