{
  "type": "Feature",
  "properties": {
    "iso:country":"US",
    "sg:address":"77 Hamilton Ave",
    "sg:city":"Fords",
    "sg:classifiers":[
        {
            "category":"Professional",
            "type":"Services"
        }
    ],
    "sg:phone":"+1 732 225 0520",
    "sg:postcode":"08863",
    "sg:province":"NJ",
    "sg:tags":[
        "establishment"
    ],
    "wof:name":"Interealty Corp",
    "wof:placetype":"venue"
},
  "geometry": {"coordinates":[-74.30921499999999,40.528462],"type":"Point"}
}