{
  "type": "Feature",
  "properties": {
    "addr:full":"554 S Livingston Ave Livingston NJ 07039",
    "addr:housenumber":"554",
    "addr:postcode":"07039",
    "addr:street":"S Livingston Ave",
    "iso:country":"US",
    "sg:address":"554 S Livingston Ave",
    "sg:city":"Livingston",
    "sg:classifiers":[
        {
            "category":"Professional",
            "subcategory":"Lawyer & Legal Services",
            "type":"Services"
        }
    ],
    "sg:phone":"+1 973 992 3500",
    "sg:postcode":"07039",
    "sg:province":"NJ",
    "sg:tags":[
        "attorney"
    ],
    "wof:name":"James C Patton",
    "wof:placetype":"venue"
},
  "geometry": {"coordinates":[-74.32561099999999,40.773476],"type":"Point"}
}