{
  "type": "Feature",
  "properties": {
    "addr:full":"3005 Chapel Ave W Cherry Hill NJ 08002",
    "addr:housenumber":"3005",
    "addr:postcode":"08002",
    "addr:street":"Chapel Ave W",
    "iso:country":"US",
    "sg:address":"3005 Chapel Ave W",
    "sg:city":"Cherry Hill",
    "sg:classifiers":[
        {
            "category":"Real Estate",
            "subcategory":"Real Estate Operator",
            "type":"Services"
        }
    ],
    "sg:phone":"+1 856 667 1000",
    "sg:postcode":"08002",
    "sg:province":"NJ",
    "sg:tags":[
        "owner",
        "building",
        "apartment",
        "an"
    ],
    "wof:name":"Towers of Windsor Park",
    "wof:placetype":"venue"
},
  "geometry": {"coordinates":[-75.003083,39.92617],"type":"Point"}
}