{
  "type": "Feature",
  "properties": {
    "addr:full":"601 Violet Ln Jackson NJ 08527",
    "addr:housenumber":"601",
    "addr:postcode":"08527",
    "addr:street":"Violet Ln",
    "iso:country":"US",
    "sg:address":"601 Violet Ln",
    "sg:city":"Jackson",
    "sg:classifiers":[
        {
            "category":"Building & Trades",
            "subcategory":"Construction",
            "type":"Services"
        }
    ],
    "sg:phone":"+1 732 961 0266",
    "sg:postcode":"08527",
    "sg:province":"NJ",
    "sg:tags":[
        "house"
    ],
    "wof:name":"Distinctive Builders",
    "wof:placetype":"venue"
},
  "geometry": {"coordinates":[-74.282056,40.121789],"type":"Point"}
}