{
  "type": "Feature",
  "properties": {
    "iso:country":"US",
    "sg:address":"151 Newark Pompton Tpke",
    "sg:city":"Pequannock",
    "sg:classifiers":[
        {
            "category":"Shopping",
            "subcategory":"Jewelry",
            "type":"Retail Goods"
        }
    ],
    "sg:phone":"+1   ",
    "sg:postcode":"07440",
    "sg:province":"NJ",
    "wof:name":"Boston Louis",
    "wof:placetype":"venue"
},
  "geometry": {"coordinates":[-74.28685900000001,40.946352],"type":"Point"}
}