{
  "type": "Feature",
  "properties": {
    "addr:full":"260 Locust Ave Rumson NJ 07760",
    "addr:housenumber":"260",
    "addr:postcode":"07760",
    "addr:street":"Locust Ave",
    "iso:country":"US",
    "sg:address":"260 Locust Ave",
    "sg:city":"Rumson",
    "sg:classifiers":[
        {
            "category":"Professional",
            "subcategory":"Management & Consulting",
            "type":"Services"
        }
    ],
    "sg:phone":"+1   ",
    "sg:postcode":"07760",
    "sg:province":"NJ",
    "sg:tags":[
        "consultant"
    ],
    "wof:name":"Allen J Bejda",
    "wof:placetype":"venue"
},
  "geometry": {"coordinates":[-74.021862,40.396764],"type":"Point"}
}