{
  "type": "Feature",
  "properties": {
    "iso:country":"US",
    "sg:address":"5 E Front St",
    "sg:city":"Keyport",
    "sg:classifiers":[
        {
            "category":"Wholesale",
            "subcategory":"Machinery & Supplies",
            "type":"Manufacturing & Wholesale Goods"
        }
    ],
    "sg:phone":"+1 732 739 5303",
    "sg:postcode":"07735",
    "sg:province":"NJ",
    "sg:tags":[
        "equipment",
        "salon",
        "establishment",
        "beauty"
    ],
    "sg:website":"www.keyport.com",
    "wof:name":"Beauty To The Max",
    "wof:placetype":"venue"
},
  "geometry": {"coordinates":[-74.201311,40.437898],"type":"Point"}
}