{
  "type": "Feature",
  "properties": {
    "iso:country":"US",
    "sg:address":"53 Briarwood Path",
    "sg:city":"Clark",
    "sg:classifiers":[
        {
            "category":"Professional",
            "type":"Services"
        }
    ],
    "sg:phone":"+1   ",
    "sg:postcode":"07066",
    "sg:province":"NJ",
    "wof:name":"Vincent Vuono Jr Inc",
    "wof:placetype":"venue"
},
  "geometry": {"coordinates":[-74.335813,40.615438],"type":"Point"}
}