{
  "type": "Feature",
  "properties": {
    "addr:full":"859 Bridgeboro St Riverside NJ 08075",
    "addr:housenumber":"859",
    "addr:postcode":"08075",
    "addr:street":"Bridgeboro St",
    "iso:country":"US",
    "sg:address":"859 Bridgeboro St",
    "sg:city":"Riverside",
    "sg:classifiers":[
        {
            "category":"Building & Trades",
            "subcategory":"Construction",
            "type":"Services"
        }
    ],
    "sg:phone":"+1 856 764 0587",
    "sg:postcode":"08075",
    "sg:province":"NJ",
    "sg:tags":[
        "general"
    ],
    "wof:name":"Del Val Cnstr & Envmtl Cons",
    "wof:placetype":"venue"
},
  "geometry": {"coordinates":[-74.942953,40.031931],"type":"Point"}
}