{
  "type": "Feature",
  "properties": {
    "iso:country":"US",
    "sg:address":"710 Hughes Ave",
    "sg:city":"Cape May",
    "sg:classifiers":[
        {
            "category":"Travel",
            "subcategory":"Campground",
            "type":"Entertainment"
        }
    ],
    "sg:phone":"+1 609 886 6164",
    "sg:postcode":"08204",
    "sg:province":"NJ",
    "sg:tags":[
        "camp"
    ],
    "wof:name":"Sea Hunt",
    "wof:placetype":"venue"
},
  "geometry": {"coordinates":[-74.94777499999999,38.975237],"type":"Point"}
}