{
  "type": "Feature",
  "properties": {
    "addr:full":"137 Davis Rd Franklin NJ 07416",
    "addr:housenumber":"137",
    "addr:postcode":"07416",
    "addr:street":"Davis Rd",
    "iso:country":"US",
    "sg:address":"137 Davis Rd",
    "sg:city":"Franklin",
    "sg:classifiers":[
        {
            "category":"Wholesale",
            "subcategory":"Stationery",
            "type":"Manufacturing & Wholesale Goods"
        }
    ],
    "sg:phone":"+1 973 827 4113",
    "sg:postcode":"07416",
    "sg:province":"NJ",
    "sg:tags":[
        "supply"
    ],
    "wof:name":"Execu/Forms Ltd Inc",
    "wof:placetype":"venue"
},
  "geometry": {"coordinates":[-74.598719,41.118077],"type":"Point"}
}