{
  "type": "Feature",
  "properties": {
    "iso:country":"US",
    "sg:address":"870 Pompton Ave",
    "sg:city":"Cedar Grove",
    "sg:classifiers":[
        {
            "category":"Health Services",
            "subcategory":"Doctor",
            "type":"Services"
        }
    ],
    "sg:phone":"+1 973 239 3865",
    "sg:postcode":"07009",
    "sg:province":"NJ",
    "wof:name":"Women First OB Gyn",
    "wof:placetype":"venue"
},
  "geometry": {"coordinates":[-74.23324599999999,40.8644],"type":"Point"}
}