{
  "type": "Feature",
  "properties": {
    "addr:full":"425 Forest Rd Mahwah NJ 07430",
    "addr:housenumber":"425",
    "addr:postcode":"07430",
    "addr:street":"Forest Rd",
    "iso:country":"US",
    "sg:address":"425 Forest Rd",
    "sg:city":"Mahwah",
    "sg:classifiers":[
        {
            "category":"Retail",
            "subcategory":"Laundry & Dry Cleaning",
            "type":"Services"
        }
    ],
    "sg:phone":"+1 201 891 1335",
    "sg:postcode":"07430",
    "sg:province":"NJ",
    "sg:tags":[
        "drycleaning",
        "plant",
        "cleaners"
    ],
    "wof:name":"Fardale Cleaners",
    "wof:placetype":"venue"
},
  "geometry": {"coordinates":[-74.16745299999999,41.030046],"type":"Point"}
}