{
  "type": "Feature",
  "properties": {
    "addr:full":"535 E 2nd Ave Roselle NJ 07203",
    "addr:housenumber":"535",
    "addr:postcode":"07203",
    "addr:street":"E 2Nd Ave",
    "iso:country":"US",
    "sg:address":"535 E 2nd Ave",
    "sg:city":"Roselle",
    "sg:classifiers":[
        {
            "category":"Shopping",
            "subcategory":"Discount & Variety Stores",
            "type":"Retail Goods"
        }
    ],
    "sg:phone":"+1   ",
    "sg:postcode":"07203",
    "sg:province":"NJ",
    "sg:tags":[
        "merchandise",
        "general"
    ],
    "wof:name":"Krishna General Store",
    "wof:placetype":"venue"
},
  "geometry": {"coordinates":[-74.24897,40.660788],"type":"Point"}
}