{
  "type": "Feature",
  "properties": {
    "iso:country":"US",
    "sg:address":"2402 Aspen Dr",
    "sg:city":"Plainsboro",
    "sg:classifiers":[
        {
            "category":"Health Services",
            "subcategory":"Medical Lab",
            "type":"Services"
        }
    ],
    "sg:phone":"+1   ",
    "sg:postcode":"08536",
    "sg:province":"NJ",
    "sg:tags":[
        "laboratory"
    ],
    "wof:name":"Rx Clinical Data Management",
    "wof:placetype":"venue"
},
  "geometry": {"coordinates":[-74.556122,40.32432],"type":"Point"}
}