{
  "type": "Feature",
  "properties": {
    "iso:country":"US",
    "sg:address":"231 Cumberland Ave",
    "sg:city":"Estell Manor",
    "sg:classifiers":[
        {
            "category":"Professional",
            "type":"Services"
        }
    ],
    "sg:phone":"+1   ",
    "sg:postcode":"08319",
    "sg:province":"NJ",
    "wof:name":"Accesssolution Co",
    "wof:placetype":"venue"
},
  "geometry": {"coordinates":[-74.79143500000001,39.382042],"type":"Point"}
}