{
  "type": "Feature",
  "properties": {
    "addr:full":"60 Industrial Pkwy Somerville NJ 08876",
    "addr:housenumber":"60",
    "addr:postcode":"08876",
    "addr:street":"Industrial Pkwy",
    "iso:country":"US",
    "sg:address":"60 Industrial Pkwy",
    "sg:city":"Somerville",
    "sg:classifiers":[
        {
            "category":"Social Services",
            "subcategory":"Job Training",
            "type":"Services"
        }
    ],
    "sg:phone":"+1   ",
    "sg:postcode":"08876",
    "sg:province":"NJ",
    "sg:tags":[
        "home",
        "adult",
        "residential"
    ],
    "wof:name":"Midland Adult Services Inc",
    "wof:placetype":"venue"
},
  "geometry": {"coordinates":[-74.69796700000001,40.596847],"type":"Point"}
}