{
  "type": "Feature",
  "properties": {
    "addr:full":"520 Cary St Orange NJ 07050",
    "addr:housenumber":"520",
    "addr:postcode":"07050",
    "addr:street":"Cary St",
    "iso:country":"US",
    "sg:address":"520 Cary St",
    "sg:city":"Orange",
    "sg:classifiers":[
        {
            "category":"Arts & Performance",
            "subcategory":"Theater",
            "type":"Entertainment"
        }
    ],
    "sg:phone":"+1 973 675 8200",
    "sg:postcode":"07050",
    "sg:province":"NJ",
    "sg:tags":[
        "bureau"
    ],
    "wof:name":"Platinum Productions",
    "wof:placetype":"venue"
},
  "geometry": {"coordinates":[-74.23935,40.77061],"type":"Point"}
}