{
  "type": "Feature",
  "properties": {
    "iso:country":"US",
    "sg:address":"849 State Rd",
    "sg:city":"Princeton",
    "sg:classifiers":[
        {
            "category":"Building & Trades",
            "subcategory":"Construction",
            "type":"Services"
        }
    ],
    "sg:phone":"+1 609 924 6777",
    "sg:postcode":"08540",
    "sg:province":"NJ",
    "sg:tags":[
        "addition",
        "residential",
        "remodeling"
    ],
    "wof:name":"Moores Cnstr & HM Imprvs",
    "wof:placetype":"venue"
},
  "geometry": {"coordinates":[-74.655011,40.390035],"type":"Point"}
}