{
  "type": "Feature",
  "properties": {
    "addr:full":"10 Lake Rd Saddle River NJ 07458",
    "addr:housenumber":"10",
    "addr:postcode":"07458",
    "addr:street":"Lake Rd",
    "iso:country":"US",
    "sg:address":"10 Lake Rd",
    "sg:city":"Saddle River",
    "sg:classifiers":[
        {
            "category":"Health Services",
            "subcategory":"Chiropractor",
            "type":"Services"
        }
    ],
    "sg:phone":"+1 201 825 7808",
    "sg:postcode":"07458",
    "sg:province":"NJ",
    "wof:name":"John Winn Chiropractic Office",
    "wof:placetype":"venue"
},
  "geometry": {"coordinates":[-74.09179899999999,41.070652],"type":"Point"}
}