{
  "type": "Feature",
  "properties": {
    "iso:country":"US",
    "sg:address":"343 Garden Street",
    "sg:city":"Hoboken",
    "sg:classifiers":[
        {
            "category":"Food & Beverages",
            "subcategory":"Candy",
            "type":"Retail Goods"
        },
        {
            "category":"Bakery",
            "type":"Food & Drink"
        }
    ],
    "sg:phone":"+1 201 420 0111",
    "sg:postcode":"07030",
    "sg:province":"NJ",
    "sg:tags":[
        "dessert"
    ],
    "sg:website":"www.sweethoboken.com",
    "wof:name":"Sweet",
    "wof:placetype":"venue"
},
  "geometry": {"coordinates":[-74.031291,40.741432],"type":"Point"}
}