{
  "type": "Feature",
  "properties": {
    "iso:country":"US",
    "sg:address":"133 Tunison Rd",
    "sg:city":"New Brunswick",
    "sg:classifiers":[
        {
            "category":"Education",
            "subcategory":"School",
            "type":"Public Place"
        }
    ],
    "sg:phone":"+1   ",
    "sg:postcode":"08901",
    "sg:province":"NJ",
    "wof:name":"Woodrow Wilson Elementary Schl",
    "wof:placetype":"venue"
},
  "geometry": {"coordinates":[-74.40522799999999,40.485065],"type":"Point"}
}