{
  "type": "Feature",
  "properties": {
    "addr:full":"11 Fieldstone Ct Randolph NJ 07869",
    "addr:housenumber":"11",
    "addr:postcode":"07869",
    "addr:street":"Fieldstone Ct",
    "iso:country":"US",
    "sg:address":"11 Fieldstone Ct",
    "sg:city":"Randolph",
    "sg:classifiers":[
        {
            "category":"Shopping",
            "subcategory":"Computers & Home Electronics",
            "type":"Retail Goods"
        }
    ],
    "sg:phone":"+1   ",
    "sg:postcode":"07869",
    "sg:province":"NJ",
    "sg:tags":[
        "software"
    ],
    "wof:name":"Carol Systems Inc",
    "wof:placetype":"venue"
},
  "geometry": {"coordinates":[-74.54324200000001,40.838733],"type":"Point"}
}