{
  "type": "Feature",
  "properties": {
    "addr:full":"660 Allwood Rd Passaic NJ 07055",
    "addr:housenumber":"660",
    "addr:postcode":"07055",
    "addr:street":"Allwood Rd",
    "iso:country":"US",
    "sg:address":"660 Allwood Rd",
    "sg:city":"Passaic",
    "sg:classifiers":[
        {
            "category":"Retail",
            "subcategory":"Funeral Services",
            "type":"Services"
        }
    ],
    "sg:phone":"+1 973 773 6666",
    "sg:postcode":"07055",
    "sg:province":"NJ",
    "sg:tags":[
        "cemetery"
    ],
    "sg:website":"www.allwoodfuneralhome.com",
    "wof:name":"Allwood Funeral Home",
    "wof:placetype":"venue"
},
  "geometry": {"coordinates":[-74.12799800000001,40.8601],"type":"Point"}
}