{
  "type": "Feature",
  "properties": {
    "addr:full":"215 Pawnee Rd Cranford NJ 07016",
    "addr:housenumber":"215",
    "addr:postcode":"07016",
    "addr:street":"Pawnee Rd",
    "iso:country":"US",
    "sg:address":"215 Pawnee Rd",
    "sg:city":"Cranford",
    "sg:classifiers":[
        {
            "category":"Banks & Credit Unions",
            "subcategory":"Financial Services",
            "type":"Services"
        }
    ],
    "sg:phone":"+1 908 497 1997",
    "sg:postcode":"07016",
    "sg:province":"NJ",
    "sg:tags":[
        "broker",
        "mortgage"
    ],
    "wof:name":"Taylex Cranford",
    "wof:placetype":"venue"
},
  "geometry": {"coordinates":[-74.321924,40.670052],"type":"Point"}
}