{
  "type": "Feature",
  "properties": {
    "addr:full":"117 Washington St Hoboken NJ 07030",
    "addr:housenumber":"117",
    "addr:postcode":"07030",
    "addr:street":"Washington St",
    "iso:country":"US",
    "sg:address":"117 Washington St",
    "sg:city":"Hoboken",
    "sg:classifiers":[
        {
            "category":"Government",
            "subcategory":"Office",
            "type":"Public Place"
        }
    ],
    "sg:phone":"+1   ",
    "sg:postcode":"07030",
    "sg:province":"NJ",
    "sg:tags":[
        "general"
    ],
    "wof:name":"Njlowestbidcom",
    "wof:placetype":"venue"
},
  "geometry": {"coordinates":[-74.03048699999999,40.738492],"type":"Point"}
}