{
  "type": "Feature",
  "properties": {
    "addr:full":"3019 US Hwy 46 Parsippany NJ 07054",
    "addr:housenumber":"3019",
    "addr:postcode":"07054",
    "addr:street":"Us Hwy 46",
    "iso:country":"US",
    "sg:address":"3019 US Hwy 46",
    "sg:city":"Parsippany",
    "sg:classifiers":[
        {
            "category":"Autos & Motor Vehicles",
            "subcategory":"Fuel & Gas Station",
            "type":"Retail Goods"
        }
    ],
    "sg:phone":"+1   ",
    "sg:postcode":"07054",
    "sg:province":"NJ",
    "sg:tags":[
        "station"
    ],
    "wof:name":"Parsippany Exxon",
    "wof:placetype":"venue"
},
  "geometry": {"coordinates":[-74.421323,40.870872],"type":"Point"}
}