{
  "type": "Feature",
  "properties": {
    "addr:full":"119 E 22nd St Bayonne NJ 07002",
    "addr:housenumber":"119",
    "addr:postcode":"07002",
    "addr:street":"E 22Nd St",
    "iso:country":"US",
    "sg:address":"119 E 22nd St",
    "sg:city":"Bayonne",
    "sg:classifiers":[
        {
            "category":"Building & Trades",
            "subcategory":"Construction",
            "type":"Services"
        }
    ],
    "sg:phone":"+1 201 436 8109",
    "sg:postcode":"07002",
    "sg:province":"NJ",
    "sg:tags":[
        "designer",
        "marine",
        "contractor"
    ],
    "wof:name":"Bayonne Lineboat Svc",
    "wof:placetype":"venue"
},
  "geometry": {"coordinates":[-74.112238,40.659912],"type":"Point"}
}