{
  "type": "Feature",
  "properties": {
    "iso:country":"US",
    "sg:address":"12 US Hwy 9",
    "sg:city":"Morganville",
    "sg:classifiers":[
        {
            "category":"Restaurant",
            "type":"Food & Drink"
        }
    ],
    "sg:phone":"+1   ",
    "sg:postcode":"07751",
    "sg:province":"NJ",
    "sg:tags":[
        "eating"
    ],
    "wof:name":"International House Pancake",
    "wof:placetype":"venue"
},
  "geometry": {"coordinates":[-74.306595,40.354038],"type":"Point"}
}