{
  "type": "Feature",
  "properties": {
    "addr:full":"6 Honiss St Belleville NJ 07109",
    "addr:housenumber":"6",
    "addr:postcode":"07109",
    "addr:street":"Honiss St",
    "iso:country":"US",
    "sg:address":"6 Honiss St",
    "sg:city":"Belleville",
    "sg:classifiers":[
        {
            "category":"Retail",
            "subcategory":"Auto Repair",
            "type":"Services"
        }
    ],
    "sg:phone":"+1 973 751 3344",
    "sg:postcode":"07109",
    "sg:province":"NJ",
    "sg:tags":[
        "body",
        "shop"
    ],
    "wof:name":"Columbus Auto Body",
    "wof:placetype":"venue"
},
  "geometry": {"coordinates":[-74.179497,40.777802],"type":"Point"}
}