{
  "type": "Feature",
  "properties": {
    "iso:country":"US",
    "sg:address":"23 Hardenburgh Ave",
    "sg:city":"Haworth",
    "sg:classifiers":[
        {
            "category":"Restaurant",
            "type":"Food & Drink"
        }
    ],
    "sg:menulink":"http://www.allmenus.com/nj/haworth/23801-andiamo/menu/",
    "sg:phone":"+1 201 384 1551",
    "sg:postcode":"07641",
    "sg:province":"NJ",
    "sg:tags":[
        "italian"
    ],
    "wof:name":"Andiamo",
    "wof:placetype":"venue"
},
  "geometry": {"coordinates":[-73.976257,40.957742],"type":"Point"}
}