{
  "type": "Feature",
  "properties": {
    "addr:full":"413 Brewers Bridge Rd Jackson NJ 08527",
    "addr:housenumber":"413",
    "addr:postcode":"08527",
    "addr:street":"Brewers Bridge Rd",
    "iso:country":"US",
    "sg:address":"413 Brewers Bridge Rd",
    "sg:city":"Jackson",
    "sg:classifiers":[
        {
            "category":"Organizations",
            "subcategory":"Religious Organization",
            "type":"Services"
        }
    ],
    "sg:phone":"+1   ",
    "sg:postcode":"08527",
    "sg:province":"NJ",
    "wof:name":"Andrews Charles II Rev",
    "wof:placetype":"venue"
},
  "geometry": {"coordinates":[-74.274418,40.107112],"type":"Point"}
}