{
  "type": "Feature",
  "properties": {
    "iso:country":"US",
    "sg:address":"447 Bellevue Ave",
    "sg:city":"Trenton",
    "sg:classifiers":[
        {
            "category":"Organizations",
            "subcategory":"Religious Organization",
            "type":"Services"
        }
    ],
    "sg:phone":"+1 609 392 4778",
    "sg:postcode":"08618",
    "sg:province":"NJ",
    "sg:tags":[
        "clergy"
    ],
    "wof:name":"Melvin Brown",
    "wof:placetype":"venue"
},
  "geometry": {"coordinates":[-74.77691,40.229258],"type":"Point"}
}