{
  "type": "Feature",
  "properties": {
    "addr:full":"328 Palisade Ave Jersey City NJ 07307",
    "addr:housenumber":"328",
    "addr:postcode":"07307",
    "addr:street":"Palisade Ave",
    "iso:country":"US",
    "sg:address":"328 Palisade Ave",
    "sg:city":"Jersey City",
    "sg:classifiers":[
        {
            "category":"Bars & Pubs",
            "type":"Food & Drink"
        }
    ],
    "sg:phone":"+1 201 798 7720",
    "sg:postcode":"07307",
    "sg:province":"NJ",
    "wof:name":"Little One's Bar International",
    "wof:placetype":"venue"
},
  "geometry": {"coordinates":[-74.04662399999999,40.73986],"type":"Point"}
}