{
  "type": "Feature",
  "properties": {
    "iso:country":"US",
    "sg:address":"81 Gless Ave",
    "sg:city":"Belleville",
    "sg:classifiers":[
        {
            "category":"Professional",
            "subcategory":"Computer Services",
            "type":"Services"
        }
    ],
    "sg:phone":"+1   ",
    "sg:postcode":"07109",
    "sg:province":"NJ",
    "sg:tags":[
        "programing",
        "custom"
    ],
    "wof:name":"Frontier Business Services",
    "wof:placetype":"venue"
},
  "geometry": {"coordinates":[-74.163465,40.807559],"type":"Point"}
}