{
  "type": "Feature",
  "properties": {
    "iso:country":"US",
    "sg:address":"711 Station Ave",
    "sg:city":"Haddon Heights",
    "sg:classifiers":[
        {
            "category":"Building & Trades",
            "subcategory":"Construction",
            "type":"Services"
        }
    ],
    "sg:phone":"+1 856 546 9700",
    "sg:postcode":"08035",
    "sg:province":"NJ",
    "sg:tags":[
        "contractor"
    ],
    "wof:name":"Interior Construction Plus Inc",
    "wof:placetype":"venue"
},
  "geometry": {"coordinates":[-75.060402,39.881001],"type":"Point"}
}