{
  "type": "Feature",
  "properties": {
    "addr:full":"1 Williamson Ct Lambertville NJ 08520",
    "addr:housenumber":"1",
    "addr:postcode":"08520",
    "addr:street":"Williamson Ct",
    "iso:country":"US",
    "sg:address":"1 Williamson Ct",
    "sg:city":"Lambertville",
    "sg:classifiers":[
        {
            "category":"Professional",
            "subcategory":"Management & Consulting",
            "type":"Services"
        }
    ],
    "sg:phone":"+1   ",
    "sg:postcode":"08520",
    "sg:province":"NJ",
    "wof:name":"Hills Hunterdon Sales Off Th",
    "wof:placetype":"venue"
},
  "geometry": {"coordinates":[-74.524017,40.285346],"type":"Point"}
}