{
  "type": "Feature",
  "properties": {
    "iso:country":"US",
    "sg:address":"9 Whippany Rd",
    "sg:city":"Whippany",
    "sg:classifiers":[
        {
            "category":"Wholesale",
            "subcategory":"Office Equipment",
            "type":"Manufacturing & Wholesale Goods"
        },
        {
            "category":"Building & Trades",
            "subcategory":"Equipment Rental",
            "type":"Services"
        }
    ],
    "sg:phone":"+1 973 560 1992",
    "sg:postcode":"07981",
    "sg:province":"NJ",
    "sg:tags":[
        "machine",
        "sales",
        "copying",
        "duplicating"
    ],
    "wof:name":"Preferred Business Systems",
    "wof:placetype":"venue"
},
  "geometry": {"coordinates":[-74.412741,40.821149],"type":"Point"}
}