{
  "type": "Feature",
  "properties": {
    "iso:country":"US",
    "sg:address":"254 S Creek Dr",
    "sg:city":"West Creek",
    "sg:classifiers":[
        {
            "category":"Mining & Drilling",
            "type":"Manufacturing & Wholesale Goods"
        },
        {
            "category":"Utilities",
            "type":"Services"
        }
    ],
    "sg:phone":"+1 609 597 3629",
    "sg:postcode":"08092",
    "sg:province":"NJ",
    "sg:tags":[
        "sanitary",
        "stone"
    ],
    "wof:name":"Southern Ocean Stone Landscpg",
    "wof:placetype":"venue"
},
  "geometry": {"coordinates":[-74.283449,39.622321],"type":"Point"}
}