{
  "type": "Feature",
  "properties": {
    "addr:full":"114 W Mt Pleasant Ave Livingston NJ 07039",
    "addr:housenumber":"114",
    "addr:postcode":"07039",
    "addr:street":"W Mt Pleasant Ave",
    "iso:country":"US",
    "sg:address":"114 W Mt Pleasant Ave",
    "sg:city":"Livingston",
    "sg:classifiers":[
        {
            "category":"Health Services",
            "subcategory":"Dentist",
            "type":"Services"
        }
    ],
    "sg:phone":"+1 973 992 7377",
    "sg:postcode":"07039",
    "sg:province":"NJ",
    "sg:tags":[
        "orthodontist"
    ],
    "sg:website":"www.drgorkowitz.com",
    "wof:name":"Bernard Gorkowitz DDS",
    "wof:placetype":"venue"
},
  "geometry": {"coordinates":[-74.320362,40.795416],"type":"Point"}
}