{
  "type": "Feature",
  "properties": {
    "iso:country":"US",
    "sg:address":"16 Fraser Ln",
    "sg:city":"Morristown",
    "sg:classifiers":[
        {
            "category":"Arts & Performance",
            "subcategory":"Music",
            "type":"Entertainment"
        }
    ],
    "sg:phone":"+1 732 738 4447",
    "sg:postcode":"07960",
    "sg:province":"NJ",
    "sg:tags":[
        "dj"
    ],
    "wof:name":"Perfect Choice Entertainment",
    "wof:placetype":"venue"
},
  "geometry": {"coordinates":[-74.465386,40.783408],"type":"Point"}
}