{
  "type": "Feature",
  "properties": {
    "addr:full":"303 Pacific Ave Jersey City NJ 07304",
    "addr:housenumber":"303",
    "addr:postcode":"07304",
    "addr:street":"Pacific Ave",
    "iso:country":"US",
    "sg:address":"303 Pacific Ave",
    "sg:city":"Jersey City",
    "sg:classifiers":[
        {
            "category":"Building & Trades",
            "subcategory":"Locksmith",
            "type":"Services"
        }
    ],
    "sg:phone":"+1 888 414 6719",
    "sg:postcode":"07304",
    "sg:province":"NJ",
    "sg:tags":[
        "key"
    ],
    "wof:name":"1 24 Hour Emergency Locksmith",
    "wof:placetype":"venue"
},
  "geometry": {"coordinates":[-74.06268300000001,40.711595],"type":"Point"}
}