{
  "type": "Feature",
  "properties": {
    "iso:country":"US",
    "sg:address":"8 Williams Ave",
    "sg:city":"Jersey City",
    "sg:classifiers":[
        {
            "category":"Building & Trades",
            "subcategory":"Construction",
            "type":"Services"
        }
    ],
    "sg:phone":"+1 201 434 2294",
    "sg:postcode":"07304",
    "sg:province":"NJ",
    "sg:tags":[
        "roofing",
        "contractor"
    ],
    "wof:name":"Miller A Roofing Co Inc",
    "wof:placetype":"venue"
},
  "geometry": {"coordinates":[-74.087653,40.719764],"type":"Point"}
}