{
  "type": "Feature",
  "properties": {
    "addr:full":"65 Nautilus Dr Manahawkin NJ 08050",
    "addr:housenumber":"65",
    "addr:postcode":"08050",
    "addr:street":"Nautilus Dr",
    "iso:country":"US",
    "sg:address":"65 Nautilus Dr",
    "sg:city":"Manahawkin",
    "sg:classifiers":[
        {
            "category":"Banks & Credit Unions",
            "subcategory":"Bank",
            "type":"Services"
        }
    ],
    "sg:phone":"+1 609 000 1111",
    "sg:postcode":"08050",
    "sg:province":"NJ",
    "wof:name":"Bank Of America",
    "wof:placetype":"venue"
},
  "geometry": {"coordinates":[-74.284565,39.718626],"type":"Point"}
}