{
  "type": "Feature",
  "properties": {
    "iso:country":"US",
    "sg:address":"341 47th St",
    "sg:city":"Union City",
    "sg:classifiers":[
        {
            "category":"Personal",
            "subcategory":"Beauty Salon",
            "type":"Services"
        }
    ],
    "sg:phone":"+1 201 520 0327",
    "sg:postcode":"07087",
    "sg:province":"NJ",
    "sg:tags":[
        "shop"
    ],
    "wof:name":"Sophies Hair & Things",
    "wof:placetype":"venue"
},
  "geometry": {"coordinates":[-74.022115,40.780813],"type":"Point"}
}