{
  "type": "Feature",
  "properties": {
    "iso:country":"US",
    "sg:address":"92 Burnett Ave",
    "sg:city":"Maplewood",
    "sg:classifiers":[
        {
            "category":"Real Estate",
            "subcategory":"Architect",
            "type":"Services"
        },
        {
            "category":"Professional",
            "subcategory":"Business Services",
            "type":"Services"
        }
    ],
    "sg:phone":"+1 973 761 5291",
    "sg:postcode":"07040",
    "sg:province":"NJ",
    "sg:tags":[
        "estimate",
        "construction"
    ],
    "wof:name":"H & H Construction Co Inc",
    "wof:placetype":"venue"
},
  "geometry": {"coordinates":[-74.259969,40.720418],"type":"Point"}
}