{
  "type": "Feature",
  "properties": {
    "addr:full":"535 41st St Union City NJ 07087",
    "addr:housenumber":"535",
    "addr:postcode":"07087",
    "addr:street":"41St St",
    "iso:country":"US",
    "sg:address":"535 41st St",
    "sg:city":"Union City",
    "sg:classifiers":[
        {
            "category":"Professional",
            "type":"Services"
        }
    ],
    "sg:phone":"+1 201 392 5091",
    "sg:postcode":"07087",
    "sg:province":"NJ",
    "sg:tags":[
        "establishment"
    ],
    "wof:name":"Victor Campos",
    "wof:placetype":"venue"
},
  "geometry": {"coordinates":[-74.027289,40.777593],"type":"Point"}
}