{
  "type": "Feature",
  "properties": {
    "addr:full":"73 Stephenville Pkwy Edison NJ 08820",
    "addr:housenumber":"73",
    "addr:postcode":"08820",
    "addr:street":"Stephenville Pkwy",
    "iso:country":"US",
    "sg:address":"73 Stephenville Pkwy",
    "sg:city":"Edison",
    "sg:classifiers":[
        {
            "category":"Shopping",
            "subcategory":"Clothing, Apparel, & Fashions",
            "type":"Retail Goods"
        }
    ],
    "sg:phone":"+1   ",
    "sg:postcode":"08820",
    "sg:province":"NJ",
    "wof:name":"Ice Concepts New York Fashion",
    "wof:placetype":"venue"
},
  "geometry": {"coordinates":[-74.370676,40.568684],"type":"Point"}
}