{
  "type": "Feature",
  "properties": {
    "iso:country":"US",
    "sg:address":"612 River St",
    "sg:city":"Paterson",
    "sg:classifiers":[
        {
            "category":"Retail",
            "subcategory":"Auto Repair",
            "type":"Services"
        }
    ],
    "sg:phone":"+1 973 345 4649",
    "sg:postcode":"07524",
    "sg:province":"NJ",
    "sg:tags":[
        "repairing",
        "automobile"
    ],
    "wof:name":"Britt Auto Repair Inc",
    "wof:placetype":"venue"
},
  "geometry": {"coordinates":[-74.155991,40.933822],"type":"Point"}
}