{
  "type": "Feature",
  "properties": {
    "addr:full":"435 Tappan Ave North Plainfield NJ 07063",
    "addr:housenumber":"435",
    "addr:postcode":"07063",
    "addr:street":"Tappan Ave",
    "iso:country":"US",
    "sg:address":"435 Tappan Ave",
    "sg:city":"North Plainfield",
    "sg:classifiers":[
        {
            "category":"Health Services",
            "subcategory":"Doctor",
            "type":"Services"
        }
    ],
    "sg:phone":"+1 908 755 3555",
    "sg:postcode":"07063",
    "sg:province":"NJ",
    "sg:tags":[
        "dentist"
    ],
    "wof:name":"Hyman S Tobey DDS",
    "wof:placetype":"venue"
},
  "geometry": {"coordinates":[-74.444557,40.609908],"type":"Point"}
}