{
  "type": "Feature",
  "properties": {
    "iso:country":"US",
    "sg:address":"336 New Albany Rd",
    "sg:city":"Moorestown",
    "sg:classifiers":[
        {
            "category":"Shopping",
            "subcategory":"Stationery & Office Supplies",
            "type":"Retail Goods"
        }
    ],
    "sg:phone":"+1 856 866 1400",
    "sg:postcode":"08057",
    "sg:province":"NJ",
    "wof:name":"S P Richards Co",
    "wof:placetype":"venue"
},
  "geometry": {"coordinates":[-74.97286699999999,39.965645],"type":"Point"}
}