{
  "type": "Feature",
  "properties": {
    "iso:country":"US",
    "sg:address":"2151 Zion Rd",
    "sg:city":"Northfield",
    "sg:classifiers":[
        {
            "category":"Organizations",
            "subcategory":"Religious Organization",
            "type":"Services"
        }
    ],
    "sg:phone":"+1 609 641 5009",
    "sg:postcode":"08225",
    "sg:province":"NJ",
    "wof:name":"Church Of The Nazarene",
    "wof:placetype":"venue"
},
  "geometry": {"coordinates":[-74.564998,39.369435],"type":"Point"}
}