{
  "type": "Feature",
  "properties": {
    "iso:country":"US",
    "sg:address":"708 N Cambridge Ave",
    "sg:city":"Ventnor City",
    "sg:classifiers":[
        {
            "category":"Building & Trades",
            "subcategory":"Construction",
            "type":"Services"
        }
    ],
    "sg:phone":"+1 609 822 1910",
    "sg:postcode":"08406",
    "sg:province":"NJ",
    "sg:tags":[
        "house"
    ],
    "wof:name":"Randys Remodeling Co",
    "wof:placetype":"venue"
},
  "geometry": {"coordinates":[-74.488332,39.349619],"type":"Point"}
}