{
  "type": "Feature",
  "properties": {
    "iso:country":"US",
    "sg:address":"90 New St",
    "sg:city":"New Brunswick",
    "sg:classifiers":[
        {
            "category":"Retail",
            "subcategory":"Photofinishing",
            "type":"Services"
        }
    ],
    "sg:phone":"+1 732 545 0260",
    "sg:postcode":"08901",
    "sg:province":"NJ",
    "sg:tags":[
        "photo",
        "finishing"
    ],
    "wof:name":"Colours",
    "wof:placetype":"venue"
},
  "geometry": {"coordinates":[-74.444738,40.492317],"type":"Point"}
}