{
  "type": "Feature",
  "properties": {
    "iso:country":"US",
    "sg:address":"9 de Young Dr",
    "sg:city":"Little Falls",
    "sg:classifiers":[
        {
            "category":"Manufacturing",
            "subcategory":"Jewelry",
            "type":"Manufacturing & Wholesale Goods"
        }
    ],
    "sg:phone":"+1 973 746 5293",
    "sg:postcode":"07424",
    "sg:province":"NJ",
    "sg:tags":[
        "manufacture",
        "retail"
    ],
    "wof:name":"Bead-Jeweled",
    "wof:placetype":"venue"
},
  "geometry": {"coordinates":[-74.215985,40.875748],"type":"Point"}
}