{
  "type": "Feature",
  "properties": {
    "iso:country":"US",
    "sg:address":"769 High Mountain Rd",
    "sg:city":"Haledon",
    "sg:classifiers":[
        {
            "category":"Personal",
            "subcategory":"Beauty Salon",
            "type":"Services"
        }
    ],
    "sg:phone":"+1 973 427 1256",
    "sg:postcode":"07508",
    "sg:province":"NJ",
    "sg:tags":[
        "shop"
    ],
    "wof:name":"Clip & Curl",
    "wof:placetype":"venue"
},
  "geometry": {"coordinates":[-74.18680000000001,40.964247],"type":"Point"}
}