{
  "type": "Feature",
  "properties": {
    "addr:full":"283 Main St Hackensack NJ 07601",
    "addr:housenumber":"283",
    "addr:postcode":"07601",
    "addr:street":"Main St",
    "iso:country":"US",
    "sg:address":"283 Main St",
    "sg:city":"Hackensack",
    "sg:classifiers":[
        {
            "category":"Education",
            "subcategory":"Music School",
            "type":"Public Place"
        }
    ],
    "sg:phone":"+1 201 525 1606",
    "sg:postcode":"07601",
    "sg:province":"NJ",
    "sg:tags":[
        "instrument",
        "teacher",
        "musical"
    ],
    "sg:website":"www.musicallyyours.com",
    "wof:name":"Musically Yours Inc",
    "wof:placetype":"venue"
},
  "geometry": {"coordinates":[-74.041397,40.887199],"type":"Point"}
}