{
  "type": "Feature",
  "properties": {
    "iso:country":"US",
    "sg:address":"1022 Berkley Rd",
    "sg:city":"Gibbstown",
    "sg:classifiers":[
        {
            "category":"Freight",
            "type":"Transportation"
        }
    ],
    "sg:phone":"+1 856 423 2323",
    "sg:postcode":"08027",
    "sg:province":"NJ",
    "sg:tags":[
        "operator",
        "trucking"
    ],
    "wof:name":"Marselle Construction Inc",
    "wof:placetype":"venue"
},
  "geometry": {"coordinates":[-75.251873,39.825251],"type":"Point"}
}