{
  "type": "Feature",
  "properties": {
    "addr:full":"189 Washington Ave Belleville NJ 07109",
    "addr:housenumber":"189",
    "addr:postcode":"07109",
    "addr:street":"Washington Ave",
    "iso:country":"US",
    "sg:address":"189 Washington Ave",
    "sg:city":"Belleville",
    "sg:classifiers":[
        {
            "category":"Cinema",
            "subcategory":"Movie Rental",
            "type":"Entertainment"
        }
    ],
    "sg:phone":"+1 973 450 4555",
    "sg:postcode":"07109",
    "sg:province":"NJ",
    "sg:tags":[
        "game",
        "video"
    ],
    "wof:name":"West Coast Video",
    "wof:placetype":"venue"
},
  "geometry": {"coordinates":[-74.152603,40.788502],"type":"Point"}
}