{
  "type": "Feature",
  "properties": {
    "iso:country":"US",
    "sg:address":"23 Erica Lynne Way",
    "sg:city":"Trenton",
    "sg:classifiers":[
        {
            "category":"Wholesale",
            "subcategory":"Groceries",
            "type":"Manufacturing & Wholesale Goods"
        }
    ],
    "sg:phone":"+1 609 581 0771",
    "sg:postcode":"08690",
    "sg:province":"NJ",
    "sg:tags":[
        "confectionery"
    ],
    "wof:name":"August Business Company",
    "wof:placetype":"venue"
},
  "geometry": {"coordinates":[-74.68348899999999,40.207118],"type":"Point"}
}