{
  "type": "Feature",
  "properties": {
    "addr:full":"11 Peachtree Ln Englishtown NJ 07726",
    "addr:housenumber":"11",
    "addr:postcode":"07726",
    "addr:street":"Peachtree Ln",
    "iso:country":"US",
    "sg:address":"11 Peachtree Ln",
    "sg:city":"Englishtown",
    "sg:classifiers":[
        {
            "category":"Professional",
            "subcategory":"Management & Consulting",
            "type":"Services"
        }
    ],
    "sg:phone":"+1   ",
    "sg:postcode":"07726",
    "sg:province":"NJ",
    "sg:tags":[
        "business"
    ],
    "wof:name":"Isy Consulting Services Inc",
    "wof:placetype":"venue"
},
  "geometry": {"coordinates":[-74.339662,40.237057],"type":"Point"}
}