{
  "type": "Feature",
  "properties": {
    "iso:country":"US",
    "sg:address":"228 Washington Ave",
    "sg:city":"Clifton",
    "sg:classifiers":[
        {
            "category":"Manufacturing",
            "subcategory":"Signs",
            "type":"Manufacturing & Wholesale Goods"
        }
    ],
    "sg:phone":"+1 973 458 0900",
    "sg:postcode":"07011",
    "sg:province":"NJ",
    "wof:name":"Alliance Sign Co",
    "wof:placetype":"venue"
},
  "geometry": {"coordinates":[-74.149699,40.87701],"type":"Point"}
}