{
  "type": "Feature",
  "properties": {
    "iso:country":"US",
    "sg:address":"103 12th St",
    "sg:city":"Beach Haven",
    "sg:classifiers":[
        {
            "category":"Shopping",
            "subcategory":"Hobbies, Toys, & Games",
            "type":"Retail Goods"
        }
    ],
    "sg:phone":"+1   ",
    "sg:postcode":"08008",
    "sg:province":"NJ",
    "wof:name":"Kite Store",
    "wof:placetype":"venue"
},
  "geometry": {"coordinates":[-74.233018,39.570632],"type":"Point"}
}