{
  "type": "Feature",
  "properties": {
    "addr:full":"408 Oak Ave Berlin NJ 08009",
    "addr:housenumber":"408",
    "addr:postcode":"08009",
    "addr:street":"Oak Ave",
    "iso:country":"US",
    "sg:address":"408 Oak Ave",
    "sg:city":"Berlin",
    "sg:classifiers":[
        {
            "category":"Personal",
            "subcategory":"Barber",
            "type":"Services"
        }
    ],
    "sg:phone":"+1 856 768 9949",
    "sg:postcode":"08009",
    "sg:province":"NJ",
    "wof:name":"Venables Emergency Bathroom Cleaning Service",
    "wof:placetype":"venue"
},
  "geometry": {"coordinates":[-74.93289900000001,39.784401],"type":"Point"}
}