{
  "type": "Feature",
  "properties": {
    "addr:full":"14 Rosewood Dr Howell NJ 07731",
    "addr:housenumber":"14",
    "addr:postcode":"07731",
    "addr:street":"Rosewood Dr",
    "iso:country":"US",
    "sg:address":"14 Rosewood Dr",
    "sg:city":"Howell",
    "sg:classifiers":[
        {
            "category":"Building & Trades",
            "subcategory":"Cleaning & Sanitation",
            "type":"Services"
        }
    ],
    "sg:phone":"+1 732 294 7927",
    "sg:postcode":"07731",
    "sg:province":"NJ",
    "sg:tags":[
        "janitor"
    ],
    "wof:name":"Wrightway Cleaning Svc Inc",
    "wof:placetype":"venue"
},
  "geometry": {"coordinates":[-74.266358,40.197702],"type":"Point"}
}