{
  "type": "Feature",
  "properties": {
    "addr:full":"57 Kennedy Rd Andover NJ 07821",
    "addr:housenumber":"57",
    "addr:postcode":"07821",
    "addr:street":"Kennedy Rd",
    "iso:country":"US",
    "sg:address":"57 Kennedy Rd",
    "sg:city":"Andover",
    "sg:classifiers":[
        {
            "category":"Building & Trades",
            "subcategory":"Construction",
            "type":"Services"
        }
    ],
    "sg:phone":"+1 908 813 1381",
    "sg:postcode":"07821",
    "sg:province":"NJ",
    "sg:tags":[
        "painter"
    ],
    "wof:name":"Top To Bottom Finishing",
    "wof:placetype":"venue"
},
  "geometry": {"coordinates":[-74.804559,40.951811],"type":"Point"}
}