{
  "type": "Feature",
  "properties": {
    "addr:full":"3 Overhill Rd Verona NJ 07044",
    "addr:housenumber":"3",
    "addr:postcode":"07044",
    "addr:street":"Overhill Rd",
    "iso:country":"US",
    "sg:address":"3 Overhill Rd",
    "sg:city":"Verona",
    "sg:classifiers":[
        {
            "category":"Building & Trades",
            "subcategory":"Construction",
            "type":"Services"
        }
    ],
    "sg:phone":"+1 973 857 0507",
    "sg:postcode":"07044",
    "sg:province":"NJ",
    "sg:tags":[
        "masonry",
        "restoration",
        "contractor"
    ],
    "wof:name":"Graciano Corporation",
    "wof:placetype":"venue"
},
  "geometry": {"coordinates":[-74.23300999999999,40.829687],"type":"Point"}
}