{
  "type": "Feature",
  "properties": {
    "addr:full":"1989 Haines Ave Union NJ 07083",
    "addr:housenumber":"1989",
    "addr:postcode":"07083",
    "addr:street":"Haines Ave",
    "iso:country":"US",
    "sg:address":"1989 Haines Ave",
    "sg:city":"Union",
    "sg:classifiers":[
        {
            "category":"Real Estate",
            "subcategory":"Real Estate Agent",
            "type":"Services"
        }
    ],
    "sg:phone":"+1   ",
    "sg:postcode":"07083",
    "sg:province":"NJ",
    "wof:name":"Sweeney Real Estate",
    "wof:placetype":"venue"
},
  "geometry": {"coordinates":[-74.265615,40.698676],"type":"Point"}
}