{
  "type": "Feature",
  "properties": {
    "iso:country":"US",
    "sg:address":"6 Saddle Dr",
    "sg:city":"Saddle River",
    "sg:classifiers":[
        {
            "category":"Professional",
            "type":"Services"
        }
    ],
    "sg:phone":"+1 201 785 1640",
    "sg:postcode":"07444",
    "sg:province":"NJ",
    "sg:tags":[
        "establishment"
    ],
    "wof:name":"Pinnacle Communities LTD",
    "wof:placetype":"venue"
},
  "geometry": {"coordinates":[-74.310182,40.970867],"type":"Point"}
}