{
  "type": "Feature",
  "properties": {
    "iso:country":"US",
    "sg:address":"555 US Hwy 1",
    "sg:city":"Iselin",
    "sg:classifiers":[
        {
            "category":"Organizations",
            "subcategory":"Community Association",
            "type":"Services"
        }
    ],
    "sg:phone":"+1   ",
    "sg:postcode":"08830",
    "sg:province":"NJ",
    "sg:tags":[
        "union"
    ],
    "wof:name":"Seiu 1199 NJ Healthcare Un",
    "wof:placetype":"venue"
},
  "geometry": {"coordinates":[-74.305458,40.558714],"type":"Point"}
}