{
  "type": "Feature",
  "properties": {
    "iso:country":"US",
    "sg:address":"236 Billingsport Rd",
    "sg:city":"Paulsboro",
    "sg:classifiers":[
        {
            "category":"Arena",
            "subcategory":"Sports Club",
            "type":"Entertainment"
        }
    ],
    "sg:phone":"+1 856 224 1448",
    "sg:postcode":"08066",
    "sg:province":"NJ",
    "wof:name":"Paulsboro Youth Soccer Assoc",
    "wof:placetype":"venue"
},
  "geometry": {"coordinates":[-75.244176,39.848062],"type":"Point"}
}