{
  "type": "Feature",
  "properties": {
    "addr:full":"127 Passaic St Passaic NJ 07055",
    "addr:housenumber":"127",
    "addr:postcode":"07055",
    "addr:street":"Passaic St",
    "iso:country":"US",
    "sg:address":"127 Passaic St",
    "sg:city":"Passaic",
    "sg:classifiers":[
        {
            "category":"Food & Beverages",
            "subcategory":"Groceries & Convenience Stores",
            "type":"Retail Goods"
        }
    ],
    "sg:phone":"+1   ",
    "sg:postcode":"07055",
    "sg:province":"NJ",
    "wof:name":"Crebeare Grocery",
    "wof:placetype":"venue"
},
  "geometry": {"coordinates":[-74.112843,40.86239],"type":"Point"}
}