{
  "type": "Feature",
  "properties": {
    "iso:country":"US",
    "sg:address":"601 South Ave E",
    "sg:city":"Cranford",
    "sg:classifiers":[
        {
            "category":"Freight",
            "type":"Transportation"
        }
    ],
    "sg:phone":"+1 908 709 0001",
    "sg:postcode":"07016",
    "sg:province":"NJ",
    "sg:tags":[
        "operator",
        "local",
        "trucking"
    ],
    "sg:website":"www.ustoreit.com",
    "wof:name":"U-Store-It",
    "wof:placetype":"venue"
},
  "geometry": {"coordinates":[-74.287902,40.656837],"type":"Point"}
}