{
  "type": "Feature",
  "properties": {
    "addr:full":"437 Pompton Ave Cedar Grove NJ 07009",
    "addr:housenumber":"437",
    "addr:postcode":"07009",
    "addr:street":"Pompton Ave",
    "iso:country":"US",
    "sg:address":"437 Pompton Ave",
    "sg:city":"Cedar Grove",
    "sg:classifiers":[
        {
            "category":"Education",
            "subcategory":"Preschool",
            "type":"Public Place"
        },
        {
            "category":"Education",
            "subcategory":"School",
            "type":"Public Place"
        }
    ],
    "sg:phone":"+1 973 239 3442",
    "sg:postcode":"07009",
    "sg:province":"NJ",
    "sg:tags":[
        "elementary"
    ],
    "wof:name":"Children's House-Children's World Magazine",
    "wof:placetype":"venue"
},
  "geometry": {"coordinates":[-74.228996,40.848202],"type":"Point"}
}