{
  "type": "Feature",
  "properties": {
    "iso:country":"US",
    "sg:address":"17 Hanover Rd",
    "sg:city":"Florham Park",
    "sg:classifiers":[
        {
            "category":"Professional",
            "subcategory":"Lawyer & Legal Services",
            "type":"Services"
        }
    ],
    "sg:phone":"+1 973 822 0500",
    "sg:postcode":"07932",
    "sg:province":"NJ",
    "wof:name":"Schaffer Steven J Attorney",
    "wof:placetype":"venue"
},
  "geometry": {"coordinates":[-74.386101,40.788601],"type":"Point"}
}