{
  "type": "Feature",
  "properties": {
    "addr:full":"276 Ridge Rd Watchung NJ 07069",
    "addr:housenumber":"276",
    "addr:postcode":"07069",
    "addr:street":"Ridge Rd",
    "iso:country":"US",
    "sg:address":"276 Ridge Rd",
    "sg:city":"Watchung",
    "sg:classifiers":[
        {
            "category":"Organizations",
            "subcategory":"Membership Organization",
            "type":"Services"
        }
    ],
    "sg:phone":"+1 908 668 4993",
    "sg:postcode":"07069",
    "sg:province":"NJ",
    "wof:name":"Provider Appreciation Day",
    "wof:placetype":"venue"
},
  "geometry": {"coordinates":[-74.442913,40.651692],"type":"Point"}
}