{
  "type": "Feature",
  "properties": {
    "addr:full":"10 Greenwood Lake Tpke Pompton Lakes NJ 07442",
    "addr:housenumber":"10",
    "addr:postcode":"07442",
    "addr:street":"Greenwood Lake Tpke",
    "iso:country":"US",
    "sg:address":"10 Greenwood Lake Tpke",
    "sg:city":"Pompton Lakes",
    "sg:classifiers":[
        {
            "category":"Health Services",
            "subcategory":"Dentist",
            "type":"Services"
        }
    ],
    "sg:phone":"+1 973 835 3900",
    "sg:postcode":"07442",
    "sg:province":"NJ",
    "wof:name":"Pergolizzi John N DMD",
    "wof:placetype":"venue"
},
  "geometry": {"coordinates":[-74.284897,41.000099],"type":"Point"}
}