{
  "type": "Feature",
  "properties": {
    "addr:full":"67 Washington Ave Morristown NJ 07960",
    "addr:housenumber":"67",
    "addr:postcode":"07960",
    "addr:street":"Washington Ave",
    "iso:country":"US",
    "sg:address":"67 Washington Ave",
    "sg:city":"Morristown",
    "sg:classifiers":[
        {
            "category":"Local Transit",
            "type":"Transportation"
        }
    ],
    "sg:phone":"+1 973 539 1621",
    "sg:postcode":"07960",
    "sg:province":"NJ",
    "sg:tags":[
        "limousine"
    ],
    "wof:name":"Alpine Livery Co",
    "wof:placetype":"venue"
},
  "geometry": {"coordinates":[-74.46503800000001,40.795228],"type":"Point"}
}