{
  "type": "Feature",
  "properties": {
    "addr:full":"88 Dorset Pl Somerdale NJ 08083",
    "addr:housenumber":"88",
    "addr:postcode":"08083",
    "addr:street":"Dorset Pl",
    "iso:country":"US",
    "sg:address":"88 Dorset Pl",
    "sg:city":"Somerdale",
    "sg:classifiers":[
        {
            "category":"Shopping",
            "subcategory":"Music",
            "type":"Retail Goods"
        }
    ],
    "sg:phone":"+1   ",
    "sg:postcode":"08083",
    "sg:province":"NJ",
    "wof:name":"Record Status",
    "wof:placetype":"venue"
},
  "geometry": {"coordinates":[-75.047827,39.839024],"type":"Point"}
}