{
  "type": "Feature",
  "properties": {
    "iso:country":"US",
    "sg:address":"31 Harrison Ave",
    "sg:city":"Harrison",
    "sg:classifiers":[
        {
            "category":"Restaurant",
            "type":"Food & Drink"
        }
    ],
    "sg:phone":"+1 973 485 7750",
    "sg:postcode":"07029",
    "sg:province":"NJ",
    "sg:tags":[
        "seafood",
        "spanish"
    ],
    "sg:website":"www.spanishpavillion.com/",
    "wof:name":"Spanish Pavillion",
    "wof:placetype":"venue"
},
  "geometry": {"coordinates":[-74.164001,40.745499],"type":"Point"}
}