{
  "type": "Feature",
  "properties": {
    "addr:full":"423 Boulevard Hasbrouck Hts NJ 07604",
    "addr:housenumber":"423",
    "addr:postcode":"07604",
    "addr:street":"Boulevard",
    "iso:country":"US",
    "sg:address":"423 Boulevard",
    "sg:city":"Hasbrouck Hts",
    "sg:classifiers":[
        {
            "category":"Retail",
            "subcategory":"Portrait Studio",
            "type":"Services"
        }
    ],
    "sg:phone":"+1 201 393 9707",
    "sg:postcode":"07604",
    "sg:province":"NJ",
    "sg:tags":[
        "photographer"
    ],
    "wof:name":"Elite Photography Studio",
    "wof:placetype":"venue"
},
  "geometry": {"coordinates":[-74.071207,40.868801],"type":"Point"}
}