{
  "type": "Feature",
  "properties": {
    "iso:country":"US",
    "sg:address":"80 Spear St",
    "sg:city":"Oakland",
    "sg:classifiers":[
        {
            "category":"Wholesale",
            "subcategory":"Groceries",
            "type":"Manufacturing & Wholesale Goods"
        }
    ],
    "sg:phone":"+1 201 337 3336",
    "sg:postcode":"07436",
    "sg:province":"NJ",
    "sg:tags":[
        "general"
    ],
    "wof:name":"J & J Distributing",
    "wof:placetype":"venue"
},
  "geometry": {"coordinates":[-74.235715,41.015677],"type":"Point"}
}