{
  "type": "Feature",
  "properties": {
    "iso:country":"US",
    "sg:address":"1578 Main Ave",
    "sg:city":"Clifton",
    "sg:classifiers":[
        {
            "category":"Banks & Credit Unions",
            "subcategory":"Bank",
            "type":"Services"
        }
    ],
    "sg:phone":"+1   ",
    "sg:postcode":"07011",
    "sg:province":"NJ",
    "wof:name":"Great Falls Bank",
    "wof:placetype":"venue"
},
  "geometry": {"coordinates":[-74.149828,40.885034],"type":"Point"}
}