{
  "type": "Feature",
  "properties": {
    "iso:country":"US",
    "sg:address":"7610 13th Ave",
    "sg:city":"Brooklyn",
    "sg:classifiers":[
        {
            "category":"Retail",
            "subcategory":"Auto Rental",
            "type":"Services"
        }
    ],
    "sg:phone":"+1 718 680 2277",
    "sg:postcode":"11228",
    "sg:province":"NY",
    "sg:tags":[
        "car"
    ],
    "sg:website":"www.empireautoleasing.com",
    "wof:name":"Empire Auto Leasing",
    "wof:placetype":"venue"
},
  "geometry": {"coordinates":[-74.233497,40.619743],"type":"Point"}
}