{
  "type": "Feature",
  "properties": {
    "iso:country":"US",
    "sg:address":"255 Old New Brunswick Rd",
    "sg:city":"Piscataway",
    "sg:classifiers":[
        {
            "category":"Professional",
            "subcategory":"Management & Consulting",
            "type":"Services"
        }
    ],
    "sg:phone":"+1 732 981 1412",
    "sg:postcode":"08854",
    "sg:province":"NJ",
    "sg:tags":[
        "firm",
        "counselor",
        "public",
        "relations"
    ],
    "sg:website":"www.issuesinc.com",
    "wof:name":"Issues Inc",
    "wof:placetype":"venue"
},
  "geometry": {"coordinates":[-74.47490500000001,40.552335],"type":"Point"}
}