{
  "type": "Feature",
  "properties": {
    "addr:full":"611 Lakeside Ave Pompton Lakes NJ 07442",
    "addr:housenumber":"611",
    "addr:postcode":"07442",
    "addr:street":"Lakeside Ave",
    "iso:country":"US",
    "sg:address":"611 Lakeside Ave",
    "sg:city":"Pompton Lakes",
    "sg:classifiers":[
        {
            "category":"Building & Trades",
            "subcategory":"Construction",
            "type":"Services"
        }
    ],
    "sg:phone":"+1 973 835 0681",
    "sg:postcode":"07442",
    "sg:province":"NJ",
    "sg:tags":[
        "floor",
        "laying",
        "contractor"
    ],
    "wof:name":"Dan Sekula Flooring",
    "wof:placetype":"venue"
},
  "geometry": {"coordinates":[-74.276241,41.006931],"type":"Point"}
}