{
  "type": "Feature",
  "properties": {
    "iso:country":"US",
    "sg:address":"93 N Mountain Ave",
    "sg:city":"Montclair",
    "sg:classifiers":[
        {
            "category":"Arts & Performance",
            "subcategory":"Theater",
            "type":"Entertainment"
        }
    ],
    "sg:phone":"+1 973 744 1916",
    "sg:postcode":"07042",
    "sg:province":"NJ",
    "sg:tags":[
        "entertainer"
    ],
    "wof:name":"Children's Magic By Ron Owens",
    "wof:placetype":"venue"
},
  "geometry": {"coordinates":[-74.22010400000001,40.82433],"type":"Point"}
}