{
  "type": "Feature",
  "properties": {
    "addr:full":"148 Mountain Ave Warren NJ 07059",
    "addr:housenumber":"148",
    "addr:postcode":"07059",
    "addr:street":"Mountain Ave",
    "iso:country":"US",
    "sg:address":"148 Mountain Ave",
    "sg:city":"Warren",
    "sg:classifiers":[
        {
            "category":"Building & Trades",
            "subcategory":"Landscaping Services",
            "type":"Services"
        }
    ],
    "sg:phone":"+1 908 647 3371",
    "sg:postcode":"07059",
    "sg:province":"NJ",
    "sg:tags":[
        "landscape"
    ],
    "wof:name":"D & M Landscaping Inc",
    "wof:placetype":"venue"
},
  "geometry": {"coordinates":[-74.48688799999999,40.653223],"type":"Point"}
}