{
  "type": "Feature",
  "properties": {
    "addr:full":"5 Jessica Pl Randolph NJ 07869",
    "addr:housenumber":"5",
    "addr:postcode":"07869",
    "addr:street":"Jessica Pl",
    "iso:country":"US",
    "sg:address":"5 Jessica Pl",
    "sg:city":"Randolph",
    "sg:classifiers":[
        {
            "category":"Wholesale",
            "subcategory":"Non-durable Goods",
            "type":"Manufacturing & Wholesale Goods"
        }
    ],
    "sg:phone":"+1 973 328 3174",
    "sg:postcode":"07869",
    "sg:province":"NJ",
    "sg:tags":[
        "chemical",
        "merchandise",
        "general"
    ],
    "wof:name":"Bon Enterprises Inc",
    "wof:placetype":"venue"
},
  "geometry": {"coordinates":[-74.55120599999999,40.865591],"type":"Point"}
}