{
  "type": "Feature",
  "properties": {
    "iso:country":"US",
    "sg:address":"1561 Morris Ave",
    "sg:city":"Union",
    "sg:classifiers":[
        {
            "category":"Restaurant",
            "type":"Food & Drink"
        }
    ],
    "sg:phone":"+1 908 686 6886",
    "sg:postcode":"07083",
    "sg:province":"NJ",
    "sg:tags":[
        "sandwich"
    ],
    "wof:name":"I Love Bagels Of Union",
    "wof:placetype":"venue"
},
  "geometry": {"coordinates":[-74.252478,40.691376],"type":"Point"}
}