{
  "type": "Feature",
  "properties": {
    "iso:country":"US",
    "sg:address":"197 State Rte 18",
    "sg:city":"New Brunswick",
    "sg:classifiers":[
        {
            "category":"Social Services",
            "type":"Services"
        }
    ],
    "sg:phone":"+1 732 937 6800",
    "sg:postcode":"08901",
    "sg:province":"NJ",
    "sg:tags":[
        "organization",
        "welfare"
    ],
    "wof:name":"Service Centers-New JERSEY Inc",
    "wof:placetype":"venue"
},
  "geometry": {"coordinates":[-74.439429,40.494767],"type":"Point"}
}