{
  "type": "Feature",
  "properties": {
    "iso:country":"US",
    "sg:address":"4 Oak Ridge Rd",
    "sg:city":"Newfoundland",
    "sg:classifiers":[
        {
            "category":"Manufacturing",
            "subcategory":"Paper Products",
            "type":"Manufacturing & Wholesale Goods"
        }
    ],
    "sg:phone":"+1 973 697 0801",
    "sg:postcode":"07435",
    "sg:province":"NJ",
    "sg:tags":[
        "printing",
        "supply"
    ],
    "wof:name":"C R Technologies",
    "wof:placetype":"venue"
},
  "geometry": {"coordinates":[-74.464364,41.051451],"type":"Point"}
}