{
  "type": "Feature",
  "properties": {
    "iso:country":"US",
    "sg:address":"52 morris ave",
    "sg:city":"Summit",
    "sg:classifiers":[
        {
            "category":"Autos & Motor Vehicles",
            "subcategory":"Automobile Sales",
            "type":"Retail Goods"
        },
        {
            "category":"Taxi",
            "type":"Transportation"
        },
        {
            "category":"Airline",
            "type":"Transportation"
        }
    ],
    "sg:phone":"+1 732 548 1140",
    "sg:postcode":"07901",
    "sg:province":"NJ",
    "sg:tags":[
        "shuttle",
        "airport",
        "limo"
    ],
    "sg:website":"www.airporttransportation-newark.us",
    "wof:name":"Summit Metro Express @ summit",
    "wof:placetype":"venue"
},
  "geometry": {"coordinates":[-74.3425,40.7129],"type":"Point"}
}