{
  "type": "Feature",
  "properties": {
    "addr:full":"1715 Long Beach Blvd Surf City NJ 08008",
    "addr:housenumber":"1715",
    "addr:postcode":"08008",
    "addr:street":"Long Beach Blvd",
    "iso:country":"US",
    "sg:address":"1715 Long Beach Blvd",
    "sg:city":"Surf City",
    "sg:classifiers":[
        {
            "category":"Home & Garden",
            "subcategory":"Home Furnishings",
            "type":"Retail Goods"
        }
    ],
    "sg:phone":"+1 609 361 7200",
    "sg:postcode":"08008",
    "sg:province":"NJ",
    "sg:tags":[
        "lighting",
        "fixture"
    ],
    "wof:name":"Living Lightscapes",
    "wof:placetype":"venue"
},
  "geometry": {"coordinates":[-74.232038,39.574727],"type":"Point"}
}