{
  "type": "Feature",
  "properties": {
    "iso:country":"US",
    "sg:address":"492 S 20th St",
    "sg:city":"Newark",
    "sg:classifiers":[
        {
            "category":"Social Services",
            "subcategory":"Child Care",
            "type":"Services"
        }
    ],
    "sg:phone":"+1 973 399 1349",
    "sg:postcode":"07103",
    "sg:province":"NJ",
    "sg:tags":[
        "day"
    ],
    "wof:name":"Good Success Christian",
    "wof:placetype":"venue"
},
  "geometry": {"coordinates":[-74.210297,40.740795],"type":"Point"}
}