{
  "type": "Feature",
  "properties": {
    "iso:country":"US",
    "sg:address":"6 E Colton Ln",
    "sg:city":"Williamstown",
    "sg:classifiers":[
        {
            "category":"Professional",
            "type":"Services"
        }
    ],
    "sg:phone":"+1   ",
    "sg:postcode":"08094",
    "sg:province":"NJ",
    "wof:name":"Zeig",
    "wof:placetype":"venue"
},
  "geometry": {"coordinates":[-74.88167,39.594305],"type":"Point"}
}