{
  "type": "Feature",
  "properties": {
    "iso:country":"US",
    "sg:address":"8 Tulip Ln",
    "sg:city":"Randolph",
    "sg:classifiers":[
        {
            "category":"Professional",
            "subcategory":"Management & Consulting",
            "type":"Services"
        }
    ],
    "sg:phone":"+1   ",
    "sg:postcode":"07869",
    "sg:province":"NJ",
    "sg:tags":[
        "business"
    ],
    "wof:name":"Scott Rappeport Consultant",
    "wof:placetype":"venue"
},
  "geometry": {"coordinates":[-74.535522,40.828979],"type":"Point"}
}