{
  "type": "Feature",
  "properties": {
    "addr:full":"26 S Broad St Woodbury NJ 08096",
    "addr:housenumber":"26",
    "addr:postcode":"08096",
    "addr:street":"S Broad St",
    "iso:country":"US",
    "sg:address":"26 S Broad St",
    "sg:city":"Woodbury",
    "sg:classifiers":[
        {
            "category":"Shopping",
            "subcategory":"Discount & Variety Stores",
            "type":"Retail Goods"
        }
    ],
    "sg:phone":"+1   ",
    "sg:postcode":"08096",
    "sg:province":"NJ",
    "wof:name":"Dollar General",
    "wof:placetype":"venue"
},
  "geometry": {"coordinates":[-75.15356300000001,39.837643],"type":"Point"}
}