{
  "type": "Feature",
  "properties": {
    "iso:country":"US",
    "sg:address":"1297 Centennial Ave",
    "sg:city":"Piscataway",
    "sg:classifiers":[
        {
            "category":"Shopping",
            "subcategory":"Clothing, Apparel, & Fashions",
            "type":"Retail Goods"
        }
    ],
    "sg:phone":"+1 732 562 9449",
    "sg:postcode":"08854",
    "sg:province":"NJ",
    "sg:tags":[
        "wear",
        "formal"
    ],
    "wof:name":"After Hours Formalwear",
    "wof:placetype":"venue"
},
  "geometry": {"coordinates":[-74.450903,40.551992],"type":"Point"}
}