{
  "type": "Feature",
  "properties": {
    "iso:country":"US",
    "sg:address":"358 Fenlon Blvd",
    "sg:city":"Clifton",
    "sg:classifiers":[
        {
            "category":"Food & Beverages",
            "subcategory":"Liquor & Beverages",
            "type":"Retail Goods"
        }
    ],
    "sg:phone":"+1   ",
    "sg:postcode":"07014",
    "sg:province":"NJ",
    "sg:tags":[
        "alcoholic"
    ],
    "wof:name":"Karam Spirits Inc",
    "wof:placetype":"venue"
},
  "geometry": {"coordinates":[-74.136577,40.839204],"type":"Point"}
}