{
  "type": "Feature",
  "properties": {
    "addr:full":"430 Genesee St Trenton NJ 08611",
    "addr:housenumber":"430",
    "addr:postcode":"08611",
    "addr:street":"Genesee St",
    "iso:country":"US",
    "sg:address":"430 Genesee St",
    "sg:city":"Trenton",
    "sg:classifiers":[
        {
            "category":"Arts & Performance",
            "subcategory":"Theater",
            "type":"Entertainment"
        }
    ],
    "sg:phone":"+1   ",
    "sg:postcode":"08611",
    "sg:province":"NJ",
    "sg:tags":[
        "disc",
        "jockey"
    ],
    "wof:name":"Alpha Entertainment",
    "wof:placetype":"venue"
},
  "geometry": {"coordinates":[-74.746556,40.206611],"type":"Point"}
}