{
  "type": "Feature",
  "properties": {
    "addr:full":"251 S Main St Manville NJ 08835",
    "addr:housenumber":"251",
    "addr:postcode":"08835",
    "addr:street":"S Main St",
    "iso:country":"US",
    "sg:address":"251 S Main St",
    "sg:city":"Manville",
    "sg:classifiers":[
        {
            "category":"Shopping",
            "subcategory":"Jewelry",
            "type":"Retail Goods"
        }
    ],
    "sg:phone":"+1 908 218 7906",
    "sg:postcode":"08835",
    "sg:province":"NJ",
    "sg:tags":[
        "jeweler"
    ],
    "wof:name":"T & A Fine Jewelry",
    "wof:placetype":"venue"
},
  "geometry": {"coordinates":[-74.588291,40.53949],"type":"Point"}
}