{
  "type": "Feature",
  "properties": {
    "iso:country":"US",
    "sg:address":"300 N 27th St",
    "sg:city":"Camden",
    "sg:classifiers":[
        {
            "category":"Retail",
            "subcategory":"Self-service Laundry",
            "type":"Services"
        }
    ],
    "sg:phone":"+1 856 338 1185",
    "sg:postcode":"08105",
    "sg:province":"NJ",
    "wof:name":"Village Laundromat",
    "wof:placetype":"venue"
},
  "geometry": {"coordinates":[-75.08885600000001,39.949223],"type":"Point"}
}