{
  "type": "Feature",
  "properties": {
    "iso:country":"US",
    "sg:address":"58 Simpson Ave",
    "sg:city":"Pitman",
    "sg:classifiers":[
        {
            "category":"Professional",
            "subcategory":"Art Services",
            "type":"Services"
        }
    ],
    "sg:phone":"+1   ",
    "sg:postcode":"08071",
    "sg:province":"NJ",
    "sg:tags":[
        "photography",
        "commercial"
    ],
    "wof:name":"Budget Photography",
    "wof:placetype":"venue"
},
  "geometry": {"coordinates":[-75.13025500000001,39.733054],"type":"Point"}
}