{
  "type": "Feature",
  "properties": {
    "iso:country":"US",
    "sg:address":"33 N Haledon Ave",
    "sg:city":"North Haledon",
    "sg:classifiers":[
        {
            "category":"Professional",
            "type":"Services"
        }
    ],
    "sg:phone":"+1 973 689 6999",
    "sg:postcode":"07508",
    "sg:province":"NJ",
    "sg:tags":[
        "establishment"
    ],
    "wof:name":"OWR Opinion",
    "wof:placetype":"venue"
},
  "geometry": {"coordinates":[-74.182957,40.962198],"type":"Point"}
}