{
  "type": "Feature",
  "properties": {
    "addr:full":"70 Union St Medford NJ 08055",
    "addr:housenumber":"70",
    "addr:postcode":"08055",
    "addr:street":"Union St",
    "iso:country":"US",
    "sg:address":"70 Union St",
    "sg:city":"Medford",
    "sg:classifiers":[
        {
            "category":"Building & Trades",
            "subcategory":"Landscaping Services",
            "type":"Services"
        }
    ],
    "sg:phone":"+1 609 654 6162",
    "sg:postcode":"08055",
    "sg:province":"NJ",
    "sg:tags":[
        "landscape"
    ],
    "wof:name":"Sasaki Landscapes",
    "wof:placetype":"venue"
},
  "geometry": {"coordinates":[-74.82879699999999,39.898835],"type":"Point"}
}