{
  "type": "Feature",
  "properties": {
    "iso:country":"US",
    "sg:address":"15 James St",
    "sg:city":"Florham Park",
    "sg:classifiers":[
        {
            "category":"Health Services",
            "subcategory":"Doctor",
            "type":"Services"
        }
    ],
    "sg:phone":"+1 973 299 7388",
    "sg:postcode":"07932",
    "sg:province":"NJ",
    "sg:tags":[
        "physician",
        "surgeon"
    ],
    "wof:name":"Pain Care & Rehabilitation Ctr",
    "wof:placetype":"venue"
},
  "geometry": {"coordinates":[-74.386629,40.78861],"type":"Point"}
}