{
  "type": "Feature",
  "properties": {
    "iso:country":"US",
    "sg:address":"3 Chimney Rock Rd",
    "sg:city":"Bound Brook",
    "sg:classifiers":[
        {
            "category":"Shopping",
            "type":"Retail Goods"
        }
    ],
    "sg:phone":"+1   ",
    "sg:postcode":"08805",
    "sg:province":"NJ",
    "sg:tags":[
        "tombstone",
        "monument"
    ],
    "wof:name":"Bridgewater Marble & Gran LLC",
    "wof:placetype":"venue"
},
  "geometry": {"coordinates":[-74.56495700000001,40.562275],"type":"Point"}
}