{
  "type": "Feature",
  "properties": {
    "addr:full":"542 Morgan Ave Deptford NJ 08096",
    "addr:housenumber":"542",
    "addr:postcode":"08096",
    "addr:street":"Morgan Ave",
    "iso:country":"US",
    "sg:address":"542 Morgan Ave",
    "sg:city":"Deptford",
    "sg:classifiers":[
        {
            "category":"Local Transit",
            "type":"Transportation"
        }
    ],
    "sg:phone":"+1 856 853 6900",
    "sg:postcode":"08096",
    "sg:province":"NJ",
    "sg:tags":[
        "airport"
    ],
    "wof:name":"Archer's Airport Svc",
    "wof:placetype":"venue"
},
  "geometry": {"coordinates":[-75.14880700000001,39.827099],"type":"Point"}
}