{
  "type": "Feature",
  "properties": {
    "iso:country":"US",
    "sg:address":"186 Bloomfield Ave",
    "sg:city":"Newark",
    "sg:classifiers":[
        {
            "category":"Banks & Credit Unions",
            "subcategory":"Bank",
            "type":"Services"
        }
    ],
    "sg:phone":"+1 973 485 1400",
    "sg:postcode":"07104",
    "sg:province":"NJ",
    "sg:tags":[
        "loan",
        "real estate"
    ],
    "wof:name":"American Fidelity Mtg Corp",
    "wof:placetype":"venue"
},
  "geometry": {"coordinates":[-74.176759,40.760713],"type":"Point"}
}