{
  "type": "Feature",
  "properties": {
    "iso:country":"US",
    "sg:address":"232 Boulevard",
    "sg:city":"Hasbrouck Hts",
    "sg:classifiers":[
        {
            "category":"Professional",
            "subcategory":"Accounting & Tax Preparation",
            "type":"Services"
        }
    ],
    "sg:phone":"+1 201 288 4420",
    "sg:postcode":"07604",
    "sg:province":"NJ",
    "sg:tags":[
        "return",
        "filing"
    ],
    "wof:name":"Heights Tax & Accounting Svc",
    "wof:placetype":"venue"
},
  "geometry": {"coordinates":[-74.07696,40.863189],"type":"Point"}
}