{
  "type": "Feature",
  "properties": {
    "addr:full":"362 Grove St Jersey City NJ 07302",
    "addr:housenumber":"362",
    "addr:postcode":"07302",
    "addr:street":"Grove St",
    "iso:country":"US",
    "sg:address":"362 Grove St",
    "sg:city":"Jersey City",
    "sg:classifiers":[
        {
            "category":"Restaurant",
            "type":"Food & Drink"
        }
    ],
    "sg:menulink":"http://www.allmenus.com/nj/jersey-city/55350-jc-sakura/menu/",
    "sg:phone":"+1 201 217 8988",
    "sg:postcode":"07302",
    "sg:province":"NJ",
    "sg:tags":[
        "sushi",
        "japanese",
        "asian"
    ],
    "wof:name":"JC Sakura",
    "wof:placetype":"venue"
},
  "geometry": {"coordinates":[-74.04265599999999,40.721269],"type":"Point"}
}