{
  "type": "Feature",
  "properties": {
    "iso:country":"US",
    "sg:address":"620 State Rte 49",
    "sg:city":"Bridgeton",
    "sg:classifiers":[
        {
            "category":"Autos & Motor Vehicles",
            "subcategory":"Fuel & Gas Station",
            "type":"Retail Goods"
        }
    ],
    "sg:phone":"+1 856 451 3504",
    "sg:postcode":"08302",
    "sg:province":"NJ",
    "sg:tags":[
        "oil"
    ],
    "wof:name":"Durham's Major",
    "wof:placetype":"venue"
},
  "geometry": {"coordinates":[-75.215576,39.426244],"type":"Point"}
}