{
  "type": "Feature",
  "properties": {
    "addr:full":"588 Avenue C Bayonne NJ 07002",
    "addr:housenumber":"588",
    "addr:postcode":"07002",
    "addr:street":"Avenue C",
    "iso:country":"US",
    "sg:address":"588 Avenue C",
    "sg:city":"Bayonne",
    "sg:classifiers":[
        {
            "category":"Deli",
            "type":"Food & Drink"
        }
    ],
    "sg:phone":"+1 201 437 3884",
    "sg:postcode":"07002",
    "sg:province":"NJ",
    "wof:name":"Sawa Provision",
    "wof:placetype":"venue"
},
  "geometry": {"coordinates":[-74.11840100000001,40.6674],"type":"Point"}
}