{
  "type": "Feature",
  "properties": {
    "addr:full":"19 Staal Ln Lodi NJ 07644",
    "addr:housenumber":"19",
    "addr:postcode":"07644",
    "addr:street":"Staal Ln",
    "iso:country":"US",
    "sg:address":"19 Staal Ln",
    "sg:city":"Lodi",
    "sg:classifiers":[
        {
            "category":"Professional",
            "subcategory":"Management & Consulting",
            "type":"Services"
        }
    ],
    "sg:phone":"+1 973 591 0089",
    "sg:postcode":"07644",
    "sg:province":"NJ",
    "sg:tags":[
        "business"
    ],
    "wof:name":"Pryme Safety Services",
    "wof:placetype":"venue"
},
  "geometry": {"coordinates":[-74.08392000000001,40.865245],"type":"Point"}
}