{
  "type": "Feature",
  "properties": {
    "iso:country":"US",
    "sg:address":"1901 N Olden Ave Exd",
    "sg:city":"Trenton",
    "sg:classifiers":[
        {
            "category":"Professional",
            "subcategory":"Art Services",
            "type":"Services"
        }
    ],
    "sg:phone":"+1 609 434 0700",
    "sg:postcode":"08618",
    "sg:province":"NJ",
    "sg:tags":[
        "graphic",
        "designer"
    ],
    "wof:name":"PDGLCC",
    "wof:placetype":"venue"
},
  "geometry": {"coordinates":[-74.78371,40.251247],"type":"Point"}
}