{
  "type": "Feature",
  "properties": {
    "addr:full":"221 Bloomfield Ave Bloomfield NJ 07003",
    "addr:housenumber":"221",
    "addr:postcode":"07003",
    "addr:street":"Bloomfield Ave",
    "iso:country":"US",
    "sg:address":"221 Bloomfield Ave",
    "sg:city":"Bloomfield",
    "sg:classifiers":[
        {
            "category":"Personal",
            "subcategory":"Tanning Parlor",
            "type":"Services"
        }
    ],
    "sg:phone":"+1 973 680 8266",
    "sg:postcode":"07003",
    "sg:province":"NJ",
    "wof:name":"Electric Beach Tanning & Nail Salon",
    "wof:placetype":"venue"
},
  "geometry": {"coordinates":[-74.19119999999999,40.781898],"type":"Point"}
}