{
  "type": "Feature",
  "properties": {
    "iso:country":"US",
    "sg:address":"16 McCay Dr",
    "sg:city":"Roebling",
    "sg:classifiers":[
        {
            "category":"Organizations",
            "subcategory":"Labor Organization",
            "type":"Services"
        }
    ],
    "sg:phone":"+1 609 499 8013",
    "sg:postcode":"08554",
    "sg:province":"NJ",
    "wof:name":"Uswa",
    "wof:placetype":"venue"
},
  "geometry": {"coordinates":[-74.791594,40.113194],"type":"Point"}
}