{
  "type": "Feature",
  "properties": {
    "iso:country":"US",
    "sg:address":"3361 Lawrenceville Rd",
    "sg:city":"Princeton",
    "sg:classifiers":[
        {
            "category":"Health Services",
            "subcategory":"Health Practitioner",
            "type":"Services"
        },
        {
            "category":"Social Services",
            "type":"Services"
        }
    ],
    "sg:phone":"+1 609 921 6632",
    "sg:postcode":"08540",
    "sg:province":"NJ",
    "sg:tags":[
        "psychotherapist"
    ],
    "wof:name":"Roberta Ruliffson Acsw",
    "wof:placetype":"venue"
},
  "geometry": {"coordinates":[-74.702442,40.317964],"type":"Point"}
}