{
  "type": "Feature",
  "properties": {
    "iso:country":"US",
    "sg:address":"1361 Fairview Blvd Ste K",
    "sg:city":"Delran",
    "sg:classifiers":[
        {
            "category":"Shopping",
            "subcategory":"Florist",
            "type":"Retail Goods"
        }
    ],
    "sg:phone":"+1 856 764 1375",
    "sg:postcode":"08075",
    "sg:province":"NJ",
    "wof:name":"Delran Flowers & Gifts",
    "wof:placetype":"venue"
},
  "geometry": {"coordinates":[-74.947923,40.023924],"type":"Point"}
}