{
  "type": "Feature",
  "properties": {
    "iso:country":"US",
    "sg:address":"702 Anderson Ave",
    "sg:city":"Cliffside Park",
    "sg:classifiers":[
        {
            "category":"Professional",
            "type":"Services"
        },
        {
            "category":"Deli",
            "type":"Food & Drink"
        }
    ],
    "sg:phone":"+1 201 941 1919",
    "sg:postcode":"07010",
    "sg:province":"NJ",
    "sg:tags":[
        "caterer"
    ],
    "wof:name":"La Deliziosa",
    "wof:placetype":"venue"
},
  "geometry": {"coordinates":[-73.986068,40.828449],"type":"Point"}
}