{
  "type": "Feature",
  "properties": {
    "iso:country":"US",
    "sg:address":"245 N White Horse Pike",
    "sg:city":"Hammonton",
    "sg:classifiers":[
        {
            "category":"Real Estate",
            "subcategory":"Real Estate Agent",
            "type":"Services"
        }
    ],
    "sg:phone":"+1 609 561 7625",
    "sg:postcode":"08037",
    "sg:province":"NJ",
    "wof:name":"Littlefield Real Estate",
    "wof:placetype":"venue"
},
  "geometry": {"coordinates":[-74.79719900000001,39.653298],"type":"Point"}
}