{
  "type": "Feature",
  "properties": {
    "addr:full":"822 Raritan Ave Highland Park NJ 08904",
    "addr:housenumber":"822",
    "addr:postcode":"08904",
    "addr:street":"Raritan Ave",
    "iso:country":"US",
    "sg:address":"822 Raritan Ave",
    "sg:city":"Highland Park",
    "sg:classifiers":[
        {
            "category":"Real Estate",
            "subcategory":"Real Estate Agent",
            "type":"Services"
        }
    ],
    "sg:phone":"+1   ",
    "sg:postcode":"08904",
    "sg:province":"NJ",
    "wof:name":"Laurano Marc W Preferred Prpts",
    "wof:placetype":"venue"
},
  "geometry": {"coordinates":[-74.42075699999999,40.502003],"type":"Point"}
}