{
  "type": "Feature",
  "properties": {
    "iso:country":"US",
    "sg:address":"135 Beach St",
    "sg:city":"Rockaway",
    "sg:classifiers":[
        {
            "category":"Professional",
            "subcategory":"Lawyer & Legal Services",
            "type":"Services"
        }
    ],
    "sg:phone":"+1 973 625 9124",
    "sg:postcode":"07866",
    "sg:province":"NJ",
    "sg:tags":[
        "attorney"
    ],
    "wof:name":"Roma K Oster",
    "wof:placetype":"venue"
},
  "geometry": {"coordinates":[-74.503911,40.902167],"type":"Point"}
}