{
  "type": "Feature",
  "properties": {
    "addr:full":"636 River Rd Fair Haven NJ 07704",
    "addr:housenumber":"636",
    "addr:postcode":"07704",
    "addr:street":"River Rd",
    "iso:country":"US",
    "sg:address":"636 River Rd",
    "sg:city":"Fair Haven",
    "sg:classifiers":[
        {
            "category":"Banks & Credit Unions",
            "subcategory":"Bank",
            "type":"Services"
        }
    ],
    "sg:phone":"+1 732 933 4445",
    "sg:postcode":"07704",
    "sg:province":"NJ",
    "sg:website":"www.rfhbank.com",
    "wof:name":"Rumson Fairhaven Bank & Trust",
    "wof:placetype":"venue"
},
  "geometry": {"coordinates":[-74.040684,40.361831],"type":"Point"}
}