{
  "type": "Feature",
  "properties": {
    "addr:full":"513 Balsam Rd Cherry Hill NJ 08003",
    "addr:housenumber":"513",
    "addr:postcode":"08003",
    "addr:street":"Balsam Rd",
    "iso:country":"US",
    "sg:address":"513 Balsam Rd",
    "sg:city":"Cherry Hill",
    "sg:classifiers":[
        {
            "category":"Cinema",
            "subcategory":"Movie Rental",
            "type":"Entertainment"
        }
    ],
    "sg:phone":"+1 856 429 6146",
    "sg:postcode":"08003",
    "sg:province":"NJ",
    "sg:tags":[
        "video",
        "tape"
    ],
    "wof:name":"Video Today Productions",
    "wof:placetype":"venue"
},
  "geometry": {"coordinates":[-74.979843,39.87098],"type":"Point"}
}