{
  "type": "Feature",
  "properties": {
    "addr:full":"4 Mount Laurel Rd Mt Laurel NJ 08054",
    "addr:housenumber":"4",
    "addr:postcode":"08054",
    "addr:street":"Mount Laurel Rd",
    "iso:country":"US",
    "sg:address":"4 Mount Laurel Rd",
    "sg:city":"Mt Laurel",
    "sg:classifiers":[
        {
            "category":"Professional",
            "subcategory":"Secretarial Services",
            "type":"Services"
        }
    ],
    "sg:phone":"+1 856 722 0047",
    "sg:postcode":"08054",
    "sg:province":"NJ",
    "sg:tags":[
        "resume"
    ],
    "wof:name":"Typing Unlimited",
    "wof:placetype":"venue"
},
  "geometry": {"coordinates":[-74.929625,39.960198],"type":"Point"}
}