{
  "type": "Feature",
  "properties": {
    "addr:full":"2089 State Rte 88 Brick NJ 08724",
    "addr:housenumber":"2089",
    "addr:postcode":"08724",
    "addr:street":"State Rte 88",
    "iso:country":"US",
    "sg:address":"2089 State Rte 88",
    "sg:city":"Brick",
    "sg:classifiers":[
        {
            "category":"Shopping",
            "subcategory":"Pharmacy",
            "type":"Retail Goods"
        }
    ],
    "sg:phone":"+1 732 899 4400",
    "sg:postcode":"08724",
    "sg:province":"NJ",
    "wof:name":"Eckerd",
    "wof:placetype":"venue"
},
  "geometry": {"coordinates":[-74.10537600000001,40.075714],"type":"Point"}
}