{
  "type": "Feature",
  "properties": {
    "iso:country":"US",
    "sg:address":"732 Union Ave",
    "sg:city":"Middlesex",
    "sg:classifiers":[
        {
            "category":"Retail",
            "subcategory":"Repair Shop",
            "type":"Services"
        }
    ],
    "sg:phone":"+1   ",
    "sg:postcode":"08846",
    "sg:province":"NJ",
    "wof:name":"01 All Day A Emergency Locksmi",
    "wof:placetype":"venue"
},
  "geometry": {"coordinates":[-74.507873,40.575964],"type":"Point"}
}