{
  "type": "Feature",
  "properties": {
    "iso:country":"US",
    "sg:address":"1906 Old Mill Rd",
    "sg:city":"Wall",
    "sg:classifiers":[
        {
            "category":"Building & Trades",
            "subcategory":"Construction",
            "type":"Services"
        }
    ],
    "sg:phone":"+1 732 974 0883",
    "sg:postcode":"07719",
    "sg:province":"NJ",
    "sg:tags":[
        "contractor"
    ],
    "wof:name":"Neighbour & Groves Builders",
    "wof:placetype":"venue"
},
  "geometry": {"coordinates":[-74.051312,40.160761],"type":"Point"}
}