{
  "type": "Feature",
  "properties": {
    "iso:country":"US",
    "sg:address":"522 Brighton Ave",
    "sg:city":"Spring Lake",
    "sg:classifiers":[
        {
            "category":"Banks & Credit Unions",
            "subcategory":"Financial Services",
            "type":"Services"
        }
    ],
    "sg:phone":"+1 732 974 2881",
    "sg:postcode":"07762",
    "sg:province":"NJ",
    "sg:tags":[
        "international",
        "trade"
    ],
    "wof:name":"Axel Trading Co",
    "wof:placetype":"venue"
},
  "geometry": {"coordinates":[-74.033085,40.155437],"type":"Point"}
}