{
  "type": "Feature",
  "properties": {
    "addr:full":"16 Weatherby Ave Clarksboro NJ 08020",
    "addr:housenumber":"16",
    "addr:postcode":"08020",
    "addr:street":"Weatherby Ave",
    "iso:country":"US",
    "sg:address":"16 Weatherby Ave",
    "sg:city":"Clarksboro",
    "sg:classifiers":[
        {
            "category":"Building & Trades",
            "subcategory":"Construction",
            "type":"Services"
        }
    ],
    "sg:phone":"+1 856 423 6030",
    "sg:postcode":"08020",
    "sg:province":"NJ",
    "sg:tags":[
        "contractor"
    ],
    "wof:name":"Glover Construction",
    "wof:placetype":"venue"
},
  "geometry": {"coordinates":[-75.220715,39.800014],"type":"Point"}
}