{
  "type": "Feature",
  "properties": {
    "iso:country":"US",
    "sg:address":"14 Euclid Ter",
    "sg:city":"Parsippany",
    "sg:classifiers":[
        {
            "category":"Real Estate",
            "subcategory":"Real Estate Agent",
            "type":"Services"
        }
    ],
    "sg:phone":"+1   ",
    "sg:postcode":"07054",
    "sg:province":"NJ",
    "sg:tags":[
        "company",
        "holding"
    ],
    "wof:name":"Lustig Enterprises",
    "wof:placetype":"venue"
},
  "geometry": {"coordinates":[-74.394473,40.876242],"type":"Point"}
}