{
  "type": "Feature",
  "properties": {
    "addr:full":"229 Broad St Elizabeth NJ 07201",
    "addr:housenumber":"229",
    "addr:postcode":"07201",
    "addr:street":"Broad St",
    "iso:country":"US",
    "sg:address":"229 Broad St",
    "sg:city":"Elizabeth",
    "sg:classifiers":[
        {
            "category":"Taxi",
            "type":"Transportation"
        }
    ],
    "sg:phone":"+1 908 354 0350",
    "sg:postcode":"07201",
    "sg:province":"NJ",
    "sg:tags":[
        "taxicab"
    ],
    "wof:name":"Yellow Cab",
    "wof:placetype":"venue"
},
  "geometry": {"coordinates":[-74.21506100000001,40.66674],"type":"Point"}
}