{
  "type": "Feature",
  "properties": {
    "addr:full":"395 Reading Ave Pennington NJ 08534",
    "addr:housenumber":"395",
    "addr:postcode":"08534",
    "addr:street":"Reading Ave",
    "iso:country":"US",
    "sg:address":"395 Reading Ave",
    "sg:city":"Pennington",
    "sg:classifiers":[
        {
            "category":"Government",
            "subcategory":"Office",
            "type":"Public Place"
        }
    ],
    "sg:phone":"+1 609 737 3855",
    "sg:postcode":"08534",
    "sg:province":"NJ",
    "wof:name":"Hopewell Valley Senior Ctr",
    "wof:placetype":"venue"
},
  "geometry": {"coordinates":[-74.79610700000001,40.320197],"type":"Point"}
}