{
  "type": "Feature",
  "properties": {
    "iso:country":"US",
    "sg:address":"2502 Palisade Ave",
    "sg:city":"Weehawken",
    "sg:classifiers":[
        {
            "category":"Sports & Exercise",
            "subcategory":"Gym",
            "type":"Entertainment"
        }
    ],
    "sg:phone":"+1 201 583 0500",
    "sg:postcode":"07086",
    "sg:province":"NJ",
    "sg:tags":[
        "trainer"
    ],
    "sg:website":"www.findawayfitness.com",
    "wof:name":"Find A Way Fitness",
    "wof:placetype":"venue"
},
  "geometry": {"coordinates":[-74.029268,40.76722],"type":"Point"}
}