{
  "type": "Feature",
  "properties": {
    "addr:full":"1550 Kearney Dr North Brunswick NJ 08902",
    "addr:housenumber":"1550",
    "addr:postcode":"08902",
    "addr:street":"Kearney Dr",
    "iso:country":"US",
    "sg:address":"1550 Kearney Dr",
    "sg:city":"North Brunswick",
    "sg:classifiers":[
        {
            "category":"Professional",
            "type":"Services"
        }
    ],
    "sg:phone":"+1 732 821 1413",
    "sg:postcode":"08902",
    "sg:province":"NJ",
    "sg:tags":[
        "establishment"
    ],
    "wof:name":"Forklift Headquarters",
    "wof:placetype":"venue"
},
  "geometry": {"coordinates":[-74.465694,40.444009],"type":"Point"}
}