{
  "type": "Feature",
  "properties": {
    "iso:country":"US",
    "sg:address":"12 Ward St",
    "sg:city":"Fair Lawn",
    "sg:classifiers":[
        {
            "category":"Building & Trades",
            "subcategory":"Construction",
            "type":"Services"
        }
    ],
    "sg:phone":"+1 201 796 8562",
    "sg:postcode":"07410",
    "sg:province":"NJ",
    "sg:tags":[
        "contractor"
    ],
    "wof:name":"Leak Master Roofing",
    "wof:placetype":"venue"
},
  "geometry": {"coordinates":[-74.115679,40.929116],"type":"Point"}
}