{
  "type": "Feature",
  "properties": {
    "iso:country":"US",
    "sg:address":"97 E Allendale Rd",
    "sg:city":"Saddle River",
    "sg:classifiers":[
        {
            "category":"Education",
            "subcategory":"School",
            "type":"Public Place"
        }
    ],
    "sg:phone":"+1   ",
    "sg:postcode":"07458",
    "sg:province":"NJ",
    "sg:website":"www.wandellschool.org",
    "wof:name":"Wandell Elementary School",
    "wof:placetype":"venue"
},
  "geometry": {"coordinates":[-74.096992,41.031568],"type":"Point"}
}