{
  "type": "Feature",
  "properties": {
    "addr:full":"17 Washington St Toms River NJ 08753",
    "addr:housenumber":"17",
    "addr:postcode":"08753",
    "addr:street":"Washington St",
    "iso:country":"US",
    "sg:address":"17 Washington St",
    "sg:city":"Toms River",
    "sg:classifiers":[
        {
            "category":"Utilities",
            "subcategory":"Telephone",
            "type":"Services"
        },
        {
            "category":"Professional",
            "subcategory":"Computer Services",
            "type":"Services"
        }
    ],
    "sg:phone":"+1 732 818 0477",
    "sg:postcode":"08753",
    "sg:province":"NJ",
    "sg:tags":[
        "internet",
        "provider"
    ],
    "wof:name":"Americom Internet",
    "wof:placetype":"venue"
},
  "geometry": {"coordinates":[-74.197714,39.953296],"type":"Point"}
}