{
  "type": "Feature",
  "properties": {
    "addr:full":"2 Old Woods Rd Saddle River NJ 07458",
    "addr:housenumber":"2",
    "addr:postcode":"07458",
    "addr:street":"Old Woods Rd",
    "iso:country":"US",
    "sg:address":"2 Old Woods Rd",
    "sg:city":"Saddle River",
    "sg:classifiers":[
        {
            "category":"Shopping",
            "subcategory":"Luggage & Leather Goods",
            "type":"Retail Goods"
        }
    ],
    "sg:phone":"+1   ",
    "sg:postcode":"07458",
    "sg:province":"NJ",
    "wof:name":"Leather Knoll Inc",
    "wof:placetype":"venue"
},
  "geometry": {"coordinates":[-74.09701200000001,41.017112],"type":"Point"}
}