{
  "type": "Feature",
  "properties": {
    "addr:full":"242 Washington Ave Nutley NJ 07110",
    "addr:housenumber":"242",
    "addr:postcode":"07110",
    "addr:street":"Washington Ave",
    "iso:country":"US",
    "sg:address":"242 Washington Ave",
    "sg:city":"Nutley",
    "sg:classifiers":[
        {
            "category":"Health Services",
            "subcategory":"Medical Lab",
            "type":"Services"
        }
    ],
    "sg:phone":"+1 973 542 0033",
    "sg:postcode":"07110",
    "sg:province":"NJ",
    "sg:tags":[
        "laboratory",
        "dental"
    ],
    "wof:name":"Press Dental Laboratories",
    "wof:placetype":"venue"
},
  "geometry": {"coordinates":[-74.145104,40.811744],"type":"Point"}
}