{
  "type": "Feature",
  "properties": {
    "addr:full":"362 Ashford Rd Toms River NJ 08755",
    "addr:housenumber":"362",
    "addr:postcode":"08755",
    "addr:street":"Ashford Rd",
    "iso:country":"US",
    "sg:address":"362 Ashford Rd",
    "sg:city":"Toms River",
    "sg:classifiers":[
        {
            "category":"Real Estate",
            "subcategory":"Real Estate Agent",
            "type":"Services"
        }
    ],
    "sg:phone":"+1 732 281 5388",
    "sg:postcode":"08755",
    "sg:province":"NJ",
    "sg:tags":[
        "appraiser"
    ],
    "wof:name":"Stuart David Group",
    "wof:placetype":"venue"
},
  "geometry": {"coordinates":[-74.224418,40.003067],"type":"Point"}
}