{
  "type": "Feature",
  "properties": {
    "addr:full":"101 Cannonade Dr Marlboro NJ 07746",
    "addr:housenumber":"101",
    "addr:postcode":"07746",
    "addr:street":"Cannonade Dr",
    "iso:country":"US",
    "sg:address":"101 Cannonade Dr",
    "sg:city":"Marlboro",
    "sg:classifiers":[
        {
            "category":"Professional",
            "subcategory":"Business Services",
            "type":"Services"
        }
    ],
    "sg:phone":"+1   ",
    "sg:postcode":"07746",
    "sg:province":"NJ",
    "wof:name":"SFM Sales Inc",
    "wof:placetype":"venue"
},
  "geometry": {"coordinates":[-74.27257400000001,40.303998],"type":"Point"}
}