{
  "type": "Feature",
  "properties": {
    "iso:country":"US",
    "sg:address":"49 Rt 17 S",
    "sg:city":"East Rutherford",
    "sg:classifiers":[
        {
            "category":"Fast Food",
            "type":"Food & Drink"
        }
    ],
    "sg:phone":"+1 201 672 9200",
    "sg:postcode":"07073",
    "sg:province":"NJ",
    "sg:tags":[
        "burger"
    ],
    "sg:website":"www.cheeburger.com",
    "wof:name":"Cheeburger Cheeburger",
    "wof:placetype":"venue"
},
  "geometry": {"coordinates":[-74.10001800000001,40.821422],"type":"Point"}
}