{
  "type": "Feature",
  "properties": {
    "iso:country":"US",
    "sg:address":"23 Alpine Dr",
    "sg:city":"Lincoln Park",
    "sg:classifiers":[
        {
            "category":"Professional",
            "subcategory":"Management & Consulting",
            "type":"Services"
        }
    ],
    "sg:phone":"+1   ",
    "sg:postcode":"07035",
    "sg:province":"NJ",
    "wof:name":"M Eijadi",
    "wof:placetype":"venue"
},
  "geometry": {"coordinates":[-74.290935,40.912774],"type":"Point"}
}