{
  "type": "Feature",
  "properties": {
    "iso:country":"US",
    "sg:address":"599 Belvidere Rd",
    "sg:city":"Phillipsburg",
    "sg:classifiers":[
        {
            "category":"Professional",
            "type":"Services"
        }
    ],
    "sg:phone":"+1   ",
    "sg:postcode":"08865",
    "sg:province":"NJ",
    "wof:name":"Meals On Go",
    "wof:placetype":"venue"
},
  "geometry": {"coordinates":[-75.191653,40.700067],"type":"Point"}
}