{
  "type": "Feature",
  "properties": {
    "addr:full":"110 Meadowlands Pkwy Secaucus NJ 07094",
    "addr:housenumber":"110",
    "addr:postcode":"07094",
    "addr:street":"Meadowlands Pkwy",
    "iso:country":"US",
    "sg:address":"110 Meadowlands Pkwy",
    "sg:city":"Secaucus",
    "sg:classifiers":[
        {
            "category":"Utilities",
            "subcategory":"Telephone",
            "type":"Services"
        }
    ],
    "sg:phone":"+1 201 770 0376",
    "sg:postcode":"07094",
    "sg:province":"NJ",
    "sg:tags":[
        "telecommunication"
    ],
    "wof:name":"Allegiance Telecom Inc",
    "wof:placetype":"venue"
},
  "geometry": {"coordinates":[-74.077783,40.781891],"type":"Point"}
}