{
  "type": "Feature",
  "properties": {
    "iso:country":"US",
    "sg:address":"15 Tall Hedge Ct",
    "sg:city":"Barnegat",
    "sg:classifiers":[
        {
            "category":"Farming",
            "subcategory":"Livestock Farm",
            "type":"Manufacturing & Wholesale Goods"
        }
    ],
    "sg:phone":"+1 609 698 0892",
    "sg:postcode":"08005",
    "sg:province":"NJ",
    "sg:tags":[
        "animal",
        "general"
    ],
    "wof:name":"Red On Line",
    "wof:placetype":"venue"
},
  "geometry": {"coordinates":[-74.271973,39.768964],"type":"Point"}
}