{
  "type": "Feature",
  "properties": {
    "addr:full":"2 Buttonwood Dr Pilesgrove NJ 08098",
    "addr:housenumber":"2",
    "addr:postcode":"08098",
    "addr:street":"Buttonwood Dr",
    "iso:country":"US",
    "sg:address":"2 Buttonwood Dr",
    "sg:city":"Pilesgrove",
    "sg:classifiers":[
        {
            "category":"Professional",
            "type":"Services"
        }
    ],
    "sg:phone":"+1 856 769 5151",
    "sg:postcode":"08098",
    "sg:province":"NJ",
    "sg:tags":[
        "establishment"
    ],
    "wof:name":"John Monforto Productions",
    "wof:placetype":"venue"
},
  "geometry": {"coordinates":[-75.349448,39.701491],"type":"Point"}
}