{
  "type": "Feature",
  "properties": {
    "iso:country":"US",
    "sg:address":"191 Cottrell Rd",
    "sg:city":"Matawan",
    "sg:classifiers":[
        {
            "category":"Professional",
            "subcategory":"Business Services",
            "type":"Services"
        }
    ],
    "sg:phone":"+1   ",
    "sg:postcode":"07747",
    "sg:province":"NJ",
    "wof:name":"Masterson Home Inspection Inc",
    "wof:placetype":"venue"
},
  "geometry": {"coordinates":[-74.29369699999999,40.416005],"type":"Point"}
}