{
  "type": "Feature",
  "properties": {
    "iso:country":"US",
    "sg:address":"358 Cedar Ln",
    "sg:city":"Teaneck",
    "sg:classifiers":[
        {
            "category":"Local Transit",
            "type":"Transportation"
        }
    ],
    "sg:phone":"+1 201 287 1400",
    "sg:postcode":"07666",
    "sg:province":"NJ",
    "sg:tags":[
        "limousine"
    ],
    "wof:name":"Dinari Limousine Svc",
    "wof:placetype":"venue"
},
  "geometry": {"coordinates":[-74.018984,40.887965],"type":"Point"}
}