{
  "type": "Feature",
  "properties": {
    "addr:full":"540 Speedwell Ave Morris Plains NJ 07950",
    "addr:housenumber":"540",
    "addr:postcode":"07950",
    "addr:street":"Speedwell Ave",
    "iso:country":"US",
    "sg:address":"540 Speedwell Ave",
    "sg:city":"Morris Plains",
    "sg:classifiers":[
        {
            "category":"Communications",
            "type":"Services"
        }
    ],
    "sg:phone":"+1 973 267 1024",
    "sg:postcode":"07950",
    "sg:province":"NJ",
    "wof:name":"Telephone & Communications",
    "wof:placetype":"venue"
},
  "geometry": {"coordinates":[-74.48003199999999,40.826112],"type":"Point"}
}