{
  "type": "Feature",
  "properties": {
    "addr:full":"230 E State St Trenton NJ 08608",
    "addr:housenumber":"230",
    "addr:postcode":"08608",
    "addr:street":"E State St",
    "iso:country":"US",
    "sg:address":"230 E State St",
    "sg:city":"Trenton",
    "sg:classifiers":[
        {
            "category":"Restaurant",
            "type":"Food & Drink"
        }
    ],
    "sg:phone":"+1   ",
    "sg:postcode":"08608",
    "sg:province":"NJ",
    "sg:tags":[
        "drinking",
        "eating"
    ],
    "wof:name":"Dantes Cafe Inc",
    "wof:placetype":"venue"
},
  "geometry": {"coordinates":[-74.761646,40.220432],"type":"Point"}
}