{
  "type": "Feature",
  "properties": {
    "iso:country":"US",
    "sg:address":"811 Main Ave",
    "sg:city":"Passaic",
    "sg:classifiers":[
        {
            "category":"Retail",
            "subcategory":"Auto Repair",
            "type":"Services"
        }
    ],
    "sg:phone":"+1 973 777 7962",
    "sg:postcode":"07055",
    "sg:province":"NJ",
    "sg:tags":[
        "repairing",
        "automobile"
    ],
    "sg:website":"www.meineke.com",
    "wof:name":"Meineke Car Care Ctr",
    "wof:placetype":"venue"
},
  "geometry": {"coordinates":[-74.12916800000001,40.864092],"type":"Point"}
}