{
  "type": "Feature",
  "properties": {
    "iso:country":"US",
    "sg:address":"58 E 6th St",
    "sg:city":"Paterson",
    "sg:classifiers":[
        {
            "category":"Manufacturing",
            "subcategory":"Furniture",
            "type":"Manufacturing & Wholesale Goods"
        }
    ],
    "sg:phone":"+1 973 754 9990",
    "sg:postcode":"07524",
    "sg:province":"NJ",
    "sg:tags":[
        "delivery",
        "installation",
        "warehousing"
    ],
    "wof:name":"Smooth Move Dlvry Installation",
    "wof:placetype":"venue"
},
  "geometry": {"coordinates":[-74.162142,40.935799],"type":"Point"}
}