{
  "type": "Feature",
  "properties": {
    "addr:full":"39 Reid St South River NJ 08882",
    "addr:housenumber":"39",
    "addr:postcode":"08882",
    "addr:street":"Reid St",
    "iso:country":"US",
    "sg:address":"39 Reid St",
    "sg:city":"South River",
    "sg:classifiers":[
        {
            "category":"Manufacturing",
            "subcategory":"Retail Goods",
            "type":"Manufacturing & Wholesale Goods"
        }
    ],
    "sg:phone":"+1 732 238 0833",
    "sg:postcode":"08882",
    "sg:province":"NJ",
    "sg:tags":[
        "carbon",
        "mfg",
        "ribbon",
        "sup"
    ],
    "wof:name":"Toner Cartridge Depot Inc",
    "wof:placetype":"venue"
},
  "geometry": {"coordinates":[-74.380381,40.452973],"type":"Point"}
}