{
  "type": "Feature",
  "properties": {
    "addr:full":"14 Pruner Farm Rd Lebanon NJ 08833",
    "addr:housenumber":"14",
    "addr:postcode":"08833",
    "addr:street":"Pruner Farm Rd",
    "iso:country":"US",
    "sg:address":"14 Pruner Farm Rd",
    "sg:city":"Lebanon",
    "sg:classifiers":[
        {
            "category":"Professional",
            "subcategory":"Business Services",
            "type":"Services"
        }
    ],
    "sg:phone":"+1   ",
    "sg:postcode":"08833",
    "sg:province":"NJ",
    "wof:name":"Decorating Den Systems",
    "wof:placetype":"venue"
},
  "geometry": {"coordinates":[-74.79461499999999,40.682899],"type":"Point"}
}