{
  "type": "Feature",
  "properties": {
    "addr:full":"58 Price St Sayreville NJ 08872",
    "addr:housenumber":"58",
    "addr:postcode":"08872",
    "addr:street":"Price St",
    "iso:country":"US",
    "sg:address":"58 Price St",
    "sg:city":"Sayreville",
    "sg:classifiers":[
        {
            "category":"Insurance",
            "subcategory":"Insurance Agent",
            "type":"Services"
        }
    ],
    "sg:phone":"+1 732 238 3896",
    "sg:postcode":"08872",
    "sg:province":"NJ",
    "wof:name":"Hartford Insurance Group",
    "wof:placetype":"venue"
},
  "geometry": {"coordinates":[-74.340653,40.465102],"type":"Point"}
}