{
  "type": "Feature",
  "properties": {
    "addr:full":"299 Swedesboro Ave Gibbstown NJ 08027",
    "addr:housenumber":"299",
    "addr:postcode":"08027",
    "addr:street":"Swedesboro Ave",
    "iso:country":"US",
    "sg:address":"299 Swedesboro Ave",
    "sg:city":"Gibbstown",
    "sg:classifiers":[
        {
            "category":"Travel",
            "subcategory":"Hotels & Motels",
            "type":"Entertainment"
        }
    ],
    "sg:phone":"+1   ",
    "sg:postcode":"08027",
    "sg:province":"NJ",
    "sg:tags":[
        "lounge",
        "banquet",
        "facility"
    ],
    "wof:name":"Ramada Inn",
    "wof:placetype":"venue"
},
  "geometry": {"coordinates":[-75.25152799999999,39.818486],"type":"Point"}
}