{
  "type": "Feature",
  "properties": {
    "iso:country":"US",
    "sg:address":"255 Crescent Ave",
    "sg:city":"Gibbstown",
    "sg:classifiers":[
        {
            "category":"Insurance",
            "subcategory":"Insurance Agent",
            "type":"Services"
        }
    ],
    "sg:phone":"+1 856 224 1325",
    "sg:postcode":"08027",
    "sg:province":"NJ",
    "wof:name":"X L Insurance",
    "wof:placetype":"venue"
},
  "geometry": {"coordinates":[-75.251458,39.82001],"type":"Point"}
}