{
  "type": "Feature",
  "properties": {
    "addr:full":"47 E Mount Pleasant Ave Livingston NJ 07039",
    "addr:housenumber":"47",
    "addr:postcode":"07039",
    "addr:street":"E Mount Pleasant Ave",
    "iso:country":"US",
    "sg:address":"47 E Mount Pleasant Ave",
    "sg:city":"Livingston",
    "sg:classifiers":[
        {
            "category":"Health Services",
            "subcategory":"Doctor",
            "type":"Services"
        }
    ],
    "sg:phone":"+1 973 535 1100",
    "sg:postcode":"07039",
    "sg:province":"NJ",
    "wof:name":"Physicians In Urology PA",
    "wof:placetype":"venue"
},
  "geometry": {"coordinates":[-74.31314999999999,40.796885],"type":"Point"}
}