{
  "type": "Feature",
  "properties": {
    "addr:full":"50 Danville Dr Princeton Junction NJ 08550",
    "addr:housenumber":"50",
    "addr:postcode":"08550",
    "addr:street":"Danville Dr",
    "iso:country":"US",
    "sg:address":"50 Danville Dr",
    "sg:city":"Princeton Junction",
    "sg:classifiers":[
        {
            "category":"Professional",
            "subcategory":"Accounting & Tax Preparation",
            "type":"Services"
        }
    ],
    "sg:phone":"+1 609 799 8412",
    "sg:postcode":"08550",
    "sg:province":"NJ",
    "sg:tags":[
        "accountant",
        "public",
        "certified"
    ],
    "wof:name":"Ashok Rathod Inc",
    "wof:placetype":"venue"
},
  "geometry": {"coordinates":[-74.608689,40.273166],"type":"Point"}
}