{
  "type": "Feature",
  "properties": {
    "addr:full":"335 High St Metuchen NJ 08840",
    "addr:housenumber":"335",
    "addr:postcode":"08840",
    "addr:street":"High St",
    "iso:country":"US",
    "sg:address":"335 High St",
    "sg:city":"Metuchen",
    "sg:classifiers":[
        {
            "category":"Wholesale",
            "subcategory":"Machinery & Supplies",
            "type":"Manufacturing & Wholesale Goods"
        }
    ],
    "sg:phone":"+1 732 494 8165",
    "sg:postcode":"08840",
    "sg:province":"NJ",
    "sg:tags":[
        "house",
        "industrial",
        "mail"
    ],
    "wof:name":"Super Pouch Inc",
    "wof:placetype":"venue"
},
  "geometry": {"coordinates":[-74.372523,40.533206],"type":"Point"}
}