{
  "type": "Feature",
  "properties": {
    "addr:full":"167 Old York Rd Ringoes NJ 08551",
    "addr:housenumber":"167",
    "addr:postcode":"08551",
    "addr:street":"Old York Rd",
    "iso:country":"US",
    "sg:address":"167 Old York Rd",
    "sg:city":"Ringoes",
    "sg:classifiers":[
        {
            "category":"Manufacturing",
            "subcategory":"Food",
            "type":"Manufacturing & Wholesale Goods"
        },
        {
            "category":"Farming",
            "subcategory":"Farm",
            "type":"Manufacturing & Wholesale Goods"
        }
    ],
    "sg:phone":"+1 908 782 6653",
    "sg:postcode":"08551",
    "sg:province":"NJ",
    "sg:tags":[
        "corn",
        "product"
    ],
    "wof:name":"Irvin Hockenbury",
    "wof:placetype":"venue"
},
  "geometry": {"coordinates":[-74.825767,40.469795],"type":"Point"}
}