{
  "type": "Feature",
  "properties": {
    "addr:full":"451 Saint Pauls Ave Jersey City NJ 07306",
    "addr:housenumber":"451",
    "addr:postcode":"07306",
    "addr:street":"Saint Pauls Ave",
    "iso:country":"US",
    "sg:address":"451 Saint Pauls Ave",
    "sg:city":"Jersey City",
    "sg:classifiers":[
        {
            "category":"Restaurant",
            "type":"Food & Drink"
        }
    ],
    "sg:phone":"+1 201 222 6808",
    "sg:postcode":"07306",
    "sg:province":"NJ",
    "sg:tags":[
        "delicatessen"
    ],
    "wof:name":"J R Convenience Deli",
    "wof:placetype":"venue"
},
  "geometry": {"coordinates":[-74.072688,40.740404],"type":"Point"}
}