{
  "type": "Feature",
  "properties": {
    "addr:full":"2411 Pennington Rd Pennington NJ 08534",
    "addr:housenumber":"2411",
    "addr:postcode":"08534",
    "addr:street":"Pennington Rd",
    "iso:country":"US",
    "sg:address":"2411 Pennington Rd",
    "sg:city":"Pennington",
    "sg:classifiers":[
        {
            "category":"Personal",
            "subcategory":"Barber",
            "type":"Services"
        }
    ],
    "sg:phone":"+1 609 737 1100",
    "sg:postcode":"08534",
    "sg:province":"NJ",
    "sg:tags":[
        "shop",
        "beauty"
    ],
    "wof:name":"Pennington Crimpers",
    "wof:placetype":"venue"
},
  "geometry": {"coordinates":[-74.783422,40.298477],"type":"Point"}
}