{
  "type": "Feature",
  "properties": {
    "iso:country":"US",
    "sg:address":"27 Hasbrouck Pl",
    "sg:city":"Rutherford",
    "sg:classifiers":[
        {
            "category":"Professional",
            "subcategory":"Management & Consulting",
            "type":"Services"
        }
    ],
    "sg:phone":"+1 201 935 3880",
    "sg:postcode":"07070",
    "sg:province":"NJ",
    "wof:name":"Destiny Representatives Ltd",
    "wof:placetype":"venue"
},
  "geometry": {"coordinates":[-74.107511,40.837734],"type":"Point"}
}