{
  "type": "Feature",
  "properties": {
    "addr:full":"211 Main St Butler NJ 07405",
    "addr:housenumber":"211",
    "addr:postcode":"07405",
    "addr:street":"Main St",
    "iso:country":"US",
    "sg:address":"211 Main St",
    "sg:city":"Butler",
    "sg:classifiers":[
        {
            "category":"Real Estate",
            "subcategory":"Surveying",
            "type":"Services"
        }
    ],
    "sg:phone":"+1 973 838 9187",
    "sg:postcode":"07405",
    "sg:province":"NJ",
    "sg:tags":[
        "surveyor"
    ],
    "wof:name":"DMC Assoc Land Surveyors",
    "wof:placetype":"venue"
},
  "geometry": {"coordinates":[-74.339803,41.00237],"type":"Point"}
}