{
  "type": "Feature",
  "properties": {
    "addr:full":"1433 Ardenwood Ave Lakewood NJ 08701",
    "addr:housenumber":"1433",
    "addr:postcode":"08701",
    "addr:street":"Ardenwood Ave",
    "iso:country":"US",
    "sg:address":"1433 Ardenwood Ave",
    "sg:city":"Lakewood",
    "sg:classifiers":[
        {
            "category":"Banks & Credit Unions",
            "subcategory":"Investment Brokerage",
            "type":"Services"
        }
    ],
    "sg:phone":"+1   ",
    "sg:postcode":"08701",
    "sg:province":"NJ",
    "wof:name":"Seh Investments",
    "wof:placetype":"venue"
},
  "geometry": {"coordinates":[-74.222281,40.104911],"type":"Point"}
}