{
  "type": "Feature",
  "properties": {
    "addr:full":"350 Riverbank Burlington NJ 08016",
    "addr:housenumber":"350",
    "addr:postcode":"08016",
    "addr:street":"Riverbank",
    "iso:country":"US",
    "sg:address":"350 Riverbank",
    "sg:city":"Burlington",
    "sg:classifiers":[
        {
            "category":"Education",
            "subcategory":"School",
            "type":"Public Place"
        }
    ],
    "sg:phone":"+1 609 386 3500",
    "sg:postcode":"08016",
    "sg:province":"NJ",
    "sg:tags":[
        "high",
        "middle",
        "elementary"
    ],
    "sg:website":"www.thehall.org",
    "wof:name":"Doane Academy",
    "wof:placetype":"venue"
},
  "geometry": {"coordinates":[-74.867716,40.079852],"type":"Point"}
}