{
  "type": "Feature",
  "properties": {
    "iso:country":"US",
    "sg:address":"66 Leigh St",
    "sg:city":"Clinton",
    "sg:classifiers":[
        {
            "category":"Travel",
            "subcategory":"Hotels & Motels",
            "type":"Entertainment"
        }
    ],
    "sg:phone":"+1 908 238 0400",
    "sg:postcode":"08809",
    "sg:province":"NJ",
    "sg:tags":[
        "breakfast",
        "accommodation",
        "bed"
    ],
    "sg:website":"www.riversidevictorian.com",
    "wof:name":"Riverside Victorian B & B",
    "wof:placetype":"venue"
},
  "geometry": {"coordinates":[-74.90872,40.635183],"type":"Point"}
}