{
  "type": "Feature",
  "properties": {
    "addr:full":"22 Union Ave Berlin NJ 08009",
    "addr:housenumber":"22",
    "addr:postcode":"08009",
    "addr:street":"Union Ave",
    "iso:country":"US",
    "sg:address":"22 Union Ave",
    "sg:city":"Berlin",
    "sg:classifiers":[
        {
            "category":"Manufacturing",
            "subcategory":"Glass & Minerals",
            "type":"Manufacturing & Wholesale Goods"
        }
    ],
    "sg:phone":"+1 856 768 6642",
    "sg:postcode":"08009",
    "sg:province":"NJ",
    "sg:tags":[
        "ready",
        "concrete",
        "product",
        "mfg"
    ],
    "wof:name":"Atlantic Quikrete",
    "wof:placetype":"venue"
},
  "geometry": {"coordinates":[-74.94495000000001,39.804599],"type":"Point"}
}