{
  "type": "Feature",
  "properties": {
    "iso:country":"US",
    "sg:address":"117 Luttgen Pl",
    "sg:city":"Linden",
    "sg:classifiers":[
        {
            "category":"Building & Trades",
            "subcategory":"Construction",
            "type":"Services"
        }
    ],
    "sg:phone":"+1 908 486 9109",
    "sg:postcode":"07036",
    "sg:province":"NJ",
    "sg:tags":[
        "house"
    ],
    "wof:name":"Ebr Home Improvement Inc",
    "wof:placetype":"venue"
},
  "geometry": {"coordinates":[-74.254464,40.634305],"type":"Point"}
}