{
  "type": "Feature",
  "properties": {
    "addr:full":"1470 Bergen Blvd Fort Lee NJ 07024",
    "addr:housenumber":"1470",
    "addr:postcode":"07024",
    "addr:street":"Bergen Blvd",
    "iso:country":"US",
    "sg:address":"1470 Bergen Blvd",
    "sg:city":"Fort Lee",
    "sg:classifiers":[
        {
            "category":"Personal",
            "subcategory":"Massage",
            "type":"Services"
        }
    ],
    "sg:phone":"+1 201 947 4600",
    "sg:postcode":"07024",
    "sg:province":"NJ",
    "sg:website":"www.wyssmont.com",
    "wof:name":"Wyssmont Co Inc",
    "wof:placetype":"venue"
},
  "geometry": {"coordinates":[-73.984703,40.852299],"type":"Point"}
}