{
  "type": "Feature",
  "properties": {
    "iso:country":"US",
    "sg:address":"30 Pine Rd",
    "sg:city":"Howell",
    "sg:classifiers":[
        {
            "category":"Building & Trades",
            "subcategory":"Landscaping Services",
            "type":"Services"
        }
    ],
    "sg:phone":"+1 732 370 2776",
    "sg:postcode":"07731",
    "sg:province":"NJ",
    "sg:tags":[
        "tree"
    ],
    "wof:name":"Clavin Tree & Lawn Svc",
    "wof:placetype":"venue"
},
  "geometry": {"coordinates":[-74.220634,40.164638],"type":"Point"}
}