{
  "type": "Feature",
  "properties": {
    "iso:country":"US",
    "sg:address":"797 Valley Rd",
    "sg:city":"Clifton",
    "sg:classifiers":[
        {
            "category":"Organizations",
            "subcategory":"Religious Organization",
            "type":"Services"
        }
    ],
    "sg:phone":"+1   ",
    "sg:postcode":"07013",
    "sg:province":"NJ",
    "sg:tags":[
        "school"
    ],
    "wof:name":"St Phlip Apstle Elmentary Schl",
    "wof:placetype":"venue"
},
  "geometry": {"coordinates":[-74.186471,40.874576],"type":"Point"}
}