{
  "type": "Feature",
  "properties": {
    "addr:full":"18 Burns Ave Vineland NJ 08360",
    "addr:housenumber":"18",
    "addr:postcode":"08360",
    "addr:street":"Burns Ave",
    "iso:country":"US",
    "sg:address":"18 Burns Ave",
    "sg:city":"Vineland",
    "sg:classifiers":[
        {
            "category":"Manufacturing",
            "subcategory":"Building Materials",
            "type":"Manufacturing & Wholesale Goods"
        }
    ],
    "sg:phone":"+1 856 825 9550",
    "sg:postcode":"08360",
    "sg:province":"NJ",
    "sg:tags":[
        "product",
        "lumber",
        "mfg"
    ],
    "wof:name":"Joffe Lumber & Supply Co Inc",
    "wof:placetype":"venue"
},
  "geometry": {"coordinates":[-75.024137,39.428278],"type":"Point"}
}