{
  "type": "Feature",
  "properties": {
    "addr:full":"201 White Horse Pike Clementon NJ 08021",
    "addr:housenumber":"201",
    "addr:postcode":"08021",
    "addr:street":"White Horse Pike",
    "iso:country":"US",
    "sg:address":"201 White Horse Pike",
    "sg:city":"Clementon",
    "sg:classifiers":[
        {
            "category":"Organizations",
            "subcategory":"Religious Organization",
            "type":"Services"
        }
    ],
    "sg:phone":"+1   ",
    "sg:postcode":"08021",
    "sg:province":"NJ",
    "wof:name":"Saint L De Paul",
    "wof:placetype":"venue"
},
  "geometry": {"coordinates":[-74.975302,39.80831],"type":"Point"}
}