{
  "type": "Feature",
  "properties": {
    "addr:full":"4 Marion Dr Jackson NJ 08536",
    "addr:housenumber":"4",
    "addr:postcode":"08536",
    "addr:street":"Marion Dr",
    "iso:country":"US",
    "sg:address":"4 Marion Dr",
    "sg:city":"Jackson",
    "sg:classifiers":[
        {
            "category":"Building & Trades",
            "subcategory":"Construction",
            "type":"Services"
        }
    ],
    "sg:phone":"+1 732 928 9575",
    "sg:postcode":"08536",
    "sg:province":"NJ",
    "sg:tags":[
        "contractor"
    ],
    "wof:name":"Cjmj Corp",
    "wof:placetype":"venue"
},
  "geometry": {"coordinates":[-74.577004,40.33314],"type":"Point"}
}