{
  "type": "Feature",
  "properties": {
    "addr:full":"823 E 28th St Paterson NJ 07513",
    "addr:housenumber":"823",
    "addr:postcode":"07513",
    "addr:street":"E 28Th St",
    "iso:country":"US",
    "sg:address":"823 E 28th St",
    "sg:city":"Paterson",
    "sg:classifiers":[
        {
            "category":"Education",
            "subcategory":"School",
            "type":"Public Place"
        }
    ],
    "sg:phone":"+1 973 321 0300",
    "sg:postcode":"07513",
    "sg:province":"NJ",
    "sg:website":"www.paterson.k12.nj.us",
    "wof:name":"Martin Luther King School",
    "wof:placetype":"venue"
},
  "geometry": {"coordinates":[-74.14866499999999,40.908198],"type":"Point"}
}