{
  "type": "Feature",
  "properties": {
    "addr:full":"13 Bassett Hwy Dover NJ 07801",
    "addr:housenumber":"13",
    "addr:postcode":"07801",
    "addr:street":"Bassett Hwy",
    "iso:country":"US",
    "sg:address":"13 Bassett Hwy",
    "sg:city":"Dover",
    "sg:classifiers":[
        {
            "category":"Travel",
            "subcategory":"Travel Agent",
            "type":"Entertainment"
        }
    ],
    "sg:phone":"+1 973 989 6800",
    "sg:postcode":"07801",
    "sg:province":"NJ",
    "sg:tags":[
        "agency",
        "bureau"
    ],
    "wof:name":"Pacific Travel Inc",
    "wof:placetype":"venue"
},
  "geometry": {"coordinates":[-74.559094,40.8849],"type":"Point"}
}