{
  "type": "Feature",
  "properties": {
    "iso:country":"US",
    "sg:address":"10 Manor Ln",
    "sg:city":"Bridgeton",
    "sg:classifiers":[
        {
            "category":"Education",
            "subcategory":"Special Training",
            "type":"Public Place"
        }
    ],
    "sg:phone":"+1   ",
    "sg:postcode":"08302",
    "sg:province":"NJ",
    "wof:name":"Beverly Pugh Associates",
    "wof:placetype":"venue"
},
  "geometry": {"coordinates":[-75.254169,39.442397],"type":"Point"}
}