{
  "type": "Feature",
  "properties": {
    "iso:country":"US",
    "sg:address":"9 Kiel Ave",
    "sg:city":"Butler",
    "sg:classifiers":[
        {
            "category":"Health Services",
            "subcategory":"Chiropractor",
            "type":"Services"
        }
    ],
    "sg:phone":"+1 973 492 0458",
    "sg:postcode":"07405",
    "sg:province":"NJ",
    "wof:name":"Berg Jeffrey M DC",
    "wof:placetype":"venue"
},
  "geometry": {"coordinates":[-74.34169799999999,41.001598],"type":"Point"}
}