{
  "type": "Feature",
  "properties": {
    "iso:country":"US",
    "sg:address":"56 Commonwealth Ave",
    "sg:city":"Newark",
    "sg:classifiers":[
        {
            "category":"Social Services",
            "subcategory":"Child Care",
            "type":"Services"
        }
    ],
    "sg:phone":"+1 973 371 4336",
    "sg:postcode":"07106",
    "sg:province":"NJ",
    "sg:tags":[
        "day"
    ],
    "wof:name":"Angel Little Daycare",
    "wof:placetype":"venue"
},
  "geometry": {"coordinates":[-74.234058,40.739689],"type":"Point"}
}