{
  "type": "Feature",
  "properties": {
    "addr:full":"1132 Ocean Ave Sea Bright NJ 07760",
    "addr:housenumber":"1132",
    "addr:postcode":"07760",
    "addr:street":"Ocean Ave",
    "iso:country":"US",
    "sg:address":"1132 Ocean Ave",
    "sg:city":"Sea Bright",
    "sg:classifiers":[
        {
            "category":"Restaurant",
            "type":"Food & Drink"
        }
    ],
    "sg:phone":"+1 732 224 9149",
    "sg:postcode":"07760",
    "sg:province":"NJ",
    "wof:name":"Subs N' More",
    "wof:placetype":"venue"
},
  "geometry": {"coordinates":[-73.9742,40.361112],"type":"Point"}
}