{
  "type": "Feature",
  "properties": {
    "addr:full":"8 Buttonwood Rd Voorhees NJ 08043",
    "addr:housenumber":"8",
    "addr:postcode":"08043",
    "addr:street":"Buttonwood Rd",
    "iso:country":"US",
    "sg:address":"8 Buttonwood Rd",
    "sg:city":"Voorhees",
    "sg:classifiers":[
        {
            "category":"Insurance",
            "subcategory":"Insurance Agent",
            "type":"Services"
        }
    ],
    "sg:phone":"+1   ",
    "sg:postcode":"08043",
    "sg:province":"NJ",
    "wof:name":"Navaho Insurance Agency",
    "wof:placetype":"venue"
},
  "geometry": {"coordinates":[-74.99312399999999,39.852018],"type":"Point"}
}