{
  "type": "Feature",
  "properties": {
    "iso:country":"US",
    "sg:address":"274 Brookside Ave",
    "sg:city":"Cresskill",
    "sg:classifiers":[
        {
            "category":"Manufacturing",
            "subcategory":"Printing",
            "type":"Manufacturing & Wholesale Goods"
        }
    ],
    "sg:phone":"+1 201 568 7129",
    "sg:postcode":"07626",
    "sg:province":"NJ",
    "sg:tags":[
        "commercial"
    ],
    "wof:name":"Dld Promotions",
    "wof:placetype":"venue"
},
  "geometry": {"coordinates":[-73.968521,40.948988],"type":"Point"}
}