{
  "type": "Feature",
  "properties": {
    "addr:full":"269 US Hwy 22 Dunellen NJ 08812",
    "addr:housenumber":"269",
    "addr:postcode":"08812",
    "addr:street":"Us Hwy 22",
    "iso:country":"US",
    "sg:address":"269 US Hwy 22",
    "sg:city":"Dunellen",
    "sg:classifiers":[
        {
            "category":"Wholesale",
            "subcategory":"Electrical",
            "type":"Manufacturing & Wholesale Goods"
        },
        {
            "category":"Shopping",
            "subcategory":"Computers & Home Electronics",
            "type":"Retail Goods"
        }
    ],
    "sg:phone":"+1 732 968 3500",
    "sg:postcode":"08812",
    "sg:province":"NJ",
    "sg:tags":[
        "parts",
        "electronic",
        "supply"
    ],
    "wof:name":"Green Brook Electronics Inc",
    "wof:placetype":"venue"
},
  "geometry": {"coordinates":[-74.49437399999999,40.593537],"type":"Point"}
}