{
  "type": "Feature",
  "properties": {
    "iso:country":"US",
    "sg:address":"1501 US Hwy 206",
    "sg:city":"Skillman",
    "sg:classifiers":[
        {
            "category":"Building & Trades",
            "subcategory":"Construction",
            "type":"Services"
        }
    ],
    "sg:phone":"+1 609 924 5497",
    "sg:postcode":"08558",
    "sg:province":"NJ",
    "sg:tags":[
        "house"
    ],
    "wof:name":"Regional Building & Imprvs",
    "wof:placetype":"venue"
},
  "geometry": {"coordinates":[-74.649644,40.410691],"type":"Point"}
}