{
  "type": "Feature",
  "properties": {
    "iso:country":"US",
    "sg:address":"10 Princeton Rd",
    "sg:city":"Livingston",
    "sg:classifiers":[
        {
            "category":"Professional",
            "type":"Services"
        }
    ],
    "sg:phone":"+1   ",
    "sg:postcode":"07039",
    "sg:province":"NJ",
    "wof:name":"Adrienne Santola",
    "wof:placetype":"venue"
},
  "geometry": {"coordinates":[-74.309392,40.767879],"type":"Point"}
}