{
  "type": "Feature",
  "properties": {
    "addr:full":"400 Mountain Ave Caldwell NJ 07006",
    "addr:housenumber":"400",
    "addr:postcode":"07006",
    "addr:street":"Mountain Ave",
    "iso:country":"US",
    "sg:address":"400 Mountain Ave",
    "sg:city":"Caldwell",
    "sg:classifiers":[
        {
            "category":"Recreation",
            "type":"Entertainment"
        }
    ],
    "sg:phone":"+1 973 226 9642",
    "sg:postcode":"07006",
    "sg:province":"NJ",
    "wof:name":"North Caldwell Skating Pond",
    "wof:placetype":"venue"
},
  "geometry": {"coordinates":[-74.2574,40.861742],"type":"Point"}
}