{
  "type": "Feature",
  "properties": {
    "iso:country":"US",
    "sg:address":"163 W Commerce St",
    "sg:city":"Bridgeton",
    "sg:classifiers":[
        {
            "category":"Professional",
            "subcategory":"Lawyer & Legal Services",
            "type":"Services"
        }
    ],
    "sg:phone":"+1 856 451 8050",
    "sg:postcode":"08302",
    "sg:province":"NJ",
    "sg:tags":[
        "attorney"
    ],
    "wof:name":"Seeley Law Office",
    "wof:placetype":"venue"
},
  "geometry": {"coordinates":[-75.242299,39.430693],"type":"Point"}
}