{
  "type": "Feature",
  "properties": {
    "addr:full":"300 Harrison Ave Harrison NJ 07029",
    "addr:housenumber":"300",
    "addr:postcode":"07029",
    "addr:street":"Harrison Ave",
    "iso:country":"US",
    "sg:address":"300 Harrison Ave",
    "sg:city":"Harrison",
    "sg:classifiers":[
        {
            "category":"Food & Beverages",
            "subcategory":"Groceries & Convenience Stores",
            "type":"Retail Goods"
        }
    ],
    "sg:phone":"+1 973 483 0748",
    "sg:postcode":"07029",
    "sg:province":"NJ",
    "wof:name":"An Li Variety Grocery Store",
    "wof:placetype":"venue"
},
  "geometry": {"coordinates":[-74.158203,40.746201],"type":"Point"}
}