{
  "type": "Feature",
  "properties": {
    "addr:full":"930 Cookman Ave Asbury Park NJ 07712",
    "addr:housenumber":"930",
    "addr:postcode":"07712",
    "addr:street":"Cookman Ave Asbury",
    "iso:country":"US",
    "sg:address":"930 Cookman Ave",
    "sg:city":"Asbury Park",
    "sg:classifiers":[
        {
            "category":"Recreation",
            "type":"Entertainment"
        }
    ],
    "sg:phone":"+1   ",
    "sg:postcode":"07712",
    "sg:province":"NJ",
    "sg:tags":[
        "club",
        "membership"
    ],
    "wof:name":"Mount Pisgah Lodge",
    "wof:placetype":"venue"
},
  "geometry": {"coordinates":[-74.01602699999999,40.216428],"type":"Point"}
}