{
  "type": "Feature",
  "properties": {
    "addr:full":"111 Charlotte Pl Englewood Cliffs NJ 07632",
    "addr:housenumber":"111",
    "addr:postcode":"07632",
    "addr:street":"Charlotte Pl",
    "iso:country":"US",
    "sg:address":"111 Charlotte Pl",
    "sg:city":"Englewood Cliffs",
    "sg:classifiers":[
        {
            "category":"Education",
            "subcategory":"Special Training",
            "type":"Public Place"
        }
    ],
    "sg:phone":"+1   ",
    "sg:postcode":"07632",
    "sg:province":"NJ",
    "wof:name":"Kumon",
    "wof:placetype":"venue"
},
  "geometry": {"coordinates":[-73.95456,40.87368],"type":"Point"}
}