{
  "type": "Feature",
  "properties": {
    "iso:country":"US",
    "sg:address":"28 Forester Dr",
    "sg:city":"Barnegat",
    "sg:classifiers":[
        {
            "category":"Professional",
            "type":"Services"
        }
    ],
    "sg:phone":"+1   ",
    "sg:postcode":"08005",
    "sg:province":"NJ",
    "wof:name":"Woodsher Inc",
    "wof:placetype":"venue"
},
  "geometry": {"coordinates":[-74.242621,39.762503],"type":"Point"}
}