{
  "type": "Feature",
  "properties": {
    "iso:country":"US",
    "sg:address":"89 Washington St",
    "sg:city":"Morristown",
    "sg:classifiers":[
        {
            "category":"Health Services",
            "subcategory":"Doctor",
            "type":"Services"
        }
    ],
    "sg:phone":"+1   ",
    "sg:postcode":"07960",
    "sg:province":"NJ",
    "sg:tags":[
        "dentist"
    ],
    "wof:name":"Steven H Richter DMD",
    "wof:placetype":"venue"
},
  "geometry": {"coordinates":[-74.48697900000001,40.799225],"type":"Point"}
}