{
  "type": "Feature",
  "properties": {
    "iso:country":"US",
    "sg:address":"317 Bailey St",
    "sg:city":"Woodstown",
    "sg:classifiers":[
        {
            "category":"Organizations",
            "subcategory":"Religious Organization",
            "type":"Services"
        }
    ],
    "sg:phone":"+1   ",
    "sg:postcode":"08098",
    "sg:province":"NJ",
    "wof:name":"Mt Nebo Masnc Lodg",
    "wof:placetype":"venue"
},
  "geometry": {"coordinates":[-75.32726099999999,39.640464],"type":"Point"}
}