{
  "type": "Feature",
  "properties": {
    "iso:country":"US",
    "sg:address":"276 Washington St",
    "sg:city":"Keyport",
    "sg:classifiers":[
        {
            "category":"Real Estate",
            "subcategory":"Real Estate Operator",
            "type":"Services"
        }
    ],
    "sg:phone":"+1   ",
    "sg:postcode":"07735",
    "sg:province":"NJ",
    "sg:tags":[
        "building",
        "ope",
        "apartment",
        "nonresidential"
    ],
    "wof:name":"Stella C Szyszlo",
    "wof:placetype":"venue"
},
  "geometry": {"coordinates":[-74.213064,40.428035],"type":"Point"}
}