{
  "type": "Feature",
  "properties": {
    "addr:full":"121 Washington St Toms River NJ 08753",
    "addr:housenumber":"121",
    "addr:postcode":"08753",
    "addr:street":"Washington St",
    "iso:country":"US",
    "sg:address":"121 Washington St",
    "sg:city":"Toms River",
    "sg:classifiers":[
        {
            "category":"Banks & Credit Unions",
            "subcategory":"Bank",
            "type":"Services"
        }
    ],
    "sg:phone":"+1   ",
    "sg:postcode":"08753",
    "sg:province":"NJ",
    "sg:tags":[
        "broker",
        "mortgage"
    ],
    "wof:name":"Ocean Home Mortgage Corp",
    "wof:placetype":"venue"
},
  "geometry": {"coordinates":[-74.193974,39.952422],"type":"Point"}
}