{
  "type": "Feature",
  "properties": {
    "addr:full":"184 Henry Ave Elmer NJ 08318",
    "addr:housenumber":"184",
    "addr:postcode":"08318",
    "addr:street":"Henry Ave",
    "iso:country":"US",
    "sg:address":"184 Henry Ave",
    "sg:city":"Elmer",
    "sg:classifiers":[
        {
            "category":"Organizations",
            "subcategory":"Community Association",
            "type":"Services"
        }
    ],
    "sg:phone":"+1 856 691 4984",
    "sg:postcode":"08318",
    "sg:province":"NJ",
    "sg:tags":[
        "fraternal"
    ],
    "wof:name":"Garden State Elks Lodge",
    "wof:placetype":"venue"
},
  "geometry": {"coordinates":[-75.091067,39.520801],"type":"Point"}
}