{
  "type": "Feature",
  "properties": {
    "addr:full":"121 Rochelle Ave Rochelle Park NJ 07662",
    "addr:housenumber":"121",
    "addr:postcode":"07662",
    "addr:street":"Rochelle Ave",
    "iso:country":"US",
    "sg:address":"121 Rochelle Ave",
    "sg:city":"Rochelle Park",
    "sg:classifiers":[
        {
            "category":"Professional",
            "subcategory":"Lawyer & Legal Services",
            "type":"Services"
        }
    ],
    "sg:phone":"+1 201 845 9266",
    "sg:postcode":"07662",
    "sg:province":"NJ",
    "wof:name":"Roy Mc Geady",
    "wof:placetype":"venue"
},
  "geometry": {"coordinates":[-74.078504,40.89984],"type":"Point"}
}