{
  "type": "Feature",
  "properties": {
    "addr:full":"160 Panorama Dr Edgewater NJ 07020",
    "addr:housenumber":"160",
    "addr:postcode":"07020",
    "addr:street":"Panorama Dr",
    "iso:country":"US",
    "sg:address":"160 Panorama Dr",
    "sg:city":"Edgewater",
    "sg:classifiers":[
        {
            "category":"Professional",
            "subcategory":"Management & Consulting",
            "type":"Services"
        }
    ],
    "sg:phone":"+1 201 224 5743",
    "sg:postcode":"07020",
    "sg:province":"NJ",
    "sg:tags":[
        "marketing",
        "program"
    ],
    "wof:name":"Hot Sauce Marketing Inc",
    "wof:placetype":"venue"
},
  "geometry": {"coordinates":[-73.974515,40.828822],"type":"Point"}
}