{
  "type": "Feature",
  "properties": {
    "addr:full":"6713 Rudderow Ave Merchantville NJ 08109",
    "addr:housenumber":"6713",
    "addr:postcode":"08109",
    "addr:street":"Rudderow Ave",
    "iso:country":"US",
    "sg:address":"6713 Rudderow Ave",
    "sg:city":"Merchantville",
    "sg:classifiers":[
        {
            "category":"Wholesale",
            "subcategory":"Medical Equipment & Supplies",
            "type":"Manufacturing & Wholesale Goods"
        }
    ],
    "sg:phone":"+1 856 488 5795",
    "sg:postcode":"08109",
    "sg:province":"NJ",
    "wof:name":"Med Concepts",
    "wof:placetype":"venue"
},
  "geometry": {"coordinates":[-75.04120500000001,39.95256],"type":"Point"}
}