{
  "type": "Feature",
  "properties": {
    "addr:full":"3 Ruby Ct Succasunna NJ 07876",
    "addr:housenumber":"3",
    "addr:postcode":"07876",
    "addr:street":"Ruby Ct",
    "iso:country":"US",
    "sg:address":"3 Ruby Ct",
    "sg:city":"Succasunna",
    "sg:classifiers":[
        {
            "category":"Professional",
            "subcategory":"Engineering",
            "type":"Services"
        }
    ],
    "sg:phone":"+1 973 927 9342",
    "sg:postcode":"07876",
    "sg:province":"NJ",
    "wof:name":"Global Project Managem",
    "wof:placetype":"venue"
},
  "geometry": {"coordinates":[-74.67085299999999,40.850341],"type":"Point"}
}