{
  "type": "Feature",
  "properties": {
    "iso:country":"US",
    "sg:address":"167 Newman Springs Rd E",
    "sg:city":"Shrewsbury",
    "sg:classifiers":[
        {
            "category":"Building & Trades",
            "subcategory":"Construction",
            "type":"Services"
        },
        {
            "category":"Manufacturing",
            "subcategory":"Building Materials",
            "type":"Manufacturing & Wholesale Goods"
        }
    ],
    "sg:phone":"+1 732 212 1009",
    "sg:postcode":"07702",
    "sg:province":"NJ",
    "sg:tags":[
        "roofing",
        "industrial",
        "sheet",
        "altering",
        "work",
        "metal",
        "specialty",
        "contractor",
        "siding",
        "contractors-commercial",
        "remodeling"
    ],
    "wof:name":"James W Bills & Son Inc",
    "wof:placetype":"venue"
},
  "geometry": {"coordinates":[-74.071394,40.337644],"type":"Point"}
}