{
  "type": "Feature",
  "properties": {
    "addr:full":"1 Matrick Ct Monroe Twp NJ 08844",
    "addr:housenumber":"1",
    "addr:postcode":"08844",
    "addr:street":"Matrick Ct",
    "iso:country":"US",
    "sg:address":"1 Matrick Ct",
    "sg:city":"Monroe Twp",
    "sg:classifiers":[
        {
            "category":"Professional",
            "subcategory":"Advertising",
            "type":"Services"
        }
    ],
    "sg:phone":"+1 609 409 5060",
    "sg:postcode":"08844",
    "sg:province":"NJ",
    "sg:tags":[
        "distribution"
    ],
    "sg:website":"www.mitsubishi-tv.com",
    "wof:name":"Mitsubishi Electronics",
    "wof:placetype":"venue"
},
  "geometry": {"coordinates":[-74.592502,40.484549],"type":"Point"}
}