{
  "type": "Feature",
  "properties": {
    "iso:country":"US",
    "sg:address":"62 W Main St",
    "sg:city":"Clinton",
    "sg:classifiers":[
        {
            "category":"Utilities",
            "subcategory":"Water",
            "type":"Services"
        }
    ],
    "sg:phone":"+1 908 534 4475",
    "sg:postcode":"08809",
    "sg:province":"NJ",
    "sg:tags":[
        "pump",
        "well",
        "drilling",
        "contractor"
    ],
    "wof:name":"D & L Well Drilling",
    "wof:placetype":"venue"
},
  "geometry": {"coordinates":[-74.916275,40.632991],"type":"Point"}
}