{
  "type": "Feature",
  "properties": {
    "iso:country":"US",
    "sg:address":"97 Lackawanna Ave",
    "sg:city":"Totowa",
    "sg:classifiers":[
        {
            "category":"Wholesale",
            "subcategory":"Electrical",
            "type":"Manufacturing & Wholesale Goods"
        }
    ],
    "sg:phone":"+1 973 237 9440",
    "sg:postcode":"07512",
    "sg:province":"NJ",
    "sg:tags":[
        "equipment",
        "parts",
        "electronic"
    ],
    "wof:name":"Strategic Sales Inc",
    "wof:placetype":"venue"
},
  "geometry": {"coordinates":[-74.22062099999999,40.893421],"type":"Point"}
}