{
  "type": "Feature",
  "properties": {
    "addr:full":"703 Mill Creek Rd Manahawkin NJ 08050",
    "addr:housenumber":"703",
    "addr:postcode":"08050",
    "addr:street":"Mill Creek Rd",
    "iso:country":"US",
    "sg:address":"703 Mill Creek Rd",
    "sg:city":"Manahawkin",
    "sg:classifiers":[
        {
            "category":"Communications",
            "subcategory":"Radio Station",
            "type":"Services"
        }
    ],
    "sg:phone":"+1 609 597 6700",
    "sg:postcode":"08050",
    "sg:province":"NJ",
    "sg:tags":[
        "company",
        "broadcasting"
    ],
    "sg:website":"www.b985radio.com",
    "wof:name":"WBBO",
    "wof:placetype":"venue"
},
  "geometry": {"coordinates":[-74.238716,39.679954],"type":"Point"}
}