{
  "type": "Feature",
  "properties": {
    "addr:full":"215 Tonnele Ave Jersey City NJ 07306",
    "addr:housenumber":"215",
    "addr:postcode":"07306",
    "addr:street":"Tonnele Ave",
    "iso:country":"US",
    "sg:address":"215 Tonnele Ave",
    "sg:city":"Jersey City",
    "sg:classifiers":[
        {
            "category":"Building & Trades",
            "subcategory":"Locksmith",
            "type":"Services"
        }
    ],
    "sg:phone":"+1 201 793 1641",
    "sg:postcode":"07306",
    "sg:province":"NJ",
    "sg:tags":[
        "key"
    ],
    "wof:name":"Always Available 24 Hour Emergency Locksmi",
    "wof:placetype":"venue"
},
  "geometry": {"coordinates":[-74.065809,40.738109],"type":"Point"}
}