{
  "type": "Feature",
  "properties": {
    "addr:full":"27 Martin Luther King Plz Elizabeth NJ 07201",
    "addr:housenumber":"27",
    "addr:postcode":"07201",
    "addr:street":"Martin Luther King Plz",
    "iso:country":"US",
    "sg:address":"27 Martin Luther King Plz",
    "sg:city":"Elizabeth",
    "sg:classifiers":[
        {
            "category":"Education",
            "subcategory":"School",
            "type":"Public Place"
        }
    ],
    "sg:phone":"+1 908 436 6767",
    "sg:postcode":"07201",
    "sg:province":"NJ",
    "sg:tags":[
        "high",
        "middle",
        "elementary"
    ],
    "wof:name":"Elizabeth City of",
    "wof:placetype":"venue"
},
  "geometry": {"coordinates":[-74.210993,40.663372],"type":"Point"}
}