{
  "type": "Feature",
  "properties": {
    "addr:full":"4 Tennis Ct Trenton NJ 08619",
    "addr:housenumber":"4",
    "addr:postcode":"08619",
    "addr:street":"Tennis Ct",
    "iso:country":"US",
    "sg:address":"4 Tennis Ct",
    "sg:city":"Trenton",
    "sg:classifiers":[
        {
            "category":"Education",
            "subcategory":"Dance Studio",
            "type":"Public Place"
        }
    ],
    "sg:phone":"+1 609 586 3008",
    "sg:postcode":"08619",
    "sg:province":"NJ",
    "sg:tags":[
        "instruction",
        "dancing"
    ],
    "wof:name":"Professional Center-The Arts",
    "wof:placetype":"venue"
},
  "geometry": {"coordinates":[-74.67796199999999,40.266438],"type":"Point"}
}