{
  "type": "Feature",
  "properties": {
    "iso:country":"US",
    "sg:address":"104 Ave C",
    "sg:city":"Newark",
    "sg:classifiers":[
        {
            "category":"Food & Beverages",
            "subcategory":"Bakery",
            "type":"Retail Goods"
        }
    ],
    "sg:phone":"+1   ",
    "sg:postcode":"07114",
    "sg:province":"NJ",
    "wof:name":"Bagel Distrubution Inc",
    "wof:placetype":"venue"
},
  "geometry": {"coordinates":[-74.174261,40.716124],"type":"Point"}
}