{
  "type": "Feature",
  "properties": {
    "iso:country":"US",
    "sg:address":"1615 Hamburg Tpke",
    "sg:city":"Wayne",
    "sg:classifiers":[
        {
            "category":"Real Estate",
            "subcategory":"Real Estate Services",
            "type":"Services"
        }
    ],
    "sg:phone":"+1 973 696 6696",
    "sg:postcode":"07470",
    "sg:province":"NJ",
    "sg:tags":[
        "company",
        "title"
    ],
    "wof:name":"Paramount Title Agency",
    "wof:placetype":"venue"
},
  "geometry": {"coordinates":[-74.25843,40.967818],"type":"Point"}
}