{
  "type": "Feature",
  "properties": {
    "addr:full":"4790 Black Horse Pike Blackwood NJ 08012",
    "addr:housenumber":"4790",
    "addr:postcode":"08012",
    "addr:street":"Black Horse Pike",
    "iso:country":"US",
    "sg:address":"4790 Black Horse Pike",
    "sg:city":"Blackwood",
    "sg:classifiers":[
        {
            "category":"Retail",
            "subcategory":"Auto Repair",
            "type":"Services"
        }
    ],
    "sg:phone":"+1 856 401 2022",
    "sg:postcode":"08012",
    "sg:province":"NJ",
    "sg:tags":[
        "transmission"
    ],
    "wof:name":"Cottman Transmissionlsr Enter",
    "wof:placetype":"venue"
},
  "geometry": {"coordinates":[-75.04525,39.747321],"type":"Point"}
}