{
  "type": "Feature",
  "properties": {
    "addr:full":"75 Montclair Ave Montclair NJ 07042",
    "addr:housenumber":"75",
    "addr:postcode":"07042",
    "addr:street":"Montclair Ave",
    "iso:country":"US",
    "sg:address":"75 Montclair Ave",
    "sg:city":"Montclair",
    "sg:classifiers":[
        {
            "category":"Professional",
            "type":"Services"
        }
    ],
    "sg:phone":"+1   ",
    "sg:postcode":"07042",
    "sg:province":"NJ",
    "wof:name":"Macoliz Inc",
    "wof:placetype":"venue"
},
  "geometry": {"coordinates":[-74.203799,40.824517],"type":"Point"}
}