{
  "type": "Feature",
  "properties": {
    "iso:country":"US",
    "sg:address":"331 Broadway",
    "sg:city":"Passaic",
    "sg:classifiers":[
        {
            "category":"Retail",
            "subcategory":"Repair Shop",
            "type":"Services"
        }
    ],
    "sg:phone":"+1 973 777 8057",
    "sg:postcode":"07055",
    "sg:province":"NJ",
    "sg:tags":[
        "reupholstery",
        "upholsterer",
        "furniture"
    ],
    "wof:name":"Broadway Upholstery Shop",
    "wof:placetype":"venue"
},
  "geometry": {"coordinates":[-74.13649700000001,40.8554],"type":"Point"}
}