{
  "type": "Feature",
  "properties": {
    "addr:full":"207 Faller Dr New Milford NJ 07646",
    "addr:housenumber":"207",
    "addr:postcode":"07646",
    "addr:street":"Faller Dr",
    "iso:country":"US",
    "sg:address":"207 Faller Dr",
    "sg:city":"New Milford",
    "sg:classifiers":[
        {
            "category":"Retail",
            "subcategory":"Repair Shop",
            "type":"Services"
        }
    ],
    "sg:phone":"+1   ",
    "sg:postcode":"07646",
    "sg:province":"NJ",
    "wof:name":"Allwood Floor Refinishing",
    "wof:placetype":"venue"
},
  "geometry": {"coordinates":[-74.023884,40.925305],"type":"Point"}
}