{
  "type": "Feature",
  "properties": {
    "iso:country":"US",
    "sg:address":"600 Pacific Ave",
    "sg:city":"Atlantic City",
    "sg:classifiers":[
        {
            "category":"Shopping",
            "type":"Retail Goods"
        },
        {
            "category":"Shopping",
            "subcategory":"Beauty & Cosmetics",
            "type":"Retail Goods"
        }
    ],
    "sg:phone":"+1 609 348 6716",
    "sg:postcode":"08401",
    "sg:province":"NJ",
    "sg:tags":[
        "merchandise",
        "perfume"
    ],
    "wof:name":"Satinee Cosmetics",
    "wof:placetype":"venue"
},
  "geometry": {"coordinates":[-74.418234,39.364137],"type":"Point"}
}