{
  "type": "Feature",
  "properties": {
    "addr:full":"8 W End Ave Hammonton NJ 08037",
    "addr:housenumber":"8",
    "addr:postcode":"08037",
    "addr:street":"W End Ave",
    "iso:country":"US",
    "sg:address":"8 W End Ave",
    "sg:city":"Hammonton",
    "sg:classifiers":[
        {
            "category":"Building & Trades",
            "subcategory":"Equipment Rental",
            "type":"Services"
        }
    ],
    "sg:phone":"+1 609 704 9211",
    "sg:postcode":"08037",
    "sg:province":"NJ",
    "sg:tags":[
        "medical",
        "durable",
        "rent"
    ],
    "wof:name":"Selfcare Mediquip Inc",
    "wof:placetype":"venue"
},
  "geometry": {"coordinates":[-74.807186,39.634158],"type":"Point"}
}