{
  "type": "Feature",
  "properties": {
    "iso:country":"US",
    "sg:address":"1055 Parsippany Blvd",
    "sg:city":"Parsippany",
    "sg:classifiers":[
        {
            "category":"Banks & Credit Unions",
            "subcategory":"Investment Brokerage",
            "type":"Services"
        },
        {
            "category":"Professional",
            "type":"Services"
        },
        {
            "category":"Insurance",
            "subcategory":"Insurance Agent",
            "type":"Services"
        }
    ],
    "sg:phone":"+1 973 334 2227",
    "sg:postcode":"07054",
    "sg:province":"NJ",
    "sg:tags":[
        "advisory",
        "establishment",
        "legal"
    ],
    "wof:name":"Planned Strategies Inc",
    "wof:placetype":"venue"
},
  "geometry": {"coordinates":[-74.421369,40.870653],"type":"Point"}
}