{
  "type": "Feature",
  "properties": {
    "addr:full":"249 Liberty Ave Jersey City NJ 07307",
    "addr:housenumber":"249",
    "addr:postcode":"07307",
    "addr:street":"Liberty Ave",
    "iso:country":"US",
    "sg:address":"249 Liberty Ave",
    "sg:city":"Jersey City",
    "sg:classifiers":[
        {
            "category":"Sports & Exercise",
            "subcategory":"Gym",
            "type":"Entertainment"
        }
    ],
    "sg:phone":"+1   ",
    "sg:postcode":"07307",
    "sg:province":"NJ",
    "sg:tags":[
        "fitness",
        "physical",
        "facility"
    ],
    "wof:name":"Personalized By Charmaine",
    "wof:placetype":"venue"
},
  "geometry": {"coordinates":[-74.059755,40.745897],"type":"Point"}
}