{
  "type": "Feature",
  "properties": {
    "addr:full":"7733 Bergenline Ave Ste 1 North Bergen NJ 07047",
    "addr:housenumber":"7733",
    "addr:postcode":"07047",
    "addr:street":"Bergenline Ave Ste 1",
    "iso:country":"US",
    "sg:address":"7733 Bergenline Ave Ste 1",
    "sg:city":"North Bergen",
    "sg:classifiers":[
        {
            "category":"Shopping",
            "subcategory":"Optician",
            "type":"Retail Goods"
        }
    ],
    "sg:phone":"+1 201 868 0768",
    "sg:postcode":"07047",
    "sg:province":"NJ",
    "sg:tags":[
        "eyewear"
    ],
    "wof:name":"Wise Optical Center",
    "wof:placetype":"venue"
},
  "geometry": {"coordinates":[-74.007401,40.8009],"type":"Point"}
}