{
  "type": "Feature",
  "properties": {
    "addr:full":"292 E Center St Clayton NJ 08312",
    "addr:housenumber":"292",
    "addr:postcode":"08312",
    "addr:street":"E Center St",
    "iso:country":"US",
    "sg:address":"292 E Center St",
    "sg:city":"Clayton",
    "sg:classifiers":[
        {
            "category":"Organizations",
            "subcategory":"Religious Organization",
            "type":"Services"
        }
    ],
    "sg:phone":"+1   ",
    "sg:postcode":"08312",
    "sg:province":"NJ",
    "wof:name":"Praise Temple Church",
    "wof:placetype":"venue"
},
  "geometry": {"coordinates":[-75.0869,39.658741],"type":"Point"}
}