{
  "type": "Feature",
  "properties": {
    "iso:country":"US",
    "sg:address":"801 N Main St",
    "sg:city":"Lanoka Harbor",
    "sg:classifiers":[
        {
            "category":"Social Services",
            "subcategory":"Child Care",
            "type":"Services"
        }
    ],
    "sg:phone":"+1   ",
    "sg:postcode":"08734",
    "sg:province":"NJ",
    "sg:tags":[
        "school",
        "nursery"
    ],
    "wof:name":"Happy Days Pre-School LLC",
    "wof:placetype":"venue"
},
  "geometry": {"coordinates":[-74.170205,39.865795],"type":"Point"}
}