{
  "type": "Feature",
  "properties": {
    "iso:country":"US",
    "sg:address":"508 Broadway",
    "sg:city":"Bayonne",
    "sg:classifiers":[
        {
            "category":"Shopping",
            "subcategory":"Discount & Variety Stores",
            "type":"Retail Goods"
        }
    ],
    "sg:phone":"+1 201 858 2055",
    "sg:postcode":"07002",
    "sg:province":"NJ",
    "wof:name":"S & A Stores Inc",
    "wof:placetype":"venue"
},
  "geometry": {"coordinates":[-74.11772000000001,40.664361],"type":"Point"}
}