{
  "type": "Feature",
  "properties": {
    "addr:full":"2558 Tilton Rd Egg Harbor Twp NJ 08234",
    "addr:housenumber":"2558",
    "addr:postcode":"08234",
    "addr:street":"Tilton Rd",
    "iso:country":"US",
    "sg:address":"2558 Tilton Rd",
    "sg:city":"Egg Harbor Twp",
    "sg:classifiers":[
        {
            "category":"Building & Trades",
            "subcategory":"Plumbing",
            "type":"Services"
        }
    ],
    "sg:phone":"+1 609 407 2111",
    "sg:postcode":"08234",
    "sg:province":"NJ",
    "sg:tags":[
        "conditioning",
        "air",
        "system",
        "contractor"
    ],
    "wof:name":"Shoreway Refrigeration Inc",
    "wof:placetype":"venue"
},
  "geometry": {"coordinates":[-74.57243699999999,39.421262],"type":"Point"}
}