{
  "type": "Feature",
  "properties": {
    "addr:full":"142 Wolfs Corner Rd Newton NJ 07860",
    "addr:housenumber":"142",
    "addr:postcode":"07860",
    "addr:street":"Wolfs Corner Rd",
    "iso:country":"US",
    "sg:address":"142 Wolfs Corner Rd",
    "sg:city":"Newton",
    "sg:classifiers":[
        {
            "category":"Building & Trades",
            "subcategory":"Landscaping Services",
            "type":"Services"
        }
    ],
    "sg:phone":"+1 973 300 9397",
    "sg:postcode":"07860",
    "sg:province":"NJ",
    "wof:name":"Johnson Lawn Care",
    "wof:placetype":"venue"
},
  "geometry": {"coordinates":[-74.80402599999999,40.989367],"type":"Point"}
}