{
  "type": "Feature",
  "properties": {
    "addr:full":"18 Buttonwood Ln Rumson NJ 07760",
    "addr:housenumber":"18",
    "addr:postcode":"07760",
    "addr:street":"Buttonwood Ln",
    "iso:country":"US",
    "sg:address":"18 Buttonwood Ln",
    "sg:city":"Rumson",
    "sg:classifiers":[
        {
            "category":"Professional",
            "type":"Services"
        }
    ],
    "sg:phone":"+1   ",
    "sg:postcode":"07760",
    "sg:province":"NJ",
    "wof:name":"F E Gilbertson M D P A",
    "wof:placetype":"venue"
},
  "geometry": {"coordinates":[-74.023656,40.346356],"type":"Point"}
}