{
  "type": "Feature",
  "properties": {
    "iso:country":"US",
    "sg:address":"310 Washington St",
    "sg:city":"Hoboken",
    "sg:classifiers":[
        {
            "category":"Bakery",
            "type":"Food & Drink"
        }
    ],
    "sg:menulink":"http://www.allmenus.com/nj/hoboken/33039-panera-bread/menu/",
    "sg:phone":"+1 201 876 3233",
    "sg:postcode":"07030",
    "sg:province":"NJ",
    "sg:tags":[
        "american",
        "sandwich",
        "pastry"
    ],
    "wof:name":"Panera Bread",
    "wof:placetype":"venue"
},
  "geometry": {"coordinates":[-74.030089,40.74013],"type":"Point"}
}