{
  "type": "Feature",
  "properties": {
    "addr:full":"5 Audrey Pl Fairfield NJ 07004",
    "addr:housenumber":"5",
    "addr:postcode":"07004",
    "addr:street":"Audrey Pl",
    "iso:country":"US",
    "sg:address":"5 Audrey Pl",
    "sg:city":"Fairfield",
    "sg:classifiers":[
        {
            "category":"Manufacturing",
            "subcategory":"Printing",
            "type":"Manufacturing & Wholesale Goods"
        }
    ],
    "sg:phone":"+1 973 344 9200",
    "sg:postcode":"07004",
    "sg:province":"NJ",
    "sg:tags":[
        "printer"
    ],
    "wof:name":"Delaser Printing Systems",
    "wof:placetype":"venue"
},
  "geometry": {"coordinates":[-74.290418,40.875272],"type":"Point"}
}