{
  "type": "Feature",
  "properties": {
    "iso:country":"US",
    "sg:address":"85 Quabeck Ave",
    "sg:city":"Irvington",
    "sg:classifiers":[
        {
            "category":"Manufacturing",
            "subcategory":"Rubber & Plastics",
            "type":"Manufacturing & Wholesale Goods"
        }
    ],
    "sg:phone":"+1 862 452 8441",
    "sg:postcode":"07111",
    "sg:province":"NJ",
    "sg:tags":[
        "product",
        "mfg"
    ],
    "wof:name":"E Traa",
    "wof:placetype":"venue"
},
  "geometry": {"coordinates":[-74.241665,40.711471],"type":"Point"}
}