{
  "type": "Feature",
  "properties": {
    "iso:country":"US",
    "sg:address":"15 Meadowbrook Rd",
    "sg:city":"Chatham",
    "sg:classifiers":[
        {
            "category":"Banks & Credit Unions",
            "subcategory":"Bank",
            "type":"Services"
        }
    ],
    "sg:phone":"+1 973 635 9700",
    "sg:postcode":"07928",
    "sg:province":"NJ",
    "sg:tags":[
        "other",
        "plan",
        "card"
    ],
    "wof:name":"American Express",
    "wof:placetype":"venue"
},
  "geometry": {"coordinates":[-74.393835,40.739546],"type":"Point"}
}