{
  "type": "Feature",
  "properties": {
    "addr:full":"1748 S Lincoln Ave Vineland NJ 08361",
    "addr:housenumber":"1748",
    "addr:postcode":"08361",
    "addr:street":"S Lincoln Ave",
    "iso:country":"US",
    "sg:address":"1748 S Lincoln Ave",
    "sg:city":"Vineland",
    "sg:classifiers":[
        {
            "category":"Banks & Credit Unions",
            "subcategory":"Bank",
            "type":"Services"
        }
    ],
    "sg:phone":"+1 856 794 7947",
    "sg:postcode":"08361",
    "sg:province":"NJ",
    "sg:website":"www.minotola.com",
    "wof:name":"Minotola National Bank",
    "wof:placetype":"venue"
},
  "geometry": {"coordinates":[-74.984894,39.458709],"type":"Point"}
}