{
  "type": "Feature",
  "properties": {
    "addr:full":"2088 Rt 130 south Monmouth junction NJ 08859",
    "addr:housenumber":"2088",
    "addr:postcode":"08859",
    "addr:street":"Rt 130 South",
    "iso:country":"US",
    "sg:address":"2088 Rt 130 south",
    "sg:city":"Monmouth junction",
    "sg:classifiers":[
        {
            "category":"Professional",
            "subcategory":"Computer Services",
            "type":"Services"
        }
    ],
    "sg:phone":"+1 212 300 5984",
    "sg:postcode":"08859",
    "sg:province":"NJ",
    "sg:tags":[
        "mobile-marketing",
        "mobile-store-front"
    ],
    "sg:website":"http://www.wire2air.com",
    "wof:name":"Wire2Air",
    "wof:placetype":"venue"
},
  "geometry": {"coordinates":[-74.288392,40.46024],"type":"Point"}
}