{
  "type": "Feature",
  "properties": {
    "addr:full":"401 Kings Hwy S Cherry Hill NJ 08034",
    "addr:housenumber":"401",
    "addr:postcode":"08034",
    "addr:street":"Kings Hwy S",
    "iso:country":"US",
    "sg:address":"401 Kings Hwy S",
    "sg:city":"Cherry Hill",
    "sg:classifiers":[
        {
            "category":"Social Services",
            "subcategory":"Child Care",
            "type":"Services"
        }
    ],
    "sg:phone":"+1 856 482 8558",
    "sg:postcode":"08034",
    "sg:province":"NJ",
    "wof:name":"Children's Discovery Ctr",
    "wof:placetype":"venue"
},
  "geometry": {"coordinates":[-75.013745,39.910914],"type":"Point"}
}