{
  "type": "Feature",
  "properties": {
    "addr:full":"27 Fairview Ave Summit NJ 07901",
    "addr:housenumber":"27",
    "addr:postcode":"07901",
    "addr:street":"Fairview Ave",
    "iso:country":"US",
    "sg:address":"27 Fairview Ave",
    "sg:city":"Summit",
    "sg:classifiers":[
        {
            "category":"Professional",
            "subcategory":"Management & Consulting",
            "type":"Services"
        }
    ],
    "sg:phone":"+1   ",
    "sg:postcode":"07901",
    "sg:province":"NJ",
    "sg:tags":[
        "business"
    ],
    "wof:name":"Stuermann Consulting",
    "wof:placetype":"venue"
},
  "geometry": {"coordinates":[-74.37432200000001,40.716251],"type":"Point"}
}