{
  "type": "Feature",
  "properties": {
    "iso:country":"US",
    "sg:address":"202 8th Ave",
    "sg:city":"Asbury Park",
    "sg:classifiers":[
        {
            "category":"Real Estate",
            "subcategory":"Real Estate Operator",
            "type":"Services"
        },
        {
            "category":"Travel",
            "subcategory":"Bed & Breakfast",
            "type":"Entertainment"
        }
    ],
    "sg:phone":"+1 732 988 3823",
    "sg:postcode":"07712",
    "sg:province":"NJ",
    "sg:tags":[
        "boarding",
        "house"
    ],
    "wof:name":"Shaker Capital LLC",
    "wof:placetype":"venue"
},
  "geometry": {"coordinates":[-74.00032,40.228352],"type":"Point"}
}