{
  "type": "Feature",
  "properties": {
    "addr:full":"249 Lodi St Hackensack NJ 07601",
    "addr:housenumber":"249",
    "addr:postcode":"07601",
    "addr:street":"Lodi St",
    "iso:country":"US",
    "sg:address":"249 Lodi St",
    "sg:city":"Hackensack",
    "sg:classifiers":[
        {
            "category":"Banks & Credit Unions",
            "subcategory":"Investment Brokerage",
            "type":"Services"
        }
    ],
    "sg:phone":"+1 201 488 4930",
    "sg:postcode":"07601",
    "sg:province":"NJ",
    "wof:name":"Na Pali Investments Inc",
    "wof:placetype":"venue"
},
  "geometry": {"coordinates":[-74.053802,40.875006],"type":"Point"}
}