{
  "type": "Feature",
  "properties": {
    "iso:country":"US",
    "sg:address":"111 S 16th Ave",
    "sg:city":"Longport",
    "sg:classifiers":[
        {
            "category":"Building & Trades",
            "subcategory":"Construction",
            "type":"Services"
        }
    ],
    "sg:phone":"+1 609 822 5448",
    "sg:postcode":"08403",
    "sg:province":"NJ",
    "sg:tags":[
        "installation",
        "furniture"
    ],
    "wof:name":"Morreale Baselice & Co LLC",
    "wof:placetype":"venue"
},
  "geometry": {"coordinates":[-74.531835,39.306587],"type":"Point"}
}