{
  "type": "Feature",
  "properties": {
    "addr:full":"636 Arnold Ave Pt Pleasant Bch NJ 08742",
    "addr:housenumber":"636",
    "addr:postcode":"08742",
    "addr:street":"Arnold Ave Pt",
    "iso:country":"US",
    "sg:address":"636 Arnold Ave",
    "sg:city":"Pt Pleasant Bch",
    "sg:classifiers":[
        {
            "category":"Personal",
            "type":"Services"
        }
    ],
    "sg:phone":"+1 732 714 7263",
    "sg:postcode":"08742",
    "sg:province":"NJ",
    "sg:tags":[
        "program",
        "physical",
        "exercise",
        "fitness"
    ],
    "wof:name":"Beach Pilates & Massage",
    "wof:placetype":"venue"
},
  "geometry": {"coordinates":[-74.04974300000001,40.09175],"type":"Point"}
}