{
  "type": "Feature",
  "properties": {
    "iso:country":"US",
    "sg:address":"96 Linwood Plz",
    "sg:city":"Fort Lee",
    "sg:classifiers":[
        {
            "category":"Professional",
            "subcategory":"Business Services",
            "type":"Services"
        }
    ],
    "sg:phone":"+1 212 613 1680",
    "sg:postcode":"07024",
    "sg:province":"NJ",
    "sg:tags":[
        "production",
        "music",
        "full"
    ],
    "wof:name":"US Girlz Entertainment",
    "wof:placetype":"venue"
},
  "geometry": {"coordinates":[-73.967997,40.861236],"type":"Point"}
}