{
  "type": "Feature",
  "properties": {
    "addr:full":"32 Newton Ave Woodbury NJ 08096",
    "addr:housenumber":"32",
    "addr:postcode":"08096",
    "addr:street":"Newton Ave",
    "iso:country":"US",
    "sg:address":"32 Newton Ave",
    "sg:city":"Woodbury",
    "sg:classifiers":[
        {
            "category":"Professional",
            "subcategory":"Lawyer & Legal Services",
            "type":"Services"
        }
    ],
    "sg:phone":"+1 856 686 4608",
    "sg:postcode":"08096",
    "sg:province":"NJ",
    "sg:tags":[
        "attorney"
    ],
    "wof:name":"Babst Calland Clements",
    "wof:placetype":"venue"
},
  "geometry": {"coordinates":[-75.150672,39.83828],"type":"Point"}
}