{
  "type": "Feature",
  "properties": {
    "iso:country":"US",
    "sg:address":"41 Long Ridge Rd",
    "sg:city":"Randolph",
    "sg:classifiers":[
        {
            "category":"Wholesale",
            "subcategory":"Home Furnishings",
            "type":"Manufacturing & Wholesale Goods"
        }
    ],
    "sg:phone":"+1 973 540 9691",
    "sg:postcode":"07869",
    "sg:province":"NJ",
    "sg:tags":[
        "wallpaper",
        "fabric",
        "furniture"
    ],
    "wof:name":"Puddingstone & Assoc Inc",
    "wof:placetype":"venue"
},
  "geometry": {"coordinates":[-74.519918,40.841711],"type":"Point"}
}