{
  "type": "Feature",
  "properties": {
    "addr:full":"140 Dutch Neck Rd Hightstown NJ 08520",
    "addr:housenumber":"140",
    "addr:postcode":"08520",
    "addr:street":"Dutch Neck Rd",
    "iso:country":"US",
    "sg:address":"140 Dutch Neck Rd",
    "sg:city":"Hightstown",
    "sg:classifiers":[
        {
            "category":"Organizations",
            "subcategory":"Community Association",
            "type":"Services"
        }
    ],
    "sg:phone":"+1 609 448 9738",
    "sg:postcode":"08520",
    "sg:province":"NJ",
    "sg:tags":[
        "military"
    ],
    "sg:website":"www.vfw.org",
    "wof:name":"Veterans Of Foreign Wars",
    "wof:placetype":"venue"
},
  "geometry": {"coordinates":[-74.53894,40.268878],"type":"Point"}
}