{
  "type": "Feature",
  "properties": {
    "addr:full":"1101 S Fairview St Delran NJ 08075",
    "addr:housenumber":"1101",
    "addr:postcode":"08075",
    "addr:street":"S Fairview St",
    "iso:country":"US",
    "sg:address":"1101 S Fairview St",
    "sg:city":"Delran",
    "sg:classifiers":[
        {
            "category":"Food & Beverages",
            "subcategory":"Groceries & Convenience Stores",
            "type":"Retail Goods"
        }
    ],
    "sg:phone":"+1 856 764 1590",
    "sg:postcode":"08075",
    "sg:province":"NJ",
    "sg:tags":[
        "market"
    ],
    "wof:name":"A & J Seabra Supermarket",
    "wof:placetype":"venue"
},
  "geometry": {"coordinates":[-74.95079800000001,40.027302],"type":"Point"}
}