{
  "type": "Feature",
  "properties": {
    "addr:full":"4 City Park Dr Millville NJ 08332",
    "addr:housenumber":"4",
    "addr:postcode":"08332",
    "addr:street":"City Park Dr",
    "iso:country":"US",
    "sg:address":"4 City Park Dr",
    "sg:city":"Millville",
    "sg:classifiers":[
        {
            "category":"Organizations",
            "subcategory":"Professional Association",
            "type":"Services"
        }
    ],
    "sg:phone":"+1 856 825 2600",
    "sg:postcode":"08332",
    "sg:province":"NJ",
    "sg:tags":[
        "chambers",
        "commerce"
    ],
    "wof:name":"Millville Chamber Of Commerce",
    "wof:placetype":"venue"
},
  "geometry": {"coordinates":[-75.04408100000001,39.395825],"type":"Point"}
}