{
  "type": "Feature",
  "properties": {
    "addr:full":"52 E Main St Bergenfield NJ 07621",
    "addr:housenumber":"52",
    "addr:postcode":"07621",
    "addr:street":"E Main St",
    "iso:country":"US",
    "sg:address":"52 E Main St",
    "sg:city":"Bergenfield",
    "sg:classifiers":[
        {
            "category":"Food & Beverages",
            "subcategory":"Groceries & Convenience Stores",
            "type":"Retail Goods"
        },
        {
            "category":"Restaurant",
            "type":"Food & Drink"
        }
    ],
    "sg:phone":"+1 201 385 0352",
    "sg:postcode":"07621",
    "sg:province":"NJ",
    "sg:tags":[
        "delicatessen"
    ],
    "wof:name":"Joey's Main Street Deli",
    "wof:placetype":"venue"
},
  "geometry": {"coordinates":[-73.993853,40.927884],"type":"Point"}
}