{
  "type": "Feature",
  "properties": {
    "iso:country":"US",
    "sg:address":"302 Trinity Ct",
    "sg:city":"Princeton",
    "sg:classifiers":[
        {
            "category":"Freight",
            "type":"Transportation"
        }
    ],
    "sg:phone":"+1 609 987 9423",
    "sg:postcode":"08540",
    "sg:province":"NJ",
    "sg:tags":[
        "delivery"
    ],
    "wof:name":"Exclusive Express Inc",
    "wof:placetype":"venue"
},
  "geometry": {"coordinates":[-74.658624,40.321568],"type":"Point"}
}