{
  "type": "Feature",
  "properties": {
    "addr:full":"291 Hilltop Rd Mendham NJ 07945",
    "addr:housenumber":"291",
    "addr:postcode":"07945",
    "addr:street":"Hilltop Rd",
    "iso:country":"US",
    "sg:address":"291 Hilltop Rd",
    "sg:city":"Mendham",
    "sg:classifiers":[
        {
            "category":"Professional",
            "type":"Services"
        }
    ],
    "sg:phone":"+1 973 543 0193",
    "sg:postcode":"07945",
    "sg:province":"NJ",
    "sg:tags":[
        "establishment"
    ],
    "wof:name":"Threshold Productions",
    "wof:placetype":"venue"
},
  "geometry": {"coordinates":[-74.604241,40.759254],"type":"Point"}
}