{
  "type": "Feature",
  "properties": {
    "iso:country":"US",
    "sg:address":"487 Market St",
    "sg:city":"Saddle Brook",
    "sg:classifiers":[
        {
            "category":"Health Services",
            "subcategory":"Dentist",
            "type":"Services"
        }
    ],
    "sg:phone":"+1 201 843 6505",
    "sg:postcode":"07663",
    "sg:province":"NJ",
    "wof:name":"Gersht Gary DMD",
    "wof:placetype":"venue"
},
  "geometry": {"coordinates":[-74.099998,40.8974],"type":"Point"}
}