{
  "type": "Feature",
  "properties": {
    "iso:country":"US",
    "sg:address":"50 US Hwy 9",
    "sg:city":"Morganville",
    "sg:classifiers":[
        {
            "category":"Professional",
            "subcategory":"Accounting & Tax Preparation",
            "type":"Services"
        }
    ],
    "sg:phone":"+1 732 617 6977",
    "sg:postcode":"07751",
    "sg:province":"NJ",
    "sg:tags":[
        "accountant",
        "auditing",
        "financial",
        "consulting"
    ],
    "wof:name":"Kumar & Co",
    "wof:placetype":"venue"
},
  "geometry": {"coordinates":[-74.305719,40.35764],"type":"Point"}
}