{
  "type": "Feature",
  "properties": {
    "iso:country":"US",
    "sg:address":"425 Gotham Pkwy",
    "sg:city":"Carlstadt",
    "sg:classifiers":[
        {
            "category":"Wholesale",
            "subcategory":"Durable Goods & Equipment",
            "type":"Manufacturing & Wholesale Goods"
        }
    ],
    "sg:phone":"+1 201 807 9720",
    "sg:postcode":"07072",
    "sg:province":"NJ",
    "sg:tags":[
        "importer"
    ],
    "wof:name":"Pyramid Trading Corp",
    "wof:placetype":"venue"
},
  "geometry": {"coordinates":[-74.070025,40.826797],"type":"Point"}
}