{
  "type": "Feature",
  "properties": {
    "iso:country":"US",
    "sg:address":"330 Totowa Ave",
    "sg:city":"Paterson",
    "sg:classifiers":[
        {
            "category":"Food & Beverages",
            "subcategory":"Groceries & Convenience Stores",
            "type":"Retail Goods"
        }
    ],
    "sg:phone":"+1   ",
    "sg:postcode":"07502",
    "sg:province":"NJ",
    "wof:name":"M & F Food Market",
    "wof:placetype":"venue"
},
  "geometry": {"coordinates":[-74.185804,40.917327],"type":"Point"}
}