{
  "type": "Feature",
  "properties": {
    "addr:full":"9 Main St Manasquan NJ 08736",
    "addr:housenumber":"9",
    "addr:postcode":"08736",
    "addr:street":"Main St",
    "iso:country":"US",
    "sg:address":"9 Main St",
    "sg:city":"Manasquan",
    "sg:classifiers":[
        {
            "category":"Building & Trades",
            "subcategory":"Plumbing",
            "type":"Services"
        }
    ],
    "sg:phone":"+1 732 223 1308",
    "sg:postcode":"08736",
    "sg:province":"NJ",
    "sg:tags":[
        "plumbing",
        "heating",
        "contractor"
    ],
    "wof:name":"Allen's Plumbing & Heating",
    "wof:placetype":"venue"
},
  "geometry": {"coordinates":[-74.053414,40.126023],"type":"Point"}
}