{
  "type": "Feature",
  "properties": {
    "addr:full":"25 W Hamilton Ave Englewood NJ 07631",
    "addr:housenumber":"25",
    "addr:postcode":"07631",
    "addr:street":"W Hamilton Ave",
    "iso:country":"US",
    "sg:address":"25 W Hamilton Ave",
    "sg:city":"Englewood",
    "sg:classifiers":[
        {
            "category":"Building & Trades",
            "subcategory":"Equipment Rental",
            "type":"Services"
        }
    ],
    "sg:phone":"+1 201 567 5666",
    "sg:postcode":"07631",
    "sg:province":"NJ",
    "sg:tags":[
        "party"
    ],
    "wof:name":"Gourmet Home Cuisine Catering",
    "wof:placetype":"venue"
},
  "geometry": {"coordinates":[-73.971358,40.901882],"type":"Point"}
}