{
  "type": "Feature",
  "properties": {
    "addr:full":"817 US Hwy 9 Manahawkin NJ 08050",
    "addr:housenumber":"817",
    "addr:postcode":"08050",
    "addr:street":"Us Hwy 9",
    "iso:country":"US",
    "sg:address":"817 US Hwy 9",
    "sg:city":"Manahawkin",
    "sg:classifiers":[
        {
            "category":"Autos & Motor Vehicles",
            "subcategory":"Auto Supplies",
            "type":"Retail Goods"
        }
    ],
    "sg:phone":"+1   ",
    "sg:postcode":"08050",
    "sg:province":"NJ",
    "sg:tags":[
        "shop",
        "automotive",
        "general",
        "tire",
        "repair"
    ],
    "wof:name":"S B R Tire Exchange Inc",
    "wof:placetype":"venue"
},
  "geometry": {"coordinates":[-74.249223,39.713253],"type":"Point"}
}