{
  "type": "Feature",
  "properties": {
    "addr:full":"55 Laauwe Ave Wayne NJ 07470",
    "addr:housenumber":"55",
    "addr:postcode":"07470",
    "addr:street":"Laauwe Ave",
    "iso:country":"US",
    "sg:address":"55 Laauwe Ave",
    "sg:city":"Wayne",
    "sg:classifiers":[
        {
            "category":"Freight",
            "type":"Transportation"
        }
    ],
    "sg:phone":"+1 973 942 8925",
    "sg:postcode":"07470",
    "sg:province":"NJ",
    "sg:tags":[
        "moving",
        "storage"
    ],
    "wof:name":"Wayne Moving & Storage Inc",
    "wof:placetype":"venue"
},
  "geometry": {"coordinates":[-74.222511,40.932877],"type":"Point"}
}