{
  "type": "Feature",
  "properties": {
    "addr:full":"220 Woodport Rd Sparta NJ 07871",
    "addr:housenumber":"220",
    "addr:postcode":"07871",
    "addr:street":"Woodport Rd",
    "iso:country":"US",
    "sg:address":"220 Woodport Rd",
    "sg:city":"Sparta",
    "sg:classifiers":[
        {
            "category":"Social Services",
            "type":"Services"
        }
    ],
    "sg:phone":"+1 973 726 9777",
    "sg:postcode":"07871",
    "sg:province":"NJ",
    "sg:tags":[
        "organization",
        "welfare"
    ],
    "wof:name":"Pass It Along",
    "wof:placetype":"venue"
},
  "geometry": {"coordinates":[-74.62773900000001,41.021586],"type":"Point"}
}