{
  "type": "Feature",
  "properties": {
    "addr:full":"66 Lincoln Ave Hawthorne NJ 07410",
    "addr:housenumber":"66",
    "addr:postcode":"07410",
    "addr:street":"Lincoln Ave",
    "iso:country":"US",
    "sg:address":"66 Lincoln Ave",
    "sg:city":"Hawthorne",
    "sg:classifiers":[
        {
            "category":"Government",
            "subcategory":"Fire Station",
            "type":"Public Place"
        }
    ],
    "sg:phone":"+1 973 427 9209",
    "sg:postcode":"07410",
    "sg:province":"NJ",
    "sg:tags":[
        "department"
    ],
    "wof:name":"Hawthorne Fire Co",
    "wof:placetype":"venue"
},
  "geometry": {"coordinates":[-74.147522,40.944836],"type":"Point"}
}