{
  "type": "Feature",
  "properties": {
    "addr:full":"299 Hillcrest Ave Trenton NJ 08618",
    "addr:housenumber":"299",
    "addr:postcode":"08618",
    "addr:street":"Hillcrest Ave",
    "iso:country":"US",
    "sg:address":"299 Hillcrest Ave",
    "sg:city":"Trenton",
    "sg:classifiers":[
        {
            "category":"Retail",
            "subcategory":"Auto Repair",
            "type":"Services"
        }
    ],
    "sg:phone":"+1 609 396 5538",
    "sg:postcode":"08618",
    "sg:province":"NJ",
    "sg:tags":[
        "repairing",
        "automobile"
    ],
    "wof:name":"Dario's Imported Car Svc",
    "wof:placetype":"venue"
},
  "geometry": {"coordinates":[-74.785185,40.241972],"type":"Point"}
}