{
  "type": "Feature",
  "properties": {
    "addr:full":"960 Cedar Bridge Ave Brick NJ 08701",
    "addr:housenumber":"960",
    "addr:postcode":"08701",
    "addr:street":"Cedar Bridge Ave",
    "iso:country":"US",
    "sg:address":"960 Cedar Bridge Ave",
    "sg:city":"Brick",
    "sg:classifiers":[
        {
            "category":"Professional",
            "type":"Services"
        }
    ],
    "sg:phone":"+1   ",
    "sg:postcode":"08701",
    "sg:province":"NJ",
    "wof:name":"Hcx Haircolorxperts",
    "wof:placetype":"venue"
},
  "geometry": {"coordinates":[-74.13312500000001,40.052819],"type":"Point"}
}