{
  "type": "Feature",
  "properties": {
    "addr:full":"321 Haddon Ave Collingswood NJ 08108",
    "addr:housenumber":"321",
    "addr:postcode":"08108",
    "addr:street":"Haddon Ave",
    "iso:country":"US",
    "sg:address":"321 Haddon Ave",
    "sg:city":"Collingswood",
    "sg:classifiers":[
        {
            "category":"Retail",
            "subcategory":"Laundry & Dry Cleaning",
            "type":"Services"
        }
    ],
    "sg:phone":"+1 856 869 0888",
    "sg:postcode":"08108",
    "sg:province":"NJ",
    "sg:tags":[
        "drycleaning",
        "plant"
    ],
    "wof:name":"Sun Cleaners",
    "wof:placetype":"venue"
},
  "geometry": {"coordinates":[-75.08049800000001,39.9202],"type":"Point"}
}