{
  "type": "Feature",
  "properties": {
    "iso:country":"US",
    "sg:address":"306 Locust Ave",
    "sg:city":"Garwood",
    "sg:classifiers":[
        {
            "category":"Wholesale",
            "subcategory":"Jewelry",
            "type":"Manufacturing & Wholesale Goods"
        }
    ],
    "sg:phone":"+1 908 232 2341",
    "sg:postcode":"07027",
    "sg:province":"NJ",
    "sg:tags":[
        "stone"
    ],
    "wof:name":"B K Enterprises Inc",
    "wof:placetype":"venue"
},
  "geometry": {"coordinates":[-74.324073,40.648527],"type":"Point"}
}