{
  "type": "Feature",
  "properties": {
    "iso:country":"US",
    "sg:address":"1480 State Rte 88",
    "sg:city":"Brick",
    "sg:classifiers":[
        {
            "category":"Professional",
            "subcategory":"Lawyer & Legal Services",
            "type":"Services"
        }
    ],
    "sg:phone":"+1 732 840 8005",
    "sg:postcode":"08724",
    "sg:province":"NJ",
    "wof:name":"Robert W Scott II Esq",
    "wof:placetype":"venue"
},
  "geometry": {"coordinates":[-74.144183,40.082282],"type":"Point"}
}