{
  "type": "Feature",
  "properties": {
    "iso:country":"US",
    "sg:address":"20 N Hill Dr",
    "sg:city":"Mt Holly",
    "sg:classifiers":[
        {
            "category":"Real Estate",
            "subcategory":"Real Estate Agent",
            "type":"Services"
        }
    ],
    "sg:phone":"+1 609 424 0404",
    "sg:postcode":"08060",
    "sg:province":"NJ",
    "sg:tags":[
        "inspection"
    ],
    "wof:name":"Absolute Home Inspection Svc",
    "wof:placetype":"venue"
},
  "geometry": {"coordinates":[-74.80839400000001,39.988257],"type":"Point"}
}