{
  "type": "Feature",
  "properties": {
    "iso:country":"US",
    "sg:address":"1059 Cedar Bridge Ave",
    "sg:city":"Brick",
    "sg:classifiers":[
        {
            "category":"Autos & Motor Vehicles",
            "subcategory":"Auto Supplies",
            "type":"Retail Goods"
        }
    ],
    "sg:phone":"+1 732 477 3480",
    "sg:postcode":"08723",
    "sg:province":"NJ",
    "sg:tags":[
        "tire"
    ],
    "sg:website":"www.vespiatires.com",
    "wof:name":"Vespia's Goodyear Tire Ctr",
    "wof:placetype":"venue"
},
  "geometry": {"coordinates":[-74.141881,40.055849],"type":"Point"}
}