{
  "type": "Feature",
  "properties": {
    "iso:country":"US",
    "sg:address":"425 Meadowlands Pkwy",
    "sg:city":"Secaucus",
    "sg:classifiers":[
        {
            "category":"Professional",
            "type":"Services"
        }
    ],
    "sg:phone":"+1 201 319 8787",
    "sg:postcode":"07094",
    "sg:province":"NJ",
    "sg:tags":[
        "establishment"
    ],
    "wof:name":"Alicomp",
    "wof:placetype":"venue"
},
  "geometry": {"coordinates":[-74.08111,40.779306],"type":"Point"}
}