{
  "type": "Feature",
  "properties": {
    "addr:full":"410 New St Plainfield NJ 07060",
    "addr:housenumber":"410",
    "addr:postcode":"07060",
    "addr:street":"New St",
    "iso:country":"US",
    "sg:address":"410 New St",
    "sg:city":"Plainfield",
    "sg:classifiers":[
        {
            "category":"Organizations",
            "subcategory":"Religious Organization",
            "type":"Services"
        }
    ],
    "sg:phone":"+1   ",
    "sg:postcode":"07060",
    "sg:province":"NJ",
    "wof:name":"Iglesia Pentecostal Unida De",
    "wof:placetype":"venue"
},
  "geometry": {"coordinates":[-74.42305399999999,40.613292],"type":"Point"}
}