{
  "type": "Feature",
  "properties": {
    "addr:full":"473 Old Hook Rd Emerson NJ 07630",
    "addr:housenumber":"473",
    "addr:postcode":"07630",
    "addr:street":"Old Hook Rd",
    "iso:country":"US",
    "sg:address":"473 Old Hook Rd",
    "sg:city":"Emerson",
    "sg:classifiers":[
        {
            "category":"Shopping",
            "subcategory":"Clothing, Apparel, & Fashions",
            "type":"Retail Goods"
        }
    ],
    "sg:phone":"+1 201 634 0111",
    "sg:postcode":"07630",
    "sg:province":"NJ",
    "sg:tags":[
        "uniform"
    ],
    "wof:name":"Flynn & OHara Uniforms Inc",
    "wof:placetype":"venue"
},
  "geometry": {"coordinates":[-74.00581200000001,40.981622],"type":"Point"}
}