{
  "type": "Feature",
  "properties": {
    "iso:country":"US",
    "sg:address":"613 Fountain Ave",
    "sg:city":"Burlington",
    "sg:classifiers":[
        {
            "category":"Professional",
            "subcategory":"Accounting & Tax Preparation",
            "type":"Services"
        }
    ],
    "sg:phone":"+1 609 386 1816",
    "sg:postcode":"08016",
    "sg:province":"NJ",
    "sg:tags":[
        "return",
        "filing"
    ],
    "wof:name":"Lane Tax & Financial Svc",
    "wof:placetype":"venue"
},
  "geometry": {"coordinates":[-74.83835000000001,40.064582],"type":"Point"}
}