{
  "type": "Feature",
  "properties": {
    "iso:country":"US",
    "sg:address":"563 Petersburg Rd",
    "sg:city":"Woodbine",
    "sg:classifiers":[
        {
            "category":"Building & Trades",
            "subcategory":"Construction",
            "type":"Services"
        }
    ],
    "sg:phone":"+1 609 861 5081",
    "sg:postcode":"08270",
    "sg:province":"NJ",
    "sg:tags":[
        "contractor"
    ],
    "wof:name":"Robert Sutton Contractor",
    "wof:placetype":"venue"
},
  "geometry": {"coordinates":[-74.81041,39.19689],"type":"Point"}
}