{
  "type": "Feature",
  "properties": {
    "iso:country":"US",
    "sg:address":"189 19th Ave",
    "sg:city":"Brick",
    "sg:classifiers":[
        {
            "category":"Building & Trades",
            "subcategory":"Construction",
            "type":"Services"
        }
    ],
    "sg:phone":"+1 732 458 8530",
    "sg:postcode":"08724",
    "sg:province":"NJ",
    "sg:tags":[
        "housing",
        "family"
    ],
    "wof:name":"Miller Brothers Construction",
    "wof:placetype":"venue"
},
  "geometry": {"coordinates":[-74.093851,40.09822],"type":"Point"}
}