{
  "type": "Feature",
  "properties": {
    "addr:full":"55 State Rte 31 Pennington NJ 08534",
    "addr:housenumber":"55",
    "addr:postcode":"08534",
    "addr:street":"State Rte 31",
    "iso:country":"US",
    "sg:address":"55 State Rte 31",
    "sg:city":"Pennington",
    "sg:classifiers":[
        {
            "category":"Professional",
            "subcategory":"Research",
            "type":"Services"
        }
    ],
    "sg:phone":"+1 609 818 0700",
    "sg:postcode":"08534",
    "sg:province":"NJ",
    "sg:tags":[
        "water",
        "company",
        "management",
        "solar",
        "power"
    ],
    "wof:name":"Worldwater Corporation",
    "wof:placetype":"venue"
},
  "geometry": {"coordinates":[-74.79643299999999,40.345593],"type":"Point"}
}