{
  "type": "Feature",
  "properties": {
    "addr:full":"195 Nassau St Princeton NJ 08542",
    "addr:housenumber":"195",
    "addr:postcode":"08542",
    "addr:street":"Nassau St",
    "iso:country":"US",
    "sg:address":"195 Nassau St",
    "sg:city":"Princeton",
    "sg:classifiers":[
        {
            "category":"Freight",
            "type":"Transportation"
        }
    ],
    "sg:phone":"+1 609 497 9600",
    "sg:postcode":"08542",
    "sg:province":"NJ",
    "sg:tags":[
        "mover"
    ],
    "sg:website":"www.princetonmoving.com",
    "wof:name":"Princeton Van Svc",
    "wof:placetype":"venue"
},
  "geometry": {"coordinates":[-74.654073,40.351383],"type":"Point"}
}