{
  "type": "Feature",
  "properties": {
    "addr:full":"28 E Prospect St Waldwick NJ 07463",
    "addr:housenumber":"28",
    "addr:postcode":"07463",
    "addr:street":"E Prospect St",
    "iso:country":"US",
    "sg:address":"28 E Prospect St",
    "sg:city":"Waldwick",
    "sg:classifiers":[
        {
            "category":"Home & Garden",
            "subcategory":"Building Materials",
            "type":"Retail Goods"
        }
    ],
    "sg:phone":"+1 201 444 2882",
    "sg:postcode":"07463",
    "sg:province":"NJ",
    "sg:tags":[
        "paint",
        "wallpaper",
        "wallcoverings"
    ],
    "sg:website":"http://www.waldwickpaint.com",
    "wof:name":"Waldwick Paint CO",
    "wof:placetype":"venue"
},
  "geometry": {"coordinates":[-74.117105,41.01071],"type":"Point"}
}