{
  "type": "Feature",
  "properties": {
    "addr:full":"43 Park Pl Pompton Lakes NJ 07442",
    "addr:housenumber":"43",
    "addr:postcode":"07442",
    "addr:street":"Park Pl",
    "iso:country":"US",
    "sg:address":"43 Park Pl",
    "sg:city":"Pompton Lakes",
    "sg:classifiers":[
        {
            "category":"Professional",
            "subcategory":"Management & Consulting",
            "type":"Services"
        }
    ],
    "sg:phone":"+1 973 831 4409",
    "sg:postcode":"07442",
    "sg:province":"NJ",
    "sg:tags":[
        "construction"
    ],
    "wof:name":"Scott Bavosa Construction",
    "wof:placetype":"venue"
},
  "geometry": {"coordinates":[-74.274107,41.010974],"type":"Point"}
}