{
  "type": "Feature",
  "properties": {
    "addr:full":"130 Maple Ave Red Bank NJ 07701",
    "addr:housenumber":"130",
    "addr:postcode":"07701",
    "addr:street":"Maple Ave",
    "iso:country":"US",
    "sg:address":"130 Maple Ave",
    "sg:city":"Red Bank",
    "sg:classifiers":[
        {
            "category":"Health Services",
            "subcategory":"Chiropractor",
            "type":"Services"
        }
    ],
    "sg:phone":"+1 732 842 7004",
    "sg:postcode":"07701",
    "sg:province":"NJ",
    "wof:name":"Wilson Pamela E DC",
    "wof:placetype":"venue"
},
  "geometry": {"coordinates":[-74.068528,40.346015],"type":"Point"}
}