{
  "type": "Feature",
  "properties": {
    "addr:full":"15 Tallahatchie Dr Sussex NJ 07461",
    "addr:housenumber":"15",
    "addr:postcode":"07461",
    "addr:street":"Tallahatchie Dr",
    "iso:country":"US",
    "sg:address":"15 Tallahatchie Dr",
    "sg:city":"Sussex",
    "sg:classifiers":[
        {
            "category":"Building & Trades",
            "subcategory":"Construction",
            "type":"Services"
        }
    ],
    "sg:phone":"+1 973 702 0531",
    "sg:postcode":"07461",
    "sg:province":"NJ",
    "sg:tags":[
        "carpentry"
    ],
    "wof:name":"LDL Carpentry",
    "wof:placetype":"venue"
},
  "geometry": {"coordinates":[-74.55492099999999,41.217479],"type":"Point"}
}