{
  "type": "Feature",
  "properties": {
    "addr:full":"2 Brunswick Woods Dr East Brunswick NJ 08816",
    "addr:housenumber":"2",
    "addr:postcode":"08816",
    "addr:street":"Brunswick Woods Dr",
    "iso:country":"US",
    "sg:address":"2 Brunswick Woods Dr",
    "sg:city":"East Brunswick",
    "sg:classifiers":[
        {
            "category":"Social Services",
            "type":"Services"
        }
    ],
    "sg:phone":"+1 732 238 6400",
    "sg:postcode":"08816",
    "sg:province":"NJ",
    "sg:tags":[
        "instruction",
        "health",
        "care"
    ],
    "wof:name":"Fein Group LLC",
    "wof:placetype":"venue"
},
  "geometry": {"coordinates":[-74.389532,40.421004],"type":"Point"}
}