{
  "type": "Feature",
  "properties": {
    "iso:country":"US",
    "sg:address":"27 Montgomery St",
    "sg:city":"Hillside",
    "sg:classifiers":[
        {
            "category":"Shopping",
            "subcategory":"Discount & Variety Stores",
            "type":"Retail Goods"
        }
    ],
    "sg:phone":"+1 908 810 1444",
    "sg:postcode":"07205",
    "sg:province":"NJ",
    "sg:tags":[
        "post",
        "trading"
    ],
    "wof:name":"L N Global Intl Trading",
    "wof:placetype":"venue"
},
  "geometry": {"coordinates":[-74.23560999999999,40.70439],"type":"Point"}
}