{
  "type": "Feature",
  "properties": {
    "addr:full":"59 Harvey Dr Short Hills NJ 07078",
    "addr:housenumber":"59",
    "addr:postcode":"07078",
    "addr:street":"Harvey Dr",
    "iso:country":"US",
    "sg:address":"59 Harvey Dr",
    "sg:city":"Short Hills",
    "sg:classifiers":[
        {
            "category":"Professional",
            "subcategory":"Management & Consulting",
            "type":"Services"
        }
    ],
    "sg:phone":"+1   ",
    "sg:postcode":"07078",
    "sg:province":"NJ",
    "wof:name":"Triple Squared Inc",
    "wof:placetype":"venue"
},
  "geometry": {"coordinates":[-74.33942500000001,40.744602],"type":"Point"}
}