{
  "type": "Feature",
  "properties": {
    "addr:full":"272 River Rd Edgewater NJ 07020",
    "addr:housenumber":"272",
    "addr:postcode":"07020",
    "addr:street":"River Rd",
    "iso:country":"US",
    "sg:address":"272 River Rd",
    "sg:city":"Edgewater",
    "sg:classifiers":[
        {
            "category":"Utilities",
            "subcategory":"Mobile Phone",
            "type":"Services"
        }
    ],
    "sg:phone":"+1 201 313 8333",
    "sg:postcode":"07020",
    "sg:province":"NJ",
    "sg:tags":[
        "telephone",
        "cellular"
    ],
    "wof:name":"Pcs Viva Kim",
    "wof:placetype":"venue"
},
  "geometry": {"coordinates":[-73.98801899999999,40.811085],"type":"Point"}
}