{
  "type": "Feature",
  "properties": {
    "addr:full":"58 Baldwin Ave Newark NJ 07108",
    "addr:housenumber":"58",
    "addr:postcode":"07108",
    "addr:street":"Baldwin Ave",
    "iso:country":"US",
    "sg:address":"58 Baldwin Ave",
    "sg:city":"Newark",
    "sg:classifiers":[
        {
            "category":"Building & Trades",
            "subcategory":"Electrical",
            "type":"Services"
        }
    ],
    "sg:phone":"+1 973 622 6652",
    "sg:postcode":"07108",
    "sg:province":"NJ",
    "sg:tags":[
        "electrical",
        "contractor"
    ],
    "wof:name":"Advanced Electric",
    "wof:placetype":"venue"
},
  "geometry": {"coordinates":[-74.20509199999999,40.722691],"type":"Point"}
}