{
  "type": "Feature",
  "properties": {
    "addr:full":"125 W State St Trenton NJ 08618",
    "addr:housenumber":"125",
    "addr:postcode":"08618",
    "addr:street":"W State St",
    "iso:country":"US",
    "sg:address":"125 W State St",
    "sg:city":"Trenton",
    "sg:classifiers":[
        {
            "category":"Restaurant",
            "type":"Food & Drink"
        }
    ],
    "sg:phone":"+1   ",
    "sg:postcode":"08618",
    "sg:province":"NJ",
    "sg:tags":[
        "eating"
    ],
    "wof:name":"Sweet Heaven",
    "wof:placetype":"venue"
},
  "geometry": {"coordinates":[-74.77090200000001,40.221261],"type":"Point"}
}