{
  "type": "Feature",
  "properties": {
    "iso:country":"US",
    "sg:address":"66 Passaic St",
    "sg:city":"Garfield",
    "sg:classifiers":[
        {
            "category":"Banks & Credit Unions",
            "subcategory":"Bank",
            "type":"Services"
        }
    ],
    "sg:phone":"+1 973 779 6665",
    "sg:postcode":"07026",
    "sg:province":"NJ",
    "sg:tags":[
        "money",
        "order"
    ],
    "wof:name":"Envios Elcosteno",
    "wof:placetype":"venue"
},
  "geometry": {"coordinates":[-74.107564,40.86582],"type":"Point"}
}