{
  "type": "Feature",
  "properties": {
    "iso:country":"US",
    "sg:address":"634 Gorge Rd",
    "sg:city":"Cliffside Park",
    "sg:classifiers":[
        {
            "category":"Banks & Credit Unions",
            "subcategory":"Bank",
            "type":"Services"
        }
    ],
    "sg:phone":"+1 201 313 9087",
    "sg:postcode":"07010",
    "sg:province":"NJ",
    "sg:tags":[
        "loan",
        "real estate"
    ],
    "wof:name":"Trans Global Mortgage Corp",
    "wof:placetype":"venue"
},
  "geometry": {"coordinates":[-73.987487,40.824906],"type":"Point"}
}