{
  "type": "Feature",
  "properties": {
    "addr:full":"34 Krakow St Garfield NJ 07026",
    "addr:housenumber":"34",
    "addr:postcode":"07026",
    "addr:street":"Krakow St",
    "iso:country":"US",
    "sg:address":"34 Krakow St",
    "sg:city":"Garfield",
    "sg:classifiers":[
        {
            "category":"Building & Trades",
            "subcategory":"Construction",
            "type":"Services"
        }
    ],
    "sg:phone":"+1 973 928 1111",
    "sg:postcode":"07026",
    "sg:province":"NJ",
    "sg:tags":[
        "contractor"
    ],
    "wof:name":"Beyco Construction",
    "wof:placetype":"venue"
},
  "geometry": {"coordinates":[-74.099424,40.881718],"type":"Point"}
}