{
  "type": "Feature",
  "properties": {
    "iso:country":"US",
    "sg:address":"265 W Grand St",
    "sg:city":"Elizabeth",
    "sg:classifiers":[
        {
            "category":"Building & Trades",
            "subcategory":"Plumbing",
            "type":"Services"
        }
    ],
    "sg:phone":"+1 908 354 3361",
    "sg:postcode":"07202",
    "sg:province":"NJ",
    "sg:tags":[
        "plumbing",
        "heating",
        "contractor"
    ],
    "sg:website":"www.ags.com",
    "wof:name":"AGS Plumbing & Heating Corp",
    "wof:placetype":"venue"
},
  "geometry": {"coordinates":[-74.225229,40.665593],"type":"Point"}
}