{
  "type": "Feature",
  "properties": {
    "iso:country":"US",
    "sg:address":"131 Rogers Ave",
    "sg:city":"Hightstown",
    "sg:classifiers":[
        {
            "category":"Government",
            "subcategory":"Office",
            "type":"Public Place"
        }
    ],
    "sg:phone":"+1   ",
    "sg:postcode":"08520",
    "sg:province":"NJ",
    "sg:tags":[
        "housing",
        "low",
        "income"
    ],
    "wof:name":"Hightstown Housing Authority",
    "wof:placetype":"venue"
},
  "geometry": {"coordinates":[-74.525881,40.269723],"type":"Point"}
}