{
  "type": "Feature",
  "properties": {
    "iso:country":"US",
    "sg:address":"111 Cedar Ave",
    "sg:city":"Newark",
    "sg:classifiers":[
        {
            "category":"Food & Beverages",
            "subcategory":"Groceries & Convenience Stores",
            "type":"Retail Goods"
        }
    ],
    "sg:phone":"+1 973 374 2744",
    "sg:postcode":"07106",
    "sg:province":"NJ",
    "sg:tags":[
        "grocer"
    ],
    "wof:name":"Tremont Grocery",
    "wof:placetype":"venue"
},
  "geometry": {"coordinates":[-74.21887,40.746967],"type":"Point"}
}