{
  "type": "Feature",
  "properties": {
    "iso:country":"US",
    "sg:address":"34 Lincoln Ave",
    "sg:city":"Florham Park",
    "sg:classifiers":[
        {
            "category":"Building & Trades",
            "subcategory":"Construction",
            "type":"Services"
        }
    ],
    "sg:phone":"+1 973 377 1246",
    "sg:postcode":"07932",
    "sg:province":"NJ",
    "sg:tags":[
        "light",
        "carpentry",
        "painting",
        "contractor"
    ],
    "wof:name":"JC Home Improvements Inc",
    "wof:placetype":"venue"
},
  "geometry": {"coordinates":[-74.38814600000001,40.773433],"type":"Point"}
}