{
  "type": "Feature",
  "properties": {
    "addr:full":"157 7th Ave Newark NJ 07104",
    "addr:housenumber":"157",
    "addr:postcode":"07104",
    "addr:street":"7Th Ave",
    "iso:country":"US",
    "sg:address":"157 7th Ave",
    "sg:city":"Newark",
    "sg:classifiers":[
        {
            "category":"Banks & Credit Unions",
            "subcategory":"Bank",
            "type":"Services"
        }
    ],
    "sg:phone":"+1 973 481 4840",
    "sg:postcode":"07104",
    "sg:province":"NJ",
    "sg:tags":[
        "saving",
        "institution"
    ],
    "sg:website":"www.hcsbonline.com",
    "wof:name":"Hudson City Savings Bank",
    "wof:placetype":"venue"
},
  "geometry": {"coordinates":[-74.17849699999999,40.751202],"type":"Point"}
}