{
  "type": "Feature",
  "properties": {
    "iso:country":"US",
    "sg:address":"16 Washington St",
    "sg:city":"Keyport",
    "sg:classifiers":[
        {
            "category":"Building & Trades",
            "subcategory":"Landscaping Services",
            "type":"Services"
        }
    ],
    "sg:phone":"+1 732 739 4927",
    "sg:postcode":"07735",
    "sg:province":"NJ",
    "sg:tags":[
        "landscape"
    ],
    "wof:name":"Garden Gate Landscaping LLC",
    "wof:placetype":"venue"
},
  "geometry": {"coordinates":[-74.210583,40.435849],"type":"Point"}
}