{
  "type": "Feature",
  "properties": {
    "iso:country":"US",
    "sg:address":"177 Hanover Rd",
    "sg:city":"East Hanover",
    "sg:classifiers":[
        {
            "category":"Professional",
            "subcategory":"Business Services",
            "type":"Services"
        }
    ],
    "sg:phone":"+1 973 285 0990",
    "sg:postcode":"07936",
    "sg:province":"NJ",
    "sg:tags":[
        "repossessing"
    ],
    "wof:name":"Metropolitan Recovery Bureau",
    "wof:placetype":"venue"
},
  "geometry": {"coordinates":[-74.372986,40.797744],"type":"Point"}
}