{
  "type": "Feature",
  "properties": {
    "iso:country":"US",
    "sg:address":"313 57th St",
    "sg:city":"Sea Isle City",
    "sg:classifiers":[
        {
            "category":"Building & Trades",
            "subcategory":"Cleaning & Sanitation",
            "type":"Services"
        }
    ],
    "sg:phone":"+1 609 263 3128",
    "sg:postcode":"08243",
    "sg:province":"NJ",
    "sg:tags":[
        "house"
    ],
    "wof:name":"Top Of Bottom Cleaning",
    "wof:placetype":"venue"
},
  "geometry": {"coordinates":[-74.704551,39.147013],"type":"Point"}
}