{
  "type": "Feature",
  "properties": {
    "iso:country":"US",
    "sg:address":"103 Johnson Ave",
    "sg:city":"Oaklyn",
    "sg:classifiers":[
        {
            "category":"Building & Trades",
            "subcategory":"Construction",
            "type":"Services"
        }
    ],
    "sg:phone":"+1 856 854 4367",
    "sg:postcode":"08107",
    "sg:province":"NJ",
    "sg:tags":[
        "general"
    ],
    "wof:name":"L & M Enterprises",
    "wof:placetype":"venue"
},
  "geometry": {"coordinates":[-75.078282,39.906692],"type":"Point"}
}