{
  "type": "Feature",
  "properties": {
    "iso:country":"US",
    "sg:address":"68 Co Rd 521",
    "sg:city":"Newton",
    "sg:classifiers":[
        {
            "category":"Wholesale",
            "subcategory":"Fruits & Vegetables",
            "type":"Manufacturing & Wholesale Goods"
        }
    ],
    "sg:phone":"+1 973 948 0593",
    "sg:postcode":"07860",
    "sg:province":"NJ",
    "wof:name":"Newton Produce",
    "wof:placetype":"venue"
},
  "geometry": {"coordinates":[-74.822965,41.151411],"type":"Point"}
}