{
  "type": "Feature",
  "properties": {
    "addr:full":"1355 Gillian Ct Toms River NJ 08753",
    "addr:housenumber":"1355",
    "addr:postcode":"08753",
    "addr:street":"Gillian Ct",
    "iso:country":"US",
    "sg:address":"1355 Gillian Ct",
    "sg:city":"Toms River",
    "sg:classifiers":[
        {
            "category":"Professional",
            "subcategory":"Business Services",
            "type":"Services"
        }
    ],
    "sg:phone":"+1   ",
    "sg:postcode":"08753",
    "sg:province":"NJ",
    "wof:name":"Biggiani & Sons LLC",
    "wof:placetype":"venue"
},
  "geometry": {"coordinates":[-74.149918,39.963096],"type":"Point"}
}