{
  "type": "Feature",
  "properties": {
    "addr:full":"37 N 2nd St Phillipsburg NJ 08865",
    "addr:housenumber":"37",
    "addr:postcode":"08865",
    "addr:street":"N 2Nd St",
    "iso:country":"US",
    "sg:address":"37 N 2nd St",
    "sg:city":"Phillipsburg",
    "sg:classifiers":[
        {
            "category":"Organizations",
            "subcategory":"Professional Association",
            "type":"Services"
        }
    ],
    "sg:phone":"+1 908 859 2061",
    "sg:postcode":"08865",
    "sg:province":"NJ",
    "sg:website":"www.57fire.com",
    "wof:name":"New Village Firemen's Club",
    "wof:placetype":"venue"
},
  "geometry": {"coordinates":[-75.19069399999999,40.704762],"type":"Point"}
}