{
  "type": "Feature",
  "properties": {
    "addr:full":"42 Tallowood Dr Medford NJ 08055",
    "addr:housenumber":"42",
    "addr:postcode":"08055",
    "addr:street":"Tallowood Dr",
    "iso:country":"US",
    "sg:address":"42 Tallowood Dr",
    "sg:city":"Medford",
    "sg:classifiers":[
        {
            "category":"Health Services",
            "subcategory":"Clinic",
            "type":"Services"
        }
    ],
    "sg:phone":"+1 609 953 9380",
    "sg:postcode":"08055",
    "sg:province":"NJ",
    "sg:tags":[
        "parenting-centers",
        "childbirth",
        "education",
        "birth"
    ],
    "sg:website":"www.birthworks.com",
    "wof:name":"Birth Works Inc",
    "wof:placetype":"venue"
},
  "geometry": {"coordinates":[-74.828148,39.858311],"type":"Point"}
}