{
  "type": "Feature",
  "properties": {
    "addr:full":"66 E Main St Moorestown NJ 08057",
    "addr:housenumber":"66",
    "addr:postcode":"08057",
    "addr:street":"E Main St",
    "iso:country":"US",
    "sg:address":"66 E Main St",
    "sg:city":"Moorestown",
    "sg:classifiers":[
        {
            "category":"Personal",
            "subcategory":"Barber",
            "type":"Services"
        }
    ],
    "sg:phone":"+1 856 802 1442",
    "sg:postcode":"08057",
    "sg:province":"NJ",
    "sg:tags":[
        "shop"
    ],
    "wof:name":"Men's Headquarters",
    "wof:placetype":"venue"
},
  "geometry": {"coordinates":[-74.94541599999999,39.964301],"type":"Point"}
}