{
  "type": "Feature",
  "properties": {
    "addr:full":"1 Millburn Ave Millburn NJ 07041",
    "addr:housenumber":"1",
    "addr:postcode":"07041",
    "addr:street":"Millburn Ave",
    "iso:country":"US",
    "sg:address":"1 Millburn Ave",
    "sg:city":"Millburn",
    "sg:classifiers":[
        {
            "category":"Home & Garden",
            "subcategory":"Furniture",
            "type":"Retail Goods"
        }
    ],
    "sg:phone":"+1 973 376 5700",
    "sg:postcode":"07041",
    "sg:province":"NJ",
    "sg:tags":[
        "equipment",
        "kitchen",
        "cabinet"
    ],
    "sg:website":"www.sawhorsedesigns.com",
    "wof:name":"Saw Horse Designs",
    "wof:placetype":"venue"
},
  "geometry": {"coordinates":[-74.28553599999999,40.722747],"type":"Point"}
}