{
  "type": "Feature",
  "properties": {
    "addr:full":"299 South Ave E Westfield NJ 07090",
    "addr:housenumber":"299",
    "addr:postcode":"07090",
    "addr:street":"South Ave E",
    "iso:country":"US",
    "sg:address":"299 South Ave E",
    "sg:city":"Westfield",
    "sg:classifiers":[
        {
            "category":"Sports & Exercise",
            "subcategory":"Gym",
            "type":"Entertainment"
        }
    ],
    "sg:phone":"+1 908 232 3200",
    "sg:postcode":"07090",
    "sg:province":"NJ",
    "sg:tags":[
        "fitness",
        "facility"
    ],
    "wof:name":"Open Window",
    "wof:placetype":"venue"
},
  "geometry": {"coordinates":[-74.34065099999999,40.649395],"type":"Point"}
}