{
  "type": "Feature",
  "properties": {
    "addr:full":"130 State Route 10 Whippany NJ 07981",
    "addr:housenumber":"130",
    "addr:postcode":"07981",
    "addr:street":"State Route 10",
    "iso:country":"US",
    "sg:address":"130 State Route 10",
    "sg:city":"Whippany",
    "sg:classifiers":[
        {
            "category":"Autos & Motor Vehicles",
            "subcategory":"Automobile Sales",
            "type":"Retail Goods"
        }
    ],
    "sg:phone":"+1 973 319 7900",
    "sg:postcode":"07981",
    "sg:province":"NJ",
    "sg:tags":[
        "car"
    ],
    "sg:website":"www.lexus.com",
    "wof:name":"Warnock Lexus",
    "wof:placetype":"venue"
},
  "geometry": {"coordinates":[-74.39841199999999,40.814788],"type":"Point"}
}