{
  "type": "Feature",
  "properties": {
    "addr:full":"3119 Revere Blvd Brigantine NJ 08203",
    "addr:housenumber":"3119",
    "addr:postcode":"08203",
    "addr:street":"Revere Blvd",
    "iso:country":"US",
    "sg:address":"3119 Revere Blvd",
    "sg:city":"Brigantine",
    "sg:classifiers":[
        {
            "category":"Professional",
            "type":"Services"
        }
    ],
    "sg:phone":"+1   ",
    "sg:postcode":"08203",
    "sg:province":"NJ",
    "wof:name":"3119 Revere Boulevard LLC",
    "wof:placetype":"venue"
},
  "geometry": {"coordinates":[-74.38681699999999,39.395564],"type":"Point"}
}