{
  "type": "Feature",
  "properties": {
    "iso:country":"US",
    "sg:address":"234 Passaic Ave",
    "sg:city":"Fairfield",
    "sg:classifiers":[
        {
            "category":"Building & Trades",
            "subcategory":"Locksmith",
            "type":"Services"
        }
    ],
    "sg:phone":"+1 888 484 6887",
    "sg:postcode":"07004",
    "sg:province":"NJ",
    "sg:tags":[
        "key"
    ],
    "wof:name":"24 Emergency Locksmith",
    "wof:placetype":"venue"
},
  "geometry": {"coordinates":[-74.271704,40.878716],"type":"Point"}
}