{
  "type": "Feature",
  "properties": {
    "iso:country":"US",
    "sg:address":"10 Woodland Dr",
    "sg:city":"Little Falls",
    "sg:classifiers":[
        {
            "category":"Wholesale",
            "subcategory":"Chemicals & Plastics",
            "type":"Manufacturing & Wholesale Goods"
        }
    ],
    "sg:phone":"+1 973 890 7815",
    "sg:postcode":"07424",
    "sg:province":"NJ",
    "sg:tags":[
        "consulting",
        "management"
    ],
    "wof:name":"Scott Chemical Corp",
    "wof:placetype":"venue"
},
  "geometry": {"coordinates":[-74.20583600000001,40.882206],"type":"Point"}
}