{
  "type": "Feature",
  "properties": {
    "addr:full":"333 N Broad St Elizabeth NJ 07208",
    "addr:housenumber":"333",
    "addr:postcode":"07208",
    "addr:street":"N Broad St",
    "iso:country":"US",
    "sg:address":"333 N Broad St",
    "sg:city":"Elizabeth",
    "sg:classifiers":[
        {
            "category":"Real Estate",
            "subcategory":"Real Estate Agent",
            "type":"Services"
        }
    ],
    "sg:phone":"+1   ",
    "sg:postcode":"07208",
    "sg:province":"NJ",
    "sg:tags":[
        "manager"
    ],
    "wof:name":"City Realty",
    "wof:placetype":"venue"
},
  "geometry": {"coordinates":[-74.214989,40.670992],"type":"Point"}
}