{
  "type": "Feature",
  "properties": {
    "iso:country":"US",
    "sg:address":"61 Somerset Pl Ste 7",
    "sg:city":"Clifton",
    "sg:classifiers":[
        {
            "category":"Building & Trades",
            "subcategory":"Construction",
            "type":"Services"
        }
    ],
    "sg:phone":"+1 973 815 0400",
    "sg:postcode":"07012",
    "sg:province":"NJ",
    "sg:tags":[
        "contractor"
    ],
    "wof:name":"Home Contractors & Builders",
    "wof:placetype":"venue"
},
  "geometry": {"coordinates":[-74.15490200000001,40.849371],"type":"Point"}
}