{
  "type": "Feature",
  "properties": {
    "addr:full":"41 Possum Way New Providence NJ 07974",
    "addr:housenumber":"41",
    "addr:postcode":"07974",
    "addr:street":"Possum Way",
    "iso:country":"US",
    "sg:address":"41 Possum Way",
    "sg:city":"New Providence",
    "sg:classifiers":[
        {
            "category":"Organizations",
            "subcategory":"Religious Organization",
            "type":"Services"
        }
    ],
    "sg:phone":"+1 908 464 1978",
    "sg:postcode":"07974",
    "sg:province":"NJ",
    "wof:name":"MacPherson Murdoch Rev",
    "wof:placetype":"venue"
},
  "geometry": {"coordinates":[-74.408997,40.683399],"type":"Point"}
}