{
  "type": "Feature",
  "properties": {
    "iso:country":"US",
    "sg:address":"37 Cinder Rd",
    "sg:city":"Edison",
    "sg:classifiers":[
        {
            "category":"Manufacturing",
            "subcategory":"Petroleum Products",
            "type":"Manufacturing & Wholesale Goods"
        }
    ],
    "sg:phone":"+1 732 512 1515",
    "sg:postcode":"08820",
    "sg:province":"NJ",
    "sg:tags":[
        "engine",
        "oil",
        "treatment",
        "mfg"
    ],
    "wof:name":"Doctor Smooth",
    "wof:placetype":"venue"
},
  "geometry": {"coordinates":[-74.346502,40.568017],"type":"Point"}
}