{
  "type": "Feature",
  "properties": {
    "addr:full":"2 Village Ct Hazlet NJ 07730",
    "addr:housenumber":"2",
    "addr:postcode":"07730",
    "addr:street":"Village Ct",
    "iso:country":"US",
    "sg:address":"2 Village Ct",
    "sg:city":"Hazlet",
    "sg:classifiers":[
        {
            "category":"Banks & Credit Unions",
            "subcategory":"Investment Brokerage",
            "type":"Services"
        }
    ],
    "sg:phone":"+1 732 264 0333",
    "sg:postcode":"07730",
    "sg:province":"NJ",
    "sg:tags":[
        "consultant",
        "planning",
        "financial"
    ],
    "wof:name":"Complete Financial",
    "wof:placetype":"venue"
},
  "geometry": {"coordinates":[-74.174386,40.416031],"type":"Point"}
}