{
  "type": "Feature",
  "properties": {
    "addr:full":"450 Murray Hill Pkwy East Rutherford NJ 07073",
    "addr:housenumber":"450",
    "addr:postcode":"07073",
    "addr:street":"Murray Hill Pkwy",
    "iso:country":"US",
    "sg:address":"450 Murray Hill Pkwy",
    "sg:city":"East Rutherford",
    "sg:classifiers":[
        {
            "category":"Personal",
            "type":"Services"
        }
    ],
    "sg:phone":"+1 800 650 8780",
    "sg:postcode":"07073",
    "sg:province":"NJ",
    "sg:tags":[
        "mover"
    ],
    "sg:website":"ccvllc.com/index.html",
    "wof:name":"Cross Country Van Lines LLC",
    "wof:placetype":"venue"
},
  "geometry": {"coordinates":[-74.09124199999999,40.817712],"type":"Point"}
}