{
  "type": "Feature",
  "properties": {
    "iso:country":"US",
    "sg:address":"12 Paulinskill Lake Rd",
    "sg:city":"Newton",
    "sg:classifiers":[
        {
            "category":"Retail",
            "subcategory":"Auto Repair",
            "type":"Services"
        }
    ],
    "sg:phone":"+1 973 383 8838",
    "sg:postcode":"07860",
    "sg:province":"NJ",
    "sg:tags":[
        "body"
    ],
    "wof:name":"American Automotive",
    "wof:placetype":"venue"
},
  "geometry": {"coordinates":[-74.814697,41.047877],"type":"Point"}
}