{
  "type": "Feature",
  "properties": {
    "addr:full":"12 Sharps Ln Trenton NJ 08610",
    "addr:housenumber":"12",
    "addr:postcode":"08610",
    "addr:street":"Sharps Ln",
    "iso:country":"US",
    "sg:address":"12 Sharps Ln",
    "sg:city":"Trenton",
    "sg:classifiers":[
        {
            "category":"Professional",
            "subcategory":"Engineering",
            "type":"Services"
        }
    ],
    "sg:phone":"+1 609 275 1383",
    "sg:postcode":"08610",
    "sg:province":"NJ",
    "sg:tags":[
        "consulting",
        "trucking"
    ],
    "wof:name":"Nu Trend Transportation Co",
    "wof:placetype":"venue"
},
  "geometry": {"coordinates":[-74.694596,40.197201],"type":"Point"}
}