{
  "type": "Feature",
  "properties": {
    "addr:full":"170 Smith St Newark NJ 07106",
    "addr:housenumber":"170",
    "addr:postcode":"07106",
    "addr:street":"Smith St",
    "iso:country":"US",
    "sg:address":"170 Smith St",
    "sg:city":"Newark",
    "sg:classifiers":[
        {
            "category":"Food & Beverages",
            "subcategory":"Groceries & Convenience Stores",
            "type":"Retail Goods"
        }
    ],
    "sg:phone":"+1 973 416 4460",
    "sg:postcode":"07106",
    "sg:province":"NJ",
    "sg:tags":[
        "market"
    ],
    "wof:name":"Coast To Coast Market",
    "wof:placetype":"venue"
},
  "geometry": {"coordinates":[-74.230948,40.744549],"type":"Point"}
}