{
  "type": "Feature",
  "properties": {
    "addr:full":"246 Duncan Ave Jersey City NJ 07306",
    "addr:housenumber":"246",
    "addr:postcode":"07306",
    "addr:street":"Duncan Ave",
    "iso:country":"US",
    "sg:address":"246 Duncan Ave",
    "sg:city":"Jersey City",
    "sg:classifiers":[
        {
            "category":"Building & Trades",
            "subcategory":"Locksmith",
            "type":"Services"
        }
    ],
    "sg:phone":"+1 888 354 3544",
    "sg:postcode":"07306",
    "sg:province":"NJ",
    "sg:tags":[
        "key"
    ],
    "wof:name":"AAA Emergency Locksmith",
    "wof:placetype":"venue"
},
  "geometry": {"coordinates":[-74.079877,40.728305],"type":"Point"}
}