{
  "type": "Feature",
  "properties": {
    "addr:full":"816 Delsea Dr N Glassboro NJ 08028",
    "addr:housenumber":"816",
    "addr:postcode":"08028",
    "addr:street":"Delsea Dr N",
    "iso:country":"US",
    "sg:address":"816 Delsea Dr N",
    "sg:city":"Glassboro",
    "sg:classifiers":[
        {
            "category":"Real Estate",
            "subcategory":"Real Estate Agent",
            "type":"Services"
        }
    ],
    "sg:phone":"+1 856 262 3388",
    "sg:postcode":"08028",
    "sg:province":"NJ",
    "sg:tags":[
        "inspection"
    ],
    "wof:name":"Pillar To Post Professional",
    "wof:placetype":"venue"
},
  "geometry": {"coordinates":[-75.115864,39.724132],"type":"Point"}
}