{
  "type": "Feature",
  "properties": {
    "iso:country":"US",
    "sg:address":"29 Alloway Friesburg Rd",
    "sg:city":"Alloway",
    "sg:classifiers":[
        {
            "category":"Building & Trades",
            "subcategory":"Construction",
            "type":"Services"
        }
    ],
    "sg:phone":"+1 856 339 4014",
    "sg:postcode":"08302",
    "sg:province":"NJ",
    "sg:tags":[
        "general",
        "contractor"
    ],
    "wof:name":"RCL Enterprise Inc",
    "wof:placetype":"venue"
},
  "geometry": {"coordinates":[-75.360022,39.558469],"type":"Point"}
}