{
  "type": "Feature",
  "properties": {
    "iso:country":"US",
    "sg:address":"56 Grayson Dr",
    "sg:city":"Belle Mead",
    "sg:classifiers":[
        {
            "category":"Professional",
            "type":"Services"
        }
    ],
    "sg:phone":"+1   ",
    "sg:postcode":"08502",
    "sg:province":"NJ",
    "wof:name":"Opinion Research Corp",
    "wof:placetype":"venue"
},
  "geometry": {"coordinates":[-74.640556,40.452169],"type":"Point"}
}