{
  "type": "Feature",
  "properties": {
    "iso:country":"US",
    "sg:address":"546 Winchester Ave",
    "sg:city":"Union",
    "sg:classifiers":[
        {
            "category":"Manufacturing",
            "subcategory":"Petroleum Products",
            "type":"Manufacturing & Wholesale Goods"
        }
    ],
    "sg:phone":"+1 908 687 2341",
    "sg:postcode":"07083",
    "sg:province":"NJ",
    "sg:tags":[
        "refiner"
    ],
    "wof:name":"Montos Oil Company Inc",
    "wof:placetype":"venue"
},
  "geometry": {"coordinates":[-74.255437,40.677566],"type":"Point"}
}