{
  "type": "Feature",
  "properties": {
    "addr:full":"27 Rosenhayn Ave Bridgeton NJ 08302",
    "addr:housenumber":"27",
    "addr:postcode":"08302",
    "addr:street":"Rosenhayn Ave",
    "iso:country":"US",
    "sg:address":"27 Rosenhayn Ave",
    "sg:city":"Bridgeton",
    "sg:classifiers":[
        {
            "category":"Building & Trades",
            "subcategory":"Construction",
            "type":"Services"
        }
    ],
    "sg:phone":"+1 856 455 0477",
    "sg:postcode":"08302",
    "sg:province":"NJ",
    "sg:tags":[
        "general",
        "contractor"
    ],
    "wof:name":"David L Construction & Excavtg",
    "wof:placetype":"venue"
},
  "geometry": {"coordinates":[-75.220777,39.445332],"type":"Point"}
}