{
  "type": "Feature",
  "properties": {
    "iso:country":"US",
    "sg:address":"240 Hamilton Rd",
    "sg:city":"Ridgewood",
    "sg:classifiers":[
        {
            "category":"Health Services",
            "subcategory":"Doctor",
            "type":"Services"
        }
    ],
    "sg:phone":"+1 201 447 6437",
    "sg:postcode":"07450",
    "sg:province":"NJ",
    "sg:tags":[
        "physician",
        "surgeon"
    ],
    "wof:name":"Robert G Lahita MD",
    "wof:placetype":"venue"
},
  "geometry": {"coordinates":[-74.123048,41.001747],"type":"Point"}
}