{
  "type": "Feature",
  "properties": {
    "iso:country":"US",
    "sg:address":"8 Riverside Dr",
    "sg:city":"Rumson",
    "sg:classifiers":[
        {
            "category":"Professional",
            "subcategory":"Management & Consulting",
            "type":"Services"
        }
    ],
    "sg:phone":"+1   ",
    "sg:postcode":"07760",
    "sg:province":"NJ",
    "wof:name":"Berenz Inc",
    "wof:placetype":"venue"
},
  "geometry": {"coordinates":[-74.030311,40.347258],"type":"Point"}
}