{
  "type": "Feature",
  "properties": {
    "addr:full":"1111 State Rte 33 Neptune NJ 07753",
    "addr:housenumber":"1111",
    "addr:postcode":"07753",
    "addr:street":"State Rte 33",
    "iso:country":"US",
    "sg:address":"1111 State Rte 33",
    "sg:city":"Neptune",
    "sg:classifiers":[
        {
            "category":"Professional",
            "subcategory":"Lawyer & Legal Services",
            "type":"Services"
        }
    ],
    "sg:phone":"+1 732 775 4753",
    "sg:postcode":"07753",
    "sg:province":"NJ",
    "sg:tags":[
        "attorney"
    ],
    "wof:name":"Daniel P Jacobson",
    "wof:placetype":"venue"
},
  "geometry": {"coordinates":[-74.02007999999999,40.21039],"type":"Point"}
}