{
  "type": "Feature",
  "properties": {
    "addr:full":"166 S Center St Orange NJ 07050",
    "addr:housenumber":"166",
    "addr:postcode":"07050",
    "addr:street":"S Center St",
    "iso:country":"US",
    "sg:address":"166 S Center St",
    "sg:city":"Orange",
    "sg:classifiers":[
        {
            "category":"Personal",
            "subcategory":"Beauty Salon",
            "type":"Services"
        }
    ],
    "sg:phone":"+1 973 673 9610",
    "sg:postcode":"07050",
    "sg:province":"NJ",
    "wof:name":"Maggie's Personal Image",
    "wof:placetype":"venue"
},
  "geometry": {"coordinates":[-74.23050600000001,40.767486],"type":"Point"}
}