{
  "type": "Feature",
  "properties": {
    "addr:full":"77 Sanford Pl Jersey City NJ 07307",
    "addr:housenumber":"77",
    "addr:postcode":"07307",
    "addr:street":"Sanford Pl",
    "iso:country":"US",
    "sg:address":"77 Sanford Pl",
    "sg:city":"Jersey City",
    "sg:classifiers":[
        {
            "category":"Real Estate",
            "subcategory":"Real Estate Agent",
            "type":"Services"
        }
    ],
    "sg:phone":"+1   ",
    "sg:postcode":"07307",
    "sg:province":"NJ",
    "wof:name":"Julie Sloane",
    "wof:placetype":"venue"
},
  "geometry": {"coordinates":[-74.055775,40.746496],"type":"Point"}
}