{
  "type": "Feature",
  "properties": {
    "addr:full":"731 Brick Blvd Brick NJ 08723",
    "addr:housenumber":"731",
    "addr:postcode":"08723",
    "addr:street":"Brick Blvd",
    "iso:country":"US",
    "sg:address":"731 Brick Blvd",
    "sg:city":"Brick",
    "sg:classifiers":[
        {
            "category":"Banks & Credit Unions",
            "subcategory":"Bank",
            "type":"Services"
        }
    ],
    "sg:phone":"+1   ",
    "sg:postcode":"08723",
    "sg:province":"NJ",
    "sg:tags":[
        "savings",
        "institution"
    ],
    "sg:website":"www.hudsoncitysavingsbank.com",
    "wof:name":"Hudson City Savings Bank",
    "wof:placetype":"venue"
},
  "geometry": {"coordinates":[-74.136837,40.05962],"type":"Point"}
}