{
  "type": "Feature",
  "properties": {
    "iso:country":"US",
    "sg:address":"227 Vreeland Ave",
    "sg:city":"Nutley",
    "sg:classifiers":[
        {
            "category":"Real Estate",
            "subcategory":"Architect",
            "type":"Services"
        }
    ],
    "sg:phone":"+1 973 667 7890",
    "sg:postcode":"07110",
    "sg:province":"NJ",
    "wof:name":"Tomm Yb Aia Architect",
    "wof:placetype":"venue"
},
  "geometry": {"coordinates":[-74.159629,40.82496],"type":"Point"}
}