{
  "type": "Feature",
  "properties": {
    "iso:country":"US",
    "sg:address":"38 Ames Ave",
    "sg:city":"Rutherford",
    "sg:classifiers":[
        {
            "category":"Social Services",
            "subcategory":"Child Care",
            "type":"Services"
        },
        {
            "category":"Education",
            "subcategory":"Preschool",
            "type":"Public Place"
        },
        {
            "category":"Education",
            "subcategory":"School",
            "type":"Public Place"
        }
    ],
    "sg:phone":"+1 201 933 8401",
    "sg:postcode":"07070",
    "sg:province":"NJ",
    "sg:tags":[
        "elementary",
        "day"
    ],
    "wof:name":"Pre-School & After School",
    "wof:placetype":"venue"
},
  "geometry": {"coordinates":[-74.102852,40.82911],"type":"Point"}
}