{
  "type": "Feature",
  "properties": {
    "addr:full":"108 Colony Ave Park Ridge NJ 07656",
    "addr:housenumber":"108",
    "addr:postcode":"07656",
    "addr:street":"Colony Ave",
    "iso:country":"US",
    "sg:address":"108 Colony Ave",
    "sg:city":"Park Ridge",
    "sg:classifiers":[
        {
            "category":"Autos & Motor Vehicles",
            "subcategory":"Automobile Sales",
            "type":"Retail Goods"
        }
    ],
    "sg:phone":"+1   ",
    "sg:postcode":"07656",
    "sg:province":"NJ",
    "sg:tags":[
        "used"
    ],
    "wof:name":"Deals On Wheels",
    "wof:placetype":"venue"
},
  "geometry": {"coordinates":[-74.04564000000001,41.042527],"type":"Point"}
}