{
  "type": "Feature",
  "properties": {
    "iso:country":"US",
    "sg:address":"410 22nd St",
    "sg:city":"Union City",
    "sg:classifiers":[
        {
            "category":"Health Services",
            "subcategory":"Doctor",
            "type":"Services"
        }
    ],
    "sg:phone":"+1 201 223 4224",
    "sg:postcode":"07087",
    "sg:province":"NJ",
    "sg:tags":[
        "physician",
        "medical",
        "surgeon"
    ],
    "wof:name":"Leon' Wong Hector MD Family Pr",
    "wof:placetype":"venue"
},
  "geometry": {"coordinates":[-74.033176,40.766333],"type":"Point"}
}