{
  "type": "Feature",
  "properties": {
    "iso:country":"US",
    "sg:address":"37 Rupell Rd",
    "sg:city":"Hampton",
    "sg:classifiers":[
        {
            "category":"Health Services",
            "subcategory":"Doctor",
            "type":"Services"
        }
    ],
    "sg:phone":"+1 908 735 7060",
    "sg:postcode":"08827",
    "sg:province":"NJ",
    "sg:tags":[
        "physician",
        "surgeon"
    ],
    "wof:name":"North Hunterdon Physicians",
    "wof:placetype":"venue"
},
  "geometry": {"coordinates":[-74.93944500000001,40.635909],"type":"Point"}
}