{
  "type": "Feature",
  "properties": {
    "iso:country":"US",
    "sg:address":"370 Hay Rd",
    "sg:city":"Manahawkin",
    "sg:classifiers":[
        {
            "category":"Manufacturing",
            "subcategory":"Printing",
            "type":"Manufacturing & Wholesale Goods"
        }
    ],
    "sg:phone":"+1 609 978 4855",
    "sg:postcode":"08050",
    "sg:province":"NJ",
    "sg:tags":[
        "periodical"
    ],
    "wof:name":"Press Communications LLC",
    "wof:placetype":"venue"
},
  "geometry": {"coordinates":[-74.30287800000001,39.720617],"type":"Point"}
}