{
  "type": "Feature",
  "properties": {
    "iso:country":"US",
    "sg:address":"1 Grand Tour",
    "sg:city":"Highlands",
    "sg:classifiers":[
        {
            "category":"Building & Trades",
            "subcategory":"Cleaning & Sanitation",
            "type":"Services"
        }
    ],
    "sg:phone":"+1   ",
    "sg:postcode":"07732",
    "sg:province":"NJ",
    "sg:tags":[
        "maintenance"
    ],
    "wof:name":"Coastal Building Maintenance",
    "wof:placetype":"venue"
},
  "geometry": {"coordinates":[-73.986853,40.39288],"type":"Point"}
}