{
  "type": "Feature",
  "properties": {
    "addr:full":"114 Tonnelle Ave Jersey City NJ 07306",
    "addr:housenumber":"114",
    "addr:postcode":"07306",
    "addr:street":"Tonnelle Ave",
    "iso:country":"US",
    "sg:address":"114 Tonnelle Ave",
    "sg:city":"Jersey City",
    "sg:classifiers":[
        {
            "category":"Shopping",
            "subcategory":"Gifts & Souvenirs",
            "type":"Retail Goods"
        }
    ],
    "sg:phone":"+1 201 946 4100",
    "sg:postcode":"07306",
    "sg:province":"NJ",
    "sg:tags":[
        "party",
        "supply"
    ],
    "wof:name":"Party Palace Plus",
    "wof:placetype":"venue"
},
  "geometry": {"coordinates":[-74.066914,40.735398],"type":"Point"}
}