{
  "type": "Feature",
  "properties": {
    "iso:country":"US",
    "sg:address":"1330 Fairview Blvd",
    "sg:city":"Delran",
    "sg:classifiers":[
        {
            "category":"Shopping",
            "subcategory":"Mobile Phones",
            "type":"Retail Goods"
        }
    ],
    "sg:phone":"+1 856 764 1844",
    "sg:postcode":"08075",
    "sg:province":"NJ",
    "wof:name":"Car-Tel Communications",
    "wof:placetype":"venue"
},
  "geometry": {"coordinates":[-74.94426199999999,40.018353],"type":"Point"}
}