{
  "type": "Feature",
  "properties": {
    "addr:full":"740 Palisade Ave Teaneck NJ 07666",
    "addr:housenumber":"740",
    "addr:postcode":"07666",
    "addr:street":"Palisade Ave",
    "iso:country":"US",
    "sg:address":"740 Palisade Ave",
    "sg:city":"Teaneck",
    "sg:classifiers":[
        {
            "category":"Banks & Credit Unions",
            "subcategory":"Bank",
            "type":"Services"
        }
    ],
    "sg:phone":"+1 201 692 2902",
    "sg:postcode":"07666",
    "sg:province":"NJ",
    "wof:name":"Nve Bank",
    "wof:placetype":"venue"
},
  "geometry": {"coordinates":[-74.019885,40.886667],"type":"Point"}
}