{
  "type": "Feature",
  "properties": {
    "iso:country":"US",
    "sg:address":"66 Knapp Ave",
    "sg:city":"Trenton",
    "sg:classifiers":[
        {
            "category":"Personal",
            "type":"Services"
        }
    ],
    "sg:phone":"+1 609 581 1234",
    "sg:postcode":"08610",
    "sg:province":"NJ",
    "sg:tags":[
        "program",
        "physical",
        "exercise",
        "fitness"
    ],
    "sg:website":"www.jazzercise.com",
    "wof:name":"Jazzercise",
    "wof:placetype":"venue"
},
  "geometry": {"coordinates":[-74.70534000000001,40.198884],"type":"Point"}
}