{
  "type": "Feature",
  "properties": {
    "iso:country":"US",
    "sg:address":"19 Turntable Junction",
    "sg:city":"Flemington",
    "sg:classifiers":[
        {
            "category":"Home & Garden",
            "subcategory":"Garden Supply",
            "type":"Retail Goods"
        }
    ],
    "sg:phone":"+1   ",
    "sg:postcode":"08822",
    "sg:province":"NJ",
    "sg:tags":[
        "florist"
    ],
    "wof:name":"Holly Hock & Ivy",
    "wof:placetype":"venue"
},
  "geometry": {"coordinates":[-74.860218,40.505819],"type":"Point"}
}