{
  "type": "Feature",
  "properties": {
    "addr:full":"606 N Warwick Rd Magnolia NJ 08049",
    "addr:housenumber":"606",
    "addr:postcode":"08049",
    "addr:street":"N Warwick Rd",
    "iso:country":"US",
    "sg:address":"606 N Warwick Rd",
    "sg:city":"Magnolia",
    "sg:classifiers":[
        {
            "category":"Retail",
            "subcategory":"Laundry & Dry Cleaning",
            "type":"Services"
        }
    ],
    "sg:phone":"+1 856 346 0069",
    "sg:postcode":"08049",
    "sg:province":"NJ",
    "wof:name":"Ninety Nine Cleaners",
    "wof:placetype":"venue"
},
  "geometry": {"coordinates":[-75.031882,39.849785],"type":"Point"}
}