{
  "type": "Feature",
  "properties": {
    "iso:country":"US",
    "sg:address":"865 State Rte 33",
    "sg:city":"Freehold",
    "sg:classifiers":[
        {
            "category":"Professional",
            "subcategory":"Business Services",
            "type":"Services"
        }
    ],
    "sg:phone":"+1 732 409 0003",
    "sg:postcode":"07728",
    "sg:province":"NJ",
    "sg:tags":[
        "water",
        "treatment"
    ],
    "wof:name":"Clover Hill Water Solution",
    "wof:placetype":"venue"
},
  "geometry": {"coordinates":[-74.215917,40.232792],"type":"Point"}
}