{
  "type": "Feature",
  "properties": {
    "addr:full":"60 Hilltop Rd Howell NJ 07731",
    "addr:housenumber":"60",
    "addr:postcode":"07731",
    "addr:street":"Hilltop Rd",
    "iso:country":"US",
    "sg:address":"60 Hilltop Rd",
    "sg:city":"Howell",
    "sg:classifiers":[
        {
            "category":"Social Services",
            "type":"Services"
        }
    ],
    "sg:phone":"+1 732 905 8496",
    "sg:postcode":"07731",
    "sg:province":"NJ",
    "wof:name":"Easter Seals",
    "wof:placetype":"venue"
},
  "geometry": {"coordinates":[-74.231762,40.149862],"type":"Point"}
}