{
  "type": "Feature",
  "properties": {
    "addr:full":"79 N Franklin Tpke Ramsey NJ 07446",
    "addr:housenumber":"79",
    "addr:postcode":"07446",
    "addr:street":"N Franklin Tpke",
    "iso:country":"US",
    "sg:address":"79 N Franklin Tpke",
    "sg:city":"Ramsey",
    "sg:classifiers":[
        {
            "category":"Personal",
            "subcategory":"Adult",
            "type":"Services"
        }
    ],
    "sg:phone":"+1   ",
    "sg:postcode":"07446",
    "sg:province":"NJ",
    "wof:name":"Lou Kallianes",
    "wof:placetype":"venue"
},
  "geometry": {"coordinates":[-74.13314200000001,41.061772],"type":"Point"}
}