{
  "type": "Feature",
  "properties": {
    "iso:country":"US",
    "sg:address":"370 US Hwy 130",
    "sg:city":"East Windsor",
    "sg:classifiers":[
        {
            "category":"Manufacturing",
            "subcategory":"Signs",
            "type":"Manufacturing & Wholesale Goods"
        }
    ],
    "sg:phone":"+1 609 490 1400",
    "sg:postcode":"08520",
    "sg:province":"NJ",
    "sg:website":"www.signarama.com",
    "wof:name":"Sign-A-Rama",
    "wof:placetype":"venue"
},
  "geometry": {"coordinates":[-74.5017,40.233052],"type":"Point"}
}