{
  "type": "Feature",
  "properties": {
    "addr:full":"336 Tindall Ave Trenton NJ 08610",
    "addr:housenumber":"336",
    "addr:postcode":"08610",
    "addr:street":"Tindall Ave",
    "iso:country":"US",
    "sg:address":"336 Tindall Ave",
    "sg:city":"Trenton",
    "sg:classifiers":[
        {
            "category":"Building & Trades",
            "subcategory":"Plumbing",
            "type":"Services"
        }
    ],
    "sg:phone":"+1 609 394 9186",
    "sg:postcode":"08610",
    "sg:province":"NJ",
    "sg:tags":[
        "contractor"
    ],
    "wof:name":"J C S Rfrgn AC & Htg Co",
    "wof:placetype":"venue"
},
  "geometry": {"coordinates":[-74.733082,40.212505],"type":"Point"}
}