{
  "type": "Feature",
  "properties": {
    "iso:country":"US",
    "sg:address":"661 N 8th St",
    "sg:city":"Newark",
    "sg:classifiers":[
        {
            "category":"Building & Trades",
            "subcategory":"Construction",
            "type":"Services"
        }
    ],
    "sg:phone":"+1 973 484 4425",
    "sg:postcode":"07107",
    "sg:province":"NJ",
    "sg:tags":[
        "contractor"
    ],
    "wof:name":"Euro Masonry & Carpentry Llc",
    "wof:placetype":"venue"
},
  "geometry": {"coordinates":[-74.18150300000001,40.773899],"type":"Point"}
}