{
  "type": "Feature",
  "properties": {
    "addr:full":"40 Bradway Ave Trenton NJ 08618",
    "addr:housenumber":"40",
    "addr:postcode":"08618",
    "addr:street":"Bradway Ave",
    "iso:country":"US",
    "sg:address":"40 Bradway Ave",
    "sg:city":"Trenton",
    "sg:classifiers":[
        {
            "category":"Wholesale",
            "subcategory":"Electrical",
            "type":"Manufacturing & Wholesale Goods"
        }
    ],
    "sg:phone":"+1 609 396 2309",
    "sg:postcode":"08618",
    "sg:province":"NJ",
    "sg:tags":[
        "fire",
        "alarm",
        "system"
    ],
    "wof:name":"Ace Electric Svc",
    "wof:placetype":"venue"
},
  "geometry": {"coordinates":[-74.775451,40.248324],"type":"Point"}
}