{
  "type": "Feature",
  "properties": {
    "addr:full":"15 Dyatt Pl Hackensack NJ 07601",
    "addr:housenumber":"15",
    "addr:postcode":"07601",
    "addr:street":"Dyatt Pl",
    "iso:country":"US",
    "sg:address":"15 Dyatt Pl",
    "sg:city":"Hackensack",
    "sg:classifiers":[
        {
            "category":"Professional",
            "subcategory":"Engineering",
            "type":"Services"
        }
    ],
    "sg:phone":"+1 201 488 3707",
    "sg:postcode":"07601",
    "sg:province":"NJ",
    "sg:tags":[
        "engineer"
    ],
    "wof:name":"KFA Consulting Engineers Inc",
    "wof:placetype":"venue"
},
  "geometry": {"coordinates":[-74.03649900000001,40.897624],"type":"Point"}
}