{
  "type": "Feature",
  "properties": {
    "iso:country":"US",
    "sg:address":"51 Dey Grove Rd",
    "sg:city":"Englishtown",
    "sg:classifiers":[
        {
            "category":"Building & Trades",
            "subcategory":"Landscaping Services",
            "type":"Services"
        }
    ],
    "sg:phone":"+1 732 786 9944",
    "sg:postcode":"07726",
    "sg:province":"NJ",
    "wof:name":"C R & Sons Inc",
    "wof:placetype":"venue"
},
  "geometry": {"coordinates":[-74.37806,40.284202],"type":"Point"}
}