{
  "type": "Feature",
  "properties": {
    "iso:country":"US",
    "sg:address":"110 N Haddon Ave",
    "sg:city":"Haddonfield",
    "sg:classifiers":[
        {
            "category":"Shopping",
            "subcategory":"Computers & Home Electronics",
            "type":"Retail Goods"
        }
    ],
    "sg:phone":"+1 856 616 1196",
    "sg:postcode":"08033",
    "sg:province":"NJ",
    "sg:tags":[
        "repair",
        "equipment"
    ],
    "wof:name":"P C Warehouse",
    "wof:placetype":"venue"
},
  "geometry": {"coordinates":[-75.03649900000001,39.900902],"type":"Point"}
}