{
  "type": "Feature",
  "properties": {
    "iso:country":"US",
    "sg:address":"RR 130",
    "sg:city":"Willingboro",
    "sg:classifiers":[
        {
            "category":"Autos & Motor Vehicles",
            "subcategory":"Automobile Sales",
            "type":"Retail Goods"
        }
    ],
    "sg:phone":"+1 856 667 0503",
    "sg:postcode":"08046",
    "sg:province":"NJ",
    "sg:tags":[
        "limo"
    ],
    "wof:name":"First Class Luxury Limos",
    "wof:placetype":"venue"
},
  "geometry": {"coordinates":[-74.885498,40.0271],"type":"Point"}
}