{
  "type": "Feature",
  "properties": {
    "addr:full":"139 N High St Millville NJ 08332",
    "addr:housenumber":"139",
    "addr:postcode":"08332",
    "addr:street":"N High St",
    "iso:country":"US",
    "sg:address":"139 N High St",
    "sg:city":"Millville",
    "sg:classifiers":[
        {
            "category":"Personal",
            "subcategory":"Beauty Salon",
            "type":"Services"
        }
    ],
    "sg:phone":"+1 856 327 6673",
    "sg:postcode":"08332",
    "sg:province":"NJ",
    "sg:tags":[
        "shop"
    ],
    "wof:name":"Hair We Are",
    "wof:placetype":"venue"
},
  "geometry": {"coordinates":[-75.038462,39.39624],"type":"Point"}
}