{
  "type": "Feature",
  "properties": {
    "iso:country":"US",
    "sg:address":"941 Ball Ave",
    "sg:city":"Union",
    "sg:classifiers":[
        {
            "category":"Manufacturing",
            "subcategory":"Metals",
            "type":"Manufacturing & Wholesale Goods"
        }
    ],
    "sg:phone":"+1 908 687 4646",
    "sg:postcode":"07083",
    "sg:province":"NJ",
    "sg:tags":[
        "equipment",
        "lighting"
    ],
    "sg:website":"www.foremost-mfg.com",
    "wof:name":"Foremost Manufacturing Co Inc",
    "wof:placetype":"venue"
},
  "geometry": {"coordinates":[-74.288545,40.689064],"type":"Point"}
}