{
  "type": "Feature",
  "properties": {
    "addr:full":"302 Morris Pesin Dr Jersey City NJ 07305",
    "addr:housenumber":"302",
    "addr:postcode":"07305",
    "addr:street":"Morris Pesin Dr",
    "iso:country":"US",
    "sg:address":"302 Morris Pesin Dr",
    "sg:city":"Jersey City",
    "sg:classifiers":[
        {
            "category":"Retail",
            "subcategory":"Auto Rental",
            "type":"Services"
        }
    ],
    "sg:phone":"+1 201 222 2454",
    "sg:postcode":"07305",
    "sg:province":"NJ",
    "sg:tags":[
        "car"
    ],
    "sg:website":"www.thrifty.com",
    "wof:name":"Thrifty Car Rental",
    "wof:placetype":"venue"
},
  "geometry": {"coordinates":[-74.06210299999999,40.696201],"type":"Point"}
}