{
  "type": "Feature",
  "properties": {
    "addr:full":"1460 US Hwy 9 Woodbridge NJ 07095",
    "addr:housenumber":"1460",
    "addr:postcode":"07095",
    "addr:street":"Us Hwy 9",
    "iso:country":"US",
    "sg:address":"1460 US Hwy 9",
    "sg:city":"Woodbridge",
    "sg:classifiers":[
        {
            "category":"Insurance",
            "subcategory":"Insurance Agent",
            "type":"Services"
        }
    ],
    "sg:phone":"+1 732 726 1400",
    "sg:postcode":"07095",
    "sg:province":"NJ",
    "wof:name":"Morstan General Agency",
    "wof:placetype":"venue"
},
  "geometry": {"coordinates":[-74.296199,40.561416],"type":"Point"}
}