{
  "type": "Feature",
  "properties": {
    "iso:country":"US",
    "sg:address":"16 Links Ct",
    "sg:city":"Sparta",
    "sg:classifiers":[
        {
            "category":"Education",
            "subcategory":"Special Training",
            "type":"Public Place"
        }
    ],
    "sg:phone":"+1 973 729 9322",
    "sg:postcode":"07871",
    "sg:province":"NJ",
    "sg:tags":[
        "school",
        "instruction",
        "art"
    ],
    "wof:name":"Abrakadoodle",
    "wof:placetype":"venue"
},
  "geometry": {"coordinates":[-74.645368,41.045613],"type":"Point"}
}