{
  "type": "Feature",
  "properties": {
    "addr:full":"465 State Rte 17 Ramsey NJ 07446",
    "addr:housenumber":"465",
    "addr:postcode":"07446",
    "addr:street":"State Rte 17",
    "iso:country":"US",
    "sg:address":"465 State Rte 17",
    "sg:city":"Ramsey",
    "sg:classifiers":[
        {
            "category":"Freight",
            "type":"Transportation"
        }
    ],
    "sg:phone":"+1 201 825 7297",
    "sg:postcode":"07446",
    "sg:province":"NJ",
    "sg:tags":[
        "mover"
    ],
    "wof:name":"Allied Van Lines",
    "wof:placetype":"venue"
},
  "geometry": {"coordinates":[-74.12033599999999,41.054827],"type":"Point"}
}