{
  "type": "Feature",
  "properties": {
    "addr:full":"332 Vreeland Ave Paterson NJ 07513",
    "addr:housenumber":"332",
    "addr:postcode":"07513",
    "addr:street":"Vreeland Ave",
    "iso:country":"US",
    "sg:address":"332 Vreeland Ave",
    "sg:city":"Paterson",
    "sg:classifiers":[
        {
            "category":"Manufacturing",
            "subcategory":"Metals",
            "type":"Manufacturing & Wholesale Goods"
        },
        {
            "category":"Building & Trades",
            "subcategory":"Construction",
            "type":"Services"
        }
    ],
    "sg:phone":"+1 973 684 2303",
    "sg:postcode":"07513",
    "sg:province":"NJ",
    "sg:tags":[
        "manufacture",
        "ornamental",
        "architectural",
        "iron",
        "railing",
        "works"
    ],
    "wof:name":"Columbian Iron Works Inc",
    "wof:placetype":"venue"
},
  "geometry": {"coordinates":[-74.138125,40.902719],"type":"Point"}
}