{
  "type": "Feature",
  "properties": {
    "addr:full":"6 Spring St Far Hills NJ 07931",
    "addr:housenumber":"6",
    "addr:postcode":"07931",
    "addr:street":"Spring St",
    "iso:country":"US",
    "sg:address":"6 Spring St",
    "sg:city":"Far Hills",
    "sg:classifiers":[
        {
            "category":"Professional",
            "subcategory":"Lawyer & Legal Services",
            "type":"Services"
        }
    ],
    "sg:phone":"+1 908 234 0536",
    "sg:postcode":"07931",
    "sg:province":"NJ",
    "sg:tags":[
        "attorney"
    ],
    "wof:name":"Anthony F Picheca Jr PC",
    "wof:placetype":"venue"
},
  "geometry": {"coordinates":[-74.638389,40.685774],"type":"Point"}
}