{
  "type": "Feature",
  "properties": {
    "iso:country":"US",
    "sg:address":"632 Livingston Ave",
    "sg:city":"North Brunswick",
    "sg:classifiers":[
        {
            "category":"Health Services",
            "subcategory":"Doctor",
            "type":"Services"
        }
    ],
    "sg:phone":"+1 732 247 1175",
    "sg:postcode":"08902",
    "sg:province":"NJ",
    "sg:tags":[
        "dentist"
    ],
    "wof:name":"Associates In Family Dentistry",
    "wof:placetype":"venue"
},
  "geometry": {"coordinates":[-74.461451,40.476579],"type":"Point"}
}