{
  "type": "Feature",
  "properties": {
    "addr:full":"2 Harrison St Edison NJ 08817",
    "addr:housenumber":"2",
    "addr:postcode":"08817",
    "addr:street":"Harrison St",
    "iso:country":"US",
    "sg:address":"2 Harrison St",
    "sg:city":"Edison",
    "sg:classifiers":[
        {
            "category":"Organizations",
            "subcategory":"Religious Organization",
            "type":"Services"
        }
    ],
    "sg:phone":"+1   ",
    "sg:postcode":"08817",
    "sg:province":"NJ",
    "sg:tags":[
        "temple"
    ],
    "wof:name":"Congregation Ohr Tarah",
    "wof:placetype":"venue"
},
  "geometry": {"coordinates":[-74.428146,40.507932],"type":"Point"}
}