{
  "type": "Feature",
  "properties": {
    "addr:full":"108 Centre Blvd Marlton NJ 08053",
    "addr:housenumber":"108",
    "addr:postcode":"08053",
    "addr:street":"Centre Blvd",
    "iso:country":"US",
    "sg:address":"108 Centre Blvd",
    "sg:city":"Marlton",
    "sg:classifiers":[
        {
            "category":"Insurance",
            "subcategory":"Insurance Agent",
            "type":"Services"
        }
    ],
    "sg:phone":"+1   ",
    "sg:postcode":"08053",
    "sg:province":"NJ",
    "sg:tags":[
        "employee",
        "benefit"
    ],
    "wof:name":"National H R",
    "wof:placetype":"venue"
},
  "geometry": {"coordinates":[-74.92977399999999,39.890087],"type":"Point"}
}