{
  "type": "Feature",
  "properties": {
    "iso:country":"US",
    "sg:address":"100 Church St",
    "sg:city":"Lodi",
    "sg:classifiers":[
        {
            "category":"Personal",
            "subcategory":"Beauty Salon",
            "type":"Services"
        }
    ],
    "sg:phone":"+1 973 916 1636",
    "sg:postcode":"07644",
    "sg:province":"NJ",
    "sg:tags":[
        "shop"
    ],
    "wof:name":"Head Hunters",
    "wof:placetype":"venue"
},
  "geometry": {"coordinates":[-74.080871,40.878178],"type":"Point"}
}