{
  "type": "Feature",
  "properties": {
    "iso:country":"US",
    "sg:address":"423 State Rt 17",
    "sg:city":"Hasbrouck Heights",
    "sg:classifiers":[
        {
            "category":"Retail",
            "subcategory":"Auto Repair",
            "type":"Services"
        }
    ],
    "sg:phone":"+1 201 343 8070",
    "sg:postcode":"07604",
    "sg:province":"NJ",
    "wof:name":"Polifly Exxon",
    "wof:placetype":"venue"
},
  "geometry": {"coordinates":[-74.06549800000001,40.8624],"type":"Point"}
}