{
  "type": "Feature",
  "properties": {
    "addr:full":"205 W Main St Somerville NJ 08876",
    "addr:housenumber":"205",
    "addr:postcode":"08876",
    "addr:street":"W Main St",
    "iso:country":"US",
    "sg:address":"205 W Main St",
    "sg:city":"Somerville",
    "sg:classifiers":[
        {
            "category":"Insurance",
            "subcategory":"Insurance Agent",
            "type":"Services"
        }
    ],
    "sg:phone":"+1 908 685 5934",
    "sg:postcode":"08876",
    "sg:province":"NJ",
    "wof:name":"Allstate Insurance Co",
    "wof:placetype":"venue"
},
  "geometry": {"coordinates":[-74.616713,40.569483],"type":"Point"}
}