{
  "type": "Feature",
  "properties": {
    "addr:full":"31 Harrison Ave West Orange NJ 07052",
    "addr:housenumber":"31",
    "addr:postcode":"07052",
    "addr:street":"Harrison Ave",
    "iso:country":"US",
    "sg:address":"31 Harrison Ave",
    "sg:city":"West Orange",
    "sg:classifiers":[
        {
            "category":"Retail",
            "subcategory":"Repair Shop",
            "type":"Services"
        }
    ],
    "sg:phone":"+1 973 736 5765",
    "sg:postcode":"07052",
    "sg:province":"NJ",
    "sg:tags":[
        "reupholstery",
        "furniture"
    ],
    "wof:name":"Schramm E Upholstery",
    "wof:placetype":"venue"
},
  "geometry": {"coordinates":[-74.228897,40.794899],"type":"Point"}
}