{
  "type": "Feature",
  "properties": {
    "addr:full":"65 Central Ave Passaic NJ 07055",
    "addr:housenumber":"65",
    "addr:postcode":"07055",
    "addr:street":"Central Ave",
    "iso:country":"US",
    "sg:address":"65 Central Ave",
    "sg:city":"Passaic",
    "sg:classifiers":[
        {
            "category":"Wholesale",
            "subcategory":"Meat",
            "type":"Manufacturing & Wholesale Goods"
        }
    ],
    "sg:phone":"+1 973 473 1305",
    "sg:postcode":"07055",
    "sg:province":"NJ",
    "sg:tags":[
        "shop",
        "packer"
    ],
    "wof:name":"Green Tree Packing Co",
    "wof:placetype":"venue"
},
  "geometry": {"coordinates":[-74.129097,40.865398],"type":"Point"}
}