{
  "type": "Feature",
  "properties": {
    "iso:country":"US",
    "sg:address":"306 Longwood Dr",
    "sg:city":"Englishtown",
    "sg:classifiers":[
        {
            "category":"Professional",
            "subcategory":"Management & Consulting",
            "type":"Services"
        }
    ],
    "sg:phone":"+1 732 833 6751",
    "sg:postcode":"07726",
    "sg:province":"NJ",
    "sg:tags":[
        "communications",
        "consultant"
    ],
    "wof:name":"Braids Communications",
    "wof:placetype":"venue"
},
  "geometry": {"coordinates":[-74.348815,40.31069],"type":"Point"}
}