{
  "type": "Feature",
  "properties": {
    "iso:country":"US",
    "sg:address":"1959 Englishtown Rd",
    "sg:city":"Monroe Twp",
    "sg:classifiers":[
        {
            "category":"Education",
            "subcategory":"Dance Studio",
            "type":"Public Place"
        }
    ],
    "sg:phone":"+1 732 972 7707",
    "sg:postcode":"08831",
    "sg:province":"NJ",
    "sg:tags":[
        "instruction",
        "dancing"
    ],
    "wof:name":"Ultimate Danceworks",
    "wof:placetype":"venue"
},
  "geometry": {"coordinates":[-74.357139,40.34833],"type":"Point"}
}