{
  "type": "Feature",
  "properties": {
    "addr:full":"87 Randolph Ave Avenel NJ 07001",
    "addr:housenumber":"87",
    "addr:postcode":"07001",
    "addr:street":"Randolph Ave",
    "iso:country":"US",
    "sg:address":"87 Randolph Ave",
    "sg:city":"Avenel",
    "sg:classifiers":[
        {
            "category":"Professional",
            "subcategory":"Business Services",
            "type":"Services"
        }
    ],
    "sg:phone":"+1 732 680 0600",
    "sg:postcode":"07001",
    "sg:province":"NJ",
    "sg:tags":[
        "automobile",
        "used"
    ],
    "sg:website":"www.ctaa.com",
    "wof:name":"Car Tech Auction Inc",
    "wof:placetype":"venue"
},
  "geometry": {"coordinates":[-74.25711,40.597441],"type":"Point"}
}