{
  "type": "Feature",
  "properties": {
    "addr:full":"188 Lafayette Ave Hawthorne NJ 07506",
    "addr:housenumber":"188",
    "addr:postcode":"07506",
    "addr:street":"Lafayette Ave",
    "iso:country":"US",
    "sg:address":"188 Lafayette Ave",
    "sg:city":"Hawthorne",
    "sg:classifiers":[
        {
            "category":"Real Estate",
            "subcategory":"Real Estate Agent",
            "type":"Services"
        }
    ],
    "sg:phone":"+1   ",
    "sg:postcode":"07506",
    "sg:province":"NJ",
    "wof:name":"NIJ Appraisal Network",
    "wof:placetype":"venue"
},
  "geometry": {"coordinates":[-74.155525,40.945036],"type":"Point"}
}