{
  "type": "Feature",
  "properties": {
    "iso:country":"US",
    "sg:address":"50 Journal Sq",
    "sg:city":"Jersey City",
    "sg:classifiers":[
        {
            "category":"Utilities",
            "subcategory":"Mobile Phone",
            "type":"Services"
        }
    ],
    "sg:phone":"+1 201 656 3396",
    "sg:postcode":"07306",
    "sg:province":"NJ",
    "sg:tags":[
        "telephone",
        "cellular"
    ],
    "wof:name":"Cingular Wireless",
    "wof:placetype":"venue"
},
  "geometry": {"coordinates":[-74.064044,40.731902],"type":"Point"}
}