{
  "type": "Feature",
  "properties": {
    "addr:full":"1199 Raritan Rd Clark NJ 07066",
    "addr:housenumber":"1199",
    "addr:postcode":"07066",
    "addr:street":"Raritan Rd",
    "iso:country":"US",
    "sg:address":"1199 Raritan Rd",
    "sg:city":"Clark",
    "sg:classifiers":[
        {
            "category":"Building & Trades",
            "subcategory":"Locksmith",
            "type":"Services"
        }
    ],
    "sg:phone":"+1 732 839 4144",
    "sg:postcode":"07066",
    "sg:province":"NJ",
    "sg:tags":[
        "key"
    ],
    "wof:name":"A-1 24 Hour 7 Day Emerg A Locksmith",
    "wof:placetype":"venue"
},
  "geometry": {"coordinates":[-74.31032500000001,40.629782],"type":"Point"}
}