{
  "type": "Feature",
  "properties": {
    "addr:full":"616 Penn Ave Teaneck NJ 07666",
    "addr:housenumber":"616",
    "addr:postcode":"07666",
    "addr:street":"Penn Ave",
    "iso:country":"US",
    "sg:address":"616 Penn Ave",
    "sg:city":"Teaneck",
    "sg:classifiers":[
        {
            "category":"Manufacturing",
            "subcategory":"Printing",
            "type":"Manufacturing & Wholesale Goods"
        }
    ],
    "sg:phone":"+1 201 801 0771",
    "sg:postcode":"07666",
    "sg:province":"NJ",
    "sg:tags":[
        "newspaper"
    ],
    "wof:name":"Connection Newspaper",
    "wof:placetype":"venue"
},
  "geometry": {"coordinates":[-74.026916,40.889595],"type":"Point"}
}