{
  "type": "Feature",
  "properties": {
    "addr:full":"231 Clarksville Rd Princeton Junction NJ 08550",
    "addr:housenumber":"231",
    "addr:postcode":"08550",
    "addr:street":"Clarksville Rd",
    "iso:country":"US",
    "sg:address":"231 Clarksville Rd",
    "sg:city":"Princeton Junction",
    "sg:classifiers":[
        {
            "category":"Professional",
            "subcategory":"Engineering",
            "type":"Services"
        }
    ],
    "sg:phone":"+1   ",
    "sg:postcode":"08550",
    "sg:province":"NJ",
    "wof:name":"Joseph R Loring & Associates",
    "wof:placetype":"venue"
},
  "geometry": {"coordinates":[-74.63799,40.301171],"type":"Point"}
}