{
  "type": "Feature",
  "properties": {
    "iso:country":"US",
    "sg:address":"220 South Ave E",
    "sg:city":"Westfield",
    "sg:classifiers":[
        {
            "category":"Building & Trades",
            "subcategory":"Landscaping Services",
            "type":"Services"
        }
    ],
    "sg:phone":"+1 908 232 1888",
    "sg:postcode":"07090",
    "sg:province":"NJ",
    "sg:tags":[
        "landscape",
        "contractor"
    ],
    "wof:name":"A & N General Contracting",
    "wof:placetype":"venue"
},
  "geometry": {"coordinates":[-74.339302,40.649464],"type":"Point"}
}