{
  "type": "Feature",
  "properties": {
    "addr:full":"10 Wonderview Way Lebanon NJ 08833",
    "addr:housenumber":"10",
    "addr:postcode":"08833",
    "addr:street":"Wonderview Way",
    "iso:country":"US",
    "sg:address":"10 Wonderview Way",
    "sg:city":"Lebanon",
    "sg:classifiers":[
        {
            "category":"Professional",
            "subcategory":"Business Services",
            "type":"Services"
        }
    ],
    "sg:phone":"+1 908 236 7000",
    "sg:postcode":"08833",
    "sg:province":"NJ",
    "sg:tags":[
        "interior",
        "consultant",
        "design",
        "decorator"
    ],
    "wof:name":"Generations At Home",
    "wof:placetype":"venue"
},
  "geometry": {"coordinates":[-74.816264,40.663447],"type":"Point"}
}