{
  "type": "Feature",
  "properties": {
    "iso:country":"US",
    "sg:address":"210 Plaza",
    "sg:city":"Teaneck",
    "sg:classifiers":[
        {
            "category":"Banks & Credit Unions",
            "subcategory":"Financial Services",
            "type":"Services"
        }
    ],
    "sg:phone":"+1 201 257 8098",
    "sg:postcode":"07666",
    "sg:province":"NJ",
    "sg:tags":[
        "broker",
        "mortgage"
    ],
    "wof:name":"Advisors Morgt Group",
    "wof:placetype":"venue"
},
  "geometry": {"coordinates":[-74.005396,40.902404],"type":"Point"}
}