{
  "type": "Feature",
  "properties": {
    "addr:full":"506 Kearny Ave Kearny NJ 07032",
    "addr:housenumber":"506",
    "addr:postcode":"07032",
    "addr:street":"Kearny Ave",
    "iso:country":"US",
    "sg:address":"506 Kearny Ave",
    "sg:city":"Kearny",
    "sg:classifiers":[
        {
            "category":"Home & Garden",
            "subcategory":"Household Appliances",
            "type":"Retail Goods"
        }
    ],
    "sg:phone":"+1 201 998 1000",
    "sg:postcode":"07032",
    "sg:province":"NJ",
    "sg:tags":[
        "repair"
    ],
    "wof:name":"R Mace Appliance",
    "wof:placetype":"venue"
},
  "geometry": {"coordinates":[-74.1465,40.7677],"type":"Point"}
}