{
  "type": "Feature",
  "properties": {
    "iso:country":"US",
    "sg:address":"20 Oak Ridge Rd",
    "sg:city":"Clifton",
    "sg:classifiers":[
        {
            "category":"Personal",
            "type":"Services"
        }
    ],
    "sg:phone":"+1 973 778 0722",
    "sg:postcode":"07013",
    "sg:province":"NJ",
    "sg:tags":[
        "mover"
    ],
    "wof:name":"Frank Bellina Moving",
    "wof:placetype":"venue"
},
  "geometry": {"coordinates":[-74.163101,40.8615],"type":"Point"}
}