{
  "type": "Feature",
  "properties": {
    "iso:country":"US",
    "sg:address":"1400 Federal Blvd",
    "sg:city":"Carteret",
    "sg:classifiers":[
        {
            "category":"Banks & Credit Unions",
            "subcategory":"Bank",
            "type":"Services"
        }
    ],
    "sg:phone":"+1 732 694 1169",
    "sg:postcode":"07008",
    "sg:province":"NJ",
    "wof:name":"Municipal Credit Union",
    "wof:placetype":"venue"
},
  "geometry": {"coordinates":[-74.24329400000001,40.583503],"type":"Point"}
}