{
  "type": "Feature",
  "properties": {
    "iso:country":"US",
    "sg:address":"89 E Cherry St",
    "sg:city":"Rahway",
    "sg:classifiers":[
        {
            "category":"Wholesale",
            "subcategory":"Dairy",
            "type":"Manufacturing & Wholesale Goods"
        }
    ],
    "sg:phone":"+1 732 381 3634",
    "sg:postcode":"07065",
    "sg:province":"NJ",
    "sg:tags":[
        "frozen",
        "dessert",
        "ice",
        "cream"
    ],
    "wof:name":"American Jubilee Desserts",
    "wof:placetype":"venue"
},
  "geometry": {"coordinates":[-74.27489,40.606942],"type":"Point"}
}