{
  "type": "Feature",
  "properties": {
    "addr:full":"6 Vincent Dr Clifton NJ 07013",
    "addr:housenumber":"6",
    "addr:postcode":"07013",
    "addr:street":"Vincent Dr",
    "iso:country":"US",
    "sg:address":"6 Vincent Dr",
    "sg:city":"Clifton",
    "sg:classifiers":[
        {
            "category":"Organizations",
            "subcategory":"Religious Organization",
            "type":"Services"
        }
    ],
    "sg:phone":"+1 973 509 9409",
    "sg:postcode":"07013",
    "sg:province":"NJ",
    "sg:tags":[
        "church"
    ],
    "wof:name":"Christ Chapel Of Essex",
    "wof:placetype":"venue"
},
  "geometry": {"coordinates":[-74.18558400000001,40.860346],"type":"Point"}
}