{
  "type": "Feature",
  "properties": {
    "addr:full":"71 Parkview Ave Elmwood Park NJ 07407",
    "addr:housenumber":"71",
    "addr:postcode":"07407",
    "addr:street":"Parkview Ave",
    "iso:country":"US",
    "sg:address":"71 Parkview Ave",
    "sg:city":"Elmwood Park",
    "sg:classifiers":[
        {
            "category":"Professional",
            "type":"Services"
        }
    ],
    "sg:phone":"+1   ",
    "sg:postcode":"07407",
    "sg:province":"NJ",
    "wof:name":"J Results",
    "wof:placetype":"venue"
},
  "geometry": {"coordinates":[-74.12863299999999,40.921575],"type":"Point"}
}