{
  "type": "Feature",
  "properties": {
    "addr:full":"225 State Rt 3 Secaucus NJ 07094",
    "addr:housenumber":"225",
    "addr:postcode":"07094",
    "addr:street":"State Rt 3",
    "iso:country":"US",
    "sg:address":"225 State Rt 3",
    "sg:city":"Secaucus",
    "sg:classifiers":[
        {
            "category":"Health Services",
            "subcategory":"Doctor",
            "type":"Services"
        }
    ],
    "sg:phone":"+1 201 866 3266",
    "sg:postcode":"07094",
    "sg:province":"NJ",
    "wof:name":"Khani Ghassan MD",
    "wof:placetype":"venue"
},
  "geometry": {"coordinates":[-74.06008300000001,40.793931],"type":"Point"}
}