{
  "type": "Feature",
  "properties": {
    "iso:country":"US",
    "sg:address":"7 Bellis Ct",
    "sg:city":"Ringoes",
    "sg:classifiers":[
        {
            "category":"Shopping",
            "type":"Retail Goods"
        }
    ],
    "sg:phone":"+1   ",
    "sg:postcode":"08551",
    "sg:province":"NJ",
    "sg:tags":[
        "merchandise"
    ],
    "wof:name":"Somerville Pet Shop",
    "wof:placetype":"venue"
},
  "geometry": {"coordinates":[-74.862977,40.446635],"type":"Point"}
}