{
  "type": "Feature",
  "properties": {
    "iso:country":"US",
    "sg:address":"292 Piaget Ave",
    "sg:city":"Clifton",
    "sg:classifiers":[
        {
            "category":"Organizations",
            "subcategory":"Non-profit Organization",
            "type":"Services"
        }
    ],
    "sg:phone":"+1 973 340 2877",
    "sg:postcode":"07011",
    "sg:province":"NJ",
    "sg:website":"www.palsplus.org",
    "wof:name":"Pals Plus",
    "wof:placetype":"venue"
},
  "geometry": {"coordinates":[-74.14921,40.879743],"type":"Point"}
}