{
  "type": "Feature",
  "properties": {
    "addr:full":"401 S Pine Ave South Amboy NJ 08879",
    "addr:housenumber":"401",
    "addr:postcode":"08879",
    "addr:street":"S Pine Ave",
    "iso:country":"US",
    "sg:address":"401 S Pine Ave",
    "sg:city":"South Amboy",
    "sg:classifiers":[
        {
            "category":"Autos & Motor Vehicles",
            "subcategory":"Fuel & Gas Station",
            "type":"Retail Goods"
        }
    ],
    "sg:phone":"+1   ",
    "sg:postcode":"08879",
    "sg:province":"NJ",
    "sg:tags":[
        "automotive",
        "station",
        "gasoline",
        "repair"
    ],
    "wof:name":"All Car Tech Inc",
    "wof:placetype":"venue"
},
  "geometry": {"coordinates":[-74.27682299999999,40.468131],"type":"Point"}
}