{
  "type": "Feature",
  "properties": {
    "iso:country":"US",
    "sg:address":"19 Morford Pl",
    "sg:city":"Red Bank",
    "sg:classifiers":[
        {
            "category":"Building & Trades",
            "subcategory":"Construction",
            "type":"Services"
        }
    ],
    "sg:phone":"+1 732 262 0866",
    "sg:postcode":"07701",
    "sg:province":"NJ",
    "sg:tags":[
        "floor",
        "laying",
        "contractor"
    ],
    "wof:name":"Solid Hardwood Flooring",
    "wof:placetype":"venue"
},
  "geometry": {"coordinates":[-74.07424899999999,40.351818],"type":"Point"}
}