{
  "type": "Feature",
  "properties": {
    "iso:country":"US",
    "sg:address":"205 Melrose Ave",
    "sg:city":"Atlantic City",
    "sg:classifiers":[
        {
            "category":"Retail",
            "subcategory":"Laundry & Dry Cleaning",
            "type":"Services"
        }
    ],
    "sg:phone":"+1 609 340 0003",
    "sg:postcode":"08401",
    "sg:province":"NJ",
    "sg:tags":[
        "drycleaning",
        "plant",
        "cleaners"
    ],
    "wof:name":"Image Dry Cleaners LLC",
    "wof:placetype":"venue"
},
  "geometry": {"coordinates":[-74.417001,39.371945],"type":"Point"}
}