{
  "type": "Feature",
  "properties": {
    "iso:country":"US",
    "sg:address":"254 Brick Blvd",
    "sg:city":"Brick",
    "sg:classifiers":[
        {
            "category":"Professional",
            "subcategory":"Accounting & Tax Preparation",
            "type":"Services"
        }
    ],
    "sg:phone":"+1 732 477 0300",
    "sg:postcode":"08723",
    "sg:province":"NJ",
    "sg:tags":[
        "accountant"
    ],
    "wof:name":"Taxfirm",
    "wof:placetype":"venue"
},
  "geometry": {"coordinates":[-74.142799,40.038555],"type":"Point"}
}