{
  "type": "Feature",
  "properties": {
    "addr:full":"1211 Hamburg Tpke Wayne NJ 07470",
    "addr:housenumber":"1211",
    "addr:postcode":"07470",
    "addr:street":"Hamburg Tpke",
    "iso:country":"US",
    "sg:address":"1211 Hamburg Tpke",
    "sg:city":"Wayne",
    "sg:classifiers":[
        {
            "category":"Banks & Credit Unions",
            "subcategory":"Bank",
            "type":"Services"
        }
    ],
    "sg:phone":"+1 973 709 9214",
    "sg:postcode":"07470",
    "sg:province":"NJ",
    "sg:tags":[
        "loan",
        "real estate"
    ],
    "wof:name":"Resource Mortgage LLC",
    "wof:placetype":"venue"
},
  "geometry": {"coordinates":[-74.242953,40.960626],"type":"Point"}
}