{
  "type": "Feature",
  "properties": {
    "iso:country":"US",
    "sg:address":"103 Princeton Ave",
    "sg:city":"Brick",
    "sg:classifiers":[
        {
            "category":"Professional",
            "subcategory":"Testing Lab",
            "type":"Services"
        },
        {
            "category":"Manufacturing",
            "subcategory":"Tools & Machinery",
            "type":"Manufacturing & Wholesale Goods"
        }
    ],
    "sg:phone":"+1 732 458 6565",
    "sg:postcode":"08724",
    "sg:province":"NJ",
    "sg:tags":[
        "consulting",
        "plastic",
        "mfg"
    ],
    "wof:name":"Seville Mold Technologies LLC",
    "wof:placetype":"venue"
},
  "geometry": {"coordinates":[-74.121982,40.06603],"type":"Point"}
}