{
  "type": "Feature",
  "properties": {
    "iso:country":"US",
    "sg:address":"1203 N High St",
    "sg:city":"Millville",
    "sg:classifiers":[
        {
            "category":"Health Services",
            "subcategory":"Doctor",
            "type":"Services"
        }
    ],
    "sg:phone":"+1 856 327 0182",
    "sg:postcode":"08332",
    "sg:province":"NJ",
    "sg:tags":[
        "physician",
        "surgeon"
    ],
    "wof:name":"Cumberland Family Medicine",
    "wof:placetype":"venue"
},
  "geometry": {"coordinates":[-75.03981400000001,39.41182],"type":"Point"}
}