{
  "type": "Feature",
  "properties": {
    "addr:full":"1 Satt Blvd Rio Grande NJ 08242",
    "addr:housenumber":"1",
    "addr:postcode":"08242",
    "addr:street":"Satt Blvd",
    "iso:country":"US",
    "sg:address":"1 Satt Blvd",
    "sg:city":"Rio Grande",
    "sg:classifiers":[
        {
            "category":"Autos & Motor Vehicles",
            "subcategory":"Fuel & Gas Station",
            "type":"Retail Goods"
        }
    ],
    "sg:phone":"+1   ",
    "sg:postcode":"08242",
    "sg:province":"NJ",
    "sg:tags":[
        "station",
        "gasoline"
    ],
    "wof:name":"Sunoco",
    "wof:placetype":"venue"
},
  "geometry": {"coordinates":[-74.876043,39.0242],"type":"Point"}
}