{
  "type": "Feature",
  "properties": {
    "iso:country":"US",
    "sg:address":"467 S Broadway",
    "sg:city":"Gloucester City",
    "sg:classifiers":[
        {
            "category":"Personal",
            "subcategory":"Beauty Salon",
            "type":"Services"
        }
    ],
    "sg:phone":"+1 856 456 4313",
    "sg:postcode":"08030",
    "sg:province":"NJ",
    "wof:name":"A Little Trim",
    "wof:placetype":"venue"
},
  "geometry": {"coordinates":[-75.120587,39.888508],"type":"Point"}
}