{
  "type": "Feature",
  "properties": {
    "addr:full":"822 S 10th St Newark NJ 07108",
    "addr:housenumber":"822",
    "addr:postcode":"07108",
    "addr:street":"S 10Th St",
    "iso:country":"US",
    "sg:address":"822 S 10th St",
    "sg:city":"Newark",
    "sg:classifiers":[
        {
            "category":"Shopping",
            "subcategory":"Clothing, Apparel, & Fashions",
            "type":"Retail Goods"
        }
    ],
    "sg:phone":"+1   ",
    "sg:postcode":"07108",
    "sg:province":"NJ",
    "wof:name":"Dolls Hosiery",
    "wof:placetype":"venue"
},
  "geometry": {"coordinates":[-74.206778,40.723942],"type":"Point"}
}