{
  "type": "Feature",
  "properties": {
    "addr:full":"848 Norway Ave Trenton NJ 08629",
    "addr:housenumber":"848",
    "addr:postcode":"08629",
    "addr:street":"Norway Ave",
    "iso:country":"US",
    "sg:address":"848 Norway Ave",
    "sg:city":"Trenton",
    "sg:classifiers":[
        {
            "category":"Building & Trades",
            "subcategory":"Cleaning & Sanitation",
            "type":"Services"
        }
    ],
    "sg:phone":"+1   ",
    "sg:postcode":"08629",
    "sg:province":"NJ",
    "sg:tags":[
        "janitorial"
    ],
    "wof:name":"Mercer Janitorial Services",
    "wof:placetype":"venue"
},
  "geometry": {"coordinates":[-74.72491599999999,40.223627],"type":"Point"}
}