{
  "type": "Feature",
  "properties": {
    "iso:country":"US",
    "sg:address":"20 Hunter Pl",
    "sg:city":"Fair Lawn",
    "sg:classifiers":[
        {
            "category":"Arts & Performance",
            "subcategory":"Theater",
            "type":"Entertainment"
        }
    ],
    "sg:phone":"+1   ",
    "sg:postcode":"07410",
    "sg:province":"NJ",
    "sg:tags":[
        "group"
    ],
    "wof:name":"Air Bag Entertainment Inc",
    "wof:placetype":"venue"
},
  "geometry": {"coordinates":[-74.113088,40.95006],"type":"Point"}
}