{
  "type": "Feature",
  "properties": {
    "addr:full":"10 Bay Ave Forked River NJ 08731",
    "addr:housenumber":"10",
    "addr:postcode":"08731",
    "addr:street":"Bay Ave",
    "iso:country":"US",
    "sg:address":"10 Bay Ave",
    "sg:city":"Forked River",
    "sg:classifiers":[
        {
            "category":"Building & Trades",
            "subcategory":"Electrical",
            "type":"Services"
        }
    ],
    "sg:phone":"+1 609 971 9909",
    "sg:postcode":"08731",
    "sg:province":"NJ",
    "sg:tags":[
        "is",
        "as",
        "parent",
        "same"
    ],
    "wof:name":"Tec Electric Inc",
    "wof:placetype":"venue"
},
  "geometry": {"coordinates":[-74.193625,39.836397],"type":"Point"}
}