{
  "type": "Feature",
  "properties": {
    "iso:country":"US",
    "sg:address":"6 West Blvd",
    "sg:city":"Newfield",
    "sg:classifiers":[
        {
            "category":"Food & Beverages",
            "subcategory":"Liquor & Beverages",
            "type":"Retail Goods"
        }
    ],
    "sg:phone":"+1 856 697 1991",
    "sg:postcode":"08344",
    "sg:province":"NJ",
    "wof:name":"Newfield Discount Liquor Store",
    "wof:placetype":"venue"
},
  "geometry": {"coordinates":[-75.024641,39.545614],"type":"Point"}
}