{
  "type": "Feature",
  "properties": {
    "addr:full":"756 Hamburg Tpke Apt 2 Pompton Lakes NJ 07442",
    "addr:housenumber":"756;2",
    "addr:postcode":"07442",
    "addr:street":"Hamburg Tpke Apt",
    "iso:country":"US",
    "sg:address":"756 Hamburg Tpke Apt 2",
    "sg:city":"Pompton Lakes",
    "sg:classifiers":[
        {
            "category":"Shopping",
            "subcategory":"Computers & Home Electronics",
            "type":"Retail Goods"
        }
    ],
    "sg:phone":"+1 973 248 1501",
    "sg:postcode":"07442",
    "sg:province":"NJ",
    "wof:name":"Home Systems",
    "wof:placetype":"venue"
},
  "geometry": {"coordinates":[-74.281097,40.993099],"type":"Point"}
}