{
  "type": "Feature",
  "properties": {
    "iso:country":"US",
    "sg:address":"6 Venice Ave",
    "sg:city":"Middlesex",
    "sg:classifiers":[
        {
            "category":"Building & Trades",
            "subcategory":"Landscaping Services",
            "type":"Services"
        }
    ],
    "sg:phone":"+1 732 560 9741",
    "sg:postcode":"08846",
    "sg:province":"NJ",
    "sg:tags":[
        "landscape",
        "contractor"
    ],
    "wof:name":"K2 Landscaping",
    "wof:placetype":"venue"
},
  "geometry": {"coordinates":[-74.505605,40.580161],"type":"Point"}
}