{
  "type": "Feature",
  "properties": {
    "addr:full":"6 Gladstone Rd Hewitt NJ 07421",
    "addr:housenumber":"6",
    "addr:postcode":"07421",
    "addr:street":"Gladstone Rd",
    "iso:country":"US",
    "sg:address":"6 Gladstone Rd",
    "sg:city":"Hewitt",
    "sg:classifiers":[
        {
            "category":"Building & Trades",
            "subcategory":"Landscaping Services",
            "type":"Services"
        }
    ],
    "sg:phone":"+1 973 853 5104",
    "sg:postcode":"07421",
    "sg:province":"NJ",
    "sg:tags":[
        "landscape"
    ],
    "wof:name":"D J Sisco Construction",
    "wof:placetype":"venue"
},
  "geometry": {"coordinates":[-74.36084099999999,41.190704],"type":"Point"}
}