{
  "type": "Feature",
  "properties": {
    "iso:country":"US",
    "sg:address":"450 Lewis St",
    "sg:city":"Fort Lee",
    "sg:classifiers":[
        {
            "category":"Health Services",
            "subcategory":"Doctor",
            "type":"Services"
        }
    ],
    "sg:phone":"+1 201 947 5367",
    "sg:postcode":"07024",
    "sg:province":"NJ",
    "sg:tags":[
        "dentist"
    ],
    "wof:name":"Martin S Halpert DDS",
    "wof:placetype":"venue"
},
  "geometry": {"coordinates":[-73.975342,40.856795],"type":"Point"}
}