{
  "type": "Feature",
  "properties": {
    "addr:full":"15 Leffler Hill Rd Flemington NJ 08822",
    "addr:housenumber":"15",
    "addr:postcode":"08822",
    "addr:street":"Leffler Hill Rd",
    "iso:country":"US",
    "sg:address":"15 Leffler Hill Rd",
    "sg:city":"Flemington",
    "sg:classifiers":[
        {
            "category":"Retail",
            "subcategory":"Animal Services",
            "type":"Services"
        }
    ],
    "sg:phone":"+1 908 782 8907",
    "sg:postcode":"08822",
    "sg:province":"NJ",
    "sg:tags":[
        "horse",
        "training"
    ],
    "wof:name":"Glen Eden LLC",
    "wof:placetype":"venue"
},
  "geometry": {"coordinates":[-74.91324299999999,40.48604],"type":"Point"}
}