{
  "type": "Feature",
  "properties": {
    "addr:full":"287 Hillside Ave Livingston NJ 07039",
    "addr:housenumber":"287",
    "addr:postcode":"07039",
    "addr:street":"Hillside Ave",
    "iso:country":"US",
    "sg:address":"287 Hillside Ave",
    "sg:city":"Livingston",
    "sg:classifiers":[
        {
            "category":"Freight",
            "type":"Transportation"
        }
    ],
    "sg:phone":"+1 973 758 1689",
    "sg:postcode":"07039",
    "sg:province":"NJ",
    "wof:name":"Paragon Transport Inc",
    "wof:placetype":"venue"
},
  "geometry": {"coordinates":[-74.342162,40.782561],"type":"Point"}
}