{
  "type": "Feature",
  "properties": {
    "addr:full":"800 New Brunswick Ave Rahway NJ 07065",
    "addr:housenumber":"800",
    "addr:postcode":"07065",
    "addr:street":"New Brunswick Ave",
    "iso:country":"US",
    "sg:address":"800 New Brunswick Ave",
    "sg:city":"Rahway",
    "sg:classifiers":[
        {
            "category":"Building & Trades",
            "subcategory":"Construction",
            "type":"Services"
        }
    ],
    "sg:phone":"+1 732 382 6500",
    "sg:postcode":"07065",
    "sg:province":"NJ",
    "sg:tags":[
        "excavation",
        "contractor"
    ],
    "wof:name":"Hawthorne Property Maint Svcs",
    "wof:placetype":"venue"
},
  "geometry": {"coordinates":[-74.282687,40.599033],"type":"Point"}
}