{
  "type": "Feature",
  "properties": {
    "iso:country":"US",
    "sg:address":"20 Truman Dr S",
    "sg:city":"Edison",
    "sg:classifiers":[
        {
            "category":"Wholesale",
            "subcategory":"Construction Materials",
            "type":"Manufacturing & Wholesale Goods"
        }
    ],
    "sg:phone":"+1 732 777 1131",
    "sg:postcode":"08817",
    "sg:province":"NJ",
    "sg:tags":[
        "representative",
        "for",
        "system"
    ],
    "wof:name":"A A W S Inc",
    "wof:placetype":"venue"
},
  "geometry": {"coordinates":[-74.420186,40.517627],"type":"Point"}
}