{
  "type": "Feature",
  "properties": {
    "iso:country":"US",
    "sg:address":"97 N Mitchell Pl",
    "sg:city":"Little Silver",
    "sg:classifiers":[
        {
            "category":"Health Services",
            "subcategory":"Doctor",
            "type":"Services"
        }
    ],
    "sg:phone":"+1   ",
    "sg:postcode":"07739",
    "sg:province":"NJ",
    "sg:tags":[
        "osteopathic"
    ],
    "wof:name":"Jeffrey W France Do PA NA",
    "wof:placetype":"venue"
},
  "geometry": {"coordinates":[-74.03654299999999,40.347015],"type":"Point"}
}