{
  "type": "Feature",
  "properties": {
    "addr:full":"42 Arneytown Hornerstown Rd Cream Ridge NJ 08514",
    "addr:housenumber":"42",
    "addr:postcode":"08514",
    "addr:street":"Arneytown Hornerstown Rd",
    "iso:country":"US",
    "sg:address":"42 Arneytown Hornerstown Rd",
    "sg:city":"Cream Ridge",
    "sg:classifiers":[
        {
            "category":"Retail",
            "subcategory":"Animal Services",
            "type":"Services"
        }
    ],
    "sg:phone":"+1 609 758 8208",
    "sg:postcode":"08514",
    "sg:province":"NJ",
    "sg:tags":[
        "breeder",
        "horse"
    ],
    "sg:website":"www.walnridgefarm.com",
    "wof:name":"Walnridge Farm",
    "wof:placetype":"venue"
},
  "geometry": {"coordinates":[-74.52512,40.102005],"type":"Point"}
}