{
  "type": "Feature",
  "properties": {
    "addr:full":"5300 Boardwalk Wildwood NJ 08260",
    "addr:housenumber":"5300",
    "addr:postcode":"08260",
    "addr:street":"Boardwalk",
    "iso:country":"US",
    "sg:address":"5300 Boardwalk",
    "sg:city":"Wildwood",
    "sg:classifiers":[
        {
            "category":"Recreation",
            "subcategory":"Amusement Park",
            "type":"Entertainment"
        }
    ],
    "sg:phone":"+1 609 523 8726",
    "sg:postcode":"08260",
    "sg:province":"NJ",
    "wof:name":"Tram Cars",
    "wof:placetype":"venue"
},
  "geometry": {"coordinates":[-74.82260100000001,38.9781],"type":"Point"}
}