{
  "type": "Feature",
  "properties": {
    "addr:full":"55 Cypress Neck Rd Lincroft NJ 07738",
    "addr:housenumber":"55",
    "addr:postcode":"07738",
    "addr:street":"Cypress Neck Rd",
    "iso:country":"US",
    "sg:address":"55 Cypress Neck Rd",
    "sg:city":"Lincroft",
    "sg:classifiers":[
        {
            "category":"Professional",
            "type":"Services"
        }
    ],
    "sg:phone":"+1   ",
    "sg:postcode":"07738",
    "sg:province":"NJ",
    "wof:name":"PSL Corp",
    "wof:placetype":"venue"
},
  "geometry": {"coordinates":[-74.144081,40.362231],"type":"Point"}
}