{
  "type": "Feature",
  "properties": {
    "iso:country":"US",
    "sg:address":"215 Broad St",
    "sg:city":"Eatontown",
    "sg:classifiers":[
        {
            "category":"Education",
            "subcategory":"School",
            "type":"Public Place"
        }
    ],
    "sg:phone":"+1   ",
    "sg:postcode":"07724",
    "sg:province":"NJ",
    "sg:tags":[
        "management"
    ],
    "wof:name":"Eatontown School District",
    "wof:placetype":"venue"
},
  "geometry": {"coordinates":[-74.05153799999999,40.306461],"type":"Point"}
}