{
  "type": "Feature",
  "properties": {
    "iso:country":"US",
    "sg:address":"9 Beverly Rd",
    "sg:city":"Piscataway",
    "sg:classifiers":[
        {
            "category":"Personal",
            "subcategory":"Beauty Salon",
            "type":"Services"
        }
    ],
    "sg:phone":"+1 732 463 1656",
    "sg:postcode":"08854",
    "sg:province":"NJ",
    "sg:tags":[
        "shop"
    ],
    "wof:name":"Nelson Lake Beauty Shop",
    "wof:placetype":"venue"
},
  "geometry": {"coordinates":[-74.443532,40.539246],"type":"Point"}
}