{
  "type": "Feature",
  "properties": {
    "iso:country":"US",
    "sg:address":"675 US Highway 1",
    "sg:city":"North Brunswick",
    "sg:classifiers":[
        {
            "category":"Professional",
            "subcategory":"Research",
            "type":"Services"
        }
    ],
    "sg:phone":"+1 732 371 2694",
    "sg:postcode":"08902",
    "sg:province":"NJ",
    "sg:website":"http://www.actinobac.com/",
    "wof:name":"Actinobac Biomed",
    "wof:placetype":"venue"
},
  "geometry": {"coordinates":[-74.471789,40.458217],"type":"Point"}
}