{
  "type": "Feature",
  "properties": {
    "addr:full":"836 Palisade Ave Teaneck NJ 07666",
    "addr:housenumber":"836",
    "addr:postcode":"07666",
    "addr:street":"Palisade Ave",
    "iso:country":"US",
    "sg:address":"836 Palisade Ave",
    "sg:city":"Teaneck",
    "sg:classifiers":[
        {
            "category":"Professional",
            "subcategory":"Management & Consulting",
            "type":"Services"
        }
    ],
    "sg:phone":"+1 888 692 8600",
    "sg:postcode":"07666",
    "sg:province":"NJ",
    "sg:tags":[
        "product",
        "marketing",
        "production",
        "video",
        "advertising",
        "advertising-promotional"
    ],
    "sg:website":"http://www.fox-videoproductions.com/",
    "wof:name":"Fox Marketing Services",
    "wof:placetype":"venue"
},
  "geometry": {"coordinates":[-74.01761,40.888875],"type":"Point"}
}