{
  "type": "Feature",
  "properties": {
    "iso:country":"US",
    "sg:address":"70 Upper Rainbow Trl",
    "sg:city":"Denville",
    "sg:classifiers":[
        {
            "category":"Professional",
            "subcategory":"Business Services",
            "type":"Services"
        }
    ],
    "sg:phone":"+1 973 627 4848",
    "sg:postcode":"07834",
    "sg:province":"NJ",
    "sg:tags":[
        "interior",
        "consultant",
        "design",
        "decorator"
    ],
    "wof:name":"Stephen Paul Design PA",
    "wof:placetype":"venue"
},
  "geometry": {"coordinates":[-74.461158,40.879321],"type":"Point"}
}