{
  "type": "Feature",
  "properties": {
    "iso:country":"US",
    "sg:address":"120 Newark Pompton Tpke",
    "sg:city":"Pequannock",
    "sg:classifiers":[
        {
            "category":"Personal",
            "subcategory":"Barber",
            "type":"Services"
        }
    ],
    "sg:phone":"+1 973 694 5367",
    "sg:postcode":"07440",
    "sg:province":"NJ",
    "sg:tags":[
        "shop"
    ],
    "wof:name":"Sayeg Michael",
    "wof:placetype":"venue"
},
  "geometry": {"coordinates":[-74.285698,40.946201],"type":"Point"}
}