{
  "type": "Feature",
  "properties": {
    "iso:country":"US",
    "sg:address":"15 Bryant Rd",
    "sg:city":"Waretown",
    "sg:classifiers":[
        {
            "category":"Wholesale",
            "subcategory":"Non-durable Goods",
            "type":"Manufacturing & Wholesale Goods"
        }
    ],
    "sg:phone":"+1 609 242 9539",
    "sg:postcode":"08758",
    "sg:province":"NJ",
    "sg:tags":[
        "advertising"
    ],
    "wof:name":"Sea-Gal Signs & Designs",
    "wof:placetype":"venue"
},
  "geometry": {"coordinates":[-74.194759,39.791304],"type":"Point"}
}