{
  "type": "Feature",
  "properties": {
    "iso:country":"US",
    "sg:address":"9 Tiffany Rd",
    "sg:city":"Morristown",
    "sg:classifiers":[
        {
            "category":"Professional",
            "subcategory":"Management & Consulting",
            "type":"Services"
        }
    ],
    "sg:phone":"+1 973 984 9595",
    "sg:postcode":"07960",
    "sg:province":"NJ",
    "sg:tags":[
        "agency",
        "advertising",
        "business"
    ],
    "wof:name":"Hobbs Communications",
    "wof:placetype":"venue"
},
  "geometry": {"coordinates":[-74.461986,40.796514],"type":"Point"}
}