{
  "type": "Feature",
  "properties": {
    "addr:full":"42 Hudson St Metuchen NJ 08840",
    "addr:housenumber":"42",
    "addr:postcode":"08840",
    "addr:street":"Hudson St",
    "iso:country":"US",
    "sg:address":"42 Hudson St",
    "sg:city":"Metuchen",
    "sg:classifiers":[
        {
            "category":"Social Services",
            "subcategory":"Job Training",
            "type":"Services"
        }
    ],
    "sg:phone":"+1 732 603 0768",
    "sg:postcode":"08840",
    "sg:province":"NJ",
    "wof:name":"Professional Dynamics Inst",
    "wof:placetype":"venue"
},
  "geometry": {"coordinates":[-74.325233,40.555897],"type":"Point"}
}