{
  "type": "Feature",
  "properties": {
    "addr:full":"125 Glasgow Ter Mahwah NJ 07430",
    "addr:housenumber":"125",
    "addr:postcode":"07430",
    "addr:street":"Glasgow Ter",
    "iso:country":"US",
    "sg:address":"125 Glasgow Ter",
    "sg:city":"Mahwah",
    "sg:classifiers":[
        {
            "category":"Place Of Worship",
            "subcategory":"Church",
            "type":"Public Place"
        },
        {
            "category":"Place Of Worship",
            "type":"Public Place"
        },
        {
            "category":"Education",
            "subcategory":"Preschool",
            "type":"Public Place"
        }
    ],
    "sg:phone":"+1 201 529 2117",
    "sg:postcode":"07430",
    "sg:province":"NJ",
    "sg:tags":[
        "lutheran",
        "school",
        "kindergarten",
        "nursery",
        "churches-lutheran-evangelical",
        "america",
        "churches-lutheran"
    ],
    "wof:name":"Holy Cross Nursery School",
    "wof:placetype":"venue"
},
  "geometry": {"coordinates":[-74.165673,41.091661],"type":"Point"}
}