{
  "type": "Feature",
  "properties": {
    "iso:country":"US",
    "sg:address":"619 S White Horse Pike",
    "sg:city":"Lindenwold",
    "sg:classifiers":[
        {
            "category":"Food & Beverages",
            "subcategory":"Liquor & Beverages",
            "type":"Retail Goods"
        }
    ],
    "sg:phone":"+1 856 346 0001",
    "sg:postcode":"08021",
    "sg:province":"NJ",
    "wof:name":"Pike Liquors",
    "wof:placetype":"venue"
},
  "geometry": {"coordinates":[-74.989996,39.815018],"type":"Point"}
}