{
  "type": "Feature",
  "properties": {
    "iso:country":"US",
    "sg:address":"905 W Main St",
    "sg:city":"Millville",
    "sg:classifiers":[
        {
            "category":"Real Estate",
            "subcategory":"Real Estate Services",
            "type":"Services"
        },
        {
            "category":"Real Estate",
            "subcategory":"Developer",
            "type":"Services"
        },
        {
            "category":"Real Estate",
            "subcategory":"Real Estate Agent",
            "type":"Services"
        }
    ],
    "sg:phone":"+1 856 825 8500",
    "sg:postcode":"08332",
    "sg:province":"NJ",
    "sg:tags":[
        "investing",
        "consultant",
        "commercial",
        "broker",
        "buyer"
    ],
    "sg:website":"http://www.C21KeyRealEstate.com",
    "wof:name":"Century 21 Key Real Estate LLC",
    "wof:placetype":"venue"
},
  "geometry": {"coordinates":[-75.059022,39.398111],"type":"Point"}
}