{
  "type": "Feature",
  "properties": {
    "addr:full":"300 Red School Ln Phillipsburg NJ 08865",
    "addr:housenumber":"300",
    "addr:postcode":"08865",
    "addr:street":"Red School Ln",
    "iso:country":"US",
    "sg:address":"300 Red School Ln",
    "sg:city":"Phillipsburg",
    "sg:classifiers":[
        {
            "category":"Manufacturing",
            "subcategory":"Tools & Machinery",
            "type":"Manufacturing & Wholesale Goods"
        }
    ],
    "sg:phone":"+1 908 454 2600",
    "sg:postcode":"08865",
    "sg:province":"NJ",
    "sg:tags":[
        "transformer",
        "mfg"
    ],
    "sg:website":"www.magnetika.com",
    "wof:name":"Magnetika Inc",
    "wof:placetype":"venue"
},
  "geometry": {"coordinates":[-75.166797,40.704861],"type":"Point"}
}