{
  "type": "Feature",
  "properties": {
    "iso:country":"US",
    "sg:address":"685 Bergen Blvd",
    "sg:city":"Ridgefield",
    "sg:classifiers":[
        {
            "category":"Professional",
            "subcategory":"Management & Consulting",
            "type":"Services"
        }
    ],
    "sg:phone":"+1 201 840 8773",
    "sg:postcode":"07657",
    "sg:province":"NJ",
    "sg:tags":[
        "magazine",
        "agent"
    ],
    "wof:name":"E & M Design",
    "wof:placetype":"venue"
},
  "geometry": {"coordinates":[-73.992474,40.831247],"type":"Point"}
}