{
  "type": "Feature",
  "properties": {
    "iso:country":"US",
    "sg:address":"110 Essex St",
    "sg:city":"Millburn",
    "sg:classifiers":[
        {
            "category":"Home & Garden",
            "subcategory":"Furniture",
            "type":"Retail Goods"
        }
    ],
    "sg:phone":"+1   ",
    "sg:postcode":"07041",
    "sg:province":"NJ",
    "wof:name":"Millburn Fine Home Furnishings",
    "wof:placetype":"venue"
},
  "geometry": {"coordinates":[-74.306085,40.725055],"type":"Point"}
}