{
  "type": "Feature",
  "properties": {
    "addr:full":"280 Hazel St Clifton NJ 07011",
    "addr:housenumber":"280",
    "addr:postcode":"07011",
    "addr:street":"Hazel St",
    "iso:country":"US",
    "sg:address":"280 Hazel St",
    "sg:city":"Clifton",
    "sg:classifiers":[
        {
            "category":"Retail",
            "subcategory":"Auto Repair",
            "type":"Services"
        },
        {
            "category":"Wholesale",
            "subcategory":"Auto Parts",
            "type":"Manufacturing & Wholesale Goods"
        }
    ],
    "sg:phone":"+1 973 772 9440",
    "sg:postcode":"07011",
    "sg:province":"NJ",
    "sg:tags":[
        "automobile",
        "general"
    ],
    "wof:name":"Spark Auto Repair",
    "wof:placetype":"venue"
},
  "geometry": {"coordinates":[-74.15982200000001,40.888856],"type":"Point"}
}