{
  "type": "Feature",
  "properties": {
    "iso:country":"US",
    "sg:address":"250 Park Ave",
    "sg:city":"Orange",
    "sg:classifiers":[
        {
            "category":"Personal",
            "subcategory":"Beauty Salon",
            "type":"Services"
        }
    ],
    "sg:phone":"+1 973 414 8224",
    "sg:postcode":"07050",
    "sg:province":"NJ",
    "sg:tags":[
        "manicuring"
    ],
    "wof:name":"Young Nails",
    "wof:placetype":"venue"
},
  "geometry": {"coordinates":[-74.225369,40.77597],"type":"Point"}
}