{
  "type": "Feature",
  "properties": {
    "iso:country":"US",
    "sg:address":"9 Ithaca Ave",
    "sg:city":"Oceanport",
    "sg:classifiers":[
        {
            "category":"Manufacturing",
            "subcategory":"Tools & Machinery",
            "type":"Manufacturing & Wholesale Goods"
        }
    ],
    "sg:phone":"+1 732 229 6163",
    "sg:postcode":"07757",
    "sg:province":"NJ",
    "sg:tags":[
        "battery",
        "equipment",
        "charging"
    ],
    "wof:name":"Battery Cables Unlimited",
    "wof:placetype":"venue"
},
  "geometry": {"coordinates":[-74.003077,40.327571],"type":"Point"}
}