{
  "type": "Feature",
  "properties": {
    "iso:country":"US",
    "sg:address":"3179 US Hwy 9",
    "sg:city":"Old Bridge",
    "sg:classifiers":[
        {
            "category":"Restaurant",
            "type":"Food & Drink"
        }
    ],
    "sg:phone":"+1 732 679 3004",
    "sg:postcode":"08857",
    "sg:province":"NJ",
    "sg:tags":[
        "cafe"
    ],
    "wof:name":"Java Joint Cafe",
    "wof:placetype":"venue"
},
  "geometry": {"coordinates":[-74.30811300000001,40.382954],"type":"Point"}
}