{
  "type": "Feature",
  "properties": {
    "addr:full":"501 Main St Boonton NJ 07005",
    "addr:housenumber":"501",
    "addr:postcode":"07005",
    "addr:street":"Main St",
    "iso:country":"US",
    "sg:address":"501 Main St",
    "sg:city":"Boonton",
    "sg:classifiers":[
        {
            "category":"Government",
            "subcategory":"Post Office",
            "type":"Public Place"
        }
    ],
    "sg:phone":"+1 973 334 2745",
    "sg:postcode":"07005",
    "sg:province":"NJ",
    "wof:name":"Boonton Post Office",
    "wof:placetype":"venue"
},
  "geometry": {"coordinates":[-74.41023199999999,40.904765],"type":"Point"}
}