{
  "type": "Feature",
  "properties": {
    "addr:full":"376 South Ave E Westfield NJ 07090",
    "addr:housenumber":"376",
    "addr:postcode":"07090",
    "addr:street":"South Ave E",
    "iso:country":"US",
    "sg:address":"376 South Ave E",
    "sg:city":"Westfield",
    "sg:classifiers":[
        {
            "category":"Professional",
            "subcategory":"Lawyer & Legal Services",
            "type":"Services"
        }
    ],
    "sg:phone":"+1 908 317 9405",
    "sg:postcode":"07090",
    "sg:province":"NJ",
    "sg:tags":[
        "attorney"
    ],
    "wof:name":"Darin D Pinto Law Offices",
    "wof:placetype":"venue"
},
  "geometry": {"coordinates":[-74.33748900000001,40.649662],"type":"Point"}
}