{
  "type": "Feature",
  "properties": {
    "addr:full":"251 Saint George Ave Roselle NJ 07203",
    "addr:housenumber":"251",
    "addr:postcode":"07203",
    "addr:street":"Saint George Ave",
    "iso:country":"US",
    "sg:address":"251 Saint George Ave",
    "sg:city":"Roselle",
    "sg:classifiers":[
        {
            "category":"Restaurant",
            "type":"Food & Drink"
        }
    ],
    "sg:menulink":"http://www.allmenus.com/nj/linden/194534-mcdonalds/menu/",
    "sg:phone":"+1 908 245 1490",
    "sg:postcode":"07203",
    "sg:province":"NJ",
    "sg:tags":[
        "burger",
        "american"
    ],
    "wof:name":"McDonald's",
    "wof:placetype":"venue"
},
  "geometry": {"coordinates":[-74.261126,40.64084],"type":"Point"}
}