{
  "type": "Feature",
  "properties": {
    "iso:country":"US",
    "sg:address":"101 N Dorset Ave",
    "sg:city":"Ventnor City",
    "sg:classifiers":[
        {
            "category":"Professional",
            "subcategory":"Engineering",
            "type":"Services"
        }
    ],
    "sg:phone":"+1 609 823 8200",
    "sg:postcode":"08406",
    "sg:province":"NJ",
    "wof:name":"Robert Booye Architect",
    "wof:placetype":"venue"
},
  "geometry": {"coordinates":[-74.47958199999999,39.343311],"type":"Point"}
}