{
  "type": "Feature",
  "properties": {
    "iso:country":"US",
    "sg:address":"25 Fairview Pl",
    "sg:city":"Morristown",
    "sg:classifiers":[
        {
            "category":"Building & Trades",
            "subcategory":"Landscaping Services",
            "type":"Services"
        }
    ],
    "sg:phone":"+1 973 695 0156",
    "sg:postcode":"07960",
    "sg:province":"NJ",
    "sg:tags":[
        "landscape",
        "contractor"
    ],
    "wof:name":"Cosco Landscaping",
    "wof:placetype":"venue"
},
  "geometry": {"coordinates":[-74.492992,40.795835],"type":"Point"}
}