{
  "type": "Feature",
  "properties": {
    "iso:country":"US",
    "sg:address":"707 State Rd",
    "sg:city":"Princeton",
    "sg:classifiers":[
        {
            "category":"Professional",
            "subcategory":"Computer Services",
            "type":"Services"
        }
    ],
    "sg:phone":"+1   ",
    "sg:postcode":"08540",
    "sg:province":"NJ",
    "wof:name":"Greathomevideo",
    "wof:placetype":"venue"
},
  "geometry": {"coordinates":[-74.658428,40.386864],"type":"Point"}
}