{
  "type": "Feature",
  "properties": {
    "iso:country":"US",
    "sg:address":"1327 Old Zion Rd",
    "sg:city":"Egg Harbor Township",
    "sg:classifiers":[
        {
            "category":"Wholesale",
            "subcategory":"Groceries",
            "type":"Manufacturing & Wholesale Goods"
        }
    ],
    "sg:phone":"+1 609 653 8419",
    "sg:postcode":"08234",
    "sg:province":"NJ",
    "wof:name":"Research and Development Dept",
    "wof:placetype":"venue"
},
  "geometry": {"coordinates":[-74.596977,39.356826],"type":"Point"}
}