{
  "type": "Feature",
  "properties": {
    "iso:country":"US",
    "sg:address":"223 S White Horse Pike",
    "sg:city":"Audubon",
    "sg:classifiers":[
        {
            "category":"Education",
            "subcategory":"School",
            "type":"Public Place"
        }
    ],
    "sg:phone":"+1 856 546 5566",
    "sg:postcode":"08106",
    "sg:province":"NJ",
    "sg:website":"http://www.princetontutoring.com",
    "wof:name":"Tutoring Academy of NJ",
    "wof:placetype":"venue"
},
  "geometry": {"coordinates":[-75.067632,39.89309],"type":"Point"}
}