{
  "type": "Feature",
  "properties": {
    "addr:full":"845 Adelaide Ave Woodbridge NJ 07095",
    "addr:housenumber":"845",
    "addr:postcode":"07095",
    "addr:street":"Adelaide Ave",
    "iso:country":"US",
    "sg:address":"845 Adelaide Ave",
    "sg:city":"Woodbridge",
    "sg:classifiers":[
        {
            "category":"Professional",
            "subcategory":"Management & Consulting",
            "type":"Services"
        }
    ],
    "sg:phone":"+1   ",
    "sg:postcode":"07095",
    "sg:province":"NJ",
    "wof:name":"Kocun Assoc LLC",
    "wof:placetype":"venue"
},
  "geometry": {"coordinates":[-74.28250800000001,40.571345],"type":"Point"}
}