{
  "type": "Feature",
  "properties": {
    "iso:country":"US",
    "sg:address":"3218 Avalon Ct",
    "sg:city":"Voorhees",
    "sg:classifiers":[
        {
            "category":"Health Services",
            "subcategory":"Doctor",
            "type":"Services"
        }
    ],
    "sg:phone":"+1 856 988 7900",
    "sg:postcode":"08043",
    "sg:province":"NJ",
    "sg:tags":[
        "medical"
    ],
    "wof:name":"Visiting Physician",
    "wof:placetype":"venue"
},
  "geometry": {"coordinates":[-74.94449899999999,39.862107],"type":"Point"}
}