{
  "type": "Feature",
  "properties": {
    "addr:full":"210 Summit Ave Ste B2 Montvale NJ 07645",
    "addr:housenumber":"210",
    "addr:postcode":"07645",
    "addr:street":"Summit Ave Ste B2",
    "iso:country":"US",
    "sg:address":"210 Summit Ave Ste B2",
    "sg:city":"Montvale",
    "sg:classifiers":[
        {
            "category":"Manufacturing",
            "subcategory":"Chemicals & Compounds",
            "type":"Manufacturing & Wholesale Goods"
        }
    ],
    "sg:phone":"+1 201 573 1955",
    "sg:postcode":"07645",
    "sg:province":"NJ",
    "sg:tags":[
        "chemicals-wholesale",
        "manufacturer"
    ],
    "wof:name":"Gantrade Corporation",
    "wof:placetype":"venue"
},
  "geometry": {"coordinates":[-74.06807499999999,41.058096],"type":"Point"}
}