{
  "type": "Feature",
  "properties": {
    "addr:full":"393 Brunswick Ave Trenton NJ 08618",
    "addr:housenumber":"393",
    "addr:postcode":"08618",
    "addr:street":"Brunswick Ave",
    "iso:country":"US",
    "sg:address":"393 Brunswick Ave",
    "sg:city":"Trenton",
    "sg:classifiers":[
        {
            "category":"Wholesale",
            "subcategory":"Toys & Hobbies",
            "type":"Manufacturing & Wholesale Goods"
        }
    ],
    "sg:phone":"+1 609 393 0419",
    "sg:postcode":"08618",
    "sg:province":"NJ",
    "sg:tags":[
        "wholesaler"
    ],
    "wof:name":"Sun Wholesale Inc",
    "wof:placetype":"venue"
},
  "geometry": {"coordinates":[-74.759974,40.228881],"type":"Point"}
}