{
  "type": "Feature",
  "properties": {
    "addr:full":"2003 S 2nd St Millville NJ 08332",
    "addr:housenumber":"2003",
    "addr:postcode":"08332",
    "addr:street":"S 2Nd St",
    "iso:country":"US",
    "sg:address":"2003 S 2nd St",
    "sg:city":"Millville",
    "sg:classifiers":[
        {
            "category":"Professional",
            "type":"Services"
        }
    ],
    "sg:phone":"+1 856 765 1776",
    "sg:postcode":"08332",
    "sg:province":"NJ",
    "sg:tags":[
        "establishment"
    ],
    "wof:name":"Heritage Hill Estates",
    "wof:placetype":"venue"
},
  "geometry": {"coordinates":[-75.025144,39.374341],"type":"Point"}
}