{
  "type": "Feature",
  "properties": {
    "addr:full":"5 Crane Ave Caldwell NJ 07006",
    "addr:housenumber":"5",
    "addr:postcode":"07006",
    "addr:street":"Crane Ave",
    "iso:country":"US",
    "sg:address":"5 Crane Ave",
    "sg:city":"Caldwell",
    "sg:classifiers":[
        {
            "category":"Building & Trades",
            "subcategory":"Construction",
            "type":"Services"
        }
    ],
    "sg:phone":"+1 973 364 0517",
    "sg:postcode":"07006",
    "sg:province":"NJ",
    "sg:tags":[
        "contractor"
    ],
    "wof:name":"JP Custom Contractors Liab",
    "wof:placetype":"venue"
},
  "geometry": {"coordinates":[-74.262595,40.846917],"type":"Point"}
}