{
  "type": "Feature",
  "properties": {
    "addr:full":"481 Brittany Ln Cherry Hill NJ 08003",
    "addr:housenumber":"481",
    "addr:postcode":"08003",
    "addr:street":"Brittany Ln",
    "iso:country":"US",
    "sg:address":"481 Brittany Ln",
    "sg:city":"Cherry Hill",
    "sg:classifiers":[
        {
            "category":"Professional",
            "subcategory":"Management & Consulting",
            "type":"Services"
        }
    ],
    "sg:phone":"+1   ",
    "sg:postcode":"08003",
    "sg:province":"NJ",
    "wof:name":"Provuncular",
    "wof:placetype":"venue"
},
  "geometry": {"coordinates":[-74.95408,39.870189],"type":"Point"}
}