{
  "type": "Feature",
  "properties": {
    "addr:full":"144 Bloomfield Ave Montclair NJ 07042",
    "addr:housenumber":"144",
    "addr:postcode":"07042",
    "addr:street":"Bloomfield Ave",
    "iso:country":"US",
    "sg:address":"144 Bloomfield Ave",
    "sg:city":"Montclair",
    "sg:classifiers":[
        {
            "category":"Insurance",
            "subcategory":"Insurance Agent",
            "type":"Services"
        }
    ],
    "sg:phone":"+1 973 744 0595",
    "sg:postcode":"07042",
    "sg:province":"NJ",
    "wof:name":"M & L Insurance",
    "wof:placetype":"venue"
},
  "geometry": {"coordinates":[-74.211365,40.808476],"type":"Point"}
}