{
  "type": "Feature",
  "properties": {
    "addr:full":"308 Herrod Blvd Dayton NJ 08810",
    "addr:housenumber":"308",
    "addr:postcode":"08810",
    "addr:street":"Herrod Blvd",
    "iso:country":"US",
    "sg:address":"308 Herrod Blvd",
    "sg:city":"Dayton",
    "sg:classifiers":[
        {
            "category":"Professional",
            "subcategory":"Advertising",
            "type":"Services"
        }
    ],
    "sg:phone":"+1 732 438 0849",
    "sg:postcode":"08810",
    "sg:province":"NJ",
    "sg:tags":[
        "distribution"
    ],
    "sg:website":"www.barnesandnoble.com",
    "wof:name":"Barnesandnoble.Com Inc",
    "wof:placetype":"venue"
},
  "geometry": {"coordinates":[-74.48229000000001,40.3676],"type":"Point"}
}