{
  "type": "Feature",
  "properties": {
    "iso:country":"US",
    "sg:address":"225 Scotland Rd",
    "sg:city":"Orange",
    "sg:classifiers":[
        {
            "category":"Personal",
            "type":"Services"
        }
    ],
    "sg:phone":"+1 973 677 2000",
    "sg:postcode":"07050",
    "sg:province":"NJ",
    "sg:tags":[
        "mover"
    ],
    "wof:name":"Mayflower Worldwide Moving G Agency",
    "wof:placetype":"venue"
},
  "geometry": {"coordinates":[-74.23870100000001,40.769901],"type":"Point"}
}