{
  "type": "Feature",
  "properties": {
    "addr:full":"400 Union Ave Paterson NJ 07502",
    "addr:housenumber":"400",
    "addr:postcode":"07502",
    "addr:street":"Union Ave",
    "iso:country":"US",
    "sg:address":"400 Union Ave",
    "sg:city":"Paterson",
    "sg:classifiers":[
        {
            "category":"Building & Trades",
            "subcategory":"Locksmith",
            "type":"Services"
        }
    ],
    "sg:phone":"+1 888 243 6458",
    "sg:postcode":"07502",
    "sg:province":"NJ",
    "sg:tags":[
        "key"
    ],
    "wof:name":"A 1 Emergency Locksmith",
    "wof:placetype":"venue"
},
  "geometry": {"coordinates":[-74.185709,40.920716],"type":"Point"}
}