{
  "type": "Feature",
  "properties": {
    "addr:full":"100 Demarest Dr Wayne NJ 07470",
    "addr:housenumber":"100",
    "addr:postcode":"07470",
    "addr:street":"Demarest Dr",
    "iso:country":"US",
    "sg:address":"100 Demarest Dr",
    "sg:city":"Wayne",
    "sg:classifiers":[
        {
            "category":"Personal",
            "type":"Services"
        }
    ],
    "sg:phone":"+1 973 694 7575",
    "sg:postcode":"07470",
    "sg:province":"NJ",
    "sg:tags":[
        "mover"
    ],
    "sg:website":"www.suddath.com",
    "wof:name":"Suddeath Relocation Systems",
    "wof:placetype":"venue"
},
  "geometry": {"coordinates":[-74.263518,40.905645],"type":"Point"}
}