{
  "type": "Feature",
  "properties": {
    "addr:full":"137 S Brewster Rd Vineland NJ 08361",
    "addr:housenumber":"137",
    "addr:postcode":"08361",
    "addr:street":"S Brewster Rd",
    "iso:country":"US",
    "sg:address":"137 S Brewster Rd",
    "sg:city":"Vineland",
    "sg:classifiers":[
        {
            "category":"Manufacturing",
            "subcategory":"Glass & Minerals",
            "type":"Manufacturing & Wholesale Goods"
        }
    ],
    "sg:phone":"+1 856 794 2861",
    "sg:postcode":"08361",
    "sg:province":"NJ",
    "sg:tags":[
        "product",
        "mfg"
    ],
    "wof:name":"Federici Designs",
    "wof:placetype":"venue"
},
  "geometry": {"coordinates":[-74.976215,39.482692],"type":"Point"}
}