{
  "type": "Feature",
  "properties": {
    "addr:full":"86 E Branch Rd Allentown NJ 08501",
    "addr:housenumber":"86",
    "addr:postcode":"08501",
    "addr:street":"E Branch Rd",
    "iso:country":"US",
    "sg:address":"86 E Branch Rd",
    "sg:city":"Allentown",
    "sg:classifiers":[
        {
            "category":"Recreation",
            "type":"Entertainment"
        }
    ],
    "sg:phone":"+1 609 259 8923",
    "sg:postcode":"08501",
    "sg:province":"NJ",
    "sg:tags":[
        "stable"
    ],
    "wof:name":"Hickory Ridge Farm",
    "wof:placetype":"venue"
},
  "geometry": {"coordinates":[-74.505071,40.200193],"type":"Point"}
}