{
  "type": "Feature",
  "properties": {
    "addr:full":"127 Cedar St East Hanover NJ 07936",
    "addr:housenumber":"127",
    "addr:postcode":"07936",
    "addr:street":"Cedar St",
    "iso:country":"US",
    "sg:address":"127 Cedar St",
    "sg:city":"East Hanover",
    "sg:classifiers":[
        {
            "category":"Travel",
            "subcategory":"Campground",
            "type":"Entertainment"
        }
    ],
    "sg:phone":"+1 973 887 5755",
    "sg:postcode":"07936",
    "sg:province":"NJ",
    "sg:tags":[
        "camp"
    ],
    "sg:website":"www.arcessex.org",
    "wof:name":"Camp Hope For Retarded Childrn",
    "wof:placetype":"venue"
},
  "geometry": {"coordinates":[-74.3456,40.824432],"type":"Point"}
}