{
  "type": "Feature",
  "properties": {
    "addr:full":"1861 Springfield Ave Maplewood NJ 07040",
    "addr:housenumber":"1861",
    "addr:postcode":"07040",
    "addr:street":"Springfield Ave",
    "iso:country":"US",
    "sg:address":"1861 Springfield Ave",
    "sg:city":"Maplewood",
    "sg:classifiers":[
        {
            "category":"Personal",
            "subcategory":"Tanning Parlor",
            "type":"Services"
        }
    ],
    "sg:phone":"+1 973 313 9600",
    "sg:postcode":"07040",
    "sg:province":"NJ",
    "sg:tags":[
        "salon"
    ],
    "wof:name":"Sunflower Tanning Salon",
    "wof:placetype":"venue"
},
  "geometry": {"coordinates":[-74.267535,40.720994],"type":"Point"}
}