{
  "type": "Feature",
  "properties": {
    "addr:full":"1100 Cornwall Rd Monmouth Junction NJ 08852",
    "addr:housenumber":"1100",
    "addr:postcode":"08852",
    "addr:street":"Cornwall Rd",
    "iso:country":"US",
    "sg:address":"1100 Cornwall Rd",
    "sg:city":"Monmouth Junction",
    "sg:classifiers":[
        {
            "category":"Real Estate",
            "subcategory":"Real Estate Agent",
            "type":"Services"
        }
    ],
    "sg:phone":"+1   ",
    "sg:postcode":"08852",
    "sg:province":"NJ",
    "wof:name":"Pricenton Park Assoc",
    "wof:placetype":"venue"
},
  "geometry": {"coordinates":[-74.532245,40.4142],"type":"Point"}
}