{
  "type": "Feature",
  "properties": {
    "addr:full":"40 Lakeshore Dr Montville NJ 07045",
    "addr:housenumber":"40",
    "addr:postcode":"07045",
    "addr:street":"Lakeshore Dr",
    "iso:country":"US",
    "sg:address":"40 Lakeshore Dr",
    "sg:city":"Montville",
    "sg:classifiers":[
        {
            "category":"Professional",
            "subcategory":"Advertising",
            "type":"Services"
        }
    ],
    "sg:phone":"+1   ",
    "sg:postcode":"07045",
    "sg:province":"NJ",
    "sg:tags":[
        "agency"
    ],
    "wof:name":"Visions Advertising Inc",
    "wof:placetype":"venue"
},
  "geometry": {"coordinates":[-74.376508,40.932985],"type":"Point"}
}