{
  "type": "Feature",
  "properties": {
    "iso:country":"US",
    "sg:address":"212 Belleville Ave",
    "sg:city":"Belleville",
    "sg:classifiers":[
        {
            "category":"Building & Trades",
            "subcategory":"Locksmith",
            "type":"Services"
        }
    ],
    "sg:phone":"+1 888 245 3142",
    "sg:postcode":"07109",
    "sg:province":"NJ",
    "sg:tags":[
        "key"
    ],
    "wof:name":"A 24 Hour Emergency Locksmith",
    "wof:placetype":"venue"
},
  "geometry": {"coordinates":[-74.158489,40.787408],"type":"Point"}
}