{
  "type": "Feature",
  "properties": {
    "addr:full":"1 Aspen Ln Howell NJ 07731",
    "addr:housenumber":"1",
    "addr:postcode":"07731",
    "addr:street":"Aspen Ln",
    "iso:country":"US",
    "sg:address":"1 Aspen Ln",
    "sg:city":"Howell",
    "sg:classifiers":[
        {
            "category":"Freight",
            "type":"Transportation"
        }
    ],
    "sg:phone":"+1 732 751 0282",
    "sg:postcode":"07731",
    "sg:province":"NJ",
    "sg:tags":[
        "hauling",
        "trucking"
    ],
    "wof:name":"Elite Transport",
    "wof:placetype":"venue"
},
  "geometry": {"coordinates":[-74.145572,40.113374],"type":"Point"}
}