{
  "type": "Feature",
  "properties": {
    "iso:country":"US",
    "sg:address":"736 Landis Ave",
    "sg:city":"Bridgeton",
    "sg:classifiers":[
        {
            "category":"Government",
            "subcategory":"Office",
            "type":"Public Place"
        }
    ],
    "sg:phone":"+1 856 455 3200",
    "sg:postcode":"08302",
    "sg:province":"NJ",
    "sg:tags":[
        "village"
    ],
    "wof:name":"Deerfield Twp Violation Bureau",
    "wof:placetype":"venue"
},
  "geometry": {"coordinates":[-75.13804,39.481024],"type":"Point"}
}