{
  "type": "Feature",
  "properties": {
    "addr:full":"319 State St Perth Amboy NJ 08861",
    "addr:housenumber":"319",
    "addr:postcode":"08861",
    "addr:street":"State St",
    "iso:country":"US",
    "sg:address":"319 State St",
    "sg:city":"Perth Amboy",
    "sg:classifiers":[
        {
            "category":"Personal",
            "subcategory":"Barber",
            "type":"Services"
        }
    ],
    "sg:phone":"+1 732 442 4320",
    "sg:postcode":"08861",
    "sg:province":"NJ",
    "sg:tags":[
        "shop"
    ],
    "wof:name":"Da Chop Shop 3",
    "wof:placetype":"venue"
},
  "geometry": {"coordinates":[-74.267641,40.508781],"type":"Point"}
}