{
  "type": "Feature",
  "properties": {
    "iso:country":"US",
    "sg:address":"2900 Dune Dr",
    "sg:city":"Avalon",
    "sg:classifiers":[
        {
            "category":"Real Estate",
            "subcategory":"Architect",
            "type":"Services"
        }
    ],
    "sg:phone":"+1 609 967 9060",
    "sg:postcode":"08202",
    "sg:province":"NJ",
    "wof:name":"Donaldson Group Architects",
    "wof:placetype":"venue"
},
  "geometry": {"coordinates":[-74.722336,39.096503],"type":"Point"}
}