{
  "type": "Feature",
  "properties": {
    "iso:country":"US",
    "sg:address":"262 W Main St",
    "sg:city":"Boonton",
    "sg:classifiers":[
        {
            "category":"Professional",
            "subcategory":"Lawyer & Legal Services",
            "type":"Services"
        }
    ],
    "sg:phone":"+1   ",
    "sg:postcode":"07005",
    "sg:province":"NJ",
    "wof:name":"Trautmann Gregg D",
    "wof:placetype":"venue"
},
  "geometry": {"coordinates":[-74.422837,40.90702],"type":"Point"}
}