{
  "type": "Feature",
  "properties": {
    "iso:country":"US",
    "sg:address":"339 Bloomfield Ave",
    "sg:city":"Caldwell",
    "sg:classifiers":[
        {
            "category":"Real Estate",
            "subcategory":"Real Estate Agent",
            "type":"Services"
        }
    ],
    "sg:phone":"+1   ",
    "sg:postcode":"07006",
    "sg:province":"NJ",
    "wof:name":"Carol Griffoul RE Closer",
    "wof:placetype":"venue"
},
  "geometry": {"coordinates":[-74.27705899999999,40.840402],"type":"Point"}
}