{
  "type": "Feature",
  "properties": {
    "iso:country":"US",
    "sg:address":"240 Williamson St",
    "sg:city":"Elizabeth",
    "sg:classifiers":[
        {
            "category":"Health Services",
            "subcategory":"Doctor",
            "type":"Services"
        }
    ],
    "sg:phone":"+1 908 289 4044",
    "sg:postcode":"07202",
    "sg:province":"NJ",
    "sg:tags":[
        "physician",
        "surgeon"
    ],
    "wof:name":"Arun C Naik MD",
    "wof:placetype":"venue"
},
  "geometry": {"coordinates":[-74.214276,40.658831],"type":"Point"}
}