{
  "type": "Feature",
  "properties": {
    "iso:country":"US",
    "sg:address":"31 Smull Ave",
    "sg:city":"Caldwell",
    "sg:classifiers":[
        {
            "category":"Health Services",
            "subcategory":"Doctor",
            "type":"Services"
        }
    ],
    "sg:phone":"+1 973 226 4848",
    "sg:postcode":"07006",
    "sg:province":"NJ",
    "sg:tags":[
        "podiatrist"
    ],
    "wof:name":"Wacha Albert DPM",
    "wof:placetype":"venue"
},
  "geometry": {"coordinates":[-74.274399,40.841599],"type":"Point"}
}