{
  "type": "Feature",
  "properties": {
    "iso:country":"US",
    "sg:address":"205 Claremont Ave",
    "sg:city":"Montclair",
    "sg:classifiers":[
        {
            "category":"Government",
            "subcategory":"Office",
            "type":"Public Place"
        }
    ],
    "sg:phone":"+1 973 509 4923",
    "sg:postcode":"07042",
    "sg:province":"NJ",
    "sg:tags":[
        "city",
        "taxation"
    ],
    "wof:name":"Montclair Tax Collector",
    "wof:placetype":"venue"
},
  "geometry": {"coordinates":[-74.216675,40.817665],"type":"Point"}
}