{
  "type": "Feature",
  "properties": {
    "addr:full":"51 E Palisade Ave Englewood NJ 07631",
    "addr:housenumber":"51",
    "addr:postcode":"07631",
    "addr:street":"E Palisade Ave",
    "iso:country":"US",
    "sg:address":"51 E Palisade Ave",
    "sg:city":"Englewood",
    "sg:classifiers":[
        {
            "category":"Shopping",
            "subcategory":"Clothing, Apparel, & Fashions",
            "type":"Retail Goods"
        }
    ],
    "sg:phone":"+1 201 541 9558",
    "sg:postcode":"07631",
    "sg:province":"NJ",
    "sg:tags":[
        "item",
        "boutique"
    ],
    "wof:name":"Anik Inc",
    "wof:placetype":"venue"
},
  "geometry": {"coordinates":[-73.97216400000001,40.892493],"type":"Point"}
}