{
  "type": "Feature",
  "properties": {
    "iso:country":"US",
    "sg:address":"51 Franklin Pl",
    "sg:city":"Montclair",
    "sg:classifiers":[
        {
            "category":"Building & Trades",
            "subcategory":"Electrical",
            "type":"Services"
        }
    ],
    "sg:phone":"+1 973 746 2621",
    "sg:postcode":"07042",
    "sg:province":"NJ",
    "sg:tags":[
        "electrician"
    ],
    "wof:name":"Econolec Electric Co",
    "wof:placetype":"venue"
},
  "geometry": {"coordinates":[-74.21489699999999,40.7966],"type":"Point"}
}