{
  "type": "Feature",
  "properties": {
    "iso:country":"US",
    "sg:address":"2 University Plz",
    "sg:city":"Hackensack",
    "sg:classifiers":[
        {
            "category":"Professional",
            "subcategory":"Lawyer & Legal Services",
            "type":"Services"
        }
    ],
    "sg:phone":"+1 201 342 0063",
    "sg:postcode":"07601",
    "sg:province":"NJ",
    "sg:tags":[
        "divorce",
        "assistance"
    ],
    "wof:name":"Divorce Mediation Svc",
    "wof:placetype":"venue"
},
  "geometry": {"coordinates":[-74.039788,40.895967],"type":"Point"}
}