{
  "type": "Feature",
  "properties": {
    "iso:country":"US",
    "sg:address":"558 Main St",
    "sg:city":"Orange",
    "sg:classifiers":[
        {
            "category":"Bars & Pubs",
            "type":"Food & Drink"
        }
    ],
    "sg:phone":"+1 973 677 1881",
    "sg:postcode":"07050",
    "sg:province":"NJ",
    "wof:name":"VIP",
    "wof:placetype":"venue"
},
  "geometry": {"coordinates":[-74.23831,40.776021],"type":"Point"}
}