{
  "type": "Feature",
  "properties": {
    "iso:country":"US",
    "sg:address":"219 White Horse Pike",
    "sg:city":"Audubon",
    "sg:classifiers":[
        {
            "category":"Food & Beverages",
            "subcategory":"Bakery",
            "type":"Retail Goods"
        }
    ],
    "sg:phone":"+1 856 672 1111",
    "sg:postcode":"08106",
    "sg:province":"NJ",
    "sg:tags":[
        "sandwich"
    ],
    "sg:website":"freshworksaudubon.com",
    "wof:name":"The Works",
    "wof:placetype":"venue"
},
  "geometry": {"coordinates":[-75.06772100000001,39.893174],"type":"Point"}
}