{
  "type": "Feature",
  "properties": {
    "addr:full":"2060 Springdale Rd Cherry Hill NJ 08003",
    "addr:housenumber":"2060",
    "addr:postcode":"08003",
    "addr:street":"Springdale Rd",
    "iso:country":"US",
    "sg:address":"2060 Springdale Rd",
    "sg:city":"Cherry Hill",
    "sg:classifiers":[
        {
            "category":"Manufacturing",
            "subcategory":"Tools & Machinery",
            "type":"Manufacturing & Wholesale Goods"
        }
    ],
    "sg:phone":"+1 856 424 1013",
    "sg:postcode":"08003",
    "sg:province":"NJ",
    "sg:tags":[
        "mfg",
        "commercial",
        "lab",
        "physical"
    ],
    "wof:name":"Den Glass Technology",
    "wof:placetype":"venue"
},
  "geometry": {"coordinates":[-74.96486899999999,39.915941],"type":"Point"}
}