{
  "type": "Feature",
  "properties": {
    "addr:full":"843 Saint Georges Ave Roselle NJ 07203",
    "addr:housenumber":"843",
    "addr:postcode":"07203",
    "addr:street":"Saint Georges Ave",
    "iso:country":"US",
    "sg:address":"843 Saint Georges Ave",
    "sg:city":"Roselle",
    "sg:classifiers":[
        {
            "category":"Food & Beverages",
            "subcategory":"Bakery",
            "type":"Retail Goods"
        }
    ],
    "sg:phone":"+1 908 241 5000",
    "sg:postcode":"07203",
    "sg:province":"NJ",
    "sg:tags":[
        "doughnut"
    ],
    "sg:website":"www.dunkindonuts.com",
    "wof:name":"Dunkin' Donuts",
    "wof:placetype":"venue"
},
  "geometry": {"coordinates":[-74.252432,40.645054],"type":"Point"}
}