{
  "type": "Feature",
  "properties": {
    "iso:country":"US",
    "sg:address":"195 Taylor Ave",
    "sg:city":"East Brunswick",
    "sg:classifiers":[
        {
            "category":"Professional",
            "subcategory":"Computer Services",
            "type":"Services"
        }
    ],
    "sg:phone":"+1 732 227 0336",
    "sg:postcode":"08816",
    "sg:province":"NJ",
    "sg:tags":[
        "prepackaged",
        "software"
    ],
    "wof:name":"TRC Squared Software Designs",
    "wof:placetype":"venue"
},
  "geometry": {"coordinates":[-74.409633,40.466021],"type":"Point"}
}