{
  "type": "Feature",
  "properties": {
    "iso:country":"US",
    "sg:address":"111 1st St",
    "sg:city":"Hoboken",
    "sg:classifiers":[
        {
            "category":"Professional",
            "type":"Services"
        }
    ],
    "sg:phone":"+1   ",
    "sg:postcode":"07030",
    "sg:province":"NJ",
    "wof:name":"J Lenard Studio",
    "wof:placetype":"venue"
},
  "geometry": {"coordinates":[-74.03158999999999,40.737472],"type":"Point"}
}