{
  "type": "Feature",
  "properties": {
    "iso:country":"US",
    "sg:address":"66 Park Ave",
    "sg:city":"Rutherford",
    "sg:classifiers":[
        {
            "category":"Food & Beverages",
            "subcategory":"Bakery",
            "type":"Retail Goods"
        }
    ],
    "sg:phone":"+1 201 438 3477",
    "sg:postcode":"07070",
    "sg:province":"NJ",
    "sg:tags":[
        "bagel"
    ],
    "wof:name":"Bagel Master N Deli",
    "wof:placetype":"venue"
},
  "geometry": {"coordinates":[-74.10365400000001,40.827658],"type":"Point"}
}