{
  "type": "Feature",
  "properties": {
    "iso:country":"US",
    "sg:address":"12 Lindsay Dr",
    "sg:city":"Morganville",
    "sg:classifiers":[
        {
            "category":"Professional",
            "subcategory":"Computer Services",
            "type":"Services"
        }
    ],
    "sg:phone":"+1 732 536 4890",
    "sg:postcode":"07751",
    "sg:province":"NJ",
    "sg:tags":[
        "consultant",
        "designer",
        "programing",
        "custom"
    ],
    "wof:name":"Ineticom Associates",
    "wof:placetype":"venue"
},
  "geometry": {"coordinates":[-74.31580099999999,40.336928],"type":"Point"}
}