{
  "type": "Feature",
  "properties": {
    "addr:full":"9 Sussex Ave Newark NJ 07103",
    "addr:housenumber":"9",
    "addr:postcode":"07103",
    "addr:street":"Sussex Ave",
    "iso:country":"US",
    "sg:address":"9 Sussex Ave",
    "sg:city":"Newark",
    "sg:classifiers":[
        {
            "category":"Organizations",
            "subcategory":"Community Association",
            "type":"Services"
        }
    ],
    "sg:phone":"+1   ",
    "sg:postcode":"07103",
    "sg:province":"NJ",
    "sg:tags":[
        "religious"
    ],
    "wof:name":"X I Kappa",
    "wof:placetype":"venue"
},
  "geometry": {"coordinates":[-74.176503,40.743925],"type":"Point"}
}