{
  "type": "Feature",
  "properties": {
    "addr:full":"2 Commerce Dr Ste 3 Moorestown NJ 08057",
    "addr:housenumber":"2",
    "addr:postcode":"08057",
    "addr:street":"Commerce Dr Ste 3",
    "iso:country":"US",
    "sg:address":"2 Commerce Dr Ste 3",
    "sg:city":"Moorestown",
    "sg:classifiers":[
        {
            "category":"Food & Beverages",
            "subcategory":"Liquor & Beverages",
            "type":"Retail Goods"
        },
        {
            "category":"Wholesale",
            "subcategory":"Wine & Distilled Alcoholic Beverages",
            "type":"Manufacturing & Wholesale Goods"
        }
    ],
    "sg:phone":"+1 856 985 6388",
    "sg:postcode":"08057",
    "sg:province":"NJ",
    "sg:tags":[
        "liquors-wholesale",
        "beer",
        "ale",
        "broker",
        "store"
    ],
    "wof:name":"Regal Wine Imports, Inc.",
    "wof:placetype":"venue"
},
  "geometry": {"coordinates":[-74.987396,39.966991],"type":"Point"}
}