{
  "type": "Feature",
  "properties": {
    "addr:full":"1704 S Black Horse Pike Williamstown NJ 08094",
    "addr:housenumber":"1704",
    "addr:postcode":"08094",
    "addr:street":"S Black Horse Pike",
    "iso:country":"US",
    "sg:address":"1704 S Black Horse Pike",
    "sg:city":"Williamstown",
    "sg:classifiers":[
        {
            "category":"Shopping",
            "subcategory":"Clothing, Apparel, & Fashions",
            "type":"Retail Goods"
        }
    ],
    "sg:phone":"+1 856 740 1056",
    "sg:postcode":"08094",
    "sg:province":"NJ",
    "wof:name":"Gallo Clothing",
    "wof:placetype":"venue"
},
  "geometry": {"coordinates":[-74.965633,39.662769],"type":"Point"}
}