{
  "type": "Feature",
  "properties": {
    "iso:country":"US",
    "sg:address":"58 1st Ave",
    "sg:city":"Atlantic Hghlnds",
    "sg:classifiers":[
        {
            "category":"Health Services",
            "subcategory":"Doctor",
            "type":"Services"
        }
    ],
    "sg:phone":"+1 732 291 0942",
    "sg:postcode":"07716",
    "sg:province":"NJ",
    "sg:tags":[
        "dentist"
    ],
    "wof:name":"Bixby & Bixby",
    "wof:placetype":"venue"
},
  "geometry": {"coordinates":[-74.037339,40.415084],"type":"Point"}
}