{
  "type": "Feature",
  "properties": {
    "iso:country":"US",
    "sg:address":"80 River St",
    "sg:city":"Hoboken",
    "sg:classifiers":[
        {
            "category":"Manufacturing",
            "subcategory":"Tools & Machinery",
            "type":"Manufacturing & Wholesale Goods"
        }
    ],
    "sg:phone":"+1 201 792 6372",
    "sg:postcode":"07030",
    "sg:province":"NJ",
    "sg:tags":[
        "equipment",
        "electric"
    ],
    "sg:website":"www.nepainc.com",
    "wof:name":"NEPA",
    "wof:placetype":"venue"
},
  "geometry": {"coordinates":[-74.02923,40.73589],"type":"Point"}
}