{
  "type": "Feature",
  "properties": {
    "addr:full":"2400 Morris Ave Union NJ 07083",
    "addr:housenumber":"2400",
    "addr:postcode":"07083",
    "addr:street":"Morris Ave",
    "iso:country":"US",
    "sg:address":"2400 Morris Ave",
    "sg:city":"Union",
    "sg:classifiers":[
        {
            "category":"Building & Trades",
            "subcategory":"Equipment Rental",
            "type":"Services"
        }
    ],
    "sg:phone":"+1   ",
    "sg:postcode":"07083",
    "sg:province":"NJ",
    "sg:tags":[
        "financing",
        "leasing"
    ],
    "wof:name":"Observer Corporation",
    "wof:placetype":"venue"
},
  "geometry": {"coordinates":[-74.288535,40.701846],"type":"Point"}
}