{
  "type": "Feature",
  "properties": {
    "addr:full":"100 Mount Laurel Rd Mount Laurel NJ 08054",
    "addr:housenumber":"100",
    "addr:postcode":"08054",
    "addr:street":"Mount Laurel Rd",
    "iso:country":"US",
    "sg:address":"100 Mount Laurel Rd",
    "sg:city":"Mount Laurel",
    "sg:classifiers":[
        {
            "category":"Social Services",
            "type":"Services"
        }
    ],
    "sg:phone":"+1   ",
    "sg:postcode":"08054",
    "sg:province":"NJ",
    "wof:name":"Mount Lurel Senior Citizen Ctr",
    "wof:placetype":"venue"
},
  "geometry": {"coordinates":[-74.92714599999999,39.958543],"type":"Point"}
}