{
  "type": "Feature",
  "properties": {
    "iso:country":"US",
    "sg:address":"215 Maine St",
    "sg:city":"Toms River",
    "sg:classifiers":[
        {
            "category":"Professional",
            "type":"Services"
        }
    ],
    "sg:phone":"+1 732 349 8060",
    "sg:postcode":"08753",
    "sg:province":"NJ",
    "sg:tags":[
        "establishment"
    ],
    "wof:name":"Public Entity",
    "wof:placetype":"venue"
},
  "geometry": {"coordinates":[-74.128303,40.010515],"type":"Point"}
}