{
  "type": "Feature",
  "properties": {
    "iso:country":"US",
    "sg:address":"97 Anderson Ave",
    "sg:city":"Fairview",
    "sg:classifiers":[
        {
            "category":"Organizations",
            "subcategory":"Community Association",
            "type":"Services"
        },
        {
            "category":"Recreation",
            "type":"Entertainment"
        }
    ],
    "sg:phone":"+1 201 941 5915",
    "sg:postcode":"07022",
    "sg:province":"NJ",
    "sg:tags":[
        "club",
        "membership",
        "nightlife"
    ],
    "wof:name":"Calabria Club",
    "wof:placetype":"venue"
},
  "geometry": {"coordinates":[-73.9991,40.812801],"type":"Point"}
}