{
  "type": "Feature",
  "properties": {
    "addr:full":"425 Higgins Ave Brielle NJ 08730",
    "addr:housenumber":"425",
    "addr:postcode":"08730",
    "addr:street":"Higgins Ave",
    "iso:country":"US",
    "sg:address":"425 Higgins Ave",
    "sg:city":"Brielle",
    "sg:classifiers":[
        {
            "category":"Health Services",
            "subcategory":"Chiropractor",
            "type":"Services"
        }
    ],
    "sg:phone":"+1   ",
    "sg:postcode":"08730",
    "sg:province":"NJ",
    "wof:name":"Mary D Tumas DC",
    "wof:placetype":"venue"
},
  "geometry": {"coordinates":[-74.058001,40.107244],"type":"Point"}
}