{
  "type": "Feature",
  "properties": {
    "iso:country":"US",
    "sg:address":"16 Arcadian Way",
    "sg:city":"Paramus",
    "sg:classifiers":[
        {
            "category":"Professional",
            "subcategory":"Accounting & Tax Preparation",
            "type":"Services"
        }
    ],
    "sg:phone":"+1 201 843 0444",
    "sg:postcode":"07652",
    "sg:province":"NJ",
    "sg:tags":[
        "accountant"
    ],
    "wof:name":"Gerson & Associates",
    "wof:placetype":"venue"
},
  "geometry": {"coordinates":[-74.08399300000001,40.923458],"type":"Point"}
}