{
  "type": "Feature",
  "properties": {
    "addr:full":"194 US Hwy 46 Budd Lake NJ 07828",
    "addr:housenumber":"194",
    "addr:postcode":"07828",
    "addr:street":"Us Hwy 46",
    "iso:country":"US",
    "sg:address":"194 US Hwy 46",
    "sg:city":"Budd Lake",
    "sg:classifiers":[
        {
            "category":"Personal",
            "subcategory":"Beauty Salon",
            "type":"Services"
        }
    ],
    "sg:phone":"+1 973 691 0005",
    "sg:postcode":"07828",
    "sg:province":"NJ",
    "sg:tags":[
        "manicuring"
    ],
    "wof:name":"Nirvana Spa & Nail",
    "wof:placetype":"venue"
},
  "geometry": {"coordinates":[-74.733417,40.873335],"type":"Point"}
}