{
  "type": "Feature",
  "properties": {
    "addr:full":"233 Tenby Chase Dr Riverside NJ 08075",
    "addr:housenumber":"233",
    "addr:postcode":"08075",
    "addr:street":"Tenby Chase Dr",
    "iso:country":"US",
    "sg:address":"233 Tenby Chase Dr",
    "sg:city":"Riverside",
    "sg:classifiers":[
        {
            "category":"Professional",
            "type":"Services"
        }
    ],
    "sg:phone":"+1   ",
    "sg:postcode":"08075",
    "sg:province":"NJ",
    "wof:name":"Henry Caraballo",
    "wof:placetype":"venue"
},
  "geometry": {"coordinates":[-74.962012,40.005973],"type":"Point"}
}