{
  "type": "Feature",
  "properties": {
    "addr:full":"720 Rutland Ct Sewell NJ 08080",
    "addr:housenumber":"720",
    "addr:postcode":"08080",
    "addr:street":"Rutland Ct",
    "iso:country":"US",
    "sg:address":"720 Rutland Ct",
    "sg:city":"Sewell",
    "sg:classifiers":[
        {
            "category":"Education",
            "subcategory":"Special Training",
            "type":"Public Place"
        }
    ],
    "sg:phone":"+1 856 256 9702",
    "sg:postcode":"08080",
    "sg:province":"NJ",
    "wof:name":"Partner In Life Care",
    "wof:placetype":"venue"
},
  "geometry": {"coordinates":[-75.099834,39.74945],"type":"Point"}
}