{
  "type": "Feature",
  "properties": {
    "addr:full":"213 Clements Bridge Rd Barrington NJ 08007",
    "addr:housenumber":"213",
    "addr:postcode":"08007",
    "addr:street":"Clements Bridge Rd",
    "iso:country":"US",
    "sg:address":"213 Clements Bridge Rd",
    "sg:city":"Barrington",
    "sg:classifiers":[
        {
            "category":"Education",
            "subcategory":"School",
            "type":"Public Place"
        }
    ],
    "sg:phone":"+1 856 546 2742",
    "sg:postcode":"08007",
    "sg:province":"NJ",
    "wof:name":"Tavistock Borough School Dist",
    "wof:placetype":"venue"
},
  "geometry": {"coordinates":[-75.051945,39.871195],"type":"Point"}
}