{
  "type": "Feature",
  "properties": {
    "addr:full":"33 Minton Ave Chatham NJ 07928",
    "addr:housenumber":"33",
    "addr:postcode":"07928",
    "addr:street":"Minton Ave",
    "iso:country":"US",
    "sg:address":"33 Minton Ave",
    "sg:city":"Chatham",
    "sg:classifiers":[
        {
            "category":"Retail",
            "subcategory":"Auto Repair",
            "type":"Services"
        }
    ],
    "sg:phone":"+1   ",
    "sg:postcode":"07928",
    "sg:province":"NJ",
    "sg:tags":[
        "general"
    ],
    "wof:name":"Paterek Preferred Ltd",
    "wof:placetype":"venue"
},
  "geometry": {"coordinates":[-74.37627500000001,40.739338],"type":"Point"}
}