{
  "type": "Feature",
  "properties": {
    "iso:country":"US",
    "sg:address":"9 Windward Way",
    "sg:city":"Red Bank",
    "sg:classifiers":[
        {
            "category":"Shopping",
            "subcategory":"Gifts & Souvenirs",
            "type":"Retail Goods"
        }
    ],
    "sg:phone":"+1 732 747 0085",
    "sg:postcode":"07701",
    "sg:province":"NJ",
    "sg:tags":[
        "shop"
    ],
    "wof:name":"Edge Incentives",
    "wof:placetype":"venue"
},
  "geometry": {"coordinates":[-74.05236600000001,40.350626],"type":"Point"}
}