{
  "type": "Feature",
  "properties": {
    "iso:country":"US",
    "sg:address":"101 US Hwy 46",
    "sg:city":"Saddle Brook",
    "sg:classifiers":[
        {
            "category":"Wholesale",
            "subcategory":"Auto Parts",
            "type":"Manufacturing & Wholesale Goods"
        }
    ],
    "sg:phone":"+1 201 845 8353",
    "sg:postcode":"07663",
    "sg:province":"NJ",
    "wof:name":"P & A Auto Parts Inc",
    "wof:placetype":"venue"
},
  "geometry": {"coordinates":[-74.09267800000001,40.887454],"type":"Point"}
}