{
  "type": "Feature",
  "properties": {
    "iso:country":"US",
    "sg:address":"16 1st St",
    "sg:city":"Bloomingdale",
    "sg:classifiers":[
        {
            "category":"Shopping",
            "subcategory":"Musical Instruments",
            "type":"Retail Goods"
        }
    ],
    "sg:phone":"+1 973 492 9694",
    "sg:postcode":"07403",
    "sg:province":"NJ",
    "sg:tags":[
        "piano"
    ],
    "wof:name":"New Jersey Installation Center",
    "wof:placetype":"venue"
},
  "geometry": {"coordinates":[-74.340716,41.007634],"type":"Point"}
}