{
  "type": "Feature",
  "properties": {
    "addr:full":"305 State Rte 17 Paramus NJ 07652",
    "addr:housenumber":"305",
    "addr:postcode":"07652",
    "addr:street":"State Rte 17",
    "iso:country":"US",
    "sg:address":"305 State Rte 17",
    "sg:city":"Paramus",
    "sg:classifiers":[
        {
            "category":"Retail",
            "subcategory":"Repair Shop",
            "type":"Services"
        }
    ],
    "sg:phone":"+1 201 967 8040",
    "sg:postcode":"07652",
    "sg:province":"NJ",
    "sg:tags":[
        "antique",
        "airplane",
        "restoration"
    ],
    "wof:name":"Buehler AVI Res Foundation",
    "wof:placetype":"venue"
},
  "geometry": {"coordinates":[-74.070825,40.910357],"type":"Point"}
}