{
  "type": "Feature",
  "properties": {
    "addr:full":"717 Kings Hwy S Cherry Hill NJ 08034",
    "addr:housenumber":"717",
    "addr:postcode":"08034",
    "addr:street":"Kings Hwy S",
    "iso:country":"US",
    "sg:address":"717 Kings Hwy S",
    "sg:city":"Cherry Hill",
    "sg:classifiers":[
        {
            "category":"Restaurant",
            "type":"Food & Drink"
        }
    ],
    "sg:phone":"+1 856 667 3232",
    "sg:postcode":"08034",
    "sg:province":"NJ",
    "wof:name":"Johnny's Pizza",
    "wof:placetype":"venue"
},
  "geometry": {"coordinates":[-75.018811,39.906184],"type":"Point"}
}