{
  "type": "Feature",
  "properties": {
    "addr:full":"109 Washington Ave Ste A Belleville NJ 07109",
    "addr:housenumber":"109",
    "addr:postcode":"07109",
    "addr:street":"Washington Ave Ste A",
    "iso:country":"US",
    "sg:address":"109 Washington Ave Ste A",
    "sg:city":"Belleville",
    "sg:classifiers":[
        {
            "category":"Building & Trades",
            "subcategory":"Cleaning & Sanitation",
            "type":"Services"
        }
    ],
    "sg:phone":"+1 973 759 0014",
    "sg:postcode":"07109",
    "sg:province":"NJ",
    "sg:tags":[
        "home"
    ],
    "wof:name":"Chuck's Professional Cleaning Inc",
    "wof:placetype":"venue"
},
  "geometry": {"coordinates":[-74.15370900000001,40.784796],"type":"Point"}
}