{
  "type": "Feature",
  "properties": {
    "iso:country":"US",
    "sg:address":"340 Bogert Rd",
    "sg:city":"River Edge",
    "sg:classifiers":[
        {
            "category":"Social Services",
            "subcategory":"Child Care",
            "type":"Services"
        }
    ],
    "sg:phone":"+1 201 488 4905",
    "sg:postcode":"07661",
    "sg:province":"NJ",
    "wof:name":"Stepping Stone Day Nursery",
    "wof:placetype":"venue"
},
  "geometry": {"coordinates":[-74.036502,40.921433],"type":"Point"}
}