{
  "type": "Feature",
  "properties": {
    "addr:full":"168 Tennent Rd Morganville NJ 07751",
    "addr:housenumber":"168",
    "addr:postcode":"07751",
    "addr:street":"Tennent Rd",
    "iso:country":"US",
    "sg:address":"168 Tennent Rd",
    "sg:city":"Morganville",
    "sg:classifiers":[
        {
            "category":"Autos & Motor Vehicles",
            "subcategory":"Auto Supplies",
            "type":"Retail Goods"
        }
    ],
    "sg:phone":"+1 732 591 9221",
    "sg:postcode":"07751",
    "sg:province":"NJ",
    "sg:tags":[
        "automobile",
        "accessory"
    ],
    "wof:name":"Rhino Linings Of Nj",
    "wof:placetype":"venue"
},
  "geometry": {"coordinates":[-74.261562,40.371001],"type":"Point"}
}