{
  "type": "Feature",
  "properties": {
    "iso:country":"US",
    "sg:address":"1121 Main Ave",
    "sg:city":"Clifton",
    "sg:classifiers":[
        {
            "category":"Professional",
            "subcategory":"Lawyer & Legal Services",
            "type":"Services"
        }
    ],
    "sg:phone":"+1 973 594 8822",
    "sg:postcode":"07011",
    "sg:province":"NJ",
    "wof:name":"Andalaft Michael J ESQ",
    "wof:placetype":"venue"
},
  "geometry": {"coordinates":[-74.138901,40.874401],"type":"Point"}
}