{
  "type": "Feature",
  "properties": {
    "addr:full":"600 Palisade Ave Union City NJ 07087",
    "addr:housenumber":"600",
    "addr:postcode":"07087",
    "addr:street":"Palisade Ave",
    "iso:country":"US",
    "sg:address":"600 Palisade Ave",
    "sg:city":"Union City",
    "sg:classifiers":[
        {
            "category":"Home & Garden",
            "subcategory":"Furniture",
            "type":"Retail Goods"
        },
        {
            "category":"Building & Trades",
            "subcategory":"Construction",
            "type":"Services"
        }
    ],
    "sg:phone":"+1 201 392 0093",
    "sg:postcode":"07087",
    "sg:province":"NJ",
    "sg:tags":[
        "builder",
        "custom",
        "contractor"
    ],
    "wof:name":"Robert Wilson Furniture Design",
    "wof:placetype":"venue"
},
  "geometry": {"coordinates":[-74.03710599999999,40.75522],"type":"Point"}
}