{
  "type": "Feature",
  "properties": {
    "addr:full":"6 Main St Califon NJ 07830",
    "addr:housenumber":"6",
    "addr:postcode":"07830",
    "addr:street":"Main St",
    "iso:country":"US",
    "sg:address":"6 Main St",
    "sg:city":"Califon",
    "sg:classifiers":[
        {
            "category":"Professional",
            "type":"Services"
        }
    ],
    "sg:phone":"+1   ",
    "sg:postcode":"07830",
    "sg:province":"NJ",
    "wof:name":"Tuners of Califon",
    "wof:placetype":"venue"
},
  "geometry": {"coordinates":[-74.832431,40.715405],"type":"Point"}
}