{
  "type": "Feature",
  "properties": {
    "iso:country":"US",
    "sg:address":"579 Tabor Rd",
    "sg:city":"Morris Plains",
    "sg:classifiers":[
        {
            "category":"Building & Trades",
            "subcategory":"Electrical",
            "type":"Services"
        }
    ],
    "sg:phone":"+1 973 267 7679",
    "sg:postcode":"07950",
    "sg:province":"NJ",
    "sg:tags":[
        "electrical",
        "contractor"
    ],
    "wof:name":"Ming Electric Inc",
    "wof:placetype":"venue"
},
  "geometry": {"coordinates":[-74.47325600000001,40.851652],"type":"Point"}
}