{
  "type": "Feature",
  "properties": {
    "iso:country":"US",
    "sg:address":"777 Bergen Ave",
    "sg:city":"Jersey City",
    "sg:classifiers":[
        {
            "category":"Building & Trades",
            "subcategory":"Construction",
            "type":"Services"
        }
    ],
    "sg:phone":"+1 201 333 6486",
    "sg:postcode":"07306",
    "sg:province":"NJ",
    "sg:tags":[
        "contractor"
    ],
    "wof:name":"Enterprise Community Development Corp",
    "wof:placetype":"venue"
},
  "geometry": {"coordinates":[-74.067802,40.726101],"type":"Point"}
}