{
  "type": "Feature",
  "properties": {
    "addr:full":"213 Cooper St Beverly NJ 08010",
    "addr:housenumber":"213",
    "addr:postcode":"08010",
    "addr:street":"Cooper St",
    "iso:country":"US",
    "sg:address":"213 Cooper St",
    "sg:city":"Beverly",
    "sg:classifiers":[
        {
            "category":"Building & Trades",
            "subcategory":"Cleaning & Sanitation",
            "type":"Services"
        }
    ],
    "sg:phone":"+1 609 386 9044",
    "sg:postcode":"08010",
    "sg:province":"NJ",
    "sg:tags":[
        "polishing",
        "waxing",
        "floor"
    ],
    "wof:name":"Conway Floor Svc",
    "wof:placetype":"venue"
},
  "geometry": {"coordinates":[-74.919757,40.065767],"type":"Point"}
}