{
  "type": "Feature",
  "properties": {
    "addr:full":"29 Ehret Ave Harrington Park NJ 07640",
    "addr:housenumber":"29",
    "addr:postcode":"07640",
    "addr:street":"Ehret Ave",
    "iso:country":"US",
    "sg:address":"29 Ehret Ave",
    "sg:city":"Harrington Park",
    "sg:classifiers":[
        {
            "category":"Building & Trades",
            "subcategory":"Construction",
            "type":"Services"
        }
    ],
    "sg:phone":"+1 201 768 4807",
    "sg:postcode":"07640",
    "sg:province":"NJ",
    "sg:tags":[
        "tile",
        "dealer",
        "contractor"
    ],
    "wof:name":"Designer Tile Inc",
    "wof:placetype":"venue"
},
  "geometry": {"coordinates":[-73.976276,40.996729],"type":"Point"}
}