{
  "type": "Feature",
  "properties": {
    "addr:full":"421 W Crystal Lake Ave Haddonfield NJ 08033",
    "addr:housenumber":"421",
    "addr:postcode":"08033",
    "addr:street":"W Crystal Lake Ave",
    "iso:country":"US",
    "sg:address":"421 W Crystal Lake Ave",
    "sg:city":"Haddonfield",
    "sg:classifiers":[
        {
            "category":"Banks & Credit Unions",
            "subcategory":"Bank",
            "type":"Services"
        }
    ],
    "sg:phone":"+1 856 000 1111",
    "sg:postcode":"08033",
    "sg:province":"NJ",
    "wof:name":"Bank Of America",
    "wof:placetype":"venue"
},
  "geometry": {"coordinates":[-75.05246200000001,39.899119],"type":"Point"}
}