{
  "type": "Feature",
  "properties": {
    "addr:full":"118 Winchester Way Shamong NJ 08088",
    "addr:housenumber":"118",
    "addr:postcode":"08088",
    "addr:street":"Winchester Way",
    "iso:country":"US",
    "sg:address":"118 Winchester Way",
    "sg:city":"Shamong",
    "sg:classifiers":[
        {
            "category":"Wholesale",
            "subcategory":"Machinery & Supplies",
            "type":"Manufacturing & Wholesale Goods"
        }
    ],
    "sg:phone":"+1 609 268 2648",
    "sg:postcode":"08088",
    "sg:province":"NJ",
    "sg:tags":[
        "machine",
        "tool"
    ],
    "wof:name":"KMT Waterjet Systems",
    "wof:placetype":"venue"
},
  "geometry": {"coordinates":[-74.72367199999999,39.811632],"type":"Point"}
}