{
  "type": "Feature",
  "properties": {
    "addr:full":"727 State Rd Princeton NJ 08540",
    "addr:housenumber":"727",
    "addr:postcode":"08540",
    "addr:street":"State Rd",
    "iso:country":"US",
    "sg:address":"727 State Rd",
    "sg:city":"Princeton",
    "sg:classifiers":[
        {
            "category":"Health Services",
            "subcategory":"Doctor",
            "type":"Services"
        }
    ],
    "sg:phone":"+1 609 921 6410",
    "sg:postcode":"08540",
    "sg:province":"NJ",
    "sg:tags":[
        "medical"
    ],
    "wof:name":"Montgmery Intrnal Mdcine Group",
    "wof:placetype":"venue"
},
  "geometry": {"coordinates":[-74.65952799999999,40.384802],"type":"Point"}
}