{
  "type": "Feature",
  "properties": {
    "iso:country":"US",
    "sg:address":"329 US Hwy 46",
    "sg:city":"Parsippany",
    "sg:classifiers":[
        {
            "category":"Home & Garden",
            "subcategory":"Building Materials",
            "type":"Retail Goods"
        }
    ],
    "sg:phone":"+1 973 244 1544",
    "sg:postcode":"07054",
    "sg:province":"NJ",
    "sg:tags":[
        "windows",
        "thermal",
        "installation",
        "vinyl",
        "replacement"
    ],
    "wof:name":"Window Clinic Inc",
    "wof:placetype":"venue"
},
  "geometry": {"coordinates":[-74.35386800000001,40.858068],"type":"Point"}
}