{
  "type": "Feature",
  "properties": {
    "addr:full":"468 Hurffville Crosskeys Rd Sewell NJ 08080",
    "addr:housenumber":"468",
    "addr:postcode":"08080",
    "addr:street":"Hurffville Crosskeys Rd",
    "iso:country":"US",
    "sg:address":"468 Hurffville Crosskeys Rd",
    "sg:city":"Sewell",
    "sg:classifiers":[
        {
            "category":"Health Services",
            "subcategory":"Doctor",
            "type":"Services"
        }
    ],
    "sg:phone":"+1   ",
    "sg:postcode":"08080",
    "sg:province":"NJ",
    "sg:tags":[
        "osteopathic"
    ],
    "wof:name":"Levin Neil Do",
    "wof:placetype":"venue"
},
  "geometry": {"coordinates":[-75.071522,39.737273],"type":"Point"}
}