{
  "type": "Feature",
  "properties": {
    "addr:full":"19 Skyline Dr Warren NJ 07059",
    "addr:housenumber":"19",
    "addr:postcode":"07059",
    "addr:street":"Skyline Dr",
    "iso:country":"US",
    "sg:address":"19 Skyline Dr",
    "sg:city":"Warren",
    "sg:classifiers":[
        {
            "category":"Real Estate",
            "subcategory":"Real Estate Agent",
            "type":"Services"
        }
    ],
    "sg:phone":"+1   ",
    "sg:postcode":"07059",
    "sg:province":"NJ",
    "wof:name":"Skyline Realty Assoc A NJ Ltd",
    "wof:placetype":"venue"
},
  "geometry": {"coordinates":[-74.550752,40.629784],"type":"Point"}
}