{
  "type": "Feature",
  "properties": {
    "iso:country":"US",
    "sg:address":"326 Penn St",
    "sg:city":"Camden",
    "sg:classifiers":[
        {
            "category":"Shopping",
            "subcategory":"Books",
            "type":"Retail Goods"
        }
    ],
    "sg:phone":"+1   ",
    "sg:postcode":"08102",
    "sg:province":"NJ",
    "wof:name":"Follett Store 561",
    "wof:placetype":"venue"
},
  "geometry": {"coordinates":[-75.124297,39.948669],"type":"Point"}
}