{
  "type": "Feature",
  "properties": {
    "addr:full":"51 Upper Montclair Plz Montclair NJ 07043",
    "addr:housenumber":"51",
    "addr:postcode":"07043",
    "addr:street":"Upper;Plz",
    "iso:country":"US",
    "sg:address":"51 Upper Montclair Plz",
    "sg:city":"Montclair",
    "sg:classifiers":[
        {
            "category":"Health Services",
            "subcategory":"Health Practitioner",
            "type":"Services"
        }
    ],
    "sg:phone":"+1   ",
    "sg:postcode":"07043",
    "sg:province":"NJ",
    "wof:name":"Porter Carol Ed D",
    "wof:placetype":"venue"
},
  "geometry": {"coordinates":[-74.20891399999999,40.839641],"type":"Point"}
}