{
  "type": "Feature",
  "properties": {
    "addr:full":"613 Newark Pompton Tpke Pompton Plains NJ 07444",
    "addr:housenumber":"613",
    "addr:postcode":"07444",
    "addr:street":"Newark Pompton Tpke",
    "iso:country":"US",
    "sg:address":"613 Newark Pompton Tpke",
    "sg:city":"Pompton Plains",
    "sg:classifiers":[
        {
            "category":"Food & Beverages",
            "subcategory":"Liquor & Beverages",
            "type":"Retail Goods"
        }
    ],
    "sg:phone":"+1 973 835 5321",
    "sg:postcode":"07444",
    "sg:province":"NJ",
    "sg:tags":[
        "beer",
        "spirit",
        "wine"
    ],
    "wof:name":"Richards Wines & Liquors",
    "wof:placetype":"venue"
},
  "geometry": {"coordinates":[-74.296097,40.968601],"type":"Point"}
}