{
  "type": "Feature",
  "properties": {
    "iso:country":"US",
    "sg:address":"10 Wellington Ct",
    "sg:city":"Medford",
    "sg:classifiers":[
        {
            "category":"Building & Trades",
            "subcategory":"Plumbing",
            "type":"Services"
        }
    ],
    "sg:phone":"+1 609 654 4801",
    "sg:postcode":"08055",
    "sg:province":"NJ",
    "sg:tags":[
        "air",
        "heating",
        "conditioning",
        "contractor"
    ],
    "wof:name":"Welsh Holdings LLC",
    "wof:placetype":"venue"
},
  "geometry": {"coordinates":[-74.831718,39.850312],"type":"Point"}
}