{
  "type": "Feature",
  "properties": {
    "iso:country":"US",
    "sg:address":"25 Westfield Ave",
    "sg:city":"Elizabeth",
    "sg:classifiers":[
        {
            "category":"Restaurant",
            "type":"Food & Drink"
        }
    ],
    "sg:phone":"+1   ",
    "sg:postcode":"07208",
    "sg:province":"NJ",
    "sg:tags":[
        "eating"
    ],
    "wof:name":"Francescos Pizzeria",
    "wof:placetype":"venue"
},
  "geometry": {"coordinates":[-74.216539,40.669177],"type":"Point"}
}