{
  "type": "Feature",
  "properties": {
    "iso:country":"US",
    "sg:address":"25 Rockaway Ave",
    "sg:city":"Oakland",
    "sg:classifiers":[
        {
            "category":"Building & Trades",
            "subcategory":"Construction",
            "type":"Services"
        }
    ],
    "sg:phone":"+1 201 337 2187",
    "sg:postcode":"07436",
    "sg:province":"NJ",
    "sg:tags":[
        "hanging",
        "contractor"
    ],
    "wof:name":"Wilson Home Improvements",
    "wof:placetype":"venue"
},
  "geometry": {"coordinates":[-74.239034,41.032796],"type":"Point"}
}