{
  "type": "Feature",
  "properties": {
    "iso:country":"US",
    "sg:address":"25 Ash St",
    "sg:city":"Basking Ridge",
    "sg:classifiers":[
        {
            "category":"Building & Trades",
            "subcategory":"Construction",
            "type":"Services"
        }
    ],
    "sg:phone":"+1 908 221 1910",
    "sg:postcode":"07920",
    "sg:province":"NJ",
    "sg:tags":[
        "industrial"
    ],
    "wof:name":"Industrial Installations",
    "wof:placetype":"venue"
},
  "geometry": {"coordinates":[-74.560203,40.703272],"type":"Point"}
}