{
  "type": "Feature",
  "properties": {
    "addr:full":"37 Passaic St Garfield NJ 07026",
    "addr:housenumber":"37",
    "addr:postcode":"07026",
    "addr:street":"Passaic St",
    "iso:country":"US",
    "sg:address":"37 Passaic St",
    "sg:city":"Garfield",
    "sg:classifiers":[
        {
            "category":"Shopping",
            "subcategory":"Music",
            "type":"Retail Goods"
        }
    ],
    "sg:phone":"+1 973 473 3912",
    "sg:postcode":"07026",
    "sg:province":"NJ",
    "sg:tags":[
        "dvd's"
    ],
    "sg:website":"www.djalski.com",
    "wof:name":"Music Universe",
    "wof:placetype":"venue"
},
  "geometry": {"coordinates":[-74.108115,40.865803],"type":"Point"}
}