{
  "type": "Feature",
  "properties": {
    "addr:full":"2801 Arctic Ave Atlantic City NJ 08401",
    "addr:housenumber":"2801",
    "addr:postcode":"08401",
    "addr:street":"Arctic Ave",
    "iso:country":"US",
    "sg:address":"2801 Arctic Ave",
    "sg:city":"Atlantic City",
    "sg:classifiers":[
        {
            "category":"Bars & Pubs",
            "type":"Food & Drink"
        },
        {
            "category":"Restaurant",
            "type":"Food & Drink"
        }
    ],
    "sg:phone":"+1 609 347 9119",
    "sg:postcode":"08401",
    "sg:province":"NJ",
    "sg:tags":[
        "vietnamese"
    ],
    "wof:name":"Little Saigon Restaurant",
    "wof:placetype":"venue"
},
  "geometry": {"coordinates":[-74.447287,39.356299],"type":"Point"}
}