{
  "type": "Feature",
  "properties": {
    "addr:full":"926 Haddon Ave Collingswood NJ 08108",
    "addr:housenumber":"926",
    "addr:postcode":"08108",
    "addr:street":"Haddon Ave",
    "iso:country":"US",
    "sg:address":"926 Haddon Ave",
    "sg:city":"Collingswood",
    "sg:classifiers":[
        {
            "category":"Banks & Credit Unions",
            "subcategory":"Investment Brokerage",
            "type":"Services"
        },
        {
            "category":"Insurance",
            "subcategory":"Hazard Insurance",
            "type":"Services"
        }
    ],
    "sg:phone":"+1 856 858 8445",
    "sg:postcode":"08108",
    "sg:province":"NJ",
    "sg:tags":[
        "agent",
        "resume"
    ],
    "sg:website":"http://www.edtobinagency.com",
    "wof:name":"Tobin, Ed & Co",
    "wof:placetype":"venue"
},
  "geometry": {"coordinates":[-75.06272300000001,39.914509],"type":"Point"}
}