{
  "type": "Feature",
  "properties": {
    "addr:full":"1280 Springfield Ave Irvington NJ 07111",
    "addr:housenumber":"1280",
    "addr:postcode":"07111",
    "addr:street":"Springfield Ave",
    "iso:country":"US",
    "sg:address":"1280 Springfield Ave",
    "sg:city":"Irvington",
    "sg:classifiers":[
        {
            "category":"Restaurant",
            "type":"Food & Drink"
        }
    ],
    "sg:phone":"+1   ",
    "sg:postcode":"07111",
    "sg:province":"NJ",
    "sg:tags":[
        "eating"
    ],
    "wof:name":"Big Joes Pizzeria Seafood Rest",
    "wof:placetype":"venue"
},
  "geometry": {"coordinates":[-74.242628,40.724548],"type":"Point"}
}