{
  "type": "Feature",
  "properties": {
    "addr:full":"426 N Lake Dr Lakewood NJ 08701",
    "addr:housenumber":"426",
    "addr:postcode":"08701",
    "addr:street":"N Lake Dr",
    "iso:country":"US",
    "sg:address":"426 N Lake Dr",
    "sg:city":"Lakewood",
    "sg:classifiers":[
        {
            "category":"Professional",
            "subcategory":"Management & Consulting",
            "type":"Services"
        }
    ],
    "sg:phone":"+1 732 730 2340",
    "sg:postcode":"08701",
    "sg:province":"NJ",
    "wof:name":"MSL Management & Dev Corp",
    "wof:placetype":"venue"
},
  "geometry": {"coordinates":[-74.21821,40.08996],"type":"Point"}
}