{
  "type": "Feature",
  "properties": {
    "iso:country":"US",
    "sg:address":"416 Bloomfield Ave",
    "sg:city":"Montclair",
    "sg:classifiers":[
        {
            "category":"Shopping",
            "subcategory":"Used Merchandise",
            "type":"Retail Goods"
        }
    ],
    "sg:phone":"+1 973 509 0990",
    "sg:postcode":"07042",
    "sg:province":"NJ",
    "sg:tags":[
        "antique"
    ],
    "wof:name":"Little Cricket Antiques",
    "wof:placetype":"venue"
},
  "geometry": {"coordinates":[-74.216499,40.813],"type":"Point"}
}