{
  "type": "Feature",
  "properties": {
    "addr:full":"27 Green Dr East Hanover NJ 07936",
    "addr:housenumber":"27",
    "addr:postcode":"07936",
    "addr:street":"Green Dr",
    "iso:country":"US",
    "sg:address":"27 Green Dr",
    "sg:city":"East Hanover",
    "sg:classifiers":[
        {
            "category":"Education",
            "subcategory":"School",
            "type":"Public Place"
        }
    ],
    "sg:phone":"+1   ",
    "sg:postcode":"07936",
    "sg:province":"NJ",
    "sg:tags":[
        "executive"
    ],
    "wof:name":"Frank J Smith Primary School",
    "wof:placetype":"venue"
},
  "geometry": {"coordinates":[-74.34843499999999,40.815265],"type":"Point"}
}