{
  "type": "Feature",
  "properties": {
    "iso:country":"US",
    "sg:address":"1938 State Rte 35",
    "sg:city":"South Amboy",
    "sg:classifiers":[
        {
            "category":"Autos & Motor Vehicles",
            "subcategory":"Auto Supplies",
            "type":"Retail Goods"
        }
    ],
    "sg:phone":"+1 732 721 7445",
    "sg:postcode":"08879",
    "sg:province":"NJ",
    "sg:tags":[
        "bo"
    ],
    "wof:name":"Waynes Auto & Speed Shop",
    "wof:placetype":"venue"
},
  "geometry": {"coordinates":[-74.27551699999999,40.464455],"type":"Point"}
}