{
  "type": "Feature",
  "properties": {
    "addr:full":"22 Stevenson Pl Kearny NJ 07032",
    "addr:housenumber":"22",
    "addr:postcode":"07032",
    "addr:street":"Stevenson Pl",
    "iso:country":"US",
    "sg:address":"22 Stevenson Pl",
    "sg:city":"Kearny",
    "sg:classifiers":[
        {
            "category":"Building & Trades",
            "subcategory":"Construction",
            "type":"Services"
        }
    ],
    "sg:phone":"+1 201 246 0045",
    "sg:postcode":"07032",
    "sg:province":"NJ",
    "sg:tags":[
        "masonry",
        "contractor"
    ],
    "wof:name":"Riva Concrete Inc",
    "wof:placetype":"venue"
},
  "geometry": {"coordinates":[-74.152275,40.772171],"type":"Point"}
}