{
  "type": "Feature",
  "properties": {
    "addr:full":"629 S Warrington Ave Cinnaminson NJ 08077",
    "addr:housenumber":"629",
    "addr:postcode":"08077",
    "addr:street":"S Warrington Ave",
    "iso:country":"US",
    "sg:address":"629 S Warrington Ave",
    "sg:city":"Cinnaminson",
    "sg:classifiers":[
        {
            "category":"Manufacturing",
            "subcategory":"Tools & Machinery",
            "type":"Manufacturing & Wholesale Goods"
        },
        {
            "category":"Wholesale",
            "subcategory":"Auto Parts",
            "type":"Manufacturing & Wholesale Goods"
        }
    ],
    "sg:phone":"+1 856 829 4721",
    "sg:postcode":"08077",
    "sg:province":"NJ",
    "sg:tags":[
        "repair",
        "industrial",
        "mfg",
        "general",
        "cutting",
        "cam"
    ],
    "sg:website":"www.trirtool.com",
    "wof:name":"Tri R Tool Inc",
    "wof:placetype":"venue"
},
  "geometry": {"coordinates":[-75.001655,40.014334],"type":"Point"}
}