{
  "type": "Feature",
  "properties": {
    "addr:full":"400 Faraday Ave Ste 1 Lakewood NJ 08701",
    "addr:housenumber":"400",
    "addr:postcode":"08701",
    "addr:street":"Faraday Ave Ste 1",
    "iso:country":"US",
    "sg:address":"400 Faraday Ave Ste 1",
    "sg:city":"Lakewood",
    "sg:classifiers":[
        {
            "category":"Retail",
            "subcategory":"Auto Repair",
            "type":"Services"
        }
    ],
    "sg:phone":"+1 732 367 9090",
    "sg:postcode":"08701",
    "sg:province":"NJ",
    "wof:name":"Exclusive Auto Service",
    "wof:placetype":"venue"
},
  "geometry": {"coordinates":[-74.248204,40.070795],"type":"Point"}
}