{
  "type": "Feature",
  "properties": {
    "addr:full":"3153 State Rte 35 Hazlet NJ 07730",
    "addr:housenumber":"3153",
    "addr:postcode":"07730",
    "addr:street":"State Rte 35",
    "iso:country":"US",
    "sg:address":"3153 State Rte 35",
    "sg:city":"Hazlet",
    "sg:classifiers":[
        {
            "category":"Restaurant",
            "type":"Food & Drink"
        }
    ],
    "sg:phone":"+1 732 264 3777",
    "sg:postcode":"07730",
    "sg:province":"NJ",
    "wof:name":"Yesterday's Restaurant",
    "wof:placetype":"venue"
},
  "geometry": {"coordinates":[-74.184545,40.420971],"type":"Point"}
}