{
  "type": "Feature",
  "properties": {
    "iso:country":"US",
    "sg:address":"911 E County Line Rd",
    "sg:city":"Lakewood",
    "sg:classifiers":[
        {
            "category":"Real Estate",
            "subcategory":"Real Estate Agent",
            "type":"Services"
        },
        {
            "category":"Professional",
            "subcategory":"Management & Consulting",
            "type":"Services"
        }
    ],
    "sg:phone":"+1 732 942 6100",
    "sg:postcode":"08701",
    "sg:province":"NJ",
    "sg:tags":[
        "property"
    ],
    "wof:name":"Jersey Central Management Corp",
    "wof:placetype":"venue"
},
  "geometry": {"coordinates":[-74.2011,40.104995],"type":"Point"}
}