{
  "type": "Feature",
  "properties": {
    "iso:country":"US",
    "sg:address":"115 Franklin Tpke",
    "sg:city":"Mahwah",
    "sg:classifiers":[
        {
            "category":"Food & Beverages",
            "subcategory":"Bakery",
            "type":"Retail Goods"
        }
    ],
    "sg:phone":"+1 201 529 5559",
    "sg:postcode":"07430",
    "sg:province":"NJ",
    "sg:tags":[
        "shop",
        "doughnut",
        "coffee"
    ],
    "wof:name":"Dunkin' Donuts",
    "wof:placetype":"venue"
},
  "geometry": {"coordinates":[-74.146354,41.097737],"type":"Point"}
}