{
  "type": "Feature",
  "properties": {
    "iso:country":"US",
    "sg:address":"25 Lindsley Dr Ste 105",
    "sg:city":"Morristown",
    "sg:classifiers":[
        {
            "category":"Professional",
            "subcategory":"Lawyer & Legal Services",
            "type":"Services"
        }
    ],
    "sg:phone":"+1 973 538 3800",
    "sg:postcode":"07960",
    "sg:province":"NJ",
    "wof:name":"Collins Thomas F Jr Attorney",
    "wof:placetype":"venue"
},
  "geometry": {"coordinates":[-74.460998,40.800345],"type":"Point"}
}