{
  "type": "Feature",
  "properties": {
    "addr:full":"170 Main St Fort Lee NJ 07024",
    "addr:housenumber":"170",
    "addr:postcode":"07024",
    "addr:street":"Main St",
    "iso:country":"US",
    "sg:address":"170 Main St",
    "sg:city":"Fort Lee",
    "sg:classifiers":[
        {
            "category":"Shopping",
            "subcategory":"Beauty & Cosmetics",
            "type":"Retail Goods"
        }
    ],
    "sg:phone":"+1   ",
    "sg:postcode":"07024",
    "sg:province":"NJ",
    "sg:tags":[
        "merchandise"
    ],
    "wof:name":"Tinas Nails",
    "wof:placetype":"venue"
},
  "geometry": {"coordinates":[-73.969701,40.851043],"type":"Point"}
}