{
  "type": "Feature",
  "properties": {
    "addr:full":"230 Broadway Long Branch NJ 07740",
    "addr:housenumber":"230",
    "addr:postcode":"07740",
    "addr:street":"Broadway",
    "iso:country":"US",
    "sg:address":"230 Broadway",
    "sg:city":"Long Branch",
    "sg:classifiers":[
        {
            "category":"Restaurant",
            "type":"Food & Drink"
        }
    ],
    "sg:menulink":"http://www.allmenus.com/nj/long-branch/254013-crown-fried-chicken/menu/",
    "sg:phone":"+1 732 222 6233",
    "sg:postcode":"07740",
    "sg:province":"NJ",
    "sg:tags":[
        "burger",
        "seafood",
        "sandwich",
        "american",
        "chicken"
    ],
    "wof:name":"Crown Fried Chicken",
    "wof:placetype":"venue"
},
  "geometry": {"coordinates":[-73.988362,40.30433],"type":"Point"}
}