{
  "type": "Feature",
  "properties": {
    "addr:full":"5200 State Rte 42 Blackwood NJ 08012",
    "addr:housenumber":"5200",
    "addr:postcode":"08012",
    "addr:street":"State Rte 42",
    "iso:country":"US",
    "sg:address":"5200 State Rte 42",
    "sg:city":"Blackwood",
    "sg:classifiers":[
        {
            "category":"Shopping",
            "subcategory":"Discount & Variety Stores",
            "type":"Retail Goods"
        }
    ],
    "sg:phone":"+1   ",
    "sg:postcode":"08012",
    "sg:province":"NJ",
    "wof:name":"Dollar General",
    "wof:placetype":"venue"
},
  "geometry": {"coordinates":[-75.04616,39.752601],"type":"Point"}
}