{
  "type": "Feature",
  "properties": {
    "addr:full":"94 Ridge Rd Branchville NJ 07826",
    "addr:housenumber":"94",
    "addr:postcode":"07826",
    "addr:street":"Ridge Rd",
    "iso:country":"US",
    "sg:address":"94 Ridge Rd",
    "sg:city":"Branchville",
    "sg:classifiers":[
        {
            "category":"Wholesale",
            "subcategory":"Non-durable Goods",
            "type":"Manufacturing & Wholesale Goods"
        }
    ],
    "sg:phone":"+1 973 948 4876",
    "sg:postcode":"07826",
    "sg:province":"NJ",
    "wof:name":"V&P Distributors Liability",
    "wof:placetype":"venue"
},
  "geometry": {"coordinates":[-74.75322300000001,41.174932],"type":"Point"}
}