{
  "type": "Feature",
  "properties": {
    "iso:country":"US",
    "sg:address":"6006 US Hwy 130",
    "sg:city":"Delran",
    "sg:classifiers":[
        {
            "category":"Restaurant",
            "type":"Food & Drink"
        }
    ],
    "sg:phone":"+1 856 829 3653",
    "sg:postcode":"08075",
    "sg:province":"NJ",
    "wof:name":"Pizza Hut",
    "wof:placetype":"venue"
},
  "geometry": {"coordinates":[-74.94628899999999,40.019713],"type":"Point"}
}