{
  "type": "Feature",
  "properties": {
    "iso:country":"US",
    "sg:address":"18 N Hartshorne Rd",
    "sg:city":"Highlands",
    "sg:classifiers":[
        {
            "category":"Organizations",
            "subcategory":"Community Association",
            "type":"Services"
        }
    ],
    "sg:phone":"+1 732 872 0111",
    "sg:postcode":"07732",
    "sg:province":"NJ",
    "sg:tags":[
        "environmental",
        "org"
    ],
    "wof:name":"Clean Ocean Action",
    "wof:placetype":"venue"
},
  "geometry": {"coordinates":[-74.020195,40.397709],"type":"Point"}
}