{
  "type": "Feature",
  "properties": {
    "addr:full":"101 Monmouth St Red Bank NJ 07701",
    "addr:housenumber":"101",
    "addr:postcode":"07701",
    "addr:street":"Monmouth St",
    "iso:country":"US",
    "sg:address":"101 Monmouth St",
    "sg:city":"Red Bank",
    "sg:classifiers":[
        {
            "category":"Professional",
            "type":"Services"
        }
    ],
    "sg:phone":"+1 732 842 5810",
    "sg:postcode":"07701",
    "sg:province":"NJ",
    "sg:tags":[
        "establishment"
    ],
    "wof:name":"Pezzutti Studio",
    "wof:placetype":"venue"
},
  "geometry": {"coordinates":[-74.07034299999999,40.349142],"type":"Point"}
}