{
  "type": "Feature",
  "properties": {
    "iso:country":"US",
    "sg:address":"515 Valley Brook Ave",
    "sg:city":"Lyndhurst",
    "sg:classifiers":[
        {
            "category":"Professional",
            "subcategory":"Computer Services",
            "type":"Services"
        }
    ],
    "sg:phone":"+1 201 935 5090",
    "sg:postcode":"07071",
    "sg:province":"NJ",
    "sg:tags":[
        "programing",
        "custom"
    ],
    "wof:name":"Techno Byte Interactive",
    "wof:placetype":"venue"
},
  "geometry": {"coordinates":[-74.12118,40.810249],"type":"Point"}
}