{
  "type": "Feature",
  "properties": {
    "iso:country":"US",
    "sg:address":"29 N Day St",
    "sg:city":"Orange",
    "sg:classifiers":[
        {
            "category":"Government",
            "subcategory":"Office",
            "type":"Public Place"
        }
    ],
    "sg:phone":"+1 973 266 4018",
    "sg:postcode":"07050",
    "sg:province":"NJ",
    "sg:tags":[
        "city",
        "taxation"
    ],
    "wof:name":"Orange Tax Collector's Ofc",
    "wof:placetype":"venue"
},
  "geometry": {"coordinates":[-74.229382,40.772598],"type":"Point"}
}