{
  "type": "Feature",
  "properties": {
    "addr:full":"1405 Broad St Bloomfield NJ 07003",
    "addr:housenumber":"1405",
    "addr:postcode":"07003",
    "addr:street":"Broad St",
    "iso:country":"US",
    "sg:address":"1405 Broad St",
    "sg:city":"Bloomfield",
    "sg:classifiers":[
        {
            "category":"Personal",
            "subcategory":"Day Spa",
            "type":"Services"
        }
    ],
    "sg:phone":"+1 973 771 1405",
    "sg:postcode":"07003",
    "sg:province":"NJ",
    "sg:website":"www.SerenitySalonSpa.net",
    "wof:name":"Serenity Salon and Spa",
    "wof:placetype":"venue"
},
  "geometry": {"coordinates":[-74.18453599999999,40.837746],"type":"Point"}
}