{
  "type": "Feature",
  "properties": {
    "iso:country":"US",
    "sg:address":"31 Clement St",
    "sg:city":"Nutley",
    "sg:classifiers":[
        {
            "category":"Manufacturing",
            "subcategory":"Retail Goods",
            "type":"Manufacturing & Wholesale Goods"
        }
    ],
    "sg:phone":"+1 973 239 0129",
    "sg:postcode":"07110",
    "sg:province":"NJ",
    "sg:tags":[
        "product",
        "mfg"
    ],
    "wof:name":"Grove Precision Mfg",
    "wof:placetype":"venue"
},
  "geometry": {"coordinates":[-74.17524,40.820226],"type":"Point"}
}