{
  "type": "Feature",
  "properties": {
    "iso:country":"US",
    "sg:address":"100 Newark Ave",
    "sg:city":"Jersey City",
    "sg:classifiers":[
        {
            "category":"Sports & Exercise",
            "subcategory":"Gym",
            "type":"Entertainment"
        }
    ],
    "sg:phone":"+1 201 332 2639",
    "sg:postcode":"07302",
    "sg:province":"NJ",
    "sg:tags":[
        "gymnasium"
    ],
    "wof:name":"Body Fitness",
    "wof:placetype":"venue"
},
  "geometry": {"coordinates":[-74.04252099999999,40.71976],"type":"Point"}
}