{
  "type": "Feature",
  "properties": {
    "addr:full":"3 Stark Pl Edison NJ 08820",
    "addr:housenumber":"3",
    "addr:postcode":"08820",
    "addr:street":"Stark Pl",
    "iso:country":"US",
    "sg:address":"3 Stark Pl",
    "sg:city":"Edison",
    "sg:classifiers":[
        {
            "category":"Building & Trades",
            "subcategory":"Construction",
            "type":"Services"
        }
    ],
    "sg:phone":"+1 732 548 5435",
    "sg:postcode":"08820",
    "sg:province":"NJ",
    "sg:tags":[
        "roofing",
        "contractor"
    ],
    "wof:name":"John Clemens Sons Roofg Siding",
    "wof:placetype":"venue"
},
  "geometry": {"coordinates":[-74.350138,40.566975],"type":"Point"}
}