{
  "type": "Feature",
  "properties": {
    "iso:country":"US",
    "sg:address":"110 Broad Ave",
    "sg:city":"Palisades Park",
    "sg:classifiers":[
        {
            "category":"Restaurant",
            "type":"Food & Drink"
        }
    ],
    "sg:phone":"+1 201 943 6666",
    "sg:postcode":"07650",
    "sg:province":"NJ",
    "sg:tags":[
        "cafe"
    ],
    "wof:name":"Cafe",
    "wof:placetype":"venue"
},
  "geometry": {"coordinates":[-74.000428,40.844056],"type":"Point"}
}