{
  "type": "Feature",
  "properties": {
    "addr:full":"4 Alta Ct Unit 1 Vernon NJ 07462",
    "addr:housenumber":"4;1",
    "addr:postcode":"07462",
    "addr:street":"Alta Ct Unit",
    "iso:country":"US",
    "sg:address":"4 Alta Ct Unit 1",
    "sg:city":"Vernon",
    "sg:classifiers":[
        {
            "category":"Manufacturing",
            "subcategory":"Glass & Minerals",
            "type":"Manufacturing & Wholesale Goods"
        }
    ],
    "sg:phone":"+1 973 827 4477",
    "sg:postcode":"07462",
    "sg:province":"NJ",
    "sg:tags":[
        "shape",
        "circle",
        "special"
    ],
    "wof:name":"Aa Ace Autoglass",
    "wof:placetype":"venue"
},
  "geometry": {"coordinates":[-74.511008,41.187269],"type":"Point"}
}