{
  "type": "Feature",
  "properties": {
    "iso:country":"US",
    "sg:address":"185 Wilson Ave",
    "sg:city":"Newark",
    "sg:classifiers":[
        {
            "category":"Autos & Motor Vehicles",
            "subcategory":"Fuel & Gas Station",
            "type":"Retail Goods"
        }
    ],
    "sg:phone":"+1   ",
    "sg:postcode":"07105",
    "sg:province":"NJ",
    "sg:tags":[
        "station",
        "gasoline",
        "dealer",
        "oil"
    ],
    "wof:name":"Texaco",
    "wof:placetype":"venue"
},
  "geometry": {"coordinates":[-74.14972400000001,40.722015],"type":"Point"}
}