{
  "type": "Feature",
  "properties": {
    "iso:country":"US",
    "sg:address":"153 Potomac Ave",
    "sg:city":"Paterson",
    "sg:classifiers":[
        {
            "category":"Health Services",
            "subcategory":"Doctor",
            "type":"Services"
        }
    ],
    "sg:phone":"+1 973 345 4808",
    "sg:postcode":"07503",
    "sg:province":"NJ",
    "sg:tags":[
        "medical"
    ],
    "wof:name":"Walid Abu Jmaian",
    "wof:placetype":"venue"
},
  "geometry": {"coordinates":[-74.14685299999999,40.891035],"type":"Point"}
}