{
  "type": "Feature",
  "properties": {
    "iso:country":"US",
    "sg:address":"125 E Ridgewood Ave",
    "sg:city":"Ridgewood",
    "sg:classifiers":[
        {
            "category":"Home & Garden",
            "subcategory":"Furniture",
            "type":"Retail Goods"
        }
    ],
    "sg:phone":"+1   ",
    "sg:postcode":"07450",
    "sg:province":"NJ",
    "wof:name":"Classic Sofa",
    "wof:placetype":"venue"
},
  "geometry": {"coordinates":[-74.118049,40.979524],"type":"Point"}
}