{
  "type": "Feature",
  "properties": {
    "addr:full":"11 Schuyler Ave North Arlington NJ 07031",
    "addr:housenumber":"11",
    "addr:postcode":"07031",
    "addr:street":"Schuyler Ave North",
    "iso:country":"US",
    "sg:address":"11 Schuyler Ave",
    "sg:city":"North Arlington",
    "sg:classifiers":[
        {
            "category":"Building & Trades",
            "subcategory":"Locksmith",
            "type":"Services"
        }
    ],
    "sg:phone":"+1 201 428 2125",
    "sg:postcode":"07031",
    "sg:province":"NJ",
    "sg:tags":[
        "key"
    ],
    "wof:name":"0 & 0 & 0 1 Emergency A 24 Hour A Loc",
    "wof:placetype":"venue"
},
  "geometry": {"coordinates":[-74.130208,40.778011],"type":"Point"}
}