{
  "type": "Feature",
  "properties": {
    "addr:full":"3 Winona Trl Lake Hopatcong NJ 07849",
    "addr:housenumber":"3",
    "addr:postcode":"07849",
    "addr:street":"Winona Trl",
    "iso:country":"US",
    "sg:address":"3 Winona Trl",
    "sg:city":"Lake Hopatcong",
    "sg:classifiers":[
        {
            "category":"Professional",
            "subcategory":"Computer Services",
            "type":"Services"
        }
    ],
    "sg:phone":"+1   ",
    "sg:postcode":"07849",
    "sg:province":"NJ",
    "sg:tags":[
        "datum"
    ],
    "wof:name":"All-Med Transcription Services",
    "wof:placetype":"venue"
},
  "geometry": {"coordinates":[-74.61063799999999,40.98593],"type":"Point"}
}