{
  "type": "Feature",
  "properties": {
    "addr:full":"9 Fair Lawn Ave Fair Lawn NJ 07410",
    "addr:housenumber":"9",
    "addr:postcode":"07410",
    "addr:street":"Fair Lawn Ave",
    "iso:country":"US",
    "sg:address":"9 Fair Lawn Ave",
    "sg:city":"Fair Lawn",
    "sg:classifiers":[
        {
            "category":"Restaurant",
            "type":"Food & Drink"
        }
    ],
    "sg:phone":"+1 201 797 6767",
    "sg:postcode":"07410",
    "sg:province":"NJ",
    "sg:tags":[
        "caterer"
    ],
    "wof:name":"Davia",
    "wof:placetype":"venue"
},
  "geometry": {"coordinates":[-74.11301899999999,40.941271],"type":"Point"}
}