{
  "type": "Feature",
  "properties": {
    "iso:country":"US",
    "sg:address":"161 State Rte 27",
    "sg:city":"Edison",
    "sg:classifiers":[
        {
            "category":"Professional",
            "subcategory":"Detective & Security Services",
            "type":"Services"
        }
    ],
    "sg:phone":"+1 732 321 0300",
    "sg:postcode":"08820",
    "sg:province":"NJ",
    "sg:tags":[
        "system"
    ],
    "wof:name":"Alltek Security Syst Grp Inc",
    "wof:placetype":"venue"
},
  "geometry": {"coordinates":[-74.33658699999999,40.561635],"type":"Point"}
}