{
  "type": "Feature",
  "properties": {
    "iso:country":"US",
    "sg:address":"345 Bloomfield Ave",
    "sg:city":"Montclair",
    "sg:classifiers":[
        {
            "category":"Personal",
            "subcategory":"Beauty Salon",
            "type":"Services"
        }
    ],
    "sg:phone":"+1   ",
    "sg:postcode":"07042",
    "sg:province":"NJ",
    "sg:tags":[
        "shop"
    ],
    "wof:name":"U Got The Look Hair Studio",
    "wof:placetype":"venue"
},
  "geometry": {"coordinates":[-74.21538700000001,40.812183],"type":"Point"}
}