{
  "type": "Feature",
  "properties": {
    "addr:full":"1528 N Broad St Hillside NJ 07205",
    "addr:housenumber":"1528",
    "addr:postcode":"07205",
    "addr:street":"N Broad St",
    "iso:country":"US",
    "sg:address":"1528 N Broad St",
    "sg:city":"Hillside",
    "sg:classifiers":[
        {
            "category":"Health Services",
            "subcategory":"Doctor",
            "type":"Services"
        }
    ],
    "sg:phone":"+1 973 923 0811",
    "sg:postcode":"07205",
    "sg:province":"NJ",
    "sg:tags":[
        "physician",
        "surgeon"
    ],
    "wof:name":"Victor Daibo MD",
    "wof:placetype":"venue"
},
  "geometry": {"coordinates":[-74.213325,40.700674],"type":"Point"}
}