{
  "type": "Feature",
  "properties": {
    "iso:country":"US",
    "sg:address":"155 E Hanover Ave",
    "sg:city":"Morristown",
    "sg:classifiers":[
        {
            "category":"Professional",
            "subcategory":"Management & Consulting",
            "type":"Services"
        }
    ],
    "sg:phone":"+1 973 401 1014",
    "sg:postcode":"07960",
    "sg:province":"NJ",
    "sg:tags":[
        "construction"
    ],
    "wof:name":"M Gordon Construction Co",
    "wof:placetype":"venue"
},
  "geometry": {"coordinates":[-74.47255699999999,40.815014],"type":"Point"}
}