{
  "type": "Feature",
  "properties": {
    "addr:full":"2878 Dune Dr Avalon NJ 08202",
    "addr:housenumber":"2878",
    "addr:postcode":"08202",
    "addr:street":"Dune Dr",
    "iso:country":"US",
    "sg:address":"2878 Dune Dr",
    "sg:city":"Avalon",
    "sg:classifiers":[
        {
            "category":"Restaurant",
            "type":"Food & Drink"
        }
    ],
    "sg:phone":"+1 609 967 8043",
    "sg:postcode":"08202",
    "sg:province":"NJ",
    "wof:name":"Avalon Salad Bar",
    "wof:placetype":"venue"
},
  "geometry": {"coordinates":[-74.72219200000001,39.096675],"type":"Point"}
}