{
  "type": "Feature",
  "properties": {
    "iso:country":"US",
    "sg:address":"514 Greenwood Ave",
    "sg:city":"Trenton",
    "sg:classifiers":[
        {
            "category":"Social Services",
            "subcategory":"Child Care",
            "type":"Services"
        }
    ],
    "sg:phone":"+1 609 396 6066",
    "sg:postcode":"08609",
    "sg:province":"NJ",
    "sg:tags":[
        "day"
    ],
    "wof:name":"Lads & Lassies Land Inc",
    "wof:placetype":"venue"
},
  "geometry": {"coordinates":[-74.74955300000001,40.218296],"type":"Point"}
}