{
  "type": "Feature",
  "properties": {
    "addr:full":"10 Bartlett Ct Roseland NJ 07068",
    "addr:housenumber":"10",
    "addr:postcode":"07068",
    "addr:street":"Bartlett Ct",
    "iso:country":"US",
    "sg:address":"10 Bartlett Ct",
    "sg:city":"Roseland",
    "sg:classifiers":[
        {
            "category":"Professional",
            "type":"Services"
        }
    ],
    "sg:phone":"+1   ",
    "sg:postcode":"07068",
    "sg:province":"NJ",
    "wof:name":"Sanford Rosenburg",
    "wof:placetype":"venue"
},
  "geometry": {"coordinates":[-74.30225900000001,40.82008],"type":"Point"}
}