{
  "type": "Feature",
  "properties": {
    "iso:country":"US",
    "sg:address":"61 Lincoln Hwy",
    "sg:city":"Kearny",
    "sg:classifiers":[
        {
            "category":"Freight",
            "type":"Transportation"
        }
    ],
    "sg:phone":"+1 973 522 1998",
    "sg:postcode":"07032",
    "sg:province":"NJ",
    "sg:tags":[
        "hauling",
        "trucking"
    ],
    "wof:name":"North Atlantic Enterprises",
    "wof:placetype":"venue"
},
  "geometry": {"coordinates":[-74.10942300000001,40.730259],"type":"Point"}
}