{
  "type": "Feature",
  "properties": {
    "iso:country":"US",
    "sg:address":"1326 Central Ave",
    "sg:city":"Glendora",
    "sg:classifiers":[
        {
            "category":"Professional",
            "subcategory":"Lawyer & Legal Services",
            "type":"Services"
        }
    ],
    "sg:phone":"+1 856 939 5511",
    "sg:postcode":"08029",
    "sg:province":"NJ",
    "sg:tags":[
        "firm",
        "attorney",
        "law"
    ],
    "sg:website":"www.masciocchiandappel.com",
    "wof:name":"Masciocchi & Appel Law Offices",
    "wof:placetype":"venue"
},
  "geometry": {"coordinates":[-75.06905500000001,39.843999],"type":"Point"}
}