{
  "type": "Feature",
  "properties": {
    "iso:country":"US",
    "sg:address":"338 Georges Rd",
    "sg:city":"Dayton",
    "sg:classifiers":[
        {
            "category":"Health Services",
            "subcategory":"Doctor",
            "type":"Services"
        }
    ],
    "sg:phone":"+1   ",
    "sg:postcode":"08810",
    "sg:province":"NJ",
    "sg:tags":[
        "dental"
    ],
    "wof:name":"Meade Harvey J DMD",
    "wof:placetype":"venue"
},
  "geometry": {"coordinates":[-74.510828,40.373693],"type":"Point"}
}