{
  "type": "Feature",
  "properties": {
    "addr:full":"1530 Palisade Ave Fort Lee NJ 07024",
    "addr:housenumber":"1530",
    "addr:postcode":"07024",
    "addr:street":"Palisade Ave",
    "iso:country":"US",
    "sg:address":"1530 Palisade Ave",
    "sg:city":"Fort Lee",
    "sg:classifiers":[
        {
            "category":"Building & Trades",
            "subcategory":"Construction",
            "type":"Services"
        }
    ],
    "sg:phone":"+1 201 242 0875",
    "sg:postcode":"07024",
    "sg:province":"NJ",
    "sg:tags":[
        "contractor"
    ],
    "wof:name":"Dreamworks Concept Llc",
    "wof:placetype":"venue"
},
  "geometry": {"coordinates":[-73.969803,40.8479],"type":"Point"}
}