{
  "type": "Feature",
  "properties": {
    "iso:country":"US",
    "sg:address":"80 Locust Ave",
    "sg:city":"Millburn",
    "sg:classifiers":[
        {
            "category":"Health Services",
            "subcategory":"Health Practitioner",
            "type":"Services"
        }
    ],
    "sg:phone":"+1 973 376 0477",
    "sg:postcode":"07041",
    "sg:province":"NJ",
    "sg:tags":[
        "nurse",
        "registry"
    ],
    "wof:name":"L D Barry",
    "wof:placetype":"venue"
},
  "geometry": {"coordinates":[-74.296485,40.71924],"type":"Point"}
}