{
  "type": "Feature",
  "properties": {
    "iso:country":"US",
    "sg:address":"24 Braemar Ave",
    "sg:city":"Blackwood",
    "sg:classifiers":[
        {
            "category":"Professional",
            "subcategory":"Management & Consulting",
            "type":"Services"
        }
    ],
    "sg:phone":"+1 856 275 1905",
    "sg:postcode":"08012",
    "sg:province":"NJ",
    "wof:name":"Strategic Data MGT Solutions",
    "wof:placetype":"venue"
},
  "geometry": {"coordinates":[-75.0471,39.796363],"type":"Point"}
}