{
  "type": "Feature",
  "properties": {
    "iso:country":"US",
    "sg:address":"1020 S Orange Ave",
    "sg:city":"Newark",
    "sg:classifiers":[
        {
            "category":"Restaurant",
            "type":"Food & Drink"
        }
    ],
    "sg:phone":"+1 973 372 8825",
    "sg:postcode":"07106",
    "sg:province":"NJ",
    "wof:name":"Your Oasis Steak & Fish",
    "wof:placetype":"venue"
},
  "geometry": {"coordinates":[-74.23026,40.746347],"type":"Point"}
}