{
  "type": "Feature",
  "properties": {
    "iso:country":"US",
    "sg:address":"62 Newark St",
    "sg:city":"Hoboken",
    "sg:classifiers":[
        {
            "category":"Food & Beverages",
            "subcategory":"Groceries & Convenience Stores",
            "type":"Retail Goods"
        }
    ],
    "sg:phone":"+1 201 420 7100",
    "sg:postcode":"07030",
    "sg:province":"NJ",
    "sg:tags":[
        "deli"
    ],
    "wof:name":"Food 3663",
    "wof:placetype":"venue"
},
  "geometry": {"coordinates":[-74.030547,40.736832],"type":"Point"}
}