{
  "type": "Feature",
  "properties": {
    "addr:full":"1400 Jones Dr Princeton NJ 08540",
    "addr:housenumber":"1400",
    "addr:postcode":"08540",
    "addr:street":"Jones Dr",
    "iso:country":"US",
    "sg:address":"1400 Jones Dr",
    "sg:city":"Princeton",
    "sg:classifiers":[
        {
            "category":"Real Estate",
            "subcategory":"Real Estate Agent",
            "type":"Services"
        }
    ],
    "sg:phone":"+1 732 329 6807",
    "sg:postcode":"08540",
    "sg:province":"NJ",
    "wof:name":"Woodhaven Of South Brunswick",
    "wof:placetype":"venue"
},
  "geometry": {"coordinates":[-74.593631,40.388897],"type":"Point"}
}