{
  "type": "Feature",
  "properties": {
    "addr:full":"1040 Pottersville Rd Gladstone NJ 07934",
    "addr:housenumber":"1040",
    "addr:postcode":"07934",
    "addr:street":"Pottersville Rd",
    "iso:country":"US",
    "sg:address":"1040 Pottersville Rd",
    "sg:city":"Gladstone",
    "sg:classifiers":[
        {
            "category":"Professional",
            "subcategory":"Management & Consulting",
            "type":"Services"
        },
        {
            "category":"Recreation",
            "type":"Entertainment"
        }
    ],
    "sg:phone":"+1 908 781 0617",
    "sg:postcode":"07934",
    "sg:province":"NJ",
    "sg:tags":[
        "club",
        "consultant",
        "private",
        "business",
        "country"
    ],
    "sg:website":"www.hamiltonfarmgolfclub.com",
    "wof:name":"Hamilton Farm Golf Club Inc",
    "wof:placetype":"venue"
},
  "geometry": {"coordinates":[-74.687623,40.718967],"type":"Point"}
}