{
  "type": "Feature",
  "properties": {
    "addr:full":"18 Corsons Tavern Rd Ocean View NJ 08230",
    "addr:housenumber":"18",
    "addr:postcode":"08230",
    "addr:street":"Tavern Rd",
    "iso:country":"US",
    "sg:address":"18 Corsons Tavern Rd",
    "sg:city":"Ocean View",
    "sg:classifiers":[
        {
            "category":"Real Estate",
            "subcategory":"Architect",
            "type":"Services"
        }
    ],
    "sg:phone":"+1 609 624 3423",
    "sg:postcode":"08230",
    "sg:province":"NJ",
    "sg:tags":[
        "architectural"
    ],
    "wof:name":"Knabb Partnership",
    "wof:placetype":"venue"
},
  "geometry": {"coordinates":[-74.71116600000001,39.204521],"type":"Point"}
}