{
  "type": "Feature",
  "properties": {
    "addr:full":"1401 3rd Ave Spring Lake NJ 07762",
    "addr:housenumber":"1401",
    "addr:postcode":"07762",
    "addr:street":"3Rd Ave",
    "iso:country":"US",
    "sg:address":"1401 3rd Ave",
    "sg:city":"Spring Lake",
    "sg:classifiers":[
        {
            "category":"Real Estate",
            "subcategory":"Real Estate Agent",
            "type":"Services"
        }
    ],
    "sg:phone":"+1 732 449 9400",
    "sg:postcode":"07762",
    "sg:province":"NJ",
    "sg:tags":[
        "appraiser"
    ],
    "wof:name":"Mac Gowan Real Estate Agency",
    "wof:placetype":"venue"
},
  "geometry": {"coordinates":[-74.027356,40.155463],"type":"Point"}
}