{
  "type": "Feature",
  "properties": {
    "addr:full":"187 Clayton Aura Rd Glassboro NJ 08028",
    "addr:housenumber":"187",
    "addr:postcode":"08028",
    "addr:street":"Clayton Aura Rd",
    "iso:country":"US",
    "sg:address":"187 Clayton Aura Rd",
    "sg:city":"Glassboro",
    "sg:classifiers":[
        {
            "category":"Professional",
            "subcategory":"Computer Services",
            "type":"Services"
        }
    ],
    "sg:phone":"+1   ",
    "sg:postcode":"08028",
    "sg:province":"NJ",
    "sg:tags":[
        "datum",
        "related"
    ],
    "wof:name":"Disk Works Sj",
    "wof:placetype":"venue"
},
  "geometry": {"coordinates":[-75.119243,39.670325],"type":"Point"}
}