{
  "type": "Feature",
  "properties": {
    "addr:full":"4069 US Hwy 9 Howell NJ 07731",
    "addr:housenumber":"4069",
    "addr:postcode":"07731",
    "addr:street":"Us Hwy 9",
    "iso:country":"US",
    "sg:address":"4069 US Hwy 9",
    "sg:city":"Howell",
    "sg:classifiers":[
        {
            "category":"Food & Beverages",
            "subcategory":"Specialty",
            "type":"Retail Goods"
        }
    ],
    "sg:phone":"+1 732 367 7778",
    "sg:postcode":"07731",
    "sg:province":"NJ",
    "sg:tags":[
        "vitamin"
    ],
    "wof:name":"GNC",
    "wof:placetype":"venue"
},
  "geometry": {"coordinates":[-74.228493,40.15352],"type":"Point"}
}