{
  "type": "Feature",
  "properties": {
    "addr:full":"106 W Franklin Ave Pennington NJ 08534",
    "addr:housenumber":"106",
    "addr:postcode":"08534",
    "addr:street":"W Franklin Ave",
    "iso:country":"US",
    "sg:address":"106 W Franklin Ave",
    "sg:city":"Pennington",
    "sg:classifiers":[
        {
            "category":"Professional",
            "subcategory":"Research",
            "type":"Services"
        }
    ],
    "sg:phone":"+1 609 818 9701",
    "sg:postcode":"08534",
    "sg:province":"NJ",
    "sg:tags":[
        "nonphysical",
        "commercial"
    ],
    "wof:name":"Fimetrix",
    "wof:placetype":"venue"
},
  "geometry": {"coordinates":[-74.799904,40.331656],"type":"Point"}
}