{
  "type": "Feature",
  "properties": {
    "addr:full":"Bch Ave & Madison A Cape May NJ 08204",
    "addr:postcode":"08204",
    "addr:street":"Bch Ave &;A;May",
    "iso:country":"US",
    "sg:address":"Bch Ave & Madison A",
    "sg:city":"Cape May",
    "sg:classifiers":[
        {
            "category":"Travel",
            "subcategory":"Hotels & Motels",
            "type":"Entertainment"
        }
    ],
    "sg:phone":"+1 609 884 7011",
    "sg:postcode":"08204",
    "sg:province":"NJ",
    "wof:name":"Montreal Liquor Store",
    "wof:placetype":"venue"
},
  "geometry": {"coordinates":[-74.929199,38.9701],"type":"Point"}
}