{
  "type": "Feature",
  "properties": {
    "iso:country":"US",
    "sg:address":"519 River Rd",
    "sg:city":"Edgewater",
    "sg:classifiers":[
        {
            "category":"Health Services",
            "subcategory":"Clinic",
            "type":"Services"
        },
        {
            "category":"Health Services",
            "subcategory":"Health Practitioner",
            "type":"Services"
        },
        {
            "category":"Health Services",
            "subcategory":"Chiropractor",
            "type":"Services"
        }
    ],
    "sg:phone":"+1 201 606 6006",
    "sg:postcode":"07020",
    "sg:province":"NJ",
    "sg:tags":[
        "medicine",
        "alternative",
        "chiropractic"
    ],
    "wof:name":"Heller Family Chiropractic",
    "wof:placetype":"venue"
},
  "geometry": {"coordinates":[-73.985659,40.813184],"type":"Point"}
}