{
  "type": "Feature",
  "properties": {
    "iso:country":"US",
    "sg:address":"38 Onondago Trl",
    "sg:city":"Medford Lakes",
    "sg:classifiers":[
        {
            "category":"Building & Trades",
            "subcategory":"Construction",
            "type":"Services"
        }
    ],
    "sg:phone":"+1 609 654 8820",
    "sg:postcode":"08055",
    "sg:province":"NJ",
    "sg:tags":[
        "general",
        "contractor"
    ],
    "wof:name":"Basements Unlimited",
    "wof:placetype":"venue"
},
  "geometry": {"coordinates":[-74.810715,39.863572],"type":"Point"}
}