{
  "type": "Feature",
  "properties": {
    "addr:full":"6 Carla Ct Morristown NJ 07960",
    "addr:housenumber":"6",
    "addr:postcode":"07960",
    "addr:street":"Carla Ct",
    "iso:country":"US",
    "sg:address":"6 Carla Ct",
    "sg:city":"Morristown",
    "sg:classifiers":[
        {
            "category":"Professional",
            "subcategory":"Management & Consulting",
            "type":"Services"
        }
    ],
    "sg:phone":"+1   ",
    "sg:postcode":"07960",
    "sg:province":"NJ",
    "sg:tags":[
        "business"
    ],
    "wof:name":"Strong Consulting",
    "wof:placetype":"venue"
},
  "geometry": {"coordinates":[-74.475737,40.783135],"type":"Point"}
}