{
  "type": "Feature",
  "properties": {
    "iso:country":"US",
    "sg:address":"371 21st Ave",
    "sg:city":"Paterson",
    "sg:classifiers":[
        {
            "category":"Shopping",
            "subcategory":"Mobile Phones",
            "type":"Retail Goods"
        }
    ],
    "sg:phone":"+1 973 925 2505",
    "sg:postcode":"07501",
    "sg:province":"NJ",
    "wof:name":"Newwave Communications",
    "wof:placetype":"venue"
},
  "geometry": {"coordinates":[-74.15764299999999,40.906874],"type":"Point"}
}