{
  "type": "Feature",
  "properties": {
    "iso:country":"US",
    "sg:address":"275 Newark Ave",
    "sg:city":"Jersey City",
    "sg:classifiers":[
        {
            "category":"Social Services",
            "subcategory":"Child Care",
            "type":"Services"
        }
    ],
    "sg:phone":"+1 201 653 5580",
    "sg:postcode":"07302",
    "sg:province":"NJ",
    "sg:tags":[
        "day"
    ],
    "wof:name":"Our Little Rugratz Day Care Center",
    "wof:placetype":"venue"
},
  "geometry": {"coordinates":[-74.049488,40.723151],"type":"Point"}
}