{
  "type": "Feature",
  "properties": {
    "addr:full":"23 Gregory Ln Warren NJ 07059",
    "addr:housenumber":"23",
    "addr:postcode":"07059",
    "addr:street":"Gregory Ln",
    "iso:country":"US",
    "sg:address":"23 Gregory Ln",
    "sg:city":"Warren",
    "sg:classifiers":[
        {
            "category":"Shopping",
            "subcategory":"Optical Goods",
            "type":"Retail Goods"
        },
        {
            "category":"Manufacturing",
            "subcategory":"Tools & Machinery",
            "type":"Manufacturing & Wholesale Goods"
        }
    ],
    "sg:phone":"+1 908 604 6292",
    "sg:postcode":"07059",
    "sg:province":"NJ",
    "sg:tags":[
        "mfg",
        "ophthalmic"
    ],
    "wof:name":"Liberty Optical Inc",
    "wof:placetype":"venue"
},
  "geometry": {"coordinates":[-74.53047599999999,40.636859],"type":"Point"}
}