{
  "type": "Feature",
  "properties": {
    "addr:full":"1111 Paulison Ave Clifton NJ 07011",
    "addr:housenumber":"1111",
    "addr:postcode":"07011",
    "addr:street":"Paulison Ave",
    "iso:country":"US",
    "sg:address":"1111 Paulison Ave",
    "sg:city":"Clifton",
    "sg:classifiers":[
        {
            "category":"Shopping",
            "subcategory":"Discount & Variety Stores",
            "type":"Retail Goods"
        }
    ],
    "sg:phone":"+1 973 947 4100",
    "sg:postcode":"07011",
    "sg:province":"NJ",
    "sg:tags":[
        "merchandise",
        "general"
    ],
    "wof:name":"Chromalox Sales Office",
    "wof:placetype":"venue"
},
  "geometry": {"coordinates":[-74.15925300000001,40.876314],"type":"Point"}
}