{
  "type": "Feature",
  "properties": {
    "iso:country":"US",
    "sg:address":"15 Boylan St",
    "sg:city":"Newark",
    "sg:classifiers":[
        {
            "category":"Education",
            "subcategory":"School",
            "type":"Public Place"
        }
    ],
    "sg:phone":"+1   ",
    "sg:postcode":"07106",
    "sg:province":"NJ",
    "wof:name":"Boylan Street School",
    "wof:placetype":"venue"
},
  "geometry": {"coordinates":[-74.22730199999999,40.743381],"type":"Point"}
}