{
  "type": "Feature",
  "properties": {
    "iso:country":"US",
    "sg:address":"341 S Jefferson St",
    "sg:city":"Orange",
    "sg:classifiers":[
        {
            "category":"Food & Beverages",
            "subcategory":"Groceries & Convenience Stores",
            "type":"Retail Goods"
        }
    ],
    "sg:phone":"+1 973 395 2767",
    "sg:postcode":"07050",
    "sg:province":"NJ",
    "sg:tags":[
        "product"
    ],
    "wof:name":"Lagniappe Louisiana Food Spec",
    "wof:placetype":"venue"
},
  "geometry": {"coordinates":[-74.243729,40.768243],"type":"Point"}
}