{
  "type": "Feature",
  "properties": {
    "iso:country":"US",
    "sg:address":"250 Maple Pl",
    "sg:city":"Keyport",
    "sg:classifiers":[
        {
            "category":"Health Services",
            "subcategory":"Doctor",
            "type":"Services"
        }
    ],
    "sg:phone":"+1   ",
    "sg:postcode":"07735",
    "sg:province":"NJ",
    "sg:tags":[
        "medical"
    ],
    "wof:name":"Damita Bryant MD",
    "wof:placetype":"venue"
},
  "geometry": {"coordinates":[-74.209762,40.428959],"type":"Point"}
}