{
  "type": "Feature",
  "properties": {
    "iso:country":"US",
    "sg:address":"271 N Livingston Ave",
    "sg:city":"Livingston",
    "sg:classifiers":[
        {
            "category":"Autos & Motor Vehicles",
            "subcategory":"Boat Sales",
            "type":"Retail Goods"
        },
        {
            "category":"Restaurant",
            "type":"Food & Drink"
        }
    ],
    "sg:phone":"+1 973 422 0222",
    "sg:postcode":"07039",
    "sg:province":"NJ",
    "sg:tags":[
        "yacht",
        "broker",
        "shipping"
    ],
    "wof:name":"Great China Chartering Agency",
    "wof:placetype":"venue"
},
  "geometry": {"coordinates":[-74.31113999999999,40.811333],"type":"Point"}
}