{
  "type": "Feature",
  "properties": {
    "iso:country":"US",
    "sg:address":"12 Ridge Rd",
    "sg:city":"Chatham",
    "sg:phone":"+1 973 701 7097",
    "sg:postcode":"07928",
    "sg:province":"NJ",
    "sg:tags":[
        "product",
        "oil",
        "petroleum"
    ],
    "wof:name":"Sprague Energy Corp",
    "wof:placetype":"venue"
},
  "geometry": {"coordinates":[-74.444418,40.692858],"type":"Point"}
}