{
  "type": "Feature",
  "properties": {
    "addr:full":"256 E 7th St Clifton NJ 07011",
    "addr:housenumber":"256",
    "addr:postcode":"07011",
    "addr:street":"E 7Th St",
    "iso:country":"US",
    "sg:address":"256 E 7th St",
    "sg:city":"Clifton",
    "sg:classifiers":[
        {
            "category":"Building & Trades",
            "subcategory":"Construction",
            "type":"Services"
        }
    ],
    "sg:phone":"+1 973 478 7228",
    "sg:postcode":"07011",
    "sg:province":"NJ",
    "sg:tags":[
        "pavement",
        "hanging",
        "marking",
        "contractor"
    ],
    "wof:name":"Bill Klein Coating Co",
    "wof:placetype":"venue"
},
  "geometry": {"coordinates":[-74.144685,40.886348],"type":"Point"}
}