{
  "type": "Feature",
  "properties": {
    "iso:country":"US",
    "sg:address":"102 Omni Ct",
    "sg:city":"Neshanic Station",
    "sg:classifiers":[
        {
            "category":"Real Estate",
            "subcategory":"Real Estate Operator",
            "type":"Services"
        }
    ],
    "sg:phone":"+1   ",
    "sg:postcode":"08853",
    "sg:province":"NJ",
    "sg:tags":[
        "building",
        "nonresidential"
    ],
    "wof:name":"Opdyke Properties LLC",
    "wof:placetype":"venue"
},
  "geometry": {"coordinates":[-74.758318,40.528273],"type":"Point"}
}