{
  "type": "Feature",
  "properties": {
    "iso:country":"US",
    "sg:address":"9 E Main St",
    "sg:city":"Flemington",
    "sg:classifiers":[
        {
            "category":"Real Estate",
            "subcategory":"Real Estate Services",
            "type":"Services"
        },
        {
            "category":"Real Estate",
            "subcategory":"Real Estate Agent",
            "type":"Services"
        }
    ],
    "sg:phone":"+1 908 782 3040",
    "sg:postcode":"08822",
    "sg:province":"NJ",
    "sg:tags":[
        "buyer",
        "broker"
    ],
    "wof:name":"Clmm Realty",
    "wof:placetype":"venue"
},
  "geometry": {"coordinates":[-74.858863,40.513309],"type":"Point"}
}