{
  "type": "Feature",
  "properties": {
    "addr:full":"42 Pine Cove Mount Laurel NJ 08054",
    "addr:housenumber":"42",
    "addr:postcode":"08054",
    "addr:street":"Pine Cove",
    "iso:country":"US",
    "sg:address":"42 Pine Cove",
    "sg:city":"Mount Laurel",
    "sg:classifiers":[
        {
            "category":"Building & Trades",
            "subcategory":"Construction",
            "type":"Services"
        }
    ],
    "sg:phone":"+1 856 439 1788",
    "sg:postcode":"08054",
    "sg:province":"NJ",
    "sg:tags":[
        "hanging",
        "contractor"
    ],
    "wof:name":"Color My Walls",
    "wof:placetype":"venue"
},
  "geometry": {"coordinates":[-74.927589,39.918548],"type":"Point"}
}