{
  "type": "Feature",
  "properties": {
    "iso:country":"US",
    "sg:address":"9 Columbia Ave",
    "sg:city":"Cranford",
    "sg:classifiers":[
        {
            "category":"Shopping",
            "subcategory":"Antiques",
            "type":"Retail Goods"
        }
    ],
    "sg:phone":"+1 908 272 3999",
    "sg:postcode":"07016",
    "sg:province":"NJ",
    "wof:name":"Cranford Antiques & Booksellers",
    "wof:placetype":"venue"
},
  "geometry": {"coordinates":[-74.301546,40.665453],"type":"Point"}
}