{
  "type": "Feature",
  "properties": {
    "iso:country":"US",
    "sg:address":"180 Glen Rd",
    "sg:city":"Woodcliff Lake",
    "sg:classifiers":[
        {
            "category":"Professional",
            "subcategory":"Management & Consulting",
            "type":"Services"
        }
    ],
    "sg:phone":"+1   ",
    "sg:postcode":"07677",
    "sg:province":"NJ",
    "sg:tags":[
        "business"
    ],
    "wof:name":"Cck Consulting Inc",
    "wof:placetype":"venue"
},
  "geometry": {"coordinates":[-74.06204,41.032771],"type":"Point"}
}