{
  "type": "Feature",
  "properties": {
    "addr:full":"326 Rochelle Ave Rochelle Park NJ 07662",
    "addr:housenumber":"326",
    "addr:postcode":"07662",
    "addr:street":"Rochelle Ave",
    "iso:country":"US",
    "sg:address":"326 Rochelle Ave",
    "sg:city":"Rochelle Park",
    "sg:classifiers":[
        {
            "category":"Personal",
            "subcategory":"Beauty Salon",
            "type":"Services"
        }
    ],
    "sg:phone":"+1 201 226 9719",
    "sg:postcode":"07662",
    "sg:province":"NJ",
    "sg:tags":[
        "hair",
        "shop"
    ],
    "wof:name":"Cutting Loose Hair Salon",
    "wof:placetype":"venue"
},
  "geometry": {"coordinates":[-74.076103,40.906502],"type":"Point"}
}