{
  "type": "Feature",
  "properties": {
    "iso:country":"US",
    "sg:address":"269 Rutgers Pl",
    "sg:city":"Nutley",
    "sg:classifiers":[
        {
            "category":"Building & Trades",
            "subcategory":"Construction",
            "type":"Services"
        }
    ],
    "sg:phone":"+1 973 661 1358",
    "sg:postcode":"07110",
    "sg:province":"NJ",
    "sg:tags":[
        "house"
    ],
    "wof:name":"Panaccione & Son Inc",
    "wof:placetype":"venue"
},
  "geometry": {"coordinates":[-74.147173,40.822979],"type":"Point"}
}