{
  "type": "Feature",
  "properties": {
    "iso:country":"US",
    "sg:address":"176 Ramapo Valley Rd",
    "sg:city":"Oakland",
    "sg:classifiers":[
        {
            "category":"Fast Food",
            "type":"Food & Drink"
        },
        {
            "category":"Restaurant",
            "type":"Food & Drink"
        }
    ],
    "sg:phone":"+1 201 337 8777",
    "sg:postcode":"07436",
    "sg:province":"NJ",
    "sg:tags":[
        "traditional",
        "grill",
        "american",
        "bar",
        "take"
    ],
    "wof:name":"Lenape Valley Grill",
    "wof:placetype":"venue"
},
  "geometry": {"coordinates":[-74.25225,41.015325],"type":"Point"}
}