{
  "type": "Feature",
  "properties": {
    "addr:full":"8306 5th Ave North Bergen NJ 07047",
    "addr:housenumber":"8306",
    "addr:postcode":"07047",
    "addr:street":"5Th Ave",
    "iso:country":"US",
    "sg:address":"8306 5th Ave",
    "sg:city":"North Bergen",
    "sg:classifiers":[
        {
            "category":"Insurance",
            "subcategory":"Insurance Agent",
            "type":"Services"
        }
    ],
    "sg:phone":"+1 201 617 2424",
    "sg:postcode":"07047",
    "sg:province":"NJ",
    "wof:name":"Alama Luis Insurance Svc",
    "wof:placetype":"venue"
},
  "geometry": {"coordinates":[-74.00840100000001,40.806254],"type":"Point"}
}