{
  "type": "Feature",
  "properties": {
    "iso:country":"US",
    "sg:address":"3200 Westfield Ave",
    "sg:city":"Camden",
    "sg:classifiers":[
        {
            "category":"Restaurant",
            "type":"Food & Drink"
        },
        {
            "category":"Food & Beverages",
            "subcategory":"Bakery",
            "type":"Retail Goods"
        }
    ],
    "sg:phone":"+1 856 963 0400",
    "sg:postcode":"08105",
    "sg:province":"NJ",
    "sg:tags":[
        "baker",
        "eating",
        "caterer"
    ],
    "wof:name":"Latino's Bakery & Restaurant",
    "wof:placetype":"venue"
},
  "geometry": {"coordinates":[-75.0783,39.950401],"type":"Point"}
}