{
  "type": "Feature",
  "properties": {
    "iso:country":"US",
    "sg:address":"204 Glenside Trl",
    "sg:city":"Sparta",
    "sg:classifiers":[
        {
            "category":"Professional",
            "subcategory":"Advertising",
            "type":"Services"
        }
    ],
    "sg:phone":"+1   ",
    "sg:postcode":"07871",
    "sg:province":"NJ",
    "sg:tags":[
        "agency"
    ],
    "wof:name":"Sabol Advertising",
    "wof:placetype":"venue"
},
  "geometry": {"coordinates":[-74.68537999999999,41.001433],"type":"Point"}
}