{
  "type": "Feature",
  "properties": {
    "iso:country":"US",
    "sg:address":"10 Orchard Ln",
    "sg:city":"Livingston",
    "sg:classifiers":[
        {
            "category":"Manufacturing",
            "subcategory":"Tools & Machinery",
            "type":"Manufacturing & Wholesale Goods"
        }
    ],
    "sg:phone":"+1 973 992 1377",
    "sg:postcode":"07039",
    "sg:province":"NJ",
    "sg:tags":[
        "equipment",
        "dental",
        "supply"
    ],
    "wof:name":"Turbotech Inc",
    "wof:placetype":"venue"
},
  "geometry": {"coordinates":[-74.295956,40.799946],"type":"Point"}
}