{
  "type": "Feature",
  "properties": {
    "addr:full":"316 Hialeah Dr Cherry Hill NJ 08002",
    "addr:housenumber":"316",
    "addr:postcode":"08002",
    "addr:street":"Hialeah Dr",
    "iso:country":"US",
    "sg:address":"316 Hialeah Dr",
    "sg:city":"Cherry Hill",
    "sg:classifiers":[
        {
            "category":"Building & Trades",
            "subcategory":"Construction",
            "type":"Services"
        }
    ],
    "sg:phone":"+1 856 779 3338",
    "sg:postcode":"08002",
    "sg:province":"NJ",
    "sg:tags":[
        "contractor"
    ],
    "wof:name":"D&R Contracting Services LLC",
    "wof:placetype":"venue"
},
  "geometry": {"coordinates":[-75.02148,39.935627],"type":"Point"}
}