{
  "type": "Feature",
  "properties": {
    "iso:country":"US",
    "sg:address":"317 Harrington Ave",
    "sg:city":"Closter",
    "sg:classifiers":[
        {
            "category":"Manufacturing",
            "subcategory":"Printing",
            "type":"Manufacturing & Wholesale Goods"
        }
    ],
    "sg:phone":"+1 201 358 6868",
    "sg:postcode":"07624",
    "sg:province":"NJ",
    "sg:tags":[
        "publisher",
        "newsletter",
        "publishing"
    ],
    "wof:name":"Gift Beat",
    "wof:placetype":"venue"
},
  "geometry": {"coordinates":[-73.96395,40.974466],"type":"Point"}
}