{
  "type": "Feature",
  "properties": {
    "addr:full":"814 Lowell Ave Toms River NJ 08753",
    "addr:housenumber":"814",
    "addr:postcode":"08753",
    "addr:street":"Lowell Ave",
    "iso:country":"US",
    "sg:address":"814 Lowell Ave",
    "sg:city":"Toms River",
    "sg:classifiers":[
        {
            "category":"Professional",
            "subcategory":"Computer Services",
            "type":"Services"
        }
    ],
    "sg:phone":"+1 732 244 2930",
    "sg:postcode":"08753",
    "sg:province":"NJ",
    "sg:tags":[
        "repair",
        "sales"
    ],
    "wof:name":"Lowell Avenue Computers Inc",
    "wof:placetype":"venue"
},
  "geometry": {"coordinates":[-74.18758699999999,39.961259],"type":"Point"}
}