{
  "type": "Feature",
  "properties": {
    "addr:full":"33 Overlook Rd Summit NJ 07960",
    "addr:housenumber":"33",
    "addr:postcode":"07960",
    "addr:street":"Overlook Rd",
    "iso:country":"US",
    "sg:address":"33 Overlook Rd",
    "sg:city":"Summit",
    "sg:classifiers":[
        {
            "category":"Health Services",
            "subcategory":"Doctor",
            "type":"Services"
        }
    ],
    "sg:phone":"+1 908 522 3100",
    "sg:postcode":"07960",
    "sg:province":"NJ",
    "sg:tags":[
        "physician",
        "surgeon"
    ],
    "wof:name":"William B Lukachko MD",
    "wof:placetype":"venue"
},
  "geometry": {"coordinates":[-74.43117599999999,40.79981],"type":"Point"}
}