{
  "type": "Feature",
  "properties": {
    "iso:country":"US",
    "sg:address":"108 Adams Dr",
    "sg:city":"Brick",
    "sg:classifiers":[
        {
            "category":"Retail",
            "subcategory":"Repair Shop",
            "type":"Services"
        }
    ],
    "sg:phone":"+1   ",
    "sg:postcode":"08724",
    "sg:province":"NJ",
    "sg:tags":[
        "household",
        "appliance"
    ],
    "wof:name":"Edwards Appliance Service",
    "wof:placetype":"venue"
},
  "geometry": {"coordinates":[-74.108395,40.078654],"type":"Point"}
}