{
  "type": "Feature",
  "properties": {
    "iso:country":"US",
    "sg:address":"83 Groveland Ave",
    "sg:city":"Trenton",
    "sg:classifiers":[
        {
            "category":"Building & Trades",
            "subcategory":"Construction",
            "type":"Services"
        }
    ],
    "sg:phone":"+1 609 538 8710",
    "sg:postcode":"08638",
    "sg:province":"NJ",
    "sg:tags":[
        "general",
        "carpentry"
    ],
    "wof:name":"Mata General Construction",
    "wof:placetype":"venue"
},
  "geometry": {"coordinates":[-74.771254,40.252637],"type":"Point"}
}