{
  "type": "Feature",
  "properties": {
    "addr:full":"1015 Springfield Ave Irvington NJ 07111",
    "addr:housenumber":"1015",
    "addr:postcode":"07111",
    "addr:street":"Springfield Ave",
    "iso:country":"US",
    "sg:address":"1015 Springfield Ave",
    "sg:city":"Irvington",
    "sg:classifiers":[
        {
            "category":"Shopping",
            "subcategory":"Pharmacy",
            "type":"Retail Goods"
        }
    ],
    "sg:phone":"+1 973 372 3010",
    "sg:postcode":"07111",
    "sg:province":"NJ",
    "wof:name":"Rite Aid Pharmacy",
    "wof:placetype":"venue"
},
  "geometry": {"coordinates":[-74.22934100000001,40.726299],"type":"Point"}
}