{
  "type": "Feature",
  "properties": {
    "iso:country":"US",
    "sg:address":"232 Nuthatch Ct",
    "sg:city":"Three Bridges",
    "sg:classifiers":[
        {
            "category":"Professional",
            "subcategory":"Business Services",
            "type":"Services"
        }
    ],
    "sg:phone":"+1   ",
    "sg:postcode":"08887",
    "sg:province":"NJ",
    "wof:name":"Artisan Interiors Decorative F",
    "wof:placetype":"venue"
},
  "geometry": {"coordinates":[-74.78020600000001,40.528957],"type":"Point"}
}