{
  "type": "Feature",
  "properties": {
    "addr:full":"937 Raritan Rd Clark NJ 07066",
    "addr:housenumber":"937",
    "addr:postcode":"07066",
    "addr:street":"Raritan Rd",
    "iso:country":"US",
    "sg:address":"937 Raritan Rd",
    "sg:city":"Clark",
    "sg:classifiers":[
        {
            "category":"Social Services",
            "subcategory":"Child Care",
            "type":"Services"
        }
    ],
    "sg:phone":"+1   ",
    "sg:postcode":"07066",
    "sg:province":"NJ",
    "sg:tags":[
        "day"
    ],
    "wof:name":"Educational Enrichment Inc",
    "wof:placetype":"venue"
},
  "geometry": {"coordinates":[-74.319864,40.622974],"type":"Point"}
}