{
  "type": "Feature",
  "properties": {
    "addr:full":"19 E Evesham Rd Voorhees NJ 08043",
    "addr:housenumber":"19",
    "addr:postcode":"08043",
    "addr:street":"E Evesham Rd",
    "iso:country":"US",
    "sg:address":"19 E Evesham Rd",
    "sg:city":"Voorhees",
    "sg:classifiers":[
        {
            "category":"Health Services",
            "subcategory":"Optometrist",
            "type":"Services"
        }
    ],
    "sg:phone":"+1 856 783 8822",
    "sg:postcode":"08043",
    "sg:province":"NJ",
    "wof:name":"David T Gubman OD",
    "wof:placetype":"venue"
},
  "geometry": {"coordinates":[-75.00352700000001,39.85969],"type":"Point"}
}