{
  "type": "Feature",
  "properties": {
    "iso:country":"US",
    "sg:address":"975 Clifton Ave",
    "sg:city":"Clifton",
    "sg:classifiers":[
        {
            "category":"Health Services",
            "subcategory":"Doctor",
            "type":"Services"
        }
    ],
    "sg:phone":"+1   ",
    "sg:postcode":"07013",
    "sg:province":"NJ",
    "wof:name":"Glenn Gorab DMD",
    "wof:placetype":"venue"
},
  "geometry": {"coordinates":[-74.16272499999999,40.864234],"type":"Point"}
}