{
  "type": "Feature",
  "properties": {
    "iso:country":"US",
    "sg:address":"15 Beacon Hill Rd",
    "sg:city":"Atlantic Hghlnds",
    "sg:classifiers":[
        {
            "category":"Shopping",
            "type":"Retail Goods"
        }
    ],
    "sg:phone":"+1 732 872 9414",
    "sg:postcode":"07716",
    "sg:province":"NJ",
    "sg:tags":[
        "wedding",
        "supply"
    ],
    "wof:name":"Pen 2 Paper",
    "wof:placetype":"venue"
},
  "geometry": {"coordinates":[-74.05118400000001,40.406634],"type":"Point"}
}