{
  "type": "Feature",
  "properties": {
    "iso:country":"US",
    "sg:address":"117 W 2nd St",
    "sg:city":"Bayonne",
    "sg:classifiers":[
        {
            "category":"Restaurant",
            "type":"Food & Drink"
        }
    ],
    "sg:phone":"+1 201 436 8181",
    "sg:postcode":"07002",
    "sg:province":"NJ",
    "sg:tags":[
        "pizza",
        "caterer",
        "italian"
    ],
    "wof:name":"Chris'corner",
    "wof:placetype":"venue"
},
  "geometry": {"coordinates":[-74.13510100000001,40.6469],"type":"Point"}
}