{
  "type": "Feature",
  "properties": {
    "addr:full":"435 Essex St Millburn NJ 07041",
    "addr:housenumber":"435",
    "addr:postcode":"07041",
    "addr:street":"Essex St",
    "iso:country":"US",
    "sg:address":"435 Essex St",
    "sg:city":"Millburn",
    "sg:classifiers":[
        {
            "category":"Government",
            "subcategory":"Police Station",
            "type":"Public Place"
        }
    ],
    "sg:phone":"+1 973 564 7013",
    "sg:postcode":"07041",
    "sg:province":"NJ",
    "sg:tags":[
        "department"
    ],
    "wof:name":"Millburn Township Police Headquarters",
    "wof:placetype":"venue"
},
  "geometry": {"coordinates":[-74.31131600000001,40.723816],"type":"Point"}
}