{
  "type": "Feature",
  "properties": {
    "addr:full":"7 Hanover Rd East Hanover NJ 07936",
    "addr:housenumber":"7",
    "addr:postcode":"07936",
    "addr:street":"Hanover Rd",
    "iso:country":"US",
    "sg:address":"7 Hanover Rd",
    "sg:city":"East Hanover",
    "sg:classifiers":[
        {
            "category":"Professional",
            "type":"Services"
        }
    ],
    "sg:phone":"+1 973 428 8334",
    "sg:postcode":"07936",
    "sg:province":"NJ",
    "wof:name":"Mike's Cleanup Svc",
    "wof:placetype":"venue"
},
  "geometry": {"coordinates":[-74.37200799999999,40.79912],"type":"Point"}
}