{
  "type": "Feature",
  "properties": {
    "addr:full":"194 N Broadway Pennsville NJ 08070",
    "addr:housenumber":"194",
    "addr:postcode":"08070",
    "addr:street":"N Broadway",
    "iso:country":"US",
    "sg:address":"194 N Broadway",
    "sg:city":"Pennsville",
    "sg:classifiers":[
        {
            "category":"Home & Garden",
            "subcategory":"Carpets & Floor Coverings",
            "type":"Retail Goods"
        }
    ],
    "sg:phone":"+1 856 678 2606",
    "sg:postcode":"08070",
    "sg:province":"NJ",
    "sg:tags":[
        "dealer",
        "rug"
    ],
    "wof:name":"Bill's Custom Carpets",
    "wof:placetype":"venue"
},
  "geometry": {"coordinates":[-75.508928,39.664745],"type":"Point"}
}