{
  "type": "Feature",
  "properties": {
    "iso:country":"US",
    "sg:address":"20 Lanning Blvd",
    "sg:city":"Hightstown",
    "sg:classifiers":[
        {
            "category":"Health Services",
            "subcategory":"Nursing And Care Facility",
            "type":"Services"
        }
    ],
    "sg:phone":"+1 609 448 7738",
    "sg:postcode":"08520",
    "sg:province":"NJ",
    "sg:tags":[
        "skilled"
    ],
    "wof:name":"Presbyterian Homes East Winsor",
    "wof:placetype":"venue"
},
  "geometry": {"coordinates":[-74.540238,40.276072],"type":"Point"}
}