{
  "type": "Feature",
  "properties": {
    "addr:full":"100 Seaview Ave Monmouth Beach NJ 07750",
    "addr:housenumber":"100",
    "addr:postcode":"07750",
    "addr:street":"Seaview Ave",
    "iso:country":"US",
    "sg:address":"100 Seaview Ave",
    "sg:city":"Monmouth Beach",
    "sg:classifiers":[
        {
            "category":"Professional",
            "subcategory":"Employment Agencies",
            "type":"Services"
        }
    ],
    "sg:phone":"+1   ",
    "sg:postcode":"07750",
    "sg:province":"NJ",
    "wof:name":"McE Consulting",
    "wof:placetype":"venue"
},
  "geometry": {"coordinates":[-73.97499500000001,40.342244],"type":"Point"}
}