{
  "type": "Feature",
  "properties": {
    "addr:full":"120 S Concourse Neptune NJ 07753",
    "addr:housenumber":"120",
    "addr:postcode":"07753",
    "addr:street":"S Concourse",
    "iso:country":"US",
    "sg:address":"120 S Concourse",
    "sg:city":"Neptune",
    "sg:classifiers":[
        {
            "category":"Building & Trades",
            "subcategory":"Construction",
            "type":"Services"
        }
    ],
    "sg:phone":"+1 732 549 4561",
    "sg:postcode":"07753",
    "sg:province":"NJ",
    "sg:tags":[
        "hanging",
        "painter",
        "contractor"
    ],
    "wof:name":"Sinnott Painting Inc",
    "wof:placetype":"venue"
},
  "geometry": {"coordinates":[-74.030469,40.189447],"type":"Point"}
}