{
  "type": "Feature",
  "properties": {
    "addr:full":"1113 6th Ave Neptune NJ 07753",
    "addr:housenumber":"1113",
    "addr:postcode":"07753",
    "addr:street":"6Th Ave",
    "iso:country":"US",
    "sg:address":"1113 6th Ave",
    "sg:city":"Neptune",
    "sg:classifiers":[
        {
            "category":"Building & Trades",
            "subcategory":"Landscaping Services",
            "type":"Services"
        }
    ],
    "sg:phone":"+1 732 774 7518",
    "sg:postcode":"07753",
    "sg:province":"NJ",
    "sg:tags":[
        "landscape",
        "contractor"
    ],
    "wof:name":"G & E Daughters & Sns Landscpg",
    "wof:placetype":"venue"
},
  "geometry": {"coordinates":[-74.021427,40.203692],"type":"Point"}
}