{
  "type": "Feature",
  "properties": {
    "addr:full":"14 Deer Trl Flemington NJ 08822",
    "addr:housenumber":"14",
    "addr:postcode":"08822",
    "addr:street":"Deer Trl",
    "iso:country":"US",
    "sg:address":"14 Deer Trl",
    "sg:city":"Flemington",
    "sg:classifiers":[
        {
            "category":"Building & Trades",
            "subcategory":"Electrical",
            "type":"Services"
        }
    ],
    "sg:phone":"+1 908 788 1607",
    "sg:postcode":"08822",
    "sg:province":"NJ",
    "sg:tags":[
        "electrical",
        "contractor"
    ],
    "wof:name":"Mw Sine Electrical Contractor",
    "wof:placetype":"venue"
},
  "geometry": {"coordinates":[-74.863164,40.549961],"type":"Point"}
}