{
  "type": "Feature",
  "properties": {
    "iso:country":"US",
    "sg:address":"830 Franklin Lake Rd",
    "sg:city":"Franklin Lakes",
    "sg:classifiers":[
        {
            "category":"Recreation",
            "type":"Entertainment"
        }
    ],
    "sg:phone":"+1   ",
    "sg:postcode":"07417",
    "sg:province":"NJ",
    "sg:tags":[
        "club",
        "specializing",
        "membership",
        "tennis",
        "sporting"
    ],
    "wof:name":"Indian Trail Club",
    "wof:placetype":"venue"
},
  "geometry": {"coordinates":[-74.215664,40.992832],"type":"Point"}
}