{
  "type": "Feature",
  "properties": {
    "iso:country":"US",
    "sg:address":"15 Brant Ave Ste 4",
    "sg:city":"Clark",
    "sg:classifiers":[
        {
            "category":"Health Services",
            "subcategory":"Dentist",
            "type":"Services"
        }
    ],
    "sg:phone":"+1 732 815 1776",
    "sg:postcode":"07066",
    "sg:province":"NJ",
    "wof:name":"Grutt Arthur T DMD",
    "wof:placetype":"venue"
},
  "geometry": {"coordinates":[-74.304298,40.622398],"type":"Point"}
}