{
  "type": "Feature",
  "properties": {
    "iso:country":"US",
    "sg:address":"1091 Bristol Rd",
    "sg:city":"Mountainside",
    "sg:classifiers":[
        {
            "category":"Professional",
            "subcategory":"Computer Services",
            "type":"Services"
        }
    ],
    "sg:phone":"+1 908 654 0900",
    "sg:postcode":"07092",
    "sg:province":"NJ",
    "sg:tags":[
        "repair"
    ],
    "sg:website":"www.usgi.com",
    "wof:name":"Unicom Solutions Group Inc",
    "wof:placetype":"venue"
},
  "geometry": {"coordinates":[-74.34229999999999,40.684601],"type":"Point"}
}