{
  "type": "Feature",
  "properties": {
    "iso:country":"US",
    "sg:address":"43 Nautilus St",
    "sg:city":"Beachwood",
    "sg:classifiers":[
        {
            "category":"Home & Garden",
            "subcategory":"Building Materials",
            "type":"Retail Goods"
        }
    ],
    "sg:phone":"+1 732 349 7772",
    "sg:postcode":"08722",
    "sg:province":"NJ",
    "sg:tags":[
        "glass",
        "leaded"
    ],
    "wof:name":"PTL Artworks",
    "wof:placetype":"venue"
},
  "geometry": {"coordinates":[-74.1932,39.93098],"type":"Point"}
}