{
  "type": "Feature",
  "properties": {
    "addr:full":"130 Kinderkamack Rd River Edge NJ 07661",
    "addr:housenumber":"130",
    "addr:postcode":"07661",
    "addr:street":"Kinderkamack Rd",
    "iso:country":"US",
    "sg:address":"130 Kinderkamack Rd",
    "sg:city":"River Edge",
    "sg:classifiers":[
        {
            "category":"Health Services",
            "subcategory":"Doctor",
            "type":"Services"
        }
    ],
    "sg:phone":"+1 201 488 2660",
    "sg:postcode":"07661",
    "sg:province":"NJ",
    "wof:name":"Gliedman Paul R MD",
    "wof:placetype":"venue"
},
  "geometry": {"coordinates":[-74.036109,40.91228],"type":"Point"}
}