{
  "type": "Feature",
  "properties": {
    "iso:country":"US",
    "sg:address":"21 Hunter Blvd",
    "sg:city":"West Milford",
    "sg:classifiers":[
        {
            "category":"Building & Trades",
            "subcategory":"Construction",
            "type":"Services"
        }
    ],
    "sg:phone":"+1 973 208 3733",
    "sg:postcode":"07480",
    "sg:province":"NJ",
    "sg:tags":[
        "contractor"
    ],
    "wof:name":"Foster Built Construction",
    "wof:placetype":"venue"
},
  "geometry": {"coordinates":[-74.392303,41.0312],"type":"Point"}
}