{
  "type": "Feature",
  "properties": {
    "addr:full":"100 Daniels Way Freehold NJ 07728",
    "addr:housenumber":"100",
    "addr:postcode":"07728",
    "addr:street":"Daniels Way",
    "iso:country":"US",
    "sg:address":"100 Daniels Way",
    "sg:city":"Freehold",
    "sg:classifiers":[
        {
            "category":"Government",
            "subcategory":"Office",
            "type":"Public Place"
        }
    ],
    "sg:phone":"+1 732 308 4073",
    "sg:postcode":"07728",
    "sg:province":"NJ",
    "sg:tags":[
        "state",
        "program"
    ],
    "wof:name":"Transportation Dept Mntnc",
    "wof:placetype":"venue"
},
  "geometry": {"coordinates":[-74.26877,40.244251],"type":"Point"}
}