{
  "type": "Feature",
  "properties": {
    "addr:full":"1272 State Rte 27 Colonia NJ 07067",
    "addr:housenumber":"1272",
    "addr:postcode":"07067",
    "addr:street":"State Rte 27",
    "iso:country":"US",
    "sg:address":"1272 State Rte 27",
    "sg:city":"Colonia",
    "sg:classifiers":[
        {
            "category":"Home & Garden",
            "subcategory":"Household Appliances",
            "type":"Retail Goods"
        }
    ],
    "sg:phone":"+1 732 382 9799",
    "sg:postcode":"07067",
    "sg:province":"NJ",
    "sg:tags":[
        "machine",
        "sewing"
    ],
    "wof:name":"Viking Sewing Gallery",
    "wof:placetype":"venue"
},
  "geometry": {"coordinates":[-74.30186399999999,40.585649],"type":"Point"}
}