{
  "type": "Feature",
  "properties": {
    "addr:full":"200 Deal Lake Dr Asbury Park NJ 07712",
    "addr:housenumber":"200",
    "addr:postcode":"07712",
    "addr:street":"Deal Lake Dr Asbury Park",
    "iso:country":"US",
    "sg:address":"200 Deal Lake Dr",
    "sg:city":"Asbury Park",
    "sg:classifiers":[
        {
            "category":"Real Estate",
            "subcategory":"Real Estate Operator",
            "type":"Services"
        }
    ],
    "sg:phone":"+1 732 774 6681",
    "sg:postcode":"07712",
    "sg:province":"NJ",
    "sg:tags":[
        "apartment"
    ],
    "wof:name":"Kingsley Arms Apartments",
    "wof:placetype":"venue"
},
  "geometry": {"coordinates":[-73.999933,40.229506],"type":"Point"}
}