{
  "type": "Feature",
  "properties": {
    "addr:full":"350 Bloomfield Ave Newark NJ 07107",
    "addr:housenumber":"350",
    "addr:postcode":"07107",
    "addr:street":"Bloomfield Ave",
    "iso:country":"US",
    "sg:address":"350 Bloomfield Ave",
    "sg:city":"Newark",
    "sg:classifiers":[
        {
            "category":"Personal",
            "subcategory":"Beauty Salon",
            "type":"Services"
        }
    ],
    "sg:phone":"+1 973 484 5300",
    "sg:postcode":"07107",
    "sg:province":"NJ",
    "wof:name":"Esther's Beauty Salon",
    "wof:placetype":"venue"
},
  "geometry": {"coordinates":[-74.18105199999999,40.766867],"type":"Point"}
}