{
  "type": "Feature",
  "properties": {
    "addr:full":"4 Dryer Ct Plainsboro NJ 08536",
    "addr:housenumber":"4",
    "addr:postcode":"08536",
    "addr:street":"Dryer Ct",
    "iso:country":"US",
    "sg:address":"4 Dryer Ct",
    "sg:city":"Plainsboro",
    "sg:classifiers":[
        {
            "category":"Education",
            "subcategory":"Dance Studio",
            "type":"Public Place"
        }
    ],
    "sg:phone":"+1   ",
    "sg:postcode":"08536",
    "sg:province":"NJ",
    "wof:name":"Payal Dancing School",
    "wof:placetype":"venue"
},
  "geometry": {"coordinates":[-74.612855,40.329798],"type":"Point"}
}