{
  "type": "Feature",
  "properties": {
    "iso:country":"US",
    "sg:address":"70 Euclid St",
    "sg:city":"Woodbury",
    "sg:classifiers":[
        {
            "category":"Professional",
            "subcategory":"Lawyer & Legal Services",
            "type":"Services"
        }
    ],
    "sg:phone":"+1 856 848 7091",
    "sg:postcode":"08096",
    "sg:province":"NJ",
    "sg:tags":[
        "transmission",
        "auto",
        "attorney",
        "repair"
    ],
    "wof:name":"Birchmeier & Powell Powell",
    "wof:placetype":"venue"
},
  "geometry": {"coordinates":[-75.149664,39.838507],"type":"Point"}
}