{
  "type": "Feature",
  "properties": {
    "addr:full":"275 Morristown Rd Gillette NJ 07933",
    "addr:housenumber":"275",
    "addr:postcode":"07933",
    "addr:street":"Morristown Rd",
    "iso:country":"US",
    "sg:address":"275 Morristown Rd",
    "sg:city":"Gillette",
    "sg:classifiers":[
        {
            "category":"Professional",
            "subcategory":"Engineering",
            "type":"Services"
        }
    ],
    "sg:phone":"+1 908 903 1000",
    "sg:postcode":"07933",
    "sg:province":"NJ",
    "sg:tags":[
        "engineer"
    ],
    "wof:name":"Ht Pump Specialities",
    "wof:placetype":"venue"
},
  "geometry": {"coordinates":[-74.47795499999999,40.673017],"type":"Point"}
}