{
  "type": "Feature",
  "properties": {
    "iso:country":"US",
    "sg:address":"1300 Westfield Ave",
    "sg:city":"Rahway",
    "sg:classifiers":[
        {
            "category":"Building & Trades",
            "subcategory":"Locksmith",
            "type":"Services"
        }
    ],
    "sg:phone":"+1 877 739 9009",
    "sg:postcode":"07065",
    "sg:province":"NJ",
    "sg:tags":[
        "key"
    ],
    "wof:name":"1 24 Hour Emergency Locksmith",
    "wof:placetype":"venue"
},
  "geometry": {"coordinates":[-74.29472800000001,40.617169],"type":"Point"}
}