{
  "type": "Feature",
  "properties": {
    "addr:full":"101 N Burgee Dr Tuckerton NJ 08087",
    "addr:housenumber":"101",
    "addr:postcode":"08087",
    "addr:street":"N Burgee Dr",
    "iso:country":"US",
    "sg:address":"101 N Burgee Dr",
    "sg:city":"Tuckerton",
    "sg:classifiers":[
        {
            "category":"Travel",
            "subcategory":"Travel Agent",
            "type":"Entertainment"
        }
    ],
    "sg:phone":"+1 609 296 5770",
    "sg:postcode":"08087",
    "sg:province":"NJ",
    "sg:tags":[
        "operator",
        "tour",
        "tours",
        "promoter"
    ],
    "wof:name":"Seniors Unlimited Tour & Trvl",
    "wof:placetype":"venue"
},
  "geometry": {"coordinates":[-74.364729,39.56135],"type":"Point"}
}