{
  "type": "Feature",
  "properties": {
    "addr:full":"371 Monroe St Passaic NJ 07055",
    "addr:housenumber":"371",
    "addr:postcode":"07055",
    "addr:street":"Monroe St",
    "iso:country":"US",
    "sg:address":"371 Monroe St",
    "sg:city":"Passaic",
    "sg:classifiers":[
        {
            "category":"Restaurant",
            "type":"Food & Drink"
        }
    ],
    "sg:phone":"+1 973 472 3654",
    "sg:postcode":"07055",
    "sg:province":"NJ",
    "wof:name":"Taqueria",
    "wof:placetype":"venue"
},
  "geometry": {"coordinates":[-74.130797,40.863451],"type":"Point"}
}