{
  "type": "Feature",
  "properties": {
    "addr:full":"112 la Roche Ave Harrington Park NJ 07640",
    "addr:housenumber":"112",
    "addr:postcode":"07640",
    "addr:street":"La Roche Ave",
    "iso:country":"US",
    "sg:address":"112 la Roche Ave",
    "sg:city":"Harrington Park",
    "sg:classifiers":[
        {
            "category":"Restaurant",
            "type":"Food & Drink"
        }
    ],
    "sg:phone":"+1 201 784 0377",
    "sg:postcode":"07640",
    "sg:province":"NJ",
    "sg:tags":[
        "caterer",
        "catering"
    ],
    "sg:website":"www.contemporaryfoods.com",
    "wof:name":"Contemporary Foods Inc",
    "wof:placetype":"venue"
},
  "geometry": {"coordinates":[-73.98486,40.991696],"type":"Point"}
}