{
  "type": "Feature",
  "properties": {
    "addr:full":"2100 State Route 35 Oakhurst NJ 07755",
    "addr:housenumber":"2100",
    "addr:postcode":"07755",
    "addr:street":"State Route 35",
    "iso:country":"US",
    "sg:address":"2100 State Route 35",
    "sg:city":"Oakhurst",
    "sg:classifiers":[
        {
            "category":"Coffee & Tea",
            "type":"Food & Drink"
        }
    ],
    "sg:menulink":"http://www.allmenus.com/nj/ocean/125780-starbucks-coffee/menu/",
    "sg:phone":"+1 732 493 8770",
    "sg:postcode":"07755",
    "sg:province":"NJ",
    "sg:tags":[
        "american"
    ],
    "wof:name":"Starbucks Coffee",
    "wof:placetype":"venue"
},
  "geometry": {"coordinates":[-74.042188,40.265923],"type":"Point"}
}