{
  "type": "Feature",
  "properties": {
    "iso:country":"US",
    "sg:address":"891 Ringwood Ave",
    "sg:city":"Haskell",
    "sg:classifiers":[
        {
            "category":"Retail",
            "subcategory":"Auto Rental",
            "type":"Services"
        }
    ],
    "sg:phone":"+1 973 831 8255",
    "sg:postcode":"07420",
    "sg:province":"NJ",
    "sg:tags":[
        "truck"
    ],
    "wof:name":"U-Haul",
    "wof:placetype":"venue"
},
  "geometry": {"coordinates":[-74.294371,41.037103],"type":"Point"}
}