{
  "type": "Feature",
  "properties": {
    "iso:country":"US",
    "sg:address":"1172 E Ridgewood Ave",
    "sg:city":"Ridgewood",
    "sg:classifiers":[
        {
            "category":"Social Services",
            "type":"Services"
        }
    ],
    "sg:phone":"+1 201 264 5462",
    "sg:postcode":"07450",
    "sg:province":"NJ",
    "sg:tags":[
        "counselor",
        "marriage",
        "family"
    ],
    "wof:name":"Theresa Villani",
    "wof:placetype":"venue"
},
  "geometry": {"coordinates":[-74.09432200000001,40.973523],"type":"Point"}
}