{
  "type": "Feature",
  "properties": {
    "addr:full":"474 Main St Orange NJ 07050",
    "addr:housenumber":"474",
    "addr:postcode":"07050",
    "addr:street":"Main St",
    "iso:country":"US",
    "sg:address":"474 Main St",
    "sg:city":"Orange",
    "sg:classifiers":[
        {
            "category":"Retail",
            "subcategory":"Auto Rental",
            "type":"Services"
        }
    ],
    "sg:phone":"+1 973 674 0170",
    "sg:postcode":"07050",
    "sg:province":"NJ",
    "sg:tags":[
        "car"
    ],
    "sg:website":"www.budgettruck.com",
    "wof:name":"Budget",
    "wof:placetype":"venue"
},
  "geometry": {"coordinates":[-74.23539100000001,40.774455],"type":"Point"}
}