{
  "type": "Feature",
  "properties": {
    "iso:country":"US",
    "sg:address":"21 Devon Dr",
    "sg:city":"West Orange",
    "sg:classifiers":[
        {
            "category":"Freight",
            "type":"Transportation"
        }
    ],
    "sg:phone":"+1 973 736 3804",
    "sg:postcode":"07052",
    "sg:province":"NJ",
    "sg:tags":[
        "consultant",
        "arrangement"
    ],
    "wof:name":"Mel Loeser Associates Inc",
    "wof:placetype":"venue"
},
  "geometry": {"coordinates":[-74.264782,40.761553],"type":"Point"}
}