{
  "type": "Feature",
  "properties": {
    "addr:full":"3003 N Mill Rd Vineland NJ 08360",
    "addr:housenumber":"3003",
    "addr:postcode":"08360",
    "addr:street":"N Mill Rd",
    "iso:country":"US",
    "sg:address":"3003 N Mill Rd",
    "sg:city":"Vineland",
    "sg:classifiers":[
        {
            "category":"Professional",
            "subcategory":"Management & Consulting",
            "type":"Services"
        }
    ],
    "sg:phone":"+1 856 765 0725",
    "sg:postcode":"08360",
    "sg:province":"NJ",
    "sg:tags":[
        "export"
    ],
    "wof:name":"Elexus International",
    "wof:placetype":"venue"
},
  "geometry": {"coordinates":[-75.058064,39.530846],"type":"Point"}
}