{
  "type": "Feature",
  "properties": {
    "addr:full":"1505 Ocean Ave Pleasantville NJ 08232",
    "addr:housenumber":"1505",
    "addr:postcode":"08232",
    "addr:street":"Ocean Ave",
    "iso:country":"US",
    "sg:address":"1505 Ocean Ave",
    "sg:city":"Pleasantville",
    "sg:classifiers":[
        {
            "category":"Building & Trades",
            "subcategory":"Plumbing",
            "type":"Services"
        }
    ],
    "sg:phone":"+1 609 641 2046",
    "sg:postcode":"08232",
    "sg:province":"NJ",
    "sg:tags":[
        "contractor"
    ],
    "wof:name":"Leatherberrys Heating & Cooli",
    "wof:placetype":"venue"
},
  "geometry": {"coordinates":[-74.498582,39.412909],"type":"Point"}
}