{
  "type": "Feature",
  "properties": {
    "iso:country":"US",
    "sg:address":"39 Zinnia Dr",
    "sg:city":"Glenwood",
    "sg:classifiers":[
        {
            "category":"Building & Trades",
            "subcategory":"Electrical",
            "type":"Services"
        }
    ],
    "sg:phone":"+1 973 764 8840",
    "sg:postcode":"07418",
    "sg:province":"NJ",
    "sg:tags":[
        "electric",
        "contractor"
    ],
    "wof:name":"Arahill Electric",
    "wof:placetype":"venue"
},
  "geometry": {"coordinates":[-74.484752,41.235392],"type":"Point"}
}