{
  "type": "Feature",
  "properties": {
    "addr:full":"1409 Willowbrook Mall Wayne NJ 07470",
    "addr:housenumber":"1409",
    "addr:postcode":"07470",
    "addr:street":"Willowbrook Mall",
    "iso:country":"US",
    "sg:address":"1409 Willowbrook Mall",
    "sg:city":"Wayne",
    "sg:classifiers":[
        {
            "category":"Shopping",
            "subcategory":"Clothing, Apparel, & Fashions",
            "type":"Retail Goods"
        }
    ],
    "sg:phone":"+1   ",
    "sg:postcode":"07470",
    "sg:province":"NJ",
    "wof:name":"Dime-A-Shirt",
    "wof:placetype":"venue"
},
  "geometry": {"coordinates":[-74.255033,40.889689],"type":"Point"}
}