{
  "type": "Feature",
  "properties": {
    "addr:full":"200 Schuyler Ave North Arlington NJ 07031",
    "addr:housenumber":"200",
    "addr:postcode":"07031",
    "addr:street":"Schuyler Ave North",
    "iso:country":"US",
    "sg:address":"200 Schuyler Ave",
    "sg:city":"North Arlington",
    "sg:classifiers":[
        {
            "category":"Sports & Exercise",
            "subcategory":"Bowling",
            "type":"Entertainment"
        }
    ],
    "sg:phone":"+1 201 998 9621",
    "sg:postcode":"07031",
    "sg:province":"NJ",
    "sg:website":"www.nwbcontest.com/index.php?sit...",
    "wof:name":"New North Arlington Bowl",
    "wof:placetype":"venue"
},
  "geometry": {"coordinates":[-74.12509900000001,40.785198],"type":"Point"}
}