{
  "type": "Feature",
  "properties": {
    "iso:country":"US",
    "sg:address":"967 Lynnwood Ave",
    "sg:city":"Brick",
    "sg:classifiers":[
        {
            "category":"Manufacturing",
            "subcategory":"Apparel",
            "type":"Manufacturing & Wholesale Goods"
        }
    ],
    "sg:phone":"+1 732 920 2127",
    "sg:postcode":"08723",
    "sg:province":"NJ",
    "sg:tags":[
        "outerwear",
        "mfg"
    ],
    "wof:name":"Cheerables",
    "wof:placetype":"venue"
},
  "geometry": {"coordinates":[-74.138094,40.049951],"type":"Point"}
}