{
  "type": "Feature",
  "properties": {
    "iso:country":"US",
    "sg:address":"6101 Hadley Rd",
    "sg:city":"South Plainfield",
    "sg:classifiers":[
        {
            "category":"Personal",
            "subcategory":"Beauty Salon",
            "type":"Services"
        }
    ],
    "sg:phone":"+1 908 755 9787",
    "sg:postcode":"07080",
    "sg:province":"NJ",
    "sg:tags":[
        "shop"
    ],
    "wof:name":"Jolie Nails",
    "wof:placetype":"venue"
},
  "geometry": {"coordinates":[-74.426743,40.554707],"type":"Point"}
}