{
  "type": "Feature",
  "properties": {
    "addr:full":"19 Smith St Newark NJ 07106",
    "addr:housenumber":"19",
    "addr:postcode":"07106",
    "addr:street":"Smith St",
    "iso:country":"US",
    "sg:address":"19 Smith St",
    "sg:city":"Newark",
    "sg:classifiers":[
        {
            "category":"Organizations",
            "subcategory":"Religious Organization",
            "type":"Services"
        }
    ],
    "sg:phone":"+1 973 374 1008",
    "sg:postcode":"07106",
    "sg:province":"NJ",
    "sg:tags":[
        "church"
    ],
    "wof:name":"Divinity Baptist Life Center",
    "wof:placetype":"venue"
},
  "geometry": {"coordinates":[-74.229308,40.749683],"type":"Point"}
}