{
  "type": "Feature",
  "properties": {
    "addr:full":"81 Morris Ave Apt 45 Springfield NJ 07081",
    "addr:housenumber":"81;45",
    "addr:postcode":"07081",
    "addr:street":"Morris Ave Apt",
    "iso:country":"US",
    "sg:address":"81 Morris Ave Apt 45",
    "sg:city":"Springfield",
    "sg:classifiers":[
        {
            "category":"Building & Trades",
            "subcategory":"Plumbing",
            "type":"Services"
        }
    ],
    "sg:phone":"+1 973 376 6296",
    "sg:postcode":"07081",
    "sg:province":"NJ",
    "wof:name":"T C Plumbing & Heating",
    "wof:placetype":"venue"
},
  "geometry": {"coordinates":[-74.30502,40.709003],"type":"Point"}
}