{
  "type": "Feature",
  "properties": {
    "addr:full":"34 Old Tuckahoe Rd Marmora NJ 08223",
    "addr:housenumber":"34",
    "addr:postcode":"08223",
    "addr:street":"Old Tuckahoe Rd",
    "iso:country":"US",
    "sg:address":"34 Old Tuckahoe Rd",
    "sg:city":"Marmora",
    "sg:classifiers":[
        {
            "category":"Travel",
            "subcategory":"Travel Agent",
            "type":"Entertainment"
        }
    ],
    "sg:phone":"+1 609 390 9101",
    "sg:postcode":"08223",
    "sg:province":"NJ",
    "sg:tags":[
        "agency",
        "bureau"
    ],
    "wof:name":"Discovery Travel & Tours Inc",
    "wof:placetype":"venue"
},
  "geometry": {"coordinates":[-74.651027,39.267923],"type":"Point"}
}