{
  "type": "Feature",
  "properties": {
    "addr:full":"1162 Cooper St Deptford NJ 08096",
    "addr:housenumber":"1162",
    "addr:postcode":"08096",
    "addr:street":"Cooper St",
    "iso:country":"US",
    "sg:address":"1162 Cooper St",
    "sg:city":"Deptford",
    "sg:classifiers":[
        {
            "category":"Professional",
            "subcategory":"Accounting & Tax Preparation",
            "type":"Services"
        }
    ],
    "sg:phone":"+1 856 848 5545",
    "sg:postcode":"08096",
    "sg:province":"NJ",
    "sg:tags":[
        "accountant"
    ],
    "wof:name":"Dean W Cunningham CPA",
    "wof:placetype":"venue"
},
  "geometry": {"coordinates":[-75.118382,39.826335],"type":"Point"}
}