{
  "type": "Feature",
  "properties": {
    "iso:country":"US",
    "sg:address":"6 Twin Pointe Rd",
    "sg:city":"Flemington",
    "sg:classifiers":[
        {
            "category":"Building & Trades",
            "subcategory":"Construction",
            "type":"Services"
        }
    ],
    "sg:phone":"+1 908 237 0044",
    "sg:postcode":"08822",
    "sg:province":"NJ",
    "sg:tags":[
        "house"
    ],
    "wof:name":"House Doctors",
    "wof:placetype":"venue"
},
  "geometry": {"coordinates":[-74.83247299999999,40.489713],"type":"Point"}
}