{
  "type": "Feature",
  "properties": {
    "addr:full":"490 New Rd Linwood NJ 08221",
    "addr:housenumber":"490",
    "addr:postcode":"08221",
    "addr:street":"New Rd",
    "iso:country":"US",
    "sg:address":"490 New Rd",
    "sg:city":"Linwood",
    "sg:classifiers":[
        {
            "category":"Health Services",
            "subcategory":"Doctor",
            "type":"Services"
        }
    ],
    "sg:phone":"+1 609 927 8960",
    "sg:postcode":"08221",
    "sg:province":"NJ",
    "sg:tags":[
        "dentist"
    ],
    "wof:name":"David I Kalter DMD",
    "wof:placetype":"venue"
},
  "geometry": {"coordinates":[-74.57136199999999,39.356656],"type":"Point"}
}