{
  "type": "Feature",
  "properties": {
    "addr:full":"784 Chimney Rock Rd Martinsville NJ 08836",
    "addr:housenumber":"784",
    "addr:postcode":"08836",
    "addr:street":"Chimney Rock Rd",
    "iso:country":"US",
    "sg:address":"784 Chimney Rock Rd",
    "sg:city":"Martinsville",
    "sg:classifiers":[
        {
            "category":"Health Services",
            "subcategory":"Clinic",
            "type":"Services"
        },
        {
            "category":"Health Services",
            "subcategory":"Doctor",
            "type":"Services"
        }
    ],
    "sg:phone":"+1 732 271 1771",
    "sg:postcode":"08836",
    "sg:province":"NJ",
    "sg:tags":[
        "physician",
        "surgeon"
    ],
    "wof:name":"Martinsville Womens Health LLC",
    "wof:placetype":"venue"
},
  "geometry": {"coordinates":[-74.560688,40.597145],"type":"Point"}
}