{
  "type": "Feature",
  "properties": {
    "addr:full":"303 Maplewood Ave Clifton NJ 07013",
    "addr:housenumber":"303",
    "addr:postcode":"07013",
    "addr:street":"Maplewood Ave",
    "iso:country":"US",
    "sg:address":"303 Maplewood Ave",
    "sg:city":"Clifton",
    "sg:classifiers":[
        {
            "category":"Social Services",
            "subcategory":"Child Care",
            "type":"Services"
        }
    ],
    "sg:phone":"+1 973 523 7704",
    "sg:postcode":"07013",
    "sg:province":"NJ",
    "sg:tags":[
        "day"
    ],
    "wof:name":"Wee Care Child Care Center",
    "wof:placetype":"venue"
},
  "geometry": {"coordinates":[-74.174599,40.887001],"type":"Point"}
}