{
  "type": "Feature",
  "properties": {
    "iso:country":"US",
    "sg:address":"245 Pegasus Ave",
    "sg:city":"Northvale",
    "sg:classifiers":[
        {
            "category":"Manufacturing",
            "subcategory":"Metals",
            "type":"Manufacturing & Wholesale Goods"
        }
    ],
    "sg:phone":"+1 201 767 9051",
    "sg:postcode":"07647",
    "sg:province":"NJ",
    "sg:tags":[
        "joint",
        "expansion"
    ],
    "sg:website":"www.papcoindustries.com",
    "wof:name":"Papco Industries Inc",
    "wof:placetype":"venue"
},
  "geometry": {"coordinates":[-73.94341900000001,41.013566],"type":"Point"}
}