{
  "type": "Feature",
  "properties": {
    "iso:country":"US",
    "sg:address":"169 Paramus Rd",
    "sg:city":"Paramus",
    "sg:classifiers":[
        {
            "category":"Wholesale",
            "subcategory":"Non-durable Goods",
            "type":"Manufacturing & Wholesale Goods"
        }
    ],
    "sg:phone":"+1 201 368 2100",
    "sg:postcode":"07652",
    "sg:province":"NJ",
    "wof:name":"NJ Trade Develop Corp",
    "wof:placetype":"venue"
},
  "geometry": {"coordinates":[-74.091904,40.936602],"type":"Point"}
}