{
  "type": "Feature",
  "properties": {
    "iso:country":"US",
    "sg:address":"160 Summit Ave",
    "sg:city":"Montvale",
    "sg:classifiers":[
        {
            "category":"Professional",
            "subcategory":"Lawyer & Legal Services",
            "type":"Services"
        }
    ],
    "sg:phone":"+1 201 391 2775",
    "sg:postcode":"07645",
    "sg:province":"NJ",
    "sg:tags":[
        "attorney"
    ],
    "wof:name":"Janice Gatto",
    "wof:placetype":"venue"
},
  "geometry": {"coordinates":[-74.063142,41.058592],"type":"Point"}
}