{
  "type": "Feature",
  "properties": {
    "iso:country":"US",
    "sg:address":"127 Broad St.",
    "sg:city":"Palisades Park",
    "sg:classifiers":[
        {
            "category":"Restaurant",
            "type":"Food & Drink"
        }
    ],
    "sg:postcode":"07650",
    "sg:province":"NJ",
    "sg:tags":[
        "korean"
    ],
    "wof:name":"Mukeunji \u00a0Korean Restaurant",
    "wof:placetype":"venue"
},
  "geometry": {"coordinates":[-73.99995800000001,40.845048],"type":"Point"}
}