{
  "type": "Feature",
  "properties": {
    "addr:full":"3 Carman Rd Harrington Park NJ 07640",
    "addr:housenumber":"3",
    "addr:postcode":"07640",
    "addr:street":"Carman Rd",
    "iso:country":"US",
    "sg:address":"3 Carman Rd",
    "sg:city":"Harrington Park",
    "sg:classifiers":[
        {
            "category":"Wholesale",
            "subcategory":"Wine & Distilled Alcoholic Beverages",
            "type":"Manufacturing & Wholesale Goods"
        }
    ],
    "sg:phone":"+1 201 784 6800",
    "sg:postcode":"07640",
    "sg:province":"NJ",
    "sg:tags":[
        "wholesaling"
    ],
    "wof:name":"Signature Selections",
    "wof:placetype":"venue"
},
  "geometry": {"coordinates":[-73.978666,40.98433],"type":"Point"}
}