{
  "type": "Feature",
  "properties": {
    "addr:full":"1623 Church Rd Toms River NJ 08755",
    "addr:housenumber":"1623",
    "addr:postcode":"08755",
    "addr:street":"Church Rd",
    "iso:country":"US",
    "sg:address":"1623 Church Rd",
    "sg:city":"Toms River",
    "sg:classifiers":[
        {
            "category":"Building & Trades",
            "subcategory":"Construction",
            "type":"Services"
        }
    ],
    "sg:phone":"+1 732 240 6980",
    "sg:postcode":"08755",
    "sg:province":"NJ",
    "sg:tags":[
        "contractor"
    ],
    "wof:name":"Boyanowski Roofing & Siding",
    "wof:placetype":"venue"
},
  "geometry": {"coordinates":[-74.186837,40.015193],"type":"Point"}
}