{
  "type": "Feature",
  "properties": {
    "iso:country":"US",
    "sg:address":"17 S Davis St",
    "sg:city":"Woodbury",
    "sg:classifiers":[
        {
            "category":"Place Of Worship",
            "subcategory":"Church",
            "type":"Public Place"
        },
        {
            "category":"Place Of Worship",
            "type":"Public Place"
        }
    ],
    "sg:phone":"+1 856 384 0430",
    "sg:postcode":"08096",
    "sg:province":"NJ",
    "sg:tags":[
        "churches-interdenominational",
        "churches-various",
        "denomination"
    ],
    "sg:website":"http://www.ncfonline.org",
    "wof:name":"New Covenant Fellowship Church Of Nj, Inc",
    "wof:placetype":"venue"
},
  "geometry": {"coordinates":[-75.160061,39.84002],"type":"Point"}
}