{
  "type": "Feature",
  "properties": {
    "addr:full":"74 Ave A Atlantic Hghlnds NJ 07716",
    "addr:postcode":"07716",
    "addr:street":"74 Ave A;Hghlnds",
    "iso:country":"US",
    "sg:address":"74 Ave A",
    "sg:city":"Atlantic Hghlnds",
    "sg:classifiers":[
        {
            "category":"Manufacturing",
            "subcategory":"Signs",
            "type":"Manufacturing & Wholesale Goods"
        }
    ],
    "sg:phone":"+1 732 872 7842",
    "sg:postcode":"07716",
    "sg:province":"NJ",
    "wof:name":"Signs & Letters Unlimited",
    "wof:placetype":"venue"
},
  "geometry": {"coordinates":[-74.040284,40.414555],"type":"Point"}
}