{
  "type": "Feature",
  "properties": {
    "iso:country":"US",
    "sg:address":"276 Werimus Rd",
    "sg:city":"Woodcliff Lake",
    "sg:classifiers":[
        {
            "category":"Building & Trades",
            "subcategory":"Construction",
            "type":"Services"
        }
    ],
    "sg:phone":"+1 201 391 1885",
    "sg:postcode":"07677",
    "sg:province":"NJ",
    "sg:tags":[
        "concrete",
        "contractor"
    ],
    "wof:name":"Pearseco Construction Inc",
    "wof:placetype":"venue"
},
  "geometry": {"coordinates":[-74.066193,41.031176],"type":"Point"}
}