{
  "type": "Feature",
  "properties": {
    "iso:country":"US",
    "sg:address":"65 Clyde Rd",
    "sg:city":"Somerset",
    "sg:classifiers":[
        {
            "category":"Wholesale",
            "subcategory":"Apparel",
            "type":"Manufacturing & Wholesale Goods"
        }
    ],
    "sg:phone":"+1 732 873 4343",
    "sg:postcode":"08873",
    "sg:province":"NJ",
    "sg:tags":[
        "umbrella",
        "mfg"
    ],
    "wof:name":"Giant Umbrella",
    "wof:placetype":"venue"
},
  "geometry": {"coordinates":[-74.51223400000001,40.484365],"type":"Point"}
}