{
  "type": "Feature",
  "properties": {
    "iso:country":"US",
    "sg:address":"100 Wood Ave S",
    "sg:city":"Iselin",
    "sg:classifiers":[
        {
            "category":"Professional",
            "subcategory":"Lawyer & Legal Services",
            "type":"Services"
        }
    ],
    "sg:phone":"+1 732 635 0800",
    "sg:postcode":"08830",
    "sg:province":"NJ",
    "sg:website":"www.shahdesailaw.com",
    "wof:name":"Shahdesai PC",
    "wof:placetype":"venue"
},
  "geometry": {"coordinates":[-74.328553,40.56292],"type":"Point"}
}