{
  "type": "Feature",
  "properties": {
    "addr:full":"218 Woodlawn Ave Collingswood NJ 08108",
    "addr:housenumber":"218",
    "addr:postcode":"08108",
    "addr:street":"Woodlawn Ave",
    "iso:country":"US",
    "sg:address":"218 Woodlawn Ave",
    "sg:city":"Collingswood",
    "sg:classifiers":[
        {
            "category":"Building & Trades",
            "subcategory":"Construction",
            "type":"Services"
        }
    ],
    "sg:phone":"+1 856 854 1327",
    "sg:postcode":"08108",
    "sg:province":"NJ",
    "sg:tags":[
        "contractor"
    ],
    "wof:name":"Moodys Roofing & Siding",
    "wof:placetype":"venue"
},
  "geometry": {"coordinates":[-75.06677500000001,39.920535],"type":"Point"}
}