{
  "type": "Feature",
  "properties": {
    "iso:country":"US",
    "sg:address":"437 Raritan Ave",
    "sg:city":"Atco",
    "sg:classifiers":[
        {
            "category":"Building & Trades",
            "subcategory":"Landscaping Services",
            "type":"Services"
        }
    ],
    "sg:phone":"+1 856 768 4798",
    "sg:postcode":"08004",
    "sg:province":"NJ",
    "sg:tags":[
        "landscape",
        "contractor"
    ],
    "wof:name":"Anderson's Landscaping",
    "wof:placetype":"venue"
},
  "geometry": {"coordinates":[-74.88521900000001,39.767866],"type":"Point"}
}