{
  "type": "Feature",
  "properties": {
    "addr:full":"1033 Landis Ave Elmer NJ 08318",
    "addr:housenumber":"1033",
    "addr:postcode":"08318",
    "addr:street":"Landis Ave",
    "iso:country":"US",
    "sg:address":"1033 Landis Ave",
    "sg:city":"Elmer",
    "sg:classifiers":[
        {
            "category":"Shopping",
            "subcategory":"Used Merchandise",
            "type":"Retail Goods"
        }
    ],
    "sg:phone":"+1 856 692 2311",
    "sg:postcode":"08318",
    "sg:province":"NJ",
    "sg:tags":[
        "furniture"
    ],
    "wof:name":"E M Used Furniture",
    "wof:placetype":"venue"
},
  "geometry": {"coordinates":[-75.111006,39.488012],"type":"Point"}
}