{
  "type": "Feature",
  "properties": {
    "addr:full":"18 Witherspoon St Princeton NJ 08542",
    "addr:housenumber":"18",
    "addr:postcode":"08542",
    "addr:street":"Witherspoon St",
    "iso:country":"US",
    "sg:address":"18 Witherspoon St",
    "sg:city":"Princeton",
    "sg:classifiers":[
        {
            "category":"Fast Food",
            "type":"Food & Drink"
        },
        {
            "category":"Restaurant",
            "type":"Food & Drink"
        },
        {
            "category":"Food & Beverages",
            "subcategory":"Groceries & Convenience Stores",
            "type":"Retail Goods"
        }
    ],
    "sg:phone":"+1 609 924 5063",
    "sg:postcode":"08542",
    "sg:province":"NJ",
    "sg:tags":[
        "shop",
        "american",
        "sandwich",
        "take"
    ],
    "sg:website":"http://www.subway.com",
    "wof:name":"Subway",
    "wof:placetype":"venue"
},
  "geometry": {"coordinates":[-74.659992,40.35029],"type":"Point"}
}