{
  "type": "Feature",
  "properties": {
    "iso:country":"US",
    "sg:address":"92 Monroe St",
    "sg:city":"Garfield",
    "sg:classifiers":[
        {
            "category":"Education",
            "subcategory":"Vocational School",
            "type":"Public Place"
        }
    ],
    "sg:phone":"+1 973 471 4800",
    "sg:postcode":"07026",
    "sg:province":"NJ",
    "sg:tags":[
        "technical",
        "trade"
    ],
    "sg:website":"www.bccatschool.com",
    "wof:name":"Bergen County Career Training",
    "wof:placetype":"venue"
},
  "geometry": {"coordinates":[-74.10733500000001,40.86985],"type":"Point"}
}