{
  "type": "Feature",
  "properties": {
    "iso:country":"US",
    "sg:address":"105 Ave K",
    "sg:city":"Monroe Twp",
    "sg:classifiers":[
        {
            "category":"Wholesale",
            "subcategory":"Non-durable Goods",
            "type":"Manufacturing & Wholesale Goods"
        }
    ],
    "sg:phone":"+1 732 251 9926",
    "sg:postcode":"08831",
    "sg:province":"NJ",
    "sg:tags":[
        "specializing",
        "item",
        "musical",
        "gift",
        "candle"
    ],
    "wof:name":"Joy World Inc",
    "wof:placetype":"venue"
},
  "geometry": {"coordinates":[-74.40253,40.373873],"type":"Point"}
}