{
  "type": "Feature",
  "properties": {
    "addr:full":"715 US Hwy 206 Hillsborough NJ 08844",
    "addr:housenumber":"715",
    "addr:postcode":"08844",
    "addr:street":"Us Hwy 206",
    "iso:country":"US",
    "sg:address":"715 US Hwy 206",
    "sg:city":"Hillsborough",
    "sg:classifiers":[
        {
            "category":"Education",
            "subcategory":"Dance Studio",
            "type":"Public Place"
        }
    ],
    "sg:phone":"+1   ",
    "sg:postcode":"08844",
    "sg:province":"NJ",
    "wof:name":"Vestoff School of Dance Arts",
    "wof:placetype":"venue"
},
  "geometry": {"coordinates":[-74.649261,40.492038],"type":"Point"}
}