{
  "type": "Feature",
  "properties": {
    "addr:full":"117 Frances Ave Villas NJ 08251",
    "addr:housenumber":"117",
    "addr:postcode":"08251",
    "addr:street":"Frances Ave Villas",
    "iso:country":"US",
    "sg:address":"117 Frances Ave",
    "sg:city":"Villas",
    "sg:classifiers":[
        {
            "category":"Professional",
            "type":"Services"
        }
    ],
    "sg:phone":"+1   ",
    "sg:postcode":"08251",
    "sg:province":"NJ",
    "wof:name":"Marine Corps League",
    "wof:placetype":"venue"
},
  "geometry": {"coordinates":[-74.940337,39.023565],"type":"Point"}
}