{
  "type": "Feature",
  "properties": {
    "iso:country":"US",
    "sg:address":"30 Howe Ave",
    "sg:city":"Passaic",
    "sg:classifiers":[
        {
            "category":"Retail",
            "subcategory":"Repair Shop",
            "type":"Services"
        }
    ],
    "sg:phone":"+1 973 777 5333",
    "sg:postcode":"07055",
    "sg:province":"NJ",
    "sg:tags":[
        "equipment",
        "medical"
    ],
    "wof:name":"Resource Trading",
    "wof:placetype":"venue"
},
  "geometry": {"coordinates":[-74.130589,40.860989],"type":"Point"}
}