{
  "type": "Feature",
  "properties": {
    "addr:full":"103 Bayard St New Brunswick NJ 08901",
    "addr:housenumber":"103",
    "addr:postcode":"08901",
    "addr:street":"Bayard St",
    "iso:country":"US",
    "sg:address":"103 Bayard St",
    "sg:city":"New Brunswick",
    "sg:classifiers":[
        {
            "category":"Professional",
            "subcategory":"Lawyer & Legal Services",
            "type":"Services"
        }
    ],
    "sg:phone":"+1 732 247 1212",
    "sg:postcode":"08901",
    "sg:province":"NJ",
    "wof:name":"Arzadi Karim",
    "wof:placetype":"venue"
},
  "geometry": {"coordinates":[-74.44651,40.494008],"type":"Point"}
}