{
  "type": "Feature",
  "properties": {
    "addr:full":"303 Omni Dr Hillsborough NJ 08844",
    "addr:housenumber":"303",
    "addr:postcode":"08844",
    "addr:street":"Omni Dr",
    "iso:country":"US",
    "sg:address":"303 Omni Dr",
    "sg:city":"Hillsborough",
    "sg:classifiers":[
        {
            "category":"Health Services",
            "subcategory":"Chiropractor",
            "type":"Services"
        }
    ],
    "sg:phone":"+1 908 359 0123",
    "sg:postcode":"08844",
    "sg:province":"NJ",
    "wof:name":"Family Chiropractic Clinic",
    "wof:placetype":"venue"
},
  "geometry": {"coordinates":[-74.629071,40.524378],"type":"Point"}
}