{
  "type": "Feature",
  "properties": {
    "addr:full":"21 Chestnut St Emerson NJ 07630",
    "addr:housenumber":"21",
    "addr:postcode":"07630",
    "addr:street":"Chestnut St",
    "iso:country":"US",
    "sg:address":"21 Chestnut St",
    "sg:city":"Emerson",
    "sg:classifiers":[
        {
            "category":"Retail",
            "subcategory":"Repair Shop",
            "type":"Services"
        }
    ],
    "sg:phone":"+1 877 379 3394",
    "sg:postcode":"07630",
    "sg:province":"NJ",
    "sg:tags":[
        "small",
        "major",
        "appliance",
        "refinishing"
    ],
    "sg:website":"http://local.ingenio.com/Listings/Details.aspx?NUM=a%3a10116125%3a13%3a4859924%3a14%3a0%3a7",
    "wof:name":"Certified Refrigeration",
    "wof:placetype":"venue"
},
  "geometry": {"coordinates":[-74.02564,40.979384],"type":"Point"}
}