{
  "type": "Feature",
  "properties": {
    "iso:country":"US",
    "sg:address":"683 Springfield Ave",
    "sg:city":"Newark",
    "sg:classifiers":[
        {
            "category":"Food & Beverages",
            "subcategory":"Ethnic Foods",
            "type":"Retail Goods"
        }
    ],
    "sg:phone":"+1 973 991 0156",
    "sg:postcode":"07103",
    "sg:province":"NJ",
    "sg:tags":[
        "soul"
    ],
    "wof:name":"Soul Food Factory",
    "wof:placetype":"venue"
},
  "geometry": {"coordinates":[-74.21249899999999,40.729842],"type":"Point"}
}