{
  "type": "Feature",
  "properties": {
    "addr:full":"4 Surrey Ln Asbury NJ 08859",
    "addr:housenumber":"4",
    "addr:postcode":"08859",
    "addr:street":"Surrey Ln",
    "iso:country":"US",
    "sg:address":"4 Surrey Ln",
    "sg:city":"Asbury",
    "sg:classifiers":[
        {
            "category":"Building & Trades",
            "subcategory":"Construction",
            "type":"Services"
        }
    ],
    "sg:phone":"+1 908 238 9451",
    "sg:postcode":"08859",
    "sg:province":"NJ",
    "sg:tags":[
        "home",
        "builder"
    ],
    "wof:name":"Ryan Homes",
    "wof:placetype":"venue"
},
  "geometry": {"coordinates":[-74.300156,40.474922],"type":"Point"}
}