{
  "type": "Feature",
  "properties": {
    "addr:full":"204 Newark Pompton Tpke Pequannock NJ 07440",
    "addr:housenumber":"204",
    "addr:postcode":"07440",
    "addr:street":"Newark Pompton Tpke",
    "iso:country":"US",
    "sg:address":"204 Newark Pompton Tpke",
    "sg:city":"Pequannock",
    "sg:classifiers":[
        {
            "category":"Personal",
            "subcategory":"Barber",
            "type":"Services"
        }
    ],
    "sg:phone":"+1 973 694 8827",
    "sg:postcode":"07440",
    "sg:province":"NJ",
    "wof:name":"Pequannock Barber Shop",
    "wof:placetype":"venue"
},
  "geometry": {"coordinates":[-74.290001,40.947701],"type":"Point"}
}