{
  "type": "Feature",
  "properties": {
    "iso:country":"US",
    "sg:address":"307 Audubon Ave",
    "sg:city":"Thorofare",
    "sg:classifiers":[
        {
            "category":"Professional",
            "type":"Services"
        }
    ],
    "sg:phone":"+1   ",
    "sg:postcode":"08086",
    "sg:province":"NJ",
    "wof:name":"Shiny Spigots",
    "wof:placetype":"venue"
},
  "geometry": {"coordinates":[-75.185338,39.850485],"type":"Point"}
}