{
  "type": "Feature",
  "properties": {
    "iso:country":"US",
    "sg:address":"261 James St Ste 2Er",
    "sg:city":"Morristown",
    "sg:classifiers":[
        {
            "category":"Health Services",
            "subcategory":"Doctor",
            "type":"Services"
        }
    ],
    "sg:phone":"+1 973 540 1656",
    "sg:postcode":"07960",
    "sg:province":"NJ",
    "wof:name":"Taylor Clifford A Dr",
    "wof:placetype":"venue"
},
  "geometry": {"coordinates":[-74.481488,40.770256],"type":"Point"}
}