{
  "type": "Feature",
  "properties": {
    "iso:country":"US",
    "sg:address":"479 Tennent Rd",
    "sg:city":"Morganville",
    "sg:classifiers":[
        {
            "category":"Building & Trades",
            "subcategory":"Landscaping Services",
            "type":"Services"
        }
    ],
    "sg:phone":"+1 732 617 1127",
    "sg:postcode":"07751",
    "sg:province":"NJ",
    "wof:name":"Egs & D Inc",
    "wof:placetype":"venue"
},
  "geometry": {"coordinates":[-74.295906,40.333856],"type":"Point"}
}