{
  "type": "Feature",
  "properties": {
    "iso:country":"US",
    "sg:address":"17 Jernee Mill Rd",
    "sg:city":"Sayreville",
    "sg:classifiers":[
        {
            "category":"Building & Trades",
            "subcategory":"Construction",
            "type":"Services"
        }
    ],
    "sg:phone":"+1 732 254 1983",
    "sg:postcode":"08872",
    "sg:province":"NJ",
    "sg:tags":[
        "general",
        "contractor"
    ],
    "wof:name":"Black Oak Construction Inc",
    "wof:placetype":"venue"
},
  "geometry": {"coordinates":[-74.366585,40.454332],"type":"Point"}
}