{
  "type": "Feature",
  "properties": {
    "addr:full":"457 Piermont Rd Cresskill NJ 07626",
    "addr:housenumber":"457",
    "addr:postcode":"07626",
    "addr:street":"Piermont Rd",
    "iso:country":"US",
    "sg:address":"457 Piermont Rd",
    "sg:city":"Cresskill",
    "sg:classifiers":[
        {
            "category":"Professional",
            "subcategory":"Business Services",
            "type":"Services"
        }
    ],
    "sg:phone":"+1   ",
    "sg:postcode":"07626",
    "sg:province":"NJ",
    "wof:name":"Natalex Design Inc",
    "wof:placetype":"venue"
},
  "geometry": {"coordinates":[-73.961555,40.951127],"type":"Point"}
}