{
  "type": "Feature",
  "properties": {
    "addr:full":"100 Route 73 N Palmyra NJ 08065",
    "addr:housenumber":"100",
    "addr:postcode":"08065",
    "addr:street":"Route 73 N",
    "iso:country":"US",
    "sg:address":"100 Route 73 N",
    "sg:city":"Palmyra",
    "sg:phone":"+1 630 230 1215",
    "sg:postcode":"08065",
    "sg:province":"NJ",
    "sg:website":"http://national.citysearch.com/profile/external/604179222/palmyra_nj/f_c_kerbeck_maserati.html?publisher=yellowpages&reference_id=1&placement=ypwebsitemip",
    "wof:name":"F.C. Kerbeck Maserati",
    "wof:placetype":"venue"
},
  "geometry": {"coordinates":[-75.036209,40.00079],"type":"Point"}
}