{
  "type": "Feature",
  "properties": {
    "addr:full":"35 W Demarest Ave Englewood NJ 07631",
    "addr:housenumber":"35",
    "addr:postcode":"07631",
    "addr:street":"W Demarest Ave",
    "iso:country":"US",
    "sg:address":"35 W Demarest Ave",
    "sg:city":"Englewood",
    "sg:classifiers":[
        {
            "category":"Retail",
            "subcategory":"Repair Shop",
            "type":"Services"
        }
    ],
    "sg:phone":"+1 201 526 2318",
    "sg:postcode":"07631",
    "sg:province":"NJ",
    "sg:tags":[
        "lock",
        "locksmith"
    ],
    "wof:name":"1 Emergency Locksmith 24 Hour",
    "wof:placetype":"venue"
},
  "geometry": {"coordinates":[-73.97392000000001,40.898224],"type":"Point"}
}