{
  "type": "Feature",
  "properties": {
    "addr:full":"5505 Marlton Pike Pennsauken NJ 08109",
    "addr:housenumber":"5505",
    "addr:postcode":"08109",
    "addr:street":"Marlton Pike",
    "iso:country":"US",
    "sg:address":"5505 Marlton Pike",
    "sg:city":"Pennsauken",
    "sg:classifiers":[
        {
            "category":"Professional",
            "subcategory":"Lawyer & Legal Services",
            "type":"Services"
        }
    ],
    "sg:phone":"+1 856 910 9360",
    "sg:postcode":"08109",
    "sg:province":"NJ",
    "wof:name":"Ulmer Karen A PC",
    "wof:placetype":"venue"
},
  "geometry": {"coordinates":[-75.06210299999999,39.931198],"type":"Point"}
}