{
  "type": "Feature",
  "properties": {
    "addr:full":"314 Washington St Newark NJ 07102",
    "addr:housenumber":"314",
    "addr:postcode":"07102",
    "addr:street":"Washington St",
    "iso:country":"US",
    "sg:address":"314 Washington St",
    "sg:city":"Newark",
    "sg:classifiers":[
        {
            "category":"Shopping",
            "subcategory":"Clothing, Apparel, & Fashions",
            "type":"Retail Goods"
        }
    ],
    "sg:phone":"+1 973 242 4224",
    "sg:postcode":"07102",
    "sg:province":"NJ",
    "wof:name":"Unity Hustelers",
    "wof:placetype":"venue"
},
  "geometry": {"coordinates":[-74.176107,40.734652],"type":"Point"}
}