{
  "type": "Feature",
  "properties": {
    "iso:country":"US",
    "sg:address":"640 Belmont Ave",
    "sg:city":"Haledon",
    "sg:classifiers":[
        {
            "category":"Freight",
            "type":"Transportation"
        }
    ],
    "sg:phone":"+1 973 942 8217",
    "sg:postcode":"07508",
    "sg:province":"NJ",
    "sg:tags":[
        "operator",
        "local",
        "trucking"
    ],
    "wof:name":"Baghs Trucking",
    "wof:placetype":"venue"
},
  "geometry": {"coordinates":[-74.185181,40.941783],"type":"Point"}
}