{
  "type": "Feature",
  "properties": {
    "iso:country":"US",
    "sg:address":"31 Leroy Pl",
    "sg:city":"Red Bank",
    "sg:classifiers":[
        {
            "category":"Professional",
            "subcategory":"Lawyer & Legal Services",
            "type":"Services"
        }
    ],
    "sg:phone":"+1 732 345 0100",
    "sg:postcode":"07701",
    "sg:province":"NJ",
    "sg:tags":[
        "attorney"
    ],
    "wof:name":"Jerry V Leaphart & Assoc",
    "wof:placetype":"venue"
},
  "geometry": {"coordinates":[-74.06746200000001,40.345743],"type":"Point"}
}