{
  "type": "Feature",
  "properties": {
    "iso:country":"US",
    "sg:address":"313 Robbins Ave",
    "sg:city":"Trenton",
    "sg:classifiers":[
        {
            "category":"Building & Trades",
            "subcategory":"Construction",
            "type":"Services"
        }
    ],
    "sg:phone":"+1 609 406 0085",
    "sg:postcode":"08638",
    "sg:province":"NJ",
    "sg:tags":[
        "general",
        "contractor"
    ],
    "wof:name":"Morency Construction Co",
    "wof:placetype":"venue"
},
  "geometry": {"coordinates":[-74.765421,40.241924],"type":"Point"}
}