{
  "type": "Feature",
  "properties": {
    "iso:country":"US",
    "sg:address":"813 Princess Ave",
    "sg:city":"Camden",
    "sg:classifiers":[
        {
            "category":"Manufacturing",
            "subcategory":"Metals",
            "type":"Manufacturing & Wholesale Goods"
        }
    ],
    "sg:phone":"+1 856 338 0707",
    "sg:postcode":"08103",
    "sg:province":"NJ",
    "sg:tags":[
        "fabricator"
    ],
    "wof:name":"R & R Metal Fabricators Inc",
    "wof:placetype":"venue"
},
  "geometry": {"coordinates":[-75.10801499999999,39.936295],"type":"Point"}
}