{
  "type": "Feature",
  "properties": {
    "iso:country":"US",
    "sg:address":"175 Beaverbrook Rd",
    "sg:city":"Lincoln Park",
    "sg:classifiers":[
        {
            "category":"Shopping",
            "subcategory":"Bicycles & Sporting Goods",
            "type":"Retail Goods"
        }
    ],
    "sg:phone":"+1 973 696 9199",
    "sg:postcode":"07035",
    "sg:province":"NJ",
    "wof:name":"The Sports Factory",
    "wof:placetype":"venue"
},
  "geometry": {"coordinates":[-74.31364000000001,40.933229],"type":"Point"}
}