{
  "type": "Feature",
  "properties": {
    "iso:country":"US",
    "sg:address":"1104 Arnold Ave",
    "sg:city":"Pt Pleasant Bch",
    "sg:classifiers":[
        {
            "category":"Real Estate",
            "subcategory":"Real Estate Agent",
            "type":"Services"
        }
    ],
    "sg:phone":"+1 732 701 0170",
    "sg:postcode":"08742",
    "sg:province":"NJ",
    "sg:tags":[
        "appraiser"
    ],
    "wof:name":"Hogan Appraisal LLC",
    "wof:placetype":"venue"
},
  "geometry": {"coordinates":[-74.062781,40.085561],"type":"Point"}
}