{
  "type": "Feature",
  "properties": {
    "addr:full":"1130 Somerset St New Brunswick NJ 08901",
    "addr:housenumber":"1130",
    "addr:postcode":"08901",
    "addr:street":"Somerset St",
    "iso:country":"US",
    "sg:address":"1130 Somerset St",
    "sg:city":"New Brunswick",
    "sg:classifiers":[
        {
            "category":"Professional",
            "type":"Services"
        }
    ],
    "sg:phone":"+1 732 249 8162",
    "sg:postcode":"08901",
    "sg:province":"NJ",
    "sg:tags":[
        "establishment"
    ],
    "wof:name":"AMP Inc",
    "wof:placetype":"venue"
},
  "geometry": {"coordinates":[-74.45984900000001,40.490974],"type":"Point"}
}