{
  "type": "Feature",
  "properties": {
    "addr:full":"1970 Old Cuthbert Rd Cherry Hill NJ 08034",
    "addr:housenumber":"1970",
    "addr:postcode":"08034",
    "addr:street":"Old Cuthbert Rd",
    "iso:country":"US",
    "sg:address":"1970 Old Cuthbert Rd",
    "sg:city":"Cherry Hill",
    "sg:classifiers":[
        {
            "category":"Professional",
            "subcategory":"Business Services",
            "type":"Services"
        }
    ],
    "sg:phone":"+1 856 616 1007",
    "sg:postcode":"08034",
    "sg:province":"NJ",
    "sg:tags":[
        "packaging"
    ],
    "wof:name":"Liberty Ribbon & Packaging",
    "wof:placetype":"venue"
},
  "geometry": {"coordinates":[-74.97281700000001,39.918775],"type":"Point"}
}