{
  "type": "Feature",
  "properties": {
    "addr:full":"7 Glen Ridge Dr Long Valley NJ 07853",
    "addr:housenumber":"7",
    "addr:postcode":"07853",
    "addr:street":"Glen Ridge Dr",
    "iso:country":"US",
    "sg:address":"7 Glen Ridge Dr",
    "sg:city":"Long Valley",
    "sg:classifiers":[
        {
            "category":"Building & Trades",
            "subcategory":"Construction",
            "type":"Services"
        }
    ],
    "sg:phone":"+1 908 684 1188",
    "sg:postcode":"07853",
    "sg:province":"NJ",
    "sg:tags":[
        "house"
    ],
    "wof:name":"Olde School Home Improvement",
    "wof:placetype":"venue"
},
  "geometry": {"coordinates":[-74.826708,40.791786],"type":"Point"}
}