{
  "type": "Feature",
  "properties": {
    "addr:full":"6 Broadway Fair Lawn NJ 07410",
    "addr:housenumber":"6",
    "addr:postcode":"07410",
    "addr:street":"Broadway",
    "iso:country":"US",
    "sg:address":"6 Broadway",
    "sg:city":"Fair Lawn",
    "sg:classifiers":[
        {
            "category":"Freight",
            "type":"Transportation"
        }
    ],
    "sg:phone":"+1 201 475 7878",
    "sg:postcode":"07410",
    "sg:province":"NJ",
    "sg:tags":[
        "mover"
    ],
    "wof:name":"All Star Moving & Storage",
    "wof:placetype":"venue"
},
  "geometry": {"coordinates":[-74.121326,40.920178],"type":"Point"}
}