{
  "type": "Feature",
  "properties": {
    "addr:full":"35 Coral Dr Hazlet NJ 07730",
    "addr:housenumber":"35",
    "addr:postcode":"07730",
    "addr:street":"Coral Dr",
    "iso:country":"US",
    "sg:address":"35 Coral Dr",
    "sg:city":"Hazlet",
    "sg:classifiers":[
        {
            "category":"Professional",
            "type":"Services"
        }
    ],
    "sg:phone":"+1   ",
    "sg:postcode":"07730",
    "sg:province":"NJ",
    "wof:name":"National Society of Tole",
    "wof:placetype":"venue"
},
  "geometry": {"coordinates":[-74.204712,40.420318],"type":"Point"}
}