{
  "type": "Feature",
  "properties": {
    "addr:full":"124 Hickory Rd Marlton NJ 08053",
    "addr:housenumber":"124",
    "addr:postcode":"08053",
    "addr:street":"Hickory Rd",
    "iso:country":"US",
    "sg:address":"124 Hickory Rd",
    "sg:city":"Marlton",
    "sg:classifiers":[
        {
            "category":"Home & Garden",
            "subcategory":"Home Furnishings",
            "type":"Retail Goods"
        }
    ],
    "sg:phone":"+1 856 768 4585",
    "sg:postcode":"08053",
    "sg:province":"NJ",
    "wof:name":"5 GS",
    "wof:placetype":"venue"
},
  "geometry": {"coordinates":[-74.89606499999999,39.80132],"type":"Point"}
}