{
  "type": "Feature",
  "properties": {
    "iso:country":"US",
    "sg:address":"65 Amelia Cir",
    "sg:city":"Little Silver",
    "sg:classifiers":[
        {
            "category":"Building & Trades",
            "subcategory":"Construction",
            "type":"Services"
        }
    ],
    "sg:phone":"+1 732 933 4708",
    "sg:postcode":"07739",
    "sg:province":"NJ",
    "sg:tags":[
        "house"
    ],
    "wof:name":"Sandy Hook Builders",
    "wof:placetype":"venue"
},
  "geometry": {"coordinates":[-74.044394,40.334825],"type":"Point"}
}