{
  "type": "Feature",
  "properties": {
    "iso:country":"US",
    "sg:address":"1695 Oak St",
    "sg:city":"Lakewood",
    "sg:classifiers":[
        {
            "category":"Shopping",
            "subcategory":"Books",
            "type":"Retail Goods"
        }
    ],
    "sg:phone":"+1 212 227 4060",
    "sg:postcode":"08701",
    "sg:province":"NJ",
    "sg:tags":[
        "dealer"
    ],
    "wof:name":"Book Club Customer Svce Ctr",
    "wof:placetype":"venue"
},
  "geometry": {"coordinates":[-74.18997899999999,40.059983],"type":"Point"}
}