{
  "type": "Feature",
  "properties": {
    "iso:country":"US",
    "sg:address":"404 Peacock St",
    "sg:city":"Paulsboro",
    "sg:classifiers":[
        {
            "category":"Local Transit",
            "type":"Transportation"
        }
    ],
    "sg:phone":"+1 856 224 9911",
    "sg:postcode":"08066",
    "sg:province":"NJ",
    "sg:tags":[
        "passenger"
    ],
    "wof:name":"All In One Transportation",
    "wof:placetype":"venue"
},
  "geometry": {"coordinates":[-75.221797,39.833673],"type":"Point"}
}