{
  "type": "Feature",
  "properties": {
    "iso:country":"US",
    "sg:address":"71 Woodthrush Trl W",
    "sg:city":"Medford",
    "sg:classifiers":[
        {
            "category":"Shopping",
            "type":"Retail Goods"
        }
    ],
    "sg:phone":"+1   ",
    "sg:postcode":"08055",
    "sg:province":"NJ",
    "sg:tags":[
        "merchandise"
    ],
    "wof:name":"All Through House",
    "wof:placetype":"venue"
},
  "geometry": {"coordinates":[-74.846778,39.857513],"type":"Point"}
}