{
  "type": "Feature",
  "properties": {
    "iso:country":"US",
    "sg:address":"187 Newark Ave",
    "sg:city":"Jersey City",
    "sg:classifiers":[
        {
            "category":"Food & Beverages",
            "subcategory":"Groceries & Convenience Stores",
            "type":"Retail Goods"
        }
    ],
    "sg:phone":"+1 201 433 7942",
    "sg:postcode":"07302",
    "sg:province":"NJ",
    "sg:tags":[
        "grocer",
        "sandwich"
    ],
    "wof:name":"The City Deli & Grocery",
    "wof:placetype":"venue"
},
  "geometry": {"coordinates":[-74.045655,40.721215],"type":"Point"}
}