{
  "type": "Feature",
  "properties": {
    "addr:full":"2025 State Rte 34 Belmar NJ 07719",
    "addr:housenumber":"2025",
    "addr:postcode":"07719",
    "addr:street":"State Rte 34",
    "iso:country":"US",
    "sg:address":"2025 State Rte 34",
    "sg:city":"Belmar",
    "sg:classifiers":[
        {
            "category":"Retail",
            "subcategory":"Auto Rental",
            "type":"Services"
        }
    ],
    "sg:phone":"+1 732 449 0010",
    "sg:postcode":"07719",
    "sg:province":"NJ",
    "sg:tags":[
        "truck"
    ],
    "wof:name":"Budget Rent-A-Car",
    "wof:placetype":"venue"
},
  "geometry": {"coordinates":[-74.20379800000001,40.374467],"type":"Point"}
}