{
  "type": "Feature",
  "properties": {
    "addr:full":"308 Almonesson Rd Blackwood NJ 08012",
    "addr:housenumber":"308",
    "addr:postcode":"08012",
    "addr:street":"Almonesson Rd",
    "iso:country":"US",
    "sg:address":"308 Almonesson Rd",
    "sg:city":"Blackwood",
    "sg:classifiers":[
        {
            "category":"Building & Trades",
            "subcategory":"Electrical",
            "type":"Services"
        }
    ],
    "sg:phone":"+1 856 228 6970",
    "sg:postcode":"08012",
    "sg:province":"NJ",
    "sg:tags":[
        "lighting",
        "fixture",
        "contractor"
    ],
    "sg:website":"http://www.rubanelectricalcontractors.com",
    "wof:name":"Ruban Electrical Contractors Inc",
    "wof:placetype":"venue"
},
  "geometry": {"coordinates":[-75.074268,39.811481],"type":"Point"}
}