{
  "type": "Feature",
  "properties": {
    "iso:country":"US",
    "sg:address":"26 E Main St",
    "sg:city":"Ramsey",
    "sg:classifiers":[
        {
            "category":"Recreation",
            "type":"Entertainment"
        }
    ],
    "sg:phone":"+1   ",
    "sg:postcode":"07446",
    "sg:province":"NJ",
    "sg:tags":[
        "amusement"
    ],
    "wof:name":"Pan Amrcan Tae Kwon Do Fdrtion",
    "wof:placetype":"venue"
},
  "geometry": {"coordinates":[-74.142145,41.057294],"type":"Point"}
}