{
  "type": "Feature",
  "properties": {
    "iso:country":"US",
    "sg:address":"11 Campus Dr",
    "sg:city":"Burlington",
    "sg:classifiers":[
        {
            "category":"Wholesale",
            "subcategory":"Groceries",
            "type":"Manufacturing & Wholesale Goods"
        }
    ],
    "sg:phone":"+1 609 387 3040",
    "sg:postcode":"08016",
    "sg:province":"NJ",
    "sg:tags":[
        "food",
        "snack"
    ],
    "wof:name":"Frito-Lay",
    "wof:placetype":"venue"
},
  "geometry": {"coordinates":[-74.879497,40.057482],"type":"Point"}
}