{
  "type": "Feature",
  "properties": {
    "iso:country":"US",
    "sg:address":"1507 Saint Georges Ave",
    "sg:city":"Rahway",
    "sg:classifiers":[
        {
            "category":"Health Services",
            "subcategory":"Doctor",
            "type":"Services"
        }
    ],
    "sg:phone":"+1 732 382 2177",
    "sg:postcode":"07065",
    "sg:province":"NJ",
    "sg:tags":[
        "cardiologist"
    ],
    "wof:name":"Cholankeril Mathew MD",
    "wof:placetype":"venue"
},
  "geometry": {"coordinates":[-74.28589599999999,40.614601],"type":"Point"}
}