{
  "type": "Feature",
  "properties": {
    "addr:full":"330 Wall St Princeton NJ 08540",
    "addr:housenumber":"330",
    "addr:postcode":"08540",
    "addr:street":"Wall St",
    "iso:country":"US",
    "sg:address":"330 Wall St",
    "sg:city":"Princeton",
    "sg:classifiers":[
        {
            "category":"Banks & Credit Unions",
            "subcategory":"Bank",
            "type":"Services"
        }
    ],
    "sg:phone":"+1 609 688 6800",
    "sg:postcode":"08540",
    "sg:province":"NJ",
    "sg:tags":[
        "loan",
        "real estate"
    ],
    "wof:name":"Allied Home Mortgage Capital",
    "wof:placetype":"venue"
},
  "geometry": {"coordinates":[-74.65067500000001,40.396641],"type":"Point"}
}