{
  "type": "Feature",
  "properties": {
    "addr:full":"11 Homer St Clifton NJ 07014",
    "addr:housenumber":"11",
    "addr:postcode":"07014",
    "addr:street":"Homer St",
    "iso:country":"US",
    "sg:address":"11 Homer St",
    "sg:city":"Clifton",
    "sg:classifiers":[
        {
            "category":"Building & Trades",
            "subcategory":"Plumbing",
            "type":"Services"
        }
    ],
    "sg:phone":"+1 973 249 8066",
    "sg:postcode":"07014",
    "sg:province":"NJ",
    "sg:tags":[
        "contractor"
    ],
    "wof:name":"Air Conditioning By Ross",
    "wof:placetype":"venue"
},
  "geometry": {"coordinates":[-74.136458,40.836517],"type":"Point"}
}