{
  "type": "Feature",
  "properties": {
    "addr:full":"Mountain View Rd Washington NJ 07882",
    "addr:postcode":"07882",
    "addr:street":"Mountain View Rd",
    "iso:country":"US",
    "sg:address":"Mountain View Rd",
    "sg:city":"Washington",
    "sg:classifiers":[
        {
            "category":"Landmark",
            "subcategory":"Tourist Information",
            "type":"Public Place"
        }
    ],
    "sg:phone":"+1 908 689 0971",
    "sg:postcode":"07882",
    "sg:province":"NJ",
    "sg:tags":[
        "tour"
    ],
    "wof:name":"Blue Army Tours",
    "wof:placetype":"venue"
},
  "geometry": {"coordinates":[-74.981201,40.759102],"type":"Point"}
}