{
  "type": "Feature",
  "properties": {
    "addr:full":"43 Roseberry Ct Deptford NJ 08096",
    "addr:housenumber":"43",
    "addr:postcode":"08096",
    "addr:street":"Roseberry Ct",
    "iso:country":"US",
    "sg:address":"43 Roseberry Ct",
    "sg:city":"Deptford",
    "sg:classifiers":[
        {
            "category":"Building & Trades",
            "subcategory":"Construction",
            "type":"Services"
        }
    ],
    "sg:phone":"+1 856 232 1605",
    "sg:postcode":"08096",
    "sg:province":"NJ",
    "sg:tags":[
        "sewer",
        "contractor"
    ],
    "wof:name":"Drain Visions",
    "wof:placetype":"venue"
},
  "geometry": {"coordinates":[-75.131502,39.82644],"type":"Point"}
}