{
  "type": "Feature",
  "properties": {
    "addr:full":"625 E Palisade Ave Englewood Cliffs NJ 07632",
    "addr:housenumber":"625",
    "addr:postcode":"07632",
    "addr:street":"E Palisade Ave",
    "iso:country":"US",
    "sg:address":"625 E Palisade Ave",
    "sg:city":"Englewood Cliffs",
    "sg:classifiers":[
        {
            "category":"Building & Trades",
            "subcategory":"Construction",
            "type":"Services"
        }
    ],
    "sg:phone":"+1 201 567 3781",
    "sg:postcode":"07632",
    "sg:province":"NJ",
    "sg:tags":[
        "contractor"
    ],
    "wof:name":"FSS Developers Inc",
    "wof:placetype":"venue"
},
  "geometry": {"coordinates":[-73.955234,40.883096],"type":"Point"}
}