{
  "type": "Feature",
  "properties": {
    "iso:country":"US",
    "sg:address":"25 Le Grande Ter",
    "sg:city":"Wayne",
    "sg:classifiers":[
        {
            "category":"Organizations",
            "subcategory":"Religious Organization",
            "type":"Services"
        }
    ],
    "sg:phone":"+1   ",
    "sg:postcode":"07470",
    "sg:province":"NJ",
    "wof:name":"David F Harwood Rev",
    "wof:placetype":"venue"
},
  "geometry": {"coordinates":[-74.25830000000001,40.916782],"type":"Point"}
}