{
  "type": "Feature",
  "properties": {
    "addr:full":"14 S Orange Ave South Orange NJ 07079",
    "addr:housenumber":"14",
    "addr:postcode":"07079",
    "addr:street":"S Orange Ave",
    "iso:country":"US",
    "sg:address":"14 S Orange Ave",
    "sg:city":"South Orange",
    "sg:classifiers":[
        {
            "category":"Retail",
            "subcategory":"Repair Shop",
            "type":"Services"
        }
    ],
    "sg:phone":"+1 973 854 5066",
    "sg:postcode":"07079",
    "sg:province":"NJ",
    "sg:tags":[
        "lock",
        "locksmith"
    ],
    "wof:name":"24 Hour 7 Day Emergency",
    "wof:placetype":"venue"
},
  "geometry": {"coordinates":[-74.258546,40.745818],"type":"Point"}
}