{
  "type": "Feature",
  "properties": {
    "addr:full":"78 E Main St Moorestown NJ 08057",
    "addr:housenumber":"78",
    "addr:postcode":"08057",
    "addr:street":"E Main St",
    "iso:country":"US",
    "sg:address":"78 E Main St",
    "sg:city":"Moorestown",
    "sg:classifiers":[
        {
            "category":"Retail",
            "subcategory":"Funeral Services",
            "type":"Services"
        }
    ],
    "sg:phone":"+1 856 235 0009",
    "sg:postcode":"08057",
    "sg:province":"NJ",
    "sg:tags":[
        "director",
        "home"
    ],
    "wof:name":"Lewis Funeral Home Inc",
    "wof:placetype":"venue"
},
  "geometry": {"coordinates":[-74.94588299999999,39.964101],"type":"Point"}
}