{
  "type": "Feature",
  "properties": {
    "iso:country":"US",
    "sg:address":"333 16th St",
    "sg:city":"Carlstadt",
    "sg:classifiers":[
        {
            "category":"Professional",
            "subcategory":"Management & Consulting",
            "type":"Services"
        }
    ],
    "sg:phone":"+1 201 672 0110",
    "sg:postcode":"07072",
    "sg:province":"NJ",
    "sg:tags":[
        "food"
    ],
    "wof:name":"PBI Food Svc Inc",
    "wof:placetype":"venue"
},
  "geometry": {"coordinates":[-74.084113,40.832002],"type":"Point"}
}