{
  "type": "Feature",
  "properties": {
    "iso:country":"US",
    "sg:address":"357 Little Silver Point Rd",
    "sg:city":"Little Silver",
    "sg:classifiers":[
        {
            "category":"Building & Trades",
            "subcategory":"Construction",
            "type":"Services"
        }
    ],
    "sg:phone":"+1 732 741 3820",
    "sg:postcode":"07739",
    "sg:province":"NJ",
    "sg:tags":[
        "general",
        "contractor"
    ],
    "wof:name":"Kelso Construction Co",
    "wof:placetype":"venue"
},
  "geometry": {"coordinates":[-74.022744,40.337122],"type":"Point"}
}