{
  "type": "Feature",
  "properties": {
    "addr:full":"16 Rolling Ridge Dr Rockaway NJ 07866",
    "addr:housenumber":"16",
    "addr:postcode":"07866",
    "addr:street":"Rolling Ridge Dr",
    "iso:country":"US",
    "sg:address":"16 Rolling Ridge Dr",
    "sg:city":"Rockaway",
    "sg:classifiers":[
        {
            "category":"Real Estate",
            "subcategory":"Real Estate Operator",
            "type":"Services"
        }
    ],
    "sg:phone":"+1   ",
    "sg:postcode":"07866",
    "sg:province":"NJ",
    "sg:tags":[
        "building",
        "nonresidential"
    ],
    "wof:name":"Faber Properties LLC",
    "wof:placetype":"venue"
},
  "geometry": {"coordinates":[-74.493861,40.971451],"type":"Point"}
}