{
  "type": "Feature",
  "properties": {
    "addr:full":"29 Cypress Ave Lincoln Park NJ 07035",
    "addr:housenumber":"29",
    "addr:postcode":"07035",
    "addr:street":"Cypress Ave",
    "iso:country":"US",
    "sg:address":"29 Cypress Ave",
    "sg:city":"Lincoln Park",
    "sg:classifiers":[
        {
            "category":"Professional",
            "subcategory":"Management & Consulting",
            "type":"Services"
        }
    ],
    "sg:phone":"+1   ",
    "sg:postcode":"07035",
    "sg:province":"NJ",
    "sg:tags":[
        "business"
    ],
    "wof:name":"S Sabani Consulting",
    "wof:placetype":"venue"
},
  "geometry": {"coordinates":[-74.27533,40.910095],"type":"Point"}
}