{
  "type": "Feature",
  "properties": {
    "iso:country":"US",
    "sg:address":"700 Main St",
    "sg:city":"Cedarville",
    "sg:classifiers":[
        {
            "category":"Farming",
            "subcategory":"Nursery",
            "type":"Manufacturing & Wholesale Goods"
        }
    ],
    "sg:phone":"+1   ",
    "sg:postcode":"08311",
    "sg:province":"NJ",
    "sg:tags":[
        "ornamental",
        "supply"
    ],
    "sg:website":"www.akerboom.com",
    "wof:name":"J G Akerboom Nurseries Inc",
    "wof:placetype":"venue"
},
  "geometry": {"coordinates":[-75.17474199999999,39.313347],"type":"Point"}
}