{
  "type": "Feature",
  "properties": {
    "addr:full":"2314 Saint Georges Ave Rahway NJ 07065",
    "addr:housenumber":"2314",
    "addr:postcode":"07065",
    "addr:street":"Saint Georges Ave",
    "iso:country":"US",
    "sg:address":"2314 Saint Georges Ave",
    "sg:city":"Rahway",
    "sg:classifiers":[
        {
            "category":"Health Services",
            "subcategory":"Chiropractor",
            "type":"Services"
        }
    ],
    "sg:phone":"+1 732 382 1997",
    "sg:postcode":"07065",
    "sg:province":"NJ",
    "wof:name":"Robert R Weber DC",
    "wof:placetype":"venue"
},
  "geometry": {"coordinates":[-74.27723,40.623675],"type":"Point"}
}