{
  "type": "Feature",
  "properties": {
    "addr:full":"108 US Hwy 130 Bordentown NJ 08505",
    "addr:housenumber":"108",
    "addr:postcode":"08505",
    "addr:street":"Us Hwy 130",
    "iso:country":"US",
    "sg:address":"108 US Hwy 130",
    "sg:city":"Bordentown",
    "sg:classifiers":[
        {
            "category":"Government",
            "subcategory":"Office",
            "type":"Public Place"
        }
    ],
    "sg:phone":"+1 609 298 1144",
    "sg:postcode":"08505",
    "sg:province":"NJ",
    "wof:name":"State CSMS",
    "wof:placetype":"venue"
},
  "geometry": {"coordinates":[-74.69477999999999,40.157859],"type":"Point"}
}