{
  "type": "Feature",
  "properties": {
    "addr:full":"235 Rock Rd Glen Rock NJ 07452",
    "addr:housenumber":"235",
    "addr:postcode":"07452",
    "addr:street":"Rock Rd",
    "iso:country":"US",
    "sg:address":"235 Rock Rd",
    "sg:city":"Glen Rock",
    "sg:classifiers":[
        {
            "category":"Food & Beverages",
            "subcategory":"Groceries & Convenience Stores",
            "type":"Retail Goods"
        }
    ],
    "sg:phone":"+1   ",
    "sg:postcode":"07452",
    "sg:province":"NJ",
    "sg:tags":[
        "bagel"
    ],
    "wof:name":"Bagel Gourmet Inc",
    "wof:placetype":"venue"
},
  "geometry": {"coordinates":[-74.130503,40.96256],"type":"Point"}
}