{
  "type": "Feature",
  "properties": {
    "iso:country":"US",
    "sg:address":"520 Speedwell Ave",
    "sg:city":"Morris Plains",
    "sg:classifiers":[
        {
            "category":"Professional",
            "subcategory":"Lawyer & Legal Services",
            "type":"Services"
        }
    ],
    "sg:phone":"+1 212 279 3334",
    "sg:postcode":"07950",
    "sg:province":"NJ",
    "wof:name":"Collopy & Carlucci",
    "wof:placetype":"venue"
},
  "geometry": {"coordinates":[-74.480273,40.82582],"type":"Point"}
}