{
  "type": "Feature",
  "properties": {
    "iso:country":"US",
    "sg:address":"245 Union St",
    "sg:city":"Lodi",
    "sg:classifiers":[
        {
            "category":"Professional",
            "subcategory":"Accounting & Tax Preparation",
            "type":"Services"
        }
    ],
    "sg:phone":"+1 973 779 6890",
    "sg:postcode":"07644",
    "sg:province":"NJ",
    "wof:name":"Di Maria & Di Maria",
    "wof:placetype":"venue"
},
  "geometry": {"coordinates":[-74.076446,40.872622],"type":"Point"}
}