{
  "type": "Feature",
  "properties": {
    "iso:country":"US",
    "sg:address":"222 S Broad St",
    "sg:city":"Trenton",
    "sg:classifiers":[
        {
            "category":"Professional",
            "subcategory":"Lawyer & Legal Services",
            "type":"Services"
        }
    ],
    "sg:phone":"+1 609 695 1736",
    "sg:postcode":"08608",
    "sg:province":"NJ",
    "sg:tags":[
        "attorney"
    ],
    "wof:name":"Arthur Swidler Law Office",
    "wof:placetype":"venue"
},
  "geometry": {"coordinates":[-74.762112,40.215985],"type":"Point"}
}