{
  "type": "Feature",
  "properties": {
    "iso:country":"US",
    "sg:address":"40 Veronica Ave",
    "sg:city":"Somerset",
    "sg:classifiers":[
        {
            "category":"Manufacturing",
            "subcategory":"Chemicals & Compounds",
            "type":"Manufacturing & Wholesale Goods"
        }
    ],
    "sg:phone":"+1 732 937 4917",
    "sg:postcode":"08873",
    "sg:province":"NJ",
    "sg:tags":[
        "mfg",
        "plastic"
    ],
    "wof:name":"Dow Chemical",
    "wof:placetype":"venue"
},
  "geometry": {"coordinates":[-74.504311,40.481992],"type":"Point"}
}