{
  "type": "Feature",
  "properties": {
    "iso:country":"US",
    "sg:address":"337 Avon Ave",
    "sg:city":"Newark",
    "sg:classifiers":[
        {
            "category":"Education",
            "subcategory":"Preschool",
            "type":"Public Place"
        },
        {
            "category":"Education",
            "subcategory":"School",
            "type":"Public Place"
        }
    ],
    "sg:phone":"+1 973 824 0184",
    "sg:postcode":"07108",
    "sg:province":"NJ",
    "sg:tags":[
        "elementary"
    ],
    "wof:name":"Leaguers Educational Cultural Youth Center",
    "wof:placetype":"venue"
},
  "geometry": {"coordinates":[-74.20542500000001,40.726739],"type":"Point"}
}