{
  "type": "Feature",
  "properties": {
    "iso:country":"US",
    "sg:address":"31 E Railroad Ave",
    "sg:city":"Monroe Township",
    "sg:classifiers":[
        {
            "category":"Real Estate",
            "subcategory":"Real Estate Agent",
            "type":"Services"
        }
    ],
    "sg:phone":"+1   ",
    "sg:postcode":"08831",
    "sg:province":"NJ",
    "wof:name":"Sale By Owner Complete Co",
    "wof:placetype":"venue"
},
  "geometry": {"coordinates":[-74.437547,40.350131],"type":"Point"}
}