{
  "type": "Feature",
  "properties": {
    "addr:full":"11 Federal St Camden NJ 08105",
    "addr:housenumber":"11",
    "addr:postcode":"08105",
    "addr:street":"Federal St",
    "iso:country":"US",
    "sg:address":"11 Federal St",
    "sg:city":"Camden",
    "sg:classifiers":[
        {
            "category":"Professional",
            "subcategory":"Computer Services",
            "type":"Services"
        }
    ],
    "sg:phone":"+1 856 338 4539",
    "sg:postcode":"08105",
    "sg:province":"NJ",
    "sg:tags":[
        "programing",
        "custom"
    ],
    "wof:name":"L-3 Cmmunications Ilex Systems",
    "wof:placetype":"venue"
},
  "geometry": {"coordinates":[-75.127274,39.944569],"type":"Point"}
}