{
  "type": "Feature",
  "properties": {
    "iso:country":"US",
    "sg:address":"357 S White Horse Pike",
    "sg:city":"Hammonton",
    "sg:classifiers":[
        {
            "category":"Retail",
            "subcategory":"Veterinary Services",
            "type":"Services"
        }
    ],
    "sg:phone":"+1 609 561 2802",
    "sg:postcode":"08037",
    "sg:province":"NJ",
    "sg:tags":[
        "hospital",
        "veterinarian",
        "clinic",
        "emergency"
    ],
    "sg:website":"http://www.shorevets.com",
    "wof:name":"Shore Veterinarian-Hammonton",
    "wof:placetype":"venue"
},
  "geometry": {"coordinates":[-74.774832,39.635665],"type":"Point"}
}