{
  "type": "Feature",
  "properties": {
    "iso:country":"US",
    "sg:address":"3125 State Rte 10",
    "sg:city":"Denville",
    "sg:classifiers":[
        {
            "category":"Wholesale",
            "subcategory":"Stationery",
            "type":"Manufacturing & Wholesale Goods"
        }
    ],
    "sg:phone":"+1 973 442 3000",
    "sg:postcode":"07834",
    "sg:province":"NJ",
    "sg:tags":[
        "product",
        "paper"
    ],
    "wof:name":"Fisher Group Corp Svc",
    "wof:placetype":"venue"
},
  "geometry": {"coordinates":[-74.516831,40.870305],"type":"Point"}
}