{
  "type": "Feature",
  "properties": {
    "iso:country":"US",
    "sg:address":"712 Erial Rd",
    "sg:city":"Pine Hill",
    "sg:classifiers":[
        {
            "category":"Food & Beverages",
            "subcategory":"Groceries & Convenience Stores",
            "type":"Retail Goods"
        }
    ],
    "sg:phone":"+1 856 783 0925",
    "sg:postcode":"08021",
    "sg:province":"NJ",
    "sg:tags":[
        "grocer"
    ],
    "wof:name":"Pine Hill Market",
    "wof:placetype":"venue"
},
  "geometry": {"coordinates":[-74.991302,39.786701],"type":"Point"}
}