{
  "type": "Feature",
  "properties": {
    "iso:country":"US",
    "sg:address":"28 Stewart St",
    "sg:city":"Camden",
    "sg:classifiers":[
        {
            "category":"Organizations",
            "subcategory":"Religious Organization",
            "type":"Services"
        }
    ],
    "sg:phone":"+1   ",
    "sg:postcode":"08105",
    "sg:province":"NJ",
    "wof:name":"Worldwide Missionary Movement",
    "wof:placetype":"venue"
},
  "geometry": {"coordinates":[-75.094359,39.946615],"type":"Point"}
}