{
  "type": "Feature",
  "properties": {
    "iso:country":"US",
    "sg:address":"210 Co Rd 539",
    "sg:city":"Cream Ridge",
    "sg:classifiers":[
        {
            "category":"Real Estate",
            "subcategory":"Real Estate Agent",
            "type":"Services"
        }
    ],
    "sg:phone":"+1 609 259 0200",
    "sg:postcode":"08514",
    "sg:province":"NJ",
    "wof:name":"ERA Advantage",
    "wof:placetype":"venue"
},
  "geometry": {"coordinates":[-74.53451699999999,40.141449],"type":"Point"}
}