{
  "type": "Feature",
  "properties": {
    "iso:country":"US",
    "sg:address":"114 Four Winds Dr",
    "sg:city":"Middletown",
    "sg:classifiers":[
        {
            "category":"Manufacturing",
            "subcategory":"Chemicals & Compounds",
            "type":"Manufacturing & Wholesale Goods"
        }
    ],
    "sg:phone":"+1 732 706 1126",
    "sg:postcode":"07748",
    "sg:province":"NJ",
    "sg:tags":[
        "ingredient"
    ],
    "wof:name":"Aromatic International LLC",
    "wof:placetype":"venue"
},
  "geometry": {"coordinates":[-74.13051,40.361957],"type":"Point"}
}