{
  "type": "Feature",
  "properties": {
    "iso:country":"US",
    "sg:address":"1000 Herrontown Rd",
    "sg:city":"Princeton",
    "sg:classifiers":[
        {
            "category":"Health Services",
            "subcategory":"Health Practitioner",
            "type":"Services"
        }
    ],
    "sg:phone":"+1 609 497 9466",
    "sg:postcode":"08540",
    "sg:province":"NJ",
    "wof:name":"Irene Rhodes Acsw",
    "wof:placetype":"venue"
},
  "geometry": {"coordinates":[-74.654837,40.388182],"type":"Point"}
}