{
  "type": "Feature",
  "properties": {
    "iso:country":"US",
    "sg:address":"110 S Jefferson Rd Ste 6",
    "sg:city":"Whippany",
    "sg:classifiers":[
        {
            "category":"Professional",
            "subcategory":"Employment Agencies",
            "type":"Services"
        }
    ],
    "sg:phone":"+1 973 884 8634",
    "sg:postcode":"07981",
    "sg:province":"NJ",
    "wof:name":"Yoh Scientific",
    "wof:placetype":"venue"
},
  "geometry": {"coordinates":[-74.443454,40.816474],"type":"Point"}
}