{
  "type": "Feature",
  "properties": {
    "addr:full":"230 Main St Fort Lee NJ 07024",
    "addr:housenumber":"230",
    "addr:postcode":"07024",
    "addr:street":"Main St",
    "iso:country":"US",
    "sg:address":"230 Main St",
    "sg:city":"Fort Lee",
    "sg:classifiers":[
        {
            "category":"Wholesale",
            "subcategory":"Durable Goods & Equipment",
            "type":"Manufacturing & Wholesale Goods"
        }
    ],
    "sg:phone":"+1 201 592 9888",
    "sg:postcode":"07024",
    "sg:province":"NJ",
    "sg:tags":[
        "exporter"
    ],
    "wof:name":"TSL Corp",
    "wof:placetype":"venue"
},
  "geometry": {"coordinates":[-73.972217,40.851886],"type":"Point"}
}