{
  "type": "Feature",
  "properties": {
    "addr:full":"138 Cannonball Rd Pompton Lakes NJ 07442",
    "addr:housenumber":"138",
    "addr:postcode":"07442",
    "addr:street":"Cannonball Rd",
    "iso:country":"US",
    "sg:address":"138 Cannonball Rd",
    "sg:city":"Pompton Lakes",
    "sg:classifiers":[
        {
            "category":"Manufacturing",
            "subcategory":"Tools & Machinery",
            "type":"Manufacturing & Wholesale Goods"
        }
    ],
    "sg:phone":"+1 973 835 8423",
    "sg:postcode":"07442",
    "sg:province":"NJ",
    "sg:tags":[
        "machine",
        "industry",
        "special",
        "mfg"
    ],
    "wof:name":"Vansco Inc",
    "wof:placetype":"venue"
},
  "geometry": {"coordinates":[-74.287401,41.009494],"type":"Point"}
}