{
  "type": "Feature",
  "properties": {
    "iso:country":"US",
    "sg:address":"1960 Spruce St",
    "sg:city":"Trenton",
    "sg:classifiers":[
        {
            "category":"Autos & Motor Vehicles",
            "subcategory":"Automobile Sales",
            "type":"Retail Goods"
        }
    ],
    "sg:phone":"+1 609 392 1888",
    "sg:postcode":"08638",
    "sg:province":"NJ",
    "wof:name":"Cadet Motors Inc",
    "wof:placetype":"venue"
},
  "geometry": {"coordinates":[-74.75428700000001,40.246145],"type":"Point"}
}