{
  "type": "Feature",
  "properties": {
    "iso:country":"US",
    "sg:address":"562 Valley Rd",
    "sg:city":"West Orange",
    "sg:classifiers":[
        {
            "category":"Restaurant",
            "type":"Food & Drink"
        }
    ],
    "sg:phone":"+1 973 731 2511",
    "sg:postcode":"07052",
    "sg:province":"NJ",
    "sg:tags":[
        "chinese"
    ],
    "wof:name":"China King",
    "wof:placetype":"venue"
},
  "geometry": {"coordinates":[-74.246696,40.7686],"type":"Point"}
}