{
  "type": "Feature",
  "properties": {
    "iso:country":"US",
    "sg:address":"55 Market St",
    "sg:city":"Passaic",
    "sg:classifiers":[
        {
            "category":"Health Services",
            "subcategory":"Doctor",
            "type":"Services"
        }
    ],
    "sg:phone":"+1 973 777 8327",
    "sg:postcode":"07055",
    "sg:province":"NJ",
    "sg:tags":[
        "surgeon",
        "oral"
    ],
    "wof:name":"Dickman Michael DDS",
    "wof:placetype":"venue"
},
  "geometry": {"coordinates":[-74.116501,40.8629],"type":"Point"}
}