{
  "type": "Feature",
  "properties": {
    "iso:country":"US",
    "sg:address":"36 Otter Creek Rd",
    "sg:city":"Skillman",
    "sg:classifiers":[
        {
            "category":"Professional",
            "subcategory":"Management & Consulting",
            "type":"Services"
        }
    ],
    "sg:phone":"+1 609 333 0203",
    "sg:postcode":"08558",
    "sg:province":"NJ",
    "wof:name":"Glenn M Parker Associates",
    "wof:placetype":"venue"
},
  "geometry": {"coordinates":[-74.69972199999999,40.385187],"type":"Point"}
}