{
  "type": "Feature",
  "properties": {
    "addr:full":"90 N Sussex St Dover NJ 07801",
    "addr:housenumber":"90",
    "addr:postcode":"07801",
    "addr:street":"N Sussex St",
    "iso:country":"US",
    "sg:address":"90 N Sussex St",
    "sg:city":"Dover",
    "sg:classifiers":[
        {
            "category":"Professional",
            "subcategory":"Employment Agencies",
            "type":"Services"
        }
    ],
    "sg:phone":"+1 973 659 9215",
    "sg:postcode":"07801",
    "sg:province":"NJ",
    "sg:tags":[
        "opportunity"
    ],
    "wof:name":"Tuttle Agency",
    "wof:placetype":"venue"
},
  "geometry": {"coordinates":[-74.55879,40.886586],"type":"Point"}
}