{
  "type": "Feature",
  "properties": {
    "addr:full":"2 Ackerman Ave Clifton NJ 07011",
    "addr:housenumber":"2",
    "addr:postcode":"07011",
    "addr:street":"Ackerman Ave",
    "iso:country":"US",
    "sg:address":"2 Ackerman Ave",
    "sg:city":"Clifton",
    "sg:classifiers":[
        {
            "category":"Manufacturing",
            "subcategory":"Chemicals & Compounds",
            "type":"Manufacturing & Wholesale Goods"
        }
    ],
    "sg:phone":"+1 973 772 5252",
    "sg:postcode":"07011",
    "sg:province":"NJ",
    "sg:tags":[
        "mfg",
        "used",
        "granule",
        "galaxy",
        "plastic"
    ],
    "sg:website":"www.safascorp.com",
    "wof:name":"Safas Corp",
    "wof:placetype":"venue"
},
  "geometry": {"coordinates":[-74.12186,40.879332],"type":"Point"}
}