{
  "type": "Feature",
  "properties": {
    "iso:country":"US",
    "sg:address":"68 Beech St",
    "sg:city":"Kearny",
    "sg:classifiers":[
        {
            "category":"Building & Trades",
            "subcategory":"Locksmith",
            "type":"Services"
        }
    ],
    "sg:phone":"+1 201 546 5559",
    "sg:postcode":"07032",
    "sg:province":"NJ",
    "sg:tags":[
        "key"
    ],
    "wof:name":"24-7 jersey-city-locksmith",
    "wof:placetype":"venue"
},
  "geometry": {"coordinates":[-74.145556,40.768107],"type":"Point"}
}