{
  "type": "Feature",
  "properties": {
    "addr:full":"23 Sawbuck Rd Freehold NJ 07728",
    "addr:housenumber":"23",
    "addr:postcode":"07728",
    "addr:street":"Sawbuck Rd",
    "iso:country":"US",
    "sg:address":"23 Sawbuck Rd",
    "sg:city":"Freehold",
    "sg:classifiers":[
        {
            "category":"Retail",
            "subcategory":"Repair Shop",
            "type":"Services"
        }
    ],
    "sg:phone":"+1   ",
    "sg:postcode":"07728",
    "sg:province":"NJ",
    "wof:name":"Tmd Equipment Repairs",
    "wof:placetype":"venue"
},
  "geometry": {"coordinates":[-74.292721,40.238429],"type":"Point"}
}