{
  "type": "Feature",
  "properties": {
    "addr:full":"499 Newark Pompton Tpke Pompton Plains NJ 07444",
    "addr:housenumber":"499",
    "addr:postcode":"07444",
    "addr:street":"Newark Pompton Tpke",
    "iso:country":"US",
    "sg:address":"499 Newark Pompton Tpke",
    "sg:city":"Pompton Plains",
    "sg:classifiers":[
        {
            "category":"Health Services",
            "subcategory":"Doctor",
            "type":"Services"
        }
    ],
    "sg:phone":"+1 973 839 8336",
    "sg:postcode":"07444",
    "sg:province":"NJ",
    "sg:tags":[
        "physician",
        "surgeon"
    ],
    "wof:name":"Donald W Rumbaugh MD",
    "wof:placetype":"venue"
},
  "geometry": {"coordinates":[-74.29451899999999,40.961069],"type":"Point"}
}