{
  "type": "Feature",
  "properties": {
    "addr:full":"151 62nd St West New York NJ 07093",
    "addr:housenumber":"151",
    "addr:postcode":"nj 07093",
    "addr:street":"62Nd St West",
    "iso:country":"US",
    "sg:address":"151 62nd St",
    "sg:city":"West New York",
    "sg:classifiers":[
        {
            "category":"Professional",
            "type":"Services"
        }
    ],
    "sg:phone":"+1   ",
    "sg:postcode":"07093",
    "sg:province":"NJ",
    "wof:name":"Jacqueline Banguera Quality CL",
    "wof:placetype":"venue"
},
  "geometry": {"coordinates":[-74.009049,40.788537],"type":"Point"}
}