{
  "type": "Feature",
  "properties": {
    "iso:country":"US",
    "sg:address":"151 62nd St",
    "sg:city":"West New York",
    "sg:classifiers":[
        {
            "category":"Professional",
            "type":"Services"
        }
    ],
    "sg:phone":"+1   ",
    "sg:postcode":"07093",
    "sg:province":"NJ",
    "wof:name":"Jacqueline Banguera Quality CL",
    "wof:placetype":"venue"
},
  "geometry": {"coordinates":[-74.009049,40.788537],"type":"Point"}
}