{
  "type": "Feature",
  "properties": {
    "addr:full":"2 Demott Rd Whitehouse Sta NJ 08889",
    "addr:housenumber":"2",
    "addr:postcode":"08889",
    "addr:street":"Demott Rd",
    "iso:country":"US",
    "sg:address":"2 Demott Rd",
    "sg:city":"Whitehouse Sta",
    "sg:classifiers":[
        {
            "category":"Manufacturing",
            "subcategory":"Electronics",
            "type":"Manufacturing & Wholesale Goods"
        }
    ],
    "sg:phone":"+1 908 534 1466",
    "sg:postcode":"08889",
    "sg:province":"NJ",
    "sg:tags":[
        "equipment",
        "electronic",
        "supply"
    ],
    "sg:website":"www.kenbar.com",
    "wof:name":"Kenbar Industries",
    "wof:placetype":"venue"
},
  "geometry": {"coordinates":[-74.74633799999999,40.594525],"type":"Point"}
}