{
  "type": "Feature",
  "properties": {
    "iso:country":"US",
    "sg:address":"27 W Main St",
    "sg:city":"Maple Shade",
    "sg:classifiers":[
        {
            "category":"Shopping",
            "subcategory":"Discount & Variety Stores",
            "type":"Retail Goods"
        }
    ],
    "sg:phone":"+1 856 779 1212",
    "sg:postcode":"08052",
    "sg:province":"NJ",
    "wof:name":"Maple Shades 5 & 10",
    "wof:placetype":"venue"
},
  "geometry": {"coordinates":[-75.004538,39.955162],"type":"Point"}
}