{
  "type": "Feature",
  "properties": {
    "addr:full":"113 E Park Ave Oaklyn NJ 08107",
    "addr:housenumber":"113",
    "addr:postcode":"08107",
    "addr:street":"E Park Ave",
    "iso:country":"US",
    "sg:address":"113 E Park Ave",
    "sg:city":"Oaklyn",
    "sg:classifiers":[
        {
            "category":"Building & Trades",
            "subcategory":"Plumbing",
            "type":"Services"
        }
    ],
    "sg:phone":"+1 856 858 5913",
    "sg:postcode":"08107",
    "sg:province":"NJ",
    "sg:tags":[
        "repair",
        "contractor"
    ],
    "wof:name":"Penney Dan Plumbing & Heating",
    "wof:placetype":"venue"
},
  "geometry": {"coordinates":[-75.069534,39.902267],"type":"Point"}
}