{
  "type": "Feature",
  "properties": {
    "addr:full":"14 Sunrise Dr Warren NJ 07059",
    "addr:housenumber":"14",
    "addr:postcode":"07059",
    "addr:street":"Sunrise Dr",
    "iso:country":"US",
    "sg:address":"14 Sunrise Dr",
    "sg:city":"Warren",
    "sg:classifiers":[
        {
            "category":"Shopping",
            "type":"Retail Goods"
        }
    ],
    "sg:phone":"+1 908 647 0480",
    "sg:postcode":"07059",
    "sg:province":"NJ",
    "sg:tags":[
        "janitorial",
        "supply"
    ],
    "wof:name":"Sunrise Enterprises",
    "wof:placetype":"venue"
},
  "geometry": {"coordinates":[-74.530911,40.637839],"type":"Point"}
}