{
  "type": "Feature",
  "properties": {
    "addr:full":"118 US Hwy 206 Branchville NJ 07826",
    "addr:housenumber":"118",
    "addr:postcode":"07826",
    "addr:street":"Us Hwy 206",
    "iso:country":"US",
    "sg:address":"118 US Hwy 206",
    "sg:city":"Branchville",
    "sg:classifiers":[
        {
            "category":"Retail",
            "subcategory":"Auto Repair",
            "type":"Services"
        }
    ],
    "sg:phone":"+1 973 948 3783",
    "sg:postcode":"07826",
    "sg:province":"NJ",
    "sg:tags":[
        "general"
    ],
    "wof:name":"Hills Precision Auto LLC",
    "wof:placetype":"venue"
},
  "geometry": {"coordinates":[-74.80298999999999,41.200396],"type":"Point"}
}