{
  "type": "Feature",
  "properties": {
    "addr:full":"59 Deerfield Ln Saddle River NJ 07458",
    "addr:housenumber":"59",
    "addr:postcode":"07458",
    "addr:street":"Deerfield Ln",
    "iso:country":"US",
    "sg:address":"59 Deerfield Ln",
    "sg:city":"Saddle River",
    "sg:classifiers":[
        {
            "category":"Professional",
            "subcategory":"Business Services",
            "type":"Services"
        }
    ],
    "sg:phone":"+1   ",
    "sg:postcode":"07458",
    "sg:province":"NJ",
    "wof:name":"G&K Sales & Marketing LLC",
    "wof:placetype":"venue"
},
  "geometry": {"coordinates":[-74.07735,41.065853],"type":"Point"}
}