{
  "type": "Feature",
  "properties": {
    "iso:country":"US",
    "sg:address":"1505 Parkway Ave",
    "sg:city":"Trenton",
    "sg:classifiers":[
        {
            "category":"Personal",
            "type":"Services"
        }
    ],
    "sg:phone":"+1 609 883 3950",
    "sg:postcode":"08628",
    "sg:province":"NJ",
    "sg:tags":[
        "shopping"
    ],
    "wof:name":"Chores Galore",
    "wof:placetype":"venue"
},
  "geometry": {"coordinates":[-74.81331900000001,40.267916],"type":"Point"}
}