{
  "type": "Feature",
  "properties": {
    "addr:full":"6 Park Ave Flemington NJ 08822",
    "addr:housenumber":"6",
    "addr:postcode":"08822",
    "addr:street":"Park Ave",
    "iso:country":"US",
    "sg:address":"6 Park Ave",
    "sg:city":"Flemington",
    "sg:classifiers":[
        {
            "category":"Social Services",
            "subcategory":"Child Care",
            "type":"Services"
        }
    ],
    "sg:phone":"+1 908 782 7905",
    "sg:postcode":"08822",
    "sg:province":"NJ",
    "sg:tags":[
        "hospital",
        "health",
        "mental",
        "day",
        "specialty"
    ],
    "sg:website":"http://www.cctrenton.org",
    "wof:name":"Catholic Charities",
    "wof:placetype":"venue"
},
  "geometry": {"coordinates":[-74.860793,40.508417],"type":"Point"}
}