{
  "type": "Feature",
  "properties": {
    "iso:country":"US",
    "sg:address":"69 Market St",
    "sg:city":"Paterson",
    "sg:classifiers":[
        {
            "category":"Professional",
            "subcategory":"Accounting & Tax Preparation",
            "type":"Services"
        }
    ],
    "sg:phone":"+1 973 345 8063",
    "sg:postcode":"07505",
    "sg:province":"NJ",
    "sg:tags":[
        "return",
        "filing"
    ],
    "wof:name":"Expertax",
    "wof:placetype":"venue"
},
  "geometry": {"coordinates":[-74.176244,40.91517],"type":"Point"}
}