{
  "type": "Feature",
  "properties": {
    "iso:country":"US",
    "sg:address":"776 Radix Rd",
    "sg:city":"Williamstown",
    "sg:classifiers":[
        {
            "category":"Professional",
            "type":"Services"
        }
    ],
    "sg:phone":"+1   ",
    "sg:postcode":"08094",
    "sg:province":"NJ",
    "wof:name":"Scarduzio Cleaning Service",
    "wof:placetype":"venue"
},
  "geometry": {"coordinates":[-74.96214999999999,39.691827],"type":"Point"}
}