{
  "type": "Feature",
  "properties": {
    "addr:full":"1342 Hooper Ave Toms River NJ 08753",
    "addr:housenumber":"1342",
    "addr:postcode":"08753",
    "addr:street":"Hooper Ave",
    "iso:country":"US",
    "sg:address":"1342 Hooper Ave",
    "sg:city":"Toms River",
    "sg:classifiers":[
        {
            "category":"Shopping",
            "subcategory":"Hobbies, Toys, & Games",
            "type":"Retail Goods"
        }
    ],
    "sg:phone":"+1   ",
    "sg:postcode":"08753",
    "sg:province":"NJ",
    "sg:tags":[
        "arts",
        "craft"
    ],
    "wof:name":"Michaels 2757",
    "wof:placetype":"venue"
},
  "geometry": {"coordinates":[-74.176636,39.989688],"type":"Point"}
}