{
  "type": "Feature",
  "properties": {
    "addr:full":"507 E Jersey St Elizabeth NJ 07206",
    "addr:housenumber":"507",
    "addr:postcode":"07206",
    "addr:street":"E Jersey St",
    "iso:country":"US",
    "sg:address":"507 E Jersey St",
    "sg:city":"Elizabeth",
    "sg:classifiers":[
        {
            "category":"Building & Trades",
            "subcategory":"Locksmith",
            "type":"Services"
        }
    ],
    "sg:phone":"+1 888 277 4514",
    "sg:postcode":"07206",
    "sg:province":"NJ",
    "sg:tags":[
        "key"
    ],
    "wof:name":"A 1 Emergency Locksmith",
    "wof:placetype":"venue"
},
  "geometry": {"coordinates":[-74.19535999999999,40.655947],"type":"Point"}
}