{
  "type": "Feature",
  "properties": {
    "iso:country":"US",
    "sg:address":"331 Grand Ave",
    "sg:city":"Hoboken",
    "sg:classifiers":[
        {
            "category":"Health Services",
            "subcategory":"Doctor",
            "type":"Services"
        }
    ],
    "sg:phone":"+1 201 420 6300",
    "sg:postcode":"07030",
    "sg:province":"NJ",
    "sg:tags":[
        "throat",
        "ear",
        "nose"
    ],
    "wof:name":"Glickman Alexander B MD PA",
    "wof:placetype":"venue"
},
  "geometry": {"coordinates":[-74.03525399999999,40.741992],"type":"Point"}
}