{
  "type": "Feature",
  "properties": {
    "addr:full":"412 E Nashville Ave Wildwood NJ 08260",
    "addr:housenumber":"412",
    "addr:postcode":"08260",
    "addr:street":"E Nashville Ave",
    "iso:country":"US",
    "sg:address":"412 E Nashville Ave",
    "sg:city":"Wildwood",
    "sg:classifiers":[
        {
            "category":"Travel",
            "subcategory":"Hotels & Motels",
            "type":"Entertainment"
        }
    ],
    "sg:phone":"+1 609 522 4836",
    "sg:postcode":"08260",
    "sg:province":"NJ",
    "wof:name":"Silver Beach Motel Inc",
    "wof:placetype":"venue"
},
  "geometry": {"coordinates":[-74.83963,38.966769],"type":"Point"}
}