{
  "type": "Feature",
  "properties": {
    "addr:full":"61 Main St Millburn NJ 07041",
    "addr:housenumber":"61",
    "addr:postcode":"07041",
    "addr:street":"Main St",
    "iso:country":"US",
    "sg:address":"61 Main St",
    "sg:city":"Millburn",
    "sg:classifiers":[
        {
            "category":"Restaurant",
            "type":"Food & Drink"
        }
    ],
    "sg:postcode":"07041",
    "sg:province":"NJ",
    "sg:tags":[
        "italian"
    ],
    "wof:name":"Peter's",
    "wof:placetype":"venue"
},
  "geometry": {"coordinates":[-74.30704299999999,40.723448],"type":"Point"}
}