{
  "type": "Feature",
  "properties": {
    "addr:full":"25 Bradford Ln Plainsboro NJ 08536",
    "addr:housenumber":"25",
    "addr:postcode":"08536",
    "addr:street":"Bradford Ln",
    "iso:country":"US",
    "sg:address":"25 Bradford Ln",
    "sg:city":"Plainsboro",
    "sg:classifiers":[
        {
            "category":"Professional",
            "subcategory":"Accounting & Tax Preparation",
            "type":"Services"
        }
    ],
    "sg:phone":"+1 609 799 8568",
    "sg:postcode":"08536",
    "sg:province":"NJ",
    "sg:tags":[
        "accountant"
    ],
    "wof:name":"Net-Controler",
    "wof:placetype":"venue"
},
  "geometry": {"coordinates":[-74.548194,40.33189],"type":"Point"}
}