{
  "type": "Feature",
  "properties": {
    "addr:full":"50 Edgeboro Rd East Brunswick NJ 08816",
    "addr:housenumber":"50",
    "addr:postcode":"08816",
    "addr:street":"Edgeboro Rd",
    "iso:country":"US",
    "sg:address":"50 Edgeboro Rd",
    "sg:city":"East Brunswick",
    "sg:classifiers":[
        {
            "category":"Freight",
            "type":"Transportation"
        }
    ],
    "sg:phone":"+1 732 246 4300",
    "sg:postcode":"08816",
    "sg:province":"NJ",
    "sg:tags":[
        "carrier",
        "motor"
    ],
    "sg:website":"www.myyellow.com",
    "wof:name":"Yellow Transportation Inc",
    "wof:placetype":"venue"
},
  "geometry": {"coordinates":[-74.395433,40.471457],"type":"Point"}
}