{
  "type": "Feature",
  "properties": {
    "iso:country":"US",
    "sg:address":"18 Washington Ave",
    "sg:city":"Chatham",
    "sg:classifiers":[
        {
            "category":"Insurance",
            "subcategory":"Insurance Agent",
            "type":"Services"
        }
    ],
    "sg:phone":"+1 973 635 7800",
    "sg:postcode":"07928",
    "sg:province":"NJ",
    "sg:website":"www.meyerandassoc.com",
    "wof:name":"Meyer & Assoc",
    "wof:placetype":"venue"
},
  "geometry": {"coordinates":[-74.387573,40.74174],"type":"Point"}
}