{
  "type": "Feature",
  "properties": {
    "iso:country":"US",
    "sg:address":"121 Constitution Way",
    "sg:city":"Basking Ridge",
    "sg:classifiers":[
        {
            "category":"Professional",
            "subcategory":"Management & Consulting",
            "type":"Services"
        }
    ],
    "sg:phone":"+1   ",
    "sg:postcode":"07920",
    "sg:province":"NJ",
    "wof:name":"Answers & Insights Inc",
    "wof:placetype":"venue"
},
  "geometry": {"coordinates":[-74.61345900000001,40.654218],"type":"Point"}
}