{
  "type": "Feature",
  "properties": {
    "iso:country":"US",
    "sg:address":"1545 US Hwy 206",
    "sg:city":"Bedminster",
    "sg:classifiers":[
        {
            "category":"Professional",
            "subcategory":"Detective & Security Services",
            "type":"Services"
        },
        {
            "category":"Professional",
            "subcategory":"Management & Consulting",
            "type":"Services"
        }
    ],
    "sg:phone":"+1 908 901 0112",
    "sg:postcode":"07921",
    "sg:province":"NJ",
    "sg:tags":[
        "consultant",
        "investigation",
        "corp",
        "business",
        "intelligence"
    ],
    "sg:website":"www.intell-group.com",
    "wof:name":"Intelligence Group LLC",
    "wof:placetype":"venue"
},
  "geometry": {"coordinates":[-74.64987000000001,40.679182],"type":"Point"}
}