{
  "type": "Feature",
  "properties": {
    "addr:full":"1300 N High St Millville NJ 08332",
    "addr:housenumber":"1300",
    "addr:postcode":"08332",
    "addr:street":"N High St",
    "iso:country":"US",
    "sg:address":"1300 N High St",
    "sg:city":"Millville",
    "sg:classifiers":[
        {
            "category":"Health Services",
            "subcategory":"Doctor",
            "type":"Services"
        }
    ],
    "sg:phone":"+1   ",
    "sg:postcode":"08332",
    "sg:province":"NJ",
    "sg:tags":[
        "dentist"
    ],
    "wof:name":"June Sun Dr",
    "wof:placetype":"venue"
},
  "geometry": {"coordinates":[-75.039878,39.410748],"type":"Point"}
}