{
  "type": "Feature",
  "properties": {
    "iso:country":"US",
    "sg:address":"2000 Route 38 Ste 1725",
    "sg:city":"Cherry Hill",
    "sg:classifiers":[
        {
            "category":"Shopping",
            "type":"Retail Goods"
        }
    ],
    "sg:phone":"+1 856 663 0779",
    "sg:postcode":"08002",
    "sg:province":"NJ",
    "wof:name":"Crabtree & Evelyn",
    "wof:placetype":"venue"
},
  "geometry": {"coordinates":[-75.025747,39.940745],"type":"Point"}
}