{
  "type": "Feature",
  "properties": {
    "addr:full":"416 N Kentucky Ave Atlantic City NJ 08401",
    "addr:housenumber":"416",
    "addr:postcode":"08401",
    "addr:street":"N Kentucky Ave",
    "iso:country":"US",
    "sg:address":"416 N Kentucky Ave",
    "sg:city":"Atlantic City",
    "sg:classifiers":[
        {
            "category":"Organizations",
            "subcategory":"Religious Organization",
            "type":"Services"
        }
    ],
    "sg:phone":"+1   ",
    "sg:postcode":"08401",
    "sg:province":"NJ",
    "wof:name":"Christ Mem A M E Zion Church",
    "wof:placetype":"venue"
},
  "geometry": {"coordinates":[-74.434518,39.366852],"type":"Point"}
}