{
  "type": "Feature",
  "properties": {
    "addr:full":"1 Stedwick Dr Budd Lake NJ 07828",
    "addr:housenumber":"1",
    "addr:postcode":"07828",
    "addr:street":"Stedwick Dr",
    "iso:country":"US",
    "sg:address":"1 Stedwick Dr",
    "sg:city":"Budd Lake",
    "sg:classifiers":[
        {
            "category":"Organizations",
            "subcategory":"Religious Organization",
            "type":"Services"
        }
    ],
    "sg:phone":"+1   ",
    "sg:postcode":"07828",
    "sg:province":"NJ",
    "wof:name":"All Nations Community Church I",
    "wof:placetype":"venue"
},
  "geometry": {"coordinates":[-74.74912999999999,40.854079],"type":"Point"}
}