{
  "type": "Feature",
  "properties": {
    "iso:country":"US",
    "sg:address":"615 W Mount Pleasant Ave Ste 3",
    "sg:city":"Livingston",
    "sg:classifiers":[
        {
            "category":"Professional",
            "subcategory":"Lawyer & Legal Services",
            "type":"Services"
        }
    ],
    "sg:phone":"+1 973 740 1000",
    "sg:postcode":"07039",
    "sg:province":"NJ",
    "sg:tags":[
        "litigation"
    ],
    "wof:name":"Lustbader David Counselor At Law",
    "wof:placetype":"venue"
},
  "geometry": {"coordinates":[-74.35520200000001,40.798401],"type":"Point"}
}