{
  "type": "Feature",
  "properties": {
    "iso:country":"US",
    "sg:address":"336 Old Deerfield Pike",
    "sg:city":"Bridgeton",
    "sg:classifiers":[
        {
            "category":"Building & Trades",
            "subcategory":"Construction",
            "type":"Services"
        }
    ],
    "sg:phone":"+1 856 455 3127",
    "sg:postcode":"08302",
    "sg:province":"NJ",
    "sg:tags":[
        "house",
        "contractor",
        "roofing"
    ],
    "wof:name":"Doug Bertucci Construction Co",
    "wof:placetype":"venue"
},
  "geometry": {"coordinates":[-75.232219,39.487998],"type":"Point"}
}