{
  "type": "Feature",
  "properties": {
    "addr:full":"600 Park Ave Plainfield NJ 07060",
    "addr:housenumber":"600",
    "addr:postcode":"07060",
    "addr:street":"Park Ave",
    "iso:country":"US",
    "sg:address":"600 Park Ave",
    "sg:city":"Plainfield",
    "sg:classifiers":[
        {
            "category":"Shopping",
            "subcategory":"Department Store",
            "type":"Retail Goods"
        }
    ],
    "sg:phone":"+1 908 561 6058",
    "sg:postcode":"07060",
    "sg:province":"NJ",
    "wof:name":"Family Dollar Store",
    "wof:placetype":"venue"
},
  "geometry": {"coordinates":[-74.41733000000001,40.614982],"type":"Point"}
}