{
  "type": "Feature",
  "properties": {
    "addr:full":"106 Brainard Ave Port Monmouth NJ 07758",
    "addr:housenumber":"106",
    "addr:postcode":"07758",
    "addr:street":"Brainard Ave",
    "iso:country":"US",
    "sg:address":"106 Brainard Ave",
    "sg:city":"Port Monmouth",
    "sg:classifiers":[
        {
            "category":"Building & Trades",
            "subcategory":"Construction",
            "type":"Services"
        }
    ],
    "sg:phone":"+1 732 495 3403",
    "sg:postcode":"07758",
    "sg:province":"NJ",
    "sg:tags":[
        "home",
        "improvement"
    ],
    "wof:name":"Muzio Construction",
    "wof:placetype":"venue"
},
  "geometry": {"coordinates":[-74.095636,40.431961],"type":"Point"}
}