{
  "type": "Feature",
  "properties": {
    "iso:country":"US",
    "sg:address":"636 Bear Tavern Rd",
    "sg:city":"Ewing",
    "sg:classifiers":[
        {
            "category":"Bars & Pubs",
            "type":"Food & Drink"
        },
        {
            "category":"Travel",
            "subcategory":"Bed & Breakfast",
            "type":"Entertainment"
        }
    ],
    "sg:phone":"+1 609 883 5252",
    "sg:postcode":"08628",
    "sg:province":"NJ",
    "sg:tags":[
        "tavern",
        "inn"
    ],
    "wof:name":"Al's Airport Inn",
    "wof:placetype":"venue"
},
  "geometry": {"coordinates":[-74.820567,40.267359],"type":"Point"}
}