{
  "type": "Feature",
  "properties": {
    "addr:full":"209 Berdan Ave Wayne NJ 07470",
    "addr:housenumber":"209",
    "addr:postcode":"07470",
    "addr:street":"Berdan Ave",
    "iso:country":"US",
    "sg:address":"209 Berdan Ave",
    "sg:city":"Wayne",
    "sg:classifiers":[
        {
            "category":"Restaurant",
            "type":"Food & Drink"
        }
    ],
    "sg:phone":"+1 973 694 0828",
    "sg:postcode":"07470",
    "sg:province":"NJ",
    "sg:tags":[
        "chinese"
    ],
    "wof:name":"Happy Panda Chinese Restaurant",
    "wof:placetype":"venue"
},
  "geometry": {"coordinates":[-74.243202,40.967602],"type":"Point"}
}