{
  "type": "Feature",
  "properties": {
    "addr:full":"504 Valley Rd Wayne NJ 07470",
    "addr:housenumber":"504",
    "addr:postcode":"07470",
    "addr:street":"Valley Rd",
    "iso:country":"US",
    "sg:address":"504 Valley Rd",
    "sg:city":"Wayne",
    "sg:classifiers":[
        {
            "category":"Professional",
            "subcategory":"Management & Consulting",
            "type":"Services"
        }
    ],
    "sg:phone":"+1 973 696 5703",
    "sg:postcode":"07470",
    "sg:province":"NJ",
    "sg:tags":[
        "business"
    ],
    "wof:name":"O Conner Robert",
    "wof:placetype":"venue"
},
  "geometry": {"coordinates":[-74.228826,40.929206],"type":"Point"}
}