{
  "type": "Feature",
  "properties": {
    "addr:full":"2177 Millburn Ave Maplewood NJ 07040",
    "addr:housenumber":"2177",
    "addr:postcode":"07040",
    "addr:street":"Millburn Ave",
    "iso:country":"US",
    "sg:address":"2177 Millburn Ave",
    "sg:city":"Maplewood",
    "sg:classifiers":[
        {
            "category":"Autos & Motor Vehicles",
            "subcategory":"Fuel & Gas Station",
            "type":"Retail Goods"
        }
    ],
    "sg:phone":"+1 973 762 6552",
    "sg:postcode":"07040",
    "sg:province":"NJ",
    "wof:name":"Garden State Gulf",
    "wof:placetype":"venue"
},
  "geometry": {"coordinates":[-74.28299699999999,40.722301],"type":"Point"}
}