{
  "type": "Feature",
  "properties": {
    "iso:country":"US",
    "sg:address":"21 Jamie Ct",
    "sg:city":"Bloomfield",
    "sg:classifiers":[
        {
            "category":"Professional",
            "subcategory":"Business Services",
            "type":"Services"
        }
    ],
    "sg:phone":"+1   ",
    "sg:postcode":"07003",
    "sg:province":"NJ",
    "wof:name":"Vegas Enterprises",
    "wof:placetype":"venue"
},
  "geometry": {"coordinates":[-74.177318,40.809825],"type":"Point"}
}