{
  "type": "Feature",
  "properties": {
    "iso:country":"US",
    "sg:address":"1049 Clinton Ave",
    "sg:city":"Irvington",
    "sg:classifiers":[
        {
            "category":"Education",
            "subcategory":"Vocational School",
            "type":"Public Place"
        }
    ],
    "sg:phone":"+1 973 373 3900",
    "sg:postcode":"07111",
    "sg:province":"NJ",
    "sg:tags":[
        "insurance"
    ],
    "wof:name":"Garden State School Business",
    "wof:placetype":"venue"
},
  "geometry": {"coordinates":[-74.244005,40.730678],"type":"Point"}
}