{
  "type": "Feature",
  "properties": {
    "iso:country":"US",
    "sg:address":"11 Asperula Dr",
    "sg:city":"Sicklerville",
    "sg:classifiers":[
        {
            "category":"Building & Trades",
            "subcategory":"Pest Control",
            "type":"Services"
        }
    ],
    "sg:phone":"+1   ",
    "sg:postcode":"08081",
    "sg:province":"NJ",
    "wof:name":"B P Pest Control Inc",
    "wof:placetype":"venue"
},
  "geometry": {"coordinates":[-75.01952199999999,39.730022],"type":"Point"}
}