{
  "type": "Feature",
  "properties": {
    "addr:full":"47 Dorchester Ct Hillsborough NJ 08844",
    "addr:housenumber":"47",
    "addr:postcode":"08844",
    "addr:street":"Dorchester Ct",
    "iso:country":"US",
    "sg:address":"47 Dorchester Ct",
    "sg:city":"Hillsborough",
    "sg:classifiers":[
        {
            "category":"Retail",
            "subcategory":"Photofinishing",
            "type":"Services"
        }
    ],
    "sg:phone":"+1 908 281 0328",
    "sg:postcode":"08844",
    "sg:province":"NJ",
    "sg:tags":[
        "printing",
        "film",
        "developing"
    ],
    "wof:name":"Ultimate Graphics",
    "wof:placetype":"venue"
},
  "geometry": {"coordinates":[-74.668982,40.503755],"type":"Point"}
}