{
  "type": "Feature",
  "properties": {
    "addr:full":"710 Moorlyn Ter Ocean City NJ 08226",
    "addr:housenumber":"710",
    "addr:postcode":"08226",
    "addr:street":"Moorlyn Ter",
    "iso:country":"US",
    "sg:address":"710 Moorlyn Ter",
    "sg:city":"Ocean City",
    "sg:classifiers":[
        {
            "category":"Real Estate",
            "subcategory":"Real Estate Operator",
            "type":"Services"
        }
    ],
    "sg:phone":"+1 609 399 4858",
    "sg:postcode":"08226",
    "sg:province":"NJ",
    "sg:tags":[
        "boarding",
        "house"
    ],
    "wof:name":"Carousel Inn",
    "wof:placetype":"venue"
},
  "geometry": {"coordinates":[-74.572354,39.277073],"type":"Point"}
}