{
  "type": "Feature",
  "properties": {
    "addr:full":"815 Charleston Rd Mount Laurel NJ 08054",
    "addr:housenumber":"815",
    "addr:postcode":"08054",
    "addr:street":"Charleston Rd",
    "iso:country":"US",
    "sg:address":"815 Charleston Rd",
    "sg:city":"Mount Laurel",
    "sg:classifiers":[
        {
            "category":"Cinema",
            "subcategory":"Movie Rental",
            "type":"Entertainment"
        }
    ],
    "sg:phone":"+1   ",
    "sg:postcode":"08054",
    "sg:province":"NJ",
    "sg:tags":[
        "video",
        "tape",
        "rent"
    ],
    "wof:name":"Movies R US",
    "wof:placetype":"venue"
},
  "geometry": {"coordinates":[-74.933933,39.928242],"type":"Point"}
}