{
  "type": "Feature",
  "properties": {
    "addr:full":"62 Ferry St South River NJ 08882",
    "addr:housenumber":"62",
    "addr:postcode":"08882",
    "addr:street":"Ferry St",
    "iso:country":"US",
    "sg:address":"62 Ferry St",
    "sg:city":"South River",
    "sg:classifiers":[
        {
            "category":"Restaurant",
            "type":"Food & Drink"
        }
    ],
    "sg:phone":"+1 732 651 0020",
    "sg:postcode":"08882",
    "sg:province":"NJ",
    "wof:name":"Restaurant Takueria LA Mxtkt",
    "wof:placetype":"venue"
},
  "geometry": {"coordinates":[-74.37921299999999,40.451389],"type":"Point"}
}