{
  "type": "Feature",
  "properties": {
    "iso:country":"US",
    "sg:address":"20 Greenway Ct",
    "sg:city":"Closter",
    "sg:classifiers":[
        {
            "category":"Professional",
            "subcategory":"Accounting & Tax Preparation",
            "type":"Services"
        }
    ],
    "sg:phone":"+1   ",
    "sg:postcode":"07624",
    "sg:province":"NJ",
    "wof:name":"Robert H Rosenblum Co",
    "wof:placetype":"venue"
},
  "geometry": {"coordinates":[-73.94837,40.974894],"type":"Point"}
}