{
  "type": "Feature",
  "properties": {
    "iso:country":"US",
    "sg:address":"1 Woodbridge Ctr",
    "sg:city":"Woodbridge",
    "sg:classifiers":[
        {
            "category":"Shopping",
            "subcategory":"Jewelry",
            "type":"Retail Goods"
        }
    ],
    "sg:phone":"+1 732 636 6666",
    "sg:postcode":"07095",
    "sg:province":"NJ",
    "wof:name":"House of Diamonds",
    "wof:placetype":"venue"
},
  "geometry": {"coordinates":[-74.298103,40.547699],"type":"Point"}
}