{
  "type": "Feature",
  "properties": {
    "iso:country":"US",
    "sg:address":"175 Washington Ave",
    "sg:city":"Dumont",
    "sg:classifiers":[
        {
            "category":"Insurance",
            "subcategory":"Insurance Agent",
            "type":"Services"
        }
    ],
    "sg:phone":"+1 201 384 2323",
    "sg:postcode":"07628",
    "sg:province":"NJ",
    "wof:name":"Mc Carthy Hillside Insurance",
    "wof:placetype":"venue"
},
  "geometry": {"coordinates":[-73.99350099999999,40.94107],"type":"Point"}
}