{
  "type": "Feature",
  "properties": {
    "addr:full":"16 Hillyer St Orange NJ 07050",
    "addr:housenumber":"16",
    "addr:postcode":"07050",
    "addr:street":"Hillyer St",
    "iso:country":"US",
    "sg:address":"16 Hillyer St",
    "sg:city":"Orange",
    "sg:classifiers":[
        {
            "category":"Communications",
            "type":"Services"
        }
    ],
    "sg:phone":"+1 973 672 8660",
    "sg:postcode":"07050",
    "sg:province":"NJ",
    "wof:name":"Clear Point Communications",
    "wof:placetype":"venue"
},
  "geometry": {"coordinates":[-74.22228200000001,40.769363],"type":"Point"}
}