{
  "type": "Feature",
  "properties": {
    "addr:full":"16 Country Club Ln Newton NJ 07860",
    "addr:housenumber":"16",
    "addr:postcode":"07860",
    "addr:street":"Country Club Ln",
    "iso:country":"US",
    "sg:address":"16 Country Club Ln",
    "sg:city":"Newton",
    "sg:classifiers":[
        {
            "category":"Building & Trades",
            "subcategory":"Construction",
            "type":"Services"
        }
    ],
    "sg:phone":"+1 973 383 6898",
    "sg:postcode":"07860",
    "sg:province":"NJ",
    "sg:tags":[
        "hanging",
        "contractor"
    ],
    "wof:name":"Just Right Painting",
    "wof:placetype":"venue"
},
  "geometry": {"coordinates":[-74.72510800000001,41.046433],"type":"Point"}
}