{
  "type": "Feature",
  "properties": {
    "addr:full":"30 Ryder Rd Wayne NJ 07470",
    "addr:housenumber":"30",
    "addr:postcode":"07470",
    "addr:street":"Ryder Rd",
    "iso:country":"US",
    "sg:address":"30 Ryder Rd",
    "sg:city":"Wayne",
    "sg:classifiers":[
        {
            "category":"Professional",
            "subcategory":"Secretarial Services",
            "type":"Services"
        }
    ],
    "sg:phone":"+1 973 956 1172",
    "sg:postcode":"07470",
    "sg:province":"NJ",
    "sg:tags":[
        "reporting",
        "court"
    ],
    "wof:name":"Misaj Transcription",
    "wof:placetype":"venue"
},
  "geometry": {"coordinates":[-74.21897199999999,40.942344],"type":"Point"}
}