{
  "type": "Feature",
  "properties": {
    "addr:full":"84 Veronica Ave Somerset NJ 08873",
    "addr:housenumber":"84",
    "addr:postcode":"08873",
    "addr:street":"Veronica Ave",
    "iso:country":"US",
    "sg:address":"84 Veronica Ave",
    "sg:city":"Somerset",
    "sg:classifiers":[
        {
            "category":"Personal",
            "subcategory":"Beauty Salon",
            "type":"Services"
        }
    ],
    "sg:phone":"+1 732 246 8884",
    "sg:postcode":"08873",
    "sg:province":"NJ",
    "wof:name":"Bamboo Hair & Body Salon",
    "wof:placetype":"venue"
},
  "geometry": {"coordinates":[-74.493826,40.476066],"type":"Point"}
}