{
  "type": "Feature",
  "properties": {
    "addr:full":"48 Sutton Rd Lebanon NJ 08833",
    "addr:housenumber":"48",
    "addr:postcode":"08833",
    "addr:street":"Sutton Rd",
    "iso:country":"US",
    "sg:address":"48 Sutton Rd",
    "sg:city":"Lebanon",
    "sg:classifiers":[
        {
            "category":"Autos & Motor Vehicles",
            "subcategory":"Auto Supplies",
            "type":"Retail Goods"
        }
    ],
    "sg:phone":"+1 908 832 7405",
    "sg:postcode":"08833",
    "sg:province":"NJ",
    "sg:tags":[
        "automobile",
        "parts"
    ],
    "sg:website":"www.frogworks.com",
    "wof:name":"Frogworks International Inc",
    "wof:placetype":"venue"
},
  "geometry": {"coordinates":[-74.810147,40.712197],"type":"Point"}
}