{
  "type": "Feature",
  "properties": {
    "addr:full":"440 Washington St Newark NJ 07102",
    "addr:housenumber":"440",
    "addr:postcode":"07102",
    "addr:street":"Washington St",
    "iso:country":"US",
    "sg:address":"440 Washington St",
    "sg:city":"Newark",
    "sg:classifiers":[
        {
            "category":"Professional",
            "type":"Services"
        }
    ],
    "sg:phone":"+1 973 733 3445",
    "sg:postcode":"07102",
    "sg:province":"NJ",
    "sg:tags":[
        "establishment"
    ],
    "wof:name":"Hunter's Home Healers",
    "wof:placetype":"venue"
},
  "geometry": {"coordinates":[-74.178534,40.730319],"type":"Point"}
}