{
  "type": "Feature",
  "properties": {
    "iso:country":"US",
    "sg:address":"830 Broad St",
    "sg:city":"Shrewsbury",
    "sg:classifiers":[
        {
            "category":"Social Services",
            "type":"Services"
        }
    ],
    "sg:phone":"+1   ",
    "sg:postcode":"07702",
    "sg:province":"NJ",
    "sg:tags":[
        "organization",
        "welfare"
    ],
    "wof:name":"American Red Cross",
    "wof:placetype":"venue"
},
  "geometry": {"coordinates":[-74.061775,40.325714],"type":"Point"}
}