{
  "type": "Feature",
  "properties": {
    "iso:country":"US",
    "sg:address":"1313 Vermont Ave",
    "sg:city":"Manville",
    "sg:classifiers":[
        {
            "category":"Building & Trades",
            "subcategory":"Equipment Rental",
            "type":"Services"
        }
    ],
    "sg:phone":"+1 908 707 1448",
    "sg:postcode":"08835",
    "sg:province":"NJ",
    "wof:name":"Fun For Kids CJ Party Rentals",
    "wof:placetype":"venue"
},
  "geometry": {"coordinates":[-74.598553,40.540894],"type":"Point"}
}