{
  "type": "Feature",
  "properties": {
    "iso:country":"US",
    "sg:address":"23 Garden St",
    "sg:city":"South River",
    "sg:classifiers":[
        {
            "category":"Professional",
            "subcategory":"Art Services",
            "type":"Services"
        }
    ],
    "sg:phone":"+1   ",
    "sg:postcode":"08882",
    "sg:province":"NJ",
    "sg:tags":[
        "photography",
        "commercial"
    ],
    "wof:name":"Ellies Images",
    "wof:placetype":"venue"
},
  "geometry": {"coordinates":[-74.37899899999999,40.43096],"type":"Point"}
}