{
  "type": "Feature",
  "properties": {
    "iso:country":"US",
    "sg:address":"3204 Beachview Dr",
    "sg:city":"Toms River",
    "sg:classifiers":[
        {
            "category":"Building & Trades",
            "subcategory":"Plumbing",
            "type":"Services"
        }
    ],
    "sg:phone":"+1 732 288 0222",
    "sg:postcode":"08753",
    "sg:province":"NJ",
    "sg:tags":[
        "plumbing",
        "contractor"
    ],
    "wof:name":"Perry's Plumbing & Heating Inc",
    "wof:placetype":"venue"
},
  "geometry": {"coordinates":[-74.112943,39.955094],"type":"Point"}
}