{
  "type": "Feature",
  "properties": {
    "iso:country":"US",
    "sg:address":"155 Paterson Ave",
    "sg:city":"Wallington",
    "sg:classifiers":[
        {
            "category":"Professional",
            "subcategory":"Business Services",
            "type":"Services"
        }
    ],
    "sg:phone":"+1 973 916 9965",
    "sg:postcode":"07057",
    "sg:province":"NJ",
    "sg:tags":[
        "appraiser"
    ],
    "wof:name":"CSR Appraisals",
    "wof:placetype":"venue"
},
  "geometry": {"coordinates":[-74.114822,40.850462],"type":"Point"}
}