{
  "type": "Feature",
  "properties": {
    "addr:full":"436 Marlyn Ave Hammonton NJ 08037",
    "addr:housenumber":"436",
    "addr:postcode":"08037",
    "addr:street":"Marlyn Ave",
    "iso:country":"US",
    "sg:address":"436 Marlyn Ave",
    "sg:city":"Hammonton",
    "sg:classifiers":[
        {
            "category":"Retail",
            "subcategory":"Repair Shop",
            "type":"Services"
        }
    ],
    "sg:phone":"+1 609 567 5540",
    "sg:postcode":"08037",
    "sg:province":"NJ",
    "sg:tags":[
        "repairing",
        "piano",
        "refinishing"
    ],
    "wof:name":"Ordille's Piano Tuning",
    "wof:placetype":"venue"
},
  "geometry": {"coordinates":[-74.78801799999999,39.642231],"type":"Point"}
}