{
  "type": "Feature",
  "properties": {
    "iso:country":"US",
    "sg:address":"356 Flaam St",
    "sg:city":"Toms River",
    "sg:classifiers":[
        {
            "category":"Professional",
            "subcategory":"Management & Consulting",
            "type":"Services"
        }
    ],
    "sg:phone":"+1 732 270 8117",
    "sg:postcode":"08753",
    "sg:province":"NJ",
    "sg:tags":[
        "consultant",
        "business"
    ],
    "wof:name":"Mc Cray Assoc",
    "wof:placetype":"venue"
},
  "geometry": {"coordinates":[-74.156171,39.983818],"type":"Point"}
}