{
  "type": "Feature",
  "properties": {
    "addr:full":"960 Radio Rd Little Egg Hbr NJ 08087",
    "addr:housenumber":"960",
    "addr:postcode":"08087",
    "addr:street":"Radio Rd",
    "iso:country":"US",
    "sg:address":"960 Radio Rd",
    "sg:city":"Little Egg Hbr",
    "sg:classifiers":[
        {
            "category":"Professional",
            "subcategory":"Lawyer & Legal Services",
            "type":"Services"
        }
    ],
    "sg:phone":"+1 609 294 2227",
    "sg:postcode":"08087",
    "sg:province":"NJ",
    "sg:tags":[
        "attorney"
    ],
    "wof:name":"Brian E Rumpf",
    "wof:placetype":"venue"
},
  "geometry": {"coordinates":[-74.36994,39.567473],"type":"Point"}
}