{
  "type": "Feature",
  "properties": {
    "iso:country":"US",
    "sg:address":"300 Millburn Ave",
    "sg:city":"Millburn",
    "sg:classifiers":[
        {
            "category":"Government",
            "subcategory":"Post Office",
            "type":"Public Place"
        }
    ],
    "sg:phone":"+1 973 376 2966",
    "sg:postcode":"07041",
    "sg:province":"NJ",
    "sg:tags":[
        "postal",
        "us"
    ],
    "wof:name":"US Post Office",
    "wof:placetype":"venue"
},
  "geometry": {"coordinates":[-74.30358699999999,40.724481],"type":"Point"}
}