{
  "type": "Feature",
  "properties": {
    "iso:country":"US",
    "sg:address":"7 Chimney Rock Rd",
    "sg:city":"Bridgewater",
    "sg:classifiers":[
        {
            "category":"Wholesale",
            "subcategory":"Machinery & Supplies",
            "type":"Manufacturing & Wholesale Goods"
        }
    ],
    "sg:phone":"+1 732 469 7009",
    "sg:postcode":"08807",
    "sg:province":"NJ",
    "sg:tags":[
        "equipment",
        "industrial",
        "hydraulic"
    ],
    "sg:website":"www.indrubber.com",
    "wof:name":"Industrial Rubber Co Inc",
    "wof:placetype":"venue"
},
  "geometry": {"coordinates":[-74.565021,40.56206],"type":"Point"}
}