{
  "type": "Feature",
  "properties": {
    "iso:country":"US",
    "sg:address":"46 Preakness Ave",
    "sg:city":"Paterson",
    "sg:classifiers":[
        {
            "category":"Organizations",
            "subcategory":"Non-profit Organization",
            "type":"Services"
        }
    ],
    "sg:phone":"+1 973 956 1921",
    "sg:postcode":"07522",
    "sg:province":"NJ",
    "sg:tags":[
        "service/non-profit",
        "community"
    ],
    "wof:name":"Daughters of Charity of the Most Precious Blood",
    "wof:placetype":"venue"
},
  "geometry": {"coordinates":[-74.185303,40.914024],"type":"Point"}
}