{
  "type": "Feature",
  "properties": {
    "iso:country":"US",
    "sg:address":"11 Pearl St",
    "sg:city":"North Plainfield",
    "sg:classifiers":[
        {
            "category":"Building & Trades",
            "subcategory":"Pest Control",
            "type":"Services"
        }
    ],
    "sg:phone":"+1 908 757 6161",
    "sg:postcode":"07060",
    "sg:province":"NJ",
    "sg:tags":[
        "termite"
    ],
    "wof:name":"Mantis Pest Control Inc",
    "wof:placetype":"venue"
},
  "geometry": {"coordinates":[-74.424796,40.620626],"type":"Point"}
}