{
  "type": "Feature",
  "properties": {
    "addr:full":"5 Hanover Ct Princeton NJ 08540",
    "addr:housenumber":"5",
    "addr:postcode":"08540",
    "addr:street":"Hanover Ct",
    "iso:country":"US",
    "sg:address":"5 Hanover Ct",
    "sg:city":"Princeton",
    "sg:classifiers":[
        {
            "category":"Professional",
            "subcategory":"Computer Services",
            "type":"Services"
        }
    ],
    "sg:phone":"+1 609 720 0703",
    "sg:postcode":"08540",
    "sg:province":"NJ",
    "sg:tags":[
        "programing",
        "custom"
    ],
    "wof:name":"Jetfrog LLC",
    "wof:placetype":"venue"
},
  "geometry": {"coordinates":[-74.651523,40.327715],"type":"Point"}
}