{
  "type": "Feature",
  "properties": {
    "addr:full":"54 Fort Dix St Wrightstown NJ 08562",
    "addr:housenumber":"54",
    "addr:postcode":"08562",
    "addr:street":"Fort Dix St",
    "iso:country":"US",
    "sg:address":"54 Fort Dix St",
    "sg:city":"Wrightstown",
    "sg:classifiers":[
        {
            "category":"Travel",
            "subcategory":"Hotels & Motels",
            "type":"Entertainment"
        }
    ],
    "sg:phone":"+1 609 723 2323",
    "sg:postcode":"08562",
    "sg:province":"NJ",
    "wof:name":"Relax Inn",
    "wof:placetype":"venue"
},
  "geometry": {"coordinates":[-74.617829,40.036204],"type":"Point"}
}