{
  "type": "Feature",
  "properties": {
    "addr:full":"98 Neptune Ave Neptune City NJ 07753",
    "addr:housenumber":"98",
    "addr:postcode":"07753",
    "addr:street":"Neptune Ave",
    "iso:country":"US",
    "sg:address":"98 Neptune Ave",
    "sg:city":"Neptune City",
    "sg:classifiers":[
        {
            "category":"Professional",
            "subcategory":"Management & Consulting",
            "type":"Services"
        }
    ],
    "sg:phone":"+1 732 988 0500",
    "sg:postcode":"07753",
    "sg:province":"NJ",
    "sg:tags":[
        "construction"
    ],
    "wof:name":"J W Petrosino Inc",
    "wof:placetype":"venue"
},
  "geometry": {"coordinates":[-74.03394299999999,40.202748],"type":"Point"}
}