{
  "type": "Feature",
  "properties": {
    "iso:country":"US",
    "sg:address":"655 Pomander Walk",
    "sg:city":"Teaneck",
    "sg:classifiers":[
        {
            "category":"Health Services",
            "subcategory":"Health Practitioner",
            "type":"Services"
        }
    ],
    "sg:phone":"+1 201 836 2990",
    "sg:postcode":"07666",
    "sg:province":"NJ",
    "sg:tags":[
        "therapist",
        "therapy",
        "physical"
    ],
    "wof:name":"Physical Medicine",
    "wof:placetype":"venue"
},
  "geometry": {"coordinates":[-74.032267,40.889114],"type":"Point"}
}