{
  "type": "Feature",
  "properties": {
    "iso:country":"US",
    "sg:address":"14 Wall St",
    "sg:city":"Princeton",
    "sg:classifiers":[
        {
            "category":"Professional",
            "subcategory":"Computer Services",
            "type":"Services"
        }
    ],
    "sg:phone":"+1   ",
    "sg:postcode":"08540",
    "sg:province":"NJ",
    "sg:tags":[
        "related"
    ],
    "sg:website":"www.princetonimaging.com",
    "wof:name":"Princeton Imaging",
    "wof:placetype":"venue"
},
  "geometry": {"coordinates":[-74.651893,40.396972],"type":"Point"}
}