{
  "type": "Feature",
  "properties": {
    "addr:full":"11 Richmond St Clifton NJ 07011",
    "addr:housenumber":"11",
    "addr:postcode":"07011",
    "addr:street":"Richmond St",
    "iso:country":"US",
    "sg:address":"11 Richmond St",
    "sg:city":"Clifton",
    "sg:classifiers":[
        {
            "category":"Manufacturing",
            "subcategory":"Printing",
            "type":"Manufacturing & Wholesale Goods"
        }
    ],
    "sg:phone":"+1 973 772 2661",
    "sg:postcode":"07011",
    "sg:province":"NJ",
    "sg:tags":[
        "lithographic",
        "commercial"
    ],
    "wof:name":"Trag Press Inc",
    "wof:placetype":"venue"
},
  "geometry": {"coordinates":[-74.160709,40.888903],"type":"Point"}
}