{
  "type": "Feature",
  "properties": {
    "iso:country":"US",
    "sg:address":"12 Woodland Dr",
    "sg:city":"Cranbury",
    "sg:classifiers":[
        {
            "category":"Professional",
            "subcategory":"Computer Services",
            "type":"Services"
        }
    ],
    "sg:phone":"+1   ",
    "sg:postcode":"08512",
    "sg:province":"NJ",
    "sg:tags":[
        "prepackaged",
        "software",
        "custom"
    ],
    "wof:name":"Compton Software Inc",
    "wof:placetype":"venue"
},
  "geometry": {"coordinates":[-74.55947399999999,40.341328],"type":"Point"}
}