{
  "type": "Feature",
  "properties": {
    "iso:country":"US",
    "sg:address":"53 Milestone Dr",
    "sg:city":"Ringoes",
    "sg:classifiers":[
        {
            "category":"Professional",
            "subcategory":"Computer Services",
            "type":"Services"
        }
    ],
    "sg:phone":"+1   ",
    "sg:postcode":"08551",
    "sg:province":"NJ",
    "sg:tags":[
        "development",
        "management",
        "financial",
        "software"
    ],
    "wof:name":"Sonic Technical Solutions",
    "wof:placetype":"venue"
},
  "geometry": {"coordinates":[-74.895067,40.476594],"type":"Point"}
}