{
  "type": "Feature",
  "properties": {
    "addr:full":"180 Monroe St Passaic NJ 07055",
    "addr:housenumber":"180",
    "addr:postcode":"07055",
    "addr:street":"Monroe St",
    "iso:country":"US",
    "sg:address":"180 Monroe St",
    "sg:city":"Passaic",
    "sg:classifiers":[
        {
            "category":"Building & Trades",
            "subcategory":"Construction",
            "type":"Services"
        }
    ],
    "sg:phone":"+1 973 779 4846",
    "sg:postcode":"07055",
    "sg:province":"NJ",
    "sg:tags":[
        "contractor"
    ],
    "wof:name":"Inca Builders Inc",
    "wof:placetype":"venue"
},
  "geometry": {"coordinates":[-74.120926,40.867275],"type":"Point"}
}