{
  "type": "Feature",
  "properties": {
    "iso:country":"US",
    "sg:address":"1005 Whitehead Rd",
    "sg:city":"Trenton",
    "sg:classifiers":[
        {
            "category":"Wholesale",
            "subcategory":"Auto Parts",
            "type":"Manufacturing & Wholesale Goods"
        }
    ],
    "sg:phone":"+1 609 538 0568",
    "sg:postcode":"08638",
    "sg:province":"NJ",
    "sg:tags":[
        "automobile",
        "retail",
        "used",
        "supply"
    ],
    "wof:name":"Central Mouldings Corporation",
    "wof:placetype":"venue"
},
  "geometry": {"coordinates":[-74.7538,40.259185],"type":"Point"}
}