{
  "type": "Feature",
  "properties": {
    "addr:full":"1214 Stewart Ave Asbury Park NJ 07712",
    "addr:housenumber":"1214",
    "addr:postcode":"07712",
    "addr:street":"Stewart Ave Asbury",
    "iso:country":"US",
    "sg:address":"1214 Stewart Ave",
    "sg:city":"Asbury Park",
    "sg:classifiers":[
        {
            "category":"Building & Trades",
            "subcategory":"Construction",
            "type":"Services"
        }
    ],
    "sg:phone":"+1 732 774 4144",
    "sg:postcode":"07712",
    "sg:province":"NJ",
    "sg:tags":[
        "specializing",
        "contractor",
        "installation",
        "interlocking",
        "paving"
    ],
    "wof:name":"Landloc Paver Systems Inc",
    "wof:placetype":"venue"
},
  "geometry": {"coordinates":[-74.02833800000001,40.230346],"type":"Point"}
}