{
  "type": "Feature",
  "properties": {
    "iso:country":"US",
    "sg:address":"18 Commerce Rd Ste N",
    "sg:city":"Fairfield",
    "sg:classifiers":[
        {
            "category":"Arts & Performance",
            "subcategory":"Art Gallery",
            "type":"Entertainment"
        },
        {
            "category":"Professional",
            "subcategory":"Art Services",
            "type":"Services"
        }
    ],
    "sg:phone":"+1 973 575 4814",
    "sg:postcode":"07004",
    "sg:province":"NJ",
    "sg:tags":[
        "framing"
    ],
    "wof:name":"Picture Frame Outlet",
    "wof:placetype":"venue"
},
  "geometry": {"coordinates":[-74.318001,40.871899],"type":"Point"}
}