{
  "type": "Feature",
  "properties": {
    "addr:full":"2222 Shore Dr Belmar NJ 07719",
    "addr:housenumber":"2222",
    "addr:postcode":"07719",
    "addr:street":"Shore Dr",
    "iso:country":"US",
    "sg:address":"2222 Shore Dr",
    "sg:city":"Belmar",
    "sg:classifiers":[
        {
            "category":"Restaurant",
            "type":"Food & Drink"
        }
    ],
    "sg:phone":"+1   ",
    "sg:postcode":"07719",
    "sg:province":"NJ",
    "sg:tags":[
        "eating"
    ],
    "wof:name":"Bobs Fms Deli Pizzaria & Grmt",
    "wof:placetype":"venue"
},
  "geometry": {"coordinates":[-74.059718,40.181836],"type":"Point"}
}