{
  "type": "Feature",
  "properties": {
    "iso:country":"US",
    "sg:address":"69 Rainbow Hill Rd",
    "sg:city":"Flemington",
    "sg:classifiers":[
        {
            "category":"Building & Trades",
            "subcategory":"Construction",
            "type":"Services"
        }
    ],
    "sg:phone":"+1 908 369 0772",
    "sg:postcode":"08822",
    "sg:province":"NJ",
    "sg:tags":[
        "carpentry",
        "contractor"
    ],
    "wof:name":"Dp Designs",
    "wof:placetype":"venue"
},
  "geometry": {"coordinates":[-74.776658,40.476991],"type":"Point"}
}