{
  "type": "Feature",
  "properties": {
    "addr:full":"5836 Moss Mill Rd Egg Harbor City NJ 08215",
    "addr:housenumber":"5836",
    "addr:postcode":"08215",
    "addr:street":"Moss Mill Rd",
    "iso:country":"US",
    "sg:address":"5836 Moss Mill Rd",
    "sg:city":"Egg Harbor City",
    "sg:classifiers":[
        {
            "category":"Travel",
            "subcategory":"Travel Agent",
            "type":"Entertainment"
        }
    ],
    "sg:phone":"+1 609 266 3100",
    "sg:postcode":"08215",
    "sg:province":"NJ",
    "sg:tags":[
        "agency"
    ],
    "wof:name":"Island Travel",
    "wof:placetype":"venue"
},
  "geometry": {"coordinates":[-74.643964,39.551634],"type":"Point"}
}