{
  "type": "Feature",
  "properties": {
    "addr:full":"14 Rutgers Rd Parlin NJ 08859",
    "addr:housenumber":"14",
    "addr:postcode":"08859",
    "addr:street":"Rutgers Rd",
    "iso:country":"US",
    "sg:address":"14 Rutgers Rd",
    "sg:city":"Parlin",
    "sg:classifiers":[
        {
            "category":"Building & Trades",
            "subcategory":"Electrical",
            "type":"Services"
        }
    ],
    "sg:phone":"+1 732 316 0118",
    "sg:postcode":"08859",
    "sg:province":"NJ",
    "sg:tags":[
        "electric",
        "contractor"
    ],
    "wof:name":"NJC Electric",
    "wof:placetype":"venue"
},
  "geometry": {"coordinates":[-74.306225,40.456829],"type":"Point"}
}