{
  "type": "Feature",
  "properties": {
    "iso:country":"US",
    "sg:address":"19 Clarke St",
    "sg:city":"Dumont",
    "sg:classifiers":[
        {
            "category":"Building & Trades",
            "subcategory":"Plumbing",
            "type":"Services"
        }
    ],
    "sg:phone":"+1 201 385 4807",
    "sg:postcode":"07628",
    "sg:province":"NJ",
    "sg:tags":[
        "conditioning",
        "air",
        "system",
        "contractor"
    ],
    "wof:name":"E N Paul Air Conditioning",
    "wof:placetype":"venue"
},
  "geometry": {"coordinates":[-73.981037,40.939637],"type":"Point"}
}