{
  "type": "Feature",
  "properties": {
    "iso:country":"US",
    "sg:address":"102 Michigan Ave",
    "sg:city":"Trenton",
    "sg:classifiers":[
        {
            "category":"Manufacturing",
            "subcategory":"Tools & Machinery",
            "type":"Manufacturing & Wholesale Goods"
        }
    ],
    "sg:phone":"+1 609 295 0256",
    "sg:postcode":"08648",
    "sg:province":"NJ",
    "wof:name":"Model Shop Machine Co",
    "wof:placetype":"venue"
},
  "geometry": {"coordinates":[-74.741496,40.244528],"type":"Point"}
}