{
  "type": "Feature",
  "properties": {
    "addr:full":"601 Piermont Rd Demarest NJ 07627",
    "addr:housenumber":"601",
    "addr:postcode":"07627",
    "addr:street":"Piermont Rd",
    "iso:country":"US",
    "sg:address":"601 Piermont Rd",
    "sg:city":"Demarest",
    "sg:classifiers":[
        {
            "category":"Professional",
            "subcategory":"Management & Consulting",
            "type":"Services"
        }
    ],
    "sg:phone":"+1 201 768 7059",
    "sg:postcode":"07627",
    "sg:province":"NJ",
    "sg:tags":[
        "consultant",
        "hygiene",
        "industrial"
    ],
    "sg:website":"www.daienviro.com",
    "wof:name":"Detail Associates Inc",
    "wof:placetype":"venue"
},
  "geometry": {"coordinates":[-73.959065,40.960606],"type":"Point"}
}