{
  "type": "Feature",
  "properties": {
    "iso:country":"US",
    "sg:address":"22 Hobart Pl",
    "sg:city":"Clifton",
    "sg:classifiers":[
        {
            "category":"Professional",
            "subcategory":"Management & Consulting",
            "type":"Services"
        },
        {
            "category":"Professional",
            "subcategory":"Computer Services",
            "type":"Services"
        }
    ],
    "sg:phone":"+1 973 546 0242",
    "sg:postcode":"07011",
    "sg:province":"NJ",
    "sg:tags":[
        "rooms-installation",
        "facility",
        "consultant",
        "space",
        "equipment",
        "planning"
    ],
    "wof:name":"Advantage It Corporation",
    "wof:placetype":"venue"
},
  "geometry": {"coordinates":[-74.152838,40.873114],"type":"Point"}
}