{
  "type": "Feature",
  "properties": {
    "addr:full":"777 Alexander Rd Princeton NJ 08540",
    "addr:housenumber":"777",
    "addr:postcode":"08540",
    "addr:street":"Alexander Rd",
    "iso:country":"US",
    "sg:address":"777 Alexander Rd",
    "sg:city":"Princeton",
    "sg:classifiers":[
        {
            "category":"Real Estate",
            "subcategory":"Developer",
            "type":"Services"
        }
    ],
    "sg:phone":"+1 609 987 8968",
    "sg:postcode":"08540",
    "sg:province":"NJ",
    "wof:name":"Telesys Development Corp",
    "wof:placetype":"venue"
},
  "geometry": {"coordinates":[-74.632846,40.316432],"type":"Point"}
}