{
  "type": "Feature",
  "properties": {
    "iso:country":"US",
    "sg:address":"1117 Hessian Ave",
    "sg:city":"National Park",
    "sg:classifiers":[
        {
            "category":"Building & Trades",
            "subcategory":"Landscaping Services",
            "type":"Services"
        }
    ],
    "sg:phone":"+1 856 848 0052",
    "sg:postcode":"08063",
    "sg:province":"NJ",
    "sg:tags":[
        "trimming",
        "tree",
        "removal"
    ],
    "wof:name":"Expert Tree Service Inc",
    "wof:placetype":"venue"
},
  "geometry": {"coordinates":[-75.171474,39.863442],"type":"Point"}
}