{
  "type": "Feature",
  "properties": {
    "iso:country":"US",
    "sg:address":"881 Black Horse Pike",
    "sg:city":"Pleasantville",
    "sg:classifiers":[
        {
            "category":"Shopping",
            "subcategory":"Used Merchandise",
            "type":"Retail Goods"
        },
        {
            "category":"Home & Garden",
            "subcategory":"Furniture",
            "type":"Retail Goods"
        }
    ],
    "sg:phone":"+1 609 641 5079",
    "sg:postcode":"08232",
    "sg:province":"NJ",
    "sg:tags":[
        "store"
    ],
    "wof:name":"Doc's Furniture & Rest Eqp",
    "wof:placetype":"venue"
},
  "geometry": {"coordinates":[-74.540592,39.394253],"type":"Point"}
}