{
  "type": "Feature",
  "properties": {
    "addr:full":"23 Joseph St Newark NJ 07105",
    "addr:housenumber":"23",
    "addr:postcode":"07105",
    "addr:street":"Joseph St",
    "iso:country":"US",
    "sg:address":"23 Joseph St",
    "sg:city":"Newark",
    "sg:classifiers":[
        {
            "category":"Wholesale",
            "subcategory":"Groceries",
            "type":"Manufacturing & Wholesale Goods"
        }
    ],
    "sg:phone":"+1 973 274 0330",
    "sg:postcode":"07105",
    "sg:province":"NJ",
    "sg:tags":[
        "food",
        "broker"
    ],
    "wof:name":"Busari International Tropical",
    "wof:placetype":"venue"
},
  "geometry": {"coordinates":[-74.134837,40.736094],"type":"Point"}
}