{
  "type": "Feature",
  "properties": {
    "iso:country":"US",
    "sg:address":"6 Port Imperial Blvd",
    "sg:city":"Weehawken",
    "sg:classifiers":[
        {
            "category":"Insurance",
            "subcategory":"Insurance Agent",
            "type":"Services"
        }
    ],
    "sg:phone":"+1   ",
    "sg:postcode":"07086",
    "sg:province":"NJ",
    "sg:tags":[
        "firm",
        "brokerage"
    ],
    "wof:name":"Imperatore De Witt Stern",
    "wof:placetype":"venue"
},
  "geometry": {"coordinates":[-74.02024400000001,40.764738],"type":"Point"}
}