{
  "type": "Feature",
  "properties": {
    "iso:country":"US",
    "sg:address":"274 Washington St",
    "sg:city":"Perth Amboy",
    "sg:classifiers":[
        {
            "category":"Retail",
            "subcategory":"Auto Repair",
            "type":"Services"
        }
    ],
    "sg:phone":"+1 732 293 0021",
    "sg:postcode":"08861",
    "sg:province":"NJ",
    "wof:name":"Valdez Auto Repair",
    "wof:placetype":"venue"
},
  "geometry": {"coordinates":[-74.271698,40.5154],"type":"Point"}
}