{
  "type": "Feature",
  "properties": {
    "addr:full":"196 Park Ave Point Pleasant Beach NJ 08742",
    "addr:housenumber":"196",
    "addr:postcode":"08742",
    "addr:street":"Park Ave",
    "iso:country":"US",
    "sg:address":"196 Park Ave",
    "sg:city":"Point Pleasant Beach",
    "sg:classifiers":[
        {
            "category":"Professional",
            "subcategory":"Business Services",
            "type":"Services"
        }
    ],
    "sg:phone":"+1   ",
    "sg:postcode":"08742",
    "sg:province":"NJ",
    "sg:tags":[
        "support",
        "computer"
    ],
    "wof:name":"Whiz Kid Enterprises",
    "wof:placetype":"venue"
},
  "geometry": {"coordinates":[-74.05175199999999,40.072407],"type":"Point"}
}