{
  "type": "Feature",
  "properties": {
    "iso:country":"US",
    "sg:address":"200 Longhouse Dr",
    "sg:city":"Hewitt",
    "sg:classifiers":[
        {
            "category":"Shopping",
            "subcategory":"Pets & Pet Supplies",
            "type":"Retail Goods"
        },
        {
            "category":"Retail",
            "subcategory":"Veterinary Services",
            "type":"Services"
        }
    ],
    "sg:phone":"+1 973 427 5998",
    "sg:postcode":"07421",
    "sg:province":"NJ",
    "sg:tags":[
        "specialty"
    ],
    "wof:name":"American Canine Academy Inc.",
    "wof:placetype":"venue"
},
  "geometry": {"coordinates":[-74.370682,41.195839],"type":"Point"}
}