{
  "type": "Feature",
  "properties": {
    "addr:full":"220 Broadway Jersey City NJ 07306",
    "addr:housenumber":"220",
    "addr:postcode":"07306",
    "addr:street":"Broadway",
    "iso:country":"US",
    "sg:address":"220 Broadway",
    "sg:city":"Jersey City",
    "sg:classifiers":[
        {
            "category":"Home & Garden",
            "subcategory":"Carpets & Floor Coverings",
            "type":"Retail Goods"
        }
    ],
    "sg:phone":"+1 201 434 8888",
    "sg:postcode":"07306",
    "sg:province":"NJ",
    "sg:tags":[
        "material",
        "carpeting"
    ],
    "sg:website":"www.wilsonscarpet.com",
    "wof:name":"Wilson's Carpet & Furniture Inc",
    "wof:placetype":"venue"
},
  "geometry": {"coordinates":[-74.078102,40.737999],"type":"Point"}
}