{
  "type": "Feature",
  "properties": {
    "addr:full":"2394 Waldheim Ave Scotch Plains NJ 07076",
    "addr:postcode":"2394;07076",
    "addr:street":"Waldheim Ave",
    "iso:country":"US",
    "sg:address":"2394 Waldheim Ave",
    "sg:city":"Scotch Plains",
    "sg:classifiers":[
        {
            "category":"Building & Trades",
            "subcategory":"Construction",
            "type":"Services"
        }
    ],
    "sg:phone":"+1 908 301 1557",
    "sg:postcode":"07076",
    "sg:province":"NJ",
    "sg:tags":[
        "general",
        "contractor"
    ],
    "wof:name":"DAT Contractors",
    "wof:placetype":"venue"
},
  "geometry": {"coordinates":[-74.37887499999999,40.656099],"type":"Point"}
}