{
  "type": "Feature",
  "properties": {
    "addr:full":"100 Mathistown Rd Little Egg Hbr NJ 08087",
    "addr:housenumber":"100",
    "addr:postcode":"08087",
    "addr:street":"Mathistown Rd",
    "iso:country":"US",
    "sg:address":"100 Mathistown Rd",
    "sg:city":"Little Egg Hbr",
    "sg:classifiers":[
        {
            "category":"Banks & Credit Unions",
            "subcategory":"Bank",
            "type":"Services"
        }
    ],
    "sg:phone":"+1 609 000 1111",
    "sg:postcode":"08087",
    "sg:province":"NJ",
    "sg:website":"www.fleet.com",
    "wof:name":"Bank Of America",
    "wof:placetype":"venue"
},
  "geometry": {"coordinates":[-74.366046,39.578717],"type":"Point"}
}