{
  "type": "Feature",
  "properties": {
    "addr:full":"7 State Rte 31 Pennington NJ 08534",
    "addr:housenumber":"7",
    "addr:postcode":"08534",
    "addr:street":"State Rte 31",
    "iso:country":"US",
    "sg:address":"7 State Rte 31",
    "sg:city":"Pennington",
    "sg:classifiers":[
        {
            "category":"Shopping",
            "type":"Retail Goods"
        }
    ],
    "sg:phone":"+1   ",
    "sg:postcode":"08534",
    "sg:province":"NJ",
    "sg:tags":[
        "equipment",
        "sales",
        "cellular"
    ],
    "wof:name":"Wireless Zone",
    "wof:placetype":"venue"
},
  "geometry": {"coordinates":[-74.79893800000001,40.327098],"type":"Point"}
}