{
  "type": "Feature",
  "properties": {
    "addr:full":"28 Walnut St Madison NJ 07940",
    "addr:housenumber":"28",
    "addr:postcode":"07940",
    "addr:street":"Walnut St",
    "iso:country":"US",
    "sg:address":"28 Walnut St",
    "sg:city":"Madison",
    "sg:classifiers":[
        {
            "category":"Social Services",
            "type":"Services"
        }
    ],
    "sg:phone":"+1 973 537 0305",
    "sg:postcode":"07940",
    "sg:province":"NJ",
    "sg:tags":[
        "worker"
    ],
    "wof:name":"Institute For Time Effect",
    "wof:placetype":"venue"
},
  "geometry": {"coordinates":[-74.41229300000001,40.761174],"type":"Point"}
}