{
  "type": "Feature",
  "properties": {
    "addr:full":"108 Vesey St Newark NJ 07105",
    "addr:housenumber":"108",
    "addr:postcode":"07105",
    "addr:street":"Vesey St",
    "iso:country":"US",
    "sg:address":"108 Vesey St",
    "sg:city":"Newark",
    "sg:classifiers":[
        {
            "category":"Building & Trades",
            "subcategory":"Construction",
            "type":"Services"
        }
    ],
    "sg:phone":"+1 973 589 3175",
    "sg:postcode":"07105",
    "sg:province":"NJ",
    "sg:tags":[
        "hanging",
        "contractor"
    ],
    "wof:name":"Jt Painting Corp",
    "wof:placetype":"venue"
},
  "geometry": {"coordinates":[-74.16909800000001,40.724293],"type":"Point"}
}