{
  "type": "Feature",
  "properties": {
    "addr:full":"42 Iroquois Dr Parlin NJ 08859",
    "addr:housenumber":"42",
    "addr:postcode":"08859",
    "addr:street":"Iroquois Dr",
    "iso:country":"US",
    "sg:address":"42 Iroquois Dr",
    "sg:city":"Parlin",
    "sg:classifiers":[
        {
            "category":"Communications",
            "subcategory":"Film & Video Production",
            "type":"Services"
        }
    ],
    "sg:phone":"+1   ",
    "sg:postcode":"08859",
    "sg:province":"NJ",
    "sg:tags":[
        "audio",
        "design",
        "system",
        "integration"
    ],
    "wof:name":"Tadros",
    "wof:placetype":"venue"
},
  "geometry": {"coordinates":[-74.31053199999999,40.475226],"type":"Point"}
}