{
  "type": "Feature",
  "properties": {
    "addr:full":"1304 Geissel Dr Millville NJ 08332",
    "addr:housenumber":"1304",
    "addr:postcode":"08332",
    "addr:street":"Geissel Dr",
    "iso:country":"US",
    "sg:address":"1304 Geissel Dr",
    "sg:city":"Millville",
    "sg:classifiers":[
        {
            "category":"Retail",
            "subcategory":"Repair Shop",
            "type":"Services"
        }
    ],
    "sg:phone":"+1   ",
    "sg:postcode":"08332",
    "sg:province":"NJ",
    "wof:name":"TV Facts",
    "wof:placetype":"venue"
},
  "geometry": {"coordinates":[-75.06906600000001,39.385325],"type":"Point"}
}