{
  "type": "Feature",
  "properties": {
    "iso:country":"US",
    "sg:address":"135 W Ward St",
    "sg:city":"Hightstown",
    "sg:classifiers":[
        {
            "category":"Home & Garden",
            "subcategory":"Building Materials",
            "type":"Retail Goods"
        }
    ],
    "sg:phone":"+1 609 448 0507",
    "sg:postcode":"08520",
    "sg:province":"NJ",
    "sg:tags":[
        "plumbing",
        "fixture",
        "supply"
    ],
    "wof:name":"Gordon & Wilson Co",
    "wof:placetype":"venue"
},
  "geometry": {"coordinates":[-74.525835,40.267542],"type":"Point"}
}