{
  "type": "Feature",
  "properties": {
    "iso:country":"US",
    "sg:address":"104 Windsor Center Dr",
    "sg:city":"Hightstown",
    "sg:classifiers":[
        {
            "category":"Social Services",
            "subcategory":"Child Care",
            "type":"Services"
        }
    ],
    "sg:phone":"+1 609 448 4333",
    "sg:postcode":"08520",
    "sg:province":"NJ",
    "sg:tags":[
        "center",
        "day"
    ],
    "wof:name":"Happy World",
    "wof:placetype":"venue"
},
  "geometry": {"coordinates":[-74.56060600000001,40.279263],"type":"Point"}
}