{
  "type": "Feature",
  "properties": {
    "iso:country":"US",
    "sg:address":"1011 US Hwy 202",
    "sg:city":"Branchburg",
    "sg:classifiers":[
        {
            "category":"Retail",
            "subcategory":"Veterinary Services",
            "type":"Services"
        }
    ],
    "sg:phone":"+1 908 707 1555",
    "sg:postcode":"08876",
    "sg:province":"NJ",
    "sg:tags":[
        "veterinarian"
    ],
    "sg:website":"www.allpets.net",
    "wof:name":"All Pets Vet Hospital Inc",
    "wof:placetype":"venue"
},
  "geometry": {"coordinates":[-74.696366,40.563082],"type":"Point"}
}