{
  "type": "Feature",
  "properties": {
    "iso:country":"US",
    "sg:address":"110 Pennsylvania Ave",
    "sg:city":"Paterson",
    "sg:classifiers":[
        {
            "category":"Wholesale",
            "subcategory":"Drugs",
            "type":"Manufacturing & Wholesale Goods"
        }
    ],
    "sg:phone":"+1 973 977 8192",
    "sg:postcode":"07503",
    "sg:province":"NJ",
    "sg:tags":[
        "pharmaceutical",
        "product"
    ],
    "wof:name":"Amitco International",
    "wof:placetype":"venue"
},
  "geometry": {"coordinates":[-74.154094,40.901061],"type":"Point"}
}