{
  "type": "Feature",
  "properties": {
    "addr:full":"168 Everdell Ave Hillsdale NJ 07642",
    "addr:housenumber":"168",
    "addr:postcode":"07642",
    "addr:street":"Everdell Ave",
    "iso:country":"US",
    "sg:address":"168 Everdell Ave",
    "sg:city":"Hillsdale",
    "sg:classifiers":[
        {
            "category":"Manufacturing",
            "subcategory":"Signs",
            "type":"Manufacturing & Wholesale Goods"
        }
    ],
    "sg:phone":"+1 201 666 6686",
    "sg:postcode":"07642",
    "sg:province":"NJ",
    "wof:name":"Ewald Behrens Signs",
    "wof:placetype":"venue"
},
  "geometry": {"coordinates":[-74.02490400000001,41.004909],"type":"Point"}
}