{
  "type": "Feature",
  "properties": {
    "addr:full":"704 Clinton Ave South Plainfield NJ 07080",
    "addr:housenumber":"704",
    "addr:postcode":"07080",
    "addr:street":"Clinton Ave",
    "iso:country":"US",
    "sg:address":"704 Clinton Ave",
    "sg:city":"South Plainfield",
    "sg:classifiers":[
        {
            "category":"Retail",
            "subcategory":"Auto Repair",
            "type":"Services"
        }
    ],
    "sg:phone":"+1 908 561 1973",
    "sg:postcode":"07080",
    "sg:province":"NJ",
    "sg:tags":[
        "repairing",
        "automobile"
    ],
    "wof:name":"Sullivan's Auto Svc",
    "wof:placetype":"venue"
},
  "geometry": {"coordinates":[-74.43623700000001,40.59626],"type":"Point"}
}