{
  "type": "Feature",
  "properties": {
    "iso:country":"US",
    "sg:address":"US Highway 130 & Lincoln Ave N",
    "sg:city":"Mount Ephraim",
    "sg:classifiers":[
        {
            "category":"Shopping",
            "subcategory":"Books",
            "type":"Retail Goods"
        }
    ],
    "sg:phone":"+1 856 456 9683",
    "sg:postcode":"08059",
    "sg:province":"NJ",
    "sg:tags":[
        "bookstore"
    ],
    "wof:name":"Edward's News Agency",
    "wof:placetype":"venue"
},
  "geometry": {"coordinates":[-75.10256099999999,39.893493],"type":"Point"}
}