{
  "type": "Feature",
  "properties": {
    "addr:full":"178 E 33rd St Paterson NJ 07504",
    "addr:housenumber":"178",
    "addr:postcode":"07504",
    "addr:street":"E 33Rd St",
    "iso:country":"US",
    "sg:address":"178 E 33rd St",
    "sg:city":"Paterson",
    "sg:classifiers":[
        {
            "category":"Building & Trades",
            "subcategory":"Locksmith",
            "type":"Services"
        }
    ],
    "sg:phone":"+1 973 413 1342",
    "sg:postcode":"07504",
    "sg:province":"NJ",
    "sg:tags":[
        "key"
    ],
    "wof:name":"Emergency Locksmith Available 24 7",
    "wof:placetype":"venue"
},
  "geometry": {"coordinates":[-74.141848,40.918019],"type":"Point"}
}