{
  "type": "Feature",
  "properties": {
    "addr:full":"140 Monticello Ave Jersey City NJ 07304",
    "addr:housenumber":"140",
    "addr:postcode":"07304",
    "addr:street":"Monticello Ave",
    "iso:country":"US",
    "sg:address":"140 Monticello Ave",
    "sg:city":"Jersey City",
    "sg:classifiers":[
        {
            "category":"Building & Trades",
            "subcategory":"Locksmith",
            "type":"Services"
        }
    ],
    "sg:phone":"+1 888 277 6689",
    "sg:postcode":"07304",
    "sg:province":"NJ",
    "sg:tags":[
        "key"
    ],
    "wof:name":"24 Emergency Locksmith",
    "wof:placetype":"venue"
},
  "geometry": {"coordinates":[-74.071178,40.719128],"type":"Point"}
}