{
  "type": "Feature",
  "properties": {
    "addr:full":"307 Triangle Rd Hillsborough NJ 08844",
    "addr:housenumber":"307",
    "addr:postcode":"08844",
    "addr:street":"Triangle Rd",
    "iso:country":"US",
    "sg:address":"307 Triangle Rd",
    "sg:city":"Hillsborough",
    "sg:classifiers":[
        {
            "category":"Building & Trades",
            "subcategory":"Construction",
            "type":"Services"
        }
    ],
    "sg:phone":"+1 908 313 6561",
    "sg:postcode":"08844",
    "sg:province":"NJ",
    "sg:tags":[
        "contractor"
    ],
    "wof:name":"Jimmy Z/J Masonry",
    "wof:placetype":"venue"
},
  "geometry": {"coordinates":[-74.637874,40.518254],"type":"Point"}
}