{
  "type": "Feature",
  "properties": {
    "iso:country":"US",
    "sg:address":"20 Kings Hwy W",
    "sg:city":"Haddonfield",
    "sg:classifiers":[
        {
            "category":"Professional",
            "subcategory":"Lawyer & Legal Services",
            "type":"Services"
        }
    ],
    "sg:phone":"+1 856 354 0192",
    "sg:postcode":"08033",
    "sg:province":"NJ",
    "wof:name":"Dickie McCamey & Chilcote PC",
    "wof:placetype":"venue"
},
  "geometry": {"coordinates":[-75.03671199999999,39.8956],"type":"Point"}
}