{
  "type": "Feature",
  "properties": {
    "iso:country":"US",
    "sg:address":"2 Euclid Ave",
    "sg:city":"Maplewood",
    "sg:classifiers":[
        {
            "category":"Professional",
            "subcategory":"Art Services",
            "type":"Services"
        }
    ],
    "sg:phone":"+1   ",
    "sg:postcode":"07040",
    "sg:province":"NJ",
    "sg:tags":[
        "commercial",
        "design"
    ],
    "wof:name":"Kensinger Studio",
    "wof:placetype":"venue"
},
  "geometry": {"coordinates":[-74.28322300000001,40.737868],"type":"Point"}
}