{
  "type": "Feature",
  "properties": {
    "iso:country":"US",
    "sg:address":"11 Bancroft Rd",
    "sg:city":"Marlton",
    "sg:classifiers":[
        {
            "category":"Building & Trades",
            "subcategory":"Cleaning & Sanitation",
            "type":"Services"
        }
    ],
    "sg:phone":"+1 856 231 4222",
    "sg:postcode":"08053",
    "sg:province":"NJ",
    "sg:tags":[
        "janitor"
    ],
    "wof:name":"Top Of The Shine Cleaning Svc",
    "wof:placetype":"venue"
},
  "geometry": {"coordinates":[-74.90303299999999,39.890091],"type":"Point"}
}