{
  "type": "Feature",
  "properties": {
    "addr:full":"10 Hershey Rd East Brunswick NJ 08816",
    "addr:housenumber":"10",
    "addr:postcode":"08816",
    "addr:street":"Hershey Rd",
    "iso:country":"US",
    "sg:address":"10 Hershey Rd",
    "sg:city":"East Brunswick",
    "sg:classifiers":[
        {
            "category":"Professional",
            "type":"Services"
        }
    ],
    "sg:phone":"+1 732 257 5331",
    "sg:postcode":"08816",
    "sg:province":"NJ",
    "wof:name":"Chem Services",
    "wof:placetype":"venue"
},
  "geometry": {"coordinates":[-74.44180299999999,40.416467],"type":"Point"}
}