{
  "type": "Feature",
  "properties": {
    "addr:full":"419 Cass St Trenton NJ 08611",
    "addr:housenumber":"419",
    "addr:postcode":"08611",
    "addr:street":"Cass St",
    "iso:country":"US",
    "sg:address":"419 Cass St",
    "sg:city":"Trenton",
    "sg:classifiers":[
        {
            "category":"Professional",
            "subcategory":"Business Services",
            "type":"Services"
        }
    ],
    "sg:phone":"+1   ",
    "sg:postcode":"08611",
    "sg:province":"NJ",
    "wof:name":"Universal Business Solutions",
    "wof:placetype":"venue"
},
  "geometry": {"coordinates":[-74.755807,40.205706],"type":"Point"}
}