{
  "type": "Feature",
  "properties": {
    "iso:country":"US",
    "sg:address":"60 Buttonwood St",
    "sg:city":"Lambertville",
    "sg:classifiers":[
        {
            "category":"Building & Trades",
            "subcategory":"Construction",
            "type":"Services"
        }
    ],
    "sg:phone":"+1 609 397 9453",
    "sg:postcode":"08530",
    "sg:province":"NJ",
    "sg:tags":[
        "contractor"
    ],
    "wof:name":"TNT Contractors Inc",
    "wof:placetype":"venue"
},
  "geometry": {"coordinates":[-74.94609699999999,40.373018],"type":"Point"}
}