{
  "type": "Feature",
  "properties": {
    "addr:full":"340 Central Ave Orange NJ 07050",
    "addr:housenumber":"340",
    "addr:postcode":"07050",
    "addr:street":"Central Ave",
    "iso:country":"US",
    "sg:address":"340 Central Ave",
    "sg:city":"Orange",
    "sg:classifiers":[
        {
            "category":"Arts & Performance",
            "subcategory":"Theater",
            "type":"Entertainment"
        }
    ],
    "sg:phone":"+1   ",
    "sg:postcode":"07050",
    "sg:province":"NJ",
    "sg:tags":[
        "group"
    ],
    "wof:name":"J G Entertainment",
    "wof:placetype":"venue"
},
  "geometry": {"coordinates":[-74.23343300000001,40.765867],"type":"Point"}
}