{
  "type": "Feature",
  "properties": {
    "iso:country":"US",
    "sg:address":"225 Newark Ave",
    "sg:city":"Jersey City",
    "sg:classifiers":[
        {
            "category":"Restaurant",
            "type":"Food & Drink"
        }
    ],
    "sg:phone":"+1 201 435 2070",
    "sg:postcode":"07302",
    "sg:province":"NJ",
    "sg:tags":[
        "pizza"
    ],
    "sg:website":"PinosPizzajc.com",
    "wof:name":"Pino's Cafe",
    "wof:placetype":"venue"
},
  "geometry": {"coordinates":[-74.04754200000001,40.722203],"type":"Point"}
}