{
  "type": "Feature",
  "properties": {
    "addr:full":"111 N Decatur Ave Margate City NJ 08402",
    "addr:housenumber":"111",
    "addr:postcode":"08402",
    "addr:street":"N Decatur Ave Margate",
    "iso:country":"US",
    "sg:address":"111 N Decatur Ave",
    "sg:city":"Margate City",
    "sg:classifiers":[
        {
            "category":"Government",
            "subcategory":"Police Station",
            "type":"Public Place"
        }
    ],
    "sg:phone":"+1 609 822 1151",
    "sg:postcode":"08402",
    "sg:province":"NJ",
    "sg:tags":[
        "department"
    ],
    "sg:website":"www.margatecity.com",
    "wof:name":"Margate City Police",
    "wof:placetype":"venue"
},
  "geometry": {"coordinates":[-74.515266,39.32512],"type":"Point"}
}