{
  "type": "Feature",
  "properties": {
    "addr:full":"401 Marlton Pike E Cherry Hill NJ 08034",
    "addr:housenumber":"401",
    "addr:postcode":"08034",
    "addr:street":"Marlton Pike E",
    "iso:country":"US",
    "sg:address":"401 Marlton Pike E",
    "sg:city":"Cherry Hill",
    "sg:classifiers":[
        {
            "category":"Real Estate",
            "subcategory":"Real Estate Services",
            "type":"Services"
        },
        {
            "category":"Education",
            "subcategory":"Vocational School",
            "type":"Public Place"
        }
    ],
    "sg:phone":"+1 856 429 3660",
    "sg:postcode":"08034",
    "sg:province":"NJ",
    "sg:tags":[
        "company",
        "title"
    ],
    "wof:name":"National Real Estate Info",
    "wof:placetype":"venue"
},
  "geometry": {"coordinates":[-75.000558,39.911981],"type":"Point"}
}