{
  "type": "Feature",
  "properties": {
    "addr:full":"1060 US Highway 1 and 9 Jersey City NJ 07306",
    "addr:housenumber":"1060;9",
    "addr:postcode":"07306",
    "addr:street":"Us Highway 1 And",
    "iso:country":"US",
    "sg:address":"1060 US Highway 1 and 9",
    "sg:city":"Jersey City",
    "sg:classifiers":[
        {
            "category":"Professional",
            "subcategory":"Computer Services",
            "type":"Services"
        }
    ],
    "sg:phone":"+1 201 413 9700",
    "sg:postcode":"07306",
    "sg:province":"NJ",
    "sg:tags":[
        "stereo",
        "installation"
    ],
    "wof:name":"Unlimited Auto",
    "wof:placetype":"venue"
},
  "geometry": {"coordinates":[-74.081299,40.7388],"type":"Point"}
}