{
  "type": "Feature",
  "properties": {
    "addr:full":"3060 John F Kennedy Blvd Jersey City NJ 07306",
    "addr:housenumber":"3060",
    "addr:postcode":"07306",
    "addr:street":"John F Kennedy Blvd",
    "iso:country":"US",
    "sg:address":"3060 John F Kennedy Blvd",
    "sg:city":"Jersey City",
    "sg:classifiers":[
        {
            "category":"Organizations",
            "subcategory":"Community Association",
            "type":"Services"
        }
    ],
    "sg:phone":"+1 201 792 4918",
    "sg:postcode":"07306",
    "sg:province":"NJ",
    "sg:tags":[
        "building",
        "apartment",
        "tenant"
    ],
    "wof:name":"Grandview Terrace Apartments",
    "wof:placetype":"venue"
},
  "geometry": {"coordinates":[-74.062358,40.738938],"type":"Point"}
}