{
  "type": "Feature",
  "properties": {
    "iso:country":"US",
    "sg:address":"40 Meadow Ln",
    "sg:city":"Clifton",
    "sg:classifiers":[
        {
            "category":"Travel",
            "subcategory":"Travel Agent",
            "type":"Entertainment"
        }
    ],
    "sg:phone":"+1 973 591 1694",
    "sg:postcode":"07012",
    "sg:province":"NJ",
    "sg:tags":[
        "agency",
        "bureau"
    ],
    "wof:name":"Vanhook Travel Com Inc",
    "wof:placetype":"venue"
},
  "geometry": {"coordinates":[-74.15839200000001,40.856752],"type":"Point"}
}