{
  "type": "Feature",
  "properties": {
    "iso:country":"US",
    "sg:address":"28 North Dr",
    "sg:city":"Rochelle Park",
    "sg:classifiers":[
        {
            "category":"Utilities",
            "subcategory":"Refuse",
            "type":"Services"
        }
    ],
    "sg:phone":"+1 201 368 1117",
    "sg:postcode":"07662",
    "sg:province":"NJ",
    "sg:tags":[
        "garbage",
        "collection"
    ],
    "wof:name":"Atlantic Waste Svc",
    "wof:placetype":"venue"
},
  "geometry": {"coordinates":[-74.080172,40.910894],"type":"Point"}
}