{
  "type": "Feature",
  "properties": {
    "addr:full":"224 Monmouth Ave Atlantic Highlands NJ 07716",
    "addr:housenumber":"224",
    "addr:postcode":"07716",
    "addr:street":"Monmouth Ave",
    "iso:country":"US",
    "sg:address":"224 Monmouth Ave",
    "sg:city":"Atlantic Highlands",
    "sg:classifiers":[
        {
            "category":"Professional",
            "subcategory":"Business Services",
            "type":"Services"
        }
    ],
    "sg:phone":"+1   ",
    "sg:postcode":"07716",
    "sg:province":"NJ",
    "wof:name":"Katelin Partners Corp",
    "wof:placetype":"venue"
},
  "geometry": {"coordinates":[-74.03624000000001,40.399176],"type":"Point"}
}