{
  "type": "Feature",
  "properties": {
    "iso:country":"US",
    "sg:address":"7 Hamden Rd",
    "sg:city":"Flemington",
    "sg:classifiers":[
        {
            "category":"Health Services",
            "subcategory":"Health Practitioner",
            "type":"Services"
        }
    ],
    "sg:phone":"+1 856 857 0021",
    "sg:postcode":"08822",
    "sg:province":"NJ",
    "sg:tags":[
        "nutritionist"
    ],
    "wof:name":"Haddonfield Nutrition",
    "wof:placetype":"venue"
},
  "geometry": {"coordinates":[-74.882013,40.57351],"type":"Point"}
}