{
  "type": "Feature",
  "properties": {
    "iso:country":"US",
    "sg:address":"1155 E Wheat Rd",
    "sg:city":"Vineland",
    "sg:classifiers":[
        {
            "category":"Real Estate",
            "subcategory":"Developer",
            "type":"Services"
        }
    ],
    "sg:phone":"+1   ",
    "sg:postcode":"08360",
    "sg:province":"NJ",
    "sg:tags":[
        "cemetery"
    ],
    "wof:name":"Petland Cemetery & Crematory",
    "wof:placetype":"venue"
},
  "geometry": {"coordinates":[-75.000066,39.511859],"type":"Point"}
}