{
  "type": "Feature",
  "properties": {
    "iso:country":"US",
    "sg:address":"560 Sylvan Ave",
    "sg:city":"Englewood Cliffs",
    "sg:classifiers":[
        {
            "category":"Building & Trades",
            "subcategory":"Construction",
            "type":"Services"
        }
    ],
    "sg:phone":"+1 201 569 3939",
    "sg:postcode":"07632",
    "sg:province":"NJ",
    "sg:tags":[
        "insulation",
        "heat",
        "contractor"
    ],
    "wof:name":"MBC Insulation",
    "wof:placetype":"venue"
},
  "geometry": {"coordinates":[-73.944664,40.889564],"type":"Point"}
}