{
  "type": "Feature",
  "properties": {
    "addr:full":"497 Observer Hwy Hoboken NJ 07030",
    "addr:housenumber":"497",
    "addr:postcode":"07030",
    "addr:street":"Observer Hwy",
    "iso:country":"US",
    "sg:address":"497 Observer Hwy",
    "sg:city":"Hoboken",
    "sg:classifiers":[
        {
            "category":"Autos & Motor Vehicles",
            "subcategory":"Automobile Sales",
            "type":"Retail Goods"
        }
    ],
    "sg:phone":"+1   ",
    "sg:postcode":"07030",
    "sg:province":"NJ",
    "sg:tags":[
        "used"
    ],
    "wof:name":"Hoboken Auto Sales Inc",
    "wof:placetype":"venue"
},
  "geometry": {"coordinates":[-74.035972,40.736128],"type":"Point"}
}