{
  "type": "Feature",
  "properties": {
    "addr:full":"5604 Bergenline Pl West New York NJ 07093",
    "addr:housenumber":"5604",
    "addr:postcode":"07093",
    "addr:street":"Bergenline Pl West",
    "iso:country":"US",
    "sg:address":"5604 Bergenline Pl",
    "sg:city":"West New York",
    "sg:classifiers":[
        {
            "category":"Shopping",
            "subcategory":"Discount & Variety Stores",
            "type":"Retail Goods"
        }
    ],
    "sg:phone":"+1   ",
    "sg:postcode":"07093",
    "sg:province":"NJ",
    "wof:name":"ABC Superstore of West NY",
    "wof:placetype":"venue"
},
  "geometry": {"coordinates":[-74.01786800000001,40.786612],"type":"Point"}
}