{
  "type": "Feature",
  "properties": {
    "addr:full":"76 Porete Ave North Arlington NJ 07031",
    "addr:housenumber":"76",
    "addr:postcode":"07031",
    "addr:street":"Porete Ave North",
    "iso:country":"US",
    "sg:address":"76 Porete Ave",
    "sg:city":"North Arlington",
    "sg:classifiers":[
        {
            "category":"Home & Garden",
            "subcategory":"Household Appliances",
            "type":"Retail Goods"
        }
    ],
    "sg:phone":"+1   ",
    "sg:postcode":"07031",
    "sg:province":"NJ",
    "sg:tags":[
        "disposal",
        "waste",
        "system"
    ],
    "wof:name":"Tech Services",
    "wof:placetype":"venue"
},
  "geometry": {"coordinates":[-74.125879,40.779145],"type":"Point"}
}