{
  "type": "Feature",
  "properties": {
    "iso:country":"US",
    "sg:address":"1089 Buckshutem Rd",
    "sg:city":"Bridgeton",
    "sg:classifiers":[
        {
            "category":"Autos & Motor Vehicles",
            "subcategory":"Automobile Sales",
            "type":"Retail Goods"
        }
    ],
    "sg:phone":"+1   ",
    "sg:postcode":"08302",
    "sg:province":"NJ",
    "sg:tags":[
        "used"
    ],
    "wof:name":"Fairfield Motors",
    "wof:placetype":"venue"
},
  "geometry": {"coordinates":[-75.183994,39.410489],"type":"Point"}
}