{
  "type": "Feature",
  "properties": {
    "iso:country":"US",
    "sg:address":"59 Bellevue Ave",
    "sg:city":"Bloomfield",
    "sg:classifiers":[
        {
            "category":"Real Estate",
            "subcategory":"Real Estate Services",
            "type":"Services"
        }
    ],
    "sg:phone":"+1 973 893 9090",
    "sg:postcode":"07003",
    "sg:province":"NJ",
    "sg:tags":[
        "home",
        "inspector"
    ],
    "wof:name":"Kevin Zehnder Home Inspections",
    "wof:placetype":"venue"
},
  "geometry": {"coordinates":[-74.18827,40.837843],"type":"Point"}
}