{
  "type": "Feature",
  "properties": {
    "addr:full":"268 Huyler Street South Hackensack NJ 07606",
    "addr:housenumber":"268",
    "addr:postcode":"07606",
    "addr:street":"Huyler Street South",
    "iso:country":"US",
    "sg:address":"268 Huyler Street",
    "sg:city":"South Hackensack",
    "sg:classifiers":[
        {
            "category":"Restaurant",
            "type":"Food & Drink"
        }
    ],
    "sg:phone":"+1 201 487 4220",
    "sg:postcode":"07606",
    "sg:province":"NJ",
    "sg:tags":[
        "italian"
    ],
    "sg:website":"www.igemelliristorante.com/",
    "wof:name":"I Gemelli",
    "wof:placetype":"venue"
},
  "geometry": {"coordinates":[-74.048615,40.870579],"type":"Point"}
}