{
  "type": "Feature",
  "properties": {
    "addr:full":"7 Cleveland St Caldwell NJ 07006",
    "addr:housenumber":"7",
    "addr:postcode":"07006",
    "addr:street":"Cleveland St",
    "iso:country":"US",
    "sg:address":"7 Cleveland St",
    "sg:city":"Caldwell",
    "sg:classifiers":[
        {
            "category":"Professional",
            "subcategory":"Accounting & Tax Preparation",
            "type":"Services"
        }
    ],
    "sg:phone":"+1 973 226 9575",
    "sg:postcode":"07006",
    "sg:province":"NJ",
    "sg:tags":[
        "accountant"
    ],
    "wof:name":"Arvanites John D CPA",
    "wof:placetype":"venue"
},
  "geometry": {"coordinates":[-74.279701,40.841801],"type":"Point"}
}