{
  "type": "Feature",
  "properties": {
    "iso:country":"US",
    "sg:address":"270 Frog Pond Rd",
    "sg:city":"Tuckerton",
    "sg:classifiers":[
        {
            "category":"Building & Trades",
            "subcategory":"Pest Control",
            "type":"Services"
        }
    ],
    "sg:phone":"+1 609 296 0675",
    "sg:postcode":"08087",
    "sg:province":"NJ",
    "sg:tags":[
        "animal"
    ],
    "wof:name":"Animal & Capture & Ctrl Svcs",
    "wof:placetype":"venue"
},
  "geometry": {"coordinates":[-74.323731,39.629309],"type":"Point"}
}