{
  "type": "Feature",
  "properties": {
    "iso:country":"US",
    "sg:address":"1077 State Rte 94",
    "sg:city":"Blairstown",
    "sg:classifiers":[
        {
            "category":"Shopping",
            "subcategory":"Bicycles & Sporting Goods",
            "type":"Retail Goods"
        }
    ],
    "sg:phone":"+1   ",
    "sg:postcode":"07825",
    "sg:province":"NJ",
    "wof:name":"Yoj Sports",
    "wof:placetype":"venue"
},
  "geometry": {"coordinates":[-74.911664,40.984563],"type":"Point"}
}