{
  "type": "Feature",
  "properties": {
    "iso:country":"US",
    "sg:address":"12 Marlton Rd",
    "sg:city":"Woodstown",
    "sg:classifiers":[
        {
            "category":"Utilities",
            "subcategory":"Water",
            "type":"Services"
        }
    ],
    "sg:phone":"+1 856 769 3972",
    "sg:postcode":"08098",
    "sg:province":"NJ",
    "sg:tags":[
        "system",
        "supply"
    ],
    "wof:name":"Alliegro Water Systems",
    "wof:placetype":"venue"
},
  "geometry": {"coordinates":[-75.32951300000001,39.653845],"type":"Point"}
}