{
  "type": "Feature",
  "properties": {
    "addr:full":"1315 US Hwy 46 Parsippany NJ 07054",
    "addr:housenumber":"1315",
    "addr:postcode":"07054",
    "addr:street":"Us Hwy 46",
    "iso:country":"US",
    "sg:address":"1315 US Hwy 46",
    "sg:city":"Parsippany",
    "sg:classifiers":[
        {
            "category":"Health Services",
            "subcategory":"Optometrist",
            "type":"Services"
        }
    ],
    "sg:phone":"+1 973 402 4838",
    "sg:postcode":"07054",
    "sg:province":"NJ",
    "wof:name":"Ooh Vision Networks",
    "wof:placetype":"venue"
},
  "geometry": {"coordinates":[-74.390429,40.863215],"type":"Point"}
}