{
  "type": "Feature",
  "properties": {
    "iso:country":"US",
    "sg:address":"201 Roosevelt Pl",
    "sg:city":"Palisades Park",
    "sg:classifiers":[
        {
            "category":"Banks & Credit Unions",
            "subcategory":"Bank",
            "type":"Services"
        }
    ],
    "sg:phone":"+1   ",
    "sg:postcode":"07650",
    "sg:province":"NJ",
    "sg:tags":[
        "savings"
    ],
    "wof:name":"New York Community Bank",
    "wof:placetype":"venue"
},
  "geometry": {"coordinates":[-74.005216,40.851579],"type":"Point"}
}