{
  "type": "Feature",
  "properties": {
    "addr:full":"400 Commerce Blvd Carlstadt NJ 07072",
    "addr:housenumber":"400",
    "addr:postcode":"07072",
    "addr:street":"Commerce Blvd",
    "iso:country":"US",
    "sg:address":"400 Commerce Blvd",
    "sg:city":"Carlstadt",
    "sg:classifiers":[
        {
            "category":"Wholesale",
            "subcategory":"Computers",
            "type":"Manufacturing & Wholesale Goods"
        }
    ],
    "sg:phone":"+1 201 939 8100",
    "sg:postcode":"07072",
    "sg:province":"NJ",
    "wof:name":"Intercept Inc",
    "wof:placetype":"venue"
},
  "geometry": {"coordinates":[-74.053398,40.828499],"type":"Point"}
}