{
  "type": "Feature",
  "properties": {
    "iso:country":"US",
    "sg:address":"9 Ventosa Dr",
    "sg:city":"Morristown",
    "sg:classifiers":[
        {
            "category":"Professional",
            "subcategory":"Management & Consulting",
            "type":"Services"
        }
    ],
    "sg:phone":"+1 973 267 1080",
    "sg:postcode":"07960",
    "sg:province":"NJ",
    "sg:tags":[
        "consultant",
        "business"
    ],
    "wof:name":"Robert L Bush & Assoc Inc",
    "wof:placetype":"venue"
},
  "geometry": {"coordinates":[-74.524721,40.828131],"type":"Point"}
}