{
  "type": "Feature",
  "properties": {
    "iso:country":"US",
    "sg:address":"1980 E State St Exd",
    "sg:city":"Trenton",
    "sg:classifiers":[
        {
            "category":"Shopping",
            "subcategory":"Clothing, Apparel, & Fashions",
            "type":"Retail Goods"
        }
    ],
    "sg:phone":"+1 609 587 2309",
    "sg:postcode":"08619",
    "sg:province":"NJ",
    "sg:tags":[
        "sportswear"
    ],
    "wof:name":"Aberdeen Sportswear Inc",
    "wof:placetype":"venue"
},
  "geometry": {"coordinates":[-74.727738,40.23589],"type":"Point"}
}