{
  "type": "Feature",
  "properties": {
    "addr:full":"330 Passaic St Passaic NJ 07055",
    "addr:housenumber":"330",
    "addr:postcode":"07055",
    "addr:street":"Passaic St",
    "iso:country":"US",
    "sg:address":"330 Passaic St",
    "sg:city":"Passaic",
    "sg:classifiers":[
        {
            "category":"Government",
            "subcategory":"Police Station",
            "type":"Public Place"
        },
        {
            "category":"Government",
            "subcategory":"Office",
            "type":"Public Place"
        }
    ],
    "sg:phone":"+1 973 365 3914",
    "sg:postcode":"07055",
    "sg:province":"NJ",
    "sg:tags":[
        "department",
        "township",
        "government-city",
        "village"
    ],
    "wof:name":"City of Passaic Police Headquarters",
    "wof:placetype":"venue"
},
  "geometry": {"coordinates":[-74.123413,40.86047],"type":"Point"}
}