{
  "type": "Feature",
  "properties": {
    "addr:full":"45 Davey St Bloomfield NJ 07003",
    "addr:housenumber":"45",
    "addr:postcode":"07003",
    "addr:street":"Davey St",
    "iso:country":"US",
    "sg:address":"45 Davey St",
    "sg:city":"Bloomfield",
    "sg:classifiers":[
        {
            "category":"Wholesale",
            "subcategory":"Electrical",
            "type":"Manufacturing & Wholesale Goods"
        }
    ],
    "sg:phone":"+1 973 429 7120",
    "sg:postcode":"07003",
    "sg:province":"NJ",
    "sg:tags":[
        "meter"
    ],
    "wof:name":"Blend-Rite Industries Inc",
    "wof:placetype":"venue"
},
  "geometry": {"coordinates":[-74.18258899999999,40.796177],"type":"Point"}
}