{
  "type": "Feature",
  "properties": {
    "iso:country":"US",
    "sg:address":"656 Godwin Ave",
    "sg:city":"Midland Park",
    "sg:classifiers":[
        {
            "category":"Building & Trades",
            "subcategory":"Cleaning & Sanitation",
            "type":"Services"
        }
    ],
    "sg:phone":"+1 201 444 0056",
    "sg:postcode":"07432",
    "sg:province":"NJ",
    "sg:tags":[
        "janitor",
        "maintenance"
    ],
    "wof:name":"Barbaras House & Office Clean",
    "wof:placetype":"venue"
},
  "geometry": {"coordinates":[-74.154067,41.000104],"type":"Point"}
}