{
  "type": "Feature",
  "properties": {
    "addr:full":"1107 Broad St Bloomfield NJ 07003",
    "addr:housenumber":"1107",
    "addr:postcode":"07003",
    "addr:street":"Broad St",
    "iso:country":"US",
    "sg:address":"1107 Broad St",
    "sg:city":"Bloomfield",
    "sg:classifiers":[
        {
            "category":"Retail",
            "subcategory":"Repair Shop",
            "type":"Services"
        }
    ],
    "sg:phone":"+1 973 338 5200",
    "sg:postcode":"07003",
    "sg:province":"NJ",
    "sg:tags":[
        "repairing",
        "equipment",
        "electric"
    ],
    "sg:website":"www.saktech.com",
    "wof:name":"Sak Technologies",
    "wof:placetype":"venue"
},
  "geometry": {"coordinates":[-74.186097,40.829048],"type":"Point"}
}