{
  "type": "Feature",
  "properties": {
    "addr:full":"208 Broad Ave Palisades Park NJ 07650",
    "addr:housenumber":"208",
    "addr:postcode":"07650",
    "addr:street":"Broad Ave",
    "iso:country":"US",
    "sg:address":"208 Broad Ave",
    "sg:city":"Palisades Park",
    "sg:classifiers":[
        {
            "category":"Shopping",
            "subcategory":"Books",
            "type":"Retail Goods"
        }
    ],
    "sg:phone":"+1 201 944 8740",
    "sg:postcode":"07650",
    "sg:province":"NJ",
    "sg:tags":[
        "dealer"
    ],
    "wof:name":"Gyopo Books",
    "wof:placetype":"venue"
},
  "geometry": {"coordinates":[-73.999371,40.845546],"type":"Point"}
}