{
  "type": "Feature",
  "properties": {
    "addr:full":"3699 US Highway 46 Parsippany NJ 07054",
    "addr:housenumber":"3699",
    "addr:postcode":"07054",
    "addr:street":"Us Highway 46",
    "iso:country":"US",
    "sg:address":"3699 US Highway 46",
    "sg:city":"Parsippany",
    "sg:classifiers":[
        {
            "category":"Personal",
            "subcategory":"Massage",
            "type":"Services"
        },
        {
            "category":"Health Services",
            "subcategory":"Health Practitioner",
            "type":"Services"
        }
    ],
    "sg:phone":"+1 973 263 2229",
    "sg:postcode":"07054",
    "sg:province":"NJ",
    "sg:tags":[
        "acupuncture"
    ],
    "sg:website":"www.newjerseymassage.com",
    "wof:name":"Interfaith Wedding Ministries",
    "wof:placetype":"venue"
},
  "geometry": {"coordinates":[-74.443806,40.877238],"type":"Point"}
}