{
  "type": "Feature",
  "properties": {
    "iso:country":"US",
    "sg:address":"439 Central Ave",
    "sg:city":"Jersey City",
    "sg:classifiers":[
        {
            "category":"Social Services",
            "type":"Services"
        }
    ],
    "sg:phone":"+1 201 420 0280",
    "sg:postcode":"07307",
    "sg:province":"NJ",
    "sg:tags":[
        "organization",
        "welfare"
    ],
    "wof:name":"God Sent Prayer Hot Line",
    "wof:placetype":"venue"
},
  "geometry": {"coordinates":[-74.047025,40.749459],"type":"Point"}
}