{
  "type": "Feature",
  "properties": {
    "iso:country":"US",
    "sg:address":"3000 State Rte 88",
    "sg:city":"Pt Pleasant Bch",
    "sg:classifiers":[
        {
            "category":"Home & Garden",
            "subcategory":"Garden Supply",
            "type":"Retail Goods"
        }
    ],
    "sg:phone":"+1 732 714 2747",
    "sg:postcode":"08742",
    "sg:province":"NJ",
    "sg:tags":[
        "nurseryman"
    ],
    "wof:name":"Point Pleasant Nursery",
    "wof:placetype":"venue"
},
  "geometry": {"coordinates":[-74.08089099999999,40.080788],"type":"Point"}
}