{
  "type": "Feature",
  "properties": {
    "iso:country":"US",
    "sg:address":"57 Cannonball Rd",
    "sg:city":"Pompton Lakes",
    "sg:classifiers":[
        {
            "category":"Retail",
            "subcategory":"Auto Repair",
            "type":"Services"
        }
    ],
    "sg:phone":"+1 973 616 6300",
    "sg:postcode":"07442",
    "sg:province":"NJ",
    "sg:tags":[
        "body"
    ],
    "wof:name":"Back In Time Auto Restoration",
    "wof:placetype":"venue"
},
  "geometry": {"coordinates":[-74.289789,41.007708],"type":"Point"}
}