{
  "type": "Feature",
  "properties": {
    "iso:country":"US",
    "sg:address":"442 S Arthur Dr",
    "sg:city":"Beverly",
    "sg:classifiers":[
        {
            "category":"Communications",
            "type":"Services"
        }
    ],
    "sg:phone":"+1 609 386 5502",
    "sg:postcode":"08010",
    "sg:province":"NJ",
    "wof:name":"Blessed Hope Communications",
    "wof:placetype":"venue"
},
  "geometry": {"coordinates":[-74.901105,40.057162],"type":"Point"}
}