{
  "type": "Feature",
  "properties": {
    "iso:country":"US",
    "sg:address":"505 Oritan Ave",
    "sg:city":"Ridgefield",
    "sg:classifiers":[
        {
            "category":"Manufacturing",
            "subcategory":"Chemicals & Compounds",
            "type":"Manufacturing & Wholesale Goods"
        }
    ],
    "sg:phone":"+1 201 941 0148",
    "sg:postcode":"07657",
    "sg:province":"NJ",
    "sg:tags":[
        "refrigeration"
    ],
    "wof:name":"Conopco Inc",
    "wof:placetype":"venue"
},
  "geometry": {"coordinates":[-74.010301,40.834869],"type":"Point"}
}