{
  "type": "Feature",
  "properties": {
    "iso:country":"US",
    "sg:address":"103 Arch St Ste A",
    "sg:city":"Butler",
    "sg:classifiers":[
        {
            "category":"Retail",
            "subcategory":"Storage",
            "type":"Services"
        }
    ],
    "sg:phone":"+1 973 838 2639",
    "sg:postcode":"07405",
    "sg:province":"NJ",
    "sg:tags":[
        "self"
    ],
    "wof:name":"Newton Enterprises",
    "wof:placetype":"venue"
},
  "geometry": {"coordinates":[-74.337097,41.0065],"type":"Point"}
}