{
  "type": "Feature",
  "properties": {
    "iso:country":"US",
    "sg:address":"211 E Inman Ave",
    "sg:city":"Rahway",
    "sg:classifiers":[
        {
            "category":"Wholesale",
            "subcategory":"Auto Parts",
            "type":"Manufacturing & Wholesale Goods"
        }
    ],
    "sg:phone":"+1 732 388 2457",
    "sg:postcode":"07065",
    "sg:province":"NJ",
    "sg:tags":[
        "automobile",
        "rebuilt",
        "truck",
        "wrecking"
    ],
    "sg:website":"http://www.brucesautowreckers.com",
    "wof:name":"Bruce's Auto Wrecking Inc",
    "wof:placetype":"venue"
},
  "geometry": {"coordinates":[-74.28282900000001,40.596008],"type":"Point"}
}