{
  "type": "Feature",
  "properties": {
    "addr:full":"482 Notch Rd Clifton NJ 07013",
    "addr:housenumber":"482",
    "addr:postcode":"07013",
    "addr:street":"Notch Rd",
    "iso:country":"US",
    "sg:address":"482 Notch Rd",
    "sg:city":"Clifton",
    "sg:classifiers":[
        {
            "category":"Banks & Credit Unions",
            "subcategory":"Financial Services",
            "type":"Services"
        }
    ],
    "sg:phone":"+1 973 237 1226",
    "sg:postcode":"07013",
    "sg:province":"NJ",
    "sg:tags":[
        "broker",
        "mortgage"
    ],
    "wof:name":"Ams Mortgage Services Inc",
    "wof:placetype":"venue"
},
  "geometry": {"coordinates":[-74.19049800000001,40.872101],"type":"Point"}
}