{
  "type": "Feature",
  "properties": {
    "iso:country":"US",
    "sg:address":"9 Mountain Ln",
    "sg:city":"Holmdel",
    "sg:classifiers":[
        {
            "category":"Building & Trades",
            "subcategory":"Electrical",
            "type":"Services"
        }
    ],
    "sg:phone":"+1 732 264 7377",
    "sg:postcode":"07733",
    "sg:province":"NJ",
    "sg:tags":[
        "electrical",
        "contractor"
    ],
    "wof:name":"Weber Electric Contractors",
    "wof:placetype":"venue"
},
  "geometry": {"coordinates":[-74.16374999999999,40.400999],"type":"Point"}
}