{
  "type": "Feature",
  "properties": {
    "addr:full":"534 Bergen Blvd Palisades Park NJ 07650",
    "addr:housenumber":"534",
    "addr:postcode":"07650",
    "addr:street":"Bergen Blvd",
    "iso:country":"US",
    "sg:address":"534 Bergen Blvd",
    "sg:city":"Palisades Park",
    "sg:classifiers":[
        {
            "category":"Arena",
            "subcategory":"Sports Club",
            "type":"Entertainment"
        }
    ],
    "sg:phone":"+1 201 461 6444",
    "sg:postcode":"07650",
    "sg:province":"NJ",
    "sg:tags":[
        "martial art"
    ],
    "wof:name":"World Martial Arts Institute",
    "wof:placetype":"venue"
},
  "geometry": {"coordinates":[-73.985001,40.847301],"type":"Point"}
}