{
  "type": "Feature",
  "properties": {
    "iso:country":"US",
    "sg:address":"815 Liberty St",
    "sg:city":"Trenton",
    "sg:classifiers":[
        {
            "category":"Food & Beverages",
            "subcategory":"Groceries & Convenience Stores",
            "type":"Retail Goods"
        }
    ],
    "sg:phone":"+1   ",
    "sg:postcode":"08611",
    "sg:province":"NJ",
    "wof:name":"Liberty Deli",
    "wof:placetype":"venue"
},
  "geometry": {"coordinates":[-74.739276,40.207586],"type":"Point"}
}