{
  "type": "Feature",
  "properties": {
    "addr:full":"364 Lakehurst Rd Browns Mills NJ 08015",
    "addr:housenumber":"364",
    "addr:postcode":"08015",
    "addr:street":"Lakehurst Rd",
    "iso:country":"US",
    "sg:address":"364 Lakehurst Rd",
    "sg:city":"Browns Mills",
    "sg:classifiers":[
        {
            "category":"Organizations",
            "subcategory":"Non-profit Organization",
            "type":"Services"
        }
    ],
    "sg:phone":"+1 609 735 0127",
    "sg:postcode":"08015",
    "sg:province":"NJ",
    "sg:tags":[
        "human"
    ],
    "wof:name":"Equal Partners Inc",
    "wof:placetype":"venue"
},
  "geometry": {"coordinates":[-74.577426,39.966247],"type":"Point"}
}