{
  "type": "Feature",
  "properties": {
    "iso:country":"US",
    "sg:address":"5 Overlook Ter",
    "sg:city":"Bloomfield",
    "sg:classifiers":[
        {
            "category":"Building & Trades",
            "subcategory":"Construction",
            "type":"Services"
        }
    ],
    "sg:phone":"+1 973 338 1540",
    "sg:postcode":"07003",
    "sg:province":"NJ",
    "sg:tags":[
        "house"
    ],
    "wof:name":"Paul Nebesni",
    "wof:placetype":"venue"
},
  "geometry": {"coordinates":[-74.18417700000001,40.833902],"type":"Point"}
}