{
  "type": "Feature",
  "properties": {
    "addr:full":"598 Ridge Rd Monmouth Junction NJ 08852",
    "addr:housenumber":"598",
    "addr:postcode":"08852",
    "addr:street":"Ridge Rd",
    "iso:country":"US",
    "sg:address":"598 Ridge Rd",
    "sg:city":"Monmouth Junction",
    "sg:classifiers":[
        {
            "category":"Building & Trades",
            "subcategory":"Cleaning & Sanitation",
            "type":"Services"
        }
    ],
    "sg:phone":"+1   ",
    "sg:postcode":"08852",
    "sg:province":"NJ",
    "sg:tags":[
        "total",
        "janitorial",
        "maintenance"
    ],
    "wof:name":"L & S Janitorial Specialists",
    "wof:placetype":"venue"
},
  "geometry": {"coordinates":[-74.544865,40.380228],"type":"Point"}
}