{
  "type": "Feature",
  "properties": {
    "iso:country":"US",
    "sg:address":"1275 Bloomfield Ave",
    "sg:city":"Fairfield",
    "sg:classifiers":[
        {
            "category":"Professional",
            "subcategory":"Business Services",
            "type":"Services"
        },
        {
            "category":"Home & Garden",
            "subcategory":"Home Furnishings",
            "type":"Retail Goods"
        }
    ],
    "sg:phone":"+1 973 227 9222",
    "sg:postcode":"07004",
    "sg:province":"NJ",
    "sg:tags":[
        "curtain",
        "made",
        "drapery"
    ],
    "wof:name":"Drapery Encores LLC",
    "wof:placetype":"venue"
},
  "geometry": {"coordinates":[-74.318907,40.858492],"type":"Point"}
}