{
  "type": "Feature",
  "properties": {
    "addr:full":"1 Susan Ave Midland Park NJ 07432",
    "addr:housenumber":"1",
    "addr:postcode":"07432",
    "addr:street":"Susan Ave",
    "iso:country":"US",
    "sg:address":"1 Susan Ave",
    "sg:city":"Midland Park",
    "sg:classifiers":[
        {
            "category":"Manufacturing",
            "subcategory":"Textiles",
            "type":"Manufacturing & Wholesale Goods"
        }
    ],
    "sg:phone":"+1 201 447 6165",
    "sg:postcode":"07432",
    "sg:province":"NJ",
    "sg:tags":[
        "mfg"
    ],
    "wof:name":"Custom Weave",
    "wof:placetype":"venue"
},
  "geometry": {"coordinates":[-74.138457,41.006505],"type":"Point"}
}