{
  "type": "Feature",
  "properties": {
    "iso:country":"US",
    "sg:address":"2113 New York Ave",
    "sg:city":"Union City",
    "sg:classifiers":[
        {
            "category":"Health Services",
            "subcategory":"Health Practitioner",
            "type":"Services"
        }
    ],
    "sg:phone":"+1 201 866 0545",
    "sg:postcode":"07087",
    "sg:province":"NJ",
    "sg:tags":[
        "acupuncture"
    ],
    "wof:name":"February 2nd Acupuncture",
    "wof:placetype":"venue"
},
  "geometry": {"coordinates":[-74.03214699999999,40.765802],"type":"Point"}
}