{
  "type": "Feature",
  "properties": {
    "iso:country":"US",
    "sg:address":"35 Chadwick Dr",
    "sg:city":"Voorhees",
    "sg:classifiers":[
        {
            "category":"Sports & Exercise",
            "subcategory":"Gym",
            "type":"Entertainment"
        }
    ],
    "sg:phone":"+1   ",
    "sg:postcode":"08043",
    "sg:province":"NJ",
    "sg:tags":[
        "fitness",
        "physical",
        "facility"
    ],
    "wof:name":"Jazzercise",
    "wof:placetype":"venue"
},
  "geometry": {"coordinates":[-74.916286,39.824195],"type":"Point"}
}