{
  "type": "Feature",
  "properties": {
    "iso:country":"US",
    "sg:address":"2176 State Rte 35",
    "sg:city":"Sea Girt",
    "sg:classifiers":[
        {
            "category":"Restaurant",
            "type":"Food & Drink"
        }
    ],
    "sg:phone":"+1 732 223 9250",
    "sg:postcode":"08750",
    "sg:province":"NJ",
    "wof:name":"Andy's Restaurant & Pizza",
    "wof:placetype":"venue"
},
  "geometry": {"coordinates":[-74.0635,40.135928],"type":"Point"}
}