{
  "type": "Feature",
  "properties": {
    "iso:country":"US",
    "sg:address":"10 W Main St",
    "sg:city":"Freehold",
    "sg:classifiers":[
        {
            "category":"Professional",
            "subcategory":"Accounting & Tax Preparation",
            "type":"Services"
        }
    ],
    "sg:phone":"+1 732 780 4433",
    "sg:postcode":"07728",
    "sg:province":"NJ",
    "sg:tags":[
        "accountant"
    ],
    "wof:name":"Susan M Schneider CPA",
    "wof:placetype":"venue"
},
  "geometry": {"coordinates":[-74.274581,40.259729],"type":"Point"}
}