{
  "type": "Feature",
  "properties": {
    "iso:country":"US",
    "sg:address":"1462 Main Ave",
    "sg:city":"Clifton",
    "sg:classifiers":[
        {
            "category":"Restaurant",
            "type":"Food & Drink"
        }
    ],
    "sg:phone":"+1 973 340 0005",
    "sg:postcode":"07011",
    "sg:province":"NJ",
    "sg:tags":[
        "middle",
        "eastern"
    ],
    "sg:website":"Www.aljannahrestaurant.com",
    "wof:name":"Al - Jannah Restaurant",
    "wof:placetype":"venue"
},
  "geometry": {"coordinates":[-74.148777,40.884235],"type":"Point"}
}