{
  "type": "Feature",
  "properties": {
    "addr:full":"21 Priscilla Ln Howell NJ 07731",
    "addr:housenumber":"21",
    "addr:postcode":"07731",
    "addr:street":"Priscilla Ln",
    "iso:country":"US",
    "sg:address":"21 Priscilla Ln",
    "sg:city":"Howell",
    "sg:classifiers":[
        {
            "category":"Professional",
            "subcategory":"Management & Consulting",
            "type":"Services"
        }
    ],
    "sg:phone":"+1 732 886 1664",
    "sg:postcode":"07731",
    "sg:province":"NJ",
    "sg:tags":[
        "environmental",
        "consultant"
    ],
    "wof:name":"Envision Environmental Inc",
    "wof:placetype":"venue"
},
  "geometry": {"coordinates":[-74.243916,40.139183],"type":"Point"}
}