{
  "type": "Feature",
  "properties": {
    "addr:full":"202 W Parkway Dr Egg Harbor Twp NJ 08234",
    "addr:housenumber":"202",
    "addr:postcode":"08234",
    "addr:street":"W Parkway Dr",
    "iso:country":"US",
    "sg:address":"202 W Parkway Dr",
    "sg:city":"Egg Harbor Twp",
    "sg:classifiers":[
        {
            "category":"Wholesale",
            "subcategory":"Electrical",
            "type":"Manufacturing & Wholesale Goods"
        },
        {
            "category":"Wholesale",
            "subcategory":"Durable Goods & Equipment",
            "type":"Manufacturing & Wholesale Goods"
        }
    ],
    "sg:phone":"+1 609 383 9970",
    "sg:postcode":"08234",
    "sg:province":"NJ",
    "sg:tags":[
        "gaming",
        "electronic",
        "supply"
    ],
    "sg:website":"www.age-gaming.com",
    "wof:name":"American Gaming & Electronics",
    "wof:placetype":"venue"
},
  "geometry": {"coordinates":[-74.56254300000001,39.420195],"type":"Point"}
}