{
  "type": "Feature",
  "properties": {
    "addr:full":"2251 State Rte 33 Trenton NJ 08690",
    "addr:housenumber":"2251",
    "addr:postcode":"08690",
    "addr:street":"State Rte 33",
    "iso:country":"US",
    "sg:address":"2251 State Rte 33",
    "sg:city":"Trenton",
    "sg:classifiers":[
        {
            "category":"Professional",
            "subcategory":"Printing & Photocopies",
            "type":"Services"
        }
    ],
    "sg:phone":"+1 609 587 1100",
    "sg:postcode":"08690",
    "sg:province":"NJ",
    "sg:tags":[
        "duplicating",
        "copying"
    ],
    "wof:name":"Copi-Rite Inc",
    "wof:placetype":"venue"
},
  "geometry": {"coordinates":[-74.643732,40.222355],"type":"Point"}
}