{
  "type": "Feature",
  "properties": {
    "iso:country":"US",
    "sg:address":"19 Jill Ter",
    "sg:city":"Succasunna",
    "sg:classifiers":[
        {
            "category":"Professional",
            "subcategory":"Business Services",
            "type":"Services"
        }
    ],
    "sg:phone":"+1   ",
    "sg:postcode":"07876",
    "sg:province":"NJ",
    "sg:tags":[
        "cleaning",
        "pool"
    ],
    "wof:name":"Dolphin Pool",
    "wof:placetype":"venue"
},
  "geometry": {"coordinates":[-74.664074,40.840329],"type":"Point"}
}