{
  "type": "Feature",
  "properties": {
    "addr:full":"8 Westbrook Ct Roselle NJ 07203",
    "addr:housenumber":"8",
    "addr:postcode":"07203",
    "addr:street":"Westbrook Ct",
    "iso:country":"US",
    "sg:address":"8 Westbrook Ct",
    "sg:city":"Roselle",
    "sg:classifiers":[
        {
            "category":"Building & Trades",
            "subcategory":"Construction",
            "type":"Services"
        }
    ],
    "sg:phone":"+1 908 245 0480",
    "sg:postcode":"07203",
    "sg:province":"NJ",
    "sg:tags":[
        "contractor"
    ],
    "wof:name":"Alexandra Development Corp",
    "wof:placetype":"venue"
},
  "geometry": {"coordinates":[-74.268996,40.649907],"type":"Point"}
}