{
  "type": "Feature",
  "properties": {
    "iso:country":"US",
    "sg:address":"14 N Spruce St",
    "sg:city":"Ramsey",
    "sg:classifiers":[
        {
            "category":"Health Services",
            "subcategory":"Doctor",
            "type":"Services"
        }
    ],
    "sg:phone":"+1 201 825 8788",
    "sg:postcode":"07446",
    "sg:province":"NJ",
    "sg:tags":[
        "dentist"
    ],
    "wof:name":"Richard M Vallese DDS",
    "wof:placetype":"venue"
},
  "geometry": {"coordinates":[-74.139511,41.057094],"type":"Point"}
}