{
  "type": "Feature",
  "properties": {
    "iso:country":"US",
    "sg:address":"83 3 Ave",
    "sg:city":"Stone Harbor",
    "sg:classifiers":[
        {
            "category":"Food & Beverages",
            "subcategory":"Groceries & Convenience Stores",
            "type":"Retail Goods"
        }
    ],
    "sg:phone":"+1 609 368 4551",
    "sg:postcode":"08247",
    "sg:province":"NJ",
    "sg:website":"www.budsmarket.com",
    "wof:name":"Bud's Market",
    "wof:placetype":"venue"
},
  "geometry": {"coordinates":[-74.770203,39.0509],"type":"Point"}
}