{
  "type": "Feature",
  "properties": {
    "addr:full":"14 Central Ave Midland Park NJ 07432",
    "addr:housenumber":"14",
    "addr:postcode":"07432",
    "addr:street":"Central Ave",
    "iso:country":"US",
    "sg:address":"14 Central Ave",
    "sg:city":"Midland Park",
    "sg:classifiers":[
        {
            "category":"Shopping",
            "subcategory":"Gifts & Souvenirs",
            "type":"Retail Goods"
        }
    ],
    "sg:phone":"+1 201 447 4460",
    "sg:postcode":"07432",
    "sg:province":"NJ",
    "sg:tags":[
        "announcement",
        "invitation"
    ],
    "wof:name":"Zak & Co",
    "wof:placetype":"venue"
},
  "geometry": {"coordinates":[-74.152491,40.99827],"type":"Point"}
}