{
  "type": "Feature",
  "properties": {
    "addr:full":"71 Kiel Ave Butler NJ 07405",
    "addr:housenumber":"71",
    "addr:postcode":"07405",
    "addr:street":"Kiel Ave",
    "iso:country":"US",
    "sg:address":"71 Kiel Ave",
    "sg:city":"Butler",
    "sg:classifiers":[
        {
            "category":"Building & Trades",
            "subcategory":"Construction",
            "type":"Services"
        }
    ],
    "sg:phone":"+1 973 838 1168",
    "sg:postcode":"07405",
    "sg:province":"NJ",
    "sg:tags":[
        "house"
    ],
    "wof:name":"Kinnelon Construction Company",
    "wof:placetype":"venue"
},
  "geometry": {"coordinates":[-74.34783899999999,41.00217],"type":"Point"}
}