{
  "type": "Feature",
  "properties": {
    "iso:country":"US",
    "sg:address":"11 York Rd",
    "sg:city":"North Arlington",
    "sg:phone":"+1 908 232 9050",
    "sg:postcode":"07031",
    "sg:province":"NJ",
    "sg:tags":[
        "oil"
    ],
    "wof:name":"Concord Fuel Oil Co",
    "wof:placetype":"venue"
},
  "geometry": {"coordinates":[-74.13534799999999,40.788683],"type":"Point"}
}