{
  "type": "Feature",
  "properties": {
    "addr:full":"226 Somerset St North Plainfield NJ 07060",
    "addr:housenumber":"226",
    "addr:postcode":"07060",
    "addr:street":"Somerset St",
    "iso:country":"US",
    "sg:address":"226 Somerset St",
    "sg:city":"North Plainfield",
    "sg:classifiers":[
        {
            "category":"Real Estate",
            "subcategory":"Real Estate Agent",
            "type":"Services"
        }
    ],
    "sg:phone":"+1 908 756 1974",
    "sg:postcode":"07060",
    "sg:province":"NJ",
    "wof:name":"Murkey Realty",
    "wof:placetype":"venue"
},
  "geometry": {"coordinates":[-74.42791,40.620957],"type":"Point"}
}