{
  "type": "Feature",
  "properties": {
    "iso:country":"US",
    "sg:address":"4 Luis Dr",
    "sg:city":"Egg Harbor Township",
    "sg:classifiers":[
        {
            "category":"Building & Trades",
            "subcategory":"Construction",
            "type":"Services"
        }
    ],
    "sg:phone":"+1 609 926 0686",
    "sg:postcode":"08234",
    "sg:province":"NJ",
    "sg:tags":[
        "house"
    ],
    "wof:name":"Mercado Builders LLC",
    "wof:placetype":"venue"
},
  "geometry": {"coordinates":[-74.605537,39.34392],"type":"Point"}
}