{
  "type": "Feature",
  "properties": {
    "addr:full":"42 Park Ave Madison NJ 07940",
    "addr:housenumber":"42",
    "addr:postcode":"07940",
    "addr:street":"Park Ave",
    "iso:country":"US",
    "sg:address":"42 Park Ave",
    "sg:city":"Madison",
    "sg:classifiers":[
        {
            "category":"Building & Trades",
            "subcategory":"Locksmith",
            "type":"Services"
        }
    ],
    "sg:phone":"+1 877 867 0938",
    "sg:postcode":"07940",
    "sg:province":"NJ",
    "sg:tags":[
        "key"
    ],
    "wof:name":"Anytime Anywhere Emergency Locksmith",
    "wof:placetype":"venue"
},
  "geometry": {"coordinates":[-74.418216,40.762461],"type":"Point"}
}