{
  "type": "Feature",
  "properties": {
    "iso:country":"US",
    "sg:address":"11 Sylvester St",
    "sg:city":"Cranford",
    "sg:classifiers":[
        {
            "category":"Professional",
            "subcategory":"Management & Consulting",
            "type":"Services"
        }
    ],
    "sg:phone":"+1   ",
    "sg:postcode":"07016",
    "sg:province":"NJ",
    "wof:name":"Vantage Display Inc",
    "wof:placetype":"venue"
},
  "geometry": {"coordinates":[-74.299004,40.658759],"type":"Point"}
}