{
  "type": "Feature",
  "properties": {
    "addr:full":"100 Black Horse Pike Pleasantville NJ 08232",
    "addr:housenumber":"100",
    "addr:postcode":"08232",
    "addr:street":"Black Horse Pike",
    "iso:country":"US",
    "sg:address":"100 Black Horse Pike",
    "sg:city":"Pleasantville",
    "sg:classifiers":[
        {
            "category":"Shopping",
            "subcategory":"Shoes",
            "type":"Retail Goods"
        }
    ],
    "sg:phone":"+1   ",
    "sg:postcode":"08232",
    "sg:province":"NJ",
    "wof:name":"Foot Locker",
    "wof:placetype":"venue"
},
  "geometry": {"coordinates":[-74.52001799999999,39.388433],"type":"Point"}
}