{
  "type": "Feature",
  "properties": {
    "iso:country":"US",
    "sg:address":"3112 Fire Rd",
    "sg:city":"Egg Harbor Twp",
    "sg:classifiers":[
        {
            "category":"Food & Beverages",
            "subcategory":"Specialty",
            "type":"Retail Goods"
        }
    ],
    "sg:phone":"+1 609 484 1550",
    "sg:postcode":"08234",
    "sg:province":"NJ",
    "sg:tags":[
        "vitamin"
    ],
    "wof:name":"Bonterra Market",
    "wof:placetype":"venue"
},
  "geometry": {"coordinates":[-74.561139,39.392786],"type":"Point"}
}