{
  "type": "Feature",
  "properties": {
    "addr:full":"1039 Hoyt Ave Ridgefield NJ 07657",
    "addr:housenumber":"1039",
    "addr:postcode":"07657",
    "addr:street":"Hoyt Ave",
    "iso:country":"US",
    "sg:address":"1039 Hoyt Ave",
    "sg:city":"Ridgefield",
    "sg:classifiers":[
        {
            "category":"Manufacturing",
            "subcategory":"Tools & Machinery",
            "type":"Manufacturing & Wholesale Goods"
        }
    ],
    "sg:phone":"+1 201 941 1262",
    "sg:postcode":"07657",
    "sg:province":"NJ",
    "sg:tags":[
        "steel",
        "die",
        "cutting",
        "rule",
        "mfg"
    ],
    "wof:name":"Lasercam LLC",
    "wof:placetype":"venue"
},
  "geometry": {"coordinates":[-74.008977,40.836206],"type":"Point"}
}