{
  "type": "Feature",
  "properties": {
    "iso:country":"US",
    "sg:address":"3001 Carmel Rd",
    "sg:city":"Millville",
    "sg:classifiers":[
        {
            "category":"Professional",
            "subcategory":"Business Services",
            "type":"Services"
        },
        {
            "category":"Recreation",
            "type":"Entertainment"
        }
    ],
    "sg:phone":"+1 856 825 3820",
    "sg:postcode":"08332",
    "sg:province":"NJ",
    "sg:tags":[
        "trade",
        "exposition",
        "fair",
        "show"
    ],
    "wof:name":"Cumberland County Co Op",
    "wof:placetype":"venue"
},
  "geometry": {"coordinates":[-75.109268,39.427261],"type":"Point"}
}