{
  "type": "Feature",
  "properties": {
    "iso:country":"US",
    "sg:address":"47 Bruce Dr",
    "sg:city":"Woodbury",
    "sg:classifiers":[
        {
            "category":"Professional",
            "type":"Services"
        }
    ],
    "sg:phone":"+1   ",
    "sg:postcode":"08096",
    "sg:province":"NJ",
    "wof:name":"Georges Snacks",
    "wof:placetype":"venue"
},
  "geometry": {"coordinates":[-75.108577,39.82062],"type":"Point"}
}