{
  "type": "Feature",
  "properties": {
    "addr:full":"40 E Park St Newark NJ 07102",
    "addr:housenumber":"40",
    "addr:postcode":"07102",
    "addr:street":"E Park St",
    "iso:country":"US",
    "sg:address":"40 E Park St",
    "sg:city":"Newark",
    "sg:classifiers":[
        {
            "category":"Organizations",
            "subcategory":"Non-profit Organization",
            "type":"Services"
        }
    ],
    "sg:phone":"+1 973 242 0302",
    "sg:postcode":"07102",
    "sg:province":"NJ",
    "wof:name":"Minority Athletes Networking",
    "wof:placetype":"venue"
},
  "geometry": {"coordinates":[-74.168865,40.738142],"type":"Point"}
}