{
  "type": "Feature",
  "properties": {
    "iso:country":"US",
    "sg:address":"1209 Oak Rd",
    "sg:city":"Manasquan",
    "sg:classifiers":[
        {
            "category":"Building & Trades",
            "subcategory":"Construction",
            "type":"Services"
        }
    ],
    "sg:phone":"+1 732 988 8812",
    "sg:postcode":"08736",
    "sg:province":"NJ",
    "sg:tags":[
        "painter"
    ],
    "wof:name":"Lucas Custom Painting",
    "wof:placetype":"venue"
},
  "geometry": {"coordinates":[-74.065625,40.119764],"type":"Point"}
}