{
  "type": "Feature",
  "properties": {
    "addr:full":"1141 Saint Georges Ave Roselle NJ 07203",
    "addr:housenumber":"1141",
    "addr:postcode":"07203",
    "addr:street":"Saint Georges Ave",
    "iso:country":"US",
    "sg:address":"1141 Saint Georges Ave",
    "sg:city":"Roselle",
    "sg:classifiers":[
        {
            "category":"Restaurant",
            "type":"Food & Drink"
        }
    ],
    "sg:phone":"+1 908 620 1766",
    "sg:postcode":"07203",
    "sg:province":"NJ",
    "wof:name":"Roselle's Fried Chicken & Pzz",
    "wof:placetype":"venue"
},
  "geometry": {"coordinates":[-74.250619,40.645762],"type":"Point"}
}