{
  "type": "Feature",
  "properties": {
    "addr:full":"236 Brick Blvd Brick NJ 08723",
    "addr:housenumber":"236",
    "addr:postcode":"08723",
    "addr:street":"Brick Blvd",
    "iso:country":"US",
    "sg:address":"236 Brick Blvd",
    "sg:city":"Brick",
    "sg:classifiers":[
        {
            "category":"Home & Garden",
            "subcategory":"Furniture",
            "type":"Retail Goods"
        }
    ],
    "sg:phone":"+1   ",
    "sg:postcode":"08723",
    "sg:province":"NJ",
    "wof:name":"Advantage Furniture",
    "wof:placetype":"venue"
},
  "geometry": {"coordinates":[-74.143049,40.036096],"type":"Point"}
}