{
  "type": "Feature",
  "properties": {
    "iso:country":"US",
    "sg:address":"590 Shiloh Pike",
    "sg:city":"Bridgeton",
    "sg:classifiers":[
        {
            "category":"Professional",
            "subcategory":"Engineering",
            "type":"Services"
        }
    ],
    "sg:phone":"+1 856 451 2847",
    "sg:postcode":"08302",
    "sg:province":"NJ",
    "sg:tags":[
        "engineer"
    ],
    "wof:name":"Fralinger Engineering",
    "wof:placetype":"venue"
},
  "geometry": {"coordinates":[-75.264983,39.43991],"type":"Point"}
}