{
  "type": "Feature",
  "properties": {
    "addr:full":"1056 Wright Ave Camden NJ 08103",
    "addr:housenumber":"1056",
    "addr:postcode":"08103",
    "addr:street":"Wright Ave",
    "iso:country":"US",
    "sg:address":"1056 Wright Ave",
    "sg:city":"Camden",
    "sg:classifiers":[
        {
            "category":"Government",
            "subcategory":"Office",
            "type":"Public Place"
        }
    ],
    "sg:phone":"+1 856 757 7680",
    "sg:postcode":"08103",
    "sg:province":"NJ",
    "sg:tags":[
        "govt",
        "city"
    ],
    "wof:name":"Camden Dev & Planning",
    "wof:placetype":"venue"
},
  "geometry": {"coordinates":[-75.11174,39.942745],"type":"Point"}
}