{
  "type": "Feature",
  "properties": {
    "iso:country":"US",
    "sg:address":"2147 Bartram Ave",
    "sg:city":"Atco",
    "sg:classifiers":[
        {
            "category":"Wholesale",
            "subcategory":"Non-durable Goods",
            "type":"Manufacturing & Wholesale Goods"
        },
        {
            "category":"Building & Trades",
            "subcategory":"Construction",
            "type":"Services"
        }
    ],
    "sg:phone":"+1 856 767 8685",
    "sg:postcode":"08004",
    "sg:province":"NJ",
    "sg:tags":[
        "shop",
        "gift",
        "woodworker"
    ],
    "wof:name":"Gillans Custom Crafts",
    "wof:placetype":"venue"
},
  "geometry": {"coordinates":[-74.888008,39.766425],"type":"Point"}
}