{
  "type": "Feature",
  "properties": {
    "addr:full":"400A Cabot Dr Trenton NJ 08691",
    "addr:housenumber":"400a",
    "addr:postcode":"08691",
    "addr:street":"Cabot Dr",
    "iso:country":"US",
    "sg:address":"400A Cabot Dr",
    "sg:city":"Trenton",
    "sg:classifiers":[
        {
            "category":"Wholesale",
            "subcategory":"Electrical",
            "type":"Manufacturing & Wholesale Goods"
        }
    ],
    "sg:phone":"+1 609 860 2612",
    "sg:postcode":"08691",
    "sg:province":"NJ",
    "sg:tags":[
        "systems-wholesale",
        "equipment",
        "air conditioning",
        "manufacturer"
    ],
    "sg:website":"http://www.trane.com",
    "wof:name":"Trane U.S. Inc.",
    "wof:placetype":"venue"
},
  "geometry": {"coordinates":[-74.663307,40.193989],"type":"Point"}
}