{
  "type": "Feature",
  "properties": {
    "addr:full":"221 Main St Fort Lee NJ 07024",
    "addr:housenumber":"221",
    "addr:postcode":"07024",
    "addr:street":"Main St",
    "iso:country":"US",
    "sg:address":"221 Main St",
    "sg:city":"Fort Lee",
    "sg:classifiers":[
        {
            "category":"Shopping",
            "subcategory":"Jewelry",
            "type":"Retail Goods"
        }
    ],
    "sg:phone":"+1 201 944 6999",
    "sg:postcode":"07024",
    "sg:province":"NJ",
    "sg:tags":[
        "jeweler"
    ],
    "wof:name":"Kiky Jewelers",
    "wof:placetype":"venue"
},
  "geometry": {"coordinates":[-73.97232700000001,40.852081],"type":"Point"}
}