{
  "type": "Feature",
  "properties": {
    "iso:country":"US",
    "sg:address":"25 Broadway",
    "sg:city":"Newark",
    "sg:classifiers":[
        {
            "category":"Restaurant",
            "type":"Food & Drink"
        }
    ],
    "sg:phone":"+1   ",
    "sg:postcode":"07104",
    "sg:province":"NJ",
    "sg:tags":[
        "eating"
    ],
    "wof:name":"Great Wall",
    "wof:placetype":"venue"
},
  "geometry": {"coordinates":[-74.169991,40.750108],"type":"Point"}
}