{
  "type": "Feature",
  "properties": {
    "iso:country":"US",
    "sg:address":"15 Egret Ln",
    "sg:city":"Marlboro",
    "sg:classifiers":[
        {
            "category":"Government",
            "subcategory":"Office",
            "type":"Public Place"
        }
    ],
    "sg:phone":"+1   ",
    "sg:postcode":"07746",
    "sg:province":"NJ",
    "sg:tags":[
        "national",
        "security"
    ],
    "wof:name":"Lo Kwok",
    "wof:placetype":"venue"
},
  "geometry": {"coordinates":[-74.242648,40.335087],"type":"Point"}
}