{
  "type": "Feature",
  "properties": {
    "iso:country":"US",
    "sg:address":"1996 Lakewood Rd",
    "sg:city":"Toms River",
    "sg:classifiers":[
        {
            "category":"Wholesale",
            "subcategory":"Durable Goods & Equipment",
            "type":"Manufacturing & Wholesale Goods"
        }
    ],
    "sg:phone":"+1 732 370 1214",
    "sg:postcode":"08755",
    "sg:province":"NJ",
    "sg:tags":[
        "fire",
        "extinguisher"
    ],
    "wof:name":"Code Hood & Ventilation Co",
    "wof:placetype":"venue"
},
  "geometry": {"coordinates":[-74.22210699999999,40.025045],"type":"Point"}
}