{
  "type": "Feature",
  "properties": {
    "iso:country":"US",
    "sg:address":"82 Bloomfield Ave",
    "sg:city":"Newark",
    "sg:classifiers":[
        {
            "category":"Home & Garden",
            "subcategory":"Household Appliances",
            "type":"Retail Goods"
        }
    ],
    "sg:phone":"+1   ",
    "sg:postcode":"07104",
    "sg:province":"NJ",
    "sg:tags":[
        "repair"
    ],
    "wof:name":"B&M Sewing Machine Service",
    "wof:placetype":"venue"
},
  "geometry": {"coordinates":[-74.17377999999999,40.756771],"type":"Point"}
}