{
  "type": "Feature",
  "properties": {
    "addr:full":"4 Jersey St Trenton NJ 08611",
    "addr:housenumber":"4",
    "addr:postcode":"08611",
    "addr:street":"Jersey St",
    "iso:country":"US",
    "sg:address":"4 Jersey St",
    "sg:city":"Trenton",
    "sg:classifiers":[
        {
            "category":"Recreation",
            "type":"Entertainment"
        }
    ],
    "sg:phone":"+1 609 599 5889",
    "sg:postcode":"08611",
    "sg:province":"NJ",
    "wof:name":"New Jersey Lottery Dist Ofc 4",
    "wof:placetype":"venue"
},
  "geometry": {"coordinates":[-74.75118000000001,40.203454],"type":"Point"}
}