{
  "type": "Feature",
  "properties": {
    "iso:country":"US",
    "sg:address":"13 5th St",
    "sg:city":"South River",
    "sg:classifiers":[
        {
            "category":"Retail",
            "subcategory":"Repair Shop",
            "type":"Services"
        }
    ],
    "sg:phone":"+1   ",
    "sg:postcode":"08882",
    "sg:province":"NJ",
    "wof:name":"Garden State Locksmith Inc",
    "wof:placetype":"venue"
},
  "geometry": {"coordinates":[-74.374546,40.432937],"type":"Point"}
}