{
  "type": "Feature",
  "properties": {
    "iso:country":"US",
    "sg:address":"1 Exchange Pl",
    "sg:city":"Jersey City",
    "sg:classifiers":[
        {
            "category":"Building & Trades",
            "subcategory":"Locksmith",
            "type":"Services"
        }
    ],
    "sg:phone":"+1 888 271 6803",
    "sg:postcode":"07302",
    "sg:province":"NJ",
    "sg:tags":[
        "key"
    ],
    "wof:name":"Emergency 24 Hour 7 Day Locksmith",
    "wof:placetype":"venue"
},
  "geometry": {"coordinates":[-74.034029,40.716234],"type":"Point"}
}