{
  "type": "Feature",
  "properties": {
    "addr:full":"410 Paterson Plank Rd Union City NJ 07087",
    "addr:housenumber":"410",
    "addr:postcode":"07087",
    "addr:street":"Paterson Plank Rd",
    "iso:country":"US",
    "sg:address":"410 Paterson Plank Rd",
    "sg:city":"Union City",
    "sg:classifiers":[
        {
            "category":"Personal",
            "subcategory":"Barber",
            "type":"Services"
        }
    ],
    "sg:phone":"+1 201 864 6100",
    "sg:postcode":"07087",
    "sg:province":"NJ",
    "wof:name":"In the Cut Stylez",
    "wof:placetype":"venue"
},
  "geometry": {"coordinates":[-74.043269,40.755881],"type":"Point"}
}