{
  "type": "Feature",
  "properties": {
    "addr:full":"232 Kings Hwy E Haddonfield NJ 08033",
    "addr:housenumber":"232",
    "addr:postcode":"08033",
    "addr:street":"Kings Hwy E",
    "iso:country":"US",
    "sg:address":"232 Kings Hwy E",
    "sg:city":"Haddonfield",
    "sg:classifiers":[
        {
            "category":"Professional",
            "subcategory":"Engineering",
            "type":"Services"
        }
    ],
    "sg:phone":"+1   ",
    "sg:postcode":"08033",
    "sg:province":"NJ",
    "sg:tags":[
        "consulting",
        "engineer"
    ],
    "sg:website":"www.rve.com",
    "wof:name":"Remington & Vernick Engineers",
    "wof:placetype":"venue"
},
  "geometry": {"coordinates":[-75.030289,39.898707],"type":"Point"}
}