{
  "type": "Feature",
  "properties": {
    "iso:country":"US",
    "sg:address":"132 Hampton St",
    "sg:city":"Bridgeton",
    "sg:classifiers":[
        {
            "category":"Health Services",
            "subcategory":"Doctor",
            "type":"Services"
        }
    ],
    "sg:phone":"+1 856 455 9911",
    "sg:postcode":"08302",
    "sg:province":"NJ",
    "sg:tags":[
        "physician",
        "surgeon"
    ],
    "wof:name":"Delaware Valley Nueropsychiatr",
    "wof:placetype":"venue"
},
  "geometry": {"coordinates":[-75.242454,39.424924],"type":"Point"}
}