{
  "type": "Feature",
  "properties": {
    "iso:country":"US",
    "sg:address":"2016 Village Dr",
    "sg:city":"Avenel",
    "sg:classifiers":[
        {
            "category":"Arts & Performance",
            "subcategory":"Theater",
            "type":"Entertainment"
        }
    ],
    "sg:phone":"+1   ",
    "sg:postcode":"07001",
    "sg:province":"NJ",
    "sg:tags":[
        "group"
    ],
    "wof:name":"Touch & Go Entertainment",
    "wof:placetype":"venue"
},
  "geometry": {"coordinates":[-74.284414,40.592172],"type":"Point"}
}