{
  "type": "Feature",
  "properties": {
    "iso:country":"US",
    "sg:address":"491 Lloyd Rd",
    "sg:city":"Matawan",
    "sg:classifiers":[
        {
            "category":"Organizations",
            "subcategory":"Religious Organization",
            "type":"Services"
        }
    ],
    "sg:phone":"+1 732 583 9759",
    "sg:postcode":"07747",
    "sg:province":"NJ",
    "sg:website":"www.atcalvary.org",
    "wof:name":"Calvary Baptist Church",
    "wof:placetype":"venue"
},
  "geometry": {"coordinates":[-74.21637699999999,40.40519],"type":"Point"}
}