{
  "type": "Feature",
  "properties": {
    "addr:full":"60 US Hwy 46 Fairfield NJ 07004",
    "addr:housenumber":"60",
    "addr:postcode":"07004",
    "addr:street":"Us Hwy 46",
    "iso:country":"US",
    "sg:address":"60 US Hwy 46",
    "sg:city":"Fairfield",
    "sg:classifiers":[
        {
            "category":"Real Estate",
            "subcategory":"Real Estate Agent",
            "type":"Services"
        }
    ],
    "sg:phone":"+1   ",
    "sg:postcode":"07004",
    "sg:province":"NJ",
    "sg:tags":[
        "rental"
    ],
    "wof:name":"Clinton Slaff Associates",
    "wof:placetype":"venue"
},
  "geometry": {"coordinates":[-74.311628,40.868082],"type":"Point"}
}