{
  "type": "Feature",
  "properties": {
    "iso:country":"US",
    "sg:address":"526 Pacific Ave",
    "sg:city":"Atlantic City",
    "sg:classifiers":[
        {
            "category":"Real Estate",
            "subcategory":"Real Estate Agent",
            "type":"Services"
        }
    ],
    "sg:phone":"+1   ",
    "sg:postcode":"08401",
    "sg:province":"NJ",
    "wof:name":"Bella Condominiums",
    "wof:placetype":"venue"
},
  "geometry": {"coordinates":[-74.41681800000001,39.364642],"type":"Point"}
}