{
  "type": "Feature",
  "properties": {
    "addr:full":"307 E Hanover Ave Morristown NJ 07960",
    "addr:housenumber":"307",
    "addr:postcode":"07960",
    "addr:street":"E Hanover Ave",
    "iso:country":"US",
    "sg:address":"307 E Hanover Ave",
    "sg:city":"Morristown",
    "sg:classifiers":[
        {
            "category":"Retail",
            "subcategory":"Storage",
            "type":"Services"
        }
    ],
    "sg:phone":"+1 973 539 5055",
    "sg:postcode":"07960",
    "sg:province":"NJ",
    "sg:tags":[
        "self"
    ],
    "sg:website":"www.ustoreit.com",
    "wof:name":"U-Store-It",
    "wof:placetype":"venue"
},
  "geometry": {"coordinates":[-74.45970199999999,40.806301],"type":"Point"}
}