{
  "type": "Feature",
  "properties": {
    "addr:full":"264 Addison Pl Paramus NJ 07652",
    "addr:housenumber":"264",
    "addr:postcode":"07652",
    "addr:street":"Addison Pl",
    "iso:country":"US",
    "sg:address":"264 Addison Pl",
    "sg:city":"Paramus",
    "sg:classifiers":[
        {
            "category":"Building & Trades",
            "subcategory":"Electrical",
            "type":"Services"
        }
    ],
    "sg:phone":"+1 201 261 0306",
    "sg:postcode":"07652",
    "sg:province":"NJ",
    "sg:tags":[
        "electrical",
        "contractor"
    ],
    "wof:name":"Hughes Electric Inc",
    "wof:placetype":"venue"
},
  "geometry": {"coordinates":[-74.054526,40.937497],"type":"Point"}
}