{
  "type": "Feature",
  "properties": {
    "iso:country":"US",
    "sg:address":"143 Franklin Tpke",
    "sg:city":"Waldwick",
    "sg:classifiers":[
        {
            "category":"Manufacturing",
            "subcategory":"Printing",
            "type":"Manufacturing & Wholesale Goods"
        }
    ],
    "sg:phone":"+1 201 652 2035",
    "sg:postcode":"07463",
    "sg:province":"NJ",
    "sg:tags":[
        "commercial"
    ],
    "wof:name":"Avenue Printing Co",
    "wof:placetype":"venue"
},
  "geometry": {"coordinates":[-74.122319,41.018494],"type":"Point"}
}