{
  "type": "Feature",
  "properties": {
    "addr:full":"67 Scotch Rd Trenton NJ 08628",
    "addr:housenumber":"67",
    "addr:postcode":"08628",
    "addr:street":"Scotch Rd",
    "iso:country":"US",
    "sg:address":"67 Scotch Rd",
    "sg:city":"Trenton",
    "sg:classifiers":[
        {
            "category":"Organizations",
            "subcategory":"Labor Organization",
            "type":"Services"
        }
    ],
    "sg:phone":"+1 609 434 1032",
    "sg:postcode":"08628",
    "sg:province":"NJ",
    "wof:name":"Communications Workers-America",
    "wof:placetype":"venue"
},
  "geometry": {"coordinates":[-74.800645,40.267528],"type":"Point"}
}