{
  "type": "Feature",
  "properties": {
    "iso:country":"US",
    "sg:address":"112 Commons Way",
    "sg:city":"Princeton",
    "sg:classifiers":[
        {
            "category":"Professional",
            "subcategory":"Management & Consulting",
            "type":"Services"
        }
    ],
    "sg:phone":"+1 609 252 9112",
    "sg:postcode":"08540",
    "sg:province":"NJ",
    "sg:tags":[
        "business"
    ],
    "wof:name":"Spire Systems Inc",
    "wof:placetype":"venue"
},
  "geometry": {"coordinates":[-74.65786199999999,40.394497],"type":"Point"}
}