{
  "type": "Feature",
  "properties": {
    "iso:country":"US",
    "sg:address":"267 State Rte 23",
    "sg:city":"Sussex",
    "sg:classifiers":[
        {
            "category":"Home & Garden",
            "subcategory":"Garden Supply",
            "type":"Retail Goods"
        }
    ],
    "sg:phone":"+1 973 702 3300",
    "sg:postcode":"07461",
    "sg:province":"NJ",
    "sg:tags":[
        "nurseryman"
    ],
    "wof:name":"Blackburn Growers",
    "wof:placetype":"venue"
},
  "geometry": {"coordinates":[-74.586625,41.189339],"type":"Point"}
}