{
  "type": "Feature",
  "properties": {
    "addr:full":"760 State St Perth Amboy NJ 08861",
    "addr:housenumber":"760",
    "addr:postcode":"08861",
    "addr:street":"State St",
    "iso:country":"US",
    "sg:address":"760 State St",
    "sg:city":"Perth Amboy",
    "sg:classifiers":[
        {
            "category":"Organizations",
            "subcategory":"Religious Organization",
            "type":"Services"
        }
    ],
    "sg:phone":"+1 732 826 8810",
    "sg:postcode":"08861",
    "sg:province":"NJ",
    "sg:tags":[
        "church"
    ],
    "wof:name":"LA Victoria SDA Church",
    "wof:placetype":"venue"
},
  "geometry": {"coordinates":[-74.26424,40.524057],"type":"Point"}
}