{
  "type": "Feature",
  "properties": {
    "addr:full":"16 Kimberly Ct Monmouth Junction NJ 08852",
    "addr:housenumber":"16",
    "addr:postcode":"08852",
    "addr:street":"Kimberly Ct",
    "iso:country":"US",
    "sg:address":"16 Kimberly Ct",
    "sg:city":"Monmouth Junction",
    "sg:classifiers":[
        {
            "category":"Professional",
            "subcategory":"Computer Services",
            "type":"Services"
        }
    ],
    "sg:phone":"+1   ",
    "sg:postcode":"08852",
    "sg:province":"NJ",
    "sg:tags":[
        "related"
    ],
    "wof:name":"Webage Inc",
    "wof:placetype":"venue"
},
  "geometry": {"coordinates":[-74.57346,40.39355],"type":"Point"}
}