{
  "type": "Feature",
  "properties": {
    "addr:full":"100 Belmont Dr Livingston NJ 07039",
    "addr:housenumber":"100",
    "addr:postcode":"07039",
    "addr:street":"Belmont Dr",
    "iso:country":"US",
    "sg:address":"100 Belmont Dr",
    "sg:city":"Livingston",
    "sg:classifiers":[
        {
            "category":"Professional",
            "type":"Services"
        }
    ],
    "sg:phone":"+1 732 560 9797",
    "sg:postcode":"07039",
    "sg:province":"NJ",
    "sg:tags":[
        "establishment"
    ],
    "wof:name":"Qwantech International Inc",
    "wof:placetype":"venue"
},
  "geometry": {"coordinates":[-74.326241,40.789348],"type":"Point"}
}