{
  "type": "Feature",
  "properties": {
    "addr:full":"427 Van Houten Ave Passaic NJ 07055",
    "addr:housenumber":"427",
    "addr:postcode":"07055",
    "addr:street":"Van Houten Ave",
    "iso:country":"US",
    "sg:address":"427 Van Houten Ave",
    "sg:city":"Passaic",
    "sg:classifiers":[
        {
            "category":"Bars & Pubs",
            "type":"Food & Drink"
        }
    ],
    "sg:phone":"+1   ",
    "sg:postcode":"07055",
    "sg:province":"NJ",
    "sg:tags":[
        "drinking"
    ],
    "wof:name":"Kids Room",
    "wof:placetype":"venue"
},
  "geometry": {"coordinates":[-74.141212,40.854033],"type":"Point"}
}