{
  "type": "Feature",
  "properties": {
    "iso:country":"US",
    "sg:address":"38 Budd Lake Heights Rd",
    "sg:city":"Budd Lake",
    "sg:classifiers":[
        {
            "category":"Restaurant",
            "type":"Food & Drink"
        }
    ],
    "sg:phone":"+1   ",
    "sg:postcode":"07828",
    "sg:province":"NJ",
    "sg:tags":[
        "eating"
    ],
    "wof:name":"Martys Ice Cream",
    "wof:placetype":"venue"
},
  "geometry": {"coordinates":[-74.75210800000001,40.885655],"type":"Point"}
}