{
  "type": "Feature",
  "properties": {
    "addr:full":"5470 Genoa Ave Vineland NJ 08361",
    "addr:housenumber":"5470",
    "addr:postcode":"08361",
    "addr:street":"Genoa Ave",
    "iso:country":"US",
    "sg:address":"5470 Genoa Ave",
    "sg:city":"Vineland",
    "sg:phone":"+1 856 691 7283",
    "sg:postcode":"08361",
    "sg:province":"NJ",
    "sg:tags":[
        "farm"
    ],
    "wof:name":"Franceschini Farms",
    "wof:placetype":"venue"
},
  "geometry": {"coordinates":[-74.934501,39.46534],"type":"Point"}
}