{
  "type": "Feature",
  "properties": {
    "iso:country":"US",
    "sg:address":"69 Brisco Ter",
    "sg:city":"Hazlet",
    "sg:classifiers":[
        {
            "category":"Travel",
            "subcategory":"Travel Agent",
            "type":"Entertainment"
        }
    ],
    "sg:phone":"+1 732 264 6609",
    "sg:postcode":"07730",
    "sg:province":"NJ",
    "sg:tags":[
        "agency"
    ],
    "wof:name":"Shrewsbury Travel",
    "wof:placetype":"venue"
},
  "geometry": {"coordinates":[-74.20186099999999,40.409706],"type":"Point"}
}