{
  "type": "Feature",
  "properties": {
    "addr:full":"14 Cushing Dr Bridgewater NJ 08807",
    "addr:housenumber":"14",
    "addr:postcode":"08807",
    "addr:street":"Cushing Dr",
    "iso:country":"US",
    "sg:address":"14 Cushing Dr",
    "sg:city":"Bridgewater",
    "sg:classifiers":[
        {
            "category":"Shopping",
            "subcategory":"Clothing, Apparel, & Fashions",
            "type":"Retail Goods"
        }
    ],
    "sg:phone":"+1 908 253 9900",
    "sg:postcode":"08807",
    "sg:province":"NJ",
    "wof:name":"Fashion House Inc",
    "wof:placetype":"venue"
},
  "geometry": {"coordinates":[-74.58653,40.62274],"type":"Point"}
}