{
  "type": "Feature",
  "properties": {
    "iso:country":"US",
    "sg:address":"3 14th St",
    "sg:city":"Lakewood",
    "sg:classifiers":[
        {
            "category":"Organizations",
            "subcategory":"Membership Organization",
            "type":"Services"
        }
    ],
    "sg:phone":"+1   ",
    "sg:postcode":"08701",
    "sg:province":"NJ",
    "wof:name":"Ner Tzadok Inc",
    "wof:placetype":"venue"
},
  "geometry": {"coordinates":[-74.20806,40.105216],"type":"Point"}
}