{
  "type": "Feature",
  "properties": {
    "addr:full":"6713 Park Ave Guttenberg NJ 07093",
    "addr:housenumber":"6713",
    "addr:postcode":"07093",
    "addr:street":"Park Ave",
    "iso:country":"US",
    "sg:address":"6713 Park Ave",
    "sg:city":"Guttenberg",
    "sg:classifiers":[
        {
            "category":"Retail",
            "subcategory":"Self-service Laundry",
            "type":"Services"
        }
    ],
    "sg:phone":"+1 201 662 7700",
    "sg:postcode":"07093",
    "sg:province":"NJ",
    "sg:tags":[
        "coin"
    ],
    "wof:name":"Speed Wash Laundromat",
    "wof:placetype":"venue"
},
  "geometry": {"coordinates":[-74.004346,40.791253],"type":"Point"}
}