{
  "type": "Feature",
  "properties": {
    "iso:country":"US",
    "sg:address":"7 Quail Run",
    "sg:city":"Warren",
    "sg:classifiers":[
        {
            "category":"Professional",
            "subcategory":"Accounting & Tax Preparation",
            "type":"Services"
        }
    ],
    "sg:phone":"+1 732 356 6017",
    "sg:postcode":"07059",
    "sg:province":"NJ",
    "wof:name":"Barry Argiro CPA",
    "wof:placetype":"venue"
},
  "geometry": {"coordinates":[-74.508205,40.609803],"type":"Point"}
}