{
  "type": "Feature",
  "properties": {
    "addr:full":"110 Little Falls Rd Fairfield NJ 07004",
    "addr:housenumber":"110",
    "addr:postcode":"07004",
    "addr:street":"Little Falls Rd",
    "iso:country":"US",
    "sg:address":"110 Little Falls Rd",
    "sg:city":"Fairfield",
    "sg:classifiers":[
        {
            "category":"Professional",
            "subcategory":"Research",
            "type":"Services"
        }
    ],
    "sg:phone":"+1 973 882 0860",
    "sg:postcode":"07004",
    "sg:province":"NJ",
    "sg:tags":[
        "company",
        "engaged",
        "product"
    ],
    "sg:website":"www.unigene.com",
    "wof:name":"Unigene Laboratories Inc",
    "wof:placetype":"venue"
},
  "geometry": {"coordinates":[-74.270853,40.888957],"type":"Point"}
}