{
  "type": "Feature",
  "properties": {
    "addr:full":"1509 Solook Dr Parlin NJ 08859",
    "addr:housenumber":"1509",
    "addr:postcode":"08859",
    "addr:street":"Solook Dr",
    "iso:country":"US",
    "sg:address":"1509 Solook Dr",
    "sg:city":"Parlin",
    "sg:classifiers":[
        {
            "category":"Professional",
            "subcategory":"Management & Consulting",
            "type":"Services"
        }
    ],
    "sg:phone":"+1   ",
    "sg:postcode":"08859",
    "sg:province":"NJ",
    "sg:tags":[
        "business"
    ],
    "wof:name":"Gertraud Pichelbauer",
    "wof:placetype":"venue"
},
  "geometry": {"coordinates":[-74.327032,40.465686],"type":"Point"}
}