{
  "type": "Feature",
  "properties": {
    "iso:country":"US",
    "sg:address":"10 Throckmorton Ave",
    "sg:city":"Eatontown",
    "sg:classifiers":[
        {
            "category":"Wholesale",
            "subcategory":"Electrical",
            "type":"Manufacturing & Wholesale Goods"
        }
    ],
    "sg:phone":"+1 732 460 9260",
    "sg:postcode":"07724",
    "sg:province":"NJ",
    "sg:tags":[
        "recording",
        "studio"
    ],
    "wof:name":"Authority Studios",
    "wof:placetype":"venue"
},
  "geometry": {"coordinates":[-74.05863600000001,40.3063],"type":"Point"}
}