{
  "type": "Feature",
  "properties": {
    "addr:full":"189 Rock Rd Glen Rock NJ 07452",
    "addr:housenumber":"189",
    "addr:postcode":"07452",
    "addr:street":"Rock Rd",
    "iso:country":"US",
    "sg:address":"189 Rock Rd",
    "sg:city":"Glen Rock",
    "sg:classifiers":[
        {
            "category":"Shopping",
            "type":"Retail Goods"
        }
    ],
    "sg:phone":"+1 201 447 4123",
    "sg:postcode":"07452",
    "sg:province":"NJ",
    "sg:tags":[
        "picture",
        "frame",
        "merchandise",
        "repair"
    ],
    "wof:name":"Glen Rock Art & Frame Inc",
    "wof:placetype":"venue"
},
  "geometry": {"coordinates":[-74.13297,40.962744],"type":"Point"}
}