{
  "type": "Feature",
  "properties": {
    "iso:country":"US",
    "sg:address":"46 College Ave",
    "sg:city":"New Brunswick",
    "sg:classifiers":[
        {
            "category":"Education",
            "subcategory":"College",
            "type":"Public Place"
        }
    ],
    "sg:phone":"+1   ",
    "sg:postcode":"08901",
    "sg:province":"NJ",
    "wof:name":"Carreer Service Rutgers Univ",
    "wof:placetype":"venue"
},
  "geometry": {"coordinates":[-74.449012,40.500222],"type":"Point"}
}