{
  "type": "Feature",
  "properties": {
    "addr:full":"57 Woodstock Dr Wayne NJ 07470",
    "addr:housenumber":"57",
    "addr:postcode":"07470",
    "addr:street":"Woodstock Dr",
    "iso:country":"US",
    "sg:address":"57 Woodstock Dr",
    "sg:city":"Wayne",
    "sg:classifiers":[
        {
            "category":"Building & Trades",
            "subcategory":"Plumbing",
            "type":"Services"
        }
    ],
    "sg:phone":"+1 973 694 6338",
    "sg:postcode":"07470",
    "sg:province":"NJ",
    "sg:tags":[
        "contractor"
    ],
    "wof:name":"Defranco Phil Plbg & Htg Co",
    "wof:placetype":"venue"
},
  "geometry": {"coordinates":[-74.23344899999999,40.935175],"type":"Point"}
}