{
  "type": "Feature",
  "properties": {
    "addr:full":"1902 Marlton Pike E Cherry Hill NJ 08003",
    "addr:housenumber":"1902",
    "addr:postcode":"08003",
    "addr:street":"Marlton Pike E",
    "iso:country":"US",
    "sg:address":"1902 Marlton Pike E",
    "sg:city":"Cherry Hill",
    "sg:classifiers":[
        {
            "category":"Personal",
            "subcategory":"Beauty Salon",
            "type":"Services"
        }
    ],
    "sg:phone":"+1 856 424 8494",
    "sg:postcode":"08003",
    "sg:province":"NJ",
    "wof:name":"Servus-Station",
    "wof:placetype":"venue"
},
  "geometry": {"coordinates":[-74.96589,39.902763],"type":"Point"}
}