{
  "type": "Feature",
  "properties": {
    "addr:full":"40 N Four Bridges Rd Long Valley NJ 07853",
    "addr:housenumber":"40",
    "addr:postcode":"07853",
    "addr:street":"N Four Bridges Rd",
    "iso:country":"US",
    "sg:address":"40 N Four Bridges Rd",
    "sg:city":"Long Valley",
    "sg:classifiers":[
        {
            "category":"Building & Trades",
            "subcategory":"Construction",
            "type":"Services"
        }
    ],
    "sg:phone":"+1 973 879 5195",
    "sg:postcode":"07853",
    "sg:province":"NJ",
    "wof:name":"Christopher Day Construction",
    "wof:placetype":"venue"
},
  "geometry": {"coordinates":[-74.73797999999999,40.816185],"type":"Point"}
}