{
  "type": "Feature",
  "properties": {
    "iso:country":"US",
    "sg:address":"4045 English Creek Ave",
    "sg:city":"Egg Harbor Township",
    "sg:classifiers":[
        {
            "category":"Manufacturing",
            "subcategory":"Metals",
            "type":"Manufacturing & Wholesale Goods"
        }
    ],
    "sg:phone":"+1 609 383 0801",
    "sg:postcode":"08234",
    "sg:province":"NJ",
    "sg:tags":[
        "steel",
        "mfg"
    ],
    "wof:name":"Pro Fabricators",
    "wof:placetype":"venue"
},
  "geometry": {"coordinates":[-74.62217800000001,39.413973],"type":"Point"}
}