{
  "type": "Feature",
  "properties": {
    "iso:country":"US",
    "sg:address":"342 Main St",
    "sg:city":"Hackensack",
    "sg:classifiers":[
        {
            "category":"Shopping",
            "subcategory":"Music",
            "type":"Retail Goods"
        }
    ],
    "sg:phone":"+1 201 487 1018",
    "sg:postcode":"07601",
    "sg:province":"NJ",
    "sg:tags":[
        "compact",
        "record",
        "disc",
        "tape"
    ],
    "wof:name":"Rinconcito Musical",
    "wof:placetype":"venue"
},
  "geometry": {"coordinates":[-74.040097,40.888773],"type":"Point"}
}