{
  "type": "Feature",
  "properties": {
    "addr:full":"7 Homestead Rd Elmwood Park NJ 07407",
    "addr:housenumber":"7",
    "addr:postcode":"07407",
    "addr:street":"Homestead Rd",
    "iso:country":"US",
    "sg:address":"7 Homestead Rd",
    "sg:city":"Elmwood Park",
    "sg:classifiers":[
        {
            "category":"Building & Trades",
            "subcategory":"Construction",
            "type":"Services"
        }
    ],
    "sg:phone":"+1 201 791 7144",
    "sg:postcode":"07407",
    "sg:province":"NJ",
    "sg:tags":[
        "home",
        "general",
        "family",
        "contractor"
    ],
    "wof:name":"Sal Lattera Jr Construction",
    "wof:placetype":"venue"
},
  "geometry": {"coordinates":[-74.12391700000001,40.897368],"type":"Point"}
}