{
  "type": "Feature",
  "properties": {
    "addr:full":"21 Division St Somerville NJ 08876",
    "addr:housenumber":"21",
    "addr:postcode":"08876",
    "addr:street":"Division St",
    "iso:country":"US",
    "sg:address":"21 Division St",
    "sg:city":"Somerville",
    "sg:classifiers":[
        {
            "category":"Personal",
            "subcategory":"Beauty Salon",
            "type":"Services"
        }
    ],
    "sg:phone":"+1 908 707 8244",
    "sg:postcode":"08876",
    "sg:province":"NJ",
    "wof:name":"Mayela Quesada",
    "wof:placetype":"venue"
},
  "geometry": {"coordinates":[-74.61302999999999,40.568026],"type":"Point"}
}