{
  "type": "Feature",
  "properties": {
    "addr:full":"1214 Plane St Union NJ 07083",
    "addr:housenumber":"1214",
    "addr:postcode":"07083",
    "addr:street":"Plane St",
    "iso:country":"US",
    "sg:address":"1214 Plane St",
    "sg:city":"Union",
    "sg:classifiers":[
        {
            "category":"Retail",
            "subcategory":"Portrait Studio",
            "type":"Services"
        }
    ],
    "sg:phone":"+1   ",
    "sg:postcode":"07083",
    "sg:province":"NJ",
    "sg:tags":[
        "laboratory",
        "photofinishing",
        "photo"
    ],
    "wof:name":"Image Network",
    "wof:placetype":"venue"
},
  "geometry": {"coordinates":[-74.267349,40.700582],"type":"Point"}
}