{
  "type": "Feature",
  "properties": {
    "addr:full":"3600 Earle St Pennsauken NJ 08110",
    "addr:housenumber":"3600",
    "addr:postcode":"08110",
    "addr:street":"Earle St",
    "iso:country":"US",
    "sg:address":"3600 Earle St",
    "sg:city":"Pennsauken",
    "sg:classifiers":[
        {
            "category":"Education",
            "subcategory":"School",
            "type":"Public Place"
        }
    ],
    "sg:phone":"+1 856 910 2815",
    "sg:postcode":"08110",
    "sg:province":"NJ",
    "wof:name":"Jdt Christian Academy",
    "wof:placetype":"venue"
},
  "geometry": {"coordinates":[-75.082397,39.935501],"type":"Point"}
}