{
  "type": "Feature",
  "properties": {
    "addr:full":"558 Anderson Ave Cliffside Park NJ 07010",
    "addr:housenumber":"558",
    "addr:postcode":"07010",
    "addr:street":"Anderson Ave",
    "iso:country":"US",
    "sg:address":"558 Anderson Ave",
    "sg:city":"Cliffside Park",
    "sg:classifiers":[
        {
            "category":"Health Services",
            "subcategory":"Health Practitioner",
            "type":"Services"
        }
    ],
    "sg:phone":"+1 201 943 2978",
    "sg:postcode":"07010",
    "sg:province":"NJ",
    "sg:tags":[
        "counseling",
        "mental"
    ],
    "wof:name":"Kehayan V Alex Edd",
    "wof:placetype":"venue"
},
  "geometry": {"coordinates":[-73.989403,40.823299],"type":"Point"}
}