{
  "type": "Feature",
  "properties": {
    "addr:full":"51 Main St Succasunna NJ 07876",
    "addr:housenumber":"51",
    "addr:postcode":"07876",
    "addr:street":"Main St",
    "iso:country":"US",
    "sg:address":"51 Main St",
    "sg:city":"Succasunna",
    "sg:classifiers":[
        {
            "category":"Personal",
            "subcategory":"Beauty Salon",
            "type":"Services"
        }
    ],
    "sg:phone":"+1   ",
    "sg:postcode":"07876",
    "sg:province":"NJ",
    "sg:tags":[
        "shop"
    ],
    "wof:name":"Perfect Touch",
    "wof:placetype":"venue"
},
  "geometry": {"coordinates":[-74.634044,40.865741],"type":"Point"}
}