{
  "type": "Feature",
  "properties": {
    "addr:full":"50 Winfield Scott Plz Elizabeth NJ 07201",
    "addr:housenumber":"50",
    "addr:postcode":"07201",
    "addr:street":"Winfield Scott Plz",
    "iso:country":"US",
    "sg:address":"50 Winfield Scott Plz",
    "sg:city":"Elizabeth",
    "sg:classifiers":[
        {
            "category":"Government",
            "subcategory":"City Hall",
            "type":"Public Place"
        }
    ],
    "sg:phone":"+1 908 820 4000",
    "sg:postcode":"07201",
    "sg:province":"NJ",
    "sg:website":"www.elizabethnj.org",
    "wof:name":"City Hall of Elizabeth, NJ",
    "wof:placetype":"venue"
},
  "geometry": {"coordinates":[-74.211519,40.663556],"type":"Point"}
}