{
  "type": "Feature",
  "properties": {
    "iso:country":"US",
    "sg:address":"3 Sylvia Way",
    "sg:city":"Trenton",
    "sg:classifiers":[
        {
            "category":"Wholesale",
            "subcategory":"Hardware",
            "type":"Manufacturing & Wholesale Goods"
        }
    ],
    "sg:phone":"+1 609 448 2228",
    "sg:postcode":"08691",
    "sg:province":"NJ",
    "wof:name":"J K Fasteners",
    "wof:placetype":"venue"
},
  "geometry": {"coordinates":[-74.614419,40.226784],"type":"Point"}
}