{
  "type": "Feature",
  "properties": {
    "iso:country":"US",
    "sg:address":"34 Church St",
    "sg:city":"Montclair",
    "sg:classifiers":[
        {
            "category":"Shopping",
            "subcategory":"Used Merchandise",
            "type":"Retail Goods"
        }
    ],
    "sg:phone":"+1 973 746 1062",
    "sg:postcode":"07042",
    "sg:province":"NJ",
    "sg:tags":[
        "antique"
    ],
    "sg:website":"www.montclairantiquecenter.com",
    "wof:name":"Montclair Antique Center",
    "wof:placetype":"venue"
},
  "geometry": {"coordinates":[-74.21929900000001,40.814201],"type":"Point"}
}