{
  "type": "Feature",
  "properties": {
    "iso:country":"US",
    "sg:address":"425 Birch Dr",
    "sg:city":"Mickleton",
    "sg:classifiers":[
        {
            "category":"Travel",
            "subcategory":"Hotels & Motels",
            "type":"Entertainment"
        }
    ],
    "sg:phone":"+1   ",
    "sg:postcode":"08056",
    "sg:province":"NJ",
    "sg:tags":[
        "shop",
        "gift"
    ],
    "wof:name":"Jolly Roger Motel & Gift",
    "wof:placetype":"venue"
},
  "geometry": {"coordinates":[-75.245305,39.795146],"type":"Point"}
}