{
  "type": "Feature",
  "properties": {
    "addr:full":"208 Leeward Rd Manahawkin NJ 08050",
    "addr:housenumber":"208",
    "addr:postcode":"08050",
    "addr:street":"Leeward Rd",
    "iso:country":"US",
    "sg:address":"208 Leeward Rd",
    "sg:city":"Manahawkin",
    "sg:classifiers":[
        {
            "category":"Arts & Performance",
            "subcategory":"Theater",
            "type":"Entertainment"
        }
    ],
    "sg:phone":"+1 609 660 0221",
    "sg:postcode":"08050",
    "sg:province":"NJ",
    "sg:tags":[
        "group",
        "live",
        "music"
    ],
    "wof:name":"Jimmy Brown Dj",
    "wof:placetype":"venue"
},
  "geometry": {"coordinates":[-74.296713,39.736469],"type":"Point"}
}