{
  "type": "Feature",
  "properties": {
    "addr:full":"8 Devonshire Ln Mendham NJ 07945",
    "addr:housenumber":"8",
    "addr:postcode":"07945",
    "addr:street":"Devonshire Ln",
    "iso:country":"US",
    "sg:address":"8 Devonshire Ln",
    "sg:city":"Mendham",
    "sg:classifiers":[
        {
            "category":"Professional",
            "type":"Services"
        }
    ],
    "sg:phone":"+1   ",
    "sg:postcode":"07945",
    "sg:province":"NJ",
    "wof:name":"RTS Aviation Inc",
    "wof:placetype":"venue"
},
  "geometry": {"coordinates":[-74.584119,40.782179],"type":"Point"}
}