{
  "type": "Feature",
  "properties": {
    "addr:full":"7 Shugal Ct Hillsborough NJ 08844",
    "addr:housenumber":"7",
    "addr:postcode":"08844",
    "addr:street":"Shugal Ct",
    "iso:country":"US",
    "sg:address":"7 Shugal Ct",
    "sg:city":"Hillsborough",
    "sg:classifiers":[
        {
            "category":"Wholesale",
            "subcategory":"Auto Parts",
            "type":"Manufacturing & Wholesale Goods"
        }
    ],
    "sg:phone":"+1 908 874 9958",
    "sg:postcode":"08844",
    "sg:province":"NJ",
    "sg:tags":[
        "automobile"
    ],
    "wof:name":"Dent King",
    "wof:placetype":"venue"
},
  "geometry": {"coordinates":[-74.649985,40.521998],"type":"Point"}
}