{
  "type": "Feature",
  "properties": {
    "addr:full":"161 Hamburg Tpke Bloomingdale NJ 07403",
    "addr:housenumber":"161",
    "addr:postcode":"07403",
    "addr:street":"Hamburg Tpke",
    "iso:country":"US",
    "sg:address":"161 Hamburg Tpke",
    "sg:city":"Bloomingdale",
    "sg:classifiers":[
        {
            "category":"Deli",
            "type":"Food & Drink"
        },
        {
            "category":"Food & Beverages",
            "subcategory":"Bakery",
            "type":"Retail Goods"
        }
    ],
    "sg:phone":"+1 973 838 6100",
    "sg:postcode":"07403",
    "sg:province":"NJ",
    "sg:tags":[
        "sandwich"
    ],
    "wof:name":"Agostino's Italian Deli & Restaurant",
    "wof:placetype":"venue"
},
  "geometry": {"coordinates":[-74.344086,41.006487],"type":"Point"}
}