{
  "type": "Feature",
  "properties": {
    "iso:country":"US",
    "sg:address":"12 William St",
    "sg:city":"Newark",
    "sg:classifiers":[
        {
            "category":"Travel",
            "subcategory":"Travel Agent",
            "type":"Entertainment"
        }
    ],
    "sg:phone":"+1 973 623 5985",
    "sg:postcode":"07102",
    "sg:province":"NJ",
    "sg:tags":[
        "ticket",
        "agency",
        "airline"
    ],
    "wof:name":"Sun Travels",
    "wof:placetype":"venue"
},
  "geometry": {"coordinates":[-74.17386,40.733169],"type":"Point"}
}