{
  "type": "Feature",
  "properties": {
    "iso:country":"US",
    "sg:address":"145 Main St",
    "sg:city":"Franklin",
    "sg:classifiers":[
        {
            "category":"Organizations",
            "subcategory":"Religious Organization",
            "type":"Services"
        }
    ],
    "sg:phone":"+1   ",
    "sg:postcode":"07416",
    "sg:province":"NJ",
    "wof:name":"Kings Bible Chapel",
    "wof:placetype":"venue"
},
  "geometry": {"coordinates":[-74.583789,41.123968],"type":"Point"}
}