{
  "type": "Feature",
  "properties": {
    "iso:country":"US",
    "sg:address":"860 Wyckoff Ave",
    "sg:city":"Mahwah",
    "sg:classifiers":[
        {
            "category":"Insurance",
            "subcategory":"Insurance Agent",
            "type":"Services"
        },
        {
            "category":"Insurance",
            "subcategory":"Hazard Insurance",
            "type":"Services"
        },
        {
            "category":"Insurance",
            "subcategory":"Title Insurance",
            "type":"Services"
        },
        {
            "category":"Insurance",
            "subcategory":"Life Insurance",
            "type":"Services"
        }
    ],
    "sg:phone":"+1 201 847 0050",
    "sg:postcode":"07430",
    "sg:province":"NJ",
    "sg:tags":[
        "business",
        "auto",
        "commercial",
        "homeowner",
        "motorcycle",
        "renter"
    ],
    "wof:name":"Allstate New Jersey Insurance Company - Regina Vitti",
    "wof:placetype":"venue"
},
  "geometry": {"coordinates":[-74.167664,41.024342],"type":"Point"}
}