{
  "type": "Feature",
  "properties": {
    "iso:country":"US",
    "sg:address":"344 Aldo Dr",
    "sg:city":"Toms River",
    "sg:classifiers":[
        {
            "category":"Banks & Credit Unions",
            "subcategory":"Bank",
            "type":"Services"
        }
    ],
    "sg:phone":"+1   ",
    "sg:postcode":"08753",
    "sg:province":"NJ",
    "sg:tags":[
        "reduction",
        "program",
        "mortgage",
        "selling"
    ],
    "wof:name":"Mortgage Savings Program",
    "wof:placetype":"venue"
},
  "geometry": {"coordinates":[-74.120982,40.00776],"type":"Point"}
}