{
  "type": "Feature",
  "properties": {
    "iso:country":"US",
    "sg:address":"1129 Broad St",
    "sg:city":"Shrewsbury",
    "sg:classifiers":[
        {
            "category":"Professional",
            "subcategory":"Lawyer & Legal Services",
            "type":"Services"
        }
    ],
    "sg:phone":"+1 732 542 2236",
    "sg:postcode":"07702",
    "sg:province":"NJ",
    "sg:tags":[
        "attorney"
    ],
    "wof:name":"Caruso & Baxter Inc",
    "wof:placetype":"venue"
},
  "geometry": {"coordinates":[-74.06401099999999,40.312834],"type":"Point"}
}