{
  "type": "Feature",
  "properties": {
    "iso:country":"US",
    "sg:address":"1211 Hamburg Tpke",
    "sg:city":"Wayne",
    "sg:classifiers":[
        {
            "category":"Health Services",
            "subcategory":"Optometrist",
            "type":"Services"
        }
    ],
    "sg:phone":"+1 973 696 0998",
    "sg:postcode":"07470",
    "sg:province":"NJ",
    "sg:tags":[
        "ophthalmologist"
    ],
    "wof:name":"Silodor Scott MD Eye Specialist",
    "wof:placetype":"venue"
},
  "geometry": {"coordinates":[-74.241302,40.9604],"type":"Point"}
}