{
  "type": "Feature",
  "properties": {
    "iso:country":"US",
    "sg:address":"1404 Kings Hwy",
    "sg:city":"Swedesboro",
    "sg:classifiers":[
        {
            "category":"Banks & Credit Unions",
            "subcategory":"Bank",
            "type":"Services"
        },
        {
            "category":"Shopping",
            "subcategory":"Used Merchandise",
            "type":"Retail Goods"
        }
    ],
    "sg:phone":"+1 856 467 1796",
    "sg:postcode":"08085",
    "sg:province":"NJ",
    "sg:tags":[
        "resale",
        "shop",
        "second",
        "hand"
    ],
    "wof:name":"The King's Things",
    "wof:placetype":"venue"
},
  "geometry": {"coordinates":[-75.310044,39.74801],"type":"Point"}
}