{
  "type": "Feature",
  "properties": {
    "addr:full":"20 S Midland Ave Kearny NJ 07032",
    "addr:housenumber":"20",
    "addr:postcode":"07032",
    "addr:street":"S Midland Ave",
    "iso:country":"US",
    "sg:address":"20 S Midland Ave",
    "sg:city":"Kearny",
    "sg:classifiers":[
        {
            "category":"Freight",
            "type":"Transportation"
        }
    ],
    "sg:phone":"+1 201 998 8032",
    "sg:postcode":"07032",
    "sg:province":"NJ",
    "sg:tags":[
        "operator",
        "trucking"
    ],
    "wof:name":"Gold & Silver Warehouse",
    "wof:placetype":"venue"
},
  "geometry": {"coordinates":[-74.152928,40.770947],"type":"Point"}
}