{
  "type": "Feature",
  "properties": {
    "addr:full":"555 Anderson Ave Cliffside Park NJ 07010",
    "addr:housenumber":"555",
    "addr:postcode":"07010",
    "addr:street":"Anderson Ave",
    "iso:country":"US",
    "sg:address":"555 Anderson Ave",
    "sg:city":"Cliffside Park",
    "sg:classifiers":[
        {
            "category":"Restaurant",
            "type":"Food & Drink"
        }
    ],
    "sg:phone":"+1 201 941 7876",
    "sg:postcode":"07010",
    "sg:province":"NJ",
    "wof:name":"Osteria Del Gusto",
    "wof:placetype":"venue"
},
  "geometry": {"coordinates":[-73.98901600000001,40.823758],"type":"Point"}
}