{
  "type": "Feature",
  "properties": {
    "iso:country":"US",
    "sg:address":"900 Lincoln Blvd",
    "sg:city":"Middlesex",
    "sg:classifiers":[
        {
            "category":"Insurance",
            "subcategory":"Insurance Agent",
            "type":"Services"
        }
    ],
    "sg:phone":"+1   ",
    "sg:postcode":"08846",
    "sg:province":"NJ",
    "sg:tags":[
        "broker"
    ],
    "wof:name":"Steeles Financial Services",
    "wof:placetype":"venue"
},
  "geometry": {"coordinates":[-74.48514299999999,40.577652],"type":"Point"}
}