{
  "type": "Feature",
  "properties": {
    "addr:full":"1010 US Hwy 202 Branchburg NJ 08876",
    "addr:housenumber":"1010",
    "addr:postcode":"08876",
    "addr:street":"Us Hwy 202",
    "iso:country":"US",
    "sg:address":"1010 US Hwy 202",
    "sg:city":"Branchburg",
    "sg:classifiers":[
        {
            "category":"Retail",
            "subcategory":"Repair Shop",
            "type":"Services"
        }
    ],
    "sg:phone":"+1 908 275 0581",
    "sg:postcode":"08876",
    "sg:province":"NJ",
    "sg:tags":[
        "lock",
        "locksmith"
    ],
    "wof:name":"USA Locksmith",
    "wof:placetype":"venue"
},
  "geometry": {"coordinates":[-74.69642,40.563355],"type":"Point"}
}