{
  "type": "Feature",
  "properties": {
    "iso:country":"US",
    "sg:address":"536 Main Ave",
    "sg:city":"Point Pleasant Beach",
    "sg:classifiers":[
        {
            "category":"Food & Beverages",
            "subcategory":"Liquor & Beverages",
            "type":"Retail Goods"
        }
    ],
    "sg:phone":"+1   ",
    "sg:postcode":"08742",
    "sg:province":"NJ",
    "sg:tags":[
        "grocery",
        "alcoholic"
    ],
    "wof:name":"Central Market",
    "wof:placetype":"venue"
},
  "geometry": {"coordinates":[-74.04454,40.066427],"type":"Point"}
}