{
  "type": "Feature",
  "properties": {
    "iso:country":"US",
    "sg:address":"81 Monmouth Rd",
    "sg:city":"Monroe Township",
    "sg:classifiers":[
        {
            "category":"Professional",
            "type":"Services"
        }
    ],
    "sg:phone":"+1   ",
    "sg:postcode":"08831",
    "sg:province":"NJ",
    "wof:name":"Brunswick Reading & Speech Cen",
    "wof:placetype":"venue"
},
  "geometry": {"coordinates":[-74.38101899999999,40.37153],"type":"Point"}
}