{
  "type": "Feature",
  "properties": {
    "iso:country":"US",
    "sg:address":"397 New Dover Rd",
    "sg:city":"Colonia",
    "sg:classifiers":[
        {
            "category":"Health Services",
            "subcategory":"Doctor",
            "type":"Services"
        }
    ],
    "sg:phone":"+1 732 381 3375",
    "sg:postcode":"07067",
    "sg:province":"NJ",
    "wof:name":"Nicora Bernard Dr",
    "wof:placetype":"venue"
},
  "geometry": {"coordinates":[-74.318521,40.586113],"type":"Point"}
}