{
  "type": "Feature",
  "properties": {
    "iso:country":"US",
    "sg:address":"519 Curtis Ln",
    "sg:city":"Lakewood",
    "sg:classifiers":[
        {
            "category":"Building & Trades",
            "subcategory":"Construction",
            "type":"Services"
        }
    ],
    "sg:phone":"+1 732 363 3346",
    "sg:postcode":"08701",
    "sg:province":"NJ",
    "sg:tags":[
        "contractor"
    ],
    "wof:name":"Aqua Flow Gutters LLC",
    "wof:placetype":"venue"
},
  "geometry": {"coordinates":[-74.241552,40.105087],"type":"Point"}
}