{
  "type": "Feature",
  "properties": {
    "addr:full":"71 Leeds Ln Monroe Township NJ 08831",
    "addr:housenumber":"71",
    "addr:postcode":"08831",
    "addr:street":"Leeds Ln",
    "iso:country":"US",
    "sg:address":"71 Leeds Ln",
    "sg:city":"Monroe Township",
    "sg:classifiers":[
        {
            "category":"Professional",
            "type":"Services"
        }
    ],
    "sg:phone":"+1   ",
    "sg:postcode":"08831",
    "sg:province":"NJ",
    "wof:name":"Dr Billig",
    "wof:placetype":"venue"
},
  "geometry": {"coordinates":[-74.447164,40.32454],"type":"Point"}
}