{
  "type": "Feature",
  "properties": {
    "addr:full":"375 Myrtle Ave Boonton NJ 07005",
    "addr:housenumber":"375",
    "addr:postcode":"07005",
    "addr:street":"Myrtle Ave",
    "iso:country":"US",
    "sg:address":"375 Myrtle Ave",
    "sg:city":"Boonton",
    "sg:classifiers":[
        {
            "category":"Retail",
            "subcategory":"Car Wash",
            "type":"Services"
        }
    ],
    "sg:phone":"+1 973 402 0400",
    "sg:postcode":"07005",
    "sg:province":"NJ",
    "sg:tags":[
        "carwash"
    ],
    "wof:name":"Boonton Express Car Wash",
    "wof:placetype":"venue"
},
  "geometry": {"coordinates":[-74.401582,40.906037],"type":"Point"}
}