{
  "type": "Feature",
  "properties": {
    "iso:country":"US",
    "sg:address":"1600 Stuyvesant Ave",
    "sg:city":"Union",
    "sg:classifiers":[
        {
            "category":"Cemetery",
            "type":"Public Place"
        },
        {
            "category":"Retail",
            "subcategory":"Funeral Services",
            "type":"Services"
        },
        {
            "category":"Professional",
            "subcategory":"Management & Consulting",
            "type":"Services"
        }
    ],
    "sg:phone":"+1 908 964 4222",
    "sg:postcode":"07083",
    "sg:province":"NJ",
    "sg:tags":[
        "director",
        "consultant",
        "crematory",
        "plans-pre-arranged"
    ],
    "sg:website":"http://www.unionfuneralhome.com",
    "wof:name":"Union Funeral Home-Lytwyn & Lytwyn",
    "wof:placetype":"venue"
},
  "geometry": {"coordinates":[-74.259552,40.709991],"type":"Point"}
}