{
  "type": "Feature",
  "properties": {
    "addr:full":"47 Sunrise Dr Montvale NJ 07645",
    "addr:housenumber":"47",
    "addr:postcode":"07645",
    "addr:street":"Sunrise Dr",
    "iso:country":"US",
    "sg:address":"47 Sunrise Dr",
    "sg:city":"Montvale",
    "sg:classifiers":[
        {
            "category":"Professional",
            "subcategory":"Management & Consulting",
            "type":"Services"
        }
    ],
    "sg:phone":"+1 201 476 1908",
    "sg:postcode":"07645",
    "sg:province":"NJ",
    "wof:name":"All American Temps Inc",
    "wof:placetype":"venue"
},
  "geometry": {"coordinates":[-74.07549899999999,41.059243],"type":"Point"}
}