{
  "type": "Feature",
  "properties": {
    "iso:country":"US",
    "sg:address":"865 N Delsea Dr Unit 113",
    "sg:city":"Clayton",
    "sg:classifiers":[
        {
            "category":"Social Services",
            "type":"Services"
        }
    ],
    "sg:phone":"+1 856 881 9950",
    "sg:postcode":"08312",
    "sg:province":"NJ",
    "sg:tags":[
        "consulting",
        "geriatric"
    ],
    "wof:name":"Clayton Mews",
    "wof:placetype":"venue"
},
  "geometry": {"coordinates":[-75.093858,39.665764],"type":"Point"}
}