{
  "type": "Feature",
  "properties": {
    "addr:full":"42 Cherry St Lebanon NJ 08833",
    "addr:housenumber":"42",
    "addr:postcode":"08833",
    "addr:street":"Cherry St",
    "iso:country":"US",
    "sg:address":"42 Cherry St",
    "sg:city":"Lebanon",
    "sg:classifiers":[
        {
            "category":"Building & Trades",
            "subcategory":"Construction",
            "type":"Services"
        }
    ],
    "sg:phone":"+1 908 236 0220",
    "sg:postcode":"08833",
    "sg:province":"NJ",
    "wof:name":"Kullman Industries",
    "wof:placetype":"venue"
},
  "geometry": {"coordinates":[-74.833465,40.637184],"type":"Point"}
}