{
  "type": "Feature",
  "properties": {
    "addr:full":"632 State Rte 17 Paramus NJ 07652",
    "addr:housenumber":"632",
    "addr:postcode":"07652",
    "addr:street":"State Rte 17",
    "iso:country":"US",
    "sg:address":"632 State Rte 17",
    "sg:city":"Paramus",
    "sg:classifiers":[
        {
            "category":"Home & Garden",
            "subcategory":"Building Materials",
            "type":"Retail Goods"
        }
    ],
    "sg:phone":"+1 201 447 4747",
    "sg:postcode":"07652",
    "sg:province":"NJ",
    "sg:tags":[
        "paint",
        "wallpaper",
        "supply"
    ],
    "wof:name":"Norton Paints",
    "wof:placetype":"venue"
},
  "geometry": {"coordinates":[-74.077743,40.965545],"type":"Point"}
}