{
  "type": "Feature",
  "properties": {
    "iso:country":"US",
    "sg:address":"164 Franklin Tpke",
    "sg:city":"Mahwah",
    "sg:classifiers":[
        {
            "category":"Wholesale",
            "subcategory":"Machinery & Supplies",
            "type":"Manufacturing & Wholesale Goods"
        }
    ],
    "sg:phone":"+1 201 529 1299",
    "sg:postcode":"07430",
    "sg:province":"NJ",
    "sg:tags":[
        "co",
        "janitorial"
    ],
    "wof:name":"Ace Janitorial Supply",
    "wof:placetype":"venue"
},
  "geometry": {"coordinates":[-74.146248,41.097004],"type":"Point"}
}