{
  "type": "Feature",
  "properties": {
    "addr:full":"63 Washington Ave Carteret NJ 07008",
    "addr:housenumber":"63",
    "addr:postcode":"07008",
    "addr:street":"Washington Ave",
    "iso:country":"US",
    "sg:address":"63 Washington Ave",
    "sg:city":"Carteret",
    "sg:classifiers":[
        {
            "category":"Manufacturing",
            "subcategory":"Jewelry",
            "type":"Manufacturing & Wholesale Goods"
        },
        {
            "category":"Wholesale",
            "subcategory":"Non-durable Goods",
            "type":"Manufacturing & Wholesale Goods"
        }
    ],
    "sg:phone":"+1 732 541 6646",
    "sg:postcode":"07008",
    "sg:province":"NJ",
    "sg:tags":[
        "import",
        "natural",
        "costume",
        "g",
        "home"
    ],
    "sg:website":"www.qeximtrade.com",
    "wof:name":"Q Eximtrade Inc",
    "wof:placetype":"venue"
},
  "geometry": {"coordinates":[-74.22206199999999,40.576391],"type":"Point"}
}