{
  "type": "Feature",
  "properties": {
    "addr:full":"200 Mount Laurel Rd Mt Laurel NJ 08054",
    "addr:housenumber":"200",
    "addr:postcode":"08054",
    "addr:street":"Mount Laurel Rd",
    "iso:country":"US",
    "sg:address":"200 Mount Laurel Rd",
    "sg:city":"Mt Laurel",
    "sg:classifiers":[
        {
            "category":"Food & Beverages",
            "subcategory":"Groceries & Convenience Stores",
            "type":"Retail Goods"
        }
    ],
    "sg:phone":"+1 856 231 8961",
    "sg:postcode":"08054",
    "sg:province":"NJ",
    "sg:tags":[
        "grocer"
    ],
    "wof:name":"Wawa Food Market",
    "wof:placetype":"venue"
},
  "geometry": {"coordinates":[-74.922056,39.955134],"type":"Point"}
}