{
  "type": "Feature",
  "properties": {
    "iso:country":"US",
    "sg:address":"206 Sanford Ave",
    "sg:city":"Emerson",
    "sg:classifiers":[
        {
            "category":"Professional",
            "subcategory":"Business Services",
            "type":"Services"
        }
    ],
    "sg:phone":"+1   ",
    "sg:postcode":"07630",
    "sg:province":"NJ",
    "wof:name":"Mjt Assoc",
    "wof:placetype":"venue"
},
  "geometry": {"coordinates":[-74.013231,40.980214],"type":"Point"}
}