{
  "type": "Feature",
  "properties": {
    "iso:country":"US",
    "sg:address":"4437 State Rte 27",
    "sg:city":"Princeton",
    "sg:classifiers":[
        {
            "category":"Food & Beverages",
            "subcategory":"Candy",
            "type":"Retail Goods"
        }
    ],
    "sg:phone":"+1 609 924 5009",
    "sg:postcode":"08540",
    "sg:province":"NJ",
    "sg:tags":[
        "confectionery"
    ],
    "wof:name":"Mom's Candy Corner",
    "wof:placetype":"venue"
},
  "geometry": {"coordinates":[-74.610131,40.377126],"type":"Point"}
}