{
  "type": "Feature",
  "properties": {
    "addr:full":"60 Lockwood St Newark NJ 07105",
    "addr:housenumber":"60",
    "addr:postcode":"07105",
    "addr:street":"Lockwood St",
    "iso:country":"US",
    "sg:address":"60 Lockwood St",
    "sg:city":"Newark",
    "sg:classifiers":[
        {
            "category":"Wholesale",
            "subcategory":"Scrap",
            "type":"Manufacturing & Wholesale Goods"
        }
    ],
    "sg:phone":"+1 973 465 3900",
    "sg:postcode":"07105",
    "sg:province":"NJ",
    "sg:tags":[
        "pulp",
        "mill",
        "material",
        "refuse",
        "system"
    ],
    "wof:name":"Recycled Fibers of New Jersey",
    "wof:placetype":"venue"
},
  "geometry": {"coordinates":[-74.132417,40.735047],"type":"Point"}
}