{
  "type": "Feature",
  "properties": {
    "iso:country":"US",
    "sg:address":"1004 White Horse Pike",
    "sg:city":"Oaklyn",
    "sg:classifiers":[
        {
            "category":"Autos & Motor Vehicles",
            "subcategory":"Automobile Sales",
            "type":"Retail Goods"
        }
    ],
    "sg:phone":"+1 856 858 9298",
    "sg:postcode":"08107",
    "sg:province":"NJ",
    "sg:tags":[
        "new",
        "car"
    ],
    "wof:name":"Classic Chrysler Inc",
    "wof:placetype":"venue"
},
  "geometry": {"coordinates":[-75.074532,39.899518],"type":"Point"}
}