{
  "type": "Feature",
  "properties": {
    "iso:country":"US",
    "sg:address":"1003 Summit Ave",
    "sg:city":"Union City",
    "sg:classifiers":[
        {
            "category":"Education",
            "subcategory":"Preschool",
            "type":"Public Place"
        },
        {
            "category":"Education",
            "subcategory":"School",
            "type":"Public Place"
        }
    ],
    "sg:phone":"+1 201 864 1856",
    "sg:postcode":"07087",
    "sg:province":"NJ",
    "sg:tags":[
        "elementary"
    ],
    "wof:name":"Junior Prep Pre-School Center",
    "wof:placetype":"venue"
},
  "geometry": {"coordinates":[-74.04239699999999,40.760201],"type":"Point"}
}