{
  "type": "Feature",
  "properties": {
    "addr:full":"709 Hamburg Tpke Wayne NJ 07470",
    "addr:housenumber":"709",
    "addr:postcode":"07470",
    "addr:street":"Hamburg Tpke",
    "iso:country":"US",
    "sg:address":"709 Hamburg Tpke",
    "sg:city":"Wayne",
    "sg:classifiers":[
        {
            "category":"Banks & Credit Unions",
            "subcategory":"Bank",
            "type":"Services"
        }
    ],
    "sg:phone":"+1   ",
    "sg:postcode":"07470",
    "sg:province":"NJ",
    "sg:tags":[
        "state"
    ],
    "wof:name":"Fleet",
    "wof:placetype":"venue"
},
  "geometry": {"coordinates":[-74.222566,40.956994],"type":"Point"}
}