{
  "type": "Feature",
  "properties": {
    "iso:country":"US",
    "sg:address":"243 la Cascata",
    "sg:city":"Clementon",
    "sg:classifiers":[
        {
            "category":"Home & Garden",
            "subcategory":"Carpets & Floor Coverings",
            "type":"Retail Goods"
        }
    ],
    "sg:phone":"+1 856 309 8771",
    "sg:postcode":"08021",
    "sg:province":"NJ",
    "sg:tags":[
        "distributor",
        "rug",
        "manufacturer"
    ],
    "wof:name":"Q's Carpet Care",
    "wof:placetype":"venue"
},
  "geometry": {"coordinates":[-75.024576,39.807651],"type":"Point"}
}