{
  "type": "Feature",
  "properties": {
    "iso:country":"US",
    "sg:address":"37 Delaware Ave",
    "sg:city":"Bloomfield",
    "sg:classifiers":[
        {
            "category":"Building & Trades",
            "subcategory":"Construction",
            "type":"Services"
        }
    ],
    "sg:phone":"+1 973 259 1305",
    "sg:postcode":"07003",
    "sg:province":"NJ",
    "sg:tags":[
        "house"
    ],
    "wof:name":"Miguel Construction",
    "wof:placetype":"venue"
},
  "geometry": {"coordinates":[-74.195007,40.78511],"type":"Point"}
}