{
  "type": "Feature",
  "properties": {
    "addr:full":"277 2nd St Elizabeth NJ 07206",
    "addr:housenumber":"277",
    "addr:postcode":"07206",
    "addr:street":"2Nd St",
    "iso:country":"US",
    "sg:address":"277 2nd St",
    "sg:city":"Elizabeth",
    "sg:classifiers":[
        {
            "category":"Personal",
            "subcategory":"Beauty Salon",
            "type":"Services"
        }
    ],
    "sg:phone":"+1 908 355 9397",
    "sg:postcode":"07206",
    "sg:province":"NJ",
    "sg:tags":[
        "shop"
    ],
    "wof:name":"Salon Monaco",
    "wof:placetype":"venue"
},
  "geometry": {"coordinates":[-74.181982,40.653991],"type":"Point"}
}