{
  "type": "Feature",
  "properties": {
    "iso:country":"US",
    "sg:address":"785 S Orange Ave",
    "sg:city":"Newark",
    "sg:classifiers":[
        {
            "category":"Taxi",
            "type":"Transportation"
        }
    ],
    "sg:phone":"+1 973 371 9755",
    "sg:postcode":"07106",
    "sg:province":"NJ",
    "sg:tags":[
        "taxicab"
    ],
    "wof:name":"First Class Car Services",
    "wof:placetype":"venue"
},
  "geometry": {"coordinates":[-74.221034,40.745123],"type":"Point"}
}