{
  "type": "Feature",
  "properties": {
    "addr:full":"3461 US Hwy 22 Branchburg NJ 08876",
    "addr:housenumber":"3461",
    "addr:postcode":"08876",
    "addr:street":"Us Hwy 22",
    "iso:country":"US",
    "sg:address":"3461 US Hwy 22",
    "sg:city":"Branchburg",
    "sg:classifiers":[
        {
            "category":"Health Services",
            "subcategory":"Health Practitioner",
            "type":"Services"
        }
    ],
    "sg:phone":"+1 908 534 6271",
    "sg:postcode":"08876",
    "sg:province":"NJ",
    "sg:tags":[
        "acupuncture"
    ],
    "wof:name":"County Line Family Practice",
    "wof:placetype":"venue"
},
  "geometry": {"coordinates":[-74.708943,40.6082],"type":"Point"}
}