{
  "type": "Feature",
  "properties": {
    "addr:full":"1000 Thomas Busch Mem Hwy Pennsauken NJ 08110",
    "addr:housenumber":"1000",
    "addr:postcode":"08110",
    "addr:street":"Thomas Busch Mem Hwy",
    "iso:country":"US",
    "sg:address":"1000 Thomas Busch Mem Hwy",
    "sg:city":"Pennsauken",
    "sg:classifiers":[
        {
            "category":"Manufacturing",
            "subcategory":"Paper Products",
            "type":"Manufacturing & Wholesale Goods"
        }
    ],
    "sg:phone":"+1 215 423 7800",
    "sg:postcode":"08110",
    "sg:province":"NJ",
    "sg:tags":[
        "box",
        "fiber",
        "mfg"
    ],
    "wof:name":"Mc Lean Corrugated Containers",
    "wof:placetype":"venue"
},
  "geometry": {"coordinates":[-75.029166,39.988701],"type":"Point"}
}