{
  "type": "Feature",
  "properties": {
    "addr:full":"1415 Queen Anne Rd # 101 Teaneck NJ 07666",
    "addr:housenumber":"1415",
    "addr:postcode":"07666",
    "addr:street":"Queen Anne Rd # 101",
    "iso:country":"US",
    "sg:address":"1415 Queen Anne Rd # 101",
    "sg:city":"Teaneck",
    "sg:classifiers":[
        {
            "category":"Health Services",
            "subcategory":"Health Practitioner",
            "type":"Services"
        },
        {
            "category":"Communications",
            "type":"Services"
        }
    ],
    "sg:phone":"+1 201 833 0655",
    "sg:postcode":"07666",
    "sg:province":"NJ",
    "sg:tags":[
        "pathologist",
        "speech-language",
        "myofunctional",
        "therapy"
    ],
    "wof:name":"Balaban & Assoc",
    "wof:placetype":"venue"
},
  "geometry": {"coordinates":[-74.017746,40.881275],"type":"Point"}
}