{
  "type": "Feature",
  "properties": {
    "iso:country":"US",
    "sg:address":"941 State Rte 37",
    "sg:city":"Toms River",
    "sg:classifiers":[
        {
            "category":"Utilities",
            "subcategory":"Mobile Phone",
            "type":"Services"
        }
    ],
    "sg:phone":"+1 732 286 9696",
    "sg:postcode":"08755",
    "sg:province":"NJ",
    "sg:tags":[
        "telephone",
        "cellular"
    ],
    "wof:name":"Nextel",
    "wof:placetype":"venue"
},
  "geometry": {"coordinates":[-74.242133,39.97464],"type":"Point"}
}