{
  "type": "Feature",
  "properties": {
    "iso:country":"US",
    "sg:address":"300 Front St",
    "sg:city":"Secaucus",
    "sg:classifiers":[
        {
            "category":"Personal",
            "subcategory":"Beauty Salon",
            "type":"Services"
        }
    ],
    "sg:phone":"+1 201 330 1234",
    "sg:postcode":"07094",
    "sg:province":"NJ",
    "wof:name":"Annie's Unisex Salon",
    "wof:placetype":"venue"
},
  "geometry": {"coordinates":[-74.06487799999999,40.794346],"type":"Point"}
}