{
  "type": "Feature",
  "properties": {
    "addr:full":"80 W Main St Mendham NJ 07945",
    "addr:housenumber":"80",
    "addr:postcode":"07945",
    "addr:street":"W Main St",
    "iso:country":"US",
    "sg:address":"80 W Main St",
    "sg:city":"Mendham",
    "sg:classifiers":[
        {
            "category":"Health Services",
            "subcategory":"Clinic",
            "type":"Services"
        }
    ],
    "sg:phone":"+1   ",
    "sg:postcode":"07945",
    "sg:province":"NJ",
    "sg:tags":[
        "hospital",
        "specialty",
        "outpatient"
    ],
    "wof:name":"Daytop Village Inc",
    "wof:placetype":"venue"
},
  "geometry": {"coordinates":[-74.61593000000001,40.773637],"type":"Point"}
}