{
  "type": "Feature",
  "properties": {
    "iso:country":"US",
    "sg:address":"1761 Greenwood Ave",
    "sg:city":"Trenton",
    "sg:classifiers":[
        {
            "category":"Autos & Motor Vehicles",
            "subcategory":"Fuel & Gas Station",
            "type":"Retail Goods"
        }
    ],
    "sg:phone":"+1   ",
    "sg:postcode":"08609",
    "sg:province":"NJ",
    "sg:tags":[
        "station",
        "gasoline"
    ],
    "wof:name":"Greenwood Texaco",
    "wof:placetype":"venue"
},
  "geometry": {"coordinates":[-74.73157999999999,40.22669],"type":"Point"}
}