{
  "type": "Feature",
  "properties": {
    "addr:full":"2681 Lawrenceville Rd Trenton NJ 08648",
    "addr:housenumber":"2681",
    "addr:postcode":"08648",
    "addr:street":"Lawrenceville Rd",
    "iso:country":"US",
    "sg:address":"2681 Lawrenceville Rd",
    "sg:city":"Trenton",
    "sg:classifiers":[
        {
            "category":"Real Estate",
            "subcategory":"Real Estate Agent",
            "type":"Services"
        }
    ],
    "sg:phone":"+1 609 896 4900",
    "sg:postcode":"08648",
    "sg:province":"NJ",
    "wof:name":"Folmer Edward Broker Sales",
    "wof:placetype":"venue"
},
  "geometry": {"coordinates":[-74.72769099999999,40.299768],"type":"Point"}
}