{
  "type": "Feature",
  "properties": {
    "addr:full":"356 Greenmount Ave Cliffside Park NJ 07010",
    "addr:housenumber":"356",
    "addr:postcode":"07010",
    "addr:street":"Greenmount Ave",
    "iso:country":"US",
    "sg:address":"356 Greenmount Ave",
    "sg:city":"Cliffside Park",
    "sg:classifiers":[
        {
            "category":"Health Services",
            "subcategory":"Medical Lab",
            "type":"Services"
        }
    ],
    "sg:phone":"+1 201 941 0553",
    "sg:postcode":"07010",
    "sg:province":"NJ",
    "sg:tags":[
        "laboratory",
        "dental"
    ],
    "wof:name":"New Age T M J Ortho Corp",
    "wof:placetype":"venue"
},
  "geometry": {"coordinates":[-73.99024199999999,40.82268],"type":"Point"}
}