{
  "type": "Feature",
  "properties": {
    "addr:full":"1460 Morris Ave Union NJ 07083",
    "addr:housenumber":"1460",
    "addr:postcode":"07083",
    "addr:street":"Morris Ave",
    "iso:country":"US",
    "sg:address":"1460 Morris Ave",
    "sg:city":"Union",
    "sg:classifiers":[
        {
            "category":"Education",
            "subcategory":"Special Training",
            "type":"Public Place"
        }
    ],
    "sg:phone":"+1 908 686 8602",
    "sg:postcode":"07083",
    "sg:province":"NJ",
    "wof:name":"E-Z Way Tutoring",
    "wof:placetype":"venue"
},
  "geometry": {"coordinates":[-74.24877499999999,40.689877],"type":"Point"}
}