{
  "type": "Feature",
  "properties": {
    "iso:country":"US",
    "sg:address":"11 N 3rd St",
    "sg:city":"Harrison",
    "sg:classifiers":[
        {
            "category":"Organizations",
            "subcategory":"Religious Organization",
            "type":"Services"
        }
    ],
    "sg:phone":"+1   ",
    "sg:postcode":"07029",
    "sg:province":"NJ",
    "wof:name":"Msn Outreach Intl",
    "wof:placetype":"venue"
},
  "geometry": {"coordinates":[-74.158264,40.746867],"type":"Point"}
}