{
  "type": "Feature",
  "properties": {
    "iso:country":"US",
    "sg:address":"815 Summer Ave",
    "sg:city":"Newark",
    "sg:classifiers":[
        {
            "category":"Organizations",
            "subcategory":"Religious Organization",
            "type":"Services"
        }
    ],
    "sg:phone":"+1 973 350 0100",
    "sg:postcode":"07104",
    "sg:province":"NJ",
    "sg:tags":[
        "church"
    ],
    "wof:name":"Iglesia Pentecostal Palabra",
    "wof:placetype":"venue"
},
  "geometry": {"coordinates":[-74.16059799999999,40.780339],"type":"Point"}
}