{
  "type": "Feature",
  "properties": {
    "iso:country":"US",
    "sg:address":"298 Chestnut St",
    "sg:city":"Ridgewood",
    "sg:classifiers":[
        {
            "category":"Restaurant",
            "type":"Food & Drink"
        }
    ],
    "sg:menulink":"http://www.allmenus.com/nj/ridgewood/27155-the-officejolly-trolley/menu/",
    "sg:phone":"+1 201 652 1070",
    "sg:postcode":"07450",
    "sg:province":"NJ",
    "sg:tags":[
        "american"
    ],
    "wof:name":"The Office/Jolly Trolley",
    "wof:placetype":"venue"
},
  "geometry": {"coordinates":[-74.117062,40.986317],"type":"Point"}
}