{
  "type": "Feature",
  "properties": {
    "addr:full":"20 Bland St Emerson NJ 07630",
    "addr:housenumber":"20",
    "addr:postcode":"07630",
    "addr:street":"Bland St",
    "iso:country":"US",
    "sg:address":"20 Bland St",
    "sg:city":"Emerson",
    "sg:classifiers":[
        {
            "category":"Shopping",
            "subcategory":"Pharmacy",
            "type":"Retail Goods"
        }
    ],
    "sg:phone":"+1 201 818 2715",
    "sg:postcode":"07630",
    "sg:province":"NJ",
    "wof:name":"Atrium Pharmacy",
    "wof:placetype":"venue"
},
  "geometry": {"coordinates":[-74.026037,40.980532],"type":"Point"}
}