{
  "type": "Feature",
  "properties": {
    "addr:full":"2600 Bergenline Ave Union City NJ 07087",
    "addr:housenumber":"2600",
    "addr:postcode":"07087",
    "addr:street":"Bergenline Ave",
    "iso:country":"US",
    "sg:address":"2600 Bergenline Ave",
    "sg:city":"Union City",
    "sg:classifiers":[
        {
            "category":"Building & Trades",
            "subcategory":"Locksmith",
            "type":"Services"
        }
    ],
    "sg:phone":"+1 201 210 6128",
    "sg:postcode":"07087",
    "sg:province":"NJ",
    "sg:tags":[
        "key"
    ],
    "wof:name":"Union City Emergency Locksmith",
    "wof:placetype":"venue"
},
  "geometry": {"coordinates":[-74.03156,40.768763],"type":"Point"}
}