{
  "type": "Feature",
  "properties": {
    "iso:country":"US",
    "sg:address":"1710 Mountain Top Rd",
    "sg:city":"Bridgewater",
    "sg:classifiers":[
        {
            "category":"Building & Trades",
            "subcategory":"Construction",
            "type":"Services"
        }
    ],
    "sg:phone":"+1 908 725 3187",
    "sg:postcode":"08807",
    "sg:province":"NJ",
    "sg:tags":[
        "builder",
        "operative"
    ],
    "wof:name":"Ardmaer Construction Inc",
    "wof:placetype":"venue"
},
  "geometry": {"coordinates":[-74.595585,40.599339],"type":"Point"}
}