{
  "type": "Feature",
  "properties": {
    "addr:full":"57 Morris Tpke Randolph NJ 07869",
    "addr:housenumber":"57",
    "addr:postcode":"07869",
    "addr:street":"Morris Tpke",
    "iso:country":"US",
    "sg:address":"57 Morris Tpke",
    "sg:city":"Randolph",
    "sg:classifiers":[
        {
            "category":"Building & Trades",
            "subcategory":"Cleaning & Sanitation",
            "type":"Services"
        }
    ],
    "sg:phone":"+1 973 598 1900",
    "sg:postcode":"07869",
    "sg:province":"NJ",
    "sg:tags":[
        "house"
    ],
    "wof:name":"Accredited House Cleaning",
    "wof:placetype":"venue"
},
  "geometry": {"coordinates":[-74.603776,40.848648],"type":"Point"}
}