{
  "type": "Feature",
  "properties": {
    "addr:full":"250 12th Ave Paterson NJ 07514",
    "addr:housenumber":"250",
    "addr:postcode":"07514",
    "addr:street":"12Th Ave",
    "iso:country":"US",
    "sg:address":"250 12th Ave",
    "sg:city":"Paterson",
    "sg:classifiers":[
        {
            "category":"Freight",
            "type":"Transportation"
        }
    ],
    "sg:phone":"+1 973 279 4436",
    "sg:postcode":"07514",
    "sg:province":"NJ",
    "sg:tags":[
        "trucking"
    ],
    "wof:name":"Teacher Trucking Inc",
    "wof:placetype":"venue"
},
  "geometry": {"coordinates":[-74.154444,40.920652],"type":"Point"}
}