{
  "type": "Feature",
  "properties": {
    "iso:country":"US",
    "sg:address":"138 Spring Valley Rd",
    "sg:city":"Paramus",
    "sg:classifiers":[
        {
            "category":"Health Services",
            "subcategory":"Doctor",
            "type":"Services"
        }
    ],
    "sg:phone":"+1 201 967 8700",
    "sg:postcode":"07652",
    "sg:province":"NJ",
    "sg:tags":[
        "dentist"
    ],
    "wof:name":"Robert V Kinoian DMD",
    "wof:placetype":"venue"
},
  "geometry": {"coordinates":[-74.058477,40.926234],"type":"Point"}
}