{
  "type": "Feature",
  "properties": {
    "addr:full":"613 State Rte 15 Lake Hopatcong NJ 07849",
    "addr:housenumber":"613",
    "addr:postcode":"07849",
    "addr:street":"State Rte 15",
    "iso:country":"US",
    "sg:address":"613 State Rte 15",
    "sg:city":"Lake Hopatcong",
    "sg:classifiers":[
        {
            "category":"Professional",
            "subcategory":"Computer Services",
            "type":"Services"
        }
    ],
    "sg:phone":"+1   ",
    "sg:postcode":"07849",
    "sg:province":"NJ",
    "sg:tags":[
        "business"
    ],
    "sg:website":"www.ecs-cadcafm.com",
    "wof:name":"ECS Group Inc",
    "wof:placetype":"venue"
},
  "geometry": {"coordinates":[-74.59643800000001,40.952326],"type":"Point"}
}