{
  "type": "Feature",
  "properties": {
    "iso:country":"US",
    "sg:address":"12 Viburnum Dr",
    "sg:city":"Skillman",
    "sg:classifiers":[
        {
            "category":"Shopping",
            "subcategory":"Gifts & Souvenirs",
            "type":"Retail Goods"
        }
    ],
    "sg:phone":"+1   ",
    "sg:postcode":"08558",
    "sg:province":"NJ",
    "wof:name":"Design Concepts",
    "wof:placetype":"venue"
},
  "geometry": {"coordinates":[-74.740478,40.423358],"type":"Point"}
}