{
  "type": "Feature",
  "properties": {
    "iso:country":"US",
    "sg:address":"973 Ringwood Ave",
    "sg:city":"Haskell",
    "sg:classifiers":[
        {
            "category":"Education",
            "subcategory":"School",
            "type":"Public Place"
        }
    ],
    "sg:phone":"+1 973 835 8200",
    "sg:postcode":"07420",
    "sg:province":"NJ",
    "sg:website":"www.wanaque.k12.nj.us",
    "wof:name":"Haskell Elementary School",
    "wof:placetype":"venue"
},
  "geometry": {"coordinates":[-74.295394,41.033315],"type":"Point"}
}