{
  "type": "Feature",
  "properties": {
    "iso:country":"US",
    "sg:address":"2905 Tuskegee Airmen Ave",
    "sg:city":"Trenton",
    "sg:classifiers":[
        {
            "category":"Education",
            "subcategory":"Special Training",
            "type":"Public Place"
        }
    ],
    "sg:phone":"+1 609 754 4046",
    "sg:postcode":"08641",
    "sg:province":"NJ",
    "sg:tags":[
        "aircraft",
        "flight",
        "school"
    ],
    "sg:website":"http://www.af.mil",
    "wof:name":"Naf Accounting Office Mcguire",
    "wof:placetype":"venue"
},
  "geometry": {"coordinates":[-74.58167,40.037171],"type":"Point"}
}