{
  "type": "Feature",
  "properties": {
    "addr:full":"490 State Rte 27 Iselin NJ 08830",
    "addr:housenumber":"490",
    "addr:postcode":"08830",
    "addr:street":"State Rte 27",
    "iso:country":"US",
    "sg:address":"490 State Rte 27",
    "sg:city":"Iselin",
    "sg:classifiers":[
        {
            "category":"Restaurant",
            "type":"Food & Drink"
        }
    ],
    "sg:phone":"+1   ",
    "sg:postcode":"08830",
    "sg:province":"NJ",
    "sg:tags":[
        "eating"
    ],
    "wof:name":"Peggys",
    "wof:placetype":"venue"
},
  "geometry": {"coordinates":[-74.31851,40.575089],"type":"Point"}
}