{
  "type": "Feature",
  "properties": {
    "iso:country":"US",
    "sg:address":"53 Maine St",
    "sg:city":"Toms River",
    "sg:classifiers":[
        {
            "category":"Restaurant",
            "type":"Food & Drink"
        }
    ],
    "sg:phone":"+1 732 341 2611",
    "sg:postcode":"08753",
    "sg:province":"NJ",
    "wof:name":"Tommy's Restaurant",
    "wof:placetype":"venue"
},
  "geometry": {"coordinates":[-74.140608,40.010943],"type":"Point"}
}