{
  "type": "Feature",
  "properties": {
    "iso:country":"US",
    "sg:address":"417 Elmer St",
    "sg:city":"Trenton",
    "sg:classifiers":[
        {
            "category":"Building & Trades",
            "subcategory":"Construction",
            "type":"Services"
        }
    ],
    "sg:phone":"+1 609 396 8421",
    "sg:postcode":"08611",
    "sg:province":"NJ",
    "sg:tags":[
        "carpentry",
        "contractor"
    ],
    "wof:name":"James Lopez Construction",
    "wof:placetype":"venue"
},
  "geometry": {"coordinates":[-74.74749300000001,40.213231],"type":"Point"}
}