{
  "type": "Feature",
  "properties": {
    "iso:country":"US",
    "sg:address":"649 Lake St",
    "sg:city":"Newark",
    "sg:classifiers":[
        {
            "category":"Professional",
            "subcategory":"Management & Consulting",
            "type":"Services"
        }
    ],
    "sg:phone":"+1   ",
    "sg:postcode":"07104",
    "sg:province":"NJ",
    "wof:name":"BBC Associates LLC",
    "wof:placetype":"venue"
},
  "geometry": {"coordinates":[-74.17139899999999,40.774924],"type":"Point"}
}