{
  "type": "Feature",
  "properties": {
    "iso:country":"US",
    "sg:address":"2230 US Hwy 206",
    "sg:city":"Belle Mead",
    "sg:classifiers":[
        {
            "category":"Health Services",
            "subcategory":"Doctor",
            "type":"Services"
        }
    ],
    "sg:phone":"+1   ",
    "sg:postcode":"08502",
    "sg:province":"NJ",
    "sg:tags":[
        "dentist"
    ],
    "wof:name":"Harvey Tesser DDS PA",
    "wof:placetype":"venue"
},
  "geometry": {"coordinates":[-74.660011,40.454581],"type":"Point"}
}