{
  "type": "Feature",
  "properties": {
    "addr:full":"11 Baywood Dr Ocean View NJ 08230",
    "addr:housenumber":"11",
    "addr:postcode":"08230",
    "addr:street":"Baywood Dr",
    "iso:country":"US",
    "sg:address":"11 Baywood Dr",
    "sg:city":"Ocean View",
    "sg:classifiers":[
        {
            "category":"Building & Trades",
            "subcategory":"Construction",
            "type":"Services"
        }
    ],
    "sg:phone":"+1 609 624 9030",
    "sg:postcode":"08230",
    "sg:province":"NJ",
    "sg:tags":[
        "house",
        "carpentry",
        "contractor"
    ],
    "wof:name":"Charles Vallese Carpentry",
    "wof:placetype":"venue"
},
  "geometry": {"coordinates":[-74.736029,39.188082],"type":"Point"}
}