{
  "type": "Feature",
  "properties": {
    "addr:full":"1019 Sunny Slope Dr Mountainside NJ 07092",
    "addr:housenumber":"1019",
    "addr:postcode":"07092",
    "addr:street":"Sunny Slope Dr",
    "iso:country":"US",
    "sg:address":"1019 Sunny Slope Dr",
    "sg:city":"Mountainside",
    "sg:classifiers":[
        {
            "category":"Manufacturing",
            "subcategory":"Retail Goods",
            "type":"Manufacturing & Wholesale Goods"
        }
    ],
    "sg:phone":"+1 908 486 7600",
    "sg:postcode":"07092",
    "sg:province":"NJ",
    "sg:tags":[
        "product",
        "mfg"
    ],
    "wof:name":"Sealand Power Industries",
    "wof:placetype":"venue"
},
  "geometry": {"coordinates":[-74.35027599999999,40.692068],"type":"Point"}
}