{
  "type": "Feature",
  "properties": {
    "iso:country":"US",
    "sg:address":"392 Smith St",
    "sg:city":"Perth Amboy",
    "sg:classifiers":[
        {
            "category":"Shopping",
            "subcategory":"Clothing, Apparel, & Fashions",
            "type":"Retail Goods"
        }
    ],
    "sg:phone":"+1 732 376 9559",
    "sg:postcode":"08861",
    "sg:province":"NJ",
    "sg:tags":[
        "western"
    ],
    "wof:name":"Michoacan Inc",
    "wof:placetype":"venue"
},
  "geometry": {"coordinates":[-74.27981,40.511923],"type":"Point"}
}