{
  "type": "Feature",
  "properties": {
    "addr:full":"60 Sip Ave Jersey City NJ 07306",
    "addr:housenumber":"60",
    "addr:postcode":"07306",
    "addr:street":"Sip Ave",
    "iso:country":"US",
    "sg:address":"60 Sip Ave",
    "sg:city":"Jersey City",
    "sg:classifiers":[
        {
            "category":"Parking",
            "type":"Transportation"
        }
    ],
    "sg:phone":"+1 201 420 1201",
    "sg:postcode":"07306",
    "sg:province":"NJ",
    "sg:tags":[
        "garage",
        "automobile"
    ],
    "wof:name":"Sip Parking",
    "wof:placetype":"venue"
},
  "geometry": {"coordinates":[-74.06199599999999,40.730499],"type":"Point"}
}