{
  "type": "Feature",
  "properties": {
    "addr:full":"77 W Haledon Ave Haledon NJ 07508",
    "addr:housenumber":"77",
    "addr:postcode":"07508",
    "addr:street":"W Haledon Ave",
    "iso:country":"US",
    "sg:address":"77 W Haledon Ave",
    "sg:city":"Haledon",
    "sg:classifiers":[
        {
            "category":"Health Services",
            "subcategory":"Doctor",
            "type":"Services"
        }
    ],
    "sg:phone":"+1 973 790 1823",
    "sg:postcode":"07508",
    "sg:province":"NJ",
    "sg:tags":[
        "medical"
    ],
    "wof:name":"Richards Afonja MD",
    "wof:placetype":"venue"
},
  "geometry": {"coordinates":[-74.18794,40.939512],"type":"Point"}
}