{
  "type": "Feature",
  "properties": {
    "iso:country":"US",
    "sg:address":"20 Wildwood Dr",
    "sg:city":"Short Hills",
    "sg:classifiers":[
        {
            "category":"Building & Trades",
            "subcategory":"Construction",
            "type":"Services"
        }
    ],
    "sg:phone":"+1 973 467 0044",
    "sg:postcode":"07078",
    "sg:province":"NJ",
    "sg:tags":[
        "contractor"
    ],
    "wof:name":"Gallinson Building Corp",
    "wof:placetype":"venue"
},
  "geometry": {"coordinates":[-74.318562,40.747416],"type":"Point"}
}