{
  "type": "Feature",
  "properties": {
    "addr:full":"28 Grunauer Ave Saddle Brook NJ 07663",
    "addr:housenumber":"28",
    "addr:postcode":"07663",
    "addr:street":"Grunauer Ave",
    "iso:country":"US",
    "sg:address":"28 Grunauer Ave",
    "sg:city":"Saddle Brook",
    "sg:classifiers":[
        {
            "category":"Building & Trades",
            "subcategory":"Landscaping Services",
            "type":"Services"
        }
    ],
    "sg:phone":"+1 201 843 0758",
    "sg:postcode":"07663",
    "sg:province":"NJ",
    "sg:tags":[
        "landscape",
        "contractor"
    ],
    "wof:name":"Pickett Landscaping",
    "wof:placetype":"venue"
},
  "geometry": {"coordinates":[-74.082199,40.894886],"type":"Point"}
}