{
  "type": "Feature",
  "properties": {
    "iso:country":"US",
    "sg:address":"1943 US Hwy 9",
    "sg:city":"Cape May Ct Hse",
    "sg:classifiers":[
        {
            "category":"Shopping",
            "subcategory":"Gifts & Souvenirs",
            "type":"Retail Goods"
        }
    ],
    "sg:phone":"+1 609 624 7670",
    "sg:postcode":"08210",
    "sg:province":"NJ",
    "sg:tags":[
        "shop"
    ],
    "wof:name":"Nest",
    "wof:placetype":"venue"
},
  "geometry": {"coordinates":[-74.85751,39.037418],"type":"Point"}
}