{
  "type": "Feature",
  "properties": {
    "addr:full":"180 Ridgedale Ave Florham Park NJ 07932",
    "addr:housenumber":"180",
    "addr:postcode":"07932",
    "addr:street":"Ridgedale Ave",
    "iso:country":"US",
    "sg:address":"180 Ridgedale Ave",
    "sg:city":"Florham Park",
    "sg:classifiers":[
        {
            "category":"Restaurant",
            "type":"Food & Drink"
        }
    ],
    "sg:phone":"+1 973 966 1008",
    "sg:postcode":"07932",
    "sg:province":"NJ",
    "wof:name":"Park Place",
    "wof:placetype":"venue"
},
  "geometry": {"coordinates":[-74.3918,40.786499],"type":"Point"}
}