{
  "type": "Feature",
  "properties": {
    "iso:country":"US",
    "sg:address":"11 Bergen Ave",
    "sg:city":"Fair Lawn",
    "sg:classifiers":[
        {
            "category":"Building & Trades",
            "subcategory":"Electrical",
            "type":"Services"
        }
    ],
    "sg:phone":"+1 201 791 9217",
    "sg:postcode":"07410",
    "sg:province":"NJ",
    "sg:tags":[
        "electrical",
        "contractor"
    ],
    "wof:name":"All American Electrical Contg",
    "wof:placetype":"venue"
},
  "geometry": {"coordinates":[-74.132977,40.937095],"type":"Point"}
}