{
  "type": "Feature",
  "properties": {
    "addr:full":"13 Court St Newark NJ 07102",
    "addr:housenumber":"13",
    "addr:postcode":"07102",
    "addr:street":"Court St",
    "iso:country":"US",
    "sg:address":"13 Court St",
    "sg:city":"Newark",
    "sg:classifiers":[
        {
            "category":"Food & Beverages",
            "subcategory":"Bakery",
            "type":"Retail Goods"
        }
    ],
    "sg:phone":"+1 973 623 2259",
    "sg:postcode":"07102",
    "sg:province":"NJ",
    "sg:tags":[
        "donut",
        "coffee",
        "espresso",
        "doughnut",
        "restaurant"
    ],
    "sg:website":"http://www.dunkindonuts.com",
    "wof:name":"Dunkin' Donuts",
    "wof:placetype":"venue"
},
  "geometry": {"coordinates":[-74.175718,40.730932],"type":"Point"}
}