{
  "type": "Feature",
  "properties": {
    "iso:country":"US",
    "sg:address":"1300 E Elizabeth Ave",
    "sg:city":"Linden",
    "sg:classifiers":[
        {
            "category":"Professional",
            "subcategory":"Business Services",
            "type":"Services"
        }
    ],
    "sg:phone":"+1 908 587 9290",
    "sg:postcode":"07036",
    "sg:province":"NJ",
    "sg:tags":[
        "trade",
        "exposition",
        "fair",
        "show"
    ],
    "wof:name":"Monarch Pipe & Drape",
    "wof:placetype":"venue"
},
  "geometry": {"coordinates":[-74.23881,40.643522],"type":"Point"}
}