{
  "type": "Feature",
  "properties": {
    "addr:full":"141 S Harrison St East Orange NJ 07018",
    "addr:housenumber":"141",
    "addr:postcode":"07018",
    "addr:street":"S Harrison St",
    "iso:country":"US",
    "sg:address":"141 S Harrison St",
    "sg:city":"East Orange",
    "sg:classifiers":[
        {
            "category":"Building & Trades",
            "subcategory":"Locksmith",
            "type":"Services"
        }
    ],
    "sg:phone":"+1 973 854 5321",
    "sg:postcode":"07018",
    "sg:province":"NJ",
    "sg:tags":[
        "key"
    ],
    "wof:name":"0 1 All Day A Emergency Locksmith",
    "wof:placetype":"venue"
},
  "geometry": {"coordinates":[-74.22360399999999,40.763587],"type":"Point"}
}