{
  "type": "Feature",
  "properties": {
    "addr:full":"10 Tidswell Ave Medford NJ 08055",
    "addr:housenumber":"10",
    "addr:postcode":"08055",
    "addr:street":"Tidswell Ave",
    "iso:country":"US",
    "sg:address":"10 Tidswell Ave",
    "sg:city":"Medford",
    "sg:classifiers":[
        {
            "category":"Building & Trades",
            "subcategory":"Construction",
            "type":"Services"
        }
    ],
    "sg:phone":"+1 609 714 9992",
    "sg:postcode":"08055",
    "sg:province":"NJ",
    "sg:tags":[
        "carpentry",
        "general",
        "contractor"
    ],
    "wof:name":"Elite Contractors Inc",
    "wof:placetype":"venue"
},
  "geometry": {"coordinates":[-74.819149,39.901336],"type":"Point"}
}