{
  "type": "Feature",
  "properties": {
    "addr:full":"100 Riser Rd Little Ferry NJ 07643",
    "addr:housenumber":"100",
    "addr:postcode":"07643",
    "addr:street":"Riser Rd",
    "iso:country":"US",
    "sg:address":"100 Riser Rd",
    "sg:city":"Little Ferry",
    "sg:classifiers":[
        {
            "category":"Retail",
            "subcategory":"Repair Shop",
            "type":"Services"
        },
        {
            "category":"Wholesale",
            "subcategory":"Durable Goods & Equipment",
            "type":"Manufacturing & Wholesale Goods"
        }
    ],
    "sg:phone":"+1 201 440 4800",
    "sg:postcode":"07643",
    "sg:province":"NJ",
    "sg:tags":[
        "instrument",
        "aircraft",
        "mfg"
    ],
    "wof:name":"Midway Aircraft Instrument Co",
    "wof:placetype":"venue"
},
  "geometry": {"coordinates":[-74.053794,40.853752],"type":"Point"}
}