{
  "type": "Feature",
  "properties": {
    "addr:full":"105 Mountain Ave Summit NJ 07901",
    "addr:housenumber":"105",
    "addr:postcode":"07901",
    "addr:street":"Mountain Ave",
    "iso:country":"US",
    "sg:address":"105 Mountain Ave",
    "sg:city":"Summit",
    "sg:classifiers":[
        {
            "category":"Professional",
            "type":"Services"
        }
    ],
    "sg:phone":"+1 908 918 1818",
    "sg:postcode":"07901",
    "sg:province":"NJ",
    "sg:tags":[
        "establishment"
    ],
    "wof:name":"Group Against Smoking Plltn",
    "wof:placetype":"venue"
},
  "geometry": {"coordinates":[-74.36152199999999,40.70771],"type":"Point"}
}