{
  "type": "Feature",
  "properties": {
    "addr:full":"41 N Delsea Dr Vineland NJ 08360",
    "addr:housenumber":"41",
    "addr:postcode":"08360",
    "addr:street":"N Delsea Dr",
    "iso:country":"US",
    "sg:address":"41 N Delsea Dr",
    "sg:city":"Vineland",
    "sg:classifiers":[
        {
            "category":"Shopping",
            "subcategory":"Gifts & Souvenirs",
            "type":"Retail Goods"
        }
    ],
    "sg:phone":"+1   ",
    "sg:postcode":"08360",
    "sg:province":"NJ",
    "wof:name":"Gift Box",
    "wof:placetype":"venue"
},
  "geometry": {"coordinates":[-75.04297800000001,39.487287],"type":"Point"}
}