{
  "type": "Feature",
  "properties": {
    "iso:country":"US",
    "sg:address":"136 Central Ave",
    "sg:city":"Clark",
    "sg:classifiers":[
        {
            "category":"Professional",
            "subcategory":"Lawyer & Legal Services",
            "type":"Services"
        }
    ],
    "sg:phone":"+1 732 388 8600",
    "sg:postcode":"07066",
    "sg:province":"NJ",
    "sg:tags":[
        "attorney"
    ],
    "wof:name":"Daniel Silberstein PC",
    "wof:placetype":"venue"
},
  "geometry": {"coordinates":[-74.308886,40.629918],"type":"Point"}
}