{
  "type": "Feature",
  "properties": {
    "iso:country":"US",
    "sg:address":"14 Luppatatong Ave",
    "sg:city":"Keyport",
    "sg:classifiers":[
        {
            "category":"Social Services",
            "subcategory":"Child Care",
            "type":"Services"
        }
    ],
    "sg:phone":"+1 732 203 9766",
    "sg:postcode":"07735",
    "sg:province":"NJ",
    "sg:tags":[
        "day"
    ],
    "wof:name":"Miles Of Smiles",
    "wof:placetype":"venue"
},
  "geometry": {"coordinates":[-74.208079,40.433302],"type":"Point"}
}