{
  "type": "Feature",
  "properties": {
    "iso:country":"US",
    "sg:address":"319 Knickerbocker Ave",
    "sg:city":"Hillsdale",
    "sg:classifiers":[
        {
            "category":"Personal",
            "type":"Services"
        }
    ],
    "sg:phone":"+1   ",
    "sg:postcode":"07642",
    "sg:province":"NJ",
    "wof:name":"Designs To Deceive",
    "wof:placetype":"venue"
},
  "geometry": {"coordinates":[-74.04480599999999,41.00746],"type":"Point"}
}