{
  "type": "Feature",
  "properties": {
    "addr:full":"1259 US Hwy 46 Parsippany NJ 07054",
    "addr:housenumber":"1259",
    "addr:postcode":"07054",
    "addr:street":"Us Hwy 46",
    "iso:country":"US",
    "sg:address":"1259 US Hwy 46",
    "sg:city":"Parsippany",
    "sg:classifiers":[
        {
            "category":"Building & Trades",
            "subcategory":"Pest Control",
            "type":"Services"
        }
    ],
    "sg:phone":"+1 973 335 9797",
    "sg:postcode":"07054",
    "sg:province":"NJ",
    "wof:name":"Terminix International Co",
    "wof:placetype":"venue"
},
  "geometry": {"coordinates":[-74.38668800000001,40.862899],"type":"Point"}
}