{
  "type": "Feature",
  "properties": {
    "addr:full":"154 Henderson Pl Hightstown NJ 08520",
    "addr:housenumber":"154",
    "addr:postcode":"08520",
    "addr:street":"Henderson Pl",
    "iso:country":"US",
    "sg:address":"154 Henderson Pl",
    "sg:city":"Hightstown",
    "sg:classifiers":[
        {
            "category":"Professional",
            "subcategory":"Lawyer & Legal Services",
            "type":"Services"
        }
    ],
    "sg:phone":"+1 609 443 1343",
    "sg:postcode":"08520",
    "sg:province":"NJ",
    "wof:name":"Curtis A Woods & Assoc",
    "wof:placetype":"venue"
},
  "geometry": {"coordinates":[-74.484842,40.257895],"type":"Point"}
}