{
  "type": "Feature",
  "properties": {
    "iso:country":"US",
    "sg:address":"101 Carl Ave",
    "sg:city":"Monroeville",
    "sg:classifiers":[
        {
            "category":"Building & Trades",
            "subcategory":"Construction",
            "type":"Services"
        }
    ],
    "sg:phone":"+1 856 881 4661",
    "sg:postcode":"08343",
    "sg:province":"NJ",
    "sg:tags":[
        "painter"
    ],
    "wof:name":"Danenhower Painting",
    "wof:placetype":"venue"
},
  "geometry": {"coordinates":[-75.12133799999999,39.653909],"type":"Point"}
}