{
  "type": "Feature",
  "properties": {
    "iso:country":"US",
    "sg:address":"64 Grant Ave",
    "sg:city":"Carteret",
    "sg:classifiers":[
        {
            "category":"Freight",
            "type":"Transportation"
        },
        {
            "category":"Building & Trades",
            "subcategory":"Plumbing",
            "type":"Services"
        }
    ],
    "sg:phone":"+1 732 802 9113",
    "sg:postcode":"07008",
    "sg:province":"NJ",
    "sg:tags":[
        "courier",
        "contractor"
    ],
    "wof:name":"A C Logistics Inc",
    "wof:placetype":"venue"
},
  "geometry": {"coordinates":[-74.223838,40.586779],"type":"Point"}
}