{
  "type": "Feature",
  "properties": {
    "addr:full":"248 Washington St Toms River NJ 08753",
    "addr:housenumber":"248",
    "addr:postcode":"08753",
    "addr:street":"Washington St",
    "iso:country":"US",
    "sg:address":"248 Washington St",
    "sg:city":"Toms River",
    "sg:classifiers":[
        {
            "category":"Real Estate",
            "subcategory":"Real Estate Operator",
            "type":"Services"
        }
    ],
    "sg:phone":"+1   ",
    "sg:postcode":"08753",
    "sg:province":"NJ",
    "sg:tags":[
        "building",
        "nonresidential"
    ],
    "wof:name":"Citta & Fetter Inc",
    "wof:placetype":"venue"
},
  "geometry": {"coordinates":[-74.189865,39.952186],"type":"Point"}
}