{
  "type": "Feature",
  "properties": {
    "iso:country":"US",
    "sg:address":"50 Newark Ave",
    "sg:city":"Belleville",
    "sg:classifiers":[
        {
            "category":"Government",
            "subcategory":"Office",
            "type":"Public Place"
        }
    ],
    "sg:phone":"+1 973 450 3392",
    "sg:postcode":"07109",
    "sg:province":"NJ",
    "sg:tags":[
        "village"
    ],
    "wof:name":"Belleville Child Health",
    "wof:placetype":"venue"
},
  "geometry": {"coordinates":[-74.17866600000001,40.784502],"type":"Point"}
}