{
  "type": "Feature",
  "properties": {
    "addr:full":"197 Smith St Perth Amboy NJ 08861",
    "addr:housenumber":"197",
    "addr:postcode":"08861",
    "addr:street":"Smith St",
    "iso:country":"US",
    "sg:address":"197 Smith St",
    "sg:city":"Perth Amboy",
    "sg:classifiers":[
        {
            "category":"Banks & Credit Unions",
            "subcategory":"Bank",
            "type":"Services"
        }
    ],
    "sg:phone":"+1 732 293 1555",
    "sg:postcode":"08861",
    "sg:province":"NJ",
    "sg:tags":[
        "money",
        "order"
    ],
    "wof:name":"Grone Express Svc",
    "wof:placetype":"venue"
},
  "geometry": {"coordinates":[-74.271731,40.509531],"type":"Point"}
}