{
  "type": "Feature",
  "properties": {
    "addr:full":"228 Godwin Ave Midland Park NJ 07432",
    "addr:housenumber":"228",
    "addr:postcode":"07432",
    "addr:street":"Godwin Ave",
    "iso:country":"US",
    "sg:address":"228 Godwin Ave",
    "sg:city":"Midland Park",
    "sg:classifiers":[
        {
            "category":"Shopping",
            "subcategory":"Used Merchandise",
            "type":"Retail Goods"
        }
    ],
    "sg:phone":"+1 201 652 2814",
    "sg:postcode":"07432",
    "sg:province":"NJ",
    "sg:tags":[
        "shop",
        "consignment"
    ],
    "wof:name":"Gingerbread Man Consignment Sp",
    "wof:placetype":"venue"
},
  "geometry": {"coordinates":[-74.140142,40.987863],"type":"Point"}
}