{
  "type": "Feature",
  "properties": {
    "addr:full":"758 Main St Paterson NJ 07503",
    "addr:housenumber":"758",
    "addr:postcode":"07503",
    "addr:street":"Main St",
    "iso:country":"US",
    "sg:address":"758 Main St",
    "sg:city":"Paterson",
    "sg:classifiers":[
        {
            "category":"Insurance",
            "subcategory":"Hazard Insurance",
            "type":"Services"
        }
    ],
    "sg:phone":"+1 973 977 8331",
    "sg:postcode":"07503",
    "sg:province":"NJ",
    "sg:website":"www.royaleins.com",
    "wof:name":"Royale Insurance Agency",
    "wof:placetype":"venue"
},
  "geometry": {"coordinates":[-74.16536600000001,40.900742],"type":"Point"}
}