{
  "type": "Feature",
  "properties": {
    "addr:full":"505 Hamilton Ave Linwood NJ 08221",
    "addr:housenumber":"505",
    "addr:postcode":"08221",
    "addr:street":"Hamilton Ave",
    "iso:country":"US",
    "sg:address":"505 Hamilton Ave",
    "sg:city":"Linwood",
    "sg:classifiers":[
        {
            "category":"Banks & Credit Unions",
            "subcategory":"Investment Brokerage",
            "type":"Services"
        }
    ],
    "sg:phone":"+1 609 927 3586",
    "sg:postcode":"08221",
    "sg:province":"NJ",
    "sg:tags":[
        "advisory",
        "financial"
    ],
    "wof:name":"Wayne & Nancy Bell Pfs",
    "wof:placetype":"venue"
},
  "geometry": {"coordinates":[-74.586737,39.343429],"type":"Point"}
}