{
  "type": "Feature",
  "properties": {
    "iso:country":"US",
    "sg:address":"96 Powerville Rd",
    "sg:city":"Mountain Lakes",
    "sg:classifiers":[
        {
            "category":"Education",
            "subcategory":"School",
            "type":"Public Place"
        }
    ],
    "sg:phone":"+1 973 334 8400",
    "sg:postcode":"07046",
    "sg:province":"NJ",
    "sg:tags":[
        "high",
        "middle"
    ],
    "wof:name":"Mountain Lks Borough of-Public Schools High School",
    "wof:placetype":"venue"
},
  "geometry": {"coordinates":[-74.425201,40.892399],"type":"Point"}
}