{
  "type": "Feature",
  "properties": {
    "iso:country":"US",
    "sg:address":"30 Two Bridges Rd",
    "sg:city":"Fairfield",
    "sg:classifiers":[
        {
            "category":"Wholesale",
            "subcategory":"Drugs",
            "type":"Manufacturing & Wholesale Goods"
        }
    ],
    "sg:phone":"+1 973 882 5733",
    "sg:postcode":"07004",
    "sg:province":"NJ",
    "sg:tags":[
        "pharmaceutical"
    ],
    "wof:name":"Allergan",
    "wof:placetype":"venue"
},
  "geometry": {"coordinates":[-74.27382,40.891808],"type":"Point"}
}