{
  "type": "Feature",
  "properties": {
    "iso:country":"US",
    "sg:address":"133 Niagara St",
    "sg:city":"Newark",
    "sg:classifiers":[
        {
            "category":"Retail",
            "subcategory":"Funeral Services",
            "type":"Services"
        }
    ],
    "sg:phone":"+1 973 344 1508",
    "sg:postcode":"07105",
    "sg:province":"NJ",
    "sg:tags":[
        "cemetery"
    ],
    "wof:name":"Bernauer Funeral Home",
    "wof:placetype":"venue"
},
  "geometry": {"coordinates":[-74.148499,40.7243],"type":"Point"}
}