{
  "type": "Feature",
  "properties": {
    "iso:country":"US",
    "sg:address":"604 Cherokee Ln",
    "sg:city":"Brielle",
    "sg:classifiers":[
        {
            "category":"Retail",
            "subcategory":"Car Wash",
            "type":"Services"
        }
    ],
    "sg:phone":"+1   ",
    "sg:postcode":"08730",
    "sg:province":"NJ",
    "sg:tags":[
        "carwash"
    ],
    "wof:name":"Marlton Clssc Car Wash",
    "wof:placetype":"venue"
},
  "geometry": {"coordinates":[-74.060879,40.106606],"type":"Point"}
}