{
  "type": "Feature",
  "properties": {
    "addr:full":"95 N Washington Ave Bergenfield NJ 07621",
    "addr:housenumber":"95",
    "addr:postcode":"07621",
    "addr:street":"N Washington Ave",
    "iso:country":"US",
    "sg:address":"95 N Washington Ave",
    "sg:city":"Bergenfield",
    "sg:classifiers":[
        {
            "category":"Banks & Credit Unions",
            "subcategory":"Bank",
            "type":"Services"
        }
    ],
    "sg:phone":"+1   ",
    "sg:postcode":"07621",
    "sg:province":"NJ",
    "sg:tags":[
        "state",
        "commercial"
    ],
    "wof:name":"Hudson United Bank",
    "wof:placetype":"venue"
},
  "geometry": {"coordinates":[-73.99558,40.930287],"type":"Point"}
}