{
  "type": "Feature",
  "properties": {
    "addr:full":"305 Passaic St Passaic NJ 07055",
    "addr:housenumber":"305",
    "addr:postcode":"07055",
    "addr:street":"Passaic St",
    "iso:country":"US",
    "sg:address":"305 Passaic St",
    "sg:city":"Passaic",
    "sg:classifiers":[
        {
            "category":"Insurance",
            "subcategory":"Hazard Insurance",
            "type":"Services"
        }
    ],
    "sg:phone":"+1 973 473 0371",
    "sg:postcode":"07055",
    "sg:province":"NJ",
    "sg:tags":[
        "bond"
    ],
    "wof:name":"Carl Ellen Bailbonding Agency",
    "wof:placetype":"venue"
},
  "geometry": {"coordinates":[-74.12130000000001,40.86145],"type":"Point"}
}