{
  "type": "Feature",
  "properties": {
    "iso:country":"US",
    "sg:address":"101 High St",
    "sg:city":"Randolph",
    "sg:classifiers":[
        {
            "category":"Building & Trades",
            "subcategory":"Construction",
            "type":"Services"
        }
    ],
    "sg:phone":"+1 973 361 4750",
    "sg:postcode":"07869",
    "sg:province":"NJ",
    "sg:tags":[
        "contractor"
    ],
    "wof:name":"Falcone Masonry",
    "wof:placetype":"venue"
},
  "geometry": {"coordinates":[-74.553657,40.864611],"type":"Point"}
}