{
  "type": "Feature",
  "properties": {
    "iso:country":"US",
    "sg:address":"178 Ogden Ave",
    "sg:city":"Jersey City",
    "sg:classifiers":[
        {
            "category":"Health Services",
            "subcategory":"Nursing And Care Facility",
            "type":"Services"
        }
    ],
    "sg:phone":"+1 201 963 1800",
    "sg:postcode":"07307",
    "sg:province":"NJ",
    "sg:tags":[
        "home",
        "convalescent"
    ],
    "wof:name":"Harbor View Health Care Center",
    "wof:placetype":"venue"
},
  "geometry": {"coordinates":[-74.04682699999999,40.738482],"type":"Point"}
}