{
  "type": "Feature",
  "properties": {
    "iso:country":"US",
    "sg:address":"502 Millbrook Ave",
    "sg:city":"Randolph",
    "sg:classifiers":[
        {
            "category":"Local Transit",
            "type":"Transportation"
        }
    ],
    "sg:phone":"+1 973 366 9964",
    "sg:postcode":"07869",
    "sg:province":"NJ",
    "sg:tags":[
        "ambulance"
    ],
    "wof:name":"Atlantic Ambulance Corp",
    "wof:placetype":"venue"
},
  "geometry": {"coordinates":[-74.563022,40.847126],"type":"Point"}
}