{
  "type": "Feature",
  "properties": {
    "iso:country":"US",
    "sg:address":"598 Main St",
    "sg:city":"East Orange",
    "sg:classifiers":[
        {
            "category":"Food & Beverages",
            "subcategory":"Groceries & Convenience Stores",
            "type":"Retail Goods"
        }
    ],
    "sg:phone":"+1 973 675 6100",
    "sg:postcode":"07018",
    "sg:province":"NJ",
    "sg:tags":[
        "grocer"
    ],
    "wof:name":"Aubon Marche",
    "wof:placetype":"venue"
},
  "geometry": {"coordinates":[-74.22,40.76763],"type":"Point"}
}