{
  "type": "Feature",
  "properties": {
    "addr:full":"304 Grove St Jersey City NJ 07302",
    "addr:housenumber":"304",
    "addr:postcode":"07302",
    "addr:street":"Grove St",
    "iso:country":"US",
    "sg:address":"304 Grove St",
    "sg:city":"Jersey City",
    "sg:classifiers":[
        {
            "category":"Real Estate",
            "subcategory":"Real Estate Agent",
            "type":"Services"
        }
    ],
    "sg:phone":"+1 201 923 1061",
    "sg:postcode":"07302",
    "sg:province":"NJ",
    "sg:website":"www.jerseyhomes.com",
    "wof:name":"Jersey Homes Reality",
    "wof:placetype":"venue"
},
  "geometry": {"coordinates":[-74.043346,40.718851],"type":"Point"}
}