{
  "type": "Feature",
  "properties": {
    "iso:country":"US",
    "sg:address":"40 Broad Ave",
    "sg:city":"Palisades Park",
    "sg:classifiers":[
        {
            "category":"Personal",
            "subcategory":"Beauty Salon",
            "type":"Services"
        }
    ],
    "sg:phone":"+1 201 943 7783",
    "sg:postcode":"07650",
    "sg:province":"NJ",
    "sg:tags":[
        "school"
    ],
    "wof:name":"Onix Body Therapy Academy",
    "wof:placetype":"venue"
},
  "geometry": {"coordinates":[-74.001147,40.843047],"type":"Point"}
}