{
  "type": "Feature",
  "properties": {
    "addr:full":"1671 Beaver Dam Rd Pt Pleasant Bch NJ 08742",
    "addr:housenumber":"1671",
    "addr:postcode":"08742",
    "addr:street":"Beaver Dam Rd Pt",
    "iso:country":"US",
    "sg:address":"1671 Beaver Dam Rd",
    "sg:city":"Pt Pleasant Bch",
    "sg:classifiers":[
        {
            "category":"Real Estate",
            "subcategory":"Real Estate Agent",
            "type":"Services"
        },
        {
            "category":"Retail",
            "subcategory":"Repair Shop",
            "type":"Services"
        }
    ],
    "sg:phone":"+1 732 899 4444",
    "sg:postcode":"08742",
    "sg:province":"NJ",
    "sg:tags":[
        "manager",
        "welding"
    ],
    "wof:name":"Ocean Towers and Welding",
    "wof:placetype":"venue"
},
  "geometry": {"coordinates":[-74.07244900000001,40.062858],"type":"Point"}
}