{
  "type": "Feature",
  "properties": {
    "addr:full":"3561 Coles Mill Rd Franklinville NJ 08322",
    "addr:housenumber":"3561",
    "addr:postcode":"08322",
    "addr:street":"Coles Mill Rd",
    "iso:country":"US",
    "sg:address":"3561 Coles Mill Rd",
    "sg:city":"Franklinville",
    "sg:classifiers":[
        {
            "category":"Building & Trades",
            "subcategory":"Pest Control",
            "type":"Services"
        }
    ],
    "sg:phone":"+1   ",
    "sg:postcode":"08322",
    "sg:province":"NJ",
    "wof:name":"Exterminating By Ross Inc",
    "wof:placetype":"venue"
},
  "geometry": {"coordinates":[-75.003033,39.619826],"type":"Point"}
}