{
  "type": "Feature",
  "properties": {
    "addr:full":"139 Van Dam Ave Bloomingdale NJ 07403",
    "addr:housenumber":"139",
    "addr:postcode":"07403",
    "addr:street":"Van Dam Ave",
    "iso:country":"US",
    "sg:address":"139 Van Dam Ave",
    "sg:city":"Bloomingdale",
    "sg:classifiers":[
        {
            "category":"Retail",
            "subcategory":"Auto Repair",
            "type":"Services"
        }
    ],
    "sg:phone":"+1 973 283 8840",
    "sg:postcode":"07403",
    "sg:province":"NJ",
    "wof:name":"Auto Tech",
    "wof:placetype":"venue"
},
  "geometry": {"coordinates":[-74.320295,41.009545],"type":"Point"}
}