{
  "type": "Feature",
  "properties": {
    "iso:country":"US",
    "sg:address":"7 Wenatchee Rd",
    "sg:city":"Highland Lakes",
    "sg:classifiers":[
        {
            "category":"Utilities",
            "subcategory":"Refuse",
            "type":"Services"
        }
    ],
    "sg:phone":"+1 973 764 2227",
    "sg:postcode":"07422",
    "sg:province":"NJ",
    "sg:tags":[
        "garbage",
        "collection"
    ],
    "wof:name":"Absolute Best Bears",
    "wof:placetype":"venue"
},
  "geometry": {"coordinates":[-74.465526,41.184398],"type":"Point"}
}