{
  "type": "Feature",
  "properties": {
    "addr:full":"199 Hardwick St Belvidere NJ 07823",
    "addr:housenumber":"199",
    "addr:postcode":"07823",
    "addr:street":"Hardwick St",
    "iso:country":"US",
    "sg:address":"199 Hardwick St",
    "sg:city":"Belvidere",
    "sg:classifiers":[
        {
            "category":"Education",
            "subcategory":"Library",
            "type":"Public Place"
        }
    ],
    "sg:phone":"+1   ",
    "sg:postcode":"07823",
    "sg:province":"NJ",
    "sg:website":"www.warrenlib.com",
    "wof:name":"Warren County Library",
    "wof:placetype":"venue"
},
  "geometry": {"coordinates":[-75.07565099999999,40.827951],"type":"Point"}
}