{
  "type": "Feature",
  "properties": {
    "addr:full":"52 Chamberlain Dr Hillsborough NJ 08844",
    "addr:housenumber":"52",
    "addr:postcode":"08844",
    "addr:street":"Chamberlain Dr",
    "iso:country":"US",
    "sg:address":"52 Chamberlain Dr",
    "sg:city":"Hillsborough",
    "sg:classifiers":[
        {
            "category":"Professional",
            "subcategory":"Management & Consulting",
            "type":"Services"
        },
        {
            "category":"Professional",
            "subcategory":"Computer Services",
            "type":"Services"
        }
    ],
    "sg:phone":"+1 908 369 8787",
    "sg:postcode":"08844",
    "sg:province":"NJ",
    "sg:tags":[
        "consultant",
        "designer",
        "datum",
        "system",
        "business"
    ],
    "wof:name":"Lifetimes Partners Inc",
    "wof:placetype":"venue"
},
  "geometry": {"coordinates":[-74.68012299999999,40.541858],"type":"Point"}
}