{
  "type": "Feature",
  "properties": {
    "iso:country":"US",
    "sg:address":"6 Main St",
    "sg:city":"Madison",
    "sg:classifiers":[
        {
            "category":"Building & Trades",
            "subcategory":"Electrical",
            "type":"Services"
        }
    ],
    "sg:phone":"+1 973 822 2828",
    "sg:postcode":"07940",
    "sg:province":"NJ",
    "sg:tags":[
        "electrical",
        "contractor"
    ],
    "wof:name":"Chatham Elc & Communications",
    "wof:placetype":"venue"
},
  "geometry": {"coordinates":[-74.416388,40.759688],"type":"Point"}
}