{
  "type": "Feature",
  "properties": {
    "iso:country":"US",
    "sg:address":"652 Rifle Camp Rd",
    "sg:city":"Little Falls",
    "sg:classifiers":[
        {
            "category":"Retail",
            "subcategory":"Laundry & Dry Cleaning",
            "type":"Services"
        }
    ],
    "sg:phone":"+1 973 785 1077",
    "sg:postcode":"07424",
    "sg:province":"NJ",
    "sg:tags":[
        "drycleaning",
        "plant"
    ],
    "wof:name":"Scalice Cleaners",
    "wof:placetype":"venue"
},
  "geometry": {"coordinates":[-74.193174,40.882099],"type":"Point"}
}