{
  "type": "Feature",
  "properties": {
    "iso:country":"US",
    "sg:address":"48 River Rd",
    "sg:city":"Chatham",
    "sg:classifiers":[
        {
            "category":"Food & Beverages",
            "subcategory":"Specialty",
            "type":"Retail Goods"
        }
    ],
    "sg:phone":"+1 973 701 1184",
    "sg:postcode":"07928",
    "sg:province":"NJ",
    "sg:tags":[
        "health",
        "market",
        "diet"
    ],
    "wof:name":"Hi-Life Vitamin & Herb Co",
    "wof:placetype":"venue"
},
  "geometry": {"coordinates":[-74.384122,40.72765],"type":"Point"}
}