{
  "type": "Feature",
  "properties": {
    "iso:country":"US",
    "sg:address":"150 Raritan Center Pkwy",
    "sg:city":"Edison",
    "sg:classifiers":[
        {
            "category":"Freight",
            "type":"Transportation"
        }
    ],
    "sg:phone":"+1 732 225 8670",
    "sg:postcode":"08837",
    "sg:province":"NJ",
    "wof:name":"Expeditors International",
    "wof:placetype":"venue"
},
  "geometry": {"coordinates":[-74.33948599999999,40.515856],"type":"Point"}
}