{
  "type": "Feature",
  "properties": {
    "addr:full":"124 E Main St Maple Shade NJ 08052",
    "addr:housenumber":"124",
    "addr:postcode":"08052",
    "addr:street":"E Main St",
    "iso:country":"US",
    "sg:address":"124 E Main St",
    "sg:city":"Maple Shade",
    "sg:classifiers":[
        {
            "category":"Banks & Credit Unions",
            "subcategory":"Bank",
            "type":"Services"
        }
    ],
    "sg:phone":"+1   ",
    "sg:postcode":"08052",
    "sg:province":"NJ",
    "sg:tags":[
        "state",
        "commercial"
    ],
    "wof:name":"Sterling Bank",
    "wof:placetype":"venue"
},
  "geometry": {"coordinates":[-74.99902299999999,39.95565],"type":"Point"}
}