{
  "type": "Feature",
  "properties": {
    "iso:country":"US",
    "sg:address":"59 Oxbow Pl",
    "sg:city":"Wayne",
    "sg:classifiers":[
        {
            "category":"Manufacturing",
            "subcategory":"Wood Products",
            "type":"Manufacturing & Wholesale Goods"
        }
    ],
    "sg:phone":"+1 973 904 0022",
    "sg:postcode":"07470",
    "sg:province":"NJ",
    "sg:tags":[
        "picture",
        "frame"
    ],
    "wof:name":"Howard Packaging Corp",
    "wof:placetype":"venue"
},
  "geometry": {"coordinates":[-74.217827,40.946153],"type":"Point"}
}