{
  "type": "Feature",
  "properties": {
    "addr:full":"945 Rahway Ave Union NJ 07083",
    "addr:housenumber":"945",
    "addr:postcode":"07083",
    "addr:street":"Rahway Ave",
    "iso:country":"US",
    "sg:address":"945 Rahway Ave",
    "sg:city":"Union",
    "sg:classifiers":[
        {
            "category":"Building & Trades",
            "subcategory":"Construction",
            "type":"Services"
        },
        {
            "category":"Home & Garden",
            "subcategory":"Furniture",
            "type":"Retail Goods"
        }
    ],
    "sg:phone":"+1 908 810 0665",
    "sg:postcode":"07083",
    "sg:province":"NJ",
    "sg:tags":[
        "cabinet",
        "contractor",
        "maker",
        "carpentry"
    ],
    "sg:website":"www.fullscalewoodworking.com",
    "wof:name":"Full Scale Woodworking Inc",
    "wof:placetype":"venue"
},
  "geometry": {"coordinates":[-74.285608,40.699275],"type":"Point"}
}