{
  "type": "Feature",
  "properties": {
    "addr:full":"707 Alexander Rd Princeton NJ 08540",
    "addr:housenumber":"707",
    "addr:postcode":"08540",
    "addr:street":"Alexander Rd",
    "iso:country":"US",
    "sg:address":"707 Alexander Rd",
    "sg:city":"Princeton",
    "sg:classifiers":[
        {
            "category":"Health Services",
            "subcategory":"Doctor",
            "type":"Services"
        }
    ],
    "sg:phone":"+1 609 419 0400",
    "sg:postcode":"08540",
    "sg:province":"NJ",
    "sg:tags":[
        "physician",
        "surgeon"
    ],
    "wof:name":"Alexander Road Assoc",
    "wof:placetype":"venue"
},
  "geometry": {"coordinates":[-74.637171,40.321417],"type":"Point"}
}