{
  "type": "Feature",
  "properties": {
    "iso:country":"US",
    "sg:address":"68 Tuers Ave",
    "sg:city":"Jersey City",
    "sg:classifiers":[
        {
            "category":"Building & Trades",
            "subcategory":"Construction",
            "type":"Services"
        }
    ],
    "sg:phone":"+1 201 434 3425",
    "sg:postcode":"07306",
    "sg:province":"NJ",
    "sg:tags":[
        "house"
    ],
    "wof:name":"Valley Const",
    "wof:placetype":"venue"
},
  "geometry": {"coordinates":[-74.06598,40.726375],"type":"Point"}
}