{
  "type": "Feature",
  "properties": {
    "addr:full":"580 Palisade Ave Cliffside Park NJ 07010",
    "addr:housenumber":"580",
    "addr:postcode":"07010",
    "addr:street":"Palisade Ave",
    "iso:country":"US",
    "sg:address":"580 Palisade Ave",
    "sg:city":"Cliffside Park",
    "sg:classifiers":[
        {
            "category":"Health Services",
            "subcategory":"Doctor",
            "type":"Services"
        }
    ],
    "sg:phone":"+1 201 943 2244",
    "sg:postcode":"07010",
    "sg:province":"NJ",
    "sg:tags":[
        "physician",
        "surgeon"
    ],
    "wof:name":"A William Pingpang MD",
    "wof:placetype":"venue"
},
  "geometry": {"coordinates":[-73.986305,40.821942],"type":"Point"}
}