{
  "type": "Feature",
  "properties": {
    "addr:full":"6656 Black Horse Pike Egg Harbor Township NJ 08234",
    "addr:housenumber":"6656",
    "addr:postcode":"08234",
    "addr:street":"Black Horse Pike",
    "iso:country":"US",
    "sg:address":"6656 Black Horse Pike",
    "sg:city":"Egg Harbor Township",
    "sg:classifiers":[
        {
            "category":"Shopping",
            "subcategory":"Gifts & Souvenirs",
            "type":"Retail Goods"
        }
    ],
    "sg:phone":"+1   ",
    "sg:postcode":"08234",
    "sg:province":"NJ",
    "sg:tags":[
        "merchandise"
    ],
    "wof:name":"Tracys Candles N More",
    "wof:placetype":"venue"
},
  "geometry": {"coordinates":[-74.57394499999999,39.413385],"type":"Point"}
}