{
  "type": "Feature",
  "properties": {
    "addr:full":"630 South St Elizabeth NJ 07202",
    "addr:housenumber":"630",
    "addr:postcode":"07202",
    "addr:street":"South St",
    "iso:country":"US",
    "sg:address":"630 South St",
    "sg:city":"Elizabeth",
    "sg:classifiers":[
        {
            "category":"Social Services",
            "subcategory":"Child Care",
            "type":"Services"
        }
    ],
    "sg:phone":"+1   ",
    "sg:postcode":"07202",
    "sg:province":"NJ",
    "sg:tags":[
        "day"
    ],
    "wof:name":"Center For Infant Development",
    "wof:placetype":"venue"
},
  "geometry": {"coordinates":[-74.211489,40.658047],"type":"Point"}
}