{
  "type": "Feature",
  "properties": {
    "iso:country":"US",
    "sg:address":"60 Railroad Ave",
    "sg:city":"Hasbrouck Heights",
    "sg:classifiers":[
        {
            "category":"Autos & Motor Vehicles",
            "subcategory":"Automobile Sales",
            "type":"Retail Goods"
        }
    ],
    "sg:phone":"+1 201 288 9300",
    "sg:postcode":"07604",
    "sg:province":"NJ",
    "sg:tags":[
        "car"
    ],
    "wof:name":"Auto Finder's",
    "wof:placetype":"venue"
},
  "geometry": {"coordinates":[-74.073601,40.850399],"type":"Point"}
}