{
  "type": "Feature",
  "properties": {
    "addr:full":"2 North St Waldwick NJ 07463",
    "addr:housenumber":"2",
    "addr:postcode":"07463",
    "addr:street":"North St",
    "iso:country":"US",
    "sg:address":"2 North St",
    "sg:city":"Waldwick",
    "sg:classifiers":[
        {
            "category":"Real Estate",
            "subcategory":"Real Estate Operator",
            "type":"Services"
        }
    ],
    "sg:phone":"+1   ",
    "sg:postcode":"07463",
    "sg:province":"NJ",
    "sg:tags":[
        "manager",
        "property",
        "commercial"
    ],
    "wof:name":"Riverdale High Tech Associates",
    "wof:placetype":"venue"
},
  "geometry": {"coordinates":[-74.121813,41.017033],"type":"Point"}
}