{
  "type": "Feature",
  "properties": {
    "addr:full":"81 S Orange Ave South Orange NJ 07079",
    "addr:housenumber":"81",
    "addr:postcode":"07079",
    "addr:street":"S Orange Ave",
    "iso:country":"US",
    "sg:address":"81 S Orange Ave",
    "sg:city":"South Orange",
    "sg:classifiers":[
        {
            "category":"Health Services",
            "subcategory":"Health Practitioner",
            "type":"Services"
        }
    ],
    "sg:phone":"+1 973 761 0400",
    "sg:postcode":"07079",
    "sg:province":"NJ",
    "wof:name":"Skin Care Plus",
    "wof:placetype":"venue"
},
  "geometry": {"coordinates":[-74.25825500000001,40.745911],"type":"Point"}
}