{
  "type": "Feature",
  "properties": {
    "addr:full":"124 S Main St Lodi NJ 07644",
    "addr:housenumber":"124",
    "addr:postcode":"07644",
    "addr:street":"S Main St",
    "iso:country":"US",
    "sg:address":"124 S Main St",
    "sg:city":"Lodi",
    "sg:classifiers":[
        {
            "category":"Food & Beverages",
            "subcategory":"Liquor & Beverages",
            "type":"Retail Goods"
        },
        {
            "category":"Food & Beverages",
            "subcategory":"Groceries & Convenience Stores",
            "type":"Retail Goods"
        }
    ],
    "sg:phone":"+1 973 778 5775",
    "sg:postcode":"07644",
    "sg:province":"NJ",
    "sg:tags":[
        "beer",
        "spirit",
        "wine"
    ],
    "wof:name":"Rizzo's Delicatessen",
    "wof:placetype":"venue"
},
  "geometry": {"coordinates":[-74.08899700000001,40.869801],"type":"Point"}
}