{
  "type": "Feature",
  "properties": {
    "addr:full":"58 Shongum Rd Randolph NJ 07869",
    "addr:housenumber":"58",
    "addr:postcode":"07869",
    "addr:street":"Shongum Rd",
    "iso:country":"US",
    "sg:address":"58 Shongum Rd",
    "sg:city":"Randolph",
    "sg:classifiers":[
        {
            "category":"Wholesale",
            "subcategory":"Stationery",
            "type":"Manufacturing & Wholesale Goods"
        }
    ],
    "sg:phone":"+1 973 361 0049",
    "sg:postcode":"07869",
    "sg:province":"NJ",
    "sg:tags":[
        "supply"
    ],
    "wof:name":"Randolph Business Forms",
    "wof:placetype":"venue"
},
  "geometry": {"coordinates":[-74.534696,40.850342],"type":"Point"}
}