{
  "type": "Feature",
  "properties": {
    "addr:full":"2143 Morris Ave Union NJ 07083",
    "addr:housenumber":"2143",
    "addr:postcode":"07083",
    "addr:street":"Morris Ave",
    "iso:country":"US",
    "sg:address":"2143 Morris Ave",
    "sg:city":"Union",
    "sg:classifiers":[
        {
            "category":"Real Estate",
            "subcategory":"Real Estate Agent",
            "type":"Services"
        }
    ],
    "sg:phone":"+1   ",
    "sg:postcode":"07083",
    "sg:province":"NJ",
    "sg:tags":[
        "property",
        "management"
    ],
    "wof:name":"Maple Realty Management Co",
    "wof:placetype":"venue"
},
  "geometry": {"coordinates":[-74.276251,40.697926],"type":"Point"}
}