{
  "type": "Feature",
  "properties": {
    "iso:country":"US",
    "sg:address":"611 Sayre Ave",
    "sg:city":"Perth Amboy",
    "sg:classifiers":[
        {
            "category":"Building & Trades",
            "subcategory":"Construction",
            "type":"Services"
        }
    ],
    "sg:phone":"+1 732 638 5861",
    "sg:postcode":"08861",
    "sg:province":"NJ",
    "sg:tags":[
        "contractor"
    ],
    "wof:name":"Dmg Mechanical Contractor Llc",
    "wof:placetype":"venue"
},
  "geometry": {"coordinates":[-74.286277,40.51947],"type":"Point"}
}