{
  "type": "Feature",
  "properties": {
    "addr:full":"110 Main St Manasquan NJ 08736",
    "addr:housenumber":"110",
    "addr:postcode":"08736",
    "addr:street":"Main St",
    "iso:country":"US",
    "sg:address":"110 Main St",
    "sg:city":"Manasquan",
    "sg:classifiers":[
        {
            "category":"Personal",
            "subcategory":"Beauty Salon",
            "type":"Services"
        }
    ],
    "sg:phone":"+1 732 223 0974",
    "sg:postcode":"08736",
    "sg:province":"NJ",
    "sg:tags":[
        "manicuring"
    ],
    "wof:name":"Sunny's Imagine Nail Inc",
    "wof:placetype":"venue"
},
  "geometry": {"coordinates":[-74.050938,40.123592],"type":"Point"}
}