{
  "type": "Feature",
  "properties": {
    "iso:country":"US",
    "sg:address":"267 Silver Ln",
    "sg:city":"Old Bridge",
    "sg:classifiers":[
        {
            "category":"Professional",
            "type":"Services"
        }
    ],
    "sg:phone":"+1   ",
    "sg:postcode":"08857",
    "sg:province":"NJ",
    "wof:name":"Andy United Inc",
    "wof:placetype":"venue"
},
  "geometry": {"coordinates":[-74.317426,40.379038],"type":"Point"}
}