{
  "type": "Feature",
  "properties": {
    "iso:country":"US",
    "sg:address":"9 Annett Ave",
    "sg:city":"Edgewater",
    "sg:classifiers":[
        {
            "category":"Wholesale",
            "subcategory":"Non-durable Goods",
            "type":"Manufacturing & Wholesale Goods"
        }
    ],
    "sg:phone":"+1 917 747 2150",
    "sg:postcode":"07020",
    "sg:province":"NJ",
    "wof:name":"Sabrinas Creations",
    "wof:placetype":"venue"
},
  "geometry": {"coordinates":[-73.967235,40.843474],"type":"Point"}
}