{
  "type": "Feature",
  "properties": {
    "iso:country":"US",
    "sg:address":"150 Conklintown Rd",
    "sg:city":"Wanaque",
    "sg:classifiers":[
        {
            "category":"Wholesale",
            "subcategory":"Groceries",
            "type":"Manufacturing & Wholesale Goods"
        }
    ],
    "sg:phone":"+1 973 962 6639",
    "sg:postcode":"07465",
    "sg:province":"NJ",
    "sg:tags":[
        "baker"
    ],
    "wof:name":"Outback Distributors Inc",
    "wof:placetype":"venue"
},
  "geometry": {"coordinates":[-74.276247,41.062339],"type":"Point"}
}