{
  "type": "Feature",
  "properties": {
    "addr:full":"635 W Front St Plainfield NJ 07060",
    "addr:housenumber":"635",
    "addr:postcode":"07060",
    "addr:street":"W Front St",
    "iso:country":"US",
    "sg:address":"635 W Front St",
    "sg:city":"Plainfield",
    "sg:classifiers":[
        {
            "category":"Autos & Motor Vehicles",
            "subcategory":"Auto Supplies",
            "type":"Retail Goods"
        }
    ],
    "sg:phone":"+1 908 561 9653",
    "sg:postcode":"07060",
    "sg:province":"NJ",
    "sg:tags":[
        "automobile",
        "parts"
    ],
    "wof:name":"Autozone",
    "wof:placetype":"venue"
},
  "geometry": {"coordinates":[-74.432303,40.612734],"type":"Point"}
}