{
  "type": "Feature",
  "properties": {
    "iso:country":"US",
    "sg:address":"42 W Holly St",
    "sg:city":"Cranford",
    "sg:classifiers":[
        {
            "category":"Professional",
            "type":"Services"
        }
    ],
    "sg:phone":"+1   ",
    "sg:postcode":"07016",
    "sg:province":"NJ",
    "wof:name":"Sharon Snyder",
    "wof:placetype":"venue"
},
  "geometry": {"coordinates":[-74.315096,40.655593],"type":"Point"}
}