{
  "type": "Feature",
  "properties": {
    "iso:country":"US",
    "sg:address":"139 Headley Ter",
    "sg:city":"Irvington",
    "sg:classifiers":[
        {
            "category":"Professional",
            "subcategory":"Management & Consulting",
            "type":"Services"
        }
    ],
    "sg:phone":"+1   ",
    "sg:postcode":"07111",
    "sg:province":"NJ",
    "sg:tags":[
        "consultant",
        "waste",
        "hauling"
    ],
    "wof:name":"Solid Waste Solutions",
    "wof:placetype":"venue"
},
  "geometry": {"coordinates":[-74.244677,40.729901],"type":"Point"}
}