{
  "type": "Feature",
  "properties": {
    "iso:country":"US",
    "sg:address":"210 Great Bay Blvd",
    "sg:city":"Tuckerton",
    "sg:classifiers":[
        {
            "category":"Health Services",
            "subcategory":"Doctor",
            "type":"Services"
        }
    ],
    "sg:phone":"+1   ",
    "sg:postcode":"08087",
    "sg:province":"NJ",
    "wof:name":"Implant Dentistry",
    "wof:placetype":"venue"
},
  "geometry": {"coordinates":[-74.345851,39.591726],"type":"Point"}
}