{
  "type": "Feature",
  "properties": {
    "addr:full":"810 Springfield Ave Irvington NJ 07111",
    "addr:housenumber":"810",
    "addr:postcode":"07111",
    "addr:street":"Springfield Ave",
    "iso:country":"US",
    "sg:address":"810 Springfield Ave",
    "sg:city":"Irvington",
    "sg:classifiers":[
        {
            "category":"Autos & Motor Vehicles",
            "subcategory":"Automobile Sales",
            "type":"Retail Goods"
        }
    ],
    "sg:phone":"+1 973 416 7111",
    "sg:postcode":"07111",
    "sg:province":"NJ",
    "sg:tags":[
        "car",
        "dealer"
    ],
    "wof:name":"Springfield Auto Mall",
    "wof:placetype":"venue"
},
  "geometry": {"coordinates":[-74.220085,40.728474],"type":"Point"}
}