{
  "type": "Feature",
  "properties": {
    "iso:country":"US",
    "sg:address":"148 State Rte 181",
    "sg:city":"Lake Hopatcong",
    "sg:classifiers":[
        {
            "category":"Travel",
            "subcategory":"Hotels & Motels",
            "type":"Entertainment"
        }
    ],
    "sg:phone":"+1 973 663 3402",
    "sg:postcode":"07849",
    "sg:province":"NJ",
    "wof:name":"Lakeview",
    "wof:placetype":"venue"
},
  "geometry": {"coordinates":[-74.610823,40.985236],"type":"Point"}
}