{
  "type": "Feature",
  "properties": {
    "iso:country":"US",
    "sg:address":"545 Lexington Ave",
    "sg:city":"Clifton",
    "sg:classifiers":[
        {
            "category":"Building & Trades",
            "subcategory":"Construction",
            "type":"Services"
        }
    ],
    "sg:phone":"+1 973 772 9301",
    "sg:postcode":"07011",
    "sg:province":"NJ",
    "sg:tags":[
        "home",
        "improvement"
    ],
    "wof:name":"NRPM Home Improvement",
    "wof:placetype":"venue"
},
  "geometry": {"coordinates":[-74.135091,40.879336],"type":"Point"}
}