{
  "type": "Feature",
  "properties": {
    "addr:full":"571 Watchung Rd Bound Brook NJ 08805",
    "addr:housenumber":"571",
    "addr:postcode":"08805",
    "addr:street":"Watchung Rd",
    "iso:country":"US",
    "sg:address":"571 Watchung Rd",
    "sg:city":"Bound Brook",
    "sg:classifiers":[
        {
            "category":"Real Estate",
            "subcategory":"Real Estate Agent",
            "type":"Services"
        }
    ],
    "sg:phone":"+1   ",
    "sg:postcode":"08805",
    "sg:province":"NJ",
    "wof:name":"Beech Haven Co",
    "wof:placetype":"venue"
},
  "geometry": {"coordinates":[-74.52954099999999,40.57306],"type":"Point"}
}