{
  "type": "Feature",
  "properties": {
    "addr:full":"1013 Wall Rd Spring Lake NJ 07762",
    "addr:housenumber":"1013",
    "addr:postcode":"07762",
    "addr:street":"Wall Rd",
    "iso:country":"US",
    "sg:address":"1013 Wall Rd",
    "sg:city":"Spring Lake",
    "sg:classifiers":[
        {
            "category":"Building & Trades",
            "subcategory":"Construction",
            "type":"Services"
        }
    ],
    "sg:phone":"+1 732 974 0520",
    "sg:postcode":"07762",
    "sg:province":"NJ",
    "sg:tags":[
        "restoration",
        "cleaning",
        "patio",
        "deck"
    ],
    "wof:name":"South Monmouth Pressure Wash",
    "wof:placetype":"venue"
},
  "geometry": {"coordinates":[-74.044501,40.160072],"type":"Point"}
}