{
  "type": "Feature",
  "properties": {
    "addr:full":"755 Catalpa Ave Teaneck NJ 07666",
    "addr:housenumber":"755",
    "addr:postcode":"07666",
    "addr:street":"Catalpa Ave",
    "iso:country":"US",
    "sg:address":"755 Catalpa Ave",
    "sg:city":"Teaneck",
    "sg:classifiers":[
        {
            "category":"Building & Trades",
            "subcategory":"Equipment Rental",
            "type":"Services"
        }
    ],
    "sg:phone":"+1   ",
    "sg:postcode":"07666",
    "sg:province":"NJ",
    "sg:tags":[
        "machine",
        "operator",
        "vending"
    ],
    "wof:name":"Bte Enterprises",
    "wof:placetype":"venue"
},
  "geometry": {"coordinates":[-74.027542,40.890232],"type":"Point"}
}