{
  "type": "Feature",
  "properties": {
    "addr:full":"537 S Olden Ave Trenton NJ 08629",
    "addr:housenumber":"537",
    "addr:postcode":"08629",
    "addr:street":"S Olden Ave",
    "iso:country":"US",
    "sg:address":"537 S Olden Ave",
    "sg:city":"Trenton",
    "sg:classifiers":[
        {
            "category":"Retail",
            "subcategory":"Funeral Services",
            "type":"Services"
        }
    ],
    "sg:phone":"+1 609 392 1039",
    "sg:postcode":"08629",
    "sg:province":"NJ",
    "sg:tags":[
        "director"
    ],
    "wof:name":"Mullens Funeral Home",
    "wof:placetype":"venue"
},
  "geometry": {"coordinates":[-74.73192,40.218746],"type":"Point"}
}