{
  "type": "Feature",
  "properties": {
    "addr:full":"665 Monroe Ave Elizabeth NJ 07201",
    "addr:housenumber":"665",
    "addr:postcode":"07201",
    "addr:street":"Monroe Ave",
    "iso:country":"US",
    "sg:address":"665 Monroe Ave",
    "sg:city":"Elizabeth",
    "sg:classifiers":[
        {
            "category":"Restaurant",
            "type":"Food & Drink"
        }
    ],
    "sg:postcode":"07201",
    "sg:province":"NJ",
    "wof:name":"Valencia",
    "wof:placetype":"venue"
},
  "geometry": {"coordinates":[-74.203141,40.678034],"type":"Point"}
}