{
  "type": "Feature",
  "properties": {
    "iso:country":"US",
    "sg:address":"828 Blackwood Clementon Rd",
    "sg:city":"Pine Hill",
    "sg:classifiers":[
        {
            "category":"Social Services",
            "type":"Services"
        }
    ],
    "sg:phone":"+1 856 627 2808",
    "sg:postcode":"08021",
    "sg:province":"NJ",
    "sg:tags":[
        "organization",
        "welfare"
    ],
    "wof:name":"Easter Seals",
    "wof:placetype":"venue"
},
  "geometry": {"coordinates":[-75.008318,39.804931],"type":"Point"}
}