{
  "type": "Feature",
  "properties": {
    "addr:full":"330 W Jersey St Elizabeth NJ 07202",
    "addr:housenumber":"330",
    "addr:postcode":"07202",
    "addr:street":"W Jersey St",
    "iso:country":"US",
    "sg:address":"330 W Jersey St",
    "sg:city":"Elizabeth",
    "sg:classifiers":[
        {
            "category":"Real Estate",
            "subcategory":"Real Estate Operator",
            "type":"Services"
        }
    ],
    "sg:phone":"+1   ",
    "sg:postcode":"07202",
    "sg:province":"NJ",
    "sg:tags":[
        "apartment",
        "complex"
    ],
    "wof:name":"Hayes House LLC",
    "wof:placetype":"venue"
},
  "geometry": {"coordinates":[-74.226483,40.662676],"type":"Point"}
}