{
  "type": "Feature",
  "properties": {
    "addr:full":"2660 Morris Ave Union NJ 07083",
    "addr:housenumber":"2660",
    "addr:postcode":"07083",
    "addr:street":"Morris Ave",
    "iso:country":"US",
    "sg:address":"2660 Morris Ave",
    "sg:city":"Union",
    "sg:classifiers":[
        {
            "category":"Banks & Credit Unions",
            "subcategory":"Bank",
            "type":"Services"
        }
    ],
    "sg:phone":"+1 908 206 2300",
    "sg:postcode":"07083",
    "sg:province":"NJ",
    "sg:website":"www.pnc.com",
    "wof:name":"Pnc Bank",
    "wof:placetype":"venue"
},
  "geometry": {"coordinates":[-74.294105,40.704037],"type":"Point"}
}