{
  "type": "Feature",
  "properties": {
    "addr:full":"215 Glenridge Ave Montclair NJ 07042",
    "addr:housenumber":"215",
    "addr:postcode":"07042",
    "addr:street":"Glenridge Ave",
    "iso:country":"US",
    "sg:address":"215 Glenridge Ave",
    "sg:city":"Montclair",
    "sg:classifiers":[
        {
            "category":"Sports & Exercise",
            "subcategory":"Gym",
            "type":"Entertainment"
        }
    ],
    "sg:phone":"+1 973 744 4170",
    "sg:postcode":"07042",
    "sg:province":"NJ",
    "wof:name":"Body Creation",
    "wof:placetype":"venue"
},
  "geometry": {"coordinates":[-74.215897,40.813702],"type":"Point"}
}