{
  "type": "Feature",
  "properties": {
    "iso:country":"US",
    "sg:address":"820 Mercer St",
    "sg:city":"Cherry Hill",
    "sg:classifiers":[
        {
            "category":"Utilities",
            "subcategory":"Mobile Phone",
            "type":"Services"
        }
    ],
    "sg:phone":"+1 609 291 2655",
    "sg:postcode":"08002",
    "sg:province":"NJ",
    "sg:tags":[
        "telephone",
        "cellular"
    ],
    "wof:name":"Sierra Wireless Inc",
    "wof:placetype":"venue"
},
  "geometry": {"coordinates":[-75.030748,39.92635],"type":"Point"}
}