{
  "type": "Feature",
  "properties": {
    "addr:full":"1932 E Saint Georges Ave Linden NJ 07036",
    "addr:housenumber":"1932",
    "addr:postcode":"07036",
    "addr:street":"E Saint Georges Ave",
    "iso:country":"US",
    "sg:address":"1932 E Saint Georges Ave",
    "sg:city":"Linden",
    "sg:classifiers":[
        {
            "category":"Retail",
            "subcategory":"Repair Shop",
            "type":"Services"
        }
    ],
    "sg:phone":"+1 908 372 6886",
    "sg:postcode":"07036",
    "sg:province":"NJ",
    "sg:tags":[
        "lock",
        "locksmith"
    ],
    "wof:name":"24 Hour A Day Locksmith",
    "wof:placetype":"venue"
},
  "geometry": {"coordinates":[-74.236136,40.652669],"type":"Point"}
}