{
  "type": "Feature",
  "properties": {
    "addr:full":"45 Wilson Ave Englishtown NJ 07726",
    "addr:housenumber":"45",
    "addr:postcode":"07726",
    "addr:street":"Wilson Ave",
    "iso:country":"US",
    "sg:address":"45 Wilson Ave",
    "sg:city":"Englishtown",
    "sg:classifiers":[
        {
            "category":"Social Services",
            "type":"Services"
        }
    ],
    "sg:phone":"+1 732 786 9960",
    "sg:postcode":"07726",
    "sg:province":"NJ",
    "wof:name":"Crohns Colitis Foundation Amer",
    "wof:placetype":"venue"
},
  "geometry": {"coordinates":[-74.358261,40.305778],"type":"Point"}
}