{
  "type": "Feature",
  "properties": {
    "iso:country":"US",
    "sg:address":"44 Lee Ave",
    "sg:city":"Perth Amboy",
    "sg:classifiers":[
        {
            "category":"Building & Trades",
            "subcategory":"Construction",
            "type":"Services"
        }
    ],
    "sg:phone":"+1 732 826 8901",
    "sg:postcode":"08861",
    "sg:province":"NJ",
    "sg:tags":[
        "contractor"
    ],
    "wof:name":"Mark Mason Kral Contractor",
    "wof:placetype":"venue"
},
  "geometry": {"coordinates":[-74.29186900000001,40.526691],"type":"Point"}
}