{
  "type": "Feature",
  "properties": {
    "addr:full":"85 E 21st St Bayonne NJ 07002",
    "addr:housenumber":"85",
    "addr:postcode":"07002",
    "addr:street":"E 21St St",
    "iso:country":"US",
    "sg:address":"85 E 21st St",
    "sg:city":"Bayonne",
    "sg:classifiers":[
        {
            "category":"Building & Trades",
            "subcategory":"Plumbing",
            "type":"Services"
        }
    ],
    "sg:phone":"+1 201 339 8122",
    "sg:postcode":"07002",
    "sg:province":"NJ",
    "sg:tags":[
        "conditioning",
        "air",
        "system",
        "contractor"
    ],
    "wof:name":"In-Line Air Conditioning Inc",
    "wof:placetype":"venue"
},
  "geometry": {"coordinates":[-74.115064,40.659997],"type":"Point"}
}