{
  "type": "Feature",
  "properties": {
    "addr:full":"6 Alberta Dr Marlboro NJ 07746",
    "addr:housenumber":"6",
    "addr:postcode":"07746",
    "addr:street":"Alberta Dr",
    "iso:country":"US",
    "sg:address":"6 Alberta Dr",
    "sg:city":"Marlboro",
    "sg:classifiers":[
        {
            "category":"Social Services",
            "type":"Services"
        },
        {
            "category":"Professional",
            "subcategory":"Secretarial Services",
            "type":"Services"
        }
    ],
    "sg:phone":"+1 732 536 0076",
    "sg:postcode":"07746",
    "sg:province":"NJ",
    "sg:tags":[
        "counseling",
        "reporting"
    ],
    "sg:website":"www.baskincareer.com",
    "wof:name":"Baskin Business & Career Svcs",
    "wof:placetype":"venue"
},
  "geometry": {"coordinates":[-74.28016,40.330106],"type":"Point"}
}