{
  "type": "Feature",
  "properties": {
    "addr:full":"875 Chambers St Trenton NJ 08611",
    "addr:housenumber":"875",
    "addr:postcode":"08611",
    "addr:street":"Chambers St",
    "iso:country":"US",
    "sg:address":"875 Chambers St",
    "sg:city":"Trenton",
    "sg:classifiers":[
        {
            "category":"Restaurant",
            "type":"Food & Drink"
        }
    ],
    "sg:phone":"+1   ",
    "sg:postcode":"08611",
    "sg:province":"NJ",
    "sg:tags":[
        "eating"
    ],
    "wof:name":"Zips Steakhouse",
    "wof:placetype":"venue"
},
  "geometry": {"coordinates":[-74.739544,40.21246],"type":"Point"}
}