{
  "type": "Feature",
  "properties": {
    "addr:full":"117 Heritage Rd Sewell NJ 08080",
    "addr:housenumber":"117",
    "addr:postcode":"08080",
    "addr:street":"Heritage Rd",
    "iso:country":"US",
    "sg:address":"117 Heritage Rd",
    "sg:city":"Sewell",
    "sg:classifiers":[
        {
            "category":"Building & Trades",
            "subcategory":"Construction",
            "type":"Services"
        }
    ],
    "sg:phone":"+1 856 464 2456",
    "sg:postcode":"08080",
    "sg:province":"NJ",
    "sg:tags":[
        "athletic",
        "fields"
    ],
    "wof:name":"Gregory G Winter Inc",
    "wof:placetype":"venue"
},
  "geometry": {"coordinates":[-75.17906600000001,39.766459],"type":"Point"}
}