{
  "type": "Feature",
  "properties": {
    "iso:country":"US",
    "sg:address":"1920 Frontage Rd",
    "sg:city":"Cherry Hill",
    "sg:classifiers":[
        {
            "category":"Real Estate",
            "subcategory":"Real Estate Agent",
            "type":"Services"
        }
    ],
    "sg:phone":"+1 856 795 0600",
    "sg:postcode":"08034",
    "sg:province":"NJ",
    "wof:name":"Cohen Schatz Associates",
    "wof:placetype":"venue"
},
  "geometry": {"coordinates":[-74.981759,39.916599],"type":"Point"}
}