{
  "type": "Feature",
  "properties": {
    "iso:country":"US",
    "sg:address":"297 E 25th St",
    "sg:city":"Paterson",
    "sg:classifiers":[
        {
            "category":"Personal",
            "subcategory":"Beauty Salon",
            "type":"Services"
        }
    ],
    "sg:phone":"+1 973 523 4872",
    "sg:postcode":"07514",
    "sg:province":"NJ",
    "sg:tags":[
        "shop"
    ],
    "wof:name":"Blessed Hands Beauty Salon",
    "wof:placetype":"venue"
},
  "geometry": {"coordinates":[-74.146545,40.929086],"type":"Point"}
}