{
  "type": "Feature",
  "properties": {
    "iso:country":"US",
    "sg:address":"293 Passaic St",
    "sg:city":"Garfield",
    "sg:classifiers":[
        {
            "category":"Home & Garden",
            "subcategory":"Furniture",
            "type":"Retail Goods"
        }
    ],
    "sg:phone":"+1 973 773 9362",
    "sg:postcode":"07026",
    "sg:province":"NJ",
    "sg:tags":[
        "equipment",
        "kitchen",
        "cabinet"
    ],
    "wof:name":"Inserra's Cabinet Refinishing",
    "wof:placetype":"venue"
},
  "geometry": {"coordinates":[-74.095851,40.870596],"type":"Point"}
}