{
  "type": "Feature",
  "properties": {
    "addr:full":"3305 Fairmount Ave Asbury Park NJ 07712",
    "addr:housenumber":"3305",
    "addr:postcode":"07712",
    "addr:street":"Fairmount Ave Asbury",
    "iso:country":"US",
    "sg:address":"3305 Fairmount Ave",
    "sg:city":"Asbury Park",
    "sg:classifiers":[
        {
            "category":"Government",
            "subcategory":"Post Office",
            "type":"Public Place"
        }
    ],
    "sg:phone":"+1 732 776 8781",
    "sg:postcode":"07712",
    "sg:province":"NJ",
    "sg:tags":[
        "postal",
        "us"
    ],
    "wof:name":"US Post Office",
    "wof:placetype":"venue"
},
  "geometry": {"coordinates":[-74.037166,40.236257],"type":"Point"}
}