{
  "type": "Feature",
  "properties": {
    "addr:full":"493 Spring Hill Rd Skillman NJ 08558",
    "addr:housenumber":"493",
    "addr:postcode":"08558",
    "addr:street":"Spring Hill Rd",
    "iso:country":"US",
    "sg:address":"493 Spring Hill Rd",
    "sg:city":"Skillman",
    "sg:classifiers":[
        {
            "category":"Professional",
            "subcategory":"Management & Consulting",
            "type":"Services"
        }
    ],
    "sg:phone":"+1   ",
    "sg:postcode":"08558",
    "sg:province":"NJ",
    "sg:tags":[
        "business"
    ],
    "wof:name":"Brook Rock Consulting",
    "wof:placetype":"venue"
},
  "geometry": {"coordinates":[-74.749487,40.426833],"type":"Point"}
}