{
  "type": "Feature",
  "properties": {
    "addr:full":"13 Smull Ave Caldwell NJ 07006",
    "addr:housenumber":"13",
    "addr:postcode":"07006",
    "addr:street":"Smull Ave",
    "iso:country":"US",
    "sg:address":"13 Smull Ave",
    "sg:city":"Caldwell",
    "sg:classifiers":[
        {
            "category":"Professional",
            "subcategory":"Lawyer & Legal Services",
            "type":"Services"
        }
    ],
    "sg:phone":"+1 973 667 6000",
    "sg:postcode":"07006",
    "sg:province":"NJ",
    "sg:tags":[
        "attorney"
    ],
    "wof:name":"Conrad & Boutillier",
    "wof:placetype":"venue"
},
  "geometry": {"coordinates":[-74.27425100000001,40.841576],"type":"Point"}
}