{
  "type": "Feature",
  "properties": {
    "iso:country":"US",
    "sg:address":"28 Olcott Ave",
    "sg:city":"Bernardsville",
    "sg:classifiers":[
        {
            "category":"Real Estate",
            "subcategory":"Architect",
            "type":"Services"
        }
    ],
    "sg:phone":"+1 908 204 0088",
    "sg:postcode":"07924",
    "sg:province":"NJ",
    "wof:name":"Daniel W Lincoln",
    "wof:placetype":"venue"
},
  "geometry": {"coordinates":[-74.567329,40.721726],"type":"Point"}
}