{
  "type": "Feature",
  "properties": {
    "iso:country":"US",
    "sg:address":"6 Grace Ave",
    "sg:city":"Clifton",
    "sg:classifiers":[
        {
            "category":"Building & Trades",
            "subcategory":"Construction",
            "type":"Services"
        }
    ],
    "sg:phone":"+1 973 458 9695",
    "sg:postcode":"07011",
    "sg:province":"NJ",
    "sg:tags":[
        "contractor"
    ],
    "wof:name":"Bruno Construction",
    "wof:placetype":"venue"
},
  "geometry": {"coordinates":[-74.137186,40.872965],"type":"Point"}
}