{
  "type": "Feature",
  "properties": {
    "addr:full":"39 Regency Way Englishtown NJ 07726",
    "addr:housenumber":"39",
    "addr:postcode":"07726",
    "addr:street":"Regency Way",
    "iso:country":"US",
    "sg:address":"39 Regency Way",
    "sg:city":"Englishtown",
    "sg:classifiers":[
        {
            "category":"Building & Trades",
            "subcategory":"Plumbing",
            "type":"Services"
        }
    ],
    "sg:phone":"+1 732 431 3520",
    "sg:postcode":"07726",
    "sg:province":"NJ",
    "sg:tags":[
        "contractor"
    ],
    "wof:name":"Jem Industrial Sales Inc",
    "wof:placetype":"venue"
},
  "geometry": {"coordinates":[-74.338179,40.222992],"type":"Point"}
}