{
  "type": "Feature",
  "properties": {
    "addr:full":"253 Cookstown New Egypt Rd Wrightstown NJ 08562",
    "addr:housenumber":"253",
    "addr:postcode":"08562",
    "addr:street":"New Egypt Rd",
    "iso:country":"US",
    "sg:address":"253 Cookstown New Egypt Rd",
    "sg:city":"Wrightstown",
    "sg:classifiers":[
        {
            "category":"Home & Garden",
            "subcategory":"Building Materials",
            "type":"Retail Goods"
        },
        {
            "category":"Building & Trades",
            "subcategory":"Construction",
            "type":"Services"
        }
    ],
    "sg:phone":"+1 609 758 1168",
    "sg:postcode":"08562",
    "sg:province":"NJ",
    "sg:tags":[
        "tile",
        "tr",
        "dealer",
        "contractor"
    ],
    "wof:name":"Maranatha Stairs & Rails",
    "wof:placetype":"venue"
},
  "geometry": {"coordinates":[-74.545255,40.061215],"type":"Point"}
}