{
  "type": "Feature",
  "properties": {
    "addr:full":"106 Mansfield St Belvidere NJ 07823",
    "addr:housenumber":"106",
    "addr:postcode":"07823",
    "addr:street":"Mansfield St",
    "iso:country":"US",
    "sg:address":"106 Mansfield St",
    "sg:city":"Belvidere",
    "sg:classifiers":[
        {
            "category":"Retail",
            "subcategory":"Portrait Studio",
            "type":"Services"
        }
    ],
    "sg:phone":"+1 908 475 2195",
    "sg:postcode":"07823",
    "sg:province":"NJ",
    "sg:tags":[
        "photographer",
        "photo"
    ],
    "wof:name":"Robert J Lubowiki Photography",
    "wof:placetype":"venue"
},
  "geometry": {"coordinates":[-75.077444,40.828233],"type":"Point"}
}