{
  "type": "Feature",
  "properties": {
    "iso:country":"US",
    "sg:address":"1054 E 26th St",
    "sg:city":"Paterson",
    "sg:classifiers":[
        {
            "category":"Freight",
            "type":"Transportation"
        }
    ],
    "sg:phone":"+1 973 247 1121",
    "sg:postcode":"07513",
    "sg:province":"NJ",
    "sg:tags":[
        "operator",
        "local",
        "trucking"
    ],
    "wof:name":"Andres Trucking",
    "wof:placetype":"venue"
},
  "geometry": {"coordinates":[-74.151796,40.90315],"type":"Point"}
}