{
  "type": "Feature",
  "properties": {
    "iso:country":"US",
    "sg:address":"151 W Passaic St",
    "sg:city":"Rochelle Park",
    "sg:classifiers":[
        {
            "category":"Utilities",
            "type":"Services"
        }
    ],
    "sg:phone":"+1 201 291 2992",
    "sg:postcode":"07662",
    "sg:province":"NJ",
    "sg:tags":[
        "provider",
        "internet"
    ],
    "wof:name":"P L N R P Inc",
    "wof:placetype":"venue"
},
  "geometry": {"coordinates":[-74.07820100000001,40.912498],"type":"Point"}
}