{
  "type": "Feature",
  "properties": {
    "iso:country":"US",
    "sg:address":"19 Carrie Dr",
    "sg:city":"Marlboro",
    "sg:classifiers":[
        {
            "category":"Banks & Credit Unions",
            "subcategory":"Financial Services",
            "type":"Services"
        }
    ],
    "sg:phone":"+1   ",
    "sg:postcode":"07746",
    "sg:province":"NJ",
    "sg:tags":[
        "trust",
        "investment",
        "real estate"
    ],
    "wof:name":"Two Fish LLC",
    "wof:placetype":"venue"
},
  "geometry": {"coordinates":[-74.26645000000001,40.302977],"type":"Point"}
}