{
  "type": "Feature",
  "properties": {
    "iso:country":"US",
    "sg:address":"1 S Derby Rd",
    "sg:city":"Springfield",
    "sg:classifiers":[
        {
            "category":"Professional",
            "subcategory":"Lawyer & Legal Services",
            "type":"Services"
        }
    ],
    "sg:phone":"+1 973 379 4657",
    "sg:postcode":"07081",
    "sg:province":"NJ",
    "wof:name":"Harelik Clara T ESQ",
    "wof:placetype":"venue"
},
  "geometry": {"coordinates":[-74.32959700000001,40.687099],"type":"Point"}
}