{
  "type": "Feature",
  "properties": {
    "addr:full":"622 US Hwy 206 Bordentown NJ 08505",
    "addr:housenumber":"622",
    "addr:postcode":"08505",
    "addr:street":"Us Hwy 206",
    "iso:country":"US",
    "sg:address":"622 US Hwy 206",
    "sg:city":"Bordentown",
    "sg:classifiers":[
        {
            "category":"Food & Beverages",
            "subcategory":"Groceries & Convenience Stores",
            "type":"Retail Goods"
        }
    ],
    "sg:phone":"+1 609 298 8700",
    "sg:postcode":"08505",
    "sg:province":"NJ",
    "sg:tags":[
        "market"
    ],
    "sg:website":"www.shoprite.com",
    "wof:name":"Shop Rite Supermarket",
    "wof:placetype":"venue"
},
  "geometry": {"coordinates":[-74.70244700000001,40.176224],"type":"Point"}
}