{
  "type": "Feature",
  "properties": {
    "iso:country":"US",
    "sg:address":"508 45th St",
    "sg:city":"Union City",
    "sg:classifiers":[
        {
            "category":"Personal",
            "type":"Services"
        }
    ],
    "sg:phone":"+1   ",
    "sg:postcode":"07087",
    "sg:province":"NJ",
    "wof:name":"Stellas",
    "wof:placetype":"venue"
},
  "geometry": {"coordinates":[-74.024002,40.779656],"type":"Point"}
}