{
  "type": "Feature",
  "properties": {
    "addr:full":"160 Sip Ave Jersey City NJ 07306",
    "addr:housenumber":"160",
    "addr:postcode":"07306",
    "addr:street":"Sip Ave",
    "iso:country":"US",
    "sg:address":"160 Sip Ave",
    "sg:city":"Jersey City",
    "sg:classifiers":[
        {
            "category":"Utilities",
            "subcategory":"Telephone",
            "type":"Services"
        }
    ],
    "sg:phone":"+1 973 649 9900",
    "sg:postcode":"07306",
    "sg:province":"NJ",
    "sg:tags":[
        "communication"
    ],
    "wof:name":"Verizon",
    "wof:placetype":"venue"
},
  "geometry": {"coordinates":[-74.066203,40.731079],"type":"Point"}
}