{
  "type": "Feature",
  "properties": {
    "iso:country":"US",
    "sg:address":"9219 Ventnor Ave",
    "sg:city":"Margate City",
    "sg:classifiers":[
        {
            "category":"Restaurant",
            "type":"Food & Drink"
        }
    ],
    "sg:phone":"+1   ",
    "sg:postcode":"08402",
    "sg:province":"NJ",
    "sg:tags":[
        "eating"
    ],
    "wof:name":"Pcs Kitchen Maestro",
    "wof:placetype":"venue"
},
  "geometry": {"coordinates":[-74.513839,39.3225],"type":"Point"}
}