{
  "type": "Feature",
  "properties": {
    "iso:country":"US",
    "sg:address":"1104 Cooper St",
    "sg:city":"Woodbury",
    "sg:classifiers":[
        {
            "category":"Health Services",
            "subcategory":"Doctor",
            "type":"Services"
        },
        {
            "category":"Health Services",
            "subcategory":"Dentist",
            "type":"Services"
        }
    ],
    "sg:phone":"+1 856 845 1200",
    "sg:postcode":"08096",
    "sg:province":"NJ",
    "sg:tags":[
        "dentists-oral",
        "physician",
        "maxillofacial",
        "surgeons",
        "surgery",
        "oral"
    ],
    "wof:name":"Timms Jr, Daniel G, Dds - Timms & Koslow",
    "wof:placetype":"venue"
},
  "geometry": {"coordinates":[-75.121579,39.827422],"type":"Point"}
}