{
  "type": "Feature",
  "properties": {
    "addr:full":"26 Locust Dr Summit NJ 07901",
    "addr:housenumber":"26",
    "addr:postcode":"07901",
    "addr:street":"Locust Dr",
    "iso:country":"US",
    "sg:address":"26 Locust Dr",
    "sg:city":"Summit",
    "sg:classifiers":[
        {
            "category":"Home & Garden",
            "subcategory":"Carpets & Floor Coverings",
            "type":"Retail Goods"
        }
    ],
    "sg:phone":"+1 908 522 9384",
    "sg:postcode":"07901",
    "sg:province":"NJ",
    "sg:tags":[
        "material"
    ],
    "wof:name":"Mondo USA",
    "wof:placetype":"venue"
},
  "geometry": {"coordinates":[-74.364906,40.714443],"type":"Point"}
}