{
  "type": "Feature",
  "properties": {
    "iso:country":"US",
    "sg:address":"1 Mercer St",
    "sg:city":"Trenton",
    "sg:classifiers":[
        {
            "category":"Personal",
            "subcategory":"Beauty Salon",
            "type":"Services"
        },
        {
            "category":"Personal",
            "subcategory":"Barber",
            "type":"Services"
        }
    ],
    "sg:phone":"+1 609 890 0741",
    "sg:postcode":"08690",
    "sg:province":"NJ",
    "sg:tags":[
        "shop"
    ],
    "wof:name":"Albert Joseph Hair Stylists",
    "wof:placetype":"venue"
},
  "geometry": {"coordinates":[-74.660354,40.231111],"type":"Point"}
}