{
  "type": "Feature",
  "properties": {
    "addr:full":"40 Wood Ave Secaucus NJ 07094",
    "addr:housenumber":"40",
    "addr:postcode":"07094",
    "addr:street":"Wood Ave",
    "iso:country":"US",
    "sg:address":"40 Wood Ave",
    "sg:city":"Secaucus",
    "sg:classifiers":[
        {
            "category":"Restaurant",
            "type":"Food & Drink"
        },
        {
            "category":"Retail",
            "subcategory":"Event Space",
            "type":"Services"
        }
    ],
    "sg:phone":"+1 201 422 0200",
    "sg:postcode":"07094",
    "sg:province":"NJ",
    "sg:tags":[
        "venue",
        "italian"
    ],
    "wof:name":"La Reggia Restaurant & Banquet Facility",
    "wof:placetype":"venue"
},
  "geometry": {"coordinates":[-74.06379699999999,40.797298],"type":"Point"}
}