{
  "type": "Feature",
  "properties": {
    "addr:full":"148 Doremus Ave Ste 182 Newark NJ 07105",
    "addr:housenumber":"148",
    "addr:postcode":"07105",
    "addr:street":"Doremus Ave Ste 182",
    "iso:country":"US",
    "sg:address":"148 Doremus Ave Ste 182",
    "sg:city":"Newark",
    "sg:classifiers":[
        {
            "category":"Building & Trades",
            "subcategory":"Construction",
            "type":"Services"
        }
    ],
    "sg:phone":"+1 973 344 8422",
    "sg:postcode":"07105",
    "sg:province":"NJ",
    "sg:tags":[
        "driveway",
        "contractor"
    ],
    "wof:name":"Eic Associates",
    "wof:placetype":"venue"
},
  "geometry": {"coordinates":[-74.122058,40.728367],"type":"Point"}
}