{
  "type": "Feature",
  "properties": {
    "iso:country":"US",
    "sg:address":"461 State Rte 10",
    "sg:city":"Dover",
    "sg:classifiers":[
        {
            "category":"Shopping",
            "type":"Retail Goods"
        }
    ],
    "sg:phone":"+1 973 537 7610",
    "sg:postcode":"07869",
    "sg:province":"NJ",
    "sg:tags":[
        "product",
        "wood"
    ],
    "wof:name":"Meadow Wood Manor",
    "wof:placetype":"venue"
},
  "geometry": {"coordinates":[-74.56565999999999,40.862686],"type":"Point"}
}