{
  "type": "Feature",
  "properties": {
    "addr:full":"1454 Columbia Ave Plainfield NJ 07062",
    "addr:housenumber":"1454",
    "addr:postcode":"07062",
    "addr:street":"Columbia Ave",
    "iso:country":"US",
    "sg:address":"1454 Columbia Ave",
    "sg:city":"Plainfield",
    "sg:classifiers":[
        {
            "category":"Building & Trades",
            "subcategory":"Construction",
            "type":"Services"
        }
    ],
    "sg:phone":"+1 908 884 1349",
    "sg:postcode":"07062",
    "sg:province":"NJ",
    "sg:tags":[
        "masonry"
    ],
    "wof:name":"Thurman Williams Masonry Inc",
    "wof:placetype":"venue"
},
  "geometry": {"coordinates":[-74.395804,40.636073],"type":"Point"}
}