{
  "type": "Feature",
  "properties": {
    "iso:country":"US",
    "sg:address":"1392 Oak Tree Rd",
    "sg:city":"Iselin",
    "sg:classifiers":[
        {
            "category":"Restaurant",
            "type":"Food & Drink"
        }
    ],
    "sg:phone":"+1 732 283 2292",
    "sg:postcode":"08830",
    "sg:province":"NJ",
    "sg:tags":[
        "indian"
    ],
    "wof:name":"Ali Baba Restaurant",
    "wof:placetype":"venue"
},
  "geometry": {"coordinates":[-74.32642199999999,40.573701],"type":"Point"}
}