{
  "type": "Feature",
  "properties": {
    "addr:full":"313 River St Paterson NJ 07524",
    "addr:housenumber":"313",
    "addr:postcode":"07524",
    "addr:street":"River St",
    "iso:country":"US",
    "sg:address":"313 River St",
    "sg:city":"Paterson",
    "sg:classifiers":[
        {
            "category":"Home & Garden",
            "subcategory":"Building Materials",
            "type":"Retail Goods"
        }
    ],
    "sg:phone":"+1 973 742 0900",
    "sg:postcode":"07524",
    "sg:province":"NJ",
    "sg:tags":[
        "plumbing",
        "fixture",
        "supply"
    ],
    "wof:name":"Bath & Kitchen Closeout Exp",
    "wof:placetype":"venue"
},
  "geometry": {"coordinates":[-74.163527,40.927663],"type":"Point"}
}