{
  "type": "Feature",
  "properties": {
    "addr:full":"101 Euclid Ave Ridgefield Park NJ 07660",
    "addr:housenumber":"101",
    "addr:postcode":"07660",
    "addr:street":"Euclid Ave",
    "iso:country":"US",
    "sg:address":"101 Euclid Ave",
    "sg:city":"Ridgefield Park",
    "sg:classifiers":[
        {
            "category":"Organizations",
            "subcategory":"Religious Organization",
            "type":"Services"
        }
    ],
    "sg:phone":"+1 201 641 9447",
    "sg:postcode":"07660",
    "sg:province":"NJ",
    "sg:tags":[
        "church"
    ],
    "wof:name":"First Baptist Church",
    "wof:placetype":"venue"
},
  "geometry": {"coordinates":[-74.02296200000001,40.852859],"type":"Point"}
}