{
  "type": "Feature",
  "properties": {
    "iso:country":"US",
    "sg:address":"300 Frank W Burr Blvd",
    "sg:city":"Teaneck",
    "sg:classifiers":[
        {
            "category":"Professional",
            "type":"Services"
        },
        {
            "category":"Professional",
            "subcategory":"Research",
            "type":"Services"
        }
    ],
    "sg:phone":"+1 201 928 2840",
    "sg:postcode":"07666",
    "sg:province":"NJ",
    "sg:tags":[
        "foundation",
        "membership",
        "establishment",
        "philanthropic",
        "organization"
    ],
    "wof:name":"Russ Berrie Foundation Zsag",
    "wof:placetype":"venue"
},
  "geometry": {"coordinates":[-74.006783,40.872839],"type":"Point"}
}