{
  "type": "Feature",
  "properties": {
    "iso:country":"US",
    "sg:address":"19 Hluchy Rd",
    "sg:city":"Trenton",
    "sg:classifiers":[
        {
            "category":"Building & Trades",
            "subcategory":"Landscaping Services",
            "type":"Services"
        }
    ],
    "sg:phone":"+1 609 259 3888",
    "sg:postcode":"08691",
    "sg:province":"NJ",
    "sg:tags":[
        "landscape",
        "contractor"
    ],
    "wof:name":"A P Landesign & Lawn Mntnc",
    "wof:placetype":"venue"
},
  "geometry": {"coordinates":[-74.540406,40.197626],"type":"Point"}
}