{
  "type": "Feature",
  "properties": {
    "addr:full":"620 Madison Ave Woodbine NJ 08270",
    "addr:housenumber":"620",
    "addr:postcode":"08270",
    "addr:street":"Madison Ave",
    "iso:country":"US",
    "sg:address":"620 Madison Ave",
    "sg:city":"Woodbine",
    "sg:classifiers":[
        {
            "category":"Shopping",
            "subcategory":"Music",
            "type":"Retail Goods"
        }
    ],
    "sg:phone":"+1   ",
    "sg:postcode":"08270",
    "sg:province":"NJ",
    "wof:name":"TNT Records",
    "wof:placetype":"venue"
},
  "geometry": {"coordinates":[-74.81421400000001,39.237881],"type":"Point"}
}