{
  "type": "Feature",
  "properties": {
    "iso:country":"US",
    "sg:address":"2 Norfolk St",
    "sg:city":"Bergenfield",
    "sg:classifiers":[
        {
            "category":"Professional",
            "subcategory":"Business Services",
            "type":"Services"
        }
    ],
    "sg:phone":"+1   ",
    "sg:postcode":"07621",
    "sg:province":"NJ",
    "wof:name":"Nexcore Technology Inc",
    "wof:placetype":"venue"
},
  "geometry": {"coordinates":[-74.014674,40.911581],"type":"Point"}
}