{
  "type": "Feature",
  "properties": {
    "iso:country":"US",
    "sg:address":"80 Lexington Ave",
    "sg:city":"Passaic",
    "sg:classifiers":[
        {
            "category":"Arena",
            "subcategory":"Sports Club",
            "type":"Entertainment"
        }
    ],
    "sg:phone":"+1 973 778 5737",
    "sg:postcode":"07055",
    "sg:province":"NJ",
    "sg:tags":[
        "martial art"
    ],
    "wof:name":"Shotokan Karate Dojo International",
    "wof:placetype":"venue"
},
  "geometry": {"coordinates":[-74.12711899999999,40.8647],"type":"Point"}
}