{
  "type": "Feature",
  "properties": {
    "iso:country":"US",
    "sg:address":"10 Schuyler Ave",
    "sg:city":"North Arlington",
    "sg:classifiers":[
        {
            "category":"Retail",
            "subcategory":"Auto Repair",
            "type":"Services"
        }
    ],
    "sg:phone":"+1 201 991 1440",
    "sg:postcode":"07031",
    "sg:province":"NJ",
    "sg:tags":[
        "body",
        "shop"
    ],
    "wof:name":"Weber Auto Body",
    "wof:placetype":"venue"
},
  "geometry": {"coordinates":[-74.129997,40.777802],"type":"Point"}
}