{
  "type": "Feature",
  "properties": {
    "iso:country":"US",
    "sg:address":"1703 State Rte 27",
    "sg:city":"Edison",
    "sg:classifiers":[
        {
            "category":"Manufacturing",
            "subcategory":"Printing",
            "type":"Manufacturing & Wholesale Goods"
        }
    ],
    "sg:phone":"+1 732 777 7872",
    "sg:postcode":"08817",
    "sg:province":"NJ",
    "sg:tags":[
        "poster",
        "silk",
        "screening"
    ],
    "wof:name":"miers architectural & industrl",
    "wof:placetype":"venue"
},
  "geometry": {"coordinates":[-74.408434,40.510962],"type":"Point"}
}