{
  "type": "Feature",
  "properties": {
    "addr:full":"811 Church Rd Ste 222 Cherry Hill NJ 08002",
    "addr:housenumber":"811",
    "addr:postcode":"08002",
    "addr:street":"Church Rd Ste 222",
    "iso:country":"US",
    "sg:address":"811 Church Rd Ste 222",
    "sg:city":"Cherry Hill",
    "sg:classifiers":[
        {
            "category":"Professional",
            "subcategory":"Lawyer & Legal Services",
            "type":"Services"
        }
    ],
    "sg:phone":"+1 856 665 7400",
    "sg:postcode":"08002",
    "sg:province":"NJ",
    "sg:tags":[
        "personal",
        "injury"
    ],
    "wof:name":"Rothenberg Barbara Attorney-At Law",
    "wof:placetype":"venue"
},
  "geometry": {"coordinates":[-75.029999,39.947399],"type":"Point"}
}