{
  "type": "Feature",
  "properties": {
    "addr:full":"141 Franklin Tpke Mahwah NJ 07430",
    "addr:housenumber":"141",
    "addr:postcode":"07430",
    "addr:street":"Franklin Tpke",
    "iso:country":"US",
    "sg:address":"141 Franklin Tpke",
    "sg:city":"Mahwah",
    "sg:classifiers":[
        {
            "category":"Banks & Credit Unions",
            "subcategory":"Bank",
            "type":"Services"
        }
    ],
    "sg:phone":"+1 201 529 6280",
    "sg:postcode":"07430",
    "sg:province":"NJ",
    "sg:tags":[
        "commercial",
        "saving"
    ],
    "sg:website":"http://www.pncbank.com",
    "wof:name":"PNC Bank",
    "wof:placetype":"venue"
},
  "geometry": {"coordinates":[-74.14653,41.097969],"type":"Point"}
}