{
  "type": "Feature",
  "properties": {
    "iso:country":"US",
    "sg:address":"48 Donald St",
    "sg:city":"Clifton",
    "sg:classifiers":[
        {
            "category":"Professional",
            "type":"Services"
        }
    ],
    "sg:phone":"+1   ",
    "sg:postcode":"07011",
    "sg:province":"NJ",
    "wof:name":"Background USA Information Svc",
    "wof:placetype":"venue"
},
  "geometry": {"coordinates":[-74.154178,40.884521],"type":"Point"}
}