{
  "type": "Feature",
  "properties": {
    "iso:country":"US",
    "sg:address":"142 E Front St",
    "sg:city":"Plainfield",
    "sg:classifiers":[
        {
            "category":"Shopping",
            "subcategory":"Jewelry",
            "type":"Retail Goods"
        }
    ],
    "sg:phone":"+1   ",
    "sg:postcode":"07060",
    "sg:province":"NJ",
    "wof:name":"Bong Jewelers",
    "wof:placetype":"venue"
},
  "geometry": {"coordinates":[-74.422669,40.619461],"type":"Point"}
}