{
  "type": "Feature",
  "properties": {
    "addr:full":"1 Addison Pl Ho Ho Kus NJ 07423",
    "addr:housenumber":"1",
    "addr:postcode":"07423",
    "addr:street":"Addison Pl",
    "iso:country":"US",
    "sg:address":"1 Addison Pl",
    "sg:city":"Ho Ho Kus",
    "sg:classifiers":[
        {
            "category":"Real Estate",
            "subcategory":"Architect",
            "type":"Services"
        }
    ],
    "sg:phone":"+1 201 652 8444",
    "sg:postcode":"07423",
    "sg:province":"NJ",
    "wof:name":"Ross R Mamola",
    "wof:placetype":"venue"
},
  "geometry": {"coordinates":[-74.10071499999999,40.99836],"type":"Point"}
}