{
  "type": "Feature",
  "properties": {
    "iso:country":"US",
    "sg:address":"500 Port au Peck Ave",
    "sg:city":"Oceanport",
    "sg:classifiers":[
        {
            "category":"Communications",
            "subcategory":"Film & Video Production",
            "type":"Services"
        }
    ],
    "sg:phone":"+1   ",
    "sg:postcode":"07757",
    "sg:province":"NJ",
    "sg:tags":[
        "motion"
    ],
    "wof:name":"Chateau Ghetto Productions",
    "wof:placetype":"venue"
},
  "geometry": {"coordinates":[-74.00342499999999,40.328264],"type":"Point"}
}