{
  "type": "Feature",
  "properties": {
    "addr:full":"324 W Saddle River Rd Upper Saddle Rvr NJ 07458",
    "addr:housenumber":"324",
    "addr:postcode":"07458",
    "addr:street":"W Saddle River Rd Upper Saddle Rvr",
    "iso:country":"US",
    "sg:address":"324 W Saddle River Rd",
    "sg:city":"Upper Saddle Rvr",
    "sg:classifiers":[
        {
            "category":"Organizations",
            "subcategory":"Religious Organization",
            "type":"Services"
        }
    ],
    "sg:phone":"+1 201 327 0503",
    "sg:postcode":"07458",
    "sg:province":"NJ",
    "sg:tags":[
        "clergy"
    ],
    "wof:name":"George H Kroner",
    "wof:placetype":"venue"
},
  "geometry": {"coordinates":[-74.099707,41.054737],"type":"Point"}
}