{
  "type": "Feature",
  "properties": {
    "addr:full":"105 Piermont Rd Tenafly NJ 07670",
    "addr:housenumber":"105",
    "addr:postcode":"07670",
    "addr:street":"Piermont Rd",
    "iso:country":"US",
    "sg:address":"105 Piermont Rd",
    "sg:city":"Tenafly",
    "sg:classifiers":[
        {
            "category":"Manufacturing",
            "subcategory":"Furniture",
            "type":"Manufacturing & Wholesale Goods"
        }
    ],
    "sg:phone":"+1 201 568 0659",
    "sg:postcode":"07670",
    "sg:province":"NJ",
    "sg:tags":[
        "household",
        "wood",
        "mfg"
    ],
    "wof:name":"Woodworks",
    "wof:placetype":"venue"
},
  "geometry": {"coordinates":[-73.96268499999999,40.931664],"type":"Point"}
}