{
  "type": "Feature",
  "properties": {
    "iso:country":"US",
    "sg:address":"291 Ryerson Rd",
    "sg:city":"Lincoln Park",
    "sg:classifiers":[
        {
            "category":"Home & Garden",
            "subcategory":"Building Materials",
            "type":"Retail Goods"
        }
    ],
    "sg:phone":"+1 973 709 0462",
    "sg:postcode":"07035",
    "sg:province":"NJ",
    "sg:tags":[
        "windows"
    ],
    "wof:name":"Window Guys",
    "wof:placetype":"venue"
},
  "geometry": {"coordinates":[-74.29195199999999,40.924862],"type":"Point"}
}