{
  "type": "Feature",
  "properties": {
    "addr:full":"1792 New York Ave Union City NJ 07087",
    "addr:housenumber":"1792",
    "addr:postcode":"07087",
    "addr:street":"New York Ave",
    "iso:country":"US",
    "sg:address":"1792 New York Ave",
    "sg:city":"Union City",
    "sg:classifiers":[
        {
            "category":"Building & Trades",
            "subcategory":"Locksmith",
            "type":"Services"
        }
    ],
    "sg:phone":"+1 201 520 6470",
    "sg:postcode":"07087",
    "sg:province":"NJ",
    "sg:tags":[
        "key"
    ],
    "wof:name":"Hour Locksmith 24",
    "wof:placetype":"venue"
},
  "geometry": {"coordinates":[-74.033635,40.763013],"type":"Point"}
}