{
  "type": "Feature",
  "properties": {
    "iso:country":"US",
    "sg:address":"10 Concord St",
    "sg:city":"Moonachie",
    "sg:classifiers":[
        {
            "category":"Freight",
            "type":"Transportation"
        }
    ],
    "sg:phone":"+1 201 842 0079",
    "sg:postcode":"07074",
    "sg:province":"NJ",
    "sg:tags":[
        "operator",
        "local",
        "trucking"
    ],
    "wof:name":"Rocama Trucking Inc",
    "wof:placetype":"venue"
},
  "geometry": {"coordinates":[-74.076375,40.841387],"type":"Point"}
}