{
  "type": "Feature",
  "properties": {
    "addr:full":"82 Barkley Ave Clifton NJ 07011",
    "addr:housenumber":"82",
    "addr:postcode":"07011",
    "addr:street":"Barkley Ave",
    "iso:country":"US",
    "sg:address":"82 Barkley Ave",
    "sg:city":"Clifton",
    "sg:classifiers":[
        {
            "category":"Retail",
            "subcategory":"Car Wash",
            "type":"Services"
        }
    ],
    "sg:phone":"+1   ",
    "sg:postcode":"07011",
    "sg:province":"NJ",
    "sg:tags":[
        "carwash"
    ],
    "wof:name":"Wet Worx Detailing",
    "wof:placetype":"venue"
},
  "geometry": {"coordinates":[-74.148399,40.879014],"type":"Point"}
}