{
  "type": "Feature",
  "properties": {
    "addr:full":"215 E Main St Millville NJ 08332",
    "addr:housenumber":"215",
    "addr:postcode":"08332",
    "addr:street":"E Main St",
    "iso:country":"US",
    "sg:address":"215 E Main St",
    "sg:city":"Millville",
    "sg:classifiers":[
        {
            "category":"Building & Trades",
            "subcategory":"Equipment Rental",
            "type":"Services"
        }
    ],
    "sg:phone":"+1 856 327 7686",
    "sg:postcode":"08332",
    "sg:province":"NJ",
    "wof:name":"Air Bounce Inflatables",
    "wof:placetype":"venue"
},
  "geometry": {"coordinates":[-75.035781,39.395316],"type":"Point"}
}