{
  "type": "Feature",
  "properties": {
    "iso:country":"US",
    "sg:address":"25 Hanover Rd",
    "sg:city":"Florham Park",
    "sg:classifiers":[
        {
            "category":"Professional",
            "subcategory":"Management & Consulting",
            "type":"Services"
        }
    ],
    "sg:phone":"+1   ",
    "sg:postcode":"07932",
    "sg:province":"NJ",
    "sg:tags":[
        "business"
    ],
    "wof:name":"Electronic Data Systems Corp",
    "wof:placetype":"venue"
},
  "geometry": {"coordinates":[-74.383087,40.789518],"type":"Point"}
}