{
  "type": "Feature",
  "properties": {
    "addr:full":"115 Parker Rd Tuckerton NJ 08087",
    "addr:housenumber":"115",
    "addr:postcode":"08087",
    "addr:street":"Parker Rd",
    "iso:country":"US",
    "sg:address":"115 Parker Rd",
    "sg:city":"Tuckerton",
    "sg:classifiers":[
        {
            "category":"Manufacturing",
            "subcategory":"Tools & Machinery",
            "type":"Manufacturing & Wholesale Goods"
        }
    ],
    "sg:phone":"+1 609 296 8271",
    "sg:postcode":"08087",
    "sg:province":"NJ",
    "sg:tags":[
        "training",
        "management",
        "retail"
    ],
    "wof:name":"Frendship Estates",
    "wof:placetype":"venue"
},
  "geometry": {"coordinates":[-74.337005,39.580016],"type":"Point"}
}