{
  "type": "Feature",
  "properties": {
    "addr:full":"36 Park Ave Newark NJ 07104",
    "addr:housenumber":"36",
    "addr:postcode":"07104",
    "addr:street":"Park Ave",
    "iso:country":"US",
    "sg:address":"36 Park Ave",
    "sg:city":"Newark",
    "sg:classifiers":[
        {
            "category":"Shopping",
            "subcategory":"Pharmacy",
            "type":"Retail Goods"
        }
    ],
    "sg:phone":"+1 973 412 1000",
    "sg:postcode":"07104",
    "sg:province":"NJ",
    "wof:name":"Amcare Rx Pharmacy",
    "wof:placetype":"venue"
},
  "geometry": {"coordinates":[-74.174454,40.75531],"type":"Point"}
}