{
  "type": "Feature",
  "properties": {
    "addr:full":"600 Park Blvd Cape May NJ 08204",
    "addr:housenumber":"600",
    "addr:postcode":"08204",
    "addr:street":"Park Blvd",
    "iso:country":"US",
    "sg:address":"600 Park Blvd",
    "sg:city":"Cape May",
    "sg:classifiers":[
        {
            "category":"Retail",
            "subcategory":"Pet Boarding",
            "type":"Services"
        }
    ],
    "sg:phone":"+1 609 884 1221",
    "sg:postcode":"08204",
    "sg:province":"NJ",
    "sg:tags":[
        "boarding/pet",
        "sitting"
    ],
    "wof:name":"Kasey's Canine Castle",
    "wof:placetype":"venue"
},
  "geometry": {"coordinates":[-74.9272,38.939201],"type":"Point"}
}