{
  "type": "Feature",
  "properties": {
    "addr:full":"183 Elmora Ave Elizabeth NJ 07202",
    "addr:housenumber":"183",
    "addr:postcode":"07202",
    "addr:street":"Elmora Ave",
    "iso:country":"US",
    "sg:address":"183 Elmora Ave",
    "sg:city":"Elizabeth",
    "sg:classifiers":[
        {
            "category":"Food & Beverages",
            "subcategory":"Bakery",
            "type":"Retail Goods"
        }
    ],
    "sg:phone":"+1   ",
    "sg:postcode":"07202",
    "sg:province":"NJ",
    "wof:name":"Elmora Bagel Bakery Inc",
    "wof:placetype":"venue"
},
  "geometry": {"coordinates":[-74.233733,40.663596],"type":"Point"}
}