{
  "type": "Feature",
  "properties": {
    "addr:full":"924 Bergen Ave Jersey City NJ 07306",
    "addr:housenumber":"924",
    "addr:postcode":"07306",
    "addr:street":"Bergen Ave",
    "iso:country":"US",
    "sg:address":"924 Bergen Ave",
    "sg:city":"Jersey City",
    "sg:classifiers":[
        {
            "category":"Restaurant",
            "type":"Food & Drink"
        }
    ],
    "sg:phone":"+1 201 610 0119",
    "sg:postcode":"07306",
    "sg:province":"NJ",
    "sg:website":"www.popeyes.com",
    "wof:name":"Popeye's Chicken & Biscuits",
    "wof:placetype":"venue"
},
  "geometry": {"coordinates":[-74.064629,40.730341],"type":"Point"}
}