{
  "type": "Feature",
  "properties": {
    "iso:country":"US",
    "sg:address":"722 McLean Ave",
    "sg:city":"Pt Pleasant Bch",
    "sg:classifiers":[
        {
            "category":"Building & Trades",
            "subcategory":"Electrical",
            "type":"Services"
        }
    ],
    "sg:phone":"+1 732 899 7565",
    "sg:postcode":"08742",
    "sg:province":"NJ",
    "sg:tags":[
        "electrical",
        "electric",
        "contractor"
    ],
    "wof:name":"Shore Electric Contractors Inc",
    "wof:placetype":"venue"
},
  "geometry": {"coordinates":[-74.054001,40.093748],"type":"Point"}
}