{
  "type": "Feature",
  "properties": {
    "iso:country":"US",
    "sg:address":"315 Cooper St",
    "sg:city":"Camden",
    "sg:classifiers":[
        {
            "category":"Social Services",
            "type":"Services"
        }
    ],
    "sg:phone":"+1   ",
    "sg:postcode":"08102",
    "sg:province":"NJ",
    "sg:tags":[
        "school"
    ],
    "wof:name":"J R C",
    "wof:placetype":"venue"
},
  "geometry": {"coordinates":[-75.12209799999999,39.94723],"type":"Point"}
}