{
  "type": "Feature",
  "properties": {
    "addr:full":"791 Stuyvesant Ave Irvington NJ 07111",
    "addr:housenumber":"791",
    "addr:postcode":"07111",
    "addr:street":"Stuyvesant Ave",
    "iso:country":"US",
    "sg:address":"791 Stuyvesant Ave",
    "sg:city":"Irvington",
    "sg:classifiers":[
        {
            "category":"Insurance",
            "subcategory":"Insurance Agent",
            "type":"Services"
        }
    ],
    "sg:phone":"+1 973 399 4077",
    "sg:postcode":"07111",
    "sg:province":"NJ",
    "wof:name":"Genesis Brokerage & Tours Inc",
    "wof:placetype":"venue"
},
  "geometry": {"coordinates":[-74.24274,40.720707],"type":"Point"}
}