{
  "type": "Feature",
  "properties": {
    "iso:country":"US",
    "sg:address":"103 Washington Ave",
    "sg:city":"Lavallette",
    "sg:classifiers":[
        {
            "category":"Organizations",
            "subcategory":"Religious Organization",
            "type":"Services"
        }
    ],
    "sg:phone":"+1 732 793 7291",
    "sg:postcode":"08735",
    "sg:province":"NJ",
    "sg:tags":[
        "church"
    ],
    "sg:website":"www.saintbonaventure.net",
    "wof:name":"St Bonaventure Church",
    "wof:placetype":"venue"
},
  "geometry": {"coordinates":[-74.069457,39.968894],"type":"Point"}
}