{
  "type": "Feature",
  "properties": {
    "addr:full":"696 Bergen St Newark NJ 07108",
    "addr:housenumber":"696",
    "addr:postcode":"07108",
    "addr:street":"Bergen St",
    "iso:country":"US",
    "sg:address":"696 Bergen St",
    "sg:city":"Newark",
    "sg:classifiers":[
        {
            "category":"Retail",
            "subcategory":"Auto Repair",
            "type":"Services"
        }
    ],
    "sg:phone":"+1 973 596 1116",
    "sg:postcode":"07108",
    "sg:province":"NJ",
    "wof:name":"Jesse's Auto Service",
    "wof:placetype":"venue"
},
  "geometry": {"coordinates":[-74.20079800000001,40.720402],"type":"Point"}
}