{
  "type": "Feature",
  "properties": {
    "addr:full":"222 Kinderkamack Rd Oradell NJ 07649",
    "addr:housenumber":"222",
    "addr:postcode":"07649",
    "addr:street":"Kinderkamack Rd",
    "iso:country":"US",
    "sg:address":"222 Kinderkamack Rd",
    "sg:city":"Oradell",
    "sg:classifiers":[
        {
            "category":"Health Services",
            "subcategory":"Podiatrist",
            "type":"Services"
        }
    ],
    "sg:phone":"+1 201 261 9445",
    "sg:postcode":"07649",
    "sg:province":"NJ",
    "wof:name":"New Jersey Foot & Ankle Ctr",
    "wof:placetype":"venue"
},
  "geometry": {"coordinates":[-74.03058299999999,40.947508],"type":"Point"}
}