{
  "type": "Feature",
  "properties": {
    "iso:country":"US",
    "sg:address":"1022 Chelsea St",
    "sg:city":"Forked River",
    "sg:classifiers":[
        {
            "category":"Building & Trades",
            "subcategory":"Construction",
            "type":"Services"
        }
    ],
    "sg:phone":"+1 609 693 6664",
    "sg:postcode":"08731",
    "sg:province":"NJ",
    "sg:tags":[
        "plastering",
        "coping",
        "contractor",
        "tiling",
        "pool",
        "swimming"
    ],
    "wof:name":"Lighthouse Pools",
    "wof:placetype":"venue"
},
  "geometry": {"coordinates":[-74.217491,39.861819],"type":"Point"}
}