{
  "type": "Feature",
  "properties": {
    "addr:full":"143 Birchwood Rd Old Tappan NJ 07675",
    "addr:housenumber":"143",
    "addr:postcode":"07675",
    "addr:street":"Birchwood Rd",
    "iso:country":"US",
    "sg:address":"143 Birchwood Rd",
    "sg:city":"Old Tappan",
    "sg:classifiers":[
        {
            "category":"Building & Trades",
            "subcategory":"Construction",
            "type":"Services"
        }
    ],
    "sg:phone":"+1 201 666 7666",
    "sg:postcode":"07675",
    "sg:province":"NJ",
    "sg:tags":[
        "painting",
        "painter",
        "contractor"
    ],
    "wof:name":"Painting Associates Inc",
    "wof:placetype":"venue"
},
  "geometry": {"coordinates":[-73.995384,41.006025],"type":"Point"}
}