{
  "type": "Feature",
  "properties": {
    "addr:full":"469 Lyons Ave Newark NJ 07112",
    "addr:housenumber":"469",
    "addr:postcode":"07112",
    "addr:street":"Lyons Ave",
    "iso:country":"US",
    "sg:address":"469 Lyons Ave",
    "sg:city":"Newark",
    "sg:classifiers":[
        {
            "category":"Restaurant",
            "type":"Food & Drink"
        }
    ],
    "sg:menulink":"http://www.allmenus.com/nj/newark/31275-chengs-restaurant/menu/",
    "sg:phone":"+1 973 926 1168",
    "sg:postcode":"07112",
    "sg:province":"NJ",
    "sg:tags":[
        "asian",
        "chinese"
    ],
    "wof:name":"Cheng's Restaurant",
    "wof:placetype":"venue"
},
  "geometry": {"coordinates":[-74.22392499999999,40.715046],"type":"Point"}
}