{
  "type": "Feature",
  "properties": {
    "iso:country":"US",
    "sg:address":"1135 Easton Ave",
    "sg:city":"Somerset",
    "sg:classifiers":[
        {
            "category":"Restaurant",
            "type":"Food & Drink"
        }
    ],
    "sg:menulink":"http://www.allmenus.com/nj/franklin/208337-taco-bell/menu/",
    "sg:phone":"+1 732 545 9706",
    "sg:postcode":"08873",
    "sg:province":"NJ",
    "sg:tags":[
        "mexican"
    ],
    "wof:name":"Taco Bell",
    "wof:placetype":"venue"
},
  "geometry": {"coordinates":[-74.490376,40.517433],"type":"Point"}
}