{
  "type": "Feature",
  "properties": {
    "iso:country":"US",
    "sg:address":"993 Phelps Rd",
    "sg:city":"Teaneck",
    "sg:classifiers":[
        {
            "category":"Professional",
            "subcategory":"Computer Services",
            "type":"Services"
        }
    ],
    "sg:phone":"+1 201 837 7767",
    "sg:postcode":"07666",
    "sg:province":"NJ",
    "sg:tags":[
        "consultant",
        "designer"
    ],
    "wof:name":"Grade System Inc",
    "wof:placetype":"venue"
},
  "geometry": {"coordinates":[-74.00051000000001,40.884637],"type":"Point"}
}