{
  "type": "Feature",
  "properties": {
    "addr:full":"142 Blackwood Barnsboro Rd Sewell NJ 08080",
    "addr:housenumber":"142",
    "addr:postcode":"08080",
    "addr:street":"Blackwood Barnsboro Rd",
    "iso:country":"US",
    "sg:address":"142 Blackwood Barnsboro Rd",
    "sg:city":"Sewell",
    "sg:classifiers":[
        {
            "category":"Building & Trades",
            "subcategory":"Landscaping Services",
            "type":"Services"
        }
    ],
    "sg:phone":"+1 856 228 5445",
    "sg:postcode":"08080",
    "sg:province":"NJ",
    "sg:tags":[
        "lawn",
        "landscape",
        "contractor"
    ],
    "wof:name":"T & M Landscaping & Lawn Svc",
    "wof:placetype":"venue"
},
  "geometry": {"coordinates":[-75.10944499999999,39.779979],"type":"Point"}
}