{
  "type": "Feature",
  "properties": {
    "iso:country":"US",
    "sg:address":"1201 Bayshore Ave",
    "sg:city":"Brigantine",
    "sg:classifiers":[
        {
            "category":"Building & Trades",
            "subcategory":"Construction",
            "type":"Services"
        }
    ],
    "sg:phone":"+1 609 266 6499",
    "sg:postcode":"08203",
    "sg:province":"NJ",
    "sg:tags":[
        "residential",
        "builder",
        "remodeling",
        "renovation",
        "including"
    ],
    "wof:name":"Ferguson Construction",
    "wof:placetype":"venue"
},
  "geometry": {"coordinates":[-74.37403399999999,39.404458],"type":"Point"}
}