{
  "type": "Feature",
  "properties": {
    "iso:country":"US",
    "sg:address":"121 Charles Dr",
    "sg:city":"Toms River",
    "sg:classifiers":[
        {
            "category":"Retail",
            "subcategory":"Repair Shop",
            "type":"Services"
        }
    ],
    "sg:phone":"+1   ",
    "sg:postcode":"08757",
    "sg:province":"NJ",
    "wof:name":"Mosley Sanitary Septic Service",
    "wof:placetype":"venue"
},
  "geometry": {"coordinates":[-74.20602700000001,39.940277],"type":"Point"}
}