{
  "type": "Feature",
  "properties": {
    "addr:full":"2200A Bayshore Rd Wildwood NJ 08260",
    "addr:housenumber":"2200a",
    "addr:postcode":"08260",
    "addr:street":"Bayshore Rd",
    "iso:country":"US",
    "sg:address":"2200A Bayshore Rd",
    "sg:city":"Wildwood",
    "sg:classifiers":[
        {
            "category":"Restaurant",
            "type":"Food & Drink"
        }
    ],
    "sg:phone":"+1 609 886 1211",
    "sg:postcode":"08260",
    "sg:province":"NJ",
    "sg:tags":[
        "pizza"
    ],
    "sg:website":"dominos.com",
    "wof:name":"Domino's Pizza",
    "wof:placetype":"venue"
},
  "geometry": {"coordinates":[-74.939307,39.01339],"type":"Point"}
}