{
  "type": "Feature",
  "properties": {
    "addr:full":"193 Alexandria Dr Hackettstown NJ 07840",
    "addr:housenumber":"193",
    "addr:postcode":"07840",
    "addr:street":"Alexandria Dr",
    "iso:country":"US",
    "sg:address":"193 Alexandria Dr",
    "sg:city":"Hackettstown",
    "sg:classifiers":[
        {
            "category":"Personal",
            "type":"Services"
        }
    ],
    "sg:phone":"+1   ",
    "sg:postcode":"07840",
    "sg:province":"NJ",
    "wof:name":"Therapeutic Massage",
    "wof:placetype":"venue"
},
  "geometry": {"coordinates":[-74.845474,40.83525],"type":"Point"}
}