{
  "type": "Feature",
  "properties": {
    "iso:country":"US",
    "sg:address":"2818 Bridge Ave",
    "sg:city":"Point Pleasant",
    "sg:classifiers":[
        {
            "category":"Personal",
            "subcategory":"Tanning Parlor",
            "type":"Services"
        }
    ],
    "sg:phone":"+1 732 295 9900",
    "sg:postcode":"08742",
    "sg:province":"NJ",
    "sg:tags":[
        "salon"
    ],
    "wof:name":"Coastal Tanning",
    "wof:placetype":"venue"
},
  "geometry": {"coordinates":[-74.081187,40.074779],"type":"Point"}
}