{
  "type": "Feature",
  "properties": {
    "iso:country":"US",
    "sg:address":"230 W Passaic St",
    "sg:city":"Maywood",
    "sg:classifiers":[
        {
            "category":"Professional",
            "subcategory":"Business Services",
            "type":"Services"
        }
    ],
    "sg:phone":"+1 201 556 9090",
    "sg:postcode":"07607",
    "sg:province":"NJ",
    "sg:tags":[
        "marketing",
        "telephone",
        "telemarketing"
    ],
    "sg:website":"www.mmius.com",
    "wof:name":"Motivational Marketing Inc",
    "wof:placetype":"venue"
},
  "geometry": {"coordinates":[-74.069242,40.907],"type":"Point"}
}