{
  "type": "Feature",
  "properties": {
    "addr:full":"22 Charlotte St Carteret NJ 07008",
    "addr:housenumber":"22",
    "addr:postcode":"07008",
    "addr:street":"Charlotte St",
    "iso:country":"US",
    "sg:address":"22 Charlotte St",
    "sg:city":"Carteret",
    "sg:classifiers":[
        {
            "category":"Building & Trades",
            "subcategory":"Construction",
            "type":"Services"
        }
    ],
    "sg:phone":"+1 732 541 6829",
    "sg:postcode":"07008",
    "sg:province":"NJ",
    "sg:tags":[
        "contractor"
    ],
    "wof:name":"Mike Schmanko Mason Contractor",
    "wof:placetype":"venue"
},
  "geometry": {"coordinates":[-74.231697,40.587898],"type":"Point"}
}