{
  "type": "Feature",
  "properties": {
    "addr:full":"9 Conkling St Basking Ridge NJ 07920",
    "addr:housenumber":"9",
    "addr:postcode":"07920",
    "addr:street":"Conkling St",
    "iso:country":"US",
    "sg:address":"9 Conkling St",
    "sg:city":"Basking Ridge",
    "sg:classifiers":[
        {
            "category":"Professional",
            "subcategory":"Management & Consulting",
            "type":"Services"
        }
    ],
    "sg:phone":"+1 908 630 9005",
    "sg:postcode":"07920",
    "sg:province":"NJ",
    "wof:name":"Walsh Company",
    "wof:placetype":"venue"
},
  "geometry": {"coordinates":[-74.563013,40.710848],"type":"Point"}
}