{
  "type": "Feature",
  "properties": {
    "addr:full":"6814 Tilton Rd Egg Harbor Township NJ 08234",
    "addr:housenumber":"6814",
    "addr:postcode":"08234",
    "addr:street":"Tilton Rd;Harbor",
    "iso:country":"US",
    "sg:address":"6814 Tilton Rd",
    "sg:city":"Egg Harbor Township",
    "sg:classifiers":[
        {
            "category":"Food & Beverages",
            "subcategory":"Specialty",
            "type":"Retail Goods"
        }
    ],
    "sg:phone":"+1   ",
    "sg:postcode":"08234",
    "sg:province":"NJ",
    "sg:tags":[
        "prod",
        "health"
    ],
    "wof:name":"Max Muscle",
    "wof:placetype":"venue"
},
  "geometry": {"coordinates":[-74.559135,39.393501],"type":"Point"}
}