{
  "type": "Feature",
  "properties": {
    "addr:full":"765 High Mountain Rd Franklin Lakes NJ 07417",
    "addr:housenumber":"765",
    "addr:postcode":"07417",
    "addr:street":"High Mountain Rd",
    "iso:country":"US",
    "sg:address":"765 High Mountain Rd",
    "sg:city":"Franklin Lakes",
    "sg:classifiers":[
        {
            "category":"Education",
            "subcategory":"School",
            "type":"Public Place"
        }
    ],
    "sg:phone":"+1 201 891 4433",
    "sg:postcode":"07417",
    "sg:province":"NJ",
    "wof:name":"High Mountain Road Elementary",
    "wof:placetype":"venue"
},
  "geometry": {"coordinates":[-74.21183000000001,40.99258],"type":"Point"}
}