{
  "type": "Feature",
  "properties": {
    "iso:country":"US",
    "sg:address":"603 Woodview Rd",
    "sg:city":"Brielle",
    "sg:classifiers":[
        {
            "category":"Wholesale",
            "subcategory":"Machinery & Supplies",
            "type":"Manufacturing & Wholesale Goods"
        }
    ],
    "sg:phone":"+1 732 528 3000",
    "sg:postcode":"08730",
    "sg:province":"NJ",
    "sg:tags":[
        "pipe",
        "fitting"
    ],
    "wof:name":"W J Coyne",
    "wof:placetype":"venue"
},
  "geometry": {"coordinates":[-74.07177299999999,40.096602],"type":"Point"}
}