{
  "type": "Feature",
  "properties": {
    "iso:country":"US",
    "sg:address":"84 Broad St",
    "sg:city":"Eatontown",
    "sg:classifiers":[
        {
            "category":"Communications",
            "subcategory":"Film & Video Production",
            "type":"Services"
        }
    ],
    "sg:phone":"+1 732 542 4747",
    "sg:postcode":"07724",
    "sg:province":"NJ",
    "sg:tags":[
        "editing",
        "tape"
    ],
    "wof:name":"ASAP Teleproductions Inc",
    "wof:placetype":"venue"
},
  "geometry": {"coordinates":[-74.056766,40.306065],"type":"Point"}
}