{
  "type": "Feature",
  "properties": {
    "addr:full":"46 Wentick St Totowa NJ 07512",
    "addr:housenumber":"46",
    "addr:postcode":"07512",
    "addr:street":"Wentick St",
    "iso:country":"US",
    "sg:address":"46 Wentick St",
    "sg:city":"Totowa",
    "sg:classifiers":[
        {
            "category":"Banks & Credit Unions",
            "subcategory":"Financial Services",
            "type":"Services"
        }
    ],
    "sg:phone":"+1   ",
    "sg:postcode":"07512",
    "sg:province":"NJ",
    "sg:tags":[
        "investor"
    ],
    "wof:name":"Capital Investments",
    "wof:placetype":"venue"
},
  "geometry": {"coordinates":[-74.21720999999999,40.898026],"type":"Point"}
}