{
  "type": "Feature",
  "properties": {
    "addr:full":"18 Cresthill Ave Clifton NJ 07012",
    "addr:housenumber":"18",
    "addr:postcode":"07012",
    "addr:street":"Cresthill Ave",
    "iso:country":"US",
    "sg:address":"18 Cresthill Ave",
    "sg:city":"Clifton",
    "sg:classifiers":[
        {
            "category":"Wholesale",
            "subcategory":"Machinery & Supplies",
            "type":"Manufacturing & Wholesale Goods"
        }
    ],
    "sg:phone":"+1 973 779 7018",
    "sg:postcode":"07012",
    "sg:province":"NJ",
    "sg:tags":[
        "equipment",
        "establishment"
    ],
    "wof:name":"Fascination LLC",
    "wof:placetype":"venue"
},
  "geometry": {"coordinates":[-74.145668,40.841185],"type":"Point"}
}