{
  "type": "Feature",
  "properties": {
    "iso:country":"US",
    "sg:address":"225 Sunset Rd",
    "sg:city":"Willingboro",
    "sg:classifiers":[
        {
            "category":"Health Services",
            "subcategory":"Optometrist",
            "type":"Services"
        }
    ],
    "sg:phone":"+1 609 877 2800",
    "sg:postcode":"08046",
    "sg:province":"NJ",
    "sg:tags":[
        "ophthalmologist"
    ],
    "wof:name":"Burlington County Eye Physicians",
    "wof:placetype":"venue"
},
  "geometry": {"coordinates":[-74.885597,40.048401],"type":"Point"}
}