{
  "type": "Feature",
  "properties": {
    "iso:country":"US",
    "sg:address":"182 Dutch Lane Rd",
    "sg:city":"Freehold",
    "sg:classifiers":[
        {
            "category":"Building & Trades",
            "subcategory":"Electrical",
            "type":"Services"
        }
    ],
    "sg:phone":"+1 732 866 9691",
    "sg:postcode":"07728",
    "sg:province":"NJ",
    "sg:tags":[
        "electrical",
        "contractor"
    ],
    "wof:name":"Monmouth Precision Alarms",
    "wof:placetype":"venue"
},
  "geometry": {"coordinates":[-74.249944,40.283052],"type":"Point"}
}