{
  "type": "Feature",
  "properties": {
    "addr:full":"1799 Hamburg Tpke Wayne NJ 07470",
    "addr:housenumber":"1799",
    "addr:postcode":"07470",
    "addr:street":"Hamburg Tpke",
    "iso:country":"US",
    "sg:address":"1799 Hamburg Tpke",
    "sg:city":"Wayne",
    "sg:classifiers":[
        {
            "category":"Education",
            "subcategory":"School",
            "type":"Public Place"
        }
    ],
    "sg:phone":"+1 973 839 2323",
    "sg:postcode":"07470",
    "sg:province":"NJ",
    "sg:tags":[
        "high",
        "middle",
        "elementary"
    ],
    "wof:name":"Our Lady of Consolation Academy",
    "wof:placetype":"venue"
},
  "geometry": {"coordinates":[-74.26129899999999,40.970402],"type":"Point"}
}