{
  "type": "Feature",
  "properties": {
    "iso:country":"US",
    "sg:address":"56A Main St",
    "sg:city":"Califon",
    "sg:classifiers":[
        {
            "category":"Arts & Performance",
            "subcategory":"Art Gallery",
            "type":"Entertainment"
        }
    ],
    "sg:phone":"+1 908 832 6314",
    "sg:postcode":"07830",
    "sg:province":"NJ",
    "wof:name":"Solaris Gallery",
    "wof:placetype":"venue"
},
  "geometry": {"coordinates":[-74.83560199999999,40.719398],"type":"Point"}
}