{
  "type": "Feature",
  "properties": {
    "iso:country":"US",
    "sg:address":"10 Mettle Ln",
    "sg:city":"Wharton",
    "sg:classifiers":[
        {
            "category":"Building & Trades",
            "subcategory":"Plumbing",
            "type":"Services"
        }
    ],
    "sg:phone":"+1 973 625 5557",
    "sg:postcode":"07885",
    "sg:province":"NJ",
    "sg:tags":[
        "plumbing",
        "contractor"
    ],
    "wof:name":"Molnar Plumbing and Heating",
    "wof:placetype":"venue"
},
  "geometry": {"coordinates":[-74.608822,40.917216],"type":"Point"}
}