{
  "type": "Feature",
  "properties": {
    "iso:country":"US",
    "sg:address":"195 Bellevue Ave",
    "sg:city":"Montclair",
    "sg:classifiers":[
        {
            "category":"Professional",
            "subcategory":"Business Services",
            "type":"Services"
        }
    ],
    "sg:phone":"+1   ",
    "sg:postcode":"07043",
    "sg:province":"NJ",
    "sg:tags":[
        "used",
        "merchandise"
    ],
    "wof:name":"Threadneedle Street",
    "wof:placetype":"venue"
},
  "geometry": {"coordinates":[-74.204956,40.840509],"type":"Point"}
}