{
  "type": "Feature",
  "properties": {
    "addr:full":"52 Belvidere Ave Lambertville NJ 08530",
    "addr:housenumber":"52",
    "addr:postcode":"08530",
    "addr:street":"Belvidere Ave",
    "iso:country":"US",
    "sg:address":"52 Belvidere Ave",
    "sg:city":"Lambertville",
    "sg:classifiers":[
        {
            "category":"Professional",
            "subcategory":"Business Services",
            "type":"Services"
        }
    ],
    "sg:phone":"+1   ",
    "sg:postcode":"08530",
    "sg:province":"NJ",
    "sg:tags":[
        "datum"
    ],
    "wof:name":"Webcontours Business Solutions",
    "wof:placetype":"venue"
},
  "geometry": {"coordinates":[-74.936697,40.370691],"type":"Point"}
}