{
  "type": "Feature",
  "properties": {
    "iso:country":"US",
    "sg:address":"124 Midland Ave",
    "sg:city":"Kearny",
    "sg:classifiers":[
        {
            "category":"Personal",
            "subcategory":"Beauty Salon",
            "type":"Services"
        }
    ],
    "sg:phone":"+1   ",
    "sg:postcode":"07032",
    "sg:province":"NJ",
    "sg:tags":[
        "shop"
    ],
    "wof:name":"Fame Haircutters Etc",
    "wof:placetype":"venue"
},
  "geometry": {"coordinates":[-74.142967,40.769693],"type":"Point"}
}