{
  "type": "Feature",
  "properties": {
    "addr:full":"825 Clonmell Rd Paulsboro NJ 08066",
    "addr:housenumber":"825",
    "addr:postcode":"08066",
    "addr:street":"Clonmell Rd",
    "iso:country":"US",
    "sg:address":"825 Clonmell Rd",
    "sg:city":"Paulsboro",
    "sg:classifiers":[
        {
            "category":"Utilities",
            "subcategory":"Fuel Oil & Lpg",
            "type":"Services"
        }
    ],
    "sg:phone":"+1 856 423 2400",
    "sg:postcode":"08066",
    "sg:province":"NJ",
    "sg:tags":[
        "oils-fuel"
    ],
    "wof:name":"Sunoco",
    "wof:placetype":"venue"
},
  "geometry": {"coordinates":[-75.24884900000001,39.845212],"type":"Point"}
}