{
  "type": "Feature",
  "properties": {
    "addr:full":"48 Johanna Farm Rd Ringoes NJ 08551",
    "addr:housenumber":"48",
    "addr:postcode":"08551",
    "addr:street":"Johanna Farm Rd",
    "iso:country":"US",
    "sg:address":"48 Johanna Farm Rd",
    "sg:city":"Ringoes",
    "sg:classifiers":[
        {
            "category":"Building & Trades",
            "subcategory":"Construction",
            "type":"Services"
        }
    ],
    "sg:phone":"+1 908 806 0662",
    "sg:postcode":"08551",
    "sg:province":"NJ",
    "sg:tags":[
        "home",
        "builder"
    ],
    "wof:name":"Beazer Homes",
    "wof:placetype":"venue"
},
  "geometry": {"coordinates":[-74.873437,40.487632],"type":"Point"}
}