{
  "type": "Feature",
  "properties": {
    "iso:country":"US",
    "sg:address":"520 S Orange Ave",
    "sg:city":"South Orange",
    "sg:classifiers":[
        {
            "category":"Retail",
            "subcategory":"Portrait Studio",
            "type":"Services"
        }
    ],
    "sg:phone":"+1   ",
    "sg:postcode":"07079",
    "sg:province":"NJ",
    "sg:tags":[
        "photo"
    ],
    "wof:name":"Lauren Rutten Photography",
    "wof:placetype":"venue"
},
  "geometry": {"coordinates":[-74.243668,40.745378],"type":"Point"}
}