{
  "type": "Feature",
  "properties": {
    "iso:country":"US",
    "sg:address":"2969 State Rte 23",
    "sg:city":"Newfoundland",
    "sg:classifiers":[
        {
            "category":"Travel",
            "subcategory":"Travel Agent",
            "type":"Entertainment"
        }
    ],
    "sg:phone":"+1 973 208 0110",
    "sg:postcode":"07435",
    "sg:province":"NJ",
    "sg:tags":[
        "agency",
        "bureau"
    ],
    "wof:name":"ACS Travel",
    "wof:placetype":"venue"
},
  "geometry": {"coordinates":[-74.44118899999999,41.048967],"type":"Point"}
}