{
  "type": "Feature",
  "properties": {
    "addr:full":"239 Tanglewood Ct Franklin Lakes NJ 07417",
    "addr:housenumber":"239",
    "addr:postcode":"07417",
    "addr:street":"Tanglewood Ct",
    "iso:country":"US",
    "sg:address":"239 Tanglewood Ct",
    "sg:city":"Franklin Lakes",
    "sg:classifiers":[
        {
            "category":"Food & Beverages",
            "subcategory":"Dairy",
            "type":"Retail Goods"
        }
    ],
    "sg:phone":"+1   ",
    "sg:postcode":"07417",
    "sg:province":"NJ",
    "wof:name":"Kuikens Dairy",
    "wof:placetype":"venue"
},
  "geometry": {"coordinates":[-74.191503,41.01045],"type":"Point"}
}