{
  "type": "Feature",
  "properties": {
    "addr:full":"10 Marconi Ave Iselin NJ 08830",
    "addr:housenumber":"10",
    "addr:postcode":"08830",
    "addr:street":"Marconi Ave",
    "iso:country":"US",
    "sg:address":"10 Marconi Ave",
    "sg:city":"Iselin",
    "sg:classifiers":[
        {
            "category":"Wholesale",
            "subcategory":"Jewelry",
            "type":"Manufacturing & Wholesale Goods"
        },
        {
            "category":"Shopping",
            "subcategory":"Jewelry",
            "type":"Retail Goods"
        }
    ],
    "sg:phone":"+1 732 283 4999",
    "sg:postcode":"08830",
    "sg:province":"NJ",
    "sg:tags":[
        "jeweler"
    ],
    "wof:name":"Virani Jewelers",
    "wof:placetype":"venue"
},
  "geometry": {"coordinates":[-74.324501,40.5741],"type":"Point"}
}