{
  "type": "Feature",
  "properties": {
    "addr:full":"555 Tilton Rd Northfield NJ 08225",
    "addr:housenumber":"555",
    "addr:postcode":"08225",
    "addr:street":"Tilton Rd",
    "iso:country":"US",
    "sg:address":"555 Tilton Rd",
    "sg:city":"Northfield",
    "sg:classifiers":[
        {
            "category":"Professional",
            "subcategory":"Research",
            "type":"Services"
        },
        {
            "category":"Health Services",
            "subcategory":"Medical Lab",
            "type":"Services"
        }
    ],
    "sg:phone":"+1 609 646 4545",
    "sg:postcode":"08225",
    "sg:province":"NJ",
    "sg:tags":[
        "laboratory",
        "dental"
    ],
    "wof:name":"Health Research Center",
    "wof:placetype":"venue"
},
  "geometry": {"coordinates":[-74.603184,39.487976],"type":"Point"}
}