{
  "type": "Feature",
  "properties": {
    "iso:country":"US",
    "sg:address":"826 S Main St",
    "sg:city":"Phillipsburg",
    "sg:classifiers":[
        {
            "category":"Autos & Motor Vehicles",
            "subcategory":"Automobile Sales",
            "type":"Retail Goods"
        }
    ],
    "sg:phone":"+1 908 454 3244",
    "sg:postcode":"08865",
    "sg:province":"NJ",
    "sg:tags":[
        "car",
        "used"
    ],
    "wof:name":"H's Auto Sales Inc",
    "wof:placetype":"venue"
},
  "geometry": {"coordinates":[-75.17652200000001,40.681103],"type":"Point"}
}