{
  "type": "Feature",
  "properties": {
    "addr:full":"709 Boulevard Kenilworth NJ 07033",
    "addr:housenumber":"709",
    "addr:postcode":"07033",
    "addr:street":"Boulevard",
    "iso:country":"US",
    "sg:address":"709 Boulevard",
    "sg:city":"Kenilworth",
    "sg:classifiers":[
        {
            "category":"Cinema",
            "subcategory":"Movie Rental",
            "type":"Entertainment"
        }
    ],
    "sg:phone":"+1 908 241 4435",
    "sg:postcode":"07033",
    "sg:province":"NJ",
    "sg:tags":[
        "game",
        "video"
    ],
    "wof:name":"Palmer Video Store",
    "wof:placetype":"venue"
},
  "geometry": {"coordinates":[-74.286102,40.677502],"type":"Point"}
}