{
  "type": "Feature",
  "properties": {
    "addr:full":"4365 US Hwy 1 Princeton NJ 08540",
    "addr:housenumber":"4365",
    "addr:postcode":"08540",
    "addr:street":"Us Hwy 1",
    "iso:country":"US",
    "sg:address":"4365 US Hwy 1",
    "sg:city":"Princeton",
    "sg:classifiers":[
        {
            "category":"Shopping",
            "type":"Retail Goods"
        }
    ],
    "sg:phone":"+1   ",
    "sg:postcode":"08540",
    "sg:province":"NJ",
    "sg:tags":[
        "fax",
        "copier",
        "furniture"
    ],
    "wof:name":"Stewart Industries Inc",
    "wof:placetype":"venue"
},
  "geometry": {"coordinates":[-74.592777,40.369107],"type":"Point"}
}