{
  "type": "Feature",
  "properties": {
    "iso:country":"US",
    "sg:address":"175 Lehigh Ave",
    "sg:city":"Lakewood",
    "sg:classifiers":[
        {
            "category":"Arts & Performance",
            "subcategory":"Theater",
            "type":"Entertainment"
        }
    ],
    "sg:phone":"+1 732 905 6556",
    "sg:postcode":"08701",
    "sg:province":"NJ",
    "sg:tags":[
        "bureau"
    ],
    "wof:name":"Front Row Entertainment",
    "wof:placetype":"venue"
},
  "geometry": {"coordinates":[-74.172737,40.072747],"type":"Point"}
}