{
  "type": "Feature",
  "properties": {
    "addr:full":"479 Green St Woodbridge NJ 07095",
    "addr:housenumber":"479",
    "addr:postcode":"07095",
    "addr:street":"Green St",
    "iso:country":"US",
    "sg:address":"479 Green St",
    "sg:city":"Woodbridge",
    "sg:classifiers":[
        {
            "category":"Shopping",
            "subcategory":"Computers & Home Electronics",
            "type":"Retail Goods"
        }
    ],
    "sg:phone":"+1 732 634 0656",
    "sg:postcode":"07095",
    "sg:province":"NJ",
    "sg:tags":[
        "equipment",
        "electronic",
        "supply"
    ],
    "wof:name":"Circuit City",
    "wof:placetype":"venue"
},
  "geometry": {"coordinates":[-74.294391,40.558671],"type":"Point"}
}