{
  "type": "Feature",
  "properties": {
    "iso:country":"US",
    "sg:address":"120 Coles St",
    "sg:city":"Jersey City",
    "sg:classifiers":[
        {
            "category":"Food & Beverages",
            "subcategory":"Groceries & Convenience Stores",
            "type":"Retail Goods"
        }
    ],
    "sg:phone":"+1 201 795 1704",
    "sg:postcode":"07302",
    "sg:province":"NJ",
    "sg:tags":[
        "grocer"
    ],
    "wof:name":"Alberts Grocery",
    "wof:placetype":"venue"
},
  "geometry": {"coordinates":[-74.046898,40.726101],"type":"Point"}
}