{
  "type": "Feature",
  "properties": {
    "iso:country":"US",
    "sg:address":"625 From Rd Ste2",
    "sg:city":"Paramus",
    "sg:classifiers":[
        {
            "category":"Insurance",
            "subcategory":"Insurance Agent",
            "type":"Services"
        },
        {
            "category":"Insurance",
            "subcategory":"Hazard Insurance",
            "type":"Services"
        }
    ],
    "sg:phone":"+1 201 225 9099",
    "sg:postcode":"07652",
    "sg:province":"NJ",
    "sg:tags":[
        "auto",
        "recreational",
        "motorcycle",
        "vehicle",
        "marine",
        "boat"
    ],
    "sg:website":"http://www.suburbangeneral.com",
    "wof:name":"Suburban General Insurance Agency",
    "wof:placetype":"venue"
},
  "geometry": {"coordinates":[-74.06664499999999,40.960148],"type":"Point"}
}