{
  "type": "Feature",
  "properties": {
    "addr:full":"42 Alabama Ave Paterson NJ 07503",
    "addr:housenumber":"42",
    "addr:postcode":"07503",
    "addr:street":"Alabama Ave",
    "iso:country":"US",
    "sg:address":"42 Alabama Ave",
    "sg:city":"Paterson",
    "sg:classifiers":[
        {
            "category":"Local Transit",
            "type":"Transportation"
        }
    ],
    "sg:phone":"+1 973 396 2058",
    "sg:postcode":"07503",
    "sg:province":"NJ",
    "sg:tags":[
        "public"
    ],
    "wof:name":"Nj Best Way Transit Corporation",
    "wof:placetype":"venue"
},
  "geometry": {"coordinates":[-74.154734,40.898845],"type":"Point"}
}