{
  "type": "Feature",
  "properties": {
    "iso:country":"US",
    "sg:address":"1086 Dumont Cir",
    "sg:city":"Voorhees",
    "sg:classifiers":[
        {
            "category":"Health Services",
            "subcategory":"Nursing And Care Facility",
            "type":"Services"
        }
    ],
    "sg:phone":"+1 856 309 1093",
    "sg:postcode":"08043",
    "sg:province":"NJ",
    "sg:tags":[
        "home",
        "convalescent"
    ],
    "wof:name":"MCR Manor Care",
    "wof:placetype":"venue"
},
  "geometry": {"coordinates":[-74.97818700000001,39.843615],"type":"Point"}
}