{
  "type": "Feature",
  "properties": {
    "addr:full":"28 Poor Farm Rd Pennington NJ 08534",
    "addr:housenumber":"28",
    "addr:postcode":"08534",
    "addr:street":"Poor Farm Rd",
    "iso:country":"US",
    "sg:address":"28 Poor Farm Rd",
    "sg:city":"Pennington",
    "sg:classifiers":[
        {
            "category":"Retail",
            "subcategory":"Animal Services",
            "type":"Services"
        }
    ],
    "sg:phone":"+1 609 737 1021",
    "sg:postcode":"08534",
    "sg:province":"NJ",
    "wof:name":"Shady Spring Farm LLC",
    "wof:placetype":"venue"
},
  "geometry": {"coordinates":[-74.823977,40.352598],"type":"Point"}
}