{
  "type": "Feature",
  "properties": {
    "addr:full":"47 Poe Rd Princeton NJ 08540",
    "addr:housenumber":"47",
    "addr:postcode":"08540",
    "addr:street":"Poe Rd",
    "iso:country":"US",
    "sg:address":"47 Poe Rd",
    "sg:city":"Princeton",
    "sg:classifiers":[
        {
            "category":"Professional",
            "type":"Services"
        }
    ],
    "sg:phone":"+1   ",
    "sg:postcode":"08540",
    "sg:province":"NJ",
    "sg:tags":[
        "lecturing"
    ],
    "wof:name":"Robert Strauss",
    "wof:placetype":"venue"
},
  "geometry": {"coordinates":[-74.629836,40.365904],"type":"Point"}
}