{
  "type": "Feature",
  "properties": {
    "addr:full":"151 Stedwick Dr Budd Lake NJ 07828",
    "addr:housenumber":"151",
    "addr:postcode":"07828",
    "addr:street":"Stedwick Dr",
    "iso:country":"US",
    "sg:address":"151 Stedwick Dr",
    "sg:city":"Budd Lake",
    "sg:classifiers":[
        {
            "category":"Shopping",
            "subcategory":"Gifts & Souvenirs",
            "type":"Retail Goods"
        }
    ],
    "sg:phone":"+1   ",
    "sg:postcode":"07828",
    "sg:province":"NJ",
    "wof:name":"Flanders Flowers & Gifts",
    "wof:placetype":"venue"
},
  "geometry": {"coordinates":[-74.748099,40.85377],"type":"Point"}
}