{
  "type": "Feature",
  "properties": {
    "iso:country":"US",
    "sg:address":"351 US Highway 46",
    "sg:city":"Great Meadows",
    "sg:classifiers":[
        {
            "category":"Personal",
            "type":"Services"
        }
    ],
    "sg:phone":"+1 908 637 4898",
    "sg:postcode":"07838",
    "sg:province":"NJ",
    "sg:tags":[
        "towing"
    ],
    "wof:name":"R T Towing",
    "wof:placetype":"venue"
},
  "geometry": {"coordinates":[-74.93620300000001,40.852299],"type":"Point"}
}