{
  "type": "Feature",
  "properties": {
    "iso:country":"US",
    "sg:address":"20 W Anchor Dr",
    "sg:city":"Tuckerton",
    "sg:classifiers":[
        {
            "category":"Building & Trades",
            "subcategory":"Construction",
            "type":"Services"
        }
    ],
    "sg:phone":"+1 609 296 2320",
    "sg:postcode":"08087",
    "sg:province":"NJ",
    "sg:tags":[
        "floor",
        "laying",
        "contractor"
    ],
    "wof:name":"Ocean Hardwood Flooring",
    "wof:placetype":"venue"
},
  "geometry": {"coordinates":[-74.371532,39.566718],"type":"Point"}
}