{
  "type": "Feature",
  "properties": {
    "addr:full":"151 Town Center Dr Warren NJ 07059",
    "addr:housenumber":"151",
    "addr:postcode":"07059",
    "addr:street":"Town Center Dr",
    "iso:country":"US",
    "sg:address":"151 Town Center Dr",
    "sg:city":"Warren",
    "sg:classifiers":[
        {
            "category":"Professional",
            "subcategory":"Business Services",
            "type":"Services"
        }
    ],
    "sg:phone":"+1   ",
    "sg:postcode":"07059",
    "sg:province":"NJ",
    "wof:name":"Global Touch Telecom Inc",
    "wof:placetype":"venue"
},
  "geometry": {"coordinates":[-74.49851700000001,40.617552],"type":"Point"}
}