{
  "type": "Feature",
  "properties": {
    "iso:country":"US",
    "sg:address":"239 W Browning Rd",
    "sg:city":"Bellmawr",
    "sg:classifiers":[
        {
            "category":"Building & Trades",
            "subcategory":"Construction",
            "type":"Services"
        }
    ],
    "sg:phone":"+1 856 931 7734",
    "sg:postcode":"08031",
    "sg:province":"NJ",
    "sg:tags":[
        "contractor"
    ],
    "wof:name":"White Oak Construction",
    "wof:placetype":"venue"
},
  "geometry": {"coordinates":[-75.091623,39.868307],"type":"Point"}
}