{
  "type": "Feature",
  "properties": {
    "iso:country":"US",
    "sg:address":"21 White St",
    "sg:city":"Shrewsbury",
    "sg:classifiers":[
        {
            "category":"Health Services",
            "subcategory":"Hospital",
            "type":"Services"
        }
    ],
    "sg:phone":"+1 732 747 1937",
    "sg:postcode":"07702",
    "sg:province":"NJ",
    "sg:tags":[
        "mental"
    ],
    "wof:name":"Terry Kwiatkowski",
    "wof:placetype":"venue"
},
  "geometry": {"coordinates":[-74.058742,40.329801],"type":"Point"}
}