{
  "type": "Feature",
  "properties": {
    "addr:full":"625 State Rte 33 Trenton NJ 08619",
    "addr:housenumber":"625",
    "addr:postcode":"08619",
    "addr:street":"State Rte 33",
    "iso:country":"US",
    "sg:address":"625 State Rte 33",
    "sg:city":"Trenton",
    "sg:classifiers":[
        {
            "category":"Shopping",
            "subcategory":"Bicycles & Sporting Goods",
            "type":"Retail Goods"
        }
    ],
    "sg:phone":"+1 609 587 3673",
    "sg:postcode":"08619",
    "sg:province":"NJ",
    "sg:tags":[
        "equipment",
        "golf",
        "supply"
    ],
    "wof:name":"Garden State Discount Golf",
    "wof:placetype":"venue"
},
  "geometry": {"coordinates":[-74.678653,40.231415],"type":"Point"}
}