{
  "type": "Feature",
  "properties": {
    "addr:full":"8 Crown Plz Hazlet NJ 07730",
    "addr:housenumber":"8",
    "addr:postcode":"07730",
    "addr:street":"Crown Plz",
    "iso:country":"US",
    "sg:address":"8 Crown Plz",
    "sg:city":"Hazlet",
    "sg:classifiers":[
        {
            "category":"Wholesale",
            "subcategory":"Machinery & Supplies",
            "type":"Manufacturing & Wholesale Goods"
        }
    ],
    "sg:phone":"+1 732 888 0111",
    "sg:postcode":"07730",
    "sg:province":"NJ",
    "sg:tags":[
        "marine",
        "electronic"
    ],
    "wof:name":"Advanced Marine Technology",
    "wof:placetype":"venue"
},
  "geometry": {"coordinates":[-74.15880799999999,40.420372],"type":"Point"}
}