{
  "type": "Feature",
  "properties": {
    "iso:country":"US",
    "sg:address":"45 Fox Hill Rd",
    "sg:city":"Middletown",
    "sg:classifiers":[
        {
            "category":"Wholesale",
            "subcategory":"Furniture",
            "type":"Manufacturing & Wholesale Goods"
        }
    ],
    "sg:phone":"+1 732 671 6504",
    "sg:postcode":"07748",
    "sg:province":"NJ",
    "sg:tags":[
        "promotion",
        "consulting",
        "household",
        "sales"
    ],
    "wof:name":"Metro Sales of New York",
    "wof:placetype":"venue"
},
  "geometry": {"coordinates":[-74.123879,40.378702],"type":"Point"}
}