{
  "type": "Feature",
  "properties": {
    "iso:country":"US",
    "sg:address":"802 W Park Ave",
    "sg:city":"Ocean",
    "sg:classifiers":[
        {
            "category":"Health Services",
            "subcategory":"Doctor",
            "type":"Services"
        }
    ],
    "sg:phone":"+1 732 918 4848",
    "sg:postcode":"07712",
    "sg:province":"NJ",
    "sg:tags":[
        "physician",
        "surgeon"
    ],
    "wof:name":"Professional Management Bureau",
    "wof:placetype":"venue"
},
  "geometry": {"coordinates":[-74.042642,40.264336],"type":"Point"}
}