{
  "type": "Feature",
  "properties": {
    "iso:country":"US",
    "sg:address":"540 Ravine Ct",
    "sg:city":"Wyckoff",
    "sg:classifiers":[
        {
            "category":"Wholesale",
            "subcategory":"Durable Goods & Equipment",
            "type":"Manufacturing & Wholesale Goods"
        }
    ],
    "sg:phone":"+1 201 447 2900",
    "sg:postcode":"07481",
    "sg:province":"NJ",
    "sg:tags":[
        "professional",
        "sporting"
    ],
    "wof:name":"Police Products Corporation",
    "wof:placetype":"venue"
},
  "geometry": {"coordinates":[-74.14873299999999,40.974883],"type":"Point"}
}