{
  "type": "Feature",
  "properties": {
    "addr:full":"562 Bayway Ave Elizabeth NJ 07202",
    "addr:housenumber":"562",
    "addr:postcode":"07202",
    "addr:street":"Bayway Ave",
    "iso:country":"US",
    "sg:address":"562 Bayway Ave",
    "sg:city":"Elizabeth",
    "sg:classifiers":[
        {
            "category":"Building & Trades",
            "subcategory":"Locksmith",
            "type":"Services"
        }
    ],
    "sg:phone":"+1 888 277 3362",
    "sg:postcode":"07202",
    "sg:province":"NJ",
    "sg:tags":[
        "key"
    ],
    "wof:name":"7 Day 24 Hour Emergency Locksmith",
    "wof:placetype":"venue"
},
  "geometry": {"coordinates":[-74.213398,40.645145],"type":"Point"}
}