{
  "type": "Feature",
  "properties": {
    "addr:full":"239 Boulevard Hasbrouck Hts NJ 07604",
    "addr:housenumber":"239",
    "addr:postcode":"07604",
    "addr:street":"Boulevard",
    "iso:country":"US",
    "sg:address":"239 Boulevard",
    "sg:city":"Hasbrouck Hts",
    "sg:classifiers":[
        {
            "category":"Utilities",
            "subcategory":"Refuse",
            "type":"Services"
        }
    ],
    "sg:phone":"+1 201 393 0095",
    "sg:postcode":"07604",
    "sg:province":"NJ",
    "sg:tags":[
        "disposal",
        "waste"
    ],
    "wof:name":"On Sight Waste Water Control",
    "wof:placetype":"venue"
},
  "geometry": {"coordinates":[-74.07723900000001,40.862949],"type":"Point"}
}