{
  "type": "Feature",
  "properties": {
    "iso:country":"US",
    "sg:address":"900 Wesley Ave",
    "sg:city":"Ocean City",
    "sg:classifiers":[
        {
            "category":"Travel",
            "subcategory":"Hotels & Motels",
            "type":"Entertainment"
        }
    ],
    "sg:phone":"+1 609 399 3350",
    "sg:postcode":"08226",
    "sg:province":"NJ",
    "wof:name":"Pebble Beach Motor Lodge",
    "wof:placetype":"venue"
},
  "geometry": {"coordinates":[-74.57629799999999,39.276537],"type":"Point"}
}