{
  "type": "Feature",
  "properties": {
    "addr:full":"59 E Washington Ave Washington NJ 07882",
    "addr:housenumber":"59",
    "addr:postcode":"07882",
    "addr:street":"E Washington Ave",
    "iso:country":"US",
    "sg:address":"59 E Washington Ave",
    "sg:city":"Washington",
    "sg:classifiers":[
        {
            "category":"Shopping",
            "subcategory":"Gifts & Souvenirs",
            "type":"Retail Goods"
        }
    ],
    "sg:phone":"+1 908 689 1115",
    "sg:postcode":"07882",
    "sg:province":"NJ",
    "sg:tags":[
        "basket",
        "parcel"
    ],
    "wof:name":"Lady Bugs Gift Boutique",
    "wof:placetype":"venue"
},
  "geometry": {"coordinates":[-74.97743199999999,40.758869],"type":"Point"}
}