{
  "type": "Feature",
  "properties": {
    "iso:country":"US",
    "sg:address":"720 King Georges Rd",
    "sg:city":"Fords",
    "sg:classifiers":[
        {
            "category":"Banks & Credit Unions",
            "subcategory":"Bank",
            "type":"Services"
        }
    ],
    "sg:phone":"+1 732 738 9100",
    "sg:postcode":"08863",
    "sg:province":"NJ",
    "sg:website":"www.thriftinvestment.com",
    "wof:name":"Thrift Investment Corp.",
    "wof:placetype":"venue"
},
  "geometry": {"coordinates":[-74.308525,40.531133],"type":"Point"}
}