{
  "type": "Feature",
  "properties": {
    "iso:country":"US",
    "sg:address":"660 Broadway Ave",
    "sg:city":"Paterson",
    "sg:classifiers":[
        {
            "category":"Health Services",
            "subcategory":"Clinic",
            "type":"Services"
        }
    ],
    "sg:phone":"+1 973 881 6927",
    "sg:postcode":"07514",
    "sg:province":"NJ",
    "wof:name":"Paterson Healthy Mothers",
    "wof:placetype":"venue"
},
  "geometry": {"coordinates":[-74.144976,40.918188],"type":"Point"}
}