{
  "type": "Feature",
  "properties": {
    "addr:full":"332 Lycoming Ave Wenonah NJ 08090",
    "addr:housenumber":"332",
    "addr:postcode":"08090",
    "addr:street":"Lycoming Ave",
    "iso:country":"US",
    "sg:address":"332 Lycoming Ave",
    "sg:city":"Wenonah",
    "sg:classifiers":[
        {
            "category":"Building & Trades",
            "subcategory":"Landscaping Services",
            "type":"Services"
        }
    ],
    "sg:phone":"+1 856 468 6229",
    "sg:postcode":"08090",
    "sg:province":"NJ",
    "wof:name":"D & S Stump Removal",
    "wof:placetype":"venue"
},
  "geometry": {"coordinates":[-75.156678,39.807454],"type":"Point"}
}