{
  "type": "Feature",
  "properties": {
    "addr:full":"220 Lincoln Blvd Middlesex NJ 08846",
    "addr:housenumber":"220",
    "addr:postcode":"08846",
    "addr:street":"Lincoln Blvd",
    "iso:country":"US",
    "sg:address":"220 Lincoln Blvd",
    "sg:city":"Middlesex",
    "sg:classifiers":[
        {
            "category":"Wholesale",
            "subcategory":"Non-durable Goods",
            "type":"Manufacturing & Wholesale Goods"
        }
    ],
    "sg:phone":"+1 732 784 1130",
    "sg:postcode":"08846",
    "sg:province":"NJ",
    "sg:tags":[
        "wholesaler"
    ],
    "wof:name":"Dollar Global Inc",
    "wof:placetype":"venue"
},
  "geometry": {"coordinates":[-74.51412999999999,40.562647],"type":"Point"}
}