{
  "type": "Feature",
  "properties": {
    "addr:full":"954 Stuyvesant Ave Union NJ 07083",
    "addr:housenumber":"954",
    "addr:postcode":"07083",
    "addr:street":"Stuyvesant Ave",
    "iso:country":"US",
    "sg:address":"954 Stuyvesant Ave",
    "sg:city":"Union",
    "sg:classifiers":[
        {
            "category":"Restaurant",
            "type":"Food & Drink"
        }
    ],
    "sg:phone":"+1 908 687 8828",
    "sg:postcode":"07083",
    "sg:province":"NJ",
    "wof:name":"Golden China Restaurant",
    "wof:placetype":"venue"
},
  "geometry": {"coordinates":[-74.27156600000001,40.695211],"type":"Point"}
}