{
  "type": "Feature",
  "properties": {
    "iso:country":"US",
    "sg:address":"72 Highland St",
    "sg:city":"Paterson",
    "sg:classifiers":[
        {
            "category":"Professional",
            "subcategory":"Art Services",
            "type":"Services"
        }
    ],
    "sg:phone":"+1 973 903 1546",
    "sg:postcode":"07524",
    "sg:province":"NJ",
    "sg:tags":[
        "graphic",
        "designer"
    ],
    "wof:name":"Juan Lopez Design",
    "wof:placetype":"venue"
},
  "geometry": {"coordinates":[-74.15882499999999,40.92953],"type":"Point"}
}