{
  "type": "Feature",
  "properties": {
    "iso:country":"US",
    "sg:address":"372 Morris Ave",
    "sg:city":"Springfield",
    "sg:classifiers":[
        {
            "category":"Health Services",
            "subcategory":"Dentist",
            "type":"Services"
        }
    ],
    "sg:phone":"+1 973 379 4471",
    "sg:postcode":"07081",
    "sg:province":"NJ",
    "wof:name":"Garden State Orthodonics PA",
    "wof:placetype":"venue"
},
  "geometry": {"coordinates":[-74.31688,40.713528],"type":"Point"}
}