{
  "type": "Feature",
  "properties": {
    "iso:country":"US",
    "sg:address":"335 Essex St",
    "sg:city":"Millburn",
    "sg:classifiers":[
        {
            "category":"Professional",
            "subcategory":"Lawyer & Legal Services",
            "type":"Services"
        }
    ],
    "sg:phone":"+1 973 564 9645",
    "sg:postcode":"07041",
    "sg:province":"NJ",
    "wof:name":"Coleman Harry J Attorney",
    "wof:placetype":"venue"
},
  "geometry": {"coordinates":[-74.30909699999999,40.724201],"type":"Point"}
}