{
  "type": "Feature",
  "properties": {
    "iso:country":"US",
    "sg:address":"3100 Dune Dr",
    "sg:city":"Avalon",
    "sg:classifiers":[
        {
            "category":"Government",
            "subcategory":"Office",
            "type":"Public Place"
        }
    ],
    "sg:phone":"+1 609 967 4045",
    "sg:postcode":"08202",
    "sg:province":"NJ",
    "sg:tags":[
        "city",
        "taxation"
    ],
    "wof:name":"Avalon Tax Collector",
    "wof:placetype":"venue"
},
  "geometry": {"coordinates":[-74.723422,39.095217],"type":"Point"}
}