{
  "type": "Feature",
  "properties": {
    "addr:full":"1159 N Delsea Dr Vineland NJ 08360",
    "addr:housenumber":"1159",
    "addr:postcode":"08360",
    "addr:street":"N Delsea Dr",
    "iso:country":"US",
    "sg:address":"1159 N Delsea Dr",
    "sg:city":"Vineland",
    "sg:classifiers":[
        {
            "category":"Organizations",
            "subcategory":"Community Association",
            "type":"Services"
        }
    ],
    "sg:phone":"+1 856 696 4190",
    "sg:postcode":"08360",
    "sg:province":"NJ",
    "sg:tags":[
        "club"
    ],
    "wof:name":"Boys & Girls Club Of Vineland",
    "wof:placetype":"venue"
},
  "geometry": {"coordinates":[-75.042239,39.498146],"type":"Point"}
}