{
  "type": "Feature",
  "properties": {
    "addr:full":"700 Pine St Camden NJ 08103",
    "addr:housenumber":"700",
    "addr:postcode":"08103",
    "addr:street":"Pine St",
    "iso:country":"US",
    "sg:address":"700 Pine St",
    "sg:city":"Camden",
    "sg:classifiers":[
        {
            "category":"Food & Beverages",
            "subcategory":"Groceries & Convenience Stores",
            "type":"Retail Goods"
        }
    ],
    "sg:phone":"+1 856 966 8416",
    "sg:postcode":"08103",
    "sg:province":"NJ",
    "sg:tags":[
        "grocer"
    ],
    "wof:name":"Camden Mini Market",
    "wof:placetype":"venue"
},
  "geometry": {"coordinates":[-75.115601,39.9366],"type":"Point"}
}