{
  "type": "Feature",
  "properties": {
    "iso:country":"US",
    "sg:address":"160 Greene St",
    "sg:city":"Jersey City",
    "sg:classifiers":[
        {
            "category":"Restaurant",
            "type":"Food & Drink"
        }
    ],
    "sg:menulink":"http://www.allmenus.com/nj/jersey-city/246865-porto-leggero/menu/",
    "sg:phone":"+1 201 434 3200",
    "sg:postcode":"07302",
    "sg:province":"NJ",
    "sg:tags":[
        "italian"
    ],
    "wof:name":"Porto Leggero",
    "wof:placetype":"venue"
},
  "geometry": {"coordinates":[-74.035408,40.718368],"type":"Point"}
}