{
  "type": "Feature",
  "properties": {
    "addr:full":"95 Broadway Keyport NJ 07735",
    "addr:housenumber":"95",
    "addr:postcode":"07735",
    "addr:street":"Broadway",
    "iso:country":"US",
    "sg:address":"95 Broadway",
    "sg:city":"Keyport",
    "sg:classifiers":[
        {
            "category":"Government",
            "subcategory":"Fire Station",
            "type":"Public Place"
        }
    ],
    "sg:phone":"+1 732 264 1126",
    "sg:postcode":"07735",
    "sg:province":"NJ",
    "sg:tags":[
        "department"
    ],
    "wof:name":"Keyport Fire Dept",
    "wof:placetype":"venue"
},
  "geometry": {"coordinates":[-74.20995000000001,40.432656],"type":"Point"}
}