{
  "type": "Feature",
  "properties": {
    "addr:full":"109 S Olden Ave Trenton NJ 08609",
    "addr:housenumber":"109",
    "addr:postcode":"08609",
    "addr:street":"S Olden Ave",
    "iso:country":"US",
    "sg:address":"109 S Olden Ave",
    "sg:city":"Trenton",
    "sg:classifiers":[
        {
            "category":"Restaurant",
            "type":"Food & Drink"
        }
    ],
    "sg:phone":"+1   ",
    "sg:postcode":"08609",
    "sg:province":"NJ",
    "sg:tags":[
        "eating"
    ],
    "wof:name":"Taqueria El Mariachi",
    "wof:placetype":"venue"
},
  "geometry": {"coordinates":[-74.737696,40.224566],"type":"Point"}
}