{
  "type": "Feature",
  "properties": {
    "iso:country":"US",
    "sg:address":"428 Woodbridge Ctr Dr",
    "sg:city":"Woodbridge",
    "sg:classifiers":[
        {
            "category":"Shopping",
            "subcategory":"Baby Store",
            "type":"Retail Goods"
        },
        {
            "category":"Shopping",
            "subcategory":"Department Store",
            "type":"Retail Goods"
        },
        {
            "category":"Shopping",
            "subcategory":"Clothing, Apparel, & Fashions",
            "type":"Retail Goods"
        }
    ],
    "sg:phone":"+1 732 636 6000",
    "sg:postcode":"07095",
    "sg:province":"NJ",
    "sg:tags":[
        "furniture",
        "clothing",
        "gear",
        "women's"
    ],
    "sg:website":"www.JCPenney.com",
    "wof:name":"JCPenney",
    "wof:placetype":"venue"
},
  "geometry": {"coordinates":[-74.301281,40.554623],"type":"Point"}
}