{
  "type": "Feature",
  "properties": {
    "addr:full":"340 Macarthur Blvd Mahwah NJ 07430",
    "addr:housenumber":"340",
    "addr:postcode":"07430",
    "addr:street":"Macarthur Blvd",
    "iso:country":"US",
    "sg:address":"340 Macarthur Blvd",
    "sg:city":"Mahwah",
    "sg:classifiers":[
        {
            "category":"Freight",
            "type":"Transportation"
        }
    ],
    "sg:phone":"+1 201 828 6197",
    "sg:postcode":"07430",
    "sg:province":"NJ",
    "sg:tags":[
        "courier"
    ],
    "wof:name":"UPS",
    "wof:placetype":"venue"
},
  "geometry": {"coordinates":[-74.17242,41.069281],"type":"Point"}
}