{
  "type": "Feature",
  "properties": {
    "addr:full":"48 Fairview Ter Manahawkin NJ 08050",
    "addr:housenumber":"48",
    "addr:postcode":"08050",
    "addr:street":"Fairview Ter",
    "iso:country":"US",
    "sg:address":"48 Fairview Ter",
    "sg:city":"Manahawkin",
    "sg:classifiers":[
        {
            "category":"Building & Trades",
            "subcategory":"Construction",
            "type":"Services"
        }
    ],
    "sg:phone":"+1 609 597 8046",
    "sg:postcode":"08050",
    "sg:province":"NJ",
    "sg:tags":[
        "carpentry"
    ],
    "wof:name":"Eastern Shore Carpentry",
    "wof:placetype":"venue"
},
  "geometry": {"coordinates":[-74.25185399999999,39.711478],"type":"Point"}
}