{
  "type": "Feature",
  "properties": {
    "addr:full":"4 Hydra Ln Sewell NJ 08080",
    "addr:housenumber":"4",
    "addr:postcode":"08080",
    "addr:street":"Hydra Ln",
    "iso:country":"US",
    "sg:address":"4 Hydra Ln",
    "sg:city":"Sewell",
    "sg:classifiers":[
        {
            "category":"Building & Trades",
            "subcategory":"Electrical",
            "type":"Services"
        }
    ],
    "sg:phone":"+1 856 218 8525",
    "sg:postcode":"08080",
    "sg:province":"NJ",
    "sg:tags":[
        "electrical",
        "contractor"
    ],
    "wof:name":"Bz Electric",
    "wof:placetype":"venue"
},
  "geometry": {"coordinates":[-75.086457,39.7201],"type":"Point"}
}