{
  "type": "Feature",
  "properties": {
    "addr:full":"19 Holly St Cranford NJ 07016",
    "addr:housenumber":"19",
    "addr:postcode":"07016",
    "addr:street":"Holly St",
    "iso:country":"US",
    "sg:address":"19 Holly St",
    "sg:city":"Cranford",
    "sg:classifiers":[
        {
            "category":"Health Services",
            "subcategory":"Doctor",
            "type":"Services"
        }
    ],
    "sg:phone":"+1 908 276 0665",
    "sg:postcode":"07016",
    "sg:province":"NJ",
    "sg:tags":[
        "medical"
    ],
    "wof:name":"Edmond R Kassouf MD",
    "wof:placetype":"venue"
},
  "geometry": {"coordinates":[-74.30792099999999,40.656813],"type":"Point"}
}