{
  "type": "Feature",
  "properties": {
    "addr:full":"648 Main Ave Passaic NJ 07055",
    "addr:housenumber":"648",
    "addr:postcode":"07055",
    "addr:street":"Main Ave",
    "iso:country":"US",
    "sg:address":"648 Main Ave",
    "sg:city":"Passaic",
    "sg:classifiers":[
        {
            "category":"Restaurant",
            "type":"Food & Drink"
        }
    ],
    "sg:phone":"+1   ",
    "sg:postcode":"07055",
    "sg:province":"NJ",
    "sg:tags":[
        "eating"
    ],
    "wof:name":"Pizza Hut",
    "wof:placetype":"venue"
},
  "geometry": {"coordinates":[-74.125152,40.860266],"type":"Point"}
}