{
  "type": "Feature",
  "properties": {
    "addr:full":"305 E Youngs Ave Wildwood NJ 08260",
    "addr:housenumber":"305",
    "addr:postcode":"08260",
    "addr:street":"E Youngs Ave",
    "iso:country":"US",
    "sg:address":"305 E Youngs Ave",
    "sg:city":"Wildwood",
    "sg:classifiers":[
        {
            "category":"Travel",
            "subcategory":"Hotels & Motels",
            "type":"Entertainment"
        }
    ],
    "sg:phone":"+1 609 522 8483",
    "sg:postcode":"08260",
    "sg:province":"NJ",
    "wof:name":"Tropicana Motel",
    "wof:placetype":"venue"
},
  "geometry": {"coordinates":[-74.815697,38.985199],"type":"Point"}
}