{
  "type": "Feature",
  "properties": {
    "addr:full":"146 Main St Lincoln Park NJ 07035",
    "addr:housenumber":"146",
    "addr:postcode":"07035",
    "addr:street":"Main St",
    "iso:country":"US",
    "sg:address":"146 Main St",
    "sg:city":"Lincoln Park",
    "sg:classifiers":[
        {
            "category":"Social Services",
            "subcategory":"Child Care",
            "type":"Services"
        },
        {
            "category":"Education",
            "subcategory":"Preschool",
            "type":"Public Place"
        },
        {
            "category":"Education",
            "subcategory":"School",
            "type":"Public Place"
        }
    ],
    "sg:phone":"+1 973 694 6433",
    "sg:postcode":"07035",
    "sg:province":"NJ",
    "sg:tags":[
        "elementary",
        "day"
    ],
    "sg:website":"www.kindercare.com",
    "wof:name":"Kindercare Learning Centers",
    "wof:placetype":"venue"
},
  "geometry": {"coordinates":[-74.309303,40.922699],"type":"Point"}
}