{
  "type": "Feature",
  "properties": {
    "addr:full":"32 Oak Knoll Rd Glen Rock NJ 07452",
    "addr:housenumber":"32",
    "addr:postcode":"07452",
    "addr:street":"Oak Knoll Rd",
    "iso:country":"US",
    "sg:address":"32 Oak Knoll Rd",
    "sg:city":"Glen Rock",
    "sg:classifiers":[
        {
            "category":"Professional",
            "subcategory":"Employment Agencies",
            "type":"Services"
        }
    ],
    "sg:phone":"+1   ",
    "sg:postcode":"07452",
    "sg:province":"NJ",
    "wof:name":"Art For Self Discovery",
    "wof:placetype":"venue"
},
  "geometry": {"coordinates":[-74.137874,40.966862],"type":"Point"}
}