{
  "type": "Feature",
  "properties": {
    "addr:full":"753 Bergen Blvd Ridgefield NJ 07657",
    "addr:housenumber":"753",
    "addr:postcode":"07657",
    "addr:street":"Bergen Blvd",
    "iso:country":"US",
    "sg:address":"753 Bergen Blvd",
    "sg:city":"Ridgefield",
    "sg:classifiers":[
        {
            "category":"Real Estate",
            "subcategory":"Real Estate Services",
            "type":"Services"
        }
    ],
    "sg:phone":"+1 201 840 7460",
    "sg:postcode":"07657",
    "sg:province":"NJ",
    "sg:tags":[
        "company",
        "title"
    ],
    "wof:name":"Malas Title Insurance",
    "wof:placetype":"venue"
},
  "geometry": {"coordinates":[-73.99157700000001,40.832575],"type":"Point"}
}