{
  "type": "Feature",
  "properties": {
    "addr:full":"85 S Maple Ave Ridgewood NJ 07450",
    "addr:housenumber":"85",
    "addr:postcode":"07450",
    "addr:street":"S Maple Ave",
    "iso:country":"US",
    "sg:address":"85 S Maple Ave",
    "sg:city":"Ridgewood",
    "sg:classifiers":[
        {
            "category":"Health Services",
            "subcategory":"Doctor",
            "type":"Services"
        }
    ],
    "sg:phone":"+1 201 445 2830",
    "sg:postcode":"07450",
    "sg:province":"NJ",
    "sg:tags":[
        "physician",
        "surgeon"
    ],
    "sg:website":"www.ridgewoodortho.com",
    "wof:name":"Ridgewood Orthopedic Group",
    "wof:placetype":"venue"
},
  "geometry": {"coordinates":[-74.11539500000001,40.97491],"type":"Point"}
}