{
  "type": "Feature",
  "properties": {
    "iso:country":"US",
    "sg:address":"200 S Broadway St",
    "sg:city":"South Amboy",
    "sg:classifiers":[
        {
            "category":"Food & Beverages",
            "subcategory":"Groceries & Convenience Stores",
            "type":"Retail Goods"
        }
    ],
    "sg:phone":"+1 732 727 4336",
    "sg:postcode":"08879",
    "sg:province":"NJ",
    "sg:tags":[
        "product"
    ],
    "wof:name":"Krauszer's Food Store",
    "wof:placetype":"venue"
},
  "geometry": {"coordinates":[-74.278325,40.481058],"type":"Point"}
}