{
  "type": "Feature",
  "properties": {
    "iso:country":"US",
    "sg:address":"330 Washington Ave",
    "sg:city":"Carlstadt",
    "sg:classifiers":[
        {
            "category":"Autos & Motor Vehicles",
            "subcategory":"Fuel & Gas Station",
            "type":"Retail Goods"
        },
        {
            "category":"Food & Beverages",
            "subcategory":"Groceries & Convenience Stores",
            "type":"Retail Goods"
        }
    ],
    "sg:phone":"+1 201 507 5072",
    "sg:postcode":"07072",
    "sg:province":"NJ",
    "wof:name":"Adpp Enterprises Inc",
    "wof:placetype":"venue"
},
  "geometry": {"coordinates":[-74.064797,40.819089],"type":"Point"}
}