{
  "type": "Feature",
  "properties": {
    "addr:full":"934 Cushing Pl Plainfield NJ 07062",
    "addr:housenumber":"934",
    "addr:postcode":"07062",
    "addr:street":"Cushing Pl",
    "iso:country":"US",
    "sg:address":"934 Cushing Pl",
    "sg:city":"Plainfield",
    "sg:classifiers":[
        {
            "category":"Professional",
            "subcategory":"Art Services",
            "type":"Services"
        }
    ],
    "sg:phone":"+1   ",
    "sg:postcode":"07062",
    "sg:province":"NJ",
    "sg:tags":[
        "commercial",
        "design"
    ],
    "wof:name":"Kenneth Bell",
    "wof:placetype":"venue"
},
  "geometry": {"coordinates":[-74.388459,40.62599],"type":"Point"}
}