{
  "type": "Feature",
  "properties": {
    "addr:full":"1502 Hamilton Ave Trenton NJ 08629",
    "addr:housenumber":"1502",
    "addr:postcode":"08629",
    "addr:street":"Hamilton Ave",
    "iso:country":"US",
    "sg:address":"1502 Hamilton Ave",
    "sg:city":"Trenton",
    "sg:classifiers":[
        {
            "category":"Organizations",
            "subcategory":"Religious Organization",
            "type":"Services"
        }
    ],
    "sg:phone":"+1 609 890 9012",
    "sg:postcode":"08629",
    "sg:province":"NJ",
    "wof:name":"Church of Nazarene",
    "wof:placetype":"venue"
},
  "geometry": {"coordinates":[-74.724057,40.222096],"type":"Point"}
}