{
  "type": "Feature",
  "properties": {
    "addr:full":"104 16th Ave Elmwood Park NJ 07407",
    "addr:housenumber":"104",
    "addr:postcode":"07407",
    "addr:street":"16Th Ave",
    "iso:country":"US",
    "sg:address":"104 16th Ave",
    "sg:city":"Elmwood Park",
    "sg:classifiers":[
        {
            "category":"Building & Trades",
            "subcategory":"Electrical",
            "type":"Services"
        }
    ],
    "sg:phone":"+1 201 703 5052",
    "sg:postcode":"07407",
    "sg:province":"NJ",
    "sg:tags":[
        "electrical",
        "contractor"
    ],
    "wof:name":"A O K Electric Inc",
    "wof:placetype":"venue"
},
  "geometry": {"coordinates":[-74.116838,40.918222],"type":"Point"}
}