{
  "type": "Feature",
  "properties": {
    "iso:country":"US",
    "sg:address":"1 Laurel Mountain Way",
    "sg:city":"Califon",
    "sg:classifiers":[
        {
            "category":"Building & Trades",
            "subcategory":"Construction",
            "type":"Services"
        }
    ],
    "sg:phone":"+1 908 439 3122",
    "sg:postcode":"07830",
    "sg:province":"NJ",
    "sg:tags":[
        "downspouts",
        "gutter"
    ],
    "wof:name":"Bruce Seamless Gutters",
    "wof:placetype":"venue"
},
  "geometry": {"coordinates":[-74.770211,40.70108],"type":"Point"}
}