{
  "type": "Feature",
  "properties": {
    "iso:country":"US",
    "sg:address":"410 Lalor St",
    "sg:city":"Trenton",
    "sg:classifiers":[
        {
            "category":"Personal",
            "subcategory":"Beauty Salon",
            "type":"Services"
        }
    ],
    "sg:phone":"+1 609 396 3800",
    "sg:postcode":"08611",
    "sg:province":"NJ",
    "sg:tags":[
        "manicuring"
    ],
    "wof:name":"LA Nails",
    "wof:placetype":"venue"
},
  "geometry": {"coordinates":[-74.751284,40.198628],"type":"Point"}
}