{
  "type": "Feature",
  "properties": {
    "iso:country":"US",
    "sg:address":"322 Green Pond Rd",
    "sg:city":"Hibernia",
    "sg:classifiers":[
        {
            "category":"Professional",
            "subcategory":"Business Services",
            "type":"Services"
        }
    ],
    "sg:phone":"+1   ",
    "sg:postcode":"07842",
    "sg:province":"NJ",
    "wof:name":"Primerica",
    "wof:placetype":"venue"
},
  "geometry": {"coordinates":[-74.49431199999999,40.945893],"type":"Point"}
}