{
  "type": "Feature",
  "properties": {
    "addr:full":"500 International Dr Budd Lake NJ 07828",
    "addr:housenumber":"500",
    "addr:postcode":"07828",
    "addr:street":"International Dr",
    "iso:country":"US",
    "sg:address":"500 International Dr",
    "sg:city":"Budd Lake",
    "sg:classifiers":[
        {
            "category":"Mining & Drilling",
            "type":"Manufacturing & Wholesale Goods"
        }
    ],
    "sg:phone":"+1 973 691 5317",
    "sg:postcode":"07828",
    "sg:province":"NJ",
    "sg:tags":[
        "exploration"
    ],
    "wof:name":"Shell",
    "wof:placetype":"venue"
},
  "geometry": {"coordinates":[-74.72596799999999,40.903739],"type":"Point"}
}