{
  "type": "Feature",
  "properties": {
    "iso:country":"US",
    "sg:address":"590 Central Ave",
    "sg:city":"New Providence",
    "sg:classifiers":[
        {
            "category":"Shopping",
            "subcategory":"Pharmacy",
            "type":"Retail Goods"
        }
    ],
    "sg:phone":"+1 908 464 4224",
    "sg:postcode":"07974",
    "sg:province":"NJ",
    "wof:name":"Crestview Drugs",
    "wof:placetype":"venue"
},
  "geometry": {"coordinates":[-74.40416999999999,40.697998],"type":"Point"}
}