{
  "type": "Feature",
  "properties": {
    "addr:full":"422 Paterson Ave East Rutherford NJ 07073",
    "addr:housenumber":"422",
    "addr:postcode":"07073",
    "addr:street":"Paterson Ave",
    "iso:country":"US",
    "sg:address":"422 Paterson Ave",
    "sg:city":"East Rutherford",
    "sg:classifiers":[
        {
            "category":"Personal",
            "type":"Services"
        },
        {
            "category":"Professional",
            "subcategory":"Management & Consulting",
            "type":"Services"
        }
    ],
    "sg:phone":"+1 201 343 9343",
    "sg:postcode":"07073",
    "sg:province":"NJ",
    "sg:tags":[
        "paying",
        "bill",
        "business"
    ],
    "wof:name":"Arbre Payments Systems",
    "wof:placetype":"venue"
},
  "geometry": {"coordinates":[-74.10074400000001,40.839126],"type":"Point"}
}