{
  "type": "Feature",
  "properties": {
    "addr:full":"405 Crescent Blvd Mt Ephraim NJ 08059",
    "addr:housenumber":"405",
    "addr:postcode":"08059",
    "addr:street":"Crescent Blvd Mt",
    "iso:country":"US",
    "sg:address":"405 Crescent Blvd",
    "sg:city":"Mt Ephraim",
    "sg:classifiers":[
        {
            "category":"Wholesale",
            "subcategory":"Machinery & Supplies",
            "type":"Manufacturing & Wholesale Goods"
        }
    ],
    "sg:phone":"+1 856 456 5200",
    "sg:postcode":"08059",
    "sg:province":"NJ",
    "sg:tags":[
        "fitting",
        "hose",
        "coupling"
    ],
    "wof:name":"Engineered Hydraulics Inc",
    "wof:placetype":"venue"
},
  "geometry": {"coordinates":[-75.101286,39.89645],"type":"Point"}
}