{
  "type": "Feature",
  "properties": {
    "iso:country":"US",
    "sg:address":"1300 Grand St",
    "sg:city":"Hoboken",
    "sg:classifiers":[
        {
            "category":"Food & Beverages",
            "subcategory":"Groceries & Convenience Stores",
            "type":"Retail Goods"
        }
    ],
    "sg:phone":"+1 201 683 7903",
    "sg:postcode":"07030",
    "sg:province":"NJ",
    "wof:name":"Grand Convenience Llc",
    "wof:placetype":"venue"
},
  "geometry": {"coordinates":[-74.03211400000001,40.753039],"type":"Point"}
}