{
  "type": "Feature",
  "properties": {
    "iso:country":"US",
    "sg:address":"358 Sheridan Ct",
    "sg:city":"New Milford",
    "sg:classifiers":[
        {
            "category":"Shopping",
            "type":"Retail Goods"
        }
    ],
    "sg:phone":"+1 201 287 1332",
    "sg:postcode":"07646",
    "sg:province":"NJ",
    "sg:tags":[
        "pet",
        "shop"
    ],
    "wof:name":"World Pets Of America",
    "wof:placetype":"venue"
},
  "geometry": {"coordinates":[-74.01924,40.91593],"type":"Point"}
}