{
  "type": "Feature",
  "properties": {
    "addr:full":"4 Elana Dr Jackson NJ 08527",
    "addr:housenumber":"4",
    "addr:postcode":"08527",
    "addr:street":"Elana Dr",
    "iso:country":"US",
    "sg:address":"4 Elana Dr",
    "sg:city":"Jackson",
    "sg:classifiers":[
        {
            "category":"Retail",
            "subcategory":"Repair Shop",
            "type":"Services"
        }
    ],
    "sg:phone":"+1   ",
    "sg:postcode":"08527",
    "sg:province":"NJ",
    "sg:tags":[
        "electronics"
    ],
    "wof:name":"Roma Electronics",
    "wof:placetype":"venue"
},
  "geometry": {"coordinates":[-74.37600399999999,40.141989],"type":"Point"}
}