{
  "type": "Feature",
  "properties": {
    "iso:country":"US",
    "sg:address":"56 Hamilton Ave",
    "sg:city":"Passaic",
    "sg:classifiers":[
        {
            "category":"Health Services",
            "subcategory":"Nursing And Care Facility",
            "type":"Services"
        }
    ],
    "sg:phone":"+1 973 458 9478",
    "sg:postcode":"07055",
    "sg:province":"NJ",
    "sg:tags":[
        "skilled"
    ],
    "wof:name":"Aculabs Inc",
    "wof:placetype":"venue"
},
  "geometry": {"coordinates":[-74.123634,40.86293],"type":"Point"}
}