{
  "type": "Feature",
  "properties": {
    "addr:full":"619 Grant Ave Franklinville NJ 08322",
    "addr:housenumber":"619",
    "addr:postcode":"08322",
    "addr:street":"Grant Ave",
    "iso:country":"US",
    "sg:address":"619 Grant Ave",
    "sg:city":"Franklinville",
    "sg:classifiers":[
        {
            "category":"Building & Trades",
            "subcategory":"Plumbing",
            "type":"Services"
        }
    ],
    "sg:phone":"+1 856 694 0078",
    "sg:postcode":"08322",
    "sg:province":"NJ",
    "sg:tags":[
        "conditioning",
        "air",
        "system",
        "contractor"
    ],
    "wof:name":"Cour Refrigeration & Air Cond",
    "wof:placetype":"venue"
},
  "geometry": {"coordinates":[-75.077809,39.634423],"type":"Point"}
}