{
  "type": "Feature",
  "properties": {
    "addr:full":"5 Stearns Ter Denville NJ 07834",
    "addr:housenumber":"5",
    "addr:postcode":"07834",
    "addr:street":"Stearns Ter",
    "iso:country":"US",
    "sg:address":"5 Stearns Ter",
    "sg:city":"Denville",
    "sg:classifiers":[
        {
            "category":"Wholesale",
            "subcategory":"Durable Goods & Equipment",
            "type":"Manufacturing & Wholesale Goods"
        }
    ],
    "sg:phone":"+1 973 442 8359",
    "sg:postcode":"07834",
    "sg:province":"NJ",
    "sg:tags":[
        "mill",
        "product",
        "imported",
        "brass",
        "nonferrous"
    ],
    "wof:name":"Wieland-America Inc",
    "wof:placetype":"venue"
},
  "geometry": {"coordinates":[-74.52489,40.850361],"type":"Point"}
}