{
  "type": "Feature",
  "properties": {
    "iso:country":"US",
    "sg:address":"1089 Stuyvesant Ave",
    "sg:city":"Irvington",
    "sg:classifiers":[
        {
            "category":"Personal",
            "subcategory":"Beauty Salon",
            "type":"Services"
        }
    ],
    "sg:phone":"+1 973 399 1254",
    "sg:postcode":"07111",
    "sg:province":"NJ",
    "sg:tags":[
        "shop"
    ],
    "wof:name":"Fine Thngs By Darlene Matthews",
    "wof:placetype":"venue"
},
  "geometry": {"coordinates":[-74.252149,40.715085],"type":"Point"}
}