{
  "type": "Feature",
  "properties": {
    "iso:country":"US",
    "sg:address":"427 Co Hwy 513 N",
    "sg:city":"Califon",
    "sg:classifiers":[
        {
            "category":"Restaurant",
            "type":"Food & Drink"
        }
    ],
    "sg:phone":"+1 908 832 0024",
    "sg:postcode":"07830",
    "sg:province":"NJ",
    "sg:tags":[
        "pizza",
        "italian"
    ],
    "wof:name":"Nicola Pizza",
    "wof:placetype":"venue"
},
  "geometry": {"coordinates":[-74.84637499999999,40.725146],"type":"Point"}
}