{
  "type": "Feature",
  "properties": {
    "iso:country":"US",
    "sg:address":"114 Ellison St",
    "sg:city":"Paterson",
    "sg:classifiers":[
        {
            "category":"Shopping",
            "subcategory":"Florist",
            "type":"Retail Goods"
        }
    ],
    "sg:phone":"+1 973 742 6150",
    "sg:postcode":"07505",
    "sg:province":"NJ",
    "wof:name":"James Smith Florist",
    "wof:placetype":"venue"
},
  "geometry": {"coordinates":[-74.172496,40.917275],"type":"Point"}
}