{
  "type": "Feature",
  "properties": {
    "addr:full":"154 Lincoln Ave Orange NJ 07050",
    "addr:housenumber":"154",
    "addr:postcode":"07050",
    "addr:street":"Lincoln Ave",
    "iso:country":"US",
    "sg:address":"154 Lincoln Ave",
    "sg:city":"Orange",
    "sg:classifiers":[
        {
            "category":"Professional",
            "type":"Services"
        }
    ],
    "sg:phone":"+1 973 395 1730",
    "sg:postcode":"07050",
    "sg:province":"NJ",
    "sg:tags":[
        "establishment"
    ],
    "wof:name":"Coram J Rimes Election Fund",
    "wof:placetype":"venue"
},
  "geometry": {"coordinates":[-74.235998,40.769785],"type":"Point"}
}