{
  "type": "Feature",
  "properties": {
    "addr:full":"114 Flock Rd Trenton NJ 08619",
    "addr:housenumber":"114",
    "addr:postcode":"08619",
    "addr:street":"Flock Rd",
    "iso:country":"US",
    "sg:address":"114 Flock Rd",
    "sg:city":"Trenton",
    "sg:classifiers":[
        {
            "category":"Retail",
            "subcategory":"Laundry & Dry Cleaning",
            "type":"Services"
        }
    ],
    "sg:phone":"+1   ",
    "sg:postcode":"08619",
    "sg:province":"NJ",
    "sg:tags":[
        "drycleaning",
        "plant"
    ],
    "wof:name":"Sainte Marie Cleaners",
    "wof:placetype":"venue"
},
  "geometry": {"coordinates":[-74.682834,40.249059],"type":"Point"}
}