{
  "type": "Feature",
  "properties": {
    "iso:country":"US",
    "sg:address":"960 Ferry Ave",
    "sg:city":"Camden",
    "sg:classifiers":[
        {
            "category":"Restaurant",
            "type":"Food & Drink"
        }
    ],
    "sg:phone":"+1 856 541 6008",
    "sg:postcode":"08104",
    "sg:province":"NJ",
    "sg:tags":[
        "eating"
    ],
    "wof:name":"Fu Hing Restaurant",
    "wof:placetype":"venue"
},
  "geometry": {"coordinates":[-75.10900100000001,39.919601],"type":"Point"}
}