{
  "type": "Feature",
  "properties": {
    "addr:full":"160 Passaic Ave Kearny NJ 07032",
    "addr:housenumber":"160",
    "addr:postcode":"07032",
    "addr:street":"Passaic Ave",
    "iso:country":"US",
    "sg:address":"160 Passaic Ave",
    "sg:city":"Kearny",
    "sg:classifiers":[
        {
            "category":"Professional",
            "type":"Services"
        }
    ],
    "sg:phone":"+1 201 998 5569",
    "sg:postcode":"07032",
    "sg:province":"NJ",
    "wof:name":"Professional Services",
    "wof:placetype":"venue"
},
  "geometry": {"coordinates":[-74.160295,40.759954],"type":"Point"}
}