{
  "type": "Feature",
  "properties": {
    "iso:country":"US",
    "sg:address":"25 Oakbrook Pl",
    "sg:city":"Somerset",
    "sg:classifiers":[
        {
            "category":"Social Services",
            "type":"Services"
        }
    ],
    "sg:phone":"+1 732 246 8484",
    "sg:postcode":"08873",
    "sg:province":"NJ",
    "sg:website":"www.drmartytashman.com",
    "wof:name":"Central Jersey Counseling Svcs",
    "wof:placetype":"venue"
},
  "geometry": {"coordinates":[-74.46807200000001,40.500189],"type":"Point"}
}