{
  "type": "Feature",
  "properties": {
    "iso:country":"US",
    "sg:address":"599 Chestnut St",
    "sg:city":"Union",
    "sg:classifiers":[
        {
            "category":"Retail",
            "subcategory":"Repair Shop",
            "type":"Services"
        }
    ],
    "sg:phone":"+1   ",
    "sg:postcode":"07083",
    "sg:province":"NJ",
    "wof:name":"24 Hour Locksmith",
    "wof:placetype":"venue"
},
  "geometry": {"coordinates":[-74.269201,40.68513],"type":"Point"}
}