{
  "type": "Feature",
  "properties": {
    "addr:full":"50 State Rte 31 Washington NJ 07882",
    "addr:housenumber":"50",
    "addr:postcode":"07882",
    "addr:street":"State Rte 31",
    "iso:country":"US",
    "sg:address":"50 State Rte 31",
    "sg:city":"Washington",
    "sg:classifiers":[
        {
            "category":"Retail",
            "subcategory":"Repair Shop",
            "type":"Services"
        }
    ],
    "sg:phone":"+1   ",
    "sg:postcode":"07882",
    "sg:province":"NJ",
    "wof:name":"24 Hour Emergency Locksmith",
    "wof:placetype":"venue"
},
  "geometry": {"coordinates":[-74.97634100000001,40.761958],"type":"Point"}
}