{
  "type": "Feature",
  "properties": {
    "iso:country":"US",
    "sg:address":"555 N Egg Harbor Rd",
    "sg:city":"Hammonton",
    "sg:classifiers":[
        {
            "category":"Building & Trades",
            "subcategory":"Construction",
            "type":"Services"
        }
    ],
    "sg:phone":"+1 609 567 6404",
    "sg:postcode":"08037",
    "sg:province":"NJ",
    "sg:tags":[
        "general",
        "contractor"
    ],
    "wof:name":"Shore Building Contractor",
    "wof:placetype":"venue"
},
  "geometry": {"coordinates":[-74.818234,39.643116],"type":"Point"}
}