{
  "type": "Feature",
  "properties": {
    "addr:full":"299 N 8th St Prospect Park NJ 07508",
    "addr:housenumber":"299",
    "addr:postcode":"07508",
    "addr:street":"N 8Th St",
    "iso:country":"US",
    "sg:address":"299 N 8th St",
    "sg:city":"Prospect Park",
    "sg:classifiers":[
        {
            "category":"Restaurant",
            "type":"Food & Drink"
        }
    ],
    "sg:phone":"+1 973 595 1412",
    "sg:postcode":"07508",
    "sg:province":"NJ",
    "wof:name":"Carousel Pizzeria",
    "wof:placetype":"venue"
},
  "geometry": {"coordinates":[-74.17080799999999,40.934625],"type":"Point"}
}