{
  "type": "Feature",
  "properties": {
    "iso:country":"US",
    "sg:address":"17 Ridge Ave",
    "sg:city":"Sayreville",
    "sg:classifiers":[
        {
            "category":"Building & Trades",
            "subcategory":"Construction",
            "type":"Services"
        }
    ],
    "sg:phone":"+1 732 613 2665",
    "sg:postcode":"08872",
    "sg:province":"NJ",
    "sg:tags":[
        "house"
    ],
    "wof:name":"S A Homeworks",
    "wof:placetype":"venue"
},
  "geometry": {"coordinates":[-74.343221,40.45827],"type":"Point"}
}