{
  "type": "Feature",
  "properties": {
    "addr:full":"80 Thomas St Paterson NJ 07503",
    "addr:housenumber":"80",
    "addr:postcode":"07503",
    "addr:street":"Thomas St",
    "iso:country":"US",
    "sg:address":"80 Thomas St",
    "sg:city":"Paterson",
    "sg:classifiers":[
        {
            "category":"Wholesale",
            "subcategory":"Machinery & Supplies",
            "type":"Manufacturing & Wholesale Goods"
        }
    ],
    "sg:phone":"+1 973 523 5903",
    "sg:postcode":"07503",
    "sg:province":"NJ",
    "sg:tags":[
        "equipment"
    ],
    "wof:name":"Zap Electrical Contractor",
    "wof:placetype":"venue"
},
  "geometry": {"coordinates":[-74.157348,40.897111],"type":"Point"}
}