{
  "type": "Feature",
  "properties": {
    "iso:country":"US",
    "sg:address":"589 Rues Ln",
    "sg:city":"East Brunswick",
    "sg:classifiers":[
        {
            "category":"Building & Trades",
            "subcategory":"Landscaping Services",
            "type":"Services"
        }
    ],
    "sg:phone":"+1 732 238 4564",
    "sg:postcode":"08816",
    "sg:province":"NJ",
    "wof:name":"Valley View Landscaping",
    "wof:placetype":"venue"
},
  "geometry": {"coordinates":[-74.415634,40.416871],"type":"Point"}
}