{
  "type": "Feature",
  "properties": {
    "addr:full":"1124 Stanton Lebanon Rd Lebanon NJ 08833",
    "addr:housenumber":"1124",
    "addr:postcode":"08833",
    "addr:street":"Stanton Lebanon Rd",
    "iso:country":"US",
    "sg:address":"1124 Stanton Lebanon Rd",
    "sg:city":"Lebanon",
    "sg:classifiers":[
        {
            "category":"Social Services",
            "type":"Services"
        }
    ],
    "sg:phone":"+1 908 236 6885",
    "sg:postcode":"08833",
    "sg:province":"NJ",
    "sg:tags":[
        "youth",
        "organization",
        "center"
    ],
    "wof:name":"Round Valley Youth Ctr",
    "wof:placetype":"venue"
},
  "geometry": {"coordinates":[-74.849284,40.609273],"type":"Point"}
}