{
  "type": "Feature",
  "properties": {
    "iso:country":"US",
    "sg:address":"5 S Pavilion Ave",
    "sg:city":"Riverside",
    "sg:classifiers":[
        {
            "category":"Professional",
            "subcategory":"Lawyer & Legal Services",
            "type":"Services"
        }
    ],
    "sg:phone":"+1 856 461 9191",
    "sg:postcode":"08075",
    "sg:province":"NJ",
    "wof:name":"Galdo Francis R Attorney",
    "wof:placetype":"venue"
},
  "geometry": {"coordinates":[-74.959503,40.038399],"type":"Point"}
}