{
  "type": "Feature",
  "properties": {
    "iso:country":"US",
    "sg:address":"696 Palisade Ave",
    "sg:city":"Teaneck",
    "sg:classifiers":[
        {
            "category":"Professional",
            "subcategory":"Accounting & Tax Preparation",
            "type":"Services"
        }
    ],
    "sg:phone":"+1 201 692 8188",
    "sg:postcode":"07666",
    "sg:province":"NJ",
    "sg:tags":[
        "accountant"
    ],
    "wof:name":"Friedbauer Robert L CPA",
    "wof:placetype":"venue"
},
  "geometry": {"coordinates":[-74.02069899999999,40.8857],"type":"Point"}
}