{
  "type": "Feature",
  "properties": {
    "iso:country":"US",
    "sg:address":"810 Gebhardt Ave",
    "sg:city":"Elizabeth",
    "sg:classifiers":[
        {
            "category":"Building & Trades",
            "subcategory":"Construction",
            "type":"Services"
        }
    ],
    "sg:phone":"+1 908 354 4435",
    "sg:postcode":"07208",
    "sg:province":"NJ",
    "wof:name":"Bozzo Claudio & Son",
    "wof:placetype":"venue"
},
  "geometry": {"coordinates":[-74.23556499999999,40.674665],"type":"Point"}
}