{
  "type": "Feature",
  "properties": {
    "addr:full":"144 Avon Ave Newark NJ 07108",
    "addr:housenumber":"144",
    "addr:postcode":"07108",
    "addr:street":"Avon Ave",
    "iso:country":"US",
    "sg:address":"144 Avon Ave",
    "sg:city":"Newark",
    "sg:classifiers":[
        {
            "category":"Building & Trades",
            "subcategory":"Locksmith",
            "type":"Services"
        }
    ],
    "sg:phone":"+1 973 854 4784",
    "sg:postcode":"07108",
    "sg:province":"NJ",
    "sg:tags":[
        "key"
    ],
    "wof:name":"0 & 0 24 Hour Locksmith",
    "wof:placetype":"venue"
},
  "geometry": {"coordinates":[-74.195758,40.724396],"type":"Point"}
}