{
  "type": "Feature",
  "properties": {
    "iso:country":"US",
    "sg:address":"45 N Stockton St",
    "sg:city":"Trenton",
    "sg:classifiers":[
        {
            "category":"Food & Beverages",
            "subcategory":"Groceries & Convenience Stores",
            "type":"Retail Goods"
        }
    ],
    "sg:phone":"+1 609 989 1464",
    "sg:postcode":"08618",
    "sg:province":"NJ",
    "sg:tags":[
        "grocer"
    ],
    "wof:name":"Torres Deli Grocery",
    "wof:placetype":"venue"
},
  "geometry": {"coordinates":[-74.76042700000001,40.222744],"type":"Point"}
}