{
  "type": "Feature",
  "properties": {
    "iso:country":"US",
    "sg:address":"107 Westwood Ave",
    "sg:city":"Westwood",
    "sg:classifiers":[
        {
            "category":"Food & Beverages",
            "subcategory":"Candy",
            "type":"Retail Goods"
        }
    ],
    "sg:phone":"+1   ",
    "sg:postcode":"07675",
    "sg:province":"NJ",
    "sg:tags":[
        "luncheonette",
        "confectionery"
    ],
    "wof:name":"Conrads Confectionery Inc",
    "wof:placetype":"venue"
},
  "geometry": {"coordinates":[-74.03163499999999,40.991821],"type":"Point"}
}