{
  "type": "Feature",
  "properties": {
    "iso:country":"US",
    "sg:address":"110 4th Ave",
    "sg:city":"Roebling",
    "sg:classifiers":[
        {
            "category":"Professional",
            "subcategory":"Business Services",
            "type":"Services"
        }
    ],
    "sg:phone":"+1   ",
    "sg:postcode":"08554",
    "sg:province":"NJ",
    "wof:name":"B & P Business System",
    "wof:placetype":"venue"
},
  "geometry": {"coordinates":[-74.77502,40.116851],"type":"Point"}
}