{
  "type": "Feature",
  "properties": {
    "addr:full":"126 State St Hackensack NJ 07601",
    "addr:housenumber":"126",
    "addr:postcode":"07601",
    "addr:street":"State St",
    "iso:country":"US",
    "sg:address":"126 State St",
    "sg:city":"Hackensack",
    "sg:classifiers":[
        {
            "category":"Professional",
            "subcategory":"Lawyer & Legal Services",
            "type":"Services"
        }
    ],
    "sg:phone":"+1 201 342 3038",
    "sg:postcode":"07601",
    "sg:province":"NJ",
    "sg:tags":[
        "attorney"
    ],
    "wof:name":"Pisarri McEnroe & Careri",
    "wof:placetype":"venue"
},
  "geometry": {"coordinates":[-74.045303,40.882401],"type":"Point"}
}