{
  "type": "Feature",
  "properties": {
    "iso:country":"US",
    "sg:address":"10 State Rte 27",
    "sg:city":"Edison",
    "sg:classifiers":[
        {
            "category":"Health Services",
            "subcategory":"Doctor",
            "type":"Services"
        }
    ],
    "sg:phone":"+1 732 494 5252",
    "sg:postcode":"08820",
    "sg:province":"NJ",
    "wof:name":"Howard D Dimond DDS",
    "wof:placetype":"venue"
},
  "geometry": {"coordinates":[-74.345636,40.555609],"type":"Point"}
}