{
  "type": "Feature",
  "properties": {
    "iso:country":"US",
    "sg:address":"51 Albany Ave",
    "sg:city":"Nutley",
    "sg:classifiers":[
        {
            "category":"Building & Trades",
            "subcategory":"Plumbing",
            "type":"Services"
        }
    ],
    "sg:phone":"+1 973 667 7816",
    "sg:postcode":"07110",
    "sg:province":"NJ",
    "sg:website":"www.mcmillanplumbing.com",
    "wof:name":"McMillan Plumbing & Heating",
    "wof:placetype":"venue"
},
  "geometry": {"coordinates":[-74.167008,40.810886],"type":"Point"}
}