{
  "type": "Feature",
  "properties": {
    "iso:country":"US",
    "sg:address":"1800 State Rte 33",
    "sg:city":"Trenton",
    "sg:classifiers":[
        {
            "category":"Shopping",
            "type":"Retail Goods"
        }
    ],
    "sg:phone":"+1 609 584 8100",
    "sg:postcode":"08690",
    "sg:province":"NJ",
    "sg:tags":[
        "stamp",
        "collector",
        "for"
    ],
    "wof:name":"Trenton Stamp & Coin Co",
    "wof:placetype":"venue"
},
  "geometry": {"coordinates":[-74.650693,40.224289],"type":"Point"}
}