{
  "type": "Feature",
  "properties": {
    "iso:country":"US",
    "sg:address":"539 Durie Ave",
    "sg:city":"Closter",
    "sg:classifiers":[
        {
            "category":"Health Services",
            "subcategory":"Doctor",
            "type":"Services"
        }
    ],
    "sg:phone":"+1 201 767 3666",
    "sg:postcode":"07624",
    "sg:province":"NJ",
    "sg:tags":[
        "dentist"
    ],
    "wof:name":"Bergen Healthcare LLC",
    "wof:placetype":"venue"
},
  "geometry": {"coordinates":[-73.961623,40.972841],"type":"Point"}
}