{
  "type": "Feature",
  "properties": {
    "iso:country":"US",
    "sg:address":"227 Richmond Ave",
    "sg:city":"New Milford",
    "sg:classifiers":[
        {
            "category":"Manufacturing",
            "subcategory":"Signs",
            "type":"Manufacturing & Wholesale Goods"
        }
    ],
    "sg:phone":"+1 201 801 0606",
    "sg:postcode":"07646",
    "sg:province":"NJ",
    "sg:tags":[
        "specialty",
        "mfg"
    ],
    "wof:name":"Dave Letter Man",
    "wof:placetype":"venue"
},
  "geometry": {"coordinates":[-74.025852,40.919676],"type":"Point"}
}