{
  "type": "Feature",
  "properties": {
    "iso:country":"US",
    "sg:address":"15 Pleasant View Rd",
    "sg:city":"Lebanon",
    "sg:classifiers":[
        {
            "category":"Manufacturing",
            "subcategory":"Printing",
            "type":"Manufacturing & Wholesale Goods"
        }
    ],
    "sg:phone":"+1 908 236 9028",
    "sg:postcode":"08833",
    "sg:province":"NJ",
    "sg:tags":[
        "publishing"
    ],
    "wof:name":"Hpt Aero Publishing",
    "wof:placetype":"venue"
},
  "geometry": {"coordinates":[-74.839665,40.583416],"type":"Point"}
}