{
  "type": "Feature",
  "properties": {
    "addr:full":"1271 Glassboro Rd Williamstown NJ 08094",
    "addr:housenumber":"1271",
    "addr:postcode":"08094",
    "addr:street":"Glassboro Rd",
    "iso:country":"US",
    "sg:address":"1271 Glassboro Rd",
    "sg:city":"Williamstown",
    "sg:classifiers":[
        {
            "category":"Wholesale",
            "subcategory":"Construction Materials",
            "type":"Manufacturing & Wholesale Goods"
        }
    ],
    "sg:phone":"+1 856 728 0171",
    "sg:postcode":"08094",
    "sg:province":"NJ",
    "sg:tags":[
        "prefabricated",
        "structure"
    ],
    "sg:website":"www.caterinasupply.com",
    "wof:name":"Caterina Supply Inc",
    "wof:placetype":"venue"
},
  "geometry": {"coordinates":[-75.037941,39.692589],"type":"Point"}
}