{
  "type": "Feature",
  "properties": {
    "iso:country":"US",
    "sg:address":"1547 Co Rd 565",
    "sg:city":"Sussex",
    "sg:classifiers":[
        {
            "category":"Government",
            "subcategory":"Office",
            "type":"Public Place"
        }
    ],
    "sg:phone":"+1 973 702 7266",
    "sg:postcode":"07461",
    "sg:province":"NJ",
    "sg:tags":[
        "federal"
    ],
    "wof:name":"US Fish & Wildlife Svc",
    "wof:placetype":"venue"
},
  "geometry": {"coordinates":[-74.56129300000001,41.203389],"type":"Point"}
}