{
  "type": "Feature",
  "properties": {
    "addr:full":"233 W Parkway Pompton Plains NJ 07444",
    "addr:housenumber":"233",
    "addr:postcode":"07444",
    "addr:street":"W Parkway",
    "iso:country":"US",
    "sg:address":"233 W Parkway",
    "sg:city":"Pompton Plains",
    "sg:classifiers":[
        {
            "category":"Building & Trades",
            "subcategory":"Pest Control",
            "type":"Services"
        }
    ],
    "sg:phone":"+1 973 616 6200",
    "sg:postcode":"07444",
    "sg:province":"NJ",
    "wof:name":"Precise Termite & Pest Control",
    "wof:placetype":"venue"
},
  "geometry": {"coordinates":[-74.311975,40.980073],"type":"Point"}
}