{
  "type": "Feature",
  "properties": {
    "iso:country":"US",
    "sg:address":"410 Arnold Ave",
    "sg:city":"Pt Pleasant Bch",
    "sg:classifiers":[
        {
            "category":"Government",
            "subcategory":"Post Office",
            "type":"Public Place"
        }
    ],
    "sg:phone":"+1 732 899 4250",
    "sg:postcode":"08742",
    "sg:province":"NJ",
    "sg:website":"www.usps.gov",
    "wof:name":"US Post Office",
    "wof:placetype":"venue"
},
  "geometry": {"coordinates":[-74.046127,40.09202],"type":"Point"}
}