{
  "type": "Feature",
  "properties": {
    "iso:country":"US",
    "sg:address":"180 State Rte 35",
    "sg:city":"Eatontown",
    "sg:classifiers":[
        {
            "category":"Personal",
            "subcategory":"Beauty Salon",
            "type":"Services"
        }
    ],
    "sg:phone":"+1 732 542 7280",
    "sg:postcode":"07724",
    "sg:province":"NJ",
    "sg:tags":[
        "manicuring"
    ],
    "wof:name":"Nail Pro Beauty Spa",
    "wof:placetype":"venue"
},
  "geometry": {"coordinates":[-74.051393,40.289449],"type":"Point"}
}