{
  "type": "Feature",
  "properties": {
    "addr:full":"75 Main St Millburn NJ 07041",
    "addr:housenumber":"75",
    "addr:postcode":"07041",
    "addr:street":"Main St",
    "iso:country":"US",
    "sg:address":"75 Main St",
    "sg:city":"Millburn",
    "sg:classifiers":[
        {
            "category":"Professional",
            "subcategory":"Lawyer & Legal Services",
            "type":"Services"
        }
    ],
    "sg:phone":"+1 973 376 6200",
    "sg:postcode":"07041",
    "sg:province":"NJ",
    "sg:tags":[
        "attorney"
    ],
    "wof:name":"Stephen H Schechner Law Office",
    "wof:placetype":"venue"
},
  "geometry": {"coordinates":[-74.307202,40.723794],"type":"Point"}
}