{
  "type": "Feature",
  "properties": {
    "iso:country":"US",
    "sg:address":"445 Cedar Ln",
    "sg:city":"Teaneck",
    "sg:classifiers":[
        {
            "category":"Restaurant",
            "type":"Food & Drink"
        }
    ],
    "sg:phone":"+1   ",
    "sg:postcode":"07666",
    "sg:province":"NJ",
    "sg:tags":[
        "eating"
    ],
    "wof:name":"Sitar Palace Inc",
    "wof:placetype":"venue"
},
  "geometry": {"coordinates":[-74.02174599999999,40.889078],"type":"Point"}
}