{
  "type": "Feature",
  "properties": {
    "addr:full":"157 Cokesbury Rd Lebanon NJ 08833",
    "addr:housenumber":"157",
    "addr:postcode":"08833",
    "addr:street":"Cokesbury Rd",
    "iso:country":"US",
    "sg:address":"157 Cokesbury Rd",
    "sg:city":"Lebanon",
    "sg:classifiers":[
        {
            "category":"Professional",
            "type":"Services"
        }
    ],
    "sg:phone":"+1   ",
    "sg:postcode":"08833",
    "sg:province":"NJ",
    "wof:name":"Thomas C Kelly",
    "wof:placetype":"venue"
},
  "geometry": {"coordinates":[-74.82772799999999,40.662108],"type":"Point"}
}