{
  "type": "Feature",
  "properties": {
    "addr:full":"165 Cedar Lake Rd Denville NJ 07834",
    "addr:housenumber":"165",
    "addr:postcode":"07834",
    "addr:street":"Cedar Lake Rd",
    "iso:country":"US",
    "sg:address":"165 Cedar Lake Rd",
    "sg:city":"Denville",
    "sg:classifiers":[
        {
            "category":"Professional",
            "subcategory":"Computer Services",
            "type":"Services"
        }
    ],
    "sg:phone":"+1   ",
    "sg:postcode":"07834",
    "sg:province":"NJ",
    "sg:tags":[
        "datum"
    ],
    "wof:name":"Ross McPherson",
    "wof:placetype":"venue"
},
  "geometry": {"coordinates":[-74.47797300000001,40.904699],"type":"Point"}
}