{
  "type": "Feature",
  "properties": {
    "addr:full":"2530 Hooper Ave Brick NJ 08723",
    "addr:housenumber":"2530",
    "addr:postcode":"08723",
    "addr:street":"Hooper Ave",
    "iso:country":"US",
    "sg:address":"2530 Hooper Ave",
    "sg:city":"Brick",
    "sg:classifiers":[
        {
            "category":"Shopping",
            "subcategory":"Gifts & Souvenirs",
            "type":"Retail Goods"
        }
    ],
    "sg:phone":"+1   ",
    "sg:postcode":"08723",
    "sg:province":"NJ",
    "sg:tags":[
        "shop",
        "card"
    ],
    "wof:name":"Wishing Well Gifts LLC",
    "wof:placetype":"venue"
},
  "geometry": {"coordinates":[-74.127887,40.044111],"type":"Point"}
}