{
  "type": "Feature",
  "properties": {
    "iso:country":"US",
    "sg:address":"418 14th St",
    "sg:city":"Union City",
    "sg:classifiers":[
        {
            "category":"Home & Garden",
            "subcategory":"Furniture",
            "type":"Retail Goods"
        }
    ],
    "sg:phone":"+1   ",
    "sg:postcode":"07087",
    "sg:province":"NJ",
    "wof:name":"JP Trucking",
    "wof:placetype":"venue"
},
  "geometry": {"coordinates":[-74.03652599999999,40.760998],"type":"Point"}
}