{
  "type": "Feature",
  "properties": {
    "iso:country":"US",
    "sg:address":"12 Morris Dr",
    "sg:city":"Hillsdale",
    "sg:classifiers":[
        {
            "category":"Organizations",
            "subcategory":"Community Association",
            "type":"Services"
        }
    ],
    "sg:phone":"+1 201 488 9829",
    "sg:postcode":"07642",
    "sg:province":"NJ",
    "sg:tags":[
        "club"
    ],
    "wof:name":"Albanian American Club",
    "wof:placetype":"venue"
},
  "geometry": {"coordinates":[-74.049408,41.009308],"type":"Point"}
}