{
  "type": "Feature",
  "properties": {
    "addr:full":"7011 Pacific Ave Wildwood Crest NJ 08260",
    "addr:housenumber":"7011",
    "addr:postcode":"08260",
    "addr:street":"Pacific Ave",
    "iso:country":"US",
    "sg:address":"7011 Pacific Ave",
    "sg:city":"Wildwood Crest",
    "sg:classifiers":[
        {
            "category":"Professional",
            "subcategory":"Business Services",
            "type":"Services"
        }
    ],
    "sg:phone":"+1 609 729 7011",
    "sg:postcode":"08260",
    "sg:province":"NJ",
    "sg:tags":[
        "reservation",
        "motel",
        "hotel"
    ],
    "wof:name":"Mahi Mahi House",
    "wof:placetype":"venue"
},
  "geometry": {"coordinates":[-74.836822,38.972529],"type":"Point"}
}