{
  "type": "Feature",
  "properties": {
    "addr:full":"312 Ewan Rd Mullica Hill NJ 08062",
    "addr:housenumber":"312",
    "addr:postcode":"08062",
    "addr:street":"Ewan Rd",
    "iso:country":"US",
    "sg:address":"312 Ewan Rd",
    "sg:city":"Mullica Hill",
    "sg:classifiers":[
        {
            "category":"Government",
            "subcategory":"Fire Station",
            "type":"Public Place"
        }
    ],
    "sg:phone":"+1   ",
    "sg:postcode":"08062",
    "sg:province":"NJ",
    "sg:tags":[
        "prevention"
    ],
    "wof:name":"Harrison Township Bureau of FI",
    "wof:placetype":"venue"
},
  "geometry": {"coordinates":[-75.188917,39.698963],"type":"Point"}
}