{
  "type": "Feature",
  "properties": {
    "addr:full":"209 Ramapo Valley Rd Mahwah NJ 07430",
    "addr:housenumber":"209",
    "addr:postcode":"07430",
    "addr:street":"Ramapo Valley Rd",
    "iso:country":"US",
    "sg:address":"209 Ramapo Valley Rd",
    "sg:city":"Mahwah",
    "sg:classifiers":[
        {
            "category":"Restaurant",
            "type":"Food & Drink"
        }
    ],
    "sg:phone":"+1   ",
    "sg:postcode":"07430",
    "sg:province":"NJ",
    "sg:tags":[
        "eating"
    ],
    "wof:name":"River Palm Terrace",
    "wof:placetype":"venue"
},
  "geometry": {"coordinates":[-74.164176,41.096909],"type":"Point"}
}