{
  "type": "Feature",
  "properties": {
    "iso:country":"US",
    "sg:address":"132 Lewis St",
    "sg:city":"Eatontown",
    "sg:classifiers":[
        {
            "category":"Manufacturing",
            "subcategory":"Tools & Machinery",
            "type":"Manufacturing & Wholesale Goods"
        }
    ],
    "sg:phone":"+1 732 542 1157",
    "sg:postcode":"07724",
    "sg:province":"NJ",
    "sg:tags":[
        "machine",
        "shop",
        "parts",
        "precision",
        "mfg"
    ],
    "wof:name":"M & M Grinding LLC",
    "wof:placetype":"venue"
},
  "geometry": {"coordinates":[-74.06815899999999,40.301652],"type":"Point"}
}