{
  "type": "Feature",
  "properties": {
    "iso:country":"US",
    "sg:address":"84 Hudson Ave",
    "sg:city":"Maplewood",
    "sg:classifiers":[
        {
            "category":"Professional",
            "type":"Services"
        }
    ],
    "sg:phone":"+1   ",
    "sg:postcode":"07040",
    "sg:province":"NJ",
    "wof:name":"Pen Processing",
    "wof:placetype":"venue"
},
  "geometry": {"coordinates":[-74.25385300000001,40.733178],"type":"Point"}
}