{
  "type": "Feature",
  "properties": {
    "iso:country":"US",
    "sg:address":"201 Sumner Ave",
    "sg:city":"Seaside Heights",
    "sg:classifiers":[
        {
            "category":"Building & Trades",
            "subcategory":"Construction",
            "type":"Services"
        }
    ],
    "sg:phone":"+1 732 793 0478",
    "sg:postcode":"08751",
    "sg:province":"NJ",
    "sg:tags":[
        "general",
        "contractor"
    ],
    "wof:name":"Murph Construction",
    "wof:placetype":"venue"
},
  "geometry": {"coordinates":[-74.075422,39.941447],"type":"Point"}
}