{
  "type": "Feature",
  "properties": {
    "addr:full":"62 Fort Dix St Wrightstown NJ 08562",
    "addr:housenumber":"62",
    "addr:postcode":"08562",
    "addr:street":"Fort Dix St",
    "iso:country":"US",
    "sg:address":"62 Fort Dix St",
    "sg:city":"Wrightstown",
    "sg:classifiers":[
        {
            "category":"Restaurant",
            "type":"Food & Drink"
        }
    ],
    "sg:menulink":"http://www.allmenus.com/nj/wrightstown/183631-kfc---kentucky-fried-chicken/menu/",
    "sg:phone":"+1 609 723 1411",
    "sg:postcode":"08562",
    "sg:province":"NJ",
    "sg:tags":[
        "american",
        "chicken"
    ],
    "wof:name":"KFC - Kentucky Fried Chicken",
    "wof:placetype":"venue"
},
  "geometry": {"coordinates":[-74.617885,40.038354],"type":"Point"}
}