{
  "type": "Feature",
  "properties": {
    "iso:country":"US",
    "sg:address":"22 Wyckoff Ave",
    "sg:city":"Waldwick",
    "sg:classifiers":[
        {
            "category":"Health Services",
            "subcategory":"Doctor",
            "type":"Services"
        }
    ],
    "sg:phone":"+1 201 652 5499",
    "sg:postcode":"07463",
    "sg:province":"NJ",
    "sg:tags":[
        "dentist"
    ],
    "wof:name":"John E Aversa DDS",
    "wof:placetype":"venue"
},
  "geometry": {"coordinates":[-74.121514,41.008724],"type":"Point"}
}