{
  "type": "Feature",
  "properties": {
    "iso:country":"US",
    "sg:address":"1731 Main St",
    "sg:city":"Belmar",
    "sg:classifiers":[
        {
            "category":"Communications",
            "subcategory":"Radio Station",
            "type":"Services"
        }
    ],
    "sg:phone":"+1 732 530 1845",
    "sg:postcode":"07719",
    "sg:province":"NJ",
    "sg:tags":[
        "broadcast"
    ],
    "wof:name":"Wrat Radio 959 FM",
    "wof:placetype":"venue"
},
  "geometry": {"coordinates":[-74.0275,40.17089],"type":"Point"}
}