{
  "type": "Feature",
  "properties": {
    "addr:full":"128 72nd St North Bergen NJ 07047",
    "addr:housenumber":"128",
    "addr:postcode":"07047",
    "addr:street":"72Nd St",
    "iso:country":"US",
    "sg:address":"128 72nd St",
    "sg:city":"North Bergen",
    "sg:classifiers":[
        {
            "category":"Professional",
            "type":"Services"
        }
    ],
    "sg:phone":"+1   ",
    "sg:postcode":"07047",
    "sg:province":"NJ",
    "wof:name":"800 Central Ave Corp",
    "wof:placetype":"venue"
},
  "geometry": {"coordinates":[-74.00401100000001,40.794541],"type":"Point"}
}