{
  "type": "Feature",
  "properties": {
    "addr:full":"615 Franklin Tpke Ridgewood NJ 07450",
    "addr:housenumber":"615",
    "addr:postcode":"07450",
    "addr:street":"Franklin Tpke",
    "iso:country":"US",
    "sg:address":"615 Franklin Tpke",
    "sg:city":"Ridgewood",
    "sg:classifiers":[
        {
            "category":"Professional",
            "subcategory":"Management & Consulting",
            "type":"Services"
        },
        {
            "category":"Professional",
            "subcategory":"Accounting & Tax Preparation",
            "type":"Services"
        }
    ],
    "sg:phone":"+1 201 612 8855",
    "sg:postcode":"07450",
    "sg:province":"NJ",
    "sg:tags":[
        "accountant",
        "business"
    ],
    "sg:website":"www.aafinance.net",
    "wof:name":"Anderson & Anderson",
    "wof:placetype":"venue"
},
  "geometry": {"coordinates":[-74.09514900000001,40.987467],"type":"Point"}
}