{
  "type": "Feature",
  "properties": {
    "addr:full":"5527 Bergenline Pl West New York NJ 07093",
    "addr:housenumber":"5527",
    "addr:postcode":"07093",
    "addr:street":"Bergenline Pl West",
    "iso:country":"US",
    "sg:address":"5527 Bergenline Pl",
    "sg:city":"West New York",
    "sg:classifiers":[
        {
            "category":"Shopping",
            "type":"Retail Goods"
        }
    ],
    "sg:phone":"+1 201 223 5393",
    "sg:postcode":"07093",
    "sg:province":"NJ",
    "sg:tags":[
        "durable",
        "merchandise"
    ],
    "wof:name":"Beeper One Inc",
    "wof:placetype":"venue"
},
  "geometry": {"coordinates":[-74.01828999999999,40.786341],"type":"Point"}
}