{
  "type": "Feature",
  "properties": {
    "addr:full":"87 Springdale Ave Newark NJ 07107",
    "addr:housenumber":"87",
    "addr:postcode":"07107",
    "addr:street":"Springdale Ave",
    "iso:country":"US",
    "sg:address":"87 Springdale Ave",
    "sg:city":"Newark",
    "sg:classifiers":[
        {
            "category":"Wholesale",
            "subcategory":"Construction Materials",
            "type":"Manufacturing & Wholesale Goods"
        },
        {
            "category":"Manufacturing",
            "subcategory":"Metals",
            "type":"Manufacturing & Wholesale Goods"
        }
    ],
    "sg:phone":"+1 973 481 4424",
    "sg:postcode":"07107",
    "sg:province":"NJ",
    "sg:tags":[
        "trim",
        "a",
        "door",
        "gates",
        "mfg",
        "contractor",
        "sash",
        "carpentry"
    ],
    "wof:name":"Guardrite Steel Door Corp",
    "wof:placetype":"venue"
},
  "geometry": {"coordinates":[-74.191158,40.765031],"type":"Point"}
}