{
  "type": "Feature",
  "properties": {
    "iso:country":"US",
    "sg:address":"106 Schraalenburgh Rd",
    "sg:city":"Harrington Park",
    "sg:classifiers":[
        {
            "category":"Retail",
            "subcategory":"Auto Repair",
            "type":"Services"
        }
    ],
    "sg:phone":"+1 201 767 1184",
    "sg:postcode":"07640",
    "sg:province":"NJ",
    "sg:tags":[
        "repairing",
        "automobile"
    ],
    "wof:name":"Euro Automotive",
    "wof:placetype":"venue"
},
  "geometry": {"coordinates":[-73.977885,40.982465],"type":"Point"}
}