{
  "type": "Feature",
  "properties": {
    "addr:full":"13 Walnut Ave Cranford NJ 07016",
    "addr:housenumber":"13",
    "addr:postcode":"07016",
    "addr:street":"Walnut Ave",
    "iso:country":"US",
    "sg:address":"13 Walnut Ave",
    "sg:city":"Cranford",
    "sg:classifiers":[
        {
            "category":"Insurance",
            "subcategory":"Health Insurance",
            "type":"Services"
        }
    ],
    "sg:phone":"+1 908 276 4270",
    "sg:postcode":"07016",
    "sg:province":"NJ",
    "sg:tags":[
        "market"
    ],
    "wof:name":"Back To Nature Health Foods",
    "wof:placetype":"venue"
},
  "geometry": {"coordinates":[-74.30439800000001,40.6548],"type":"Point"}
}