{
  "type": "Feature",
  "properties": {
    "iso:country":"US",
    "sg:address":"1 Slater Dr",
    "sg:city":"Elizabeth",
    "sg:classifiers":[
        {
            "category":"Freight",
            "type":"Transportation"
        }
    ],
    "sg:phone":"+1 908 355 8200",
    "sg:postcode":"07206",
    "sg:province":"NJ",
    "wof:name":"Admiral Air Express",
    "wof:placetype":"venue"
},
  "geometry": {"coordinates":[-74.17943,40.652619],"type":"Point"}
}