{
  "type": "Feature",
  "properties": {
    "iso:country":"US",
    "sg:address":"1055 River Rd",
    "sg:city":"Edgewater",
    "sg:classifiers":[
        {
            "category":"Professional",
            "subcategory":"Employment Agencies",
            "type":"Services"
        }
    ],
    "sg:phone":"+1   ",
    "sg:postcode":"07020",
    "sg:province":"NJ",
    "wof:name":"Nubiz Fusion",
    "wof:placetype":"venue"
},
  "geometry": {"coordinates":[-73.97239399999999,40.832778],"type":"Point"}
}