{
  "type": "Feature",
  "properties": {
    "addr:full":"818 Tinton Ave Tinton Falls NJ 07724",
    "addr:housenumber":"818",
    "addr:postcode":"07724",
    "addr:street":"Tinton Ave",
    "iso:country":"US",
    "sg:address":"818 Tinton Ave",
    "sg:city":"Tinton Falls",
    "sg:classifiers":[
        {
            "category":"Social Services",
            "subcategory":"Child Care",
            "type":"Services"
        }
    ],
    "sg:phone":"+1 732 542 7447",
    "sg:postcode":"07724",
    "sg:province":"NJ",
    "sg:tags":[
        "kindergarten",
        "academic",
        "school"
    ],
    "wof:name":"Luther Memorial Christian",
    "wof:placetype":"venue"
},
  "geometry": {"coordinates":[-74.104724,40.306396],"type":"Point"}
}