{
  "type": "Feature",
  "properties": {
    "addr:full":"190 Passaic St Passaic NJ 07055",
    "addr:housenumber":"190",
    "addr:postcode":"07055",
    "addr:street":"Passaic St",
    "iso:country":"US",
    "sg:address":"190 Passaic St",
    "sg:city":"Passaic",
    "sg:classifiers":[
        {
            "category":"Home & Garden",
            "subcategory":"Furniture",
            "type":"Retail Goods"
        }
    ],
    "sg:phone":"+1 973 365 0711",
    "sg:postcode":"07055",
    "sg:province":"NJ",
    "sg:tags":[
        "equipment",
        "kitchen",
        "cabinet"
    ],
    "wof:name":"Exclusive Kitchen Cabinets",
    "wof:placetype":"venue"
},
  "geometry": {"coordinates":[-74.1183,40.862031],"type":"Point"}
}