{
  "type": "Feature",
  "properties": {
    "iso:country":"US",
    "sg:address":"998 Madison Ave",
    "sg:city":"Paterson",
    "sg:classifiers":[
        {
            "category":"Professional",
            "subcategory":"Lawyer & Legal Services",
            "type":"Services"
        }
    ],
    "sg:phone":"+1 973 345 9420",
    "sg:postcode":"07501",
    "sg:province":"NJ",
    "sg:tags":[
        "firm",
        "law"
    ],
    "wof:name":"Ramires  Torres & Martinez LLP",
    "wof:placetype":"venue"
},
  "geometry": {"coordinates":[-74.15714699999999,40.908225],"type":"Point"}
}