{
  "type": "Feature",
  "properties": {
    "addr:full":"237 Park Ave East Rutherford NJ 07073",
    "addr:housenumber":"237",
    "addr:postcode":"07073",
    "addr:street":"Park Ave",
    "iso:country":"US",
    "sg:address":"237 Park Ave",
    "sg:city":"East Rutherford",
    "sg:classifiers":[
        {
            "category":"Health Services",
            "subcategory":"Chiropractor",
            "type":"Services"
        }
    ],
    "sg:phone":"+1 201 438 7474",
    "sg:postcode":"07073",
    "sg:province":"NJ",
    "wof:name":"Bozan Michael DC PC",
    "wof:placetype":"venue"
},
  "geometry": {"coordinates":[-74.099503,40.830002],"type":"Point"}
}