{
  "type": "Feature",
  "properties": {
    "iso:country":"US",
    "sg:address":"2704 Morris Ave",
    "sg:city":"Union",
    "sg:classifiers":[
        {
            "category":"Restaurant",
            "type":"Food & Drink"
        }
    ],
    "sg:phone":"+1 908 964 7655",
    "sg:postcode":"07083",
    "sg:province":"NJ",
    "wof:name":"Joey's Italian Take-Out",
    "wof:placetype":"venue"
},
  "geometry": {"coordinates":[-74.295727,40.70485],"type":"Point"}
}