{
  "type": "Feature",
  "properties": {
    "addr:full":"421 Carvin St Clayton NJ 08312",
    "addr:housenumber":"421",
    "addr:postcode":"08312",
    "addr:street":"Carvin St",
    "iso:country":"US",
    "sg:address":"421 Carvin St",
    "sg:city":"Clayton",
    "sg:classifiers":[
        {
            "category":"Building & Trades",
            "subcategory":"Construction",
            "type":"Services"
        }
    ],
    "sg:phone":"+1 856 881 5035",
    "sg:postcode":"08312",
    "sg:province":"NJ",
    "sg:tags":[
        "house"
    ],
    "wof:name":"Nick Falisi Construction",
    "wof:placetype":"venue"
},
  "geometry": {"coordinates":[-75.102799,39.660699],"type":"Point"}
}