{
  "type": "Feature",
  "properties": {
    "iso:country":"US",
    "sg:address":"4 Larkspur Dr",
    "sg:city":"Parsippany",
    "sg:classifiers":[
        {
            "category":"Professional",
            "subcategory":"Accounting & Tax Preparation",
            "type":"Services"
        }
    ],
    "sg:phone":"+1 973 808 5755",
    "sg:postcode":"07054",
    "sg:province":"NJ",
    "sg:tags":[
        "accountant"
    ],
    "wof:name":"Kenneth I Bailynson & Assoc",
    "wof:placetype":"venue"
},
  "geometry": {"coordinates":[-74.36873199999999,40.865488],"type":"Point"}
}