{
  "type": "Feature",
  "properties": {
    "addr:full":"26 Sandpiper Dr Voorhees NJ 08043",
    "addr:housenumber":"26",
    "addr:postcode":"08043",
    "addr:street":"Sandpiper Dr",
    "iso:country":"US",
    "sg:address":"26 Sandpiper Dr",
    "sg:city":"Voorhees",
    "sg:classifiers":[
        {
            "category":"Banks & Credit Unions",
            "subcategory":"Bank",
            "type":"Services"
        }
    ],
    "sg:phone":"+1   ",
    "sg:postcode":"08043",
    "sg:province":"NJ",
    "sg:tags":[
        "loan",
        "broker"
    ],
    "wof:name":"Coast To Coast Mortgage Inc",
    "wof:placetype":"venue"
},
  "geometry": {"coordinates":[-74.931263,39.865236],"type":"Point"}
}