{
  "type": "Feature",
  "properties": {
    "iso:country":"US",
    "sg:address":"36 Berlin Rd",
    "sg:city":"Stratford",
    "sg:classifiers":[
        {
            "category":"Retail",
            "subcategory":"Auto Repair",
            "type":"Services"
        }
    ],
    "sg:phone":"+1 856 784 1424",
    "sg:postcode":"08084",
    "sg:province":"NJ",
    "sg:tags":[
        "repairing",
        "automobile",
        "automotive"
    ],
    "wof:name":"Speed Line Auto Repair Inc",
    "wof:placetype":"venue"
},
  "geometry": {"coordinates":[-75.002448,39.832605],"type":"Point"}
}