{
  "type": "Feature",
  "properties": {
    "addr:full":"78 Apple St Eatontown NJ 07724",
    "addr:housenumber":"78",
    "addr:postcode":"07724",
    "addr:street":"Apple St",
    "iso:country":"US",
    "sg:address":"78 Apple St",
    "sg:city":"Eatontown",
    "sg:classifiers":[
        {
            "category":"Freight",
            "type":"Transportation"
        },
        {
            "category":"Professional",
            "subcategory":"Management & Consulting",
            "type":"Services"
        }
    ],
    "sg:phone":"+1 732 747 1600",
    "sg:postcode":"07724",
    "sg:province":"NJ",
    "sg:tags":[
        "consultant"
    ],
    "wof:name":"Gagliano Associates",
    "wof:placetype":"venue"
},
  "geometry": {"coordinates":[-74.080617,40.330366],"type":"Point"}
}