{
  "type": "Feature",
  "properties": {
    "iso:country":"US",
    "sg:address":"190 Moore St",
    "sg:city":"Hackensack",
    "sg:classifiers":[
        {
            "category":"Building & Trades",
            "subcategory":"Equipment Rental",
            "type":"Services"
        },
        {
            "category":"Banks & Credit Unions",
            "subcategory":"Bank",
            "type":"Services"
        }
    ],
    "sg:phone":"+1 201 487 1100",
    "sg:postcode":"07601",
    "sg:province":"NJ",
    "sg:tags":[
        "financing",
        "leasing",
        "general"
    ],
    "sg:website":"www.firstgreenwich.com",
    "wof:name":"First Greenwich Capital Corp",
    "wof:placetype":"venue"
},
  "geometry": {"coordinates":[-74.041088,40.885204],"type":"Point"}
}