{
  "type": "Feature",
  "properties": {
    "iso:country":"US",
    "sg:address":"1406 W Dahlia Ave",
    "sg:city":"Egg Harbor City",
    "sg:classifiers":[
        {
            "category":"Organizations",
            "subcategory":"Religious Organization",
            "type":"Services"
        }
    ],
    "sg:phone":"+1   ",
    "sg:postcode":"08215",
    "sg:province":"NJ",
    "wof:name":"Saint James Bb Del Evan Assoc",
    "wof:placetype":"venue"
},
  "geometry": {"coordinates":[-74.64783300000001,39.509365],"type":"Point"}
}