{
  "type": "Feature",
  "properties": {
    "addr:full":"479 W Perry St Cape May NJ 08204",
    "addr:housenumber":"479",
    "addr:postcode":"08204",
    "addr:street":"W Perry St",
    "iso:country":"US",
    "sg:address":"479 W Perry St",
    "sg:city":"Cape May",
    "sg:classifiers":[
        {
            "category":"Restaurant",
            "type":"Food & Drink"
        }
    ],
    "sg:postcode":"08204",
    "sg:province":"NJ",
    "sg:tags":[
        "mexican"
    ],
    "wof:name":"Key West Tacos",
    "wof:placetype":"venue"
},
  "geometry": {"coordinates":[-74.92792799999999,38.934571],"type":"Point"}
}