{
  "type": "Feature",
  "properties": {
    "addr:full":"4043 US Hwy 9 Howell NJ 07731",
    "addr:housenumber":"4043",
    "addr:postcode":"07731",
    "addr:street":"Us Hwy 9",
    "iso:country":"US",
    "sg:address":"4043 US Hwy 9",
    "sg:city":"Howell",
    "sg:classifiers":[
        {
            "category":"Real Estate",
            "subcategory":"Real Estate Agent",
            "type":"Services"
        }
    ],
    "sg:phone":"+1 732 364 0300",
    "sg:postcode":"07731",
    "sg:province":"NJ",
    "wof:name":"Re/Max Of Howell Jackson",
    "wof:placetype":"venue"
},
  "geometry": {"coordinates":[-74.22831100000001,40.15327],"type":"Point"}
}