{
  "type": "Feature",
  "properties": {
    "iso:country":"US",
    "sg:address":"47 Oxycocus Rd",
    "sg:city":"Manahawkin",
    "sg:classifiers":[
        {
            "category":"Real Estate",
            "subcategory":"Real Estate Agent",
            "type":"Services"
        }
    ],
    "sg:phone":"+1   ",
    "sg:postcode":"08050",
    "sg:province":"NJ",
    "wof:name":"First Realty",
    "wof:placetype":"venue"
},
  "geometry": {"coordinates":[-74.25848000000001,39.701878],"type":"Point"}
}