{
  "type": "Feature",
  "properties": {
    "iso:country":"US",
    "sg:address":"4 Center St",
    "sg:city":"Toms River",
    "sg:classifiers":[
        {
            "category":"Building & Trades",
            "subcategory":"Construction",
            "type":"Services"
        }
    ],
    "sg:phone":"+1 732 286 4936",
    "sg:postcode":"08757",
    "sg:province":"NJ",
    "sg:tags":[
        "paving",
        "contractor"
    ],
    "wof:name":"Oscar L Cradle Sr-Paving Contr",
    "wof:placetype":"venue"
},
  "geometry": {"coordinates":[-74.198297,39.946052],"type":"Point"}
}