{
  "type": "Feature",
  "properties": {
    "iso:country":"US",
    "sg:address":"3091 RT-35",
    "sg:city":"Hazlet",
    "sg:classifiers":[
        {
            "category":"Restaurant",
            "type":"Food & Drink"
        }
    ],
    "sg:menulink":"http://www.allmenus.com/nj/hazlet/82393-dominos-pizza/menu/",
    "sg:phone":"+1 732 888 1700",
    "sg:postcode":"07730",
    "sg:province":"NJ",
    "sg:tags":[
        "american",
        "wing",
        "pizza"
    ],
    "wof:name":"Domino's Pizza",
    "wof:placetype":"venue"
},
  "geometry": {"coordinates":[-74.181692,40.420028],"type":"Point"}
}