{
  "type": "Feature",
  "properties": {
    "addr:full":"710 Valley St Orange NJ 07050",
    "addr:housenumber":"710",
    "addr:postcode":"07050",
    "addr:street":"Valley St",
    "iso:country":"US",
    "sg:address":"710 Valley St",
    "sg:city":"Orange",
    "sg:classifiers":[
        {
            "category":"Personal",
            "subcategory":"Beauty Salon",
            "type":"Services"
        }
    ],
    "sg:phone":"+1 973 675 7724",
    "sg:postcode":"07050",
    "sg:province":"NJ",
    "sg:tags":[
        "shop"
    ],
    "wof:name":"Rhodenas Hair Gallery",
    "wof:placetype":"venue"
},
  "geometry": {"coordinates":[-74.25269,40.759186],"type":"Point"}
}