{
  "type": "Feature",
  "properties": {
    "addr:full":"5 Foster Ave Gibbsboro NJ 08026",
    "addr:housenumber":"5",
    "addr:postcode":"08026",
    "addr:street":"Foster Ave",
    "iso:country":"US",
    "sg:address":"5 Foster Ave",
    "sg:city":"Gibbsboro",
    "sg:classifiers":[
        {
            "category":"Retail",
            "subcategory":"Auto Repair",
            "type":"Services"
        }
    ],
    "sg:phone":"+1 856 783 4910",
    "sg:postcode":"08026",
    "sg:province":"NJ",
    "sg:tags":[
        "body"
    ],
    "wof:name":"Maintenance Dept",
    "wof:placetype":"venue"
},
  "geometry": {"coordinates":[-74.96401400000001,39.836598],"type":"Point"}
}