{
  "type": "Feature",
  "properties": {
    "iso:country":"US",
    "sg:address":"590 Rutherford Ave",
    "sg:city":"Trenton",
    "sg:classifiers":[
        {
            "category":"Arts & Performance",
            "subcategory":"Theater",
            "type":"Entertainment"
        }
    ],
    "sg:phone":"+1   ",
    "sg:postcode":"08618",
    "sg:province":"NJ",
    "sg:tags":[
        "group"
    ],
    "wof:name":"Uptop Entertainment LLC",
    "wof:placetype":"venue"
},
  "geometry": {"coordinates":[-74.77922700000001,40.232397],"type":"Point"}
}