{
  "type": "Feature",
  "properties": {
    "addr:full":"347 Norwich Ln Monroe Township NJ 08831",
    "addr:housenumber":"347",
    "addr:postcode":"08831",
    "addr:street":"Norwich Ln",
    "iso:country":"US",
    "sg:address":"347 Norwich Ln",
    "sg:city":"Monroe Township",
    "sg:classifiers":[
        {
            "category":"Restaurant",
            "type":"Food & Drink"
        }
    ],
    "sg:phone":"+1   ",
    "sg:postcode":"08831",
    "sg:province":"NJ",
    "sg:tags":[
        "eating"
    ],
    "wof:name":"Pollack Family Assoc LP",
    "wof:placetype":"venue"
},
  "geometry": {"coordinates":[-74.473826,40.326681],"type":"Point"}
}