{
  "type": "Feature",
  "properties": {
    "iso:country":"US",
    "sg:address":"162 Inman Ave",
    "sg:city":"Colonia",
    "sg:classifiers":[
        {
            "category":"Personal",
            "type":"Services"
        }
    ],
    "sg:phone":"+1 732 381 4445",
    "sg:postcode":"07067",
    "sg:province":"NJ",
    "sg:tags":[
        "towing"
    ],
    "wof:name":"M & N Auto Repair Inc",
    "wof:placetype":"venue"
},
  "geometry": {"coordinates":[-74.309898,40.600399],"type":"Point"}
}