{
  "type": "Feature",
  "properties": {
    "iso:country":"US",
    "sg:address":"556 Williamstown Rd",
    "sg:city":"Sicklerville",
    "sg:classifiers":[
        {
            "category":"Personal",
            "subcategory":"Barber",
            "type":"Services"
        }
    ],
    "sg:phone":"+1 856 629 4958",
    "sg:postcode":"08081",
    "sg:province":"NJ",
    "wof:name":"Colonial Barber Shop",
    "wof:placetype":"venue"
},
  "geometry": {"coordinates":[-74.97324,39.712647],"type":"Point"}
}