{
  "type": "Feature",
  "properties": {
    "addr:full":"39 Lake St Fair Lawn NJ 07410",
    "addr:housenumber":"39",
    "addr:postcode":"07410",
    "addr:street":"Lake St",
    "iso:country":"US",
    "sg:address":"39 Lake St",
    "sg:city":"Fair Lawn",
    "sg:classifiers":[
        {
            "category":"Building & Trades",
            "subcategory":"Electrical",
            "type":"Services"
        }
    ],
    "sg:phone":"+1 201 796 6360",
    "sg:postcode":"07410",
    "sg:province":"NJ",
    "sg:tags":[
        "electrical",
        "contractor"
    ],
    "wof:name":"Polan Electric",
    "wof:placetype":"venue"
},
  "geometry": {"coordinates":[-74.13807199999999,40.940638],"type":"Point"}
}