{
  "type": "Feature",
  "properties": {
    "addr:full":"638 Sun Haven Dr Clayton NJ 08312",
    "addr:housenumber":"638",
    "addr:postcode":"08312",
    "addr:street":"Sun Haven Dr",
    "iso:country":"US",
    "sg:address":"638 Sun Haven Dr",
    "sg:city":"Clayton",
    "sg:classifiers":[
        {
            "category":"Retail",
            "subcategory":"Portrait Studio",
            "type":"Services"
        }
    ],
    "sg:phone":"+1   ",
    "sg:postcode":"08312",
    "sg:province":"NJ",
    "sg:tags":[
        "photo"
    ],
    "wof:name":"Lillys Portraits",
    "wof:placetype":"venue"
},
  "geometry": {"coordinates":[-75.07948399999999,39.654706],"type":"Point"}
}