{
  "type": "Feature",
  "properties": {
    "addr:full":"2900 Central Ave Union City NJ 07087",
    "addr:housenumber":"2900",
    "addr:postcode":"07087",
    "addr:street":"Central Ave",
    "iso:country":"US",
    "sg:address":"2900 Central Ave",
    "sg:city":"Union City",
    "sg:classifiers":[
        {
            "category":"Building & Trades",
            "subcategory":"Locksmith",
            "type":"Services"
        }
    ],
    "sg:phone":"+1 877 759 5092",
    "sg:postcode":"07087",
    "sg:province":"NJ",
    "sg:tags":[
        "key"
    ],
    "wof:name":"24 Emergency Locksmith",
    "wof:placetype":"venue"
},
  "geometry": {"coordinates":[-74.031991,40.771362],"type":"Point"}
}