{
  "type": "Feature",
  "properties": {
    "iso:country":"US",
    "sg:address":"7 Industrial Ave",
    "sg:city":"Upper Saddle Rvr",
    "sg:classifiers":[
        {
            "category":"Communications",
            "type":"Services"
        }
    ],
    "sg:phone":"+1 201 995 0111",
    "sg:postcode":"07458",
    "sg:province":"NJ",
    "wof:name":"W V Communications",
    "wof:placetype":"venue"
},
  "geometry": {"coordinates":[-74.121416,41.053483],"type":"Point"}
}