{
  "type": "Feature",
  "properties": {
    "addr:full":"189 Berdan Ave Wayne NJ 07470",
    "addr:housenumber":"189",
    "addr:postcode":"07470",
    "addr:street":"Berdan Ave",
    "iso:country":"US",
    "sg:address":"189 Berdan Ave",
    "sg:city":"Wayne",
    "sg:classifiers":[
        {
            "category":"Professional",
            "subcategory":"Lawyer & Legal Services",
            "type":"Services"
        }
    ],
    "sg:phone":"+1 973 628 1901",
    "sg:postcode":"07470",
    "sg:province":"NJ",
    "sg:tags":[
        "notary"
    ],
    "sg:website":"www.mbe.com",
    "wof:name":"Mail Boxes Etc",
    "wof:placetype":"venue"
},
  "geometry": {"coordinates":[-74.243103,40.966999],"type":"Point"}
}