{
  "type": "Feature",
  "properties": {
    "addr:full":"1015 Asbury Ave Asbury Park NJ 07712",
    "addr:housenumber":"1015",
    "addr:postcode":"07712",
    "addr:street":"Asbury Ave Asbury",
    "iso:country":"US",
    "sg:address":"1015 Asbury Ave",
    "sg:city":"Asbury Park",
    "sg:classifiers":[
        {
            "category":"Retail",
            "subcategory":"Auto Rental",
            "type":"Services"
        }
    ],
    "sg:phone":"+1 732 988 3800",
    "sg:postcode":"07712",
    "sg:province":"NJ",
    "sg:tags":[
        "renting",
        "automobile"
    ],
    "wof:name":"Enterprise Rent-A-Car",
    "wof:placetype":"venue"
},
  "geometry": {"coordinates":[-74.01646100000001,40.221415],"type":"Point"}
}