{
  "type": "Feature",
  "properties": {
    "addr:full":"51 Bridge St Lambertville NJ 08530",
    "addr:housenumber":"51",
    "addr:postcode":"08530",
    "addr:street":"Bridge St",
    "iso:country":"US",
    "sg:address":"51 Bridge St",
    "sg:city":"Lambertville",
    "sg:classifiers":[
        {
            "category":"Professional",
            "subcategory":"Business Services",
            "type":"Services"
        }
    ],
    "sg:phone":"+1   ",
    "sg:postcode":"08530",
    "sg:province":"NJ",
    "sg:tags":[
        "furniture"
    ],
    "wof:name":"Poum Digs",
    "wof:placetype":"venue"
},
  "geometry": {"coordinates":[-74.94440400000001,40.365676],"type":"Point"}
}