{
  "type": "Feature",
  "properties": {
    "iso:country":"US",
    "sg:address":"1 London Rd",
    "sg:city":"Burlington",
    "sg:classifiers":[
        {
            "category":"Local Transit",
            "type":"Transportation"
        }
    ],
    "sg:phone":"+1 609 386 2479",
    "sg:postcode":"08016",
    "sg:province":"NJ",
    "sg:tags":[
        "passenger",
        "suppl"
    ],
    "wof:name":"Total Coverage Travel",
    "wof:placetype":"venue"
},
  "geometry": {"coordinates":[-74.828311,40.081246],"type":"Point"}
}