{
  "type": "Feature",
  "properties": {
    "addr:full":"311 Windeler Rd Howell NJ 07731",
    "addr:housenumber":"311",
    "addr:postcode":"07731",
    "addr:street":"Windeler Rd",
    "iso:country":"US",
    "sg:address":"311 Windeler Rd",
    "sg:city":"Howell",
    "sg:classifiers":[
        {
            "category":"Recreation",
            "type":"Entertainment"
        }
    ],
    "sg:phone":"+1 732 919 0996",
    "sg:postcode":"07731",
    "sg:province":"NJ",
    "sg:tags":[
        "parks"
    ],
    "wof:name":"Joseph C Irwin Recreation Area",
    "wof:placetype":"venue"
},
  "geometry": {"coordinates":[-74.20314399999999,40.16926],"type":"Point"}
}