{
  "type": "Feature",
  "properties": {
    "iso:country":"US",
    "sg:address":"7 Naughright Rd",
    "sg:city":"Budd Lake",
    "sg:classifiers":[
        {
            "category":"Food & Beverages",
            "subcategory":"Liquor & Beverages",
            "type":"Retail Goods"
        }
    ],
    "sg:phone":"+1 908 852 4000",
    "sg:postcode":"07840",
    "sg:province":"NJ",
    "sg:tags":[
        "drinking",
        "alcoholic"
    ],
    "wof:name":"Village Bar & Liquors",
    "wof:placetype":"venue"
},
  "geometry": {"coordinates":[-74.78268199999999,40.852041],"type":"Point"}
}