{
  "type": "Feature",
  "properties": {
    "iso:country":"US",
    "sg:address":"21 N Main St",
    "sg:city":"Milltown",
    "sg:classifiers":[
        {
            "category":"Shopping",
            "subcategory":"Pharmacy",
            "type":"Retail Goods"
        }
    ],
    "sg:phone":"+1   ",
    "sg:postcode":"08850",
    "sg:province":"NJ",
    "sg:tags":[
        "shop",
        "gift",
        "greeting",
        "drug",
        "store",
        "card"
    ],
    "wof:name":"Milltown Pharmacy",
    "wof:placetype":"venue"
},
  "geometry": {"coordinates":[-74.43761499999999,40.451192],"type":"Point"}
}