{
  "type": "Feature",
  "properties": {
    "addr:full":"29 E 29th St Bayonne NJ 07002",
    "addr:housenumber":"29",
    "addr:postcode":"07002",
    "addr:street":"E 29Th St",
    "iso:country":"US",
    "sg:address":"29 E 29th St",
    "sg:city":"Bayonne",
    "sg:classifiers":[
        {
            "category":"Banks & Credit Unions",
            "subcategory":"Bank",
            "type":"Services"
        }
    ],
    "sg:phone":"+1 201 339 1403",
    "sg:postcode":"07002",
    "sg:province":"NJ",
    "wof:name":"Pamrapo Savings Bank",
    "wof:placetype":"venue"
},
  "geometry": {"coordinates":[-74.114092,40.668568],"type":"Point"}
}