{
  "type": "Feature",
  "properties": {
    "addr:full":"205 Sheridan Ave Roselle NJ 07203",
    "addr:housenumber":"205",
    "addr:postcode":"07203",
    "addr:street":"Sheridan Ave",
    "iso:country":"US",
    "sg:address":"205 Sheridan Ave",
    "sg:city":"Roselle",
    "sg:classifiers":[
        {
            "category":"Food & Beverages",
            "subcategory":"Groceries & Convenience Stores",
            "type":"Retail Goods"
        }
    ],
    "sg:phone":"+1   ",
    "sg:postcode":"07203",
    "sg:province":"NJ",
    "wof:name":"Eshtasigutl Deli Grocery",
    "wof:placetype":"venue"
},
  "geometry": {"coordinates":[-74.249702,40.660268],"type":"Point"}
}