{
  "type": "Feature",
  "properties": {
    "iso:country":"US",
    "sg:address":"25 Kilmer Dr",
    "sg:city":"Morganville",
    "sg:classifiers":[
        {
            "category":"Professional",
            "subcategory":"Accounting & Tax Preparation",
            "type":"Services"
        }
    ],
    "sg:phone":"+1 732 845 2333",
    "sg:postcode":"07751",
    "sg:province":"NJ",
    "sg:tags":[
        "accountant"
    ],
    "wof:name":"Bernknopf Group LTD",
    "wof:placetype":"venue"
},
  "geometry": {"coordinates":[-74.312843,40.340328],"type":"Point"}
}