{
  "type": "Feature",
  "properties": {
    "addr:full":"241 US Hwy 206 Stanhope NJ 07874",
    "addr:housenumber":"241",
    "addr:postcode":"07874",
    "addr:street":"Us Hwy 206",
    "iso:country":"US",
    "sg:address":"241 US Hwy 206",
    "sg:city":"Stanhope",
    "sg:classifiers":[
        {
            "category":"Home & Garden",
            "subcategory":"Building Materials",
            "type":"Retail Goods"
        }
    ],
    "sg:phone":"+1 973 448 0110",
    "sg:postcode":"07874",
    "sg:province":"NJ",
    "sg:tags":[
        "glass",
        "window",
        "plate"
    ],
    "wof:name":"Master Glass Inc",
    "wof:placetype":"venue"
},
  "geometry": {"coordinates":[-74.718276,40.917694],"type":"Point"}
}