{
  "type": "Feature",
  "properties": {
    "iso:country":"US",
    "sg:address":"1073 S Elmora Ave",
    "sg:city":"Elizabeth",
    "sg:classifiers":[
        {
            "category":"Restaurant",
            "type":"Food & Drink"
        },
        {
            "category":"Food & Beverages",
            "subcategory":"Groceries & Convenience Stores",
            "type":"Retail Goods"
        }
    ],
    "sg:phone":"+1 908 355 7810",
    "sg:postcode":"07202",
    "sg:province":"NJ",
    "sg:tags":[
        "delicatessen",
        "sandwich"
    ],
    "wof:name":"Mac's Place",
    "wof:placetype":"venue"
},
  "geometry": {"coordinates":[-74.22779800000001,40.655102],"type":"Point"}
}