{
  "type": "Feature",
  "properties": {
    "iso:country":"US",
    "sg:address":"8 Eton Dr",
    "sg:city":"Caldwell",
    "sg:classifiers":[
        {
            "category":"Home & Garden",
            "subcategory":"Garden Supply",
            "type":"Retail Goods"
        }
    ],
    "sg:phone":"+1   ",
    "sg:postcode":"07006",
    "sg:province":"NJ",
    "wof:name":"Lush Gardens",
    "wof:placetype":"venue"
},
  "geometry": {"coordinates":[-74.265078,40.860411],"type":"Point"}
}