{
  "type": "Feature",
  "properties": {
    "addr:full":"5041 White Horse Pike Egg Harbor City NJ 08215",
    "addr:housenumber":"5041",
    "addr:postcode":"08215",
    "addr:street":"White Horse Pike",
    "iso:country":"US",
    "sg:address":"5041 White Horse Pike",
    "sg:city":"Egg Harbor City",
    "sg:classifiers":[
        {
            "category":"Autos & Motor Vehicles",
            "subcategory":"Automobile Sales",
            "type":"Retail Goods"
        }
    ],
    "sg:phone":"+1   ",
    "sg:postcode":"08215",
    "sg:province":"NJ",
    "sg:tags":[
        "used"
    ],
    "wof:name":"Parkside Motors Inc",
    "wof:placetype":"venue"
},
  "geometry": {"coordinates":[-74.69567000000001,39.56204],"type":"Point"}
}