{
  "type": "Feature",
  "properties": {
    "addr:full":"9 Ray Pl Fairfield NJ 07004",
    "addr:housenumber":"9",
    "addr:postcode":"07004",
    "addr:street":"Ray Pl",
    "iso:country":"US",
    "sg:address":"9 Ray Pl",
    "sg:city":"Fairfield",
    "sg:classifiers":[
        {
            "category":"Manufacturing",
            "subcategory":"Metals",
            "type":"Manufacturing & Wholesale Goods"
        }
    ],
    "sg:phone":"+1 973 276 0880",
    "sg:postcode":"07004",
    "sg:province":"NJ",
    "sg:tags":[
        "fabrication",
        "structural"
    ],
    "wof:name":"Bergen Steel Fabricators",
    "wof:placetype":"venue"
},
  "geometry": {"coordinates":[-74.31400499999999,40.86185],"type":"Point"}
}