{
  "type": "Feature",
  "properties": {
    "iso:country":"US",
    "sg:address":"550 Myrtle Ave",
    "sg:city":"Boonton",
    "sg:classifiers":[
        {
            "category":"Food & Beverages",
            "subcategory":"Groceries & Convenience Stores",
            "type":"Retail Goods"
        }
    ],
    "sg:phone":"+1 908 394 9570",
    "sg:postcode":"07005",
    "sg:province":"NJ",
    "sg:tags":[
        "grocer"
    ],
    "sg:website":"www.aandp.com",
    "wof:name":"A & P Food Store",
    "wof:placetype":"venue"
},
  "geometry": {"coordinates":[-74.39697700000001,40.907715],"type":"Point"}
}