{
  "type": "Feature",
  "properties": {
    "addr:full":"488 Riverside Dr Wayne NJ 07470",
    "addr:housenumber":"488",
    "addr:postcode":"07470",
    "addr:street":"Riverside Dr",
    "iso:country":"US",
    "sg:address":"488 Riverside Dr",
    "sg:city":"Wayne",
    "sg:classifiers":[
        {
            "category":"Personal",
            "type":"Services"
        }
    ],
    "sg:phone":"+1   ",
    "sg:postcode":"07470",
    "sg:province":"NJ",
    "wof:name":"Northeast Leak Detection",
    "wof:placetype":"venue"
},
  "geometry": {"coordinates":[-74.26377599999999,40.888226],"type":"Point"}
}