{
  "type": "Feature",
  "properties": {
    "iso:country":"US",
    "sg:address":"519 Market St",
    "sg:city":"Paterson",
    "sg:classifiers":[
        {
            "category":"Restaurant",
            "type":"Food & Drink"
        }
    ],
    "sg:phone":"+1 973 881 9230",
    "sg:postcode":"07501",
    "sg:province":"NJ",
    "sg:tags":[
        "eating",
        "pizza"
    ],
    "wof:name":"Eastside Pizzeria & Grill",
    "wof:placetype":"venue"
},
  "geometry": {"coordinates":[-74.155998,40.9123],"type":"Point"}
}