{
  "type": "Feature",
  "properties": {
    "iso:country":"US",
    "sg:address":"465 Coit St",
    "sg:city":"Irvington",
    "sg:classifiers":[
        {
            "category":"Autos & Motor Vehicles",
            "subcategory":"Fuel & Gas Station",
            "type":"Retail Goods"
        }
    ],
    "sg:phone":"+1   ",
    "sg:postcode":"07111",
    "sg:province":"NJ",
    "sg:tags":[
        "repair",
        "station",
        "gasoline",
        "general"
    ],
    "wof:name":"S A S Auto Repair Center",
    "wof:placetype":"venue"
},
  "geometry": {"coordinates":[-74.2321,40.710397],"type":"Point"}
}