{
  "type": "Feature",
  "properties": {
    "iso:country":"US",
    "sg:address":"10 Sommers Ave",
    "sg:city":"Somers Point",
    "sg:classifiers":[
        {
            "category":"Health Services",
            "subcategory":"Doctor",
            "type":"Services"
        }
    ],
    "sg:phone":"+1 609 404 1100",
    "sg:postcode":"08244",
    "sg:province":"NJ",
    "sg:tags":[
        "medical"
    ],
    "wof:name":"Lawrence G Ognibene Do",
    "wof:placetype":"venue"
},
  "geometry": {"coordinates":[-74.595815,39.309844],"type":"Point"}
}