{
  "type": "Feature",
  "properties": {
    "addr:full":"19 Miller Rd Howell NJ 07731",
    "addr:housenumber":"19",
    "addr:postcode":"07731",
    "addr:street":"Miller Rd",
    "iso:country":"US",
    "sg:address":"19 Miller Rd",
    "sg:city":"Howell",
    "sg:classifiers":[
        {
            "category":"Wholesale",
            "subcategory":"Fruits & Vegetables",
            "type":"Manufacturing & Wholesale Goods"
        }
    ],
    "sg:phone":"+1 732 730 9970",
    "sg:postcode":"07731",
    "sg:province":"NJ",
    "wof:name":"All Sweet Watermelons",
    "wof:placetype":"venue"
},
  "geometry": {"coordinates":[-74.19422,40.122629],"type":"Point"}
}