{
  "type": "Feature",
  "properties": {
    "iso:country":"US",
    "sg:address":"750 State Rte 70",
    "sg:city":"Marlton",
    "sg:classifiers":[
        {
            "category":"Retail",
            "subcategory":"Laundry & Dry Cleaning",
            "type":"Services"
        }
    ],
    "sg:phone":"+1 856 596 5992",
    "sg:postcode":"08053",
    "sg:province":"NJ",
    "sg:tags":[
        "cleaners"
    ],
    "wof:name":"Dutch Cleaners By Kim",
    "wof:placetype":"venue"
},
  "geometry": {"coordinates":[-74.883357,39.894095],"type":"Point"}
}