{
  "type": "Feature",
  "properties": {
    "iso:country":"US",
    "sg:address":"507 Washington Rd",
    "sg:city":"Parlin",
    "sg:classifiers":[
        {
            "category":"Retail",
            "subcategory":"Auto Repair",
            "type":"Services"
        }
    ],
    "sg:phone":"+1 732 238 9788",
    "sg:postcode":"08859",
    "sg:province":"NJ",
    "sg:tags":[
        "repairing",
        "automobile",
        "general"
    ],
    "wof:name":"George's Auto & Truck Repair",
    "wof:placetype":"venue"
},
  "geometry": {"coordinates":[-74.335081,40.4611],"type":"Point"}
}