{
  "type": "Feature",
  "properties": {
    "addr:full":"805 Cooper Rd Voorhees NJ 08043",
    "addr:housenumber":"805",
    "addr:postcode":"08043",
    "addr:street":"Cooper Rd",
    "iso:country":"US",
    "sg:address":"805 Cooper Rd",
    "sg:city":"Voorhees",
    "sg:classifiers":[
        {
            "category":"Health Services",
            "subcategory":"Doctor",
            "type":"Services"
        }
    ],
    "sg:phone":"+1 856 489 9822",
    "sg:postcode":"08043",
    "sg:province":"NJ",
    "sg:tags":[
        "physician",
        "surgeon"
    ],
    "wof:name":"Advanced Pain Consultants",
    "wof:placetype":"venue"
},
  "geometry": {"coordinates":[-74.953908,39.862818],"type":"Point"}
}