{
  "type": "Feature",
  "properties": {
    "addr:full":"82 Farnwood Rd Mount Laurel NJ 08054",
    "addr:housenumber":"82",
    "addr:postcode":"08054",
    "addr:street":"Farnwood Rd",
    "iso:country":"US",
    "sg:address":"82 Farnwood Rd",
    "sg:city":"Mount Laurel",
    "sg:classifiers":[
        {
            "category":"Restaurant",
            "type":"Food & Drink"
        }
    ],
    "sg:phone":"+1   ",
    "sg:postcode":"08054",
    "sg:province":"NJ",
    "sg:tags":[
        "eating"
    ],
    "wof:name":"Gregory McKain",
    "wof:placetype":"venue"
},
  "geometry": {"coordinates":[-74.924888,39.922256],"type":"Point"}
}