{
  "type": "Feature",
  "properties": {
    "iso:country":"US",
    "sg:address":"253 Hurffville Rd",
    "sg:city":"Sewell",
    "sg:classifiers":[
        {
            "category":"Organizations",
            "subcategory":"Religious Organization",
            "type":"Services"
        }
    ],
    "sg:phone":"+1 856 228 0969",
    "sg:postcode":"08080",
    "sg:province":"NJ",
    "sg:tags":[
        "church"
    ],
    "wof:name":"Church Of The Resurrection",
    "wof:placetype":"venue"
},
  "geometry": {"coordinates":[-75.075208,39.76283],"type":"Point"}
}