{
  "type": "Feature",
  "properties": {
    "addr:full":"120 State Rte 37 Toms River NJ 08755",
    "addr:housenumber":"120",
    "addr:postcode":"08755",
    "addr:street":"State Rte 37",
    "iso:country":"US",
    "sg:address":"120 State Rte 37",
    "sg:city":"Toms River",
    "sg:classifiers":[
        {
            "category":"Home & Garden",
            "subcategory":"Furniture",
            "type":"Retail Goods"
        }
    ],
    "sg:phone":"+1   ",
    "sg:postcode":"08755",
    "sg:province":"NJ",
    "sg:tags":[
        "bedding",
        "mattress"
    ],
    "wof:name":"Mister Mattress",
    "wof:placetype":"venue"
},
  "geometry": {"coordinates":[-74.21758800000001,39.965791],"type":"Point"}
}