{
  "type": "Feature",
  "properties": {
    "iso:country":"US",
    "sg:address":"117 US Hwy 202",
    "sg:city":"Ringoes",
    "sg:classifiers":[
        {
            "category":"Building & Trades",
            "subcategory":"Plumbing",
            "type":"Services"
        }
    ],
    "sg:phone":"+1 908 996 7686",
    "sg:postcode":"08551",
    "sg:province":"NJ",
    "sg:tags":[
        "plumbing",
        "contractor"
    ],
    "wof:name":"Roto-Rooter Plumbing & Drain",
    "wof:placetype":"venue"
},
  "geometry": {"coordinates":[-74.86056000000001,40.466964],"type":"Point"}
}