{
  "type": "Feature",
  "properties": {
    "addr:full":"617 Ridge Rd Lyndhurst NJ 07071",
    "addr:housenumber":"617",
    "addr:postcode":"07071",
    "addr:street":"Ridge Rd",
    "iso:country":"US",
    "sg:address":"617 Ridge Rd",
    "sg:city":"Lyndhurst",
    "sg:classifiers":[
        {
            "category":"Home & Garden",
            "subcategory":"Carpets & Floor Coverings",
            "type":"Retail Goods"
        }
    ],
    "sg:phone":"+1 201 531 1222",
    "sg:postcode":"07071",
    "sg:province":"NJ",
    "sg:tags":[
        "dealer",
        "rug"
    ],
    "wof:name":"Lyndhurst Carpet LLC",
    "wof:placetype":"venue"
},
  "geometry": {"coordinates":[-74.12313899999999,40.802689],"type":"Point"}
}