{
  "type": "Feature",
  "properties": {
    "addr:full":"888 River Rd Edgewater NJ 07020",
    "addr:housenumber":"888",
    "addr:postcode":"07020",
    "addr:street":"River Rd",
    "iso:country":"US",
    "sg:address":"888 River Rd",
    "sg:city":"Edgewater",
    "sg:classifiers":[
        {
            "category":"Restaurant",
            "type":"Food & Drink"
        }
    ],
    "sg:phone":"+1 201 941 8181",
    "sg:postcode":"07020",
    "sg:province":"NJ",
    "sg:tags":[
        "pizza"
    ],
    "wof:name":"Brothers Restaurant & Pizzeria",
    "wof:placetype":"venue"
},
  "geometry": {"coordinates":[-73.975818,40.82318],"type":"Point"}
}