{
  "type": "Feature",
  "properties": {
    "addr:full":"1 Emerson Dr Fair Lawn NJ 07410",
    "addr:housenumber":"1",
    "addr:postcode":"07410",
    "addr:street":"Emerson Dr",
    "iso:country":"US",
    "sg:address":"1 Emerson Dr",
    "sg:city":"Fair Lawn",
    "sg:classifiers":[
        {
            "category":"Home & Garden",
            "subcategory":"Carpets & Floor Coverings",
            "type":"Retail Goods"
        }
    ],
    "sg:phone":"+1   ",
    "sg:postcode":"07410",
    "sg:province":"NJ",
    "wof:name":"Saccos Carpet",
    "wof:placetype":"venue"
},
  "geometry": {"coordinates":[-74.128608,40.940397],"type":"Point"}
}