{
  "type": "Feature",
  "properties": {
    "addr:full":"9 Crane Ter Verona NJ 07044",
    "addr:housenumber":"9",
    "addr:postcode":"07044",
    "addr:street":"Crane Ter",
    "iso:country":"US",
    "sg:address":"9 Crane Ter",
    "sg:city":"Verona",
    "sg:classifiers":[
        {
            "category":"Real Estate",
            "subcategory":"Real Estate Operator",
            "type":"Services"
        }
    ],
    "sg:phone":"+1   ",
    "sg:postcode":"07044",
    "sg:province":"NJ",
    "sg:tags":[
        "building",
        "apartment"
    ],
    "wof:name":"Areligh Mews Condo",
    "wof:placetype":"venue"
},
  "geometry": {"coordinates":[-74.239137,40.837447],"type":"Point"}
}