{
  "type": "Feature",
  "properties": {
    "addr:full":"11 Diamond Rd Springfield NJ 07081",
    "addr:housenumber":"11",
    "addr:postcode":"07081",
    "addr:street":"Diamond Rd",
    "iso:country":"US",
    "sg:address":"11 Diamond Rd",
    "sg:city":"Springfield",
    "sg:classifiers":[
        {
            "category":"Shopping",
            "subcategory":"Computers & Home Electronics",
            "type":"Retail Goods"
        }
    ],
    "sg:phone":"+1   ",
    "sg:postcode":"07081",
    "sg:province":"NJ",
    "sg:tags":[
        "equipment"
    ],
    "sg:website":"www.westcomp.com",
    "wof:name":"Westwood Computer Corp",
    "wof:placetype":"venue"
},
  "geometry": {"coordinates":[-74.31282899999999,40.685472],"type":"Point"}
}