{
  "type": "Feature",
  "properties": {
    "iso:country":"US",
    "sg:address":"156 Beaver Run Rd",
    "sg:city":"Hamburg",
    "sg:classifiers":[
        {
            "category":"Taxi",
            "type":"Transportation"
        }
    ],
    "sg:phone":"+1 973 875 8460",
    "sg:postcode":"07419",
    "sg:province":"NJ",
    "sg:tags":[
        "taxicab"
    ],
    "wof:name":"Sussex County Taxi Service",
    "wof:placetype":"venue"
},
  "geometry": {"coordinates":[-74.615459,41.155722],"type":"Point"}
}