{
  "type": "Feature",
  "properties": {
    "iso:country":"US",
    "sg:address":"8 Edge Ln",
    "sg:city":"Riverside",
    "sg:classifiers":[
        {
            "category":"Wholesale",
            "subcategory":"Machinery & Supplies",
            "type":"Manufacturing & Wholesale Goods"
        }
    ],
    "sg:phone":"+1 609 306 7933",
    "sg:postcode":"08046",
    "sg:province":"NJ",
    "sg:tags":[
        "lift",
        "truck",
        "parts"
    ],
    "wof:name":"Hand Trucks R Us LLC",
    "wof:placetype":"venue"
},
  "geometry": {"coordinates":[-74.86889499999999,40.0144],"type":"Point"}
}