{
  "type": "Feature",
  "properties": {
    "addr:full":"278 Haywood Dr Paramus NJ 07652",
    "addr:housenumber":"278",
    "addr:postcode":"07652",
    "addr:street":"Haywood Dr",
    "iso:country":"US",
    "sg:address":"278 Haywood Dr",
    "sg:city":"Paramus",
    "sg:classifiers":[
        {
            "category":"Manufacturing",
            "subcategory":"Printing",
            "type":"Manufacturing & Wholesale Goods"
        }
    ],
    "sg:phone":"+1 201 576 9792",
    "sg:postcode":"07652",
    "sg:province":"NJ",
    "sg:tags":[
        "lithographic",
        "commercial"
    ],
    "wof:name":"Image Data Printing Supplies",
    "wof:placetype":"venue"
},
  "geometry": {"coordinates":[-74.06350500000001,40.93808],"type":"Point"}
}