{
  "type": "Feature",
  "properties": {
    "iso:country":"US",
    "sg:address":"1107 S Black Horse Pike",
    "sg:city":"Blackwood",
    "sg:classifiers":[
        {
            "category":"Home & Garden",
            "subcategory":"Carpets & Floor Coverings",
            "type":"Retail Goods"
        }
    ],
    "sg:phone":"+1 215 913 0477",
    "sg:postcode":"08012",
    "sg:province":"NJ",
    "sg:tags":[
        "dealer",
        "rug"
    ],
    "wof:name":"MGM Carpet & Floor Covering",
    "wof:placetype":"venue"
},
  "geometry": {"coordinates":[-75.057076,39.787337],"type":"Point"}
}