{
  "type": "Feature",
  "properties": {
    "iso:country":"US",
    "sg:address":"255 State Rte 31",
    "sg:city":"Washington",
    "sg:classifiers":[
        {
            "category":"Building & Trades",
            "subcategory":"Equipment Rental",
            "type":"Services"
        }
    ],
    "sg:phone":"+1 908 689 4666",
    "sg:postcode":"07882",
    "sg:province":"NJ",
    "sg:tags":[
        "yard"
    ],
    "wof:name":"Taylor Rental Center",
    "wof:placetype":"venue"
},
  "geometry": {"coordinates":[-74.980012,40.770228],"type":"Point"}
}