{
  "type": "Feature",
  "properties": {
    "addr:full":"25 Pequot Rd Ringwood NJ 07456",
    "addr:housenumber":"25",
    "addr:postcode":"07456",
    "addr:street":"Pequot Rd",
    "iso:country":"US",
    "sg:address":"25 Pequot Rd",
    "sg:city":"Ringwood",
    "sg:classifiers":[
        {
            "category":"Shopping",
            "subcategory":"Gifts & Souvenirs",
            "type":"Retail Goods"
        }
    ],
    "sg:phone":"+1 973 962 6222",
    "sg:postcode":"07456",
    "sg:province":"NJ",
    "sg:tags":[
        "shop"
    ],
    "wof:name":"Terry's Treasures",
    "wof:placetype":"venue"
},
  "geometry": {"coordinates":[-74.248244,41.092309],"type":"Point"}
}